{
  "type": "Feature",
  "properties": {
    "iso:country": "GB",
    "wof:name": "CF5 4JB",
    "wof:placetype": "postalcode"
  },
  "geometry": {"coordinates":[-3.25174,51.480596],"type":"Point"}
}
