{
  "type": "Feature",
  "properties": {
    "iso:country":"GB",
    "wof:name":"CF5 4JB",
    "wof:placetype":"postalcode"
},
  "geometry": {"coordinates":[-3.25174030456974,51.48059587825038],"type":"Point"}
}