{
  "type": "Feature",
  "properties": {
    "iso:country":"GB",
    "wof:name":"NG6 8EN",
    "wof:placetype":"postalcode"
},
  "geometry": {"coordinates":[-1.1931328041023,53.00440131756235],"type":"Point"}
}