{
  "type": "Feature",
  "properties": {
    "date:inception_lower": "1980-01-01",
    "date:inception_upper": "1980-01-01",
    "iso:country": "GB",
    "wof:name": "ST2 8LS",
    "wof:placetype": "postalcode"
  },
  "geometry": {"coordinates":[-2.137897,53.029556],"type":"Point"}
}
