{
  "type": "Feature",
  "properties": {
    "iso:country":"GB",
    "wof:name":"ST2 8LS",
    "wof:placetype":"postalcode"
},
  "geometry": {"coordinates":[-2.1378967228748,53.02955631950941],"type":"Point"}
}