{
  "type": "Feature",
  "properties": {
    "iso:country": "GB",
    "wof:name": "TF9 3GF",
    "wof:placetype": "postalcode"
  },
  "geometry": {"coordinates":[-2.513174,52.899406],"type":"Point"}
}
