{
  "type": "Feature",
  "properties": {
    "date:inception_lower": "1980-01-01",
    "date:inception_upper": "1980-01-01",
    "iso:country": "GB",
    "wof:name": "SA73 3NB",
    "wof:placetype": "postalcode"
  },
  "geometry": {"coordinates":[-5.044908,51.714132],"type":"Point"}
}
