{
  "type": "Feature",
  "properties": {
    "iso:country":"GB",
    "wof:name":"G23 5HQ",
    "wof:placetype":"postalcode"
},
  "geometry": {"coordinates":[-4.29232665778464,55.92086620637065],"type":"Point"}
}