{
  "type": "Feature",
  "properties": {
    "iso:country":"GB",
    "wof:name":"NG16 6FA",
    "wof:placetype":"postalcode"
},
  "geometry": {"coordinates":[-1.30145763514585,53.075454869083],"type":"Point"}
}