{
  "type": "Feature",
  "properties": {
    "date:inception_lower":"2001-12-01",
    "date:inception_upper":"2001-12-31",
    "iso:country":"GB",
    "wof:name":"NG16 6FA",
    "wof:placetype":"postalcode"
},
  "geometry": {"coordinates":[-1.301458,53.075455],"type":"Point"}
}