{
  "type": "Feature",
  "properties": {
    "iso:country":"GB",
    "wof:name":"GL4 8LH",
    "wof:placetype":"postalcode"
},
  "geometry": {"coordinates":[-2.10584591872505,51.8196457214764],"type":"Point"}
}