{
  "type": "Feature",
  "properties": {
    "iso:country": "GB",
    "wof:name": "GL4 8LH",
    "wof:placetype": "postalcode"
  },
  "geometry": {"coordinates":[-2.105853,51.819221],"type":"Point"}
}
