{
  "type": "Feature",
  "properties": {
    "iso:country":"GB",
    "wof:name":"CF32 7ET",
    "wof:placetype":"postalcode"
},
  "geometry": {"coordinates":[-3.54333119320631,51.61182198709731],"type":"Point"}
}