{
  "type": "Feature",
  "properties": {
    "iso:country":"GB",
    "wof:name":"MK6 1BU",
    "wof:placetype":"postalcode"
},
  "geometry": {"coordinates":[-0.76408527360529,52.02748310222115],"type":"Point"}
}