{
  "type": "Feature",
  "properties": {
    "iso:country": "GB",
    "wof:name": "MK6 1BU",
    "wof:placetype": "postalcode"
  },
  "geometry": {"coordinates":[-0.764412,52.027801],"type":"Point"}
}
