{
  "type": "Feature",
  "properties": {
    "iso:country": "GB",
    "wof:name": "N3 3RJ",
    "wof:placetype": "postalcode"
  },
  "geometry": {"coordinates":[-0.198467,51.597872],"type":"Point"}
}
