{
  "type": "Feature",
  "properties": {
    "iso:country":"GB",
    "wof:name":"WR5 1HR",
    "wof:placetype":"postalcode"
},
  "geometry": {"coordinates":[-2.19714665862006,52.19440397567257],"type":"Point"}
}