{
  "type": "Feature",
  "properties": {
    "date:inception_lower":"1990-07-01",
    "date:inception_upper":"1990-07-31",
    "iso:country":"GB",
    "wof:name":"PO41 0RD",
    "wof:placetype":"postalcode"
},
  "geometry": {"coordinates":[-1.495866,50.705003],"type":"Point"}
}