{
  "type": "Feature",
  "properties": {
    "iso:country":"GB",
    "wof:name":"PO41 0RD",
    "wof:placetype":"postalcode"
},
  "geometry": {"coordinates":[-1.49586577435099,50.70500251207363],"type":"Point"}
}