{
  "type": "Feature",
  "properties": {
    "iso:country":"GB",
    "wof:name":"B45 8DB",
    "wof:placetype":"postalcode"
},
  "geometry": {"coordinates":[-2.01878381549869,52.36716263118493],"type":"Point"}
}