{
  "type": "Feature",
  "properties": {
    "iso:country": "GB",
    "wof:name": "B45 8DB",
    "wof:placetype": "postalcode"
  },
  "geometry": {"coordinates":[-2.018784,52.367163],"type":"Point"}
}
