{
  "type": "Feature",
  "properties": {
    "date:inception_lower":"1980-01-01",
    "date:inception_upper":"1980-01-31",
    "iso:country":"GB",
    "wof:name":"B45 8DB",
    "wof:placetype":"postalcode"
},
  "geometry": {"coordinates":[-2.018784,52.367163],"type":"Point"}
}