{
  "type": "Feature",
  "properties": {
    "iso:country":"GB",
    "wof:name":"SO30 0TT",
    "wof:placetype":"postalcode"
},
  "geometry": {"coordinates":[-1.30963188234735,50.91392864680883],"type":"Point"}
}