{
  "type": "Feature",
  "properties": {
    "iso:country":"GB",
    "wof:name":"SP4 0HB",
    "wof:placetype":"postalcode"
},
  "geometry": {"coordinates":[-1.69123783425943,51.16047216387751],"type":"Point"}
}