{
  "type": "Feature",
  "properties": {
    "iso:country": "GB",
    "wof:name": "SP4 0HB",
    "wof:placetype": "postalcode"
  },
  "geometry": {"coordinates":[-1.691238,51.160472],"type":"Point"}
}
