{
  "type": "Feature",
  "properties": {
    "date:inception_lower":"2009-02-01",
    "date:inception_upper":"2009-02-28",
    "iso:country":"GB",
    "wof:name":"RM1 3AW",
    "wof:placetype":"postalcode"
},
  "geometry": {"coordinates":[0.187198,51.580662],"type":"Point"}
}