{
  "type": "Feature",
  "properties": {
    "iso:country":"GB",
    "wof:name":"KA15 1JT",
    "wof:placetype":"postalcode"
},
  "geometry": {"coordinates":[-4.62712091199404,55.73678995977285],"type":"Point"}
}