{
  "type": "Feature",
  "properties": {
    "iso:country":"GB",
    "wof:name":"WF2 8EX",
    "wof:placetype":"postalcode"
},
  "geometry": {"coordinates":[-1.52249508307424,53.67481533740633],"type":"Point"}
}