{
  "type": "Feature",
  "properties": {
    "iso:country":"GB",
    "wof:name":"GU7 3RQ",
    "wof:placetype":"postalcode"
},
  "geometry": {"coordinates":[-0.61045309090852,51.20403871103954],"type":"Point"}
}