{
  "type": "Feature",
  "properties": {
    "iso:country":"GB",
    "wof:name":"AL1 5BJ",
    "wof:placetype":"postalcode"
},
  "geometry": {"coordinates":[-0.32415976242052,51.75094488326346],"type":"Point"}
}