{
  "type": "Feature",
  "properties": {
    "iso:country":"GB",
    "wof:name":"GL54 3QA",
    "wof:placetype":"postalcode"
},
  "geometry": {"coordinates":[-1.84471236227083,51.80882022035441],"type":"Point"}
}