{
  "type": "Feature",
  "properties": {
    "date:inception_lower":"1983-03-01",
    "date:inception_upper":"1983-03-31",
    "iso:country":"GB",
    "wof:name":"GL54 3QA",
    "wof:placetype":"postalcode"
},
  "geometry": {"coordinates":[-1.844712,51.80882],"type":"Point"}
}