{
  "type": "Feature",
  "properties": {
    "date:inception_lower":"1980-01-01",
    "date:inception_upper":"1980-01-31",
    "iso:country":"GB",
    "wof:name":"IV2 3TY",
    "wof:placetype":"postalcode"
},
  "geometry": {"coordinates":[-4.196344,57.480549],"type":"Point"}
}