{
  "type": "Feature",
  "properties": {
    "iso:country":"GB",
    "wof:name":"IV2 3TY",
    "wof:placetype":"postalcode"
},
  "geometry": {"coordinates":[-4.19634446839451,57.48054870153729],"type":"Point"}
}