{
  "type": "Feature",
  "properties": {
    "iso:country": "GB",
    "wof:name": "HX5 9QW",
    "wof:placetype": "postalcode"
  },
  "geometry": {"coordinates":[-1.822701,53.685945],"type":"Point"}
}
