{
  "type": "Feature",
  "properties": {
    "date:inception_lower": "2002-06-01",
    "date:inception_upper": "2002-06-01",
    "iso:country": "GB",
    "wof:name": "HX5 9QW",
    "wof:placetype": "postalcode"
  },
  "geometry": {"coordinates":[-1.822701,53.685945],"type":"Point"}
}
