{
  "type": "Feature",
  "properties": {
    "iso:country":"GB",
    "wof:name":"HX5 9QW",
    "wof:placetype":"postalcode"
},
  "geometry": {"coordinates":[-1.82270142822683,53.68594472198616],"type":"Point"}
}