{
  "type": "Feature",
  "properties": {
    "date:inception_lower":"2012-07-01",
    "date:inception_upper":"2012-07-31",
    "iso:country":"GB",
    "wof:name":"NG12 4FN",
    "wof:placetype":"postalcode"
},
  "geometry": {"coordinates":[-1.100401,52.900114],"type":"Point"}
}