{
  "type": "Feature",
  "properties": {
    "iso:country":"GB",
    "wof:name":"NG12 4FN",
    "wof:placetype":"postalcode"
},
  "geometry": {"coordinates":[-1.10040060337088,52.9001137333698],"type":"Point"}
}