{
  "type": "Feature",
  "properties": {
    "iso:country":"GB",
    "wof:name":"WF17 0HU",
    "wof:placetype":"postalcode"
},
  "geometry": {"coordinates":[-1.64194383541873,53.73753756393003],"type":"Point"}
}