{
  "type": "Feature",
  "properties": {
    "date:inception_lower": "1980-01-01",
    "date:inception_upper": "1980-01-01",
    "iso:country": "GB",
    "wof:name": "WF17 0HU",
    "wof:placetype": "postalcode"
  },
  "geometry": {"coordinates":[-1.641944,53.737538],"type":"Point"}
}
