{
  "type": "Feature",
  "properties": {
    "date:inception_lower": "2010-07-01",
    "date:inception_upper": "2010-07-01",
    "iso:country": "GB",
    "wof:name": "SP11 6GS",
    "wof:placetype": "postalcode"
  },
  "geometry": {"coordinates":[-1.463248,51.227107],"type":"Point"}
}
