{
  "type": "Feature",
  "properties": {
    "iso:country":"GB",
    "wof:name":"W1W 8SD",
    "wof:placetype":"postalcode"
},
  "geometry": {"coordinates":[-0.14189841836827,51.51639105567209],"type":"Point"}
}