{
  "type": "Feature",
  "properties": {
    "iso:country":"GB",
    "wof:name":"DE7 4GZ",
    "wof:placetype":"postalcode"
},
  "geometry": {"coordinates":[-1.31833484910728,52.95370250925941],"type":"Point"}
}