{
  "type": "Feature",
  "properties": {
    "iso:country": "GB",
    "wof:name": "HA8 6DG",
    "wof:placetype": "postalcode"
  },
  "geometry": {"coordinates":[-0.285402,51.602466],"type":"Point"}
}
