{
  "type": "Feature",
  "properties": {
    "iso:country":"GB",
    "wof:name":"DN15 7UW",
    "wof:placetype":"postalcode"
},
  "geometry": {"coordinates":[-0.68904308386863,53.58688446098397],"type":"Point"}
}