{
  "type": "Feature",
  "properties": {
    "date:inception_lower": "1994-05-01",
    "date:inception_upper": "1994-05-01",
    "iso:country": "GB",
    "wof:name": "M46 0LW",
    "wof:placetype": "postalcode"
  },
  "geometry": {"coordinates":[-2.50392,53.52511],"type":"Point"}
}
