{
  "type": "Feature",
  "properties": {
    "iso:country":"GB",
    "wof:name":"YO23 1HJ",
    "wof:placetype":"postalcode"
},
  "geometry": {"coordinates":[-1.09105710077857,53.94495150203449],"type":"Point"}
}