{
  "type": "Feature",
  "properties": {
    "date:inception_lower":"1998-06-01",
    "date:inception_upper":"1998-06-30",
    "iso:country":"GB",
    "wof:name":"S1 3GG",
    "wof:placetype":"postalcode"
},
  "geometry": {"coordinates":[-1.472215,53.384061],"type":"Point"}
}