{
  "type": "Feature",
  "properties": {
    "iso:country": "GB",
    "wof:name": "SN5 8YU",
    "wof:placetype": "postalcode"
  },
  "geometry": {"coordinates":[-1.83738,51.543966],"type":"Point"}
}
