{
  "type": "Feature",
  "properties": {
    "iso:country":"GB",
    "wof:name":"SN5 8YU",
    "wof:placetype":"postalcode"
},
  "geometry": {"coordinates":[-1.83738015227351,51.54396553710086],"type":"Point"}
}