{
  "type": "Feature",
  "properties": {
    "iso:country":"GB",
    "wof:name":"B71 1HP",
    "wof:placetype":"postalcode"
},
  "geometry": {"coordinates":[-1.99097833492658,52.53489031261446],"type":"Point"}
}