{
  "type": "Feature",
  "properties": {
    "iso:country": "GB",
    "wof:name": "CW7 1FY",
    "wof:placetype": "postalcode"
  },
  "geometry": {"coordinates":[-2.55084,53.182143],"type":"Point"}
}
