{
  "type": "Feature",
  "properties": {
    "date:inception_lower":"1980-01-01",
    "date:inception_upper":"1980-01-31",
    "iso:country":"GB",
    "wof:name":"KA8 0LT",
    "wof:placetype":"postalcode"
},
  "geometry": {"coordinates":[-4.58802,55.471882],"type":"Point"}
}