{
  "type": "Feature",
  "properties": {
    "iso:country": "GB",
    "wof:name": "KA8 0LT",
    "wof:placetype": "postalcode"
  },
  "geometry": {"coordinates":[-4.58802,55.471882],"type":"Point"}
}
