{
  "type": "Feature",
  "properties": {
    "iso:country":"GB",
    "wof:name":"DA6 8LB",
    "wof:placetype":"postalcode"
},
  "geometry": {"coordinates":[0.13468773038781,51.45214103506432],"type":"Point"}
}