{
  "type": "Feature",
  "properties": {
    "date:inception_lower": "1980-01-01",
    "date:inception_upper": "1980-01-01",
    "iso:country": "GB",
    "wof:name": "G81 2DA",
    "wof:placetype": "postalcode"
  },
  "geometry": {"coordinates":[-4.398819,55.912681],"type":"Point"}
}
