{
  "type": "Feature",
  "properties": {
    "iso:country":"GB",
    "wof:name":"G81 2DA",
    "wof:placetype":"postalcode"
},
  "geometry": {"coordinates":[-4.39881922736464,55.91268062207842],"type":"Point"}
}