{
  "type": "Feature",
  "properties": {
    "iso:country": "GB",
    "wof:name": "NN18 8NA",
    "wof:placetype": "postalcode"
  },
  "geometry": {"coordinates":[-0.718051,52.470286],"type":"Point"}
}
