{
  "type": "Feature",
  "properties": {
    "iso:country":"GB",
    "wof:name":"NN18 8NA",
    "wof:placetype":"postalcode"
},
  "geometry": {"coordinates":[-0.71805122069547,52.47028628421589],"type":"Point"}
}