{
  "type": "Feature",
  "properties": {
    "iso:country":"GB",
    "wof:name":"NR35 2PX",
    "wof:placetype":"postalcode"
},
  "geometry": {"coordinates":[1.48871039592341,52.47834655946208],"type":"Point"}
}