{
  "type": "Feature",
  "properties": {
    "iso:country":"GB",
    "wof:name":"CO11 2BH",
    "wof:placetype":"postalcode"
},
  "geometry": {"coordinates":[1.05834060494117,51.94201854262278],"type":"Point"}
}