{
  "type": "Feature",
  "properties": {
    "iso:country": "GB",
    "wof:name": "CB1 3UB",
    "wof:placetype": "postalcode"
  },
  "geometry": {"coordinates":[0.1652,52.189576],"type":"Point"}
}
