{
  "type": "Feature",
  "properties": {
    "date:inception_lower": "1980-01-01",
    "date:inception_upper": "1980-01-01",
    "iso:country": "GB",
    "wof:name": "CB1 3UB",
    "wof:placetype": "postalcode"
  },
  "geometry": {"coordinates":[0.1652,52.189576],"type":"Point"}
}
