{
  "type": "Feature",
  "properties": {
    "iso:country":"GB",
    "wof:name":"CB1 3UB",
    "wof:placetype":"postalcode"
},
  "geometry": {"coordinates":[0.16520002529244,52.18957617941461],"type":"Point"}
}