{
  "type": "Feature",
  "properties": {
    "date:inception_lower":"1980-01-01",
    "date:inception_upper":"1980-01-31",
    "iso:country":"GB",
    "wof:name":"NG15 7TJ",
    "wof:placetype":"postalcode"
},
  "geometry": {"coordinates":[-1.196049,53.039965],"type":"Point"}
}