{
  "type": "Feature",
  "properties": {
    "date:inception_lower": "1980-01-01",
    "date:inception_upper": "1980-01-01",
    "iso:country": "GB",
    "wof:name": "SG8 9LT",
    "wof:placetype": "postalcode"
  },
  "geometry": {"coordinates":[-0.01872,52.037368],"type":"Point"}
}
