{
  "type": "Feature",
  "properties": {
    "iso:country":"GB",
    "wof:name":"BH20 5SH",
    "wof:placetype":"postalcode"
},
  "geometry": {"coordinates":[-2.24169537938205,50.62560674539012],"type":"Point"}
}