{
  "type": "Feature",
  "properties": {
    "date:inception_lower": "1994-12-01",
    "date:inception_upper": "1994-12-01",
    "iso:country": "GB",
    "wof:name": "DL6 1LX",
    "wof:placetype": "postalcode"
  },
  "geometry": {"coordinates":[-1.424828,54.340752],"type":"Point"}
}
