{
  "type": "Feature",
  "properties": {
    "iso:country":"GB",
    "wof:name":"DL6 1LX",
    "wof:placetype":"postalcode"
},
  "geometry": {"coordinates":[-1.42468445452484,54.34044300727719],"type":"Point"}
}