{
  "type": "Feature",
  "properties": {
    "iso:country": "GB",
    "wof:name": "DL6 1LX",
    "wof:placetype": "postalcode"
  },
  "geometry": {"coordinates":[-1.424828,54.340752],"type":"Point"}
}
