{
  "type": "Feature",
  "properties": {
    "date:inception_lower": "2004-08-01",
    "date:inception_upper": "2004-08-01",
    "iso:country": "GB",
    "wof:name": "SN1 3JA",
    "wof:placetype": "postalcode"
  },
  "geometry": {"coordinates":[-1.779313,51.555389],"type":"Point"}
}
