{
  "type": "Feature",
  "properties": {
    "iso:country": "GB",
    "wof:name": "SN1 3JA",
    "wof:placetype": "postalcode"
  },
  "geometry": {"coordinates":[-1.779313,51.555389],"type":"Point"}
}
