{
  "type": "Feature",
  "properties": {
    "iso:country": "GB",
    "wof:name": "IP4 3HR",
    "wof:placetype": "postalcode"
  },
  "geometry": {"coordinates":[1.192772,52.070452],"type":"Point"}
}
