{
  "type": "Feature",
  "properties": {
    "date:inception_lower": "1980-01-01",
    "date:inception_upper": "1980-01-01",
    "iso:country": "GB",
    "wof:name": "SR7 9DZ",
    "wof:placetype": "postalcode"
  },
  "geometry": {"coordinates":[-1.387206,54.820764],"type":"Point"}
}
