{
  "type": "Feature",
  "properties": {
    "iso:country":"GB",
    "wof:name":"IV8 8PD",
    "wof:placetype":"postalcode"
},
  "geometry": {"coordinates":[-4.28153684430026,57.55723646184237],"type":"Point"}
}