{
  "type": "Feature",
  "properties": {
    "iso:country": "GB",
    "wof:name": "SY1 4BE",
    "wof:placetype": "postalcode"
  },
  "geometry": {"coordinates":[-2.739107,52.723501],"type":"Point"}
}
