{
  "type": "Feature",
  "properties": {
    "date:inception_lower": "1980-01-01",
    "date:inception_upper": "1980-01-01",
    "iso:country": "GB",
    "wof:name": "SY1 4BE",
    "wof:placetype": "postalcode"
  },
  "geometry": {"coordinates":[-2.739107,52.723501],"type":"Point"}
}
