{
  "type": "Feature",
  "properties": {
    "date:inception_lower": "1980-01-01",
    "date:inception_upper": "1980-01-01",
    "iso:country": "GB",
    "wof:name": "BS6 7QX",
    "wof:placetype": "postalcode"
  },
  "geometry": {"coordinates":[-2.604559,51.477518],"type":"Point"}
}
