{
  "type": "Feature",
  "properties": {
    "iso:country":"GB",
    "wof:name":"BS6 7QX",
    "wof:placetype":"postalcode"
},
  "geometry": {"coordinates":[-2.60467259177619,51.47759043538332],"type":"Point"}
}