{
  "type": "Feature",
  "properties": {
    "iso:country":"GB",
    "wof:name":"SW9 0PE",
    "wof:placetype":"postalcode"
},
  "geometry": {"coordinates":[-0.11477963660531,51.47642701606166],"type":"Point"}
}