{
  "type": "Feature",
  "properties": {
    "iso:country": "GB",
    "wof:name": "SW9 0PE",
    "wof:placetype": "postalcode"
  },
  "geometry": {"coordinates":[-0.11478,51.476427],"type":"Point"}
}
