{
  "type": "Feature",
  "properties": {
    "iso:country": "GB",
    "wof:name": "OX16 0FP",
    "wof:placetype": "postalcode"
  },
  "geometry": {"coordinates":[-1.369162,52.067638],"type":"Point"}
}
