{
  "type": "Feature",
  "properties": {
    "date:inception_lower": "2004-01-01",
    "date:inception_upper": "2004-01-01",
    "iso:country": "GB",
    "wof:name": "ST7 3ET",
    "wof:placetype": "postalcode"
  },
  "geometry": {"coordinates":[-2.265547,53.097521],"type":"Point"}
}
