{
  "type": "Feature",
  "properties": {
    "iso:country":"GB",
    "wof:name":"ST7 3ET",
    "wof:placetype":"postalcode"
},
  "geometry": {"coordinates":[-2.26559186347385,53.09754871918267],"type":"Point"}
}