{
  "type": "Feature",
  "properties": {
    "date:inception_lower":"1995-07-01",
    "date:inception_upper":"1995-07-31",
    "iso:country":"GB",
    "wof:name":"EX4 3JR",
    "wof:placetype":"postalcode"
},
  "geometry": {"coordinates":[-3.530667,50.724664],"type":"Point"}
}