{
  "type": "Feature",
  "properties": {
    "iso:country":"GB",
    "wof:name":"EX4 3JR",
    "wof:placetype":"postalcode"
},
  "geometry": {"coordinates":[-3.53066673846627,50.72466412367366],"type":"Point"}
}