{
  "type": "Feature",
  "properties": {
    "iso:country": "GB",
    "wof:name": "EX4 3JR",
    "wof:placetype": "postalcode"
  },
  "geometry": {"coordinates":[-3.530667,50.724664],"type":"Point"}
}
