{
  "type": "Feature",
  "properties": {
    "iso:country": "GB",
    "wof:name": "EH47 0LE",
    "wof:placetype": "postalcode"
  },
  "geometry": {"coordinates":[-3.699853,55.865122],"type":"Point"}
}
