{
  "type": "Feature",
  "properties": {
    "iso:country":"GB",
    "wof:name":"S71 3PG",
    "wof:placetype":"postalcode"
},
  "geometry": {"coordinates":[-1.44467772854312,53.58569321815036],"type":"Point"}
}