{
  "type": "Feature",
  "properties": {
    "iso:country": "GB",
    "wof:name": "S71 3PG",
    "wof:placetype": "postalcode"
  },
  "geometry": {"coordinates":[-1.444678,53.585693],"type":"Point"}
}
