{
  "type": "Feature",
  "properties": {
    "date:inception_lower": "2002-11-01",
    "date:inception_upper": "2002-11-01",
    "iso:country": "GB",
    "wof:name": "S71 3PG",
    "wof:placetype": "postalcode"
  },
  "geometry": {"coordinates":[-1.444678,53.585693],"type":"Point"}
}
