{
  "type": "Feature",
  "properties": {
    "iso:country":"GB",
    "wof:name":"KW15 1SX",
    "wof:placetype":"postalcode"
},
  "geometry": {"coordinates":[-2.96031868189496,58.95261663022482],"type":"Point"}
}