{
  "type": "Feature",
  "properties": {
    "date:inception_lower":"1980-01-01",
    "date:inception_upper":"1980-01-31",
    "iso:country":"GB",
    "wof:name":"KW15 1SX",
    "wof:placetype":"postalcode"
},
  "geometry": {"coordinates":[-2.960319,58.952617],"type":"Point"}
}