{
  "type": "Feature",
  "properties": {
    "iso:country":"GB",
    "wof:name":"TA3 6JQ",
    "wof:placetype":"postalcode"
},
  "geometry": {"coordinates":[-2.93425616515072,51.04415736804061],"type":"Point"}
}