{
  "type": "Feature",
  "properties": {
    "date:inception_lower":"2003-02-01",
    "date:inception_upper":"2003-02-28",
    "iso:country":"GB",
    "wof:name":"EX16 5HP",
    "wof:placetype":"postalcode"
},
  "geometry": {"coordinates":[-3.491224,50.8994],"type":"Point"}
}