{
  "type": "Feature",
  "properties": {
    "iso:country": "GB",
    "wof:name": "LL32 8TA",
    "wof:placetype": "postalcode"
  },
  "geometry": {"coordinates":[-3.84277,53.222698],"type":"Point"}
}
