{
  "type": "Feature",
  "properties": {
    "iso:country": "GB",
    "wof:name": "TN27 9LH",
    "wof:placetype": "postalcode"
  },
  "geometry": {"coordinates":[0.660551,51.186272],"type":"Point"}
}
