{
  "type": "Feature",
  "properties": {
    "date:inception_lower": "1980-01-01",
    "date:inception_upper": "1980-01-01",
    "iso:country": "GB",
    "wof:name": "TN27 9LH",
    "wof:placetype": "postalcode"
  },
  "geometry": {"coordinates":[0.660551,51.186272],"type":"Point"}
}
