{
  "type": "Feature",
  "properties": {
    "iso:country":"GB",
    "wof:name":"TN27 9LH",
    "wof:placetype":"postalcode"
},
  "geometry": {"coordinates":[0.66055129077,51.18627154520286],"type":"Point"}
}