{
  "type": "Feature",
  "properties": {
    "iso:country":"GB",
    "wof:name":"IP17 2DY",
    "wof:placetype":"postalcode"
},
  "geometry": {"coordinates":[1.40631292252223,52.23602754979913],"type":"Point"}
}