{
  "type": "Feature",
  "properties": {
    "date:inception_lower":"1980-01-01",
    "date:inception_upper":"1980-01-31",
    "iso:country":"GB",
    "wof:name":"IP17 2DY",
    "wof:placetype":"postalcode"
},
  "geometry": {"coordinates":[1.406837,52.236167],"type":"Point"}
}