{
  "type": "Feature",
  "properties": {
    "iso:country": "GB",
    "wof:name": "IP17 2DY",
    "wof:placetype": "postalcode"
  },
  "geometry": {"coordinates":[1.406837,52.236167],"type":"Point"}
}
