{
  "type": "Feature",
  "properties": {
    "iso:country": "GB",
    "wof:name": "LA6 1AR",
    "wof:placetype": "postalcode"
  },
  "geometry": {"coordinates":[-2.65435,54.15122],"type":"Point"}
}
