{
  "type": "Feature",
  "properties": {
    "date:inception_lower": "1980-01-01",
    "date:inception_upper": "1980-01-01",
    "iso:country": "GB",
    "wof:name": "BD10 9BD",
    "wof:placetype": "postalcode"
  },
  "geometry": {"coordinates":[-1.717488,53.830636],"type":"Point"}
}
