{
  "type": "Feature",
  "properties": {
    "date:inception_lower": "1980-01-01",
    "date:inception_upper": "1980-01-01",
    "iso:country": "GB",
    "wof:name": "KT1 2RX",
    "wof:placetype": "postalcode"
  },
  "geometry": {"coordinates":[-0.30313,51.405521],"type":"Point"}
}
