{
  "type": "Feature",
  "properties": {
    "iso:country":"GB",
    "wof:name":"L21 1BT",
    "wof:placetype":"postalcode"
},
  "geometry": {"coordinates":[-3.01467760095566,53.46567789815735],"type":"Point"}
}