{
  "type": "Feature",
  "properties": {
    "iso:country":"GB",
    "wof:name":"CT2 0EW",
    "wof:placetype":"postalcode"
},
  "geometry": {"coordinates":[1.13523116833643,51.30618911932745],"type":"Point"}
}