{
  "type": "Feature",
  "properties": {
    "iso:country": "GB",
    "wof:name": "PE28 9EW",
    "wof:placetype": "postalcode"
  },
  "geometry": {"coordinates":[-0.094856,52.314298],"type":"Point"}
}
