{
  "type": "Feature",
  "properties": {
    "iso:country":"GB",
    "wof:name":"PE28 9EW",
    "wof:placetype":"postalcode"
},
  "geometry": {"coordinates":[-0.09485607996873,52.31429761603303],"type":"Point"}
}