{
  "type": "Feature",
  "properties": {
    "iso:country":"GB",
    "wof:name":"IP6 9DD",
    "wof:placetype":"postalcode"
},
  "geometry": {"coordinates":[1.21086636580311,52.09459508514102],"type":"Point"}
}