{
  "type": "Feature",
  "properties": {
    "date:inception_lower": "1980-01-01",
    "date:inception_upper": "1980-01-01",
    "iso:country": "GB",
    "wof:name": "IP6 9DD",
    "wof:placetype": "postalcode"
  },
  "geometry": {"coordinates":[1.209564,52.094961],"type":"Point"}
}
