{
  "type": "Feature",
  "properties": {
    "iso:country": "GB",
    "wof:name": "HP21 8JX",
    "wof:placetype": "postalcode"
  },
  "geometry": {"coordinates":[-0.815703,51.812313],"type":"Point"}
}
