{
  "type": "Feature",
  "properties": {
    "iso:country":"GB",
    "wof:name":"HP21 8JX",
    "wof:placetype":"postalcode"
},
  "geometry": {"coordinates":[-0.81570303889682,51.81231252200583],"type":"Point"}
}