{
  "type": "Feature",
  "properties": {
    "date:inception_lower":"1998-06-01",
    "date:inception_upper":"1998-06-30",
    "iso:country":"GB",
    "wof:name":"M44 5XL",
    "wof:placetype":"postalcode"
},
  "geometry": {"coordinates":[-2.433311,53.430452],"type":"Point"}
}