{
  "type": "Feature",
  "properties": {
    "iso:country":"GB",
    "wof:name":"M44 5XL",
    "wof:placetype":"postalcode"
},
  "geometry": {"coordinates":[-2.43331128801128,53.43045192731498],"type":"Point"}
}