{
  "type": "Feature",
  "properties": {
    "iso:country": "GB",
    "wof:name": "BN24 6AJ",
    "wof:placetype": "postalcode"
  },
  "geometry": {"coordinates":[0.353838,50.813767],"type":"Point"}
}
