{
  "type": "Feature",
  "properties": {
    "date:inception_lower":"1980-01-01",
    "date:inception_upper":"1980-01-31",
    "iso:country":"GB",
    "wof:name":"BN24 6AJ",
    "wof:placetype":"postalcode"
},
  "geometry": {"coordinates":[0.353838,50.813767],"type":"Point"}
}