{
  "type": "Feature",
  "properties": {
    "iso:country": "GB",
    "wof:name": "DL14 6HD",
    "wof:placetype": "postalcode"
  },
  "geometry": {"coordinates":[-1.672811,54.654008],"type":"Point"}
}
