{
  "type": "Feature",
  "properties": {
    "iso:country":"GB",
    "wof:name":"HD3 3HQ",
    "wof:placetype":"postalcode"
},
  "geometry": {"coordinates":[-1.81584050621098,53.66203487862448],"type":"Point"}
}