{
  "type": "Feature",
  "properties": {
    "date:inception_lower": "2020-10-01",
    "date:inception_upper": "2020-10-01",
    "iso:country": "GB",
    "wof:name": "GL1 1AR",
    "wof:placetype": "postalcode"
  },
  "geometry": {"coordinates":[-2.241283,51.864713],"type":"Point"}
}
