{
  "type": "Feature",
  "properties": {
    "iso:country":"GB",
    "wof:name":"PO33 4DH",
    "wof:placetype":"postalcode"
},
  "geometry": {"coordinates":[-1.2038856896114,50.71178326373725],"type":"Point"}
}