{
  "type": "Feature",
  "properties": {
    "iso:country":"GB",
    "wof:name":"TA11 6DW",
    "wof:placetype":"postalcode"
},
  "geometry": {"coordinates":[-2.64248687551763,51.07601644747044],"type":"Point"}
}