{
  "type": "Feature",
  "properties": {
    "date:inception_lower": "2023-05-01",
    "date:inception_upper": "2023-05-01",
    "iso:country": "GB",
    "wof:name": "HU17 6HF",
    "wof:placetype": "postalcode"
  },
  "geometry": {"coordinates":[-0.401341,53.840773],"type":"Point"}
}
