{
  "type": "Feature",
  "properties": {
    "iso:country":"GB",
    "wof:name":"SN10 2HT",
    "wof:placetype":"postalcode"
},
  "geometry": {"coordinates":[-1.9755479563054,51.36277003205706],"type":"Point"}
}