{
  "type": "Feature",
  "properties": {
    "date:inception_lower": "1980-01-01",
    "date:inception_upper": "1980-01-01",
    "iso:country": "GB",
    "wof:name": "SN10 2HT",
    "wof:placetype": "postalcode"
  },
  "geometry": {"coordinates":[-1.976316,51.362542],"type":"Point"}
}
