{
  "type": "Feature",
  "properties": {
    "date:inception_lower": "1985-10-01",
    "date:inception_upper": "1985-10-01",
    "iso:country": "GB",
    "wof:name": "RH10 1NP",
    "wof:placetype": "postalcode"
  },
  "geometry": {"coordinates":[-0.162696,51.119172],"type":"Point"}
}
