{
  "type": "Feature",
  "properties": {
    "iso:country":"GB",
    "wof:name":"RH10 1NP",
    "wof:placetype":"postalcode"
},
  "geometry": {"coordinates":[-0.1627235132267,51.11917651469125],"type":"Point"}
}