{
  "type": "Feature",
  "properties": {
    "iso:country":"GB",
    "wof:name":"LE9 4TE",
    "wof:placetype":"postalcode"
},
  "geometry": {"coordinates":[-1.28608957373995,52.54417478282514],"type":"Point"}
}