{
  "type": "Feature",
  "properties": {
    "iso:country": "GB",
    "wof:name": "EN1 1SP",
    "wof:placetype": "postalcode"
  },
  "geometry": {"coordinates":[-0.058244,51.6454],"type":"Point"}
}
