{
  "type": "Feature",
  "properties": {
    "iso:country":"GB",
    "wof:name":"EN1 1SP",
    "wof:placetype":"postalcode"
},
  "geometry": {"coordinates":[-0.05824447128752,51.64540040414839],"type":"Point"}
}