{
  "type": "Feature",
  "properties": {
    "date:inception_lower": "1992-08-01",
    "date:inception_upper": "1992-08-01",
    "iso:country": "GB",
    "wof:name": "MK17 0SB",
    "wof:placetype": "postalcode"
  },
  "geometry": {"coordinates":[-0.815262,51.95402],"type":"Point"}
}
