{
  "type": "Feature",
  "properties": {
    "iso:country":"GB",
    "wof:name":"MK17 0SB",
    "wof:placetype":"postalcode"
},
  "geometry": {"coordinates":[-0.81526245741267,51.95402041722532],"type":"Point"}
}