{
  "type": "Feature",
  "properties": {
    "iso:country": "GB",
    "wof:name": "MK17 0SB",
    "wof:placetype": "postalcode"
  },
  "geometry": {"coordinates":[-0.815262,51.95402],"type":"Point"}
}
