{
  "type": "Feature",
  "properties": {
    "date:inception_lower": "1980-01-01",
    "date:inception_upper": "1980-01-01",
    "iso:country": "GB",
    "wof:name": "TQ1 2DJ",
    "wof:placetype": "postalcode"
  },
  "geometry": {"coordinates":[-3.519865,50.456485],"type":"Point"}
}
