{
  "type": "Feature",
  "properties": {
    "iso:country":"GB",
    "wof:name":"TQ1 2DJ",
    "wof:placetype":"postalcode"
},
  "geometry": {"coordinates":[-3.51986501371177,50.45648490752573],"type":"Point"}
}