{
  "type": "Feature",
  "properties": {
    "iso:country": "GB",
    "wof:name": "TR11 5BJ",
    "wof:placetype": "postalcode"
  },
  "geometry": {"coordinates":[-5.094134,50.138422],"type":"Point"}
}
