{
  "type": "Feature",
  "properties": {
    "date:inception_lower": "1980-01-01",
    "date:inception_upper": "1980-01-01",
    "iso:country": "GB",
    "wof:name": "TR11 5BJ",
    "wof:placetype": "postalcode"
  },
  "geometry": {"coordinates":[-5.094133,50.138413],"type":"Point"}
}
