{
  "type": "Feature",
  "properties": {
    "iso:country":"GB",
    "wof:name":"SW6 4UJ",
    "wof:placetype":"postalcode"
},
  "geometry": {"coordinates":[-0.19852090003933,51.473427107583],"type":"Point"}
}