{
  "type": "Feature",
  "properties": {
    "iso:country":"GB",
    "wof:name":"HX2 6HE",
    "wof:placetype":"postalcode"
},
  "geometry": {"coordinates":[-1.94793882870902,53.72099209827894],"type":"Point"}
}