{
  "type": "Feature",
  "properties": {
    "iso:country":"GB",
    "wof:name":"TQ5 0LE",
    "wof:placetype":"postalcode"
},
  "geometry": {"coordinates":[-3.54658255441142,50.39361727894774],"type":"Point"}
}