{
  "type": "Feature",
  "properties": {
    "iso:country":"GB",
    "wof:name":"BD22 9JB",
    "wof:placetype":"postalcode"
},
  "geometry": {"coordinates":[-1.95026062456109,53.80857221123932],"type":"Point"}
}