{
  "type": "Feature",
  "properties": {
    "date:inception_lower":"1985-04-01",
    "date:inception_upper":"1985-04-30",
    "iso:country":"GB",
    "wof:name":"DN3 1QJ",
    "wof:placetype":"postalcode"
},
  "geometry": {"coordinates":[-1.060292,53.558403],"type":"Point"}
}