{
  "type": "Feature",
  "properties": {
    "iso:country": "GB",
    "wof:name": "DN3 1QJ",
    "wof:placetype": "postalcode"
  },
  "geometry": {"coordinates":[-1.060292,53.558403],"type":"Point"}
}
