{
  "type": "Feature",
  "properties": {
    "date:inception_lower": "2008-01-01",
    "date:inception_upper": "2008-01-01",
    "iso:country": "GB",
    "wof:name": "CW2 6GR",
    "wof:placetype": "postalcode"
  },
  "geometry": {"coordinates":[-2.45656,53.079673],"type":"Point"}
}
