{
  "type": "Feature",
  "properties": {
    "iso:country":"GB",
    "wof:name":"DH2 3PY",
    "wof:placetype":"postalcode"
},
  "geometry": {"coordinates":[-1.59978024103237,54.82257582894754],"type":"Point"}
}