{
  "type": "Feature",
  "properties": {
    "iso:country": "GB",
    "wof:name": "DH2 3PY",
    "wof:placetype": "postalcode"
  },
  "geometry": {"coordinates":[-1.59978,54.822576],"type":"Point"}
}
