{
  "type": "Feature",
  "properties": {
    "iso:country":"GB",
    "wof:name":"DH5 8EA",
    "wof:placetype":"postalcode"
},
  "geometry": {"coordinates":[-1.45813809077282,54.84204855821523],"type":"Point"}
}