{
  "type": "Feature",
  "properties": {
    "iso:country": "GB",
    "wof:name": "OL15 0DZ",
    "wof:placetype": "postalcode"
  },
  "geometry": {"coordinates":[-2.112063,53.632283],"type":"Point"}
}
