{
  "type": "Feature",
  "properties": {
    "iso:country":"GB",
    "wof:name":"OL15 0DZ",
    "wof:placetype":"postalcode"
},
  "geometry": {"coordinates":[-2.11206325873215,53.63228261334091],"type":"Point"}
}