{
  "type": "Feature",
  "properties": {
    "iso:country": "GB",
    "wof:name": "PR25 1BD",
    "wof:placetype": "postalcode"
  },
  "geometry": {"coordinates":[-2.708996,53.683221],"type":"Point"}
}
