{
  "type": "Feature",
  "properties": {
    "iso:country": "GB",
    "wof:name": "WR9 7JQ",
    "wof:placetype": "postalcode"
  },
  "geometry": {"coordinates":[-2.145188,52.247672],"type":"Point"}
}
