{
  "type": "Feature",
  "properties": {
    "iso:country":"GB",
    "wof:name":"WR9 7JQ",
    "wof:placetype":"postalcode"
},
  "geometry": {"coordinates":[-2.1459068579749,52.2502188013119],"type":"Point"}
}