{
  "type": "Feature",
  "properties": {
    "iso:country":"GB",
    "wof:name":"GU23 6EP",
    "wof:placetype":"postalcode"
},
  "geometry": {"coordinates":[-0.50309006587164,51.29505869235947],"type":"Point"}
}