{
  "type": "Feature",
  "properties": {
    "date:inception_lower": "1980-01-01",
    "date:inception_upper": "1980-01-01",
    "iso:country": "GB",
    "wof:name": "GU23 6EP",
    "wof:placetype": "postalcode"
  },
  "geometry": {"coordinates":[-0.50309,51.295059],"type":"Point"}
}
