{
  "type": "Feature",
  "properties": {
    "iso:country":"GB",
    "wof:name":"WA4 4PJ",
    "wof:placetype":"postalcode"
},
  "geometry": {"coordinates":[-2.55646409702573,53.32274201713485],"type":"Point"}
}