{
  "type": "Feature",
  "properties": {
    "date:inception_lower": "1980-01-01",
    "date:inception_upper": "1980-01-01",
    "iso:country": "GB",
    "wof:name": "WA4 4PJ",
    "wof:placetype": "postalcode"
  },
  "geometry": {"coordinates":[-2.556464,53.322742],"type":"Point"}
}
