{
  "type": "Feature",
  "properties": {
    "iso:country": "GB",
    "wof:name": "E14 8AF",
    "wof:placetype": "postalcode"
  },
  "geometry": {"coordinates":[-0.02861,51.509731],"type":"Point"}
}
