{
  "type": "Feature",
  "properties": {
    "iso:country":"GB",
    "wof:name":"ME13 0AG",
    "wof:placetype":"postalcode"
},
  "geometry": {"coordinates":[0.81830613674761,51.27997402029973],"type":"Point"}
}