{
  "type": "Feature",
  "properties": {
    "date:inception_lower": "1980-01-01",
    "date:inception_upper": "1980-01-01",
    "iso:country": "GB",
    "wof:name": "ME13 0AG",
    "wof:placetype": "postalcode"
  },
  "geometry": {"coordinates":[0.818307,51.279983],"type":"Point"}
}
