{
  "type": "Feature",
  "properties": {
    "iso:country": "GB",
    "wof:name": "B8 2HS",
    "wof:placetype": "postalcode"
  },
  "geometry": {"coordinates":[-1.827777,52.493934],"type":"Point"}
}
