{
  "type": "Feature",
  "properties": {
    "date:inception_lower": "1980-01-01",
    "date:inception_upper": "1980-01-01",
    "iso:country": "GB",
    "wof:name": "WV3 0AB",
    "wof:placetype": "postalcode"
  },
  "geometry": {"coordinates":[-2.143005,52.571833],"type":"Point"}
}
