{
  "type": "Feature",
  "properties": {
    "date:inception_lower": "1980-01-01",
    "date:inception_upper": "1980-01-01",
    "iso:country": "GB",
    "wof:name": "BD24 9EW",
    "wof:placetype": "postalcode"
  },
  "geometry": {"coordinates":[-2.276582,54.068279],"type":"Point"}
}
