{
  "type": "Feature",
  "properties": {
    "iso:country":"GB",
    "wof:name":"BD24 9EW",
    "wof:placetype":"postalcode"
},
  "geometry": {"coordinates":[-2.27658229183406,54.06827928245479],"type":"Point"}
}