{
  "type": "Feature",
  "properties": {
    "iso:country":"GB",
    "wof:name":"CV32 4NT",
    "wof:placetype":"postalcode"
},
  "geometry": {"coordinates":[-1.53507645341448,52.29055274442766],"type":"Point"}
}