{
  "type": "Feature",
  "properties": {
    "date:inception_lower":"2000-06-01",
    "date:inception_upper":"2000-06-30",
    "iso:country":"GB",
    "wof:name":"CF62 7XX",
    "wof:placetype":"postalcode"
},
  "geometry": {"coordinates":[-3.279938,51.401377],"type":"Point"}
}