{
  "type": "Feature",
  "properties": {
    "iso:country": "GB",
    "wof:name": "DG7 2JW",
    "wof:placetype": "postalcode"
  },
  "geometry": {"coordinates":[-4.183528,54.88283],"type":"Point"}
}
