{
  "type": "Feature",
  "properties": {
    "date:inception_lower": "1980-01-01",
    "date:inception_upper": "1980-01-01",
    "iso:country": "GB",
    "wof:name": "ST14 8LZ",
    "wof:placetype": "postalcode"
  },
  "geometry": {"coordinates":[-1.805265,52.861846],"type":"Point"}
}
