{
  "type": "Feature",
  "properties": {
    "iso:country":"GB",
    "wof:name":"BS16 1UG",
    "wof:placetype":"postalcode"
},
  "geometry": {"coordinates":[-2.54192795939245,51.48792291672534],"type":"Point"}
}