{
  "type": "Feature",
  "properties": {
    "iso:country":"GB",
    "wof:name":"S12 4PF",
    "wof:placetype":"postalcode"
},
  "geometry": {"coordinates":[-1.38894848510829,53.34355626082952],"type":"Point"}
}