{
  "type": "Feature",
  "properties": {
    "iso:country":"GB",
    "wof:name":"ML2 0AD",
    "wof:placetype":"postalcode"
},
  "geometry": {"coordinates":[-3.9587618210701,55.76799785883314],"type":"Point"}
}