{
  "type": "Feature",
  "properties": {
    "date:inception_lower": "2021-02-01",
    "date:inception_upper": "2021-02-01",
    "iso:country": "GB",
    "wof:name": "TN40 2GB",
    "wof:placetype": "postalcode"
  },
  "geometry": {"coordinates":[0.485017,50.852838],"type":"Point"}
}
