{
  "type": "Feature",
  "properties": {
    "date:inception_lower":"2006-02-01",
    "date:inception_upper":"2006-02-28",
    "iso:country":"GB",
    "wof:name":"EH33 2QR",
    "wof:placetype":"postalcode"
},
  "geometry": {"coordinates":[-2.95177,55.938074],"type":"Point"}
}