{
  "type": "Feature",
  "properties": {
    "iso:country":"GB",
    "wof:name":"EH33 2QR",
    "wof:placetype":"postalcode"
},
  "geometry": {"coordinates":[-2.95177013052015,55.93807385130107],"type":"Point"}
}