{
  "type": "Feature",
  "properties": {
    "date:inception_lower":"1980-01-01",
    "date:inception_upper":"1980-01-31",
    "iso:country":"GB",
    "wof:name":"LS27 9PL",
    "wof:placetype":"postalcode"
},
  "geometry": {"coordinates":[-1.603045,53.753432],"type":"Point"}
}