{
  "type": "Feature",
  "properties": {
    "iso:country":"GB",
    "wof:name":"LS27 9PL",
    "wof:placetype":"postalcode"
},
  "geometry": {"coordinates":[-1.60304498490089,53.75343191935868],"type":"Point"}
}