{
  "type": "Feature",
  "properties": {
    "iso:country":"GB",
    "wof:name":"CV7 8DT",
    "wof:placetype":"postalcode"
},
  "geometry": {"coordinates":[-1.61748595497554,52.47448117210148],"type":"Point"}
}