{
  "type": "Feature",
  "properties": {
    "date:inception_lower": "1980-01-01",
    "date:inception_upper": "1980-01-01",
    "iso:country": "GB",
    "wof:name": "CV7 8DT",
    "wof:placetype": "postalcode"
  },
  "geometry": {"coordinates":[-1.61858,52.474743],"type":"Point"}
}
