{
  "type": "Feature",
  "properties": {
    "iso:country": "GB",
    "wof:name": "PL6 7EL",
    "wof:placetype": "postalcode"
  },
  "geometry": {"coordinates":[-4.115281,50.43548],"type":"Point"}
}
