{
  "type": "Feature",
  "properties": {
    "date:inception_lower": "2020-10-01",
    "date:inception_upper": "2020-10-01",
    "iso:country": "GB",
    "wof:name": "MK8 1ET",
    "wof:placetype": "postalcode"
  },
  "geometry": {"coordinates":[-0.817264,52.025989],"type":"Point"}
}
