{
  "type": "Feature",
  "properties": {
    "date:inception_lower": "2008-01-01",
    "date:inception_upper": "2008-01-01",
    "iso:country": "GB",
    "wof:name": "LS27 9RF",
    "wof:placetype": "postalcode"
  },
  "geometry": {"coordinates":[-1.604625,53.753543],"type":"Point"}
}
