{
  "type": "Feature",
  "properties": {
    "iso:country":"GB",
    "wof:name":"LS27 9RF",
    "wof:placetype":"postalcode"
},
  "geometry": {"coordinates":[-1.60462125298241,53.75353599423266],"type":"Point"}
}