{
  "type": "Feature",
  "properties": {
    "date:inception_lower": "2007-09-01",
    "date:inception_upper": "2007-09-01",
    "iso:country": "GB",
    "wof:name": "GU1 1EX",
    "wof:placetype": "postalcode"
  },
  "geometry": {"coordinates":[-0.54573,51.255589],"type":"Point"}
}
