{
  "type": "Feature",
  "properties": {
    "iso:country":"GB",
    "wof:name":"GU1 1EX",
    "wof:placetype":"postalcode"
},
  "geometry": {"coordinates":[-0.54573048881733,51.25558864560698],"type":"Point"}
}