{
  "type": "Feature",
  "properties": {
    "iso:country": "GB",
    "wof:name": "OL2 7TJ",
    "wof:placetype": "postalcode"
  },
  "geometry": {"coordinates":[-2.092672,53.581884],"type":"Point"}
}
