{
  "type": "Feature",
  "properties": {
    "iso:country":"GB",
    "wof:name":"OL2 7TJ",
    "wof:placetype":"postalcode"
},
  "geometry": {"coordinates":[-2.09267169685137,53.58188416088157],"type":"Point"}
}