{
  "type": "Feature",
  "properties": {
    "iso:country":"GB",
    "wof:name":"GL51 6GA",
    "wof:placetype":"postalcode"
},
  "geometry": {"coordinates":[-2.1315286013527,51.88554121675745],"type":"Point"}
}