{
  "type": "Feature",
  "properties": {
    "iso:country": "GB",
    "wof:name": "GL51 6GA",
    "wof:placetype": "postalcode"
  },
  "geometry": {"coordinates":[-2.131529,51.885541],"type":"Point"}
}
