{
  "type": "Feature",
  "properties": {
    "iso:country":"GB",
    "wof:name":"DL7 8NQ",
    "wof:placetype":"postalcode"
},
  "geometry": {"coordinates":[-1.44037480980443,54.33693082680594],"type":"Point"}
}