{
  "type": "Feature",
  "properties": {
    "iso:country": "GB",
    "wof:name": "SO51 7UJ",
    "wof:placetype": "postalcode"
  },
  "geometry": {"coordinates":[-1.470128,51.000374],"type":"Point"}
}
