{
  "type": "Feature",
  "properties": {
    "iso:country":"GB",
    "wof:name":"SO51 7UJ",
    "wof:placetype":"postalcode"
},
  "geometry": {"coordinates":[-1.4701281952354,51.00037440409608],"type":"Point"}
}