{
  "type": "Feature",
  "properties": {
    "date:inception_lower": "1986-01-01",
    "date:inception_upper": "1986-01-01",
    "iso:country": "GB",
    "wof:name": "SO51 7UJ",
    "wof:placetype": "postalcode"
  },
  "geometry": {"coordinates":[-1.470128,51.000374],"type":"Point"}
}
