{
  "type": "Feature",
  "properties": {
    "iso:country":"GB",
    "wof:name":"WC2N 4DS",
    "wof:placetype":"postalcode"
},
  "geometry": {"coordinates":[-0.12572214717757,51.51089103777505],"type":"Point"}
}