{
  "type": "Feature",
  "properties": {
    "date:inception_lower": "2000-12-01",
    "date:inception_upper": "2000-12-01",
    "iso:country": "GB",
    "wof:name": "WC2N 4DS",
    "wof:placetype": "postalcode"
  },
  "geometry": {"coordinates":[-0.125722,51.510891],"type":"Point"}
}
