{
  "type": "Feature",
  "properties": {
    "date:inception_lower":"1980-01-01",
    "date:inception_upper":"1980-01-31",
    "iso:country":"GB",
    "wof:name":"OL1 4LD",
    "wof:placetype":"postalcode"
},
  "geometry": {"coordinates":[-2.093915,53.550253],"type":"Point"}
}