{
  "type": "Feature",
  "properties": {
    "iso:country":"GB",
    "wof:name":"OL1 4LD",
    "wof:placetype":"postalcode"
},
  "geometry": {"coordinates":[-2.09391547357749,53.55025332902251],"type":"Point"}
}