{
  "type": "Feature",
  "properties": {
    "iso:country":"GB",
    "wof:name":"BS11 9XH",
    "wof:placetype":"postalcode"
},
  "geometry": {"coordinates":[-2.67015960061449,51.48538076402757],"type":"Point"}
}