{
  "type": "Feature",
  "properties": {
    "iso:country":"GB",
    "wof:name":"CH66 4XL",
    "wof:placetype":"postalcode"
},
  "geometry": {"coordinates":[-2.94093907639517,53.27057400258398],"type":"Point"}
}