{
  "type": "Feature",
  "properties": {
    "iso:country": "GB",
    "wof:name": "BN1 5EG",
    "wof:placetype": "postalcode"
  },
  "geometry": {"coordinates":[-0.156518,50.857817],"type":"Point"}
}
