{
  "type": "Feature",
  "properties": {
    "iso:country":"GB",
    "wof:name":"BN1 5EG",
    "wof:placetype":"postalcode"
},
  "geometry": {"coordinates":[-0.15651782301696,50.85781690380795],"type":"Point"}
}