{
  "type": "Feature",
  "properties": {
    "date:inception_lower": "1980-01-01",
    "date:inception_upper": "1980-01-01",
    "iso:country": "GB",
    "wof:name": "BN1 5EG",
    "wof:placetype": "postalcode"
  },
  "geometry": {"coordinates":[-0.156518,50.857817],"type":"Point"}
}
