{
  "type": "Feature",
  "properties": {
    "date:inception_lower": "1980-01-01",
    "date:inception_upper": "1980-01-01",
    "iso:country": "GB",
    "wof:name": "HU10 7JE",
    "wof:placetype": "postalcode"
  },
  "geometry": {"coordinates":[-0.452861,53.747414],"type":"Point"}
}
