{
  "type": "Feature",
  "properties": {
    "iso:country":"GB",
    "wof:name":"AB42 0SA",
    "wof:placetype":"postalcode"
},
  "geometry": {"coordinates":[-1.91889150940379,57.41813176767879],"type":"Point"}
}