{
  "type": "Feature",
  "properties": {
    "iso:country":"GB",
    "wof:name":"S13 8DL",
    "wof:placetype":"postalcode"
},
  "geometry": {"coordinates":[-1.4139847573331,53.36125480517166],"type":"Point"}
}