{
  "type": "Feature",
  "properties": {
    "iso:country": "GB",
    "wof:name": "LA9 6JR",
    "wof:placetype": "postalcode"
  },
  "geometry": {"coordinates":[-2.730168,54.333518],"type":"Point"}
}
