{
  "type": "Feature",
  "properties": {
    "iso:country":"GB",
    "wof:name":"BD16 1TJ",
    "wof:placetype":"postalcode"
},
  "geometry": {"coordinates":[-1.8320358950858,53.82878690501872],"type":"Point"}
}