{
  "type": "Feature",
  "properties": {
    "date:inception_lower": "1980-01-01",
    "date:inception_upper": "1980-01-01",
    "iso:country": "GB",
    "wof:name": "LE16 7HU",
    "wof:placetype": "postalcode"
  },
  "geometry": {"coordinates":[-0.916775,52.486028],"type":"Point"}
}
