{
  "type": "Feature",
  "properties": {
    "iso:country":"GB",
    "wof:name":"LE16 7HU",
    "wof:placetype":"postalcode"
},
  "geometry": {"coordinates":[-0.91677526448336,52.48602782433019],"type":"Point"}
}