{
  "type": "Feature",
  "properties": {
    "iso:country":"GB",
    "wof:name":"LU5 4JU",
    "wof:placetype":"postalcode"
},
  "geometry": {"coordinates":[-0.48485665008594,51.88962936691675],"type":"Point"}
}