{
  "type": "Feature",
  "properties": {
    "iso:country": "GB",
    "wof:name": "LU5 4JU",
    "wof:placetype": "postalcode"
  },
  "geometry": {"coordinates":[-0.486261,51.889036],"type":"Point"}
}
