{
  "type": "Feature",
  "properties": {
    "iso:country": "GB",
    "wof:name": "LU5 4JU",
    "wof:placetype": "postalcode"
  },
  "geometry": {"coordinates":[-0.484831,51.889638],"type":"Point"}
}
