{
  "type": "Feature",
  "properties": {
    "iso:country": "GB",
    "wof:name": "WF15 8DE",
    "wof:placetype": "postalcode"
  },
  "geometry": {"coordinates":[-1.716661,53.718626],"type":"Point"}
}
