{
  "type": "Feature",
  "properties": {
    "iso:country":"GB",
    "wof:name":"WF15 8DE",
    "wof:placetype":"postalcode"
},
  "geometry": {"coordinates":[-1.71647747783653,53.71848439591774],"type":"Point"}
}