{
  "type": "Feature",
  "properties": {
    "date:inception_lower": "2000-12-01",
    "date:inception_upper": "2000-12-01",
    "iso:country": "GB",
    "wof:name": "W1K 6WZ",
    "wof:placetype": "postalcode"
  },
  "geometry": {"coordinates":[-0.153214,51.513253],"type":"Point"}
}
