{
  "type": "Feature",
  "properties": {
    "iso:country":"GB",
    "wof:name":"W1K 6WZ",
    "wof:placetype":"postalcode"
},
  "geometry": {"coordinates":[-0.15338237718315,51.51326318251645],"type":"Point"}
}