{
  "type": "Feature",
  "properties": {
    "iso:country":"GB",
    "wof:name":"B76 1BN",
    "wof:placetype":"postalcode"
},
  "geometry": {"coordinates":[-1.80926154964896,52.55901903101568],"type":"Point"}
}