{
  "type": "Feature",
  "properties": {
    "date:inception_lower":"1993-08-01",
    "date:inception_upper":"1993-08-31",
    "iso:country":"GB",
    "wof:name":"B76 1BN",
    "wof:placetype":"postalcode"
},
  "geometry": {"coordinates":[-1.809262,52.559019],"type":"Point"}
}