{
  "type": "Feature",
  "properties": {
    "iso:country": "GB",
    "wof:name": "B76 1BN",
    "wof:placetype": "postalcode"
  },
  "geometry": {"coordinates":[-1.809262,52.559019],"type":"Point"}
}
