{
  "type": "Feature",
  "properties": {
    "iso:country":"GB",
    "wof:name":"S45 8AE",
    "wof:placetype":"postalcode"
},
  "geometry": {"coordinates":[-1.34426200094481,53.16225482974441],"type":"Point"}
}