{
  "type": "Feature",
  "properties": {
    "date:inception_lower": "1980-01-01",
    "date:inception_upper": "1980-01-01",
    "iso:country": "GB",
    "wof:name": "S45 8AE",
    "wof:placetype": "postalcode"
  },
  "geometry": {"coordinates":[-1.344262,53.162255],"type":"Point"}
}
