{
  "type": "Feature",
  "properties": {
    "date:inception_lower":"2018-06-01",
    "date:inception_upper":"2018-06-30",
    "iso:country":"GB",
    "wof:name":"N3 3PQ",
    "wof:placetype":"postalcode"
},
  "geometry": {"coordinates":[-0.205158,51.59341],"type":"Point"}
}