{
  "type": "Feature",
  "properties": {
    "iso:country":"GB",
    "wof:name":"SE9 1PG",
    "wof:placetype":"postalcode"
},
  "geometry": {"coordinates":[0.06154642629063,51.45832432950729],"type":"Point"}
}