{
  "type": "Feature",
  "properties": {
    "date:inception_lower": "2001-06-01",
    "date:inception_upper": "2001-06-01",
    "iso:country": "GB",
    "wof:name": "PR26 7AB",
    "wof:placetype": "postalcode"
  },
  "geometry": {"coordinates":[-2.738556,53.69132],"type":"Point"}
}
