{
  "type": "Feature",
  "properties": {
    "iso:country":"GB",
    "wof:name":"PR26 7AB",
    "wof:placetype":"postalcode"
},
  "geometry": {"coordinates":[-2.73855646365644,53.69132023897383],"type":"Point"}
}