{
  "type": "Feature",
  "properties": {
    "iso:country": "GB",
    "wof:name": "PR26 7AB",
    "wof:placetype": "postalcode"
  },
  "geometry": {"coordinates":[-2.738556,53.69132],"type":"Point"}
}
