{
  "type": "Feature",
  "properties": {
    "date:inception_lower": "1999-06-01",
    "date:inception_upper": "1999-06-01",
    "iso:country": "GB",
    "wof:name": "FK8 2NU",
    "wof:placetype": "postalcode"
  },
  "geometry": {"coordinates":[-3.940764,56.111134],"type":"Point"}
}
