{
  "type": "Feature",
  "properties": {
    "iso:country":"GB",
    "wof:name":"PO7 8DF",
    "wof:placetype":"postalcode"
},
  "geometry": {"coordinates":[-1.02135645697589,50.87098819161943],"type":"Point"}
}