{
  "type": "Feature",
  "properties": {
    "date:inception_lower": "2022-04-01",
    "date:inception_upper": "2022-04-01",
    "iso:country": "GB",
    "wof:name": "MK17 9GR",
    "wof:placetype": "postalcode"
  },
  "geometry": {"coordinates":[-0.707514,51.990409],"type":"Point"}
}
