{
  "type": "Feature",
  "properties": {
    "iso:country":"GB",
    "wof:name":"EX16 5JF",
    "wof:placetype":"postalcode"
},
  "geometry": {"coordinates":[-3.49327279600815,50.90163955506119],"type":"Point"}
}