{
  "type": "Feature",
  "properties": {
    "iso:country":"GB",
    "wof:name":"CF10 5BB",
    "wof:placetype":"postalcode"
},
  "geometry": {"coordinates":[-3.16697541286016,51.465284797263],"type":"Point"}
}