{
  "type": "Feature",
  "properties": {
    "date:inception_lower": "1980-01-01",
    "date:inception_upper": "1980-01-01",
    "iso:country": "GB",
    "wof:name": "HP17 8RY",
    "wof:placetype": "postalcode"
  },
  "geometry": {"coordinates":[-0.855209,51.798639],"type":"Point"}
}
