{
  "type": "Feature",
  "properties": {
    "iso:country":"GB",
    "wof:name":"HP17 8RY",
    "wof:placetype":"postalcode"
},
  "geometry": {"coordinates":[-0.8555296357167,51.7988600176542],"type":"Point"}
}