{
  "type": "Feature",
  "properties": {
    "iso:country":"GB",
    "wof:name":"AL10 0HR",
    "wof:placetype":"postalcode"
},
  "geometry": {"coordinates":[-0.22331917658348,51.76777158001337],"type":"Point"}
}