{
  "type": "Feature",
  "properties": {
    "date:inception_lower":"1980-01-01",
    "date:inception_upper":"1980-01-31",
    "iso:country":"GB",
    "wof:name":"CB1 3ST",
    "wof:placetype":"postalcode"
},
  "geometry": {"coordinates":[0.157494,52.191174],"type":"Point"}
}