{
  "type": "Feature",
  "properties": {
    "iso:country": "GB",
    "wof:name": "CB1 3ST",
    "wof:placetype": "postalcode"
  },
  "geometry": {"coordinates":[0.157494,52.191174],"type":"Point"}
}
