{
  "type": "Feature",
  "properties": {
    "iso:country":"GB",
    "wof:name":"BN6 8RP",
    "wof:placetype":"postalcode"
},
  "geometry": {"coordinates":[-0.08036146122827,50.89578240191078],"type":"Point"}
}