{
  "type": "Feature",
  "properties": {
    "iso:country":"GB",
    "wof:name":"PL1 4BQ",
    "wof:placetype":"postalcode"
},
  "geometry": {"coordinates":[-4.17622514152812,50.3739583066132],"type":"Point"}
}