{
  "type": "Feature",
  "properties": {
    "date:inception_lower": "2017-05-01",
    "date:inception_upper": "2017-05-01",
    "iso:country": "GB",
    "wof:name": "BL5 1FN",
    "wof:placetype": "postalcode"
  },
  "geometry": {"coordinates":[-2.453173,53.54321],"type":"Point"}
}
