{
  "type": "Feature",
  "properties": {
    "iso:country": "GB",
    "wof:name": "B14 6JY",
    "wof:placetype": "postalcode"
  },
  "geometry": {"coordinates":[-1.908349,52.412843],"type":"Point"}
}
