{
  "type": "Feature",
  "properties": {
    "iso:country":"GB",
    "wof:name":"B14 6JY",
    "wof:placetype":"postalcode"
},
  "geometry": {"coordinates":[-1.90834942655055,52.41284348671659],"type":"Point"}
}