{
  "type": "Feature",
  "properties": {
    "iso:country":"GB",
    "wof:name":"B70 9HD",
    "wof:placetype":"postalcode"
},
  "geometry": {"coordinates":[-2.00409770752072,52.52065956862399],"type":"Point"}
}