{
  "type": "Feature",
  "properties": {
    "date:inception_lower":"1998-12-01",
    "date:inception_upper":"1998-12-31",
    "iso:country":"GB",
    "wof:name":"B70 9HD",
    "wof:placetype":"postalcode"
},
  "geometry": {"coordinates":[-2.004098,52.52066],"type":"Point"}
}