{
  "type": "Feature",
  "properties": {
    "date:inception_lower":"1984-02-01",
    "date:inception_upper":"1984-02-29",
    "iso:country":"GB",
    "wof:name":"TS1 5EA",
    "wof:placetype":"postalcode"
},
  "geometry": {"coordinates":[-1.23923,54.576023],"type":"Point"}
}