{
  "type": "Feature",
  "properties": {
    "iso:country":"GB",
    "wof:name":"TS1 5EA",
    "wof:placetype":"postalcode"
},
  "geometry": {"coordinates":[-1.23923030759359,54.57602334169307],"type":"Point"}
}