{
  "type": "Feature",
  "properties": {
    "iso:country":"GB",
    "wof:name":"IV30 4GP",
    "wof:placetype":"postalcode"
},
  "geometry": {"coordinates":[-3.32203402343702,57.65671083252246],"type":"Point"}
}