{
  "type": "Feature",
  "properties": {
    "iso:country":"GB",
    "wof:name":"S74 9BB",
    "wof:placetype":"postalcode"
},
  "geometry": {"coordinates":[-1.4385312515996,53.49886291421863],"type":"Point"}
}