{
  "type": "Feature",
  "properties": {
    "date:inception_lower": "1980-01-01",
    "date:inception_upper": "1980-01-01",
    "iso:country": "GB",
    "wof:name": "S74 9BB",
    "wof:placetype": "postalcode"
  },
  "geometry": {"coordinates":[-1.438518,53.498782],"type":"Point"}
}
