{
  "type": "Feature",
  "properties": {
    "iso:country": "GB",
    "wof:name": "S74 9BB",
    "wof:placetype": "postalcode"
  },
  "geometry": {"coordinates":[-1.438518,53.498782],"type":"Point"}
}
