{
  "type": "Feature",
  "properties": {
    "iso:country":"GB",
    "wof:name":"WS10 0EE",
    "wof:placetype":"postalcode"
},
  "geometry": {"coordinates":[-1.99575327226979,52.55276241167632],"type":"Point"}
}