{
  "type": "Feature",
  "properties": {
    "iso:country":"GB",
    "wof:name":"RG19 8EX",
    "wof:placetype":"postalcode"
},
  "geometry": {"coordinates":[-1.31281748391232,51.38394877847042],"type":"Point"}
}