{
  "type": "Feature",
  "properties": {
    "date:inception_lower": "2002-12-01",
    "date:inception_upper": "2002-12-01",
    "iso:country": "GB",
    "wof:name": "RG19 8EX",
    "wof:placetype": "postalcode"
  },
  "geometry": {"coordinates":[-1.312817,51.383949],"type":"Point"}
}
