{
  "type": "Feature",
  "properties": {
    "iso:country":"GB",
    "wof:name":"M27 8HP",
    "wof:placetype":"postalcode"
},
  "geometry": {"coordinates":[-2.3314748723962,53.51879342153567],"type":"Point"}
}