{
  "type": "Feature",
  "properties": {
    "iso:country": "GB",
    "wof:name": "CA3 8DH",
    "wof:placetype": "postalcode"
  },
  "geometry": {"coordinates":[-2.933123,54.894261],"type":"Point"}
}
