{
  "type": "Feature",
  "properties": {
    "date:inception_lower": "1980-01-01",
    "date:inception_upper": "1980-01-01",
    "iso:country": "GB",
    "wof:name": "CA3 8DH",
    "wof:placetype": "postalcode"
  },
  "geometry": {"coordinates":[-2.933123,54.894261],"type":"Point"}
}
