{
  "type": "Feature",
  "properties": {
    "iso:country": "GB",
    "wof:name": "KT21 1SH",
    "wof:placetype": "postalcode"
  },
  "geometry": {"coordinates":[-0.29584,51.314591],"type":"Point"}
}
