{
  "type": "Feature",
  "properties": {
    "iso:country":"GB",
    "wof:name":"M6 8NQ",
    "wof:placetype":"postalcode"
},
  "geometry": {"coordinates":[-2.31931935242094,53.49480044023322],"type":"Point"}
}