{
  "type": "Feature",
  "properties": {
    "iso:country":"GB",
    "wof:name":"PE14 8RX",
    "wof:placetype":"postalcode"
},
  "geometry": {"coordinates":[0.24918172521371,52.5977095577961],"type":"Point"}
}