{
  "type": "Feature",
  "properties": {
    "iso:country":"GB",
    "wof:name":"FY1 3RA",
    "wof:placetype":"postalcode"
},
  "geometry": {"coordinates":[-3.04455730615518,53.82525314185298],"type":"Point"}
}