{
  "type": "Feature",
  "properties": {
    "date:inception_lower": "1999-06-01",
    "date:inception_upper": "1999-06-01",
    "iso:country": "GB",
    "wof:name": "NP22 4QU",
    "wof:placetype": "postalcode"
  },
  "geometry": {"coordinates":[-3.24488,51.785381],"type":"Point"}
}
