{
  "type": "Feature",
  "properties": {
    "date:inception_lower": "1980-01-01",
    "date:inception_upper": "1980-01-01",
    "iso:country": "GB",
    "wof:name": "NE3 1RT",
    "wof:placetype": "postalcode"
  },
  "geometry": {"coordinates":[-1.6069,55.007664],"type":"Point"}
}
