{
  "type": "Feature",
  "properties": {
    "iso:country":"GB",
    "wof:name":"NE3 1RT",
    "wof:placetype":"postalcode"
},
  "geometry": {"coordinates":[-1.60689972674303,55.00766400864857],"type":"Point"}
}