{
  "type": "Feature",
  "properties": {
    "iso:country": "GB",
    "wof:name": "WF10 4LR",
    "wof:placetype": "postalcode"
  },
  "geometry": {"coordinates":[-1.342648,53.726132],"type":"Point"}
}
