{
  "type": "Feature",
  "properties": {
    "iso:country":"GB",
    "wof:name":"WF10 4LR",
    "wof:placetype":"postalcode"
},
  "geometry": {"coordinates":[-1.34264778287296,53.72613162365592],"type":"Point"}
}