{
  "type": "Feature",
  "properties": {
    "iso:country":"GB",
    "wof:name":"N3 1JH",
    "wof:placetype":"postalcode"
},
  "geometry": {"coordinates":[-0.19295011780796,51.60589851175342],"type":"Point"}
}