{
  "type": "Feature",
  "properties": {
    "date:inception_lower":"2002-06-01",
    "date:inception_upper":"2002-06-30",
    "iso:country":"GB",
    "wof:name":"EX14 1JA",
    "wof:placetype":"postalcode"
},
  "geometry": {"coordinates":[-3.19179,50.798524],"type":"Point"}
}