{
  "type": "Feature",
  "properties": {
    "iso:country": "GB",
    "wof:name": "LE67 2AD",
    "wof:placetype": "postalcode"
  },
  "geometry": {"coordinates":[-1.406094,52.71969],"type":"Point"}
}
