{
  "type": "Feature",
  "properties": {
    "iso:country":"GB",
    "wof:name":"G81 1JH",
    "wof:placetype":"postalcode"
},
  "geometry": {"coordinates":[-4.38852634637208,55.89207420516673],"type":"Point"}
}