{
  "type": "Feature",
  "properties": {
    "iso:country":"GB",
    "wof:name":"CT4 6RY",
    "wof:placetype":"postalcode"
},
  "geometry": {"coordinates":[1.2107857319424,51.17479335150588],"type":"Point"}
}