{
  "type": "Feature",
  "properties": {
    "iso:country":"GB",
    "wof:name":"CB11 3SG",
    "wof:placetype":"postalcode"
},
  "geometry": {"coordinates":[0.23734704690499,51.96173297966167],"type":"Point"}
}