{
  "type": "Feature",
  "properties": {
    "iso:country": "GB",
    "wof:name": "NP7 9TU",
    "wof:placetype": "postalcode"
  },
  "geometry": {"coordinates":[-2.938347,51.808503],"type":"Point"}
}
