{
  "type": "Feature",
  "properties": {
    "iso:country":"GB",
    "wof:name":"NP7 9TU",
    "wof:placetype":"postalcode"
},
  "geometry": {"coordinates":[-2.93834687652565,51.80850335121167],"type":"Point"}
}