{
  "type": "Feature",
  "properties": {
    "iso:country": "GB",
    "wof:name": "S81 7PD",
    "wof:placetype": "postalcode"
  },
  "geometry": {"coordinates":[-1.127838,53.32286],"type":"Point"}
}
