{
  "type": "Feature",
  "properties": {
    "date:inception_lower": "1980-01-01",
    "date:inception_upper": "1980-01-01",
    "iso:country": "GB",
    "wof:name": "S81 7PD",
    "wof:placetype": "postalcode"
  },
  "geometry": {"coordinates":[-1.127838,53.32286],"type":"Point"}
}
