{
  "type": "Feature",
  "properties": {
    "iso:country":"GB",
    "wof:name":"S81 7PD",
    "wof:placetype":"postalcode"
},
  "geometry": {"coordinates":[-1.12783812035833,53.32285960728006],"type":"Point"}
}