{
  "type": "Feature",
  "properties": {
    "iso:country":"GB",
    "wof:name":"TN31 6TR",
    "wof:placetype":"postalcode"
},
  "geometry": {"coordinates":[0.65288971558265,50.98883561173115],"type":"Point"}
}