{
  "type": "Feature",
  "properties": {
    "date:inception_lower": "1980-01-01",
    "date:inception_upper": "1980-01-01",
    "iso:country": "GB",
    "wof:name": "TN31 6TR",
    "wof:placetype": "postalcode"
  },
  "geometry": {"coordinates":[0.652877,50.988824],"type":"Point"}
}
