{
  "type": "Feature",
  "properties": {
    "iso:country":"GB",
    "wof:name":"PA14 5YQ",
    "wof:placetype":"postalcode"
},
  "geometry": {"coordinates":[-4.66478657367691,55.92145624944202],"type":"Point"}
}