{
  "type": "Feature",
  "properties": {
    "iso:country": "GB",
    "wof:name": "L15 6UL",
    "wof:placetype": "postalcode"
  },
  "geometry": {"coordinates":[-2.910968,53.39614],"type":"Point"}
}
