{
  "type": "Feature",
  "properties": {
    "date:inception_lower": "1980-01-01",
    "date:inception_upper": "1980-01-01",
    "iso:country": "GB",
    "wof:name": "OX12 0DT",
    "wof:placetype": "postalcode"
  },
  "geometry": {"coordinates":[-1.449331,51.624375],"type":"Point"}
}
