{
  "type": "Feature",
  "properties": {
    "date:inception_lower": "1994-05-01",
    "date:inception_upper": "1994-05-01",
    "iso:country": "GB",
    "wof:name": "PA12 4HT",
    "wof:placetype": "postalcode"
  },
  "geometry": {"coordinates":[-4.62788,55.797104],"type":"Point"}
}
