{
  "type": "Feature",
  "properties": {
    "iso:country":"GB",
    "wof:name":"PA12 4HT",
    "wof:placetype":"postalcode"
},
  "geometry": {"coordinates":[-4.62788004631656,55.7971044509366],"type":"Point"}
}