{
  "type": "Feature",
  "properties": {
    "iso:country":"GB",
    "wof:name":"G65 9PT",
    "wof:placetype":"postalcode"
},
  "geometry": {"coordinates":[-4.05933529843271,55.98288630986439],"type":"Point"}
}