{
  "type": "Feature",
  "properties": {
    "iso:country":"GB",
    "wof:name":"WA4 1QU",
    "wof:placetype":"postalcode"
},
  "geometry": {"coordinates":[-2.56521916705034,53.3853704232987],"type":"Point"}
}