{
  "type": "Feature",
  "properties": {
    "iso:country":"GB",
    "wof:name":"ST4 8BQ",
    "wof:placetype":"postalcode"
},
  "geometry": {"coordinates":[-2.18930422734454,52.96736127926903],"type":"Point"}
}