{
  "type": "Feature",
  "properties": {
    "iso:country": "GB",
    "wof:name": "CB9 7ER",
    "wof:placetype": "postalcode"
  },
  "geometry": {"coordinates":[0.443184,52.040499],"type":"Point"}
}
