{
  "type": "Feature",
  "properties": {
    "iso:country":"GB",
    "wof:name":"CB9 7ER",
    "wof:placetype":"postalcode"
},
  "geometry": {"coordinates":[0.44318427056142,52.04049887828008],"type":"Point"}
}