{
  "type": "Feature",
  "properties": {
    "date:inception_lower":"1991-09-01",
    "date:inception_upper":"1991-09-30",
    "iso:country":"GB",
    "wof:name":"CB9 7ER",
    "wof:placetype":"postalcode"
},
  "geometry": {"coordinates":[0.443184,52.040499],"type":"Point"}
}