{
  "type": "Feature",
  "properties": {
    "iso:country":"GB",
    "wof:name":"SA71 5BY",
    "wof:placetype":"postalcode"
},
  "geometry": {"coordinates":[-4.9095296904896,51.64506551914855],"type":"Point"}
}