{
  "type": "Feature",
  "properties": {
    "date:inception_lower": "1980-01-01",
    "date:inception_upper": "1980-01-01",
    "iso:country": "GB",
    "wof:name": "SA71 5BY",
    "wof:placetype": "postalcode"
  },
  "geometry": {"coordinates":[-4.90953,51.645066],"type":"Point"}
}
