{
  "type": "Feature",
  "properties": {
    "iso:country": "GB",
    "wof:name": "ST5 6SS",
    "wof:placetype": "postalcode"
  },
  "geometry": {"coordinates":[-2.282288,53.01996],"type":"Point"}
}
