{
  "type": "Feature",
  "properties": {
    "iso:country":"GB",
    "wof:name":"ST5 6SS",
    "wof:placetype":"postalcode"
},
  "geometry": {"coordinates":[-2.28297651404092,53.02040007978992],"type":"Point"}
}