{
  "type": "Feature",
  "properties": {
    "iso:country": "GB",
    "wof:name": "ST5 6SS",
    "wof:placetype": "postalcode"
  },
  "geometry": {"coordinates":[-2.282199,53.020006],"type":"Point"}
}
