{
  "type": "Feature",
  "properties": {
    "iso:country":"GB",
    "wof:name":"S6 5LG",
    "wof:placetype":"postalcode"
},
  "geometry": {"coordinates":[-1.52912403588006,53.39599317748357],"type":"Point"}
}