{
  "type": "Feature",
  "properties": {
    "iso:country":"GB",
    "wof:name":"CF64 3DH",
    "wof:placetype":"postalcode"
},
  "geometry": {"coordinates":[-3.17321596278541,51.43525230361461],"type":"Point"}
}