{
  "type": "Feature",
  "properties": {
    "iso:country": "GB",
    "wof:name": "MK2 2JU",
    "wof:placetype": "postalcode"
  },
  "geometry": {"coordinates":[-0.735597,51.996197],"type":"Point"}
}
