{
  "type": "Feature",
  "properties": {
    "iso:country":"GB",
    "wof:name":"MK2 2JU",
    "wof:placetype":"postalcode"
},
  "geometry": {"coordinates":[-0.73559698631333,51.99619716716312],"type":"Point"}
}