{
  "type": "Feature",
  "properties": {
    "date:inception_lower":"1981-06-01",
    "date:inception_upper":"1981-06-30",
    "iso:country":"GB",
    "wof:name":"MK2 2JU",
    "wof:placetype":"postalcode"
},
  "geometry": {"coordinates":[-0.735597,51.996197],"type":"Point"}
}