{
  "type": "Feature",
  "properties": {
    "iso:country": "GB",
    "wof:name": "DT2 9RN",
    "wof:placetype": "postalcode"
  },
  "geometry": {"coordinates":[-2.459538,50.741524],"type":"Point"}
}
