{
  "type": "Feature",
  "properties": {
    "iso:country":"GB",
    "wof:name":"DT2 9RN",
    "wof:placetype":"postalcode"
},
  "geometry": {"coordinates":[-2.45953831090151,50.74152421822016],"type":"Point"}
}