{
  "type": "Feature",
  "properties": {
    "date:inception_lower": "1980-01-01",
    "date:inception_upper": "1980-01-01",
    "iso:country": "GB",
    "wof:name": "DL13 3PX",
    "wof:placetype": "postalcode"
  },
  "geometry": {"coordinates":[-1.820892,54.674771],"type":"Point"}
}
