{
  "type": "Feature",
  "properties": {
    "iso:country":"GB",
    "wof:name":"DL13 3PX",
    "wof:placetype":"postalcode"
},
  "geometry": {"coordinates":[-1.8208924272873,54.67477104974238],"type":"Point"}
}