{
  "type": "Feature",
  "properties": {
    "iso:country":"GB",
    "wof:name":"BN11 4HN",
    "wof:placetype":"postalcode"
},
  "geometry": {"coordinates":[-0.38976812539759,50.81819094080036],"type":"Point"}
}