{
  "type": "Feature",
  "properties": {
    "iso:country": "GB",
    "wof:name": "RM16 6YA",
    "wof:placetype": "postalcode"
  },
  "geometry": {"coordinates":[0.289158,51.488373],"type":"Point"}
}
