{
  "type": "Feature",
  "properties": {
    "iso:country":"GB",
    "wof:name":"B64 5LD",
    "wof:placetype":"postalcode"
},
  "geometry": {"coordinates":[-2.07676710090065,52.47728513578991],"type":"Point"}
}