{
  "type": "Feature",
  "properties": {
    "iso:country": "GB",
    "wof:name": "B64 5LD",
    "wof:placetype": "postalcode"
  },
  "geometry": {"coordinates":[-2.076767,52.477285],"type":"Point"}
}
