{
  "type": "Feature",
  "properties": {
    "date:inception_lower": "2023-05-01",
    "date:inception_upper": "2023-05-01",
    "iso:country": "GB",
    "wof:name": "PR2 5TX",
    "wof:placetype": "postalcode"
  },
  "geometry": {"coordinates":[-2.633122,53.800058],"type":"Point"}
}
