{
  "type": "Feature",
  "properties": {
    "iso:country":"GB",
    "wof:name":"N11 2RT",
    "wof:placetype":"postalcode"
},
  "geometry": {"coordinates":[-0.13376427837335,51.61201345890385],"type":"Point"}
}