{
  "type": "Feature",
  "properties": {
    "iso:country":"GB",
    "wof:name":"TF9 3TQ",
    "wof:placetype":"postalcode"
},
  "geometry": {"coordinates":[-2.50452202251505,52.95821548047621],"type":"Point"}
}