{
  "type": "Feature",
  "properties": {
    "iso:country": "GB",
    "wof:name": "TF9 3TQ",
    "wof:placetype": "postalcode"
  },
  "geometry": {"coordinates":[-2.504386,52.958052],"type":"Point"}
}
