{
  "type": "Feature",
  "properties": {
    "iso:country":"GB",
    "wof:name":"DA15 8LL",
    "wof:placetype":"postalcode"
},
  "geometry": {"coordinates":[0.10030626825055,51.43686269990241],"type":"Point"}
}