{
  "type": "Feature",
  "properties": {
    "iso:country": "GB",
    "wof:name": "NR12 7GL",
    "wof:placetype": "postalcode"
  },
  "geometry": {"coordinates":[1.326669,52.707521],"type":"Point"}
}
