{
  "type": "Feature",
  "properties": {
    "iso:country": "GB",
    "wof:name": "TN5 7EZ",
    "wof:placetype": "postalcode"
  },
  "geometry": {"coordinates":[0.410947,51.045949],"type":"Point"}
}
