{
  "type": "Feature",
  "properties": {
    "iso:country":"GB",
    "wof:name":"TN5 7EZ",
    "wof:placetype":"postalcode"
},
  "geometry": {"coordinates":[0.41087631507498,51.04596873131619],"type":"Point"}
}