{
  "type": "Feature",
  "properties": {
    "iso:country":"GB",
    "wof:name":"EX39 6HB",
    "wof:placetype":"postalcode"
},
  "geometry": {"coordinates":[-4.46362919648779,50.94738934332756],"type":"Point"}
}