{
  "type": "Feature",
  "properties": {
    "iso:country":"GB",
    "wof:name":"IG2 7QH",
    "wof:placetype":"postalcode"
},
  "geometry": {"coordinates":[0.09935206023596,51.58221250283158],"type":"Point"}
}