{
  "type": "Feature",
  "properties": {
    "iso:country": "GB",
    "wof:name": "KY11 8QJ",
    "wof:placetype": "postalcode"
  },
  "geometry": {"coordinates":[-3.412379,56.049111],"type":"Point"}
}
