{
  "type": "Feature",
  "properties": {
    "iso:country":"GB",
    "wof:name":"CM6 1SX",
    "wof:placetype":"postalcode"
},
  "geometry": {"coordinates":[0.28880804522288,51.86861509015232],"type":"Point"}
}