{
  "type": "Feature",
  "properties": {
    "iso:country": "GB",
    "wof:name": "CM6 1SX",
    "wof:placetype": "postalcode"
  },
  "geometry": {"coordinates":[0.288808,51.868615],"type":"Point"}
}
