{
  "type": "Feature",
  "properties": {
    "iso:country":"GB",
    "wof:name":"IP31 3ST",
    "wof:placetype":"postalcode"
},
  "geometry": {"coordinates":[0.82330654427858,52.24979580684832],"type":"Point"}
}