{
  "type": "Feature",
  "properties": {
    "iso:country":"GB",
    "wof:name":"SW17 9SD",
    "wof:placetype":"postalcode"
},
  "geometry": {"coordinates":[-0.16553754447423,51.42265624068268],"type":"Point"}
}