{
  "type": "Feature",
  "properties": {
    "iso:country":"GB",
    "wof:name":"EX4 3SP",
    "wof:placetype":"postalcode"
},
  "geometry": {"coordinates":[-3.53351403913954,50.72551703360168],"type":"Point"}
}