{
  "type": "Feature",
  "properties": {
    "iso:country":"GB",
    "wof:name":"TQ2 5LT",
    "wof:placetype":"postalcode"
},
  "geometry": {"coordinates":[-3.54822389554029,50.47115740321742],"type":"Point"}
}