{
  "type": "Feature",
  "properties": {
    "iso:country":"GB",
    "wof:name":"SN2 8BS",
    "wof:placetype":"postalcode"
},
  "geometry": {"coordinates":[-1.77439395643383,51.57011634790069],"type":"Point"}
}