{
  "type": "Feature",
  "properties": {
    "iso:country": "GB",
    "wof:name": "SN2 8BS",
    "wof:placetype": "postalcode"
  },
  "geometry": {"coordinates":[-1.774526,51.570091],"type":"Point"}
}
