{
  "type": "Feature",
  "properties": {
    "iso:country": "GB",
    "wof:name": "M30 9JU",
    "wof:placetype": "postalcode"
  },
  "geometry": {"coordinates":[-2.349264,53.490339],"type":"Point"}
}
