{
  "type": "Feature",
  "properties": {
    "iso:country":"GB",
    "wof:name":"M30 9JU",
    "wof:placetype":"postalcode"
},
  "geometry": {"coordinates":[-2.34926355862595,53.49033924958182],"type":"Point"}
}