{
  "type": "Feature",
  "properties": {
    "date:inception_lower": "1980-01-01",
    "date:inception_upper": "1980-01-01",
    "iso:country": "GB",
    "wof:name": "M30 9JU",
    "wof:placetype": "postalcode"
  },
  "geometry": {"coordinates":[-2.349264,53.490339],"type":"Point"}
}
