{
  "type": "Feature",
  "properties": {
    "date:inception_lower": "1991-08-01",
    "date:inception_upper": "1991-08-01",
    "iso:country": "GB",
    "wof:name": "AB38 9QE",
    "wof:placetype": "postalcode"
  },
  "geometry": {"coordinates":[-3.216631,57.472147],"type":"Point"}
}
