{
  "type": "Feature",
  "properties": {
    "date:inception_lower": "2022-11-01",
    "date:inception_upper": "2022-11-01",
    "iso:country": "GB",
    "wof:name": "PE19 6FH",
    "wof:placetype": "postalcode"
  },
  "geometry": {"coordinates":[-0.265839,52.248602],"type":"Point"}
}
