{
  "type": "Feature",
  "properties": {
    "iso:country":"GB",
    "wof:name":"LN5 7SL",
    "wof:placetype":"postalcode"
},
  "geometry": {"coordinates":[-0.54198967023909,53.22166096892523],"type":"Point"}
}