{
  "type": "Feature",
  "properties": {
    "iso:country": "GB",
    "wof:name": "LN5 7SL",
    "wof:placetype": "postalcode"
  },
  "geometry": {"coordinates":[-0.54199,53.221661],"type":"Point"}
}
