{
  "type": "Feature",
  "properties": {
    "iso:country": "GB",
    "wof:name": "GL53 7QH",
    "wof:placetype": "postalcode"
  },
  "geometry": {"coordinates":[-2.064617,51.891981],"type":"Point"}
}
