{
  "type": "Feature",
  "properties": {
    "iso:country": "GB",
    "wof:name": "NR21 8ED",
    "wof:placetype": "postalcode"
  },
  "geometry": {"coordinates":[0.859796,52.835703],"type":"Point"}
}
