{
  "type": "Feature",
  "properties": {
    "date:inception_lower":"2019-02-01",
    "date:inception_upper":"2019-02-28",
    "iso:country":"GB",
    "wof:name":"NR21 8ED",
    "wof:placetype":"postalcode"
},
  "geometry": {"coordinates":[0.859796,52.835703],"type":"Point"}
}