{
  "type": "Feature",
  "properties": {
    "date:inception_lower": "2019-02-01",
    "date:inception_upper": "2019-02-01",
    "iso:country": "GB",
    "wof:name": "NR21 8ED",
    "wof:placetype": "postalcode"
  },
  "geometry": {"coordinates":[0.859804,52.835586],"type":"Point"}
}
