{
  "type": "Feature",
  "properties": {
    "iso:country":"GB",
    "wof:name":"ML8 5SF",
    "wof:placetype":"postalcode"
},
  "geometry": {"coordinates":[-3.87023211025688,55.70058321331476],"type":"Point"}
}