{
  "type": "Feature",
  "properties": {
    "iso:country":"GB",
    "wof:name":"WS6 7PA",
    "wof:placetype":"postalcode"
},
  "geometry": {"coordinates":[-2.03487411503433,52.65499790601643],"type":"Point"}
}