{
  "type": "Feature",
  "properties": {
    "iso:country": "GB",
    "wof:name": "WS6 7PA",
    "wof:placetype": "postalcode"
  },
  "geometry": {"coordinates":[-2.034874,52.654998],"type":"Point"}
}
