{
  "type": "Feature",
  "properties": {
    "iso:country":"GB",
    "wof:name":"EX37 9SD",
    "wof:placetype":"postalcode"
},
  "geometry": {"coordinates":[-3.9804536504471,51.02794963642004],"type":"Point"}
}