{
  "type": "Feature",
  "properties": {
    "iso:country":"GB",
    "wof:name":"AL7 2PE",
    "wof:placetype":"postalcode"
},
  "geometry": {"coordinates":[-0.16391101846863,51.79887947524835],"type":"Point"}
}