{
  "type": "Feature",
  "properties": {
    "date:inception_lower": "1987-10-01",
    "date:inception_upper": "1987-10-01",
    "iso:country": "GB",
    "wof:name": "AL7 2PE",
    "wof:placetype": "postalcode"
  },
  "geometry": {"coordinates":[-0.163913,51.798904],"type":"Point"}
}
