{
  "type": "Feature",
  "properties": {
    "iso:country":"GB",
    "wof:name":"S43 2DW",
    "wof:placetype":"postalcode"
},
  "geometry": {"coordinates":[-1.40526471799481,53.27193472017846],"type":"Point"}
}