{
  "type": "Feature",
  "properties": {
    "iso:country": "GB",
    "wof:name": "S43 2DW",
    "wof:placetype": "postalcode"
  },
  "geometry": {"coordinates":[-1.405277,53.271935],"type":"Point"}
}
