{
  "type": "Feature",
  "properties": {
    "date:inception_lower": "2001-06-01",
    "date:inception_upper": "2001-06-01",
    "iso:country": "GB",
    "wof:name": "HD9 6RD",
    "wof:placetype": "postalcode"
  },
  "geometry": {"coordinates":[-1.797481,53.609143],"type":"Point"}
}
