{
  "type": "Feature",
  "properties": {
    "date:inception_lower":"1980-01-01",
    "date:inception_upper":"1980-01-31",
    "iso:country":"GB",
    "wof:name":"G68 9DY",
    "wof:placetype":"postalcode"
},
  "geometry": {"coordinates":[-4.042719,55.934975],"type":"Point"}
}