{
  "type": "Feature",
  "properties": {
    "iso:country":"GB",
    "wof:name":"G68 9DY",
    "wof:placetype":"postalcode"
},
  "geometry": {"coordinates":[-4.04271863040471,55.9349752844929],"type":"Point"}
}