{
  "type": "Feature",
  "properties": {
    "date:inception_lower": "1980-01-01",
    "date:inception_upper": "1980-01-01",
    "iso:country": "GB",
    "wof:name": "S41 7PL",
    "wof:placetype": "postalcode"
  },
  "geometry": {"coordinates":[-1.432586,53.241236],"type":"Point"}
}
