{
  "type": "Feature",
  "properties": {
    "iso:country":"GB",
    "wof:name":"WD25 0JS",
    "wof:placetype":"postalcode"
},
  "geometry": {"coordinates":[-0.38592158426183,51.70045630651378],"type":"Point"}
}