{
  "type": "Feature",
  "properties": {
    "date:inception_lower": "1981-09-01",
    "date:inception_upper": "1981-09-01",
    "iso:country": "GB",
    "wof:name": "S10 5SS",
    "wof:placetype": "postalcode"
  },
  "geometry": {"coordinates":[-1.540123,53.375874],"type":"Point"}
}
