{
  "type": "Feature",
  "properties": {
    "date:inception_lower": "1990-07-01",
    "date:inception_upper": "1990-07-01",
    "iso:country": "GB",
    "wof:name": "OX10 7PA",
    "wof:placetype": "postalcode"
  },
  "geometry": {"coordinates":[-1.171471,51.664581],"type":"Point"}
}
