{
  "type": "Feature",
  "properties": {
    "date:inception_lower": "1980-01-01",
    "date:inception_upper": "1980-01-01",
    "iso:country": "GB",
    "wof:name": "CR3 6DT",
    "wof:placetype": "postalcode"
  },
  "geometry": {"coordinates":[-0.079883,51.273577],"type":"Point"}
}
