{
  "type": "Feature",
  "properties": {
    "iso:country":"GB",
    "wof:name":"OL9 8BN",
    "wof:placetype":"postalcode"
},
  "geometry": {"coordinates":[-2.15563225040946,53.52603709433103],"type":"Point"}
}