{
  "type": "Feature",
  "properties": {
    "iso:country": "GB",
    "wof:name": "OL9 8BN",
    "wof:placetype": "postalcode"
  },
  "geometry": {"coordinates":[-2.155632,53.526037],"type":"Point"}
}
