{
  "type": "Feature",
  "properties": {
    "iso:country": "GB",
    "wof:name": "NE34 7SJ",
    "wof:placetype": "postalcode"
  },
  "geometry": {"coordinates":[-1.40283,54.984269],"type":"Point"}
}
