{
  "type": "Feature",
  "properties": {
    "iso:country":"GB",
    "wof:name":"NE34 7SJ",
    "wof:placetype":"postalcode"
},
  "geometry": {"coordinates":[-1.40282981693386,54.9842694164989],"type":"Point"}
}