{
  "type": "Feature",
  "properties": {
    "iso:country":"GB",
    "wof:name":"LN8 2FS",
    "wof:placetype":"postalcode"
},
  "geometry": {"coordinates":[-0.49843767449966,53.38106295126498],"type":"Point"}
}