{
  "type": "Feature",
  "properties": {
    "iso:country":"GB",
    "wof:name":"SL3 9AL",
    "wof:placetype":"postalcode"
},
  "geometry": {"coordinates":[-0.58265484683287,51.48935480670158],"type":"Point"}
}