{
  "type": "Feature",
  "properties": {
    "iso:country":"GB",
    "wof:name":"YO13 0DW",
    "wof:placetype":"postalcode"
},
  "geometry": {"coordinates":[-0.48667360234337,54.3403443429827],"type":"Point"}
}