{
  "type": "Feature",
  "properties": {
    "iso:country":"GB",
    "wof:name":"DN21 5AD",
    "wof:placetype":"postalcode"
},
  "geometry": {"coordinates":[-0.73797382453396,53.32836259455805],"type":"Point"}
}