{
  "type": "Feature",
  "properties": {
    "iso:country": "GB",
    "wof:name": "TS26 0QJ",
    "wof:placetype": "postalcode"
  },
  "geometry": {"coordinates":[-1.25267,54.687806],"type":"Point"}
}
