{
  "type": "Feature",
  "properties": {
    "iso:country":"GB",
    "wof:name":"TS26 0QJ",
    "wof:placetype":"postalcode"
},
  "geometry": {"coordinates":[-1.25266972748594,54.6878059013484],"type":"Point"}
}