{
  "type": "Feature",
  "properties": {
    "iso:country": "GB",
    "wof:name": "GL4 8DS",
    "wof:placetype": "postalcode"
  },
  "geometry": {"coordinates":[-2.186625,51.822917],"type":"Point"}
}
