{
  "type": "Feature",
  "properties": {
    "iso:country": "GB",
    "wof:name": "TN3 0UT",
    "wof:placetype": "postalcode"
  },
  "geometry": {"coordinates":[0.236647,51.168832],"type":"Point"}
}
