{
  "type": "Feature",
  "properties": {
    "iso:country":"GB",
    "wof:name":"TN3 0UT",
    "wof:placetype":"postalcode"
},
  "geometry": {"coordinates":[0.23664716384911,51.16883198872469],"type":"Point"}
}