{
  "type": "Feature",
  "properties": {
    "date:inception_lower": "1980-01-01",
    "date:inception_upper": "1980-01-01",
    "iso:country": "GB",
    "wof:name": "PL16 0DB",
    "wof:placetype": "postalcode"
  },
  "geometry": {"coordinates":[-4.306894,50.645237],"type":"Point"}
}
