{
  "type": "Feature",
  "properties": {
    "date:inception_lower":"2000-10-01",
    "date:inception_upper":"2000-10-31",
    "iso:country":"GB",
    "wof:name":"OX25 4SQ",
    "wof:placetype":"postalcode"
},
  "geometry": {"coordinates":[-1.309017,51.929307],"type":"Point"}
}