{
  "type": "Feature",
  "properties": {
    "iso:country":"GB",
    "wof:name":"OX25 4SQ",
    "wof:placetype":"postalcode"
},
  "geometry": {"coordinates":[-1.30901657768606,51.92930710308875],"type":"Point"}
}