{
  "type": "Feature",
  "properties": {
    "iso:country": "GB",
    "wof:name": "AL2 1BL",
    "wof:placetype": "postalcode"
  },
  "geometry": {"coordinates":[-0.286585,51.719012],"type":"Point"}
}
