{
  "type": "Feature",
  "properties": {
    "iso:country":"GB",
    "wof:name":"AL2 1BL",
    "wof:placetype":"postalcode"
},
  "geometry": {"coordinates":[-0.28658536183063,51.71901191483278],"type":"Point"}
}