{
  "type": "Feature",
  "properties": {
    "iso:country":"GB",
    "wof:name":"ME8 9DD",
    "wof:placetype":"postalcode"
},
  "geometry": {"coordinates":[0.60325096535638,51.36103407253987],"type":"Point"}
}