{
  "type": "Feature",
  "properties": {
    "iso:country": "GB",
    "wof:name": "ME8 9DD",
    "wof:placetype": "postalcode"
  },
  "geometry": {"coordinates":[0.603251,51.361034],"type":"Point"}
}
