{
  "type": "Feature",
  "properties": {
    "date:inception_lower": "1980-01-01",
    "date:inception_upper": "1980-01-01",
    "iso:country": "GB",
    "wof:name": "ME8 9DD",
    "wof:placetype": "postalcode"
  },
  "geometry": {"coordinates":[0.603251,51.361034],"type":"Point"}
}
