{
  "type": "Feature",
  "properties": {
    "date:inception_lower": "2011-05-01",
    "date:inception_upper": "2011-05-01",
    "iso:country": "GB",
    "wof:name": "LE5 0QN",
    "wof:placetype": "postalcode"
  },
  "geometry": {"coordinates":[-1.08982,52.644318],"type":"Point"}
}
