{
  "type": "Feature",
  "properties": {
    "iso:country": "GB",
    "wof:name": "OX12 7FJ",
    "wof:placetype": "postalcode"
  },
  "geometry": {"coordinates":[-1.419145,51.590909],"type":"Point"}
}
