{
  "type": "Feature",
  "properties": {
    "iso:country": "GB",
    "wof:name": "TA14 6TL",
    "wof:placetype": "postalcode"
  },
  "geometry": {"coordinates":[-2.753047,50.92941],"type":"Point"}
}
