{
  "type": "Feature",
  "properties": {
    "iso:country": "GB",
    "wof:name": "HP18 0PW",
    "wof:placetype": "postalcode"
  },
  "geometry": {"coordinates":[-0.958359,51.848063],"type":"Point"}
}
