{
  "type": "Feature",
  "properties": {
    "date:inception_lower": "2008-03-01",
    "date:inception_upper": "2008-03-01",
    "iso:country": "GB",
    "wof:name": "HP18 0PW",
    "wof:placetype": "postalcode"
  },
  "geometry": {"coordinates":[-0.958359,51.848063],"type":"Point"}
}
