{
  "type": "Feature",
  "properties": {
    "iso:country":"GB",
    "wof:name":"HP18 0PW",
    "wof:placetype":"postalcode"
},
  "geometry": {"coordinates":[-0.95835916628206,51.8480631049248],"type":"Point"}
}