{
  "type": "Feature",
  "properties": {
    "iso:country":"GB",
    "wof:name":"EN11 8FL",
    "wof:placetype":"postalcode"
},
  "geometry": {"coordinates":[-0.01091684568911,51.76297513532744],"type":"Point"}
}