{
  "type": "Feature",
  "properties": {
    "iso:country": "GB",
    "wof:name": "EN11 8FL",
    "wof:placetype": "postalcode"
  },
  "geometry": {"coordinates":[-0.010917,51.762975],"type":"Point"}
}
