{
  "type": "Feature",
  "properties": {
    "iso:country":"GB",
    "wof:name":"SW9 0DA",
    "wof:placetype":"postalcode"
},
  "geometry": {"coordinates":[-0.11702040167099,51.47166997330388],"type":"Point"}
}