{
  "type": "Feature",
  "properties": {
    "iso:country":"GB",
    "wof:name":"CM2 0JL",
    "wof:placetype":"postalcode"
},
  "geometry": {"coordinates":[0.46339665075089,51.72510341161462],"type":"Point"}
}