{
  "type": "Feature",
  "properties": {
    "iso:country": "GB",
    "wof:name": "CM2 0JL",
    "wof:placetype": "postalcode"
  },
  "geometry": {"coordinates":[0.463397,51.725103],"type":"Point"}
}
