{
  "type": "Feature",
  "properties": {
    "iso:country":"GB",
    "wof:name":"E16 3AE",
    "wof:placetype":"postalcode"
},
  "geometry": {"coordinates":[0.02069971461595,51.51092364023488],"type":"Point"}
}