{
  "type": "Feature",
  "properties": {
    "iso:country": "GB",
    "wof:name": "SL9 9FT",
    "wof:placetype": "postalcode"
  },
  "geometry": {"coordinates":[-0.558811,51.603931],"type":"Point"}
}
