{
  "type": "Feature",
  "properties": {
    "iso:country":"GB",
    "wof:name":"BN3 1TA",
    "wof:placetype":"postalcode"
},
  "geometry": {"coordinates":[-0.1536963325637,50.83175433492097],"type":"Point"}
}