{
  "type": "Feature",
  "properties": {
    "iso:country":"GB",
    "wof:name":"DN12 2NX",
    "wof:placetype":"postalcode"
},
  "geometry": {"coordinates":[-1.23840639092475,53.47805269404719],"type":"Point"}
}