{
  "type": "Feature",
  "properties": {
    "date:inception_lower":"1995-07-01",
    "date:inception_upper":"1995-07-31",
    "iso:country":"GB",
    "wof:name":"DN12 2NX",
    "wof:placetype":"postalcode"
},
  "geometry": {"coordinates":[-1.238406,53.478053],"type":"Point"}
}