{
  "type": "Feature",
  "properties": {
    "date:inception_lower":"1984-02-01",
    "date:inception_upper":"1984-02-29",
    "iso:country":"GB",
    "wof:name":"SG7 5BG",
    "wof:placetype":"postalcode"
},
  "geometry": {"coordinates":[-0.196781,51.98937],"type":"Point"}
}