{
  "type": "Feature",
  "properties": {
    "iso:country":"GB",
    "wof:name":"SG7 5BG",
    "wof:placetype":"postalcode"
},
  "geometry": {"coordinates":[-0.19683728303439,51.98936122511851],"type":"Point"}
}