{
  "type": "Feature",
  "properties": {
    "iso:country": "GB",
    "wof:name": "HR1 2QG",
    "wof:placetype": "postalcode"
  },
  "geometry": {"coordinates":[-2.709668,52.052862],"type":"Point"}
}
