{
  "type": "Feature",
  "properties": {
    "date:inception_lower":"1980-01-01",
    "date:inception_upper":"1980-01-31",
    "iso:country":"GB",
    "wof:name":"HR1 2QG",
    "wof:placetype":"postalcode"
},
  "geometry": {"coordinates":[-2.709668,52.052862],"type":"Point"}
}