{
  "type": "Feature",
  "properties": {
    "iso:country":"GB",
    "wof:name":"BA2 5PA",
    "wof:placetype":"postalcode"
},
  "geometry": {"coordinates":[-2.3601362038182,51.3612471425238],"type":"Point"}
}