{
  "type": "Feature",
  "properties": {
    "iso:country":"GB",
    "wof:name":"DT11 9LE",
    "wof:placetype":"postalcode"
},
  "geometry": {"coordinates":[-2.16176669673596,50.85256688423702],"type":"Point"}
}