{
  "type": "Feature",
  "properties": {
    "iso:country":"GB",
    "wof:name":"SE10 9JU",
    "wof:placetype":"postalcode"
},
  "geometry": {"coordinates":[-0.01466571868965,51.47877630936777],"type":"Point"}
}