{
  "type": "Feature",
  "properties": {
    "iso:country":"GB",
    "wof:name":"WN2 2PF",
    "wof:placetype":"postalcode"
},
  "geometry": {"coordinates":[-2.59494692390785,53.54394661820262],"type":"Point"}
}