{
  "type": "Feature",
  "properties": {
    "iso:country":"GB",
    "wof:name":"NE4 6EY",
    "wof:placetype":"postalcode"
},
  "geometry": {"coordinates":[-1.631019875301,54.97242359157454],"type":"Point"}
}