{
  "type": "Feature",
  "properties": {
    "iso:country":"GB",
    "wof:name":"HU17 0EH",
    "wof:placetype":"postalcode"
},
  "geometry": {"coordinates":[-0.41874366253905,53.84135323093173],"type":"Point"}
}