{
  "type": "Feature",
  "properties": {
    "iso:country": "GB",
    "wof:name": "HU17 0EH",
    "wof:placetype": "postalcode"
  },
  "geometry": {"coordinates":[-0.418782,53.841364],"type":"Point"}
}
