{
  "type": "Feature",
  "properties": {
    "date:inception_lower":"1980-01-01",
    "date:inception_upper":"1980-01-31",
    "iso:country":"GB",
    "wof:name":"HU17 0EH",
    "wof:placetype":"postalcode"
},
  "geometry": {"coordinates":[-0.418782,53.841364],"type":"Point"}
}