{
  "type": "Feature",
  "properties": {
    "iso:country":"GB",
    "wof:name":"BA1 7PA",
    "wof:placetype":"postalcode"
},
  "geometry": {"coordinates":[-2.31647159763132,51.41089044226119],"type":"Point"}
}