{
  "type": "Feature",
  "properties": {
    "iso:country":"GB",
    "wof:name":"LN2 4JY",
    "wof:placetype":"postalcode"
},
  "geometry": {"coordinates":[-0.5060079809768,53.23681246241375],"type":"Point"}
}