{
  "type": "Feature",
  "properties": {
    "date:inception_lower": "1980-01-01",
    "date:inception_upper": "1980-01-01",
    "iso:country": "GB",
    "wof:name": "PH7 4DL",
    "wof:placetype": "postalcode"
  },
  "geometry": {"coordinates":[-3.84248,56.373246],"type":"Point"}
}
