{
  "type": "Feature",
  "properties": {
    "iso:country":"GB",
    "wof:name":"PH7 4DL",
    "wof:placetype":"postalcode"
},
  "geometry": {"coordinates":[-3.84245316051881,56.37325549660224],"type":"Point"}
}