{
  "type": "Feature",
  "properties": {
    "date:inception_lower": "1998-06-01",
    "date:inception_upper": "1998-06-01",
    "iso:country": "GB",
    "wof:name": "YO41 1EF",
    "wof:placetype": "postalcode"
  },
  "geometry": {"coordinates":[-0.907469,53.967556],"type":"Point"}
}
