{
  "type": "Feature",
  "properties": {
    "date:inception_lower": "2010-05-01",
    "date:inception_upper": "2010-05-01",
    "iso:country": "GB",
    "wof:name": "TF4 3ST",
    "wof:placetype": "postalcode"
  },
  "geometry": {"coordinates":[-2.48562,52.652425],"type":"Point"}
}
