{
  "type": "Feature",
  "properties": {
    "iso:country":"GB",
    "wof:name":"SG6 4SA",
    "wof:placetype":"postalcode"
},
  "geometry": {"coordinates":[-0.23266109165121,51.98873535392924],"type":"Point"}
}