{
  "type": "Feature",
  "properties": {
    "iso:country": "GB",
    "wof:name": "TN33 9LH",
    "wof:placetype": "postalcode"
  },
  "geometry": {"coordinates":[0.42203,50.889306],"type":"Point"}
}
