{
  "type": "Feature",
  "properties": {
    "date:inception_lower": "1985-10-01",
    "date:inception_upper": "1985-10-01",
    "iso:country": "GB",
    "wof:name": "TN33 9LH",
    "wof:placetype": "postalcode"
  },
  "geometry": {"coordinates":[0.422073,50.889301],"type":"Point"}
}
