{
  "type": "Feature",
  "properties": {
    "iso:country":"GB",
    "wof:name":"TN33 9LH",
    "wof:placetype":"postalcode"
},
  "geometry": {"coordinates":[0.42202999488215,50.88930636643161],"type":"Point"}
}