{
  "type": "Feature",
  "properties": {
    "iso:country":"GB",
    "wof:name":"SA8 4PR",
    "wof:placetype":"postalcode"
},
  "geometry": {"coordinates":[-3.83846172812472,51.73115930329912],"type":"Point"}
}