{
  "type": "Feature",
  "properties": {
    "date:inception_lower": "1980-01-01",
    "date:inception_upper": "1980-01-01",
    "iso:country": "GB",
    "wof:name": "SA8 4PR",
    "wof:placetype": "postalcode"
  },
  "geometry": {"coordinates":[-3.838462,51.731159],"type":"Point"}
}
