{
  "type": "Feature",
  "properties": {
    "iso:country":"GB",
    "wof:name":"S73 8PY",
    "wof:placetype":"postalcode"
},
  "geometry": {"coordinates":[-1.41152067668163,53.52255265072606],"type":"Point"}
}