{
  "type": "Feature",
  "properties": {
    "date:inception_lower": "1980-01-01",
    "date:inception_upper": "1980-01-01",
    "iso:country": "GB",
    "wof:name": "FK15 0ER",
    "wof:placetype": "postalcode"
  },
  "geometry": {"coordinates":[-3.963355,56.188654],"type":"Point"}
}
