{
  "type": "Feature",
  "properties": {
    "date:inception_lower": "1980-01-01",
    "date:inception_upper": "1980-01-01",
    "iso:country": "GB",
    "wof:name": "ME16 9HS",
    "wof:placetype": "postalcode"
  },
  "geometry": {"coordinates":[0.474495,51.270175],"type":"Point"}
}
