{
  "type": "Feature",
  "properties": {
    "iso:country":"GB",
    "wof:name":"ME16 9HS",
    "wof:placetype":"postalcode"
},
  "geometry": {"coordinates":[0.47449541383824,51.27017542768321],"type":"Point"}
}