{
  "type": "Feature",
  "properties": {
    "iso:country":"GB",
    "wof:name":"NE24 4RR",
    "wof:placetype":"postalcode"
},
  "geometry": {"coordinates":[-1.54264180629996,55.13101712712339],"type":"Point"}
}