{
  "type": "Feature",
  "properties": {
    "date:inception_lower": "1995-07-01",
    "date:inception_upper": "1995-07-01",
    "iso:country": "GB",
    "wof:name": "NE24 4RR",
    "wof:placetype": "postalcode"
  },
  "geometry": {"coordinates":[-1.542752,55.131018],"type":"Point"}
}
