{
  "type": "Feature",
  "properties": {
    "iso:country": "GB",
    "wof:name": "NE24 4RR",
    "wof:placetype": "postalcode"
  },
  "geometry": {"coordinates":[-1.542752,55.131018],"type":"Point"}
}
