{
  "type": "Feature",
  "properties": {
    "iso:country":"GB",
    "wof:name":"IP19 9DU",
    "wof:placetype":"postalcode"
},
  "geometry": {"coordinates":[1.55091460797596,52.32828259367368],"type":"Point"}
}