{
  "type": "Feature",
  "properties": {
    "date:inception_lower":"2017-06-01",
    "date:inception_upper":"2017-06-30",
    "iso:country":"GB",
    "wof:name":"LD3 7WD",
    "wof:placetype":"postalcode"
},
  "geometry": {"coordinates":[-3.411715,51.941196],"type":"Point"}
}