{
  "type": "Feature",
  "properties": {
    "iso:country": "GB",
    "wof:name": "WA14 3PZ",
    "wof:placetype": "postalcode"
  },
  "geometry": {"coordinates":[-2.346576,53.364049],"type":"Point"}
}
