{
  "type": "Feature",
  "properties": {
    "iso:country": "GB",
    "wof:name": "HX3 6AQ",
    "wof:placetype": "postalcode"
  },
  "geometry": {"coordinates":[-1.84889,53.725816],"type":"Point"}
}
