{
  "type": "Feature",
  "properties": {
    "iso:country":"GB",
    "wof:name":"HX3 6AQ",
    "wof:placetype":"postalcode"
},
  "geometry": {"coordinates":[-1.84888990936689,53.72581583823344],"type":"Point"}
}