{
  "type": "Feature",
  "properties": {
    "date:inception_lower": "2005-03-01",
    "date:inception_upper": "2005-03-01",
    "iso:country": "GB",
    "wof:name": "CF23 7HA",
    "wof:placetype": "postalcode"
  },
  "geometry": {"coordinates":[-3.141975,51.530237],"type":"Point"}
}
