{
  "type": "Feature",
  "properties": {
    "iso:country":"GB",
    "wof:name":"CF23 7HA",
    "wof:placetype":"postalcode"
},
  "geometry": {"coordinates":[-3.14196559001944,51.5302365800567],"type":"Point"}
}