{
  "type": "Feature",
  "properties": {
    "iso:country": "GB",
    "wof:name": "CF23 7HA",
    "wof:placetype": "postalcode"
  },
  "geometry": {"coordinates":[-3.141975,51.530237],"type":"Point"}
}
