{
  "type": "Feature",
  "properties": {
    "iso:country": "GB",
    "wof:name": "CO9 1SB",
    "wof:placetype": "postalcode"
  },
  "geometry": {"coordinates":[0.568139,51.952633],"type":"Point"}
}
