{
  "type": "Feature",
  "properties": {
    "date:inception_lower":"1993-08-01",
    "date:inception_upper":"1993-08-31",
    "iso:country":"GB",
    "wof:name":"CO9 1SB",
    "wof:placetype":"postalcode"
},
  "geometry": {"coordinates":[0.568139,51.952633],"type":"Point"}
}