{
  "type": "Feature",
  "properties": {
    "iso:country":"GB",
    "wof:name":"CO9 1SB",
    "wof:placetype":"postalcode"
},
  "geometry": {"coordinates":[0.56813883464964,51.95263298732878],"type":"Point"}
}