{
  "type": "Feature",
  "properties": {
    "iso:country":"GB",
    "wof:name":"BN24 5AR",
    "wof:placetype":"postalcode"
},
  "geometry": {"coordinates":[0.29159673581928,50.81948571845253],"type":"Point"}
}