{
  "type": "Feature",
  "properties": {
    "iso:country":"GB",
    "wof:name":"CW9 7NB",
    "wof:placetype":"postalcode"
},
  "geometry": {"coordinates":[-2.48166888877789,53.26660887694423],"type":"Point"}
}