{
  "type": "Feature",
  "properties": {
    "iso:country": "GB",
    "wof:name": "CA14 4UJ",
    "wof:placetype": "postalcode"
  },
  "geometry": {"coordinates":[-3.521844,54.643735],"type":"Point"}
}
