{
  "type": "Feature",
  "properties": {
    "iso:country":"GB",
    "wof:name":"CM3 6ED",
    "wof:placetype":"postalcode"
},
  "geometry": {"coordinates":[0.78249020458182,51.66028294641915],"type":"Point"}
}