{
  "type": "Feature",
  "properties": {
    "iso:country": "GB",
    "wof:name": "BS32 9AE",
    "wof:placetype": "postalcode"
  },
  "geometry": {"coordinates":[-2.564235,51.54254],"type":"Point"}
}
