{
  "type": "Feature",
  "properties": {
    "iso:country":"GB",
    "wof:name":"BS32 9AE",
    "wof:placetype":"postalcode"
},
  "geometry": {"coordinates":[-2.56423522984886,51.54254017411149],"type":"Point"}
}