{
  "type": "Feature",
  "properties": {
    "iso:country":"GB",
    "wof:name":"DT6 4DE",
    "wof:placetype":"postalcode"
},
  "geometry": {"coordinates":[-2.7483542549951,50.73161949906235],"type":"Point"}
}