{
  "type": "Feature",
  "properties": {
    "date:inception_lower": "2023-10-01",
    "date:inception_upper": "2023-10-01",
    "iso:country": "GB",
    "wof:name": "NG9 1EB",
    "wof:placetype": "postalcode"
  },
  "geometry": {"coordinates":[-1.219834,52.922516],"type":"Point"}
}
