{
  "type": "Feature",
  "properties": {
    "date:inception_lower": "1980-01-01",
    "date:inception_upper": "1980-01-01",
    "iso:country": "GB",
    "wof:name": "LN9 6AP",
    "wof:placetype": "postalcode"
  },
  "geometry": {"coordinates":[-0.11174,53.208554],"type":"Point"}
}
