{
  "type": "Feature",
  "properties": {
    "iso:country": "GB",
    "wof:name": "LN9 6AP",
    "wof:placetype": "postalcode"
  },
  "geometry": {"coordinates":[-0.11174,53.208554],"type":"Point"}
}
