{
  "type": "Feature",
  "properties": {
    "date:inception_lower": "1980-01-01",
    "date:inception_upper": "1980-01-01",
    "iso:country": "GB",
    "wof:name": "S5 7NA",
    "wof:placetype": "postalcode"
  },
  "geometry": {"coordinates":[-1.472008,53.414181],"type":"Point"}
}
