{
  "type": "Feature",
  "properties": {
    "iso:country":"GB",
    "wof:name":"CO10 9QD",
    "wof:placetype":"postalcode"
},
  "geometry": {"coordinates":[0.79957001888406,52.11289332469546],"type":"Point"}
}