{
  "type": "Feature",
  "properties": {
    "iso:country":"GB",
    "wof:name":"GU34 1AF",
    "wof:placetype":"postalcode"
},
  "geometry": {"coordinates":[-0.97682869184673,51.14777388217126],"type":"Point"}
}