{
  "type": "Feature",
  "properties": {
    "date:inception_lower": "1980-01-01",
    "date:inception_upper": "1980-01-01",
    "iso:country": "GB",
    "wof:name": "PH16 5RU",
    "wof:placetype": "postalcode"
  },
  "geometry": {"coordinates":[-3.944049,56.714387],"type":"Point"}
}
