{
  "type": "Feature",
  "properties": {
    "iso:country": "GB",
    "wof:name": "WA6 0NU",
    "wof:placetype": "postalcode"
  },
  "geometry": {"coordinates":[-2.798489,53.243295],"type":"Point"}
}
