{
  "type": "Feature",
  "properties": {
    "iso:country":"GB",
    "wof:name":"WA6 0NU",
    "wof:placetype":"postalcode"
},
  "geometry": {"coordinates":[-2.7985468843411,53.24312669921272],"type":"Point"}
}