{
  "type": "Feature",
  "properties": {
    "iso:country": "GB",
    "wof:name": "CW9 8DE",
    "wof:placetype": "postalcode"
  },
  "geometry": {"coordinates":[-2.506408,53.242533],"type":"Point"}
}
