{
  "type": "Feature",
  "properties": {
    "iso:country":"GB",
    "wof:name":"CW9 8DE",
    "wof:placetype":"postalcode"
},
  "geometry": {"coordinates":[-2.50640775031212,53.24253299155554],"type":"Point"}
}