{
  "type": "Feature",
  "properties": {
    "iso:country":"GB",
    "wof:name":"CF23 9PG",
    "wof:placetype":"postalcode"
},
  "geometry": {"coordinates":[-3.14846857742085,51.51367306374966],"type":"Point"}
}