{
  "type": "Feature",
  "properties": {
    "iso:country":"GB",
    "wof:name":"IP22 2BB",
    "wof:placetype":"postalcode"
},
  "geometry": {"coordinates":[1.07234284102906,52.39567923509768],"type":"Point"}
}