{
  "type": "Feature",
  "properties": {
    "iso:country":"GB",
    "wof:name":"WF12 9QS",
    "wof:placetype":"postalcode"
},
  "geometry": {"coordinates":[-1.6353247636386,53.68776827688737],"type":"Point"}
}