{
  "type": "Feature",
  "properties": {
    "date:inception_lower": "1986-04-01",
    "date:inception_upper": "1986-04-01",
    "iso:country": "GB",
    "wof:name": "WF12 9QS",
    "wof:placetype": "postalcode"
  },
  "geometry": {"coordinates":[-1.635328,53.687783],"type":"Point"}
}
