{
  "type": "Feature",
  "properties": {
    "iso:country":"GB",
    "wof:name":"LS23 6EY",
    "wof:placetype":"postalcode"
},
  "geometry": {"coordinates":[-1.34852053408956,53.89222806370163],"type":"Point"}
}