{
  "type": "Feature",
  "properties": {
    "iso:country":"GB",
    "wof:name":"PH1 2SE",
    "wof:placetype":"postalcode"
},
  "geometry": {"coordinates":[-3.4593725500985,56.40966237298588],"type":"Point"}
}