{
  "type": "Feature",
  "properties": {
    "date:inception_lower": "1998-12-01",
    "date:inception_upper": "1998-12-01",
    "iso:country": "GB",
    "wof:name": "PH1 2SE",
    "wof:placetype": "postalcode"
  },
  "geometry": {"coordinates":[-3.459372,56.409662],"type":"Point"}
}
