{
  "type": "Feature",
  "properties": {
    "date:inception_lower": "2017-07-01",
    "date:inception_upper": "2017-07-01",
    "iso:country": "GB",
    "wof:name": "WV15 6LZ",
    "wof:placetype": "postalcode"
  },
  "geometry": {"coordinates":[-2.343861,52.460768],"type":"Point"}
}
