{
  "type": "Feature",
  "properties": {
    "date:inception_lower": "2023-10-01",
    "date:inception_upper": "2023-10-01",
    "iso:country": "GB",
    "wof:name": "CB21 4AU",
    "wof:placetype": "postalcode"
  },
  "geometry": {"coordinates":[0.292658,52.09447],"type":"Point"}
}
