{
  "type": "Feature",
  "properties": {
    "iso:country":"GB",
    "wof:name":"NG11 6BH",
    "wof:placetype":"postalcode"
},
  "geometry": {"coordinates":[-1.15091231425146,52.89732106955866],"type":"Point"}
}