{
  "type": "Feature",
  "properties": {
    "date:inception_lower": "1980-01-01",
    "date:inception_upper": "1980-01-01",
    "iso:country": "GB",
    "wof:name": "NG11 6BH",
    "wof:placetype": "postalcode"
  },
  "geometry": {"coordinates":[-1.150912,52.897321],"type":"Point"}
}
