{
  "type": "Feature",
  "properties": {
    "date:inception_lower":"1980-01-01",
    "date:inception_upper":"1980-01-31",
    "iso:country":"GB",
    "wof:name":"RM4 1SJ",
    "wof:placetype":"postalcode"
},
  "geometry": {"coordinates":[0.154581,51.657042],"type":"Point"}
}