{
  "type": "Feature",
  "properties": {
    "iso:country": "GB",
    "wof:name": "RM4 1SJ",
    "wof:placetype": "postalcode"
  },
  "geometry": {"coordinates":[0.154581,51.657042],"type":"Point"}
}
