{
  "type": "Feature",
  "properties": {
    "iso:country":"GB",
    "wof:name":"RM4 1SJ",
    "wof:placetype":"postalcode"
},
  "geometry": {"coordinates":[0.15443714734884,51.65700476993395],"type":"Point"}
}