{
  "type": "Feature",
  "properties": {
    "iso:country":"GB",
    "wof:name":"SW17 0RJ",
    "wof:placetype":"postalcode"
},
  "geometry": {"coordinates":[-0.16656259176443,51.42867034331096],"type":"Point"}
}