{
  "type": "Feature",
  "properties": {
    "iso:country":"GB",
    "wof:name":"DL15 9QL",
    "wof:placetype":"postalcode"
},
  "geometry": {"coordinates":[-1.76825006069503,54.73127067380583],"type":"Point"}
}