{
  "type": "Feature",
  "properties": {
    "iso:country":"GB",
    "wof:name":"GL51 6GL",
    "wof:placetype":"postalcode"
},
  "geometry": {"coordinates":[-2.12727065229021,51.8852132458855],"type":"Point"}
}