{
  "type": "Feature",
  "properties": {
    "date:inception_lower": "2012-04-01",
    "date:inception_upper": "2012-04-01",
    "iso:country": "GB",
    "wof:name": "GL51 6GL",
    "wof:placetype": "postalcode"
  },
  "geometry": {"coordinates":[-2.127271,51.885213],"type":"Point"}
}
