{
  "type": "Feature",
  "properties": {
    "date:inception_lower": "1980-01-01",
    "date:inception_upper": "1980-01-01",
    "iso:country": "GB",
    "wof:name": "CW4 7EE",
    "wof:placetype": "postalcode"
  },
  "geometry": {"coordinates":[-2.360727,53.203314],"type":"Point"}
}
