{
  "type": "Feature",
  "properties": {
    "iso:country":"GB",
    "wof:name":"CH63 1JW",
    "wof:placetype":"postalcode"
},
  "geometry": {"coordinates":[-3.04422184018711,53.32090717739464],"type":"Point"}
}