{
  "type": "Feature",
  "properties": {
    "iso:country":"GB",
    "wof:name":"SY3 9QW",
    "wof:placetype":"postalcode"
},
  "geometry": {"coordinates":[-2.76938097691569,52.68622498580343],"type":"Point"}
}