{
  "type": "Feature",
  "properties": {
    "iso:country":"GB",
    "wof:name":"OL8 1LU",
    "wof:placetype":"postalcode"
},
  "geometry": {"coordinates":[-2.10602967418781,53.53000141448551],"type":"Point"}
}