{
  "type": "Feature",
  "properties": {
    "iso:country":"GB",
    "wof:name":"GU14 6DT",
    "wof:placetype":"postalcode"
},
  "geometry": {"coordinates":[-0.7470507249152,51.27700695849649],"type":"Point"}
}