{
  "type": "Feature",
  "properties": {
    "date:inception_lower": "1992-08-01",
    "date:inception_upper": "1992-08-01",
    "iso:country": "GB",
    "wof:name": "SN14 8RA",
    "wof:placetype": "postalcode"
  },
  "geometry": {"coordinates":[-2.312242,51.463287],"type":"Point"}
}
