{
  "type": "Feature",
  "properties": {
    "date:inception_lower": "2023-06-01",
    "date:inception_upper": "2023-06-01",
    "iso:country": "GB",
    "wof:name": "BD16 2BJ",
    "wof:placetype": "postalcode"
  },
  "geometry": {"coordinates":[-1.84241,53.854566],"type":"Point"}
}
