{
  "type": "Feature",
  "properties": {
    "iso:country":"GB",
    "wof:name":"MK14 6GF",
    "wof:placetype":"postalcode"
},
  "geometry": {"coordinates":[-0.76959036635683,52.07278402765919],"type":"Point"}
}