{
  "type": "Feature",
  "properties": {
    "iso:country": "GB",
    "wof:name": "LE4 0FD",
    "wof:placetype": "postalcode"
  },
  "geometry": {"coordinates":[-1.155537,52.648976],"type":"Point"}
}
