{
  "type": "Feature",
  "properties": {
    "iso:country":"GB",
    "wof:name":"LE4 0FD",
    "wof:placetype":"postalcode"
},
  "geometry": {"coordinates":[-1.15553729760921,52.64897565613744],"type":"Point"}
}