{
  "type": "Feature",
  "properties": {
    "iso:country":"GB",
    "wof:name":"WF3 1EE",
    "wof:placetype":"postalcode"
},
  "geometry": {"coordinates":[-1.56759987757359,53.72116785281904],"type":"Point"}
}