{
  "type": "Feature",
  "properties": {
    "iso:country": "GB",
    "wof:name": "WF3 1EE",
    "wof:placetype": "postalcode"
  },
  "geometry": {"coordinates":[-1.5676,53.721168],"type":"Point"}
}
