{
  "type": "Feature",
  "properties": {
    "date:inception_lower": "1980-01-01",
    "date:inception_upper": "1980-01-01",
    "iso:country": "GB",
    "wof:name": "DL8 5ET",
    "wof:placetype": "postalcode"
  },
  "geometry": {"coordinates":[-1.822025,54.308007],"type":"Point"}
}
