{
  "type": "Feature",
  "properties": {
    "iso:country":"GB",
    "wof:name":"LS22 6LX",
    "wof:placetype":"postalcode"
},
  "geometry": {"coordinates":[-1.38493678823029,53.92720341507592],"type":"Point"}
}