{
  "type": "Feature",
  "properties": {
    "date:inception_lower": "1993-01-01",
    "date:inception_upper": "1993-01-01",
    "iso:country": "GB",
    "wof:name": "LS22 6LX",
    "wof:placetype": "postalcode"
  },
  "geometry": {"coordinates":[-1.384937,53.927203],"type":"Point"}
}
