{
  "type": "Feature",
  "properties": {
    "iso:country": "GB",
    "wof:name": "RM11 2DW",
    "wof:placetype": "postalcode"
  },
  "geometry": {"coordinates":[0.217195,51.57011],"type":"Point"}
}
