{
  "type": "Feature",
  "properties": {
    "iso:country":"GB",
    "wof:name":"OX16 0UY",
    "wof:placetype":"postalcode"
},
  "geometry": {"coordinates":[-1.36653637903558,52.06657884819656],"type":"Point"}
}