{
  "type": "Feature",
  "properties": {
    "iso:country":"GB",
    "wof:name":"HD3 3GA",
    "wof:placetype":"postalcode"
},
  "geometry": {"coordinates":[-1.876492989964,53.65689951967053],"type":"Point"}
}