{
  "type": "Feature",
  "properties": {
    "iso:country": "GB",
    "wof:name": "NN13 5NN",
    "wof:placetype": "postalcode"
  },
  "geometry": {"coordinates":[-1.185023,52.02861],"type":"Point"}
}
