{
  "type": "Feature",
  "properties": {
    "iso:country":"GB",
    "wof:name":"NN13 5NN",
    "wof:placetype":"postalcode"
},
  "geometry": {"coordinates":[-1.18502261799328,52.02861045666834],"type":"Point"}
}