{
  "type": "Feature",
  "properties": {
    "date:inception_lower": "1983-01-01",
    "date:inception_upper": "1983-01-01",
    "iso:country": "GB",
    "wof:name": "NN13 5NN",
    "wof:placetype": "postalcode"
  },
  "geometry": {"coordinates":[-1.185023,52.02861],"type":"Point"}
}
