{
  "type": "Feature",
  "properties": {
    "iso:country":"GB",
    "wof:name":"CR0 7PY",
    "wof:placetype":"postalcode"
},
  "geometry": {"coordinates":[-0.04548152143775,51.38176787994383],"type":"Point"}
}