{
  "type": "Feature",
  "properties": {
    "iso:country":"GB",
    "wof:name":"SK7 6LJ",
    "wof:placetype":"postalcode"
},
  "geometry": {"coordinates":[-2.1194263016199,53.37483854832373],"type":"Point"}
}