{
  "type": "Feature",
  "properties": {
    "iso:country":"GB",
    "wof:name":"TN8 6DB",
    "wof:placetype":"postalcode"
},
  "geometry": {"coordinates":[0.06974669758066,51.20640268663952],"type":"Point"}
}