{
  "type": "Feature",
  "properties": {
    "iso:country": "GB",
    "wof:name": "TN8 6DB",
    "wof:placetype": "postalcode"
  },
  "geometry": {"coordinates":[0.069747,51.206403],"type":"Point"}
}
