{
  "type": "Feature",
  "properties": {
    "iso:country":"GB",
    "wof:name":"N15 5RG",
    "wof:placetype":"postalcode"
},
  "geometry": {"coordinates":[-0.0837594734591,51.58049854169039],"type":"Point"}
}