{
  "type": "Feature",
  "properties": {
    "iso:country":"GB",
    "wof:name":"HG3 2WE",
    "wof:placetype":"postalcode"
},
  "geometry": {"coordinates":[-1.57656747866853,54.00331308294246],"type":"Point"}
}