{
  "type": "Feature",
  "properties": {
    "iso:country": "GB",
    "wof:name": "HG3 2WE",
    "wof:placetype": "postalcode"
  },
  "geometry": {"coordinates":[-1.576567,54.003313],"type":"Point"}
}
