{
  "type": "Feature",
  "properties": {
    "iso:country":"GB",
    "wof:name":"TD1 3JE",
    "wof:placetype":"postalcode"
},
  "geometry": {"coordinates":[-2.78616307415382,55.60402669187058],"type":"Point"}
}