{
  "type": "Feature",
  "properties": {
    "date:inception_lower": "1980-07-01",
    "date:inception_upper": "1980-07-01",
    "iso:country": "GB",
    "wof:name": "TD1 3JE",
    "wof:placetype": "postalcode"
  },
  "geometry": {"coordinates":[-2.785993,55.604081],"type":"Point"}
}
