{
  "type": "Feature",
  "properties": {
    "iso:country": "GB",
    "wof:name": "TD1 3JE",
    "wof:placetype": "postalcode"
  },
  "geometry": {"coordinates":[-2.786163,55.604027],"type":"Point"}
}
