{
  "type": "Feature",
  "properties": {
    "iso:country": "GB",
    "wof:name": "BS11 0BL",
    "wof:placetype": "postalcode"
  },
  "geometry": {"coordinates":[-2.676786,51.491313],"type":"Point"}
}
