{
  "type": "Feature",
  "properties": {
    "iso:country":"GB",
    "wof:name":"GL3 3PG",
    "wof:placetype":"postalcode"
},
  "geometry": {"coordinates":[-2.18618817473879,51.85772138361964],"type":"Point"}
}