{
  "type": "Feature",
  "properties": {
    "date:inception_lower": "1980-01-01",
    "date:inception_upper": "1980-01-01",
    "iso:country": "GB",
    "wof:name": "GL3 3PG",
    "wof:placetype": "postalcode"
  },
  "geometry": {"coordinates":[-2.186188,51.857721],"type":"Point"}
}
