{
  "type": "Feature",
  "properties": {
    "iso:country":"GB",
    "wof:name":"WR15 8RR",
    "wof:placetype":"postalcode"
},
  "geometry": {"coordinates":[-2.54416281149342,52.26511985562904],"type":"Point"}
}