{
  "type": "Feature",
  "properties": {
    "iso:country": "GB",
    "wof:name": "WR15 8RR",
    "wof:placetype": "postalcode"
  },
  "geometry": {"coordinates":[-2.544163,52.26512],"type":"Point"}
}
