{
  "type": "Feature",
  "properties": {
    "iso:country":"GB",
    "wof:name":"KW1 5HG",
    "wof:placetype":"postalcode"
},
  "geometry": {"coordinates":[-3.08210468896102,58.43638419955663],"type":"Point"}
}