{
  "type": "Feature",
  "properties": {
    "iso:country": "GB",
    "wof:name": "KW1 5HG",
    "wof:placetype": "postalcode"
  },
  "geometry": {"coordinates":[-3.082105,58.436384],"type":"Point"}
}
