{
  "type": "Feature",
  "properties": {
    "iso:country":"GB",
    "wof:name":"NP7 0NE",
    "wof:placetype":"postalcode"
},
  "geometry": {"coordinates":[-3.11931946639155,51.80950008508774],"type":"Point"}
}