{
  "type": "Feature",
  "properties": {
    "date:inception_lower": "1980-01-01",
    "date:inception_upper": "1980-01-01",
    "iso:country": "GB",
    "wof:name": "NP7 0NE",
    "wof:placetype": "postalcode"
  },
  "geometry": {"coordinates":[-3.119319,51.8095],"type":"Point"}
}
