{
  "type": "Feature",
  "properties": {
    "iso:country":"GB",
    "wof:name":"RH1 2HP",
    "wof:placetype":"postalcode"
},
  "geometry": {"coordinates":[-0.16058190614018,51.24853327298986],"type":"Point"}
}