{
  "type": "Feature",
  "properties": {
    "date:inception_lower": "1980-01-01",
    "date:inception_upper": "1980-01-01",
    "iso:country": "GB",
    "wof:name": "RH1 2HP",
    "wof:placetype": "postalcode"
  },
  "geometry": {"coordinates":[-0.160582,51.248533],"type":"Point"}
}
