{
  "type": "Feature",
  "properties": {
    "date:inception_lower":"1980-01-01",
    "date:inception_upper":"1980-01-31",
    "iso:country":"GB",
    "wof:name":"BD23 5QA",
    "wof:placetype":"postalcode"
},
  "geometry": {"coordinates":[-2.07036,54.131292],"type":"Point"}
}