{
  "type": "Feature",
  "properties": {
    "iso:country": "GB",
    "wof:name": "BD23 5QA",
    "wof:placetype": "postalcode"
  },
  "geometry": {"coordinates":[-2.070471,54.131368],"type":"Point"}
}
