{
  "type": "Feature",
  "properties": {
    "date:inception_lower": "1980-01-01",
    "date:inception_upper": "1980-01-01",
    "iso:country": "GB",
    "wof:name": "BD23 5QA",
    "wof:placetype": "postalcode"
  },
  "geometry": {"coordinates":[-2.070471,54.131368],"type":"Point"}
}
