{
  "type": "Feature",
  "properties": {
    "iso:country": "GB",
    "wof:name": "BD23 5QA",
    "wof:placetype": "postalcode"
  },
  "geometry": {"coordinates":[-2.07036,54.131292],"type":"Point"}
}
