{
  "type": "Feature",
  "properties": {
    "iso:country":"GB",
    "wof:name":"DE5 3SD",
    "wof:placetype":"postalcode"
},
  "geometry": {"coordinates":[-1.41228691623426,53.05471321024208],"type":"Point"}
}