{
  "type": "Feature",
  "properties": {
    "iso:country":"GB",
    "wof:name":"HX6 4JQ",
    "wof:placetype":"postalcode"
},
  "geometry": {"coordinates":[-1.95283236807482,53.66758674931852],"type":"Point"}
}