{
  "type": "Feature",
  "properties": {
    "iso:country": "GB",
    "wof:name": "HX6 4JQ",
    "wof:placetype": "postalcode"
  },
  "geometry": {"coordinates":[-1.952832,53.667587],"type":"Point"}
}
