{
  "type": "Feature",
  "properties": {
    "iso:country":"GB",
    "wof:name":"RG4 6GG",
    "wof:placetype":"postalcode"
},
  "geometry": {"coordinates":[-0.90261697895466,51.46530549132054],"type":"Point"}
}