{
  "type": "Feature",
  "properties": {
    "iso:country": "GB",
    "wof:name": "BB11 3HG",
    "wof:placetype": "postalcode"
  },
  "geometry": {"coordinates":[-2.231881,53.781762],"type":"Point"}
}
