{
  "type": "Feature",
  "properties": {
    "iso:country": "GB",
    "wof:name": "KT13 9AU",
    "wof:placetype": "postalcode"
  },
  "geometry": {"coordinates":[-0.4497,51.366717],"type":"Point"}
}
