{
  "type": "Feature",
  "properties": {
    "iso:country":"GB",
    "wof:name":"BR6 9PT",
    "wof:placetype":"postalcode"
},
  "geometry": {"coordinates":[0.08125010177361,51.36611356560749],"type":"Point"}
}