{
  "type": "Feature",
  "properties": {
    "iso:country":"GB",
    "wof:name":"YO10 3AP",
    "wof:placetype":"postalcode"
},
  "geometry": {"coordinates":[-1.04881117955176,53.95621915526444],"type":"Point"}
}