{
  "type": "Feature",
  "properties": {
    "iso:country":"GB",
    "wof:name":"OL6 7AW",
    "wof:placetype":"postalcode"
},
  "geometry": {"coordinates":[-2.09775676053845,53.48823041989348],"type":"Point"}
}