{
  "type": "Feature",
  "properties": {
    "iso:country":"GB",
    "wof:name":"W1T 5DU",
    "wof:placetype":"postalcode"
},
  "geometry": {"coordinates":[-0.13876292072971,51.52330153660746],"type":"Point"}
}