{
  "type": "Feature",
  "properties": {
    "date:inception_lower": "1993-01-01",
    "date:inception_upper": "1993-01-01",
    "iso:country": "GB",
    "wof:name": "NR34 7ES",
    "wof:placetype": "postalcode"
  },
  "geometry": {"coordinates":[1.587377,52.447761],"type":"Point"}
}
