{
  "type": "Feature",
  "properties": {
    "iso:country": "GB",
    "wof:name": "NR34 7ES",
    "wof:placetype": "postalcode"
  },
  "geometry": {"coordinates":[1.587377,52.447761],"type":"Point"}
}
