{
  "type": "Feature",
  "properties": {
    "date:inception_lower": "1992-08-01",
    "date:inception_upper": "1992-08-01",
    "iso:country": "GB",
    "wof:name": "ST1 5QF",
    "wof:placetype": "postalcode"
  },
  "geometry": {"coordinates":[-2.186841,53.027862],"type":"Point"}
}
