{
  "type": "Feature",
  "properties": {
    "iso:country":"GB",
    "wof:name":"NR33 0NF",
    "wof:placetype":"postalcode"
},
  "geometry": {"coordinates":[1.7343390379307,52.4629056134021],"type":"Point"}
}