{
  "type": "Feature",
  "properties": {
    "iso:country": "GB",
    "wof:name": "IP28 7NJ",
    "wof:placetype": "postalcode"
  },
  "geometry": {"coordinates":[0.517732,52.34633],"type":"Point"}
}
