{
  "type": "Feature",
  "properties": {
    "iso:country": "GB",
    "wof:name": "BD4 8HT",
    "wof:placetype": "postalcode"
  },
  "geometry": {"coordinates":[-1.707066,53.790699],"type":"Point"}
}
