{
  "type": "Feature",
  "properties": {
    "iso:country":"GB",
    "wof:name":"LL77 7UD",
    "wof:placetype":"postalcode"
},
  "geometry": {"coordinates":[-4.28852132053759,53.27907324102122],"type":"Point"}
}