{
  "type": "Feature",
  "properties": {
    "date:inception_lower": "2000-06-01",
    "date:inception_upper": "2000-06-01",
    "iso:country": "GB",
    "wof:name": "LL77 7UD",
    "wof:placetype": "postalcode"
  },
  "geometry": {"coordinates":[-4.288521,53.279073],"type":"Point"}
}
