{
  "type": "Feature",
  "properties": {
    "iso:country":"GB",
    "wof:name":"SG6 4SE",
    "wof:placetype":"postalcode"
},
  "geometry": {"coordinates":[-0.23308300677321,51.98985666050354],"type":"Point"}
}