{
  "type": "Feature",
  "properties": {
    "iso:country": "GB",
    "wof:name": "WS14 9JG",
    "wof:placetype": "postalcode"
  },
  "geometry": {"coordinates":[-1.797744,52.675596],"type":"Point"}
}
