{
  "type": "Feature",
  "properties": {
    "iso:country":"GB",
    "wof:name":"WS14 9JG",
    "wof:placetype":"postalcode"
},
  "geometry": {"coordinates":[-1.79775139325393,52.67557919633741],"type":"Point"}
}