{
  "type": "Feature",
  "properties": {
    "iso:country":"GB",
    "wof:name":"LL13 7DG",
    "wof:placetype":"postalcode"
},
  "geometry": {"coordinates":[-2.99479503425371,53.0420330784946],"type":"Point"}
}