{
  "type": "Feature",
  "properties": {
    "date:inception_lower": "1980-01-01",
    "date:inception_upper": "1980-01-01",
    "iso:country": "GB",
    "wof:name": "DD11 5AE",
    "wof:placetype": "postalcode"
  },
  "geometry": {"coordinates":[-2.573981,56.566111],"type":"Point"}
}
