{
  "type": "Feature",
  "properties": {
    "iso:country":"GB",
    "wof:name":"DD11 5AE",
    "wof:placetype":"postalcode"
},
  "geometry": {"coordinates":[-2.57398102221402,56.56611076040046],"type":"Point"}
}