{
  "type": "Feature",
  "properties": {
    "iso:country":"GB",
    "wof:name":"CH1 6HN",
    "wof:placetype":"postalcode"
},
  "geometry": {"coordinates":[-2.95424440385283,53.258674516959],"type":"Point"}
}