{
  "type": "Feature",
  "properties": {
    "iso:country": "GB",
    "wof:name": "PL31 2GP",
    "wof:placetype": "postalcode"
  },
  "geometry": {"coordinates":[-4.706518,50.464707],"type":"Point"}
}
