{
  "type": "Feature",
  "properties": {
    "iso:country":"GB",
    "wof:name":"PL31 2GP",
    "wof:placetype":"postalcode"
},
  "geometry": {"coordinates":[-4.70651754784133,50.46470651018343],"type":"Point"}
}