{
  "type": "Feature",
  "properties": {
    "date:inception_lower": "2014-01-01",
    "date:inception_upper": "2014-01-01",
    "iso:country": "GB",
    "wof:name": "CF23 9FJ",
    "wof:placetype": "postalcode"
  },
  "geometry": {"coordinates":[-3.147853,51.49664],"type":"Point"}
}
