{
  "type": "Feature",
  "properties": {
    "iso:country": "GB",
    "wof:name": "CF23 9FJ",
    "wof:placetype": "postalcode"
  },
  "geometry": {"coordinates":[-3.147853,51.49664],"type":"Point"}
}
