{
  "type": "Feature",
  "properties": {
    "iso:country": "GB",
    "wof:name": "SN2 7LW",
    "wof:placetype": "postalcode"
  },
  "geometry": {"coordinates":[-1.763602,51.589534],"type":"Point"}
}
