{
  "type": "Feature",
  "properties": {
    "iso:country": "GB",
    "wof:name": "CV5 9GT",
    "wof:placetype": "postalcode"
  },
  "geometry": {"coordinates":[-1.560931,52.423266],"type":"Point"}
}
