{
  "type": "Feature",
  "properties": {
    "iso:country":"GB",
    "wof:name":"DG11 3JU",
    "wof:placetype":"postalcode"
},
  "geometry": {"coordinates":[-3.21828781178678,55.06513091799572],"type":"Point"}
}