{
  "type": "Feature",
  "properties": {
    "iso:country":"GB",
    "wof:name":"WS5 3HW",
    "wof:placetype":"postalcode"
},
  "geometry": {"coordinates":[-1.94930574105695,52.56971555631911],"type":"Point"}
}