{
  "type": "Feature",
  "properties": {
    "iso:country":"GB",
    "wof:name":"HP19 9DZ",
    "wof:placetype":"postalcode"
},
  "geometry": {"coordinates":[-0.8204737964601,51.83516268399228],"type":"Point"}
}