{
  "type": "Feature",
  "properties": {
    "date:inception_lower": "2012-07-01",
    "date:inception_upper": "2012-07-01",
    "iso:country": "GB",
    "wof:name": "HP19 9DZ",
    "wof:placetype": "postalcode"
  },
  "geometry": {"coordinates":[-0.820474,51.835163],"type":"Point"}
}
