{
  "type": "Feature",
  "properties": {
    "iso:country":"GB",
    "wof:name":"NP7 0BD",
    "wof:placetype":"postalcode"
},
  "geometry": {"coordinates":[-3.09178661472231,51.8310235556933],"type":"Point"}
}