{
  "type": "Feature",
  "properties": {
    "date:inception_lower": "1980-01-01",
    "date:inception_upper": "1980-01-01",
    "iso:country": "GB",
    "wof:name": "NP7 0BD",
    "wof:placetype": "postalcode"
  },
  "geometry": {"coordinates":[-3.091765,51.831038],"type":"Point"}
}
