{
  "type": "Feature",
  "properties": {
    "date:inception_lower": "1996-06-01",
    "date:inception_upper": "1996-06-01",
    "iso:country": "GB",
    "wof:name": "AB56 1SE",
    "wof:placetype": "postalcode"
  },
  "geometry": {"coordinates":[-2.948715,57.682932],"type":"Point"}
}
