{
  "type": "Feature",
  "properties": {
    "iso:country":"GB",
    "wof:name":"AB56 1SE",
    "wof:placetype":"postalcode"
},
  "geometry": {"coordinates":[-2.9487151182142,57.6829322702507],"type":"Point"}
}