{
  "type": "Feature",
  "properties": {
    "iso:country":"GB",
    "wof:name":"TW1 4QJ",
    "wof:placetype":"postalcode"
},
  "geometry": {"coordinates":[-0.33064260434971,51.44320779047473],"type":"Point"}
}