{
  "type": "Feature",
  "properties": {
    "iso:country": "GB",
    "wof:name": "EX17 5AU",
    "wof:placetype": "postalcode"
  },
  "geometry": {"coordinates":[-3.836044,50.754582],"type":"Point"}
}
