{
  "type": "Feature",
  "properties": {
    "iso:country":"GB",
    "wof:name":"EX17 5AU",
    "wof:placetype":"postalcode"
},
  "geometry": {"coordinates":[-3.83604427752766,50.75458191217557],"type":"Point"}
}