{
  "type": "Feature",
  "properties": {
    "iso:country":"GB",
    "wof:name":"NW3 1HU",
    "wof:placetype":"postalcode"
},
  "geometry": {"coordinates":[-0.17653702418457,51.55813799441655],"type":"Point"}
}