{
  "type": "Feature",
  "properties": {
    "iso:country": "GB",
    "wof:name": "SO31 1DG",
    "wof:placetype": "postalcode"
  },
  "geometry": {"coordinates":[-1.262778,50.87323],"type":"Point"}
}
