{
  "type": "Feature",
  "properties": {
    "date:inception_lower": "1997-12-01",
    "date:inception_upper": "1997-12-01",
    "iso:country": "GB",
    "wof:name": "SO31 1DG",
    "wof:placetype": "postalcode"
  },
  "geometry": {"coordinates":[-1.262778,50.87323],"type":"Point"}
}
