{
  "type": "Feature",
  "properties": {
    "date:inception_lower": "1995-07-01",
    "date:inception_upper": "1995-07-01",
    "iso:country": "GB",
    "wof:name": "CT13 9FZ",
    "wof:placetype": "postalcode"
  },
  "geometry": {"coordinates":[1.33684,51.276137],"type":"Point"}
}
