{
  "type": "Feature",
  "properties": {
    "iso:country":"GB",
    "wof:name":"ML4 2UP",
    "wof:placetype":"postalcode"
},
  "geometry": {"coordinates":[-4.03655002204159,55.80850500718124],"type":"Point"}
}