{
  "type": "Feature",
  "properties": {
    "iso:country": "GB",
    "wof:name": "CR3 0EF",
    "wof:placetype": "postalcode"
  },
  "geometry": {"coordinates":[-0.079968,51.308012],"type":"Point"}
}
