{
  "type": "Feature",
  "properties": {
    "iso:country":"GB",
    "wof:name":"LS17 7RQ",
    "wof:placetype":"postalcode"
},
  "geometry": {"coordinates":[-1.55078694924456,53.8582906579899],"type":"Point"}
}