{
  "type": "Feature",
  "properties": {
    "date:inception_lower": "1980-01-01",
    "date:inception_upper": "1980-01-01",
    "iso:country": "GB",
    "wof:name": "LS17 7RQ",
    "wof:placetype": "postalcode"
  },
  "geometry": {"coordinates":[-1.550787,53.858291],"type":"Point"}
}
