{
  "type": "Feature",
  "properties": {
    "date:inception_lower": "1980-01-01",
    "date:inception_upper": "1980-01-01",
    "iso:country": "GB",
    "wof:name": "FY7 7BL",
    "wof:placetype": "postalcode"
  },
  "geometry": {"coordinates":[-3.024755,53.921392],"type":"Point"}
}
