{
  "type": "Feature",
  "properties": {
    "iso:country": "GB",
    "wof:name": "ST17 4SU",
    "wof:placetype": "postalcode"
  },
  "geometry": {"coordinates":[-2.102331,52.794909],"type":"Point"}
}
