{
  "type": "Feature",
  "properties": {
    "date:inception_lower": "1992-08-01",
    "date:inception_upper": "1992-08-01",
    "iso:country": "GB",
    "wof:name": "ST17 4SU",
    "wof:placetype": "postalcode"
  },
  "geometry": {"coordinates":[-2.102331,52.794909],"type":"Point"}
}
