{
  "type": "Feature",
  "properties": {
    "iso:country": "GB",
    "wof:name": "MK45 1TP",
    "wof:placetype": "postalcode"
  },
  "geometry": {"coordinates":[-0.507533,52.000748],"type":"Point"}
}
