{
  "type": "Feature",
  "properties": {
    "date:inception_lower": "2024-01-01",
    "date:inception_upper": "2024-01-01",
    "iso:country": "GB",
    "wof:name": "M15 4ZX",
    "wof:placetype": "postalcode"
  },
  "geometry": {"coordinates":[-2.261297,53.467148],"type":"Point"}
}
