{
  "type": "Feature",
  "properties": {
    "iso:country":"GB",
    "wof:name":"LS28 5UE",
    "wof:placetype":"postalcode"
},
  "geometry": {"coordinates":[-1.69631205199464,53.82950909428725],"type":"Point"}
}