{
  "type": "Feature",
  "properties": {
    "iso:country":"GB",
    "wof:name":"E6 6AQ",
    "wof:placetype":"postalcode"
},
  "geometry": {"coordinates":[0.0635019130665,51.52558290970163],"type":"Point"}
}