{
  "type": "Feature",
  "properties": {
    "iso:country":"GB",
    "wof:name":"NE3 2RQ",
    "wof:placetype":"postalcode"
},
  "geometry": {"coordinates":[-1.64251457240781,55.01497171550184],"type":"Point"}
}