{
  "type": "Feature",
  "properties": {
    "iso:country": "GB",
    "wof:name": "NE3 2RQ",
    "wof:placetype": "postalcode"
  },
  "geometry": {"coordinates":[-1.642515,55.014972],"type":"Point"}
}
