{
  "type": "Feature",
  "properties": {
    "iso:country": "GB",
    "wof:name": "ME16 9EE",
    "wof:placetype": "postalcode"
  },
  "geometry": {"coordinates":[0.474889,51.26523],"type":"Point"}
}
