{
  "type": "Feature",
  "properties": {
    "iso:country":"GB",
    "wof:name":"CT9 4FA",
    "wof:placetype":"postalcode"
},
  "geometry": {"coordinates":[1.39212235841299,51.36085586050218],"type":"Point"}
}