{
  "type": "Feature",
  "properties": {
    "date:inception_lower": "1980-01-01",
    "date:inception_upper": "1980-01-01",
    "iso:country": "GB",
    "wof:name": "RH2 7DZ",
    "wof:placetype": "postalcode"
  },
  "geometry": {"coordinates":[-0.195587,51.232441],"type":"Point"}
}
