{
  "type": "Feature",
  "properties": {
    "iso:country": "GB",
    "wof:name": "RH2 7DZ",
    "wof:placetype": "postalcode"
  },
  "geometry": {"coordinates":[-0.195587,51.232441],"type":"Point"}
}
