{
  "type": "Feature",
  "properties": {
    "iso:country":"GB",
    "wof:name":"RH2 7DZ",
    "wof:placetype":"postalcode"
},
  "geometry": {"coordinates":[-0.19558697405061,51.2324414493674],"type":"Point"}
}