{
  "type": "Feature",
  "properties": {
    "iso:country": "GB",
    "wof:name": "TS13 4QH",
    "wof:placetype": "postalcode"
  },
  "geometry": {"coordinates":[-0.901124,54.552104],"type":"Point"}
}
