{
  "type": "Feature",
  "properties": {
    "date:inception_lower":"1980-01-01",
    "date:inception_upper":"1980-01-31",
    "iso:country":"GB",
    "wof:name":"WA8 9RT",
    "wof:placetype":"postalcode"
},
  "geometry": {"coordinates":[-2.726015,53.38877],"type":"Point"}
}