{
  "type": "Feature",
  "properties": {
    "iso:country":"GB",
    "wof:name":"WA8 9RT",
    "wof:placetype":"postalcode"
},
  "geometry": {"coordinates":[-2.72601484094205,53.38877022233813],"type":"Point"}
}