{
  "type": "Feature",
  "properties": {
    "iso:country": "GB",
    "wof:name": "WA8 9RT",
    "wof:placetype": "postalcode"
  },
  "geometry": {"coordinates":[-2.726015,53.38877],"type":"Point"}
}
