{
  "type": "Feature",
  "properties": {
    "iso:country": "GB",
    "wof:name": "G65 0LU",
    "wof:placetype": "postalcode"
  },
  "geometry": {"coordinates":[-4.058906,55.974203],"type":"Point"}
}
