{
  "type": "Feature",
  "properties": {
    "date:inception_lower": "1980-01-01",
    "date:inception_upper": "1980-01-01",
    "iso:country": "GB",
    "wof:name": "G65 0LU",
    "wof:placetype": "postalcode"
  },
  "geometry": {"coordinates":[-4.058906,55.974203],"type":"Point"}
}
