{
  "type": "Feature",
  "properties": {
    "iso:country": "GB",
    "wof:name": "RH12 1PL",
    "wof:placetype": "postalcode"
  },
  "geometry": {"coordinates":[-0.330165,51.06278],"type":"Point"}
}
