{
  "type": "Feature",
  "properties": {
    "iso:country":"GB",
    "wof:name":"HA5 1AY",
    "wof:placetype":"postalcode"
},
  "geometry": {"coordinates":[-0.39034060448984,51.59011252046285],"type":"Point"}
}