{
  "type": "Feature",
  "properties": {
    "iso:country": "GB",
    "wof:name": "DL16 7EJ",
    "wof:placetype": "postalcode"
  },
  "geometry": {"coordinates":[-1.615785,54.692286],"type":"Point"}
}
