{
  "type": "Feature",
  "properties": {
    "iso:country":"GB",
    "wof:name":"CO12 3RF",
    "wof:placetype":"postalcode"
},
  "geometry": {"coordinates":[1.27958875063608,51.93469973628557],"type":"Point"}
}