{
  "type": "Feature",
  "properties": {
    "iso:country": "GB",
    "wof:name": "SL1 9EA",
    "wof:placetype": "postalcode"
  },
  "geometry": {"coordinates":[-0.634725,51.505736],"type":"Point"}
}
