{
  "type": "Feature",
  "properties": {
    "date:inception_lower": "1986-07-01",
    "date:inception_upper": "1986-07-01",
    "iso:country": "GB",
    "wof:name": "SL1 9EA",
    "wof:placetype": "postalcode"
  },
  "geometry": {"coordinates":[-0.634725,51.505736],"type":"Point"}
}
