{
  "type": "Feature",
  "properties": {
    "iso:country": "GB",
    "wof:name": "E17 4NX",
    "wof:placetype": "postalcode"
  },
  "geometry": {"coordinates":[-0.014785,51.590692],"type":"Point"}
}
