{
  "type": "Feature",
  "properties": {
    "iso:country":"GB",
    "wof:name":"E17 4NX",
    "wof:placetype":"postalcode"
},
  "geometry": {"coordinates":[-0.01478499036131,51.59069156289233],"type":"Point"}
}