{
  "type": "Feature",
  "properties": {
    "iso:country":"GB",
    "wof:name":"SS14 2ST",
    "wof:placetype":"postalcode"
},
  "geometry": {"coordinates":[0.48148165685476,51.58111989559738],"type":"Point"}
}