{
  "type": "Feature",
  "properties": {
    "iso:country": "GB",
    "wof:name": "DL7 9PF",
    "wof:placetype": "postalcode"
  },
  "geometry": {"coordinates":[-1.521223,54.286923],"type":"Point"}
}
