{
  "type": "Feature",
  "properties": {
    "iso:country":"GB",
    "wof:name":"DL7 9PF",
    "wof:placetype":"postalcode"
},
  "geometry": {"coordinates":[-1.52122273513323,54.28692274502194],"type":"Point"}
}