{
  "type": "Feature",
  "properties": {
    "iso:country":"GB",
    "wof:name":"KT11 2QX",
    "wof:placetype":"postalcode"
},
  "geometry": {"coordinates":[-0.37373591208842,51.32978941744853],"type":"Point"}
}