{
  "type": "Feature",
  "properties": {
    "date:inception_lower": "1980-01-01",
    "date:inception_upper": "1980-01-01",
    "iso:country": "GB",
    "wof:name": "CV31 1DL",
    "wof:placetype": "postalcode"
  },
  "geometry": {"coordinates":[-1.520368,52.286754],"type":"Point"}
}
