{
  "type": "Feature",
  "properties": {
    "iso:country":"GB",
    "wof:name":"WS13 8TJ",
    "wof:placetype":"postalcode"
},
  "geometry": {"coordinates":[-1.77455106810352,52.71201739080153],"type":"Point"}
}