{
  "type": "Feature",
  "properties": {
    "date:inception_lower": "2003-02-01",
    "date:inception_upper": "2003-02-01",
    "iso:country": "GB",
    "wof:name": "OX10 9GL",
    "wof:placetype": "postalcode"
  },
  "geometry": {"coordinates":[-1.13526,51.596551],"type":"Point"}
}
