{
  "type": "Feature",
  "properties": {
    "iso:country": "GB",
    "wof:name": "PE21 8ET",
    "wof:placetype": "postalcode"
  },
  "geometry": {"coordinates":[-0.035569,52.976276],"type":"Point"}
}
