{
  "type": "Feature",
  "properties": {
    "date:inception_lower":"1993-08-01",
    "date:inception_upper":"1993-08-31",
    "iso:country":"GB",
    "wof:name":"SY10 0LL",
    "wof:placetype":"postalcode"
},
  "geometry": {"coordinates":[-3.296305,52.823623],"type":"Point"}
}