{
  "type": "Feature",
  "properties": {
    "date:inception_lower":"2000-06-01",
    "date:inception_upper":"2000-06-30",
    "iso:country":"GB",
    "wof:name":"OX16 3HF",
    "wof:placetype":"postalcode"
},
  "geometry": {"coordinates":[-1.327006,52.06832],"type":"Point"}
}