{
  "type": "Feature",
  "properties": {
    "iso:country": "GB",
    "wof:name": "OX16 3HF",
    "wof:placetype": "postalcode"
  },
  "geometry": {"coordinates":[-1.327006,52.06832],"type":"Point"}
}
