{
  "type": "Feature",
  "properties": {
    "iso:country":"GB",
    "wof:name":"OX16 3HF",
    "wof:placetype":"postalcode"
},
  "geometry": {"coordinates":[-1.32700596889638,52.06831983158207],"type":"Point"}
}