{
  "type": "Feature",
  "properties": {
    "iso:country":"GB",
    "wof:name":"WA11 8PQ",
    "wof:placetype":"postalcode"
},
  "geometry": {"coordinates":[-2.78228617321425,53.5103377270547],"type":"Point"}
}