{
  "type": "Feature",
  "properties": {
    "iso:country":"GB",
    "wof:name":"DN7 4BJ",
    "wof:placetype":"postalcode"
},
  "geometry": {"coordinates":[-1.01433411444348,53.57546220613905],"type":"Point"}
}