{
  "type": "Feature",
  "properties": {
    "iso:country": "GB",
    "wof:name": "NE9 5XN",
    "wof:placetype": "postalcode"
  },
  "geometry": {"coordinates":[-1.59516,54.935951],"type":"Point"}
}
