{
  "type": "Feature",
  "properties": {
    "date:inception_lower":"1980-01-01",
    "date:inception_upper":"1980-01-31",
    "iso:country":"GB",
    "wof:name":"NE9 5XN",
    "wof:placetype":"postalcode"
},
  "geometry": {"coordinates":[-1.59516,54.935951],"type":"Point"}
}