{
  "type": "Feature",
  "properties": {
    "iso:country":"GB",
    "wof:name":"NE9 5XN",
    "wof:placetype":"postalcode"
},
  "geometry": {"coordinates":[-1.5951598517853,54.93595103372279],"type":"Point"}
}