{
  "type": "Feature",
  "properties": {
    "iso:country":"GB",
    "wof:name":"L9 5AE",
    "wof:placetype":"postalcode"
},
  "geometry": {"coordinates":[-2.95182419423925,53.48416387074683],"type":"Point"}
}