{
  "type": "Feature",
  "properties": {
    "date:inception_lower": "1980-01-01",
    "date:inception_upper": "1980-01-01",
    "iso:country": "GB",
    "wof:name": "L9 5AE",
    "wof:placetype": "postalcode"
  },
  "geometry": {"coordinates":[-2.951824,53.484164],"type":"Point"}
}
