{
  "type": "Feature",
  "properties": {
    "iso:country": "GB",
    "wof:name": "SW19 1QU",
    "wof:placetype": "postalcode"
  },
  "geometry": {"coordinates":[-0.202725,51.418457],"type":"Point"}
}
