{
  "type": "Feature",
  "properties": {
    "iso:country":"GB",
    "wof:name":"LE12 7DA",
    "wof:placetype":"postalcode"
},
  "geometry": {"coordinates":[-1.1408901599766,52.72055595881005],"type":"Point"}
}