{
  "type": "Feature",
  "properties": {
    "date:inception_lower":"1980-01-01",
    "date:inception_upper":"1980-01-31",
    "iso:country":"GB",
    "wof:name":"G76 9BP",
    "wof:placetype":"postalcode"
},
  "geometry": {"coordinates":[-4.23716,55.790584],"type":"Point"}
}