{
  "type": "Feature",
  "properties": {
    "date:inception_lower": "1980-01-01",
    "date:inception_upper": "1980-01-01",
    "iso:country": "GB",
    "wof:name": "IG11 9BL",
    "wof:placetype": "postalcode"
  },
  "geometry": {"coordinates":[0.103855,51.542195],"type":"Point"}
}
