{
  "type": "Feature",
  "properties": {
    "iso:country": "GB",
    "wof:name": "B67 5LZ",
    "wof:placetype": "postalcode"
  },
  "geometry": {"coordinates":[-1.984688,52.477462],"type":"Point"}
}
