{
  "type": "Feature",
  "properties": {
    "iso:country":"GB",
    "wof:name":"B67 5LZ",
    "wof:placetype":"postalcode"
},
  "geometry": {"coordinates":[-1.98468818933604,52.47746208482474],"type":"Point"}
}