{
  "type": "Feature",
  "properties": {
    "date:inception_lower": "2003-02-01",
    "date:inception_upper": "2003-02-01",
    "iso:country": "GB",
    "wof:name": "SE5 8WU",
    "wof:placetype": "postalcode"
  },
  "geometry": {"coordinates":[-0.096725,51.473914],"type":"Point"}
}
