{
  "type": "Feature",
  "properties": {
    "iso:country":"GB",
    "wof:name":"BS35 2XG",
    "wof:placetype":"postalcode"
},
  "geometry": {"coordinates":[-2.51188576664373,51.60236657182378],"type":"Point"}
}