{
  "type": "Feature",
  "properties": {
    "date:inception_lower": "1980-01-01",
    "date:inception_upper": "1980-01-01",
    "iso:country": "GB",
    "wof:name": "SA20 0BA",
    "wof:placetype": "postalcode"
  },
  "geometry": {"coordinates":[-3.803108,51.991764],"type":"Point"}
}
