{
  "type": "Feature",
  "properties": {
    "iso:country": "GB",
    "wof:name": "PE31 6UH",
    "wof:placetype": "postalcode"
  },
  "geometry": {"coordinates":[0.499842,52.842746],"type":"Point"}
}
