{
  "type": "Feature",
  "properties": {
    "iso:country":"GB",
    "wof:name":"BD5 7NU",
    "wof:placetype":"postalcode"
},
  "geometry": {"coordinates":[-1.76177871688281,53.7787219805125],"type":"Point"}
}