{
  "type": "Feature",
  "properties": {
    "iso:country": "GB",
    "wof:name": "BD5 7NU",
    "wof:placetype": "postalcode"
  },
  "geometry": {"coordinates":[-1.761779,53.778722],"type":"Point"}
}
