{
  "type": "Feature",
  "properties": {
    "iso:country":"GB",
    "wof:name":"YO25 5BQ",
    "wof:placetype":"postalcode"
},
  "geometry": {"coordinates":[-0.44694848200603,54.00723191776558],"type":"Point"}
}