{
  "type": "Feature",
  "properties": {
    "iso:country": "GB",
    "wof:name": "YO25 5BQ",
    "wof:placetype": "postalcode"
  },
  "geometry": {"coordinates":[-0.446948,54.007232],"type":"Point"}
}
