{
  "type": "Feature",
  "properties": {
    "iso:country":"GB",
    "wof:name":"OX3 7AW",
    "wof:placetype":"postalcode"
},
  "geometry": {"coordinates":[-1.2103870787784,51.75642588678145],"type":"Point"}
}