{
  "type": "Feature",
  "properties": {
    "iso:country": "GB",
    "wof:name": "OX3 7AW",
    "wof:placetype": "postalcode"
  },
  "geometry": {"coordinates":[-1.210387,51.756426],"type":"Point"}
}
