{
  "type": "Feature",
  "properties": {
    "iso:country": "GB",
    "wof:name": "B23 6PJ",
    "wof:placetype": "postalcode"
  },
  "geometry": {"coordinates":[-1.845644,52.527464],"type":"Point"}
}
