{
  "type": "Feature",
  "properties": {
    "date:inception_lower": "2024-07-01",
    "date:inception_upper": "2024-07-01",
    "iso:country": "GB",
    "wof:name": "G69 8GS",
    "wof:placetype": "postalcode"
  },
  "geometry": {"coordinates":[-4.077944,55.89695],"type":"Point"}
}
