{
  "type": "Feature",
  "properties": {
    "iso:country": "GB",
    "wof:name": "DN21 1YD",
    "wof:placetype": "postalcode"
  },
  "geometry": {"coordinates":[-0.762775,53.406846],"type":"Point"}
}
