{
  "type": "Feature",
  "properties": {
    "iso:country":"GB",
    "wof:name":"TQ3 3QL",
    "wof:placetype":"postalcode"
},
  "geometry": {"coordinates":[-3.57929656079912,50.43561026754629],"type":"Point"}
}