{
  "type": "Feature",
  "properties": {
    "iso:country":"GB",
    "wof:name":"NR11 8ET",
    "wof:placetype":"postalcode"
},
  "geometry": {"coordinates":[1.41269377671306,52.87750190834062],"type":"Point"}
}