{
  "type": "Feature",
  "properties": {
    "iso:country": "GB",
    "wof:name": "NR11 8ET",
    "wof:placetype": "postalcode"
  },
  "geometry": {"coordinates":[1.413501,52.877328],"type":"Point"}
}
