{
  "type": "Feature",
  "properties": {
    "date:inception_lower": "1983-03-01",
    "date:inception_upper": "1983-03-01",
    "iso:country": "GB",
    "wof:name": "BH17 8AY",
    "wof:placetype": "postalcode"
  },
  "geometry": {"coordinates":[-1.959182,50.749294],"type":"Point"}
}
