{
  "type": "Feature",
  "properties": {
    "date:inception_lower": "2023-01-01",
    "date:inception_upper": "2023-01-01",
    "iso:country": "GB",
    "wof:name": "PR4 0GG",
    "wof:placetype": "postalcode"
  },
  "geometry": {"coordinates":[-2.73859,53.795429],"type":"Point"}
}
