{
  "type": "Feature",
  "properties": {
    "iso:country":"GB",
    "wof:name":"WR9 8DJ",
    "wof:placetype":"postalcode"
},
  "geometry": {"coordinates":[-2.14987067838059,52.26586594909359],"type":"Point"}
}