{
  "type": "Feature",
  "properties": {
    "iso:country":"GB",
    "wof:name":"LA9 7JS",
    "wof:placetype":"postalcode"
},
  "geometry": {"coordinates":[-2.73458681090801,54.31741287453379],"type":"Point"}
}