{
  "type": "Feature",
  "properties": {
    "iso:country":"GB",
    "wof:name":"CF11 7BT",
    "wof:placetype":"postalcode"
},
  "geometry": {"coordinates":[-3.18126198993214,51.46885537428841],"type":"Point"}
}