{
  "type": "Feature",
  "properties": {
    "iso:country":"GB",
    "wof:name":"NP19 8DT",
    "wof:placetype":"postalcode"
},
  "geometry": {"coordinates":[-2.98358104584311,51.5913854189194],"type":"Point"}
}