{
  "type": "Feature",
  "properties": {
    "date:inception_lower": "1984-10-01",
    "date:inception_upper": "1984-10-01",
    "iso:country": "GB",
    "wof:name": "CV31 1YW",
    "wof:placetype": "postalcode"
  },
  "geometry": {"coordinates":[-1.518637,52.278719],"type":"Point"}
}
