{
  "type": "Feature",
  "properties": {
    "iso:country":"GB",
    "wof:name":"CV31 1YW",
    "wof:placetype":"postalcode"
},
  "geometry": {"coordinates":[-1.51863734106357,52.27871857396908],"type":"Point"}
}