{
  "type": "Feature",
  "properties": {
    "iso:country":"GB",
    "wof:name":"CF24 3RT",
    "wof:placetype":"postalcode"
},
  "geometry": {"coordinates":[-3.1653447896925,51.49394025482669],"type":"Point"}
}