{
  "type": "Feature",
  "properties": {
    "iso:country":"GB",
    "wof:name":"SA15 5BJ",
    "wof:placetype":"postalcode"
},
  "geometry": {"coordinates":[-4.17060884061404,51.7450048977065],"type":"Point"}
}