{
  "type": "Feature",
  "properties": {
    "date:inception_lower":"1980-01-01",
    "date:inception_upper":"1980-01-31",
    "iso:country":"GB",
    "wof:name":"BS16 6UU",
    "wof:placetype":"postalcode"
},
  "geometry": {"coordinates":[-2.49159,51.493126],"type":"Point"}
}