{
  "type": "Feature",
  "properties": {
    "iso:country":"GB",
    "wof:name":"BS16 6UU",
    "wof:placetype":"postalcode"
},
  "geometry": {"coordinates":[-2.49158967076461,51.49312614023515],"type":"Point"}
}