{
  "type": "Feature",
  "properties": {
    "iso:country":"GB",
    "wof:name":"W1H 5JB",
    "wof:placetype":"postalcode"
},
  "geometry": {"coordinates":[-0.1647359432422,51.51836026860466],"type":"Point"}
}