{
  "type": "Feature",
  "properties": {
    "iso:country":"GB",
    "wof:name":"TR5 0NW",
    "wof:placetype":"postalcode"
},
  "geometry": {"coordinates":[-5.21564139323109,50.3049644998378],"type":"Point"}
}