{
  "type": "Feature",
  "properties": {
    "iso:country":"GB",
    "wof:name":"NR22 6AG",
    "wof:placetype":"postalcode"
},
  "geometry": {"coordinates":[0.8709341140457,52.87757394273009],"type":"Point"}
}