{
  "type": "Feature",
  "properties": {
    "iso:country":"GB",
    "wof:name":"LS4 2AU",
    "wof:placetype":"postalcode"
},
  "geometry": {"coordinates":[-1.57816554657066,53.8041475040809],"type":"Point"}
}