{
  "type": "Feature",
  "properties": {
    "date:inception_lower": "2021-05-01",
    "date:inception_upper": "2021-05-01",
    "iso:country": "GB",
    "wof:name": "SK17 8FT",
    "wof:placetype": "postalcode"
  },
  "geometry": {"coordinates":[-1.884128,53.304064],"type":"Point"}
}
