{
  "type": "Feature",
  "properties": {
    "date:inception_lower": "1987-04-01",
    "date:inception_upper": "1987-04-01",
    "iso:country": "GB",
    "wof:name": "CV9 1RS",
    "wof:placetype": "postalcode"
  },
  "geometry": {"coordinates":[-1.525384,52.570143],"type":"Point"}
}
