{
  "type": "Feature",
  "properties": {
    "iso:country":"GB",
    "wof:name":"CV9 1RS",
    "wof:placetype":"postalcode"
},
  "geometry": {"coordinates":[-1.52538412915264,52.5701426753501],"type":"Point"}
}