{
  "type": "Feature",
  "properties": {
    "iso:country":"GB",
    "wof:name":"SW8 1JE",
    "wof:placetype":"postalcode"
},
  "geometry": {"coordinates":[-0.1209758781251,51.47632864096956],"type":"Point"}
}