{
  "type": "Feature",
  "properties": {
    "iso:country": "GB",
    "wof:name": "HU2 8NH",
    "wof:placetype": "postalcode"
  },
  "geometry": {"coordinates":[-0.347128,53.74801],"type":"Point"}
}
