{
  "type": "Feature",
  "properties": {
    "date:inception_lower":"2010-05-01",
    "date:inception_upper":"2010-05-31",
    "iso:country":"GB",
    "wof:name":"HU2 8NH",
    "wof:placetype":"postalcode"
},
  "geometry": {"coordinates":[-0.347128,53.74801],"type":"Point"}
}