{
  "type": "Feature",
  "properties": {
    "iso:country": "GB",
    "wof:name": "TR5 0QX",
    "wof:placetype": "postalcode"
  },
  "geometry": {"coordinates":[-5.199722,50.312341],"type":"Point"}
}
