{
  "type": "Feature",
  "properties": {
    "iso:country":"GB",
    "wof:name":"TR5 0QX",
    "wof:placetype":"postalcode"
},
  "geometry": {"coordinates":[-5.19967551097863,50.3123503071801],"type":"Point"}
}