{
  "type": "Feature",
  "properties": {
    "iso:country":"GB",
    "wof:name":"HR6 9UQ",
    "wof:placetype":"postalcode"
},
  "geometry": {"coordinates":[-2.89382983016344,52.30734907641109],"type":"Point"}
}