{
  "type": "Feature",
  "properties": {
    "iso:country": "GB",
    "wof:name": "HR6 9UQ",
    "wof:placetype": "postalcode"
  },
  "geometry": {"coordinates":[-2.89383,52.307349],"type":"Point"}
}
