{
  "type": "Feature",
  "properties": {
    "iso:country": "GB",
    "wof:name": "HD4 5TP",
    "wof:placetype": "postalcode"
  },
  "geometry": {"coordinates":[-1.832357,53.63371],"type":"Point"}
}
