{
  "type": "Feature",
  "properties": {
    "date:inception_lower": "1980-01-01",
    "date:inception_upper": "1980-01-01",
    "iso:country": "GB",
    "wof:name": "PL30 4LH",
    "wof:placetype": "postalcode"
  },
  "geometry": {"coordinates":[-4.67188,50.544644],"type":"Point"}
}
