{
  "type": "Feature",
  "properties": {
    "iso:country": "GB",
    "wof:name": "PL30 4LH",
    "wof:placetype": "postalcode"
  },
  "geometry": {"coordinates":[-4.67188,50.544644],"type":"Point"}
}
