{
  "type": "Feature",
  "properties": {
    "iso:country":"GB",
    "wof:name":"PL30 4LH",
    "wof:placetype":"postalcode"
},
  "geometry": {"coordinates":[-4.67187985164542,50.54464432033336],"type":"Point"}
}