{
  "type": "Feature",
  "properties": {
    "date:inception_lower":"1980-04-01",
    "date:inception_upper":"1980-04-30",
    "iso:country":"GB",
    "wof:name":"KA11 1NP",
    "wof:placetype":"postalcode"
},
  "geometry": {"coordinates":[-4.629558,55.627553],"type":"Point"}
}