{
  "type": "Feature",
  "properties": {
    "iso:country": "GB",
    "wof:name": "KA11 1NP",
    "wof:placetype": "postalcode"
  },
  "geometry": {"coordinates":[-4.629558,55.627553],"type":"Point"}
}
