{
  "type": "Feature",
  "properties": {
    "iso:country":"GB",
    "wof:name":"SP2 7DU",
    "wof:placetype":"postalcode"
},
  "geometry": {"coordinates":[-1.8054259127072,51.07164213455096],"type":"Point"}
}