{
  "type": "Feature",
  "properties": {
    "date:inception_lower": "1980-01-01",
    "date:inception_upper": "1980-01-01",
    "iso:country": "GB",
    "wof:name": "CV5 8DD",
    "wof:placetype": "postalcode"
  },
  "geometry": {"coordinates":[-1.53416,52.407215],"type":"Point"}
}
