{
  "type": "Feature",
  "properties": {
    "iso:country": "GB",
    "wof:name": "CV5 8DD",
    "wof:placetype": "postalcode"
  },
  "geometry": {"coordinates":[-1.53416,52.407215],"type":"Point"}
}
