{
  "type": "Feature",
  "properties": {
    "iso:country":"GB",
    "wof:name":"CV5 8DD",
    "wof:placetype":"postalcode"
},
  "geometry": {"coordinates":[-1.53416030639297,52.40721539685875],"type":"Point"}
}