{
  "type": "Feature",
  "properties": {
    "iso:country": "GB",
    "wof:name": "CV13 6EJ",
    "wof:placetype": "postalcode"
  },
  "geometry": {"coordinates":[-1.411245,52.571159],"type":"Point"}
}
