{
  "type": "Feature",
  "properties": {
    "iso:country":"GB",
    "wof:name":"CV13 6EJ",
    "wof:placetype":"postalcode"
},
  "geometry": {"coordinates":[-1.41124495951593,52.57115873011099],"type":"Point"}
}