{
  "type": "Feature",
  "properties": {
    "date:inception_lower": "1980-01-01",
    "date:inception_upper": "1980-01-01",
    "iso:country": "GB",
    "wof:name": "CV13 6EJ",
    "wof:placetype": "postalcode"
  },
  "geometry": {"coordinates":[-1.411245,52.571159],"type":"Point"}
}
