{
  "type": "Feature",
  "properties": {
    "iso:country":"GB",
    "wof:name":"AB43 7AS",
    "wof:placetype":"postalcode"
},
  "geometry": {"coordinates":[-2.04622705610279,57.63636012659683],"type":"Point"}
}