{
  "type": "Feature",
  "properties": {
    "iso:country": "GB",
    "wof:name": "HD3 4AD",
    "wof:placetype": "postalcode"
  },
  "geometry": {"coordinates":[-1.84242,53.648237],"type":"Point"}
}
