{
  "type": "Feature",
  "properties": {
    "iso:country":"GB",
    "wof:name":"BH9 3DG",
    "wof:placetype":"postalcode"
},
  "geometry": {"coordinates":[-1.86472040267333,50.75020310164363],"type":"Point"}
}