{
  "type": "Feature",
  "properties": {
    "iso:country":"GB",
    "wof:name":"W9 3LR",
    "wof:placetype":"postalcode"
},
  "geometry": {"coordinates":[-0.1983782788649,51.52600383084069],"type":"Point"}
}