{
  "type": "Feature",
  "properties": {
    "iso:country":"GB",
    "wof:name":"G84 8LX",
    "wof:placetype":"postalcode"
},
  "geometry": {"coordinates":[-4.7786813865816,56.01954797646566],"type":"Point"}
}