{
  "type": "Feature",
  "properties": {
    "iso:country":"GB",
    "wof:name":"S42 6HS",
    "wof:placetype":"postalcode"
},
  "geometry": {"coordinates":[-1.42544633464558,53.17577093963025],"type":"Point"}
}