{
  "type": "Feature",
  "properties": {
    "iso:country": "GB",
    "wof:name": "S42 6HS",
    "wof:placetype": "postalcode"
  },
  "geometry": {"coordinates":[-1.425431,53.17578],"type":"Point"}
}
