{
  "type": "Feature",
  "properties": {
    "iso:country": "GB",
    "wof:name": "MK4 4GJ",
    "wof:placetype": "postalcode"
  },
  "geometry": {"coordinates":[-0.797334,52.00026],"type":"Point"}
}
