{
  "type": "Feature",
  "properties": {
    "iso:country":"GB",
    "wof:name":"MK4 4GJ",
    "wof:placetype":"postalcode"
},
  "geometry": {"coordinates":[-0.79733398660624,52.00026027168349],"type":"Point"}
}