{
  "type": "Feature",
  "properties": {
    "date:inception_lower": "2006-07-01",
    "date:inception_upper": "2006-07-01",
    "iso:country": "GB",
    "wof:name": "MK4 4GJ",
    "wof:placetype": "postalcode"
  },
  "geometry": {"coordinates":[-0.797334,52.00026],"type":"Point"}
}
