{
  "type": "Feature",
  "properties": {
    "iso:country":"GB",
    "wof:name":"N10 3NG",
    "wof:placetype":"postalcode"
},
  "geometry": {"coordinates":[-0.1466544505771,51.58773143613615],"type":"Point"}
}