{
  "type": "Feature",
  "properties": {
    "iso:country":"GB",
    "wof:name":"GL1 4RU",
    "wof:placetype":"postalcode"
},
  "geometry": {"coordinates":[-2.23666747510192,51.84805520704938],"type":"Point"}
}