{
  "type": "Feature",
  "properties": {
    "iso:country":"GB",
    "wof:name":"NN6 6HA",
    "wof:placetype":"postalcode"
},
  "geometry": {"coordinates":[-1.05632035588781,52.42016412435553],"type":"Point"}
}