{
  "type": "Feature",
  "properties": {
    "iso:country":"GB",
    "wof:name":"N13 5AZ",
    "wof:placetype":"postalcode"
},
  "geometry": {"coordinates":[-0.09282615480277,51.62076152590402],"type":"Point"}
}