{
  "type": "Feature",
  "properties": {
    "date:inception_lower": "1986-07-01",
    "date:inception_upper": "1986-07-01",
    "iso:country": "GB",
    "wof:name": "CT1 1AS",
    "wof:placetype": "postalcode"
  },
  "geometry": {"coordinates":[1.109056,51.280281],"type":"Point"}
}
