{
  "type": "Feature",
  "properties": {
    "iso:country":"GB",
    "wof:name":"PL6 7EW",
    "wof:placetype":"postalcode"
},
  "geometry": {"coordinates":[-4.11063300173126,50.43641886751804],"type":"Point"}
}