{
  "type": "Feature",
  "properties": {
    "iso:country": "GB",
    "wof:name": "HU17 9GS",
    "wof:placetype": "postalcode"
  },
  "geometry": {"coordinates":[-0.426678,53.857961],"type":"Point"}
}
