{
  "type": "Feature",
  "properties": {
    "date:inception_lower": "1997-06-01",
    "date:inception_upper": "1997-06-01",
    "iso:country": "GB",
    "wof:name": "HU17 9GS",
    "wof:placetype": "postalcode"
  },
  "geometry": {"coordinates":[-0.426678,53.857961],"type":"Point"}
}
