{
  "type": "Feature",
  "properties": {
    "iso:country":"GB",
    "wof:name":"OX1 5QY",
    "wof:placetype":"postalcode"
},
  "geometry": {"coordinates":[-1.24213041164529,51.70877414573629],"type":"Point"}
}