{
  "type": "Feature",
  "properties": {
    "iso:country": "GB",
    "wof:name": "CR4 3PT",
    "wof:placetype": "postalcode"
  },
  "geometry": {"coordinates":[-0.182254,51.40664],"type":"Point"}
}
