{
  "type": "Feature",
  "properties": {
    "date:inception_lower": "1980-01-01",
    "date:inception_upper": "1980-01-01",
    "iso:country": "GB",
    "wof:name": "CR4 3PT",
    "wof:placetype": "postalcode"
  },
  "geometry": {"coordinates":[-0.182254,51.40664],"type":"Point"}
}
