{
  "type": "Feature",
  "properties": {
    "iso:country": "GB",
    "wof:name": "IP11 9FN",
    "wof:placetype": "postalcode"
  },
  "geometry": {"coordinates":[1.369418,51.977283],"type":"Point"}
}
