{
  "type": "Feature",
  "properties": {
    "date:inception_lower": "2019-12-01",
    "date:inception_upper": "2019-12-01",
    "iso:country": "GB",
    "wof:name": "IP11 9FN",
    "wof:placetype": "postalcode"
  },
  "geometry": {"coordinates":[1.370603,51.977735],"type":"Point"}
}
