{
  "type": "Feature",
  "properties": {
    "date:inception_lower": "1980-01-01",
    "date:inception_upper": "1980-01-01",
    "iso:country": "GB",
    "wof:name": "LS8 4LW",
    "wof:placetype": "postalcode"
  },
  "geometry": {"coordinates":[-1.522973,53.817324],"type":"Point"}
}
