{
  "type": "Feature",
  "properties": {
    "iso:country":"GB",
    "wof:name":"LS8 4LW",
    "wof:placetype":"postalcode"
},
  "geometry": {"coordinates":[-1.52297353540221,53.81732399052292],"type":"Point"}
}