{
  "type": "Feature",
  "properties": {
    "date:inception_lower": "1999-06-01",
    "date:inception_upper": "1999-06-01",
    "iso:country": "GB",
    "wof:name": "CF45 4TX",
    "wof:placetype": "postalcode"
  },
  "geometry": {"coordinates":[-3.326781,51.65055],"type":"Point"}
}
