{
  "type": "Feature",
  "properties": {
    "iso:country": "GB",
    "wof:name": "DH6 1QU",
    "wof:placetype": "postalcode"
  },
  "geometry": {"coordinates":[-1.507132,54.773708],"type":"Point"}
}
