{
  "type": "Feature",
  "properties": {
    "iso:country":"GB",
    "wof:name":"DH6 1QU",
    "wof:placetype":"postalcode"
},
  "geometry": {"coordinates":[-1.50713223544377,54.77370778506551],"type":"Point"}
}