{
  "type": "Feature",
  "properties": {
    "date:inception_lower": "1982-12-01",
    "date:inception_upper": "1982-12-01",
    "iso:country": "GB",
    "wof:name": "FK2 8DT",
    "wof:placetype": "postalcode"
  },
  "geometry": {"coordinates":[-3.786014,56.026717],"type":"Point"}
}
