{
  "type": "Feature",
  "properties": {
    "date:inception_lower": "2016-12-01",
    "date:inception_upper": "2016-12-01",
    "iso:country": "GB",
    "wof:name": "B42 2AA",
    "wof:placetype": "postalcode"
  },
  "geometry": {"coordinates":[-1.907809,52.542728],"type":"Point"}
}
