{
  "type": "Feature",
  "properties": {
    "iso:country":"GB",
    "wof:name":"NG15 7BH",
    "wof:placetype":"postalcode"
},
  "geometry": {"coordinates":[-1.20312242997261,53.03973395512333],"type":"Point"}
}