{
  "type": "Feature",
  "properties": {
    "iso:country": "GB",
    "wof:name": "ML8 4LA",
    "wof:placetype": "postalcode"
  },
  "geometry": {"coordinates":[-3.829559,55.726844],"type":"Point"}
}
