{
  "type": "Feature",
  "properties": {
    "iso:country":"GB",
    "wof:name":"ML8 4LA",
    "wof:placetype":"postalcode"
},
  "geometry": {"coordinates":[-3.82955890642613,55.72684438888871],"type":"Point"}
}