{
  "type": "Feature",
  "properties": {
    "date:inception_lower": "1980-01-01",
    "date:inception_upper": "1980-01-01",
    "iso:country": "GB",
    "wof:name": "ML8 4LA",
    "wof:placetype": "postalcode"
  },
  "geometry": {"coordinates":[-3.829559,55.726844],"type":"Point"}
}
