{
  "type": "Feature",
  "properties": {
    "iso:country":"GB",
    "wof:name":"G51 4FA",
    "wof:placetype":"postalcode"
},
  "geometry": {"coordinates":[-4.32607363277834,55.85311389793814],"type":"Point"}
}