{
  "type": "Feature",
  "properties": {
    "iso:country": "GB",
    "wof:name": "G51 4FA",
    "wof:placetype": "postalcode"
  },
  "geometry": {"coordinates":[-4.326074,55.853114],"type":"Point"}
}
