{
  "type": "Feature",
  "properties": {
    "iso:country":"GB",
    "wof:name":"CR0 4JX",
    "wof:placetype":"postalcode"
},
  "geometry": {"coordinates":[-0.11850129079069,51.37085906465867],"type":"Point"}
}