{
  "type": "Feature",
  "properties": {
    "date:inception_lower":"1980-01-01",
    "date:inception_upper":"1980-01-31",
    "iso:country":"GB",
    "wof:name":"LA13 9QP",
    "wof:placetype":"postalcode"
},
  "geometry": {"coordinates":[-3.210265,54.112544],"type":"Point"}
}