{
  "type": "Feature",
  "properties": {
    "iso:country":"GB",
    "wof:name":"G3 6NH",
    "wof:placetype":"postalcode"
},
  "geometry": {"coordinates":[-4.27974050514253,55.87169579492296],"type":"Point"}
}