{
  "type": "Feature",
  "properties": {
    "iso:country":"GB",
    "wof:name":"HD9 5RU",
    "wof:placetype":"postalcode"
},
  "geometry": {"coordinates":[-1.84607381239012,53.59605002732142],"type":"Point"}
}