{
  "type": "Feature",
  "properties": {
    "iso:country":"GB",
    "wof:name":"SN2 1RL",
    "wof:placetype":"postalcode"
},
  "geometry": {"coordinates":[-1.78256918950361,51.58038191230782],"type":"Point"}
}