{
  "type": "Feature",
  "properties": {
    "iso:country":"GB",
    "wof:name":"BH24 2EY",
    "wof:placetype":"postalcode"
},
  "geometry": {"coordinates":[-1.8345318563049,50.84169952318845],"type":"Point"}
}