{
  "type": "Feature",
  "properties": {
    "date:inception_lower":"1980-01-01",
    "date:inception_upper":"1980-01-31",
    "iso:country":"GB",
    "wof:name":"BH24 2EY",
    "wof:placetype":"postalcode"
},
  "geometry": {"coordinates":[-1.834532,50.8417],"type":"Point"}
}