{
  "type": "Feature",
  "properties": {
    "date:inception_lower":"1994-12-01",
    "date:inception_upper":"1994-12-31",
    "iso:country":"GB",
    "wof:name":"CR0 6YH",
    "wof:placetype":"postalcode"
},
  "geometry": {"coordinates":[-0.076433,51.390077],"type":"Point"}
}