{
  "type": "Feature",
  "properties": {
    "iso:country":"GB",
    "wof:name":"CW2 6JR",
    "wof:placetype":"postalcode"
},
  "geometry": {"coordinates":[-2.44615535224613,53.08549346311187],"type":"Point"}
}