{
  "type": "Feature",
  "properties": {
    "iso:country": "GB",
    "wof:name": "L8 3TP",
    "wof:placetype": "postalcode"
  },
  "geometry": {"coordinates":[-2.960639,53.387373],"type":"Point"}
}
