{
  "type": "Feature",
  "properties": {
    "date:inception_lower": "1987-04-01",
    "date:inception_upper": "1987-04-01",
    "iso:country": "GB",
    "wof:name": "GU14 0PX",
    "wof:placetype": "postalcode"
  },
  "geometry": {"coordinates":[-0.78957,51.289189],"type":"Point"}
}
