{
  "type": "Feature",
  "properties": {
    "date:inception_lower":"1980-01-01",
    "date:inception_upper":"1980-01-31",
    "iso:country":"GB",
    "wof:name":"HD6 2NU",
    "wof:placetype":"postalcode"
},
  "geometry": {"coordinates":[-1.797248,53.714415],"type":"Point"}
}