{
  "type": "Feature",
  "properties": {
    "iso:country":"GB",
    "wof:name":"HD6 2NU",
    "wof:placetype":"postalcode"
},
  "geometry": {"coordinates":[-1.7972482825346,53.71441471421457],"type":"Point"}
}