{
  "type": "Feature",
  "properties": {
    "date:inception_lower": "1980-01-01",
    "date:inception_upper": "1980-01-01",
    "iso:country": "GB",
    "wof:name": "SY6 6RA",
    "wof:placetype": "postalcode"
  },
  "geometry": {"coordinates":[-2.818283,52.530736],"type":"Point"}
}
