{
  "type": "Feature",
  "properties": {
    "iso:country":"GB",
    "wof:name":"SY6 6RA",
    "wof:placetype":"postalcode"
},
  "geometry": {"coordinates":[-2.81828392775873,52.53072097437416],"type":"Point"}
}