{
  "type": "Feature",
  "properties": {
    "date:inception_lower":"1980-01-01",
    "date:inception_upper":"1980-01-31",
    "iso:country":"GB",
    "wof:name":"G44 3XF",
    "wof:placetype":"postalcode"
},
  "geometry": {"coordinates":[-4.266652,55.79877],"type":"Point"}
}