{
  "type": "Feature",
  "properties": {
    "iso:country":"GB",
    "wof:name":"IP9 2ST",
    "wof:placetype":"postalcode"
},
  "geometry": {"coordinates":[1.11957202276219,51.9721233802499],"type":"Point"}
}