{
  "type": "Feature",
  "properties": {
    "iso:country": "GB",
    "wof:name": "IP9 2ST",
    "wof:placetype": "postalcode"
  },
  "geometry": {"coordinates":[1.119572,51.972123],"type":"Point"}
}
