{
  "type": "Feature",
  "properties": {
    "iso:country":"GB",
    "wof:name":"PE1 4LU",
    "wof:placetype":"postalcode"
},
  "geometry": {"coordinates":[-0.23280395768744,52.5974227251223],"type":"Point"}
}