{
  "type": "Feature",
  "properties": {
    "iso:country": "GB",
    "wof:name": "GL4 4TD",
    "wof:placetype": "postalcode"
  },
  "geometry": {"coordinates":[-2.21795,51.846986],"type":"Point"}
}
