{
  "type": "Feature",
  "properties": {
    "iso:country":"GB",
    "wof:name":"GL4 4TD",
    "wof:placetype":"postalcode"
},
  "geometry": {"coordinates":[-2.21794985433079,51.84698552913156],"type":"Point"}
}