{
  "type": "Feature",
  "properties": {
    "iso:country":"GB",
    "wof:name":"GL7 4BB",
    "wof:placetype":"postalcode"
},
  "geometry": {"coordinates":[-1.7781808825688,51.7081124947255],"type":"Point"}
}