{
  "type": "Feature",
  "properties": {
    "iso:country":"GB",
    "wof:name":"GU51 2RP",
    "wof:placetype":"postalcode"
},
  "geometry": {"coordinates":[-0.82583307161309,51.2916084719309],"type":"Point"}
}