{
  "type": "Feature",
  "properties": {
    "iso:country": "GB",
    "wof:name": "GU51 2RP",
    "wof:placetype": "postalcode"
  },
  "geometry": {"coordinates":[-0.825833,51.291608],"type":"Point"}
}
