{
  "type": "Feature",
  "properties": {
    "date:inception_lower": "1981-12-01",
    "date:inception_upper": "1981-12-01",
    "iso:country": "GB",
    "wof:name": "PA6 7NA",
    "wof:placetype": "postalcode"
  },
  "geometry": {"coordinates":[-4.523609,55.856275],"type":"Point"}
}
