{
  "type": "Feature",
  "properties": {
    "iso:country":"GB",
    "wof:name":"PA6 7NA",
    "wof:placetype":"postalcode"
},
  "geometry": {"coordinates":[-4.52360937891647,55.85627485833872],"type":"Point"}
}