{
  "type": "Feature",
  "properties": {
    "iso:country": "GB",
    "wof:name": "PA6 7NA",
    "wof:placetype": "postalcode"
  },
  "geometry": {"coordinates":[-4.523609,55.856275],"type":"Point"}
}
