{
  "type": "Feature",
  "properties": {
    "iso:country":"GB",
    "wof:name":"LA12 9AY",
    "wof:placetype":"postalcode"
},
  "geometry": {"coordinates":[-3.0838517539949,54.1959255381379],"type":"Point"}
}