{
  "type": "Feature",
  "properties": {
    "iso:country":"GB",
    "wof:name":"MK43 8GB",
    "wof:placetype":"postalcode"
},
  "geometry": {"coordinates":[-0.54683970165935,52.15209561795403],"type":"Point"}
}