{
  "type": "Feature",
  "properties": {
    "iso:country":"GB",
    "wof:name":"EX1 2EH",
    "wof:placetype":"postalcode"
},
  "geometry": {"coordinates":[-3.51544020722832,50.72523181479423],"type":"Point"}
}