{
  "type": "Feature",
  "properties": {
    "date:inception_lower": "1980-01-01",
    "date:inception_upper": "1980-01-01",
    "iso:country": "GB",
    "wof:name": "AL6 0SF",
    "wof:placetype": "postalcode"
  },
  "geometry": {"coordinates":[-0.183411,51.842441],"type":"Point"}
}
