{
  "type": "Feature",
  "properties": {
    "date:inception_lower": "1995-12-01",
    "date:inception_upper": "1995-12-01",
    "iso:country": "GB",
    "wof:name": "ZE1 0LY",
    "wof:placetype": "postalcode"
  },
  "geometry": {"coordinates":[-1.17155,60.144613],"type":"Point"}
}
