{
  "type": "Feature",
  "properties": {
    "iso:country":"GB",
    "wof:name":"LL74 8RH",
    "wof:placetype":"postalcode"
},
  "geometry": {"coordinates":[-4.23996118227191,53.31513130301372],"type":"Point"}
}