{
  "type": "Feature",
  "properties": {
    "date:inception_lower":"1980-01-01",
    "date:inception_upper":"1980-01-31",
    "iso:country":"GB",
    "wof:name":"IG1 4AF",
    "wof:placetype":"postalcode"
},
  "geometry": {"coordinates":[0.083767,51.565251],"type":"Point"}
}