{
  "type": "Feature",
  "properties": {
    "iso:country":"GB",
    "wof:name":"CR3 5AF",
    "wof:placetype":"postalcode"
},
  "geometry": {"coordinates":[-0.12001329946526,51.28373424282709],"type":"Point"}
}