{
  "type": "Feature",
  "properties": {
    "iso:country":"GB",
    "wof:name":"SG13 8PL",
    "wof:placetype":"postalcode"
},
  "geometry": {"coordinates":[-0.10162960971739,51.75963755380333],"type":"Point"}
}