{
  "type": "Feature",
  "properties": {
    "iso:country": "GB",
    "wof:name": "TW5 0TD",
    "wof:placetype": "postalcode"
  },
  "geometry": {"coordinates":[-0.363248,51.480257],"type":"Point"}
}
