{
  "type": "Feature",
  "properties": {
    "iso:country":"GB",
    "wof:name":"TW5 0TD",
    "wof:placetype":"postalcode"
},
  "geometry": {"coordinates":[-0.36324841688355,51.48025738303636],"type":"Point"}
}