{
  "type": "Feature",
  "properties": {
    "iso:country": "GB",
    "wof:name": "BL9 9TN",
    "wof:placetype": "postalcode"
  },
  "geometry": {"coordinates":[-2.292162,53.563424],"type":"Point"}
}
