{
  "type": "Feature",
  "properties": {
    "date:inception_lower":"1980-01-01",
    "date:inception_upper":"1980-01-31",
    "iso:country":"GB",
    "wof:name":"BL9 9TN",
    "wof:placetype":"postalcode"
},
  "geometry": {"coordinates":[-2.292162,53.563424],"type":"Point"}
}