{
  "type": "Feature",
  "properties": {
    "iso:country":"GB",
    "wof:name":"TW19 5DT",
    "wof:placetype":"postalcode"
},
  "geometry": {"coordinates":[-0.5645078354701,51.45810225369158],"type":"Point"}
}