{
  "type": "Feature",
  "properties": {
    "iso:country": "GB",
    "wof:name": "N9 0LH",
    "wof:placetype": "postalcode"
  },
  "geometry": {"coordinates":[-0.048109,51.624604],"type":"Point"}
}
