{
  "type": "Feature",
  "properties": {
    "iso:country":"GB",
    "wof:name":"KA8 9LW",
    "wof:placetype":"postalcode"
},
  "geometry": {"coordinates":[-4.6122038472691,55.47218612873669],"type":"Point"}
}