{
  "type": "Feature",
  "properties": {
    "date:inception_lower":"1999-12-01",
    "date:inception_upper":"1999-12-31",
    "iso:country":"GB",
    "wof:name":"CV47 8FH",
    "wof:placetype":"postalcode"
},
  "geometry": {"coordinates":[-1.319906,52.247567],"type":"Point"}
}