{
  "type": "Feature",
  "properties": {
    "iso:country": "GB",
    "wof:name": "ST11 9LD",
    "wof:placetype": "postalcode"
  },
  "geometry": {"coordinates":[-2.06898,52.964103],"type":"Point"}
}
