{
  "type": "Feature",
  "properties": {
    "iso:country":"GB",
    "wof:name":"W11 4BP",
    "wof:placetype":"postalcode"
},
  "geometry": {"coordinates":[-0.21453891745947,51.51235763999435],"type":"Point"}
}