{
  "type": "Feature",
  "properties": {
    "iso:country":"GB",
    "wof:name":"NW10 5DL",
    "wof:placetype":"postalcode"
},
  "geometry": {"coordinates":[-0.22097439513958,51.52990968558294],"type":"Point"}
}