{
  "type": "Feature",
  "properties": {
    "iso:country": "GB",
    "wof:name": "KA6 7JZ",
    "wof:placetype": "postalcode"
  },
  "geometry": {"coordinates":[-4.496895,55.35981],"type":"Point"}
}
