{
  "type": "Feature",
  "properties": {
    "date:inception_lower": "1980-01-01",
    "date:inception_upper": "1980-01-01",
    "iso:country": "GB",
    "wof:name": "KA6 7JZ",
    "wof:placetype": "postalcode"
  },
  "geometry": {"coordinates":[-4.496895,55.35981],"type":"Point"}
}
