{
  "type": "Feature",
  "properties": {
    "date:inception_lower": "1980-01-01",
    "date:inception_upper": "1980-01-01",
    "iso:country": "GB",
    "wof:name": "WS10 0HF",
    "wof:placetype": "postalcode"
  },
  "geometry": {"coordinates":[-2.000305,52.555825],"type":"Point"}
}
