{
  "type": "Feature",
  "properties": {
    "iso:country":"GB",
    "wof:name":"WS10 0HF",
    "wof:placetype":"postalcode"
},
  "geometry": {"coordinates":[-2.00036957600673,52.55565720684348],"type":"Point"}
}