{
  "type": "Feature",
  "properties": {
    "iso:country":"GB",
    "wof:name":"L20 6GG",
    "wof:placetype":"postalcode"
},
  "geometry": {"coordinates":[-2.99223374018873,53.46378101915554],"type":"Point"}
}