{
  "type": "Feature",
  "properties": {
    "date:inception_lower": "2011-08-01",
    "date:inception_upper": "2011-08-01",
    "iso:country": "GB",
    "wof:name": "L20 6GG",
    "wof:placetype": "postalcode"
  },
  "geometry": {"coordinates":[-2.992234,53.463781],"type":"Point"}
}
