{
  "type": "Feature",
  "properties": {
    "iso:country": "GB",
    "wof:name": "RG31 7PD",
    "wof:placetype": "postalcode"
  },
  "geometry": {"coordinates":[-1.029875,51.44089],"type":"Point"}
}
