{
  "type": "Feature",
  "properties": {
    "iso:country":"GB",
    "wof:name":"RG31 7PD",
    "wof:placetype":"postalcode"
},
  "geometry": {"coordinates":[-1.02987468155414,51.4408903716842],"type":"Point"}
}