{
  "type": "Feature",
  "properties": {
    "iso:country":"GB",
    "wof:name":"DG1 1QR",
    "wof:placetype":"postalcode"
},
  "geometry": {"coordinates":[-3.58672706748595,55.11006390239711],"type":"Point"}
}