{
  "type": "Feature",
  "properties": {
    "iso:country": "GB",
    "wof:name": "ST6 1ED",
    "wof:placetype": "postalcode"
  },
  "geometry": {"coordinates":[-2.188129,53.046251],"type":"Point"}
}
