{
  "type": "Feature",
  "properties": {
    "date:inception_lower": "2023-04-01",
    "date:inception_upper": "2023-04-01",
    "iso:country": "GB",
    "wof:name": "SG16 6PG",
    "wof:placetype": "postalcode"
  },
  "geometry": {"coordinates":[-0.304906,52.006738],"type":"Point"}
}
