{
  "type": "Feature",
  "properties": {
    "iso:country": "GB",
    "wof:name": "IP25 7NB",
    "wof:placetype": "postalcode"
  },
  "geometry": {"coordinates":[0.909654,52.63374],"type":"Point"}
}
