{
  "type": "Feature",
  "properties": {
    "date:inception_lower": "1980-01-01",
    "date:inception_upper": "1980-01-01",
    "iso:country": "GB",
    "wof:name": "IP25 7NB",
    "wof:placetype": "postalcode"
  },
  "geometry": {"coordinates":[0.909654,52.63374],"type":"Point"}
}
