{
  "type": "Feature",
  "properties": {
    "iso:country":"GB",
    "wof:name":"IP25 7NB",
    "wof:placetype":"postalcode"
},
  "geometry": {"coordinates":[0.90965363467565,52.63373995536998],"type":"Point"}
}