{
  "type": "Feature",
  "properties": {
    "iso:country": "GB",
    "wof:name": "BS24 7JH",
    "wof:placetype": "postalcode"
  },
  "geometry": {"coordinates":[-2.93066,51.348014],"type":"Point"}
}
