{
  "type": "Feature",
  "properties": {
    "iso:country":"GB",
    "wof:name":"PE13 5QN",
    "wof:placetype":"postalcode"
},
  "geometry": {"coordinates":[0.13129948911173,52.74018148345446],"type":"Point"}
}