{
  "type": "Feature",
  "properties": {
    "date:inception_lower":"1980-01-01",
    "date:inception_upper":"1980-01-31",
    "iso:country":"GB",
    "wof:name":"PE13 5QN",
    "wof:placetype":"postalcode"
},
  "geometry": {"coordinates":[0.131314,52.740201],"type":"Point"}
}