{
  "type": "Feature",
  "properties": {
    "date:inception_lower": "1990-02-01",
    "date:inception_upper": "1990-02-01",
    "iso:country": "GB",
    "wof:name": "WN8 6UL",
    "wof:placetype": "postalcode"
  },
  "geometry": {"coordinates":[-2.77742,53.56573],"type":"Point"}
}
