{
  "type": "Feature",
  "properties": {
    "iso:country": "GB",
    "wof:name": "GL4 4SG",
    "wof:placetype": "postalcode"
  },
  "geometry": {"coordinates":[-2.21493,51.850657],"type":"Point"}
}
