{
  "type": "Feature",
  "properties": {
    "date:inception_lower": "2016-11-01",
    "date:inception_upper": "2016-11-01",
    "iso:country": "GB",
    "wof:name": "GL4 4SG",
    "wof:placetype": "postalcode"
  },
  "geometry": {"coordinates":[-2.214552,51.850658],"type":"Point"}
}
