{
  "type": "Feature",
  "properties": {
    "iso:country":"GB",
    "wof:name":"BN6 9AH",
    "wof:placetype":"postalcode"
},
  "geometry": {"coordinates":[-0.16394816899122,50.93413459654244],"type":"Point"}
}