{
  "type": "Feature",
  "properties": {
    "date:inception_lower": "1990-08-01",
    "date:inception_upper": "1990-08-01",
    "iso:country": "GB",
    "wof:name": "AB41 8HQ",
    "wof:placetype": "postalcode"
  },
  "geometry": {"coordinates":[-1.977745,57.414904],"type":"Point"}
}
