{
  "type": "Feature",
  "properties": {
    "iso:country":"GB",
    "wof:name":"PR9 7DT",
    "wof:placetype":"postalcode"
},
  "geometry": {"coordinates":[-2.97926904965866,53.65153618464399],"type":"Point"}
}