{
  "type": "Feature",
  "properties": {
    "iso:country":"GB",
    "wof:name":"BS40 8RN",
    "wof:placetype":"postalcode"
},
  "geometry": {"coordinates":[-2.6062827717526,51.36766764176239],"type":"Point"}
}