{
  "type": "Feature",
  "properties": {
    "date:inception_lower":"1997-12-01",
    "date:inception_upper":"1997-12-31",
    "iso:country":"GB",
    "wof:name":"BS40 8RN",
    "wof:placetype":"postalcode"
},
  "geometry": {"coordinates":[-2.606283,51.367668],"type":"Point"}
}