{
  "type": "Feature",
  "properties": {
    "iso:country": "GB",
    "wof:name": "LS8 2LL",
    "wof:placetype": "postalcode"
  },
  "geometry": {"coordinates":[-1.483464,53.839774],"type":"Point"}
}
