{
  "type": "Feature",
  "properties": {
    "iso:country":"GB",
    "wof:name":"LS8 2LL",
    "wof:placetype":"postalcode"
},
  "geometry": {"coordinates":[-1.483464541781,53.83977431491216],"type":"Point"}
}