{
  "type": "Feature",
  "properties": {
    "iso:country":"GB",
    "wof:name":"LU5 5JL",
    "wof:placetype":"postalcode"
},
  "geometry": {"coordinates":[-0.51666510848957,51.91217183081233],"type":"Point"}
}