{
  "type": "Feature",
  "properties": {
    "date:inception_lower": "1996-06-01",
    "date:inception_upper": "1996-06-01",
    "iso:country": "GB",
    "wof:name": "PR4 0NZ",
    "wof:placetype": "postalcode"
  },
  "geometry": {"coordinates":[-2.760966,53.783596],"type":"Point"}
}
