{
  "type": "Feature",
  "properties": {
    "iso:country":"GB",
    "wof:name":"NP7 9AD",
    "wof:placetype":"postalcode"
},
  "geometry": {"coordinates":[-3.00017057926188,51.79625096393762],"type":"Point"}
}