{
  "type": "Feature",
  "properties": {
    "date:inception_lower":"1980-01-01",
    "date:inception_upper":"1980-01-31",
    "iso:country":"GB",
    "wof:name":"NP7 9AD",
    "wof:placetype":"postalcode"
},
  "geometry": {"coordinates":[-3.000177,51.796255],"type":"Point"}
}