{
  "type": "Feature",
  "properties": {
    "date:inception_lower":"1980-03-01",
    "date:inception_upper":"1980-03-31",
    "iso:country":"GB",
    "wof:name":"IV30 1XZ",
    "wof:placetype":"postalcode"
},
  "geometry": {"coordinates":[-3.292208,57.648844],"type":"Point"}
}