{
  "type": "Feature",
  "properties": {
    "iso:country": "GB",
    "wof:name": "IV30 1XZ",
    "wof:placetype": "postalcode"
  },
  "geometry": {"coordinates":[-3.292208,57.648844],"type":"Point"}
}
