{
  "type": "Feature",
  "properties": {
    "iso:country":"GB",
    "wof:name":"SM1 4DT",
    "wof:placetype":"postalcode"
},
  "geometry": {"coordinates":[-0.19037307670008,51.36886183539177],"type":"Point"}
}