{
  "type": "Feature",
  "properties": {
    "iso:country": "GB",
    "wof:name": "SM1 4DT",
    "wof:placetype": "postalcode"
  },
  "geometry": {"coordinates":[-0.190373,51.368862],"type":"Point"}
}
