{
  "type": "Feature",
  "properties": {
    "iso:country":"GB",
    "wof:name":"PH2 9QD",
    "wof:placetype":"postalcode"
},
  "geometry": {"coordinates":[-3.3611132756811,56.28080053946491],"type":"Point"}
}