{
  "type": "Feature",
  "properties": {
    "iso:country":"GB",
    "wof:name":"NW2 4HJ",
    "wof:placetype":"postalcode"
},
  "geometry": {"coordinates":[-0.20845404287587,51.54989807178539],"type":"Point"}
}