{
  "type": "Feature",
  "properties": {
    "date:inception_lower": "1980-01-01",
    "date:inception_upper": "1980-01-01",
    "iso:country": "GB",
    "wof:name": "NW2 4HJ",
    "wof:placetype": "postalcode"
  },
  "geometry": {"coordinates":[-0.208454,51.549898],"type":"Point"}
}
