{
  "type": "Feature",
  "properties": {
    "iso:country": "GB",
    "wof:name": "LS14 6FU",
    "wof:placetype": "postalcode"
  },
  "geometry": {"coordinates":[-1.475346,53.805097],"type":"Point"}
}
