{
  "type": "Feature",
  "properties": {
    "iso:country":"GB",
    "wof:name":"NG1 1QN",
    "wof:placetype":"postalcode"
},
  "geometry": {"coordinates":[-1.14433968102422,52.95175959603503],"type":"Point"}
}