{
  "type": "Feature",
  "properties": {
    "date:inception_lower":"1980-01-01",
    "date:inception_upper":"1980-01-31",
    "iso:country":"GB",
    "wof:name":"NP4 9EZ",
    "wof:placetype":"postalcode"
},
  "geometry": {"coordinates":[-3.083165,51.773505],"type":"Point"}
}