{
  "type": "Feature",
  "properties": {
    "date:inception_lower": "2005-01-01",
    "date:inception_upper": "2005-01-01",
    "iso:country": "GB",
    "wof:name": "LL28 4RR",
    "wof:placetype": "postalcode"
  },
  "geometry": {"coordinates":[-3.742072,53.309986],"type":"Point"}
}
