{
  "type": "Feature",
  "properties": {
    "iso:country":"GB",
    "wof:name":"LL28 4RR",
    "wof:placetype":"postalcode"
},
  "geometry": {"coordinates":[-3.74207202703584,53.30998643524516],"type":"Point"}
}