{
  "type": "Feature",
  "properties": {
    "iso:country":"GB",
    "wof:name":"OX1 1BD",
    "wof:placetype":"postalcode"
},
  "geometry": {"coordinates":[-1.25762622689662,51.75148273171844],"type":"Point"}
}