{
  "type": "Feature",
  "properties": {
    "date:inception_lower":"1990-07-01",
    "date:inception_upper":"1990-07-31",
    "iso:country":"GB",
    "wof:name":"OX1 1BD",
    "wof:placetype":"postalcode"
},
  "geometry": {"coordinates":[-1.257626,51.751483],"type":"Point"}
}