{
  "type": "Feature",
  "properties": {
    "date:inception_lower":"1980-01-01",
    "date:inception_upper":"1980-01-31",
    "iso:country":"GB",
    "wof:name":"YO18 7HZ",
    "wof:placetype":"postalcode"
},
  "geometry": {"coordinates":[-0.763705,54.239951],"type":"Point"}
}