{
  "type": "Feature",
  "properties": {
    "iso:country":"GB",
    "wof:name":"GL7 3FB",
    "wof:placetype":"postalcode"
},
  "geometry": {"coordinates":[-1.69547768760311,51.69435975540689],"type":"Point"}
}