{
  "type": "Feature",
  "properties": {
    "iso:country": "GB",
    "wof:name": "GL7 3FB",
    "wof:placetype": "postalcode"
  },
  "geometry": {"coordinates":[-1.695478,51.69436],"type":"Point"}
}
