{
  "type": "Feature",
  "properties": {
    "date:inception_lower":"2000-06-01",
    "date:inception_upper":"2000-06-30",
    "iso:country":"GB",
    "wof:name":"GL7 3FB",
    "wof:placetype":"postalcode"
},
  "geometry": {"coordinates":[-1.695478,51.69436],"type":"Point"}
}