{
  "type": "Feature",
  "properties": {
    "date:inception_lower":"2010-09-01",
    "date:inception_upper":"2010-09-30",
    "iso:country":"GB",
    "wof:name":"CF35 6SY",
    "wof:placetype":"postalcode"
},
  "geometry": {"coordinates":[-3.498355,51.526216],"type":"Point"}
}