{
  "type": "Feature",
  "properties": {
    "iso:country":"GB",
    "wof:name":"CF35 6SY",
    "wof:placetype":"postalcode"
},
  "geometry": {"coordinates":[-3.49835514945981,51.52621598674541],"type":"Point"}
}