{
  "type": "Feature",
  "properties": {
    "date:inception_lower": "1980-01-01",
    "date:inception_upper": "1980-01-01",
    "iso:country": "GB",
    "wof:name": "SR5 3PN",
    "wof:placetype": "postalcode"
  },
  "geometry": {"coordinates":[-1.447878,54.922908],"type":"Point"}
}
