{
  "type": "Feature",
  "properties": {
    "iso:country": "GB",
    "wof:name": "G84 9PH",
    "wof:placetype": "postalcode"
  },
  "geometry": {"coordinates":[-4.74524,56.011274],"type":"Point"}
}
