{
  "type": "Feature",
  "properties": {
    "iso:country":"GB",
    "wof:name":"CF82 7RX",
    "wof:placetype":"postalcode"
},
  "geometry": {"coordinates":[-3.21916824616997,51.64571434651761],"type":"Point"}
}