{
  "type": "Feature",
  "properties": {
    "iso:country": "GB",
    "wof:name": "NN12 8EJ",
    "wof:placetype": "postalcode"
  },
  "geometry": {"coordinates":[-1.054068,52.130371],"type":"Point"}
}
