{
  "type": "Feature",
  "properties": {
    "iso:country":"GB",
    "wof:name":"NN12 8EJ",
    "wof:placetype":"postalcode"
},
  "geometry": {"coordinates":[-1.05406804988698,52.13037081808891],"type":"Point"}
}