{
  "type": "Feature",
  "properties": {
    "iso:country":"GB",
    "wof:name":"PO33 1JD",
    "wof:placetype":"postalcode"
},
  "geometry": {"coordinates":[-1.15479628280795,50.73061960507188],"type":"Point"}
}