{
  "type": "Feature",
  "properties": {
    "iso:country":"GB",
    "wof:name":"LD1 6HG",
    "wof:placetype":"postalcode"
},
  "geometry": {"coordinates":[-3.46926492083264,52.25144816979785],"type":"Point"}
}