{
  "type": "Feature",
  "properties": {
    "iso:country": "GB",
    "wof:name": "LD1 6HG",
    "wof:placetype": "postalcode"
  },
  "geometry": {"coordinates":[-3.470254,52.251914],"type":"Point"}
}
