{
  "type": "Feature",
  "properties": {
    "iso:country": "GB",
    "wof:name": "G65 0GZ",
    "wof:placetype": "postalcode"
  },
  "geometry": {"coordinates":[-4.046676,55.979628],"type":"Point"}
}
