{
  "type": "Feature",
  "properties": {
    "date:inception_lower":"2011-02-01",
    "date:inception_upper":"2011-02-28",
    "iso:country":"GB",
    "wof:name":"G65 0GZ",
    "wof:placetype":"postalcode"
},
  "geometry": {"coordinates":[-4.046676,55.979628],"type":"Point"}
}