{
  "type": "Feature",
  "properties": {
    "iso:country":"GB",
    "wof:name":"G65 0GZ",
    "wof:placetype":"postalcode"
},
  "geometry": {"coordinates":[-4.04683101695208,55.97953584197939],"type":"Point"}
}