{
  "type": "Feature",
  "properties": {
    "iso:country":"GB",
    "wof:name":"SW16 5DQ",
    "wof:placetype":"postalcode"
},
  "geometry": {"coordinates":[-0.12724116250749,51.41509924383583],"type":"Point"}
}