{
  "type": "Feature",
  "properties": {
    "iso:country": "GB",
    "wof:name": "SW16 5DQ",
    "wof:placetype": "postalcode"
  },
  "geometry": {"coordinates":[-0.127241,51.415099],"type":"Point"}
}
