{
  "type": "Feature",
  "properties": {
    "iso:country":"GB",
    "wof:name":"S41 7LZ",
    "wof:placetype":"postalcode"
},
  "geometry": {"coordinates":[-1.42435374110845,53.24509760961676],"type":"Point"}
}