{
  "type": "Feature",
  "properties": {
    "iso:country":"GB",
    "wof:name":"BS7 0BA",
    "wof:placetype":"postalcode"
},
  "geometry": {"coordinates":[-2.57534360583803,51.49378803857423],"type":"Point"}
}