{
  "type": "Feature",
  "properties": {
    "iso:country": "GB",
    "wof:name": "PR4 1JU",
    "wof:placetype": "postalcode"
  },
  "geometry": {"coordinates":[-2.868317,53.769691],"type":"Point"}
}
