{
  "type": "Feature",
  "properties": {
    "iso:country": "GB",
    "wof:name": "M33 5UL",
    "wof:placetype": "postalcode"
  },
  "geometry": {"coordinates":[-2.339076,53.422406],"type":"Point"}
}
