{
  "type": "Feature",
  "properties": {
    "iso:country":"GB",
    "wof:name":"M33 5UL",
    "wof:placetype":"postalcode"
},
  "geometry": {"coordinates":[-2.33907561973338,53.42240642852743],"type":"Point"}
}