{
  "type": "Feature",
  "properties": {
    "iso:country":"GB",
    "wof:name":"CM6 1XD",
    "wof:placetype":"postalcode"
},
  "geometry": {"coordinates":[0.36809956621869,51.86817837876231],"type":"Point"}
}