{
  "type": "Feature",
  "properties": {
    "iso:country": "GB",
    "wof:name": "KT14 7AJ",
    "wof:placetype": "postalcode"
  },
  "geometry": {"coordinates":[-0.480935,51.342253],"type":"Point"}
}
