{
  "type": "Feature",
  "properties": {
    "iso:country":"GB",
    "wof:name":"KT14 7AJ",
    "wof:placetype":"postalcode"
},
  "geometry": {"coordinates":[-0.48093547089247,51.34225343431043],"type":"Point"}
}