{
  "type": "Feature",
  "properties": {
    "iso:country": "GB",
    "wof:name": "EX1 9SA",
    "wof:placetype": "postalcode"
  },
  "geometry": {"coordinates":[-3.524465,50.724762],"type":"Point"}
}
