{
  "type": "Feature",
  "properties": {
    "date:inception_lower":"2005-02-01",
    "date:inception_upper":"2005-02-28",
    "iso:country":"GB",
    "wof:name":"EX1 9SA",
    "wof:placetype":"postalcode"
},
  "geometry": {"coordinates":[-3.524465,50.724762],"type":"Point"}
}