{
  "type": "Feature",
  "properties": {
    "iso:country":"GB",
    "wof:name":"W10 6JE",
    "wof:placetype":"postalcode"
},
  "geometry": {"coordinates":[-0.21347819118366,51.51736825249382],"type":"Point"}
}