{
  "type": "Feature",
  "properties": {
    "iso:country":"GB",
    "wof:name":"BD2 2LT",
    "wof:placetype":"postalcode"
},
  "geometry": {"coordinates":[-1.72975745806071,53.82162569962221],"type":"Point"}
}