{
  "type": "Feature",
  "properties": {
    "iso:country":"GB",
    "wof:name":"EX5 5ES",
    "wof:placetype":"postalcode"
},
  "geometry": {"coordinates":[-3.55441750025497,50.75562848141257],"type":"Point"}
}