{
  "type": "Feature",
  "properties": {
    "iso:country": "GB",
    "wof:name": "EX5 5ES",
    "wof:placetype": "postalcode"
  },
  "geometry": {"coordinates":[-3.554417,50.755628],"type":"Point"}
}
