{
  "type": "Feature",
  "properties": {
    "iso:country":"GB",
    "wof:name":"BD23 3BD",
    "wof:placetype":"postalcode"
},
  "geometry": {"coordinates":[-2.08203620394985,53.93768254462835],"type":"Point"}
}