{
  "type": "Feature",
  "properties": {
    "iso:country":"GB",
    "wof:name":"DH8 5TA",
    "wof:placetype":"postalcode"
},
  "geometry": {"coordinates":[-1.84243435909883,54.85843133738108],"type":"Point"}
}