{
  "type": "Feature",
  "properties": {
    "date:inception_lower":"2002-06-01",
    "date:inception_upper":"2002-06-30",
    "iso:country":"GB",
    "wof:name":"NR7 0GR",
    "wof:placetype":"postalcode"
},
  "geometry": {"coordinates":[1.369037,52.627834],"type":"Point"}
}