{
  "type": "Feature",
  "properties": {
    "iso:country":"GB",
    "wof:name":"NR7 0GR",
    "wof:placetype":"postalcode"
},
  "geometry": {"coordinates":[1.3690373556198,52.62783450492763],"type":"Point"}
}