{
  "type": "Feature",
  "properties": {
    "iso:country": "GB",
    "wof:name": "NR7 0GR",
    "wof:placetype": "postalcode"
  },
  "geometry": {"coordinates":[1.369037,52.627834],"type":"Point"}
}
