{
  "type": "Feature",
  "properties": {
    "iso:country": "GB",
    "wof:name": "TA11 6BQ",
    "wof:placetype": "postalcode"
  },
  "geometry": {"coordinates":[-2.748098,51.053296],"type":"Point"}
}
