{
  "type": "Feature",
  "properties": {
    "date:inception_lower":"1993-01-01",
    "date:inception_upper":"1993-01-31",
    "iso:country":"GB",
    "wof:name":"LS28 8PW",
    "wof:placetype":"postalcode"
},
  "geometry": {"coordinates":[-1.66522,53.786428],"type":"Point"}
}