{
  "type": "Feature",
  "properties": {
    "iso:country":"GB",
    "wof:name":"LL15 1LN",
    "wof:placetype":"postalcode"
},
  "geometry": {"coordinates":[-3.32069404112324,53.11243223013914],"type":"Point"}
}