{
  "type": "Feature",
  "properties": {
    "iso:country":"GB",
    "wof:name":"LD4 4AP",
    "wof:placetype":"postalcode"
},
  "geometry": {"coordinates":[-3.55507937669606,52.14617644931283],"type":"Point"}
}