{
  "type": "Feature",
  "properties": {
    "iso:country":"GB",
    "wof:name":"B94 5SD",
    "wof:placetype":"postalcode"
},
  "geometry": {"coordinates":[-1.84244024060896,52.35947181504316],"type":"Point"}
}