{
  "type": "Feature",
  "properties": {
    "iso:country":"GB",
    "wof:name":"LA3 1TB",
    "wof:placetype":"postalcode"
},
  "geometry": {"coordinates":[-2.88383948379519,54.06378515446511],"type":"Point"}
}