{
  "type": "Feature",
  "properties": {
    "date:inception_lower":"2012-04-01",
    "date:inception_upper":"2012-04-30",
    "iso:country":"GB",
    "wof:name":"LA3 1TB",
    "wof:placetype":"postalcode"
},
  "geometry": {"coordinates":[-2.883839,54.063785],"type":"Point"}
}