{
  "type": "Feature",
  "properties": {
    "iso:country":"GB",
    "wof:name":"HA7 1FX",
    "wof:placetype":"postalcode"
},
  "geometry": {"coordinates":[-0.29696966173293,51.60590707247835],"type":"Point"}
}