{
  "type": "Feature",
  "properties": {
    "date:inception_lower":"2012-05-01",
    "date:inception_upper":"2012-05-31",
    "iso:country":"GB",
    "wof:name":"HA7 1FX",
    "wof:placetype":"postalcode"
},
  "geometry": {"coordinates":[-0.29697,51.605907],"type":"Point"}
}