{
  "type": "Feature",
  "properties": {
    "iso:country": "GB",
    "wof:name": "L9 8AQ",
    "wof:placetype": "postalcode"
  },
  "geometry": {"coordinates":[-2.97028,53.462793],"type":"Point"}
}
