{
  "type": "Feature",
  "properties": {
    "date:inception_lower":"2008-01-01",
    "date:inception_upper":"2008-01-31",
    "iso:country":"GB",
    "wof:name":"RH11 7GS",
    "wof:placetype":"postalcode"
},
  "geometry": {"coordinates":[-0.194974,51.119904],"type":"Point"}
}