{
  "type": "Feature",
  "properties": {
    "date:inception_lower":"1998-06-01",
    "date:inception_upper":"1998-06-30",
    "iso:country":"GB",
    "wof:name":"YO26 8JR",
    "wof:placetype":"postalcode"
},
  "geometry": {"coordinates":[-1.2062,53.973423],"type":"Point"}
}