{
  "type": "Feature",
  "properties": {
    "iso:country": "GB",
    "wof:name": "YO26 8JR",
    "wof:placetype": "postalcode"
  },
  "geometry": {"coordinates":[-1.2062,53.973423],"type":"Point"}
}
