{
  "type": "Feature",
  "properties": {
    "iso:country":"GB",
    "wof:name":"SG11 1PW",
    "wof:placetype":"postalcode"
},
  "geometry": {"coordinates":[0.01858793093773,51.88403867366028],"type":"Point"}
}