{
  "type": "Feature",
  "properties": {
    "iso:country": "GB",
    "wof:name": "SG11 1PW",
    "wof:placetype": "postalcode"
  },
  "geometry": {"coordinates":[0.018617,51.884046],"type":"Point"}
}
