{
  "type": "Feature",
  "properties": {
    "date:inception_lower": "1986-06-01",
    "date:inception_upper": "1986-06-01",
    "iso:country": "GB",
    "wof:name": "G68 9BJ",
    "wof:placetype": "postalcode"
  },
  "geometry": {"coordinates":[-4.016383,55.948548],"type":"Point"}
}
