{
  "type": "Feature",
  "properties": {
    "iso:country":"GB",
    "wof:name":"S25 3PH",
    "wof:placetype":"postalcode"
},
  "geometry": {"coordinates":[-1.23007906347148,53.38029167263719],"type":"Point"}
}