{
  "type": "Feature",
  "properties": {
    "iso:country":"GB",
    "wof:name":"SA44 6PA",
    "wof:placetype":"postalcode"
},
  "geometry": {"coordinates":[-4.4873885997497,52.10757385482529],"type":"Point"}
}