{
  "type": "Feature",
  "properties": {
    "date:inception_lower": "1980-01-01",
    "date:inception_upper": "1980-01-01",
    "iso:country": "GB",
    "wof:name": "SA44 6PA",
    "wof:placetype": "postalcode"
  },
  "geometry": {"coordinates":[-4.487389,52.107574],"type":"Point"}
}
