{
  "type": "Feature",
  "properties": {
    "iso:country":"GB",
    "wof:name":"CV11 4QY",
    "wof:placetype":"postalcode"
},
  "geometry": {"coordinates":[-1.45803148790761,52.50535065395934],"type":"Point"}
}