{
  "type": "Feature",
  "properties": {
    "iso:country": "GB",
    "wof:name": "HU11 4NH",
    "wof:placetype": "postalcode"
  },
  "geometry": {"coordinates":[-0.145176,53.794946],"type":"Point"}
}
