{
  "type": "Feature",
  "properties": {
    "iso:country":"GB",
    "wof:name":"HU11 4NH",
    "wof:placetype":"postalcode"
},
  "geometry": {"coordinates":[-0.14516699599322,53.79492488276997],"type":"Point"}
}