{
  "type": "Feature",
  "properties": {
    "iso:country": "GB",
    "wof:name": "LN4 2HL",
    "wof:placetype": "postalcode"
  },
  "geometry": {"coordinates":[-0.540555,53.199079],"type":"Point"}
}
