{
  "type": "Feature",
  "properties": {
    "iso:country":"GB",
    "wof:name":"W1U 5LH",
    "wof:placetype":"postalcode"
},
  "geometry": {"coordinates":[-0.15341885508166,51.5216267688299],"type":"Point"}
}