{
  "type": "Feature",
  "properties": {
    "iso:country": "GB",
    "wof:name": "GU9 9TF",
    "wof:placetype": "postalcode"
  },
  "geometry": {"coordinates":[-0.772087,51.237041],"type":"Point"}
}
