{
  "type": "Feature",
  "properties": {
    "iso:country": "GB",
    "wof:name": "RM3 9XP",
    "wof:placetype": "postalcode"
  },
  "geometry": {"coordinates":[0.241587,51.608038],"type":"Point"}
}
