{
  "type": "Feature",
  "properties": {
    "iso:country":"GB",
    "wof:name":"RM3 9XP",
    "wof:placetype":"postalcode"
},
  "geometry": {"coordinates":[0.24161711400649,51.60798940890649],"type":"Point"}
}