{
  "type": "Feature",
  "properties": {
    "iso:country":"GB",
    "wof:name":"B46 2JX",
    "wof:placetype":"postalcode"
},
  "geometry": {"coordinates":[-1.65763710031069,52.51580514434833],"type":"Point"}
}