{
  "type": "Feature",
  "properties": {
    "iso:country": "GB",
    "wof:name": "NE66 5RA",
    "wof:placetype": "postalcode"
  },
  "geometry": {"coordinates":[-1.89571,55.551145],"type":"Point"}
}
