{
  "type": "Feature",
  "properties": {
    "iso:country":"GB",
    "wof:name":"NE66 5RA",
    "wof:placetype":"postalcode"
},
  "geometry": {"coordinates":[-1.89571013633983,55.5511453616007],"type":"Point"}
}