{
  "type": "Feature",
  "properties": {
    "iso:country":"GB",
    "wof:name":"KA30 8SR",
    "wof:placetype":"postalcode"
},
  "geometry": {"coordinates":[-4.87856130508228,55.80835084042653],"type":"Point"}
}