{
  "type": "Feature",
  "properties": {
    "date:inception_lower": "1986-11-01",
    "date:inception_upper": "1986-11-01",
    "iso:country": "GB",
    "wof:name": "KA30 8SR",
    "wof:placetype": "postalcode"
  },
  "geometry": {"coordinates":[-4.878561,55.808351],"type":"Point"}
}
