{
  "type": "Feature",
  "properties": {
    "iso:country": "GB",
    "wof:name": "KA30 8SR",
    "wof:placetype": "postalcode"
  },
  "geometry": {"coordinates":[-4.878561,55.808351],"type":"Point"}
}
