{
  "type": "Feature",
  "properties": {
    "date:inception_lower": "2001-12-01",
    "date:inception_upper": "2001-12-01",
    "iso:country": "GB",
    "wof:name": "SY11 2LQ",
    "wof:placetype": "postalcode"
  },
  "geometry": {"coordinates":[-3.036377,52.864546],"type":"Point"}
}
