{
  "type": "Feature",
  "properties": {
    "date:inception_lower": "1980-01-01",
    "date:inception_upper": "1980-01-01",
    "iso:country": "GB",
    "wof:name": "CT18 7BJ",
    "wof:placetype": "postalcode"
  },
  "geometry": {"coordinates":[1.164672,51.134126],"type":"Point"}
}
