{
  "type": "Feature",
  "properties": {
    "iso:country":"GB",
    "wof:name":"MK16 8LT",
    "wof:placetype":"postalcode"
},
  "geometry": {"coordinates":[-0.7613784219304,52.10063329209841],"type":"Point"}
}