{
  "type": "Feature",
  "properties": {
    "iso:country": "GB",
    "wof:name": "MK16 8LT",
    "wof:placetype": "postalcode"
  },
  "geometry": {"coordinates":[-0.761378,52.100633],"type":"Point"}
}
