{
  "type": "Feature",
  "properties": {
    "date:inception_lower":"1980-01-01",
    "date:inception_upper":"1980-01-31",
    "iso:country":"GB",
    "wof:name":"N16 5AW",
    "wof:placetype":"postalcode"
},
  "geometry": {"coordinates":[-0.081896,51.575046],"type":"Point"}
}