{
  "type": "Feature",
  "properties": {
    "iso:country":"GB",
    "wof:name":"ST17 4DU",
    "wof:placetype":"postalcode"
},
  "geometry": {"coordinates":[-2.11331209680136,52.79759544779809],"type":"Point"}
}