{
  "type": "Feature",
  "properties": {
    "iso:country":"GB",
    "wof:name":"HR2 0DP",
    "wof:placetype":"postalcode"
},
  "geometry": {"coordinates":[-2.91740555230953,51.93854595938344],"type":"Point"}
}