{
  "type": "Feature",
  "properties": {
    "date:inception_lower": "1980-01-01",
    "date:inception_upper": "1980-01-01",
    "iso:country": "GB",
    "wof:name": "HR2 0DP",
    "wof:placetype": "postalcode"
  },
  "geometry": {"coordinates":[-2.917406,51.938546],"type":"Point"}
}
