{
  "type": "Feature",
  "properties": {
    "iso:country":"GB",
    "wof:name":"NG8 2FD",
    "wof:placetype":"postalcode"
},
  "geometry": {"coordinates":[-1.24170165058652,52.95321150466703],"type":"Point"}
}