{
  "type": "Feature",
  "properties": {
    "iso:country":"GB",
    "wof:name":"TN38 0UE",
    "wof:placetype":"postalcode"
},
  "geometry": {"coordinates":[0.54415484868879,50.85993162156591],"type":"Point"}
}