{
  "type": "Feature",
  "properties": {
    "iso:country": "GB",
    "wof:name": "SE2 9ST",
    "wof:placetype": "postalcode"
  },
  "geometry": {"coordinates":[0.122021,51.495555],"type":"Point"}
}
