{
  "type": "Feature",
  "properties": {
    "iso:country":"GB",
    "wof:name":"SE2 9ST",
    "wof:placetype":"postalcode"
},
  "geometry": {"coordinates":[0.12202049885772,51.49555485687661],"type":"Point"}
}