{
  "type": "Feature",
  "properties": {
    "iso:country":"GB",
    "wof:name":"SA70 8TR",
    "wof:placetype":"postalcode"
},
  "geometry": {"coordinates":[-4.708462658202,51.69478355424004],"type":"Point"}
}