{
  "type": "Feature",
  "properties": {
    "iso:country": "GB",
    "wof:name": "SA70 8TR",
    "wof:placetype": "postalcode"
  },
  "geometry": {"coordinates":[-4.708522,51.694774],"type":"Point"}
}
