{
  "type": "Feature",
  "properties": {
    "iso:country":"GB",
    "wof:name":"PE8 5PH",
    "wof:placetype":"postalcode"
},
  "geometry": {"coordinates":[-0.45573879492654,52.45165280247614],"type":"Point"}
}