{
  "type": "Feature",
  "properties": {
    "date:inception_lower":"1994-05-01",
    "date:inception_upper":"1994-05-31",
    "iso:country":"GB",
    "wof:name":"LE8 9EH",
    "wof:placetype":"postalcode"
},
  "geometry": {"coordinates":[-1.026404,52.575903],"type":"Point"}
}