{
  "type": "Feature",
  "properties": {
    "iso:country":"GB",
    "wof:name":"LE8 9EH",
    "wof:placetype":"postalcode"
},
  "geometry": {"coordinates":[-1.02640391609634,52.57590273473846],"type":"Point"}
}