{
  "type": "Feature",
  "properties": {
    "iso:country":"GB",
    "wof:name":"IP24 2SQ",
    "wof:placetype":"postalcode"
},
  "geometry": {"coordinates":[0.8319037088285,52.37702031596525],"type":"Point"}
}