{
  "type": "Feature",
  "properties": {
    "date:inception_lower":"1980-01-01",
    "date:inception_upper":"1980-01-31",
    "iso:country":"GB",
    "wof:name":"PE4 6SG",
    "wof:placetype":"postalcode"
},
  "geometry": {"coordinates":[-0.262581,52.608733],"type":"Point"}
}