{
  "type": "Feature",
  "properties": {
    "date:inception_lower":"2007-10-01",
    "date:inception_upper":"2007-10-31",
    "iso:country":"GB",
    "wof:name":"DG12 5AD",
    "wof:placetype":"postalcode"
},
  "geometry": {"coordinates":[-3.262115,54.990929],"type":"Point"}
}