{
  "type": "Feature",
  "properties": {
    "iso:country":"GB",
    "wof:name":"LL18 4RB",
    "wof:placetype":"postalcode"
},
  "geometry": {"coordinates":[-3.48152150828306,53.31878486698739],"type":"Point"}
}