{
  "type": "Feature",
  "properties": {
    "iso:country":"GB",
    "wof:name":"IV7 8DA",
    "wof:placetype":"postalcode"
},
  "geometry": {"coordinates":[-4.43179238282368,57.56923976260659],"type":"Point"}
}