{
  "type": "Feature",
  "properties": {
    "date:inception_lower":"1992-10-01",
    "date:inception_upper":"1992-10-31",
    "iso:country":"GB",
    "wof:name":"IV7 8DA",
    "wof:placetype":"postalcode"
},
  "geometry": {"coordinates":[-4.431488,57.569453],"type":"Point"}
}