{
  "type": "Feature",
  "properties": {
    "iso:country": "GB",
    "wof:name": "NP44 2EE",
    "wof:placetype": "postalcode"
  },
  "geometry": {"coordinates":[-3.00638,51.657568],"type":"Point"}
}
