{
  "type": "Feature",
  "properties": {
    "iso:country":"GB",
    "wof:name":"TS23 3GF",
    "wof:placetype":"postalcode"
},
  "geometry": {"coordinates":[-1.29545459989422,54.62138833179048],"type":"Point"}
}