{
  "type": "Feature",
  "properties": {
    "date:inception_lower": "1996-06-01",
    "date:inception_upper": "1996-06-01",
    "iso:country": "GB",
    "wof:name": "TS23 3GF",
    "wof:placetype": "postalcode"
  },
  "geometry": {"coordinates":[-1.295455,54.621388],"type":"Point"}
}
