{
  "type": "Feature",
  "properties": {
    "iso:country":"GB",
    "wof:name":"WN2 5DP",
    "wof:placetype":"postalcode"
},
  "geometry": {"coordinates":[-2.60311936332458,53.5179918076276],"type":"Point"}
}