{
  "type": "Feature",
  "properties": {
    "date:inception_lower":"1980-01-01",
    "date:inception_upper":"1980-01-31",
    "iso:country":"GB",
    "wof:name":"NE40 3SR",
    "wof:placetype":"postalcode"
},
  "geometry": {"coordinates":[-1.793061,54.97872],"type":"Point"}
}