{
  "type": "Feature",
  "properties": {
    "iso:country":"GB",
    "wof:name":"SW1V 3EY",
    "wof:placetype":"postalcode"
},
  "geometry": {"coordinates":[-0.13883731979043,51.4878811845183],"type":"Point"}
}