{
  "type": "Feature",
  "properties": {
    "date:inception_lower": "1980-01-01",
    "date:inception_upper": "1980-01-01",
    "iso:country": "GB",
    "wof:name": "SW1V 3EY",
    "wof:placetype": "postalcode"
  },
  "geometry": {"coordinates":[-0.13874,51.48789],"type":"Point"}
}
