{
  "type": "Feature",
  "properties": {
    "date:inception_lower":"1983-07-01",
    "date:inception_upper":"1983-07-31",
    "iso:country":"GB",
    "wof:name":"SW19 1DS",
    "wof:placetype":"postalcode"
},
  "geometry": {"coordinates":[-0.185594,51.419587],"type":"Point"}
}