{
  "type": "Feature",
  "properties": {
    "iso:country":"GB",
    "wof:name":"SW19 1DS",
    "wof:placetype":"postalcode"
},
  "geometry": {"coordinates":[-0.18559453494621,51.41958724233657],"type":"Point"}
}