{
  "type": "Feature",
  "properties": {
    "date:inception_lower": "2018-09-01",
    "date:inception_upper": "2018-09-01",
    "iso:country": "GB",
    "wof:name": "NG20 8UQ",
    "wof:placetype": "postalcode"
  },
  "geometry": {"coordinates":[-1.208894,53.204932],"type":"Point"}
}
