{
  "type": "Feature",
  "properties": {
    "iso:country":"GB",
    "wof:name":"PL3 4HF",
    "wof:placetype":"postalcode"
},
  "geometry": {"coordinates":[-4.15180780635775,50.38013326640208],"type":"Point"}
}