{
  "type": "Feature",
  "properties": {
    "iso:country": "GB",
    "wof:name": "CF37 2SB",
    "wof:placetype": "postalcode"
  },
  "geometry": {"coordinates":[-3.357755,51.608801],"type":"Point"}
}
