{
  "type": "Feature",
  "properties": {
    "iso:country":"GB",
    "wof:name":"CF37 2SB",
    "wof:placetype":"postalcode"
},
  "geometry": {"coordinates":[-3.35775499647878,51.6088014164993],"type":"Point"}
}