{
  "type": "Feature",
  "properties": {
    "iso:country": "GB",
    "wof:name": "G13 1BD",
    "wof:placetype": "postalcode"
  },
  "geometry": {"coordinates":[-4.331149,55.89703],"type":"Point"}
}
