{
  "type": "Feature",
  "properties": {
    "iso:country":"GB",
    "wof:name":"G13 1BD",
    "wof:placetype":"postalcode"
},
  "geometry": {"coordinates":[-4.3311495159284,55.89703015223533],"type":"Point"}
}