{
  "type": "Feature",
  "properties": {
    "date:inception_lower": "2014-02-01",
    "date:inception_upper": "2014-02-01",
    "iso:country": "GB",
    "wof:name": "G13 1BD",
    "wof:placetype": "postalcode"
  },
  "geometry": {"coordinates":[-4.331149,55.89703],"type":"Point"}
}
