{
  "type": "Feature",
  "properties": {
    "date:inception_lower": "1980-01-01",
    "date:inception_upper": "1980-01-01",
    "iso:country": "GB",
    "wof:name": "IP25 7JZ",
    "wof:placetype": "postalcode"
  },
  "geometry": {"coordinates":[0.888166,52.632899],"type":"Point"}
}
