{
  "type": "Feature",
  "properties": {
    "iso:country":"GB",
    "wof:name":"PE13 5HH",
    "wof:placetype":"postalcode"
},
  "geometry": {"coordinates":[0.12701175018334,52.71114487768088],"type":"Point"}
}