{
  "type": "Feature",
  "properties": {
    "iso:country":"GB",
    "wof:name":"DD3 6BB",
    "wof:placetype":"postalcode"
},
  "geometry": {"coordinates":[-2.99574247101826,56.47089889003825],"type":"Point"}
}