{
  "type": "Feature",
  "properties": {
    "date:inception_lower": "2017-03-01",
    "date:inception_upper": "2017-03-01",
    "iso:country": "GB",
    "wof:name": "BS23 2EL",
    "wof:placetype": "postalcode"
  },
  "geometry": {"coordinates":[-2.991429,51.355129],"type":"Point"}
}
