{
  "type": "Feature",
  "properties": {
    "iso:country":"GB",
    "wof:name":"RM5 3XX",
    "wof:placetype":"postalcode"
},
  "geometry": {"coordinates":[0.17526178446118,51.60546108279767],"type":"Point"}
}