{
  "type": "Feature",
  "properties": {
    "iso:country": "GB",
    "wof:name": "RM5 3XX",
    "wof:placetype": "postalcode"
  },
  "geometry": {"coordinates":[0.175262,51.605461],"type":"Point"}
}
