{
  "type": "Feature",
  "properties": {
    "iso:country":"GB",
    "wof:name":"ME3 9JH",
    "wof:placetype":"postalcode"
},
  "geometry": {"coordinates":[0.55674130698488,51.42662385632226],"type":"Point"}
}