{
  "type": "Feature",
  "properties": {
    "iso:country":"GB",
    "wof:name":"TA21 0NB",
    "wof:placetype":"postalcode"
},
  "geometry": {"coordinates":[-3.32681684635542,50.96441518294241],"type":"Point"}
}