{
  "type": "Feature",
  "properties": {
    "iso:country": "GB",
    "wof:name": "TA21 0NB",
    "wof:placetype": "postalcode"
  },
  "geometry": {"coordinates":[-3.326817,50.964415],"type":"Point"}
}
