{
  "type": "Feature",
  "properties": {
    "iso:country": "GB",
    "wof:name": "L36 7XJ",
    "wof:placetype": "postalcode"
  },
  "geometry": {"coordinates":[-2.832713,53.41655],"type":"Point"}
}
