{
  "type": "Feature",
  "properties": {
    "iso:country":"GB",
    "wof:name":"L30 7QJ",
    "wof:placetype":"postalcode"
},
  "geometry": {"coordinates":[-2.95922189684165,53.49076540243622],"type":"Point"}
}