{
  "type": "Feature",
  "properties": {
    "iso:country": "GB",
    "wof:name": "L30 7QJ",
    "wof:placetype": "postalcode"
  },
  "geometry": {"coordinates":[-2.959222,53.490765],"type":"Point"}
}
