{
  "type": "Feature",
  "properties": {
    "iso:country":"GB",
    "wof:name":"NR13 4SQ",
    "wof:placetype":"postalcode"
},
  "geometry": {"coordinates":[1.42746714117634,52.64978393068606],"type":"Point"}
}