{
  "type": "Feature",
  "properties": {
    "iso:country":"GB",
    "wof:name":"KA1 4SZ",
    "wof:placetype":"postalcode"
},
  "geometry": {"coordinates":[-4.50228078980256,55.58605739497814],"type":"Point"}
}