{
  "type": "Feature",
  "properties": {
    "date:inception_lower": "1980-01-01",
    "date:inception_upper": "1980-01-01",
    "iso:country": "GB",
    "wof:name": "ST7 1BD",
    "wof:placetype": "postalcode"
  },
  "geometry": {"coordinates":[-2.253931,53.080342],"type":"Point"}
}
