{
  "type": "Feature",
  "properties": {
    "iso:country":"GB",
    "wof:name":"ST7 1BD",
    "wof:placetype":"postalcode"
},
  "geometry": {"coordinates":[-2.2539314574924,53.08034217439278],"type":"Point"}
}