{
  "type": "Feature",
  "properties": {
    "iso:country":"GB",
    "wof:name":"EX7 0AE",
    "wof:placetype":"postalcode"
},
  "geometry": {"coordinates":[-3.4586686502656,50.58506643736504],"type":"Point"}
}