{
  "type": "Feature",
  "properties": {
    "iso:country":"GB",
    "wof:name":"CW6 0HR",
    "wof:placetype":"postalcode"
},
  "geometry": {"coordinates":[-2.66951815542878,53.16198646867288],"type":"Point"}
}