{
  "type": "Feature",
  "properties": {
    "iso:country": "GB",
    "wof:name": "CW6 0HR",
    "wof:placetype": "postalcode"
  },
  "geometry": {"coordinates":[-2.669518,53.161986],"type":"Point"}
}
