{
  "type": "Feature",
  "properties": {
    "date:inception_lower": "1980-01-01",
    "date:inception_upper": "1980-01-01",
    "iso:country": "GB",
    "wof:name": "CW6 0HR",
    "wof:placetype": "postalcode"
  },
  "geometry": {"coordinates":[-2.669518,53.161986],"type":"Point"}
}
