{
  "type": "Feature",
  "properties": {
    "iso:country":"GB",
    "wof:name":"CH7 6UW",
    "wof:placetype":"postalcode"
},
  "geometry": {"coordinates":[-3.10920912613022,53.17075706191198],"type":"Point"}
}