{
  "type": "Feature",
  "properties": {
    "iso:country":"GB",
    "wof:name":"L21 2PY",
    "wof:placetype":"postalcode"
},
  "geometry": {"coordinates":[-3.00570537236718,53.46783019939141],"type":"Point"}
}