{
  "type": "Feature",
  "properties": {
    "iso:country":"GB",
    "wof:name":"CT15 5EZ",
    "wof:placetype":"postalcode"
},
  "geometry": {"coordinates":[1.31206863429017,51.16262111135133],"type":"Point"}
}