{
  "type": "Feature",
  "properties": {
    "iso:country":"GB",
    "wof:name":"NN7 3QY",
    "wof:placetype":"postalcode"
},
  "geometry": {"coordinates":[-1.00091119823001,52.21042691853523],"type":"Point"}
}