{
  "type": "Feature",
  "properties": {
    "iso:country":"GB",
    "wof:name":"G41 2BA",
    "wof:placetype":"postalcode"
},
  "geometry": {"coordinates":[-4.27498242427403,55.83680448113441],"type":"Point"}
}