{
  "type": "Feature",
  "properties": {
    "iso:country":"GB",
    "wof:name":"N17 6JJ",
    "wof:placetype":"postalcode"
},
  "geometry": {"coordinates":[-0.08081689574648,51.5934715585307],"type":"Point"}
}