{
  "type": "Feature",
  "properties": {
    "date:inception_lower":"1980-01-01",
    "date:inception_upper":"1980-01-31",
    "iso:country":"GB",
    "wof:name":"NE4 5JL",
    "wof:placetype":"postalcode"
},
  "geometry": {"coordinates":[-1.636566,54.974067],"type":"Point"}
}