{
  "type": "Feature",
  "properties": {
    "iso:country":"GB",
    "wof:name":"NE4 5JL",
    "wof:placetype":"postalcode"
},
  "geometry": {"coordinates":[-1.6365663443283,54.97406679111841],"type":"Point"}
}