{
  "type": "Feature",
  "properties": {
    "iso:country":"GB",
    "wof:name":"WA16 6NY",
    "wof:placetype":"postalcode"
},
  "geometry": {"coordinates":[-2.42765176006337,53.36143961714297],"type":"Point"}
}