{
  "type": "Feature",
  "properties": {
    "date:inception_lower": "1980-01-01",
    "date:inception_upper": "1980-01-01",
    "iso:country": "GB",
    "wof:name": "WA16 6NY",
    "wof:placetype": "postalcode"
  },
  "geometry": {"coordinates":[-2.42765,53.361456],"type":"Point"}
}
