{
  "type": "Feature",
  "properties": {
    "date:inception_lower":"2002-06-01",
    "date:inception_upper":"2002-06-30",
    "iso:country":"GB",
    "wof:name":"B15 2HY",
    "wof:placetype":"postalcode"
},
  "geometry": {"coordinates":[-1.906294,52.467052],"type":"Point"}
}