{
  "type": "Feature",
  "properties": {
    "iso:country": "GB",
    "wof:name": "KT2 5TS",
    "wof:placetype": "postalcode"
  },
  "geometry": {"coordinates":[-0.297916,51.422037],"type":"Point"}
}
