{
  "type": "Feature",
  "properties": {
    "iso:country":"GB",
    "wof:name":"KT2 5TS",
    "wof:placetype":"postalcode"
},
  "geometry": {"coordinates":[-0.2979160758942,51.42203658292873],"type":"Point"}
}