{
  "type": "Feature",
  "properties": {
    "iso:country":"GB",
    "wof:name":"OL2 7QZ",
    "wof:placetype":"postalcode"
},
  "geometry": {"coordinates":[-2.10608992156684,53.58413803382695],"type":"Point"}
}