{
  "type": "Feature",
  "properties": {
    "iso:country": "GB",
    "wof:name": "OL2 7QZ",
    "wof:placetype": "postalcode"
  },
  "geometry": {"coordinates":[-2.10609,53.584138],"type":"Point"}
}
