{
  "type": "Feature",
  "properties": {
    "iso:country": "GB",
    "wof:name": "PR1 8EU",
    "wof:placetype": "postalcode"
  },
  "geometry": {"coordinates":[-2.711802,53.749906],"type":"Point"}
}
