{
  "type": "Feature",
  "properties": {
    "iso:country":"GB",
    "wof:name":"SA13 9SB",
    "wof:placetype":"postalcode"
},
  "geometry": {"coordinates":[-3.78396532459229,51.59784475550145],"type":"Point"}
}