{
  "type": "Feature",
  "properties": {
    "iso:country":"GB",
    "wof:name":"SW1W 8JU",
    "wof:placetype":"postalcode"
},
  "geometry": {"coordinates":[-0.15537514959018,51.49282760160771],"type":"Point"}
}