{
  "type": "Feature",
  "properties": {
    "iso:country": "GB",
    "wof:name": "MK42 9BH",
    "wof:placetype": "postalcode"
  },
  "geometry": {"coordinates":[-0.475653,52.130134],"type":"Point"}
}
