{
  "type": "Feature",
  "properties": {
    "iso:country":"GB",
    "wof:name":"PO22 7QN",
    "wof:placetype":"postalcode"
},
  "geometry": {"coordinates":[-0.63382028190985,50.79229217952085],"type":"Point"}
}