{
  "type": "Feature",
  "properties": {
    "date:inception_lower": "1999-06-01",
    "date:inception_upper": "1999-06-01",
    "iso:country": "GB",
    "wof:name": "CH63 5JE",
    "wof:placetype": "postalcode"
  },
  "geometry": {"coordinates":[-3.014642,53.359922],"type":"Point"}
}
