{
  "type": "Feature",
  "properties": {
    "iso:country":"GB",
    "wof:name":"CH63 5JE",
    "wof:placetype":"postalcode"
},
  "geometry": {"coordinates":[-3.01464177226699,53.35990529127006],"type":"Point"}
}