{
  "type": "Feature",
  "properties": {
    "date:inception_lower":"2014-12-01",
    "date:inception_upper":"2014-12-31",
    "iso:country":"GB",
    "wof:name":"WR10 2RA",
    "wof:placetype":"postalcode"
},
  "geometry": {"coordinates":[-2.014265,52.111029],"type":"Point"}
}