{
  "type": "Feature",
  "properties": {
    "iso:country": "GB",
    "wof:name": "WR10 2RA",
    "wof:placetype": "postalcode"
  },
  "geometry": {"coordinates":[-2.014265,52.111029],"type":"Point"}
}
