{
  "type": "Feature",
  "properties": {
    "iso:country":"GB",
    "wof:name":"WR10 2RA",
    "wof:placetype":"postalcode"
},
  "geometry": {"coordinates":[-2.01426459515218,52.1110288600571],"type":"Point"}
}