{
  "type": "Feature",
  "properties": {
    "iso:country":"GB",
    "wof:name":"NE61 1PJ",
    "wof:placetype":"postalcode"
},
  "geometry": {"coordinates":[-1.68732487313,55.16679774904726],"type":"Point"}
}