{
  "type": "Feature",
  "properties": {
    "iso:country": "GB",
    "wof:name": "KY10 3SA",
    "wof:placetype": "postalcode"
  },
  "geometry": {"coordinates":[-2.630486,56.26091],"type":"Point"}
}
