{
  "type": "Feature",
  "properties": {
    "date:inception_lower": "2021-07-01",
    "date:inception_upper": "2021-07-01",
    "iso:country": "GB",
    "wof:name": "B19 3AF",
    "wof:placetype": "postalcode"
  },
  "geometry": {"coordinates":[-1.912006,52.493591],"type":"Point"}
}
