{
  "type": "Feature",
  "properties": {
    "iso:country":"GB",
    "wof:name":"PO5 3PA",
    "wof:placetype":"postalcode"
},
  "geometry": {"coordinates":[-1.08879591086536,50.77809947745951],"type":"Point"}
}