{
  "type": "Feature",
  "properties": {
    "iso:country": "GB",
    "wof:name": "CV6 4FF",
    "wof:placetype": "postalcode"
  },
  "geometry": {"coordinates":[-1.512044,52.442574],"type":"Point"}
}
