{
  "type": "Feature",
  "properties": {
    "iso:country":"GB",
    "wof:name":"CV6 4FF",
    "wof:placetype":"postalcode"
},
  "geometry": {"coordinates":[-1.51204369138664,52.44257430212372],"type":"Point"}
}