{
  "type": "Feature",
  "properties": {
    "iso:country":"GB",
    "wof:name":"BS22 7FF",
    "wof:placetype":"postalcode"
},
  "geometry": {"coordinates":[-2.90223741907896,51.36742527282629],"type":"Point"}
}