{
  "type": "Feature",
  "properties": {
    "date:inception_lower": "1973-08-01",
    "date:inception_upper": "1973-08-01",
    "iso:country": "GB",
    "wof:name": "IV7 8AP",
    "wof:placetype": "postalcode"
  },
  "geometry": {"coordinates":[-4.42076,57.545145],"type":"Point"}
}
