{
  "type": "Feature",
  "properties": {
    "iso:country":"GB",
    "wof:name":"IV7 8AP",
    "wof:placetype":"postalcode"
},
  "geometry": {"coordinates":[-4.42076033716494,57.54514513037322],"type":"Point"}
}