{
  "type": "Feature",
  "properties": {
    "iso:country": "GB",
    "wof:name": "IV7 8AP",
    "wof:placetype": "postalcode"
  },
  "geometry": {"coordinates":[-4.42076,57.545145],"type":"Point"}
}
