{
  "type": "Feature",
  "properties": {
    "iso:country":"GB",
    "wof:name":"L23 0RT",
    "wof:placetype":"postalcode"
},
  "geometry": {"coordinates":[-3.02561257875558,53.4849914662957],"type":"Point"}
}