{
  "type": "Feature",
  "properties": {
    "iso:country":"GB",
    "wof:name":"SY3 0HT",
    "wof:placetype":"postalcode"
},
  "geometry": {"coordinates":[-2.77255060786269,52.67470632412275],"type":"Point"}
}