{
  "type": "Feature",
  "properties": {
    "date:inception_lower": "2016-09-01",
    "date:inception_upper": "2016-09-01",
    "iso:country": "GB",
    "wof:name": "DN39 6AA",
    "wof:placetype": "postalcode"
  },
  "geometry": {"coordinates":[-0.330218,53.616299],"type":"Point"}
}
