{
  "type": "Feature",
  "properties": {
    "iso:country":"GB",
    "wof:name":"BA16 0LH",
    "wof:placetype":"postalcode"
},
  "geometry": {"coordinates":[-2.74497902535439,51.12147526284036],"type":"Point"}
}