{
  "type": "Feature",
  "properties": {
    "iso:country":"GB",
    "wof:name":"SY3 8EL",
    "wof:placetype":"postalcode"
},
  "geometry": {"coordinates":[-2.81753290021231,52.72809196005368],"type":"Point"}
}