{
  "type": "Feature",
  "properties": {
    "iso:country": "GB",
    "wof:name": "GL54 1HX",
    "wof:placetype": "postalcode"
  },
  "geometry": {"coordinates":[-1.715934,51.898354],"type":"Point"}
}
