{
  "type": "Feature",
  "properties": {
    "iso:country":"GB",
    "wof:name":"GL54 1HX",
    "wof:placetype":"postalcode"
},
  "geometry": {"coordinates":[-1.71690334354846,51.89851871479645],"type":"Point"}
}