{
  "type": "Feature",
  "properties": {
    "date:inception_lower": "1980-01-01",
    "date:inception_upper": "1980-01-01",
    "iso:country": "GB",
    "wof:name": "ST17 0NA",
    "wof:placetype": "postalcode"
  },
  "geometry": {"coordinates":[-2.06718,52.783481],"type":"Point"}
}
