{
  "type": "Feature",
  "properties": {
    "iso:country":"GB",
    "wof:name":"EX36 4RW",
    "wof:placetype":"postalcode"
},
  "geometry": {"coordinates":[-3.67090866122604,50.99506197023036],"type":"Point"}
}