{
  "type": "Feature",
  "properties": {
    "iso:country": "GB",
    "wof:name": "EX36 4RW",
    "wof:placetype": "postalcode"
  },
  "geometry": {"coordinates":[-3.670909,50.995062],"type":"Point"}
}
