{
  "type": "Feature",
  "properties": {
    "date:inception_lower": "1987-10-01",
    "date:inception_upper": "1987-10-01",
    "iso:country": "GB",
    "wof:name": "IP20 9PE",
    "wof:placetype": "postalcode"
  },
  "geometry": {"coordinates":[1.287025,52.40545],"type":"Point"}
}
