{
  "type": "Feature",
  "properties": {
    "iso:country": "GB",
    "wof:name": "IP31 3SQ",
    "wof:placetype": "postalcode"
  },
  "geometry": {"coordinates":[0.842868,52.25232],"type":"Point"}
}
