{
  "type": "Feature",
  "properties": {
    "date:inception_lower":"1980-01-01",
    "date:inception_upper":"1980-01-31",
    "iso:country":"GB",
    "wof:name":"IP31 3SQ",
    "wof:placetype":"postalcode"
},
  "geometry": {"coordinates":[0.843093,52.252396],"type":"Point"}
}