{
  "type": "Feature",
  "properties": {
    "iso:country":"GB",
    "wof:name":"AL7 1FJ",
    "wof:placetype":"postalcode"
},
  "geometry": {"coordinates":[-0.17922766962393,51.79668082497432],"type":"Point"}
}