{
  "type": "Feature",
  "properties": {
    "iso:country":"GB",
    "wof:name":"IP24 3TX",
    "wof:placetype":"postalcode"
},
  "geometry": {"coordinates":[0.61188922799122,52.38099281222214],"type":"Point"}
}