{
  "type": "Feature",
  "properties": {
    "date:inception_lower": "2001-06-01",
    "date:inception_upper": "2001-06-01",
    "iso:country": "GB",
    "wof:name": "IP24 3TX",
    "wof:placetype": "postalcode"
  },
  "geometry": {"coordinates":[0.611889,52.380993],"type":"Point"}
}
