{
  "type": "Feature",
  "properties": {
    "date:inception_lower": "1980-01-01",
    "date:inception_upper": "1980-01-01",
    "iso:country": "GB",
    "wof:name": "RH14 0QD",
    "wof:placetype": "postalcode"
  },
  "geometry": {"coordinates":[-0.568727,51.069006],"type":"Point"}
}
