{
  "type": "Feature",
  "properties": {
    "iso:country":"GB",
    "wof:name":"NW11 0HA",
    "wof:placetype":"postalcode"
},
  "geometry": {"coordinates":[-0.20200246305152,51.58036443012971],"type":"Point"}
}