{
  "type": "Feature",
  "properties": {
    "date:inception_lower": "1980-01-01",
    "date:inception_upper": "1980-01-01",
    "iso:country": "GB",
    "wof:name": "NW11 0HA",
    "wof:placetype": "postalcode"
  },
  "geometry": {"coordinates":[-0.20196,51.58043],"type":"Point"}
}
