{
  "type": "Feature",
  "properties": {
    "iso:country": "GB",
    "wof:name": "W11 2EQ",
    "wof:placetype": "postalcode"
  },
  "geometry": {"coordinates":[-0.210548,51.513799],"type":"Point"}
}
