{
  "type": "Feature",
  "properties": {
    "iso:country":"GB",
    "wof:name":"W11 2EQ",
    "wof:placetype":"postalcode"
},
  "geometry": {"coordinates":[-0.21054807986199,51.51379855732115],"type":"Point"}
}