{
  "type": "Feature",
  "properties": {
    "iso:country": "GB",
    "wof:name": "CM4 9RA",
    "wof:placetype": "postalcode"
  },
  "geometry": {"coordinates":[0.465445,51.674375],"type":"Point"}
}
