{
  "type": "Feature",
  "properties": {
    "iso:country":"GB",
    "wof:name":"CM4 9RA",
    "wof:placetype":"postalcode"
},
  "geometry": {"coordinates":[0.46544452527002,51.67437544702783],"type":"Point"}
}