{
  "type": "Feature",
  "properties": {
    "iso:country":"GB",
    "wof:name":"LU5 4RT",
    "wof:placetype":"postalcode"
},
  "geometry": {"coordinates":[-0.51758619440077,51.8872857976033],"type":"Point"}
}