{
  "type": "Feature",
  "properties": {
    "iso:country": "GB",
    "wof:name": "LU5 4RT",
    "wof:placetype": "postalcode"
  },
  "geometry": {"coordinates":[-0.517586,51.887286],"type":"Point"}
}
