{
  "type": "Feature",
  "properties": {
    "date:inception_lower": "1980-01-01",
    "date:inception_upper": "1980-01-01",
    "iso:country": "GB",
    "wof:name": "SY4 4SH",
    "wof:placetype": "postalcode"
  },
  "geometry": {"coordinates":[-2.69992,52.721051],"type":"Point"}
}
