{
  "type": "Feature",
  "properties": {
    "iso:country":"GB",
    "wof:name":"SY4 4SH",
    "wof:placetype":"postalcode"
},
  "geometry": {"coordinates":[-2.69991962625197,52.72105056112333],"type":"Point"}
}