{
  "type": "Feature",
  "properties": {
    "iso:country":"GB",
    "wof:name":"PE9 3SX",
    "wof:placetype":"postalcode"
},
  "geometry": {"coordinates":[-0.54619956312858,52.63682805352605],"type":"Point"}
}