{
  "type": "Feature",
  "properties": {
    "iso:country": "GB",
    "wof:name": "CA14 3XR",
    "wof:placetype": "postalcode"
  },
  "geometry": {"coordinates":[-3.555498,54.634248],"type":"Point"}
}
