{
  "type": "Feature",
  "properties": {
    "iso:country": "GB",
    "wof:name": "CA14 3XR",
    "wof:placetype": "postalcode"
  },
  "geometry": {"coordinates":[-3.555483,54.634256],"type":"Point"}
}
