{
  "type": "Feature",
  "properties": {
    "iso:country":"GB",
    "wof:name":"EN11 9EG",
    "wof:placetype":"postalcode"
},
  "geometry": {"coordinates":[-0.01046231153045,51.76902826382577],"type":"Point"}
}