{
  "type": "Feature",
  "properties": {
    "iso:country":"GB",
    "wof:name":"PO36 9FH",
    "wof:placetype":"postalcode"
},
  "geometry": {"coordinates":[-1.17790119240502,50.64663816599529],"type":"Point"}
}