{
  "type": "Feature",
  "properties": {
    "iso:country": "GB",
    "wof:name": "PO36 9FH",
    "wof:placetype": "postalcode"
  },
  "geometry": {"coordinates":[-1.177901,50.646638],"type":"Point"}
}
