{
  "type": "Feature",
  "properties": {
    "date:inception_lower":"2004-02-01",
    "date:inception_upper":"2004-02-29",
    "iso:country":"GB",
    "wof:name":"PO36 9FH",
    "wof:placetype":"postalcode"
},
  "geometry": {"coordinates":[-1.177901,50.646638],"type":"Point"}
}