{
  "type": "Feature",
  "properties": {
    "iso:country":"GB",
    "wof:name":"DD5 4NW",
    "wof:placetype":"postalcode"
},
  "geometry": {"coordinates":[-2.82948784500377,56.47811373199895],"type":"Point"}
}