{
  "type": "Feature",
  "properties": {
    "iso:country": "GB",
    "wof:name": "SP5 1PA",
    "wof:placetype": "postalcode"
  },
  "geometry": {"coordinates":[-1.603844,51.052675],"type":"Point"}
}
