{
  "type": "Feature",
  "properties": {
    "date:inception_lower": "1980-01-01",
    "date:inception_upper": "1980-01-01",
    "iso:country": "GB",
    "wof:name": "SP5 1PA",
    "wof:placetype": "postalcode"
  },
  "geometry": {"coordinates":[-1.602673,51.051134],"type":"Point"}
}
