{
  "type": "Feature",
  "properties": {
    "iso:country":"GB",
    "wof:name":"GL11 4PF",
    "wof:placetype":"postalcode"
},
  "geometry": {"coordinates":[-2.35013446647159,51.67982727613566],"type":"Point"}
}