{
  "type": "Feature",
  "properties": {
    "date:inception_lower": "1980-01-01",
    "date:inception_upper": "1980-01-01",
    "iso:country": "GB",
    "wof:name": "GL11 4PF",
    "wof:placetype": "postalcode"
  },
  "geometry": {"coordinates":[-2.350133,51.67983],"type":"Point"}
}
