{
  "type": "Feature",
  "properties": {
    "iso:country": "GB",
    "wof:name": "DT11 0JZ",
    "wof:placetype": "postalcode"
  },
  "geometry": {"coordinates":[-2.281017,50.780463],"type":"Point"}
}
