{
  "type": "Feature",
  "properties": {
    "iso:country": "GB",
    "wof:name": "CV22 7XA",
    "wof:placetype": "postalcode"
  },
  "geometry": {"coordinates":[-1.314503,52.356752],"type":"Point"}
}
