{
  "type": "Feature",
  "properties": {
    "date:inception_lower": "2020-06-01",
    "date:inception_upper": "2020-06-01",
    "iso:country": "GB",
    "wof:name": "CW12 2GU",
    "wof:placetype": "postalcode"
  },
  "geometry": {"coordinates":[-2.213581,53.176909],"type":"Point"}
}
