{
  "type": "Feature",
  "properties": {
    "iso:country":"GB",
    "wof:name":"BN8 4BG",
    "wof:placetype":"postalcode"
},
  "geometry": {"coordinates":[-0.02140574091193,50.94501735864219],"type":"Point"}
}