{
  "type": "Feature",
  "properties": {
    "iso:country":"GB",
    "wof:name":"EH4 2BW",
    "wof:placetype":"postalcode"
},
  "geometry": {"coordinates":[-3.24671615339163,55.95691716578393],"type":"Point"}
}