{
  "type": "Feature",
  "properties": {
    "iso:country":"GB",
    "wof:name":"NW6 1EY",
    "wof:placetype":"postalcode"
},
  "geometry": {"coordinates":[-0.20258329922796,51.5535670968087],"type":"Point"}
}