{
  "type": "Feature",
  "properties": {
    "iso:country":"GB",
    "wof:name":"CA28 8JR",
    "wof:placetype":"postalcode"
},
  "geometry": {"coordinates":[-3.56799660029398,54.53060041408163],"type":"Point"}
}