{
  "type": "Feature",
  "properties": {
    "iso:country": "GB",
    "wof:name": "CA28 8JR",
    "wof:placetype": "postalcode"
  },
  "geometry": {"coordinates":[-3.567997,54.5306],"type":"Point"}
}
