{
  "type": "Feature",
  "properties": {
    "date:inception_lower": "2021-12-01",
    "date:inception_upper": "2021-12-01",
    "iso:country": "GB",
    "wof:name": "SL4 1EQ",
    "wof:placetype": "postalcode"
  },
  "geometry": {"coordinates":[-0.609812,51.481031],"type":"Point"}
}
