{
  "type": "Feature",
  "properties": {
    "iso:country":"GB",
    "wof:name":"TS1 3QH",
    "wof:placetype":"postalcode"
},
  "geometry": {"coordinates":[-1.23796257458139,54.57017378582994],"type":"Point"}
}