{
  "type": "Feature",
  "properties": {
    "date:inception_lower": "1980-01-01",
    "date:inception_upper": "1980-01-01",
    "iso:country": "GB",
    "wof:name": "WA15 0LN",
    "wof:placetype": "postalcode"
  },
  "geometry": {"coordinates":[-2.334411,53.368704],"type":"Point"}
}
