{
  "type": "Feature",
  "properties": {
    "iso:country": "GB",
    "wof:name": "OL7 0PA",
    "wof:placetype": "postalcode"
  },
  "geometry": {"coordinates":[-2.101541,53.482583],"type":"Point"}
}
