{
  "type": "Feature",
  "properties": {
    "date:inception_lower":"2005-08-01",
    "date:inception_upper":"2005-08-31",
    "iso:country":"GB",
    "wof:name":"OL7 0PA",
    "wof:placetype":"postalcode"
},
  "geometry": {"coordinates":[-2.101541,53.482583],"type":"Point"}
}