{
  "type": "Feature",
  "properties": {
    "iso:country":"GB",
    "wof:name":"OL7 0PA",
    "wof:placetype":"postalcode"
},
  "geometry": {"coordinates":[-2.10154111684822,53.48258252152534],"type":"Point"}
}