{
  "type": "Feature",
  "properties": {
    "date:inception_lower": "2009-06-01",
    "date:inception_upper": "2009-06-01",
    "iso:country": "GB",
    "wof:name": "WC1A 2SL",
    "wof:placetype": "postalcode"
  },
  "geometry": {"coordinates":[-0.124362,51.517427],"type":"Point"}
}
