{
  "type": "Feature",
  "properties": {
    "iso:country":"GB",
    "wof:name":"WC1A 2SL",
    "wof:placetype":"postalcode"
},
  "geometry": {"coordinates":[-0.12357627293826,51.51822160339186],"type":"Point"}
}