{
  "type": "Feature",
  "properties": {
    "iso:country": "GB",
    "wof:name": "EX22 7SX",
    "wof:placetype": "postalcode"
  },
  "geometry": {"coordinates":[-4.385074,50.902159],"type":"Point"}
}
