{
  "type": "Feature",
  "properties": {
    "iso:country": "GB",
    "wof:name": "M33 4DN",
    "wof:placetype": "postalcode"
  },
  "geometry": {"coordinates":[-2.333407,53.41142],"type":"Point"}
}
