{
  "type": "Feature",
  "properties": {
    "iso:country":"GB",
    "wof:name":"M33 4DN",
    "wof:placetype":"postalcode"
},
  "geometry": {"coordinates":[-2.33340690460443,53.41142038290479],"type":"Point"}
}