{
  "type": "Feature",
  "properties": {
    "iso:country":"GB",
    "wof:name":"DT11 7LT",
    "wof:placetype":"postalcode"
},
  "geometry": {"coordinates":[-2.15849553097279,50.86399180862112],"type":"Point"}
}