{
  "type": "Feature",
  "properties": {
    "iso:country":"GB",
    "wof:name":"BS10 7TF",
    "wof:placetype":"postalcode"
},
  "geometry": {"coordinates":[-2.62168744381783,51.51849407142346],"type":"Point"}
}