{
  "type": "Feature",
  "properties": {
    "date:inception_lower": "2008-06-01",
    "date:inception_upper": "2008-06-01",
    "iso:country": "GB",
    "wof:name": "CM24 8SJ",
    "wof:placetype": "postalcode"
  },
  "geometry": {"coordinates":[0.19633,51.89481],"type":"Point"}
}
