{
  "type": "Feature",
  "properties": {
    "iso:country":"GB",
    "wof:name":"CM24 8SJ",
    "wof:placetype":"postalcode"
},
  "geometry": {"coordinates":[0.19660903141951,51.89482355165673],"type":"Point"}
}