{
  "type": "Feature",
  "properties": {
    "date:inception_lower": "2020-07-01",
    "date:inception_upper": "2020-07-01",
    "iso:country": "GB",
    "wof:name": "L3 0AQ",
    "wof:placetype": "postalcode"
  },
  "geometry": {"coordinates":[-3.000742,53.415672],"type":"Point"}
}
