{
  "type": "Feature",
  "properties": {
    "iso:country": "GB",
    "wof:name": "DA12 2FL",
    "wof:placetype": "postalcode"
  },
  "geometry": {"coordinates":[0.401406,51.436593],"type":"Point"}
}
