{
  "type": "Feature",
  "properties": {
    "date:inception_lower":"1998-06-01",
    "date:inception_upper":"1998-06-30",
    "iso:country":"GB",
    "wof:name":"CV37 8JT",
    "wof:placetype":"postalcode"
},
  "geometry": {"coordinates":[-1.739292,52.145625],"type":"Point"}
}