{
  "type": "Feature",
  "properties": {
    "iso:country": "GB",
    "wof:name": "CV37 8JT",
    "wof:placetype": "postalcode"
  },
  "geometry": {"coordinates":[-1.739292,52.145625],"type":"Point"}
}
