{
  "type": "Feature",
  "properties": {
    "iso:country": "GB",
    "wof:name": "FY3 8ED",
    "wof:placetype": "postalcode"
  },
  "geometry": {"coordinates":[-3.031056,53.825442],"type":"Point"}
}
