{
  "type": "Feature",
  "properties": {
    "iso:country":"GB",
    "wof:name":"FY3 8ED",
    "wof:placetype":"postalcode"
},
  "geometry": {"coordinates":[-3.03105591072273,53.825441884191],"type":"Point"}
}