{
  "type": "Feature",
  "properties": {
    "iso:country":"GB",
    "wof:name":"NE31 2PN",
    "wof:placetype":"postalcode"
},
  "geometry": {"coordinates":[-1.51730024381214,54.9627967520228],"type":"Point"}
}