{
  "type": "Feature",
  "properties": {
    "iso:country": "GB",
    "wof:name": "PE12 9DT",
    "wof:placetype": "postalcode"
  },
  "geometry": {"coordinates":[0.124583,52.787588],"type":"Point"}
}
