{
  "type": "Feature",
  "properties": {
    "iso:country": "GB",
    "wof:name": "WF15 7NZ",
    "wof:placetype": "postalcode"
  },
  "geometry": {"coordinates":[-1.696631,53.703075],"type":"Point"}
}
