{
  "type": "Feature",
  "properties": {
    "iso:country":"GB",
    "wof:name":"NG7 5GF",
    "wof:placetype":"postalcode"
},
  "geometry": {"coordinates":[-1.17418983734444,52.96701008289936],"type":"Point"}
}