{
  "type": "Feature",
  "properties": {
    "date:inception_lower": "2022-03-01",
    "date:inception_upper": "2022-03-01",
    "iso:country": "GB",
    "wof:name": "LE9 6AH",
    "wof:placetype": "postalcode"
  },
  "geometry": {"coordinates":[-1.230499,52.535115],"type":"Point"}
}
