{
  "type": "Feature",
  "properties": {
    "iso:country":"GB",
    "wof:name":"TN28 8DY",
    "wof:placetype":"postalcode"
},
  "geometry": {"coordinates":[0.93392201950976,50.98485467692749],"type":"Point"}
}