{
  "type": "Feature",
  "properties": {
    "iso:country": "GB",
    "wof:name": "RG18 0XP",
    "wof:placetype": "postalcode"
  },
  "geometry": {"coordinates":[-1.205735,51.465996],"type":"Point"}
}
