{
  "type": "Feature",
  "properties": {
    "iso:country":"GB",
    "wof:name":"RG18 0XP",
    "wof:placetype":"postalcode"
},
  "geometry": {"coordinates":[-1.20573455614019,51.46599643671782],"type":"Point"}
}