{
  "type": "Feature",
  "properties": {
    "iso:country":"GB",
    "wof:name":"BH1 4AL",
    "wof:placetype":"postalcode"
},
  "geometry": {"coordinates":[-1.84201590955748,50.72805269246877],"type":"Point"}
}