{
  "type": "Feature",
  "properties": {
    "iso:country":"GB",
    "wof:name":"RG24 7HX",
    "wof:placetype":"postalcode"
},
  "geometry": {"coordinates":[-1.045614589414,51.27777959647234],"type":"Point"}
}