{
  "type": "Feature",
  "properties": {
    "iso:country":"GB",
    "wof:name":"LA12 0QW",
    "wof:placetype":"postalcode"
},
  "geometry": {"coordinates":[-3.15358648468666,54.12130668217242],"type":"Point"}
}