{
  "type": "Feature",
  "properties": {
    "date:inception_lower":"1980-01-01",
    "date:inception_upper":"1980-01-31",
    "iso:country":"GB",
    "wof:name":"LA12 0QW",
    "wof:placetype":"postalcode"
},
  "geometry": {"coordinates":[-3.153586,54.121307],"type":"Point"}
}