{
  "type": "Feature",
  "properties": {
    "iso:country":"GB",
    "wof:name":"BA22 7LD",
    "wof:placetype":"postalcode"
},
  "geometry": {"coordinates":[-2.56699506740859,51.03787538568672],"type":"Point"}
}