{
  "type": "Feature",
  "properties": {
    "iso:country": "GB",
    "wof:name": "BA4 4HW",
    "wof:placetype": "postalcode"
  },
  "geometry": {"coordinates":[-2.618511,51.167281],"type":"Point"}
}
