{
  "type": "Feature",
  "properties": {
    "date:inception_lower": "1993-01-01",
    "date:inception_upper": "1993-01-01",
    "iso:country": "GB",
    "wof:name": "BA4 4HW",
    "wof:placetype": "postalcode"
  },
  "geometry": {"coordinates":[-2.618511,51.167281],"type":"Point"}
}
