{
  "type": "Feature",
  "properties": {
    "iso:country": "GB",
    "wof:name": "PE8 5DW",
    "wof:placetype": "postalcode"
  },
  "geometry": {"coordinates":[-0.477824,52.55625],"type":"Point"}
}
