{
  "type": "Feature",
  "properties": {
    "iso:country":"GB",
    "wof:name":"KA26 9BB",
    "wof:placetype":"postalcode"
},
  "geometry": {"coordinates":[-4.85910863269522,55.24187075058992],"type":"Point"}
}