{
  "type": "Feature",
  "properties": {
    "iso:country":"GB",
    "wof:name":"NN10 8PP",
    "wof:placetype":"postalcode"
},
  "geometry": {"coordinates":[-0.59823286066177,52.30271463000874],"type":"Point"}
}