{
  "type": "Feature",
  "properties": {
    "date:inception_lower": "2006-02-01",
    "date:inception_upper": "2006-02-01",
    "iso:country": "GB",
    "wof:name": "NN10 8PP",
    "wof:placetype": "postalcode"
  },
  "geometry": {"coordinates":[-0.598233,52.302715],"type":"Point"}
}
