{
  "type": "Feature",
  "properties": {
    "iso:country": "GB",
    "wof:name": "WR4 0UD",
    "wof:placetype": "postalcode"
  },
  "geometry": {"coordinates":[-2.17571,52.204408],"type":"Point"}
}
