{
  "type": "Feature",
  "properties": {
    "date:inception_lower":"2003-04-01",
    "date:inception_upper":"2003-04-30",
    "iso:country":"GB",
    "wof:name":"WR4 0UD",
    "wof:placetype":"postalcode"
},
  "geometry": {"coordinates":[-2.17571,52.204408],"type":"Point"}
}