{
  "type": "Feature",
  "properties": {
    "date:inception_lower":"1980-01-01",
    "date:inception_upper":"1980-01-31",
    "iso:country":"GB",
    "wof:name":"LL67 0EA",
    "wof:placetype":"postalcode"
},
  "geometry": {"coordinates":[-4.507217,53.400737],"type":"Point"}
}