{
  "type": "Feature",
  "properties": {
    "iso:country": "GB",
    "wof:name": "LL67 0EA",
    "wof:placetype": "postalcode"
  },
  "geometry": {"coordinates":[-4.507217,53.400737],"type":"Point"}
}
