{
  "type": "Feature",
  "properties": {
    "date:inception_lower": "1980-01-01",
    "date:inception_upper": "1980-01-01",
    "iso:country": "GB",
    "wof:name": "PO30 2BN",
    "wof:placetype": "postalcode"
  },
  "geometry": {"coordinates":[-1.282145,50.6965],"type":"Point"}
}
