{
  "type": "Feature",
  "properties": {
    "iso:country":"GB",
    "wof:name":"B63 2NY",
    "wof:placetype":"postalcode"
},
  "geometry": {"coordinates":[-2.09734214374683,52.46702138138101],"type":"Point"}
}