{
  "type": "Feature",
  "properties": {
    "iso:country":"GB",
    "wof:name":"DH8 8PB",
    "wof:placetype":"postalcode"
},
  "geometry": {"coordinates":[-1.85302357910131,54.8593791732136],"type":"Point"}
}