{
  "type": "Feature",
  "properties": {
    "iso:country": "GB",
    "wof:name": "SK3 9JG",
    "wof:placetype": "postalcode"
  },
  "geometry": {"coordinates":[-2.174588,53.403867],"type":"Point"}
}
