{
  "type": "Feature",
  "properties": {
    "date:inception_lower": "2007-07-01",
    "date:inception_upper": "2007-07-01",
    "iso:country": "GB",
    "wof:name": "SK3 9JG",
    "wof:placetype": "postalcode"
  },
  "geometry": {"coordinates":[-2.174588,53.403867],"type":"Point"}
}
