{
  "type": "Feature",
  "properties": {
    "date:inception_lower":"1980-01-01",
    "date:inception_upper":"1980-01-31",
    "iso:country":"GB",
    "wof:name":"EH52 6SQ",
    "wof:placetype":"postalcode"
},
  "geometry": {"coordinates":[-3.464789,55.954724],"type":"Point"}
}