{
  "type": "Feature",
  "properties": {
    "iso:country": "GB",
    "wof:name": "EH52 6SQ",
    "wof:placetype": "postalcode"
  },
  "geometry": {"coordinates":[-3.464789,55.954724],"type":"Point"}
}
