{
  "type": "Feature",
  "properties": {
    "iso:country":"GB",
    "wof:name":"EH52 6SQ",
    "wof:placetype":"postalcode"
},
  "geometry": {"coordinates":[-3.46478891039384,55.9547241943567],"type":"Point"}
}