{
  "type": "Feature",
  "properties": {
    "date:inception_lower": "1980-01-01",
    "date:inception_upper": "1980-01-01",
    "iso:country": "GB",
    "wof:name": "TS16 0NP",
    "wof:placetype": "postalcode"
  },
  "geometry": {"coordinates":[-1.362162,54.523009],"type":"Point"}
}
