{
  "type": "Feature",
  "properties": {
    "iso:country":"GB",
    "wof:name":"TS16 0NP",
    "wof:placetype":"postalcode"
},
  "geometry": {"coordinates":[-1.36216157053305,54.52300905796966],"type":"Point"}
}