{
  "type": "Feature",
  "properties": {
    "date:inception_lower":"2002-07-01",
    "date:inception_upper":"2002-07-31",
    "iso:country":"GB",
    "wof:name":"G77 6RJ",
    "wof:placetype":"postalcode"
},
  "geometry": {"coordinates":[-4.333066,55.771948],"type":"Point"}
}