{
  "type": "Feature",
  "properties": {
    "iso:country":"GB",
    "wof:name":"PE10 0QY",
    "wof:placetype":"postalcode"
},
  "geometry": {"coordinates":[-0.37042111797508,52.75703765046462],"type":"Point"}
}