{
  "type": "Feature",
  "properties": {
    "iso:country":"GB",
    "wof:name":"CM13 3PZ",
    "wof:placetype":"postalcode"
},
  "geometry": {"coordinates":[0.35086162979347,51.59649010392363],"type":"Point"}
}