{
  "type": "Feature",
  "properties": {
    "iso:country": "GB",
    "wof:name": "CM13 3PZ",
    "wof:placetype": "postalcode"
  },
  "geometry": {"coordinates":[0.350805,51.596513],"type":"Point"}
}
