{
  "type": "Feature",
  "properties": {
    "iso:country":"GB",
    "wof:name":"KA3 7JN",
    "wof:placetype":"postalcode"
},
  "geometry": {"coordinates":[-4.47057453124935,55.61586775759763],"type":"Point"}
}