{
  "type": "Feature",
  "properties": {
    "date:inception_lower":"1985-04-01",
    "date:inception_upper":"1985-04-30",
    "iso:country":"GB",
    "wof:name":"CT20 3RL",
    "wof:placetype":"postalcode"
},
  "geometry": {"coordinates":[1.14154,51.085916],"type":"Point"}
}