{
  "type": "Feature",
  "properties": {
    "iso:country":"GB",
    "wof:name":"DN12 3HH",
    "wof:placetype":"postalcode"
},
  "geometry": {"coordinates":[-1.22814332183731,53.48397332679744],"type":"Point"}
}