{
  "type": "Feature",
  "properties": {
    "date:inception_lower": "2022-03-01",
    "date:inception_upper": "2022-03-01",
    "iso:country": "GB",
    "wof:name": "BA2 5FX",
    "wof:placetype": "postalcode"
  },
  "geometry": {"coordinates":[-2.34946,51.364666],"type":"Point"}
}
