{
  "type": "Feature",
  "properties": {
    "iso:country": "GB",
    "wof:name": "SL3 7NQ",
    "wof:placetype": "postalcode"
  },
  "geometry": {"coordinates":[-0.569701,51.498244],"type":"Point"}
}
