{
  "type": "Feature",
  "properties": {
    "date:inception_lower":"1980-01-01",
    "date:inception_upper":"1980-01-31",
    "iso:country":"GB",
    "wof:name":"CV35 8LL",
    "wof:placetype":"postalcode"
},
  "geometry": {"coordinates":[-1.71465,52.283409],"type":"Point"}
}