{
  "type": "Feature",
  "properties": {
    "iso:country":"GB",
    "wof:name":"LA8 8ES",
    "wof:placetype":"postalcode"
},
  "geometry": {"coordinates":[-2.82009143847546,54.2556208617161],"type":"Point"}
}