{
  "type": "Feature",
  "properties": {
    "iso:country": "GB",
    "wof:name": "LA8 8ES",
    "wof:placetype": "postalcode"
  },
  "geometry": {"coordinates":[-2.820091,54.255621],"type":"Point"}
}
