{
  "type": "Feature",
  "properties": {
    "iso:country": "GB",
    "wof:name": "WA7 4UJ",
    "wof:placetype": "postalcode"
  },
  "geometry": {"coordinates":[-2.748291,53.335203],"type":"Point"}
}
