{
  "type": "Feature",
  "properties": {
    "iso:country":"GB",
    "wof:name":"WA7 4UJ",
    "wof:placetype":"postalcode"
},
  "geometry": {"coordinates":[-2.74829124137988,53.33520300221276],"type":"Point"}
}