{
  "type": "Feature",
  "properties": {
    "date:inception_lower": "1984-10-01",
    "date:inception_upper": "1984-10-01",
    "iso:country": "GB",
    "wof:name": "LL29 8RN",
    "wof:placetype": "postalcode"
  },
  "geometry": {"coordinates":[-3.712004,53.285538],"type":"Point"}
}
