{
  "type": "Feature",
  "properties": {
    "iso:country":"GB",
    "wof:name":"BH18 9LA",
    "wof:placetype":"postalcode"
},
  "geometry": {"coordinates":[-2.00103955278508,50.75503834090966],"type":"Point"}
}