{
  "type": "Feature",
  "properties": {
    "iso:country": "GB",
    "wof:name": "BH18 9LA",
    "wof:placetype": "postalcode"
  },
  "geometry": {"coordinates":[-2.00104,50.755038],"type":"Point"}
}
