{
  "type": "Feature",
  "properties": {
    "iso:country":"GB",
    "wof:name":"SP3 4RA",
    "wof:placetype":"postalcode"
},
  "geometry": {"coordinates":[-1.91315293156782,51.12722574277448],"type":"Point"}
}