{
  "type": "Feature",
  "properties": {
    "iso:country": "GB",
    "wof:name": "SP3 4RA",
    "wof:placetype": "postalcode"
  },
  "geometry": {"coordinates":[-1.913153,51.127226],"type":"Point"}
}
