{
  "type": "Feature",
  "properties": {
    "iso:country":"GB",
    "wof:name":"BL5 3ES",
    "wof:placetype":"postalcode"
},
  "geometry": {"coordinates":[-2.51002113914015,53.55573646078231],"type":"Point"}
}