{
  "type": "Feature",
  "properties": {
    "iso:country": "GB",
    "wof:name": "BL5 3ES",
    "wof:placetype": "postalcode"
  },
  "geometry": {"coordinates":[-2.510021,53.555736],"type":"Point"}
}
