{
  "type": "Feature",
  "properties": {
    "date:inception_lower":"1998-06-01",
    "date:inception_upper":"1998-06-30",
    "iso:country":"GB",
    "wof:name":"BL5 3ES",
    "wof:placetype":"postalcode"
},
  "geometry": {"coordinates":[-2.510021,53.555736],"type":"Point"}
}