{
  "type": "Feature",
  "properties": {
    "iso:country":"GB",
    "wof:name":"HG1 1SG",
    "wof:placetype":"postalcode"
},
  "geometry": {"coordinates":[-1.53746276092519,53.98836624602487],"type":"Point"}
}