{
  "type": "Feature",
  "properties": {
    "iso:country":"GB",
    "wof:name":"EH38 5YG",
    "wof:placetype":"postalcode"
},
  "geometry": {"coordinates":[-2.96391079361969,55.7925426447196],"type":"Point"}
}