{
  "type": "Feature",
  "properties": {
    "iso:country":"GB",
    "wof:name":"UB6 8LQ",
    "wof:placetype":"postalcode"
},
  "geometry": {"coordinates":[-0.32867757678965,51.53757232574866],"type":"Point"}
}