{
  "type": "Feature",
  "properties": {
    "iso:country":"GB",
    "wof:name":"WF2 9ER",
    "wof:placetype":"postalcode"
},
  "geometry": {"coordinates":[-1.52465057055514,53.68370427446664],"type":"Point"}
}