{
  "type": "Feature",
  "properties": {
    "iso:country": "GB",
    "wof:name": "YO62 6DL",
    "wof:placetype": "postalcode"
  },
  "geometry": {"coordinates":[-0.931277,54.26688],"type":"Point"}
}
