{
  "type": "Feature",
  "properties": {
    "date:inception_lower": "1980-01-01",
    "date:inception_upper": "1980-01-01",
    "iso:country": "GB",
    "wof:name": "EH21 8BE",
    "wof:placetype": "postalcode"
  },
  "geometry": {"coordinates":[-3.01299,55.935106],"type":"Point"}
}
