{
  "type": "Feature",
  "properties": {
    "iso:country":"GB",
    "wof:name":"EH21 8BE",
    "wof:placetype":"postalcode"
},
  "geometry": {"coordinates":[-3.01299004958137,55.93510566284834],"type":"Point"}
}