{
  "type": "Feature",
  "properties": {
    "iso:country":"GB",
    "wof:name":"SY10 8LZ",
    "wof:placetype":"postalcode"
},
  "geometry": {"coordinates":[-3.10653996076796,52.80339310765277],"type":"Point"}
}