{
  "type": "Feature",
  "properties": {
    "iso:country":"GB",
    "wof:name":"HR5 3HS",
    "wof:placetype":"postalcode"
},
  "geometry": {"coordinates":[-2.9713813231968,52.20169010043969],"type":"Point"}
}