{
  "type": "Feature",
  "properties": {
    "date:inception_lower":"1980-01-01",
    "date:inception_upper":"1980-01-31",
    "iso:country":"GB",
    "wof:name":"HR5 3HS",
    "wof:placetype":"postalcode"
},
  "geometry": {"coordinates":[-2.972082,52.202216],"type":"Point"}
}