{
  "type": "Feature",
  "properties": {
    "iso:country": "GB",
    "wof:name": "HR5 3HS",
    "wof:placetype": "postalcode"
  },
  "geometry": {"coordinates":[-2.972082,52.202216],"type":"Point"}
}
