{
  "type": "Feature",
  "properties": {
    "iso:country":"GB",
    "wof:name":"CO10 7BX",
    "wof:placetype":"postalcode"
},
  "geometry": {"coordinates":[0.6071012317577,52.04764102506518],"type":"Point"}
}