{
  "type": "Feature",
  "properties": {
    "iso:country": "GB",
    "wof:name": "CO10 7BX",
    "wof:placetype": "postalcode"
  },
  "geometry": {"coordinates":[0.607101,52.047641],"type":"Point"}
}
