{
  "type": "Feature",
  "properties": {
    "iso:country":"GB",
    "wof:name":"HG3 2LE",
    "wof:placetype":"postalcode"
},
  "geometry": {"coordinates":[-1.65896092560757,54.01349729376874],"type":"Point"}
}