{
  "type": "Feature",
  "properties": {
    "iso:country": "GB",
    "wof:name": "HG3 2LE",
    "wof:placetype": "postalcode"
  },
  "geometry": {"coordinates":[-1.658961,54.013497],"type":"Point"}
}
