{
  "type": "Feature",
  "properties": {
    "iso:country": "GB",
    "wof:name": "BS16 4DY",
    "wof:placetype": "postalcode"
  },
  "geometry": {"coordinates":[-2.503974,51.477112],"type":"Point"}
}
