{
  "type": "Feature",
  "properties": {
    "iso:country": "GB",
    "wof:name": "PE11 3WT",
    "wof:placetype": "postalcode"
  },
  "geometry": {"coordinates":[-0.169888,52.790034],"type":"Point"}
}
