{
  "type": "Feature",
  "properties": {
    "date:inception_lower":"2014-10-01",
    "date:inception_upper":"2014-10-31",
    "iso:country":"GB",
    "wof:name":"PE11 3WT",
    "wof:placetype":"postalcode"
},
  "geometry": {"coordinates":[-0.169888,52.790034],"type":"Point"}
}