{
  "type": "Feature",
  "properties": {
    "iso:country":"GB",
    "wof:name":"CM15 0XQ",
    "wof:placetype":"postalcode"
},
  "geometry": {"coordinates":[0.27610141380703,51.66416065510024],"type":"Point"}
}