{
  "type": "Feature",
  "properties": {
    "date:inception_lower":"1994-05-01",
    "date:inception_upper":"1994-05-31",
    "iso:country":"GB",
    "wof:name":"M23 1AP",
    "wof:placetype":"postalcode"
},
  "geometry": {"coordinates":[-2.276639,53.398694],"type":"Point"}
}