{
  "type": "Feature",
  "properties": {
    "iso:country":"GB",
    "wof:name":"M23 1AP",
    "wof:placetype":"postalcode"
},
  "geometry": {"coordinates":[-2.27663906301397,53.39869384879179],"type":"Point"}
}