{
  "type": "Feature",
  "properties": {
    "iso:country": "GB",
    "wof:name": "NR20 5SL",
    "wof:placetype": "postalcode"
  },
  "geometry": {"coordinates":[1.014173,52.78387],"type":"Point"}
}
