{
  "type": "Feature",
  "properties": {
    "iso:country":"GB",
    "wof:name":"N19 4HR",
    "wof:placetype":"postalcode"
},
  "geometry": {"coordinates":[-0.12344098131205,51.56533107772176],"type":"Point"}
}