{
  "type": "Feature",
  "properties": {
    "date:inception_lower": "1980-01-01",
    "date:inception_upper": "1980-01-01",
    "iso:country": "GB",
    "wof:name": "DH7 8SH",
    "wof:placetype": "postalcode"
  },
  "geometry": {"coordinates":[-1.632245,54.75412],"type":"Point"}
}
