{
  "type": "Feature",
  "properties": {
    "iso:country":"GB",
    "wof:name":"RG14 6JU",
    "wof:placetype":"postalcode"
},
  "geometry": {"coordinates":[-1.33464739541114,51.38579213734953],"type":"Point"}
}