{
  "type": "Feature",
  "properties": {
    "iso:country":"GB",
    "wof:name":"LA4 5PX",
    "wof:placetype":"postalcode"
},
  "geometry": {"coordinates":[-2.85578030274404,54.07385678148184],"type":"Point"}
}