{
  "type": "Feature",
  "properties": {
    "iso:country": "GB",
    "wof:name": "LA4 5PX",
    "wof:placetype": "postalcode"
  },
  "geometry": {"coordinates":[-2.85578,54.073857],"type":"Point"}
}
