{
  "type": "Feature",
  "properties": {
    "iso:country":"GB",
    "wof:name":"CH7 6UF",
    "wof:placetype":"postalcode"
},
  "geometry": {"coordinates":[-3.11015690514787,53.16748508485539],"type":"Point"}
}