{
  "type": "Feature",
  "properties": {
    "iso:country":"GB",
    "wof:name":"HR2 6HW",
    "wof:placetype":"postalcode"
},
  "geometry": {"coordinates":[-2.71116159916445,52.03943899868165],"type":"Point"}
}