{
  "type": "Feature",
  "properties": {
    "iso:country": "GB",
    "wof:name": "DY8 5JD",
    "wof:placetype": "postalcode"
  },
  "geometry": {"coordinates":[-2.175279,52.477081],"type":"Point"}
}
