{
  "type": "Feature",
  "properties": {
    "iso:country": "GB",
    "wof:name": "GU14 7GH",
    "wof:placetype": "postalcode"
  },
  "geometry": {"coordinates":[-0.755488,51.286827],"type":"Point"}
}
