{
  "type": "Feature",
  "properties": {
    "iso:country":"GB",
    "wof:name":"BH16 5AT",
    "wof:placetype":"postalcode"
},
  "geometry": {"coordinates":[-2.02993935368112,50.72433356060434],"type":"Point"}
}