{
  "type": "Feature",
  "properties": {
    "iso:country": "GB",
    "wof:name": "CW8 1SY",
    "wof:placetype": "postalcode"
  },
  "geometry": {"coordinates":[-2.534571,53.240817],"type":"Point"}
}
