{
  "type": "Feature",
  "properties": {
    "date:inception_lower": "2018-02-01",
    "date:inception_upper": "2018-02-01",
    "iso:country": "GB",
    "wof:name": "CW8 1SY",
    "wof:placetype": "postalcode"
  },
  "geometry": {"coordinates":[-2.534571,53.240817],"type":"Point"}
}
