{
  "type": "Feature",
  "properties": {
    "iso:country":"GB",
    "wof:name":"BN21 3PF",
    "wof:placetype":"postalcode"
},
  "geometry": {"coordinates":[0.29295512211909,50.76923654228618],"type":"Point"}
}