{
  "type": "Feature",
  "properties": {
    "iso:country": "GB",
    "wof:name": "DG9 9EN",
    "wof:placetype": "postalcode"
  },
  "geometry": {"coordinates":[-5.045697,54.821755],"type":"Point"}
}
