{
  "type": "Feature",
  "properties": {
    "iso:country":"GB",
    "wof:name":"LN4 1AW",
    "wof:placetype":"postalcode"
},
  "geometry": {"coordinates":[-0.46642135147145,53.22378705380108],"type":"Point"}
}