{
  "type": "Feature",
  "properties": {
    "date:inception_lower": "1980-01-01",
    "date:inception_upper": "1980-01-01",
    "iso:country": "GB",
    "wof:name": "TN22 1QY",
    "wof:placetype": "postalcode"
  },
  "geometry": {"coordinates":[0.099373,50.970371],"type":"Point"}
}
