{
  "type": "Feature",
  "properties": {
    "iso:country":"GB",
    "wof:name":"TN22 1QY",
    "wof:placetype":"postalcode"
},
  "geometry": {"coordinates":[0.09931802699555,50.9703844177976],"type":"Point"}
}