{
  "type": "Feature",
  "properties": {
    "iso:country":"GB",
    "wof:name":"DA4 0AW",
    "wof:placetype":"postalcode"
},
  "geometry": {"coordinates":[0.21466480958463,51.36957550604113],"type":"Point"}
}