{
  "type": "Feature",
  "properties": {
    "date:inception_lower":"1980-01-01",
    "date:inception_upper":"1980-01-31",
    "iso:country":"GB",
    "wof:name":"DA4 0AW",
    "wof:placetype":"postalcode"
},
  "geometry": {"coordinates":[0.214665,51.369575],"type":"Point"}
}