{
  "type": "Feature",
  "properties": {
    "iso:country":"GB",
    "wof:name":"PE21 6LQ",
    "wof:placetype":"postalcode"
},
  "geometry": {"coordinates":[-0.02827515302752,52.98108193131429],"type":"Point"}
}