{
  "type": "Feature",
  "properties": {
    "iso:country": "GB",
    "wof:name": "PE21 6LQ",
    "wof:placetype": "postalcode"
  },
  "geometry": {"coordinates":[-0.028275,52.981082],"type":"Point"}
}
