{
  "type": "Feature",
  "properties": {
    "date:inception_lower": "1980-01-01",
    "date:inception_upper": "1980-01-01",
    "iso:country": "GB",
    "wof:name": "DD8 5PZ",
    "wof:placetype": "postalcode"
  },
  "geometry": {"coordinates":[-2.988909,56.666705],"type":"Point"}
}
