{
  "type": "Feature",
  "properties": {
    "iso:country":"GB",
    "wof:name":"EX13 7JJ",
    "wof:placetype":"postalcode"
},
  "geometry": {"coordinates":[-2.9918179618649,50.80350772325781],"type":"Point"}
}