{
  "type": "Feature",
  "properties": {
    "date:inception_lower": "1980-01-01",
    "date:inception_upper": "1980-01-01",
    "iso:country": "GB",
    "wof:name": "EX13 7JJ",
    "wof:placetype": "postalcode"
  },
  "geometry": {"coordinates":[-2.991818,50.803508],"type":"Point"}
}
