{
  "type": "Feature",
  "properties": {
    "iso:country": "GB",
    "wof:name": "MK11 4BF",
    "wof:placetype": "postalcode"
  },
  "geometry": {"coordinates":[-0.830358,52.04368],"type":"Point"}
}
