{
  "type": "Feature",
  "properties": {
    "date:inception_lower": "2017-08-01",
    "date:inception_upper": "2017-08-01",
    "iso:country": "GB",
    "wof:name": "MK11 4BF",
    "wof:placetype": "postalcode"
  },
  "geometry": {"coordinates":[-0.830358,52.04368],"type":"Point"}
}
