{
  "type": "Feature",
  "properties": {
    "iso:country":"GB",
    "wof:name":"B17 0LP",
    "wof:placetype":"postalcode"
},
  "geometry": {"coordinates":[-1.95083796520598,52.45221805814681],"type":"Point"}
}