{
  "type": "Feature",
  "properties": {
    "iso:country":"GB",
    "wof:name":"DN15 9UA",
    "wof:placetype":"postalcode"
},
  "geometry": {"coordinates":[-0.5890976923507,53.65385758361366],"type":"Point"}
}