{
  "type": "Feature",
  "properties": {
    "iso:country": "GB",
    "wof:name": "SO15 3EL",
    "wof:placetype": "postalcode"
  },
  "geometry": {"coordinates":[-1.4266,50.915209],"type":"Point"}
}
