{
  "type": "Feature",
  "properties": {
    "iso:country":"GB",
    "wof:name":"SO15 3EL",
    "wof:placetype":"postalcode"
},
  "geometry": {"coordinates":[-1.42659963502505,50.91520884043662],"type":"Point"}
}