{
  "type": "Feature",
  "properties": {
    "iso:country": "GB",
    "wof:name": "DL5 4YQ",
    "wof:placetype": "postalcode"
  },
  "geometry": {"coordinates":[-1.559514,54.635119],"type":"Point"}
}
