{
  "type": "Feature",
  "properties": {
    "iso:country":"GB",
    "wof:name":"DL5 4YQ",
    "wof:placetype":"postalcode"
},
  "geometry": {"coordinates":[-1.55951448858995,54.63511883664273],"type":"Point"}
}