{
  "type": "Feature",
  "properties": {
    "date:inception_lower":"1997-12-01",
    "date:inception_upper":"1997-12-31",
    "iso:country":"GB",
    "wof:name":"DL5 4YQ",
    "wof:placetype":"postalcode"
},
  "geometry": {"coordinates":[-1.559514,54.635119],"type":"Point"}
}