{
  "type": "Feature",
  "properties": {
    "date:inception_lower": "1980-01-01",
    "date:inception_upper": "1980-01-01",
    "iso:country": "GB",
    "wof:name": "DN9 2NH",
    "wof:placetype": "postalcode"
  },
  "geometry": {"coordinates":[-0.839694,53.474155],"type":"Point"}
}
