{
  "type": "Feature",
  "properties": {
    "iso:country":"GB",
    "wof:name":"DN9 2NH",
    "wof:placetype":"postalcode"
},
  "geometry": {"coordinates":[-0.83969388178346,53.47415522826304],"type":"Point"}
}