{
  "type": "Feature",
  "properties": {
    "date:inception_lower": "2004-08-01",
    "date:inception_upper": "2004-08-01",
    "iso:country": "GB",
    "wof:name": "PE38 9UX",
    "wof:placetype": "postalcode"
  },
  "geometry": {"coordinates":[0.382626,52.60883],"type":"Point"}
}
