{
  "type": "Feature",
  "properties": {
    "date:inception_lower": "1980-01-01",
    "date:inception_upper": "1980-01-01",
    "iso:country": "GB",
    "wof:name": "DN22 8JR",
    "wof:placetype": "postalcode"
  },
  "geometry": {"coordinates":[-0.991889,53.333243],"type":"Point"}
}
