{
  "type": "Feature",
  "properties": {
    "iso:country": "GB",
    "wof:name": "DN22 8JR",
    "wof:placetype": "postalcode"
  },
  "geometry": {"coordinates":[-0.991997,53.333125],"type":"Point"}
}
