{
  "type": "Feature",
  "properties": {
    "iso:country":"GB",
    "wof:name":"DN22 8JR",
    "wof:placetype":"postalcode"
},
  "geometry": {"coordinates":[-0.99199708751657,53.33312474340094],"type":"Point"}
}