{
  "type": "Feature",
  "properties": {
    "iso:country": "GB",
    "wof:name": "HP6 5QX",
    "wof:placetype": "postalcode"
  },
  "geometry": {"coordinates":[-0.62286,51.68164],"type":"Point"}
}
