{
  "type": "Feature",
  "properties": {
    "iso:country":"GB",
    "wof:name":"HP6 5QX",
    "wof:placetype":"postalcode"
},
  "geometry": {"coordinates":[-0.62285973119802,51.68164041859104],"type":"Point"}
}