{
  "type": "Feature",
  "properties": {
    "date:inception_lower":"1980-01-01",
    "date:inception_upper":"1980-01-31",
    "iso:country":"GB",
    "wof:name":"WS15 4BN",
    "wof:placetype":"postalcode"
},
  "geometry": {"coordinates":[-1.87869,52.741754],"type":"Point"}
}