{
  "type": "Feature",
  "properties": {
    "iso:country":"GB",
    "wof:name":"WS15 4BN",
    "wof:placetype":"postalcode"
},
  "geometry": {"coordinates":[-1.87869036616303,52.74175415112593],"type":"Point"}
}