{
  "type": "Feature",
  "properties": {
    "iso:country":"GB",
    "wof:name":"IG8 9AT",
    "wof:placetype":"postalcode"
},
  "geometry": {"coordinates":[0.0306909218783,51.60266497168896],"type":"Point"}
}