{
  "type": "Feature",
  "properties": {
    "date:inception_lower": "1997-12-01",
    "date:inception_upper": "1997-12-01",
    "iso:country": "GB",
    "wof:name": "SO22 5QH",
    "wof:placetype": "postalcode"
  },
  "geometry": {"coordinates":[-1.336085,51.061116],"type":"Point"}
}
