{
  "type": "Feature",
  "properties": {
    "iso:country":"GB",
    "wof:name":"TR1 1PE",
    "wof:placetype":"postalcode"
},
  "geometry": {"coordinates":[-5.04108715408783,50.26502974469759],"type":"Point"}
}