{
  "type": "Feature",
  "properties": {
    "iso:country": "GB",
    "wof:name": "PO7 6PB",
    "wof:placetype": "postalcode"
  },
  "geometry": {"coordinates":[-1.055175,50.901482],"type":"Point"}
}
