{
  "type": "Feature",
  "properties": {
    "iso:country":"GB",
    "wof:name":"KT17 3BA",
    "wof:placetype":"postalcode"
},
  "geometry": {"coordinates":[-0.24584335598175,51.33310556739918],"type":"Point"}
}