{
  "type": "Feature",
  "properties": {
    "iso:country":"GB",
    "wof:name":"B46 2NJ",
    "wof:placetype":"postalcode"
},
  "geometry": {"coordinates":[-1.61653246468132,52.51305412839513],"type":"Point"}
}