{
  "type": "Feature",
  "properties": {
    "iso:country":"GB",
    "wof:name":"AB15 6AB",
    "wof:placetype":"postalcode"
},
  "geometry": {"coordinates":[-2.15579307364879,57.14332121142509],"type":"Point"}
}