{
  "type": "Feature",
  "properties": {
    "iso:country":"GB",
    "wof:name":"KT7 0TP",
    "wof:placetype":"postalcode"
},
  "geometry": {"coordinates":[-0.32992664229013,51.39062780699624],"type":"Point"}
}