{
  "type": "Feature",
  "properties": {
    "iso:country": "GB",
    "wof:name": "CV34 5DF",
    "wof:placetype": "postalcode"
  },
  "geometry": {"coordinates":[-1.590291,52.294008],"type":"Point"}
}
