{
  "type": "Feature",
  "properties": {
    "iso:country": "GB",
    "wof:name": "WR9 0QF",
    "wof:placetype": "postalcode"
  },
  "geometry": {"coordinates":[-2.1784,52.311097],"type":"Point"}
}
