{
  "type": "Feature",
  "properties": {
    "iso:country":"GB",
    "wof:name":"WR9 0QF",
    "wof:placetype":"postalcode"
},
  "geometry": {"coordinates":[-2.17840630412653,52.31111016929345],"type":"Point"}
}