{
  "type": "Feature",
  "properties": {
    "date:inception_lower":"2010-07-01",
    "date:inception_upper":"2010-07-31",
    "iso:country":"GB",
    "wof:name":"WR9 0QF",
    "wof:placetype":"postalcode"
},
  "geometry": {"coordinates":[-2.1784,52.311097],"type":"Point"}
}