{
  "type": "Feature",
  "properties": {
    "iso:country":"GB",
    "wof:name":"PO7 8QB",
    "wof:placetype":"postalcode"
},
  "geometry": {"coordinates":[-1.00962593122183,50.88467507799201],"type":"Point"}
}