{
  "type": "Feature",
  "properties": {
    "date:inception_lower": "1980-01-01",
    "date:inception_upper": "1980-01-01",
    "iso:country": "GB",
    "wof:name": "TS16 0NW",
    "wof:placetype": "postalcode"
  },
  "geometry": {"coordinates":[-1.360893,54.523101],"type":"Point"}
}
