{
  "type": "Feature",
  "properties": {
    "iso:country":"GB",
    "wof:name":"TS16 0NW",
    "wof:placetype":"postalcode"
},
  "geometry": {"coordinates":[-1.36089324833564,54.52310122292732],"type":"Point"}
}