{
  "type": "Feature",
  "properties": {
    "iso:country": "GB",
    "wof:name": "DH2 2NB",
    "wof:placetype": "postalcode"
  },
  "geometry": {"coordinates":[-1.601238,54.849998],"type":"Point"}
}
