{
  "type": "Feature",
  "properties": {
    "iso:country":"GB",
    "wof:name":"DH2 2NB",
    "wof:placetype":"postalcode"
},
  "geometry": {"coordinates":[-1.60123777094355,54.84999834482515],"type":"Point"}
}