{
  "type": "Feature",
  "properties": {
    "iso:country":"GB",
    "wof:name":"FY5 3FR",
    "wof:placetype":"postalcode"
},
  "geometry": {"coordinates":[-3.02377107267897,53.87058968003372],"type":"Point"}
}