{
  "type": "Feature",
  "properties": {
    "iso:country": "GB",
    "wof:name": "FY5 3FR",
    "wof:placetype": "postalcode"
  },
  "geometry": {"coordinates":[-3.023771,53.87059],"type":"Point"}
}
