{
  "type": "Feature",
  "properties": {
    "iso:country":"GB",
    "wof:name":"BL6 5TB",
    "wof:placetype":"postalcode"
},
  "geometry": {"coordinates":[-2.5754730755201,53.58682692417953],"type":"Point"}
}