{
  "type": "Feature",
  "properties": {
    "iso:country":"GB",
    "wof:name":"IP3 9NJ",
    "wof:placetype":"postalcode"
},
  "geometry": {"coordinates":[1.1877416447268,52.03283189568396],"type":"Point"}
}