{
  "type": "Feature",
  "properties": {
    "iso:country": "GB",
    "wof:name": "WN7 3ND",
    "wof:placetype": "postalcode"
  },
  "geometry": {"coordinates":[-2.524032,53.482635],"type":"Point"}
}
