{
  "type": "Feature",
  "properties": {
    "iso:country":"GB",
    "wof:name":"WN7 3ND",
    "wof:placetype":"postalcode"
},
  "geometry": {"coordinates":[-2.52403182001308,53.48263542789865],"type":"Point"}
}