{
  "type": "Feature",
  "properties": {
    "iso:country":"GB",
    "wof:name":"CV4 9NF",
    "wof:placetype":"postalcode"
},
  "geometry": {"coordinates":[-1.58321298896224,52.40577116544416],"type":"Point"}
}