{
  "type": "Feature",
  "properties": {
    "date:inception_lower": "1980-01-01",
    "date:inception_upper": "1980-01-01",
    "iso:country": "GB",
    "wof:name": "CV4 9NF",
    "wof:placetype": "postalcode"
  },
  "geometry": {"coordinates":[-1.583213,52.405771],"type":"Point"}
}
