{
  "type": "Feature",
  "properties": {
    "iso:country":"GB",
    "wof:name":"CH6 6EF",
    "wof:placetype":"postalcode"
},
  "geometry": {"coordinates":[-3.17336917881278,53.27029264021818],"type":"Point"}
}