{
  "type": "Feature",
  "properties": {
    "iso:country": "GB",
    "wof:name": "BA3 4SW",
    "wof:placetype": "postalcode"
  },
  "geometry": {"coordinates":[-2.579656,51.274818],"type":"Point"}
}
