{
  "type": "Feature",
  "properties": {
    "iso:country":"GB",
    "wof:name":"BA3 4SW",
    "wof:placetype":"postalcode"
},
  "geometry": {"coordinates":[-2.57965634758749,51.27481783261674],"type":"Point"}
}