{
  "type": "Feature",
  "properties": {
    "date:inception_lower": "1999-12-01",
    "date:inception_upper": "1999-12-01",
    "iso:country": "GB",
    "wof:name": "BA3 4SW",
    "wof:placetype": "postalcode"
  },
  "geometry": {"coordinates":[-2.579656,51.274818],"type":"Point"}
}
