{
  "type": "Feature",
  "properties": {
    "iso:country": "GB",
    "wof:name": "HA2 8YR",
    "wof:placetype": "postalcode"
  },
  "geometry": {"coordinates":[-0.329664,51.585229],"type":"Point"}
}
