{
  "type": "Feature",
  "properties": {
    "iso:country":"GB",
    "wof:name":"G52 3LA",
    "wof:placetype":"postalcode"
},
  "geometry": {"coordinates":[-4.35783473962843,55.84304506132952],"type":"Point"}
}