{
  "type": "Feature",
  "properties": {
    "date:inception_lower": "1980-01-01",
    "date:inception_upper": "1980-01-01",
    "iso:country": "GB",
    "wof:name": "G52 3LA",
    "wof:placetype": "postalcode"
  },
  "geometry": {"coordinates":[-4.357835,55.843045],"type":"Point"}
}
