{
  "type": "Feature",
  "properties": {
    "date:inception_lower": "1980-01-01",
    "date:inception_upper": "1980-01-01",
    "iso:country": "GB",
    "wof:name": "NG34 7HU",
    "wof:placetype": "postalcode"
  },
  "geometry": {"coordinates":[-0.397243,52.998073],"type":"Point"}
}
