{
  "type": "Feature",
  "properties": {
    "iso:country":"GB",
    "wof:name":"NG34 7HU",
    "wof:placetype":"postalcode"
},
  "geometry": {"coordinates":[-0.3972425665316,52.9980734863603],"type":"Point"}
}