{
  "type": "Feature",
  "properties": {
    "iso:country":"GB",
    "wof:name":"LS28 5RF",
    "wof:placetype":"postalcode"
},
  "geometry": {"coordinates":[-1.68571428008351,53.81433711179588],"type":"Point"}
}