{
  "type": "Feature",
  "properties": {
    "iso:country":"GB",
    "wof:name":"BH5 1HP",
    "wof:placetype":"postalcode"
},
  "geometry": {"coordinates":[-1.83690178687474,50.7238011232754],"type":"Point"}
}