{
  "type": "Feature",
  "properties": {
    "date:inception_lower": "1980-01-01",
    "date:inception_upper": "1980-01-01",
    "iso:country": "GB",
    "wof:name": "PO40 9BX",
    "wof:placetype": "postalcode"
  },
  "geometry": {"coordinates":[-1.512511,50.685334],"type":"Point"}
}
