{
  "type": "Feature",
  "properties": {
    "iso:country": "GB",
    "wof:name": "NN3 7AR",
    "wof:placetype": "postalcode"
  },
  "geometry": {"coordinates":[-0.855895,52.279068],"type":"Point"}
}
