{
  "type": "Feature",
  "properties": {
    "date:inception_lower": "2018-10-01",
    "date:inception_upper": "2018-10-01",
    "iso:country": "GB",
    "wof:name": "PE2 8WL",
    "wof:placetype": "postalcode"
  },
  "geometry": {"coordinates":[-0.205489,52.546789],"type":"Point"}
}
