{
  "type": "Feature",
  "properties": {
    "iso:country": "GB",
    "wof:name": "G44 5NA",
    "wof:placetype": "postalcode"
  },
  "geometry": {"coordinates":[-4.226828,55.812746],"type":"Point"}
}
