{
  "type": "Feature",
  "properties": {
    "iso:country":"GB",
    "wof:name":"G44 5NA",
    "wof:placetype":"postalcode"
},
  "geometry": {"coordinates":[-4.22682850665295,55.81274577242564],"type":"Point"}
}