{
  "type": "Feature",
  "properties": {
    "iso:country":"GB",
    "wof:name":"FY6 8BY",
    "wof:placetype":"postalcode"
},
  "geometry": {"coordinates":[-2.99147114341459,53.83344270510536],"type":"Point"}
}