{
  "type": "Feature",
  "properties": {
    "iso:country":"GB",
    "wof:name":"WA3 3ND",
    "wof:placetype":"postalcode"
},
  "geometry": {"coordinates":[-2.59251477348821,53.47676943505662],"type":"Point"}
}