{
  "type": "Feature",
  "properties": {
    "iso:country":"GB",
    "wof:name":"DY8 4PF",
    "wof:placetype":"postalcode"
},
  "geometry": {"coordinates":[-2.15814746781416,52.4664431575669],"type":"Point"}
}