{
  "type": "Feature",
  "properties": {
    "iso:country":"GB",
    "wof:name":"M45 7QN",
    "wof:placetype":"postalcode"
},
  "geometry": {"coordinates":[-2.31031765011479,53.54183358473881],"type":"Point"}
}