{
  "type": "Feature",
  "properties": {
    "iso:country":"GB",
    "wof:name":"NE3 1YF",
    "wof:placetype":"postalcode"
},
  "geometry": {"coordinates":[-1.60778834334707,55.00311984781625],"type":"Point"}
}