{
  "type": "Feature",
  "properties": {
    "iso:country":"GB",
    "wof:name":"TR10 8DD",
    "wof:placetype":"postalcode"
},
  "geometry": {"coordinates":[-5.10750137010344,50.17348379447535],"type":"Point"}
}