{
  "type": "Feature",
  "properties": {
    "iso:country":"GB",
    "wof:name":"CH4 8NB",
    "wof:placetype":"postalcode"
},
  "geometry": {"coordinates":[-2.92539897268231,53.17446672431598],"type":"Point"}
}