{
  "type": "Feature",
  "properties": {
    "date:inception_lower":"1980-01-01",
    "date:inception_upper":"1980-01-31",
    "iso:country":"GB",
    "wof:name":"S72 8TG",
    "wof:placetype":"postalcode"
},
  "geometry": {"coordinates":[-1.414439,53.581091],"type":"Point"}
}