{
  "type": "Feature",
  "properties": {
    "iso:country": "GB",
    "wof:name": "S72 8TG",
    "wof:placetype": "postalcode"
  },
  "geometry": {"coordinates":[-1.414439,53.581091],"type":"Point"}
}
