{
  "type": "Feature",
  "properties": {
    "iso:country":"GB",
    "wof:name":"S72 8TG",
    "wof:placetype":"postalcode"
},
  "geometry": {"coordinates":[-1.41427477903219,53.58095523400764],"type":"Point"}
}