{
  "type": "Feature",
  "properties": {
    "iso:country":"GB",
    "wof:name":"WR11 2FP",
    "wof:placetype":"postalcode"
},
  "geometry": {"coordinates":[-1.95028192815663,52.08064931571703],"type":"Point"}
}