{
  "type": "Feature",
  "properties": {
    "iso:country":"GB",
    "wof:name":"NR16 2RH",
    "wof:placetype":"postalcode"
},
  "geometry": {"coordinates":[0.87298321810064,52.44906899195407],"type":"Point"}
}