{
  "type": "Feature",
  "properties": {
    "iso:country": "GB",
    "wof:name": "NR16 2RH",
    "wof:placetype": "postalcode"
  },
  "geometry": {"coordinates":[0.872983,52.449069],"type":"Point"}
}
