{
  "type": "Feature",
  "properties": {
    "iso:country":"GB",
    "wof:name":"TQ1 4TF",
    "wof:placetype":"postalcode"
},
  "geometry": {"coordinates":[-3.52378881462127,50.50623138790336],"type":"Point"}
}