{
  "type": "Feature",
  "properties": {
    "date:inception_lower": "1980-01-01",
    "date:inception_upper": "1980-01-01",
    "iso:country": "GB",
    "wof:name": "TQ1 4TF",
    "wof:placetype": "postalcode"
  },
  "geometry": {"coordinates":[-3.523789,50.506231],"type":"Point"}
}
