{
  "type": "Feature",
  "properties": {
    "iso:country": "GB",
    "wof:name": "CF81 9QH",
    "wof:placetype": "postalcode"
  },
  "geometry": {"coordinates":[-3.281354,51.742967],"type":"Point"}
}
