{
  "type": "Feature",
  "properties": {
    "iso:country":"GB",
    "wof:name":"CF81 9QH",
    "wof:placetype":"postalcode"
},
  "geometry": {"coordinates":[-3.28127109742571,51.74296342727593],"type":"Point"}
}