{
  "type": "Feature",
  "properties": {
    "date:inception_lower": "2005-10-01",
    "date:inception_upper": "2005-10-01",
    "iso:country": "GB",
    "wof:name": "HA3 5BU",
    "wof:placetype": "postalcode"
  },
  "geometry": {"coordinates":[-0.33522,51.593168],"type":"Point"}
}
