{
  "type": "Feature",
  "properties": {
    "iso:country":"GB",
    "wof:name":"HA3 5BU",
    "wof:placetype":"postalcode"
},
  "geometry": {"coordinates":[-0.33531483591824,51.59315768842237],"type":"Point"}
}