{
  "type": "Feature",
  "properties": {
    "iso:country":"GB",
    "wof:name":"UB9 6NT",
    "wof:placetype":"postalcode"
},
  "geometry": {"coordinates":[-0.48114448124461,51.60389348736233],"type":"Point"}
}