{
  "type": "Feature",
  "properties": {
    "iso:country":"GB",
    "wof:name":"NE7 7QS",
    "wof:placetype":"postalcode"
},
  "geometry": {"coordinates":[-1.58782920833153,55.00111289310352],"type":"Point"}
}