{
  "type": "Feature",
  "properties": {
    "iso:country": "GB",
    "wof:name": "BS48 3PW",
    "wof:placetype": "postalcode"
  },
  "geometry": {"coordinates":[-2.724663,51.420379],"type":"Point"}
}
