{
  "type": "Feature",
  "properties": {
    "iso:country":"GB",
    "wof:name":"BS48 3PW",
    "wof:placetype":"postalcode"
},
  "geometry": {"coordinates":[-2.72466261972315,51.42037926179776],"type":"Point"}
}