{
  "type": "Feature",
  "properties": {
    "iso:country":"GB",
    "wof:name":"W1G 7HU",
    "wof:placetype":"postalcode"
},
  "geometry": {"coordinates":[-0.1475994165863,51.52081561132383],"type":"Point"}
}