{
  "type": "Feature",
  "properties": {
    "iso:country":"GB",
    "wof:name":"CT2 0DA",
    "wof:placetype":"postalcode"
},
  "geometry": {"coordinates":[1.12542062217646,51.29507329761606],"type":"Point"}
}