{
  "type": "Feature",
  "properties": {
    "iso:country":"GB",
    "wof:name":"WD19 6HP",
    "wof:placetype":"postalcode"
},
  "geometry": {"coordinates":[-0.39143101198074,51.62217533673135],"type":"Point"}
}