{
  "type": "Feature",
  "properties": {
    "iso:country":"GB",
    "wof:name":"EX8 2HS",
    "wof:placetype":"postalcode"
},
  "geometry": {"coordinates":[-3.3948274608456,50.61880037220136],"type":"Point"}
}