{
  "type": "Feature",
  "properties": {
    "date:inception_lower":"1980-01-01",
    "date:inception_upper":"1980-01-31",
    "iso:country":"GB",
    "wof:name":"EX8 2HS",
    "wof:placetype":"postalcode"
},
  "geometry": {"coordinates":[-3.394827,50.6188],"type":"Point"}
}