{
  "type": "Feature",
  "properties": {
    "iso:country":"GB",
    "wof:name":"WD17 1HD",
    "wof:placetype":"postalcode"
},
  "geometry": {"coordinates":[-0.3976829940309,51.65752765637595],"type":"Point"}
}