{
  "type": "Feature",
  "properties": {
    "iso:country": "GB",
    "wof:name": "WD17 1HD",
    "wof:placetype": "postalcode"
  },
  "geometry": {"coordinates":[-0.397683,51.657528],"type":"Point"}
}
