{
  "type": "Feature",
  "properties": {
    "date:inception_lower":"2001-06-01",
    "date:inception_upper":"2001-06-30",
    "iso:country":"GB",
    "wof:name":"ST5 2ST",
    "wof:placetype":"postalcode"
},
  "geometry": {"coordinates":[-2.233968,53.010726],"type":"Point"}
}