{
  "type": "Feature",
  "properties": {
    "iso:country":"GB",
    "wof:name":"ST5 2ST",
    "wof:placetype":"postalcode"
},
  "geometry": {"coordinates":[-2.23396804237006,53.01072647944582],"type":"Point"}
}