{
  "type": "Feature",
  "properties": {
    "iso:country": "GB",
    "wof:name": "ST5 2ST",
    "wof:placetype": "postalcode"
  },
  "geometry": {"coordinates":[-2.233923,53.010735],"type":"Point"}
}
