{
  "type": "Feature",
  "properties": {
    "iso:country":"GB",
    "wof:name":"UB1 1PL",
    "wof:placetype":"postalcode"
},
  "geometry": {"coordinates":[-0.38858615631762,51.51317827272816],"type":"Point"}
}