{
  "type": "Feature",
  "properties": {
    "iso:country":"GB",
    "wof:name":"SL4 4PR",
    "wof:placetype":"postalcode"
},
  "geometry": {"coordinates":[-0.6521404102698,51.47512120875513],"type":"Point"}
}