{
  "type": "Feature",
  "properties": {
    "iso:country": "GB",
    "wof:name": "CB6 1LH",
    "wof:placetype": "postalcode"
  },
  "geometry": {"coordinates":[0.293893,52.459359],"type":"Point"}
}
