{
  "type": "Feature",
  "properties": {
    "iso:country":"GB",
    "wof:name":"CB6 1LH",
    "wof:placetype":"postalcode"
},
  "geometry": {"coordinates":[0.2938933630166,52.459358881052],"type":"Point"}
}