{
  "type": "Feature",
  "properties": {
    "iso:country": "GB",
    "wof:name": "BN7 2JB",
    "wof:placetype": "postalcode"
  },
  "geometry": {"coordinates":[0.015102,50.88294],"type":"Point"}
}
