{
  "type": "Feature",
  "properties": {
    "iso:country":"GB",
    "wof:name":"BN7 2JB",
    "wof:placetype":"postalcode"
},
  "geometry": {"coordinates":[0.01510204548234,50.88294037305634],"type":"Point"}
}