{
  "type": "Feature",
  "properties": {
    "iso:country":"GB",
    "wof:name":"LS17 6PP",
    "wof:placetype":"postalcode"
},
  "geometry": {"coordinates":[-1.52754643559868,53.84019856422518],"type":"Point"}
}