{
  "type": "Feature",
  "properties": {
    "iso:country":"GB",
    "wof:name":"BS5 0AL",
    "wof:placetype":"postalcode"
},
  "geometry": {"coordinates":[-2.56613901885265,51.45424282629968],"type":"Point"}
}