{
  "type": "Feature",
  "properties": {
    "iso:country": "GB",
    "wof:name": "RG27 0LN",
    "wof:placetype": "postalcode"
  },
  "geometry": {"coordinates":[-0.976427,51.342783],"type":"Point"}
}
