{
  "type": "Feature",
  "properties": {
    "date:inception_lower":"1980-01-01",
    "date:inception_upper":"1980-01-31",
    "iso:country":"GB",
    "wof:name":"RG27 0LN",
    "wof:placetype":"postalcode"
},
  "geometry": {"coordinates":[-0.976427,51.342783],"type":"Point"}
}