{
  "type": "Feature",
  "properties": {
    "iso:country":"GB",
    "wof:name":"TA7 8LE",
    "wof:placetype":"postalcode"
},
  "geometry": {"coordinates":[-2.92136944395827,51.16094408510742],"type":"Point"}
}