{
  "type": "Feature",
  "properties": {
    "date:inception_lower": "1994-05-01",
    "date:inception_upper": "1994-05-01",
    "iso:country": "GB",
    "wof:name": "CV1 2HL",
    "wof:placetype": "postalcode"
  },
  "geometry": {"coordinates":[-1.50936,52.403895],"type":"Point"}
}
