{
  "type": "Feature",
  "properties": {
    "iso:country":"GB",
    "wof:name":"SY23 2AT",
    "wof:placetype":"postalcode"
},
  "geometry": {"coordinates":[-4.08695500147851,52.41442157696865],"type":"Point"}
}