{
  "type": "Feature",
  "properties": {
    "iso:country": "GB",
    "wof:name": "SY23 2AT",
    "wof:placetype": "postalcode"
  },
  "geometry": {"coordinates":[-4.086955,52.414422],"type":"Point"}
}
