{
  "type": "Feature",
  "properties": {
    "iso:country": "GB",
    "wof:name": "NN11 3RB",
    "wof:placetype": "postalcode"
  },
  "geometry": {"coordinates":[-1.209476,52.169311],"type":"Point"}
}
