{
  "type": "Feature",
  "properties": {
    "iso:country":"GB",
    "wof:name":"NN11 3RB",
    "wof:placetype":"postalcode"
},
  "geometry": {"coordinates":[-1.20947590158392,52.16931143010397],"type":"Point"}
}