{
  "type": "Feature",
  "properties": {
    "date:inception_lower": "2021-08-01",
    "date:inception_upper": "2021-08-01",
    "iso:country": "GB",
    "wof:name": "NG34 4FN",
    "wof:placetype": "postalcode"
  },
  "geometry": {"coordinates":[-0.409431,52.996336],"type":"Point"}
}
