{
  "type": "Feature",
  "properties": {
    "date:inception_lower": "2022-11-01",
    "date:inception_upper": "2022-11-01",
    "iso:country": "GB",
    "wof:name": "B11 2FG",
    "wof:placetype": "postalcode"
  },
  "geometry": {"coordinates":[-1.845632,52.453365],"type":"Point"}
}
