{
  "type": "Feature",
  "properties": {
    "date:inception_lower": "1980-01-01",
    "date:inception_upper": "1980-01-01",
    "iso:country": "GB",
    "wof:name": "PL19 8QT",
    "wof:placetype": "postalcode"
  },
  "geometry": {"coordinates":[-4.215962,50.555756],"type":"Point"}
}
