{
  "type": "Feature",
  "properties": {
    "iso:country":"GB",
    "wof:name":"CH60 3RH",
    "wof:placetype":"postalcode"
},
  "geometry": {"coordinates":[-3.08519356841267,53.31507603379271],"type":"Point"}
}