{
  "type": "Feature",
  "properties": {
    "iso:country":"GB",
    "wof:name":"RH1 5QL",
    "wof:placetype":"postalcode"
},
  "geometry": {"coordinates":[-0.15016781509596,51.20308992076574],"type":"Point"}
}