{
  "type": "Feature",
  "properties": {
    "iso:country":"GB",
    "wof:name":"NG5 1BJ",
    "wof:placetype":"postalcode"
},
  "geometry": {"coordinates":[-1.15573086866874,52.97444959364913],"type":"Point"}
}