{
  "type": "Feature",
  "properties": {
    "date:inception_lower":"1985-10-01",
    "date:inception_upper":"1985-10-31",
    "iso:country":"GB",
    "wof:name":"SR6 7LN",
    "wof:placetype":"postalcode"
},
  "geometry": {"coordinates":[-1.366551,54.957118],"type":"Point"}
}