{
  "type": "Feature",
  "properties": {
    "date:inception_lower": "1994-12-01",
    "date:inception_upper": "1994-12-01",
    "iso:country": "GB",
    "wof:name": "TN23 4UX",
    "wof:placetype": "postalcode"
  },
  "geometry": {"coordinates":[0.848275,51.144919],"type":"Point"}
}
