{
  "type": "Feature",
  "properties": {
    "iso:country":"GB",
    "wof:name":"PE11 1AB",
    "wof:placetype":"postalcode"
},
  "geometry": {"coordinates":[-0.15344135056941,52.78675535499563],"type":"Point"}
}