{
  "type": "Feature",
  "properties": {
    "date:inception_lower": "2020-10-01",
    "date:inception_upper": "2020-10-01",
    "iso:country": "GB",
    "wof:name": "N3 3DN",
    "wof:placetype": "postalcode"
  },
  "geometry": {"coordinates":[-0.196948,51.597646],"type":"Point"}
}
