{
  "type": "Feature",
  "properties": {
    "iso:country":"GB",
    "wof:name":"EH8 9RL",
    "wof:placetype":"postalcode"
},
  "geometry": {"coordinates":[-3.17803950539555,55.9417605530714],"type":"Point"}
}