{
  "type": "Feature",
  "properties": {
    "iso:country":"GB",
    "wof:name":"KT4 7BB",
    "wof:placetype":"postalcode"
},
  "geometry": {"coordinates":[-0.24781437800227,51.37138964534937],"type":"Point"}
}