{
  "type": "Feature",
  "properties": {
    "iso:country":"GB",
    "wof:name":"GL4 6UB",
    "wof:placetype":"postalcode"
},
  "geometry": {"coordinates":[-2.23985585017707,51.84431749866521],"type":"Point"}
}