{
  "type": "Feature",
  "properties": {
    "iso:country":"GB",
    "wof:name":"B31 4LA",
    "wof:placetype":"postalcode"
},
  "geometry": {"coordinates":[-1.97780922629676,52.39500450098654],"type":"Point"}
}