{
  "type": "Feature",
  "properties": {
    "iso:country": "GB",
    "wof:name": "B31 4LA",
    "wof:placetype": "postalcode"
  },
  "geometry": {"coordinates":[-1.977809,52.395004],"type":"Point"}
}
