{
  "type": "Feature",
  "properties": {
    "iso:country": "GB",
    "wof:name": "CM2 8RX",
    "wof:placetype": "postalcode"
  },
  "geometry": {"coordinates":[0.470969,51.695677],"type":"Point"}
}
