{
  "type": "Feature",
  "properties": {
    "iso:country": "GB",
    "wof:name": "NP20 5FD",
    "wof:placetype": "postalcode"
  },
  "geometry": {"coordinates":[-2.999184,51.59129],"type":"Point"}
}
