{
  "type": "Feature",
  "properties": {
    "iso:country":"GB",
    "wof:name":"PR3 0UY",
    "wof:placetype":"postalcode"
},
  "geometry": {"coordinates":[-2.86289192122484,53.85425565178908],"type":"Point"}
}