{
  "type": "Feature",
  "properties": {
    "date:inception_lower": "2020-06-01",
    "date:inception_upper": "2020-06-01",
    "iso:country": "GB",
    "wof:name": "SA14 9PX",
    "wof:placetype": "postalcode"
  },
  "geometry": {"coordinates":[-4.102037,51.679147],"type":"Point"}
}
