{
  "type": "Feature",
  "properties": {
    "iso:country": "GB",
    "wof:name": "IP22 2TG",
    "wof:placetype": "postalcode"
  },
  "geometry": {"coordinates":[0.876123,52.381366],"type":"Point"}
}
