{
  "type": "Feature",
  "properties": {
    "iso:country":"GB",
    "wof:name":"IP22 2TG",
    "wof:placetype":"postalcode"
},
  "geometry": {"coordinates":[0.87612266011735,52.38136563461212],"type":"Point"}
}