{
  "type": "Feature",
  "properties": {
    "iso:country": "GB",
    "wof:name": "W3 9DA",
    "wof:placetype": "postalcode"
  },
  "geometry": {"coordinates":[-0.278853,51.50806],"type":"Point"}
}
