{
  "type": "Feature",
  "properties": {
    "iso:country":"GB",
    "wof:name":"TQ7 3BQ",
    "wof:placetype":"postalcode"
},
  "geometry": {"coordinates":[-3.80810893677071,50.26756996116904],"type":"Point"}
}