{
  "type": "Feature",
  "properties": {
    "iso:country": "GB",
    "wof:name": "TQ5 0HJ",
    "wof:placetype": "postalcode"
  },
  "geometry": {"coordinates":[-3.550118,50.389001],"type":"Point"}
}
