{
  "type": "Feature",
  "properties": {
    "date:inception_lower":"2003-09-01",
    "date:inception_upper":"2003-09-30",
    "iso:country":"GB",
    "wof:name":"TQ5 0HJ",
    "wof:placetype":"postalcode"
},
  "geometry": {"coordinates":[-3.550118,50.389001],"type":"Point"}
}