{
  "type": "Feature",
  "properties": {
    "iso:country":"GB",
    "wof:name":"M45 8LQ",
    "wof:placetype":"postalcode"
},
  "geometry": {"coordinates":[-2.27025821325535,53.55438877618209],"type":"Point"}
}