{
  "type": "Feature",
  "properties": {
    "iso:country":"GB",
    "wof:name":"NP16 5XJ",
    "wof:placetype":"postalcode"
},
  "geometry": {"coordinates":[-2.67521676096014,51.64228051192532],"type":"Point"}
}