{
  "type": "Feature",
  "properties": {
    "iso:country": "GB",
    "wof:name": "IP23 8BP",
    "wof:placetype": "postalcode"
  },
  "geometry": {"coordinates":[1.111403,52.324822],"type":"Point"}
}
