{
  "type": "Feature",
  "properties": {
    "iso:country":"GB",
    "wof:name":"TN27 0ER",
    "wof:placetype":"postalcode"
},
  "geometry": {"coordinates":[0.78801733029714,51.18567623658361],"type":"Point"}
}