{
  "type": "Feature",
  "properties": {
    "iso:country": "GB",
    "wof:name": "TN27 0ER",
    "wof:placetype": "postalcode"
  },
  "geometry": {"coordinates":[0.788017,51.185676],"type":"Point"}
}
