{
  "type": "Feature",
  "properties": {
    "iso:country": "GB",
    "wof:name": "TA4 1NZ",
    "wof:placetype": "postalcode"
  },
  "geometry": {"coordinates":[-3.189908,51.041833],"type":"Point"}
}
