{
  "type": "Feature",
  "properties": {
    "iso:country":"GB",
    "wof:name":"UB3 2AX",
    "wof:placetype":"postalcode"
},
  "geometry": {"coordinates":[-0.42186181386905,51.51236276826209],"type":"Point"}
}