{
  "type": "Feature",
  "properties": {
    "iso:country": "GB",
    "wof:name": "SO14 1PW",
    "wof:placetype": "postalcode"
  },
  "geometry": {"coordinates":[-1.39339,50.904943],"type":"Point"}
}
