{
  "type": "Feature",
  "properties": {
    "iso:country": "GB",
    "wof:name": "DN17 1RQ",
    "wof:placetype": "postalcode"
  },
  "geometry": {"coordinates":[-0.678218,53.566819],"type":"Point"}
}
