{
  "type": "Feature",
  "properties": {
    "date:inception_lower": "1980-01-01",
    "date:inception_upper": "1980-01-01",
    "iso:country": "GB",
    "wof:name": "DN17 1RQ",
    "wof:placetype": "postalcode"
  },
  "geometry": {"coordinates":[-0.678218,53.566819],"type":"Point"}
}
