{
  "type": "Feature",
  "properties": {
    "iso:country":"GB",
    "wof:name":"DD4 6LF",
    "wof:placetype":"postalcode"
},
  "geometry": {"coordinates":[-2.94319734970308,56.46822758917505],"type":"Point"}
}