{
  "type": "Feature",
  "properties": {
    "date:inception_lower": "1980-01-01",
    "date:inception_upper": "1980-01-01",
    "iso:country": "GB",
    "wof:name": "CA5 6QP",
    "wof:placetype": "postalcode"
  },
  "geometry": {"coordinates":[-3.062254,54.846929],"type":"Point"}
}
