{
  "type": "Feature",
  "properties": {
    "iso:country": "GB",
    "wof:name": "BS6 5UL",
    "wof:placetype": "postalcode"
  },
  "geometry": {"coordinates":[-2.596653,51.462093],"type":"Point"}
}
