{
  "type": "Feature",
  "properties": {
    "date:inception_lower": "1983-03-01",
    "date:inception_upper": "1983-03-01",
    "iso:country": "GB",
    "wof:name": "LS15 4JZ",
    "wof:placetype": "postalcode"
  },
  "geometry": {"coordinates":[-1.397007,53.830643],"type":"Point"}
}
