{
  "type": "Feature",
  "properties": {
    "iso:country":"GB",
    "wof:name":"W3 0UE",
    "wof:placetype":"postalcode"
},
  "geometry": {"coordinates":[-0.25693719856705,51.50633201841681],"type":"Point"}
}