{
  "type": "Feature",
  "properties": {
    "date:inception_lower": "1980-01-01",
    "date:inception_upper": "1980-01-01",
    "iso:country": "GB",
    "wof:name": "EH13 0BR",
    "wof:placetype": "postalcode"
  },
  "geometry": {"coordinates":[-3.247501,55.904613],"type":"Point"}
}
