{
  "type": "Feature",
  "properties": {
    "iso:country":"GB",
    "wof:name":"EH13 0BR",
    "wof:placetype":"postalcode"
},
  "geometry": {"coordinates":[-3.24750061317912,55.90461320193882],"type":"Point"}
}