{
  "type": "Feature",
  "properties": {
    "iso:country": "GB",
    "wof:name": "GL13 9TE",
    "wof:placetype": "postalcode"
  },
  "geometry": {"coordinates":[-2.467036,51.692008],"type":"Point"}
}
