{
  "type": "Feature",
  "properties": {
    "iso:country":"GB",
    "wof:name":"GL13 9TE",
    "wof:placetype":"postalcode"
},
  "geometry": {"coordinates":[-2.46703597761015,51.69200815978643],"type":"Point"}
}