{
  "type": "Feature",
  "properties": {
    "date:inception_lower": "2023-04-01",
    "date:inception_upper": "2023-04-01",
    "iso:country": "GB",
    "wof:name": "PO19 6HD",
    "wof:placetype": "postalcode"
  },
  "geometry": {"coordinates":[-0.765906,50.84783],"type":"Point"}
}
