{
  "type": "Feature",
  "properties": {
    "iso:country":"GB",
    "wof:name":"OX4 1RF",
    "wof:placetype":"postalcode"
},
  "geometry": {"coordinates":[-1.23556623196863,51.74188256619467],"type":"Point"}
}