{
  "type": "Feature",
  "properties": {
    "iso:country":"GB",
    "wof:name":"CW3 9BS",
    "wof:placetype":"postalcode"
},
  "geometry": {"coordinates":[-2.37114536188472,53.02457113256978],"type":"Point"}
}