{
  "type": "Feature",
  "properties": {
    "date:inception_lower": "1980-01-01",
    "date:inception_upper": "1980-01-01",
    "iso:country": "GB",
    "wof:name": "CW3 9BS",
    "wof:placetype": "postalcode"
  },
  "geometry": {"coordinates":[-2.370994,53.024238],"type":"Point"}
}
