{
  "type": "Feature",
  "properties": {
    "iso:country": "GB",
    "wof:name": "B43 6QP",
    "wof:placetype": "postalcode"
  },
  "geometry": {"coordinates":[-1.949112,52.546153],"type":"Point"}
}
