{
  "type": "Feature",
  "properties": {
    "iso:country":"GB",
    "wof:name":"CF3 0ND",
    "wof:placetype":"postalcode"
},
  "geometry": {"coordinates":[-3.09338782981513,51.52864937103596],"type":"Point"}
}