{
  "type": "Feature",
  "properties": {
    "iso:country": "GB",
    "wof:name": "GL15 6LW",
    "wof:placetype": "postalcode"
  },
  "geometry": {"coordinates":[-2.571632,51.751571],"type":"Point"}
}
