{
  "type": "Feature",
  "properties": {
    "date:inception_lower": "1980-01-01",
    "date:inception_upper": "1980-01-01",
    "iso:country": "GB",
    "wof:name": "GL15 6LW",
    "wof:placetype": "postalcode"
  },
  "geometry": {"coordinates":[-2.571632,51.751571],"type":"Point"}
}
