{
  "type": "Feature",
  "properties": {
    "iso:country":"GB",
    "wof:name":"YO25 8BH",
    "wof:placetype":"postalcode"
},
  "geometry": {"coordinates":[-0.29337157362705,53.98417851138876],"type":"Point"}
}