{
  "type": "Feature",
  "properties": {
    "date:inception_lower":"1980-01-01",
    "date:inception_upper":"1980-01-31",
    "iso:country":"GB",
    "wof:name":"YO25 8BH",
    "wof:placetype":"postalcode"
},
  "geometry": {"coordinates":[-0.304955,53.986925],"type":"Point"}
}