{
  "type": "Feature",
  "properties": {
    "iso:country":"GB",
    "wof:name":"TN15 6RG",
    "wof:placetype":"postalcode"
},
  "geometry": {"coordinates":[0.21185890491631,51.30626258313475],"type":"Point"}
}