{
  "type": "Feature",
  "properties": {
    "date:inception_lower": "2007-04-01",
    "date:inception_upper": "2007-04-01",
    "iso:country": "GB",
    "wof:name": "CR0 2NQ",
    "wof:placetype": "postalcode"
  },
  "geometry": {"coordinates":[-0.101896,51.390645],"type":"Point"}
}
