{
  "type": "Feature",
  "properties": {
    "iso:country":"GB",
    "wof:name":"TR13 0EE",
    "wof:placetype":"postalcode"
},
  "geometry": {"coordinates":[-5.23175551194613,50.15764807253903],"type":"Point"}
}