{
  "type": "Feature",
  "properties": {
    "date:inception_lower": "1999-12-01",
    "date:inception_upper": "1999-12-01",
    "iso:country": "GB",
    "wof:name": "NG13 8QA",
    "wof:placetype": "postalcode"
  },
  "geometry": {"coordinates":[-0.94569,52.946981],"type":"Point"}
}
