{
  "type": "Feature",
  "properties": {
    "iso:country":"GB",
    "wof:name":"NG13 8QA",
    "wof:placetype":"postalcode"
},
  "geometry": {"coordinates":[-0.94568999327689,52.94698150349881],"type":"Point"}
}