{
  "type": "Feature",
  "properties": {
    "date:inception_lower": "1980-01-01",
    "date:inception_upper": "1980-01-01",
    "iso:country": "GB",
    "wof:name": "SN4 8BA",
    "wof:placetype": "postalcode"
  },
  "geometry": {"coordinates":[-1.893744,51.545864],"type":"Point"}
}
