{
  "type": "Feature",
  "properties": {
    "iso:country":"GB",
    "wof:name":"SN4 8BA",
    "wof:placetype":"postalcode"
},
  "geometry": {"coordinates":[-1.89374368552704,51.54586423005838],"type":"Point"}
}