{
  "type": "Feature",
  "properties": {
    "iso:country": "GB",
    "wof:name": "SE18 5LD",
    "wof:placetype": "postalcode"
  },
  "geometry": {"coordinates":[0.053672,51.490757],"type":"Point"}
}
