{
  "type": "Feature",
  "properties": {
    "date:inception_lower":"1980-01-01",
    "date:inception_upper":"1980-01-31",
    "iso:country":"GB",
    "wof:name":"SE18 5LD",
    "wof:placetype":"postalcode"
},
  "geometry": {"coordinates":[0.053672,51.490757],"type":"Point"}
}