{
  "type": "Feature",
  "properties": {
    "iso:country":"GB",
    "wof:name":"S43 4SQ",
    "wof:placetype":"postalcode"
},
  "geometry": {"coordinates":[-1.25422571967065,53.27502327404803],"type":"Point"}
}