{
  "type": "Feature",
  "properties": {
    "iso:country": "GB",
    "wof:name": "KY12 0US",
    "wof:placetype": "postalcode"
  },
  "geometry": {"coordinates":[-3.410695,56.096646],"type":"Point"}
}
