{
  "type": "Feature",
  "properties": {
    "date:inception_lower": "2000-12-01",
    "date:inception_upper": "2000-12-01",
    "iso:country": "GB",
    "wof:name": "KY12 0US",
    "wof:placetype": "postalcode"
  },
  "geometry": {"coordinates":[-3.410695,56.096646],"type":"Point"}
}
