{
  "type": "Feature",
  "properties": {
    "iso:country":"GB",
    "wof:name":"AB11 6UU",
    "wof:placetype":"postalcode"
},
  "geometry": {"coordinates":[-2.11021230866642,57.14132149429235],"type":"Point"}
}