{
  "type": "Feature",
  "properties": {
    "iso:country": "GB",
    "wof:name": "G52 4FF",
    "wof:placetype": "postalcode"
  },
  "geometry": {"coordinates":[-4.372487,55.852021],"type":"Point"}
}
