{
  "type": "Feature",
  "properties": {
    "date:inception_lower": "2006-10-01",
    "date:inception_upper": "2006-10-01",
    "iso:country": "GB",
    "wof:name": "G52 4FF",
    "wof:placetype": "postalcode"
  },
  "geometry": {"coordinates":[-4.372487,55.852021],"type":"Point"}
}
