{
  "type": "Feature",
  "properties": {
    "iso:country":"GB",
    "wof:name":"M46 0EH",
    "wof:placetype":"postalcode"
},
  "geometry": {"coordinates":[-2.49773858190968,53.52400508989569],"type":"Point"}
}