{
  "type": "Feature",
  "properties": {
    "iso:country":"GB",
    "wof:name":"M28 3SD",
    "wof:placetype":"postalcode"
},
  "geometry": {"coordinates":[-2.40477305200554,53.5188192624657],"type":"Point"}
}