{
  "type": "Feature",
  "properties": {
    "date:inception_lower": "2019-06-01",
    "date:inception_upper": "2019-06-01",
    "iso:country": "GB",
    "wof:name": "TS13 4BY",
    "wof:placetype": "postalcode"
  },
  "geometry": {"coordinates":[-0.89173,54.550167],"type":"Point"}
}
