{
  "type": "Feature",
  "properties": {
    "iso:country":"GB",
    "wof:name":"HR1 4NA",
    "wof:placetype":"postalcode"
},
  "geometry": {"coordinates":[-2.60533908108084,52.04430997655895],"type":"Point"}
}