{
  "type": "Feature",
  "properties": {
    "iso:country": "GB",
    "wof:name": "HR1 4NA",
    "wof:placetype": "postalcode"
  },
  "geometry": {"coordinates":[-2.605339,52.044319],"type":"Point"}
}
