{
  "type": "Feature",
  "properties": {
    "date:inception_lower": "1980-01-01",
    "date:inception_upper": "1980-01-01",
    "iso:country": "GB",
    "wof:name": "HR1 4NA",
    "wof:placetype": "postalcode"
  },
  "geometry": {"coordinates":[-2.605339,52.044319],"type":"Point"}
}
