{
  "type": "Feature",
  "properties": {
    "iso:country": "GB",
    "wof:name": "TS9 6LJ",
    "wof:placetype": "postalcode"
  },
  "geometry": {"coordinates":[-1.107658,54.454786],"type":"Point"}
}
