{
  "type": "Feature",
  "properties": {
    "iso:country":"GB",
    "wof:name":"TS9 6LJ",
    "wof:placetype":"postalcode"
},
  "geometry": {"coordinates":[-1.10765805513511,54.45478598329888],"type":"Point"}
}