{
  "type": "Feature",
  "properties": {
    "iso:country": "GB",
    "wof:name": "SA73 1UH",
    "wof:placetype": "postalcode"
  },
  "geometry": {"coordinates":[-4.950425,51.712357],"type":"Point"}
}
