{
  "type": "Feature",
  "properties": {
    "iso:country":"GB",
    "wof:name":"SA73 1UH",
    "wof:placetype":"postalcode"
},
  "geometry": {"coordinates":[-4.95031502911822,51.71229303498139],"type":"Point"}
}