{
  "type": "Feature",
  "properties": {
    "date:inception_lower":"1997-06-01",
    "date:inception_upper":"1997-06-30",
    "iso:country":"GB",
    "wof:name":"SA73 1UH",
    "wof:placetype":"postalcode"
},
  "geometry": {"coordinates":[-4.950425,51.712357],"type":"Point"}
}