{
  "type": "Feature",
  "properties": {
    "iso:country":"GB",
    "wof:name":"CV1 4EH",
    "wof:placetype":"postalcode"
},
  "geometry": {"coordinates":[-1.5099856223312,52.41987474415905],"type":"Point"}
}