{
  "type": "Feature",
  "properties": {
    "iso:country":"GB",
    "wof:name":"DE23 4BX",
    "wof:placetype":"postalcode"
},
  "geometry": {"coordinates":[-1.52750980474257,52.89486643330486],"type":"Point"}
}