{
  "type": "Feature",
  "properties": {
    "iso:country":"GB",
    "wof:name":"LE7 9AD",
    "wof:placetype":"postalcode"
},
  "geometry": {"coordinates":[-0.9412540579179,52.6201320789203],"type":"Point"}
}