{
  "type": "Feature",
  "properties": {
    "iso:country": "GB",
    "wof:name": "LE7 9AD",
    "wof:placetype": "postalcode"
  },
  "geometry": {"coordinates":[-0.941254,52.620132],"type":"Point"}
}
