{
  "type": "Feature",
  "properties": {
    "iso:country":"GB",
    "wof:name":"HP4 2PG",
    "wof:placetype":"postalcode"
},
  "geometry": {"coordinates":[-0.55120209227244,51.7654182065618],"type":"Point"}
}