{
  "type": "Feature",
  "properties": {
    "iso:country": "GB",
    "wof:name": "CV6 3GE",
    "wof:placetype": "postalcode"
  },
  "geometry": {"coordinates":[-1.516224,52.422211],"type":"Point"}
}
