{
  "type": "Feature",
  "properties": {
    "iso:country": "GB",
    "wof:name": "BN17 5QY",
    "wof:placetype": "postalcode"
  },
  "geometry": {"coordinates":[-0.580447,50.812312],"type":"Point"}
}
