{
  "type": "Feature",
  "properties": {
    "iso:country":"GB",
    "wof:name":"CB1 3TP",
    "wof:placetype":"postalcode"
},
  "geometry": {"coordinates":[0.15125107895345,52.18914800748199],"type":"Point"}
}