{
  "type": "Feature",
  "properties": {
    "iso:country": "GB",
    "wof:name": "CB1 3TP",
    "wof:placetype": "postalcode"
  },
  "geometry": {"coordinates":[0.151251,52.189148],"type":"Point"}
}
