{
  "type": "Feature",
  "properties": {
    "iso:country":"GB",
    "wof:name":"HA9 7JG",
    "wof:placetype":"postalcode"
},
  "geometry": {"coordinates":[-0.29837534473483,51.55515727763258],"type":"Point"}
}