{
  "type": "Feature",
  "properties": {
    "date:inception_lower": "2023-06-01",
    "date:inception_upper": "2023-06-01",
    "iso:country": "GB",
    "wof:name": "YO12 7BF",
    "wof:placetype": "postalcode"
  },
  "geometry": {"coordinates":[-0.398117,54.286925],"type":"Point"}
}
