{
  "type": "Feature",
  "properties": {
    "iso:country":"GB",
    "wof:name":"ST5 6EP",
    "wof:placetype":"postalcode"
},
  "geometry": {"coordinates":[-2.24764872954124,53.01830358306469],"type":"Point"}
}