{
  "type": "Feature",
  "properties": {
    "iso:country": "GB",
    "wof:name": "RH16 9QF",
    "wof:placetype": "postalcode"
  },
  "geometry": {"coordinates":[-0.103795,51.006411],"type":"Point"}
}
