{
  "type": "Feature",
  "properties": {
    "date:inception_lower": "1980-01-01",
    "date:inception_upper": "1980-01-01",
    "iso:country": "GB",
    "wof:name": "DY6 8LT",
    "wof:placetype": "postalcode"
  },
  "geometry": {"coordinates":[-2.156567,52.487442],"type":"Point"}
}
