{
  "type": "Feature",
  "properties": {
    "date:inception_lower": "2016-10-01",
    "date:inception_upper": "2016-10-01",
    "iso:country": "GB",
    "wof:name": "CF35 6PA",
    "wof:placetype": "postalcode"
  },
  "geometry": {"coordinates":[-3.567635,51.524035],"type":"Point"}
}
