{
  "type": "Feature",
  "properties": {
    "iso:country": "GB",
    "wof:name": "LL68 9HF",
    "wof:placetype": "postalcode"
  },
  "geometry": {"coordinates":[-4.333028,53.41273],"type":"Point"}
}
