{
  "type": "Feature",
  "properties": {
    "iso:country":"GB",
    "wof:name":"LL68 9HF",
    "wof:placetype":"postalcode"
},
  "geometry": {"coordinates":[-4.33302776687704,53.41273034328314],"type":"Point"}
}