{
  "type": "Feature",
  "properties": {
    "date:inception_lower": "1980-01-01",
    "date:inception_upper": "1980-01-01",
    "iso:country": "GB",
    "wof:name": "LL68 9HF",
    "wof:placetype": "postalcode"
  },
  "geometry": {"coordinates":[-4.333028,53.41273],"type":"Point"}
}
