{
  "type": "Feature",
  "properties": {
    "iso:country":"GB",
    "wof:name":"AB54 7UB",
    "wof:placetype":"postalcode"
},
  "geometry": {"coordinates":[-2.64840675259513,57.55573007645378],"type":"Point"}
}