{
  "type": "Feature",
  "properties": {
    "iso:country":"GB",
    "wof:name":"CO15 6DT",
    "wof:placetype":"postalcode"
},
  "geometry": {"coordinates":[1.15817617328943,51.79433206916546],"type":"Point"}
}