{
  "type": "Feature",
  "properties": {
    "iso:country":"GB",
    "wof:name":"BS15 8FE",
    "wof:placetype":"postalcode"
},
  "geometry": {"coordinates":[-2.51420508785413,51.46249372052424],"type":"Point"}
}