{
  "type": "Feature",
  "properties": {
    "date:inception_lower": "2007-09-01",
    "date:inception_upper": "2007-09-01",
    "iso:country": "GB",
    "wof:name": "BS15 8FE",
    "wof:placetype": "postalcode"
  },
  "geometry": {"coordinates":[-2.514205,51.462494],"type":"Point"}
}
