{
  "type": "Feature",
  "properties": {
    "iso:country":"GB",
    "wof:name":"DA18 4DE",
    "wof:placetype":"postalcode"
},
  "geometry": {"coordinates":[0.13096110742218,51.49326140658474],"type":"Point"}
}