{
  "type": "Feature",
  "properties": {
    "date:inception_lower": "1980-01-01",
    "date:inception_upper": "1980-01-01",
    "iso:country": "GB",
    "wof:name": "IV20 1YJ",
    "wof:placetype": "postalcode"
  },
  "geometry": {"coordinates":[-3.824864,57.835015],"type":"Point"}
}
