{
  "type": "Feature",
  "properties": {
    "iso:country":"GB",
    "wof:name":"IV20 1YJ",
    "wof:placetype":"postalcode"
},
  "geometry": {"coordinates":[-3.82486442713066,57.83501508049584],"type":"Point"}
}