{
  "type": "Feature",
  "properties": {
    "iso:country": "GB",
    "wof:name": "PE14 7YA",
    "wof:placetype": "postalcode"
  },
  "geometry": {"coordinates":[0.178197,52.676786],"type":"Point"}
}
