{
  "type": "Feature",
  "properties": {
    "date:inception_lower": "1999-12-01",
    "date:inception_upper": "1999-12-01",
    "iso:country": "GB",
    "wof:name": "PE14 7YA",
    "wof:placetype": "postalcode"
  },
  "geometry": {"coordinates":[0.178197,52.676786],"type":"Point"}
}
