{
  "type": "Feature",
  "properties": {
    "iso:country":"GB",
    "wof:name":"LA8 0AY",
    "wof:placetype":"postalcode"
},
  "geometry": {"coordinates":[-2.64311275999978,54.33375306635057],"type":"Point"}
}