{
  "type": "Feature",
  "properties": {
    "iso:country": "GB",
    "wof:name": "AB51 3TL",
    "wof:placetype": "postalcode"
  },
  "geometry": {"coordinates":[-2.371494,57.282086],"type":"Point"}
}
