{
  "type": "Feature",
  "properties": {
    "date:inception_lower": "2012-10-01",
    "date:inception_upper": "2012-10-01",
    "iso:country": "GB",
    "wof:name": "AB51 3TL",
    "wof:placetype": "postalcode"
  },
  "geometry": {"coordinates":[-2.371494,57.282086],"type":"Point"}
}
