{
  "type": "Feature",
  "properties": {
    "date:inception_lower": "1994-05-01",
    "date:inception_upper": "1994-05-01",
    "iso:country": "GB",
    "wof:name": "SN8 1XF",
    "wof:placetype": "postalcode"
  },
  "geometry": {"coordinates":[-1.730213,51.448252],"type":"Point"}
}
