{
  "type": "Feature",
  "properties": {
    "iso:country": "GB",
    "wof:name": "SN8 1XF",
    "wof:placetype": "postalcode"
  },
  "geometry": {"coordinates":[-1.730213,51.448252],"type":"Point"}
}
