{
  "type": "Feature",
  "properties": {
    "iso:country":"GB",
    "wof:name":"SN8 1XF",
    "wof:placetype":"postalcode"
},
  "geometry": {"coordinates":[-1.73021297933507,51.44825170162055],"type":"Point"}
}