{
  "type": "Feature",
  "properties": {
    "iso:country":"GB",
    "wof:name":"WA9 4ES",
    "wof:placetype":"postalcode"
},
  "geometry": {"coordinates":[-2.72214960024744,53.42156667318203],"type":"Point"}
}