{
  "type": "Feature",
  "properties": {
    "iso:country": "GB",
    "wof:name": "CM1 7FT",
    "wof:placetype": "postalcode"
  },
  "geometry": {"coordinates":[0.472135,51.774596],"type":"Point"}
}
