{
  "type": "Feature",
  "properties": {
    "iso:country":"GB",
    "wof:name":"S17 4LP",
    "wof:placetype":"postalcode"
},
  "geometry": {"coordinates":[-1.52011094189223,53.31480719777137],"type":"Point"}
}