{
  "type": "Feature",
  "properties": {
    "iso:country":"GB",
    "wof:name":"BA14 6RZ",
    "wof:placetype":"postalcode"
},
  "geometry": {"coordinates":[-2.19208873376721,51.35324529234516],"type":"Point"}
}