{
  "type": "Feature",
  "properties": {
    "iso:country": "GB",
    "wof:name": "EX10 9UH",
    "wof:placetype": "postalcode"
  },
  "geometry": {"coordinates":[-3.244863,50.696528],"type":"Point"}
}
