{
  "type": "Feature",
  "properties": {
    "iso:country":"GB",
    "wof:name":"EX10 9UH",
    "wof:placetype":"postalcode"
},
  "geometry": {"coordinates":[-3.24486271929376,50.6965280944052],"type":"Point"}
}