{
  "type": "Feature",
  "properties": {
    "date:inception_lower": "1980-01-01",
    "date:inception_upper": "1980-01-01",
    "iso:country": "GB",
    "wof:name": "TN17 3RA",
    "wof:placetype": "postalcode"
  },
  "geometry": {"coordinates":[0.520224,51.091437],"type":"Point"}
}
