{
  "type": "Feature",
  "properties": {
    "iso:country": "GB",
    "wof:name": "TN17 3RA",
    "wof:placetype": "postalcode"
  },
  "geometry": {"coordinates":[0.520224,51.091437],"type":"Point"}
}
