{
  "type": "Feature",
  "properties": {
    "iso:country":"GB",
    "wof:name":"TN17 3RA",
    "wof:placetype":"postalcode"
},
  "geometry": {"coordinates":[0.52022444435721,51.09143678131458],"type":"Point"}
}