{
  "type": "Feature",
  "properties": {
    "iso:country":"GB",
    "wof:name":"DN22 6QX",
    "wof:placetype":"postalcode"
},
  "geometry": {"coordinates":[-0.93695221656585,53.32377489303652],"type":"Point"}
}