{
  "type": "Feature",
  "properties": {
    "iso:country":"GB",
    "wof:name":"IV17 0XW",
    "wof:placetype":"postalcode"
},
  "geometry": {"coordinates":[-4.28805274757573,57.73312363828954],"type":"Point"}
}