{
  "type": "Feature",
  "properties": {
    "iso:country":"GB",
    "wof:name":"YO22 5NW",
    "wof:placetype":"postalcode"
},
  "geometry": {"coordinates":[-0.70809190950973,54.38925889282321],"type":"Point"}
}