{
  "type": "Feature",
  "properties": {
    "iso:country": "GB",
    "wof:name": "YO22 5NW",
    "wof:placetype": "postalcode"
  },
  "geometry": {"coordinates":[-0.708092,54.389259],"type":"Point"}
}
