{
  "type": "Feature",
  "properties": {
    "date:inception_lower":"1980-01-01",
    "date:inception_upper":"1980-01-31",
    "iso:country":"GB",
    "wof:name":"YO22 5NW",
    "wof:placetype":"postalcode"
},
  "geometry": {"coordinates":[-0.708092,54.389259],"type":"Point"}
}