{
  "type": "Feature",
  "properties": {
    "iso:country":"GB",
    "wof:name":"TS8 0SU",
    "wof:placetype":"postalcode"
},
  "geometry": {"coordinates":[-1.21535493561536,54.51827260312845],"type":"Point"}
}