{
  "type": "Feature",
  "properties": {
    "iso:country": "GB",
    "wof:name": "TS8 0SU",
    "wof:placetype": "postalcode"
  },
  "geometry": {"coordinates":[-1.215355,54.518273],"type":"Point"}
}
