{
  "type": "Feature",
  "properties": {
    "date:inception_lower": "2010-12-01",
    "date:inception_upper": "2010-12-01",
    "iso:country": "GB",
    "wof:name": "LA12 9GP",
    "wof:placetype": "postalcode"
  },
  "geometry": {"coordinates":[-3.064575,54.18009],"type":"Point"}
}
