{
  "type": "Feature",
  "properties": {
    "iso:country":"GB",
    "wof:name":"ME16 9ED",
    "wof:placetype":"postalcode"
},
  "geometry": {"coordinates":[0.4764597161189,51.2648456148552],"type":"Point"}
}