{
  "type": "Feature",
  "properties": {
    "date:inception_lower": "2018-03-01",
    "date:inception_upper": "2018-03-01",
    "iso:country": "GB",
    "wof:name": "TS15 9ZP",
    "wof:placetype": "postalcode"
  },
  "geometry": {"coordinates":[-1.360029,54.491186],"type":"Point"}
}
