{
  "type": "Feature",
  "properties": {
    "iso:country": "GB",
    "wof:name": "CH46 6JE",
    "wof:placetype": "postalcode"
  },
  "geometry": {"coordinates":[-3.132536,53.398882],"type":"Point"}
}
