{
  "type": "Feature",
  "properties": {
    "iso:country":"GB",
    "wof:name":"CV11 6QS",
    "wof:placetype":"postalcode"
},
  "geometry": {"coordinates":[-1.40280578207341,52.49501611368768],"type":"Point"}
}