{
  "type": "Feature",
  "properties": {
    "date:inception_lower": "1980-01-01",
    "date:inception_upper": "1980-01-01",
    "iso:country": "GB",
    "wof:name": "CV11 6QS",
    "wof:placetype": "postalcode"
  },
  "geometry": {"coordinates":[-1.402806,52.495016],"type":"Point"}
}
