{
  "type": "Feature",
  "properties": {
    "date:inception_lower": "1980-01-01",
    "date:inception_upper": "1980-01-01",
    "iso:country": "GB",
    "wof:name": "BD23 6RH",
    "wof:placetype": "postalcode"
  },
  "geometry": {"coordinates":[-1.990469,53.980155],"type":"Point"}
}
