{
  "type": "Feature",
  "properties": {
    "iso:country":"GB",
    "wof:name":"NG11 0BA",
    "wof:placetype":"postalcode"
},
  "geometry": {"coordinates":[-1.23490853739722,52.87334110084382],"type":"Point"}
}