{
  "type": "Feature",
  "properties": {
    "iso:country": "GB",
    "wof:name": "NG11 0BA",
    "wof:placetype": "postalcode"
  },
  "geometry": {"coordinates":[-1.234908,52.873341],"type":"Point"}
}
