{
  "type": "Feature",
  "properties": {
    "date:inception_lower": "1991-01-01",
    "date:inception_upper": "1991-01-01",
    "iso:country": "GB",
    "wof:name": "NG11 0BA",
    "wof:placetype": "postalcode"
  },
  "geometry": {"coordinates":[-1.234908,52.873341],"type":"Point"}
}
