{
  "type": "Feature",
  "properties": {
    "iso:country": "GB",
    "wof:name": "B90 4SH",
    "wof:placetype": "postalcode"
  },
  "geometry": {"coordinates":[-1.797521,52.394923],"type":"Point"}
}
