{
  "type": "Feature",
  "properties": {
    "date:inception_lower": "2001-12-01",
    "date:inception_upper": "2001-12-01",
    "iso:country": "GB",
    "wof:name": "B90 4SH",
    "wof:placetype": "postalcode"
  },
  "geometry": {"coordinates":[-1.797514,52.394938],"type":"Point"}
}
