{
  "type": "Feature",
  "properties": {
    "iso:country":"GB",
    "wof:name":"TN37 6RB",
    "wof:placetype":"postalcode"
},
  "geometry": {"coordinates":[0.55775077921849,50.86401451682439],"type":"Point"}
}