{
  "type": "Feature",
  "properties": {
    "iso:country":"GB",
    "wof:name":"W1D 3RA",
    "wof:placetype":"postalcode"
},
  "geometry": {"coordinates":[-0.13261056889393,51.5140673637593],"type":"Point"}
}