{
  "type": "Feature",
  "properties": {
    "iso:country":"GB",
    "wof:name":"DN4 7PP",
    "wof:placetype":"postalcode"
},
  "geometry": {"coordinates":[-1.07743749030841,53.49886936028233],"type":"Point"}
}