{
  "type": "Feature",
  "properties": {
    "iso:country":"GB",
    "wof:name":"PE14 8DH",
    "wof:placetype":"postalcode"
},
  "geometry": {"coordinates":[0.21198262174146,52.65361811006081],"type":"Point"}
}