{
  "type": "Feature",
  "properties": {
    "date:inception_lower": "1980-01-01",
    "date:inception_upper": "1980-01-01",
    "iso:country": "GB",
    "wof:name": "PE14 8DH",
    "wof:placetype": "postalcode"
  },
  "geometry": {"coordinates":[0.213893,52.653089],"type":"Point"}
}
