{
  "type": "Feature",
  "properties": {
    "date:inception_lower": "2023-07-01",
    "date:inception_upper": "2023-07-01",
    "iso:country": "GB",
    "wof:name": "WF7 5PY",
    "wof:placetype": "postalcode"
  },
  "geometry": {"coordinates":[-1.348344,53.677464],"type":"Point"}
}
