{
  "type": "Feature",
  "properties": {
    "iso:country":"GB",
    "wof:name":"NG6 8FN",
    "wof:placetype":"postalcode"
},
  "geometry": {"coordinates":[-1.19708185774645,53.00360101314356],"type":"Point"}
}