{
  "type": "Feature",
  "properties": {
    "date:inception_lower": "1980-01-01",
    "date:inception_upper": "1980-01-01",
    "iso:country": "GB",
    "wof:name": "TQ14 9NH",
    "wof:placetype": "postalcode"
  },
  "geometry": {"coordinates":[-3.508395,50.555528],"type":"Point"}
}
