{
  "type": "Feature",
  "properties": {
    "iso:country":"GB",
    "wof:name":"TQ14 9NH",
    "wof:placetype":"postalcode"
},
  "geometry": {"coordinates":[-3.50839504186904,50.55552777376619],"type":"Point"}
}