{
  "type": "Feature",
  "properties": {
    "iso:country":"GB",
    "wof:name":"BN1 3TB",
    "wof:placetype":"postalcode"
},
  "geometry": {"coordinates":[-0.14570982513948,50.83117800369951],"type":"Point"}
}