{
  "type": "Feature",
  "properties": {
    "iso:country":"GB",
    "wof:name":"IP17 2ED",
    "wof:placetype":"postalcode"
},
  "geometry": {"coordinates":[1.39418309210759,52.24638793788197],"type":"Point"}
}