{
  "type": "Feature",
  "properties": {
    "date:inception_lower": "2020-06-01",
    "date:inception_upper": "2020-06-01",
    "iso:country": "GB",
    "wof:name": "MK17 8XN",
    "wof:placetype": "postalcode"
  },
  "geometry": {"coordinates":[-0.675956,52.0323],"type":"Point"}
}
