{
  "type": "Feature",
  "properties": {
    "iso:country":"GB",
    "wof:name":"TS1 3DG",
    "wof:placetype":"postalcode"
},
  "geometry": {"coordinates":[-1.23749213862753,54.57217493659537],"type":"Point"}
}