{
  "type": "Feature",
  "properties": {
    "iso:country":"GB",
    "wof:name":"CV35 7DY",
    "wof:placetype":"postalcode"
},
  "geometry": {"coordinates":[-1.61111110965068,52.28875064979365],"type":"Point"}
}