{
  "type": "Feature",
  "properties": {
    "iso:country": "GB",
    "wof:name": "CV35 7DY",
    "wof:placetype": "postalcode"
  },
  "geometry": {"coordinates":[-1.611111,52.288751],"type":"Point"}
}
