{
  "type": "Feature",
  "properties": {
    "iso:country": "GB",
    "wof:name": "S4 8DQ",
    "wof:placetype": "postalcode"
  },
  "geometry": {"coordinates":[-1.438667,53.402838],"type":"Point"}
}
