{
  "type": "Feature",
  "properties": {
    "iso:country":"GB",
    "wof:name":"SA43 1RS",
    "wof:placetype":"postalcode"
},
  "geometry": {"coordinates":[-4.5647475161521,52.11899073804928],"type":"Point"}
}