{
  "type": "Feature",
  "properties": {
    "date:inception_lower": "1980-01-01",
    "date:inception_upper": "1980-01-01",
    "iso:country": "GB",
    "wof:name": "SA43 1RS",
    "wof:placetype": "postalcode"
  },
  "geometry": {"coordinates":[-4.564747,52.118991],"type":"Point"}
}
