{
  "type": "Feature",
  "properties": {
    "iso:country":"GB",
    "wof:name":"EX4 2AH",
    "wof:placetype":"postalcode"
},
  "geometry": {"coordinates":[-3.54950791065627,50.73232028806989],"type":"Point"}
}