{
  "type": "Feature",
  "properties": {
    "iso:country": "GB",
    "wof:name": "L8 9UR",
    "wof:placetype": "postalcode"
  },
  "geometry": {"coordinates":[-2.966177,53.378924],"type":"Point"}
}
