{
  "type": "Feature",
  "properties": {
    "date:inception_lower": "2023-03-01",
    "date:inception_upper": "2023-03-01",
    "iso:country": "GB",
    "wof:name": "CB6 2YF",
    "wof:placetype": "postalcode"
  },
  "geometry": {"coordinates":[0.259733,52.410992],"type":"Point"}
}
