{
  "type": "Feature",
  "properties": {
    "date:inception_lower": "1997-12-01",
    "date:inception_upper": "1997-12-01",
    "iso:country": "GB",
    "wof:name": "BS35 3UF",
    "wof:placetype": "postalcode"
  },
  "geometry": {"coordinates":[-2.490774,51.622265],"type":"Point"}
}
