{
  "type": "Feature",
  "properties": {
    "iso:country":"GB",
    "wof:name":"GL17 0BZ",
    "wof:placetype":"postalcode"
},
  "geometry": {"coordinates":[-2.48825032489411,51.86030745464383],"type":"Point"}
}