{
  "type": "Feature",
  "properties": {
    "iso:country":"GB",
    "wof:name":"W1S 4EY",
    "wof:placetype":"postalcode"
},
  "geometry": {"coordinates":[-0.14308507549483,51.50953957531095],"type":"Point"}
}