{
  "type": "Feature",
  "properties": {
    "date:inception_lower":"2000-12-01",
    "date:inception_upper":"2000-12-31",
    "iso:country":"GB",
    "wof:name":"W1S 4EY",
    "wof:placetype":"postalcode"
},
  "geometry": {"coordinates":[-0.143085,51.50954],"type":"Point"}
}