{
  "type": "Feature",
  "properties": {
    "iso:country":"GB",
    "wof:name":"N22 6RU",
    "wof:placetype":"postalcode"
},
  "geometry": {"coordinates":[-0.09430772944889,51.59608338320623],"type":"Point"}
}