{
  "type": "Feature",
  "properties": {
    "iso:country": "GB",
    "wof:name": "LL12 7DN",
    "wof:placetype": "postalcode"
  },
  "geometry": {"coordinates":[-2.982784,53.052345],"type":"Point"}
}
