{
  "type": "Feature",
  "properties": {
    "iso:country": "GB",
    "wof:name": "TF8 7EJ",
    "wof:placetype": "postalcode"
  },
  "geometry": {"coordinates":[-2.491301,52.642573],"type":"Point"}
}
