{
  "type": "Feature",
  "properties": {
    "iso:country":"GB",
    "wof:name":"NP26 3PH",
    "wof:placetype":"postalcode"
},
  "geometry": {"coordinates":[-2.81500919220491,51.58200434912669],"type":"Point"}
}