{
  "type": "Feature",
  "properties": {
    "date:inception_lower": "2021-05-01",
    "date:inception_upper": "2021-05-01",
    "iso:country": "GB",
    "wof:name": "G77 5WT",
    "wof:placetype": "postalcode"
  },
  "geometry": {"coordinates":[-4.349704,55.759062],"type":"Point"}
}
