{
  "type": "Feature",
  "properties": {
    "date:inception_lower": "2020-02-01",
    "date:inception_upper": "2020-02-01",
    "iso:country": "GB",
    "wof:name": "CH5 3SS",
    "wof:placetype": "postalcode"
  },
  "geometry": {"coordinates":[-3.051921,53.185253],"type":"Point"}
}
