{
  "type": "Feature",
  "properties": {
    "iso:country":"GB",
    "wof:name":"GU21 3AQ",
    "wof:placetype":"postalcode"
},
  "geometry": {"coordinates":[-0.58125896013929,51.3220467103157],"type":"Point"}
}