{
  "type": "Feature",
  "properties": {
    "date:inception_lower": "1980-01-01",
    "date:inception_upper": "1980-01-01",
    "iso:country": "GB",
    "wof:name": "GU21 3AQ",
    "wof:placetype": "postalcode"
  },
  "geometry": {"coordinates":[-0.581259,51.322047],"type":"Point"}
}
