{
  "type": "Feature",
  "properties": {
    "iso:country":"GB",
    "wof:name":"SG2 8AA",
    "wof:placetype":"postalcode"
},
  "geometry": {"coordinates":[-0.18446571724417,51.88213191722195],"type":"Point"}
}