{
  "type": "Feature",
  "properties": {
    "iso:country": "GB",
    "wof:name": "SG2 8AA",
    "wof:placetype": "postalcode"
  },
  "geometry": {"coordinates":[-0.184466,51.882132],"type":"Point"}
}
