{
  "type": "Feature",
  "properties": {
    "iso:country":"GB",
    "wof:name":"CM17 9AY",
    "wof:placetype":"postalcode"
},
  "geometry": {"coordinates":[0.13417469320429,51.76079853450022],"type":"Point"}
}