{
  "type": "Feature",
  "properties": {
    "iso:country": "GB",
    "wof:name": "CM17 9AY",
    "wof:placetype": "postalcode"
  },
  "geometry": {"coordinates":[0.134175,51.760799],"type":"Point"}
}
