{
  "type": "Feature",
  "properties": {
    "date:inception_lower": "1980-01-01",
    "date:inception_upper": "1980-01-01",
    "iso:country": "GB",
    "wof:name": "GL56 0PG",
    "wof:placetype": "postalcode"
  },
  "geometry": {"coordinates":[-1.659578,51.983915],"type":"Point"}
}
