{
  "type": "Feature",
  "properties": {
    "iso:country":"GB",
    "wof:name":"GL56 0PG",
    "wof:placetype":"postalcode"
},
  "geometry": {"coordinates":[-1.65957816151619,51.98391466692458],"type":"Point"}
}