{
  "type": "Feature",
  "properties": {
    "iso:country": "GB",
    "wof:name": "SO16 0AF",
    "wof:placetype": "postalcode"
  },
  "geometry": {"coordinates":[-1.477044,50.940364],"type":"Point"}
}
