{
  "type": "Feature",
  "properties": {
    "date:inception_lower": "1980-01-01",
    "date:inception_upper": "1980-01-01",
    "iso:country": "GB",
    "wof:name": "NE2 4NN",
    "wof:placetype": "postalcode"
  },
  "geometry": {"coordinates":[-1.630949,54.985229],"type":"Point"}
}
