{
  "type": "Feature",
  "properties": {
    "iso:country":"GB",
    "wof:name":"NE2 4NN",
    "wof:placetype":"postalcode"
},
  "geometry": {"coordinates":[-1.63094940004433,54.98522878288316],"type":"Point"}
}