{
  "type": "Feature",
  "properties": {
    "iso:country": "GB",
    "wof:name": "SO51 6RN",
    "wof:placetype": "postalcode"
  },
  "geometry": {"coordinates":[-1.589676,50.97163],"type":"Point"}
}
