{
  "type": "Feature",
  "properties": {
    "iso:country":"GB",
    "wof:name":"SO51 6RN",
    "wof:placetype":"postalcode"
},
  "geometry": {"coordinates":[-1.58967649492377,50.97163013841141],"type":"Point"}
}