{
  "type": "Feature",
  "properties": {
    "iso:country": "GB",
    "wof:name": "OX11 6HR",
    "wof:placetype": "postalcode"
  },
  "geometry": {"coordinates":[-1.261256,51.598709],"type":"Point"}
}
