{
  "type": "Feature",
  "properties": {
    "iso:country": "GB",
    "wof:name": "PL9 9PH",
    "wof:placetype": "postalcode"
  },
  "geometry": {"coordinates":[-4.108574,50.353295],"type":"Point"}
}
