{
  "type": "Feature",
  "properties": {
    "date:inception_lower": "2019-02-01",
    "date:inception_upper": "2019-02-01",
    "iso:country": "GB",
    "wof:name": "TQ1 9JH",
    "wof:placetype": "postalcode"
  },
  "geometry": {"coordinates":[-3.549713,50.484759],"type":"Point"}
}
