{
  "type": "Feature",
  "properties": {
    "iso:country":"GB",
    "wof:name":"S32 1AD",
    "wof:placetype":"postalcode"
},
  "geometry": {"coordinates":[-1.65702006615365,53.32931941992049],"type":"Point"}
}