{
  "type": "Feature",
  "properties": {
    "iso:country":"GB",
    "wof:name":"SK12 1SW",
    "wof:placetype":"postalcode"
},
  "geometry": {"coordinates":[-2.09597068046809,53.34486473054096],"type":"Point"}
}