{
  "type": "Feature",
  "properties": {
    "iso:country":"GB",
    "wof:name":"NE38 0AD",
    "wof:placetype":"postalcode"
},
  "geometry": {"coordinates":[-1.55723740020728,54.90290186507835],"type":"Point"}
}