{
  "type": "Feature",
  "properties": {
    "iso:country":"GB",
    "wof:name":"NG34 7EQ",
    "wof:placetype":"postalcode"
},
  "geometry": {"coordinates":[-0.3967070088622,53.00448521889012],"type":"Point"}
}