{
  "type": "Feature",
  "properties": {
    "iso:country":"GB",
    "wof:name":"CH2 1NA",
    "wof:placetype":"postalcode"
},
  "geometry": {"coordinates":[-2.87477673750088,53.21743099261951],"type":"Point"}
}