{
  "type": "Feature",
  "properties": {
    "date:inception_lower": "1980-01-01",
    "date:inception_upper": "1980-01-01",
    "iso:country": "GB",
    "wof:name": "LA11 6BY",
    "wof:placetype": "postalcode"
  },
  "geometry": {"coordinates":[-2.920401,54.194186],"type":"Point"}
}
