{
  "type": "Feature",
  "properties": {
    "iso:country":"GB",
    "wof:name":"LA11 6BY",
    "wof:placetype":"postalcode"
},
  "geometry": {"coordinates":[-2.92015481259227,54.19412374776556],"type":"Point"}
}