{
  "type": "Feature",
  "properties": {
    "date:inception_lower": "2006-03-01",
    "date:inception_upper": "2006-03-01",
    "iso:country": "GB",
    "wof:name": "SO50 7FG",
    "wof:placetype": "postalcode"
  },
  "geometry": {"coordinates":[-1.296601,50.953815],"type":"Point"}
}
