{
  "type": "Feature",
  "properties": {
    "date:inception_lower": "1980-01-01",
    "date:inception_upper": "1980-01-01",
    "iso:country": "GB",
    "wof:name": "PO40 9BU",
    "wof:placetype": "postalcode"
  },
  "geometry": {"coordinates":[-1.51295,50.685282],"type":"Point"}
}
