{
  "type": "Feature",
  "properties": {
    "iso:country": "GB",
    "wof:name": "LU5 5SL",
    "wof:placetype": "postalcode"
  },
  "geometry": {"coordinates":[-0.507264,51.906298],"type":"Point"}
}
