{
  "type": "Feature",
  "properties": {
    "iso:country":"GB",
    "wof:name":"B74 4AU",
    "wof:placetype":"postalcode"
},
  "geometry": {"coordinates":[-1.84227355622292,52.59189835940442],"type":"Point"}
}