{
  "type": "Feature",
  "properties": {
    "iso:country":"GB",
    "wof:name":"DE56 2BN",
    "wof:placetype":"postalcode"
},
  "geometry": {"coordinates":[-1.45055546914352,53.04531350948498],"type":"Point"}
}