{
  "type": "Feature",
  "properties": {
    "iso:country": "GB",
    "wof:name": "LS23 7FS",
    "wof:placetype": "postalcode"
  },
  "geometry": {"coordinates":[-1.319954,53.908823],"type":"Point"}
}
