{
  "type": "Feature",
  "properties": {
    "date:inception_lower": "2008-08-01",
    "date:inception_upper": "2008-08-01",
    "iso:country": "GB",
    "wof:name": "LS23 7FS",
    "wof:placetype": "postalcode"
  },
  "geometry": {"coordinates":[-1.319786,53.908903],"type":"Point"}
}
