{
  "type": "Feature",
  "properties": {
    "iso:country":"GB",
    "wof:name":"NE66 4AT",
    "wof:placetype":"postalcode"
},
  "geometry": {"coordinates":[-1.88966068705917,55.42436454386173],"type":"Point"}
}