{
  "type": "Feature",
  "properties": {
    "iso:country":"GB",
    "wof:name":"NW8 0DU",
    "wof:placetype":"postalcode"
},
  "geometry": {"coordinates":[-0.17960869929298,51.54082134313295],"type":"Point"}
}