{
  "type": "Feature",
  "properties": {
    "iso:country":"GB",
    "wof:name":"WD19 6FS",
    "wof:placetype":"postalcode"
},
  "geometry": {"coordinates":[-0.38732269469904,51.61988893938278],"type":"Point"}
}