{
  "type": "Feature",
  "properties": {
    "iso:country": "GB",
    "wof:name": "SN14 7EB",
    "wof:placetype": "postalcode"
  },
  "geometry": {"coordinates":[-2.204303,51.45831],"type":"Point"}
}
