{
  "type": "Feature",
  "properties": {
    "date:inception_lower":"1996-12-01",
    "date:inception_upper":"1996-12-31",
    "iso:country":"GB",
    "wof:name":"TW6 2ES",
    "wof:placetype":"postalcode"
},
  "geometry": {"coordinates":[-0.423788,51.475763],"type":"Point"}
}