{
  "type": "Feature",
  "properties": {
    "iso:country": "GB",
    "wof:name": "TW6 2ES",
    "wof:placetype": "postalcode"
  },
  "geometry": {"coordinates":[-0.423788,51.475763],"type":"Point"}
}
