{
  "type": "Feature",
  "properties": {
    "iso:country":"GB",
    "wof:name":"WD23 3DQ",
    "wof:placetype":"postalcode"
},
  "geometry": {"coordinates":[-0.35431155126643,51.65072337056943],"type":"Point"}
}