{
  "type": "Feature",
  "properties": {
    "date:inception_lower": "2022-03-01",
    "date:inception_upper": "2022-03-01",
    "iso:country": "GB",
    "wof:name": "CM23 4RJ",
    "wof:placetype": "postalcode"
  },
  "geometry": {"coordinates":[0.156495,51.852113],"type":"Point"}
}
