{
  "type": "Feature",
  "properties": {
    "iso:country": "GB",
    "wof:name": "SW19 6LP",
    "wof:placetype": "postalcode"
  },
  "geometry": {"coordinates":[-0.209179,51.444311],"type":"Point"}
}
