{
  "type": "Feature",
  "properties": {
    "iso:country":"GB",
    "wof:name":"SW19 6LP",
    "wof:placetype":"postalcode"
},
  "geometry": {"coordinates":[-0.20917886327825,51.44431077493712],"type":"Point"}
}