{
  "type": "Feature",
  "properties": {
    "iso:country":"GB",
    "wof:name":"TN22 1DZ",
    "wof:placetype":"postalcode"
},
  "geometry": {"coordinates":[0.10271936916295,50.97189708952502],"type":"Point"}
}