{
  "type": "Feature",
  "properties": {
    "date:inception_lower": "1980-01-01",
    "date:inception_upper": "1980-01-01",
    "iso:country": "GB",
    "wof:name": "TN22 1DZ",
    "wof:placetype": "postalcode"
  },
  "geometry": {"coordinates":[0.102719,50.971897],"type":"Point"}
}
