{
  "type": "Feature",
  "properties": {
    "iso:country":"GB",
    "wof:name":"B35 7JG",
    "wof:placetype":"postalcode"
},
  "geometry": {"coordinates":[-1.78812332024208,52.51622724384291],"type":"Point"}
}