{
  "type": "Feature",
  "properties": {
    "date:inception_lower": "2022-02-01",
    "date:inception_upper": "2022-02-01",
    "iso:country": "GB",
    "wof:name": "DN21 4AZ",
    "wof:placetype": "postalcode"
  },
  "geometry": {"coordinates":[-0.597536,53.481127],"type":"Point"}
}
