{
  "type": "Feature",
  "properties": {
    "iso:country":"GB",
    "wof:name":"FK8 3QT",
    "wof:placetype":"postalcode"
},
  "geometry": {"coordinates":[-4.1730605670213,56.14710324104695],"type":"Point"}
}