{
  "type": "Feature",
  "properties": {
    "date:inception_lower": "1980-01-01",
    "date:inception_upper": "1980-01-01",
    "iso:country": "GB",
    "wof:name": "FK8 3QT",
    "wof:placetype": "postalcode"
  },
  "geometry": {"coordinates":[-4.163877,56.150697],"type":"Point"}
}
