{
  "type": "Feature",
  "properties": {
    "date:inception_lower":"2011-10-01",
    "date:inception_upper":"2011-10-31",
    "iso:country":"GB",
    "wof:name":"PL24 2FH",
    "wof:placetype":"postalcode"
},
  "geometry": {"coordinates":[-4.712012,50.350108],"type":"Point"}
}