{
  "type": "Feature",
  "properties": {
    "iso:country": "GB",
    "wof:name": "WA8 7DD",
    "wof:placetype": "postalcode"
  },
  "geometry": {"coordinates":[-2.734874,53.371484],"type":"Point"}
}
