{
  "type": "Feature",
  "properties": {
    "iso:country":"GB",
    "wof:name":"KA2 9AJ",
    "wof:placetype":"postalcode"
},
  "geometry": {"coordinates":[-4.5525087926649,55.59118746291044],"type":"Point"}
}