{
  "type": "Feature",
  "properties": {
    "iso:country":"GB",
    "wof:name":"M46 9RY",
    "wof:placetype":"postalcode"
},
  "geometry": {"coordinates":[-2.47850469404011,53.5318496751921],"type":"Point"}
}