{
  "type": "Feature",
  "properties": {
    "date:inception_lower": "1980-01-01",
    "date:inception_upper": "1980-01-01",
    "iso:country": "GB",
    "wof:name": "BA22 8ST",
    "wof:placetype": "postalcode"
  },
  "geometry": {"coordinates":[-2.686462,50.94928],"type":"Point"}
}
