{
  "type": "Feature",
  "properties": {
    "iso:country": "GB",
    "wof:name": "BA22 8ST",
    "wof:placetype": "postalcode"
  },
  "geometry": {"coordinates":[-2.686462,50.94928],"type":"Point"}
}
