{
  "type": "Feature",
  "properties": {
    "iso:country":"GB",
    "wof:name":"BA22 8ST",
    "wof:placetype":"postalcode"
},
  "geometry": {"coordinates":[-2.68646163580025,50.94927997909586],"type":"Point"}
}