{
  "type": "Feature",
  "properties": {
    "date:inception_lower":"2001-12-01",
    "date:inception_upper":"2001-12-31",
    "iso:country":"GB",
    "wof:name":"S73 0QY",
    "wof:placetype":"postalcode"
},
  "geometry": {"coordinates":[-1.383169,53.515992],"type":"Point"}
}