{
  "type": "Feature",
  "properties": {
    "iso:country":"GB",
    "wof:name":"S73 0QY",
    "wof:placetype":"postalcode"
},
  "geometry": {"coordinates":[-1.38316870867406,53.51599200160684],"type":"Point"}
}