{
  "type": "Feature",
  "properties": {
    "date:inception_lower":"1980-01-01",
    "date:inception_upper":"1980-01-31",
    "iso:country":"GB",
    "wof:name":"BH11 8AT",
    "wof:placetype":"postalcode"
},
  "geometry": {"coordinates":[-1.910799,50.759537],"type":"Point"}
}