{
  "type": "Feature",
  "properties": {
    "iso:country":"GB",
    "wof:name":"BH11 8AT",
    "wof:placetype":"postalcode"
},
  "geometry": {"coordinates":[-1.91079916389499,50.75953671830334],"type":"Point"}
}