{
  "type": "Feature",
  "properties": {
    "iso:country":"GB",
    "wof:name":"HP22 5DL",
    "wof:placetype":"postalcode"
},
  "geometry": {"coordinates":[-0.78435455079452,51.8328168706168],"type":"Point"}
}