{
  "type": "Feature",
  "properties": {
    "date:inception_lower": "1991-09-01",
    "date:inception_upper": "1991-09-01",
    "iso:country": "GB",
    "wof:name": "CR0 9DA",
    "wof:placetype": "postalcode"
  },
  "geometry": {"coordinates":[-0.024518,51.352639],"type":"Point"}
}
