{
  "type": "Feature",
  "properties": {
    "iso:country":"GB",
    "wof:name":"CR0 9DA",
    "wof:placetype":"postalcode"
},
  "geometry": {"coordinates":[-0.02451819872818,51.35263918074492],"type":"Point"}
}