{
  "type": "Feature",
  "properties": {
    "iso:country": "GB",
    "wof:name": "GU10 1LS",
    "wof:placetype": "postalcode"
  },
  "geometry": {"coordinates":[-0.73997,51.210736],"type":"Point"}
}
