{
  "type": "Feature",
  "properties": {
    "iso:country":"GB",
    "wof:name":"NE3 4DU",
    "wof:placetype":"postalcode"
},
  "geometry": {"coordinates":[-1.62748171169401,55.00533838095439],"type":"Point"}
}