{
  "type": "Feature",
  "properties": {
    "iso:country": "GB",
    "wof:name": "NE3 4DU",
    "wof:placetype": "postalcode"
  },
  "geometry": {"coordinates":[-1.627482,55.005338],"type":"Point"}
}
