{
  "type": "Feature",
  "properties": {
    "date:inception_lower":"1980-01-01",
    "date:inception_upper":"1980-01-31",
    "iso:country":"GB",
    "wof:name":"NE3 4DU",
    "wof:placetype":"postalcode"
},
  "geometry": {"coordinates":[-1.627482,55.005338],"type":"Point"}
}