{
  "type": "Feature",
  "properties": {
    "iso:country":"GB",
    "wof:name":"KA21 5HY",
    "wof:placetype":"postalcode"
},
  "geometry": {"coordinates":[-4.78042743086507,55.63363581010067],"type":"Point"}
}