{
  "type": "Feature",
  "properties": {
    "iso:country": "GB",
    "wof:name": "KA21 5HY",
    "wof:placetype": "postalcode"
  },
  "geometry": {"coordinates":[-4.780272,55.633684],"type":"Point"}
}
