{
  "type": "Feature",
  "properties": {
    "date:inception_lower": "1980-01-01",
    "date:inception_upper": "1980-01-01",
    "iso:country": "GB",
    "wof:name": "PO22 7ES",
    "wof:placetype": "postalcode"
  },
  "geometry": {"coordinates":[-0.651492,50.790546],"type":"Point"}
}
