{
  "type": "Feature",
  "properties": {
    "iso:country":"GB",
    "wof:name":"WA3 6PL",
    "wof:placetype":"postalcode"
},
  "geometry": {"coordinates":[-2.51544543480816,53.42819301159312],"type":"Point"}
}