{
  "type": "Feature",
  "properties": {
    "iso:country":"GB",
    "wof:name":"CO10 2BJ",
    "wof:placetype":"postalcode"
},
  "geometry": {"coordinates":[0.7238217711045,52.03602429631244],"type":"Point"}
}