{
  "type": "Feature",
  "properties": {
    "iso:country":"GB",
    "wof:name":"BL8 1XP",
    "wof:placetype":"postalcode"
},
  "geometry": {"coordinates":[-2.30792244690972,53.60470418022715],"type":"Point"}
}