{
  "type": "Feature",
  "properties": {
    "date:inception_lower":"1980-01-01",
    "date:inception_upper":"1980-01-31",
    "iso:country":"GB",
    "wof:name":"BL8 1XP",
    "wof:placetype":"postalcode"
},
  "geometry": {"coordinates":[-2.307922,53.604704],"type":"Point"}
}