{
  "type": "Feature",
  "properties": {
    "iso:country":"GB",
    "wof:name":"ME5 7ND",
    "wof:placetype":"postalcode"
},
  "geometry": {"coordinates":[0.53517862728708,51.34919003378023],"type":"Point"}
}