{
  "type": "Feature",
  "properties": {
    "iso:country":"GB",
    "wof:name":"RG31 5DX",
    "wof:placetype":"postalcode"
},
  "geometry": {"coordinates":[-1.04803527178308,51.46012883095845],"type":"Point"}
}