{
  "type": "Feature",
  "properties": {
    "iso:country":"GB",
    "wof:name":"BD2 2EG",
    "wof:placetype":"postalcode"
},
  "geometry": {"coordinates":[-1.72916351690703,53.81950320501079],"type":"Point"}
}