{
  "type": "Feature",
  "properties": {
    "iso:country":"GB",
    "wof:name":"EH15 1HE",
    "wof:placetype":"postalcode"
},
  "geometry": {"coordinates":[-3.11057335784144,55.95470622445996],"type":"Point"}
}