{
  "type": "Feature",
  "properties": {
    "date:inception_lower": "1980-01-01",
    "date:inception_upper": "1980-01-01",
    "iso:country": "GB",
    "wof:name": "G67 4JA",
    "wof:placetype": "postalcode"
  },
  "geometry": {"coordinates":[-4.01948,55.932671],"type":"Point"}
}
