{
  "type": "Feature",
  "properties": {
    "iso:country":"GB",
    "wof:name":"G67 4JA",
    "wof:placetype":"postalcode"
},
  "geometry": {"coordinates":[-4.01947983530128,55.93267148955058],"type":"Point"}
}