{
  "type": "Feature",
  "properties": {
    "iso:country": "GB",
    "wof:name": "G67 4JA",
    "wof:placetype": "postalcode"
  },
  "geometry": {"coordinates":[-4.01948,55.932671],"type":"Point"}
}
