{
  "type": "Feature",
  "properties": {
    "iso:country":"GB",
    "wof:name":"W14 8AS",
    "wof:placetype":"postalcode"
},
  "geometry": {"coordinates":[-0.21508653712626,51.50313974108108],"type":"Point"}
}