{
  "type": "Feature",
  "properties": {
    "iso:country":"GB",
    "wof:name":"OX16 9EG",
    "wof:placetype":"postalcode"
},
  "geometry": {"coordinates":[-1.33639794598355,52.04587820079529],"type":"Point"}
}