{
  "type": "Feature",
  "properties": {
    "iso:country":"GB",
    "wof:name":"SP7 0HF",
    "wof:placetype":"postalcode"
},
  "geometry": {"coordinates":[-2.06336572120706,51.00050527124174],"type":"Point"}
}