{
  "type": "Feature",
  "properties": {
    "iso:country":"GB",
    "wof:name":"DY9 9XD",
    "wof:placetype":"postalcode"
},
  "geometry": {"coordinates":[-2.0737660469135,52.39098276429703],"type":"Point"}
}