{
  "type": "Feature",
  "properties": {
    "iso:country": "GB",
    "wof:name": "SG8 8DU",
    "wof:placetype": "postalcode"
  },
  "geometry": {"coordinates":[0.009146,52.008804],"type":"Point"}
}
