{
  "type": "Feature",
  "properties": {
    "iso:country":"GB",
    "wof:name":"SY11 1PN",
    "wof:placetype":"postalcode"
},
  "geometry": {"coordinates":[-3.05525748585095,52.85903091198492],"type":"Point"}
}