{
  "type": "Feature",
  "properties": {
    "iso:country":"GB",
    "wof:name":"G81 4NW",
    "wof:placetype":"postalcode"
},
  "geometry": {"coordinates":[-4.43310000060316,55.91502768917998],"type":"Point"}
}