{
  "type": "Feature",
  "properties": {
    "date:inception_lower":"1980-01-01",
    "date:inception_upper":"1980-01-31",
    "iso:country":"GB",
    "wof:name":"G81 4NW",
    "wof:placetype":"postalcode"
},
  "geometry": {"coordinates":[-4.433085,55.915021],"type":"Point"}
}