{
  "type": "Feature",
  "properties": {
    "iso:country": "GB",
    "wof:name": "G81 4NW",
    "wof:placetype": "postalcode"
  },
  "geometry": {"coordinates":[-4.433085,55.915021],"type":"Point"}
}
