{
  "type": "Feature",
  "properties": {
    "iso:country":"GB",
    "wof:name":"GU14 7RH",
    "wof:placetype":"postalcode"
},
  "geometry": {"coordinates":[-0.75582458444004,51.2934754064658],"type":"Point"}
}