{
  "type": "Feature",
  "properties": {
    "iso:country":"GB",
    "wof:name":"WR9 7PG",
    "wof:placetype":"postalcode"
},
  "geometry": {"coordinates":[-2.11387671560439,52.29204993343929],"type":"Point"}
}