{
  "type": "Feature",
  "properties": {
    "iso:country": "GB",
    "wof:name": "PH1 3HX",
    "wof:placetype": "postalcode"
  },
  "geometry": {"coordinates":[-3.488559,56.439039],"type":"Point"}
}
