{
  "type": "Feature",
  "properties": {
    "iso:country": "GB",
    "wof:name": "N21 2JD",
    "wof:placetype": "postalcode"
  },
  "geometry": {"coordinates":[-0.08604,51.634409],"type":"Point"}
}
