{
  "type": "Feature",
  "properties": {
    "iso:country": "GB",
    "wof:name": "HP5 3QW",
    "wof:placetype": "postalcode"
  },
  "geometry": {"coordinates":[-0.570324,51.717439],"type":"Point"}
}
