{
  "type": "Feature",
  "properties": {
    "iso:country":"GB",
    "wof:name":"SY23 5EB",
    "wof:placetype":"postalcode"
},
  "geometry": {"coordinates":[-4.13216627500269,52.30084929453254],"type":"Point"}
}