{
  "type": "Feature",
  "properties": {
    "iso:country": "GB",
    "wof:name": "SA40 9XA",
    "wof:placetype": "postalcode"
  },
  "geometry": {"coordinates":[-4.203778,52.06762],"type":"Point"}
}
