{
  "type": "Feature",
  "properties": {
    "iso:country":"GB",
    "wof:name":"KA24 4DA",
    "wof:placetype":"postalcode"
},
  "geometry": {"coordinates":[-4.71343229224795,55.70640034226262],"type":"Point"}
}