{
  "type": "Feature",
  "properties": {
    "iso:country":"GB",
    "wof:name":"SR8 2AW",
    "wof:placetype":"postalcode"
},
  "geometry": {"coordinates":[-1.34285501536784,54.76388893936686],"type":"Point"}
}