{
  "type": "Feature",
  "properties": {
    "date:inception_lower":"2006-03-01",
    "date:inception_upper":"2006-03-31",
    "iso:country":"GB",
    "wof:name":"S74 9LH",
    "wof:placetype":"postalcode"
},
  "geometry": {"coordinates":[-1.464131,53.508293],"type":"Point"}
}