{
  "type": "Feature",
  "properties": {
    "iso:country":"GB",
    "wof:name":"S74 9LH",
    "wof:placetype":"postalcode"
},
  "geometry": {"coordinates":[-1.46413043628385,53.5082744799928],"type":"Point"}
}