{
  "type": "Feature",
  "properties": {
    "iso:country":"GB",
    "wof:name":"EH14 2TS",
    "wof:placetype":"postalcode"
},
  "geometry": {"coordinates":[-3.29563953292614,55.91589622727093],"type":"Point"}
}