{
  "type": "Feature",
  "properties": {
    "date:inception_lower":"1998-06-01",
    "date:inception_upper":"1998-06-30",
    "iso:country":"GB",
    "wof:name":"YO26 9TL",
    "wof:placetype":"postalcode"
},
  "geometry": {"coordinates":[-1.329036,54.033642],"type":"Point"}
}