{
  "type": "Feature",
  "properties": {
    "iso:country":"GB",
    "wof:name":"YO26 9TL",
    "wof:placetype":"postalcode"
},
  "geometry": {"coordinates":[-1.32918438687528,54.03350121805823],"type":"Point"}
}