{
  "type": "Feature",
  "properties": {
    "iso:country":"GB",
    "wof:name":"OL11 3AL",
    "wof:placetype":"postalcode"
},
  "geometry": {"coordinates":[-2.17983950121611,53.59282231856566],"type":"Point"}
}