{
  "type": "Feature",
  "properties": {
    "iso:country":"GB",
    "wof:name":"FY5 2EG",
    "wof:placetype":"postalcode"
},
  "geometry": {"coordinates":[-3.0233798577635,53.88197217130588],"type":"Point"}
}