{
  "type": "Feature",
  "properties": {
    "date:inception_lower":"2008-02-01",
    "date:inception_upper":"2008-02-29",
    "iso:country":"GB",
    "wof:name":"BB1 2EQ",
    "wof:placetype":"postalcode"
},
  "geometry": {"coordinates":[-2.44747,53.730287],"type":"Point"}
}