{
  "type": "Feature",
  "properties": {
    "iso:country":"GB",
    "wof:name":"BB1 2EQ",
    "wof:placetype":"postalcode"
},
  "geometry": {"coordinates":[-2.44754676140948,53.7303411362001],"type":"Point"}
}