{
  "type": "Feature",
  "properties": {
    "iso:country":"GB",
    "wof:name":"NP18 2EZ",
    "wof:placetype":"postalcode"
},
  "geometry": {"coordinates":[-2.89428033963313,51.59565162235329],"type":"Point"}
}