{
  "type": "Feature",
  "properties": {
    "iso:country":"GB",
    "wof:name":"EX8 2ET",
    "wof:placetype":"postalcode"
},
  "geometry": {"coordinates":[-3.38869422737677,50.62462040271951],"type":"Point"}
}