{
  "type": "Feature",
  "properties": {
    "iso:country":"GB",
    "wof:name":"CF34 0HD",
    "wof:placetype":"postalcode"
},
  "geometry": {"coordinates":[-3.66451091048072,51.62260197134189],"type":"Point"}
}