{
  "type": "Feature",
  "properties": {
    "iso:country":"GB",
    "wof:name":"G61 1JU",
    "wof:placetype":"postalcode"
},
  "geometry": {"coordinates":[-4.34332019274169,55.9097231996602],"type":"Point"}
}