{
  "type": "Feature",
  "properties": {
    "iso:country":"GB",
    "wof:name":"BH24 2JQ",
    "wof:placetype":"postalcode"
},
  "geometry": {"coordinates":[-1.83980443514662,50.84069071643149],"type":"Point"}
}