{
  "type": "Feature",
  "properties": {
    "date:inception_lower":"1984-10-01",
    "date:inception_upper":"1984-10-31",
    "iso:country":"GB",
    "wof:name":"BH24 2JQ",
    "wof:placetype":"postalcode"
},
  "geometry": {"coordinates":[-1.839804,50.840691],"type":"Point"}
}