{
  "type": "Feature",
  "properties": {
    "iso:country":"GB",
    "wof:name":"AB24 3PL",
    "wof:placetype":"postalcode"
},
  "geometry": {"coordinates":[-2.1067732736289,57.15776338704353],"type":"Point"}
}