{
  "type": "Feature",
  "properties": {
    "date:inception_lower": "2002-06-01",
    "date:inception_upper": "2002-06-01",
    "iso:country": "GB",
    "wof:name": "LE19 3YP",
    "wof:placetype": "postalcode"
  },
  "geometry": {"coordinates":[-1.218591,52.583053],"type":"Point"}
}
