{
  "type": "Feature",
  "properties": {
    "iso:country":"GB",
    "wof:name":"LE19 3YP",
    "wof:placetype":"postalcode"
},
  "geometry": {"coordinates":[-1.21908291187205,52.58413516796169],"type":"Point"}
}