{
  "type": "Feature",
  "properties": {
    "iso:country": "GB",
    "wof:name": "WS9 9PB",
    "wof:placetype": "postalcode"
  },
  "geometry": {"coordinates":[-1.919073,52.634902],"type":"Point"}
}
