{
  "type": "Feature",
  "properties": {
    "iso:country":"GB",
    "wof:name":"PE37 8NQ",
    "wof:placetype":"postalcode"
},
  "geometry": {"coordinates":[0.77794002217529,52.64485274323538],"type":"Point"}
}