{
  "type": "Feature",
  "properties": {
    "date:inception_lower": "2005-10-01",
    "date:inception_upper": "2005-10-01",
    "iso:country": "GB",
    "wof:name": "PE37 8NQ",
    "wof:placetype": "postalcode"
  },
  "geometry": {"coordinates":[0.77794,52.644853],"type":"Point"}
}
