{
  "type": "Feature",
  "properties": {
    "date:inception_lower":"1997-12-01",
    "date:inception_upper":"1997-12-31",
    "iso:country":"GB",
    "wof:name":"BS41 9HN",
    "wof:placetype":"postalcode"
},
  "geometry": {"coordinates":[-2.66389,51.429488],"type":"Point"}
}