{
  "type": "Feature",
  "properties": {
    "iso:country":"GB",
    "wof:name":"DD4 9JX",
    "wof:placetype":"postalcode"
},
  "geometry": {"coordinates":[-2.9320839723766,56.48630737632956],"type":"Point"}
}