{
  "type": "Feature",
  "properties": {
    "iso:country":"GB",
    "wof:name":"RH12 4JZ",
    "wof:placetype":"postalcode"
},
  "geometry": {"coordinates":[-0.29956766680338,51.07907887867986],"type":"Point"}
}