{
  "type": "Feature",
  "properties": {
    "date:inception_lower": "2000-06-01",
    "date:inception_upper": "2000-06-01",
    "iso:country": "GB",
    "wof:name": "OX4 7YH",
    "wof:placetype": "postalcode"
  },
  "geometry": {"coordinates":[-1.191422,51.716672],"type":"Point"}
}
