{
  "type": "Feature",
  "properties": {
    "iso:country":"GB",
    "wof:name":"OX4 7YH",
    "wof:placetype":"postalcode"
},
  "geometry": {"coordinates":[-1.19142206054525,51.71667231133448],"type":"Point"}
}