{
  "type": "Feature",
  "properties": {
    "date:inception_lower":"1980-01-01",
    "date:inception_upper":"1980-01-31",
    "iso:country":"GB",
    "wof:name":"KA7 3BY",
    "wof:placetype":"postalcode"
},
  "geometry": {"coordinates":[-4.621952,55.454566],"type":"Point"}
}