{
  "type": "Feature",
  "properties": {
    "iso:country":"GB",
    "wof:name":"B24 9EY",
    "wof:placetype":"postalcode"
},
  "geometry": {"coordinates":[-1.82871537767366,52.52542660258244],"type":"Point"}
}