{
  "type": "Feature",
  "properties": {
    "iso:country": "GB",
    "wof:name": "OX7 6NP",
    "wof:placetype": "postalcode"
  },
  "geometry": {"coordinates":[-1.592705,51.912567],"type":"Point"}
}
