{
  "type": "Feature",
  "properties": {
    "iso:country":"GB",
    "wof:name":"OX7 6NP",
    "wof:placetype":"postalcode"
},
  "geometry": {"coordinates":[-1.5927054177782,51.9125671221237],"type":"Point"}
}