{
  "type": "Feature",
  "properties": {
    "iso:country":"GB",
    "wof:name":"ST2 9JH",
    "wof:placetype":"postalcode"
},
  "geometry": {"coordinates":[-2.15223831404173,53.02042381495338],"type":"Point"}
}