{
  "type": "Feature",
  "properties": {
    "iso:country":"GB",
    "wof:name":"CH42 6QG",
    "wof:placetype":"postalcode"
},
  "geometry": {"coordinates":[-3.03145371204031,53.3741076312303],"type":"Point"}
}