{
  "type": "Feature",
  "properties": {
    "iso:country":"GB",
    "wof:name":"CR3 5NU",
    "wof:placetype":"postalcode"
},
  "geometry": {"coordinates":[-0.10040920118018,51.29106172157793],"type":"Point"}
}