{
  "type": "Feature",
  "properties": {
    "date:inception_lower": "1980-01-01",
    "date:inception_upper": "1980-01-01",
    "iso:country": "GB",
    "wof:name": "CR3 5NU",
    "wof:placetype": "postalcode"
  },
  "geometry": {"coordinates":[-0.100409,51.291062],"type":"Point"}
}
