{
  "type": "Feature",
  "properties": {
    "iso:country":"GB",
    "wof:name":"M27 5AE",
    "wof:placetype":"postalcode"
},
  "geometry": {"coordinates":[-2.33580222239303,53.50911877524846],"type":"Point"}
}