{
  "type": "Feature",
  "properties": {
    "iso:country":"GB",
    "wof:name":"NR29 4TU",
    "wof:placetype":"postalcode"
},
  "geometry": {"coordinates":[1.62939075860335,52.70116708909317],"type":"Point"}
}