{
  "type": "Feature",
  "properties": {
    "date:inception_lower": "1982-03-01",
    "date:inception_upper": "1982-03-01",
    "iso:country": "GB",
    "wof:name": "NR29 4TU",
    "wof:placetype": "postalcode"
  },
  "geometry": {"coordinates":[1.629391,52.701167],"type":"Point"}
}
