{
  "type": "Feature",
  "properties": {
    "iso:country": "GB",
    "wof:name": "WA6 8AS",
    "wof:placetype": "postalcode"
  },
  "geometry": {"coordinates":[-2.672526,53.267231],"type":"Point"}
}
