{
  "type": "Feature",
  "properties": {
    "iso:country":"GB",
    "wof:name":"WA6 8AS",
    "wof:placetype":"postalcode"
},
  "geometry": {"coordinates":[-2.67252611592329,53.26723085765428],"type":"Point"}
}