{
  "type": "Feature",
  "properties": {
    "date:inception_lower":"1980-01-01",
    "date:inception_upper":"1980-01-31",
    "iso:country":"GB",
    "wof:name":"WA6 8AS",
    "wof:placetype":"postalcode"
},
  "geometry": {"coordinates":[-2.672526,53.267231],"type":"Point"}
}