{
  "type": "Feature",
  "properties": {
    "iso:country":"GB",
    "wof:name":"G21 3SA",
    "wof:placetype":"postalcode"
},
  "geometry": {"coordinates":[-4.20022283410136,55.89613305410742],"type":"Point"}
}