{
  "type": "Feature",
  "properties": {
    "date:inception_lower": "1996-06-01",
    "date:inception_upper": "1996-06-01",
    "iso:country": "GB",
    "wof:name": "AB39 2FH",
    "wof:placetype": "postalcode"
  },
  "geometry": {"coordinates":[-2.215989,56.96279],"type":"Point"}
}
