{
  "type": "Feature",
  "properties": {
    "iso:country": "GB",
    "wof:name": "TN2 4NR",
    "wof:placetype": "postalcode"
  },
  "geometry": {"coordinates":[0.318824,51.143893],"type":"Point"}
}
