{
  "type": "Feature",
  "properties": {
    "iso:country":"GB",
    "wof:name":"TN2 4NR",
    "wof:placetype":"postalcode"
},
  "geometry": {"coordinates":[0.3188238567724,51.14389311154358],"type":"Point"}
}