{
  "type": "Feature",
  "properties": {
    "iso:country":"GB",
    "wof:name":"NG5 1RB",
    "wof:placetype":"postalcode"
},
  "geometry": {"coordinates":[-1.15930960178101,52.98111816059534],"type":"Point"}
}