{
  "type": "Feature",
  "properties": {
    "date:inception_lower": "2005-12-01",
    "date:inception_upper": "2005-12-01",
    "iso:country": "GB",
    "wof:name": "NG5 1RB",
    "wof:placetype": "postalcode"
  },
  "geometry": {"coordinates":[-1.15931,52.981118],"type":"Point"}
}
