{
  "type": "Feature",
  "properties": {
    "date:inception_lower": "2024-07-01",
    "date:inception_upper": "2024-07-01",
    "iso:country": "GB",
    "wof:name": "DN18 5FZ",
    "wof:placetype": "postalcode"
  },
  "geometry": {"coordinates":[-0.442809,53.68802],"type":"Point"}
}
