{
  "type": "Feature",
  "properties": {
    "date:inception_lower":"1990-02-01",
    "date:inception_upper":"1990-02-28",
    "iso:country":"GB",
    "wof:name":"CT20 2AD",
    "wof:placetype":"postalcode"
},
  "geometry": {"coordinates":[1.175848,51.078458],"type":"Point"}
}