{
  "type": "Feature",
  "properties": {
    "iso:country": "GB",
    "wof:name": "CT20 2AD",
    "wof:placetype": "postalcode"
  },
  "geometry": {"coordinates":[1.175848,51.078458],"type":"Point"}
}
