{
  "type": "Feature",
  "properties": {
    "iso:country":"GB",
    "wof:name":"PR5 6ER",
    "wof:placetype":"postalcode"
},
  "geometry": {"coordinates":[-2.66385698401997,53.72238971009072],"type":"Point"}
}