{
  "type": "Feature",
  "properties": {
    "iso:country":"GB",
    "wof:name":"BN6 9NN",
    "wof:placetype":"postalcode"
},
  "geometry": {"coordinates":[-0.15620665456667,50.92583769613044],"type":"Point"}
}