{
  "type": "Feature",
  "properties": {
    "iso:country":"GB",
    "wof:name":"HA2 6HT",
    "wof:placetype":"postalcode"
},
  "geometry": {"coordinates":[-0.36043995068459,51.59583130998199],"type":"Point"}
}