{
  "type": "Feature",
  "properties": {
    "iso:country":"GB",
    "wof:name":"DH6 2LD",
    "wof:placetype":"postalcode"
},
  "geometry": {"coordinates":[-1.38573268972343,54.75985385679071],"type":"Point"}
}