{
  "type": "Feature",
  "properties": {
    "iso:country": "GB",
    "wof:name": "DG7 2LB",
    "wof:placetype": "postalcode"
  },
  "geometry": {"coordinates":[-4.188858,54.883804],"type":"Point"}
}
