{
  "type": "Feature",
  "properties": {
    "iso:country":"GB",
    "wof:name":"DA13 9QB",
    "wof:placetype":"postalcode"
},
  "geometry": {"coordinates":[0.32464786692239,51.41207787769934],"type":"Point"}
}