{
  "type": "Feature",
  "properties": {
    "iso:country": "GB",
    "wof:name": "LL31 9EW",
    "wof:placetype": "postalcode"
  },
  "geometry": {"coordinates":[-3.803042,53.284663],"type":"Point"}
}
