{
  "type": "Feature",
  "properties": {
    "iso:country":"GB",
    "wof:name":"LL31 9EW",
    "wof:placetype":"postalcode"
},
  "geometry": {"coordinates":[-3.80304171463763,53.28466333685807],"type":"Point"}
}