{
  "type": "Feature",
  "properties": {
    "iso:country": "GB",
    "wof:name": "BB10 3DP",
    "wof:placetype": "postalcode"
  },
  "geometry": {"coordinates":[-2.231067,53.801978],"type":"Point"}
}
