{
  "type": "Feature",
  "properties": {
    "iso:country":"GB",
    "wof:name":"TS1 4PP",
    "wof:placetype":"postalcode"
},
  "geometry": {"coordinates":[-1.24892048211124,54.56644074552953],"type":"Point"}
}