{
  "type": "Feature",
  "properties": {
    "date:inception_lower": "1980-01-01",
    "date:inception_upper": "1980-01-01",
    "iso:country": "GB",
    "wof:name": "DN6 9JD",
    "wof:placetype": "postalcode"
  },
  "geometry": {"coordinates":[-1.159107,53.600748],"type":"Point"}
}
