{
  "type": "Feature",
  "properties": {
    "iso:country":"GB",
    "wof:name":"OL7 0AS",
    "wof:placetype":"postalcode"
},
  "geometry": {"coordinates":[-2.10658560818611,53.48714424220951],"type":"Point"}
}