{
  "type": "Feature",
  "properties": {
    "iso:country": "GB",
    "wof:name": "OL7 0AS",
    "wof:placetype": "postalcode"
  },
  "geometry": {"coordinates":[-2.106586,53.487144],"type":"Point"}
}
