{
  "type": "Feature",
  "properties": {
    "date:inception_lower": "1980-01-01",
    "date:inception_upper": "1980-01-01",
    "iso:country": "GB",
    "wof:name": "B69 2LA",
    "wof:placetype": "postalcode"
  },
  "geometry": {"coordinates":[-2.056509,52.512402],"type":"Point"}
}
