{
  "type": "Feature",
  "properties": {
    "iso:country":"GB",
    "wof:name":"B69 2LA",
    "wof:placetype":"postalcode"
},
  "geometry": {"coordinates":[-2.05650902339718,52.5124022920817],"type":"Point"}
}