{
  "type": "Feature",
  "properties": {
    "iso:country":"GB",
    "wof:name":"LE13 0BZ",
    "wof:placetype":"postalcode"
},
  "geometry": {"coordinates":[-0.89890717305871,52.76174435167761],"type":"Point"}
}