{
  "type": "Feature",
  "properties": {
    "iso:country":"GB",
    "wof:name":"BH22 8BH",
    "wof:placetype":"postalcode"
},
  "geometry": {"coordinates":[-1.87525739471721,50.80704795783093],"type":"Point"}
}