{
  "type": "Feature",
  "properties": {
    "iso:country":"GB",
    "wof:name":"OX13 5JT",
    "wof:placetype":"postalcode"
},
  "geometry": {"coordinates":[-1.35923583532036,51.70927305193995],"type":"Point"}
}