{
  "type": "Feature",
  "properties": {
    "iso:country": "GB",
    "wof:name": "OX13 5JT",
    "wof:placetype": "postalcode"
  },
  "geometry": {"coordinates":[-1.359236,51.709273],"type":"Point"}
}
