{
  "type": "Feature",
  "properties": {
    "date:inception_lower": "1980-01-01",
    "date:inception_upper": "1980-01-01",
    "iso:country": "GB",
    "wof:name": "OX13 5JT",
    "wof:placetype": "postalcode"
  },
  "geometry": {"coordinates":[-1.359236,51.709273],"type":"Point"}
}
