{
  "type": "Feature",
  "properties": {
    "date:inception_lower": "1980-01-01",
    "date:inception_upper": "1980-01-01",
    "iso:country": "GB",
    "wof:name": "LS12 1TX",
    "wof:placetype": "postalcode"
  },
  "geometry": {"coordinates":[-1.590535,53.795373],"type":"Point"}
}
