{
  "type": "Feature",
  "properties": {
    "iso:country": "GB",
    "wof:name": "LS12 1TX",
    "wof:placetype": "postalcode"
  },
  "geometry": {"coordinates":[-1.590535,53.795373],"type":"Point"}
}
