{
  "type": "Feature",
  "properties": {
    "date:inception_lower":"1980-01-01",
    "date:inception_upper":"1980-01-31",
    "iso:country":"GB",
    "wof:name":"ST11 9BZ",
    "wof:placetype":"postalcode"
},
  "geometry": {"coordinates":[-2.05498,52.971913],"type":"Point"}
}