{
  "type": "Feature",
  "properties": {
    "date:inception_lower": "1980-01-01",
    "date:inception_upper": "1980-01-01",
    "iso:country": "GB",
    "wof:name": "BH3 7DJ",
    "wof:placetype": "postalcode"
  },
  "geometry": {"coordinates":[-1.888392,50.73816],"type":"Point"}
}
