{
  "type": "Feature",
  "properties": {
    "iso:country":"GB",
    "wof:name":"BH3 7DJ",
    "wof:placetype":"postalcode"
},
  "geometry": {"coordinates":[-1.88839253376101,50.73815998471815],"type":"Point"}
}