{
  "type": "Feature",
  "properties": {
    "iso:country":"GB",
    "wof:name":"CA7 2QR",
    "wof:placetype":"postalcode"
},
  "geometry": {"coordinates":[-3.37890981553559,54.72862667444677],"type":"Point"}
}