{
  "type": "Feature",
  "properties": {
    "iso:country": "GB",
    "wof:name": "FY4 3RN",
    "wof:placetype": "postalcode"
  },
  "geometry": {"coordinates":[-3.028296,53.779864],"type":"Point"}
}
