{
  "type": "Feature",
  "properties": {
    "iso:country":"GB",
    "wof:name":"FY4 3RN",
    "wof:placetype":"postalcode"
},
  "geometry": {"coordinates":[-3.02741748793026,53.78043231833645],"type":"Point"}
}