{
  "type": "Feature",
  "properties": {
    "date:inception_lower": "1991-09-01",
    "date:inception_upper": "1991-09-01",
    "iso:country": "GB",
    "wof:name": "IP3 8SN",
    "wof:placetype": "postalcode"
  },
  "geometry": {"coordinates":[1.211049,52.036147],"type":"Point"}
}
