{
  "type": "Feature",
  "properties": {
    "iso:country":"GB",
    "wof:name":"BH21 1QE",
    "wof:placetype":"postalcode"
},
  "geometry": {"coordinates":[-1.98434019311279,50.79742837348496],"type":"Point"}
}