{
  "type": "Feature",
  "properties": {
    "date:inception_lower": "1980-01-01",
    "date:inception_upper": "1980-01-01",
    "iso:country": "GB",
    "wof:name": "BH21 1QE",
    "wof:placetype": "postalcode"
  },
  "geometry": {"coordinates":[-1.98434,50.797428],"type":"Point"}
}
