{
  "type": "Feature",
  "properties": {
    "date:inception_lower": "1980-01-01",
    "date:inception_upper": "1980-01-01",
    "iso:country": "GB",
    "wof:name": "B13 0QF",
    "wof:placetype": "postalcode"
  },
  "geometry": {"coordinates":[-1.88585,52.426354],"type":"Point"}
}
