{
  "type": "Feature",
  "properties": {
    "iso:country":"GB",
    "wof:name":"B13 0QF",
    "wof:placetype":"postalcode"
},
  "geometry": {"coordinates":[-1.88585037976305,52.42635398963169],"type":"Point"}
}