{
  "type": "Feature",
  "properties": {
    "iso:country": "GB",
    "wof:name": "B13 0QF",
    "wof:placetype": "postalcode"
  },
  "geometry": {"coordinates":[-1.88585,52.426354],"type":"Point"}
}
