{
  "type": "Feature",
  "properties": {
    "iso:country":"GB",
    "wof:name":"KT15 2PN",
    "wof:placetype":"postalcode"
},
  "geometry": {"coordinates":[-0.4831120824215,51.37373696180016],"type":"Point"}
}