{
  "type": "Feature",
  "properties": {
    "date:inception_lower": "1980-01-01",
    "date:inception_upper": "1980-01-01",
    "iso:country": "GB",
    "wof:name": "EX20 4BS",
    "wof:placetype": "postalcode"
  },
  "geometry": {"coordinates":[-4.199392,50.658029],"type":"Point"}
}
