{
  "type": "Feature",
  "properties": {
    "iso:country":"GB",
    "wof:name":"EX20 4BS",
    "wof:placetype":"postalcode"
},
  "geometry": {"coordinates":[-4.1991591707101,50.65847359082821],"type":"Point"}
}