{
  "type": "Feature",
  "properties": {
    "iso:country": "GB",
    "wof:name": "EX20 4BS",
    "wof:placetype": "postalcode"
  },
  "geometry": {"coordinates":[-4.199392,50.658029],"type":"Point"}
}
