{
  "type": "Feature",
  "properties": {
    "iso:country": "GB",
    "wof:name": "IV30 6LS",
    "wof:placetype": "postalcode"
  },
  "geometry": {"coordinates":[-3.280918,57.645617],"type":"Point"}
}
