{
  "type": "Feature",
  "properties": {
    "iso:country":"GB",
    "wof:name":"IV30 6LS",
    "wof:placetype":"postalcode"
},
  "geometry": {"coordinates":[-3.28091835128321,57.64561741897579],"type":"Point"}
}