{
  "type": "Feature",
  "properties": {
    "iso:country": "GB",
    "wof:name": "CT8 8NL",
    "wof:placetype": "postalcode"
  },
  "geometry": {"coordinates":[1.335909,51.378555],"type":"Point"}
}
