{
  "type": "Feature",
  "properties": {
    "iso:country":"GB",
    "wof:name":"PR7 5EF",
    "wof:placetype":"postalcode"
},
  "geometry": {"coordinates":[-2.66552574722462,53.61976970775122],"type":"Point"}
}