{
  "type": "Feature",
  "properties": {
    "iso:country": "GB",
    "wof:name": "PR7 5EF",
    "wof:placetype": "postalcode"
  },
  "geometry": {"coordinates":[-2.665526,53.61977],"type":"Point"}
}
