{
  "type": "Feature",
  "properties": {
    "date:inception_lower": "2006-01-01",
    "date:inception_upper": "2006-01-01",
    "iso:country": "GB",
    "wof:name": "PR7 5EF",
    "wof:placetype": "postalcode"
  },
  "geometry": {"coordinates":[-2.665526,53.61977],"type":"Point"}
}
