{
  "type": "Feature",
  "properties": {
    "iso:country": "GB",
    "wof:name": "PA2 0DW",
    "wof:placetype": "postalcode"
  },
  "geometry": {"coordinates":[-4.467614,55.823472],"type":"Point"}
}
