{
  "type": "Feature",
  "properties": {
    "iso:country":"GB",
    "wof:name":"AL7 3LS",
    "wof:placetype":"postalcode"
},
  "geometry": {"coordinates":[-0.18984103807309,51.79275332557944],"type":"Point"}
}