{
  "type": "Feature",
  "properties": {
    "iso:country":"GB",
    "wof:name":"LN6 8TN",
    "wof:placetype":"postalcode"
},
  "geometry": {"coordinates":[-0.58032455788461,53.19705169101771],"type":"Point"}
}