{
  "type": "Feature",
  "properties": {
    "iso:country":"GB",
    "wof:name":"RG12 2SG",
    "wof:placetype":"postalcode"
},
  "geometry": {"coordinates":[-0.72157672533339,51.41521135183061],"type":"Point"}
}