{
  "type": "Feature",
  "properties": {
    "iso:country": "GB",
    "wof:name": "RG12 2SG",
    "wof:placetype": "postalcode"
  },
  "geometry": {"coordinates":[-0.721577,51.415211],"type":"Point"}
}
