{
  "type": "Feature",
  "properties": {
    "date:inception_lower":"1980-01-01",
    "date:inception_upper":"1980-01-31",
    "iso:country":"GB",
    "wof:name":"RG12 2SG",
    "wof:placetype":"postalcode"
},
  "geometry": {"coordinates":[-0.721577,51.415211],"type":"Point"}
}