{
  "type": "Feature",
  "properties": {
    "iso:country": "GB",
    "wof:name": "M21 9FU",
    "wof:placetype": "postalcode"
  },
  "geometry": {"coordinates":[-2.287705,53.438352],"type":"Point"}
}
