{
  "type": "Feature",
  "properties": {
    "date:inception_lower": "1994-05-01",
    "date:inception_upper": "1994-05-01",
    "iso:country": "GB",
    "wof:name": "M21 9FU",
    "wof:placetype": "postalcode"
  },
  "geometry": {"coordinates":[-2.287705,53.438352],"type":"Point"}
}
