{
  "type": "Feature",
  "properties": {
    "date:inception_lower": "1980-01-01",
    "date:inception_upper": "1980-01-01",
    "iso:country": "GB",
    "wof:name": "DL8 3AT",
    "wof:placetype": "postalcode"
  },
  "geometry": {"coordinates":[-1.99404,54.294668],"type":"Point"}
}
