{
  "type": "Feature",
  "properties": {
    "iso:country":"GB",
    "wof:name":"DL8 3AT",
    "wof:placetype":"postalcode"
},
  "geometry": {"coordinates":[-1.99368187610655,54.29491780567405],"type":"Point"}
}