{
  "type": "Feature",
  "properties": {
    "date:inception_lower": "1980-01-01",
    "date:inception_upper": "1980-01-01",
    "iso:country": "GB",
    "wof:name": "GL14 2BT",
    "wof:placetype": "postalcode"
  },
  "geometry": {"coordinates":[-2.488533,51.82737],"type":"Point"}
}
