{
  "type": "Feature",
  "properties": {
    "iso:country":"GB",
    "wof:name":"NG25 0NU",
    "wof:placetype":"postalcode"
},
  "geometry": {"coordinates":[-0.96579100066539,53.07568167555016],"type":"Point"}
}