{
  "type": "Feature",
  "properties": {
    "iso:country":"GB",
    "wof:name":"B42 1NP",
    "wof:placetype":"postalcode"
},
  "geometry": {"coordinates":[-1.92952168242207,52.53198406248804],"type":"Point"}
}