{
  "type": "Feature",
  "properties": {
    "iso:country": "GB",
    "wof:name": "LE8 9HF",
    "wof:placetype": "postalcode"
  },
  "geometry": {"coordinates":[-1.029524,52.580945],"type":"Point"}
}
