{
  "type": "Feature",
  "properties": {
    "iso:country":"GB",
    "wof:name":"LE8 9HF",
    "wof:placetype":"postalcode"
},
  "geometry": {"coordinates":[-1.02952433401434,52.58094484265889],"type":"Point"}
}