{
  "type": "Feature",
  "properties": {
    "date:inception_lower": "2001-12-01",
    "date:inception_upper": "2001-12-01",
    "iso:country": "GB",
    "wof:name": "LS1 3DA",
    "wof:placetype": "postalcode"
  },
  "geometry": {"coordinates":[-1.549455,53.801059],"type":"Point"}
}
