{
  "type": "Feature",
  "properties": {
    "iso:country":"GB",
    "wof:name":"DH5 9DZ",
    "wof:placetype":"postalcode"
},
  "geometry": {"coordinates":[-1.44829632177001,54.82496577942663],"type":"Point"}
}