{
  "type": "Feature",
  "properties": {
    "iso:country":"GB",
    "wof:name":"BN7 2AN",
    "wof:placetype":"postalcode"
},
  "geometry": {"coordinates":[0.01805120544297,50.87420163803003],"type":"Point"}
}