{
  "type": "Feature",
  "properties": {
    "date:inception_lower": "1980-01-01",
    "date:inception_upper": "1980-01-01",
    "iso:country": "GB",
    "wof:name": "KT15 2SW",
    "wof:placetype": "postalcode"
  },
  "geometry": {"coordinates":[-0.478565,51.371331],"type":"Point"}
}
