{
  "type": "Feature",
  "properties": {
    "iso:country":"GB",
    "wof:name":"SO20 6DT",
    "wof:placetype":"postalcode"
},
  "geometry": {"coordinates":[-1.49060709525485,51.13044782863422],"type":"Point"}
}