{
  "type": "Feature",
  "properties": {
    "date:inception_lower": "1980-01-01",
    "date:inception_upper": "1980-01-01",
    "iso:country": "GB",
    "wof:name": "NW6 5BU",
    "wof:placetype": "postalcode"
  },
  "geometry": {"coordinates":[-0.200539,51.533366],"type":"Point"}
}
