{
  "type": "Feature",
  "properties": {
    "iso:country":"GB",
    "wof:name":"ML9 2QW",
    "wof:placetype":"postalcode"
},
  "geometry": {"coordinates":[-3.96049704205,55.73428702074467],"type":"Point"}
}