{
  "type": "Feature",
  "properties": {
    "iso:country":"GB",
    "wof:name":"CR7 7QN",
    "wof:placetype":"postalcode"
},
  "geometry": {"coordinates":[-0.11319791831266,51.40095331754336],"type":"Point"}
}