{
  "type": "Feature",
  "properties": {
    "iso:country":"GB",
    "wof:name":"NW9 6JR",
    "wof:placetype":"postalcode"
},
  "geometry": {"coordinates":[-0.24681610757105,51.58302075091717],"type":"Point"}
}