{
  "type": "Feature",
  "properties": {
    "iso:country": "GB",
    "wof:name": "CM9 6HS",
    "wof:placetype": "postalcode"
  },
  "geometry": {"coordinates":[0.66692,51.728429],"type":"Point"}
}
