{
  "type": "Feature",
  "properties": {
    "iso:country": "GB",
    "wof:name": "PH10 6TZ",
    "wof:placetype": "postalcode"
  },
  "geometry": {"coordinates":[-3.329159,56.58502],"type":"Point"}
}
