{
  "type": "Feature",
  "properties": {
    "date:inception_lower": "1992-05-01",
    "date:inception_upper": "1992-05-01",
    "iso:country": "GB",
    "wof:name": "EH19 3BX",
    "wof:placetype": "postalcode"
  },
  "geometry": {"coordinates":[-3.100408,55.873542],"type":"Point"}
}
