{
  "type": "Feature",
  "properties": {
    "iso:country":"GB",
    "wof:name":"WR8 0SH",
    "wof:placetype":"postalcode"
},
  "geometry": {"coordinates":[-2.23089761401043,52.0589994401672],"type":"Point"}
}