{
  "type": "Feature",
  "properties": {
    "iso:country":"GB",
    "wof:name":"LS15 9LD",
    "wof:placetype":"postalcode"
},
  "geometry": {"coordinates":[-1.44275564949342,53.79135334848714],"type":"Point"}
}