{
  "type": "Feature",
  "properties": {
    "date:inception_lower":"1998-12-01",
    "date:inception_upper":"1998-12-31",
    "iso:country":"GB",
    "wof:name":"LS15 9LD",
    "wof:placetype":"postalcode"
},
  "geometry": {"coordinates":[-1.442756,53.791353],"type":"Point"}
}