{
  "type": "Feature",
  "properties": {
    "iso:country":"GB",
    "wof:name":"W10 5EW",
    "wof:placetype":"postalcode"
},
  "geometry": {"coordinates":[-0.22390076197435,51.52436075941866],"type":"Point"}
}