{
  "type": "Feature",
  "properties": {
    "iso:country":"GB",
    "wof:name":"ME9 7AR",
    "wof:placetype":"postalcode"
},
  "geometry": {"coordinates":[0.64527239840194,51.37601131882558],"type":"Point"}
}