{
  "type": "Feature",
  "properties": {
    "iso:country": "GB",
    "wof:name": "ME9 7AR",
    "wof:placetype": "postalcode"
  },
  "geometry": {"coordinates":[0.645403,51.376028],"type":"Point"}
}
