{
  "type": "Feature",
  "properties": {
    "iso:country":"GB",
    "wof:name":"OX2 6TH",
    "wof:placetype":"postalcode"
},
  "geometry": {"coordinates":[-1.2676688440469,51.76917751679942],"type":"Point"}
}