{
  "type": "Feature",
  "properties": {
    "iso:country":"GB",
    "wof:name":"WA4 2NB",
    "wof:placetype":"postalcode"
},
  "geometry": {"coordinates":[-2.53858104032039,53.38207791403913],"type":"Point"}
}