{
  "type": "Feature",
  "properties": {
    "iso:country":"GB",
    "wof:name":"EN10 6HP",
    "wof:placetype":"postalcode"
},
  "geometry": {"coordinates":[-0.02222110461857,51.72614448084961],"type":"Point"}
}