{
  "type": "Feature",
  "properties": {
    "iso:country": "GB",
    "wof:name": "PE10 0JJ",
    "wof:placetype": "postalcode"
  },
  "geometry": {"coordinates":[-0.445878,52.737903],"type":"Point"}
}
