{
  "type": "Feature",
  "properties": {
    "iso:country":"GB",
    "wof:name":"DE22 3LJ",
    "wof:placetype":"postalcode"
},
  "geometry": {"coordinates":[-1.49928328785768,52.91799746042017],"type":"Point"}
}