{
  "type": "Feature",
  "properties": {
    "date:inception_lower": "1995-07-01",
    "date:inception_upper": "1995-07-01",
    "iso:country": "GB",
    "wof:name": "SW18 1QU",
    "wof:placetype": "postalcode"
  },
  "geometry": {"coordinates":[-0.200201,51.453157],"type":"Point"}
}
