{
  "type": "Feature",
  "properties": {
    "iso:country": "GB",
    "wof:name": "SW18 1QU",
    "wof:placetype": "postalcode"
  },
  "geometry": {"coordinates":[-0.200241,51.45313],"type":"Point"}
}
