{
  "type": "Feature",
  "properties": {
    "iso:country":"GB",
    "wof:name":"L20 5ED",
    "wof:placetype":"postalcode"
},
  "geometry": {"coordinates":[-2.9921529794612,53.45902658551135],"type":"Point"}
}