{
  "type": "Feature",
  "properties": {
    "iso:country":"GB",
    "wof:name":"ME20 7DA",
    "wof:placetype":"postalcode"
},
  "geometry": {"coordinates":[0.4666720734861,51.3074571760533],"type":"Point"}
}