{
  "type": "Feature",
  "properties": {
    "iso:country":"GB",
    "wof:name":"S73 8RN",
    "wof:placetype":"postalcode"
},
  "geometry": {"coordinates":[-1.42080704404039,53.5295550735809],"type":"Point"}
}