{
  "type": "Feature",
  "properties": {
    "iso:country":"GB",
    "wof:name":"MK13 8AU",
    "wof:placetype":"postalcode"
},
  "geometry": {"coordinates":[-0.7703085501926,52.04716687338269],"type":"Point"}
}