{
  "type": "Feature",
  "properties": {
    "date:inception_lower": "1980-01-01",
    "date:inception_upper": "1980-01-01",
    "iso:country": "GB",
    "wof:name": "DH3 2ND",
    "wof:placetype": "postalcode"
  },
  "geometry": {"coordinates":[-1.565964,54.891934],"type":"Point"}
}
