{
  "type": "Feature",
  "properties": {
    "iso:country": "GB",
    "wof:name": "DH3 2ND",
    "wof:placetype": "postalcode"
  },
  "geometry": {"coordinates":[-1.565964,54.891934],"type":"Point"}
}
