{
  "type": "Feature",
  "properties": {
    "iso:country":"GB",
    "wof:name":"DH3 2ND",
    "wof:placetype":"postalcode"
},
  "geometry": {"coordinates":[-1.5659635881849,54.89193398023868],"type":"Point"}
}