{
  "type": "Feature",
  "properties": {
    "iso:country":"GB",
    "wof:name":"OX7 7BX",
    "wof:placetype":"postalcode"
},
  "geometry": {"coordinates":[-1.36256228632682,51.92645328084681],"type":"Point"}
}