{
  "type": "Feature",
  "properties": {
    "date:inception_lower": "1998-12-01",
    "date:inception_upper": "1998-12-01",
    "iso:country": "GB",
    "wof:name": "KY13 8QY",
    "wof:placetype": "postalcode"
  },
  "geometry": {"coordinates":[-3.431483,56.209714],"type":"Point"}
}
