{
  "type": "Feature",
  "properties": {
    "date:inception_lower":"2004-08-01",
    "date:inception_upper":"2004-08-31",
    "iso:country":"GB",
    "wof:name":"SN11 9RH",
    "wof:placetype":"postalcode"
},
  "geometry": {"coordinates":[-2.005289,51.445333],"type":"Point"}
}