{
  "type": "Feature",
  "properties": {
    "iso:country":"GB",
    "wof:name":"SN11 9RH",
    "wof:placetype":"postalcode"
},
  "geometry": {"coordinates":[-2.00528948537238,51.44533337732066],"type":"Point"}
}