{
  "type": "Feature",
  "properties": {
    "iso:country": "GB",
    "wof:name": "SN11 9RH",
    "wof:placetype": "postalcode"
  },
  "geometry": {"coordinates":[-2.005289,51.445333],"type":"Point"}
}
