{
  "type": "Feature",
  "properties": {
    "iso:country":"GB",
    "wof:name":"TS24 9JH",
    "wof:placetype":"postalcode"
},
  "geometry": {"coordinates":[-1.22618286145081,54.70775236040214],"type":"Point"}
}