{
  "type": "Feature",
  "properties": {
    "iso:country":"GB",
    "wof:name":"FY3 9TU",
    "wof:placetype":"postalcode"
},
  "geometry": {"coordinates":[-3.00118994702344,53.80324204574779],"type":"Point"}
}