{
  "type": "Feature",
  "properties": {
    "date:inception_lower": "1992-08-01",
    "date:inception_upper": "1992-08-01",
    "iso:country": "GB",
    "wof:name": "NN17 3EQ",
    "wof:placetype": "postalcode"
  },
  "geometry": {"coordinates":[-0.606198,52.507897],"type":"Point"}
}
