{
  "type": "Feature",
  "properties": {
    "iso:country":"GB",
    "wof:name":"NN17 3EQ",
    "wof:placetype":"postalcode"
},
  "geometry": {"coordinates":[-0.60619837744292,52.50789687795275],"type":"Point"}
}