{
  "type": "Feature",
  "properties": {
    "iso:country":"GB",
    "wof:name":"AB15 8QJ",
    "wof:placetype":"postalcode"
},
  "geometry": {"coordinates":[-2.2325083641073,57.12881148790478],"type":"Point"}
}