{
  "type": "Feature",
  "properties": {
    "iso:country": "GB",
    "wof:name": "BL5 1EU",
    "wof:placetype": "postalcode"
  },
  "geometry": {"coordinates":[-2.471118,53.543222],"type":"Point"}
}
