{
  "type": "Feature",
  "properties": {
    "iso:country":"GB",
    "wof:name":"BL5 1EU",
    "wof:placetype":"postalcode"
},
  "geometry": {"coordinates":[-2.47111788261102,53.5432224299327],"type":"Point"}
}