{
  "type": "Feature",
  "properties": {
    "iso:country":"GB",
    "wof:name":"CB7 5AG",
    "wof:placetype":"postalcode"
},
  "geometry": {"coordinates":[0.34560740059252,52.32913815098165],"type":"Point"}
}