{
  "type": "Feature",
  "properties": {
    "iso:country":"GB",
    "wof:name":"SL1 2JA",
    "wof:placetype":"postalcode"
},
  "geometry": {"coordinates":[-0.59850898133125,51.50547027606643],"type":"Point"}
}