{
  "type": "Feature",
  "properties": {
    "iso:country": "GB",
    "wof:name": "SL1 2JA",
    "wof:placetype": "postalcode"
  },
  "geometry": {"coordinates":[-0.598509,51.50547],"type":"Point"}
}
