{
  "type": "Feature",
  "properties": {
    "iso:country":"GB",
    "wof:name":"BB1 8JD",
    "wof:placetype":"postalcode"
},
  "geometry": {"coordinates":[-2.48236275425207,53.75805121543051],"type":"Point"}
}