{
  "type": "Feature",
  "properties": {
    "date:inception_lower": "1980-01-01",
    "date:inception_upper": "1980-01-01",
    "iso:country": "GB",
    "wof:name": "BB5 4AH",
    "wof:placetype": "postalcode"
  },
  "geometry": {"coordinates":[-2.369318,53.756188],"type":"Point"}
}
