{
  "type": "Feature",
  "properties": {
    "iso:country":"GB",
    "wof:name":"BB5 4AH",
    "wof:placetype":"postalcode"
},
  "geometry": {"coordinates":[-2.36931820900426,53.75618803062231],"type":"Point"}
}