{
  "type": "Feature",
  "properties": {
    "date:inception_lower":"2014-03-01",
    "date:inception_upper":"2014-03-31",
    "iso:country":"GB",
    "wof:name":"E10 5RY",
    "wof:placetype":"postalcode"
},
  "geometry": {"coordinates":[-0.014023,51.563134],"type":"Point"}
}