{
  "type": "Feature",
  "properties": {
    "iso:country":"GB",
    "wof:name":"N4 2HG",
    "wof:placetype":"postalcode"
},
  "geometry": {"coordinates":[-0.10114339236397,51.56650107761099],"type":"Point"}
}