{
  "type": "Feature",
  "properties": {
    "iso:country": "GB",
    "wof:name": "N4 2HG",
    "wof:placetype": "postalcode"
  },
  "geometry": {"coordinates":[-0.101143,51.566501],"type":"Point"}
}
