{
  "type": "Feature",
  "properties": {
    "iso:country": "GB",
    "wof:name": "CH45 8QN",
    "wof:placetype": "postalcode"
  },
  "geometry": {"coordinates":[-3.08362,53.419373],"type":"Point"}
}
