{
  "type": "Feature",
  "properties": {
    "iso:country":"GB",
    "wof:name":"CH45 8QN",
    "wof:placetype":"postalcode"
},
  "geometry": {"coordinates":[-3.08361978879489,53.41937252641098],"type":"Point"}
}