{
  "type": "Feature",
  "properties": {
    "date:inception_lower": "1983-07-01",
    "date:inception_upper": "1983-07-01",
    "iso:country": "GB",
    "wof:name": "SE25 4RP",
    "wof:placetype": "postalcode"
  },
  "geometry": {"coordinates":[-0.064929,51.38986],"type":"Point"}
}
