{
  "type": "Feature",
  "properties": {
    "date:inception_lower": "1994-12-01",
    "date:inception_upper": "1994-12-01",
    "iso:country": "GB",
    "wof:name": "SO15 7QR",
    "wof:placetype": "postalcode"
  },
  "geometry": {"coordinates":[-1.41944,50.926316],"type":"Point"}
}
