{
  "type": "Feature",
  "properties": {
    "iso:country":"GB",
    "wof:name":"SK11 7LE",
    "wof:placetype":"postalcode"
},
  "geometry": {"coordinates":[-2.1148937090424,53.25464622610957],"type":"Point"}
}