{
  "type": "Feature",
  "properties": {
    "iso:country":"GB",
    "wof:name":"CF62 8NU",
    "wof:placetype":"postalcode"
},
  "geometry": {"coordinates":[-3.29275574040219,51.41443685329003],"type":"Point"}
}