{
  "type": "Feature",
  "properties": {
    "iso:country":"GB",
    "wof:name":"E16 2JF",
    "wof:placetype":"postalcode"
},
  "geometry": {"coordinates":[0.06240289944964,51.50125886150367],"type":"Point"}
}