{
  "type": "Feature",
  "properties": {
    "iso:country": "GB",
    "wof:name": "CF31 3HR",
    "wof:placetype": "postalcode"
  },
  "geometry": {"coordinates":[-3.576116,51.500432],"type":"Point"}
}
