{
  "type": "Feature",
  "properties": {
    "iso:country":"GB",
    "wof:name":"WS5 3LT",
    "wof:placetype":"postalcode"
},
  "geometry": {"coordinates":[-1.94178266832203,52.56855242637966],"type":"Point"}
}