{
  "type": "Feature",
  "properties": {
    "iso:country": "GB",
    "wof:name": "GL14 3AH",
    "wof:placetype": "postalcode"
  },
  "geometry": {"coordinates":[-2.50748,51.805156],"type":"Point"}
}
