{
  "type": "Feature",
  "properties": {
    "iso:country":"GB",
    "wof:name":"PA14 5TG",
    "wof:placetype":"postalcode"
},
  "geometry": {"coordinates":[-4.6691279202929,55.92778890690063],"type":"Point"}
}