{
  "type": "Feature",
  "properties": {
    "iso:country": "GB",
    "wof:name": "PA14 5TG",
    "wof:placetype": "postalcode"
  },
  "geometry": {"coordinates":[-4.669128,55.927789],"type":"Point"}
}
