{
  "type": "Feature",
  "properties": {
    "iso:country":"GB",
    "wof:name":"EH41 3EP",
    "wof:placetype":"postalcode"
},
  "geometry": {"coordinates":[-2.77661823106554,55.95553869730946],"type":"Point"}
}