{
  "type": "Feature",
  "properties": {
    "iso:country":"GB",
    "wof:name":"SO23 7QN",
    "wof:placetype":"postalcode"
},
  "geometry": {"coordinates":[-1.29707013419253,51.08855758599959],"type":"Point"}
}