{
  "type": "Feature",
  "properties": {
    "iso:country": "GB",
    "wof:name": "TF2 6FF",
    "wof:placetype": "postalcode"
  },
  "geometry": {"coordinates":[-2.451065,52.694765],"type":"Point"}
}
