{
  "type": "Feature",
  "properties": {
    "date:inception_lower": "2019-04-01",
    "date:inception_upper": "2019-04-01",
    "iso:country": "GB",
    "wof:name": "TF2 6FF",
    "wof:placetype": "postalcode"
  },
  "geometry": {"coordinates":[-2.451065,52.694765],"type":"Point"}
}
