{
  "type": "Feature",
  "properties": {
    "date:inception_lower": "1980-01-01",
    "date:inception_upper": "1980-01-01",
    "iso:country": "GB",
    "wof:name": "NE65 0NP",
    "wof:placetype": "postalcode"
  },
  "geometry": {"coordinates":[-1.590689,55.33089],"type":"Point"}
}
