{
  "type": "Feature",
  "properties": {
    "iso:country":"GB",
    "wof:name":"LS28 5GW",
    "wof:placetype":"postalcode"
},
  "geometry": {"coordinates":[-1.66287498323624,53.81395158084762],"type":"Point"}
}