{
  "type": "Feature",
  "properties": {
    "date:inception_lower": "1980-01-01",
    "date:inception_upper": "1980-01-01",
    "iso:country": "GB",
    "wof:name": "CV22 6HR",
    "wof:placetype": "postalcode"
  },
  "geometry": {"coordinates":[-1.270471,52.358341],"type":"Point"}
}
