{
  "type": "Feature",
  "properties": {
    "iso:country":"GB",
    "wof:name":"CF5 1RF",
    "wof:placetype":"postalcode"
},
  "geometry": {"coordinates":[-3.21014527759836,51.48364925819661],"type":"Point"}
}