{
  "type": "Feature",
  "properties": {
    "iso:country": "GB",
    "wof:name": "HG4 1ES",
    "wof:placetype": "postalcode"
  },
  "geometry": {"coordinates":[-1.523517,54.141147],"type":"Point"}
}
