{
  "type": "Feature",
  "properties": {
    "iso:country": "GB",
    "wof:name": "AB24 3AB",
    "wof:placetype": "postalcode"
  },
  "geometry": {"coordinates":[-2.101639,57.15777],"type":"Point"}
}
