{
  "type": "Feature",
  "properties": {
    "iso:country":"GB",
    "wof:name":"BS5 6RH",
    "wof:placetype":"postalcode"
},
  "geometry": {"coordinates":[-2.54586435328584,51.47383282347646],"type":"Point"}
}