{
  "type": "Feature",
  "properties": {
    "iso:country":"GB",
    "wof:name":"DN1 1AF",
    "wof:placetype":"postalcode"
},
  "geometry": {"coordinates":[-1.13611862324503,53.52590525230375],"type":"Point"}
}