{
  "type": "Feature",
  "properties": {
    "iso:country": "GB",
    "wof:name": "EH5 3PL",
    "wof:placetype": "postalcode"
  },
  "geometry": {"coordinates":[-3.210071,55.9739],"type":"Point"}
}
