{
  "type": "Feature",
  "properties": {
    "iso:country": "GB",
    "wof:name": "BN5 9EX",
    "wof:placetype": "postalcode"
  },
  "geometry": {"coordinates":[-0.276404,50.92735],"type":"Point"}
}
