{
  "type": "Feature",
  "properties": {
    "iso:country":"GB",
    "wof:name":"BN5 9EX",
    "wof:placetype":"postalcode"
},
  "geometry": {"coordinates":[-0.27640433894232,50.92735021156508],"type":"Point"}
}