{
  "type": "Feature",
  "properties": {
    "iso:country":"GB",
    "wof:name":"NG2 4HE",
    "wof:placetype":"postalcode"
},
  "geometry": {"coordinates":[-1.12664216666859,52.95176575039115],"type":"Point"}
}