{
  "type": "Feature",
  "properties": {
    "iso:country":"GB",
    "wof:name":"BB1 7DT",
    "wof:placetype":"postalcode"
},
  "geometry": {"coordinates":[-2.48510942116602,53.75027439208218],"type":"Point"}
}