{
  "type": "Feature",
  "properties": {
    "iso:country": "GB",
    "wof:name": "RH16 2PX",
    "wof:placetype": "postalcode"
  },
  "geometry": {"coordinates":[-0.081451,51.014512],"type":"Point"}
}
