{
  "type": "Feature",
  "properties": {
    "date:inception_lower": "1996-06-01",
    "date:inception_upper": "1996-06-01",
    "iso:country": "GB",
    "wof:name": "M29 8RN",
    "wof:placetype": "postalcode"
  },
  "geometry": {"coordinates":[-2.457266,53.513965],"type":"Point"}
}
