{
  "type": "Feature",
  "properties": {
    "iso:country":"GB",
    "wof:name":"M29 8RN",
    "wof:placetype":"postalcode"
},
  "geometry": {"coordinates":[-2.4572661713058,53.51396490128193],"type":"Point"}
}