{
  "type": "Feature",
  "properties": {
    "iso:country": "GB",
    "wof:name": "M29 8RN",
    "wof:placetype": "postalcode"
  },
  "geometry": {"coordinates":[-2.457266,53.513965],"type":"Point"}
}
