{
  "type": "Feature",
  "properties": {
    "iso:country":"GB",
    "wof:name":"SL3 7TA",
    "wof:placetype":"postalcode"
},
  "geometry": {"coordinates":[-0.56424048051521,51.50514576552943],"type":"Point"}
}