{
  "type": "Feature",
  "properties": {
    "iso:country":"GB",
    "wof:name":"SW16 6BH",
    "wof:placetype":"postalcode"
},
  "geometry": {"coordinates":[-0.13977666104496,51.42053260536451],"type":"Point"}
}