{
  "type": "Feature",
  "properties": {
    "date:inception_lower": "1980-01-01",
    "date:inception_upper": "1980-01-01",
    "iso:country": "GB",
    "wof:name": "NR35 1PD",
    "wof:placetype": "postalcode"
  },
  "geometry": {"coordinates":[1.43057,52.443352],"type":"Point"}
}
