{
  "type": "Feature",
  "properties": {
    "iso:country": "GB",
    "wof:name": "BN22 0JW",
    "wof:placetype": "postalcode"
  },
  "geometry": {"coordinates":[0.257829,50.802602],"type":"Point"}
}
