{
  "type": "Feature",
  "properties": {
    "date:inception_lower": "1987-04-01",
    "date:inception_upper": "1987-04-01",
    "iso:country": "GB",
    "wof:name": "BN22 0JW",
    "wof:placetype": "postalcode"
  },
  "geometry": {"coordinates":[0.257829,50.802602],"type":"Point"}
}
