{
  "type": "Feature",
  "properties": {
    "iso:country":"GB",
    "wof:name":"BN22 0JW",
    "wof:placetype":"postalcode"
},
  "geometry": {"coordinates":[0.25777183725869,50.80259822242074],"type":"Point"}
}