{
  "type": "Feature",
  "properties": {
    "iso:country": "GB",
    "wof:name": "TW15 1JE",
    "wof:placetype": "postalcode"
  },
  "geometry": {"coordinates":[-0.444905,51.425131],"type":"Point"}
}
