{
  "type": "Feature",
  "properties": {
    "date:inception_lower":"1982-03-01",
    "date:inception_upper":"1982-03-31",
    "iso:country":"GB",
    "wof:name":"E17 8NT",
    "wof:placetype":"postalcode"
},
  "geometry": {"coordinates":[-0.024933,51.576403],"type":"Point"}
}