{
  "type": "Feature",
  "properties": {
    "iso:country":"GB",
    "wof:name":"E17 8NT",
    "wof:placetype":"postalcode"
},
  "geometry": {"coordinates":[-0.02493299292908,51.57640277224595],"type":"Point"}
}