{
  "type": "Feature",
  "properties": {
    "iso:country":"GB",
    "wof:name":"LA9 4HA",
    "wof:placetype":"postalcode"
},
  "geometry": {"coordinates":[-2.74841830429283,54.32565916751493],"type":"Point"}
}