{
  "type": "Feature",
  "properties": {
    "iso:country":"GB",
    "wof:name":"CM1 4QW",
    "wof:placetype":"postalcode"
},
  "geometry": {"coordinates":[0.34922381430609,51.80755927550337],"type":"Point"}
}