{
  "type": "Feature",
  "properties": {
    "iso:country":"GB",
    "wof:name":"HP14 4ES",
    "wof:placetype":"postalcode"
},
  "geometry": {"coordinates":[-0.79739467853058,51.64702356344549],"type":"Point"}
}