{
  "type": "Feature",
  "properties": {
    "date:inception_lower":"1980-01-01",
    "date:inception_upper":"1980-01-31",
    "iso:country":"GB",
    "wof:name":"HP14 4ES",
    "wof:placetype":"postalcode"
},
  "geometry": {"coordinates":[-0.797395,51.647024],"type":"Point"}
}