{
  "type": "Feature",
  "properties": {
    "iso:country":"GB",
    "wof:name":"OX33 1TA",
    "wof:placetype":"postalcode"
},
  "geometry": {"coordinates":[-1.14542946067134,51.74226896246213],"type":"Point"}
}