{
  "type": "Feature",
  "properties": {
    "iso:country": "GB",
    "wof:name": "EH17 7QW",
    "wof:placetype": "postalcode"
  },
  "geometry": {"coordinates":[-3.151214,55.910727],"type":"Point"}
}
