{
  "type": "Feature",
  "properties": {
    "date:inception_lower": "1980-01-01",
    "date:inception_upper": "1980-01-01",
    "iso:country": "GB",
    "wof:name": "NW2 5UG",
    "wof:placetype": "postalcode"
  },
  "geometry": {"coordinates":[-0.227922,51.549351],"type":"Point"}
}
