{
  "type": "Feature",
  "properties": {
    "iso:country":"GB",
    "wof:name":"NW2 5UG",
    "wof:placetype":"postalcode"
},
  "geometry": {"coordinates":[-0.22794708675755,51.54934882083302],"type":"Point"}
}