{
  "type": "Feature",
  "properties": {
    "iso:country":"GB",
    "wof:name":"GL7 5QH",
    "wof:placetype":"postalcode"
},
  "geometry": {"coordinates":[-1.8907282006842,51.66109406888638],"type":"Point"}
}