{
  "type": "Feature",
  "properties": {
    "iso:country": "GB",
    "wof:name": "GL7 5QH",
    "wof:placetype": "postalcode"
  },
  "geometry": {"coordinates":[-1.890728,51.661094],"type":"Point"}
}
