{
  "type": "Feature",
  "properties": {
    "date:inception_lower": "1980-01-01",
    "date:inception_upper": "1980-01-01",
    "iso:country": "GB",
    "wof:name": "GL7 5QH",
    "wof:placetype": "postalcode"
  },
  "geometry": {"coordinates":[-1.890728,51.661094],"type":"Point"}
}
