{
  "type": "Feature",
  "properties": {
    "iso:country": "GB",
    "wof:name": "AL7 1DP",
    "wof:placetype": "postalcode"
  },
  "geometry": {"coordinates":[-0.191349,51.8163],"type":"Point"}
}
