{
  "type": "Feature",
  "properties": {
    "date:inception_lower": "1980-01-01",
    "date:inception_upper": "1980-01-01",
    "iso:country": "GB",
    "wof:name": "AL7 1DP",
    "wof:placetype": "postalcode"
  },
  "geometry": {"coordinates":[-0.191349,51.8163],"type":"Point"}
}
