{
  "type": "Feature",
  "properties": {
    "iso:country":"GB",
    "wof:name":"AL7 1DP",
    "wof:placetype":"postalcode"
},
  "geometry": {"coordinates":[-0.19134949658907,51.8162997302847],"type":"Point"}
}