{
  "type": "Feature",
  "properties": {
    "iso:country":"GB",
    "wof:name":"BN12 4RE",
    "wof:placetype":"postalcode"
},
  "geometry": {"coordinates":[-0.42293562296121,50.81679137994401],"type":"Point"}
}