{
  "type": "Feature",
  "properties": {
    "date:inception_lower": "1980-01-01",
    "date:inception_upper": "1980-01-01",
    "iso:country": "GB",
    "wof:name": "B31 1HZ",
    "wof:placetype": "postalcode"
  },
  "geometry": {"coordinates":[-1.986853,52.425698],"type":"Point"}
}
