{
  "type": "Feature",
  "properties": {
    "iso:country":"GB",
    "wof:name":"B31 1HZ",
    "wof:placetype":"postalcode"
},
  "geometry": {"coordinates":[-1.98685289700415,52.42569791247904],"type":"Point"}
}