{
  "type": "Feature",
  "properties": {
    "iso:country": "GB",
    "wof:name": "B31 1HZ",
    "wof:placetype": "postalcode"
  },
  "geometry": {"coordinates":[-1.986853,52.425698],"type":"Point"}
}
