{
  "type": "Feature",
  "properties": {
    "iso:country":"GB",
    "wof:name":"RG4 5HH",
    "wof:placetype":"postalcode"
},
  "geometry": {"coordinates":[-0.96379303778713,51.47319928299937],"type":"Point"}
}