{
  "type": "Feature",
  "properties": {
    "iso:country": "GB",
    "wof:name": "PO19 6AZ",
    "wof:placetype": "postalcode"
  },
  "geometry": {"coordinates":[-0.772963,50.851933],"type":"Point"}
}
