{
  "type": "Feature",
  "properties": {
    "iso:country":"GB",
    "wof:name":"PO19 6AZ",
    "wof:placetype":"postalcode"
},
  "geometry": {"coordinates":[-0.77296310985493,50.85193289254273],"type":"Point"}
}