{
  "type": "Feature",
  "properties": {
    "iso:country": "GB",
    "wof:name": "WR5 1NU",
    "wof:placetype": "postalcode"
  },
  "geometry": {"coordinates":[-2.19343,52.191815],"type":"Point"}
}
