{
  "type": "Feature",
  "properties": {
    "iso:country":"GB",
    "wof:name":"WR5 1NU",
    "wof:placetype":"postalcode"
},
  "geometry": {"coordinates":[-2.19341936407102,52.19178495253422],"type":"Point"}
}