{
  "type": "Feature",
  "properties": {
    "iso:country":"GB",
    "wof:name":"CA8 9AR",
    "wof:placetype":"postalcode"
},
  "geometry": {"coordinates":[-2.80698882233098,54.90478264851247],"type":"Point"}
}