{
  "type": "Feature",
  "properties": {
    "iso:country": "GB",
    "wof:name": "KA18 3RB",
    "wof:placetype": "postalcode"
  },
  "geometry": {"coordinates":[-4.066967,55.521455],"type":"Point"}
}
