{
  "type": "Feature",
  "properties": {
    "date:inception_lower":"2006-07-01",
    "date:inception_upper":"2006-07-31",
    "iso:country":"GB",
    "wof:name":"IG9 6DF",
    "wof:placetype":"postalcode"
},
  "geometry": {"coordinates":[0.047696,51.624662],"type":"Point"}
}