{
  "type": "Feature",
  "properties": {
    "iso:country":"GB",
    "wof:name":"RH13 0NN",
    "wof:placetype":"postalcode"
},
  "geometry": {"coordinates":[-0.38302415792978,51.03901267779506],"type":"Point"}
}