{
  "type": "Feature",
  "properties": {
    "iso:country": "GB",
    "wof:name": "RH13 0NN",
    "wof:placetype": "postalcode"
  },
  "geometry": {"coordinates":[-0.383024,51.039013],"type":"Point"}
}
