{
  "type": "Feature",
  "properties": {
    "iso:country":"GB",
    "wof:name":"CB4 1NU",
    "wof:placetype":"postalcode"
},
  "geometry": {"coordinates":[0.14434794515562,52.21776917029996],"type":"Point"}
}