{
  "type": "Feature",
  "properties": {
    "date:inception_lower": "1980-01-01",
    "date:inception_upper": "1980-01-01",
    "iso:country": "GB",
    "wof:name": "CB4 1NU",
    "wof:placetype": "postalcode"
  },
  "geometry": {"coordinates":[0.144348,52.217769],"type":"Point"}
}
