{
  "type": "Feature",
  "properties": {
    "iso:country":"GB",
    "wof:name":"KA13 7EF",
    "wof:placetype":"postalcode"
},
  "geometry": {"coordinates":[-4.6962846988687,55.66084568157928],"type":"Point"}
}