{
  "type": "Feature",
  "properties": {
    "iso:country": "GB",
    "wof:name": "SA47 0PY",
    "wof:placetype": "postalcode"
  },
  "geometry": {"coordinates":[-4.299932,52.209136],"type":"Point"}
}
