{
  "type": "Feature",
  "properties": {
    "iso:country":"GB",
    "wof:name":"SA47 0PY",
    "wof:placetype":"postalcode"
},
  "geometry": {"coordinates":[-4.29993237538753,52.20913646552611],"type":"Point"}
}