{
  "type": "Feature",
  "properties": {
    "iso:country":"GB",
    "wof:name":"SE19 3HB",
    "wof:placetype":"postalcode"
},
  "geometry": {"coordinates":[-0.10627343989284,51.42240607779798],"type":"Point"}
}