{
  "type": "Feature",
  "properties": {
    "iso:country": "GB",
    "wof:name": "TN2 4QN",
    "wof:placetype": "postalcode"
  },
  "geometry": {"coordinates":[0.309225,51.14553],"type":"Point"}
}
