{
  "type": "Feature",
  "properties": {
    "iso:country":"GB",
    "wof:name":"TN2 4QN",
    "wof:placetype":"postalcode"
},
  "geometry": {"coordinates":[0.30919763863952,51.14553159347319],"type":"Point"}
}