{
  "type": "Feature",
  "properties": {
    "iso:country": "GB",
    "wof:name": "G41 1HA",
    "wof:placetype": "postalcode"
  },
  "geometry": {"coordinates":[-4.274207,55.845411],"type":"Point"}
}
