{
  "type": "Feature",
  "properties": {
    "iso:country":"GB",
    "wof:name":"BN43 5JP",
    "wof:placetype":"postalcode"
},
  "geometry": {"coordinates":[-0.26540959956848,50.83035695314366],"type":"Point"}
}