{
  "type": "Feature",
  "properties": {
    "iso:country":"GB",
    "wof:name":"OX1 5JX",
    "wof:placetype":"postalcode"
},
  "geometry": {"coordinates":[-1.32211608707256,51.71876643549035],"type":"Point"}
}