{
  "type": "Feature",
  "properties": {
    "iso:country": "GB",
    "wof:name": "OX1 5JX",
    "wof:placetype": "postalcode"
  },
  "geometry": {"coordinates":[-1.322153,51.719014],"type":"Point"}
}
