{
  "type": "Feature",
  "properties": {
    "date:inception_lower": "1980-01-01",
    "date:inception_upper": "1980-01-01",
    "iso:country": "GB",
    "wof:name": "OX1 5JX",
    "wof:placetype": "postalcode"
  },
  "geometry": {"coordinates":[-1.322153,51.719014],"type":"Point"}
}
