{
  "type": "Feature",
  "properties": {
    "date:inception_lower": "1980-01-01",
    "date:inception_upper": "1980-01-01",
    "iso:country": "GB",
    "wof:name": "SG7 6NA",
    "wof:placetype": "postalcode"
  },
  "geometry": {"coordinates":[-0.186506,51.978017],"type":"Point"}
}
