{
  "type": "Feature",
  "properties": {
    "iso:country":"GB",
    "wof:name":"CO14 8EQ",
    "wof:placetype":"postalcode"
},
  "geometry": {"coordinates":[1.2694003095472,51.84680282264951],"type":"Point"}
}