{
  "type": "Feature",
  "properties": {
    "iso:country": "GB",
    "wof:name": "CO14 8EQ",
    "wof:placetype": "postalcode"
  },
  "geometry": {"coordinates":[1.2694,51.846803],"type":"Point"}
}
