{
  "type": "Feature",
  "properties": {
    "iso:country": "GB",
    "wof:name": "DE22 4JZ",
    "wof:placetype": "postalcode"
  },
  "geometry": {"coordinates":[-1.527073,52.925411],"type":"Point"}
}
