{
  "type": "Feature",
  "properties": {
    "iso:country":"GB",
    "wof:name":"KY6 1AZ",
    "wof:placetype":"postalcode"
},
  "geometry": {"coordinates":[-3.19185113360601,56.19554352942066],"type":"Point"}
}