{
  "type": "Feature",
  "properties": {
    "iso:country":"GB",
    "wof:name":"PR9 9EZ",
    "wof:placetype":"postalcode"
},
  "geometry": {"coordinates":[-2.99327825263439,53.65342520408036],"type":"Point"}
}