{
  "type": "Feature",
  "properties": {
    "iso:country":"GB",
    "wof:name":"BN9 9HJ",
    "wof:placetype":"postalcode"
},
  "geometry": {"coordinates":[0.04256937014996,50.78991829477157],"type":"Point"}
}