{
  "type": "Feature",
  "properties": {
    "date:inception_lower": "1980-01-01",
    "date:inception_upper": "1980-01-01",
    "iso:country": "GB",
    "wof:name": "BN9 9HJ",
    "wof:placetype": "postalcode"
  },
  "geometry": {"coordinates":[0.042569,50.789918],"type":"Point"}
}
