{
  "type": "Feature",
  "properties": {
    "iso:country": "GB",
    "wof:name": "BN9 9HJ",
    "wof:placetype": "postalcode"
  },
  "geometry": {"coordinates":[0.042569,50.789918],"type":"Point"}
}
