{
  "type": "Feature",
  "properties": {
    "date:inception_lower": "1980-01-01",
    "date:inception_upper": "1980-01-01",
    "iso:country": "GB",
    "wof:name": "RG14 6HB",
    "wof:placetype": "postalcode"
  },
  "geometry": {"coordinates":[-1.343321,51.386219],"type":"Point"}
}
