{
  "type": "Feature",
  "properties": {
    "iso:country":"GB",
    "wof:name":"RG14 6HB",
    "wof:placetype":"postalcode"
},
  "geometry": {"coordinates":[-1.34332106043123,51.38621869762442],"type":"Point"}
}