{
  "type": "Feature",
  "properties": {
    "iso:country":"GB",
    "wof:name":"B31 3UJ",
    "wof:placetype":"postalcode"
},
  "geometry": {"coordinates":[-1.95895569545528,52.4096713069866],"type":"Point"}
}