{
  "type": "Feature",
  "properties": {
    "iso:country":"GB",
    "wof:name":"TN26 1EB",
    "wof:placetype":"postalcode"
},
  "geometry": {"coordinates":[0.81923421123222,51.17119343769117],"type":"Point"}
}