{
  "type": "Feature",
  "properties": {
    "iso:country":"GB",
    "wof:name":"N8 0SA",
    "wof:placetype":"postalcode"
},
  "geometry": {"coordinates":[-0.10015528274804,51.58639440375126],"type":"Point"}
}