{
  "type": "Feature",
  "properties": {
    "iso:country":"GB",
    "wof:name":"SK17 0SR",
    "wof:placetype":"postalcode"
},
  "geometry": {"coordinates":[-1.97659605782234,53.19293737928221],"type":"Point"}
}