{
  "type": "Feature",
  "properties": {
    "iso:country":"GB",
    "wof:name":"N2 0PE",
    "wof:placetype":"postalcode"
},
  "geometry": {"coordinates":[-0.15804666839937,51.58195782658678],"type":"Point"}
}