{
  "type": "Feature",
  "properties": {
    "iso:country": "GB",
    "wof:name": "N2 0PE",
    "wof:placetype": "postalcode"
  },
  "geometry": {"coordinates":[-0.157962,51.581912],"type":"Point"}
}
