{
  "type": "Feature",
  "properties": {
    "date:inception_lower": "2010-08-01",
    "date:inception_upper": "2010-08-01",
    "iso:country": "GB",
    "wof:name": "TN11 8DY",
    "wof:placetype": "postalcode"
  },
  "geometry": {"coordinates":[0.193776,51.165543],"type":"Point"}
}
