{
  "type": "Feature",
  "properties": {
    "iso:country": "GB",
    "wof:name": "CF31 4TH",
    "wof:placetype": "postalcode"
  },
  "geometry": {"coordinates":[-3.600711,51.516087],"type":"Point"}
}
