{
  "type": "Feature",
  "properties": {
    "iso:country":"GB",
    "wof:name":"CF31 4TH",
    "wof:placetype":"postalcode"
},
  "geometry": {"coordinates":[-3.60071111238478,51.51608718033066],"type":"Point"}
}