{
  "type": "Feature",
  "properties": {
    "iso:country":"GB",
    "wof:name":"EN2 8JH",
    "wof:placetype":"postalcode"
},
  "geometry": {"coordinates":[-0.10617545231816,51.66478846188322],"type":"Point"}
}