{
  "type": "Feature",
  "properties": {
    "date:inception_lower": "2022-12-01",
    "date:inception_upper": "2022-12-01",
    "iso:country": "GB",
    "wof:name": "WA3 2SU",
    "wof:placetype": "postalcode"
  },
  "geometry": {"coordinates":[-2.578025,53.469414],"type":"Point"}
}
