{
  "type": "Feature",
  "properties": {
    "iso:country":"GB",
    "wof:name":"EC2A 4BY",
    "wof:placetype":"postalcode"
},
  "geometry": {"coordinates":[-0.08618169980856,51.52454167383096],"type":"Point"}
}