{
  "type": "Feature",
  "properties": {
    "date:inception_lower": "2012-05-01",
    "date:inception_upper": "2012-05-01",
    "iso:country": "GB",
    "wof:name": "EC2A 4BY",
    "wof:placetype": "postalcode"
  },
  "geometry": {"coordinates":[-0.086182,51.524542],"type":"Point"}
}
