{
  "type": "Feature",
  "properties": {
    "iso:country":"GB",
    "wof:name":"BB10 1PZ",
    "wof:placetype":"postalcode"
},
  "geometry": {"coordinates":[-2.24143339807122,53.80396176666181],"type":"Point"}
}