{
  "type": "Feature",
  "properties": {
    "iso:country":"GB",
    "wof:name":"BB3 1EP",
    "wof:placetype":"postalcode"
},
  "geometry": {"coordinates":[-2.47279487884298,53.70429529033561],"type":"Point"}
}