{
  "type": "Feature",
  "properties": {
    "date:inception_lower": "1980-01-01",
    "date:inception_upper": "1980-01-01",
    "iso:country": "GB",
    "wof:name": "BB3 1EP",
    "wof:placetype": "postalcode"
  },
  "geometry": {"coordinates":[-2.472795,53.704295],"type":"Point"}
}
