{
  "type": "Feature",
  "properties": {
    "iso:country": "GB",
    "wof:name": "BB3 1EP",
    "wof:placetype": "postalcode"
  },
  "geometry": {"coordinates":[-2.472795,53.704295],"type":"Point"}
}
