{
  "type": "Feature",
  "properties": {
    "iso:country":"GB",
    "wof:name":"NP19 4SW",
    "wof:placetype":"postalcode"
},
  "geometry": {"coordinates":[-2.93977099220459,51.57258332971801],"type":"Point"}
}