{
  "type": "Feature",
  "properties": {
    "iso:country":"GB",
    "wof:name":"SW17 7QY",
    "wof:placetype":"postalcode"
},
  "geometry": {"coordinates":[-0.15903535839037,51.44164557355587],"type":"Point"}
}