{
  "type": "Feature",
  "properties": {
    "date:inception_lower": "2023-07-01",
    "date:inception_upper": "2023-07-01",
    "iso:country": "GB",
    "wof:name": "GL54 5FY",
    "wof:placetype": "postalcode"
  },
  "geometry": {"coordinates":[-1.973303,51.976006],"type":"Point"}
}
