{
  "type": "Feature",
  "properties": {
    "iso:country":"GB",
    "wof:name":"RG45 7AN",
    "wof:placetype":"postalcode"
},
  "geometry": {"coordinates":[-0.79560617975842,51.36703349643835],"type":"Point"}
}