{
  "type": "Feature",
  "properties": {
    "iso:country":"GB",
    "wof:name":"DN40 3AJ",
    "wof:placetype":"postalcode"
},
  "geometry": {"coordinates":[-0.26858510876098,53.60901945948501],"type":"Point"}
}