{
  "type": "Feature",
  "properties": {
    "date:inception_lower": "1980-01-01",
    "date:inception_upper": "1980-01-01",
    "iso:country": "GB",
    "wof:name": "DN40 3AJ",
    "wof:placetype": "postalcode"
  },
  "geometry": {"coordinates":[-0.268585,53.609019],"type":"Point"}
}
