{
  "type": "Feature",
  "properties": {
    "iso:country":"GB",
    "wof:name":"B61 0NU",
    "wof:placetype":"postalcode"
},
  "geometry": {"coordinates":[-2.06060910571433,52.36569208848516],"type":"Point"}
}