{
  "type": "Feature",
  "properties": {
    "iso:country":"GB",
    "wof:name":"PE32 2LQ",
    "wof:placetype":"postalcode"
},
  "geometry": {"coordinates":[0.77129251944517,52.6982077917504],"type":"Point"}
}