{
  "type": "Feature",
  "properties": {
    "date:inception_lower":"1980-01-01",
    "date:inception_upper":"1980-01-31",
    "iso:country":"GB",
    "wof:name":"SA67 8PY",
    "wof:placetype":"postalcode"
},
  "geometry": {"coordinates":[-4.635377,51.757422],"type":"Point"}
}