{
  "type": "Feature",
  "properties": {
    "iso:country":"GB",
    "wof:name":"SA67 8PY",
    "wof:placetype":"postalcode"
},
  "geometry": {"coordinates":[-4.63537704162276,51.75742173827977],"type":"Point"}
}