{
  "type": "Feature",
  "properties": {
    "iso:country":"GB",
    "wof:name":"G84 9LA",
    "wof:placetype":"postalcode"
},
  "geometry": {"coordinates":[-4.73195668802732,56.00944672842648],"type":"Point"}
}