{
  "type": "Feature",
  "properties": {
    "date:inception_lower": "2020-07-01",
    "date:inception_upper": "2020-07-01",
    "iso:country": "GB",
    "wof:name": "BS49 4GA",
    "wof:placetype": "postalcode"
  },
  "geometry": {"coordinates":[-2.82501,51.386264],"type":"Point"}
}
