{
  "type": "Feature",
  "properties": {
    "iso:country":"GB",
    "wof:name":"CH7 1HA",
    "wof:placetype":"postalcode"
},
  "geometry": {"coordinates":[-3.13144616850051,53.16189106393404],"type":"Point"}
}