{
  "type": "Feature",
  "properties": {
    "date:inception_lower": "1996-12-01",
    "date:inception_upper": "1996-12-01",
    "iso:country": "GB",
    "wof:name": "CH7 1HA",
    "wof:placetype": "postalcode"
  },
  "geometry": {"coordinates":[-3.131686,53.161916],"type":"Point"}
}
