{
  "type": "Feature",
  "properties": {
    "date:inception_lower":"1980-01-01",
    "date:inception_upper":"1980-01-31",
    "iso:country":"GB",
    "wof:name":"SN10 5JF",
    "wof:placetype":"postalcode"
},
  "geometry": {"coordinates":[-1.999865,51.343036],"type":"Point"}
}