{
  "type": "Feature",
  "properties": {
    "iso:country": "GB",
    "wof:name": "IP1 3TE",
    "wof:placetype": "postalcode"
  },
  "geometry": {"coordinates":[1.15441,52.070335],"type":"Point"}
}
