{
  "type": "Feature",
  "properties": {
    "iso:country":"GB",
    "wof:name":"HD4 5RR",
    "wof:placetype":"postalcode"
},
  "geometry": {"coordinates":[-1.81202612932124,53.63839001422365],"type":"Point"}
}