{
  "type": "Feature",
  "properties": {
    "iso:country":"GB",
    "wof:name":"OX2 0DB",
    "wof:placetype":"postalcode"
},
  "geometry": {"coordinates":[-1.27803768294844,51.75146597072824],"type":"Point"}
}