{
  "type": "Feature",
  "properties": {
    "iso:country":"GB",
    "wof:name":"PO19 7UP",
    "wof:placetype":"postalcode"
},
  "geometry": {"coordinates":[-0.76965872579184,50.83497347503923],"type":"Point"}
}