{
  "type": "Feature",
  "properties": {
    "date:inception_lower":"2002-06-01",
    "date:inception_upper":"2002-06-30",
    "iso:country":"GB",
    "wof:name":"PO19 7UP",
    "wof:placetype":"postalcode"
},
  "geometry": {"coordinates":[-0.769659,50.834973],"type":"Point"}
}