{
  "type": "Feature",
  "properties": {
    "iso:country": "GB",
    "wof:name": "PO19 7UP",
    "wof:placetype": "postalcode"
  },
  "geometry": {"coordinates":[-0.769659,50.834973],"type":"Point"}
}
