{
  "type": "Feature",
  "properties": {
    "iso:country":"GB",
    "wof:name":"W1F 0EN",
    "wof:placetype":"postalcode"
},
  "geometry": {"coordinates":[-0.1328172120471,51.51324334223759],"type":"Point"}
}