{
  "type": "Feature",
  "properties": {
    "iso:country":"GB",
    "wof:name":"OX11 7DR",
    "wof:placetype":"postalcode"
},
  "geometry": {"coordinates":[-1.23435627756764,51.61280350875921],"type":"Point"}
}