{
  "type": "Feature",
  "properties": {
    "date:inception_lower": "1980-01-01",
    "date:inception_upper": "1980-01-01",
    "iso:country": "GB",
    "wof:name": "CA14 4NR",
    "wof:placetype": "postalcode"
  },
  "geometry": {"coordinates":[-3.540004,54.61416],"type":"Point"}
}
