{
  "type": "Feature",
  "properties": {
    "date:inception_lower": "1981-03-01",
    "date:inception_upper": "1981-03-01",
    "iso:country": "GB",
    "wof:name": "G64 1YG",
    "wof:placetype": "postalcode"
  },
  "geometry": {"coordinates":[-4.197625,55.905355],"type":"Point"}
}
