{
  "type": "Feature",
  "properties": {
    "iso:country": "GB",
    "wof:name": "SE24 9AY",
    "wof:placetype": "postalcode"
  },
  "geometry": {"coordinates":[-0.106218,51.441847],"type":"Point"}
}
