{
  "type": "Feature",
  "properties": {
    "date:inception_lower": "1980-01-01",
    "date:inception_upper": "1980-01-01",
    "iso:country": "GB",
    "wof:name": "NR27 0AS",
    "wof:placetype": "postalcode"
  },
  "geometry": {"coordinates":[1.307477,52.927816],"type":"Point"}
}
