{
  "type": "Feature",
  "properties": {
    "iso:country":"GB",
    "wof:name":"NR27 0AS",
    "wof:placetype":"postalcode"
},
  "geometry": {"coordinates":[1.30748628593249,52.92776860758229],"type":"Point"}
}