{
  "type": "Feature",
  "properties": {
    "iso:country": "GB",
    "wof:name": "NR27 0AS",
    "wof:placetype": "postalcode"
  },
  "geometry": {"coordinates":[1.307477,52.927816],"type":"Point"}
}
