{
  "type": "Feature",
  "properties": {
    "iso:country":"GB",
    "wof:name":"PL12 4LR",
    "wof:placetype":"postalcode"
},
  "geometry": {"coordinates":[-4.23396359879797,50.41385079742225],"type":"Point"}
}