{
  "type": "Feature",
  "properties": {
    "date:inception_lower": "1980-01-01",
    "date:inception_upper": "1980-01-01",
    "iso:country": "GB",
    "wof:name": "PL12 4LR",
    "wof:placetype": "postalcode"
  },
  "geometry": {"coordinates":[-4.233964,50.413851],"type":"Point"}
}
