{
  "type": "Feature",
  "properties": {
    "iso:country": "GB",
    "wof:name": "CB24 1BB",
    "wof:placetype": "postalcode"
  },
  "geometry": {"coordinates":[0.053334,52.288892],"type":"Point"}
}
