{
  "type": "Feature",
  "properties": {
    "iso:country":"GB",
    "wof:name":"CV7 9HJ",
    "wof:placetype":"postalcode"
},
  "geometry": {"coordinates":[-1.50480313729394,52.46116269397754],"type":"Point"}
}