{
  "type": "Feature",
  "properties": {
    "iso:country": "GB",
    "wof:name": "CV7 9HJ",
    "wof:placetype": "postalcode"
  },
  "geometry": {"coordinates":[-1.504803,52.461163],"type":"Point"}
}
