{
  "type": "Feature",
  "properties": {
    "date:inception_lower": "2006-07-01",
    "date:inception_upper": "2006-07-01",
    "iso:country": "GB",
    "wof:name": "CV21 1EF",
    "wof:placetype": "postalcode"
  },
  "geometry": {"coordinates":[-1.280923,52.38998],"type":"Point"}
}
