{
  "type": "Feature",
  "properties": {
    "iso:country":"GB",
    "wof:name":"CV21 1EF",
    "wof:placetype":"postalcode"
},
  "geometry": {"coordinates":[-1.28092326564332,52.38998027545691],"type":"Point"}
}