{
  "type": "Feature",
  "properties": {
    "date:inception_lower": "1980-01-01",
    "date:inception_upper": "1980-01-01",
    "iso:country": "GB",
    "wof:name": "BR7 5HS",
    "wof:placetype": "postalcode"
  },
  "geometry": {"coordinates":[0.059539,51.411165],"type":"Point"}
}
