{
  "type": "Feature",
  "properties": {
    "iso:country":"GB",
    "wof:name":"BR7 5HS",
    "wof:placetype":"postalcode"
},
  "geometry": {"coordinates":[0.05953927100751,51.41116511430052],"type":"Point"}
}