{
  "type": "Feature",
  "properties": {
    "iso:country": "GB",
    "wof:name": "EX16 6XA",
    "wof:placetype": "postalcode"
  },
  "geometry": {"coordinates":[-3.473646,50.913787],"type":"Point"}
}
