{
  "type": "Feature",
  "properties": {
    "date:inception_lower": "2003-09-01",
    "date:inception_upper": "2003-09-01",
    "iso:country": "GB",
    "wof:name": "EX16 6XA",
    "wof:placetype": "postalcode"
  },
  "geometry": {"coordinates":[-3.473647,50.913771],"type":"Point"}
}
