{
  "type": "Feature",
  "properties": {
    "iso:country":"GB",
    "wof:name":"KY5 8JG",
    "wof:placetype":"postalcode"
},
  "geometry": {"coordinates":[-3.32223927857453,56.16153814856066],"type":"Point"}
}