{
  "type": "Feature",
  "properties": {
    "iso:country": "GB",
    "wof:name": "KY5 8JG",
    "wof:placetype": "postalcode"
  },
  "geometry": {"coordinates":[-3.322239,56.161538],"type":"Point"}
}
