{
  "type": "Feature",
  "properties": {
    "iso:country": "GB",
    "wof:name": "S64 8JB",
    "wof:placetype": "postalcode"
  },
  "geometry": {"coordinates":[-1.317555,53.482872],"type":"Point"}
}
