{
  "type": "Feature",
  "properties": {
    "iso:country":"GB",
    "wof:name":"S64 8JB",
    "wof:placetype":"postalcode"
},
  "geometry": {"coordinates":[-1.31755497259166,53.48287220480219],"type":"Point"}
}