{
  "type": "Feature",
  "properties": {
    "iso:country": "GB",
    "wof:name": "GL51 8NA",
    "wof:placetype": "postalcode"
  },
  "geometry": {"coordinates":[-2.10159,51.907545],"type":"Point"}
}
