{
  "type": "Feature",
  "properties": {
    "iso:country":"GB",
    "wof:name":"ML9 3RP",
    "wof:placetype":"postalcode"
},
  "geometry": {"coordinates":[-4.00157622999499,55.6879429105275],"type":"Point"}
}