{
  "type": "Feature",
  "properties": {
    "date:inception_lower": "1991-01-01",
    "date:inception_upper": "1991-01-01",
    "iso:country": "GB",
    "wof:name": "SA73 1AS",
    "wof:placetype": "postalcode"
  },
  "geometry": {"coordinates":[-5.017655,51.725808],"type":"Point"}
}
