{
  "type": "Feature",
  "properties": {
    "iso:country": "GB",
    "wof:name": "TW16 5JS",
    "wof:placetype": "postalcode"
  },
  "geometry": {"coordinates":[-0.40023,51.411509],"type":"Point"}
}
