{
  "type": "Feature",
  "properties": {
    "iso:country":"GB",
    "wof:name":"TW16 5JS",
    "wof:placetype":"postalcode"
},
  "geometry": {"coordinates":[-0.40022999622706,51.41150881856439],"type":"Point"}
}