{
  "type": "Feature",
  "properties": {
    "date:inception_lower": "1980-01-01",
    "date:inception_upper": "1980-01-01",
    "iso:country": "GB",
    "wof:name": "ME13 7QF",
    "wof:placetype": "postalcode"
  },
  "geometry": {"coordinates":[0.879852,51.319741],"type":"Point"}
}
