{
  "type": "Feature",
  "properties": {
    "iso:country":"GB",
    "wof:name":"NP4 6BP",
    "wof:placetype":"postalcode"
},
  "geometry": {"coordinates":[-3.06051268509679,51.70118605863077],"type":"Point"}
}