{
  "type": "Feature",
  "properties": {
    "date:inception_lower": "1994-12-01",
    "date:inception_upper": "1994-12-01",
    "iso:country": "GB",
    "wof:name": "SO31 4HR",
    "wof:placetype": "postalcode"
  },
  "geometry": {"coordinates":[-1.314409,50.869785],"type":"Point"}
}
