{
  "type": "Feature",
  "properties": {
    "iso:country":"GB",
    "wof:name":"SO31 4HR",
    "wof:placetype":"postalcode"
},
  "geometry": {"coordinates":[-1.3135798367194,50.86889031535546],"type":"Point"}
}