{
  "type": "Feature",
  "properties": {
    "iso:country":"GB",
    "wof:name":"B74 3DU",
    "wof:placetype":"postalcode"
},
  "geometry": {"coordinates":[-1.87912853111598,52.58823782660792],"type":"Point"}
}