{
  "type": "Feature",
  "properties": {
    "date:inception_lower":"1980-01-01",
    "date:inception_upper":"1980-01-31",
    "iso:country":"GB",
    "wof:name":"CM7 5LH",
    "wof:placetype":"postalcode"
},
  "geometry": {"coordinates":[0.564355,51.905188],"type":"Point"}
}