{
  "type": "Feature",
  "properties": {
    "iso:country":"GB",
    "wof:name":"CM7 5LH",
    "wof:placetype":"postalcode"
},
  "geometry": {"coordinates":[0.56435481443436,51.90518773502047],"type":"Point"}
}