{
  "type": "Feature",
  "properties": {
    "date:inception_lower": "1980-01-01",
    "date:inception_upper": "1980-01-01",
    "iso:country": "GB",
    "wof:name": "GU21 3QD",
    "wof:placetype": "postalcode"
  },
  "geometry": {"coordinates":[-0.595017,51.318445],"type":"Point"}
}
