{
  "type": "Feature",
  "properties": {
    "iso:country":"GB",
    "wof:name":"GU21 3QD",
    "wof:placetype":"postalcode"
},
  "geometry": {"coordinates":[-0.59501707765938,51.31844476083634],"type":"Point"}
}