{
  "type": "Feature",
  "properties": {
    "iso:country": "GB",
    "wof:name": "BD13 3PB",
    "wof:placetype": "postalcode"
  },
  "geometry": {"coordinates":[-1.856659,53.79435],"type":"Point"}
}
