{
  "type": "Feature",
  "properties": {
    "iso:country":"GB",
    "wof:name":"BD13 3PB",
    "wof:placetype":"postalcode"
},
  "geometry": {"coordinates":[-1.85665940630082,53.79435003553301],"type":"Point"}
}