{
  "type": "Feature",
  "properties": {
    "iso:country":"GB",
    "wof:name":"TQ2 8QX",
    "wof:placetype":"postalcode"
},
  "geometry": {"coordinates":[-3.53831972989768,50.4955446556536],"type":"Point"}
}