{
  "type": "Feature",
  "properties": {
    "date:inception_lower": "1993-08-01",
    "date:inception_upper": "1993-08-01",
    "iso:country": "GB",
    "wof:name": "NN4 7EB",
    "wof:placetype": "postalcode"
  },
  "geometry": {"coordinates":[-0.861056,52.22009],"type":"Point"}
}
