{
  "type": "Feature",
  "properties": {
    "iso:country":"GB",
    "wof:name":"NN4 7EB",
    "wof:placetype":"postalcode"
},
  "geometry": {"coordinates":[-0.86096345705651,52.21972359903864],"type":"Point"}
}