{
  "type": "Feature",
  "properties": {
    "iso:country":"GB",
    "wof:name":"UB8 3EW",
    "wof:placetype":"postalcode"
},
  "geometry": {"coordinates":[-0.44769917860022,51.52598896910593],"type":"Point"}
}