{
  "type": "Feature",
  "properties": {
    "date:inception_lower": "1980-01-01",
    "date:inception_upper": "1980-01-01",
    "iso:country": "GB",
    "wof:name": "CF48 2BY",
    "wof:placetype": "postalcode"
  },
  "geometry": {"coordinates":[-3.356776,51.772409],"type":"Point"}
}
