{
  "type": "Feature",
  "properties": {
    "iso:country": "GB",
    "wof:name": "HU14 3QH",
    "wof:placetype": "postalcode"
  },
  "geometry": {"coordinates":[-0.49307,53.740888],"type":"Point"}
}
