{
  "type": "Feature",
  "properties": {
    "date:inception_lower": "1980-01-01",
    "date:inception_upper": "1980-01-01",
    "iso:country": "GB",
    "wof:name": "HU14 3QH",
    "wof:placetype": "postalcode"
  },
  "geometry": {"coordinates":[-0.49307,53.740888],"type":"Point"}
}
