{
  "type": "Feature",
  "properties": {
    "iso:country":"GB",
    "wof:name":"HU14 3QH",
    "wof:placetype":"postalcode"
},
  "geometry": {"coordinates":[-0.49307037835427,53.74088797257662],"type":"Point"}
}