{
  "type": "Feature",
  "properties": {
    "iso:country":"GB",
    "wof:name":"LA2 8NG",
    "wof:placetype":"postalcode"
},
  "geometry": {"coordinates":[-2.59894607509912,54.10502451545459],"type":"Point"}
}