{
  "type": "Feature",
  "properties": {
    "iso:country": "GB",
    "wof:name": "SM5 1HZ",
    "wof:placetype": "postalcode"
  },
  "geometry": {"coordinates":[-0.164563,51.387452],"type":"Point"}
}
