{
  "type": "Feature",
  "properties": {
    "iso:country":"GB",
    "wof:name":"SM5 1HZ",
    "wof:placetype":"postalcode"
},
  "geometry": {"coordinates":[-0.16463211334833,51.38744491489746],"type":"Point"}
}