{
  "type": "Feature",
  "properties": {
    "iso:country":"GB",
    "wof:name":"RH15 8TX",
    "wof:placetype":"postalcode"
},
  "geometry": {"coordinates":[-0.14905238450018,50.96410783341016],"type":"Point"}
}