{
  "type": "Feature",
  "properties": {
    "iso:country": "GB",
    "wof:name": "CT19 6BE",
    "wof:placetype": "postalcode"
  },
  "geometry": {"coordinates":[1.195043,51.084303],"type":"Point"}
}
