{
  "type": "Feature",
  "properties": {
    "iso:country": "GB",
    "wof:name": "S18 7SD",
    "wof:placetype": "postalcode"
  },
  "geometry": {"coordinates":[-1.499106,53.290865],"type":"Point"}
}
