{
  "type": "Feature",
  "properties": {
    "date:inception_lower": "1997-06-01",
    "date:inception_upper": "1997-06-01",
    "iso:country": "GB",
    "wof:name": "S18 7SD",
    "wof:placetype": "postalcode"
  },
  "geometry": {"coordinates":[-1.499106,53.290865],"type":"Point"}
}
