{
  "type": "Feature",
  "properties": {
    "iso:country":"GB",
    "wof:name":"S18 7SD",
    "wof:placetype":"postalcode"
},
  "geometry": {"coordinates":[-1.50241064427639,53.29186721912827],"type":"Point"}
}