{
  "type": "Feature",
  "properties": {
    "iso:country": "GB",
    "wof:name": "BH10 5FA",
    "wof:placetype": "postalcode"
  },
  "geometry": {"coordinates":[-1.892106,50.75255],"type":"Point"}
}
