{
  "type": "Feature",
  "properties": {
    "date:inception_lower": "1996-12-01",
    "date:inception_upper": "1996-12-01",
    "iso:country": "GB",
    "wof:name": "W4 2TU",
    "wof:placetype": "postalcode"
  },
  "geometry": {"coordinates":[-0.251427,51.482771],"type":"Point"}
}
