{
  "type": "Feature",
  "properties": {
    "iso:country":"GB",
    "wof:name":"W4 2TU",
    "wof:placetype":"postalcode"
},
  "geometry": {"coordinates":[-0.25142671093513,51.48277081388726],"type":"Point"}
}