{
  "type": "Feature",
  "properties": {
    "iso:country":"GB",
    "wof:name":"G13 4ND",
    "wof:placetype":"postalcode"
},
  "geometry": {"coordinates":[-4.37802011619103,55.89968354573597],"type":"Point"}
}