{
  "type": "Feature",
  "properties": {
    "iso:country": "GB",
    "wof:name": "L13 0AW",
    "wof:placetype": "postalcode"
  },
  "geometry": {"coordinates":[-2.921324,53.428653],"type":"Point"}
}
