{
  "type": "Feature",
  "properties": {
    "date:inception_lower": "1980-01-01",
    "date:inception_upper": "1980-01-01",
    "iso:country": "GB",
    "wof:name": "PO19 1QP",
    "wof:placetype": "postalcode"
  },
  "geometry": {"coordinates":[-0.782388,50.836977],"type":"Point"}
}
