{
  "type": "Feature",
  "properties": {
    "iso:country":"GB",
    "wof:name":"RH2 9LJ",
    "wof:placetype":"postalcode"
},
  "geometry": {"coordinates":[-0.20868260157445,51.24673436850523],"type":"Point"}
}