{
  "type": "Feature",
  "properties": {
    "iso:country":"GB",
    "wof:name":"L32 0RB",
    "wof:placetype":"postalcode"
},
  "geometry": {"coordinates":[-2.90487947830154,53.48409717279636],"type":"Point"}
}