{
  "type": "Feature",
  "properties": {
    "iso:country":"GB",
    "wof:name":"TW9 4EG",
    "wof:placetype":"postalcode"
},
  "geometry": {"coordinates":[-0.27962030228857,51.4760388655687],"type":"Point"}
}