{
  "type": "Feature",
  "properties": {
    "iso:country":"GB",
    "wof:name":"DT9 5JX",
    "wof:placetype":"postalcode"
},
  "geometry": {"coordinates":[-2.44789683780255,50.91291377911213],"type":"Point"}
}