{
  "type": "Feature",
  "properties": {
    "iso:country": "GB",
    "wof:name": "DT9 5JX",
    "wof:placetype": "postalcode"
  },
  "geometry": {"coordinates":[-2.447186,50.913062],"type":"Point"}
}
