{
  "type": "Feature",
  "properties": {
    "date:inception_lower": "1980-01-01",
    "date:inception_upper": "1980-01-01",
    "iso:country": "GB",
    "wof:name": "DT9 5JX",
    "wof:placetype": "postalcode"
  },
  "geometry": {"coordinates":[-2.447186,50.913062],"type":"Point"}
}
