{
  "type": "Feature",
  "properties": {
    "iso:country":"GB",
    "wof:name":"TN10 3TA",
    "wof:placetype":"postalcode"
},
  "geometry": {"coordinates":[0.27329276294592,51.20596984847514],"type":"Point"}
}