{
  "type": "Feature",
  "properties": {
    "iso:country":"GB",
    "wof:name":"NN6 8AZ",
    "wof:placetype":"postalcode"
},
  "geometry": {"coordinates":[-0.94252994212069,52.28193382818764],"type":"Point"}
}