{
  "type": "Feature",
  "properties": {
    "iso:country": "GB",
    "wof:name": "NN6 8AZ",
    "wof:placetype": "postalcode"
  },
  "geometry": {"coordinates":[-0.94253,52.281934],"type":"Point"}
}
