{
  "type": "Feature",
  "properties": {
    "date:inception_lower": "1980-01-01",
    "date:inception_upper": "1980-01-01",
    "iso:country": "GB",
    "wof:name": "NN6 8AZ",
    "wof:placetype": "postalcode"
  },
  "geometry": {"coordinates":[-0.94253,52.281934],"type":"Point"}
}
