{
  "type": "Feature",
  "properties": {
    "iso:country":"GB",
    "wof:name":"DN1 2NE",
    "wof:placetype":"postalcode"
},
  "geometry": {"coordinates":[-1.12672854805371,53.52846175169734],"type":"Point"}
}