{
  "type": "Feature",
  "properties": {
    "iso:country": "GB",
    "wof:name": "N8 0RY",
    "wof:placetype": "postalcode"
  },
  "geometry": {"coordinates":[-0.099695,51.584708],"type":"Point"}
}
