{
  "type": "Feature",
  "properties": {
    "iso:country":"GB",
    "wof:name":"N8 0RY",
    "wof:placetype":"postalcode"
},
  "geometry": {"coordinates":[-0.09978963212466,51.58477883448724],"type":"Point"}
}