{
  "type": "Feature",
  "properties": {
    "iso:country":"GB",
    "wof:name":"TQ5 9DY",
    "wof:placetype":"postalcode"
},
  "geometry": {"coordinates":[-3.51207062914069,50.39006892850975],"type":"Point"}
}