{
  "type": "Feature",
  "properties": {
    "iso:country":"GB",
    "wof:name":"G76 7XU",
    "wof:placetype":"postalcode"
},
  "geometry": {"coordinates":[-4.29043606598438,55.78264592696787],"type":"Point"}
}