{
  "type": "Feature",
  "properties": {
    "iso:country": "GB",
    "wof:name": "G76 7XU",
    "wof:placetype": "postalcode"
  },
  "geometry": {"coordinates":[-4.290436,55.782646],"type":"Point"}
}
