{
  "type": "Feature",
  "properties": {
    "iso:country":"GB",
    "wof:name":"TR19 7TA",
    "wof:placetype":"postalcode"
},
  "geometry": {"coordinates":[-5.67313465690029,50.14604982709616],"type":"Point"}
}