{
  "type": "Feature",
  "properties": {
    "iso:country":"GB",
    "wof:name":"NE5 5HR",
    "wof:placetype":"postalcode"
},
  "geometry": {"coordinates":[-1.69237228170033,54.99817787198445],"type":"Point"}
}