{
  "type": "Feature",
  "properties": {
    "iso:country":"GB",
    "wof:name":"N18 1BT",
    "wof:placetype":"postalcode"
},
  "geometry": {"coordinates":[-0.08549072275089,51.6131334439001],"type":"Point"}
}