{
  "type": "Feature",
  "properties": {
    "iso:country":"GB",
    "wof:name":"GU7 1GX",
    "wof:placetype":"postalcode"
},
  "geometry": {"coordinates":[-0.61477047391139,51.18513371350871],"type":"Point"}
}