{
  "type": "Feature",
  "properties": {
    "iso:country":"GB",
    "wof:name":"PL1 2NW",
    "wof:placetype":"postalcode"
},
  "geometry": {"coordinates":[-4.13597500880393,50.36616916273815],"type":"Point"}
}