{
  "type": "Feature",
  "properties": {
    "date:inception_lower":"1980-01-01",
    "date:inception_upper":"1980-01-31",
    "iso:country":"GB",
    "wof:name":"PL1 2NW",
    "wof:placetype":"postalcode"
},
  "geometry": {"coordinates":[-4.135975,50.366169],"type":"Point"}
}