{
  "type": "Feature",
  "properties": {
    "iso:country":"GB",
    "wof:name":"BS30 8YZ",
    "wof:placetype":"postalcode"
},
  "geometry": {"coordinates":[-2.46807341509131,51.44446106513865],"type":"Point"}
}