{
  "type": "Feature",
  "properties": {
    "date:inception_lower": "2000-06-01",
    "date:inception_upper": "2000-06-01",
    "iso:country": "GB",
    "wof:name": "M20 6AZ",
    "wof:placetype": "postalcode"
  },
  "geometry": {"coordinates":[-2.230577,53.41871],"type":"Point"}
}
