{
  "type": "Feature",
  "properties": {
    "iso:country":"GB",
    "wof:name":"WC1X 9ET",
    "wof:placetype":"postalcode"
},
  "geometry": {"coordinates":[-0.11363977314552,51.52916798580197],"type":"Point"}
}