{
  "type": "Feature",
  "properties": {
    "iso:country":"GB",
    "wof:name":"DN22 6TB",
    "wof:placetype":"postalcode"
},
  "geometry": {"coordinates":[-0.93738395735396,53.33177904428329],"type":"Point"}
}