{
  "type": "Feature",
  "properties": {
    "date:inception_lower": "1980-01-01",
    "date:inception_upper": "1980-01-01",
    "iso:country": "GB",
    "wof:name": "DN22 6TB",
    "wof:placetype": "postalcode"
  },
  "geometry": {"coordinates":[-0.937384,53.331779],"type":"Point"}
}
