{
  "type": "Feature",
  "properties": {
    "date:inception_lower":"2006-05-01",
    "date:inception_upper":"2006-05-31",
    "iso:country":"GB",
    "wof:name":"IP4 4PA",
    "wof:placetype":"postalcode"
},
  "geometry": {"coordinates":[1.187169,52.05982],"type":"Point"}
}