{
  "type": "Feature",
  "properties": {
    "iso:country": "GB",
    "wof:name": "IP4 4PA",
    "wof:placetype": "postalcode"
  },
  "geometry": {"coordinates":[1.187169,52.05982],"type":"Point"}
}
