{
  "type": "Feature",
  "properties": {
    "date:inception_lower": "1980-01-01",
    "date:inception_upper": "1980-01-01",
    "iso:country": "GB",
    "wof:name": "OL13 9AE",
    "wof:placetype": "postalcode"
  },
  "geometry": {"coordinates":[-2.20008,53.703615],"type":"Point"}
}
