{
  "type": "Feature",
  "properties": {
    "iso:country": "GB",
    "wof:name": "E3 2WR",
    "wof:placetype": "postalcode"
  },
  "geometry": {"coordinates":[-0.016634,51.530016],"type":"Point"}
}
