{
  "type": "Feature",
  "properties": {
    "iso:country":"GB",
    "wof:name":"BN26 6FY",
    "wof:placetype":"postalcode"
},
  "geometry": {"coordinates":[0.20463793942044,50.84186559429947],"type":"Point"}
}