{
  "type": "Feature",
  "properties": {
    "date:inception_lower": "2013-11-01",
    "date:inception_upper": "2013-11-01",
    "iso:country": "GB",
    "wof:name": "BN26 6FY",
    "wof:placetype": "postalcode"
  },
  "geometry": {"coordinates":[0.204638,50.841866],"type":"Point"}
}
