{
  "type": "Feature",
  "properties": {
    "iso:country":"GB",
    "wof:name":"CH3 7QR",
    "wof:placetype":"postalcode"
},
  "geometry": {"coordinates":[-2.81814061772813,53.17283381557716],"type":"Point"}
}