{
  "type": "Feature",
  "properties": {
    "iso:country":"GB",
    "wof:name":"B30 3RB",
    "wof:placetype":"postalcode"
},
  "geometry": {"coordinates":[-1.91521680812457,52.41196756867964],"type":"Point"}
}