{
  "type": "Feature",
  "properties": {
    "date:inception_lower": "2020-10-01",
    "date:inception_upper": "2020-10-01",
    "iso:country": "GB",
    "wof:name": "SN14 6FF",
    "wof:placetype": "postalcode"
  },
  "geometry": {"coordinates":[-2.138303,51.466668],"type":"Point"}
}
