{
  "type": "Feature",
  "properties": {
    "iso:country":"GB",
    "wof:name":"IV52 8TJ",
    "wof:placetype":"postalcode"
},
  "geometry": {"coordinates":[-5.64741107831881,57.34158407898846],"type":"Point"}
}