{
  "type": "Feature",
  "properties": {
    "iso:country": "GB",
    "wof:name": "SY3 7RT",
    "wof:placetype": "postalcode"
  },
  "geometry": {"coordinates":[-2.743716,52.699415],"type":"Point"}
}
