{
  "type": "Feature",
  "properties": {
    "iso:country":"GB",
    "wof:name":"GU35 9HL",
    "wof:placetype":"postalcode"
},
  "geometry": {"coordinates":[-0.87873822912877,51.11650753620944],"type":"Point"}
}