{
  "type": "Feature",
  "properties": {
    "date:inception_lower": "2007-09-01",
    "date:inception_upper": "2007-09-01",
    "iso:country": "GB",
    "wof:name": "AB15 9DW",
    "wof:placetype": "postalcode"
  },
  "geometry": {"coordinates":[-2.163772,57.124006],"type":"Point"}
}
