{
  "type": "Feature",
  "properties": {
    "iso:country":"GB",
    "wof:name":"AB15 9DW",
    "wof:placetype":"postalcode"
},
  "geometry": {"coordinates":[-2.16377163776771,57.12400647387338],"type":"Point"}
}