{
  "type": "Feature",
  "properties": {
    "iso:country":"GB",
    "wof:name":"DA2 7PQ",
    "wof:placetype":"postalcode"
},
  "geometry": {"coordinates":[0.1706998556763,51.42300783322032],"type":"Point"}
}