{
  "type": "Feature",
  "properties": {
    "iso:country":"GB",
    "wof:name":"CO15 1UF",
    "wof:placetype":"postalcode"
},
  "geometry": {"coordinates":[1.15682593160981,51.78912473149425],"type":"Point"}
}