{
  "type": "Feature",
  "properties": {
    "iso:country": "GB",
    "wof:name": "LA4 6LL",
    "wof:placetype": "postalcode"
  },
  "geometry": {"coordinates":[-2.836524,54.075367],"type":"Point"}
}
