{
  "type": "Feature",
  "properties": {
    "iso:country":"GB",
    "wof:name":"LA4 6LL",
    "wof:placetype":"postalcode"
},
  "geometry": {"coordinates":[-2.83652383240129,54.07536740330255],"type":"Point"}
}