{
  "type": "Feature",
  "properties": {
    "date:inception_lower": "2018-01-01",
    "date:inception_upper": "2018-01-01",
    "iso:country": "GB",
    "wof:name": "L3 4DJ",
    "wof:placetype": "postalcode"
  },
  "geometry": {"coordinates":[-2.984879,53.392029],"type":"Point"}
}
