{
  "type": "Feature",
  "properties": {
    "iso:country": "GB",
    "wof:name": "OL11 2TS",
    "wof:placetype": "postalcode"
  },
  "geometry": {"coordinates":[-2.176355,53.587316],"type":"Point"}
}
