{
  "type": "Feature",
  "properties": {
    "date:inception_lower": "1980-01-01",
    "date:inception_upper": "1980-01-01",
    "iso:country": "GB",
    "wof:name": "OL11 2TS",
    "wof:placetype": "postalcode"
  },
  "geometry": {"coordinates":[-2.176355,53.587316],"type":"Point"}
}
