{
  "type": "Feature",
  "properties": {
    "iso:country":"GB",
    "wof:name":"CV5 9GD",
    "wof:placetype":"postalcode"
},
  "geometry": {"coordinates":[-1.56633080047691,52.42600118973434],"type":"Point"}
}