{
  "type": "Feature",
  "properties": {
    "iso:country":"GB",
    "wof:name":"SA1 8EF",
    "wof:placetype":"postalcode"
},
  "geometry": {"coordinates":[-3.93057670275161,51.62846345237997],"type":"Point"}
}