{
  "type": "Feature",
  "properties": {
    "iso:country": "GB",
    "wof:name": "TN28 8RP",
    "wof:placetype": "postalcode"
  },
  "geometry": {"coordinates":[0.963611,50.958434],"type":"Point"}
}
