{
  "type": "Feature",
  "properties": {
    "date:inception_lower": "2022-04-01",
    "date:inception_upper": "2022-04-01",
    "iso:country": "GB",
    "wof:name": "MK43 9TH",
    "wof:placetype": "postalcode"
  },
  "geometry": {"coordinates":[-0.504347,52.069],"type":"Point"}
}
