{
  "type": "Feature",
  "properties": {
    "iso:country":"GB",
    "wof:name":"LS12 5AB",
    "wof:placetype":"postalcode"
},
  "geometry": {"coordinates":[-1.62006527523596,53.78659004762982],"type":"Point"}
}