{
  "type": "Feature",
  "properties": {
    "date:inception_lower":"2000-06-01",
    "date:inception_upper":"2000-06-30",
    "iso:country":"GB",
    "wof:name":"PE29 6XZ",
    "wof:placetype":"postalcode"
},
  "geometry": {"coordinates":[-0.206351,52.331455],"type":"Point"}
}