{
  "type": "Feature",
  "properties": {
    "iso:country": "GB",
    "wof:name": "DY5 2EE",
    "wof:placetype": "postalcode"
  },
  "geometry": {"coordinates":[-2.105717,52.469384],"type":"Point"}
}
