{
  "type": "Feature",
  "properties": {
    "iso:country":"GB",
    "wof:name":"DY5 2EE",
    "wof:placetype":"postalcode"
},
  "geometry": {"coordinates":[-2.10573805548945,52.46936953104372],"type":"Point"}
}