{
  "type": "Feature",
  "properties": {
    "date:inception_lower":"1981-09-01",
    "date:inception_upper":"1981-09-30",
    "iso:country":"GB",
    "wof:name":"DY5 2EE",
    "wof:placetype":"postalcode"
},
  "geometry": {"coordinates":[-2.105717,52.469384],"type":"Point"}
}