{
  "type": "Feature",
  "properties": {
    "iso:country":"GB",
    "wof:name":"WR2 6LH",
    "wof:placetype":"postalcode"
},
  "geometry": {"coordinates":[-2.25610035553496,52.22684483692086],"type":"Point"}
}