{
  "type": "Feature",
  "properties": {
    "iso:country":"GB",
    "wof:name":"TN21 0QE",
    "wof:placetype":"postalcode"
},
  "geometry": {"coordinates":[0.22214443630972,50.96744613469154],"type":"Point"}
}