{
  "type": "Feature",
  "properties": {
    "iso:country": "GB",
    "wof:name": "WC2N 6HW",
    "wof:placetype": "postalcode"
  },
  "geometry": {"coordinates":[-0.124229,51.508655],"type":"Point"}
}
