{
  "type": "Feature",
  "properties": {
    "iso:country":"GB",
    "wof:name":"DN37 0BZ",
    "wof:placetype":"postalcode"
},
  "geometry": {"coordinates":[-0.10767343609323,53.5132962839403],"type":"Point"}
}