{
  "type": "Feature",
  "properties": {
    "iso:country": "GB",
    "wof:name": "TA24 7UF",
    "wof:placetype": "postalcode"
  },
  "geometry": {"coordinates":[-3.514334,51.153159],"type":"Point"}
}
