{
  "type": "Feature",
  "properties": {
    "iso:country":"GB",
    "wof:name":"BN11 5AY",
    "wof:placetype":"postalcode"
},
  "geometry": {"coordinates":[-0.39481803509878,50.81499598492564],"type":"Point"}
}