{
  "type": "Feature",
  "properties": {
    "date:inception_lower": "1980-01-01",
    "date:inception_upper": "1980-01-01",
    "iso:country": "GB",
    "wof:name": "BN11 5AY",
    "wof:placetype": "postalcode"
  },
  "geometry": {"coordinates":[-0.394818,50.814996],"type":"Point"}
}
