{
  "type": "Feature",
  "properties": {
    "iso:country":"GB",
    "wof:name":"NN5 6SN",
    "wof:placetype":"postalcode"
},
  "geometry": {"coordinates":[-0.94360344309033,52.25342504546574],"type":"Point"}
}