{
  "type": "Feature",
  "properties": {
    "date:inception_lower": "1980-01-01",
    "date:inception_upper": "1980-01-01",
    "iso:country": "GB",
    "wof:name": "NN5 6SN",
    "wof:placetype": "postalcode"
  },
  "geometry": {"coordinates":[-0.943603,52.253425],"type":"Point"}
}
