{
  "type": "Feature",
  "properties": {
    "iso:country": "GB",
    "wof:name": "SA1 5DF",
    "wof:placetype": "postalcode"
  },
  "geometry": {"coordinates":[-3.944746,51.622618],"type":"Point"}
}
