{
  "type": "Feature",
  "properties": {
    "date:inception_lower":"1980-01-01",
    "date:inception_upper":"1980-01-31",
    "iso:country":"GB",
    "wof:name":"SA1 5DF",
    "wof:placetype":"postalcode"
},
  "geometry": {"coordinates":[-3.944746,51.622618],"type":"Point"}
}