{
  "type": "Feature",
  "properties": {
    "date:inception_lower": "1980-01-01",
    "date:inception_upper": "1980-01-01",
    "iso:country": "GB",
    "wof:name": "EX10 0JQ",
    "wof:placetype": "postalcode"
  },
  "geometry": {"coordinates":[-3.205378,50.693409],"type":"Point"}
}
