{
  "type": "Feature",
  "properties": {
    "iso:country":"GB",
    "wof:name":"EX10 0JQ",
    "wof:placetype":"postalcode"
},
  "geometry": {"coordinates":[-3.20537756316316,50.6934088989154],"type":"Point"}
}