{
  "type": "Feature",
  "properties": {
    "iso:country":"GB",
    "wof:name":"L5 0SX",
    "wof:placetype":"postalcode"
},
  "geometry": {"coordinates":[-2.97039702891263,53.42765439914552],"type":"Point"}
}