{
  "type": "Feature",
  "properties": {
    "iso:country": "GB",
    "wof:name": "L5 0SX",
    "wof:placetype": "postalcode"
  },
  "geometry": {"coordinates":[-2.970397,53.427654],"type":"Point"}
}
