{
  "type": "Feature",
  "properties": {
    "iso:country": "GB",
    "wof:name": "BS16 9BB",
    "wof:placetype": "postalcode"
  },
  "geometry": {"coordinates":[-2.483979,51.491297],"type":"Point"}
}
