{
  "type": "Feature",
  "properties": {
    "iso:country":"GB",
    "wof:name":"BS16 9BB",
    "wof:placetype":"postalcode"
},
  "geometry": {"coordinates":[-2.48397932332515,51.4912965566735],"type":"Point"}
}