{
  "type": "Feature",
  "properties": {
    "iso:country":"GB",
    "wof:name":"SK8 5DQ",
    "wof:placetype":"postalcode"
},
  "geometry": {"coordinates":[-2.19471263712259,53.37737299167141],"type":"Point"}
}