{
  "type": "Feature",
  "properties": {
    "iso:country":"GB",
    "wof:name":"BA1 7NX",
    "wof:placetype":"postalcode"
},
  "geometry": {"coordinates":[-2.31638846619019,51.40926318130641],"type":"Point"}
}