{
  "type": "Feature",
  "properties": {
    "iso:country": "GB",
    "wof:name": "BA1 7NX",
    "wof:placetype": "postalcode"
  },
  "geometry": {"coordinates":[-2.316388,51.409263],"type":"Point"}
}
