{
  "type": "Feature",
  "properties": {
    "iso:country":"GB",
    "wof:name":"TW7 4JF",
    "wof:placetype":"postalcode"
},
  "geometry": {"coordinates":[-0.33999937348206,51.47723288050778],"type":"Point"}
}