{
  "type": "Feature",
  "properties": {
    "iso:country":"GB",
    "wof:name":"BD20 6PE",
    "wof:placetype":"postalcode"
},
  "geometry": {"coordinates":[-1.96077978845367,53.89522818536651],"type":"Point"}
}