{
  "type": "Feature",
  "properties": {
    "date:inception_lower":"2006-03-01",
    "date:inception_upper":"2006-03-31",
    "iso:country":"GB",
    "wof:name":"EC2M 2BS",
    "wof:placetype":"postalcode"
},
  "geometry": {"coordinates":[-0.084167,51.518619],"type":"Point"}
}