{
  "type": "Feature",
  "properties": {
    "iso:country": "GB",
    "wof:name": "EC2M 2BS",
    "wof:placetype": "postalcode"
  },
  "geometry": {"coordinates":[-0.084167,51.518619],"type":"Point"}
}
