{
  "type": "Feature",
  "properties": {
    "date:inception_lower": "2021-02-01",
    "date:inception_upper": "2021-02-01",
    "iso:country": "GB",
    "wof:name": "BN27 1GH",
    "wof:placetype": "postalcode"
  },
  "geometry": {"coordinates":[0.27052,50.876393],"type":"Point"}
}
