{
  "type": "Feature",
  "properties": {
    "iso:country": "GB",
    "wof:name": "BN27 1GH",
    "wof:placetype": "postalcode"
  },
  "geometry": {"coordinates":[0.270253,50.876749],"type":"Point"}
}
