{
  "type": "Feature",
  "properties": {
    "iso:country":"GB",
    "wof:name":"RM8 2EQ",
    "wof:placetype":"postalcode"
},
  "geometry": {"coordinates":[0.12260621869094,51.54535548442577],"type":"Point"}
}