{
  "type": "Feature",
  "properties": {
    "iso:country":"GB",
    "wof:name":"G71 6AG",
    "wof:placetype":"postalcode"
},
  "geometry": {"coordinates":[-4.08335389683138,55.82876857381432],"type":"Point"}
}