{
  "type": "Feature",
  "properties": {
    "date:inception_lower": "1980-01-01",
    "date:inception_upper": "1980-01-01",
    "iso:country": "GB",
    "wof:name": "G71 6AG",
    "wof:placetype": "postalcode"
  },
  "geometry": {"coordinates":[-4.083354,55.828769],"type":"Point"}
}
