{
  "type": "Feature",
  "properties": {
    "iso:country": "GB",
    "wof:name": "CM1 4PF",
    "wof:placetype": "postalcode"
  },
  "geometry": {"coordinates":[0.378812,51.750669],"type":"Point"}
}
