{
  "type": "Feature",
  "properties": {
    "iso:country":"GB",
    "wof:name":"CM1 4PF",
    "wof:placetype":"postalcode"
},
  "geometry": {"coordinates":[0.37881146594153,51.75066902428485],"type":"Point"}
}