{
  "type": "Feature",
  "properties": {
    "date:inception_lower": "1992-08-01",
    "date:inception_upper": "1992-08-01",
    "iso:country": "GB",
    "wof:name": "KT14 6HJ",
    "wof:placetype": "postalcode"
  },
  "geometry": {"coordinates":[-0.473429,51.342165],"type":"Point"}
}
