{
  "type": "Feature",
  "properties": {
    "iso:country": "GB",
    "wof:name": "NR28 9DB",
    "wof:placetype": "postalcode"
  },
  "geometry": {"coordinates":[1.392974,52.821004],"type":"Point"}
}
