{
  "type": "Feature",
  "properties": {
    "iso:country":"GB",
    "wof:name":"NR28 9DB",
    "wof:placetype":"postalcode"
},
  "geometry": {"coordinates":[1.39289351262856,52.82097805118632],"type":"Point"}
}