{
  "type": "Feature",
  "properties": {
    "iso:country":"GB",
    "wof:name":"PO12 4UN",
    "wof:placetype":"postalcode"
},
  "geometry": {"coordinates":[-1.13272044361802,50.79814640312514],"type":"Point"}
}