{
  "type": "Feature",
  "properties": {
    "iso:country": "GB",
    "wof:name": "PO12 4UN",
    "wof:placetype": "postalcode"
  },
  "geometry": {"coordinates":[-1.13272,50.798146],"type":"Point"}
}
