{
  "type": "Feature",
  "properties": {
    "iso:country":"GB",
    "wof:name":"TQ5 9QX",
    "wof:placetype":"postalcode"
},
  "geometry": {"coordinates":[-3.52229207886303,50.38417055550973],"type":"Point"}
}