{
  "type": "Feature",
  "properties": {
    "iso:country": "GB",
    "wof:name": "HP22 5EY",
    "wof:placetype": "postalcode"
  },
  "geometry": {"coordinates":[-0.728301,51.804629],"type":"Point"}
}
