{
  "type": "Feature",
  "properties": {
    "iso:country":"GB",
    "wof:name":"NR2 4HQ",
    "wof:placetype":"postalcode"
},
  "geometry": {"coordinates":[1.26974703915262,52.63659078732169],"type":"Point"}
}