{
  "type": "Feature",
  "properties": {
    "date:inception_lower": "2018-05-01",
    "date:inception_upper": "2018-05-01",
    "iso:country": "GB",
    "wof:name": "L2 8AB",
    "wof:placetype": "postalcode"
  },
  "geometry": {"coordinates":[-2.993723,53.406311],"type":"Point"}
}
