{
  "type": "Feature",
  "properties": {
    "iso:country":"GB",
    "wof:name":"BN20 7HD",
    "wof:placetype":"postalcode"
},
  "geometry": {"coordinates":[0.27490170243996,50.76136966016226],"type":"Point"}
}