{
  "type": "Feature",
  "properties": {
    "iso:country":"GB",
    "wof:name":"WV8 2AS",
    "wof:placetype":"postalcode"
},
  "geometry": {"coordinates":[-2.20078654764634,52.62057271563311],"type":"Point"}
}