{
  "type": "Feature",
  "properties": {
    "iso:country":"GB",
    "wof:name":"BA10 0NW",
    "wof:placetype":"postalcode"
},
  "geometry": {"coordinates":[-2.46722136130738,51.10088474188616],"type":"Point"}
}