{
  "type": "Feature",
  "properties": {
    "iso:country": "GB",
    "wof:name": "BA10 0NW",
    "wof:placetype": "postalcode"
  },
  "geometry": {"coordinates":[-2.467221,51.100885],"type":"Point"}
}
