{
  "type": "Feature",
  "properties": {
    "iso:country":"GB",
    "wof:name":"IV4 7DP",
    "wof:placetype":"postalcode"
},
  "geometry": {"coordinates":[-4.45990665809731,57.4842359450199],"type":"Point"}
}