{
  "type": "Feature",
  "properties": {
    "date:inception_lower":"1980-01-01",
    "date:inception_upper":"1980-01-31",
    "iso:country":"GB",
    "wof:name":"IV4 7DP",
    "wof:placetype":"postalcode"
},
  "geometry": {"coordinates":[-4.460362,57.484326],"type":"Point"}
}