{
  "type": "Feature",
  "properties": {
    "iso:country":"GB",
    "wof:name":"SK7 1EZ",
    "wof:placetype":"postalcode"
},
  "geometry": {"coordinates":[-2.17778139400715,53.35804694736705],"type":"Point"}
}