{
  "type": "Feature",
  "properties": {
    "date:inception_lower":"1980-01-01",
    "date:inception_upper":"1980-01-31",
    "iso:country":"GB",
    "wof:name":"SK7 1EZ",
    "wof:placetype":"postalcode"
},
  "geometry": {"coordinates":[-2.177781,53.358047],"type":"Point"}
}