{
  "type": "Feature",
  "properties": {
    "iso:country":"GB",
    "wof:name":"NE3 4JN",
    "wof:placetype":"postalcode"
},
  "geometry": {"coordinates":[-1.63933087541426,54.99681019218649],"type":"Point"}
}