{
  "type": "Feature",
  "properties": {
    "date:inception_lower": "1980-01-01",
    "date:inception_upper": "1980-01-01",
    "iso:country": "GB",
    "wof:name": "NE30 3TF",
    "wof:placetype": "postalcode"
  },
  "geometry": {"coordinates":[-1.43336,55.026669],"type":"Point"}
}
