{
  "type": "Feature",
  "properties": {
    "iso:country": "GB",
    "wof:name": "M29 8BF",
    "wof:placetype": "postalcode"
  },
  "geometry": {"coordinates":[-2.467589,53.516171],"type":"Point"}
}
