{
  "type": "Feature",
  "properties": {
    "iso:country":"GB",
    "wof:name":"M29 8BF",
    "wof:placetype":"postalcode"
},
  "geometry": {"coordinates":[-2.46759007313026,53.51615408833281],"type":"Point"}
}