{
  "type": "Feature",
  "properties": {
    "date:inception_lower":"1980-01-01",
    "date:inception_upper":"1980-01-31",
    "iso:country":"GB",
    "wof:name":"BN15 9ST",
    "wof:placetype":"postalcode"
},
  "geometry": {"coordinates":[-0.334837,50.83109],"type":"Point"}
}