{
  "type": "Feature",
  "properties": {
    "iso:country":"GB",
    "wof:name":"NN10 0DQ",
    "wof:placetype":"postalcode"
},
  "geometry": {"coordinates":[-0.59424274637539,52.29162636449207],"type":"Point"}
}