{
  "type": "Feature",
  "properties": {
    "iso:country": "GB",
    "wof:name": "ME8 6QL",
    "wof:placetype": "postalcode"
  },
  "geometry": {"coordinates":[0.585342,51.379229],"type":"Point"}
}
