{
  "type": "Feature",
  "properties": {
    "iso:country":"GB",
    "wof:name":"ME8 6QL",
    "wof:placetype":"postalcode"
},
  "geometry": {"coordinates":[0.58534197019903,51.37922932429449],"type":"Point"}
}