{
  "type": "Feature",
  "properties": {
    "iso:country": "GB",
    "wof:name": "EH4 7DA",
    "wof:placetype": "postalcode"
  },
  "geometry": {"coordinates":[-3.283716,55.956942],"type":"Point"}
}
