{
  "type": "Feature",
  "properties": {
    "iso:country":"GB",
    "wof:name":"EX7 0DA",
    "wof:placetype":"postalcode"
},
  "geometry": {"coordinates":[-3.4641514012108,50.58421519608144],"type":"Point"}
}