{
  "type": "Feature",
  "properties": {
    "date:inception_lower":"1999-06-01",
    "date:inception_upper":"1999-06-30",
    "iso:country":"GB",
    "wof:name":"CH43 4XJ",
    "wof:placetype":"postalcode"
},
  "geometry": {"coordinates":[-3.038896,53.389603],"type":"Point"}
}