{
  "type": "Feature",
  "properties": {
    "date:inception_lower": "1990-07-01",
    "date:inception_upper": "1990-07-01",
    "iso:country": "GB",
    "wof:name": "MK8 0EZ",
    "wof:placetype": "postalcode"
  },
  "geometry": {"coordinates":[-0.8076,52.029442],"type":"Point"}
}
