{
  "type": "Feature",
  "properties": {
    "date:inception_lower": "2024-03-01",
    "date:inception_upper": "2024-03-01",
    "iso:country": "GB",
    "wof:name": "LA14 4SL",
    "wof:placetype": "postalcode"
  },
  "geometry": {"coordinates":[-3.200826,54.142244],"type":"Point"}
}
