{
  "type": "Feature",
  "properties": {
    "date:inception_lower": "1980-01-01",
    "date:inception_upper": "1980-01-01",
    "iso:country": "GB",
    "wof:name": "SA18 2DE",
    "wof:placetype": "postalcode"
  },
  "geometry": {"coordinates":[-3.996412,51.796436],"type":"Point"}
}
