{
  "type": "Feature",
  "properties": {
    "iso:country":"GB",
    "wof:name":"SA18 2DE",
    "wof:placetype":"postalcode"
},
  "geometry": {"coordinates":[-3.9963798798196,51.79647365016515],"type":"Point"}
}