{
  "type": "Feature",
  "properties": {
    "iso:country": "GB",
    "wof:name": "SA18 2DE",
    "wof:placetype": "postalcode"
  },
  "geometry": {"coordinates":[-3.9964,51.796481],"type":"Point"}
}
