{
  "type": "Feature",
  "properties": {
    "iso:country":"GB",
    "wof:name":"KT23 4JW",
    "wof:placetype":"postalcode"
},
  "geometry": {"coordinates":[-0.37635443743395,51.27595136243575],"type":"Point"}
}