{
  "type": "Feature",
  "properties": {
    "iso:country":"GB",
    "wof:name":"RG10 0QL",
    "wof:placetype":"postalcode"
},
  "geometry": {"coordinates":[-0.80120594503086,51.46005953494671],"type":"Point"}
}