{
  "type": "Feature",
  "properties": {
    "iso:country":"GB",
    "wof:name":"LL19 7PU",
    "wof:placetype":"postalcode"
},
  "geometry": {"coordinates":[-3.42663007850679,53.33301920390094],"type":"Point"}
}