{
  "type": "Feature",
  "properties": {
    "iso:country": "GB",
    "wof:name": "AB41 8YX",
    "wof:placetype": "postalcode"
  },
  "geometry": {"coordinates":[-2.07573,57.430175],"type":"Point"}
}
