{
  "type": "Feature",
  "properties": {
    "date:inception_lower": "1990-08-01",
    "date:inception_upper": "1990-08-01",
    "iso:country": "GB",
    "wof:name": "AB41 8YX",
    "wof:placetype": "postalcode"
  },
  "geometry": {"coordinates":[-2.073104,57.433069],"type":"Point"}
}
