{
  "type": "Feature",
  "properties": {
    "iso:country":"GB",
    "wof:name":"SA65 9DN",
    "wof:placetype":"postalcode"
},
  "geometry": {"coordinates":[-4.98275487846884,51.99794385663628],"type":"Point"}
}