{
  "type": "Feature",
  "properties": {
    "iso:country": "GB",
    "wof:name": "SA65 9DN",
    "wof:placetype": "postalcode"
  },
  "geometry": {"coordinates":[-4.982755,51.997944],"type":"Point"}
}
