{
  "type": "Feature",
  "properties": {
    "iso:country":"GB",
    "wof:name":"TW16 6LY",
    "wof:placetype":"postalcode"
},
  "geometry": {"coordinates":[-0.4246195268294,51.41354772593775],"type":"Point"}
}