{
  "type": "Feature",
  "properties": {
    "date:inception_lower": "2020-09-01",
    "date:inception_upper": "2020-09-01",
    "iso:country": "GB",
    "wof:name": "OX11 9FQ",
    "wof:placetype": "postalcode"
  },
  "geometry": {"coordinates":[-1.22889,51.618103],"type":"Point"}
}
