{
  "type": "Feature",
  "properties": {
    "date:inception_lower": "1980-01-01",
    "date:inception_upper": "1980-01-01",
    "iso:country": "GB",
    "wof:name": "DY11 6DH",
    "wof:placetype": "postalcode"
  },
  "geometry": {"coordinates":[-2.277229,52.386841],"type":"Point"}
}
