{
  "type": "Feature",
  "properties": {
    "iso:country": "GB",
    "wof:name": "TN34 2AN",
    "wof:placetype": "postalcode"
  },
  "geometry": {"coordinates":[0.592618,50.875621],"type":"Point"}
}
