{
  "type": "Feature",
  "properties": {
    "iso:country":"GB",
    "wof:name":"TN34 2AN",
    "wof:placetype":"postalcode"
},
  "geometry": {"coordinates":[0.59261782601055,50.87562098777017],"type":"Point"}
}