{
  "type": "Feature",
  "properties": {
    "iso:country":"GB",
    "wof:name":"TA8 2HE",
    "wof:placetype":"postalcode"
},
  "geometry": {"coordinates":[-2.99873725105355,51.24369373936501],"type":"Point"}
}