{
  "type": "Feature",
  "properties": {
    "iso:country": "GB",
    "wof:name": "NR16 2TW",
    "wof:placetype": "postalcode"
  },
  "geometry": {"coordinates":[0.909689,52.450365],"type":"Point"}
}
