{
  "type": "Feature",
  "properties": {
    "date:inception_lower":"2014-04-01",
    "date:inception_upper":"2014-04-30",
    "iso:country":"GB",
    "wof:name":"NR16 2TW",
    "wof:placetype":"postalcode"
},
  "geometry": {"coordinates":[0.909689,52.450365],"type":"Point"}
}