{
  "type": "Feature",
  "properties": {
    "iso:country": "GB",
    "wof:name": "NE63 0BN",
    "wof:placetype": "postalcode"
  },
  "geometry": {"coordinates":[-1.565335,55.183066],"type":"Point"}
}
