{
  "type": "Feature",
  "properties": {
    "iso:country":"GB",
    "wof:name":"NE63 0BN",
    "wof:placetype":"postalcode"
},
  "geometry": {"coordinates":[-1.56533520275384,55.18306622142747],"type":"Point"}
}