{
  "type": "Feature",
  "properties": {
    "iso:country":"GB",
    "wof:name":"NE15 0BL",
    "wof:placetype":"postalcode"
},
  "geometry": {"coordinates":[-1.79991678984767,54.99516699559376],"type":"Point"}
}