{
  "type": "Feature",
  "properties": {
    "date:inception_lower":"1980-01-01",
    "date:inception_upper":"1980-01-31",
    "iso:country":"GB",
    "wof:name":"NE15 0BL",
    "wof:placetype":"postalcode"
},
  "geometry": {"coordinates":[-1.799917,54.995167],"type":"Point"}
}