{
  "type": "Feature",
  "properties": {
    "iso:country": "GB",
    "wof:name": "NE15 0BL",
    "wof:placetype": "postalcode"
  },
  "geometry": {"coordinates":[-1.799917,54.995167],"type":"Point"}
}
