{
  "type": "Feature",
  "properties": {
    "iso:country":"GB",
    "wof:name":"LA4 4ND",
    "wof:placetype":"postalcode"
},
  "geometry": {"coordinates":[-2.87005676830317,54.06446987801886],"type":"Point"}
}