{
  "type": "Feature",
  "properties": {
    "iso:country": "GB",
    "wof:name": "LA4 4ND",
    "wof:placetype": "postalcode"
  },
  "geometry": {"coordinates":[-2.870057,54.06447],"type":"Point"}
}
