{
  "type": "Feature",
  "properties": {
    "date:inception_lower": "1980-01-01",
    "date:inception_upper": "1980-01-01",
    "iso:country": "GB",
    "wof:name": "LA4 4ND",
    "wof:placetype": "postalcode"
  },
  "geometry": {"coordinates":[-2.870057,54.06447],"type":"Point"}
}
