{
  "type": "Feature",
  "properties": {
    "iso:country":"GB",
    "wof:name":"RG9 1QD",
    "wof:placetype":"postalcode"
},
  "geometry": {"coordinates":[-0.91708009650851,51.527519512048],"type":"Point"}
}