{
  "type": "Feature",
  "properties": {
    "iso:country":"GB",
    "wof:name":"RH6 8HT",
    "wof:placetype":"postalcode"
},
  "geometry": {"coordinates":[-0.17324990351767,51.18555669026655],"type":"Point"}
}