{
  "type": "Feature",
  "properties": {
    "iso:country": "GB",
    "wof:name": "RH6 8HT",
    "wof:placetype": "postalcode"
  },
  "geometry": {"coordinates":[-0.17325,51.185557],"type":"Point"}
}
