{
  "type": "Feature",
  "properties": {
    "iso:country":"GB",
    "wof:name":"CO12 3PJ",
    "wof:placetype":"postalcode"
},
  "geometry": {"coordinates":[1.27613536572356,51.9358303281651],"type":"Point"}
}