{
  "type": "Feature",
  "properties": {
    "date:inception_lower":"1992-08-01",
    "date:inception_upper":"1992-08-31",
    "iso:country":"GB",
    "wof:name":"DE21 6BX",
    "wof:placetype":"postalcode"
},
  "geometry": {"coordinates":[-1.459166,52.932843],"type":"Point"}
}