{
  "type": "Feature",
  "properties": {
    "date:inception_lower":"1980-01-01",
    "date:inception_upper":"1980-01-31",
    "iso:country":"GB",
    "wof:name":"LS25 6DF",
    "wof:placetype":"postalcode"
},
  "geometry": {"coordinates":[-1.246931,53.800189],"type":"Point"}
}