{
  "type": "Feature",
  "properties": {
    "iso:country": "GB",
    "wof:name": "LS25 6DF",
    "wof:placetype": "postalcode"
  },
  "geometry": {"coordinates":[-1.246931,53.800189],"type":"Point"}
}
