{
  "type": "Feature",
  "properties": {
    "iso:country":"GB",
    "wof:name":"LS25 6DF",
    "wof:placetype":"postalcode"
},
  "geometry": {"coordinates":[-1.2469313406467,53.80018892088222],"type":"Point"}
}