{
  "type": "Feature",
  "properties": {
    "iso:country":"GB",
    "wof:name":"DA8 1QA",
    "wof:placetype":"postalcode"
},
  "geometry": {"coordinates":[0.15917552527773,51.48304189138335],"type":"Point"}
}