{
  "type": "Feature",
  "properties": {
    "iso:country": "GB",
    "wof:name": "DL15 0SZ",
    "wof:placetype": "postalcode"
  },
  "geometry": {"coordinates":[-1.686468,54.724239],"type":"Point"}
}
