{
  "type": "Feature",
  "properties": {
    "iso:country":"GB",
    "wof:name":"DL15 0SZ",
    "wof:placetype":"postalcode"
},
  "geometry": {"coordinates":[-1.68646821481332,54.72423918385035],"type":"Point"}
}