{
  "type": "Feature",
  "properties": {
    "date:inception_lower": "1980-01-01",
    "date:inception_upper": "1980-01-01",
    "iso:country": "GB",
    "wof:name": "SO21 2JT",
    "wof:placetype": "postalcode"
  },
  "geometry": {"coordinates":[-1.38904,51.02638],"type":"Point"}
}
