{
  "type": "Feature",
  "properties": {
    "iso:country": "GB",
    "wof:name": "SO21 2JT",
    "wof:placetype": "postalcode"
  },
  "geometry": {"coordinates":[-1.38904,51.02638],"type":"Point"}
}
