{
  "type": "Feature",
  "properties": {
    "iso:country": "GB",
    "wof:name": "SY18 6HB",
    "wof:placetype": "postalcode"
  },
  "geometry": {"coordinates":[-3.545567,52.455315],"type":"Point"}
}
