{
  "type": "Feature",
  "properties": {
    "date:inception_lower": "1993-08-01",
    "date:inception_upper": "1993-08-01",
    "iso:country": "GB",
    "wof:name": "WR2 5QF",
    "wof:placetype": "postalcode"
  },
  "geometry": {"coordinates":[-2.25714,52.194652],"type":"Point"}
}
