{
  "type": "Feature",
  "properties": {
    "iso:country":"GB",
    "wof:name":"WR2 5QF",
    "wof:placetype":"postalcode"
},
  "geometry": {"coordinates":[-2.25720224649991,52.1946028899349],"type":"Point"}
}