{
  "type": "Feature",
  "properties": {
    "iso:country": "GB",
    "wof:name": "WR2 5QF",
    "wof:placetype": "postalcode"
  },
  "geometry": {"coordinates":[-2.25714,52.194652],"type":"Point"}
}
