{
  "type": "Feature",
  "properties": {
    "iso:country":"GB",
    "wof:name":"BL1 4RR",
    "wof:placetype":"postalcode"
},
  "geometry": {"coordinates":[-2.44958697116364,53.57769495451178],"type":"Point"}
}