{
  "type": "Feature",
  "properties": {
    "iso:country": "GB",
    "wof:name": "TN12 0LJ",
    "wof:placetype": "postalcode"
  },
  "geometry": {"coordinates":[0.548079,51.162928],"type":"Point"}
}
