{
  "type": "Feature",
  "properties": {
    "iso:country":"GB",
    "wof:name":"NG1 5EF",
    "wof:placetype":"postalcode"
},
  "geometry": {"coordinates":[-1.15928823382941,52.95381696341298],"type":"Point"}
}