{
  "type": "Feature",
  "properties": {
    "date:inception_lower": "2021-03-01",
    "date:inception_upper": "2021-03-01",
    "iso:country": "GB",
    "wof:name": "GL3 1GF",
    "wof:placetype": "postalcode"
  },
  "geometry": {"coordinates":[-2.196991,51.881896],"type":"Point"}
}
