{
  "type": "Feature",
  "properties": {
    "iso:country":"GB",
    "wof:name":"SW11 5JA",
    "wof:placetype":"postalcode"
},
  "geometry": {"coordinates":[-0.15403033344353,51.47333760648258],"type":"Point"}
}