{
  "type": "Feature",
  "properties": {
    "iso:country": "GB",
    "wof:name": "NP7 8SE",
    "wof:placetype": "postalcode"
  },
  "geometry": {"coordinates":[-2.939719,51.824973],"type":"Point"}
}
