{
  "type": "Feature",
  "properties": {
    "iso:country":"GB",
    "wof:name":"NP7 8SE",
    "wof:placetype":"postalcode"
},
  "geometry": {"coordinates":[-2.93971937163239,51.82497336722367],"type":"Point"}
}