{
  "type": "Feature",
  "properties": {
    "date:inception_lower": "1980-01-01",
    "date:inception_upper": "1980-01-01",
    "iso:country": "GB",
    "wof:name": "NE47 5AT",
    "wof:placetype": "postalcode"
  },
  "geometry": {"coordinates":[-2.210997,55.010325],"type":"Point"}
}
