{
  "type": "Feature",
  "properties": {
    "iso:country":"GB",
    "wof:name":"SA43 2TL",
    "wof:placetype":"postalcode"
},
  "geometry": {"coordinates":[-4.63021599235305,52.0387248761696],"type":"Point"}
}