{
  "type": "Feature",
  "properties": {
    "iso:country":"GB",
    "wof:name":"NE4 5DX",
    "wof:placetype":"postalcode"
},
  "geometry": {"coordinates":[-1.63174348300852,54.97529239871736],"type":"Point"}
}