{
  "type": "Feature",
  "properties": {
    "iso:country":"GB",
    "wof:name":"GL52 3BG",
    "wof:placetype":"postalcode"
},
  "geometry": {"coordinates":[-2.04564848713598,51.91529383740209],"type":"Point"}
}