{
  "type": "Feature",
  "properties": {
    "iso:country": "GB",
    "wof:name": "DY6 7XT",
    "wof:placetype": "postalcode"
  },
  "geometry": {"coordinates":[-2.153466,52.50436],"type":"Point"}
}
