{
  "type": "Feature",
  "properties": {
    "iso:country":"GB",
    "wof:name":"GU33 7BX",
    "wof:placetype":"postalcode"
},
  "geometry": {"coordinates":[-0.88468010345099,51.05719613078357],"type":"Point"}
}