{
  "type": "Feature",
  "properties": {
    "iso:country": "GB",
    "wof:name": "GU33 7BX",
    "wof:placetype": "postalcode"
  },
  "geometry": {"coordinates":[-0.88468,51.057196],"type":"Point"}
}
