{
  "type": "Feature",
  "properties": {
    "iso:country": "GB",
    "wof:name": "BS3 2JP",
    "wof:placetype": "postalcode"
  },
  "geometry": {"coordinates":[-2.631499,51.442002],"type":"Point"}
}
