{
  "type": "Feature",
  "properties": {
    "date:inception_lower":"1980-01-01",
    "date:inception_upper":"1980-01-31",
    "iso:country":"GB",
    "wof:name":"BS3 2JP",
    "wof:placetype":"postalcode"
},
  "geometry": {"coordinates":[-2.631499,51.442002],"type":"Point"}
}