{
  "type": "Feature",
  "properties": {
    "iso:country":"GB",
    "wof:name":"BR1 1JW",
    "wof:placetype":"postalcode"
},
  "geometry": {"coordinates":[0.01560078003783,51.4031611060168],"type":"Point"}
}