{
  "type": "Feature",
  "properties": {
    "date:inception_lower":"1980-01-01",
    "date:inception_upper":"1980-01-31",
    "iso:country":"GB",
    "wof:name":"BR1 1JW",
    "wof:placetype":"postalcode"
},
  "geometry": {"coordinates":[0.015543,51.402883],"type":"Point"}
}