{
  "type": "Feature",
  "properties": {
    "iso:country":"GB",
    "wof:name":"EH16 6PN",
    "wof:placetype":"postalcode"
},
  "geometry": {"coordinates":[-3.1640315881014,55.90070426772182],"type":"Point"}
}