{
  "type": "Feature",
  "properties": {
    "date:inception_lower": "1981-06-01",
    "date:inception_upper": "1981-06-01",
    "iso:country": "GB",
    "wof:name": "SN16 9PD",
    "wof:placetype": "postalcode"
  },
  "geometry": {"coordinates":[-2.062209,51.579712],"type":"Point"}
}
