{
  "type": "Feature",
  "properties": {
    "iso:country": "GB",
    "wof:name": "YO24 4FA",
    "wof:placetype": "postalcode"
  },
  "geometry": {"coordinates":[-1.120107,53.945581],"type":"Point"}
}
