{
  "type": "Feature",
  "properties": {
    "iso:country":"GB",
    "wof:name":"CB9 0DS",
    "wof:placetype":"postalcode"
},
  "geometry": {"coordinates":[0.43604281523194,52.08855023706553],"type":"Point"}
}