{
  "type": "Feature",
  "properties": {
    "date:inception_lower":"1980-01-01",
    "date:inception_upper":"1980-01-31",
    "iso:country":"GB",
    "wof:name":"SK11 7UY",
    "wof:placetype":"postalcode"
},
  "geometry": {"coordinates":[-2.151159,53.244098],"type":"Point"}
}