{
  "type": "Feature",
  "properties": {
    "iso:country":"GB",
    "wof:name":"SN14 0DP",
    "wof:placetype":"postalcode"
},
  "geometry": {"coordinates":[-2.13068510564382,51.45899945943056],"type":"Point"}
}