{
  "type": "Feature",
  "properties": {
    "date:inception_lower": "1980-01-01",
    "date:inception_upper": "1980-01-01",
    "iso:country": "GB",
    "wof:name": "SN14 0DP",
    "wof:placetype": "postalcode"
  },
  "geometry": {"coordinates":[-2.130685,51.458999],"type":"Point"}
}
