{
  "type": "Feature",
  "properties": {
    "iso:country":"GB",
    "wof:name":"E2 6LN",
    "wof:placetype":"postalcode"
},
  "geometry": {"coordinates":[-0.0615630331004,51.52853477911727],"type":"Point"}
}