{
  "type": "Feature",
  "properties": {
    "iso:country":"GB",
    "wof:name":"OL4 1JT",
    "wof:placetype":"postalcode"
},
  "geometry": {"coordinates":[-2.09605670411881,53.542737372666],"type":"Point"}
}