{
  "type": "Feature",
  "properties": {
    "iso:country":"GB",
    "wof:name":"CT6 5HR",
    "wof:placetype":"postalcode"
},
  "geometry": {"coordinates":[1.13378820401968,51.37151102043897],"type":"Point"}
}