{
  "type": "Feature",
  "properties": {
    "iso:country":"GB",
    "wof:name":"TA8 1JP",
    "wof:placetype":"postalcode"
},
  "geometry": {"coordinates":[-2.97894262289348,51.22905992769725],"type":"Point"}
}