{
  "type": "Feature",
  "properties": {
    "date:inception_lower":"2002-06-01",
    "date:inception_upper":"2002-06-30",
    "iso:country":"GB",
    "wof:name":"IV30 5GE",
    "wof:placetype":"postalcode"
},
  "geometry": {"coordinates":[-3.474635,57.700633],"type":"Point"}
}