{
  "type": "Feature",
  "properties": {
    "iso:country":"GB",
    "wof:name":"IV30 5GE",
    "wof:placetype":"postalcode"
},
  "geometry": {"coordinates":[-3.47463475688133,57.70063289213534],"type":"Point"}
}