{
  "type": "Feature",
  "properties": {
    "iso:country":"GB",
    "wof:name":"SO22 6LP",
    "wof:placetype":"postalcode"
},
  "geometry": {"coordinates":[-1.33908685037549,51.08081745964731],"type":"Point"}
}