{
  "type": "Feature",
  "properties": {
    "date:inception_lower": "2001-12-01",
    "date:inception_upper": "2001-12-01",
    "iso:country": "GB",
    "wof:name": "SY1 1JF",
    "wof:placetype": "postalcode"
  },
  "geometry": {"coordinates":[-2.757894,52.705615],"type":"Point"}
}
