{
  "type": "Feature",
  "properties": {
    "date:inception_lower": "1980-01-01",
    "date:inception_upper": "1980-01-01",
    "iso:country": "GB",
    "wof:name": "BS20 8EY",
    "wof:placetype": "postalcode"
  },
  "geometry": {"coordinates":[-2.804812,51.478319],"type":"Point"}
}
