{
  "type": "Feature",
  "properties": {
    "iso:country": "GB",
    "wof:name": "BS20 8EY",
    "wof:placetype": "postalcode"
  },
  "geometry": {"coordinates":[-2.804694,51.478411],"type":"Point"}
}
