{
  "type": "Feature",
  "properties": {
    "iso:country":"GB",
    "wof:name":"BS20 8EY",
    "wof:placetype":"postalcode"
},
  "geometry": {"coordinates":[-2.80469385530033,51.47841119697976],"type":"Point"}
}