{
  "type": "Feature",
  "properties": {
    "iso:country": "GB",
    "wof:name": "SG1 1PW",
    "wof:placetype": "postalcode"
  },
  "geometry": {"coordinates":[-0.189113,51.904971],"type":"Point"}
}
