{
  "type": "Feature",
  "properties": {
    "date:inception_lower": "1980-01-01",
    "date:inception_upper": "1980-01-01",
    "iso:country": "GB",
    "wof:name": "NE10 0BH",
    "wof:placetype": "postalcode"
  },
  "geometry": {"coordinates":[-1.571772,54.951408],"type":"Point"}
}
