{
  "type": "Feature",
  "properties": {
    "iso:country": "GB",
    "wof:name": "M8 9ER",
    "wof:placetype": "postalcode"
  },
  "geometry": {"coordinates":[-2.242658,53.508356],"type":"Point"}
}
