{
  "type": "Feature",
  "properties": {
    "iso:country":"GB",
    "wof:name":"SA1 6NQ",
    "wof:placetype":"postalcode"
},
  "geometry": {"coordinates":[-3.96154370863485,51.62586371881546],"type":"Point"}
}