{
  "type": "Feature",
  "properties": {
    "date:inception_lower": "1980-01-01",
    "date:inception_upper": "1980-01-01",
    "iso:country": "GB",
    "wof:name": "SA1 6NQ",
    "wof:placetype": "postalcode"
  },
  "geometry": {"coordinates":[-3.961577,51.625868],"type":"Point"}
}
