{
  "type": "Feature",
  "properties": {
    "iso:country":"GB",
    "wof:name":"LL16 4YG",
    "wof:placetype":"postalcode"
},
  "geometry": {"coordinates":[-3.33634907697987,53.17495115383745],"type":"Point"}
}