{
  "type": "Feature",
  "properties": {
    "date:inception_lower": "1980-01-01",
    "date:inception_upper": "1980-01-01",
    "iso:country": "GB",
    "wof:name": "LL16 4YG",
    "wof:placetype": "postalcode"
  },
  "geometry": {"coordinates":[-3.336349,53.174951],"type":"Point"}
}
