{
  "type": "Feature",
  "properties": {
    "date:inception_lower": "1980-01-01",
    "date:inception_upper": "1980-01-01",
    "iso:country": "GB",
    "wof:name": "DN4 0BD",
    "wof:placetype": "postalcode"
  },
  "geometry": {"coordinates":[-1.146604,53.518349],"type":"Point"}
}
