{
  "type": "Feature",
  "properties": {
    "iso:country":"GB",
    "wof:name":"DN4 0BD",
    "wof:placetype":"postalcode"
},
  "geometry": {"coordinates":[-1.14660355170177,53.51834914883239],"type":"Point"}
}