{
  "type": "Feature",
  "properties": {
    "iso:country": "GB",
    "wof:name": "HR2 9SY",
    "wof:placetype": "postalcode"
  },
  "geometry": {"coordinates":[-2.80105,52.030078],"type":"Point"}
}
