{
  "type": "Feature",
  "properties": {
    "iso:country":"GB",
    "wof:name":"YO1 9NF",
    "wof:placetype":"postalcode"
},
  "geometry": {"coordinates":[-1.08223339385895,53.95754863144608],"type":"Point"}
}