{
  "type": "Feature",
  "properties": {
    "iso:country": "GB",
    "wof:name": "B17 0RB",
    "wof:placetype": "postalcode"
  },
  "geometry": {"coordinates":[-1.96351,52.448788],"type":"Point"}
}
