{
  "type": "Feature",
  "properties": {
    "iso:country":"GB",
    "wof:name":"RM6 5BL",
    "wof:placetype":"postalcode"
},
  "geometry": {"coordinates":[0.13004422213891,51.58262159662792],"type":"Point"}
}