{
  "type": "Feature",
  "properties": {
    "date:inception_lower": "1980-01-01",
    "date:inception_upper": "1980-01-01",
    "iso:country": "GB",
    "wof:name": "NP7 8LY",
    "wof:placetype": "postalcode"
  },
  "geometry": {"coordinates":[-2.846482,51.872909],"type":"Point"}
}
