{
  "type": "Feature",
  "properties": {
    "iso:country":"GB",
    "wof:name":"NP7 8LY",
    "wof:placetype":"postalcode"
},
  "geometry": {"coordinates":[-2.84575740796787,51.87323204230355],"type":"Point"}
}