{
  "type": "Feature",
  "properties": {
    "iso:country": "GB",
    "wof:name": "NP7 8LY",
    "wof:placetype": "postalcode"
  },
  "geometry": {"coordinates":[-2.845757,51.873232],"type":"Point"}
}
