{
  "type": "Feature",
  "properties": {
    "date:inception_lower":"1980-01-01",
    "date:inception_upper":"1980-01-31",
    "iso:country":"GB",
    "wof:name":"NP7 8LY",
    "wof:placetype":"postalcode"
},
  "geometry": {"coordinates":[-2.845757,51.873232],"type":"Point"}
}