{
  "type": "Feature",
  "properties": {
    "iso:country":"GB",
    "wof:name":"S66 1WL",
    "wof:placetype":"postalcode"
},
  "geometry": {"coordinates":[-1.25873882487906,53.41887304312298],"type":"Point"}
}