{
  "type": "Feature",
  "properties": {
    "iso:country":"GB",
    "wof:name":"LU3 2DS",
    "wof:placetype":"postalcode"
},
  "geometry": {"coordinates":[-0.42842673329533,51.91597212036052],"type":"Point"}
}