{
  "type": "Feature",
  "properties": {
    "iso:country": "GB",
    "wof:name": "OL8 2BD",
    "wof:placetype": "postalcode"
  },
  "geometry": {"coordinates":[-2.098057,53.53355],"type":"Point"}
}
