{
  "type": "Feature",
  "properties": {
    "iso:country":"GB",
    "wof:name":"OL8 2BD",
    "wof:placetype":"postalcode"
},
  "geometry": {"coordinates":[-2.09805751661722,53.53354964927344],"type":"Point"}
}