{
  "type": "Feature",
  "properties": {
    "iso:country":"GB",
    "wof:name":"SL6 4QU",
    "wof:placetype":"postalcode"
},
  "geometry": {"coordinates":[-0.74551617375031,51.5172054239155],"type":"Point"}
}