{
  "type": "Feature",
  "properties": {
    "iso:country": "GB",
    "wof:name": "SA71 4AP",
    "wof:placetype": "postalcode"
  },
  "geometry": {"coordinates":[-4.904414,51.673577],"type":"Point"}
}
