{
  "type": "Feature",
  "properties": {
    "iso:country": "GB",
    "wof:name": "NR17 2NB",
    "wof:placetype": "postalcode"
  },
  "geometry": {"coordinates":[1.024818,52.517883],"type":"Point"}
}
