{
  "type": "Feature",
  "properties": {
    "iso:country":"GB",
    "wof:name":"NR17 2NB",
    "wof:placetype":"postalcode"
},
  "geometry": {"coordinates":[1.02481752897744,52.51788251821061],"type":"Point"}
}