{
  "type": "Feature",
  "properties": {
    "iso:country":"GB",
    "wof:name":"NR35 1HD",
    "wof:placetype":"postalcode"
},
  "geometry": {"coordinates":[1.43887424949915,52.45698007724604],"type":"Point"}
}