{
  "type": "Feature",
  "properties": {
    "iso:country":"GB",
    "wof:name":"EC4N 8AF",
    "wof:placetype":"postalcode"
},
  "geometry": {"coordinates":[-0.09038151206083,51.51202054212926],"type":"Point"}
}