{
  "type": "Feature",
  "properties": {
    "iso:country": "GB",
    "wof:name": "EC4N 8AF",
    "wof:placetype": "postalcode"
  },
  "geometry": {"coordinates":[-0.090177,51.512154],"type":"Point"}
}
