{
  "type": "Feature",
  "properties": {
    "iso:country": "GB",
    "wof:name": "PE14 0JQ",
    "wof:placetype": "postalcode"
  },
  "geometry": {"coordinates":[0.169422,52.637906],"type":"Point"}
}
