{
  "type": "Feature",
  "properties": {
    "date:inception_lower": "2004-05-01",
    "date:inception_upper": "2004-05-01",
    "iso:country": "GB",
    "wof:name": "PE14 0JQ",
    "wof:placetype": "postalcode"
  },
  "geometry": {"coordinates":[0.167664,52.638227],"type":"Point"}
}
