{
  "type": "Feature",
  "properties": {
    "date:inception_lower": "2022-04-01",
    "date:inception_upper": "2022-04-01",
    "iso:country": "GB",
    "wof:name": "WR5 3DS",
    "wof:placetype": "postalcode"
  },
  "geometry": {"coordinates":[-2.218367,52.184867],"type":"Point"}
}
