{
  "type": "Feature",
  "properties": {
    "iso:country":"GB",
    "wof:name":"TW18 1JN",
    "wof:placetype":"postalcode"
},
  "geometry": {"coordinates":[-0.48587098073033,51.42379687873145],"type":"Point"}
}