{
  "type": "Feature",
  "properties": {
    "iso:country": "GB",
    "wof:name": "TW18 1JN",
    "wof:placetype": "postalcode"
  },
  "geometry": {"coordinates":[-0.485871,51.423797],"type":"Point"}
}
