{
  "type": "Feature",
  "properties": {
    "iso:country":"GB",
    "wof:name":"BS27 3EU",
    "wof:placetype":"postalcode"
},
  "geometry": {"coordinates":[-2.78176426613824,51.28164519951037],"type":"Point"}
}