{
  "type": "Feature",
  "properties": {
    "date:inception_lower": "2008-02-01",
    "date:inception_upper": "2008-02-01",
    "iso:country": "GB",
    "wof:name": "BS27 3EU",
    "wof:placetype": "postalcode"
  },
  "geometry": {"coordinates":[-2.781764,51.281645],"type":"Point"}
}
