{
  "type": "Feature",
  "properties": {
    "iso:country": "GB",
    "wof:name": "BS27 3EU",
    "wof:placetype": "postalcode"
  },
  "geometry": {"coordinates":[-2.781764,51.281645],"type":"Point"}
}
