{
  "type": "Feature",
  "properties": {
    "iso:country":"GB",
    "wof:name":"TN16 3HS",
    "wof:placetype":"postalcode"
},
  "geometry": {"coordinates":[0.04317405692805,51.30592849162018],"type":"Point"}
}