{
  "type": "Feature",
  "properties": {
    "iso:country":"GB",
    "wof:name":"HX6 4QA",
    "wof:placetype":"postalcode"
},
  "geometry": {"coordinates":[-1.95005245945803,53.66341512387802],"type":"Point"}
}