{
  "type": "Feature",
  "properties": {
    "iso:country":"GB",
    "wof:name":"DT2 8SP",
    "wof:placetype":"postalcode"
},
  "geometry": {"coordinates":[-2.33205803541218,50.73938527488311],"type":"Point"}
}