{
  "type": "Feature",
  "properties": {
    "iso:country": "GB",
    "wof:name": "SO16 3HX",
    "wof:placetype": "postalcode"
  },
  "geometry": {"coordinates":[-1.405756,50.941606],"type":"Point"}
}
