{
  "type": "Feature",
  "properties": {
    "iso:country":"GB",
    "wof:name":"W8 7LE",
    "wof:placetype":"postalcode"
},
  "geometry": {"coordinates":[-0.20094221459049,51.50740186629628],"type":"Point"}
}