{
  "type": "Feature",
  "properties": {
    "date:inception_lower": "2016-06-01",
    "date:inception_upper": "2016-06-01",
    "iso:country": "GB",
    "wof:name": "SO21 1FQ",
    "wof:placetype": "postalcode"
  },
  "geometry": {"coordinates":[-1.312222,50.991191],"type":"Point"}
}
