{
  "type": "Feature",
  "properties": {
    "iso:country":"GB",
    "wof:name":"PO2 0UY",
    "wof:placetype":"postalcode"
},
  "geometry": {"coordinates":[-1.06863599885534,50.82904625302548],"type":"Point"}
}