{
  "type": "Feature",
  "properties": {
    "date:inception_lower":"1980-01-01",
    "date:inception_upper":"1980-01-31",
    "iso:country":"GB",
    "wof:name":"PO2 0UY",
    "wof:placetype":"postalcode"
},
  "geometry": {"coordinates":[-1.068636,50.829046],"type":"Point"}
}