{
  "type": "Feature",
  "properties": {
    "iso:country":"GB",
    "wof:name":"BB5 1HS",
    "wof:placetype":"postalcode"
},
  "geometry": {"coordinates":[-2.36366733189698,53.75165735264729],"type":"Point"}
}