{
  "type": "Feature",
  "properties": {
    "date:inception_lower": "1980-01-01",
    "date:inception_upper": "1980-01-01",
    "iso:country": "GB",
    "wof:name": "BB5 1HS",
    "wof:placetype": "postalcode"
  },
  "geometry": {"coordinates":[-2.363697,53.751645],"type":"Point"}
}
