{
  "type": "Feature",
  "properties": {
    "iso:country": "GB",
    "wof:name": "NG20 9BP",
    "wof:placetype": "postalcode"
  },
  "geometry": {"coordinates":[-1.204809,53.233114],"type":"Point"}
}
