{
  "type": "Feature",
  "properties": {
    "iso:country":"GB",
    "wof:name":"WN1 2LZ",
    "wof:placetype":"postalcode"
},
  "geometry": {"coordinates":[-2.62592676962153,53.55608467338062],"type":"Point"}
}