{
  "type": "Feature",
  "properties": {
    "iso:country": "GB",
    "wof:name": "IP31 1ES",
    "wof:placetype": "postalcode"
  },
  "geometry": {"coordinates":[0.780693,52.314792],"type":"Point"}
}
