{
  "type": "Feature",
  "properties": {
    "iso:country":"GB",
    "wof:name":"KT1 1EG",
    "wof:placetype":"postalcode"
},
  "geometry": {"coordinates":[-0.30296255893568,51.41005086126237],"type":"Point"}
}