{
  "type": "Feature",
  "properties": {
    "date:inception_lower": "1980-01-01",
    "date:inception_upper": "1980-01-01",
    "iso:country": "GB",
    "wof:name": "KT1 1EG",
    "wof:placetype": "postalcode"
  },
  "geometry": {"coordinates":[-0.30277,51.410012],"type":"Point"}
}
