{
  "type": "Feature",
  "properties": {
    "iso:country":"GB",
    "wof:name":"WD6 3JF",
    "wof:placetype":"postalcode"
},
  "geometry": {"coordinates":[-0.27966415576808,51.64538224867572],"type":"Point"}
}