{
  "type": "Feature",
  "properties": {
    "iso:country":"GB",
    "wof:name":"PH2 9BL",
    "wof:placetype":"postalcode"
},
  "geometry": {"coordinates":[-3.40388968744388,56.34083850243511],"type":"Point"}
}