{
  "type": "Feature",
  "properties": {
    "iso:country":"GB",
    "wof:name":"NE19 1AG",
    "wof:placetype":"postalcode"
},
  "geometry": {"coordinates":[-2.1411936660337,55.24026981028977],"type":"Point"}
}