{
  "type": "Feature",
  "properties": {
    "date:inception_lower":"1980-01-01",
    "date:inception_upper":"1980-01-31",
    "iso:country":"GB",
    "wof:name":"NE19 1AG",
    "wof:placetype":"postalcode"
},
  "geometry": {"coordinates":[-2.141202,55.240273],"type":"Point"}
}