{
  "type": "Feature",
  "properties": {
    "iso:country": "GB",
    "wof:name": "NE19 1AG",
    "wof:placetype": "postalcode"
  },
  "geometry": {"coordinates":[-2.141202,55.240273],"type":"Point"}
}
