{
  "type": "Feature",
  "properties": {
    "iso:country":"GB",
    "wof:name":"EH32 0BT",
    "wof:placetype":"postalcode"
},
  "geometry": {"coordinates":[-2.95575459430759,55.96854779339462],"type":"Point"}
}