{
  "type": "Feature",
  "properties": {
    "iso:country":"GB",
    "wof:name":"WV10 0SX",
    "wof:placetype":"postalcode"
},
  "geometry": {"coordinates":[-2.0989985838839,52.60778344318568],"type":"Point"}
}