{
  "type": "Feature",
  "properties": {
    "iso:country":"GB",
    "wof:name":"NE63 9JH",
    "wof:placetype":"postalcode"
},
  "geometry": {"coordinates":[-1.55717767167396,55.1851306251845],"type":"Point"}
}