{
  "type": "Feature",
  "properties": {
    "iso:country":"GB",
    "wof:name":"SO51 0NE",
    "wof:placetype":"postalcode"
},
  "geometry": {"coordinates":[-1.50739484778014,51.01919638651142],"type":"Point"}
}