{
  "type": "Feature",
  "properties": {
    "iso:country":"GB",
    "wof:name":"CF82 7JE",
    "wof:placetype":"postalcode"
},
  "geometry": {"coordinates":[-3.23463568108467,51.66017321520722],"type":"Point"}
}