{
  "type": "Feature",
  "properties": {
    "iso:country":"GB",
    "wof:name":"HX2 8EQ",
    "wof:placetype":"postalcode"
},
  "geometry": {"coordinates":[-1.89325946333827,53.74641016415272],"type":"Point"}
}