{
  "type": "Feature",
  "properties": {
    "iso:country":"GB",
    "wof:name":"SL7 1DF",
    "wof:placetype":"postalcode"
},
  "geometry": {"coordinates":[-0.77652617499071,51.57225733893777],"type":"Point"}
}