{
  "type": "Feature",
  "properties": {
    "iso:country": "GB",
    "wof:name": "SL7 1DF",
    "wof:placetype": "postalcode"
  },
  "geometry": {"coordinates":[-0.776637,51.57228],"type":"Point"}
}
