{
  "type": "Feature",
  "properties": {
    "iso:country":"GB",
    "wof:name":"WA5 3EH",
    "wof:placetype":"postalcode"
},
  "geometry": {"coordinates":[-2.65691817643831,53.39327839670961],"type":"Point"}
}