{
  "type": "Feature",
  "properties": {
    "iso:country":"GB",
    "wof:name":"TQ7 2LG",
    "wof:placetype":"postalcode"
},
  "geometry": {"coordinates":[-3.69573995676842,50.27194459701234],"type":"Point"}
}