{
  "type": "Feature",
  "properties": {
    "iso:country": "GB",
    "wof:name": "TQ7 2LG",
    "wof:placetype": "postalcode"
  },
  "geometry": {"coordinates":[-3.69574,50.271945],"type":"Point"}
}
