{
  "type": "Feature",
  "properties": {
    "iso:country":"GB",
    "wof:name":"LL31 9SZ",
    "wof:placetype":"postalcode"
},
  "geometry": {"coordinates":[-3.79625809134723,53.28709415013464],"type":"Point"}
}