{
  "type": "Feature",
  "properties": {
    "iso:country": "GB",
    "wof:name": "NG22 9FP",
    "wof:placetype": "postalcode"
  },
  "geometry": {"coordinates":[-1.008998,53.199367],"type":"Point"}
}
