{
  "type": "Feature",
  "properties": {
    "iso:country":"GB",
    "wof:name":"SY5 0UT",
    "wof:placetype":"postalcode"
},
  "geometry": {"coordinates":[-2.88974387217369,52.64914389147018],"type":"Point"}
}