{
  "type": "Feature",
  "properties": {
    "date:inception_lower": "1980-01-01",
    "date:inception_upper": "1980-01-01",
    "iso:country": "GB",
    "wof:name": "B3 3BY",
    "wof:placetype": "postalcode"
  },
  "geometry": {"coordinates":[-1.903475,52.481691],"type":"Point"}
}
