{
  "type": "Feature",
  "properties": {
    "date:inception_lower": "1985-04-01",
    "date:inception_upper": "1985-04-01",
    "iso:country": "GB",
    "wof:name": "IP14 3SA",
    "wof:placetype": "postalcode"
  },
  "geometry": {"coordinates":[0.970258,52.220637],"type":"Point"}
}
