{
  "type": "Feature",
  "properties": {
    "iso:country":"GB",
    "wof:name":"OX2 9RL",
    "wof:placetype":"postalcode"
},
  "geometry": {"coordinates":[-1.33014189053839,51.73206555744124],"type":"Point"}
}