{
  "type": "Feature",
  "properties": {
    "date:inception_lower":"1990-07-01",
    "date:inception_upper":"1990-07-31",
    "iso:country":"GB",
    "wof:name":"OX2 9RL",
    "wof:placetype":"postalcode"
},
  "geometry": {"coordinates":[-1.330142,51.732066],"type":"Point"}
}