{
  "type": "Feature",
  "properties": {
    "iso:country": "GB",
    "wof:name": "OX2 9RL",
    "wof:placetype": "postalcode"
  },
  "geometry": {"coordinates":[-1.330142,51.732066],"type":"Point"}
}
