{
  "type": "Feature",
  "properties": {
    "iso:country":"GB",
    "wof:name":"NW9 7BS",
    "wof:placetype":"postalcode"
},
  "geometry": {"coordinates":[-0.23918168771034,51.57627013668347],"type":"Point"}
}