{
  "type": "Feature",
  "properties": {
    "iso:country": "GB",
    "wof:name": "NW9 7BS",
    "wof:placetype": "postalcode"
  },
  "geometry": {"coordinates":[-0.239182,51.57627],"type":"Point"}
}
