{
  "type": "Feature",
  "properties": {
    "date:inception_lower": "2012-02-01",
    "date:inception_upper": "2012-02-01",
    "iso:country": "GB",
    "wof:name": "NW9 7BS",
    "wof:placetype": "postalcode"
  },
  "geometry": {"coordinates":[-0.239257,51.576275],"type":"Point"}
}
