{
  "type": "Feature",
  "properties": {
    "date:inception_lower": "2018-01-01",
    "date:inception_upper": "2018-01-01",
    "iso:country": "GB",
    "wof:name": "L31 1LS",
    "wof:placetype": "postalcode"
  },
  "geometry": {"coordinates":[-2.917199,53.516621],"type":"Point"}
}
