{
  "type": "Feature",
  "properties": {
    "date:inception_lower": "2006-10-01",
    "date:inception_upper": "2006-10-01",
    "iso:country": "GB",
    "wof:name": "EX39 3NE",
    "wof:placetype": "postalcode"
  },
  "geometry": {"coordinates":[-4.212323,51.028802],"type":"Point"}
}
