{
  "type": "Feature",
  "properties": {
    "iso:country":"GB",
    "wof:name":"EX39 3NE",
    "wof:placetype":"postalcode"
},
  "geometry": {"coordinates":[-4.2124937148127,51.02872203770142],"type":"Point"}
}