{
  "type": "Feature",
  "properties": {
    "iso:country": "GB",
    "wof:name": "EX39 3NE",
    "wof:placetype": "postalcode"
  },
  "geometry": {"coordinates":[-4.212309,51.028802],"type":"Point"}
}
