{
  "type": "Feature",
  "properties": {
    "iso:country":"GB",
    "wof:name":"SG18 8GP",
    "wof:placetype":"postalcode"
},
  "geometry": {"coordinates":[-0.24371884268667,52.09168439563368],"type":"Point"}
}