{
  "type": "Feature",
  "properties": {
    "iso:country": "GB",
    "wof:name": "GU16 6SJ",
    "wof:placetype": "postalcode"
  },
  "geometry": {"coordinates":[-0.702518,51.309128],"type":"Point"}
}
