{
  "type": "Feature",
  "properties": {
    "iso:country": "GB",
    "wof:name": "GL53 8DT",
    "wof:placetype": "postalcode"
  },
  "geometry": {"coordinates":[-2.057601,51.888944],"type":"Point"}
}
