{
  "type": "Feature",
  "properties": {
    "date:inception_lower": "2019-12-01",
    "date:inception_upper": "2019-12-01",
    "iso:country": "GB",
    "wof:name": "GL53 8DT",
    "wof:placetype": "postalcode"
  },
  "geometry": {"coordinates":[-2.057601,51.888944],"type":"Point"}
}
