{
  "type": "Feature",
  "properties": {
    "iso:country":"GB",
    "wof:name":"OX28 6DX",
    "wof:placetype":"postalcode"
},
  "geometry": {"coordinates":[-1.49115596129758,51.78524607198123],"type":"Point"}
}