{
  "type": "Feature",
  "properties": {
    "iso:country": "GB",
    "wof:name": "OX28 6DX",
    "wof:placetype": "postalcode"
  },
  "geometry": {"coordinates":[-1.491156,51.785246],"type":"Point"}
}
