{
  "type": "Feature",
  "properties": {
    "iso:country":"GB",
    "wof:name":"BS21 7HL",
    "wof:placetype":"postalcode"
},
  "geometry": {"coordinates":[-2.85323976216602,51.44161538021891],"type":"Point"}
}