{
  "type": "Feature",
  "properties": {
    "iso:country": "GB",
    "wof:name": "BS21 7HL",
    "wof:placetype": "postalcode"
  },
  "geometry": {"coordinates":[-2.85324,51.441615],"type":"Point"}
}
