{
  "type": "Feature",
  "properties": {
    "date:inception_lower": "1980-01-01",
    "date:inception_upper": "1980-01-01",
    "iso:country": "GB",
    "wof:name": "WV4 5HZ",
    "wof:placetype": "postalcode"
  },
  "geometry": {"coordinates":[-2.15757,52.556028],"type":"Point"}
}
