{
  "type": "Feature",
  "properties": {
    "iso:country":"GB",
    "wof:name":"WV4 5HZ",
    "wof:placetype":"postalcode"
},
  "geometry": {"coordinates":[-2.15757018938016,52.55602847072419],"type":"Point"}
}