{
  "type": "Feature",
  "properties": {
    "iso:country":"GB",
    "wof:name":"DH5 0SF",
    "wof:placetype":"postalcode"
},
  "geometry": {"coordinates":[-1.44742933783316,54.8189228703982],"type":"Point"}
}