{
  "type": "Feature",
  "properties": {
    "iso:country": "GB",
    "wof:name": "DH5 0SF",
    "wof:placetype": "postalcode"
  },
  "geometry": {"coordinates":[-1.447207,54.81903],"type":"Point"}
}
