{
  "type": "Feature",
  "properties": {
    "date:inception_lower":"2008-06-01",
    "date:inception_upper":"2008-06-30",
    "iso:country":"GB",
    "wof:name":"DH5 0SF",
    "wof:placetype":"postalcode"
},
  "geometry": {"coordinates":[-1.447207,54.81903],"type":"Point"}
}