{
  "type": "Feature",
  "properties": {
    "iso:country": "GB",
    "wof:name": "NR23 1FF",
    "wof:placetype": "postalcode"
  },
  "geometry": {"coordinates":[0.853746,52.953461],"type":"Point"}
}
