{
  "type": "Feature",
  "properties": {
    "iso:country":"GB",
    "wof:name":"NR23 1FF",
    "wof:placetype":"postalcode"
},
  "geometry": {"coordinates":[0.85374547919767,52.95346111785739],"type":"Point"}
}