{
  "type": "Feature",
  "properties": {
    "iso:country":"GB",
    "wof:name":"CO1 1DS",
    "wof:placetype":"postalcode"
},
  "geometry": {"coordinates":[0.89884177124125,51.89020673260871],"type":"Point"}
}