{
  "type": "Feature",
  "properties": {
    "iso:country":"GB",
    "wof:name":"DY2 0UE",
    "wof:placetype":"postalcode"
},
  "geometry": {"coordinates":[-2.10509021952089,52.50013373395019],"type":"Point"}
}