{
  "type": "Feature",
  "properties": {
    "iso:country": "GB",
    "wof:name": "DY2 0UE",
    "wof:placetype": "postalcode"
  },
  "geometry": {"coordinates":[-2.10507,52.500158],"type":"Point"}
}
