{
  "type": "Feature",
  "properties": {
    "iso:country":"GB",
    "wof:name":"CV3 2JG",
    "wof:placetype":"postalcode"
},
  "geometry": {"coordinates":[-1.42109746531822,52.39299707691336],"type":"Point"}
}