{
  "type": "Feature",
  "properties": {
    "date:inception_lower": "1980-01-01",
    "date:inception_upper": "1980-01-01",
    "iso:country": "GB",
    "wof:name": "CV3 2JG",
    "wof:placetype": "postalcode"
  },
  "geometry": {"coordinates":[-1.421131,52.393051],"type":"Point"}
}
