{
  "type": "Feature",
  "properties": {
    "iso:country": "GB",
    "wof:name": "KA10 7GY",
    "wof:placetype": "postalcode"
  },
  "geometry": {"coordinates":[-4.637716,55.560582],"type":"Point"}
}
