{
  "type": "Feature",
  "properties": {
    "date:inception_lower": "2018-06-01",
    "date:inception_upper": "2018-06-01",
    "iso:country": "GB",
    "wof:name": "KA10 7GY",
    "wof:placetype": "postalcode"
  },
  "geometry": {"coordinates":[-4.637716,55.560582],"type":"Point"}
}
