{
  "type": "Feature",
  "properties": {
    "date:inception_lower":"2017-11-01",
    "date:inception_upper":"2017-11-30",
    "iso:country":"GB",
    "wof:name":"BL9 0PN",
    "wof:placetype":"postalcode"
},
  "geometry": {"coordinates":[-2.293494,53.594725],"type":"Point"}
}