{
  "type": "Feature",
  "properties": {
    "date:inception_lower": "2017-11-01",
    "date:inception_upper": "2017-11-01",
    "iso:country": "GB",
    "wof:name": "BL9 0PN",
    "wof:placetype": "postalcode"
  },
  "geometry": {"coordinates":[-2.293794,53.594347],"type":"Point"}
}
