{
  "type": "Feature",
  "properties": {
    "iso:country": "GB",
    "wof:name": "BL9 0PN",
    "wof:placetype": "postalcode"
  },
  "geometry": {"coordinates":[-2.293494,53.594725],"type":"Point"}
}
