{
  "type": "Feature",
  "properties": {
    "iso:country":"GB",
    "wof:name":"BR8 7RU",
    "wof:placetype":"postalcode"
},
  "geometry": {"coordinates":[0.18539729063329,51.41389450299211],"type":"Point"}
}