{
  "type": "Feature",
  "properties": {
    "date:inception_lower": "1980-01-01",
    "date:inception_upper": "1980-01-01",
    "iso:country": "GB",
    "wof:name": "BR8 7RU",
    "wof:placetype": "postalcode"
  },
  "geometry": {"coordinates":[0.185513,51.413947],"type":"Point"}
}
