{
  "type": "Feature",
  "properties": {
    "iso:country": "GB",
    "wof:name": "SO41 3SF",
    "wof:placetype": "postalcode"
  },
  "geometry": {"coordinates":[-1.530228,50.75447],"type":"Point"}
}
