{
  "type": "Feature",
  "properties": {
    "iso:country":"GB",
    "wof:name":"HX7 7NN",
    "wof:placetype":"postalcode"
},
  "geometry": {"coordinates":[-2.02069270581546,53.75018565748883],"type":"Point"}
}