{
  "type": "Feature",
  "properties": {
    "date:inception_lower":"1997-06-01",
    "date:inception_upper":"1997-06-30",
    "iso:country":"GB",
    "wof:name":"SY13 1SS",
    "wof:placetype":"postalcode"
},
  "geometry": {"coordinates":[-2.684976,52.965942],"type":"Point"}
}