{
  "type": "Feature",
  "properties": {
    "iso:country": "GB",
    "wof:name": "DN22 8SG",
    "wof:placetype": "postalcode"
  },
  "geometry": {"coordinates":[-0.969666,53.341917],"type":"Point"}
}
