{
  "type": "Feature",
  "properties": {
    "date:inception_lower": "1992-01-01",
    "date:inception_upper": "1992-01-01",
    "iso:country": "GB",
    "wof:name": "DN22 8SG",
    "wof:placetype": "postalcode"
  },
  "geometry": {"coordinates":[-0.969666,53.341917],"type":"Point"}
}
