{
  "type": "Feature",
  "properties": {
    "iso:country":"GB",
    "wof:name":"DN22 8SG",
    "wof:placetype":"postalcode"
},
  "geometry": {"coordinates":[-0.9680389253925,53.35204871269121],"type":"Point"}
}