{
  "type": "Feature",
  "properties": {
    "iso:country":"GB",
    "wof:name":"RM1 4TH",
    "wof:placetype":"postalcode"
},
  "geometry": {"coordinates":[0.1747556225108,51.59728703178574],"type":"Point"}
}