{
  "type": "Feature",
  "properties": {
    "iso:country": "GB",
    "wof:name": "RM1 4TH",
    "wof:placetype": "postalcode"
  },
  "geometry": {"coordinates":[0.174845,51.597378],"type":"Point"}
}
