{
  "type": "Feature",
  "properties": {
    "iso:country": "GB",
    "wof:name": "G41 5NN",
    "wof:placetype": "postalcode"
  },
  "geometry": {"coordinates":[-4.310591,55.842849],"type":"Point"}
}
