{
  "type": "Feature",
  "properties": {
    "date:inception_lower": "1980-01-01",
    "date:inception_upper": "1980-01-01",
    "iso:country": "GB",
    "wof:name": "CV22 6RQ",
    "wof:placetype": "postalcode"
  },
  "geometry": {"coordinates":[-1.291647,52.340768],"type":"Point"}
}
