{
  "type": "Feature",
  "properties": {
    "iso:country":"GB",
    "wof:name":"LL32 8HJ",
    "wof:placetype":"postalcode"
},
  "geometry": {"coordinates":[-3.83356800622629,53.26080559430799],"type":"Point"}
}