{
  "type": "Feature",
  "properties": {
    "date:inception_lower":"2013-05-01",
    "date:inception_upper":"2013-05-31",
    "iso:country":"GB",
    "wof:name":"DD4 9AP",
    "wof:placetype":"postalcode"
},
  "geometry": {"coordinates":[-2.970223,56.478459],"type":"Point"}
}