{
  "type": "Feature",
  "properties": {
    "iso:country":"GB",
    "wof:name":"M28 0SD",
    "wof:placetype":"postalcode"
},
  "geometry": {"coordinates":[-2.40967899968964,53.52551690656512],"type":"Point"}
}