{
  "type": "Feature",
  "properties": {
    "iso:country":"GB",
    "wof:name":"DL3 9TS",
    "wof:placetype":"postalcode"
},
  "geometry": {"coordinates":[-1.59841384445943,54.5392205846752],"type":"Point"}
}