{
  "type": "Feature",
  "properties": {
    "iso:country": "GB",
    "wof:name": "DL3 9TS",
    "wof:placetype": "postalcode"
  },
  "geometry": {"coordinates":[-1.598423,54.539249],"type":"Point"}
}
