{
  "type": "Feature",
  "properties": {
    "date:inception_lower": "2023-04-01",
    "date:inception_upper": "2023-04-01",
    "iso:country": "GB",
    "wof:name": "BH31 7BZ",
    "wof:placetype": "postalcode"
  },
  "geometry": {"coordinates":[-1.8861,50.885807],"type":"Point"}
}
