{
  "type": "Feature",
  "properties": {
    "iso:country":"GB",
    "wof:name":"WF8 2RY",
    "wof:placetype":"postalcode"
},
  "geometry": {"coordinates":[-1.30845465449892,53.68550992574627],"type":"Point"}
}