{
  "type": "Feature",
  "properties": {
    "date:inception_lower": "1980-01-01",
    "date:inception_upper": "1980-01-01",
    "iso:country": "GB",
    "wof:name": "WF8 2RY",
    "wof:placetype": "postalcode"
  },
  "geometry": {"coordinates":[-1.308455,53.68551],"type":"Point"}
}
