{
  "type": "Feature",
  "properties": {
    "date:inception_lower": "2009-06-01",
    "date:inception_upper": "2009-06-01",
    "iso:country": "GB",
    "wof:name": "SA62 6YT",
    "wof:placetype": "postalcode"
  },
  "geometry": {"coordinates":[-4.979123,51.792556],"type":"Point"}
}
