{
  "type": "Feature",
  "properties": {
    "iso:country": "GB",
    "wof:name": "ZE1 0TU",
    "wof:placetype": "postalcode"
  },
  "geometry": {"coordinates":[-1.278138,60.137882],"type":"Point"}
}
