{
  "type": "Feature",
  "properties": {
    "iso:country":"GB",
    "wof:name":"ZE1 0TU",
    "wof:placetype":"postalcode"
},
  "geometry": {"coordinates":[-1.2781383162451,60.13788217293813],"type":"Point"}
}