{
  "type": "Feature",
  "properties": {
    "iso:country":"GB",
    "wof:name":"MK12 5DA",
    "wof:placetype":"postalcode"
},
  "geometry": {"coordinates":[-0.81645834983742,52.05610894945256],"type":"Point"}
}