{
  "type": "Feature",
  "properties": {
    "iso:country":"GB",
    "wof:name":"WF4 1NS",
    "wof:placetype":"postalcode"
},
  "geometry": {"coordinates":[-1.43735148327944,53.65961513307168],"type":"Point"}
}