{
  "type": "Feature",
  "properties": {
    "iso:country":"GB",
    "wof:name":"EN1 3EZ",
    "wof:placetype":"postalcode"
},
  "geometry": {"coordinates":[-0.08034717100674,51.65800249221413],"type":"Point"}
}