{
  "type": "Feature",
  "properties": {
    "iso:country": "GB",
    "wof:name": "M23 2ZT",
    "wof:placetype": "postalcode"
  },
  "geometry": {"coordinates":[-2.282446,53.378742],"type":"Point"}
}
