{
  "type": "Feature",
  "properties": {
    "iso:country": "GB",
    "wof:name": "PL19 0PN",
    "wof:placetype": "postalcode"
  },
  "geometry": {"coordinates":[-4.154354,50.553729],"type":"Point"}
}
