{
  "type": "Feature",
  "properties": {
    "date:inception_lower": "2006-08-01",
    "date:inception_upper": "2006-08-01",
    "iso:country": "GB",
    "wof:name": "CM0 7GQ",
    "wof:placetype": "postalcode"
  },
  "geometry": {"coordinates":[0.88751,51.733519],"type":"Point"}
}
