{
  "type": "Feature",
  "properties": {
    "iso:country": "GB",
    "wof:name": "CM0 7GQ",
    "wof:placetype": "postalcode"
  },
  "geometry": {"coordinates":[0.88751,51.733519],"type":"Point"}
}
