{
  "type": "Feature",
  "properties": {
    "iso:country": "GB",
    "wof:name": "PE3 9QW",
    "wof:placetype": "postalcode"
  },
  "geometry": {"coordinates":[-0.282564,52.575489],"type":"Point"}
}
