{
  "type": "Feature",
  "properties": {
    "iso:country":"GB",
    "wof:name":"PE3 9QW",
    "wof:placetype":"postalcode"
},
  "geometry": {"coordinates":[-0.28256407162957,52.57548885214761],"type":"Point"}
}