{
  "type": "Feature",
  "properties": {
    "date:inception_lower": "1992-01-01",
    "date:inception_upper": "1992-01-01",
    "iso:country": "GB",
    "wof:name": "PE3 9QW",
    "wof:placetype": "postalcode"
  },
  "geometry": {"coordinates":[-0.282564,52.575489],"type":"Point"}
}
