{
  "type": "Feature",
  "properties": {
    "iso:country": "GB",
    "wof:name": "AB22 8XG",
    "wof:placetype": "postalcode"
  },
  "geometry": {"coordinates":[-2.124729,57.197757],"type":"Point"}
}
