{
  "type": "Feature",
  "properties": {
    "date:inception_lower":"1990-12-01",
    "date:inception_upper":"1990-12-31",
    "iso:country":"GB",
    "wof:name":"AB22 8XG",
    "wof:placetype":"postalcode"
},
  "geometry": {"coordinates":[-2.124729,57.197757],"type":"Point"}
}