{
  "type": "Feature",
  "properties": {
    "iso:country":"GB",
    "wof:name":"BS15 9LA",
    "wof:placetype":"postalcode"
},
  "geometry": {"coordinates":[-2.4991961615577,51.44971859431283],"type":"Point"}
}