{
  "type": "Feature",
  "properties": {
    "date:inception_lower": "2000-06-01",
    "date:inception_upper": "2000-06-01",
    "iso:country": "GB",
    "wof:name": "BS15 9LA",
    "wof:placetype": "postalcode"
  },
  "geometry": {"coordinates":[-2.499197,51.449717],"type":"Point"}
}
