{
  "type": "Feature",
  "properties": {
    "iso:country":"GB",
    "wof:name":"W1K 5RL",
    "wof:placetype":"postalcode"
},
  "geometry": {"coordinates":[-0.14853321243338,51.51413994088063],"type":"Point"}
}