{
  "type": "Feature",
  "properties": {
    "iso:country":"GB",
    "wof:name":"CT19 6LZ",
    "wof:placetype":"postalcode"
},
  "geometry": {"coordinates":[1.18864580423663,51.09261858760523],"type":"Point"}
}