{
  "type": "Feature",
  "properties": {
    "iso:country": "GB",
    "wof:name": "SY1 4LU",
    "wof:placetype": "postalcode"
  },
  "geometry": {"coordinates":[-2.725837,52.734011],"type":"Point"}
}
