{
  "type": "Feature",
  "properties": {
    "iso:country":"GB",
    "wof:name":"SY1 4LU",
    "wof:placetype":"postalcode"
},
  "geometry": {"coordinates":[-2.72583714469497,52.73401077515477],"type":"Point"}
}