{
  "type": "Feature",
  "properties": {
    "iso:country":"GB",
    "wof:name":"WR8 9DA",
    "wof:placetype":"postalcode"
},
  "geometry": {"coordinates":[-2.20191438549058,52.07788803357591],"type":"Point"}
}