{
  "type": "Feature",
  "properties": {
    "iso:country":"GB",
    "wof:name":"SL9 8RL",
    "wof:placetype":"postalcode"
},
  "geometry": {"coordinates":[-0.56498562746416,51.59421188346673],"type":"Point"}
}