{
  "type": "Feature",
  "properties": {
    "iso:country":"GB",
    "wof:name":"L12 9ER",
    "wof:placetype":"postalcode"
},
  "geometry": {"coordinates":[-2.89535215840836,53.42454628490648],"type":"Point"}
}