{
  "type": "Feature",
  "properties": {
    "iso:country":"GB",
    "wof:name":"NG5 1ED",
    "wof:placetype":"postalcode"
},
  "geometry": {"coordinates":[-1.16605804111737,52.9795026247444],"type":"Point"}
}