{
  "type": "Feature",
  "properties": {
    "iso:country": "GB",
    "wof:name": "NG5 1ED",
    "wof:placetype": "postalcode"
  },
  "geometry": {"coordinates":[-1.166058,52.979503],"type":"Point"}
}
