{
  "type": "Feature",
  "properties": {
    "iso:country":"GB",
    "wof:name":"LE17 4XH",
    "wof:placetype":"postalcode"
},
  "geometry": {"coordinates":[-1.24724184070559,52.451407797352],"type":"Point"}
}