{
  "type": "Feature",
  "properties": {
    "iso:country": "GB",
    "wof:name": "SW1E 5BP",
    "wof:placetype": "postalcode"
  },
  "geometry": {"coordinates":[-0.138402,51.496804],"type":"Point"}
}
