{
  "type": "Feature",
  "properties": {
    "date:inception_lower":"2013-05-01",
    "date:inception_upper":"2013-05-31",
    "iso:country":"GB",
    "wof:name":"SW1E 5BP",
    "wof:placetype":"postalcode"
},
  "geometry": {"coordinates":[-0.138402,51.496804],"type":"Point"}
}