{
  "type": "Feature",
  "properties": {
    "date:inception_lower": "1986-07-01",
    "date:inception_upper": "1986-07-01",
    "iso:country": "GB",
    "wof:name": "SK14 1RD",
    "wof:placetype": "postalcode"
  },
  "geometry": {"coordinates":[-2.0725,53.445704],"type":"Point"}
}
