{
  "type": "Feature",
  "properties": {
    "iso:country": "GB",
    "wof:name": "SK14 1RD",
    "wof:placetype": "postalcode"
  },
  "geometry": {"coordinates":[-2.07229,53.44567],"type":"Point"}
}
