{
  "type": "Feature",
  "properties": {
    "date:inception_lower": "1980-01-01",
    "date:inception_upper": "1980-01-01",
    "iso:country": "GB",
    "wof:name": "BN2 8SB",
    "wof:placetype": "postalcode"
  },
  "geometry": {"coordinates":[-0.045024,50.803016],"type":"Point"}
}
