{
  "type": "Feature",
  "properties": {
    "iso:country":"GB",
    "wof:name":"BN2 8SB",
    "wof:placetype":"postalcode"
},
  "geometry": {"coordinates":[-0.04500400010048,50.80313779615027],"type":"Point"}
}