{
  "type": "Feature",
  "properties": {
    "iso:country": "GB",
    "wof:name": "PL20 7JY",
    "wof:placetype": "postalcode"
  },
  "geometry": {"coordinates":[-4.186465,50.45468],"type":"Point"}
}
