{
  "type": "Feature",
  "properties": {
    "iso:country":"GB",
    "wof:name":"PL20 7JY",
    "wof:placetype":"postalcode"
},
  "geometry": {"coordinates":[-4.18646532842575,50.45467952900289],"type":"Point"}
}