{
  "type": "Feature",
  "properties": {
    "iso:country":"GB",
    "wof:name":"BL2 6DE",
    "wof:placetype":"postalcode"
},
  "geometry": {"coordinates":[-2.4026008578022,53.58075664418029],"type":"Point"}
}