{
  "type": "Feature",
  "properties": {
    "date:inception_lower":"1980-01-01",
    "date:inception_upper":"1980-01-31",
    "iso:country":"GB",
    "wof:name":"BL2 6DE",
    "wof:placetype":"postalcode"
},
  "geometry": {"coordinates":[-2.402601,53.580757],"type":"Point"}
}