{
  "type": "Feature",
  "properties": {
    "iso:country":"GB",
    "wof:name":"G15 8NE",
    "wof:placetype":"postalcode"
},
  "geometry": {"coordinates":[-4.37224725960245,55.9096724121908],"type":"Point"}
}