{
  "type": "Feature",
  "properties": {
    "iso:country": "GB",
    "wof:name": "LN13 0HF",
    "wof:placetype": "postalcode"
  },
  "geometry": {"coordinates":[0.128749,53.229718],"type":"Point"}
}
