{
  "type": "Feature",
  "properties": {
    "iso:country":"GB",
    "wof:name":"LN13 0HF",
    "wof:placetype":"postalcode"
},
  "geometry": {"coordinates":[0.12874860231136,53.22971835949566],"type":"Point"}
}