{
  "type": "Feature",
  "properties": {
    "iso:country": "GB",
    "wof:name": "HA3 8LF",
    "wof:placetype": "postalcode"
  },
  "geometry": {"coordinates":[-0.318818,51.589901],"type":"Point"}
}
