{
  "type": "Feature",
  "properties": {
    "iso:country":"GB",
    "wof:name":"HA3 8LF",
    "wof:placetype":"postalcode"
},
  "geometry": {"coordinates":[-0.31881807451353,51.58990118266532],"type":"Point"}
}