{
  "type": "Feature",
  "properties": {
    "iso:country":"GB",
    "wof:name":"IP13 9EW",
    "wof:placetype":"postalcode"
},
  "geometry": {"coordinates":[1.33702662000852,52.22244872284508],"type":"Point"}
}