{
  "type": "Feature",
  "properties": {
    "iso:country":"GB",
    "wof:name":"ME5 8RY",
    "wof:placetype":"postalcode"
},
  "geometry": {"coordinates":[0.54175585986622,51.33490943487512],"type":"Point"}
}