{
  "type": "Feature",
  "properties": {
    "iso:country":"GB",
    "wof:name":"DN14 8PG",
    "wof:placetype":"postalcode"
},
  "geometry": {"coordinates":[-0.94720176430896,53.68487559817227],"type":"Point"}
}