{
  "type": "Feature",
  "properties": {
    "iso:country": "GB",
    "wof:name": "DN14 8PG",
    "wof:placetype": "postalcode"
  },
  "geometry": {"coordinates":[-0.947202,53.684876],"type":"Point"}
}
