{
  "type": "Feature",
  "properties": {
    "date:inception_lower": "2023-05-01",
    "date:inception_upper": "2023-05-01",
    "iso:country": "GB",
    "wof:name": "WR14 9LH",
    "wof:placetype": "postalcode"
  },
  "geometry": {"coordinates":[-2.329262,52.111299],"type":"Point"}
}
