{
  "type": "Feature",
  "properties": {
    "iso:country":"GB",
    "wof:name":"IG10 4RP",
    "wof:placetype":"postalcode"
},
  "geometry": {"coordinates":[0.03475239353849,51.6382681625978],"type":"Point"}
}