{
  "type": "Feature",
  "properties": {
    "iso:country":"GB",
    "wof:name":"GL7 7BX",
    "wof:placetype":"postalcode"
},
  "geometry": {"coordinates":[-1.97591123931306,51.76877508248747],"type":"Point"}
}