{
  "type": "Feature",
  "properties": {
    "iso:country":"GB",
    "wof:name":"SM1 4PS",
    "wof:placetype":"postalcode"
},
  "geometry": {"coordinates":[-0.18566476207001,51.36694551864402],"type":"Point"}
}