{
  "type": "Feature",
  "properties": {
    "date:inception_lower":"1980-01-01",
    "date:inception_upper":"1980-01-31",
    "iso:country":"GB",
    "wof:name":"SW15 3HF",
    "wof:placetype":"postalcode"
},
  "geometry": {"coordinates":[-0.216697,51.454479],"type":"Point"}
}