{
  "type": "Feature",
  "properties": {
    "iso:country":"GB",
    "wof:name":"SW15 3HF",
    "wof:placetype":"postalcode"
},
  "geometry": {"coordinates":[-0.21669732553319,51.45447901656904],"type":"Point"}
}