{
  "type": "Feature",
  "properties": {
    "iso:country": "GB",
    "wof:name": "N15 4UR",
    "wof:placetype": "postalcode"
  },
  "geometry": {"coordinates":[-0.071031,51.586243],"type":"Point"}
}
