{
  "type": "Feature",
  "properties": {
    "iso:country": "GB",
    "wof:name": "SW6 4UG",
    "wof:placetype": "postalcode"
  },
  "geometry": {"coordinates":[-0.201783,51.473234],"type":"Point"}
}
