{
  "type": "Feature",
  "properties": {
    "iso:country": "GB",
    "wof:name": "BS21 6PQ",
    "wof:placetype": "postalcode"
  },
  "geometry": {"coordinates":[-2.85958,51.432146],"type":"Point"}
}
