{
  "type": "Feature",
  "properties": {
    "date:inception_lower": "2017-11-01",
    "date:inception_upper": "2017-11-01",
    "iso:country": "GB",
    "wof:name": "SK5 7FS",
    "wof:placetype": "postalcode"
  },
  "geometry": {"coordinates":[-2.159649,53.435615],"type":"Point"}
}
