{
  "type": "Feature",
  "properties": {
    "date:inception_lower": "1980-01-01",
    "date:inception_upper": "1980-01-01",
    "iso:country": "GB",
    "wof:name": "TN1 1UE",
    "wof:placetype": "postalcode"
  },
  "geometry": {"coordinates":[0.261194,51.126693],"type":"Point"}
}
