{
  "type": "Feature",
  "properties": {
    "iso:country":"GB",
    "wof:name":"EX4 2JW",
    "wof:placetype":"postalcode"
},
  "geometry": {"coordinates":[-3.60429620532881,50.72998725935093],"type":"Point"}
}