{
  "type": "Feature",
  "properties": {
    "iso:country": "GB",
    "wof:name": "EX4 2JW",
    "wof:placetype": "postalcode"
  },
  "geometry": {"coordinates":[-3.604296,50.729987],"type":"Point"}
}
