{
  "type": "Feature",
  "properties": {
    "iso:country":"GB",
    "wof:name":"DY12 1SJ",
    "wof:placetype":"postalcode"
},
  "geometry": {"coordinates":[-2.35181914967409,52.43025387832289],"type":"Point"}
}