{
  "type": "Feature",
  "properties": {
    "iso:country":"GB",
    "wof:name":"TA14 6TD",
    "wof:placetype":"postalcode"
},
  "geometry": {"coordinates":[-2.74786737723863,50.93825567111639],"type":"Point"}
}