{
  "type": "Feature",
  "properties": {
    "iso:country":"GB",
    "wof:name":"LD3 7HN",
    "wof:placetype":"postalcode"
},
  "geometry": {"coordinates":[-3.240860478854,51.89238580087006],"type":"Point"}
}