{
  "type": "Feature",
  "properties": {
    "iso:country":"GB",
    "wof:name":"BD1 5RW",
    "wof:placetype":"postalcode"
},
  "geometry": {"coordinates":[-1.75360922155233,53.79002138245398],"type":"Point"}
}