{
  "type": "Feature",
  "properties": {
    "iso:country":"GB",
    "wof:name":"CM6 1WG",
    "wof:placetype":"postalcode"
},
  "geometry": {"coordinates":[0.31893797085955,51.79662296166349],"type":"Point"}
}