{
  "type": "Feature",
  "properties": {
    "iso:country":"GB",
    "wof:name":"SR2 0BU",
    "wof:placetype":"postalcode"
},
  "geometry": {"coordinates":[-1.38244565059356,54.87264599666727],"type":"Point"}
}