{
  "type": "Feature",
  "properties": {
    "iso:country":"GB",
    "wof:name":"SA15 4AH",
    "wof:placetype":"postalcode"
},
  "geometry": {"coordinates":[-4.20697362684417,51.68801517035882],"type":"Point"}
}