{
  "type": "Feature",
  "properties": {
    "iso:country": "GB",
    "wof:name": "SA15 4AH",
    "wof:placetype": "postalcode"
  },
  "geometry": {"coordinates":[-4.206974,51.688015],"type":"Point"}
}
