{
  "type": "Feature",
  "properties": {
    "iso:country":"GB",
    "wof:name":"EH22 5RX",
    "wof:placetype":"postalcode"
},
  "geometry": {"coordinates":[-3.04566156434787,55.86794548781953],"type":"Point"}
}