{
  "type": "Feature",
  "properties": {
    "iso:country":"GB",
    "wof:name":"WA8 4DY",
    "wof:placetype":"postalcode"
},
  "geometry": {"coordinates":[-2.76739048019408,53.38019671099665],"type":"Point"}
}