{
  "type": "Feature",
  "properties": {
    "date:inception_lower": "1980-01-01",
    "date:inception_upper": "1980-01-01",
    "iso:country": "GB",
    "wof:name": "SY11 4PF",
    "wof:placetype": "postalcode"
  },
  "geometry": {"coordinates":[-2.979083,52.864538],"type":"Point"}
}
