{
  "type": "Feature",
  "properties": {
    "iso:country":"GB",
    "wof:name":"FK5 4BX",
    "wof:placetype":"postalcode"
},
  "geometry": {"coordinates":[-3.80391983652307,56.02767855743429],"type":"Point"}
}