{
  "type": "Feature",
  "properties": {
    "iso:country": "GB",
    "wof:name": "OX2 9NU",
    "wof:placetype": "postalcode"
  },
  "geometry": {"coordinates":[-1.345732,51.748427],"type":"Point"}
}
