{
  "type": "Feature",
  "properties": {
    "iso:country":"GB",
    "wof:name":"OX2 9NU",
    "wof:placetype":"postalcode"
},
  "geometry": {"coordinates":[-1.34573238883336,51.74842747670138],"type":"Point"}
}