{
  "type": "Feature",
  "properties": {
    "iso:country": "GB",
    "wof:name": "WF1 5QA",
    "wof:placetype": "postalcode"
  },
  "geometry": {"coordinates":[-1.494407,53.672956],"type":"Point"}
}
