{
  "type": "Feature",
  "properties": {
    "iso:country":"GB",
    "wof:name":"HU15 2SB",
    "wof:placetype":"postalcode"
},
  "geometry": {"coordinates":[-0.74012963986442,53.76365839185974],"type":"Point"}
}