{
  "type": "Feature",
  "properties": {
    "date:inception_lower": "1993-01-01",
    "date:inception_upper": "1993-01-01",
    "iso:country": "GB",
    "wof:name": "HU15 2SB",
    "wof:placetype": "postalcode"
  },
  "geometry": {"coordinates":[-0.739039,53.763811],"type":"Point"}
}
