{
  "type": "Feature",
  "properties": {
    "iso:country": "GB",
    "wof:name": "HU15 2SB",
    "wof:placetype": "postalcode"
  },
  "geometry": {"coordinates":[-0.739039,53.763811],"type":"Point"}
}
