{
  "type": "Feature",
  "properties": {
    "iso:country": "GB",
    "wof:name": "HP12 4UZ",
    "wof:placetype": "postalcode"
  },
  "geometry": {"coordinates":[-0.794547,51.614858],"type":"Point"}
}
