{
  "type": "Feature",
  "properties": {
    "date:inception_lower":"1990-02-01",
    "date:inception_upper":"1990-02-28",
    "iso:country":"GB",
    "wof:name":"HP12 4UZ",
    "wof:placetype":"postalcode"
},
  "geometry": {"coordinates":[-0.794547,51.614858],"type":"Point"}
}