{
  "type": "Feature",
  "properties": {
    "iso:country":"GB",
    "wof:name":"EH22 5DD",
    "wof:placetype":"postalcode"
},
  "geometry": {"coordinates":[-3.04049448314381,55.87610311423096],"type":"Point"}
}