{
  "type": "Feature",
  "properties": {
    "date:inception_lower":"1998-06-01",
    "date:inception_upper":"1998-06-30",
    "iso:country":"GB",
    "wof:name":"SL5 0EJ",
    "wof:placetype":"postalcode"
},
  "geometry": {"coordinates":[-0.63413,51.391061],"type":"Point"}
}