{
  "type": "Feature",
  "properties": {
    "iso:country":"GB",
    "wof:name":"SL5 0EJ",
    "wof:placetype":"postalcode"
},
  "geometry": {"coordinates":[-0.6341304493854,51.39106119434216],"type":"Point"}
}