{
  "type": "Feature",
  "properties": {
    "iso:country": "GB",
    "wof:name": "SL5 0EJ",
    "wof:placetype": "postalcode"
  },
  "geometry": {"coordinates":[-0.63413,51.391061],"type":"Point"}
}
