{
  "type": "Feature",
  "properties": {
    "iso:country": "GB",
    "wof:name": "AB33 8NR",
    "wof:placetype": "postalcode"
  },
  "geometry": {"coordinates":[-2.759667,57.222676],"type":"Point"}
}
