{
  "type": "Feature",
  "properties": {
    "iso:country": "GB",
    "wof:name": "SO14 1BP",
    "wof:placetype": "postalcode"
  },
  "geometry": {"coordinates":[-1.40225,50.902668],"type":"Point"}
}
