{
  "type": "Feature",
  "properties": {
    "date:inception_lower":"2015-09-01",
    "date:inception_upper":"2015-09-30",
    "iso:country":"GB",
    "wof:name":"SO14 1BP",
    "wof:placetype":"postalcode"
},
  "geometry": {"coordinates":[-1.40225,50.902668],"type":"Point"}
}