{
  "type": "Feature",
  "properties": {
    "date:inception_lower":"2009-06-01",
    "date:inception_upper":"2009-06-30",
    "iso:country":"GB",
    "wof:name":"KW17 2EE",
    "wof:placetype":"postalcode"
},
  "geometry": {"coordinates":[-3.1156,59.007262],"type":"Point"}
}