{
  "type": "Feature",
  "properties": {
    "iso:country":"GB",
    "wof:name":"KW17 2EE",
    "wof:placetype":"postalcode"
},
  "geometry": {"coordinates":[-3.11557319016991,59.00726123909671],"type":"Point"}
}