{
  "type": "Feature",
  "properties": {
    "iso:country":"GB",
    "wof:name":"GU9 7EP",
    "wof:placetype":"postalcode"
},
  "geometry": {"coordinates":[-0.80384850870112,51.21369279665843],"type":"Point"}
}