{
  "type": "Feature",
  "properties": {
    "iso:country":"GB",
    "wof:name":"SP9 7SP",
    "wof:placetype":"postalcode"
},
  "geometry": {"coordinates":[-1.65919421864165,51.22993615035588],"type":"Point"}
}