{
  "type": "Feature",
  "properties": {
    "iso:country":"GB",
    "wof:name":"HR9 6AF",
    "wof:placetype":"postalcode"
},
  "geometry": {"coordinates":[-2.60471648667542,51.91493490695481],"type":"Point"}
}