{
  "type": "Feature",
  "properties": {
    "iso:country":"GB",
    "wof:name":"CM7 3PY",
    "wof:placetype":"postalcode"
},
  "geometry": {"coordinates":[0.57537212840992,51.87031491173289],"type":"Point"}
}