{
  "type": "Feature",
  "properties": {
    "iso:country":"GB",
    "wof:name":"NR8 6SX",
    "wof:placetype":"postalcode"
},
  "geometry": {"coordinates":[1.19960066741318,52.67845615500524],"type":"Point"}
}