{
  "type": "Feature",
  "properties": {
    "date:inception_lower": "1980-01-01",
    "date:inception_upper": "1980-01-01",
    "iso:country": "GB",
    "wof:name": "AL5 1BU",
    "wof:placetype": "postalcode"
  },
  "geometry": {"coordinates":[-0.344341,51.79742],"type":"Point"}
}
