{
  "type": "Feature",
  "properties": {
    "iso:country": "GB",
    "wof:name": "AL5 1BU",
    "wof:placetype": "postalcode"
  },
  "geometry": {"coordinates":[-0.344468,51.79737],"type":"Point"}
}
