{
  "type": "Feature",
  "properties": {
    "iso:country": "GB",
    "wof:name": "BH17 8QQ",
    "wof:placetype": "postalcode"
  },
  "geometry": {"coordinates":[-1.966417,50.741194],"type":"Point"}
}
