{
  "type": "Feature",
  "properties": {
    "iso:country":"GB",
    "wof:name":"EX6 7QW",
    "wof:placetype":"postalcode"
},
  "geometry": {"coordinates":[-3.6328113989834,50.6473822783231],"type":"Point"}
}