{
  "type": "Feature",
  "properties": {
    "date:inception_lower": "1980-01-01",
    "date:inception_upper": "1980-01-01",
    "iso:country": "GB",
    "wof:name": "PL9 9PP",
    "wof:placetype": "postalcode"
  },
  "geometry": {"coordinates":[-4.108651,50.352169],"type":"Point"}
}
