{
  "type": "Feature",
  "properties": {
    "date:inception_lower":"1980-01-01",
    "date:inception_upper":"1980-01-31",
    "iso:country":"GB",
    "wof:name":"LA11 6SA",
    "wof:placetype":"postalcode"
},
  "geometry": {"coordinates":[-2.881201,54.262892],"type":"Point"}
}