{
  "type": "Feature",
  "properties": {
    "iso:country": "GB",
    "wof:name": "LA11 6SA",
    "wof:placetype": "postalcode"
  },
  "geometry": {"coordinates":[-2.881201,54.262892],"type":"Point"}
}
