{
  "type": "Feature",
  "properties": {
    "iso:country": "GB",
    "wof:name": "BA1 3AG",
    "wof:placetype": "postalcode"
  },
  "geometry": {"coordinates":[-2.373389,51.383879],"type":"Point"}
}
