{
  "type": "Feature",
  "properties": {
    "iso:country":"GB",
    "wof:name":"BA1 3AG",
    "wof:placetype":"postalcode"
},
  "geometry": {"coordinates":[-2.37321740520068,51.38381131539393],"type":"Point"}
}