{
  "type": "Feature",
  "properties": {
    "iso:country":"GB",
    "wof:name":"KA6 5EL",
    "wof:placetype":"postalcode"
},
  "geometry": {"coordinates":[-4.52497806765631,55.47189617004873],"type":"Point"}
}