{
  "type": "Feature",
  "properties": {
    "iso:country":"GB",
    "wof:name":"SE9 5JJ",
    "wof:placetype":"postalcode"
},
  "geometry": {"coordinates":[0.03526763800291,51.44811806706261],"type":"Point"}
}