{
  "type": "Feature",
  "properties": {
    "iso:country":"GB",
    "wof:name":"PR1 0NW",
    "wof:placetype":"postalcode"
},
  "geometry": {"coordinates":[-2.73702533119053,53.73715204559694],"type":"Point"}
}