{
  "type": "Feature",
  "properties": {
    "date:inception_lower": "1999-06-01",
    "date:inception_upper": "1999-06-01",
    "iso:country": "GB",
    "wof:name": "PR1 0NW",
    "wof:placetype": "postalcode"
  },
  "geometry": {"coordinates":[-2.737025,53.737152],"type":"Point"}
}
