{
  "type": "Feature",
  "properties": {
    "iso:country":"GB",
    "wof:name":"WD6 5EU",
    "wof:placetype":"postalcode"
},
  "geometry": {"coordinates":[-0.27791706657259,51.66593069062597],"type":"Point"}
}