{
  "type": "Feature",
  "properties": {
    "iso:country": "GB",
    "wof:name": "LS12 6GY",
    "wof:placetype": "postalcode"
  },
  "geometry": {"coordinates":[-1.603843,53.779868],"type":"Point"}
}
