{
  "type": "Feature",
  "properties": {
    "date:inception_lower":"2014-01-01",
    "date:inception_upper":"2014-01-31",
    "iso:country":"GB",
    "wof:name":"LS12 6GY",
    "wof:placetype":"postalcode"
},
  "geometry": {"coordinates":[-1.603843,53.779868],"type":"Point"}
}