{
  "type": "Feature",
  "properties": {
    "iso:country":"GB",
    "wof:name":"LS12 6GY",
    "wof:placetype":"postalcode"
},
  "geometry": {"coordinates":[-1.60384280772425,53.77986846118036],"type":"Point"}
}