{
  "type": "Feature",
  "properties": {
    "iso:country":"GB",
    "wof:name":"BH10 6JT",
    "wof:placetype":"postalcode"
},
  "geometry": {"coordinates":[-1.88399143219227,50.75866789043609],"type":"Point"}
}