{
  "type": "Feature",
  "properties": {
    "iso:country":"GB",
    "wof:name":"B36 8ND",
    "wof:placetype":"postalcode"
},
  "geometry": {"coordinates":[-1.80122664031814,52.50252232801211],"type":"Point"}
}