{
  "type": "Feature",
  "properties": {
    "iso:country": "GB",
    "wof:name": "B36 8ND",
    "wof:placetype": "postalcode"
  },
  "geometry": {"coordinates":[-1.801227,52.502522],"type":"Point"}
}
