{
  "type": "Feature",
  "properties": {
    "date:inception_lower": "1980-01-01",
    "date:inception_upper": "1980-01-01",
    "iso:country": "GB",
    "wof:name": "DY12 2XQ",
    "wof:placetype": "postalcode"
  },
  "geometry": {"coordinates":[-2.349178,52.347328],"type":"Point"}
}
