{
  "type": "Feature",
  "properties": {
    "iso:country": "GB",
    "wof:name": "DY12 2XQ",
    "wof:placetype": "postalcode"
  },
  "geometry": {"coordinates":[-2.349178,52.347328],"type":"Point"}
}
