{
  "type": "Feature",
  "properties": {
    "date:inception_lower":"1980-01-01",
    "date:inception_upper":"1980-01-31",
    "iso:country":"GB",
    "wof:name":"PO33 3SG",
    "wof:placetype":"postalcode"
},
  "geometry": {"coordinates":[-1.190472,50.721895],"type":"Point"}
}