{
  "type": "Feature",
  "properties": {
    "iso:country":"GB",
    "wof:name":"PO33 3SG",
    "wof:placetype":"postalcode"
},
  "geometry": {"coordinates":[-1.19063864846233,50.72189897114033],"type":"Point"}
}