{
  "type": "Feature",
  "properties": {
    "date:inception_lower": "2013-03-01",
    "date:inception_upper": "2013-03-01",
    "iso:country": "GB",
    "wof:name": "GU26 6GZ",
    "wof:placetype": "postalcode"
  },
  "geometry": {"coordinates":[-0.754974,51.122126],"type":"Point"}
}
