{
  "type": "Feature",
  "properties": {
    "iso:country": "GB",
    "wof:name": "GU26 6GZ",
    "wof:placetype": "postalcode"
  },
  "geometry": {"coordinates":[-0.754974,51.122126],"type":"Point"}
}
