{
  "type": "Feature",
  "properties": {
    "iso:country":"GB",
    "wof:name":"PA12 4LA",
    "wof:placetype":"postalcode"
},
  "geometry": {"coordinates":[-4.62414768948122,55.8075568697993],"type":"Point"}
}