{
  "type": "Feature",
  "properties": {
    "iso:country":"GB",
    "wof:name":"SN6 7JY",
    "wof:placetype":"postalcode"
},
  "geometry": {"coordinates":[-1.71347292971725,51.63743652287359],"type":"Point"}
}