{
  "type": "Feature",
  "properties": {
    "iso:country": "GB",
    "wof:name": "LA18 4PX",
    "wof:placetype": "postalcode"
  },
  "geometry": {"coordinates":[-3.274393,54.207731],"type":"Point"}
}
