{
  "type": "Feature",
  "properties": {
    "iso:country":"GB",
    "wof:name":"LA18 4PX",
    "wof:placetype":"postalcode"
},
  "geometry": {"coordinates":[-3.27439294469858,54.20773089372025],"type":"Point"}
}