{
  "type": "Feature",
  "properties": {
    "iso:country":"GB",
    "wof:name":"SY1 4JF",
    "wof:placetype":"postalcode"
},
  "geometry": {"coordinates":[-2.72955701985319,52.7288457955902],"type":"Point"}
}