{
  "type": "Feature",
  "properties": {
    "iso:country":"GB",
    "wof:name":"ML3 8EP",
    "wof:placetype":"postalcode"
},
  "geometry": {"coordinates":[-4.05390042399916,55.76039590497763],"type":"Point"}
}