{
  "type": "Feature",
  "properties": {
    "iso:country": "GB",
    "wof:name": "ML3 8EP",
    "wof:placetype": "postalcode"
  },
  "geometry": {"coordinates":[-4.0539,55.760396],"type":"Point"}
}
