{
  "type": "Feature",
  "properties": {
    "date:inception_lower":"2008-11-01",
    "date:inception_upper":"2008-11-30",
    "iso:country":"GB",
    "wof:name":"NR16 2TR",
    "wof:placetype":"postalcode"
},
  "geometry": {"coordinates":[0.93654,52.440981],"type":"Point"}
}