{
  "type": "Feature",
  "properties": {
    "iso:country": "GB",
    "wof:name": "NR16 2TR",
    "wof:placetype": "postalcode"
  },
  "geometry": {"coordinates":[0.93654,52.440981],"type":"Point"}
}
