{
  "type": "Feature",
  "properties": {
    "iso:country":"GB",
    "wof:name":"GU7 3RP",
    "wof:placetype":"postalcode"
},
  "geometry": {"coordinates":[-0.61339085399416,51.20488288106809],"type":"Point"}
}