{
  "type": "Feature",
  "properties": {
    "iso:country":"GB",
    "wof:name":"TN34 2NU",
    "wof:placetype":"postalcode"
},
  "geometry": {"coordinates":[0.5698307454794,50.87976782865651],"type":"Point"}
}