{
  "type": "Feature",
  "properties": {
    "date:inception_lower": "2005-12-01",
    "date:inception_upper": "2005-12-01",
    "iso:country": "GB",
    "wof:name": "DL14 8DT",
    "wof:placetype": "postalcode"
  },
  "geometry": {"coordinates":[-1.629179,54.672997],"type":"Point"}
}
