{
  "type": "Feature",
  "properties": {
    "iso:country": "GB",
    "wof:name": "M32 9HY",
    "wof:placetype": "postalcode"
  },
  "geometry": {"coordinates":[-2.318821,53.448502],"type":"Point"}
}
