{
  "type": "Feature",
  "properties": {
    "iso:country":"GB",
    "wof:name":"M32 9HY",
    "wof:placetype":"postalcode"
},
  "geometry": {"coordinates":[-2.31882116798676,53.44850206510346],"type":"Point"}
}