{
  "type": "Feature",
  "properties": {
    "iso:country":"GB",
    "wof:name":"N13 4BQ",
    "wof:placetype":"postalcode"
},
  "geometry": {"coordinates":[-0.1125946083467,51.6244441801913],"type":"Point"}
}