{
  "type": "Feature",
  "properties": {
    "iso:country": "GB",
    "wof:name": "PR25 1AB",
    "wof:placetype": "postalcode"
  },
  "geometry": {"coordinates":[-2.712141,53.686573],"type":"Point"}
}
