{
  "type": "Feature",
  "properties": {
    "iso:country":"GB",
    "wof:name":"SW2 5BF",
    "wof:placetype":"postalcode"
},
  "geometry": {"coordinates":[-0.11756540307654,51.46052790319413],"type":"Point"}
}