{
  "type": "Feature",
  "properties": {
    "iso:country": "GB",
    "wof:name": "WV15 6EJ",
    "wof:placetype": "postalcode"
  },
  "geometry": {"coordinates":[-2.308013,52.494619],"type":"Point"}
}
