{
  "type": "Feature",
  "properties": {
    "date:inception_lower":"1980-01-01",
    "date:inception_upper":"1980-01-31",
    "iso:country":"GB",
    "wof:name":"WV15 6EJ",
    "wof:placetype":"postalcode"
},
  "geometry": {"coordinates":[-2.308013,52.494619],"type":"Point"}
}