{
  "type": "Feature",
  "properties": {
    "iso:country":"GB",
    "wof:name":"W1T 7DL",
    "wof:placetype":"postalcode"
},
  "geometry": {"coordinates":[-0.13580659524047,51.52262511465255],"type":"Point"}
}