{
  "type": "Feature",
  "properties": {
    "iso:country":"GB",
    "wof:name":"BA22 8EY",
    "wof:placetype":"postalcode"
},
  "geometry": {"coordinates":[-2.65069688037684,51.00493188714326],"type":"Point"}
}