{
  "type": "Feature",
  "properties": {
    "iso:country":"GB",
    "wof:name":"NE4 6AR",
    "wof:placetype":"postalcode"
},
  "geometry": {"coordinates":[-1.62869861483128,54.97173357691655],"type":"Point"}
}