{
  "type": "Feature",
  "properties": {
    "iso:country":"GB",
    "wof:name":"SY3 8RU",
    "wof:placetype":"postalcode"
},
  "geometry": {"coordinates":[-2.77132850052939,52.70942409413717],"type":"Point"}
}