{
  "type": "Feature",
  "properties": {
    "iso:country":"GB",
    "wof:name":"PO9 4RY",
    "wof:placetype":"postalcode"
},
  "geometry": {"coordinates":[-0.9932908414623,50.8702010014384],"type":"Point"}
}