{
  "type": "Feature",
  "properties": {
    "date:inception_lower": "1995-01-01",
    "date:inception_upper": "1995-01-01",
    "iso:country": "GB",
    "wof:name": "ST14 8UW",
    "wof:placetype": "postalcode"
  },
  "geometry": {"coordinates":[-1.872729,52.891629],"type":"Point"}
}
