{
  "type": "Feature",
  "properties": {
    "iso:country":"GB",
    "wof:name":"ST14 8UW",
    "wof:placetype":"postalcode"
},
  "geometry": {"coordinates":[-1.87272929799675,52.89162901022364],"type":"Point"}
}