{
  "type": "Feature",
  "properties": {
    "date:inception_lower": "1980-01-01",
    "date:inception_upper": "1980-01-01",
    "iso:country": "GB",
    "wof:name": "YO15 3LR",
    "wof:placetype": "postalcode"
  },
  "geometry": {"coordinates":[-0.20381,54.075641],"type":"Point"}
}
