{
  "type": "Feature",
  "properties": {
    "iso:country":"GB",
    "wof:name":"SK5 8DP",
    "wof:placetype":"postalcode"
},
  "geometry": {"coordinates":[-2.13061564745177,53.42592678686093],"type":"Point"}
}