{
  "type": "Feature",
  "properties": {
    "iso:country":"GB",
    "wof:name":"OX10 0AW",
    "wof:placetype":"postalcode"
},
  "geometry": {"coordinates":[-1.16053387159802,51.61639915379713],"type":"Point"}
}