{
  "type": "Feature",
  "properties": {
    "date:inception_lower":"2007-04-01",
    "date:inception_upper":"2007-04-30",
    "iso:country":"GB",
    "wof:name":"OX10 0AW",
    "wof:placetype":"postalcode"
},
  "geometry": {"coordinates":[-1.160534,51.616399],"type":"Point"}
}