{
  "type": "Feature",
  "properties": {
    "iso:country":"GB",
    "wof:name":"FY7 8LP",
    "wof:placetype":"postalcode"
},
  "geometry": {"coordinates":[-3.03893735808276,53.90812914937764],"type":"Point"}
}