{
  "type": "Feature",
  "properties": {
    "iso:country":"GB",
    "wof:name":"LE14 3TR",
    "wof:placetype":"postalcode"
},
  "geometry": {"coordinates":[-0.96131202727375,52.76550746208771],"type":"Point"}
}