{
  "type": "Feature",
  "properties": {
    "date:inception_lower": "1980-01-01",
    "date:inception_upper": "1980-01-01",
    "iso:country": "GB",
    "wof:name": "BS7 8JL",
    "wof:placetype": "postalcode"
  },
  "geometry": {"coordinates":[-2.60156,51.479603],"type":"Point"}
}
