{
  "type": "Feature",
  "properties": {
    "iso:country":"GB",
    "wof:name":"BN7 2LE",
    "wof:placetype":"postalcode"
},
  "geometry": {"coordinates":[0.01436303371439,50.87272746016671],"type":"Point"}
}