{
  "type": "Feature",
  "properties": {
    "iso:country":"GB",
    "wof:name":"PO33 1UP",
    "wof:placetype":"postalcode"
},
  "geometry": {"coordinates":[-1.11362295920086,50.69819136486514],"type":"Point"}
}