{
  "type": "Feature",
  "properties": {
    "iso:country":"GB",
    "wof:name":"RM19 1GH",
    "wof:placetype":"postalcode"
},
  "geometry": {"coordinates":[0.23510722409698,51.48653807009201],"type":"Point"}
}