{
  "type": "Feature",
  "properties": {
    "date:inception_lower":"2007-01-01",
    "date:inception_upper":"2007-01-31",
    "iso:country":"GB",
    "wof:name":"N16 7TT",
    "wof:placetype":"postalcode"
},
  "geometry": {"coordinates":[-0.072458,51.553552],"type":"Point"}
}