{
  "type": "Feature",
  "properties": {
    "iso:country":"GB",
    "wof:name":"N16 7TT",
    "wof:placetype":"postalcode"
},
  "geometry": {"coordinates":[-0.07245791007941,51.55355173406549],"type":"Point"}
}