{
  "type": "Feature",
  "properties": {
    "date:inception_lower":"1980-01-01",
    "date:inception_upper":"1980-01-31",
    "iso:country":"GB",
    "wof:name":"YO14 9ED",
    "wof:placetype":"postalcode"
},
  "geometry": {"coordinates":[-0.28942,54.212032],"type":"Point"}
}