{
  "type": "Feature",
  "properties": {
    "date:inception_lower": "2003-03-01",
    "date:inception_upper": "2003-03-01",
    "iso:country": "GB",
    "wof:name": "LS10 4UZ",
    "wof:placetype": "postalcode"
  },
  "geometry": {"coordinates":[-1.532085,53.747855],"type":"Point"}
}
