{
  "type": "Feature",
  "properties": {
    "iso:country": "GB",
    "wof:name": "LS10 4UZ",
    "wof:placetype": "postalcode"
  },
  "geometry": {"coordinates":[-1.532085,53.747855],"type":"Point"}
}
