{
  "type": "Feature",
  "properties": {
    "iso:country":"GB",
    "wof:name":"DA5 1NU",
    "wof:placetype":"postalcode"
},
  "geometry": {"coordinates":[0.15037464077889,51.44383258376133],"type":"Point"}
}