{
  "type": "Feature",
  "properties": {
    "iso:country":"GB",
    "wof:name":"WS9 8EN",
    "wof:placetype":"postalcode"
},
  "geometry": {"coordinates":[-1.93821857487845,52.60620887966462],"type":"Point"}
}