{
  "type": "Feature",
  "properties": {
    "iso:country":"GB",
    "wof:name":"ST14 8RG",
    "wof:placetype":"postalcode"
},
  "geometry": {"coordinates":[-1.86481300433229,52.85624713887721],"type":"Point"}
}