{
  "type": "Feature",
  "properties": {
    "iso:country": "GB",
    "wof:name": "KT16 0HY",
    "wof:placetype": "postalcode"
  },
  "geometry": {"coordinates":[-0.52147,51.36492],"type":"Point"}
}
