{
  "type": "Feature",
  "properties": {
    "iso:country":"GB",
    "wof:name":"BH20 6LD",
    "wof:placetype":"postalcode"
},
  "geometry": {"coordinates":[-2.24716968002192,50.70159319298227],"type":"Point"}
}