{
  "type": "Feature",
  "properties": {
    "iso:country":"GB",
    "wof:name":"E2 8AN",
    "wof:placetype":"postalcode"
},
  "geometry": {"coordinates":[-0.07723704904241,51.53462892168664],"type":"Point"}
}