{
  "type": "Feature",
  "properties": {
    "iso:country":"GB",
    "wof:name":"PO16 8NZ",
    "wof:placetype":"postalcode"
},
  "geometry": {"coordinates":[-1.12826864454284,50.84675485991439],"type":"Point"}
}