{
  "type": "Feature",
  "properties": {
    "iso:country":"GB",
    "wof:name":"M18 7WR",
    "wof:placetype":"postalcode"
},
  "geometry": {"coordinates":[-2.17235180403944,53.4532887166002],"type":"Point"}
}