{
  "type": "Feature",
  "properties": {
    "iso:country":"GB",
    "wof:name":"TN4 9LN",
    "wof:placetype":"postalcode"
},
  "geometry": {"coordinates":[0.26337822111462,51.1403839091337],"type":"Point"}
}