{
  "type": "Feature",
  "properties": {
    "iso:country":"GB",
    "wof:name":"TQ13 9PH",
    "wof:placetype":"postalcode"
},
  "geometry": {"coordinates":[-3.66008185276268,50.59677681928585],"type":"Point"}
}