{
  "type": "Feature",
  "properties": {
    "date:inception_lower":"1980-01-01",
    "date:inception_upper":"1980-01-31",
    "iso:country":"GB",
    "wof:name":"TR14 0HB",
    "wof:placetype":"postalcode"
},
  "geometry": {"coordinates":[-5.285336,50.231171],"type":"Point"}
}