{
  "type": "Feature",
  "properties": {
    "iso:country": "GB",
    "wof:name": "OX7 6SS",
    "wof:placetype": "postalcode"
  },
  "geometry": {"coordinates":[-1.693046,51.891149],"type":"Point"}
}
