{
  "type": "Feature",
  "properties": {
    "iso:country":"GB",
    "wof:name":"OX7 6SS",
    "wof:placetype":"postalcode"
},
  "geometry": {"coordinates":[-1.69304623219049,51.89114937508751],"type":"Point"}
}