{
  "type": "Feature",
  "properties": {
    "iso:country": "GB",
    "wof:name": "TA4 4PB",
    "wof:placetype": "postalcode"
  },
  "geometry": {"coordinates":[-3.315998,51.159777],"type":"Point"}
}
