{
  "type": "Feature",
  "properties": {
    "iso:country": "GB",
    "wof:name": "TN15 9HT",
    "wof:placetype": "postalcode"
  },
  "geometry": {"coordinates":[0.283813,51.299026],"type":"Point"}
}
