{
  "type": "Feature",
  "properties": {
    "iso:country":"GB",
    "wof:name":"L25 5LN",
    "wof:placetype":"postalcode"
},
  "geometry": {"coordinates":[-2.85449381612171,53.3772407623649],"type":"Point"}
}