{
  "type": "Feature",
  "properties": {
    "iso:country":"GB",
    "wof:name":"GL13 9AA",
    "wof:placetype":"postalcode"
},
  "geometry": {"coordinates":[-2.45965985588291,51.69221709178493],"type":"Point"}
}