{
  "type": "Feature",
  "properties": {
    "iso:country":"GB",
    "wof:name":"NR11 6BB",
    "wof:placetype":"postalcode"
},
  "geometry": {"coordinates":[1.25671170583696,52.79338239804608],"type":"Point"}
}