{
  "type": "Feature",
  "properties": {
    "iso:country":"GB",
    "wof:name":"TD4 6EJ",
    "wof:placetype":"postalcode"
},
  "geometry": {"coordinates":[-2.67689272585747,55.64044079816987],"type":"Point"}
}