{
  "type": "Feature",
  "properties": {
    "date:inception_lower": "1983-03-01",
    "date:inception_upper": "1983-03-01",
    "iso:country": "GB",
    "wof:name": "DE15 0DW",
    "wof:placetype": "postalcode"
  },
  "geometry": {"coordinates":[-1.595683,52.80952],"type":"Point"}
}
