{
  "type": "Feature",
  "properties": {
    "iso:country":"GB",
    "wof:name":"DE15 0DW",
    "wof:placetype":"postalcode"
},
  "geometry": {"coordinates":[-1.59568350244465,52.80952033908446],"type":"Point"}
}