{
  "type": "Feature",
  "properties": {
    "date:inception_lower":"2013-10-01",
    "date:inception_upper":"2013-10-31",
    "iso:country":"GB",
    "wof:name":"DN34 4BU",
    "wof:placetype":"postalcode"
},
  "geometry": {"coordinates":[-0.110708,53.565089],"type":"Point"}
}