{
  "type": "Feature",
  "properties": {
    "iso:country":"GB",
    "wof:name":"DN34 4BU",
    "wof:placetype":"postalcode"
},
  "geometry": {"coordinates":[-0.11070760717007,53.56508944046914],"type":"Point"}
}