{
  "type": "Feature",
  "properties": {
    "iso:country":"GB",
    "wof:name":"B16 8BP",
    "wof:placetype":"postalcode"
},
  "geometry": {"coordinates":[-1.91698040306986,52.47508771864934],"type":"Point"}
}