{
  "type": "Feature",
  "properties": {
    "iso:country": "GB",
    "wof:name": "B16 8BP",
    "wof:placetype": "postalcode"
  },
  "geometry": {"coordinates":[-1.91698,52.475088],"type":"Point"}
}
