{
  "type": "Feature",
  "properties": {
    "date:inception_lower":"1980-01-01",
    "date:inception_upper":"1980-01-31",
    "iso:country":"GB",
    "wof:name":"DY2 9LW",
    "wof:placetype":"postalcode"
},
  "geometry": {"coordinates":[-2.069813,52.483466],"type":"Point"}
}