{
  "type": "Feature",
  "properties": {
    "iso:country":"GB",
    "wof:name":"DN3 2NR",
    "wof:placetype":"postalcode"
},
  "geometry": {"coordinates":[-1.07255717143411,53.55670090316687],"type":"Point"}
}