{
  "type": "Feature",
  "properties": {
    "iso:country":"GB",
    "wof:name":"DH9 8TE",
    "wof:placetype":"postalcode"
},
  "geometry": {"coordinates":[-1.73696272307449,54.8651055580707],"type":"Point"}
}