{
  "type": "Feature",
  "properties": {
    "date:inception_lower":"1993-01-01",
    "date:inception_upper":"1993-01-31",
    "iso:country":"GB",
    "wof:name":"HG2 8PD",
    "wof:placetype":"postalcode"
},
  "geometry": {"coordinates":[-1.519222,53.977842],"type":"Point"}
}