{
  "type": "Feature",
  "properties": {
    "iso:country": "GB",
    "wof:name": "HG2 8PD",
    "wof:placetype": "postalcode"
  },
  "geometry": {"coordinates":[-1.519222,53.977842],"type":"Point"}
}
