{
  "type": "Feature",
  "properties": {
    "iso:country":"GB",
    "wof:name":"HG2 8PD",
    "wof:placetype":"postalcode"
},
  "geometry": {"coordinates":[-1.51922159144237,53.97784192257837],"type":"Point"}
}