{
  "type": "Feature",
  "properties": {
    "date:inception_lower": "2013-10-01",
    "date:inception_upper": "2013-10-01",
    "iso:country": "GB",
    "wof:name": "WV99 1TS",
    "wof:placetype": "postalcode"
  },
  "geometry": {"coordinates":[-2.42142,52.670758],"type":"Point"}
}
