{
  "type": "Feature",
  "properties": {
    "date:inception_lower": "1980-01-01",
    "date:inception_upper": "1980-01-01",
    "iso:country": "GB",
    "wof:name": "NG34 8EY",
    "wof:placetype": "postalcode"
  },
  "geometry": {"coordinates":[-0.524875,53.031483],"type":"Point"}
}
