{
  "type": "Feature",
  "properties": {
    "iso:country": "GB",
    "wof:name": "NG34 8EY",
    "wof:placetype": "postalcode"
  },
  "geometry": {"coordinates":[-0.524875,53.031483],"type":"Point"}
}
