{
  "type": "Feature",
  "properties": {
    "date:inception_lower": "1980-01-01",
    "date:inception_upper": "1980-01-01",
    "iso:country": "GB",
    "wof:name": "WC2N 6EZ",
    "wof:placetype": "postalcode"
  },
  "geometry": {"coordinates":[-0.122743,51.509396],"type":"Point"}
}
