{
  "type": "Feature",
  "properties": {
    "iso:country":"GB",
    "wof:name":"WC2N 6EZ",
    "wof:placetype":"postalcode"
},
  "geometry": {"coordinates":[-0.12274283202982,51.50939559144538],"type":"Point"}
}