{
  "type": "Feature",
  "properties": {
    "iso:country": "GB",
    "wof:name": "G82 2LB",
    "wof:placetype": "postalcode"
  },
  "geometry": {"coordinates":[-4.558375,55.94606],"type":"Point"}
}
