{
  "type": "Feature",
  "properties": {
    "iso:country": "GB",
    "wof:name": "M8 9GH",
    "wof:placetype": "postalcode"
  },
  "geometry": {"coordinates":[-2.247674,53.509981],"type":"Point"}
}
