{
  "type": "Feature",
  "properties": {
    "iso:country":"GB",
    "wof:name":"SE9 4RW",
    "wof:placetype":"postalcode"
},
  "geometry": {"coordinates":[0.03665579033694,51.43920905650812],"type":"Point"}
}