{
  "type": "Feature",
  "properties": {
    "iso:country":"GB",
    "wof:name":"W1K 4DS",
    "wof:placetype":"postalcode"
},
  "geometry": {"coordinates":[-0.14648818859365,51.5123271265385],"type":"Point"}
}