{
  "type": "Feature",
  "properties": {
    "iso:country":"GB",
    "wof:name":"BL5 2NX",
    "wof:placetype":"postalcode"
},
  "geometry": {"coordinates":[-2.51888352849151,53.54106514309206],"type":"Point"}
}