{
  "type": "Feature",
  "properties": {
    "iso:country": "GB",
    "wof:name": "LL57 2BU",
    "wof:placetype": "postalcode"
  },
  "geometry": {"coordinates":[-4.128229,53.232326],"type":"Point"}
}
