{
  "type": "Feature",
  "properties": {
    "iso:country":"GB",
    "wof:name":"LE4 4HQ",
    "wof:placetype":"postalcode"
},
  "geometry": {"coordinates":[-1.12017332999964,52.67732448528677],"type":"Point"}
}