{
  "type": "Feature",
  "properties": {
    "iso:country": "GB",
    "wof:name": "LE4 4HQ",
    "wof:placetype": "postalcode"
  },
  "geometry": {"coordinates":[-1.120173,52.677324],"type":"Point"}
}
