{
  "type": "Feature",
  "properties": {
    "iso:country":"GB",
    "wof:name":"ME9 8DH",
    "wof:placetype":"postalcode"
},
  "geometry": {"coordinates":[0.68452158988824,51.34020404856166],"type":"Point"}
}