{
  "type": "Feature",
  "properties": {
    "iso:country": "GB",
    "wof:name": "ME9 8DH",
    "wof:placetype": "postalcode"
  },
  "geometry": {"coordinates":[0.684685,51.340022],"type":"Point"}
}
