{
  "type": "Feature",
  "properties": {
    "date:inception_lower":"2002-06-01",
    "date:inception_upper":"2002-06-30",
    "iso:country":"GB",
    "wof:name":"TQ14 9HH",
    "wof:placetype":"postalcode"
},
  "geometry": {"coordinates":[-3.505009,50.564017],"type":"Point"}
}