{
  "type": "Feature",
  "properties": {
    "iso:country":"GB",
    "wof:name":"YO24 4AG",
    "wof:placetype":"postalcode"
},
  "geometry": {"coordinates":[-1.09561128972919,53.95487274189855],"type":"Point"}
}