{
  "type": "Feature",
  "properties": {
    "date:inception_lower":"1998-06-01",
    "date:inception_upper":"1998-06-30",
    "iso:country":"GB",
    "wof:name":"YO24 4AG",
    "wof:placetype":"postalcode"
},
  "geometry": {"coordinates":[-1.095611,53.954873],"type":"Point"}
}