{
  "type": "Feature",
  "properties": {
    "iso:country":"GB",
    "wof:name":"GL9 1AR",
    "wof:placetype":"postalcode"
},
  "geometry": {"coordinates":[-2.31681532673255,51.57886876294221],"type":"Point"}
}