{
  "type": "Feature",
  "properties": {
    "iso:country":"GB",
    "wof:name":"WV15 6LT",
    "wof:placetype":"postalcode"
},
  "geometry": {"coordinates":[-2.34694486487623,52.46129296067188],"type":"Point"}
}