{
  "type": "Feature",
  "properties": {
    "iso:country": "GB",
    "wof:name": "WV15 6LT",
    "wof:placetype": "postalcode"
  },
  "geometry": {"coordinates":[-2.346945,52.461293],"type":"Point"}
}
