{
  "type": "Feature",
  "properties": {
    "date:inception_lower":"1981-09-01",
    "date:inception_upper":"1981-09-30",
    "iso:country":"GB",
    "wof:name":"WN3 5PN",
    "wof:placetype":"postalcode"
},
  "geometry": {"coordinates":[-2.64107,53.519295],"type":"Point"}
}