{
  "type": "Feature",
  "properties": {
    "iso:country":"GB",
    "wof:name":"WN3 5PN",
    "wof:placetype":"postalcode"
},
  "geometry": {"coordinates":[-2.64106968343748,53.51929534964916],"type":"Point"}
}