{
  "type": "Feature",
  "properties": {
    "iso:country":"GB",
    "wof:name":"SP2 9BX",
    "wof:placetype":"postalcode"
},
  "geometry": {"coordinates":[-1.81993671387598,51.08019888273873],"type":"Point"}
}