{
  "type": "Feature",
  "properties": {
    "iso:country":"GB",
    "wof:name":"B74 2RQ",
    "wof:placetype":"postalcode"
},
  "geometry": {"coordinates":[-1.84148308394708,52.58185569554917],"type":"Point"}
}