{
  "type": "Feature",
  "properties": {
    "iso:country": "GB",
    "wof:name": "ST16 1YL",
    "wof:placetype": "postalcode"
  },
  "geometry": {"coordinates":[-2.133915,52.827239],"type":"Point"}
}
