{
  "type": "Feature",
  "properties": {
    "iso:country": "GB",
    "wof:name": "PL5 4JU",
    "wof:placetype": "postalcode"
  },
  "geometry": {"coordinates":[-4.163762,50.423642],"type":"Point"}
}
