{
  "type": "Feature",
  "properties": {
    "iso:country":"GB",
    "wof:name":"PL5 4JU",
    "wof:placetype":"postalcode"
},
  "geometry": {"coordinates":[-4.16376177794694,50.4236419871086],"type":"Point"}
}