{
  "type": "Feature",
  "properties": {
    "iso:country": "GB",
    "wof:name": "OX27 9AH",
    "wof:placetype": "postalcode"
  },
  "geometry": {"coordinates":[-1.11475,51.946771],"type":"Point"}
}
