{
  "type": "Feature",
  "properties": {
    "date:inception_lower":"1980-01-01",
    "date:inception_upper":"1980-01-31",
    "iso:country":"GB",
    "wof:name":"WA3 3QY",
    "wof:placetype":"postalcode"
},
  "geometry": {"coordinates":[-2.607943,53.479919],"type":"Point"}
}