{
  "type": "Feature",
  "properties": {
    "iso:country":"GB",
    "wof:name":"WA3 3QY",
    "wof:placetype":"postalcode"
},
  "geometry": {"coordinates":[-2.60794334300325,53.47991881366571],"type":"Point"}
}