{
  "type": "Feature",
  "properties": {
    "iso:country":"GB",
    "wof:name":"WF2 6JW",
    "wof:placetype":"postalcode"
},
  "geometry": {"coordinates":[-1.48016073492375,53.65221343601701],"type":"Point"}
}