{
  "type": "Feature",
  "properties": {
    "date:inception_lower": "2015-07-01",
    "date:inception_upper": "2015-07-01",
    "iso:country": "GB",
    "wof:name": "HP11 1GR",
    "wof:placetype": "postalcode"
  },
  "geometry": {"coordinates":[-0.727778,51.621005],"type":"Point"}
}
