{
  "type": "Feature",
  "properties": {
    "iso:country":"GB",
    "wof:name":"G32 0TR",
    "wof:placetype":"postalcode"
},
  "geometry": {"coordinates":[-4.14360258787609,55.85120767249577],"type":"Point"}
}