{
  "type": "Feature",
  "properties": {
    "iso:country": "GB",
    "wof:name": "RG21 7RF",
    "wof:placetype": "postalcode"
  },
  "geometry": {"coordinates":[-1.098538,51.264306],"type":"Point"}
}
