{
  "type": "Feature",
  "properties": {
    "iso:country":"GB",
    "wof:name":"TQ9 7TD",
    "wof:placetype":"postalcode"
},
  "geometry": {"coordinates":[-3.71154848925231,50.39372557603054],"type":"Point"}
}