{
  "type": "Feature",
  "properties": {
    "iso:country": "GB",
    "wof:name": "TQ9 7TD",
    "wof:placetype": "postalcode"
  },
  "geometry": {"coordinates":[-3.711548,50.393726],"type":"Point"}
}
