{
  "type": "Feature",
  "properties": {
    "iso:country":"GB",
    "wof:name":"CO6 1BN",
    "wof:placetype":"postalcode"
},
  "geometry": {"coordinates":[0.80811261349244,51.88107646477413],"type":"Point"}
}