{
  "type": "Feature",
  "properties": {
    "iso:country": "GB",
    "wof:name": "CO6 1BN",
    "wof:placetype": "postalcode"
  },
  "geometry": {"coordinates":[0.808113,51.881076],"type":"Point"}
}
