{
  "type": "Feature",
  "properties": {
    "iso:country":"GB",
    "wof:name":"RH20 2EA",
    "wof:placetype":"postalcode"
},
  "geometry": {"coordinates":[-0.48235545519186,50.95738540174037],"type":"Point"}
}