{
  "type": "Feature",
  "properties": {
    "iso:country":"GB",
    "wof:name":"LE5 5HE",
    "wof:placetype":"postalcode"
},
  "geometry": {"coordinates":[-1.10684069522474,52.62828334415604],"type":"Point"}
}