{
  "type": "Feature",
  "properties": {
    "iso:country":"GB",
    "wof:name":"ME19 4FL",
    "wof:placetype":"postalcode"
},
  "geometry": {"coordinates":[0.39418827076895,51.26923781893573],"type":"Point"}
}