{
  "type": "Feature",
  "properties": {
    "iso:country": "GB",
    "wof:name": "ME19 4FL",
    "wof:placetype": "postalcode"
  },
  "geometry": {"coordinates":[0.394188,51.269238],"type":"Point"}
}
