{
  "type": "Feature",
  "properties": {
    "iso:country":"GB",
    "wof:name":"S81 9LZ",
    "wof:placetype":"postalcode"
},
  "geometry": {"coordinates":[-1.11712052894768,53.3591411110569],"type":"Point"}
}