{
  "type": "Feature",
  "properties": {
    "iso:country":"GB",
    "wof:name":"WC1N 2LW",
    "wof:placetype":"postalcode"
},
  "geometry": {"coordinates":[-0.11636149929841,51.52365434772378],"type":"Point"}
}