{
  "type": "Feature",
  "properties": {
    "iso:country":"GB",
    "wof:name":"BN2 9XQ",
    "wof:placetype":"postalcode"
},
  "geometry": {"coordinates":[-0.12133569406862,50.83060819697654],"type":"Point"}
}