{
  "type": "Feature",
  "properties": {
    "iso:country":"GB",
    "wof:name":"LL17 0AU",
    "wof:placetype":"postalcode"
},
  "geometry": {"coordinates":[-3.38374186029318,53.24581416930486],"type":"Point"}
}