{
  "type": "Feature",
  "properties": {
    "iso:country": "GB",
    "wof:name": "LL17 0AU",
    "wof:placetype": "postalcode"
  },
  "geometry": {"coordinates":[-3.383742,53.245814],"type":"Point"}
}
