{
  "type": "Feature",
  "properties": {
    "iso:country": "GB",
    "wof:name": "NG9 5FT",
    "wof:placetype": "postalcode"
  },
  "geometry": {"coordinates":[-1.244472,52.918089],"type":"Point"}
}
