{
  "type": "Feature",
  "properties": {
    "date:inception_lower": "2005-03-01",
    "date:inception_upper": "2005-03-01",
    "iso:country": "GB",
    "wof:name": "LS5 3GZ",
    "wof:placetype": "postalcode"
  },
  "geometry": {"coordinates":[-1.595239,53.817697],"type":"Point"}
}
