{
  "type": "Feature",
  "properties": {
    "iso:country": "GB",
    "wof:name": "NE11 0UZ",
    "wof:placetype": "postalcode"
  },
  "geometry": {"coordinates":[-1.610575,54.933189],"type":"Point"}
}
