{
  "type": "Feature",
  "properties": {
    "date:inception_lower": "1980-01-01",
    "date:inception_upper": "1980-01-01",
    "iso:country": "GB",
    "wof:name": "HD4 6XY",
    "wof:placetype": "postalcode"
  },
  "geometry": {"coordinates":[-1.754199,53.59],"type":"Point"}
}
