{
  "type": "Feature",
  "properties": {
    "iso:country": "GB",
    "wof:name": "HD4 6XY",
    "wof:placetype": "postalcode"
  },
  "geometry": {"coordinates":[-1.754199,53.59],"type":"Point"}
}
