{
  "type": "Feature",
  "properties": {
    "iso:country": "GB",
    "wof:name": "SR2 0DY",
    "wof:placetype": "postalcode"
  },
  "geometry": {"coordinates":[-1.372286,54.877617],"type":"Point"}
}
