{
  "type": "Feature",
  "properties": {
    "iso:country":"GB",
    "wof:name":"OX10 6DZ",
    "wof:placetype":"postalcode"
},
  "geometry": {"coordinates":[-1.09110948537342,51.61037056355351],"type":"Point"}
}