{
  "type": "Feature",
  "properties": {
    "iso:country":"GB",
    "wof:name":"G83 0TA",
    "wof:placetype":"postalcode"
},
  "geometry": {"coordinates":[-4.57931272528761,55.98461197860048],"type":"Point"}
}