{
  "type": "Feature",
  "properties": {
    "iso:country":"GB",
    "wof:name":"ST20 0QW",
    "wof:placetype":"postalcode"
},
  "geometry": {"coordinates":[-2.35102612052356,52.84730916400196],"type":"Point"}
}