{
  "type": "Feature",
  "properties": {
    "date:inception_lower": "1982-03-01",
    "date:inception_upper": "1982-03-01",
    "iso:country": "GB",
    "wof:name": "ST20 0QW",
    "wof:placetype": "postalcode"
  },
  "geometry": {"coordinates":[-2.351026,52.847309],"type":"Point"}
}
