{
  "type": "Feature",
  "properties": {
    "iso:country": "GB",
    "wof:name": "CW11 3JU",
    "wof:placetype": "postalcode"
  },
  "geometry": {"coordinates":[-2.399827,53.145012],"type":"Point"}
}
