{
  "type": "Feature",
  "properties": {
    "iso:country":"GB",
    "wof:name":"CW11 3JU",
    "wof:placetype":"postalcode"
},
  "geometry": {"coordinates":[-2.39975009979259,53.14475248699829],"type":"Point"}
}