{
  "type": "Feature",
  "properties": {
    "date:inception_lower": "1980-01-01",
    "date:inception_upper": "1980-01-01",
    "iso:country": "GB",
    "wof:name": "RH20 3AY",
    "wof:placetype": "postalcode"
  },
  "geometry": {"coordinates":[-0.392718,50.941081],"type":"Point"}
}
