{
  "type": "Feature",
  "properties": {
    "iso:country": "GB",
    "wof:name": "RH20 3AY",
    "wof:placetype": "postalcode"
  },
  "geometry": {"coordinates":[-0.392718,50.941081],"type":"Point"}
}
