{
  "type": "Feature",
  "properties": {
    "iso:country":"GB",
    "wof:name":"RH20 3AY",
    "wof:placetype":"postalcode"
},
  "geometry": {"coordinates":[-0.39215095500672,50.94092622762064],"type":"Point"}
}