{
  "type": "Feature",
  "properties": {
    "iso:country":"GB",
    "wof:name":"EX2 4RX",
    "wof:placetype":"postalcode"
},
  "geometry": {"coordinates":[-3.5215724532754,50.71334372260237],"type":"Point"}
}