{
  "type": "Feature",
  "properties": {
    "date:inception_lower":"1996-06-01",
    "date:inception_upper":"1996-06-30",
    "iso:country":"GB",
    "wof:name":"BN41 2JB",
    "wof:placetype":"postalcode"
},
  "geometry": {"coordinates":[-0.21772,50.848749],"type":"Point"}
}