{
  "type": "Feature",
  "properties": {
    "iso:country": "GB",
    "wof:name": "BN41 2JB",
    "wof:placetype": "postalcode"
  },
  "geometry": {"coordinates":[-0.21772,50.848749],"type":"Point"}
}
