{
  "type": "Feature",
  "properties": {
    "date:inception_lower": "2021-05-01",
    "date:inception_upper": "2021-05-01",
    "iso:country": "GB",
    "wof:name": "WF15 7FB",
    "wof:placetype": "postalcode"
  },
  "geometry": {"coordinates":[-1.682763,53.706551],"type":"Point"}
}
