{
  "type": "Feature",
  "properties": {
    "date:inception_lower": "2021-07-01",
    "date:inception_upper": "2021-07-01",
    "iso:country": "GB",
    "wof:name": "G74 5EA",
    "wof:placetype": "postalcode"
  },
  "geometry": {"coordinates":[-4.231318,55.77067],"type":"Point"}
}
