{
  "type": "Feature",
  "properties": {
    "iso:country":"GB",
    "wof:name":"WD4 9LP",
    "wof:placetype":"postalcode"
},
  "geometry": {"coordinates":[-0.50112224205692,51.70798005924735],"type":"Point"}
}