{
  "type": "Feature",
  "properties": {
    "iso:country": "GB",
    "wof:name": "BH25 7LG",
    "wof:placetype": "postalcode"
  },
  "geometry": {"coordinates":[-1.668231,50.743884],"type":"Point"}
}
