{
  "type": "Feature",
  "properties": {
    "iso:country":"GB",
    "wof:name":"BH25 7LG",
    "wof:placetype":"postalcode"
},
  "geometry": {"coordinates":[-1.66823117354654,50.74388394626077],"type":"Point"}
}