{
  "type": "Feature",
  "properties": {
    "iso:country": "GB",
    "wof:name": "LN8 5JN",
    "wof:placetype": "postalcode"
  },
  "geometry": {"coordinates":[-0.295479,53.228132],"type":"Point"}
}
