{
  "type": "Feature",
  "properties": {
    "iso:country":"GB",
    "wof:name":"LN8 5JN",
    "wof:placetype":"postalcode"
},
  "geometry": {"coordinates":[-0.30931522587632,53.2389944659067],"type":"Point"}
}