{
  "type": "Feature",
  "properties": {
    "date:inception_lower": "1996-12-01",
    "date:inception_upper": "1996-12-01",
    "iso:country": "GB",
    "wof:name": "LN8 5JN",
    "wof:placetype": "postalcode"
  },
  "geometry": {"coordinates":[-0.291235,53.230894],"type":"Point"}
}
