{
  "type": "Feature",
  "properties": {
    "iso:country": "GB",
    "wof:name": "BB2 5HN",
    "wof:placetype": "postalcode"
  },
  "geometry": {"coordinates":[-2.5298,53.727354],"type":"Point"}
}
