{
  "type": "Feature",
  "properties": {
    "iso:country":"GB",
    "wof:name":"BB2 5HN",
    "wof:placetype":"postalcode"
},
  "geometry": {"coordinates":[-2.52979958502643,53.72735404434957],"type":"Point"}
}