{
  "type": "Feature",
  "properties": {
    "date:inception_lower": "2009-11-01",
    "date:inception_upper": "2009-11-01",
    "iso:country": "GB",
    "wof:name": "LS1 4GN",
    "wof:placetype": "postalcode"
  },
  "geometry": {"coordinates":[-1.548551,53.793344],"type":"Point"}
}
