{
  "type": "Feature",
  "properties": {
    "iso:country": "GB",
    "wof:name": "L21 8LB",
    "wof:placetype": "postalcode"
  },
  "geometry": {"coordinates":[-2.99914,53.462798],"type":"Point"}
}
