{
  "type": "Feature",
  "properties": {
    "date:inception_lower": "1980-01-01",
    "date:inception_upper": "1980-01-01",
    "iso:country": "GB",
    "wof:name": "FK2 8JL",
    "wof:placetype": "postalcode"
  },
  "geometry": {"coordinates":[-3.769418,56.067313],"type":"Point"}
}
