{
  "type": "Feature",
  "properties": {
    "iso:country":"GB",
    "wof:name":"CT18 8EJ",
    "wof:placetype":"postalcode"
},
  "geometry": {"coordinates":[1.08572877825058,51.12645060149182],"type":"Point"}
}