{
  "type": "Feature",
  "properties": {
    "iso:country":"GB",
    "wof:name":"PO40 9QR",
    "wof:placetype":"postalcode"
},
  "geometry": {"coordinates":[-1.51472560126355,50.67645847858596],"type":"Point"}
}