{
  "type": "Feature",
  "properties": {
    "date:inception_lower": "1980-01-01",
    "date:inception_upper": "1980-01-01",
    "iso:country": "GB",
    "wof:name": "DE15 9SW",
    "wof:placetype": "postalcode"
  },
  "geometry": {"coordinates":[-1.60933,52.783182],"type":"Point"}
}
