{
  "type": "Feature",
  "properties": {
    "date:inception_lower": "2016-12-01",
    "date:inception_upper": "2016-12-01",
    "iso:country": "GB",
    "wof:name": "EH30 9AU",
    "wof:placetype": "postalcode"
  },
  "geometry": {"coordinates":[-3.381303,55.984689],"type":"Point"}
}
