{
  "type": "Feature",
  "properties": {
    "iso:country":"GB",
    "wof:name":"FY5 2JR",
    "wof:placetype":"postalcode"
},
  "geometry": {"coordinates":[-3.02474029837677,53.88285938850275],"type":"Point"}
}