{
  "type": "Feature",
  "properties": {
    "iso:country": "GB",
    "wof:name": "BL3 3AR",
    "wof:placetype": "postalcode"
  },
  "geometry": {"coordinates":[-2.439099,53.559613],"type":"Point"}
}
