{
  "type": "Feature",
  "properties": {
    "iso:country":"GB",
    "wof:name":"BL3 3AR",
    "wof:placetype":"postalcode"
},
  "geometry": {"coordinates":[-2.43909935957072,53.55961335582519],"type":"Point"}
}