{
  "type": "Feature",
  "properties": {
    "iso:country":"GB",
    "wof:name":"EH47 7HE",
    "wof:placetype":"postalcode"
},
  "geometry": {"coordinates":[-3.62734134028398,55.87713772441258],"type":"Point"}
}