{
  "type": "Feature",
  "properties": {
    "iso:country": "GB",
    "wof:name": "BS5 7SQ",
    "wof:placetype": "postalcode"
  },
  "geometry": {"coordinates":[-2.534712,51.464533],"type":"Point"}
}
