{
  "type": "Feature",
  "properties": {
    "iso:country":"GB",
    "wof:name":"YO32 9LX",
    "wof:placetype":"postalcode"
},
  "geometry": {"coordinates":[-1.05522786492227,53.98584950985875],"type":"Point"}
}