{
  "type": "Feature",
  "properties": {
    "date:inception_lower": "1999-12-01",
    "date:inception_upper": "1999-12-01",
    "iso:country": "GB",
    "wof:name": "YO32 9LX",
    "wof:placetype": "postalcode"
  },
  "geometry": {"coordinates":[-1.055228,53.98585],"type":"Point"}
}
