{
  "type": "Feature",
  "properties": {
    "date:inception_lower": "1981-06-01",
    "date:inception_upper": "1981-06-01",
    "iso:country": "GB",
    "wof:name": "DE7 4HG",
    "wof:placetype": "postalcode"
  },
  "geometry": {"coordinates":[-1.325946,52.961989],"type":"Point"}
}
