{
  "type": "Feature",
  "properties": {
    "iso:country":"GB",
    "wof:name":"SW1X 0JX",
    "wof:placetype":"postalcode"
},
  "geometry": {"coordinates":[-0.16068092673523,51.49665182390935],"type":"Point"}
}