{
  "type": "Feature",
  "properties": {
    "date:inception_lower": "2016-07-01",
    "date:inception_upper": "2016-07-01",
    "iso:country": "GB",
    "wof:name": "LS25 6QB",
    "wof:placetype": "postalcode"
  },
  "geometry": {"coordinates":[-1.242287,53.794452],"type":"Point"}
}
