{
  "type": "Feature",
  "properties": {
    "iso:country":"GB",
    "wof:name":"EX39 2RH",
    "wof:placetype":"postalcode"
},
  "geometry": {"coordinates":[-4.20448770171132,51.03221903603155],"type":"Point"}
}