{
  "type": "Feature",
  "properties": {
    "iso:country":"GB",
    "wof:name":"BS30 8AW",
    "wof:placetype":"postalcode"
},
  "geometry": {"coordinates":[-2.48718841612561,51.44238701081014],"type":"Point"}
}