{
  "type": "Feature",
  "properties": {
    "iso:country":"GB",
    "wof:name":"GU14 8BU",
    "wof:placetype":"postalcode"
},
  "geometry": {"coordinates":[-0.74388673480648,51.30154890036091],"type":"Point"}
}