{
  "type": "Feature",
  "properties": {
    "iso:country": "GB",
    "wof:name": "GU14 8BU",
    "wof:placetype": "postalcode"
  },
  "geometry": {"coordinates":[-0.743887,51.301549],"type":"Point"}
}
