{
  "type": "Feature",
  "properties": {
    "date:inception_lower": "2020-09-01",
    "date:inception_upper": "2020-09-01",
    "iso:country": "GB",
    "wof:name": "ME1 3GN",
    "wof:placetype": "postalcode"
  },
  "geometry": {"coordinates":[0.462726,51.343614],"type":"Point"}
}
