{
  "type": "Feature",
  "properties": {
    "iso:country": "GB",
    "wof:name": "OX12 9ET",
    "wof:placetype": "postalcode"
  },
  "geometry": {"coordinates":[-1.432205,51.597006],"type":"Point"}
}
