{
  "type": "Feature",
  "properties": {
    "iso:country":"GB",
    "wof:name":"N13 4DQ",
    "wof:placetype":"postalcode"
},
  "geometry": {"coordinates":[-0.11016895233355,51.61536779993305],"type":"Point"}
}