{
  "type": "Feature",
  "properties": {
    "iso:country": "GB",
    "wof:name": "N13 4DQ",
    "wof:placetype": "postalcode"
  },
  "geometry": {"coordinates":[-0.110169,51.615368],"type":"Point"}
}
