{
  "type": "Feature",
  "properties": {
    "date:inception_lower": "2022-05-01",
    "date:inception_upper": "2022-05-01",
    "iso:country": "GB",
    "wof:name": "SO24 0FG",
    "wof:placetype": "postalcode"
  },
  "geometry": {"coordinates":[-1.093904,51.087092],"type":"Point"}
}
