{
  "type": "Feature",
  "properties": {
    "date:inception_lower":"1980-01-01",
    "date:inception_upper":"1980-01-31",
    "iso:country":"GB",
    "wof:name":"SA1 4JP",
    "wof:placetype":"postalcode"
},
  "geometry": {"coordinates":[-3.957413,51.618438],"type":"Point"}
}