{
  "type": "Feature",
  "properties": {
    "iso:country":"GB",
    "wof:name":"SA1 4JP",
    "wof:placetype":"postalcode"
},
  "geometry": {"coordinates":[-3.95743920041827,51.61845051063656],"type":"Point"}
}