{
  "type": "Feature",
  "properties": {
    "iso:country":"GB",
    "wof:name":"AB51 8XL",
    "wof:placetype":"postalcode"
},
  "geometry": {"coordinates":[-2.47109257931308,57.4372807622939],"type":"Point"}
}