{
  "type": "Feature",
  "properties": {
    "iso:country":"GB",
    "wof:name":"CO7 9HW",
    "wof:placetype":"postalcode"
},
  "geometry": {"coordinates":[0.9668420085363,51.87020850085996],"type":"Point"}
}