{
  "type": "Feature",
  "properties": {
    "iso:country": "GB",
    "wof:name": "RH20 1BN",
    "wof:placetype": "postalcode"
  },
  "geometry": {"coordinates":[-0.495561,50.972197],"type":"Point"}
}
