{
  "type": "Feature",
  "properties": {
    "date:inception_lower": "2015-07-01",
    "date:inception_upper": "2015-07-01",
    "iso:country": "GB",
    "wof:name": "CT3 3FD",
    "wof:placetype": "postalcode"
  },
  "geometry": {"coordinates":[1.19805,51.229522],"type":"Point"}
}
