{
  "type": "Feature",
  "properties": {
    "iso:country": "GB",
    "wof:name": "CT3 3FD",
    "wof:placetype": "postalcode"
  },
  "geometry": {"coordinates":[1.19805,51.229522],"type":"Point"}
}
