{
  "type": "Feature",
  "properties": {
    "date:inception_lower": "2023-10-01",
    "date:inception_upper": "2023-10-01",
    "iso:country": "GB",
    "wof:name": "G11 5BG",
    "wof:placetype": "postalcode"
  },
  "geometry": {"coordinates":[-4.310285,55.871076],"type":"Point"}
}
