{
  "type": "Feature",
  "properties": {
    "date:inception_lower": "1980-01-01",
    "date:inception_upper": "1980-01-01",
    "iso:country": "GB",
    "wof:name": "M11 2NG",
    "wof:placetype": "postalcode"
  },
  "geometry": {"coordinates":[-2.175835,53.473038],"type":"Point"}
}
