{
  "type": "Feature",
  "properties": {
    "iso:country":"GB",
    "wof:name":"M11 2NG",
    "wof:placetype":"postalcode"
},
  "geometry": {"coordinates":[-2.17606270695018,53.47303097426409],"type":"Point"}
}