{
  "type": "Feature",
  "properties": {
    "iso:country":"GB",
    "wof:name":"HP9 1PG",
    "wof:placetype":"postalcode"
},
  "geometry": {"coordinates":[-0.6506764196872,51.60759193886508],"type":"Point"}
}