{
  "type": "Feature",
  "properties": {
    "iso:country":"GB",
    "wof:name":"ME12 3FP",
    "wof:placetype":"postalcode"
},
  "geometry": {"coordinates":[0.80173548436352,51.41378081962047],"type":"Point"}
}