{
  "type": "Feature",
  "properties": {
    "date:inception_lower": "2010-08-01",
    "date:inception_upper": "2010-08-01",
    "iso:country": "GB",
    "wof:name": "ME12 3FP",
    "wof:placetype": "postalcode"
  },
  "geometry": {"coordinates":[0.801736,51.413781],"type":"Point"}
}
