{
  "type": "Feature",
  "properties": {
    "date:inception_lower": "1980-01-01",
    "date:inception_upper": "1980-01-01",
    "iso:country": "GB",
    "wof:name": "GU14 9JX",
    "wof:placetype": "postalcode"
  },
  "geometry": {"coordinates":[-0.785395,51.307041],"type":"Point"}
}
