{
  "type": "Feature",
  "properties": {
    "iso:country":"GB",
    "wof:name":"GU14 9JX",
    "wof:placetype":"postalcode"
},
  "geometry": {"coordinates":[-0.78523763800139,51.30716459783583],"type":"Point"}
}