{
  "type": "Feature",
  "properties": {
    "iso:country": "GB",
    "wof:name": "GU14 9JX",
    "wof:placetype": "postalcode"
  },
  "geometry": {"coordinates":[-0.78522,51.307165],"type":"Point"}
}
