{
  "type": "Feature",
  "properties": {
    "iso:country":"GB",
    "wof:name":"NN14 1ES",
    "wof:placetype":"postalcode"
},
  "geometry": {"coordinates":[-0.73971933034659,52.36308130348876],"type":"Point"}
}