{
  "type": "Feature",
  "properties": {
    "iso:country": "GB",
    "wof:name": "GL3 2PW",
    "wof:placetype": "postalcode"
  },
  "geometry": {"coordinates":[-2.158854,51.8805],"type":"Point"}
}
