{
  "type": "Feature",
  "properties": {
    "date:inception_lower":"1980-01-01",
    "date:inception_upper":"1980-01-31",
    "iso:country":"GB",
    "wof:name":"IP8 3AX",
    "wof:placetype":"postalcode"
},
  "geometry": {"coordinates":[1.102792,52.057109],"type":"Point"}
}