{
  "type": "Feature",
  "properties": {
    "iso:country":"GB",
    "wof:name":"IP8 3AX",
    "wof:placetype":"postalcode"
},
  "geometry": {"coordinates":[1.10279166107313,52.05710939202175],"type":"Point"}
}