{
  "type": "Feature",
  "properties": {
    "iso:country": "GB",
    "wof:name": "IP8 3AX",
    "wof:placetype": "postalcode"
  },
  "geometry": {"coordinates":[1.102835,52.057106],"type":"Point"}
}
