{
  "type": "Feature",
  "properties": {
    "iso:country":"GB",
    "wof:name":"W1B 5PF",
    "wof:placetype":"postalcode"
},
  "geometry": {"coordinates":[-0.1387611518986,51.51238461083667],"type":"Point"}
}