{
  "type": "Feature",
  "properties": {
    "iso:country": "GB",
    "wof:name": "WA10 1DZ",
    "wof:placetype": "postalcode"
  },
  "geometry": {"coordinates":[-2.733826,53.453846],"type":"Point"}
}
