{
  "type": "Feature",
  "properties": {
    "iso:country":"GB",
    "wof:name":"TR26 2DG",
    "wof:placetype":"postalcode"
},
  "geometry": {"coordinates":[-5.4792872732313,50.20886650919599],"type":"Point"}
}