{
  "type": "Feature",
  "properties": {
    "iso:country":"GB",
    "wof:name":"UB5 5QB",
    "wof:placetype":"postalcode"
},
  "geometry": {"coordinates":[-0.3772787973342,51.54140188062427],"type":"Point"}
}