{
  "type": "Feature",
  "properties": {
    "iso:country": "GB",
    "wof:name": "UB5 5QB",
    "wof:placetype": "postalcode"
  },
  "geometry": {"coordinates":[-0.377279,51.541402],"type":"Point"}
}
