{
  "type": "Feature",
  "properties": {
    "iso:country":"GB",
    "wof:name":"DN21 5QE",
    "wof:placetype":"postalcode"
},
  "geometry": {"coordinates":[-0.6887002211444,53.41425420565832],"type":"Point"}
}