{
  "type": "Feature",
  "properties": {
    "date:inception_lower": "2004-08-01",
    "date:inception_upper": "2004-08-01",
    "iso:country": "GB",
    "wof:name": "DN21 5QE",
    "wof:placetype": "postalcode"
  },
  "geometry": {"coordinates":[-0.6887,53.414254],"type":"Point"}
}
