{
  "type": "Feature",
  "properties": {
    "date:inception_lower": "1980-01-01",
    "date:inception_upper": "1980-01-01",
    "iso:country": "GB",
    "wof:name": "IP7 5PB",
    "wof:placetype": "postalcode"
  },
  "geometry": {"coordinates":[0.927516,52.035287],"type":"Point"}
}
