{
  "type": "Feature",
  "properties": {
    "iso:country": "GB",
    "wof:name": "NE15 9AU",
    "wof:placetype": "postalcode"
  },
  "geometry": {"coordinates":[-1.75042,54.991641],"type":"Point"}
}
