{
  "type": "Feature",
  "properties": {
    "iso:country":"GB",
    "wof:name":"NW11 7RJ",
    "wof:placetype":"postalcode"
},
  "geometry": {"coordinates":[-0.19197908252757,51.57144288290285],"type":"Point"}
}