{
  "type": "Feature",
  "properties": {
    "iso:country":"GB",
    "wof:name":"SW19 4SQ",
    "wof:placetype":"postalcode"
},
  "geometry": {"coordinates":[-0.22218798794579,51.42021097710467],"type":"Point"}
}