{
  "type": "Feature",
  "properties": {
    "iso:country":"GB",
    "wof:name":"S61 4JD",
    "wof:placetype":"postalcode"
},
  "geometry": {"coordinates":[-1.38317996525513,53.45389895187476],"type":"Point"}
}