{
  "type": "Feature",
  "properties": {
    "iso:country":"GB",
    "wof:name":"LA13 0LA",
    "wof:placetype":"postalcode"
},
  "geometry": {"coordinates":[-3.18761799380725,54.11979818668784],"type":"Point"}
}