{
  "type": "Feature",
  "properties": {
    "date:inception_lower":"1980-01-01",
    "date:inception_upper":"1980-01-31",
    "iso:country":"GB",
    "wof:name":"ML1 5AP",
    "wof:placetype":"postalcode"
},
  "geometry": {"coordinates":[-3.95289,55.810905],"type":"Point"}
}