{
  "type": "Feature",
  "properties": {
    "iso:country":"GB",
    "wof:name":"ML1 5AP",
    "wof:placetype":"postalcode"
},
  "geometry": {"coordinates":[-3.95288970907416,55.81090494790332],"type":"Point"}
}