{
  "type": "Feature",
  "properties": {
    "iso:country": "GB",
    "wof:name": "BS9 2QB",
    "wof:placetype": "postalcode"
  },
  "geometry": {"coordinates":[-2.652963,51.49134],"type":"Point"}
}
