{
  "type": "Feature",
  "properties": {
    "iso:country":"GB",
    "wof:name":"BS9 2QB",
    "wof:placetype":"postalcode"
},
  "geometry": {"coordinates":[-2.65296264411281,51.49134033898002],"type":"Point"}
}