{
  "type": "Feature",
  "properties": {
    "iso:country":"GB",
    "wof:name":"HD4 7NG",
    "wof:placetype":"postalcode"
},
  "geometry": {"coordinates":[-1.79238809866083,53.61812511045289],"type":"Point"}
}