{
  "type": "Feature",
  "properties": {
    "date:inception_lower":"1980-01-01",
    "date:inception_upper":"1980-01-31",
    "iso:country":"GB",
    "wof:name":"PO6 4DX",
    "wof:placetype":"postalcode"
},
  "geometry": {"coordinates":[-1.098375,50.85231],"type":"Point"}
}