{
  "type": "Feature",
  "properties": {
    "iso:country": "GB",
    "wof:name": "PO6 4DX",
    "wof:placetype": "postalcode"
  },
  "geometry": {"coordinates":[-1.098375,50.85231],"type":"Point"}
}
