{
  "type": "Feature",
  "properties": {
    "iso:country": "GB",
    "wof:name": "SA73 2PG",
    "wof:placetype": "postalcode"
  },
  "geometry": {"coordinates":[-5.027433,51.718046],"type":"Point"}
}
