{
  "type": "Feature",
  "properties": {
    "iso:country":"GB",
    "wof:name":"SA73 2PG",
    "wof:placetype":"postalcode"
},
  "geometry": {"coordinates":[-5.02743328622995,51.71804639780706],"type":"Point"}
}