{
  "type": "Feature",
  "properties": {
    "date:inception_lower": "1980-01-01",
    "date:inception_upper": "1980-01-01",
    "iso:country": "GB",
    "wof:name": "CF45 3YN",
    "wof:placetype": "postalcode"
  },
  "geometry": {"coordinates":[-3.371112,51.673491],"type":"Point"}
}
