{
  "type": "Feature",
  "properties": {
    "iso:country":"GB",
    "wof:name":"CF45 3YN",
    "wof:placetype":"postalcode"
},
  "geometry": {"coordinates":[-3.37109950060024,51.67348640118959],"type":"Point"}
}