{
  "type": "Feature",
  "properties": {
    "date:inception_lower": "1984-10-01",
    "date:inception_upper": "1984-10-01",
    "iso:country": "GB",
    "wof:name": "RH6 0AB",
    "wof:placetype": "postalcode"
  },
  "geometry": {"coordinates":[-0.178067,51.166819],"type":"Point"}
}
