{
  "type": "Feature",
  "properties": {
    "iso:country":"GB",
    "wof:name":"RH6 0AB",
    "wof:placetype":"postalcode"
},
  "geometry": {"coordinates":[-0.17806688433559,51.16681859519633],"type":"Point"}
}