{
  "type": "Feature",
  "properties": {
    "iso:country": "GB",
    "wof:name": "PE19 1QZ",
    "wof:placetype": "postalcode"
  },
  "geometry": {"coordinates":[-0.258588,52.227424],"type":"Point"}
}
