{
  "type": "Feature",
  "properties": {
    "iso:country":"GB",
    "wof:name":"BB2 2RS",
    "wof:placetype":"postalcode"
},
  "geometry": {"coordinates":[-2.50840142735322,53.73512267209038],"type":"Point"}
}