{
  "type": "Feature",
  "properties": {
    "iso:country":"GB",
    "wof:name":"NE9 5LP",
    "wof:placetype":"postalcode"
},
  "geometry": {"coordinates":[-1.59216002641712,54.94861172114435],"type":"Point"}
}