{
  "type": "Feature",
  "properties": {
    "date:inception_lower": "1980-01-01",
    "date:inception_upper": "1980-01-01",
    "iso:country": "GB",
    "wof:name": "NE9 5LP",
    "wof:placetype": "postalcode"
  },
  "geometry": {"coordinates":[-1.59216,54.948612],"type":"Point"}
}
