{
  "type": "Feature",
  "properties": {
    "date:inception_lower": "2005-12-01",
    "date:inception_upper": "2005-12-01",
    "iso:country": "GB",
    "wof:name": "ML6 6GE",
    "wof:placetype": "postalcode"
  },
  "geometry": {"coordinates":[-3.979775,55.881786],"type":"Point"}
}
