{
  "type": "Feature",
  "properties": {
    "date:inception_lower": "2006-08-01",
    "date:inception_upper": "2006-08-01",
    "iso:country": "GB",
    "wof:name": "SN2 1FD",
    "wof:placetype": "postalcode"
  },
  "geometry": {"coordinates":[-1.78578,51.569598],"type":"Point"}
}
