{
  "type": "Feature",
  "properties": {
    "date:inception_lower": "1980-01-01",
    "date:inception_upper": "1980-01-01",
    "iso:country": "GB",
    "wof:name": "DA1 2NT",
    "wof:placetype": "postalcode"
  },
  "geometry": {"coordinates":[0.203656,51.443401],"type":"Point"}
}
