{
  "type": "Feature",
  "properties": {
    "iso:country": "GB",
    "wof:name": "DY4 0QQ",
    "wof:placetype": "postalcode"
  },
  "geometry": {"coordinates":[-2.034858,52.543183],"type":"Point"}
}
