{
  "type": "Feature",
  "properties": {
    "iso:country": "GB",
    "wof:name": "PO8 0SD",
    "wof:placetype": "postalcode"
  },
  "geometry": {"coordinates":[-1.040723,50.952173],"type":"Point"}
}
