{
  "type": "Feature",
  "properties": {
    "date:inception_lower":"1980-01-01",
    "date:inception_upper":"1980-01-31",
    "iso:country":"GB",
    "wof:name":"PO8 0SD",
    "wof:placetype":"postalcode"
},
  "geometry": {"coordinates":[-1.040723,50.952173],"type":"Point"}
}