{
  "type": "Feature",
  "properties": {
    "iso:country":"GB",
    "wof:name":"PO8 0SD",
    "wof:placetype":"postalcode"
},
  "geometry": {"coordinates":[-1.04072294491226,50.95217252505147],"type":"Point"}
}