{
  "type": "Feature",
  "properties": {
    "iso:country":"GB",
    "wof:name":"G64 4DJ",
    "wof:placetype":"postalcode"
},
  "geometry": {"coordinates":[-4.21241062321829,55.95004496656595],"type":"Point"}
}