{
  "type": "Feature",
  "properties": {
    "iso:country": "GB",
    "wof:name": "LA5 9TU",
    "wof:placetype": "postalcode"
  },
  "geometry": {"coordinates":[-2.775219,54.122721],"type":"Point"}
}
