{
  "type": "Feature",
  "properties": {
    "iso:country":"GB",
    "wof:name":"LA5 9TU",
    "wof:placetype":"postalcode"
},
  "geometry": {"coordinates":[-2.77521906398665,54.12272124741264],"type":"Point"}
}