{
  "type": "Feature",
  "properties": {
    "date:inception_lower":"1982-03-01",
    "date:inception_upper":"1982-03-31",
    "iso:country":"GB",
    "wof:name":"LA5 9TU",
    "wof:placetype":"postalcode"
},
  "geometry": {"coordinates":[-2.775219,54.122721],"type":"Point"}
}