{
  "type": "Feature",
  "properties": {
    "iso:country":"GB",
    "wof:name":"NW3 2YU",
    "wof:placetype":"postalcode"
},
  "geometry": {"coordinates":[-0.15778375080148,51.55026443382351],"type":"Point"}
}