{
  "type": "Feature",
  "properties": {
    "iso:country":"GB",
    "wof:name":"E6 6LF",
    "wof:placetype":"postalcode"
},
  "geometry": {"coordinates":[0.0706426485483,51.51774128259991],"type":"Point"}
}