{
  "type": "Feature",
  "properties": {
    "date:inception_lower":"1980-01-01",
    "date:inception_upper":"1980-01-31",
    "iso:country":"GB",
    "wof:name":"TS10 1HJ",
    "wof:placetype":"postalcode"
},
  "geometry": {"coordinates":[-1.070021,54.611914],"type":"Point"}
}