{
  "type": "Feature",
  "properties": {
    "iso:country":"GB",
    "wof:name":"TS10 1HJ",
    "wof:placetype":"postalcode"
},
  "geometry": {"coordinates":[-1.07002127870736,54.61191372165722],"type":"Point"}
}