{
  "type": "Feature",
  "properties": {
    "iso:country":"GB",
    "wof:name":"SP2 8JJ",
    "wof:placetype":"postalcode"
},
  "geometry": {"coordinates":[-1.7983285353694,51.05936483374049],"type":"Point"}
}