{
  "type": "Feature",
  "properties": {
    "date:inception_lower":"1980-01-01",
    "date:inception_upper":"1980-01-31",
    "iso:country":"GB",
    "wof:name":"TA24 7NZ",
    "wof:placetype":"postalcode"
},
  "geometry": {"coordinates":[-3.611097,51.135949],"type":"Point"}
}