{
  "type": "Feature",
  "properties": {
    "date:inception_lower": "1980-01-01",
    "date:inception_upper": "1980-01-01",
    "iso:country": "GB",
    "wof:name": "EH8 8AB",
    "wof:placetype": "postalcode"
  },
  "geometry": {"coordinates":[-3.182953,55.950636],"type":"Point"}
}
