{
  "type": "Feature",
  "properties": {
    "iso:country":"GB",
    "wof:name":"SA5 4QS",
    "wof:placetype":"postalcode"
},
  "geometry": {"coordinates":[-4.02667248045909,51.64070985438939],"type":"Point"}
}