{
  "type": "Feature",
  "properties": {
    "date:inception_lower": "1980-01-01",
    "date:inception_upper": "1980-01-01",
    "iso:country": "GB",
    "wof:name": "BN18 0AZ",
    "wof:placetype": "postalcode"
  },
  "geometry": {"coordinates":[-0.630889,50.845506],"type":"Point"}
}
