{
  "type": "Feature",
  "properties": {
    "iso:country":"GB",
    "wof:name":"NE3 3PE",
    "wof:placetype":"postalcode"
},
  "geometry": {"coordinates":[-1.63761556968079,55.01197381978023],"type":"Point"}
}