{
  "type": "Feature",
  "properties": {
    "iso:country": "GB",
    "wof:name": "OL9 0DZ",
    "wof:placetype": "postalcode"
  },
  "geometry": {"coordinates":[-2.139333,53.551117],"type":"Point"}
}
