{
  "type": "Feature",
  "properties": {
    "date:inception_lower": "2002-08-01",
    "date:inception_upper": "2002-08-01",
    "iso:country": "GB",
    "wof:name": "OX16 1AH",
    "wof:placetype": "postalcode"
  },
  "geometry": {"coordinates":[-1.363233,52.078348],"type":"Point"}
}
