{
  "type": "Feature",
  "properties": {
    "iso:country":"GB",
    "wof:name":"SE23 1AL",
    "wof:placetype":"postalcode"
},
  "geometry": {"coordinates":[-0.04490206199218,51.44322370212488],"type":"Point"}
}