{
  "type": "Feature",
  "properties": {
    "date:inception_lower": "2006-02-01",
    "date:inception_upper": "2006-02-01",
    "iso:country": "GB",
    "wof:name": "S43 4UL",
    "wof:placetype": "postalcode"
  },
  "geometry": {"coordinates":[-1.290914,53.281809],"type":"Point"}
}
