{
  "type": "Feature",
  "properties": {
    "iso:country": "GB",
    "wof:name": "S43 4UL",
    "wof:placetype": "postalcode"
  },
  "geometry": {"coordinates":[-1.290914,53.281809],"type":"Point"}
}
