{
  "type": "Feature",
  "properties": {
    "iso:country":"GB",
    "wof:name":"TN13 2JG",
    "wof:placetype":"postalcode"
},
  "geometry": {"coordinates":[0.17876541302174,51.27792504136173],"type":"Point"}
}