{
  "type": "Feature",
  "properties": {
    "date:inception_lower": "1980-01-01",
    "date:inception_upper": "1980-01-01",
    "iso:country": "GB",
    "wof:name": "TN13 2JG",
    "wof:placetype": "postalcode"
  },
  "geometry": {"coordinates":[0.178765,51.277925],"type":"Point"}
}
