{
  "type": "Feature",
  "properties": {
    "iso:country":"GB",
    "wof:name":"PH26 3PB",
    "wof:placetype":"postalcode"
},
  "geometry": {"coordinates":[-3.69490803222641,57.27761265375477],"type":"Point"}
}