{
  "type": "Feature",
  "properties": {
    "iso:country": "GB",
    "wof:name": "PH26 3PB",
    "wof:placetype": "postalcode"
  },
  "geometry": {"coordinates":[-3.694907,57.277598],"type":"Point"}
}
