{
  "type": "Feature",
  "properties": {
    "date:inception_lower":"1984-10-01",
    "date:inception_upper":"1984-10-31",
    "iso:country":"GB",
    "wof:name":"GU17 9JQ",
    "wof:placetype":"postalcode"
},
  "geometry": {"coordinates":[-0.786761,51.327737],"type":"Point"}
}