{
  "type": "Feature",
  "properties": {
    "iso:country":"GB",
    "wof:name":"NR6 6UZ",
    "wof:placetype":"postalcode"
},
  "geometry": {"coordinates":[1.26524006602181,52.66834549649347],"type":"Point"}
}