{
  "type": "Feature",
  "properties": {
    "iso:country":"GB",
    "wof:name":"CM23 4FW",
    "wof:placetype":"postalcode"
},
  "geometry": {"coordinates":[0.13975998326996,51.85893058136448],"type":"Point"}
}