{
  "type": "Feature",
  "properties": {
    "iso:country":"GB",
    "wof:name":"G73 2NY",
    "wof:placetype":"postalcode"
},
  "geometry": {"coordinates":[-4.22244348605392,55.82373587377803],"type":"Point"}
}