{
  "type": "Feature",
  "properties": {
    "iso:country":"GB",
    "wof:name":"PE11 4HW",
    "wof:placetype":"postalcode"
},
  "geometry": {"coordinates":[-0.12805177669308,52.85550515420192],"type":"Point"}
}