{
  "type": "Feature",
  "properties": {
    "iso:country":"GB",
    "wof:name":"NR27 0DP",
    "wof:placetype":"postalcode"
},
  "geometry": {"coordinates":[1.30825517361241,52.92653307770355],"type":"Point"}
}