{
  "type": "Feature",
  "properties": {
    "date:inception_lower": "2006-11-01",
    "date:inception_upper": "2006-11-01",
    "iso:country": "GB",
    "wof:name": "NR27 0DP",
    "wof:placetype": "postalcode"
  },
  "geometry": {"coordinates":[1.308227,52.926552],"type":"Point"}
}
