{
  "type": "Feature",
  "properties": {
    "iso:country":"GB",
    "wof:name":"SE1 1YP",
    "wof:placetype":"postalcode"
},
  "geometry": {"coordinates":[-0.09025023330316,51.50413191892116],"type":"Point"}
}