{
  "type": "Feature",
  "properties": {
    "date:inception_lower":"1996-06-01",
    "date:inception_upper":"1996-06-30",
    "iso:country":"GB",
    "wof:name":"SE1 1YP",
    "wof:placetype":"postalcode"
},
  "geometry": {"coordinates":[-0.09025,51.504132],"type":"Point"}
}