{
  "type": "Feature",
  "properties": {
    "date:inception_lower": "2014-03-01",
    "date:inception_upper": "2014-03-01",
    "iso:country": "GB",
    "wof:name": "SR1 3NQ",
    "wof:placetype": "postalcode"
  },
  "geometry": {"coordinates":[-1.388314,54.902924],"type":"Point"}
}
