{
  "type": "Feature",
  "properties": {
    "iso:country":"GB",
    "wof:name":"SR1 3NQ",
    "wof:placetype":"postalcode"
},
  "geometry": {"coordinates":[-1.38831407886221,54.90292421474988],"type":"Point"}
}