{
  "type": "Feature",
  "properties": {
    "iso:country":"GB",
    "wof:name":"ME12 3PN",
    "wof:placetype":"postalcode"
},
  "geometry": {"coordinates":[0.80904802106302,51.41880420959486],"type":"Point"}
}