{
  "type": "Feature",
  "properties": {
    "iso:country":"GB",
    "wof:name":"E12 6DD",
    "wof:placetype":"postalcode"
},
  "geometry": {"coordinates":[0.0543254603197,51.55166996925219],"type":"Point"}
}