{
  "type": "Feature",
  "properties": {
    "date:inception_lower": "1980-01-01",
    "date:inception_upper": "1980-01-01",
    "iso:country": "GB",
    "wof:name": "E12 6DD",
    "wof:placetype": "postalcode"
  },
  "geometry": {"coordinates":[0.054326,51.55167],"type":"Point"}
}
