{
  "type": "Feature",
  "properties": {
    "iso:country": "GB",
    "wof:name": "LU2 0PA",
    "wof:placetype": "postalcode"
  },
  "geometry": {"coordinates":[-0.399051,51.886245],"type":"Point"}
}
