{
  "type": "Feature",
  "properties": {
    "date:inception_lower": "1995-01-01",
    "date:inception_upper": "1995-01-01",
    "iso:country": "GB",
    "wof:name": "LU2 0PA",
    "wof:placetype": "postalcode"
  },
  "geometry": {"coordinates":[-0.399051,51.886245],"type":"Point"}
}
