{
  "type": "Feature",
  "properties": {
    "iso:country":"GB",
    "wof:name":"M23 2ZF",
    "wof:placetype":"postalcode"
},
  "geometry": {"coordinates":[-2.27780065603084,53.38539701101761],"type":"Point"}
}