{
  "type": "Feature",
  "properties": {
    "iso:country":"GB",
    "wof:name":"PO1 2HG",
    "wof:placetype":"postalcode"
},
  "geometry": {"coordinates":[-1.10150063706185,50.7923616523456],"type":"Point"}
}