{
  "type": "Feature",
  "properties": {
    "iso:country":"GB",
    "wof:name":"WA6 9LL",
    "wof:placetype":"postalcode"
},
  "geometry": {"coordinates":[-2.75698343072697,53.27736736185276],"type":"Point"}
}