{
  "type": "Feature",
  "properties": {
    "iso:country":"GB",
    "wof:name":"LN6 7QP",
    "wof:placetype":"postalcode"
},
  "geometry": {"coordinates":[-0.56494549251212,53.20974963530664],"type":"Point"}
}