{
  "type": "Feature",
  "properties": {
    "iso:country":"GB",
    "wof:name":"TA7 8JP",
    "wof:placetype":"postalcode"
},
  "geometry": {"coordinates":[-2.94005660677665,51.16567814395971],"type":"Point"}
}