{
  "type": "Feature",
  "properties": {
    "date:inception_lower": "1999-12-01",
    "date:inception_upper": "1999-12-01",
    "iso:country": "GB",
    "wof:name": "TA7 8JP",
    "wof:placetype": "postalcode"
  },
  "geometry": {"coordinates":[-2.940057,51.165678],"type":"Point"}
}
