{
  "type": "Feature",
  "properties": {
    "iso:country":"GB",
    "wof:name":"HP19 7GU",
    "wof:placetype":"postalcode"
},
  "geometry": {"coordinates":[-0.84436548586457,51.81692249963273],"type":"Point"}
}