{
  "type": "Feature",
  "properties": {
    "date:inception_lower": "2003-01-01",
    "date:inception_upper": "2003-01-01",
    "iso:country": "GB",
    "wof:name": "HP19 7GU",
    "wof:placetype": "postalcode"
  },
  "geometry": {"coordinates":[-0.844365,51.816922],"type":"Point"}
}
