{
  "type": "Feature",
  "properties": {
    "iso:country": "GB",
    "wof:name": "HP19 7GU",
    "wof:placetype": "postalcode"
  },
  "geometry": {"coordinates":[-0.844365,51.816922],"type":"Point"}
}
