{
  "type": "Feature",
  "properties": {
    "date:inception_lower":"2006-09-01",
    "date:inception_upper":"2006-09-30",
    "iso:country":"GB",
    "wof:name":"CB23 2NG",
    "wof:placetype":"postalcode"
},
  "geometry": {"coordinates":[-0.033118,52.180533],"type":"Point"}
}