{
  "type": "Feature",
  "properties": {
    "iso:country":"GB",
    "wof:name":"CB23 2NG",
    "wof:placetype":"postalcode"
},
  "geometry": {"coordinates":[-0.03311816564842,52.18053306125719],"type":"Point"}
}