{
  "type": "Feature",
  "properties": {
    "iso:country":"GB",
    "wof:name":"CF5 3TE",
    "wof:placetype":"postalcode"
},
  "geometry": {"coordinates":[-3.25095579261013,51.49349872701878],"type":"Point"}
}