{
  "type": "Feature",
  "properties": {
    "date:inception_lower": "1980-01-01",
    "date:inception_upper": "1980-01-01",
    "iso:country": "GB",
    "wof:name": "CF5 3TE",
    "wof:placetype": "postalcode"
  },
  "geometry": {"coordinates":[-3.250921,51.493473],"type":"Point"}
}
