{
  "type": "Feature",
  "properties": {
    "iso:country": "GB",
    "wof:name": "G64 2RE",
    "wof:placetype": "postalcode"
  },
  "geometry": {"coordinates":[-4.22515,55.904636],"type":"Point"}
}
