{
  "type": "Feature",
  "properties": {
    "iso:country":"GB",
    "wof:name":"G64 2RE",
    "wof:placetype":"postalcode"
},
  "geometry": {"coordinates":[-4.22515017021589,55.90463628737908],"type":"Point"}
}