{
  "type": "Feature",
  "properties": {
    "iso:country":"GB",
    "wof:name":"SO30 0JZ",
    "wof:placetype":"postalcode"
},
  "geometry": {"coordinates":[-1.30337960695427,50.90395479842672],"type":"Point"}
}