{
  "type": "Feature",
  "properties": {
    "iso:country": "GB",
    "wof:name": "SO30 0JZ",
    "wof:placetype": "postalcode"
  },
  "geometry": {"coordinates":[-1.30338,50.903955],"type":"Point"}
}
