{
  "type": "Feature",
  "properties": {
    "iso:country": "GB",
    "wof:name": "RM3 8SH",
    "wof:placetype": "postalcode"
  },
  "geometry": {"coordinates":[0.215153,51.596669],"type":"Point"}
}
