{
  "type": "Feature",
  "properties": {
    "iso:country":"GB",
    "wof:name":"NG18 1QU",
    "wof:placetype":"postalcode"
},
  "geometry": {"coordinates":[-1.20485118000605,53.145953666678],"type":"Point"}
}