{
  "type": "Feature",
  "properties": {
    "iso:country":"GB",
    "wof:name":"PO30 1UL",
    "wof:placetype":"postalcode"
},
  "geometry": {"coordinates":[-1.29597039580229,50.69894020422122],"type":"Point"}
}