{
  "type": "Feature",
  "properties": {
    "iso:country": "GB",
    "wof:name": "YO30 1XR",
    "wof:placetype": "postalcode"
  },
  "geometry": {"coordinates":[-1.135107,54.000426],"type":"Point"}
}
