{
  "type": "Feature",
  "properties": {
    "iso:country":"GB",
    "wof:name":"GU8 6NT",
    "wof:placetype":"postalcode"
},
  "geometry": {"coordinates":[-0.69580099724416,51.14909689927227],"type":"Point"}
}