{
  "type": "Feature",
  "properties": {
    "date:inception_lower":"1980-01-01",
    "date:inception_upper":"1980-01-31",
    "iso:country":"GB",
    "wof:name":"GU8 6NT",
    "wof:placetype":"postalcode"
},
  "geometry": {"coordinates":[-0.695781,51.149093],"type":"Point"}
}