{
  "type": "Feature",
  "properties": {
    "iso:country":"GB",
    "wof:name":"G42 9AS",
    "wof:placetype":"postalcode"
},
  "geometry": {"coordinates":[-4.25207142809542,55.82753769928006],"type":"Point"}
}