{
  "type": "Feature",
  "properties": {
    "iso:country":"GB",
    "wof:name":"SG17 5PF",
    "wof:placetype":"postalcode"
},
  "geometry": {"coordinates":[-0.35772756087706,52.03077402772674],"type":"Point"}
}