{
  "type": "Feature",
  "properties": {
    "iso:country": "GB",
    "wof:name": "SG17 5PF",
    "wof:placetype": "postalcode"
  },
  "geometry": {"coordinates":[-0.357728,52.030774],"type":"Point"}
}
