{
  "type": "Feature",
  "properties": {
    "iso:country":"GB",
    "wof:name":"BS7 8SX",
    "wof:placetype":"postalcode"
},
  "geometry": {"coordinates":[-2.58682725939165,51.48844406885632],"type":"Point"}
}