{
  "type": "Feature",
  "properties": {
    "iso:country":"GB",
    "wof:name":"NR31 6NY",
    "wof:placetype":"postalcode"
},
  "geometry": {"coordinates":[1.72773124254088,52.58386996165817],"type":"Point"}
}