{
  "type": "Feature",
  "properties": {
    "iso:country": "GB",
    "wof:name": "PO15 7QG",
    "wof:placetype": "postalcode"
  },
  "geometry": {"coordinates":[-1.253944,50.892544],"type":"Point"}
}
