{
  "type": "Feature",
  "properties": {
    "iso:country": "GB",
    "wof:name": "HX3 6NA",
    "wof:placetype": "postalcode"
  },
  "geometry": {"coordinates":[-1.867901,53.733595],"type":"Point"}
}
