{
  "type": "Feature",
  "properties": {
    "iso:country":"GB",
    "wof:name":"BR7 6TL",
    "wof:placetype":"postalcode"
},
  "geometry": {"coordinates":[0.07841911236701,51.41430302493786],"type":"Point"}
}