{
  "type": "Feature",
  "properties": {
    "iso:country": "GB",
    "wof:name": "BR7 6TL",
    "wof:placetype": "postalcode"
  },
  "geometry": {"coordinates":[0.078419,51.414303],"type":"Point"}
}
