{
  "type": "Feature",
  "properties": {
    "iso:country":"GB",
    "wof:name":"BH4 8AD",
    "wof:placetype":"postalcode"
},
  "geometry": {"coordinates":[-1.89747067003174,50.71468845294459],"type":"Point"}
}