{
  "type": "Feature",
  "properties": {
    "iso:country": "GB",
    "wof:name": "PE13 4EW",
    "wof:placetype": "postalcode"
  },
  "geometry": {"coordinates":[0.0675,52.613753],"type":"Point"}
}
