{
  "type": "Feature",
  "properties": {
    "iso:country":"GB",
    "wof:name":"BS9 2DG",
    "wof:placetype":"postalcode"
},
  "geometry": {"coordinates":[-2.64173767399422,51.48794055077996],"type":"Point"}
}