{
  "type": "Feature",
  "properties": {
    "date:inception_lower": "1980-01-01",
    "date:inception_upper": "1980-01-01",
    "iso:country": "GB",
    "wof:name": "BS9 2DG",
    "wof:placetype": "postalcode"
  },
  "geometry": {"coordinates":[-2.641738,51.487941],"type":"Point"}
}
