{
  "type": "Feature",
  "properties": {
    "iso:country":"GB",
    "wof:name":"NN17 2YF",
    "wof:placetype":"postalcode"
},
  "geometry": {"coordinates":[-0.70627225635209,52.50095965383513],"type":"Point"}
}