{
  "type": "Feature",
  "properties": {
    "date:inception_lower": "1995-07-01",
    "date:inception_upper": "1995-07-01",
    "iso:country": "GB",
    "wof:name": "NN17 2YF",
    "wof:placetype": "postalcode"
  },
  "geometry": {"coordinates":[-0.706272,52.50096],"type":"Point"}
}
