{
  "type": "Feature",
  "properties": {
    "iso:country":"GB",
    "wof:name":"CO4 0QB",
    "wof:placetype":"postalcode"
},
  "geometry": {"coordinates":[0.92542901239856,51.9018786100137],"type":"Point"}
}