{
  "type": "Feature",
  "properties": {
    "iso:country":"GB",
    "wof:name":"L10 8LQ",
    "wof:placetype":"postalcode"
},
  "geometry": {"coordinates":[-2.92186365609449,53.47576957146941],"type":"Point"}
}