{
  "type": "Feature",
  "properties": {
    "iso:country":"GB",
    "wof:name":"OX10 8DY",
    "wof:placetype":"postalcode"
},
  "geometry": {"coordinates":[-1.11258675973686,51.58355115897826],"type":"Point"}
}