{
  "type": "Feature",
  "properties": {
    "date:inception_lower": "2007-03-01",
    "date:inception_upper": "2007-03-01",
    "iso:country": "GB",
    "wof:name": "OX10 8DY",
    "wof:placetype": "postalcode"
  },
  "geometry": {"coordinates":[-1.112153,51.583308],"type":"Point"}
}
