{
  "type": "Feature",
  "properties": {
    "iso:country":"GB",
    "wof:name":"LS25 7JR",
    "wof:placetype":"postalcode"
},
  "geometry": {"coordinates":[-1.37289516662456,53.76717196721103],"type":"Point"}
}