{
  "type": "Feature",
  "properties": {
    "iso:country":"GB",
    "wof:name":"S10 3GA",
    "wof:placetype":"postalcode"
},
  "geometry": {"coordinates":[-1.5228211970111,53.37058416112901],"type":"Point"}
}