{
  "type": "Feature",
  "properties": {
    "iso:country":"GB",
    "wof:name":"CA1 3HZ",
    "wof:placetype":"postalcode"
},
  "geometry": {"coordinates":[-2.89478049078303,54.87535641314392],"type":"Point"}
}