{
  "type": "Feature",
  "properties": {
    "iso:country":"GB",
    "wof:name":"TW18 3JF",
    "wof:placetype":"postalcode"
},
  "geometry": {"coordinates":[-0.51656818873613,51.43257913007469],"type":"Point"}
}