{
  "type": "Feature",
  "properties": {
    "date:inception_lower": "1980-01-01",
    "date:inception_upper": "1980-01-01",
    "iso:country": "GB",
    "wof:name": "TW18 3JF",
    "wof:placetype": "postalcode"
  },
  "geometry": {"coordinates":[-0.51652,51.432579],"type":"Point"}
}
