{
  "type": "Feature",
  "properties": {
    "iso:country": "GB",
    "wof:name": "NN6 6NX",
    "wof:placetype": "postalcode"
  },
  "geometry": {"coordinates":[-1.092162,52.372589],"type":"Point"}
}
