{
  "type": "Feature",
  "properties": {
    "iso:country":"GB",
    "wof:name":"PO7 5PN",
    "wof:placetype":"postalcode"
},
  "geometry": {"coordinates":[-1.02821317742914,50.86520020951811],"type":"Point"}
}