{
  "type": "Feature",
  "properties": {
    "iso:country": "GB",
    "wof:name": "PO7 5PN",
    "wof:placetype": "postalcode"
  },
  "geometry": {"coordinates":[-1.028213,50.8652],"type":"Point"}
}
