{
  "type": "Feature",
  "properties": {
    "date:inception_lower": "1980-01-01",
    "date:inception_upper": "1980-01-01",
    "iso:country": "GB",
    "wof:name": "PO7 5PN",
    "wof:placetype": "postalcode"
  },
  "geometry": {"coordinates":[-1.028213,50.8652],"type":"Point"}
}
