{
  "type": "Feature",
  "properties": {
    "iso:country": "GB",
    "wof:name": "TQ9 5JW",
    "wof:placetype": "postalcode"
  },
  "geometry": {"coordinates":[-3.69064,50.435601],"type":"Point"}
}
