{
  "type": "Feature",
  "properties": {
    "iso:country":"GB",
    "wof:name":"TQ9 5JW",
    "wof:placetype":"postalcode"
},
  "geometry": {"coordinates":[-3.69064035239609,50.43560114323919],"type":"Point"}
}