{
  "type": "Feature",
  "properties": {
    "iso:country":"GB",
    "wof:name":"LE11 3JZ",
    "wof:placetype":"postalcode"
},
  "geometry": {"coordinates":[-1.23772343774234,52.76011648620942],"type":"Point"}
}