{
  "type": "Feature",
  "properties": {
    "date:inception_lower": "1980-01-01",
    "date:inception_upper": "1980-01-01",
    "iso:country": "GB",
    "wof:name": "OX17 2SB",
    "wof:placetype": "postalcode"
  },
  "geometry": {"coordinates":[-1.185261,52.106104],"type":"Point"}
}
