{
  "type": "Feature",
  "properties": {
    "iso:country":"GB",
    "wof:name":"RG24 9UU",
    "wof:placetype":"postalcode"
},
  "geometry": {"coordinates":[-1.07248721595676,51.28321988954524],"type":"Point"}
}