{
  "type": "Feature",
  "properties": {
    "date:inception_lower":"2011-05-01",
    "date:inception_upper":"2011-05-31",
    "iso:country":"GB",
    "wof:name":"RG24 9UU",
    "wof:placetype":"postalcode"
},
  "geometry": {"coordinates":[-1.072487,51.28322],"type":"Point"}
}