{
  "type": "Feature",
  "properties": {
    "iso:country": "GB",
    "wof:name": "RG24 9UU",
    "wof:placetype": "postalcode"
  },
  "geometry": {"coordinates":[-1.072487,51.28322],"type":"Point"}
}
