{
  "type": "Feature",
  "properties": {
    "date:inception_lower": "2022-03-01",
    "date:inception_upper": "2022-03-01",
    "iso:country": "GB",
    "wof:name": "BD9 6FF",
    "wof:placetype": "postalcode"
  },
  "geometry": {"coordinates":[-1.807735,53.82108],"type":"Point"}
}
