{
  "type": "Feature",
  "properties": {
    "iso:country":"GB",
    "wof:name":"NN16 9PB",
    "wof:placetype":"postalcode"
},
  "geometry": {"coordinates":[-0.71171694723993,52.4108975039137],"type":"Point"}
}