{
  "type": "Feature",
  "properties": {
    "date:inception_lower":"1992-08-01",
    "date:inception_upper":"1992-08-31",
    "iso:country":"GB",
    "wof:name":"LN6 5UH",
    "wof:placetype":"postalcode"
},
  "geometry": {"coordinates":[-0.622922,53.236027],"type":"Point"}
}