{
  "type": "Feature",
  "properties": {
    "iso:country":"GB",
    "wof:name":"LN6 5UH",
    "wof:placetype":"postalcode"
},
  "geometry": {"coordinates":[-0.62292198612474,53.23602693344272],"type":"Point"}
}