{
  "type": "Feature",
  "properties": {
    "iso:country": "GB",
    "wof:name": "W1S 2XE",
    "wof:placetype": "postalcode"
  },
  "geometry": {"coordinates":[-0.141301,51.513],"type":"Point"}
}
