{
  "type": "Feature",
  "properties": {
    "date:inception_lower": "1980-01-01",
    "date:inception_upper": "1980-01-01",
    "iso:country": "GB",
    "wof:name": "NE11 9RB",
    "wof:placetype": "postalcode"
  },
  "geometry": {"coordinates":[-1.643871,54.944811],"type":"Point"}
}
