{
  "type": "Feature",
  "properties": {
    "iso:country":"GB",
    "wof:name":"WF2 7SN",
    "wof:placetype":"postalcode"
},
  "geometry": {"coordinates":[-1.50181397387659,53.63784328459647],"type":"Point"}
}