{
  "type": "Feature",
  "properties": {
    "date:inception_lower": "1973-08-01",
    "date:inception_upper": "1973-08-01",
    "iso:country": "GB",
    "wof:name": "DD3 6PQ",
    "wof:placetype": "postalcode"
  },
  "geometry": {"coordinates":[-2.976817,56.470322],"type":"Point"}
}
