{
  "type": "Feature",
  "properties": {
    "date:inception_lower": "1980-01-01",
    "date:inception_upper": "1980-01-01",
    "iso:country": "GB",
    "wof:name": "PL6 6RX",
    "wof:placetype": "postalcode"
  },
  "geometry": {"coordinates":[-4.139872,50.422123],"type":"Point"}
}
