{
  "type": "Feature",
  "properties": {
    "iso:country":"GB",
    "wof:name":"AB24 5LD",
    "wof:placetype":"postalcode"
},
  "geometry": {"coordinates":[-2.09090733060039,57.15260170651019],"type":"Point"}
}