{
  "type": "Feature",
  "properties": {
    "iso:country":"GB",
    "wof:name":"SL6 3AT",
    "wof:placetype":"postalcode"
},
  "geometry": {"coordinates":[-0.75274102995147,51.50860524924031],"type":"Point"}
}