{
  "type": "Feature",
  "properties": {
    "iso:country": "GB",
    "wof:name": "NG17 1GY",
    "wof:placetype": "postalcode"
  },
  "geometry": {"coordinates":[-1.271117,53.115814],"type":"Point"}
}
