{
  "type": "Feature",
  "properties": {
    "date:inception_lower":"1981-09-01",
    "date:inception_upper":"1981-09-30",
    "iso:country":"GB",
    "wof:name":"NG17 1GY",
    "wof:placetype":"postalcode"
},
  "geometry": {"coordinates":[-1.271117,53.115814],"type":"Point"}
}