{
  "type": "Feature",
  "properties": {
    "iso:country":"GB",
    "wof:name":"NG17 1GY",
    "wof:placetype":"postalcode"
},
  "geometry": {"coordinates":[-1.27111667271556,53.11581435782984],"type":"Point"}
}