{
  "type": "Feature",
  "properties": {
    "date:inception_lower": "1980-01-01",
    "date:inception_upper": "1980-01-01",
    "iso:country": "GB",
    "wof:name": "DA11 0LZ",
    "wof:placetype": "postalcode"
  },
  "geometry": {"coordinates":[0.358265,51.435427],"type":"Point"}
}
