{
  "type": "Feature",
  "properties": {
    "iso:country": "GB",
    "wof:name": "IP27 9GQ",
    "wof:placetype": "postalcode"
  },
  "geometry": {"coordinates":[0.536544,52.385782],"type":"Point"}
}
