{
  "type": "Feature",
  "properties": {
    "date:inception_lower": "2009-09-01",
    "date:inception_upper": "2009-09-01",
    "iso:country": "GB",
    "wof:name": "IP27 9GQ",
    "wof:placetype": "postalcode"
  },
  "geometry": {"coordinates":[0.536544,52.385782],"type":"Point"}
}
