{
  "type": "Feature",
  "properties": {
    "iso:country":"GB",
    "wof:name":"RG4 8DD",
    "wof:placetype":"postalcode"
},
  "geometry": {"coordinates":[-0.96910924463936,51.46538726403533],"type":"Point"}
}