{
  "type": "Feature",
  "properties": {
    "iso:country":"GB",
    "wof:name":"CM1 4YD",
    "wof:placetype":"postalcode"
},
  "geometry": {"coordinates":[0.45974644723045,51.75654755854681],"type":"Point"}
}