{
  "type": "Feature",
  "properties": {
    "date:inception_lower": "1980-01-01",
    "date:inception_upper": "1980-01-01",
    "iso:country": "GB",
    "wof:name": "RG2 7BD",
    "wof:placetype": "postalcode"
  },
  "geometry": {"coordinates":[-0.956354,51.443325],"type":"Point"}
}
