{
  "type": "Feature",
  "properties": {
    "iso:country": "GB",
    "wof:name": "RG2 7BD",
    "wof:placetype": "postalcode"
  },
  "geometry": {"coordinates":[-0.956354,51.443325],"type":"Point"}
}
