{
  "type": "Feature",
  "properties": {
    "iso:country":"GB",
    "wof:name":"RG2 7BD",
    "wof:placetype":"postalcode"
},
  "geometry": {"coordinates":[-0.9563538434902,51.44332531018589],"type":"Point"}
}