{
  "type": "Feature",
  "properties": {
    "iso:country":"GB",
    "wof:name":"WN1 1UE",
    "wof:placetype":"postalcode"
},
  "geometry": {"coordinates":[-2.63090178554709,53.54753743888457],"type":"Point"}
}