{
  "type": "Feature",
  "properties": {
    "iso:country":"GB",
    "wof:name":"NW11 6BA",
    "wof:placetype":"postalcode"
},
  "geometry": {"coordinates":[-0.19685273880768,51.58721851701958],"type":"Point"}
}