{
  "type": "Feature",
  "properties": {
    "iso:country": "GB",
    "wof:name": "NG16 6LX",
    "wof:placetype": "postalcode"
  },
  "geometry": {"coordinates":[-1.321815,53.091762],"type":"Point"}
}
