{
  "type": "Feature",
  "properties": {
    "date:inception_lower": "1993-08-01",
    "date:inception_upper": "1993-08-01",
    "iso:country": "GB",
    "wof:name": "TS21 2JU",
    "wof:placetype": "postalcode"
  },
  "geometry": {"coordinates":[-1.488625,54.63211],"type":"Point"}
}
