{
  "type": "Feature",
  "properties": {
    "iso:country": "GB",
    "wof:name": "TS21 2JU",
    "wof:placetype": "postalcode"
  },
  "geometry": {"coordinates":[-1.488625,54.63211],"type":"Point"}
}
