{
  "type": "Feature",
  "properties": {
    "iso:country":"GB",
    "wof:name":"TS21 2JU",
    "wof:placetype":"postalcode"
},
  "geometry": {"coordinates":[-1.48878146969462,54.63232477957963],"type":"Point"}
}