{
  "type": "Feature",
  "properties": {
    "iso:country": "GB",
    "wof:name": "ST3 1NY",
    "wof:placetype": "postalcode"
  },
  "geometry": {"coordinates":[-2.130968,52.98683],"type":"Point"}
}
