{
  "type": "Feature",
  "properties": {
    "iso:country":"GB",
    "wof:name":"ST3 1NY",
    "wof:placetype":"postalcode"
},
  "geometry": {"coordinates":[-2.13096784448822,52.98682970630137],"type":"Point"}
}