{
  "type": "Feature",
  "properties": {
    "iso:country":"GB",
    "wof:name":"PO35 5YF",
    "wof:placetype":"postalcode"
},
  "geometry": {"coordinates":[-1.08428337694608,50.69243399638992],"type":"Point"}
}