{
  "type": "Feature",
  "properties": {
    "iso:country":"GB",
    "wof:name":"SP5 1PD",
    "wof:placetype":"postalcode"
},
  "geometry": {"coordinates":[-1.60933363997471,51.06973996954071],"type":"Point"}
}