{
  "type": "Feature",
  "properties": {
    "date:inception_lower": "1980-01-01",
    "date:inception_upper": "1980-01-01",
    "iso:country": "GB",
    "wof:name": "SP5 1PD",
    "wof:placetype": "postalcode"
  },
  "geometry": {"coordinates":[-1.609334,51.06974],"type":"Point"}
}
