{
  "type": "Feature",
  "properties": {
    "iso:country":"GB",
    "wof:name":"SE12 8ED",
    "wof:placetype":"postalcode"
},
  "geometry": {"coordinates":[0.01310787566351,51.45278129713004],"type":"Point"}
}