{
  "type": "Feature",
  "properties": {
    "date:inception_lower":"1980-01-01",
    "date:inception_upper":"1980-01-31",
    "iso:country":"GB",
    "wof:name":"SE12 8ED",
    "wof:placetype":"postalcode"
},
  "geometry": {"coordinates":[0.013108,51.452781],"type":"Point"}
}