{
  "type": "Feature",
  "properties": {
    "date:inception_lower":"1980-01-01",
    "date:inception_upper":"1980-01-31",
    "iso:country":"GB",
    "wof:name":"LE10 0LJ",
    "wof:placetype":"postalcode"
},
  "geometry": {"coordinates":[-1.382139,52.536111],"type":"Point"}
}