{
  "type": "Feature",
  "properties": {
    "iso:country":"GB",
    "wof:name":"LE10 0LJ",
    "wof:placetype":"postalcode"
},
  "geometry": {"coordinates":[-1.38213905352965,52.53611139820063],"type":"Point"}
}