{
  "type": "Feature",
  "properties": {
    "date:inception_lower":"1985-04-01",
    "date:inception_upper":"1985-04-30",
    "iso:country":"GB",
    "wof:name":"WA9 4TU",
    "wof:placetype":"postalcode"
},
  "geometry": {"coordinates":[-2.680784,53.430113],"type":"Point"}
}