{
  "type": "Feature",
  "properties": {
    "iso:country":"GB",
    "wof:name":"WA9 4TU",
    "wof:placetype":"postalcode"
},
  "geometry": {"coordinates":[-2.68004326121526,53.42986780762758],"type":"Point"}
}