{
  "type": "Feature",
  "properties": {
    "iso:country": "GB",
    "wof:name": "S6 4JJ",
    "wof:placetype": "postalcode"
  },
  "geometry": {"coordinates":[-1.503274,53.402351],"type":"Point"}
}
