{
  "type": "Feature",
  "properties": {
    "iso:country":"GB",
    "wof:name":"S6 4JJ",
    "wof:placetype":"postalcode"
},
  "geometry": {"coordinates":[-1.50327405991323,53.40235134126945],"type":"Point"}
}