{
  "type": "Feature",
  "properties": {
    "date:inception_lower": "1980-01-01",
    "date:inception_upper": "1980-01-01",
    "iso:country": "GB",
    "wof:name": "EH4 3EB",
    "wof:placetype": "postalcode"
  },
  "geometry": {"coordinates":[-3.232256,55.952489],"type":"Point"}
}
