{
  "type": "Feature",
  "properties": {
    "iso:country":"GB",
    "wof:name":"PR8 4HH",
    "wof:placetype":"postalcode"
},
  "geometry": {"coordinates":[-3.00824187354339,53.62994770591831],"type":"Point"}
}