{
  "type": "Feature",
  "properties": {
    "iso:country":"GB",
    "wof:name":"BS16 2FG",
    "wof:placetype":"postalcode"
},
  "geometry": {"coordinates":[-2.5364246616433,51.47797656834057],"type":"Point"}
}