{
  "type": "Feature",
  "properties": {
    "iso:country": "GB",
    "wof:name": "BS16 2FG",
    "wof:placetype": "postalcode"
  },
  "geometry": {"coordinates":[-2.536425,51.477977],"type":"Point"}
}
