{
  "type": "Feature",
  "properties": {
    "iso:country":"GB",
    "wof:name":"DY13 9GT",
    "wof:placetype":"postalcode"
},
  "geometry": {"coordinates":[-2.26601236544713,52.3443168610535],"type":"Point"}
}