{
  "type": "Feature",
  "properties": {
    "date:inception_lower": "1994-05-01",
    "date:inception_upper": "1994-05-01",
    "iso:country": "GB",
    "wof:name": "M9 8BX",
    "wof:placetype": "postalcode"
  },
  "geometry": {"coordinates":[-2.217995,53.520996],"type":"Point"}
}
