{
  "type": "Feature",
  "properties": {
    "iso:country":"GB",
    "wof:name":"TQ2 5QZ",
    "wof:placetype":"postalcode"
},
  "geometry": {"coordinates":[-3.53885555146327,50.47081401752198],"type":"Point"}
}