{
  "type": "Feature",
  "properties": {
    "iso:country":"GB",
    "wof:name":"DY5 4DD",
    "wof:placetype":"postalcode"
},
  "geometry": {"coordinates":[-2.13304106946856,52.49739957853591],"type":"Point"}
}