{
  "type": "Feature",
  "properties": {
    "iso:country":"GB",
    "wof:name":"DE13 9JZ",
    "wof:placetype":"postalcode"
},
  "geometry": {"coordinates":[-1.68834649837737,52.85490869919796],"type":"Point"}
}