{
  "type": "Feature",
  "properties": {
    "iso:country": "GB",
    "wof:name": "DE13 9JZ",
    "wof:placetype": "postalcode"
  },
  "geometry": {"coordinates":[-1.688346,52.854909],"type":"Point"}
}
