{
  "type": "Feature",
  "properties": {
    "iso:country": "GB",
    "wof:name": "CM9 6HT",
    "wof:placetype": "postalcode"
  },
  "geometry": {"coordinates":[0.666691,51.730197],"type":"Point"}
}
