{
  "type": "Feature",
  "properties": {
    "iso:country":"GB",
    "wof:name":"CM9 6HT",
    "wof:placetype":"postalcode"
},
  "geometry": {"coordinates":[0.66669053572677,51.73019660833789],"type":"Point"}
}