{
  "type": "Feature",
  "properties": {
    "date:inception_lower": "2016-12-01",
    "date:inception_upper": "2016-12-01",
    "iso:country": "GB",
    "wof:name": "DT8 3FN",
    "wof:placetype": "postalcode"
  },
  "geometry": {"coordinates":[-2.833694,50.845366],"type":"Point"}
}
