{
  "type": "Feature",
  "properties": {
    "iso:country": "GB",
    "wof:name": "DT8 3FN",
    "wof:placetype": "postalcode"
  },
  "geometry": {"coordinates":[-2.833694,50.845366],"type":"Point"}
}
