{
  "type": "Feature",
  "properties": {
    "date:inception_lower": "2018-12-01",
    "date:inception_upper": "2018-12-01",
    "iso:country": "GB",
    "wof:name": "BR2 6ER",
    "wof:placetype": "postalcode"
  },
  "geometry": {"coordinates":[0.036963,51.362973],"type":"Point"}
}
