{
  "type": "Feature",
  "properties": {
    "date:inception_lower": "1980-01-01",
    "date:inception_upper": "1980-01-01",
    "iso:country": "GB",
    "wof:name": "HP14 4TR",
    "wof:placetype": "postalcode"
  },
  "geometry": {"coordinates":[-0.789382,51.672738],"type":"Point"}
}
