{
  "type": "Feature",
  "properties": {
    "iso:country": "GB",
    "wof:name": "DN17 4JN",
    "wof:placetype": "postalcode"
  },
  "geometry": {"coordinates":[-0.818372,53.594194],"type":"Point"}
}
