{
  "type": "Feature",
  "properties": {
    "iso:country":"GB",
    "wof:name":"DN17 4JN",
    "wof:placetype":"postalcode"
},
  "geometry": {"coordinates":[-0.81846954541531,53.59431782868687],"type":"Point"}
}