{
  "type": "Feature",
  "properties": {
    "iso:country": "GB",
    "wof:name": "DN17 4JN",
    "wof:placetype": "postalcode"
  },
  "geometry": {"coordinates":[-0.818605,53.594502],"type":"Point"}
}
