{
  "type": "Feature",
  "properties": {
    "iso:country":"GB",
    "wof:name":"AL5 1RB",
    "wof:placetype":"postalcode"
},
  "geometry": {"coordinates":[-0.33794752438903,51.80392323513675],"type":"Point"}
}