{
  "type": "Feature",
  "properties": {
    "iso:country":"GB",
    "wof:name":"NE28 6HZ",
    "wof:placetype":"postalcode"
},
  "geometry": {"coordinates":[-1.51909878283877,54.99005931193179],"type":"Point"}
}