{
  "type": "Feature",
  "properties": {
    "iso:country":"GB",
    "wof:name":"UB3 2RW",
    "wof:placetype":"postalcode"
},
  "geometry": {"coordinates":[-0.42339247903262,51.51937029342419],"type":"Point"}
}