{
  "type": "Feature",
  "properties": {
    "iso:country": "GB",
    "wof:name": "UB3 2RW",
    "wof:placetype": "postalcode"
  },
  "geometry": {"coordinates":[-0.423392,51.51937],"type":"Point"}
}
