{
  "type": "Feature",
  "properties": {
    "iso:country": "GB",
    "wof:name": "SM5 1QG",
    "wof:placetype": "postalcode"
  },
  "geometry": {"coordinates":[-0.17564,51.382419],"type":"Point"}
}
