{
  "type": "Feature",
  "properties": {
    "iso:country":"GB",
    "wof:name":"SM5 1QG",
    "wof:placetype":"postalcode"
},
  "geometry": {"coordinates":[-0.17564003613467,51.38241907800464],"type":"Point"}
}