{
  "type": "Feature",
  "properties": {
    "date:inception_lower": "1990-07-01",
    "date:inception_upper": "1990-07-01",
    "iso:country": "GB",
    "wof:name": "LN2 4XB",
    "wof:placetype": "postalcode"
  },
  "geometry": {"coordinates":[-0.52501,53.253311],"type":"Point"}
}
