{
  "type": "Feature",
  "properties": {
    "iso:country":"GB",
    "wof:name":"LN2 4XB",
    "wof:placetype":"postalcode"
},
  "geometry": {"coordinates":[-0.52500973689597,53.2533113469274],"type":"Point"}
}