{
  "type": "Feature",
  "properties": {
    "iso:country":"GB",
    "wof:name":"SY10 8HU",
    "wof:placetype":"postalcode"
},
  "geometry": {"coordinates":[-3.00802755850798,52.8033360487649],"type":"Point"}
}