{
  "type": "Feature",
  "properties": {
    "date:inception_lower": "1980-01-01",
    "date:inception_upper": "1980-01-01",
    "iso:country": "GB",
    "wof:name": "SY10 8HU",
    "wof:placetype": "postalcode"
  },
  "geometry": {"coordinates":[-3.008119,52.80352],"type":"Point"}
}
