{
  "type": "Feature",
  "properties": {
    "date:inception_lower": "1983-03-01",
    "date:inception_upper": "1983-03-01",
    "iso:country": "GB",
    "wof:name": "DY14 8EE",
    "wof:placetype": "postalcode"
  },
  "geometry": {"coordinates":[-2.492238,52.379264],"type":"Point"}
}
