{
  "type": "Feature",
  "properties": {
    "iso:country":"GB",
    "wof:name":"DY14 8EE",
    "wof:placetype":"postalcode"
},
  "geometry": {"coordinates":[-2.49223823267264,52.37926372589477],"type":"Point"}
}