{
  "type": "Feature",
  "properties": {
    "iso:country": "GB",
    "wof:name": "DY14 8EE",
    "wof:placetype": "postalcode"
  },
  "geometry": {"coordinates":[-2.492238,52.379264],"type":"Point"}
}
