{
  "type": "Feature",
  "properties": {
    "iso:country": "GB",
    "wof:name": "TS26 8AB",
    "wof:placetype": "postalcode"
  },
  "geometry": {"coordinates":[-1.216484,54.685889],"type":"Point"}
}
