{
  "type": "Feature",
  "properties": {
    "iso:country":"GB",
    "wof:name":"IV30 6BL",
    "wof:placetype":"postalcode"
},
  "geometry": {"coordinates":[-3.30634153832421,57.6355655329959],"type":"Point"}
}