{
  "type": "Feature",
  "properties": {
    "date:inception_lower": "1998-12-01",
    "date:inception_upper": "1998-12-01",
    "iso:country": "GB",
    "wof:name": "IV30 6BL",
    "wof:placetype": "postalcode"
  },
  "geometry": {"coordinates":[-3.306341,57.635566],"type":"Point"}
}
