{
  "type": "Feature",
  "properties": {
    "iso:country":"GB",
    "wof:name":"TS23 3QT",
    "wof:placetype":"postalcode"
},
  "geometry": {"coordinates":[-1.27663385136821,54.61811399795972],"type":"Point"}
}