{
  "type": "Feature",
  "properties": {
    "date:inception_lower": "1980-01-01",
    "date:inception_upper": "1980-01-01",
    "iso:country": "GB",
    "wof:name": "GL7 1AY",
    "wof:placetype": "postalcode"
  },
  "geometry": {"coordinates":[-1.95233,51.717069],"type":"Point"}
}
