{
  "type": "Feature",
  "properties": {
    "iso:country":"GB",
    "wof:name":"GL7 1AY",
    "wof:placetype":"postalcode"
},
  "geometry": {"coordinates":[-1.95232965672874,51.7170691713369],"type":"Point"}
}