{
  "type": "Feature",
  "properties": {
    "iso:country": "GB",
    "wof:name": "S13 8HQ",
    "wof:placetype": "postalcode"
  },
  "geometry": {"coordinates":[-1.396948,53.372765],"type":"Point"}
}
