{
  "type": "Feature",
  "properties": {
    "iso:country":"GB",
    "wof:name":"S13 8HQ",
    "wof:placetype":"postalcode"
},
  "geometry": {"coordinates":[-1.3969477220378,53.37276546909063],"type":"Point"}
}