{
  "type": "Feature",
  "properties": {
    "iso:country":"GB",
    "wof:name":"PE19 5BJ",
    "wof:placetype":"postalcode"
},
  "geometry": {"coordinates":[-0.35082803316933,52.2409775077363],"type":"Point"}
}