{
  "type": "Feature",
  "properties": {
    "date:inception_lower": "2021-05-01",
    "date:inception_upper": "2021-05-01",
    "iso:country": "GB",
    "wof:name": "NN3 3EW",
    "wof:placetype": "postalcode"
  },
  "geometry": {"coordinates":[-0.845409,52.255586],"type":"Point"}
}
