{
  "type": "Feature",
  "properties": {
    "iso:country":"GB",
    "wof:name":"BS1 5DX",
    "wof:placetype":"postalcode"
},
  "geometry": {"coordinates":[-2.59931151393687,51.45417679761141],"type":"Point"}
}