{
  "type": "Feature",
  "properties": {
    "iso:country":"GB",
    "wof:name":"LL55 1UH",
    "wof:placetype":"postalcode"
},
  "geometry": {"coordinates":[-4.24428774615798,53.15196651846482],"type":"Point"}
}