{
  "type": "Feature",
  "properties": {
    "iso:country": "GB",
    "wof:name": "BN16 1NN",
    "wof:placetype": "postalcode"
  },
  "geometry": {"coordinates":[-0.48183,50.805117],"type":"Point"}
}
