{
  "type": "Feature",
  "properties": {
    "date:inception_lower": "2021-10-01",
    "date:inception_upper": "2021-10-01",
    "iso:country": "GB",
    "wof:name": "TS10 5FF",
    "wof:placetype": "postalcode"
  },
  "geometry": {"coordinates":[-1.087252,54.598163],"type":"Point"}
}
