{
  "type": "Feature",
  "properties": {
    "iso:country": "GB",
    "wof:name": "SA2 9JD",
    "wof:placetype": "postalcode"
  },
  "geometry": {"coordinates":[-3.999016,51.627629],"type":"Point"}
}
