{
  "type": "Feature",
  "properties": {
    "date:inception_lower": "1992-08-01",
    "date:inception_upper": "1992-08-01",
    "iso:country": "GB",
    "wof:name": "SA2 9JD",
    "wof:placetype": "postalcode"
  },
  "geometry": {"coordinates":[-3.999016,51.627629],"type":"Point"}
}
