{
  "type": "Feature",
  "properties": {
    "iso:country": "GB",
    "wof:name": "SS7 4PQ",
    "wof:placetype": "postalcode"
  },
  "geometry": {"coordinates":[0.546863,51.571418],"type":"Point"}
}
