{
  "type": "Feature",
  "properties": {
    "iso:country":"GB",
    "wof:name":"SS7 4PQ",
    "wof:placetype":"postalcode"
},
  "geometry": {"coordinates":[0.54686344792376,51.57141782374762],"type":"Point"}
}