{
  "type": "Feature",
  "properties": {
    "iso:country":"GB",
    "wof:name":"LL14 4DP",
    "wof:placetype":"postalcode"
},
  "geometry": {"coordinates":[-3.02495083914187,53.02868828586403],"type":"Point"}
}