{
  "type": "Feature",
  "properties": {
    "iso:country":"GB",
    "wof:name":"TD15 2UF",
    "wof:placetype":"postalcode"
},
  "geometry": {"coordinates":[-1.97548584350769,55.65160641893424],"type":"Point"}
}