{
  "type": "Feature",
  "properties": {
    "iso:country": "GB",
    "wof:name": "TD15 2UF",
    "wof:placetype": "postalcode"
  },
  "geometry": {"coordinates":[-1.975486,55.651606],"type":"Point"}
}
