{
  "type": "Feature",
  "properties": {
    "iso:country": "GB",
    "wof:name": "CF32 9PL",
    "wof:placetype": "postalcode"
  },
  "geometry": {"coordinates":[-3.596637,51.541348],"type":"Point"}
}
