{
  "type": "Feature",
  "properties": {
    "iso:country":"GB",
    "wof:name":"CF32 9PL",
    "wof:placetype":"postalcode"
},
  "geometry": {"coordinates":[-3.59663690747392,51.54134787592525],"type":"Point"}
}