{
  "type": "Feature",
  "properties": {
    "date:inception_lower": "1993-08-01",
    "date:inception_upper": "1993-08-01",
    "iso:country": "GB",
    "wof:name": "CF32 9PL",
    "wof:placetype": "postalcode"
  },
  "geometry": {"coordinates":[-3.596637,51.541348],"type":"Point"}
}
