{
  "type": "Feature",
  "properties": {
    "iso:country":"GB",
    "wof:name":"LL48 6HE",
    "wof:placetype":"postalcode"
},
  "geometry": {"coordinates":[-4.07928749408535,52.9271737075554],"type":"Point"}
}