{
  "type": "Feature",
  "properties": {
    "date:inception_lower":"1980-01-01",
    "date:inception_upper":"1980-01-31",
    "iso:country":"GB",
    "wof:name":"LL48 6HE",
    "wof:placetype":"postalcode"
},
  "geometry": {"coordinates":[-4.079287,52.927174],"type":"Point"}
}