{
  "type": "Feature",
  "properties": {
    "iso:country":"GB",
    "wof:name":"TN14 6JW",
    "wof:placetype":"postalcode"
},
  "geometry": {"coordinates":[0.12732496052845,51.24579436165159],"type":"Point"}
}