{
  "type": "Feature",
  "properties": {
    "date:inception_lower": "1980-01-01",
    "date:inception_upper": "1980-01-01",
    "iso:country": "GB",
    "wof:name": "TN14 6JW",
    "wof:placetype": "postalcode"
  },
  "geometry": {"coordinates":[0.127325,51.245794],"type":"Point"}
}
