{
  "type": "Feature",
  "properties": {
    "iso:country":"GB",
    "wof:name":"M22 5EJ",
    "wof:placetype":"postalcode"
},
  "geometry": {"coordinates":[-2.25083204796599,53.38089056078237],"type":"Point"}
}