{
  "type": "Feature",
  "properties": {
    "iso:country":"GB",
    "wof:name":"B63 2RR",
    "wof:placetype":"postalcode"
},
  "geometry": {"coordinates":[-2.09850111232218,52.45870468106859],"type":"Point"}
}