{
  "type": "Feature",
  "properties": {
    "iso:country": "GB",
    "wof:name": "B63 2RR",
    "wof:placetype": "postalcode"
  },
  "geometry": {"coordinates":[-2.097288,52.45872],"type":"Point"}
}
