{
  "type": "Feature",
  "properties": {
    "date:inception_lower":"1980-01-01",
    "date:inception_upper":"1980-01-31",
    "iso:country":"GB",
    "wof:name":"B63 2RR",
    "wof:placetype":"postalcode"
},
  "geometry": {"coordinates":[-2.097288,52.45872],"type":"Point"}
}