{
  "type": "Feature",
  "properties": {
    "iso:country": "GB",
    "wof:name": "BS37 7DS",
    "wof:placetype": "postalcode"
  },
  "geometry": {"coordinates":[-2.417654,51.55798],"type":"Point"}
}
