{
  "type": "Feature",
  "properties": {
    "iso:country":"GB",
    "wof:name":"B96 6JH",
    "wof:placetype":"postalcode"
},
  "geometry": {"coordinates":[-1.98647943282188,52.24876220832365],"type":"Point"}
}