{
  "type": "Feature",
  "properties": {
    "iso:country":"GB",
    "wof:name":"TW2 5PB",
    "wof:placetype":"postalcode"
},
  "geometry": {"coordinates":[-0.35299779834157,51.43658187328136],"type":"Point"}
}