{
  "type": "Feature",
  "properties": {
    "iso:country": "GB",
    "wof:name": "SA42 0PS",
    "wof:placetype": "postalcode"
  },
  "geometry": {"coordinates":[-4.8312,52.01602],"type":"Point"}
}
