{
  "type": "Feature",
  "properties": {
    "iso:country":"GB",
    "wof:name":"SA42 0PS",
    "wof:placetype":"postalcode"
},
  "geometry": {"coordinates":[-4.83144787134055,52.01597184742645],"type":"Point"}
}