{
  "type": "Feature",
  "properties": {
    "iso:country": "GB",
    "wof:name": "BS37 7AN",
    "wof:placetype": "postalcode"
  },
  "geometry": {"coordinates":[-2.403586,51.544282],"type":"Point"}
}
