{
  "type": "Feature",
  "properties": {
    "date:inception_lower":"1997-12-01",
    "date:inception_upper":"1997-12-31",
    "iso:country":"GB",
    "wof:name":"BS37 7AN",
    "wof:placetype":"postalcode"
},
  "geometry": {"coordinates":[-2.403586,51.544282],"type":"Point"}
}