{
  "type": "Feature",
  "properties": {
    "iso:country":"GB",
    "wof:name":"BR5 3NR",
    "wof:placetype":"postalcode"
},
  "geometry": {"coordinates":[0.11582547433205,51.39344437221682],"type":"Point"}
}