{
  "type": "Feature",
  "properties": {
    "date:inception_lower": "2021-12-01",
    "date:inception_upper": "2021-12-01",
    "iso:country": "GB",
    "wof:name": "PR2 5BZ",
    "wof:placetype": "postalcode"
  },
  "geometry": {"coordinates":[-2.63471,53.785597],"type":"Point"}
}
