{
  "type": "Feature",
  "properties": {
    "date:inception_lower": "1980-01-01",
    "date:inception_upper": "1980-01-01",
    "iso:country": "GB",
    "wof:name": "TW5 9SJ",
    "wof:placetype": "postalcode"
  },
  "geometry": {"coordinates":[-0.4144,51.479063],"type":"Point"}
}
