{
  "type": "Feature",
  "properties": {
    "iso:country":"GB",
    "wof:name":"LN2 4EQ",
    "wof:placetype":"postalcode"
},
  "geometry": {"coordinates":[-0.51983446589762,53.24430252148169],"type":"Point"}
}