{
  "type": "Feature",
  "properties": {
    "iso:country": "GB",
    "wof:name": "LN2 4EQ",
    "wof:placetype": "postalcode"
  },
  "geometry": {"coordinates":[-0.519834,53.244303],"type":"Point"}
}
