{
  "type": "Feature",
  "properties": {
    "iso:country": "GB",
    "wof:name": "HP19 0FH",
    "wof:placetype": "postalcode"
  },
  "geometry": {"coordinates":[-0.805017,51.834063],"type":"Point"}
}
