{
  "type": "Feature",
  "properties": {
    "iso:country":"GB",
    "wof:name":"SN8 1DS",
    "wof:placetype":"postalcode"
},
  "geometry": {"coordinates":[-1.72789841390729,51.4212176479891],"type":"Point"}
}