{
  "type": "Feature",
  "properties": {
    "iso:country": "GB",
    "wof:name": "SN8 1DS",
    "wof:placetype": "postalcode"
  },
  "geometry": {"coordinates":[-1.727898,51.421218],"type":"Point"}
}
