{
  "type": "Feature",
  "properties": {
    "iso:country":"GB",
    "wof:name":"SG8 6JY",
    "wof:placetype":"postalcode"
},
  "geometry": {"coordinates":[0.00790273389421,52.09066982059522],"type":"Point"}
}