{
  "type": "Feature",
  "properties": {
    "date:inception_lower": "1980-01-01",
    "date:inception_upper": "1980-01-01",
    "iso:country": "GB",
    "wof:name": "HD1 4UJ",
    "wof:placetype": "postalcode"
  },
  "geometry": {"coordinates":[-1.810523,53.643035],"type":"Point"}
}
