{
  "type": "Feature",
  "properties": {
    "iso:country":"GB",
    "wof:name":"HD1 4UJ",
    "wof:placetype":"postalcode"
},
  "geometry": {"coordinates":[-1.81052314969818,53.64303455133209],"type":"Point"}
}