{
  "type": "Feature",
  "properties": {
    "iso:country": "GB",
    "wof:name": "NE31 1DL",
    "wof:placetype": "postalcode"
  },
  "geometry": {"coordinates":[-1.524765,54.977429],"type":"Point"}
}
