{
  "type": "Feature",
  "properties": {
    "date:inception_lower": "2020-02-01",
    "date:inception_upper": "2020-02-01",
    "iso:country": "GB",
    "wof:name": "MK18 1YD",
    "wof:placetype": "postalcode"
  },
  "geometry": {"coordinates":[-1.00108,51.996195],"type":"Point"}
}
