{
  "type": "Feature",
  "properties": {
    "iso:country": "GB",
    "wof:name": "KT22 0HW",
    "wof:placetype": "postalcode"
  },
  "geometry": {"coordinates":[-0.360268,51.326679],"type":"Point"}
}
