{
  "type": "Feature",
  "properties": {
    "date:inception_lower": "1980-01-01",
    "date:inception_upper": "1980-01-01",
    "iso:country": "GB",
    "wof:name": "PO21 5NW",
    "wof:placetype": "postalcode"
  },
  "geometry": {"coordinates":[-0.693787,50.788473],"type":"Point"}
}
