{
  "type": "Feature",
  "properties": {
    "iso:country":"GB",
    "wof:name":"PO21 5NW",
    "wof:placetype":"postalcode"
},
  "geometry": {"coordinates":[-0.69378709637268,50.78847349722367],"type":"Point"}
}