{
  "type": "Feature",
  "properties": {
    "iso:country":"GB",
    "wof:name":"WV11 2QF",
    "wof:placetype":"postalcode"
},
  "geometry": {"coordinates":[-2.05510190301954,52.61204626976658],"type":"Point"}
}