{
  "type": "Feature",
  "properties": {
    "date:inception_lower": "1991-09-01",
    "date:inception_upper": "1991-09-01",
    "iso:country": "GB",
    "wof:name": "OX18 3QQ",
    "wof:placetype": "postalcode"
  },
  "geometry": {"coordinates":[-1.559327,51.751801],"type":"Point"}
}
