{
  "type": "Feature",
  "properties": {
    "iso:country":"GB",
    "wof:name":"IP21 4BL",
    "wof:placetype":"postalcode"
},
  "geometry": {"coordinates":[1.11950381438953,52.34293725317052],"type":"Point"}
}