{
  "type": "Feature",
  "properties": {
    "iso:country": "GB",
    "wof:name": "IP21 4BL",
    "wof:placetype": "postalcode"
  },
  "geometry": {"coordinates":[1.119504,52.342937],"type":"Point"}
}
