{
  "type": "Feature",
  "properties": {
    "date:inception_lower": "1980-01-01",
    "date:inception_upper": "1980-01-01",
    "iso:country": "GB",
    "wof:name": "IP21 4BL",
    "wof:placetype": "postalcode"
  },
  "geometry": {"coordinates":[1.119578,52.342982],"type":"Point"}
}
