{
  "type": "Feature",
  "properties": {
    "iso:country": "GB",
    "wof:name": "GL13 9NA",
    "wof:placetype": "postalcode"
  },
  "geometry": {"coordinates":[-2.472959,51.71618],"type":"Point"}
}
