{
  "type": "Feature",
  "properties": {
    "iso:country":"GB",
    "wof:name":"GL13 9NA",
    "wof:placetype":"postalcode"
},
  "geometry": {"coordinates":[-2.47295920723214,51.71617982334566],"type":"Point"}
}