{
  "type": "Feature",
  "properties": {
    "iso:country":"GB",
    "wof:name":"GU12 4AD",
    "wof:placetype":"postalcode"
},
  "geometry": {"coordinates":[-0.7448491796096,51.23835244596506],"type":"Point"}
}