{
  "type": "Feature",
  "properties": {
    "iso:country": "GB",
    "wof:name": "GU12 4AD",
    "wof:placetype": "postalcode"
  },
  "geometry": {"coordinates":[-0.744849,51.238352],"type":"Point"}
}
