{
  "type": "Feature",
  "properties": {
    "iso:country":"GB",
    "wof:name":"GL14 1RE",
    "wof:placetype":"postalcode"
},
  "geometry": {"coordinates":[-2.38828816704207,51.80642836158909],"type":"Point"}
}