{
  "type": "Feature",
  "properties": {
    "iso:country": "GB",
    "wof:name": "NG2 7QX",
    "wof:placetype": "postalcode"
  },
  "geometry": {"coordinates":[-1.14045,52.93173],"type":"Point"}
}
