{
  "type": "Feature",
  "properties": {
    "iso:country": "GB",
    "wof:name": "BH25 5UN",
    "wof:placetype": "postalcode"
  },
  "geometry": {"coordinates":[-1.66937,50.756234],"type":"Point"}
}
