{
  "type": "Feature",
  "properties": {
    "iso:country":"GB",
    "wof:name":"LA9 7HP",
    "wof:placetype":"postalcode"
},
  "geometry": {"coordinates":[-2.72691285558249,54.29806452169581],"type":"Point"}
}