{
  "type": "Feature",
  "properties": {
    "iso:country":"GB",
    "wof:name":"OL16 2TF",
    "wof:placetype":"postalcode"
},
  "geometry": {"coordinates":[-2.13968779021429,53.62656396480404],"type":"Point"}
}