{
  "type": "Feature",
  "properties": {
    "iso:country": "GB",
    "wof:name": "ZE2 9HG",
    "wof:placetype": "postalcode"
  },
  "geometry": {"coordinates":[-1.210508,60.052516],"type":"Point"}
}
