{
  "type": "Feature",
  "properties": {
    "iso:country":"GB",
    "wof:name":"ZE2 9HG",
    "wof:placetype":"postalcode"
},
  "geometry": {"coordinates":[-1.21050849983912,60.05251642241257],"type":"Point"}
}