{
  "type": "Feature",
  "properties": {
    "iso:country":"GB",
    "wof:name":"PE32 1JF",
    "wof:placetype":"postalcode"
},
  "geometry": {"coordinates":[0.55990205523712,52.6897269684917],"type":"Point"}
}