{
  "type": "Feature",
  "properties": {
    "date:inception_lower": "1980-01-01",
    "date:inception_upper": "1980-01-01",
    "iso:country": "GB",
    "wof:name": "E5 8JT",
    "wof:placetype": "postalcode"
  },
  "geometry": {"coordinates":[-0.057956,51.550957],"type":"Point"}
}
