{
  "type": "Feature",
  "properties": {
    "iso:country": "GB",
    "wof:name": "LS6 3HS",
    "wof:placetype": "postalcode"
  },
  "geometry": {"coordinates":[-1.577595,53.818643],"type":"Point"}
}
