{
  "type": "Feature",
  "properties": {
    "iso:country": "GB",
    "wof:name": "EN8 0ST",
    "wof:placetype": "postalcode"
  },
  "geometry": {"coordinates":[-0.036301,51.711984],"type":"Point"}
}
