{
  "type": "Feature",
  "properties": {
    "iso:country":"GB",
    "wof:name":"PE12 6PF",
    "wof:placetype":"postalcode"
},
  "geometry": {"coordinates":[-0.06553078776229,52.80448703489282],"type":"Point"}
}