{
  "type": "Feature",
  "properties": {
    "date:inception_lower": "1980-01-01",
    "date:inception_upper": "1980-01-01",
    "iso:country": "GB",
    "wof:name": "PE12 6PF",
    "wof:placetype": "postalcode"
  },
  "geometry": {"coordinates":[-0.065592,52.804443],"type":"Point"}
}
