{
  "type": "Feature",
  "properties": {
    "iso:country": "GB",
    "wof:name": "PE29 7DY",
    "wof:placetype": "postalcode"
  },
  "geometry": {"coordinates":[-0.182812,52.346443],"type":"Point"}
}
