{
  "type": "Feature",
  "properties": {
    "iso:country":"GB",
    "wof:name":"PE29 7DY",
    "wof:placetype":"postalcode"
},
  "geometry": {"coordinates":[-0.18281210681858,52.34644295036016],"type":"Point"}
}