{
  "type": "Feature",
  "properties": {
    "date:inception_lower":"1999-06-01",
    "date:inception_upper":"1999-06-30",
    "iso:country":"GB",
    "wof:name":"IP2 8RL",
    "wof:placetype":"postalcode"
},
  "geometry": {"coordinates":[1.156779,52.045799],"type":"Point"}
}