{
  "type": "Feature",
  "properties": {
    "iso:country":"GB",
    "wof:name":"DN36 4DT",
    "wof:placetype":"postalcode"
},
  "geometry": {"coordinates":[-0.02768404080837,53.53164617277348],"type":"Point"}
}