{
  "type": "Feature",
  "properties": {
    "date:inception_lower": "2002-06-01",
    "date:inception_upper": "2002-06-01",
    "iso:country": "GB",
    "wof:name": "CB4 1GX",
    "wof:placetype": "postalcode"
  },
  "geometry": {"coordinates":[0.139358,52.217815],"type":"Point"}
}
