{
  "type": "Feature",
  "properties": {
    "iso:country":"GB",
    "wof:name":"HS7 5LY",
    "wof:placetype":"postalcode"
},
  "geometry": {"coordinates":[-7.33969677127498,57.47463998794014],"type":"Point"}
}