{
  "type": "Feature",
  "properties": {
    "date:inception_lower": "1995-07-01",
    "date:inception_upper": "1995-07-01",
    "iso:country": "GB",
    "wof:name": "HS7 5LY",
    "wof:placetype": "postalcode"
  },
  "geometry": {"coordinates":[-7.339681,57.474607],"type":"Point"}
}
