{
  "type": "Feature",
  "properties": {
    "iso:country": "GB",
    "wof:name": "MK43 7DX",
    "wof:placetype": "postalcode"
  },
  "geometry": {"coordinates":[-0.60522,52.202557],"type":"Point"}
}
