{
  "type": "Feature",
  "properties": {
    "iso:country":"GB",
    "wof:name":"MK43 7DX",
    "wof:placetype":"postalcode"
},
  "geometry": {"coordinates":[-0.60522031552445,52.20255701430161],"type":"Point"}
}