{
  "type": "Feature",
  "properties": {
    "date:inception_lower": "1994-12-01",
    "date:inception_upper": "1994-12-01",
    "iso:country": "GB",
    "wof:name": "FY8 1LW",
    "wof:placetype": "postalcode"
  },
  "geometry": {"coordinates":[-3.033768,53.749826],"type":"Point"}
}
