{
  "type": "Feature",
  "properties": {
    "iso:country":"GB",
    "wof:name":"M32 0SB",
    "wof:placetype":"postalcode"
},
  "geometry": {"coordinates":[-2.29151765208628,53.46091308606962],"type":"Point"}
}