{
  "type": "Feature",
  "properties": {
    "iso:country":"GB",
    "wof:name":"SA4 3HJ",
    "wof:placetype":"postalcode"
},
  "geometry": {"coordinates":[-4.04344172747594,51.64112051935239],"type":"Point"}
}