{
  "type": "Feature",
  "properties": {
    "iso:country":"GB",
    "wof:name":"SN7 8LY",
    "wof:placetype":"postalcode"
},
  "geometry": {"coordinates":[-1.50940040182275,51.63733718173467],"type":"Point"}
}