{
  "type": "Feature",
  "properties": {
    "iso:country":"GB",
    "wof:name":"S18 8SA",
    "wof:placetype":"postalcode"
},
  "geometry": {"coordinates":[-1.50043505002217,53.29661404818545],"type":"Point"}
}