{
  "type": "Feature",
  "properties": {
    "iso:country": "GB",
    "wof:name": "S18 8SA",
    "wof:placetype": "postalcode"
  },
  "geometry": {"coordinates":[-1.500435,53.296614],"type":"Point"}
}
