{
  "type": "Feature",
  "properties": {
    "iso:country":"GB",
    "wof:name":"G46 6NE",
    "wof:placetype":"postalcode"
},
  "geometry": {"coordinates":[-4.28777045992872,55.79974509681491],"type":"Point"}
}