{
  "type": "Feature",
  "properties": {
    "iso:country":"GB",
    "wof:name":"BA2 1ST",
    "wof:placetype":"postalcode"
},
  "geometry": {"coordinates":[-2.40127857764392,51.38183925990669],"type":"Point"}
}