{
  "type": "Feature",
  "properties": {
    "date:inception_lower": "1980-01-01",
    "date:inception_upper": "1980-01-01",
    "iso:country": "GB",
    "wof:name": "BA2 1ST",
    "wof:placetype": "postalcode"
  },
  "geometry": {"coordinates":[-2.401279,51.381839],"type":"Point"}
}
