{
  "type": "Feature",
  "properties": {
    "iso:country": "GB",
    "wof:name": "WD3 8LA",
    "wof:placetype": "postalcode"
  },
  "geometry": {"coordinates":[-0.495012,51.643034],"type":"Point"}
}
