{
  "type": "Feature",
  "properties": {
    "iso:country":"GB",
    "wof:name":"WD3 8LA",
    "wof:placetype":"postalcode"
},
  "geometry": {"coordinates":[-0.4950122517709,51.64303434406776],"type":"Point"}
}