{
  "type": "Feature",
  "properties": {
    "iso:country":"GB",
    "wof:name":"M6 7AF",
    "wof:placetype":"postalcode"
},
  "geometry": {"coordinates":[-2.29327040956435,53.4922965484059],"type":"Point"}
}