{
  "type": "Feature",
  "properties": {
    "date:inception_lower": "2021-05-01",
    "date:inception_upper": "2021-05-01",
    "iso:country": "GB",
    "wof:name": "CF37 5ND",
    "wof:placetype": "postalcode"
  },
  "geometry": {"coordinates":[-3.311125,51.585882],"type":"Point"}
}
