{
  "type": "Feature",
  "properties": {
    "date:inception_lower": "1991-09-01",
    "date:inception_upper": "1991-09-01",
    "iso:country": "GB",
    "wof:name": "LL68 9BP",
    "wof:placetype": "postalcode"
  },
  "geometry": {"coordinates":[-4.344541,53.40908],"type":"Point"}
}
