{
  "type": "Feature",
  "properties": {
    "iso:country": "GB",
    "wof:name": "LL68 9BP",
    "wof:placetype": "postalcode"
  },
  "geometry": {"coordinates":[-4.344541,53.40908],"type":"Point"}
}
