{
  "type": "Feature",
  "properties": {
    "iso:country":"GB",
    "wof:name":"SL3 8TT",
    "wof:placetype":"postalcode"
},
  "geometry": {"coordinates":[-0.53771380753048,51.49389265573527],"type":"Point"}
}