{
  "type": "Feature",
  "properties": {
    "date:inception_lower": "1980-01-01",
    "date:inception_upper": "1980-01-01",
    "iso:country": "GB",
    "wof:name": "SL3 8TT",
    "wof:placetype": "postalcode"
  },
  "geometry": {"coordinates":[-0.537714,51.493893],"type":"Point"}
}
