{
  "type": "Feature",
  "properties": {
    "iso:country":"GB",
    "wof:name":"ML7 5AW",
    "wof:placetype":"postalcode"
},
  "geometry": {"coordinates":[-3.83481758533889,55.79918986304022],"type":"Point"}
}