{
  "type": "Feature",
  "properties": {
    "date:inception_lower": "1992-01-01",
    "date:inception_upper": "1992-01-01",
    "iso:country": "GB",
    "wof:name": "NR19 2UB",
    "wof:placetype": "postalcode"
  },
  "geometry": {"coordinates":[0.927844,52.675917],"type":"Point"}
}
