{
  "type": "Feature",
  "properties": {
    "iso:country":"GB",
    "wof:name":"NR19 2UB",
    "wof:placetype":"postalcode"
},
  "geometry": {"coordinates":[0.92784399504133,52.67591733596559],"type":"Point"}
}