{
  "type": "Feature",
  "properties": {
    "iso:country":"GB",
    "wof:name":"W3 7HY",
    "wof:placetype":"postalcode"
},
  "geometry": {"coordinates":[-0.2551353852893,51.51162871922771],"type":"Point"}
}