{
  "type": "Feature",
  "properties": {
    "iso:country":"GB",
    "wof:name":"NG7 1JZ",
    "wof:placetype":"postalcode"
},
  "geometry": {"coordinates":[-1.16890402306654,52.94837400752574],"type":"Point"}
}