{
  "type": "Feature",
  "properties": {
    "date:inception_lower": "1980-01-01",
    "date:inception_upper": "1980-01-01",
    "iso:country": "GB",
    "wof:name": "NG7 1JZ",
    "wof:placetype": "postalcode"
  },
  "geometry": {"coordinates":[-1.168904,52.948374],"type":"Point"}
}
