{
  "type": "Feature",
  "properties": {
    "date:inception_lower": "2019-01-01",
    "date:inception_upper": "2019-01-01",
    "iso:country": "GB",
    "wof:name": "CB24 1BY",
    "wof:placetype": "postalcode"
  },
  "geometry": {"coordinates":[0.056872,52.285818],"type":"Point"}
}
