{
  "type": "Feature",
  "properties": {
    "date:inception_lower":"1980-01-01",
    "date:inception_upper":"1980-01-31",
    "iso:country":"GB",
    "wof:name":"LS7 1AR",
    "wof:placetype":"postalcode"
},
  "geometry": {"coordinates":[-1.535198,53.803818],"type":"Point"}
}