{
  "type": "Feature",
  "properties": {
    "iso:country": "GB",
    "wof:name": "WS8 7PE",
    "wof:placetype": "postalcode"
  },
  "geometry": {"coordinates":[-1.936844,52.658403],"type":"Point"}
}
