{
  "type": "Feature",
  "properties": {
    "iso:country":"GB",
    "wof:name":"WS8 7PE",
    "wof:placetype":"postalcode"
},
  "geometry": {"coordinates":[-1.93687396120918,52.65836656657686],"type":"Point"}
}