{
  "type": "Feature",
  "properties": {
    "iso:country": "GB",
    "wof:name": "CM20 2FT",
    "wof:placetype": "postalcode"
  },
  "geometry": {"coordinates":[0.098215,51.78539],"type":"Point"}
}
