{
  "type": "Feature",
  "properties": {
    "iso:country": "GB",
    "wof:name": "DH4 5PY",
    "wof:placetype": "postalcode"
  },
  "geometry": {"coordinates":[-1.484378,54.841893],"type":"Point"}
}
