{
  "type": "Feature",
  "properties": {
    "iso:country":"GB",
    "wof:name":"DH4 5PY",
    "wof:placetype":"postalcode"
},
  "geometry": {"coordinates":[-1.48437777113715,54.84189316266902],"type":"Point"}
}