{
  "type": "Feature",
  "properties": {
    "iso:country":"GB",
    "wof:name":"ST1 4JH",
    "wof:placetype":"postalcode"
},
  "geometry": {"coordinates":[-2.18059303661592,53.02060880944726],"type":"Point"}
}