{
  "type": "Feature",
  "properties": {
    "iso:country":"GB",
    "wof:name":"M21 9JZ",
    "wof:placetype":"postalcode"
},
  "geometry": {"coordinates":[-2.28874685269372,53.44323941843279],"type":"Point"}
}