{
  "type": "Feature",
  "properties": {
    "iso:country": "GB",
    "wof:name": "M21 9JZ",
    "wof:placetype": "postalcode"
  },
  "geometry": {"coordinates":[-2.288747,53.443239],"type":"Point"}
}
