{
  "type": "Feature",
  "properties": {
    "iso:country":"GB",
    "wof:name":"BN10 7JA",
    "wof:placetype":"postalcode"
},
  "geometry": {"coordinates":[-0.00754233311388,50.79130680402137],"type":"Point"}
}