{
  "type": "Feature",
  "properties": {
    "date:inception_lower": "1999-06-01",
    "date:inception_upper": "1999-06-01",
    "iso:country": "GB",
    "wof:name": "CH43 5TD",
    "wof:placetype": "postalcode"
  },
  "geometry": {"coordinates":[-3.042568,53.381785],"type":"Point"}
}
