{
  "type": "Feature",
  "properties": {
    "iso:country": "GB",
    "wof:name": "SO16 0YB",
    "wof:placetype": "postalcode"
  },
  "geometry": {"coordinates":[-1.48865,50.946287],"type":"Point"}
}
