{
  "type": "Feature",
  "properties": {
    "iso:country":"GB",
    "wof:name":"SO16 0YB",
    "wof:placetype":"postalcode"
},
  "geometry": {"coordinates":[-1.48864995789363,50.94628696443607],"type":"Point"}
}