{
  "type": "Feature",
  "properties": {
    "date:inception_lower": "1980-01-01",
    "date:inception_upper": "1980-01-01",
    "iso:country": "GB",
    "wof:name": "LA3 3AZ",
    "wof:placetype": "postalcode"
  },
  "geometry": {"coordinates":[-2.840921,54.06154],"type":"Point"}
}
