{
  "type": "Feature",
  "properties": {
    "iso:country":"GB",
    "wof:name":"LA3 3AZ",
    "wof:placetype":"postalcode"
},
  "geometry": {"coordinates":[-2.84153676783165,54.06176976746871],"type":"Point"}
}