{
  "type": "Feature",
  "properties": {
    "iso:country": "GB",
    "wof:name": "CA2 5RB",
    "wof:placetype": "postalcode"
  },
  "geometry": {"coordinates":[-2.95822,54.888245],"type":"Point"}
}
