{
  "type": "Feature",
  "properties": {
    "iso:country":"GB",
    "wof:name":"OL9 8JR",
    "wof:placetype":"postalcode"
},
  "geometry": {"coordinates":[-2.14728154008418,53.52777345751005],"type":"Point"}
}