{
  "type": "Feature",
  "properties": {
    "iso:country":"GB",
    "wof:name":"KT2 6SB",
    "wof:placetype":"postalcode"
},
  "geometry": {"coordinates":[-0.287254839872,51.41558654376082],"type":"Point"}
}