{
  "type": "Feature",
  "properties": {
    "iso:country": "GB",
    "wof:name": "EX17 5HS",
    "wof:placetype": "postalcode"
  },
  "geometry": {"coordinates":[-3.752072,50.813792],"type":"Point"}
}
