{
  "type": "Feature",
  "properties": {
    "date:inception_lower":"1980-01-01",
    "date:inception_upper":"1980-01-31",
    "iso:country":"GB",
    "wof:name":"EX34 7EE",
    "wof:placetype":"postalcode"
},
  "geometry": {"coordinates":[-4.207098,51.186911],"type":"Point"}
}