{
  "type": "Feature",
  "properties": {
    "iso:country":"GB",
    "wof:name":"TA2 8RF",
    "wof:placetype":"postalcode"
},
  "geometry": {"coordinates":[-3.0371657709736,51.05900798151184],"type":"Point"}
}