{
  "type": "Feature",
  "properties": {
    "date:inception_lower": "1980-01-01",
    "date:inception_upper": "1980-01-01",
    "iso:country": "GB",
    "wof:name": "CA11 9QJ",
    "wof:placetype": "postalcode"
  },
  "geometry": {"coordinates":[-2.827296,54.753919],"type":"Point"}
}
