{
  "type": "Feature",
  "properties": {
    "iso:country": "GB",
    "wof:name": "CA11 9QJ",
    "wof:placetype": "postalcode"
  },
  "geometry": {"coordinates":[-2.827326,54.753883],"type":"Point"}
}
