{
  "type": "Feature",
  "properties": {
    "iso:country":"GB",
    "wof:name":"CA11 9QJ",
    "wof:placetype":"postalcode"
},
  "geometry": {"coordinates":[-2.82729108143266,54.7539117791208],"type":"Point"}
}