{
  "type": "Feature",
  "properties": {
    "iso:country":"GB",
    "wof:name":"E1 1PZ",
    "wof:placetype":"postalcode"
},
  "geometry": {"coordinates":[-0.06266423428377,51.51447957441136],"type":"Point"}
}