{
  "type": "Feature",
  "properties": {
    "date:inception_lower": "1985-10-01",
    "date:inception_upper": "1985-10-01",
    "iso:country": "GB",
    "wof:name": "MK14 5HB",
    "wof:placetype": "postalcode"
  },
  "geometry": {"coordinates":[-0.758487,52.065924],"type":"Point"}
}
