{
  "type": "Feature",
  "properties": {
    "iso:country":"GB",
    "wof:name":"MK14 5HB",
    "wof:placetype":"postalcode"
},
  "geometry": {"coordinates":[-0.75848748797356,52.06592429177554],"type":"Point"}
}