{
  "type": "Feature",
  "properties": {
    "date:inception_lower": "1980-01-01",
    "date:inception_upper": "1980-01-01",
    "iso:country": "GB",
    "wof:name": "KT3 4HP",
    "wof:placetype": "postalcode"
  },
  "geometry": {"coordinates":[-0.251505,51.403997],"type":"Point"}
}
