{
  "type": "Feature",
  "properties": {
    "iso:country":"GB",
    "wof:name":"TA21 0PP",
    "wof:placetype":"postalcode"
},
  "geometry": {"coordinates":[-3.33961012697537,50.9626144352107],"type":"Point"}
}