{
  "type": "Feature",
  "properties": {
    "iso:country":"GB",
    "wof:name":"LE12 6QE",
    "wof:placetype":"postalcode"
},
  "geometry": {"coordinates":[-1.18085980660675,52.83061256237388],"type":"Point"}
}