{
  "type": "Feature",
  "properties": {
    "date:inception_lower": "1980-01-01",
    "date:inception_upper": "1980-01-01",
    "iso:country": "GB",
    "wof:name": "LE12 6QE",
    "wof:placetype": "postalcode"
  },
  "geometry": {"coordinates":[-1.18086,52.830613],"type":"Point"}
}
