{
  "type": "Feature",
  "properties": {
    "iso:country": "GB",
    "wof:name": "BN3 4JL",
    "wof:placetype": "postalcode"
  },
  "geometry": {"coordinates":[-0.193895,50.828184],"type":"Point"}
}
