{
  "type": "Feature",
  "properties": {
    "iso:country":"GB",
    "wof:name":"BN3 4JL",
    "wof:placetype":"postalcode"
},
  "geometry": {"coordinates":[-0.19389497123917,50.82818362276986],"type":"Point"}
}