{
  "type": "Feature",
  "properties": {
    "iso:country": "GB",
    "wof:name": "BS32 4TD",
    "wof:placetype": "postalcode"
  },
  "geometry": {"coordinates":[-2.572068,51.542591],"type":"Point"}
}
