{
  "type": "Feature",
  "properties": {
    "iso:country":"GB",
    "wof:name":"BS32 4TD",
    "wof:placetype":"postalcode"
},
  "geometry": {"coordinates":[-2.57205149604771,51.54260121686058],"type":"Point"}
}