{
  "type": "Feature",
  "properties": {
    "date:inception_lower": "2000-12-01",
    "date:inception_upper": "2000-12-01",
    "iso:country": "GB",
    "wof:name": "IV2 5DJ",
    "wof:placetype": "postalcode"
  },
  "geometry": {"coordinates":[-4.172584,57.468651],"type":"Point"}
}
