{
  "type": "Feature",
  "properties": {
    "iso:country":"GB",
    "wof:name":"OL2 8HF",
    "wof:placetype":"postalcode"
},
  "geometry": {"coordinates":[-2.08745865760741,53.5808814084691],"type":"Point"}
}