{
  "type": "Feature",
  "properties": {
    "iso:country": "GB",
    "wof:name": "NR29 4SD",
    "wof:placetype": "postalcode"
  },
  "geometry": {"coordinates":[1.634418,52.701085],"type":"Point"}
}
