{
  "type": "Feature",
  "properties": {
    "date:inception_lower": "1999-06-01",
    "date:inception_upper": "1999-06-01",
    "iso:country": "GB",
    "wof:name": "NG20 8ES",
    "wof:placetype": "postalcode"
  },
  "geometry": {"coordinates":[-1.226633,53.198441],"type":"Point"}
}
