{
  "type": "Feature",
  "properties": {
    "iso:country":"GB",
    "wof:name":"NG20 8ES",
    "wof:placetype":"postalcode"
},
  "geometry": {"coordinates":[-1.22664910689718,53.19844088071845],"type":"Point"}
}