{
  "type": "Feature",
  "properties": {
    "iso:country": "GB",
    "wof:name": "CV35 8LS",
    "wof:placetype": "postalcode"
  },
  "geometry": {"coordinates":[-1.702086,52.283549],"type":"Point"}
}
