{
  "type": "Feature",
  "properties": {
    "iso:country": "GB",
    "wof:name": "CV21 3BH",
    "wof:placetype": "postalcode"
  },
  "geometry": {"coordinates":[-1.26219,52.371506],"type":"Point"}
}
