{
  "type": "Feature",
  "properties": {
    "iso:country":"GB",
    "wof:name":"CV21 3BH",
    "wof:placetype":"postalcode"
},
  "geometry": {"coordinates":[-1.26222973637257,52.37159683886082],"type":"Point"}
}