{
  "type": "Feature",
  "properties": {
    "iso:country": "GB",
    "wof:name": "PL24 2RB",
    "wof:placetype": "postalcode"
  },
  "geometry": {"coordinates":[-4.688567,50.358379],"type":"Point"}
}
