{
  "type": "Feature",
  "properties": {
    "iso:country":"GB",
    "wof:name":"SS7 2AT",
    "wof:placetype":"postalcode"
},
  "geometry": {"coordinates":[0.60788092053933,51.54971589220424],"type":"Point"}
}