{
  "type": "Feature",
  "properties": {
    "date:inception_lower": "1980-01-01",
    "date:inception_upper": "1980-01-01",
    "iso:country": "GB",
    "wof:name": "NN7 1NY",
    "wof:placetype": "postalcode"
  },
  "geometry": {"coordinates":[-0.789837,52.238481],"type":"Point"}
}
