{
  "type": "Feature",
  "properties": {
    "iso:country":"GB",
    "wof:name":"LD6 5LL",
    "wof:placetype":"postalcode"
},
  "geometry": {"coordinates":[-3.49368480677529,52.3599056775328],"type":"Point"}
}