{
  "type": "Feature",
  "properties": {
    "iso:country": "GB",
    "wof:name": "NG21 0TW",
    "wof:placetype": "postalcode"
  },
  "geometry": {"coordinates":[-1.109975,53.097945],"type":"Point"}
}
