{
  "type": "Feature",
  "properties": {
    "iso:country": "GB",
    "wof:name": "RG2 9JJ",
    "wof:placetype": "postalcode"
  },
  "geometry": {"coordinates":[-0.903233,51.414768],"type":"Point"}
}
