{
  "type": "Feature",
  "properties": {
    "iso:country": "GB",
    "wof:name": "RG2 9JJ",
    "wof:placetype": "postalcode"
  },
  "geometry": {"coordinates":[-0.903763,51.415033],"type":"Point"}
}
