{
  "type": "Feature",
  "properties": {
    "iso:country": "GB",
    "wof:name": "BH21 4JH",
    "wof:placetype": "postalcode"
  },
  "geometry": {"coordinates":[-1.973646,50.841148],"type":"Point"}
}
