{
  "type": "Feature",
  "properties": {
    "iso:country":"GB",
    "wof:name":"BH21 4JH",
    "wof:placetype":"postalcode"
},
  "geometry": {"coordinates":[-1.97364566134533,50.84114809153982],"type":"Point"}
}