{
  "type": "Feature",
  "properties": {
    "iso:country":"GB",
    "wof:name":"WA15 8DG",
    "wof:placetype":"postalcode"
},
  "geometry": {"coordinates":[-2.33235734830074,53.37908230013002],"type":"Point"}
}