{
  "type": "Feature",
  "properties": {
    "date:inception_lower": "1980-01-01",
    "date:inception_upper": "1980-01-01",
    "iso:country": "GB",
    "wof:name": "WA15 8DG",
    "wof:placetype": "postalcode"
  },
  "geometry": {"coordinates":[-2.332357,53.379082],"type":"Point"}
}
