{
  "type": "Feature",
  "properties": {
    "iso:country":"GB",
    "wof:name":"HU3 2HF",
    "wof:placetype":"postalcode"
},
  "geometry": {"coordinates":[-0.35099329795279,53.74206463129659],"type":"Point"}
}