{
  "type": "Feature",
  "properties": {
    "iso:country": "GB",
    "wof:name": "HU3 2HF",
    "wof:placetype": "postalcode"
  },
  "geometry": {"coordinates":[-0.350993,53.742065],"type":"Point"}
}
