{
  "type": "Feature",
  "properties": {
    "iso:country":"GB",
    "wof:name":"PL14 3NU",
    "wof:placetype":"postalcode"
},
  "geometry": {"coordinates":[-4.4561694621908,50.45674406350754],"type":"Point"}
}