{
  "type": "Feature",
  "properties": {
    "date:inception_lower": "1988-03-01",
    "date:inception_upper": "1988-03-01",
    "iso:country": "GB",
    "wof:name": "PL14 3NU",
    "wof:placetype": "postalcode"
  },
  "geometry": {"coordinates":[-4.456169,50.456744],"type":"Point"}
}
