{
  "type": "Feature",
  "properties": {
    "iso:country":"GB",
    "wof:name":"AB21 0TE",
    "wof:placetype":"postalcode"
},
  "geometry": {"coordinates":[-2.27653800201794,57.21848931667277],"type":"Point"}
}