{
  "type": "Feature",
  "properties": {
    "date:inception_lower": "1996-06-01",
    "date:inception_upper": "1996-06-01",
    "iso:country": "GB",
    "wof:name": "AB21 0TE",
    "wof:placetype": "postalcode"
  },
  "geometry": {"coordinates":[-2.276538,57.218489],"type":"Point"}
}
