{
  "type": "Feature",
  "properties": {
    "date:inception_lower": "2019-09-01",
    "date:inception_upper": "2019-09-01",
    "iso:country": "GB",
    "wof:name": "KW10 6UE",
    "wof:placetype": "postalcode"
  },
  "geometry": {"coordinates":[-3.994973,57.972566],"type":"Point"}
}
