{
  "type": "Feature",
  "properties": {
    "iso:country":"GB",
    "wof:name":"B8 2TR",
    "wof:placetype":"postalcode"
},
  "geometry": {"coordinates":[-1.83084749289688,52.49215795575635],"type":"Point"}
}