{
  "type": "Feature",
  "properties": {
    "iso:country":"GB",
    "wof:name":"TN40 2QP",
    "wof:placetype":"postalcode"
},
  "geometry": {"coordinates":[0.49459836361409,50.85720632764368],"type":"Point"}
}