{
  "type": "Feature",
  "properties": {
    "date:inception_lower": "1980-01-01",
    "date:inception_upper": "1980-01-01",
    "iso:country": "GB",
    "wof:name": "SW1P 4NX",
    "wof:placetype": "postalcode"
  },
  "geometry": {"coordinates":[-0.133934,51.491294],"type":"Point"}
}
