{
  "type": "Feature",
  "properties": {
    "iso:country":"GB",
    "wof:name":"PE11 1PD",
    "wof:placetype":"postalcode"
},
  "geometry": {"coordinates":[-0.16045535556155,52.79098206634993],"type":"Point"}
}