{
  "type": "Feature",
  "properties": {
    "iso:country":"GB",
    "wof:name":"ME2 2ET",
    "wof:placetype":"postalcode"
},
  "geometry": {"coordinates":[0.48592916746136,51.39316305022002],"type":"Point"}
}