{
  "type": "Feature",
  "properties": {
    "date:inception_lower": "1980-01-01",
    "date:inception_upper": "1980-01-01",
    "iso:country": "GB",
    "wof:name": "OX2 6BS",
    "wof:placetype": "postalcode"
  },
  "geometry": {"coordinates":[-1.268746,51.758125],"type":"Point"}
}
