{
  "type": "Feature",
  "properties": {
    "iso:country":"GB",
    "wof:name":"CT19 5LB",
    "wof:placetype":"postalcode"
},
  "geometry": {"coordinates":[1.15610674715304,51.08653116966459],"type":"Point"}
}