{
  "type": "Feature",
  "properties": {
    "date:inception_lower": "1980-01-01",
    "date:inception_upper": "1980-01-01",
    "iso:country": "GB",
    "wof:name": "YO18 7RJ",
    "wof:placetype": "postalcode"
  },
  "geometry": {"coordinates":[-0.721829,54.230012],"type":"Point"}
}
