{
  "type": "Feature",
  "properties": {
    "date:inception_lower":"1984-02-01",
    "date:inception_upper":"1984-02-29",
    "iso:country":"GB",
    "wof:name":"LU6 3LE",
    "wof:placetype":"postalcode"
},
  "geometry": {"coordinates":[-0.513632,51.878982],"type":"Point"}
}