{
  "type": "Feature",
  "properties": {
    "iso:country": "GB",
    "wof:name": "LU6 3LE",
    "wof:placetype": "postalcode"
  },
  "geometry": {"coordinates":[-0.513632,51.878982],"type":"Point"}
}
