{
  "type": "Feature",
  "properties": {
    "iso:country":"GB",
    "wof:name":"TS26 8NW",
    "wof:placetype":"postalcode"
},
  "geometry": {"coordinates":[-1.22851936839595,54.69012601726094],"type":"Point"}
}