{
  "type": "Feature",
  "properties": {
    "iso:country": "GB",
    "wof:name": "TS26 8NW",
    "wof:placetype": "postalcode"
  },
  "geometry": {"coordinates":[-1.228519,54.690126],"type":"Point"}
}
