{
  "type": "Feature",
  "properties": {
    "iso:country": "GB",
    "wof:name": "ME14 3HG",
    "wof:placetype": "postalcode"
  },
  "geometry": {"coordinates":[0.604289,51.325387],"type":"Point"}
}
