{
  "type": "Feature",
  "properties": {
    "iso:country":"GB",
    "wof:name":"ME14 3HG",
    "wof:placetype":"postalcode"
},
  "geometry": {"coordinates":[0.60428864637557,51.32538679258957],"type":"Point"}
}