{
  "type": "Feature",
  "properties": {
    "iso:country":"GB",
    "wof:name":"SW8 1TW",
    "wof:placetype":"postalcode"
},
  "geometry": {"coordinates":[-0.12247176704696,51.48408621646924],"type":"Point"}
}