{
  "type": "Feature",
  "properties": {
    "iso:country":"GB",
    "wof:name":"OX3 9UL",
    "wof:placetype":"postalcode"
},
  "geometry": {"coordinates":[-1.21509211275976,51.79173001467489],"type":"Point"}
}