{
  "type": "Feature",
  "properties": {
    "date:inception_lower": "1980-01-01",
    "date:inception_upper": "1980-01-01",
    "iso:country": "GB",
    "wof:name": "GU29 9DD",
    "wof:placetype": "postalcode"
  },
  "geometry": {"coordinates":[-0.740069,50.986528],"type":"Point"}
}
