{
  "type": "Feature",
  "properties": {
    "iso:country":"GB",
    "wof:name":"GU29 9DD",
    "wof:placetype":"postalcode"
},
  "geometry": {"coordinates":[-0.74006889218795,50.98652849458208],"type":"Point"}
}