{
  "type": "Feature",
  "properties": {
    "iso:country":"GB",
    "wof:name":"W5 5EU",
    "wof:placetype":"postalcode"
},
  "geometry": {"coordinates":[-0.3054623183357,51.50611691118044],"type":"Point"}
}