{
  "type": "Feature",
  "properties": {
    "date:inception_lower": "1980-01-01",
    "date:inception_upper": "1980-01-01",
    "iso:country": "GB",
    "wof:name": "SP8 5RF",
    "wof:placetype": "postalcode"
  },
  "geometry": {"coordinates":[-2.289334,51.0242],"type":"Point"}
}
