{
  "type": "Feature",
  "properties": {
    "iso:country":"GB",
    "wof:name":"SP8 5RF",
    "wof:placetype":"postalcode"
},
  "geometry": {"coordinates":[-2.28933364171508,51.02419996213575],"type":"Point"}
}