{
  "type": "Feature",
  "properties": {
    "date:inception_lower": "2002-08-01",
    "date:inception_upper": "2002-08-01",
    "iso:country": "GB",
    "wof:name": "DT2 0HS",
    "wof:placetype": "postalcode"
  },
  "geometry": {"coordinates":[-2.642616,50.808778],"type":"Point"}
}
