{
  "type": "Feature",
  "properties": {
    "iso:country": "GB",
    "wof:name": "DT2 0HS",
    "wof:placetype": "postalcode"
  },
  "geometry": {"coordinates":[-2.642616,50.808778],"type":"Point"}
}
