{
  "type": "Feature",
  "properties": {
    "date:inception_lower": "1980-01-01",
    "date:inception_upper": "1980-01-01",
    "iso:country": "GB",
    "wof:name": "SL4 3QZ",
    "wof:placetype": "postalcode"
  },
  "geometry": {"coordinates":[-0.63186,51.477737],"type":"Point"}
}
