{
  "type": "Feature",
  "properties": {
    "iso:country":"GB",
    "wof:name":"KA18 1PS",
    "wof:placetype":"postalcode"
},
  "geometry": {"coordinates":[-4.25647118431096,55.45638052966041],"type":"Point"}
}