{
  "type": "Feature",
  "properties": {
    "iso:country": "GB",
    "wof:name": "E15 3AT",
    "wof:placetype": "postalcode"
  },
  "geometry": {"coordinates":[0.005388,51.529478],"type":"Point"}
}
