{
  "type": "Feature",
  "properties": {
    "date:inception_lower": "1994-12-01",
    "date:inception_upper": "1994-12-01",
    "iso:country": "GB",
    "wof:name": "E15 3AT",
    "wof:placetype": "postalcode"
  },
  "geometry": {"coordinates":[0.005388,51.529478],"type":"Point"}
}
