{
  "type": "Feature",
  "properties": {
    "iso:country":"GB",
    "wof:name":"E15 3AT",
    "wof:placetype":"postalcode"
},
  "geometry": {"coordinates":[0.00538806412136,51.52947755260949],"type":"Point"}
}