{
  "type": "Feature",
  "properties": {
    "iso:country":"GB",
    "wof:name":"PL26 8JB",
    "wof:placetype":"postalcode"
},
  "geometry": {"coordinates":[-4.82853738605102,50.40887496946359],"type":"Point"}
}