{
  "type": "Feature",
  "properties": {
    "iso:country":"GB",
    "wof:name":"CF15 9JX",
    "wof:placetype":"postalcode"
},
  "geometry": {"coordinates":[-3.32535997060715,51.52040360539652],"type":"Point"}
}