{
  "type": "Feature",
  "properties": {
    "iso:country":"GB",
    "wof:name":"WN6 0ES",
    "wof:placetype":"postalcode"
},
  "geometry": {"coordinates":[-2.65767242497485,53.58430885197424],"type":"Point"}
}