{
  "type": "Feature",
  "properties": {
    "iso:country":"GB",
    "wof:name":"HG5 8BF",
    "wof:placetype":"postalcode"
},
  "geometry": {"coordinates":[-1.46906984062515,54.00930386195512],"type":"Point"}
}