{
  "type": "Feature",
  "properties": {
    "iso:country": "GB",
    "wof:name": "HG5 8BF",
    "wof:placetype": "postalcode"
  },
  "geometry": {"coordinates":[-1.46907,54.009304],"type":"Point"}
}
