{
  "type": "Feature",
  "properties": {
    "iso:country":"GB",
    "wof:name":"SA17 5LS",
    "wof:placetype":"postalcode"
},
  "geometry": {"coordinates":[-4.22890650551861,51.78803108541995],"type":"Point"}
}