{
  "type": "Feature",
  "properties": {
    "iso:country":"GB",
    "wof:name":"OX26 3ER",
    "wof:placetype":"postalcode"
},
  "geometry": {"coordinates":[-1.15144563558616,51.90573651610103],"type":"Point"}
}