{
  "type": "Feature",
  "properties": {
    "date:inception_lower": "1980-01-01",
    "date:inception_upper": "1980-01-01",
    "iso:country": "GB",
    "wof:name": "G53 7EY",
    "wof:placetype": "postalcode"
  },
  "geometry": {"coordinates":[-4.370679,55.82156],"type":"Point"}
}
