{
  "type": "Feature",
  "properties": {
    "iso:country":"GB",
    "wof:name":"G53 7EY",
    "wof:placetype":"postalcode"
},
  "geometry": {"coordinates":[-4.37067939061268,55.82156003313173],"type":"Point"}
}