{
  "type": "Feature",
  "properties": {
    "iso:country":"GB",
    "wof:name":"G44 3QL",
    "wof:placetype":"postalcode"
},
  "geometry": {"coordinates":[-4.26886130082151,55.80355582986169],"type":"Point"}
}