{
  "type": "Feature",
  "properties": {
    "iso:country": "GB",
    "wof:name": "G44 3QL",
    "wof:placetype": "postalcode"
  },
  "geometry": {"coordinates":[-4.268861,55.803556],"type":"Point"}
}
