{
  "type": "Feature",
  "properties": {
    "iso:country":"GB",
    "wof:name":"OX26 2JN",
    "wof:placetype":"postalcode"
},
  "geometry": {"coordinates":[-1.1604150274885,51.89867989208012],"type":"Point"}
}