{
  "type": "Feature",
  "properties": {
    "iso:country": "GB",
    "wof:name": "OX26 2JN",
    "wof:placetype": "postalcode"
  },
  "geometry": {"coordinates":[-1.160415,51.89868],"type":"Point"}
}
