{
  "type": "Feature",
  "properties": {
    "iso:country":"GB",
    "wof:name":"LS9 0JF",
    "wof:placetype":"postalcode"
},
  "geometry": {"coordinates":[-1.49222320533378,53.79660621620555],"type":"Point"}
}