{
  "type": "Feature",
  "properties": {
    "date:inception_lower": "2001-06-01",
    "date:inception_upper": "2001-06-01",
    "iso:country": "GB",
    "wof:name": "HA8 8UU",
    "wof:placetype": "postalcode"
  },
  "geometry": {"coordinates":[-0.27079,51.625382],"type":"Point"}
}
