{
  "type": "Feature",
  "properties": {
    "iso:country":"GB",
    "wof:name":"HA8 8UU",
    "wof:placetype":"postalcode"
},
  "geometry": {"coordinates":[-0.27071435963398,51.62532409085904],"type":"Point"}
}