{
  "type": "Feature",
  "properties": {
    "iso:country":"GB",
    "wof:name":"E1 4LR",
    "wof:placetype":"postalcode"
},
  "geometry": {"coordinates":[-0.04454469822545,51.52094131766014],"type":"Point"}
}