{
  "type": "Feature",
  "properties": {
    "iso:country":"GB",
    "wof:name":"DY8 1ET",
    "wof:placetype":"postalcode"
},
  "geometry": {"coordinates":[-2.14464946289567,52.45743450924458],"type":"Point"}
}