{
  "type": "Feature",
  "properties": {
    "iso:country":"GB",
    "wof:name":"WD25 9LD",
    "wof:placetype":"postalcode"
},
  "geometry": {"coordinates":[-0.38947697716349,51.68876156968312],"type":"Point"}
}