{
  "type": "Feature",
  "properties": {
    "iso:country": "GB",
    "wof:name": "EH41 4RU",
    "wof:placetype": "postalcode"
  },
  "geometry": {"coordinates":[-2.789111,55.95165],"type":"Point"}
}
