{
  "type": "Feature",
  "properties": {
    "iso:country":"GB",
    "wof:name":"EH41 4RU",
    "wof:placetype":"postalcode"
},
  "geometry": {"coordinates":[-2.78911134672447,55.95164964704109],"type":"Point"}
}