{
  "type": "Feature",
  "properties": {
    "date:inception_lower": "1986-09-01",
    "date:inception_upper": "1986-09-01",
    "iso:country": "GB",
    "wof:name": "EH41 4RU",
    "wof:placetype": "postalcode"
  },
  "geometry": {"coordinates":[-2.789111,55.95165],"type":"Point"}
}
