{
  "type": "Feature",
  "properties": {
    "date:inception_lower": "1980-01-01",
    "date:inception_upper": "1980-01-01",
    "iso:country": "GB",
    "wof:name": "TN31 6UB",
    "wof:placetype": "postalcode"
  },
  "geometry": {"coordinates":[0.639651,51.001851],"type":"Point"}
}
