{
  "type": "Feature",
  "properties": {
    "iso:country": "GB",
    "wof:name": "BN1 3YH",
    "wof:placetype": "postalcode"
  },
  "geometry": {"coordinates":[-0.142972,50.825747],"type":"Point"}
}
