{
  "type": "Feature",
  "properties": {
    "date:inception_lower":"1980-01-01",
    "date:inception_upper":"1980-01-31",
    "iso:country":"GB",
    "wof:name":"BN1 3YH",
    "wof:placetype":"postalcode"
},
  "geometry": {"coordinates":[-0.142972,50.825747],"type":"Point"}
}