{
  "type": "Feature",
  "properties": {
    "iso:country":"GB",
    "wof:name":"BN1 3YH",
    "wof:placetype":"postalcode"
},
  "geometry": {"coordinates":[-0.14297156742288,50.82574737293052],"type":"Point"}
}