{
  "type": "Feature",
  "properties": {
    "date:inception_lower": "2020-12-01",
    "date:inception_upper": "2020-12-01",
    "iso:country": "GB",
    "wof:name": "SE12 9AY",
    "wof:placetype": "postalcode"
  },
  "geometry": {"coordinates":[0.030205,51.445644],"type":"Point"}
}
