{
  "type": "Feature",
  "properties": {
    "iso:country":"GB",
    "wof:name":"EN5 3JH",
    "wof:placetype":"postalcode"
},
  "geometry": {"coordinates":[-0.25393173968911,51.64136958214134],"type":"Point"}
}