{
  "type": "Feature",
  "properties": {
    "iso:country":"GB",
    "wof:name":"NG20 8SP",
    "wof:placetype":"postalcode"
},
  "geometry": {"coordinates":[-1.2031518111499,53.2038323874253],"type":"Point"}
}