{
  "type": "Feature",
  "properties": {
    "iso:country":"GB",
    "wof:name":"BN17 7BD",
    "wof:placetype":"postalcode"
},
  "geometry": {"coordinates":[-0.55844074670231,50.82492934960786],"type":"Point"}
}