{
  "type": "Feature",
  "properties": {
    "iso:country": "GB",
    "wof:name": "BN17 7BD",
    "wof:placetype": "postalcode"
  },
  "geometry": {"coordinates":[-0.558251,50.824791],"type":"Point"}
}
