{
  "type": "Feature",
  "properties": {
    "iso:country":"GB",
    "wof:name":"S61 2EZ",
    "wof:placetype":"postalcode"
},
  "geometry": {"coordinates":[-1.4102818163458,53.42920014473192],"type":"Point"}
}