{
  "type": "Feature",
  "properties": {
    "iso:country": "GB",
    "wof:name": "S61 2EZ",
    "wof:placetype": "postalcode"
  },
  "geometry": {"coordinates":[-1.410282,53.4292],"type":"Point"}
}
