{
  "type": "Feature",
  "properties": {
    "date:inception_lower": "1984-10-01",
    "date:inception_upper": "1984-10-01",
    "iso:country": "GB",
    "wof:name": "CV37 0TQ",
    "wof:placetype": "postalcode"
  },
  "geometry": {"coordinates":[-1.720799,52.202807],"type":"Point"}
}
