{
  "type": "Feature",
  "properties": {
    "iso:country":"GB",
    "wof:name":"CV37 0TQ",
    "wof:placetype":"postalcode"
},
  "geometry": {"coordinates":[-1.7207992868174,52.20280729437803],"type":"Point"}
}