{
  "type": "Feature",
  "properties": {
    "iso:country":"GB",
    "wof:name":"BA2 3JZ",
    "wof:placetype":"postalcode"
},
  "geometry": {"coordinates":[-2.37086882956402,51.37592407236372],"type":"Point"}
}