{
  "type": "Feature",
  "properties": {
    "iso:country":"GB",
    "wof:name":"EH3 9NH",
    "wof:placetype":"postalcode"
},
  "geometry": {"coordinates":[-3.20717355929447,55.94107414467291],"type":"Point"}
}