{
  "type": "Feature",
  "properties": {
    "iso:country":"GB",
    "wof:name":"BB9 6AH",
    "wof:placetype":"postalcode"
},
  "geometry": {"coordinates":[-2.20936101075895,53.85796762437186],"type":"Point"}
}