{
  "type": "Feature",
  "properties": {
    "iso:country":"GB",
    "wof:name":"TF9 1NJ",
    "wof:placetype":"postalcode"
},
  "geometry": {"coordinates":[-2.50783887814905,52.89826921942849],"type":"Point"}
}