{
  "type": "Feature",
  "properties": {
    "iso:country":"GB",
    "wof:name":"SW19 1HG",
    "wof:placetype":"postalcode"
},
  "geometry": {"coordinates":[-0.18710876243776,51.41693987637869],"type":"Point"}
}