{
  "type": "Feature",
  "properties": {
    "iso:country":"GB",
    "wof:name":"DA16 3JL",
    "wof:placetype":"postalcode"
},
  "geometry": {"coordinates":[0.10892351268028,51.46743667496058],"type":"Point"}
}