{
  "type": "Feature",
  "properties": {
    "date:inception_lower":"2008-03-01",
    "date:inception_upper":"2008-03-31",
    "iso:country":"GB",
    "wof:name":"DA16 3JL",
    "wof:placetype":"postalcode"
},
  "geometry": {"coordinates":[0.108924,51.467437],"type":"Point"}
}