{
  "type": "Feature",
  "properties": {
    "iso:country":"GB",
    "wof:name":"SA62 3HZ",
    "wof:placetype":"postalcode"
},
  "geometry": {"coordinates":[-5.09343015684503,51.78326017630608],"type":"Point"}
}