{
  "type": "Feature",
  "properties": {
    "date:inception_lower": "2001-06-01",
    "date:inception_upper": "2001-06-01",
    "iso:country": "GB",
    "wof:name": "LU7 2LN",
    "wof:placetype": "postalcode"
  },
  "geometry": {"coordinates":[-0.683254,51.914504],"type":"Point"}
}
