{
  "type": "Feature",
  "properties": {
    "iso:country":"GB",
    "wof:name":"HA5 2EW",
    "wof:placetype":"postalcode"
},
  "geometry": {"coordinates":[-0.40563405966209,51.58499791939465],"type":"Point"}
}