{
  "type": "Feature",
  "properties": {
    "date:inception_lower": "1991-01-01",
    "date:inception_upper": "1991-01-01",
    "iso:country": "GB",
    "wof:name": "MK11 3JB",
    "wof:placetype": "postalcode"
  },
  "geometry": {"coordinates":[-0.819386,52.041691],"type":"Point"}
}
