{
  "type": "Feature",
  "properties": {
    "date:inception_lower": "1993-08-01",
    "date:inception_upper": "1993-08-01",
    "iso:country": "GB",
    "wof:name": "NN14 6AQ",
    "wof:placetype": "postalcode"
  },
  "geometry": {"coordinates":[-0.805916,52.418386],"type":"Point"}
}
