{
  "type": "Feature",
  "properties": {
    "iso:country":"GB",
    "wof:name":"NN14 6AQ",
    "wof:placetype":"postalcode"
},
  "geometry": {"coordinates":[-0.80591597491752,52.41838643785444],"type":"Point"}
}