{
  "type": "Feature",
  "properties": {
    "iso:country":"GB",
    "wof:name":"DY14 9SN",
    "wof:placetype":"postalcode"
},
  "geometry": {"coordinates":[-2.36910970176427,52.33451892005897],"type":"Point"}
}