{
  "type": "Feature",
  "properties": {
    "iso:country":"GB",
    "wof:name":"W3 7AN",
    "wof:placetype":"postalcode"
},
  "geometry": {"coordinates":[-0.25849481688793,51.51461016093564],"type":"Point"}
}