{
  "type": "Feature",
  "properties": {
    "iso:country":"GB",
    "wof:name":"HA3 7DB",
    "wof:placetype":"postalcode"
},
  "geometry": {"coordinates":[-0.33143941182035,51.6043608684838],"type":"Point"}
}