{
  "type": "Feature",
  "properties": {
    "iso:country": "GB",
    "wof:name": "WF7 5FA",
    "wof:placetype": "postalcode"
  },
  "geometry": {"coordinates":[-1.361693,53.670615],"type":"Point"}
}
