{
  "type": "Feature",
  "properties": {
    "iso:country":"GB",
    "wof:name":"NE24 4LY",
    "wof:placetype":"postalcode"
},
  "geometry": {"coordinates":[-1.54959704965008,55.12477972979367],"type":"Point"}
}