{
  "type": "Feature",
  "properties": {
    "date:inception_lower":"1980-01-01",
    "date:inception_upper":"1980-01-31",
    "iso:country":"GB",
    "wof:name":"DY8 4LB",
    "wof:placetype":"postalcode"
},
  "geometry": {"coordinates":[-2.143156,52.461631],"type":"Point"}
}