{
  "type": "Feature",
  "properties": {
    "iso:country": "GB",
    "wof:name": "PE6 8LX",
    "wof:placetype": "postalcode"
  },
  "geometry": {"coordinates":[-0.320797,52.681732],"type":"Point"}
}
