{
  "type": "Feature",
  "properties": {
    "iso:country":"GB",
    "wof:name":"TR1 2RU",
    "wof:placetype":"postalcode"
},
  "geometry": {"coordinates":[-5.05369475602179,50.26291771325533],"type":"Point"}
}