{
  "type": "Feature",
  "properties": {
    "iso:country":"GB",
    "wof:name":"PO33 3HR",
    "wof:placetype":"postalcode"
},
  "geometry": {"coordinates":[-1.17489940384001,50.7178767954713],"type":"Point"}
}