{
  "type": "Feature",
  "properties": {
    "iso:country":"GB",
    "wof:name":"WS11 0BD",
    "wof:placetype":"postalcode"
},
  "geometry": {"coordinates":[-2.03342650527325,52.67566558913082],"type":"Point"}
}