{
  "type": "Feature",
  "properties": {
    "iso:country":"GB",
    "wof:name":"LU3 1TU",
    "wof:placetype":"postalcode"
},
  "geometry": {"coordinates":[-0.43907399988388,51.90076509152077],"type":"Point"}
}