{
  "type": "Feature",
  "properties": {
    "date:inception_lower": "2020-05-01",
    "date:inception_upper": "2020-05-01",
    "iso:country": "GB",
    "wof:name": "LS18 4GX",
    "wof:placetype": "postalcode"
  },
  "geometry": {"coordinates":[-1.640524,53.829829],"type":"Point"}
}
