{
  "type": "Feature",
  "properties": {
    "iso:country": "GB",
    "wof:name": "NG25 0QA",
    "wof:placetype": "postalcode"
  },
  "geometry": {"coordinates":[-0.931657,53.080324],"type":"Point"}
}
