{
  "type": "Feature",
  "properties": {
    "iso:country":"GB",
    "wof:name":"NG25 0QA",
    "wof:placetype":"postalcode"
},
  "geometry": {"coordinates":[-0.93165701523327,53.08032441097055],"type":"Point"}
}