{
  "type": "Feature",
  "properties": {
    "iso:country": "GB",
    "wof:name": "RH1 5BW",
    "wof:placetype": "postalcode"
  },
  "geometry": {"coordinates":[-0.16039,51.215625],"type":"Point"}
}
