{
  "type": "Feature",
  "properties": {
    "iso:country":"GB",
    "wof:name":"WV11 2JT",
    "wof:placetype":"postalcode"
},
  "geometry": {"coordinates":[-2.05977927534087,52.61977517757478],"type":"Point"}
}