{
  "type": "Feature",
  "properties": {
    "iso:country": "GB",
    "wof:name": "MK46 4BT",
    "wof:placetype": "postalcode"
  },
  "geometry": {"coordinates":[-0.701379,52.158753],"type":"Point"}
}
