{
  "type": "Feature",
  "properties": {
    "iso:country":"GB",
    "wof:name":"IP11 7RS",
    "wof:placetype":"postalcode"
},
  "geometry": {"coordinates":[1.34068676310848,51.96150149793591],"type":"Point"}
}