{
  "type": "Feature",
  "properties": {
    "iso:country":"GB",
    "wof:name":"GU15 3DB",
    "wof:placetype":"postalcode"
},
  "geometry": {"coordinates":[-0.76726648804772,51.33107591886039],"type":"Point"}
}