{
  "type": "Feature",
  "properties": {
    "iso:country":"GB",
    "wof:name":"RH5 4AL",
    "wof:placetype":"postalcode"
},
  "geometry": {"coordinates":[-0.31948792093869,51.23324302861639],"type":"Point"}
}