{
  "type": "Feature",
  "properties": {
    "iso:country": "GB",
    "wof:name": "SA73 1EE",
    "wof:placetype": "postalcode"
  },
  "geometry": {"coordinates":[-4.970634,51.705107],"type":"Point"}
}
