{
  "type": "Feature",
  "properties": {
    "date:inception_lower":"1980-01-01",
    "date:inception_upper":"1980-01-31",
    "iso:country":"GB",
    "wof:name":"SA73 1EE",
    "wof:placetype":"postalcode"
},
  "geometry": {"coordinates":[-4.970634,51.705107],"type":"Point"}
}