{
  "type": "Feature",
  "properties": {
    "iso:country":"GB",
    "wof:name":"EN3 7XF",
    "wof:placetype":"postalcode"
},
  "geometry": {"coordinates":[-0.02192851144336,51.65785124113],"type":"Point"}
}