{
  "type": "Feature",
  "properties": {
    "date:inception_lower":"1991-09-01",
    "date:inception_upper":"1991-09-30",
    "iso:country":"GB",
    "wof:name":"EN3 7XF",
    "wof:placetype":"postalcode"
},
  "geometry": {"coordinates":[-0.021852,51.657958],"type":"Point"}
}