{
  "type": "Feature",
  "properties": {
    "iso:country":"GB",
    "wof:name":"SE8 5AJ",
    "wof:placetype":"postalcode"
},
  "geometry": {"coordinates":[-0.04215316497721,51.48830312357805],"type":"Point"}
}