{
  "type": "Feature",
  "properties": {
    "iso:country":"GB",
    "wof:name":"LL13 0UY",
    "wof:placetype":"postalcode"
},
  "geometry": {"coordinates":[-2.99225913776256,53.019940119924],"type":"Point"}
}