{
  "type": "Feature",
  "properties": {
    "iso:country":"GB",
    "wof:name":"DD6 9HY",
    "wof:placetype":"postalcode"
},
  "geometry": {"coordinates":[-2.88307307829602,56.44775415048726],"type":"Point"}
}