{
  "type": "Feature",
  "properties": {
    "date:inception_lower":"1980-01-01",
    "date:inception_upper":"1980-01-31",
    "iso:country":"GB",
    "wof:name":"DD6 9HY",
    "wof:placetype":"postalcode"
},
  "geometry": {"coordinates":[-2.883221,56.447699],"type":"Point"}
}