{
  "type": "Feature",
  "properties": {
    "iso:country":"GB",
    "wof:name":"RM3 7DU",
    "wof:placetype":"postalcode"
},
  "geometry": {"coordinates":[0.20731414305566,51.60349570175904],"type":"Point"}
}