{
  "type": "Feature",
  "properties": {
    "iso:country":"GB",
    "wof:name":"CH29 9EQ",
    "wof:placetype":"postalcode"
},
  "geometry": {"coordinates":[-3.17943083514908,53.39015783880384],"type":"Point"}
}