{
  "type": "Feature",
  "properties": {
    "iso:country":"GB",
    "wof:name":"AL8 7AW",
    "wof:placetype":"postalcode"
},
  "geometry": {"coordinates":[-0.19905408769359,51.8130100061891],"type":"Point"}
}