{
  "type": "Feature",
  "properties": {
    "iso:country":"GB",
    "wof:name":"CB4 1HJ",
    "wof:placetype":"postalcode"
},
  "geometry": {"coordinates":[0.13003554946784,52.2120667822289],"type":"Point"}
}