{
  "type": "Feature",
  "properties": {
    "iso:country":"GB",
    "wof:name":"B61 9EF",
    "wof:placetype":"postalcode"
},
  "geometry": {"coordinates":[-2.1259013163721,52.35465446571979],"type":"Point"}
}