{
  "type": "Feature",
  "properties": {
    "iso:country":"GB",
    "wof:name":"CR2 0ED",
    "wof:placetype":"postalcode"
},
  "geometry": {"coordinates":[-0.08336246904854,51.34909345747838],"type":"Point"}
}