{
  "type": "Feature",
  "properties": {
    "iso:country": "GB",
    "wof:name": "WD18 0DB",
    "wof:placetype": "postalcode"
  },
  "geometry": {"coordinates":[-0.394399,51.651863],"type":"Point"}
}
