{
  "type": "Feature",
  "properties": {
    "iso:country":"GB",
    "wof:name":"WD18 0DB",
    "wof:placetype":"postalcode"
},
  "geometry": {"coordinates":[-0.39439896721373,51.6518627832553],"type":"Point"}
}