{
  "type": "Feature",
  "properties": {
    "date:inception_lower": "1980-01-01",
    "date:inception_upper": "1980-01-01",
    "iso:country": "GB",
    "wof:name": "B8 2QE",
    "wof:placetype": "postalcode"
  },
  "geometry": {"coordinates":[-1.837261,52.49837],"type":"Point"}
}
