{
  "type": "Feature",
  "properties": {
    "iso:country": "GB",
    "wof:name": "PO19 8BJ",
    "wof:placetype": "postalcode"
  },
  "geometry": {"coordinates":[-0.770648,50.829012],"type":"Point"}
}
