{
  "type": "Feature",
  "properties": {
    "iso:country":"GB",
    "wof:name":"PO19 8BJ",
    "wof:placetype":"postalcode"
},
  "geometry": {"coordinates":[-0.77066712364612,50.82902179986579],"type":"Point"}
}