{
  "type": "Feature",
  "properties": {
    "iso:country":"GB",
    "wof:name":"LD3 9NB",
    "wof:placetype":"postalcode"
},
  "geometry": {"coordinates":[-3.54853129180685,52.00957575126786],"type":"Point"}
}