{
  "type": "Feature",
  "properties": {
    "iso:country":"GB",
    "wof:name":"PR4 6TA",
    "wof:placetype":"postalcode"
},
  "geometry": {"coordinates":[-2.85166634075131,53.70710784202672],"type":"Point"}
}