{
  "type": "Feature",
  "properties": {
    "iso:country":"GB",
    "wof:name":"N11 1NY",
    "wof:placetype":"postalcode"
},
  "geometry": {"coordinates":[-0.14437463249404,51.61746018487845],"type":"Point"}
}