{
  "type": "Feature",
  "properties": {
    "iso:country":"GB",
    "wof:name":"TN1 2EX",
    "wof:placetype":"postalcode"
},
  "geometry": {"coordinates":[0.26789402219893,51.14063815571642],"type":"Point"}
}