{
  "type": "Feature",
  "properties": {
    "iso:country":"GB",
    "wof:name":"W14 0DS",
    "wof:placetype":"postalcode"
},
  "geometry": {"coordinates":[-0.21966017932588,51.50002593593254],"type":"Point"}
}