{
  "type": "Feature",
  "properties": {
    "iso:country": "GB",
    "wof:name": "M11 4WJ",
    "wof:placetype": "postalcode"
  },
  "geometry": {"coordinates":[-2.179106,53.483687],"type":"Point"}
}
