{
  "type": "Feature",
  "properties": {
    "date:inception_lower": "1980-01-01",
    "date:inception_upper": "1980-01-01",
    "iso:country": "GB",
    "wof:name": "DG8 0HW",
    "wof:placetype": "postalcode"
  },
  "geometry": {"coordinates":[-4.60252,54.91007],"type":"Point"}
}
