{
  "type": "Feature",
  "properties": {
    "iso:country": "GB",
    "wof:name": "DG8 0HW",
    "wof:placetype": "postalcode"
  },
  "geometry": {"coordinates":[-4.60252,54.91007],"type":"Point"}
}
