{
  "type": "Feature",
  "properties": {
    "iso:country":"GB",
    "wof:name":"DG8 0HW",
    "wof:placetype":"postalcode"
},
  "geometry": {"coordinates":[-4.60251964961099,54.91007046635964],"type":"Point"}
}