{
  "type": "Feature",
  "properties": {
    "iso:country":"GB",
    "wof:name":"LE18 4PE",
    "wof:placetype":"postalcode"
},
  "geometry": {"coordinates":[-1.13446478054613,52.57902513383748],"type":"Point"}
}