{
  "type": "Feature",
  "properties": {
    "iso:country":"GB",
    "wof:name":"CA7 4AR",
    "wof:placetype":"postalcode"
},
  "geometry": {"coordinates":[-3.38668588414504,54.86842584838108],"type":"Point"}
}