{
  "type": "Feature",
  "properties": {
    "date:inception_lower": "1980-01-01",
    "date:inception_upper": "1980-01-01",
    "iso:country": "GB",
    "wof:name": "PH10 6HQ",
    "wof:placetype": "postalcode"
  },
  "geometry": {"coordinates":[-3.345223,56.593994],"type":"Point"}
}
