{
  "type": "Feature",
  "properties": {
    "iso:country": "GB",
    "wof:name": "PH10 6HQ",
    "wof:placetype": "postalcode"
  },
  "geometry": {"coordinates":[-3.345223,56.593994],"type":"Point"}
}
