{
  "type": "Feature",
  "properties": {
    "iso:country":"GB",
    "wof:name":"DN4 5FA",
    "wof:placetype":"postalcode"
},
  "geometry": {"coordinates":[-1.10230923344044,53.50612381815221],"type":"Point"}
}