{
  "type": "Feature",
  "properties": {
    "date:inception_lower":"2015-08-01",
    "date:inception_upper":"2015-08-31",
    "iso:country":"GB",
    "wof:name":"DN4 5FA",
    "wof:placetype":"postalcode"
},
  "geometry": {"coordinates":[-1.102129,53.506233],"type":"Point"}
}