{
  "type": "Feature",
  "properties": {
    "iso:country": "GB",
    "wof:name": "DN4 5FA",
    "wof:placetype": "postalcode"
  },
  "geometry": {"coordinates":[-1.102129,53.506233],"type":"Point"}
}
