{
  "type": "Feature",
  "properties": {
    "date:inception_lower": "2023-09-01",
    "date:inception_upper": "2023-09-01",
    "iso:country": "GB",
    "wof:name": "HR4 9FH",
    "wof:placetype": "postalcode"
  },
  "geometry": {"coordinates":[-2.727124,52.079692],"type":"Point"}
}
