{
  "type": "Feature",
  "properties": {
    "date:inception_lower": "2022-09-01",
    "date:inception_upper": "2022-09-01",
    "iso:country": "GB",
    "wof:name": "DN2 4SS",
    "wof:placetype": "postalcode"
  },
  "geometry": {"coordinates":[-1.099349,53.544917],"type":"Point"}
}
