{
  "type": "Feature",
  "properties": {
    "iso:country":"GB",
    "wof:name":"OX14 4DR",
    "wof:placetype":"postalcode"
},
  "geometry": {"coordinates":[-1.30472096441443,51.6173502323791],"type":"Point"}
}