{
  "type": "Feature",
  "properties": {
    "iso:country": "GB",
    "wof:name": "SS2 6HS",
    "wof:placetype": "postalcode"
  },
  "geometry": {"coordinates":[0.704339,51.547702],"type":"Point"}
}
