{
  "type": "Feature",
  "properties": {
    "iso:country":"GB",
    "wof:name":"SS2 6HS",
    "wof:placetype":"postalcode"
},
  "geometry": {"coordinates":[0.7043392068111,51.54770212070888],"type":"Point"}
}