{
  "type": "Feature",
  "properties": {
    "iso:country":"GB",
    "wof:name":"S75 4HQ",
    "wof:placetype":"postalcode"
},
  "geometry": {"coordinates":[-1.57213807457883,53.56793428480314],"type":"Point"}
}