{
  "type": "Feature",
  "properties": {
    "date:inception_lower": "1980-01-01",
    "date:inception_upper": "1980-01-01",
    "iso:country": "GB",
    "wof:name": "S75 4HQ",
    "wof:placetype": "postalcode"
  },
  "geometry": {"coordinates":[-1.572138,53.567934],"type":"Point"}
}
