{
  "type": "Feature",
  "properties": {
    "iso:country":"GB",
    "wof:name":"BA2 0AF",
    "wof:placetype":"postalcode"
},
  "geometry": {"coordinates":[-2.48532473370845,51.34391764720075],"type":"Point"}
}