{
  "type": "Feature",
  "properties": {
    "iso:country":"GB",
    "wof:name":"PR7 5DU",
    "wof:placetype":"postalcode"
},
  "geometry": {"coordinates":[-2.67402261488259,53.6112640444906],"type":"Point"}
}