{
  "type": "Feature",
  "properties": {
    "iso:country":"GB",
    "wof:name":"BB6 7QF",
    "wof:placetype":"postalcode"
},
  "geometry": {"coordinates":[-2.41236792519667,53.78777544576903],"type":"Point"}
}