{
  "type": "Feature",
  "properties": {
    "iso:country": "GB",
    "wof:name": "IP3 8UW",
    "wof:placetype": "postalcode"
  },
  "geometry": {"coordinates":[1.214201,52.038624],"type":"Point"}
}
