{
  "type": "Feature",
  "properties": {
    "iso:country":"GB",
    "wof:name":"IP3 8UW",
    "wof:placetype":"postalcode"
},
  "geometry": {"coordinates":[1.21420135906967,52.03862413090628],"type":"Point"}
}