{
  "type": "Feature",
  "properties": {
    "iso:country": "GB",
    "wof:name": "BS2 8XT",
    "wof:placetype": "postalcode"
  },
  "geometry": {"coordinates":[-2.58277,51.465041],"type":"Point"}
}
