{
  "type": "Feature",
  "properties": {
    "iso:country":"GB",
    "wof:name":"BS2 8XT",
    "wof:placetype":"postalcode"
},
  "geometry": {"coordinates":[-2.58276971554797,51.46504118215544],"type":"Point"}
}