{
  "type": "Feature",
  "properties": {
    "iso:country":"GB",
    "wof:name":"PR25 1TB",
    "wof:placetype":"postalcode"
},
  "geometry": {"coordinates":[-2.71659492095048,53.68757072254107],"type":"Point"}
}