{
  "type": "Feature",
  "properties": {
    "iso:country": "GB",
    "wof:name": "BH25 7ED",
    "wof:placetype": "postalcode"
  },
  "geometry": {"coordinates":[-1.664259,50.736445],"type":"Point"}
}
