{
  "type": "Feature",
  "properties": {
    "date:inception_lower": "2024-08-01",
    "date:inception_upper": "2024-08-01",
    "iso:country": "GB",
    "wof:name": "CM14 4LZ",
    "wof:placetype": "postalcode"
  },
  "geometry": {"coordinates":[0.305236,51.621383],"type":"Point"}
}
