{
  "type": "Feature",
  "properties": {
    "iso:country":"GB",
    "wof:name":"WN2 5TU",
    "wof:placetype":"postalcode"
},
  "geometry": {"coordinates":[-2.57009420214083,53.51378549501449],"type":"Point"}
}