{
  "type": "Feature",
  "properties": {
    "iso:country": "GB",
    "wof:name": "WN2 5TU",
    "wof:placetype": "postalcode"
  },
  "geometry": {"coordinates":[-2.570064,53.513786],"type":"Point"}
}
