{
  "type": "Feature",
  "properties": {
    "iso:country":"GB",
    "wof:name":"IP17 3JN",
    "wof:placetype":"postalcode"
},
  "geometry": {"coordinates":[1.49432891850865,52.27272203644544],"type":"Point"}
}