{
  "type": "Feature",
  "properties": {
    "iso:country": "GB",
    "wof:name": "IP17 3JN",
    "wof:placetype": "postalcode"
  },
  "geometry": {"coordinates":[1.495016,52.27213],"type":"Point"}
}
