{
  "type": "Feature",
  "properties": {
    "iso:country":"GB",
    "wof:name":"ME2 4PF",
    "wof:placetype":"postalcode"
},
  "geometry": {"coordinates":[0.50321711021647,51.40858749164279],"type":"Point"}
}