{
  "type": "Feature",
  "properties": {
    "date:inception_lower": "2015-01-01",
    "date:inception_upper": "2015-01-01",
    "iso:country": "GB",
    "wof:name": "S11 0FU",
    "wof:placetype": "postalcode"
  },
  "geometry": {"coordinates":[-1.508338,53.363523],"type":"Point"}
}
