{
  "type": "Feature",
  "properties": {
    "date:inception_lower": "1981-06-01",
    "date:inception_upper": "1981-06-01",
    "iso:country": "GB",
    "wof:name": "DE13 0RS",
    "wof:placetype": "postalcode"
  },
  "geometry": {"coordinates":[-1.651929,52.816351],"type":"Point"}
}
