{
  "type": "Feature",
  "properties": {
    "iso:country": "GB",
    "wof:name": "DE13 0RS",
    "wof:placetype": "postalcode"
  },
  "geometry": {"coordinates":[-1.651929,52.816351],"type":"Point"}
}
