{
  "type": "Feature",
  "properties": {
    "iso:country":"GB",
    "wof:name":"S45 9QS",
    "wof:placetype":"postalcode"
},
  "geometry": {"coordinates":[-1.42816126637837,53.17187377047945],"type":"Point"}
}