{
  "type": "Feature",
  "properties": {
    "date:inception_lower":"2015-04-01",
    "date:inception_upper":"2015-04-30",
    "iso:country":"GB",
    "wof:name":"UB6 0FB",
    "wof:placetype":"postalcode"
},
  "geometry": {"coordinates":[-0.333018,51.555908],"type":"Point"}
}