{
  "type": "Feature",
  "properties": {
    "iso:country":"GB",
    "wof:name":"UB6 0FB",
    "wof:placetype":"postalcode"
},
  "geometry": {"coordinates":[-0.3329236979166,51.55593196680036],"type":"Point"}
}