{
  "type": "Feature",
  "properties": {
    "date:inception_lower": "2007-11-01",
    "date:inception_upper": "2007-11-01",
    "iso:country": "GB",
    "wof:name": "DL16 7GN",
    "wof:placetype": "postalcode"
  },
  "geometry": {"coordinates":[-1.612271,54.70128],"type":"Point"}
}
