{
  "type": "Feature",
  "properties": {
    "iso:country":"GB",
    "wof:name":"DL16 7GN",
    "wof:placetype":"postalcode"
},
  "geometry": {"coordinates":[-1.61227097407152,54.70127957128089],"type":"Point"}
}