{
  "type": "Feature",
  "properties": {
    "iso:country":"GB",
    "wof:name":"B68 9AJ",
    "wof:placetype":"postalcode"
},
  "geometry": {"coordinates":[-1.99467053414535,52.47763374258169],"type":"Point"}
}