{
  "type": "Feature",
  "properties": {
    "iso:country":"GB",
    "wof:name":"SA67 7ED",
    "wof:placetype":"postalcode"
},
  "geometry": {"coordinates":[-4.74281691739103,51.79897582541305],"type":"Point"}
}