{
  "type": "Feature",
  "properties": {
    "date:inception_lower":"1992-01-01",
    "date:inception_upper":"1992-01-31",
    "iso:country":"GB",
    "wof:name":"SA67 7ED",
    "wof:placetype":"postalcode"
},
  "geometry": {"coordinates":[-4.742817,51.798976],"type":"Point"}
}