{
  "type": "Feature",
  "properties": {
    "iso:country":"GB",
    "wof:name":"B72 1BS",
    "wof:placetype":"postalcode"
},
  "geometry": {"coordinates":[-1.81526736957895,52.53383892910129],"type":"Point"}
}