{
  "type": "Feature",
  "properties": {
    "date:inception_lower":"1980-01-01",
    "date:inception_upper":"1980-01-31",
    "iso:country":"GB",
    "wof:name":"B72 1BS",
    "wof:placetype":"postalcode"
},
  "geometry": {"coordinates":[-1.815267,52.533839],"type":"Point"}
}