{
  "type": "Feature",
  "properties": {
    "date:inception_lower": "2002-07-01",
    "date:inception_upper": "2002-07-01",
    "iso:country": "GB",
    "wof:name": "BN9 0TP",
    "wof:placetype": "postalcode"
  },
  "geometry": {"coordinates":[0.054218,50.81159],"type":"Point"}
}
