{
  "type": "Feature",
  "properties": {
    "iso:country":"GB",
    "wof:name":"BN9 0TP",
    "wof:placetype":"postalcode"
},
  "geometry": {"coordinates":[0.05418966281687,50.81159587759539],"type":"Point"}
}