{
  "type": "Feature",
  "properties": {
    "iso:country": "GB",
    "wof:name": "BN9 0TP",
    "wof:placetype": "postalcode"
  },
  "geometry": {"coordinates":[0.053176,50.81115],"type":"Point"}
}
