{
  "type": "Feature",
  "properties": {
    "iso:country": "GB",
    "wof:name": "BN9 0TP",
    "wof:placetype": "postalcode"
  },
  "geometry": {"coordinates":[0.054218,50.81159],"type":"Point"}
}
