{
  "type": "Feature",
  "properties": {
    "iso:country": "GB",
    "wof:name": "ME4 6UG",
    "wof:placetype": "postalcode"
  },
  "geometry": {"coordinates":[0.514896,51.377175],"type":"Point"}
}
