{
  "type": "Feature",
  "properties": {
    "iso:country":"GB",
    "wof:name":"ME4 6UG",
    "wof:placetype":"postalcode"
},
  "geometry": {"coordinates":[0.51489595331535,51.37717474172388],"type":"Point"}
}