{
  "type": "Feature",
  "properties": {
    "iso:country": "GB",
    "wof:name": "IG3 9BY",
    "wof:placetype": "postalcode"
  },
  "geometry": {"coordinates":[0.104621,51.554152],"type":"Point"}
}
