{
  "type": "Feature",
  "properties": {
    "iso:country":"GB",
    "wof:name":"IG3 9BY",
    "wof:placetype":"postalcode"
},
  "geometry": {"coordinates":[0.10507500250303,51.55425048708416],"type":"Point"}
}