{
  "type": "Feature",
  "properties": {
    "date:inception_lower": "1993-01-01",
    "date:inception_upper": "1993-01-01",
    "iso:country": "GB",
    "wof:name": "NW10 4RL",
    "wof:placetype": "postalcode"
  },
  "geometry": {"coordinates":[-0.243152,51.534299],"type":"Point"}
}
