{
  "type": "Feature",
  "properties": {
    "iso:country":"GB",
    "wof:name":"NW10 4RL",
    "wof:placetype":"postalcode"
},
  "geometry": {"coordinates":[-0.24328442499904,51.53422951882609],"type":"Point"}
}