{
  "type": "Feature",
  "properties": {
    "date:inception_lower": "1980-01-01",
    "date:inception_upper": "1980-01-01",
    "iso:country": "GB",
    "wof:name": "DL11 6EZ",
    "wof:placetype": "postalcode"
  },
  "geometry": {"coordinates":[-1.984224,54.417143],"type":"Point"}
}
