{
  "type": "Feature",
  "properties": {
    "iso:country": "GB",
    "wof:name": "DL11 6EZ",
    "wof:placetype": "postalcode"
  },
  "geometry": {"coordinates":[-1.984177,54.417161],"type":"Point"}
}
