{
  "type": "Feature",
  "properties": {
    "iso:country":"GB",
    "wof:name":"DE24 0UH",
    "wof:placetype":"postalcode"
},
  "geometry": {"coordinates":[-1.41729863126184,52.88643949600396],"type":"Point"}
}