{
  "type": "Feature",
  "properties": {
    "iso:country": "GB",
    "wof:name": "DE24 0UH",
    "wof:placetype": "postalcode"
  },
  "geometry": {"coordinates":[-1.417299,52.886439],"type":"Point"}
}
