{
  "type": "Feature",
  "properties": {
    "date:inception_lower": "2000-12-01",
    "date:inception_upper": "2000-12-01",
    "iso:country": "GB",
    "wof:name": "W10 4JW",
    "wof:placetype": "postalcode"
  },
  "geometry": {"coordinates":[-0.209247,51.531179],"type":"Point"}
}
