{
  "type": "Feature",
  "properties": {
    "iso:country":"GB",
    "wof:name":"W10 4JW",
    "wof:placetype":"postalcode"
},
  "geometry": {"coordinates":[-0.20924668254869,51.53117902140782],"type":"Point"}
}