{
  "type": "Feature",
  "properties": {
    "iso:country": "GB",
    "wof:name": "NR7 8BX",
    "wof:placetype": "postalcode"
  },
  "geometry": {"coordinates":[1.325947,52.656385],"type":"Point"}
}
