{
  "type": "Feature",
  "properties": {
    "iso:country":"GB",
    "wof:name":"NR7 8BX",
    "wof:placetype":"postalcode"
},
  "geometry": {"coordinates":[1.32594726054684,52.65638506734672],"type":"Point"}
}