{
  "type": "Feature",
  "properties": {
    "iso:country": "GB",
    "wof:name": "ME13 7QH",
    "wof:placetype": "postalcode"
  },
  "geometry": {"coordinates":[0.877375,51.31687],"type":"Point"}
}
