{
  "type": "Feature",
  "properties": {
    "iso:country":"GB",
    "wof:name":"ME13 7QH",
    "wof:placetype":"postalcode"
},
  "geometry": {"coordinates":[0.87737544474514,51.31686979370267],"type":"Point"}
}