{
  "type": "Feature",
  "properties": {
    "date:inception_lower": "2017-07-01",
    "date:inception_upper": "2017-07-01",
    "iso:country": "GB",
    "wof:name": "SL5 0FD",
    "wof:placetype": "postalcode"
  },
  "geometry": {"coordinates":[-0.634946,51.389623],"type":"Point"}
}
