{
  "type": "Feature",
  "properties": {
    "iso:country":"GB",
    "wof:name":"GU19 5LD",
    "wof:placetype":"postalcode"
},
  "geometry": {"coordinates":[-0.68738524336967,51.3597834924683],"type":"Point"}
}