{
  "type": "Feature",
  "properties": {
    "iso:country":"GB",
    "wof:name":"TR13 0RX",
    "wof:placetype":"postalcode"
},
  "geometry": {"coordinates":[-5.300816630704,50.13081119734713],"type":"Point"}
}