{
  "type": "Feature",
  "properties": {
    "iso:country":"GB",
    "wof:name":"M25 2NQ",
    "wof:placetype":"postalcode"
},
  "geometry": {"coordinates":[-2.27434348805026,53.53957563051286],"type":"Point"}
}