{
  "type": "Feature",
  "properties": {
    "iso:country":"GB",
    "wof:name":"SN12 6PP",
    "wof:placetype":"postalcode"
},
  "geometry": {"coordinates":[-2.11208178365039,51.33869284977649],"type":"Point"}
}