{
  "type": "Feature",
  "properties": {
    "iso:country": "GB",
    "wof:name": "CH46 6BZ",
    "wof:placetype": "postalcode"
  },
  "geometry": {"coordinates":[-3.116791,53.400693],"type":"Point"}
}
