{
  "type": "Feature",
  "properties": {
    "iso:country": "GB",
    "wof:name": "HX3 0LE",
    "wof:placetype": "postalcode"
  },
  "geometry": {"coordinates":[-1.860504,53.705984],"type":"Point"}
}
