{
  "type": "Feature",
  "properties": {
    "iso:country":"GB",
    "wof:name":"TD1 2NR",
    "wof:placetype":"postalcode"
},
  "geometry": {"coordinates":[-2.76795617526652,55.63317433441065],"type":"Point"}
}