{
  "type": "Feature",
  "properties": {
    "date:inception_lower":"1980-01-01",
    "date:inception_upper":"1980-01-31",
    "iso:country":"GB",
    "wof:name":"CT1 1SA",
    "wof:placetype":"postalcode"
},
  "geometry": {"coordinates":[1.105616,51.275641],"type":"Point"}
}