{
  "type": "Feature",
  "properties": {
    "iso:country": "GB",
    "wof:name": "EX17 6JE",
    "wof:placetype": "postalcode"
  },
  "geometry": {"coordinates":[-3.820434,50.79912],"type":"Point"}
}
