{
  "type": "Feature",
  "properties": {
    "iso:country":"GB",
    "wof:name":"EX17 6JE",
    "wof:placetype":"postalcode"
},
  "geometry": {"coordinates":[-3.82043410215142,50.79911966110565],"type":"Point"}
}