{
  "type": "Feature",
  "properties": {
    "iso:country":"GB",
    "wof:name":"LU4 9AN",
    "wof:placetype":"postalcode"
},
  "geometry": {"coordinates":[-0.46599589920223,51.90623530654087],"type":"Point"}
}