{
  "type": "Feature",
  "properties": {
    "date:inception_lower": "1995-12-01",
    "date:inception_upper": "1995-12-01",
    "iso:country": "GB",
    "wof:name": "NG32 2HQ",
    "wof:placetype": "postalcode"
  },
  "geometry": {"coordinates":[-0.67235,52.98289],"type":"Point"}
}
