{
  "type": "Feature",
  "properties": {
    "iso:country":"GB",
    "wof:name":"ST17 4TR",
    "wof:placetype":"postalcode"
},
  "geometry": {"coordinates":[-2.09490146326297,52.79521144809862],"type":"Point"}
}