{
  "type": "Feature",
  "properties": {
    "date:inception_lower": "1980-01-01",
    "date:inception_upper": "1980-01-01",
    "iso:country": "GB",
    "wof:name": "EX16 7LF",
    "wof:placetype": "postalcode"
  },
  "geometry": {"coordinates":[-3.33021,50.920186],"type":"Point"}
}
