{
  "type": "Feature",
  "properties": {
    "date:inception_lower": "1980-01-01",
    "date:inception_upper": "1980-01-01",
    "iso:country": "GB",
    "wof:name": "YO13 0RZ",
    "wof:placetype": "postalcode"
  },
  "geometry": {"coordinates":[-0.449335,54.305311],"type":"Point"}
}
