{
  "type": "Feature",
  "properties": {
    "iso:country": "GB",
    "wof:name": "NP4 7PG",
    "wof:placetype": "postalcode"
  },
  "geometry": {"coordinates":[-3.063195,51.731014],"type":"Point"}
}
