{
  "type": "Feature",
  "properties": {
    "iso:country":"GB",
    "wof:name":"NP4 7PG",
    "wof:placetype":"postalcode"
},
  "geometry": {"coordinates":[-3.06319459791431,51.73101355585852],"type":"Point"}
}