{
  "type": "Feature",
  "properties": {
    "iso:country":"GB",
    "wof:name":"TN4 9SX",
    "wof:placetype":"postalcode"
},
  "geometry": {"coordinates":[0.24595850431303,51.13906502957626],"type":"Point"}
}