{
  "type": "Feature",
  "properties": {
    "iso:country": "GB",
    "wof:name": "DE6 1SD",
    "wof:placetype": "postalcode"
  },
  "geometry": {"coordinates":[-1.728408,53.010369],"type":"Point"}
}
