{
  "type": "Feature",
  "properties": {
    "iso:country":"GB",
    "wof:name":"NR21 9EX",
    "wof:placetype":"postalcode"
},
  "geometry": {"coordinates":[0.83919717952158,52.83702645493823],"type":"Point"}
}