{
  "type": "Feature",
  "properties": {
    "iso:country": "GB",
    "wof:name": "NR21 9EX",
    "wof:placetype": "postalcode"
  },
  "geometry": {"coordinates":[0.839197,52.837026],"type":"Point"}
}
