{
  "type": "Feature",
  "properties": {
    "iso:country":"GB",
    "wof:name":"DN31 3RP",
    "wof:placetype":"postalcode"
},
  "geometry": {"coordinates":[-0.06975403031174,53.57869330674892],"type":"Point"}
}