{
  "type": "Feature",
  "properties": {
    "date:inception_lower": "2023-02-01",
    "date:inception_upper": "2023-02-01",
    "iso:country": "GB",
    "wof:name": "DN31 3RP",
    "wof:placetype": "postalcode"
  },
  "geometry": {"coordinates":[-0.069643,53.578959],"type":"Point"}
}
