{
  "type": "Feature",
  "properties": {
    "iso:country": "GB",
    "wof:name": "DN31 3RP",
    "wof:placetype": "postalcode"
  },
  "geometry": {"coordinates":[-0.069754,53.578693],"type":"Point"}
}
