{
  "type": "Feature",
  "properties": {
    "date:inception_lower": "1980-01-01",
    "date:inception_upper": "1980-01-01",
    "iso:country": "GB",
    "wof:name": "BN6 8TQ",
    "wof:placetype": "postalcode"
  },
  "geometry": {"coordinates":[-0.108247,50.931941],"type":"Point"}
}
