{
  "type": "Feature",
  "properties": {
    "iso:country":"GB",
    "wof:name":"BN6 8TQ",
    "wof:placetype":"postalcode"
},
  "geometry": {"coordinates":[-0.1082470469724,50.93194135990269],"type":"Point"}
}