{
  "type": "Feature",
  "properties": {
    "iso:country":"GB",
    "wof:name":"GL11 6HN",
    "wof:placetype":"postalcode"
},
  "geometry": {"coordinates":[-2.37848249969994,51.69371165702511],"type":"Point"}
}