{
  "type": "Feature",
  "properties": {
    "iso:country": "GB",
    "wof:name": "IG10 3JS",
    "wof:placetype": "postalcode"
  },
  "geometry": {"coordinates":[0.073105,51.64453],"type":"Point"}
}
