{
  "type": "Feature",
  "properties": {
    "iso:country":"GB",
    "wof:name":"IG10 3JS",
    "wof:placetype":"postalcode"
},
  "geometry": {"coordinates":[0.07310471295278,51.64453046640403],"type":"Point"}
}