{
  "type": "Feature",
  "properties": {
    "iso:country":"GB",
    "wof:name":"CW12 2LP",
    "wof:placetype":"postalcode"
},
  "geometry": {"coordinates":[-2.28082472196943,53.20974989123052],"type":"Point"}
}