{
  "type": "Feature",
  "properties": {
    "iso:country": "GB",
    "wof:name": "CW12 2LP",
    "wof:placetype": "postalcode"
  },
  "geometry": {"coordinates":[-2.280825,53.20975],"type":"Point"}
}
