{
  "type": "Feature",
  "properties": {
    "iso:country":"GB",
    "wof:name":"TA4 1LY",
    "wof:placetype":"postalcode"
},
  "geometry": {"coordinates":[-3.26071453664999,51.02287171532844],"type":"Point"}
}