{
  "type": "Feature",
  "properties": {
    "iso:country":"GB",
    "wof:name":"NG2 7GW",
    "wof:placetype":"postalcode"
},
  "geometry": {"coordinates":[-1.14310298255321,52.91641281321587],"type":"Point"}
}