{
  "type": "Feature",
  "properties": {
    "iso:country":"GB",
    "wof:name":"LN1 1YZ",
    "wof:placetype":"postalcode"
},
  "geometry": {"coordinates":[-0.54456471356078,53.2318597228096],"type":"Point"}
}