{
  "type": "Feature",
  "properties": {
    "iso:country":"GB",
    "wof:name":"EH4 8EQ",
    "wof:placetype":"postalcode"
},
  "geometry": {"coordinates":[-3.31066760926894,55.96009032339921],"type":"Point"}
}