{
  "type": "Feature",
  "properties": {
    "iso:country": "GB",
    "wof:name": "EH4 8EQ",
    "wof:placetype": "postalcode"
  },
  "geometry": {"coordinates":[-3.310668,55.96009],"type":"Point"}
}
