{
  "type": "Feature",
  "properties": {
    "date:inception_lower": "1980-01-01",
    "date:inception_upper": "1980-01-01",
    "iso:country": "GB",
    "wof:name": "HR2 6EP",
    "wof:placetype": "postalcode"
  },
  "geometry": {"coordinates":[-2.703101,52.039577],"type":"Point"}
}
