{
  "type": "Feature",
  "properties": {
    "iso:country":"GB",
    "wof:name":"HR2 6EP",
    "wof:placetype":"postalcode"
},
  "geometry": {"coordinates":[-2.7031014817927,52.03957729393463],"type":"Point"}
}