{
  "type": "Feature",
  "properties": {
    "date:inception_lower":"1983-01-01",
    "date:inception_upper":"1983-01-31",
    "iso:country":"GB",
    "wof:name":"YO22 5HG",
    "wof:placetype":"postalcode"
},
  "geometry": {"coordinates":[-0.670268,54.446883],"type":"Point"}
}