{
  "type": "Feature",
  "properties": {
    "iso:country":"GB",
    "wof:name":"YO22 5HG",
    "wof:placetype":"postalcode"
},
  "geometry": {"coordinates":[-0.67026812600033,54.44688257022666],"type":"Point"}
}