{
  "type": "Feature",
  "properties": {
    "iso:country": "GB",
    "wof:name": "YO25 4SN",
    "wof:placetype": "postalcode"
  },
  "geometry": {"coordinates":[-0.376693,54.063292],"type":"Point"}
}
