{
  "type": "Feature",
  "properties": {
    "iso:country": "GB",
    "wof:name": "ME14 2UN",
    "wof:placetype": "postalcode"
  },
  "geometry": {"coordinates":[0.525523,51.280148],"type":"Point"}
}
