{
  "type": "Feature",
  "properties": {
    "iso:country":"GB",
    "wof:name":"SY18 6JJ",
    "wof:placetype":"postalcode"
},
  "geometry": {"coordinates":[-3.52055616194871,52.42863991323846],"type":"Point"}
}