{
  "type": "Feature",
  "properties": {
    "date:inception_lower": "1980-01-01",
    "date:inception_upper": "1980-01-01",
    "iso:country": "GB",
    "wof:name": "SY18 6JJ",
    "wof:placetype": "postalcode"
  },
  "geometry": {"coordinates":[-3.520556,52.42864],"type":"Point"}
}
