{
  "type": "Feature",
  "properties": {
    "date:inception_lower":"1980-01-01",
    "date:inception_upper":"1980-01-31",
    "iso:country":"GB",
    "wof:name":"NE22 5RX",
    "wof:placetype":"postalcode"
},
  "geometry": {"coordinates":[-1.585912,55.126451],"type":"Point"}
}