{
  "type": "Feature",
  "properties": {
    "iso:country":"GB",
    "wof:name":"L32 6RN",
    "wof:placetype":"postalcode"
},
  "geometry": {"coordinates":[-2.87268292979573,53.47127603675307],"type":"Point"}
}