{
  "type": "Feature",
  "properties": {
    "iso:country": "GB",
    "wof:name": "GL7 4GP",
    "wof:placetype": "postalcode"
  },
  "geometry": {"coordinates":[-1.766509,51.707186],"type":"Point"}
}
