{
  "type": "Feature",
  "properties": {
    "iso:country": "GB",
    "wof:name": "LA12 0PZ",
    "wof:placetype": "postalcode"
  },
  "geometry": {"coordinates":[-3.141079,54.128373],"type":"Point"}
}
