{
  "type": "Feature",
  "properties": {
    "iso:country": "GB",
    "wof:name": "CF32 7AP",
    "wof:placetype": "postalcode"
  },
  "geometry": {"coordinates":[-3.540372,51.597813],"type":"Point"}
}
