{
  "type": "Feature",
  "properties": {
    "iso:country":"GB",
    "wof:name":"CF32 7AP",
    "wof:placetype":"postalcode"
},
  "geometry": {"coordinates":[-3.54027149745537,51.59780762166201],"type":"Point"}
}