{
  "type": "Feature",
  "properties": {
    "iso:country":"GB",
    "wof:name":"LU5 4HL",
    "wof:placetype":"postalcode"
},
  "geometry": {"coordinates":[-0.51562981003523,51.88756685019003],"type":"Point"}
}