{
  "type": "Feature",
  "properties": {
    "date:inception_lower": "1980-01-01",
    "date:inception_upper": "1980-01-01",
    "iso:country": "GB",
    "wof:name": "LU5 4HL",
    "wof:placetype": "postalcode"
  },
  "geometry": {"coordinates":[-0.51563,51.887567],"type":"Point"}
}
