{
  "type": "Feature",
  "properties": {
    "iso:country":"GB",
    "wof:name":"SY5 6HD",
    "wof:placetype":"postalcode"
},
  "geometry": {"coordinates":[-2.70079718092579,52.65664233057417],"type":"Point"}
}