{
  "type": "Feature",
  "properties": {
    "iso:country":"GB",
    "wof:name":"PE21 9BD",
    "wof:placetype":"postalcode"
},
  "geometry": {"coordinates":[-0.02009248958287,52.98215965666196],"type":"Point"}
}