{
  "type": "Feature",
  "properties": {
    "iso:country":"GB",
    "wof:name":"BL6 7LE",
    "wof:placetype":"postalcode"
},
  "geometry": {"coordinates":[-2.55354895505025,53.60377464265763],"type":"Point"}
}