{
  "type": "Feature",
  "properties": {
    "iso:country":"GB",
    "wof:name":"CV6 3FS",
    "wof:placetype":"postalcode"
},
  "geometry": {"coordinates":[-1.51075952826108,52.42966819403929],"type":"Point"}
}