{
  "type": "Feature",
  "properties": {
    "date:inception_lower":"2002-08-01",
    "date:inception_upper":"2002-08-31",
    "iso:country":"GB",
    "wof:name":"BS40 8DB",
    "wof:placetype":"postalcode"
},
  "geometry": {"coordinates":[-2.668476,51.387965],"type":"Point"}
}