{
  "type": "Feature",
  "properties": {
    "iso:country":"GB",
    "wof:name":"EX37 9LG",
    "wof:placetype":"postalcode"
},
  "geometry": {"coordinates":[-3.9748867771868,50.94056542813872],"type":"Point"}
}