{
  "type": "Feature",
  "properties": {
    "date:inception_lower": "1980-01-01",
    "date:inception_upper": "1980-01-01",
    "iso:country": "GB",
    "wof:name": "EX37 9LG",
    "wof:placetype": "postalcode"
  },
  "geometry": {"coordinates":[-3.984734,50.937308],"type":"Point"}
}
