{
  "type": "Feature",
  "properties": {
    "iso:country":"GB",
    "wof:name":"AL1 2RJ",
    "wof:placetype":"postalcode"
},
  "geometry": {"coordinates":[-0.34135985406398,51.74174731762012],"type":"Point"}
}