{
  "type": "Feature",
  "properties": {
    "iso:country":"GB",
    "wof:name":"S64 0EZ",
    "wof:placetype":"postalcode"
},
  "geometry": {"coordinates":[-1.27559896898239,53.49277352482454],"type":"Point"}
}