{
  "type": "Feature",
  "properties": {
    "iso:country":"GB",
    "wof:name":"RM20 3BP",
    "wof:placetype":"postalcode"
},
  "geometry": {"coordinates":[0.28393335781703,51.47577660612326],"type":"Point"}
}