{
  "type": "Feature",
  "properties": {
    "iso:country":"GB",
    "wof:name":"IP23 8GA",
    "wof:placetype":"postalcode"
},
  "geometry": {"coordinates":[1.11105174138596,52.32629740685176],"type":"Point"}
}