{
  "type": "Feature",
  "properties": {
    "date:inception_lower": "2014-11-01",
    "date:inception_upper": "2014-11-01",
    "iso:country": "GB",
    "wof:name": "IP23 8GA",
    "wof:placetype": "postalcode"
  },
  "geometry": {"coordinates":[1.110616,52.326598],"type":"Point"}
}
