{
  "type": "Feature",
  "properties": {
    "iso:country":"GB",
    "wof:name":"NE38 0NJ",
    "wof:placetype":"postalcode"
},
  "geometry": {"coordinates":[-1.54988920088512,54.89758189859877],"type":"Point"}
}