{
  "type": "Feature",
  "properties": {
    "iso:country":"GB",
    "wof:name":"LE7 1FZ",
    "wof:placetype":"postalcode"
},
  "geometry": {"coordinates":[-1.07713440243006,52.69896873048347],"type":"Point"}
}