{
  "type": "Feature",
  "properties": {
    "date:inception_lower":"2008-02-01",
    "date:inception_upper":"2008-02-29",
    "iso:country":"GB",
    "wof:name":"LE7 1FZ",
    "wof:placetype":"postalcode"
},
  "geometry": {"coordinates":[-1.077128,52.698997],"type":"Point"}
}