{
  "type": "Feature",
  "properties": {
    "iso:country": "GB",
    "wof:name": "SL9 8UX",
    "wof:placetype": "postalcode"
  },
  "geometry": {"coordinates":[-0.554003,51.587111],"type":"Point"}
}
