{
  "type": "Feature",
  "properties": {
    "iso:country":"GB",
    "wof:name":"LE5 1HQ",
    "wof:placetype":"postalcode"
},
  "geometry": {"coordinates":[-1.06309499958992,52.64691454034993],"type":"Point"}
}