{
  "type": "Feature",
  "properties": {
    "iso:country": "GB",
    "wof:name": "GL5 2TE",
    "wof:placetype": "postalcode"
  },
  "geometry": {"coordinates":[-2.181732,51.718713],"type":"Point"}
}
