{
  "type": "Feature",
  "properties": {
    "date:inception_lower":"2017-04-01",
    "date:inception_upper":"2017-04-30",
    "iso:country":"GB",
    "wof:name":"GL5 2TE",
    "wof:placetype":"postalcode"
},
  "geometry": {"coordinates":[-2.181746,51.718569],"type":"Point"}
}