{
  "type": "Feature",
  "properties": {
    "iso:country":"GB",
    "wof:name":"BB9 0NA",
    "wof:placetype":"postalcode"
},
  "geometry": {"coordinates":[-2.20882365524072,53.83251482357817],"type":"Point"}
}