{
  "type": "Feature",
  "properties": {
    "date:inception_lower": "1993-08-01",
    "date:inception_upper": "1993-08-01",
    "iso:country": "GB",
    "wof:name": "BB9 0NA",
    "wof:placetype": "postalcode"
  },
  "geometry": {"coordinates":[-2.208824,53.832515],"type":"Point"}
}
