{
  "type": "Feature",
  "properties": {
    "iso:country": "GB",
    "wof:name": "BB9 0NA",
    "wof:placetype": "postalcode"
  },
  "geometry": {"coordinates":[-2.208824,53.832515],"type":"Point"}
}
