{
  "type": "Feature",
  "properties": {
    "date:inception_lower": "1980-01-01",
    "date:inception_upper": "1980-01-01",
    "iso:country": "GB",
    "wof:name": "PL8 2JP",
    "wof:placetype": "postalcode"
  },
  "geometry": {"coordinates":[-4.001786,50.348527],"type":"Point"}
}
