{
  "type": "Feature",
  "properties": {
    "iso:country":"GB",
    "wof:name":"PL8 2JP",
    "wof:placetype":"postalcode"
},
  "geometry": {"coordinates":[-4.00178626590071,50.34852712096914],"type":"Point"}
}