{
  "type": "Feature",
  "properties": {
    "iso:country":"GB",
    "wof:name":"TS1 3AG",
    "wof:placetype":"postalcode"
},
  "geometry": {"coordinates":[-1.23349435589709,54.57171831161425],"type":"Point"}
}