{
  "type": "Feature",
  "properties": {
    "iso:country": "GB",
    "wof:name": "TS1 3AG",
    "wof:placetype": "postalcode"
  },
  "geometry": {"coordinates":[-1.233372,54.572404],"type":"Point"}
}
