{
  "type": "Feature",
  "properties": {
    "date:inception_lower": "1980-01-01",
    "date:inception_upper": "1980-01-01",
    "iso:country": "GB",
    "wof:name": "DY3 2BP",
    "wof:placetype": "postalcode"
  },
  "geometry": {"coordinates":[-2.117639,52.526885],"type":"Point"}
}
