{
  "type": "Feature",
  "properties": {
    "iso:country": "GB",
    "wof:name": "DY3 2BP",
    "wof:placetype": "postalcode"
  },
  "geometry": {"coordinates":[-2.117639,52.526885],"type":"Point"}
}
