{
  "type": "Feature",
  "properties": {
    "iso:country": "GB",
    "wof:name": "GL4 0BD",
    "wof:placetype": "postalcode"
  },
  "geometry": {"coordinates":[-2.241786,51.836723],"type":"Point"}
}
