{
  "type": "Feature",
  "properties": {
    "iso:country":"GB",
    "wof:name":"CR0 5FJ",
    "wof:placetype":"postalcode"
},
  "geometry": {"coordinates":[-0.08094614472199,51.37255204075994],"type":"Point"}
}