{
  "type": "Feature",
  "properties": {
    "iso:country": "GB",
    "wof:name": "CV37 6NZ",
    "wof:placetype": "postalcode"
  },
  "geometry": {"coordinates":[-1.710807,52.193487],"type":"Point"}
}
