{
  "type": "Feature",
  "properties": {
    "iso:country":"GB",
    "wof:name":"ME20 6QQ",
    "wof:placetype":"postalcode"
},
  "geometry": {"coordinates":[0.43940507457257,51.30087870348386],"type":"Point"}
}