{
  "type": "Feature",
  "properties": {
    "iso:country":"GB",
    "wof:name":"SO41 8LD",
    "wof:placetype":"postalcode"
},
  "geometry": {"coordinates":[-1.57655191779959,50.75899174589],"type":"Point"}
}