{
  "type": "Feature",
  "properties": {
    "date:inception_lower": "1999-06-01",
    "date:inception_upper": "1999-06-01",
    "iso:country": "GB",
    "wof:name": "NP25 4PZ",
    "wof:placetype": "postalcode"
  },
  "geometry": {"coordinates":[-2.721925,51.742098],"type":"Point"}
}
