{
  "type": "Feature",
  "properties": {
    "iso:country":"GB",
    "wof:name":"NP25 4PZ",
    "wof:placetype":"postalcode"
},
  "geometry": {"coordinates":[-2.72192096452376,51.74209408875551],"type":"Point"}
}