{
  "type": "Feature",
  "properties": {
    "date:inception_lower": "1980-01-01",
    "date:inception_upper": "1980-01-01",
    "iso:country": "GB",
    "wof:name": "LA13 9HS",
    "wof:placetype": "postalcode"
  },
  "geometry": {"coordinates":[-3.202817,54.119467],"type":"Point"}
}
