{
  "type": "Feature",
  "properties": {
    "iso:country":"GB",
    "wof:name":"LA13 9HS",
    "wof:placetype":"postalcode"
},
  "geometry": {"coordinates":[-3.20281679702551,54.11946745947867],"type":"Point"}
}