{
  "type": "Feature",
  "properties": {
    "date:inception_lower":"1999-06-01",
    "date:inception_upper":"1999-06-30",
    "iso:country":"GB",
    "wof:name":"CF10 3BD",
    "wof:placetype":"postalcode"
},
  "geometry": {"coordinates":[-3.17585,51.48684],"type":"Point"}
}