{
  "type": "Feature",
  "properties": {
    "iso:country": "GB",
    "wof:name": "CF10 3BD",
    "wof:placetype": "postalcode"
  },
  "geometry": {"coordinates":[-3.17585,51.48684],"type":"Point"}
}
