{
  "type": "Feature",
  "properties": {
    "iso:country": "GB",
    "wof:name": "SP11 6WX",
    "wof:placetype": "postalcode"
  },
  "geometry": {"coordinates":[-1.455535,51.22303],"type":"Point"}
}
