{
  "type": "Feature",
  "properties": {
    "date:inception_lower": "2017-07-01",
    "date:inception_upper": "2017-07-01",
    "iso:country": "GB",
    "wof:name": "SP11 6WX",
    "wof:placetype": "postalcode"
  },
  "geometry": {"coordinates":[-1.455535,51.22303],"type":"Point"}
}
