{
  "type": "Feature",
  "properties": {
    "date:inception_lower":"2012-08-01",
    "date:inception_upper":"2012-08-31",
    "iso:country":"GB",
    "wof:name":"CT9 1BT",
    "wof:placetype":"postalcode"
},
  "geometry": {"coordinates":[1.383556,51.38925],"type":"Point"}
}