{
  "type": "Feature",
  "properties": {
    "iso:country":"GB",
    "wof:name":"RM10 7TR",
    "wof:placetype":"postalcode"
},
  "geometry": {"coordinates":[0.16596539384768,51.54726973037056],"type":"Point"}
}