{
  "type": "Feature",
  "properties": {
    "iso:country":"GB",
    "wof:name":"PO33 1UB",
    "wof:placetype":"postalcode"
},
  "geometry": {"coordinates":[-1.10939789769427,50.69773650493324],"type":"Point"}
}