{
  "type": "Feature",
  "properties": {
    "iso:country":"GB",
    "wof:name":"OX1 1ER",
    "wof:placetype":"postalcode"
},
  "geometry": {"coordinates":[-1.25921367455516,51.75185239364795],"type":"Point"}
}