{
  "type": "Feature",
  "properties": {
    "iso:country": "GB",
    "wof:name": "OX1 1ER",
    "wof:placetype": "postalcode"
  },
  "geometry": {"coordinates":[-1.259214,51.751852],"type":"Point"}
}
