{
  "type": "Feature",
  "properties": {
    "iso:country": "GB",
    "wof:name": "EX12 3EJ",
    "wof:placetype": "postalcode"
  },
  "geometry": {"coordinates":[-3.093168,50.698245],"type":"Point"}
}
