{
  "type": "Feature",
  "properties": {
    "date:inception_lower": "1980-01-01",
    "date:inception_upper": "1980-01-01",
    "iso:country": "GB",
    "wof:name": "EX12 3EJ",
    "wof:placetype": "postalcode"
  },
  "geometry": {"coordinates":[-3.093168,50.698245],"type":"Point"}
}
