{
  "type": "Feature",
  "properties": {
    "iso:country":"GB",
    "wof:name":"B91 3FS",
    "wof:placetype":"postalcode"
},
  "geometry": {"coordinates":[-1.78162759851284,52.40543163416856],"type":"Point"}
}