{
  "type": "Feature",
  "properties": {
    "date:inception_lower": "1980-01-01",
    "date:inception_upper": "1980-01-01",
    "iso:country": "GB",
    "wof:name": "TQ5 8DA",
    "wof:placetype": "postalcode"
  },
  "geometry": {"coordinates":[-3.526098,50.390102],"type":"Point"}
}
