{
  "type": "Feature",
  "properties": {
    "iso:country":"GB",
    "wof:name":"BN24 6LA",
    "wof:placetype":"postalcode"
},
  "geometry": {"coordinates":[0.34944265070881,50.81303733357873],"type":"Point"}
}