{
  "type": "Feature",
  "properties": {
    "iso:country":"GB",
    "wof:name":"WA15 0QP",
    "wof:placetype":"postalcode"
},
  "geometry": {"coordinates":[-2.34003743740305,53.35437781511777],"type":"Point"}
}