{
  "type": "Feature",
  "properties": {
    "iso:country":"GB",
    "wof:name":"GU7 2EW",
    "wof:placetype":"postalcode"
},
  "geometry": {"coordinates":[-0.61322875130132,51.19264217871994],"type":"Point"}
}