{
  "type": "Feature",
  "properties": {
    "iso:country":"GB",
    "wof:name":"DY2 9EW",
    "wof:placetype":"postalcode"
},
  "geometry": {"coordinates":[-2.07583005489191,52.488855814475],"type":"Point"}
}