{
  "type": "Feature",
  "properties": {
    "iso:country": "GB",
    "wof:name": "NP15 2AY",
    "wof:placetype": "postalcode"
  },
  "geometry": {"coordinates":[-2.907378,51.795439],"type":"Point"}
}
