{
  "type": "Feature",
  "properties": {
    "iso:country":"GB",
    "wof:name":"BD23 1HE",
    "wof:placetype":"postalcode"
},
  "geometry": {"coordinates":[-2.0067463488828,53.96225601170858],"type":"Point"}
}