{
  "type": "Feature",
  "properties": {
    "iso:country":"GB",
    "wof:name":"B78 1DE",
    "wof:placetype":"postalcode"
},
  "geometry": {"coordinates":[-1.61614752825949,52.61979869327882],"type":"Point"}
}