{
  "type": "Feature",
  "properties": {
    "date:inception_lower": "1998-12-01",
    "date:inception_upper": "1998-12-01",
    "iso:country": "GB",
    "wof:name": "B78 1DE",
    "wof:placetype": "postalcode"
  },
  "geometry": {"coordinates":[-1.616147,52.619799],"type":"Point"}
}
