{
  "type": "Feature",
  "properties": {
    "iso:country": "GB",
    "wof:name": "E17 4HG",
    "wof:placetype": "postalcode"
  },
  "geometry": {"coordinates":[-0.008425,51.599109],"type":"Point"}
}
