{
  "type": "Feature",
  "properties": {
    "iso:country":"GB",
    "wof:name":"E17 4HG",
    "wof:placetype":"postalcode"
},
  "geometry": {"coordinates":[-0.00842554067843,51.59910875298373],"type":"Point"}
}