{
  "type": "Feature",
  "properties": {
    "date:inception_lower": "1980-01-01",
    "date:inception_upper": "1980-01-01",
    "iso:country": "GB",
    "wof:name": "SN10 4RE",
    "wof:placetype": "postalcode"
  },
  "geometry": {"coordinates":[-1.947225,51.311562],"type":"Point"}
}
