{
  "type": "Feature",
  "properties": {
    "iso:country":"GB",
    "wof:name":"SN10 4RE",
    "wof:placetype":"postalcode"
},
  "geometry": {"coordinates":[-1.94722508173793,51.31156193113075],"type":"Point"}
}