{
  "type": "Feature",
  "properties": {
    "iso:country":"GB",
    "wof:name":"CT1 3JX",
    "wof:placetype":"postalcode"
},
  "geometry": {"coordinates":[1.08525555588099,51.27183581791982],"type":"Point"}
}