{
  "type": "Feature",
  "properties": {
    "iso:country": "GB",
    "wof:name": "CT1 3JX",
    "wof:placetype": "postalcode"
  },
  "geometry": {"coordinates":[1.085256,51.271836],"type":"Point"}
}
