{
  "type": "Feature",
  "properties": {
    "date:inception_lower":"1980-01-01",
    "date:inception_upper":"1980-01-31",
    "iso:country":"GB",
    "wof:name":"DY8 5DW",
    "wof:placetype":"postalcode"
},
  "geometry": {"coordinates":[-2.16796,52.474238],"type":"Point"}
}