{
  "type": "Feature",
  "properties": {
    "iso:country": "GB",
    "wof:name": "DY8 5DW",
    "wof:placetype": "postalcode"
  },
  "geometry": {"coordinates":[-2.16796,52.474238],"type":"Point"}
}
