{
  "type": "Feature",
  "properties": {
    "iso:country":"GB",
    "wof:name":"DY8 5DW",
    "wof:placetype":"postalcode"
},
  "geometry": {"coordinates":[-2.1679214930683,52.47422398076711],"type":"Point"}
}