{
  "type": "Feature",
  "properties": {
    "date:inception_lower":"1980-01-01",
    "date:inception_upper":"1980-01-31",
    "iso:country":"GB",
    "wof:name":"SK7 6NH",
    "wof:placetype":"postalcode"
},
  "geometry": {"coordinates":[-2.091438,53.367358],"type":"Point"}
}