{
  "type": "Feature",
  "properties": {
    "iso:country": "GB",
    "wof:name": "SK7 6NH",
    "wof:placetype": "postalcode"
  },
  "geometry": {"coordinates":[-2.091438,53.367358],"type":"Point"}
}
