{
  "type": "Feature",
  "properties": {
    "iso:country": "GB",
    "wof:name": "SL1 2HH",
    "wof:placetype": "postalcode"
  },
  "geometry": {"coordinates":[-0.597664,51.507187],"type":"Point"}
}
