{
  "type": "Feature",
  "properties": {
    "date:inception_lower": "1980-01-01",
    "date:inception_upper": "1980-01-01",
    "iso:country": "GB",
    "wof:name": "SL1 2HH",
    "wof:placetype": "postalcode"
  },
  "geometry": {"coordinates":[-0.597664,51.507187],"type":"Point"}
}
