{
  "type": "Feature",
  "properties": {
    "iso:country":"GB",
    "wof:name":"PL4 7BB",
    "wof:placetype":"postalcode"
},
  "geometry": {"coordinates":[-4.12532444606232,50.38334572230048],"type":"Point"}
}