{
  "type": "Feature",
  "properties": {
    "iso:country":"GB",
    "wof:name":"SA19 8SR",
    "wof:placetype":"postalcode"
},
  "geometry": {"coordinates":[-3.95306439647866,52.02635545743449],"type":"Point"}
}