{
  "type": "Feature",
  "properties": {
    "iso:country":"GB",
    "wof:name":"WS11 7FR",
    "wof:placetype":"postalcode"
},
  "geometry": {"coordinates":[-1.99769334619272,52.6973443866018],"type":"Point"}
}