{
  "type": "Feature",
  "properties": {
    "iso:country": "GB",
    "wof:name": "DE75 7HB",
    "wof:placetype": "postalcode"
  },
  "geometry": {"coordinates":[-1.34391,53.01252],"type":"Point"}
}
