{
  "type": "Feature",
  "properties": {
    "iso:country":"GB",
    "wof:name":"DE75 7HB",
    "wof:placetype":"postalcode"
},
  "geometry": {"coordinates":[-1.34390979611589,53.01251987159148],"type":"Point"}
}