{
  "type": "Feature",
  "properties": {
    "iso:country":"GB",
    "wof:name":"YO62 5HY",
    "wof:placetype":"postalcode"
},
  "geometry": {"coordinates":[-1.02327458069332,54.2476268601084],"type":"Point"}
}