{
  "type": "Feature",
  "properties": {
    "iso:country": "GB",
    "wof:name": "YO62 5HY",
    "wof:placetype": "postalcode"
  },
  "geometry": {"coordinates":[-1.023439,54.247643],"type":"Point"}
}
