{
  "type": "Feature",
  "properties": {
    "date:inception_lower":"1998-06-01",
    "date:inception_upper":"1998-06-30",
    "iso:country":"GB",
    "wof:name":"YO62 5HY",
    "wof:placetype":"postalcode"
},
  "geometry": {"coordinates":[-1.023439,54.247643],"type":"Point"}
}