{
  "type": "Feature",
  "properties": {
    "date:inception_lower": "2000-12-01",
    "date:inception_upper": "2000-12-01",
    "iso:country": "GB",
    "wof:name": "G31 4AB",
    "wof:placetype": "postalcode"
  },
  "geometry": {"coordinates":[-4.211463,55.853323],"type":"Point"}
}
