{
  "type": "Feature",
  "properties": {
    "iso:country":"GB",
    "wof:name":"G31 4AB",
    "wof:placetype":"postalcode"
},
  "geometry": {"coordinates":[-4.21146264231084,55.85332262434047],"type":"Point"}
}