{
  "type": "Feature",
  "properties": {
    "iso:country":"GB",
    "wof:name":"OX16 0NW",
    "wof:placetype":"postalcode"
},
  "geometry": {"coordinates":[-1.35718976113896,52.05713294567135],"type":"Point"}
}