{
  "type": "Feature",
  "properties": {
    "iso:country":"GB",
    "wof:name":"DN20 0HT",
    "wof:placetype":"postalcode"
},
  "geometry": {"coordinates":[-0.55290657017189,53.56667201185229],"type":"Point"}
}