{
  "type": "Feature",
  "properties": {
    "iso:country":"GB",
    "wof:name":"M13 9WY",
    "wof:placetype":"postalcode"
},
  "geometry": {"coordinates":[-2.2316599588902,53.47122820253885],"type":"Point"}
}