{
  "type": "Feature",
  "properties": {
    "iso:country":"GB",
    "wof:name":"PH7 3DX",
    "wof:placetype":"postalcode"
},
  "geometry": {"coordinates":[-3.83415982181896,56.37488813879391],"type":"Point"}
}