{
  "type": "Feature",
  "properties": {
    "iso:country":"GB",
    "wof:name":"N21 1SJ",
    "wof:placetype":"postalcode"
},
  "geometry": {"coordinates":[-0.11559464372438,51.64443744781212],"type":"Point"}
}