{
  "type": "Feature",
  "properties": {
    "iso:country": "GB",
    "wof:name": "LU5 6FB",
    "wof:placetype": "postalcode"
  },
  "geometry": {"coordinates":[-0.53551,51.943366],"type":"Point"}
}
