{
  "type": "Feature",
  "properties": {
    "iso:country":"GB",
    "wof:name":"GU15 3AE",
    "wof:placetype":"postalcode"
},
  "geometry": {"coordinates":[-0.7585612322385,51.3302646158819],"type":"Point"}
}