{
  "type": "Feature",
  "properties": {
    "iso:country": "GB",
    "wof:name": "YO12 4RW",
    "wof:placetype": "postalcode"
  },
  "geometry": {"coordinates":[-0.449828,54.251693],"type":"Point"}
}
