{
  "type": "Feature",
  "properties": {
    "date:inception_lower":"1980-01-01",
    "date:inception_upper":"1980-01-31",
    "iso:country":"GB",
    "wof:name":"YO12 4RW",
    "wof:placetype":"postalcode"
},
  "geometry": {"coordinates":[-0.449828,54.251693],"type":"Point"}
}