{
  "type": "Feature",
  "properties": {
    "iso:country":"GB",
    "wof:name":"PE16 6DQ",
    "wof:placetype":"postalcode"
},
  "geometry": {"coordinates":[0.05544353908809,52.45806134175973],"type":"Point"}
}