{
  "type": "Feature",
  "properties": {
    "date:inception_lower": "1990-07-01",
    "date:inception_upper": "1990-07-01",
    "iso:country": "GB",
    "wof:name": "PE16 6DQ",
    "wof:placetype": "postalcode"
  },
  "geometry": {"coordinates":[0.055444,52.458061],"type":"Point"}
}
