{
  "type": "Feature",
  "properties": {
    "iso:country":"GB",
    "wof:name":"SO45 1YF",
    "wof:placetype":"postalcode"
},
  "geometry": {"coordinates":[-1.36839847205559,50.81469559709858],"type":"Point"}
}