{
  "type": "Feature",
  "properties": {
    "iso:country":"GB",
    "wof:name":"SG4 8EF",
    "wof:placetype":"postalcode"
},
  "geometry": {"coordinates":[-0.2915972098775,51.85364053482296],"type":"Point"}
}