{
  "type": "Feature",
  "properties": {
    "iso:country": "GB",
    "wof:name": "SG4 8EF",
    "wof:placetype": "postalcode"
  },
  "geometry": {"coordinates":[-0.291732,51.853659],"type":"Point"}
}
