{
  "type": "Feature",
  "properties": {
    "iso:country":"GB",
    "wof:name":"L37 7DF",
    "wof:placetype":"postalcode"
},
  "geometry": {"coordinates":[-3.0650548475718,53.56505139924352],"type":"Point"}
}