{
  "type": "Feature",
  "properties": {
    "iso:country": "GB",
    "wof:name": "YO19 5PY",
    "wof:placetype": "postalcode"
  },
  "geometry": {"coordinates":[-0.984091,53.964866],"type":"Point"}
}
