{
  "type": "Feature",
  "properties": {
    "date:inception_lower":"1998-06-01",
    "date:inception_upper":"1998-06-30",
    "iso:country":"GB",
    "wof:name":"YO19 5PY",
    "wof:placetype":"postalcode"
},
  "geometry": {"coordinates":[-0.984091,53.964866],"type":"Point"}
}