{
  "type": "Feature",
  "properties": {
    "iso:country":"GB",
    "wof:name":"YO19 5PY",
    "wof:placetype":"postalcode"
},
  "geometry": {"coordinates":[-0.98409055850503,53.96486632997195],"type":"Point"}
}