{
  "type": "Feature",
  "properties": {
    "iso:country":"GB",
    "wof:name":"SN8 3LP",
    "wof:placetype":"postalcode"
},
  "geometry": {"coordinates":[-1.60582899912398,51.38103794787821],"type":"Point"}
}