{
  "type": "Feature",
  "properties": {
    "date:inception_lower":"2017-10-01",
    "date:inception_upper":"2017-10-31",
    "iso:country":"GB",
    "wof:name":"NR10 4SL",
    "wof:placetype":"postalcode"
},
  "geometry": {"coordinates":[1.105457,52.751611],"type":"Point"}
}