{
  "type": "Feature",
  "properties": {
    "iso:country": "GB",
    "wof:name": "NR10 4SL",
    "wof:placetype": "postalcode"
  },
  "geometry": {"coordinates":[1.105457,52.751611],"type":"Point"}
}
