{
  "type": "Feature",
  "properties": {
    "date:inception_lower":"1980-01-01",
    "date:inception_upper":"1980-01-31",
    "iso:country":"GB",
    "wof:name":"DD3 9BJ",
    "wof:placetype":"postalcode"
},
  "geometry": {"coordinates":[-3.001134,56.491322],"type":"Point"}
}