{
  "type": "Feature",
  "properties": {
    "iso:country":"GB",
    "wof:name":"WA5 2PF",
    "wof:placetype":"postalcode"
},
  "geometry": {"coordinates":[-2.66443912977015,53.37893566013798],"type":"Point"}
}