{
  "type": "Feature",
  "properties": {
    "iso:country":"GB",
    "wof:name":"DL1 3TL",
    "wof:placetype":"postalcode"
},
  "geometry": {"coordinates":[-1.53182194408435,54.54671909366101],"type":"Point"}
}