{
  "type": "Feature",
  "properties": {
    "iso:country": "GB",
    "wof:name": "DL1 3TL",
    "wof:placetype": "postalcode"
  },
  "geometry": {"coordinates":[-1.531822,54.546719],"type":"Point"}
}
