{
  "type": "Feature",
  "properties": {
    "date:inception_lower": "1992-01-01",
    "date:inception_upper": "1992-01-01",
    "iso:country": "GB",
    "wof:name": "DL1 3TL",
    "wof:placetype": "postalcode"
  },
  "geometry": {"coordinates":[-1.531815,54.54673],"type":"Point"}
}
