{
  "type": "Feature",
  "properties": {
    "iso:country": "GB",
    "wof:name": "CF24 1LZ",
    "wof:placetype": "postalcode"
  },
  "geometry": {"coordinates":[-3.159285,51.486735],"type":"Point"}
}
