{
  "type": "Feature",
  "properties": {
    "iso:country":"GB",
    "wof:name":"NG5 4AY",
    "wof:placetype":"postalcode"
},
  "geometry": {"coordinates":[-1.13999962920473,52.98296676206196],"type":"Point"}
}