{
  "type": "Feature",
  "properties": {
    "iso:country":"GB",
    "wof:name":"DN7 6EE",
    "wof:placetype":"postalcode"
},
  "geometry": {"coordinates":[-0.97016131092768,53.54427678524714],"type":"Point"}
}