{
  "type": "Feature",
  "properties": {
    "iso:country": "GB",
    "wof:name": "ST15 8PU",
    "wof:placetype": "postalcode"
  },
  "geometry": {"coordinates":[-2.132415,52.895102],"type":"Point"}
}
