{
  "type": "Feature",
  "properties": {
    "iso:country": "GB",
    "wof:name": "PL19 8LX",
    "wof:placetype": "postalcode"
  },
  "geometry": {"coordinates":[-4.151975,50.550778],"type":"Point"}
}
