{
  "type": "Feature",
  "properties": {
    "date:inception_lower": "1980-01-01",
    "date:inception_upper": "1980-01-01",
    "iso:country": "GB",
    "wof:name": "KA5 6BL",
    "wof:placetype": "postalcode"
  },
  "geometry": {"coordinates":[-4.369573,55.514301],"type":"Point"}
}
