{
  "type": "Feature",
  "properties": {
    "iso:country":"GB",
    "wof:name":"KA5 6BL",
    "wof:placetype":"postalcode"
},
  "geometry": {"coordinates":[-4.36957311483798,55.51430096491178],"type":"Point"}
}