{
  "type": "Feature",
  "properties": {
    "iso:country":"GB",
    "wof:name":"TR11 2RB",
    "wof:placetype":"postalcode"
},
  "geometry": {"coordinates":[-5.08039420464228,50.15057439420317],"type":"Point"}
}