{
  "type": "Feature",
  "properties": {
    "iso:country":"GB",
    "wof:name":"HP2 7BG",
    "wof:placetype":"postalcode"
},
  "geometry": {"coordinates":[-0.44932781356691,51.77424329068459],"type":"Point"}
}