{
  "type": "Feature",
  "properties": {
    "iso:country": "GB",
    "wof:name": "SA18 3SG",
    "wof:placetype": "postalcode"
  },
  "geometry": {"coordinates":[-4.042484,51.784297],"type":"Point"}
}
