{
  "type": "Feature",
  "properties": {
    "iso:country":"GB",
    "wof:name":"SA18 3SG",
    "wof:placetype":"postalcode"
},
  "geometry": {"coordinates":[-4.04248419099095,51.78429713079548],"type":"Point"}
}