{
  "type": "Feature",
  "properties": {
    "iso:country":"GB",
    "wof:name":"WN7 5JF",
    "wof:placetype":"postalcode"
},
  "geometry": {"coordinates":[-2.52627943090869,53.51324044333214],"type":"Point"}
}