{
  "type": "Feature",
  "properties": {
    "iso:country":"GB",
    "wof:name":"BB4 8DU",
    "wof:placetype":"postalcode"
},
  "geometry": {"coordinates":[-2.28638900181876,53.71648096905879],"type":"Point"}
}