{
  "type": "Feature",
  "properties": {
    "iso:country": "GB",
    "wof:name": "BB4 8DU",
    "wof:placetype": "postalcode"
  },
  "geometry": {"coordinates":[-2.286389,53.716481],"type":"Point"}
}
