{
  "type": "Feature",
  "properties": {
    "date:inception_lower": "2016-06-01",
    "date:inception_upper": "2016-06-01",
    "iso:country": "GB",
    "wof:name": "SA11 2TP",
    "wof:placetype": "postalcode"
  },
  "geometry": {"coordinates":[-3.814375,51.640605],"type":"Point"}
}
