{
  "type": "Feature",
  "properties": {
    "iso:country": "GB",
    "wof:name": "SA11 2TP",
    "wof:placetype": "postalcode"
  },
  "geometry": {"coordinates":[-3.814375,51.640605],"type":"Point"}
}
