{
  "type": "Feature",
  "properties": {
    "iso:country":"GB",
    "wof:name":"OL16 2BB",
    "wof:placetype":"postalcode"
},
  "geometry": {"coordinates":[-2.149096652194,53.61487688194446],"type":"Point"}
}