{
  "type": "Feature",
  "properties": {
    "date:inception_lower": "2008-01-01",
    "date:inception_upper": "2008-01-01",
    "iso:country": "GB",
    "wof:name": "LS10 4GY",
    "wof:placetype": "postalcode"
  },
  "geometry": {"coordinates":[-1.524482,53.74441],"type":"Point"}
}
