{
  "type": "Feature",
  "properties": {
    "iso:country":"GB",
    "wof:name":"LS10 4GY",
    "wof:placetype":"postalcode"
},
  "geometry": {"coordinates":[-1.5244816151017,53.74440973162616],"type":"Point"}
}