{
  "type": "Feature",
  "properties": {
    "iso:country": "GB",
    "wof:name": "LS10 4GY",
    "wof:placetype": "postalcode"
  },
  "geometry": {"coordinates":[-1.524482,53.74441],"type":"Point"}
}
