{
  "type": "Feature",
  "properties": {
    "iso:country": "GB",
    "wof:name": "CW5 9DX",
    "wof:placetype": "postalcode"
  },
  "geometry": {"coordinates":[-2.521507,53.068232],"type":"Point"}
}
