{
  "type": "Feature",
  "properties": {
    "iso:country":"GB",
    "wof:name":"HP2 4JH",
    "wof:placetype":"postalcode"
},
  "geometry": {"coordinates":[-0.45092983433648,51.75031018984292],"type":"Point"}
}