{
  "type": "Feature",
  "properties": {
    "iso:country": "GB",
    "wof:name": "CV9 3DX",
    "wof:placetype": "postalcode"
  },
  "geometry": {"coordinates":[-1.560354,52.589093],"type":"Point"}
}
