{
  "type": "Feature",
  "properties": {
    "date:inception_lower":"1980-01-01",
    "date:inception_upper":"1980-01-31",
    "iso:country":"GB",
    "wof:name":"CV9 3DX",
    "wof:placetype":"postalcode"
},
  "geometry": {"coordinates":[-1.560354,52.589093],"type":"Point"}
}