{
  "type": "Feature",
  "properties": {
    "date:inception_lower": "2022-02-01",
    "date:inception_upper": "2022-02-01",
    "iso:country": "GB",
    "wof:name": "E16 4BW",
    "wof:placetype": "postalcode"
  },
  "geometry": {"coordinates":[0.012031,51.521254],"type":"Point"}
}
