{
  "type": "Feature",
  "properties": {
    "iso:country": "GB",
    "wof:name": "HU2 8TH",
    "wof:placetype": "postalcode"
  },
  "geometry": {"coordinates":[-0.35147,53.74848],"type":"Point"}
}
