{
  "type": "Feature",
  "properties": {
    "iso:country":"GB",
    "wof:name":"RG17 0YT",
    "wof:placetype":"postalcode"
},
  "geometry": {"coordinates":[-1.51800304480708,51.42104652559956],"type":"Point"}
}