{
  "type": "Feature",
  "properties": {
    "date:inception_lower":"1995-01-01",
    "date:inception_upper":"1995-01-31",
    "iso:country":"GB",
    "wof:name":"RG17 0YT",
    "wof:placetype":"postalcode"
},
  "geometry": {"coordinates":[-1.517988,51.421045],"type":"Point"}
}