{
  "type": "Feature",
  "properties": {
    "date:inception_lower": "2018-07-01",
    "date:inception_upper": "2018-07-01",
    "iso:country": "GB",
    "wof:name": "SE23 3DJ",
    "wof:placetype": "postalcode"
  },
  "geometry": {"coordinates":[-0.053118,51.446346],"type":"Point"}
}
