{
  "type": "Feature",
  "properties": {
    "date:inception_lower": "2018-07-01",
    "date:inception_upper": "2018-07-01",
    "iso:country": "GB",
    "wof:name": "SE23 3DJ",
    "wof:placetype": "postalcode"
  },
  "geometry": {"coordinates":[-0.052694,51.446177],"type":"Point"}
}
