{
  "type": "Feature",
  "properties": {
    "iso:country":"GB",
    "wof:name":"TR10 9HQ",
    "wof:placetype":"postalcode"
},
  "geometry": {"coordinates":[-5.13321949783903,50.16493877297913],"type":"Point"}
}