{
  "type": "Feature",
  "properties": {
    "iso:country": "GB",
    "wof:name": "TR10 9HQ",
    "wof:placetype": "postalcode"
  },
  "geometry": {"coordinates":[-5.133219,50.164939],"type":"Point"}
}
