{
  "type": "Feature",
  "properties": {
    "date:inception_lower": "1998-06-01",
    "date:inception_upper": "1998-06-01",
    "iso:country": "GB",
    "wof:name": "PH20 1AN",
    "wof:placetype": "postalcode"
  },
  "geometry": {"coordinates":[-4.286814,57.019665],"type":"Point"}
}
