{
  "type": "Feature",
  "properties": {
    "iso:country": "GB",
    "wof:name": "PH20 1AN",
    "wof:placetype": "postalcode"
  },
  "geometry": {"coordinates":[-4.286814,57.019665],"type":"Point"}
}
