{
  "type": "Feature",
  "properties": {
    "iso:country":"GB",
    "wof:name":"PH20 1AN",
    "wof:placetype":"postalcode"
},
  "geometry": {"coordinates":[-4.28681367709974,57.0196654280384],"type":"Point"}
}