{
  "type": "Feature",
  "properties": {
    "iso:country":"GB",
    "wof:name":"TR4 9LZ",
    "wof:placetype":"postalcode"
},
  "geometry": {"coordinates":[-5.15162298752571,50.32008718927607],"type":"Point"}
}