{
  "type": "Feature",
  "properties": {
    "iso:country":"GB",
    "wof:name":"WA3 7NB",
    "wof:placetype":"postalcode"
},
  "geometry": {"coordinates":[-2.53395600664278,53.42572967208049],"type":"Point"}
}