{
  "type": "Feature",
  "properties": {
    "iso:country":"GB",
    "wof:name":"M3 4FN",
    "wof:placetype":"postalcode"
},
  "geometry": {"coordinates":[-2.25128719292694,53.47591643585651],"type":"Point"}
}