{
  "type": "Feature",
  "properties": {
    "iso:country":"GB",
    "wof:name":"LA18 4DS",
    "wof:placetype":"postalcode"
},
  "geometry": {"coordinates":[-3.26440058999059,54.20838446684238],"type":"Point"}
}