{
  "type": "Feature",
  "properties": {
    "date:inception_lower": "1980-01-01",
    "date:inception_upper": "1980-01-01",
    "iso:country": "GB",
    "wof:name": "KA10 6TY",
    "wof:placetype": "postalcode"
  },
  "geometry": {"coordinates":[-4.643728,55.563123],"type":"Point"}
}
