{
  "type": "Feature",
  "properties": {
    "iso:country":"GB",
    "wof:name":"KA10 6TY",
    "wof:placetype":"postalcode"
},
  "geometry": {"coordinates":[-4.64372771940193,55.56312300541705],"type":"Point"}
}