{
  "type": "Feature",
  "properties": {
    "iso:country": "GB",
    "wof:name": "PR2 3RN",
    "wof:placetype": "postalcode"
  },
  "geometry": {"coordinates":[-2.727942,53.776495],"type":"Point"}
}
