{
  "type": "Feature",
  "properties": {
    "iso:country":"GB",
    "wof:name":"HR6 8DR",
    "wof:placetype":"postalcode"
},
  "geometry": {"coordinates":[-2.73977416770197,52.22861532457907],"type":"Point"}
}