{
  "type": "Feature",
  "properties": {
    "iso:country":"GB",
    "wof:name":"WA9 5TD",
    "wof:placetype":"postalcode"
},
  "geometry": {"coordinates":[-2.74658214968261,53.42729502903948],"type":"Point"}
}