{
  "type": "Feature",
  "properties": {
    "iso:country":"GB",
    "wof:name":"SN1 5BD",
    "wof:placetype":"postalcode"
},
  "geometry": {"coordinates":[-1.78352303115591,51.55880438310786],"type":"Point"}
}