{
  "type": "Feature",
  "properties": {
    "date:inception_lower": "2001-06-01",
    "date:inception_upper": "2001-06-01",
    "iso:country": "GB",
    "wof:name": "SN1 5BD",
    "wof:placetype": "postalcode"
  },
  "geometry": {"coordinates":[-1.783523,51.558804],"type":"Point"}
}
