{
  "type": "Feature",
  "properties": {
    "iso:country":"GB",
    "wof:name":"HD4 6UQ",
    "wof:placetype":"postalcode"
},
  "geometry": {"coordinates":[-1.75196005479869,53.61117223300764],"type":"Point"}
}