{
  "type": "Feature",
  "properties": {
    "iso:country":"GB",
    "wof:name":"M33 4GU",
    "wof:placetype":"postalcode"
},
  "geometry": {"coordinates":[-2.35529033856592,53.41799081323952],"type":"Point"}
}