{
  "type": "Feature",
  "properties": {
    "iso:country":"GB",
    "wof:name":"TN2 4BS",
    "wof:placetype":"postalcode"
},
  "geometry": {"coordinates":[0.3277416659178,51.15234075130115],"type":"Point"}
}