{
  "type": "Feature",
  "properties": {
    "iso:country":"GB",
    "wof:name":"NN6 6HR",
    "wof:placetype":"postalcode"
},
  "geometry": {"coordinates":[-1.06004431231724,52.41445792758078],"type":"Point"}
}