{
  "type": "Feature",
  "properties": {
    "date:inception_lower": "1993-08-01",
    "date:inception_upper": "1993-08-01",
    "iso:country": "GB",
    "wof:name": "NN6 6HR",
    "wof:placetype": "postalcode"
  },
  "geometry": {"coordinates":[-1.060046,52.414492],"type":"Point"}
}
