{
  "type": "Feature",
  "properties": {
    "date:inception_lower":"1994-05-01",
    "date:inception_upper":"1994-05-31",
    "iso:country":"GB",
    "wof:name":"M45 8UZ",
    "wof:placetype":"postalcode"
},
  "geometry": {"coordinates":[-2.289799,53.553462],"type":"Point"}
}