{
  "type": "Feature",
  "properties": {
    "iso:country": "GB",
    "wof:name": "BH20 5BY",
    "wof:placetype": "postalcode"
  },
  "geometry": {"coordinates":[-2.093128,50.676612],"type":"Point"}
}
