{
  "type": "Feature",
  "properties": {
    "iso:country": "GB",
    "wof:name": "NG19 9FG",
    "wof:placetype": "postalcode"
  },
  "geometry": {"coordinates":[-1.186927,53.155245],"type":"Point"}
}
