{
  "type": "Feature",
  "properties": {
    "iso:country":"GB",
    "wof:name":"KT7 0DR",
    "wof:placetype":"postalcode"
},
  "geometry": {"coordinates":[-0.339025773954,51.3802809040661],"type":"Point"}
}