{
  "type": "Feature",
  "properties": {
    "iso:country": "GB",
    "wof:name": "KT7 0DR",
    "wof:placetype": "postalcode"
  },
  "geometry": {"coordinates":[-0.339026,51.380281],"type":"Point"}
}
