{
  "type": "Feature",
  "properties": {
    "date:inception_lower": "1980-01-01",
    "date:inception_upper": "1980-01-01",
    "iso:country": "GB",
    "wof:name": "LA12 9JJ",
    "wof:placetype": "postalcode"
  },
  "geometry": {"coordinates":[-3.091481,54.182986],"type":"Point"}
}
