{
  "type": "Feature",
  "properties": {
    "iso:country":"GB",
    "wof:name":"LD1 6SL",
    "wof:placetype":"postalcode"
},
  "geometry": {"coordinates":[-3.29330583171199,52.30260652599656],"type":"Point"}
}