{
  "type": "Feature",
  "properties": {
    "iso:country":"GB",
    "wof:name":"SY3 8TQ",
    "wof:placetype":"postalcode"
},
  "geometry": {"coordinates":[-2.78031392784241,52.70947315905718],"type":"Point"}
}