{
  "type": "Feature",
  "properties": {
    "iso:country":"GB",
    "wof:name":"LL13 0JY",
    "wof:placetype":"postalcode"
},
  "geometry": {"coordinates":[-2.97277190003696,53.03704631657061],"type":"Point"}
}