{
  "type": "Feature",
  "properties": {
    "iso:country": "GB",
    "wof:name": "LL13 0JY",
    "wof:placetype": "postalcode"
  },
  "geometry": {"coordinates":[-2.972772,53.037046],"type":"Point"}
}
