{
  "type": "Feature",
  "properties": {
    "date:inception_lower":"2003-03-01",
    "date:inception_upper":"2003-03-31",
    "iso:country":"GB",
    "wof:name":"LL13 0JY",
    "wof:placetype":"postalcode"
},
  "geometry": {"coordinates":[-2.972772,53.037046],"type":"Point"}
}