{
  "type": "Feature",
  "properties": {
    "date:inception_lower":"1991-09-01",
    "date:inception_upper":"1991-09-30",
    "iso:country":"GB",
    "wof:name":"DT8 3SJ",
    "wof:placetype":"postalcode"
},
  "geometry": {"coordinates":[-2.730818,50.811118],"type":"Point"}
}