{
  "type": "Feature",
  "properties": {
    "iso:country":"GB",
    "wof:name":"DT8 3SJ",
    "wof:placetype":"postalcode"
},
  "geometry": {"coordinates":[-2.73081794608325,50.81111865113763],"type":"Point"}
}