{
  "type": "Feature",
  "properties": {
    "iso:country":"GB",
    "wof:name":"KT3 4AE",
    "wof:placetype":"postalcode"
},
  "geometry": {"coordinates":[-0.25199270552678,51.40087571897452],"type":"Point"}
}