{
  "type": "Feature",
  "properties": {
    "iso:country":"GB",
    "wof:name":"EH6 4DL",
    "wof:placetype":"postalcode"
},
  "geometry": {"coordinates":[-3.18283799554381,55.97416104099901],"type":"Point"}
}