{
  "type": "Feature",
  "properties": {
    "iso:country": "GB",
    "wof:name": "BL4 7DZ",
    "wof:placetype": "postalcode"
  },
  "geometry": {"coordinates":[-2.403358,53.547659],"type":"Point"}
}
