{
  "type": "Feature",
  "properties": {
    "date:inception_lower": "1986-07-01",
    "date:inception_upper": "1986-07-01",
    "iso:country": "GB",
    "wof:name": "BL4 7DZ",
    "wof:placetype": "postalcode"
  },
  "geometry": {"coordinates":[-2.403358,53.547659],"type":"Point"}
}
