{
  "type": "Feature",
  "properties": {
    "iso:country":"GB",
    "wof:name":"DH9 8NG",
    "wof:placetype":"postalcode"
},
  "geometry": {"coordinates":[-1.69615024886206,54.87865174579418],"type":"Point"}
}