{
  "type": "Feature",
  "properties": {
    "iso:country":"GB",
    "wof:name":"WA11 8LW",
    "wof:placetype":"postalcode"
},
  "geometry": {"coordinates":[-2.76926027712927,53.48883156401287],"type":"Point"}
}