{
  "type": "Feature",
  "properties": {
    "iso:country":"GB",
    "wof:name":"KA23 9QB",
    "wof:placetype":"postalcode"
},
  "geometry": {"coordinates":[-4.88484820734357,55.70885464644676],"type":"Point"}
}