{
  "type": "Feature",
  "properties": {
    "iso:country":"GB",
    "wof:name":"SN11 8DT",
    "wof:placetype":"postalcode"
},
  "geometry": {"coordinates":[-2.00019572019596,51.43758278832902],"type":"Point"}
}