{
  "type": "Feature",
  "properties": {
    "iso:country": "GB",
    "wof:name": "NE47 6AA",
    "wof:placetype": "postalcode"
  },
  "geometry": {"coordinates":[-2.244135,54.972656],"type":"Point"}
}
