{
  "type": "Feature",
  "properties": {
    "date:inception_lower": "1980-01-01",
    "date:inception_upper": "1980-01-01",
    "iso:country": "GB",
    "wof:name": "NE47 6AA",
    "wof:placetype": "postalcode"
  },
  "geometry": {"coordinates":[-2.244346,54.972554],"type":"Point"}
}
