{
  "type": "Feature",
  "properties": {
    "iso:country":"GB",
    "wof:name":"NE47 6AA",
    "wof:placetype":"postalcode"
},
  "geometry": {"coordinates":[-2.24413542247937,54.9726560517088],"type":"Point"}
}