{
  "type": "Feature",
  "properties": {
    "iso:country":"GB",
    "wof:name":"LL30 1LB",
    "wof:placetype":"postalcode"
},
  "geometry": {"coordinates":[-3.82794400076861,53.31136202495345],"type":"Point"}
}