{
  "type": "Feature",
  "properties": {
    "iso:country": "GB",
    "wof:name": "LL30 1LB",
    "wof:placetype": "postalcode"
  },
  "geometry": {"coordinates":[-3.827944,53.311362],"type":"Point"}
}
