{
  "type": "Feature",
  "properties": {
    "iso:country": "GB",
    "wof:name": "WS13 8RJ",
    "wof:placetype": "postalcode"
  },
  "geometry": {"coordinates":[-1.784962,52.694515],"type":"Point"}
}
