{
  "type": "Feature",
  "properties": {
    "iso:country":"GB",
    "wof:name":"WS11 1EZ",
    "wof:placetype":"postalcode"
},
  "geometry": {"coordinates":[-2.04665750786415,52.68399449880832],"type":"Point"}
}