{
  "type": "Feature",
  "properties": {
    "iso:country": "GB",
    "wof:name": "TF2 9FD",
    "wof:placetype": "postalcode"
  },
  "geometry": {"coordinates":[-2.414322,52.694201],"type":"Point"}
}
