{
  "type": "Feature",
  "properties": {
    "iso:country": "GB",
    "wof:name": "KY13 0PJ",
    "wof:placetype": "postalcode"
  },
  "geometry": {"coordinates":[-3.459495,56.206484],"type":"Point"}
}
