{
  "type": "Feature",
  "properties": {
    "iso:country":"GB",
    "wof:name":"HX3 7JX",
    "wof:placetype":"postalcode"
},
  "geometry": {"coordinates":[-1.8212258254992,53.75198699776288],"type":"Point"}
}