{
  "type": "Feature",
  "properties": {
    "iso:country": "GB",
    "wof:name": "HX3 7JX",
    "wof:placetype": "postalcode"
  },
  "geometry": {"coordinates":[-1.821226,53.751987],"type":"Point"}
}
