{
  "type": "Feature",
  "properties": {
    "iso:country":"GB",
    "wof:name":"HP1 2QX",
    "wof:placetype":"postalcode"
},
  "geometry": {"coordinates":[-0.50057851414639,51.76117769850709],"type":"Point"}
}