{
  "type": "Feature",
  "properties": {
    "iso:country":"GB",
    "wof:name":"TW9 3QF",
    "wof:placetype":"postalcode"
},
  "geometry": {"coordinates":[-0.28716305523319,51.47803768926025],"type":"Point"}
}