{
  "type": "Feature",
  "properties": {
    "date:inception_lower": "1992-05-01",
    "date:inception_upper": "1992-05-01",
    "iso:country": "GB",
    "wof:name": "PH26 3NA",
    "wof:placetype": "postalcode"
  },
  "geometry": {"coordinates":[-3.620561,57.32474],"type":"Point"}
}
