{
  "type": "Feature",
  "properties": {
    "iso:country": "GB",
    "wof:name": "PH26 3NA",
    "wof:placetype": "postalcode"
  },
  "geometry": {"coordinates":[-3.620561,57.32474],"type":"Point"}
}
