{
  "type": "Feature",
  "properties": {
    "iso:country":"GB",
    "wof:name":"PH26 3NA",
    "wof:placetype":"postalcode"
},
  "geometry": {"coordinates":[-3.61961193380984,57.32506321374743],"type":"Point"}
}