{
  "type": "Feature",
  "properties": {
    "iso:country": "GB",
    "wof:name": "WV8 1FD",
    "wof:placetype": "postalcode"
  },
  "geometry": {"coordinates":[-2.189153,52.633337],"type":"Point"}
}
