{
  "type": "Feature",
  "properties": {
    "iso:country": "GB",
    "wof:name": "BH20 7DR",
    "wof:placetype": "postalcode"
  },
  "geometry": {"coordinates":[-2.118616,50.760086],"type":"Point"}
}
