{
  "type": "Feature",
  "properties": {
    "iso:country":"GB",
    "wof:name":"BH20 7DR",
    "wof:placetype":"postalcode"
},
  "geometry": {"coordinates":[-2.11861603042108,50.76008556562567],"type":"Point"}
}