{
  "type": "Feature",
  "properties": {
    "iso:country":"GB",
    "wof:name":"AB55 6YJ",
    "wof:placetype":"postalcode"
},
  "geometry": {"coordinates":[-3.07372553757247,57.53833966525949],"type":"Point"}
}