{
  "type": "Feature",
  "properties": {
    "iso:country": "GB",
    "wof:name": "ST5 6LT",
    "wof:placetype": "postalcode"
  },
  "geometry": {"coordinates":[-2.272064,53.015652],"type":"Point"}
}
