{
  "type": "Feature",
  "properties": {
    "iso:country":"GB",
    "wof:name":"ST5 6LT",
    "wof:placetype":"postalcode"
},
  "geometry": {"coordinates":[-2.27206417225874,53.01565231820917],"type":"Point"}
}