{
  "type": "Feature",
  "properties": {
    "iso:country":"GB",
    "wof:name":"CV33 9RB",
    "wof:placetype":"postalcode"
},
  "geometry": {"coordinates":[-1.54927490210075,52.24944993468344],"type":"Point"}
}