{
  "type": "Feature",
  "properties": {
    "iso:country":"GB",
    "wof:name":"BB9 5LB",
    "wof:placetype":"postalcode"
},
  "geometry": {"coordinates":[-2.23727958387001,53.82124491713666],"type":"Point"}
}