{
  "type": "Feature",
  "properties": {
    "date:inception_lower": "1995-07-01",
    "date:inception_upper": "1995-07-01",
    "iso:country": "GB",
    "wof:name": "BB9 5LB",
    "wof:placetype": "postalcode"
  },
  "geometry": {"coordinates":[-2.23728,53.821245],"type":"Point"}
}
