{
  "type": "Feature",
  "properties": {
    "iso:country":"GB",
    "wof:name":"BN8 6AY",
    "wof:placetype":"postalcode"
},
  "geometry": {"coordinates":[0.12659995223147,50.86377492308146],"type":"Point"}
}