{
  "type": "Feature",
  "properties": {
    "date:inception_lower": "1980-01-01",
    "date:inception_upper": "1980-01-01",
    "iso:country": "GB",
    "wof:name": "BN8 6AY",
    "wof:placetype": "postalcode"
  },
  "geometry": {"coordinates":[0.1266,50.863775],"type":"Point"}
}
