{
  "type": "Feature",
  "properties": {
    "iso:country":"GB",
    "wof:name":"PO15 6AZ",
    "wof:placetype":"postalcode"
},
  "geometry": {"coordinates":[-1.20356274284289,50.86362346330144],"type":"Point"}
}