{
  "type": "Feature",
  "properties": {
    "iso:country":"GB",
    "wof:name":"B79 9HD",
    "wof:placetype":"postalcode"
},
  "geometry": {"coordinates":[-1.64862458833478,52.69416356822093],"type":"Point"}
}