{
  "type": "Feature",
  "properties": {
    "date:inception_lower": "1980-01-01",
    "date:inception_upper": "1980-01-01",
    "iso:country": "GB",
    "wof:name": "B79 9HD",
    "wof:placetype": "postalcode"
  },
  "geometry": {"coordinates":[-1.648625,52.694164],"type":"Point"}
}
