{
  "type": "Feature",
  "properties": {
    "date:inception_lower":"1980-01-01",
    "date:inception_upper":"1980-01-31",
    "iso:country":"GB",
    "wof:name":"BD24 0EL",
    "wof:placetype":"postalcode"
},
  "geometry": {"coordinates":[-2.303061,54.120406],"type":"Point"}
}