{
  "type": "Feature",
  "properties": {
    "iso:country": "GB",
    "wof:name": "BD24 0EL",
    "wof:placetype": "postalcode"
  },
  "geometry": {"coordinates":[-2.303061,54.120406],"type":"Point"}
}
