{
  "type": "Feature",
  "properties": {
    "iso:country":"GB",
    "wof:name":"EN7 6NJ",
    "wof:placetype":"postalcode"
},
  "geometry": {"coordinates":[-0.07046890176789,51.71966298201591],"type":"Point"}
}