{
  "type": "Feature",
  "properties": {
    "date:inception_lower": "1990-07-01",
    "date:inception_upper": "1990-07-01",
    "iso:country": "GB",
    "wof:name": "EN7 6NJ",
    "wof:placetype": "postalcode"
  },
  "geometry": {"coordinates":[-0.070469,51.719663],"type":"Point"}
}
