{
  "type": "Feature",
  "properties": {
    "iso:country":"GB",
    "wof:name":"PO38 2NF",
    "wof:placetype":"postalcode"
},
  "geometry": {"coordinates":[-1.2977942398692,50.57570308349033],"type":"Point"}
}