{
  "type": "Feature",
  "properties": {
    "date:inception_lower":"1980-01-01",
    "date:inception_upper":"1980-01-31",
    "iso:country":"GB",
    "wof:name":"PO38 2NF",
    "wof:placetype":"postalcode"
},
  "geometry": {"coordinates":[-1.299613,50.576224],"type":"Point"}
}