{
  "type": "Feature",
  "properties": {
    "date:inception_lower":"1980-01-01",
    "date:inception_upper":"1980-01-31",
    "iso:country":"GB",
    "wof:name":"GL1 3LN",
    "wof:placetype":"postalcode"
},
  "geometry": {"coordinates":[-2.229702,51.874134],"type":"Point"}
}