{
  "type": "Feature",
  "properties": {
    "date:inception_lower": "1993-08-01",
    "date:inception_upper": "1993-08-01",
    "iso:country": "GB",
    "wof:name": "BL8 2UF",
    "wof:placetype": "postalcode"
  },
  "geometry": {"coordinates":[-2.332531,53.592001],"type":"Point"}
}
