{
  "type": "Feature",
  "properties": {
    "iso:country":"GB",
    "wof:name":"SA14 8GE",
    "wof:placetype":"postalcode"
},
  "geometry": {"coordinates":[-4.0890938168365,51.68972208610848],"type":"Point"}
}