{
  "type": "Feature",
  "properties": {
    "iso:country":"GB",
    "wof:name":"PH16 5BJ",
    "wof:placetype":"postalcode"
},
  "geometry": {"coordinates":[-3.734254610957,56.7033715647125],"type":"Point"}
}