{
  "type": "Feature",
  "properties": {
    "iso:country": "GB",
    "wof:name": "EH3 8FF",
    "wof:placetype": "postalcode"
  },
  "geometry": {"coordinates":[-3.211711,55.944363],"type":"Point"}
}
