{
  "type": "Feature",
  "properties": {
    "iso:country":"GB",
    "wof:name":"EH3 8FF",
    "wof:placetype":"postalcode"
},
  "geometry": {"coordinates":[-3.21171116214322,55.94436321745018],"type":"Point"}
}