{
  "type": "Feature",
  "properties": {
    "date:inception_lower":"1991-01-01",
    "date:inception_upper":"1991-01-31",
    "iso:country":"GB",
    "wof:name":"DN15 8SJ",
    "wof:placetype":"postalcode"
},
  "geometry": {"coordinates":[-0.700121,53.622682],"type":"Point"}
}