{
  "type": "Feature",
  "properties": {
    "iso:country":"GB",
    "wof:name":"DN15 8SJ",
    "wof:placetype":"postalcode"
},
  "geometry": {"coordinates":[-0.70012080398893,53.62268237280703],"type":"Point"}
}