{
  "type": "Feature",
  "properties": {
    "iso:country": "GB",
    "wof:name": "DN15 8SJ",
    "wof:placetype": "postalcode"
  },
  "geometry": {"coordinates":[-0.700121,53.622682],"type":"Point"}
}
