{
  "type": "Feature",
  "properties": {
    "iso:country":"GB",
    "wof:name":"LD1 6SW",
    "wof:placetype":"postalcode"
},
  "geometry": {"coordinates":[-3.26442426319892,52.30967140670138],"type":"Point"}
}