{
  "type": "Feature",
  "properties": {
    "iso:country": "GB",
    "wof:name": "CH3 5EJ",
    "wof:placetype": "postalcode"
  },
  "geometry": {"coordinates":[-2.86326,53.191357],"type":"Point"}
}
