{
  "type": "Feature",
  "properties": {
    "iso:country":"GB",
    "wof:name":"WD25 0JD",
    "wof:placetype":"postalcode"
},
  "geometry": {"coordinates":[-0.39346595722902,51.70317637703423],"type":"Point"}
}