{
  "type": "Feature",
  "properties": {
    "date:inception_lower": "1980-01-01",
    "date:inception_upper": "1980-01-01",
    "iso:country": "GB",
    "wof:name": "OX15 4NS",
    "wof:placetype": "postalcode"
  },
  "geometry": {"coordinates":[-1.367159,52.024586],"type":"Point"}
}
