{
  "type": "Feature",
  "properties": {
    "iso:country":"GB",
    "wof:name":"SE15 6TL",
    "wof:placetype":"postalcode"
},
  "geometry": {"coordinates":[-0.06667618028749,51.48235222069403],"type":"Point"}
}