{
  "type": "Feature",
  "properties": {
    "iso:country": "GB",
    "wof:name": "M2 1AB",
    "wof:placetype": "postalcode"
  },
  "geometry": {"coordinates":[-2.241662,53.481581],"type":"Point"}
}
