{
  "type": "Feature",
  "properties": {
    "date:inception_lower": "2005-06-01",
    "date:inception_upper": "2005-06-01",
    "iso:country": "GB",
    "wof:name": "M2 1AB",
    "wof:placetype": "postalcode"
  },
  "geometry": {"coordinates":[-2.241662,53.481581],"type":"Point"}
}
