{
  "type": "Feature",
  "properties": {
    "iso:country": "GB",
    "wof:name": "DE22 3HN",
    "wof:placetype": "postalcode"
  },
  "geometry": {"coordinates":[-1.514106,52.913115],"type":"Point"}
}
