{
  "type": "Feature",
  "properties": {
    "date:inception_lower": "1980-01-01",
    "date:inception_upper": "1980-01-01",
    "iso:country": "GB",
    "wof:name": "CA21 2XW",
    "wof:placetype": "postalcode"
  },
  "geometry": {"coordinates":[-3.50991,54.439456],"type":"Point"}
}
