{
  "type": "Feature",
  "properties": {
    "iso:country":"GB",
    "wof:name":"GU34 4QB",
    "wof:placetype":"postalcode"
},
  "geometry": {"coordinates":[-0.85422239961716,51.15920866173965],"type":"Point"}
}