{
  "type": "Feature",
  "properties": {
    "iso:country": "GB",
    "wof:name": "GU34 4QB",
    "wof:placetype": "postalcode"
  },
  "geometry": {"coordinates":[-0.854222,51.159209],"type":"Point"}
}
