{
  "type": "Feature",
  "properties": {
    "date:inception_lower":"1980-01-01",
    "date:inception_upper":"1980-01-31",
    "iso:country":"GB",
    "wof:name":"GU34 4QB",
    "wof:placetype":"postalcode"
},
  "geometry": {"coordinates":[-0.854222,51.159209],"type":"Point"}
}