{
  "type": "Feature",
  "properties": {
    "iso:country":"GB",
    "wof:name":"SR1 3LF",
    "wof:placetype":"postalcode"
},
  "geometry": {"coordinates":[-1.38360903088403,54.90568625696935],"type":"Point"}
}