{
  "type": "Feature",
  "properties": {
    "iso:country":"GB",
    "wof:name":"TN30 6RW",
    "wof:placetype":"postalcode"
},
  "geometry": {"coordinates":[0.69567671584023,51.07250060952695],"type":"Point"}
}