{
  "type": "Feature",
  "properties": {
    "iso:country": "GB",
    "wof:name": "TN30 6RW",
    "wof:placetype": "postalcode"
  },
  "geometry": {"coordinates":[0.695677,51.072501],"type":"Point"}
}
