{
  "type": "Feature",
  "properties": {
    "date:inception_lower": "2023-03-01",
    "date:inception_upper": "2023-03-01",
    "iso:country": "GB",
    "wof:name": "ME12 9BW",
    "wof:placetype": "postalcode"
  },
  "geometry": {"coordinates":[0.764326,51.440702],"type":"Point"}
}
