{
  "type": "Feature",
  "properties": {
    "iso:country":"GB",
    "wof:name":"BD15 7PA",
    "wof:placetype":"postalcode"
},
  "geometry": {"coordinates":[-1.82034984578303,53.80096130601483],"type":"Point"}
}