{
  "type": "Feature",
  "properties": {
    "iso:country": "GB",
    "wof:name": "BD15 7PA",
    "wof:placetype": "postalcode"
  },
  "geometry": {"coordinates":[-1.82035,53.800961],"type":"Point"}
}
