{
  "type": "Feature",
  "properties": {
    "iso:country":"GB",
    "wof:name":"BN18 0SA",
    "wof:placetype":"postalcode"
},
  "geometry": {"coordinates":[-0.64398346353009,50.85390500224013],"type":"Point"}
}