{
  "type": "Feature",
  "properties": {
    "iso:country": "GB",
    "wof:name": "LA19 5YA",
    "wof:placetype": "postalcode"
  },
  "geometry": {"coordinates":[-3.412446,54.303227],"type":"Point"}
}
