{
  "type": "Feature",
  "properties": {
    "iso:country":"GB",
    "wof:name":"LA19 5YA",
    "wof:placetype":"postalcode"
},
  "geometry": {"coordinates":[-3.41244561577321,54.30322706137048],"type":"Point"}
}