{
  "type": "Feature",
  "properties": {
    "date:inception_lower": "1980-01-01",
    "date:inception_upper": "1980-01-01",
    "iso:country": "GB",
    "wof:name": "SK11 0LL",
    "wof:placetype": "postalcode"
  },
  "geometry": {"coordinates":[-2.124891,53.234025],"type":"Point"}
}
