{
  "type": "Feature",
  "properties": {
    "iso:country":"GB",
    "wof:name":"TN8 7PT",
    "wof:placetype":"postalcode"
},
  "geometry": {"coordinates":[0.10216110328447,51.20110328499236],"type":"Point"}
}