{
  "type": "Feature",
  "properties": {
    "iso:country":"GB",
    "wof:name":"E1W 2NB",
    "wof:placetype":"postalcode"
},
  "geometry": {"coordinates":[-0.06070164930337,51.50299955212419],"type":"Point"}
}