{
  "type": "Feature",
  "properties": {
    "date:inception_lower": "1999-12-01",
    "date:inception_upper": "1999-12-01",
    "iso:country": "GB",
    "wof:name": "E1W 2NB",
    "wof:placetype": "postalcode"
  },
  "geometry": {"coordinates":[-0.060702,51.503],"type":"Point"}
}
