{
  "type": "Feature",
  "properties": {
    "date:inception_lower": "2021-10-01",
    "date:inception_upper": "2021-10-01",
    "iso:country": "GB",
    "wof:name": "PL25 3GP",
    "wof:placetype": "postalcode"
  },
  "geometry": {"coordinates":[-4.760291,50.344569],"type":"Point"}
}
