{
  "type": "Feature",
  "properties": {
    "iso:country":"GB",
    "wof:name":"DA14 6PA",
    "wof:placetype":"postalcode"
},
  "geometry": {"coordinates":[0.0941511983719,51.42780907330875],"type":"Point"}
}