{
  "type": "Feature",
  "properties": {
    "date:inception_lower":"1981-06-01",
    "date:inception_upper":"1981-06-30",
    "iso:country":"GB",
    "wof:name":"PL12 6EQ",
    "wof:placetype":"postalcode"
},
  "geometry": {"coordinates":[-4.222856,50.411658],"type":"Point"}
}