{
  "type": "Feature",
  "properties": {
    "iso:country":"GB",
    "wof:name":"PL12 6EQ",
    "wof:placetype":"postalcode"
},
  "geometry": {"coordinates":[-4.22335982294616,50.4116525262485],"type":"Point"}
}