{
  "type": "Feature",
  "properties": {
    "date:inception_lower": "1995-07-01",
    "date:inception_upper": "1995-07-01",
    "iso:country": "GB",
    "wof:name": "SS7 1SE",
    "wof:placetype": "postalcode"
  },
  "geometry": {"coordinates":[0.594766,51.559558],"type":"Point"}
}
