{
  "type": "Feature",
  "properties": {
    "iso:country":"GB",
    "wof:name":"SS7 1SE",
    "wof:placetype":"postalcode"
},
  "geometry": {"coordinates":[0.59476606205395,51.55955784760491],"type":"Point"}
}