{
  "type": "Feature",
  "properties": {
    "iso:country":"GB",
    "wof:name":"NP8 1SB",
    "wof:placetype":"postalcode"
},
  "geometry": {"coordinates":[-3.20835918795144,51.8877698905892],"type":"Point"}
}