{
  "type": "Feature",
  "properties": {
    "iso:country":"GB",
    "wof:name":"WN7 3BN",
    "wof:placetype":"postalcode"
},
  "geometry": {"coordinates":[-2.49769945384712,53.49108040278733],"type":"Point"}
}