{
  "type": "Feature",
  "properties": {
    "iso:country": "GB",
    "wof:name": "TR14 7SU",
    "wof:placetype": "postalcode"
  },
  "geometry": {"coordinates":[-5.287158,50.208314],"type":"Point"}
}
