{
  "type": "Feature",
  "properties": {
    "date:inception_lower":"1991-09-01",
    "date:inception_upper":"1991-09-30",
    "iso:country":"GB",
    "wof:name":"TR14 7SU",
    "wof:placetype":"postalcode"
},
  "geometry": {"coordinates":[-5.287158,50.208314],"type":"Point"}
}