{
  "type": "Feature",
  "properties": {
    "iso:country":"GB",
    "wof:name":"TR14 7SU",
    "wof:placetype":"postalcode"
},
  "geometry": {"coordinates":[-5.2871575684676,50.20831433870782],"type":"Point"}
}