{
  "type": "Feature",
  "properties": {
    "iso:country":"GB",
    "wof:name":"HP19 7SR",
    "wof:placetype":"postalcode"
},
  "geometry": {"coordinates":[-0.83287282083383,51.81252910939291],"type":"Point"}
}