{
  "type": "Feature",
  "properties": {
    "date:inception_lower": "1996-06-01",
    "date:inception_upper": "1996-06-01",
    "iso:country": "GB",
    "wof:name": "AB16 7YX",
    "wof:placetype": "postalcode"
  },
  "geometry": {"coordinates":[-2.145224,57.170319],"type":"Point"}
}
