{
  "type": "Feature",
  "properties": {
    "iso:country": "GB",
    "wof:name": "SA42 0XG",
    "wof:placetype": "postalcode"
  },
  "geometry": {"coordinates":[-4.907366,52.009155],"type":"Point"}
}
