{
  "type": "Feature",
  "properties": {
    "iso:country":"GB",
    "wof:name":"SA42 0XG",
    "wof:placetype":"postalcode"
},
  "geometry": {"coordinates":[-4.90733585544713,52.00911250313523],"type":"Point"}
}