{
  "type": "Feature",
  "properties": {
    "iso:country":"GB",
    "wof:name":"NN8 3SE",
    "wof:placetype":"postalcode"
},
  "geometry": {"coordinates":[-0.71940465129745,52.29866897071175],"type":"Point"}
}