{
  "type": "Feature",
  "properties": {
    "iso:country":"GB",
    "wof:name":"DY3 1LX",
    "wof:placetype":"postalcode"
},
  "geometry": {"coordinates":[-2.11334210649958,52.54685557861672],"type":"Point"}
}