{
  "type": "Feature",
  "properties": {
    "iso:country": "GB",
    "wof:name": "GU47 0FL",
    "wof:placetype": "postalcode"
  },
  "geometry": {"coordinates":[-0.78309,51.34009],"type":"Point"}
}
