{
  "type": "Feature",
  "properties": {
    "iso:country":"GB",
    "wof:name":"LE4 2LB",
    "wof:placetype":"postalcode"
},
  "geometry": {"coordinates":[-1.15149401556662,52.67001021843989],"type":"Point"}
}