{
  "type": "Feature",
  "properties": {
    "iso:country":"GB",
    "wof:name":"L4 9SL",
    "wof:placetype":"postalcode"
},
  "geometry": {"coordinates":[-2.94197263874563,53.44218328602084],"type":"Point"}
}