{
  "type": "Feature",
  "properties": {
    "iso:country":"GB",
    "wof:name":"CV7 7DN",
    "wof:placetype":"postalcode"
},
  "geometry": {"coordinates":[-1.65044514066299,52.39128105856422],"type":"Point"}
}