{
  "type": "Feature",
  "properties": {
    "iso:country": "GB",
    "wof:name": "CV7 7DN",
    "wof:placetype": "postalcode"
  },
  "geometry": {"coordinates":[-1.650436,52.391296],"type":"Point"}
}
