{
  "type": "Feature",
  "properties": {
    "date:inception_lower": "1980-01-01",
    "date:inception_upper": "1980-01-01",
    "iso:country": "GB",
    "wof:name": "CV7 7DN",
    "wof:placetype": "postalcode"
  },
  "geometry": {"coordinates":[-1.650449,52.391494],"type":"Point"}
}
