{
  "type": "Feature",
  "properties": {
    "iso:country":"GB",
    "wof:name":"DN10 6RT",
    "wof:placetype":"postalcode"
},
  "geometry": {"coordinates":[-1.02821280450721,53.43042494025934],"type":"Point"}
}