{
  "type": "Feature",
  "properties": {
    "iso:country": "GB",
    "wof:name": "DN10 6RT",
    "wof:placetype": "postalcode"
  },
  "geometry": {"coordinates":[-1.028213,53.430425],"type":"Point"}
}
