{
  "type": "Feature",
  "properties": {
    "iso:country": "GB",
    "wof:name": "G31 3RZ",
    "wof:placetype": "postalcode"
  },
  "geometry": {"coordinates":[-4.200857,55.86068],"type":"Point"}
}
