{
  "type": "Feature",
  "properties": {
    "date:inception_lower": "1992-08-01",
    "date:inception_upper": "1992-08-01",
    "iso:country": "GB",
    "wof:name": "DE56 1YA",
    "wof:placetype": "postalcode"
  },
  "geometry": {"coordinates":[-1.486271,53.020905],"type":"Point"}
}
