{
  "type": "Feature",
  "properties": {
    "date:inception_lower":"2005-01-01",
    "date:inception_upper":"2005-01-31",
    "iso:country":"GB",
    "wof:name":"RH16 4TW",
    "wof:placetype":"postalcode"
},
  "geometry": {"coordinates":[-0.114931,50.9852],"type":"Point"}
}