{
  "type": "Feature",
  "properties": {
    "iso:country":"GB",
    "wof:name":"GL14 3DB",
    "wof:placetype":"postalcode"
},
  "geometry": {"coordinates":[-2.49813244114452,51.81631788913709],"type":"Point"}
}