{
  "type": "Feature",
  "properties": {
    "iso:country": "GB",
    "wof:name": "DL3 0UW",
    "wof:placetype": "postalcode"
  },
  "geometry": {"coordinates":[-1.574098,54.548502],"type":"Point"}
}
