{
  "type": "Feature",
  "properties": {
    "date:inception_lower": "2020-06-01",
    "date:inception_upper": "2020-06-01",
    "iso:country": "GB",
    "wof:name": "PE12 7FF",
    "wof:placetype": "postalcode"
  },
  "geometry": {"coordinates":[-0.005418,52.800627],"type":"Point"}
}
