{
  "type": "Feature",
  "properties": {
    "iso:country":"GB",
    "wof:name":"TS18 5NP",
    "wof:placetype":"postalcode"
},
  "geometry": {"coordinates":[-1.35920346329041,54.55505014572427],"type":"Point"}
}