{
  "type": "Feature",
  "properties": {
    "iso:country": "GB",
    "wof:name": "HX4 9AL",
    "wof:placetype": "postalcode"
  },
  "geometry": {"coordinates":[-1.86794,53.678027],"type":"Point"}
}
