{
  "type": "Feature",
  "properties": {
    "iso:country":"GB",
    "wof:name":"HX4 9AL",
    "wof:placetype":"postalcode"
},
  "geometry": {"coordinates":[-1.86796874394012,53.6780575578655],"type":"Point"}
}