{
  "type": "Feature",
  "properties": {
    "iso:country":"GB",
    "wof:name":"TW13 4BZ",
    "wof:placetype":"postalcode"
},
  "geometry": {"coordinates":[-0.40959932013382,51.44773158109291],"type":"Point"}
}