{
  "type": "Feature",
  "properties": {
    "iso:country":"GB",
    "wof:name":"N11 3FT",
    "wof:placetype":"postalcode"
},
  "geometry": {"coordinates":[-0.14787176372474,51.61281241046095],"type":"Point"}
}