{
  "type": "Feature",
  "properties": {
    "iso:country":"GB",
    "wof:name":"GU7 3RB",
    "wof:placetype":"postalcode"
},
  "geometry": {"coordinates":[-0.61108554020347,51.20062008102356],"type":"Point"}
}