{
  "type": "Feature",
  "properties": {
    "iso:country": "GB",
    "wof:name": "GU7 3RB",
    "wof:placetype": "postalcode"
  },
  "geometry": {"coordinates":[-0.611085,51.20062],"type":"Point"}
}
