{
  "type": "Feature",
  "properties": {
    "iso:country": "GB",
    "wof:name": "LN4 1UA",
    "wof:placetype": "postalcode"
  },
  "geometry": {"coordinates":[-0.464847,53.197445],"type":"Point"}
}
