{
  "type": "Feature",
  "properties": {
    "date:inception_lower": "1980-01-01",
    "date:inception_upper": "1980-01-01",
    "iso:country": "GB",
    "wof:name": "LN4 1UA",
    "wof:placetype": "postalcode"
  },
  "geometry": {"coordinates":[-0.464847,53.197445],"type":"Point"}
}
