{
  "type": "Feature",
  "properties": {
    "iso:country":"GB",
    "wof:name":"LN4 1UA",
    "wof:placetype":"postalcode"
},
  "geometry": {"coordinates":[-0.46484670332925,53.19744478357746],"type":"Point"}
}