{
  "type": "Feature",
  "properties": {
    "iso:country":"GB",
    "wof:name":"WD4 8PU",
    "wof:placetype":"postalcode"
},
  "geometry": {"coordinates":[-0.43179189805517,51.69383903535645],"type":"Point"}
}