{
  "type": "Feature",
  "properties": {
    "iso:country": "GB",
    "wof:name": "WD4 8PU",
    "wof:placetype": "postalcode"
  },
  "geometry": {"coordinates":[-0.43161,51.693861],"type":"Point"}
}
