{
  "type": "Feature",
  "properties": {
    "iso:country":"GB",
    "wof:name":"NE3 1QD",
    "wof:placetype":"postalcode"
},
  "geometry": {"coordinates":[-1.60429525185476,55.00699059275382],"type":"Point"}
}