{
  "type": "Feature",
  "properties": {
    "date:inception_lower": "1980-01-01",
    "date:inception_upper": "1980-01-01",
    "iso:country": "GB",
    "wof:name": "NE3 1QD",
    "wof:placetype": "postalcode"
  },
  "geometry": {"coordinates":[-1.60431,55.006998],"type":"Point"}
}
