{
  "type": "Feature",
  "properties": {
    "iso:country":"GB",
    "wof:name":"SE20 8SN",
    "wof:placetype":"postalcode"
},
  "geometry": {"coordinates":[-0.06854936311705,51.40593627413798],"type":"Point"}
}