{
  "type": "Feature",
  "properties": {
    "date:inception_lower": "2019-06-01",
    "date:inception_upper": "2019-06-01",
    "iso:country": "GB",
    "wof:name": "PH36 4LF",
    "wof:placetype": "postalcode"
  },
  "geometry": {"coordinates":[-6.094961,56.690786],"type":"Point"}
}
