{
  "type": "Feature",
  "properties": {
    "iso:country": "GB",
    "wof:name": "PH36 4LF",
    "wof:placetype": "postalcode"
  },
  "geometry": {"coordinates":[-6.094961,56.690786],"type":"Point"}
}
