{
  "type": "Feature",
  "properties": {
    "iso:country":"GB",
    "wof:name":"RG5 3DQ",
    "wof:placetype":"postalcode"
},
  "geometry": {"coordinates":[-0.90947830633399,51.45405769556656],"type":"Point"}
}