{
  "type": "Feature",
  "properties": {
    "iso:country": "GB",
    "wof:name": "RG5 3DQ",
    "wof:placetype": "postalcode"
  },
  "geometry": {"coordinates":[-0.909373,51.454058],"type":"Point"}
}
