{
  "type": "Feature",
  "properties": {
    "iso:country":"GB",
    "wof:name":"WA6 9AN",
    "wof:placetype":"postalcode"
},
  "geometry": {"coordinates":[-2.75473389375932,53.26545325719749],"type":"Point"}
}