{
  "type": "Feature",
  "properties": {
    "iso:country":"GB",
    "wof:name":"EN6 2LT",
    "wof:placetype":"postalcode"
},
  "geometry": {"coordinates":[-0.19391579068196,51.69286849952961],"type":"Point"}
}