{
  "type": "Feature",
  "properties": {
    "iso:country":"GB",
    "wof:name":"M27 6UN",
    "wof:placetype":"postalcode"
},
  "geometry": {"coordinates":[-2.34489310720588,53.51451290145013],"type":"Point"}
}