{
  "type": "Feature",
  "properties": {
    "iso:country":"GB",
    "wof:name":"G66 8BJ",
    "wof:placetype":"postalcode"
},
  "geometry": {"coordinates":[-4.16084881505066,55.96264360243349],"type":"Point"}
}