{
  "type": "Feature",
  "properties": {
    "iso:country": "GB",
    "wof:name": "DA12 2SA",
    "wof:placetype": "postalcode"
  },
  "geometry": {"coordinates":[0.382474,51.439696],"type":"Point"}
}
