{
  "type": "Feature",
  "properties": {
    "iso:country":"GB",
    "wof:name":"DA12 2SA",
    "wof:placetype":"postalcode"
},
  "geometry": {"coordinates":[0.38244549374213,51.43972240160248],"type":"Point"}
}