{
  "type": "Feature",
  "properties": {
    "iso:country":"GB",
    "wof:name":"HD3 3HR",
    "wof:placetype":"postalcode"
},
  "geometry": {"coordinates":[-1.82611515036842,53.6548147325671],"type":"Point"}
}