{
  "type": "Feature",
  "properties": {
    "iso:country":"GB",
    "wof:name":"KY2 5BQ",
    "wof:placetype":"postalcode"
},
  "geometry": {"coordinates":[-3.16015750016549,56.12153786396891],"type":"Point"}
}