{
  "type": "Feature",
  "properties": {
    "date:inception_lower":"1980-01-01",
    "date:inception_upper":"1980-01-31",
    "iso:country":"GB",
    "wof:name":"KY2 5BQ",
    "wof:placetype":"postalcode"
},
  "geometry": {"coordinates":[-3.160157,56.121538],"type":"Point"}
}