{
  "type": "Feature",
  "properties": {
    "iso:country": "GB",
    "wof:name": "KY2 5BQ",
    "wof:placetype": "postalcode"
  },
  "geometry": {"coordinates":[-3.160157,56.121538],"type":"Point"}
}
