{
  "type": "Feature",
  "properties": {
    "date:inception_lower": "2018-12-01",
    "date:inception_upper": "2018-12-01",
    "iso:country": "GB",
    "wof:name": "CA10 1DN",
    "wof:placetype": "postalcode"
  },
  "geometry": {"coordinates":[-2.60222,54.659807],"type":"Point"}
}
