{
  "type": "Feature",
  "properties": {
    "iso:country": "GB",
    "wof:name": "CA10 1DN",
    "wof:placetype": "postalcode"
  },
  "geometry": {"coordinates":[-2.60222,54.659807],"type":"Point"}
}
