{
  "type": "Feature",
  "properties": {
    "iso:country":"GB",
    "wof:name":"BN1 8GE",
    "wof:placetype":"postalcode"
},
  "geometry": {"coordinates":[-0.1228435045062,50.86239732736662],"type":"Point"}
}