{
  "type": "Feature",
  "properties": {
    "date:inception_lower": "1980-01-01",
    "date:inception_upper": "1980-01-01",
    "iso:country": "GB",
    "wof:name": "CT9 3XA",
    "wof:placetype": "postalcode"
  },
  "geometry": {"coordinates":[1.41051,51.378393],"type":"Point"}
}
