{
  "type": "Feature",
  "properties": {
    "iso:country":"GB",
    "wof:name":"CT9 3XA",
    "wof:placetype":"postalcode"
},
  "geometry": {"coordinates":[1.41050993276286,51.37839280250458],"type":"Point"}
}