{
  "type": "Feature",
  "properties": {
    "iso:country": "GB",
    "wof:name": "BA2 6QS",
    "wof:placetype": "postalcode"
  },
  "geometry": {"coordinates":[-2.346298,51.390728],"type":"Point"}
}
