{
  "type": "Feature",
  "properties": {
    "iso:country":"GB",
    "wof:name":"BA2 6QS",
    "wof:placetype":"postalcode"
},
  "geometry": {"coordinates":[-2.34629770311779,51.3907276894755],"type":"Point"}
}