{
  "type": "Feature",
  "properties": {
    "iso:country":"GB",
    "wof:name":"NR25 6SU",
    "wof:placetype":"postalcode"
},
  "geometry": {"coordinates":[1.08209190182582,52.89896864209233],"type":"Point"}
}