{
  "type": "Feature",
  "properties": {
    "date:inception_lower": "1980-01-01",
    "date:inception_upper": "1980-01-01",
    "iso:country": "GB",
    "wof:name": "S73 0PZ",
    "wof:placetype": "postalcode"
  },
  "geometry": {"coordinates":[-1.410172,53.511041],"type":"Point"}
}
