{
  "type": "Feature",
  "properties": {
    "iso:country":"GB",
    "wof:name":"LS29 7SG",
    "wof:placetype":"postalcode"
},
  "geometry": {"coordinates":[-1.75734767602297,53.90765367934382],"type":"Point"}
}