{
  "type": "Feature",
  "properties": {
    "date:inception_lower": "2002-06-01",
    "date:inception_upper": "2002-06-01",
    "iso:country": "GB",
    "wof:name": "LS29 7SG",
    "wof:placetype": "postalcode"
  },
  "geometry": {"coordinates":[-1.757348,53.907654],"type":"Point"}
}
