{
  "type": "Feature",
  "properties": {
    "iso:country": "GB",
    "wof:name": "SY8 2BZ",
    "wof:placetype": "postalcode"
  },
  "geometry": {"coordinates":[-2.752011,52.422227],"type":"Point"}
}
