{
  "type": "Feature",
  "properties": {
    "date:inception_lower":"1980-01-01",
    "date:inception_upper":"1980-01-31",
    "iso:country":"GB",
    "wof:name":"SY8 2BZ",
    "wof:placetype":"postalcode"
},
  "geometry": {"coordinates":[-2.752011,52.422227],"type":"Point"}
}