{
  "type": "Feature",
  "properties": {
    "iso:country":"GB",
    "wof:name":"SY8 2BZ",
    "wof:placetype":"postalcode"
},
  "geometry": {"coordinates":[-2.75201133414747,52.42222692655338],"type":"Point"}
}