{
  "type": "Feature",
  "properties": {
    "iso:country": "GB",
    "wof:name": "SK9 7HP",
    "wof:placetype": "postalcode"
  },
  "geometry": {"coordinates":[-2.230431,53.303142],"type":"Point"}
}
