{
  "type": "Feature",
  "properties": {
    "iso:country":"GB",
    "wof:name":"SK9 7HP",
    "wof:placetype":"postalcode"
},
  "geometry": {"coordinates":[-2.2304482260738,53.30316175622627],"type":"Point"}
}