{
  "type": "Feature",
  "properties": {
    "date:inception_lower": "1997-12-01",
    "date:inception_upper": "1997-12-01",
    "iso:country": "GB",
    "wof:name": "BS30 6RQ",
    "wof:placetype": "postalcode"
  },
  "geometry": {"coordinates":[-2.476086,51.435995],"type":"Point"}
}
