{
  "type": "Feature",
  "properties": {
    "iso:country":"GB",
    "wof:name":"BS30 6RQ",
    "wof:placetype":"postalcode"
},
  "geometry": {"coordinates":[-2.47608621815765,51.43599463956514],"type":"Point"}
}