{
  "type": "Feature",
  "properties": {
    "iso:country": "GB",
    "wof:name": "ML11 7FB",
    "wof:placetype": "postalcode"
  },
  "geometry": {"coordinates":[-3.761627,55.680396],"type":"Point"}
}
