{
  "type": "Feature",
  "properties": {
    "iso:country":"GB",
    "wof:name":"SK6 4PQ",
    "wof:placetype":"postalcode"
},
  "geometry": {"coordinates":[-2.08499867381448,53.41653909338492],"type":"Point"}
}