{
  "type": "Feature",
  "properties": {
    "iso:country":"GB",
    "wof:name":"SY2 5PF",
    "wof:placetype":"postalcode"
},
  "geometry": {"coordinates":[-2.72841683050525,52.70663904206601],"type":"Point"}
}