{
  "type": "Feature",
  "properties": {
    "iso:country":"GB",
    "wof:name":"LL14 5DE",
    "wof:placetype":"postalcode"
},
  "geometry": {"coordinates":[-3.05041135698513,52.92646995548125],"type":"Point"}
}