{
  "type": "Feature",
  "properties": {
    "date:inception_lower": "1980-01-01",
    "date:inception_upper": "1980-01-01",
    "iso:country": "GB",
    "wof:name": "LL14 5DE",
    "wof:placetype": "postalcode"
  },
  "geometry": {"coordinates":[-3.050411,52.92647],"type":"Point"}
}
