{
  "type": "Feature",
  "properties": {
    "iso:country": "GB",
    "wof:name": "LL14 5DE",
    "wof:placetype": "postalcode"
  },
  "geometry": {"coordinates":[-3.050411,52.92647],"type":"Point"}
}
