{
  "type": "Feature",
  "properties": {
    "date:inception_lower": "2022-12-01",
    "date:inception_upper": "2022-12-01",
    "iso:country": "GB",
    "wof:name": "BS20 7SW",
    "wof:placetype": "postalcode"
  },
  "geometry": {"coordinates":[-2.761545,51.486431],"type":"Point"}
}
