{
  "type": "Feature",
  "properties": {
    "date:inception_lower":"1980-01-01",
    "date:inception_upper":"1980-01-31",
    "iso:country":"GB",
    "wof:name":"KA3 6ET",
    "wof:placetype":"postalcode"
},
  "geometry": {"coordinates":[-4.388995,55.687412],"type":"Point"}
}