{
  "type": "Feature",
  "properties": {
    "iso:country":"GB",
    "wof:name":"KA3 6ET",
    "wof:placetype":"postalcode"
},
  "geometry": {"coordinates":[-4.38899461552168,55.68741158400984],"type":"Point"}
}