{
  "type": "Feature",
  "properties": {
    "date:inception_lower":"1986-07-01",
    "date:inception_upper":"1986-07-31",
    "iso:country":"GB",
    "wof:name":"RM17 5QU",
    "wof:placetype":"postalcode"
},
  "geometry": {"coordinates":[0.338288,51.483195],"type":"Point"}
}