{
  "type": "Feature",
  "properties": {
    "iso:country":"GB",
    "wof:name":"LN1 1JT",
    "wof:placetype":"postalcode"
},
  "geometry": {"coordinates":[-0.54148668852679,53.2311748463106],"type":"Point"}
}