{
  "type": "Feature",
  "properties": {
    "iso:country":"GB",
    "wof:name":"DT6 6EW",
    "wof:placetype":"postalcode"
},
  "geometry": {"coordinates":[-2.85492384870345,50.74179491052978],"type":"Point"}
}