{
  "type": "Feature",
  "properties": {
    "date:inception_lower":"1980-01-01",
    "date:inception_upper":"1980-01-31",
    "iso:country":"GB",
    "wof:name":"CM5 0EB",
    "wof:placetype":"postalcode"
},
  "geometry": {"coordinates":[0.186864,51.758373],"type":"Point"}
}