{
  "type": "Feature",
  "properties": {
    "iso:country":"GB",
    "wof:name":"CM5 0EB",
    "wof:placetype":"postalcode"
},
  "geometry": {"coordinates":[0.18686414608259,51.75837302615852],"type":"Point"}
}