{
  "type": "Feature",
  "properties": {
    "iso:country": "GB",
    "wof:name": "WV3 9JG",
    "wof:placetype": "postalcode"
  },
  "geometry": {"coordinates":[-2.157356,52.584335],"type":"Point"}
}
