{
  "type": "Feature",
  "properties": {
    "iso:country":"GB",
    "wof:name":"KA13 7JS",
    "wof:placetype":"postalcode"
},
  "geometry": {"coordinates":[-4.68639222926815,55.65524702713012],"type":"Point"}
}