{
  "type": "Feature",
  "properties": {
    "date:inception_lower": "1980-01-01",
    "date:inception_upper": "1980-01-01",
    "iso:country": "GB",
    "wof:name": "ML10 6JS",
    "wof:placetype": "postalcode"
  },
  "geometry": {"coordinates":[-4.062607,55.681657],"type":"Point"}
}
