{
  "type": "Feature",
  "properties": {
    "iso:country": "GB",
    "wof:name": "SK1 3NW",
    "wof:placetype": "postalcode"
  },
  "geometry": {"coordinates":[-2.157441,53.404276],"type":"Point"}
}
