{
  "type": "Feature",
  "properties": {
    "date:inception_lower":"2018-09-01",
    "date:inception_upper":"2018-09-30",
    "iso:country":"GB",
    "wof:name":"SK1 3NW",
    "wof:placetype":"postalcode"
},
  "geometry": {"coordinates":[-2.157441,53.404276],"type":"Point"}
}