{
  "type": "Feature",
  "properties": {
    "iso:country": "GB",
    "wof:name": "TF8 7LR",
    "wof:placetype": "postalcode"
  },
  "geometry": {"coordinates":[-2.457023,52.620658],"type":"Point"}
}
