{
  "type": "Feature",
  "properties": {
    "iso:country":"GB",
    "wof:name":"TF8 7LR",
    "wof:placetype":"postalcode"
},
  "geometry": {"coordinates":[-2.45686158633475,52.62057160192906],"type":"Point"}
}