{
  "type": "Feature",
  "properties": {
    "date:inception_lower": "2000-12-01",
    "date:inception_upper": "2000-12-01",
    "iso:country": "GB",
    "wof:name": "CR2 6JW",
    "wof:placetype": "postalcode"
  },
  "geometry": {"coordinates":[-0.105931,51.364227],"type":"Point"}
}
