{
  "type": "Feature",
  "properties": {
    "iso:country": "GB",
    "wof:name": "CR2 6JW",
    "wof:placetype": "postalcode"
  },
  "geometry": {"coordinates":[-0.105931,51.364227],"type":"Point"}
}
