{
  "type": "Feature",
  "properties": {
    "iso:country":"GB",
    "wof:name":"CR2 6JW",
    "wof:placetype":"postalcode"
},
  "geometry": {"coordinates":[-0.10593061359958,51.36422668633923],"type":"Point"}
}