{
  "type": "Feature",
  "properties": {
    "date:inception_lower": "2023-11-01",
    "date:inception_upper": "2023-11-01",
    "iso:country": "GB",
    "wof:name": "CH66 4BW",
    "wof:placetype": "postalcode"
  },
  "geometry": {"coordinates":[-2.94923,53.274614],"type":"Point"}
}
