{
  "type": "Feature",
  "properties": {
    "date:inception_lower": "1980-01-01",
    "date:inception_upper": "1980-01-01",
    "iso:country": "GB",
    "wof:name": "CR0 4EE",
    "wof:placetype": "postalcode"
  },
  "geometry": {"coordinates":[-0.111176,51.36138],"type":"Point"}
}
