{
  "type": "Feature",
  "properties": {
    "iso:country":"GB",
    "wof:name":"SG5 3JU",
    "wof:placetype":"postalcode"
},
  "geometry": {"coordinates":[-0.36821824421098,51.96000320678732],"type":"Point"}
}