{
  "type": "Feature",
  "properties": {
    "iso:country": "GB",
    "wof:name": "SG5 3JU",
    "wof:placetype": "postalcode"
  },
  "geometry": {"coordinates":[-0.368225,51.959914],"type":"Point"}
}
