{
  "type": "Feature",
  "properties": {
    "date:inception_lower": "1990-02-01",
    "date:inception_upper": "1990-02-01",
    "iso:country": "GB",
    "wof:name": "SK11 9SU",
    "wof:placetype": "postalcode"
  },
  "geometry": {"coordinates":[-2.277256,53.273831],"type":"Point"}
}
