{
  "type": "Feature",
  "properties": {
    "iso:country": "GB",
    "wof:name": "YO61 1RL",
    "wof:placetype": "postalcode"
  },
  "geometry": {"coordinates":[-1.238412,54.086032],"type":"Point"}
}
