{
  "type": "Feature",
  "properties": {
    "iso:country":"GB",
    "wof:name":"YO61 1RL",
    "wof:placetype":"postalcode"
},
  "geometry": {"coordinates":[-1.23838878516034,54.086015654066],"type":"Point"}
}