{
  "type": "Feature",
  "properties": {
    "date:inception_lower": "1998-06-01",
    "date:inception_upper": "1998-06-01",
    "iso:country": "GB",
    "wof:name": "YO61 1RL",
    "wof:placetype": "postalcode"
  },
  "geometry": {"coordinates":[-1.238412,54.086032],"type":"Point"}
}
