{
  "type": "Feature",
  "properties": {
    "iso:country": "GB",
    "wof:name": "CB24 5NQ",
    "wof:placetype": "postalcode"
  },
  "geometry": {"coordinates":[0.015568,52.314558],"type":"Point"}
}
