{
  "type": "Feature",
  "properties": {
    "iso:country":"GB",
    "wof:name":"SN12 7JT",
    "wof:placetype":"postalcode"
},
  "geometry": {"coordinates":[-2.12331460344485,51.37857765243533],"type":"Point"}
}