{
  "type": "Feature",
  "properties": {
    "date:inception_lower":"1980-01-01",
    "date:inception_upper":"1980-01-31",
    "iso:country":"GB",
    "wof:name":"SN12 7JT",
    "wof:placetype":"postalcode"
},
  "geometry": {"coordinates":[-2.123315,51.378578],"type":"Point"}
}