{
  "type": "Feature",
  "properties": {
    "iso:country": "GB",
    "wof:name": "DY11 6SQ",
    "wof:placetype": "postalcode"
  },
  "geometry": {"coordinates":[-2.259333,52.384347],"type":"Point"}
}
