{
  "type": "Feature",
  "properties": {
    "iso:country":"GB",
    "wof:name":"NN8 5AA",
    "wof:placetype":"postalcode"
},
  "geometry": {"coordinates":[-0.70219637181474,52.30490958479648],"type":"Point"}
}