{
  "type": "Feature",
  "properties": {
    "iso:country": "GB",
    "wof:name": "NN8 5AA",
    "wof:placetype": "postalcode"
  },
  "geometry": {"coordinates":[-0.702196,52.30491],"type":"Point"}
}
