{
  "type": "Feature",
  "properties": {
    "date:inception_lower": "1991-09-01",
    "date:inception_upper": "1991-09-01",
    "iso:country": "GB",
    "wof:name": "NN8 5AA",
    "wof:placetype": "postalcode"
  },
  "geometry": {"coordinates":[-0.702196,52.30491],"type":"Point"}
}
