{
  "type": "Feature",
  "properties": {
    "iso:country": "GB",
    "wof:name": "CA12 4TB",
    "wof:placetype": "postalcode"
  },
  "geometry": {"coordinates":[-3.074388,54.615709],"type":"Point"}
}
