{
  "type": "Feature",
  "properties": {
    "iso:country": "GB",
    "wof:name": "CH64 9QZ",
    "wof:placetype": "postalcode"
  },
  "geometry": {"coordinates":[-3.048535,53.288032],"type":"Point"}
}
