{
  "type": "Feature",
  "properties": {
    "date:inception_lower": "2016-09-01",
    "date:inception_upper": "2016-09-01",
    "iso:country": "GB",
    "wof:name": "NR14 7GT",
    "wof:placetype": "postalcode"
  },
  "geometry": {"coordinates":[1.341451,52.572376],"type":"Point"}
}
