{
  "type": "Feature",
  "properties": {
    "iso:country": "GB",
    "wof:name": "CB8 9DG",
    "wof:placetype": "postalcode"
  },
  "geometry": {"coordinates":[0.464245,52.219279],"type":"Point"}
}
