{
  "type": "Feature",
  "properties": {
    "iso:country":"GB",
    "wof:name":"YO11 3DE",
    "wof:placetype":"postalcode"
},
  "geometry": {"coordinates":[-0.41237898086041,54.24077904110838],"type":"Point"}
}