{
  "type": "Feature",
  "properties": {
    "date:inception_lower": "1980-01-01",
    "date:inception_upper": "1980-01-01",
    "iso:country": "GB",
    "wof:name": "YO11 3DE",
    "wof:placetype": "postalcode"
  },
  "geometry": {"coordinates":[-0.412379,54.240779],"type":"Point"}
}
