{
  "type": "Feature",
  "properties": {
    "iso:country": "GB",
    "wof:name": "HP21 8PN",
    "wof:placetype": "postalcode"
  },
  "geometry": {"coordinates":[-0.826512,51.810578],"type":"Point"}
}
