{
  "type": "Feature",
  "properties": {
    "iso:country": "GB",
    "wof:name": "OX3 8LD",
    "wof:placetype": "postalcode"
  },
  "geometry": {"coordinates":[-1.19504,51.760764],"type":"Point"}
}
