{
  "type": "Feature",
  "properties": {
    "date:inception_lower": "1980-01-01",
    "date:inception_upper": "1980-01-01",
    "iso:country": "GB",
    "wof:name": "OX3 8LD",
    "wof:placetype": "postalcode"
  },
  "geometry": {"coordinates":[-1.19504,51.760764],"type":"Point"}
}
