{
  "type": "Feature",
  "properties": {
    "iso:country":"GB",
    "wof:name":"HU5 5SR",
    "wof:placetype":"postalcode"
},
  "geometry": {"coordinates":[-0.39780009051123,53.76405756156628],"type":"Point"}
}