{
  "type": "Feature",
  "properties": {
    "date:inception_lower":"2010-09-01",
    "date:inception_upper":"2010-09-30",
    "iso:country":"GB",
    "wof:name":"NW9 8AF",
    "wof:placetype":"postalcode"
},
  "geometry": {"coordinates":[-0.263613,51.566215],"type":"Point"}
}