{
  "type": "Feature",
  "properties": {
    "iso:country": "GB",
    "wof:name": "NW9 8AF",
    "wof:placetype": "postalcode"
  },
  "geometry": {"coordinates":[-0.263613,51.566215],"type":"Point"}
}
