{
  "type": "Feature",
  "properties": {
    "iso:country": "GB",
    "wof:name": "M12 4LS",
    "wof:placetype": "postalcode"
  },
  "geometry": {"coordinates":[-2.211006,53.465217],"type":"Point"}
}
