{
  "type": "Feature",
  "properties": {
    "iso:country":"GB",
    "wof:name":"GL50 4NR",
    "wof:placetype":"postalcode"
},
  "geometry": {"coordinates":[-2.07590423518095,51.91574567082711],"type":"Point"}
}