{
  "type": "Feature",
  "properties": {
    "iso:country": "GB",
    "wof:name": "GL50 4NR",
    "wof:placetype": "postalcode"
  },
  "geometry": {"coordinates":[-2.075904,51.915746],"type":"Point"}
}
