{
  "type": "Feature",
  "properties": {
    "iso:country":"GB",
    "wof:name":"PO32 6HH",
    "wof:placetype":"postalcode"
},
  "geometry": {"coordinates":[-1.28004590678825,50.74762895541721],"type":"Point"}
}