{
  "type": "Feature",
  "properties": {
    "iso:country": "GB",
    "wof:name": "PO32 6HH",
    "wof:placetype": "postalcode"
  },
  "geometry": {"coordinates":[-1.280022,50.747609],"type":"Point"}
}
