{
  "type": "Feature",
  "properties": {
    "iso:country":"GB",
    "wof:name":"SM3 9BU",
    "wof:placetype":"postalcode"
},
  "geometry": {"coordinates":[-0.2202508714359,51.3778715047216],"type":"Point"}
}