{
  "type": "Feature",
  "properties": {
    "iso:country":"GB",
    "wof:name":"BS20 7GZ",
    "wof:placetype":"postalcode"
},
  "geometry": {"coordinates":[-2.7557845422517,51.4857592028218],"type":"Point"}
}