{
  "type": "Feature",
  "properties": {
    "iso:country":"GB",
    "wof:name":"SO16 6QS",
    "wof:placetype":"postalcode"
},
  "geometry": {"coordinates":[-1.42851406500399,50.93312218120504],"type":"Point"}
}