{
  "type": "Feature",
  "properties": {
    "iso:country":"GB",
    "wof:name":"BL5 2NG",
    "wof:placetype":"postalcode"
},
  "geometry": {"coordinates":[-2.51651970358374,53.54273824406972],"type":"Point"}
}