{
  "type": "Feature",
  "properties": {
    "iso:country": "GB",
    "wof:name": "PE7 1SF",
    "wof:placetype": "postalcode"
  },
  "geometry": {"coordinates":[-0.124153,52.556443],"type":"Point"}
}
