{
  "type": "Feature",
  "properties": {
    "iso:country":"GB",
    "wof:name":"PE7 1SF",
    "wof:placetype":"postalcode"
},
  "geometry": {"coordinates":[-0.12415337858627,52.55644260491485],"type":"Point"}
}