{
  "type": "Feature",
  "properties": {
    "date:inception_lower": "1980-01-01",
    "date:inception_upper": "1980-01-01",
    "iso:country": "GB",
    "wof:name": "RM2 6QB",
    "wof:placetype": "postalcode"
  },
  "geometry": {"coordinates":[0.214342,51.587727],"type":"Point"}
}
