{
  "type": "Feature",
  "properties": {
    "iso:country":"GB",
    "wof:name":"RM2 6QB",
    "wof:placetype":"postalcode"
},
  "geometry": {"coordinates":[0.2140829027525,51.58797244701694],"type":"Point"}
}