{
  "type": "Feature",
  "properties": {
    "iso:country": "GB",
    "wof:name": "RM2 6QB",
    "wof:placetype": "postalcode"
  },
  "geometry": {"coordinates":[0.214342,51.587727],"type":"Point"}
}
