{
  "type": "Feature",
  "properties": {
    "iso:country": "GB",
    "wof:name": "KT12 2SB",
    "wof:placetype": "postalcode"
  },
  "geometry": {"coordinates":[-0.414692,51.389584],"type":"Point"}
}
