{
  "type": "Feature",
  "properties": {
    "date:inception_lower":"1980-01-01",
    "date:inception_upper":"1980-01-31",
    "iso:country":"GB",
    "wof:name":"L36 7TT",
    "wof:placetype":"postalcode"
},
  "geometry": {"coordinates":[-2.845737,53.417007],"type":"Point"}
}