{
  "type": "Feature",
  "properties": {
    "iso:country":"GB",
    "wof:name":"L36 7TT",
    "wof:placetype":"postalcode"
},
  "geometry": {"coordinates":[-2.84573669766168,53.41700686521617],"type":"Point"}
}