{
  "type": "Feature",
  "properties": {
    "date:inception_lower": "1980-01-01",
    "date:inception_upper": "1980-01-01",
    "iso:country": "GB",
    "wof:name": "NG17 3HF",
    "wof:placetype": "postalcode"
  },
  "geometry": {"coordinates":[-1.27517,53.142177],"type":"Point"}
}
