{
  "type": "Feature",
  "properties": {
    "iso:country": "GB",
    "wof:name": "NG17 3HF",
    "wof:placetype": "postalcode"
  },
  "geometry": {"coordinates":[-1.27517,53.142177],"type":"Point"}
}
