{
  "type": "Feature",
  "properties": {
    "iso:country": "GB",
    "wof:name": "GU52 0YZ",
    "wof:placetype": "postalcode"
  },
  "geometry": {"coordinates":[-0.854497,51.257776],"type":"Point"}
}
