{
  "type": "Feature",
  "properties": {
    "iso:country":"GB",
    "wof:name":"GU52 0YZ",
    "wof:placetype":"postalcode"
},
  "geometry": {"coordinates":[-0.85449708459259,51.25777593600046],"type":"Point"}
}