{
  "type": "Feature",
  "properties": {
    "date:inception_lower": "2001-06-01",
    "date:inception_upper": "2001-06-01",
    "iso:country": "GB",
    "wof:name": "GU52 0YZ",
    "wof:placetype": "postalcode"
  },
  "geometry": {"coordinates":[-0.854309,51.257755],"type":"Point"}
}
