{
  "type": "Feature",
  "properties": {
    "iso:country":"GB",
    "wof:name":"ST4 8BX",
    "wof:placetype":"postalcode"
},
  "geometry": {"coordinates":[-2.18139499579272,52.9666275224765],"type":"Point"}
}