{
  "type": "Feature",
  "properties": {
    "date:inception_lower": "2003-03-01",
    "date:inception_upper": "2003-03-01",
    "iso:country": "GB",
    "wof:name": "BS22 7RP",
    "wof:placetype": "postalcode"
  },
  "geometry": {"coordinates":[-2.898607,51.364675],"type":"Point"}
}
