{
  "type": "Feature",
  "properties": {
    "iso:country":"GB",
    "wof:name":"BS22 7RP",
    "wof:placetype":"postalcode"
},
  "geometry": {"coordinates":[-2.89860670320377,51.36467468213989],"type":"Point"}
}