{
  "type": "Feature",
  "properties": {
    "iso:country":"GB",
    "wof:name":"TR10 9JE",
    "wof:placetype":"postalcode"
},
  "geometry": {"coordinates":[-5.13370187086,50.1590423978725],"type":"Point"}
}