{
  "type": "Feature",
  "properties": {
    "date:inception_lower":"1980-01-01",
    "date:inception_upper":"1980-01-31",
    "iso:country":"GB",
    "wof:name":"CV5 7JW",
    "wof:placetype":"postalcode"
},
  "geometry": {"coordinates":[-1.572326,52.41279],"type":"Point"}
}