{
  "type": "Feature",
  "properties": {
    "iso:country": "GB",
    "wof:name": "CV5 7JW",
    "wof:placetype": "postalcode"
  },
  "geometry": {"coordinates":[-1.572326,52.41279],"type":"Point"}
}
