{
  "type": "Feature",
  "properties": {
    "date:inception_lower": "1980-01-01",
    "date:inception_upper": "1980-01-01",
    "iso:country": "GB",
    "wof:name": "ST7 2QG",
    "wof:placetype": "postalcode"
  },
  "geometry": {"coordinates":[-2.283459,53.091645],"type":"Point"}
}
