{
  "type": "Feature",
  "properties": {
    "iso:country": "GB",
    "wof:name": "ST7 2QG",
    "wof:placetype": "postalcode"
  },
  "geometry": {"coordinates":[-2.283489,53.091629],"type":"Point"}
}
