{
  "type": "Feature",
  "properties": {
    "iso:country":"GB",
    "wof:name":"ST7 2QG",
    "wof:placetype":"postalcode"
},
  "geometry": {"coordinates":[-2.2834887854266,53.09162856369208],"type":"Point"}
}