{
  "type": "Feature",
  "properties": {
    "iso:country": "GB",
    "wof:name": "BS21 6AS",
    "wof:placetype": "postalcode"
  },
  "geometry": {"coordinates":[-2.841917,51.443999],"type":"Point"}
}
