{
  "type": "Feature",
  "properties": {
    "iso:country":"GB",
    "wof:name":"GL53 9QN",
    "wof:placetype":"postalcode"
},
  "geometry": {"coordinates":[-2.06419287240864,51.85964066051324],"type":"Point"}
}