{
  "type": "Feature",
  "properties": {
    "date:inception_lower": "1980-01-01",
    "date:inception_upper": "1980-01-01",
    "iso:country": "GB",
    "wof:name": "GL53 9QN",
    "wof:placetype": "postalcode"
  },
  "geometry": {"coordinates":[-2.064193,51.859641],"type":"Point"}
}
