{
  "type": "Feature",
  "properties": {
    "iso:country":"GB",
    "wof:name":"DT7 3TN",
    "wof:placetype":"postalcode"
},
  "geometry": {"coordinates":[-2.95385973134163,50.73466938536314],"type":"Point"}
}