{
  "type": "Feature",
  "properties": {
    "iso:country":"GB",
    "wof:name":"NG7 2QD",
    "wof:placetype":"postalcode"
},
  "geometry": {"coordinates":[-1.20428326215915,52.93689377139665],"type":"Point"}
}