{
  "type": "Feature",
  "properties": {
    "iso:country":"GB",
    "wof:name":"PL6 7AX",
    "wof:placetype":"postalcode"
},
  "geometry": {"coordinates":[-4.10550194519287,50.43947997496767],"type":"Point"}
}