{
  "type": "Feature",
  "properties": {
    "iso:country": "GB",
    "wof:name": "SN7 7BB",
    "wof:placetype": "postalcode"
  },
  "geometry": {"coordinates":[-1.583382,51.656454],"type":"Point"}
}
