{
  "type": "Feature",
  "properties": {
    "iso:country": "GB",
    "wof:name": "ST11 9TN",
    "wof:placetype": "postalcode"
  },
  "geometry": {"coordinates":[-2.083753,52.950862],"type":"Point"}
}
