{
  "type": "Feature",
  "properties": {
    "iso:country":"GB",
    "wof:name":"ST11 9TN",
    "wof:placetype":"postalcode"
},
  "geometry": {"coordinates":[-2.08375267437681,52.95086164941248],"type":"Point"}
}