{
  "type": "Feature",
  "properties": {
    "iso:country":"GB",
    "wof:name":"NW3 7RY",
    "wof:placetype":"postalcode"
},
  "geometry": {"coordinates":[-0.18595161194325,51.55864362256722],"type":"Point"}
}