{
  "type": "Feature",
  "properties": {
    "date:inception_lower": "1980-01-01",
    "date:inception_upper": "1980-01-01",
    "iso:country": "GB",
    "wof:name": "NW3 7RY",
    "wof:placetype": "postalcode"
  },
  "geometry": {"coordinates":[-0.185952,51.558644],"type":"Point"}
}
