{
  "type": "Feature",
  "properties": {
    "iso:country":"GB",
    "wof:name":"WF17 7NA",
    "wof:placetype":"postalcode"
},
  "geometry": {"coordinates":[-1.63469293695414,53.70129354223712],"type":"Point"}
}