{
  "type": "Feature",
  "properties": {
    "iso:country": "GB",
    "wof:name": "WF17 7NA",
    "wof:placetype": "postalcode"
  },
  "geometry": {"coordinates":[-1.634693,53.701294],"type":"Point"}
}
