{
  "type": "Feature",
  "properties": {
    "date:inception_lower":"1980-01-01",
    "date:inception_upper":"1980-01-31",
    "iso:country":"GB",
    "wof:name":"GL7 5AP",
    "wof:placetype":"postalcode"
},
  "geometry": {"coordinates":[-1.791478,51.749658],"type":"Point"}
}