{
  "type": "Feature",
  "properties": {
    "iso:country":"GB",
    "wof:name":"YO12 6NU",
    "wof:placetype":"postalcode"
},
  "geometry": {"coordinates":[-0.42801181645691,54.2856918726632],"type":"Point"}
}