{
  "type": "Feature",
  "properties": {
    "iso:country":"GB",
    "wof:name":"RH10 4UZ",
    "wof:placetype":"postalcode"
},
  "geometry": {"coordinates":[-0.07553522248174,51.12494145501538],"type":"Point"}
}