{
  "type": "Feature",
  "properties": {
    "date:inception_lower": "2020-01-01",
    "date:inception_upper": "2020-01-01",
    "iso:country": "GB",
    "wof:name": "ML2 9PG",
    "wof:placetype": "postalcode"
  },
  "geometry": {"coordinates":[-3.846956,55.792616],"type":"Point"}
}
