{
  "type": "Feature",
  "properties": {
    "iso:country": "GB",
    "wof:name": "TS6 7QQ",
    "wof:placetype": "postalcode"
  },
  "geometry": {"coordinates":[-1.138633,54.56993],"type":"Point"}
}
