{
  "type": "Feature",
  "properties": {
    "date:inception_lower": "1980-01-01",
    "date:inception_upper": "1980-01-01",
    "iso:country": "GB",
    "wof:name": "B36 8LS",
    "wof:placetype": "postalcode"
  },
  "geometry": {"coordinates":[-1.803483,52.505196],"type":"Point"}
}
