{
  "type": "Feature",
  "properties": {
    "iso:country":"GB",
    "wof:name":"SK22 4AP",
    "wof:placetype":"postalcode"
},
  "geometry": {"coordinates":[-2.00081738316954,53.36806720576923],"type":"Point"}
}