{
  "type": "Feature",
  "properties": {
    "iso:country":"GB",
    "wof:name":"EH42 1DH",
    "wof:placetype":"postalcode"
},
  "geometry": {"coordinates":[-2.52497259180444,55.99966284168475],"type":"Point"}
}