{
  "type": "Feature",
  "properties": {
    "iso:country": "GB",
    "wof:name": "EH42 1DH",
    "wof:placetype": "postalcode"
  },
  "geometry": {"coordinates":[-2.524973,55.999663],"type":"Point"}
}
