{
  "type": "Feature",
  "properties": {
    "iso:country": "GB",
    "wof:name": "CM7 5NH",
    "wof:placetype": "postalcode"
  },
  "geometry": {"coordinates":[0.568137,51.898362],"type":"Point"}
}
