{
  "type": "Feature",
  "properties": {
    "iso:country":"GB",
    "wof:name":"CM7 5NH",
    "wof:placetype":"postalcode"
},
  "geometry": {"coordinates":[0.56810837423967,51.89835211108098],"type":"Point"}
}