{
  "type": "Feature",
  "properties": {
    "iso:country":"GB",
    "wof:name":"TS9 6SF",
    "wof:placetype":"postalcode"
},
  "geometry": {"coordinates":[-1.132094708492,54.48739000038508],"type":"Point"}
}