{
  "type": "Feature",
  "properties": {
    "date:inception_lower": "1999-12-01",
    "date:inception_upper": "1999-12-01",
    "iso:country": "GB",
    "wof:name": "TS9 6SF",
    "wof:placetype": "postalcode"
  },
  "geometry": {"coordinates":[-1.132217,54.487358],"type":"Point"}
}
