{
  "type": "Feature",
  "properties": {
    "date:inception_lower": "1980-01-01",
    "date:inception_upper": "1980-01-01",
    "iso:country": "GB",
    "wof:name": "NR10 3PA",
    "wof:placetype": "postalcode"
  },
  "geometry": {"coordinates":[1.323162,52.690405],"type":"Point"}
}
