{
  "type": "Feature",
  "properties": {
    "iso:country":"GB",
    "wof:name":"BA2 3QB",
    "wof:placetype":"postalcode"
},
  "geometry": {"coordinates":[-2.38186532344112,51.3783164867428],"type":"Point"}
}