{
  "type": "Feature",
  "properties": {
    "date:inception_lower":"2007-06-01",
    "date:inception_upper":"2007-06-30",
    "iso:country":"GB",
    "wof:name":"EX7 0WR",
    "wof:placetype":"postalcode"
},
  "geometry": {"coordinates":[-3.470748,50.580153],"type":"Point"}
}