{
  "type": "Feature",
  "properties": {
    "iso:country":"GB",
    "wof:name":"BD18 1PH",
    "wof:placetype":"postalcode"
},
  "geometry": {"coordinates":[-1.75284224153795,53.82757151896314],"type":"Point"}
}