{
  "type": "Feature",
  "properties": {
    "iso:country": "GB",
    "wof:name": "LE6 0FE",
    "wof:placetype": "postalcode"
  },
  "geometry": {"coordinates":[-1.227541,52.661288],"type":"Point"}
}
