{
  "type": "Feature",
  "properties": {
    "iso:country":"GB",
    "wof:name":"LE6 0FE",
    "wof:placetype":"postalcode"
},
  "geometry": {"coordinates":[-1.22754120304135,52.66128846302698],"type":"Point"}
}