{
  "type": "Feature",
  "properties": {
    "iso:country": "GB",
    "wof:name": "SK6 8DF",
    "wof:placetype": "postalcode"
  },
  "geometry": {"coordinates":[-2.066631,53.360633],"type":"Point"}
}
