{
  "type": "Feature",
  "properties": {
    "iso:country":"GB",
    "wof:name":"G75 8TU",
    "wof:placetype":"postalcode"
},
  "geometry": {"coordinates":[-4.22343700813838,55.73814807099475],"type":"Point"}
}