{
  "type": "Feature",
  "properties": {
    "date:inception_lower": "2011-03-01",
    "date:inception_upper": "2011-03-01",
    "iso:country": "GB",
    "wof:name": "G75 8TU",
    "wof:placetype": "postalcode"
  },
  "geometry": {"coordinates":[-4.223437,55.738148],"type":"Point"}
}
