{
  "type": "Feature",
  "properties": {
    "iso:country":"GB",
    "wof:name":"CO16 9PL",
    "wof:placetype":"postalcode"
},
  "geometry": {"coordinates":[1.13717253506806,51.82376606654027],"type":"Point"}
}