{
  "type": "Feature",
  "properties": {
    "iso:country": "GB",
    "wof:name": "EX8 1XW",
    "wof:placetype": "postalcode"
  },
  "geometry": {"coordinates":[-3.424736,50.618214],"type":"Point"}
}
