{
  "type": "Feature",
  "properties": {
    "iso:country":"GB",
    "wof:name":"EX8 1XW",
    "wof:placetype":"postalcode"
},
  "geometry": {"coordinates":[-3.42473582878372,50.61821352205405],"type":"Point"}
}