{
  "type": "Feature",
  "properties": {
    "date:inception_lower": "1980-01-01",
    "date:inception_upper": "1980-01-01",
    "iso:country": "GB",
    "wof:name": "BA15 2LU",
    "wof:placetype": "postalcode"
  },
  "geometry": {"coordinates":[-2.289,51.345975],"type":"Point"}
}
