{
  "type": "Feature",
  "properties": {
    "iso:country":"GB",
    "wof:name":"BA15 2LU",
    "wof:placetype":"postalcode"
},
  "geometry": {"coordinates":[-2.28873026983125,51.34607818443794],"type":"Point"}
}