{
  "type": "Feature",
  "properties": {
    "iso:country": "GB",
    "wof:name": "BA15 2LU",
    "wof:placetype": "postalcode"
  },
  "geometry": {"coordinates":[-2.289214,51.345768],"type":"Point"}
}
