{
  "type": "Feature",
  "properties": {
    "iso:country":"GB",
    "wof:name":"SN5 5RQ",
    "wof:placetype":"postalcode"
},
  "geometry": {"coordinates":[-1.83762642360435,51.56393575174574],"type":"Point"}
}