{
  "type": "Feature",
  "properties": {
    "iso:country":"GB",
    "wof:name":"AB54 4SF",
    "wof:placetype":"postalcode"
},
  "geometry": {"coordinates":[-2.78574708956002,57.46129487196894],"type":"Point"}
}