{
  "type": "Feature",
  "properties": {
    "iso:country": "GB",
    "wof:name": "HP22 4DY",
    "wof:placetype": "postalcode"
  },
  "geometry": {"coordinates":[-0.830676,51.865449],"type":"Point"}
}
