{
  "type": "Feature",
  "properties": {
    "iso:country":"GB",
    "wof:name":"HP22 4DY",
    "wof:placetype":"postalcode"
},
  "geometry": {"coordinates":[-0.83067605165929,51.86544854821201],"type":"Point"}
}