{
  "type": "Feature",
  "properties": {
    "date:inception_lower": "2009-05-01",
    "date:inception_upper": "2009-05-01",
    "iso:country": "GB",
    "wof:name": "EH5 1FD",
    "wof:placetype": "postalcode"
  },
  "geometry": {"coordinates":[-3.253969,55.97613],"type":"Point"}
}
