{
  "type": "Feature",
  "properties": {
    "date:inception_lower": "2019-11-01",
    "date:inception_upper": "2019-11-01",
    "iso:country": "GB",
    "wof:name": "RH16 2GG",
    "wof:placetype": "postalcode"
  },
  "geometry": {"coordinates":[-0.076283,51.005062],"type":"Point"}
}
