{
  "type": "Feature",
  "properties": {
    "date:inception_lower":"2007-11-01",
    "date:inception_upper":"2007-11-30",
    "iso:country":"GB",
    "wof:name":"NG13 9WN",
    "wof:placetype":"postalcode"
},
  "geometry": {"coordinates":[-1.135601,52.945098],"type":"Point"}
}