{
  "type": "Feature",
  "properties": {
    "iso:country": "GB",
    "wof:name": "OX9 2BU",
    "wof:placetype": "postalcode"
  },
  "geometry": {"coordinates":[-0.978839,51.747459],"type":"Point"}
}
