{
  "type": "Feature",
  "properties": {
    "iso:country":"GB",
    "wof:name":"CH41 2PH",
    "wof:placetype":"postalcode"
},
  "geometry": {"coordinates":[-3.02938009103612,53.38909222446063],"type":"Point"}
}