{
  "type": "Feature",
  "properties": {
    "iso:country":"GB",
    "wof:name":"EX20 3HS",
    "wof:placetype":"postalcode"
},
  "geometry": {"coordinates":[-4.07301894952174,50.82016606157951],"type":"Point"}
}