{
  "type": "Feature",
  "properties": {
    "date:inception_lower": "1980-01-01",
    "date:inception_upper": "1980-01-01",
    "iso:country": "GB",
    "wof:name": "ST21 6RS",
    "wof:placetype": "postalcode"
  },
  "geometry": {"coordinates":[-2.255846,52.912177],"type":"Point"}
}
