{
  "type": "Feature",
  "properties": {
    "iso:country":"GB",
    "wof:name":"ST21 6RS",
    "wof:placetype":"postalcode"
},
  "geometry": {"coordinates":[-2.25584554864277,52.9121772046765],"type":"Point"}
}