{
  "type": "Feature",
  "properties": {
    "date:inception_lower":"1980-01-01",
    "date:inception_upper":"1980-01-31",
    "iso:country":"GB",
    "wof:name":"SK6 7QX",
    "wof:placetype":"postalcode"
},
  "geometry": {"coordinates":[-2.076073,53.38922],"type":"Point"}
}