{
  "type": "Feature",
  "properties": {
    "iso:country":"GB",
    "wof:name":"BN16 3NE",
    "wof:placetype":"postalcode"
},
  "geometry": {"coordinates":[-0.50726769251763,50.81520285827533],"type":"Point"}
}