{
  "type": "Feature",
  "properties": {
    "date:inception_lower": "1980-01-01",
    "date:inception_upper": "1980-01-01",
    "iso:country": "GB",
    "wof:name": "BN16 3NE",
    "wof:placetype": "postalcode"
  },
  "geometry": {"coordinates":[-0.507268,50.815203],"type":"Point"}
}
