{
  "type": "Feature",
  "properties": {
    "date:inception_lower": "1995-07-01",
    "date:inception_upper": "1995-07-01",
    "iso:country": "GB",
    "wof:name": "CF83 4FH",
    "wof:placetype": "postalcode"
  },
  "geometry": {"coordinates":[-3.267836,51.600788],"type":"Point"}
}
