{
  "type": "Feature",
  "properties": {
    "iso:country": "GB",
    "wof:name": "ST16 1FQ",
    "wof:placetype": "postalcode"
  },
  "geometry": {"coordinates":[-2.145149,52.810143],"type":"Point"}
}
