{
  "type": "Feature",
  "properties": {
    "iso:country":"GB",
    "wof:name":"SG13 7SY",
    "wof:placetype":"postalcode"
},
  "geometry": {"coordinates":[-0.04573992602345,51.80089516352669],"type":"Point"}
}