{
  "type": "Feature",
  "properties": {
    "iso:country":"GB",
    "wof:name":"N17 9FQ",
    "wof:placetype":"postalcode"
},
  "geometry": {"coordinates":[-0.05903031292874,51.59009178918218],"type":"Point"}
}