{
  "type": "Feature",
  "properties": {
    "iso:country": "GB",
    "wof:name": "CM11 2PA",
    "wof:placetype": "postalcode"
  },
  "geometry": {"coordinates":[0.429298,51.61599],"type":"Point"}
}
