{
  "type": "Feature",
  "properties": {
    "iso:country":"GB",
    "wof:name":"HD3 4YJ",
    "wof:placetype":"postalcode"
},
  "geometry": {"coordinates":[-1.82345311167603,53.65097288744161],"type":"Point"}
}