{
  "type": "Feature",
  "properties": {
    "iso:country":"GB",
    "wof:name":"NE6 3BQ",
    "wof:placetype":"postalcode"
},
  "geometry": {"coordinates":[-1.55183517106952,54.96948884286895],"type":"Point"}
}