{
  "type": "Feature",
  "properties": {
    "iso:country": "GB",
    "wof:name": "YO12 4NJ",
    "wof:placetype": "postalcode"
  },
  "geometry": {"coordinates":[-0.435939,54.254488],"type":"Point"}
}
