{
  "type": "Feature",
  "properties": {
    "iso:country":"GB",
    "wof:name":"M7 1TW",
    "wof:placetype":"postalcode"
},
  "geometry": {"coordinates":[-2.25534614396626,53.49196120552877],"type":"Point"}
}