{
  "type": "Feature",
  "properties": {
    "date:inception_lower": "2017-06-01",
    "date:inception_upper": "2017-06-01",
    "iso:country": "GB",
    "wof:name": "E15 1GE",
    "wof:placetype": "postalcode"
  },
  "geometry": {"coordinates":[-0.003211,51.548142],"type":"Point"}
}
