{
  "type": "Feature",
  "properties": {
    "date:inception_lower": "2022-07-01",
    "date:inception_upper": "2022-07-01",
    "iso:country": "GB",
    "wof:name": "BD9 4NE",
    "wof:placetype": "postalcode"
  },
  "geometry": {"coordinates":[-1.770926,53.81059],"type":"Point"}
}
