{
  "type": "Feature",
  "properties": {
    "iso:country":"GB",
    "wof:name":"GU20 6LP",
    "wof:placetype":"postalcode"
},
  "geometry": {"coordinates":[-0.65110641394102,51.37389388462265],"type":"Point"}
}