{
  "type": "Feature",
  "properties": {
    "iso:country":"GB",
    "wof:name":"B92 8AP",
    "wof:placetype":"postalcode"
},
  "geometry": {"coordinates":[-1.79615650806814,52.43285926265553],"type":"Point"}
}