{
  "type": "Feature",
  "properties": {
    "iso:country":"GB",
    "wof:name":"DA6 7PY",
    "wof:placetype":"postalcode"
},
  "geometry": {"coordinates":[0.15516272961794,51.44894257042735],"type":"Point"}
}