{
  "type": "Feature",
  "properties": {
    "date:inception_lower":"2002-06-01",
    "date:inception_upper":"2002-06-30",
    "iso:country":"GB",
    "wof:name":"SP3 6QU",
    "wof:placetype":"postalcode"
},
  "geometry": {"coordinates":[-2.079714,51.059952],"type":"Point"}
}