{
  "type": "Feature",
  "properties": {
    "iso:country":"GB",
    "wof:name":"SP3 6QU",
    "wof:placetype":"postalcode"
},
  "geometry": {"coordinates":[-2.07971402252207,51.05995159758564],"type":"Point"}
}