{
  "type": "Feature",
  "properties": {
    "iso:country":"GB",
    "wof:name":"DN22 7ST",
    "wof:placetype":"postalcode"
},
  "geometry": {"coordinates":[-0.94755804311154,53.33206695825866],"type":"Point"}
}