{
  "type": "Feature",
  "properties": {
    "iso:country": "GB",
    "wof:name": "WD3 5HE",
    "wof:placetype": "postalcode"
  },
  "geometry": {"coordinates":[-0.519612,51.64698],"type":"Point"}
}
