{
  "type": "Feature",
  "properties": {
    "iso:country": "GB",
    "wof:name": "CM8 3RY",
    "wof:placetype": "postalcode"
  },
  "geometry": {"coordinates":[0.623964,51.845301],"type":"Point"}
}
