{
  "type": "Feature",
  "properties": {
    "iso:country": "GB",
    "wof:name": "SG9 9NH",
    "wof:placetype": "postalcode"
  },
  "geometry": {"coordinates":[-0.050751,51.923694],"type":"Point"}
}
