{
  "type": "Feature",
  "properties": {
    "iso:country":"GB",
    "wof:name":"SG9 9NH",
    "wof:placetype":"postalcode"
},
  "geometry": {"coordinates":[-0.05075088169372,51.92369402895899],"type":"Point"}
}