{
  "type": "Feature",
  "properties": {
    "iso:country": "GB",
    "wof:name": "RG14 2NG",
    "wof:placetype": "postalcode"
  },
  "geometry": {"coordinates":[-1.303597,51.41105],"type":"Point"}
}
