{
  "type": "Feature",
  "properties": {
    "date:inception_lower":"1995-07-01",
    "date:inception_upper":"1995-07-31",
    "iso:country":"GB",
    "wof:name":"RG14 2NG",
    "wof:placetype":"postalcode"
},
  "geometry": {"coordinates":[-1.303597,51.41105],"type":"Point"}
}