{
  "type": "Feature",
  "properties": {
    "iso:country": "GB",
    "wof:name": "TN26 1ED",
    "wof:placetype": "postalcode"
  },
  "geometry": {"coordinates":[0.81875,51.1717],"type":"Point"}
}
