{
  "type": "Feature",
  "properties": {
    "date:inception_lower": "1980-01-01",
    "date:inception_upper": "1980-01-01",
    "iso:country": "GB",
    "wof:name": "TN26 1ED",
    "wof:placetype": "postalcode"
  },
  "geometry": {"coordinates":[0.81875,51.1717],"type":"Point"}
}
