{
  "type": "Feature",
  "properties": {
    "iso:country": "GB",
    "wof:name": "LS24 9YR",
    "wof:placetype": "postalcode"
  },
  "geometry": {"coordinates":[-1.207785,53.833724],"type":"Point"}
}
