{
  "type": "Feature",
  "properties": {
    "iso:country":"GB",
    "wof:name":"BA22 9PN",
    "wof:placetype":"postalcode"
},
  "geometry": {"coordinates":[-2.70787234971374,50.9043335469609],"type":"Point"}
}