{
  "type": "Feature",
  "properties": {
    "date:inception_lower": "1999-12-01",
    "date:inception_upper": "1999-12-01",
    "iso:country": "GB",
    "wof:name": "LL14 6BQ",
    "wof:placetype": "postalcode"
  },
  "geometry": {"coordinates":[-3.034444,52.994823],"type":"Point"}
}
