{
  "type": "Feature",
  "properties": {
    "iso:country":"GB",
    "wof:name":"LL14 6BQ",
    "wof:placetype":"postalcode"
},
  "geometry": {"coordinates":[-3.03444394474583,52.99482335250644],"type":"Point"}
}