{
  "type": "Feature",
  "properties": {
    "date:inception_lower":"1998-12-01",
    "date:inception_upper":"1998-12-31",
    "iso:country":"GB",
    "wof:name":"IG10 4PN",
    "wof:placetype":"postalcode"
},
  "geometry": {"coordinates":[0.045801,51.635549],"type":"Point"}
}