{
  "type": "Feature",
  "properties": {
    "date:inception_lower": "1991-01-01",
    "date:inception_upper": "1991-01-01",
    "iso:country": "GB",
    "wof:name": "NR34 7RR",
    "wof:placetype": "postalcode"
  },
  "geometry": {"coordinates":[1.597409,52.45002],"type":"Point"}
}
