{
  "type": "Feature",
  "properties": {
    "iso:country": "GB",
    "wof:name": "NR34 7RR",
    "wof:placetype": "postalcode"
  },
  "geometry": {"coordinates":[1.597409,52.45002],"type":"Point"}
}
