{
  "type": "Feature",
  "properties": {
    "iso:country":"GB",
    "wof:name":"LS28 8DR",
    "wof:placetype":"postalcode"
},
  "geometry": {"coordinates":[-1.65842565211812,53.78021601086918],"type":"Point"}
}