{
  "type": "Feature",
  "properties": {
    "iso:country":"GB",
    "wof:name":"PL25 3EA",
    "wof:placetype":"postalcode"
},
  "geometry": {"coordinates":[-4.7619805974942,50.34607915733594],"type":"Point"}
}