{
  "type": "Feature",
  "properties": {
    "iso:country": "GB",
    "wof:name": "NG7 2TJ",
    "wof:placetype": "postalcode"
  },
  "geometry": {"coordinates":[-1.180872,52.93642],"type":"Point"}
}
