{
  "type": "Feature",
  "properties": {
    "iso:country":"GB",
    "wof:name":"NG7 2TJ",
    "wof:placetype":"postalcode"
},
  "geometry": {"coordinates":[-1.18087249435859,52.9364201281154],"type":"Point"}
}