{
  "type": "Feature",
  "properties": {
    "iso:country": "GB",
    "wof:name": "BH20 4BG",
    "wof:placetype": "postalcode"
  },
  "geometry": {"coordinates":[-2.11578,50.693101],"type":"Point"}
}
