{
  "type": "Feature",
  "properties": {
    "iso:country": "GB",
    "wof:name": "ME17 3FB",
    "wof:placetype": "postalcode"
  },
  "geometry": {"coordinates":[0.56748,51.214497],"type":"Point"}
}
