{
  "type": "Feature",
  "properties": {
    "iso:country":"GB",
    "wof:name":"ME17 3FB",
    "wof:placetype":"postalcode"
},
  "geometry": {"coordinates":[0.56747994658814,51.21449718329562],"type":"Point"}
}