{
  "type": "Feature",
  "properties": {
    "iso:country":"GB",
    "wof:name":"OL16 3EW",
    "wof:placetype":"postalcode"
},
  "geometry": {"coordinates":[-2.10623925468807,53.61349355968341],"type":"Point"}
}