{
  "type": "Feature",
  "properties": {
    "iso:country":"GB",
    "wof:name":"TN8 5BS",
    "wof:placetype":"postalcode"
},
  "geometry": {"coordinates":[0.06509304611571,51.19294120020175],"type":"Point"}
}