{
  "type": "Feature",
  "properties": {
    "date:inception_lower":"1980-01-01",
    "date:inception_upper":"1980-01-31",
    "iso:country":"GB",
    "wof:name":"TN8 5BS",
    "wof:placetype":"postalcode"
},
  "geometry": {"coordinates":[0.065093,51.192941],"type":"Point"}
}