{
  "type": "Feature",
  "properties": {
    "iso:country":"GB",
    "wof:name":"KA11 4AZ",
    "wof:placetype":"postalcode"
},
  "geometry": {"coordinates":[-4.61248738776277,55.60881750277429],"type":"Point"}
}