{
  "type": "Feature",
  "properties": {
    "iso:country":"GB",
    "wof:name":"CW2 8JR",
    "wof:placetype":"postalcode"
},
  "geometry": {"coordinates":[-2.46415870182331,53.08389642522138],"type":"Point"}
}