{
  "type": "Feature",
  "properties": {
    "iso:country": "GB",
    "wof:name": "NR28 0QF",
    "wof:placetype": "postalcode"
  },
  "geometry": {"coordinates":[1.397405,52.861069],"type":"Point"}
}
