{
  "type": "Feature",
  "properties": {
    "iso:country": "GB",
    "wof:name": "GL52 5FN",
    "wof:placetype": "postalcode"
  },
  "geometry": {"coordinates":[-2.040031,51.901602],"type":"Point"}
}
