{
  "type": "Feature",
  "properties": {
    "date:inception_lower": "2009-10-01",
    "date:inception_upper": "2009-10-01",
    "iso:country": "GB",
    "wof:name": "PO21 3FF",
    "wof:placetype": "postalcode"
  },
  "geometry": {"coordinates":[-0.723979,50.787152],"type":"Point"}
}
