{
  "type": "Feature",
  "properties": {
    "iso:country":"GB",
    "wof:name":"PO21 3FF",
    "wof:placetype":"postalcode"
},
  "geometry": {"coordinates":[-0.7239850225677,50.78714399350325],"type":"Point"}
}