{
  "type": "Feature",
  "properties": {
    "iso:country": "GB",
    "wof:name": "SA1 2AQ",
    "wof:placetype": "postalcode"
  },
  "geometry": {"coordinates":[-3.941421,51.623146],"type":"Point"}
}
