{
  "type": "Feature",
  "properties": {
    "date:inception_lower": "1980-01-01",
    "date:inception_upper": "1980-01-01",
    "iso:country": "GB",
    "wof:name": "SA1 2AQ",
    "wof:placetype": "postalcode"
  },
  "geometry": {"coordinates":[-3.941421,51.623146],"type":"Point"}
}
