{
  "type": "Feature",
  "properties": {
    "date:inception_lower": "2017-01-01",
    "date:inception_upper": "2017-01-01",
    "iso:country": "GB",
    "wof:name": "FY6 9FD",
    "wof:placetype": "postalcode"
  },
  "geometry": {"coordinates":[-2.954339,53.878672],"type":"Point"}
}
