{
  "type": "Feature",
  "properties": {
    "iso:country":"GB",
    "wof:name":"OX15 5DH",
    "wof:placetype":"postalcode"
},
  "geometry": {"coordinates":[-1.48495271986733,52.00893159926069],"type":"Point"}
}