{
  "type": "Feature",
  "properties": {
    "iso:country": "GB",
    "wof:name": "OX15 5DH",
    "wof:placetype": "postalcode"
  },
  "geometry": {"coordinates":[-1.484938,52.008942],"type":"Point"}
}
