{
  "type": "Feature",
  "properties": {
    "iso:country":"GB",
    "wof:name":"OX4 6LA",
    "wof:placetype":"postalcode"
},
  "geometry": {"coordinates":[-1.20831244167303,51.72343187419759],"type":"Point"}
}