{
  "type": "Feature",
  "properties": {
    "date:inception_lower": "2000-12-01",
    "date:inception_upper": "2000-12-01",
    "iso:country": "GB",
    "wof:name": "OX4 6LA",
    "wof:placetype": "postalcode"
  },
  "geometry": {"coordinates":[-1.208312,51.723432],"type":"Point"}
}
