{
  "type": "Feature",
  "properties": {
    "iso:country": "GB",
    "wof:name": "BN3 7JR",
    "wof:placetype": "postalcode"
  },
  "geometry": {"coordinates":[-0.187144,50.83936],"type":"Point"}
}
