{
  "type": "Feature",
  "properties": {
    "iso:country":"GB",
    "wof:name":"BN3 7JR",
    "wof:placetype":"postalcode"
},
  "geometry": {"coordinates":[-0.18734472386091,50.83928781530966],"type":"Point"}
}