{
  "type": "Feature",
  "properties": {
    "iso:country":"GB",
    "wof:name":"W2 4SB",
    "wof:placetype":"postalcode"
},
  "geometry": {"coordinates":[-0.18857479858557,51.51548456753054],"type":"Point"}
}