{
  "type": "Feature",
  "properties": {
    "iso:country":"GB",
    "wof:name":"B91 3UA",
    "wof:placetype":"postalcode"
},
  "geometry": {"coordinates":[-1.79159951544084,52.39795187177591],"type":"Point"}
}