{
  "type": "Feature",
  "properties": {
    "date:inception_lower": "1980-01-01",
    "date:inception_upper": "1980-01-01",
    "iso:country": "GB",
    "wof:name": "SW15 6LR",
    "wof:placetype": "postalcode"
  },
  "geometry": {"coordinates":[-0.228838,51.459492],"type":"Point"}
}
