{
  "type": "Feature",
  "properties": {
    "date:inception_lower": "1980-01-01",
    "date:inception_upper": "1980-01-01",
    "iso:country": "GB",
    "wof:name": "PR4 1PP",
    "wof:placetype": "postalcode"
  },
  "geometry": {"coordinates":[-2.860186,53.751908],"type":"Point"}
}
