{
  "type": "Feature",
  "properties": {
    "iso:country": "GB",
    "wof:name": "BS15 4EE",
    "wof:placetype": "postalcode"
  },
  "geometry": {"coordinates":[-2.49847,51.463641],"type":"Point"}
}
