{
  "type": "Feature",
  "properties": {
    "iso:country":"GB",
    "wof:name":"BS15 4EE",
    "wof:placetype":"postalcode"
},
  "geometry": {"coordinates":[-2.49847004227327,51.46364069197777],"type":"Point"}
}