{
  "type": "Feature",
  "properties": {
    "iso:country":"GB",
    "wof:name":"IV32 7NY",
    "wof:placetype":"postalcode"
},
  "geometry": {"coordinates":[-3.11293965378047,57.67332998225272],"type":"Point"}
}