{
  "type": "Feature",
  "properties": {
    "iso:country":"GB",
    "wof:name":"PE16 6UQ",
    "wof:placetype":"postalcode"
},
  "geometry": {"coordinates":[0.02770282677926,52.47738627452996],"type":"Point"}
}