{
  "type": "Feature",
  "properties": {
    "iso:country": "GB",
    "wof:name": "PE16 6UQ",
    "wof:placetype": "postalcode"
  },
  "geometry": {"coordinates":[0.027703,52.477386],"type":"Point"}
}
