{
  "type": "Feature",
  "properties": {
    "iso:country":"GB",
    "wof:name":"SN2 5EE",
    "wof:placetype":"postalcode"
},
  "geometry": {"coordinates":[-1.77905481645232,51.59086825927644],"type":"Point"}
}