{
  "type": "Feature",
  "properties": {
    "iso:country": "GB",
    "wof:name": "DL11 7SU",
    "wof:placetype": "postalcode"
  },
  "geometry": {"coordinates":[-1.68914,54.49761],"type":"Point"}
}
