{
  "type": "Feature",
  "properties": {
    "iso:country":"GB",
    "wof:name":"BB2 2NL",
    "wof:placetype":"postalcode"
},
  "geometry": {"coordinates":[-2.49708643532046,53.74102144527336],"type":"Point"}
}