{
  "type": "Feature",
  "properties": {
    "iso:country": "GB",
    "wof:name": "BB2 2NL",
    "wof:placetype": "postalcode"
  },
  "geometry": {"coordinates":[-2.497086,53.741021],"type":"Point"}
}
