{
  "type": "Feature",
  "properties": {
    "iso:country":"GB",
    "wof:name":"HU6 7AZ",
    "wof:placetype":"postalcode"
},
  "geometry": {"coordinates":[-0.35800997233142,53.78494017266034],"type":"Point"}
}