{
  "type": "Feature",
  "properties": {
    "date:inception_lower": "1980-01-01",
    "date:inception_upper": "1980-01-01",
    "iso:country": "GB",
    "wof:name": "HU6 7AZ",
    "wof:placetype": "postalcode"
  },
  "geometry": {"coordinates":[-0.35801,53.78494],"type":"Point"}
}
