{
  "type": "Feature",
  "properties": {
    "date:inception_lower": "1980-01-01",
    "date:inception_upper": "1980-01-01",
    "iso:country": "GB",
    "wof:name": "BN1 7JL",
    "wof:placetype": "postalcode"
  },
  "geometry": {"coordinates":[-0.133211,50.844757],"type":"Point"}
}
