{
  "type": "Feature",
  "properties": {
    "iso:country":"GB",
    "wof:name":"BN1 7JL",
    "wof:placetype":"postalcode"
},
  "geometry": {"coordinates":[-0.13321098024633,50.84475664919368],"type":"Point"}
}