{
  "type": "Feature",
  "properties": {
    "iso:country": "GB",
    "wof:name": "OL9 8AH",
    "wof:placetype": "postalcode"
  },
  "geometry": {"coordinates":[-2.153881,53.529922],"type":"Point"}
}
