{
  "type": "Feature",
  "properties": {
    "date:inception_lower": "1980-01-01",
    "date:inception_upper": "1980-01-01",
    "iso:country": "GB",
    "wof:name": "OL9 8AH",
    "wof:placetype": "postalcode"
  },
  "geometry": {"coordinates":[-2.153881,53.529922],"type":"Point"}
}
