{
  "type": "Feature",
  "properties": {
    "iso:country":"GB",
    "wof:name":"OL9 8AH",
    "wof:placetype":"postalcode"
},
  "geometry": {"coordinates":[-2.15388148433992,53.52992234099011],"type":"Point"}
}