{
  "type": "Feature",
  "properties": {
    "iso:country": "GB",
    "wof:name": "AB22 8BJ",
    "wof:placetype": "postalcode"
  },
  "geometry": {"coordinates":[-2.11849,57.182348],"type":"Point"}
}
