{
  "type": "Feature",
  "properties": {
    "date:inception_lower":"2016-01-01",
    "date:inception_upper":"2016-01-31",
    "iso:country":"GB",
    "wof:name":"AB22 8BJ",
    "wof:placetype":"postalcode"
},
  "geometry": {"coordinates":[-2.11849,57.182348],"type":"Point"}
}