{
  "type": "Feature",
  "properties": {
    "iso:country":"GB",
    "wof:name":"BN8 5NR",
    "wof:placetype":"postalcode"
},
  "geometry": {"coordinates":[0.07259668344304,50.89803201286227],"type":"Point"}
}