{
  "type": "Feature",
  "properties": {
    "date:inception_lower":"1992-08-01",
    "date:inception_upper":"1992-08-31",
    "iso:country":"GB",
    "wof:name":"DH3 1PF",
    "wof:placetype":"postalcode"
},
  "geometry": {"coordinates":[-1.575855,54.897244],"type":"Point"}
}