{
  "type": "Feature",
  "properties": {
    "iso:country": "GB",
    "wof:name": "DH3 1PF",
    "wof:placetype": "postalcode"
  },
  "geometry": {"coordinates":[-1.575855,54.897244],"type":"Point"}
}
