{
  "type": "Feature",
  "properties": {
    "iso:country":"GB",
    "wof:name":"DH3 1PF",
    "wof:placetype":"postalcode"
},
  "geometry": {"coordinates":[-1.57585456755908,54.8972439015059],"type":"Point"}
}