{
  "type": "Feature",
  "properties": {
    "iso:country": "GB",
    "wof:name": "SL3 8LL",
    "wof:placetype": "postalcode"
  },
  "geometry": {"coordinates":[-0.542488,51.501371],"type":"Point"}
}
