{
  "type": "Feature",
  "properties": {
    "iso:country": "GB",
    "wof:name": "BS9 2AN",
    "wof:placetype": "postalcode"
  },
  "geometry": {"coordinates":[-2.63621,51.490237],"type":"Point"}
}
