{
  "type": "Feature",
  "properties": {
    "iso:country":"GB",
    "wof:name":"IP11 7PP",
    "wof:placetype":"postalcode"
},
  "geometry": {"coordinates":[1.34478534691285,51.96081838215327],"type":"Point"}
}