{
  "type": "Feature",
  "properties": {
    "date:inception_lower": "1980-01-01",
    "date:inception_upper": "1980-01-01",
    "iso:country": "GB",
    "wof:name": "HU17 8HY",
    "wof:placetype": "postalcode"
  },
  "geometry": {"coordinates":[-0.427931,53.837914],"type":"Point"}
}
