{
  "type": "Feature",
  "properties": {
    "iso:country":"GB",
    "wof:name":"DH4 4TA",
    "wof:placetype":"postalcode"
},
  "geometry": {"coordinates":[-1.47799446193616,54.8611329604358],"type":"Point"}
}