{
  "type": "Feature",
  "properties": {
    "date:inception_lower": "1994-05-01",
    "date:inception_upper": "1994-05-01",
    "iso:country": "GB",
    "wof:name": "M25 3EN",
    "wof:placetype": "postalcode"
  },
  "geometry": {"coordinates":[-2.283003,53.537093],"type":"Point"}
}
