{
  "type": "Feature",
  "properties": {
    "iso:country":"GB",
    "wof:name":"PR9 8AJ",
    "wof:placetype":"postalcode"
},
  "geometry": {"coordinates":[-2.88967743433911,53.63891466253718],"type":"Point"}
}