{
  "type": "Feature",
  "properties": {
    "date:inception_lower": "1980-01-01",
    "date:inception_upper": "1980-01-01",
    "iso:country": "GB",
    "wof:name": "PR9 8AJ",
    "wof:placetype": "postalcode"
  },
  "geometry": {"coordinates":[-2.889662,53.638957],"type":"Point"}
}
