{
  "type": "Feature",
  "properties": {
    "date:inception_lower": "1985-10-01",
    "date:inception_upper": "1985-10-01",
    "iso:country": "GB",
    "wof:name": "TF9 3LH",
    "wof:placetype": "postalcode"
  },
  "geometry": {"coordinates":[-2.612722,52.843873],"type":"Point"}
}
