{
  "type": "Feature",
  "properties": {
    "iso:country":"GB",
    "wof:name":"TW4 5PH",
    "wof:placetype":"postalcode"
},
  "geometry": {"coordinates":[-0.38541887452512,51.44865100369455],"type":"Point"}
}