{
  "type": "Feature",
  "properties": {
    "iso:country":"GB",
    "wof:name":"TQ5 9UW",
    "wof:placetype":"postalcode"
},
  "geometry": {"coordinates":[-3.50664295015495,50.39503198374534],"type":"Point"}
}