{
  "type": "Feature",
  "properties": {
    "iso:country":"GB",
    "wof:name":"EH9 1NJ",
    "wof:placetype":"postalcode"
},
  "geometry": {"coordinates":[-3.18239362497808,55.93858290522002],"type":"Point"}
}