{
  "type": "Feature",
  "properties": {
    "date:inception_lower": "1985-04-01",
    "date:inception_upper": "1985-04-01",
    "iso:country": "GB",
    "wof:name": "EH9 1NJ",
    "wof:placetype": "postalcode"
  },
  "geometry": {"coordinates":[-3.182394,55.938583],"type":"Point"}
}
