{
  "type": "Feature",
  "properties": {
    "date:inception_lower": "1994-12-01",
    "date:inception_upper": "1994-12-01",
    "iso:country": "GB",
    "wof:name": "SO50 9JU",
    "wof:placetype": "postalcode"
  },
  "geometry": {"coordinates":[-1.37912,50.964381],"type":"Point"}
}
