{
  "type": "Feature",
  "properties": {
    "iso:country":"GB",
    "wof:name":"SO50 9JU",
    "wof:placetype":"postalcode"
},
  "geometry": {"coordinates":[-1.3791307750657,50.96438862932677],"type":"Point"}
}