{
  "type": "Feature",
  "properties": {
    "iso:country": "GB",
    "wof:name": "BH16 6JH",
    "wof:placetype": "postalcode"
  },
  "geometry": {"coordinates":[-2.061829,50.734869],"type":"Point"}
}
