{
  "type": "Feature",
  "properties": {
    "iso:country":"GB",
    "wof:name":"BH16 6JH",
    "wof:placetype":"postalcode"
},
  "geometry": {"coordinates":[-2.06182900303425,50.73486932627702],"type":"Point"}
}