{
  "type": "Feature",
  "properties": {
    "iso:country":"GB",
    "wof:name":"WR6 6QB",
    "wof:placetype":"postalcode"
},
  "geometry": {"coordinates":[-2.34219466222951,52.23569774486046],"type":"Point"}
}