{
  "type": "Feature",
  "properties": {
    "iso:country":"GB",
    "wof:name":"CF14 2AE",
    "wof:placetype":"postalcode"
},
  "geometry": {"coordinates":[-3.22343877727376,51.51433560971306],"type":"Point"}
}