{
  "type": "Feature",
  "properties": {
    "iso:country":"GB",
    "wof:name":"OL11 4NA",
    "wof:placetype":"postalcode"
},
  "geometry": {"coordinates":[-2.17120240027298,53.60519387415295],"type":"Point"}
}