{
  "type": "Feature",
  "properties": {
    "date:inception_lower": "1980-01-01",
    "date:inception_upper": "1980-01-01",
    "iso:country": "GB",
    "wof:name": "DH8 8LZ",
    "wof:placetype": "postalcode"
  },
  "geometry": {"coordinates":[-1.847842,54.857926],"type":"Point"}
}
