{
  "type": "Feature",
  "properties": {
    "iso:country":"GB",
    "wof:name":"GL54 3LL",
    "wof:placetype":"postalcode"
},
  "geometry": {"coordinates":[-1.89730422631857,51.81570194466413],"type":"Point"}
}