{
  "type": "Feature",
  "properties": {
    "iso:country":"GB",
    "wof:name":"LU1 4ER",
    "wof:placetype":"postalcode"
},
  "geometry": {"coordinates":[-0.46064251379811,51.8604069422924],"type":"Point"}
}