{
  "type": "Feature",
  "properties": {
    "iso:country": "GB",
    "wof:name": "LU1 4ER",
    "wof:placetype": "postalcode"
  },
  "geometry": {"coordinates":[-0.460642,51.860407],"type":"Point"}
}
