{
  "type": "Feature",
  "properties": {
    "iso:country":"GB",
    "wof:name":"WD19 7HL",
    "wof:placetype":"postalcode"
},
  "geometry": {"coordinates":[-0.3957048120729,51.62551592144177],"type":"Point"}
}