{
  "type": "Feature",
  "properties": {
    "iso:country":"GB",
    "wof:name":"CA10 3DY",
    "wof:placetype":"postalcode"
},
  "geometry": {"coordinates":[-2.69764897007643,54.58236787172552],"type":"Point"}
}