{
  "type": "Feature",
  "properties": {
    "date:inception_lower": "2011-05-01",
    "date:inception_upper": "2011-05-01",
    "iso:country": "GB",
    "wof:name": "KT17 4AE",
    "wof:placetype": "postalcode"
  },
  "geometry": {"coordinates":[-0.25546,51.326721],"type":"Point"}
}
