{
  "type": "Feature",
  "properties": {
    "iso:country": "GB",
    "wof:name": "KT17 4AE",
    "wof:placetype": "postalcode"
  },
  "geometry": {"coordinates":[-0.25546,51.326721],"type":"Point"}
}
