{
  "type": "Feature",
  "properties": {
    "iso:country":"GB",
    "wof:name":"KT17 4AE",
    "wof:placetype":"postalcode"
},
  "geometry": {"coordinates":[-0.25545967515735,51.32672054187331],"type":"Point"}
}