{
  "type": "Feature",
  "properties": {
    "iso:country": "GB",
    "wof:name": "LN9 5HA",
    "wof:placetype": "postalcode"
  },
  "geometry": {"coordinates":[-0.120274,53.210631],"type":"Point"}
}
