{
  "type": "Feature",
  "properties": {
    "date:inception_lower":"1990-07-01",
    "date:inception_upper":"1990-07-31",
    "iso:country":"GB",
    "wof:name":"LN9 5HA",
    "wof:placetype":"postalcode"
},
  "geometry": {"coordinates":[-0.120274,53.210631],"type":"Point"}
}