{
  "type": "Feature",
  "properties": {
    "iso:country":"GB",
    "wof:name":"LS15 4BD",
    "wof:placetype":"postalcode"
},
  "geometry": {"coordinates":[-1.43134661825381,53.82795316931463],"type":"Point"}
}