{
  "type": "Feature",
  "properties": {
    "date:inception_lower":"2011-07-01",
    "date:inception_upper":"2011-07-31",
    "iso:country":"GB",
    "wof:name":"LS15 4BD",
    "wof:placetype":"postalcode"
},
  "geometry": {"coordinates":[-1.431347,53.827953],"type":"Point"}
}