{
  "type": "Feature",
  "properties": {
    "iso:country": "GB",
    "wof:name": "DY9 8PT",
    "wof:placetype": "postalcode"
  },
  "geometry": {"coordinates":[-2.106509,52.459624],"type":"Point"}
}
