{
  "type": "Feature",
  "properties": {
    "iso:country":"GB",
    "wof:name":"CW2 8DB",
    "wof:placetype":"postalcode"
},
  "geometry": {"coordinates":[-2.4631853942308,53.08223723204345],"type":"Point"}
}