{
  "type": "Feature",
  "properties": {
    "date:inception_lower": "2023-04-01",
    "date:inception_upper": "2023-04-01",
    "iso:country": "GB",
    "wof:name": "WC2H 8ED",
    "wof:placetype": "postalcode"
  },
  "geometry": {"coordinates":[-0.125629,51.516404],"type":"Point"}
}
