{
  "type": "Feature",
  "properties": {
    "iso:country":"GB",
    "wof:name":"TN39 4RQ",
    "wof:placetype":"postalcode"
},
  "geometry": {"coordinates":[0.43583703853315,50.84814083017096],"type":"Point"}
}