{
  "type": "Feature",
  "properties": {
    "iso:country":"GB",
    "wof:name":"IP21 4AA",
    "wof:placetype":"postalcode"
},
  "geometry": {"coordinates":[1.1295397950513,52.36526344572133],"type":"Point"}
}