{
  "type": "Feature",
  "properties": {
    "date:inception_lower": "1980-01-01",
    "date:inception_upper": "1980-01-01",
    "iso:country": "GB",
    "wof:name": "IP21 4AA",
    "wof:placetype": "postalcode"
  },
  "geometry": {"coordinates":[1.128954,52.365326],"type":"Point"}
}
