{
  "type": "Feature",
  "properties": {
    "date:inception_lower": "1980-01-01",
    "date:inception_upper": "1980-01-01",
    "iso:country": "GB",
    "wof:name": "IP21 4AA",
    "wof:placetype": "postalcode"
  },
  "geometry": {"coordinates":[1.128941,52.365354],"type":"Point"}
}
