{
  "type": "Feature",
  "properties": {
    "iso:country":"GB",
    "wof:name":"GU2 7QE",
    "wof:placetype":"postalcode"
},
  "geometry": {"coordinates":[-0.59645007213815,51.23240472968311],"type":"Point"}
}