{
  "type": "Feature",
  "properties": {
    "iso:country":"GB",
    "wof:name":"EH48 2NT",
    "wof:placetype":"postalcode"
},
  "geometry": {"coordinates":[-3.69890113573246,55.89858248217225],"type":"Point"}
}