{
  "type": "Feature",
  "properties": {
    "iso:country": "GB",
    "wof:name": "ML3 9QP",
    "wof:placetype": "postalcode"
  },
  "geometry": {"coordinates":[-4.093493,55.776174],"type":"Point"}
}
