{
  "type": "Feature",
  "properties": {
    "date:inception_lower":"1980-01-01",
    "date:inception_upper":"1980-01-31",
    "iso:country":"GB",
    "wof:name":"ML3 9QP",
    "wof:placetype":"postalcode"
},
  "geometry": {"coordinates":[-4.093493,55.776174],"type":"Point"}
}