{
  "type": "Feature",
  "properties": {
    "iso:country":"GB",
    "wof:name":"WF15 8LJ",
    "wof:placetype":"postalcode"
},
  "geometry": {"coordinates":[-1.72910005134194,53.71376784819159],"type":"Point"}
}