{
  "type": "Feature",
  "properties": {
    "date:inception_lower": "1984-02-01",
    "date:inception_upper": "1984-02-01",
    "iso:country": "GB",
    "wof:name": "B31 3XE",
    "wof:placetype": "postalcode"
  },
  "geometry": {"coordinates":[-1.959031,52.407235],"type":"Point"}
}
