{
  "type": "Feature",
  "properties": {
    "iso:country": "GB",
    "wof:name": "W5 2UA",
    "wof:placetype": "postalcode"
  },
  "geometry": {"coordinates":[-0.311912,51.513081],"type":"Point"}
}
