{
  "type": "Feature",
  "properties": {
    "iso:country":"GB",
    "wof:name":"W5 2UA",
    "wof:placetype":"postalcode"
},
  "geometry": {"coordinates":[-0.3120212884759,51.51306363872555],"type":"Point"}
}