{
  "type": "Feature",
  "properties": {
    "date:inception_lower":"1980-01-01",
    "date:inception_upper":"1980-01-31",
    "iso:country":"GB",
    "wof:name":"W5 2UA",
    "wof:placetype":"postalcode"
},
  "geometry": {"coordinates":[-0.311912,51.513081],"type":"Point"}
}