{
  "type": "Feature",
  "properties": {
    "iso:country":"GB",
    "wof:name":"DE1 2FT",
    "wof:placetype":"postalcode"
},
  "geometry": {"coordinates":[-1.47421675127808,52.92345366942391],"type":"Point"}
}