{
  "type": "Feature",
  "properties": {
    "iso:country":"GB",
    "wof:name":"L2 2HJ",
    "wof:placetype":"postalcode"
},
  "geometry": {"coordinates":[-2.98798117975619,53.40842673218515],"type":"Point"}
}