{
  "type": "Feature",
  "properties": {
    "date:inception_lower": "1980-01-01",
    "date:inception_upper": "1980-01-01",
    "iso:country": "GB",
    "wof:name": "L2 2HJ",
    "wof:placetype": "postalcode"
  },
  "geometry": {"coordinates":[-2.98795,53.408399],"type":"Point"}
}
