{
  "type": "Feature",
  "properties": {
    "iso:country":"GB",
    "wof:name":"HG1 5NS",
    "wof:placetype":"postalcode"
},
  "geometry": {"coordinates":[-1.52924827170311,53.99325966208761],"type":"Point"}
}