{
  "type": "Feature",
  "properties": {
    "iso:country":"GB",
    "wof:name":"CB23 8BU",
    "wof:placetype":"postalcode"
},
  "geometry": {"coordinates":[0.01658756099515,52.24037911560826],"type":"Point"}
}