{
  "type": "Feature",
  "properties": {
    "date:inception_lower": "2018-08-01",
    "date:inception_upper": "2018-08-01",
    "iso:country": "GB",
    "wof:name": "MK18 3GN",
    "wof:placetype": "postalcode"
  },
  "geometry": {"coordinates":[-0.887577,51.945923],"type":"Point"}
}
