{
  "type": "Feature",
  "properties": {
    "iso:country": "GB",
    "wof:name": "S80 2RX",
    "wof:placetype": "postalcode"
  },
  "geometry": {"coordinates":[-1.115788,53.300093],"type":"Point"}
}
