{
  "type": "Feature",
  "properties": {
    "date:inception_lower": "1980-01-01",
    "date:inception_upper": "1980-01-01",
    "iso:country": "GB",
    "wof:name": "SA18 1PR",
    "wof:placetype": "postalcode"
  },
  "geometry": {"coordinates":[-3.872681,51.784032],"type":"Point"}
}
