{
  "type": "Feature",
  "properties": {
    "iso:country":"GB",
    "wof:name":"SA18 1PR",
    "wof:placetype":"postalcode"
},
  "geometry": {"coordinates":[-3.87268119165019,51.78403234516928],"type":"Point"}
}