{
  "type": "Feature",
  "properties": {
    "iso:country":"GB",
    "wof:name":"WA7 1EE",
    "wof:placetype":"postalcode"
},
  "geometry": {"coordinates":[-2.74000065565539,53.34121434018871],"type":"Point"}
}