{
  "type": "Feature",
  "properties": {
    "date:inception_lower":"2000-12-01",
    "date:inception_upper":"2000-12-31",
    "iso:country":"GB",
    "wof:name":"NN1 1BQ",
    "wof:placetype":"postalcode"
},
  "geometry": {"coordinates":[-0.901689,52.232145],"type":"Point"}
}