{
  "type": "Feature",
  "properties": {
    "iso:country":"GB",
    "wof:name":"NN1 1BQ",
    "wof:placetype":"postalcode"
},
  "geometry": {"coordinates":[-0.90317139224085,52.23081333591272],"type":"Point"}
}