{
  "type": "Feature",
  "properties": {
    "iso:country":"GB",
    "wof:name":"B90 4YS",
    "wof:placetype":"postalcode"
},
  "geometry": {"coordinates":[-1.78614718721812,52.38878122887703],"type":"Point"}
}