{
  "type": "Feature",
  "properties": {
    "iso:country": "GB",
    "wof:name": "B90 4YS",
    "wof:placetype": "postalcode"
  },
  "geometry": {"coordinates":[-1.786147,52.388781],"type":"Point"}
}
