{
  "type": "Feature",
  "properties": {
    "date:inception_lower":"1991-09-01",
    "date:inception_upper":"1991-09-30",
    "iso:country":"GB",
    "wof:name":"B90 4YS",
    "wof:placetype":"postalcode"
},
  "geometry": {"coordinates":[-1.786147,52.388781],"type":"Point"}
}