{
  "type": "Feature",
  "properties": {
    "iso:country":"GB",
    "wof:name":"CB11 4NA",
    "wof:placetype":"postalcode"
},
  "geometry": {"coordinates":[0.13884145327766,52.03805538340659],"type":"Point"}
}