{
  "type": "Feature",
  "properties": {
    "iso:country":"GB",
    "wof:name":"NR18 0JE",
    "wof:placetype":"postalcode"
},
  "geometry": {"coordinates":[1.11555333116588,52.58028763192622],"type":"Point"}
}