{
  "type": "Feature",
  "properties": {
    "iso:country":"GB",
    "wof:name":"DY3 2UJ",
    "wof:placetype":"postalcode"
},
  "geometry": {"coordinates":[-2.13548202425484,52.51994352423215],"type":"Point"}
}