{
  "type": "Feature",
  "properties": {
    "date:inception_lower": "1980-01-01",
    "date:inception_upper": "1980-01-01",
    "iso:country": "GB",
    "wof:name": "CV21 1NQ",
    "wof:placetype": "postalcode"
  },
  "geometry": {"coordinates":[-1.248712,52.38916],"type":"Point"}
}
