{
  "type": "Feature",
  "properties": {
    "iso:country":"GB",
    "wof:name":"CT6 8AU",
    "wof:placetype":"postalcode"
},
  "geometry": {"coordinates":[1.08565480870649,51.36692510673534],"type":"Point"}
}