{
  "type": "Feature",
  "properties": {
    "date:inception_lower": "1980-01-01",
    "date:inception_upper": "1980-01-01",
    "iso:country": "GB",
    "wof:name": "CT6 8AU",
    "wof:placetype": "postalcode"
  },
  "geometry": {"coordinates":[1.085655,51.366925],"type":"Point"}
}
