{
  "type": "Feature",
  "properties": {
    "iso:country": "GB",
    "wof:name": "SY8 4LW",
    "wof:placetype": "postalcode"
  },
  "geometry": {"coordinates":[-2.636997,52.309553],"type":"Point"}
}
