{
  "type": "Feature",
  "properties": {
    "iso:country":"GB",
    "wof:name":"SY8 4LW",
    "wof:placetype":"postalcode"
},
  "geometry": {"coordinates":[-2.63699678924989,52.30955334173454],"type":"Point"}
}