{
  "type": "Feature",
  "properties": {
    "date:inception_lower": "1997-06-01",
    "date:inception_upper": "1997-06-01",
    "iso:country": "GB",
    "wof:name": "M24 5JJ",
    "wof:placetype": "postalcode"
  },
  "geometry": {"coordinates":[-2.217516,53.56282],"type":"Point"}
}
