{
  "type": "Feature",
  "properties": {
    "iso:country":"GB",
    "wof:name":"EH21 7PW",
    "wof:placetype":"postalcode"
},
  "geometry": {"coordinates":[-3.02885698527778,55.94429191078842],"type":"Point"}
}