{
  "type": "Feature",
  "properties": {
    "date:inception_lower":"1980-01-01",
    "date:inception_upper":"1980-01-31",
    "iso:country":"GB",
    "wof:name":"S81 9EF",
    "wof:placetype":"postalcode"
},
  "geometry": {"coordinates":[-1.11496,53.347377],"type":"Point"}
}