{
  "type": "Feature",
  "properties": {
    "iso:country":"GB",
    "wof:name":"S81 9EF",
    "wof:placetype":"postalcode"
},
  "geometry": {"coordinates":[-1.11496005984045,53.34737657703644],"type":"Point"}
}