{
  "type": "Feature",
  "properties": {
    "iso:country": "GB",
    "wof:name": "S81 9EF",
    "wof:placetype": "postalcode"
  },
  "geometry": {"coordinates":[-1.11496,53.347377],"type":"Point"}
}
