{
  "type": "Feature",
  "properties": {
    "iso:country":"GB",
    "wof:name":"EN3 6RQ",
    "wof:placetype":"postalcode"
},
  "geometry": {"coordinates":[-0.03952618698455,51.67722827147099],"type":"Point"}
}