{
  "type": "Feature",
  "properties": {
    "date:inception_lower":"1980-01-01",
    "date:inception_upper":"1980-01-31",
    "iso:country":"GB",
    "wof:name":"EN3 6RQ",
    "wof:placetype":"postalcode"
},
  "geometry": {"coordinates":[-0.039526,51.677228],"type":"Point"}
}