{
  "type": "Feature",
  "properties": {
    "iso:country":"GB",
    "wof:name":"FK1 5LA",
    "wof:placetype":"postalcode"
},
  "geometry": {"coordinates":[-3.79737439988932,55.98800965544145],"type":"Point"}
}