{
  "type": "Feature",
  "properties": {
    "iso:country": "GB",
    "wof:name": "NE23 7HJ",
    "wof:placetype": "postalcode"
  },
  "geometry": {"coordinates":[-1.552085,55.066334],"type":"Point"}
}
