{
  "type": "Feature",
  "properties": {
    "date:inception_lower": "1992-08-01",
    "date:inception_upper": "1992-08-01",
    "iso:country": "GB",
    "wof:name": "NE23 7HJ",
    "wof:placetype": "postalcode"
  },
  "geometry": {"coordinates":[-1.552085,55.066334],"type":"Point"}
}
