{
  "type": "Feature",
  "properties": {
    "iso:country":"GB",
    "wof:name":"NE23 7HJ",
    "wof:placetype":"postalcode"
},
  "geometry": {"coordinates":[-1.55208524917436,55.06633427102654],"type":"Point"}
}