{
  "type": "Feature",
  "properties": {
    "iso:country":"GB",
    "wof:name":"TW4 7EN",
    "wof:placetype":"postalcode"
},
  "geometry": {"coordinates":[-0.38391086668303,51.47179444644635],"type":"Point"}
}