{
  "type": "Feature",
  "properties": {
    "date:inception_lower": "1980-01-01",
    "date:inception_upper": "1980-01-01",
    "iso:country": "GB",
    "wof:name": "CA22 2UG",
    "wof:placetype": "postalcode"
  },
  "geometry": {"coordinates":[-3.556382,54.463332],"type":"Point"}
}
