{
  "type": "Feature",
  "properties": {
    "iso:country":"GB",
    "wof:name":"SK14 5RZ",
    "wof:placetype":"postalcode"
},
  "geometry": {"coordinates":[-2.07060080438072,53.44414323830492],"type":"Point"}
}