{
  "type": "Feature",
  "properties": {
    "iso:country":"GB",
    "wof:name":"CM23 3NH",
    "wof:placetype":"postalcode"
},
  "geometry": {"coordinates":[0.16171523379792,51.85764783924908],"type":"Point"}
}