{
  "type": "Feature",
  "properties": {
    "iso:country": "GB",
    "wof:name": "SA3 1BG",
    "wof:placetype": "postalcode"
  },
  "geometry": {"coordinates":[-4.148343,51.596645],"type":"Point"}
}
