{
  "type": "Feature",
  "properties": {
    "date:inception_lower": "1980-01-01",
    "date:inception_upper": "1980-01-01",
    "iso:country": "GB",
    "wof:name": "SK3 0QS",
    "wof:placetype": "postalcode"
  },
  "geometry": {"coordinates":[-2.199327,53.399891],"type":"Point"}
}
