{
  "type": "Feature",
  "properties": {
    "iso:country":"GB",
    "wof:name":"HA6 1DT",
    "wof:placetype":"postalcode"
},
  "geometry": {"coordinates":[-0.42095523500974,51.60937577771318],"type":"Point"}
}