{
  "type": "Feature",
  "properties": {
    "date:inception_lower": "1980-01-01",
    "date:inception_upper": "1980-01-01",
    "iso:country": "GB",
    "wof:name": "HA6 1DT",
    "wof:placetype": "postalcode"
  },
  "geometry": {"coordinates":[-0.420852,51.609252],"type":"Point"}
}
