{
  "type": "Feature",
  "properties": {
    "iso:country":"GB",
    "wof:name":"N21 1AU",
    "wof:placetype":"postalcode"
},
  "geometry": {"coordinates":[-0.10214961638626,51.63724281199536],"type":"Point"}
}