{
  "type": "Feature",
  "properties": {
    "date:inception_lower": "1980-01-01",
    "date:inception_upper": "1980-01-01",
    "iso:country": "GB",
    "wof:name": "NR16 2SF",
    "wof:placetype": "postalcode"
  },
  "geometry": {"coordinates":[0.913505,52.42501],"type":"Point"}
}
