{
  "type": "Feature",
  "properties": {
    "iso:country":"GB",
    "wof:name":"NR16 2SF",
    "wof:placetype":"postalcode"
},
  "geometry": {"coordinates":[0.91350471025844,52.42500999956978],"type":"Point"}
}