{
  "type": "Feature",
  "properties": {
    "iso:country": "GB",
    "wof:name": "WR5 3AG",
    "wof:placetype": "postalcode"
  },
  "geometry": {"coordinates":[-2.216243,52.181095],"type":"Point"}
}
