{
  "type": "Feature",
  "properties": {
    "date:inception_lower": "1980-01-01",
    "date:inception_upper": "1980-01-01",
    "iso:country": "GB",
    "wof:name": "CH7 2QS",
    "wof:placetype": "postalcode"
  },
  "geometry": {"coordinates":[-3.091653,53.172825],"type":"Point"}
}
