{
  "type": "Feature",
  "properties": {
    "iso:country": "GB",
    "wof:name": "NR33 8AP",
    "wof:placetype": "postalcode"
  },
  "geometry": {"coordinates":[1.697644,52.451881],"type":"Point"}
}
