{
  "type": "Feature",
  "properties": {
    "iso:country":"GB",
    "wof:name":"NR33 8AP",
    "wof:placetype":"postalcode"
},
  "geometry": {"coordinates":[1.69764383658831,52.45188084825918],"type":"Point"}
}