{
  "type": "Feature",
  "properties": {
    "iso:country": "GB",
    "wof:name": "SW19 8LB",
    "wof:placetype": "postalcode"
  },
  "geometry": {"coordinates":[-0.197685,51.424459],"type":"Point"}
}
