{
  "type": "Feature",
  "properties": {
    "iso:country":"GB",
    "wof:name":"S81 8NA",
    "wof:placetype":"postalcode"
},
  "geometry": {"coordinates":[-1.16575789140588,53.31994860877008],"type":"Point"}
}