{
  "type": "Feature",
  "properties": {
    "iso:country": "GB",
    "wof:name": "S81 8NA",
    "wof:placetype": "postalcode"
  },
  "geometry": {"coordinates":[-1.165758,53.319949],"type":"Point"}
}
