{
  "type": "Feature",
  "properties": {
    "iso:country":"GB",
    "wof:name":"HS9 5XS",
    "wof:placetype":"postalcode"
},
  "geometry": {"coordinates":[-7.50207733624489,56.9843144829505],"type":"Point"}
}