{
  "type": "Feature",
  "properties": {
    "iso:country":"GB",
    "wof:name":"CT16 2QZ",
    "wof:placetype":"postalcode"
},
  "geometry": {"coordinates":[1.2871227386515,51.15181164743059],"type":"Point"}
}