{
  "type": "Feature",
  "properties": {
    "iso:country": "GB",
    "wof:name": "CT16 2QZ",
    "wof:placetype": "postalcode"
  },
  "geometry": {"coordinates":[1.287123,51.151812],"type":"Point"}
}
