{
  "type": "Feature",
  "properties": {
    "iso:country":"GB",
    "wof:name":"LA5 0UH",
    "wof:placetype":"postalcode"
},
  "geometry": {"coordinates":[-2.81180286122872,54.18060349217568],"type":"Point"}
}