{
  "type": "Feature",
  "properties": {
    "iso:country": "GB",
    "wof:name": "TS6 0SX",
    "wof:placetype": "postalcode"
  },
  "geometry": {"coordinates":[-1.162815,54.553797],"type":"Point"}
}
