{
  "type": "Feature",
  "properties": {
    "iso:country":"GB",
    "wof:name":"B90 4DB",
    "wof:placetype":"postalcode"
},
  "geometry": {"coordinates":[-1.82454738997416,52.39483178163228],"type":"Point"}
}