{
  "type": "Feature",
  "properties": {
    "iso:country":"GB",
    "wof:name":"TQ2 6UF",
    "wof:placetype":"postalcode"
},
  "geometry": {"coordinates":[-3.55902894211895,50.45905150523943],"type":"Point"}
}