{
  "type": "Feature",
  "properties": {
    "iso:country": "GB",
    "wof:name": "CM11 1RP",
    "wof:placetype": "postalcode"
  },
  "geometry": {"coordinates":[0.480322,51.617864],"type":"Point"}
}
