{
  "type": "Feature",
  "properties": {
    "iso:country":"GB",
    "wof:name":"CM11 1RP",
    "wof:placetype":"postalcode"
},
  "geometry": {"coordinates":[0.48032227912348,51.61786376673982],"type":"Point"}
}