{
  "type": "Feature",
  "properties": {
    "iso:country":"GB",
    "wof:name":"GL3 2ES",
    "wof:placetype":"postalcode"
},
  "geometry": {"coordinates":[-2.16717632253419,51.87592959212257],"type":"Point"}
}