{
  "type": "Feature",
  "properties": {
    "date:inception_lower": "1980-01-01",
    "date:inception_upper": "1980-01-01",
    "iso:country": "GB",
    "wof:name": "GL3 2ES",
    "wof:placetype": "postalcode"
  },
  "geometry": {"coordinates":[-2.167176,51.87593],"type":"Point"}
}
