{
  "type": "Feature",
  "properties": {
    "iso:country":"GB",
    "wof:name":"ML10 6TP",
    "wof:placetype":"postalcode"
},
  "geometry": {"coordinates":[-4.02663991251498,55.70221662612866],"type":"Point"}
}