{
  "type": "Feature",
  "properties": {
    "iso:country": "GB",
    "wof:name": "ML10 6TP",
    "wof:placetype": "postalcode"
  },
  "geometry": {"coordinates":[-4.02664,55.702217],"type":"Point"}
}
