{
  "type": "Feature",
  "properties": {
    "date:inception_lower": "2000-12-01",
    "date:inception_upper": "2000-12-01",
    "iso:country": "GB",
    "wof:name": "BN1 9RX",
    "wof:placetype": "postalcode"
  },
  "geometry": {"coordinates":[-0.083705,50.866294],"type":"Point"}
}
