{
  "type": "Feature",
  "properties": {
    "iso:country":"GB",
    "wof:name":"BN1 9RX",
    "wof:placetype":"postalcode"
},
  "geometry": {"coordinates":[-0.08370473299612,50.86629388093446],"type":"Point"}
}