{
  "type": "Feature",
  "properties": {
    "iso:country":"GB",
    "wof:name":"WN2 4EU",
    "wof:placetype":"postalcode"
},
  "geometry": {"coordinates":[-2.55265064321744,53.53380391317987],"type":"Point"}
}