{
  "type": "Feature",
  "properties": {
    "iso:country": "GB",
    "wof:name": "WN2 4EU",
    "wof:placetype": "postalcode"
  },
  "geometry": {"coordinates":[-2.552651,53.533804],"type":"Point"}
}
