{
  "type": "Feature",
  "properties": {
    "iso:country":"GB",
    "wof:name":"LL13 7UG",
    "wof:placetype":"postalcode"
},
  "geometry": {"coordinates":[-3.00460118334745,53.04039546758678],"type":"Point"}
}