{
  "type": "Feature",
  "properties": {
    "iso:country":"GB",
    "wof:name":"SK8 1AL",
    "wof:placetype":"postalcode"
},
  "geometry": {"coordinates":[-2.21441848744953,53.39513660239745],"type":"Point"}
}