{
  "type": "Feature",
  "properties": {
    "date:inception_lower": "1991-07-01",
    "date:inception_upper": "1991-07-01",
    "iso:country": "GB",
    "wof:name": "IV55 8WH",
    "wof:placetype": "postalcode"
  },
  "geometry": {"coordinates":[-6.569027,57.429371],"type":"Point"}
}
