{
  "type": "Feature",
  "properties": {
    "iso:country":"GB",
    "wof:name":"IV55 8WH",
    "wof:placetype":"postalcode"
},
  "geometry": {"coordinates":[-6.56902690938264,57.42937086457378],"type":"Point"}
}