{
  "type": "Feature",
  "properties": {
    "iso:country": "GB",
    "wof:name": "LU7 0PZ",
    "wof:placetype": "postalcode"
  },
  "geometry": {"coordinates":[-0.691223,51.888104],"type":"Point"}
}
