{
  "type": "Feature",
  "properties": {
    "iso:country":"GB",
    "wof:name":"LU7 0PZ",
    "wof:placetype":"postalcode"
},
  "geometry": {"coordinates":[-0.69131844466417,51.88815913204503],"type":"Point"}
}