{
  "type": "Feature",
  "properties": {
    "iso:country":"GB",
    "wof:name":"SA14 7TP",
    "wof:placetype":"postalcode"
},
  "geometry": {"coordinates":[-4.04497023683981,51.82898177309584],"type":"Point"}
}