{
  "type": "Feature",
  "properties": {
    "iso:country": "GB",
    "wof:name": "DE5 3TP",
    "wof:placetype": "postalcode"
  },
  "geometry": {"coordinates":[-1.40233,53.040947],"type":"Point"}
}
