{
  "type": "Feature",
  "properties": {
    "iso:country":"GB",
    "wof:name":"CM1 3EW",
    "wof:placetype":"postalcode"
},
  "geometry": {"coordinates":[0.43323942185883,51.73114577882923],"type":"Point"}
}