{
  "type": "Feature",
  "properties": {
    "iso:country": "GB",
    "wof:name": "CM1 3EW",
    "wof:placetype": "postalcode"
  },
  "geometry": {"coordinates":[0.433239,51.731146],"type":"Point"}
}
