{
  "type": "Feature",
  "properties": {
    "iso:country": "GB",
    "wof:name": "CM15 0JA",
    "wof:placetype": "postalcode"
  },
  "geometry": {"coordinates":[0.287996,51.664595],"type":"Point"}
}
