{
  "type": "Feature",
  "properties": {
    "date:inception_lower": "2007-09-01",
    "date:inception_upper": "2007-09-01",
    "iso:country": "GB",
    "wof:name": "CM15 0JA",
    "wof:placetype": "postalcode"
  },
  "geometry": {"coordinates":[0.287996,51.664595],"type":"Point"}
}
