{
  "type": "Feature",
  "properties": {
    "iso:country":"GB",
    "wof:name":"MK5 6EL",
    "wof:placetype":"postalcode"
},
  "geometry": {"coordinates":[-0.79248074071617,52.02741785978336],"type":"Point"}
}