{
  "type": "Feature",
  "properties": {
    "iso:country":"GB",
    "wof:name":"LN6 0FL",
    "wof:placetype":"postalcode"
},
  "geometry": {"coordinates":[-0.61288274018807,53.21795838086277],"type":"Point"}
}