{
  "type": "Feature",
  "properties": {
    "iso:country":"GB",
    "wof:name":"CB7 5RN",
    "wof:placetype":"postalcode"
},
  "geometry": {"coordinates":[0.41228679028057,52.34452939971791],"type":"Point"}
}