{
  "type": "Feature",
  "properties": {
    "date:inception_lower": "1991-01-01",
    "date:inception_upper": "1991-01-01",
    "iso:country": "GB",
    "wof:name": "CB7 5RN",
    "wof:placetype": "postalcode"
  },
  "geometry": {"coordinates":[0.41257,52.344684],"type":"Point"}
}
