{
  "type": "Feature",
  "properties": {
    "iso:country":"GB",
    "wof:name":"OX16 0BX",
    "wof:placetype":"postalcode"
},
  "geometry": {"coordinates":[-1.34658127301958,52.06349402078508],"type":"Point"}
}