{
  "type": "Feature",
  "properties": {
    "iso:country": "GB",
    "wof:name": "NR34 9EU",
    "wof:placetype": "postalcode"
  },
  "geometry": {"coordinates":[1.574368,52.443503],"type":"Point"}
}
