{
  "type": "Feature",
  "properties": {
    "iso:country":"GB",
    "wof:name":"N1 5DR",
    "wof:placetype":"postalcode"
},
  "geometry": {"coordinates":[-0.08682857544605,51.53352678870991],"type":"Point"}
}