{
  "type": "Feature",
  "properties": {
    "iso:country":"GB",
    "wof:name":"NG3 5LP",
    "wof:placetype":"postalcode"
},
  "geometry": {"coordinates":[-1.12291668468033,52.98730078191746],"type":"Point"}
}