{
  "type": "Feature",
  "properties": {
    "iso:country":"GB",
    "wof:name":"HU18 1SG",
    "wof:placetype":"postalcode"
},
  "geometry": {"coordinates":[-0.17007519000875,53.90451820876361],"type":"Point"}
}