{
  "type": "Feature",
  "properties": {
    "iso:country":"GB",
    "wof:name":"NR2 4SL",
    "wof:placetype":"postalcode"
},
  "geometry": {"coordinates":[1.29686225147918,52.63073929697143],"type":"Point"}
}