{
  "type": "Feature",
  "properties": {
    "iso:country":"GB",
    "wof:name":"HP17 8RA",
    "wof:placetype":"postalcode"
},
  "geometry": {"coordinates":[-0.85759311697032,51.80271042446869],"type":"Point"}
}