{
  "type": "Feature",
  "properties": {
    "iso:country":"GB",
    "wof:name":"CM9 5EE",
    "wof:placetype":"postalcode"
},
  "geometry": {"coordinates":[0.68174868734885,51.72450267913517],"type":"Point"}
}