{
  "type": "Feature",
  "properties": {
    "date:inception_lower":"1995-12-01",
    "date:inception_upper":"1995-12-31",
    "iso:country":"GB",
    "wof:name":"HU12 8PH",
    "wof:placetype":"postalcode"
},
  "geometry": {"coordinates":[-0.18867,53.735631],"type":"Point"}
}