{
  "type": "Feature",
  "properties": {
    "iso:country":"GB",
    "wof:name":"CF82 8AS",
    "wof:placetype":"postalcode"
},
  "geometry": {"coordinates":[-3.22730505725482,51.66229118391357],"type":"Point"}
}