{
  "type": "Feature",
  "properties": {
    "iso:country": "GB",
    "wof:name": "CF82 8AS",
    "wof:placetype": "postalcode"
  },
  "geometry": {"coordinates":[-3.227305,51.662291],"type":"Point"}
}
