{
  "type": "Feature",
  "properties": {
    "date:inception_lower":"1995-07-01",
    "date:inception_upper":"1995-07-31",
    "iso:country":"GB",
    "wof:name":"CF82 8AS",
    "wof:placetype":"postalcode"
},
  "geometry": {"coordinates":[-3.227305,51.662291],"type":"Point"}
}