{
  "type": "Feature",
  "properties": {
    "date:inception_lower": "2017-02-01",
    "date:inception_upper": "2017-02-01",
    "iso:country": "GB",
    "wof:name": "E8 1AA",
    "wof:placetype": "postalcode"
  },
  "geometry": {"coordinates":[-0.061661,51.547998],"type":"Point"}
}
