{
  "type": "Feature",
  "properties": {
    "iso:country": "GB",
    "wof:name": "CH62 9AE",
    "wof:placetype": "postalcode"
  },
  "geometry": {"coordinates":[-2.965142,53.313213],"type":"Point"}
}
