{
  "type": "Feature",
  "properties": {
    "iso:country":"GB",
    "wof:name":"TR14 9EH",
    "wof:placetype":"postalcode"
},
  "geometry": {"coordinates":[-5.27760709716913,50.19700643412019],"type":"Point"}
}