{
  "type": "Feature",
  "properties": {
    "iso:country": "GB",
    "wof:name": "HD3 3YS",
    "wof:placetype": "postalcode"
  },
  "geometry": {"coordinates":[-1.872512,53.65748],"type":"Point"}
}
