{
  "type": "Feature",
  "properties": {
    "iso:country":"GB",
    "wof:name":"SG13 8LG",
    "wof:placetype":"postalcode"
},
  "geometry": {"coordinates":[-0.13586603502882,51.77065244509444],"type":"Point"}
}