{
  "type": "Feature",
  "properties": {
    "date:inception_lower": "1980-01-01",
    "date:inception_upper": "1980-01-01",
    "iso:country": "GB",
    "wof:name": "SG13 8LG",
    "wof:placetype": "postalcode"
  },
  "geometry": {"coordinates":[-0.134799,51.771289],"type":"Point"}
}
