{
  "type": "Feature",
  "properties": {
    "iso:country": "GB",
    "wof:name": "EX32 9ET",
    "wof:placetype": "postalcode"
  },
  "geometry": {"coordinates":[-4.044802,51.06589],"type":"Point"}
}
