{
  "type": "Feature",
  "properties": {
    "date:inception_lower": "1980-01-01",
    "date:inception_upper": "1980-01-01",
    "iso:country": "GB",
    "wof:name": "EX32 9ET",
    "wof:placetype": "postalcode"
  },
  "geometry": {"coordinates":[-4.044802,51.06589],"type":"Point"}
}
