{
  "type": "Feature",
  "properties": {
    "iso:country":"GB",
    "wof:name":"CO10 8JJ",
    "wof:placetype":"postalcode"
},
  "geometry": {"coordinates":[0.54351607144695,52.05314100850747],"type":"Point"}
}