{
  "type": "Feature",
  "properties": {
    "iso:country": "GB",
    "wof:name": "CO10 8JJ",
    "wof:placetype": "postalcode"
  },
  "geometry": {"coordinates":[0.543516,52.053141],"type":"Point"}
}
