{
  "type": "Feature",
  "properties": {
    "iso:country":"GB",
    "wof:name":"LS17 5BT",
    "wof:placetype":"postalcode"
},
  "geometry": {"coordinates":[-1.54666547701981,53.84292373237191],"type":"Point"}
}