{
  "type": "Feature",
  "properties": {
    "iso:country":"GB",
    "wof:name":"G34 0BX",
    "wof:placetype":"postalcode"
},
  "geometry": {"coordinates":[-4.09607722719056,55.86848212675137],"type":"Point"}
}