{
  "type": "Feature",
  "properties": {
    "iso:country":"GB",
    "wof:name":"CV35 8QH",
    "wof:placetype":"postalcode"
},
  "geometry": {"coordinates":[-1.62922755988309,52.29276460245735],"type":"Point"}
}