{
  "type": "Feature",
  "properties": {
    "iso:country":"GB",
    "wof:name":"BN12 5HE",
    "wof:placetype":"postalcode"
},
  "geometry": {"coordinates":[-0.44128798565637,50.8049421552412],"type":"Point"}
}