{
  "type": "Feature",
  "properties": {
    "iso:country": "GB",
    "wof:name": "BN12 5HE",
    "wof:placetype": "postalcode"
  },
  "geometry": {"coordinates":[-0.441288,50.804942],"type":"Point"}
}
