{
  "type": "Feature",
  "properties": {
    "iso:country":"GB",
    "wof:name":"NG21 9QQ",
    "wof:placetype":"postalcode"
},
  "geometry": {"coordinates":[-1.05035584748826,53.19489235825246],"type":"Point"}
}