{
  "type": "Feature",
  "properties": {
    "iso:country":"GB",
    "wof:name":"AB10 7BL",
    "wof:placetype":"postalcode"
},
  "geometry": {"coordinates":[-2.13656744157896,57.12336537102313],"type":"Point"}
}