{
  "type": "Feature",
  "properties": {
    "iso:country": "GB",
    "wof:name": "DN4 5AZ",
    "wof:placetype": "postalcode"
  },
  "geometry": {"coordinates":[-1.1195,53.515483],"type":"Point"}
}
