{
  "type": "Feature",
  "properties": {
    "iso:country":"GB",
    "wof:name":"S10 4DG",
    "wof:placetype":"postalcode"
},
  "geometry": {"coordinates":[-1.55133567851996,53.3702542285835],"type":"Point"}
}