{
  "type": "Feature",
  "properties": {
    "date:inception_lower": "1980-01-01",
    "date:inception_upper": "1980-01-01",
    "iso:country": "GB",
    "wof:name": "S10 4DG",
    "wof:placetype": "postalcode"
  },
  "geometry": {"coordinates":[-1.55135,53.370272],"type":"Point"}
}
