{
  "type": "Feature",
  "properties": {
    "iso:country": "GB",
    "wof:name": "S72 8WA",
    "wof:placetype": "postalcode"
  },
  "geometry": {"coordinates":[-1.408915,53.592722],"type":"Point"}
}
