{
  "type": "Feature",
  "properties": {
    "iso:country": "GB",
    "wof:name": "GU3 3PP",
    "wof:placetype": "postalcode"
  },
  "geometry": {"coordinates":[-0.622839,51.283058],"type":"Point"}
}
