{
  "type": "Feature",
  "properties": {
    "date:inception_lower":"1992-08-01",
    "date:inception_upper":"1992-08-31",
    "iso:country":"GB",
    "wof:name":"LE12 7UL",
    "wof:placetype":"postalcode"
},
  "geometry": {"coordinates":[-1.152104,52.719459],"type":"Point"}
}