{
  "type": "Feature",
  "properties": {
    "iso:country":"GB",
    "wof:name":"LE12 7UL",
    "wof:placetype":"postalcode"
},
  "geometry": {"coordinates":[-1.15210431885277,52.71945897842691],"type":"Point"}
}