{
  "type": "Feature",
  "properties": {
    "date:inception_lower": "2020-08-01",
    "date:inception_upper": "2020-08-01",
    "iso:country": "GB",
    "wof:name": "S80 3FZ",
    "wof:placetype": "postalcode"
  },
  "geometry": {"coordinates":[-1.152814,53.314817],"type":"Point"}
}
