{
  "type": "Feature",
  "properties": {
    "iso:country":"GB",
    "wof:name":"B8 1EY",
    "wof:placetype":"postalcode"
},
  "geometry": {"coordinates":[-1.85400445803928,52.48640820248592],"type":"Point"}
}