{
  "type": "Feature",
  "properties": {
    "iso:country":"GB",
    "wof:name":"WD6 2HF",
    "wof:placetype":"postalcode"
},
  "geometry": {"coordinates":[-0.26956944597138,51.64705933256607],"type":"Point"}
}