{
  "type": "Feature",
  "properties": {
    "iso:country": "GB",
    "wof:name": "PA14 6HA",
    "wof:placetype": "postalcode"
  },
  "geometry": {"coordinates":[-4.661562,55.922748],"type":"Point"}
}
