{
  "type": "Feature",
  "properties": {
    "date:inception_lower": "1980-01-01",
    "date:inception_upper": "1980-01-01",
    "iso:country": "GB",
    "wof:name": "PA14 6HA",
    "wof:placetype": "postalcode"
  },
  "geometry": {"coordinates":[-4.661558,55.922733],"type":"Point"}
}
