{
  "type": "Feature",
  "properties": {
    "iso:country": "GB",
    "wof:name": "CM23 2GF",
    "wof:placetype": "postalcode"
  },
  "geometry": {"coordinates":[0.171542,51.878347],"type":"Point"}
}
