{
  "type": "Feature",
  "properties": {
    "iso:country":"GB",
    "wof:name":"CM23 2GF",
    "wof:placetype":"postalcode"
},
  "geometry": {"coordinates":[0.17154188100296,51.878347225715],"type":"Point"}
}