{
  "type": "Feature",
  "properties": {
    "date:inception_lower": "2007-03-01",
    "date:inception_upper": "2007-03-01",
    "iso:country": "GB",
    "wof:name": "CM23 2GF",
    "wof:placetype": "postalcode"
  },
  "geometry": {"coordinates":[0.171542,51.878347],"type":"Point"}
}
