{
  "type": "Feature",
  "properties": {
    "iso:country":"GB",
    "wof:name":"EX36 4DR",
    "wof:placetype":"postalcode"
},
  "geometry": {"coordinates":[-3.84036821594047,51.01607654314316],"type":"Point"}
}