{
  "type": "Feature",
  "properties": {
    "date:inception_lower": "1980-01-01",
    "date:inception_upper": "1980-01-01",
    "iso:country": "GB",
    "wof:name": "NR1 4EZ",
    "wof:placetype": "postalcode"
  },
  "geometry": {"coordinates":[1.312429,52.633902],"type":"Point"}
}
