{
  "type": "Feature",
  "properties": {
    "iso:country": "GB",
    "wof:name": "NR1 4EZ",
    "wof:placetype": "postalcode"
  },
  "geometry": {"coordinates":[1.312429,52.633902],"type":"Point"}
}
