{
  "type": "Feature",
  "properties": {
    "iso:country":"GB",
    "wof:name":"LL12 0EW",
    "wof:placetype":"postalcode"
},
  "geometry": {"coordinates":[-2.93405232951046,53.1120405264143],"type":"Point"}
}