{
  "type": "Feature",
  "properties": {
    "date:inception_lower": "1980-01-01",
    "date:inception_upper": "1980-01-01",
    "iso:country": "GB",
    "wof:name": "CH8 8HT",
    "wof:placetype": "postalcode"
  },
  "geometry": {"coordinates":[-3.197173,53.24049],"type":"Point"}
}
