{
  "type": "Feature",
  "properties": {
    "iso:country":"GB",
    "wof:name":"G12 8LJ",
    "wof:placetype":"postalcode"
},
  "geometry": {"coordinates":[-4.28532188865522,55.87445926020398],"type":"Point"}
}