{
  "type": "Feature",
  "properties": {
    "date:inception_lower": "2005-11-01",
    "date:inception_upper": "2005-11-01",
    "iso:country": "GB",
    "wof:name": "G12 8LJ",
    "wof:placetype": "postalcode"
  },
  "geometry": {"coordinates":[-4.285322,55.874459],"type":"Point"}
}
