{
  "type": "Feature",
  "properties": {
    "date:inception_lower":"2012-04-01",
    "date:inception_upper":"2012-04-30",
    "iso:country":"GB",
    "wof:name":"LE4 3LR",
    "wof:placetype":"postalcode"
},
  "geometry": {"coordinates":[-1.131655,52.685338],"type":"Point"}
}