{
  "type": "Feature",
  "properties": {
    "iso:country":"GB",
    "wof:name":"LE4 3LR",
    "wof:placetype":"postalcode"
},
  "geometry": {"coordinates":[-1.13165482143152,52.68533823946381],"type":"Point"}
}