{
  "type": "Feature",
  "properties": {
    "iso:country": "GB",
    "wof:name": "MK17 9AU",
    "wof:placetype": "postalcode"
  },
  "geometry": {"coordinates":[-0.681988,51.966883],"type":"Point"}
}
