{
  "type": "Feature",
  "properties": {
    "iso:country":"GB",
    "wof:name":"LL55 3PT",
    "wof:placetype":"postalcode"
},
  "geometry": {"coordinates":[-4.15586940740132,53.14573387217854],"type":"Point"}
}