{
  "type": "Feature",
  "properties": {
    "iso:country":"GB",
    "wof:name":"YO7 3NR",
    "wof:placetype":"postalcode"
},
  "geometry": {"coordinates":[-1.32131790693061,54.15835020753052],"type":"Point"}
}