{
  "type": "Feature",
  "properties": {
    "iso:country": "GB",
    "wof:name": "DL14 0TR",
    "wof:placetype": "postalcode"
  },
  "geometry": {"coordinates":[-1.697872,54.656266],"type":"Point"}
}
