{
  "type": "Feature",
  "properties": {
    "iso:country":"GB",
    "wof:name":"WR9 0JH",
    "wof:placetype":"postalcode"
},
  "geometry": {"coordinates":[-2.22990650209257,52.28580338680974],"type":"Point"}
}