{
  "type": "Feature",
  "properties": {
    "iso:country": "GB",
    "wof:name": "ME12 1DJ",
    "wof:placetype": "postalcode"
  },
  "geometry": {"coordinates":[0.757285,51.437045],"type":"Point"}
}
