{
  "type": "Feature",
  "properties": {
    "iso:country":"GB",
    "wof:name":"WD6 1DZ",
    "wof:placetype":"postalcode"
},
  "geometry": {"coordinates":[-0.27571873873447,51.65565637677683],"type":"Point"}
}