{
  "type": "Feature",
  "properties": {
    "date:inception_lower": "1980-01-01",
    "date:inception_upper": "1980-01-01",
    "iso:country": "GB",
    "wof:name": "DA1 4JU",
    "wof:placetype": "postalcode"
  },
  "geometry": {"coordinates":[0.186108,51.454701],"type":"Point"}
}
