{
  "type": "Feature",
  "properties": {
    "iso:country":"GB",
    "wof:name":"DA1 4JU",
    "wof:placetype":"postalcode"
},
  "geometry": {"coordinates":[0.18610796683172,51.45470055508316],"type":"Point"}
}