{
  "type": "Feature",
  "properties": {
    "iso:country":"GB",
    "wof:name":"CW5 5UT",
    "wof:placetype":"postalcode"
},
  "geometry": {"coordinates":[-2.52894511664395,53.0686680349493],"type":"Point"}
}