{
  "type": "Feature",
  "properties": {
    "date:inception_lower": "2004-03-01",
    "date:inception_upper": "2004-03-01",
    "iso:country": "GB",
    "wof:name": "CW5 5UT",
    "wof:placetype": "postalcode"
  },
  "geometry": {"coordinates":[-2.528945,53.068668],"type":"Point"}
}
