{
  "type": "Feature",
  "properties": {
    "iso:country": "GB",
    "wof:name": "CW5 5UT",
    "wof:placetype": "postalcode"
  },
  "geometry": {"coordinates":[-2.528945,53.068668],"type":"Point"}
}
