{
  "type": "Feature",
  "properties": {
    "iso:country":"GB",
    "wof:name":"S44 5XF",
    "wof:placetype":"postalcode"
},
  "geometry": {"coordinates":[-1.36550249973433,53.21689728305202],"type":"Point"}
}