{
  "type": "Feature",
  "properties": {
    "iso:country":"GB",
    "wof:name":"SE4 2JJ",
    "wof:placetype":"postalcode"
},
  "geometry": {"coordinates":[-0.04265576600375,51.46344677452343],"type":"Point"}
}