{
  "type": "Feature",
  "properties": {
    "iso:country":"GB",
    "wof:name":"BB4 4RL",
    "wof:placetype":"postalcode"
},
  "geometry": {"coordinates":[-2.33403936675724,53.69492977655658],"type":"Point"}
}