{
  "type": "Feature",
  "properties": {
    "iso:country": "GB",
    "wof:name": "IV3 5DD",
    "wof:placetype": "postalcode"
  },
  "geometry": {"coordinates":[-4.231219,57.476055],"type":"Point"}
}
