{
  "type": "Feature",
  "properties": {
    "iso:country":"GB",
    "wof:name":"IV3 5DD",
    "wof:placetype":"postalcode"
},
  "geometry": {"coordinates":[-4.23121885811483,57.47605463093927],"type":"Point"}
}