{
  "type": "Feature",
  "properties": {
    "iso:country":"GB",
    "wof:name":"G51 3BJ",
    "wof:placetype":"postalcode"
},
  "geometry": {"coordinates":[-4.31589759357967,55.86361470351458],"type":"Point"}
}