{
  "type": "Feature",
  "properties": {
    "iso:country":"GB",
    "wof:name":"DY6 8NY",
    "wof:placetype":"postalcode"
},
  "geometry": {"coordinates":[-2.15074328147433,52.48357873994554],"type":"Point"}
}