{
  "type": "Feature",
  "properties": {
    "date:inception_lower":"1990-07-01",
    "date:inception_upper":"1990-07-31",
    "iso:country":"GB",
    "wof:name":"PO16 8HP",
    "wof:placetype":"postalcode"
},
  "geometry": {"coordinates":[-1.123692,50.850713],"type":"Point"}
}