{
  "type": "Feature",
  "properties": {
    "iso:country":"GB",
    "wof:name":"PO16 8HP",
    "wof:placetype":"postalcode"
},
  "geometry": {"coordinates":[-1.12369171894709,50.85071334267877],"type":"Point"}
}