{
  "type": "Feature",
  "properties": {
    "date:inception_lower": "2022-09-01",
    "date:inception_upper": "2022-09-01",
    "iso:country": "GB",
    "wof:name": "CM21 0FJ",
    "wof:placetype": "postalcode"
  },
  "geometry": {"coordinates":[0.14134,51.814271],"type":"Point"}
}
