{
  "type": "Feature",
  "properties": {
    "iso:country":"GB",
    "wof:name":"RG45 6NJ",
    "wof:placetype":"postalcode"
},
  "geometry": {"coordinates":[-0.79963629681371,51.37277583813371],"type":"Point"}
}