{
  "type": "Feature",
  "properties": {
    "iso:country":"GB",
    "wof:name":"TF2 7QD",
    "wof:placetype":"postalcode"
},
  "geometry": {"coordinates":[-2.43007680135696,52.7089422012936],"type":"Point"}
}