{
  "type": "Feature",
  "properties": {
    "date:inception_lower": "1980-01-01",
    "date:inception_upper": "1980-01-01",
    "iso:country": "GB",
    "wof:name": "TF2 7QD",
    "wof:placetype": "postalcode"
  },
  "geometry": {"coordinates":[-2.429479,52.708528],"type":"Point"}
}
