{
  "type": "Feature",
  "properties": {
    "date:inception_lower": "2019-04-01",
    "date:inception_upper": "2019-04-01",
    "iso:country": "GB",
    "wof:name": "BD23 9FR",
    "wof:placetype": "postalcode"
  },
  "geometry": {"coordinates":[-2.025738,53.95772],"type":"Point"}
}
