{
  "type": "Feature",
  "properties": {
    "iso:country":"GB",
    "wof:name":"CF14 0UD",
    "wof:placetype":"postalcode"
},
  "geometry": {"coordinates":[-3.18161357136366,51.54482424430002],"type":"Point"}
}