{
  "type": "Feature",
  "properties": {
    "date:inception_lower":"1980-01-01",
    "date:inception_upper":"1980-01-31",
    "iso:country":"GB",
    "wof:name":"NN17 3DD",
    "wof:placetype":"postalcode"
},
  "geometry": {"coordinates":[-0.670745,52.542246],"type":"Point"}
}