{
  "type": "Feature",
  "properties": {
    "iso:country":"GB",
    "wof:name":"NN17 3DD",
    "wof:placetype":"postalcode"
},
  "geometry": {"coordinates":[-0.67074514375762,52.54224598918072],"type":"Point"}
}