{
  "type": "Feature",
  "properties": {
    "iso:country": "GB",
    "wof:name": "CV23 8EL",
    "wof:placetype": "postalcode"
  },
  "geometry": {"coordinates":[-1.368371,52.311554],"type":"Point"}
}
