{
  "type": "Feature",
  "properties": {
    "iso:country": "GB",
    "wof:name": "PO15 5QS",
    "wof:placetype": "postalcode"
  },
  "geometry": {"coordinates":[-1.222505,50.850739],"type":"Point"}
}
