{
  "type": "Feature",
  "properties": {
    "date:inception_lower":"1980-01-01",
    "date:inception_upper":"1980-01-31",
    "iso:country":"GB",
    "wof:name":"PO15 5QS",
    "wof:placetype":"postalcode"
},
  "geometry": {"coordinates":[-1.222505,50.850739],"type":"Point"}
}