{
  "type": "Feature",
  "properties": {
    "iso:country": "GB",
    "wof:name": "LA3 3NJ",
    "wof:placetype": "postalcode"
  },
  "geometry": {"coordinates":[-2.853169,54.059791],"type":"Point"}
}
