{
  "type": "Feature",
  "properties": {
    "date:inception_lower":"1980-01-01",
    "date:inception_upper":"1980-01-31",
    "iso:country":"GB",
    "wof:name":"LA3 3NJ",
    "wof:placetype":"postalcode"
},
  "geometry": {"coordinates":[-2.853169,54.059791],"type":"Point"}
}