{
  "type": "Feature",
  "properties": {
    "iso:country":"GB",
    "wof:name":"LA3 3NJ",
    "wof:placetype":"postalcode"
},
  "geometry": {"coordinates":[-2.8531688507654,54.0597913596091],"type":"Point"}
}