{
  "type": "Feature",
  "properties": {
    "iso:country":"GB",
    "wof:name":"WF3 4AE",
    "wof:placetype":"postalcode"
},
  "geometry": {"coordinates":[-1.46633229260024,53.71452205709731],"type":"Point"}
}