{
  "type": "Feature",
  "properties": {
    "iso:country":"GB",
    "wof:name":"IP24 3HX",
    "wof:placetype":"postalcode"
},
  "geometry": {"coordinates":[0.75073574995364,52.40424394812098],"type":"Point"}
}