{
  "type": "Feature",
  "properties": {
    "date:inception_lower": "1997-06-01",
    "date:inception_upper": "1997-06-01",
    "iso:country": "GB",
    "wof:name": "IP24 3HX",
    "wof:placetype": "postalcode"
  },
  "geometry": {"coordinates":[0.750736,52.404244],"type":"Point"}
}
