{
  "type": "Feature",
  "properties": {
    "iso:country": "GB",
    "wof:name": "CW2 7LF",
    "wof:placetype": "postalcode"
  },
  "geometry": {"coordinates":[-2.445162,53.091942],"type":"Point"}
}
