{
  "type": "Feature",
  "properties": {
    "iso:country":"GB",
    "wof:name":"CW2 7LF",
    "wof:placetype":"postalcode"
},
  "geometry": {"coordinates":[-2.44516190085947,53.09194237335065],"type":"Point"}
}