{
  "type": "Feature",
  "properties": {
    "date:inception_lower": "1980-01-01",
    "date:inception_upper": "1980-01-01",
    "iso:country": "GB",
    "wof:name": "CW2 7LF",
    "wof:placetype": "postalcode"
  },
  "geometry": {"coordinates":[-2.445162,53.091942],"type":"Point"}
}
