{
  "type": "Feature",
  "properties": {
    "iso:country": "GB",
    "wof:name": "OX44 7LU",
    "wof:placetype": "postalcode"
  },
  "geometry": {"coordinates":[-1.059384,51.695477],"type":"Point"}
}
