{
  "type": "Feature",
  "properties": {
    "iso:country":"GB",
    "wof:name":"OX44 7LU",
    "wof:placetype":"postalcode"
},
  "geometry": {"coordinates":[-1.05938381039343,51.69547708896035],"type":"Point"}
}