{
  "type": "Feature",
  "properties": {
    "iso:country":"GB",
    "wof:name":"B27 7RE",
    "wof:placetype":"postalcode"
},
  "geometry": {"coordinates":[-1.82757166583138,52.44091928860158],"type":"Point"}
}