{
  "type": "Feature",
  "properties": {
    "iso:country":"GB",
    "wof:name":"ST7 4HW",
    "wof:placetype":"postalcode"
},
  "geometry": {"coordinates":[-2.22884938391097,53.07981780165886],"type":"Point"}
}