{
  "type": "Feature",
  "properties": {
    "date:inception_lower":"1980-01-01",
    "date:inception_upper":"1980-01-31",
    "iso:country":"GB",
    "wof:name":"RG25 2LX",
    "wof:placetype":"postalcode"
},
  "geometry": {"coordinates":[-1.029225,51.233511],"type":"Point"}
}