{
  "type": "Feature",
  "properties": {
    "iso:country": "GB",
    "wof:name": "RG25 2LX",
    "wof:placetype": "postalcode"
  },
  "geometry": {"coordinates":[-1.029225,51.233511],"type":"Point"}
}
