{
  "type": "Feature",
  "properties": {
    "date:inception_lower": "1980-01-01",
    "date:inception_upper": "1980-01-01",
    "iso:country": "GB",
    "wof:name": "NR21 8AH",
    "wof:placetype": "postalcode"
  },
  "geometry": {"coordinates":[0.850865,52.836961],"type":"Point"}
}
