{
  "type": "Feature",
  "properties": {
    "iso:country":"GB",
    "wof:name":"NR21 8AH",
    "wof:placetype":"postalcode"
},
  "geometry": {"coordinates":[0.85087715852289,52.8369262099312],"type":"Point"}
}