{
  "type": "Feature",
  "properties": {
    "iso:country": "GB",
    "wof:name": "NR21 8AH",
    "wof:placetype": "postalcode"
  },
  "geometry": {"coordinates":[0.850865,52.836961],"type":"Point"}
}
