{
  "type": "Feature",
  "properties": {
    "date:inception_lower": "2003-01-01",
    "date:inception_upper": "2003-01-01",
    "iso:country": "GB",
    "wof:name": "IP24 2TX",
    "wof:placetype": "postalcode"
  },
  "geometry": {"coordinates":[0.769719,52.420446],"type":"Point"}
}
