{
  "type": "Feature",
  "properties": {
    "iso:country":"GB",
    "wof:name":"IP24 2TX",
    "wof:placetype":"postalcode"
},
  "geometry": {"coordinates":[0.76971852665979,52.42044605009691],"type":"Point"}
}