{
  "type": "Feature",
  "properties": {
    "iso:country": "GB",
    "wof:name": "GL20 5TE",
    "wof:placetype": "postalcode"
  },
  "geometry": {"coordinates":[-2.155008,51.984528],"type":"Point"}
}
