{
  "type": "Feature",
  "properties": {
    "iso:country":"GB",
    "wof:name":"B94 5EH",
    "wof:placetype":"postalcode"
},
  "geometry": {"coordinates":[-1.85148314082861,52.34704112407761],"type":"Point"}
}