{
  "type": "Feature",
  "properties": {
    "iso:country":"GB",
    "wof:name":"B13 0QJ",
    "wof:placetype":"postalcode"
},
  "geometry": {"coordinates":[-1.88479052869442,52.42673953611071],"type":"Point"}
}