{
  "type": "Feature",
  "properties": {
    "iso:country":"GB",
    "wof:name":"E1W 1NU",
    "wof:placetype":"postalcode"
},
  "geometry": {"coordinates":[-0.06521737080005,51.50422519277001],"type":"Point"}
}