{
  "type": "Feature",
  "properties": {
    "iso:country":"GB",
    "wof:name":"KA11 2FG",
    "wof:placetype":"postalcode"
},
  "geometry": {"coordinates":[-4.65022506100706,55.63034425447348],"type":"Point"}
}