{
  "type": "Feature",
  "properties": {
    "date:inception_lower":"2005-01-01",
    "date:inception_upper":"2005-01-31",
    "iso:country":"GB",
    "wof:name":"KA11 2FG",
    "wof:placetype":"postalcode"
},
  "geometry": {"coordinates":[-4.650225,55.630344],"type":"Point"}
}