{
  "type": "Feature",
  "properties": {
    "date:inception_lower":"1980-01-01",
    "date:inception_upper":"1980-01-31",
    "iso:country":"GB",
    "wof:name":"FK5 4JF",
    "wof:placetype":"postalcode"
},
  "geometry": {"coordinates":[-3.815843,56.033479],"type":"Point"}
}