{
  "type": "Feature",
  "properties": {
    "iso:country":"GB",
    "wof:name":"FK5 4JF",
    "wof:placetype":"postalcode"
},
  "geometry": {"coordinates":[-3.81584302986053,56.03347947687567],"type":"Point"}
}