{
  "type": "Feature",
  "properties": {
    "iso:country": "GB",
    "wof:name": "BH31 6UR",
    "wof:placetype": "postalcode"
  },
  "geometry": {"coordinates":[-1.877815,50.876877],"type":"Point"}
}
