{
  "type": "Feature",
  "properties": {
    "iso:country":"GB",
    "wof:name":"BR6 6BJ",
    "wof:placetype":"postalcode"
},
  "geometry": {"coordinates":[0.08949882577601,51.35133511324936],"type":"Point"}
}