{
  "type": "Feature",
  "properties": {
    "iso:country": "GB",
    "wof:name": "CT19 4HU",
    "wof:placetype": "postalcode"
  },
  "geometry": {"coordinates":[1.13776,51.089139],"type":"Point"}
}
