{
  "type": "Feature",
  "properties": {
    "iso:country":"GB",
    "wof:name":"SL6 3LD",
    "wof:placetype":"postalcode"
},
  "geometry": {"coordinates":[-0.73430477558253,51.48230412572499],"type":"Point"}
}