{
  "type": "Feature",
  "properties": {
    "iso:country":"GB",
    "wof:name":"TS14 8HF",
    "wof:placetype":"postalcode"
},
  "geometry": {"coordinates":[-1.09572852955203,54.52085270687397],"type":"Point"}
}