{
  "type": "Feature",
  "properties": {
    "iso:country": "GB",
    "wof:name": "TS14 8HF",
    "wof:placetype": "postalcode"
  },
  "geometry": {"coordinates":[-1.095728,54.520853],"type":"Point"}
}
