{
  "type": "Feature",
  "properties": {
    "iso:country":"GB",
    "wof:name":"SM2 7HQ",
    "wof:placetype":"postalcode"
},
  "geometry": {"coordinates":[-0.21722297841347,51.34669298175039],"type":"Point"}
}