{
  "type": "Feature",
  "properties": {
    "iso:country": "GB",
    "wof:name": "GU51 3LS",
    "wof:placetype": "postalcode"
  },
  "geometry": {"coordinates":[-0.84145,51.276737],"type":"Point"}
}
