{
  "type": "Feature",
  "properties": {
    "date:inception_lower": "1995-12-01",
    "date:inception_upper": "1995-12-01",
    "iso:country": "GB",
    "wof:name": "ST4 1AA",
    "wof:placetype": "postalcode"
  },
  "geometry": {"coordinates":[-2.183306,53.003255],"type":"Point"}
}
