{
  "type": "Feature",
  "properties": {
    "iso:country":"GB",
    "wof:name":"SP11 6JY",
    "wof:placetype":"postalcode"
},
  "geometry": {"coordinates":[-1.47560530165445,51.24617187439276],"type":"Point"}
}