{
  "type": "Feature",
  "properties": {
    "iso:country": "GB",
    "wof:name": "SP11 6JY",
    "wof:placetype": "postalcode"
  },
  "geometry": {"coordinates":[-1.475605,51.246172],"type":"Point"}
}
