{
  "type": "Feature",
  "properties": {
    "iso:country":"GB",
    "wof:name":"LS16 6LR",
    "wof:placetype":"postalcode"
},
  "geometry": {"coordinates":[-1.60268892917852,53.84260088706414],"type":"Point"}
}