{
  "type": "Feature",
  "properties": {
    "iso:country":"GB",
    "wof:name":"SG14 1PX",
    "wof:placetype":"postalcode"
},
  "geometry": {"coordinates":[-0.07922165114808,51.79663612527685],"type":"Point"}
}