{
  "type": "Feature",
  "properties": {
    "iso:country":"GB",
    "wof:name":"W1F 0ES",
    "wof:placetype":"postalcode"
},
  "geometry": {"coordinates":[-0.13312297491662,51.51316727683545],"type":"Point"}
}