{
  "type": "Feature",
  "properties": {
    "iso:country":"GB",
    "wof:name":"BD19 3TL",
    "wof:placetype":"postalcode"
},
  "geometry": {"coordinates":[-1.71864136284598,53.73029985290511],"type":"Point"}
}