{
  "type": "Feature",
  "properties": {
    "iso:country": "GB",
    "wof:name": "DG7 1RW",
    "wof:placetype": "postalcode"
  },
  "geometry": {"coordinates":[-3.876959,54.841694],"type":"Point"}
}
