{
  "type": "Feature",
  "properties": {
    "iso:country":"GB",
    "wof:name":"DG7 1RW",
    "wof:placetype":"postalcode"
},
  "geometry": {"coordinates":[-3.87773282834418,54.84155662425076],"type":"Point"}
}