{
  "type": "Feature",
  "properties": {
    "date:inception_lower":"1986-04-01",
    "date:inception_upper":"1986-04-30",
    "iso:country":"GB",
    "wof:name":"NW9 0EW",
    "wof:placetype":"postalcode"
},
  "geometry": {"coordinates":[-0.264735,51.59308],"type":"Point"}
}