{
  "type": "Feature",
  "properties": {
    "iso:country":"GB",
    "wof:name":"NW9 0EW",
    "wof:placetype":"postalcode"
},
  "geometry": {"coordinates":[-0.26473508563604,51.5930796366445],"type":"Point"}
}