{
  "type": "Feature",
  "properties": {
    "iso:country":"GB",
    "wof:name":"BN23 6UE",
    "wof:placetype":"postalcode"
},
  "geometry": {"coordinates":[0.31827230225149,50.79105012575886],"type":"Point"}
}