{
  "type": "Feature",
  "properties": {
    "date:inception_lower": "1980-01-01",
    "date:inception_upper": "1980-01-01",
    "iso:country": "GB",
    "wof:name": "BH9 2QY",
    "wof:placetype": "postalcode"
  },
  "geometry": {"coordinates":[-1.884008,50.746096],"type":"Point"}
}
