{
  "type": "Feature",
  "properties": {
    "iso:country":"GB",
    "wof:name":"TS7 0NW",
    "wof:placetype":"postalcode"
},
  "geometry": {"coordinates":[-1.16639276330383,54.51026108690478],"type":"Point"}
}