{
  "type": "Feature",
  "properties": {
    "date:inception_lower": "2012-04-01",
    "date:inception_upper": "2012-04-01",
    "iso:country": "GB",
    "wof:name": "LS18 5GL",
    "wof:placetype": "postalcode"
  },
  "geometry": {"coordinates":[-1.659484,53.838893],"type":"Point"}
}
