{
  "type": "Feature",
  "properties": {
    "iso:country":"GB",
    "wof:name":"CB2 3NH",
    "wof:placetype":"postalcode"
},
  "geometry": {"coordinates":[0.12010995672544,52.20466538427629],"type":"Point"}
}