{
  "type": "Feature",
  "properties": {
    "iso:country":"GB",
    "wof:name":"MK45 3LT",
    "wof:placetype":"postalcode"
},
  "geometry": {"coordinates":[-0.47316517130078,52.06418302578475],"type":"Point"}
}