{
  "type": "Feature",
  "properties": {
    "iso:country":"GB",
    "wof:name":"B32 2RU",
    "wof:placetype":"postalcode"
},
  "geometry": {"coordinates":[-1.98755038749207,52.45614717624539],"type":"Point"}
}