{
  "type": "Feature",
  "properties": {
    "iso:country": "GB",
    "wof:name": "B32 2RU",
    "wof:placetype": "postalcode"
  },
  "geometry": {"coordinates":[-1.98755,52.456147],"type":"Point"}
}
