{
  "type": "Feature",
  "properties": {
    "iso:country":"GB",
    "wof:name":"HP7 9BS",
    "wof:placetype":"postalcode"
},
  "geometry": {"coordinates":[-0.60278729284897,51.66786173620734],"type":"Point"}
}