{
  "type": "Feature",
  "properties": {
    "iso:country": "GB",
    "wof:name": "HP7 9BS",
    "wof:placetype": "postalcode"
  },
  "geometry": {"coordinates":[-0.602787,51.667862],"type":"Point"}
}
