{
  "type": "Feature",
  "properties": {
    "iso:country":"GB",
    "wof:name":"N8 0DY",
    "wof:placetype":"postalcode"
},
  "geometry": {"coordinates":[-0.1082373956658,51.58921370313202],"type":"Point"}
}