{
  "type": "Feature",
  "properties": {
    "iso:country":"GB",
    "wof:name":"S7 2QF",
    "wof:placetype":"postalcode"
},
  "geometry": {"coordinates":[-1.49633659641982,53.34657440969904],"type":"Point"}
}