{
  "type": "Feature",
  "properties": {
    "date:inception_lower": "1980-01-01",
    "date:inception_upper": "1980-01-01",
    "iso:country": "GB",
    "wof:name": "S7 2QF",
    "wof:placetype": "postalcode"
  },
  "geometry": {"coordinates":[-1.496321,53.346592],"type":"Point"}
}
