{
  "type": "Feature",
  "properties": {
    "iso:country":"GB",
    "wof:name":"TQ2 6DF",
    "wof:placetype":"postalcode"
},
  "geometry": {"coordinates":[-3.55071904584596,50.47678119646586],"type":"Point"}
}