{
  "type": "Feature",
  "properties": {
    "iso:country":"GB",
    "wof:name":"TQ12 5SB",
    "wof:placetype":"postalcode"
},
  "geometry": {"coordinates":[-3.64543084239143,50.48654264279167],"type":"Point"}
}