{
  "type": "Feature",
  "properties": {
    "iso:country": "GB",
    "wof:name": "TQ12 5SB",
    "wof:placetype": "postalcode"
  },
  "geometry": {"coordinates":[-3.645431,50.486543],"type":"Point"}
}
