{
  "type": "Feature",
  "properties": {
    "date:inception_lower": "1980-01-01",
    "date:inception_upper": "1980-01-01",
    "iso:country": "GB",
    "wof:name": "HR8 2BY",
    "wof:placetype": "postalcode"
  },
  "geometry": {"coordinates":[-2.431827,52.035013],"type":"Point"}
}
