{
  "type": "Feature",
  "properties": {
    "iso:country":"GB",
    "wof:name":"HR8 2BY",
    "wof:placetype":"postalcode"
},
  "geometry": {"coordinates":[-2.43182724863058,52.03501334187786],"type":"Point"}
}