{
  "type": "Feature",
  "properties": {
    "date:inception_lower":"1980-01-01",
    "date:inception_upper":"1980-01-31",
    "iso:country":"GB",
    "wof:name":"BL5 2BX",
    "wof:placetype":"postalcode"
},
  "geometry": {"coordinates":[-2.546104,53.542094],"type":"Point"}
}