{
  "type": "Feature",
  "properties": {
    "iso:country":"GB",
    "wof:name":"BL5 2BX",
    "wof:placetype":"postalcode"
},
  "geometry": {"coordinates":[-2.546103859585,53.54209440598083],"type":"Point"}
}