{
  "type": "Feature",
  "properties": {
    "iso:country":"GB",
    "wof:name":"NE61 2LQ",
    "wof:placetype":"postalcode"
},
  "geometry": {"coordinates":[-1.69490188446705,55.16332139075715],"type":"Point"}
}