{
  "type": "Feature",
  "properties": {
    "iso:country": "GB",
    "wof:name": "FK3 9AX",
    "wof:placetype": "postalcode"
  },
  "geometry": {"coordinates":[-3.706529,56.016835],"type":"Point"}
}
