{
  "type": "Feature",
  "properties": {
    "date:inception_lower":"1980-01-01",
    "date:inception_upper":"1980-01-31",
    "iso:country":"GB",
    "wof:name":"FK3 9AX",
    "wof:placetype":"postalcode"
},
  "geometry": {"coordinates":[-3.706529,56.016835],"type":"Point"}
}