{
  "type": "Feature",
  "properties": {
    "iso:country":"GB",
    "wof:name":"FK3 9AX",
    "wof:placetype":"postalcode"
},
  "geometry": {"coordinates":[-3.70652907482032,56.01683455069652],"type":"Point"}
}