{
  "type": "Feature",
  "properties": {
    "iso:country": "GB",
    "wof:name": "G77 6ZF",
    "wof:placetype": "postalcode"
  },
  "geometry": {"coordinates":[-4.346499,55.783444],"type":"Point"}
}
