{
  "type": "Feature",
  "properties": {
    "date:inception_lower": "2022-10-01",
    "date:inception_upper": "2022-10-01",
    "iso:country": "GB",
    "wof:name": "CV9 9EN",
    "wof:placetype": "postalcode"
  },
  "geometry": {"coordinates":[-1.546658,52.576618],"type":"Point"}
}
