{
  "type": "Feature",
  "properties": {
    "iso:country":"GB",
    "wof:name":"S7 2EA",
    "wof:placetype":"postalcode"
},
  "geometry": {"coordinates":[-1.49694737016976,53.35211404378938],"type":"Point"}
}