{
  "type": "Feature",
  "properties": {
    "iso:country":"GB",
    "wof:name":"LU6 1HL",
    "wof:placetype":"postalcode"
},
  "geometry": {"coordinates":[-0.52739903805762,51.88936916456022],"type":"Point"}
}