{
  "type": "Feature",
  "properties": {
    "iso:country": "GB",
    "wof:name": "LU6 1HL",
    "wof:placetype": "postalcode"
  },
  "geometry": {"coordinates":[-0.527399,51.889369],"type":"Point"}
}
