{
  "type": "Feature",
  "properties": {
    "iso:country":"GB",
    "wof:name":"NG1 5LB",
    "wof:placetype":"postalcode"
},
  "geometry": {"coordinates":[-1.15329766249507,52.9564533233704],"type":"Point"}
}