{
  "type": "Feature",
  "properties": {
    "iso:country": "GB",
    "wof:name": "S13 9AA",
    "wof:placetype": "postalcode"
  },
  "geometry": {"coordinates":[-1.39232,53.376895],"type":"Point"}
}
