{
  "type": "Feature",
  "properties": {
    "iso:country":"GB",
    "wof:name":"S13 9AA",
    "wof:placetype":"postalcode"
},
  "geometry": {"coordinates":[-1.39231973160967,53.37689480823922],"type":"Point"}
}