{
  "type": "Feature",
  "properties": {
    "iso:country":"GB",
    "wof:name":"DY6 8HZ",
    "wof:placetype":"postalcode"
},
  "geometry": {"coordinates":[-2.15910834576089,52.48795486775451],"type":"Point"}
}