{
  "type": "Feature",
  "properties": {
    "iso:country":"GB",
    "wof:name":"DY5 2NL",
    "wof:placetype":"postalcode"
},
  "geometry": {"coordinates":[-2.12205780276488,52.46743891683462],"type":"Point"}
}