{
  "type": "Feature",
  "properties": {
    "iso:country":"GB",
    "wof:name":"GU5 9ND",
    "wof:placetype":"postalcode"
},
  "geometry": {"coordinates":[-0.44974670920889,51.22182176205843],"type":"Point"}
}