{
  "type": "Feature",
  "properties": {
    "iso:country": "GB",
    "wof:name": "NE9 5AT",
    "wof:placetype": "postalcode"
  },
  "geometry": {"coordinates":[-1.601383,54.940769],"type":"Point"}
}
