{
  "type": "Feature",
  "properties": {
    "iso:country":"GB",
    "wof:name":"NE9 5AT",
    "wof:placetype":"postalcode"
},
  "geometry": {"coordinates":[-1.60174987389836,54.94032216427338],"type":"Point"}
}