{
  "type": "Feature",
  "properties": {
    "iso:country":"GB",
    "wof:name":"NR12 8HG",
    "wof:placetype":"postalcode"
},
  "geometry": {"coordinates":[1.40921111550327,52.7684901462839],"type":"Point"}
}