{
  "type": "Feature",
  "properties": {
    "iso:country": "GB",
    "wof:name": "NR12 8HG",
    "wof:placetype": "postalcode"
  },
  "geometry": {"coordinates":[1.409211,52.76849],"type":"Point"}
}
