{
  "type": "Feature",
  "properties": {
    "date:inception_lower":"1980-01-01",
    "date:inception_upper":"1980-01-31",
    "iso:country":"GB",
    "wof:name":"NR12 8HG",
    "wof:placetype":"postalcode"
},
  "geometry": {"coordinates":[1.409211,52.76849],"type":"Point"}
}