{
  "type": "Feature",
  "properties": {
    "iso:country":"GB",
    "wof:name":"SO23 9SB",
    "wof:placetype":"postalcode"
},
  "geometry": {"coordinates":[-1.32163482497538,51.04906475121928],"type":"Point"}
}