{
  "type": "Feature",
  "properties": {
    "iso:country":"GB",
    "wof:name":"UB2 5PR",
    "wof:placetype":"postalcode"
},
  "geometry": {"coordinates":[-0.38646209437733,51.49579402020662],"type":"Point"}
}