{
  "type": "Feature",
  "properties": {
    "iso:country":"GB",
    "wof:name":"SM6 9GW",
    "wof:placetype":"postalcode"
},
  "geometry": {"coordinates":[-0.12873936724487,51.3551418867692],"type":"Point"}
}