{
  "type": "Feature",
  "properties": {
    "date:inception_lower":"2002-06-01",
    "date:inception_upper":"2002-06-30",
    "iso:country":"GB",
    "wof:name":"SM6 9GW",
    "wof:placetype":"postalcode"
},
  "geometry": {"coordinates":[-0.128739,51.355142],"type":"Point"}
}