{
  "type": "Feature",
  "properties": {
    "iso:country": "GB",
    "wof:name": "SM6 9GW",
    "wof:placetype": "postalcode"
  },
  "geometry": {"coordinates":[-0.128739,51.355142],"type":"Point"}
}
