{
  "type": "Feature",
  "properties": {
    "iso:country": "GB",
    "wof:name": "BN11 5PN",
    "wof:placetype": "postalcode"
  },
  "geometry": {"coordinates":[-0.394612,50.81064],"type":"Point"}
}
