{
  "type": "Feature",
  "properties": {
    "iso:country": "GB",
    "wof:name": "DA6 7AH",
    "wof:placetype": "postalcode"
  },
  "geometry": {"coordinates":[0.140088,51.455892],"type":"Point"}
}
