{
  "type": "Feature",
  "properties": {
    "iso:country":"GB",
    "wof:name":"DA6 7AH",
    "wof:placetype":"postalcode"
},
  "geometry": {"coordinates":[0.14008792031133,51.45589153808925],"type":"Point"}
}