{
  "type": "Feature",
  "properties": {
    "iso:country":"GB",
    "wof:name":"PE30 4DW",
    "wof:placetype":"postalcode"
},
  "geometry": {"coordinates":[0.42673271147874,52.76386043156287],"type":"Point"}
}