{
  "type": "Feature",
  "properties": {
    "date:inception_lower":"1980-01-01",
    "date:inception_upper":"1980-01-31",
    "iso:country":"GB",
    "wof:name":"PE30 4DW",
    "wof:placetype":"postalcode"
},
  "geometry": {"coordinates":[0.426733,52.76386],"type":"Point"}
}