{
  "type": "Feature",
  "properties": {
    "iso:country":"GB",
    "wof:name":"SY12 9AB",
    "wof:placetype":"postalcode"
},
  "geometry": {"coordinates":[-2.89189297073319,52.89521458952183],"type":"Point"}
}