{
  "type": "Feature",
  "properties": {
    "iso:country": "GB",
    "wof:name": "SY12 9AB",
    "wof:placetype": "postalcode"
  },
  "geometry": {"coordinates":[-2.891893,52.895215],"type":"Point"}
}
