{
  "type": "Feature",
  "properties": {
    "iso:country":"GB",
    "wof:name":"OL7 9DN",
    "wof:placetype":"postalcode"
},
  "geometry": {"coordinates":[-2.10222785038942,53.49241527540596],"type":"Point"}
}