{
  "type": "Feature",
  "properties": {
    "date:inception_lower": "1980-01-01",
    "date:inception_upper": "1980-01-01",
    "iso:country": "GB",
    "wof:name": "OL5 9NZ",
    "wof:placetype": "postalcode"
  },
  "geometry": {"coordinates":[-2.03407,53.5108],"type":"Point"}
}
