{
  "type": "Feature",
  "properties": {
    "iso:country": "GB",
    "wof:name": "OL5 9NZ",
    "wof:placetype": "postalcode"
  },
  "geometry": {"coordinates":[-2.03407,53.5108],"type":"Point"}
}
