{
  "type": "Feature",
  "properties": {
    "iso:country":"GB",
    "wof:name":"OL5 9NZ",
    "wof:placetype":"postalcode"
},
  "geometry": {"coordinates":[-2.03407009466043,53.51079961526592],"type":"Point"}
}