{
  "type": "Feature",
  "properties": {
    "iso:country": "GB",
    "wof:name": "TD9 0AA",
    "wof:placetype": "postalcode"
  },
  "geometry": {"coordinates":[-2.78917,55.420852],"type":"Point"}
}
