{
  "type": "Feature",
  "properties": {
    "iso:country":"GB",
    "wof:name":"TD9 0AA",
    "wof:placetype":"postalcode"
},
  "geometry": {"coordinates":[-2.78917049434508,55.42085184054978],"type":"Point"}
}