{
  "type": "Feature",
  "properties": {
    "date:inception_lower": "1980-01-01",
    "date:inception_upper": "1980-01-01",
    "iso:country": "GB",
    "wof:name": "TD9 0AA",
    "wof:placetype": "postalcode"
  },
  "geometry": {"coordinates":[-2.78917,55.420852],"type":"Point"}
}
