{
  "type": "Feature",
  "properties": {
    "date:inception_lower":"1980-01-01",
    "date:inception_upper":"1980-01-31",
    "iso:country":"GB",
    "wof:name":"KA17 0LH",
    "wof:placetype":"postalcode"
},
  "geometry": {"coordinates":[-4.272472,55.60709],"type":"Point"}
}