{
  "type": "Feature",
  "properties": {
    "date:inception_lower": "1980-01-01",
    "date:inception_upper": "1980-01-01",
    "iso:country": "GB",
    "wof:name": "NN16 8XX",
    "wof:placetype": "postalcode"
  },
  "geometry": {"coordinates":[-0.717243,52.402857],"type":"Point"}
}
