{
  "type": "Feature",
  "properties": {
    "iso:country":"GB",
    "wof:name":"NN16 8XX",
    "wof:placetype":"postalcode"
},
  "geometry": {"coordinates":[-0.71724291037131,52.40285701086979],"type":"Point"}
}