{
  "type": "Feature",
  "properties": {
    "iso:country":"GB",
    "wof:name":"DA10 0JZ",
    "wof:placetype":"postalcode"
},
  "geometry": {"coordinates":[0.30622296750297,51.44173281546526],"type":"Point"}
}