{
  "type": "Feature",
  "properties": {
    "iso:country":"GB",
    "wof:name":"EN6 2ET",
    "wof:placetype":"postalcode"
},
  "geometry": {"coordinates":[-0.19949033572242,51.69058013895886],"type":"Point"}
}