{
  "type": "Feature",
  "properties": {
    "iso:country":"GB",
    "wof:name":"OL6 6RL",
    "wof:placetype":"postalcode"
},
  "geometry": {"coordinates":[-2.07194501918615,53.4910531880812],"type":"Point"}
}