{
  "type": "Feature",
  "properties": {
    "iso:country":"GB",
    "wof:name":"WF10 2BX",
    "wof:placetype":"postalcode"
},
  "geometry": {"coordinates":[-1.36736174490701,53.74065472441926],"type":"Point"}
}