{
  "type": "Feature",
  "properties": {
    "date:inception_lower": "2008-09-01",
    "date:inception_upper": "2008-09-01",
    "iso:country": "GB",
    "wof:name": "S35 1QP",
    "wof:placetype": "postalcode"
  },
  "geometry": {"coordinates":[-1.451023,53.452585],"type":"Point"}
}
