{
  "type": "Feature",
  "properties": {
    "iso:country":"GB",
    "wof:name":"S35 1QP",
    "wof:placetype":"postalcode"
},
  "geometry": {"coordinates":[-1.45095053819959,53.45234184634958],"type":"Point"}
}