{
  "type": "Feature",
  "properties": {
    "iso:country":"GB",
    "wof:name":"WN1 3UE",
    "wof:placetype":"postalcode"
},
  "geometry": {"coordinates":[-2.61524184984,53.55418064676247],"type":"Point"}
}