{
  "type": "Feature",
  "properties": {
    "date:inception_lower": "1980-01-01",
    "date:inception_upper": "1980-01-01",
    "iso:country": "GB",
    "wof:name": "WN1 3UE",
    "wof:placetype": "postalcode"
  },
  "geometry": {"coordinates":[-2.615242,53.554181],"type":"Point"}
}
