{
  "type": "Feature",
  "properties": {
    "iso:country":"GB",
    "wof:name":"RM7 7ER",
    "wof:placetype":"postalcode"
},
  "geometry": {"coordinates":[0.17282762115619,51.58230477835854],"type":"Point"}
}