{
  "type": "Feature",
  "properties": {
    "iso:country":"GB",
    "wof:name":"ME1 2BB",
    "wof:placetype":"postalcode"
},
  "geometry": {"coordinates":[0.51077133773636,51.3695557555391],"type":"Point"}
}