{
  "type": "Feature",
  "properties": {
    "iso:country": "GB",
    "wof:name": "LL28 4RD",
    "wof:placetype": "postalcode"
  },
  "geometry": {"coordinates":[-3.740627,53.310259],"type":"Point"}
}
