{
  "type": "Feature",
  "properties": {
    "date:inception_lower":"1987-04-01",
    "date:inception_upper":"1987-04-30",
    "iso:country":"GB",
    "wof:name":"LL28 4RD",
    "wof:placetype":"postalcode"
},
  "geometry": {"coordinates":[-3.740627,53.310259],"type":"Point"}
}