{
  "type": "Feature",
  "properties": {
    "iso:country": "GB",
    "wof:name": "CH65 8BQ",
    "wof:placetype": "postalcode"
  },
  "geometry": {"coordinates":[-2.90226,53.281649],"type":"Point"}
}
