{
  "type": "Feature",
  "properties": {
    "iso:country": "GB",
    "wof:name": "TR3 6GD",
    "wof:placetype": "postalcode"
  },
  "geometry": {"coordinates":[-5.11481,50.263129],"type":"Point"}
}
