{
  "type": "Feature",
  "properties": {
    "iso:country":"GB",
    "wof:name":"TR3 6GD",
    "wof:placetype":"postalcode"
},
  "geometry": {"coordinates":[-5.11480986904575,50.26312945258876],"type":"Point"}
}