{
  "type": "Feature",
  "properties": {
    "iso:country": "GB",
    "wof:name": "LA2 0JA",
    "wof:placetype": "postalcode"
  },
  "geometry": {"coordinates":[-2.780602,53.979996],"type":"Point"}
}
