{
  "type": "Feature",
  "properties": {
    "iso:country":"GB",
    "wof:name":"NW10 0UA",
    "wof:placetype":"postalcode"
},
  "geometry": {"coordinates":[-0.26513385028666,51.55001247727702],"type":"Point"}
}