{
  "type": "Feature",
  "properties": {
    "iso:country": "GB",
    "wof:name": "RG42 4GL",
    "wof:placetype": "postalcode"
  },
  "geometry": {"coordinates":[-0.790803,51.417287],"type":"Point"}
}
