{
  "type": "Feature",
  "properties": {
    "iso:country":"GB",
    "wof:name":"B18 4JU",
    "wof:placetype":"postalcode"
},
  "geometry": {"coordinates":[-1.94352350499745,52.48781510614225],"type":"Point"}
}