{
  "type": "Feature",
  "properties": {
    "iso:country":"GB",
    "wof:name":"NR4 6PP",
    "wof:placetype":"postalcode"
},
  "geometry": {"coordinates":[1.2746726393403,52.61229782488154],"type":"Point"}
}