{
  "type": "Feature",
  "properties": {
    "date:inception_lower": "2018-05-01",
    "date:inception_upper": "2018-05-01",
    "iso:country": "GB",
    "wof:name": "CW4 8AZ",
    "wof:placetype": "postalcode"
  },
  "geometry": {"coordinates":[-2.344554,53.202992],"type":"Point"}
}
