{
  "type": "Feature",
  "properties": {
    "iso:country": "GB",
    "wof:name": "CW4 8AZ",
    "wof:placetype": "postalcode"
  },
  "geometry": {"coordinates":[-2.34451,53.203082],"type":"Point"}
}
