{
  "type": "Feature",
  "properties": {
    "iso:country":"GB",
    "wof:name":"RG21 7QW",
    "wof:placetype":"postalcode"
},
  "geometry": {"coordinates":[-1.08931065954568,51.26487323232611],"type":"Point"}
}