{
  "type": "Feature",
  "properties": {
    "iso:country": "GB",
    "wof:name": "TN1 2LY",
    "wof:placetype": "postalcode"
  },
  "geometry": {"coordinates":[0.266848,51.131573],"type":"Point"}
}
