{
  "type": "Feature",
  "properties": {
    "iso:country":"GB",
    "wof:name":"DN10 6TF",
    "wof:placetype":"postalcode"
},
  "geometry": {"coordinates":[-1.02189291010311,53.43166776789698],"type":"Point"}
}