{
  "type": "Feature",
  "properties": {
    "iso:country": "GB",
    "wof:name": "DN10 6TF",
    "wof:placetype": "postalcode"
  },
  "geometry": {"coordinates":[-1.021893,53.431668],"type":"Point"}
}
