{
  "type": "Feature",
  "properties": {
    "iso:country": "GB",
    "wof:name": "LL22 8HG",
    "wof:placetype": "postalcode"
  },
  "geometry": {"coordinates":[-3.644531,53.291864],"type":"Point"}
}
