{
  "type": "Feature",
  "properties": {
    "date:inception_lower": "2009-05-01",
    "date:inception_upper": "2009-05-01",
    "iso:country": "GB",
    "wof:name": "M46 9TG",
    "wof:placetype": "postalcode"
  },
  "geometry": {"coordinates":[-2.487666,53.523013],"type":"Point"}
}
