{
  "type": "Feature",
  "properties": {
    "iso:country":"GB",
    "wof:name":"M46 9TG",
    "wof:placetype":"postalcode"
},
  "geometry": {"coordinates":[-2.48766628452679,53.5230129423352],"type":"Point"}
}