{
  "type": "Feature",
  "properties": {
    "iso:country":"GB",
    "wof:name":"TS24 9BW",
    "wof:placetype":"postalcode"
},
  "geometry": {"coordinates":[-1.22723306825625,54.70475744546204],"type":"Point"}
}