{
  "type": "Feature",
  "properties": {
    "iso:country": "GB",
    "wof:name": "AB21 0PN",
    "wof:placetype": "postalcode"
  },
  "geometry": {"coordinates":[-2.190378,57.265136],"type":"Point"}
}
