{
  "type": "Feature",
  "properties": {
    "iso:country":"GB",
    "wof:name":"AB21 0PN",
    "wof:placetype":"postalcode"
},
  "geometry": {"coordinates":[-2.19037786977772,57.26513609221296],"type":"Point"}
}