{
  "type": "Feature",
  "properties": {
    "iso:country":"GB",
    "wof:name":"ME20 6QE",
    "wof:placetype":"postalcode"
},
  "geometry": {"coordinates":[0.43812732332276,51.3032976065797],"type":"Point"}
}