{
  "type": "Feature",
  "properties": {
    "iso:country":"GB",
    "wof:name":"SY6 6AF",
    "wof:placetype":"postalcode"
},
  "geometry": {"coordinates":[-2.81425593992878,52.53769811634609],"type":"Point"}
}