{
  "type": "Feature",
  "properties": {
    "iso:country":"GB",
    "wof:name":"CF3 6XF",
    "wof:placetype":"postalcode"
},
  "geometry": {"coordinates":[-3.09584708409086,51.5440113517507],"type":"Point"}
}