{
  "type": "Feature",
  "properties": {
    "date:inception_lower": "1999-06-01",
    "date:inception_upper": "1999-06-01",
    "iso:country": "GB",
    "wof:name": "CF3 6XF",
    "wof:placetype": "postalcode"
  },
  "geometry": {"coordinates":[-3.095847,51.544011],"type":"Point"}
}
