{
  "type": "Feature",
  "properties": {
    "iso:country":"GB",
    "wof:name":"S44 6XQ",
    "wof:placetype":"postalcode"
},
  "geometry": {"coordinates":[-1.28166227773387,53.22976133330133],"type":"Point"}
}