{
  "type": "Feature",
  "properties": {
    "date:inception_lower": "1985-04-01",
    "date:inception_upper": "1985-04-01",
    "iso:country": "GB",
    "wof:name": "HG1 1HN",
    "wof:placetype": "postalcode"
  },
  "geometry": {"coordinates":[-1.537784,53.988278],"type":"Point"}
}
