{
  "type": "Feature",
  "properties": {
    "date:inception_lower": "1980-01-01",
    "date:inception_upper": "1980-01-01",
    "iso:country": "GB",
    "wof:name": "WN6 9SW",
    "wof:placetype": "postalcode"
  },
  "geometry": {"coordinates":[-2.712416,53.619392],"type":"Point"}
}
