{
  "type": "Feature",
  "properties": {
    "iso:country":"GB",
    "wof:name":"WN6 9SW",
    "wof:placetype":"postalcode"
},
  "geometry": {"coordinates":[-2.71241566635578,53.61939183723027],"type":"Point"}
}