{
  "type": "Feature",
  "properties": {
    "iso:country":"GB",
    "wof:name":"ST13 8TH",
    "wof:placetype":"postalcode"
},
  "geometry": {"coordinates":[-2.01233088296299,53.11851962905671],"type":"Point"}
}