{
  "type": "Feature",
  "properties": {
    "date:inception_lower": "1980-01-01",
    "date:inception_upper": "1980-01-01",
    "iso:country": "GB",
    "wof:name": "ST13 8TH",
    "wof:placetype": "postalcode"
  },
  "geometry": {"coordinates":[-1.996012,53.123563],"type":"Point"}
}
