{
  "type": "Feature",
  "properties": {
    "date:inception_lower": "1984-02-01",
    "date:inception_upper": "1984-02-01",
    "iso:country": "GB",
    "wof:name": "B60 1HZ",
    "wof:placetype": "postalcode"
  },
  "geometry": {"coordinates":[-2.037436,52.367877],"type":"Point"}
}
