{
  "type": "Feature",
  "properties": {
    "iso:country":"GB",
    "wof:name":"B60 1HZ",
    "wof:placetype":"postalcode"
},
  "geometry": {"coordinates":[-2.03743634939074,52.36787736370523],"type":"Point"}
}