{
  "type": "Feature",
  "properties": {
    "iso:country": "GB",
    "wof:name": "SS17 8EP",
    "wof:placetype": "postalcode"
  },
  "geometry": {"coordinates":[0.43794,51.527588],"type":"Point"}
}
