{
  "type": "Feature",
  "properties": {
    "iso:country":"GB",
    "wof:name":"SS17 8EP",
    "wof:placetype":"postalcode"
},
  "geometry": {"coordinates":[0.43793956431409,51.52758784043654],"type":"Point"}
}