{
  "type": "Feature",
  "properties": {
    "iso:country":"GB",
    "wof:name":"DA12 5AE",
    "wof:placetype":"postalcode"
},
  "geometry": {"coordinates":[0.37257097659117,51.42939160787211],"type":"Point"}
}