{
  "type": "Feature",
  "properties": {
    "iso:country": "GB",
    "wof:name": "NR10 4PN",
    "wof:placetype": "postalcode"
  },
  "geometry": {"coordinates":[1.189007,52.746983],"type":"Point"}
}
