{
  "type": "Feature",
  "properties": {
    "date:inception_lower": "1980-01-01",
    "date:inception_upper": "1980-01-01",
    "iso:country": "GB",
    "wof:name": "NR10 4PN",
    "wof:placetype": "postalcode"
  },
  "geometry": {"coordinates":[1.18916,52.747041],"type":"Point"}
}
