{
  "type": "Feature",
  "properties": {
    "date:inception_lower":"1980-01-01",
    "date:inception_upper":"1980-01-31",
    "iso:country":"GB",
    "wof:name":"DN6 9AY",
    "wof:placetype":"postalcode"
},
  "geometry": {"coordinates":[-1.201651,53.66757],"type":"Point"}
}