{
  "type": "Feature",
  "properties": {
    "iso:country":"GB",
    "wof:name":"DN6 9AY",
    "wof:placetype":"postalcode"
},
  "geometry": {"coordinates":[-1.20165135321822,53.66757020527887],"type":"Point"}
}