{
  "type": "Feature",
  "properties": {
    "iso:country":"GB",
    "wof:name":"CF3 0AF",
    "wof:placetype":"postalcode"
},
  "geometry": {"coordinates":[-3.11081614399451,51.52211940305627],"type":"Point"}
}