{
  "type": "Feature",
  "properties": {
    "iso:country": "GB",
    "wof:name": "WS2 8QZ",
    "wof:placetype": "postalcode"
  },
  "geometry": {"coordinates":[-1.99851,52.587733],"type":"Point"}
}
