{
  "type": "Feature",
  "properties": {
    "iso:country":"GB",
    "wof:name":"LN9 5QP",
    "wof:placetype":"postalcode"
},
  "geometry": {"coordinates":[-0.13680679751922,53.24515206032415],"type":"Point"}
}