{
  "type": "Feature",
  "properties": {
    "iso:country":"GB",
    "wof:name":"NG7 6GX",
    "wof:placetype":"postalcode"
},
  "geometry": {"coordinates":[-1.16901088287981,52.97075857006377],"type":"Point"}
}