{
  "type": "Feature",
  "properties": {
    "iso:country": "GB",
    "wof:name": "SG9 9TW",
    "wof:placetype": "postalcode"
  },
  "geometry": {"coordinates":[-0.010806,51.943321],"type":"Point"}
}
