{
  "type": "Feature",
  "properties": {
    "iso:country":"GB",
    "wof:name":"BS41 9AX",
    "wof:placetype":"postalcode"
},
  "geometry": {"coordinates":[-2.66425838082729,51.42615027481452],"type":"Point"}
}