{
  "type": "Feature",
  "properties": {
    "iso:country": "GB",
    "wof:name": "HG2 0HS",
    "wof:placetype": "postalcode"
  },
  "geometry": {"coordinates":[-1.552066,53.979047],"type":"Point"}
}
