{
  "type": "Feature",
  "properties": {
    "iso:country":"GB",
    "wof:name":"PO16 9DU",
    "wof:placetype":"postalcode"
},
  "geometry": {"coordinates":[-1.14317987608459,50.84383472612243],"type":"Point"}
}