{
  "type": "Feature",
  "properties": {
    "iso:country":"GB",
    "wof:name":"PH16 5JJ",
    "wof:placetype":"postalcode"
},
  "geometry": {"coordinates":[-3.72410229881649,56.71817644254149],"type":"Point"}
}