{
  "type": "Feature",
  "properties": {
    "iso:country":"GB",
    "wof:name":"SN2 8YY",
    "wof:placetype":"postalcode"
},
  "geometry": {"coordinates":[-1.76839850023948,51.57163321678111],"type":"Point"}
}