{
  "type": "Feature",
  "properties": {
    "iso:country":"GB",
    "wof:name":"SE9 1DA",
    "wof:placetype":"postalcode"
},
  "geometry": {"coordinates":[0.04946318774269,51.4511261260959],"type":"Point"}
}