{
  "type": "Feature",
  "properties": {
    "date:inception_lower": "1980-01-01",
    "date:inception_upper": "1980-01-01",
    "iso:country": "GB",
    "wof:name": "IG1 1BY",
    "wof:placetype": "postalcode"
  },
  "geometry": {"coordinates":[0.073456,51.558725],"type":"Point"}
}
