{
  "type": "Feature",
  "properties": {
    "iso:country":"GB",
    "wof:name":"TW13 4TG",
    "wof:placetype":"postalcode"
},
  "geometry": {"coordinates":[-0.42517662398245,51.4442010597267],"type":"Point"}
}