{
  "type": "Feature",
  "properties": {
    "date:inception_lower": "2000-12-01",
    "date:inception_upper": "2000-12-01",
    "iso:country": "GB",
    "wof:name": "HX1 1EB",
    "wof:placetype": "postalcode"
  },
  "geometry": {"coordinates":[-1.873055,53.718653],"type":"Point"}
}
