{
  "type": "Feature",
  "properties": {
    "iso:country": "GB",
    "wof:name": "HX1 1EB",
    "wof:placetype": "postalcode"
  },
  "geometry": {"coordinates":[-1.873055,53.718653],"type":"Point"}
}
