{
  "type": "Feature",
  "properties": {
    "iso:country":"GB",
    "wof:name":"BH25 7HJ",
    "wof:placetype":"postalcode"
},
  "geometry": {"coordinates":[-1.65897222381634,50.73662715138711],"type":"Point"}
}