{
  "type": "Feature",
  "properties": {
    "iso:country":"GB",
    "wof:name":"IP33 3LG",
    "wof:placetype":"postalcode"
},
  "geometry": {"coordinates":[0.69825213770248,52.2387022163316],"type":"Point"}
}