{
  "type": "Feature",
  "properties": {
    "iso:country":"GB",
    "wof:name":"BN10 8PL",
    "wof:placetype":"postalcode"
},
  "geometry": {"coordinates":[0.01180388202479,50.78782690674137],"type":"Point"}
}