{
  "type": "Feature",
  "properties": {
    "iso:country":"GB",
    "wof:name":"SE9 5EP",
    "wof:placetype":"postalcode"
},
  "geometry": {"coordinates":[0.04105757308347,51.44595803706367],"type":"Point"}
}