{
  "type": "Feature",
  "properties": {
    "iso:country": "GB",
    "wof:name": "PR4 0YH",
    "wof:placetype": "postalcode"
  },
  "geometry": {"coordinates":[-2.817171,53.778185],"type":"Point"}
}
