{
  "type": "Feature",
  "properties": {
    "iso:country":"GB",
    "wof:name":"PR4 0YH",
    "wof:placetype":"postalcode"
},
  "geometry": {"coordinates":[-2.81717056352903,53.77818506471008],"type":"Point"}
}