{
  "type": "Feature",
  "properties": {
    "iso:country":"GB",
    "wof:name":"N1 5HU",
    "wof:placetype":"postalcode"
},
  "geometry": {"coordinates":[-0.07990750993576,51.53353060926264],"type":"Point"}
}