{
  "type": "Feature",
  "properties": {
    "iso:country":"GB",
    "wof:name":"PH2 7JG",
    "wof:placetype":"postalcode"
},
  "geometry": {"coordinates":[-3.41516292555879,56.40365151246635],"type":"Point"}
}