{
  "type": "Feature",
  "properties": {
    "date:inception_lower": "1980-01-01",
    "date:inception_upper": "1980-01-01",
    "iso:country": "GB",
    "wof:name": "PH2 7JG",
    "wof:placetype": "postalcode"
  },
  "geometry": {"coordinates":[-3.414813,56.403413],"type":"Point"}
}
