{
  "type": "Feature",
  "properties": {
    "date:inception_lower":"2007-09-01",
    "date:inception_upper":"2007-09-30",
    "iso:country":"GB",
    "wof:name":"WR5 3FH",
    "wof:placetype":"postalcode"
},
  "geometry": {"coordinates":[-2.217709,52.169078],"type":"Point"}
}