{
  "type": "Feature",
  "properties": {
    "iso:country":"GB",
    "wof:name":"WR5 3FH",
    "wof:placetype":"postalcode"
},
  "geometry": {"coordinates":[-2.2177090288769,52.16907770294112],"type":"Point"}
}