{
  "type": "Feature",
  "properties": {
    "iso:country": "GB",
    "wof:name": "CM7 5BH",
    "wof:placetype": "postalcode"
  },
  "geometry": {"coordinates":[0.534457,51.901726],"type":"Point"}
}
