{
  "type": "Feature",
  "properties": {
    "iso:country": "GB",
    "wof:name": "CT9 2QH",
    "wof:placetype": "postalcode"
  },
  "geometry": {"coordinates":[1.394076,51.387452],"type":"Point"}
}
