{
  "type": "Feature",
  "properties": {
    "date:inception_lower": "2003-10-01",
    "date:inception_upper": "2003-10-01",
    "iso:country": "GB",
    "wof:name": "M9 8NY",
    "wof:placetype": "postalcode"
  },
  "geometry": {"coordinates":[-2.221078,53.519139],"type":"Point"}
}
