{
  "type": "Feature",
  "properties": {
    "iso:country":"GB",
    "wof:name":"M9 8NY",
    "wof:placetype":"postalcode"
},
  "geometry": {"coordinates":[-2.22107760379079,53.51913863800922],"type":"Point"}
}