{
  "type": "Feature",
  "properties": {
    "date:inception_lower": "2002-12-01",
    "date:inception_upper": "2002-12-01",
    "iso:country": "GB",
    "wof:name": "HP4 2FE",
    "wof:placetype": "postalcode"
  },
  "geometry": {"coordinates":[-0.558224,51.759705],"type":"Point"}
}
