{
  "type": "Feature",
  "properties": {
    "iso:country":"GB",
    "wof:name":"KA25 7JW",
    "wof:placetype":"postalcode"
},
  "geometry": {"coordinates":[-4.67900966336141,55.75560551828949],"type":"Point"}
}