{
  "type": "Feature",
  "properties": {
    "iso:country": "GB",
    "wof:name": "KA25 7JW",
    "wof:placetype": "postalcode"
  },
  "geometry": {"coordinates":[-4.67901,55.755606],"type":"Point"}
}
