{
  "type": "Feature",
  "properties": {
    "date:inception_lower":"1983-02-01",
    "date:inception_upper":"1983-02-28",
    "iso:country":"GB",
    "wof:name":"KA25 7JW",
    "wof:placetype":"postalcode"
},
  "geometry": {"coordinates":[-4.67901,55.755606],"type":"Point"}
}