{
  "type": "Feature",
  "properties": {
    "iso:country": "GB",
    "wof:name": "CT3 1UU",
    "wof:placetype": "postalcode"
  },
  "geometry": {"coordinates":[1.166835,51.271886],"type":"Point"}
}
