{
  "type": "Feature",
  "properties": {
    "iso:country":"GB",
    "wof:name":"GU22 8ET",
    "wof:placetype":"postalcode"
},
  "geometry": {"coordinates":[-0.53345570363634,51.32291469612959],"type":"Point"}
}