{
  "type": "Feature",
  "properties": {
    "iso:country": "GB",
    "wof:name": "SK3 9LL",
    "wof:placetype": "postalcode"
  },
  "geometry": {"coordinates":[-2.175622,53.40275],"type":"Point"}
}
