{
  "type": "Feature",
  "properties": {
    "date:inception_lower":"1980-01-01",
    "date:inception_upper":"1980-01-31",
    "iso:country":"GB",
    "wof:name":"SK3 9LL",
    "wof:placetype":"postalcode"
},
  "geometry": {"coordinates":[-2.175622,53.40275],"type":"Point"}
}