{
  "type": "Feature",
  "properties": {
    "date:inception_lower": "1980-01-01",
    "date:inception_upper": "1980-01-01",
    "iso:country": "GB",
    "wof:name": "WR2 6RA",
    "wof:placetype": "postalcode"
  },
  "geometry": {"coordinates":[-2.277811,52.212726],"type":"Point"}
}
