{
  "type": "Feature",
  "properties": {
    "iso:country":"GB",
    "wof:name":"HX2 6RE",
    "wof:placetype":"postalcode"
},
  "geometry": {"coordinates":[-1.94252700218978,53.73351000871106],"type":"Point"}
}