{
  "type": "Feature",
  "properties": {
    "iso:country":"GB",
    "wof:name":"BA12 9EY",
    "wof:placetype":"postalcode"
},
  "geometry": {"coordinates":[-2.15550549173584,51.19824474467089],"type":"Point"}
}