{
  "type": "Feature",
  "properties": {
    "date:inception_lower": "1998-12-01",
    "date:inception_upper": "1998-12-01",
    "iso:country": "GB",
    "wof:name": "IV30 8PY",
    "wof:placetype": "postalcode"
  },
  "geometry": {"coordinates":[-3.222118,57.634333],"type":"Point"}
}
