{
  "type": "Feature",
  "properties": {
    "date:inception_lower": "1980-01-01",
    "date:inception_upper": "1980-01-01",
    "iso:country": "GB",
    "wof:name": "N13 4LA",
    "wof:placetype": "postalcode"
  },
  "geometry": {"coordinates":[-0.122644,51.615478],"type":"Point"}
}
