{
  "type": "Feature",
  "properties": {
    "date:inception_lower": "1994-05-01",
    "date:inception_upper": "1994-05-01",
    "iso:country": "GB",
    "wof:name": "M20 2WQ",
    "wof:placetype": "postalcode"
  },
  "geometry": {"coordinates":[-2.245485,53.423481],"type":"Point"}
}
