{
  "type": "Feature",
  "properties": {
    "iso:country":"GB",
    "wof:name":"M20 2WQ",
    "wof:placetype":"postalcode"
},
  "geometry": {"coordinates":[-2.24521556594384,53.42372382256475],"type":"Point"}
}