{
  "type": "Feature",
  "properties": {
    "iso:country":"GB",
    "wof:name":"DN17 1PX",
    "wof:placetype":"postalcode"
},
  "geometry": {"coordinates":[-0.6792677228596,53.57334741831347],"type":"Point"}
}