{
  "type": "Feature",
  "properties": {
    "date:inception_lower":"1980-01-01",
    "date:inception_upper":"1980-01-31",
    "iso:country":"GB",
    "wof:name":"PO37 6NU",
    "wof:placetype":"postalcode"
},
  "geometry": {"coordinates":[-1.179214,50.62483],"type":"Point"}
}