{
  "type": "Feature",
  "properties": {
    "iso:country": "GB",
    "wof:name": "CH64 6RW",
    "wof:placetype": "postalcode"
  },
  "geometry": {"coordinates":[-3.084481,53.297084],"type":"Point"}
}
