{
  "type": "Feature",
  "properties": {
    "iso:country":"GB",
    "wof:name":"DD5 3GQ",
    "wof:placetype":"postalcode"
},
  "geometry": {"coordinates":[-2.86761457811633,56.48409727012152],"type":"Point"}
}