{
  "type": "Feature",
  "properties": {
    "date:inception_lower":"2008-08-01",
    "date:inception_upper":"2008-08-31",
    "iso:country":"GB",
    "wof:name":"DD5 3GQ",
    "wof:placetype":"postalcode"
},
  "geometry": {"coordinates":[-2.867615,56.484097],"type":"Point"}
}