{
  "type": "Feature",
  "properties": {
    "iso:country": "GB",
    "wof:name": "DD5 3GQ",
    "wof:placetype": "postalcode"
  },
  "geometry": {"coordinates":[-2.867615,56.484097],"type":"Point"}
}
