{
  "type": "Feature",
  "properties": {
    "iso:country": "GB",
    "wof:name": "EX5 2SW",
    "wof:placetype": "postalcode"
  },
  "geometry": {"coordinates":[-3.358445,50.765981],"type":"Point"}
}
