{
  "type": "Feature",
  "properties": {
    "iso:country":"GB",
    "wof:name":"WF4 2EA",
    "wof:placetype":"postalcode"
},
  "geometry": {"coordinates":[-1.42124661050224,53.64223591179099],"type":"Point"}
}