{
  "type": "Feature",
  "properties": {
    "date:inception_lower": "1980-01-01",
    "date:inception_upper": "1980-01-01",
    "iso:country": "GB",
    "wof:name": "WF4 2EA",
    "wof:placetype": "postalcode"
  },
  "geometry": {"coordinates":[-1.421247,53.642236],"type":"Point"}
}
