{
  "type": "Feature",
  "properties": {
    "iso:country": "GB",
    "wof:name": "L37 8DB",
    "wof:placetype": "postalcode"
  },
  "geometry": {"coordinates":[-3.048048,53.559341],"type":"Point"}
}
