{
  "type": "Feature",
  "properties": {
    "date:inception_lower":"1980-01-01",
    "date:inception_upper":"1980-01-31",
    "iso:country":"GB",
    "wof:name":"L37 8DB",
    "wof:placetype":"postalcode"
},
  "geometry": {"coordinates":[-3.048048,53.559341],"type":"Point"}
}