{
  "type": "Feature",
  "properties": {
    "iso:country":"GB",
    "wof:name":"L37 8DB",
    "wof:placetype":"postalcode"
},
  "geometry": {"coordinates":[-3.04804806527817,53.55934099118971],"type":"Point"}
}