{
  "type": "Feature",
  "properties": {
    "iso:country":"GB",
    "wof:name":"DT11 7EA",
    "wof:placetype":"postalcode"
},
  "geometry": {"coordinates":[-2.16133955646475,50.85639826859029],"type":"Point"}
}