{
  "type": "Feature",
  "properties": {
    "iso:country": "GB",
    "wof:name": "HP16 9QG",
    "wof:placetype": "postalcode"
  },
  "geometry": {"coordinates":[-0.687777,51.708648],"type":"Point"}
}
