{
  "type": "Feature",
  "properties": {
    "iso:country":"GB",
    "wof:name":"HP16 9QG",
    "wof:placetype":"postalcode"
},
  "geometry": {"coordinates":[-0.68777731793206,51.70864824808916],"type":"Point"}
}