{
  "type": "Feature",
  "properties": {
    "iso:country":"GB",
    "wof:name":"TF5 0DY",
    "wof:placetype":"postalcode"
},
  "geometry": {"coordinates":[-2.54029871047476,52.71712106192081],"type":"Point"}
}