{
  "type": "Feature",
  "properties": {
    "iso:country":"GB",
    "wof:name":"DE1 2AD",
    "wof:placetype":"postalcode"
},
  "geometry": {"coordinates":[-1.47496351710174,52.91951062910329],"type":"Point"}
}