{
  "type": "Feature",
  "properties": {
    "date:inception_lower":"1980-01-01",
    "date:inception_upper":"1980-01-31",
    "iso:country":"GB",
    "wof:name":"DE1 2AD",
    "wof:placetype":"postalcode"
},
  "geometry": {"coordinates":[-1.474963,52.919511],"type":"Point"}
}