{
  "type": "Feature",
  "properties": {
    "date:inception_lower": "2000-06-01",
    "date:inception_upper": "2000-06-01",
    "iso:country": "GB",
    "wof:name": "HG5 0TY",
    "wof:placetype": "postalcode"
  },
  "geometry": {"coordinates":[-1.441539,54.006177],"type":"Point"}
}
