{
  "type": "Feature",
  "properties": {
    "iso:country":"GB",
    "wof:name":"HG5 0TY",
    "wof:placetype":"postalcode"
},
  "geometry": {"coordinates":[-1.44153903338942,54.00617726771799],"type":"Point"}
}