{
  "type": "Feature",
  "properties": {
    "iso:country":"GB",
    "wof:name":"WD3 1JS",
    "wof:placetype":"postalcode"
},
  "geometry": {"coordinates":[-0.46050917449445,51.62823586144228],"type":"Point"}
}