{
  "type": "Feature",
  "properties": {
    "iso:country": "GB",
    "wof:name": "WD3 1JS",
    "wof:placetype": "postalcode"
  },
  "geometry": {"coordinates":[-0.460509,51.628236],"type":"Point"}
}
