{
  "type": "Feature",
  "properties": {
    "iso:country": "GB",
    "wof:name": "CH66 3SA",
    "wof:placetype": "postalcode"
  },
  "geometry": {"coordinates":[-2.93879,53.284048],"type":"Point"}
}
