{
  "type": "Feature",
  "properties": {
    "iso:country":"GB",
    "wof:name":"CH66 3SA",
    "wof:placetype":"postalcode"
},
  "geometry": {"coordinates":[-2.93879019749505,53.28404760661581],"type":"Point"}
}