{
  "type": "Feature",
  "properties": {
    "iso:country":"GB",
    "wof:name":"LE5 5ND",
    "wof:placetype":"postalcode"
},
  "geometry": {"coordinates":[-1.09434455096986,52.62599493984069],"type":"Point"}
}