{
  "type": "Feature",
  "properties": {
    "date:inception_lower":"2004-03-01",
    "date:inception_upper":"2004-03-31",
    "iso:country":"GB",
    "wof:name":"G20 6NT",
    "wof:placetype":"postalcode"
},
  "geometry": {"coordinates":[-4.27748,55.875642],"type":"Point"}
}