{
  "type": "Feature",
  "properties": {
    "date:inception_lower": "2019-11-01",
    "date:inception_upper": "2019-11-01",
    "iso:country": "GB",
    "wof:name": "SO14 0TD",
    "wof:placetype": "postalcode"
  },
  "geometry": {"coordinates":[-1.395955,50.91697],"type":"Point"}
}
