{
  "type": "Feature",
  "properties": {
    "iso:country": "GB",
    "wof:name": "LS13 4FA",
    "wof:placetype": "postalcode"
  },
  "geometry": {"coordinates":[-1.646286,53.807172],"type":"Point"}
}
