{
  "type": "Feature",
  "properties": {
    "iso:country":"GB",
    "wof:name":"LS13 4FA",
    "wof:placetype":"postalcode"
},
  "geometry": {"coordinates":[-1.64628638059206,53.80717184614865],"type":"Point"}
}