{
  "type": "Feature",
  "properties": {
    "iso:country":"GB",
    "wof:name":"WC2H 9HN",
    "wof:placetype":"postalcode"
},
  "geometry": {"coordinates":[-0.12495673452506,51.51408913521744],"type":"Point"}
}