{
  "type": "Feature",
  "properties": {
    "date:inception_lower":"2006-07-01",
    "date:inception_upper":"2006-07-31",
    "iso:country":"GB",
    "wof:name":"SO23 0HZ",
    "wof:placetype":"postalcode"
},
  "geometry": {"coordinates":[-1.305896,51.057902],"type":"Point"}
}