{
  "type": "Feature",
  "properties": {
    "iso:country":"GB",
    "wof:name":"S73 0JQ",
    "wof:placetype":"postalcode"
},
  "geometry": {"coordinates":[-1.40007543421591,53.51913409215702],"type":"Point"}
}