{
  "type": "Feature",
  "properties": {
    "iso:country":"GB",
    "wof:name":"TS15 9BH",
    "wof:placetype":"postalcode"
},
  "geometry": {"coordinates":[-1.35449532763631,54.50850822006988],"type":"Point"}
}