{
  "type": "Feature",
  "properties": {
    "iso:country":"GB",
    "wof:name":"SY13 4BD",
    "wof:placetype":"postalcode"
},
  "geometry": {"coordinates":[-2.57275486846892,52.97468922901612],"type":"Point"}
}