{
  "type": "Feature",
  "properties": {
    "iso:country": "GB",
    "wof:name": "SY13 4BD",
    "wof:placetype": "postalcode"
  },
  "geometry": {"coordinates":[-2.572755,52.974689],"type":"Point"}
}
