{
  "type": "Feature",
  "properties": {
    "iso:country":"GB",
    "wof:name":"AB31 5NY",
    "wof:placetype":"postalcode"
},
  "geometry": {"coordinates":[-2.46642097942369,57.06033611699623],"type":"Point"}
}