{
  "type": "Feature",
  "properties": {
    "date:inception_lower": "1980-01-01",
    "date:inception_upper": "1980-01-01",
    "iso:country": "GB",
    "wof:name": "YO12 5AT",
    "wof:placetype": "postalcode"
  },
  "geometry": {"coordinates":[-0.410921,54.277566],"type":"Point"}
}
