{
  "type": "Feature",
  "properties": {
    "date:inception_lower": "1980-01-01",
    "date:inception_upper": "1980-01-01",
    "iso:country": "GB",
    "wof:name": "NE47 6JS",
    "wof:placetype": "postalcode"
  },
  "geometry": {"coordinates":[-2.231962,54.980094],"type":"Point"}
}
