{
  "type": "Feature",
  "properties": {
    "iso:country":"GB",
    "wof:name":"BN44 3LY",
    "wof:placetype":"postalcode"
},
  "geometry": {"coordinates":[-0.33277529044939,50.89133277826446],"type":"Point"}
}