{
  "type": "Feature",
  "properties": {
    "iso:country":"GB",
    "wof:name":"SN4 8LW",
    "wof:placetype":"postalcode"
},
  "geometry": {"coordinates":[-1.88801089021986,51.54316149219853],"type":"Point"}
}