{
  "type": "Feature",
  "properties": {
    "date:inception_lower": "1983-01-01",
    "date:inception_upper": "1983-01-01",
    "iso:country": "GB",
    "wof:name": "SN4 8LW",
    "wof:placetype": "postalcode"
  },
  "geometry": {"coordinates":[-1.888011,51.543161],"type":"Point"}
}
