{
  "type": "Feature",
  "properties": {
    "date:inception_lower":"2005-02-01",
    "date:inception_upper":"2005-02-28",
    "iso:country":"GB",
    "wof:name":"CM0 7JZ",
    "wof:placetype":"postalcode"
},
  "geometry": {"coordinates":[0.830297,51.714064],"type":"Point"}
}