{
  "type": "Feature",
  "properties": {
    "iso:country": "GB",
    "wof:name": "CM0 7JZ",
    "wof:placetype": "postalcode"
  },
  "geometry": {"coordinates":[0.830297,51.714064],"type":"Point"}
}
