{
  "type": "Feature",
  "properties": {
    "iso:country": "GB",
    "wof:name": "SG2 8BH",
    "wof:placetype": "postalcode"
  },
  "geometry": {"coordinates":[-0.167507,51.883622],"type":"Point"}
}
