{
  "type": "Feature",
  "properties": {
    "iso:country":"GB",
    "wof:name":"SG2 8BH",
    "wof:placetype":"postalcode"
},
  "geometry": {"coordinates":[-0.16750703897191,51.88362243938079],"type":"Point"}
}