{
  "type": "Feature",
  "properties": {
    "iso:country": "GB",
    "wof:name": "EN10 6RN",
    "wof:placetype": "postalcode"
  },
  "geometry": {"coordinates":[-0.006791,51.737529],"type":"Point"}
}
