{
  "type": "Feature",
  "properties": {
    "iso:country": "GB",
    "wof:name": "TQ14 8HR",
    "wof:placetype": "postalcode"
  },
  "geometry": {"coordinates":[-3.49516,50.546827],"type":"Point"}
}
