{
  "type": "Feature",
  "properties": {
    "iso:country": "GB",
    "wof:name": "YO25 5AR",
    "wof:placetype": "postalcode"
  },
  "geometry": {"coordinates":[-0.445143,54.012585],"type":"Point"}
}
