{
  "type": "Feature",
  "properties": {
    "date:inception_lower":"1987-04-01",
    "date:inception_upper":"1987-04-30",
    "iso:country":"GB",
    "wof:name":"IG8 9DN",
    "wof:placetype":"postalcode"
},
  "geometry": {"coordinates":[0.086868,51.646481],"type":"Point"}
}