{
  "type": "Feature",
  "properties": {
    "iso:country":"GB",
    "wof:name":"BS37 8QU",
    "wof:placetype":"postalcode"
},
  "geometry": {"coordinates":[-2.43995685591476,51.5146681652239],"type":"Point"}
}