{
  "type": "Feature",
  "properties": {
    "iso:country":"GB",
    "wof:name":"B4 6NH",
    "wof:placetype":"postalcode"
},
  "geometry": {"coordinates":[-1.89375423623368,52.48489522098551],"type":"Point"}
}