{
  "type": "Feature",
  "properties": {
    "iso:country":"GB",
    "wof:name":"LL58 8AP",
    "wof:placetype":"postalcode"
},
  "geometry": {"coordinates":[-4.09148987162096,53.26338196153095],"type":"Point"}
}