{
  "type": "Feature",
  "properties": {
    "iso:country": "GB",
    "wof:name": "CM2 8XN",
    "wof:placetype": "postalcode"
  },
  "geometry": {"coordinates":[0.474809,51.711869],"type":"Point"}
}
