{
  "type": "Feature",
  "properties": {
    "iso:country":"GB",
    "wof:name":"PE24 4QF",
    "wof:placetype":"postalcode"
},
  "geometry": {"coordinates":[0.1752245165818,53.12914503432548],"type":"Point"}
}