{
  "type": "Feature",
  "properties": {
    "iso:country":"GB",
    "wof:name":"CT13 0LF",
    "wof:placetype":"postalcode"
},
  "geometry": {"coordinates":[1.29887573150984,51.24348261262833],"type":"Point"}
}