{
  "type": "Feature",
  "properties": {
    "date:inception_lower":"1980-01-01",
    "date:inception_upper":"1980-01-31",
    "iso:country":"GB",
    "wof:name":"TW19 7LD",
    "wof:placetype":"postalcode"
},
  "geometry": {"coordinates":[-0.474241,51.458149],"type":"Point"}
}