{
  "type": "Feature",
  "properties": {
    "iso:country":"GB",
    "wof:name":"TW19 7LD",
    "wof:placetype":"postalcode"
},
  "geometry": {"coordinates":[-0.4742412960187,51.4581493936887],"type":"Point"}
}