{
  "type": "Feature",
  "properties": {
    "iso:country":"GB",
    "wof:name":"PL20 7TN",
    "wof:placetype":"postalcode"
},
  "geometry": {"coordinates":[-4.09873550139866,50.51060243786696],"type":"Point"}
}