{
  "type": "Feature",
  "properties": {
    "iso:country": "GB",
    "wof:name": "LL44 2BS",
    "wof:placetype": "postalcode"
  },
  "geometry": {"coordinates":[-4.103074,52.795351],"type":"Point"}
}
