{
  "type": "Feature",
  "properties": {
    "iso:country":"GB",
    "wof:name":"LL44 2BS",
    "wof:placetype":"postalcode"
},
  "geometry": {"coordinates":[-4.10307374523445,52.79535121209182],"type":"Point"}
}