{
  "type": "Feature",
  "properties": {
    "iso:country":"GB",
    "wof:name":"HS1 2UH",
    "wof:placetype":"postalcode"
},
  "geometry": {"coordinates":[-6.39388203764087,58.22255143438419],"type":"Point"}
}