{
  "type": "Feature",
  "properties": {
    "iso:country":"GB",
    "wof:name":"DY4 7BG",
    "wof:placetype":"postalcode"
},
  "geometry": {"coordinates":[-2.04005270948055,52.53134175949662],"type":"Point"}
}