{
  "type": "Feature",
  "properties": {
    "iso:country": "GB",
    "wof:name": "FK9 4BE",
    "wof:placetype": "postalcode"
  },
  "geometry": {"coordinates":[-3.94051,56.151265],"type":"Point"}
}
