{
  "type": "Feature",
  "properties": {
    "iso:country":"GB",
    "wof:name":"GL11 5SW",
    "wof:placetype":"postalcode"
},
  "geometry": {"coordinates":[-2.30305861916879,51.68443588416164],"type":"Point"}
}