{
  "type": "Feature",
  "properties": {
    "iso:country":"GB",
    "wof:name":"PE19 6SU",
    "wof:placetype":"postalcode"
},
  "geometry": {"coordinates":[-0.15163559725258,52.22227319122203],"type":"Point"}
}