{
  "type": "Feature",
  "properties": {
    "date:inception_lower": "2000-06-01",
    "date:inception_upper": "2000-06-01",
    "iso:country": "GB",
    "wof:name": "PE19 6SU",
    "wof:placetype": "postalcode"
  },
  "geometry": {"coordinates":[-0.151636,52.222273],"type":"Point"}
}
