{
  "type": "Feature",
  "properties": {
    "iso:country":"GB",
    "wof:name":"SN8 4AN",
    "wof:placetype":"postalcode"
},
  "geometry": {"coordinates":[-1.7206413145896,51.41558982787257],"type":"Point"}
}