{
  "type": "Feature",
  "properties": {
    "iso:country":"GB",
    "wof:name":"G71 5AF",
    "wof:placetype":"postalcode"
},
  "geometry": {"coordinates":[-4.0511517586749,55.82730583263673],"type":"Point"}
}