{
  "type": "Feature",
  "properties": {
    "iso:country":"GB",
    "wof:name":"ST2 8BG",
    "wof:placetype":"postalcode"
},
  "geometry": {"coordinates":[-2.14004383859141,53.02955380637088],"type":"Point"}
}