{
  "type": "Feature",
  "properties": {
    "date:inception_lower":"1980-01-01",
    "date:inception_upper":"1980-01-31",
    "iso:country":"GB",
    "wof:name":"ST2 8BG",
    "wof:placetype":"postalcode"
},
  "geometry": {"coordinates":[-2.140044,53.029554],"type":"Point"}
}