{
  "type": "Feature",
  "properties": {
    "date:inception_lower": "1980-01-01",
    "date:inception_upper": "1980-01-01",
    "iso:country": "GB",
    "wof:name": "IG10 2JX",
    "wof:placetype": "postalcode"
  },
  "geometry": {"coordinates":[0.077636,51.658272],"type":"Point"}
}
