{
  "type": "Feature",
  "properties": {
    "iso:country":"GB",
    "wof:name":"IG10 2JX",
    "wof:placetype":"postalcode"
},
  "geometry": {"coordinates":[0.07763562601597,51.65827197732058],"type":"Point"}
}