{
  "type": "Feature",
  "properties": {
    "iso:country":"GB",
    "wof:name":"OX9 2DY",
    "wof:placetype":"postalcode"
},
  "geometry": {"coordinates":[-0.97804097445647,51.74494317255167],"type":"Point"}
}