{
  "type": "Feature",
  "properties": {
    "iso:country": "GB",
    "wof:name": "OX9 2DY",
    "wof:placetype": "postalcode"
  },
  "geometry": {"coordinates":[-0.978041,51.744943],"type":"Point"}
}
