{
  "type": "Feature",
  "properties": {
    "iso:country": "GB",
    "wof:name": "WV12 5XX",
    "wof:placetype": "postalcode"
  },
  "geometry": {"coordinates":[-2.042347,52.616807],"type":"Point"}
}
