{
  "type": "Feature",
  "properties": {
    "iso:country":"GB",
    "wof:name":"WV12 5XX",
    "wof:placetype":"postalcode"
},
  "geometry": {"coordinates":[-2.04234666757436,52.61680712366871],"type":"Point"}
}