{
  "type": "Feature",
  "properties": {
    "iso:country": "GB",
    "wof:name": "DY7 6EY",
    "wof:placetype": "postalcode"
  },
  "geometry": {"coordinates":[-2.231485,52.447722],"type":"Point"}
}
