{
  "type": "Feature",
  "properties": {
    "iso:country":"GB",
    "wof:name":"SN10 3JL",
    "wof:placetype":"postalcode"
},
  "geometry": {"coordinates":[-1.9346003601274,51.34146209451646],"type":"Point"}
}