{
  "type": "Feature",
  "properties": {
    "iso:country": "GB",
    "wof:name": "SN10 3JL",
    "wof:placetype": "postalcode"
  },
  "geometry": {"coordinates":[-1.9346,51.341462],"type":"Point"}
}
