{
  "type": "Feature",
  "properties": {
    "iso:country":"GB",
    "wof:name":"RG45 7QQ",
    "wof:placetype":"postalcode"
},
  "geometry": {"coordinates":[-0.80007063055733,51.36275409419851],"type":"Point"}
}