{
  "type": "Feature",
  "properties": {
    "iso:country":"GB",
    "wof:name":"UB5 4SL",
    "wof:placetype":"postalcode"
},
  "geometry": {"coordinates":[-0.35179911100769,51.5505425080252],"type":"Point"}
}