{
  "type": "Feature",
  "properties": {
    "date:inception_lower":"2000-12-01",
    "date:inception_upper":"2000-12-31",
    "iso:country":"GB",
    "wof:name":"IP9 2TT",
    "wof:placetype":"postalcode"
},
  "geometry": {"coordinates":[1.154065,51.983854],"type":"Point"}
}