{
  "type": "Feature",
  "properties": {
    "iso:country":"GB",
    "wof:name":"IP9 2TT",
    "wof:placetype":"postalcode"
},
  "geometry": {"coordinates":[1.15403447294238,51.98384121603644],"type":"Point"}
}