{
  "type": "Feature",
  "properties": {
    "iso:country":"GB",
    "wof:name":"EH1 2LE",
    "wof:placetype":"postalcode"
},
  "geometry": {"coordinates":[-3.20001682455083,55.94624783184344],"type":"Point"}
}