{
  "type": "Feature",
  "properties": {
    "date:inception_lower": "1992-01-01",
    "date:inception_upper": "1992-01-01",
    "iso:country": "GB",
    "wof:name": "EH1 2LE",
    "wof:placetype": "postalcode"
  },
  "geometry": {"coordinates":[-3.200018,55.946243],"type":"Point"}
}
