{
  "type": "Feature",
  "properties": {
    "iso:country":"GB",
    "wof:name":"CW11 1WQ",
    "wof:placetype":"postalcode"
},
  "geometry": {"coordinates":[-2.38295740624398,53.14774710885182],"type":"Point"}
}