{
  "type": "Feature",
  "properties": {
    "iso:country": "GB",
    "wof:name": "CW11 1WQ",
    "wof:placetype": "postalcode"
  },
  "geometry": {"coordinates":[-2.382957,53.147747],"type":"Point"}
}
