{
  "type": "Feature",
  "properties": {
    "iso:country":"GB",
    "wof:name":"WN8 8JZ",
    "wof:placetype":"postalcode"
},
  "geometry": {"coordinates":[-2.80609774237374,53.55012491641642],"type":"Point"}
}