{
  "type": "Feature",
  "properties": {
    "date:inception_lower": "2022-09-01",
    "date:inception_upper": "2022-09-01",
    "iso:country": "GB",
    "wof:name": "S81 7GB",
    "wof:placetype": "postalcode"
  },
  "geometry": {"coordinates":[-1.13858,53.334463],"type":"Point"}
}
