{
  "type": "Feature",
  "properties": {
    "iso:country":"GB",
    "wof:name":"EX23 8QR",
    "wof:placetype":"postalcode"
},
  "geometry": {"coordinates":[-4.53689993244084,50.82321057097558],"type":"Point"}
}