{
  "type": "Feature",
  "properties": {
    "iso:country":"GB",
    "wof:name":"LA1 2QG",
    "wof:placetype":"postalcode"
},
  "geometry": {"coordinates":[-2.81241365444196,54.05615492014076],"type":"Point"}
}