{
  "type": "Feature",
  "properties": {
    "date:inception_lower": "1997-12-01",
    "date:inception_upper": "1997-12-01",
    "iso:country": "GB",
    "wof:name": "BS34 7LJ",
    "wof:placetype": "postalcode"
  },
  "geometry": {"coordinates":[-2.564336,51.504038],"type":"Point"}
}
