{
  "type": "Feature",
  "properties": {
    "iso:country":"GB",
    "wof:name":"RM11 1UB",
    "wof:placetype":"postalcode"
},
  "geometry": {"coordinates":[0.2197522768703,51.56271225558303],"type":"Point"}
}