{
  "type": "Feature",
  "properties": {
    "date:inception_lower": "1981-06-01",
    "date:inception_upper": "1981-06-01",
    "iso:country": "GB",
    "wof:name": "CO16 8FG",
    "wof:placetype": "postalcode"
  },
  "geometry": {"coordinates":[1.137609,51.807709],"type":"Point"}
}
