{
  "type": "Feature",
  "properties": {
    "iso:country": "GB",
    "wof:name": "CO16 8FG",
    "wof:placetype": "postalcode"
  },
  "geometry": {"coordinates":[1.137609,51.807709],"type":"Point"}
}
