{
  "type": "Feature",
  "properties": {
    "iso:country":"GB",
    "wof:name":"CO16 8FG",
    "wof:placetype":"postalcode"
},
  "geometry": {"coordinates":[1.13760917604528,51.80770884286125],"type":"Point"}
}