{
  "type": "Feature",
  "properties": {
    "date:inception_lower": "1988-03-01",
    "date:inception_upper": "1988-03-01",
    "iso:country": "GB",
    "wof:name": "TR7 2TQ",
    "wof:placetype": "postalcode"
  },
  "geometry": {"coordinates":[-5.068419,50.404661],"type":"Point"}
}
