{
  "type": "Feature",
  "properties": {
    "iso:country": "GB",
    "wof:name": "GU35 8BS",
    "wof:placetype": "postalcode"
  },
  "geometry": {"coordinates":[-0.822748,51.12209],"type":"Point"}
}
