{
  "type": "Feature",
  "properties": {
    "iso:country": "GB",
    "wof:name": "BB12 7SB",
    "wof:placetype": "postalcode"
  },
  "geometry": {"coordinates":[-2.346268,53.811884],"type":"Point"}
}
