{
  "type": "Feature",
  "properties": {
    "date:inception_lower":"2001-12-01",
    "date:inception_upper":"2001-12-31",
    "iso:country":"GB",
    "wof:name":"BB12 7SB",
    "wof:placetype":"postalcode"
},
  "geometry": {"coordinates":[-2.346268,53.811884],"type":"Point"}
}