{
  "type": "Feature",
  "properties": {
    "iso:country":"GB",
    "wof:name":"WA9 3TS",
    "wof:placetype":"postalcode"
},
  "geometry": {"coordinates":[-2.7230879381843,53.43340812999952],"type":"Point"}
}