{
  "type": "Feature",
  "properties": {
    "iso:country": "GB",
    "wof:name": "WA9 3TS",
    "wof:placetype": "postalcode"
  },
  "geometry": {"coordinates":[-2.723088,53.433408],"type":"Point"}
}
