{
  "type": "Feature",
  "properties": {
    "iso:country":"GB",
    "wof:name":"YO10 3JY",
    "wof:placetype":"postalcode"
},
  "geometry": {"coordinates":[-1.04342007631486,53.95405517007662],"type":"Point"}
}