{
  "type": "Feature",
  "properties": {
    "iso:country":"GB",
    "wof:name":"BS27 3YU",
    "wof:placetype":"postalcode"
},
  "geometry": {"coordinates":[-2.75542075584962,51.27699848635378],"type":"Point"}
}