{
  "type": "Feature",
  "properties": {
    "date:inception_lower": "1980-01-01",
    "date:inception_upper": "1980-01-01",
    "iso:country": "GB",
    "wof:name": "BS27 3YU",
    "wof:placetype": "postalcode"
  },
  "geometry": {"coordinates":[-2.755421,51.276998],"type":"Point"}
}
