{
  "type": "Feature",
  "properties": {
    "iso:country": "GB",
    "wof:name": "BS27 3YU",
    "wof:placetype": "postalcode"
  },
  "geometry": {"coordinates":[-2.755421,51.276998],"type":"Point"}
}
