{
  "type": "Feature",
  "properties": {
    "iso:country":"GB",
    "wof:name":"DA5 1ER",
    "wof:placetype":"postalcode"
},
  "geometry": {"coordinates":[0.13703332222736,51.44812341811161],"type":"Point"}
}