{
  "type": "Feature",
  "properties": {
    "iso:country": "GB",
    "wof:name": "DA5 1ER",
    "wof:placetype": "postalcode"
  },
  "geometry": {"coordinates":[0.137247,51.448129],"type":"Point"}
}
