{
  "type": "Feature",
  "properties": {
    "iso:country": "GB",
    "wof:name": "KA20 3ER",
    "wof:placetype": "postalcode"
  },
  "geometry": {"coordinates":[-4.755377,55.641983],"type":"Point"}
}
