{
  "type": "Feature",
  "properties": {
    "iso:country":"GB",
    "wof:name":"KA20 3ER",
    "wof:placetype":"postalcode"
},
  "geometry": {"coordinates":[-4.75539882734757,55.64198535308919],"type":"Point"}
}