{
  "type": "Feature",
  "properties": {
    "date:inception_lower":"2000-12-01",
    "date:inception_upper":"2000-12-31",
    "iso:country":"GB",
    "wof:name":"KA20 3ER",
    "wof:placetype":"postalcode"
},
  "geometry": {"coordinates":[-4.755377,55.641983],"type":"Point"}
}