{
  "type": "Feature",
  "properties": {
    "iso:country": "GB",
    "wof:name": "KA20 3ER",
    "wof:placetype": "postalcode"
  },
  "geometry": {"coordinates":[-4.755282,55.641985],"type":"Point"}
}
