{
  "type": "Feature",
  "properties": {
    "iso:country":"GB",
    "wof:name":"LE3 1RG",
    "wof:placetype":"postalcode"
},
  "geometry": {"coordinates":[-1.18443140200169,52.62927422026865],"type":"Point"}
}