{
  "type": "Feature",
  "properties": {
    "iso:country": "GB",
    "wof:name": "LE3 1RG",
    "wof:placetype": "postalcode"
  },
  "geometry": {"coordinates":[-1.184431,52.629274],"type":"Point"}
}
