{
  "type": "Feature",
  "properties": {
    "iso:country": "GB",
    "wof:name": "SO16 8AE",
    "wof:placetype": "postalcode"
  },
  "geometry": {"coordinates":[-1.455118,50.948366],"type":"Point"}
}
