{
  "type": "Feature",
  "properties": {
    "date:inception_lower": "2021-01-01",
    "date:inception_upper": "2021-01-01",
    "iso:country": "GB",
    "wof:name": "WF8 2FX",
    "wof:placetype": "postalcode"
  },
  "geometry": {"coordinates":[-1.287358,53.702042],"type":"Point"}
}
