{
  "type": "Feature",
  "properties": {
    "iso:country": "GB",
    "wof:name": "LS27 8FH",
    "wof:placetype": "postalcode"
  },
  "geometry": {"coordinates":[-1.580534,53.749749],"type":"Point"}
}
