{
  "type": "Feature",
  "properties": {
    "date:inception_lower": "2019-10-01",
    "date:inception_upper": "2019-10-01",
    "iso:country": "GB",
    "wof:name": "LS27 8FH",
    "wof:placetype": "postalcode"
  },
  "geometry": {"coordinates":[-1.580534,53.749749],"type":"Point"}
}
