{
  "type": "Feature",
  "properties": {
    "date:inception_lower": "2007-10-01",
    "date:inception_upper": "2007-10-01",
    "iso:country": "GB",
    "wof:name": "G33 2EB",
    "wof:placetype": "postalcode"
  },
  "geometry": {"coordinates":[-4.198915,55.862562],"type":"Point"}
}
