{
  "type": "Feature",
  "properties": {
    "iso:country":"GB",
    "wof:name":"NN17 1LF",
    "wof:placetype":"postalcode"
},
  "geometry": {"coordinates":[-0.70333149869563,52.49776280549762],"type":"Point"}
}