{
  "type": "Feature",
  "properties": {
    "iso:country":"GB",
    "wof:name":"BS13 8RH",
    "wof:placetype":"postalcode"
},
  "geometry": {"coordinates":[-2.62772828352267,51.40538298927615],"type":"Point"}
}