{
  "type": "Feature",
  "properties": {
    "date:inception_lower": "1998-12-01",
    "date:inception_upper": "1998-12-01",
    "iso:country": "GB",
    "wof:name": "EC4N 5AF",
    "wof:placetype": "postalcode"
  },
  "geometry": {"coordinates":[-0.089736,51.511614],"type":"Point"}
}
