{
  "type": "Feature",
  "properties": {
    "iso:country":"GB",
    "wof:name":"EC4N 5AF",
    "wof:placetype":"postalcode"
},
  "geometry": {"coordinates":[-0.08973556404253,51.51161435010384],"type":"Point"}
}