{
  "type": "Feature",
  "properties": {
    "date:inception_lower":"1995-12-01",
    "date:inception_upper":"1995-12-31",
    "iso:country":"GB",
    "wof:name":"KY15 7BU",
    "wof:placetype":"postalcode"
},
  "geometry": {"coordinates":[-3.207743,56.253002],"type":"Point"}
}