{
  "type": "Feature",
  "properties": {
    "iso:country": "GB",
    "wof:name": "KY15 7BU",
    "wof:placetype": "postalcode"
  },
  "geometry": {"coordinates":[-3.207743,56.253002],"type":"Point"}
}
