{
  "type": "Feature",
  "properties": {
    "iso:country": "GB",
    "wof:name": "HP3 8DU",
    "wof:placetype": "postalcode"
  },
  "geometry": {"coordinates":[-0.450645,51.74635],"type":"Point"}
}
