{
  "type": "Feature",
  "properties": {
    "iso:country":"GB",
    "wof:name":"IP21 4NN",
    "wof:placetype":"postalcode"
},
  "geometry": {"coordinates":[1.18274190284258,52.39594870615652],"type":"Point"}
}