{
  "type": "Feature",
  "properties": {
    "date:inception_lower": "1980-01-01",
    "date:inception_upper": "1980-01-01",
    "iso:country": "GB",
    "wof:name": "BR5 4PE",
    "wof:placetype": "postalcode"
  },
  "geometry": {"coordinates":[0.117961,51.373702],"type":"Point"}
}
