{
  "type": "Feature",
  "properties": {
    "iso:country":"GB",
    "wof:name":"SW19 6ET",
    "wof:placetype":"postalcode"
},
  "geometry": {"coordinates":[-0.21625813044149,51.44432878305],"type":"Point"}
}