{
  "type": "Feature",
  "properties": {
    "iso:country": "GB",
    "wof:name": "TN18 4HH",
    "wof:placetype": "postalcode"
  },
  "geometry": {"coordinates":[0.513393,51.048123],"type":"Point"}
}
