{
  "type": "Feature",
  "properties": {
    "date:inception_lower":"1980-01-01",
    "date:inception_upper":"1980-01-31",
    "iso:country":"GB",
    "wof:name":"TN18 4HH",
    "wof:placetype":"postalcode"
},
  "geometry": {"coordinates":[0.513288,51.048046],"type":"Point"}
}