{
  "type": "Feature",
  "properties": {
    "iso:country": "GB",
    "wof:name": "WA15 7BX",
    "wof:placetype": "postalcode"
  },
  "geometry": {"coordinates":[-2.315468,53.392216],"type":"Point"}
}
