{
  "type": "Feature",
  "properties": {
    "iso:country":"GB",
    "wof:name":"IV54 8XX",
    "wof:placetype":"postalcode"
},
  "geometry": {"coordinates":[-5.86209028581008,57.50821476244414],"type":"Point"}
}