{
  "type": "Feature",
  "properties": {
    "date:inception_lower": "1980-01-01",
    "date:inception_upper": "1980-01-01",
    "iso:country": "GB",
    "wof:name": "IV54 8XX",
    "wof:placetype": "postalcode"
  },
  "geometry": {"coordinates":[-5.86209,57.508215],"type":"Point"}
}
