{
  "type": "Feature",
  "properties": {
    "iso:country": "GB",
    "wof:name": "ST19 9JS",
    "wof:placetype": "postalcode"
  },
  "geometry": {"coordinates":[-2.189121,52.713842],"type":"Point"}
}
