{
  "type": "Feature",
  "properties": {
    "iso:country": "GB",
    "wof:name": "RH13 0RW",
    "wof:placetype": "postalcode"
  },
  "geometry": {"coordinates":[-0.40995,51.071226],"type":"Point"}
}
