{
  "type": "Feature",
  "properties": {
    "iso:country": "GB",
    "wof:name": "KT13 9JL",
    "wof:placetype": "postalcode"
  },
  "geometry": {"coordinates":[-0.42843,51.384616],"type":"Point"}
}
