{
  "type": "Feature",
  "properties": {
    "iso:country":"GB",
    "wof:name":"L13 2DU",
    "wof:placetype":"postalcode"
},
  "geometry": {"coordinates":[-2.91928728797932,53.41442272282118],"type":"Point"}
}