{
  "type": "Feature",
  "properties": {
    "date:inception_lower": "1995-07-01",
    "date:inception_upper": "1995-07-01",
    "iso:country": "GB",
    "wof:name": "TA2 7SZ",
    "wof:placetype": "postalcode"
  },
  "geometry": {"coordinates":[-3.108911,51.02969],"type":"Point"}
}
