{
  "type": "Feature",
  "properties": {
    "iso:country":"GB",
    "wof:name":"WD3 8LX",
    "wof:placetype":"postalcode"
},
  "geometry": {"coordinates":[-0.49687633207515,51.64566588414471],"type":"Point"}
}