{
  "type": "Feature",
  "properties": {
    "iso:country":"GB",
    "wof:name":"WC2B 5HH",
    "wof:placetype":"postalcode"
},
  "geometry": {"coordinates":[-0.12073970189008,51.51324828583791],"type":"Point"}
}