{
  "type": "Feature",
  "properties": {
    "date:inception_lower":"2000-12-01",
    "date:inception_upper":"2000-12-31",
    "iso:country":"GB",
    "wof:name":"WC2H 7BF",
    "wof:placetype":"postalcode"
},
  "geometry": {"coordinates":[-0.131485,51.511289],"type":"Point"}
}