{
  "type": "Feature",
  "properties": {
    "iso:country": "GB",
    "wof:name": "S81 8FN",
    "wof:placetype": "postalcode"
  },
  "geometry": {"coordinates":[-1.157533,53.326752],"type":"Point"}
}
