{
  "type": "Feature",
  "properties": {
    "date:inception_lower": "2020-02-01",
    "date:inception_upper": "2020-02-01",
    "iso:country": "GB",
    "wof:name": "S81 8FN",
    "wof:placetype": "postalcode"
  },
  "geometry": {"coordinates":[-1.157548,53.326707],"type":"Point"}
}
