{
  "type": "Feature",
  "properties": {
    "iso:country":"GB",
    "wof:name":"KW16 3BB",
    "wof:placetype":"postalcode"
},
  "geometry": {"coordinates":[-3.29933065786519,58.96258072761584],"type":"Point"}
}