{
  "type": "Feature",
  "properties": {
    "iso:country":"GB",
    "wof:name":"HU12 9NN",
    "wof:placetype":"postalcode"
},
  "geometry": {"coordinates":[-0.15085303966387,53.71498884351863],"type":"Point"}
}