{
  "type": "Feature",
  "properties": {
    "date:inception_lower":"1980-01-01",
    "date:inception_upper":"1980-01-31",
    "iso:country":"GB",
    "wof:name":"UB8 3PE",
    "wof:placetype":"postalcode"
},
  "geometry": {"coordinates":[-0.475907,51.527816],"type":"Point"}
}