{
  "type": "Feature",
  "properties": {
    "iso:country":"GB",
    "wof:name":"NG12 4DW",
    "wof:placetype":"postalcode"
},
  "geometry": {"coordinates":[-1.10997387304339,52.91176443163646],"type":"Point"}
}