{
  "type": "Feature",
  "properties": {
    "date:inception_lower": "1980-01-01",
    "date:inception_upper": "1980-01-01",
    "iso:country": "GB",
    "wof:name": "SA5 4SH",
    "wof:placetype": "postalcode"
  },
  "geometry": {"coordinates":[-4.025526,51.642435],"type":"Point"}
}
