{
  "type": "Feature",
  "properties": {
    "iso:country":"GB",
    "wof:name":"SA5 4SH",
    "wof:placetype":"postalcode"
},
  "geometry": {"coordinates":[-4.02551183208103,51.64223164263245],"type":"Point"}
}