{
  "type": "Feature",
  "properties": {
    "iso:country": "GB",
    "wof:name": "HP23 5FP",
    "wof:placetype": "postalcode"
  },
  "geometry": {"coordinates":[-0.655338,51.796291],"type":"Point"}
}
