{
  "type": "Feature",
  "properties": {
    "iso:country":"GB",
    "wof:name":"IP21 4EY",
    "wof:placetype":"postalcode"
},
  "geometry": {"coordinates":[1.14412435228744,52.37657663634783],"type":"Point"}
}