{
  "type": "Feature",
  "properties": {
    "iso:country": "GB",
    "wof:name": "IP21 4EY",
    "wof:placetype": "postalcode"
  },
  "geometry": {"coordinates":[1.144182,52.376605],"type":"Point"}
}
