{
  "type": "Feature",
  "properties": {
    "iso:country":"GB",
    "wof:name":"G76 0QB",
    "wof:placetype":"postalcode"
},
  "geometry": {"coordinates":[-4.30174889056064,55.73756798835711],"type":"Point"}
}