{
  "type": "Feature",
  "properties": {
    "iso:country":"GB",
    "wof:name":"HU3 6SY",
    "wof:placetype":"postalcode"
},
  "geometry": {"coordinates":[-0.3848962348561,53.74371287735685],"type":"Point"}
}