{
  "type": "Feature",
  "properties": {
    "iso:country":"GB",
    "wof:name":"PL6 8UU",
    "wof:placetype":"postalcode"
},
  "geometry": {"coordinates":[-4.10496090532549,50.41522324208569],"type":"Point"}
}