{
  "type": "Feature",
  "properties": {
    "date:inception_lower": "2005-01-01",
    "date:inception_upper": "2005-01-01",
    "iso:country": "GB",
    "wof:name": "SE10 0RU",
    "wof:placetype": "postalcode"
  },
  "geometry": {"coordinates":[0.014483,51.492829],"type":"Point"}
}
