{
  "type": "Feature",
  "properties": {
    "iso:country":"GB",
    "wof:name":"IP4 2SZ",
    "wof:placetype":"postalcode"
},
  "geometry": {"coordinates":[1.16554086454989,52.0659441204519],"type":"Point"}
}