{
  "type": "Feature",
  "properties": {
    "iso:country":"GB",
    "wof:name":"YO18 8EG",
    "wof:placetype":"postalcode"
},
  "geometry": {"coordinates":[-0.7830308969054,54.24491998172096],"type":"Point"}
}