{
  "type": "Feature",
  "properties": {
    "iso:country":"GB",
    "wof:name":"BN25 3RG",
    "wof:placetype":"postalcode"
},
  "geometry": {"coordinates":[0.12239689095031,50.77398582771951],"type":"Point"}
}