{
  "type": "Feature",
  "properties": {
    "iso:country":"GB",
    "wof:name":"S36 6AJ",
    "wof:placetype":"postalcode"
},
  "geometry": {"coordinates":[-1.63175186187778,53.52774768992574],"type":"Point"}
}