{
  "type": "Feature",
  "properties": {
    "date:inception_lower": "1980-01-01",
    "date:inception_upper": "1980-01-01",
    "iso:country": "GB",
    "wof:name": "RG1 4DX",
    "wof:placetype": "postalcode"
  },
  "geometry": {"coordinates":[-0.95708,51.452891],"type":"Point"}
}
