{
  "type": "Feature",
  "properties": {
    "iso:country":"GB",
    "wof:name":"RG1 4DX",
    "wof:placetype":"postalcode"
},
  "geometry": {"coordinates":[-0.95710005179581,51.45289031177813],"type":"Point"}
}