{
  "type": "Feature",
  "properties": {
    "iso:country": "GB",
    "wof:name": "BS48 3SD",
    "wof:placetype": "postalcode"
  },
  "geometry": {"coordinates":[-2.67679,51.408704],"type":"Point"}
}
