{
  "type": "Feature",
  "properties": {
    "iso:country":"GB",
    "wof:name":"DN7 5AT",
    "wof:placetype":"postalcode"
},
  "geometry": {"coordinates":[-1.02934308706956,53.60131041542231],"type":"Point"}
}