{
  "type": "Feature",
  "properties": {
    "iso:country":"GB",
    "wof:name":"EN6 5ES",
    "wof:placetype":"postalcode"
},
  "geometry": {"coordinates":[-0.17401459381965,51.68871215315455],"type":"Point"}
}