{
  "type": "Feature",
  "properties": {
    "iso:country": "GB",
    "wof:name": "TA6 6QZ",
    "wof:placetype": "postalcode"
  },
  "geometry": {"coordinates":[-3.009389,51.09303],"type":"Point"}
}
