{
  "type": "Feature",
  "properties": {
    "date:inception_lower": "1980-01-01",
    "date:inception_upper": "1980-01-01",
    "iso:country": "GB",
    "wof:name": "TA6 6QZ",
    "wof:placetype": "postalcode"
  },
  "geometry": {"coordinates":[-3.009389,51.09303],"type":"Point"}
}
