{
  "type": "Feature",
  "properties": {
    "iso:country":"GB",
    "wof:name":"TA6 6QZ",
    "wof:placetype":"postalcode"
},
  "geometry": {"coordinates":[-3.00938106978365,51.09300880905577],"type":"Point"}
}