{
  "type": "Feature",
  "properties": {
    "iso:country": "GB",
    "wof:name": "YO31 0SE",
    "wof:placetype": "postalcode"
  },
  "geometry": {"coordinates":[-1.059441,53.96334],"type":"Point"}
}
