{
  "type": "Feature",
  "properties": {
    "date:inception_lower": "2000-10-01",
    "date:inception_upper": "2000-10-01",
    "iso:country": "GB",
    "wof:name": "OX25 6LU",
    "wof:placetype": "postalcode"
  },
  "geometry": {"coordinates":[-1.255392,51.968145],"type":"Point"}
}
