{
  "type": "Feature",
  "properties": {
    "iso:country":"GB",
    "wof:name":"OX25 6LU",
    "wof:placetype":"postalcode"
},
  "geometry": {"coordinates":[-1.25539199272695,51.96814484579851],"type":"Point"}
}