{
  "type": "Feature",
  "properties": {
    "date:inception_lower": "1993-01-01",
    "date:inception_upper": "1993-01-01",
    "iso:country": "GB",
    "wof:name": "BB3 1LY",
    "wof:placetype": "postalcode"
  },
  "geometry": {"coordinates":[-2.479796,53.703216],"type":"Point"}
}
