{
  "type": "Feature",
  "properties": {
    "iso:country": "GB",
    "wof:name": "BB3 1LY",
    "wof:placetype": "postalcode"
  },
  "geometry": {"coordinates":[-2.479796,53.703216],"type":"Point"}
}
