{
  "type": "Feature",
  "properties": {
    "iso:country":"GB",
    "wof:name":"BB3 1LY",
    "wof:placetype":"postalcode"
},
  "geometry": {"coordinates":[-2.47979620545398,53.70321582265414],"type":"Point"}
}