{
  "type": "Feature",
  "properties": {
    "iso:country":"GB",
    "wof:name":"NW10 7BN",
    "wof:placetype":"postalcode"
},
  "geometry": {"coordinates":[-0.26224948960598,51.53183225762512],"type":"Point"}
}