{
  "type": "Feature",
  "properties": {
    "date:inception_lower": "1980-01-01",
    "date:inception_upper": "1980-01-01",
    "iso:country": "GB",
    "wof:name": "NW10 7BN",
    "wof:placetype": "postalcode"
  },
  "geometry": {"coordinates":[-0.262249,51.531832],"type":"Point"}
}
