{
  "type": "Feature",
  "properties": {
    "iso:country":"GB",
    "wof:name":"ME13 0BT",
    "wof:placetype":"postalcode"
},
  "geometry": {"coordinates":[0.78826512544099,51.25374731608907],"type":"Point"}
}