{
  "type": "Feature",
  "properties": {
    "date:inception_lower":"1980-01-01",
    "date:inception_upper":"1980-01-31",
    "iso:country":"GB",
    "wof:name":"ME13 0BT",
    "wof:placetype":"postalcode"
},
  "geometry": {"coordinates":[0.788265,51.253747],"type":"Point"}
}