{
  "type": "Feature",
  "properties": {
    "iso:country":"GB",
    "wof:name":"BN18 0RP",
    "wof:placetype":"postalcode"
},
  "geometry": {"coordinates":[-0.63262191355857,50.86736981957689],"type":"Point"}
}