{
  "type": "Feature",
  "properties": {
    "iso:country": "GB",
    "wof:name": "BN18 0RP",
    "wof:placetype": "postalcode"
  },
  "geometry": {"coordinates":[-0.632622,50.86737],"type":"Point"}
}
