{
  "type": "Feature",
  "properties": {
    "iso:country":"GB",
    "wof:name":"RH16 1JZ",
    "wof:placetype":"postalcode"
},
  "geometry": {"coordinates":[-0.11508100284001,51.00681307989937],"type":"Point"}
}