{
  "type": "Feature",
  "properties": {
    "iso:country":"GB",
    "wof:name":"NW7 2AJ",
    "wof:placetype":"postalcode"
},
  "geometry": {"coordinates":[-0.24470543617165,51.60969625683087],"type":"Point"}
}