{
  "type": "Feature",
  "properties": {
    "iso:country":"GB",
    "wof:name":"EH21 6HT",
    "wof:placetype":"postalcode"
},
  "geometry": {"coordinates":[-3.06664553220415,55.9327028851314],"type":"Point"}
}