{
  "type": "Feature",
  "properties": {
    "date:inception_lower": "2017-06-01",
    "date:inception_upper": "2017-06-01",
    "iso:country": "GB",
    "wof:name": "CT6 6FB",
    "wof:placetype": "postalcode"
  },
  "geometry": {"coordinates":[1.194127,51.376425],"type":"Point"}
}
