{
  "type": "Feature",
  "properties": {
    "iso:country":"GB",
    "wof:name":"OX2 7RL",
    "wof:placetype":"postalcode"
},
  "geometry": {"coordinates":[-1.269353679136,51.78600155246455],"type":"Point"}
}