{
  "type": "Feature",
  "properties": {
    "iso:country": "GB",
    "wof:name": "OX2 7RL",
    "wof:placetype": "postalcode"
  },
  "geometry": {"coordinates":[-1.269354,51.786002],"type":"Point"}
}
