{
  "type": "Feature",
  "properties": {
    "iso:country": "GB",
    "wof:name": "PE23 5NH",
    "wof:placetype": "postalcode"
  },
  "geometry": {"coordinates":[0.068352,53.179024],"type":"Point"}
}
