{
  "type": "Feature",
  "properties": {
    "iso:country":"GB",
    "wof:name":"BN2 6BP",
    "wof:placetype":"postalcode"
},
  "geometry": {"coordinates":[-0.0823474176589,50.83702477418691],"type":"Point"}
}