{
  "type": "Feature",
  "properties": {
    "iso:country": "GB",
    "wof:name": "EX33 1JE",
    "wof:placetype": "postalcode"
  },
  "geometry": {"coordinates":[-4.172125,51.114259],"type":"Point"}
}
