{
  "type": "Feature",
  "properties": {
    "iso:country":"GB",
    "wof:name":"FY3 8RS",
    "wof:placetype":"postalcode"
},
  "geometry": {"coordinates":[-3.0359429561971,53.82462677041566],"type":"Point"}
}