{
  "type": "Feature",
  "properties": {
    "iso:country":"GB",
    "wof:name":"BL7 9BY",
    "wof:placetype":"postalcode"
},
  "geometry": {"coordinates":[-2.42326317323802,53.6170250980696],"type":"Point"}
}