{
  "type": "Feature",
  "properties": {
    "date:inception_lower": "1980-01-01",
    "date:inception_upper": "1980-01-01",
    "iso:country": "GB",
    "wof:name": "BL7 9BY",
    "wof:placetype": "postalcode"
  },
  "geometry": {"coordinates":[-2.423263,53.617025],"type":"Point"}
}
