{
  "type": "Feature",
  "properties": {
    "iso:country":"GB",
    "wof:name":"OL4 1BB",
    "wof:placetype":"postalcode"
},
  "geometry": {"coordinates":[-2.0936930877427,53.53843383441822],"type":"Point"}
}