{
  "type": "Feature",
  "properties": {
    "iso:country":"GB",
    "wof:name":"BD9 6NE",
    "wof:placetype":"postalcode"
},
  "geometry": {"coordinates":[-1.81294921790871,53.81610369846909],"type":"Point"}
}