{
  "type": "Feature",
  "properties": {
    "iso:country":"GB",
    "wof:name":"EN8 0QY",
    "wof:placetype":"postalcode"
},
  "geometry": {"coordinates":[-0.04968240035948,51.71318698152817],"type":"Point"}
}