{
  "type": "Feature",
  "properties": {
    "date:inception_lower": "1999-12-01",
    "date:inception_upper": "1999-12-01",
    "iso:country": "GB",
    "wof:name": "OL13 8RX",
    "wof:placetype": "postalcode"
  },
  "geometry": {"coordinates":[-2.199389,53.724177],"type":"Point"}
}
