{
  "type": "Feature",
  "properties": {
    "iso:country":"GB",
    "wof:name":"ST3 3HU",
    "wof:placetype":"postalcode"
},
  "geometry": {"coordinates":[-2.16393535069009,52.97189363624907],"type":"Point"}
}