{
  "type": "Feature",
  "properties": {
    "iso:country": "GB",
    "wof:name": "ST3 3HU",
    "wof:placetype": "postalcode"
  },
  "geometry": {"coordinates":[-2.163935,52.971894],"type":"Point"}
}
