{
  "type": "Feature",
  "properties": {
    "date:inception_lower": "2002-12-01",
    "date:inception_upper": "2002-12-01",
    "iso:country": "GB",
    "wof:name": "KA5 5TW",
    "wof:placetype": "postalcode"
  },
  "geometry": {"coordinates":[-4.410942,55.5463],"type":"Point"}
}
