{
  "type": "Feature",
  "properties": {
    "iso:country":"GB",
    "wof:name":"KA5 5TW",
    "wof:placetype":"postalcode"
},
  "geometry": {"coordinates":[-4.41094164833296,55.54630025637],"type":"Point"}
}