{
  "type": "Feature",
  "properties": {
    "iso:country": "GB",
    "wof:name": "NE15 8TW",
    "wof:placetype": "postalcode"
  },
  "geometry": {"coordinates":[-1.716272,54.987255],"type":"Point"}
}
