{
  "type": "Feature",
  "properties": {
    "iso:country":"GB",
    "wof:name":"NE15 8TW",
    "wof:placetype":"postalcode"
},
  "geometry": {"coordinates":[-1.71627181471301,54.98725475980252],"type":"Point"}
}