{
  "type": "Feature",
  "properties": {
    "iso:country":"GB",
    "wof:name":"DD1 5LP",
    "wof:placetype":"postalcode"
},
  "geometry": {"coordinates":[-2.99334788930634,56.460010864896],"type":"Point"}
}