{
  "type": "Feature",
  "properties": {
    "iso:country": "GB",
    "wof:name": "DD1 5LP",
    "wof:placetype": "postalcode"
  },
  "geometry": {"coordinates":[-2.993348,56.460011],"type":"Point"}
}
