{
  "type": "Feature",
  "properties": {
    "iso:country":"GB",
    "wof:name":"IV25 3SL",
    "wof:placetype":"postalcode"
},
  "geometry": {"coordinates":[-4.03230313169672,57.88082594054377],"type":"Point"}
}