{
  "type": "Feature",
  "properties": {
    "date:inception_lower":"1980-01-01",
    "date:inception_upper":"1980-01-31",
    "iso:country":"GB",
    "wof:name":"IV25 3SL",
    "wof:placetype":"postalcode"
},
  "geometry": {"coordinates":[-4.032115,57.880775],"type":"Point"}
}