{
  "type": "Feature",
  "properties": {
    "iso:country":"GB",
    "wof:name":"NR18 9BY",
    "wof:placetype":"postalcode"
},
  "geometry": {"coordinates":[1.10183074984496,52.56429842431333],"type":"Point"}
}