{
  "type": "Feature",
  "properties": {
    "iso:country":"GB",
    "wof:name":"PE30 1PL",
    "wof:placetype":"postalcode"
},
  "geometry": {"coordinates":[0.40079559310515,52.75826507805792],"type":"Point"}
}