{
  "type": "Feature",
  "properties": {
    "date:inception_lower":"2014-08-01",
    "date:inception_upper":"2014-08-31",
    "iso:country":"GB",
    "wof:name":"PE30 1PL",
    "wof:placetype":"postalcode"
},
  "geometry": {"coordinates":[0.400796,52.758265],"type":"Point"}
}