{
  "type": "Feature",
  "properties": {
    "iso:country": "GB",
    "wof:name": "CV2 1HH",
    "wof:placetype": "postalcode"
  },
  "geometry": {"coordinates":[-1.465349,52.437068],"type":"Point"}
}
