{
  "type": "Feature",
  "properties": {
    "iso:country":"GB",
    "wof:name":"CV2 1HH",
    "wof:placetype":"postalcode"
},
  "geometry": {"coordinates":[-1.46537156083646,52.4370235202073],"type":"Point"}
}