{
  "type": "Feature",
  "properties": {
    "date:inception_lower": "1999-12-01",
    "date:inception_upper": "1999-12-01",
    "iso:country": "GB",
    "wof:name": "BL3 4TB",
    "wof:placetype": "postalcode"
  },
  "geometry": {"coordinates":[-2.47265,53.564231],"type":"Point"}
}
