{
  "type": "Feature",
  "properties": {
    "iso:country":"GB",
    "wof:name":"FK2 9XJ",
    "wof:placetype":"postalcode"
},
  "geometry": {"coordinates":[-3.74113549018233,55.98763075900264],"type":"Point"}
}