{
  "type": "Feature",
  "properties": {
    "iso:country": "GB",
    "wof:name": "S72 0HU",
    "wof:placetype": "postalcode"
  },
  "geometry": {"coordinates":[-1.3506,53.541248],"type":"Point"}
}
