{
  "type": "Feature",
  "properties": {
    "iso:country": "GB",
    "wof:name": "LL30 1LN",
    "wof:placetype": "postalcode"
  },
  "geometry": {"coordinates":[-3.820912,53.314014],"type":"Point"}
}
