{
  "type": "Feature",
  "properties": {
    "iso:country":"GB",
    "wof:name":"LL30 1LN",
    "wof:placetype":"postalcode"
},
  "geometry": {"coordinates":[-3.82091177740748,53.31401378250482],"type":"Point"}
}