{
  "type": "Feature",
  "properties": {
    "iso:country": "GB",
    "wof:name": "TN31 7AA",
    "wof:placetype": "postalcode"
  },
  "geometry": {"coordinates":[0.731356,50.951732],"type":"Point"}
}
