{
  "type": "Feature",
  "properties": {
    "iso:country":"GB",
    "wof:name":"EX36 3HG",
    "wof:placetype":"postalcode"
},
  "geometry": {"coordinates":[-3.80689907368135,51.04924412969715],"type":"Point"}
}