{
  "type": "Feature",
  "properties": {
    "date:inception_lower": "2016-10-01",
    "date:inception_upper": "2016-10-01",
    "iso:country": "GB",
    "wof:name": "PE7 8PG",
    "wof:placetype": "postalcode"
  },
  "geometry": {"coordinates":[-0.262749,52.537267],"type":"Point"}
}
