{
  "type": "Feature",
  "properties": {
    "iso:country":"GB",
    "wof:name":"AL6 0SH",
    "wof:placetype":"postalcode"
},
  "geometry": {"coordinates":[-0.1925269444236,51.84198102870896],"type":"Point"}
}