{
  "type": "Feature",
  "properties": {
    "date:inception_lower": "1980-01-01",
    "date:inception_upper": "1980-01-01",
    "iso:country": "GB",
    "wof:name": "PO10 8SS",
    "wof:placetype": "postalcode"
  },
  "geometry": {"coordinates":[-0.926298,50.866475],"type":"Point"}
}
