{
  "type": "Feature",
  "properties": {
    "iso:country":"GB",
    "wof:name":"PO10 8SS",
    "wof:placetype":"postalcode"
},
  "geometry": {"coordinates":[-0.92629754303579,50.86647460350211],"type":"Point"}
}