{
  "type": "Feature",
  "properties": {
    "iso:country": "GB",
    "wof:name": "SE10 9HB",
    "wof:placetype": "postalcode"
  },
  "geometry": {"coordinates":[0.008092,51.484423],"type":"Point"}
}
