{
  "type": "Feature",
  "properties": {
    "iso:country":"GB",
    "wof:name":"DN3 1NS",
    "wof:placetype":"postalcode"
},
  "geometry": {"coordinates":[-1.06677485931458,53.56701986592824],"type":"Point"}
}