{
  "type": "Feature",
  "properties": {
    "iso:country": "GB",
    "wof:name": "IP24 2YR",
    "wof:placetype": "postalcode"
  },
  "geometry": {"coordinates":[0.752132,52.404238],"type":"Point"}
}
