{
  "type": "Feature",
  "properties": {
    "iso:country": "GB",
    "wof:name": "NP11 5LW",
    "wof:placetype": "postalcode"
  },
  "geometry": {"coordinates":[-3.128716,51.674583],"type":"Point"}
}
