{
  "type": "Feature",
  "properties": {
    "iso:country":"GB",
    "wof:name":"EH16 4RW",
    "wof:placetype":"postalcode"
},
  "geometry": {"coordinates":[-3.12371923870069,55.93414523759355],"type":"Point"}
}