{
  "type": "Feature",
  "properties": {
    "iso:country":"GB",
    "wof:name":"G69 8HD",
    "wof:placetype":"postalcode"
},
  "geometry": {"coordinates":[-4.0623374626976,55.89320939311052],"type":"Point"}
}