{
  "type": "Feature",
  "properties": {
    "iso:country":"GB",
    "wof:name":"NP26 5QZ",
    "wof:placetype":"postalcode"
},
  "geometry": {"coordinates":[-2.75702533783285,51.60924138817958],"type":"Point"}
}