{
  "type": "Feature",
  "properties": {
    "iso:country":"GB",
    "wof:name":"MK41 7ES",
    "wof:placetype":"postalcode"
},
  "geometry": {"coordinates":[-0.45767612536667,52.16014350722845],"type":"Point"}
}