{
  "type": "Feature",
  "properties": {
    "date:inception_lower":"1980-01-01",
    "date:inception_upper":"1980-01-31",
    "iso:country":"GB",
    "wof:name":"WS3 3JJ",
    "wof:placetype":"postalcode"
},
  "geometry": {"coordinates":[-2.0004,52.613363],"type":"Point"}
}