{
  "type": "Feature",
  "properties": {
    "iso:country":"GB",
    "wof:name":"WS3 3JJ",
    "wof:placetype":"postalcode"
},
  "geometry": {"coordinates":[-2.00039994618707,52.61336272021951],"type":"Point"}
}