{
  "type": "Feature",
  "properties": {
    "iso:country":"GB",
    "wof:name":"RH19 4AX",
    "wof:placetype":"postalcode"
},
  "geometry": {"coordinates":[-0.00758022700965,51.11335310573346],"type":"Point"}
}