{
  "type": "Feature",
  "properties": {
    "date:inception_lower": "1980-01-01",
    "date:inception_upper": "1980-01-01",
    "iso:country": "GB",
    "wof:name": "RH19 4AX",
    "wof:placetype": "postalcode"
  },
  "geometry": {"coordinates":[-0.00758,51.113353],"type":"Point"}
}
