{
  "type": "Feature",
  "properties": {
    "iso:country": "GB",
    "wof:name": "BS31 1GA",
    "wof:placetype": "postalcode"
  },
  "geometry": {"coordinates":[-2.497125,51.412787],"type":"Point"}
}
