{
  "type": "Feature",
  "properties": {
    "iso:country":"GB",
    "wof:name":"DY8 5TG",
    "wof:placetype":"postalcode"
},
  "geometry": {"coordinates":[-2.15818498541739,52.48508831163716],"type":"Point"}
}