{
  "type": "Feature",
  "properties": {
    "iso:country":"GB",
    "wof:name":"ST3 1AF",
    "wof:placetype":"postalcode"
},
  "geometry": {"coordinates":[-2.13102791868255,52.99681662261978],"type":"Point"}
}