{
  "type": "Feature",
  "properties": {
    "iso:country": "GB",
    "wof:name": "ST3 1AF",
    "wof:placetype": "postalcode"
  },
  "geometry": {"coordinates":[-2.131028,52.996817],"type":"Point"}
}
