{
  "type": "Feature",
  "properties": {
    "date:inception_lower": "1980-01-01",
    "date:inception_upper": "1980-01-01",
    "iso:country": "GB",
    "wof:name": "NE16 4PA",
    "wof:placetype": "postalcode"
  },
  "geometry": {"coordinates":[-1.676398,54.945549],"type":"Point"}
}
