{
  "type": "Feature",
  "properties": {
    "iso:country":"GB",
    "wof:name":"NE9 6LA",
    "wof:placetype":"postalcode"
},
  "geometry": {"coordinates":[-1.60673641245075,54.9267780210676],"type":"Point"}
}