{
  "type": "Feature",
  "properties": {
    "iso:country": "GB",
    "wof:name": "BA8 0PJ",
    "wof:placetype": "postalcode"
  },
  "geometry": {"coordinates":[-2.409273,50.977144],"type":"Point"}
}
