{
  "type": "Feature",
  "properties": {
    "iso:country":"GB",
    "wof:name":"BA8 0PJ",
    "wof:placetype":"postalcode"
},
  "geometry": {"coordinates":[-2.40927300216543,50.97714425347986],"type":"Point"}
}