{
  "type": "Feature",
  "properties": {
    "iso:country":"GB",
    "wof:name":"SW1X 9NR",
    "wof:placetype":"postalcode"
},
  "geometry": {"coordinates":[-0.16011272002307,51.49931368488051],"type":"Point"}
}