{
  "type": "Feature",
  "properties": {
    "iso:country": "GB",
    "wof:name": "SK2 7JT",
    "wof:placetype": "postalcode"
  },
  "geometry": {"coordinates":[-2.135684,53.387073],"type":"Point"}
}
