{
  "type": "Feature",
  "properties": {
    "iso:country":"GB",
    "wof:name":"SK2 7JT",
    "wof:placetype":"postalcode"
},
  "geometry": {"coordinates":[-2.13568359923059,53.38707259460661],"type":"Point"}
}