{
  "type": "Feature",
  "properties": {
    "iso:country":"GB",
    "wof:name":"NR13 4HE",
    "wof:placetype":"postalcode"
},
  "geometry": {"coordinates":[1.49141146587144,52.60322333404623],"type":"Point"}
}