{
  "type": "Feature",
  "properties": {
    "date:inception_lower":"1980-01-01",
    "date:inception_upper":"1980-01-31",
    "iso:country":"GB",
    "wof:name":"NR13 4HE",
    "wof:placetype":"postalcode"
},
  "geometry": {"coordinates":[1.491412,52.603223],"type":"Point"}
}