{
  "type": "Feature",
  "properties": {
    "date:inception_lower": "1980-01-01",
    "date:inception_upper": "1980-01-01",
    "iso:country": "GB",
    "wof:name": "EH11 3TN",
    "wof:placetype": "postalcode"
  },
  "geometry": {"coordinates":[-3.279761,55.924931],"type":"Point"}
}
