{
  "type": "Feature",
  "properties": {
    "iso:country":"GB",
    "wof:name":"EH11 3TN",
    "wof:placetype":"postalcode"
},
  "geometry": {"coordinates":[-3.27976105793875,55.92493108707502],"type":"Point"}
}