{
  "type": "Feature",
  "properties": {
    "iso:country":"GB",
    "wof:name":"FY7 8ND",
    "wof:placetype":"postalcode"
},
  "geometry": {"coordinates":[-3.04241359576569,53.90835068324951],"type":"Point"}
}