{
  "type": "Feature",
  "properties": {
    "iso:country": "GB",
    "wof:name": "EH54 5FD",
    "wof:placetype": "postalcode"
  },
  "geometry": {"coordinates":[-3.51061,55.908181],"type":"Point"}
}
