{
  "type": "Feature",
  "properties": {
    "iso:country": "GB",
    "wof:name": "B92 8SG",
    "wof:placetype": "postalcode"
  },
  "geometry": {"coordinates":[-1.786461,52.439558],"type":"Point"}
}
