{
  "type": "Feature",
  "properties": {
    "iso:country": "GB",
    "wof:name": "B62 9HH",
    "wof:placetype": "postalcode"
  },
  "geometry": {"coordinates":[-2.028687,52.472629],"type":"Point"}
}
