{
  "type": "Feature",
  "properties": {
    "date:inception_lower": "1980-01-01",
    "date:inception_upper": "1980-01-01",
    "iso:country": "GB",
    "wof:name": "B62 9HH",
    "wof:placetype": "postalcode"
  },
  "geometry": {"coordinates":[-2.028687,52.472629],"type":"Point"}
}
