{
  "type": "Feature",
  "properties": {
    "iso:country": "GB",
    "wof:name": "B62 9HH",
    "wof:placetype": "postalcode"
  },
  "geometry": {"coordinates":[-2.028554,52.472602],"type":"Point"}
}
