{
  "type": "Feature",
  "properties": {
    "date:inception_lower": "1980-01-01",
    "date:inception_upper": "1980-01-01",
    "iso:country": "GB",
    "wof:name": "DN14 8PE",
    "wof:placetype": "postalcode"
  },
  "geometry": {"coordinates":[-0.947559,53.685715],"type":"Point"}
}
