{
  "type": "Feature",
  "properties": {
    "date:inception_lower": "1980-01-01",
    "date:inception_upper": "1980-01-01",
    "iso:country": "GB",
    "wof:name": "CV31 3NY",
    "wof:placetype": "postalcode"
  },
  "geometry": {"coordinates":[-1.5503,52.283146],"type":"Point"}
}
