{
  "type": "Feature",
  "properties": {
    "iso:country":"GB",
    "wof:name":"SW6 7PB",
    "wof:placetype":"postalcode"
},
  "geometry": {"coordinates":[-0.21583227794119,51.48256736888538],"type":"Point"}
}