{
  "type": "Feature",
  "properties": {
    "date:inception_lower":"1980-01-01",
    "date:inception_upper":"1980-01-31",
    "iso:country":"GB",
    "wof:name":"PO11 9HU",
    "wof:placetype":"postalcode"
},
  "geometry": {"coordinates":[-0.973411,50.785854],"type":"Point"}
}