{
  "type": "Feature",
  "properties": {
    "iso:country":"GB",
    "wof:name":"NR28 9UF",
    "wof:placetype":"postalcode"
},
  "geometry": {"coordinates":[1.44843345362238,52.83353209095008],"type":"Point"}
}