{
  "type": "Feature",
  "properties": {
    "iso:country":"GB",
    "wof:name":"FY4 4XY",
    "wof:placetype":"postalcode"
},
  "geometry": {"coordinates":[-3.02515130633953,53.79454553914185],"type":"Point"}
}