{
  "type": "Feature",
  "properties": {
    "iso:country":"GB",
    "wof:name":"G72 0SB",
    "wof:placetype":"postalcode"
},
  "geometry": {"coordinates":[-4.09703305217095,55.78803983980869],"type":"Point"}
}