{
  "type": "Feature",
  "properties": {
    "iso:country":"GB",
    "wof:name":"FK10 4LU",
    "wof:placetype":"postalcode"
},
  "geometry": {"coordinates":[-3.7209431591764,56.06855612082312],"type":"Point"}
}