{
  "type": "Feature",
  "properties": {
    "date:inception_lower": "1980-01-01",
    "date:inception_upper": "1980-01-01",
    "iso:country": "GB",
    "wof:name": "FK10 4LU",
    "wof:placetype": "postalcode"
  },
  "geometry": {"coordinates":[-3.720943,56.068556],"type":"Point"}
}
