{
  "type": "Feature",
  "properties": {
    "iso:country":"GB",
    "wof:name":"DA13 0PL",
    "wof:placetype":"postalcode"
},
  "geometry": {"coordinates":[0.3602354110666,51.36672355466919],"type":"Point"}
}