{
  "type": "Feature",
  "properties": {
    "iso:country": "GB",
    "wof:name": "DA13 0PL",
    "wof:placetype": "postalcode"
  },
  "geometry": {"coordinates":[0.360235,51.366724],"type":"Point"}
}
