{
  "type": "Feature",
  "properties": {
    "iso:country":"GB",
    "wof:name":"YO7 2AH",
    "wof:placetype":"postalcode"
},
  "geometry": {"coordinates":[-1.27355720081637,54.22114659386713],"type":"Point"}
}