{
  "type": "Feature",
  "properties": {
    "iso:country": "GB",
    "wof:name": "YO7 2AH",
    "wof:placetype": "postalcode"
  },
  "geometry": {"coordinates":[-1.273566,54.221169],"type":"Point"}
}
