{
  "type": "Feature",
  "properties": {
    "date:inception_lower": "2001-06-01",
    "date:inception_upper": "2001-06-01",
    "iso:country": "GB",
    "wof:name": "YO7 2AH",
    "wof:placetype": "postalcode"
  },
  "geometry": {"coordinates":[-1.273566,54.221169],"type":"Point"}
}
