{
  "type": "Feature",
  "properties": {
    "date:inception_lower": "2002-06-01",
    "date:inception_upper": "2002-06-01",
    "iso:country": "GB",
    "wof:name": "CM7 1WR",
    "wof:placetype": "postalcode"
  },
  "geometry": {"coordinates":[0.548654,51.870537],"type":"Point"}
}
