{
  "type": "Feature",
  "properties": {
    "date:inception_lower": "2021-11-01",
    "date:inception_upper": "2021-11-01",
    "iso:country": "GB",
    "wof:name": "PL21 0XD",
    "wof:placetype": "postalcode"
  },
  "geometry": {"coordinates":[-3.89738,50.389604],"type":"Point"}
}
