{
  "type": "Feature",
  "properties": {
    "date:inception_lower":"1980-01-01",
    "date:inception_upper":"1980-01-31",
    "iso:country":"GB",
    "wof:name":"DD2 4TD",
    "wof:placetype":"postalcode"
},
  "geometry": {"coordinates":[-3.037382,56.477593],"type":"Point"}
}