{
  "type": "Feature",
  "properties": {
    "iso:country":"GB",
    "wof:name":"DD2 4TD",
    "wof:placetype":"postalcode"
},
  "geometry": {"coordinates":[-3.03738247660827,56.4775927980952],"type":"Point"}
}