{
  "type": "Feature",
  "properties": {
    "iso:country":"GB",
    "wof:name":"CR7 8HS",
    "wof:placetype":"postalcode"
},
  "geometry": {"coordinates":[-0.09741761460614,51.4087915989019],"type":"Point"}
}