{
  "type": "Feature",
  "properties": {
    "iso:country": "GB",
    "wof:name": "SO50 6QG",
    "wof:placetype": "postalcode"
  },
  "geometry": {"coordinates":[-1.333993,50.971317],"type":"Point"}
}
