{
  "type": "Feature",
  "properties": {
    "date:inception_lower":"1994-12-01",
    "date:inception_upper":"1994-12-31",
    "iso:country":"GB",
    "wof:name":"SO50 6QG",
    "wof:placetype":"postalcode"
},
  "geometry": {"coordinates":[-1.333993,50.971317],"type":"Point"}
}