{
  "type": "Feature",
  "properties": {
    "iso:country":"GB",
    "wof:name":"SO50 6QG",
    "wof:placetype":"postalcode"
},
  "geometry": {"coordinates":[-1.33400444526142,50.97133407727519],"type":"Point"}
}