{
  "type": "Feature",
  "properties": {
    "iso:country":"GB",
    "wof:name":"CA8 2JJ",
    "wof:placetype":"postalcode"
},
  "geometry": {"coordinates":[-2.68102650688213,54.9770683370801],"type":"Point"}
}