{
  "type": "Feature",
  "properties": {
    "date:inception_lower":"1980-01-01",
    "date:inception_upper":"1980-01-31",
    "iso:country":"GB",
    "wof:name":"CA8 2JJ",
    "wof:placetype":"postalcode"
},
  "geometry": {"coordinates":[-2.681026,54.977068],"type":"Point"}
}