{
  "type": "Feature",
  "properties": {
    "iso:country": "GB",
    "wof:name": "CA8 2JJ",
    "wof:placetype": "postalcode"
  },
  "geometry": {"coordinates":[-2.681026,54.977068],"type":"Point"}
}
