{
  "type": "Feature",
  "properties": {
    "iso:country":"GB",
    "wof:name":"NE19 1JG",
    "wof:placetype":"postalcode"
},
  "geometry": {"coordinates":[-2.2042146436484,55.24133068778971],"type":"Point"}
}