{
  "type": "Feature",
  "properties": {
    "iso:country": "GB",
    "wof:name": "EH14 5AG",
    "wof:placetype": "postalcode"
  },
  "geometry": {"coordinates":[-3.33181,55.890521],"type":"Point"}
}
