{
  "type": "Feature",
  "properties": {
    "date:inception_lower":"1980-01-01",
    "date:inception_upper":"1980-01-31",
    "iso:country":"GB",
    "wof:name":"B74 2PU",
    "wof:placetype":"postalcode"
},
  "geometry": {"coordinates":[-1.835395,52.572165],"type":"Point"}
}