{
  "type": "Feature",
  "properties": {
    "iso:country":"GB",
    "wof:name":"B74 2PU",
    "wof:placetype":"postalcode"
},
  "geometry": {"coordinates":[-1.83539466074182,52.57216536823392],"type":"Point"}
}