{
  "type": "Feature",
  "properties": {
    "iso:country": "GB",
    "wof:name": "PR1 9AN",
    "wof:placetype": "postalcode"
  },
  "geometry": {"coordinates":[-2.726864,53.742185],"type":"Point"}
}
