{
  "type": "Feature",
  "properties": {
    "date:inception_lower": "1980-01-01",
    "date:inception_upper": "1980-01-01",
    "iso:country": "GB",
    "wof:name": "TQ9 7TZ",
    "wof:placetype": "postalcode"
  },
  "geometry": {"coordinates":[-3.701407,50.38319],"type":"Point"}
}
