{
  "type": "Feature",
  "properties": {
    "iso:country": "GB",
    "wof:name": "TQ9 7TZ",
    "wof:placetype": "postalcode"
  },
  "geometry": {"coordinates":[-3.701407,50.38319],"type":"Point"}
}
