{
  "type": "Feature",
  "properties": {
    "iso:country":"GB",
    "wof:name":"TQ9 7TZ",
    "wof:placetype":"postalcode"
},
  "geometry": {"coordinates":[-3.70140712016339,50.38318962038885],"type":"Point"}
}