{
  "type": "Feature",
  "properties": {
    "iso:country": "GB",
    "wof:name": "ST10 4BG",
    "wof:placetype": "postalcode"
  },
  "geometry": {"coordinates":[-1.901357,52.976416],"type":"Point"}
}
