{
  "type": "Feature",
  "properties": {
    "iso:country":"GB",
    "wof:name":"LA14 5BS",
    "wof:placetype":"postalcode"
},
  "geometry": {"coordinates":[-3.22917469449613,54.12242783432028],"type":"Point"}
}