{
  "type": "Feature",
  "properties": {
    "date:inception_lower": "2003-03-01",
    "date:inception_upper": "2003-03-01",
    "iso:country": "GB",
    "wof:name": "NE8 3JA",
    "wof:placetype": "postalcode"
  },
  "geometry": {"coordinates":[-1.586284,54.959852],"type":"Point"}
}
