{
  "type": "Feature",
  "properties": {
    "iso:country":"GB",
    "wof:name":"EN6 5DA",
    "wof:placetype":"postalcode"
},
  "geometry": {"coordinates":[-0.17421106961616,51.69857067843253],"type":"Point"}
}