{
  "type": "Feature",
  "properties": {
    "date:inception_lower": "1980-01-01",
    "date:inception_upper": "1980-01-01",
    "iso:country": "GB",
    "wof:name": "EN6 5DA",
    "wof:placetype": "postalcode"
  },
  "geometry": {"coordinates":[-0.174232,51.69853],"type":"Point"}
}
