{
  "type": "Feature",
  "properties": {
    "iso:country":"GB",
    "wof:name":"LL53 8AX",
    "wof:placetype":"postalcode"
},
  "geometry": {"coordinates":[-4.62771586118812,52.88289010431149],"type":"Point"}
}