{
  "type": "Feature",
  "properties": {
    "iso:country":"GB",
    "wof:name":"KT17 1LF",
    "wof:placetype":"postalcode"
},
  "geometry": {"coordinates":[-0.2525313844986,51.34107409304865],"type":"Point"}
}