{
  "type": "Feature",
  "properties": {
    "iso:country":"GB",
    "wof:name":"DT9 3RQ",
    "wof:placetype":"postalcode"
},
  "geometry": {"coordinates":[-2.52094940000563,50.94190785427138],"type":"Point"}
}