{
  "type": "Feature",
  "properties": {
    "date:inception_lower": "1991-09-01",
    "date:inception_upper": "1991-09-01",
    "iso:country": "GB",
    "wof:name": "DT9 3RQ",
    "wof:placetype": "postalcode"
  },
  "geometry": {"coordinates":[-2.52095,50.941902],"type":"Point"}
}
