{
  "type": "Feature",
  "properties": {
    "iso:country": "GB",
    "wof:name": "DT9 3RQ",
    "wof:placetype": "postalcode"
  },
  "geometry": {"coordinates":[-2.520892,50.941875],"type":"Point"}
}
