{
  "type": "Feature",
  "properties": {
    "iso:country":"GB",
    "wof:name":"SA11 4NN",
    "wof:placetype":"postalcode"
},
  "geometry": {"coordinates":[-3.69085717334463,51.71063576639143],"type":"Point"}
}