{
  "type": "Feature",
  "properties": {
    "iso:country":"GB",
    "wof:name":"GL14 3JY",
    "wof:placetype":"postalcode"
},
  "geometry": {"coordinates":[-2.48389193804094,51.8208728988993],"type":"Point"}
}