{
  "type": "Feature",
  "properties": {
    "iso:country": "GB",
    "wof:name": "IP2 9DY",
    "wof:placetype": "postalcode"
  },
  "geometry": {"coordinates":[1.133434,52.039441],"type":"Point"}
}
