{
  "type": "Feature",
  "properties": {
    "date:inception_lower":"1980-01-01",
    "date:inception_upper":"1980-01-31",
    "iso:country":"GB",
    "wof:name":"PL16 0HT",
    "wof:placetype":"postalcode"
},
  "geometry": {"coordinates":[-4.21816,50.616695],"type":"Point"}
}