{
  "type": "Feature",
  "properties": {
    "iso:country":"GB",
    "wof:name":"G83 9NZ",
    "wof:placetype":"postalcode"
},
  "geometry": {"coordinates":[-4.57462866262774,55.98192363877575],"type":"Point"}
}