{
  "type": "Feature",
  "properties": {
    "iso:country": "GB",
    "wof:name": "G83 9NZ",
    "wof:placetype": "postalcode"
  },
  "geometry": {"coordinates":[-4.574629,55.981924],"type":"Point"}
}
