{
  "type": "Feature",
  "properties": {
    "iso:country": "GB",
    "wof:name": "BL5 2JF",
    "wof:placetype": "postalcode"
  },
  "geometry": {"coordinates":[-2.516874,53.535923],"type":"Point"}
}
