{
  "type": "Feature",
  "properties": {
    "date:inception_lower": "2004-06-01",
    "date:inception_upper": "2004-06-01",
    "iso:country": "GB",
    "wof:name": "BL5 2JF",
    "wof:placetype": "postalcode"
  },
  "geometry": {"coordinates":[-2.516874,53.535923],"type":"Point"}
}
