{
  "type": "Feature",
  "properties": {
    "iso:country":"GB",
    "wof:name":"SA2 7UT",
    "wof:placetype":"postalcode"
},
  "geometry": {"coordinates":[-4.04911518478266,51.62559034996653],"type":"Point"}
}