{
  "type": "Feature",
  "properties": {
    "iso:country":"GB",
    "wof:name":"RH10 5BP",
    "wof:placetype":"postalcode"
},
  "geometry": {"coordinates":[-0.18391332676129,51.10315825432917],"type":"Point"}
}