{
  "type": "Feature",
  "properties": {
    "iso:country":"GB",
    "wof:name":"CF37 3DS",
    "wof:placetype":"postalcode"
},
  "geometry": {"coordinates":[-3.35614928356114,51.63486937421427],"type":"Point"}
}