{
  "type": "Feature",
  "properties": {
    "date:inception_lower": "1994-10-01",
    "date:inception_upper": "1994-10-01",
    "iso:country": "GB",
    "wof:name": "DG1 1PX",
    "wof:placetype": "postalcode"
  },
  "geometry": {"coordinates":[-3.594655,55.074524],"type":"Point"}
}
