{
  "type": "Feature",
  "properties": {
    "iso:country": "GB",
    "wof:name": "HP14 3SG",
    "wof:placetype": "postalcode"
  },
  "geometry": {"coordinates":[-0.890302,51.653495],"type":"Point"}
}
