{
  "type": "Feature",
  "properties": {
    "date:inception_lower":"1980-01-01",
    "date:inception_upper":"1980-01-31",
    "iso:country":"GB",
    "wof:name":"TW16 6RR",
    "wof:placetype":"postalcode"
},
  "geometry": {"coordinates":[-0.413969,51.405904],"type":"Point"}
}