{
  "type": "Feature",
  "properties": {
    "iso:country":"GB",
    "wof:name":"TW16 6RR",
    "wof:placetype":"postalcode"
},
  "geometry": {"coordinates":[-0.4139694530269,51.40590446356585],"type":"Point"}
}