{
  "type": "Feature",
  "properties": {
    "iso:country":"GB",
    "wof:name":"BL9 9JG",
    "wof:placetype":"postalcode"
},
  "geometry": {"coordinates":[-2.29145279864117,53.58319152086694],"type":"Point"}
}