{
  "type": "Feature",
  "properties": {
    "iso:country":"GB",
    "wof:name":"CF24 5DZ",
    "wof:placetype":"postalcode"
},
  "geometry": {"coordinates":[-3.15847750601542,51.47193318963564],"type":"Point"}
}