{
  "type": "Feature",
  "properties": {
    "iso:country": "GB",
    "wof:name": "TR15 2EL",
    "wof:placetype": "postalcode"
  },
  "geometry": {"coordinates":[-5.222244,50.234964],"type":"Point"}
}
