{
  "type": "Feature",
  "properties": {
    "iso:country":"GB",
    "wof:name":"CR8 3AJ",
    "wof:placetype":"postalcode"
},
  "geometry": {"coordinates":[-0.12481366339713,51.33731841698297],"type":"Point"}
}