{
  "type": "Feature",
  "properties": {
    "iso:country":"GB",
    "wof:name":"YO12 7SB",
    "wof:placetype":"postalcode"
},
  "geometry": {"coordinates":[-0.41731001420606,54.27952973069331],"type":"Point"}
}