{
  "type": "Feature",
  "properties": {
    "date:inception_lower": "1980-01-01",
    "date:inception_upper": "1980-01-01",
    "iso:country": "GB",
    "wof:name": "YO12 7SB",
    "wof:placetype": "postalcode"
  },
  "geometry": {"coordinates":[-0.41731,54.27953],"type":"Point"}
}
