{
  "type": "Feature",
  "properties": {
    "iso:country":"GB",
    "wof:name":"GU47 9BQ",
    "wof:placetype":"postalcode"
},
  "geometry": {"coordinates":[-0.79645933181156,51.34379762833678],"type":"Point"}
}