{
  "type": "Feature",
  "properties": {
    "iso:country": "GB",
    "wof:name": "GU47 9BQ",
    "wof:placetype": "postalcode"
  },
  "geometry": {"coordinates":[-0.796459,51.343798],"type":"Point"}
}
