{
  "type": "Feature",
  "properties": {
    "date:inception_lower":"1980-01-01",
    "date:inception_upper":"1980-01-31",
    "iso:country":"GB",
    "wof:name":"YO14 9EA",
    "wof:placetype":"postalcode"
},
  "geometry": {"coordinates":[-0.289299,54.210493],"type":"Point"}
}