{
  "type": "Feature",
  "properties": {
    "iso:country":"GB",
    "wof:name":"YO14 9EA",
    "wof:placetype":"postalcode"
},
  "geometry": {"coordinates":[-0.2892993933461,54.21049334684916],"type":"Point"}
}