{
  "type": "Feature",
  "properties": {
    "iso:country": "GB",
    "wof:name": "M28 7XT",
    "wof:placetype": "postalcode"
  },
  "geometry": {"coordinates":[-2.410457,53.510818],"type":"Point"}
}
