{
  "type": "Feature",
  "properties": {
    "iso:country":"GB",
    "wof:name":"M28 7XT",
    "wof:placetype":"postalcode"
},
  "geometry": {"coordinates":[-2.410456963814,53.51081812868801],"type":"Point"}
}