{
  "type": "Feature",
  "properties": {
    "date:inception_lower": "1980-01-01",
    "date:inception_upper": "1980-01-01",
    "iso:country": "GB",
    "wof:name": "SP4 7EQ",
    "wof:placetype": "postalcode"
  },
  "geometry": {"coordinates":[-1.770908,51.17694],"type":"Point"}
}
