{
  "type": "Feature",
  "properties": {
    "iso:country":"GB",
    "wof:name":"N17 6YQ",
    "wof:placetype":"postalcode"
},
  "geometry": {"coordinates":[-0.07658619494669,51.5924580898212],"type":"Point"}
}