{
  "type": "Feature",
  "properties": {
    "iso:country":"GB",
    "wof:name":"SP5 4NE",
    "wof:placetype":"postalcode"
},
  "geometry": {"coordinates":[-1.83917085157298,51.03332379299389],"type":"Point"}
}