{
  "type": "Feature",
  "properties": {
    "iso:country":"GB",
    "wof:name":"CH48 1PL",
    "wof:placetype":"postalcode"
},
  "geometry": {"coordinates":[-3.14654002518017,53.37432489767928],"type":"Point"}
}