{
  "type": "Feature",
  "properties": {
    "iso:country":"GB",
    "wof:name":"LN6 9BX",
    "wof:placetype":"postalcode"
},
  "geometry": {"coordinates":[-0.64948426364379,53.20327629657912],"type":"Point"}
}