{
  "type": "Feature",
  "properties": {
    "date:inception_lower":"1992-08-01",
    "date:inception_upper":"1992-08-31",
    "iso:country":"GB",
    "wof:name":"SE23 2LX",
    "wof:placetype":"postalcode"
},
  "geometry": {"coordinates":[-0.05322,51.436788],"type":"Point"}
}