{
  "type": "Feature",
  "properties": {
    "iso:country": "GB",
    "wof:name": "FK2 0DS",
    "wof:placetype": "postalcode"
  },
  "geometry": {"coordinates":[-3.739796,55.981009],"type":"Point"}
}
