{
  "type": "Feature",
  "properties": {
    "iso:country":"GB",
    "wof:name":"FK2 0DS",
    "wof:placetype":"postalcode"
},
  "geometry": {"coordinates":[-3.73979600422951,55.98100883622305],"type":"Point"}
}