{
  "type": "Feature",
  "properties": {
    "iso:country":"GB",
    "wof:name":"LS17 7QH",
    "wof:placetype":"postalcode"
},
  "geometry": {"coordinates":[-1.5552256182758,53.86123724993994],"type":"Point"}
}