{
  "type": "Feature",
  "properties": {
    "iso:country": "GB",
    "wof:name": "SP11 6LS",
    "wof:placetype": "postalcode"
  },
  "geometry": {"coordinates":[-1.433625,51.211384],"type":"Point"}
}
