{
  "type": "Feature",
  "properties": {
    "date:inception_lower":"1980-01-01",
    "date:inception_upper":"1980-01-31",
    "iso:country":"GB",
    "wof:name":"SP11 6LS",
    "wof:placetype":"postalcode"
},
  "geometry": {"coordinates":[-1.433625,51.211384],"type":"Point"}
}