{
  "type": "Feature",
  "properties": {
    "iso:country":"GB",
    "wof:name":"SP11 6LS",
    "wof:placetype":"postalcode"
},
  "geometry": {"coordinates":[-1.43362480014083,51.21138424309646],"type":"Point"}
}