{
  "type": "Feature",
  "properties": {
    "date:inception_lower":"1993-08-01",
    "date:inception_upper":"1993-08-31",
    "iso:country":"GB",
    "wof:name":"NN6 6DJ",
    "wof:placetype":"postalcode"
},
  "geometry": {"coordinates":[-0.984563,52.379104],"type":"Point"}
}