{
  "type": "Feature",
  "properties": {
    "iso:country": "GB",
    "wof:name": "HG4 2TS",
    "wof:placetype": "postalcode"
  },
  "geometry": {"coordinates":[-1.550931,54.139877],"type":"Point"}
}
