{
  "type": "Feature",
  "properties": {
    "iso:country":"GB",
    "wof:name":"GL11 4NU",
    "wof:placetype":"postalcode"
},
  "geometry": {"coordinates":[-2.34448669448836,51.6769847765773],"type":"Point"}
}