{
  "type": "Feature",
  "properties": {
    "iso:country": "GB",
    "wof:name": "GL11 4NU",
    "wof:placetype": "postalcode"
  },
  "geometry": {"coordinates":[-2.344487,51.676985],"type":"Point"}
}
