{
  "type": "Feature",
  "properties": {
    "iso:country":"GB",
    "wof:name":"AL8 6LH",
    "wof:placetype":"postalcode"
},
  "geometry": {"coordinates":[-0.22072280788948,51.7947264201693],"type":"Point"}
}