{
  "type": "Feature",
  "properties": {
    "iso:country":"GB",
    "wof:name":"TR11 3NG",
    "wof:placetype":"postalcode"
},
  "geometry": {"coordinates":[-5.07096945879087,50.15140896013725],"type":"Point"}
}