{
  "type": "Feature",
  "properties": {
    "iso:country":"GB",
    "wof:name":"YO15 3DG",
    "wof:placetype":"postalcode"
},
  "geometry": {"coordinates":[-0.19926410342266,54.07898718985926],"type":"Point"}
}