{
  "type": "Feature",
  "properties": {
    "iso:country": "GB",
    "wof:name": "ST1 4BX",
    "wof:placetype": "postalcode"
  },
  "geometry": {"coordinates":[-2.192626,53.021309],"type":"Point"}
}
