{
  "type": "Feature",
  "properties": {
    "iso:country":"GB",
    "wof:name":"ST1 4BX",
    "wof:placetype":"postalcode"
},
  "geometry": {"coordinates":[-2.19262651797686,53.0213090353696],"type":"Point"}
}