{
  "type": "Feature",
  "properties": {
    "iso:country":"GB",
    "wof:name":"GU31 4DB",
    "wof:placetype":"postalcode"
},
  "geometry": {"coordinates":[-0.9183178367132,51.01098492426551],"type":"Point"}
}