{
  "type": "Feature",
  "properties": {
    "iso:country":"GB",
    "wof:name":"LE65 2GU",
    "wof:placetype":"postalcode"
},
  "geometry": {"coordinates":[-1.48079237296531,52.74774656024783],"type":"Point"}
}