{
  "type": "Feature",
  "properties": {
    "iso:country": "GB",
    "wof:name": "LE65 2GU",
    "wof:placetype": "postalcode"
  },
  "geometry": {"coordinates":[-1.480792,52.747747],"type":"Point"}
}
