{
  "type": "Feature",
  "properties": {
    "iso:country": "GB",
    "wof:name": "ST1 2NA",
    "wof:placetype": "postalcode"
  },
  "geometry": {"coordinates":[-2.165769,53.034582],"type":"Point"}
}
