{
  "type": "Feature",
  "properties": {
    "iso:country":"GB",
    "wof:name":"DA5 3NX",
    "wof:placetype":"postalcode"
},
  "geometry": {"coordinates":[0.13532678878427,51.43992598139699],"type":"Point"}
}