{
  "type": "Feature",
  "properties": {
    "iso:country": "GB",
    "wof:name": "IP26 5HB",
    "wof:placetype": "postalcode"
  },
  "geometry": {"coordinates":[0.662802,52.519923],"type":"Point"}
}
