{
  "type": "Feature",
  "properties": {
    "date:inception_lower":"2001-12-01",
    "date:inception_upper":"2001-12-31",
    "iso:country":"GB",
    "wof:name":"IP26 5HB",
    "wof:placetype":"postalcode"
},
  "geometry": {"coordinates":[0.662802,52.519923],"type":"Point"}
}