{
  "type": "Feature",
  "properties": {
    "date:inception_lower":"1980-01-01",
    "date:inception_upper":"1980-01-31",
    "iso:country":"GB",
    "wof:name":"PH26 3HU",
    "wof:placetype":"postalcode"
},
  "geometry": {"coordinates":[-3.598911,57.334474],"type":"Point"}
}