{
  "type": "Feature",
  "properties": {
    "iso:country": "GB",
    "wof:name": "IG11 0DW",
    "wof:placetype": "postalcode"
  },
  "geometry": {"coordinates":[0.096422,51.520404],"type":"Point"}
}
