{
  "type": "Feature",
  "properties": {
    "iso:country":"GB",
    "wof:name":"PH22 1TF",
    "wof:placetype":"postalcode"
},
  "geometry": {"coordinates":[-3.82942702151673,57.20117086311826],"type":"Point"}
}