{
  "type": "Feature",
  "properties": {
    "iso:country": "GB",
    "wof:name": "PH22 1TF",
    "wof:placetype": "postalcode"
  },
  "geometry": {"coordinates":[-3.829427,57.201171],"type":"Point"}
}
