{
  "type": "Feature",
  "properties": {
    "iso:country": "GB",
    "wof:name": "OL16 4PW",
    "wof:placetype": "postalcode"
  },
  "geometry": {"coordinates":[-2.141187,53.600209],"type":"Point"}
}
