{
  "type": "Feature",
  "properties": {
    "iso:country":"GB",
    "wof:name":"E2 6GT",
    "wof:placetype":"postalcode"
},
  "geometry": {"coordinates":[-0.06217815494081,51.53068517581336],"type":"Point"}
}