{
  "type": "Feature",
  "properties": {
    "iso:country":"GB",
    "wof:name":"M1 2DP",
    "wof:placetype":"postalcode"
},
  "geometry": {"coordinates":[-2.23034954015072,53.47960798672821],"type":"Point"}
}