{
  "type": "Feature",
  "properties": {
    "iso:country": "GB",
    "wof:name": "M1 2DP",
    "wof:placetype": "postalcode"
  },
  "geometry": {"coordinates":[-2.230349,53.479608],"type":"Point"}
}
