{
  "type": "Feature",
  "properties": {
    "date:inception_lower":"2004-02-01",
    "date:inception_upper":"2004-02-29",
    "iso:country":"GB",
    "wof:name":"M1 2DP",
    "wof:placetype":"postalcode"
},
  "geometry": {"coordinates":[-2.230349,53.479608],"type":"Point"}
}