{
  "type": "Feature",
  "properties": {
    "iso:country":"GB",
    "wof:name":"BB7 4PX",
    "wof:placetype":"postalcode"
},
  "geometry": {"coordinates":[-2.38328977276499,53.88292863603802],"type":"Point"}
}