{
  "type": "Feature",
  "properties": {
    "iso:country": "GB",
    "wof:name": "CF63 1LS",
    "wof:placetype": "postalcode"
  },
  "geometry": {"coordinates":[-3.249526,51.417487],"type":"Point"}
}
