{
  "type": "Feature",
  "properties": {
    "iso:country": "GB",
    "wof:name": "AB15 8PR",
    "wof:placetype": "postalcode"
  },
  "geometry": {"coordinates":[-2.19769,57.153961],"type":"Point"}
}
