{
  "type": "Feature",
  "properties": {
    "iso:country":"GB",
    "wof:name":"CR4 3FG",
    "wof:placetype":"postalcode"
},
  "geometry": {"coordinates":[-0.16483852604191,51.4074297929069],"type":"Point"}
}