{
  "type": "Feature",
  "properties": {
    "iso:country": "GB",
    "wof:name": "G67 3NG",
    "wof:placetype": "postalcode"
  },
  "geometry": {"coordinates":[-3.947156,55.962764],"type":"Point"}
}
