{
  "type": "Feature",
  "properties": {
    "iso:country":"GB",
    "wof:name":"IP1 6LY",
    "wof:placetype":"postalcode"
},
  "geometry": {"coordinates":[1.133142292836,52.08653411729186],"type":"Point"}
}