{
  "type": "Feature",
  "properties": {
    "iso:country": "GB",
    "wof:name": "HG3 1RP",
    "wof:placetype": "postalcode"
  },
  "geometry": {"coordinates":[-1.708824,53.983888],"type":"Point"}
}
