{
  "type": "Feature",
  "properties": {
    "date:inception_lower":"2003-07-01",
    "date:inception_upper":"2003-07-31",
    "iso:country":"GB",
    "wof:name":"HG3 1RP",
    "wof:placetype":"postalcode"
},
  "geometry": {"coordinates":[-1.708824,53.983888],"type":"Point"}
}