{
  "type": "Feature",
  "properties": {
    "iso:country":"GB",
    "wof:name":"W1S 2QG",
    "wof:placetype":"postalcode"
},
  "geometry": {"coordinates":[-0.14168074399369,51.51324023105738],"type":"Point"}
}