{
  "type": "Feature",
  "properties": {
    "date:inception_lower": "2022-10-01",
    "date:inception_upper": "2022-10-01",
    "iso:country": "GB",
    "wof:name": "S64 0FL",
    "wof:placetype": "postalcode"
  },
  "geometry": {"coordinates":[-1.262495,53.495796],"type":"Point"}
}
