{
  "type": "Feature",
  "properties": {
    "iso:country":"GB",
    "wof:name":"CB23 8DN",
    "wof:placetype":"postalcode"
},
  "geometry": {"coordinates":[0.00102845407192,52.26372557553702],"type":"Point"}
}