{
  "type": "Feature",
  "properties": {
    "iso:country":"GB",
    "wof:name":"HU12 8GA",
    "wof:placetype":"postalcode"
},
  "geometry": {"coordinates":[-0.23974129220207,53.73726400696641],"type":"Point"}
}