{
  "type": "Feature",
  "properties": {
    "iso:country": "GB",
    "wof:name": "HU12 8GA",
    "wof:placetype": "postalcode"
  },
  "geometry": {"coordinates":[-0.239741,53.737264],"type":"Point"}
}
