{
  "type": "Feature",
  "properties": {
    "date:inception_lower": "2001-12-01",
    "date:inception_upper": "2001-12-01",
    "iso:country": "GB",
    "wof:name": "HU12 8GA",
    "wof:placetype": "postalcode"
  },
  "geometry": {"coordinates":[-0.239741,53.737264],"type":"Point"}
}
