{
  "type": "Feature",
  "properties": {
    "date:inception_lower": "2013-09-01",
    "date:inception_upper": "2013-09-01",
    "iso:country": "GB",
    "wof:name": "G53 7ZU",
    "wof:placetype": "postalcode"
  },
  "geometry": {"coordinates":[-4.362256,55.810083],"type":"Point"}
}
