{
  "type": "Feature",
  "properties": {
    "iso:country":"GB",
    "wof:name":"G53 7ZU",
    "wof:placetype":"postalcode"
},
  "geometry": {"coordinates":[-4.36225654815574,55.81008301476373],"type":"Point"}
}