{
  "type": "Feature",
  "properties": {
    "iso:country": "GB",
    "wof:name": "G31 2NH",
    "wof:placetype": "postalcode"
  },
  "geometry": {"coordinates":[-4.226334,55.860514],"type":"Point"}
}
