{
  "type": "Feature",
  "properties": {
    "iso:country":"GB",
    "wof:name":"G31 2NH",
    "wof:placetype":"postalcode"
},
  "geometry": {"coordinates":[-4.22633360018384,55.86051389330412],"type":"Point"}
}