{
  "type": "Feature",
  "properties": {
    "iso:country":"GB",
    "wof:name":"SW17 8TE",
    "wof:placetype":"postalcode"
},
  "geometry": {"coordinates":[-0.16121529589889,51.42641935943144],"type":"Point"}
}