{
  "type": "Feature",
  "properties": {
    "iso:country":"GB",
    "wof:name":"CW11 3NH",
    "wof:placetype":"postalcode"
},
  "geometry": {"coordinates":[-2.43725800942827,53.14739820423433],"type":"Point"}
}