{
  "type": "Feature",
  "properties": {
    "iso:country": "GB",
    "wof:name": "CW11 3NH",
    "wof:placetype": "postalcode"
  },
  "geometry": {"coordinates":[-2.437258,53.147398],"type":"Point"}
}
