{
  "type": "Feature",
  "properties": {
    "date:inception_lower": "2018-06-01",
    "date:inception_upper": "2018-06-01",
    "iso:country": "GB",
    "wof:name": "CF32 9FB",
    "wof:placetype": "postalcode"
  },
  "geometry": {"coordinates":[-3.586557,51.54797],"type":"Point"}
}
