{
  "type": "Feature",
  "properties": {
    "iso:country":"GB",
    "wof:name":"RG24 8SF",
    "wof:placetype":"postalcode"
},
  "geometry": {"coordinates":[-1.05723522277339,51.27530198676708],"type":"Point"}
}