{
  "type": "Feature",
  "properties": {
    "date:inception_lower":"1980-01-01",
    "date:inception_upper":"1980-01-31",
    "iso:country":"GB",
    "wof:name":"LS23 6HF",
    "wof:placetype":"postalcode"
},
  "geometry": {"coordinates":[-1.349723,53.896153],"type":"Point"}
}