{
  "type": "Feature",
  "properties": {
    "iso:country": "GB",
    "wof:name": "LS23 6HF",
    "wof:placetype": "postalcode"
  },
  "geometry": {"coordinates":[-1.349723,53.896153],"type":"Point"}
}
