{
  "type": "Feature",
  "properties": {
    "iso:country":"GB",
    "wof:name":"LS23 6HF",
    "wof:placetype":"postalcode"
},
  "geometry": {"coordinates":[-1.34972256696932,53.89615333975065],"type":"Point"}
}