{
  "type": "Feature",
  "properties": {
    "iso:country":"GB",
    "wof:name":"IP31 3NN",
    "wof:placetype":"postalcode"
},
  "geometry": {"coordinates":[0.89642988923852,52.2604877540608],"type":"Point"}
}