{
  "type": "Feature",
  "properties": {
    "date:inception_lower": "1991-01-01",
    "date:inception_upper": "1991-01-01",
    "iso:country": "GB",
    "wof:name": "CT15 7QD",
    "wof:placetype": "postalcode"
  },
  "geometry": {"coordinates":[1.23128,51.188933],"type":"Point"}
}
