{
  "type": "Feature",
  "properties": {
    "iso:country":"GB",
    "wof:name":"CT15 7QD",
    "wof:placetype":"postalcode"
},
  "geometry": {"coordinates":[1.23134743405347,51.1890954680816],"type":"Point"}
}