{
  "type": "Feature",
  "properties": {
    "iso:country":"GB",
    "wof:name":"LN6 0RJ",
    "wof:placetype":"postalcode"
},
  "geometry": {"coordinates":[-0.60838532524657,53.2130066301413],"type":"Point"}
}