{
  "type": "Feature",
  "properties": {
    "iso:country": "GB",
    "wof:name": "LN6 0RJ",
    "wof:placetype": "postalcode"
  },
  "geometry": {"coordinates":[-0.608385,53.213007],"type":"Point"}
}
