{
  "type": "Feature",
  "properties": {
    "date:inception_lower": "1994-05-01",
    "date:inception_upper": "1994-05-01",
    "iso:country": "GB",
    "wof:name": "LN6 0RJ",
    "wof:placetype": "postalcode"
  },
  "geometry": {"coordinates":[-0.608385,53.213007],"type":"Point"}
}
