{
  "type": "Feature",
  "properties": {
    "iso:country":"GB",
    "wof:name":"TW9 3PP",
    "wof:placetype":"postalcode"
},
  "geometry": {"coordinates":[-0.28531009343181,51.4779116922741],"type":"Point"}
}