{
  "type": "Feature",
  "properties": {
    "iso:country": "GB",
    "wof:name": "TW9 3PP",
    "wof:placetype": "postalcode"
  },
  "geometry": {"coordinates":[-0.28531,51.477912],"type":"Point"}
}
