{
  "type": "Feature",
  "properties": {
    "iso:country":"GB",
    "wof:name":"KA22 8DR",
    "wof:placetype":"postalcode"
},
  "geometry": {"coordinates":[-4.81052299886006,55.6398352197893],"type":"Point"}
}