{
  "type": "Feature",
  "properties": {
    "iso:country":"GB",
    "wof:name":"IV22 2JN",
    "wof:placetype":"postalcode"
},
  "geometry": {"coordinates":[-5.62300256669319,57.8579754741748],"type":"Point"}
}