{
  "type": "Feature",
  "properties": {
    "iso:country": "GB",
    "wof:name": "HP11 1DN",
    "wof:placetype": "postalcode"
  },
  "geometry": {"coordinates":[-0.737906,51.619352],"type":"Point"}
}
