{
  "type": "Feature",
  "properties": {
    "date:inception_lower":"1981-06-01",
    "date:inception_upper":"1981-06-30",
    "iso:country":"GB",
    "wof:name":"HP11 1DN",
    "wof:placetype":"postalcode"
},
  "geometry": {"coordinates":[-0.737906,51.619352],"type":"Point"}
}