{
  "type": "Feature",
  "properties": {
    "iso:country":"GB",
    "wof:name":"TS6 9DW",
    "wof:placetype":"postalcode"
},
  "geometry": {"coordinates":[-1.15307839857935,54.56106292453942],"type":"Point"}
}