{
  "type": "Feature",
  "properties": {
    "iso:country": "GB",
    "wof:name": "TS6 9DW",
    "wof:placetype": "postalcode"
  },
  "geometry": {"coordinates":[-1.153078,54.561063],"type":"Point"}
}
