{
  "type": "Feature",
  "properties": {
    "iso:country":"GB",
    "wof:name":"KT23 4PA",
    "wof:placetype":"postalcode"
},
  "geometry": {"coordinates":[-0.37101759473293,51.27645275466156],"type":"Point"}
}