{
  "type": "Feature",
  "properties": {
    "iso:country": "GB",
    "wof:name": "RM11 1EF",
    "wof:placetype": "postalcode"
  },
  "geometry": {"coordinates":[0.195507,51.569232],"type":"Point"}
}
