{
  "type": "Feature",
  "properties": {
    "iso:country":"GB",
    "wof:name":"CM5 9LL",
    "wof:placetype":"postalcode"
},
  "geometry": {"coordinates":[0.19263576520968,51.70131510280699],"type":"Point"}
}