{
  "type": "Feature",
  "properties": {
    "iso:country":"GB",
    "wof:name":"SW19 2QJ",
    "wof:placetype":"postalcode"
},
  "geometry": {"coordinates":[-0.17723885887039,51.41089663317298],"type":"Point"}
}