{
  "type": "Feature",
  "properties": {
    "iso:country":"GB",
    "wof:name":"DH2 2NU",
    "wof:placetype":"postalcode"
},
  "geometry": {"coordinates":[-1.61163544672377,54.85873089278493],"type":"Point"}
}