{
  "type": "Feature",
  "properties": {
    "iso:country": "GB",
    "wof:name": "YO8 3JX",
    "wof:placetype": "postalcode"
  },
  "geometry": {"coordinates":[-1.067784,53.785898],"type":"Point"}
}
