{
  "type": "Feature",
  "properties": {
    "iso:country":"GB",
    "wof:name":"YO8 3JX",
    "wof:placetype":"postalcode"
},
  "geometry": {"coordinates":[-1.06778434280798,53.78589751886013],"type":"Point"}
}