{
  "type": "Feature",
  "properties": {
    "iso:country":"GB",
    "wof:name":"OX18 2TD",
    "wof:placetype":"postalcode"
},
  "geometry": {"coordinates":[-1.5905091040122,51.71249097666587],"type":"Point"}
}