{
  "type": "Feature",
  "properties": {
    "date:inception_lower": "1995-07-01",
    "date:inception_upper": "1995-07-01",
    "iso:country": "GB",
    "wof:name": "OX18 2TD",
    "wof:placetype": "postalcode"
  },
  "geometry": {"coordinates":[-1.590509,51.712491],"type":"Point"}
}
