{
  "type": "Feature",
  "properties": {
    "iso:country": "GB",
    "wof:name": "OX18 2TD",
    "wof:placetype": "postalcode"
  },
  "geometry": {"coordinates":[-1.590509,51.712491],"type":"Point"}
}
