{
  "type": "Feature",
  "properties": {
    "iso:country":"GB",
    "wof:name":"OL3 6BJ",
    "wof:placetype":"postalcode"
},
  "geometry": {"coordinates":[-2.00341790599831,53.54906793720717],"type":"Point"}
}