{
  "type": "Feature",
  "properties": {
    "iso:country":"GB",
    "wof:name":"G84 7SA",
    "wof:placetype":"postalcode"
},
  "geometry": {"coordinates":[-4.72536627725419,56.00767809852199],"type":"Point"}
}