{
  "type": "Feature",
  "properties": {
    "date:inception_lower": "1980-01-01",
    "date:inception_upper": "1980-01-01",
    "iso:country": "GB",
    "wof:name": "G20 7NP",
    "wof:placetype": "postalcode"
  },
  "geometry": {"coordinates":[-4.266035,55.873782],"type":"Point"}
}
