{
  "type": "Feature",
  "properties": {
    "date:inception_lower": "2020-12-01",
    "date:inception_upper": "2020-12-01",
    "iso:country": "GB",
    "wof:name": "CT6 5FJ",
    "wof:placetype": "postalcode"
  },
  "geometry": {"coordinates":[1.121415,51.355441],"type":"Point"}
}
