{
  "type": "Feature",
  "properties": {
    "iso:country":"GB",
    "wof:name":"CW8 4JX",
    "wof:placetype":"postalcode"
},
  "geometry": {"coordinates":[-2.53984479035464,53.27277761471608],"type":"Point"}
}