{
  "type": "Feature",
  "properties": {
    "date:inception_lower": "1993-08-01",
    "date:inception_upper": "1993-08-01",
    "iso:country": "GB",
    "wof:name": "PE3 8YF",
    "wof:placetype": "postalcode"
  },
  "geometry": {"coordinates":[-0.267673,52.597984],"type":"Point"}
}
