{
  "type": "Feature",
  "properties": {
    "iso:country":"GB",
    "wof:name":"PE3 8YF",
    "wof:placetype":"postalcode"
},
  "geometry": {"coordinates":[-0.26906373763753,52.59826392551959],"type":"Point"}
}