{
  "type": "Feature",
  "properties": {
    "iso:country": "GB",
    "wof:name": "YO18 8JW",
    "wof:placetype": "postalcode"
  },
  "geometry": {"coordinates":[-0.760825,54.286862],"type":"Point"}
}
