{
  "type": "Feature",
  "properties": {
    "iso:country":"GB",
    "wof:name":"B60 1DF",
    "wof:placetype":"postalcode"
},
  "geometry": {"coordinates":[-2.04419936799091,52.36031430866187],"type":"Point"}
}