{
  "type": "Feature",
  "properties": {
    "date:inception_lower": "2021-08-01",
    "date:inception_upper": "2021-08-01",
    "iso:country": "GB",
    "wof:name": "L31 1FP",
    "wof:placetype": "postalcode"
  },
  "geometry": {"coordinates":[-2.909677,53.513299],"type":"Point"}
}
