{
  "type": "Feature",
  "properties": {
    "iso:country":"GB",
    "wof:name":"WA8 9RJ",
    "wof:placetype":"postalcode"
},
  "geometry": {"coordinates":[-2.72759534083821,53.38622576039944],"type":"Point"}
}