{
  "type": "Feature",
  "properties": {
    "date:inception_lower": "1980-01-01",
    "date:inception_upper": "1980-01-01",
    "iso:country": "GB",
    "wof:name": "GL19 3NZ",
    "wof:placetype": "postalcode"
  },
  "geometry": {"coordinates":[-2.305306,51.968913],"type":"Point"}
}
