{
  "type": "Feature",
  "properties": {
    "iso:country": "GB",
    "wof:name": "GL19 3NZ",
    "wof:placetype": "postalcode"
  },
  "geometry": {"coordinates":[-2.305306,51.968913],"type":"Point"}
}
