{
  "type": "Feature",
  "properties": {
    "iso:country":"GB",
    "wof:name":"NP12 1EE",
    "wof:placetype":"postalcode"
},
  "geometry": {"coordinates":[-3.19796552720738,51.66215360464067],"type":"Point"}
}