{
  "type": "Feature",
  "properties": {
    "iso:country":"GB",
    "wof:name":"EH6 7BY",
    "wof:placetype":"postalcode"
},
  "geometry": {"coordinates":[-3.16707569583819,55.97699795269033],"type":"Point"}
}