{
  "type": "Feature",
  "properties": {
    "iso:country":"GB",
    "wof:name":"SE28 8HL",
    "wof:placetype":"postalcode"
},
  "geometry": {"coordinates":[0.11627738331029,51.5046874601935],"type":"Point"}
}