{
  "type": "Feature",
  "properties": {
    "iso:country":"GB",
    "wof:name":"CF15 8RA",
    "wof:placetype":"postalcode"
},
  "geometry": {"coordinates":[-3.25941175966334,51.5222453536048],"type":"Point"}
}