{
  "type": "Feature",
  "properties": {
    "iso:country":"GB",
    "wof:name":"DD3 8PQ",
    "wof:placetype":"postalcode"
},
  "geometry": {"coordinates":[-2.99853656040353,56.48519775496462],"type":"Point"}
}