{
  "type": "Feature",
  "properties": {
    "iso:country":"GB",
    "wof:name":"B28 8NG",
    "wof:placetype":"postalcode"
},
  "geometry": {"coordinates":[-1.8465736517502,52.43804164339437],"type":"Point"}
}