{
  "type": "Feature",
  "properties": {
    "iso:country":"GB",
    "wof:name":"M33 3PU",
    "wof:placetype":"postalcode"
},
  "geometry": {"coordinates":[-2.30785674996229,53.40854976893324],"type":"Point"}
}