{
  "type": "Feature",
  "properties": {
    "iso:country":"GB",
    "wof:name":"BH6 5BP",
    "wof:placetype":"postalcode"
},
  "geometry": {"coordinates":[-1.81092913953731,50.73205320125452],"type":"Point"}
}