{
  "type": "Feature",
  "properties": {
    "iso:country":"GB",
    "wof:name":"TR2 4LH",
    "wof:placetype":"postalcode"
},
  "geometry": {"coordinates":[-4.95690544503917,50.29095213450073],"type":"Point"}
}