{
  "type": "Feature",
  "properties": {
    "date:inception_lower": "2012-02-01",
    "date:inception_upper": "2012-02-01",
    "iso:country": "GB",
    "wof:name": "CR0 4BW",
    "wof:placetype": "postalcode"
  },
  "geometry": {"coordinates":[-0.116051,51.372879],"type":"Point"}
}
