{
  "type": "Feature",
  "properties": {
    "date:inception_lower":"2012-02-01",
    "date:inception_upper":"2012-02-29",
    "iso:country":"GB",
    "wof:name":"CR0 4BW",
    "wof:placetype":"postalcode"
},
  "geometry": {"coordinates":[-0.11605,51.372816],"type":"Point"}
}