{
  "type": "Feature",
  "properties": {
    "iso:country":"GB",
    "wof:name":"CR0 4BW",
    "wof:placetype":"postalcode"
},
  "geometry": {"coordinates":[-0.11605035615712,51.3728160622427],"type":"Point"}
}