{
  "type": "Feature",
  "properties": {
    "iso:country": "GB",
    "wof:name": "ST20 0LF",
    "wof:placetype": "postalcode"
  },
  "geometry": {"coordinates":[-2.300389,52.827177],"type":"Point"}
}
