{
  "type": "Feature",
  "properties": {
    "iso:country":"GB",
    "wof:name":"ST20 0LF",
    "wof:placetype":"postalcode"
},
  "geometry": {"coordinates":[-2.30038860187178,52.82717698076502],"type":"Point"}
}