{
  "type": "Feature",
  "properties": {
    "iso:country":"GB",
    "wof:name":"DD5 3PN",
    "wof:placetype":"postalcode"
},
  "geometry": {"coordinates":[-2.86981069584171,56.52470910962962],"type":"Point"}
}