{
  "type": "Feature",
  "properties": {
    "iso:country":"GB",
    "wof:name":"DN32 7LA",
    "wof:placetype":"postalcode"
},
  "geometry": {"coordinates":[-0.06020519413931,53.56686107111202],"type":"Point"}
}