{
  "type": "Feature",
  "properties": {
    "iso:country":"GB",
    "wof:name":"NW3 5QE",
    "wof:placetype":"postalcode"
},
  "geometry": {"coordinates":[-0.1720279695653,51.55150337159898],"type":"Point"}
}