{
  "type": "Feature",
  "properties": {
    "iso:country": "GB",
    "wof:name": "S72 8HG",
    "wof:placetype": "postalcode"
  },
  "geometry": {"coordinates":[-1.40756,53.56859],"type":"Point"}
}
