{
  "type": "Feature",
  "properties": {
    "iso:country":"GB",
    "wof:name":"S72 8HG",
    "wof:placetype":"postalcode"
},
  "geometry": {"coordinates":[-1.40756009507328,53.56859005745565],"type":"Point"}
}