{
  "type": "Feature",
  "properties": {
    "iso:country":"GB",
    "wof:name":"PR6 7JD",
    "wof:placetype":"postalcode"
},
  "geometry": {"coordinates":[-2.64007406714694,53.70210684025682],"type":"Point"}
}