{
  "type": "Feature",
  "properties": {
    "iso:country":"GB",
    "wof:name":"NN5 7NG",
    "wof:placetype":"postalcode"
},
  "geometry": {"coordinates":[-0.91693135012595,52.25864077505294],"type":"Point"}
}