{
  "type": "Feature",
  "properties": {
    "iso:country": "GB",
    "wof:name": "NN5 7NG",
    "wof:placetype": "postalcode"
  },
  "geometry": {"coordinates":[-0.916931,52.258641],"type":"Point"}
}
