{
  "type": "Feature",
  "properties": {
    "date:inception_lower":"1980-01-01",
    "date:inception_upper":"1980-01-31",
    "iso:country":"GB",
    "wof:name":"NN5 7NG",
    "wof:placetype":"postalcode"
},
  "geometry": {"coordinates":[-0.916931,52.258641],"type":"Point"}
}