{
  "type": "Feature",
  "properties": {
    "iso:country":"GB",
    "wof:name":"DN9 1NJ",
    "wof:placetype":"postalcode"
},
  "geometry": {"coordinates":[-0.81631563981499,53.55297476538229],"type":"Point"}
}