{
  "type": "Feature",
  "properties": {
    "date:inception_lower":"2001-06-01",
    "date:inception_upper":"2001-06-30",
    "iso:country":"GB",
    "wof:name":"OX29 7YA",
    "wof:placetype":"postalcode"
},
  "geometry": {"coordinates":[-1.487057,51.766985],"type":"Point"}
}