{
  "type": "Feature",
  "properties": {
    "date:inception_lower": "1980-01-01",
    "date:inception_upper": "1980-01-01",
    "iso:country": "GB",
    "wof:name": "TW12 2DL",
    "wof:placetype": "postalcode"
  },
  "geometry": {"coordinates":[-0.372021,51.413818],"type":"Point"}
}
