{
  "type": "Feature",
  "properties": {
    "iso:country": "GB",
    "wof:name": "ST4 7EZ",
    "wof:placetype": "postalcode"
  },
  "geometry": {"coordinates":[-2.194545,53.00704],"type":"Point"}
}
