{
  "type": "Feature",
  "properties": {
    "iso:country":"GB",
    "wof:name":"ST4 7EZ",
    "wof:placetype":"postalcode"
},
  "geometry": {"coordinates":[-2.19454498019736,53.00704011645565],"type":"Point"}
}