{
  "type": "Feature",
  "properties": {
    "date:inception_lower":"1997-12-01",
    "date:inception_upper":"1997-12-31",
    "iso:country":"GB",
    "wof:name":"SP4 7XE",
    "wof:placetype":"postalcode"
},
  "geometry": {"coordinates":[-1.765524,51.166687],"type":"Point"}
}