{
  "type": "Feature",
  "properties": {
    "iso:country":"GB",
    "wof:name":"SP4 7XE",
    "wof:placetype":"postalcode"
},
  "geometry": {"coordinates":[-1.76552443558343,51.16668710216828],"type":"Point"}
}