{
  "type": "Feature",
  "properties": {
    "iso:country": "GB",
    "wof:name": "SP4 7XE",
    "wof:placetype": "postalcode"
  },
  "geometry": {"coordinates":[-1.765524,51.166687],"type":"Point"}
}
