{
  "type": "Feature",
  "properties": {
    "date:inception_lower":"1980-01-01",
    "date:inception_upper":"1980-01-31",
    "iso:country":"GB",
    "wof:name":"AL3 7NL",
    "wof:placetype":"postalcode"
},
  "geometry": {"coordinates":[-0.40434,51.791992],"type":"Point"}
}