{
  "type": "Feature",
  "properties": {
    "iso:country":"GB",
    "wof:name":"AL3 7NL",
    "wof:placetype":"postalcode"
},
  "geometry": {"coordinates":[-0.40436308201603,51.79198493891739],"type":"Point"}
}