{
  "type": "Feature",
  "properties": {
    "iso:country": "GB",
    "wof:name": "DE24 9AS",
    "wof:placetype": "postalcode"
  },
  "geometry": {"coordinates":[-1.454862,52.887013],"type":"Point"}
}
