{
  "type": "Feature",
  "properties": {
    "iso:country":"GB",
    "wof:name":"B26 3LS",
    "wof:placetype":"postalcode"
},
  "geometry": {"coordinates":[-1.77251039465165,52.45190203531939],"type":"Point"}
}