{
  "type": "Feature",
  "properties": {
    "date:inception_lower": "1980-01-01",
    "date:inception_upper": "1980-01-01",
    "iso:country": "GB",
    "wof:name": "B26 3LS",
    "wof:placetype": "postalcode"
  },
  "geometry": {"coordinates":[-1.772754,52.451872],"type":"Point"}
}
