{
  "type": "Feature",
  "properties": {
    "iso:country": "GB",
    "wof:name": "BN14 8HQ",
    "wof:placetype": "postalcode"
  },
  "geometry": {"coordinates":[-0.355954,50.826632],"type":"Point"}
}
