{
  "type": "Feature",
  "properties": {
    "iso:country":"GB",
    "wof:name":"NN4 0UP",
    "wof:placetype":"postalcode"
},
  "geometry": {"coordinates":[-0.91973995089621,52.20874995425847],"type":"Point"}
}