{
  "type": "Feature",
  "properties": {
    "iso:country": "GB",
    "wof:name": "NN4 0UP",
    "wof:placetype": "postalcode"
  },
  "geometry": {"coordinates":[-0.91974,52.20875],"type":"Point"}
}
