{
  "type": "Feature",
  "properties": {
    "date:inception_lower":"1994-05-01",
    "date:inception_upper":"1994-05-31",
    "iso:country":"GB",
    "wof:name":"NN4 0UP",
    "wof:placetype":"postalcode"
},
  "geometry": {"coordinates":[-0.91974,52.20875],"type":"Point"}
}