{
  "type": "Feature",
  "properties": {
    "iso:country": "GB",
    "wof:name": "OX3 7AN",
    "wof:placetype": "postalcode"
  },
  "geometry": {"coordinates":[-1.211049,51.755846],"type":"Point"}
}
