{
  "type": "Feature",
  "properties": {
    "date:inception_lower":"1980-01-01",
    "date:inception_upper":"1980-01-31",
    "iso:country":"GB",
    "wof:name":"CB8 8TP",
    "wof:placetype":"postalcode"
},
  "geometry": {"coordinates":[0.55271,52.205782],"type":"Point"}
}