{
  "type": "Feature",
  "properties": {
    "iso:country": "GB",
    "wof:name": "CB8 8TP",
    "wof:placetype": "postalcode"
  },
  "geometry": {"coordinates":[0.55271,52.205782],"type":"Point"}
}
