{
  "type": "Feature",
  "properties": {
    "iso:country":"GB",
    "wof:name":"HU10 7UZ",
    "wof:placetype":"postalcode"
},
  "geometry": {"coordinates":[-0.44883662461038,53.75622521125872],"type":"Point"}
}