{
  "type": "Feature",
  "properties": {
    "iso:country": "GB",
    "wof:name": "EH30 9PN",
    "wof:placetype": "postalcode"
  },
  "geometry": {"coordinates":[-3.384908,55.981904],"type":"Point"}
}
