{
  "type": "Feature",
  "properties": {
    "date:inception_lower":"1980-01-01",
    "date:inception_upper":"1980-01-31",
    "iso:country":"GB",
    "wof:name":"EH30 9PN",
    "wof:placetype":"postalcode"
},
  "geometry": {"coordinates":[-3.384908,55.981904],"type":"Point"}
}