{
  "type": "Feature",
  "properties": {
    "iso:country": "GB",
    "wof:name": "SG8 5HN",
    "wof:placetype": "postalcode"
  },
  "geometry": {"coordinates":[-0.038434,52.05365],"type":"Point"}
}
