{
  "type": "Feature",
  "properties": {
    "date:inception_lower": "1983-03-01",
    "date:inception_upper": "1983-03-01",
    "iso:country": "GB",
    "wof:name": "SG8 5HN",
    "wof:placetype": "postalcode"
  },
  "geometry": {"coordinates":[-0.038434,52.05365],"type":"Point"}
}
