{
  "type": "Feature",
  "properties": {
    "iso:country":"GB",
    "wof:name":"SG8 5HN",
    "wof:placetype":"postalcode"
},
  "geometry": {"coordinates":[-0.03836505556229,52.05354823662125],"type":"Point"}
}