{
  "type": "Feature",
  "properties": {
    "iso:country":"GB",
    "wof:name":"PO1 1PB",
    "wof:placetype":"postalcode"
},
  "geometry": {"coordinates":[-1.0795380363704,50.79957354622884],"type":"Point"}
}