{
  "type": "Feature",
  "properties": {
    "iso:country":"GB",
    "wof:name":"BN2 5PS",
    "wof:placetype":"postalcode"
},
  "geometry": {"coordinates":[-0.10341268564386,50.8310017172418],"type":"Point"}
}