{
  "type": "Feature",
  "properties": {
    "iso:country": "GB",
    "wof:name": "UB9 5HT",
    "wof:placetype": "postalcode"
  },
  "geometry": {"coordinates":[-0.501189,51.582786],"type":"Point"}
}
