{
  "type": "Feature",
  "properties": {
    "iso:country":"GB",
    "wof:name":"UB9 5HT",
    "wof:placetype":"postalcode"
},
  "geometry": {"coordinates":[-0.50118914039229,51.58278607962427],"type":"Point"}
}