{
  "type": "Feature",
  "properties": {
    "iso:country":"GB",
    "wof:name":"OX5 2YH",
    "wof:placetype":"postalcode"
},
  "geometry": {"coordinates":[-1.28798260219912,51.8265310385678],"type":"Point"}
}