{
  "type": "Feature",
  "properties": {
    "iso:country": "GB",
    "wof:name": "OX5 2YH",
    "wof:placetype": "postalcode"
  },
  "geometry": {"coordinates":[-1.287983,51.826531],"type":"Point"}
}
