{
  "type": "Feature",
  "properties": {
    "iso:country":"GB",
    "wof:name":"NE5 5JH",
    "wof:placetype":"postalcode"
},
  "geometry": {"coordinates":[-1.69287118417608,54.99630101500048],"type":"Point"}
}