{
  "type": "Feature",
  "properties": {
    "date:inception_lower": "1995-12-01",
    "date:inception_upper": "1995-12-01",
    "iso:country": "GB",
    "wof:name": "AB45 2JH",
    "wof:placetype": "postalcode"
  },
  "geometry": {"coordinates":[-2.536953,57.668768],"type":"Point"}
}
