{
  "type": "Feature",
  "properties": {
    "date:inception_lower":"1995-07-01",
    "date:inception_upper":"1995-07-31",
    "iso:country":"GB",
    "wof:name":"CF83 2PA",
    "wof:placetype":"postalcode"
},
  "geometry": {"coordinates":[-3.239726,51.588689],"type":"Point"}
}