{
  "type": "Feature",
  "properties": {
    "iso:country": "GB",
    "wof:name": "CF83 2PA",
    "wof:placetype": "postalcode"
  },
  "geometry": {"coordinates":[-3.239726,51.588689],"type":"Point"}
}
