{
  "type": "Feature",
  "properties": {
    "iso:country":"GB",
    "wof:name":"CF83 2PA",
    "wof:placetype":"postalcode"
},
  "geometry": {"coordinates":[-3.23972619228871,51.58868909344811],"type":"Point"}
}