{
  "type": "Feature",
  "properties": {
    "iso:country":"GB",
    "wof:name":"SO23 0QL",
    "wof:placetype":"postalcode"
},
  "geometry": {"coordinates":[-1.29657649785539,51.05801688570597],"type":"Point"}
}