{
  "type": "Feature",
  "properties": {
    "date:inception_lower": "1980-01-01",
    "date:inception_upper": "1980-01-01",
    "iso:country": "GB",
    "wof:name": "SN6 7RU",
    "wof:placetype": "postalcode"
  },
  "geometry": {"coordinates":[-1.747647,51.642514],"type":"Point"}
}
