{
  "type": "Feature",
  "properties": {
    "iso:country":"GB",
    "wof:name":"SN6 7RU",
    "wof:placetype":"postalcode"
},
  "geometry": {"coordinates":[-1.74764720240431,51.64251400069325],"type":"Point"}
}