{
  "type": "Feature",
  "properties": {
    "iso:country": "GB",
    "wof:name": "IP17 1NJ",
    "wof:placetype": "postalcode"
  },
  "geometry": {"coordinates":[1.523655,52.192151],"type":"Point"}
}
