{
  "type": "Feature",
  "properties": {
    "iso:country": "GB",
    "wof:name": "RG7 3AA",
    "wof:placetype": "postalcode"
  },
  "geometry": {"coordinates":[-1.024914,51.3769],"type":"Point"}
}
