{
  "type": "Feature",
  "properties": {
    "iso:country":"GB",
    "wof:name":"RG7 3AA",
    "wof:placetype":"postalcode"
},
  "geometry": {"coordinates":[-1.02493448007838,51.37689906320856],"type":"Point"}
}