{
  "type": "Feature",
  "properties": {
    "iso:country": "GB",
    "wof:name": "CF45 4EY",
    "wof:placetype": "postalcode"
  },
  "geometry": {"coordinates":[-3.375911,51.68249],"type":"Point"}
}
