{
  "type": "Feature",
  "properties": {
    "iso:country":"GB",
    "wof:name":"TN22 1AN",
    "wof:placetype":"postalcode"
},
  "geometry": {"coordinates":[0.09604698556611,50.97081191031083],"type":"Point"}
}