{
  "type": "Feature",
  "properties": {
    "iso:country":"GB",
    "wof:name":"G45 0BH",
    "wof:placetype":"postalcode"
},
  "geometry": {"coordinates":[-4.21693180700924,55.81132488568699],"type":"Point"}
}