{
  "type": "Feature",
  "properties": {
    "date:inception_lower": "1980-01-01",
    "date:inception_upper": "1980-01-01",
    "iso:country": "GB",
    "wof:name": "ME3 9HW",
    "wof:placetype": "postalcode"
  },
  "geometry": {"coordinates":[0.554794,51.427044],"type":"Point"}
}
