{
  "type": "Feature",
  "properties": {
    "iso:country":"GB",
    "wof:name":"ME3 9HW",
    "wof:placetype":"postalcode"
},
  "geometry": {"coordinates":[0.55479383690672,51.42704406693547],"type":"Point"}
}