{
  "type": "Feature",
  "properties": {
    "iso:country": "GB",
    "wof:name": "AB42 1GH",
    "wof:placetype": "postalcode"
  },
  "geometry": {"coordinates":[-1.814552,57.518159],"type":"Point"}
}
