{
  "type": "Feature",
  "properties": {
    "iso:country":"GB",
    "wof:name":"HP7 9JG",
    "wof:placetype":"postalcode"
},
  "geometry": {"coordinates":[-0.58569952700377,51.6719013780829],"type":"Point"}
}