{
  "type": "Feature",
  "properties": {
    "date:inception_lower": "1980-01-01",
    "date:inception_upper": "1980-01-01",
    "iso:country": "GB",
    "wof:name": "HP7 9JG",
    "wof:placetype": "postalcode"
  },
  "geometry": {"coordinates":[-0.585936,51.671962],"type":"Point"}
}
