{
  "type": "Feature",
  "properties": {
    "iso:country": "GB",
    "wof:name": "HP7 9JG",
    "wof:placetype": "postalcode"
  },
  "geometry": {"coordinates":[-0.585936,51.671962],"type":"Point"}
}
