{
  "type": "Feature",
  "properties": {
    "date:inception_lower": "1980-01-01",
    "date:inception_upper": "1980-01-01",
    "iso:country": "GB",
    "wof:name": "LA5 9DJ",
    "wof:placetype": "postalcode"
  },
  "geometry": {"coordinates":[-2.773361,54.127272],"type":"Point"}
}
