{
  "type": "Feature",
  "properties": {
    "iso:country":"GB",
    "wof:name":"LA5 9DJ",
    "wof:placetype":"postalcode"
},
  "geometry": {"coordinates":[-2.7733606462898,54.12727200352119],"type":"Point"}
}