{
  "type": "Feature",
  "properties": {
    "date:inception_lower": "2019-08-01",
    "date:inception_upper": "2019-08-01",
    "iso:country": "GB",
    "wof:name": "LE19 4DD",
    "wof:placetype": "postalcode"
  },
  "geometry": {"coordinates":[-1.220412,52.61364],"type":"Point"}
}
