{
  "type": "Feature",
  "properties": {
    "iso:country":"GB",
    "wof:name":"YO1 9PH",
    "wof:placetype":"postalcode"
},
  "geometry": {"coordinates":[-1.07552476364945,53.95630179697426],"type":"Point"}
}