{
  "type": "Feature",
  "properties": {
    "iso:country": "GB",
    "wof:name": "CR0 8PU",
    "wof:placetype": "postalcode"
  },
  "geometry": {"coordinates":[-0.033167,51.371004],"type":"Point"}
}
