{
  "type": "Feature",
  "properties": {
    "date:inception_lower":"1980-01-01",
    "date:inception_upper":"1980-01-31",
    "iso:country":"GB",
    "wof:name":"CR0 8PU",
    "wof:placetype":"postalcode"
},
  "geometry": {"coordinates":[-0.033167,51.371004],"type":"Point"}
}