{
  "type": "Feature",
  "properties": {
    "iso:country":"GB",
    "wof:name":"CR0 8PU",
    "wof:placetype":"postalcode"
},
  "geometry": {"coordinates":[-0.03316725028819,51.37100422629248],"type":"Point"}
}