{
  "type": "Feature",
  "properties": {
    "iso:country": "GB",
    "wof:name": "LS7 2DP",
    "wof:placetype": "postalcode"
  },
  "geometry": {"coordinates":[-1.547544,53.822003],"type":"Point"}
}
