{
  "type": "Feature",
  "properties": {
    "iso:country": "GB",
    "wof:name": "NW1 1PR",
    "wof:placetype": "postalcode"
  },
  "geometry": {"coordinates":[-0.134669,51.53177],"type":"Point"}
}
