{
  "type": "Feature",
  "properties": {
    "date:inception_lower":"1980-01-01",
    "date:inception_upper":"1980-01-31",
    "iso:country":"GB",
    "wof:name":"NW1 1PR",
    "wof:placetype":"postalcode"
},
  "geometry": {"coordinates":[-0.134669,51.53177],"type":"Point"}
}