{
  "type": "Feature",
  "properties": {
    "iso:country":"GB",
    "wof:name":"TR1 3PX",
    "wof:placetype":"postalcode"
},
  "geometry": {"coordinates":[-5.07937824427,50.26078209707945],"type":"Point"}
}