{
  "type": "Feature",
  "properties": {
    "date:inception_lower": "1985-10-01",
    "date:inception_upper": "1985-10-01",
    "iso:country": "GB",
    "wof:name": "LA6 3BB",
    "wof:placetype": "postalcode"
  },
  "geometry": {"coordinates":[-2.468481,54.146389],"type":"Point"}
}
