{
  "type": "Feature",
  "properties": {
    "iso:country": "GB",
    "wof:name": "LA6 3BB",
    "wof:placetype": "postalcode"
  },
  "geometry": {"coordinates":[-2.468481,54.146389],"type":"Point"}
}
