{
  "type": "Feature",
  "properties": {
    "iso:country":"GB",
    "wof:name":"SE1 3FW",
    "wof:placetype":"postalcode"
},
  "geometry": {"coordinates":[-0.07837904511408,51.49586265357566],"type":"Point"}
}