{
  "type": "Feature",
  "properties": {
    "iso:country":"GB",
    "wof:name":"NN18 0AY",
    "wof:placetype":"postalcode"
},
  "geometry": {"coordinates":[-0.72404421014664,52.48907834627795],"type":"Point"}
}