{
  "type": "Feature",
  "properties": {
    "iso:country": "GB",
    "wof:name": "NN18 0AY",
    "wof:placetype": "postalcode"
  },
  "geometry": {"coordinates":[-0.724044,52.489078],"type":"Point"}
}
