{
  "type": "Feature",
  "properties": {
    "iso:country":"GB",
    "wof:name":"TS26 0QL",
    "wof:placetype":"postalcode"
},
  "geometry": {"coordinates":[-1.25267369134554,54.68674547477065],"type":"Point"}
}