{
  "type": "Feature",
  "properties": {
    "iso:country":"GB",
    "wof:name":"S45 0ED",
    "wof:placetype":"postalcode"
},
  "geometry": {"coordinates":[-1.50506999331634,53.16284242728142],"type":"Point"}
}