{
  "type": "Feature",
  "properties": {
    "iso:country":"GB",
    "wof:name":"DT11 0RA",
    "wof:placetype":"postalcode"
},
  "geometry": {"coordinates":[-2.25264888078583,50.90386008974482],"type":"Point"}
}