{
  "type": "Feature",
  "properties": {
    "iso:country":"GB",
    "wof:name":"G43 2PR",
    "wof:placetype":"postalcode"
},
  "geometry": {"coordinates":[-4.2747186416833,55.81560774371445],"type":"Point"}
}