{
  "type": "Feature",
  "properties": {
    "iso:country": "GB",
    "wof:name": "KT19 9JX",
    "wof:placetype": "postalcode"
  },
  "geometry": {"coordinates":[-0.272534,51.363933],"type":"Point"}
}
