{
  "type": "Feature",
  "properties": {
    "date:inception_lower": "1998-06-01",
    "date:inception_upper": "1998-06-01",
    "iso:country": "GB",
    "wof:name": "BA14 7HY",
    "wof:placetype": "postalcode"
  },
  "geometry": {"coordinates":[-2.186696,51.323177],"type":"Point"}
}
