{
  "type": "Feature",
  "properties": {
    "iso:country":"GB",
    "wof:name":"BA14 7HY",
    "wof:placetype":"postalcode"
},
  "geometry": {"coordinates":[-2.18669622228496,51.32317670458147],"type":"Point"}
}