{
  "type": "Feature",
  "properties": {
    "date:inception_lower":"1980-01-01",
    "date:inception_upper":"1980-01-31",
    "iso:country":"GB",
    "wof:name":"EX13 7LR",
    "wof:placetype":"postalcode"
},
  "geometry": {"coordinates":[-2.981842,50.804896],"type":"Point"}
}