{
  "type": "Feature",
  "properties": {
    "iso:country":"GB",
    "wof:name":"EX13 7LR",
    "wof:placetype":"postalcode"
},
  "geometry": {"coordinates":[-2.98184217674757,50.80489608869524],"type":"Point"}
}