{
  "type": "Feature",
  "properties": {
    "iso:country":"GB",
    "wof:name":"PO13 0BA",
    "wof:placetype":"postalcode"
},
  "geometry": {"coordinates":[-1.16412254706989,50.82516487479343],"type":"Point"}
}