{
  "type": "Feature",
  "properties": {
    "date:inception_lower":"1990-02-01",
    "date:inception_upper":"1990-02-28",
    "iso:country":"GB",
    "wof:name":"PO13 0BA",
    "wof:placetype":"postalcode"
},
  "geometry": {"coordinates":[-1.164123,50.825165],"type":"Point"}
}