{
  "type": "Feature",
  "properties": {
    "iso:country":"GB",
    "wof:name":"PO36 8JG",
    "wof:placetype":"postalcode"
},
  "geometry": {"coordinates":[-1.15708886660301,50.65570732104594],"type":"Point"}
}