{
  "type": "Feature",
  "properties": {
    "iso:country": "GB",
    "wof:name": "LS11 7HB",
    "wof:placetype": "postalcode"
  },
  "geometry": {"coordinates":[-1.558689,53.769391],"type":"Point"}
}
