{
  "type": "Feature",
  "properties": {
    "iso:country":"GB",
    "wof:name":"M40 2XP",
    "wof:placetype":"postalcode"
},
  "geometry": {"coordinates":[-2.19079073127222,53.49179418988497],"type":"Point"}
}