{
  "type": "Feature",
  "properties": {
    "iso:country":"GB",
    "wof:name":"DN33 1HX",
    "wof:placetype":"postalcode"
},
  "geometry": {"coordinates":[-0.10966883359439,53.54436062320444],"type":"Point"}
}