{
  "type": "Feature",
  "properties": {
    "iso:country":"GB",
    "wof:name":"BB3 2UR",
    "wof:placetype":"postalcode"
},
  "geometry": {"coordinates":[-2.45493204716782,53.68154345479222],"type":"Point"}
}