{
  "type": "Feature",
  "properties": {
    "iso:country": "GB",
    "wof:name": "SO16 9GQ",
    "wof:placetype": "postalcode"
  },
  "geometry": {"coordinates":[-1.451741,50.935266],"type":"Point"}
}
