{
  "type": "Feature",
  "properties": {
    "iso:country": "GB",
    "wof:name": "HP18 9QG",
    "wof:placetype": "postalcode"
  },
  "geometry": {"coordinates":[-1.06904,51.804832],"type":"Point"}
}
