{
  "type": "Feature",
  "properties": {
    "iso:country":"GB",
    "wof:name":"HP18 9QG",
    "wof:placetype":"postalcode"
},
  "geometry": {"coordinates":[-1.06906115038035,51.80482607306738],"type":"Point"}
}