{
  "type": "Feature",
  "properties": {
    "iso:country": "GB",
    "wof:name": "NR1 2EJ",
    "wof:placetype": "postalcode"
  },
  "geometry": {"coordinates":[1.300378,52.612654],"type":"Point"}
}
