{
  "type": "Feature",
  "properties": {
    "iso:country":"GB",
    "wof:name":"NR1 2EJ",
    "wof:placetype":"postalcode"
},
  "geometry": {"coordinates":[1.30037808165708,52.61265399351188],"type":"Point"}
}