{
  "type": "Feature",
  "properties": {
    "iso:country":"GB",
    "wof:name":"CH8 7QZ",
    "wof:placetype":"postalcode"
},
  "geometry": {"coordinates":[-3.2175486696851,53.28467297979137],"type":"Point"}
}