{
  "type": "Feature",
  "properties": {
    "iso:country":"GB",
    "wof:name":"DL6 1SE",
    "wof:placetype":"postalcode"
},
  "geometry": {"coordinates":[-1.42460271972434,54.33087115305857],"type":"Point"}
}