{
  "type": "Feature",
  "properties": {
    "iso:country": "GB",
    "wof:name": "DL6 1SE",
    "wof:placetype": "postalcode"
  },
  "geometry": {"coordinates":[-1.424121,54.330836],"type":"Point"}
}
