{
  "type": "Feature",
  "properties": {
    "iso:country":"GB",
    "wof:name":"HD9 3HA",
    "wof:placetype":"postalcode"
},
  "geometry": {"coordinates":[-1.79287517377396,53.58342224207156],"type":"Point"}
}