{
  "type": "Feature",
  "properties": {
    "iso:country":"GB",
    "wof:name":"S63 9DH",
    "wof:placetype":"postalcode"
},
  "geometry": {"coordinates":[-1.30562942779991,53.53213290238008],"type":"Point"}
}