{
  "type": "Feature",
  "properties": {
    "iso:country": "GB",
    "wof:name": "TD6 0AG",
    "wof:placetype": "postalcode"
  },
  "geometry": {"coordinates":[-2.681671,55.579591],"type":"Point"}
}
