{
  "type": "Feature",
  "properties": {
    "date:inception_lower":"1980-01-01",
    "date:inception_upper":"1980-01-31",
    "iso:country":"GB",
    "wof:name":"WA14 2NZ",
    "wof:placetype":"postalcode"
},
  "geometry": {"coordinates":[-2.355744,53.380399],"type":"Point"}
}