{
  "type": "Feature",
  "properties": {
    "iso:country":"GB",
    "wof:name":"LE10 0HN",
    "wof:placetype":"postalcode"
},
  "geometry": {"coordinates":[-1.38698520467055,52.55018794417789],"type":"Point"}
}