{
  "type": "Feature",
  "properties": {
    "date:inception_lower": "2003-08-01",
    "date:inception_upper": "2003-08-01",
    "iso:country": "GB",
    "wof:name": "MK8 0NJ",
    "wof:placetype": "postalcode"
  },
  "geometry": {"coordinates":[-0.807532,52.023804],"type":"Point"}
}
