{
  "type": "Feature",
  "properties": {
    "iso:country":"GB",
    "wof:name":"MK8 0NJ",
    "wof:placetype":"postalcode"
},
  "geometry": {"coordinates":[-0.8075316001729,52.02380384915379],"type":"Point"}
}