{
  "type": "Feature",
  "properties": {
    "iso:country":"GB",
    "wof:name":"BD23 3HE",
    "wof:placetype":"postalcode"
},
  "geometry": {"coordinates":[-2.04393134180712,53.94403896421585],"type":"Point"}
}