{
  "type": "Feature",
  "properties": {
    "date:inception_lower": "1980-01-01",
    "date:inception_upper": "1980-01-01",
    "iso:country": "GB",
    "wof:name": "BD23 3HE",
    "wof:placetype": "postalcode"
  },
  "geometry": {"coordinates":[-2.043722,53.944035],"type":"Point"}
}
