{
  "type": "Feature",
  "properties": {
    "date:inception_lower": "1980-01-01",
    "date:inception_upper": "1980-01-01",
    "iso:country": "GB",
    "wof:name": "LS17 0DE",
    "wof:placetype": "postalcode"
  },
  "geometry": {"coordinates":[-1.578239,53.937493],"type":"Point"}
}
