{
  "type": "Feature",
  "properties": {
    "iso:country":"GB",
    "wof:name":"G31 2LY",
    "wof:placetype":"postalcode"
},
  "geometry": {"coordinates":[-4.22070724564405,55.86189180065503],"type":"Point"}
}