{
  "type": "Feature",
  "properties": {
    "iso:country":"GB",
    "wof:name":"WF4 4HX",
    "wof:placetype":"postalcode"
},
  "geometry": {"coordinates":[-1.58470286359391,53.63708972707913],"type":"Point"}
}