{
  "type": "Feature",
  "properties": {
    "date:inception_lower": "1980-01-01",
    "date:inception_upper": "1980-01-01",
    "iso:country": "GB",
    "wof:name": "WF4 4HX",
    "wof:placetype": "postalcode"
  },
  "geometry": {"coordinates":[-1.584703,53.63709],"type":"Point"}
}
