{
  "type": "Feature",
  "properties": {
    "date:inception_lower":"2007-11-01",
    "date:inception_upper":"2007-11-30",
    "iso:country":"GB",
    "wof:name":"CA28 8WE",
    "wof:placetype":"postalcode"
},
  "geometry": {"coordinates":[-3.551768,54.56109],"type":"Point"}
}