{
  "type": "Feature",
  "properties": {
    "iso:country":"GB",
    "wof:name":"M40 7EZ",
    "wof:placetype":"postalcode"
},
  "geometry": {"coordinates":[-2.21424055470667,53.48530969636323],"type":"Point"}
}