{
  "type": "Feature",
  "properties": {
    "date:inception_lower":"1995-07-01",
    "date:inception_upper":"1995-07-31",
    "iso:country":"GB",
    "wof:name":"WN7 2AR",
    "wof:placetype":"postalcode"
},
  "geometry": {"coordinates":[-2.503719,53.494217],"type":"Point"}
}