{
  "type": "Feature",
  "properties": {
    "date:inception_lower": "1995-07-01",
    "date:inception_upper": "1995-07-01",
    "iso:country": "GB",
    "wof:name": "WN7 2AR",
    "wof:placetype": "postalcode"
  },
  "geometry": {"coordinates":[-2.503704,53.494244],"type":"Point"}
}
