{
  "type": "Feature",
  "properties": {
    "date:inception_lower": "2017-01-01",
    "date:inception_upper": "2017-01-01",
    "iso:country": "GB",
    "wof:name": "TQ9 6FL",
    "wof:placetype": "postalcode"
  },
  "geometry": {"coordinates":[-3.695698,50.441],"type":"Point"}
}
