{
  "type": "Feature",
  "properties": {
    "date:inception_lower": "2020-11-01",
    "date:inception_upper": "2020-11-01",
    "iso:country": "GB",
    "wof:name": "M11 4TU",
    "wof:placetype": "postalcode"
  },
  "geometry": {"coordinates":[-2.188492,53.487077],"type":"Point"}
}
