{
  "type": "Feature",
  "properties": {
    "iso:country": "GB",
    "wof:name": "IP33 3DQ",
    "wof:placetype": "postalcode"
  },
  "geometry": {"coordinates":[0.706883,52.244764],"type":"Point"}
}
