{
  "type": "Feature",
  "properties": {
    "iso:country":"GB",
    "wof:name":"TN16 1TP",
    "wof:placetype":"postalcode"
},
  "geometry": {"coordinates":[0.06806075655794,51.26717210706356],"type":"Point"}
}