{
  "type": "Feature",
  "properties": {
    "date:inception_lower":"2004-09-01",
    "date:inception_upper":"2004-09-30",
    "iso:country":"GB",
    "wof:name":"BS24 0WY",
    "wof:placetype":"postalcode"
},
  "geometry": {"coordinates":[-2.957023,51.343881],"type":"Point"}
}