{
  "type": "Feature",
  "properties": {
    "iso:country":"GB",
    "wof:name":"CO6 4QB",
    "wof:placetype":"postalcode"
},
  "geometry": {"coordinates":[0.84593437907319,52.00164160605065],"type":"Point"}
}