{
  "type": "Feature",
  "properties": {
    "date:inception_lower":"2005-11-01",
    "date:inception_upper":"2005-11-30",
    "iso:country":"GB",
    "wof:name":"EN1 4TU",
    "wof:placetype":"postalcode"
},
  "geometry": {"coordinates":[-0.063623,51.661972],"type":"Point"}
}