{
  "type": "Feature",
  "properties": {
    "iso:country":"GB",
    "wof:name":"BH22 8AY",
    "wof:placetype":"postalcode"
},
  "geometry": {"coordinates":[-1.87675567457586,50.80936062908714],"type":"Point"}
}