{
  "type": "Feature",
  "properties": {
    "iso:country":"GB",
    "wof:name":"OX10 6DG",
    "wof:placetype":"postalcode"
},
  "geometry": {"coordinates":[-1.08010277990167,51.61620130006446],"type":"Point"}
}