{
  "type": "Feature",
  "properties": {
    "iso:country":"GB",
    "wof:name":"NW3 3AS",
    "wof:placetype":"postalcode"
},
  "geometry": {"coordinates":[-0.15873513318636,51.54099017689087],"type":"Point"}
}