{
  "type": "Feature",
  "properties": {
    "iso:country": "GB",
    "wof:name": "CM2 8TG",
    "wof:placetype": "postalcode"
  },
  "geometry": {"coordinates":[0.443034,51.709476],"type":"Point"}
}
