{
  "type": "Feature",
  "properties": {
    "iso:country":"GB",
    "wof:name":"CM2 8TG",
    "wof:placetype":"postalcode"
},
  "geometry": {"coordinates":[0.44303408439447,51.70947614599058],"type":"Point"}
}