{
  "type": "Feature",
  "properties": {
    "iso:country": "GB",
    "wof:name": "WA3 4AJ",
    "wof:placetype": "postalcode"
  },
  "geometry": {"coordinates":[-2.513569,53.45852],"type":"Point"}
}
