{
  "type": "Feature",
  "properties": {
    "date:inception_lower":"1980-01-01",
    "date:inception_upper":"1980-01-31",
    "iso:country":"GB",
    "wof:name":"ME17 3HU",
    "wof:placetype":"postalcode"
},
  "geometry": {"coordinates":[0.592894,51.218505],"type":"Point"}
}