{
  "type": "Feature",
  "properties": {
    "iso:country":"GB",
    "wof:name":"PE13 2LJ",
    "wof:placetype":"postalcode"
},
  "geometry": {"coordinates":[0.1636213260509,52.66262142343438],"type":"Point"}
}