{
  "type": "Feature",
  "properties": {
    "iso:country": "GB",
    "wof:name": "PE13 2LJ",
    "wof:placetype": "postalcode"
  },
  "geometry": {"coordinates":[0.163621,52.662621],"type":"Point"}
}
