{
  "type": "Feature",
  "properties": {
    "iso:country": "GB",
    "wof:name": "LS27 0HT",
    "wof:placetype": "postalcode"
  },
  "geometry": {"coordinates":[-1.589786,53.733595],"type":"Point"}
}
