{
  "type": "Feature",
  "properties": {
    "iso:country":"GB",
    "wof:name":"LS27 0HT",
    "wof:placetype":"postalcode"
},
  "geometry": {"coordinates":[-1.5897860179464,53.73359549880693],"type":"Point"}
}