{
  "type": "Feature",
  "properties": {
    "iso:country":"GB",
    "wof:name":"RM11 2NW",
    "wof:placetype":"postalcode"
},
  "geometry": {"coordinates":[0.22265202093976,51.58281940215236],"type":"Point"}
}