{
  "type": "Feature",
  "properties": {
    "date:inception_lower": "1980-01-01",
    "date:inception_upper": "1980-01-01",
    "iso:country": "GB",
    "wof:name": "YO17 9LT",
    "wof:placetype": "postalcode"
  },
  "geometry": {"coordinates":[-0.812706,54.068511],"type":"Point"}
}
