{
  "type": "Feature",
  "properties": {
    "iso:country":"GB",
    "wof:name":"YO17 9LT",
    "wof:placetype":"postalcode"
},
  "geometry": {"coordinates":[-0.81270584573762,54.06851141741787],"type":"Point"}
}