{
  "type": "Feature",
  "properties": {
    "iso:country":"GB",
    "wof:name":"CA2 6DS",
    "wof:placetype":"postalcode"
},
  "geometry": {"coordinates":[-2.9562259155305,54.88502518563362],"type":"Point"}
}