{
  "type": "Feature",
  "properties": {
    "iso:country":"GB",
    "wof:name":"NN15 7HT",
    "wof:placetype":"postalcode"
},
  "geometry": {"coordinates":[-0.72465513314177,52.39151007739852],"type":"Point"}
}