{
  "type": "Feature",
  "properties": {
    "iso:country":"GB",
    "wof:name":"GL15 6BP",
    "wof:placetype":"postalcode"
},
  "geometry": {"coordinates":[-2.57890872248711,51.75531164982407],"type":"Point"}
}