{
  "type": "Feature",
  "properties": {
    "iso:country": "GB",
    "wof:name": "GL15 6BP",
    "wof:placetype": "postalcode"
  },
  "geometry": {"coordinates":[-2.578953,51.755289],"type":"Point"}
}
