{
  "type": "Feature",
  "properties": {
    "iso:country":"GB",
    "wof:name":"SP5 4EZ",
    "wof:placetype":"postalcode"
},
  "geometry": {"coordinates":[-1.75928394731879,51.02442832400268],"type":"Point"}
}