{
  "type": "Feature",
  "properties": {
    "date:inception_lower": "1980-01-01",
    "date:inception_upper": "1980-01-01",
    "iso:country": "GB",
    "wof:name": "DD10 0RS",
    "wof:placetype": "postalcode"
  },
  "geometry": {"coordinates":[-2.27663,56.843035],"type":"Point"}
}
