{
  "type": "Feature",
  "properties": {
    "iso:country":"GB",
    "wof:name":"DD10 0RS",
    "wof:placetype":"postalcode"
},
  "geometry": {"coordinates":[-2.27662982091939,56.84303544714463],"type":"Point"}
}