{
  "type": "Feature",
  "properties": {
    "iso:country":"GB",
    "wof:name":"WR13 5EP",
    "wof:placetype":"postalcode"
},
  "geometry": {"coordinates":[-2.39080500925848,52.14342152649759],"type":"Point"}
}