{
  "type": "Feature",
  "properties": {
    "date:inception_lower": "2011-03-01",
    "date:inception_upper": "2011-03-01",
    "iso:country": "GB",
    "wof:name": "EH3 9GH",
    "wof:placetype": "postalcode"
  },
  "geometry": {"coordinates":[-3.192438,55.943994],"type":"Point"}
}
