{
  "type": "Feature",
  "properties": {
    "iso:country": "GB",
    "wof:name": "BL0 9UJ",
    "wof:placetype": "postalcode"
  },
  "geometry": {"coordinates":[-2.324014,53.627923],"type":"Point"}
}
