{
  "type": "Feature",
  "properties": {
    "iso:country":"GB",
    "wof:name":"BL0 9UJ",
    "wof:placetype":"postalcode"
},
  "geometry": {"coordinates":[-2.32401373174222,53.62792330922775],"type":"Point"}
}