{
  "type": "Feature",
  "properties": {
    "iso:country": "GB",
    "wof:name": "S64 5UP",
    "wof:placetype": "postalcode"
  },
  "geometry": {"coordinates":[-1.307088,53.47696],"type":"Point"}
}
