{
  "type": "Feature",
  "properties": {
    "iso:country":"GB",
    "wof:name":"S64 5UP",
    "wof:placetype":"postalcode"
},
  "geometry": {"coordinates":[-1.30708764453158,53.4769604037272],"type":"Point"}
}