{
  "type": "Feature",
  "properties": {
    "iso:country":"GB",
    "wof:name":"L18 0HB",
    "wof:placetype":"postalcode"
},
  "geometry": {"coordinates":[-2.9045811047392,53.39141566595696],"type":"Point"}
}