{
  "type": "Feature",
  "properties": {
    "iso:country": "GB",
    "wof:name": "LE65 1FF",
    "wof:placetype": "postalcode"
  },
  "geometry": {"coordinates":[-1.461856,52.746853],"type":"Point"}
}
