{
  "type": "Feature",
  "properties": {
    "iso:country":"GB",
    "wof:name":"LE65 1FF",
    "wof:placetype":"postalcode"
},
  "geometry": {"coordinates":[-1.46185581104755,52.74685313402438],"type":"Point"}
}