{
  "type": "Feature",
  "properties": {
    "date:inception_lower":"2013-01-01",
    "date:inception_upper":"2013-01-31",
    "iso:country":"GB",
    "wof:name":"LE65 1FF",
    "wof:placetype":"postalcode"
},
  "geometry": {"coordinates":[-1.461856,52.746853],"type":"Point"}
}