{
  "type": "Feature",
  "properties": {
    "iso:country":"GB",
    "wof:name":"L2 4TQ",
    "wof:placetype":"postalcode"
},
  "geometry": {"coordinates":[-2.99038766735867,53.40711238599401],"type":"Point"}
}