{
  "type": "Feature",
  "properties": {
    "iso:country":"GB",
    "wof:name":"LU2 9DW",
    "wof:placetype":"postalcode"
},
  "geometry": {"coordinates":[-0.39697433359082,51.89315868444828],"type":"Point"}
}