{
  "type": "Feature",
  "properties": {
    "iso:country":"GB",
    "wof:name":"B70 6LH",
    "wof:placetype":"postalcode"
},
  "geometry": {"coordinates":[-1.9860027109085,52.51140824232262],"type":"Point"}
}