{
  "type": "Feature",
  "properties": {
    "iso:country": "GB",
    "wof:name": "BS15 9TR",
    "wof:placetype": "postalcode"
  },
  "geometry": {"coordinates":[-2.500977,51.462504],"type":"Point"}
}
