{
  "type": "Feature",
  "properties": {
    "iso:country":"GB",
    "wof:name":"BS15 9TR",
    "wof:placetype":"postalcode"
},
  "geometry": {"coordinates":[-2.50130934073164,51.46264849752656],"type":"Point"}
}