{
  "type": "Feature",
  "properties": {
    "iso:country": "GB",
    "wof:name": "SL3 7AH",
    "wof:placetype": "postalcode"
  },
  "geometry": {"coordinates":[-0.568005,51.505929],"type":"Point"}
}
