{
  "type": "Feature",
  "properties": {
    "iso:country":"GB",
    "wof:name":"SL3 7AH",
    "wof:placetype":"postalcode"
},
  "geometry": {"coordinates":[-0.56800543681373,51.50592913839683],"type":"Point"}
}