{
  "type": "Feature",
  "properties": {
    "iso:country": "GB",
    "wof:name": "ML10 6AB",
    "wof:placetype": "postalcode"
  },
  "geometry": {"coordinates":[-4.067835,55.676743],"type":"Point"}
}
