{
  "type": "Feature",
  "properties": {
    "iso:country":"GB",
    "wof:name":"PE12 6BX",
    "wof:placetype":"postalcode"
},
  "geometry": {"coordinates":[-0.09626415501108,52.77915349100262],"type":"Point"}
}