{
  "type": "Feature",
  "properties": {
    "iso:country": "GB",
    "wof:name": "PE12 6BX",
    "wof:placetype": "postalcode"
  },
  "geometry": {"coordinates":[-0.096264,52.779153],"type":"Point"}
}
