{
  "type": "Feature",
  "properties": {
    "iso:country":"GB",
    "wof:name":"NG6 8FF",
    "wof:placetype":"postalcode"
},
  "geometry": {"coordinates":[-1.20168173421814,52.99497517519107],"type":"Point"}
}