{
  "type": "Feature",
  "properties": {
    "date:inception_lower": "1980-01-01",
    "date:inception_upper": "1980-01-01",
    "iso:country": "GB",
    "wof:name": "TN17 2HN",
    "wof:placetype": "postalcode"
  },
  "geometry": {"coordinates":[0.545921,51.108372],"type":"Point"}
}
