{
  "type": "Feature",
  "properties": {
    "iso:country":"GB",
    "wof:name":"L39 0EN",
    "wof:placetype":"postalcode"
},
  "geometry": {"coordinates":[-2.86666097060804,53.51878027990642],"type":"Point"}
}