{
  "type": "Feature",
  "properties": {
    "iso:country": "GB",
    "wof:name": "L39 0EN",
    "wof:placetype": "postalcode"
  },
  "geometry": {"coordinates":[-2.866661,53.51878],"type":"Point"}
}
