{
  "type": "Feature",
  "properties": {
    "iso:country": "GB",
    "wof:name": "HX7 8RZ",
    "wof:placetype": "postalcode"
  },
  "geometry": {"coordinates":[-1.997006,53.749361],"type":"Point"}
}
