{
  "type": "Feature",
  "properties": {
    "iso:country":"GB",
    "wof:name":"HX7 8RZ",
    "wof:placetype":"postalcode"
},
  "geometry": {"coordinates":[-1.99700575213246,53.7493605594937],"type":"Point"}
}