{
  "type": "Feature",
  "properties": {
    "date:inception_lower": "2010-06-01",
    "date:inception_upper": "2010-06-01",
    "iso:country": "GB",
    "wof:name": "PH22 1UQ",
    "wof:placetype": "postalcode"
  },
  "geometry": {"coordinates":[-3.824435,57.201324],"type":"Point"}
}
