{
  "type": "Feature",
  "properties": {
    "iso:country": "GB",
    "wof:name": "WR13 5FB",
    "wof:placetype": "postalcode"
  },
  "geometry": {"coordinates":[-2.322779,52.153475],"type":"Point"}
}
