{
  "type": "Feature",
  "properties": {
    "iso:country":"GB",
    "wof:name":"PL31 1LL",
    "wof:placetype":"postalcode"
},
  "geometry": {"coordinates":[-4.7334650584797,50.47111031824915],"type":"Point"}
}