{
  "type": "Feature",
  "properties": {
    "iso:country": "GB",
    "wof:name": "PL31 1LL",
    "wof:placetype": "postalcode"
  },
  "geometry": {"coordinates":[-4.733465,50.47111],"type":"Point"}
}
