{
  "type": "Feature",
  "properties": {
    "iso:country":"GB",
    "wof:name":"IP8 4SP",
    "wof:placetype":"postalcode"
},
  "geometry": {"coordinates":[1.01460798423094,52.11962106622958],"type":"Point"}
}