{
  "type": "Feature",
  "properties": {
    "iso:country":"GB",
    "wof:name":"L24 1XQ",
    "wof:placetype":"postalcode"
},
  "geometry": {"coordinates":[-2.86130256958046,53.34740258309314],"type":"Point"}
}