{
  "type": "Feature",
  "properties": {
    "iso:country": "GB",
    "wof:name": "ST2 0LE",
    "wof:placetype": "postalcode"
  },
  "geometry": {"coordinates":[-2.124907,53.013273],"type":"Point"}
}
