{
  "type": "Feature",
  "properties": {
    "iso:country":"GB",
    "wof:name":"ST2 0LE",
    "wof:placetype":"postalcode"
},
  "geometry": {"coordinates":[-2.12490720178068,53.01327339032874],"type":"Point"}
}