{
  "type": "Feature",
  "properties": {
    "iso:country": "GB",
    "wof:name": "NN15 7NQ",
    "wof:placetype": "postalcode"
  },
  "geometry": {"coordinates":[-0.71765,52.393385],"type":"Point"}
}
