{
  "type": "Feature",
  "properties": {
    "iso:country":"GB",
    "wof:name":"NN15 7NQ",
    "wof:placetype":"postalcode"
},
  "geometry": {"coordinates":[-0.71764978754969,52.39338527310439],"type":"Point"}
}