{
  "type": "Feature",
  "properties": {
    "iso:country":"GB",
    "wof:name":"CW8 2JS",
    "wof:placetype":"postalcode"
},
  "geometry": {"coordinates":[-2.59034522609385,53.23442519845652],"type":"Point"}
}