{
  "type": "Feature",
  "properties": {
    "iso:country": "GB",
    "wof:name": "CW8 2JS",
    "wof:placetype": "postalcode"
  },
  "geometry": {"coordinates":[-2.590345,53.234425],"type":"Point"}
}
