{
  "type": "Feature",
  "properties": {
    "date:inception_lower": "1980-01-01",
    "date:inception_upper": "1980-01-01",
    "iso:country": "GB",
    "wof:name": "WN6 8BQ",
    "wof:placetype": "postalcode"
  },
  "geometry": {"coordinates":[-2.691457,53.573764],"type":"Point"}
}
