{
  "type": "Feature",
  "properties": {
    "iso:country":"GB",
    "wof:name":"WN6 8BQ",
    "wof:placetype":"postalcode"
},
  "geometry": {"coordinates":[-2.69145721535552,53.57376357226163],"type":"Point"}
}