{
  "type": "Feature",
  "properties": {
    "iso:country":"GB",
    "wof:name":"TR1 2NS",
    "wof:placetype":"postalcode"
},
  "geometry": {"coordinates":[-5.05339603954372,50.26044275232806],"type":"Point"}
}