{
  "type": "Feature",
  "properties": {
    "iso:country":"GB",
    "wof:name":"PO21 5HQ",
    "wof:placetype":"postalcode"
},
  "geometry": {"coordinates":[-0.69127878271965,50.79751934938072],"type":"Point"}
}