{
  "type": "Feature",
  "properties": {
    "date:inception_lower":"2001-12-01",
    "date:inception_upper":"2001-12-31",
    "iso:country":"GB",
    "wof:name":"PO21 5HQ",
    "wof:placetype":"postalcode"
},
  "geometry": {"coordinates":[-0.691279,50.797519],"type":"Point"}
}