{
  "type": "Feature",
  "properties": {
    "iso:country": "GB",
    "wof:name": "PO21 5HQ",
    "wof:placetype": "postalcode"
  },
  "geometry": {"coordinates":[-0.691279,50.797519],"type":"Point"}
}
