{
  "type": "Feature",
  "properties": {
    "iso:country": "GB",
    "wof:name": "CV10 7LR",
    "wof:placetype": "postalcode"
  },
  "geometry": {"coordinates":[-1.489798,52.515291],"type":"Point"}
}
