{
  "type": "Feature",
  "properties": {
    "iso:country":"GB",
    "wof:name":"NE47 9QW",
    "wof:placetype":"postalcode"
},
  "geometry": {"coordinates":[-2.26981043644227,54.91339120063569],"type":"Point"}
}