{
  "type": "Feature",
  "properties": {
    "date:inception_lower": "1980-01-01",
    "date:inception_upper": "1980-01-01",
    "iso:country": "GB",
    "wof:name": "WS14 9EB",
    "wof:placetype": "postalcode"
  },
  "geometry": {"coordinates":[-1.822944,52.677903],"type":"Point"}
}
