{
  "type": "Feature",
  "properties": {
    "iso:country":"GB",
    "wof:name":"WS14 9EB",
    "wof:placetype":"postalcode"
},
  "geometry": {"coordinates":[-1.8229438120293,52.67790282216058],"type":"Point"}
}