{
  "type": "Feature",
  "properties": {
    "iso:country":"GB",
    "wof:name":"TR3 6PU",
    "wof:placetype":"postalcode"
},
  "geometry": {"coordinates":[-5.09176220757986,50.21192965407905],"type":"Point"}
}