{
  "type": "Feature",
  "properties": {
    "iso:country": "GB",
    "wof:name": "GU34 1FZ",
    "wof:placetype": "postalcode"
  },
  "geometry": {"coordinates":[-0.972581,51.147149],"type":"Point"}
}
