{
  "type": "Feature",
  "properties": {
    "iso:country": "GB",
    "wof:name": "BS48 4AE",
    "wof:placetype": "postalcode"
  },
  "geometry": {"coordinates":[-2.758333,51.406723],"type":"Point"}
}
