{
  "type": "Feature",
  "properties": {
    "iso:country": "GB",
    "wof:name": "ML7 4HF",
    "wof:placetype": "postalcode"
  },
  "geometry": {"coordinates":[-3.806986,55.827245],"type":"Point"}
}
