{
  "type": "Feature",
  "properties": {
    "iso:country":"GB",
    "wof:name":"ML7 4HF",
    "wof:placetype":"postalcode"
},
  "geometry": {"coordinates":[-3.80698593906198,55.8272449104596],"type":"Point"}
}