{
  "type": "Feature",
  "properties": {
    "date:inception_lower": "1995-07-01",
    "date:inception_upper": "1995-07-01",
    "iso:country": "GB",
    "wof:name": "RG30 3AB",
    "wof:placetype": "postalcode"
  },
  "geometry": {"coordinates":[-0.995972,51.447646],"type":"Point"}
}
