{
  "type": "Feature",
  "properties": {
    "iso:country":"GB",
    "wof:name":"RG30 3AB",
    "wof:placetype":"postalcode"
},
  "geometry": {"coordinates":[-0.99597227851988,51.44764561902668],"type":"Point"}
}