{
  "type": "Feature",
  "properties": {
    "iso:country":"GB",
    "wof:name":"ML4 2AQ",
    "wof:placetype":"postalcode"
},
  "geometry": {"coordinates":[-4.02914179897411,55.80904990290703],"type":"Point"}
}