{
  "type": "Feature",
  "properties": {
    "iso:country":"GB",
    "wof:name":"TS25 2DF",
    "wof:placetype":"postalcode"
},
  "geometry": {"coordinates":[-1.20174552120364,54.63860129634048],"type":"Point"}
}