{
  "type": "Feature",
  "properties": {
    "iso:country": "GB",
    "wof:name": "CM2 0BX",
    "wof:placetype": "postalcode"
  },
  "geometry": {"coordinates":[0.474721,51.730684],"type":"Point"}
}
