{
  "type": "Feature",
  "properties": {
    "iso:country":"GB",
    "wof:name":"CM2 0BX",
    "wof:placetype":"postalcode"
},
  "geometry": {"coordinates":[0.4747213209837,51.73068387083448],"type":"Point"}
}