{
  "type": "Feature",
  "properties": {
    "iso:country":"GB",
    "wof:name":"BD21 1QY",
    "wof:placetype":"postalcode"
},
  "geometry": {"coordinates":[-1.91808463973889,53.86206858905884],"type":"Point"}
}