{
  "type": "Feature",
  "properties": {
    "date:inception_lower": "2014-09-01",
    "date:inception_upper": "2014-09-01",
    "iso:country": "GB",
    "wof:name": "SK7 5DP",
    "wof:placetype": "postalcode"
  },
  "geometry": {"coordinates":[-2.137067,53.377876],"type":"Point"}
}
