{
  "type": "Feature",
  "properties": {
    "iso:country":"GB",
    "wof:name":"SK7 5DP",
    "wof:placetype":"postalcode"
},
  "geometry": {"coordinates":[-2.13706731352071,53.3778756826401],"type":"Point"}
}