{
  "type": "Feature",
  "properties": {
    "iso:country": "GB",
    "wof:name": "SK7 5DP",
    "wof:placetype": "postalcode"
  },
  "geometry": {"coordinates":[-2.137067,53.377876],"type":"Point"}
}
