{
  "type": "Feature",
  "properties": {
    "iso:country":"GB",
    "wof:name":"HX3 6HU",
    "wof:placetype":"postalcode"
},
  "geometry": {"coordinates":[-1.86225713421109,53.73516152990967],"type":"Point"}
}