{
  "type": "Feature",
  "properties": {
    "iso:country":"GB",
    "wof:name":"TS14 6LB",
    "wof:placetype":"postalcode"
},
  "geometry": {"coordinates":[-1.06540073330725,54.53374359109302],"type":"Point"}
}