{
  "type": "Feature",
  "properties": {
    "iso:country":"GB",
    "wof:name":"PA10 2PP",
    "wof:placetype":"postalcode"
},
  "geometry": {"coordinates":[-4.55931298989544,55.83884594714063],"type":"Point"}
}