{
  "type": "Feature",
  "properties": {
    "iso:country":"GB",
    "wof:name":"BA3 3JZ",
    "wof:placetype":"postalcode"
},
  "geometry": {"coordinates":[-2.43643404113873,51.29058189652267],"type":"Point"}
}