{
  "type": "Feature",
  "properties": {
    "iso:country": "GB",
    "wof:name": "BA3 3JZ",
    "wof:placetype": "postalcode"
  },
  "geometry": {"coordinates":[-2.436434,51.290582],"type":"Point"}
}
