{
  "type": "Feature",
  "properties": {
    "date:inception_lower":"1980-01-01",
    "date:inception_upper":"1980-01-31",
    "iso:country":"GB",
    "wof:name":"BA3 3JZ",
    "wof:placetype":"postalcode"
},
  "geometry": {"coordinates":[-2.436434,51.290582],"type":"Point"}
}