{
  "type": "Feature",
  "properties": {
    "iso:country":"GB",
    "wof:name":"GU51 3NR",
    "wof:placetype":"postalcode"
},
  "geometry": {"coordinates":[-0.83449830405052,51.27505945546674],"type":"Point"}
}