{
  "type": "Feature",
  "properties": {
    "iso:country": "GB",
    "wof:name": "MK12 5BB",
    "wof:placetype": "postalcode"
  },
  "geometry": {"coordinates":[-0.81773,52.058756],"type":"Point"}
}
