{
  "type": "Feature",
  "properties": {
    "date:inception_lower": "1996-06-01",
    "date:inception_upper": "1996-06-01",
    "iso:country": "GB",
    "wof:name": "AB14 0XQ",
    "wof:placetype": "postalcode"
  },
  "geometry": {"coordinates":[-2.27478,57.10449],"type":"Point"}
}
