{
  "type": "Feature",
  "properties": {
    "iso:country": "GB",
    "wof:name": "BN1 8JE",
    "wof:placetype": "postalcode"
  },
  "geometry": {"coordinates":[-0.137771,50.859021],"type":"Point"}
}
