{
  "type": "Feature",
  "properties": {
    "iso:country":"GB",
    "wof:name":"KT12 2RE",
    "wof:placetype":"postalcode"
},
  "geometry": {"coordinates":[-0.40896734955225,51.38390422549008],"type":"Point"}
}