{
  "type": "Feature",
  "properties": {
    "iso:country": "GB",
    "wof:name": "CM1 6AZ",
    "wof:placetype": "postalcode"
  },
  "geometry": {"coordinates":[0.502669,51.762124],"type":"Point"}
}
