{
  "type": "Feature",
  "properties": {
    "iso:country":"GB",
    "wof:name":"ST17 4BP",
    "wof:placetype":"postalcode"
},
  "geometry": {"coordinates":[-2.11370811518181,52.80157740533402],"type":"Point"}
}