{
  "type": "Feature",
  "properties": {
    "date:inception_lower": "1980-01-01",
    "date:inception_upper": "1980-01-01",
    "iso:country": "GB",
    "wof:name": "TN15 8LU",
    "wof:placetype": "postalcode"
  },
  "geometry": {"coordinates":[0.312787,51.288394],"type":"Point"}
}
