{
  "type": "Feature",
  "properties": {
    "date:inception_lower": "1980-01-01",
    "date:inception_upper": "1980-01-01",
    "iso:country": "GB",
    "wof:name": "PL20 6DR",
    "wof:placetype": "postalcode"
  },
  "geometry": {"coordinates":[-4.085458,50.492904],"type":"Point"}
}
