{
  "type": "Feature",
  "properties": {
    "iso:country":"GB",
    "wof:name":"DY3 1TA",
    "wof:placetype":"postalcode"
},
  "geometry": {"coordinates":[-2.11923152622928,52.53261881410435],"type":"Point"}
}