{
  "type": "Feature",
  "properties": {
    "date:inception_lower": "1980-01-01",
    "date:inception_upper": "1980-01-01",
    "iso:country": "GB",
    "wof:name": "DY3 1TA",
    "wof:placetype": "postalcode"
  },
  "geometry": {"coordinates":[-2.119255,52.532625],"type":"Point"}
}
