{
  "type": "Feature",
  "properties": {
    "iso:country":"GB",
    "wof:name":"M24 5PD",
    "wof:placetype":"postalcode"
},
  "geometry": {"coordinates":[-2.2139694717229,53.56008459413784],"type":"Point"}
}