{
  "type": "Feature",
  "properties": {
    "iso:country": "GB",
    "wof:name": "M24 5PD",
    "wof:placetype": "postalcode"
  },
  "geometry": {"coordinates":[-2.213969,53.560085],"type":"Point"}
}
