{
  "type": "Feature",
  "properties": {
    "iso:country":"GB",
    "wof:name":"G20 9EZ",
    "wof:placetype":"postalcode"
},
  "geometry": {"coordinates":[-4.27998732545826,55.88980999878805],"type":"Point"}
}