{
  "type": "Feature",
  "properties": {
    "iso:country":"GB",
    "wof:name":"WR2 4QJ",
    "wof:placetype":"postalcode"
},
  "geometry": {"coordinates":[-2.26257055378554,52.15477235661016],"type":"Point"}
}