{
  "type": "Feature",
  "properties": {
    "iso:country":"GB",
    "wof:name":"ME3 7AE",
    "wof:placetype":"postalcode"
},
  "geometry": {"coordinates":[0.45751205127825,51.41387200705505],"type":"Point"}
}