{
  "type": "Feature",
  "properties": {
    "iso:country":"GB",
    "wof:name":"NW4 3RY",
    "wof:placetype":"postalcode"
},
  "geometry": {"coordinates":[-0.23220539192884,51.57939349564741],"type":"Point"}
}