{
  "type": "Feature",
  "properties": {
    "date:inception_lower": "1980-01-01",
    "date:inception_upper": "1980-01-01",
    "iso:country": "GB",
    "wof:name": "BA2 1NH",
    "wof:placetype": "postalcode"
  },
  "geometry": {"coordinates":[-2.39633,51.37296],"type":"Point"}
}
