{
  "type": "Feature",
  "properties": {
    "date:inception_lower": "2010-11-01",
    "date:inception_upper": "2010-11-01",
    "iso:country": "GB",
    "wof:name": "LA14 3JT",
    "wof:placetype": "postalcode"
  },
  "geometry": {"coordinates":[-3.258522,54.104875],"type":"Point"}
}
