{
  "type": "Feature",
  "properties": {
    "date:inception_lower":"2010-11-01",
    "date:inception_upper":"2010-11-30",
    "iso:country":"GB",
    "wof:name":"LA14 3JT",
    "wof:placetype":"postalcode"
},
  "geometry": {"coordinates":[-3.258526,54.104867],"type":"Point"}
}