{
  "type": "Feature",
  "properties": {
    "iso:country":"GB",
    "wof:name":"LA14 3JT",
    "wof:placetype":"postalcode"
},
  "geometry": {"coordinates":[-3.25852581158274,54.10486718225355],"type":"Point"}
}