{
  "type": "Feature",
  "properties": {
    "iso:country": "GB",
    "wof:name": "CO15 3RR",
    "wof:placetype": "postalcode"
  },
  "geometry": {"coordinates":[1.154872,51.801023],"type":"Point"}
}
