{
  "type": "Feature",
  "properties": {
    "iso:country": "GB",
    "wof:name": "SA2 0QY",
    "wof:placetype": "postalcode"
  },
  "geometry": {"coordinates":[-3.965999,51.619647],"type":"Point"}
}
