{
  "type": "Feature",
  "properties": {
    "iso:country":"GB",
    "wof:name":"B60 2DP",
    "wof:placetype":"postalcode"
},
  "geometry": {"coordinates":[-2.0391054681288,52.32900336875192],"type":"Point"}
}