{
  "type": "Feature",
  "properties": {
    "date:inception_lower":"2002-05-01",
    "date:inception_upper":"2002-05-31",
    "iso:country":"GB",
    "wof:name":"B60 2DP",
    "wof:placetype":"postalcode"
},
  "geometry": {"coordinates":[-2.039105,52.329003],"type":"Point"}
}