{
  "type": "Feature",
  "properties": {
    "iso:country":"GB",
    "wof:name":"OL11 3HS",
    "wof:placetype":"postalcode"
},
  "geometry": {"coordinates":[-2.18366558557373,53.59715783581365],"type":"Point"}
}