{
  "type": "Feature",
  "properties": {
    "date:inception_lower": "2019-08-01",
    "date:inception_upper": "2019-08-01",
    "iso:country": "GB",
    "wof:name": "CT6 5FS",
    "wof:placetype": "postalcode"
  },
  "geometry": {"coordinates":[1.115049,51.357103],"type":"Point"}
}
