{
  "type": "Feature",
  "properties": {
    "iso:country":"GB",
    "wof:name":"TW18 4YX",
    "wof:placetype":"postalcode"
},
  "geometry": {"coordinates":[-0.52017855843086,51.44150008703673],"type":"Point"}
}