{
  "type": "Feature",
  "properties": {
    "date:inception_lower":"1980-01-01",
    "date:inception_upper":"1980-01-31",
    "iso:country":"GB",
    "wof:name":"TW18 4YX",
    "wof:placetype":"postalcode"
},
  "geometry": {"coordinates":[-0.520179,51.4415],"type":"Point"}
}