{
  "type": "Feature",
  "properties": {
    "date:inception_lower":"1995-07-01",
    "date:inception_upper":"1995-07-31",
    "iso:country":"GB",
    "wof:name":"WN1 3JB",
    "wof:placetype":"postalcode"
},
  "geometry": {"coordinates":[-2.619161,53.545522],"type":"Point"}
}