{
  "type": "Feature",
  "properties": {
    "iso:country":"GB",
    "wof:name":"WN1 3JB",
    "wof:placetype":"postalcode"
},
  "geometry": {"coordinates":[-2.61916076487602,53.54552248268199],"type":"Point"}
}