{
  "type": "Feature",
  "properties": {
    "date:inception_lower": "1980-01-01",
    "date:inception_upper": "1980-01-01",
    "iso:country": "GB",
    "wof:name": "DE14 2SB",
    "wof:placetype": "postalcode"
  },
  "geometry": {"coordinates":[-1.632619,52.822333],"type":"Point"}
}
