{
  "type": "Feature",
  "properties": {
    "iso:country":"GB",
    "wof:name":"SN10 4HW",
    "wof:placetype":"postalcode"
},
  "geometry": {"coordinates":[-1.99663826802495,51.28355528559261],"type":"Point"}
}