{
  "type": "Feature",
  "properties": {
    "date:inception_lower": "1980-01-01",
    "date:inception_upper": "1980-01-01",
    "iso:country": "GB",
    "wof:name": "SN10 4HW",
    "wof:placetype": "postalcode"
  },
  "geometry": {"coordinates":[-1.996846,51.283443],"type":"Point"}
}
