{
  "type": "Feature",
  "properties": {
    "iso:country":"GB",
    "wof:name":"SK17 0NZ",
    "wof:placetype":"postalcode"
},
  "geometry": {"coordinates":[-1.87029923990685,53.18292761582821],"type":"Point"}
}