{
  "type": "Feature",
  "properties": {
    "date:inception_lower":"1980-01-01",
    "date:inception_upper":"1980-01-31",
    "iso:country":"GB",
    "wof:name":"SK17 0NZ",
    "wof:placetype":"postalcode"
},
  "geometry": {"coordinates":[-1.870299,53.182928],"type":"Point"}
}