{
  "type": "Feature",
  "properties": {
    "iso:country": "GB",
    "wof:name": "YO10 4BD",
    "wof:placetype": "postalcode"
  },
  "geometry": {"coordinates":[-1.074397,53.949822],"type":"Point"}
}
