{
  "type": "Feature",
  "properties": {
    "iso:country":"GB",
    "wof:name":"SW2 2ES",
    "wof:placetype":"postalcode"
},
  "geometry": {"coordinates":[-0.11471168773839,51.44978083371797],"type":"Point"}
}