{
  "type": "Feature",
  "properties": {
    "iso:country": "GB",
    "wof:name": "RG7 4QB",
    "wof:placetype": "postalcode"
  },
  "geometry": {"coordinates":[-1.116943,51.371091],"type":"Point"}
}
