{
  "type": "Feature",
  "properties": {
    "iso:country":"GB",
    "wof:name":"RG7 4QB",
    "wof:placetype":"postalcode"
},
  "geometry": {"coordinates":[-1.11694326131812,51.3710912805833],"type":"Point"}
}