{
  "type": "Feature",
  "properties": {
    "iso:country": "GB",
    "wof:name": "DE12 7DD",
    "wof:placetype": "postalcode"
  },
  "geometry": {"coordinates":[-1.490208,52.682208],"type":"Point"}
}
