{
  "type": "Feature",
  "properties": {
    "iso:country":"GB",
    "wof:name":"DE12 7DD",
    "wof:placetype":"postalcode"
},
  "geometry": {"coordinates":[-1.49020814776608,52.68220756962094],"type":"Point"}
}