{
  "type": "Feature",
  "properties": {
    "iso:country":"GB",
    "wof:name":"E14 7PR",
    "wof:placetype":"postalcode"
},
  "geometry": {"coordinates":[-0.03655992915138,51.5142163316936],"type":"Point"}
}