{
  "type": "Feature",
  "properties": {
    "iso:country":"GB",
    "wof:name":"N15 4LJ",
    "wof:placetype":"postalcode"
},
  "geometry": {"coordinates":[-0.08007684016651,51.58808195693076],"type":"Point"}
}