{
  "type": "Feature",
  "properties": {
    "iso:country":"GB",
    "wof:name":"S6 6TE",
    "wof:placetype":"postalcode"
},
  "geometry": {"coordinates":[-1.52761996827618,53.40552419098416],"type":"Point"}
}