{
  "type": "Feature",
  "properties": {
    "iso:country":"GB",
    "wof:name":"E8 3HS",
    "wof:placetype":"postalcode"
},
  "geometry": {"coordinates":[-0.07198898050279,51.54349037123828],"type":"Point"}
}