{
  "type": "Feature",
  "properties": {
    "date:inception_lower": "1980-01-01",
    "date:inception_upper": "1980-01-01",
    "iso:country": "GB",
    "wof:name": "E8 3HS",
    "wof:placetype": "postalcode"
  },
  "geometry": {"coordinates":[-0.071989,51.54349],"type":"Point"}
}
