{
  "type": "Feature",
  "properties": {
    "iso:country": "GB",
    "wof:name": "AB11 9JX",
    "wof:placetype": "postalcode"
  },
  "geometry": {"coordinates":[-2.079439,57.134709],"type":"Point"}
}
