{
  "type": "Feature",
  "properties": {
    "iso:country":"GB",
    "wof:name":"AB11 9JX",
    "wof:placetype":"postalcode"
},
  "geometry": {"coordinates":[-2.07941412262915,57.13454468154793],"type":"Point"}
}