{
  "type": "Feature",
  "properties": {
    "iso:country":"GB",
    "wof:name":"PR4 2WD",
    "wof:placetype":"postalcode"
},
  "geometry": {"coordinates":[-2.91229563904596,53.77642019516346],"type":"Point"}
}