{
  "type": "Feature",
  "properties": {
    "iso:country": "GB",
    "wof:name": "PR4 2WD",
    "wof:placetype": "postalcode"
  },
  "geometry": {"coordinates":[-2.912296,53.77642],"type":"Point"}
}
