{
  "type": "Feature",
  "properties": {
    "iso:country":"GB",
    "wof:name":"TS26 8NP",
    "wof:placetype":"postalcode"
},
  "geometry": {"coordinates":[-1.22643860841015,54.69022958807093],"type":"Point"}
}