{
  "type": "Feature",
  "properties": {
    "date:inception_lower": "2016-08-01",
    "date:inception_upper": "2016-08-01",
    "iso:country": "GB",
    "wof:name": "SY1 4SY",
    "wof:placetype": "postalcode"
  },
  "geometry": {"coordinates":[-2.723056,52.727229],"type":"Point"}
}
