{
  "type": "Feature",
  "properties": {
    "iso:country":"GB",
    "wof:name":"SG9 0EL",
    "wof:placetype":"postalcode"
},
  "geometry": {"coordinates":[-0.00081252752994,51.96712437091281],"type":"Point"}
}