{
  "type": "Feature",
  "properties": {
    "iso:country":"GB",
    "wof:name":"N1 5PE",
    "wof:placetype":"postalcode"
},
  "geometry": {"coordinates":[-0.08140517417312,51.53563239222895],"type":"Point"}
}