{
  "type": "Feature",
  "properties": {
    "date:inception_lower":"1980-01-01",
    "date:inception_upper":"1980-01-31",
    "iso:country":"GB",
    "wof:name":"N1 5PE",
    "wof:placetype":"postalcode"
},
  "geometry": {"coordinates":[-0.081405,51.535632],"type":"Point"}
}