{
  "type": "Feature",
  "properties": {
    "date:inception_lower":"1980-01-01",
    "date:inception_upper":"1980-01-31",
    "iso:country":"GB",
    "wof:name":"TR1 1EU",
    "wof:placetype":"postalcode"
},
  "geometry": {"coordinates":[-5.050348,50.264921],"type":"Point"}
}