{
  "type": "Feature",
  "properties": {
    "iso:country": "GB",
    "wof:name": "W1F 0JQ",
    "wof:placetype": "postalcode"
  },
  "geometry": {"coordinates":[-0.135847,51.513166],"type":"Point"}
}
