{
  "type": "Feature",
  "properties": {
    "iso:country":"GB",
    "wof:name":"N16 6HR",
    "wof:placetype":"postalcode"
},
  "geometry": {"coordinates":[-0.06404083892053,51.56833175404489],"type":"Point"}
}