{
  "type": "Feature",
  "properties": {
    "date:inception_lower": "1980-01-01",
    "date:inception_upper": "1980-01-01",
    "iso:country": "GB",
    "wof:name": "PA23 7BA",
    "wof:placetype": "postalcode"
  },
  "geometry": {"coordinates":[-4.934665,55.950842],"type":"Point"}
}
