{
  "type": "Feature",
  "properties": {
    "iso:country":"GB",
    "wof:name":"PA23 7BA",
    "wof:placetype":"postalcode"
},
  "geometry": {"coordinates":[-4.93466486102572,55.95084240095184],"type":"Point"}
}