{
  "type": "Feature",
  "properties": {
    "date:inception_lower": "2003-02-01",
    "date:inception_upper": "2003-02-01",
    "iso:country": "GB",
    "wof:name": "BD98 8XX",
    "wof:placetype": "postalcode"
  },
  "geometry": {"coordinates":[-1.779517,53.836791],"type":"Point"}
}
