{
  "type": "Feature",
  "properties": {
    "iso:country":"GB",
    "wof:name":"DT3 6NT",
    "wof:placetype":"postalcode"
},
  "geometry": {"coordinates":[-2.42503021511241,50.64929954897847],"type":"Point"}
}