{
  "type": "Feature",
  "properties": {
    "iso:country":"GB",
    "wof:name":"LA21 8EJ",
    "wof:placetype":"postalcode"
},
  "geometry": {"coordinates":[-3.07175226345901,54.36786117334176],"type":"Point"}
}