{
  "type": "Feature",
  "properties": {
    "iso:country":"GB",
    "wof:name":"NP4 8AB",
    "wof:placetype":"postalcode"
},
  "geometry": {"coordinates":[-3.02065662258216,51.69906650647368],"type":"Point"}
}