{
  "type": "Feature",
  "properties": {
    "iso:country": "GB",
    "wof:name": "G40 3HX",
    "wof:placetype": "postalcode"
  },
  "geometry": {"coordinates":[-4.20703,55.844469],"type":"Point"}
}
