{
  "type": "Feature",
  "properties": {
    "date:inception_lower": "2014-06-01",
    "date:inception_upper": "2014-06-01",
    "iso:country": "GB",
    "wof:name": "G40 3HX",
    "wof:placetype": "postalcode"
  },
  "geometry": {"coordinates":[-4.20703,55.844469],"type":"Point"}
}
