{
  "type": "Feature",
  "properties": {
    "iso:country": "GB",
    "wof:name": "G81 4PA",
    "wof:placetype": "postalcode"
  },
  "geometry": {"coordinates":[-4.43317,55.913337],"type":"Point"}
}
