{
  "type": "Feature",
  "properties": {
    "iso:country":"GB",
    "wof:name":"G81 4PA",
    "wof:placetype":"postalcode"
},
  "geometry": {"coordinates":[-4.43317006068423,55.91333659507313],"type":"Point"}
}