{
  "type": "Feature",
  "properties": {
    "iso:country": "GB",
    "wof:name": "ST3 7NH",
    "wof:placetype": "postalcode"
  },
  "geometry": {"coordinates":[-2.114127,52.949812],"type":"Point"}
}
