{
  "type": "Feature",
  "properties": {
    "iso:country": "GB",
    "wof:name": "NN17 1ST",
    "wof:placetype": "postalcode"
  },
  "geometry": {"coordinates":[-0.684577,52.488925],"type":"Point"}
}
