{
  "type": "Feature",
  "properties": {
    "iso:country":"GB",
    "wof:name":"NN17 1ST",
    "wof:placetype":"postalcode"
},
  "geometry": {"coordinates":[-0.68457748069885,52.48892490262499],"type":"Point"}
}