{
  "type": "Feature",
  "properties": {
    "date:inception_lower":"2015-07-01",
    "date:inception_upper":"2015-07-31",
    "iso:country":"GB",
    "wof:name":"IP11 7FA",
    "wof:placetype":"postalcode"
},
  "geometry": {"coordinates":[1.355792,51.961782],"type":"Point"}
}