{
  "type": "Feature",
  "properties": {
    "iso:country":"GB",
    "wof:name":"LS12 5BU",
    "wof:placetype":"postalcode"
},
  "geometry": {"coordinates":[-1.61600194032224,53.78778151012554],"type":"Point"}
}