{
  "type": "Feature",
  "properties": {
    "iso:country":"GB",
    "wof:name":"LA4 6AJ",
    "wof:placetype":"postalcode"
},
  "geometry": {"coordinates":[-2.83487748885331,54.08167032373031],"type":"Point"}
}