{
  "type": "Feature",
  "properties": {
    "iso:country": "GB",
    "wof:name": "LA4 6AJ",
    "wof:placetype": "postalcode"
  },
  "geometry": {"coordinates":[-2.834876,54.081681],"type":"Point"}
}
