{
  "type": "Feature",
  "properties": {
    "iso:country":"GB",
    "wof:name":"IP22 1SG",
    "wof:placetype":"postalcode"
},
  "geometry": {"coordinates":[1.01726972800753,52.37238530773688],"type":"Point"}
}