{
  "type": "Feature",
  "properties": {
    "iso:country": "GB",
    "wof:name": "PR5 5BJ",
    "wof:placetype": "postalcode"
  },
  "geometry": {"coordinates":[-2.686218,53.726783],"type":"Point"}
}
