{
  "type": "Feature",
  "properties": {
    "iso:country":"GB",
    "wof:name":"PR5 5BJ",
    "wof:placetype":"postalcode"
},
  "geometry": {"coordinates":[-2.68622164349934,53.72680274285965],"type":"Point"}
}