{
  "type": "Feature",
  "properties": {
    "iso:country": "GB",
    "wof:name": "SA31 3AF",
    "wof:placetype": "postalcode"
  },
  "geometry": {"coordinates":[-4.334327,51.850939],"type":"Point"}
}
