{
  "type": "Feature",
  "properties": {
    "date:inception_lower":"2015-08-01",
    "date:inception_upper":"2015-08-31",
    "iso:country":"GB",
    "wof:name":"SA31 3AF",
    "wof:placetype":"postalcode"
},
  "geometry": {"coordinates":[-4.334327,51.850939],"type":"Point"}
}