{
  "type": "Feature",
  "properties": {
    "iso:country":"GB",
    "wof:name":"SA31 3AF",
    "wof:placetype":"postalcode"
},
  "geometry": {"coordinates":[-4.33432715035894,51.85093860860348],"type":"Point"}
}