{
  "type": "Feature",
  "properties": {
    "iso:country":"GB",
    "wof:name":"PL13 2PY",
    "wof:placetype":"postalcode"
},
  "geometry": {"coordinates":[-4.56017729761173,50.3473543469838],"type":"Point"}
}