{
  "type": "Feature",
  "properties": {
    "iso:country":"GB",
    "wof:name":"CW7 4AT",
    "wof:placetype":"postalcode"
},
  "geometry": {"coordinates":[-2.52346919598737,53.18678173835671],"type":"Point"}
}