{
  "type": "Feature",
  "properties": {
    "date:inception_lower": "1980-01-01",
    "date:inception_upper": "1980-01-01",
    "iso:country": "GB",
    "wof:name": "CW7 4AT",
    "wof:placetype": "postalcode"
  },
  "geometry": {"coordinates":[-2.523469,53.186782],"type":"Point"}
}
