{
  "type": "Feature",
  "properties": {
    "iso:country":"GB",
    "wof:name":"DN21 1UF",
    "wof:placetype":"postalcode"
},
  "geometry": {"coordinates":[-0.75759482567997,53.3961943936476],"type":"Point"}
}