{
  "type": "Feature",
  "properties": {
    "date:inception_lower": "1980-01-01",
    "date:inception_upper": "1980-01-01",
    "iso:country": "GB",
    "wof:name": "DN21 1UF",
    "wof:placetype": "postalcode"
  },
  "geometry": {"coordinates":[-0.757595,53.396194],"type":"Point"}
}
