{
  "type": "Feature",
  "properties": {
    "iso:country": "GB",
    "wof:name": "DN21 1UF",
    "wof:placetype": "postalcode"
  },
  "geometry": {"coordinates":[-0.757595,53.396194],"type":"Point"}
}
