{
  "type": "Feature",
  "properties": {
    "iso:country":"GB",
    "wof:name":"PO6 3PP",
    "wof:placetype":"postalcode"
},
  "geometry": {"coordinates":[-1.08790162381272,50.84957589016466],"type":"Point"}
}