{
  "type": "Feature",
  "properties": {
    "iso:country": "GB",
    "wof:name": "ME16 0JA",
    "wof:placetype": "postalcode"
  },
  "geometry": {"coordinates":[0.502875,51.27504],"type":"Point"}
}
