{
  "type": "Feature",
  "properties": {
    "date:inception_lower":"1980-01-01",
    "date:inception_upper":"1980-01-31",
    "iso:country":"GB",
    "wof:name":"ME16 0JA",
    "wof:placetype":"postalcode"
},
  "geometry": {"coordinates":[0.502875,51.27504],"type":"Point"}
}