{
  "type": "Feature",
  "properties": {
    "date:inception_lower": "1980-01-01",
    "date:inception_upper": "1980-01-01",
    "iso:country": "GB",
    "wof:name": "YO7 1AZ",
    "wof:placetype": "postalcode"
  },
  "geometry": {"coordinates":[-1.340627,54.237966],"type":"Point"}
}
