{
  "type": "Feature",
  "properties": {
    "iso:country":"GB",
    "wof:name":"YO7 1AZ",
    "wof:placetype":"postalcode"
},
  "geometry": {"coordinates":[-1.34064907050615,54.23797032328358],"type":"Point"}
}