{
  "type": "Feature",
  "properties": {
    "date:inception_lower": "1980-01-01",
    "date:inception_upper": "1980-01-01",
    "iso:country": "GB",
    "wof:name": "ME15 0JY",
    "wof:placetype": "postalcode"
  },
  "geometry": {"coordinates":[0.468752,51.255574],"type":"Point"}
}
