{
  "type": "Feature",
  "properties": {
    "iso:country":"GB",
    "wof:name":"ME15 0JY",
    "wof:placetype":"postalcode"
},
  "geometry": {"coordinates":[0.46875208385834,51.25557415007874],"type":"Point"}
}