{
  "type": "Feature",
  "properties": {
    "date:inception_lower": "2001-06-01",
    "date:inception_upper": "2001-06-01",
    "iso:country": "GB",
    "wof:name": "GU51 3BT",
    "wof:placetype": "postalcode"
  },
  "geometry": {"coordinates":[-0.843687,51.279656],"type":"Point"}
}
