{
  "type": "Feature",
  "properties": {
    "iso:country": "GB",
    "wof:name": "B4 6GA",
    "wof:placetype": "postalcode"
  },
  "geometry": {"coordinates":[-1.89842,52.483727],"type":"Point"}
}
