{
  "type": "Feature",
  "properties": {
    "date:inception_lower":"2010-09-01",
    "date:inception_upper":"2010-09-30",
    "iso:country":"GB",
    "wof:name":"B4 6GA",
    "wof:placetype":"postalcode"
},
  "geometry": {"coordinates":[-1.89842,52.483727],"type":"Point"}
}