{
  "type": "Feature",
  "properties": {
    "iso:country":"GB",
    "wof:name":"NG32 1AQ",
    "wof:placetype":"postalcode"
},
  "geometry": {"coordinates":[-0.69084757514491,52.87251038721413],"type":"Point"}
}