{
  "type": "Feature",
  "properties": {
    "iso:country": "GB",
    "wof:name": "IG1 4BT",
    "wof:placetype": "postalcode"
  },
  "geometry": {"coordinates":[0.074949,51.560462],"type":"Point"}
}
