{
  "type": "Feature",
  "properties": {
    "iso:country":"GB",
    "wof:name":"IG1 4BT",
    "wof:placetype":"postalcode"
},
  "geometry": {"coordinates":[0.07494883835007,51.56046159286544],"type":"Point"}
}