{
  "type": "Feature",
  "properties": {
    "iso:country": "GB",
    "wof:name": "DY10 2RE",
    "wof:placetype": "postalcode"
  },
  "geometry": {"coordinates":[-2.237037,52.393941],"type":"Point"}
}
