{
  "type": "Feature",
  "properties": {
    "iso:country":"GB",
    "wof:name":"DY10 2RE",
    "wof:placetype":"postalcode"
},
  "geometry": {"coordinates":[-2.23703752887232,52.39394128155234],"type":"Point"}
}