{
  "type": "Feature",
  "properties": {
    "iso:country":"GB",
    "wof:name":"HP19 8BB",
    "wof:placetype":"postalcode"
},
  "geometry": {"coordinates":[-0.83319086297558,51.82155964314614],"type":"Point"}
}