{
  "type": "Feature",
  "properties": {
    "iso:country": "GB",
    "wof:name": "GU16 6EP",
    "wof:placetype": "postalcode"
  },
  "geometry": {"coordinates":[-0.72628,51.295532],"type":"Point"}
}
