{
  "type": "Feature",
  "properties": {
    "iso:country":"GB",
    "wof:name":"GU16 6EP",
    "wof:placetype":"postalcode"
},
  "geometry": {"coordinates":[-0.7262801662192,51.29553176143556],"type":"Point"}
}