{
  "type": "Feature",
  "properties": {
    "date:inception_lower": "1980-01-01",
    "date:inception_upper": "1980-01-01",
    "iso:country": "GB",
    "wof:name": "EH14 6AQ",
    "wof:placetype": "postalcode"
  },
  "geometry": {"coordinates":[-3.298737,55.89322],"type":"Point"}
}
