{
  "type": "Feature",
  "properties": {
    "iso:country":"GB",
    "wof:name":"EH14 6AQ",
    "wof:placetype":"postalcode"
},
  "geometry": {"coordinates":[-3.29873736420763,55.89321969492367],"type":"Point"}
}