{
  "type": "Feature",
  "properties": {
    "iso:country":"GB",
    "wof:name":"PA17 5DT",
    "wof:placetype":"postalcode"
},
  "geometry": {"coordinates":[-4.88911758948571,55.86890561785506],"type":"Point"}
}