{
  "type": "Feature",
  "properties": {
    "iso:country":"GB",
    "wof:name":"SL7 2AE",
    "wof:placetype":"postalcode"
},
  "geometry": {"coordinates":[-0.77696486670967,51.56773902570427],"type":"Point"}
}