{
  "type": "Feature",
  "properties": {
    "iso:country":"GB",
    "wof:name":"OL11 5YY",
    "wof:placetype":"postalcode"
},
  "geometry": {"coordinates":[-2.19082243176762,53.62279909813691],"type":"Point"}
}