{
  "type": "Feature",
  "properties": {
    "iso:country":"GB",
    "wof:name":"LE12 5EP",
    "wof:placetype":"postalcode"
},
  "geometry": {"coordinates":[-1.20336593299252,52.82306153832443],"type":"Point"}
}