{
  "type": "Feature",
  "properties": {
    "iso:country": "GB",
    "wof:name": "SM7 1RR",
    "wof:placetype": "postalcode"
  },
  "geometry": {"coordinates":[-0.212663,51.327325],"type":"Point"}
}
