{
  "type": "Feature",
  "properties": {
    "date:inception_lower":"1980-01-01",
    "date:inception_upper":"1980-01-31",
    "iso:country":"GB",
    "wof:name":"SM7 1RR",
    "wof:placetype":"postalcode"
},
  "geometry": {"coordinates":[-0.212663,51.327325],"type":"Point"}
}