{
  "type": "Feature",
  "properties": {
    "iso:country":"GB",
    "wof:name":"SE3 9SF",
    "wof:placetype":"postalcode"
},
  "geometry": {"coordinates":[0.01700220742851,51.46569991010474],"type":"Point"}
}