{
  "type": "Feature",
  "properties": {
    "iso:country": "GB",
    "wof:name": "EX2 9TR",
    "wof:placetype": "postalcode"
  },
  "geometry": {"coordinates":[-3.574419,50.677783],"type":"Point"}
}
