{
  "type": "Feature",
  "properties": {
    "date:inception_lower": "1980-01-01",
    "date:inception_upper": "1980-01-01",
    "iso:country": "GB",
    "wof:name": "EX2 9TR",
    "wof:placetype": "postalcode"
  },
  "geometry": {"coordinates":[-3.576857,50.678684],"type":"Point"}
}
