{
  "type": "Feature",
  "properties": {
    "iso:country":"GB",
    "wof:name":"EX2 9TR",
    "wof:placetype":"postalcode"
},
  "geometry": {"coordinates":[-3.5744193833935,50.67778346421274],"type":"Point"}
}