{
  "type": "Feature",
  "properties": {
    "iso:country":"GB",
    "wof:name":"SM4 5PX",
    "wof:placetype":"postalcode"
},
  "geometry": {"coordinates":[-0.2030269855111,51.39278813616077],"type":"Point"}
}