{
  "type": "Feature",
  "properties": {
    "iso:country": "GB",
    "wof:name": "PH33 6GA",
    "wof:placetype": "postalcode"
  },
  "geometry": {"coordinates":[-5.11383,56.811506],"type":"Point"}
}
