{
  "type": "Feature",
  "properties": {
    "iso:country":"GB",
    "wof:name":"PH33 6GA",
    "wof:placetype":"postalcode"
},
  "geometry": {"coordinates":[-5.11384434273943,56.81152245824978],"type":"Point"}
}