{
  "type": "Feature",
  "properties": {
    "iso:country": "GB",
    "wof:name": "PH33 6GA",
    "wof:placetype": "postalcode"
  },
  "geometry": {"coordinates":[-5.113355,56.811706],"type":"Point"}
}
