{
  "type": "Feature",
  "properties": {
    "date:inception_lower": "2010-08-01",
    "date:inception_upper": "2010-08-01",
    "iso:country": "GB",
    "wof:name": "PH33 6GA",
    "wof:placetype": "postalcode"
  },
  "geometry": {"coordinates":[-5.113355,56.811706],"type":"Point"}
}
