{
  "type": "Feature",
  "properties": {
    "date:inception_lower": "1980-01-01",
    "date:inception_upper": "1980-01-01",
    "iso:country": "GB",
    "wof:name": "NG7 7GB",
    "wof:placetype": "postalcode"
  },
  "geometry": {"coordinates":[-1.170946,52.975287],"type":"Point"}
}
