{
  "type": "Feature",
  "properties": {
    "date:inception_lower": "1980-01-01",
    "date:inception_upper": "1980-01-01",
    "iso:country": "GB",
    "wof:name": "SY3 9DG",
    "wof:placetype": "postalcode"
  },
  "geometry": {"coordinates":[-2.770233,52.695991],"type":"Point"}
}
