{
  "type": "Feature",
  "properties": {
    "iso:country": "GB",
    "wof:name": "SY3 9DG",
    "wof:placetype": "postalcode"
  },
  "geometry": {"coordinates":[-2.770233,52.695991],"type":"Point"}
}
