{
  "type": "Feature",
  "properties": {
    "iso:country":"GB",
    "wof:name":"LL68 9UD",
    "wof:placetype":"postalcode"
},
  "geometry": {"coordinates":[-4.36988234698882,53.3678504599836],"type":"Point"}
}