{
  "type": "Feature",
  "properties": {
    "iso:country":"GB",
    "wof:name":"CR2 0LD",
    "wof:placetype":"postalcode"
},
  "geometry": {"coordinates":[-0.08022651354733,51.34269317937856],"type":"Point"}
}