{
  "type": "Feature",
  "properties": {
    "iso:country": "GB",
    "wof:name": "M11 3AJ",
    "wof:placetype": "postalcode"
  },
  "geometry": {"coordinates":[-2.194487,53.47613],"type":"Point"}
}
