{
  "type": "Feature",
  "properties": {
    "iso:country":"GB",
    "wof:name":"CA14 4LL",
    "wof:placetype":"postalcode"
},
  "geometry": {"coordinates":[-3.5503300933058,54.61447831545957],"type":"Point"}
}