{
  "type": "Feature",
  "properties": {
    "iso:country":"GB",
    "wof:name":"MK4 1AX",
    "wof:placetype":"postalcode"
},
  "geometry": {"coordinates":[-0.75535705018401,52.01268166962014],"type":"Point"}
}