{
  "type": "Feature",
  "properties": {
    "iso:country": "GB",
    "wof:name": "MK4 1AX",
    "wof:placetype": "postalcode"
  },
  "geometry": {"coordinates":[-0.755357,52.012682],"type":"Point"}
}
