{
  "type": "Feature",
  "properties": {
    "date:inception_lower":"1994-12-01",
    "date:inception_upper":"1994-12-31",
    "iso:country":"GB",
    "wof:name":"CV11 6LT",
    "wof:placetype":"postalcode"
},
  "geometry": {"coordinates":[-1.442484,52.534793],"type":"Point"}
}