{
  "type": "Feature",
  "properties": {
    "iso:country":"GB",
    "wof:name":"NE3 3LJ",
    "wof:placetype":"postalcode"
},
  "geometry": {"coordinates":[-1.65510460968865,55.00752252140001],"type":"Point"}
}