{
  "type": "Feature",
  "properties": {
    "date:inception_lower":"1980-01-01",
    "date:inception_upper":"1980-01-31",
    "iso:country":"GB",
    "wof:name":"NE3 3LJ",
    "wof:placetype":"postalcode"
},
  "geometry": {"coordinates":[-1.655105,55.007523],"type":"Point"}
}