{
  "type": "Feature",
  "properties": {
    "iso:country":"GB",
    "wof:name":"PR5 4QD",
    "wof:placetype":"postalcode"
},
  "geometry": {"coordinates":[-2.67362575248513,53.74191155876743],"type":"Point"}
}