{
  "type": "Feature",
  "properties": {
    "iso:country": "GB",
    "wof:name": "PL19 8SA",
    "wof:placetype": "postalcode"
  },
  "geometry": {"coordinates":[-4.20423,50.570289],"type":"Point"}
}
