{
  "type": "Feature",
  "properties": {
    "iso:country":"GB",
    "wof:name":"PL19 8SA",
    "wof:placetype":"postalcode"
},
  "geometry": {"coordinates":[-4.20477198331533,50.56952348585199],"type":"Point"}
}