{
  "type": "Feature",
  "properties": {
    "date:inception_lower": "2016-06-01",
    "date:inception_upper": "2016-06-01",
    "iso:country": "GB",
    "wof:name": "BS31 2FQ",
    "wof:placetype": "postalcode"
  },
  "geometry": {"coordinates":[-2.51532,51.403024],"type":"Point"}
}
