{
  "type": "Feature",
  "properties": {
    "date:inception_lower": "2018-01-01",
    "date:inception_upper": "2018-01-01",
    "iso:country": "GB",
    "wof:name": "DN33 3TL",
    "wof:placetype": "postalcode"
  },
  "geometry": {"coordinates":[-0.105605,53.538136],"type":"Point"}
}
