{
  "type": "Feature",
  "properties": {
    "iso:country": "GB",
    "wof:name": "LL15 2HN",
    "wof:placetype": "postalcode"
  },
  "geometry": {"coordinates":[-3.244105,53.057385],"type":"Point"}
}
