{
  "type": "Feature",
  "properties": {
    "iso:country":"GB",
    "wof:name":"LL15 2HN",
    "wof:placetype":"postalcode"
},
  "geometry": {"coordinates":[-3.24410435207607,53.05736003209944],"type":"Point"}
}