{
  "type": "Feature",
  "properties": {
    "iso:country":"GB",
    "wof:name":"MK41 0UA",
    "wof:placetype":"postalcode"
},
  "geometry": {"coordinates":[-0.42204874390501,52.14275965669284],"type":"Point"}
}