{
  "type": "Feature",
  "properties": {
    "date:inception_lower": "1995-01-01",
    "date:inception_upper": "1995-01-01",
    "iso:country": "GB",
    "wof:name": "MK41 0UA",
    "wof:placetype": "postalcode"
  },
  "geometry": {"coordinates":[-0.422049,52.14276],"type":"Point"}
}
