{
  "type": "Feature",
  "properties": {
    "iso:country":"GB",
    "wof:name":"CF15 7SY",
    "wof:placetype":"postalcode"
},
  "geometry": {"coordinates":[-3.27199533986962,51.56154801667709],"type":"Point"}
}