{
  "type": "Feature",
  "properties": {
    "date:inception_lower": "2022-02-01",
    "date:inception_upper": "2022-02-01",
    "iso:country": "GB",
    "wof:name": "BN24 6BF",
    "wof:placetype": "postalcode"
  },
  "geometry": {"coordinates":[0.335194,50.805422],"type":"Point"}
}
