{
  "type": "Feature",
  "properties": {
    "iso:country":"GB",
    "wof:name":"DY2 0JQ",
    "wof:placetype":"postalcode"
},
  "geometry": {"coordinates":[-2.08739989559361,52.48602496438708],"type":"Point"}
}