{
  "type": "Feature",
  "properties": {
    "iso:country": "GB",
    "wof:name": "AB21 0NS",
    "wof:placetype": "postalcode"
  },
  "geometry": {"coordinates":[-2.188422,57.268445],"type":"Point"}
}
