{
  "type": "Feature",
  "properties": {
    "iso:country":"GB",
    "wof:name":"DE22 2DY",
    "wof:placetype":"postalcode"
},
  "geometry": {"coordinates":[-1.48279172161126,52.95404610944964],"type":"Point"}
}