{
  "type": "Feature",
  "properties": {
    "iso:country": "GB",
    "wof:name": "AB31 6JA",
    "wof:placetype": "postalcode"
  },
  "geometry": {"coordinates":[-2.438733,57.052962],"type":"Point"}
}
