{
  "type": "Feature",
  "properties": {
    "iso:country":"GB",
    "wof:name":"SW18 2NF",
    "wof:placetype":"postalcode"
},
  "geometry": {"coordinates":[-0.18620249036853,51.45472159445951],"type":"Point"}
}