{
  "type": "Feature",
  "properties": {
    "date:inception_lower": "1980-01-01",
    "date:inception_upper": "1980-01-01",
    "iso:country": "GB",
    "wof:name": "SW18 2NF",
    "wof:placetype": "postalcode"
  },
  "geometry": {"coordinates":[-0.186276,51.454777],"type":"Point"}
}
