{
  "type": "Feature",
  "properties": {
    "date:inception_lower": "1980-01-01",
    "date:inception_upper": "1980-01-01",
    "iso:country": "GB",
    "wof:name": "WA6 8JN",
    "wof:placetype": "postalcode"
  },
  "geometry": {"coordinates":[-2.657599,53.248105],"type":"Point"}
}
