{
  "type": "Feature",
  "properties": {
    "date:inception_lower": "1990-07-01",
    "date:inception_upper": "1990-07-01",
    "iso:country": "GB",
    "wof:name": "BN41 2HL",
    "wof:placetype": "postalcode"
  },
  "geometry": {"coordinates":[-0.219716,50.845569],"type":"Point"}
}
