{
  "type": "Feature",
  "properties": {
    "iso:country":"GB",
    "wof:name":"BN41 2HL",
    "wof:placetype":"postalcode"
},
  "geometry": {"coordinates":[-0.21971616295394,50.84556894982492],"type":"Point"}
}