{
  "type": "Feature",
  "properties": {
    "date:inception_lower":"1980-01-01",
    "date:inception_upper":"1980-01-31",
    "iso:country":"GB",
    "wof:name":"SK15 3DA",
    "wof:placetype":"postalcode"
},
  "geometry": {"coordinates":[-2.047981,53.491614],"type":"Point"}
}