{
  "type": "Feature",
  "properties": {
    "iso:country": "GB",
    "wof:name": "SW19 3HN",
    "wof:placetype": "postalcode"
  },
  "geometry": {"coordinates":[-0.207338,51.41083],"type":"Point"}
}
