{
  "type": "Feature",
  "properties": {
    "iso:country":"GB",
    "wof:name":"SW19 3HN",
    "wof:placetype":"postalcode"
},
  "geometry": {"coordinates":[-0.20733819813519,51.410830352217],"type":"Point"}
}