{
  "type": "Feature",
  "properties": {
    "date:inception_lower": "2020-04-01",
    "date:inception_upper": "2020-04-01",
    "iso:country": "GB",
    "wof:name": "WS12 4WU",
    "wof:placetype": "postalcode"
  },
  "geometry": {"coordinates":[-2.022398,52.72173],"type":"Point"}
}
