{
  "type": "Feature",
  "properties": {
    "date:inception_lower":"1992-01-01",
    "date:inception_upper":"1992-01-31",
    "iso:country":"GB",
    "wof:name":"SN3 1NQ",
    "wof:placetype":"postalcode"
},
  "geometry": {"coordinates":[-1.755923,51.538313],"type":"Point"}
}