{
  "type": "Feature",
  "properties": {
    "iso:country": "GB",
    "wof:name": "SN3 1NQ",
    "wof:placetype": "postalcode"
  },
  "geometry": {"coordinates":[-1.755923,51.538313],"type":"Point"}
}
