{
  "type": "Feature",
  "properties": {
    "iso:country":"GB",
    "wof:name":"N16 9BG",
    "wof:placetype":"postalcode"
},
  "geometry": {"coordinates":[-0.08866851307685,51.55568738335609],"type":"Point"}
}