{
  "type": "Feature",
  "properties": {
    "iso:country":"GB",
    "wof:name":"BA3 2SD",
    "wof:placetype":"postalcode"
},
  "geometry": {"coordinates":[-2.49199304236987,51.29224081995874],"type":"Point"}
}