{
  "type": "Feature",
  "properties": {
    "date:inception_lower": "1996-06-01",
    "date:inception_upper": "1996-06-01",
    "iso:country": "GB",
    "wof:name": "BA3 2SD",
    "wof:placetype": "postalcode"
  },
  "geometry": {"coordinates":[-2.491993,51.292241],"type":"Point"}
}
