{
  "type": "Feature",
  "properties": {
    "iso:country":"GB",
    "wof:name":"CF38 2HR",
    "wof:placetype":"postalcode"
},
  "geometry": {"coordinates":[-3.33978682400533,51.55473283532784],"type":"Point"}
}