{
  "type": "Feature",
  "properties": {
    "iso:country": "GB",
    "wof:name": "NG16 2UW",
    "wof:placetype": "postalcode"
  },
  "geometry": {"coordinates":[-1.29562,53.005016],"type":"Point"}
}
