{
  "type": "Feature",
  "properties": {
    "iso:country":"GB",
    "wof:name":"NE23 8JS",
    "wof:placetype":"postalcode"
},
  "geometry": {"coordinates":[-1.61531026782791,55.08622985345744],"type":"Point"}
}