{
  "type": "Feature",
  "properties": {
    "date:inception_lower": "1988-03-01",
    "date:inception_upper": "1988-03-01",
    "iso:country": "GB",
    "wof:name": "NE23 8JS",
    "wof:placetype": "postalcode"
  },
  "geometry": {"coordinates":[-1.61531,55.08623],"type":"Point"}
}
