{
  "type": "Feature",
  "properties": {
    "iso:country": "GB",
    "wof:name": "EN7 5SR",
    "wof:placetype": "postalcode"
  },
  "geometry": {"coordinates":[-0.090973,51.712696],"type":"Point"}
}
