{
  "type": "Feature",
  "properties": {
    "iso:country":"GB",
    "wof:name":"EN7 5SR",
    "wof:placetype":"postalcode"
},
  "geometry": {"coordinates":[-0.09097323580318,51.71269620697445],"type":"Point"}
}