{
  "type": "Feature",
  "properties": {
    "date:inception_lower": "1980-01-01",
    "date:inception_upper": "1980-01-01",
    "iso:country": "GB",
    "wof:name": "W13 9SH",
    "wof:placetype": "postalcode"
  },
  "geometry": {"coordinates":[-0.316688,51.500622],"type":"Point"}
}
