{
  "type": "Feature",
  "properties": {
    "iso:country":"GB",
    "wof:name":"W13 9SH",
    "wof:placetype":"postalcode"
},
  "geometry": {"coordinates":[-0.31668804872103,51.50062238149608],"type":"Point"}
}