{
  "type": "Feature",
  "properties": {
    "iso:country":"GB",
    "wof:name":"S43 3NE",
    "wof:placetype":"postalcode"
},
  "geometry": {"coordinates":[-1.3590422680662,53.25741193971175],"type":"Point"}
}