{
  "type": "Feature",
  "properties": {
    "iso:country":"GB",
    "wof:name":"TR20 9SA",
    "wof:placetype":"postalcode"
},
  "geometry": {"coordinates":[-5.37973379757156,50.12582167112718],"type":"Point"}
}