{
  "type": "Feature",
  "properties": {
    "iso:country": "GB",
    "wof:name": "TR20 9SA",
    "wof:placetype": "postalcode"
  },
  "geometry": {"coordinates":[-5.379734,50.125822],"type":"Point"}
}
