{
  "type": "Feature",
  "properties": {
    "date:inception_lower": "2016-02-01",
    "date:inception_upper": "2016-02-01",
    "iso:country": "GB",
    "wof:name": "NW6 5FT",
    "wof:placetype": "postalcode"
  },
  "geometry": {"coordinates":[-0.202547,51.53399],"type":"Point"}
}
