{
  "type": "Feature",
  "properties": {
    "iso:country":"GB",
    "wof:name":"SA7 9GF",
    "wof:placetype":"postalcode"
},
  "geometry": {"coordinates":[-3.90129411477018,51.66518973123362],"type":"Point"}
}