{
  "type": "Feature",
  "properties": {
    "date:inception_lower": "1980-01-01",
    "date:inception_upper": "1980-01-01",
    "iso:country": "GB",
    "wof:name": "PE21 8PE",
    "wof:placetype": "postalcode"
  },
  "geometry": {"coordinates":[-0.035023,52.980429],"type":"Point"}
}
