{
  "type": "Feature",
  "properties": {
    "iso:country":"GB",
    "wof:name":"PE21 8PE",
    "wof:placetype":"postalcode"
},
  "geometry": {"coordinates":[-0.03502298804053,52.98042946658335],"type":"Point"}
}