{
  "type": "Feature",
  "properties": {
    "iso:country": "GB",
    "wof:name": "OX28 1JR",
    "wof:placetype": "postalcode"
  },
  "geometry": {"coordinates":[-1.487682,51.797594],"type":"Point"}
}
