{
  "type": "Feature",
  "properties": {
    "iso:country": "GB",
    "wof:name": "CH2 4DS",
    "wof:placetype": "postalcode"
  },
  "geometry": {"coordinates":[-2.831717,53.223456],"type":"Point"}
}
