{
  "type": "Feature",
  "properties": {
    "date:inception_lower":"2001-12-01",
    "date:inception_upper":"2001-12-31",
    "iso:country":"GB",
    "wof:name":"SG11 2JD",
    "wof:placetype":"postalcode"
},
  "geometry": {"coordinates":[0.093917,51.903449],"type":"Point"}
}