{
  "type": "Feature",
  "properties": {
    "iso:country":"GB",
    "wof:name":"SG11 2JD",
    "wof:placetype":"postalcode"
},
  "geometry": {"coordinates":[0.09391699237015,51.90344924240017],"type":"Point"}
}