{
  "type": "Feature",
  "properties": {
    "iso:country": "GB",
    "wof:name": "SG11 2JD",
    "wof:placetype": "postalcode"
  },
  "geometry": {"coordinates":[0.093917,51.903449],"type":"Point"}
}
