{
  "type": "Feature",
  "properties": {
    "date:inception_lower": "2007-03-01",
    "date:inception_upper": "2007-03-01",
    "iso:country": "GB",
    "wof:name": "WF9 1FE",
    "wof:placetype": "postalcode"
  },
  "geometry": {"coordinates":[-1.279105,53.613942],"type":"Point"}
}
