{
  "type": "Feature",
  "properties": {
    "iso:country": "GB",
    "wof:name": "WF9 1FE",
    "wof:placetype": "postalcode"
  },
  "geometry": {"coordinates":[-1.279105,53.613942],"type":"Point"}
}
