{
  "type": "Feature",
  "properties": {
    "iso:country":"GB",
    "wof:name":"WF9 1FE",
    "wof:placetype":"postalcode"
},
  "geometry": {"coordinates":[-1.27910503620044,53.61394216353804],"type":"Point"}
}