{
  "type": "Feature",
  "properties": {
    "iso:country":"GB",
    "wof:name":"M41 5SU",
    "wof:placetype":"postalcode"
},
  "geometry": {"coordinates":[-2.36541450096882,53.45108307974873],"type":"Point"}
}