{
  "type": "Feature",
  "properties": {
    "iso:country":"GB",
    "wof:name":"SE7 8HS",
    "wof:placetype":"postalcode"
},
  "geometry": {"coordinates":[0.0453446780247,51.48423757818481],"type":"Point"}
}