{
  "type": "Feature",
  "properties": {
    "iso:country":"GB",
    "wof:name":"PE3 9XL",
    "wof:placetype":"postalcode"
},
  "geometry": {"coordinates":[-0.28640488189244,52.5833395692876],"type":"Point"}
}