{
  "type": "Feature",
  "properties": {
    "iso:country":"GB",
    "wof:name":"BS8 1TQ",
    "wof:placetype":"postalcode"
},
  "geometry": {"coordinates":[-2.60127741380542,51.45921103892583],"type":"Point"}
}