{
  "type": "Feature",
  "properties": {
    "date:inception_lower": "1980-01-01",
    "date:inception_upper": "1980-01-01",
    "iso:country": "GB",
    "wof:name": "BS8 1TQ",
    "wof:placetype": "postalcode"
  },
  "geometry": {"coordinates":[-2.601277,51.459211],"type":"Point"}
}
