{
  "type": "Feature",
  "properties": {
    "date:inception_lower": "1992-08-01",
    "date:inception_upper": "1992-08-01",
    "iso:country": "GB",
    "wof:name": "CR4 3SD",
    "wof:placetype": "postalcode"
  },
  "geometry": {"coordinates":[-0.172232,51.410954],"type":"Point"}
}
