{
  "type": "Feature",
  "properties": {
    "iso:country":"GB",
    "wof:name":"CR4 3SD",
    "wof:placetype":"postalcode"
},
  "geometry": {"coordinates":[-0.17223243701302,51.41095354791093],"type":"Point"}
}