{
  "type": "Feature",
  "properties": {
    "iso:country": "GB",
    "wof:name": "BH24 3DR",
    "wof:placetype": "postalcode"
  },
  "geometry": {"coordinates":[-1.766586,50.841871],"type":"Point"}
}
