{
  "type": "Feature",
  "properties": {
    "iso:country":"GB",
    "wof:name":"GL4 3GB",
    "wof:placetype":"postalcode"
},
  "geometry": {"coordinates":[-2.20460587416577,51.8558835777577],"type":"Point"}
}