{
  "type": "Feature",
  "properties": {
    "iso:country": "GB",
    "wof:name": "GL4 3GB",
    "wof:placetype": "postalcode"
  },
  "geometry": {"coordinates":[-2.204606,51.855884],"type":"Point"}
}
