{
  "type": "Feature",
  "properties": {
    "iso:country":"GB",
    "wof:name":"KT5 9JP",
    "wof:placetype":"postalcode"
},
  "geometry": {"coordinates":[-0.27940899103174,51.38592223245831],"type":"Point"}
}