{
  "type": "Feature",
  "properties": {
    "date:inception_lower": "1994-12-01",
    "date:inception_upper": "1994-12-01",
    "iso:country": "GB",
    "wof:name": "NN10 0QG",
    "wof:placetype": "postalcode"
  },
  "geometry": {"coordinates":[-0.587891,52.2871],"type":"Point"}
}
