{
  "type": "Feature",
  "properties": {
    "iso:country": "GB",
    "wof:name": "CV23 0LA",
    "wof:placetype": "postalcode"
  },
  "geometry": {"coordinates":[-1.376465,52.389326],"type":"Point"}
}
