{
  "type": "Feature",
  "properties": {
    "iso:country":"GB",
    "wof:name":"CV23 0LA",
    "wof:placetype":"postalcode"
},
  "geometry": {"coordinates":[-1.37662291125345,52.38928280936548],"type":"Point"}
}