{
  "type": "Feature",
  "properties": {
    "iso:country":"GB",
    "wof:name":"RG14 7WE",
    "wof:placetype":"postalcode"
},
  "geometry": {"coordinates":[-1.30556576145365,51.39216050133683],"type":"Point"}
}