{
  "type": "Feature",
  "properties": {
    "date:inception_lower":"2005-07-01",
    "date:inception_upper":"2005-07-31",
    "iso:country":"GB",
    "wof:name":"RG14 7WE",
    "wof:placetype":"postalcode"
},
  "geometry": {"coordinates":[-1.305566,51.39216],"type":"Point"}
}