{
  "type": "Feature",
  "properties": {
    "date:inception_lower": "1997-06-01",
    "date:inception_upper": "1997-06-01",
    "iso:country": "GB",
    "wof:name": "LE2 4EE",
    "wof:placetype": "postalcode"
  },
  "geometry": {"coordinates":[-1.077873,52.606243],"type":"Point"}
}
