{
  "type": "Feature",
  "properties": {
    "iso:country":"GB",
    "wof:name":"LE2 4EE",
    "wof:placetype":"postalcode"
},
  "geometry": {"coordinates":[-1.07787340703939,52.60624262889054],"type":"Point"}
}