{
  "type": "Feature",
  "properties": {
    "iso:country":"GB",
    "wof:name":"HG1 4BQ",
    "wof:placetype":"postalcode"
},
  "geometry": {"coordinates":[-1.52778307017238,53.99873644569927],"type":"Point"}
}