{
  "type": "Feature",
  "properties": {
    "iso:country":"GB",
    "wof:name":"SA11 2HL",
    "wof:placetype":"postalcode"
},
  "geometry": {"coordinates":[-3.8192045736905,51.64753474669699],"type":"Point"}
}