{
  "type": "Feature",
  "properties": {
    "date:inception_lower": "2009-10-01",
    "date:inception_upper": "2009-10-01",
    "iso:country": "GB",
    "wof:name": "PR4 3EN",
    "wof:placetype": "postalcode"
  },
  "geometry": {"coordinates":[-2.890365,53.793474],"type":"Point"}
}
