{
  "type": "Feature",
  "properties": {
    "iso:country": "GB",
    "wof:name": "PR4 3EN",
    "wof:placetype": "postalcode"
  },
  "geometry": {"coordinates":[-2.890365,53.793474],"type":"Point"}
}
