{
  "type": "Feature",
  "properties": {
    "iso:country":"GB",
    "wof:name":"OL8 3DH",
    "wof:placetype":"postalcode"
},
  "geometry": {"coordinates":[-2.11616859643004,53.52496747405485],"type":"Point"}
}