{
  "type": "Feature",
  "properties": {
    "iso:country":"GB",
    "wof:name":"LU7 9SG",
    "wof:placetype":"postalcode"
},
  "geometry": {"coordinates":[-0.65421355480489,51.90203707000709],"type":"Point"}
}