{
  "type": "Feature",
  "properties": {
    "date:inception_lower":"2016-04-01",
    "date:inception_upper":"2016-04-30",
    "iso:country":"GB",
    "wof:name":"LU7 9SG",
    "wof:placetype":"postalcode"
},
  "geometry": {"coordinates":[-0.653655,51.90187],"type":"Point"}
}