{
  "type": "Feature",
  "properties": {
    "iso:country": "GB",
    "wof:name": "TQ2 6QN",
    "wof:placetype": "postalcode"
  },
  "geometry": {"coordinates":[-3.543747,50.459574],"type":"Point"}
}
