{
  "type": "Feature",
  "properties": {
    "date:inception_lower":"1980-01-01",
    "date:inception_upper":"1980-01-31",
    "iso:country":"GB",
    "wof:name":"TQ2 6QN",
    "wof:placetype":"postalcode"
},
  "geometry": {"coordinates":[-3.543747,50.459574],"type":"Point"}
}