{
  "type": "Feature",
  "properties": {
    "iso:country": "GB",
    "wof:name": "OL11 2RU",
    "wof:placetype": "postalcode"
  },
  "geometry": {"coordinates":[-2.158253,53.593752],"type":"Point"}
}
