{
  "type": "Feature",
  "properties": {
    "iso:country":"GB",
    "wof:name":"YO12 4AY",
    "wof:placetype":"postalcode"
},
  "geometry": {"coordinates":[-0.41698238398812,54.26162966099015],"type":"Point"}
}