{
  "type": "Feature",
  "properties": {
    "iso:country":"GB",
    "wof:name":"IP1 6AR",
    "wof:placetype":"postalcode"
},
  "geometry": {"coordinates":[1.14195183051554,52.07664901641773],"type":"Point"}
}