{
  "type": "Feature",
  "properties": {
    "date:inception_lower": "1980-01-01",
    "date:inception_upper": "1980-01-01",
    "iso:country": "GB",
    "wof:name": "PO37 7LN",
    "wof:placetype": "postalcode"
  },
  "geometry": {"coordinates":[-1.180376,50.631179],"type":"Point"}
}
