{
  "type": "Feature",
  "properties": {
    "iso:country":"GB",
    "wof:name":"OX5 1HB",
    "wof:placetype":"postalcode"
},
  "geometry": {"coordinates":[-1.28687784024233,51.81286681474501],"type":"Point"}
}