{
  "type": "Feature",
  "properties": {
    "iso:country": "GB",
    "wof:name": "GL2 0NS",
    "wof:placetype": "postalcode"
  },
  "geometry": {"coordinates":[-2.214573,51.866547],"type":"Point"}
}
