{
  "type": "Feature",
  "properties": {
    "iso:country":"GB",
    "wof:name":"GL2 0NS",
    "wof:placetype":"postalcode"
},
  "geometry": {"coordinates":[-2.21457350726843,51.86654701394419],"type":"Point"}
}