{
  "type": "Feature",
  "properties": {
    "date:inception_lower": "2021-02-01",
    "date:inception_upper": "2021-02-01",
    "iso:country": "GB",
    "wof:name": "SK14 4XQ",
    "wof:placetype": "postalcode"
  },
  "geometry": {"coordinates":[-2.083391,53.456133],"type":"Point"}
}
