{
  "type": "Feature",
  "properties": {
    "iso:country":"GB",
    "wof:name":"TR8 4JG",
    "wof:placetype":"postalcode"
},
  "geometry": {"coordinates":[-4.9650839400277,50.43041622452461],"type":"Point"}
}