{
  "type": "Feature",
  "properties": {
    "iso:country":"GB",
    "wof:name":"PH2 7DJ",
    "wof:placetype":"postalcode"
},
  "geometry": {"coordinates":[-3.42114094815671,56.39665558725436],"type":"Point"}
}