{
  "type": "Feature",
  "properties": {
    "iso:country": "GB",
    "wof:name": "PH2 7DJ",
    "wof:placetype": "postalcode"
  },
  "geometry": {"coordinates":[-3.420032,56.396911],"type":"Point"}
}
