{
  "type": "Feature",
  "properties": {
    "iso:country":"GB",
    "wof:name":"BD22 9RS",
    "wof:placetype":"postalcode"
},
  "geometry": {"coordinates":[-1.96044196429172,53.81733921349898],"type":"Point"}
}