{
  "type": "Feature",
  "properties": {
    "iso:country": "GB",
    "wof:name": "BD22 9RS",
    "wof:placetype": "postalcode"
  },
  "geometry": {"coordinates":[-1.960442,53.817339],"type":"Point"}
}
