{
  "type": "Feature",
  "properties": {
    "iso:country":"GB",
    "wof:name":"SG12 8RG",
    "wof:placetype":"postalcode"
},
  "geometry": {"coordinates":[0.05337449207617,51.82120105443846],"type":"Point"}
}