{
  "type": "Feature",
  "properties": {
    "iso:country": "GB",
    "wof:name": "SG12 8RG",
    "wof:placetype": "postalcode"
  },
  "geometry": {"coordinates":[0.053401,51.821208],"type":"Point"}
}
