{
  "type": "Feature",
  "properties": {
    "iso:country":"GB",
    "wof:name":"WF12 7LR",
    "wof:placetype":"postalcode"
},
  "geometry": {"coordinates":[-1.61041516889354,53.69604891180067],"type":"Point"}
}