{
  "type": "Feature",
  "properties": {
    "iso:country": "GB",
    "wof:name": "WF12 7LR",
    "wof:placetype": "postalcode"
  },
  "geometry": {"coordinates":[-1.610415,53.696049],"type":"Point"}
}
