{
  "type": "Feature",
  "properties": {
    "iso:country": "GB",
    "wof:name": "CA11 8SU",
    "wof:placetype": "postalcode"
  },
  "geometry": {"coordinates":[-2.675812,54.686307],"type":"Point"}
}
