{
  "type": "Feature",
  "properties": {
    "iso:country":"GB",
    "wof:name":"CA11 8SU",
    "wof:placetype":"postalcode"
},
  "geometry": {"coordinates":[-2.67580798203739,54.68638945008754],"type":"Point"}
}