{
  "type": "Feature",
  "properties": {
    "iso:country":"GB",
    "wof:name":"ME13 0NW",
    "wof:placetype":"postalcode"
},
  "geometry": {"coordinates":[0.87568311858897,51.26043648120798],"type":"Point"}
}