{
  "type": "Feature",
  "properties": {
    "iso:country":"GB",
    "wof:name":"SY7 9RS",
    "wof:placetype":"postalcode"
},
  "geometry": {"coordinates":[-2.8326726041726,52.43722144558023],"type":"Point"}
}