{
  "type": "Feature",
  "properties": {
    "date:inception_lower":"2000-12-01",
    "date:inception_upper":"2000-12-31",
    "iso:country":"GB",
    "wof:name":"SY7 9RS",
    "wof:placetype":"postalcode"
},
  "geometry": {"coordinates":[-2.832673,52.437221],"type":"Point"}
}