{
  "type": "Feature",
  "properties": {
    "date:inception_lower":"2002-11-01",
    "date:inception_upper":"2002-11-30",
    "iso:country":"GB",
    "wof:name":"S64 9DP",
    "wof:placetype":"postalcode"
},
  "geometry": {"coordinates":[-1.292476,53.493971],"type":"Point"}
}