{
  "type": "Feature",
  "properties": {
    "iso:country": "GB",
    "wof:name": "IG11 7XQ",
    "wof:placetype": "postalcode"
  },
  "geometry": {"coordinates":[0.091651,51.532989],"type":"Point"}
}
