{
  "type": "Feature",
  "properties": {
    "iso:country":"GB",
    "wof:name":"IG11 7XQ",
    "wof:placetype":"postalcode"
},
  "geometry": {"coordinates":[0.09165051427533,51.53298894399489],"type":"Point"}
}