{
  "type": "Feature",
  "properties": {
    "date:inception_lower": "1990-02-01",
    "date:inception_upper": "1990-02-01",
    "iso:country": "GB",
    "wof:name": "E8 3RW",
    "wof:placetype": "postalcode"
  },
  "geometry": {"coordinates":[-0.058821,51.53911],"type":"Point"}
}
