{
  "type": "Feature",
  "properties": {
    "iso:country": "GB",
    "wof:name": "PA9 1AE",
    "wof:placetype": "postalcode"
  },
  "geometry": {"coordinates":[-4.546102,55.815629],"type":"Point"}
}
