{
  "type": "Feature",
  "properties": {
    "date:inception_lower": "1980-01-01",
    "date:inception_upper": "1980-01-01",
    "iso:country": "GB",
    "wof:name": "PA9 1AE",
    "wof:placetype": "postalcode"
  },
  "geometry": {"coordinates":[-4.546102,55.815629],"type":"Point"}
}
