{
  "type": "Feature",
  "properties": {
    "date:inception_lower": "2013-02-01",
    "date:inception_upper": "2013-02-01",
    "iso:country": "GB",
    "wof:name": "CF40 1LZ",
    "wof:placetype": "postalcode"
  },
  "geometry": {"coordinates":[-3.452674,51.616436],"type":"Point"}
}
