{
  "type": "Feature",
  "properties": {
    "iso:country":"GB",
    "wof:name":"CF40 1LZ",
    "wof:placetype":"postalcode"
},
  "geometry": {"coordinates":[-3.4525896944619,51.61639711937637],"type":"Point"}
}