{
  "type": "Feature",
  "properties": {
    "iso:country": "GB",
    "wof:name": "CF40 1LZ",
    "wof:placetype": "postalcode"
  },
  "geometry": {"coordinates":[-3.452674,51.616436],"type":"Point"}
}
