{
  "type": "Feature",
  "properties": {
    "iso:country":"GB",
    "wof:name":"TN25 6PY",
    "wof:placetype":"postalcode"
},
  "geometry": {"coordinates":[0.97621600435084,51.12366949241827],"type":"Point"}
}