{
  "type": "Feature",
  "properties": {
    "iso:country": "GB",
    "wof:name": "NN4 5WT",
    "wof:placetype": "postalcode"
  },
  "geometry": {"coordinates":[-0.898245,52.24527],"type":"Point"}
}
