{
  "type": "Feature",
  "properties": {
    "iso:country":"GB",
    "wof:name":"SE1 6AH",
    "wof:placetype":"postalcode"
},
  "geometry": {"coordinates":[-0.09324912859448,51.49442376492551],"type":"Point"}
}