{
  "type": "Feature",
  "properties": {
    "date:inception_lower": "1980-01-01",
    "date:inception_upper": "1980-01-01",
    "iso:country": "GB",
    "wof:name": "KA2 9DN",
    "wof:placetype": "postalcode"
  },
  "geometry": {"coordinates":[-4.60322,55.578966],"type":"Point"}
}
