{
  "type": "Feature",
  "properties": {
    "iso:country":"GB",
    "wof:name":"KA2 9DN",
    "wof:placetype":"postalcode"
},
  "geometry": {"coordinates":[-4.60322028128581,55.57896570553718],"type":"Point"}
}