{
  "type": "Feature",
  "properties": {
    "iso:country": "GB",
    "wof:name": "KA2 9DN",
    "wof:placetype": "postalcode"
  },
  "geometry": {"coordinates":[-4.60322,55.578966],"type":"Point"}
}
