{
  "type": "Feature",
  "properties": {
    "date:inception_lower": "1980-01-01",
    "date:inception_upper": "1980-01-01",
    "iso:country": "GB",
    "wof:name": "KA9 2HT",
    "wof:placetype": "postalcode"
  },
  "geometry": {"coordinates":[-4.603628,55.486113],"type":"Point"}
}
