{
  "type": "Feature",
  "properties": {
    "iso:country":"GB",
    "wof:name":"BR2 8DF",
    "wof:placetype":"postalcode"
},
  "geometry": {"coordinates":[0.05845235855078,51.38504184735893],"type":"Point"}
}