{
  "type": "Feature",
  "properties": {
    "date:inception_lower":"2018-01-01",
    "date:inception_upper":"2018-01-31",
    "iso:country":"GB",
    "wof:name":"HA5 4SE",
    "wof:placetype":"postalcode"
},
  "geometry": {"coordinates":[-0.376105,51.60776],"type":"Point"}
}