{
  "type": "Feature",
  "properties": {
    "iso:country": "GB",
    "wof:name": "HA5 4SE",
    "wof:placetype": "postalcode"
  },
  "geometry": {"coordinates":[-0.376105,51.60776],"type":"Point"}
}
