{
  "type": "Feature",
  "properties": {
    "iso:country":"GB",
    "wof:name":"BS36 2UH",
    "wof:placetype":"postalcode"
},
  "geometry": {"coordinates":[-2.46558612135278,51.51250114258594],"type":"Point"}
}