{
  "type": "Feature",
  "properties": {
    "date:inception_lower": "1997-12-01",
    "date:inception_upper": "1997-12-01",
    "iso:country": "GB",
    "wof:name": "BS36 2UH",
    "wof:placetype": "postalcode"
  },
  "geometry": {"coordinates":[-2.465586,51.512501],"type":"Point"}
}
