{
  "type": "Feature",
  "properties": {
    "iso:country":"GB",
    "wof:name":"HP5 1RZ",
    "wof:placetype":"postalcode"
},
  "geometry": {"coordinates":[-0.60145238448356,51.69571143756068],"type":"Point"}
}