{
  "type": "Feature",
  "properties": {
    "iso:country": "GB",
    "wof:name": "SN13 0FE",
    "wof:placetype": "postalcode"
  },
  "geometry": {"coordinates":[-2.212903,51.429681],"type":"Point"}
}
