{
  "type": "Feature",
  "properties": {
    "date:inception_lower":"1980-01-01",
    "date:inception_upper":"1980-01-31",
    "iso:country":"GB",
    "wof:name":"EX16 4DQ",
    "wof:placetype":"postalcode"
},
  "geometry": {"coordinates":[-3.472304,50.905487],"type":"Point"}
}