{
  "type": "Feature",
  "properties": {
    "iso:country":"GB",
    "wof:name":"GL18 1NT",
    "wof:placetype":"postalcode"
},
  "geometry": {"coordinates":[-2.45602602958305,51.91893183922392],"type":"Point"}
}