{
  "type": "Feature",
  "properties": {
    "iso:country": "GB",
    "wof:name": "GL18 1NT",
    "wof:placetype": "postalcode"
  },
  "geometry": {"coordinates":[-2.456026,51.918932],"type":"Point"}
}
