{
  "type": "Feature",
  "properties": {
    "date:inception_lower": "2020-12-01",
    "date:inception_upper": "2020-12-01",
    "iso:country": "GB",
    "wof:name": "GL11 5FN",
    "wof:placetype": "postalcode"
  },
  "geometry": {"coordinates":[-2.359955,51.714552],"type":"Point"}
}
