{
  "type": "Feature",
  "properties": {
    "date:inception_lower":"1980-01-01",
    "date:inception_upper":"1980-01-31",
    "iso:country":"GB",
    "wof:name":"EH18 1AR",
    "wof:placetype":"postalcode"
},
  "geometry": {"coordinates":[-3.101753,55.896767],"type":"Point"}
}