{
  "type": "Feature",
  "properties": {
    "iso:country":"GB",
    "wof:name":"EH18 1AR",
    "wof:placetype":"postalcode"
},
  "geometry": {"coordinates":[-3.10175276714183,55.89676666361682],"type":"Point"}
}