{
  "type": "Feature",
  "properties": {
    "iso:country":"GB",
    "wof:name":"SW6 3QP",
    "wof:placetype":"postalcode"
},
  "geometry": {"coordinates":[-0.20650793378253,51.47024031158566],"type":"Point"}
}