{
  "type": "Feature",
  "properties": {
    "iso:country": "GB",
    "wof:name": "NN14 3FF",
    "wof:placetype": "postalcode"
  },
  "geometry": {"coordinates":[-0.615685,52.466641],"type":"Point"}
}
