{
  "type": "Feature",
  "properties": {
    "date:inception_lower":"2012-08-01",
    "date:inception_upper":"2012-08-31",
    "iso:country":"GB",
    "wof:name":"NN14 3FF",
    "wof:placetype":"postalcode"
},
  "geometry": {"coordinates":[-0.615685,52.466641],"type":"Point"}
}