{
  "type": "Feature",
  "properties": {
    "iso:country":"GB",
    "wof:name":"WC1X 9AX",
    "wof:placetype":"postalcode"
},
  "geometry": {"coordinates":[-0.11472228269596,51.53053426585023],"type":"Point"}
}