{
  "type": "Feature",
  "properties": {
    "iso:country": "GB",
    "wof:name": "WC1X 9AX",
    "wof:placetype": "postalcode"
  },
  "geometry": {"coordinates":[-0.114722,51.530534],"type":"Point"}
}
