{
  "type": "Feature",
  "properties": {
    "date:inception_lower": "1980-01-01",
    "date:inception_upper": "1980-01-01",
    "iso:country": "GB",
    "wof:name": "SL4 2NR",
    "wof:placetype": "postalcode"
  },
  "geometry": {"coordinates":[-0.575644,51.457797],"type":"Point"}
}
