{
  "type": "Feature",
  "properties": {
    "date:inception_lower":"1980-01-01",
    "date:inception_upper":"1980-01-31",
    "iso:country":"GB",
    "wof:name":"DY4 9JG",
    "wof:placetype":"postalcode"
},
  "geometry": {"coordinates":[-2.067917,52.54289],"type":"Point"}
}