{
  "type": "Feature",
  "properties": {
    "iso:country":"GB",
    "wof:name":"DY4 9JG",
    "wof:placetype":"postalcode"
},
  "geometry": {"coordinates":[-2.06791684654715,52.54288996541618],"type":"Point"}
}