{
  "type": "Feature",
  "properties": {
    "iso:country":"GB",
    "wof:name":"SW1V 3AD",
    "wof:placetype":"postalcode"
},
  "geometry": {"coordinates":[-0.14296726748438,51.4865618092763],"type":"Point"}
}