{
  "type": "Feature",
  "properties": {
    "iso:country": "GB",
    "wof:name": "WF14 9EJ",
    "wof:placetype": "postalcode"
  },
  "geometry": {"coordinates":[-1.708497,53.682585],"type":"Point"}
}
