{
  "type": "Feature",
  "properties": {
    "iso:country":"GB",
    "wof:name":"IG3 9AQ",
    "wof:placetype":"postalcode"
},
  "geometry": {"coordinates":[0.0938655912135,51.55297628213145],"type":"Point"}
}