{
  "type": "Feature",
  "properties": {
    "date:inception_lower": "2017-01-01",
    "date:inception_upper": "2017-01-01",
    "iso:country": "GB",
    "wof:name": "OX14 4FY",
    "wof:placetype": "postalcode"
  },
  "geometry": {"coordinates":[-1.310639,51.650773],"type":"Point"}
}
