{
  "type": "Feature",
  "properties": {
    "iso:country": "GB",
    "wof:name": "B27 7AY",
    "wof:placetype": "postalcode"
  },
  "geometry": {"coordinates":[-1.816205,52.439823],"type":"Point"}
}
