{
  "type": "Feature",
  "properties": {
    "date:inception_lower": "1980-01-01",
    "date:inception_upper": "1980-01-01",
    "iso:country": "GB",
    "wof:name": "PE11 2SL",
    "wof:placetype": "postalcode"
  },
  "geometry": {"coordinates":[-0.160479,52.776705],"type":"Point"}
}
