{
  "type": "Feature",
  "properties": {
    "iso:country":"GB",
    "wof:name":"PE11 2SL",
    "wof:placetype":"postalcode"
},
  "geometry": {"coordinates":[-0.16047920902799,52.77670515123926],"type":"Point"}
}