{
  "type": "Feature",
  "properties": {
    "iso:country": "GB",
    "wof:name": "NE4 6BJ",
    "wof:placetype": "postalcode"
  },
  "geometry": {"coordinates":[-1.628582,54.975903],"type":"Point"}
}
