{
  "type": "Feature",
  "properties": {
    "iso:country":"GB",
    "wof:name":"NE4 6BJ",
    "wof:placetype":"postalcode"
},
  "geometry": {"coordinates":[-1.62858206085487,54.97590284471113],"type":"Point"}
}