{
  "type": "Feature",
  "properties": {
    "date:inception_lower": "1996-12-01",
    "date:inception_upper": "1996-12-01",
    "iso:country": "GB",
    "wof:name": "AB11 6QF",
    "wof:placetype": "postalcode"
  },
  "geometry": {"coordinates":[-2.09641,57.145726],"type":"Point"}
}
