{
  "type": "Feature",
  "properties": {
    "iso:country": "GB",
    "wof:name": "S72 8JQ",
    "wof:placetype": "postalcode"
  },
  "geometry": {"coordinates":[-1.410924,53.567708],"type":"Point"}
}
