{
  "type": "Feature",
  "properties": {
    "date:inception_lower": "1986-07-01",
    "date:inception_upper": "1986-07-01",
    "iso:country": "GB",
    "wof:name": "S72 8JQ",
    "wof:placetype": "postalcode"
  },
  "geometry": {"coordinates":[-1.410924,53.567708],"type":"Point"}
}
