{
  "type": "Feature",
  "properties": {
    "iso:country":"GB",
    "wof:name":"SK15 2LT",
    "wof:placetype":"postalcode"
},
  "geometry": {"coordinates":[-2.04852924149485,53.48317320195876],"type":"Point"}
}