{
  "type": "Feature",
  "properties": {
    "iso:country":"GB",
    "wof:name":"KY7 4JP",
    "wof:placetype":"postalcode"
},
  "geometry": {"coordinates":[-3.16960208073486,56.1915509839188],"type":"Point"}
}