{
  "type": "Feature",
  "properties": {
    "iso:country": "GB",
    "wof:name": "GL51 0QB",
    "wof:placetype": "postalcode"
  },
  "geometry": {"coordinates":[-2.120219,51.916023],"type":"Point"}
}
