{
  "type": "Feature",
  "properties": {
    "iso:country":"GB",
    "wof:name":"GL51 0QB",
    "wof:placetype":"postalcode"
},
  "geometry": {"coordinates":[-2.12021931548463,51.91602333292501],"type":"Point"}
}