{
  "type": "Feature",
  "properties": {
    "iso:country": "GB",
    "wof:name": "DL5 6RH",
    "wof:placetype": "postalcode"
  },
  "geometry": {"coordinates":[-1.619977,54.594785],"type":"Point"}
}
