{
  "type": "Feature",
  "properties": {
    "iso:country":"GB",
    "wof:name":"DL5 6RH",
    "wof:placetype":"postalcode"
},
  "geometry": {"coordinates":[-1.6199533114148,54.59475704903786],"type":"Point"}
}