{
  "type": "Feature",
  "properties": {
    "iso:country":"GB",
    "wof:name":"EX6 8UL",
    "wof:placetype":"postalcode"
},
  "geometry": {"coordinates":[-3.50397334770378,50.68259918107388],"type":"Point"}
}