{
  "type": "Feature",
  "properties": {
    "iso:country": "GB",
    "wof:name": "EX6 8UL",
    "wof:placetype": "postalcode"
  },
  "geometry": {"coordinates":[-3.503973,50.682599],"type":"Point"}
}
