{
  "type": "Feature",
  "properties": {
    "date:inception_lower":"1997-06-01",
    "date:inception_upper":"1997-06-30",
    "iso:country":"GB",
    "wof:name":"IP5 1AH",
    "wof:placetype":"postalcode"
},
  "geometry": {"coordinates":[1.218972,52.064001],"type":"Point"}
}