{
  "type": "Feature",
  "properties": {
    "iso:country":"GB",
    "wof:name":"IP5 1AH",
    "wof:placetype":"postalcode"
},
  "geometry": {"coordinates":[1.21897217283533,52.06400096146354],"type":"Point"}
}