{
  "type": "Feature",
  "properties": {
    "iso:country":"GB",
    "wof:name":"UB8 3SZ",
    "wof:placetype":"postalcode"
},
  "geometry": {"coordinates":[-0.4774393179413,51.52207147479503],"type":"Point"}
}