{
  "type": "Feature",
  "properties": {
    "iso:country":"GB",
    "wof:name":"TN21 9AX",
    "wof:placetype":"postalcode"
},
  "geometry": {"coordinates":[0.28048575057162,50.94334218639843],"type":"Point"}
}