{
  "type": "Feature",
  "properties": {
    "iso:country":"GB",
    "wof:name":"LE2 2HJ",
    "wof:placetype":"postalcode"
},
  "geometry": {"coordinates":[-1.08476200119293,52.61156421652856],"type":"Point"}
}