{
  "type": "Feature",
  "properties": {
    "date:inception_lower": "1980-01-01",
    "date:inception_upper": "1980-01-01",
    "iso:country": "GB",
    "wof:name": "SG4 0QR",
    "wof:placetype": "postalcode"
  },
  "geometry": {"coordinates":[-0.259813,51.953046],"type":"Point"}
}
