{
  "type": "Feature",
  "properties": {
    "iso:country": "GB",
    "wof:name": "SG4 0QR",
    "wof:placetype": "postalcode"
  },
  "geometry": {"coordinates":[-0.259813,51.953046],"type":"Point"}
}
