{
  "type": "Feature",
  "properties": {
    "iso:country":"GB",
    "wof:name":"SG4 0QR",
    "wof:placetype":"postalcode"
},
  "geometry": {"coordinates":[-0.25994352376957,51.9529319053062],"type":"Point"}
}