{
  "type": "Feature",
  "properties": {
    "date:inception_lower":"2000-06-01",
    "date:inception_upper":"2000-06-30",
    "iso:country":"GB",
    "wof:name":"PE27 5WA",
    "wof:placetype":"postalcode"
},
  "geometry": {"coordinates":[-0.085466,52.319073],"type":"Point"}
}