{
  "type": "Feature",
  "properties": {
    "iso:country":"GB",
    "wof:name":"PE27 5WA",
    "wof:placetype":"postalcode"
},
  "geometry": {"coordinates":[-0.08546586570145,52.31907309815166],"type":"Point"}
}