{
  "type": "Feature",
  "properties": {
    "iso:country":"GB",
    "wof:name":"CV3 1AR",
    "wof:placetype":"postalcode"
},
  "geometry": {"coordinates":[-1.48530327428609,52.40293137895404],"type":"Point"}
}