{
  "type": "Feature",
  "properties": {
    "iso:country":"GB",
    "wof:name":"G2 4AE",
    "wof:placetype":"postalcode"
},
  "geometry": {"coordinates":[-4.26219874571586,55.86472177372799],"type":"Point"}
}