{
  "type": "Feature",
  "properties": {
    "iso:country":"GB",
    "wof:name":"YO41 5QE",
    "wof:placetype":"postalcode"
},
  "geometry": {"coordinates":[-0.83663785876301,53.96888636750128],"type":"Point"}
}