{
  "type": "Feature",
  "properties": {
    "iso:country": "GB",
    "wof:name": "YO41 5QE",
    "wof:placetype": "postalcode"
  },
  "geometry": {"coordinates":[-0.836638,53.968886],"type":"Point"}
}
