{
  "type": "Feature",
  "properties": {
    "iso:country": "GB",
    "wof:name": "RH18 5LZ",
    "wof:placetype": "postalcode"
  },
  "geometry": {"coordinates":[0.052249,51.093531],"type":"Point"}
}
