{
  "type": "Feature",
  "properties": {
    "date:inception_lower": "1995-01-01",
    "date:inception_upper": "1995-01-01",
    "iso:country": "GB",
    "wof:name": "YO18 8TG",
    "wof:placetype": "postalcode"
  },
  "geometry": {"coordinates":[-0.781585,54.241373],"type":"Point"}
}
