{
  "type": "Feature",
  "properties": {
    "iso:country":"GB",
    "wof:name":"YO18 8TG",
    "wof:placetype":"postalcode"
},
  "geometry": {"coordinates":[-0.78158540333401,54.24137312618574],"type":"Point"}
}