{
  "type": "Feature",
  "properties": {
    "iso:country":"GB",
    "wof:name":"OL16 1NR",
    "wof:placetype":"postalcode"
},
  "geometry": {"coordinates":[-2.15616131736455,53.61635990559047],"type":"Point"}
}