{
  "type": "Feature",
  "properties": {
    "iso:country":"GB",
    "wof:name":"B97 5JR",
    "wof:placetype":"postalcode"
},
  "geometry": {"coordinates":[-1.9362564148471,52.27743390673982],"type":"Point"}
}