{
  "type": "Feature",
  "properties": {
    "iso:country":"GB",
    "wof:name":"WR9 7HU",
    "wof:placetype":"postalcode"
},
  "geometry": {"coordinates":[-2.15634724188193,52.25336101462039],"type":"Point"}
}