{
  "type": "Feature",
  "properties": {
    "iso:country":"GB",
    "wof:name":"EX34 9JY",
    "wof:placetype":"postalcode"
},
  "geometry": {"coordinates":[-4.11848431933948,51.20742721847718],"type":"Point"}
}