{
  "type": "Feature",
  "properties": {
    "date:inception_lower": "2018-07-01",
    "date:inception_upper": "2018-07-01",
    "iso:country": "GB",
    "wof:name": "NP16 6FF",
    "wof:placetype": "postalcode"
  },
  "geometry": {"coordinates":[-2.749677,51.639735],"type":"Point"}
}
