{
  "type": "Feature",
  "properties": {
    "iso:country": "GB",
    "wof:name": "CA20 1AP",
    "wof:placetype": "postalcode"
  },
  "geometry": {"coordinates":[-3.438979,54.417439],"type":"Point"}
}
