{
  "type": "Feature",
  "properties": {
    "iso:country":"GB",
    "wof:name":"S63 0DF",
    "wof:placetype":"postalcode"
},
  "geometry": {"coordinates":[-1.29677694302511,53.54467414138414],"type":"Point"}
}