{
  "type": "Feature",
  "properties": {
    "iso:country": "GB",
    "wof:name": "RG26 3PD",
    "wof:placetype": "postalcode"
  },
  "geometry": {"coordinates":[-1.136743,51.344146],"type":"Point"}
}
