{
  "type": "Feature",
  "properties": {
    "iso:country":"GB",
    "wof:name":"RG26 3PD",
    "wof:placetype":"postalcode"
},
  "geometry": {"coordinates":[-1.13674331919305,51.34414617244897],"type":"Point"}
}