{
  "type": "Feature",
  "properties": {
    "date:inception_lower": "2006-09-01",
    "date:inception_upper": "2006-09-01",
    "iso:country": "GB",
    "wof:name": "TR26 2QN",
    "wof:placetype": "postalcode"
  },
  "geometry": {"coordinates":[-5.498646,50.205406],"type":"Point"}
}
