{
  "type": "Feature",
  "properties": {
    "date:inception_lower":"2004-08-01",
    "date:inception_upper":"2004-08-31",
    "iso:country":"GB",
    "wof:name":"YO16 6GT",
    "wof:placetype":"postalcode"
},
  "geometry": {"coordinates":[-0.19001,54.106157],"type":"Point"}
}