{
  "type": "Feature",
  "properties": {
    "iso:country":"GB",
    "wof:name":"YO16 6GT",
    "wof:placetype":"postalcode"
},
  "geometry": {"coordinates":[-0.19001038830896,54.1061566155477],"type":"Point"}
}