{
  "type": "Feature",
  "properties": {
    "iso:country":"GB",
    "wof:name":"M24 5RU",
    "wof:placetype":"postalcode"
},
  "geometry": {"coordinates":[-2.20770588665324,53.55422626426549],"type":"Point"}
}