{
  "type": "Feature",
  "properties": {
    "date:inception_lower":"1980-01-01",
    "date:inception_upper":"1980-01-31",
    "iso:country":"GB",
    "wof:name":"LE4 0AG",
    "wof:placetype":"postalcode"
},
  "geometry": {"coordinates":[-1.144193,52.650117],"type":"Point"}
}