{
  "type": "Feature",
  "properties": {
    "iso:country":"GB",
    "wof:name":"CH7 2EB",
    "wof:placetype":"postalcode"
},
  "geometry": {"coordinates":[-3.07997567273044,53.16832896081468],"type":"Point"}
}