{
  "type": "Feature",
  "properties": {
    "iso:country":"GB",
    "wof:name":"SM1 2SY",
    "wof:placetype":"postalcode"
},
  "geometry": {"coordinates":[-0.20495538810638,51.36187407608551],"type":"Point"}
}