{
  "type": "Feature",
  "properties": {
    "date:inception_lower": "1991-09-01",
    "date:inception_upper": "1991-09-01",
    "iso:country": "GB",
    "wof:name": "EN8 7TF",
    "wof:placetype": "postalcode"
  },
  "geometry": {"coordinates":[-0.025791,51.685139],"type":"Point"}
}
