{
  "type": "Feature",
  "properties": {
    "iso:country":"GB",
    "wof:name":"EN8 7TF",
    "wof:placetype":"postalcode"
},
  "geometry": {"coordinates":[-0.02512488591086,51.6850891515419],"type":"Point"}
}