{
  "type": "Feature",
  "properties": {
    "iso:country":"GB",
    "wof:name":"WR13 5HQ",
    "wof:placetype":"postalcode"
},
  "geometry": {"coordinates":[-2.31689741948727,52.15434211189383],"type":"Point"}
}