{
  "type": "Feature",
  "properties": {
    "date:inception_lower": "1997-06-01",
    "date:inception_upper": "1997-06-01",
    "iso:country": "GB",
    "wof:name": "WR13 5HQ",
    "wof:placetype": "postalcode"
  },
  "geometry": {"coordinates":[-2.316897,52.154342],"type":"Point"}
}
