{
  "type": "Feature",
  "properties": {
    "iso:country":"GB",
    "wof:name":"PO41 0TQ",
    "wof:placetype":"postalcode"
},
  "geometry": {"coordinates":[-1.43223086386533,50.69395474338985],"type":"Point"}
}