{
  "type": "Feature",
  "properties": {
    "date:inception_lower":"1980-01-01",
    "date:inception_upper":"1980-01-31",
    "iso:country":"GB",
    "wof:name":"PO41 0TQ",
    "wof:placetype":"postalcode"
},
  "geometry": {"coordinates":[-1.432231,50.693955],"type":"Point"}
}