{
  "type": "Feature",
  "properties": {
    "iso:country": "GB",
    "wof:name": "PO41 0TQ",
    "wof:placetype": "postalcode"
  },
  "geometry": {"coordinates":[-1.432231,50.693955],"type":"Point"}
}
