{
  "type": "Feature",
  "properties": {
    "iso:country":"GB",
    "wof:name":"S20 8NL",
    "wof:placetype":"postalcode"
},
  "geometry": {"coordinates":[-1.34945875536524,53.33281272120023],"type":"Point"}
}