{
  "type": "Feature",
  "properties": {
    "date:inception_lower": "1997-06-01",
    "date:inception_upper": "1997-06-01",
    "iso:country": "GB",
    "wof:name": "S20 8NL",
    "wof:placetype": "postalcode"
  },
  "geometry": {"coordinates":[-1.349504,53.332814],"type":"Point"}
}
