{
  "type": "Feature",
  "properties": {
    "iso:country":"GB",
    "wof:name":"LE13 1JJ",
    "wof:placetype":"postalcode"
},
  "geometry": {"coordinates":[-0.89204318510681,52.77527328291671],"type":"Point"}
}