{
  "type": "Feature",
  "properties": {
    "date:inception_lower": "2022-08-01",
    "date:inception_upper": "2022-08-01",
    "iso:country": "GB",
    "wof:name": "L24 1AA",
    "wof:placetype": "postalcode"
  },
  "geometry": {"coordinates":[-2.858672,53.343617],"type":"Point"}
}
