{
  "type": "Feature",
  "properties": {
    "date:inception_lower": "2013-12-01",
    "date:inception_upper": "2013-12-01",
    "iso:country": "GB",
    "wof:name": "SG18 8GT",
    "wof:placetype": "postalcode"
  },
  "geometry": {"coordinates":[-0.244201,52.09218],"type":"Point"}
}
