{
  "type": "Feature",
  "properties": {
    "iso:country":"GB",
    "wof:name":"PE26 1AX",
    "wof:placetype":"postalcode"
},
  "geometry": {"coordinates":[-0.11692826385242,52.44742674900391],"type":"Point"}
}