{
  "type": "Feature",
  "properties": {
    "iso:country": "GB",
    "wof:name": "WR8 0BY",
    "wof:placetype": "postalcode"
  },
  "geometry": {"coordinates":[-2.23898,52.07969],"type":"Point"}
}
