{
  "type": "Feature",
  "properties": {
    "iso:country": "GB",
    "wof:name": "DL5 7GA",
    "wof:placetype": "postalcode"
  },
  "geometry": {"coordinates":[-1.581034,54.624429],"type":"Point"}
}
