{
  "type": "Feature",
  "properties": {
    "date:inception_lower":"2002-07-01",
    "date:inception_upper":"2002-07-31",
    "iso:country":"GB",
    "wof:name":"DL5 7GA",
    "wof:placetype":"postalcode"
},
  "geometry": {"coordinates":[-1.581034,54.624429],"type":"Point"}
}