{
  "type": "Feature",
  "properties": {
    "iso:country":"GB",
    "wof:name":"DL5 7GA",
    "wof:placetype":"postalcode"
},
  "geometry": {"coordinates":[-1.58103437955289,54.62442897444566],"type":"Point"}
}