{
  "type": "Feature",
  "properties": {
    "date:inception_lower": "1980-01-01",
    "date:inception_upper": "1980-01-01",
    "iso:country": "GB",
    "wof:name": "TN6 2PD",
    "wof:placetype": "postalcode"
  },
  "geometry": {"coordinates":[0.165614,51.04854],"type":"Point"}
}
