{
  "type": "Feature",
  "properties": {
    "iso:country":"GB",
    "wof:name":"TN6 2PD",
    "wof:placetype":"postalcode"
},
  "geometry": {"coordinates":[0.1656148154493,51.04855986209935],"type":"Point"}
}