{
  "type": "Feature",
  "properties": {
    "iso:country": "GB",
    "wof:name": "TN6 2PD",
    "wof:placetype": "postalcode"
  },
  "geometry": {"coordinates":[0.165615,51.04856],"type":"Point"}
}
