{
  "type": "Feature",
  "properties": {
    "date:inception_lower": "2022-04-01",
    "date:inception_upper": "2022-04-01",
    "iso:country": "GB",
    "wof:name": "TF1 2GB",
    "wof:placetype": "postalcode"
  },
  "geometry": {"coordinates":[-2.535287,52.697319],"type":"Point"}
}
