{
  "type": "Feature",
  "properties": {
    "date:inception_lower": "1993-08-01",
    "date:inception_upper": "1993-08-01",
    "iso:country": "GB",
    "wof:name": "NN14 6SY",
    "wof:placetype": "postalcode"
  },
  "geometry": {"coordinates":[-0.788504,52.420052],"type":"Point"}
}
