{
  "type": "Feature",
  "properties": {
    "iso:country": "GB",
    "wof:name": "NN14 6SY",
    "wof:placetype": "postalcode"
  },
  "geometry": {"coordinates":[-0.788504,52.420052],"type":"Point"}
}
