{
  "type": "Feature",
  "properties": {
    "iso:country": "GB",
    "wof:name": "RH11 8HP",
    "wof:placetype": "postalcode"
  },
  "geometry": {"coordinates":[-0.216235,51.108809],"type":"Point"}
}
