{
  "type": "Feature",
  "properties": {
    "iso:country":"GB",
    "wof:name":"DT9 4LQ",
    "wof:placetype":"postalcode"
},
  "geometry": {"coordinates":[-2.51412910224187,50.99453441215217],"type":"Point"}
}