{
  "type": "Feature",
  "properties": {
    "iso:country": "GB",
    "wof:name": "DT9 4LQ",
    "wof:placetype": "postalcode"
  },
  "geometry": {"coordinates":[-2.514129,50.994534],"type":"Point"}
}
