{
  "type": "Feature",
  "properties": {
    "iso:country":"GB",
    "wof:name":"RG4 7AX",
    "wof:placetype":"postalcode"
},
  "geometry": {"coordinates":[-0.98326421856156,51.47104080076819],"type":"Point"}
}