{
  "type": "Feature",
  "properties": {
    "iso:country":"GB",
    "wof:name":"N14 5NG",
    "wof:placetype":"postalcode"
},
  "geometry": {"coordinates":[-0.14633261082196,51.63676170909955],"type":"Point"}
}