{
  "type": "Feature",
  "properties": {
    "iso:country": "GB",
    "wof:name": "N14 5NG",
    "wof:placetype": "postalcode"
  },
  "geometry": {"coordinates":[-0.146333,51.636762],"type":"Point"}
}
