{
  "type": "Feature",
  "properties": {
    "iso:country":"GB",
    "wof:name":"ST9 0HJ",
    "wof:placetype":"postalcode"
},
  "geometry": {"coordinates":[-2.08288836190891,53.0278725892413],"type":"Point"}
}