{
  "type": "Feature",
  "properties": {
    "iso:country": "GB",
    "wof:name": "HR2 7RE",
    "wof:placetype": "postalcode"
  },
  "geometry": {"coordinates":[-2.718717,52.051441],"type":"Point"}
}
