{
  "type": "Feature",
  "properties": {
    "iso:country":"GB",
    "wof:name":"HR2 7RE",
    "wof:placetype":"postalcode"
},
  "geometry": {"coordinates":[-2.71871666352736,52.05144080897699],"type":"Point"}
}