{
  "type": "Feature",
  "properties": {
    "iso:country":"GB",
    "wof:name":"ST5 6PW",
    "wof:placetype":"postalcode"
},
  "geometry": {"coordinates":[-2.26437512900931,53.01603823082687],"type":"Point"}
}