{
  "type": "Feature",
  "properties": {
    "iso:country":"GB",
    "wof:name":"OL14 5SW",
    "wof:placetype":"postalcode"
},
  "geometry": {"coordinates":[-2.08039305961556,53.71723710980357],"type":"Point"}
}