{
  "type": "Feature",
  "properties": {
    "date:inception_lower":"1981-06-01",
    "date:inception_upper":"1981-06-30",
    "iso:country":"GB",
    "wof:name":"LL22 9AW",
    "wof:placetype":"postalcode"
},
  "geometry": {"coordinates":[-3.56639,53.297105],"type":"Point"}
}