{
  "type": "Feature",
  "properties": {
    "iso:country": "GB",
    "wof:name": "LL22 9AW",
    "wof:placetype": "postalcode"
  },
  "geometry": {"coordinates":[-3.56639,53.297105],"type":"Point"}
}
