{
  "type": "Feature",
  "properties": {
    "date:inception_lower":"1994-05-01",
    "date:inception_upper":"1994-05-31",
    "iso:country":"GB",
    "wof:name":"M27 5YT",
    "wof:placetype":"postalcode"
},
  "geometry": {"coordinates":[-2.344371,53.505868],"type":"Point"}
}