{
  "type": "Feature",
  "properties": {
    "iso:country":"GB",
    "wof:name":"M27 5YT",
    "wof:placetype":"postalcode"
},
  "geometry": {"coordinates":[-2.34437055367443,53.50586753203579],"type":"Point"}
}