{
  "type": "Feature",
  "properties": {
    "iso:country":"GB",
    "wof:name":"HU9 3SR",
    "wof:placetype":"postalcode"
},
  "geometry": {"coordinates":[-0.2862711926628,53.75706754628006],"type":"Point"}
}