{
  "type": "Feature",
  "properties": {
    "iso:country": "GB",
    "wof:name": "M40 3LX",
    "wof:placetype": "postalcode"
  },
  "geometry": {"coordinates":[-2.169332,53.519259],"type":"Point"}
}
