{
  "type": "Feature",
  "properties": {
    "iso:country":"GB",
    "wof:name":"BH23 5HW",
    "wof:placetype":"postalcode"
},
  "geometry": {"coordinates":[-1.69645194126027,50.74350212661876],"type":"Point"}
}