{
  "type": "Feature",
  "properties": {
    "date:inception_lower": "1980-01-01",
    "date:inception_upper": "1980-01-01",
    "iso:country": "GB",
    "wof:name": "BH23 5HW",
    "wof:placetype": "postalcode"
  },
  "geometry": {"coordinates":[-1.696332,50.743429],"type":"Point"}
}
