{
  "type": "Feature",
  "properties": {
    "iso:country":"GB",
    "wof:name":"LA18 4ES",
    "wof:placetype":"postalcode"
},
  "geometry": {"coordinates":[-3.28851044141453,54.19577937706727],"type":"Point"}
}