{
  "type": "Feature",
  "properties": {
    "iso:country":"GB",
    "wof:name":"TS1 3JF",
    "wof:placetype":"postalcode"
},
  "geometry": {"coordinates":[-1.22892070076609,54.5681753254183],"type":"Point"}
}