{
  "type": "Feature",
  "properties": {
    "iso:country":"GB",
    "wof:name":"NW8 9SP",
    "wof:placetype":"postalcode"
},
  "geometry": {"coordinates":[-0.1712844449402,51.53227495804644],"type":"Point"}
}