{
  "type": "Feature",
  "properties": {
    "iso:country":"GB",
    "wof:name":"LS2 7JG",
    "wof:placetype":"postalcode"
},
  "geometry": {"coordinates":[-1.53877838572286,53.79718067589123],"type":"Point"}
}