{
  "type": "Feature",
  "properties": {
    "iso:country":"GB",
    "wof:name":"PL15 9QZ",
    "wof:placetype":"postalcode"
},
  "geometry": {"coordinates":[-4.3398685785282,50.62761578366604],"type":"Point"}
}