{
  "type": "Feature",
  "properties": {
    "date:inception_lower":"1990-02-01",
    "date:inception_upper":"1990-02-28",
    "iso:country":"GB",
    "wof:name":"PL15 9QZ",
    "wof:placetype":"postalcode"
},
  "geometry": {"coordinates":[-4.339869,50.627616],"type":"Point"}
}