{
  "type": "Feature",
  "properties": {
    "iso:country":"GB",
    "wof:name":"SY10 9AX",
    "wof:placetype":"postalcode"
},
  "geometry": {"coordinates":[-3.10659465813148,52.8429211210515],"type":"Point"}
}