{
  "type": "Feature",
  "properties": {
    "iso:country":"GB",
    "wof:name":"S6 1QE",
    "wof:placetype":"postalcode"
},
  "geometry": {"coordinates":[-1.49841036899223,53.41177808787253],"type":"Point"}
}