{
  "type": "Feature",
  "properties": {
    "iso:country":"GB",
    "wof:name":"SO18 2RG",
    "wof:placetype":"postalcode"
},
  "geometry": {"coordinates":[-1.37055835357257,50.93802194361226],"type":"Point"}
}