{
  "type": "Feature",
  "properties": {
    "date:inception_lower": "2020-11-01",
    "date:inception_upper": "2020-11-01",
    "iso:country": "GB",
    "wof:name": "PO6 2ZJ",
    "wof:placetype": "postalcode"
  },
  "geometry": {"coordinates":[-1.069603,50.844674],"type":"Point"}
}
