{
  "type": "Feature",
  "properties": {
    "date:inception_lower": "2018-06-01",
    "date:inception_upper": "2018-06-01",
    "iso:country": "GB",
    "wof:name": "RH13 9FN",
    "wof:placetype": "postalcode"
  },
  "geometry": {"coordinates":[-0.353063,51.030029],"type":"Point"}
}
