{
  "type": "Feature",
  "properties": {
    "date:inception_lower": "2013-09-01",
    "date:inception_upper": "2013-09-01",
    "iso:country": "GB",
    "wof:name": "BN7 2FJ",
    "wof:placetype": "postalcode"
  },
  "geometry": {"coordinates":[0.016932,50.873951],"type":"Point"}
}
