{
  "type": "Feature",
  "properties": {
    "iso:country":"GB",
    "wof:name":"GU8 5DQ",
    "wof:placetype":"postalcode"
},
  "geometry": {"coordinates":[-0.64993449088021,51.1682161947316],"type":"Point"}
}