{
  "type": "Feature",
  "properties": {
    "iso:country": "GB",
    "wof:name": "TR27 5LL",
    "wof:placetype": "postalcode"
  },
  "geometry": {"coordinates":[-5.386072,50.192994],"type":"Point"}
}
