{
  "type": "Feature",
  "properties": {
    "iso:country":"GB",
    "wof:name":"TR27 5LL",
    "wof:placetype":"postalcode"
},
  "geometry": {"coordinates":[-5.38578569922722,50.19304584668],"type":"Point"}
}