{
  "type": "Feature",
  "properties": {
    "iso:country":"GB",
    "wof:name":"FY8 3BZ",
    "wof:placetype":"postalcode"
},
  "geometry": {"coordinates":[-3.02700548671166,53.76915537614713],"type":"Point"}
}