{
  "type": "Feature",
  "properties": {
    "date:inception_lower": "1980-01-01",
    "date:inception_upper": "1980-01-01",
    "iso:country": "GB",
    "wof:name": "FY8 3BZ",
    "wof:placetype": "postalcode"
  },
  "geometry": {"coordinates":[-3.027005,53.769155],"type":"Point"}
}
