{
  "type": "Feature",
  "properties": {
    "date:inception_lower": "1980-01-01",
    "date:inception_upper": "1980-01-01",
    "iso:country": "GB",
    "wof:name": "PA20 9BN",
    "wof:placetype": "postalcode"
  },
  "geometry": {"coordinates":[-5.055757,55.833342],"type":"Point"}
}
