{
  "type": "Feature",
  "properties": {
    "iso:country": "GB",
    "wof:name": "BD1 2AF",
    "wof:placetype": "postalcode"
  },
  "geometry": {"coordinates":[-1.758405,53.793353],"type":"Point"}
}
