{
  "type": "Feature",
  "properties": {
    "date:inception_lower": "1980-01-01",
    "date:inception_upper": "1980-01-01",
    "iso:country": "GB",
    "wof:name": "TN38 8EE",
    "wof:placetype": "postalcode"
  },
  "geometry": {"coordinates":[0.508446,50.872964],"type":"Point"}
}
