{
  "type": "Feature",
  "properties": {
    "iso:country": "GB",
    "wof:name": "TN38 8EE",
    "wof:placetype": "postalcode"
  },
  "geometry": {"coordinates":[0.508446,50.872964],"type":"Point"}
}
