{
  "type": "Feature",
  "properties": {
    "iso:country":"GB",
    "wof:name":"TN38 8EE",
    "wof:placetype":"postalcode"
},
  "geometry": {"coordinates":[0.5084463384342,50.87296400786059],"type":"Point"}
}