{
  "type": "Feature",
  "properties": {
    "iso:country":"GB",
    "wof:name":"KA8 8BQ",
    "wof:placetype":"postalcode"
},
  "geometry": {"coordinates":[-4.6331521343179,55.46881565426146],"type":"Point"}
}