{
  "type": "Feature",
  "properties": {
    "iso:country": "GB",
    "wof:name": "SA73 2BW",
    "wof:placetype": "postalcode"
  },
  "geometry": {"coordinates":[-5.038606,51.716013],"type":"Point"}
}
