{
  "type": "Feature",
  "properties": {
    "iso:country": "GB",
    "wof:name": "LE5 6RA",
    "wof:placetype": "postalcode"
  },
  "geometry": {"coordinates":[-1.070175,52.636434],"type":"Point"}
}
