{
  "type": "Feature",
  "properties": {
    "date:inception_lower":"1980-01-01",
    "date:inception_upper":"1980-01-31",
    "iso:country":"GB",
    "wof:name":"LE5 6RA",
    "wof:placetype":"postalcode"
},
  "geometry": {"coordinates":[-1.070175,52.636434],"type":"Point"}
}