{
  "type": "Feature",
  "properties": {
    "iso:country": "GB",
    "wof:name": "TN15 7LT",
    "wof:placetype": "postalcode"
  },
  "geometry": {"coordinates":[0.330064,51.327074],"type":"Point"}
}
