{
  "type": "Feature",
  "properties": {
    "iso:country":"GB",
    "wof:name":"CR4 3WZ",
    "wof:placetype":"postalcode"
},
  "geometry": {"coordinates":[-0.17816689926814,51.40636080353388],"type":"Point"}
}