{
  "type": "Feature",
  "properties": {
    "date:inception_lower":"1995-12-01",
    "date:inception_upper":"1995-12-31",
    "iso:country":"GB",
    "wof:name":"CR4 3WZ",
    "wof:placetype":"postalcode"
},
  "geometry": {"coordinates":[-0.178167,51.406361],"type":"Point"}
}