{
  "type": "Feature",
  "properties": {
    "date:inception_lower": "2023-03-01",
    "date:inception_upper": "2023-03-01",
    "iso:country": "GB",
    "wof:name": "TN40 2FZ",
    "wof:placetype": "postalcode"
  },
  "geometry": {"coordinates":[0.488947,50.846575],"type":"Point"}
}
