{
  "type": "Feature",
  "properties": {
    "date:inception_lower": "2003-02-01",
    "date:inception_upper": "2003-02-01",
    "iso:country": "GB",
    "wof:name": "PO17 5FE",
    "wof:placetype": "postalcode"
  },
  "geometry": {"coordinates":[-1.204526,50.882991],"type":"Point"}
}
