{
  "type": "Feature",
  "properties": {
    "iso:country":"GB",
    "wof:name":"PO17 5FE",
    "wof:placetype":"postalcode"
},
  "geometry": {"coordinates":[-1.20452628757153,50.88299111865408],"type":"Point"}
}