{
  "type": "Feature",
  "properties": {
    "iso:country": "GB",
    "wof:name": "NN8 5EY",
    "wof:placetype": "postalcode"
  },
  "geometry": {"coordinates":[-0.707742,52.309879],"type":"Point"}
}
