{
  "type": "Feature",
  "properties": {
    "iso:country":"GB",
    "wof:name":"LL65 4EW",
    "wof:placetype":"postalcode"
},
  "geometry": {"coordinates":[-4.56065270401747,53.39730101322562],"type":"Point"}
}