{
  "type": "Feature",
  "properties": {
    "date:inception_lower": "1980-01-01",
    "date:inception_upper": "1980-01-01",
    "iso:country": "GB",
    "wof:name": "CO15 5EU",
    "wof:placetype": "postalcode"
  },
  "geometry": {"coordinates":[1.184242,51.799682],"type":"Point"}
}
