{
  "type": "Feature",
  "properties": {
    "iso:country": "GB",
    "wof:name": "CO15 5EU",
    "wof:placetype": "postalcode"
  },
  "geometry": {"coordinates":[1.184242,51.799682],"type":"Point"}
}
