{
  "type": "Feature",
  "properties": {
    "date:inception_lower": "2009-04-01",
    "date:inception_upper": "2009-04-01",
    "iso:country": "GB",
    "wof:name": "G21 3HT",
    "wof:placetype": "postalcode"
  },
  "geometry": {"coordinates":[-4.205129,55.883382],"type":"Point"}
}
