{
  "type": "Feature",
  "properties": {
    "iso:country":"GB",
    "wof:name":"G21 3HT",
    "wof:placetype":"postalcode"
},
  "geometry": {"coordinates":[-4.2051294869161,55.88338212351277],"type":"Point"}
}