{
  "type": "Feature",
  "properties": {
    "iso:country":"GB",
    "wof:name":"EH4 7SU",
    "wof:placetype":"postalcode"
},
  "geometry": {"coordinates":[-3.27022602250712,55.95926487749776],"type":"Point"}
}