{
  "type": "Feature",
  "properties": {
    "iso:country":"GB",
    "wof:name":"FY4 1HT",
    "wof:placetype":"postalcode"
},
  "geometry": {"coordinates":[-3.05039228752435,53.79554048195897],"type":"Point"}
}