{
  "type": "Feature",
  "properties": {
    "iso:country": "GB",
    "wof:name": "GL50 2TT",
    "wof:placetype": "postalcode"
  },
  "geometry": {"coordinates":[-2.089043,51.891596],"type":"Point"}
}
