{
  "type": "Feature",
  "properties": {
    "iso:country": "GB",
    "wof:name": "TN34 3BF",
    "wof:placetype": "postalcode"
  },
  "geometry": {"coordinates":[0.591258,50.862645],"type":"Point"}
}
