{
  "type": "Feature",
  "properties": {
    "iso:country": "GB",
    "wof:name": "SE23 2NU",
    "wof:placetype": "postalcode"
  },
  "geometry": {"coordinates":[-0.052063,51.432534],"type":"Point"}
}
