{
  "type": "Feature",
  "properties": {
    "iso:country":"GB",
    "wof:name":"SE23 2NU",
    "wof:placetype":"postalcode"
},
  "geometry": {"coordinates":[-0.05206272869968,51.43253367737409],"type":"Point"}
}