{
  "type": "Feature",
  "properties": {
    "iso:country":"GB",
    "wof:name":"CV37 0JW",
    "wof:placetype":"postalcode"
},
  "geometry": {"coordinates":[-1.69297063804218,52.23861887141393],"type":"Point"}
}