{
  "type": "Feature",
  "properties": {
    "iso:country": "GB",
    "wof:name": "CV37 0JW",
    "wof:placetype": "postalcode"
  },
  "geometry": {"coordinates":[-1.692971,52.238619],"type":"Point"}
}
