{
  "type": "Feature",
  "properties": {
    "date:inception_lower": "1992-01-01",
    "date:inception_upper": "1992-01-01",
    "iso:country": "GB",
    "wof:name": "WS9 0YZ",
    "wof:placetype": "postalcode"
  },
  "geometry": {"coordinates":[-1.894527,52.586958],"type":"Point"}
}
