{
  "type": "Feature",
  "properties": {
    "iso:country":"GB",
    "wof:name":"CV6 4GA",
    "wof:placetype":"postalcode"
},
  "geometry": {"coordinates":[-1.51184331085139,52.44340056469054],"type":"Point"}
}