{
  "type": "Feature",
  "properties": {
    "iso:country":"GB",
    "wof:name":"SW6 3SB",
    "wof:placetype":"postalcode"
},
  "geometry": {"coordinates":[-0.20636528674374,51.46690191399485],"type":"Point"}
}