{
  "type": "Feature",
  "properties": {
    "iso:country":"GB",
    "wof:name":"CT21 5HJ",
    "wof:placetype":"postalcode"
},
  "geometry": {"coordinates":[1.08021019758774,51.07810512281833],"type":"Point"}
}