{
  "type": "Feature",
  "properties": {
    "iso:country":"GB",
    "wof:name":"WD4 9JF",
    "wof:placetype":"postalcode"
},
  "geometry": {"coordinates":[-0.47582646186693,51.71002849813365],"type":"Point"}
}