{
  "type": "Feature",
  "properties": {
    "iso:country":"GB",
    "wof:name":"DL1 2PB",
    "wof:placetype":"postalcode"
},
  "geometry": {"coordinates":[-1.54706775302753,54.5352199043199],"type":"Point"}
}