{
  "type": "Feature",
  "properties": {
    "iso:country": "GB",
    "wof:name": "SN10 3JJ",
    "wof:placetype": "postalcode"
  },
  "geometry": {"coordinates":[-1.937042,51.340942],"type":"Point"}
}
