{
  "type": "Feature",
  "properties": {
    "iso:country":"GB",
    "wof:name":"SN10 3JJ",
    "wof:placetype":"postalcode"
},
  "geometry": {"coordinates":[-1.93704165811938,51.34094190722413],"type":"Point"}
}