{
  "type": "Feature",
  "properties": {
    "iso:country":"GB",
    "wof:name":"LS25 2EZ",
    "wof:placetype":"postalcode"
},
  "geometry": {"coordinates":[-1.3725484912797,53.79653441196966],"type":"Point"}
}