{
  "type": "Feature",
  "properties": {
    "iso:country":"GB",
    "wof:name":"W1T 5JX",
    "wof:placetype":"postalcode"
},
  "geometry": {"coordinates":[-0.1387033275929,51.52405596050841],"type":"Point"}
}