{
  "type": "Feature",
  "properties": {
    "date:inception_lower": "2000-10-01",
    "date:inception_upper": "2000-10-01",
    "iso:country": "GB",
    "wof:name": "W1T 5JX",
    "wof:placetype": "postalcode"
  },
  "geometry": {"coordinates":[-0.138605,51.524084],"type":"Point"}
}
