{
  "type": "Feature",
  "properties": {
    "iso:country":"GB",
    "wof:name":"SE13 5LD",
    "wof:placetype":"postalcode"
},
  "geometry": {"coordinates":[-0.00844056393602,51.4623309606818],"type":"Point"}
}