{
  "type": "Feature",
  "properties": {
    "date:inception_lower": "1980-01-01",
    "date:inception_upper": "1980-01-01",
    "iso:country": "GB",
    "wof:name": "SE13 5LD",
    "wof:placetype": "postalcode"
  },
  "geometry": {"coordinates":[-0.008853,51.462518],"type":"Point"}
}
