{
  "type": "Feature",
  "properties": {
    "iso:country":"GB",
    "wof:name":"BH14 0LP",
    "wof:placetype":"postalcode"
},
  "geometry": {"coordinates":[-1.95345047328089,50.72566819419042],"type":"Point"}
}