{
  "type": "Feature",
  "properties": {
    "iso:country": "GB",
    "wof:name": "ME13 9ST",
    "wof:placetype": "postalcode"
  },
  "geometry": {"coordinates":[0.956872,51.292942],"type":"Point"}
}
