{
  "type": "Feature",
  "properties": {
    "iso:country":"GB",
    "wof:name":"ME13 9ST",
    "wof:placetype":"postalcode"
},
  "geometry": {"coordinates":[0.956872094285,51.29294205596754],"type":"Point"}
}