{
  "type": "Feature",
  "properties": {
    "iso:country":"GB",
    "wof:name":"NR28 0QP",
    "wof:placetype":"postalcode"
},
  "geometry": {"coordinates":[1.37177228324331,52.85245560501176],"type":"Point"}
}