{
  "type": "Feature",
  "properties": {
    "iso:country": "GB",
    "wof:name": "NR28 0QP",
    "wof:placetype": "postalcode"
  },
  "geometry": {"coordinates":[1.371772,52.852456],"type":"Point"}
}
