{
  "type": "Feature",
  "properties": {
    "iso:country": "GB",
    "wof:name": "CH66 1TP",
    "wof:placetype": "postalcode"
  },
  "geometry": {"coordinates":[-2.920735,53.290508],"type":"Point"}
}
