{
  "type": "Feature",
  "properties": {
    "iso:country":"GB",
    "wof:name":"SW20 0NS",
    "wof:placetype":"postalcode"
},
  "geometry": {"coordinates":[-0.24416836157291,51.41598311375294],"type":"Point"}
}