{
  "type": "Feature",
  "properties": {
    "date:inception_lower": "2020-01-01",
    "date:inception_upper": "2020-01-01",
    "iso:country": "GB",
    "wof:name": "ME15 8ZA",
    "wof:placetype": "postalcode"
  },
  "geometry": {"coordinates":[0.564746,51.244362],"type":"Point"}
}
