{
  "type": "Feature",
  "properties": {
    "iso:country":"GB",
    "wof:name":"EN4 8JE",
    "wof:placetype":"postalcode"
},
  "geometry": {"coordinates":[-0.16402765002513,51.6405287612691],"type":"Point"}
}