{
  "type": "Feature",
  "properties": {
    "date:inception_lower":"2014-12-01",
    "date:inception_upper":"2014-12-31",
    "iso:country":"GB",
    "wof:name":"DT11 7GY",
    "wof:placetype":"postalcode"
},
  "geometry": {"coordinates":[-2.160416,50.86177],"type":"Point"}
}