{
  "type": "Feature",
  "properties": {
    "date:inception_lower":"1983-03-01",
    "date:inception_upper":"1983-03-31",
    "iso:country":"GB",
    "wof:name":"SS8 9UY",
    "wof:placetype":"postalcode"
},
  "geometry": {"coordinates":[0.587815,51.528873],"type":"Point"}
}