{
  "type": "Feature",
  "properties": {
    "iso:country":"GB",
    "wof:name":"SS8 9UY",
    "wof:placetype":"postalcode"
},
  "geometry": {"coordinates":[0.58781529786883,51.52887281235735],"type":"Point"}
}