{
  "type": "Feature",
  "properties": {
    "iso:country":"GB",
    "wof:name":"IG11 0EU",
    "wof:placetype":"postalcode"
},
  "geometry": {"coordinates":[0.09443895011998,51.52934207863159],"type":"Point"}
}