{
  "type": "Feature",
  "properties": {
    "iso:country": "GB",
    "wof:name": "DY12 2AY",
    "wof:placetype": "postalcode"
  },
  "geometry": {"coordinates":[-2.319564,52.375191],"type":"Point"}
}
