{
  "type": "Feature",
  "properties": {
    "iso:country":"GB",
    "wof:name":"DY12 2AY",
    "wof:placetype":"postalcode"
},
  "geometry": {"coordinates":[-2.3195641199583,52.37519117388888],"type":"Point"}
}