{
  "type": "Feature",
  "properties": {
    "iso:country":"GB",
    "wof:name":"CO15 4LH",
    "wof:placetype":"postalcode"
},
  "geometry": {"coordinates":[1.1701176344998,51.81133333162459],"type":"Point"}
}