{
  "type": "Feature",
  "properties": {
    "iso:country": "GB",
    "wof:name": "CO15 4LH",
    "wof:placetype": "postalcode"
  },
  "geometry": {"coordinates":[1.170118,51.811333],"type":"Point"}
}
