{
  "type": "Feature",
  "properties": {
    "date:inception_lower":"1980-01-01",
    "date:inception_upper":"1980-01-31",
    "iso:country":"GB",
    "wof:name":"CO15 4LH",
    "wof:placetype":"postalcode"
},
  "geometry": {"coordinates":[1.170118,51.811333],"type":"Point"}
}