{
  "type": "Feature",
  "properties": {
    "date:inception_lower": "1986-01-01",
    "date:inception_upper": "1986-01-01",
    "iso:country": "GB",
    "wof:name": "SO41 9GS",
    "wof:placetype": "postalcode"
  },
  "geometry": {"coordinates":[-1.552697,50.761331],"type":"Point"}
}
