{
  "type": "Feature",
  "properties": {
    "iso:country": "GB",
    "wof:name": "WS8 6DN",
    "wof:placetype": "postalcode"
  },
  "geometry": {"coordinates":[-1.924912,52.64198],"type":"Point"}
}
