{
  "type": "Feature",
  "properties": {
    "date:inception_lower": "2012-02-01",
    "date:inception_upper": "2012-02-01",
    "iso:country": "GB",
    "wof:name": "WS8 6DN",
    "wof:placetype": "postalcode"
  },
  "geometry": {"coordinates":[-1.924912,52.64198],"type":"Point"}
}
