{
  "type": "Feature",
  "properties": {
    "iso:country":"GB",
    "wof:name":"UB6 8LW",
    "wof:placetype":"postalcode"
},
  "geometry": {"coordinates":[-0.33243587894352,51.53692440830049],"type":"Point"}
}