{
  "type": "Feature",
  "properties": {
    "iso:country":"GB",
    "wof:name":"G72 9HW",
    "wof:placetype":"postalcode"
},
  "geometry": {"coordinates":[-4.10301011651584,55.79802134908017],"type":"Point"}
}