{
  "type": "Feature",
  "properties": {
    "date:inception_lower": "1980-01-01",
    "date:inception_upper": "1980-01-01",
    "iso:country": "GB",
    "wof:name": "G72 9HW",
    "wof:placetype": "postalcode"
  },
  "geometry": {"coordinates":[-4.10301,55.798021],"type":"Point"}
}
