{
  "type": "Feature",
  "properties": {
    "iso:country": "GB",
    "wof:name": "NE8 1BH",
    "wof:placetype": "postalcode"
  },
  "geometry": {"coordinates":[-1.603965,54.962407],"type":"Point"}
}
