{
  "type": "Feature",
  "properties": {
    "date:inception_lower":"1986-07-01",
    "date:inception_upper":"1986-07-31",
    "iso:country":"GB",
    "wof:name":"NE8 1BH",
    "wof:placetype":"postalcode"
},
  "geometry": {"coordinates":[-1.603965,54.962407],"type":"Point"}
}