{
  "type": "Feature",
  "properties": {
    "iso:country":"GB",
    "wof:name":"PL4 8JY",
    "wof:placetype":"postalcode"
},
  "geometry": {"coordinates":[-4.1344709203684,50.37965236769725],"type":"Point"}
}