{
  "type": "Feature",
  "properties": {
    "date:inception_lower": "1980-01-01",
    "date:inception_upper": "1980-01-01",
    "iso:country": "GB",
    "wof:name": "PL4 8JY",
    "wof:placetype": "postalcode"
  },
  "geometry": {"coordinates":[-4.134431,50.379707],"type":"Point"}
}
