{
  "type": "Feature",
  "properties": {
    "iso:country": "GB",
    "wof:name": "PL4 8JY",
    "wof:placetype": "postalcode"
  },
  "geometry": {"coordinates":[-4.134431,50.379707],"type":"Point"}
}
