{
  "type": "Feature",
  "properties": {
    "iso:country":"GB",
    "wof:name":"WV3 7EJ",
    "wof:placetype":"postalcode"
},
  "geometry": {"coordinates":[-2.15494910547922,52.56979538018206],"type":"Point"}
}