{
  "type": "Feature",
  "properties": {
    "iso:country":"GB",
    "wof:name":"W8 5BE",
    "wof:placetype":"postalcode"
},
  "geometry": {"coordinates":[-0.18886749859334,51.50120007058673],"type":"Point"}
}