{
  "type": "Feature",
  "properties": {
    "iso:country":"GB",
    "wof:name":"EH39 5JX",
    "wof:placetype":"postalcode"
},
  "geometry": {"coordinates":[-2.71148592048587,56.00631073665003],"type":"Point"}
}