{
  "type": "Feature",
  "properties": {
    "iso:country":"GB",
    "wof:name":"W1J 7QW",
    "wof:placetype":"postalcode"
},
  "geometry": {"coordinates":[-0.14662079605232,51.50657401897837],"type":"Point"}
}