{
  "type": "Feature",
  "properties": {
    "iso:country":"GB",
    "wof:name":"S11 8ZL",
    "wof:placetype":"postalcode"
},
  "geometry": {"coordinates":[-1.49801171706663,53.36766001357967],"type":"Point"}
}