{
  "type": "Feature",
  "properties": {
    "iso:country":"GB",
    "wof:name":"AL7 2LZ",
    "wof:placetype":"postalcode"
},
  "geometry": {"coordinates":[-0.1687236121443,51.79929623351521],"type":"Point"}
}