{
  "type": "Feature",
  "properties": {
    "date:inception_lower": "1980-01-01",
    "date:inception_upper": "1980-01-01",
    "iso:country": "GB",
    "wof:name": "LE12 6HA",
    "wof:placetype": "postalcode"
  },
  "geometry": {"coordinates":[-1.18606,52.832734],"type":"Point"}
}
