{
  "type": "Feature",
  "properties": {
    "iso:country":"GB",
    "wof:name":"LE12 6HA",
    "wof:placetype":"postalcode"
},
  "geometry": {"coordinates":[-1.18605966470894,52.83273391983426],"type":"Point"}
}