{
  "type": "Feature",
  "properties": {
    "iso:country":"GB",
    "wof:name":"TW4 7AJ",
    "wof:placetype":"postalcode"
},
  "geometry": {"coordinates":[-0.37975375515426,51.4663956457136],"type":"Point"}
}