{
  "type": "Feature",
  "properties": {
    "date:inception_lower":"1980-01-01",
    "date:inception_upper":"1980-01-31",
    "iso:country":"GB",
    "wof:name":"E1 4JG",
    "wof:placetype":"postalcode"
},
  "geometry": {"coordinates":[-0.051197,51.523804],"type":"Point"}
}