{
  "type": "Feature",
  "properties": {
    "iso:country":"GB",
    "wof:name":"E1 4JG",
    "wof:placetype":"postalcode"
},
  "geometry": {"coordinates":[-0.05119737497465,51.52380377659802],"type":"Point"}
}