{
  "type": "Feature",
  "properties": {
    "date:inception_lower": "1984-02-01",
    "date:inception_upper": "1984-02-01",
    "iso:country": "GB",
    "wof:name": "TA24 8TZ",
    "wof:placetype": "postalcode"
  },
  "geometry": {"coordinates":[-3.495083,51.205195],"type":"Point"}
}
