{
  "type": "Feature",
  "properties": {
    "iso:country": "GB",
    "wof:name": "TA24 8TZ",
    "wof:placetype": "postalcode"
  },
  "geometry": {"coordinates":[-3.495083,51.205195],"type":"Point"}
}
