{
  "type": "Feature",
  "properties": {
    "iso:country": "GB",
    "wof:name": "YO15 3TF",
    "wof:placetype": "postalcode"
  },
  "geometry": {"coordinates":[-0.209312,54.079227],"type":"Point"}
}
