{
  "type": "Feature",
  "properties": {
    "iso:country": "GB",
    "wof:name": "TS21 3FE",
    "wof:placetype": "postalcode"
  },
  "geometry": {"coordinates":[-1.447279,54.66996],"type":"Point"}
}
