{
  "type": "Feature",
  "properties": {
    "iso:country":"GB",
    "wof:name":"CT20 1DY",
    "wof:placetype":"postalcode"
},
  "geometry": {"coordinates":[1.18104471188075,51.08010686888703],"type":"Point"}
}