{
  "type": "Feature",
  "properties": {
    "iso:country": "GB",
    "wof:name": "SA73 1BB",
    "wof:placetype": "postalcode"
  },
  "geometry": {"coordinates":[-5.023805,51.717821],"type":"Point"}
}
