{
  "type": "Feature",
  "properties": {
    "iso:country":"GB",
    "wof:name":"SA73 1BB",
    "wof:placetype":"postalcode"
},
  "geometry": {"coordinates":[-5.02370999034984,51.71780058482697],"type":"Point"}
}