{
  "type": "Feature",
  "properties": {
    "date:inception_lower":"1992-01-01",
    "date:inception_upper":"1992-01-31",
    "iso:country":"GB",
    "wof:name":"SP10 5NJ",
    "wof:placetype":"postalcode"
},
  "geometry": {"coordinates":[-1.473994,51.227902],"type":"Point"}
}