{
  "type": "Feature",
  "properties": {
    "iso:country":"GB",
    "wof:name":"N8 8LL",
    "wof:placetype":"postalcode"
},
  "geometry": {"coordinates":[-0.12447736922132,51.58607521953975],"type":"Point"}
}