{
  "type": "Feature",
  "properties": {
    "iso:country":"GB",
    "wof:name":"NP16 6EF",
    "wof:placetype":"postalcode"
},
  "geometry": {"coordinates":[-2.70174487751223,51.66817294930989],"type":"Point"}
}