{
  "type": "Feature",
  "properties": {
    "iso:country": "GB",
    "wof:name": "RG24 7LQ",
    "wof:placetype": "postalcode"
  },
  "geometry": {"coordinates":[-1.034134,51.265285],"type":"Point"}
}
