{
  "type": "Feature",
  "properties": {
    "iso:country":"GB",
    "wof:name":"RG24 7LQ",
    "wof:placetype":"postalcode"
},
  "geometry": {"coordinates":[-1.03413453131891,51.26528538354986],"type":"Point"}
}