{
  "type": "Feature",
  "properties": {
    "iso:country": "GB",
    "wof:name": "HP2 6EP",
    "wof:placetype": "postalcode"
  },
  "geometry": {"coordinates":[-0.451919,51.776453],"type":"Point"}
}
