{
  "type": "Feature",
  "properties": {
    "iso:country":"GB",
    "wof:name":"SE1 5QT",
    "wof:placetype":"postalcode"
},
  "geometry": {"coordinates":[-0.07141055374293,51.49029873238899],"type":"Point"}
}