{
  "type": "Feature",
  "properties": {
    "iso:country":"GB",
    "wof:name":"SA48 8DH",
    "wof:placetype":"postalcode"
},
  "geometry": {"coordinates":[-4.19283203812726,52.22309966035661],"type":"Point"}
}