{
  "type": "Feature",
  "properties": {
    "iso:country":"GB",
    "wof:name":"FK5 3AH",
    "wof:placetype":"postalcode"
},
  "geometry": {"coordinates":[-3.83312562785378,56.01783016362719],"type":"Point"}
}