{
  "type": "Feature",
  "properties": {
    "iso:country":"GB",
    "wof:name":"B80 7LX",
    "wof:placetype":"postalcode"
},
  "geometry": {"coordinates":[-1.89229923750991,52.27186408721366],"type":"Point"}
}