{
  "type": "Feature",
  "properties": {
    "iso:country":"GB",
    "wof:name":"PE1 3QF",
    "wof:placetype":"postalcode"
},
  "geometry": {"coordinates":[-0.24521704751368,52.5938401222242],"type":"Point"}
}