{
  "type": "Feature",
  "properties": {
    "iso:country":"GB",
    "wof:name":"RH15 0QB",
    "wof:placetype":"postalcode"
},
  "geometry": {"coordinates":[-0.1133375480797,50.94963266515144],"type":"Point"}
}