{
  "type": "Feature",
  "properties": {
    "iso:country": "GB",
    "wof:name": "RH15 0QB",
    "wof:placetype": "postalcode"
  },
  "geometry": {"coordinates":[-0.113338,50.949633],"type":"Point"}
}
