{
  "type": "Feature",
  "properties": {
    "iso:country":"GB",
    "wof:name":"OX25 1QH",
    "wof:placetype":"postalcode"
},
  "geometry": {"coordinates":[-1.11391727042905,51.85085687608782],"type":"Point"}
}