{
  "type": "Feature",
  "properties": {
    "iso:country":"GB",
    "wof:name":"LS25 4BS",
    "wof:placetype":"postalcode"
},
  "geometry": {"coordinates":[-1.33743424714006,53.78589241922756],"type":"Point"}
}