{
  "type": "Feature",
  "properties": {
    "date:inception_lower": "1980-01-01",
    "date:inception_upper": "1980-01-01",
    "iso:country": "GB",
    "wof:name": "LS25 4BS",
    "wof:placetype": "postalcode"
  },
  "geometry": {"coordinates":[-1.337484,53.785874],"type":"Point"}
}
