{
  "type": "Feature",
  "properties": {
    "date:inception_lower": "2008-05-01",
    "date:inception_upper": "2008-05-01",
    "iso:country": "GB",
    "wof:name": "SO41 9NS",
    "wof:placetype": "postalcode"
  },
  "geometry": {"coordinates":[-1.543053,50.75731],"type":"Point"}
}
