{
  "type": "Feature",
  "properties": {
    "date:inception_lower":"1999-06-01",
    "date:inception_upper":"1999-06-30",
    "iso:country":"GB",
    "wof:name":"CF14 9ED",
    "wof:placetype":"postalcode"
},
  "geometry": {"coordinates":[-3.195758,51.539223],"type":"Point"}
}