{
  "type": "Feature",
  "properties": {
    "iso:country":"GB",
    "wof:name":"CF14 9ED",
    "wof:placetype":"postalcode"
},
  "geometry": {"coordinates":[-3.19575792277937,51.53922286241544],"type":"Point"}
}