{
  "type": "Feature",
  "properties": {
    "iso:country": "GB",
    "wof:name": "CF14 9ED",
    "wof:placetype": "postalcode"
  },
  "geometry": {"coordinates":[-3.195758,51.539223],"type":"Point"}
}
