{
  "type": "Feature",
  "properties": {
    "iso:country":"GB",
    "wof:name":"S44 6XB",
    "wof:placetype":"postalcode"
},
  "geometry": {"coordinates":[-1.26723240936141,53.23086007947212],"type":"Point"}
}