{
  "type": "Feature",
  "properties": {
    "iso:country":"GB",
    "wof:name":"NE3 4DJ",
    "wof:placetype":"postalcode"
},
  "geometry": {"coordinates":[-1.62098588761896,55.00282016746034],"type":"Point"}
}