{
  "type": "Feature",
  "properties": {
    "date:inception_lower": "1980-01-01",
    "date:inception_upper": "1980-01-01",
    "iso:country": "GB",
    "wof:name": "CV1 5AQ",
    "wof:placetype": "postalcode"
  },
  "geometry": {"coordinates":[-1.49388,52.415087],"type":"Point"}
}
