{
  "type": "Feature",
  "properties": {
    "iso:country":"GB",
    "wof:name":"HS2 9AZ",
    "wof:placetype":"postalcode"
},
  "geometry": {"coordinates":[-6.79351342419166,58.26886682793079],"type":"Point"}
}