{
  "type": "Feature",
  "properties": {
    "date:inception_lower":"1995-07-01",
    "date:inception_upper":"1995-07-31",
    "iso:country":"GB",
    "wof:name":"HS2 9AZ",
    "wof:placetype":"postalcode"
},
  "geometry": {"coordinates":[-6.793513,58.268867],"type":"Point"}
}