{
  "type": "Feature",
  "properties": {
    "iso:country":"GB",
    "wof:name":"SK4 1UG",
    "wof:placetype":"postalcode"
},
  "geometry": {"coordinates":[-2.16539372073388,53.42206349172663],"type":"Point"}
}