{
  "type": "Feature",
  "properties": {
    "date:inception_lower":"1981-06-01",
    "date:inception_upper":"1981-06-30",
    "iso:country":"GB",
    "wof:name":"NN9 6PB",
    "wof:placetype":"postalcode"
},
  "geometry": {"coordinates":[-0.528006,52.344405],"type":"Point"}
}