{
  "type": "Feature",
  "properties": {
    "date:inception_lower": "2021-08-01",
    "date:inception_upper": "2021-08-01",
    "iso:country": "GB",
    "wof:name": "TD6 9NR",
    "wof:placetype": "postalcode"
  },
  "geometry": {"coordinates":[-2.731368,55.606926],"type":"Point"}
}
