{
  "type": "Feature",
  "properties": {
    "iso:country": "GB",
    "wof:name": "CM77 8HB",
    "wof:placetype": "postalcode"
  },
  "geometry": {"coordinates":[0.577596,51.859672],"type":"Point"}
}
