{
  "type": "Feature",
  "properties": {
    "date:inception_lower": "2002-06-01",
    "date:inception_upper": "2002-06-01",
    "iso:country": "GB",
    "wof:name": "CM77 8HB",
    "wof:placetype": "postalcode"
  },
  "geometry": {"coordinates":[0.577596,51.859672],"type":"Point"}
}
