{
  "type": "Feature",
  "properties": {
    "date:inception_lower": "1980-01-01",
    "date:inception_upper": "1980-01-01",
    "iso:country": "GB",
    "wof:name": "E18 2HN",
    "wof:placetype": "postalcode"
  },
  "geometry": {"coordinates":[0.01293,51.58995],"type":"Point"}
}
