{
  "type": "Feature",
  "properties": {
    "iso:country":"GB",
    "wof:name":"E18 2HN",
    "wof:placetype":"postalcode"
},
  "geometry": {"coordinates":[0.01292977766731,51.58994968269539],"type":"Point"}
}