{
  "type": "Feature",
  "properties": {
    "iso:country":"GB",
    "wof:name":"NE25 9XQ",
    "wof:placetype":"postalcode"
},
  "geometry": {"coordinates":[-1.47412171931781,55.04968581136134],"type":"Point"}
}