{
  "type": "Feature",
  "properties": {
    "iso:country":"GB",
    "wof:name":"OL1 2TT",
    "wof:placetype":"postalcode"
},
  "geometry": {"coordinates":[-2.16394043254305,53.55247870814179],"type":"Point"}
}