{
  "type": "Feature",
  "properties": {
    "iso:country":"GB",
    "wof:name":"DL14 9HB",
    "wof:placetype":"postalcode"
},
  "geometry": {"coordinates":[-1.71658331076279,54.63362877451824],"type":"Point"}
}