{
  "type": "Feature",
  "properties": {
    "date:inception_lower": "1980-01-01",
    "date:inception_upper": "1980-01-01",
    "iso:country": "GB",
    "wof:name": "EN10 7EH",
    "wof:placetype": "postalcode"
  },
  "geometry": {"coordinates":[-0.024763,51.746213],"type":"Point"}
}
