{
  "type": "Feature",
  "properties": {
    "iso:country":"GB",
    "wof:name":"EN10 7EH",
    "wof:placetype":"postalcode"
},
  "geometry": {"coordinates":[-0.02476341587796,51.74621319096526],"type":"Point"}
}