{
  "type": "Feature",
  "properties": {
    "iso:country": "GB",
    "wof:name": "EN10 7EH",
    "wof:placetype": "postalcode"
  },
  "geometry": {"coordinates":[-0.024763,51.746213],"type":"Point"}
}
