{
  "type": "Feature",
  "properties": {
    "iso:country": "GB",
    "wof:name": "CO14 8LD",
    "wof:placetype": "postalcode"
  },
  "geometry": {"coordinates":[1.286788,51.861995],"type":"Point"}
}
