{
  "type": "Feature",
  "properties": {
    "iso:country":"GB",
    "wof:name":"RM5 2ND",
    "wof:placetype":"postalcode"
},
  "geometry": {"coordinates":[0.15898763418342,51.59910695150555],"type":"Point"}
}