{
  "type": "Feature",
  "properties": {
    "iso:country":"GB",
    "wof:name":"PE1 5AT",
    "wof:placetype":"postalcode"
},
  "geometry": {"coordinates":[-0.22917292910106,52.57249061847381],"type":"Point"}
}