{
  "type": "Feature",
  "properties": {
    "iso:country": "GB",
    "wof:name": "PE1 5AT",
    "wof:placetype": "postalcode"
  },
  "geometry": {"coordinates":[-0.229173,52.572491],"type":"Point"}
}
