{
  "type": "Feature",
  "properties": {
    "iso:country":"GB",
    "wof:name":"HU6 7UL",
    "wof:placetype":"postalcode"
},
  "geometry": {"coordinates":[-0.3605084979916,53.77847525204853],"type":"Point"}
}