{
  "type": "Feature",
  "properties": {
    "iso:country":"GB",
    "wof:name":"OL9 9EW",
    "wof:placetype":"postalcode"
},
  "geometry": {"coordinates":[-2.14176800940657,53.54356369266356],"type":"Point"}
}