{
  "type": "Feature",
  "properties": {
    "iso:country": "GB",
    "wof:name": "OL9 9EW",
    "wof:placetype": "postalcode"
  },
  "geometry": {"coordinates":[-2.141768,53.543564],"type":"Point"}
}
