{
  "type": "Feature",
  "properties": {
    "iso:country": "GB",
    "wof:name": "LL29 8BL",
    "wof:placetype": "postalcode"
  },
  "geometry": {"coordinates":[-3.681677,53.292099],"type":"Point"}
}
