{
  "type": "Feature",
  "properties": {
    "date:inception_lower": "2008-05-01",
    "date:inception_upper": "2008-05-01",
    "iso:country": "GB",
    "wof:name": "LL29 8BL",
    "wof:placetype": "postalcode"
  },
  "geometry": {"coordinates":[-3.681958,53.292374],"type":"Point"}
}
