{
  "type": "Feature",
  "properties": {
    "date:inception_lower":"2008-05-01",
    "date:inception_upper":"2008-05-31",
    "iso:country":"GB",
    "wof:name":"LL29 8BL",
    "wof:placetype":"postalcode"
},
  "geometry": {"coordinates":[-3.681377,53.292104],"type":"Point"}
}