{
  "type": "Feature",
  "properties": {
    "date:inception_lower": "2020-12-01",
    "date:inception_upper": "2020-12-01",
    "iso:country": "GB",
    "wof:name": "NR6 5FL",
    "wof:placetype": "postalcode"
  },
  "geometry": {"coordinates":[1.261239,52.654883],"type":"Point"}
}
