{
  "type": "Feature",
  "properties": {
    "iso:country":"GB",
    "wof:name":"PE30 5GH",
    "wof:placetype":"postalcode"
},
  "geometry": {"coordinates":[0.39478487494647,52.75136415677383],"type":"Point"}
}