{
  "type": "Feature",
  "properties": {
    "iso:country":"GB",
    "wof:name":"NW2 3XJ",
    "wof:placetype":"postalcode"
},
  "geometry": {"coordinates":[-0.20888514537097,51.5517750682539],"type":"Point"}
}