{
  "type": "Feature",
  "properties": {
    "iso:country":"GB",
    "wof:name":"ST17 9JS",
    "wof:placetype":"postalcode"
},
  "geometry": {"coordinates":[-2.11263193167874,52.78120825668834],"type":"Point"}
}