{
  "type": "Feature",
  "properties": {
    "iso:country":"GB",
    "wof:name":"RH10 3SW",
    "wof:placetype":"postalcode"
},
  "geometry": {"coordinates":[-0.1521693330723,51.13981106215259],"type":"Point"}
}