{
  "type": "Feature",
  "properties": {
    "date:inception_lower": "2015-03-01",
    "date:inception_upper": "2015-03-01",
    "iso:country": "GB",
    "wof:name": "RH10 3SW",
    "wof:placetype": "postalcode"
  },
  "geometry": {"coordinates":[-0.153358,51.136571],"type":"Point"}
}
