{
  "type": "Feature",
  "properties": {
    "date:inception_lower": "2017-07-01",
    "date:inception_upper": "2017-07-01",
    "iso:country": "GB",
    "wof:name": "CB8 9EU",
    "wof:placetype": "postalcode"
  },
  "geometry": {"coordinates":[0.465126,52.215897],"type":"Point"}
}
