{
  "type": "Feature",
  "properties": {
    "date:inception_lower": "1980-01-01",
    "date:inception_upper": "1980-01-01",
    "iso:country": "GB",
    "wof:name": "BB4 5PR",
    "wof:placetype": "postalcode"
  },
  "geometry": {"coordinates":[-2.320231,53.701448],"type":"Point"}
}
