{
  "type": "Feature",
  "properties": {
    "iso:country":"GB",
    "wof:name":"CW9 8ER",
    "wof:placetype":"postalcode"
},
  "geometry": {"coordinates":[-2.51024811174796,53.24415258671035],"type":"Point"}
}