{
  "type": "Feature",
  "properties": {
    "iso:country": "GB",
    "wof:name": "CW9 8ER",
    "wof:placetype": "postalcode"
  },
  "geometry": {"coordinates":[-2.510248,53.244153],"type":"Point"}
}
