{
  "type": "Feature",
  "properties": {
    "date:inception_lower": "2005-11-01",
    "date:inception_upper": "2005-11-01",
    "iso:country": "GB",
    "wof:name": "BB6 7EN",
    "wof:placetype": "postalcode"
  },
  "geometry": {"coordinates":[-2.401085,53.785585],"type":"Point"}
}
