{
  "type": "Feature",
  "properties": {
    "iso:country": "GB",
    "wof:name": "BB6 7EN",
    "wof:placetype": "postalcode"
  },
  "geometry": {"coordinates":[-2.401085,53.785585],"type":"Point"}
}
