{
  "type": "Feature",
  "properties": {
    "iso:country":"GB",
    "wof:name":"BB6 7EN",
    "wof:placetype":"postalcode"
},
  "geometry": {"coordinates":[-2.40108478855442,53.78558470567422],"type":"Point"}
}