{
  "type": "Feature",
  "properties": {
    "iso:country": "GB",
    "wof:name": "CR2 7EW",
    "wof:placetype": "postalcode"
  },
  "geometry": {"coordinates":[-0.091266,51.364861],"type":"Point"}
}
