{
  "type": "Feature",
  "properties": {
    "iso:country":"GB",
    "wof:name":"CR2 7EW",
    "wof:placetype":"postalcode"
},
  "geometry": {"coordinates":[-0.09126604957623,51.36486096116137],"type":"Point"}
}