{
  "type": "Feature",
  "properties": {
    "date:inception_lower":"1993-08-01",
    "date:inception_upper":"1993-08-31",
    "iso:country":"GB",
    "wof:name":"CR2 7EW",
    "wof:placetype":"postalcode"
},
  "geometry": {"coordinates":[-0.091266,51.364861],"type":"Point"}
}