{
  "type": "Feature",
  "properties": {
    "iso:country":"GB",
    "wof:name":"UB5 5AL",
    "wof:placetype":"postalcode"
},
  "geometry": {"coordinates":[-0.37393807671662,51.5432889548483],"type":"Point"}
}