{
  "type": "Feature",
  "properties": {
    "iso:country":"GB",
    "wof:name":"DN3 2LH",
    "wof:placetype":"postalcode"
},
  "geometry": {"coordinates":[-1.06310931942093,53.5504520696789],"type":"Point"}
}