{
  "type": "Feature",
  "properties": {
    "date:inception_lower":"1999-06-01",
    "date:inception_upper":"1999-06-30",
    "iso:country":"GB",
    "wof:name":"CF11 7JE",
    "wof:placetype":"postalcode"
},
  "geometry": {"coordinates":[-3.187679,51.465392],"type":"Point"}
}