{
  "type": "Feature",
  "properties": {
    "date:inception_lower":"1980-01-01",
    "date:inception_upper":"1980-01-31",
    "iso:country":"GB",
    "wof:name":"DE12 7DE",
    "wof:placetype":"postalcode"
},
  "geometry": {"coordinates":[-1.477959,52.673659],"type":"Point"}
}