{
  "type": "Feature",
  "properties": {
    "iso:country": "GB",
    "wof:name": "DE12 7DE",
    "wof:placetype": "postalcode"
  },
  "geometry": {"coordinates":[-1.477959,52.673659],"type":"Point"}
}
