{
  "type": "Feature",
  "properties": {
    "iso:country":"GB",
    "wof:name":"DE12 7DE",
    "wof:placetype":"postalcode"
},
  "geometry": {"coordinates":[-1.47795856175038,52.67365896749084],"type":"Point"}
}