{
  "type": "Feature",
  "properties": {
    "iso:country": "GB",
    "wof:name": "DT9 3HG",
    "wof:placetype": "postalcode"
  },
  "geometry": {"coordinates":[-2.523413,50.944595],"type":"Point"}
}
