{
  "type": "Feature",
  "properties": {
    "iso:country":"GB",
    "wof:name":"DT9 3HG",
    "wof:placetype":"postalcode"
},
  "geometry": {"coordinates":[-2.52341344634272,50.9445945518892],"type":"Point"}
}