{
  "type": "Feature",
  "properties": {
    "iso:country": "GB",
    "wof:name": "DT1 3BQ",
    "wof:placetype": "postalcode"
  },
  "geometry": {"coordinates":[-2.467731,50.711753],"type":"Point"}
}
