{
  "type": "Feature",
  "properties": {
    "iso:country":"GB",
    "wof:name":"CV34 6AU",
    "wof:placetype":"postalcode"
},
  "geometry": {"coordinates":[-1.59405665008369,52.2747493173686],"type":"Point"}
}