{
  "type": "Feature",
  "properties": {
    "iso:country":"GB",
    "wof:name":"G66 4DQ",
    "wof:placetype":"postalcode"
},
  "geometry": {"coordinates":[-4.17037876310525,55.92394810771412],"type":"Point"}
}