{
  "type": "Feature",
  "properties": {
    "iso:country":"GB",
    "wof:name":"SE4 2EW",
    "wof:placetype":"postalcode"
},
  "geometry": {"coordinates":[-0.03908580695952,51.46377380251619],"type":"Point"}
}