{
  "type": "Feature",
  "properties": {
    "date:inception_lower": "1980-01-01",
    "date:inception_upper": "1980-01-01",
    "iso:country": "GB",
    "wof:name": "LA10 5QX",
    "wof:placetype": "postalcode"
  },
  "geometry": {"coordinates":[-2.435405,54.270845],"type":"Point"}
}
