{
  "type": "Feature",
  "properties": {
    "date:inception_lower": "2016-02-01",
    "date:inception_upper": "2016-02-01",
    "iso:country": "GB",
    "wof:name": "DE73 6WE",
    "wof:placetype": "postalcode"
  },
  "geometry": {"coordinates":[-1.432688,52.877534],"type":"Point"}
}
