{
  "type": "Feature",
  "properties": {
    "iso:country":"GB",
    "wof:name":"DE73 6WE",
    "wof:placetype":"postalcode"
},
  "geometry": {"coordinates":[-1.43100441044903,52.87596126885089],"type":"Point"}
}