{
  "type": "Feature",
  "properties": {
    "date:inception_lower":"1980-01-01",
    "date:inception_upper":"1980-01-31",
    "iso:country":"GB",
    "wof:name":"BS15 4SU",
    "wof:placetype":"postalcode"
},
  "geometry": {"coordinates":[-2.489133,51.469516],"type":"Point"}
}