{
  "type": "Feature",
  "properties": {
    "date:inception_lower": "2013-09-01",
    "date:inception_upper": "2013-09-01",
    "iso:country": "GB",
    "wof:name": "SS0 7FR",
    "wof:placetype": "postalcode"
  },
  "geometry": {"coordinates":[0.702528,51.546107],"type":"Point"}
}
