{
  "type": "Feature",
  "properties": {
    "iso:country":"GB",
    "wof:name":"SS0 7FR",
    "wof:placetype":"postalcode"
},
  "geometry": {"coordinates":[0.70252808926106,51.54610702764282],"type":"Point"}
}