{
  "type": "Feature",
  "properties": {
    "iso:country": "GB",
    "wof:name": "ST6 6AB",
    "wof:placetype": "postalcode"
  },
  "geometry": {"coordinates":[-2.20391,53.055637],"type":"Point"}
}
