{
  "type": "Feature",
  "properties": {
    "iso:country":"GB",
    "wof:name":"ST6 6AB",
    "wof:placetype":"postalcode"
},
  "geometry": {"coordinates":[-2.20390989003972,53.05565561407051],"type":"Point"}
}