{
  "type": "Feature",
  "properties": {
    "iso:country":"GB",
    "wof:name":"NE47 6HW",
    "wof:placetype":"postalcode"
},
  "geometry": {"coordinates":[-2.26729394619728,54.98079376310736],"type":"Point"}
}