{
  "type": "Feature",
  "properties": {
    "iso:country":"GB",
    "wof:name":"LL14 3PN",
    "wof:placetype":"postalcode"
},
  "geometry": {"coordinates":[-3.07205600046442,52.96800665667339],"type":"Point"}
}