{
  "type": "Feature",
  "properties": {
    "iso:country": "GB",
    "wof:name": "BS25 5NW",
    "wof:placetype": "postalcode"
  },
  "geometry": {"coordinates":[-2.793991,51.332961],"type":"Point"}
}
