{
  "type": "Feature",
  "properties": {
    "date:inception_lower":"1997-12-01",
    "date:inception_upper":"1997-12-31",
    "iso:country":"GB",
    "wof:name":"BS25 5NW",
    "wof:placetype":"postalcode"
},
  "geometry": {"coordinates":[-2.793991,51.332961],"type":"Point"}
}