{
  "type": "Feature",
  "properties": {
    "iso:country":"GB",
    "wof:name":"BS25 5NW",
    "wof:placetype":"postalcode"
},
  "geometry": {"coordinates":[-2.7939910298482,51.33296088047803],"type":"Point"}
}