{
  "type": "Feature",
  "properties": {
    "date:inception_lower": "1980-01-01",
    "date:inception_upper": "1980-01-01",
    "iso:country": "GB",
    "wof:name": "ST14 7LP",
    "wof:placetype": "postalcode"
  },
  "geometry": {"coordinates":[-1.8852,52.902744],"type":"Point"}
}
