{
  "type": "Feature",
  "properties": {
    "iso:country": "GB",
    "wof:name": "LE5 6PY",
    "wof:placetype": "postalcode"
  },
  "geometry": {"coordinates":[-1.064903,52.632113],"type":"Point"}
}
