{
  "type": "Feature",
  "properties": {
    "iso:country": "GB",
    "wof:name": "NG19 8NS",
    "wof:placetype": "postalcode"
  },
  "geometry": {"coordinates":[-1.195748,53.174631],"type":"Point"}
}
