{
  "type": "Feature",
  "properties": {
    "iso:country":"GB",
    "wof:name":"NG19 8NS",
    "wof:placetype":"postalcode"
},
  "geometry": {"coordinates":[-1.19574842129261,53.17463093245487],"type":"Point"}
}