{
  "type": "Feature",
  "properties": {
    "date:inception_lower":"2007-08-01",
    "date:inception_upper":"2007-08-31",
    "iso:country":"GB",
    "wof:name":"NG18 4FX",
    "wof:placetype":"postalcode"
},
  "geometry": {"coordinates":[-1.19638,53.132809],"type":"Point"}
}