{
  "type": "Feature",
  "properties": {
    "iso:country":"GB",
    "wof:name":"NG18 4FX",
    "wof:placetype":"postalcode"
},
  "geometry": {"coordinates":[-1.19637988388517,53.13280854797814],"type":"Point"}
}