{
  "type": "Feature",
  "properties": {
    "iso:country":"GB",
    "wof:name":"BD21 3EJ",
    "wof:placetype":"postalcode"
},
  "geometry": {"coordinates":[-1.90302543368091,53.87138679294637],"type":"Point"}
}