{
  "type": "Feature",
  "properties": {
    "date:inception_lower":"1980-01-01",
    "date:inception_upper":"1980-01-31",
    "iso:country":"GB",
    "wof:name":"ST13 5AT",
    "wof:placetype":"postalcode"
},
  "geometry": {"coordinates":[-2.015538,53.10473],"type":"Point"}
}