{
  "type": "Feature",
  "properties": {
    "iso:country":"GB",
    "wof:name":"FY1 4PP",
    "wof:placetype":"postalcode"
},
  "geometry": {"coordinates":[-3.04886721048807,53.81472608924147],"type":"Point"}
}