{
  "type": "Feature",
  "properties": {
    "iso:country":"GB",
    "wof:name":"WF17 9DY",
    "wof:placetype":"postalcode"
},
  "geometry": {"coordinates":[-1.66239573479626,53.73173663422543],"type":"Point"}
}