{
  "type": "Feature",
  "properties": {
    "iso:country":"GB",
    "wof:name":"PR4 1RR",
    "wof:placetype":"postalcode"
},
  "geometry": {"coordinates":[-2.87643582419832,53.75154743260052],"type":"Point"}
}