{
  "type": "Feature",
  "properties": {
    "iso:country": "GB",
    "wof:name": "PR4 1RR",
    "wof:placetype": "postalcode"
  },
  "geometry": {"coordinates":[-2.876436,53.751547],"type":"Point"}
}
