{
  "type": "Feature",
  "properties": {
    "date:inception_lower": "2018-12-01",
    "date:inception_upper": "2018-12-01",
    "iso:country": "GB",
    "wof:name": "BB3 1BF",
    "wof:placetype": "postalcode"
  },
  "geometry": {"coordinates":[-2.471714,53.699956],"type":"Point"}
}
