{
  "type": "Feature",
  "properties": {
    "iso:country":"GB",
    "wof:name":"SE2 9AF",
    "wof:placetype":"postalcode"
},
  "geometry": {"coordinates":[0.12355289736453,51.49721777114058],"type":"Point"}
}