{
  "type": "Feature",
  "properties": {
    "iso:country":"GB",
    "wof:name":"B68 9HL",
    "wof:placetype":"postalcode"
},
  "geometry": {"coordinates":[-1.99243364039957,52.47129569941941],"type":"Point"}
}