{
  "type": "Feature",
  "properties": {
    "iso:country":"GB",
    "wof:name":"BL6 6TA",
    "wof:placetype":"postalcode"
},
  "geometry": {"coordinates":[-2.52420225870545,53.58923783079962],"type":"Point"}
}