{
  "type": "Feature",
  "properties": {
    "iso:country":"GB",
    "wof:name":"NG2 6AJ",
    "wof:placetype":"postalcode"
},
  "geometry": {"coordinates":[-1.13026864796776,52.93718434694263],"type":"Point"}
}