{
  "type": "Feature",
  "properties": {
    "iso:country": "GB",
    "wof:name": "EX19 8DP",
    "wof:placetype": "postalcode"
  },
  "geometry": {"coordinates":[-3.955345,50.862903],"type":"Point"}
}
