{
  "type": "Feature",
  "properties": {
    "iso:country":"GB",
    "wof:name":"EX19 8DP",
    "wof:placetype":"postalcode"
},
  "geometry": {"coordinates":[-3.95534553145659,50.86290315253152],"type":"Point"}
}