{
  "type": "Feature",
  "properties": {
    "date:inception_lower":"1980-01-01",
    "date:inception_upper":"1980-01-31",
    "iso:country":"GB",
    "wof:name":"EX19 8DP",
    "wof:placetype":"postalcode"
},
  "geometry": {"coordinates":[-3.955345,50.862903],"type":"Point"}
}