{
  "type": "Feature",
  "properties": {
    "iso:country":"GB",
    "wof:name":"CO15 5RL",
    "wof:placetype":"postalcode"
},
  "geometry": {"coordinates":[1.19688234067889,51.80979865965229],"type":"Point"}
}