{
  "type": "Feature",
  "properties": {
    "iso:country":"GB",
    "wof:name":"LE4 2FN",
    "wof:placetype":"postalcode"
},
  "geometry": {"coordinates":[-1.13836123019581,52.66102444989249],"type":"Point"}
}