{
  "type": "Feature",
  "properties": {
    "date:inception_lower": "1999-12-01",
    "date:inception_upper": "1999-12-01",
    "iso:country": "GB",
    "wof:name": "CF31 4GE",
    "wof:placetype": "postalcode"
  },
  "geometry": {"coordinates":[-3.589695,51.524645],"type":"Point"}
}
