{
  "type": "Feature",
  "properties": {
    "iso:country":"GB",
    "wof:name":"SW7 1BQ",
    "wof:placetype":"postalcode"
},
  "geometry": {"coordinates":[-0.1676653783159,51.50139229491352],"type":"Point"}
}