{
  "type": "Feature",
  "properties": {
    "iso:country": "GB",
    "wof:name": "B25 8TF",
    "wof:placetype": "postalcode"
  },
  "geometry": {"coordinates":[-1.816847,52.469384],"type":"Point"}
}
