{
  "type": "Feature",
  "properties": {
    "date:inception_lower": "2022-10-01",
    "date:inception_upper": "2022-10-01",
    "iso:country": "GB",
    "wof:name": "E1 2FJ",
    "wof:placetype": "postalcode"
  },
  "geometry": {"coordinates":[-0.056781,51.518332],"type":"Point"}
}
