{
  "type": "Feature",
  "properties": {
    "iso:country":"GB",
    "wof:name":"M44 6FP",
    "wof:placetype":"postalcode"
},
  "geometry": {"coordinates":[-2.40473258414747,53.45603479813254],"type":"Point"}
}