{
  "type": "Feature",
  "properties": {
    "iso:country": "GB",
    "wof:name": "DE4 5JU",
    "wof:placetype": "postalcode"
  },
  "geometry": {"coordinates":[-1.539244,53.127869],"type":"Point"}
}
