{
  "type": "Feature",
  "properties": {
    "date:inception_lower":"1980-01-01",
    "date:inception_upper":"1980-01-31",
    "iso:country":"GB",
    "wof:name":"DE4 5JU",
    "wof:placetype":"postalcode"
},
  "geometry": {"coordinates":[-1.539244,53.127869],"type":"Point"}
}