{
  "type": "Feature",
  "properties": {
    "iso:country": "GB",
    "wof:name": "FK8 1SU",
    "wof:placetype": "postalcode"
  },
  "geometry": {"coordinates":[-3.952746,56.128085],"type":"Point"}
}
