{
  "type": "Feature",
  "properties": {
    "iso:country":"GB",
    "wof:name":"EX36 4LL",
    "wof:placetype":"postalcode"
},
  "geometry": {"coordinates":[-3.79362489780587,50.98408663506066],"type":"Point"}
}