{
  "type": "Feature",
  "properties": {
    "iso:country": "GB",
    "wof:name": "PH1 4AS",
    "wof:placetype": "postalcode"
  },
  "geometry": {"coordinates":[-3.552266,56.51846],"type":"Point"}
}
