{
  "type": "Feature",
  "properties": {
    "date:inception_lower":"2008-02-01",
    "date:inception_upper":"2008-02-29",
    "iso:country":"GB",
    "wof:name":"DL1 2AF",
    "wof:placetype":"postalcode"
},
  "geometry": {"coordinates":[-1.532374,54.545715],"type":"Point"}
}