{
  "type": "Feature",
  "properties": {
    "iso:country":"GB",
    "wof:name":"FY4 2QJ",
    "wof:placetype":"postalcode"
},
  "geometry": {"coordinates":[-3.03859210598317,53.78063263487785],"type":"Point"}
}