{
  "type": "Feature",
  "properties": {
    "iso:country": "GB",
    "wof:name": "NG16 5LL",
    "wof:placetype": "postalcode"
  },
  "geometry": {"coordinates":[-1.341441,53.064069],"type":"Point"}
}
