{
  "type": "Feature",
  "properties": {
    "iso:country":"GB",
    "wof:name":"BA4 5SH",
    "wof:placetype":"postalcode"
},
  "geometry": {"coordinates":[-2.55263059934538,51.18494793533961],"type":"Point"}
}