{
  "type": "Feature",
  "properties": {
    "iso:country":"GB",
    "wof:name":"PL21 0PF",
    "wof:placetype":"postalcode"
},
  "geometry": {"coordinates":[-3.84884549486783,50.39860299367326],"type":"Point"}
}