{
  "type": "Feature",
  "properties": {
    "iso:country": "GB",
    "wof:name": "PL21 0PF",
    "wof:placetype": "postalcode"
  },
  "geometry": {"coordinates":[-3.848868,50.398579],"type":"Point"}
}
