{
  "type": "Feature",
  "properties": {
    "date:inception_lower": "1996-06-01",
    "date:inception_upper": "1996-06-01",
    "iso:country": "GB",
    "wof:name": "PL21 0PF",
    "wof:placetype": "postalcode"
  },
  "geometry": {"coordinates":[-3.848868,50.398579],"type":"Point"}
}
