{
  "type": "Feature",
  "properties": {
    "iso:country":"GB",
    "wof:name":"S75 4DD",
    "wof:placetype":"postalcode"
},
  "geometry": {"coordinates":[-1.54201852278909,53.6067334346142],"type":"Point"}
}