{
  "type": "Feature",
  "properties": {
    "iso:country": "GB",
    "wof:name": "S75 4DD",
    "wof:placetype": "postalcode"
  },
  "geometry": {"coordinates":[-1.542018,53.606733],"type":"Point"}
}
