{
  "type": "Feature",
  "properties": {
    "date:inception_lower": "1980-01-01",
    "date:inception_upper": "1980-01-01",
    "iso:country": "GB",
    "wof:name": "S75 4DD",
    "wof:placetype": "postalcode"
  },
  "geometry": {"coordinates":[-1.542018,53.606733],"type":"Point"}
}
