{
  "type": "Feature",
  "properties": {
    "iso:country": "GB",
    "wof:name": "PE7 8AX",
    "wof:placetype": "postalcode"
  },
  "geometry": {"coordinates":[-0.266669,52.53995],"type":"Point"}
}
