{
  "type": "Feature",
  "properties": {
    "date:inception_lower": "1998-06-01",
    "date:inception_upper": "1998-06-01",
    "iso:country": "GB",
    "wof:name": "PE7 8AX",
    "wof:placetype": "postalcode"
  },
  "geometry": {"coordinates":[-0.266669,52.53995],"type":"Point"}
}
