{
  "type": "Feature",
  "properties": {
    "iso:country": "GB",
    "wof:name": "HA9 6DE",
    "wof:placetype": "postalcode"
  },
  "geometry": {"coordinates":[-0.27392,51.544612],"type":"Point"}
}
