{
  "type": "Feature",
  "properties": {
    "iso:country":"GB",
    "wof:name":"HA9 6DE",
    "wof:placetype":"postalcode"
},
  "geometry": {"coordinates":[-0.27392018828197,51.54461179265022],"type":"Point"}
}