{
  "type": "Feature",
  "properties": {
    "iso:country":"GB",
    "wof:name":"CF38 1TD",
    "wof:placetype":"postalcode"
},
  "geometry": {"coordinates":[-3.3132297504144,51.57369132915126],"type":"Point"}
}