{
  "type": "Feature",
  "properties": {
    "iso:country": "GB",
    "wof:name": "BD5 9BW",
    "wof:placetype": "postalcode"
  },
  "geometry": {"coordinates":[-1.77452,53.77744],"type":"Point"}
}
