{
  "type": "Feature",
  "properties": {
    "date:inception_lower": "2013-07-01",
    "date:inception_upper": "2013-07-01",
    "iso:country": "GB",
    "wof:name": "TF9 3GE",
    "wof:placetype": "postalcode"
  },
  "geometry": {"coordinates":[-2.513288,52.899061],"type":"Point"}
}
