{
  "type": "Feature",
  "properties": {
    "iso:country":"GB",
    "wof:name":"RH2 8LE",
    "wof:placetype":"postalcode"
},
  "geometry": {"coordinates":[-0.22104432957419,51.22863155299871],"type":"Point"}
}