{
  "type": "Feature",
  "properties": {
    "iso:country": "GB",
    "wof:name": "SA44 6BD",
    "wof:placetype": "postalcode"
  },
  "geometry": {"coordinates":[-4.36526,52.184011],"type":"Point"}
}
