{
  "type": "Feature",
  "properties": {
    "iso:country": "GB",
    "wof:name": "DL5 4QL",
    "wof:placetype": "postalcode"
  },
  "geometry": {"coordinates":[-1.57735,54.630204],"type":"Point"}
}
