{
  "type": "Feature",
  "properties": {
    "iso:country":"GB",
    "wof:name":"EX23 9QY",
    "wof:placetype":"postalcode"
},
  "geometry": {"coordinates":[-4.4933174831409,50.87294415833937],"type":"Point"}
}