{
  "type": "Feature",
  "properties": {
    "date:inception_lower":"1980-01-01",
    "date:inception_upper":"1980-01-31",
    "iso:country":"GB",
    "wof:name":"EX23 9QY",
    "wof:placetype":"postalcode"
},
  "geometry": {"coordinates":[-4.493317,50.872944],"type":"Point"}
}