{
  "type": "Feature",
  "properties": {
    "iso:country": "GB",
    "wof:name": "SW1P 3HX",
    "wof:placetype": "postalcode"
  },
  "geometry": {"coordinates":[-0.126134,51.495583],"type":"Point"}
}
