{
  "type": "Feature",
  "properties": {
    "iso:country": "GB",
    "wof:name": "G32 9QL",
    "wof:placetype": "postalcode"
  },
  "geometry": {"coordinates":[-4.142747,55.839382],"type":"Point"}
}
