{
  "type": "Feature",
  "properties": {
    "iso:country":"GB",
    "wof:name":"RM15 5QY",
    "wof:placetype":"postalcode"
},
  "geometry": {"coordinates":[0.28756673979806,51.50406095552935],"type":"Point"}
}