{
  "type": "Feature",
  "properties": {
    "date:inception_lower": "1992-01-01",
    "date:inception_upper": "1992-01-01",
    "iso:country": "GB",
    "wof:name": "ST6 6XL",
    "wof:placetype": "postalcode"
  },
  "geometry": {"coordinates":[-2.206506,53.080524],"type":"Point"}
}
