{
  "type": "Feature",
  "properties": {
    "iso:country":"GB",
    "wof:name":"CH45 3HY",
    "wof:placetype":"postalcode"
},
  "geometry": {"coordinates":[-3.06651236894576,53.42964814494221],"type":"Point"}
}