{
  "type": "Feature",
  "properties": {
    "date:inception_lower": "1999-06-01",
    "date:inception_upper": "1999-06-01",
    "iso:country": "GB",
    "wof:name": "CH45 3HY",
    "wof:placetype": "postalcode"
  },
  "geometry": {"coordinates":[-3.066512,53.429648],"type":"Point"}
}
