{
  "type": "Feature",
  "properties": {
    "date:inception_lower":"1993-01-01",
    "date:inception_upper":"1993-01-31",
    "iso:country":"GB",
    "wof:name":"WS15 4TQ",
    "wof:placetype":"postalcode"
},
  "geometry": {"coordinates":[-1.863601,52.735697],"type":"Point"}
}