{
  "type": "Feature",
  "properties": {
    "iso:country": "GB",
    "wof:name": "WS15 4TQ",
    "wof:placetype": "postalcode"
  },
  "geometry": {"coordinates":[-1.863601,52.735697],"type":"Point"}
}
