{
  "type": "Feature",
  "properties": {
    "iso:country": "GB",
    "wof:name": "BS23 1HE",
    "wof:placetype": "postalcode"
  },
  "geometry": {"coordinates":[-2.979289,51.348873],"type":"Point"}
}
