{
  "type": "Feature",
  "properties": {
    "iso:country":"GB",
    "wof:name":"DL10 4RR",
    "wof:placetype":"postalcode"
},
  "geometry": {"coordinates":[-1.73960919481193,54.4018183016772],"type":"Point"}
}