{
  "type": "Feature",
  "properties": {
    "iso:country": "GB",
    "wof:name": "DL10 4RR",
    "wof:placetype": "postalcode"
  },
  "geometry": {"coordinates":[-1.739609,54.401818],"type":"Point"}
}
