{
  "type": "Feature",
  "properties": {
    "iso:country": "GB",
    "wof:name": "PA4 9EJ",
    "wof:placetype": "postalcode"
  },
  "geometry": {"coordinates":[-4.407398,55.880427],"type":"Point"}
}
