{
  "type": "Feature",
  "properties": {
    "iso:country":"GB",
    "wof:name":"PA4 9EJ",
    "wof:placetype":"postalcode"
},
  "geometry": {"coordinates":[-4.40739758832375,55.88042679873509],"type":"Point"}
}