{
  "type": "Feature",
  "properties": {
    "iso:country": "GB",
    "wof:name": "SA17 4NN",
    "wof:placetype": "postalcode"
  },
  "geometry": {"coordinates":[-4.273109,51.756248],"type":"Point"}
}
