{
  "type": "Feature",
  "properties": {
    "date:inception_lower": "1980-01-01",
    "date:inception_upper": "1980-01-01",
    "iso:country": "GB",
    "wof:name": "SA17 4NN",
    "wof:placetype": "postalcode"
  },
  "geometry": {"coordinates":[-4.274876,51.755935],"type":"Point"}
}
