{
  "type": "Feature",
  "properties": {
    "iso:country":"GB",
    "wof:name":"SA17 4NN",
    "wof:placetype":"postalcode"
},
  "geometry": {"coordinates":[-4.27485209810559,51.75592794283666],"type":"Point"}
}