{
  "type": "Feature",
  "properties": {
    "iso:country": "GB",
    "wof:name": "NW7 2GB",
    "wof:placetype": "postalcode"
  },
  "geometry": {"coordinates":[-0.248863,51.612006],"type":"Point"}
}
