{
  "type": "Feature",
  "properties": {
    "iso:country":"GB",
    "wof:name":"DE14 2LA",
    "wof:placetype":"postalcode"
},
  "geometry": {"coordinates":[-1.64290221528878,52.8079457047453],"type":"Point"}
}