{
  "type": "Feature",
  "properties": {
    "iso:country": "GB",
    "wof:name": "BS49 4HS",
    "wof:placetype": "postalcode"
  },
  "geometry": {"coordinates":[-2.812961,51.386135],"type":"Point"}
}
