{
  "type": "Feature",
  "properties": {
    "iso:country":"GB",
    "wof:name":"CV2 3BJ",
    "wof:placetype":"postalcode"
},
  "geometry": {"coordinates":[-1.44975175707336,52.42385327966878],"type":"Point"}
}