{
  "type": "Feature",
  "properties": {
    "iso:country": "GB",
    "wof:name": "CV2 3BJ",
    "wof:placetype": "postalcode"
  },
  "geometry": {"coordinates":[-1.449752,52.423853],"type":"Point"}
}
