{
  "type": "Feature",
  "properties": {
    "date:inception_lower": "1994-05-01",
    "date:inception_upper": "1994-05-01",
    "iso:country": "GB",
    "wof:name": "TS8 9XL",
    "wof:placetype": "postalcode"
  },
  "geometry": {"coordinates":[-1.195633,54.522727],"type":"Point"}
}
