{
  "type": "Feature",
  "properties": {
    "iso:country":"GB",
    "wof:name":"RM7 8RA",
    "wof:placetype":"postalcode"
},
  "geometry": {"coordinates":[0.16448743450807,51.58874488239277],"type":"Point"}
}