{
  "type": "Feature",
  "properties": {
    "iso:country":"GB",
    "wof:name":"SO20 8HB",
    "wof:placetype":"postalcode"
},
  "geometry": {"coordinates":[-1.57574788401649,51.124735796679],"type":"Point"}
}