{
  "type": "Feature",
  "properties": {
    "date:inception_lower":"1980-01-01",
    "date:inception_upper":"1980-01-31",
    "iso:country":"GB",
    "wof:name":"KT4 8NB",
    "wof:placetype":"postalcode"
},
  "geometry": {"coordinates":[-0.227926,51.376702],"type":"Point"}
}