{
  "type": "Feature",
  "properties": {
    "iso:country":"GB",
    "wof:name":"S5 7AS",
    "wof:placetype":"postalcode"
},
  "geometry": {"coordinates":[-1.45649364800682,53.40736111600568],"type":"Point"}
}