{
  "type": "Feature",
  "properties": {
    "iso:country":"GB",
    "wof:name":"W1U 1NJ",
    "wof:placetype":"postalcode"
},
  "geometry": {"coordinates":[-0.15061084513288,51.51586330734837],"type":"Point"}
}