{
  "type": "Feature",
  "properties": {
    "iso:country":"GB",
    "wof:name":"EN11 9HH",
    "wof:placetype":"postalcode"
},
  "geometry": {"coordinates":[-0.00851165696562,51.77020919030372],"type":"Point"}
}