{
  "type": "Feature",
  "properties": {
    "iso:country":"GB",
    "wof:name":"SS9 2JE",
    "wof:placetype":"postalcode"
},
  "geometry": {"coordinates":[0.64900684783554,51.54623100134432],"type":"Point"}
}