{
  "type": "Feature",
  "properties": {
    "iso:country":"GB",
    "wof:name":"TQ6 0DE",
    "wof:placetype":"postalcode"
},
  "geometry": {"coordinates":[-3.56490902319318,50.35113705152563],"type":"Point"}
}