{
  "type": "Feature",
  "properties": {
    "iso:country": "GB",
    "wof:name": "TQ6 0DE",
    "wof:placetype": "postalcode"
  },
  "geometry": {"coordinates":[-3.565089,50.350965],"type":"Point"}
}
