{
  "type": "Feature",
  "properties": {
    "date:inception_lower": "2009-02-01",
    "date:inception_upper": "2009-02-01",
    "iso:country": "GB",
    "wof:name": "NW11 7GZ",
    "wof:placetype": "postalcode"
  },
  "geometry": {"coordinates":[-0.19775,51.577682],"type":"Point"}
}
