{
  "type": "Feature",
  "properties": {
    "iso:country":"GB",
    "wof:name":"NW11 7GZ",
    "wof:placetype":"postalcode"
},
  "geometry": {"coordinates":[-0.1977497524594,51.57768242400141],"type":"Point"}
}