{
  "type": "Feature",
  "properties": {
    "iso:country": "GB",
    "wof:name": "TN16 1EX",
    "wof:placetype": "postalcode"
  },
  "geometry": {"coordinates":[0.069333,51.267725],"type":"Point"}
}
