{
  "type": "Feature",
  "properties": {
    "iso:country":"GB",
    "wof:name":"NR29 3LT",
    "wof:placetype":"postalcode"
},
  "geometry": {"coordinates":[1.64672053667142,52.67746491726634],"type":"Point"}
}