{
  "type": "Feature",
  "properties": {
    "iso:country":"GB",
    "wof:name":"CM8 3HW",
    "wof:placetype":"postalcode"
},
  "geometry": {"coordinates":[0.68004898295495,51.78239579917921],"type":"Point"}
}