{
  "type": "Feature",
  "properties": {
    "iso:country":"GB",
    "wof:name":"OL8 2BS",
    "wof:placetype":"postalcode"
},
  "geometry": {"coordinates":[-2.09644380055114,53.53381162752631],"type":"Point"}
}