{
  "type": "Feature",
  "properties": {
    "iso:country":"GB",
    "wof:name":"B31 4EH",
    "wof:placetype":"postalcode"
},
  "geometry": {"coordinates":[-1.9747507546063,52.39809648367126],"type":"Point"}
}