{
  "type": "Feature",
  "properties": {
    "iso:country": "GB",
    "wof:name": "SN15 4PX",
    "wof:placetype": "postalcode"
  },
  "geometry": {"coordinates":[-1.968079,51.509349],"type":"Point"}
}
