{
  "type": "Feature",
  "properties": {
    "iso:country":"GB",
    "wof:name":"SN15 4PX",
    "wof:placetype":"postalcode"
},
  "geometry": {"coordinates":[-1.96807855413759,51.50934870865974],"type":"Point"}
}