{
  "type": "Feature",
  "properties": {
    "date:inception_lower":"2003-11-01",
    "date:inception_upper":"2003-11-30",
    "iso:country":"GB",
    "wof:name":"SN15 4PX",
    "wof:placetype":"postalcode"
},
  "geometry": {"coordinates":[-1.968079,51.509349],"type":"Point"}
}