{
  "type": "Feature",
  "properties": {
    "date:inception_lower": "1980-01-01",
    "date:inception_upper": "1980-01-01",
    "iso:country": "GB",
    "wof:name": "NE40 3BG",
    "wof:placetype": "postalcode"
  },
  "geometry": {"coordinates":[-1.777026,54.971143],"type":"Point"}
}
