{
  "type": "Feature",
  "properties": {
    "iso:country":"GB",
    "wof:name":"NE40 3BG",
    "wof:placetype":"postalcode"
},
  "geometry": {"coordinates":[-1.77702626652278,54.97114307370445],"type":"Point"}
}