{
  "type": "Feature",
  "properties": {
    "iso:country":"GB",
    "wof:name":"B94 6QH",
    "wof:placetype":"postalcode"
},
  "geometry": {"coordinates":[-1.77974932989129,52.35156828568895],"type":"Point"}
}