{
  "type": "Feature",
  "properties": {
    "iso:country": "GB",
    "wof:name": "DL3 8BP",
    "wof:placetype": "postalcode"
  },
  "geometry": {"coordinates":[-1.596759,54.523614],"type":"Point"}
}
