{
  "type": "Feature",
  "properties": {
    "iso:country": "GB",
    "wof:name": "SS3 0DX",
    "wof:placetype": "postalcode"
  },
  "geometry": {"coordinates":[0.815979,51.547305],"type":"Point"}
}
