{
  "type": "Feature",
  "properties": {
    "iso:country":"GB",
    "wof:name":"SS3 0DX",
    "wof:placetype":"postalcode"
},
  "geometry": {"coordinates":[0.8159785785722,51.54730485413578],"type":"Point"}
}