{
  "type": "Feature",
  "properties": {
    "iso:country": "GB",
    "wof:name": "KA9 1SD",
    "wof:placetype": "postalcode"
  },
  "geometry": {"coordinates":[-4.618358,55.489331],"type":"Point"}
}
