{
  "type": "Feature",
  "properties": {
    "iso:country":"GB",
    "wof:name":"KA9 1SD",
    "wof:placetype":"postalcode"
},
  "geometry": {"coordinates":[-4.61835757306997,55.48933104564681],"type":"Point"}
}