{
  "type": "Feature",
  "properties": {
    "iso:country": "GB",
    "wof:name": "S2 5QR",
    "wof:placetype": "postalcode"
  },
  "geometry": {"coordinates":[-1.454012,53.379134],"type":"Point"}
}
