{
  "type": "Feature",
  "properties": {
    "iso:country":"GB",
    "wof:name":"S2 5QR",
    "wof:placetype":"postalcode"
},
  "geometry": {"coordinates":[-1.45401179100711,53.3791343197617],"type":"Point"}
}