{
  "type": "Feature",
  "properties": {
    "iso:country":"GB",
    "wof:name":"CT5 1DS",
    "wof:placetype":"postalcode"
},
  "geometry": {"coordinates":[1.02296001151439,51.35684099507424],"type":"Point"}
}