{
  "type": "Feature",
  "properties": {
    "date:inception_lower":"1980-01-01",
    "date:inception_upper":"1980-01-31",
    "iso:country":"GB",
    "wof:name":"FY2 9AR",
    "wof:placetype":"postalcode"
},
  "geometry": {"coordinates":[-3.044278,53.854333],"type":"Point"}
}