{
  "type": "Feature",
  "properties": {
    "iso:country":"GB",
    "wof:name":"SE3 7QA",
    "wof:placetype":"postalcode"
},
  "geometry": {"coordinates":[0.0108755231656,51.47861981690382],"type":"Point"}
}