{
  "type": "Feature",
  "properties": {
    "date:inception_lower": "2019-07-01",
    "date:inception_upper": "2019-07-01",
    "iso:country": "GB",
    "wof:name": "NG19 8UH",
    "wof:placetype": "postalcode"
  },
  "geometry": {"coordinates":[-1.259782,53.193681],"type":"Point"}
}
