{
  "type": "Feature",
  "properties": {
    "iso:country":"GB",
    "wof:name":"LU7 2YR",
    "wof:placetype":"postalcode"
},
  "geometry": {"coordinates":[-0.69094462371485,51.92102752622919],"type":"Point"}
}