{
  "type": "Feature",
  "properties": {
    "iso:country":"GB",
    "wof:name":"M9 5PA",
    "wof:placetype":"postalcode"
},
  "geometry": {"coordinates":[-2.21009325459864,53.50905550394953],"type":"Point"}
}