{
  "type": "Feature",
  "properties": {
    "iso:country":"GB",
    "wof:name":"NE5 4TP",
    "wof:placetype":"postalcode"
},
  "geometry": {"coordinates":[-1.67928004549798,55.00121737550828],"type":"Point"}
}