{
  "type": "Feature",
  "properties": {
    "date:inception_lower": "1980-01-01",
    "date:inception_upper": "1980-01-01",
    "iso:country": "GB",
    "wof:name": "NE5 4TP",
    "wof:placetype": "postalcode"
  },
  "geometry": {"coordinates":[-1.67928,55.001217],"type":"Point"}
}
