{
  "type": "Feature",
  "properties": {
    "iso:country":"GB",
    "wof:name":"YO61 3LG",
    "wof:placetype":"postalcode"
},
  "geometry": {"coordinates":[-1.25106392132038,54.13174384992922],"type":"Point"}
}