{
  "type": "Feature",
  "properties": {
    "date:inception_lower":"1998-06-01",
    "date:inception_upper":"1998-06-30",
    "iso:country":"GB",
    "wof:name":"YO61 3LG",
    "wof:placetype":"postalcode"
},
  "geometry": {"coordinates":[-1.251135,54.131723],"type":"Point"}
}