{
  "type": "Feature",
  "properties": {
    "iso:country":"GB",
    "wof:name":"OX15 5AU",
    "wof:placetype":"postalcode"
},
  "geometry": {"coordinates":[-1.55857963701187,52.05539761074184],"type":"Point"}
}