{
  "type": "Feature",
  "properties": {
    "iso:country":"GB",
    "wof:name":"YO31 1HH",
    "wof:placetype":"postalcode"
},
  "geometry": {"coordinates":[-1.0436112209443,53.96967799552198],"type":"Point"}
}