{
  "type": "Feature",
  "properties": {
    "iso:country":"GB",
    "wof:name":"DA7 6DJ",
    "wof:placetype":"postalcode"
},
  "geometry": {"coordinates":[0.15690881945704,51.4585059333921],"type":"Point"}
}