{
  "type": "Feature",
  "properties": {
    "iso:country":"GB",
    "wof:name":"KT16 0AD",
    "wof:placetype":"postalcode"
},
  "geometry": {"coordinates":[-0.5255258619606,51.38265918220092],"type":"Point"}
}