{
  "type": "Feature",
  "properties": {
    "iso:country": "GB",
    "wof:name": "KT16 0AD",
    "wof:placetype": "postalcode"
  },
  "geometry": {"coordinates":[-0.524923,51.383397],"type":"Point"}
}
