{
  "type": "Feature",
  "properties": {
    "iso:country":"GB",
    "wof:name":"DN15 8PP",
    "wof:placetype":"postalcode"
},
  "geometry": {"coordinates":[-0.67987848254337,53.60464477483433],"type":"Point"}
}