{
  "type": "Feature",
  "properties": {
    "date:inception_lower":"1992-01-01",
    "date:inception_upper":"1992-01-31",
    "iso:country":"GB",
    "wof:name":"DN15 8PP",
    "wof:placetype":"postalcode"
},
  "geometry": {"coordinates":[-0.679878,53.604645],"type":"Point"}
}