{
  "type": "Feature",
  "properties": {
    "iso:country": "GB",
    "wof:name": "BS37 4HS",
    "wof:placetype": "postalcode"
  },
  "geometry": {"coordinates":[-2.422826,51.533712],"type":"Point"}
}
