{
  "type": "Feature",
  "properties": {
    "iso:country":"GB",
    "wof:name":"BS37 4HS",
    "wof:placetype":"postalcode"
},
  "geometry": {"coordinates":[-2.42282584899869,51.53371221715707],"type":"Point"}
}