{
  "type": "Feature",
  "properties": {
    "iso:country":"GB",
    "wof:name":"TQ6 0LT",
    "wof:placetype":"postalcode"
},
  "geometry": {"coordinates":[-3.64084295721338,50.34746385066533],"type":"Point"}
}