{
  "type": "Feature",
  "properties": {
    "iso:country":"GB",
    "wof:name":"PE22 8SG",
    "wof:placetype":"postalcode"
},
  "geometry": {"coordinates":[0.20194237999976,53.08568651133991],"type":"Point"}
}