{
  "type": "Feature",
  "properties": {
    "iso:country": "GB",
    "wof:name": "NG33 4QH",
    "wof:placetype": "postalcode"
  },
  "geometry": {"coordinates":[-0.490861,52.7907],"type":"Point"}
}
