{
  "type": "Feature",
  "properties": {
    "date:inception_lower": "2006-09-01",
    "date:inception_upper": "2006-09-01",
    "iso:country": "GB",
    "wof:name": "NG33 4QH",
    "wof:placetype": "postalcode"
  },
  "geometry": {"coordinates":[-0.490762,52.790728],"type":"Point"}
}
