{
  "type": "Feature",
  "properties": {
    "iso:country":"GB",
    "wof:name":"NG33 4QH",
    "wof:placetype":"postalcode"
},
  "geometry": {"coordinates":[-0.49086065138238,52.79069958118482],"type":"Point"}
}