{
  "type": "Feature",
  "properties": {
    "iso:country": "GB",
    "wof:name": "TN9 2DT",
    "wof:placetype": "postalcode"
  },
  "geometry": {"coordinates":[0.287312,51.189266],"type":"Point"}
}
