{
  "type": "Feature",
  "properties": {
    "iso:country":"GB",
    "wof:name":"SE5 0BX",
    "wof:placetype":"postalcode"
},
  "geometry": {"coordinates":[-0.0939113143021,51.47405729741021],"type":"Point"}
}