{
  "type": "Feature",
  "properties": {
    "date:inception_lower": "2020-02-01",
    "date:inception_upper": "2020-02-01",
    "iso:country": "GB",
    "wof:name": "BH16 6FT",
    "wof:placetype": "postalcode"
  },
  "geometry": {"coordinates":[-2.035251,50.749088],"type":"Point"}
}
