{
  "type": "Feature",
  "properties": {
    "date:inception_lower": "2000-06-01",
    "date:inception_upper": "2000-06-01",
    "iso:country": "GB",
    "wof:name": "PE28 5NH",
    "wof:placetype": "postalcode"
  },
  "geometry": {"coordinates":[-0.274278,52.431198],"type":"Point"}
}
