{
  "type": "Feature",
  "properties": {
    "iso:country":"GB",
    "wof:name":"PE28 5NH",
    "wof:placetype":"postalcode"
},
  "geometry": {"coordinates":[-0.27427838919575,52.43119810243844],"type":"Point"}
}