{
  "type": "Feature",
  "properties": {
    "date:inception_lower":"2011-03-01",
    "date:inception_upper":"2011-03-31",
    "iso:country":"GB",
    "wof:name":"S95 1AG",
    "wof:placetype":"postalcode"
},
  "geometry": {"coordinates":[-1.358836,53.428468],"type":"Point"}
}