{
  "type": "Feature",
  "properties": {
    "iso:country":"GB",
    "wof:name":"S95 1AG",
    "wof:placetype":"postalcode"
},
  "geometry": {"coordinates":[-1.35883583232736,53.42846777618335],"type":"Point"}
}