{
  "type": "Feature",
  "properties": {
    "iso:country": "GB",
    "wof:name": "G42 7AY",
    "wof:placetype": "postalcode"
  },
  "geometry": {"coordinates":[-4.256974,55.840776],"type":"Point"}
}
