{
  "type": "Feature",
  "properties": {
    "date:inception_lower":"1980-01-01",
    "date:inception_upper":"1980-01-31",
    "iso:country":"GB",
    "wof:name":"G42 7AY",
    "wof:placetype":"postalcode"
},
  "geometry": {"coordinates":[-4.256974,55.840776],"type":"Point"}
}