{
  "type": "Feature",
  "properties": {
    "iso:country":"GB",
    "wof:name":"G42 7AY",
    "wof:placetype":"postalcode"
},
  "geometry": {"coordinates":[-4.25697393378277,55.84077625881155],"type":"Point"}
}