{
  "type": "Feature",
  "properties": {
    "date:inception_lower": "2008-04-01",
    "date:inception_upper": "2008-04-01",
    "iso:country": "GB",
    "wof:name": "HU3 1PH",
    "wof:placetype": "postalcode"
  },
  "geometry": {"coordinates":[-0.355953,53.750978],"type":"Point"}
}
