{
  "type": "Feature",
  "properties": {
    "iso:country": "GB",
    "wof:name": "TS10 1HP",
    "wof:placetype": "postalcode"
  },
  "geometry": {"coordinates":[-1.069008,54.611519],"type":"Point"}
}
