{
  "type": "Feature",
  "properties": {
    "iso:country":"GB",
    "wof:name":"TS10 1HP",
    "wof:placetype":"postalcode"
},
  "geometry": {"coordinates":[-1.06900834291817,54.61151949293677],"type":"Point"}
}