{
  "type": "Feature",
  "properties": {
    "iso:country": "GB",
    "wof:name": "SM6 7AW",
    "wof:placetype": "postalcode"
  },
  "geometry": {"coordinates":[-0.137198,51.371455],"type":"Point"}
}
