{
  "type": "Feature",
  "properties": {
    "iso:country":"GB",
    "wof:name":"LA14 2DJ",
    "wof:placetype":"postalcode"
},
  "geometry": {"coordinates":[-3.22182223239968,54.11071929549406],"type":"Point"}
}