{
  "type": "Feature",
  "properties": {
    "iso:country": "GB",
    "wof:name": "CW12 3LA",
    "wof:placetype": "postalcode"
  },
  "geometry": {"coordinates":[-2.191415,53.154852],"type":"Point"}
}
