{
  "type": "Feature",
  "properties": {
    "iso:country": "GB",
    "wof:name": "PL4 6HR",
    "wof:placetype": "postalcode"
  },
  "geometry": {"coordinates":[-4.137548,50.378651],"type":"Point"}
}
