{
  "type": "Feature",
  "properties": {
    "iso:country":"GB",
    "wof:name":"PL4 6HR",
    "wof:placetype":"postalcode"
},
  "geometry": {"coordinates":[-4.13754853674238,50.37865141323741],"type":"Point"}
}