{
  "type": "Feature",
  "properties": {
    "iso:country": "GB",
    "wof:name": "B12 8NN",
    "wof:placetype": "postalcode"
  },
  "geometry": {"coordinates":[-1.882431,52.45689],"type":"Point"}
}
