{
  "type": "Feature",
  "properties": {
    "date:inception_lower": "1980-01-01",
    "date:inception_upper": "1980-01-01",
    "iso:country": "GB",
    "wof:name": "BN22 7DR",
    "wof:placetype": "postalcode"
  },
  "geometry": {"coordinates":[0.299243,50.775696],"type":"Point"}
}
