{
  "type": "Feature",
  "properties": {
    "iso:country":"GB",
    "wof:name":"PL15 9HE",
    "wof:placetype":"postalcode"
},
  "geometry": {"coordinates":[-4.35197241227196,50.63356000628376],"type":"Point"}
}