{
  "type": "Feature",
  "properties": {
    "date:inception_lower": "1994-12-01",
    "date:inception_upper": "1994-12-01",
    "iso:country": "GB",
    "wof:name": "PL15 9HE",
    "wof:placetype": "postalcode"
  },
  "geometry": {"coordinates":[-4.352003,50.633551],"type":"Point"}
}
