{
  "type": "Feature",
  "properties": {
    "date:inception_lower":"1994-12-01",
    "date:inception_upper":"1994-12-31",
    "iso:country":"GB",
    "wof:name":"PL15 9HE",
    "wof:placetype":"postalcode"
},
  "geometry": {"coordinates":[-4.351972,50.63356],"type":"Point"}
}