{
  "type": "Feature",
  "properties": {
    "iso:country": "GB",
    "wof:name": "ST17 4PQ",
    "wof:placetype": "postalcode"
  },
  "geometry": {"coordinates":[-2.091232,52.791996],"type":"Point"}
}
