{
  "type": "Feature",
  "properties": {
    "iso:country":"GB",
    "wof:name":"BA5 1SG",
    "wof:placetype":"postalcode"
},
  "geometry": {"coordinates":[-2.64485454573337,51.20817883698965],"type":"Point"}
}