{
  "type": "Feature",
  "properties": {
    "date:inception_lower": "1990-07-01",
    "date:inception_upper": "1990-07-01",
    "iso:country": "GB",
    "wof:name": "BA5 1SG",
    "wof:placetype": "postalcode"
  },
  "geometry": {"coordinates":[-2.644855,51.208179],"type":"Point"}
}
