{
  "type": "Feature",
  "properties": {
    "iso:country":"GB",
    "wof:name":"NG3 5JW",
    "wof:placetype":"postalcode"
},
  "geometry": {"coordinates":[-1.12112645478059,52.98743139756231],"type":"Point"}
}