{
  "type": "Feature",
  "properties": {
    "iso:country":"GB",
    "wof:name":"PE32 2AH",
    "wof:placetype":"postalcode"
},
  "geometry": {"coordinates":[0.69130437371758,52.70207489585749],"type":"Point"}
}