{
  "type": "Feature",
  "properties": {
    "iso:country":"GB",
    "wof:name":"WR14 1EG",
    "wof:placetype":"postalcode"
},
  "geometry": {"coordinates":[-2.31091301707508,52.13038036622545],"type":"Point"}
}