{
  "type": "Feature",
  "properties": {
    "iso:country": "GB",
    "wof:name": "WR14 1EG",
    "wof:placetype": "postalcode"
  },
  "geometry": {"coordinates":[-2.310913,52.13038],"type":"Point"}
}
