{
  "type": "Feature",
  "properties": {
    "iso:country":"GB",
    "wof:name":"CW3 0HN",
    "wof:placetype":"postalcode"
},
  "geometry": {"coordinates":[-2.50534371592873,52.9903667120935],"type":"Point"}
}