{
  "type": "Feature",
  "properties": {
    "date:inception_lower":"1980-01-01",
    "date:inception_upper":"1980-01-31",
    "iso:country":"GB",
    "wof:name":"CW3 0HN",
    "wof:placetype":"postalcode"
},
  "geometry": {"coordinates":[-2.505344,52.990367],"type":"Point"}
}