{
  "type": "Feature",
  "properties": {
    "date:inception_lower": "1994-05-01",
    "date:inception_upper": "1994-05-01",
    "iso:country": "GB",
    "wof:name": "M20 2UG",
    "wof:placetype": "postalcode"
  },
  "geometry": {"coordinates":[-2.237875,53.413669],"type":"Point"}
}
