{
  "type": "Feature",
  "properties": {
    "iso:country":"GB",
    "wof:name":"DY11 6PF",
    "wof:placetype":"postalcode"
},
  "geometry": {"coordinates":[-2.27211867325202,52.38011076591926],"type":"Point"}
}