{
  "type": "Feature",
  "properties": {
    "date:inception_lower": "1980-01-01",
    "date:inception_upper": "1980-01-01",
    "iso:country": "GB",
    "wof:name": "DE7 6EA",
    "wof:placetype": "postalcode"
  },
  "geometry": {"coordinates":[-1.375534,53.008681],"type":"Point"}
}
