{
  "type": "Feature",
  "properties": {
    "iso:country":"GB",
    "wof:name":"BA14 7SB",
    "wof:placetype":"postalcode"
},
  "geometry": {"coordinates":[-2.18730801868234,51.33595298546015],"type":"Point"}
}