{
  "type": "Feature",
  "properties": {
    "date:inception_lower": "1980-01-01",
    "date:inception_upper": "1980-01-01",
    "iso:country": "GB",
    "wof:name": "BA14 7SB",
    "wof:placetype": "postalcode"
  },
  "geometry": {"coordinates":[-2.187308,51.335953],"type":"Point"}
}
