{
  "type": "Feature",
  "properties": {
    "iso:country":"GB",
    "wof:name":"RG4 6LE",
    "wof:placetype":"postalcode"
},
  "geometry": {"coordinates":[-0.95096448706042,51.47067543422236],"type":"Point"}
}