{
  "type": "Feature",
  "properties": {
    "date:inception_lower":"2004-05-01",
    "date:inception_upper":"2004-05-31",
    "iso:country":"GB",
    "wof:name":"RG4 6LE",
    "wof:placetype":"postalcode"
},
  "geometry": {"coordinates":[-0.950964,51.470675],"type":"Point"}
}