{
  "type": "Feature",
  "properties": {
    "iso:country":"GB",
    "wof:name":"BH21 7DP",
    "wof:placetype":"postalcode"
},
  "geometry": {"coordinates":[-1.95360762555689,50.83967611679828],"type":"Point"}
}