{
  "type": "Feature",
  "properties": {
    "date:inception_lower":"1980-01-01",
    "date:inception_upper":"1980-01-31",
    "iso:country":"GB",
    "wof:name":"B97 5HT",
    "wof:placetype":"postalcode"
},
  "geometry": {"coordinates":[-1.947755,52.28349],"type":"Point"}
}