{
  "type": "Feature",
  "properties": {
    "iso:country":"GB",
    "wof:name":"B97 5HT",
    "wof:placetype":"postalcode"
},
  "geometry": {"coordinates":[-1.94775497975608,52.28348997565837],"type":"Point"}
}