{
  "type": "Feature",
  "properties": {
    "iso:country":"GB",
    "wof:name":"N16 9PU",
    "wof:placetype":"postalcode"
},
  "geometry": {"coordinates":[-0.08432586733336,51.55123720250185],"type":"Point"}
}