{
  "type": "Feature",
  "properties": {
    "iso:country":"GB",
    "wof:name":"TS25 5JB",
    "wof:placetype":"postalcode"
},
  "geometry": {"coordinates":[-1.22870842038334,54.66787565177493],"type":"Point"}
}