{
  "type": "Feature",
  "properties": {
    "iso:country": "GB",
    "wof:name": "PE31 7US",
    "wof:placetype": "postalcode"
  },
  "geometry": {"coordinates":[0.490574,52.898986],"type":"Point"}
}
