{
  "type": "Feature",
  "properties": {
    "iso:country":"GB",
    "wof:name":"WV11 3JF",
    "wof:placetype":"postalcode"
},
  "geometry": {"coordinates":[-2.0697846398736,52.60466689181757],"type":"Point"}
}