{
  "type": "Feature",
  "properties": {
    "date:inception_lower":"1991-01-01",
    "date:inception_upper":"1991-01-31",
    "iso:country":"GB",
    "wof:name":"NG7 6EX",
    "wof:placetype":"postalcode"
},
  "geometry": {"coordinates":[-1.171784,52.968225],"type":"Point"}
}