{
  "type": "Feature",
  "properties": {
    "iso:country":"GB",
    "wof:name":"NG7 6EX",
    "wof:placetype":"postalcode"
},
  "geometry": {"coordinates":[-1.17178431002074,52.96822491001248],"type":"Point"}
}