{
  "type": "Feature",
  "properties": {
    "iso:country":"GB",
    "wof:name":"SP3 4HB",
    "wof:placetype":"postalcode"
},
  "geometry": {"coordinates":[-1.89903707293401,51.19174098234613],"type":"Point"}
}