{
  "type": "Feature",
  "properties": {
    "iso:country":"GB",
    "wof:name":"TN24 9QQ",
    "wof:placetype":"postalcode"
},
  "geometry": {"coordinates":[0.88567396207141,51.16106363631305],"type":"Point"}
}