{
  "type": "Feature",
  "properties": {
    "date:inception_lower": "1985-10-01",
    "date:inception_upper": "1985-10-01",
    "iso:country": "GB",
    "wof:name": "BS15 1LA",
    "wof:placetype": "postalcode"
  },
  "geometry": {"coordinates":[-2.521758,51.468357],"type":"Point"}
}
