{
  "type": "Feature",
  "properties": {
    "iso:country":"GB",
    "wof:name":"BH17 9AQ",
    "wof:placetype":"postalcode"
},
  "geometry": {"coordinates":[-1.97620206233803,50.75642083710794],"type":"Point"}
}