{
  "type": "Feature",
  "properties": {
    "iso:country":"GB",
    "wof:name":"BN20 8PH",
    "wof:placetype":"postalcode"
},
  "geometry": {"coordinates":[0.25453889880495,50.77936642646144],"type":"Point"}
}