{
  "type": "Feature",
  "properties": {
    "iso:country": "GB",
    "wof:name": "SG18 8HL",
    "wof:placetype": "postalcode"
  },
  "geometry": {"coordinates":[-0.242972,52.089884],"type":"Point"}
}
