{
  "type": "Feature",
  "properties": {
    "iso:country":"GB",
    "wof:name":"LU5 5JP",
    "wof:placetype":"postalcode"
},
  "geometry": {"coordinates":[-0.51718465490115,51.91096451840544],"type":"Point"}
}