{
  "type": "Feature",
  "properties": {
    "date:inception_lower":"1980-01-01",
    "date:inception_upper":"1980-01-31",
    "iso:country":"GB",
    "wof:name":"LU5 5JP",
    "wof:placetype":"postalcode"
},
  "geometry": {"coordinates":[-0.517185,51.910965],"type":"Point"}
}