{
  "type": "Feature",
  "properties": {
    "iso:country":"GB",
    "wof:name":"L33 2DF",
    "wof:placetype":"postalcode"
},
  "geometry": {"coordinates":[-2.89312244009112,53.4918710119325],"type":"Point"}
}