{
  "type": "Feature",
  "properties": {
    "iso:country": "GB",
    "wof:name": "AB31 5JJ",
    "wof:placetype": "postalcode"
  },
  "geometry": {"coordinates":[-2.407256,57.072737],"type":"Point"}
}
