{
  "type": "Feature",
  "properties": {
    "iso:country":"GB",
    "wof:name":"AB31 5JJ",
    "wof:placetype":"postalcode"
},
  "geometry": {"coordinates":[-2.40726619721175,57.07271473246343],"type":"Point"}
}