{
  "type": "Feature",
  "properties": {
    "iso:country": "GB",
    "wof:name": "CO15 1AY",
    "wof:placetype": "postalcode"
  },
  "geometry": {"coordinates":[1.140984,51.78239],"type":"Point"}
}
