{
  "type": "Feature",
  "properties": {
    "iso:country":"GB",
    "wof:name":"CO15 1AY",
    "wof:placetype":"postalcode"
},
  "geometry": {"coordinates":[1.14098433922385,51.78238998663183],"type":"Point"}
}