{
  "type": "Feature",
  "properties": {
    "iso:country":"GB",
    "wof:name":"PO38 2NU",
    "wof:placetype":"postalcode"
},
  "geometry": {"coordinates":[-1.28025586922848,50.59690052171839],"type":"Point"}
}