{
  "type": "Feature",
  "properties": {
    "iso:country": "GB",
    "wof:name": "PO38 2NU",
    "wof:placetype": "postalcode"
  },
  "geometry": {"coordinates":[-1.280256,50.596901],"type":"Point"}
}
