{
  "type": "Feature",
  "properties": {
    "iso:country":"GB",
    "wof:name":"TQ7 4RY",
    "wof:placetype":"postalcode"
},
  "geometry": {"coordinates":[-3.79738278597222,50.33409511134725],"type":"Point"}
}