{
  "type": "Feature",
  "properties": {
    "iso:country":"GB",
    "wof:name":"S35 4AB",
    "wof:placetype":"postalcode"
},
  "geometry": {"coordinates":[-1.49415169831079,53.47021297505775],"type":"Point"}
}