{
  "type": "Feature",
  "properties": {
    "iso:country": "GB",
    "wof:name": "M1 7HF",
    "wof:placetype": "postalcode"
  },
  "geometry": {"coordinates":[-2.23455,53.470773],"type":"Point"}
}
