{
  "type": "Feature",
  "properties": {
    "iso:country":"GB",
    "wof:name":"SS4 1AT",
    "wof:placetype":"postalcode"
},
  "geometry": {"coordinates":[0.708753292165,51.5877478453812],"type":"Point"}
}