{
  "type": "Feature",
  "properties": {
    "iso:country": "GB",
    "wof:name": "SS4 1AT",
    "wof:placetype": "postalcode"
  },
  "geometry": {"coordinates":[0.708753,51.587748],"type":"Point"}
}
