{
  "type": "Feature",
  "properties": {
    "iso:country":"GB",
    "wof:name":"PE9 2QL",
    "wof:placetype":"postalcode"
},
  "geometry": {"coordinates":[-0.48661054863744,52.64765275328951],"type":"Point"}
}