{
  "type": "Feature",
  "properties": {
    "date:inception_lower": "1980-01-01",
    "date:inception_upper": "1980-01-01",
    "iso:country": "GB",
    "wof:name": "B49 5QG",
    "wof:placetype": "postalcode"
  },
  "geometry": {"coordinates":[-1.875873,52.231621],"type":"Point"}
}
