{
  "type": "Feature",
  "properties": {
    "iso:country":"GB",
    "wof:name":"B49 5QG",
    "wof:placetype":"postalcode"
},
  "geometry": {"coordinates":[-1.87553053649829,52.23109455129001],"type":"Point"}
}