{
  "type": "Feature",
  "properties": {
    "iso:country":"GB",
    "wof:name":"SW10 0UB",
    "wof:placetype":"postalcode"
},
  "geometry": {"coordinates":[-0.18370904386767,51.4812738739524],"type":"Point"}
}