{
  "type": "Feature",
  "properties": {
    "iso:country": "GB",
    "wof:name": "LD3 7RB",
    "wof:placetype": "postalcode"
  },
  "geometry": {"coordinates":[-3.365052,51.942217],"type":"Point"}
}
