{
  "type": "Feature",
  "properties": {
    "iso:country":"GB",
    "wof:name":"CT21 4LD",
    "wof:placetype":"postalcode"
},
  "geometry": {"coordinates":[1.02566673775954,51.07573488466335],"type":"Point"}
}