{
  "type": "Feature",
  "properties": {
    "iso:country": "GB",
    "wof:name": "CT21 4LD",
    "wof:placetype": "postalcode"
  },
  "geometry": {"coordinates":[1.025667,51.075735],"type":"Point"}
}
