{
  "type": "Feature",
  "properties": {
    "iso:country": "GB",
    "wof:name": "BD23 3QZ",
    "wof:placetype": "postalcode"
  },
  "geometry": {"coordinates":[-2.098722,54.036939],"type":"Point"}
}
