{
  "type": "Feature",
  "properties": {
    "iso:country":"GB",
    "wof:name":"BD23 3QZ",
    "wof:placetype":"postalcode"
},
  "geometry": {"coordinates":[-2.09872232717679,54.03693881112596],"type":"Point"}
}