{
  "type": "Feature",
  "properties": {
    "iso:country":"GB",
    "wof:name":"PE34 3HE",
    "wof:placetype":"postalcode"
},
  "geometry": {"coordinates":[0.37279123088114,52.69649878466965],"type":"Point"}
}