{
  "type": "Feature",
  "properties": {
    "iso:country": "GB",
    "wof:name": "FY7 6SA",
    "wof:placetype": "postalcode"
  },
  "geometry": {"coordinates":[-3.016918,53.922213],"type":"Point"}
}
