{
  "type": "Feature",
  "properties": {
    "date:inception_lower":"1994-05-01",
    "date:inception_upper":"1994-05-31",
    "iso:country":"GB",
    "wof:name":"FY7 6SA",
    "wof:placetype":"postalcode"
},
  "geometry": {"coordinates":[-3.016918,53.922213],"type":"Point"}
}