{
  "type": "Feature",
  "properties": {
    "iso:country":"GB",
    "wof:name":"BN12 6NJ",
    "wof:placetype":"postalcode"
},
  "geometry": {"coordinates":[-0.42725528375378,50.81962858736012],"type":"Point"}
}