{
  "type": "Feature",
  "properties": {
    "iso:country": "GB",
    "wof:name": "BN12 6NJ",
    "wof:placetype": "postalcode"
  },
  "geometry": {"coordinates":[-0.427255,50.819629],"type":"Point"}
}
