{
  "type": "Feature",
  "properties": {
    "iso:country":"GB",
    "wof:name":"CO10 8JY",
    "wof:placetype":"postalcode"
},
  "geometry": {"coordinates":[0.5763901041558,52.05026826092204],"type":"Point"}
}