{
  "type": "Feature",
  "properties": {
    "date:inception_lower": "1980-01-01",
    "date:inception_upper": "1980-01-01",
    "iso:country": "GB",
    "wof:name": "CO10 8JY",
    "wof:placetype": "postalcode"
  },
  "geometry": {"coordinates":[0.576014,52.050317],"type":"Point"}
}
