{
  "type": "Feature",
  "properties": {
    "date:inception_lower":"1980-01-01",
    "date:inception_upper":"1980-01-31",
    "iso:country":"GB",
    "wof:name":"BA6 8BH",
    "wof:placetype":"postalcode"
},
  "geometry": {"coordinates":[-2.70398,51.142441],"type":"Point"}
}