{
  "type": "Feature",
  "properties": {
    "iso:country":"GB",
    "wof:name":"BA6 8BH",
    "wof:placetype":"postalcode"
},
  "geometry": {"coordinates":[-2.70397603701971,51.14244734928191],"type":"Point"}
}