{
  "type": "Feature",
  "properties": {
    "iso:country": "GB",
    "wof:name": "BA6 8BH",
    "wof:placetype": "postalcode"
  },
  "geometry": {"coordinates":[-2.70398,51.142441],"type":"Point"}
}
