{
  "type": "Feature",
  "properties": {
    "date:inception_lower":"1980-01-01",
    "date:inception_upper":"1980-01-31",
    "iso:country":"GB",
    "wof:name":"BS15 4JA",
    "wof:placetype":"postalcode"
},
  "geometry": {"coordinates":[-2.493713,51.463004],"type":"Point"}
}