{
  "type": "Feature",
  "properties": {
    "iso:country": "GB",
    "wof:name": "ME2 4PN",
    "wof:placetype": "postalcode"
  },
  "geometry": {"coordinates":[0.501163,51.407318],"type":"Point"}
}
