{
  "type": "Feature",
  "properties": {
    "iso:country": "GB",
    "wof:name": "NE30 3BA",
    "wof:placetype": "postalcode"
  },
  "geometry": {"coordinates":[-1.443672,55.030994],"type":"Point"}
}
