{
  "type": "Feature",
  "properties": {
    "iso:country":"GB",
    "wof:name":"DE13 9RH",
    "wof:placetype":"postalcode"
},
  "geometry": {"coordinates":[-1.73806147980839,52.79895245227466],"type":"Point"}
}