{
  "type": "Feature",
  "properties": {
    "date:inception_lower":"1994-12-01",
    "date:inception_upper":"1994-12-31",
    "iso:country":"GB",
    "wof:name":"DE13 9RH",
    "wof:placetype":"postalcode"
},
  "geometry": {"coordinates":[-1.738026,52.799149],"type":"Point"}
}