{
  "type": "Feature",
  "properties": {
    "date:inception_lower":"1980-01-01",
    "date:inception_upper":"1980-01-31",
    "iso:country":"GB",
    "wof:name":"MK45 3AH",
    "wof:placetype":"postalcode"
},
  "geometry": {"coordinates":[-0.415973,52.095276],"type":"Point"}
}