{
  "type": "Feature",
  "properties": {
    "iso:country":"GB",
    "wof:name":"TA24 6DS",
    "wof:placetype":"postalcode"
},
  "geometry": {"coordinates":[-3.47148891872418,51.19880382747368],"type":"Point"}
}