{
  "type": "Feature",
  "properties": {
    "iso:country": "GB",
    "wof:name": "TA24 6DS",
    "wof:placetype": "postalcode"
  },
  "geometry": {"coordinates":[-3.471489,51.198804],"type":"Point"}
}
