{
  "type": "Feature",
  "properties": {
    "iso:country": "GB",
    "wof:name": "OX4 4FE",
    "wof:placetype": "postalcode"
  },
  "geometry": {"coordinates":[-1.234037,51.723512],"type":"Point"}
}
