{
  "type": "Feature",
  "properties": {
    "iso:country":"GB",
    "wof:name":"OX4 4FE",
    "wof:placetype":"postalcode"
},
  "geometry": {"coordinates":[-1.23403735539597,51.72351239918805],"type":"Point"}
}