{
  "type": "Feature",
  "properties": {
    "iso:country":"GB",
    "wof:name":"W4 2RN",
    "wof:placetype":"postalcode"
},
  "geometry": {"coordinates":[-0.2551289720423,51.48538880060173],"type":"Point"}
}