{
  "type": "Feature",
  "properties": {
    "iso:country":"GB",
    "wof:name":"GL54 2JR",
    "wof:placetype":"postalcode"
},
  "geometry": {"coordinates":[-1.75243640085303,51.9172008202429],"type":"Point"}
}