{
  "type": "Feature",
  "properties": {
    "iso:country":"GB",
    "wof:name":"B60 1NU",
    "wof:placetype":"postalcode"
},
  "geometry": {"coordinates":[-2.01888826987828,52.37097442846841],"type":"Point"}
}