{
  "type": "Feature",
  "properties": {
    "iso:country": "GB",
    "wof:name": "SL2 2DN",
    "wof:placetype": "postalcode"
  },
  "geometry": {"coordinates":[-0.633419,51.532031],"type":"Point"}
}
