{
  "type": "Feature",
  "properties": {
    "iso:country":"GB",
    "wof:name":"SL2 2DN",
    "wof:placetype":"postalcode"
},
  "geometry": {"coordinates":[-0.63341939125992,51.53203093072126],"type":"Point"}
}