{
  "type": "Feature",
  "properties": {
    "iso:country": "GB",
    "wof:name": "EH17 7NN",
    "wof:placetype": "postalcode"
  },
  "geometry": {"coordinates":[-3.137189,55.914182],"type":"Point"}
}
