{
  "type": "Feature",
  "properties": {
    "iso:country":"GB",
    "wof:name":"CH45 2JD",
    "wof:placetype":"postalcode"
},
  "geometry": {"coordinates":[-3.04261790831122,53.43790426711573],"type":"Point"}
}