{
  "type": "Feature",
  "properties": {
    "iso:country": "GB",
    "wof:name": "CH45 2JD",
    "wof:placetype": "postalcode"
  },
  "geometry": {"coordinates":[-3.042527,53.437949],"type":"Point"}
}
