{
  "type": "Feature",
  "properties": {
    "iso:country": "GB",
    "wof:name": "PL5 4DJ",
    "wof:placetype": "postalcode"
  },
  "geometry": {"coordinates":[-4.139569,50.416337],"type":"Point"}
}
