{
  "type": "Feature",
  "properties": {
    "iso:country":"GB",
    "wof:name":"NE16 4RQ",
    "wof:placetype":"postalcode"
},
  "geometry": {"coordinates":[-1.6701026193251,54.94220713412282],"type":"Point"}
}