{
  "type": "Feature",
  "properties": {
    "iso:country": "GB",
    "wof:name": "M33 2TH",
    "wof:placetype": "postalcode"
  },
  "geometry": {"coordinates":[-2.30057,53.4162],"type":"Point"}
}
