{
  "type": "Feature",
  "properties": {
    "iso:country":"GB",
    "wof:name":"B6 6AR",
    "wof:placetype":"postalcode"
},
  "geometry": {"coordinates":[-1.89810763837601,52.5064119607308],"type":"Point"}
}