{
  "type": "Feature",
  "properties": {
    "iso:country":"GB",
    "wof:name":"NG11 8FH",
    "wof:placetype":"postalcode"
},
  "geometry": {"coordinates":[-1.17849302469957,52.90963287925654],"type":"Point"}
}