{
  "type": "Feature",
  "properties": {
    "iso:country": "GB",
    "wof:name": "EH6 7DY",
    "wof:placetype": "postalcode"
  },
  "geometry": {"coordinates":[-3.160499,55.972966],"type":"Point"}
}
