{
  "type": "Feature",
  "properties": {
    "iso:country":"GB",
    "wof:name":"S75 3EX",
    "wof:placetype":"postalcode"
},
  "geometry": {"coordinates":[-1.53002982533409,53.52259154748139],"type":"Point"}
}