{
  "type": "Feature",
  "properties": {
    "iso:country": "GB",
    "wof:name": "S75 3EX",
    "wof:placetype": "postalcode"
  },
  "geometry": {"coordinates":[-1.530136,53.522601],"type":"Point"}
}
