{
  "type": "Feature",
  "properties": {
    "iso:country":"GB",
    "wof:name":"LL16 3SB",
    "wof:placetype":"postalcode"
},
  "geometry": {"coordinates":[-3.4256142683828,53.18355292481116],"type":"Point"}
}