{
  "type": "Feature",
  "properties": {
    "date:inception_lower":"2001-06-01",
    "date:inception_upper":"2001-06-30",
    "iso:country":"GB",
    "wof:name":"LL16 3SB",
    "wof:placetype":"postalcode"
},
  "geometry": {"coordinates":[-3.425614,53.183553],"type":"Point"}
}