{
  "type": "Feature",
  "properties": {
    "iso:country": "GB",
    "wof:name": "NN18 0QH",
    "wof:placetype": "postalcode"
  },
  "geometry": {"coordinates":[-0.722888,52.481208],"type":"Point"}
}
