{
  "type": "Feature",
  "properties": {
    "iso:country":"GB",
    "wof:name":"HS1 2LH",
    "wof:placetype":"postalcode"
},
  "geometry": {"coordinates":[-6.38165814934384,58.21424873592346],"type":"Point"}
}