{
  "type": "Feature",
  "properties": {
    "date:inception_lower": "1990-02-01",
    "date:inception_upper": "1990-02-01",
    "iso:country": "GB",
    "wof:name": "DT9 3EQ",
    "wof:placetype": "postalcode"
  },
  "geometry": {"coordinates":[-2.512056,50.947274],"type":"Point"}
}
