{
  "type": "Feature",
  "properties": {
    "iso:country": "GB",
    "wof:name": "DT9 3EQ",
    "wof:placetype": "postalcode"
  },
  "geometry": {"coordinates":[-2.512042,50.94728],"type":"Point"}
}
