{
  "type": "Feature",
  "properties": {
    "iso:country":"GB",
    "wof:name":"HX2 6TU",
    "wof:placetype":"postalcode"
},
  "geometry": {"coordinates":[-1.94845540896371,53.73234424497644],"type":"Point"}
}