{
  "type": "Feature",
  "properties": {
    "iso:country": "GB",
    "wof:name": "EN10 6RJ",
    "wof:placetype": "postalcode"
  },
  "geometry": {"coordinates":[-0.009068,51.738449],"type":"Point"}
}
