{
  "type": "Feature",
  "properties": {
    "iso:country":"GB",
    "wof:name":"EN10 6RJ",
    "wof:placetype":"postalcode"
},
  "geometry": {"coordinates":[-0.00906841077299,51.73844870178777],"type":"Point"}
}