{
  "type": "Feature",
  "properties": {
    "date:inception_lower": "1980-01-01",
    "date:inception_upper": "1980-01-01",
    "iso:country": "GB",
    "wof:name": "EN10 6RJ",
    "wof:placetype": "postalcode"
  },
  "geometry": {"coordinates":[-0.009108,51.738599],"type":"Point"}
}
