{
  "type": "Feature",
  "properties": {
    "iso:country":"GB",
    "wof:name":"PE6 8EY",
    "wof:placetype":"postalcode"
},
  "geometry": {"coordinates":[-0.3030373355113,52.67621092140288],"type":"Point"}
}