{
  "type": "Feature",
  "properties": {
    "iso:country":"GB",
    "wof:name":"M34 3QY",
    "wof:placetype":"postalcode"
},
  "geometry": {"coordinates":[-2.117420530589,53.45417339965682],"type":"Point"}
}