{
  "type": "Feature",
  "properties": {
    "date:inception_lower": "1980-01-01",
    "date:inception_upper": "1980-01-01",
    "iso:country": "GB",
    "wof:name": "M34 3QY",
    "wof:placetype": "postalcode"
  },
  "geometry": {"coordinates":[-2.11742,53.454173],"type":"Point"}
}
