{
  "type": "Feature",
  "properties": {
    "iso:country":"GB",
    "wof:name":"DE13 8TQ",
    "wof:placetype":"postalcode"
},
  "geometry": {"coordinates":[-1.75829860330461,52.84592030858887],"type":"Point"}
}