{
  "type": "Feature",
  "properties": {
    "iso:country":"GB",
    "wof:name":"G72 8NE",
    "wof:placetype":"postalcode"
},
  "geometry": {"coordinates":[-4.1709071133337,55.8165590622636],"type":"Point"}
}