{
  "type": "Feature",
  "properties": {
    "date:inception_lower": "1980-01-01",
    "date:inception_upper": "1980-01-01",
    "iso:country": "GB",
    "wof:name": "WA12 8JT",
    "wof:placetype": "postalcode"
  },
  "geometry": {"coordinates":[-2.631414,53.450117],"type":"Point"}
}
