{
  "type": "Feature",
  "properties": {
    "iso:country":"GB",
    "wof:name":"WA12 8JT",
    "wof:placetype":"postalcode"
},
  "geometry": {"coordinates":[-2.6314140872183,53.45011665103691],"type":"Point"}
}