{
  "type": "Feature",
  "properties": {
    "iso:country":"GB",
    "wof:name":"CO12 3SR",
    "wof:placetype":"postalcode"
},
  "geometry": {"coordinates":[1.27599933646332,51.93176868634598],"type":"Point"}
}