{
  "type": "Feature",
  "properties": {
    "date:inception_lower": "1980-01-01",
    "date:inception_upper": "1980-01-01",
    "iso:country": "GB",
    "wof:name": "TD7 4LE",
    "wof:placetype": "postalcode"
  },
  "geometry": {"coordinates":[-2.842229,55.548572],"type":"Point"}
}
