{
  "type": "Feature",
  "properties": {
    "iso:country":"GB",
    "wof:name":"M9 7EE",
    "wof:placetype":"postalcode"
},
  "geometry": {"coordinates":[-2.19206986851484,53.52132805461657],"type":"Point"}
}