{
  "type": "Feature",
  "properties": {
    "iso:country":"GB",
    "wof:name":"SL7 1TP",
    "wof:placetype":"postalcode"
},
  "geometry": {"coordinates":[-0.76480998243553,51.58341036981372],"type":"Point"}
}