{
  "type": "Feature",
  "properties": {
    "iso:country":"GB",
    "wof:name":"PO20 7JN",
    "wof:placetype":"postalcode"
},
  "geometry": {"coordinates":[-0.84419246396199,50.76509609396309],"type":"Point"}
}