{
  "type": "Feature",
  "properties": {
    "iso:country":"GB",
    "wof:name":"PO4 0BZ",
    "wof:placetype":"postalcode"
},
  "geometry": {"coordinates":[-1.07623220000648,50.79523088626815],"type":"Point"}
}