{
  "type": "Feature",
  "properties": {
    "iso:country":"GB",
    "wof:name":"AB55 6NN",
    "wof:placetype":"postalcode"
},
  "geometry": {"coordinates":[-2.87930092709962,57.59626506641938],"type":"Point"}
}