{
  "type": "Feature",
  "properties": {
    "iso:country": "GB",
    "wof:name": "BB8 9BL",
    "wof:placetype": "postalcode"
  },
  "geometry": {"coordinates":[-2.171031,53.857615],"type":"Point"}
}
