{
  "type": "Feature",
  "properties": {
    "iso:country":"GB",
    "wof:name":"BS23 1HD",
    "wof:placetype":"postalcode"
},
  "geometry": {"coordinates":[-2.97906447368417,51.34805103867635],"type":"Point"}
}