{
  "type": "Feature",
  "properties": {
    "iso:country":"GB",
    "wof:name":"LS20 8EJ",
    "wof:placetype":"postalcode"
},
  "geometry": {"coordinates":[-1.71853002975362,53.86951448760524],"type":"Point"}
}