{
  "type": "Feature",
  "properties": {
    "iso:country":"GB",
    "wof:name":"IP17 2NF",
    "wof:placetype":"postalcode"
},
  "geometry": {"coordinates":[1.44508209352504,52.26048125312055],"type":"Point"}
}