{
  "type": "Feature",
  "properties": {
    "date:inception_lower": "1980-01-01",
    "date:inception_upper": "1980-01-01",
    "iso:country": "GB",
    "wof:name": "IP17 2NF",
    "wof:placetype": "postalcode"
  },
  "geometry": {"coordinates":[1.445407,52.259935],"type":"Point"}
}
