{
  "type": "Feature",
  "properties": {
    "iso:country":"GB",
    "wof:name":"WA3 1BH",
    "wof:placetype":"postalcode"
},
  "geometry": {"coordinates":[-2.55194865036366,53.48330968359911],"type":"Point"}
}