{
  "type": "Feature",
  "properties": {
    "iso:country":"GB",
    "wof:name":"NG1 3NT",
    "wof:placetype":"postalcode"
},
  "geometry": {"coordinates":[-1.14366094853627,52.95673489668295],"type":"Point"}
}