{
  "type": "Feature",
  "properties": {
    "date:inception_lower":"2007-08-01",
    "date:inception_upper":"2007-08-31",
    "iso:country":"GB",
    "wof:name":"NG1 3NT",
    "wof:placetype":"postalcode"
},
  "geometry": {"coordinates":[-1.143661,52.956735],"type":"Point"}
}