{
  "type": "Feature",
  "properties": {
    "iso:country":"GB",
    "wof:name":"ST6 5TZ",
    "wof:placetype":"postalcode"
},
  "geometry": {"coordinates":[-2.20883764138969,53.06270349268573],"type":"Point"}
}