{
  "type": "Feature",
  "properties": {
    "iso:country":"GB",
    "wof:name":"AB24 2TF",
    "wof:placetype":"postalcode"
},
  "geometry": {"coordinates":[-2.10897325597825,57.16943938098113],"type":"Point"}
}