{
  "type": "Feature",
  "properties": {
    "date:inception_lower": "2010-06-01",
    "date:inception_upper": "2010-06-01",
    "iso:country": "GB",
    "wof:name": "BL8 1WL",
    "wof:placetype": "postalcode"
  },
  "geometry": {"coordinates":[-2.318044,53.602233],"type":"Point"}
}
