{
  "type": "Feature",
  "properties": {
    "iso:country":"GB",
    "wof:name":"NR12 0AS",
    "wof:placetype":"postalcode"
},
  "geometry": {"coordinates":[1.55931599014784,52.74972209776273],"type":"Point"}
}