{
  "type": "Feature",
  "properties": {
    "iso:country":"GB",
    "wof:name":"IG1 1FT",
    "wof:placetype":"postalcode"
},
  "geometry": {"coordinates":[0.08975374715539,51.5614578003944],"type":"Point"}
}