{
  "type": "Feature",
  "properties": {
    "iso:country":"GB",
    "wof:name":"SA16 0AN",
    "wof:placetype":"postalcode"
},
  "geometry": {"coordinates":[-4.25529047408761,51.68466895275864],"type":"Point"}
}