{
  "type": "Feature",
  "properties": {
    "iso:country":"GB",
    "wof:name":"DT10 1PZ",
    "wof:placetype":"postalcode"
},
  "geometry": {"coordinates":[-2.31593497655891,50.96692217639857],"type":"Point"}
}