{
  "type": "Feature",
  "properties": {
    "iso:country": "GB",
    "wof:name": "TW15 3PG",
    "wof:placetype": "postalcode"
  },
  "geometry": {"coordinates":[-0.473861,51.431132],"type":"Point"}
}
