{
  "type": "Feature",
  "properties": {
    "iso:country":"GB",
    "wof:name":"DY13 8SW",
    "wof:placetype":"postalcode"
},
  "geometry": {"coordinates":[-2.2886891230139,52.34395791833339],"type":"Point"}
}