{
  "type": "Feature",
  "properties": {
    "date:inception_lower": "2007-11-01",
    "date:inception_upper": "2007-11-01",
    "iso:country": "GB",
    "wof:name": "RH6 9HJ",
    "wof:placetype": "postalcode"
  },
  "geometry": {"coordinates":[-0.160402,51.173296],"type":"Point"}
}
