{
  "type": "Feature",
  "properties": {
    "iso:country":"GB",
    "wof:name":"EH52 6TJ",
    "wof:placetype":"postalcode"
},
  "geometry": {"coordinates":[-3.50193218821045,55.93529874996634],"type":"Point"}
}