{
  "type": "Feature",
  "properties": {
    "date:inception_lower": "2005-10-01",
    "date:inception_upper": "2005-10-01",
    "iso:country": "GB",
    "wof:name": "TD14 5GN",
    "wof:placetype": "postalcode"
  },
  "geometry": {"coordinates":[-2.100741,55.869149],"type":"Point"}
}
