{
  "type": "Feature",
  "properties": {
    "iso:country": "GB",
    "wof:name": "BB5 4BD",
    "wof:placetype": "postalcode"
  },
  "geometry": {"coordinates":[-2.373318,53.759169],"type":"Point"}
}
