{
  "type": "Feature",
  "properties": {
    "iso:country": "GB",
    "wof:name": "DT11 8LZ",
    "wof:placetype": "postalcode"
  },
  "geometry": {"coordinates":[-2.190946,50.929219],"type":"Point"}
}
