{
  "type": "Feature",
  "properties": {
    "iso:country":"GB",
    "wof:name":"DT11 8LZ",
    "wof:placetype":"postalcode"
},
  "geometry": {"coordinates":[-2.19094647417864,50.92921904477975],"type":"Point"}
}