{
  "type": "Feature",
  "properties": {
    "iso:country":"GB",
    "wof:name":"G78 1JN",
    "wof:placetype":"postalcode"
},
  "geometry": {"coordinates":[-4.40643603020916,55.81061913752099],"type":"Point"}
}