{
  "type": "Feature",
  "properties": {
    "iso:country": "GB",
    "wof:name": "G78 1JN",
    "wof:placetype": "postalcode"
  },
  "geometry": {"coordinates":[-4.406436,55.810619],"type":"Point"}
}
