{
  "type": "Feature",
  "properties": {
    "iso:country":"GB",
    "wof:name":"TS14 6AB",
    "wof:placetype":"postalcode"
},
  "geometry": {"coordinates":[-1.05320947120141,54.53498790602293],"type":"Point"}
}