{
  "type": "Feature",
  "properties": {
    "date:inception_lower":"1981-06-01",
    "date:inception_upper":"1981-06-30",
    "iso:country":"GB",
    "wof:name":"PR9 8RB",
    "wof:placetype":"postalcode"
},
  "geometry": {"coordinates":[-2.944213,53.673858],"type":"Point"}
}