{
  "type": "Feature",
  "properties": {
    "iso:country":"GB",
    "wof:name":"PR9 8RB",
    "wof:placetype":"postalcode"
},
  "geometry": {"coordinates":[-2.94421309246116,53.67385770917424],"type":"Point"}
}