{
  "type": "Feature",
  "properties": {
    "iso:country":"GB",
    "wof:name":"E13 8NF",
    "wof:placetype":"postalcode"
},
  "geometry": {"coordinates":[0.02834215329277,51.51783300093459],"type":"Point"}
}