{
  "type": "Feature",
  "properties": {
    "iso:country":"GB",
    "wof:name":"TS18 2SX",
    "wof:placetype":"postalcode"
},
  "geometry": {"coordinates":[-1.29498104594436,54.56633132117314],"type":"Point"}
}