{
  "type": "Feature",
  "properties": {
    "iso:country": "GB",
    "wof:name": "TS18 2SX",
    "wof:placetype": "postalcode"
  },
  "geometry": {"coordinates":[-1.295058,54.566332],"type":"Point"}
}
