{
  "type": "Feature",
  "properties": {
    "date:inception_lower": "2015-09-01",
    "date:inception_upper": "2015-09-01",
    "iso:country": "GB",
    "wof:name": "TS18 2SX",
    "wof:placetype": "postalcode"
  },
  "geometry": {"coordinates":[-1.295058,54.566332],"type":"Point"}
}
