{
  "type": "Feature",
  "properties": {
    "iso:country": "GB",
    "wof:name": "BN43 5DN",
    "wof:placetype": "postalcode"
  },
  "geometry": {"coordinates":[-0.276342,50.832731],"type":"Point"}
}
