{
  "type": "Feature",
  "properties": {
    "iso:country":"GB",
    "wof:name":"LS17 9LJ",
    "wof:placetype":"postalcode"
},
  "geometry": {"coordinates":[-1.51279987319231,53.90219238618579],"type":"Point"}
}