{
  "type": "Feature",
  "properties": {
    "date:inception_lower": "1980-01-01",
    "date:inception_upper": "1980-01-01",
    "iso:country": "GB",
    "wof:name": "WF4 5DU",
    "wof:placetype": "postalcode"
  },
  "geometry": {"coordinates":[-1.54502,53.656477],"type":"Point"}
}
