{
  "type": "Feature",
  "properties": {
    "date:inception_lower": "1980-01-01",
    "date:inception_upper": "1980-01-01",
    "iso:country": "GB",
    "wof:name": "E17 6HB",
    "wof:placetype": "postalcode"
  },
  "geometry": {"coordinates":[-0.032087,51.589859],"type":"Point"}
}
