{
  "type": "Feature",
  "properties": {
    "iso:country":"GB",
    "wof:name":"CV9 3NP",
    "wof:placetype":"postalcode"
},
  "geometry": {"coordinates":[-1.52695538072572,52.63803130182158],"type":"Point"}
}