{
  "type": "Feature",
  "properties": {
    "iso:country":"GB",
    "wof:name":"BN20 7UB",
    "wof:placetype":"postalcode"
},
  "geometry": {"coordinates":[0.26113907671332,50.7567986151777],"type":"Point"}
}