{
  "type": "Feature",
  "properties": {
    "date:inception_lower": "2009-08-01",
    "date:inception_upper": "2009-08-01",
    "iso:country": "GB",
    "wof:name": "PE7 1AZ",
    "wof:placetype": "postalcode"
  },
  "geometry": {"coordinates":[-0.129386,52.557586],"type":"Point"}
}
