{
  "type": "Feature",
  "properties": {
    "iso:country":"GB",
    "wof:name":"YO25 4PA",
    "wof:placetype":"postalcode"
},
  "geometry": {"coordinates":[-0.38953569452717,54.01410788333256],"type":"Point"}
}