{
  "type": "Feature",
  "properties": {
    "date:inception_lower": "1998-06-01",
    "date:inception_upper": "1998-06-01",
    "iso:country": "GB",
    "wof:name": "YO25 4PA",
    "wof:placetype": "postalcode"
  },
  "geometry": {"coordinates":[-0.389536,54.014108],"type":"Point"}
}
