{
  "type": "Feature",
  "properties": {
    "iso:country":"GB",
    "wof:name":"G81 1AZ",
    "wof:placetype":"postalcode"
},
  "geometry": {"coordinates":[-4.38086545696416,55.89834329265664],"type":"Point"}
}