{
  "type": "Feature",
  "properties": {
    "iso:country":"GB",
    "wof:name":"NG19 9QW",
    "wof:placetype":"postalcode"
},
  "geometry": {"coordinates":[-1.17975658959518,53.17453990624849],"type":"Point"}
}