{
  "type": "Feature",
  "properties": {
    "iso:country":"GB",
    "wof:name":"HG1 4EZ",
    "wof:placetype":"postalcode"
},
  "geometry": {"coordinates":[-1.52632971009297,54.00985755110811],"type":"Point"}
}