{
  "type": "Feature",
  "properties": {
    "iso:country":"GB",
    "wof:name":"B23 5TH",
    "wof:placetype":"postalcode"
},
  "geometry": {"coordinates":[-1.83022876814429,52.53431978240596],"type":"Point"}
}