{
  "type": "Feature",
  "properties": {
    "date:inception_lower": "2017-12-01",
    "date:inception_upper": "2017-12-01",
    "iso:country": "GB",
    "wof:name": "IV15 9AA",
    "wof:placetype": "postalcode"
  },
  "geometry": {"coordinates":[-4.423224,57.60285],"type":"Point"}
}
