{
  "type": "Feature",
  "properties": {
    "iso:country": "GB",
    "wof:name": "GL52 8HX",
    "wof:placetype": "postalcode"
  },
  "geometry": {"coordinates":[-2.057774,51.9551],"type":"Point"}
}
