{
  "type": "Feature",
  "properties": {
    "date:inception_lower": "2019-06-01",
    "date:inception_upper": "2019-06-01",
    "iso:country": "GB",
    "wof:name": "GL52 8HX",
    "wof:placetype": "postalcode"
  },
  "geometry": {"coordinates":[-2.057774,51.9551],"type":"Point"}
}
