{
  "type": "Feature",
  "properties": {
    "iso:country": "GB",
    "wof:name": "FK15 9DJ",
    "wof:placetype": "postalcode"
  },
  "geometry": {"coordinates":[-3.970083,56.183146],"type":"Point"}
}
