{
  "type": "Feature",
  "properties": {
    "iso:country":"GB",
    "wof:name":"FK15 9DJ",
    "wof:placetype":"postalcode"
},
  "geometry": {"coordinates":[-3.96991742565825,56.18305884501596],"type":"Point"}
}