{
  "type": "Feature",
  "properties": {
    "iso:country": "GB",
    "wof:name": "SK7 2RB",
    "wof:placetype": "postalcode"
  },
  "geometry": {"coordinates":[-2.166518,53.359412],"type":"Point"}
}
