{
  "type": "Feature",
  "properties": {
    "date:inception_lower":"1991-01-01",
    "date:inception_upper":"1991-01-31",
    "iso:country":"GB",
    "wof:name":"FY4 4QH",
    "wof:placetype":"postalcode"
},
  "geometry": {"coordinates":[-3.018481,53.797619],"type":"Point"}
}