{
  "type": "Feature",
  "properties": {
    "iso:country": "GB",
    "wof:name": "SG18 9FR",
    "wof:placetype": "postalcode"
  },
  "geometry": {"coordinates":[-0.265551,52.04903],"type":"Point"}
}
