{
  "type": "Feature",
  "properties": {
    "date:inception_lower": "2018-02-01",
    "date:inception_upper": "2018-02-01",
    "iso:country": "GB",
    "wof:name": "SG18 9FR",
    "wof:placetype": "postalcode"
  },
  "geometry": {"coordinates":[-0.265222,52.049241],"type":"Point"}
}
