{
  "type": "Feature",
  "properties": {
    "iso:country":"GB",
    "wof:name":"CT10 2DA",
    "wof:placetype":"postalcode"
},
  "geometry": {"coordinates":[1.43046818280154,51.35736345988126],"type":"Point"}
}