{
  "type": "Feature",
  "properties": {
    "iso:country": "GB",
    "wof:name": "TN22 5LA",
    "wof:placetype": "postalcode"
  },
  "geometry": {"coordinates":[0.169898,50.969837],"type":"Point"}
}
