{
  "type": "Feature",
  "properties": {
    "date:inception_lower":"2003-03-01",
    "date:inception_upper":"2003-03-31",
    "iso:country":"GB",
    "wof:name":"WR2 5TL",
    "wof:placetype":"postalcode"
},
  "geometry": {"coordinates":[-2.264525,52.181119],"type":"Point"}
}