{
  "type": "Feature",
  "properties": {
    "iso:country":"GB",
    "wof:name":"WR2 5TL",
    "wof:placetype":"postalcode"
},
  "geometry": {"coordinates":[-2.26452474306422,52.18111902331668],"type":"Point"}
}