{
  "type": "Feature",
  "properties": {
    "iso:country":"GB",
    "wof:name":"WA4 4BL",
    "wof:placetype":"postalcode"
},
  "geometry": {"coordinates":[-2.63109463858718,53.31880187416963],"type":"Point"}
}