{
  "type": "Feature",
  "properties": {
    "iso:country":"GB",
    "wof:name":"G76 0YG",
    "wof:placetype":"postalcode"
},
  "geometry": {"coordinates":[-4.27699359246476,55.78897138015105],"type":"Point"}
}