{
  "type": "Feature",
  "properties": {
    "date:inception_lower":"2014-12-01",
    "date:inception_upper":"2014-12-31",
    "iso:country":"GB",
    "wof:name":"WS9 9NR",
    "wof:placetype":"postalcode"
},
  "geometry": {"coordinates":[-1.929293,52.628984],"type":"Point"}
}