{
  "type": "Feature",
  "properties": {
    "iso:country": "GB",
    "wof:name": "WS9 9NR",
    "wof:placetype": "postalcode"
  },
  "geometry": {"coordinates":[-1.929293,52.628984],"type":"Point"}
}
