{
  "type": "Feature",
  "properties": {
    "iso:country":"GB",
    "wof:name":"WS9 9NR",
    "wof:placetype":"postalcode"
},
  "geometry": {"coordinates":[-1.92929266082171,52.62898393261123],"type":"Point"}
}