{
  "type": "Feature",
  "properties": {
    "iso:country": "GB",
    "wof:name": "N12 9RE",
    "wof:placetype": "postalcode"
  },
  "geometry": {"coordinates":[-0.176269,51.617909],"type":"Point"}
}
