{
  "type": "Feature",
  "properties": {
    "iso:country":"GB",
    "wof:name":"N12 9RE",
    "wof:placetype":"postalcode"
},
  "geometry": {"coordinates":[-0.17605320954831,51.61780379262295],"type":"Point"}
}