{
  "type": "Feature",
  "properties": {
    "iso:country":"GB",
    "wof:name":"NG20 0NN",
    "wof:placetype":"postalcode"
},
  "geometry": {"coordinates":[-1.15212301880101,53.20035211567097],"type":"Point"}
}