{
  "type": "Feature",
  "properties": {
    "iso:country":"GB",
    "wof:name":"LU1 4BU",
    "wof:placetype":"postalcode"
},
  "geometry": {"coordinates":[-0.43507657171937,51.853487717417],"type":"Point"}
}