{
  "type": "Feature",
  "properties": {
    "iso:country": "GB",
    "wof:name": "LU1 4BU",
    "wof:placetype": "postalcode"
  },
  "geometry": {"coordinates":[-0.435077,51.853488],"type":"Point"}
}
