{
  "type": "Feature",
  "properties": {
    "iso:country":"GB",
    "wof:name":"BR6 0RT",
    "wof:placetype":"postalcode"
},
  "geometry": {"coordinates":[0.10058314197616,51.37575967769469],"type":"Point"}
}