{
  "type": "Feature",
  "properties": {
    "date:inception_lower": "1980-01-01",
    "date:inception_upper": "1980-01-01",
    "iso:country": "GB",
    "wof:name": "BR6 0RT",
    "wof:placetype": "postalcode"
  },
  "geometry": {"coordinates":[0.101298,51.37573],"type":"Point"}
}
