{
  "type": "Feature",
  "properties": {
    "date:inception_lower": "1980-01-01",
    "date:inception_upper": "1980-01-01",
    "iso:country": "GB",
    "wof:name": "DY7 5JA",
    "wof:placetype": "postalcode"
  },
  "geometry": {"coordinates":[-2.260689,52.479692],"type":"Point"}
}
