{
  "type": "Feature",
  "properties": {
    "iso:country":"GB",
    "wof:name":"CO10 9EU",
    "wof:placetype":"postalcode"
},
  "geometry": {"coordinates":[0.71968698514042,52.07430445451836],"type":"Point"}
}