{
  "type": "Feature",
  "properties": {
    "date:inception_lower":"1980-01-01",
    "date:inception_upper":"1980-01-31",
    "iso:country":"GB",
    "wof:name":"CO10 9EU",
    "wof:placetype":"postalcode"
},
  "geometry": {"coordinates":[0.719687,52.074304],"type":"Point"}
}