{
  "type": "Feature",
  "properties": {
    "iso:country": "GB",
    "wof:name": "IP24 1QR",
    "wof:placetype": "postalcode"
  },
  "geometry": {"coordinates":[0.836146,52.478196],"type":"Point"}
}
