{
  "type": "Feature",
  "properties": {
    "iso:country":"GB",
    "wof:name":"IP24 1QR",
    "wof:placetype":"postalcode"
},
  "geometry": {"coordinates":[0.83614620807133,52.47819609216322],"type":"Point"}
}