{
  "type": "Feature",
  "properties": {
    "date:inception_lower": "1995-07-01",
    "date:inception_upper": "1995-07-01",
    "iso:country": "GB",
    "wof:name": "SO31 8JD",
    "wof:placetype": "postalcode"
  },
  "geometry": {"coordinates":[-1.325043,50.886249],"type":"Point"}
}
