{
  "type": "Feature",
  "properties": {
    "iso:country":"GB",
    "wof:name":"SO31 8JD",
    "wof:placetype":"postalcode"
},
  "geometry": {"coordinates":[-1.32505299576254,50.88626786173974],"type":"Point"}
}