{
  "type": "Feature",
  "properties": {
    "date:inception_lower": "2005-03-01",
    "date:inception_upper": "2005-03-01",
    "iso:country": "GB",
    "wof:name": "B18 5SQ",
    "wof:placetype": "postalcode"
  },
  "geometry": {"coordinates":[-1.927021,52.492733],"type":"Point"}
}
