{
  "type": "Feature",
  "properties": {
    "iso:country": "GB",
    "wof:name": "B18 5SQ",
    "wof:placetype": "postalcode"
  },
  "geometry": {"coordinates":[-1.927021,52.492733],"type":"Point"}
}
