{
  "type": "Feature",
  "properties": {
    "date:inception_lower": "1990-02-01",
    "date:inception_upper": "1990-02-01",
    "iso:country": "GB",
    "wof:name": "M5 4TP",
    "wof:placetype": "postalcode"
  },
  "geometry": {"coordinates":[-2.265678,53.473818],"type":"Point"}
}
