{
  "type": "Feature",
  "properties": {
    "iso:country": "GB",
    "wof:name": "IP6 0NX",
    "wof:placetype": "postalcode"
  },
  "geometry": {"coordinates":[1.103365,52.110796],"type":"Point"}
}
