{
  "type": "Feature",
  "properties": {
    "iso:country":"GB",
    "wof:name":"IP6 0NX",
    "wof:placetype":"postalcode"
},
  "geometry": {"coordinates":[1.10336503563104,52.11079620172406],"type":"Point"}
}