{
  "type": "Feature",
  "properties": {
    "iso:country":"GB",
    "wof:name":"HP27 9BN",
    "wof:placetype":"postalcode"
},
  "geometry": {"coordinates":[-0.82483753501368,51.73434907667924],"type":"Point"}
}