{
  "type": "Feature",
  "properties": {
    "iso:country": "GB",
    "wof:name": "HP27 9BN",
    "wof:placetype": "postalcode"
  },
  "geometry": {"coordinates":[-0.824837,51.734349],"type":"Point"}
}
