{
  "type": "Feature",
  "properties": {
    "date:inception_lower":"2010-09-01",
    "date:inception_upper":"2010-09-30",
    "iso:country":"GB",
    "wof:name":"HP27 9BN",
    "wof:placetype":"postalcode"
},
  "geometry": {"coordinates":[-0.824837,51.734349],"type":"Point"}
}