{
  "type": "Feature",
  "properties": {
    "date:inception_lower":"1980-01-01",
    "date:inception_upper":"1980-01-31",
    "iso:country":"GB",
    "wof:name":"PA17 5BN",
    "wof:placetype":"postalcode"
},
  "geometry": {"coordinates":[-4.883227,55.86428],"type":"Point"}
}