{
  "type": "Feature",
  "properties": {
    "iso:country": "GB",
    "wof:name": "PA17 5BN",
    "wof:placetype": "postalcode"
  },
  "geometry": {"coordinates":[-4.883227,55.86428],"type":"Point"}
}
