{
  "type": "Feature",
  "properties": {
    "iso:country":"GB",
    "wof:name":"PA17 5BN",
    "wof:placetype":"postalcode"
},
  "geometry": {"coordinates":[-4.88322712630973,55.8642796339972],"type":"Point"}
}