{
  "type": "Feature",
  "properties": {
    "iso:country": "GB",
    "wof:name": "HU4 6RL",
    "wof:placetype": "postalcode"
  },
  "geometry": {"coordinates":[-0.394089,53.732879],"type":"Point"}
}
