{
  "type": "Feature",
  "properties": {
    "iso:country":"GB",
    "wof:name":"CM6 3QE",
    "wof:placetype":"postalcode"
},
  "geometry": {"coordinates":[0.34933564459816,51.93873326506403],"type":"Point"}
}