{
  "type": "Feature",
  "properties": {
    "iso:country": "GB",
    "wof:name": "CM6 3QE",
    "wof:placetype": "postalcode"
  },
  "geometry": {"coordinates":[0.348169,51.938702],"type":"Point"}
}
