{
  "type": "Feature",
  "properties": {
    "iso:country":"GB",
    "wof:name":"PA28 6DU",
    "wof:placetype":"postalcode"
},
  "geometry": {"coordinates":[-5.60227368807858,55.43005983681439],"type":"Point"}
}