{
  "type": "Feature",
  "properties": {
    "date:inception_lower":"1980-01-01",
    "date:inception_upper":"1980-01-31",
    "iso:country":"GB",
    "wof:name":"PA28 6DU",
    "wof:placetype":"postalcode"
},
  "geometry": {"coordinates":[-5.602274,55.43006],"type":"Point"}
}