{
  "type": "Feature",
  "properties": {
    "iso:country": "GB",
    "wof:name": "PA28 6DU",
    "wof:placetype": "postalcode"
  },
  "geometry": {"coordinates":[-5.602274,55.43006],"type":"Point"}
}
