{
  "type": "Feature",
  "properties": {
    "iso:country": "GB",
    "wof:name": "LA12 9EX",
    "wof:placetype": "postalcode"
  },
  "geometry": {"coordinates":[-3.089015,54.187125],"type":"Point"}
}
