{
  "type": "Feature",
  "properties": {
    "iso:country":"GB",
    "wof:name":"ME15 8EW",
    "wof:placetype":"postalcode"
},
  "geometry": {"coordinates":[0.55492068462832,51.25714196822241],"type":"Point"}
}