{
  "type": "Feature",
  "properties": {
    "date:inception_lower": "1980-01-01",
    "date:inception_upper": "1980-01-01",
    "iso:country": "GB",
    "wof:name": "ME15 8EW",
    "wof:placetype": "postalcode"
  },
  "geometry": {"coordinates":[0.554921,51.257142],"type":"Point"}
}
