{
  "type": "Feature",
  "properties": {
    "date:inception_lower": "1984-10-01",
    "date:inception_upper": "1984-10-01",
    "iso:country": "GB",
    "wof:name": "TA4 4PY",
    "wof:placetype": "postalcode"
  },
  "geometry": {"coordinates":[-3.32033,51.16084],"type":"Point"}
}
