{
  "type": "Feature",
  "properties": {
    "iso:country": "GB",
    "wof:name": "ML3 8EJ",
    "wof:placetype": "postalcode"
  },
  "geometry": {"coordinates":[-4.060167,55.763167],"type":"Point"}
}
