{
  "type": "Feature",
  "properties": {
    "iso:country":"GB",
    "wof:name":"CR2 0FD",
    "wof:placetype":"postalcode"
},
  "geometry": {"coordinates":[-0.09541709504612,51.34444297804549],"type":"Point"}
}