{
  "type": "Feature",
  "properties": {
    "date:inception_lower": "2010-05-01",
    "date:inception_upper": "2010-05-01",
    "iso:country": "GB",
    "wof:name": "CR2 0FD",
    "wof:placetype": "postalcode"
  },
  "geometry": {"coordinates":[-0.095417,51.344443],"type":"Point"}
}
