{
  "type": "Feature",
  "properties": {
    "date:inception_lower": "1980-01-01",
    "date:inception_upper": "1980-01-01",
    "iso:country": "GB",
    "wof:name": "GL5 1EN",
    "wof:placetype": "postalcode"
  },
  "geometry": {"coordinates":[-2.204608,51.74114],"type":"Point"}
}
