{
  "type": "Feature",
  "properties": {
    "iso:country":"GB",
    "wof:name":"GL5 1EN",
    "wof:placetype":"postalcode"
},
  "geometry": {"coordinates":[-2.20460790292663,51.7411402134453],"type":"Point"}
}