{
  "type": "Feature",
  "properties": {
    "date:inception_lower":"1992-01-01",
    "date:inception_upper":"1992-01-31",
    "iso:country":"GB",
    "wof:name":"DY4 8XY",
    "wof:placetype":"postalcode"
},
  "geometry": {"coordinates":[-2.059937,52.519691],"type":"Point"}
}