{
  "type": "Feature",
  "properties": {
    "iso:country": "GB",
    "wof:name": "DY4 8XY",
    "wof:placetype": "postalcode"
  },
  "geometry": {"coordinates":[-2.059937,52.519691],"type":"Point"}
}
