{
  "type": "Feature",
  "properties": {
    "iso:country":"GB",
    "wof:name":"DY4 8XY",
    "wof:placetype":"postalcode"
},
  "geometry": {"coordinates":[-2.05993748781705,52.51969140993825],"type":"Point"}
}