{
  "type": "Feature",
  "properties": {
    "iso:country": "GB",
    "wof:name": "DN20 9BX",
    "wof:placetype": "postalcode"
  },
  "geometry": {"coordinates":[-0.533688,53.535542],"type":"Point"}
}
