{
  "type": "Feature",
  "properties": {
    "date:inception_lower": "2021-12-01",
    "date:inception_upper": "2021-12-01",
    "iso:country": "GB",
    "wof:name": "CV37 9GB",
    "wof:placetype": "postalcode"
  },
  "geometry": {"coordinates":[-1.734345,52.204579],"type":"Point"}
}
