{
  "type": "Feature",
  "properties": {
    "iso:country":"GB",
    "wof:name":"WA8 7AL",
    "wof:placetype":"postalcode"
},
  "geometry": {"coordinates":[-2.73944229259716,53.36102022958733],"type":"Point"}
}