{
  "type": "Feature",
  "properties": {
    "iso:country":"GB",
    "wof:name":"PE1 4UB",
    "wof:placetype":"postalcode"
},
  "geometry": {"coordinates":[-0.21820123448244,52.59669144006025],"type":"Point"}
}