{
  "type": "Feature",
  "properties": {
    "iso:country": "GB",
    "wof:name": "BA20 1DR",
    "wof:placetype": "postalcode"
  },
  "geometry": {"coordinates":[-2.633858,50.942716],"type":"Point"}
}
