{
  "type": "Feature",
  "properties": {
    "iso:country":"GB",
    "wof:name":"BA20 1DR",
    "wof:placetype":"postalcode"
},
  "geometry": {"coordinates":[-2.63385775874957,50.94271621429973],"type":"Point"}
}