{
  "type": "Feature",
  "properties": {
    "date:inception_lower":"2008-01-01",
    "date:inception_upper":"2008-01-31",
    "iso:country":"GB",
    "wof:name":"BA20 1DR",
    "wof:placetype":"postalcode"
},
  "geometry": {"coordinates":[-2.633858,50.942716],"type":"Point"}
}