{
  "type": "Feature",
  "properties": {
    "iso:country":"GB",
    "wof:name":"OL15 0AS",
    "wof:placetype":"postalcode"
},
  "geometry": {"coordinates":[-2.09036231538674,53.624975613527],"type":"Point"}
}