{
  "type": "Feature",
  "properties": {
    "iso:country": "GB",
    "wof:name": "CV36 5LT",
    "wof:placetype": "postalcode"
  },
  "geometry": {"coordinates":[-1.615685,52.027387],"type":"Point"}
}
