{
  "type": "Feature",
  "properties": {
    "iso:country":"GB",
    "wof:name":"CV36 5LT",
    "wof:placetype":"postalcode"
},
  "geometry": {"coordinates":[-1.61620762120307,52.0291666427393],"type":"Point"}
}