{
  "type": "Feature",
  "properties": {
    "iso:country": "GB",
    "wof:name": "G72 0TN",
    "wof:placetype": "postalcode"
  },
  "geometry": {"coordinates":[-4.130819,55.768235],"type":"Point"}
}
