{
  "type": "Feature",
  "properties": {
    "iso:country": "GB",
    "wof:name": "FK8 2BX",
    "wof:placetype": "postalcode"
  },
  "geometry": {"coordinates":[-3.936763,56.119332],"type":"Point"}
}
