{
  "type": "Feature",
  "properties": {
    "iso:country": "GB",
    "wof:name": "ST2 8NT",
    "wof:placetype": "postalcode"
  },
  "geometry": {"coordinates":[-2.135252,53.028219],"type":"Point"}
}
