{
  "type": "Feature",
  "properties": {
    "date:inception_lower":"2017-04-01",
    "date:inception_upper":"2017-04-30",
    "iso:country":"GB",
    "wof:name":"ST2 8NT",
    "wof:placetype":"postalcode"
},
  "geometry": {"coordinates":[-2.135252,53.028219],"type":"Point"}
}