{
  "type": "Feature",
  "properties": {
    "date:inception_lower": "1980-01-01",
    "date:inception_upper": "1980-01-01",
    "iso:country": "GB",
    "wof:name": "TQ7 4DT",
    "wof:placetype": "postalcode"
  },
  "geometry": {"coordinates":[-3.794109,50.341197],"type":"Point"}
}
