{
  "type": "Feature",
  "properties": {
    "iso:country":"GB",
    "wof:name":"RH19 4HS",
    "wof:placetype":"postalcode"
},
  "geometry": {"coordinates":[-0.02749810166194,51.07607225479634],"type":"Point"}
}