{
  "type": "Feature",
  "properties": {
    "date:inception_lower": "1980-01-01",
    "date:inception_upper": "1980-01-01",
    "iso:country": "GB",
    "wof:name": "RH19 4HS",
    "wof:placetype": "postalcode"
  },
  "geometry": {"coordinates":[-0.027471,51.076068],"type":"Point"}
}
