{
  "type": "Feature",
  "properties": {
    "iso:country": "GB",
    "wof:name": "NN8 3FS",
    "wof:placetype": "postalcode"
  },
  "geometry": {"coordinates":[-0.718183,52.30592],"type":"Point"}
}
