{
  "type": "Feature",
  "properties": {
    "date:inception_lower": "1992-08-01",
    "date:inception_upper": "1992-08-01",
    "iso:country": "GB",
    "wof:name": "NN8 3FS",
    "wof:placetype": "postalcode"
  },
  "geometry": {"coordinates":[-0.718183,52.30592],"type":"Point"}
}
