{
  "type": "Feature",
  "properties": {
    "iso:country":"GB",
    "wof:name":"AL10 9QY",
    "wof:placetype":"postalcode"
},
  "geometry": {"coordinates":[-0.23563365927657,51.74818353380765],"type":"Point"}
}