{
  "type": "Feature",
  "properties": {
    "date:inception_lower": "1980-01-01",
    "date:inception_upper": "1980-01-01",
    "iso:country": "GB",
    "wof:name": "AL10 9QY",
    "wof:placetype": "postalcode"
  },
  "geometry": {"coordinates":[-0.235613,51.748135],"type":"Point"}
}
