{
  "type": "Feature",
  "properties": {
    "iso:country": "GB",
    "wof:name": "DN36 4HF",
    "wof:placetype": "postalcode"
  },
  "geometry": {"coordinates":[-0.056445,53.526678],"type":"Point"}
}
