{
  "type": "Feature",
  "properties": {
    "date:inception_lower":"2008-01-01",
    "date:inception_upper":"2008-01-31",
    "iso:country":"GB",
    "wof:name":"DN36 4HF",
    "wof:placetype":"postalcode"
},
  "geometry": {"coordinates":[-0.056445,53.526678],"type":"Point"}
}