{
  "type": "Feature",
  "properties": {
    "iso:country":"GB",
    "wof:name":"DN36 4HF",
    "wof:placetype":"postalcode"
},
  "geometry": {"coordinates":[-0.0564447212467,53.52667831438439],"type":"Point"}
}