{
  "type": "Feature",
  "properties": {
    "iso:country":"GB",
    "wof:name":"M35 0GX",
    "wof:placetype":"postalcode"
},
  "geometry": {"coordinates":[-2.1501779141284,53.50224281614607],"type":"Point"}
}