{
  "type": "Feature",
  "properties": {
    "iso:country":"GB",
    "wof:name":"CO14 8BY",
    "wof:placetype":"postalcode"
},
  "geometry": {"coordinates":[1.26728426240614,51.84766217046024],"type":"Point"}
}