{
  "type": "Feature",
  "properties": {
    "date:inception_lower":"2009-02-01",
    "date:inception_upper":"2009-02-28",
    "iso:country":"GB",
    "wof:name":"CO14 8BY",
    "wof:placetype":"postalcode"
},
  "geometry": {"coordinates":[1.267284,51.847662],"type":"Point"}
}