{
  "type": "Feature",
  "properties": {
    "iso:country": "GB",
    "wof:name": "TQ13 9GD",
    "wof:placetype": "postalcode"
  },
  "geometry": {"coordinates":[-3.657534,50.589374],"type":"Point"}
}
