{
  "type": "Feature",
  "properties": {
    "date:inception_lower": "2019-05-01",
    "date:inception_upper": "2019-05-01",
    "iso:country": "GB",
    "wof:name": "S71 1AH",
    "wof:placetype": "postalcode"
  },
  "geometry": {"coordinates":[-1.476753,53.555997],"type":"Point"}
}
