{
  "type": "Feature",
  "properties": {
    "iso:country": "GB",
    "wof:name": "S71 1AH",
    "wof:placetype": "postalcode"
  },
  "geometry": {"coordinates":[-1.476753,53.555997],"type":"Point"}
}
