{
  "type": "Feature",
  "properties": {
    "date:inception_lower": "1980-01-01",
    "date:inception_upper": "1980-01-01",
    "iso:country": "GB",
    "wof:name": "DH6 2LQ",
    "wof:placetype": "postalcode"
  },
  "geometry": {"coordinates":[-1.388095,54.760836],"type":"Point"}
}
