{
  "type": "Feature",
  "properties": {
    "iso:country": "GB",
    "wof:name": "S42 5HX",
    "wof:placetype": "postalcode"
  },
  "geometry": {"coordinates":[-1.394608,53.175987],"type":"Point"}
}
