{
  "type": "Feature",
  "properties": {
    "iso:country":"GB",
    "wof:name":"S42 5HX",
    "wof:placetype":"postalcode"
},
  "geometry": {"coordinates":[-1.39460777056526,53.17598683473108],"type":"Point"}
}