{
  "type": "Feature",
  "properties": {
    "iso:country": "GB",
    "wof:name": "TS17 5HE",
    "wof:placetype": "postalcode"
  },
  "geometry": {"coordinates":[-1.327468,54.51414],"type":"Point"}
}
