{
  "type": "Feature",
  "properties": {
    "date:inception_lower":"1999-12-01",
    "date:inception_upper":"1999-12-31",
    "iso:country":"GB",
    "wof:name":"TS17 5HE",
    "wof:placetype":"postalcode"
},
  "geometry": {"coordinates":[-1.327468,54.51414],"type":"Point"}
}