{
  "type": "Feature",
  "properties": {
    "iso:country":"GB",
    "wof:name":"E20 1DR",
    "wof:placetype":"postalcode"
},
  "geometry": {"coordinates":[-0.0112510066819,51.54631627052476],"type":"Point"}
}