{
  "type": "Feature",
  "properties": {
    "date:inception_lower": "2014-04-01",
    "date:inception_upper": "2014-04-01",
    "iso:country": "GB",
    "wof:name": "E20 1DR",
    "wof:placetype": "postalcode"
  },
  "geometry": {"coordinates":[-0.011251,51.546316],"type":"Point"}
}
