{
  "type": "Feature",
  "properties": {
    "iso:country":"GB",
    "wof:name":"TA13 5HB",
    "wof:placetype":"postalcode"
},
  "geometry": {"coordinates":[-2.85105939020915,50.96990404725438],"type":"Point"}
}