{
  "type": "Feature",
  "properties": {
    "date:inception_lower":"1980-01-01",
    "date:inception_upper":"1980-01-31",
    "iso:country":"GB",
    "wof:name":"TA13 5HB",
    "wof:placetype":"postalcode"
},
  "geometry": {"coordinates":[-2.852601,50.968258],"type":"Point"}
}