{
  "type": "Feature",
  "properties": {
    "iso:country":"GB",
    "wof:name":"GU32 1RR",
    "wof:placetype":"postalcode"
},
  "geometry": {"coordinates":[-0.9962146497094,50.9953495364196],"type":"Point"}
}