{
  "type": "Feature",
  "properties": {
    "iso:country": "GB",
    "wof:name": "GU32 1RR",
    "wof:placetype": "postalcode"
  },
  "geometry": {"coordinates":[-0.99614,50.995415],"type":"Point"}
}
