{
  "type": "Feature",
  "properties": {
    "date:inception_lower": "1980-01-01",
    "date:inception_upper": "1980-01-01",
    "iso:country": "GB",
    "wof:name": "GU32 1RR",
    "wof:placetype": "postalcode"
  },
  "geometry": {"coordinates":[-0.99614,50.995415],"type":"Point"}
}
