{
  "type": "Feature",
  "properties": {
    "iso:country": "GB",
    "wof:name": "DN11 0DF",
    "wof:placetype": "postalcode"
  },
  "geometry": {"coordinates":[-1.062711,53.47142],"type":"Point"}
}
