{
  "type": "Feature",
  "properties": {
    "iso:country": "GB",
    "wof:name": "WN6 9RE",
    "wof:placetype": "postalcode"
  },
  "geometry": {"coordinates":[-2.697406,53.598429],"type":"Point"}
}
