{
  "type": "Feature",
  "properties": {
    "iso:country":"GB",
    "wof:name":"WN6 9RE",
    "wof:placetype":"postalcode"
},
  "geometry": {"coordinates":[-2.69740563504538,53.59842934970645],"type":"Point"}
}