{
  "type": "Feature",
  "properties": {
    "iso:country":"GB",
    "wof:name":"CH8 8LF",
    "wof:placetype":"postalcode"
},
  "geometry": {"coordinates":[-3.24390773929829,53.26466027172441],"type":"Point"}
}