{
  "type": "Feature",
  "properties": {
    "iso:country":"GB",
    "wof:name":"G71 7NU",
    "wof:placetype":"postalcode"
},
  "geometry": {"coordinates":[-4.07594078873412,55.81849586165625],"type":"Point"}
}