{
  "type": "Feature",
  "properties": {
    "date:inception_lower": "1997-06-01",
    "date:inception_upper": "1997-06-01",
    "iso:country": "GB",
    "wof:name": "LE12 5LU",
    "wof:placetype": "postalcode"
  },
  "geometry": {"coordinates":[-1.259446,52.796015],"type":"Point"}
}
