{
  "type": "Feature",
  "properties": {
    "iso:country":"GB",
    "wof:name":"LE12 5LU",
    "wof:placetype":"postalcode"
},
  "geometry": {"coordinates":[-1.25944639554227,52.79601507240724],"type":"Point"}
}