{
  "type": "Feature",
  "properties": {
    "iso:country":"GB",
    "wof:name":"B28 0EG",
    "wof:placetype":"postalcode"
},
  "geometry": {"coordinates":[-1.85327063186609,52.4279992649559],"type":"Point"}
}