{
  "type": "Feature",
  "properties": {
    "iso:country":"GB",
    "wof:name":"GU34 4AH",
    "wof:placetype":"postalcode"
},
  "geometry": {"coordinates":[-1.01150107274691,51.14496064470668],"type":"Point"}
}