{
  "type": "Feature",
  "properties": {
    "iso:country": "GB",
    "wof:name": "BN44 3BA",
    "wof:placetype": "postalcode"
  },
  "geometry": {"coordinates":[-0.325618,50.939519],"type":"Point"}
}
