{
  "type": "Feature",
  "properties": {
    "date:inception_lower":"1990-07-01",
    "date:inception_upper":"1990-07-31",
    "iso:country":"GB",
    "wof:name":"BN44 3BA",
    "wof:placetype":"postalcode"
},
  "geometry": {"coordinates":[-0.325703,50.93952],"type":"Point"}
}