{
  "type": "Feature",
  "properties": {
    "iso:country":"GB",
    "wof:name":"BN44 3BA",
    "wof:placetype":"postalcode"
},
  "geometry": {"coordinates":[-0.3257276734309,50.93956110331249],"type":"Point"}
}