{
  "type": "Feature",
  "properties": {
    "iso:country": "GB",
    "wof:name": "G69 6DR",
    "wof:placetype": "postalcode"
  },
  "geometry": {"coordinates":[-4.106113,55.854291],"type":"Point"}
}
