{
  "type": "Feature",
  "properties": {
    "date:inception_lower": "1980-01-01",
    "date:inception_upper": "1980-01-01",
    "iso:country": "GB",
    "wof:name": "G69 6DR",
    "wof:placetype": "postalcode"
  },
  "geometry": {"coordinates":[-4.106113,55.854291],"type":"Point"}
}
