{
  "type": "Feature",
  "properties": {
    "iso:country": "GB",
    "wof:name": "BL7 0BF",
    "wof:placetype": "postalcode"
  },
  "geometry": {"coordinates":[-2.39628,53.63806],"type":"Point"}
}
