{
  "type": "Feature",
  "properties": {
    "date:inception_lower": "1997-06-01",
    "date:inception_upper": "1997-06-01",
    "iso:country": "GB",
    "wof:name": "BL7 0BF",
    "wof:placetype": "postalcode"
  },
  "geometry": {"coordinates":[-2.39628,53.63806],"type":"Point"}
}
