{
  "type": "Feature",
  "properties": {
    "iso:country": "GB",
    "wof:name": "KT6 5DA",
    "wof:placetype": "postalcode"
  },
  "geometry": {"coordinates":[-0.305812,51.376279],"type":"Point"}
}
