{
  "type": "Feature",
  "properties": {
    "date:inception_lower": "2019-06-01",
    "date:inception_upper": "2019-06-01",
    "iso:country": "GB",
    "wof:name": "KT6 5DA",
    "wof:placetype": "postalcode"
  },
  "geometry": {"coordinates":[-0.305812,51.376279],"type":"Point"}
}
