{
  "type": "Feature",
  "properties": {
    "date:inception_lower": "1996-12-01",
    "date:inception_upper": "1996-12-01",
    "iso:country": "GB",
    "wof:name": "G33 6BQ",
    "wof:placetype": "postalcode"
  },
  "geometry": {"coordinates":[-4.143215,55.885002],"type":"Point"}
}
