{
  "type": "Feature",
  "properties": {
    "iso:country":"GB",
    "wof:name":"W1U 4EW",
    "wof:placetype":"postalcode"
},
  "geometry": {"coordinates":[-0.15221919540157,51.51992628245782],"type":"Point"}
}