{
  "type": "Feature",
  "properties": {
    "date:inception_lower": "1980-01-01",
    "date:inception_upper": "1980-01-01",
    "iso:country": "GB",
    "wof:name": "WV16 5BX",
    "wof:placetype": "postalcode"
  },
  "geometry": {"coordinates":[-2.431283,52.532414],"type":"Point"}
}
