{
  "type": "Feature",
  "properties": {
    "iso:country":"GB",
    "wof:name":"N10 3ED",
    "wof:placetype":"postalcode"
},
  "geometry": {"coordinates":[-0.15158671754775,51.58962568476759],"type":"Point"}
}