{
  "type": "Feature",
  "properties": {
    "iso:country":"GB",
    "wof:name":"NP23 6PE",
    "wof:placetype":"postalcode"
},
  "geometry": {"coordinates":[-3.21439055007127,51.77616013128598],"type":"Point"}
}