{
  "type": "Feature",
  "properties": {
    "date:inception_lower": "2018-09-01",
    "date:inception_upper": "2018-09-01",
    "iso:country": "GB",
    "wof:name": "NW1W 9QY",
    "wof:placetype": "postalcode"
  },
  "geometry": {"coordinates":[-0.135404,51.530786],"type":"Point"}
}
