{
  "type": "Feature",
  "properties": {
    "iso:country":"GB",
    "wof:name":"S60 2QS",
    "wof:placetype":"postalcode"
},
  "geometry": {"coordinates":[-1.34680227388373,53.42411499950841],"type":"Point"}
}