{
  "type": "Feature",
  "properties": {
    "date:inception_lower": "1991-11-01",
    "date:inception_upper": "1991-11-01",
    "iso:country": "GB",
    "wof:name": "G60 5LH",
    "wof:placetype": "postalcode"
  },
  "geometry": {"coordinates":[-4.451271,55.91944],"type":"Point"}
}
