{
  "type": "Feature",
  "properties": {
    "iso:country":"GB",
    "wof:name":"G60 5LH",
    "wof:placetype":"postalcode"
},
  "geometry": {"coordinates":[-4.45127076920528,55.91943973508243],"type":"Point"}
}