{
  "type": "Feature",
  "properties": {
    "iso:country": "GB",
    "wof:name": "TQ1 3ED",
    "wof:placetype": "postalcode"
  },
  "geometry": {"coordinates":[-3.536016,50.471441],"type":"Point"}
}
