{
  "type": "Feature",
  "properties": {
    "iso:country": "GB",
    "wof:name": "S9 4GB",
    "wof:placetype": "postalcode"
  },
  "geometry": {"coordinates":[-1.414453,53.377527],"type":"Point"}
}
