{
  "type": "Feature",
  "properties": {
    "date:inception_lower": "1980-01-01",
    "date:inception_upper": "1980-01-01",
    "iso:country": "GB",
    "wof:name": "PO33 1PQ",
    "wof:placetype": "postalcode"
  },
  "geometry": {"coordinates":[-1.13826,50.721416],"type":"Point"}
}
