{
  "type": "Feature",
  "properties": {
    "iso:country":"GB",
    "wof:name":"B74 4QL",
    "wof:placetype":"postalcode"
},
  "geometry": {"coordinates":[-1.84269912284896,52.58847381131259],"type":"Point"}
}