{
  "type": "Feature",
  "properties": {
    "date:inception_lower":"1991-01-01",
    "date:inception_upper":"1991-01-31",
    "iso:country":"GB",
    "wof:name":"B74 4QL",
    "wof:placetype":"postalcode"
},
  "geometry": {"coordinates":[-1.842699,52.588474],"type":"Point"}
}