{
  "type": "Feature",
  "properties": {
    "iso:country":"GB",
    "wof:name":"WS13 8RB",
    "wof:placetype":"postalcode"
},
  "geometry": {"coordinates":[-1.70228366261584,52.71904983583115],"type":"Point"}
}