{
  "type": "Feature",
  "properties": {
    "date:inception_lower": "1983-03-01",
    "date:inception_upper": "1983-03-01",
    "iso:country": "GB",
    "wof:name": "L12 0JQ",
    "wof:placetype": "postalcode"
  },
  "geometry": {"coordinates":[-2.887539,53.449701],"type":"Point"}
}
