{
  "type": "Feature",
  "properties": {
    "date:inception_lower": "2017-10-01",
    "date:inception_upper": "2017-10-01",
    "iso:country": "GB",
    "wof:name": "HU13 0FJ",
    "wof:placetype": "postalcode"
  },
  "geometry": {"coordinates":[-0.460813,53.731238],"type":"Point"}
}
