{
  "type": "Feature",
  "properties": {
    "iso:country":"GB",
    "wof:name":"NR2 2TL",
    "wof:placetype":"postalcode"
},
  "geometry": {"coordinates":[1.28791510758379,52.62338855090617],"type":"Point"}
}