{
  "type": "Feature",
  "properties": {
    "iso:country": "GB",
    "wof:name": "NR2 2TL",
    "wof:placetype": "postalcode"
  },
  "geometry": {"coordinates":[1.288045,52.623068],"type":"Point"}
}
