{
  "type": "Feature",
  "properties": {
    "iso:country":"GB",
    "wof:name":"S6 5HG",
    "wof:placetype":"postalcode"
},
  "geometry": {"coordinates":[-1.51885704290492,53.39828033226583],"type":"Point"}
}