{
  "type": "Feature",
  "properties": {
    "iso:country": "GB",
    "wof:name": "PE10 0PJ",
    "wof:placetype": "postalcode"
  },
  "geometry": {"coordinates":[-0.36432,52.802392],"type":"Point"}
}
