{
  "type": "Feature",
  "properties": {
    "iso:country":"GB",
    "wof:name":"PE10 0PJ",
    "wof:placetype":"postalcode"
},
  "geometry": {"coordinates":[-0.36432025409192,52.8023915644356],"type":"Point"}
}