{
  "type": "Feature",
  "properties": {
    "iso:country":"GB",
    "wof:name":"E1 3BX",
    "wof:placetype":"postalcode"
},
  "geometry": {"coordinates":[-0.05407750958284,51.51913947318187],"type":"Point"}
}