{
  "type": "Feature",
  "properties": {
    "date:inception_lower": "2019-02-01",
    "date:inception_upper": "2019-02-01",
    "iso:country": "GB",
    "wof:name": "IP18 6FA",
    "wof:placetype": "postalcode"
  },
  "geometry": {"coordinates":[1.676029,52.327984],"type":"Point"}
}
