{
  "type": "Feature",
  "properties": {
    "iso:country":"GB",
    "wof:name":"TA20 4PT",
    "wof:placetype":"postalcode"
},
  "geometry": {"coordinates":[-2.88503522112652,50.82639015131443],"type":"Point"}
}