{
  "type": "Feature",
  "properties": {
    "iso:country": "GB",
    "wof:name": "YO22 5LB",
    "wof:placetype": "postalcode"
  },
  "geometry": {"coordinates":[-0.7251,54.40595],"type":"Point"}
}
