{
  "type": "Feature",
  "properties": {
    "iso:country":"GB",
    "wof:name":"BH9 1NX",
    "wof:placetype":"postalcode"
},
  "geometry": {"coordinates":[-1.87519029833931,50.74685150827897],"type":"Point"}
}