{
  "type": "Feature",
  "properties": {
    "date:inception_lower": "1980-01-01",
    "date:inception_upper": "1980-01-01",
    "iso:country": "GB",
    "wof:name": "OL9 7DQ",
    "wof:placetype": "postalcode"
  },
  "geometry": {"coordinates":[-2.137837,53.531955],"type":"Point"}
}
