{
  "type": "Feature",
  "properties": {
    "iso:country":"GB",
    "wof:name":"OL9 7DQ",
    "wof:placetype":"postalcode"
},
  "geometry": {"coordinates":[-2.13783685396257,53.5319553407256],"type":"Point"}
}