{
  "type": "Feature",
  "properties": {
    "iso:country": "GB",
    "wof:name": "OL9 7DQ",
    "wof:placetype": "postalcode"
  },
  "geometry": {"coordinates":[-2.137837,53.531955],"type":"Point"}
}
