{
  "type": "Feature",
  "properties": {
    "iso:country": "GB",
    "wof:name": "TS4 3JN",
    "wof:placetype": "postalcode"
  },
  "geometry": {"coordinates":[-1.23083,54.546448],"type":"Point"}
}
