{
  "type": "Feature",
  "properties": {
    "iso:country": "GB",
    "wof:name": "L18 1DA",
    "wof:placetype": "postalcode"
  },
  "geometry": {"coordinates":[-2.920003,53.385563],"type":"Point"}
}
