{
  "type": "Feature",
  "properties": {
    "date:inception_lower":"1984-10-01",
    "date:inception_upper":"1984-10-31",
    "iso:country":"GB",
    "wof:name":"LE9 7EX",
    "wof:placetype":"postalcode"
},
  "geometry": {"coordinates":[-1.299434,52.578479],"type":"Point"}
}