{
  "type": "Feature",
  "properties": {
    "iso:country":"GB",
    "wof:name":"LE9 7EX",
    "wof:placetype":"postalcode"
},
  "geometry": {"coordinates":[-1.29943407354786,52.57847943543324],"type":"Point"}
}