{
  "type": "Feature",
  "properties": {
    "iso:country": "GB",
    "wof:name": "LE9 7EX",
    "wof:placetype": "postalcode"
  },
  "geometry": {"coordinates":[-1.299434,52.578479],"type":"Point"}
}
