{
  "type": "Feature",
  "properties": {
    "iso:country":"GB",
    "wof:name":"WF17 6HF",
    "wof:placetype":"postalcode"
},
  "geometry": {"coordinates":[-1.61086973042679,53.71574343751265],"type":"Point"}
}