{
  "type": "Feature",
  "properties": {
    "date:inception_lower": "1980-01-01",
    "date:inception_upper": "1980-01-01",
    "iso:country": "GB",
    "wof:name": "CV3 5EH",
    "wof:placetype": "postalcode"
  },
  "geometry": {"coordinates":[-1.502542,52.385302],"type":"Point"}
}
