{
  "type": "Feature",
  "properties": {
    "iso:country":"GB",
    "wof:name":"CV3 5EH",
    "wof:placetype":"postalcode"
},
  "geometry": {"coordinates":[-1.5017839266538,52.38564191230989],"type":"Point"}
}