{
  "type": "Feature",
  "properties": {
    "iso:country":"GB",
    "wof:name":"SY7 8ET",
    "wof:placetype":"postalcode"
},
  "geometry": {"coordinates":[-2.89617414883651,52.43129102908809],"type":"Point"}
}