{
  "type": "Feature",
  "properties": {
    "iso:country": "GB",
    "wof:name": "SY7 8ET",
    "wof:placetype": "postalcode"
  },
  "geometry": {"coordinates":[-2.896174,52.431291],"type":"Point"}
}
