{
  "type": "Feature",
  "properties": {
    "iso:country":"GB",
    "wof:name":"BB1 6BB",
    "wof:placetype":"postalcode"
},
  "geometry": {"coordinates":[-2.47703834432544,53.75532217107033],"type":"Point"}
}