{
  "type": "Feature",
  "properties": {
    "iso:country": "GB",
    "wof:name": "BB1 6BB",
    "wof:placetype": "postalcode"
  },
  "geometry": {"coordinates":[-2.477038,53.755322],"type":"Point"}
}
