{
  "type": "Feature",
  "properties": {
    "date:inception_lower": "2019-02-01",
    "date:inception_upper": "2019-02-01",
    "iso:country": "GB",
    "wof:name": "TS9 5FU",
    "wof:placetype": "postalcode"
  },
  "geometry": {"coordinates":[-1.190033,54.478467],"type":"Point"}
}
