{
  "type": "Feature",
  "properties": {
    "iso:country": "GB",
    "wof:name": "HU12 9HS",
    "wof:placetype": "postalcode"
  },
  "geometry": {"coordinates":[-0.135188,53.730639],"type":"Point"}
}
