{
  "type": "Feature",
  "properties": {
    "date:inception_lower": "1980-01-01",
    "date:inception_upper": "1980-01-01",
    "iso:country": "GB",
    "wof:name": "OL3 5PJ",
    "wof:placetype": "postalcode"
  },
  "geometry": {"coordinates":[-1.997936,53.567232],"type":"Point"}
}
