{
  "type": "Feature",
  "properties": {
    "iso:country":"GB",
    "wof:name":"OL3 5PJ",
    "wof:placetype":"postalcode"
},
  "geometry": {"coordinates":[-1.9979838393969,53.56718842892373],"type":"Point"}
}