{
  "type": "Feature",
  "properties": {
    "date:inception_lower": "1980-01-01",
    "date:inception_upper": "1980-01-01",
    "iso:country": "GB",
    "wof:name": "IP22 1LP",
    "wof:placetype": "postalcode"
  },
  "geometry": {"coordinates":[1.00154,52.325914],"type":"Point"}
}
