{
  "type": "Feature",
  "properties": {
    "date:inception_lower": "2018-01-01",
    "date:inception_upper": "2018-01-01",
    "iso:country": "GB",
    "wof:name": "EX11 1FW",
    "wof:placetype": "postalcode"
  },
  "geometry": {"coordinates":[-3.32405,50.7366],"type":"Point"}
}
