{
  "type": "Feature",
  "properties": {
    "iso:country": "GB",
    "wof:name": "EX11 1FW",
    "wof:placetype": "postalcode"
  },
  "geometry": {"coordinates":[-3.323811,50.736648],"type":"Point"}
}
