{
  "type": "Feature",
  "properties": {
    "iso:country":"GB",
    "wof:name":"TS15 9JJ",
    "wof:placetype":"postalcode"
},
  "geometry": {"coordinates":[-1.31832008907665,54.50321410034205],"type":"Point"}
}