{
  "type": "Feature",
  "properties": {
    "iso:country":"GB",
    "wof:name":"SW9 0LH",
    "wof:placetype":"postalcode"
},
  "geometry": {"coordinates":[-0.1136183098768,51.47874641059254],"type":"Point"}
}