{
  "type": "Feature",
  "properties": {
    "iso:country":"GB",
    "wof:name":"CV32 6PJ",
    "wof:placetype":"postalcode"
},
  "geometry": {"coordinates":[-1.54698517714848,52.29593924276778],"type":"Point"}
}