{
  "type": "Feature",
  "properties": {
    "iso:country":"GB",
    "wof:name":"B64 7BJ",
    "wof:placetype":"postalcode"
},
  "geometry": {"coordinates":[-2.08156053633359,52.46593657183918],"type":"Point"}
}