{
  "type": "Feature",
  "properties": {
    "iso:country": "GB",
    "wof:name": "BB5 5TL",
    "wof:placetype": "postalcode"
  },
  "geometry": {"coordinates":[-2.388552,53.781042],"type":"Point"}
}
