{
  "type": "Feature",
  "properties": {
    "iso:country": "GB",
    "wof:name": "G1 1SS",
    "wof:placetype": "postalcode"
  },
  "geometry": {"coordinates":[-4.246617,55.858653],"type":"Point"}
}
