{
  "type": "Feature",
  "properties": {
    "iso:country":"GB",
    "wof:name":"G1 1SS",
    "wof:placetype":"postalcode"
},
  "geometry": {"coordinates":[-4.24661720877241,55.85865320090404],"type":"Point"}
}