{
  "type": "Feature",
  "properties": {
    "date:inception_lower":"1989-04-01",
    "date:inception_upper":"1989-04-30",
    "iso:country":"GB",
    "wof:name":"G1 1SS",
    "wof:placetype":"postalcode"
},
  "geometry": {"coordinates":[-4.246617,55.858653],"type":"Point"}
}