{
  "type": "Feature",
  "properties": {
    "iso:country":"GB",
    "wof:name":"CV12 9BP",
    "wof:placetype":"postalcode"
},
  "geometry": {"coordinates":[-1.46639525018782,52.48380356724127],"type":"Point"}
}