{
  "type": "Feature",
  "properties": {
    "iso:country":"GB",
    "wof:name":"TF7 4BW",
    "wof:placetype":"postalcode"
},
  "geometry": {"coordinates":[-2.43748271094912,52.63697026533656],"type":"Point"}
}