{
  "type": "Feature",
  "properties": {
    "iso:country":"GB",
    "wof:name":"NW11 6TY",
    "wof:placetype":"postalcode"
},
  "geometry": {"coordinates":[-0.18395054608231,51.57917824137982],"type":"Point"}
}