{
  "type": "Feature",
  "properties": {
    "iso:country": "GB",
    "wof:name": "DN10 4QG",
    "wof:placetype": "postalcode"
  },
  "geometry": {"coordinates":[-0.842704,53.395602],"type":"Point"}
}
