{
  "type": "Feature",
  "properties": {
    "date:inception_lower": "2012-03-01",
    "date:inception_upper": "2012-03-01",
    "iso:country": "GB",
    "wof:name": "DN10 4QG",
    "wof:placetype": "postalcode"
  },
  "geometry": {"coordinates":[-0.839918,53.395785],"type":"Point"}
}
