{
  "type": "Feature",
  "properties": {
    "iso:country":"GB",
    "wof:name":"DN10 4QG",
    "wof:placetype":"postalcode"
},
  "geometry": {"coordinates":[-0.84270358404643,53.39560227039704],"type":"Point"}
}