{
  "type": "Feature",
  "properties": {
    "iso:country": "GB",
    "wof:name": "NN3 6RW",
    "wof:placetype": "postalcode"
  },
  "geometry": {"coordinates":[-0.863274,52.272564],"type":"Point"}
}
