{
  "type": "Feature",
  "properties": {
    "iso:country":"GB",
    "wof:name":"NN3 6RW",
    "wof:placetype":"postalcode"
},
  "geometry": {"coordinates":[-0.86341097283478,52.27292751510672],"type":"Point"}
}