{
  "type": "Feature",
  "properties": {
    "iso:country":"GB",
    "wof:name":"WV10 7AG",
    "wof:placetype":"postalcode"
},
  "geometry": {"coordinates":[-2.08314034767485,52.64739545127262],"type":"Point"}
}