{
  "type": "Feature",
  "properties": {
    "iso:country":"GB",
    "wof:name":"RH6 0QX",
    "wof:placetype":"postalcode"
},
  "geometry": {"coordinates":[-0.16304911981146,51.15598998892342],"type":"Point"}
}