{
  "type": "Feature",
  "properties": {
    "date:inception_lower": "2022-09-01",
    "date:inception_upper": "2022-09-01",
    "iso:country": "GB",
    "wof:name": "CB10 2SH",
    "wof:placetype": "postalcode"
  },
  "geometry": {"coordinates":[0.244336,52.03462],"type":"Point"}
}
