{
  "type": "Feature",
  "properties": {
    "iso:country":"GB",
    "wof:name":"PO18 9JL",
    "wof:placetype":"postalcode"
},
  "geometry": {"coordinates":[-0.86223355501493,50.89577778291605],"type":"Point"}
}