{
  "type": "Feature",
  "properties": {
    "iso:country": "GB",
    "wof:name": "PO18 9JL",
    "wof:placetype": "postalcode"
  },
  "geometry": {"coordinates":[-0.862234,50.895778],"type":"Point"}
}
