{
  "type": "Feature",
  "properties": {
    "iso:country":"GB",
    "wof:name":"NE23 7JG",
    "wof:placetype":"postalcode"
},
  "geometry": {"coordinates":[-1.58684728493968,55.06777805598988],"type":"Point"}
}