{
  "type": "Feature",
  "properties": {
    "date:inception_lower": "2002-07-01",
    "date:inception_upper": "2002-07-01",
    "iso:country": "GB",
    "wof:name": "NE23 7JG",
    "wof:placetype": "postalcode"
  },
  "geometry": {"coordinates":[-1.586847,55.067778],"type":"Point"}
}
