{
  "type": "Feature",
  "properties": {
    "iso:country":"GB",
    "wof:name":"BR1 3HY",
    "wof:placetype":"postalcode"
},
  "geometry": {"coordinates":[0.02492224826577,51.41042848357043],"type":"Point"}
}