{
  "type": "Feature",
  "properties": {
    "iso:country": "GB",
    "wof:name": "NE71 6XG",
    "wof:placetype": "postalcode"
  },
  "geometry": {"coordinates":[-2.136946,55.565695],"type":"Point"}
}
