{
  "type": "Feature",
  "properties": {
    "iso:country":"GB",
    "wof:name":"PL7 1NY",
    "wof:placetype":"postalcode"
},
  "geometry": {"coordinates":[-4.04182396142935,50.38008420786886],"type":"Point"}
}