{
  "type": "Feature",
  "properties": {
    "iso:country":"GB",
    "wof:name":"SW6 4AU",
    "wof:placetype":"postalcode"
},
  "geometry": {"coordinates":[-0.19759188545001,51.47617352672498],"type":"Point"}
}