{
  "type": "Feature",
  "properties": {
    "iso:country": "GB",
    "wof:name": "SW6 4AU",
    "wof:placetype": "postalcode"
  },
  "geometry": {"coordinates":[-0.197592,51.476174],"type":"Point"}
}
