{
  "type": "Feature",
  "properties": {
    "iso:country":"GB",
    "wof:name":"IP14 1TE",
    "wof:placetype":"postalcode"
},
  "geometry": {"coordinates":[0.98731242003461,52.19725538298307],"type":"Point"}
}