{
  "type": "Feature",
  "properties": {
    "iso:country":"GB",
    "wof:name":"BA2 5PR",
    "wof:placetype":"postalcode"
},
  "geometry": {"coordinates":[-2.35760192402124,51.36226198260837],"type":"Point"}
}