{
  "type": "Feature",
  "properties": {
    "iso:country": "GB",
    "wof:name": "BA2 5PR",
    "wof:placetype": "postalcode"
  },
  "geometry": {"coordinates":[-2.357602,51.362262],"type":"Point"}
}
