{
  "type": "Feature",
  "properties": {
    "iso:country":"GB",
    "wof:name":"LA23 3DG",
    "wof:placetype":"postalcode"
},
  "geometry": {"coordinates":[-2.92127872950822,54.36434030170078],"type":"Point"}
}