{
  "type": "Feature",
  "properties": {
    "iso:country":"GB",
    "wof:name":"G76 8HS",
    "wof:placetype":"postalcode"
},
  "geometry": {"coordinates":[-4.26145544555249,55.78096278328447],"type":"Point"}
}