{
  "type": "Feature",
  "properties": {
    "date:inception_lower": "1991-09-01",
    "date:inception_upper": "1991-09-01",
    "iso:country": "GB",
    "wof:name": "WS15 4TR",
    "wof:placetype": "postalcode"
  },
  "geometry": {"coordinates":[-1.870592,52.740307],"type":"Point"}
}
