{
  "type": "Feature",
  "properties": {
    "iso:country": "GB",
    "wof:name": "SA8 3AU",
    "wof:placetype": "postalcode"
  },
  "geometry": {"coordinates":[-3.852306,51.712031],"type":"Point"}
}
