{
  "type": "Feature",
  "properties": {
    "iso:country": "GB",
    "wof:name": "BA16 0HS",
    "wof:placetype": "postalcode"
  },
  "geometry": {"coordinates":[-2.755005,51.127319],"type":"Point"}
}
