{
  "type": "Feature",
  "properties": {
    "iso:country":"GB",
    "wof:name":"BA16 0HS",
    "wof:placetype":"postalcode"
},
  "geometry": {"coordinates":[-2.75500473422772,51.12731882310907],"type":"Point"}
}