{
  "type": "Feature",
  "properties": {
    "date:inception_lower": "1996-06-01",
    "date:inception_upper": "1996-06-01",
    "iso:country": "GB",
    "wof:name": "BA16 0HS",
    "wof:placetype": "postalcode"
  },
  "geometry": {"coordinates":[-2.755005,51.127319],"type":"Point"}
}
