{
  "type": "Feature",
  "properties": {
    "iso:country":"GB",
    "wof:name":"ME8 6XQ",
    "wof:placetype":"postalcode"
},
  "geometry": {"coordinates":[0.58410586284149,51.37386939731847],"type":"Point"}
}