{
  "type": "Feature",
  "properties": {
    "date:inception_lower": "1999-06-01",
    "date:inception_upper": "1999-06-01",
    "iso:country": "GB",
    "wof:name": "KA27 8AB",
    "wof:placetype": "postalcode"
  },
  "geometry": {"coordinates":[-5.151765,55.576948],"type":"Point"}
}
