{
  "type": "Feature",
  "properties": {
    "iso:country": "GB",
    "wof:name": "SP6 3HZ",
    "wof:placetype": "postalcode"
  },
  "geometry": {"coordinates":[-1.827591,50.910005],"type":"Point"}
}
