{
  "type": "Feature",
  "properties": {
    "iso:country":"GB",
    "wof:name":"SP3 6AQ",
    "wof:placetype":"postalcode"
},
  "geometry": {"coordinates":[-2.17856279328584,51.0726739582604],"type":"Point"}
}