{
  "type": "Feature",
  "properties": {
    "iso:country": "GB",
    "wof:name": "SP3 6AQ",
    "wof:placetype": "postalcode"
  },
  "geometry": {"coordinates":[-2.178563,51.072674],"type":"Point"}
}
