{
  "type": "Feature",
  "properties": {
    "iso:country":"GB",
    "wof:name":"DN1 3DP",
    "wof:placetype":"postalcode"
},
  "geometry": {"coordinates":[-1.13512191962527,53.52077450766262],"type":"Point"}
}