{
  "type": "Feature",
  "properties": {
    "iso:country":"GB",
    "wof:name":"M24 4AZ",
    "wof:placetype":"postalcode"
},
  "geometry": {"coordinates":[-2.20324004761269,53.55151946630966],"type":"Point"}
}