{
  "type": "Feature",
  "properties": {
    "iso:country":"GB",
    "wof:name":"BN13 1NF",
    "wof:placetype":"postalcode"
},
  "geometry": {"coordinates":[-0.39664748066741,50.82831312067709],"type":"Point"}
}