{
  "type": "Feature",
  "properties": {
    "iso:country": "GB",
    "wof:name": "BN13 1NF",
    "wof:placetype": "postalcode"
  },
  "geometry": {"coordinates":[-0.396647,50.828313],"type":"Point"}
}
