{
  "type": "Feature",
  "properties": {
    "date:inception_lower": "2008-04-01",
    "date:inception_upper": "2008-04-01",
    "iso:country": "GB",
    "wof:name": "LE7 2DL",
    "wof:placetype": "postalcode"
  },
  "geometry": {"coordinates":[-1.062413,52.69399],"type":"Point"}
}
