{
  "type": "Feature",
  "properties": {
    "iso:country":"GB",
    "wof:name":"LE7 2DL",
    "wof:placetype":"postalcode"
},
  "geometry": {"coordinates":[-1.06241328010178,52.69398969519816],"type":"Point"}
}