{
  "type": "Feature",
  "properties": {
    "iso:country": "GB",
    "wof:name": "WF4 4SH",
    "wof:placetype": "postalcode"
  },
  "geometry": {"coordinates":[-1.580786,53.641651],"type":"Point"}
}
