{
  "type": "Feature",
  "properties": {
    "iso:country":"GB",
    "wof:name":"WF4 4SH",
    "wof:placetype":"postalcode"
},
  "geometry": {"coordinates":[-1.5807859070964,53.64165111119897],"type":"Point"}
}