{
  "type": "Feature",
  "properties": {
    "iso:country": "GB",
    "wof:name": "NE32 4DD",
    "wof:placetype": "postalcode"
  },
  "geometry": {"coordinates":[-1.48159,54.960933],"type":"Point"}
}
