{
  "type": "Feature",
  "properties": {
    "iso:country":"GB",
    "wof:name":"HP5 2HE",
    "wof:placetype":"postalcode"
},
  "geometry": {"coordinates":[-0.61286985132783,51.70892080981373],"type":"Point"}
}