{
  "type": "Feature",
  "properties": {
    "iso:country": "GB",
    "wof:name": "SA14 9LR",
    "wof:placetype": "postalcode"
  },
  "geometry": {"coordinates":[-4.102327,51.673371],"type":"Point"}
}
