{
  "type": "Feature",
  "properties": {
    "date:inception_lower": "2023-01-01",
    "date:inception_upper": "2023-01-01",
    "iso:country": "GB",
    "wof:name": "B78 3UZ",
    "wof:placetype": "postalcode"
  },
  "geometry": {"coordinates":[-1.701319,52.614272],"type":"Point"}
}
