{
  "type": "Feature",
  "properties": {
    "iso:country":"GB",
    "wof:name":"FY8 1DD",
    "wof:placetype":"postalcode"
},
  "geometry": {"coordinates":[-2.99293651245527,53.74054468044989],"type":"Point"}
}