{
  "type": "Feature",
  "properties": {
    "date:inception_lower":"1994-05-01",
    "date:inception_upper":"1994-05-31",
    "iso:country":"GB",
    "wof:name":"M40 8BA",
    "wof:placetype":"postalcode"
},
  "geometry": {"coordinates":[-2.210734,53.495482],"type":"Point"}
}