{
  "type": "Feature",
  "properties": {
    "iso:country":"GB",
    "wof:name":"M40 8BA",
    "wof:placetype":"postalcode"
},
  "geometry": {"coordinates":[-2.2107345292064,53.49548186008447],"type":"Point"}
}