{
  "type": "Feature",
  "properties": {
    "date:inception_lower": "1997-06-01",
    "date:inception_upper": "1997-06-01",
    "iso:country": "GB",
    "wof:name": "S21 1GR",
    "wof:placetype": "postalcode"
  },
  "geometry": {"coordinates":[-1.323948,53.318424],"type":"Point"}
}
