{
  "type": "Feature",
  "properties": {
    "iso:country":"GB",
    "wof:name":"S21 1GR",
    "wof:placetype":"postalcode"
},
  "geometry": {"coordinates":[-1.32394805674107,53.31842364483094],"type":"Point"}
}