{
  "type": "Feature",
  "properties": {
    "iso:country": "GB",
    "wof:name": "NN3 8QS",
    "wof:placetype": "postalcode"
  },
  "geometry": {"coordinates":[-0.820612,52.264767],"type":"Point"}
}
