{
  "type": "Feature",
  "properties": {
    "iso:country":"GB",
    "wof:name":"LS28 5DB",
    "wof:placetype":"postalcode"
},
  "geometry": {"coordinates":[-1.67170319308891,53.81146840210111],"type":"Point"}
}