{
  "type": "Feature",
  "properties": {
    "iso:country":"GB",
    "wof:name":"GU14 6RE",
    "wof:placetype":"postalcode"
},
  "geometry": {"coordinates":[-0.73928485672662,51.28573603215916],"type":"Point"}
}