{
  "type": "Feature",
  "properties": {
    "date:inception_lower":"1980-01-01",
    "date:inception_upper":"1980-01-31",
    "iso:country":"GB",
    "wof:name":"EX39 6HG",
    "wof:placetype":"postalcode"
},
  "geometry": {"coordinates":[-4.519038,50.933633],"type":"Point"}
}