{
  "type": "Feature",
  "properties": {
    "iso:country": "GB",
    "wof:name": "EX39 6HG",
    "wof:placetype": "postalcode"
  },
  "geometry": {"coordinates":[-4.519038,50.933633],"type":"Point"}
}
