{
  "type": "Feature",
  "properties": {
    "date:inception_lower":"1980-01-01",
    "date:inception_upper":"1980-01-31",
    "iso:country":"GB",
    "wof:name":"BN6 9EW",
    "wof:placetype":"postalcode"
},
  "geometry": {"coordinates":[-0.180581,50.924044],"type":"Point"}
}