{
  "type": "Feature",
  "properties": {
    "iso:country":"GB",
    "wof:name":"BN6 9EW",
    "wof:placetype":"postalcode"
},
  "geometry": {"coordinates":[-0.18058077525949,50.92404370014478],"type":"Point"}
}