{
  "type": "Feature",
  "properties": {
    "iso:country": "GB",
    "wof:name": "FK2 7TB",
    "wof:placetype": "postalcode"
  },
  "geometry": {"coordinates":[-3.796431,56.013976],"type":"Point"}
}
