{
  "type": "Feature",
  "properties": {
    "date:inception_lower": "1998-06-01",
    "date:inception_upper": "1998-06-01",
    "iso:country": "GB",
    "wof:name": "YO42 4EA",
    "wof:placetype": "postalcode"
  },
  "geometry": {"coordinates":[-0.820659,53.931159],"type":"Point"}
}
