{
  "type": "Feature",
  "properties": {
    "iso:country": "GB",
    "wof:name": "YO42 4EA",
    "wof:placetype": "postalcode"
  },
  "geometry": {"coordinates":[-0.820659,53.931159],"type":"Point"}
}
