{
  "type": "Feature",
  "properties": {
    "iso:country":"GB",
    "wof:name":"CO1 2RE",
    "wof:placetype":"postalcode"
},
  "geometry": {"coordinates":[0.91096266904221,51.89243452481005],"type":"Point"}
}