{
  "type": "Feature",
  "properties": {
    "date:inception_lower": "1980-01-01",
    "date:inception_upper": "1980-01-01",
    "iso:country": "GB",
    "wof:name": "CO1 2RE",
    "wof:placetype": "postalcode"
  },
  "geometry": {"coordinates":[0.910963,51.892435],"type":"Point"}
}
