{
  "type": "Feature",
  "properties": {
    "date:inception_lower": "1980-01-01",
    "date:inception_upper": "1980-01-01",
    "iso:country": "GB",
    "wof:name": "NG12 5DF",
    "wof:placetype": "postalcode"
  },
  "geometry": {"coordinates":[-1.081248,52.871488],"type":"Point"}
}
