{
  "type": "Feature",
  "properties": {
    "date:inception_lower": "1980-01-01",
    "date:inception_upper": "1980-01-01",
    "iso:country": "GB",
    "wof:name": "TF3 2HY",
    "wof:placetype": "postalcode"
  },
  "geometry": {"coordinates":[-2.453301,52.671926],"type":"Point"}
}
