{
  "type": "Feature",
  "properties": {
    "iso:country":"GB",
    "wof:name":"WA8 4QB",
    "wof:placetype":"postalcode"
},
  "geometry": {"coordinates":[-2.7757652681877,53.38357629545578],"type":"Point"}
}