{
  "type": "Feature",
  "properties": {
    "date:inception_lower":"1995-07-01",
    "date:inception_upper":"1995-07-31",
    "iso:country":"GB",
    "wof:name":"WA8 4QB",
    "wof:placetype":"postalcode"
},
  "geometry": {"coordinates":[-2.775765,53.383576],"type":"Point"}
}