{
  "type": "Feature",
  "properties": {
    "date:inception_lower":"1980-01-01",
    "date:inception_upper":"1980-01-31",
    "iso:country":"GB",
    "wof:name":"S75 2DN",
    "wof:placetype":"postalcode"
},
  "geometry": {"coordinates":[-1.502297,53.555638],"type":"Point"}
}