{
  "type": "Feature",
  "properties": {
    "iso:country": "GB",
    "wof:name": "TQ5 0SJ",
    "wof:placetype": "postalcode"
  },
  "geometry": {"coordinates":[-3.528886,50.384516],"type":"Point"}
}
