{
  "type": "Feature",
  "properties": {
    "date:inception_lower":"1990-02-01",
    "date:inception_upper":"1990-02-28",
    "iso:country":"GB",
    "wof:name":"TQ5 0SJ",
    "wof:placetype":"postalcode"
},
  "geometry": {"coordinates":[-3.528886,50.384516],"type":"Point"}
}