{
  "type": "Feature",
  "properties": {
    "iso:country":"GB",
    "wof:name":"M19 3BE",
    "wof:placetype":"postalcode"
},
  "geometry": {"coordinates":[-2.19147082264153,53.44874734183207],"type":"Point"}
}