{
  "type": "Feature",
  "properties": {
    "iso:country":"GB",
    "wof:name":"OX2 9FW",
    "wof:placetype":"postalcode"
},
  "geometry": {"coordinates":[-1.31084839012015,51.74294135217269],"type":"Point"}
}