{
  "type": "Feature",
  "properties": {
    "iso:country": "GB",
    "wof:name": "OX2 9FW",
    "wof:placetype": "postalcode"
  },
  "geometry": {"coordinates":[-1.310917,51.742965],"type":"Point"}
}
