{
  "type": "Feature",
  "properties": {
    "date:inception_lower":"2008-11-01",
    "date:inception_upper":"2008-11-30",
    "iso:country":"GB",
    "wof:name":"OX2 9FW",
    "wof:placetype":"postalcode"
},
  "geometry": {"coordinates":[-1.310917,51.742965],"type":"Point"}
}