{
  "type": "Feature",
  "properties": {
    "iso:country":"GB",
    "wof:name":"CA7 2PH",
    "wof:placetype":"postalcode"
},
  "geometry": {"coordinates":[-3.37776955165926,54.75725553057704],"type":"Point"}
}