{
  "type": "Feature",
  "properties": {
    "iso:country": "GB",
    "wof:name": "CA7 2PH",
    "wof:placetype": "postalcode"
  },
  "geometry": {"coordinates":[-3.37777,54.757256],"type":"Point"}
}
