{
  "type": "Feature",
  "properties": {
    "iso:country":"GB",
    "wof:name":"OX4 2EU",
    "wof:placetype":"postalcode"
},
  "geometry": {"coordinates":[-1.21074762139823,51.7365665660305],"type":"Point"}
}