{
  "type": "Feature",
  "properties": {
    "iso:country": "GB",
    "wof:name": "OX4 2EU",
    "wof:placetype": "postalcode"
  },
  "geometry": {"coordinates":[-1.210748,51.736567],"type":"Point"}
}
