{
  "type": "Feature",
  "properties": {
    "date:inception_lower":"1980-01-01",
    "date:inception_upper":"1980-01-31",
    "iso:country":"GB",
    "wof:name":"BS9 2NT",
    "wof:placetype":"postalcode"
},
  "geometry": {"coordinates":[-2.647306,51.492395],"type":"Point"}
}