{
  "type": "Feature",
  "properties": {
    "iso:country":"GB",
    "wof:name":"BS9 2NT",
    "wof:placetype":"postalcode"
},
  "geometry": {"coordinates":[-2.64727313781006,51.49235197350887],"type":"Point"}
}