{
  "type": "Feature",
  "properties": {
    "iso:country": "GB",
    "wof:name": "SP1 3TE",
    "wof:placetype": "postalcode"
  },
  "geometry": {"coordinates":[-1.796498,51.074463],"type":"Point"}
}
