{
  "type": "Feature",
  "properties": {
    "iso:country":"GB",
    "wof:name":"SP1 3TE",
    "wof:placetype":"postalcode"
},
  "geometry": {"coordinates":[-1.7968050983241,51.07491860933522],"type":"Point"}
}