{
  "type": "Feature",
  "properties": {
    "iso:country": "GB",
    "wof:name": "CF15 7TW",
    "wof:placetype": "postalcode"
  },
  "geometry": {"coordinates":[-3.272797,51.563033],"type":"Point"}
}
