{
  "type": "Feature",
  "properties": {
    "date:inception_lower":"1994-05-01",
    "date:inception_upper":"1994-05-31",
    "iso:country":"GB",
    "wof:name":"M27 4HU",
    "wof:placetype":"postalcode"
},
  "geometry": {"coordinates":[-2.315351,53.508455],"type":"Point"}
}