{
  "type": "Feature",
  "properties": {
    "iso:country":"GB",
    "wof:name":"M27 4HU",
    "wof:placetype":"postalcode"
},
  "geometry": {"coordinates":[-2.3153509510334,53.50845544009253],"type":"Point"}
}