{
  "type": "Feature",
  "properties": {
    "date:inception_lower": "1998-06-01",
    "date:inception_upper": "1998-06-01",
    "iso:country": "GB",
    "wof:name": "DL16 6LB",
    "wof:placetype": "postalcode"
  },
  "geometry": {"coordinates":[-1.599647,54.71471],"type":"Point"}
}
