{
  "type": "Feature",
  "properties": {
    "iso:country":"GB",
    "wof:name":"DL16 6LB",
    "wof:placetype":"postalcode"
},
  "geometry": {"coordinates":[-1.59964739571783,54.71470956918177],"type":"Point"}
}