{
  "type": "Feature",
  "properties": {
    "iso:country":"GB",
    "wof:name":"TN33 0QS",
    "wof:placetype":"postalcode"
},
  "geometry": {"coordinates":[0.52858886049962,50.94854786016136],"type":"Point"}
}