{
  "type": "Feature",
  "properties": {
    "iso:country":"GB",
    "wof:name":"GU35 8TB",
    "wof:placetype":"postalcode"
},
  "geometry": {"coordinates":[-0.82180590862978,51.13552441343009],"type":"Point"}
}