{
  "type": "Feature",
  "properties": {
    "date:inception_lower": "1980-01-01",
    "date:inception_upper": "1980-01-01",
    "iso:country": "GB",
    "wof:name": "GU35 8TB",
    "wof:placetype": "postalcode"
  },
  "geometry": {"coordinates":[-0.821806,51.135524],"type":"Point"}
}
