{
  "type": "Feature",
  "properties": {
    "iso:country":"GB",
    "wof:name":"NE40 3AF",
    "wof:placetype":"postalcode"
},
  "geometry": {"coordinates":[-1.77553827737452,54.97185923761756],"type":"Point"}
}