{
  "type": "Feature",
  "properties": {
    "iso:country": "GB",
    "wof:name": "NE40 3AF",
    "wof:placetype": "postalcode"
  },
  "geometry": {"coordinates":[-1.775551,54.971866],"type":"Point"}
}
