{
  "type": "Feature",
  "properties": {
    "date:inception_lower":"1998-12-01",
    "date:inception_upper":"1998-12-31",
    "iso:country":"GB",
    "wof:name":"LE12 8SW",
    "wof:placetype":"postalcode"
},
  "geometry": {"coordinates":[-1.14011,52.750415],"type":"Point"}
}