{
  "type": "Feature",
  "properties": {
    "date:inception_lower":"1980-01-01",
    "date:inception_upper":"1980-01-31",
    "iso:country":"GB",
    "wof:name":"BA2 7EF",
    "wof:placetype":"postalcode"
},
  "geometry": {"coordinates":[-2.37485,51.340889],"type":"Point"}
}