{
  "type": "Feature",
  "properties": {
    "iso:country": "GB",
    "wof:name": "BA2 7EF",
    "wof:placetype": "postalcode"
  },
  "geometry": {"coordinates":[-2.37485,51.340889],"type":"Point"}
}
