{
  "type": "Feature",
  "properties": {
    "iso:country":"GB",
    "wof:name":"SA14 7PF",
    "wof:placetype":"postalcode"
},
  "geometry": {"coordinates":[-4.06117275461142,51.79796296206629],"type":"Point"}
}