{
  "type": "Feature",
  "properties": {
    "iso:country": "GB",
    "wof:name": "HA5 4QX",
    "wof:placetype": "postalcode"
  },
  "geometry": {"coordinates":[-0.3783,51.60553],"type":"Point"}
}
