{
  "type": "Feature",
  "properties": {
    "iso:country":"GB",
    "wof:name":"RG27 0ER",
    "wof:placetype":"postalcode"
},
  "geometry": {"coordinates":[-1.02555012249579,51.31334881874378],"type":"Point"}
}