{
  "type": "Feature",
  "properties": {
    "date:inception_lower":"2002-07-01",
    "date:inception_upper":"2002-07-31",
    "iso:country":"GB",
    "wof:name":"RG27 0ER",
    "wof:placetype":"postalcode"
},
  "geometry": {"coordinates":[-1.02555,51.313349],"type":"Point"}
}