{
  "type": "Feature",
  "properties": {
    "iso:country":"GB",
    "wof:name":"IP7 7AD",
    "wof:placetype":"postalcode"
},
  "geometry": {"coordinates":[0.8629153795222,52.08795274490002],"type":"Point"}
}