{
  "type": "Feature",
  "properties": {
    "iso:country":"GB",
    "wof:name":"NE37 2HW",
    "wof:placetype":"postalcode"
},
  "geometry": {"coordinates":[-1.5285598754698,54.91748680688367],"type":"Point"}
}