{
  "type": "Feature",
  "properties": {
    "date:inception_lower": "1980-01-01",
    "date:inception_upper": "1980-01-01",
    "iso:country": "GB",
    "wof:name": "HU3 5PS",
    "wof:placetype": "postalcode"
  },
  "geometry": {"coordinates":[-0.380502,53.741049],"type":"Point"}
}
