{
  "type": "Feature",
  "properties": {
    "iso:country":"GB",
    "wof:name":"HU3 5PS",
    "wof:placetype":"postalcode"
},
  "geometry": {"coordinates":[-0.38041309825886,53.740811817989],"type":"Point"}
}