{
  "type": "Feature",
  "properties": {
    "date:inception_lower": "2023-09-01",
    "date:inception_upper": "2023-09-01",
    "iso:country": "GB",
    "wof:name": "CV37 9ZS",
    "wof:placetype": "postalcode"
  },
  "geometry": {"coordinates":[-1.738596,52.200722],"type":"Point"}
}
