{
  "type": "Feature",
  "properties": {
    "date:inception_lower": "1980-01-01",
    "date:inception_upper": "1980-01-01",
    "iso:country": "GB",
    "wof:name": "LL18 2HG",
    "wof:placetype": "postalcode"
  },
  "geometry": {"coordinates":[-3.484061,53.312353],"type":"Point"}
}
