{
  "type": "Feature",
  "properties": {
    "iso:country":"GB",
    "wof:name":"LL18 2HG",
    "wof:placetype":"postalcode"
},
  "geometry": {"coordinates":[-3.48406061954275,53.31235274178469],"type":"Point"}
}