{
  "type": "Feature",
  "properties": {
    "iso:country": "GB",
    "wof:name": "NR28 9TE",
    "wof:placetype": "postalcode"
  },
  "geometry": {"coordinates":[1.440786,52.864135],"type":"Point"}
}
