{
  "type": "Feature",
  "properties": {
    "iso:country":"GB",
    "wof:name":"L25 5NU",
    "wof:placetype":"postalcode"
},
  "geometry": {"coordinates":[-2.86194178424037,53.3798209439107],"type":"Point"}
}