{
  "type": "Feature",
  "properties": {
    "date:inception_lower": "1980-01-01",
    "date:inception_upper": "1980-01-01",
    "iso:country": "GB",
    "wof:name": "G2 3EH",
    "wof:placetype": "postalcode"
  },
  "geometry": {"coordinates":[-4.262337,55.865447],"type":"Point"}
}
