{
  "type": "Feature",
  "properties": {
    "iso:country":"GB",
    "wof:name":"G2 3EH",
    "wof:placetype":"postalcode"
},
  "geometry": {"coordinates":[-4.26233682842284,55.86544721929873],"type":"Point"}
}