{
  "type": "Feature",
  "properties": {
    "iso:country": "GB",
    "wof:name": "HP18 0TB",
    "wof:placetype": "postalcode"
  },
  "geometry": {"coordinates":[-0.850288,51.842155],"type":"Point"}
}
