{
  "type": "Feature",
  "properties": {
    "date:inception_lower": "2017-08-01",
    "date:inception_upper": "2017-08-01",
    "iso:country": "GB",
    "wof:name": "RH12 0BB",
    "wof:placetype": "postalcode"
  },
  "geometry": {"coordinates":[-0.238463,51.098305],"type":"Point"}
}
