{
  "type": "Feature",
  "properties": {
    "iso:country":"GB",
    "wof:name":"BL3 2DN",
    "wof:placetype":"postalcode"
},
  "geometry": {"coordinates":[-2.42691773588943,53.56123044705758],"type":"Point"}
}