{
  "type": "Feature",
  "properties": {
    "iso:country": "GB",
    "wof:name": "BL3 2DN",
    "wof:placetype": "postalcode"
  },
  "geometry": {"coordinates":[-2.426918,53.56123],"type":"Point"}
}
