{
  "type": "Feature",
  "properties": {
    "date:inception_lower": "1980-01-01",
    "date:inception_upper": "1980-01-01",
    "iso:country": "GB",
    "wof:name": "BN14 7RT",
    "wof:placetype": "postalcode"
  },
  "geometry": {"coordinates":[-0.381494,50.826341],"type":"Point"}
}
