{
  "type": "Feature",
  "properties": {
    "iso:country":"GB",
    "wof:name":"BN14 7RT",
    "wof:placetype":"postalcode"
},
  "geometry": {"coordinates":[-0.3814937386787,50.82634123041561],"type":"Point"}
}