{
  "type": "Feature",
  "properties": {
    "iso:country":"GB",
    "wof:name":"DE13 0FH",
    "wof:placetype":"postalcode"
},
  "geometry": {"coordinates":[-1.63745801239221,52.82934217476099],"type":"Point"}
}