{
  "type": "Feature",
  "properties": {
    "iso:country":"GB",
    "wof:name":"CW10 9NE",
    "wof:placetype":"postalcode"
},
  "geometry": {"coordinates":[-2.41133030228307,53.23160015616861],"type":"Point"}
}