{
  "type": "Feature",
  "properties": {
    "iso:country":"GB",
    "wof:name":"GL1 3PG",
    "wof:placetype":"postalcode"
},
  "geometry": {"coordinates":[-2.23295442639385,51.86835515417017],"type":"Point"}
}