{
  "type": "Feature",
  "properties": {
    "iso:country": "GB",
    "wof:name": "GL1 3PG",
    "wof:placetype": "postalcode"
  },
  "geometry": {"coordinates":[-2.232954,51.868355],"type":"Point"}
}
