{
  "type": "Feature",
  "properties": {
    "iso:country":"GB",
    "wof:name":"DG13 0NX",
    "wof:placetype":"postalcode"
},
  "geometry": {"coordinates":[-3.02200362800585,55.16384718394398],"type":"Point"}
}