{
  "type": "Feature",
  "properties": {
    "iso:country":"GB",
    "wof:name":"NR8 5FJ",
    "wof:placetype":"postalcode"
},
  "geometry": {"coordinates":[1.18675131300728,52.66639179956079],"type":"Point"}
}