{
  "type": "Feature",
  "properties": {
    "iso:country": "GB",
    "wof:name": "NR8 5FJ",
    "wof:placetype": "postalcode"
  },
  "geometry": {"coordinates":[1.186751,52.666392],"type":"Point"}
}
