{
  "type": "Feature",
  "properties": {
    "date:inception_lower": "2008-07-01",
    "date:inception_upper": "2008-07-01",
    "iso:country": "GB",
    "wof:name": "NR8 5FJ",
    "wof:placetype": "postalcode"
  },
  "geometry": {"coordinates":[1.186751,52.666392],"type":"Point"}
}
