{
  "type": "Feature",
  "properties": {
    "iso:country":"GB",
    "wof:name":"GU17 0JH",
    "wof:placetype":"postalcode"
},
  "geometry": {"coordinates":[-0.78470811802775,51.33427053076225],"type":"Point"}
}