{
  "type": "Feature",
  "properties": {
    "iso:country": "GB",
    "wof:name": "WV9 5PB",
    "wof:placetype": "postalcode"
  },
  "geometry": {"coordinates":[-2.1474,52.619698],"type":"Point"}
}
