{
  "type": "Feature",
  "properties": {
    "iso:country": "GB",
    "wof:name": "ME2 3HH",
    "wof:placetype": "postalcode"
  },
  "geometry": {"coordinates":[0.489919,51.399931],"type":"Point"}
}
