{
  "type": "Feature",
  "properties": {
    "iso:country":"GB",
    "wof:name":"ME2 3HH",
    "wof:placetype":"postalcode"
},
  "geometry": {"coordinates":[0.48991941589359,51.39993134569072],"type":"Point"}
}