{
  "type": "Feature",
  "properties": {
    "iso:country":"GB",
    "wof:name":"CM13 1EA",
    "wof:placetype":"postalcode"
},
  "geometry": {"coordinates":[0.34114266928019,51.63603777237139],"type":"Point"}
}