{
  "type": "Feature",
  "properties": {
    "iso:country": "GB",
    "wof:name": "CO2 8AA",
    "wof:placetype": "postalcode"
  },
  "geometry": {"coordinates":[0.919531,51.876852],"type":"Point"}
}
