{
  "type": "Feature",
  "properties": {
    "iso:country":"GB",
    "wof:name":"EX10 8QJ",
    "wof:placetype":"postalcode"
},
  "geometry": {"coordinates":[-3.2371442322571,50.68247308737808],"type":"Point"}
}