{
  "type": "Feature",
  "properties": {
    "date:inception_lower": "2002-07-01",
    "date:inception_upper": "2002-07-01",
    "iso:country": "GB",
    "wof:name": "SK7 6LZ",
    "wof:placetype": "postalcode"
  },
  "geometry": {"coordinates":[-2.102531,53.368302],"type":"Point"}
}
