{
  "type": "Feature",
  "properties": {
    "iso:country":"GB",
    "wof:name":"SK7 6LZ",
    "wof:placetype":"postalcode"
},
  "geometry": {"coordinates":[-2.10253086871175,53.36830159921618],"type":"Point"}
}