{
  "type": "Feature",
  "properties": {
    "iso:country":"GB",
    "wof:name":"OX2 6RE",
    "wof:placetype":"postalcode"
},
  "geometry": {"coordinates":[-1.27038783684785,51.76322424520539],"type":"Point"}
}