{
  "type": "Feature",
  "properties": {
    "iso:country":"GB",
    "wof:name":"OX33 1DD",
    "wof:placetype":"postalcode"
},
  "geometry": {"coordinates":[-1.12341935107479,51.81086325169104],"type":"Point"}
}