{
  "type": "Feature",
  "properties": {
    "iso:country": "GB",
    "wof:name": "OX33 1DD",
    "wof:placetype": "postalcode"
  },
  "geometry": {"coordinates":[-1.123419,51.810863],"type":"Point"}
}
