{
  "type": "Feature",
  "properties": {
    "iso:country":"GB",
    "wof:name":"DE11 9BZ",
    "wof:placetype":"postalcode"
},
  "geometry": {"coordinates":[-1.56825126632404,52.77073275001391],"type":"Point"}
}