{
  "type": "Feature",
  "properties": {
    "date:inception_lower": "1998-12-01",
    "date:inception_upper": "1998-12-01",
    "iso:country": "GB",
    "wof:name": "DE11 9BZ",
    "wof:placetype": "postalcode"
  },
  "geometry": {"coordinates":[-1.568193,52.770652],"type":"Point"}
}
