{
  "type": "Feature",
  "properties": {
    "date:inception_lower":"1995-01-01",
    "date:inception_upper":"1995-01-31",
    "iso:country":"GB",
    "wof:name":"BB3 2NL",
    "wof:placetype":"postalcode"
},
  "geometry": {"coordinates":[-2.469799,53.691058],"type":"Point"}
}