{
  "type": "Feature",
  "properties": {
    "iso:country":"GB",
    "wof:name":"BB3 2NL",
    "wof:placetype":"postalcode"
},
  "geometry": {"coordinates":[-2.46979951833375,53.69105847816902],"type":"Point"}
}