{
  "type": "Feature",
  "properties": {
    "iso:country":"GB",
    "wof:name":"N19 4PJ",
    "wof:placetype":"postalcode"
},
  "geometry": {"coordinates":[-0.12503074189158,51.55895386231224],"type":"Point"}
}