{
  "type": "Feature",
  "properties": {
    "iso:country":"GB",
    "wof:name":"DN40 1PL",
    "wof:placetype":"postalcode"
},
  "geometry": {"coordinates":[-0.22069423921385,53.60909903512935],"type":"Point"}
}