{
  "type": "Feature",
  "properties": {
    "date:inception_lower": "1980-01-01",
    "date:inception_upper": "1980-01-01",
    "iso:country": "GB",
    "wof:name": "DN40 1PL",
    "wof:placetype": "postalcode"
  },
  "geometry": {"coordinates":[-0.220694,53.609099],"type":"Point"}
}
