{
  "type": "Feature",
  "properties": {
    "iso:country":"GB",
    "wof:name":"PE25 2EL",
    "wof:placetype":"postalcode"
},
  "geometry": {"coordinates":[0.32429919543847,53.14402168595356],"type":"Point"}
}