{
  "type": "Feature",
  "properties": {
    "iso:country":"GB",
    "wof:name":"HG3 5QP",
    "wof:placetype":"postalcode"
},
  "geometry": {"coordinates":[-1.73866373772979,54.07703248418257],"type":"Point"}
}