{
  "type": "Feature",
  "properties": {
    "date:inception_lower": "1980-01-01",
    "date:inception_upper": "1980-01-01",
    "iso:country": "GB",
    "wof:name": "IV30 1EP",
    "wof:placetype": "postalcode"
  },
  "geometry": {"coordinates":[-3.308882,57.648897],"type":"Point"}
}
