{
  "type": "Feature",
  "properties": {
    "date:inception_lower": "1993-01-01",
    "date:inception_upper": "1993-01-01",
    "iso:country": "GB",
    "wof:name": "LN1 2AX",
    "wof:placetype": "postalcode"
  },
  "geometry": {"coordinates":[-0.666099,53.313327],"type":"Point"}
}
