{
  "type": "Feature",
  "properties": {
    "iso:country":"GB",
    "wof:name":"LN1 2AX",
    "wof:placetype":"postalcode"
},
  "geometry": {"coordinates":[-0.66604964424555,53.31341298514206],"type":"Point"}
}