{
  "type": "Feature",
  "properties": {
    "iso:country":"GB",
    "wof:name":"CR0 8LQ",
    "wof:placetype":"postalcode"
},
  "geometry": {"coordinates":[-0.02599574465008,51.36671092451985],"type":"Point"}
}