{
  "type": "Feature",
  "properties": {
    "iso:country": "GB",
    "wof:name": "CR0 8LQ",
    "wof:placetype": "postalcode"
  },
  "geometry": {"coordinates":[-0.025996,51.366711],"type":"Point"}
}
