{
  "type": "Feature",
  "properties": {
    "iso:country":"GB",
    "wof:name":"G42 9AJ",
    "wof:placetype":"postalcode"
},
  "geometry": {"coordinates":[-4.25697121083507,55.82750178031102],"type":"Point"}
}