{
  "type": "Feature",
  "properties": {
    "iso:country":"GB",
    "wof:name":"SL4 2ET",
    "wof:placetype":"postalcode"
},
  "geometry": {"coordinates":[-0.67387875782607,51.43553416692734],"type":"Point"}
}