{
  "type": "Feature",
  "properties": {
    "iso:country":"GB",
    "wof:name":"LE12 8QQ",
    "wof:placetype":"postalcode"
},
  "geometry": {"coordinates":[-1.14822189108555,52.75611865030302],"type":"Point"}
}