{
  "type": "Feature",
  "properties": {
    "date:inception_lower": "1980-01-01",
    "date:inception_upper": "1980-01-01",
    "iso:country": "GB",
    "wof:name": "LE12 8QQ",
    "wof:placetype": "postalcode"
  },
  "geometry": {"coordinates":[-1.148222,52.756119],"type":"Point"}
}
