{
  "type": "Feature",
  "properties": {
    "iso:country":"GB",
    "wof:name":"GL8 8XX",
    "wof:placetype":"postalcode"
},
  "geometry": {"coordinates":[-2.24739470557537,51.66515438787471],"type":"Point"}
}