{
  "type": "Feature",
  "properties": {
    "date:inception_lower":"1980-01-01",
    "date:inception_upper":"1980-01-31",
    "iso:country":"GB",
    "wof:name":"GL8 8XX",
    "wof:placetype":"postalcode"
},
  "geometry": {"coordinates":[-2.247395,51.665154],"type":"Point"}
}