{
  "type": "Feature",
  "properties": {
    "date:inception_lower": "1991-09-01",
    "date:inception_upper": "1991-09-01",
    "iso:country": "GB",
    "wof:name": "OL5 9SB",
    "wof:placetype": "postalcode"
  },
  "geometry": {"coordinates":[-2.034238,53.513793],"type":"Point"}
}
