{
  "type": "Feature",
  "properties": {
    "iso:country": "GB",
    "wof:name": "OL5 9SB",
    "wof:placetype": "postalcode"
  },
  "geometry": {"coordinates":[-2.034238,53.513793],"type":"Point"}
}
