{
  "type": "Feature",
  "properties": {
    "iso:country":"GB",
    "wof:name":"AB42 1LG",
    "wof:placetype":"postalcode"
},
  "geometry": {"coordinates":[-1.77865963200514,57.50720574869004],"type":"Point"}
}