{
  "type": "Feature",
  "properties": {
    "date:inception_lower": "2018-10-01",
    "date:inception_upper": "2018-10-01",
    "iso:country": "GB",
    "wof:name": "SL0 9DG",
    "wof:placetype": "postalcode"
  },
  "geometry": {"coordinates":[-0.504699,51.507767],"type":"Point"}
}
