{
  "type": "Feature",
  "properties": {
    "iso:country": "GB",
    "wof:name": "SL0 9DG",
    "wof:placetype": "postalcode"
  },
  "geometry": {"coordinates":[-0.504699,51.507767],"type":"Point"}
}
