{
  "type": "Feature",
  "properties": {
    "iso:country":"GB",
    "wof:name":"TW8 8QY",
    "wof:placetype":"postalcode"
},
  "geometry": {"coordinates":[-0.30557441330922,51.48094893252805],"type":"Point"}
}