{
  "type": "Feature",
  "properties": {
    "iso:country": "GB",
    "wof:name": "CH62 3NX",
    "wof:placetype": "postalcode"
  },
  "geometry": {"coordinates":[-2.972675,53.332272],"type":"Point"}
}
