{
  "type": "Feature",
  "properties": {
    "iso:country":"GB",
    "wof:name":"CH62 3NX",
    "wof:placetype":"postalcode"
},
  "geometry": {"coordinates":[-2.97267513285576,53.33227198725147],"type":"Point"}
}