{
  "type": "Feature",
  "properties": {
    "iso:country":"GB",
    "wof:name":"B31 3TT",
    "wof:placetype":"postalcode"
},
  "geometry": {"coordinates":[-1.96528101674376,52.40449503916447],"type":"Point"}
}