{
  "type": "Feature",
  "properties": {
    "iso:country":"GB",
    "wof:name":"BS4 4AL",
    "wof:placetype":"postalcode"
},
  "geometry": {"coordinates":[-2.54364795837913,51.45332426962663],"type":"Point"}
}