{
  "type": "Feature",
  "properties": {
    "iso:country":"GB",
    "wof:name":"ML11 0PY",
    "wof:placetype":"postalcode"
},
  "geometry": {"coordinates":[-3.84568399972635,55.55545664050692],"type":"Point"}
}