{
  "type": "Feature",
  "properties": {
    "date:inception_lower": "2005-05-01",
    "date:inception_upper": "2005-05-01",
    "iso:country": "GB",
    "wof:name": "RG40 1BD",
    "wof:placetype": "postalcode"
  },
  "geometry": {"coordinates":[-0.83754,51.411761],"type":"Point"}
}
