{
  "type": "Feature",
  "properties": {
    "iso:country":"GB",
    "wof:name":"BD19 4JT",
    "wof:placetype":"postalcode"
},
  "geometry": {"coordinates":[-1.68780622486425,53.7330098707524],"type":"Point"}
}