{
  "type": "Feature",
  "properties": {
    "iso:country":"GB",
    "wof:name":"RH16 4HF",
    "wof:placetype":"postalcode"
},
  "geometry": {"coordinates":[-0.0941150602302,50.99214663295179],"type":"Point"}
}