{
  "type": "Feature",
  "properties": {
    "iso:country":"GB",
    "wof:name":"WA1 3HG",
    "wof:placetype":"postalcode"
},
  "geometry": {"coordinates":[-2.55573698650352,53.40189122332593],"type":"Point"}
}