{
  "type": "Feature",
  "properties": {
    "date:inception_lower":"1980-01-01",
    "date:inception_upper":"1980-01-31",
    "iso:country":"GB",
    "wof:name":"EX17 4QQ",
    "wof:placetype":"postalcode"
},
  "geometry": {"coordinates":[-3.740523,50.881873],"type":"Point"}
}