{
  "type": "Feature",
  "properties": {
    "iso:country":"GB",
    "wof:name":"EX17 4QQ",
    "wof:placetype":"postalcode"
},
  "geometry": {"coordinates":[-3.74052255345849,50.88187321886713],"type":"Point"}
}