{
  "type": "Feature",
  "properties": {
    "iso:country":"GB",
    "wof:name":"PH13 9ED",
    "wof:placetype":"postalcode"
},
  "geometry": {"coordinates":[-3.27349095896299,56.54529701727733],"type":"Point"}
}