{
  "type": "Feature",
  "properties": {
    "date:inception_lower": "1980-01-01",
    "date:inception_upper": "1980-01-01",
    "iso:country": "GB",
    "wof:name": "PH13 9ED",
    "wof:placetype": "postalcode"
  },
  "geometry": {"coordinates":[-3.273491,56.545297],"type":"Point"}
}
