{
  "type": "Feature",
  "properties": {
    "iso:country":"GB",
    "wof:name":"NE29 7UN",
    "wof:placetype":"postalcode"
},
  "geometry": {"coordinates":[-1.48877348547582,55.01512424605119],"type":"Point"}
}