{
  "type": "Feature",
  "properties": {
    "date:inception_lower":"1980-01-01",
    "date:inception_upper":"1980-01-31",
    "iso:country":"GB",
    "wof:name":"NE29 7UN",
    "wof:placetype":"postalcode"
},
  "geometry": {"coordinates":[-1.488773,55.015124],"type":"Point"}
}