{
  "type": "Feature",
  "properties": {
    "iso:country":"GB",
    "wof:name":"CR0 7TT",
    "wof:placetype":"postalcode"
},
  "geometry": {"coordinates":[-0.0532383087322,51.3943790055143],"type":"Point"}
}