{
  "type": "Feature",
  "properties": {
    "date:inception_lower": "1996-12-01",
    "date:inception_upper": "1996-12-01",
    "iso:country": "GB",
    "wof:name": "CR0 7TT",
    "wof:placetype": "postalcode"
  },
  "geometry": {"coordinates":[-0.053238,51.394379],"type":"Point"}
}
