{
  "type": "Feature",
  "properties": {
    "iso:country":"GB",
    "wof:name":"W3 8LZ",
    "wof:placetype":"postalcode"
},
  "geometry": {"coordinates":[-0.28153460914355,51.49790045398115],"type":"Point"}
}