{
  "type": "Feature",
  "properties": {
    "iso:country":"GB",
    "wof:name":"B65 9JH",
    "wof:placetype":"postalcode"
},
  "geometry": {"coordinates":[-2.03304728170838,52.48796760861832],"type":"Point"}
}