{
  "type": "Feature",
  "properties": {
    "date:inception_lower": "2018-04-01",
    "date:inception_upper": "2018-04-01",
    "iso:country": "GB",
    "wof:name": "NP4 0DB",
    "wof:placetype": "postalcode"
  },
  "geometry": {"coordinates":[-2.982686,51.734118],"type":"Point"}
}
