{
  "type": "Feature",
  "properties": {
    "iso:country": "GB",
    "wof:name": "NP4 0DB",
    "wof:placetype": "postalcode"
  },
  "geometry": {"coordinates":[-2.982627,51.734029],"type":"Point"}
}
