{
  "type": "Feature",
  "properties": {
    "iso:country": "GB",
    "wof:name": "PA2 6QP",
    "wof:placetype": "postalcode"
  },
  "geometry": {"coordinates":[-4.415371,55.830145],"type":"Point"}
}
