{
  "type": "Feature",
  "properties": {
    "iso:country":"GB",
    "wof:name":"CH49 1RW",
    "wof:placetype":"postalcode"
},
  "geometry": {"coordinates":[-3.12055876730873,53.37406829314368],"type":"Point"}
}