{
  "type": "Feature",
  "properties": {
    "date:inception_lower":"1980-01-01",
    "date:inception_upper":"1980-01-31",
    "iso:country":"GB",
    "wof:name":"CA16 6JN",
    "wof:placetype":"postalcode"
},
  "geometry": {"coordinates":[-2.496799,54.595896],"type":"Point"}
}