{
  "type": "Feature",
  "properties": {
    "iso:country":"GB",
    "wof:name":"CA16 6JN",
    "wof:placetype":"postalcode"
},
  "geometry": {"coordinates":[-2.49679865682404,54.5958960359181],"type":"Point"}
}