{
  "type": "Feature",
  "properties": {
    "iso:country":"GB",
    "wof:name":"CT2 9ED",
    "wof:placetype":"postalcode"
},
  "geometry": {"coordinates":[1.05166295483401,51.29871124033555],"type":"Point"}
}