{
  "type": "Feature",
  "properties": {
    "iso:country": "GB",
    "wof:name": "SG6 4BH",
    "wof:placetype": "postalcode"
  },
  "geometry": {"coordinates":[-0.247339,51.981707],"type":"Point"}
}
