{
  "type": "Feature",
  "properties": {
    "iso:country":"GB",
    "wof:name":"SG6 4BH",
    "wof:placetype":"postalcode"
},
  "geometry": {"coordinates":[-0.2473393666256,51.98170738152765],"type":"Point"}
}