{
  "type": "Feature",
  "properties": {
    "iso:country":"GB",
    "wof:name":"S62 5RX",
    "wof:placetype":"postalcode"
},
  "geometry": {"coordinates":[-1.33329884199404,53.46579276643381],"type":"Point"}
}