{
  "type": "Feature",
  "properties": {
    "date:inception_lower": "1998-12-01",
    "date:inception_upper": "1998-12-01",
    "iso:country": "GB",
    "wof:name": "ML3 7GA",
    "wof:placetype": "postalcode"
  },
  "geometry": {"coordinates":[-4.036442,55.770689],"type":"Point"}
}
