{
  "type": "Feature",
  "properties": {
    "iso:country":"GB",
    "wof:name":"ML3 7GA",
    "wof:placetype":"postalcode"
},
  "geometry": {"coordinates":[-4.03644233767277,55.77068919013318],"type":"Point"}
}