{
  "type": "Feature",
  "properties": {
    "iso:country":"GB",
    "wof:name":"BR4 9BJ",
    "wof:placetype":"postalcode"
},
  "geometry": {"coordinates":[-0.00146596616235,51.3714838816198],"type":"Point"}
}