{
  "type": "Feature",
  "properties": {
    "iso:country": "GB",
    "wof:name": "BR4 9BJ",
    "wof:placetype": "postalcode"
  },
  "geometry": {"coordinates":[-0.001466,51.371484],"type":"Point"}
}
