{
  "type": "Feature",
  "properties": {
    "iso:country":"GB",
    "wof:name":"NE13 7HS",
    "wof:placetype":"postalcode"
},
  "geometry": {"coordinates":[-1.63785123596506,55.04310262966597],"type":"Point"}
}