{
  "type": "Feature",
  "properties": {
    "iso:country":"GB",
    "wof:name":"LL34 6EH",
    "wof:placetype":"postalcode"
},
  "geometry": {"coordinates":[-3.91698974130014,53.26984965790891],"type":"Point"}
}