{
  "type": "Feature",
  "properties": {
    "iso:country": "GB",
    "wof:name": "CO12 5BB",
    "wof:placetype": "postalcode"
  },
  "geometry": {"coordinates":[1.186014,51.898547],"type":"Point"}
}
