{
  "type": "Feature",
  "properties": {
    "iso:country":"GB",
    "wof:name":"CO12 5BB",
    "wof:placetype":"postalcode"
},
  "geometry": {"coordinates":[1.18610572620194,51.89882825700847],"type":"Point"}
}