{
  "type": "Feature",
  "properties": {
    "iso:country":"GB",
    "wof:name":"KT1 2TE",
    "wof:placetype":"postalcode"
},
  "geometry": {"coordinates":[-0.30158097158433,51.40076859117149],"type":"Point"}
}