{
  "type": "Feature",
  "properties": {
    "iso:country":"GB",
    "wof:name":"LA4 4JR",
    "wof:placetype":"postalcode"
},
  "geometry": {"coordinates":[-2.87523646811078,54.06519625983739],"type":"Point"}
}