{
  "type": "Feature",
  "properties": {
    "iso:country": "GB",
    "wof:name": "LA4 4JR",
    "wof:placetype": "postalcode"
  },
  "geometry": {"coordinates":[-2.875236,54.065196],"type":"Point"}
}
