{
  "type": "Feature",
  "properties": {
    "iso:country":"GB",
    "wof:name":"SN2 1LG",
    "wof:placetype":"postalcode"
},
  "geometry": {"coordinates":[-1.78975467623516,51.577562709589],"type":"Point"}
}