{
  "type": "Feature",
  "properties": {
    "iso:country": "GB",
    "wof:name": "G76 0DA",
    "wof:placetype": "postalcode"
  },
  "geometry": {"coordinates":[-4.277504,55.757811],"type":"Point"}
}
