{
  "type": "Feature",
  "properties": {
    "iso:country":"GB",
    "wof:name":"G76 0DA",
    "wof:placetype":"postalcode"
},
  "geometry": {"coordinates":[-4.27750369263492,55.75781084914391],"type":"Point"}
}