{
  "type": "Feature",
  "properties": {
    "date:inception_lower": "1980-01-01",
    "date:inception_upper": "1980-01-01",
    "iso:country": "GB",
    "wof:name": "DY9 0SY",
    "wof:placetype": "postalcode"
  },
  "geometry": {"coordinates":[-2.127236,52.437943],"type":"Point"}
}
