{
  "type": "Feature",
  "properties": {
    "iso:country":"GB",
    "wof:name":"DY9 0SY",
    "wof:placetype":"postalcode"
},
  "geometry": {"coordinates":[-2.12722754102248,52.43791927095126],"type":"Point"}
}