{
  "type": "Feature",
  "properties": {
    "iso:country":"GB",
    "wof:name":"E14 9JZ",
    "wof:placetype":"postalcode"
},
  "geometry": {"coordinates":[-0.00427874463232,51.50920210912619],"type":"Point"}
}