{
  "type": "Feature",
  "properties": {
    "iso:country":"GB",
    "wof:name":"DN20 8LD",
    "wof:placetype":"postalcode"
},
  "geometry": {"coordinates":[-0.49329303161548,53.55173302760017],"type":"Point"}
}