{
  "type": "Feature",
  "properties": {
    "iso:country":"GB",
    "wof:name":"TN4 9GE",
    "wof:placetype":"postalcode"
},
  "geometry": {"coordinates":[0.25971899000222,51.14010394277224],"type":"Point"}
}