{
  "type": "Feature",
  "properties": {
    "date:inception_lower":"2008-11-01",
    "date:inception_upper":"2008-11-30",
    "iso:country":"GB",
    "wof:name":"TN4 9GE",
    "wof:placetype":"postalcode"
},
  "geometry": {"coordinates":[0.259719,51.140104],"type":"Point"}
}