{
  "type": "Feature",
  "properties": {
    "iso:country":"GB",
    "wof:name":"EH8 9QS",
    "wof:placetype":"postalcode"
},
  "geometry": {"coordinates":[-3.17972215325709,55.94233749120415],"type":"Point"}
}