{
  "type": "Feature",
  "properties": {
    "iso:country": "GB",
    "wof:name": "HR9 6AX",
    "wof:placetype": "postalcode"
  },
  "geometry": {"coordinates":[-2.652902,51.907233],"type":"Point"}
}
