{
  "type": "Feature",
  "properties": {
    "iso:country":"GB",
    "wof:name":"FK3 8NF",
    "wof:placetype":"postalcode"
},
  "geometry": {"coordinates":[-3.72804785924644,56.01407263918527],"type":"Point"}
}