{
  "type": "Feature",
  "properties": {
    "iso:country":"GB",
    "wof:name":"ME7 2UW",
    "wof:placetype":"postalcode"
},
  "geometry": {"coordinates":[0.58454659305535,51.38322207828904],"type":"Point"}
}