{
  "type": "Feature",
  "properties": {
    "iso:country":"GB",
    "wof:name":"TN4 9BX",
    "wof:placetype":"postalcode"
},
  "geometry": {"coordinates":[0.27135562767534,51.15086852817268],"type":"Point"}
}