{
  "type": "Feature",
  "properties": {
    "iso:country": "GB",
    "wof:name": "TN4 9BX",
    "wof:placetype": "postalcode"
  },
  "geometry": {"coordinates":[0.271356,51.150869],"type":"Point"}
}
