{
  "type": "Feature",
  "properties": {
    "date:inception_lower":"1980-01-01",
    "date:inception_upper":"1980-01-31",
    "iso:country":"GB",
    "wof:name":"TN4 9BX",
    "wof:placetype":"postalcode"
},
  "geometry": {"coordinates":[0.271356,51.150869],"type":"Point"}
}