{
  "type": "Feature",
  "properties": {
    "iso:country":"GB",
    "wof:name":"CM21 9AD",
    "wof:placetype":"postalcode"
},
  "geometry": {"coordinates":[0.15232431318633,51.81179674946294],"type":"Point"}
}