{
  "type": "Feature",
  "properties": {
    "date:inception_lower": "1986-07-01",
    "date:inception_upper": "1986-07-01",
    "iso:country": "GB",
    "wof:name": "EX22 6HL",
    "wof:placetype": "postalcode"
  },
  "geometry": {"coordinates":[-4.35655,50.819767],"type":"Point"}
}
