{
  "type": "Feature",
  "properties": {
    "iso:country": "GB",
    "wof:name": "EX22 6HL",
    "wof:placetype": "postalcode"
  },
  "geometry": {"coordinates":[-4.35655,50.819767],"type":"Point"}
}
