{
  "type": "Feature",
  "properties": {
    "iso:country":"GB",
    "wof:name":"NW4 3XD",
    "wof:placetype":"postalcode"
},
  "geometry": {"coordinates":[-0.23052108342769,51.58225464421653],"type":"Point"}
}