{
  "type": "Feature",
  "properties": {
    "date:inception_lower": "1980-01-01",
    "date:inception_upper": "1980-01-01",
    "iso:country": "GB",
    "wof:name": "NG16 6LY",
    "wof:placetype": "postalcode"
  },
  "geometry": {"coordinates":[-1.320225,53.091304],"type":"Point"}
}
