{
  "type": "Feature",
  "properties": {
    "iso:country": "GB",
    "wof:name": "CM5 9HF",
    "wof:placetype": "postalcode"
  },
  "geometry": {"coordinates":[0.24034,51.701071],"type":"Point"}
}
