{
  "type": "Feature",
  "properties": {
    "iso:country":"GB",
    "wof:name":"CM5 9HF",
    "wof:placetype":"postalcode"
},
  "geometry": {"coordinates":[0.24033954340217,51.70107132907188],"type":"Point"}
}