{
  "type": "Feature",
  "properties": {
    "iso:country":"GB",
    "wof:name":"DE4 4JG",
    "wof:placetype":"postalcode"
},
  "geometry": {"coordinates":[-1.57083435684795,53.07886997741231],"type":"Point"}
}