{
  "type": "Feature",
  "properties": {
    "iso:country": "GB",
    "wof:name": "DE4 4JG",
    "wof:placetype": "postalcode"
  },
  "geometry": {"coordinates":[-1.570834,53.07887],"type":"Point"}
}
