{
  "type": "Feature",
  "properties": {
    "iso:country":"GB",
    "wof:name":"GU25 4AZ",
    "wof:placetype":"postalcode"
},
  "geometry": {"coordinates":[-0.56020873050362,51.4012008472934],"type":"Point"}
}