{
  "type": "Feature",
  "properties": {
    "date:inception_lower":"1992-08-01",
    "date:inception_upper":"1992-08-31",
    "iso:country":"GB",
    "wof:name":"GU25 4AZ",
    "wof:placetype":"postalcode"
},
  "geometry": {"coordinates":[-0.560209,51.401201],"type":"Point"}
}