{
  "type": "Feature",
  "properties": {
    "iso:country":"GB",
    "wof:name":"LS25 7LD",
    "wof:placetype":"postalcode"
},
  "geometry": {"coordinates":[-1.37491447271985,53.76400069801625],"type":"Point"}
}