{
  "type": "Feature",
  "properties": {
    "date:inception_lower": "1995-12-01",
    "date:inception_upper": "1995-12-01",
    "iso:country": "GB",
    "wof:name": "G60 5AL",
    "wof:placetype": "postalcode"
  },
  "geometry": {"coordinates":[-4.443962,55.921814],"type":"Point"}
}
