{
  "type": "Feature",
  "properties": {
    "iso:country": "GB",
    "wof:name": "CH3 9FE",
    "wof:placetype": "postalcode"
  },
  "geometry": {"coordinates":[-2.776625,53.119795],"type":"Point"}
}
