{
  "type": "Feature",
  "properties": {
    "iso:country": "GB",
    "wof:name": "ML8 5RH",
    "wof:placetype": "postalcode"
  },
  "geometry": {"coordinates":[-3.872171,55.701524],"type":"Point"}
}
