{
  "type": "Feature",
  "properties": {
    "iso:country":"GB",
    "wof:name":"SR7 7HD",
    "wof:placetype":"postalcode"
},
  "geometry": {"coordinates":[-1.33133806573072,54.83746268502865],"type":"Point"}
}