{
  "type": "Feature",
  "properties": {
    "iso:country":"GB",
    "wof:name":"BD17 7DJ",
    "wof:placetype":"postalcode"
},
  "geometry": {"coordinates":[-1.77613777441216,53.83511312711444],"type":"Point"}
}