{
  "type": "Feature",
  "properties": {
    "date:inception_lower": "1999-06-01",
    "date:inception_upper": "1999-06-01",
    "iso:country": "GB",
    "wof:name": "BD17 7DJ",
    "wof:placetype": "postalcode"
  },
  "geometry": {"coordinates":[-1.776156,53.83511],"type":"Point"}
}
