{
  "type": "Feature",
  "properties": {
    "date:inception_lower": "1980-01-01",
    "date:inception_upper": "1980-01-01",
    "iso:country": "GB",
    "wof:name": "DG2 0JR",
    "wof:placetype": "postalcode"
  },
  "geometry": {"coordinates":[-3.784074,55.121412],"type":"Point"}
}
