{
  "type": "Feature",
  "properties": {
    "date:inception_lower": "2011-12-01",
    "date:inception_upper": "2011-12-01",
    "iso:country": "GB",
    "wof:name": "SY5 9XG",
    "wof:placetype": "postalcode"
  },
  "geometry": {"coordinates":[-2.953054,52.678567],"type":"Point"}
}
