{
  "type": "Feature",
  "properties": {
    "iso:country": "GB",
    "wof:name": "CA12 5FB",
    "wof:placetype": "postalcode"
  },
  "geometry": {"coordinates":[-3.137174,54.600406],"type":"Point"}
}
