{
  "type": "Feature",
  "properties": {
    "date:inception_lower": "1997-12-01",
    "date:inception_upper": "1997-12-01",
    "iso:country": "GB",
    "wof:name": "BS40 6PP",
    "wof:placetype": "postalcode"
  },
  "geometry": {"coordinates":[-2.682017,51.321447],"type":"Point"}
}
