{
  "type": "Feature",
  "properties": {
    "iso:country":"GB",
    "wof:name":"BS40 6PP",
    "wof:placetype":"postalcode"
},
  "geometry": {"coordinates":[-2.68201679052824,51.32144666538383],"type":"Point"}
}