{
  "type": "Feature",
  "properties": {
    "date:inception_lower": "1980-01-01",
    "date:inception_upper": "1980-01-01",
    "iso:country": "GB",
    "wof:name": "L7 1PF",
    "wof:placetype": "postalcode"
  },
  "geometry": {"coordinates":[-2.952796,53.405134],"type":"Point"}
}
