{
  "type": "Feature",
  "properties": {
    "date:inception_lower": "2022-06-01",
    "date:inception_upper": "2022-06-01",
    "iso:country": "GB",
    "wof:name": "CB6 2YG",
    "wof:placetype": "postalcode"
  },
  "geometry": {"coordinates":[0.260552,52.410059],"type":"Point"}
}
