{
  "type": "Feature",
  "properties": {
    "iso:country": "GB",
    "wof:name": "ME12 2SU",
    "wof:placetype": "postalcode"
  },
  "geometry": {"coordinates":[0.766087,51.436978],"type":"Point"}
}
