{
  "type": "Feature",
  "properties": {
    "iso:country":"GB",
    "wof:name":"ME12 2SU",
    "wof:placetype":"postalcode"
},
  "geometry": {"coordinates":[0.76608645944254,51.43697791373042],"type":"Point"}
}