{
  "type": "Feature",
  "properties": {
    "iso:country":"GB",
    "wof:name":"HG5 0QG",
    "wof:placetype":"postalcode"
},
  "geometry": {"coordinates":[-1.45487370465268,54.02256919553014],"type":"Point"}
}