{
  "type": "Feature",
  "properties": {
    "iso:country": "GB",
    "wof:name": "HG5 0QG",
    "wof:placetype": "postalcode"
  },
  "geometry": {"coordinates":[-1.450067,54.022913],"type":"Point"}
}
