{
  "type": "Feature",
  "properties": {
    "iso:country": "GB",
    "wof:name": "LE12 9DG",
    "wof:placetype": "postalcode"
  },
  "geometry": {"coordinates":[-1.287548,52.762584],"type":"Point"}
}
