{
  "type": "Feature",
  "properties": {
    "date:inception_lower": "1980-01-01",
    "date:inception_upper": "1980-01-01",
    "iso:country": "GB",
    "wof:name": "LE12 9DG",
    "wof:placetype": "postalcode"
  },
  "geometry": {"coordinates":[-1.287523,52.762737],"type":"Point"}
}
