{
  "type": "Feature",
  "properties": {
    "iso:country":"GB",
    "wof:name":"B77 2TS",
    "wof:placetype":"postalcode"
},
  "geometry": {"coordinates":[-1.67832476057274,52.61293570057205],"type":"Point"}
}