{
  "type": "Feature",
  "properties": {
    "iso:country":"GB",
    "wof:name":"CR0 5JX",
    "wof:placetype":"postalcode"
},
  "geometry": {"coordinates":[-0.08170264322855,51.36820293650562],"type":"Point"}
}