{
  "type": "Feature",
  "properties": {
    "iso:country":"GB",
    "wof:name":"KY16 9AF",
    "wof:placetype":"postalcode"
},
  "geometry": {"coordinates":[-2.79751261533904,56.34139179021034],"type":"Point"}
}