{
  "type": "Feature",
  "properties": {
    "date:inception_lower": "1980-01-01",
    "date:inception_upper": "1980-01-01",
    "iso:country": "GB",
    "wof:name": "KY16 9AF",
    "wof:placetype": "postalcode"
  },
  "geometry": {"coordinates":[-2.797513,56.341392],"type":"Point"}
}
