{
  "type": "Feature",
  "properties": {
    "date:inception_lower":"2003-11-01",
    "date:inception_upper":"2003-11-30",
    "iso:country":"GB",
    "wof:name":"SY5 9EQ",
    "wof:placetype":"postalcode"
},
  "geometry": {"coordinates":[-2.953514,52.677829],"type":"Point"}
}