{
  "type": "Feature",
  "properties": {
    "iso:country":"GB",
    "wof:name":"SY5 9EQ",
    "wof:placetype":"postalcode"
},
  "geometry": {"coordinates":[-2.95351409821388,52.67782932745063],"type":"Point"}
}