{
  "type": "Feature",
  "properties": {
    "iso:country": "GB",
    "wof:name": "SY5 9EQ",
    "wof:placetype": "postalcode"
  },
  "geometry": {"coordinates":[-2.953514,52.677829],"type":"Point"}
}
