{
  "type": "Feature",
  "properties": {
    "date:inception_lower":"1981-06-01",
    "date:inception_upper":"1981-06-30",
    "iso:country":"GB",
    "wof:name":"NG24 4RZ",
    "wof:placetype":"postalcode"
},
  "geometry": {"coordinates":[-0.822211,53.069352],"type":"Point"}
}