{
  "type": "Feature",
  "properties": {
    "iso:country":"GB",
    "wof:name":"CF32 0EE",
    "wof:placetype":"postalcode"
},
  "geometry": {"coordinates":[-3.60301742278106,51.56491926458128],"type":"Point"}
}