{
  "type": "Feature",
  "properties": {
    "date:inception_lower": "1980-01-01",
    "date:inception_upper": "1980-01-01",
    "iso:country": "GB",
    "wof:name": "CF32 0EE",
    "wof:placetype": "postalcode"
  },
  "geometry": {"coordinates":[-3.603046,51.564913],"type":"Point"}
}
