{
  "type": "Feature",
  "properties": {
    "iso:country":"GB",
    "wof:name":"LU1 5HJ",
    "wof:placetype":"postalcode"
},
  "geometry": {"coordinates":[-0.42402809860829,51.87173726022608],"type":"Point"}
}