{
  "type": "Feature",
  "properties": {
    "date:inception_lower": "2018-06-01",
    "date:inception_upper": "2018-06-01",
    "iso:country": "GB",
    "wof:name": "ME17 2YY",
    "wof:placetype": "postalcode"
  },
  "geometry": {"coordinates":[0.699975,51.244153],"type":"Point"}
}
