{
  "type": "Feature",
  "properties": {
    "iso:country":"GB",
    "wof:name":"KY14 7QG",
    "wof:placetype":"postalcode"
},
  "geometry": {"coordinates":[-3.26863636382788,56.27870993820333],"type":"Point"}
}