{
  "type": "Feature",
  "properties": {
    "iso:country":"GB",
    "wof:name":"PE21 9DX",
    "wof:placetype":"postalcode"
},
  "geometry": {"coordinates":[-0.03296911954071,52.98498072464952],"type":"Point"}
}