{
  "type": "Feature",
  "properties": {
    "iso:country":"GB",
    "wof:name":"SE1 6AY",
    "wof:placetype":"postalcode"
},
  "geometry": {"coordinates":[-0.092659584587,51.49612276906981],"type":"Point"}
}