{
  "type": "Feature",
  "properties": {
    "date:inception_lower": "1980-01-01",
    "date:inception_upper": "1980-01-01",
    "iso:country": "GB",
    "wof:name": "SS9 4AU",
    "wof:placetype": "postalcode"
  },
  "geometry": {"coordinates":[0.659323,51.55938],"type":"Point"}
}
