{
  "type": "Feature",
  "properties": {
    "iso:country":"GB",
    "wof:name":"SS9 4AU",
    "wof:placetype":"postalcode"
},
  "geometry": {"coordinates":[0.65932275910712,51.55937996376529],"type":"Point"}
}