{
  "type": "Feature",
  "properties": {
    "iso:country": "GB",
    "wof:name": "SO19 9UX",
    "wof:placetype": "postalcode"
  },
  "geometry": {"coordinates":[-1.380288,50.893732],"type":"Point"}
}
