{
  "type": "Feature",
  "properties": {
    "iso:country":"GB",
    "wof:name":"M6 8LP",
    "wof:placetype":"postalcode"
},
  "geometry": {"coordinates":[-2.32366408497214,53.49527412198169],"type":"Point"}
}