{
  "type": "Feature",
  "properties": {
    "iso:country": "GB",
    "wof:name": "WC2A 3QQ",
    "wof:placetype": "postalcode"
  },
  "geometry": {"coordinates":[-0.11306,51.515994],"type":"Point"}
}
