{
  "type": "Feature",
  "properties": {
    "iso:country":"GB",
    "wof:name":"WC2A 3QQ",
    "wof:placetype":"postalcode"
},
  "geometry": {"coordinates":[-0.11305991138608,51.51599360231729],"type":"Point"}
}