{
  "type": "Feature",
  "properties": {
    "iso:country":"GB",
    "wof:name":"TN8 6HP",
    "wof:placetype":"postalcode"
},
  "geometry": {"coordinates":[0.05904108808889,51.20807546798287],"type":"Point"}
}