{
  "type": "Feature",
  "properties": {
    "iso:country": "GB",
    "wof:name": "LS9 0LL",
    "wof:placetype": "postalcode"
  },
  "geometry": {"coordinates":[-1.49652,53.79906],"type":"Point"}
}
