{
  "type": "Feature",
  "properties": {
    "iso:country":"GB",
    "wof:name":"LS9 0LL",
    "wof:placetype":"postalcode"
},
  "geometry": {"coordinates":[-1.49652054488664,53.7990600887088],"type":"Point"}
}