{
  "type": "Feature",
  "properties": {
    "date:inception_lower": "1980-01-01",
    "date:inception_upper": "1980-01-01",
    "iso:country": "GB",
    "wof:name": "LL52 0BU",
    "wof:placetype": "postalcode"
  },
  "geometry": {"coordinates":[-4.236479,52.91886],"type":"Point"}
}
