{
  "type": "Feature",
  "properties": {
    "iso:country":"GB",
    "wof:name":"LL52 0BU",
    "wof:placetype":"postalcode"
},
  "geometry": {"coordinates":[-4.2364789412573,52.9188598923447],"type":"Point"}
}