{
  "type": "Feature",
  "properties": {
    "iso:country": "GB",
    "wof:name": "NG33 4DX",
    "wof:placetype": "postalcode"
  },
  "geometry": {"coordinates":[-0.533252,52.842952],"type":"Point"}
}
