{
  "type": "Feature",
  "properties": {
    "iso:country": "GB",
    "wof:name": "CV34 4DY",
    "wof:placetype": "postalcode"
  },
  "geometry": {"coordinates":[-1.591657,52.282338],"type":"Point"}
}
