{
  "type": "Feature",
  "properties": {
    "iso:country":"GB",
    "wof:name":"DN4 7ER",
    "wof:placetype":"postalcode"
},
  "geometry": {"coordinates":[-1.08819081465587,53.50357205875321],"type":"Point"}
}