{
  "type": "Feature",
  "properties": {
    "iso:country": "GB",
    "wof:name": "FK8 3SD",
    "wof:placetype": "postalcode"
  },
  "geometry": {"coordinates":[-4.393235,56.152767],"type":"Point"}
}
