{
  "type": "Feature",
  "properties": {
    "date:inception_lower": "2008-04-01",
    "date:inception_upper": "2008-04-01",
    "iso:country": "GB",
    "wof:name": "S44 6FE",
    "wof:placetype": "postalcode"
  },
  "geometry": {"coordinates":[-1.307272,53.224609],"type":"Point"}
}
