{
  "type": "Feature",
  "properties": {
    "iso:country":"GB",
    "wof:name":"S44 6FE",
    "wof:placetype":"postalcode"
},
  "geometry": {"coordinates":[-1.30727191819397,53.22460935162825],"type":"Point"}
}