{
  "type": "Feature",
  "properties": {
    "iso:country":"GB",
    "wof:name":"SK4 2LL",
    "wof:placetype":"postalcode"
},
  "geometry": {"coordinates":[-2.16935969383095,53.4166288478948],"type":"Point"}
}