{
  "type": "Feature",
  "properties": {
    "date:inception_lower":"1980-01-01",
    "date:inception_upper":"1980-01-31",
    "iso:country":"GB",
    "wof:name":"LS12 5DP",
    "wof:placetype":"postalcode"
},
  "geometry": {"coordinates":[-1.623961,53.775232],"type":"Point"}
}