{
  "type": "Feature",
  "properties": {
    "iso:country":"GB",
    "wof:name":"LE7 7PP",
    "wof:placetype":"postalcode"
},
  "geometry": {"coordinates":[-1.13050096891751,52.7195992511713],"type":"Point"}
}