{
  "type": "Feature",
  "properties": {
    "iso:country":"GB",
    "wof:name":"LL55 2PH",
    "wof:placetype":"postalcode"
},
  "geometry": {"coordinates":[-4.27245599901935,53.13791871226778],"type":"Point"}
}