{
  "type": "Feature",
  "properties": {
    "date:inception_lower": "2018-07-01",
    "date:inception_upper": "2018-07-01",
    "iso:country": "GB",
    "wof:name": "DL6 2FE",
    "wof:placetype": "postalcode"
  },
  "geometry": {"coordinates":[-1.444383,54.352914],"type":"Point"}
}
