{
  "type": "Feature",
  "properties": {
    "iso:country":"GB",
    "wof:name":"EH47 7EP",
    "wof:placetype":"postalcode"
},
  "geometry": {"coordinates":[-3.62435883105892,55.87308840760141],"type":"Point"}
}