{
  "type": "Feature",
  "properties": {
    "iso:country": "GB",
    "wof:name": "RG42 3XG",
    "wof:placetype": "postalcode"
  },
  "geometry": {"coordinates":[-0.725395,51.423723],"type":"Point"}
}
