{
  "type": "Feature",
  "properties": {
    "iso:country":"GB",
    "wof:name":"RG42 3XG",
    "wof:placetype":"postalcode"
},
  "geometry": {"coordinates":[-0.72539524398839,51.42372347291594],"type":"Point"}
}