{
  "type": "Feature",
  "properties": {
    "iso:country": "GB",
    "wof:name": "BA11 1FF",
    "wof:placetype": "postalcode"
  },
  "geometry": {"coordinates":[-2.31869,51.232033],"type":"Point"}
}
