{
  "type": "Feature",
  "properties": {
    "iso:country":"GB",
    "wof:name":"BA11 1FF",
    "wof:placetype":"postalcode"
},
  "geometry": {"coordinates":[-2.31869385356272,51.23203811303761],"type":"Point"}
}