{
  "type": "Feature",
  "properties": {
    "date:inception_lower": "2004-05-01",
    "date:inception_upper": "2004-05-01",
    "iso:country": "GB",
    "wof:name": "BA11 1FF",
    "wof:placetype": "postalcode"
  },
  "geometry": {"coordinates":[-2.318676,51.232069],"type":"Point"}
}
