{
  "type": "Feature",
  "properties": {
    "iso:country": "GB",
    "wof:name": "TS14 6FA",
    "wof:placetype": "postalcode"
  },
  "geometry": {"coordinates":[-1.071986,54.534364],"type":"Point"}
}
