{
  "type": "Feature",
  "properties": {
    "date:inception_lower": "2002-11-01",
    "date:inception_upper": "2002-11-01",
    "iso:country": "GB",
    "wof:name": "LA2 9RY",
    "wof:placetype": "postalcode"
  },
  "geometry": {"coordinates":[-2.690211,54.079695],"type":"Point"}
}
