{
  "type": "Feature",
  "properties": {
    "iso:country":"GB",
    "wof:name":"LA2 9RY",
    "wof:placetype":"postalcode"
},
  "geometry": {"coordinates":[-2.69021318844477,54.07971142904587],"type":"Point"}
}