{
  "type": "Feature",
  "properties": {
    "iso:country": "GB",
    "wof:name": "LA2 9RY",
    "wof:placetype": "postalcode"
  },
  "geometry": {"coordinates":[-2.690211,54.079695],"type":"Point"}
}
