{
  "type": "Feature",
  "properties": {
    "iso:country":"GB",
    "wof:name":"NR21 8LU",
    "wof:placetype":"postalcode"
},
  "geometry": {"coordinates":[0.87311248547339,52.83363811326657],"type":"Point"}
}