{
  "type": "Feature",
  "properties": {
    "date:inception_lower":"1984-10-01",
    "date:inception_upper":"1984-10-31",
    "iso:country":"GB",
    "wof:name":"NR21 8LU",
    "wof:placetype":"postalcode"
},
  "geometry": {"coordinates":[0.873129,52.833645],"type":"Point"}
}