{
  "type": "Feature",
  "properties": {
    "iso:country":"GB",
    "wof:name":"M7 1AR",
    "wof:placetype":"postalcode"
},
  "geometry": {"coordinates":[-2.26252491324816,53.49266471429359],"type":"Point"}
}