{
  "type": "Feature",
  "properties": {
    "iso:country":"GB",
    "wof:name":"WD3 1FZ",
    "wof:placetype":"postalcode"
},
  "geometry": {"coordinates":[-0.47146257236721,51.63892656709186],"type":"Point"}
}