{
  "type": "Feature",
  "properties": {
    "date:inception_lower": "2009-09-01",
    "date:inception_upper": "2009-09-01",
    "iso:country": "GB",
    "wof:name": "WD3 1FZ",
    "wof:placetype": "postalcode"
  },
  "geometry": {"coordinates":[-0.471463,51.638927],"type":"Point"}
}
