{
  "type": "Feature",
  "properties": {
    "iso:country":"GB",
    "wof:name":"IP24 2YA",
    "wof:placetype":"postalcode"
},
  "geometry": {"coordinates":[0.76617517221836,52.41788518528738],"type":"Point"}
}