{
  "type": "Feature",
  "properties": {
    "iso:country": "GB",
    "wof:name": "NE7 7AA",
    "wof:placetype": "postalcode"
  },
  "geometry": {"coordinates":[-1.591791,54.998925],"type":"Point"}
}
