{
  "type": "Feature",
  "properties": {
    "date:inception_lower": "2000-12-01",
    "date:inception_upper": "2000-12-01",
    "iso:country": "GB",
    "wof:name": "MK5 7EX",
    "wof:placetype": "postalcode"
  },
  "geometry": {"coordinates":[-0.778544,52.018409],"type":"Point"}
}
