{
  "type": "Feature",
  "properties": {
    "iso:country":"GB",
    "wof:name":"MK5 7EX",
    "wof:placetype":"postalcode"
},
  "geometry": {"coordinates":[-0.77854389532021,52.01840894206802],"type":"Point"}
}