{
  "type": "Feature",
  "properties": {
    "date:inception_lower": "1980-01-01",
    "date:inception_upper": "1980-01-01",
    "iso:country": "GB",
    "wof:name": "DH8 9HJ",
    "wof:placetype": "postalcode"
  },
  "geometry": {"coordinates":[-1.863573,54.816769],"type":"Point"}
}
