{
  "type": "Feature",
  "properties": {
    "iso:country":"GB",
    "wof:name":"DH8 9HJ",
    "wof:placetype":"postalcode"
},
  "geometry": {"coordinates":[-1.86357306204663,54.81676894507699],"type":"Point"}
}