{
  "type": "Feature",
  "properties": {
    "iso:country":"GB",
    "wof:name":"W9 3JT",
    "wof:placetype":"postalcode"
},
  "geometry": {"coordinates":[-0.20021360357626,51.53137350064035],"type":"Point"}
}