{
  "type": "Feature",
  "properties": {
    "date:inception_lower": "2004-11-01",
    "date:inception_upper": "2004-11-01",
    "iso:country": "GB",
    "wof:name": "G15 8BU",
    "wof:placetype": "postalcode"
  },
  "geometry": {"coordinates":[-4.386617,55.910725],"type":"Point"}
}
