{
  "type": "Feature",
  "properties": {
    "iso:country":"GB",
    "wof:name":"CH61 9NG",
    "wof:placetype":"postalcode"
},
  "geometry": {"coordinates":[-3.0935952162402,53.3430813415371],"type":"Point"}
}