{
  "type": "Feature",
  "properties": {
    "iso:country":"GB",
    "wof:name":"PL18 9DY",
    "wof:placetype":"postalcode"
},
  "geometry": {"coordinates":[-4.2205783046963,50.5167236480675],"type":"Point"}
}