{
  "type": "Feature",
  "properties": {
    "iso:country": "GB",
    "wof:name": "CW4 7LD",
    "wof:placetype": "postalcode"
  },
  "geometry": {"coordinates":[-2.371288,53.200612],"type":"Point"}
}
