{
  "type": "Feature",
  "properties": {
    "date:inception_lower": "1987-04-01",
    "date:inception_upper": "1987-04-01",
    "iso:country": "GB",
    "wof:name": "SK4 2LY",
    "wof:placetype": "postalcode"
  },
  "geometry": {"coordinates":[-2.171746,53.415043],"type":"Point"}
}
