{
  "type": "Feature",
  "properties": {
    "iso:country": "GB",
    "wof:name": "SK4 2LY",
    "wof:placetype": "postalcode"
  },
  "geometry": {"coordinates":[-2.171746,53.415043],"type":"Point"}
}
