{
  "type": "Feature",
  "properties": {
    "iso:country": "GB",
    "wof:name": "GL51 8DW",
    "wof:placetype": "postalcode"
  },
  "geometry": {"coordinates":[-2.085,51.905427],"type":"Point"}
}
