{
  "type": "Feature",
  "properties": {
    "iso:country":"GB",
    "wof:name":"GL51 8DW",
    "wof:placetype":"postalcode"
},
  "geometry": {"coordinates":[-2.08500053349351,51.90542694721886],"type":"Point"}
}