{
  "type": "Feature",
  "properties": {
    "iso:country": "GB",
    "wof:name": "WS12 4TD",
    "wof:placetype": "postalcode"
  },
  "geometry": {"coordinates":[-2.040074,52.715029],"type":"Point"}
}
