{
  "type": "Feature",
  "properties": {
    "date:inception_lower":"1990-07-01",
    "date:inception_upper":"1990-07-31",
    "iso:country":"GB",
    "wof:name":"WS12 4TD",
    "wof:placetype":"postalcode"
},
  "geometry": {"coordinates":[-2.040074,52.715029],"type":"Point"}
}