{
  "type": "Feature",
  "properties": {
    "iso:country":"GB",
    "wof:name":"WS12 4TD",
    "wof:placetype":"postalcode"
},
  "geometry": {"coordinates":[-2.04007381041054,52.71502910030043],"type":"Point"}
}