{
  "type": "Feature",
  "properties": {
    "iso:country":"GB",
    "wof:name":"TA3 6QE",
    "wof:placetype":"postalcode"
},
  "geometry": {"coordinates":[-2.92365807221594,51.00114983810342],"type":"Point"}
}