{
  "type": "Feature",
  "properties": {
    "date:inception_lower":"1990-02-01",
    "date:inception_upper":"1990-02-28",
    "iso:country":"GB",
    "wof:name":"TA3 6QE",
    "wof:placetype":"postalcode"
},
  "geometry": {"coordinates":[-2.923658,51.00115],"type":"Point"}
}