{
  "type": "Feature",
  "properties": {
    "iso:country":"GB",
    "wof:name":"G84 0NE",
    "wof:placetype":"postalcode"
},
  "geometry": {"coordinates":[-4.86437295522467,56.01639078152725],"type":"Point"}
}