{
  "type": "Feature",
  "properties": {
    "iso:country": "GB",
    "wof:name": "G84 0NE",
    "wof:placetype": "postalcode"
  },
  "geometry": {"coordinates":[-4.864087,56.016489],"type":"Point"}
}
