{
  "type": "Feature",
  "properties": {
    "iso:country": "GB",
    "wof:name": "CF14 6DJ",
    "wof:placetype": "postalcode"
  },
  "geometry": {"coordinates":[-3.212189,51.519973],"type":"Point"}
}
