{
  "type": "Feature",
  "properties": {
    "iso:country":"GB",
    "wof:name":"PO7 6PH",
    "wof:placetype":"postalcode"
},
  "geometry": {"coordinates":[-1.06354806473403,50.9009380607142],"type":"Point"}
}