{
  "type": "Feature",
  "properties": {
    "iso:country":"GB",
    "wof:name":"SK15 1QS",
    "wof:placetype":"postalcode"
},
  "geometry": {"coordinates":[-2.07089447956045,53.48473495479026],"type":"Point"}
}