{
  "type": "Feature",
  "properties": {
    "iso:country": "GB",
    "wof:name": "GL18 1RU",
    "wof:placetype": "postalcode"
  },
  "geometry": {"coordinates":[-2.41419,51.934263],"type":"Point"}
}
