{
  "type": "Feature",
  "properties": {
    "iso:country":"GB",
    "wof:name":"LS8 1PQ",
    "wof:placetype":"postalcode"
},
  "geometry": {"coordinates":[-1.52111152521091,53.83010651527633],"type":"Point"}
}