{
  "type": "Feature",
  "properties": {
    "iso:country":"GB",
    "wof:name":"WA1 3LA",
    "wof:placetype":"postalcode"
},
  "geometry": {"coordinates":[-2.5654140633489,53.40234015123628],"type":"Point"}
}