{
  "type": "Feature",
  "properties": {
    "date:inception_lower": "1980-01-01",
    "date:inception_upper": "1980-01-01",
    "iso:country": "GB",
    "wof:name": "WA1 3LA",
    "wof:placetype": "postalcode"
  },
  "geometry": {"coordinates":[-2.565414,53.40234],"type":"Point"}
}
