{
  "type": "Feature",
  "properties": {
    "iso:country":"GB",
    "wof:name":"NP22 4QH",
    "wof:placetype":"postalcode"
},
  "geometry": {"coordinates":[-3.24210257131313,51.78084283605097],"type":"Point"}
}