{
  "type": "Feature",
  "properties": {
    "iso:country":"GB",
    "wof:name":"L36 7UY",
    "wof:placetype":"postalcode"
},
  "geometry": {"coordinates":[-2.84473492445384,53.41960273506302],"type":"Point"}
}