{
  "type": "Feature",
  "properties": {
    "iso:country": "GB",
    "wof:name": "L36 7UY",
    "wof:placetype": "postalcode"
  },
  "geometry": {"coordinates":[-2.844735,53.419603],"type":"Point"}
}
