{
  "type": "Feature",
  "properties": {
    "date:inception_lower":"1999-12-01",
    "date:inception_upper":"1999-12-31",
    "iso:country":"GB",
    "wof:name":"LL23 7BF",
    "wof:placetype":"postalcode"
},
  "geometry": {"coordinates":[-3.594229,52.908333],"type":"Point"}
}