{
  "type": "Feature",
  "properties": {
    "iso:country":"GB",
    "wof:name":"LL23 7BF",
    "wof:placetype":"postalcode"
},
  "geometry": {"coordinates":[-3.59422950519522,52.90833313145104],"type":"Point"}
}