{
  "type": "Feature",
  "properties": {
    "iso:country":"GB",
    "wof:name":"E1W 3AX",
    "wof:placetype":"postalcode"
},
  "geometry": {"coordinates":[-0.04693985740004,51.51044188242291],"type":"Point"}
}