{
  "type": "Feature",
  "properties": {
    "iso:country": "GB",
    "wof:name": "G71 7JH",
    "wof:placetype": "postalcode"
  },
  "geometry": {"coordinates":[-4.074608,55.820738],"type":"Point"}
}
