{
  "type": "Feature",
  "properties": {
    "iso:country":"GB",
    "wof:name":"IG10 1BL",
    "wof:placetype":"postalcode"
},
  "geometry": {"coordinates":[0.05745080504025,51.64708095527561],"type":"Point"}
}