{
  "type": "Feature",
  "properties": {
    "iso:country": "GB",
    "wof:name": "NP4 6RY",
    "wof:placetype": "postalcode"
  },
  "geometry": {"coordinates":[-3.061368,51.712079],"type":"Point"}
}
