{
  "type": "Feature",
  "properties": {
    "date:inception_lower": "1980-01-01",
    "date:inception_upper": "1980-01-01",
    "iso:country": "GB",
    "wof:name": "NP4 6RY",
    "wof:placetype": "postalcode"
  },
  "geometry": {"coordinates":[-3.061454,51.71206],"type":"Point"}
}
