{
  "type": "Feature",
  "properties": {
    "iso:country":"GB",
    "wof:name":"NP4 6RY",
    "wof:placetype":"postalcode"
},
  "geometry": {"coordinates":[-3.0614472771138,51.71205733357279],"type":"Point"}
}