{
  "type": "Feature",
  "properties": {
    "iso:country":"GB",
    "wof:name":"NE45 5QY",
    "wof:placetype":"postalcode"
},
  "geometry": {"coordinates":[-2.03864293427502,54.96674880134294],"type":"Point"}
}