{
  "type": "Feature",
  "properties": {
    "iso:country":"GB",
    "wof:name":"SA14 9SA",
    "wof:placetype":"postalcode"
},
  "geometry": {"coordinates":[-4.09508422822411,51.67030830054021],"type":"Point"}
}