{
  "type": "Feature",
  "properties": {
    "iso:country":"GB",
    "wof:name":"HS2 0PW",
    "wof:placetype":"postalcode"
},
  "geometry": {"coordinates":[-6.22791513321641,58.22037546079815],"type":"Point"}
}