{
  "type": "Feature",
  "properties": {
    "date:inception_lower": "1980-01-01",
    "date:inception_upper": "1980-01-01",
    "iso:country": "GB",
    "wof:name": "NG5 7JZ",
    "wof:placetype": "postalcode"
  },
  "geometry": {"coordinates":[-1.112901,53.00063],"type":"Point"}
}
