{
  "type": "Feature",
  "properties": {
    "iso:country": "GB",
    "wof:name": "W1T 4JG",
    "wof:placetype": "postalcode"
  },
  "geometry": {"coordinates":[-0.138449,51.520752],"type":"Point"}
}
