{
  "type": "Feature",
  "properties": {
    "iso:country":"GB",
    "wof:name":"AB15 6HG",
    "wof:placetype":"postalcode"
},
  "geometry": {"coordinates":[-2.17261115209375,57.14956033626213],"type":"Point"}
}