{
  "type": "Feature",
  "properties": {
    "date:inception_lower": "2010-03-01",
    "date:inception_upper": "2010-03-01",
    "iso:country": "GB",
    "wof:name": "OX39 4AW",
    "wof:placetype": "postalcode"
  },
  "geometry": {"coordinates":[-0.907198,51.699268],"type":"Point"}
}
