{
  "type": "Feature",
  "properties": {
    "iso:country":"GB",
    "wof:name":"OX39 4AW",
    "wof:placetype":"postalcode"
},
  "geometry": {"coordinates":[-0.90719799093483,51.69926753486141],"type":"Point"}
}