{
  "type": "Feature",
  "properties": {
    "date:inception_lower": "1980-01-01",
    "date:inception_upper": "1980-01-01",
    "iso:country": "GB",
    "wof:name": "OX7 6UW",
    "wof:placetype": "postalcode"
  },
  "geometry": {"coordinates":[-1.625741,51.903191],"type":"Point"}
}
