{
  "type": "Feature",
  "properties": {
    "iso:country":"GB",
    "wof:name":"OX7 6UW",
    "wof:placetype":"postalcode"
},
  "geometry": {"coordinates":[-1.62574065835688,51.90319134216443],"type":"Point"}
}