{
  "type": "Feature",
  "properties": {
    "date:inception_lower": "1980-01-01",
    "date:inception_upper": "1980-01-01",
    "iso:country": "GB",
    "wof:name": "NE29 8AZ",
    "wof:placetype": "postalcode"
  },
  "geometry": {"coordinates":[-1.479008,55.019297],"type":"Point"}
}
