{
  "type": "Feature",
  "properties": {
    "iso:country":"GB",
    "wof:name":"NE29 8AZ",
    "wof:placetype":"postalcode"
},
  "geometry": {"coordinates":[-1.47900800829165,55.01929740592364],"type":"Point"}
}