{
  "type": "Feature",
  "properties": {
    "iso:country": "GB",
    "wof:name": "SS17 9JG",
    "wof:placetype": "postalcode"
  },
  "geometry": {"coordinates":[0.472684,51.529927],"type":"Point"}
}
