{
  "type": "Feature",
  "properties": {
    "iso:country": "GB",
    "wof:name": "TW14 9XF",
    "wof:placetype": "postalcode"
  },
  "geometry": {"coordinates":[-0.41866,51.449131],"type":"Point"}
}
