{
  "type": "Feature",
  "properties": {
    "iso:country":"GB",
    "wof:name":"TS6 9LG",
    "wof:placetype":"postalcode"
},
  "geometry": {"coordinates":[-1.14159967199048,54.55904982676051],"type":"Point"}
}