{
  "type": "Feature",
  "properties": {
    "date:inception_lower": "1980-01-01",
    "date:inception_upper": "1980-01-01",
    "iso:country": "GB",
    "wof:name": "TS6 9LG",
    "wof:placetype": "postalcode"
  },
  "geometry": {"coordinates":[-1.1416,54.55905],"type":"Point"}
}
