{
  "type": "Feature",
  "properties": {
    "iso:country": "GB",
    "wof:name": "BS40 8UX",
    "wof:placetype": "postalcode"
  },
  "geometry": {"coordinates":[-2.638346,51.353272],"type":"Point"}
}
