{
  "type": "Feature",
  "properties": {
    "iso:country": "GB",
    "wof:name": "AB16 7QL",
    "wof:placetype": "postalcode"
  },
  "geometry": {"coordinates":[-2.164722,57.166944],"type":"Point"}
}
