{
  "type": "Feature",
  "properties": {
    "date:inception_lower": "2019-09-01",
    "date:inception_upper": "2019-09-01",
    "iso:country": "GB",
    "wof:name": "ST19 5TU",
    "wof:placetype": "postalcode"
  },
  "geometry": {"coordinates":[-2.115432,52.715103],"type":"Point"}
}
