{
  "type": "Feature",
  "properties": {
    "iso:country": "GB",
    "wof:name": "ST19 5TU",
    "wof:placetype": "postalcode"
  },
  "geometry": {"coordinates":[-2.115077,52.715256],"type":"Point"}
}
