{
  "type": "Feature",
  "properties": {
    "iso:country": "GB",
    "wof:name": "S71 1XA",
    "wof:placetype": "postalcode"
  },
  "geometry": {"coordinates":[-1.471556,53.574373],"type":"Point"}
}
