{
  "type": "Feature",
  "properties": {
    "iso:country": "GB",
    "wof:name": "DN4 5JZ",
    "wof:placetype": "postalcode"
  },
  "geometry": {"coordinates":[-1.089855,53.51598],"type":"Point"}
}
