{
  "type": "Feature",
  "properties": {
    "iso:country":"GB",
    "wof:name":"DN4 5JZ",
    "wof:placetype":"postalcode"
},
  "geometry": {"coordinates":[-1.08985492582785,53.51598018374814],"type":"Point"}
}