{
  "type": "Feature",
  "properties": {
    "iso:country":"GB",
    "wof:name":"PE6 8DA",
    "wof:placetype":"postalcode"
},
  "geometry": {"coordinates":[-0.32056154181762,52.67862728234365],"type":"Point"}
}