{
  "type": "Feature",
  "properties": {
    "date:inception_lower": "1980-01-01",
    "date:inception_upper": "1980-01-01",
    "iso:country": "GB",
    "wof:name": "CM3 5NL",
    "wof:placetype": "postalcode"
  },
  "geometry": {"coordinates":[0.60587,51.647213],"type":"Point"}
}
