{
  "type": "Feature",
  "properties": {
    "iso:country":"GB",
    "wof:name":"CM3 5NL",
    "wof:placetype":"postalcode"
},
  "geometry": {"coordinates":[0.60587038315112,51.64721338927333],"type":"Point"}
}