{
  "type": "Feature",
  "properties": {
    "iso:country":"GB",
    "wof:name":"BN44 3HT",
    "wof:placetype":"postalcode"
},
  "geometry": {"coordinates":[-0.30257398663328,50.88508790117591],"type":"Point"}
}