{
  "type": "Feature",
  "properties": {
    "iso:country": "GB",
    "wof:name": "DN32 8HN",
    "wof:placetype": "postalcode"
  },
  "geometry": {"coordinates":[-0.061303,53.56135],"type":"Point"}
}
