{
  "type": "Feature",
  "properties": {
    "iso:country":"GB",
    "wof:name":"SY11 4LS",
    "wof:placetype":"postalcode"
},
  "geometry": {"coordinates":[-3.00307102758479,52.8457649751476],"type":"Point"}
}