{
  "type": "Feature",
  "properties": {
    "date:inception_lower":"1980-01-01",
    "date:inception_upper":"1980-01-31",
    "iso:country":"GB",
    "wof:name":"SY11 4LS",
    "wof:placetype":"postalcode"
},
  "geometry": {"coordinates":[-3.003071,52.845765],"type":"Point"}
}