{
  "type": "Feature",
  "properties": {
    "iso:country":"GB",
    "wof:name":"CV37 8BF",
    "wof:placetype":"postalcode"
},
  "geometry": {"coordinates":[-1.80944354909715,52.16133087742799],"type":"Point"}
}