{
  "type": "Feature",
  "properties": {
    "iso:country": "GB",
    "wof:name": "CV37 8BF",
    "wof:placetype": "postalcode"
  },
  "geometry": {"coordinates":[-1.809444,52.161331],"type":"Point"}
}
