{
  "type": "Feature",
  "properties": {
    "date:inception_lower":"2012-04-01",
    "date:inception_upper":"2012-04-30",
    "iso:country":"GB",
    "wof:name":"CV37 8BF",
    "wof:placetype":"postalcode"
},
  "geometry": {"coordinates":[-1.809444,52.161331],"type":"Point"}
}