{
  "type": "Feature",
  "properties": {
    "iso:country": "GB",
    "wof:name": "CF43 4DH",
    "wof:placetype": "postalcode"
  },
  "geometry": {"coordinates":[-3.486621,51.675623],"type":"Point"}
}
