{
  "type": "Feature",
  "properties": {
    "iso:country":"GB",
    "wof:name":"CF43 4DH",
    "wof:placetype":"postalcode"
},
  "geometry": {"coordinates":[-3.48662091891788,51.67562347465469],"type":"Point"}
}