{
  "type": "Feature",
  "properties": {
    "iso:country":"GB",
    "wof:name":"PH6 2EA",
    "wof:placetype":"postalcode"
},
  "geometry": {"coordinates":[-3.98255492124698,56.37600895838118],"type":"Point"}
}