{
  "type": "Feature",
  "properties": {
    "iso:country":"GB",
    "wof:name":"CV3 1GA",
    "wof:placetype":"postalcode"
},
  "geometry": {"coordinates":[-1.47724585241553,52.40190712608187],"type":"Point"}
}