{
  "type": "Feature",
  "properties": {
    "iso:country": "GB",
    "wof:name": "CV3 1GA",
    "wof:placetype": "postalcode"
  },
  "geometry": {"coordinates":[-1.477246,52.401907],"type":"Point"}
}
