{
  "type": "Feature",
  "properties": {
    "iso:country":"GB",
    "wof:name":"KT20 6TR",
    "wof:placetype":"postalcode"
},
  "geometry": {"coordinates":[-0.20964433082431,51.27288210945196],"type":"Point"}
}