{
  "type": "Feature",
  "properties": {
    "iso:country":"GB",
    "wof:name":"RM7 0PH",
    "wof:placetype":"postalcode"
},
  "geometry": {"coordinates":[0.18435261928551,51.56497743575741],"type":"Point"}
}