{
  "type": "Feature",
  "properties": {
    "iso:country":"GB",
    "wof:name":"G66 3BB",
    "wof:placetype":"postalcode"
},
  "geometry": {"coordinates":[-4.13332203161415,55.93963115181214],"type":"Point"}
}