{
  "type": "Feature",
  "properties": {
    "iso:country": "GB",
    "wof:name": "G66 3BB",
    "wof:placetype": "postalcode"
  },
  "geometry": {"coordinates":[-4.133322,55.939631],"type":"Point"}
}
