{
  "type": "Feature",
  "properties": {
    "date:inception_lower": "1996-12-01",
    "date:inception_upper": "1996-12-01",
    "iso:country": "GB",
    "wof:name": "HR8 2QY",
    "wof:placetype": "postalcode"
  },
  "geometry": {"coordinates":[-2.433955,52.045525],"type":"Point"}
}
