{
  "type": "Feature",
  "properties": {
    "iso:country":"GB",
    "wof:name":"HR8 2QY",
    "wof:placetype":"postalcode"
},
  "geometry": {"coordinates":[-2.43395536979695,52.04552463149378],"type":"Point"}
}