{
  "type": "Feature",
  "properties": {
    "iso:country":"GB",
    "wof:name":"GU52 8ED",
    "wof:placetype":"postalcode"
},
  "geometry": {"coordinates":[-0.82524076048912,51.26423022781805],"type":"Point"}
}