{
  "type": "Feature",
  "properties": {
    "date:inception_lower":"1980-01-01",
    "date:inception_upper":"1980-01-31",
    "iso:country":"GB",
    "wof:name":"LN9 5RF",
    "wof:placetype":"postalcode"
},
  "geometry": {"coordinates":[-0.149816,53.212136],"type":"Point"}
}