{
  "type": "Feature",
  "properties": {
    "iso:country": "GB",
    "wof:name": "LN9 5RF",
    "wof:placetype": "postalcode"
  },
  "geometry": {"coordinates":[-0.149816,53.212136],"type":"Point"}
}
