{
  "type": "Feature",
  "properties": {
    "iso:country":"GB",
    "wof:name":"G20 8HZ",
    "wof:placetype":"postalcode"
},
  "geometry": {"coordinates":[-4.28833273561994,55.88731834655098],"type":"Point"}
}