{
  "type": "Feature",
  "properties": {
    "date:inception_lower": "1996-12-01",
    "date:inception_upper": "1996-12-01",
    "iso:country": "GB",
    "wof:name": "SK6 5RY",
    "wof:placetype": "postalcode"
  },
  "geometry": {"coordinates":[-2.029708,53.419145],"type":"Point"}
}
