{
  "type": "Feature",
  "properties": {
    "iso:country":"GB",
    "wof:name":"SK6 5RY",
    "wof:placetype":"postalcode"
},
  "geometry": {"coordinates":[-2.02970796933111,53.41914547403061],"type":"Point"}
}