{
  "type": "Feature",
  "properties": {
    "iso:country":"GB",
    "wof:name":"RM12 4DP",
    "wof:placetype":"postalcode"
},
  "geometry": {"coordinates":[0.18611443978812,51.55959387445719],"type":"Point"}
}