{
  "type": "Feature",
  "properties": {
    "iso:country":"GB",
    "wof:name":"TN30 6EN",
    "wof:placetype":"postalcode"
},
  "geometry": {"coordinates":[0.68974774132349,51.08153252319116],"type":"Point"}
}