{
  "type": "Feature",
  "properties": {
    "date:inception_lower":"1993-08-01",
    "date:inception_upper":"1993-08-31",
    "iso:country":"GB",
    "wof:name":"TN30 6EN",
    "wof:placetype":"postalcode"
},
  "geometry": {"coordinates":[0.689748,51.081533],"type":"Point"}
}