{
  "type": "Feature",
  "properties": {
    "iso:country": "GB",
    "wof:name": "DT1 2AH",
    "wof:placetype": "postalcode"
  },
  "geometry": {"coordinates":[-2.416869,50.708636],"type":"Point"}
}
