{
  "type": "Feature",
  "properties": {
    "iso:country":"GB",
    "wof:name":"DT1 2AH",
    "wof:placetype":"postalcode"
},
  "geometry": {"coordinates":[-2.41670113162161,50.70862804941953],"type":"Point"}
}