{
  "type": "Feature",
  "properties": {
    "iso:country": "GB",
    "wof:name": "LL47 6TN",
    "wof:placetype": "postalcode"
  },
  "geometry": {"coordinates":[-4.089084,52.894248],"type":"Point"}
}
