{
  "type": "Feature",
  "properties": {
    "iso:country":"GB",
    "wof:name":"LL47 6TN",
    "wof:placetype":"postalcode"
},
  "geometry": {"coordinates":[-4.08908359806064,52.89424785092861],"type":"Point"}
}