{
  "type": "Feature",
  "properties": {
    "iso:country":"GB",
    "wof:name":"M32 9QN",
    "wof:placetype":"postalcode"
},
  "geometry": {"coordinates":[-2.33380617946814,53.45276660797273],"type":"Point"}
}