{
  "type": "Feature",
  "properties": {
    "iso:country": "GB",
    "wof:name": "M32 9QN",
    "wof:placetype": "postalcode"
  },
  "geometry": {"coordinates":[-2.333926,53.452738],"type":"Point"}
}
