{
  "type": "Feature",
  "properties": {
    "date:inception_lower": "2004-09-01",
    "date:inception_upper": "2004-09-01",
    "iso:country": "GB",
    "wof:name": "OX4 6GA",
    "wof:placetype": "postalcode"
  },
  "geometry": {"coordinates":[-1.197847,51.727178],"type":"Point"}
}
