{
  "type": "Feature",
  "properties": {
    "iso:country": "GB",
    "wof:name": "DA1 5QY",
    "wof:placetype": "postalcode"
  },
  "geometry": {"coordinates":[0.227891,51.463204],"type":"Point"}
}
