{
  "type": "Feature",
  "properties": {
    "iso:country":"GB",
    "wof:name":"DA1 5QY",
    "wof:placetype":"postalcode"
},
  "geometry": {"coordinates":[0.22789118303817,51.46320363055172],"type":"Point"}
}