{
  "type": "Feature",
  "properties": {
    "iso:country":"GB",
    "wof:name":"RH19 1QE",
    "wof:placetype":"postalcode"
},
  "geometry": {"coordinates":[-0.02884927709317,51.13528825506157],"type":"Point"}
}