{
  "type": "Feature",
  "properties": {
    "date:inception_lower": "1980-01-01",
    "date:inception_upper": "1980-01-01",
    "iso:country": "GB",
    "wof:name": "RH19 1QE",
    "wof:placetype": "postalcode"
  },
  "geometry": {"coordinates":[-0.028849,51.135288],"type":"Point"}
}
