{
  "type": "Feature",
  "properties": {
    "date:inception_lower": "1994-05-01",
    "date:inception_upper": "1994-05-01",
    "iso:country": "GB",
    "wof:name": "M40 3NS",
    "wof:placetype": "postalcode"
  },
  "geometry": {"coordinates":[-2.170943,53.518511],"type":"Point"}
}
