{
  "type": "Feature",
  "properties": {
    "iso:country": "GB",
    "wof:name": "M40 3NS",
    "wof:placetype": "postalcode"
  },
  "geometry": {"coordinates":[-2.170943,53.518511],"type":"Point"}
}
