{
  "type": "Feature",
  "properties": {
    "iso:country":"GB",
    "wof:name":"M40 3NS",
    "wof:placetype":"postalcode"
},
  "geometry": {"coordinates":[-2.17094271619045,53.51851085325504],"type":"Point"}
}