{
  "type": "Feature",
  "properties": {
    "date:inception_lower": "2015-04-01",
    "date:inception_upper": "2015-04-01",
    "iso:country": "GB",
    "wof:name": "LA8 9AN",
    "wof:placetype": "postalcode"
  },
  "geometry": {"coordinates":[-2.818228,54.377683],"type":"Point"}
}
