{
  "type": "Feature",
  "properties": {
    "iso:country":"GB",
    "wof:name":"LA8 9AN",
    "wof:placetype":"postalcode"
},
  "geometry": {"coordinates":[-2.81822795919935,54.37768333124158],"type":"Point"}
}