{
  "type": "Feature",
  "properties": {
    "iso:country":"GB",
    "wof:name":"NR9 4HL",
    "wof:placetype":"postalcode"
},
  "geometry": {"coordinates":[0.98283187854604,52.57984070170865],"type":"Point"}
}