{
  "type": "Feature",
  "properties": {
    "iso:country": "GB",
    "wof:name": "NR9 4HL",
    "wof:placetype": "postalcode"
  },
  "geometry": {"coordinates":[0.982832,52.579841],"type":"Point"}
}
