{
  "type": "Feature",
  "properties": {
    "date:inception_lower": "1980-01-01",
    "date:inception_upper": "1980-01-01",
    "iso:country": "GB",
    "wof:name": "GL7 7AQ",
    "wof:placetype": "postalcode"
  },
  "geometry": {"coordinates":[-2.00694,51.742681],"type":"Point"}
}
