{
  "type": "Feature",
  "properties": {
    "iso:country": "GB",
    "wof:name": "OX44 9EW",
    "wof:placetype": "postalcode"
  },
  "geometry": {"coordinates":[-1.159543,51.718454],"type":"Point"}
}
