{
  "type": "Feature",
  "properties": {
    "date:inception_lower": "1983-08-01",
    "date:inception_upper": "1983-08-01",
    "iso:country": "GB",
    "wof:name": "G66 5EL",
    "wof:placetype": "postalcode"
  },
  "geometry": {"coordinates":[-4.144703,55.921603],"type":"Point"}
}
