{
  "type": "Feature",
  "properties": {
    "iso:country":"GB",
    "wof:name":"G66 5EL",
    "wof:placetype":"postalcode"
},
  "geometry": {"coordinates":[-4.14470322526725,55.92160302475935],"type":"Point"}
}