{
  "type": "Feature",
  "properties": {
    "date:inception_lower": "1980-01-01",
    "date:inception_upper": "1980-01-01",
    "iso:country": "GB",
    "wof:name": "RM3 8YN",
    "wof:placetype": "postalcode"
  },
  "geometry": {"coordinates":[0.223874,51.605542],"type":"Point"}
}
