{
  "type": "Feature",
  "properties": {
    "iso:country":"GB",
    "wof:name":"OL6 7EL",
    "wof:placetype":"postalcode"
},
  "geometry": {"coordinates":[-2.10434666687255,53.48981578558631],"type":"Point"}
}