{
  "type": "Feature",
  "properties": {
    "date:inception_lower": "2000-12-01",
    "date:inception_upper": "2000-12-01",
    "iso:country": "GB",
    "wof:name": "NE11 9ND",
    "wof:placetype": "postalcode"
  },
  "geometry": {"coordinates":[-1.632886,54.945911],"type":"Point"}
}
