{
  "type": "Feature",
  "properties": {
    "date:inception_lower":"2012-09-01",
    "date:inception_upper":"2012-09-30",
    "iso:country":"GB",
    "wof:name":"LE67 6AQ",
    "wof:placetype":"postalcode"
},
  "geometry": {"coordinates":[-1.405827,52.694715],"type":"Point"}
}