{
  "type": "Feature",
  "properties": {
    "iso:country":"GB",
    "wof:name":"NN11 3AZ",
    "wof:placetype":"postalcode"
},
  "geometry": {"coordinates":[-1.18047077849983,52.22557464714647],"type":"Point"}
}