{
  "type": "Feature",
  "properties": {
    "iso:country": "GB",
    "wof:name": "TS19 7SJ",
    "wof:placetype": "postalcode"
  },
  "geometry": {"coordinates":[-1.366141,54.566338],"type":"Point"}
}
