{
  "type": "Feature",
  "properties": {
    "iso:country":"GB",
    "wof:name":"TS19 7SJ",
    "wof:placetype":"postalcode"
},
  "geometry": {"coordinates":[-1.36614095695488,54.56633838290306],"type":"Point"}
}