{
  "type": "Feature",
  "properties": {
    "iso:country": "GB",
    "wof:name": "SN1 4BG",
    "wof:placetype": "postalcode"
  },
  "geometry": {"coordinates":[-1.777303,51.55053],"type":"Point"}
}
