{
  "type": "Feature",
  "properties": {
    "iso:country":"GB",
    "wof:name":"SN1 4BG",
    "wof:placetype":"postalcode"
},
  "geometry": {"coordinates":[-1.77730305284768,51.55052966714695],"type":"Point"}
}