{
  "type": "Feature",
  "properties": {
    "date:inception_lower": "1980-01-01",
    "date:inception_upper": "1980-01-01",
    "iso:country": "GB",
    "wof:name": "SA18 3YF",
    "wof:placetype": "postalcode"
  },
  "geometry": {"coordinates":[-4.003485,51.818033],"type":"Point"}
}
