{
  "type": "Feature",
  "properties": {
    "iso:country":"GB",
    "wof:name":"HP21 7JG",
    "wof:placetype":"postalcode"
},
  "geometry": {"coordinates":[-0.79252398600731,51.81061123770009],"type":"Point"}
}