{
  "type": "Feature",
  "properties": {
    "iso:country": "GB",
    "wof:name": "G21 3PH",
    "wof:placetype": "postalcode"
  },
  "geometry": {"coordinates":[-4.193032,55.890869],"type":"Point"}
}
