{
  "type": "Feature",
  "properties": {
    "date:inception_lower":"1980-01-01",
    "date:inception_upper":"1980-01-31",
    "iso:country":"GB",
    "wof:name":"LS18 4DD",
    "wof:placetype":"postalcode"
},
  "geometry": {"coordinates":[-1.619838,53.836904],"type":"Point"}
}