{
  "type": "Feature",
  "properties": {
    "iso:country":"GB",
    "wof:name":"W1W 6DB",
    "wof:placetype":"postalcode"
},
  "geometry": {"coordinates":[-0.14424865158448,51.52097846621102],"type":"Point"}
}