{
  "type": "Feature",
  "properties": {
    "iso:country":"GB",
    "wof:name":"NW6 4TW",
    "wof:placetype":"postalcode"
},
  "geometry": {"coordinates":[-0.17750299116652,51.54227240045001],"type":"Point"}
}