{
  "type": "Feature",
  "properties": {
    "iso:country": "GB",
    "wof:name": "CV1 5ED",
    "wof:placetype": "postalcode"
  },
  "geometry": {"coordinates":[-1.493856,52.407489],"type":"Point"}
}
