{
  "type": "Feature",
  "properties": {
    "iso:country":"GB",
    "wof:name":"EH54 5QA",
    "wof:placetype":"postalcode"
},
  "geometry": {"coordinates":[-3.50085134281855,55.91852620623901],"type":"Point"}
}