{
  "type": "Feature",
  "properties": {
    "iso:country":"GB",
    "wof:name":"TA1 5AY",
    "wof:placetype":"postalcode"
},
  "geometry": {"coordinates":[-3.1232529032872,51.01949029254232],"type":"Point"}
}