{
  "type": "Feature",
  "properties": {
    "iso:country": "GB",
    "wof:name": "TA1 5AY",
    "wof:placetype": "postalcode"
  },
  "geometry": {"coordinates":[-3.123253,51.01949],"type":"Point"}
}
