{
  "type": "Feature",
  "properties": {
    "iso:country":"GB",
    "wof:name":"ST13 8ND",
    "wof:placetype":"postalcode"
},
  "geometry": {"coordinates":[-2.0430951380417,53.10371651284128],"type":"Point"}
}