{
  "type": "Feature",
  "properties": {
    "iso:country":"GB",
    "wof:name":"DL12 0TQ",
    "wof:placetype":"postalcode"
},
  "geometry": {"coordinates":[-2.07864247406822,54.6225658709872],"type":"Point"}
}