{
  "type": "Feature",
  "properties": {
    "date:inception_lower": "1994-12-01",
    "date:inception_upper": "1994-12-01",
    "iso:country": "GB",
    "wof:name": "UB10 8XB",
    "wof:placetype": "postalcode"
  },
  "geometry": {"coordinates":[-0.442107,51.564374],"type":"Point"}
}
