{
  "type": "Feature",
  "properties": {
    "iso:country":"GB",
    "wof:name":"NW3 7EX",
    "wof:placetype":"postalcode"
},
  "geometry": {"coordinates":[-0.18275512036688,51.5653654301948],"type":"Point"}
}