{
  "type": "Feature",
  "properties": {
    "date:inception_lower":"1999-12-01",
    "date:inception_upper":"1999-12-31",
    "iso:country":"GB",
    "wof:name":"L6 5NA",
    "wof:placetype":"postalcode"
},
  "geometry": {"coordinates":[-2.954075,53.419229],"type":"Point"}
}