{
  "type": "Feature",
  "properties": {
    "iso:country":"GB",
    "wof:name":"RG2 8LA",
    "wof:placetype":"postalcode"
},
  "geometry": {"coordinates":[-0.95662434224817,51.41818636268533],"type":"Point"}
}