{
  "type": "Feature",
  "properties": {
    "iso:country": "GB",
    "wof:name": "RG1 7LF",
    "wof:placetype": "postalcode"
  },
  "geometry": {"coordinates":[-0.979936,51.456301],"type":"Point"}
}
