{
  "type": "Feature",
  "properties": {
    "iso:country":"GB",
    "wof:name":"RG1 7LF",
    "wof:placetype":"postalcode"
},
  "geometry": {"coordinates":[-0.97993585590511,51.4563012562797],"type":"Point"}
}