{
  "type": "Feature",
  "properties": {
    "iso:country": "GB",
    "wof:name": "CW12 2DS",
    "wof:placetype": "postalcode"
  },
  "geometry": {"coordinates":[-2.201637,53.169478],"type":"Point"}
}
