{
  "type": "Feature",
  "properties": {
    "iso:country":"GB",
    "wof:name":"CR0 8EL",
    "wof:placetype":"postalcode"
},
  "geometry": {"coordinates":[-0.03964221210745,51.37582499311505],"type":"Point"}
}