{
  "type": "Feature",
  "properties": {
    "iso:country":"GB",
    "wof:name":"OX28 5JJ",
    "wof:placetype":"postalcode"
},
  "geometry": {"coordinates":[-1.49931404385763,51.77771955326874],"type":"Point"}
}