{
  "type": "Feature",
  "properties": {
    "iso:country":"GB",
    "wof:name":"NE47 5AF",
    "wof:placetype":"postalcode"
},
  "geometry": {"coordinates":[-2.19439200082579,55.00409864330081],"type":"Point"}
}