{
  "type": "Feature",
  "properties": {
    "date:inception_lower": "1980-01-01",
    "date:inception_upper": "1980-01-01",
    "iso:country": "GB",
    "wof:name": "RH3 7BL",
    "wof:placetype": "postalcode"
  },
  "geometry": {"coordinates":[-0.254066,51.249237],"type":"Point"}
}
