{
  "type": "Feature",
  "properties": {
    "date:inception_lower": "1980-01-01",
    "date:inception_upper": "1980-01-01",
    "iso:country": "GB",
    "wof:name": "DY6 8DH",
    "wof:placetype": "postalcode"
  },
  "geometry": {"coordinates":[-2.156069,52.498855],"type":"Point"}
}
