{
  "type": "Feature",
  "properties": {
    "iso:country":"GB",
    "wof:name":"DY6 8DH",
    "wof:placetype":"postalcode"
},
  "geometry": {"coordinates":[-2.15606909899586,52.49885473677832],"type":"Point"}
}