{
  "type": "Feature",
  "properties": {
    "date:inception_lower": "1980-01-01",
    "date:inception_upper": "1980-01-01",
    "iso:country": "GB",
    "wof:name": "DN18 6AX",
    "wof:placetype": "postalcode"
  },
  "geometry": {"coordinates":[-0.43666,53.677269],"type":"Point"}
}
