{
  "type": "Feature",
  "properties": {
    "iso:country":"GB",
    "wof:name":"DT11 8LH",
    "wof:placetype":"postalcode"
},
  "geometry": {"coordinates":[-2.15948767763128,50.95052420322531],"type":"Point"}
}