{
  "type": "Feature",
  "properties": {
    "iso:country": "GB",
    "wof:name": "DT11 8LH",
    "wof:placetype": "postalcode"
  },
  "geometry": {"coordinates":[-2.159488,50.950524],"type":"Point"}
}
