{
  "type": "Feature",
  "properties": {
    "iso:country": "GB",
    "wof:name": "HP9 1LH",
    "wof:placetype": "postalcode"
  },
  "geometry": {"coordinates":[-0.638167,51.605784],"type":"Point"}
}
