{
  "type": "Feature",
  "properties": {
    "iso:country":"GB",
    "wof:name":"HP9 1LH",
    "wof:placetype":"postalcode"
},
  "geometry": {"coordinates":[-0.63816675196614,51.60578400316547],"type":"Point"}
}