{
  "type": "Feature",
  "properties": {
    "date:inception_lower":"2005-02-01",
    "date:inception_upper":"2005-02-28",
    "iso:country":"GB",
    "wof:name":"SO40 0SN",
    "wof:placetype":"postalcode"
},
  "geometry": {"coordinates":[-1.570615,50.8701],"type":"Point"}
}