{
  "type": "Feature",
  "properties": {
    "iso:country":"GB",
    "wof:name":"NE4 9NQ",
    "wof:placetype":"postalcode"
},
  "geometry": {"coordinates":[-1.65403143841721,54.97959030680198],"type":"Point"}
}