{
  "type": "Feature",
  "properties": {
    "iso:country":"GB",
    "wof:name":"DL9 4UX",
    "wof:placetype":"postalcode"
},
  "geometry": {"coordinates":[-1.68889247908613,54.38234918309411],"type":"Point"}
}