{
  "type": "Feature",
  "properties": {
    "date:inception_lower": "1990-02-01",
    "date:inception_upper": "1990-02-01",
    "iso:country": "GB",
    "wof:name": "YO25 9DJ",
    "wof:placetype": "postalcode"
  },
  "geometry": {"coordinates":[-0.461141,53.999237],"type":"Point"}
}
