{
  "type": "Feature",
  "properties": {
    "date:inception_lower":"2004-11-01",
    "date:inception_upper":"2004-11-30",
    "iso:country":"GB",
    "wof:name":"BD15 7UB",
    "wof:placetype":"postalcode"
},
  "geometry": {"coordinates":[-1.829008,53.796264],"type":"Point"}
}