{
  "type": "Feature",
  "properties": {
    "iso:country": "GB",
    "wof:name": "BD15 7UB",
    "wof:placetype": "postalcode"
  },
  "geometry": {"coordinates":[-1.829008,53.796264],"type":"Point"}
}
