{
  "type": "Feature",
  "properties": {
    "iso:country":"GB",
    "wof:name":"LE4 9LZ",
    "wof:placetype":"postalcode"
},
  "geometry": {"coordinates":[-1.08586884613277,52.65982219775729],"type":"Point"}
}