{
  "type": "Feature",
  "properties": {
    "date:inception_lower": "2016-10-01",
    "date:inception_upper": "2016-10-01",
    "iso:country": "GB",
    "wof:name": "G2 1AP",
    "wof:placetype": "postalcode"
  },
  "geometry": {"coordinates":[-4.255169,55.862806],"type":"Point"}
}
