{
  "type": "Feature",
  "properties": {
    "date:inception_lower":"2004-05-01",
    "date:inception_upper":"2004-05-31",
    "iso:country":"GB",
    "wof:name":"DL16 6GD",
    "wof:placetype":"postalcode"
},
  "geometry": {"coordinates":[-1.588359,54.704319],"type":"Point"}
}