{
  "type": "Feature",
  "properties": {
    "iso:country":"GB",
    "wof:name":"DL16 6GD",
    "wof:placetype":"postalcode"
},
  "geometry": {"coordinates":[-1.58835912719367,54.70431915481643],"type":"Point"}
}