{
  "type": "Feature",
  "properties": {
    "iso:country": "GB",
    "wof:name": "DL16 6GD",
    "wof:placetype": "postalcode"
  },
  "geometry": {"coordinates":[-1.588359,54.704319],"type":"Point"}
}
