{
  "type": "Feature",
  "properties": {
    "date:inception_lower": "2002-06-01",
    "date:inception_upper": "2002-06-01",
    "iso:country": "GB",
    "wof:name": "SR5 1PQ",
    "wof:placetype": "postalcode"
  },
  "geometry": {"coordinates":[-1.394666,54.926501],"type":"Point"}
}
