{
  "type": "Feature",
  "properties": {
    "iso:country":"GB",
    "wof:name":"SR5 1PQ",
    "wof:placetype":"postalcode"
},
  "geometry": {"coordinates":[-1.39466630758854,54.92650051023735],"type":"Point"}
}