{
  "type": "Feature",
  "properties": {
    "iso:country":"GB",
    "wof:name":"EC1M 6DR",
    "wof:placetype":"postalcode"
},
  "geometry": {"coordinates":[-0.10223582517351,51.5201533722166],"type":"Point"}
}