{
  "type": "Feature",
  "properties": {
    "iso:country":"GB",
    "wof:name":"CH8 9LL",
    "wof:placetype":"postalcode"
},
  "geometry": {"coordinates":[-3.33717672148211,53.33655455398434],"type":"Point"}
}