{
  "type": "Feature",
  "properties": {
    "date:inception_lower": "1980-01-01",
    "date:inception_upper": "1980-01-01",
    "iso:country": "GB",
    "wof:name": "EX8 4PW",
    "wof:placetype": "postalcode"
  },
  "geometry": {"coordinates":[-3.397567,50.638247],"type":"Point"}
}
