{
  "type": "Feature",
  "properties": {
    "iso:country": "GB",
    "wof:name": "GL54 4DU",
    "wof:placetype": "postalcode"
  },
  "geometry": {"coordinates":[-1.925267,51.854645],"type":"Point"}
}
