{
  "type": "Feature",
  "properties": {
    "iso:country":"GB",
    "wof:name":"GL54 4DU",
    "wof:placetype":"postalcode"
},
  "geometry": {"coordinates":[-1.92526678127084,51.85464479225978],"type":"Point"}
}