{
  "type": "Feature",
  "properties": {
    "date:inception_lower": "2013-11-01",
    "date:inception_upper": "2013-11-01",
    "iso:country": "GB",
    "wof:name": "WF4 2FJ",
    "wof:placetype": "postalcode"
  },
  "geometry": {"coordinates":[-1.408026,53.625119],"type":"Point"}
}
