{
  "type": "Feature",
  "properties": {
    "iso:country": "GB",
    "wof:name": "WF4 2FJ",
    "wof:placetype": "postalcode"
  },
  "geometry": {"coordinates":[-1.407074,53.624936],"type":"Point"}
}
