{
  "type": "Feature",
  "properties": {
    "iso:country":"GB",
    "wof:name":"WF4 2FJ",
    "wof:placetype":"postalcode"
},
  "geometry": {"coordinates":[-1.40707401289984,53.6249359340913],"type":"Point"}
}