{
  "type": "Feature",
  "properties": {
    "iso:country": "GB",
    "wof:name": "CB4 2QY",
    "wof:placetype": "postalcode"
  },
  "geometry": {"coordinates":[0.135074,52.22862],"type":"Point"}
}
