{
  "type": "Feature",
  "properties": {
    "iso:country":"GB",
    "wof:name":"CB4 2QY",
    "wof:placetype":"postalcode"
},
  "geometry": {"coordinates":[0.13507443822363,52.2286197255937],"type":"Point"}
}