{
  "type": "Feature",
  "properties": {
    "iso:country":"GB",
    "wof:name":"PO12 4BT",
    "wof:placetype":"postalcode"
},
  "geometry": {"coordinates":[-1.14592445359569,50.81329763310688],"type":"Point"}
}