{
  "type": "Feature",
  "properties": {
    "iso:country": "GB",
    "wof:name": "NW7 4QH",
    "wof:placetype": "postalcode"
  },
  "geometry": {"coordinates":[-0.251435,51.623986],"type":"Point"}
}
