{
  "type": "Feature",
  "properties": {
    "date:inception_lower": "1980-01-01",
    "date:inception_upper": "1980-01-01",
    "iso:country": "GB",
    "wof:name": "NW7 4QH",
    "wof:placetype": "postalcode"
  },
  "geometry": {"coordinates":[-0.251435,51.623986],"type":"Point"}
}
