{
  "type": "Feature",
  "properties": {
    "iso:country":"GB",
    "wof:name":"SK2 6EY",
    "wof:placetype":"postalcode"
},
  "geometry": {"coordinates":[-2.14947522158157,53.39259306091412],"type":"Point"}
}