{
  "type": "Feature",
  "properties": {
    "date:inception_lower":"2014-10-01",
    "date:inception_upper":"2014-10-31",
    "iso:country":"GB",
    "wof:name":"SG16 6FU",
    "wof:placetype":"postalcode"
},
  "geometry": {"coordinates":[-0.308876,52.005779],"type":"Point"}
}