{
  "type": "Feature",
  "properties": {
    "date:inception_lower": "2014-10-01",
    "date:inception_upper": "2014-10-01",
    "iso:country": "GB",
    "wof:name": "SG16 6FU",
    "wof:placetype": "postalcode"
  },
  "geometry": {"coordinates":[-0.309426,52.00549],"type":"Point"}
}
