{
  "type": "Feature",
  "properties": {
    "iso:country": "GB",
    "wof:name": "PL21 0YE",
    "wof:placetype": "postalcode"
  },
  "geometry": {"coordinates":[-3.914418,50.385724],"type":"Point"}
}
