{
  "type": "Feature",
  "properties": {
    "iso:country":"GB",
    "wof:name":"DY13 0JQ",
    "wof:placetype":"postalcode"
},
  "geometry": {"coordinates":[-2.28685694912787,52.32624268415853],"type":"Point"}
}