{
  "type": "Feature",
  "properties": {
    "iso:country": "GB",
    "wof:name": "MK18 5LA",
    "wof:placetype": "postalcode"
  },
  "geometry": {"coordinates":[-1.028082,52.036115],"type":"Point"}
}
