{
  "type": "Feature",
  "properties": {
    "iso:country": "GB",
    "wof:name": "BB7 1QS",
    "wof:placetype": "postalcode"
  },
  "geometry": {"coordinates":[-2.373973,53.880531],"type":"Point"}
}
