{
  "type": "Feature",
  "properties": {
    "iso:country":"GB",
    "wof:name":"BB7 1QS",
    "wof:placetype":"postalcode"
},
  "geometry": {"coordinates":[-2.37397344380754,53.88053131074725],"type":"Point"}
}