{
  "type": "Feature",
  "properties": {
    "date:inception_lower": "2016-08-01",
    "date:inception_upper": "2016-08-01",
    "iso:country": "GB",
    "wof:name": "G77 6ZH",
    "wof:placetype": "postalcode"
  },
  "geometry": {"coordinates":[-4.347658,55.78708],"type":"Point"}
}
