{
  "type": "Feature",
  "properties": {
    "iso:country": "GB",
    "wof:name": "G77 6ZH",
    "wof:placetype": "postalcode"
  },
  "geometry": {"coordinates":[-4.347658,55.78708],"type":"Point"}
}
