{
  "type": "Feature",
  "properties": {
    "iso:country":"GB",
    "wof:name":"LS14 3JE",
    "wof:placetype":"postalcode"
},
  "geometry": {"coordinates":[-1.45581298350832,53.86736213737611],"type":"Point"}
}