{
  "type": "Feature",
  "properties": {
    "iso:country": "GB",
    "wof:name": "SE16 7PS",
    "wof:placetype": "postalcode"
  },
  "geometry": {"coordinates":[-0.042867,51.495518],"type":"Point"}
}
