{
  "type": "Feature",
  "properties": {
    "iso:country":"GB",
    "wof:name":"W1T 1RW",
    "wof:placetype":"postalcode"
},
  "geometry": {"coordinates":[-0.13519205600442,51.51861368261688],"type":"Point"}
}