{
  "type": "Feature",
  "properties": {
    "date:inception_lower":"2005-02-01",
    "date:inception_upper":"2005-02-28",
    "iso:country":"GB",
    "wof:name":"B74 2AE",
    "wof:placetype":"postalcode"
},
  "geometry": {"coordinates":[-1.889134,52.571428],"type":"Point"}
}