{
  "type": "Feature",
  "properties": {
    "date:inception_lower": "2006-03-01",
    "date:inception_upper": "2006-03-01",
    "iso:country": "GB",
    "wof:name": "CA11 8SB",
    "wof:placetype": "postalcode"
  },
  "geometry": {"coordinates":[-2.72456,54.677615],"type":"Point"}
}
