{
  "type": "Feature",
  "properties": {
    "iso:country":"GB",
    "wof:name":"SY16 4AZ",
    "wof:placetype":"postalcode"
},
  "geometry": {"coordinates":[-3.31806277272746,52.46587376837522],"type":"Point"}
}