{
  "type": "Feature",
  "properties": {
    "date:inception_lower": "2009-08-01",
    "date:inception_upper": "2009-08-01",
    "iso:country": "GB",
    "wof:name": "CF3 3PY",
    "wof:placetype": "postalcode"
  },
  "geometry": {"coordinates":[-3.11635,51.514641],"type":"Point"}
}
