{
  "type": "Feature",
  "properties": {
    "iso:country":"GB",
    "wof:name":"CF3 3PY",
    "wof:placetype":"postalcode"
},
  "geometry": {"coordinates":[-3.11641397088846,51.51467497387308],"type":"Point"}
}