{
  "type": "Feature",
  "properties": {
    "iso:country": "GB",
    "wof:name": "FK8 2EJ",
    "wof:placetype": "postalcode"
  },
  "geometry": {"coordinates":[-3.936584,56.117367],"type":"Point"}
}
