{
  "type": "Feature",
  "properties": {
    "iso:country":"GB",
    "wof:name":"OL8 4LN",
    "wof:placetype":"postalcode"
},
  "geometry": {"coordinates":[-2.13455270955386,53.52868732276745],"type":"Point"}
}