{
  "type": "Feature",
  "properties": {
    "iso:country":"GB",
    "wof:name":"BH10 4BA",
    "wof:placetype":"postalcode"
},
  "geometry": {"coordinates":[-1.89985889027603,50.75059819187684],"type":"Point"}
}