{
  "type": "Feature",
  "properties": {
    "iso:country":"GB",
    "wof:name":"BL0 9UT",
    "wof:placetype":"postalcode"
},
  "geometry": {"coordinates":[-2.32619467827976,53.62642533087105],"type":"Point"}
}