{
  "type": "Feature",
  "properties": {
    "iso:country":"GB",
    "wof:name":"SE9 3QW",
    "wof:placetype":"postalcode"
},
  "geometry": {"coordinates":[0.06450985738753,51.43690518205312],"type":"Point"}
}