{
  "type": "Feature",
  "properties": {
    "iso:country": "GB",
    "wof:name": "BN2 7JB",
    "wof:placetype": "postalcode"
  },
  "geometry": {"coordinates":[-0.058474,50.80414],"type":"Point"}
}
