{
  "type": "Feature",
  "properties": {
    "iso:country":"GB",
    "wof:name":"DN14 5FG",
    "wof:placetype":"postalcode"
},
  "geometry": {"coordinates":[-0.85028227946422,53.7275345808271],"type":"Point"}
}