{
  "type": "Feature",
  "properties": {
    "date:inception_lower": "1980-01-01",
    "date:inception_upper": "1980-01-01",
    "iso:country": "GB",
    "wof:name": "SK14 8LZ",
    "wof:placetype": "postalcode"
  },
  "geometry": {"coordinates":[-2.000805,53.460056],"type":"Point"}
}
