{
  "type": "Feature",
  "properties": {
    "iso:country":"GB",
    "wof:name":"SK14 8LZ",
    "wof:placetype":"postalcode"
},
  "geometry": {"coordinates":[-2.00080465611315,53.46005587880377],"type":"Point"}
}