{
  "type": "Feature",
  "properties": {
    "iso:country":"GB",
    "wof:name":"DH9 9BA",
    "wof:placetype":"postalcode"
},
  "geometry": {"coordinates":[-1.75141819657309,54.87570394781894],"type":"Point"}
}