{
  "type": "Feature",
  "properties": {
    "date:inception_lower": "1999-06-01",
    "date:inception_upper": "1999-06-01",
    "iso:country": "GB",
    "wof:name": "B79 7YE",
    "wof:placetype": "postalcode"
  },
  "geometry": {"coordinates":[-1.719984,52.638878],"type":"Point"}
}
