{
  "type": "Feature",
  "properties": {
    "iso:country":"GB",
    "wof:name":"WA15 8NP",
    "wof:placetype":"postalcode"
},
  "geometry": {"coordinates":[-2.31967196303536,53.38135513670571],"type":"Point"}
}