{
  "type": "Feature",
  "properties": {
    "iso:country":"GB",
    "wof:name":"EH27 8EQ",
    "wof:placetype":"postalcode"
},
  "geometry": {"coordinates":[-3.36845898385848,55.909141953218],"type":"Point"}
}