{
  "type": "Feature",
  "properties": {
    "date:inception_lower": "2016-01-01",
    "date:inception_upper": "2016-01-01",
    "iso:country": "GB",
    "wof:name": "EH27 8EQ",
    "wof:placetype": "postalcode"
  },
  "geometry": {"coordinates":[-3.40961,55.915444],"type":"Point"}
}
