{
  "type": "Feature",
  "properties": {
    "iso:country": "GB",
    "wof:name": "EH27 8EQ",
    "wof:placetype": "postalcode"
  },
  "geometry": {"coordinates":[-3.40961,55.915444],"type":"Point"}
}
