{
  "type": "Feature",
  "properties": {
    "iso:country":"GB",
    "wof:name":"DG7 3TF",
    "wof:placetype":"postalcode"
},
  "geometry": {"coordinates":[-4.25288534903002,55.2120419602015],"type":"Point"}
}