{
  "type": "Feature",
  "properties": {
    "date:inception_lower": "1997-06-01",
    "date:inception_upper": "1997-06-01",
    "iso:country": "GB",
    "wof:name": "WR4 0NQ",
    "wof:placetype": "postalcode"
  },
  "geometry": {"coordinates":[-2.172019,52.203398],"type":"Point"}
}
