{
  "type": "Feature",
  "properties": {
    "iso:country":"GB",
    "wof:name":"W1K 2QL",
    "wof:placetype":"postalcode"
},
  "geometry": {"coordinates":[-0.15195518066218,51.50935594547725],"type":"Point"}
}