{
  "type": "Feature",
  "properties": {
    "iso:country":"GB",
    "wof:name":"CB21 4TA",
    "wof:placetype":"postalcode"
},
  "geometry": {"coordinates":[0.38098391690666,52.06616031195621],"type":"Point"}
}