{
  "type": "Feature",
  "properties": {
    "iso:country":"GB",
    "wof:name":"KY2 6UZ",
    "wof:placetype":"postalcode"
},
  "geometry": {"coordinates":[-3.2013608135335,56.12543887515891],"type":"Point"}
}