{
  "type": "Feature",
  "properties": {
    "iso:country": "GB",
    "wof:name": "KY2 6UZ",
    "wof:placetype": "postalcode"
  },
  "geometry": {"coordinates":[-3.201361,56.125439],"type":"Point"}
}
