{
  "type": "Feature",
  "properties": {
    "date:inception_lower": "1980-01-01",
    "date:inception_upper": "1980-01-01",
    "iso:country": "GB",
    "wof:name": "B6 7SJ",
    "wof:placetype": "postalcode"
  },
  "geometry": {"coordinates":[-1.865558,52.506349],"type":"Point"}
}
