{
  "type": "Feature",
  "properties": {
    "iso:country": "GB",
    "wof:name": "WA15 6XW",
    "wof:placetype": "postalcode"
  },
  "geometry": {"coordinates":[-2.315358,53.399721],"type":"Point"}
}
