{
  "type": "Feature",
  "properties": {
    "date:inception_lower":"1980-01-01",
    "date:inception_upper":"1980-01-31",
    "iso:country":"GB",
    "wof:name":"SN3 3AE",
    "wof:placetype":"postalcode"
},
  "geometry": {"coordinates":[-1.761525,51.559257],"type":"Point"}
}