{
  "type": "Feature",
  "properties": {
    "iso:country":"GB",
    "wof:name":"SL1 9JL",
    "wof:placetype":"postalcode"
},
  "geometry": {"coordinates":[-0.62452975137423,51.50647964936425],"type":"Point"}
}