{
  "type": "Feature",
  "properties": {
    "date:inception_lower": "1980-01-01",
    "date:inception_upper": "1980-01-01",
    "iso:country": "GB",
    "wof:name": "CF42 5PD",
    "wof:placetype": "postalcode"
  },
  "geometry": {"coordinates":[-3.533855,51.673433],"type":"Point"}
}
