{
  "type": "Feature",
  "properties": {
    "date:inception_lower": "1980-01-01",
    "date:inception_upper": "1980-01-01",
    "iso:country": "GB",
    "wof:name": "SK14 3EH",
    "wof:placetype": "postalcode"
  },
  "geometry": {"coordinates":[-2.027426,53.450228],"type":"Point"}
}
