{
  "type": "Feature",
  "properties": {
    "iso:country": "GB",
    "wof:name": "SK14 3EH",
    "wof:placetype": "postalcode"
  },
  "geometry": {"coordinates":[-2.027426,53.450228],"type":"Point"}
}
