{
  "type": "Feature",
  "properties": {
    "iso:country":"GB",
    "wof:name":"SK14 3EH",
    "wof:placetype":"postalcode"
},
  "geometry": {"coordinates":[-2.02742604982245,53.45022827377943],"type":"Point"}
}