{
  "type": "Feature",
  "properties": {
    "iso:country":"GB",
    "wof:name":"LS19 6EU",
    "wof:placetype":"postalcode"
},
  "geometry": {"coordinates":[-1.67999889076403,53.85486662067734],"type":"Point"}
}