{
  "type": "Feature",
  "properties": {
    "iso:country":"GB",
    "wof:name":"IP29 5DD",
    "wof:placetype":"postalcode"
},
  "geometry": {"coordinates":[0.59643534132317,52.24575295258033],"type":"Point"}
}