{
  "type": "Feature",
  "properties": {
    "iso:country":"GB",
    "wof:name":"N9 0JS",
    "wof:placetype":"postalcode"
},
  "geometry": {"coordinates":[-0.05063979417247,51.62724454165075],"type":"Point"}
}