{
  "type": "Feature",
  "properties": {
    "iso:country": "GB",
    "wof:name": "N9 0JS",
    "wof:placetype": "postalcode"
  },
  "geometry": {"coordinates":[-0.05064,51.627245],"type":"Point"}
}
