{
  "type": "Feature",
  "properties": {
    "date:inception_lower": "1980-01-01",
    "date:inception_upper": "1980-01-01",
    "iso:country": "GB",
    "wof:name": "TF2 7JA",
    "wof:placetype": "postalcode"
  },
  "geometry": {"coordinates":[-2.44182,52.709723],"type":"Point"}
}
