{
  "type": "Feature",
  "properties": {
    "iso:country":"GB",
    "wof:name":"LA3 1NS",
    "wof:placetype":"postalcode"
},
  "geometry": {"coordinates":[-2.89188456796641,54.0584678352967],"type":"Point"}
}