{
  "type": "Feature",
  "properties": {
    "iso:country":"GB",
    "wof:name":"TW13 5AN",
    "wof:placetype":"postalcode"
},
  "geometry": {"coordinates":[-0.40536106719961,51.44628919379728],"type":"Point"}
}