{
  "type": "Feature",
  "properties": {
    "iso:country":"GB",
    "wof:name":"KW8 6LA",
    "wof:placetype":"postalcode"
},
  "geometry": {"coordinates":[-3.64630645668605,58.11510960832515],"type":"Point"}
}