{
  "type": "Feature",
  "properties": {
    "iso:country":"GB",
    "wof:name":"OX16 3LF",
    "wof:placetype":"postalcode"
},
  "geometry": {"coordinates":[-1.32536715996295,52.06573911423307],"type":"Point"}
}