{
  "type": "Feature",
  "properties": {
    "iso:country":"GB",
    "wof:name":"GU2 8AH",
    "wof:placetype":"postalcode"
},
  "geometry": {"coordinates":[-0.59390889880287,51.25092564505279],"type":"Point"}
}