{
  "type": "Feature",
  "properties": {
    "iso:country":"GB",
    "wof:name":"HD9 7RW",
    "wof:placetype":"postalcode"
},
  "geometry": {"coordinates":[-1.77841502391819,53.58434912796057],"type":"Point"}
}