{
  "type": "Feature",
  "properties": {
    "iso:country": "GB",
    "wof:name": "NP4 5BA",
    "wof:placetype": "postalcode"
  },
  "geometry": {"coordinates":[-3.030527,51.684486],"type":"Point"}
}
