{
  "type": "Feature",
  "properties": {
    "iso:country": "GB",
    "wof:name": "HD8 0LE",
    "wof:placetype": "postalcode"
  },
  "geometry": {"coordinates":[-1.719314,53.624922],"type":"Point"}
}
