{
  "type": "Feature",
  "properties": {
    "date:inception_lower": "1994-05-01",
    "date:inception_upper": "1994-05-01",
    "iso:country": "GB",
    "wof:name": "M5 4HZ",
    "wof:placetype": "postalcode"
  },
  "geometry": {"coordinates":[-2.285134,53.481422],"type":"Point"}
}
