{
  "type": "Feature",
  "properties": {
    "iso:country":"GB",
    "wof:name":"M5 4HZ",
    "wof:placetype":"postalcode"
},
  "geometry": {"coordinates":[-2.28513365157913,53.48142224202521],"type":"Point"}
}