{
  "type": "Feature",
  "properties": {
    "iso:country":"GB",
    "wof:name":"W13 0AW",
    "wof:placetype":"postalcode"
},
  "geometry": {"coordinates":[-0.33301121559183,51.52749070023834],"type":"Point"}
}