{
  "type": "Feature",
  "properties": {
    "date:inception_lower": "2023-04-01",
    "date:inception_upper": "2023-04-01",
    "iso:country": "GB",
    "wof:name": "SK10 3PF",
    "wof:placetype": "postalcode"
  },
  "geometry": {"coordinates":[-2.172199,53.259835],"type":"Point"}
}
