{
  "type": "Feature",
  "properties": {
    "iso:country": "GB",
    "wof:name": "DG5 4DP",
    "wof:placetype": "postalcode"
  },
  "geometry": {"coordinates":[-3.819539,54.928807],"type":"Point"}
}
