{
  "type": "Feature",
  "properties": {
    "iso:country":"GB",
    "wof:name":"DG5 4DP",
    "wof:placetype":"postalcode"
},
  "geometry": {"coordinates":[-3.81953872948445,54.92880728737852],"type":"Point"}
}