{
  "type": "Feature",
  "properties": {
    "iso:country":"GB",
    "wof:name":"BA16 0QT",
    "wof:placetype":"postalcode"
},
  "geometry": {"coordinates":[-2.74360975751176,51.11806694050986],"type":"Point"}
}