{
  "type": "Feature",
  "properties": {
    "iso:country":"GB",
    "wof:name":"TR7 3HE",
    "wof:placetype":"postalcode"
},
  "geometry": {"coordinates":[-5.04371707075138,50.4217812339385],"type":"Point"}
}