{
  "type": "Feature",
  "properties": {
    "date:inception_lower": "2000-10-01",
    "date:inception_upper": "2000-10-01",
    "iso:country": "GB",
    "wof:name": "OX26 4FT",
    "wof:placetype": "postalcode"
  },
  "geometry": {"coordinates":[-1.137232,51.910938],"type":"Point"}
}
