{
  "type": "Feature",
  "properties": {
    "iso:country":"GB",
    "wof:name":"BA5 2JG",
    "wof:placetype":"postalcode"
},
  "geometry": {"coordinates":[-2.66068852807946,51.21228076667288],"type":"Point"}
}