{
  "type": "Feature",
  "properties": {
    "iso:country": "GB",
    "wof:name": "GL15 5FS",
    "wof:placetype": "postalcode"
  },
  "geometry": {"coordinates":[-2.515956,51.730677],"type":"Point"}
}
