{
  "type": "Feature",
  "properties": {
    "date:inception_lower": "1998-12-01",
    "date:inception_upper": "1998-12-01",
    "iso:country": "GB",
    "wof:name": "DH6 1RD",
    "wof:placetype": "postalcode"
  },
  "geometry": {"coordinates":[-1.472882,54.788383],"type":"Point"}
}
