{
  "type": "Feature",
  "properties": {
    "iso:country":"GB",
    "wof:name":"DH6 1RD",
    "wof:placetype":"postalcode"
},
  "geometry": {"coordinates":[-1.47288230111992,54.78838280369493],"type":"Point"}
}