{
  "type": "Feature",
  "properties": {
    "iso:country": "GB",
    "wof:name": "PL27 9DF",
    "wof:placetype": "postalcode"
  },
  "geometry": {"coordinates":[-4.836427,50.515663],"type":"Point"}
}
