{
  "type": "Feature",
  "properties": {
    "date:inception_lower": "1981-06-01",
    "date:inception_upper": "1981-06-01",
    "iso:country": "GB",
    "wof:name": "B4 7LA",
    "wof:placetype": "postalcode"
  },
  "geometry": {"coordinates":[-1.893437,52.482063],"type":"Point"}
}
