{
  "type": "Feature",
  "properties": {
    "iso:country":"GB",
    "wof:name":"TS6 9AP",
    "wof:placetype":"postalcode"
},
  "geometry": {"coordinates":[-1.15436589662966,54.56610471632778],"type":"Point"}
}