{
  "type": "Feature",
  "properties": {
    "iso:country": "GB",
    "wof:name": "B43 7EN",
    "wof:placetype": "postalcode"
  },
  "geometry": {"coordinates":[-1.898349,52.555065],"type":"Point"}
}
