{
  "type": "Feature",
  "properties": {
    "iso:country":"GB",
    "wof:name":"B43 7EN",
    "wof:placetype":"postalcode"
},
  "geometry": {"coordinates":[-1.89834924610027,52.55506541941078],"type":"Point"}
}