{
  "type": "Feature",
  "properties": {
    "date:inception_lower": "1980-01-01",
    "date:inception_upper": "1980-01-01",
    "iso:country": "GB",
    "wof:name": "CT8 8RN",
    "wof:placetype": "postalcode"
  },
  "geometry": {"coordinates":[1.337,51.382283],"type":"Point"}
}
