{
  "type": "Feature",
  "properties": {
    "iso:country": "GB",
    "wof:name": "TR11 5GD",
    "wof:placetype": "postalcode"
  },
  "geometry": {"coordinates":[-5.084858,50.143574],"type":"Point"}
}
