{
  "type": "Feature",
  "properties": {
    "date:inception_lower": "2012-02-01",
    "date:inception_upper": "2012-02-01",
    "iso:country": "GB",
    "wof:name": "TR11 5GD",
    "wof:placetype": "postalcode"
  },
  "geometry": {"coordinates":[-5.084858,50.143574],"type":"Point"}
}
