{
  "type": "Feature",
  "properties": {
    "iso:country":"GB",
    "wof:name":"TR11 5GD",
    "wof:placetype":"postalcode"
},
  "geometry": {"coordinates":[-5.08485754823722,50.14357395614341],"type":"Point"}
}