{
  "type": "Feature",
  "properties": {
    "iso:country":"GB",
    "wof:name":"BH8 9AB",
    "wof:placetype":"postalcode"
},
  "geometry": {"coordinates":[-1.84825890765414,50.73404108849541],"type":"Point"}
}