{
  "type": "Feature",
  "properties": {
    "iso:country":"GB",
    "wof:name":"WF3 1UB",
    "wof:placetype":"postalcode"
},
  "geometry": {"coordinates":[-1.57044430072633,53.72756864540916],"type":"Point"}
}