{
  "type": "Feature",
  "properties": {
    "date:inception_lower": "1993-01-01",
    "date:inception_upper": "1993-01-01",
    "iso:country": "GB",
    "wof:name": "SP9 7XY",
    "wof:placetype": "postalcode"
  },
  "geometry": {"coordinates":[-1.654122,51.239821],"type":"Point"}
}
