{
  "type": "Feature",
  "properties": {
    "iso:country":"GB",
    "wof:name":"MK18 2LP",
    "wof:placetype":"postalcode"
},
  "geometry": {"coordinates":[-0.93481934736158,51.91536760142024],"type":"Point"}
}