{
  "type": "Feature",
  "properties": {
    "iso:country":"GB",
    "wof:name":"PO7 5JX",
    "wof:placetype":"postalcode"
},
  "geometry": {"coordinates":[-1.04338792729642,50.86944419312601],"type":"Point"}
}