{
  "type": "Feature",
  "properties": {
    "iso:country":"GB",
    "wof:name":"SS14 2PX",
    "wof:placetype":"postalcode"
},
  "geometry": {"coordinates":[0.47363428395396,51.57483746197621],"type":"Point"}
}