{
  "type": "Feature",
  "properties": {
    "iso:country":"GB",
    "wof:name":"RM4 1PP",
    "wof:placetype":"postalcode"
},
  "geometry": {"coordinates":[0.18261450367203,51.61784251855291],"type":"Point"}
}