{
  "type": "Feature",
  "properties": {
    "date:inception_lower": "1996-06-01",
    "date:inception_upper": "1996-06-01",
    "iso:country": "GB",
    "wof:name": "GU47 8LF",
    "wof:placetype": "postalcode"
  },
  "geometry": {"coordinates":[-0.806207,51.354266],"type":"Point"}
}
