{
  "type": "Feature",
  "properties": {
    "iso:country":"GB",
    "wof:name":"TR18 5HJ",
    "wof:placetype":"postalcode"
},
  "geometry": {"coordinates":[-5.55008443809832,50.10655354424269],"type":"Point"}
}