{
  "type": "Feature",
  "properties": {
    "iso:country": "GB",
    "wof:name": "BN2 8EE",
    "wof:placetype": "postalcode"
  },
  "geometry": {"coordinates":[-0.036307,50.800366],"type":"Point"}
}
