{
  "type": "Feature",
  "properties": {
    "iso:country":"GB",
    "wof:name":"BN2 8EE",
    "wof:placetype":"postalcode"
},
  "geometry": {"coordinates":[-0.03630670265702,50.80036556601887],"type":"Point"}
}