{
  "type": "Feature",
  "properties": {
    "iso:country":"GB",
    "wof:name":"BL6 5SW",
    "wof:placetype":"postalcode"
},
  "geometry": {"coordinates":[-2.56977591708094,53.58105667797391],"type":"Point"}
}