{
  "type": "Feature",
  "properties": {
    "iso:country":"GB",
    "wof:name":"M19 1JD",
    "wof:placetype":"postalcode"
},
  "geometry": {"coordinates":[-2.19506435271239,53.4279420997936],"type":"Point"}
}