{
  "type": "Feature",
  "properties": {
    "iso:country": "GB",
    "wof:name": "NE2 2SU",
    "wof:placetype": "postalcode"
  },
  "geometry": {"coordinates":[-1.606837,54.991722],"type":"Point"}
}
