{
  "type": "Feature",
  "properties": {
    "iso:country":"GB",
    "wof:name":"NE2 2SU",
    "wof:placetype":"postalcode"
},
  "geometry": {"coordinates":[-1.60683664262176,54.99172223868215],"type":"Point"}
}