{
  "type": "Feature",
  "properties": {
    "iso:country":"GB",
    "wof:name":"EH26 0PQ",
    "wof:placetype":"postalcode"
},
  "geometry": {"coordinates":[-3.20657807993542,55.86268096341404],"type":"Point"}
}