{
  "type": "Feature",
  "properties": {
    "date:inception_lower": "1980-01-01",
    "date:inception_upper": "1980-01-01",
    "iso:country": "GB",
    "wof:name": "L37 2HQ",
    "wof:placetype": "postalcode"
  },
  "geometry": {"coordinates":[-3.075911,53.55139],"type":"Point"}
}
