{
  "type": "Feature",
  "properties": {
    "iso:country":"GB",
    "wof:name":"L37 2HQ",
    "wof:placetype":"postalcode"
},
  "geometry": {"coordinates":[-3.07591153605343,53.55139013960611],"type":"Point"}
}