{
  "type": "Feature",
  "properties": {
    "iso:country":"GB",
    "wof:name":"M40 2UJ",
    "wof:placetype":"postalcode"
},
  "geometry": {"coordinates":[-2.1835680035872,53.49455597544788],"type":"Point"}
}