{
  "type": "Feature",
  "properties": {
    "iso:country":"GB",
    "wof:name":"SN4 0HT",
    "wof:placetype":"postalcode"
},
  "geometry": {"coordinates":[-1.72561825104586,51.51143343706735],"type":"Point"}
}