{
  "type": "Feature",
  "properties": {
    "iso:country":"GB",
    "wof:name":"HX6 1HQ",
    "wof:placetype":"postalcode"
},
  "geometry": {"coordinates":[-1.93894849155887,53.70274205920806],"type":"Point"}
}