{
  "type": "Feature",
  "properties": {
    "iso:country": "GB",
    "wof:name": "DG8 9DF",
    "wof:placetype": "postalcode"
  },
  "geometry": {"coordinates":[-4.449937,54.8154],"type":"Point"}
}
