{
  "type": "Feature",
  "properties": {
    "iso:country":"GB",
    "wof:name":"WV4 4BJ",
    "wof:placetype":"postalcode"
},
  "geometry": {"coordinates":[-2.15668058990773,52.5671321079387],"type":"Point"}
}