{
  "type": "Feature",
  "properties": {
    "iso:country": "GB",
    "wof:name": "WV4 4BJ",
    "wof:placetype": "postalcode"
  },
  "geometry": {"coordinates":[-2.156681,52.567132],"type":"Point"}
}
