{
  "type": "Feature",
  "properties": {
    "iso:country":"GB",
    "wof:name":"ST17 9QW",
    "wof:placetype":"postalcode"
},
  "geometry": {"coordinates":[-2.1212817222694,52.78885876355449],"type":"Point"}
}