{
  "type": "Feature",
  "properties": {
    "iso:country":"GB",
    "wof:name":"BH16 5RA",
    "wof:placetype":"postalcode"
},
  "geometry": {"coordinates":[-2.03202993725424,50.73602345279189],"type":"Point"}
}