{
  "type": "Feature",
  "properties": {
    "date:inception_lower": "2021-11-01",
    "date:inception_upper": "2021-11-01",
    "iso:country": "GB",
    "wof:name": "NG34 9XD",
    "wof:placetype": "postalcode"
  },
  "geometry": {"coordinates":[-0.287554,52.969623],"type":"Point"}
}
