{
  "type": "Feature",
  "properties": {
    "iso:country": "GB",
    "wof:name": "B63 3NY",
    "wof:placetype": "postalcode"
  },
  "geometry": {"coordinates":[-2.071427,52.456456],"type":"Point"}
}
