{
  "type": "Feature",
  "properties": {
    "iso:country":"GB",
    "wof:name":"SA11 5BR",
    "wof:placetype":"postalcode"
},
  "geometry": {"coordinates":[-3.62402930595248,51.74578417322098],"type":"Point"}
}