{
  "type": "Feature",
  "properties": {
    "date:inception_lower": "1980-01-01",
    "date:inception_upper": "1980-01-01",
    "iso:country": "GB",
    "wof:name": "SE9 6LG",
    "wof:placetype": "postalcode"
  },
  "geometry": {"coordinates":[0.040637,51.460741],"type":"Point"}
}
