{
  "type": "Feature",
  "properties": {
    "iso:country":"GB",
    "wof:name":"HA9 7EN",
    "wof:placetype":"postalcode"
},
  "geometry": {"coordinates":[-0.29246148456876,51.55129460651011],"type":"Point"}
}