{
  "type": "Feature",
  "properties": {
    "iso:country":"GB",
    "wof:name":"NR31 9QW",
    "wof:placetype":"postalcode"
},
  "geometry": {"coordinates":[1.67729042097957,52.58672617972141],"type":"Point"}
}