{
  "type": "Feature",
  "properties": {
    "iso:country":"GB",
    "wof:name":"FY8 4FH",
    "wof:placetype":"postalcode"
},
  "geometry": {"coordinates":[-2.9841613060172,53.7549626139954],"type":"Point"}
}