{
  "type": "Feature",
  "properties": {
    "date:inception_lower":"2001-06-01",
    "date:inception_upper":"2001-06-30",
    "iso:country":"GB",
    "wof:name":"FY8 4FH",
    "wof:placetype":"postalcode"
},
  "geometry": {"coordinates":[-2.984161,53.754963],"type":"Point"}
}