{
  "type": "Feature",
  "properties": {
    "iso:country":"GB",
    "wof:name":"PO12 4LF",
    "wof:placetype":"postalcode"
},
  "geometry": {"coordinates":[-1.13741533146618,50.81366670294923],"type":"Point"}
}