{
  "type": "Feature",
  "properties": {
    "iso:country": "GB",
    "wof:name": "BN22 7LA",
    "wof:placetype": "postalcode"
  },
  "geometry": {"coordinates":[0.304186,50.776696],"type":"Point"}
}
