{
  "type": "Feature",
  "properties": {
    "date:inception_lower": "1980-01-01",
    "date:inception_upper": "1980-01-01",
    "iso:country": "GB",
    "wof:name": "BN22 7LA",
    "wof:placetype": "postalcode"
  },
  "geometry": {"coordinates":[0.304186,50.776696],"type":"Point"}
}
