{
  "type": "Feature",
  "properties": {
    "iso:country":"GB",
    "wof:name":"GU33 6HW",
    "wof:placetype":"postalcode"
},
  "geometry": {"coordinates":[-0.91681856032456,51.07533039374773],"type":"Point"}
}