{
  "type": "Feature",
  "properties": {
    "iso:country": "GB",
    "wof:name": "TN11 0FQ",
    "wof:placetype": "postalcode"
  },
  "geometry": {"coordinates":[0.289493,51.186802],"type":"Point"}
}
