{
  "type": "Feature",
  "properties": {
    "iso:country": "GB",
    "wof:name": "TS7 9HR",
    "wof:placetype": "postalcode"
  },
  "geometry": {"coordinates":[-1.164426,54.535388],"type":"Point"}
}
