{
  "type": "Feature",
  "properties": {
    "iso:country":"GB",
    "wof:name":"TS7 9HR",
    "wof:placetype":"postalcode"
},
  "geometry": {"coordinates":[-1.1644130004049,54.53537557399486],"type":"Point"}
}