{
  "type": "Feature",
  "properties": {
    "iso:country":"GB",
    "wof:name":"RH20 2AT",
    "wof:placetype":"postalcode"
},
  "geometry": {"coordinates":[-0.49786187288402,50.96046360019194],"type":"Point"}
}