{
  "type": "Feature",
  "properties": {
    "iso:country":"GB",
    "wof:name":"CV11 6QJ",
    "wof:placetype":"postalcode"
},
  "geometry": {"coordinates":[-1.38726262457906,52.48998315369911],"type":"Point"}
}