{
  "type": "Feature",
  "properties": {
    "date:inception_lower": "1994-12-01",
    "date:inception_upper": "1994-12-01",
    "iso:country": "GB",
    "wof:name": "CV11 6QJ",
    "wof:placetype": "postalcode"
  },
  "geometry": {"coordinates":[-1.387263,52.489983],"type":"Point"}
}
