{
  "type": "Feature",
  "properties": {
    "iso:country":"GB",
    "wof:name":"SG1 2BL",
    "wof:placetype":"postalcode"
},
  "geometry": {"coordinates":[-0.2041609836266,51.89178577407466],"type":"Point"}
}