{
  "type": "Feature",
  "properties": {
    "iso:country":"GB",
    "wof:name":"SR8 2EQ",
    "wof:placetype":"postalcode"
},
  "geometry": {"coordinates":[-1.35413569103512,54.76696902881655],"type":"Point"}
}