{
  "type": "Feature",
  "properties": {
    "date:inception_lower": "2015-12-01",
    "date:inception_upper": "2015-12-01",
    "iso:country": "GB",
    "wof:name": "SG18 8RE",
    "wof:placetype": "postalcode"
  },
  "geometry": {"coordinates":[-0.24244,52.092277],"type":"Point"}
}
