{
  "type": "Feature",
  "properties": {
    "iso:country":"GB",
    "wof:name":"S36 1AR",
    "wof:placetype":"postalcode"
},
  "geometry": {"coordinates":[-1.60018908706615,53.47374255053531],"type":"Point"}
}