{
  "type": "Feature",
  "properties": {
    "date:inception_lower":"1980-01-01",
    "date:inception_upper":"1980-01-31",
    "iso:country":"GB",
    "wof:name":"ME14 4AA",
    "wof:placetype":"postalcode"
},
  "geometry": {"coordinates":[0.551832,51.270466],"type":"Point"}
}