{
  "type": "Feature",
  "properties": {
    "date:inception_lower":"1989-04-01",
    "date:inception_upper":"1989-04-30",
    "iso:country":"GB",
    "wof:name":"G68 9BT",
    "wof:placetype":"postalcode"
},
  "geometry": {"coordinates":[-4.011605,55.951232],"type":"Point"}
}