{
  "type": "Feature",
  "properties": {
    "iso:country":"GB",
    "wof:name":"G68 9BT",
    "wof:placetype":"postalcode"
},
  "geometry": {"coordinates":[-4.01160496754549,55.9512323560018],"type":"Point"}
}