{
  "type": "Feature",
  "properties": {
    "iso:country": "GB",
    "wof:name": "G68 9BT",
    "wof:placetype": "postalcode"
  },
  "geometry": {"coordinates":[-4.011605,55.951232],"type":"Point"}
}
