{
  "type": "Feature",
  "properties": {
    "iso:country":"GB",
    "wof:name":"SA15 5SD",
    "wof:placetype":"postalcode"
},
  "geometry": {"coordinates":[-4.21793862142042,51.75983992940792],"type":"Point"}
}