{
  "type": "Feature",
  "properties": {
    "date:inception_lower": "1980-01-01",
    "date:inception_upper": "1980-01-01",
    "iso:country": "GB",
    "wof:name": "LL53 8RP",
    "wof:placetype": "postalcode"
  },
  "geometry": {"coordinates":[-4.608192,52.871892],"type":"Point"}
}
