{
  "type": "Feature",
  "properties": {
    "iso:country":"GB",
    "wof:name":"LL53 8RP",
    "wof:placetype":"postalcode"
},
  "geometry": {"coordinates":[-4.60819249473079,52.87189207299441],"type":"Point"}
}