{
  "type": "Feature",
  "properties": {
    "iso:country":"GB",
    "wof:name":"OL14 6PD",
    "wof:placetype":"postalcode"
},
  "geometry": {"coordinates":[-2.10620877210666,53.70346517155737],"type":"Point"}
}