{
  "type": "Feature",
  "properties": {
    "iso:country": "GB",
    "wof:name": "OL14 6PD",
    "wof:placetype": "postalcode"
  },
  "geometry": {"coordinates":[-2.106209,53.703465],"type":"Point"}
}
