{
  "type": "Feature",
  "properties": {
    "iso:country":"GB",
    "wof:name":"G75 9DH",
    "wof:placetype":"postalcode"
},
  "geometry": {"coordinates":[-4.20291156663859,55.74649887035674],"type":"Point"}
}