{
  "type": "Feature",
  "properties": {
    "iso:country": "GB",
    "wof:name": "EX5 1FE",
    "wof:placetype": "postalcode"
  },
  "geometry": {"coordinates":[-3.454613,50.710035],"type":"Point"}
}
