{
  "type": "Feature",
  "properties": {
    "date:inception_lower": "2013-07-01",
    "date:inception_upper": "2013-07-01",
    "iso:country": "GB",
    "wof:name": "EX5 1FE",
    "wof:placetype": "postalcode"
  },
  "geometry": {"coordinates":[-3.45456,50.71015],"type":"Point"}
}
