{
  "type": "Feature",
  "properties": {
    "date:inception_lower": "1990-02-01",
    "date:inception_upper": "1990-02-01",
    "iso:country": "GB",
    "wof:name": "WA11 8HP",
    "wof:placetype": "postalcode"
  },
  "geometry": {"coordinates":[-2.798007,53.505998],"type":"Point"}
}
