{
  "type": "Feature",
  "properties": {
    "iso:country": "GB",
    "wof:name": "WA11 8HP",
    "wof:placetype": "postalcode"
  },
  "geometry": {"coordinates":[-2.797886,53.505956],"type":"Point"}
}
