{
  "type": "Feature",
  "properties": {
    "date:inception_lower": "1980-01-01",
    "date:inception_upper": "1980-01-01",
    "iso:country": "GB",
    "wof:name": "AL3 7NQ",
    "wof:placetype": "postalcode"
  },
  "geometry": {"coordinates":[-0.400307,51.794331],"type":"Point"}
}
