{
  "type": "Feature",
  "properties": {
    "iso:country": "GB",
    "wof:name": "LE7 7HT",
    "wof:placetype": "postalcode"
  },
  "geometry": {"coordinates":[-1.17814,52.69502],"type":"Point"}
}
