{
  "type": "Feature",
  "properties": {
    "iso:country":"GB",
    "wof:name":"LE7 7HT",
    "wof:placetype":"postalcode"
},
  "geometry": {"coordinates":[-1.17797876919491,52.69528759259163],"type":"Point"}
}