{
  "type": "Feature",
  "properties": {
    "date:inception_lower": "1993-01-01",
    "date:inception_upper": "1993-01-01",
    "iso:country": "GB",
    "wof:name": "NG34 7FX",
    "wof:placetype": "postalcode"
  },
  "geometry": {"coordinates":[-0.393754,52.998521],"type":"Point"}
}
