{
  "type": "Feature",
  "properties": {
    "iso:country": "GB",
    "wof:name": "NG34 7FX",
    "wof:placetype": "postalcode"
  },
  "geometry": {"coordinates":[-0.393754,52.998521],"type":"Point"}
}
