{
  "type": "Feature",
  "properties": {
    "iso:country":"GB",
    "wof:name":"WF1 4JD",
    "wof:placetype":"postalcode"
},
  "geometry": {"coordinates":[-1.47219273383332,53.68935404010803],"type":"Point"}
}