{
  "type": "Feature",
  "properties": {
    "date:inception_lower": "2008-09-01",
    "date:inception_upper": "2008-09-01",
    "iso:country": "GB",
    "wof:name": "IG11 7FF",
    "wof:placetype": "postalcode"
  },
  "geometry": {"coordinates":[0.080206,51.535297],"type":"Point"}
}
