{
  "type": "Feature",
  "properties": {
    "iso:country": "GB",
    "wof:name": "IG11 7FF",
    "wof:placetype": "postalcode"
  },
  "geometry": {"coordinates":[0.080206,51.535297],"type":"Point"}
}
