{
  "type": "Feature",
  "properties": {
    "iso:country":"GB",
    "wof:name":"IG11 7FF",
    "wof:placetype":"postalcode"
},
  "geometry": {"coordinates":[0.08020634291931,51.53529676519911],"type":"Point"}
}