{
  "type": "Feature",
  "properties": {
    "iso:country": "GB",
    "wof:name": "NP13 3LD",
    "wof:placetype": "postalcode"
  },
  "geometry": {"coordinates":[-3.1595,51.766819],"type":"Point"}
}
