{
  "type": "Feature",
  "properties": {
    "iso:country":"GB",
    "wof:name":"DL10 7PW",
    "wof:placetype":"postalcode"
},
  "geometry": {"coordinates":[-1.65425541954606,54.35968832451374],"type":"Point"}
}