{
  "type": "Feature",
  "properties": {
    "iso:country": "GB",
    "wof:name": "DL10 7PW",
    "wof:placetype": "postalcode"
  },
  "geometry": {"coordinates":[-1.658199,54.361966],"type":"Point"}
}
