{
  "type": "Feature",
  "properties": {
    "iso:country":"GB",
    "wof:name":"SK9 2AG",
    "wof:placetype":"postalcode"
},
  "geometry": {"coordinates":[-2.21584383770223,53.32618221328984],"type":"Point"}
}