{
  "type": "Feature",
  "properties": {
    "iso:country":"GB",
    "wof:name":"B78 3TY",
    "wof:placetype":"postalcode"
},
  "geometry": {"coordinates":[-1.71620823578881,52.59894541859553],"type":"Point"}
}