{
  "type": "Feature",
  "properties": {
    "iso:country":"GB",
    "wof:name":"LE4 9AL",
    "wof:placetype":"postalcode"
},
  "geometry": {"coordinates":[-1.07722431706211,52.66732478849996],"type":"Point"}
}