{
  "type": "Feature",
  "properties": {
    "iso:country":"GB",
    "wof:name":"CR0 3BB",
    "wof:placetype":"postalcode"
},
  "geometry": {"coordinates":[-0.12239881893724,51.39112821415979],"type":"Point"}
}