{
  "type": "Feature",
  "properties": {
    "iso:country":"GB",
    "wof:name":"NE25 0PQ",
    "wof:placetype":"postalcode"
},
  "geometry": {"coordinates":[-1.53786356979763,55.07755877706062],"type":"Point"}
}