{
  "type": "Feature",
  "properties": {
    "date:inception_lower":"2015-01-01",
    "date:inception_upper":"2015-01-31",
    "iso:country":"GB",
    "wof:name":"NE25 0PQ",
    "wof:placetype":"postalcode"
},
  "geometry": {"coordinates":[-1.53789,55.077907],"type":"Point"}
}