{
  "type": "Feature",
  "properties": {
    "iso:country":"GB",
    "wof:name":"SY21 9HD",
    "wof:placetype":"postalcode"
},
  "geometry": {"coordinates":[-3.29239124052858,52.64655919607091],"type":"Point"}
}