{
  "type": "Feature",
  "properties": {
    "iso:country": "GB",
    "wof:name": "SY21 9HD",
    "wof:placetype": "postalcode"
  },
  "geometry": {"coordinates":[-3.292392,52.646574],"type":"Point"}
}
