{
  "type": "Feature",
  "properties": {
    "iso:country":"GB",
    "wof:name":"NG19 9EJ",
    "wof:placetype":"postalcode"
},
  "geometry": {"coordinates":[-1.17699840985712,53.17716370083254],"type":"Point"}
}