{
  "type": "Feature",
  "properties": {
    "iso:country":"GB",
    "wof:name":"NP18 1AR",
    "wof:placetype":"postalcode"
},
  "geometry": {"coordinates":[-2.95371118176609,51.61123365245284],"type":"Point"}
}