{
  "type": "Feature",
  "properties": {
    "iso:country": "GB",
    "wof:name": "ME1 1JR",
    "wof:placetype": "postalcode"
  },
  "geometry": {"coordinates":[0.515145,51.383546],"type":"Point"}
}
