{
  "type": "Feature",
  "properties": {
    "iso:country":"GB",
    "wof:name":"ME1 1JR",
    "wof:placetype":"postalcode"
},
  "geometry": {"coordinates":[0.51514470046661,51.38354583203708],"type":"Point"}
}