{
  "type": "Feature",
  "properties": {
    "date:inception_lower":"1999-12-01",
    "date:inception_upper":"1999-12-31",
    "iso:country":"GB",
    "wof:name":"ME1 1JR",
    "wof:placetype":"postalcode"
},
  "geometry": {"coordinates":[0.515145,51.383546],"type":"Point"}
}