{
  "type": "Feature",
  "properties": {
    "iso:country": "GB",
    "wof:name": "PR1 1FB",
    "wof:placetype": "postalcode"
  },
  "geometry": {"coordinates":[-2.697713,53.760838],"type":"Point"}
}
