{
  "type": "Feature",
  "properties": {
    "date:inception_lower": "1985-10-01",
    "date:inception_upper": "1985-10-01",
    "iso:country": "GB",
    "wof:name": "PR1 1FB",
    "wof:placetype": "postalcode"
  },
  "geometry": {"coordinates":[-2.697797,53.76061],"type":"Point"}
}
