{
  "type": "Feature",
  "properties": {
    "iso:country":"GB",
    "wof:name":"PR1 1FB",
    "wof:placetype":"postalcode"
},
  "geometry": {"coordinates":[-2.69771324848981,53.76083773081509],"type":"Point"}
}