{
  "type": "Feature",
  "properties": {
    "iso:country": "GB",
    "wof:name": "L20 5AP",
    "wof:placetype": "postalcode"
  },
  "geometry": {"coordinates":[-2.990588,53.455858],"type":"Point"}
}
