{
  "type": "Feature",
  "properties": {
    "iso:country": "GB",
    "wof:name": "DE12 8BN",
    "wof:placetype": "postalcode"
  },
  "geometry": {"coordinates":[-1.577856,52.715508],"type":"Point"}
}
