{
  "type": "Feature",
  "properties": {
    "iso:country":"GB",
    "wof:name":"TS6 7DX",
    "wof:placetype":"postalcode"
},
  "geometry": {"coordinates":[-1.15396468415011,54.57502611778862],"type":"Point"}
}