{
  "type": "Feature",
  "properties": {
    "date:inception_lower": "2020-10-01",
    "date:inception_upper": "2020-10-01",
    "iso:country": "GB",
    "wof:name": "TN28 8FZ",
    "wof:placetype": "postalcode"
  },
  "geometry": {"coordinates":[0.944284,50.991296],"type":"Point"}
}
