{
  "type": "Feature",
  "properties": {
    "iso:country":"GB",
    "wof:name":"NE15 9EH",
    "wof:placetype":"postalcode"
},
  "geometry": {"coordinates":[-1.75883612181185,54.99583844491796],"type":"Point"}
}