{
  "type": "Feature",
  "properties": {
    "iso:country": "GB",
    "wof:name": "NE15 9EH",
    "wof:placetype": "postalcode"
  },
  "geometry": {"coordinates":[-1.758836,54.995838],"type":"Point"}
}
