{
  "type": "Feature",
  "properties": {
    "date:inception_lower": "1980-01-01",
    "date:inception_upper": "1980-01-01",
    "iso:country": "GB",
    "wof:name": "BB11 5AW",
    "wof:placetype": "postalcode"
  },
  "geometry": {"coordinates":[-2.265199,53.787469],"type":"Point"}
}
