{
  "type": "Feature",
  "properties": {
    "iso:country":"GB",
    "wof:name":"SK17 8PY",
    "wof:placetype":"postalcode"
},
  "geometry": {"coordinates":[-1.76878145094639,53.28107594713016],"type":"Point"}
}