{
  "type": "Feature",
  "properties": {
    "iso:country": "GB",
    "wof:name": "OX17 1EX",
    "wof:placetype": "postalcode"
  },
  "geometry": {"coordinates":[-1.334286,52.147767],"type":"Point"}
}
