{
  "type": "Feature",
  "properties": {
    "iso:country":"GB",
    "wof:name":"OX17 1EX",
    "wof:placetype":"postalcode"
},
  "geometry": {"coordinates":[-1.33428571368518,52.14776680778065],"type":"Point"}
}