{
  "type": "Feature",
  "properties": {
    "iso:country":"GB",
    "wof:name":"B71 4EH",
    "wof:placetype":"postalcode"
},
  "geometry": {"coordinates":[-1.99129001856301,52.52398560810928],"type":"Point"}
}