{
  "type": "Feature",
  "properties": {
    "iso:country":"GB",
    "wof:name":"EX1 2SU",
    "wof:placetype":"postalcode"
},
  "geometry": {"coordinates":[-3.50742572085537,50.72626204873045],"type":"Point"}
}