{
  "type": "Feature",
  "properties": {
    "iso:country":"GB",
    "wof:name":"MK17 8UH",
    "wof:placetype":"postalcode"
},
  "geometry": {"coordinates":[-0.65716952044455,52.02266272848677],"type":"Point"}
}