{
  "type": "Feature",
  "properties": {
    "iso:country":"GB",
    "wof:name":"NN7 2DH",
    "wof:placetype":"postalcode"
},
  "geometry": {"coordinates":[-0.83065806825663,52.19086337291026],"type":"Point"}
}