{
  "type": "Feature",
  "properties": {
    "iso:country": "GB",
    "wof:name": "HU17 7BZ",
    "wof:placetype": "postalcode"
  },
  "geometry": {"coordinates":[-0.432565,53.845274],"type":"Point"}
}
