{
  "type": "Feature",
  "properties": {
    "date:inception_lower": "1980-01-01",
    "date:inception_upper": "1980-01-01",
    "iso:country": "GB",
    "wof:name": "SK17 9TT",
    "wof:placetype": "postalcode"
  },
  "geometry": {"coordinates":[-1.790266,53.236558],"type":"Point"}
}
