{
  "type": "Feature",
  "properties": {
    "date:inception_lower": "1980-01-01",
    "date:inception_upper": "1980-01-01",
    "iso:country": "GB",
    "wof:name": "WD7 9DG",
    "wof:placetype": "postalcode"
  },
  "geometry": {"coordinates":[-0.291065,51.698485],"type":"Point"}
}
