{
  "type": "Feature",
  "properties": {
    "iso:country":"GB",
    "wof:name":"WD7 9DG",
    "wof:placetype":"postalcode"
},
  "geometry": {"coordinates":[-0.2910652571673,51.69848532614302],"type":"Point"}
}