{
  "type": "Feature",
  "properties": {
    "iso:country": "GB",
    "wof:name": "EX7 0BU",
    "wof:placetype": "postalcode"
  },
  "geometry": {"coordinates":[-3.46174,50.58346],"type":"Point"}
}
