{
  "type": "Feature",
  "properties": {
    "date:inception_lower": "1980-01-01",
    "date:inception_upper": "1980-01-01",
    "iso:country": "GB",
    "wof:name": "EX7 0BU",
    "wof:placetype": "postalcode"
  },
  "geometry": {"coordinates":[-3.46174,50.58346],"type":"Point"}
}
