{
  "type": "Feature",
  "properties": {
    "iso:country":"GB",
    "wof:name":"OX11 7EL",
    "wof:placetype":"postalcode"
},
  "geometry": {"coordinates":[-1.25792628060051,51.61277497245619],"type":"Point"}
}