{
  "type": "Feature",
  "properties": {
    "iso:country": "GB",
    "wof:name": "OX11 7EL",
    "wof:placetype": "postalcode"
  },
  "geometry": {"coordinates":[-1.257926,51.612775],"type":"Point"}
}
