{
  "type": "Feature",
  "properties": {
    "date:inception_lower":"1994-12-01",
    "date:inception_upper":"1994-12-31",
    "iso:country":"GB",
    "wof:name":"DE14 2WE",
    "wof:placetype":"postalcode"
},
  "geometry": {"coordinates":[-1.673444,52.790441],"type":"Point"}
}