{
  "type": "Feature",
  "properties": {
    "iso:country":"GB",
    "wof:name":"DE14 2WE",
    "wof:placetype":"postalcode"
},
  "geometry": {"coordinates":[-1.67344441155847,52.79044112833139],"type":"Point"}
}