{
  "type": "Feature",
  "properties": {
    "iso:country": "GB",
    "wof:name": "DE14 2WE",
    "wof:placetype": "postalcode"
  },
  "geometry": {"coordinates":[-1.673444,52.790441],"type":"Point"}
}
