{
  "type": "Feature",
  "properties": {
    "iso:country": "GB",
    "wof:name": "RH11 0GB",
    "wof:placetype": "postalcode"
  },
  "geometry": {"coordinates":[-0.224849,51.117398],"type":"Point"}
}
