{
  "type": "Feature",
  "properties": {
    "iso:country":"GB",
    "wof:name":"WC2N 5JR",
    "wof:placetype":"postalcode"
},
  "geometry": {"coordinates":[-0.12678099313976,51.50756273348784],"type":"Point"}
}