{
  "type": "Feature",
  "properties": {
    "date:inception_lower": "2004-01-01",
    "date:inception_upper": "2004-01-01",
    "iso:country": "GB",
    "wof:name": "WC2N 5JR",
    "wof:placetype": "postalcode"
  },
  "geometry": {"coordinates":[-0.126781,51.507563],"type":"Point"}
}
