{
  "type": "Feature",
  "properties": {
    "date:inception_lower":"2017-01-01",
    "date:inception_upper":"2017-01-31",
    "iso:country":"GB",
    "wof:name":"PE32 1WE",
    "wof:placetype":"postalcode"
},
  "geometry": {"coordinates":[0.587014,52.679692],"type":"Point"}
}