{
  "type": "Feature",
  "properties": {
    "date:inception_lower": "2017-10-01",
    "date:inception_upper": "2017-10-01",
    "iso:country": "GB",
    "wof:name": "CA5 6AJ",
    "wof:placetype": "postalcode"
  },
  "geometry": {"coordinates":[-3.056967,54.84115],"type":"Point"}
}
