{
  "type": "Feature",
  "properties": {
    "iso:country": "GB",
    "wof:name": "BA13 4DX",
    "wof:placetype": "postalcode"
  },
  "geometry": {"coordinates":[-2.225001,51.247569],"type":"Point"}
}
