{
  "type": "Feature",
  "properties": {
    "iso:country": "GB",
    "wof:name": "CV2 2RD",
    "wof:placetype": "postalcode"
  },
  "geometry": {"coordinates":[-1.440647,52.434473],"type":"Point"}
}
