{
  "type": "Feature",
  "properties": {
    "iso:country":"GB",
    "wof:name":"CV2 2RD",
    "wof:placetype":"postalcode"
},
  "geometry": {"coordinates":[-1.44064701135872,52.43447289481094],"type":"Point"}
}