{
  "type": "Feature",
  "properties": {
    "iso:country":"GB",
    "wof:name":"B69 1UP",
    "wof:placetype":"postalcode"
},
  "geometry": {"coordinates":[-2.06065781826781,52.50773446429049],"type":"Point"}
}