{
  "type": "Feature",
  "properties": {
    "iso:country":"GB",
    "wof:name":"HA3 6PJ",
    "wof:placetype":"postalcode"
},
  "geometry": {"coordinates":[-0.35781810712416,51.6072776307474],"type":"Point"}
}