{
  "type": "Feature",
  "properties": {
    "iso:country":"GB",
    "wof:name":"NE41 8BG",
    "wof:placetype":"postalcode"
},
  "geometry": {"coordinates":[-1.83780371266106,54.98767492970029],"type":"Point"}
}