{
  "type": "Feature",
  "properties": {
    "date:inception_lower": "1992-08-01",
    "date:inception_upper": "1992-08-01",
    "iso:country": "GB",
    "wof:name": "PL32 9UD",
    "wof:placetype": "postalcode"
  },
  "geometry": {"coordinates":[-4.681866,50.62454],"type":"Point"}
}
