{
  "type": "Feature",
  "properties": {
    "iso:country":"GB",
    "wof:name":"PL32 9UD",
    "wof:placetype":"postalcode"
},
  "geometry": {"coordinates":[-4.68186650755202,50.62454012328383],"type":"Point"}
}