{
  "type": "Feature",
  "properties": {
    "iso:country": "GB",
    "wof:name": "HA0 3DJ",
    "wof:placetype": "postalcode"
  },
  "geometry": {"coordinates":[-0.311459,51.556704],"type":"Point"}
}
