{
  "type": "Feature",
  "properties": {
    "date:inception_lower": "1980-01-01",
    "date:inception_upper": "1980-01-01",
    "iso:country": "GB",
    "wof:name": "CT12 5BG",
    "wof:placetype": "postalcode"
  },
  "geometry": {"coordinates":[1.368975,51.345198],"type":"Point"}
}
