{
  "type": "Feature",
  "properties": {
    "iso:country": "GB",
    "wof:name": "PL14 3PF",
    "wof:placetype": "postalcode"
  },
  "geometry": {"coordinates":[-4.446494,50.432797],"type":"Point"}
}
