{
  "type": "Feature",
  "properties": {
    "iso:country":"GB",
    "wof:name":"PE28 2FH",
    "wof:placetype":"postalcode"
},
  "geometry": {"coordinates":[-0.14028105429855,52.3369605939892],"type":"Point"}
}