{
  "type": "Feature",
  "properties": {
    "date:inception_lower": "2006-08-01",
    "date:inception_upper": "2006-08-01",
    "iso:country": "GB",
    "wof:name": "PE28 2FH",
    "wof:placetype": "postalcode"
  },
  "geometry": {"coordinates":[-0.140281,52.336961],"type":"Point"}
}
