{
  "type": "Feature",
  "properties": {
    "iso:country": "GB",
    "wof:name": "PE28 2FH",
    "wof:placetype": "postalcode"
  },
  "geometry": {"coordinates":[-0.140281,52.336961],"type":"Point"}
}
