{
  "type": "Feature",
  "properties": {
    "iso:country": "GB",
    "wof:name": "EX8 2SJ",
    "wof:placetype": "postalcode"
  },
  "geometry": {"coordinates":[-3.413263,50.617487],"type":"Point"}
}
