{
  "type": "Feature",
  "properties": {
    "date:inception_lower": "2010-11-01",
    "date:inception_upper": "2010-11-01",
    "iso:country": "GB",
    "wof:name": "BA9 9GD",
    "wof:placetype": "postalcode"
  },
  "geometry": {"coordinates":[-2.403175,51.052494],"type":"Point"}
}
