{
  "type": "Feature",
  "properties": {
    "iso:country": "GB",
    "wof:name": "BA9 9GD",
    "wof:placetype": "postalcode"
  },
  "geometry": {"coordinates":[-2.403175,51.052494],"type":"Point"}
}
