{
  "type": "Feature",
  "properties": {
    "iso:country":"GB",
    "wof:name":"RG22 5NJ",
    "wof:placetype":"postalcode"
},
  "geometry": {"coordinates":[-1.13929269287177,51.23859877793821],"type":"Point"}
}