{
  "type": "Feature",
  "properties": {
    "iso:country":"GB",
    "wof:name":"BD2 4QP",
    "wof:placetype":"postalcode"
},
  "geometry": {"coordinates":[-1.72979541247908,53.80862919592944],"type":"Point"}
}