{
  "type": "Feature",
  "properties": {
    "iso:country":"GB",
    "wof:name":"WN2 2LF",
    "wof:placetype":"postalcode"
},
  "geometry": {"coordinates":[-2.59593830644417,53.54146984719534],"type":"Point"}
}