{
  "type": "Feature",
  "properties": {
    "iso:country":"GB",
    "wof:name":"BS1 5SZ",
    "wof:placetype":"postalcode"
},
  "geometry": {"coordinates":[-2.6018728223123,51.44976675619166],"type":"Point"}
}