{
  "type": "Feature",
  "properties": {
    "date:inception_lower": "2006-07-01",
    "date:inception_upper": "2006-07-01",
    "iso:country": "GB",
    "wof:name": "BS1 5SZ",
    "wof:placetype": "postalcode"
  },
  "geometry": {"coordinates":[-2.602094,51.450016],"type":"Point"}
}
