{
  "type": "Feature",
  "properties": {
    "iso:country": "GB",
    "wof:name": "BS1 5SZ",
    "wof:placetype": "postalcode"
  },
  "geometry": {"coordinates":[-2.601961,51.449773],"type":"Point"}
}
