{
  "type": "Feature",
  "properties": {
    "iso:country":"GB",
    "wof:name":"BB4 8BL",
    "wof:placetype":"postalcode"
},
  "geometry": {"coordinates":[-2.28735128442868,53.72871147094727],"type":"Point"}
}