{
  "type": "Feature",
  "properties": {
    "iso:country":"GB",
    "wof:name":"LL18 2UN",
    "wof:placetype":"postalcode"
},
  "geometry": {"coordinates":[-3.46553325464997,53.29469267424595],"type":"Point"}
}