{
  "type": "Feature",
  "properties": {
    "iso:country":"GB",
    "wof:name":"W14 0HB",
    "wof:placetype":"postalcode"
},
  "geometry": {"coordinates":[-0.21602905027891,51.4974528744083],"type":"Point"}
}