{
  "type": "Feature",
  "properties": {
    "iso:country": "GB",
    "wof:name": "W14 0HB",
    "wof:placetype": "postalcode"
  },
  "geometry": {"coordinates":[-0.216029,51.497453],"type":"Point"}
}
