{
  "type": "Feature",
  "properties": {
    "iso:country":"GB",
    "wof:name":"G83 7AZ",
    "wof:placetype":"postalcode"
},
  "geometry": {"coordinates":[-4.77746547166706,56.16224134595933],"type":"Point"}
}