{
  "type": "Feature",
  "properties": {
    "date:inception_lower":"2016-01-01",
    "date:inception_upper":"2016-01-31",
    "iso:country":"GB",
    "wof:name":"G83 7AZ",
    "wof:placetype":"postalcode"
},
  "geometry": {"coordinates":[-4.777465,56.162241],"type":"Point"}
}