{
  "type": "Feature",
  "properties": {
    "iso:country": "GB",
    "wof:name": "EN8 0LH",
    "wof:placetype": "postalcode"
  },
  "geometry": {"coordinates":[-0.03003,51.713713],"type":"Point"}
}
