{
  "type": "Feature",
  "properties": {
    "date:inception_lower":"1986-07-01",
    "date:inception_upper":"1986-07-31",
    "iso:country":"GB",
    "wof:name":"NE4 5JN",
    "wof:placetype":"postalcode"
},
  "geometry": {"coordinates":[-1.637033,54.973958],"type":"Point"}
}