{
  "type": "Feature",
  "properties": {
    "iso:country":"GB",
    "wof:name":"NE4 5JN",
    "wof:placetype":"postalcode"
},
  "geometry": {"coordinates":[-1.63700424162201,54.9740141802674],"type":"Point"}
}