{
  "type": "Feature",
  "properties": {
    "iso:country": "GB",
    "wof:name": "NE4 5JN",
    "wof:placetype": "postalcode"
  },
  "geometry": {"coordinates":[-1.637033,54.973958],"type":"Point"}
}
