{
  "type": "Feature",
  "properties": {
    "date:inception_lower": "1999-06-01",
    "date:inception_upper": "1999-06-01",
    "iso:country": "GB",
    "wof:name": "EX16 5LN",
    "wof:placetype": "postalcode"
  },
  "geometry": {"coordinates":[-3.494792,50.902906],"type":"Point"}
}
