{
  "type": "Feature",
  "properties": {
    "iso:country":"GB",
    "wof:name":"NP4 8ED",
    "wof:placetype":"postalcode"
},
  "geometry": {"coordinates":[-3.04575491716238,51.71759297420514],"type":"Point"}
}