{
  "type": "Feature",
  "properties": {
    "date:inception_lower": "1980-01-01",
    "date:inception_upper": "1980-01-01",
    "iso:country": "GB",
    "wof:name": "NP4 8ED",
    "wof:placetype": "postalcode"
  },
  "geometry": {"coordinates":[-3.045755,51.717593],"type":"Point"}
}
