{
  "type": "Feature",
  "properties": {
    "iso:country":"GB",
    "wof:name":"CM14 5EY",
    "wof:placetype":"postalcode"
},
  "geometry": {"coordinates":[0.29648652908166,51.61258508469216],"type":"Point"}
}