{
  "type": "Feature",
  "properties": {
    "iso:country": "GB",
    "wof:name": "CM6 2LJ",
    "wof:placetype": "postalcode"
  },
  "geometry": {"coordinates":[0.348771,51.953268],"type":"Point"}
}
