{
  "type": "Feature",
  "properties": {
    "iso:country": "GB",
    "wof:name": "B40 1PP",
    "wof:placetype": "postalcode"
  },
  "geometry": {"coordinates":[-1.715721,52.45044],"type":"Point"}
}
