{
  "type": "Feature",
  "properties": {
    "iso:country":"GB",
    "wof:name":"SW11 6ER",
    "wof:placetype":"postalcode"
},
  "geometry": {"coordinates":[-0.163929636036,51.44949191986866],"type":"Point"}
}