{
  "type": "Feature",
  "properties": {
    "iso:country":"GB",
    "wof:name":"SG2 8BB",
    "wof:placetype":"postalcode"
},
  "geometry": {"coordinates":[-0.17703927867802,51.87966119369275],"type":"Point"}
}