{
  "type": "Feature",
  "properties": {
    "iso:country":"GB",
    "wof:name":"RG27 8BQ",
    "wof:placetype":"postalcode"
},
  "geometry": {"coordinates":[-0.8663987320448,51.31050500530563],"type":"Point"}
}