{
  "type": "Feature",
  "properties": {
    "iso:country": "GB",
    "wof:name": "RG27 8BQ",
    "wof:placetype": "postalcode"
  },
  "geometry": {"coordinates":[-0.857094,51.305514],"type":"Point"}
}
