{
  "type": "Feature",
  "properties": {
    "iso:country":"GB",
    "wof:name":"TW1 3EL",
    "wof:placetype":"postalcode"
},
  "geometry": {"coordinates":[-0.32080928287018,51.45315682795717],"type":"Point"}
}