{
  "type": "Feature",
  "properties": {
    "iso:country": "GB",
    "wof:name": "TW1 3EL",
    "wof:placetype": "postalcode"
  },
  "geometry": {"coordinates":[-0.320809,51.453157],"type":"Point"}
}
