{
  "type": "Feature",
  "properties": {
    "iso:country":"GB",
    "wof:name":"LL17 0EP",
    "wof:placetype":"postalcode"
},
  "geometry": {"coordinates":[-3.44181619426745,53.23467080060796],"type":"Point"}
}