{
  "type": "Feature",
  "properties": {
    "date:inception_lower": "2007-11-01",
    "date:inception_upper": "2007-11-01",
    "iso:country": "GB",
    "wof:name": "EX15 1FQ",
    "wof:placetype": "postalcode"
  },
  "geometry": {"coordinates":[-3.388098,50.863198],"type":"Point"}
}
