{
  "type": "Feature",
  "properties": {
    "iso:country":"GB",
    "wof:name":"EX15 1FQ",
    "wof:placetype":"postalcode"
},
  "geometry": {"coordinates":[-3.38809838795021,50.86319798771025],"type":"Point"}
}