{
  "type": "Feature",
  "properties": {
    "iso:country":"GB",
    "wof:name":"CF82 7RY",
    "wof:placetype":"postalcode"
},
  "geometry": {"coordinates":[-3.22046406927808,51.64553003997084],"type":"Point"}
}