{
  "type": "Feature",
  "properties": {
    "date:inception_lower": "1995-07-01",
    "date:inception_upper": "1995-07-01",
    "iso:country": "GB",
    "wof:name": "CF82 7RY",
    "wof:placetype": "postalcode"
  },
  "geometry": {"coordinates":[-3.220464,51.64553],"type":"Point"}
}
