{
  "type": "Feature",
  "properties": {
    "iso:country": "GB",
    "wof:name": "S75 5NU",
    "wof:placetype": "postalcode"
  },
  "geometry": {"coordinates":[-1.5297,53.579631],"type":"Point"}
}
