{
  "type": "Feature",
  "properties": {
    "iso:country":"GB",
    "wof:name":"B15 2TT",
    "wof:placetype":"postalcode"
},
  "geometry": {"coordinates":[-1.93004718440533,52.45140752607474],"type":"Point"}
}