{
  "type": "Feature",
  "properties": {
    "date:inception_lower":"1980-01-01",
    "date:inception_upper":"1980-01-31",
    "iso:country":"GB",
    "wof:name":"SE5 7LP",
    "wof:placetype":"postalcode"
},
  "geometry": {"coordinates":[-0.087506,51.474672],"type":"Point"}
}