{
  "type": "Feature",
  "properties": {
    "iso:country":"GB",
    "wof:name":"SE5 7LP",
    "wof:placetype":"postalcode"
},
  "geometry": {"coordinates":[-0.08750649100855,51.47467240984857],"type":"Point"}
}