{
  "type": "Feature",
  "properties": {
    "date:inception_lower":"2015-07-01",
    "date:inception_upper":"2015-07-31",
    "iso:country":"GB",
    "wof:name":"BH22 9FP",
    "wof:placetype":"postalcode"
},
  "geometry": {"coordinates":[-1.888889,50.803797],"type":"Point"}
}