{
  "type": "Feature",
  "properties": {
    "iso:country": "GB",
    "wof:name": "BH22 9FP",
    "wof:placetype": "postalcode"
  },
  "geometry": {"coordinates":[-1.888889,50.803797],"type":"Point"}
}
