{
  "type": "Feature",
  "properties": {
    "iso:country":"GB",
    "wof:name":"BH22 9FP",
    "wof:placetype":"postalcode"
},
  "geometry": {"coordinates":[-1.88888940018903,50.80379741239712],"type":"Point"}
}