{
  "type": "Feature",
  "properties": {
    "iso:country":"GB",
    "wof:name":"WS7 4UT",
    "wof:placetype":"postalcode"
},
  "geometry": {"coordinates":[-1.92047727183305,52.67541913765323],"type":"Point"}
}