{
  "type": "Feature",
  "properties": {
    "date:inception_lower": "2003-07-01",
    "date:inception_upper": "2003-07-01",
    "iso:country": "GB",
    "wof:name": "CF62 3LW",
    "wof:placetype": "postalcode"
  },
  "geometry": {"coordinates":[-3.345473,51.386022],"type":"Point"}
}
