{
  "type": "Feature",
  "properties": {
    "iso:country": "GB",
    "wof:name": "CF62 3LW",
    "wof:placetype": "postalcode"
  },
  "geometry": {"coordinates":[-3.345473,51.386022],"type":"Point"}
}
