{
  "type": "Feature",
  "properties": {
    "iso:country":"GB",
    "wof:name":"CF62 3LW",
    "wof:placetype":"postalcode"
},
  "geometry": {"coordinates":[-3.34547292367419,51.38602161806953],"type":"Point"}
}