{
  "type": "Feature",
  "properties": {
    "date:inception_lower": "1980-01-01",
    "date:inception_upper": "1980-01-01",
    "iso:country": "GB",
    "wof:name": "HU18 1EL",
    "wof:placetype": "postalcode"
  },
  "geometry": {"coordinates":[-0.183836,53.926292],"type":"Point"}
}
