{
  "type": "Feature",
  "properties": {
    "date:inception_lower": "1999-06-01",
    "date:inception_upper": "1999-06-01",
    "iso:country": "GB",
    "wof:name": "DN15 8EF",
    "wof:placetype": "postalcode"
  },
  "geometry": {"coordinates":[-0.682586,53.593888],"type":"Point"}
}
