{
  "type": "Feature",
  "properties": {
    "date:inception_lower": "1992-08-01",
    "date:inception_upper": "1992-08-01",
    "iso:country": "GB",
    "wof:name": "WN7 4JT",
    "wof:placetype": "postalcode"
  },
  "geometry": {"coordinates":[-2.522243,53.494005],"type":"Point"}
}
