{
  "type": "Feature",
  "properties": {
    "iso:country":"GB",
    "wof:name":"BB4 5TF",
    "wof:placetype":"postalcode"
},
  "geometry": {"coordinates":[-2.32325110667796,53.70412730573427],"type":"Point"}
}