{
  "type": "Feature",
  "properties": {
    "iso:country": "GB",
    "wof:name": "SW14 7NW",
    "wof:placetype": "postalcode"
  },
  "geometry": {"coordinates":[-0.274911,51.46651],"type":"Point"}
}
