{
  "type": "Feature",
  "properties": {
    "iso:country":"GB",
    "wof:name":"SW14 7NW",
    "wof:placetype":"postalcode"
},
  "geometry": {"coordinates":[-0.27491095476216,51.46650965490085],"type":"Point"}
}