{
  "type": "Feature",
  "properties": {
    "iso:country": "GB",
    "wof:name": "NN9 5HU",
    "wof:placetype": "postalcode"
  },
  "geometry": {"coordinates":[-0.65238,52.338472],"type":"Point"}
}
