{
  "type": "Feature",
  "properties": {
    "iso:country":"GB",
    "wof:name":"NN9 5HU",
    "wof:placetype":"postalcode"
},
  "geometry": {"coordinates":[-0.65238030329226,52.33847195851975],"type":"Point"}
}