{
  "type": "Feature",
  "properties": {
    "date:inception_lower":"1987-04-01",
    "date:inception_upper":"1987-04-30",
    "iso:country":"GB",
    "wof:name":"NN9 5HU",
    "wof:placetype":"postalcode"
},
  "geometry": {"coordinates":[-0.65238,52.338472],"type":"Point"}
}