{
  "type": "Feature",
  "properties": {
    "iso:country":"GB",
    "wof:name":"B63 3HN",
    "wof:placetype":"postalcode"
},
  "geometry": {"coordinates":[-2.04905609587892,52.4491972416293],"type":"Point"}
}