{
  "type": "Feature",
  "properties": {
    "iso:country": "GB",
    "wof:name": "NP11 6GA",
    "wof:placetype": "postalcode"
  },
  "geometry": {"coordinates":[-3.097341,51.612056],"type":"Point"}
}
