{
  "type": "Feature",
  "properties": {
    "iso:country": "GB",
    "wof:name": "BB12 9HE",
    "wof:placetype": "postalcode"
  },
  "geometry": {"coordinates":[-2.29165,53.824033],"type":"Point"}
}
