{
  "type": "Feature",
  "properties": {
    "iso:country":"GB",
    "wof:name":"BB12 9HE",
    "wof:placetype":"postalcode"
},
  "geometry": {"coordinates":[-2.29164957513576,53.82402804754776],"type":"Point"}
}