{
  "type": "Feature",
  "properties": {
    "iso:country":"GB",
    "wof:name":"OL11 1PR",
    "wof:placetype":"postalcode"
},
  "geometry": {"coordinates":[-2.15541771169498,53.60735465261773],"type":"Point"}
}