{
  "type": "Feature",
  "properties": {
    "date:inception_lower":"1980-01-01",
    "date:inception_upper":"1980-01-31",
    "iso:country":"GB",
    "wof:name":"OL11 1PR",
    "wof:placetype":"postalcode"
},
  "geometry": {"coordinates":[-2.155418,53.607355],"type":"Point"}
}