{
  "type": "Feature",
  "properties": {
    "iso:country":"GB",
    "wof:name":"TN8 5AX",
    "wof:placetype":"postalcode"
},
  "geometry": {"coordinates":[0.06611719222255,51.19375948209612],"type":"Point"}
}