{
  "type": "Feature",
  "properties": {
    "iso:country":"GB",
    "wof:name":"OL11 4NE",
    "wof:placetype":"postalcode"
},
  "geometry": {"coordinates":[-2.17260888882029,53.6054435220272],"type":"Point"}
}