{
  "type": "Feature",
  "properties": {
    "iso:country":"GB",
    "wof:name":"WN8 7PF",
    "wof:placetype":"postalcode"
},
  "geometry": {"coordinates":[-2.77276128367974,53.59012830541993],"type":"Point"}
}