{
  "type": "Feature",
  "properties": {
    "date:inception_lower": "2018-03-01",
    "date:inception_upper": "2018-03-01",
    "iso:country": "GB",
    "wof:name": "SE3 9GH",
    "wof:placetype": "postalcode"
  },
  "geometry": {"coordinates":[0.02302,51.459257],"type":"Point"}
}
