{
  "type": "Feature",
  "properties": {
    "date:inception_lower":"1980-01-01",
    "date:inception_upper":"1980-01-31",
    "iso:country":"GB",
    "wof:name":"M24 4PH",
    "wof:placetype":"postalcode"
},
  "geometry": {"coordinates":[-2.218802,53.545856],"type":"Point"}
}