{
  "type": "Feature",
  "properties": {
    "iso:country":"GB",
    "wof:name":"M24 4PH",
    "wof:placetype":"postalcode"
},
  "geometry": {"coordinates":[-2.21880233645001,53.54585628011198],"type":"Point"}
}