{
  "type": "Feature",
  "properties": {
    "date:inception_lower": "1980-01-01",
    "date:inception_upper": "1980-01-01",
    "iso:country": "GB",
    "wof:name": "TQ9 6LN",
    "wof:placetype": "postalcode"
  },
  "geometry": {"coordinates":[-3.652905,50.440146],"type":"Point"}
}
