{
  "type": "Feature",
  "properties": {
    "iso:country": "GB",
    "wof:name": "S61 2RR",
    "wof:placetype": "postalcode"
  },
  "geometry": {"coordinates":[-1.437052,53.462632],"type":"Point"}
}
