{
  "type": "Feature",
  "properties": {
    "iso:country": "GB",
    "wof:name": "M24 4SY",
    "wof:placetype": "postalcode"
  },
  "geometry": {"coordinates":[-2.224402,53.55779],"type":"Point"}
}
