{
  "type": "Feature",
  "properties": {
    "iso:country":"GB",
    "wof:name":"M43 7DT",
    "wof:placetype":"postalcode"
},
  "geometry": {"coordinates":[-2.13649399804754,53.48506440120259],"type":"Point"}
}