{
  "type": "Feature",
  "properties": {
    "date:inception_lower": "1980-01-01",
    "date:inception_upper": "1980-01-01",
    "iso:country": "GB",
    "wof:name": "MK45 5AX",
    "wof:placetype": "postalcode"
  },
  "geometry": {"coordinates":[-0.528646,52.005501],"type":"Point"}
}
