{
  "type": "Feature",
  "properties": {
    "iso:country":"GB",
    "wof:name":"MK45 5AX",
    "wof:placetype":"postalcode"
},
  "geometry": {"coordinates":[-0.52864604936055,52.00550078179532],"type":"Point"}
}