{
  "type": "Feature",
  "properties": {
    "iso:country":"GB",
    "wof:name":"IP13 9JG",
    "wof:placetype":"postalcode"
},
  "geometry": {"coordinates":[1.35518615069255,52.24728798408874],"type":"Point"}
}