{
  "type": "Feature",
  "properties": {
    "iso:country":"GB",
    "wof:name":"BS13 9PN",
    "wof:placetype":"postalcode"
},
  "geometry": {"coordinates":[-2.60701093912881,51.40967331149039],"type":"Point"}
}