{
  "type": "Feature",
  "properties": {
    "iso:country":"GB",
    "wof:name":"L40 8TF",
    "wof:placetype":"postalcode"
},
  "geometry": {"coordinates":[-2.86347121505526,53.59327408598139],"type":"Point"}
}