{
  "type": "Feature",
  "properties": {
    "date:inception_lower": "2001-12-01",
    "date:inception_upper": "2001-12-01",
    "iso:country": "GB",
    "wof:name": "L40 8TF",
    "wof:placetype": "postalcode"
  },
  "geometry": {"coordinates":[-2.863471,53.593274],"type":"Point"}
}
