{
  "type": "Feature",
  "properties": {
    "iso:country": "GB",
    "wof:name": "YO25 5DJ",
    "wof:placetype": "postalcode"
  },
  "geometry": {"coordinates":[-0.436253,54.007183],"type":"Point"}
}
