{
  "type": "Feature",
  "properties": {
    "date:inception_lower": "2021-02-01",
    "date:inception_upper": "2021-02-01",
    "iso:country": "GB",
    "wof:name": "GU23 7BG",
    "wof:placetype": "postalcode"
  },
  "geometry": {"coordinates":[-0.529008,51.292129],"type":"Point"}
}
