{
  "type": "Feature",
  "properties": {
    "iso:country": "GB",
    "wof:name": "SA62 4PF",
    "wof:placetype": "postalcode"
  },
  "geometry": {"coordinates":[-4.939597,51.763912],"type":"Point"}
}
