{
  "type": "Feature",
  "properties": {
    "date:inception_lower":"2016-04-01",
    "date:inception_upper":"2016-04-30",
    "iso:country":"GB",
    "wof:name":"SA62 4PF",
    "wof:placetype":"postalcode"
},
  "geometry": {"coordinates":[-4.939597,51.763912],"type":"Point"}
}