{
  "type": "Feature",
  "properties": {
    "iso:country":"GB",
    "wof:name":"B24 0JL",
    "wof:placetype":"postalcode"
},
  "geometry": {"coordinates":[-1.81489188645119,52.52495632774749],"type":"Point"}
}