{
  "type": "Feature",
  "properties": {
    "iso:country":"GB",
    "wof:name":"RH13 9HT",
    "wof:placetype":"postalcode"
},
  "geometry": {"coordinates":[-0.34518390920844,51.01653112099899],"type":"Point"}
}