{
  "type": "Feature",
  "properties": {
    "iso:country":"GB",
    "wof:name":"ME14 5TT",
    "wof:placetype":"postalcode"
},
  "geometry": {"coordinates":[0.55588497000333,51.27968624785029],"type":"Point"}
}