{
  "type": "Feature",
  "properties": {
    "iso:country":"GB",
    "wof:name":"RH13 6QA",
    "wof:placetype":"postalcode"
},
  "geometry": {"coordinates":[-0.30675269205727,51.05354425945424],"type":"Point"}
}