{
  "type": "Feature",
  "properties": {
    "iso:country":"GB",
    "wof:name":"EH39 4NF",
    "wof:placetype":"postalcode"
},
  "geometry": {"coordinates":[-2.73646639670269,56.0583124582147],"type":"Point"}
}