{
  "type": "Feature",
  "properties": {
    "iso:country": "GB",
    "wof:name": "N18 1AD",
    "wof:placetype": "postalcode"
  },
  "geometry": {"coordinates":[-0.08739,51.60883],"type":"Point"}
}
