{
  "type": "Feature",
  "properties": {
    "iso:country": "GB",
    "wof:name": "HP2 6HZ",
    "wof:placetype": "postalcode"
  },
  "geometry": {"coordinates":[-0.494032,51.811142],"type":"Point"}
}
