{
  "type": "Feature",
  "properties": {
    "iso:country":"GB",
    "wof:name":"SG5 3QN",
    "wof:placetype":"postalcode"
},
  "geometry": {"coordinates":[-0.33636101220714,51.97722599306704],"type":"Point"}
}