{
  "type": "Feature",
  "properties": {
    "iso:country":"GB",
    "wof:name":"W1T 1SW",
    "wof:placetype":"postalcode"
},
  "geometry": {"coordinates":[-0.13599769594962,51.5190041736201],"type":"Point"}
}