{
  "type": "Feature",
  "properties": {
    "iso:country": "GB",
    "wof:name": "N9 9RF",
    "wof:placetype": "postalcode"
  },
  "geometry": {"coordinates":[-0.072794,51.624391],"type":"Point"}
}
