{
  "type": "Feature",
  "properties": {
    "date:inception_lower":"1980-01-01",
    "date:inception_upper":"1980-01-31",
    "iso:country":"GB",
    "wof:name":"N9 9RF",
    "wof:placetype":"postalcode"
},
  "geometry": {"coordinates":[-0.072794,51.624391],"type":"Point"}
}