{
  "type": "Feature",
  "properties": {
    "iso:country":"GB",
    "wof:name":"N9 9RF",
    "wof:placetype":"postalcode"
},
  "geometry": {"coordinates":[-0.07279439072398,51.62439104128256],"type":"Point"}
}