{
  "type": "Feature",
  "properties": {
    "date:inception_lower": "1980-01-01",
    "date:inception_upper": "1980-01-01",
    "iso:country": "GB",
    "wof:name": "NW3 7PR",
    "wof:placetype": "postalcode"
  },
  "geometry": {"coordinates":[-0.195188,51.559649],"type":"Point"}
}
