{
  "type": "Feature",
  "properties": {
    "iso:country": "GB",
    "wof:name": "BH24 3DG",
    "wof:placetype": "postalcode"
  },
  "geometry": {"coordinates":[-1.759959,50.838108],"type":"Point"}
}
