{
  "type": "Feature",
  "properties": {
    "iso:country":"GB",
    "wof:name":"BH24 3DG",
    "wof:placetype":"postalcode"
},
  "geometry": {"coordinates":[-1.75995865672476,50.83810801974132],"type":"Point"}
}