{
  "type": "Feature",
  "properties": {
    "iso:country":"GB",
    "wof:name":"TS5 7LZ",
    "wof:placetype":"postalcode"
},
  "geometry": {"coordinates":[-1.24212910653356,54.54567422746451],"type":"Point"}
}