{
  "type": "Feature",
  "properties": {
    "iso:country":"GB",
    "wof:name":"OX11 0BE",
    "wof:placetype":"postalcode"
},
  "geometry": {"coordinates":[-1.25843797380476,51.59909318480839],"type":"Point"}
}