{
  "type": "Feature",
  "properties": {
    "date:inception_lower": "2008-03-01",
    "date:inception_upper": "2008-03-01",
    "iso:country": "GB",
    "wof:name": "SA70 8BA",
    "wof:placetype": "postalcode"
  },
  "geometry": {"coordinates":[-4.771624,51.678551],"type":"Point"}
}
