{
  "type": "Feature",
  "properties": {
    "iso:country":"GB",
    "wof:name":"SA70 8BA",
    "wof:placetype":"postalcode"
},
  "geometry": {"coordinates":[-4.77162358638053,51.67855075904859],"type":"Point"}
}