{
  "type": "Feature",
  "properties": {
    "iso:country":"GB",
    "wof:name":"SN9 6DR",
    "wof:placetype":"postalcode"
},
  "geometry": {"coordinates":[-1.81379077115181,51.30252424485175],"type":"Point"}
}