{
  "type": "Feature",
  "properties": {
    "date:inception_lower": "1980-01-01",
    "date:inception_upper": "1980-01-01",
    "iso:country": "GB",
    "wof:name": "SN9 6DR",
    "wof:placetype": "postalcode"
  },
  "geometry": {"coordinates":[-1.813791,51.302524],"type":"Point"}
}
