{
  "type": "Feature",
  "properties": {
    "iso:country": "GB",
    "wof:name": "SN9 6DR",
    "wof:placetype": "postalcode"
  },
  "geometry": {"coordinates":[-1.813791,51.302524],"type":"Point"}
}
