{
  "type": "Feature",
  "properties": {
    "iso:country":"GB",
    "wof:name":"KT4 7SU",
    "wof:placetype":"postalcode"
},
  "geometry": {"coordinates":[-0.24674433095848,51.3858606787476],"type":"Point"}
}