{
  "type": "Feature",
  "properties": {
    "iso:country": "GB",
    "wof:name": "TN22 4PR",
    "wof:placetype": "postalcode"
  },
  "geometry": {"coordinates":[0.138744,50.981861],"type":"Point"}
}
