{
  "type": "Feature",
  "properties": {
    "iso:country":"GB",
    "wof:name":"TN22 4PR",
    "wof:placetype":"postalcode"
},
  "geometry": {"coordinates":[0.13870502411373,50.98223371369364],"type":"Point"}
}