{
  "type": "Feature",
  "properties": {
    "iso:country":"GB",
    "wof:name":"CA2 5DX",
    "wof:placetype":"postalcode"
},
  "geometry": {"coordinates":[-2.94024960854882,54.8897870720603],"type":"Point"}
}