{
  "type": "Feature",
  "properties": {
    "date:inception_lower": "1980-01-01",
    "date:inception_upper": "1980-01-01",
    "iso:country": "GB",
    "wof:name": "EH16 5PH",
    "wof:placetype": "postalcode"
  },
  "geometry": {"coordinates":[-3.16868,55.929705],"type":"Point"}
}
