{
  "type": "Feature",
  "properties": {
    "iso:country":"GB",
    "wof:name":"EH16 5PH",
    "wof:placetype":"postalcode"
},
  "geometry": {"coordinates":[-3.16853539851638,55.92973866664369],"type":"Point"}
}