{
  "type": "Feature",
  "properties": {
    "iso:country": "GB",
    "wof:name": "SS5 5HL",
    "wof:placetype": "postalcode"
  },
  "geometry": {"coordinates":[0.666169,51.61029],"type":"Point"}
}
