{
  "type": "Feature",
  "properties": {
    "iso:country":"GB",
    "wof:name":"SS5 5HL",
    "wof:placetype":"postalcode"
},
  "geometry": {"coordinates":[0.66616932328561,51.61028987819941],"type":"Point"}
}