{
  "type": "Feature",
  "properties": {
    "date:inception_lower":"2015-10-01",
    "date:inception_upper":"2015-10-31",
    "iso:country":"GB",
    "wof:name":"MK18 1WF",
    "wof:placetype":"postalcode"
},
  "geometry": {"coordinates":[-0.979594,52.010503],"type":"Point"}
}