{
  "type": "Feature",
  "properties": {
    "iso:country":"GB",
    "wof:name":"S80 2HP",
    "wof:placetype":"postalcode"
},
  "geometry": {"coordinates":[-1.11770098977524,53.30263177245917],"type":"Point"}
}