{
  "type": "Feature",
  "properties": {
    "iso:country":"GB",
    "wof:name":"E1 2QE",
    "wof:placetype":"postalcode"
},
  "geometry": {"coordinates":[-0.05640406496055,51.51155232275958],"type":"Point"}
}