{
  "type": "Feature",
  "properties": {
    "date:inception_lower": "1980-01-01",
    "date:inception_upper": "1980-01-01",
    "iso:country": "GB",
    "wof:name": "E1 2QE",
    "wof:placetype": "postalcode"
  },
  "geometry": {"coordinates":[-0.056404,51.511552],"type":"Point"}
}
