{
  "type": "Feature",
  "properties": {
    "iso:country": "GB",
    "wof:name": "TN13 1NU",
    "wof:placetype": "postalcode"
  },
  "geometry": {"coordinates":[0.18555,51.267699],"type":"Point"}
}
