{
  "type": "Feature",
  "properties": {
    "iso:country":"GB",
    "wof:name":"TN13 1NU",
    "wof:placetype":"postalcode"
},
  "geometry": {"coordinates":[0.1855498480672,51.26769915989755],"type":"Point"}
}