{
  "type": "Feature",
  "properties": {
    "date:inception_lower": "1980-01-01",
    "date:inception_upper": "1980-01-01",
    "iso:country": "GB",
    "wof:name": "LE6 0HE",
    "wof:placetype": "postalcode"
  },
  "geometry": {"coordinates":[-1.204999,52.689512],"type":"Point"}
}
