{
  "type": "Feature",
  "properties": {
    "iso:country":"GB",
    "wof:name":"LE6 0HE",
    "wof:placetype":"postalcode"
},
  "geometry": {"coordinates":[-1.20499907212168,52.68951152774881],"type":"Point"}
}