{
  "type": "Feature",
  "properties": {
    "iso:country": "GB",
    "wof:name": "HD9 4HL",
    "wof:placetype": "postalcode"
  },
  "geometry": {"coordinates":[-1.835697,53.591389],"type":"Point"}
}
