{
  "type": "Feature",
  "properties": {
    "iso:country":"GB",
    "wof:name":"HD9 4HL",
    "wof:placetype":"postalcode"
},
  "geometry": {"coordinates":[-1.83569666381293,53.59138931432094],"type":"Point"}
}