{
  "type": "Feature",
  "properties": {
    "iso:country":"GB",
    "wof:name":"CA14 4QD",
    "wof:placetype":"postalcode"
},
  "geometry": {"coordinates":[-3.51571194297796,54.58387296316065],"type":"Point"}
}