{
  "type": "Feature",
  "properties": {
    "date:inception_lower": "1980-01-01",
    "date:inception_upper": "1980-01-01",
    "iso:country": "GB",
    "wof:name": "CA14 4QD",
    "wof:placetype": "postalcode"
  },
  "geometry": {"coordinates":[-3.515712,54.583873],"type":"Point"}
}
