{
  "type": "Feature",
  "properties": {
    "iso:country": "GB",
    "wof:name": "ST7 4SJ",
    "wof:placetype": "postalcode"
  },
  "geometry": {"coordinates":[-2.194687,53.088113],"type":"Point"}
}
