{
  "type": "Feature",
  "properties": {
    "iso:country":"GB",
    "wof:name":"ST7 4SJ",
    "wof:placetype":"postalcode"
},
  "geometry": {"coordinates":[-2.19468690380738,53.08811263421374],"type":"Point"}
}