{
  "type": "Feature",
  "properties": {
    "date:inception_lower": "1980-01-01",
    "date:inception_upper": "1980-01-01",
    "iso:country": "GB",
    "wof:name": "ST7 4SJ",
    "wof:placetype": "postalcode"
  },
  "geometry": {"coordinates":[-2.194687,53.088113],"type":"Point"}
}
