{
  "type": "Feature",
  "properties": {
    "iso:country":"GB",
    "wof:name":"CF48 1DR",
    "wof:placetype":"postalcode"
},
  "geometry": {"coordinates":[-3.38673042037496,51.74815914919389],"type":"Point"}
}