{
  "type": "Feature",
  "properties": {
    "iso:country":"GB",
    "wof:name":"SK4 1TD",
    "wof:placetype":"postalcode"
},
  "geometry": {"coordinates":[-2.16304200672136,53.41701517195514],"type":"Point"}
}