{
  "type": "Feature",
  "properties": {
    "date:inception_lower":"1980-01-01",
    "date:inception_upper":"1980-01-31",
    "iso:country":"GB",
    "wof:name":"SK4 1TD",
    "wof:placetype":"postalcode"
},
  "geometry": {"coordinates":[-2.163042,53.417015],"type":"Point"}
}