{
  "type": "Feature",
  "properties": {
    "date:inception_lower":"1987-04-01",
    "date:inception_upper":"1987-04-30",
    "iso:country":"GB",
    "wof:name":"LE15 6HP",
    "wof:placetype":"postalcode"
},
  "geometry": {"coordinates":[-0.724806,52.668256],"type":"Point"}
}