{
  "type": "Feature",
  "properties": {
    "iso:country": "GB",
    "wof:name": "TA18 8AH",
    "wof:placetype": "postalcode"
  },
  "geometry": {"coordinates":[-2.7865,50.879613],"type":"Point"}
}
