{
  "type": "Feature",
  "properties": {
    "iso:country":"GB",
    "wof:name":"OX12 9SB",
    "wof:placetype":"postalcode"
},
  "geometry": {"coordinates":[-1.45507250967625,51.590009903356],"type":"Point"}
}