{
  "type": "Feature",
  "properties": {
    "iso:country": "GB",
    "wof:name": "OX12 9SB",
    "wof:placetype": "postalcode"
  },
  "geometry": {"coordinates":[-1.455072,51.59001],"type":"Point"}
}
