{
  "type": "Feature",
  "properties": {
    "iso:country":"GB",
    "wof:name":"OX29 4NP",
    "wof:placetype":"postalcode"
},
  "geometry": {"coordinates":[-1.37935330700167,51.78643560977198],"type":"Point"}
}