{
  "type": "Feature",
  "properties": {
    "iso:country":"GB",
    "wof:name":"TR18 4JP",
    "wof:placetype":"postalcode"
},
  "geometry": {"coordinates":[-5.54745154739962,50.12012913256084],"type":"Point"}
}