{
  "type": "Feature",
  "properties": {
    "iso:country":"GB",
    "wof:name":"KY11 9LJ",
    "wof:placetype":"postalcode"
},
  "geometry": {"coordinates":[-3.33757236079604,56.04019529861734],"type":"Point"}
}