{
  "type": "Feature",
  "properties": {
    "iso:country": "GB",
    "wof:name": "KY11 9LJ",
    "wof:placetype": "postalcode"
  },
  "geometry": {"coordinates":[-3.337572,56.040195],"type":"Point"}
}
