{
  "type": "Feature",
  "properties": {
    "iso:country":"GB",
    "wof:name":"TD1 3JG",
    "wof:placetype":"postalcode"
},
  "geometry": {"coordinates":[-2.80968317569361,55.61315572197631],"type":"Point"}
}