{
  "type": "Feature",
  "properties": {
    "iso:country":"GB",
    "wof:name":"DN6 8HH",
    "wof:placetype":"postalcode"
},
  "geometry": {"coordinates":[-1.18934910734325,53.58297788071871],"type":"Point"}
}