{
  "type": "Feature",
  "properties": {
    "iso:country": "GB",
    "wof:name": "DN6 8HH",
    "wof:placetype": "postalcode"
  },
  "geometry": {"coordinates":[-1.189349,53.582978],"type":"Point"}
}
