{
  "type": "Feature",
  "properties": {
    "iso:country":"GB",
    "wof:name":"M14 4US",
    "wof:placetype":"postalcode"
},
  "geometry": {"coordinates":[-2.24296986553326,53.45473881379014],"type":"Point"}
}