{
  "type": "Feature",
  "properties": {
    "iso:country":"GB",
    "wof:name":"NE71 6JW",
    "wof:placetype":"postalcode"
},
  "geometry": {"coordinates":[-2.01886113545508,55.60556703986323],"type":"Point"}
}