{
  "type": "Feature",
  "properties": {
    "date:inception_lower": "1980-01-01",
    "date:inception_upper": "1980-01-01",
    "iso:country": "GB",
    "wof:name": "NE71 6JW",
    "wof:placetype": "postalcode"
  },
  "geometry": {"coordinates":[-2.018861,55.605567],"type":"Point"}
}
