{
  "type": "Feature",
  "properties": {
    "iso:country": "GB",
    "wof:name": "PO18 8NU",
    "wof:placetype": "postalcode"
  },
  "geometry": {"coordinates":[-0.849033,50.834785],"type":"Point"}
}
