{
  "type": "Feature",
  "properties": {
    "date:inception_lower": "2009-02-01",
    "date:inception_upper": "2009-02-01",
    "iso:country": "GB",
    "wof:name": "DY1 4AH",
    "wof:placetype": "postalcode"
  },
  "geometry": {"coordinates":[-2.073404,52.517868],"type":"Point"}
}
