{
  "type": "Feature",
  "properties": {
    "iso:country":"GB",
    "wof:name":"DG8 6RT",
    "wof:placetype":"postalcode"
},
  "geometry": {"coordinates":[-4.62600347870337,55.0187594597592],"type":"Point"}
}