{
  "type": "Feature",
  "properties": {
    "date:inception_lower": "2019-03-01",
    "date:inception_upper": "2019-03-01",
    "iso:country": "GB",
    "wof:name": "CF24 0JU",
    "wof:placetype": "postalcode"
  },
  "geometry": {"coordinates":[-3.163775,51.484021],"type":"Point"}
}
