{
  "type": "Feature",
  "properties": {
    "iso:country": "GB",
    "wof:name": "CF24 0JU",
    "wof:placetype": "postalcode"
  },
  "geometry": {"coordinates":[-3.163916,51.483884],"type":"Point"}
}
