{
  "type": "Feature",
  "properties": {
    "date:inception_lower":"2019-03-01",
    "date:inception_upper":"2019-03-31",
    "iso:country":"GB",
    "wof:name":"CF24 0JU",
    "wof:placetype":"postalcode"
},
  "geometry": {"coordinates":[-3.163916,51.483884],"type":"Point"}
}