{
  "type": "Feature",
  "properties": {
    "iso:country":"GB",
    "wof:name":"M8 5UJ",
    "wof:placetype":"postalcode"
},
  "geometry": {"coordinates":[-2.23267026626544,53.51266294246662],"type":"Point"}
}