{
  "type": "Feature",
  "properties": {
    "iso:country":"GB",
    "wof:name":"TS26 0UD",
    "wof:placetype":"postalcode"
},
  "geometry": {"coordinates":[-1.23558900389528,54.69944525203353],"type":"Point"}
}