{
  "type": "Feature",
  "properties": {
    "date:inception_lower": "1980-01-01",
    "date:inception_upper": "1980-01-01",
    "iso:country": "GB",
    "wof:name": "SG4 9LW",
    "wof:placetype": "postalcode"
  },
  "geometry": {"coordinates":[-0.266109,51.943777],"type":"Point"}
}
