{
  "type": "Feature",
  "properties": {
    "iso:country":"GB",
    "wof:name":"SG4 9LW",
    "wof:placetype":"postalcode"
},
  "geometry": {"coordinates":[-0.266132421624,51.94377069366013],"type":"Point"}
}