{
  "type": "Feature",
  "properties": {
    "iso:country":"GB",
    "wof:name":"SG3 6EY",
    "wof:placetype":"postalcode"
},
  "geometry": {"coordinates":[-0.18331354941684,51.86565884966072],"type":"Point"}
}