{
  "type": "Feature",
  "properties": {
    "iso:country": "GB",
    "wof:name": "SG3 6EY",
    "wof:placetype": "postalcode"
  },
  "geometry": {"coordinates":[-0.183257,51.865747],"type":"Point"}
}
