{
  "type": "Feature",
  "properties": {
    "iso:country":"GB",
    "wof:name":"BL4 7EF",
    "wof:placetype":"postalcode"
},
  "geometry": {"coordinates":[-2.40740000148732,53.54737553944054],"type":"Point"}
}