{
  "type": "Feature",
  "properties": {
    "iso:country": "GB",
    "wof:name": "YO30 4WH",
    "wof:placetype": "postalcode"
  },
  "geometry": {"coordinates":[-1.098589,53.986398],"type":"Point"}
}
