{
  "type": "Feature",
  "properties": {
    "iso:country":"GB",
    "wof:name":"YO30 4WH",
    "wof:placetype":"postalcode"
},
  "geometry": {"coordinates":[-1.09858878730041,53.98639818006161],"type":"Point"}
}