{
  "type": "Feature",
  "properties": {
    "iso:country":"GB",
    "wof:name":"PH4 1AB",
    "wof:placetype":"postalcode"
},
  "geometry": {"coordinates":[-3.7838503986441,56.26195995475458],"type":"Point"}
}