{
  "type": "Feature",
  "properties": {
    "iso:country": "GB",
    "wof:name": "PH4 1AB",
    "wof:placetype": "postalcode"
  },
  "geometry": {"coordinates":[-3.784625,56.261734],"type":"Point"}
}
