{
  "type": "Feature",
  "properties": {
    "date:inception_lower": "2011-10-01",
    "date:inception_upper": "2011-10-01",
    "iso:country": "GB",
    "wof:name": "PH4 1AB",
    "wof:placetype": "postalcode"
  },
  "geometry": {"coordinates":[-3.784625,56.261734],"type":"Point"}
}
