{
  "type": "Feature",
  "properties": {
    "iso:country":"GB",
    "wof:name":"N8 0EE",
    "wof:placetype":"postalcode"
},
  "geometry": {"coordinates":[-0.10711833938994,51.58939349308658],"type":"Point"}
}