{
  "type": "Feature",
  "properties": {
    "date:inception_lower": "2023-01-01",
    "date:inception_upper": "2023-01-01",
    "iso:country": "GB",
    "wof:name": "PH33 6FL",
    "wof:placetype": "postalcode"
  },
  "geometry": {"coordinates":[-5.109935,56.818875],"type":"Point"}
}
