{
  "type": "Feature",
  "properties": {
    "date:inception_lower": "2018-10-01",
    "date:inception_upper": "2018-10-01",
    "iso:country": "GB",
    "wof:name": "BN6 9YN",
    "wof:placetype": "postalcode"
  },
  "geometry": {"coordinates":[-0.173473,50.940233],"type":"Point"}
}
