{
  "type": "Feature",
  "properties": {
    "iso:country":"GB",
    "wof:name":"TR10 8RH",
    "wof:placetype":"postalcode"
},
  "geometry": {"coordinates":[-5.11465140083549,50.17121404739218],"type":"Point"}
}