{
  "type": "Feature",
  "properties": {
    "iso:country":"GB",
    "wof:name":"PO39 0EY",
    "wof:placetype":"postalcode"
},
  "geometry": {"coordinates":[-1.54046806409091,50.67948540718412],"type":"Point"}
}