{
  "type": "Feature",
  "properties": {
    "date:inception_lower": "1980-01-01",
    "date:inception_upper": "1980-01-01",
    "iso:country": "GB",
    "wof:name": "PO39 0EY",
    "wof:placetype": "postalcode"
  },
  "geometry": {"coordinates":[-1.540468,50.679485],"type":"Point"}
}
