{
  "type": "Feature",
  "properties": {
    "iso:country": "GB",
    "wof:name": "PE13 5NU",
    "wof:placetype": "postalcode"
  },
  "geometry": {"coordinates":[0.056883,52.705479],"type":"Point"}
}
