{
  "type": "Feature",
  "properties": {
    "iso:country":"GB",
    "wof:name":"PE13 5NU",
    "wof:placetype":"postalcode"
},
  "geometry": {"coordinates":[0.05728840213322,52.70559610301564],"type":"Point"}
}