{
  "type": "Feature",
  "properties": {
    "iso:country":"GB",
    "wof:name":"B32 2SX",
    "wof:placetype":"postalcode"
},
  "geometry": {"coordinates":[-1.98794683498055,52.45947351339424],"type":"Point"}
}