{
  "type": "Feature",
  "properties": {
    "iso:country":"GB",
    "wof:name":"NN11 4SA",
    "wof:placetype":"postalcode"
},
  "geometry": {"coordinates":[-1.15348853015866,52.24792364459167],"type":"Point"}
}