{
  "type": "Feature",
  "properties": {
    "iso:country":"GB",
    "wof:name":"RM15 5FT",
    "wof:placetype":"postalcode"
},
  "geometry": {"coordinates":[0.28894494739365,51.51746968958447],"type":"Point"}
}