{
  "type": "Feature",
  "properties": {
    "iso:country":"GB",
    "wof:name":"L20 3AZ",
    "wof:placetype":"postalcode"
},
  "geometry": {"coordinates":[-2.98516344967627,53.44792027189192],"type":"Point"}
}