{
  "type": "Feature",
  "properties": {
    "iso:country":"GB",
    "wof:name":"LE15 9DP",
    "wof:placetype":"postalcode"
},
  "geometry": {"coordinates":[-0.63596539575403,52.59531678931579],"type":"Point"}
}