{
  "type": "Feature",
  "properties": {
    "date:inception_lower":"2004-05-01",
    "date:inception_upper":"2004-05-31",
    "iso:country":"GB",
    "wof:name":"LE15 9DP",
    "wof:placetype":"postalcode"
},
  "geometry": {"coordinates":[-0.635965,52.595317],"type":"Point"}
}