{
  "type": "Feature",
  "properties": {
    "iso:country":"GB",
    "wof:name":"NW3 5AB",
    "wof:placetype":"postalcode"
},
  "geometry": {"coordinates":[-0.16930132707349,51.55223420653671],"type":"Point"}
}