{
  "type": "Feature",
  "properties": {
    "date:inception_lower": "1980-01-01",
    "date:inception_upper": "1980-01-01",
    "iso:country": "GB",
    "wof:name": "CW12 2JY",
    "wof:placetype": "postalcode"
  },
  "geometry": {"coordinates":[-2.275258,53.198518],"type":"Point"}
}
