{
  "type": "Feature",
  "properties": {
    "iso:country":"GB",
    "wof:name":"TQ12 5LS",
    "wof:placetype":"postalcode"
},
  "geometry": {"coordinates":[-3.58742112916168,50.48692579138329],"type":"Point"}
}