{
  "type": "Feature",
  "properties": {
    "iso:country":"GB",
    "wof:name":"NE5 2PZ",
    "wof:placetype":"postalcode"
},
  "geometry": {"coordinates":[-1.68576042139956,54.99413516928239],"type":"Point"}
}