{
  "type": "Feature",
  "properties": {
    "iso:country": "GB",
    "wof:name": "NE5 2PZ",
    "wof:placetype": "postalcode"
  },
  "geometry": {"coordinates":[-1.68576,54.994135],"type":"Point"}
}
