{
  "type": "Feature",
  "properties": {
    "iso:country": "GB",
    "wof:name": "SG9 9BQ",
    "wof:placetype": "postalcode"
  },
  "geometry": {"coordinates":[-0.019407,51.950183],"type":"Point"}
}
