{
  "type": "Feature",
  "properties": {
    "date:inception_lower": "1994-05-01",
    "date:inception_upper": "1994-05-01",
    "iso:country": "GB",
    "wof:name": "LE2 7TG",
    "wof:placetype": "postalcode"
  },
  "geometry": {"coordinates":[-1.129059,52.616483],"type":"Point"}
}
