{
  "type": "Feature",
  "properties": {
    "iso:country":"GB",
    "wof:name":"DG7 2ER",
    "wof:placetype":"postalcode"
},
  "geometry": {"coordinates":[-4.25348703220462,54.85286878464024],"type":"Point"}
}