{
  "type": "Feature",
  "properties": {
    "date:inception_lower": "1994-05-01",
    "date:inception_upper": "1994-05-01",
    "iso:country": "GB",
    "wof:name": "M24 6BJ",
    "wof:placetype": "postalcode"
  },
  "geometry": {"coordinates":[-2.193451,53.55638],"type":"Point"}
}
