{
  "type": "Feature",
  "properties": {
    "iso:country": "GB",
    "wof:name": "M24 6BJ",
    "wof:placetype": "postalcode"
  },
  "geometry": {"coordinates":[-2.193451,53.55638],"type":"Point"}
}
