{
  "type": "Feature",
  "properties": {
    "iso:country": "GB",
    "wof:name": "RH10 7HF",
    "wof:placetype": "postalcode"
  },
  "geometry": {"coordinates":[-0.146887,51.107496],"type":"Point"}
}
