{
  "type": "Feature",
  "properties": {
    "iso:country":"GB",
    "wof:name":"RH10 7HF",
    "wof:placetype":"postalcode"
},
  "geometry": {"coordinates":[-0.1468871109208,51.10749642492166],"type":"Point"}
}