{
  "type": "Feature",
  "properties": {
    "iso:country":"GB",
    "wof:name":"SE15 3DG",
    "wof:placetype":"postalcode"
},
  "geometry": {"coordinates":[-0.04935216087512,51.45698473149194],"type":"Point"}
}