{
  "type": "Feature",
  "properties": {
    "iso:country":"GB",
    "wof:name":"KA21 5AS",
    "wof:placetype":"postalcode"
},
  "geometry": {"coordinates":[-4.79641297847723,55.64165903976257],"type":"Point"}
}