{
  "type": "Feature",
  "properties": {
    "iso:country":"GB",
    "wof:name":"FY1 3LW",
    "wof:placetype":"postalcode"
},
  "geometry": {"coordinates":[-3.04331136809401,53.82096754745603],"type":"Point"}
}