{
  "type": "Feature",
  "properties": {
    "iso:country": "GB",
    "wof:name": "CT21 6EY",
    "wof:placetype": "postalcode"
  },
  "geometry": {"coordinates":[1.080344,51.066147],"type":"Point"}
}
