{
  "type": "Feature",
  "properties": {
    "iso:country":"GB",
    "wof:name":"IV54 8YT",
    "wof:placetype":"postalcode"
},
  "geometry": {"coordinates":[-5.47983033870551,57.40479456546083],"type":"Point"}
}