{
  "type": "Feature",
  "properties": {
    "iso:country":"GB",
    "wof:name":"IP20 0AH",
    "wof:placetype":"postalcode"
},
  "geometry": {"coordinates":[1.36183220296381,52.44351161437248],"type":"Point"}
}