{
  "type": "Feature",
  "properties": {
    "iso:country":"GB",
    "wof:name":"GL6 8BH",
    "wof:placetype":"postalcode"
},
  "geometry": {"coordinates":[-2.15313381548497,51.72757915124097],"type":"Point"}
}