{
  "type": "Feature",
  "properties": {
    "date:inception_lower": "1980-01-01",
    "date:inception_upper": "1980-01-01",
    "iso:country": "GB",
    "wof:name": "GL6 8BH",
    "wof:placetype": "postalcode"
  },
  "geometry": {"coordinates":[-2.153134,51.727579],"type":"Point"}
}
