{
  "type": "Feature",
  "properties": {
    "iso:country":"GB",
    "wof:name":"CW5 6DD",
    "wof:placetype":"postalcode"
},
  "geometry": {"coordinates":[-2.54691504407029,53.11466508908772],"type":"Point"}
}