{
  "type": "Feature",
  "properties": {
    "date:inception_lower": "1980-01-01",
    "date:inception_upper": "1980-01-01",
    "iso:country": "GB",
    "wof:name": "CW5 6DD",
    "wof:placetype": "postalcode"
  },
  "geometry": {"coordinates":[-2.54696,53.114691],"type":"Point"}
}
