{
  "type": "Feature",
  "properties": {
    "iso:country":"GB",
    "wof:name":"B10 9QS",
    "wof:placetype":"postalcode"
},
  "geometry": {"coordinates":[-1.85406176836542,52.47351666275743],"type":"Point"}
}