{
  "type": "Feature",
  "properties": {
    "date:inception_lower":"1980-01-01",
    "date:inception_upper":"1980-01-31",
    "iso:country":"GB",
    "wof:name":"CF37 2HY",
    "wof:placetype":"postalcode"
},
  "geometry": {"coordinates":[-3.346352,51.604104],"type":"Point"}
}