{
  "type": "Feature",
  "properties": {
    "iso:country":"GB",
    "wof:name":"BB4 8DE",
    "wof:placetype":"postalcode"
},
  "geometry": {"coordinates":[-2.28710809948408,53.71527483952667],"type":"Point"}
}