{
  "type": "Feature",
  "properties": {
    "date:inception_lower": "2019-01-01",
    "date:inception_upper": "2019-01-01",
    "iso:country": "GB",
    "wof:name": "SO45 2AQ",
    "wof:placetype": "postalcode"
  },
  "geometry": {"coordinates":[-1.389174,50.838286],"type":"Point"}
}
