{
  "type": "Feature",
  "properties": {
    "iso:country": "GB",
    "wof:name": "OX12 9RA",
    "wof:placetype": "postalcode"
  },
  "geometry": {"coordinates":[-1.490999,51.610824],"type":"Point"}
}
