{
  "type": "Feature",
  "properties": {
    "date:inception_lower": "1980-01-01",
    "date:inception_upper": "1980-01-01",
    "iso:country": "GB",
    "wof:name": "OX12 9RA",
    "wof:placetype": "postalcode"
  },
  "geometry": {"coordinates":[-1.490999,51.610824],"type":"Point"}
}
