{
  "type": "Feature",
  "properties": {
    "iso:country":"GB",
    "wof:name":"OX12 9RA",
    "wof:placetype":"postalcode"
},
  "geometry": {"coordinates":[-1.4909990171311,51.61082432585414],"type":"Point"}
}