{
  "type": "Feature",
  "properties": {
    "iso:country":"GB",
    "wof:name":"BD10 9DA",
    "wof:placetype":"postalcode"
},
  "geometry": {"coordinates":[-1.72848318700521,53.83311840184698],"type":"Point"}
}