{
  "type": "Feature",
  "properties": {
    "date:inception_lower": "2011-11-01",
    "date:inception_upper": "2011-11-01",
    "iso:country": "GB",
    "wof:name": "NG13 8LB",
    "wof:placetype": "postalcode"
  },
  "geometry": {"coordinates":[-0.930038,52.993813],"type":"Point"}
}
