{
  "type": "Feature",
  "properties": {
    "iso:country":"GB",
    "wof:name":"NG13 8LB",
    "wof:placetype":"postalcode"
},
  "geometry": {"coordinates":[-0.9300383905566,52.99381251519961],"type":"Point"}
}