{
  "type": "Feature",
  "properties": {
    "iso:country":"GB",
    "wof:name":"TN12 5BS",
    "wof:placetype":"postalcode"
},
  "geometry": {"coordinates":[0.38448183755788,51.21493513907607],"type":"Point"}
}