{
  "type": "Feature",
  "properties": {
    "iso:country": "GB",
    "wof:name": "TN12 5BS",
    "wof:placetype": "postalcode"
  },
  "geometry": {"coordinates":[0.384482,51.214935],"type":"Point"}
}
