{
  "type": "Feature",
  "properties": {
    "iso:country":"GB",
    "wof:name":"YO12 4TX",
    "wof:placetype":"postalcode"
},
  "geometry": {"coordinates":[-0.42193852366135,54.23999674985503],"type":"Point"}
}