{
  "type": "Feature",
  "properties": {
    "iso:country":"GB",
    "wof:name":"L30 0QD",
    "wof:placetype":"postalcode"
},
  "geometry": {"coordinates":[-2.98258012473293,53.49515090334607],"type":"Point"}
}