{
  "type": "Feature",
  "properties": {
    "iso:country": "GB",
    "wof:name": "NG14 6PA",
    "wof:placetype": "postalcode"
  },
  "geometry": {"coordinates":[-1.084653,53.045525],"type":"Point"}
}
