{
  "type": "Feature",
  "properties": {
    "iso:country":"GB",
    "wof:name":"SN10 1JP",
    "wof:placetype":"postalcode"
},
  "geometry": {"coordinates":[-1.99967790863501,51.35459908947295],"type":"Point"}
}