{
  "type": "Feature",
  "properties": {
    "iso:country": "GB",
    "wof:name": "SN10 1JP",
    "wof:placetype": "postalcode"
  },
  "geometry": {"coordinates":[-1.999678,51.354599],"type":"Point"}
}
