{
  "type": "Feature",
  "properties": {
    "date:inception_lower": "1992-08-01",
    "date:inception_upper": "1992-08-01",
    "iso:country": "GB",
    "wof:name": "SW8 5NQ",
    "wof:placetype": "postalcode"
  },
  "geometry": {"coordinates":[-0.127639,51.484269],"type":"Point"}
}
