{
  "type": "Feature",
  "properties": {
    "date:inception_lower": "2021-05-01",
    "date:inception_upper": "2021-05-01",
    "iso:country": "GB",
    "wof:name": "DD2 9AX",
    "wof:placetype": "postalcode"
  },
  "geometry": {"coordinates":[-3.01205,56.483309],"type":"Point"}
}
