{
  "type": "Feature",
  "properties": {
    "iso:country": "GB",
    "wof:name": "TF3 2EB",
    "wof:placetype": "postalcode"
  },
  "geometry": {"coordinates":[-2.432438,52.673793],"type":"Point"}
}
