{
  "type": "Feature",
  "properties": {
    "iso:country":"GB",
    "wof:name":"TF3 2EB",
    "wof:placetype":"postalcode"
},
  "geometry": {"coordinates":[-2.43243778462098,52.67379286160353],"type":"Point"}
}