{
  "type": "Feature",
  "properties": {
    "iso:country":"GB",
    "wof:name":"AL3 4NA",
    "wof:placetype":"postalcode"
},
  "geometry": {"coordinates":[-0.36072106719475,51.74266639351945],"type":"Point"}
}