{
  "type": "Feature",
  "properties": {
    "iso:country": "GB",
    "wof:name": "AL3 4NA",
    "wof:placetype": "postalcode"
  },
  "geometry": {"coordinates":[-0.360558,51.742553],"type":"Point"}
}
