{
  "type": "Feature",
  "properties": {
    "iso:country":"GB",
    "wof:name":"S8 7RF",
    "wof:placetype":"postalcode"
},
  "geometry": {"coordinates":[-1.4808586560593,53.32604970395249],"type":"Point"}
}