{
  "type": "Feature",
  "properties": {
    "iso:country":"GB",
    "wof:name":"OX13 6QP",
    "wof:placetype":"postalcode"
},
  "geometry": {"coordinates":[-1.34082603000366,51.67144373103257],"type":"Point"}
}