{
  "type": "Feature",
  "properties": {
    "date:inception_lower": "1994-05-01",
    "date:inception_upper": "1994-05-01",
    "iso:country": "GB",
    "wof:name": "OX13 6QP",
    "wof:placetype": "postalcode"
  },
  "geometry": {"coordinates":[-1.340826,51.671444],"type":"Point"}
}
