{
  "type": "Feature",
  "properties": {
    "iso:country": "GB",
    "wof:name": "TA24 5BF",
    "wof:placetype": "postalcode"
  },
  "geometry": {"coordinates":[-3.463992,51.202943],"type":"Point"}
}
