{
  "type": "Feature",
  "properties": {
    "iso:country":"GB",
    "wof:name":"SE10 0HQ",
    "wof:placetype":"postalcode"
},
  "geometry": {"coordinates":[0.0108030978333,51.48679544910025],"type":"Point"}
}