{
  "type": "Feature",
  "properties": {
    "iso:country":"GB",
    "wof:name":"RG1 2ST",
    "wof:placetype":"postalcode"
},
  "geometry": {"coordinates":[-0.96670063021741,51.44964830680255],"type":"Point"}
}