{
  "type": "Feature",
  "properties": {
    "date:inception_lower": "2005-03-01",
    "date:inception_upper": "2005-03-01",
    "iso:country": "GB",
    "wof:name": "ML2 0NN",
    "wof:placetype": "postalcode"
  },
  "geometry": {"coordinates":[-3.938688,55.771776],"type":"Point"}
}
