{
  "type": "Feature",
  "properties": {
    "iso:country":"GB",
    "wof:name":"ML2 0NN",
    "wof:placetype":"postalcode"
},
  "geometry": {"coordinates":[-3.93868780707991,55.7717762011269],"type":"Point"}
}