{
  "type": "Feature",
  "properties": {
    "iso:country": "GB",
    "wof:name": "ML2 0NN",
    "wof:placetype": "postalcode"
  },
  "geometry": {"coordinates":[-3.938688,55.771776],"type":"Point"}
}
