{
  "type": "Feature",
  "properties": {
    "date:inception_lower":"2001-12-01",
    "date:inception_upper":"2001-12-31",
    "iso:country":"GB",
    "wof:name":"EX17 2ET",
    "wof:placetype":"postalcode"
},
  "geometry": {"coordinates":[-3.665619,50.794941],"type":"Point"}
}