{
  "type": "Feature",
  "properties": {
    "iso:country":"GB",
    "wof:name":"EX17 2ET",
    "wof:placetype":"postalcode"
},
  "geometry": {"coordinates":[-3.66561884101879,50.7949405089232],"type":"Point"}
}