{
  "type": "Feature",
  "properties": {
    "iso:country": "GB",
    "wof:name": "EX17 2ET",
    "wof:placetype": "postalcode"
  },
  "geometry": {"coordinates":[-3.665619,50.794941],"type":"Point"}
}
