{
  "type": "Feature",
  "properties": {
    "date:inception_lower": "2020-12-01",
    "date:inception_upper": "2020-12-01",
    "iso:country": "GB",
    "wof:name": "S5 8EA",
    "wof:placetype": "postalcode"
  },
  "geometry": {"coordinates":[-1.472151,53.422127],"type":"Point"}
}
