{
  "type": "Feature",
  "properties": {
    "date:inception_lower": "1985-04-01",
    "date:inception_upper": "1985-04-01",
    "iso:country": "GB",
    "wof:name": "CW12 4AS",
    "wof:placetype": "postalcode"
  },
  "geometry": {"coordinates":[-2.212878,53.158762],"type":"Point"}
}
