{
  "type": "Feature",
  "properties": {
    "iso:country":"GB",
    "wof:name":"CW12 4AS",
    "wof:placetype":"postalcode"
},
  "geometry": {"coordinates":[-2.21287844509099,53.15876190834982],"type":"Point"}
}