{
  "type": "Feature",
  "properties": {
    "iso:country":"GB",
    "wof:name":"DT9 4RT",
    "wof:placetype":"postalcode"
},
  "geometry": {"coordinates":[-2.53608422878042,50.98439124650137],"type":"Point"}
}