{
  "type": "Feature",
  "properties": {
    "iso:country": "GB",
    "wof:name": "DT9 4RT",
    "wof:placetype": "postalcode"
  },
  "geometry": {"coordinates":[-2.536028,50.984359],"type":"Point"}
}
