{
  "type": "Feature",
  "properties": {
    "date:inception_lower": "1980-01-01",
    "date:inception_upper": "1980-01-01",
    "iso:country": "GB",
    "wof:name": "RH11 7NU",
    "wof:placetype": "postalcode"
  },
  "geometry": {"coordinates":[-0.19641,51.130717],"type":"Point"}
}
