{
  "type": "Feature",
  "properties": {
    "iso:country":"GB",
    "wof:name":"RH11 7NU",
    "wof:placetype":"postalcode"
},
  "geometry": {"coordinates":[-0.19641028749562,51.13071739975654],"type":"Point"}
}