{
  "type": "Feature",
  "properties": {
    "iso:country":"GB",
    "wof:name":"NP23 4ES",
    "wof:placetype":"postalcode"
},
  "geometry": {"coordinates":[-3.17373713644081,51.79977113170933],"type":"Point"}
}