{
  "type": "Feature",
  "properties": {
    "iso:country":"GB",
    "wof:name":"PL12 6RY",
    "wof:placetype":"postalcode"
},
  "geometry": {"coordinates":[-4.28846137074063,50.4505227761722],"type":"Point"}
}