{
  "type": "Feature",
  "properties": {
    "iso:country":"GB",
    "wof:name":"WV6 8DN",
    "wof:placetype":"postalcode"
},
  "geometry": {"coordinates":[-2.19461248420673,52.58737477780485],"type":"Point"}
}