{
  "type": "Feature",
  "properties": {
    "date:inception_lower": "1980-01-01",
    "date:inception_upper": "1980-01-01",
    "iso:country": "GB",
    "wof:name": "WV6 8DN",
    "wof:placetype": "postalcode"
  },
  "geometry": {"coordinates":[-2.194612,52.587375],"type":"Point"}
}
