{
  "type": "Feature",
  "properties": {
    "date:inception_lower": "1999-06-01",
    "date:inception_upper": "1999-06-01",
    "iso:country": "GB",
    "wof:name": "GL6 9BH",
    "wof:placetype": "postalcode"
  },
  "geometry": {"coordinates":[-2.148246,51.711788],"type":"Point"}
}
