{
  "type": "Feature",
  "properties": {
    "date:inception_lower": "2009-05-01",
    "date:inception_upper": "2009-05-01",
    "iso:country": "GB",
    "wof:name": "BN8 6BD",
    "wof:placetype": "postalcode"
  },
  "geometry": {"coordinates":[0.144057,50.870736],"type":"Point"}
}
