{
  "type": "Feature",
  "properties": {
    "iso:country":"GB",
    "wof:name":"BN8 6BD",
    "wof:placetype":"postalcode"
},
  "geometry": {"coordinates":[0.14403025198809,50.87074985031617],"type":"Point"}
}