{
  "type": "Feature",
  "properties": {
    "iso:country":"GB",
    "wof:name":"GU6 7HN",
    "wof:placetype":"postalcode"
},
  "geometry": {"coordinates":[-0.47488308047238,51.13974351704488],"type":"Point"}
}