{
  "type": "Feature",
  "properties": {
    "iso:country":"GB",
    "wof:name":"SP1 3AD",
    "wof:placetype":"postalcode"
},
  "geometry": {"coordinates":[-1.79456258028368,51.07526538838783],"type":"Point"}
}