{
  "type": "Feature",
  "properties": {
    "date:inception_lower": "1980-01-01",
    "date:inception_upper": "1980-01-01",
    "iso:country": "GB",
    "wof:name": "ST3 4NZ",
    "wof:placetype": "postalcode"
  },
  "geometry": {"coordinates":[-2.135296,52.975373],"type":"Point"}
}
