{
  "type": "Feature",
  "properties": {
    "iso:country":"GB",
    "wof:name":"ST3 4NZ",
    "wof:placetype":"postalcode"
},
  "geometry": {"coordinates":[-2.13529646811679,52.97537260926486],"type":"Point"}
}