{
  "type": "Feature",
  "properties": {
    "iso:country":"GB",
    "wof:name":"BB10 3QB",
    "wof:placetype":"postalcode"
},
  "geometry": {"coordinates":[-2.19595832944182,53.81391355683458],"type":"Point"}
}