{
  "type": "Feature",
  "properties": {
    "iso:country":"GB",
    "wof:name":"TN13 2ND",
    "wof:placetype":"postalcode"
},
  "geometry": {"coordinates":[0.17737483865896,51.26367867283329],"type":"Point"}
}