{
  "type": "Feature",
  "properties": {
    "iso:country": "GB",
    "wof:name": "SY23 2BH",
    "wof:placetype": "postalcode"
  },
  "geometry": {"coordinates":[-4.088238,52.414822],"type":"Point"}
}
