{
  "type": "Feature",
  "properties": {
    "date:inception_lower":"2011-07-01",
    "date:inception_upper":"2011-07-31",
    "iso:country":"GB",
    "wof:name":"SY23 2BH",
    "wof:placetype":"postalcode"
},
  "geometry": {"coordinates":[-4.088238,52.414822],"type":"Point"}
}