{
  "type": "Feature",
  "properties": {
    "iso:country":"GB",
    "wof:name":"SY23 2BH",
    "wof:placetype":"postalcode"
},
  "geometry": {"coordinates":[-4.08823850997706,52.41482150806935],"type":"Point"}
}