{
  "type": "Feature",
  "properties": {
    "iso:country": "GB",
    "wof:name": "SK9 1LX",
    "wof:placetype": "postalcode"
  },
  "geometry": {"coordinates":[-2.234995,53.322441],"type":"Point"}
}
