{
  "type": "Feature",
  "properties": {
    "iso:country":"GB",
    "wof:name":"SK9 1LX",
    "wof:placetype":"postalcode"
},
  "geometry": {"coordinates":[-2.23498084656499,53.32243368847385],"type":"Point"}
}