{
  "type": "Feature",
  "properties": {
    "iso:country":"GB",
    "wof:name":"WA1 3RJ",
    "wof:placetype":"postalcode"
},
  "geometry": {"coordinates":[-2.56803332872814,53.39573001939733],"type":"Point"}
}