{
  "type": "Feature",
  "properties": {
    "iso:country":"GB",
    "wof:name":"G82 2DE",
    "wof:placetype":"postalcode"
},
  "geometry": {"coordinates":[-4.56092045212681,55.94699403770307],"type":"Point"}
}