{
  "type": "Feature",
  "properties": {
    "iso:country": "GB",
    "wof:name": "NN14 4AZ",
    "wof:placetype": "postalcode"
  },
  "geometry": {"coordinates":[-0.594695,52.350063],"type":"Point"}
}
