{
  "type": "Feature",
  "properties": {
    "iso:country":"GB",
    "wof:name":"NW10 0AZ",
    "wof:placetype":"postalcode"
},
  "geometry": {"coordinates":[-0.27524916568983,51.5441727288357],"type":"Point"}
}