{
  "type": "Feature",
  "properties": {
    "iso:country":"GB",
    "wof:name":"SL4 3NZ",
    "wof:placetype":"postalcode"
},
  "geometry": {"coordinates":[-0.62312636103337,51.47749977074619],"type":"Point"}
}