{
  "type": "Feature",
  "properties": {
    "date:inception_lower": "1980-01-01",
    "date:inception_upper": "1980-01-01",
    "iso:country": "GB",
    "wof:name": "SL4 3NZ",
    "wof:placetype": "postalcode"
  },
  "geometry": {"coordinates":[-0.623126,51.4775],"type":"Point"}
}
