{
  "type": "Feature",
  "properties": {
    "date:inception_lower":"1983-07-01",
    "date:inception_upper":"1983-07-31",
    "iso:country":"GB",
    "wof:name":"TR15 3ER",
    "wof:placetype":"postalcode"
},
  "geometry": {"coordinates":[-5.244376,50.229381],"type":"Point"}
}