{
  "type": "Feature",
  "properties": {
    "iso:country":"GB",
    "wof:name":"TR15 3ER",
    "wof:placetype":"postalcode"
},
  "geometry": {"coordinates":[-5.24437569815193,50.22938149103183],"type":"Point"}
}