{
  "type": "Feature",
  "properties": {
    "iso:country":"GB",
    "wof:name":"CO15 6PS",
    "wof:placetype":"postalcode"
},
  "geometry": {"coordinates":[1.15812190463578,51.79189609512126],"type":"Point"}
}