{
  "type": "Feature",
  "properties": {
    "iso:country": "GB",
    "wof:name": "ST17 4DE",
    "wof:placetype": "postalcode"
  },
  "geometry": {"coordinates":[-2.113807,52.799519],"type":"Point"}
}
