{
  "type": "Feature",
  "properties": {
    "iso:country":"GB",
    "wof:name":"KW15 1BW",
    "wof:placetype":"postalcode"
},
  "geometry": {"coordinates":[-2.96221364530835,58.97571072365825],"type":"Point"}
}