{
  "type": "Feature",
  "properties": {
    "date:inception_lower":"1980-01-01",
    "date:inception_upper":"1980-01-31",
    "iso:country":"GB",
    "wof:name":"KW15 1BW",
    "wof:placetype":"postalcode"
},
  "geometry": {"coordinates":[-2.962214,58.975711],"type":"Point"}
}