{
  "type": "Feature",
  "properties": {
    "iso:country": "GB",
    "wof:name": "KW15 1BW",
    "wof:placetype": "postalcode"
  },
  "geometry": {"coordinates":[-2.962214,58.975711],"type":"Point"}
}
