{
  "type": "Feature",
  "properties": {
    "date:inception_lower":"1980-01-01",
    "date:inception_upper":"1980-01-31",
    "iso:country":"GB",
    "wof:name":"G32 9TS",
    "wof:placetype":"postalcode"
},
  "geometry": {"coordinates":[-4.163821,55.844464],"type":"Point"}
}