{
  "type": "Feature",
  "properties": {
    "iso:country":"GB",
    "wof:name":"LL57 3ER",
    "wof:placetype":"postalcode"
},
  "geometry": {"coordinates":[-4.06134631468098,53.19126421092706],"type":"Point"}
}