{
  "type": "Feature",
  "properties": {
    "iso:country":"GB",
    "wof:name":"OL16 3QQ",
    "wof:placetype":"postalcode"
},
  "geometry": {"coordinates":[-2.08539305628247,53.60508830988473],"type":"Point"}
}