{
  "type": "Feature",
  "properties": {
    "iso:country": "GB",
    "wof:name": "OL16 3QQ",
    "wof:placetype": "postalcode"
  },
  "geometry": {"coordinates":[-2.085393,53.605088],"type":"Point"}
}
