{
  "type": "Feature",
  "properties": {
    "iso:country":"GB",
    "wof:name":"TD9 0QF",
    "wof:placetype":"postalcode"
},
  "geometry": {"coordinates":[-2.81644436135685,55.17729514170419],"type":"Point"}
}