{
  "type": "Feature",
  "properties": {
    "iso:country":"GB",
    "wof:name":"LA12 8AP",
    "wof:placetype":"postalcode"
},
  "geometry": {"coordinates":[-2.95748187795689,54.27651057186516],"type":"Point"}
}