{
  "type": "Feature",
  "properties": {
    "iso:country": "GB",
    "wof:name": "LA12 8AP",
    "wof:placetype": "postalcode"
  },
  "geometry": {"coordinates":[-2.957513,54.276546],"type":"Point"}
}
