{
  "type": "Feature",
  "properties": {
    "iso:country": "GB",
    "wof:name": "IP14 6RH",
    "wof:placetype": "postalcode"
  },
  "geometry": {"coordinates":[1.174902,52.223364],"type":"Point"}
}
