{
  "type": "Feature",
  "properties": {
    "date:inception_lower":"1980-01-01",
    "date:inception_upper":"1980-01-31",
    "iso:country":"GB",
    "wof:name":"IP14 6RH",
    "wof:placetype":"postalcode"
},
  "geometry": {"coordinates":[1.174902,52.223364],"type":"Point"}
}