{
  "type": "Feature",
  "properties": {
    "iso:country": "GB",
    "wof:name": "MK43 0YQ",
    "wof:placetype": "postalcode"
  },
  "geometry": {"coordinates":[-0.60781,52.064558],"type":"Point"}
}
