{
  "type": "Feature",
  "properties": {
    "date:inception_lower":"2018-05-01",
    "date:inception_upper":"2018-05-31",
    "iso:country":"GB",
    "wof:name":"MK43 0YQ",
    "wof:placetype":"postalcode"
},
  "geometry": {"coordinates":[-0.60781,52.064558],"type":"Point"}
}