{
  "type": "Feature",
  "properties": {
    "iso:country": "GB",
    "wof:name": "SO41 3NJ",
    "wof:placetype": "postalcode"
  },
  "geometry": {"coordinates":[-1.548334,50.756485],"type":"Point"}
}
