{
  "type": "Feature",
  "properties": {
    "iso:country":"GB",
    "wof:name":"BL9 9GH",
    "wof:placetype":"postalcode"
},
  "geometry": {"coordinates":[-2.28271978380024,53.5805609414001],"type":"Point"}
}