{
  "type": "Feature",
  "properties": {
    "date:inception_lower":"2003-07-01",
    "date:inception_upper":"2003-07-31",
    "iso:country":"GB",
    "wof:name":"BL9 9GH",
    "wof:placetype":"postalcode"
},
  "geometry": {"coordinates":[-2.28272,53.580561],"type":"Point"}
}