{
  "type": "Feature",
  "properties": {
    "iso:country":"GB",
    "wof:name":"DY7 6AW",
    "wof:placetype":"postalcode"
},
  "geometry": {"coordinates":[-2.23941620775618,52.45594094182066],"type":"Point"}
}