{
  "type": "Feature",
  "properties": {
    "date:inception_lower": "2000-06-01",
    "date:inception_upper": "2000-06-01",
    "iso:country": "GB",
    "wof:name": "NN4 6ES",
    "wof:placetype": "postalcode"
  },
  "geometry": {"coordinates":[-0.879328,52.202547],"type":"Point"}
}
