{
  "type": "Feature",
  "properties": {
    "iso:country":"GB",
    "wof:name":"NN4 6ES",
    "wof:placetype":"postalcode"
},
  "geometry": {"coordinates":[-0.879327949852,52.20254713793229],"type":"Point"}
}