{
  "type": "Feature",
  "properties": {
    "iso:country": "GB",
    "wof:name": "BD23 1HW",
    "wof:placetype": "postalcode"
  },
  "geometry": {"coordinates":[-2.010008,53.963128],"type":"Point"}
}
