{
  "type": "Feature",
  "properties": {
    "date:inception_lower": "1980-01-01",
    "date:inception_upper": "1980-01-01",
    "iso:country": "GB",
    "wof:name": "BD23 1HW",
    "wof:placetype": "postalcode"
  },
  "geometry": {"coordinates":[-2.010008,53.963128],"type":"Point"}
}
