{
  "type": "Feature",
  "properties": {
    "iso:country":"GB",
    "wof:name":"SA8 3EH",
    "wof:placetype":"postalcode"
},
  "geometry": {"coordinates":[-3.82592864115174,51.71123028405473],"type":"Point"}
}