{
  "type": "Feature",
  "properties": {
    "iso:country":"GB",
    "wof:name":"RH13 8EU",
    "wof:placetype":"postalcode"
},
  "geometry": {"coordinates":[-0.29644048275863,50.96199804734943],"type":"Point"}
}