{
  "type": "Feature",
  "properties": {
    "date:inception_lower": "1980-01-01",
    "date:inception_upper": "1980-01-01",
    "iso:country": "GB",
    "wof:name": "RH13 8EU",
    "wof:placetype": "postalcode"
  },
  "geometry": {"coordinates":[-0.29644,50.961998],"type":"Point"}
}
