{
  "type": "Feature",
  "properties": {
    "date:inception_lower": "2006-03-01",
    "date:inception_upper": "2006-03-01",
    "iso:country": "GB",
    "wof:name": "SY1 2DL",
    "wof:placetype": "postalcode"
  },
  "geometry": {"coordinates":[-2.752233,52.714509],"type":"Point"}
}
