{
  "type": "Feature",
  "properties": {
    "iso:country":"GB",
    "wof:name":"SY1 2DL",
    "wof:placetype":"postalcode"
},
  "geometry": {"coordinates":[-2.7522331748214,52.71450919320136],"type":"Point"}
}