{
  "type": "Feature",
  "properties": {
    "iso:country":"GB",
    "wof:name":"SN4 8AB",
    "wof:placetype":"postalcode"
},
  "geometry": {"coordinates":[-1.9028376659039,51.54163714280656],"type":"Point"}
}