{
  "type": "Feature",
  "properties": {
    "iso:country": "GB",
    "wof:name": "SN4 8AB",
    "wof:placetype": "postalcode"
  },
  "geometry": {"coordinates":[-1.902838,51.541637],"type":"Point"}
}
