{
  "type": "Feature",
  "properties": {
    "iso:country": "GB",
    "wof:name": "DN37 7AB",
    "wof:placetype": "postalcode"
  },
  "geometry": {"coordinates":[-0.169609,53.542839],"type":"Point"}
}
