{
  "type": "Feature",
  "properties": {
    "iso:country": "GB",
    "wof:name": "CW8 4QQ",
    "wof:placetype": "postalcode"
  },
  "geometry": {"coordinates":[-2.554937,53.277913],"type":"Point"}
}
