{
  "type": "Feature",
  "properties": {
    "date:inception_lower": "1998-06-01",
    "date:inception_upper": "1998-06-01",
    "iso:country": "GB",
    "wof:name": "YO62 5HG",
    "wof:placetype": "postalcode"
  },
  "geometry": {"coordinates":[-1.052776,54.258171],"type":"Point"}
}
