{
  "type": "Feature",
  "properties": {
    "iso:country":"GB",
    "wof:name":"HA1 4HX",
    "wof:placetype":"postalcode"
},
  "geometry": {"coordinates":[-0.34645448243486,51.58059121352461],"type":"Point"}
}