{
  "type": "Feature",
  "properties": {
    "iso:country": "GB",
    "wof:name": "HA1 4HX",
    "wof:placetype": "postalcode"
  },
  "geometry": {"coordinates":[-0.346432,51.580593],"type":"Point"}
}
