{
  "type": "Feature",
  "properties": {
    "iso:country": "GB",
    "wof:name": "SL4 4DT",
    "wof:placetype": "postalcode"
  },
  "geometry": {"coordinates":[-0.642374,51.474271],"type":"Point"}
}
