{
  "type": "Feature",
  "properties": {
    "iso:country": "GB",
    "wof:name": "BH9 1SW",
    "wof:placetype": "postalcode"
  },
  "geometry": {"coordinates":[-1.867952,50.75018],"type":"Point"}
}
