{
  "type": "Feature",
  "properties": {
    "iso:country":"GB",
    "wof:name":"BH9 1SW",
    "wof:placetype":"postalcode"
},
  "geometry": {"coordinates":[-1.86795232272952,50.7501798204629],"type":"Point"}
}