{
  "type": "Feature",
  "properties": {
    "date:inception_lower": "1980-01-01",
    "date:inception_upper": "1980-01-01",
    "iso:country": "GB",
    "wof:name": "BA16 0TF",
    "wof:placetype": "postalcode"
  },
  "geometry": {"coordinates":[-2.741273,51.119332],"type":"Point"}
}
