{
  "type": "Feature",
  "properties": {
    "iso:country":"GB",
    "wof:name":"BA16 0TF",
    "wof:placetype":"postalcode"
},
  "geometry": {"coordinates":[-2.74127259770876,51.11933170180274],"type":"Point"}
}