{
  "type": "Feature",
  "properties": {
    "iso:country": "GB",
    "wof:name": "NE15 8EZ",
    "wof:placetype": "postalcode"
  },
  "geometry": {"coordinates":[-1.717356,54.979709],"type":"Point"}
}
