{
  "type": "Feature",
  "properties": {
    "iso:country":"GB",
    "wof:name":"NE15 8EZ",
    "wof:placetype":"postalcode"
},
  "geometry": {"coordinates":[-1.7173561867314,54.97970886022712],"type":"Point"}
}