{
  "type": "Feature",
  "properties": {
    "date:inception_lower": "2011-07-01",
    "date:inception_upper": "2011-07-01",
    "iso:country": "GB",
    "wof:name": "ME3 9GD",
    "wof:placetype": "postalcode"
  },
  "geometry": {"coordinates":[0.557503,51.428928],"type":"Point"}
}
