{
  "type": "Feature",
  "properties": {
    "iso:country":"GB",
    "wof:name":"ME3 9GD",
    "wof:placetype":"postalcode"
},
  "geometry": {"coordinates":[0.55755593687691,51.4288454740553],"type":"Point"}
}