{
  "type": "Feature",
  "properties": {
    "iso:country":"GB",
    "wof:name":"YO32 2PW",
    "wof:placetype":"postalcode"
},
  "geometry": {"coordinates":[-1.08673416584726,54.02007661260463],"type":"Point"}
}