{
  "type": "Feature",
  "properties": {
    "date:inception_lower": "2006-11-01",
    "date:inception_upper": "2006-11-01",
    "iso:country": "GB",
    "wof:name": "CR4 3FF",
    "wof:placetype": "postalcode"
  },
  "geometry": {"coordinates":[-0.173203,51.405438],"type":"Point"}
}
