{
  "type": "Feature",
  "properties": {
    "iso:country":"GB",
    "wof:name":"CR4 3FF",
    "wof:placetype":"postalcode"
},
  "geometry": {"coordinates":[-0.17322874976571,51.4054386240481],"type":"Point"}
}