{
  "type": "Feature",
  "properties": {
    "iso:country": "GB",
    "wof:name": "SA13 2RJ",
    "wof:placetype": "postalcode"
  },
  "geometry": {"coordinates":[-3.71184,51.614997],"type":"Point"}
}
