{
  "type": "Feature",
  "properties": {
    "date:inception_lower":"1987-04-01",
    "date:inception_upper":"1987-04-30",
    "iso:country":"GB",
    "wof:name":"SA13 2RJ",
    "wof:placetype":"postalcode"
},
  "geometry": {"coordinates":[-3.71184,51.614997],"type":"Point"}
}