{
  "type": "Feature",
  "properties": {
    "iso:country":"GB",
    "wof:name":"IV12 5TF",
    "wof:placetype":"postalcode"
},
  "geometry": {"coordinates":[-3.81074444493118,57.57743577255162],"type":"Point"}
}