{
  "type": "Feature",
  "properties": {
    "date:inception_lower": "1980-01-01",
    "date:inception_upper": "1980-01-01",
    "iso:country": "GB",
    "wof:name": "IV12 5TF",
    "wof:placetype": "postalcode"
  },
  "geometry": {"coordinates":[-3.810744,57.577436],"type":"Point"}
}
