{
  "type": "Feature",
  "properties": {
    "iso:country": "GB",
    "wof:name": "IV12 5TF",
    "wof:placetype": "postalcode"
  },
  "geometry": {"coordinates":[-3.810744,57.577436],"type":"Point"}
}
