{
  "type": "Feature",
  "properties": {
    "iso:country": "GB",
    "wof:name": "WA5 1PG",
    "wof:placetype": "postalcode"
  },
  "geometry": {"coordinates":[-2.612601,53.392157],"type":"Point"}
}
