{
  "type": "Feature",
  "properties": {
    "iso:country":"GB",
    "wof:name":"WA5 1PG",
    "wof:placetype":"postalcode"
},
  "geometry": {"coordinates":[-2.61260115358516,53.39215679536537],"type":"Point"}
}