{
  "type": "Feature",
  "properties": {
    "date:inception_lower": "1984-10-01",
    "date:inception_upper": "1984-10-01",
    "iso:country": "GB",
    "wof:name": "WA5 1PG",
    "wof:placetype": "postalcode"
  },
  "geometry": {"coordinates":[-2.612601,53.392157],"type":"Point"}
}
