{
  "type": "Feature",
  "properties": {
    "iso:country": "GB",
    "wof:name": "EH21 7RT",
    "wof:placetype": "postalcode"
  },
  "geometry": {"coordinates":[-3.048641,55.945257],"type":"Point"}
}
