{
  "type": "Feature",
  "properties": {
    "date:inception_lower":"1990-02-01",
    "date:inception_upper":"1990-02-28",
    "iso:country":"GB",
    "wof:name":"BD22 8BW",
    "wof:placetype":"postalcode"
},
  "geometry": {"coordinates":[-1.954204,53.827493],"type":"Point"}
}