{
  "type": "Feature",
  "properties": {
    "iso:country":"GB",
    "wof:name":"CF72 9AY",
    "wof:placetype":"postalcode"
},
  "geometry": {"coordinates":[-3.38720114936374,51.52633351619788],"type":"Point"}
}