{
  "type": "Feature",
  "properties": {
    "iso:country": "GB",
    "wof:name": "CF72 9AY",
    "wof:placetype": "postalcode"
  },
  "geometry": {"coordinates":[-3.387201,51.526334],"type":"Point"}
}
