{
  "type": "Feature",
  "properties": {
    "iso:country": "GB",
    "wof:name": "SO21 3FW",
    "wof:placetype": "postalcode"
  },
  "geometry": {"coordinates":[-1.298726,51.178207],"type":"Point"}
}
