{
  "type": "Feature",
  "properties": {
    "iso:country":"GB",
    "wof:name":"AL5 3DP",
    "wof:placetype":"postalcode"
},
  "geometry": {"coordinates":[-0.37172843880311,51.82041032632323],"type":"Point"}
}