{
  "type": "Feature",
  "properties": {
    "date:inception_lower":"2002-06-01",
    "date:inception_upper":"2002-06-30",
    "iso:country":"GB",
    "wof:name":"AL5 3DP",
    "wof:placetype":"postalcode"
},
  "geometry": {"coordinates":[-0.371728,51.82041],"type":"Point"}
}