{
  "type": "Feature",
  "properties": {
    "iso:country": "GB",
    "wof:name": "AL5 3DP",
    "wof:placetype": "postalcode"
  },
  "geometry": {"coordinates":[-0.371728,51.82041],"type":"Point"}
}
