{
  "type": "Feature",
  "properties": {
    "iso:country":"GB",
    "wof:name":"PO20 3RH",
    "wof:placetype":"postalcode"
},
  "geometry": {"coordinates":[-0.66880374172101,50.84040451603259],"type":"Point"}
}