{
  "type": "Feature",
  "properties": {
    "iso:country": "GB",
    "wof:name": "B24 8EG",
    "wof:placetype": "postalcode"
  },
  "geometry": {"coordinates":[-1.83695,52.51065],"type":"Point"}
}
