{
  "type": "Feature",
  "properties": {
    "iso:country":"GB",
    "wof:name":"B24 8EG",
    "wof:placetype":"postalcode"
},
  "geometry": {"coordinates":[-1.83695031078556,52.51064981390152],"type":"Point"}
}