{
  "type": "Feature",
  "properties": {
    "iso:country": "GB",
    "wof:name": "DA11 8RJ",
    "wof:placetype": "postalcode"
  },
  "geometry": {"coordinates":[0.353256,51.434835],"type":"Point"}
}
