{
  "type": "Feature",
  "properties": {
    "date:inception_lower": "1986-04-01",
    "date:inception_upper": "1986-04-01",
    "iso:country": "GB",
    "wof:name": "DA11 8RJ",
    "wof:placetype": "postalcode"
  },
  "geometry": {"coordinates":[0.353256,51.434835],"type":"Point"}
}
