{
  "type": "Feature",
  "properties": {
    "date:inception_lower":"1980-01-01",
    "date:inception_upper":"1980-01-31",
    "iso:country":"GB",
    "wof:name":"BN11 2JS",
    "wof:placetype":"postalcode"
},
  "geometry": {"coordinates":[-0.358807,50.818956],"type":"Point"}
}