{
  "type": "Feature",
  "properties": {
    "iso:country": "GB",
    "wof:name": "BN11 2JS",
    "wof:placetype": "postalcode"
  },
  "geometry": {"coordinates":[-0.358807,50.818956],"type":"Point"}
}
