{
  "type": "Feature",
  "properties": {
    "iso:country":"GB",
    "wof:name":"BN11 2JS",
    "wof:placetype":"postalcode"
},
  "geometry": {"coordinates":[-0.35880712170126,50.81895562792182],"type":"Point"}
}