{
  "type": "Feature",
  "properties": {
    "iso:country":"GB",
    "wof:name":"EC4N 8BS",
    "wof:placetype":"postalcode"
},
  "geometry": {"coordinates":[-0.08958388189957,51.51248415851777],"type":"Point"}
}