{
  "type": "Feature",
  "properties": {
    "iso:country":"GB",
    "wof:name":"RH5 4BJ",
    "wof:placetype":"postalcode"
},
  "geometry": {"coordinates":[-0.31578580807071,51.23106753108416],"type":"Point"}
}