{
  "type": "Feature",
  "properties": {
    "iso:country":"GB",
    "wof:name":"SO31 4HX",
    "wof:placetype":"postalcode"
},
  "geometry": {"coordinates":[-1.32633060572552,50.86371291450052],"type":"Point"}
}