{
  "type": "Feature",
  "properties": {
    "iso:country":"GB",
    "wof:name":"CM16 6ER",
    "wof:placetype":"postalcode"
},
  "geometry": {"coordinates":[0.18148555747879,51.72524531989927],"type":"Point"}
}