{
  "type": "Feature",
  "properties": {
    "iso:country": "GB",
    "wof:name": "CM16 6ER",
    "wof:placetype": "postalcode"
  },
  "geometry": {"coordinates":[0.181486,51.725245],"type":"Point"}
}
