{
  "type": "Feature",
  "properties": {
    "iso:country":"GB",
    "wof:name":"NE6 4DU",
    "wof:placetype":"postalcode"
},
  "geometry": {"coordinates":[-1.54648661283162,54.97837444066032],"type":"Point"}
}