{
  "type": "Feature",
  "properties": {
    "iso:country":"GB",
    "wof:name":"BD7 3EN",
    "wof:placetype":"postalcode"
},
  "geometry": {"coordinates":[-1.78590231211852,53.7825783392401],"type":"Point"}
}