{
  "type": "Feature",
  "properties": {
    "date:inception_lower": "1985-04-01",
    "date:inception_upper": "1985-04-01",
    "iso:country": "GB",
    "wof:name": "ST1 6RS",
    "wof:placetype": "postalcode"
  },
  "geometry": {"coordinates":[-2.154096,53.035667],"type":"Point"}
}
