{
  "type": "Feature",
  "properties": {
    "iso:country":"GB",
    "wof:name":"ST1 6RS",
    "wof:placetype":"postalcode"
},
  "geometry": {"coordinates":[-2.15420088028544,53.03565785904822],"type":"Point"}
}