{
  "type": "Feature",
  "properties": {
    "iso:country":"GB",
    "wof:name":"TR18 3JA",
    "wof:placetype":"postalcode"
},
  "geometry": {"coordinates":[-5.54664115859159,50.12846683549983],"type":"Point"}
}