{
  "type": "Feature",
  "properties": {
    "date:inception_lower": "1980-01-01",
    "date:inception_upper": "1980-01-01",
    "iso:country": "GB",
    "wof:name": "SW20 0NL",
    "wof:placetype": "postalcode"
  },
  "geometry": {"coordinates":[-0.241107,51.418698],"type":"Point"}
}
