{
  "type": "Feature",
  "properties": {
    "iso:country":"GB",
    "wof:name":"NN14 2SF",
    "wof:placetype":"postalcode"
},
  "geometry": {"coordinates":[-0.81357072232674,52.43779312080876],"type":"Point"}
}