{
  "type": "Feature",
  "properties": {
    "date:inception_lower": "2011-12-01",
    "date:inception_upper": "2011-12-01",
    "iso:country": "GB",
    "wof:name": "TQ11 0FF",
    "wof:placetype": "postalcode"
  },
  "geometry": {"coordinates":[-3.782715,50.48077],"type":"Point"}
}
