{
  "type": "Feature",
  "properties": {
    "iso:country":"GB",
    "wof:name":"TQ11 0FF",
    "wof:placetype":"postalcode"
},
  "geometry": {"coordinates":[-3.78271533928975,50.48076981433761],"type":"Point"}
}