{
  "type": "Feature",
  "properties": {
    "iso:country": "GB",
    "wof:name": "TQ11 0FF",
    "wof:placetype": "postalcode"
  },
  "geometry": {"coordinates":[-3.782715,50.48077],"type":"Point"}
}
