{
  "type": "Feature",
  "properties": {
    "iso:country":"GB",
    "wof:name":"ST5 8AL",
    "wof:placetype":"postalcode"
},
  "geometry": {"coordinates":[-2.22826733481868,53.03190702218743],"type":"Point"}
}