{
  "type": "Feature",
  "properties": {
    "iso:country": "GB",
    "wof:name": "LA2 8PT",
    "wof:placetype": "postalcode"
  },
  "geometry": {"coordinates":[-2.539839,54.091185],"type":"Point"}
}
