{
  "type": "Feature",
  "properties": {
    "iso:country":"GB",
    "wof:name":"DE14 3LB",
    "wof:placetype":"postalcode"
},
  "geometry": {"coordinates":[-1.64077543290759,52.79959702585341],"type":"Point"}
}