{
  "type": "Feature",
  "properties": {
    "iso:country": "GB",
    "wof:name": "DE14 3LB",
    "wof:placetype": "postalcode"
  },
  "geometry": {"coordinates":[-1.640799,52.799669],"type":"Point"}
}
