{
  "type": "Feature",
  "properties": {
    "iso:country":"GB",
    "wof:name":"KA26 0AG",
    "wof:placetype":"postalcode"
},
  "geometry": {"coordinates":[-4.85717873874359,55.2366839723318],"type":"Point"}
}