{
  "type": "Feature",
  "properties": {
    "iso:country":"GB",
    "wof:name":"L32 6SS",
    "wof:placetype":"postalcode"
},
  "geometry": {"coordinates":[-2.88075698389145,53.47195385951211],"type":"Point"}
}