{
  "type": "Feature",
  "properties": {
    "iso:country": "GB",
    "wof:name": "L32 6SS",
    "wof:placetype": "postalcode"
  },
  "geometry": {"coordinates":[-2.880757,53.471954],"type":"Point"}
}
