{
  "type": "Feature",
  "properties": {
    "iso:country":"GB",
    "wof:name":"AL6 0JJ",
    "wof:placetype":"postalcode"
},
  "geometry": {"coordinates":[-0.15681145420688,51.81400097526262],"type":"Point"}
}