{
  "type": "Feature",
  "properties": {
    "iso:country": "GB",
    "wof:name": "AL6 0JJ",
    "wof:placetype": "postalcode"
  },
  "geometry": {"coordinates":[-0.156811,51.814001],"type":"Point"}
}
