{
  "type": "Feature",
  "properties": {
    "date:inception_lower": "2021-05-01",
    "date:inception_upper": "2021-05-01",
    "iso:country": "GB",
    "wof:name": "SN26 7DA",
    "wof:placetype": "postalcode"
  },
  "geometry": {"coordinates":[-1.777602,51.613804],"type":"Point"}
}
