{
  "type": "Feature",
  "properties": {
    "date:inception_lower": "1990-07-01",
    "date:inception_upper": "1990-07-01",
    "iso:country": "GB",
    "wof:name": "BN41 2RD",
    "wof:placetype": "postalcode"
  },
  "geometry": {"coordinates":[-0.233354,50.853439],"type":"Point"}
}
