{
  "type": "Feature",
  "properties": {
    "iso:country":"GB",
    "wof:name":"BN41 2RD",
    "wof:placetype":"postalcode"
},
  "geometry": {"coordinates":[-0.23335404372895,50.85343854463068],"type":"Point"}
}