{
  "type": "Feature",
  "properties": {
    "date:inception_lower": "2021-12-01",
    "date:inception_upper": "2021-12-01",
    "iso:country": "GB",
    "wof:name": "E5 0FU",
    "wof:placetype": "postalcode"
  },
  "geometry": {"coordinates":[-0.040466,51.555218],"type":"Point"}
}
