{
  "type": "Feature",
  "properties": {
    "iso:country": "GB",
    "wof:name": "PE2 8XL",
    "wof:placetype": "postalcode"
  },
  "geometry": {"coordinates":[-0.205774,52.553545],"type":"Point"}
}
