{
  "type": "Feature",
  "properties": {
    "iso:country":"GB",
    "wof:name":"PE2 8XL",
    "wof:placetype":"postalcode"
},
  "geometry": {"coordinates":[-0.20577441812521,52.553545008032],"type":"Point"}
}