{
  "type": "Feature",
  "properties": {
    "date:inception_lower":"1999-12-01",
    "date:inception_upper":"1999-12-31",
    "iso:country":"GB",
    "wof:name":"PE2 8XL",
    "wof:placetype":"postalcode"
},
  "geometry": {"coordinates":[-0.205774,52.553545],"type":"Point"}
}