{
  "type": "Feature",
  "properties": {
    "iso:country":"GB",
    "wof:name":"LS10 1NL",
    "wof:placetype":"postalcode"
},
  "geometry": {"coordinates":[-1.52829536501518,53.78297474553018],"type":"Point"}
}