{
  "type": "Feature",
  "properties": {
    "iso:country":"GB",
    "wof:name":"SA13 2DA",
    "wof:placetype":"postalcode"
},
  "geometry": {"coordinates":[-3.75917994637553,51.57408364324212],"type":"Point"}
}