{
  "type": "Feature",
  "properties": {
    "date:inception_lower": "1980-01-01",
    "date:inception_upper": "1980-01-01",
    "iso:country": "GB",
    "wof:name": "RH17 6BP",
    "wof:placetype": "postalcode"
  },
  "geometry": {"coordinates":[-0.200359,51.053768],"type":"Point"}
}
