{
  "type": "Feature",
  "properties": {
    "iso:country":"GB",
    "wof:name":"N14 6NA",
    "wof:placetype":"postalcode"
},
  "geometry": {"coordinates":[-0.12203234200605,51.62575555108337],"type":"Point"}
}