{
  "type": "Feature",
  "properties": {
    "iso:country":"GB",
    "wof:name":"ST15 8EW",
    "wof:placetype":"postalcode"
},
  "geometry": {"coordinates":[-2.1506437976252,52.90514796887853],"type":"Point"}
}