{
  "type": "Feature",
  "properties": {
    "date:inception_lower":"1980-01-01",
    "date:inception_upper":"1980-01-31",
    "iso:country":"GB",
    "wof:name":"TA10 9SX",
    "wof:placetype":"postalcode"
},
  "geometry": {"coordinates":[-2.822047,51.042339],"type":"Point"}
}