{
  "type": "Feature",
  "properties": {
    "date:inception_lower":"1980-01-01",
    "date:inception_upper":"1980-01-31",
    "iso:country":"GB",
    "wof:name":"RM15 4EP",
    "wof:placetype":"postalcode"
},
  "geometry": {"coordinates":[0.250138,51.49956],"type":"Point"}
}