{
  "type": "Feature",
  "properties": {
    "date:inception_lower": "1985-10-01",
    "date:inception_upper": "1985-10-01",
    "iso:country": "GB",
    "wof:name": "WR7 4JE",
    "wof:placetype": "postalcode"
  },
  "geometry": {"coordinates":[-1.981207,52.21245],"type":"Point"}
}
