{
  "type": "Feature",
  "properties": {
    "iso:country":"GB",
    "wof:name":"WR7 4JE",
    "wof:placetype":"postalcode"
},
  "geometry": {"coordinates":[-1.9812068352109,52.21244951566786],"type":"Point"}
}