{
  "type": "Feature",
  "properties": {
    "iso:country":"GB",
    "wof:name":"TS1 3BX",
    "wof:placetype":"postalcode"
},
  "geometry": {"coordinates":[-1.23698436116987,54.57037432646663],"type":"Point"}
}