{
  "type": "Feature",
  "properties": {
    "iso:country":"GB",
    "wof:name":"WS13 8AU",
    "wof:placetype":"postalcode"
},
  "geometry": {"coordinates":[-1.84554850848841,52.68076612314629],"type":"Point"}
}