{
  "type": "Feature",
  "properties": {
    "iso:country": "GB",
    "wof:name": "EC4Y 1BD",
    "wof:placetype": "postalcode"
  },
  "geometry": {"coordinates":[-0.111819,51.513591],"type":"Point"}
}
