{
  "type": "Feature",
  "properties": {
    "iso:country":"GB",
    "wof:name":"EC4Y 1BD",
    "wof:placetype":"postalcode"
},
  "geometry": {"coordinates":[-0.11181888021426,51.51359060774141],"type":"Point"}
}