{
  "type": "Feature",
  "properties": {
    "iso:country": "GB",
    "wof:name": "LN5 9FY",
    "wof:placetype": "postalcode"
  },
  "geometry": {"coordinates":[-0.555515,53.177106],"type":"Point"}
}
