{
  "type": "Feature",
  "properties": {
    "iso:country":"GB",
    "wof:name":"CM8 1FW",
    "wof:placetype":"postalcode"
},
  "geometry": {"coordinates":[0.6280969764033,51.79012530017241],"type":"Point"}
}