{
  "type": "Feature",
  "properties": {
    "iso:country": "GB",
    "wof:name": "CM8 1FW",
    "wof:placetype": "postalcode"
  },
  "geometry": {"coordinates":[0.628097,51.790125],"type":"Point"}
}
