{
  "type": "Feature",
  "properties": {
    "iso:country":"GB",
    "wof:name":"IV2 4HG",
    "wof:placetype":"postalcode"
},
  "geometry": {"coordinates":[-4.21416921845386,57.46691161422741],"type":"Point"}
}