{
  "type": "Feature",
  "properties": {
    "iso:country":"GB",
    "wof:name":"CF33 6HN",
    "wof:placetype":"postalcode"
},
  "geometry": {"coordinates":[-3.67289504820843,51.52922449448728],"type":"Point"}
}