{
  "type": "Feature",
  "properties": {
    "iso:country":"GB",
    "wof:name":"SK7 4AE",
    "wof:placetype":"postalcode"
},
  "geometry": {"coordinates":[-2.12200100791173,53.38163131762209],"type":"Point"}
}