{
  "type": "Feature",
  "properties": {
    "iso:country":"GB",
    "wof:name":"LS6 3EJ",
    "wof:placetype":"postalcode"
},
  "geometry": {"coordinates":[-1.58604764497088,53.81787267054138],"type":"Point"}
}