{
  "type": "Feature",
  "properties": {
    "iso:country": "GB",
    "wof:name": "LL22 7SX",
    "wof:placetype": "postalcode"
  },
  "geometry": {"coordinates":[-3.580209,53.295044],"type":"Point"}
}
