{
  "type": "Feature",
  "properties": {
    "date:inception_lower": "2019-07-01",
    "date:inception_upper": "2019-07-01",
    "iso:country": "GB",
    "wof:name": "EH6 7GG",
    "wof:placetype": "postalcode"
  },
  "geometry": {"coordinates":[-3.160286,55.973354],"type":"Point"}
}
