{
  "type": "Feature",
  "properties": {
    "iso:country": "GB",
    "wof:name": "EH6 7GG",
    "wof:placetype": "postalcode"
  },
  "geometry": {"coordinates":[-3.160286,55.973363],"type":"Point"}
}
