{
  "type": "Feature",
  "properties": {
    "iso:country":"GB",
    "wof:name":"DG2 8JL",
    "wof:placetype":"postalcode"
},
  "geometry": {"coordinates":[-3.73691719108168,54.99799871917693],"type":"Point"}
}