{
  "type": "Feature",
  "properties": {
    "iso:country":"GB",
    "wof:name":"EX15 3RA",
    "wof:placetype":"postalcode"
},
  "geometry": {"coordinates":[-3.23051020557637,50.91168412021253],"type":"Point"}
}