{
  "type": "Feature",
  "properties": {
    "iso:country":"GB",
    "wof:name":"HX6 4AL",
    "wof:placetype":"postalcode"
},
  "geometry": {"coordinates":[-1.93830589426691,53.67593016770093],"type":"Point"}
}