{
  "type": "Feature",
  "properties": {
    "date:inception_lower": "1994-05-01",
    "date:inception_upper": "1994-05-01",
    "iso:country": "GB",
    "wof:name": "M43 6EP",
    "wof:placetype": "postalcode"
  },
  "geometry": {"coordinates":[-2.145998,53.479238],"type":"Point"}
}
