{
  "type": "Feature",
  "properties": {
    "date:inception_lower": "2017-05-01",
    "date:inception_upper": "2017-05-01",
    "iso:country": "GB",
    "wof:name": "PL10 1FA",
    "wof:placetype": "postalcode"
  },
  "geometry": {"coordinates":[-4.214746,50.353331],"type":"Point"}
}
