{
  "type": "Feature",
  "properties": {
    "iso:country":"GB",
    "wof:name":"CM1 3HE",
    "wof:placetype":"postalcode"
},
  "geometry": {"coordinates":[0.42507670072601,51.72610764203228],"type":"Point"}
}