{
  "type": "Feature",
  "properties": {
    "iso:country": "GB",
    "wof:name": "CM1 3HE",
    "wof:placetype": "postalcode"
  },
  "geometry": {"coordinates":[0.425077,51.726108],"type":"Point"}
}
