{
  "type": "Feature",
  "properties": {
    "iso:country":"GB",
    "wof:name":"PO11 0PX",
    "wof:placetype":"postalcode"
},
  "geometry": {"coordinates":[-0.974586322361,50.80612654145563],"type":"Point"}
}