{
  "type": "Feature",
  "properties": {
    "iso:country": "GB",
    "wof:name": "OX7 5UZ",
    "wof:placetype": "postalcode"
  },
  "geometry": {"coordinates":[-1.532023,51.947658],"type":"Point"}
}
