{
  "type": "Feature",
  "properties": {
    "date:inception_lower": "1999-12-01",
    "date:inception_upper": "1999-12-01",
    "iso:country": "GB",
    "wof:name": "BH9 1TB",
    "wof:placetype": "postalcode"
  },
  "geometry": {"coordinates":[-1.875195,50.750296],"type":"Point"}
}
