{
  "type": "Feature",
  "properties": {
    "iso:country":"GB",
    "wof:name":"WF2 6RZ",
    "wof:placetype":"postalcode"
},
  "geometry": {"coordinates":[-1.4813608485775,53.6456481982781],"type":"Point"}
}