{
  "type": "Feature",
  "properties": {
    "iso:country":"GB",
    "wof:name":"SA1 1NZ",
    "wof:placetype":"postalcode"
},
  "geometry": {"coordinates":[-3.94203898223031,51.62214149201273],"type":"Point"}
}