{
  "type": "Feature",
  "properties": {
    "date:inception_lower":"1980-01-01",
    "date:inception_upper":"1980-01-31",
    "iso:country":"GB",
    "wof:name":"DY4 8RA",
    "wof:placetype":"postalcode"
},
  "geometry": {"coordinates":[-2.04814,52.525945],"type":"Point"}
}