{
  "type": "Feature",
  "properties": {
    "iso:country": "GB",
    "wof:name": "DY4 8RA",
    "wof:placetype": "postalcode"
  },
  "geometry": {"coordinates":[-2.04814,52.525945],"type":"Point"}
}
