{
  "type": "Feature",
  "properties": {
    "iso:country": "GB",
    "wof:name": "PL12 4QS",
    "wof:placetype": "postalcode"
  },
  "geometry": {"coordinates":[-4.235445,50.401662],"type":"Point"}
}
