{
  "type": "Feature",
  "properties": {
    "date:inception_lower":"1993-08-01",
    "date:inception_upper":"1993-08-31",
    "iso:country":"GB",
    "wof:name":"ST16 2LJ",
    "wof:placetype":"postalcode"
},
  "geometry": {"coordinates":[-2.115711,52.807185],"type":"Point"}
}