{
  "type": "Feature",
  "properties": {
    "iso:country": "GB",
    "wof:name": "ST16 2LJ",
    "wof:placetype": "postalcode"
  },
  "geometry": {"coordinates":[-2.115711,52.807185],"type":"Point"}
}
