{
  "type": "Feature",
  "properties": {
    "iso:country":"GB",
    "wof:name":"NE24 5LP",
    "wof:placetype":"postalcode"
},
  "geometry": {"coordinates":[-1.54384646512455,55.12714864695668],"type":"Point"}
}