{
  "type": "Feature",
  "properties": {
    "date:inception_lower":"1980-01-01",
    "date:inception_upper":"1980-01-31",
    "iso:country":"GB",
    "wof:name":"NE24 5LP",
    "wof:placetype":"postalcode"
},
  "geometry": {"coordinates":[-1.543846,55.127149],"type":"Point"}
}