{
  "type": "Feature",
  "properties": {
    "date:inception_lower": "1980-01-01",
    "date:inception_upper": "1980-01-01",
    "iso:country": "GB",
    "wof:name": "LA5 8AJ",
    "wof:placetype": "postalcode"
  },
  "geometry": {"coordinates":[-2.795649,54.093369],"type":"Point"}
}
