{
  "type": "Feature",
  "properties": {
    "iso:country":"GB",
    "wof:name":"LA5 8AJ",
    "wof:placetype":"postalcode"
},
  "geometry": {"coordinates":[-2.79564920893137,54.093368691701],"type":"Point"}
}