{
  "type": "Feature",
  "properties": {
    "iso:country": "GB",
    "wof:name": "ST10 3HU",
    "wof:placetype": "postalcode"
  },
  "geometry": {"coordinates":[-1.882027,53.053058],"type":"Point"}
}
