{
  "type": "Feature",
  "properties": {
    "iso:country":"GB",
    "wof:name":"ST10 3HU",
    "wof:placetype":"postalcode"
},
  "geometry": {"coordinates":[-1.88202692420836,53.05305786068197],"type":"Point"}
}