{
  "type": "Feature",
  "properties": {
    "iso:country":"GB",
    "wof:name":"SK17 8BD",
    "wof:placetype":"postalcode"
},
  "geometry": {"coordinates":[-1.86286973963333,53.28861876738545],"type":"Point"}
}