{
  "type": "Feature",
  "properties": {
    "iso:country": "GB",
    "wof:name": "IP12 2GY",
    "wof:placetype": "postalcode"
  },
  "geometry": {"coordinates":[1.415307,52.130506],"type":"Point"}
}
