{
  "type": "Feature",
  "properties": {
    "iso:country":"GB",
    "wof:name":"KA7 2QB",
    "wof:placetype":"postalcode"
},
  "geometry": {"coordinates":[-4.62684398113067,55.44416003101265],"type":"Point"}
}