{
  "type": "Feature",
  "properties": {
    "iso:country": "GB",
    "wof:name": "CF61 1AW",
    "wof:placetype": "postalcode"
  },
  "geometry": {"coordinates":[-3.47175,51.404736],"type":"Point"}
}
