{
  "type": "Feature",
  "properties": {
    "date:inception_lower": "1993-01-01",
    "date:inception_upper": "1993-01-01",
    "iso:country": "GB",
    "wof:name": "CF61 1AW",
    "wof:placetype": "postalcode"
  },
  "geometry": {"coordinates":[-3.47175,51.404736],"type":"Point"}
}
