{
  "type": "Feature",
  "properties": {
    "date:inception_lower": "1980-01-01",
    "date:inception_upper": "1980-01-01",
    "iso:country": "GB",
    "wof:name": "WR6 5UH",
    "wof:placetype": "postalcode"
  },
  "geometry": {"coordinates":[-2.442378,52.202783],"type":"Point"}
}
