{
  "type": "Feature",
  "properties": {
    "iso:country":"GB",
    "wof:name":"WR6 5UH",
    "wof:placetype":"postalcode"
},
  "geometry": {"coordinates":[-2.44237832903178,52.2027832983461],"type":"Point"}
}