{
  "type": "Feature",
  "properties": {
    "iso:country": "GB",
    "wof:name": "NE63 0AU",
    "wof:placetype": "postalcode"
  },
  "geometry": {"coordinates":[-1.566721,55.181274],"type":"Point"}
}
