{
  "type": "Feature",
  "properties": {
    "iso:country":"GB",
    "wof:name":"NE63 0AU",
    "wof:placetype":"postalcode"
},
  "geometry": {"coordinates":[-1.56672088127561,55.18127395448638],"type":"Point"}
}