{
  "type": "Feature",
  "properties": {
    "date:inception_lower":"1987-04-01",
    "date:inception_upper":"1987-04-30",
    "iso:country":"GB",
    "wof:name":"NE63 0AU",
    "wof:placetype":"postalcode"
},
  "geometry": {"coordinates":[-1.566721,55.181274],"type":"Point"}
}