{
  "type": "Feature",
  "properties": {
    "date:inception_lower": "1984-10-01",
    "date:inception_upper": "1984-10-01",
    "iso:country": "GB",
    "wof:name": "PO40 9RT",
    "wof:placetype": "postalcode"
  },
  "geometry": {"coordinates":[-1.521035,50.692006],"type":"Point"}
}
