{
  "type": "Feature",
  "properties": {
    "iso:country":"GB",
    "wof:name":"PO40 9RT",
    "wof:placetype":"postalcode"
},
  "geometry": {"coordinates":[-1.52099475023019,50.69180810721785],"type":"Point"}
}