{
  "type": "Feature",
  "properties": {
    "iso:country":"GB",
    "wof:name":"SA42 0XD",
    "wof:placetype":"postalcode"
},
  "geometry": {"coordinates":[-4.90213137716923,52.01088675336234],"type":"Point"}
}