{
  "type": "Feature",
  "properties": {
    "date:inception_lower": "1980-01-01",
    "date:inception_upper": "1980-01-01",
    "iso:country": "GB",
    "wof:name": "OX5 2HB",
    "wof:placetype": "postalcode"
  },
  "geometry": {"coordinates":[-1.282956,51.824181],"type":"Point"}
}
