{
  "type": "Feature",
  "properties": {
    "iso:country":"GB",
    "wof:name":"OX5 2HB",
    "wof:placetype":"postalcode"
},
  "geometry": {"coordinates":[-1.28295579552238,51.82418080043228],"type":"Point"}
}