{
  "type": "Feature",
  "properties": {
    "iso:country":"GB",
    "wof:name":"IP33 1SZ",
    "wof:placetype":"postalcode"
},
  "geometry": {"coordinates":[0.71096567410247,52.24997553870915],"type":"Point"}
}