{
  "type": "Feature",
  "properties": {
    "date:inception_lower": "2017-10-01",
    "date:inception_upper": "2017-10-01",
    "iso:country": "GB",
    "wof:name": "CR2 9FA",
    "wof:placetype": "postalcode"
  },
  "geometry": {"coordinates":[-0.073964,51.335612],"type":"Point"}
}
