{
  "type": "Feature",
  "properties": {
    "date:inception_lower": "1990-02-01",
    "date:inception_upper": "1990-02-01",
    "iso:country": "GB",
    "wof:name": "HA0 2NQ",
    "wof:placetype": "postalcode"
  },
  "geometry": {"coordinates":[-0.302328,51.556707],"type":"Point"}
}
