{
  "type": "Feature",
  "properties": {
    "iso:country":"GB",
    "wof:name":"HP15 7PA",
    "wof:placetype":"postalcode"
},
  "geometry": {"coordinates":[-0.6998520057545,51.64637991562162],"type":"Point"}
}