{
  "type": "Feature",
  "properties": {
    "date:inception_lower":"1990-02-01",
    "date:inception_upper":"1990-02-28",
    "iso:country":"GB",
    "wof:name":"HP15 7PA",
    "wof:placetype":"postalcode"
},
  "geometry": {"coordinates":[-0.699852,51.64638],"type":"Point"}
}