{
  "type": "Feature",
  "properties": {
    "iso:country":"GB",
    "wof:name":"NE6 4AE",
    "wof:placetype":"postalcode"
},
  "geometry": {"coordinates":[-1.56014729967911,54.97645658080091],"type":"Point"}
}