{
  "type": "Feature",
  "properties": {
    "iso:country":"GB",
    "wof:name":"IG1 2SW",
    "wof:placetype":"postalcode"
},
  "geometry": {"coordinates":[0.08294090139724,51.5462373670607],"type":"Point"}
}