{
  "type": "Feature",
  "properties": {
    "date:inception_lower":"1995-01-01",
    "date:inception_upper":"1995-01-31",
    "iso:country":"GB",
    "wof:name":"IG1 2SW",
    "wof:placetype":"postalcode"
},
  "geometry": {"coordinates":[0.082941,51.546237],"type":"Point"}
}