{
  "type": "Feature",
  "properties": {
    "iso:country": "GB",
    "wof:name": "IG1 2SW",
    "wof:placetype": "postalcode"
  },
  "geometry": {"coordinates":[0.082941,51.546237],"type":"Point"}
}
