{
  "type": "Feature",
  "properties": {
    "iso:country":"GB",
    "wof:name":"HU19 2BY",
    "wof:placetype":"postalcode"
},
  "geometry": {"coordinates":[-0.01355664398412,53.7509430222927],"type":"Point"}
}