{
  "type": "Feature",
  "properties": {
    "date:inception_lower":"1980-01-01",
    "date:inception_upper":"1980-01-31",
    "iso:country":"GB",
    "wof:name":"HU19 2BY",
    "wof:placetype":"postalcode"
},
  "geometry": {"coordinates":[-0.013557,53.750943],"type":"Point"}
}