{
  "type": "Feature",
  "properties": {
    "iso:country":"GB",
    "wof:name":"TR26 1LS",
    "wof:placetype":"postalcode"
},
  "geometry": {"coordinates":[-5.4796125094885,50.21545116244636],"type":"Point"}
}