{
  "type": "Feature",
  "properties": {
    "date:inception_lower": "1980-01-01",
    "date:inception_upper": "1980-01-01",
    "iso:country": "GB",
    "wof:name": "IP17 3JW",
    "wof:placetype": "postalcode"
  },
  "geometry": {"coordinates":[1.492778,52.276118],"type":"Point"}
}
