{
  "type": "Feature",
  "properties": {
    "date:inception_lower": "2021-01-01",
    "date:inception_upper": "2021-01-01",
    "iso:country": "GB",
    "wof:name": "RG14 5BB",
    "wof:placetype": "postalcode"
  },
  "geometry": {"coordinates":[-1.296116,51.4007],"type":"Point"}
}
