{
  "type": "Feature",
  "properties": {
    "iso:country":"GB",
    "wof:name":"WC2E 8JG",
    "wof:placetype":"postalcode"
},
  "geometry": {"coordinates":[-0.12473103047923,51.5118643730609],"type":"Point"}
}