{
  "type": "Feature",
  "properties": {
    "iso:country": "GB",
    "wof:name": "SP11 7EH",
    "wof:placetype": "postalcode"
  },
  "geometry": {"coordinates":[-1.625599,51.167618],"type":"Point"}
}
