{
  "type": "Feature",
  "properties": {
    "iso:country":"GB",
    "wof:name":"SP11 7EH",
    "wof:placetype":"postalcode"
},
  "geometry": {"coordinates":[-1.62559928129232,51.16761814390939],"type":"Point"}
}