{
  "type": "Feature",
  "properties": {
    "iso:country":"GB",
    "wof:name":"EX10 0BH",
    "wof:placetype":"postalcode"
},
  "geometry": {"coordinates":[-3.30792909998891,50.69808563770244],"type":"Point"}
}