{
  "type": "Feature",
  "properties": {
    "iso:country":"GB",
    "wof:name":"SE6 2EU",
    "wof:placetype":"postalcode"
},
  "geometry": {"coordinates":[-0.01191842509549,51.44358617011873],"type":"Point"}
}