{
  "type": "Feature",
  "properties": {
    "date:inception_lower":"2004-08-01",
    "date:inception_upper":"2004-08-31",
    "iso:country":"GB",
    "wof:name":"TW8 8LJ",
    "wof:placetype":"postalcode"
},
  "geometry": {"coordinates":[-0.309953,51.482892],"type":"Point"}
}