{
  "type": "Feature",
  "properties": {
    "iso:country":"GB",
    "wof:name":"TW8 8LJ",
    "wof:placetype":"postalcode"
},
  "geometry": {"coordinates":[-0.3099526840804,51.48289151848611],"type":"Point"}
}