{
  "type": "Feature",
  "properties": {
    "date:inception_lower": "2023-05-01",
    "date:inception_upper": "2023-05-01",
    "iso:country": "GB",
    "wof:name": "SY12 9FG",
    "wof:placetype": "postalcode"
  },
  "geometry": {"coordinates":[-2.908303,52.909435],"type":"Point"}
}
