{
  "type": "Feature",
  "properties": {
    "iso:country":"GB",
    "wof:name":"ML6 9ST",
    "wof:placetype":"postalcode"
},
  "geometry": {"coordinates":[-3.96665813231823,55.84150149110938],"type":"Point"}
}