{
  "type": "Feature",
  "properties": {
    "date:inception_lower": "2019-02-01",
    "date:inception_upper": "2019-02-01",
    "iso:country": "GB",
    "wof:name": "BS16 7LY",
    "wof:placetype": "postalcode"
  },
  "geometry": {"coordinates":[-2.463975,51.497247],"type":"Point"}
}
