{
  "type": "Feature",
  "properties": {
    "iso:country":"GB",
    "wof:name":"SY6 6NR",
    "wof:placetype":"postalcode"
},
  "geometry": {"coordinates":[-2.83543944682974,52.59030423727166],"type":"Point"}
}