{
  "type": "Feature",
  "properties": {
    "iso:country":"GB",
    "wof:name":"B70 7EH",
    "wof:placetype":"postalcode"
},
  "geometry": {"coordinates":[-1.99515283066206,52.51201127429105],"type":"Point"}
}