{
  "type": "Feature",
  "properties": {
    "iso:country":"GB",
    "wof:name":"CV2 2QL",
    "wof:placetype":"postalcode"
},
  "geometry": {"coordinates":[-1.43966392598196,52.42964053748533],"type":"Point"}
}