{
  "type": "Feature",
  "properties": {
    "iso:country": "GB",
    "wof:name": "CV2 2QL",
    "wof:placetype": "postalcode"
  },
  "geometry": {"coordinates":[-1.439664,52.429641],"type":"Point"}
}
