{
  "type": "Feature",
  "properties": {
    "date:inception_lower":"2001-12-01",
    "date:inception_upper":"2001-12-31",
    "iso:country":"GB",
    "wof:name":"CV2 2QL",
    "wof:placetype":"postalcode"
},
  "geometry": {"coordinates":[-1.439664,52.429641],"type":"Point"}
}