{
  "type": "Feature",
  "properties": {
    "iso:country":"GB",
    "wof:name":"TF11 8PH",
    "wof:placetype":"postalcode"
},
  "geometry": {"coordinates":[-2.31200401351928,52.65442990798863],"type":"Point"}
}