{
  "type": "Feature",
  "properties": {
    "date:inception_lower":"2004-10-01",
    "date:inception_upper":"2004-10-31",
    "iso:country":"GB",
    "wof:name":"BS36 1AR",
    "wof:placetype":"postalcode"
},
  "geometry": {"coordinates":[-2.491024,51.500762],"type":"Point"}
}