{
  "type": "Feature",
  "properties": {
    "date:inception_lower":"1980-01-01",
    "date:inception_upper":"1980-01-31",
    "iso:country":"GB",
    "wof:name":"DT11 9NH",
    "wof:placetype":"postalcode"
},
  "geometry": {"coordinates":[-2.140801,50.834267],"type":"Point"}
}