{
  "type": "Feature",
  "properties": {
    "iso:country": "GB",
    "wof:name": "DT11 9NH",
    "wof:placetype": "postalcode"
  },
  "geometry": {"coordinates":[-2.140801,50.834267],"type":"Point"}
}
