{
  "type": "Feature",
  "properties": {
    "iso:country":"GB",
    "wof:name":"DT11 9NH",
    "wof:placetype":"postalcode"
},
  "geometry": {"coordinates":[-2.14080055959785,50.83426742363481],"type":"Point"}
}