{
  "type": "Feature",
  "properties": {
    "iso:country":"GB",
    "wof:name":"IP6 8TA",
    "wof:placetype":"postalcode"
},
  "geometry": {"coordinates":[1.04961066223293,52.14866007524816],"type":"Point"}
}