{
  "type": "Feature",
  "properties": {
    "iso:country": "GB",
    "wof:name": "PH2 8LU",
    "wof:placetype": "postalcode"
  },
  "geometry": {"coordinates":[-3.432564,56.392804],"type":"Point"}
}
