{
  "type": "Feature",
  "properties": {
    "iso:country": "GB",
    "wof:name": "HP16 0LN",
    "wof:placetype": "postalcode"
  },
  "geometry": {"coordinates":[-0.735584,51.696116],"type":"Point"}
}
