{
  "type": "Feature",
  "properties": {
    "iso:country":"GB",
    "wof:name":"HP16 0LN",
    "wof:placetype":"postalcode"
},
  "geometry": {"coordinates":[-0.73558420581297,51.69611650029173],"type":"Point"}
}