{
  "type": "Feature",
  "properties": {
    "iso:country":"GB",
    "wof:name":"YO25 8EW",
    "wof:placetype":"postalcode"
},
  "geometry": {"coordinates":[-0.28723415735902,53.94045887562774],"type":"Point"}
}