{
  "type": "Feature",
  "properties": {
    "date:inception_lower":"1980-01-01",
    "date:inception_upper":"1980-01-31",
    "iso:country":"GB",
    "wof:name":"YO25 8EW",
    "wof:placetype":"postalcode"
},
  "geometry": {"coordinates":[-0.287234,53.940459],"type":"Point"}
}