{
  "type": "Feature",
  "properties": {
    "iso:country":"GB",
    "wof:name":"SL6 9AB",
    "wof:placetype":"postalcode"
},
  "geometry": {"coordinates":[-0.73160201251186,51.56359788321946],"type":"Point"}
}