{
  "type": "Feature",
  "properties": {
    "iso:country": "GB",
    "wof:name": "NG23 5HL",
    "wof:placetype": "postalcode"
  },
  "geometry": {"coordinates":[-0.735254,52.990534],"type":"Point"}
}
