{
  "type": "Feature",
  "properties": {
    "date:inception_lower":"1980-01-01",
    "date:inception_upper":"1980-01-31",
    "iso:country":"GB",
    "wof:name":"NG23 5HL",
    "wof:placetype":"postalcode"
},
  "geometry": {"coordinates":[-0.735254,52.990534],"type":"Point"}
}