{
  "type": "Feature",
  "properties": {
    "iso:country":"GB",
    "wof:name":"NG23 5HL",
    "wof:placetype":"postalcode"
},
  "geometry": {"coordinates":[-0.73525384772992,52.9905340303639],"type":"Point"}
}