{
  "type": "Feature",
  "properties": {
    "iso:country":"GB",
    "wof:name":"NG18 3HU",
    "wof:placetype":"postalcode"
},
  "geometry": {"coordinates":[-1.1591479203497,53.133558325677],"type":"Point"}
}