{
  "type": "Feature",
  "properties": {
    "iso:country":"GB",
    "wof:name":"EX15 2LE",
    "wof:placetype":"postalcode"
},
  "geometry": {"coordinates":[-3.33766232826289,50.81831862566039],"type":"Point"}
}