{
  "type": "Feature",
  "properties": {
    "iso:country":"GB",
    "wof:name":"M33 4HR",
    "wof:placetype":"postalcode"
},
  "geometry": {"coordinates":[-2.35261546122647,53.4093067841285],"type":"Point"}
}