{
  "type": "Feature",
  "properties": {
    "date:inception_lower": "2008-04-01",
    "date:inception_upper": "2008-04-01",
    "iso:country": "GB",
    "wof:name": "WV10 9NA",
    "wof:placetype": "postalcode"
  },
  "geometry": {"coordinates":[-2.120244,52.606406],"type":"Point"}
}
