{
  "type": "Feature",
  "properties": {
    "iso:country":"GB",
    "wof:name":"EC1V 0ER",
    "wof:placetype":"postalcode"
},
  "geometry": {"coordinates":[-0.1024315472285,51.52654123986294],"type":"Point"}
}