{
  "type": "Feature",
  "properties": {
    "date:inception_lower":"1987-04-01",
    "date:inception_upper":"1987-04-30",
    "iso:country":"GB",
    "wof:name":"SE1 2HD",
    "wof:placetype":"postalcode"
},
  "geometry": {"coordinates":[-0.083548,51.505893],"type":"Point"}
}