{
  "type": "Feature",
  "properties": {
    "date:inception_lower":"2010-10-01",
    "date:inception_upper":"2010-10-31",
    "iso:country":"GB",
    "wof:name":"EN8 0FG",
    "wof:placetype":"postalcode"
},
  "geometry": {"coordinates":[-0.041726,51.713405],"type":"Point"}
}