{
  "type": "Feature",
  "properties": {
    "iso:country":"GB",
    "wof:name":"M30 8FD",
    "wof:placetype":"postalcode"
},
  "geometry": {"coordinates":[-2.36642572958089,53.49155520649042],"type":"Point"}
}