{
  "type": "Feature",
  "properties": {
    "iso:country":"GB",
    "wof:name":"SW5 9NL",
    "wof:placetype":"postalcode"
},
  "geometry": {"coordinates":[-0.19488468814479,51.49149104794642],"type":"Point"}
}