{
  "type": "Feature",
  "properties": {
    "iso:country":"GB",
    "wof:name":"RG25 3AZ",
    "wof:placetype":"postalcode"
},
  "geometry": {"coordinates":[-1.2199193805303,51.23646609921133],"type":"Point"}
}