{
  "type": "Feature",
  "properties": {
    "iso:country":"GB",
    "wof:name":"SA43 2DR",
    "wof:placetype":"postalcode"
},
  "geometry": {"coordinates":[-4.56226204446783,52.1321921535987],"type":"Point"}
}