{
  "type": "Feature",
  "properties": {
    "iso:country":"GB",
    "wof:name":"HP18 0SB",
    "wof:placetype":"postalcode"
},
  "geometry": {"coordinates":[-1.0060544930441,51.83991600449919],"type":"Point"}
}