{
  "type": "Feature",
  "properties": {
    "iso:country": "GB",
    "wof:name": "HP18 0SB",
    "wof:placetype": "postalcode"
  },
  "geometry": {"coordinates":[-1.0051,51.839099],"type":"Point"}
}
