{
  "type": "Feature",
  "properties": {
    "date:inception_lower": "1980-01-01",
    "date:inception_upper": "1980-01-01",
    "iso:country": "GB",
    "wof:name": "HP18 0SB",
    "wof:placetype": "postalcode"
  },
  "geometry": {"coordinates":[-1.0051,51.839099],"type":"Point"}
}
