{
  "type": "Feature",
  "properties": {
    "iso:country":"GB",
    "wof:name":"N22 7XD",
    "wof:placetype":"postalcode"
},
  "geometry": {"coordinates":[-0.12700966401137,51.59926256846608],"type":"Point"}
}