{
  "type": "Feature",
  "properties": {
    "iso:country":"GB",
    "wof:name":"LE5 2QJ",
    "wof:placetype":"postalcode"
},
  "geometry": {"coordinates":[-1.0494471231717,52.64102528402307],"type":"Point"}
}