{
  "type": "Feature",
  "properties": {
    "iso:country":"GB",
    "wof:name":"ST5 2DP",
    "wof:placetype":"postalcode"
},
  "geometry": {"coordinates":[-2.22813413696016,53.01233789761172],"type":"Point"}
}