{
  "type": "Feature",
  "properties": {
    "iso:country":"GB",
    "wof:name":"SE2 0YB",
    "wof:placetype":"postalcode"
},
  "geometry": {"coordinates":[0.1022677117149,51.48050593197255],"type":"Point"}
}