{
  "type": "Feature",
  "properties": {
    "iso:country": "GB",
    "wof:name": "SW16 6NT",
    "wof:placetype": "postalcode"
  },
  "geometry": {"coordinates":[-0.145154,51.421634],"type":"Point"}
}
