{
  "type": "Feature",
  "properties": {
    "iso:country":"GB",
    "wof:name":"SW16 6NT",
    "wof:placetype":"postalcode"
},
  "geometry": {"coordinates":[-0.14515439785359,51.42163400542302],"type":"Point"}
}