{
  "type": "Feature",
  "properties": {
    "iso:country":"GB",
    "wof:name":"DH4 4AT",
    "wof:placetype":"postalcode"
},
  "geometry": {"coordinates":[-1.47240758531337,54.84754820544088],"type":"Point"}
}