{
  "type": "Feature",
  "properties": {
    "iso:country":"GB",
    "wof:name":"G71 7SW",
    "wof:placetype":"postalcode"
},
  "geometry": {"coordinates":[-4.10920679661147,55.83707234879439],"type":"Point"}
}