{
  "type": "Feature",
  "properties": {
    "date:inception_lower":"2016-04-01",
    "date:inception_upper":"2016-04-30",
    "iso:country":"GB",
    "wof:name":"G71 7SW",
    "wof:placetype":"postalcode"
},
  "geometry": {"coordinates":[-4.103366,55.844178],"type":"Point"}
}