{
  "type": "Feature",
  "properties": {
    "iso:country": "GB",
    "wof:name": "G71 7SW",
    "wof:placetype": "postalcode"
  },
  "geometry": {"coordinates":[-4.103366,55.844178],"type":"Point"}
}
