{
  "type": "Feature",
  "properties": {
    "iso:country":"GB",
    "wof:name":"TW1 3RY",
    "wof:placetype":"postalcode"
},
  "geometry": {"coordinates":[-0.32812841342833,51.44703869333794],"type":"Point"}
}