{
  "type": "Feature",
  "properties": {
    "iso:country":"GB",
    "wof:name":"SO41 3TB",
    "wof:placetype":"postalcode"
},
  "geometry": {"coordinates":[-1.53987701568167,50.75296270793455],"type":"Point"}
}