{
  "type": "Feature",
  "properties": {
    "date:inception_lower": "1994-12-01",
    "date:inception_upper": "1994-12-01",
    "iso:country": "GB",
    "wof:name": "SO41 3TB",
    "wof:placetype": "postalcode"
  },
  "geometry": {"coordinates":[-1.539877,50.752963],"type":"Point"}
}
