{
  "type": "Feature",
  "properties": {
    "date:inception_lower": "1980-01-01",
    "date:inception_upper": "1980-01-01",
    "iso:country": "GB",
    "wof:name": "EX34 8HU",
    "wof:placetype": "postalcode"
  },
  "geometry": {"coordinates":[-4.124018,51.202929],"type":"Point"}
}
