{
  "type": "Feature",
  "properties": {
    "iso:country":"GB",
    "wof:name":"EX34 8HU",
    "wof:placetype":"postalcode"
},
  "geometry": {"coordinates":[-4.12401833954979,51.20292915294894],"type":"Point"}
}