{
  "type": "Feature",
  "properties": {
    "date:inception_lower": "1980-01-01",
    "date:inception_upper": "1980-01-01",
    "iso:country": "GB",
    "wof:name": "L33 4YH",
    "wof:placetype": "postalcode"
  },
  "geometry": {"coordinates":[-2.843296,53.507262],"type":"Point"}
}
