{
  "type": "Feature",
  "properties": {
    "iso:country":"GB",
    "wof:name":"L33 4YH",
    "wof:placetype":"postalcode"
},
  "geometry": {"coordinates":[-2.84327920247902,53.50641732908605],"type":"Point"}
}