{
  "type": "Feature",
  "properties": {
    "date:inception_lower": "1999-06-01",
    "date:inception_upper": "1999-06-01",
    "iso:country": "GB",
    "wof:name": "NP18 3RP",
    "wof:placetype": "postalcode"
  },
  "geometry": {"coordinates":[-2.980575,51.610014],"type":"Point"}
}
