{
  "type": "Feature",
  "properties": {
    "iso:country":"GB",
    "wof:name":"NP18 3RP",
    "wof:placetype":"postalcode"
},
  "geometry": {"coordinates":[-2.98057554025534,51.61001420950164],"type":"Point"}
}