{
  "type": "Feature",
  "properties": {
    "iso:country":"GB",
    "wof:name":"G69 7LS",
    "wof:placetype":"postalcode"
},
  "geometry": {"coordinates":[-4.13222333475396,55.84821500419693],"type":"Point"}
}