{
  "type": "Feature",
  "properties": {
    "iso:country":"GB",
    "wof:name":"CB1 7BX",
    "wof:placetype":"postalcode"
},
  "geometry": {"coordinates":[0.14478294091372,52.18820474068984],"type":"Point"}
}