{
  "type": "Feature",
  "properties": {
    "iso:country":"GB",
    "wof:name":"RG12 7AY",
    "wof:placetype":"postalcode"
},
  "geometry": {"coordinates":[-0.75340737485403,51.40595962500615],"type":"Point"}
}