{
  "type": "Feature",
  "properties": {
    "iso:country":"GB",
    "wof:name":"SE11 4RX",
    "wof:placetype":"postalcode"
},
  "geometry": {"coordinates":[-0.10239199866919,51.49211709543259],"type":"Point"}
}