{
  "type": "Feature",
  "properties": {
    "date:inception_lower": "1990-02-01",
    "date:inception_upper": "1990-02-01",
    "iso:country": "GB",
    "wof:name": "TN22 2DE",
    "wof:placetype": "postalcode"
  },
  "geometry": {"coordinates":[0.083993,50.972041],"type":"Point"}
}
