{
  "type": "Feature",
  "properties": {
    "iso:country":"GB",
    "wof:name":"WN2 4QL",
    "wof:placetype":"postalcode"
},
  "geometry": {"coordinates":[-2.55565644466216,53.52945752950371],"type":"Point"}
}