{
  "type": "Feature",
  "properties": {
    "iso:country": "GB",
    "wof:name": "WN2 4QL",
    "wof:placetype": "postalcode"
  },
  "geometry": {"coordinates":[-2.555656,53.529458],"type":"Point"}
}
