{
  "type": "Feature",
  "properties": {
    "iso:country": "GB",
    "wof:name": "WR6 5SS",
    "wof:placetype": "postalcode"
  },
  "geometry": {"coordinates":[-2.431692,52.211346],"type":"Point"}
}
