{
  "type": "Feature",
  "properties": {
    "iso:country":"GB",
    "wof:name":"WR6 5SS",
    "wof:placetype":"postalcode"
},
  "geometry": {"coordinates":[-2.431691900156,52.21134583415997],"type":"Point"}
}