{
  "type": "Feature",
  "properties": {
    "date:inception_lower":"1980-01-01",
    "date:inception_upper":"1980-01-31",
    "iso:country":"GB",
    "wof:name":"BL4 9SB",
    "wof:placetype":"postalcode"
},
  "geometry": {"coordinates":[-2.423859,53.548244],"type":"Point"}
}