{
  "type": "Feature",
  "properties": {
    "iso:country":"GB",
    "wof:name":"BL4 9SB",
    "wof:placetype":"postalcode"
},
  "geometry": {"coordinates":[-2.42385903412178,53.54824411213463],"type":"Point"}
}