{
  "type": "Feature",
  "properties": {
    "date:inception_lower": "2003-03-01",
    "date:inception_upper": "2003-03-01",
    "iso:country": "GB",
    "wof:name": "WS11 8LX",
    "wof:placetype": "postalcode"
  },
  "geometry": {"coordinates":[-2.008527,52.668612],"type":"Point"}
}
