{
  "type": "Feature",
  "properties": {
    "date:inception_lower": "2017-09-01",
    "date:inception_upper": "2017-09-01",
    "iso:country": "GB",
    "wof:name": "EH55 8QG",
    "wof:placetype": "postalcode"
  },
  "geometry": {"coordinates":[-3.572142,55.858208],"type":"Point"}
}
