{
  "type": "Feature",
  "properties": {
    "date:inception_lower": "1980-01-01",
    "date:inception_upper": "1980-01-01",
    "iso:country": "GB",
    "wof:name": "LL18 5BN",
    "wof:placetype": "postalcode"
  },
  "geometry": {"coordinates":[-3.517431,53.312795],"type":"Point"}
}
