{
  "type": "Feature",
  "properties": {
    "date:inception_lower": "2019-08-01",
    "date:inception_upper": "2019-08-01",
    "iso:country": "GB",
    "wof:name": "E17 6DQ",
    "wof:placetype": "postalcode"
  },
  "geometry": {"coordinates":[-0.028851,51.583971],"type":"Point"}
}
