{
  "type": "Feature",
  "properties": {
    "iso:country":"GB",
    "wof:name":"HS3 3ED",
    "wof:placetype":"postalcode"
},
  "geometry": {"coordinates":[-6.76337631393007,57.83171172939954],"type":"Point"}
}