{
  "type": "Feature",
  "properties": {
    "date:inception_lower": "1995-07-01",
    "date:inception_upper": "1995-07-01",
    "iso:country": "GB",
    "wof:name": "HS3 3ED",
    "wof:placetype": "postalcode"
  },
  "geometry": {"coordinates":[-6.763376,57.831712],"type":"Point"}
}
