{
  "type": "Feature",
  "properties": {
    "iso:country": "GB",
    "wof:name": "BH21 3TD",
    "wof:placetype": "postalcode"
  },
  "geometry": {"coordinates":[-2.021106,50.770809],"type":"Point"}
}
