{
  "type": "Feature",
  "properties": {
    "date:inception_lower":"1981-06-01",
    "date:inception_upper":"1981-06-30",
    "iso:country":"GB",
    "wof:name":"BH21 3TD",
    "wof:placetype":"postalcode"
},
  "geometry": {"coordinates":[-2.021106,50.770809],"type":"Point"}
}