{
  "type": "Feature",
  "properties": {
    "date:inception_lower": "1980-01-01",
    "date:inception_upper": "1980-01-01",
    "iso:country": "GB",
    "wof:name": "SR7 8LR",
    "wof:placetype": "postalcode"
  },
  "geometry": {"coordinates":[-1.353064,54.835154],"type":"Point"}
}
