{
  "type": "Feature",
  "properties": {
    "date:inception_lower":"1980-01-01",
    "date:inception_upper":"1980-01-31",
    "iso:country":"GB",
    "wof:name":"TR7 2SH",
    "wof:placetype":"postalcode"
},
  "geometry": {"coordinates":[-5.062965,50.409788],"type":"Point"}
}