{
  "type": "Feature",
  "properties": {
    "iso:country":"GB",
    "wof:name":"TR7 2SH",
    "wof:placetype":"postalcode"
},
  "geometry": {"coordinates":[-5.06296503885652,50.40978829850572],"type":"Point"}
}