{
  "type": "Feature",
  "properties": {
    "date:inception_lower": "1993-01-01",
    "date:inception_upper": "1993-01-01",
    "iso:country": "GB",
    "wof:name": "SY11 4RD",
    "wof:placetype": "postalcode"
  },
  "geometry": {"coordinates":[-2.970378,52.81936],"type":"Point"}
}
