{
  "type": "Feature",
  "properties": {
    "iso:country": "GB",
    "wof:name": "SY11 4RD",
    "wof:placetype": "postalcode"
  },
  "geometry": {"coordinates":[-2.970365,52.819337],"type":"Point"}
}
