{
  "type": "Feature",
  "properties": {
    "date:inception_lower":"1993-01-01",
    "date:inception_upper":"1993-01-31",
    "iso:country":"GB",
    "wof:name":"SY11 4RD",
    "wof:placetype":"postalcode"
},
  "geometry": {"coordinates":[-2.970365,52.819337],"type":"Point"}
}