{
  "type": "Feature",
  "properties": {
    "date:inception_lower": "1980-01-01",
    "date:inception_upper": "1980-01-01",
    "iso:country": "GB",
    "wof:name": "L9 3BS",
    "wof:placetype": "postalcode"
  },
  "geometry": {"coordinates":[-2.967763,53.462085],"type":"Point"}
}
