{
  "type": "Feature",
  "properties": {
    "date:inception_lower": "2022-04-01",
    "date:inception_upper": "2022-04-01",
    "iso:country": "GB",
    "wof:name": "PO30 2LE",
    "wof:placetype": "postalcode"
  },
  "geometry": {"coordinates":[-1.27986,50.715647],"type":"Point"}
}
