{
  "type": "Feature",
  "properties": {
    "iso:country":"GB",
    "wof:name":"CM7 1JP",
    "wof:placetype":"postalcode"
},
  "geometry": {"coordinates":[0.55020476574842,51.87817467773993],"type":"Point"}
}