{
  "type": "Feature",
  "properties": {
    "date:inception_lower": "1997-12-01",
    "date:inception_upper": "1997-12-01",
    "iso:country": "GB",
    "wof:name": "CM8 3UN",
    "wof:placetype": "postalcode"
  },
  "geometry": {"coordinates":[0.650965,51.802949],"type":"Point"}
}
