{
  "type": "Feature",
  "properties": {
    "iso:country": "GB",
    "wof:name": "SE5 7NF",
    "wof:placetype": "postalcode"
  },
  "geometry": {"coordinates":[-0.089181,51.479394],"type":"Point"}
}
