{
  "type": "Feature",
  "properties": {
    "iso:country":"GB",
    "wof:name":"SE5 7NF",
    "wof:placetype":"postalcode"
},
  "geometry": {"coordinates":[-0.0891811753251,51.47939385985792],"type":"Point"}
}