{
  "type": "Feature",
  "properties": {
    "iso:country":"GB",
    "wof:name":"SN10 1FG",
    "wof:placetype":"postalcode"
},
  "geometry": {"coordinates":[-1.99591555708834,51.3533851491952],"type":"Point"}
}