{
  "type": "Feature",
  "properties": {
    "iso:country": "GB",
    "wof:name": "SN10 1FG",
    "wof:placetype": "postalcode"
  },
  "geometry": {"coordinates":[-1.995916,51.353385],"type":"Point"}
}
