{
  "type": "Feature",
  "properties": {
    "date:inception_lower":"2010-04-01",
    "date:inception_upper":"2010-04-30",
    "iso:country":"GB",
    "wof:name":"SN10 1FG",
    "wof:placetype":"postalcode"
},
  "geometry": {"coordinates":[-1.995916,51.353385],"type":"Point"}
}