{
  "type": "Feature",
  "properties": {
    "date:inception_lower":"1995-07-01",
    "date:inception_upper":"1995-07-31",
    "iso:country":"GB",
    "wof:name":"TQ12 5JT",
    "wof:placetype":"postalcode"
},
  "geometry": {"coordinates":[-3.584403,50.501204],"type":"Point"}
}