{
  "type": "Feature",
  "properties": {
    "iso:country": "GB",
    "wof:name": "TR2 5RL",
    "wof:placetype": "postalcode"
  },
  "geometry": {"coordinates":[-4.922523,50.21856],"type":"Point"}
}
