{
  "type": "Feature",
  "properties": {
    "date:inception_lower":"2002-08-01",
    "date:inception_upper":"2002-08-31",
    "iso:country":"GB",
    "wof:name":"TR2 5RL",
    "wof:placetype":"postalcode"
},
  "geometry": {"coordinates":[-4.92254,50.218614],"type":"Point"}
}