{
  "type": "Feature",
  "properties": {
    "iso:country":"GB",
    "wof:name":"M14 5LL",
    "wof:placetype":"postalcode"
},
  "geometry": {"coordinates":[-2.22138146267784,53.45017870045413],"type":"Point"}
}