{
  "type": "Feature",
  "properties": {
    "iso:country":"GB",
    "wof:name":"B79 7HU",
    "wof:placetype":"postalcode"
},
  "geometry": {"coordinates":[-1.68880982051434,52.63596850945272],"type":"Point"}
}