{
  "type": "Feature",
  "properties": {
    "iso:country":"GB",
    "wof:name":"WF4 2HN",
    "wof:placetype":"postalcode"
},
  "geometry": {"coordinates":[-1.39857148021464,53.62742825212712],"type":"Point"}
}