{
  "type": "Feature",
  "properties": {
    "iso:country":"GB",
    "wof:name":"HU5 1EZ",
    "wof:placetype":"postalcode"
},
  "geometry": {"coordinates":[-0.34529759481846,53.76082738442281],"type":"Point"}
}