{
  "type": "Feature",
  "properties": {
    "iso:country": "GB",
    "wof:name": "KW1 4TS",
    "wof:placetype": "postalcode"
  },
  "geometry": {"coordinates":[-3.307888,58.544436],"type":"Point"}
}
