{
  "type": "Feature",
  "properties": {
    "iso:country":"GB",
    "wof:name":"KW1 4TS",
    "wof:placetype":"postalcode"
},
  "geometry": {"coordinates":[-3.30788776447802,58.54443641050397],"type":"Point"}
}