{
  "type": "Feature",
  "properties": {
    "iso:country": "GB",
    "wof:name": "CM3 3PH",
    "wof:placetype": "postalcode"
  },
  "geometry": {"coordinates":[0.473967,51.776258],"type":"Point"}
}
