{
  "type": "Feature",
  "properties": {
    "iso:country":"GB",
    "wof:name":"CM3 3PH",
    "wof:placetype":"postalcode"
},
  "geometry": {"coordinates":[0.4739673491804,51.77625842142852],"type":"Point"}
}