{
  "type": "Feature",
  "properties": {
    "date:inception_lower": "1980-01-01",
    "date:inception_upper": "1980-01-01",
    "iso:country": "GB",
    "wof:name": "SE24 0EJ",
    "wof:placetype": "postalcode"
  },
  "geometry": {"coordinates":[-0.105797,51.453756],"type":"Point"}
}
