{
  "type": "Feature",
  "properties": {
    "iso:country":"GB",
    "wof:name":"DN3 2JJ",
    "wof:placetype":"postalcode"
},
  "geometry": {"coordinates":[-1.06399887404509,53.54981184789044],"type":"Point"}
}