{
  "type": "Feature",
  "properties": {
    "date:inception_lower": "1980-01-01",
    "date:inception_upper": "1980-01-01",
    "iso:country": "GB",
    "wof:name": "DN3 2JJ",
    "wof:placetype": "postalcode"
  },
  "geometry": {"coordinates":[-1.063999,53.549812],"type":"Point"}
}
