{
  "type": "Feature",
  "properties": {
    "iso:country":"GB",
    "wof:name":"TR7 2SW",
    "wof:placetype":"postalcode"
},
  "geometry": {"coordinates":[-5.06330591101356,50.40787225545229],"type":"Point"}
}