{
  "type": "Feature",
  "properties": {
    "iso:country":"GB",
    "wof:name":"S43 3LL",
    "wof:placetype":"postalcode"
},
  "geometry": {"coordinates":[-1.35806106120729,53.25887185894406],"type":"Point"}
}