{
  "type": "Feature",
  "properties": {
    "date:inception_lower": "1980-01-01",
    "date:inception_upper": "1980-01-01",
    "iso:country": "GB",
    "wof:name": "GL20 7JA",
    "wof:placetype": "postalcode"
  },
  "geometry": {"coordinates":[-2.081809,52.03291],"type":"Point"}
}
