{
  "type": "Feature",
  "properties": {
    "iso:country":"GB",
    "wof:name":"NE25 8EG",
    "wof:placetype":"postalcode"
},
  "geometry": {"coordinates":[-1.46717492101701,55.04241273030651],"type":"Point"}
}