{
  "type": "Feature",
  "properties": {
    "iso:country":"GB",
    "wof:name":"GU7 1TP",
    "wof:placetype":"postalcode"
},
  "geometry": {"coordinates":[-0.60658490323939,51.17567530064441],"type":"Point"}
}