{
  "type": "Feature",
  "properties": {
    "iso:country":"GB",
    "wof:name":"IP33 3DE",
    "wof:placetype":"postalcode"
},
  "geometry": {"coordinates":[0.70975875535202,52.24459857485159],"type":"Point"}
}