{
  "type": "Feature",
  "properties": {
    "iso:country": "GB",
    "wof:name": "GU11 1BL",
    "wof:placetype": "postalcode"
  },
  "geometry": {"coordinates":[-0.761517,51.249276],"type":"Point"}
}
