{
  "type": "Feature",
  "properties": {
    "iso:country":"GB",
    "wof:name":"DA14 6JW",
    "wof:placetype":"postalcode"
},
  "geometry": {"coordinates":[0.11500050221941,51.41980864573632],"type":"Point"}
}