{
  "type": "Feature",
  "properties": {
    "iso:country":"GB",
    "wof:name":"BA9 8HF",
    "wof:placetype":"postalcode"
},
  "geometry": {"coordinates":[-2.39660688719252,51.08194752094239],"type":"Point"}
}