{
  "type": "Feature",
  "properties": {
    "date:inception_lower": "1980-01-01",
    "date:inception_upper": "1980-01-01",
    "iso:country": "GB",
    "wof:name": "BA9 8HF",
    "wof:placetype": "postalcode"
  },
  "geometry": {"coordinates":[-2.396607,51.081948],"type":"Point"}
}
