{
  "type": "Feature",
  "properties": {
    "date:inception_lower": "1980-01-01",
    "date:inception_upper": "1980-01-01",
    "iso:country": "GB",
    "wof:name": "SY25 6AQ",
    "wof:placetype": "postalcode"
  },
  "geometry": {"coordinates":[-3.931819,52.310007],"type":"Point"}
}
