{
  "type": "Feature",
  "properties": {
    "date:inception_lower": "1980-01-01",
    "date:inception_upper": "1980-01-01",
    "iso:country": "GB",
    "wof:name": "L34 2RQ",
    "wof:placetype": "postalcode"
  },
  "geometry": {"coordinates":[-2.78847,53.430765],"type":"Point"}
}
