{
  "type": "Feature",
  "properties": {
    "iso:country":"GB",
    "wof:name":"PO22 8PA",
    "wof:placetype":"postalcode"
},
  "geometry": {"coordinates":[-0.67043023651714,50.7931468217231],"type":"Point"}
}