{
  "type": "Feature",
  "properties": {
    "iso:country":"GB",
    "wof:name":"BD2 2EF",
    "wof:placetype":"postalcode"
},
  "geometry": {"coordinates":[-1.72335561580094,53.8203348324258],"type":"Point"}
}