{
  "type": "Feature",
  "properties": {
    "iso:country": "GB",
    "wof:name": "BS15 4SA",
    "wof:placetype": "postalcode"
  },
  "geometry": {"coordinates":[-2.496289,51.472264],"type":"Point"}
}
