{
  "type": "Feature",
  "properties": {
    "iso:country":"GB",
    "wof:name":"TA6 3DD",
    "wof:placetype":"postalcode"
},
  "geometry": {"coordinates":[-3.00232919079624,51.12942558696566],"type":"Point"}
}