{
  "type": "Feature",
  "properties": {
    "iso:country":"GB",
    "wof:name":"HD1 4NW",
    "wof:placetype":"postalcode"
},
  "geometry": {"coordinates":[-1.80106895526637,53.65277143153693],"type":"Point"}
}