{
  "type": "Feature",
  "properties": {
    "date:inception_lower": "1993-01-01",
    "date:inception_upper": "1993-01-01",
    "iso:country": "GB",
    "wof:name": "HD1 4NW",
    "wof:placetype": "postalcode"
  },
  "geometry": {"coordinates":[-1.801069,53.652771],"type":"Point"}
}
