{
  "type": "Feature",
  "properties": {
    "iso:country":"GB",
    "wof:name":"RM3 7QR",
    "wof:placetype":"postalcode"
},
  "geometry": {"coordinates":[0.21245036978159,51.60755367028192],"type":"Point"}
}