{
  "type": "Feature",
  "properties": {
    "iso:country":"GB",
    "wof:name":"G72 9UR",
    "wof:placetype":"postalcode"
},
  "geometry": {"coordinates":[-4.12318694833258,55.78473282051999],"type":"Point"}
}