{
  "type": "Feature",
  "properties": {
    "date:inception_lower":"2006-10-01",
    "date:inception_upper":"2006-10-31",
    "iso:country":"GB",
    "wof:name":"G72 9UR",
    "wof:placetype":"postalcode"
},
  "geometry": {"coordinates":[-4.123187,55.784733],"type":"Point"}
}