{
  "type": "Feature",
  "properties": {
    "iso:country": "GB",
    "wof:name": "G72 9UR",
    "wof:placetype": "postalcode"
  },
  "geometry": {"coordinates":[-4.123187,55.784733],"type":"Point"}
}
