{
  "type": "Feature",
  "properties": {
    "iso:country":"GB",
    "wof:name":"SN3 1EQ",
    "wof:placetype":"postalcode"
},
  "geometry": {"coordinates":[-1.76696829422368,51.55502330503729],"type":"Point"}
}