{
  "type": "Feature",
  "properties": {
    "date:inception_lower": "1980-01-01",
    "date:inception_upper": "1980-01-01",
    "iso:country": "GB",
    "wof:name": "M8 8BB",
    "wof:placetype": "postalcode"
  },
  "geometry": {"coordinates":[-2.238502,53.499095],"type":"Point"}
}
