{
  "type": "Feature",
  "properties": {
    "iso:country":"GB",
    "wof:name":"M8 8BB",
    "wof:placetype":"postalcode"
},
  "geometry": {"coordinates":[-2.2379481832792,53.4992238450125],"type":"Point"}
}