{
  "type": "Feature",
  "properties": {
    "iso:country": "GB",
    "wof:name": "W1K 4AE",
    "wof:placetype": "postalcode"
  },
  "geometry": {"coordinates":[-0.14978,51.511822],"type":"Point"}
}
