{
  "type": "Feature",
  "properties": {
    "iso:country":"GB",
    "wof:name":"MK10 9AB",
    "wof:placetype":"postalcode"
},
  "geometry": {"coordinates":[-0.70600301908582,52.04860028129752],"type":"Point"}
}