{
  "type": "Feature",
  "properties": {
    "date:inception_lower": "1997-06-01",
    "date:inception_upper": "1997-06-01",
    "iso:country": "GB",
    "wof:name": "MK10 9AB",
    "wof:placetype": "postalcode"
  },
  "geometry": {"coordinates":[-0.706003,52.0486],"type":"Point"}
}
