{
  "type": "Feature",
  "properties": {
    "iso:country":"GB",
    "wof:name":"SS9 4LD",
    "wof:placetype":"postalcode"
},
  "geometry": {"coordinates":[0.65365936864285,51.5617296468987],"type":"Point"}
}