{
  "type": "Feature",
  "properties": {
    "iso:country": "GB",
    "wof:name": "SW1W 8UN",
    "wof:placetype": "postalcode"
  },
  "geometry": {"coordinates":[-0.153174,51.490967],"type":"Point"}
}
