{
  "type": "Feature",
  "properties": {
    "iso:country":"GB",
    "wof:name":"SW1W 8UN",
    "wof:placetype":"postalcode"
},
  "geometry": {"coordinates":[-0.15317424524255,51.49096747931561],"type":"Point"}
}