{
  "type": "Feature",
  "properties": {
    "iso:country":"GB",
    "wof:name":"MK41 0AY",
    "wof:placetype":"postalcode"
},
  "geometry": {"coordinates":[-0.42122954644637,52.1506340706762],"type":"Point"}
}