{
  "type": "Feature",
  "properties": {
    "iso:country":"GB",
    "wof:name":"DY14 8QQ",
    "wof:placetype":"postalcode"
},
  "geometry": {"coordinates":[-2.476226847259,52.37940127617117],"type":"Point"}
}