{
  "type": "Feature",
  "properties": {
    "iso:country":"GB",
    "wof:name":"L11 3EQ",
    "wof:placetype":"postalcode"
},
  "geometry": {"coordinates":[-2.92133339052673,53.45198930318329],"type":"Point"}
}