{
  "type": "Feature",
  "properties": {
    "date:inception_lower":"2000-10-01",
    "date:inception_upper":"2000-10-31",
    "iso:country":"GB",
    "wof:name":"W1W 6SP",
    "wof:placetype":"postalcode"
},
  "geometry": {"coordinates":[-0.141072,51.520038],"type":"Point"}
}