{
  "type": "Feature",
  "properties": {
    "iso:country":"GB",
    "wof:name":"BD10 8UT",
    "wof:placetype":"postalcode"
},
  "geometry": {"coordinates":[-1.74192074649783,53.82973261491202],"type":"Point"}
}