{
  "type": "Feature",
  "properties": {
    "iso:country":"GB",
    "wof:name":"MK11 1EB",
    "wof:placetype":"postalcode"
},
  "geometry": {"coordinates":[-0.84885495856449,52.05768854464598],"type":"Point"}
}