{
  "type": "Feature",
  "properties": {
    "iso:country": "GB",
    "wof:name": "MK11 1EB",
    "wof:placetype": "postalcode"
  },
  "geometry": {"coordinates":[-0.848855,52.057689],"type":"Point"}
}
