{
  "type": "Feature",
  "properties": {
    "iso:country":"GB",
    "wof:name":"UB2 4LX",
    "wof:placetype":"postalcode"
},
  "geometry": {"coordinates":[-0.36452617313061,51.49647034384861],"type":"Point"}
}