{
  "type": "Feature",
  "properties": {
    "date:inception_lower":"1980-01-01",
    "date:inception_upper":"1980-01-31",
    "iso:country":"GB",
    "wof:name":"LL53 8SG",
    "wof:placetype":"postalcode"
},
  "geometry": {"coordinates":[-4.576652,52.87455],"type":"Point"}
}