{
  "type": "Feature",
  "properties": {
    "iso:country": "GB",
    "wof:name": "LL53 8SG",
    "wof:placetype": "postalcode"
  },
  "geometry": {"coordinates":[-4.576652,52.87455],"type":"Point"}
}
