{
  "type": "Feature",
  "properties": {
    "iso:country": "GB",
    "wof:name": "IG2 7NE",
    "wof:placetype": "postalcode"
  },
  "geometry": {"coordinates":[0.084754,51.578957],"type":"Point"}
}
