{
  "type": "Feature",
  "properties": {
    "iso:country":"GB",
    "wof:name":"IG2 7NE",
    "wof:placetype":"postalcode"
},
  "geometry": {"coordinates":[0.08466898224083,51.57898511299553],"type":"Point"}
}