{
  "type": "Feature",
  "properties": {
    "date:inception_lower":"1980-01-01",
    "date:inception_upper":"1980-01-31",
    "iso:country":"GB",
    "wof:name":"CA2 7NA",
    "wof:placetype":"postalcode"
},
  "geometry": {"coordinates":[-2.973943,54.898146],"type":"Point"}
}