{
  "type": "Feature",
  "properties": {
    "iso:country": "GB",
    "wof:name": "CA2 7NA",
    "wof:placetype": "postalcode"
  },
  "geometry": {"coordinates":[-2.973943,54.898146],"type":"Point"}
}
