{
  "type": "Feature",
  "properties": {
    "iso:country": "GB",
    "wof:name": "MK45 2UN",
    "wof:placetype": "postalcode"
  },
  "geometry": {"coordinates":[-0.506312,52.024308],"type":"Point"}
}
