{
  "type": "Feature",
  "properties": {
    "iso:country":"GB",
    "wof:name":"MK45 2UN",
    "wof:placetype":"postalcode"
},
  "geometry": {"coordinates":[-0.50631194666661,52.02430846589984],"type":"Point"}
}