{
  "type": "Feature",
  "properties": {
    "date:inception_lower": "1988-03-01",
    "date:inception_upper": "1988-03-01",
    "iso:country": "GB",
    "wof:name": "NE17 7LH",
    "wof:placetype": "postalcode"
  },
  "geometry": {"coordinates":[-1.813269,54.906584],"type":"Point"}
}
