{
  "type": "Feature",
  "properties": {
    "iso:country": "GB",
    "wof:name": "NE17 7LH",
    "wof:placetype": "postalcode"
  },
  "geometry": {"coordinates":[-1.813269,54.906584],"type":"Point"}
}
