{
  "type": "Feature",
  "properties": {
    "date:inception_lower": "1995-07-01",
    "date:inception_upper": "1995-07-01",
    "iso:country": "GB",
    "wof:name": "BN27 3XL",
    "wof:placetype": "postalcode"
  },
  "geometry": {"coordinates":[0.249046,50.87296],"type":"Point"}
}
