{
  "type": "Feature",
  "properties": {
    "iso:country":"GB",
    "wof:name":"BB1 8HZ",
    "wof:placetype":"postalcode"
},
  "geometry": {"coordinates":[-2.48483499300229,53.75672897231026],"type":"Point"}
}