{
  "type": "Feature",
  "properties": {
    "date:inception_lower": "1980-01-01",
    "date:inception_upper": "1980-01-01",
    "iso:country": "GB",
    "wof:name": "TN4 0QE",
    "wof:placetype": "postalcode"
  },
  "geometry": {"coordinates":[0.255487,51.160907],"type":"Point"}
}
