{
  "type": "Feature",
  "properties": {
    "iso:country":"GB",
    "wof:name":"TN4 0QE",
    "wof:placetype":"postalcode"
},
  "geometry": {"coordinates":[0.25548648327479,51.16090665399094],"type":"Point"}
}