{
  "type": "Feature",
  "properties": {
    "date:inception_lower": "2019-12-01",
    "date:inception_upper": "2019-12-01",
    "iso:country": "GB",
    "wof:name": "MK17 9WA",
    "wof:placetype": "postalcode"
  },
  "geometry": {"coordinates":[-0.689958,52.030568],"type":"Point"}
}
