{
  "type": "Feature",
  "properties": {
    "date:inception_lower":"1999-06-01",
    "date:inception_upper":"1999-06-30",
    "iso:country":"GB",
    "wof:name":"CH61 8RJ",
    "wof:placetype":"postalcode"
},
  "geometry": {"coordinates":[-3.096397,53.348063],"type":"Point"}
}