{
  "type": "Feature",
  "properties": {
    "iso:country": "GB",
    "wof:name": "CH61 8RJ",
    "wof:placetype": "postalcode"
  },
  "geometry": {"coordinates":[-3.096397,53.348063],"type":"Point"}
}
