{
  "type": "Feature",
  "properties": {
    "iso:country":"GB",
    "wof:name":"DN21 5AA",
    "wof:placetype":"postalcode"
},
  "geometry": {"coordinates":[-0.74101614254396,53.32958131673499],"type":"Point"}
}