{
  "type": "Feature",
  "properties": {
    "iso:country": "GB",
    "wof:name": "DL6 1LL",
    "wof:placetype": "postalcode"
  },
  "geometry": {"coordinates":[-1.431854,54.343275],"type":"Point"}
}
