{
  "type": "Feature",
  "properties": {
    "iso:country":"GB",
    "wof:name":"DL6 1LL",
    "wof:placetype":"postalcode"
},
  "geometry": {"coordinates":[-1.43182885421599,54.3432449200884],"type":"Point"}
}