{
  "type": "Feature",
  "properties": {
    "iso:country":"GB",
    "wof:name":"GL1 2DF",
    "wof:placetype":"postalcode"
},
  "geometry": {"coordinates":[-2.24297945631549,51.86905412981325],"type":"Point"}
}