{
  "type": "Feature",
  "properties": {
    "date:inception_lower":"1980-01-01",
    "date:inception_upper":"1980-01-31",
    "iso:country":"GB",
    "wof:name":"GL1 2DF",
    "wof:placetype":"postalcode"
},
  "geometry": {"coordinates":[-2.242979,51.869054],"type":"Point"}
}