{
  "type": "Feature",
  "properties": {
    "iso:country": "GB",
    "wof:name": "GL1 2DF",
    "wof:placetype": "postalcode"
  },
  "geometry": {"coordinates":[-2.242979,51.869054],"type":"Point"}
}
