{
  "type": "Feature",
  "properties": {
    "iso:country":"GB",
    "wof:name":"CM11 1BY",
    "wof:placetype":"postalcode"
},
  "geometry": {"coordinates":[0.43228997413776,51.63627079293094],"type":"Point"}
}