{
  "type": "Feature",
  "properties": {
    "date:inception_lower":"1980-01-01",
    "date:inception_upper":"1980-01-31",
    "iso:country":"GB",
    "wof:name":"EH4 4RF",
    "wof:placetype":"postalcode"
},
  "geometry": {"coordinates":[-3.259268,55.968093],"type":"Point"}
}