{
  "type": "Feature",
  "properties": {
    "iso:country":"GB",
    "wof:name":"EH4 4RF",
    "wof:placetype":"postalcode"
},
  "geometry": {"coordinates":[-3.25926809707324,55.96809332996786],"type":"Point"}
}