{
  "type": "Feature",
  "properties": {
    "iso:country": "GB",
    "wof:name": "GL11 6LJ",
    "wof:placetype": "postalcode"
  },
  "geometry": {"coordinates":[-2.377951,51.697616],"type":"Point"}
}
