{
  "type": "Feature",
  "properties": {
    "iso:country": "GB",
    "wof:name": "IV12 5ST",
    "wof:placetype": "postalcode"
  },
  "geometry": {"coordinates":[-3.836383,57.5897],"type":"Point"}
}
