{
  "type": "Feature",
  "properties": {
    "iso:country": "GB",
    "wof:name": "TQ7 4DJ",
    "wof:placetype": "postalcode"
  },
  "geometry": {"coordinates":[-3.759457,50.342619],"type":"Point"}
}
