{
  "type": "Feature",
  "properties": {
    "iso:country":"GB",
    "wof:name":"TQ7 4DJ",
    "wof:placetype":"postalcode"
},
  "geometry": {"coordinates":[-3.75976552256773,50.34282831752739],"type":"Point"}
}