{
  "type": "Feature",
  "properties": {
    "iso:country":"GB",
    "wof:name":"CO9 3JB",
    "wof:placetype":"postalcode"
},
  "geometry": {"coordinates":[0.59189379468876,51.97537697971067],"type":"Point"}
}