{
  "type": "Feature",
  "properties": {
    "iso:country": "GB",
    "wof:name": "CO9 3JB",
    "wof:placetype": "postalcode"
  },
  "geometry": {"coordinates":[0.591894,51.975377],"type":"Point"}
}
