{
  "type": "Feature",
  "properties": {
    "iso:country":"GB",
    "wof:name":"HD1 3NP",
    "wof:placetype":"postalcode"
},
  "geometry": {"coordinates":[-1.79352891274339,53.63839553665176],"type":"Point"}
}