{
  "type": "Feature",
  "properties": {
    "date:inception_lower": "2009-08-01",
    "date:inception_upper": "2009-08-01",
    "iso:country": "GB",
    "wof:name": "HD1 3NP",
    "wof:placetype": "postalcode"
  },
  "geometry": {"coordinates":[-1.793529,53.638396],"type":"Point"}
}
