{
  "type": "Feature",
  "properties": {
    "iso:country": "GB",
    "wof:name": "HD1 3NP",
    "wof:placetype": "postalcode"
  },
  "geometry": {"coordinates":[-1.793529,53.638396],"type":"Point"}
}
