{
  "type": "Feature",
  "properties": {
    "iso:country":"GB",
    "wof:name":"W2 4TH",
    "wof:placetype":"postalcode"
},
  "geometry": {"coordinates":[-0.19660513226706,51.51213722659107],"type":"Point"}
}