{
  "type": "Feature",
  "properties": {
    "iso:country": "GB",
    "wof:name": "W2 4TH",
    "wof:placetype": "postalcode"
  },
  "geometry": {"coordinates":[-0.196402,51.51217],"type":"Point"}
}
