{
  "type": "Feature",
  "properties": {
    "date:inception_lower": "2024-02-01",
    "date:inception_upper": "2024-02-01",
    "iso:country": "GB",
    "wof:name": "CF10 4EF",
    "wof:placetype": "postalcode"
  },
  "geometry": {"coordinates":[-3.17089,51.476711],"type":"Point"}
}
