{
  "type": "Feature",
  "properties": {
    "iso:country":"GB",
    "wof:name":"NG5 9HS",
    "wof:placetype":"postalcode"
},
  "geometry": {"coordinates":[-1.16946687103147,53.00600935356385],"type":"Point"}
}