{
  "type": "Feature",
  "properties": {
    "iso:country": "GB",
    "wof:name": "NG5 9HS",
    "wof:placetype": "postalcode"
  },
  "geometry": {"coordinates":[-1.169467,53.006009],"type":"Point"}
}
