{
  "type": "Feature",
  "properties": {
    "date:inception_lower":"1980-01-01",
    "date:inception_upper":"1980-01-31",
    "iso:country":"GB",
    "wof:name":"NG5 9HS",
    "wof:placetype":"postalcode"
},
  "geometry": {"coordinates":[-1.169467,53.006009],"type":"Point"}
}