{
  "type": "Feature",
  "properties": {
    "iso:country": "GB",
    "wof:name": "BA4 4JS",
    "wof:placetype": "postalcode"
  },
  "geometry": {"coordinates":[-2.537773,51.201557],"type":"Point"}
}
