{
  "type": "Feature",
  "properties": {
    "iso:country": "GB",
    "wof:name": "ME17 1LJ",
    "wof:placetype": "postalcode"
  },
  "geometry": {"coordinates":[0.669771,51.241258],"type":"Point"}
}
