{
  "type": "Feature",
  "properties": {
    "iso:country": "GB",
    "wof:name": "AB12 5YL",
    "wof:placetype": "postalcode"
  },
  "geometry": {"coordinates":[-2.134521,57.114771],"type":"Point"}
}
