{
  "type": "Feature",
  "properties": {
    "iso:country": "GB",
    "wof:name": "AB12 5YL",
    "wof:placetype": "postalcode"
  },
  "geometry": {"coordinates":[-2.140962,57.11306],"type":"Point"}
}
