{
  "type": "Feature",
  "properties": {
    "iso:country":"GB",
    "wof:name":"AB12 5YL",
    "wof:placetype":"postalcode"
},
  "geometry": {"coordinates":[-2.1345213102493,57.11477079836158],"type":"Point"}
}