{
  "type": "Feature",
  "properties": {
    "date:inception_lower": "2006-01-01",
    "date:inception_upper": "2006-01-01",
    "iso:country": "GB",
    "wof:name": "CO5 8FA",
    "wof:placetype": "postalcode"
  },
  "geometry": {"coordinates":[0.913373,51.775268],"type":"Point"}
}
