{
  "type": "Feature",
  "properties": {
    "iso:country":"GB",
    "wof:name":"CO5 8FA",
    "wof:placetype":"postalcode"
},
  "geometry": {"coordinates":[0.91337247510883,51.77526798951398],"type":"Point"}
}