{
  "type": "Feature",
  "properties": {
    "iso:country":"GB",
    "wof:name":"GU8 6EL",
    "wof:placetype":"postalcode"
},
  "geometry": {"coordinates":[-0.69758458352,51.18223605305403],"type":"Point"}
}