{
  "type": "Feature",
  "properties": {
    "date:inception_lower": "1980-01-01",
    "date:inception_upper": "1980-01-01",
    "iso:country": "GB",
    "wof:name": "GU8 6EL",
    "wof:placetype": "postalcode"
  },
  "geometry": {"coordinates":[-0.697585,51.182236],"type":"Point"}
}
