{
  "type": "Feature",
  "properties": {
    "iso:country":"GB",
    "wof:name":"SG18 8DG",
    "wof:placetype":"postalcode"
},
  "geometry": {"coordinates":[-0.24187518225609,52.07656901203097],"type":"Point"}
}