{
  "type": "Feature",
  "properties": {
    "date:inception_lower": "2009-09-01",
    "date:inception_upper": "2009-09-01",
    "iso:country": "GB",
    "wof:name": "SG18 8DG",
    "wof:placetype": "postalcode"
  },
  "geometry": {"coordinates":[-0.241875,52.076569],"type":"Point"}
}
