{
  "type": "Feature",
  "properties": {
    "iso:country": "GB",
    "wof:name": "SG18 8DG",
    "wof:placetype": "postalcode"
  },
  "geometry": {"coordinates":[-0.241875,52.076569],"type":"Point"}
}
