{
  "type": "Feature",
  "properties": {
    "iso:country":"GB",
    "wof:name":"NP18 1GS",
    "wof:placetype":"postalcode"
},
  "geometry": {"coordinates":[-2.97697035462395,51.6304281798309],"type":"Point"}
}