{
  "type": "Feature",
  "properties": {
    "date:inception_lower": "1999-06-01",
    "date:inception_upper": "1999-06-01",
    "iso:country": "GB",
    "wof:name": "NP18 1GS",
    "wof:placetype": "postalcode"
  },
  "geometry": {"coordinates":[-2.97697,51.630428],"type":"Point"}
}
