{
  "type": "Feature",
  "properties": {
    "iso:country": "GB",
    "wof:name": "NP18 1GS",
    "wof:placetype": "postalcode"
  },
  "geometry": {"coordinates":[-2.97697,51.630428],"type":"Point"}
}
