{
  "type": "Feature",
  "properties": {
    "date:inception_lower": "2002-12-01",
    "date:inception_upper": "2002-12-01",
    "iso:country": "GB",
    "wof:name": "NE31 1AT",
    "wof:placetype": "postalcode"
  },
  "geometry": {"coordinates":[-1.507586,54.984243],"type":"Point"}
}
