{
  "type": "Feature",
  "properties": {
    "iso:country":"GB",
    "wof:name":"SR6 9RJ",
    "wof:placetype":"postalcode"
},
  "geometry": {"coordinates":[-1.38229405195063,54.92536890916917],"type":"Point"}
}