{
  "type": "Feature",
  "properties": {
    "iso:country":"GB",
    "wof:name":"UB8 9UG",
    "wof:placetype":"postalcode"
},
  "geometry": {"coordinates":[-0.52718992725648,51.57366460611152],"type":"Point"}
}