{
  "type": "Feature",
  "properties": {
    "iso:country": "GB",
    "wof:name": "EX11 1UE",
    "wof:placetype": "postalcode"
  },
  "geometry": {"coordinates":[-3.310911,50.736462],"type":"Point"}
}
