{
  "type": "Feature",
  "properties": {
    "iso:country":"GB",
    "wof:name":"EX11 1UE",
    "wof:placetype":"postalcode"
},
  "geometry": {"coordinates":[-3.31091115021797,50.7364618328487],"type":"Point"}
}