{
  "type": "Feature",
  "properties": {
    "date:inception_lower": "1980-01-01",
    "date:inception_upper": "1980-01-01",
    "iso:country": "GB",
    "wof:name": "BS4 3NG",
    "wof:placetype": "postalcode"
  },
  "geometry": {"coordinates":[-2.552921,51.439443],"type":"Point"}
}
