{
  "type": "Feature",
  "properties": {
    "iso:country":"GB",
    "wof:name":"BS4 3NG",
    "wof:placetype":"postalcode"
},
  "geometry": {"coordinates":[-2.55292109204733,51.43944275294244],"type":"Point"}
}