{
  "type": "Feature",
  "properties": {
    "iso:country":"GB",
    "wof:name":"PO8 0SJ",
    "wof:placetype":"postalcode"
},
  "geometry": {"coordinates":[-1.03755727877241,50.913802039982],"type":"Point"}
}