{
  "type": "Feature",
  "properties": {
    "iso:country":"GB",
    "wof:name":"W10 4RS",
    "wof:placetype":"postalcode"
},
  "geometry": {"coordinates":[-0.2078520340611,51.52777657799009],"type":"Point"}
}