{
  "type": "Feature",
  "properties": {
    "iso:country": "GB",
    "wof:name": "M35 0SY",
    "wof:placetype": "postalcode"
  },
  "geometry": {"coordinates":[-2.173035,53.506911],"type":"Point"}
}
