{
  "type": "Feature",
  "properties": {
    "date:inception_lower": "2018-12-01",
    "date:inception_upper": "2018-12-01",
    "iso:country": "GB",
    "wof:name": "M35 0SY",
    "wof:placetype": "postalcode"
  },
  "geometry": {"coordinates":[-2.173141,53.506857],"type":"Point"}
}
