{
  "type": "Feature",
  "properties": {
    "iso:country":"GB",
    "wof:name":"SA2 7JR",
    "wof:placetype":"postalcode"
},
  "geometry": {"coordinates":[-4.05405972075408,51.60263571278178],"type":"Point"}
}