{
  "type": "Feature",
  "properties": {
    "iso:country": "GB",
    "wof:name": "SA2 7JR",
    "wof:placetype": "postalcode"
  },
  "geometry": {"coordinates":[-4.05408,51.602641],"type":"Point"}
}
