{
  "type": "Feature",
  "properties": {
    "iso:country":"GB",
    "wof:name":"L9 9DQ",
    "wof:placetype":"postalcode"
},
  "geometry": {"coordinates":[-2.93993454302867,53.4678354720705],"type":"Point"}
}