{
  "type": "Feature",
  "properties": {
    "date:inception_lower":"1980-01-01",
    "date:inception_upper":"1980-01-31",
    "iso:country":"GB",
    "wof:name":"L9 9DQ",
    "wof:placetype":"postalcode"
},
  "geometry": {"coordinates":[-2.939934,53.467835],"type":"Point"}
}