{
  "type": "Feature",
  "properties": {
    "date:inception_lower": "1980-01-01",
    "date:inception_upper": "1980-01-01",
    "iso:country": "GB",
    "wof:name": "PA15 4AN",
    "wof:placetype": "postalcode"
  },
  "geometry": {"coordinates":[-4.757502,55.943522],"type":"Point"}
}
