{
  "type": "Feature",
  "properties": {
    "iso:country": "GB",
    "wof:name": "PA15 4AN",
    "wof:placetype": "postalcode"
  },
  "geometry": {"coordinates":[-4.757502,55.943522],"type":"Point"}
}
