{
  "type": "Feature",
  "properties": {
    "iso:country":"GB",
    "wof:name":"BD19 4RX",
    "wof:placetype":"postalcode"
},
  "geometry": {"coordinates":[-1.68957734459897,53.73333803876523],"type":"Point"}
}