{
  "type": "Feature",
  "properties": {
    "date:inception_lower":"1980-01-01",
    "date:inception_upper":"1980-01-31",
    "iso:country":"GB",
    "wof:name":"BD19 4RX",
    "wof:placetype":"postalcode"
},
  "geometry": {"coordinates":[-1.689577,53.733338],"type":"Point"}
}