{
  "type": "Feature",
  "properties": {
    "iso:country":"GB",
    "wof:name":"HA0 3JW",
    "wof:placetype":"postalcode"
},
  "geometry": {"coordinates":[-0.31995824447591,51.56603417297189],"type":"Point"}
}