{
  "type": "Feature",
  "properties": {
    "date:inception_lower": "1980-01-01",
    "date:inception_upper": "1980-01-01",
    "iso:country": "GB",
    "wof:name": "NW4 3XT",
    "wof:placetype": "postalcode"
  },
  "geometry": {"coordinates":[-0.229415,51.583227],"type":"Point"}
}
