{
  "type": "Feature",
  "properties": {
    "iso:country":"GB",
    "wof:name":"NW4 3XT",
    "wof:placetype":"postalcode"
},
  "geometry": {"coordinates":[-0.22941518878978,51.58322711912843],"type":"Point"}
}