{
  "type": "Feature",
  "properties": {
    "date:inception_lower": "2020-09-01",
    "date:inception_upper": "2020-09-01",
    "iso:country": "GB",
    "wof:name": "CV36 4RL",
    "wof:placetype": "postalcode"
  },
  "geometry": {"coordinates":[-1.637455,52.062413],"type":"Point"}
}
