{
  "type": "Feature",
  "properties": {
    "iso:country":"GB",
    "wof:name":"CV1 2LL",
    "wof:placetype":"postalcode"
},
  "geometry": {"coordinates":[-1.5110268515603,52.40416427834541],"type":"Point"}
}