{
  "type": "Feature",
  "properties": {
    "iso:country":"GB",
    "wof:name":"HU7 4LX",
    "wof:placetype":"postalcode"
},
  "geometry": {"coordinates":[-0.31543824057664,53.79276345388753],"type":"Point"}
}