{
  "type": "Feature",
  "properties": {
    "iso:country":"GB",
    "wof:name":"N4 4AA",
    "wof:placetype":"postalcode"
},
  "geometry": {"coordinates":[-0.11970449075828,51.57266305823286],"type":"Point"}
}