{
  "type": "Feature",
  "properties": {
    "iso:country": "GB",
    "wof:name": "DN15 9TN",
    "wof:placetype": "postalcode"
  },
  "geometry": {"coordinates":[-0.609907,53.652834],"type":"Point"}
}
