{
  "type": "Feature",
  "properties": {
    "iso:country":"GB",
    "wof:name":"TR20 8TB",
    "wof:placetype":"postalcode"
},
  "geometry": {"coordinates":[-5.5659192834501,50.11181656951197],"type":"Point"}
}