{
  "type": "Feature",
  "properties": {
    "date:inception_lower":"1980-01-01",
    "date:inception_upper":"1980-01-31",
    "iso:country":"GB",
    "wof:name":"LL15 1AT",
    "wof:placetype":"postalcode"
},
  "geometry": {"coordinates":[-3.308833,53.114946],"type":"Point"}
}