{
  "type": "Feature",
  "properties": {
    "iso:country":"GB",
    "wof:name":"LL15 1AT",
    "wof:placetype":"postalcode"
},
  "geometry": {"coordinates":[-3.30883307052726,53.11494551861067],"type":"Point"}
}