{
  "type": "Feature",
  "properties": {
    "iso:country":"GB",
    "wof:name":"LL18 4TY",
    "wof:placetype":"postalcode"
},
  "geometry": {"coordinates":[-3.46449453423368,53.30906173701676],"type":"Point"}
}