{
  "type": "Feature",
  "properties": {
    "iso:country": "GB",
    "wof:name": "CF83 4FQ",
    "wof:placetype": "postalcode"
  },
  "geometry": {"coordinates":[-3.271642,51.602654],"type":"Point"}
}
