{
  "type": "Feature",
  "properties": {
    "date:inception_lower": "2021-11-01",
    "date:inception_upper": "2021-11-01",
    "iso:country": "GB",
    "wof:name": "LU2 0GT",
    "wof:placetype": "postalcode"
  },
  "geometry": {"coordinates":[-0.396106,51.874821],"type":"Point"}
}
