{
  "type": "Feature",
  "properties": {
    "iso:country":"GB",
    "wof:name":"TW13 4SP",
    "wof:placetype":"postalcode"
},
  "geometry": {"coordinates":[-0.4246673094374,51.43934736301527],"type":"Point"}
}