{
  "type": "Feature",
  "properties": {
    "date:inception_lower": "2004-07-01",
    "date:inception_upper": "2004-07-01",
    "iso:country": "GB",
    "wof:name": "TW13 4SP",
    "wof:placetype": "postalcode"
  },
  "geometry": {"coordinates":[-0.424667,51.439347],"type":"Point"}
}
