{
  "type": "Feature",
  "properties": {
    "iso:country": "GB",
    "wof:name": "L37 8BQ",
    "wof:placetype": "postalcode"
  },
  "geometry": {"coordinates":[-3.05661,53.557018],"type":"Point"}
}
