{
  "type": "Feature",
  "properties": {
    "iso:country":"GB",
    "wof:name":"L37 8BQ",
    "wof:placetype":"postalcode"
},
  "geometry": {"coordinates":[-3.0566105350815,53.55701844570888],"type":"Point"}
}