{
  "type": "Feature",
  "properties": {
    "date:inception_lower":"1980-01-01",
    "date:inception_upper":"1980-01-31",
    "iso:country":"GB",
    "wof:name":"L37 8BQ",
    "wof:placetype":"postalcode"
},
  "geometry": {"coordinates":[-3.05661,53.557018],"type":"Point"}
}