{
  "type": "Feature",
  "properties": {
    "iso:country":"GB",
    "wof:name":"HX1 4AZ",
    "wof:placetype":"postalcode"
},
  "geometry": {"coordinates":[-1.87939767807157,53.72610202284032],"type":"Point"}
}