{
  "type": "Feature",
  "properties": {
    "iso:country":"GB",
    "wof:name":"ME15 9ER",
    "wof:placetype":"postalcode"
},
  "geometry": {"coordinates":[0.55420481589304,51.24267761390465],"type":"Point"}
}