{
  "type": "Feature",
  "properties": {
    "date:inception_lower": "1992-08-01",
    "date:inception_upper": "1992-08-01",
    "iso:country": "GB",
    "wof:name": "TS9 5QB",
    "wof:placetype": "postalcode"
  },
  "geometry": {"coordinates":[-1.191264,54.474841],"type":"Point"}
}
