{
  "type": "Feature",
  "properties": {
    "iso:country": "GB",
    "wof:name": "TS9 5QB",
    "wof:placetype": "postalcode"
  },
  "geometry": {"coordinates":[-1.191264,54.474841],"type":"Point"}
}
