{
  "type": "Feature",
  "properties": {
    "date:inception_lower":"1980-01-01",
    "date:inception_upper":"1980-01-31",
    "iso:country":"GB",
    "wof:name":"NE61 4NN",
    "wof:placetype":"postalcode"
},
  "geometry": {"coordinates":[-1.818209,55.198118],"type":"Point"}
}