{
  "type": "Feature",
  "properties": {
    "iso:country":"GB",
    "wof:name":"NE61 4NN",
    "wof:placetype":"postalcode"
},
  "geometry": {"coordinates":[-1.81820925357739,55.19811810588609],"type":"Point"}
}