{
  "type": "Feature",
  "properties": {
    "iso:country":"GB",
    "wof:name":"DL14 6PF",
    "wof:placetype":"postalcode"
},
  "geometry": {"coordinates":[-1.6835725314073,54.64940868569313],"type":"Point"}
}