{
  "type": "Feature",
  "properties": {
    "date:inception_lower":"2008-07-01",
    "date:inception_upper":"2008-07-31",
    "iso:country":"GB",
    "wof:name":"SE23 9AB",
    "wof:placetype":"postalcode"
},
  "geometry": {"coordinates":[-0.053321,51.437114],"type":"Point"}
}