{
  "type": "Feature",
  "properties": {
    "date:inception_lower": "1982-03-01",
    "date:inception_upper": "1982-03-01",
    "iso:country": "GB",
    "wof:name": "ML1 5EX",
    "wof:placetype": "postalcode"
  },
  "geometry": {"coordinates":[-3.958986,55.811545],"type":"Point"}
}
