{
  "type": "Feature",
  "properties": {
    "iso:country":"GB",
    "wof:name":"BL0 9UN",
    "wof:placetype":"postalcode"
},
  "geometry": {"coordinates":[-2.32386724793182,53.6265664793739],"type":"Point"}
}