{
  "type": "Feature",
  "properties": {
    "date:inception_lower":"1980-01-01",
    "date:inception_upper":"1980-01-31",
    "iso:country":"GB",
    "wof:name":"RG10 0EG",
    "wof:placetype":"postalcode"
},
  "geometry": {"coordinates":[-0.859953,51.459315],"type":"Point"}
}