{
  "type": "Feature",
  "properties": {
    "iso:country":"GB",
    "wof:name":"B32 2RW",
    "wof:placetype":"postalcode"
},
  "geometry": {"coordinates":[-1.97836933454907,52.4523880552864],"type":"Point"}
}