{
  "type": "Feature",
  "properties": {
    "iso:country":"GB",
    "wof:name":"DN9 1JB",
    "wof:placetype":"postalcode"
},
  "geometry": {"coordinates":[-0.82824532826375,53.53039526406808],"type":"Point"}
}