{
  "type": "Feature",
  "properties": {
    "date:inception_lower":"1980-01-01",
    "date:inception_upper":"1980-01-31",
    "iso:country":"GB",
    "wof:name":"LA16 7AJ",
    "wof:placetype":"postalcode"
},
  "geometry": {"coordinates":[-3.205752,54.188916],"type":"Point"}
}