{
  "type": "Feature",
  "properties": {
    "iso:country": "GB",
    "wof:name": "LA16 7AJ",
    "wof:placetype": "postalcode"
  },
  "geometry": {"coordinates":[-3.205752,54.188916],"type":"Point"}
}
