{
  "type": "Feature",
  "properties": {
    "iso:country":"GB",
    "wof:name":"LA16 7AJ",
    "wof:placetype":"postalcode"
},
  "geometry": {"coordinates":[-3.20575217698104,54.18891565275945],"type":"Point"}
}