{
  "type": "Feature",
  "properties": {
    "iso:country":"GB",
    "wof:name":"PO36 0PR",
    "wof:placetype":"postalcode"
},
  "geometry": {"coordinates":[-1.20262706992093,50.65234957780527],"type":"Point"}
}