{
  "type": "Feature",
  "properties": {
    "date:inception_lower": "1990-02-01",
    "date:inception_upper": "1990-02-01",
    "iso:country": "GB",
    "wof:name": "PO36 0PR",
    "wof:placetype": "postalcode"
  },
  "geometry": {"coordinates":[-1.202627,50.65235],"type":"Point"}
}
