{
  "type": "Feature",
  "properties": {
    "iso:country":"GB",
    "wof:name":"BA2 4HQ",
    "wof:placetype":"postalcode"
},
  "geometry": {"coordinates":[-2.34991688931333,51.37909968258317],"type":"Point"}
}