{
  "type": "Feature",
  "properties": {
    "iso:country":"GB",
    "wof:name":"TA3 5EL",
    "wof:placetype":"postalcode"
},
  "geometry": {"coordinates":[-3.03095340917739,51.03693249763106],"type":"Point"}
}