{
  "type": "Feature",
  "properties": {
    "date:inception_lower": "1980-01-01",
    "date:inception_upper": "1980-01-01",
    "iso:country": "GB",
    "wof:name": "EH4 2JR",
    "wof:placetype": "postalcode"
  },
  "geometry": {"coordinates":[-3.237561,55.959642],"type":"Point"}
}
