{
  "type": "Feature",
  "properties": {
    "date:inception_lower": "2023-11-01",
    "date:inception_upper": "2023-11-01",
    "iso:country": "GB",
    "wof:name": "WD3 6DP",
    "wof:placetype": "postalcode"
  },
  "geometry": {"coordinates":[-0.51785,51.668003],"type":"Point"}
}
