{
  "type": "Feature",
  "properties": {
    "date:inception_lower": "1980-01-01",
    "date:inception_upper": "1980-01-01",
    "iso:country": "GB",
    "wof:name": "DT5 2HW",
    "wof:placetype": "postalcode"
  },
  "geometry": {"coordinates":[-2.447633,50.540929],"type":"Point"}
}
