{
  "type": "Feature",
  "properties": {
    "iso:country":"GB",
    "wof:name":"FY3 7AT",
    "wof:placetype":"postalcode"
},
  "geometry": {"coordinates":[-3.03892792277514,53.82553573836338],"type":"Point"}
}