{
  "type": "Feature",
  "properties": {
    "iso:country": "GB",
    "wof:name": "LE17 4GG",
    "wof:placetype": "postalcode"
  },
  "geometry": {"coordinates":[-1.201402,52.468863],"type":"Point"}
}
