{
  "type": "Feature",
  "properties": {
    "date:inception_lower":"1983-03-01",
    "date:inception_upper":"1983-03-31",
    "iso:country":"GB",
    "wof:name":"BH5 1NF",
    "wof:placetype":"postalcode"
},
  "geometry": {"coordinates":[-1.82784,50.726414],"type":"Point"}
}