{
  "type": "Feature",
  "properties": {
    "iso:country":"GB",
    "wof:name":"BH5 1NF",
    "wof:placetype":"postalcode"
},
  "geometry": {"coordinates":[-1.82783961732409,50.72641397616812],"type":"Point"}
}