{
  "type": "Feature",
  "properties": {
    "iso:country": "GB",
    "wof:name": "PE16 6JH",
    "wof:placetype": "postalcode"
  },
  "geometry": {"coordinates":[0.056841,52.454881],"type":"Point"}
}
