{
  "type": "Feature",
  "properties": {
    "iso:country": "GB",
    "wof:name": "CF47 9HS",
    "wof:placetype": "postalcode"
  },
  "geometry": {"coordinates":[-3.367154,51.756589],"type":"Point"}
}
