{
  "type": "Feature",
  "properties": {
    "date:inception_lower": "1980-01-01",
    "date:inception_upper": "1980-01-01",
    "iso:country": "GB",
    "wof:name": "NE70 7QA",
    "wof:placetype": "postalcode"
  },
  "geometry": {"coordinates":[-1.830458,55.598192],"type":"Point"}
}
