{
  "type": "Feature",
  "properties": {
    "iso:country":"GB",
    "wof:name":"NE70 7QA",
    "wof:placetype":"postalcode"
},
  "geometry": {"coordinates":[-1.83045849143997,55.59819161124595],"type":"Point"}
}