{
  "type": "Feature",
  "properties": {
    "iso:country": "GB",
    "wof:name": "SA2 0JL",
    "wof:placetype": "postalcode"
  },
  "geometry": {"coordinates":[-3.974245,51.61691],"type":"Point"}
}
