{
  "type": "Feature",
  "properties": {
    "iso:country":"GB",
    "wof:name":"SA2 0JL",
    "wof:placetype":"postalcode"
},
  "geometry": {"coordinates":[-3.9742447486033,51.61691004137567],"type":"Point"}
}