{
  "type": "Feature",
  "properties": {
    "iso:country":"GB",
    "wof:name":"HU8 9RH",
    "wof:placetype":"postalcode"
},
  "geometry": {"coordinates":[-0.26408630409621,53.77932028588584],"type":"Point"}
}