{
  "type": "Feature",
  "properties": {
    "iso:country":"GB",
    "wof:name":"ME10 4RE",
    "wof:placetype":"postalcode"
},
  "geometry": {"coordinates":[0.73144299069933,51.3280381655477],"type":"Point"}
}