{
  "type": "Feature",
  "properties": {
    "date:inception_lower":"1980-01-01",
    "date:inception_upper":"1980-01-31",
    "iso:country":"GB",
    "wof:name":"CM23 2NR",
    "wof:placetype":"postalcode"
},
  "geometry": {"coordinates":[0.153084,51.870926],"type":"Point"}
}