{
  "type": "Feature",
  "properties": {
    "date:inception_lower": "1991-09-01",
    "date:inception_upper": "1991-09-01",
    "iso:country": "GB",
    "wof:name": "IP7 7RP",
    "wof:placetype": "postalcode"
  },
  "geometry": {"coordinates":[0.96502,52.12112],"type":"Point"}
}
