{
  "type": "Feature",
  "properties": {
    "iso:country": "GB",
    "wof:name": "W3 0BT",
    "wof:placetype": "postalcode"
  },
  "geometry": {"coordinates":[-0.270308,51.522115],"type":"Point"}
}
