{
  "type": "Feature",
  "properties": {
    "iso:country": "GB",
    "wof:name": "W3 0BT",
    "wof:placetype": "postalcode"
  },
  "geometry": {"coordinates":[-0.265282,51.522752],"type":"Point"}
}
