{
  "type": "Feature",
  "properties": {
    "date:inception_lower": "2018-06-01",
    "date:inception_upper": "2018-06-01",
    "iso:country": "GB",
    "wof:name": "W3 0BT",
    "wof:placetype": "postalcode"
  },
  "geometry": {"coordinates":[-0.265282,51.522752],"type":"Point"}
}
