{
  "type": "Feature",
  "properties": {
    "iso:country":"GB",
    "wof:name":"SW6 2HP",
    "wof:placetype":"postalcode"
},
  "geometry": {"coordinates":[-0.1909635578243,51.4791918486105],"type":"Point"}
}