{
  "type": "Feature",
  "properties": {
    "date:inception_lower": "1998-06-01",
    "date:inception_upper": "1998-06-01",
    "iso:country": "GB",
    "wof:name": "SK9 1EJ",
    "wof:placetype": "postalcode"
  },
  "geometry": {"coordinates":[-2.230804,53.32751],"type":"Point"}
}
