{
  "type": "Feature",
  "properties": {
    "iso:country":"GB",
    "wof:name":"SK9 1EJ",
    "wof:placetype":"postalcode"
},
  "geometry": {"coordinates":[-2.2309396616304,53.32746626623692],"type":"Point"}
}