{
  "type": "Feature",
  "properties": {
    "iso:country": "GB",
    "wof:name": "DH9 8TF",
    "wof:placetype": "postalcode"
  },
  "geometry": {"coordinates":[-1.736653,54.864754],"type":"Point"}
}
