{
  "type": "Feature",
  "properties": {
    "date:inception_lower": "1999-12-01",
    "date:inception_upper": "1999-12-01",
    "iso:country": "GB",
    "wof:name": "PA7 5HR",
    "wof:placetype": "postalcode"
  },
  "geometry": {"coordinates":[-4.494215,55.903019],"type":"Point"}
}
