{
  "type": "Feature",
  "properties": {
    "iso:country": "GB",
    "wof:name": "LE16 9SL",
    "wof:placetype": "postalcode"
  },
  "geometry": {"coordinates":[-0.952289,52.460276],"type":"Point"}
}
