{
  "type": "Feature",
  "properties": {
    "iso:country":"GB",
    "wof:name":"WA15 7LB",
    "wof:placetype":"postalcode"
},
  "geometry": {"coordinates":[-2.31108758448597,53.39366526737965],"type":"Point"}
}