{
  "type": "Feature",
  "properties": {
    "iso:country":"GB",
    "wof:name":"WV16 6SL",
    "wof:placetype":"postalcode"
},
  "geometry": {"coordinates":[-2.58155779519906,52.495406016903],"type":"Point"}
}