{
  "type": "Feature",
  "properties": {
    "iso:country":"GB",
    "wof:name":"TN31 6NL",
    "wof:placetype":"postalcode"
},
  "geometry": {"coordinates":[0.60665818584455,50.9867468971502],"type":"Point"}
}