{
  "type": "Feature",
  "properties": {
    "iso:country":"GB",
    "wof:name":"YO19 6GB",
    "wof:placetype":"postalcode"
},
  "geometry": {"coordinates":[-0.95994673123568,53.89619662803936],"type":"Point"}
}