{
  "type": "Feature",
  "properties": {
    "date:inception_lower": "2002-06-01",
    "date:inception_upper": "2002-06-01",
    "iso:country": "GB",
    "wof:name": "YO19 6GB",
    "wof:placetype": "postalcode"
  },
  "geometry": {"coordinates":[-0.959938,53.896216],"type":"Point"}
}
