{
  "type": "Feature",
  "properties": {
    "date:inception_lower":"2002-06-01",
    "date:inception_upper":"2002-06-30",
    "iso:country":"GB",
    "wof:name":"YO19 6GB",
    "wof:placetype":"postalcode"
},
  "geometry": {"coordinates":[-0.959947,53.896197],"type":"Point"}
}