{
  "type": "Feature",
  "properties": {
    "date:inception_lower": "1980-01-01",
    "date:inception_upper": "1980-01-01",
    "iso:country": "GB",
    "wof:name": "BA1 5QW",
    "wof:placetype": "postalcode"
  },
  "geometry": {"coordinates":[-2.360983,51.394073],"type":"Point"}
}
