{
  "type": "Feature",
  "properties": {
    "iso:country": "GB",
    "wof:name": "BA1 5QW",
    "wof:placetype": "postalcode"
  },
  "geometry": {"coordinates":[-2.360983,51.394073],"type":"Point"}
}
