{
  "type": "Feature",
  "properties": {
    "date:inception_lower": "2001-12-01",
    "date:inception_upper": "2001-12-01",
    "iso:country": "GB",
    "wof:name": "DN36 4BL",
    "wof:placetype": "postalcode"
  },
  "geometry": {"coordinates":[-0.070192,53.527935],"type":"Point"}
}
