{
  "type": "Feature",
  "properties": {
    "iso:country":"GB",
    "wof:name":"BS13 0BP",
    "wof:placetype":"postalcode"
},
  "geometry": {"coordinates":[-2.60474624043007,51.40475756192108],"type":"Point"}
}