{
  "type": "Feature",
  "properties": {
    "iso:country":"GB",
    "wof:name":"DH7 9SX",
    "wof:placetype":"postalcode"
},
  "geometry": {"coordinates":[-1.66732943464583,54.79951356609715],"type":"Point"}
}