{
  "type": "Feature",
  "properties": {
    "iso:country":"GB",
    "wof:name":"SA72 6RS",
    "wof:placetype":"postalcode"
},
  "geometry": {"coordinates":[-4.95038575726226,51.68291712099499],"type":"Point"}
}