{
  "type": "Feature",
  "properties": {
    "iso:country":"GB",
    "wof:name":"DT11 7UL",
    "wof:placetype":"postalcode"
},
  "geometry": {"coordinates":[-2.16471171523789,50.865898580737],"type":"Point"}
}