{
  "type": "Feature",
  "properties": {
    "iso:country": "GB",
    "wof:name": "DT11 7UL",
    "wof:placetype": "postalcode"
  },
  "geometry": {"coordinates":[-2.164712,50.865899],"type":"Point"}
}
