{
  "type": "Feature",
  "properties": {
    "iso:country": "GB",
    "wof:name": "TR5 0TX",
    "wof:placetype": "postalcode"
  },
  "geometry": {"coordinates":[-5.201902,50.31058],"type":"Point"}
}
