{
  "type": "Feature",
  "properties": {
    "iso:country":"GB",
    "wof:name":"PA11 3RP",
    "wof:placetype":"postalcode"
},
  "geometry": {"coordinates":[-4.57818080577022,55.84782653234419],"type":"Point"}
}