{
  "type": "Feature",
  "properties": {
    "date:inception_lower": "2024-01-01",
    "date:inception_upper": "2024-01-01",
    "iso:country": "GB",
    "wof:name": "OL10 2AQ",
    "wof:placetype": "postalcode"
  },
  "geometry": {"coordinates":[-2.210953,53.588275],"type":"Point"}
}
