{
  "type": "Feature",
  "properties": {
    "iso:country": "GB",
    "wof:name": "SE2 9XN",
    "wof:placetype": "postalcode"
  },
  "geometry": {"coordinates":[0.119731,51.499931],"type":"Point"}
}
