{
  "type": "Feature",
  "properties": {
    "iso:country":"GB",
    "wof:name":"SE2 9XN",
    "wof:placetype":"postalcode"
},
  "geometry": {"coordinates":[0.11973113272499,51.49993081749079],"type":"Point"}
}