{
  "type": "Feature",
  "properties": {
    "iso:country": "GB",
    "wof:name": "W6 7HG",
    "wof:placetype": "postalcode"
  },
  "geometry": {"coordinates":[-0.227924,51.500314],"type":"Point"}
}
