{
  "type": "Feature",
  "properties": {
    "iso:country":"GB",
    "wof:name":"W6 7HG",
    "wof:placetype":"postalcode"
},
  "geometry": {"coordinates":[-0.22794787565647,51.50031331583367],"type":"Point"}
}