{
  "type": "Feature",
  "properties": {
    "date:inception_lower":"1997-06-01",
    "date:inception_upper":"1997-06-30",
    "iso:country":"GB",
    "wof:name":"TR13 8GB",
    "wof:placetype":"postalcode"
},
  "geometry": {"coordinates":[-5.264865,50.113989],"type":"Point"}
}