{
  "type": "Feature",
  "properties": {
    "iso:country":"GB",
    "wof:name":"TR13 8GB",
    "wof:placetype":"postalcode"
},
  "geometry": {"coordinates":[-5.26486514823345,50.11398920834952],"type":"Point"}
}