{
  "type": "Feature",
  "properties": {
    "iso:country":"GB",
    "wof:name":"KA11 1JY",
    "wof:placetype":"postalcode"
},
  "geometry": {"coordinates":[-4.63389705489028,55.61882210006394],"type":"Point"}
}