{
  "type": "Feature",
  "properties": {
    "iso:country": "GB",
    "wof:name": "EX39 6JB",
    "wof:placetype": "postalcode"
  },
  "geometry": {"coordinates":[-4.479852,50.994552],"type":"Point"}
}
