{
  "type": "Feature",
  "properties": {
    "date:inception_lower": "2014-07-01",
    "date:inception_upper": "2014-07-01",
    "iso:country": "GB",
    "wof:name": "EX39 6JB",
    "wof:placetype": "postalcode"
  },
  "geometry": {"coordinates":[-4.479852,50.994552],"type":"Point"}
}
