{
  "type": "Feature",
  "properties": {
    "iso:country":"GB",
    "wof:name":"EX39 6JB",
    "wof:placetype":"postalcode"
},
  "geometry": {"coordinates":[-4.47985181083058,50.99455218787458],"type":"Point"}
}