{
  "type": "Feature",
  "properties": {
    "iso:country":"GB",
    "wof:name":"G13 1DH",
    "wof:placetype":"postalcode"
},
  "geometry": {"coordinates":[-4.32406320626489,55.89355116975053],"type":"Point"}
}