{
  "type": "Feature",
  "properties": {
    "date:inception_lower": "1980-01-01",
    "date:inception_upper": "1980-01-01",
    "iso:country": "GB",
    "wof:name": "W11 3NA",
    "wof:placetype": "postalcode"
  },
  "geometry": {"coordinates":[-0.202692,51.509921],"type":"Point"}
}
