{
  "type": "Feature",
  "properties": {
    "iso:country":"GB",
    "wof:name":"W1W 6RP",
    "wof:placetype":"postalcode"
},
  "geometry": {"coordinates":[-0.14144142630582,51.51982794227165],"type":"Point"}
}