{
  "type": "Feature",
  "properties": {
    "iso:country":"GB",
    "wof:name":"CO12 3PR",
    "wof:placetype":"postalcode"
},
  "geometry": {"coordinates":[1.27933795178331,51.93584900831677],"type":"Point"}
}