{
  "type": "Feature",
  "properties": {
    "iso:country": "GB",
    "wof:name": "DD11 5LA",
    "wof:placetype": "postalcode"
  },
  "geometry": {"coordinates":[-2.547436,56.632173],"type":"Point"}
}
