{
  "type": "Feature",
  "properties": {
    "iso:country":"GB",
    "wof:name":"DD11 5LA",
    "wof:placetype":"postalcode"
},
  "geometry": {"coordinates":[-2.54743559035891,56.63217280364567],"type":"Point"}
}