{
  "type": "Feature",
  "properties": {
    "iso:country":"GB",
    "wof:name":"DN11 9NT",
    "wof:placetype":"postalcode"
},
  "geometry": {"coordinates":[-1.11586127554037,53.43085400552557],"type":"Point"}
}