{
  "type": "Feature",
  "properties": {
    "iso:country": "GB",
    "wof:name": "DN11 9NT",
    "wof:placetype": "postalcode"
  },
  "geometry": {"coordinates":[-1.116027,53.430875],"type":"Point"}
}
