{
  "type": "Feature",
  "properties": {
    "date:inception_lower": "2005-05-01",
    "date:inception_upper": "2005-05-01",
    "iso:country": "GB",
    "wof:name": "LN2 4FH",
    "wof:placetype": "postalcode"
  },
  "geometry": {"coordinates":[-0.495282,53.24315],"type":"Point"}
}
