{
  "type": "Feature",
  "properties": {
    "iso:country":"GB",
    "wof:name":"S74 8EN",
    "wof:placetype":"postalcode"
},
  "geometry": {"coordinates":[-1.42586790876407,53.49889267685697],"type":"Point"}
}