{
  "type": "Feature",
  "properties": {
    "iso:country": "GB",
    "wof:name": "G64 4BJ",
    "wof:placetype": "postalcode"
  },
  "geometry": {"coordinates":[-4.203727,55.944326],"type":"Point"}
}
