{
  "type": "Feature",
  "properties": {
    "iso:country":"GB",
    "wof:name":"IG9 5NS",
    "wof:placetype":"postalcode"
},
  "geometry": {"coordinates":[0.03992930049135,51.62738724876152],"type":"Point"}
}