{
  "type": "Feature",
  "properties": {
    "date:inception_lower": "1980-01-01",
    "date:inception_upper": "1980-01-01",
    "iso:country": "GB",
    "wof:name": "WV3 0BS",
    "wof:placetype": "postalcode"
  },
  "geometry": {"coordinates":[-2.142598,52.580254],"type":"Point"}
}
