{
  "type": "Feature",
  "properties": {
    "iso:country":"GB",
    "wof:name":"WV3 0BS",
    "wof:placetype":"postalcode"
},
  "geometry": {"coordinates":[-2.14261920440512,52.5802840394773],"type":"Point"}
}