{
  "type": "Feature",
  "properties": {
    "iso:country": "GB",
    "wof:name": "GU14 8YD",
    "wof:placetype": "postalcode"
  },
  "geometry": {"coordinates":[-0.760679,51.307609],"type":"Point"}
}
