{
  "type": "Feature",
  "properties": {
    "iso:country":"GB",
    "wof:name":"WA4 2TH",
    "wof:placetype":"postalcode"
},
  "geometry": {"coordinates":[-2.51492350860905,53.38252391513613],"type":"Point"}
}