{
  "type": "Feature",
  "properties": {
    "iso:country": "GB",
    "wof:name": "WA4 2TH",
    "wof:placetype": "postalcode"
  },
  "geometry": {"coordinates":[-2.514923,53.382524],"type":"Point"}
}
