{
  "type": "Feature",
  "properties": {
    "iso:country":"GB",
    "wof:name":"GU47 0TB",
    "wof:placetype":"postalcode"
},
  "geometry": {"coordinates":[-0.77711627964304,51.3530840424251],"type":"Point"}
}