{
  "type": "Feature",
  "properties": {
    "date:inception_lower": "1980-01-01",
    "date:inception_upper": "1980-01-01",
    "iso:country": "GB",
    "wof:name": "CV35 7NX",
    "wof:placetype": "postalcode"
  },
  "geometry": {"coordinates":[-1.648043,52.336722],"type":"Point"}
}
