{
  "type": "Feature",
  "properties": {
    "iso:country":"GB",
    "wof:name":"DN14 8AD",
    "wof:placetype":"postalcode"
},
  "geometry": {"coordinates":[-0.85551297240031,53.68281227794595],"type":"Point"}
}