{
  "type": "Feature",
  "properties": {
    "iso:country":"GB",
    "wof:name":"SY25 6NH",
    "wof:placetype":"postalcode"
},
  "geometry": {"coordinates":[-3.92305710324793,52.21579293503368],"type":"Point"}
}