{
  "type": "Feature",
  "properties": {
    "iso:country":"GB",
    "wof:name":"S64 0HB",
    "wof:placetype":"postalcode"
},
  "geometry": {"coordinates":[-1.27531929218488,53.49149544515379],"type":"Point"}
}