{
  "type": "Feature",
  "properties": {
    "iso:country":"GB",
    "wof:name":"SE9 6TZ",
    "wof:placetype":"postalcode"
},
  "geometry": {"coordinates":[0.05248882437521,51.46788075134467],"type":"Point"}
}