{
  "type": "Feature",
  "properties": {
    "iso:country":"GB",
    "wof:name":"S70 5JG",
    "wof:placetype":"postalcode"
},
  "geometry": {"coordinates":[-1.47938987437272,53.5316400201265],"type":"Point"}
}