{
  "type": "Feature",
  "properties": {
    "iso:country": "GB",
    "wof:name": "TS11 6DL",
    "wof:placetype": "postalcode"
  },
  "geometry": {"coordinates":[-1.02715,54.59034],"type":"Point"}
}
