{
  "type": "Feature",
  "properties": {
    "iso:country":"GB",
    "wof:name":"TS11 6DL",
    "wof:placetype":"postalcode"
},
  "geometry": {"coordinates":[-1.0271499036052,54.59034023309966],"type":"Point"}
}