{
  "type": "Feature",
  "properties": {
    "iso:country": "GB",
    "wof:name": "CO11 2PB",
    "wof:placetype": "postalcode"
  },
  "geometry": {"coordinates":[1.098794,51.906517],"type":"Point"}
}
