{
  "type": "Feature",
  "properties": {
    "iso:country":"GB",
    "wof:name":"BN2 3LW",
    "wof:placetype":"postalcode"
},
  "geometry": {"coordinates":[-0.12294430681346,50.83617406417837],"type":"Point"}
}