{
  "type": "Feature",
  "properties": {
    "iso:country": "GB",
    "wof:name": "BN2 3LW",
    "wof:placetype": "postalcode"
  },
  "geometry": {"coordinates":[-0.122944,50.836174],"type":"Point"}
}
