{
  "type": "Feature",
  "properties": {
    "iso:country":"GB",
    "wof:name":"TF2 9RS",
    "wof:placetype":"postalcode"
},
  "geometry": {"coordinates":[-2.42596370220901,52.68632101546046],"type":"Point"}
}