{
  "type": "Feature",
  "properties": {
    "iso:country":"GB",
    "wof:name":"WF10 5SW",
    "wof:placetype":"postalcode"
},
  "geometry": {"coordinates":[-1.35817555967935,53.71764997074175],"type":"Point"}
}