{
  "type": "Feature",
  "properties": {
    "iso:country": "GB",
    "wof:name": "WF10 5SW",
    "wof:placetype": "postalcode"
  },
  "geometry": {"coordinates":[-1.358176,53.71765],"type":"Point"}
}
