{
  "type": "Feature",
  "properties": {
    "iso:country": "GB",
    "wof:name": "WD23 3PS",
    "wof:placetype": "postalcode"
  },
  "geometry": {"coordinates":[-0.354413,51.649529],"type":"Point"}
}
