{
  "type": "Feature",
  "properties": {
    "iso:country":"GB",
    "wof:name":"HU1 2QW",
    "wof:placetype":"postalcode"
},
  "geometry": {"coordinates":[-0.34706068806191,53.74103962700382],"type":"Point"}
}