{
  "type": "Feature",
  "properties": {
    "iso:country": "GB",
    "wof:name": "HU1 2QW",
    "wof:placetype": "postalcode"
  },
  "geometry": {"coordinates":[-0.347061,53.74104],"type":"Point"}
}
