{
  "type": "Feature",
  "properties": {
    "iso:country":"GB",
    "wof:name":"SR6 7BU",
    "wof:placetype":"postalcode"
},
  "geometry": {"coordinates":[-1.36550214072134,54.9503186580701],"type":"Point"}
}