{
  "type": "Feature",
  "properties": {
    "iso:country": "GB",
    "wof:name": "IP13 7QG",
    "wof:placetype": "postalcode"
  },
  "geometry": {"coordinates":[1.293199,52.166317],"type":"Point"}
}
