{
  "type": "Feature",
  "properties": {
    "iso:country":"GB",
    "wof:name":"IP13 7QG",
    "wof:placetype":"postalcode"
},
  "geometry": {"coordinates":[1.29319878182649,52.16631667855754],"type":"Point"}
}