{
  "type": "Feature",
  "properties": {
    "iso:country":"GB",
    "wof:name":"PO9 3AE",
    "wof:placetype":"postalcode"
},
  "geometry": {"coordinates":[-0.99038739680682,50.8598702621506],"type":"Point"}
}