{
  "type": "Feature",
  "properties": {
    "iso:country":"GB",
    "wof:name":"CB2 0SZ",
    "wof:placetype":"postalcode"
},
  "geometry": {"coordinates":[0.13615144884559,52.17844323863199],"type":"Point"}
}