{
  "type": "Feature",
  "properties": {
    "iso:country":"GB",
    "wof:name":"S63 7JW",
    "wof:placetype":"postalcode"
},
  "geometry": {"coordinates":[-1.34075135050789,53.49326733337116],"type":"Point"}
}