{
  "type": "Feature",
  "properties": {
    "iso:country":"GB",
    "wof:name":"E3 2SQ",
    "wof:placetype":"postalcode"
},
  "geometry": {"coordinates":[-0.02471458337092,51.53349546515079],"type":"Point"}
}