{
  "type": "Feature",
  "properties": {
    "date:inception_lower": "2005-06-01",
    "date:inception_upper": "2005-06-01",
    "iso:country": "GB",
    "wof:name": "FK5 4AQ",
    "wof:placetype": "postalcode"
  },
  "geometry": {"coordinates":[-3.834812,56.022936],"type":"Point"}
}
