{
  "type": "Feature",
  "properties": {
    "iso:country": "GB",
    "wof:name": "FK5 4AQ",
    "wof:placetype": "postalcode"
  },
  "geometry": {"coordinates":[-3.834812,56.022936],"type":"Point"}
}
