{
  "type": "Feature",
  "properties": {
    "iso:country":"GB",
    "wof:name":"FK5 4AQ",
    "wof:placetype":"postalcode"
},
  "geometry": {"coordinates":[-3.83481177993611,56.02293630443194],"type":"Point"}
}