{
  "type": "Feature",
  "properties": {
    "iso:country":"GB",
    "wof:name":"CW6 9BL",
    "wof:placetype":"postalcode"
},
  "geometry": {"coordinates":[-2.6026981407888,53.17525173434465],"type":"Point"}
}