{
  "type": "Feature",
  "properties": {
    "iso:country":"GB",
    "wof:name":"RH13 5HD",
    "wof:placetype":"postalcode"
},
  "geometry": {"coordinates":[-0.31260705274094,51.06520287004288],"type":"Point"}
}