{
  "type": "Feature",
  "properties": {
    "iso:country":"GB",
    "wof:name":"CB6 2AJ",
    "wof:placetype":"postalcode"
},
  "geometry": {"coordinates":[0.11789063743907,52.40729880362832],"type":"Point"}
}