{
  "type": "Feature",
  "properties": {
    "iso:country": "GB",
    "wof:name": "RM16 4QH",
    "wof:placetype": "postalcode"
  },
  "geometry": {"coordinates":[0.37627,51.487053],"type":"Point"}
}
