{
  "type": "Feature",
  "properties": {
    "date:inception_lower":"1980-01-01",
    "date:inception_upper":"1980-01-31",
    "iso:country":"GB",
    "wof:name":"BL1 2AH",
    "wof:placetype":"postalcode"
},
  "geometry": {"coordinates":[-2.430067,53.579933],"type":"Point"}
}