{
  "type": "Feature",
  "properties": {
    "iso:country":"GB",
    "wof:name":"BL1 2AH",
    "wof:placetype":"postalcode"
},
  "geometry": {"coordinates":[-2.43006657981507,53.57993295345963],"type":"Point"}
}