{
  "type": "Feature",
  "properties": {
    "iso:country":"GB",
    "wof:name":"KY9 1AA",
    "wof:placetype":"postalcode"
},
  "geometry": {"coordinates":[-2.83607136122099,56.18860508374591],"type":"Point"}
}