{
  "type": "Feature",
  "properties": {
    "iso:country": "GB",
    "wof:name": "KY9 1AA",
    "wof:placetype": "postalcode"
  },
  "geometry": {"coordinates":[-2.836071,56.188605],"type":"Point"}
}
