{
  "type": "Feature",
  "properties": {
    "date:inception_lower":"1980-01-01",
    "date:inception_upper":"1980-01-31",
    "iso:country":"GB",
    "wof:name":"KY9 1AA",
    "wof:placetype":"postalcode"
},
  "geometry": {"coordinates":[-2.836071,56.188605],"type":"Point"}
}