{
  "type": "Feature",
  "properties": {
    "date:inception_lower": "1980-01-01",
    "date:inception_upper": "1980-01-01",
    "iso:country": "GB",
    "wof:name": "G13 2BS",
    "wof:placetype": "postalcode"
  },
  "geometry": {"coordinates":[-4.344083,55.900362],"type":"Point"}
}
