{
  "type": "Feature",
  "properties": {
    "date:inception_lower":"2007-09-01",
    "date:inception_upper":"2007-09-30",
    "iso:country":"GB",
    "wof:name":"CM1 1JR",
    "wof:placetype":"postalcode"
},
  "geometry": {"coordinates":[0.46995,51.736144],"type":"Point"}
}