{
  "type": "Feature",
  "properties": {
    "iso:country": "GB",
    "wof:name": "DG8 6HT",
    "wof:placetype": "postalcode"
  },
  "geometry": {"coordinates":[-4.489165,54.962076],"type":"Point"}
}
