{
  "type": "Feature",
  "properties": {
    "iso:country":"GB",
    "wof:name":"DG8 6HT",
    "wof:placetype":"postalcode"
},
  "geometry": {"coordinates":[-4.48916498282301,54.96207567923261],"type":"Point"}
}