{
  "type": "Feature",
  "properties": {
    "iso:country": "GB",
    "wof:name": "NW1 5NT",
    "wof:placetype": "postalcode"
  },
  "geometry": {"coordinates":[-0.166363,51.520904],"type":"Point"}
}
