{
  "type": "Feature",
  "properties": {
    "iso:country":"GB",
    "wof:name":"NW1 5NT",
    "wof:placetype":"postalcode"
},
  "geometry": {"coordinates":[-0.1663634267628,51.52090361302666],"type":"Point"}
}