{
  "type": "Feature",
  "properties": {
    "iso:country": "GB",
    "wof:name": "SK10 4EX",
    "wof:placetype": "postalcode"
  },
  "geometry": {"coordinates":[-2.13666,53.288987],"type":"Point"}
}
