{
  "type": "Feature",
  "properties": {
    "date:inception_lower":"1980-01-01",
    "date:inception_upper":"1980-01-31",
    "iso:country":"GB",
    "wof:name":"SK10 4EX",
    "wof:placetype":"postalcode"
},
  "geometry": {"coordinates":[-2.13666,53.288987],"type":"Point"}
}