{
  "type": "Feature",
  "properties": {
    "iso:country":"GB",
    "wof:name":"BS10 6PQ",
    "wof:placetype":"postalcode"
},
  "geometry": {"coordinates":[-2.5991073059476,51.51328861227785],"type":"Point"}
}