{
  "type": "Feature",
  "properties": {
    "date:inception_lower": "2008-02-01",
    "date:inception_upper": "2008-02-01",
    "iso:country": "GB",
    "wof:name": "LN11 7BS",
    "wof:placetype": "postalcode"
  },
  "geometry": {"coordinates":[0.009441,53.371328],"type":"Point"}
}
