{
  "type": "Feature",
  "properties": {
    "iso:country":"GB",
    "wof:name":"PL15 8GW",
    "wof:placetype":"postalcode"
},
  "geometry": {"coordinates":[-4.42662132786149,50.67760270828578],"type":"Point"}
}