{
  "type": "Feature",
  "properties": {
    "date:inception_lower":"2003-05-01",
    "date:inception_upper":"2003-05-31",
    "iso:country":"GB",
    "wof:name":"PL15 8GW",
    "wof:placetype":"postalcode"
},
  "geometry": {"coordinates":[-4.426621,50.677603],"type":"Point"}
}