{
  "type": "Feature",
  "properties": {
    "iso:country": "GB",
    "wof:name": "PL15 8GW",
    "wof:placetype": "postalcode"
  },
  "geometry": {"coordinates":[-4.426621,50.677603],"type":"Point"}
}
