{
  "type": "Feature",
  "properties": {
    "iso:country":"GB",
    "wof:name":"PE24 4TL",
    "wof:placetype":"postalcode"
},
  "geometry": {"coordinates":[0.31791063813218,53.19530487966323],"type":"Point"}
}