{
  "type": "Feature",
  "properties": {
    "date:inception_lower": "1980-01-01",
    "date:inception_upper": "1980-01-01",
    "iso:country": "GB",
    "wof:name": "PE24 4TL",
    "wof:placetype": "postalcode"
  },
  "geometry": {"coordinates":[0.317911,53.195305],"type":"Point"}
}
