{
  "type": "Feature",
  "properties": {
    "iso:country":"GB",
    "wof:name":"ME7 1QG",
    "wof:placetype":"postalcode"
},
  "geometry": {"coordinates":[0.55305804242779,51.39203392651493],"type":"Point"}
}