{
  "type": "Feature",
  "properties": {
    "iso:country":"GB",
    "wof:name":"BN9 9HZ",
    "wof:placetype":"postalcode"
},
  "geometry": {"coordinates":[0.04252394370903,50.79050368114945],"type":"Point"}
}