{
  "type": "Feature",
  "properties": {
    "iso:country":"GB",
    "wof:name":"DH7 9NY",
    "wof:placetype":"postalcode"
},
  "geometry": {"coordinates":[-1.709027339361,54.76763760189439],"type":"Point"}
}