{
  "type": "Feature",
  "properties": {
    "iso:country": "GB",
    "wof:name": "LN2 2SR",
    "wof:placetype": "postalcode"
  },
  "geometry": {"coordinates":[-0.485266,53.268338],"type":"Point"}
}
