{
  "type": "Feature",
  "properties": {
    "iso:country":"GB",
    "wof:name":"LN2 2SR",
    "wof:placetype":"postalcode"
},
  "geometry": {"coordinates":[-0.48526581255619,53.2683381668672],"type":"Point"}
}