{
  "type": "Feature",
  "properties": {
    "iso:country":"GB",
    "wof:name":"G72 9PQ",
    "wof:placetype":"postalcode"
},
  "geometry": {"coordinates":[-4.0957954718674,55.79439692306566],"type":"Point"}
}