{
  "type": "Feature",
  "properties": {
    "iso:country":"GB",
    "wof:name":"CA5 6HN",
    "wof:placetype":"postalcode"
},
  "geometry": {"coordinates":[-3.07234808082983,54.89923420617518],"type":"Point"}
}