{
  "type": "Feature",
  "properties": {
    "date:inception_lower": "2024-06-01",
    "date:inception_upper": "2024-06-01",
    "iso:country": "GB",
    "wof:name": "CM7 5XZ",
    "wof:placetype": "postalcode"
  },
  "geometry": {"coordinates":[0.541295,51.899016],"type":"Point"}
}
