{
  "type": "Feature",
  "properties": {
    "date:inception_lower":"2002-08-01",
    "date:inception_upper":"2002-08-31",
    "iso:country":"GB",
    "wof:name":"PE15 0NR",
    "wof:placetype":"postalcode"
},
  "geometry": {"coordinates":[0.082057,52.512039],"type":"Point"}
}