{
  "type": "Feature",
  "properties": {
    "iso:country":"GB",
    "wof:name":"PE15 0NR",
    "wof:placetype":"postalcode"
},
  "geometry": {"coordinates":[0.08205723075684,52.51203917341435],"type":"Point"}
}