{
  "type": "Feature",
  "properties": {
    "iso:country":"GB",
    "wof:name":"PL32 9ND",
    "wof:placetype":"postalcode"
},
  "geometry": {"coordinates":[-4.67258078176542,50.62511344062982],"type":"Point"}
}