{
  "type": "Feature",
  "properties": {
    "date:inception_lower": "2023-03-01",
    "date:inception_upper": "2023-03-01",
    "iso:country": "GB",
    "wof:name": "DE5 3WJ",
    "wof:placetype": "postalcode"
  },
  "geometry": {"coordinates":[-1.390351,53.040041],"type":"Point"}
}
