{
  "type": "Feature",
  "properties": {
    "iso:country":"GB",
    "wof:name":"W12 0RY",
    "wof:placetype":"postalcode"
},
  "geometry": {"coordinates":[-0.23948215384348,51.51281561312324],"type":"Point"}
}