{
  "type": "Feature",
  "properties": {
    "date:inception_lower": "2000-06-01",
    "date:inception_upper": "2000-06-01",
    "iso:country": "GB",
    "wof:name": "BA13 4JZ",
    "wof:placetype": "postalcode"
  },
  "geometry": {"coordinates":[-2.184645,51.280559],"type":"Point"}
}
