{
  "type": "Feature",
  "properties": {
    "iso:country":"GB",
    "wof:name":"BA13 4JZ",
    "wof:placetype":"postalcode"
},
  "geometry": {"coordinates":[-2.18464496256845,51.28055892367681],"type":"Point"}
}