{
  "type": "Feature",
  "properties": {
    "iso:country": "GB",
    "wof:name": "BA13 4JZ",
    "wof:placetype": "postalcode"
  },
  "geometry": {"coordinates":[-2.184645,51.280559],"type":"Point"}
}
