{
  "type": "Feature",
  "properties": {
    "iso:country":"GB",
    "wof:name":"E8 2AU",
    "wof:placetype":"postalcode"
},
  "geometry": {"coordinates":[-0.06613678671468,51.55260241344558],"type":"Point"}
}