{
  "type": "Feature",
  "properties": {
    "date:inception_lower": "1992-01-01",
    "date:inception_upper": "1992-01-01",
    "iso:country": "GB",
    "wof:name": "YO8 9SZ",
    "wof:placetype": "postalcode"
  },
  "geometry": {"coordinates":[-1.082773,53.767416],"type":"Point"}
}
