{
  "type": "Feature",
  "properties": {
    "iso:country": "GB",
    "wof:name": "YO8 9SZ",
    "wof:placetype": "postalcode"
  },
  "geometry": {"coordinates":[-1.082773,53.767416],"type":"Point"}
}
