{
  "type": "Feature",
  "properties": {
    "iso:country": "GB",
    "wof:name": "DA1 4BF",
    "wof:placetype": "postalcode"
  },
  "geometry": {"coordinates":[0.172547,51.45042],"type":"Point"}
}
