{
  "type": "Feature",
  "properties": {
    "iso:country":"GB",
    "wof:name":"DA1 4BF",
    "wof:placetype":"postalcode"
},
  "geometry": {"coordinates":[0.17254689615242,51.45042023096719],"type":"Point"}
}