{
  "type": "Feature",
  "properties": {
    "date:inception_lower": "2005-09-01",
    "date:inception_upper": "2005-09-01",
    "iso:country": "GB",
    "wof:name": "DA1 4BF",
    "wof:placetype": "postalcode"
  },
  "geometry": {"coordinates":[0.172547,51.45042],"type":"Point"}
}
