{
  "type": "Feature",
  "properties": {
    "date:inception_lower":"1980-01-01",
    "date:inception_upper":"1980-01-31",
    "iso:country":"GB",
    "wof:name":"SS0 8BS",
    "wof:placetype":"postalcode"
},
  "geometry": {"coordinates":[0.688906,51.538425],"type":"Point"}
}