{
  "type": "Feature",
  "properties": {
    "date:inception_lower":"2014-02-01",
    "date:inception_upper":"2014-02-28",
    "iso:country":"GB",
    "wof:name":"SP9 7FP",
    "wof:placetype":"postalcode"
},
  "geometry": {"coordinates":[-1.663502,51.246427],"type":"Point"}
}