{
  "type": "Feature",
  "properties": {
    "iso:country": "GB",
    "wof:name": "SP9 7FP",
    "wof:placetype": "postalcode"
  },
  "geometry": {"coordinates":[-1.663502,51.246427],"type":"Point"}
}
