{
  "type": "Feature",
  "properties": {
    "date:inception_lower":"1998-06-01",
    "date:inception_upper":"1998-06-30",
    "iso:country":"GB",
    "wof:name":"DN35 0UD",
    "wof:placetype":"postalcode"
},
  "geometry": {"coordinates":[-0.032043,53.537534],"type":"Point"}
}