{
  "type": "Feature",
  "properties": {
    "iso:country":"GB",
    "wof:name":"DN35 0UD",
    "wof:placetype":"postalcode"
},
  "geometry": {"coordinates":[-0.03204328460375,53.53753447893283],"type":"Point"}
}