{
  "type": "Feature",
  "properties": {
    "iso:country":"GB",
    "wof:name":"IV19 1HA",
    "wof:placetype":"postalcode"
},
  "geometry": {"coordinates":[-4.06209330934131,57.81106574081719],"type":"Point"}
}