{
  "type": "Feature",
  "properties": {
    "iso:country":"GB",
    "wof:name":"CM9 4UN",
    "wof:placetype":"postalcode"
},
  "geometry": {"coordinates":[0.67744807206703,51.74238971686837],"type":"Point"}
}