{
  "type": "Feature",
  "properties": {
    "date:inception_lower":"2003-05-01",
    "date:inception_upper":"2003-05-31",
    "iso:country":"GB",
    "wof:name":"CM9 4UN",
    "wof:placetype":"postalcode"
},
  "geometry": {"coordinates":[0.677448,51.74239],"type":"Point"}
}