{
  "type": "Feature",
  "properties": {
    "date:inception_lower": "2017-09-01",
    "date:inception_upper": "2017-09-01",
    "iso:country": "GB",
    "wof:name": "G77 6WQ",
    "wof:placetype": "postalcode"
  },
  "geometry": {"coordinates":[-4.38979,55.750982],"type":"Point"}
}
