{
  "type": "Feature",
  "properties": {
    "iso:country":"GB",
    "wof:name":"B14 4ND",
    "wof:placetype":"postalcode"
},
  "geometry": {"coordinates":[-1.87876207351262,52.41020080785231],"type":"Point"}
}