{
  "type": "Feature",
  "properties": {
    "date:inception_lower": "1980-01-01",
    "date:inception_upper": "1980-01-01",
    "iso:country": "GB",
    "wof:name": "WA16 7QX",
    "wof:placetype": "postalcode"
  },
  "geometry": {"coordinates":[-2.317053,53.322493],"type":"Point"}
}
