{
  "type": "Feature",
  "properties": {
    "iso:country":"GB",
    "wof:name":"BD18 2DH",
    "wof:placetype":"postalcode"
},
  "geometry": {"coordinates":[-1.7734666033561,53.82324405296098],"type":"Point"}
}