{
  "type": "Feature",
  "properties": {
    "iso:country":"GB",
    "wof:name":"B97 4LD",
    "wof:placetype":"postalcode"
},
  "geometry": {"coordinates":[-1.94736297345026,52.29271380163073],"type":"Point"}
}