{
  "type": "Feature",
  "properties": {
    "date:inception_lower": "1980-01-01",
    "date:inception_upper": "1980-01-01",
    "iso:country": "GB",
    "wof:name": "B97 4LD",
    "wof:placetype": "postalcode"
  },
  "geometry": {"coordinates":[-1.947363,52.292714],"type":"Point"}
}
