{
  "type": "Feature",
  "properties": {
    "iso:country":"GB",
    "wof:name":"M22 4WB",
    "wof:placetype":"postalcode"
},
  "geometry": {"coordinates":[-2.25250349799338,53.40420344494801],"type":"Point"}
}