{
  "type": "Feature",
  "properties": {
    "iso:country": "GB",
    "wof:name": "PO38 2DF",
    "wof:placetype": "postalcode"
  },
  "geometry": {"coordinates":[-1.284602,50.589823],"type":"Point"}
}
