{
  "type": "Feature",
  "properties": {
    "iso:country":"GB",
    "wof:name":"M3 7LB",
    "wof:placetype":"postalcode"
},
  "geometry": {"coordinates":[-2.25504633229604,53.48972372340632],"type":"Point"}
}