{
  "type": "Feature",
  "properties": {
    "iso:country":"GB",
    "wof:name":"SM7 2FB",
    "wof:placetype":"postalcode"
},
  "geometry": {"coordinates":[-0.18891769309797,51.30813865470542],"type":"Point"}
}