{
  "type": "Feature",
  "properties": {
    "iso:country":"GB",
    "wof:name":"SA6 8ES",
    "wof:placetype":"postalcode"
},
  "geometry": {"coordinates":[-3.9230930583304,51.65989786002863],"type":"Point"}
}