{
  "type": "Feature",
  "properties": {
    "iso:country":"GB",
    "wof:name":"CH66 2EN",
    "wof:placetype":"postalcode"
},
  "geometry": {"coordinates":[-2.93601324109591,53.26748457635367],"type":"Point"}
}