{
  "type": "Feature",
  "properties": {
    "iso:country": "GB",
    "wof:name": "TS10 2BP",
    "wof:placetype": "postalcode"
  },
  "geometry": {"coordinates":[-1.061554,54.612495],"type":"Point"}
}
