{
  "type": "Feature",
  "properties": {
    "iso:country":"GB",
    "wof:name":"TS10 2BP",
    "wof:placetype":"postalcode"
},
  "geometry": {"coordinates":[-1.06155373455902,54.61249547744175],"type":"Point"}
}