{
  "type": "Feature",
  "properties": {
    "date:inception_lower": "1980-01-01",
    "date:inception_upper": "1980-01-01",
    "iso:country": "GB",
    "wof:name": "TS10 2BP",
    "wof:placetype": "postalcode"
  },
  "geometry": {"coordinates":[-1.061554,54.612495],"type":"Point"}
}
