{
  "type": "Feature",
  "properties": {
    "iso:country":"GB",
    "wof:name":"NE4 5DD",
    "wof:placetype":"postalcode"
},
  "geometry": {"coordinates":[-1.62988948126073,54.97643701602588],"type":"Point"}
}