{
  "type": "Feature",
  "properties": {
    "date:inception_lower": "1980-01-01",
    "date:inception_upper": "1980-01-01",
    "iso:country": "GB",
    "wof:name": "SL6 3HH",
    "wof:placetype": "postalcode"
  },
  "geometry": {"coordinates":[-0.742686,51.50589],"type":"Point"}
}
