{
  "type": "Feature",
  "properties": {
    "iso:country":"GB",
    "wof:name":"SL6 3HH",
    "wof:placetype":"postalcode"
},
  "geometry": {"coordinates":[-0.74268577625994,51.50589025147935],"type":"Point"}
}