{
  "type": "Feature",
  "properties": {
    "iso:country": "GB",
    "wof:name": "SL6 3HH",
    "wof:placetype": "postalcode"
  },
  "geometry": {"coordinates":[-0.742686,51.50589],"type":"Point"}
}
