{
  "type": "Feature",
  "properties": {
    "iso:country":"GB",
    "wof:name":"PL12 6QR",
    "wof:placetype":"postalcode"
},
  "geometry": {"coordinates":[-4.29803416743833,50.46056070960427],"type":"Point"}
}