{
  "type": "Feature",
  "properties": {
    "date:inception_lower": "1980-01-01",
    "date:inception_upper": "1980-01-01",
    "iso:country": "GB",
    "wof:name": "PL12 6QR",
    "wof:placetype": "postalcode"
  },
  "geometry": {"coordinates":[-4.297979,50.460589],"type":"Point"}
}
