{
  "type": "Feature",
  "properties": {
    "iso:country": "GB",
    "wof:name": "PL12 6QR",
    "wof:placetype": "postalcode"
  },
  "geometry": {"coordinates":[-4.297979,50.460589],"type":"Point"}
}
