{
  "type": "Feature",
  "properties": {
    "iso:country":"GB",
    "wof:name":"IP14 4AR",
    "wof:placetype":"postalcode"
},
  "geometry": {"coordinates":[1.02284858450055,52.20179975026819],"type":"Point"}
}