{
  "type": "Feature",
  "properties": {
    "iso:country":"GB",
    "wof:name":"B90 2QU",
    "wof:placetype":"postalcode"
},
  "geometry": {"coordinates":[-1.8421931584149,52.4041613560947],"type":"Point"}
}