{
  "type": "Feature",
  "properties": {
    "iso:country":"GB",
    "wof:name":"OL10 4TT",
    "wof:placetype":"postalcode"
},
  "geometry": {"coordinates":[-2.22926153689212,53.59899357233641],"type":"Point"}
}