{
  "type": "Feature",
  "properties": {
    "date:inception_lower": "1980-01-01",
    "date:inception_upper": "1980-01-01",
    "iso:country": "GB",
    "wof:name": "CO16 9PZ",
    "wof:placetype": "postalcode"
  },
  "geometry": {"coordinates":[1.158264,51.843492],"type":"Point"}
}
