{
  "type": "Feature",
  "properties": {
    "iso:country":"GB",
    "wof:name":"CO16 9PZ",
    "wof:placetype":"postalcode"
},
  "geometry": {"coordinates":[1.15826387085995,51.84349195402473],"type":"Point"}
}