{
  "type": "Feature",
  "properties": {
    "iso:country": "GB",
    "wof:name": "LE67 8FZ",
    "wof:placetype": "postalcode"
  },
  "geometry": {"coordinates":[-1.421848,52.752059],"type":"Point"}
}
