{
  "type": "Feature",
  "properties": {
    "date:inception_lower": "2004-09-01",
    "date:inception_upper": "2004-09-01",
    "iso:country": "GB",
    "wof:name": "LE67 8FZ",
    "wof:placetype": "postalcode"
  },
  "geometry": {"coordinates":[-1.421848,52.752059],"type":"Point"}
}
