{
  "type": "Feature",
  "properties": {
    "date:inception_lower": "1980-01-01",
    "date:inception_upper": "1980-01-01",
    "iso:country": "GB",
    "wof:name": "PA5 9SX",
    "wof:placetype": "postalcode"
  },
  "geometry": {"coordinates":[-4.505832,55.824641],"type":"Point"}
}
