{
  "type": "Feature",
  "properties": {
    "iso:country": "GB",
    "wof:name": "DN4 6LX",
    "wof:placetype": "postalcode"
  },
  "geometry": {"coordinates":[-1.077992,53.504599],"type":"Point"}
}
