{
  "type": "Feature",
  "properties": {
    "iso:country":"GB",
    "wof:name":"CF32 8SW",
    "wof:placetype":"postalcode"
},
  "geometry": {"coordinates":[-3.59127861333332,51.571274668957],"type":"Point"}
}