{
  "type": "Feature",
  "properties": {
    "date:inception_lower": "2004-02-01",
    "date:inception_upper": "2004-02-01",
    "iso:country": "GB",
    "wof:name": "CF32 8SW",
    "wof:placetype": "postalcode"
  },
  "geometry": {"coordinates":[-3.591798,51.57128],"type":"Point"}
}
