{
  "type": "Feature",
  "properties": {
    "iso:country":"GB",
    "wof:name":"SP2 9LY",
    "wof:placetype":"postalcode"
},
  "geometry": {"coordinates":[-1.81824564710513,51.0818777964289],"type":"Point"}
}