{
  "type": "Feature",
  "properties": {
    "iso:country":"GB",
    "wof:name":"DD11 3BJ",
    "wof:placetype":"postalcode"
},
  "geometry": {"coordinates":[-2.59279510370445,56.56319248270376],"type":"Point"}
}