{
  "type": "Feature",
  "properties": {
    "date:inception_lower":"1980-01-01",
    "date:inception_upper":"1980-01-31",
    "iso:country":"GB",
    "wof:name":"TR12 7QL",
    "wof:placetype":"postalcode"
},
  "geometry": {"coordinates":[-5.259173,50.063357],"type":"Point"}
}