{
  "type": "Feature",
  "properties": {
    "date:inception_lower": "2000-12-01",
    "date:inception_upper": "2000-12-01",
    "iso:country": "GB",
    "wof:name": "NR32 4WR",
    "wof:placetype": "postalcode"
  },
  "geometry": {"coordinates":[1.72507,52.498368],"type":"Point"}
}
