{
  "type": "Feature",
  "properties": {
    "iso:country":"GB",
    "wof:name":"NR32 4WR",
    "wof:placetype":"postalcode"
},
  "geometry": {"coordinates":[1.72506983547898,52.4983681734639],"type":"Point"}
}