{
  "type": "Feature",
  "properties": {
    "iso:country":"GB",
    "wof:name":"B97 5SU",
    "wof:placetype":"postalcode"
},
  "geometry": {"coordinates":[-2.00981011525633,52.30162531898164],"type":"Point"}
}