{
  "type": "Feature",
  "properties": {
    "iso:country":"GB",
    "wof:name":"NR4 7AL",
    "wof:placetype":"postalcode"
},
  "geometry": {"coordinates":[1.26479336923211,52.62109668988536],"type":"Point"}
}