{
  "type": "Feature",
  "properties": {
    "date:inception_lower":"1995-07-01",
    "date:inception_upper":"1995-07-31",
    "iso:country":"GB",
    "wof:name":"CM1 7SF",
    "wof:placetype":"postalcode"
},
  "geometry": {"coordinates":[0.484789,51.744195],"type":"Point"}
}