{
  "type": "Feature",
  "properties": {
    "iso:country":"GB",
    "wof:name":"HA1 1QB",
    "wof:placetype":"postalcode"
},
  "geometry": {"coordinates":[-0.34043487999005,51.58299708627056],"type":"Point"}
}