{
  "type": "Feature",
  "properties": {
    "iso:country": "GB",
    "wof:name": "HA1 1QB",
    "wof:placetype": "postalcode"
  },
  "geometry": {"coordinates":[-0.340435,51.582997],"type":"Point"}
}
