{
  "type": "Feature",
  "properties": {
    "iso:country":"GB",
    "wof:name":"N20 0DU",
    "wof:placetype":"postalcode"
},
  "geometry": {"coordinates":[-0.15944350901601,51.62239141651243],"type":"Point"}
}