{
  "type": "Feature",
  "properties": {
    "iso:country": "GB",
    "wof:name": "SK4 3GN",
    "wof:placetype": "postalcode"
  },
  "geometry": {"coordinates":[-2.202262,53.406895],"type":"Point"}
}
