{
  "type": "Feature",
  "properties": {
    "iso:country": "GB",
    "wof:name": "SK4 3GN",
    "wof:placetype": "postalcode"
  },
  "geometry": {"coordinates":[-2.202426,53.4065],"type":"Point"}
}
