{
  "type": "Feature",
  "properties": {
    "date:inception_lower": "2002-07-01",
    "date:inception_upper": "2002-07-01",
    "iso:country": "GB",
    "wof:name": "PR2 3LG",
    "wof:placetype": "postalcode"
  },
  "geometry": {"coordinates":[-2.731183,53.776089],"type":"Point"}
}
