{
  "type": "Feature",
  "properties": {
    "iso:country":"GB",
    "wof:name":"PR2 3LG",
    "wof:placetype":"postalcode"
},
  "geometry": {"coordinates":[-2.73118265236733,53.77608893781282],"type":"Point"}
}