{
  "type": "Feature",
  "properties": {
    "iso:country":"GB",
    "wof:name":"TS24 8BZ",
    "wof:placetype":"postalcode"
},
  "geometry": {"coordinates":[-1.21360621585938,54.68957186843689],"type":"Point"}
}