{
  "type": "Feature",
  "properties": {
    "iso:country":"GB",
    "wof:name":"TA10 9LF",
    "wof:placetype":"postalcode"
},
  "geometry": {"coordinates":[-2.76557827356956,51.00098010307529],"type":"Point"}
}