{
  "type": "Feature",
  "properties": {
    "iso:country": "GB",
    "wof:name": "TA10 9LF",
    "wof:placetype": "postalcode"
  },
  "geometry": {"coordinates":[-2.765578,51.00098],"type":"Point"}
}
