{
  "type": "Feature",
  "properties": {
    "iso:country": "GB",
    "wof:name": "CB2 8BS",
    "wof:placetype": "postalcode"
  },
  "geometry": {"coordinates":[0.132073,52.188323],"type":"Point"}
}
