{
  "type": "Feature",
  "properties": {
    "iso:country":"GB",
    "wof:name":"DH5 8JH",
    "wof:placetype":"postalcode"
},
  "geometry": {"coordinates":[-1.46745232896205,54.83712019728475],"type":"Point"}
}