{
  "type": "Feature",
  "properties": {
    "date:inception_lower": "1980-01-01",
    "date:inception_upper": "1980-01-01",
    "iso:country": "GB",
    "wof:name": "DH5 8JH",
    "wof:placetype": "postalcode"
  },
  "geometry": {"coordinates":[-1.467452,54.83712],"type":"Point"}
}
