{
  "type": "Feature",
  "properties": {
    "date:inception_lower": "1980-01-01",
    "date:inception_upper": "1980-01-01",
    "iso:country": "GB",
    "wof:name": "KT3 5PW",
    "wof:placetype": "postalcode"
  },
  "geometry": {"coordinates":[-0.263503,51.384689],"type":"Point"}
}
