{
  "type": "Feature",
  "properties": {
    "iso:country": "GB",
    "wof:name": "KT3 5PW",
    "wof:placetype": "postalcode"
  },
  "geometry": {"coordinates":[-0.263503,51.384689],"type":"Point"}
}
