{
  "type": "Feature",
  "properties": {
    "date:inception_lower":"1980-01-01",
    "date:inception_upper":"1980-01-31",
    "iso:country":"GB",
    "wof:name":"PH2 7ET",
    "wof:placetype":"postalcode"
},
  "geometry": {"coordinates":[-3.418728,56.402784],"type":"Point"}
}