{
  "type": "Feature",
  "properties": {
    "iso:country":"GB",
    "wof:name":"YO7 3RS",
    "wof:placetype":"postalcode"
},
  "geometry": {"coordinates":[-1.38436387474989,54.1790187371065],"type":"Point"}
}