{
  "type": "Feature",
  "properties": {
    "iso:country": "GB",
    "wof:name": "YO7 3RS",
    "wof:placetype": "postalcode"
  },
  "geometry": {"coordinates":[-1.384364,54.179019],"type":"Point"}
}
