{
  "type": "Feature",
  "properties": {
    "iso:country":"GB",
    "wof:name":"HG2 0EA",
    "wof:placetype":"postalcode"
},
  "geometry": {"coordinates":[-1.54858859596295,53.98200025118614],"type":"Point"}
}