{
  "type": "Feature",
  "properties": {
    "iso:country": "GB",
    "wof:name": "HG2 0EA",
    "wof:placetype": "postalcode"
  },
  "geometry": {"coordinates":[-1.548589,53.982],"type":"Point"}
}
