{
  "type": "Feature",
  "properties": {
    "iso:country":"GB",
    "wof:name":"N12 0AE",
    "wof:placetype":"postalcode"
},
  "geometry": {"coordinates":[-0.17364934878784,51.60319883729196],"type":"Point"}
}