{
  "type": "Feature",
  "properties": {
    "date:inception_lower": "1981-06-01",
    "date:inception_upper": "1981-06-01",
    "iso:country": "GB",
    "wof:name": "DY9 0QB",
    "wof:placetype": "postalcode"
  },
  "geometry": {"coordinates":[-2.130217,52.430873],"type":"Point"}
}
