{
  "type": "Feature",
  "properties": {
    "date:inception_lower": "1981-06-01",
    "date:inception_upper": "1981-06-01",
    "iso:country": "GB",
    "wof:name": "TF11 9QA",
    "wof:placetype": "postalcode"
  },
  "geometry": {"coordinates":[-2.368795,52.664808],"type":"Point"}
}
