{
  "type": "Feature",
  "properties": {
    "iso:country":"GB",
    "wof:name":"BA5 3HJ",
    "wof:placetype":"postalcode"
},
  "geometry": {"coordinates":[-2.61417451475403,51.21550159507601],"type":"Point"}
}