{
  "type": "Feature",
  "properties": {
    "iso:country": "GB",
    "wof:name": "BA5 3HJ",
    "wof:placetype": "postalcode"
  },
  "geometry": {"coordinates":[-2.614174,51.215502],"type":"Point"}
}
