{
  "type": "Feature",
  "properties": {
    "iso:country":"GB",
    "wof:name":"NW5 1BN",
    "wof:placetype":"postalcode"
},
  "geometry": {"coordinates":[-0.1455447384549,51.55648323367065],"type":"Point"}
}