{
  "type": "Feature",
  "properties": {
    "date:inception_lower": "1980-01-01",
    "date:inception_upper": "1980-01-01",
    "iso:country": "GB",
    "wof:name": "EX20 1JZ",
    "wof:placetype": "postalcode"
  },
  "geometry": {"coordinates":[-4.003944,50.738966],"type":"Point"}
}
