{
  "type": "Feature",
  "properties": {
    "iso:country":"GB",
    "wof:name":"EX20 1JZ",
    "wof:placetype":"postalcode"
},
  "geometry": {"coordinates":[-4.00400625035243,50.73895434197658],"type":"Point"}
}