{
  "type": "Feature",
  "properties": {
    "iso:country": "GB",
    "wof:name": "EX20 1JZ",
    "wof:placetype": "postalcode"
  },
  "geometry": {"coordinates":[-4.004006,50.738954],"type":"Point"}
}
