{
  "type": "Feature",
  "properties": {
    "iso:country": "GB",
    "wof:name": "L25 0NG",
    "wof:placetype": "postalcode"
  },
  "geometry": {"coordinates":[-2.859631,53.36061],"type":"Point"}
}
