{
  "type": "Feature",
  "properties": {
    "date:inception_lower": "2019-01-01",
    "date:inception_upper": "2019-01-01",
    "iso:country": "GB",
    "wof:name": "CA24 3AB",
    "wof:placetype": "postalcode"
  },
  "geometry": {"coordinates":[-3.545549,54.514846],"type":"Point"}
}
