{
  "type": "Feature",
  "properties": {
    "iso:country": "GB",
    "wof:name": "YO23 3PX",
    "wof:placetype": "postalcode"
  },
  "geometry": {"coordinates":[-1.18721,53.926846],"type":"Point"}
}
