{
  "type": "Feature",
  "properties": {
    "iso:country":"GB",
    "wof:name":"YO23 3PX",
    "wof:placetype":"postalcode"
},
  "geometry": {"coordinates":[-1.18721050618884,53.92684641075333],"type":"Point"}
}