{
  "type": "Feature",
  "properties": {
    "iso:country":"GB",
    "wof:name":"FK1 4PF",
    "wof:placetype":"postalcode"
},
  "geometry": {"coordinates":[-3.81482295607641,56.00114366171076],"type":"Point"}
}