{
  "type": "Feature",
  "properties": {
    "iso:country": "GB",
    "wof:name": "G61 3ED",
    "wof:placetype": "postalcode"
  },
  "geometry": {"coordinates":[-4.314865,55.930828],"type":"Point"}
}
