{
  "type": "Feature",
  "properties": {
    "date:inception_lower":"1980-01-01",
    "date:inception_upper":"1980-01-31",
    "iso:country":"GB",
    "wof:name":"B94 5AA",
    "wof:placetype":"postalcode"
},
  "geometry": {"coordinates":[-1.813151,52.342282],"type":"Point"}
}