{
  "type": "Feature",
  "properties": {
    "iso:country":"GB",
    "wof:name":"BA5 2PY",
    "wof:placetype":"postalcode"
},
  "geometry": {"coordinates":[-2.65000276947389,51.20882474550721],"type":"Point"}
}