{
  "type": "Feature",
  "properties": {
    "iso:country":"GB",
    "wof:name":"SG15 6TN",
    "wof:placetype":"postalcode"
},
  "geometry": {"coordinates":[-0.26590602284623,52.02203120530432],"type":"Point"}
}