{
  "type": "Feature",
  "properties": {
    "date:inception_lower":"1988-03-01",
    "date:inception_upper":"1988-03-31",
    "iso:country":"GB",
    "wof:name":"SG15 6TN",
    "wof:placetype":"postalcode"
},
  "geometry": {"coordinates":[-0.265906,52.022031],"type":"Point"}
}