{
  "type": "Feature",
  "properties": {
    "iso:country": "GB",
    "wof:name": "KA9 2RL",
    "wof:placetype": "postalcode"
  },
  "geometry": {"coordinates":[-4.601736,55.516229],"type":"Point"}
}
