{
  "type": "Feature",
  "properties": {
    "iso:country": "GB",
    "wof:name": "RG6 1NY",
    "wof:placetype": "postalcode"
  },
  "geometry": {"coordinates":[-0.933223,51.447361],"type":"Point"}
}
