{
  "type": "Feature",
  "properties": {
    "iso:country":"GB",
    "wof:name":"RG6 1NY",
    "wof:placetype":"postalcode"
},
  "geometry": {"coordinates":[-0.93322326036837,51.44736133853562],"type":"Point"}
}