{
  "type": "Feature",
  "properties": {
    "iso:country": "GB",
    "wof:name": "RH19 2QA",
    "wof:placetype": "postalcode"
  },
  "geometry": {"coordinates":[-0.070145,51.139085],"type":"Point"}
}
