{
  "type": "Feature",
  "properties": {
    "iso:country":"GB",
    "wof:name":"ST19 9JN",
    "wof:placetype":"postalcode"
},
  "geometry": {"coordinates":[-2.18831878053292,52.71312404577344],"type":"Point"}
}