{
  "type": "Feature",
  "properties": {
    "iso:country":"GB",
    "wof:name":"PE19 8TT",
    "wof:placetype":"postalcode"
},
  "geometry": {"coordinates":[-0.29571186631296,52.21272605829392],"type":"Point"}
}