{
  "type": "Feature",
  "properties": {
    "iso:country":"GB",
    "wof:name":"CM0 8BT",
    "wof:placetype":"postalcode"
},
  "geometry": {"coordinates":[0.81762160162306,51.63311119828342],"type":"Point"}
}