{
  "type": "Feature",
  "properties": {
    "date:inception_lower": "1980-01-01",
    "date:inception_upper": "1980-01-01",
    "iso:country": "GB",
    "wof:name": "S74 9BQ",
    "wof:placetype": "postalcode"
  },
  "geometry": {"coordinates":[-1.436758,53.497336],"type":"Point"}
}
