{
  "type": "Feature",
  "properties": {
    "iso:country":"GB",
    "wof:name":"PL30 5BH",
    "wof:placetype":"postalcode"
},
  "geometry": {"coordinates":[-4.72979424657176,50.44800741767762],"type":"Point"}
}