{
  "type": "Feature",
  "properties": {
    "iso:country":"GB",
    "wof:name":"LE3 0HH",
    "wof:placetype":"postalcode"
},
  "geometry": {"coordinates":[-1.15467809758132,52.62453478041527],"type":"Point"}
}