{
  "type": "Feature",
  "properties": {
    "iso:country": "GB",
    "wof:name": "LE3 0HH",
    "wof:placetype": "postalcode"
  },
  "geometry": {"coordinates":[-1.154678,52.624535],"type":"Point"}
}
