{
  "type": "Feature",
  "properties": {
    "iso:country":"GB",
    "wof:name":"NE7 7EU",
    "wof:placetype":"postalcode"
},
  "geometry": {"coordinates":[-1.58204678855988,54.99492862075651],"type":"Point"}
}