{
  "type": "Feature",
  "properties": {
    "iso:country": "GB",
    "wof:name": "NE7 7EU",
    "wof:placetype": "postalcode"
  },
  "geometry": {"coordinates":[-1.582047,54.994929],"type":"Point"}
}
