{
  "type": "Feature",
  "properties": {
    "date:inception_lower":"1980-01-01",
    "date:inception_upper":"1980-01-31",
    "iso:country":"GB",
    "wof:name":"NE7 7EU",
    "wof:placetype":"postalcode"
},
  "geometry": {"coordinates":[-1.582047,54.994929],"type":"Point"}
}