{
  "type": "Feature",
  "properties": {
    "date:inception_lower": "1994-05-01",
    "date:inception_upper": "1994-05-01",
    "iso:country": "GB",
    "wof:name": "NE29 8LS",
    "wof:placetype": "postalcode"
  },
  "geometry": {"coordinates":[-1.466227,55.023079],"type":"Point"}
}
