{
  "type": "Feature",
  "properties": {
    "iso:country":"GB",
    "wof:name":"EX34 9RL",
    "wof:placetype":"postalcode"
},
  "geometry": {"coordinates":[-4.0950842403886,51.20160743740794],"type":"Point"}
}