{
  "type": "Feature",
  "properties": {
    "date:inception_lower": "1980-01-01",
    "date:inception_upper": "1980-01-01",
    "iso:country": "GB",
    "wof:name": "IP6 8JQ",
    "wof:placetype": "postalcode"
  },
  "geometry": {"coordinates":[1.049786,52.147378],"type":"Point"}
}
