{
  "type": "Feature",
  "properties": {
    "iso:country": "GB",
    "wof:name": "EN5 4SA",
    "wof:placetype": "postalcode"
  },
  "geometry": {"coordinates":[-0.188526,51.681824],"type":"Point"}
}
