{
  "type": "Feature",
  "properties": {
    "iso:country":"GB",
    "wof:name":"PR7 3LU",
    "wof:placetype":"postalcode"
},
  "geometry": {"coordinates":[-2.63211511327718,53.64810244793172],"type":"Point"}
}