{
  "type": "Feature",
  "properties": {
    "iso:country":"GB",
    "wof:name":"NR1 4AQ",
    "wof:placetype":"postalcode"
},
  "geometry": {"coordinates":[1.31715384333057,52.62581941566443],"type":"Point"}
}