{
  "type": "Feature",
  "properties": {
    "iso:country": "GB",
    "wof:name": "NR1 4AQ",
    "wof:placetype": "postalcode"
  },
  "geometry": {"coordinates":[1.317154,52.625819],"type":"Point"}
}
