{
  "type": "Feature",
  "properties": {
    "iso:country":"GB",
    "wof:name":"WV1 3NG",
    "wof:placetype":"postalcode"
},
  "geometry": {"coordinates":[-2.12803825830491,52.58521815777928],"type":"Point"}
}