{
  "type": "Feature",
  "properties": {
    "iso:country":"GB",
    "wof:name":"DY3 1PG",
    "wof:placetype":"postalcode"
},
  "geometry": {"coordinates":[-2.11703483298255,52.54361562689669],"type":"Point"}
}