{
  "type": "Feature",
  "properties": {
    "date:inception_lower":"1993-01-01",
    "date:inception_upper":"1993-01-31",
    "iso:country":"GB",
    "wof:name":"EC4M 7JH",
    "wof:placetype":"postalcode"
},
  "geometry": {"coordinates":[-0.103585,51.514033],"type":"Point"}
}