{
  "type": "Feature",
  "properties": {
    "iso:country":"GB",
    "wof:name":"BR6 8EF",
    "wof:placetype":"postalcode"
},
  "geometry": {"coordinates":[0.07640119931349,51.37102884056527],"type":"Point"}
}