{
  "type": "Feature",
  "properties": {
    "date:inception_lower": "2001-06-01",
    "date:inception_upper": "2001-06-01",
    "iso:country": "GB",
    "wof:name": "BA15 1BW",
    "wof:placetype": "postalcode"
  },
  "geometry": {"coordinates":[-2.250956,51.338378],"type":"Point"}
}
