{
  "type": "Feature",
  "properties": {
    "iso:country":"GB",
    "wof:name":"E17 8QB",
    "wof:placetype":"postalcode"
},
  "geometry": {"coordinates":[-0.02158113275818,51.5798084425325],"type":"Point"}
}