{
  "type": "Feature",
  "properties": {
    "iso:country":"GB",
    "wof:name":"NE63 0TE",
    "wof:placetype":"postalcode"
},
  "geometry": {"coordinates":[-1.55557939818894,55.16927353818349],"type":"Point"}
}