{
  "type": "Feature",
  "properties": {
    "iso:country": "GB",
    "wof:name": "WF6 1LD",
    "wof:placetype": "postalcode"
  },
  "geometry": {"coordinates":[-1.417203,53.687553],"type":"Point"}
}
