{
  "type": "Feature",
  "properties": {
    "iso:country":"GB",
    "wof:name":"FY5 1EA",
    "wof:placetype":"postalcode"
},
  "geometry": {"coordinates":[-3.04158275405697,53.8804673167067],"type":"Point"}
}