{
  "type": "Feature",
  "properties": {
    "iso:country": "GB",
    "wof:name": "IP21 4RT",
    "wof:placetype": "postalcode"
  },
  "geometry": {"coordinates":[1.245745,52.39802],"type":"Point"}
}
