{
  "type": "Feature",
  "properties": {
    "iso:country":"GB",
    "wof:name":"IP21 4RT",
    "wof:placetype":"postalcode"
},
  "geometry": {"coordinates":[1.24574514509548,52.39802048067511],"type":"Point"}
}