{
  "type": "Feature",
  "properties": {
    "iso:country": "GB",
    "wof:name": "NE61 3UP",
    "wof:placetype": "postalcode"
  },
  "geometry": {"coordinates":[-1.795859,55.126501],"type":"Point"}
}
