{
  "type": "Feature",
  "properties": {
    "iso:country":"GB",
    "wof:name":"NE61 3UP",
    "wof:placetype":"postalcode"
},
  "geometry": {"coordinates":[-1.79585862771775,55.12650085728549],"type":"Point"}
}