{
  "type": "Feature",
  "properties": {
    "iso:country":"GB",
    "wof:name":"SR5 2AS",
    "wof:placetype":"postalcode"
},
  "geometry": {"coordinates":[-1.40817538504583,54.91507335370937],"type":"Point"}
}