{
  "type": "Feature",
  "properties": {
    "iso:country": "GB",
    "wof:name": "G78 2EJ",
    "wof:placetype": "postalcode"
  },
  "geometry": {"coordinates":[-4.385926,55.7921],"type":"Point"}
}
