{
  "type": "Feature",
  "properties": {
    "iso:country":"GB",
    "wof:name":"G78 2EJ",
    "wof:placetype":"postalcode"
},
  "geometry": {"coordinates":[-4.38592633169404,55.79209956142391],"type":"Point"}
}