{
  "type": "Feature",
  "properties": {
    "iso:country":"GB",
    "wof:name":"SY4 4NZ",
    "wof:placetype":"postalcode"
},
  "geometry": {"coordinates":[-2.65497957323961,52.78782214673914],"type":"Point"}
}