{
  "type": "Feature",
  "properties": {
    "iso:country": "GB",
    "wof:name": "NE5 1DP",
    "wof:placetype": "postalcode"
  },
  "geometry": {"coordinates":[-1.711412,54.993713],"type":"Point"}
}
