{
  "type": "Feature",
  "properties": {
    "iso:country": "GB",
    "wof:name": "PO19 6TP",
    "wof:placetype": "postalcode"
  },
  "geometry": {"coordinates":[-0.766436,50.842467],"type":"Point"}
}
