{
  "type": "Feature",
  "properties": {
    "date:inception_lower":"2003-01-01",
    "date:inception_upper":"2003-01-31",
    "iso:country":"GB",
    "wof:name":"DN5 7FR",
    "wof:placetype":"postalcode"
},
  "geometry": {"coordinates":[-1.282978,53.515605],"type":"Point"}
}