{
  "type": "Feature",
  "properties": {
    "iso:country":"GB",
    "wof:name":"DN5 7FR",
    "wof:placetype":"postalcode"
},
  "geometry": {"coordinates":[-1.28299186478662,53.51558621912523],"type":"Point"}
}