{
  "type": "Feature",
  "properties": {
    "iso:country":"GB",
    "wof:name":"N9 0RH",
    "wof:placetype":"postalcode"
},
  "geometry": {"coordinates":[-0.05405356971435,51.62445057065828],"type":"Point"}
}