{
  "type": "Feature",
  "properties": {
    "iso:country": "GB",
    "wof:name": "SO41 9LB",
    "wof:placetype": "postalcode"
  },
  "geometry": {"coordinates":[-1.561674,50.759575],"type":"Point"}
}
