{
  "type": "Feature",
  "properties": {
    "iso:country":"GB",
    "wof:name":"PO31 8QP",
    "wof:placetype":"postalcode"
},
  "geometry": {"coordinates":[-1.31554084312528,50.7416106223598],"type":"Point"}
}