{
  "type": "Feature",
  "properties": {
    "iso:country": "GB",
    "wof:name": "PO31 8QP",
    "wof:placetype": "postalcode"
  },
  "geometry": {"coordinates":[-1.315573,50.74159],"type":"Point"}
}
