{
  "type": "Feature",
  "properties": {
    "iso:country":"GB",
    "wof:name":"SS14 1PR",
    "wof:placetype":"postalcode"
},
  "geometry": {"coordinates":[0.47566849102381,51.56924571197592],"type":"Point"}
}