{
  "type": "Feature",
  "properties": {
    "iso:country": "GB",
    "wof:name": "B5 7TD",
    "wof:placetype": "postalcode"
  },
  "geometry": {"coordinates":[-1.908156,52.456427],"type":"Point"}
}
