{
  "type": "Feature",
  "properties": {
    "iso:country":"GB",
    "wof:name":"FY5 4DL",
    "wof:placetype":"postalcode"
},
  "geometry": {"coordinates":[-3.00136716658311,53.87244157160608],"type":"Point"}
}