{
  "type": "Feature",
  "properties": {
    "iso:country":"GB",
    "wof:name":"TW5 9AD",
    "wof:placetype":"postalcode"
},
  "geometry": {"coordinates":[-0.38916597809174,51.47793655360704],"type":"Point"}
}