{
  "type": "Feature",
  "properties": {
    "iso:country":"GB",
    "wof:name":"LA9 5JP",
    "wof:placetype":"postalcode"
},
  "geometry": {"coordinates":[-2.74822672020361,54.31256569153939],"type":"Point"}
}