{
  "type": "Feature",
  "properties": {
    "date:inception_lower": "2019-06-01",
    "date:inception_upper": "2019-06-01",
    "iso:country": "GB",
    "wof:name": "ST5 9FN",
    "wof:placetype": "postalcode"
  },
  "geometry": {"coordinates":[-2.243168,53.022025],"type":"Point"}
}
