{
  "type": "Feature",
  "properties": {
    "iso:country": "GB",
    "wof:name": "TD1 1HE",
    "wof:placetype": "postalcode"
  },
  "geometry": {"coordinates":[-2.814728,55.617552],"type":"Point"}
}
