{
  "type": "Feature",
  "properties": {
    "iso:country":"GB",
    "wof:name":"HP10 8PF",
    "wof:placetype":"postalcode"
},
  "geometry": {"coordinates":[-0.68281439417206,51.61834245757902],"type":"Point"}
}