{
  "type": "Feature",
  "properties": {
    "date:inception_lower": "1980-01-01",
    "date:inception_upper": "1980-01-01",
    "iso:country": "GB",
    "wof:name": "HP10 8PF",
    "wof:placetype": "postalcode"
  },
  "geometry": {"coordinates":[-0.682795,51.618346],"type":"Point"}
}
