{
  "type": "Feature",
  "properties": {
    "iso:country": "GB",
    "wof:name": "HP10 8PF",
    "wof:placetype": "postalcode"
  },
  "geometry": {"coordinates":[-0.681439,51.618267],"type":"Point"}
}
