{
  "type": "Feature",
  "properties": {
    "iso:country": "GB",
    "wof:name": "PL7 4JZ",
    "wof:placetype": "postalcode"
  },
  "geometry": {"coordinates":[-4.06391,50.390829],"type":"Point"}
}
