{
  "type": "Feature",
  "properties": {
    "iso:country": "GB",
    "wof:name": "ST11 9PS",
    "wof:placetype": "postalcode"
  },
  "geometry": {"coordinates":[-2.05523,52.969423],"type":"Point"}
}
