{
  "type": "Feature",
  "properties": {
    "date:inception_lower": "1980-01-01",
    "date:inception_upper": "1980-01-01",
    "iso:country": "GB",
    "wof:name": "ST11 9PS",
    "wof:placetype": "postalcode"
  },
  "geometry": {"coordinates":[-2.05523,52.969423],"type":"Point"}
}
