{
  "type": "Feature",
  "properties": {
    "date:inception_lower": "1980-01-01",
    "date:inception_upper": "1980-01-01",
    "iso:country": "GB",
    "wof:name": "DN37 0NF",
    "wof:placetype": "postalcode"
  },
  "geometry": {"coordinates":[-0.09706,53.521282],"type":"Point"}
}
