{
  "type": "Feature",
  "properties": {
    "iso:country": "GB",
    "wof:name": "DN37 0NF",
    "wof:placetype": "postalcode"
  },
  "geometry": {"coordinates":[-0.09706,53.521282],"type":"Point"}
}
