{
  "type": "Feature",
  "properties": {
    "iso:country": "GB",
    "wof:name": "RM2 6RA",
    "wof:placetype": "postalcode"
  },
  "geometry": {"coordinates":[0.21302,51.588676],"type":"Point"}
}
