{
  "type": "Feature",
  "properties": {
    "iso:country":"GB",
    "wof:name":"RM2 6RA",
    "wof:placetype":"postalcode"
},
  "geometry": {"coordinates":[0.21301992830476,51.58867595600672],"type":"Point"}
}