{
  "type": "Feature",
  "properties": {
    "date:inception_lower":"1980-01-01",
    "date:inception_upper":"1980-01-31",
    "iso:country":"GB",
    "wof:name":"HP22 4HR",
    "wof:placetype":"postalcode"
},
  "geometry": {"coordinates":[-0.867156,51.882331],"type":"Point"}
}