{
  "type": "Feature",
  "properties": {
    "iso:country": "GB",
    "wof:name": "HP22 4HR",
    "wof:placetype": "postalcode"
  },
  "geometry": {"coordinates":[-0.867156,51.882331],"type":"Point"}
}
