{
  "type": "Feature",
  "properties": {
    "date:inception_lower": "1980-01-01",
    "date:inception_upper": "1980-01-01",
    "iso:country": "GB",
    "wof:name": "KT18 5HT",
    "wof:placetype": "postalcode"
  },
  "geometry": {"coordinates":[-0.262301,51.328],"type":"Point"}
}
