{
  "type": "Feature",
  "properties": {
    "iso:country":"GB",
    "wof:name":"NW10 7SY",
    "wof:placetype":"postalcode"
},
  "geometry": {"coordinates":[-0.28235721238814,51.53732594888073],"type":"Point"}
}