{
  "type": "Feature",
  "properties": {
    "date:inception_lower": "1985-10-01",
    "date:inception_upper": "1985-10-01",
    "iso:country": "GB",
    "wof:name": "NW10 7SY",
    "wof:placetype": "postalcode"
  },
  "geometry": {"coordinates":[-0.282357,51.537326],"type":"Point"}
}
