{
  "type": "Feature",
  "properties": {
    "iso:country":"GB",
    "wof:name":"SO17 1QQ",
    "wof:placetype":"postalcode"
},
  "geometry": {"coordinates":[-1.39891601753342,50.92639118026491],"type":"Point"}
}