{
  "type": "Feature",
  "properties": {
    "iso:country": "GB",
    "wof:name": "SO17 1QQ",
    "wof:placetype": "postalcode"
  },
  "geometry": {"coordinates":[-1.398916,50.926391],"type":"Point"}
}
