{
  "type": "Feature",
  "properties": {
    "date:inception_lower": "2021-11-01",
    "date:inception_upper": "2021-11-01",
    "iso:country": "GB",
    "wof:name": "MK42 6FP",
    "wof:placetype": "postalcode"
  },
  "geometry": {"coordinates":[-0.466158,52.084532],"type":"Point"}
}
