{
  "type": "Feature",
  "properties": {
    "date:inception_lower": "2020-01-01",
    "date:inception_upper": "2020-01-01",
    "iso:country": "GB",
    "wof:name": "IP13 9FX",
    "wof:placetype": "postalcode"
  },
  "geometry": {"coordinates":[1.346576,52.214866],"type":"Point"}
}
