{
  "type": "Feature",
  "properties": {
    "iso:country":"GB",
    "wof:name":"AL10 0AL",
    "wof:placetype":"postalcode"
},
  "geometry": {"coordinates":[-0.2231812379942,51.77239141168503],"type":"Point"}
}