{
  "type": "Feature",
  "properties": {
    "iso:country":"GB",
    "wof:name":"HR1 1FA",
    "wof:placetype":"postalcode"
},
  "geometry": {"coordinates":[-2.71395779728943,52.07765984356945],"type":"Point"}
}