{
  "type": "Feature",
  "properties": {
    "date:inception_lower":"2015-12-01",
    "date:inception_upper":"2015-12-31",
    "iso:country":"GB",
    "wof:name":"HR1 1FA",
    "wof:placetype":"postalcode"
},
  "geometry": {"coordinates":[-2.713481,52.077869],"type":"Point"}
}