{
  "type": "Feature",
  "properties": {
    "iso:country": "GB",
    "wof:name": "HR1 1FA",
    "wof:placetype": "postalcode"
  },
  "geometry": {"coordinates":[-2.713481,52.077869],"type":"Point"}
}
