{
  "type": "Feature",
  "properties": {
    "iso:country":"GB",
    "wof:name":"B5 7AH",
    "wof:placetype":"postalcode"
},
  "geometry": {"coordinates":[-1.89932143760037,52.47157694984842],"type":"Point"}
}