{
  "type": "Feature",
  "properties": {
    "date:inception_lower": "1980-01-01",
    "date:inception_upper": "1980-01-01",
    "iso:country": "GB",
    "wof:name": "B5 7AH",
    "wof:placetype": "postalcode"
  },
  "geometry": {"coordinates":[-1.899302,52.47152],"type":"Point"}
}
