{
  "type": "Feature",
  "properties": {
    "iso:country":"GB",
    "wof:name":"NE13 6AW",
    "wof:placetype":"postalcode"
},
  "geometry": {"coordinates":[-1.62970014293375,55.05136335573501],"type":"Point"}
}