{
  "type": "Feature",
  "properties": {
    "date:inception_lower":"1980-01-01",
    "date:inception_upper":"1980-01-31",
    "iso:country":"GB",
    "wof:name":"NE13 6AW",
    "wof:placetype":"postalcode"
},
  "geometry": {"coordinates":[-1.6297,55.051363],"type":"Point"}
}