{
  "type": "Feature",
  "properties": {
    "date:inception_lower": "1980-01-01",
    "date:inception_upper": "1980-01-01",
    "iso:country": "GB",
    "wof:name": "G21 1SX",
    "wof:placetype": "postalcode"
  },
  "geometry": {"coordinates":[-4.23777,55.879584],"type":"Point"}
}
