{
  "type": "Feature",
  "properties": {
    "iso:country": "GB",
    "wof:name": "G21 1SX",
    "wof:placetype": "postalcode"
  },
  "geometry": {"coordinates":[-4.23777,55.879584],"type":"Point"}
}
