{
  "type": "Feature",
  "properties": {
    "date:inception_lower": "1980-01-01",
    "date:inception_upper": "1980-01-01",
    "iso:country": "GB",
    "wof:name": "PR8 4RZ",
    "wof:placetype": "postalcode"
  },
  "geometry": {"coordinates":[-3.017481,53.623029],"type":"Point"}
}
