{
  "type": "Feature",
  "properties": {
    "iso:country":"GB",
    "wof:name":"PR8 4RZ",
    "wof:placetype":"postalcode"
},
  "geometry": {"coordinates":[-3.01748132900066,53.62302915377827],"type":"Point"}
}