{
  "type": "Feature",
  "properties": {
    "iso:country":"GB",
    "wof:name":"TR11 4LJ",
    "wof:placetype":"postalcode"
},
  "geometry": {"coordinates":[-5.09823215661227,50.15665744996908],"type":"Point"}
}