{
  "type": "Feature",
  "properties": {
    "iso:country": "GB",
    "wof:name": "WV16 5DQ",
    "wof:placetype": "postalcode"
  },
  "geometry": {"coordinates":[-2.430761,52.530339],"type":"Point"}
}
