{
  "type": "Feature",
  "properties": {
    "iso:country":"GB",
    "wof:name":"BD13 5JQ",
    "wof:placetype":"postalcode"
},
  "geometry": {"coordinates":[-1.89533640466466,53.83216623806297],"type":"Point"}
}