{
  "type": "Feature",
  "properties": {
    "iso:country":"GB",
    "wof:name":"CF5 5QP",
    "wof:placetype":"postalcode"
},
  "geometry": {"coordinates":[-3.25939271099363,51.47034398744505],"type":"Point"}
}