{
  "type": "Feature",
  "properties": {
    "date:inception_lower":"1980-01-01",
    "date:inception_upper":"1980-01-31",
    "iso:country":"GB",
    "wof:name":"CF5 5QP",
    "wof:placetype":"postalcode"
},
  "geometry": {"coordinates":[-3.259393,51.470344],"type":"Point"}
}