{
  "type": "Feature",
  "properties": {
    "iso:country":"GB",
    "wof:name":"CO7 0SY",
    "wof:placetype":"postalcode"
},
  "geometry": {"coordinates":[1.03434235890307,51.81365882198536],"type":"Point"}
}