{
  "type": "Feature",
  "properties": {
    "date:inception_lower":"1990-07-01",
    "date:inception_upper":"1990-07-31",
    "iso:country":"GB",
    "wof:name":"CO7 0SY",
    "wof:placetype":"postalcode"
},
  "geometry": {"coordinates":[1.034342,51.813659],"type":"Point"}
}