{
  "type": "Feature",
  "properties": {
    "date:inception_lower": "1998-12-01",
    "date:inception_upper": "1998-12-01",
    "iso:country": "GB",
    "wof:name": "EX24 6DU",
    "wof:placetype": "postalcode"
  },
  "geometry": {"coordinates":[-3.10999,50.751426],"type":"Point"}
}
