{
  "type": "Feature",
  "properties": {
    "date:inception_lower": "2016-06-01",
    "date:inception_upper": "2016-06-01",
    "iso:country": "GB",
    "wof:name": "PL2 3FG",
    "wof:placetype": "postalcode"
  },
  "geometry": {"coordinates":[-4.147965,50.398099],"type":"Point"}
}
