{
  "type": "Feature",
  "properties": {
    "iso:country":"GB",
    "wof:name":"CM20 1NS",
    "wof:placetype":"postalcode"
},
  "geometry": {"coordinates":[0.09033544556507,51.77672977756145],"type":"Point"}
}