{
  "type": "Feature",
  "properties": {
    "iso:country":"GB",
    "wof:name":"NE24 3RS",
    "wof:placetype":"postalcode"
},
  "geometry": {"coordinates":[-1.51949096698934,55.10765414079064],"type":"Point"}
}