{
  "type": "Feature",
  "properties": {
    "iso:country":"GB",
    "wof:name":"CT9 2NF",
    "wof:placetype":"postalcode"
},
  "geometry": {"coordinates":[1.40125929929841,51.38389713592328],"type":"Point"}
}