{
  "type": "Feature",
  "properties": {
    "date:inception_lower":"2004-02-01",
    "date:inception_upper":"2004-02-29",
    "iso:country":"GB",
    "wof:name":"HR6 8FD",
    "wof:placetype":"postalcode"
},
  "geometry": {"coordinates":[-2.7413,52.232339],"type":"Point"}
}