{
  "type": "Feature",
  "properties": {
    "iso:country":"GB",
    "wof:name":"HR6 8FD",
    "wof:placetype":"postalcode"
},
  "geometry": {"coordinates":[-2.74130013557384,52.2323278257282],"type":"Point"}
}