{
  "type": "Feature",
  "properties": {
    "iso:country":"GB",
    "wof:name":"S60 1ND",
    "wof:placetype":"postalcode"
},
  "geometry": {"coordinates":[-1.35852559108228,53.43108181541561],"type":"Point"}
}