{
  "type": "Feature",
  "properties": {
    "date:inception_lower": "1987-04-01",
    "date:inception_upper": "1987-04-01",
    "iso:country": "GB",
    "wof:name": "S60 1ND",
    "wof:placetype": "postalcode"
  },
  "geometry": {"coordinates":[-1.358584,53.431208],"type":"Point"}
}
