{
  "type": "Feature",
  "properties": {
    "date:inception_lower": "1980-01-01",
    "date:inception_upper": "1980-01-01",
    "iso:country": "GB",
    "wof:name": "SL2 2NH",
    "wof:placetype": "postalcode"
  },
  "geometry": {"coordinates":[-0.647973,51.531795],"type":"Point"}
}
