{
  "type": "Feature",
  "properties": {
    "iso:country": "GB",
    "wof:name": "SR7 9JW",
    "wof:placetype": "postalcode"
  },
  "geometry": {"coordinates":[-1.384253,54.820506],"type":"Point"}
}
