{
  "type": "Feature",
  "properties": {
    "iso:country":"GB",
    "wof:name":"SR7 9JW",
    "wof:placetype":"postalcode"
},
  "geometry": {"coordinates":[-1.38425269016,54.82050617634373],"type":"Point"}
}