{
  "type": "Feature",
  "properties": {
    "iso:country":"GB",
    "wof:name":"SW5 9TT",
    "wof:placetype":"postalcode"
},
  "geometry": {"coordinates":[-0.19303626543257,51.49087806998899],"type":"Point"}
}