{
  "type": "Feature",
  "properties": {
    "date:inception_lower":"1980-01-01",
    "date:inception_upper":"1980-01-31",
    "iso:country":"GB",
    "wof:name":"SW5 9TT",
    "wof:placetype":"postalcode"
},
  "geometry": {"coordinates":[-0.193036,51.490878],"type":"Point"}
}