{
  "type": "Feature",
  "properties": {
    "iso:country":"GB",
    "wof:name":"RM3 8JP",
    "wof:placetype":"postalcode"
},
  "geometry": {"coordinates":[0.2145054729695,51.5975508486181],"type":"Point"}
}