{
  "type": "Feature",
  "properties": {
    "date:inception_lower": "1980-01-01",
    "date:inception_upper": "1980-01-01",
    "iso:country": "GB",
    "wof:name": "RM3 8JP",
    "wof:placetype": "postalcode"
  },
  "geometry": {"coordinates":[0.214369,51.597484],"type":"Point"}
}
