{
  "type": "Feature",
  "properties": {
    "date:inception_lower": "2020-02-01",
    "date:inception_upper": "2020-02-01",
    "iso:country": "GB",
    "wof:name": "EX1 3LQ",
    "wof:placetype": "postalcode"
  },
  "geometry": {"coordinates":[-3.461241,50.74462],"type":"Point"}
}
