{
  "type": "Feature",
  "properties": {
    "iso:country": "GB",
    "wof:name": "EX1 3LQ",
    "wof:placetype": "postalcode"
  },
  "geometry": {"coordinates":[-3.461241,50.74462],"type":"Point"}
}
