{
  "type": "Feature",
  "properties": {
    "iso:country": "GB",
    "wof:name": "WS15 4PA",
    "wof:placetype": "postalcode"
  },
  "geometry": {"coordinates":[-1.882731,52.726161],"type":"Point"}
}
