{
  "type": "Feature",
  "properties": {
    "date:inception_lower":"1990-02-01",
    "date:inception_upper":"1990-02-28",
    "iso:country":"GB",
    "wof:name":"EN3 6BH",
    "wof:placetype":"postalcode"
},
  "geometry": {"coordinates":[-0.033218,51.671925],"type":"Point"}
}