{
  "type": "Feature",
  "properties": {
    "iso:country": "GB",
    "wof:name": "SA47 0PN",
    "wof:placetype": "postalcode"
  },
  "geometry": {"coordinates":[-4.307362,52.166081],"type":"Point"}
}
