{
  "type": "Feature",
  "properties": {
    "iso:country":"GB",
    "wof:name":"SA47 0PN",
    "wof:placetype":"postalcode"
},
  "geometry": {"coordinates":[-4.30736178877977,52.16608051692776],"type":"Point"}
}