{
  "type": "Feature",
  "properties": {
    "date:inception_lower": "2002-09-01",
    "date:inception_upper": "2002-09-01",
    "iso:country": "GB",
    "wof:name": "BS8 2SA",
    "wof:placetype": "postalcode"
  },
  "geometry": {"coordinates":[-2.613836,51.469459],"type":"Point"}
}
