{
  "type": "Feature",
  "properties": {
    "date:inception_lower": "2011-02-01",
    "date:inception_upper": "2011-02-01",
    "iso:country": "GB",
    "wof:name": "SO40 2AW",
    "wof:placetype": "postalcode"
  },
  "geometry": {"coordinates":[-1.509464,50.92485],"type":"Point"}
}
