{
  "type": "Feature",
  "properties": {
    "iso:country":"GB",
    "wof:name":"SO40 2AW",
    "wof:placetype":"postalcode"
},
  "geometry": {"coordinates":[-1.50943046543123,50.92480327512946],"type":"Point"}
}