{
  "type": "Feature",
  "properties": {
    "date:inception_lower":"1980-01-01",
    "date:inception_upper":"1980-01-31",
    "iso:country":"GB",
    "wof:name":"SA14 9SS",
    "wof:placetype":"postalcode"
},
  "geometry": {"coordinates":[-4.101251,51.671376],"type":"Point"}
}