{
  "type": "Feature",
  "properties": {
    "iso:country":"GB",
    "wof:name":"SA14 9SS",
    "wof:placetype":"postalcode"
},
  "geometry": {"coordinates":[-4.10125123362811,51.67137611207117],"type":"Point"}
}