{
  "type": "Feature",
  "properties": {
    "date:inception_lower": "1980-01-01",
    "date:inception_upper": "1980-01-01",
    "iso:country": "GB",
    "wof:name": "CT13 9PA",
    "wof:placetype": "postalcode"
  },
  "geometry": {"coordinates":[1.361999,51.269929],"type":"Point"}
}
