{
  "type": "Feature",
  "properties": {
    "iso:country": "GB",
    "wof:name": "CT13 9PA",
    "wof:placetype": "postalcode"
  },
  "geometry": {"coordinates":[1.361984,51.269912],"type":"Point"}
}
