{
  "type": "Feature",
  "properties": {
    "iso:country":"GB",
    "wof:name":"CT13 9PA",
    "wof:placetype":"postalcode"
},
  "geometry": {"coordinates":[1.36198437208053,51.26991213952507],"type":"Point"}
}