{
  "type": "Feature",
  "properties": {
    "iso:country":"GB",
    "wof:name":"AL4 0HQ",
    "wof:placetype":"postalcode"
},
  "geometry": {"coordinates":[-0.26422005627173,51.7522240168618],"type":"Point"}
}