{
  "type": "Feature",
  "properties": {
    "iso:country": "GB",
    "wof:name": "WD25 9RP",
    "wof:placetype": "postalcode"
  },
  "geometry": {"coordinates":[-0.378789,51.678957],"type":"Point"}
}
