{
  "type": "Feature",
  "properties": {
    "iso:country":"GB",
    "wof:name":"WD25 9RP",
    "wof:placetype":"postalcode"
},
  "geometry": {"coordinates":[-0.37878865128811,51.67895713037353],"type":"Point"}
}