{
  "type": "Feature",
  "properties": {
    "iso:country":"GB",
    "wof:name":"W5 4LP",
    "wof:placetype":"postalcode"
},
  "geometry": {"coordinates":[-0.28961280487811,51.50378264428569],"type":"Point"}
}