{
  "type": "Feature",
  "properties": {
    "iso:country":"GB",
    "wof:name":"HP11 1AL",
    "wof:placetype":"postalcode"
},
  "geometry": {"coordinates":[-0.71261847921533,51.61305313661441],"type":"Point"}
}