{
  "type": "Feature",
  "properties": {
    "date:inception_lower": "2000-06-01",
    "date:inception_upper": "2000-06-01",
    "iso:country": "GB",
    "wof:name": "PE27 3FG",
    "wof:placetype": "postalcode"
  },
  "geometry": {"coordinates":[-0.071662,52.340923],"type":"Point"}
}
