{
  "type": "Feature",
  "properties": {
    "iso:country":"GB",
    "wof:name":"TR9 6PS",
    "wof:placetype":"postalcode"
},
  "geometry": {"coordinates":[-4.93764530875406,50.39484352407251],"type":"Point"}
}