{
  "type": "Feature",
  "properties": {
    "iso:country": "GB",
    "wof:name": "PH11 8HS",
    "wof:placetype": "postalcode"
  },
  "geometry": {"coordinates":[-3.229696,56.66827],"type":"Point"}
}
