{
  "type": "Feature",
  "properties": {
    "iso:country":"GB",
    "wof:name":"CR0 6YG",
    "wof:placetype":"postalcode"
},
  "geometry": {"coordinates":[-0.07409337710856,51.38965173807112],"type":"Point"}
}