{
  "type": "Feature",
  "properties": {
    "iso:country":"GB",
    "wof:name":"EN3 5JR",
    "wof:placetype":"postalcode"
},
  "geometry": {"coordinates":[-0.04255681626841,51.6629629094399],"type":"Point"}
}