{
  "type": "Feature",
  "properties": {
    "iso:country":"GB",
    "wof:name":"SR7 0LT",
    "wof:placetype":"postalcode"
},
  "geometry": {"coordinates":[-1.38647549705315,54.84328042609607],"type":"Point"}
}