{
  "type": "Feature",
  "properties": {
    "iso:country": "GB",
    "wof:name": "HP5 3DL",
    "wof:placetype": "postalcode"
  },
  "geometry": {"coordinates":[-0.598407,51.716077],"type":"Point"}
}
