{
  "type": "Feature",
  "properties": {
    "date:inception_lower":"1980-01-01",
    "date:inception_upper":"1980-01-31",
    "iso:country":"GB",
    "wof:name":"HP5 3DL",
    "wof:placetype":"postalcode"
},
  "geometry": {"coordinates":[-0.598407,51.716077],"type":"Point"}
}