{
  "type": "Feature",
  "properties": {
    "iso:country":"GB",
    "wof:name":"SW16 3LT",
    "wof:placetype":"postalcode"
},
  "geometry": {"coordinates":[-0.12237907583082,51.41442793117165],"type":"Point"}
}