{
  "type": "Feature",
  "properties": {
    "iso:country": "GB",
    "wof:name": "EH33 1JY",
    "wof:placetype": "postalcode"
  },
  "geometry": {"coordinates":[-2.952974,55.947984],"type":"Point"}
}
