{
  "type": "Feature",
  "properties": {
    "iso:country":"GB",
    "wof:name":"DA12 4UL",
    "wof:placetype":"postalcode"
},
  "geometry": {"coordinates":[0.40965315932742,51.43144982650463],"type":"Point"}
}