{
  "type": "Feature",
  "properties": {
    "date:inception_lower": "1980-01-01",
    "date:inception_upper": "1980-01-01",
    "iso:country": "GB",
    "wof:name": "DA12 4UL",
    "wof:placetype": "postalcode"
  },
  "geometry": {"coordinates":[0.40971,51.431423],"type":"Point"}
}
