{
  "type": "Feature",
  "properties": {
    "iso:country":"GB",
    "wof:name":"WF2 0UL",
    "wof:placetype":"postalcode"
},
  "geometry": {"coordinates":[-1.53604119505828,53.69154168922052],"type":"Point"}
}