{
  "type": "Feature",
  "properties": {
    "iso:country":"GB",
    "wof:name":"ST5 3RX",
    "wof:placetype":"postalcode"
},
  "geometry": {"coordinates":[-2.22936074622093,52.99913043693477],"type":"Point"}
}