{
  "type": "Feature",
  "properties": {
    "date:inception_lower": "2011-10-01",
    "date:inception_upper": "2011-10-01",
    "iso:country": "GB",
    "wof:name": "PO7 7JQ",
    "wof:placetype": "postalcode"
  },
  "geometry": {"coordinates":[-1.047458,50.890071],"type":"Point"}
}
