{
  "type": "Feature",
  "properties": {
    "iso:country":"GB",
    "wof:name":"PO7 7JQ",
    "wof:placetype":"postalcode"
},
  "geometry": {"coordinates":[-1.04745835611693,50.89007070020083],"type":"Point"}
}