{
  "type": "Feature",
  "properties": {
    "iso:country":"GB",
    "wof:name":"TR19 6BL",
    "wof:placetype":"postalcode"
},
  "geometry": {"coordinates":[-5.57440248968754,50.06231619550373],"type":"Point"}
}