{
  "type": "Feature",
  "properties": {
    "iso:country":"GB",
    "wof:name":"M12 4QD",
    "wof:placetype":"postalcode"
},
  "geometry": {"coordinates":[-2.19497597128004,53.45134832930843],"type":"Point"}
}