{
  "type": "Feature",
  "properties": {
    "iso:country":"GB",
    "wof:name":"SG4 8SD",
    "wof:placetype":"postalcode"
},
  "geometry": {"coordinates":[-0.29488825056696,51.85185394582066],"type":"Point"}
}