{
  "type": "Feature",
  "properties": {
    "iso:country": "GB",
    "wof:name": "SS17 0FU",
    "wof:placetype": "postalcode"
  },
  "geometry": {"coordinates":[0.418598,51.508646],"type":"Point"}
}
