{
  "type": "Feature",
  "properties": {
    "iso:country":"GB",
    "wof:name":"MK19 7AQ",
    "wof:placetype":"postalcode"
},
  "geometry": {"coordinates":[-0.80675892335974,52.07637592012151],"type":"Point"}
}