{
  "type": "Feature",
  "properties": {
    "date:inception_lower": "2005-02-01",
    "date:inception_upper": "2005-02-01",
    "iso:country": "GB",
    "wof:name": "SS14 0SD",
    "wof:placetype": "postalcode"
  },
  "geometry": {"coordinates":[0.454346,51.57044],"type":"Point"}
}
