{
  "type": "Feature",
  "properties": {
    "iso:country":"GB",
    "wof:name":"B11 1PR",
    "wof:placetype":"postalcode"
},
  "geometry": {"coordinates":[-1.86439222038621,52.46053840461946],"type":"Point"}
}