{
  "type": "Feature",
  "properties": {
    "iso:country": "GB",
    "wof:name": "B11 1PR",
    "wof:placetype": "postalcode"
  },
  "geometry": {"coordinates":[-1.864392,52.460538],"type":"Point"}
}
