{
  "type": "Feature",
  "properties": {
    "iso:country":"GB",
    "wof:name":"M19 1JA",
    "wof:placetype":"postalcode"
},
  "geometry": {"coordinates":[-2.19490016652643,53.42823898963163],"type":"Point"}
}