{
  "type": "Feature",
  "properties": {
    "date:inception_lower":"1980-01-01",
    "date:inception_upper":"1980-01-31",
    "iso:country":"GB",
    "wof:name":"M19 1JA",
    "wof:placetype":"postalcode"
},
  "geometry": {"coordinates":[-2.1949,53.428239],"type":"Point"}
}