{
  "type": "Feature",
  "properties": {
    "iso:country":"GB",
    "wof:name":"HU11 5EE",
    "wof:placetype":"postalcode"
},
  "geometry": {"coordinates":[-0.27805860114864,53.83504785775863],"type":"Point"}
}