{
  "type": "Feature",
  "properties": {
    "iso:country":"GB",
    "wof:name":"RM14 1NJ",
    "wof:placetype":"postalcode"
},
  "geometry": {"coordinates":[0.27320061811174,51.57062776426328],"type":"Point"}
}