{
  "type": "Feature",
  "properties": {
    "iso:country": "GB",
    "wof:name": "RM14 1NJ",
    "wof:placetype": "postalcode"
  },
  "geometry": {"coordinates":[0.273228,51.570621],"type":"Point"}
}
