{
  "type": "Feature",
  "properties": {
    "iso:country": "GB",
    "wof:name": "WD24 7RE",
    "wof:placetype": "postalcode"
  },
  "geometry": {"coordinates":[-0.391637,51.676963],"type":"Point"}
}
