{
  "type": "Feature",
  "properties": {
    "iso:country":"GB",
    "wof:name":"HD1 5QP",
    "wof:placetype":"postalcode"
},
  "geometry": {"coordinates":[-1.79521346119607,53.65284246697563],"type":"Point"}
}