{
  "type": "Feature",
  "properties": {
    "iso:country":"GB",
    "wof:name":"SS17 9JS",
    "wof:placetype":"postalcode"
},
  "geometry": {"coordinates":[0.47432499493949,51.52935287560638],"type":"Point"}
}