{
  "type": "Feature",
  "properties": {
    "iso:country": "GB",
    "wof:name": "SS17 9JS",
    "wof:placetype": "postalcode"
  },
  "geometry": {"coordinates":[0.474325,51.529353],"type":"Point"}
}
