{
  "type": "Feature",
  "properties": {
    "iso:country": "GB",
    "wof:name": "DN22 0AZ",
    "wof:placetype": "postalcode"
  },
  "geometry": {"coordinates":[-0.828402,53.329294],"type":"Point"}
}
