{
  "type": "Feature",
  "properties": {
    "iso:country":"GB",
    "wof:name":"DN22 0AZ",
    "wof:placetype":"postalcode"
},
  "geometry": {"coordinates":[-0.82840177479751,53.32929366078659],"type":"Point"}
}