{
  "type": "Feature",
  "properties": {
    "iso:country":"GB",
    "wof:name":"NP11 6QN",
    "wof:placetype":"postalcode"
},
  "geometry": {"coordinates":[-3.09028955346087,51.60768852118986],"type":"Point"}
}