{
  "type": "Feature",
  "properties": {
    "iso:country": "GB",
    "wof:name": "BS36 2US",
    "wof:placetype": "postalcode"
  },
  "geometry": {"coordinates":[-2.467286,51.511047],"type":"Point"}
}
