{
  "type": "Feature",
  "properties": {
    "iso:country":"GB",
    "wof:name":"BS36 2US",
    "wof:placetype":"postalcode"
},
  "geometry": {"coordinates":[-2.46728604725252,51.51104674609524],"type":"Point"}
}