{
  "type": "Feature",
  "properties": {
    "iso:country":"GB",
    "wof:name":"SL9 0NN",
    "wof:placetype":"postalcode"
},
  "geometry": {"coordinates":[-0.55725860502295,51.62028373622477],"type":"Point"}
}