{
  "type": "Feature",
  "properties": {
    "date:inception_lower":"1980-01-01",
    "date:inception_upper":"1980-01-31",
    "iso:country":"GB",
    "wof:name":"SL9 0NN",
    "wof:placetype":"postalcode"
},
  "geometry": {"coordinates":[-0.557259,51.620284],"type":"Point"}
}