{
  "type": "Feature",
  "properties": {
    "iso:country": "GB",
    "wof:name": "SL9 0NN",
    "wof:placetype": "postalcode"
  },
  "geometry": {"coordinates":[-0.557259,51.620284],"type":"Point"}
}
