{
  "type": "Feature",
  "properties": {
    "date:inception_lower":"2003-01-01",
    "date:inception_upper":"2003-01-31",
    "iso:country":"GB",
    "wof:name":"BD13 2LY",
    "wof:placetype":"postalcode"
},
  "geometry": {"coordinates":[-1.851589,53.759992],"type":"Point"}
}