{
  "type": "Feature",
  "properties": {
    "date:inception_lower": "1994-05-01",
    "date:inception_upper": "1994-05-01",
    "iso:country": "GB",
    "wof:name": "M11 4NP",
    "wof:placetype": "postalcode"
  },
  "geometry": {"coordinates":[-2.181683,53.487413],"type":"Point"}
}
