{
  "type": "Feature",
  "properties": {
    "iso:country":"GB",
    "wof:name":"M11 4NP",
    "wof:placetype":"postalcode"
},
  "geometry": {"coordinates":[-2.18168342528456,53.48741305520447],"type":"Point"}
}