{
  "type": "Feature",
  "properties": {
    "date:inception_lower": "1980-01-01",
    "date:inception_upper": "1980-01-01",
    "iso:country": "GB",
    "wof:name": "S64 9EF",
    "wof:placetype": "postalcode"
  },
  "geometry": {"coordinates":[-1.300587,53.496581],"type":"Point"}
}
