{
  "type": "Feature",
  "properties": {
    "date:inception_lower":"1980-01-01",
    "date:inception_upper":"1980-01-31",
    "iso:country":"GB",
    "wof:name":"SW8 4UB",
    "wof:placetype":"postalcode"
},
  "geometry": {"coordinates":[-0.136593,51.472344],"type":"Point"}
}