{
  "type": "Feature",
  "properties": {
    "iso:country": "GB",
    "wof:name": "SW8 4UB",
    "wof:placetype": "postalcode"
  },
  "geometry": {"coordinates":[-0.136593,51.472344],"type":"Point"}
}
