{
  "type": "Feature",
  "properties": {
    "iso:country":"GB",
    "wof:name":"SW8 4UB",
    "wof:placetype":"postalcode"
},
  "geometry": {"coordinates":[-0.13661875150331,51.47234278341564],"type":"Point"}
}