{
  "type": "Feature",
  "properties": {
    "iso:country": "GB",
    "wof:name": "M15 4AS",
    "wof:placetype": "postalcode"
  },
  "geometry": {"coordinates":[-2.257227,53.461621],"type":"Point"}
}
