{
  "type": "Feature",
  "properties": {
    "iso:country":"GB",
    "wof:name":"NP23 5BP",
    "wof:placetype":"postalcode"
},
  "geometry": {"coordinates":[-3.22878307183217,51.79800375634451],"type":"Point"}
}