{
  "type": "Feature",
  "properties": {
    "date:inception_lower": "1999-06-01",
    "date:inception_upper": "1999-06-01",
    "iso:country": "GB",
    "wof:name": "NP23 5BP",
    "wof:placetype": "postalcode"
  },
  "geometry": {"coordinates":[-3.228783,51.798004],"type":"Point"}
}
