{
  "type": "Feature",
  "properties": {
    "iso:country": "GB",
    "wof:name": "ME7 4RH",
    "wof:placetype": "postalcode"
  },
  "geometry": {"coordinates":[0.54636,51.384023],"type":"Point"}
}
