{
  "type": "Feature",
  "properties": {
    "date:inception_lower": "1990-07-01",
    "date:inception_upper": "1990-07-01",
    "iso:country": "GB",
    "wof:name": "ME7 4RH",
    "wof:placetype": "postalcode"
  },
  "geometry": {"coordinates":[0.54636,51.384023],"type":"Point"}
}
