{
  "type": "Feature",
  "properties": {
    "iso:country": "GB",
    "wof:name": "AB23 8GL",
    "wof:placetype": "postalcode"
  },
  "geometry": {"coordinates":[-2.103516,57.198818],"type":"Point"}
}
