{
  "type": "Feature",
  "properties": {
    "date:inception_lower":"1990-08-01",
    "date:inception_upper":"1990-08-31",
    "iso:country":"GB",
    "wof:name":"AB23 8GL",
    "wof:placetype":"postalcode"
},
  "geometry": {"coordinates":[-2.103516,57.198818],"type":"Point"}
}