{
  "type": "Feature",
  "properties": {
    "iso:country": "GB",
    "wof:name": "NW1 1SR",
    "wof:placetype": "postalcode"
  },
  "geometry": {"coordinates":[-0.132823,51.531786],"type":"Point"}
}
