{
  "type": "Feature",
  "properties": {
    "iso:country": "GB",
    "wof:name": "LE16 9SD",
    "wof:placetype": "postalcode"
  },
  "geometry": {"coordinates":[-0.952283,52.426436],"type":"Point"}
}
