{
  "type": "Feature",
  "properties": {
    "iso:country":"GB",
    "wof:name":"LE16 9SD",
    "wof:placetype":"postalcode"
},
  "geometry": {"coordinates":[-0.95228283313867,52.42643563119515],"type":"Point"}
}