{
  "type": "Feature",
  "properties": {
    "date:inception_lower":"1980-01-01",
    "date:inception_upper":"1980-01-31",
    "iso:country":"GB",
    "wof:name":"LE16 9SD",
    "wof:placetype":"postalcode"
},
  "geometry": {"coordinates":[-0.952283,52.426436],"type":"Point"}
}