{
  "type": "Feature",
  "properties": {
    "iso:country": "GB",
    "wof:name": "L26 9TX",
    "wof:placetype": "postalcode"
  },
  "geometry": {"coordinates":[-2.818946,53.356247],"type":"Point"}
}
