{
  "type": "Feature",
  "properties": {
    "iso:country":"GB",
    "wof:name":"L26 9TX",
    "wof:placetype":"postalcode"
},
  "geometry": {"coordinates":[-2.81876943848851,53.35645725024515],"type":"Point"}
}