{
  "type": "Feature",
  "properties": {
    "iso:country":"GB",
    "wof:name":"SP11 9HQ",
    "wof:placetype":"postalcode"
},
  "geometry": {"coordinates":[-1.55502864652837,51.23921709089883],"type":"Point"}
}