{
  "type": "Feature",
  "properties": {
    "iso:country": "GB",
    "wof:name": "SP11 9HQ",
    "wof:placetype": "postalcode"
  },
  "geometry": {"coordinates":[-1.555029,51.239217],"type":"Point"}
}
