{
  "type": "Feature",
  "properties": {
    "date:inception_lower": "2007-03-01",
    "date:inception_upper": "2007-03-01",
    "iso:country": "GB",
    "wof:name": "SP11 9HQ",
    "wof:placetype": "postalcode"
  },
  "geometry": {"coordinates":[-1.555029,51.239217],"type":"Point"}
}
