{
  "type": "Feature",
  "properties": {
    "iso:country":"GB",
    "wof:name":"ST10 2QE",
    "wof:placetype":"postalcode"
},
  "geometry": {"coordinates":[-1.96954587254977,53.04455464084571],"type":"Point"}
}