{
  "type": "Feature",
  "properties": {
    "date:inception_lower": "1992-08-01",
    "date:inception_upper": "1992-08-01",
    "iso:country": "GB",
    "wof:name": "ST10 2QE",
    "wof:placetype": "postalcode"
  },
  "geometry": {"coordinates":[-1.969588,53.044725],"type":"Point"}
}
