{
  "type": "Feature",
  "properties": {
    "iso:country":"GB",
    "wof:name":"WR2 5QS",
    "wof:placetype":"postalcode"
},
  "geometry": {"coordinates":[-2.25475248777249,52.19344844559527],"type":"Point"}
}