{
  "type": "Feature",
  "properties": {
    "iso:country":"GB",
    "wof:name":"M32 9PQ",
    "wof:placetype":"postalcode"
},
  "geometry": {"coordinates":[-2.33278609408703,53.45326382441596],"type":"Point"}
}