{
  "type": "Feature",
  "properties": {
    "iso:country":"GB",
    "wof:name":"BR7 6QG",
    "wof:placetype":"postalcode"
},
  "geometry": {"coordinates":[0.07801326670199,51.41011053487671],"type":"Point"}
}