{
  "type": "Feature",
  "properties": {
    "date:inception_lower": "1980-01-01",
    "date:inception_upper": "1980-01-01",
    "iso:country": "GB",
    "wof:name": "BR7 6QG",
    "wof:placetype": "postalcode"
  },
  "geometry": {"coordinates":[0.078039,51.410111],"type":"Point"}
}
