{
  "type": "Feature",
  "properties": {
    "date:inception_lower":"1980-01-01",
    "date:inception_upper":"1980-01-31",
    "iso:country":"GB",
    "wof:name":"SL4 6JR",
    "wof:placetype":"postalcode"
},
  "geometry": {"coordinates":[-0.635483,51.4982],"type":"Point"}
}