{
  "type": "Feature",
  "properties": {
    "iso:country":"GB",
    "wof:name":"SL4 6JR",
    "wof:placetype":"postalcode"
},
  "geometry": {"coordinates":[-0.63548301431042,51.49820002020037],"type":"Point"}
}