{
  "type": "Feature",
  "properties": {
    "iso:country":"GB",
    "wof:name":"DT9 4RR",
    "wof:placetype":"postalcode"
},
  "geometry": {"coordinates":[-2.53411238045956,50.98387872697921],"type":"Point"}
}