{
  "type": "Feature",
  "properties": {
    "iso:country":"GB",
    "wof:name":"TD8 6SF",
    "wof:placetype":"postalcode"
},
  "geometry": {"coordinates":[-2.55165427267125,55.48517907807054],"type":"Point"}
}