{
  "type": "Feature",
  "properties": {
    "iso:country": "GB",
    "wof:name": "MK44 1EQ",
    "wof:placetype": "postalcode"
  },
  "geometry": {"coordinates":[-0.481969,52.253904],"type":"Point"}
}
