{
  "type": "Feature",
  "properties": {
    "iso:country":"GB",
    "wof:name":"MK44 1EQ",
    "wof:placetype":"postalcode"
},
  "geometry": {"coordinates":[-0.48196890048791,52.25390374056817],"type":"Point"}
}