{
  "type": "Feature",
  "properties": {
    "date:inception_lower": "2006-03-01",
    "date:inception_upper": "2006-03-01",
    "iso:country": "GB",
    "wof:name": "CA28 9UJ",
    "wof:placetype": "postalcode"
  },
  "geometry": {"coordinates":[-3.601246,54.518148],"type":"Point"}
}
