{
  "type": "Feature",
  "properties": {
    "iso:country":"GB",
    "wof:name":"CA28 9UJ",
    "wof:placetype":"postalcode"
},
  "geometry": {"coordinates":[-3.60124578240661,54.51814770382401],"type":"Point"}
}