{
  "type": "Feature",
  "properties": {
    "date:inception_lower": "2023-02-01",
    "date:inception_upper": "2023-02-01",
    "iso:country": "GB",
    "wof:name": "EX1 3WA",
    "wof:placetype": "postalcode"
  },
  "geometry": {"coordinates":[-3.484619,50.723711],"type":"Point"}
}
