{
  "type": "Feature",
  "properties": {
    "date:inception_lower": "1980-01-01",
    "date:inception_upper": "1980-01-01",
    "iso:country": "GB",
    "wof:name": "BB10 3JW",
    "wof:placetype": "postalcode"
  },
  "geometry": {"coordinates":[-2.199441,53.789254],"type":"Point"}
}
