{
  "type": "Feature",
  "properties": {
    "date:inception_lower": "1980-01-01",
    "date:inception_upper": "1980-01-01",
    "iso:country": "GB",
    "wof:name": "WF9 5BG",
    "wof:placetype": "postalcode"
  },
  "geometry": {"coordinates":[-1.37608,53.637102],"type":"Point"}
}
