{
  "type": "Feature",
  "properties": {
    "iso:country":"GB",
    "wof:name":"WF9 5BG",
    "wof:placetype":"postalcode"
},
  "geometry": {"coordinates":[-1.3760803793913,53.63710151374181],"type":"Point"}
}