{
  "type": "Feature",
  "properties": {
    "iso:country": "GB",
    "wof:name": "WF9 5BG",
    "wof:placetype": "postalcode"
  },
  "geometry": {"coordinates":[-1.37608,53.637102],"type":"Point"}
}
