{
  "type": "Feature",
  "properties": {
    "iso:country":"GB",
    "wof:name":"NE38 0AL",
    "wof:placetype":"postalcode"
},
  "geometry": {"coordinates":[-1.55529858931169,54.88636879597265],"type":"Point"}
}