{
  "type": "Feature",
  "properties": {
    "date:inception_lower": "2014-03-01",
    "date:inception_upper": "2014-03-01",
    "iso:country": "GB",
    "wof:name": "NE38 0AL",
    "wof:placetype": "postalcode"
  },
  "geometry": {"coordinates":[-1.555299,54.886369],"type":"Point"}
}
