{
  "type": "Feature",
  "properties": {
    "iso:country":"GB",
    "wof:name":"PO8 0DL",
    "wof:placetype":"postalcode"
},
  "geometry": {"coordinates":[-0.99248813668997,50.90941119767928],"type":"Point"}
}