{
  "type": "Feature",
  "properties": {
    "iso:country":"GB",
    "wof:name":"OL5 9JH",
    "wof:placetype":"postalcode"
},
  "geometry": {"coordinates":[-2.02983610113426,53.51530393755479],"type":"Point"}
}