{
  "type": "Feature",
  "properties": {
    "iso:country":"GB",
    "wof:name":"B46 2BJ",
    "wof:placetype":"postalcode"
},
  "geometry": {"coordinates":[-1.66189411264629,52.51410928292626],"type":"Point"}
}