{
  "type": "Feature",
  "properties": {
    "date:inception_lower": "1996-06-01",
    "date:inception_upper": "1996-06-01",
    "iso:country": "GB",
    "wof:name": "B46 2BJ",
    "wof:placetype": "postalcode"
  },
  "geometry": {"coordinates":[-1.661894,52.514109],"type":"Point"}
}
