{
  "type": "Feature",
  "properties": {
    "iso:country": "GB",
    "wof:name": "B46 2BJ",
    "wof:placetype": "postalcode"
  },
  "geometry": {"coordinates":[-1.661894,52.514109],"type":"Point"}
}
