{
  "type": "Feature",
  "properties": {
    "date:inception_lower": "2009-09-01",
    "date:inception_upper": "2009-09-01",
    "iso:country": "GB",
    "wof:name": "ST16 3NG",
    "wof:placetype": "postalcode"
  },
  "geometry": {"coordinates":[-2.111134,52.815675],"type":"Point"}
}
