{
  "type": "Feature",
  "properties": {
    "date:inception_lower": "1994-12-01",
    "date:inception_upper": "1994-12-01",
    "iso:country": "GB",
    "wof:name": "SO50 5ND",
    "wof:placetype": "postalcode"
  },
  "geometry": {"coordinates":[-1.355042,50.961184],"type":"Point"}
}
