{
  "type": "Feature",
  "properties": {
    "iso:country":"GB",
    "wof:name":"SO50 5ND",
    "wof:placetype":"postalcode"
},
  "geometry": {"coordinates":[-1.35505237587758,50.96119180247183],"type":"Point"}
}