{
  "type": "Feature",
  "properties": {
    "iso:country":"GB",
    "wof:name":"BS35 4NN",
    "wof:placetype":"postalcode"
},
  "geometry": {"coordinates":[-2.65080418007595,51.55920261699923],"type":"Point"}
}