{
  "type": "Feature",
  "properties": {
    "iso:country":"GB",
    "wof:name":"IP22 4WR",
    "wof:placetype":"postalcode"
},
  "geometry": {"coordinates":[1.12135549043918,52.37441063483582],"type":"Point"}
}