{
  "type": "Feature",
  "properties": {
    "iso:country":"GB",
    "wof:name":"DE14 1SL",
    "wof:placetype":"postalcode"
},
  "geometry": {"coordinates":[-1.62606393727872,52.80804670883117],"type":"Point"}
}