{
  "type": "Feature",
  "properties": {
    "date:inception_lower": "1995-01-01",
    "date:inception_upper": "1995-01-01",
    "iso:country": "GB",
    "wof:name": "DE14 1SL",
    "wof:placetype": "postalcode"
  },
  "geometry": {"coordinates":[-1.626064,52.808047],"type":"Point"}
}
