{
  "type": "Feature",
  "properties": {
    "iso:country":"GB",
    "wof:name":"NE61 1JP",
    "wof:placetype":"postalcode"
},
  "geometry": {"coordinates":[-1.68699991451839,55.17221544321627],"type":"Point"}
}