{
  "type": "Feature",
  "properties": {
    "iso:country":"GB",
    "wof:name":"WS4 1TE",
    "wof:placetype":"postalcode"
},
  "geometry": {"coordinates":[-1.94912200768368,52.61395422342024],"type":"Point"}
}