{
  "type": "Feature",
  "properties": {
    "date:inception_lower":"1990-07-01",
    "date:inception_upper":"1990-07-31",
    "iso:country":"GB",
    "wof:name":"WS4 1TE",
    "wof:placetype":"postalcode"
},
  "geometry": {"coordinates":[-1.949122,52.613954],"type":"Point"}
}