{
  "type": "Feature",
  "properties": {
    "iso:country": "GB",
    "wof:name": "WS4 1TE",
    "wof:placetype": "postalcode"
  },
  "geometry": {"coordinates":[-1.949122,52.613954],"type":"Point"}
}
