{
  "type": "Feature",
  "properties": {
    "iso:country":"GB",
    "wof:name":"CV31 3DB",
    "wof:placetype":"postalcode"
},
  "geometry": {"coordinates":[-1.53470388348394,52.26312174154528],"type":"Point"}
}