{
  "type": "Feature",
  "properties": {
    "date:inception_lower": "2023-03-01",
    "date:inception_upper": "2023-03-01",
    "iso:country": "GB",
    "wof:name": "CT21 4FJ",
    "wof:placetype": "postalcode"
  },
  "geometry": {"coordinates":[1.041801,51.058453],"type":"Point"}
}
