{
  "type": "Feature",
  "properties": {
    "iso:country":"GB",
    "wof:name":"HU5 2RG",
    "wof:placetype":"postalcode"
},
  "geometry": {"coordinates":[-0.35806602246586,53.7601759609627],"type":"Point"}
}