{
  "type": "Feature",
  "properties": {
    "date:inception_lower": "1992-01-01",
    "date:inception_upper": "1992-01-01",
    "iso:country": "GB",
    "wof:name": "B32 3RD",
    "wof:placetype": "postalcode"
  },
  "geometry": {"coordinates":[-2.009327,52.44073],"type":"Point"}
}
