{
  "type": "Feature",
  "properties": {
    "iso:country":"GB",
    "wof:name":"B32 3RD",
    "wof:placetype":"postalcode"
},
  "geometry": {"coordinates":[-2.0093269274966,52.44072955451243],"type":"Point"}
}