{
  "type": "Feature",
  "properties": {
    "date:inception_lower": "2008-06-01",
    "date:inception_upper": "2008-06-01",
    "iso:country": "GB",
    "wof:name": "CO10 2BF",
    "wof:placetype": "postalcode"
  },
  "geometry": {"coordinates":[0.725537,52.034712],"type":"Point"}
}
