{
  "type": "Feature",
  "properties": {
    "iso:country": "GB",
    "wof:name": "CO10 2BF",
    "wof:placetype": "postalcode"
  },
  "geometry": {"coordinates":[0.725569,52.034514],"type":"Point"}
}
