{
  "type": "Feature",
  "properties": {
    "iso:country": "GB",
    "wof:name": "LE17 5NA",
    "wof:placetype": "postalcode"
  },
  "geometry": {"coordinates":[-1.162633,52.496285],"type":"Point"}
}
