{
  "type": "Feature",
  "properties": {
    "iso:country":"GB",
    "wof:name":"TQ9 7DY",
    "wof:placetype":"postalcode"
},
  "geometry": {"coordinates":[-3.68404759699102,50.407752850287],"type":"Point"}
}