{
  "type": "Feature",
  "properties": {
    "iso:country": "GB",
    "wof:name": "DT11 8UH",
    "wof:placetype": "postalcode"
  },
  "geometry": {"coordinates":[-2.133516,50.883833],"type":"Point"}
}
