{
  "type": "Feature",
  "properties": {
    "iso:country":"GB",
    "wof:name":"DT11 8UH",
    "wof:placetype":"postalcode"
},
  "geometry": {"coordinates":[-2.13351557417809,50.88383345200695],"type":"Point"}
}