{
  "type": "Feature",
  "properties": {
    "iso:country":"GB",
    "wof:name":"TA7 0DZ",
    "wof:placetype":"postalcode"
},
  "geometry": {"coordinates":[-2.9289300327226,51.1080276558944],"type":"Point"}
}