{
  "type": "Feature",
  "properties": {
    "date:inception_lower": "1980-01-01",
    "date:inception_upper": "1980-01-01",
    "iso:country": "GB",
    "wof:name": "TA7 0DZ",
    "wof:placetype": "postalcode"
  },
  "geometry": {"coordinates":[-2.928592,51.107908],"type":"Point"}
}
