{
  "type": "Feature",
  "properties": {
    "date:inception_lower": "2004-09-01",
    "date:inception_upper": "2004-09-01",
    "iso:country": "GB",
    "wof:name": "ME16 0GQ",
    "wof:placetype": "postalcode"
  },
  "geometry": {"coordinates":[0.515641,51.275657],"type":"Point"}
}
