{
  "type": "Feature",
  "properties": {
    "iso:country": "GB",
    "wof:name": "CM14 5WH",
    "wof:placetype": "postalcode"
  },
  "geometry": {"coordinates":[0.290762,51.610197],"type":"Point"}
}
