{
  "type": "Feature",
  "properties": {
    "date:inception_lower": "2001-12-01",
    "date:inception_upper": "2001-12-01",
    "iso:country": "GB",
    "wof:name": "CM14 5WH",
    "wof:placetype": "postalcode"
  },
  "geometry": {"coordinates":[0.290762,51.610197],"type":"Point"}
}
