{
  "type": "Feature",
  "properties": {
    "iso:country":"GB",
    "wof:name":"LE2 5HG",
    "wof:placetype":"postalcode"
},
  "geometry": {"coordinates":[-1.08739567423261,52.59782973081554],"type":"Point"}
}