{
  "type": "Feature",
  "properties": {
    "iso:country": "GB",
    "wof:name": "LE2 5HG",
    "wof:placetype": "postalcode"
  },
  "geometry": {"coordinates":[-1.087396,52.59783],"type":"Point"}
}
