{
  "type": "Feature",
  "properties": {
    "iso:country":"GB",
    "wof:name":"BN3 7LF",
    "wof:placetype":"postalcode"
},
  "geometry": {"coordinates":[-0.18538311318111,50.84555269780294],"type":"Point"}
}