{
  "type": "Feature",
  "properties": {
    "iso:country":"GB",
    "wof:name":"NW9 0QN",
    "wof:placetype":"postalcode"
},
  "geometry": {"coordinates":[-0.26782350724659,51.5946269623052],"type":"Point"}
}