{
  "type": "Feature",
  "properties": {
    "iso:country": "GB",
    "wof:name": "SW1E 6SA",
    "wof:placetype": "postalcode"
  },
  "geometry": {"coordinates":[-0.137502,51.497662],"type":"Point"}
}
