{
  "type": "Feature",
  "properties": {
    "iso:country": "GB",
    "wof:name": "IP31 3PZ",
    "wof:placetype": "postalcode"
  },
  "geometry": {"coordinates":[0.799254,52.252914],"type":"Point"}
}
