{
  "type": "Feature",
  "properties": {
    "iso:country":"GB",
    "wof:name":"IP31 3PZ",
    "wof:placetype":"postalcode"
},
  "geometry": {"coordinates":[0.79925358924819,52.25291396613331],"type":"Point"}
}