{
  "type": "Feature",
  "properties": {
    "date:inception_lower": "1980-01-01",
    "date:inception_upper": "1980-01-01",
    "iso:country": "GB",
    "wof:name": "IP31 3PZ",
    "wof:placetype": "postalcode"
  },
  "geometry": {"coordinates":[0.799172,52.253023],"type":"Point"}
}
