{
  "type": "Feature",
  "properties": {
    "date:inception_lower":"2006-10-01",
    "date:inception_upper":"2006-10-31",
    "iso:country":"GB",
    "wof:name":"RH4 3DB",
    "wof:placetype":"postalcode"
},
  "geometry": {"coordinates":[-0.343226,51.225965],"type":"Point"}
}