{
  "type": "Feature",
  "properties": {
    "iso:country":"GB",
    "wof:name":"RH4 3DB",
    "wof:placetype":"postalcode"
},
  "geometry": {"coordinates":[-0.34322636070956,51.22596467294533],"type":"Point"}
}