{
  "type": "Feature",
  "properties": {
    "iso:country": "GB",
    "wof:name": "PR7 7JR",
    "wof:placetype": "postalcode"
  },
  "geometry": {"coordinates":[-2.657015,53.675293],"type":"Point"}
}
