{
  "type": "Feature",
  "properties": {
    "iso:country":"GB",
    "wof:name":"PR7 7JR",
    "wof:placetype":"postalcode"
},
  "geometry": {"coordinates":[-2.65701540862663,53.67529288658373],"type":"Point"}
}