{
  "type": "Feature",
  "properties": {
    "iso:country":"GB",
    "wof:name":"BD9 4RH",
    "wof:placetype":"postalcode"
},
  "geometry": {"coordinates":[-1.77720211065863,53.80918490172988],"type":"Point"}
}