{
  "type": "Feature",
  "properties": {
    "date:inception_lower": "2003-03-01",
    "date:inception_upper": "2003-03-01",
    "iso:country": "GB",
    "wof:name": "S20 1XJ",
    "wof:placetype": "postalcode"
  },
  "geometry": {"coordinates":[-1.349854,53.346334],"type":"Point"}
}
