{
  "type": "Feature",
  "properties": {
    "iso:country":"GB",
    "wof:name":"AB15 8BE",
    "wof:placetype":"postalcode"
},
  "geometry": {"coordinates":[-2.17812418555367,57.14464788735093],"type":"Point"}
}