{
  "type": "Feature",
  "properties": {
    "iso:country":"GB",
    "wof:name":"TW17 0SS",
    "wof:placetype":"postalcode"
},
  "geometry": {"coordinates":[-0.44341390487646,51.41525558805978],"type":"Point"}
}