{
  "type": "Feature",
  "properties": {
    "iso:country":"GB",
    "wof:name":"NG20 0AU",
    "wof:placetype":"postalcode"
},
  "geometry": {"coordinates":[-1.15265366535462,53.2068460421142],"type":"Point"}
}