{
  "type": "Feature",
  "properties": {
    "iso:country":"GB",
    "wof:name":"AL3 6LA",
    "wof:placetype":"postalcode"
},
  "geometry": {"coordinates":[-0.36721529458211,51.76622571160705],"type":"Point"}
}