{
  "type": "Feature",
  "properties": {
    "iso:country": "GB",
    "wof:name": "SW19 1QT",
    "wof:placetype": "postalcode"
  },
  "geometry": {"coordinates":[-0.202079,51.418159],"type":"Point"}
}
