{
  "type": "Feature",
  "properties": {
    "date:inception_lower":"1980-01-01",
    "date:inception_upper":"1980-01-31",
    "iso:country":"GB",
    "wof:name":"SW19 1QT",
    "wof:placetype":"postalcode"
},
  "geometry": {"coordinates":[-0.202079,51.418159],"type":"Point"}
}