{
  "type": "Feature",
  "properties": {
    "iso:country":"GB",
    "wof:name":"G64 1JZ",
    "wof:placetype":"postalcode"
},
  "geometry": {"coordinates":[-4.20659593170271,55.8990746385649],"type":"Point"}
}