{
  "type": "Feature",
  "properties": {
    "iso:country": "GB",
    "wof:name": "G64 1JZ",
    "wof:placetype": "postalcode"
  },
  "geometry": {"coordinates":[-4.206596,55.899075],"type":"Point"}
}
