{
  "type": "Feature",
  "properties": {
    "iso:country": "GB",
    "wof:name": "BB7 4AJ",
    "wof:placetype": "postalcode"
  },
  "geometry": {"coordinates":[-2.356822,53.89385],"type":"Point"}
}
