{
  "type": "Feature",
  "properties": {
    "iso:country":"GB",
    "wof:name":"SK10 5BW",
    "wof:placetype":"postalcode"
},
  "geometry": {"coordinates":[-2.09474887136317,53.2952302095856],"type":"Point"}
}