{
  "type": "Feature",
  "properties": {
    "date:inception_lower": "1980-01-01",
    "date:inception_upper": "1980-01-01",
    "iso:country": "GB",
    "wof:name": "SK10 5BW",
    "wof:placetype": "postalcode"
  },
  "geometry": {"coordinates":[-2.094749,53.29523],"type":"Point"}
}
