{
  "type": "Feature",
  "properties": {
    "iso:country":"GB",
    "wof:name":"BS5 6UQ",
    "wof:placetype":"postalcode"
},
  "geometry": {"coordinates":[-2.56795674131614,51.47661416287935],"type":"Point"}
}