{
  "type": "Feature",
  "properties": {
    "date:inception_lower": "2022-02-01",
    "date:inception_upper": "2022-02-01",
    "iso:country": "GB",
    "wof:name": "IP28 6FB",
    "wof:placetype": "postalcode"
  },
  "geometry": {"coordinates":[0.706787,52.27401],"type":"Point"}
}
