{
  "type": "Feature",
  "properties": {
    "date:inception_lower":"1993-08-01",
    "date:inception_upper":"1993-08-31",
    "iso:country":"GB",
    "wof:name":"CW3 0NB",
    "wof:placetype":"postalcode"
},
  "geometry": {"coordinates":[-2.508139,52.988665],"type":"Point"}
}