{
  "type": "Feature",
  "properties": {
    "date:inception_lower": "1993-08-01",
    "date:inception_upper": "1993-08-01",
    "iso:country": "GB",
    "wof:name": "CW3 0NB",
    "wof:placetype": "postalcode"
  },
  "geometry": {"coordinates":[-2.508679,52.988948],"type":"Point"}
}
