{
  "type": "Feature",
  "properties": {
    "date:inception_lower": "1995-12-01",
    "date:inception_upper": "1995-12-01",
    "iso:country": "GB",
    "wof:name": "CW11 2JZ",
    "wof:placetype": "postalcode"
  },
  "geometry": {"coordinates":[-2.347123,53.142778],"type":"Point"}
}
