{
  "type": "Feature",
  "properties": {
    "iso:country": "GB",
    "wof:name": "CW11 2JZ",
    "wof:placetype": "postalcode"
  },
  "geometry": {"coordinates":[-2.347123,53.142778],"type":"Point"}
}
