{
  "type": "Feature",
  "properties": {
    "iso:country":"GB",
    "wof:name":"CW11 2JZ",
    "wof:placetype":"postalcode"
},
  "geometry": {"coordinates":[-2.34712327399606,53.14277824212553],"type":"Point"}
}