{
  "type": "Feature",
  "properties": {
    "iso:country":"GB",
    "wof:name":"DL12 0HT",
    "wof:placetype":"postalcode"
},
  "geometry": {"coordinates":[-2.28031024194623,54.69358500179167],"type":"Point"}
}