{
  "type": "Feature",
  "properties": {
    "date:inception_lower": "1980-01-01",
    "date:inception_upper": "1980-01-01",
    "iso:country": "GB",
    "wof:name": "DL12 0HT",
    "wof:placetype": "postalcode"
  },
  "geometry": {"coordinates":[-2.28031,54.693585],"type":"Point"}
}
