{
  "type": "Feature",
  "properties": {
    "iso:country":"GB",
    "wof:name":"W2 6BJ",
    "wof:placetype":"postalcode"
},
  "geometry": {"coordinates":[-0.18608546141962,51.51755932270067],"type":"Point"}
}