{
  "type": "Feature",
  "properties": {
    "iso:country":"GB",
    "wof:name":"PO20 0QR",
    "wof:placetype":"postalcode"
},
  "geometry": {"coordinates":[-0.78925689675841,50.73442119130698],"type":"Point"}
}