{
  "type": "Feature",
  "properties": {
    "iso:country":"GB",
    "wof:name":"S35 8PH",
    "wof:placetype":"postalcode"
},
  "geometry": {"coordinates":[-1.51014967058566,53.43885554985438],"type":"Point"}
}