{
  "type": "Feature",
  "properties": {
    "iso:country":"GB",
    "wof:name":"SG4 9JQ",
    "wof:placetype":"postalcode"
},
  "geometry": {"coordinates":[-0.26789744132847,51.94176453752597],"type":"Point"}
}