{
  "type": "Feature",
  "properties": {
    "iso:country":"GB",
    "wof:name":"W1U 7NR",
    "wof:placetype":"postalcode"
},
  "geometry": {"coordinates":[-0.1553963947314,51.51941875666839],"type":"Point"}
}