{
  "type": "Feature",
  "properties": {
    "iso:country": "GB",
    "wof:name": "NG14 5GE",
    "wof:placetype": "postalcode"
  },
  "geometry": {"coordinates":[-1.028523,52.991682],"type":"Point"}
}
