{
  "type": "Feature",
  "properties": {
    "date:inception_lower": "2018-09-01",
    "date:inception_upper": "2018-09-01",
    "iso:country": "GB",
    "wof:name": "S6 4NH",
    "wof:placetype": "postalcode"
  },
  "geometry": {"coordinates":[-1.501467,53.402577],"type":"Point"}
}
