{
  "type": "Feature",
  "properties": {
    "iso:country": "GB",
    "wof:name": "SN14 0YY",
    "wof:placetype": "postalcode"
  },
  "geometry": {"coordinates":[-2.141034,51.441974],"type":"Point"}
}
