{
  "type": "Feature",
  "properties": {
    "iso:country":"GB",
    "wof:name":"IP26 4EH",
    "wof:placetype":"postalcode"
},
  "geometry": {"coordinates":[0.50447409229901,52.48586608431027],"type":"Point"}
}