{
  "type": "Feature",
  "properties": {
    "iso:country": "GB",
    "wof:name": "IP26 4EH",
    "wof:placetype": "postalcode"
  },
  "geometry": {"coordinates":[0.503324,52.48599],"type":"Point"}
}
