{
  "type": "Feature",
  "properties": {
    "date:inception_lower": "2018-06-01",
    "date:inception_upper": "2018-06-01",
    "iso:country": "GB",
    "wof:name": "RH12 0BW",
    "wof:placetype": "postalcode"
  },
  "geometry": {"coordinates":[-0.231483,51.100799],"type":"Point"}
}
