{
  "type": "Feature",
  "properties": {
    "iso:country": "GB",
    "wof:name": "SR8 5UP",
    "wof:placetype": "postalcode"
  },
  "geometry": {"coordinates":[-1.333039,54.754067],"type":"Point"}
}
