{
  "type": "Feature",
  "properties": {
    "iso:country":"GB",
    "wof:name":"SR8 5UP",
    "wof:placetype":"postalcode"
},
  "geometry": {"coordinates":[-1.33303884697346,54.75406682727083],"type":"Point"}
}