{
  "type": "Feature",
  "properties": {
    "date:inception_lower":"2007-07-01",
    "date:inception_upper":"2007-07-31",
    "iso:country":"GB",
    "wof:name":"SR8 5UP",
    "wof:placetype":"postalcode"
},
  "geometry": {"coordinates":[-1.333039,54.754067],"type":"Point"}
}