{
  "type": "Feature",
  "properties": {
    "date:inception_lower": "1993-08-01",
    "date:inception_upper": "1993-08-01",
    "iso:country": "GB",
    "wof:name": "SY22 6ND",
    "wof:placetype": "postalcode"
  },
  "geometry": {"coordinates":[-3.078072,52.758355],"type":"Point"}
}
