{
  "type": "Feature",
  "properties": {
    "date:inception_lower": "1992-08-01",
    "date:inception_upper": "1992-08-01",
    "iso:country": "GB",
    "wof:name": "B23 7RL",
    "wof:placetype": "postalcode"
  },
  "geometry": {"coordinates":[-1.875583,52.521503],"type":"Point"}
}
