{
  "type": "Feature",
  "properties": {
    "iso:country": "GB",
    "wof:name": "GL3 2SG",
    "wof:placetype": "postalcode"
  },
  "geometry": {"coordinates":[-2.180676,51.8809],"type":"Point"}
}
