{
  "type": "Feature",
  "properties": {
    "date:inception_lower":"1980-01-01",
    "date:inception_upper":"1980-01-31",
    "iso:country":"GB",
    "wof:name":"GL3 2SG",
    "wof:placetype":"postalcode"
},
  "geometry": {"coordinates":[-2.180676,51.8809],"type":"Point"}
}