{
  "type": "Feature",
  "properties": {
    "iso:country":"GB",
    "wof:name":"BD12 0UA",
    "wof:placetype":"postalcode"
},
  "geometry": {"coordinates":[-1.77138012463053,53.75155187147832],"type":"Point"}
}