{
  "type": "Feature",
  "properties": {
    "date:inception_lower":"1980-01-01",
    "date:inception_upper":"1980-01-31",
    "iso:country":"GB",
    "wof:name":"BD12 0UA",
    "wof:placetype":"postalcode"
},
  "geometry": {"coordinates":[-1.77138,53.751552],"type":"Point"}
}