{
  "type": "Feature",
  "properties": {
    "iso:country": "GB",
    "wof:name": "S75 3PY",
    "wof:placetype": "postalcode"
  },
  "geometry": {"coordinates":[-1.517515,53.538146],"type":"Point"}
}
