{
  "type": "Feature",
  "properties": {
    "iso:country":"GB",
    "wof:name":"S75 3PY",
    "wof:placetype":"postalcode"
},
  "geometry": {"coordinates":[-1.51751503479035,53.53814568397735],"type":"Point"}
}