{
  "type": "Feature",
  "properties": {
    "iso:country":"GB",
    "wof:name":"LE15 8JW",
    "wof:placetype":"postalcode"
},
  "geometry": {"coordinates":[-0.6179987956735,52.61921191160073],"type":"Point"}
}