{
  "type": "Feature",
  "properties": {
    "iso:country": "GB",
    "wof:name": "LE15 8JW",
    "wof:placetype": "postalcode"
  },
  "geometry": {"coordinates":[-0.617999,52.619212],"type":"Point"}
}
