{
  "type": "Feature",
  "properties": {
    "date:inception_lower":"1980-01-01",
    "date:inception_upper":"1980-01-31",
    "iso:country":"GB",
    "wof:name":"LE15 8JW",
    "wof:placetype":"postalcode"
},
  "geometry": {"coordinates":[-0.617999,52.619212],"type":"Point"}
}