{
  "type": "Feature",
  "properties": {
    "date:inception_lower": "1988-03-01",
    "date:inception_upper": "1988-03-01",
    "iso:country": "GB",
    "wof:name": "IP13 6EY",
    "wof:placetype": "postalcode"
  },
  "geometry": {"coordinates":[1.350284,52.126599],"type":"Point"}
}
