{
  "type": "Feature",
  "properties": {
    "iso:country":"GB",
    "wof:name":"IP13 6EY",
    "wof:placetype":"postalcode"
},
  "geometry": {"coordinates":[1.35028430344861,52.12659896777996],"type":"Point"}
}