{
  "type": "Feature",
  "properties": {
    "iso:country": "GB",
    "wof:name": "EX17 4PB",
    "wof:placetype": "postalcode"
  },
  "geometry": {"coordinates":[-3.687094,50.81038],"type":"Point"}
}
