{
  "type": "Feature",
  "properties": {
    "iso:country":"GB",
    "wof:name":"EX17 4PB",
    "wof:placetype":"postalcode"
},
  "geometry": {"coordinates":[-3.68707645127406,50.81038834942412],"type":"Point"}
}