{
  "type": "Feature",
  "properties": {
    "iso:country":"GB",
    "wof:name":"LL18 3EH",
    "wof:placetype":"postalcode"
},
  "geometry": {"coordinates":[-3.48658312860574,53.32360320406637],"type":"Point"}
}