{
  "type": "Feature",
  "properties": {
    "date:inception_lower": "1980-01-01",
    "date:inception_upper": "1980-01-01",
    "iso:country": "GB",
    "wof:name": "LA15 8JQ",
    "wof:placetype": "postalcode"
  },
  "geometry": {"coordinates":[-3.16652,54.156325],"type":"Point"}
}
