{
  "type": "Feature",
  "properties": {
    "date:inception_lower":"2011-08-01",
    "date:inception_upper":"2011-08-31",
    "iso:country":"GB",
    "wof:name":"TN24 0TZ",
    "wof:placetype":"postalcode"
},
  "geometry": {"coordinates":[0.886395,51.138929],"type":"Point"}
}