{
  "type": "Feature",
  "properties": {
    "iso:country":"GB",
    "wof:name":"TN24 0TZ",
    "wof:placetype":"postalcode"
},
  "geometry": {"coordinates":[0.88639454493561,51.13892854141486],"type":"Point"}
}