{
  "type": "Feature",
  "properties": {
    "iso:country":"GB",
    "wof:name":"HD4 6DQ",
    "wof:placetype":"postalcode"
},
  "geometry": {"coordinates":[-1.78103082726091,53.63649482043963],"type":"Point"}
}