{
  "type": "Feature",
  "properties": {
    "iso:country": "GB",
    "wof:name": "S25 4FN",
    "wof:placetype": "postalcode"
  },
  "geometry": {"coordinates":[-1.214264,53.359074],"type":"Point"}
}
