{
  "type": "Feature",
  "properties": {
    "iso:country": "GB",
    "wof:name": "BH23 2RY",
    "wof:placetype": "postalcode"
  },
  "geometry": {"coordinates":[-1.800396,50.756631],"type":"Point"}
}
