{
  "type": "Feature",
  "properties": {
    "iso:country":"GB",
    "wof:name":"BS27 3LF",
    "wof:placetype":"postalcode"
},
  "geometry": {"coordinates":[-2.77860842951639,51.28155833109346],"type":"Point"}
}