{
  "type": "Feature",
  "properties": {
    "iso:country":"GB",
    "wof:name":"W1D 4UR",
    "wof:placetype":"postalcode"
},
  "geometry": {"coordinates":[-0.13109078970719,51.51352159109243],"type":"Point"}
}