{
  "type": "Feature",
  "properties": {
    "iso:country": "GB",
    "wof:name": "DN9 1SD",
    "wof:placetype": "postalcode"
  },
  "geometry": {"coordinates":[-0.81329,53.524612],"type":"Point"}
}
