{
  "type": "Feature",
  "properties": {
    "iso:country":"GB",
    "wof:name":"DN9 1SD",
    "wof:placetype":"postalcode"
},
  "geometry": {"coordinates":[-0.81328997062814,53.52461173954659],"type":"Point"}
}