{
  "type": "Feature",
  "properties": {
    "iso:country": "GB",
    "wof:name": "W5 1UB",
    "wof:placetype": "postalcode"
  },
  "geometry": {"coordinates":[-0.310758,51.524223],"type":"Point"}
}
