{
  "type": "Feature",
  "properties": {
    "date:inception_lower": "1980-01-01",
    "date:inception_upper": "1980-01-01",
    "iso:country": "GB",
    "wof:name": "SK10 4DW",
    "wof:placetype": "postalcode"
  },
  "geometry": {"coordinates":[-2.150202,53.291587],"type":"Point"}
}
