{
  "type": "Feature",
  "properties": {
    "iso:country":"GB",
    "wof:name":"SK10 4DW",
    "wof:placetype":"postalcode"
},
  "geometry": {"coordinates":[-2.15020191919626,53.29158664752781],"type":"Point"}
}