{
  "type": "Feature",
  "properties": {
    "date:inception_lower":"1994-12-01",
    "date:inception_upper":"1994-12-31",
    "iso:country":"GB",
    "wof:name":"NN4 6BA",
    "wof:placetype":"postalcode"
},
  "geometry": {"coordinates":[-0.868026,52.205047],"type":"Point"}
}