{
  "type": "Feature",
  "properties": {
    "iso:country":"GB",
    "wof:name":"HG4 1EQ",
    "wof:placetype":"postalcode"
},
  "geometry": {"coordinates":[-1.52291856690519,54.13728875601876],"type":"Point"}
}