{
  "type": "Feature",
  "properties": {
    "iso:country":"GB",
    "wof:name":"CO10 7SW",
    "wof:placetype":"postalcode"
},
  "geometry": {"coordinates":[0.66867595161929,52.09624480016107],"type":"Point"}
}