{
  "type": "Feature",
  "properties": {
    "iso:country": "GB",
    "wof:name": "MK10 7LD",
    "wof:placetype": "postalcode"
  },
  "geometry": {"coordinates":[-0.677823,52.048595],"type":"Point"}
}
