{
  "type": "Feature",
  "properties": {
    "iso:country":"GB",
    "wof:name":"SK4 3JG",
    "wof:placetype":"postalcode"
},
  "geometry": {"coordinates":[-2.19203040097462,53.41261257190251],"type":"Point"}
}