{
  "type": "Feature",
  "properties": {
    "iso:country": "GB",
    "wof:name": "WR11 2UT",
    "wof:placetype": "postalcode"
  },
  "geometry": {"coordinates":[-1.938059,52.076885],"type":"Point"}
}
