{
  "type": "Feature",
  "properties": {
    "iso:country":"GB",
    "wof:name":"GL2 0PY",
    "wof:placetype":"postalcode"
},
  "geometry": {"coordinates":[-2.2112341197348,51.86983474642282],"type":"Point"}
}