{
  "type": "Feature",
  "properties": {
    "iso:country":"GB",
    "wof:name":"NW3 2AP",
    "wof:placetype":"postalcode"
},
  "geometry": {"coordinates":[-0.16275714873667,51.55033342724774],"type":"Point"}
}