{
  "type": "Feature",
  "properties": {
    "date:inception_lower": "1980-01-01",
    "date:inception_upper": "1980-01-01",
    "iso:country": "GB",
    "wof:name": "DE7 6HH",
    "wof:placetype": "postalcode"
  },
  "geometry": {"coordinates":[-1.354108,52.970344],"type":"Point"}
}
