{
  "type": "Feature",
  "properties": {
    "date:inception_lower": "2011-05-01",
    "date:inception_upper": "2011-05-01",
    "iso:country": "GB",
    "wof:name": "SE16 3FD",
    "wof:placetype": "postalcode"
  },
  "geometry": {"coordinates":[-0.070743,51.495863],"type":"Point"}
}
