{
  "type": "Feature",
  "properties": {
    "iso:country":"GB",
    "wof:name":"B33 9HD",
    "wof:placetype":"postalcode"
},
  "geometry": {"coordinates":[-1.80192162108959,52.48553248596225],"type":"Point"}
}