{
  "type": "Feature",
  "properties": {
    "date:inception_lower": "1997-06-01",
    "date:inception_upper": "1997-06-01",
    "iso:country": "GB",
    "wof:name": "DN14 5SP",
    "wof:placetype": "postalcode"
  },
  "geometry": {"coordinates":[-0.87911,53.699819],"type":"Point"}
}
