{
  "type": "Feature",
  "properties": {
    "iso:country":"GB",
    "wof:name":"TN31 7EA",
    "wof:placetype":"postalcode"
},
  "geometry": {"coordinates":[0.71825985954999,50.9486381962529],"type":"Point"}
}