{
  "type": "Feature",
  "properties": {
    "iso:country": "GB",
    "wof:name": "TN31 7EA",
    "wof:placetype": "postalcode"
  },
  "geometry": {"coordinates":[0.71826,50.948638],"type":"Point"}
}
