{
  "type": "Feature",
  "properties": {
    "date:inception_lower": "1980-01-01",
    "date:inception_upper": "1980-01-01",
    "iso:country": "GB",
    "wof:name": "TN31 7EA",
    "wof:placetype": "postalcode"
  },
  "geometry": {"coordinates":[0.71826,50.948638],"type":"Point"}
}
