{
  "type": "Feature",
  "properties": {
    "date:inception_lower":"2015-10-01",
    "date:inception_upper":"2015-10-31",
    "iso:country":"GB",
    "wof:name":"NE22 5BP",
    "wof:placetype":"postalcode"
},
  "geometry": {"coordinates":[-1.586275,55.135423],"type":"Point"}
}