{
  "type": "Feature",
  "properties": {
    "date:inception_lower": "2017-02-01",
    "date:inception_upper": "2017-02-01",
    "iso:country": "GB",
    "wof:name": "OX16 2DD",
    "wof:placetype": "postalcode"
  },
  "geometry": {"coordinates":[-1.334794,52.087067],"type":"Point"}
}
