{
  "type": "Feature",
  "properties": {
    "iso:country":"GB",
    "wof:name":"KA5 6RJ",
    "wof:placetype":"postalcode"
},
  "geometry": {"coordinates":[-4.32957457187261,55.50488516371903],"type":"Point"}
}