{
  "type": "Feature",
  "properties": {
    "iso:country": "GB",
    "wof:name": "SG5 3UP",
    "wof:placetype": "postalcode"
  },
  "geometry": {"coordinates":[-0.278356,51.96847],"type":"Point"}
}
