{
  "type": "Feature",
  "properties": {
    "iso:country":"GB",
    "wof:name":"SG5 3UP",
    "wof:placetype":"postalcode"
},
  "geometry": {"coordinates":[-0.2783981047293,51.96845318061738],"type":"Point"}
}