{
  "type": "Feature",
  "properties": {
    "iso:country":"GB",
    "wof:name":"TW7 7QD",
    "wof:placetype":"postalcode"
},
  "geometry": {"coordinates":[-0.33546401130053,51.459408681636],"type":"Point"}
}