{
  "type": "Feature",
  "properties": {
    "iso:country":"GB",
    "wof:name":"WF8 4PY",
    "wof:placetype":"postalcode"
},
  "geometry": {"coordinates":[-1.31517495270624,53.6950042228511],"type":"Point"}
}