{
  "type": "Feature",
  "properties": {
    "date:inception_lower":"1980-01-01",
    "date:inception_upper":"1980-01-31",
    "iso:country":"GB",
    "wof:name":"M35 9HT",
    "wof:placetype":"postalcode"
},
  "geometry": {"coordinates":[-2.143148,53.509829],"type":"Point"}
}