{
  "type": "Feature",
  "properties": {
    "iso:country": "GB",
    "wof:name": "NP4 9AS",
    "wof:placetype": "postalcode"
  },
  "geometry": {"coordinates":[-3.08775,51.773103],"type":"Point"}
}
