{
  "type": "Feature",
  "properties": {
    "date:inception_lower":"2007-11-01",
    "date:inception_upper":"2007-11-30",
    "iso:country":"GB",
    "wof:name":"NP4 9AS",
    "wof:placetype":"postalcode"
},
  "geometry": {"coordinates":[-3.08775,51.773103],"type":"Point"}
}