{
  "type": "Feature",
  "properties": {
    "date:inception_lower": "1992-01-01",
    "date:inception_upper": "1992-01-01",
    "iso:country": "GB",
    "wof:name": "KY4 0HL",
    "wof:placetype": "postalcode"
  },
  "geometry": {"coordinates":[-3.36955,56.13944],"type":"Point"}
}
