{
  "type": "Feature",
  "properties": {
    "iso:country": "GB",
    "wof:name": "KY4 0HL",
    "wof:placetype": "postalcode"
  },
  "geometry": {"coordinates":[-3.36955,56.13944],"type":"Point"}
}
