{
  "type": "Feature",
  "properties": {
    "date:inception_lower": "1980-01-01",
    "date:inception_upper": "1980-01-01",
    "iso:country": "GB",
    "wof:name": "BN26 5XR",
    "wof:placetype": "postalcode"
  },
  "geometry": {"coordinates":[0.154224,50.807592],"type":"Point"}
}
