{
  "type": "Feature",
  "properties": {
    "iso:country":"GB",
    "wof:name":"BN26 5XR",
    "wof:placetype":"postalcode"
},
  "geometry": {"coordinates":[0.15415347732083,50.80759803798181],"type":"Point"}
}