{
  "type": "Feature",
  "properties": {
    "iso:country":"GB",
    "wof:name":"ML5 3EW",
    "wof:placetype":"postalcode"
},
  "geometry": {"coordinates":[-4.02251840450049,55.86316183765005],"type":"Point"}
}