{
  "type": "Feature",
  "properties": {
    "iso:country":"GB",
    "wof:name":"KY13 9JS",
    "wof:placetype":"postalcode"
},
  "geometry": {"coordinates":[-3.33143044722771,56.21401259440227],"type":"Point"}
}