{
  "type": "Feature",
  "properties": {
    "iso:country": "GB",
    "wof:name": "BN43 6YJ",
    "wof:placetype": "postalcode"
  },
  "geometry": {"coordinates":[-0.248029,50.839073],"type":"Point"}
}
