{
  "type": "Feature",
  "properties": {
    "iso:country":"GB",
    "wof:name":"CH1 5EA",
    "wof:placetype":"postalcode"
},
  "geometry": {"coordinates":[-2.92425624876672,53.20968630086674],"type":"Point"}
}