{
  "type": "Feature",
  "properties": {
    "iso:country":"GB",
    "wof:name":"TA24 8HB",
    "wof:placetype":"postalcode"
},
  "geometry": {"coordinates":[-3.58936966552566,51.21121809043144],"type":"Point"}
}