{
  "type": "Feature",
  "properties": {
    "iso:country":"GB",
    "wof:name":"LS11 6AY",
    "wof:placetype":"postalcode"
},
  "geometry": {"coordinates":[-1.55454650440963,53.77763730182882],"type":"Point"}
}