{
  "type": "Feature",
  "properties": {
    "iso:country":"GB",
    "wof:name":"WN7 1RT",
    "wof:placetype":"postalcode"
},
  "geometry": {"coordinates":[-2.51981797091433,53.50279712176788],"type":"Point"}
}