{
  "type": "Feature",
  "properties": {
    "iso:country":"GB",
    "wof:name":"KA20 4BA",
    "wof:placetype":"postalcode"
},
  "geometry": {"coordinates":[-4.75418917944678,55.64422381838661],"type":"Point"}
}