{
  "type": "Feature",
  "properties": {
    "iso:country":"GB",
    "wof:name":"BA6 8LJ",
    "wof:placetype":"postalcode"
},
  "geometry": {"coordinates":[-2.66120476931124,51.13535946586247],"type":"Point"}
}