{
  "type": "Feature",
  "properties": {
    "date:inception_lower":"2006-07-01",
    "date:inception_upper":"2006-07-31",
    "iso:country":"GB",
    "wof:name":"TN24 0SR",
    "wof:placetype":"postalcode"
},
  "geometry": {"coordinates":[0.905204,51.142699],"type":"Point"}
}