{
  "type": "Feature",
  "properties": {
    "iso:country":"GB",
    "wof:name":"TN24 0SR",
    "wof:placetype":"postalcode"
},
  "geometry": {"coordinates":[0.90520364660519,51.14269890769209],"type":"Point"}
}