{
  "type": "Feature",
  "properties": {
    "iso:country": "GB",
    "wof:name": "LA15 8NL",
    "wof:placetype": "postalcode"
  },
  "geometry": {"coordinates":[-3.182578,54.148043],"type":"Point"}
}
