{
  "type": "Feature",
  "properties": {
    "date:inception_lower":"1993-08-01",
    "date:inception_upper":"1993-08-31",
    "iso:country":"GB",
    "wof:name":"PL15 8QL",
    "wof:placetype":"postalcode"
},
  "geometry": {"coordinates":[-4.367058,50.645855],"type":"Point"}
}