{
  "type": "Feature",
  "properties": {
    "iso:country":"GB",
    "wof:name":"PL15 8QL",
    "wof:placetype":"postalcode"
},
  "geometry": {"coordinates":[-4.36705763301083,50.64585535092698],"type":"Point"}
}