{
  "type": "Feature",
  "properties": {
    "iso:country": "GB",
    "wof:name": "GL15 5LN",
    "wof:placetype": "postalcode"
  },
  "geometry": {"coordinates":[-2.527374,51.732586],"type":"Point"}
}
