{
  "type": "Feature",
  "properties": {
    "iso:country":"GB",
    "wof:name":"BA3 5UD",
    "wof:placetype":"postalcode"
},
  "geometry": {"coordinates":[-2.42485335121504,51.28507654283682],"type":"Point"}
}