{
  "type": "Feature",
  "properties": {
    "iso:country":"GB",
    "wof:name":"TS4 3LY",
    "wof:placetype":"postalcode"
},
  "geometry": {"coordinates":[-1.21789449564314,54.54544813927772],"type":"Point"}
}