{
  "type": "Feature",
  "properties": {
    "date:inception_lower": "1984-02-01",
    "date:inception_upper": "1984-02-01",
    "iso:country": "GB",
    "wof:name": "HA6 3PX",
    "wof:placetype": "postalcode"
  },
  "geometry": {"coordinates":[-0.416741,51.610965],"type":"Point"}
}
