{
  "type": "Feature",
  "properties": {
    "iso:country":"GB",
    "wof:name":"CW3 9EN",
    "wof:placetype":"postalcode"
},
  "geometry": {"coordinates":[-2.34718355972979,53.00190987788722],"type":"Point"}
}