{
  "type": "Feature",
  "properties": {
    "iso:country":"GB",
    "wof:name":"DD5 3PD",
    "wof:placetype":"postalcode"
},
  "geometry": {"coordinates":[-2.8833434775093,56.51040938350391],"type":"Point"}
}