{
  "type": "Feature",
  "properties": {
    "date:inception_lower": "1980-01-01",
    "date:inception_upper": "1980-01-01",
    "iso:country": "GB",
    "wof:name": "OX16 9PN",
    "wof:placetype": "postalcode"
  },
  "geometry": {"coordinates":[-1.341452,52.058163],"type":"Point"}
}
