{
  "type": "Feature",
  "properties": {
    "date:inception_lower":"1980-01-01",
    "date:inception_upper":"1980-01-31",
    "iso:country":"GB",
    "wof:name":"OL7 9DX",
    "wof:placetype":"postalcode"
},
  "geometry": {"coordinates":[-2.102596,53.494986],"type":"Point"}
}