{
  "type": "Feature",
  "properties": {
    "iso:country":"GB",
    "wof:name":"OL7 9DX",
    "wof:placetype":"postalcode"
},
  "geometry": {"coordinates":[-2.10259580834447,53.49498564722145],"type":"Point"}
}