{
  "type": "Feature",
  "properties": {
    "iso:country":"GB",
    "wof:name":"DN3 3TS",
    "wof:placetype":"postalcode"
},
  "geometry": {"coordinates":[-1.04401457291165,53.52773034737255],"type":"Point"}
}