{
  "type": "Feature",
  "properties": {
    "date:inception_lower":"1997-12-01",
    "date:inception_upper":"1997-12-31",
    "iso:country":"GB",
    "wof:name":"PE11 2YU",
    "wof:placetype":"postalcode"
},
  "geometry": {"coordinates":[-0.139979,52.794091],"type":"Point"}
}