{
  "type": "Feature",
  "properties": {
    "iso:country":"GB",
    "wof:name":"PE11 2YU",
    "wof:placetype":"postalcode"
},
  "geometry": {"coordinates":[-0.13994668319676,52.79405183388246],"type":"Point"}
}