{
  "type": "Feature",
  "properties": {
    "iso:country": "GB",
    "wof:name": "WD19 5EW",
    "wof:placetype": "postalcode"
  },
  "geometry": {"coordinates":[-0.376805,51.62294],"type":"Point"}
}
