{
  "type": "Feature",
  "properties": {
    "iso:country": "GB",
    "wof:name": "S6 3FW",
    "wof:placetype": "postalcode"
  },
  "geometry": {"coordinates":[-1.487459,53.389179],"type":"Point"}
}
