{
  "type": "Feature",
  "properties": {
    "iso:country":"GB",
    "wof:name":"S6 3FW",
    "wof:placetype":"postalcode"
},
  "geometry": {"coordinates":[-1.48750431208379,53.38916128431382],"type":"Point"}
}