{
  "type": "Feature",
  "properties": {
    "iso:country":"GB",
    "wof:name":"SP6 3QR",
    "wof:placetype":"postalcode"
},
  "geometry": {"coordinates":[-1.82519625601693,50.97983592652478],"type":"Point"}
}