{
  "type": "Feature",
  "properties": {
    "date:inception_lower": "1980-01-01",
    "date:inception_upper": "1980-01-01",
    "iso:country": "GB",
    "wof:name": "SP6 3QR",
    "wof:placetype": "postalcode"
  },
  "geometry": {"coordinates":[-1.825259,50.979766],"type":"Point"}
}
