{
  "type": "Feature",
  "properties": {
    "date:inception_lower": "2002-06-01",
    "date:inception_upper": "2002-06-01",
    "iso:country": "GB",
    "wof:name": "B94 6EE",
    "wof:placetype": "postalcode"
  },
  "geometry": {"coordinates":[-1.816777,52.376103],"type":"Point"}
}
