{
  "type": "Feature",
  "properties": {
    "iso:country":"GB",
    "wof:name":"B94 6EE",
    "wof:placetype":"postalcode"
},
  "geometry": {"coordinates":[-1.81677729756049,52.376102594442],"type":"Point"}
}