{
  "type": "Feature",
  "properties": {
    "iso:country": "GB",
    "wof:name": "CO11 2QH",
    "wof:placetype": "postalcode"
  },
  "geometry": {"coordinates":[1.095996,51.936438],"type":"Point"}
}
