{
  "type": "Feature",
  "properties": {
    "date:inception_lower":"1980-01-01",
    "date:inception_upper":"1980-01-31",
    "iso:country":"GB",
    "wof:name":"CO11 2QH",
    "wof:placetype":"postalcode"
},
  "geometry": {"coordinates":[1.095996,51.936438],"type":"Point"}
}