{
  "type": "Feature",
  "properties": {
    "iso:country": "GB",
    "wof:name": "DN37 9BB",
    "wof:placetype": "postalcode"
  },
  "geometry": {"coordinates":[-0.12016,53.569877],"type":"Point"}
}
