{
  "type": "Feature",
  "properties": {
    "iso:country": "GB",
    "wof:name": "SA31 2JQ",
    "wof:placetype": "postalcode"
  },
  "geometry": {"coordinates":[-4.265171,51.869557],"type":"Point"}
}
