{
  "type": "Feature",
  "properties": {
    "iso:country": "GB",
    "wof:name": "AB51 5DP",
    "wof:placetype": "postalcode"
  },
  "geometry": {"coordinates":[-2.431555,57.301534],"type":"Point"}
}
