{
  "type": "Feature",
  "properties": {
    "date:inception_lower": "1980-01-01",
    "date:inception_upper": "1980-01-01",
    "iso:country": "GB",
    "wof:name": "NG20 0PZ",
    "wof:placetype": "postalcode"
  },
  "geometry": {"coordinates":[-1.146664,53.203118],"type":"Point"}
}
