{
  "type": "Feature",
  "properties": {
    "iso:country":"GB",
    "wof:name":"SL1 5BS",
    "wof:placetype":"postalcode"
},
  "geometry": {"coordinates":[-0.63399384055955,51.51909813385551],"type":"Point"}
}