{
  "type": "Feature",
  "properties": {
    "iso:country": "GB",
    "wof:name": "SY25 6JN",
    "wof:placetype": "postalcode"
  },
  "geometry": {"coordinates":[-3.933729,52.219161],"type":"Point"}
}
