{
  "type": "Feature",
  "properties": {
    "iso:country":"GB",
    "wof:name":"SY25 6JN",
    "wof:placetype":"postalcode"
},
  "geometry": {"coordinates":[-3.93372863135829,52.2191611914843],"type":"Point"}
}