{
  "type": "Feature",
  "properties": {
    "iso:country":"GB",
    "wof:name":"DL3 0XS",
    "wof:placetype":"postalcode"
},
  "geometry": {"coordinates":[-1.55704367073611,54.54019963524929],"type":"Point"}
}