{
  "type": "Feature",
  "properties": {
    "iso:country":"GB",
    "wof:name":"CV10 7AE",
    "wof:placetype":"postalcode"
},
  "geometry": {"coordinates":[-1.46753720430836,52.50753340840799],"type":"Point"}
}