{
  "type": "Feature",
  "properties": {
    "iso:country": "GB",
    "wof:name": "MK19 6LR",
    "wof:placetype": "postalcode"
  },
  "geometry": {"coordinates":[-0.897536,52.058993],"type":"Point"}
}
