{
  "type": "Feature",
  "properties": {
    "iso:country":"GB",
    "wof:name":"NP12 2QL",
    "wof:placetype":"postalcode"
},
  "geometry": {"coordinates":[-3.20609174319431,51.65510186346384],"type":"Point"}
}