{
  "type": "Feature",
  "properties": {
    "date:inception_lower":"1999-06-01",
    "date:inception_upper":"1999-06-30",
    "iso:country":"GB",
    "wof:name":"NP12 2QL",
    "wof:placetype":"postalcode"
},
  "geometry": {"coordinates":[-3.206092,51.655102],"type":"Point"}
}