{
  "type": "Feature",
  "properties": {
    "iso:country": "GB",
    "wof:name": "ML2 9BS",
    "wof:placetype": "postalcode"
  },
  "geometry": {"coordinates":[-3.877064,55.791255],"type":"Point"}
}
