{
  "type": "Feature",
  "properties": {
    "date:inception_lower": "1980-01-01",
    "date:inception_upper": "1980-01-01",
    "iso:country": "GB",
    "wof:name": "NG4 1SD",
    "wof:placetype": "postalcode"
  },
  "geometry": {"coordinates":[-1.092148,52.967733],"type":"Point"}
}
