{
  "type": "Feature",
  "properties": {
    "iso:country":"GB",
    "wof:name":"NG4 1SD",
    "wof:placetype":"postalcode"
},
  "geometry": {"coordinates":[-1.09214839722899,52.96773346113309],"type":"Point"}
}