{
  "type": "Feature",
  "properties": {
    "iso:country":"GB",
    "wof:name":"BD20 8NX",
    "wof:placetype":"postalcode"
},
  "geometry": {"coordinates":[-2.02307455026746,53.91601201490937],"type":"Point"}
}