{
  "type": "Feature",
  "properties": {
    "date:inception_lower": "1980-01-01",
    "date:inception_upper": "1980-01-01",
    "iso:country": "GB",
    "wof:name": "SY7 0PZ",
    "wof:placetype": "postalcode"
  },
  "geometry": {"coordinates":[-2.890846,52.385962],"type":"Point"}
}
