{
  "type": "Feature",
  "properties": {
    "iso:country": "GB",
    "wof:name": "SY7 0PZ",
    "wof:placetype": "postalcode"
  },
  "geometry": {"coordinates":[-2.892533,52.385814],"type":"Point"}
}
