{
  "type": "Feature",
  "properties": {
    "iso:country":"GB",
    "wof:name":"SY7 0PZ",
    "wof:placetype":"postalcode"
},
  "geometry": {"coordinates":[-2.89084666187687,52.3859120762196],"type":"Point"}
}