{
  "type": "Feature",
  "properties": {
    "date:inception_lower": "1980-01-01",
    "date:inception_upper": "1980-01-01",
    "iso:country": "GB",
    "wof:name": "YO13 9AF",
    "wof:placetype": "postalcode"
  },
  "geometry": {"coordinates":[-0.578795,54.226219],"type":"Point"}
}
