{
  "type": "Feature",
  "properties": {
    "iso:country":"GB",
    "wof:name":"YO13 9AF",
    "wof:placetype":"postalcode"
},
  "geometry": {"coordinates":[-0.57879527594426,54.22621890448917],"type":"Point"}
}