{
  "type": "Feature",
  "properties": {
    "iso:country":"GB",
    "wof:name":"SE9 4LZ",
    "wof:placetype":"postalcode"
},
  "geometry": {"coordinates":[0.05231388783689,51.42803659795454],"type":"Point"}
}