{
  "type": "Feature",
  "properties": {
    "date:inception_lower": "2005-08-01",
    "date:inception_upper": "2005-08-01",
    "iso:country": "GB",
    "wof:name": "SO52 9PS",
    "wof:placetype": "postalcode"
  },
  "geometry": {"coordinates":[-1.443591,50.975468],"type":"Point"}
}
