{
  "type": "Feature",
  "properties": {
    "iso:country": "GB",
    "wof:name": "SO52 9PS",
    "wof:placetype": "postalcode"
  },
  "geometry": {"coordinates":[-1.443591,50.975468],"type":"Point"}
}
