{
  "type": "Feature",
  "properties": {
    "iso:country":"GB",
    "wof:name":"WF4 4NP",
    "wof:placetype":"postalcode"
},
  "geometry": {"coordinates":[-1.5884469242531,53.6533264472522],"type":"Point"}
}