{
  "type": "Feature",
  "properties": {
    "date:inception_lower": "1980-01-01",
    "date:inception_upper": "1980-01-01",
    "iso:country": "GB",
    "wof:name": "MK43 7LU",
    "wof:placetype": "postalcode"
  },
  "geometry": {"coordinates":[-0.605046,52.187921],"type":"Point"}
}
