{
  "type": "Feature",
  "properties": {
    "iso:country": "GB",
    "wof:name": "HU4 6SW",
    "wof:placetype": "postalcode"
  },
  "geometry": {"coordinates":[-0.39786,53.728201],"type":"Point"}
}
