{
  "type": "Feature",
  "properties": {
    "iso:country":"GB",
    "wof:name":"HU4 6SW",
    "wof:placetype":"postalcode"
},
  "geometry": {"coordinates":[-0.39786009452796,53.72820089634789],"type":"Point"}
}