{
  "type": "Feature",
  "properties": {
    "date:inception_lower":"1990-07-01",
    "date:inception_upper":"1990-07-31",
    "iso:country":"GB",
    "wof:name":"HU4 6SW",
    "wof:placetype":"postalcode"
},
  "geometry": {"coordinates":[-0.39786,53.728201],"type":"Point"}
}