{
  "type": "Feature",
  "properties": {
    "iso:country":"GB",
    "wof:name":"GL7 1PP",
    "wof:placetype":"postalcode"
},
  "geometry": {"coordinates":[-1.9673013158064,51.71079844560224],"type":"Point"}
}