{
  "type": "Feature",
  "properties": {
    "date:inception_lower": "1980-01-01",
    "date:inception_upper": "1980-01-01",
    "iso:country": "GB",
    "wof:name": "SY23 5NE",
    "wof:placetype": "postalcode"
  },
  "geometry": {"coordinates":[-4.136957,52.249248],"type":"Point"}
}
