{
  "type": "Feature",
  "properties": {
    "iso:country":"GB",
    "wof:name":"SY23 5NE",
    "wof:placetype":"postalcode"
},
  "geometry": {"coordinates":[-4.13695671966605,52.24924842571802],"type":"Point"}
}