{
  "type": "Feature",
  "properties": {
    "iso:country":"GB",
    "wof:name":"SK5 6TJ",
    "wof:placetype":"postalcode"
},
  "geometry": {"coordinates":[-2.15729089224581,53.43638418249596],"type":"Point"}
}