{
  "type": "Feature",
  "properties": {
    "iso:country":"GB",
    "wof:name":"PO7 7BW",
    "wof:placetype":"postalcode"
},
  "geometry": {"coordinates":[-1.02158173211807,50.86837320285618],"type":"Point"}
}