{
  "type": "Feature",
  "properties": {
    "iso:country": "GB",
    "wof:name": "CB8 7JZ",
    "wof:placetype": "postalcode"
  },
  "geometry": {"coordinates":[0.367916,52.268147],"type":"Point"}
}
