{
  "type": "Feature",
  "properties": {
    "iso:country":"GB",
    "wof:name":"PR5 5AS",
    "wof:placetype":"postalcode"
},
  "geometry": {"coordinates":[-2.68591258748948,53.72923134137554],"type":"Point"}
}