{
  "type": "Feature",
  "properties": {
    "iso:country":"GB",
    "wof:name":"CR0 5JW",
    "wof:placetype":"postalcode"
},
  "geometry": {"coordinates":[-0.08512355765812,51.36781825835063],"type":"Point"}
}