{
  "type": "Feature",
  "properties": {
    "iso:country": "GB",
    "wof:name": "CR0 5JW",
    "wof:placetype": "postalcode"
  },
  "geometry": {"coordinates":[-0.085124,51.367818],"type":"Point"}
}
