{
  "type": "Feature",
  "properties": {
    "iso:country":"GB",
    "wof:name":"BA4 4DD",
    "wof:placetype":"postalcode"
},
  "geometry": {"coordinates":[-2.57962159806359,51.16492682959694],"type":"Point"}
}