{
  "type": "Feature",
  "properties": {
    "iso:country":"GB",
    "wof:name":"EX10 9JB",
    "wof:placetype":"postalcode"
},
  "geometry": {"coordinates":[-3.23423957667924,50.69207258179573],"type":"Point"}
}