{
  "type": "Feature",
  "properties": {
    "iso:country": "GB",
    "wof:name": "EX10 9JB",
    "wof:placetype": "postalcode"
  },
  "geometry": {"coordinates":[-3.23424,50.692073],"type":"Point"}
}
