{
  "type": "Feature",
  "properties": {
    "iso:country": "GB",
    "wof:name": "B45 5FH",
    "wof:placetype": "postalcode"
  },
  "geometry": {"coordinates":[-2.0029,52.385949],"type":"Point"}
}
