{
  "type": "Feature",
  "properties": {
    "date:inception_lower": "1980-01-01",
    "date:inception_upper": "1980-01-01",
    "iso:country": "GB",
    "wof:name": "RH1 2JH",
    "wof:placetype": "postalcode"
  },
  "geometry": {"coordinates":[-0.1651,51.25311],"type":"Point"}
}
