{
  "type": "Feature",
  "properties": {
    "iso:country":"GB",
    "wof:name":"ML6 6PR",
    "wof:placetype":"postalcode"
},
  "geometry": {"coordinates":[-3.97642216201328,55.87495583884039],"type":"Point"}
}