{
  "type": "Feature",
  "properties": {
    "iso:country": "GB",
    "wof:name": "ML6 6PR",
    "wof:placetype": "postalcode"
  },
  "geometry": {"coordinates":[-3.976422,55.874956],"type":"Point"}
}
