{
  "type": "Feature",
  "properties": {
    "date:inception_lower": "1980-01-01",
    "date:inception_upper": "1980-01-01",
    "iso:country": "GB",
    "wof:name": "SY5 9PL",
    "wof:placetype": "postalcode"
  },
  "geometry": {"coordinates":[-2.890426,52.685752],"type":"Point"}
}
