{
  "type": "Feature",
  "properties": {
    "iso:country": "GB",
    "wof:name": "SY5 9PL",
    "wof:placetype": "postalcode"
  },
  "geometry": {"coordinates":[-2.890369,52.685746],"type":"Point"}
}
