{
  "type": "Feature",
  "properties": {
    "iso:country":"GB",
    "wof:name":"SY5 9PL",
    "wof:placetype":"postalcode"
},
  "geometry": {"coordinates":[-2.89036951677953,52.68574629839886],"type":"Point"}
}