{
  "type": "Feature",
  "properties": {
    "iso:country": "GB",
    "wof:name": "CF23 8GL",
    "wof:placetype": "postalcode"
  },
  "geometry": {"coordinates":[-3.137739,51.539971],"type":"Point"}
}
