{
  "type": "Feature",
  "properties": {
    "date:inception_lower":"2016-06-01",
    "date:inception_upper":"2016-06-30",
    "iso:country":"GB",
    "wof:name":"CF23 8GL",
    "wof:placetype":"postalcode"
},
  "geometry": {"coordinates":[-3.137739,51.539971],"type":"Point"}
}