{
  "type": "Feature",
  "properties": {
    "iso:country":"GB",
    "wof:name":"HP12 3UN",
    "wof:placetype":"postalcode"
},
  "geometry": {"coordinates":[-0.77857911519822,51.62432312102859],"type":"Point"}
}