{
  "type": "Feature",
  "properties": {
    "date:inception_lower":"1980-01-01",
    "date:inception_upper":"1980-01-31",
    "iso:country":"GB",
    "wof:name":"HP12 3UN",
    "wof:placetype":"postalcode"
},
  "geometry": {"coordinates":[-0.778579,51.624323],"type":"Point"}
}