{
  "type": "Feature",
  "properties": {
    "date:inception_lower": "2002-09-01",
    "date:inception_upper": "2002-09-01",
    "iso:country": "GB",
    "wof:name": "CV6 6RE",
    "wof:placetype": "postalcode"
  },
  "geometry": {"coordinates":[-1.47617,52.459205],"type":"Point"}
}
