{
  "type": "Feature",
  "properties": {
    "iso:country":"GB",
    "wof:name":"CV6 6RE",
    "wof:placetype":"postalcode"
},
  "geometry": {"coordinates":[-1.47617048159897,52.45920545317141],"type":"Point"}
}