{
  "type": "Feature",
  "properties": {
    "date:inception_lower": "1980-01-01",
    "date:inception_upper": "1980-01-01",
    "iso:country": "GB",
    "wof:name": "TR7 2QZ",
    "wof:placetype": "postalcode"
  },
  "geometry": {"coordinates":[-5.068635,50.416233],"type":"Point"}
}
