{
  "type": "Feature",
  "properties": {
    "iso:country":"GB",
    "wof:name":"TR7 2QZ",
    "wof:placetype":"postalcode"
},
  "geometry": {"coordinates":[-5.06797628416024,50.41653773513922],"type":"Point"}
}