{
  "type": "Feature",
  "properties": {
    "iso:country":"GB",
    "wof:name":"IV30 4AL",
    "wof:placetype":"postalcode"
},
  "geometry": {"coordinates":[-3.29946665345921,57.65316276454197],"type":"Point"}
}