{
  "type": "Feature",
  "properties": {
    "date:inception_lower": "1980-01-01",
    "date:inception_upper": "1980-01-01",
    "iso:country": "GB",
    "wof:name": "BA12 7PD",
    "wof:placetype": "postalcode"
  },
  "geometry": {"coordinates":[-2.258673,51.212332],"type":"Point"}
}
