{
  "type": "Feature",
  "properties": {
    "iso:country": "GB",
    "wof:name": "BA12 7PD",
    "wof:placetype": "postalcode"
  },
  "geometry": {"coordinates":[-2.258673,51.212332],"type":"Point"}
}
