{
  "type": "Feature",
  "properties": {
    "iso:country":"GB",
    "wof:name":"NR16 2SB",
    "wof:placetype":"postalcode"
},
  "geometry": {"coordinates":[0.86394105553694,52.42926124782546],"type":"Point"}
}