{
  "type": "Feature",
  "properties": {
    "iso:country": "GB",
    "wof:name": "TN4 0PZ",
    "wof:placetype": "postalcode"
  },
  "geometry": {"coordinates":[0.259604,51.156212],"type":"Point"}
}
