{
  "type": "Feature",
  "properties": {
    "iso:country":"GB",
    "wof:name":"TN4 0PZ",
    "wof:placetype":"postalcode"
},
  "geometry": {"coordinates":[0.25957655736042,51.15621403894536],"type":"Point"}
}