{
  "type": "Feature",
  "properties": {
    "iso:country":"GB",
    "wof:name":"WR9 0RG",
    "wof:placetype":"postalcode"
},
  "geometry": {"coordinates":[-2.16780425604038,52.26151745176345],"type":"Point"}
}