{
  "type": "Feature",
  "properties": {
    "date:inception_lower": "1994-05-01",
    "date:inception_upper": "1994-05-01",
    "iso:country": "GB",
    "wof:name": "M6 8NH",
    "wof:placetype": "postalcode"
  },
  "geometry": {"coordinates":[-2.315653,53.494325],"type":"Point"}
}
