{
  "type": "Feature",
  "properties": {
    "iso:country": "GB",
    "wof:name": "OL3 5GR",
    "wof:placetype": "postalcode"
  },
  "geometry": {"coordinates":[-1.999205,53.564292],"type":"Point"}
}
