{
  "type": "Feature",
  "properties": {
    "iso:country": "GB",
    "wof:name": "DL10 7HG",
    "wof:placetype": "postalcode"
  },
  "geometry": {"coordinates":[-1.668381,54.391257],"type":"Point"}
}
