{
  "type": "Feature",
  "properties": {
    "date:inception_lower": "1999-06-01",
    "date:inception_upper": "1999-06-01",
    "iso:country": "GB",
    "wof:name": "CF3 4JS",
    "wof:placetype": "postalcode"
  },
  "geometry": {"coordinates":[-3.133699,51.519545],"type":"Point"}
}
