{
  "type": "Feature",
  "properties": {
    "iso:country":"GB",
    "wof:name":"CF3 4JS",
    "wof:placetype":"postalcode"
},
  "geometry": {"coordinates":[-3.13369888536467,51.51954457584399],"type":"Point"}
}