{
  "type": "Feature",
  "properties": {
    "date:inception_lower": "2003-06-01",
    "date:inception_upper": "2003-06-01",
    "iso:country": "GB",
    "wof:name": "DT11 9HH",
    "wof:placetype": "postalcode"
  },
  "geometry": {"coordinates":[-2.200669,50.824441],"type":"Point"}
}
