{
  "type": "Feature",
  "properties": {
    "iso:country":"GB",
    "wof:name":"DT11 9HH",
    "wof:placetype":"postalcode"
},
  "geometry": {"coordinates":[-2.20066924015627,50.82444080404738],"type":"Point"}
}