{
  "type": "Feature",
  "properties": {
    "iso:country":"GB",
    "wof:name":"B38 9TX",
    "wof:placetype":"postalcode"
},
  "geometry": {"coordinates":[-1.94248151260878,52.39424649296096],"type":"Point"}
}