{
  "type": "Feature",
  "properties": {
    "iso:country":"GB",
    "wof:name":"N9 0PU",
    "wof:placetype":"postalcode"
},
  "geometry": {"coordinates":[-0.06026526785634,51.6197244280883],"type":"Point"}
}