{
  "type": "Feature",
  "properties": {
    "iso:country":"GB",
    "wof:name":"BR4 0JD",
    "wof:placetype":"postalcode"
},
  "geometry": {"coordinates":[-0.00405668264064,51.38558387791176],"type":"Point"}
}