{
  "type": "Feature",
  "properties": {
    "iso:country":"GB",
    "wof:name":"NE1 2TE",
    "wof:placetype":"postalcode"
},
  "geometry": {"coordinates":[-1.60188350143894,54.97420990651444],"type":"Point"}
}