{
  "type": "Feature",
  "properties": {
    "date:inception_lower": "1980-01-01",
    "date:inception_upper": "1980-01-01",
    "iso:country": "GB",
    "wof:name": "NE1 2TE",
    "wof:placetype": "postalcode"
  },
  "geometry": {"coordinates":[-1.601883,54.97421],"type":"Point"}
}
