{
  "type": "Feature",
  "properties": {
    "iso:country":"GB",
    "wof:name":"DH4 6EX",
    "wof:placetype":"postalcode"
},
  "geometry": {"coordinates":[-1.51917277473193,54.85818456300817],"type":"Point"}
}