{
  "type": "Feature",
  "properties": {
    "date:inception_lower": "1980-01-01",
    "date:inception_upper": "1980-01-01",
    "iso:country": "GB",
    "wof:name": "DH4 6EX",
    "wof:placetype": "postalcode"
  },
  "geometry": {"coordinates":[-1.519173,54.858185],"type":"Point"}
}
