{
  "type": "Feature",
  "properties": {
    "iso:country": "GB",
    "wof:name": "DH4 6EX",
    "wof:placetype": "postalcode"
  },
  "geometry": {"coordinates":[-1.519173,54.858185],"type":"Point"}
}
