{
  "type": "Feature",
  "properties": {
    "iso:country":"GB",
    "wof:name":"NE23 7EW",
    "wof:placetype":"postalcode"
},
  "geometry": {"coordinates":[-1.53935608276622,55.06488497300318],"type":"Point"}
}