{
  "type": "Feature",
  "properties": {
    "iso:country":"GB",
    "wof:name":"G73 3EF",
    "wof:placetype":"postalcode"
},
  "geometry": {"coordinates":[-4.20823582368492,55.82432440506179],"type":"Point"}
}