{
  "type": "Feature",
  "properties": {
    "iso:country": "GB",
    "wof:name": "ME7 3TN",
    "wof:placetype": "postalcode"
  },
  "geometry": {"coordinates":[0.567722,51.342761],"type":"Point"}
}
