{
  "type": "Feature",
  "properties": {
    "iso:country":"GB",
    "wof:name":"CF64 5RS",
    "wof:placetype":"postalcode"
},
  "geometry": {"coordinates":[-3.18010587637487,51.42404204563147],"type":"Point"}
}