{
  "type": "Feature",
  "properties": {
    "iso:country":"GB",
    "wof:name":"DL14 0EU",
    "wof:placetype":"postalcode"
},
  "geometry": {"coordinates":[-1.73898757300068,54.65485178127901],"type":"Point"}
}