{
  "type": "Feature",
  "properties": {
    "date:inception_lower": "1980-01-01",
    "date:inception_upper": "1980-01-01",
    "iso:country": "GB",
    "wof:name": "DL14 0EU",
    "wof:placetype": "postalcode"
  },
  "geometry": {"coordinates":[-1.738988,54.654852],"type":"Point"}
}
