{
  "type": "Feature",
  "properties": {
    "iso:country": "GB",
    "wof:name": "NG7 2QS",
    "wof:placetype": "postalcode"
  },
  "geometry": {"coordinates":[-1.206727,52.937485],"type":"Point"}
}
