{
  "type": "Feature",
  "properties": {
    "date:inception_lower": "1980-01-01",
    "date:inception_upper": "1980-01-01",
    "iso:country": "GB",
    "wof:name": "NG7 2QS",
    "wof:placetype": "postalcode"
  },
  "geometry": {"coordinates":[-1.206727,52.937485],"type":"Point"}
}
