{
  "type": "Feature",
  "properties": {
    "iso:country":"GB",
    "wof:name":"NG7 2QS",
    "wof:placetype":"postalcode"
},
  "geometry": {"coordinates":[-1.20672749564051,52.93748543481062],"type":"Point"}
}