{
  "type": "Feature",
  "properties": {
    "date:inception_lower":"2004-01-01",
    "date:inception_upper":"2004-01-31",
    "iso:country":"GB",
    "wof:name":"S17 4AZ",
    "wof:placetype":"postalcode"
},
  "geometry": {"coordinates":[-1.540092,53.314508],"type":"Point"}
}