{
  "type": "Feature",
  "properties": {
    "iso:country":"GB",
    "wof:name":"S17 4AZ",
    "wof:placetype":"postalcode"
},
  "geometry": {"coordinates":[-1.54009237305724,53.31450832520777],"type":"Point"}
}