{
  "type": "Feature",
  "properties": {
    "iso:country": "GB",
    "wof:name": "CH8 7LY",
    "wof:placetype": "postalcode"
  },
  "geometry": {"coordinates":[-3.224318,53.275363],"type":"Point"}
}
