{
  "type": "Feature",
  "properties": {
    "date:inception_lower":"2003-06-01",
    "date:inception_upper":"2003-06-30",
    "iso:country":"GB",
    "wof:name":"CH8 7LY",
    "wof:placetype":"postalcode"
},
  "geometry": {"coordinates":[-3.224318,53.275363],"type":"Point"}
}