{
  "type": "Feature",
  "properties": {
    "iso:country":"GB",
    "wof:name":"BS16 1WP",
    "wof:placetype":"postalcode"
},
  "geometry": {"coordinates":[-2.54584570414761,51.4963837880527],"type":"Point"}
}