{
  "type": "Feature",
  "properties": {
    "date:inception_lower":"2000-12-01",
    "date:inception_upper":"2000-12-31",
    "iso:country":"GB",
    "wof:name":"BS16 1WP",
    "wof:placetype":"postalcode"
},
  "geometry": {"coordinates":[-2.545831,51.496366],"type":"Point"}
}