{
  "type": "Feature",
  "properties": {
    "iso:country":"GB",
    "wof:name":"TW13 6RN",
    "wof:placetype":"postalcode"
},
  "geometry": {"coordinates":[-0.39366787153237,51.43011419931956],"type":"Point"}
}