{
  "type": "Feature",
  "properties": {
    "date:inception_lower": "1995-07-01",
    "date:inception_upper": "1995-07-01",
    "iso:country": "GB",
    "wof:name": "S3 7XL",
    "wof:placetype": "postalcode"
  },
  "geometry": {"coordinates":[-1.481281,53.376613],"type":"Point"}
}
