{
  "type": "Feature",
  "properties": {
    "date:inception_lower":"1980-01-01",
    "date:inception_upper":"1980-01-31",
    "iso:country":"GB",
    "wof:name":"LL16 5PY",
    "wof:placetype":"postalcode"
},
  "geometry": {"coordinates":[-3.506346,53.146663],"type":"Point"}
}