{
  "type": "Feature",
  "properties": {
    "iso:country":"GB",
    "wof:name":"LL16 5PY",
    "wof:placetype":"postalcode"
},
  "geometry": {"coordinates":[-3.50634635538021,53.14666295649471],"type":"Point"}
}