{
  "type": "Feature",
  "properties": {
    "date:inception_lower": "1980-01-01",
    "date:inception_upper": "1980-01-01",
    "iso:country": "GB",
    "wof:name": "PA19 1LD",
    "wof:placetype": "postalcode"
  },
  "geometry": {"coordinates":[-4.82786,55.954692],"type":"Point"}
}
