{
  "type": "Feature",
  "properties": {
    "iso:country":"GB",
    "wof:name":"PA19 1LD",
    "wof:placetype":"postalcode"
},
  "geometry": {"coordinates":[-4.82791397580849,55.95472465073604],"type":"Point"}
}