{
  "type": "Feature",
  "properties": {
    "date:inception_lower": "1986-04-01",
    "date:inception_upper": "1986-04-01",
    "iso:country": "GB",
    "wof:name": "DY10 1YJ",
    "wof:placetype": "postalcode"
  },
  "geometry": {"coordinates":[-2.248303,52.366723],"type":"Point"}
}
