{
  "type": "Feature",
  "properties": {
    "iso:country":"GB",
    "wof:name":"DY10 1YJ",
    "wof:placetype":"postalcode"
},
  "geometry": {"coordinates":[-2.2483030272269,52.36672298283816],"type":"Point"}
}