{
  "type": "Feature",
  "properties": {
    "iso:country": "GB",
    "wof:name": "PL21 9TN",
    "wof:placetype": "postalcode"
  },
  "geometry": {"coordinates":[-3.939076,50.389794],"type":"Point"}
}
