{
  "type": "Feature",
  "properties": {
    "iso:country":"GB",
    "wof:name":"LL15 2HY",
    "wof:placetype":"postalcode"
},
  "geometry": {"coordinates":[-3.30689596494387,53.03183004559457],"type":"Point"}
}