{
  "type": "Feature",
  "properties": {
    "date:inception_lower": "1983-03-01",
    "date:inception_upper": "1983-03-01",
    "iso:country": "GB",
    "wof:name": "G40 2DL",
    "wof:placetype": "postalcode"
  },
  "geometry": {"coordinates":[-4.233564,55.854523],"type":"Point"}
}
