{
  "type": "Feature",
  "properties": {
    "iso:country":"GB",
    "wof:name":"YO32 2JJ",
    "wof:placetype":"postalcode"
},
  "geometry": {"coordinates":[-1.0803762530785,54.01838336220005],"type":"Point"}
}