{
  "type": "Feature",
  "properties": {
    "date:inception_lower":"1998-06-01",
    "date:inception_upper":"1998-06-30",
    "iso:country":"GB",
    "wof:name":"YO32 2JJ",
    "wof:placetype":"postalcode"
},
  "geometry": {"coordinates":[-1.080376,54.018383],"type":"Point"}
}