{
  "type": "Feature",
  "properties": {
    "iso:country": "GB",
    "wof:name": "YO32 2JJ",
    "wof:placetype": "postalcode"
  },
  "geometry": {"coordinates":[-1.080376,54.018383],"type":"Point"}
}
