{
  "type": "Feature",
  "properties": {
    "iso:country":"GB",
    "wof:name":"BR4 0HZ",
    "wof:placetype":"postalcode"
},
  "geometry": {"coordinates":[-0.0008824244022,51.39048481416021],"type":"Point"}
}