{
  "type": "Feature",
  "properties": {
    "iso:country":"GB",
    "wof:name":"NW11 0PB",
    "wof:placetype":"postalcode"
},
  "geometry": {"coordinates":[-0.19793771103254,51.57657925099836],"type":"Point"}
}