{
  "type": "Feature",
  "properties": {
    "iso:country": "GB",
    "wof:name": "NW11 0PB",
    "wof:placetype": "postalcode"
  },
  "geometry": {"coordinates":[-0.197938,51.576579],"type":"Point"}
}
