{
  "type": "Feature",
  "properties": {
    "iso:country":"GB",
    "wof:name":"CM9 6JS",
    "wof:placetype":"postalcode"
},
  "geometry": {"coordinates":[0.67062957593521,51.72355992608907],"type":"Point"}
}