{
  "type": "Feature",
  "properties": {
    "date:inception_lower":"2013-09-01",
    "date:inception_upper":"2013-09-30",
    "iso:country":"GB",
    "wof:name":"SL7 2PH",
    "wof:placetype":"postalcode"
},
  "geometry": {"coordinates":[-0.777601,51.571981],"type":"Point"}
}