{
  "type": "Feature",
  "properties": {
    "iso:country": "GB",
    "wof:name": "SL7 2PH",
    "wof:placetype": "postalcode"
  },
  "geometry": {"coordinates":[-0.777601,51.571981],"type":"Point"}
}
