{
  "type": "Feature",
  "properties": {
    "iso:country":"GB",
    "wof:name":"GL51 0RG",
    "wof:placetype":"postalcode"
},
  "geometry": {"coordinates":[-2.11772979626027,51.90919282190593],"type":"Point"}
}