{
  "type": "Feature",
  "properties": {
    "date:inception_lower": "1980-01-01",
    "date:inception_upper": "1980-01-01",
    "iso:country": "GB",
    "wof:name": "GL51 0RG",
    "wof:placetype": "postalcode"
  },
  "geometry": {"coordinates":[-2.11773,51.909193],"type":"Point"}
}
