{
  "type": "Feature",
  "properties": {
    "iso:country": "GB",
    "wof:name": "BA9 9FL",
    "wof:placetype": "postalcode"
  },
  "geometry": {"coordinates":[-2.40644,51.057131],"type":"Point"}
}
