{
  "type": "Feature",
  "properties": {
    "iso:country":"GB",
    "wof:name":"BA9 9FL",
    "wof:placetype":"postalcode"
},
  "geometry": {"coordinates":[-2.4064396401371,51.05713128979362],"type":"Point"}
}