{
  "type": "Feature",
  "properties": {
    "iso:country":"GB",
    "wof:name":"CV37 0SA",
    "wof:placetype":"postalcode"
},
  "geometry": {"coordinates":[-1.74758318154603,52.24556283465054],"type":"Point"}
}