{
  "type": "Feature",
  "properties": {
    "iso:country":"GB",
    "wof:name":"M40 1HR",
    "wof:placetype":"postalcode"
},
  "geometry": {"coordinates":[-2.1756095269665,53.50188452391615],"type":"Point"}
}