{
  "type": "Feature",
  "properties": {
    "date:inception_lower": "1994-05-01",
    "date:inception_upper": "1994-05-01",
    "iso:country": "GB",
    "wof:name": "M40 1HR",
    "wof:placetype": "postalcode"
  },
  "geometry": {"coordinates":[-2.175609,53.501885],"type":"Point"}
}
