{
  "type": "Feature",
  "properties": {
    "date:inception_lower": "2018-05-01",
    "date:inception_upper": "2018-05-01",
    "iso:country": "GB",
    "wof:name": "DE15 0TW",
    "wof:placetype": "postalcode"
  },
  "geometry": {"coordinates":[-1.607758,52.815781],"type":"Point"}
}
