{
  "type": "Feature",
  "properties": {
    "iso:country":"GB",
    "wof:name":"FY4 4BD",
    "wof:placetype":"postalcode"
},
  "geometry": {"coordinates":[-3.02972177752686,53.79891967174191],"type":"Point"}
}