{
  "type": "Feature",
  "properties": {
    "iso:country":"GB",
    "wof:name":"MK42 8QY",
    "wof:placetype":"postalcode"
},
  "geometry": {"coordinates":[-0.49833345167196,52.12407376736054],"type":"Point"}
}