{
  "type": "Feature",
  "properties": {
    "iso:country":"GB",
    "wof:name":"GU14 8JD",
    "wof:placetype":"postalcode"
},
  "geometry": {"coordinates":[-0.75505329751964,51.30926656045299],"type":"Point"}
}