{
  "type": "Feature",
  "properties": {
    "iso:country": "GB",
    "wof:name": "GU14 8JD",
    "wof:placetype": "postalcode"
  },
  "geometry": {"coordinates":[-0.755053,51.309267],"type":"Point"}
}
