{
  "type": "Feature",
  "properties": {
    "iso:country":"GB",
    "wof:name":"NR20 4NL",
    "wof:placetype":"postalcode"
},
  "geometry": {"coordinates":[0.98150189304544,52.70733978268553],"type":"Point"}
}