{
  "type": "Feature",
  "properties": {
    "iso:country":"GB",
    "wof:name":"CA7 8LY",
    "wof:placetype":"postalcode"
},
  "geometry": {"coordinates":[-3.134979982328,54.80182156978573],"type":"Point"}
}