{
  "type": "Feature",
  "properties": {
    "iso:country": "GB",
    "wof:name": "DN5 7PX",
    "wof:placetype": "postalcode"
  },
  "geometry": {"coordinates":[-1.169107,53.519092],"type":"Point"}
}
