{
  "type": "Feature",
  "properties": {
    "iso:country":"GB",
    "wof:name":"CH1 5BJ",
    "wof:placetype":"postalcode"
},
  "geometry": {"coordinates":[-2.91293561022232,53.20543182231144],"type":"Point"}
}