{
  "type": "Feature",
  "properties": {
    "iso:country": "GB",
    "wof:name": "GL6 0HW",
    "wof:placetype": "postalcode"
  },
  "geometry": {"coordinates":[-2.216723,51.694338],"type":"Point"}
}
