{
  "type": "Feature",
  "properties": {
    "iso:country":"GB",
    "wof:name":"NN14 6JS",
    "wof:placetype":"postalcode"
},
  "geometry": {"coordinates":[-0.78639065267923,52.42152317030838],"type":"Point"}
}