{
  "type": "Feature",
  "properties": {
    "iso:country":"GB",
    "wof:name":"DE23 2QQ",
    "wof:placetype":"postalcode"
},
  "geometry": {"coordinates":[-1.50517373529189,52.88788065615252],"type":"Point"}
}