{
  "type": "Feature",
  "properties": {
    "date:inception_lower": "1980-01-01",
    "date:inception_upper": "1980-01-01",
    "iso:country": "GB",
    "wof:name": "LE7 9QE",
    "wof:placetype": "postalcode"
  },
  "geometry": {"coordinates":[-1.03742,52.629466],"type":"Point"}
}
