{
  "type": "Feature",
  "properties": {
    "iso:country":"GB",
    "wof:name":"BS2 9DS",
    "wof:placetype":"postalcode"
},
  "geometry": {"coordinates":[-2.58094198459254,51.45941250651055],"type":"Point"}
}