{
  "type": "Feature",
  "properties": {
    "date:inception_lower":"1980-01-01",
    "date:inception_upper":"1980-01-31",
    "iso:country":"GB",
    "wof:name":"NW2 4JT",
    "wof:placetype":"postalcode"
},
  "geometry": {"coordinates":[-0.223505,51.553151],"type":"Point"}
}