{
  "type": "Feature",
  "properties": {
    "iso:country":"GB",
    "wof:name":"NW2 4JT",
    "wof:placetype":"postalcode"
},
  "geometry": {"coordinates":[-0.22342885781545,51.55314720811925],"type":"Point"}
}