{
  "type": "Feature",
  "properties": {
    "iso:country":"GB",
    "wof:name":"LN6 8HT",
    "wof:placetype":"postalcode"
},
  "geometry": {"coordinates":[-0.57593474721329,53.19354728385402],"type":"Point"}
}