{
  "type": "Feature",
  "properties": {
    "iso:country":"GB",
    "wof:name":"PO20 1NR",
    "wof:placetype":"postalcode"
},
  "geometry": {"coordinates":[-0.7743680452187,50.81294540141536],"type":"Point"}
}