{
  "type": "Feature",
  "properties": {
    "iso:country":"GB",
    "wof:name":"PO22 7QY",
    "wof:placetype":"postalcode"
},
  "geometry": {"coordinates":[-0.62929863560806,50.79262584278472],"type":"Point"}
}