{
  "type": "Feature",
  "properties": {
    "date:inception_lower": "2018-05-01",
    "date:inception_upper": "2018-05-01",
    "iso:country": "GB",
    "wof:name": "N22 5BF",
    "wof:placetype": "postalcode"
  },
  "geometry": {"coordinates":[-0.111352,51.601569],"type":"Point"}
}
