{
  "type": "Feature",
  "properties": {
    "iso:country": "GB",
    "wof:name": "NP23 7RR",
    "wof:placetype": "postalcode"
  },
  "geometry": {"coordinates":[-3.18089,51.741605],"type":"Point"}
}
