{
  "type": "Feature",
  "properties": {
    "iso:country":"GB",
    "wof:name":"NP23 7RR",
    "wof:placetype":"postalcode"
},
  "geometry": {"coordinates":[-3.18089002699305,51.74160546216461],"type":"Point"}
}