{
  "type": "Feature",
  "properties": {
    "iso:country":"GB",
    "wof:name":"SO41 8YF",
    "wof:placetype":"postalcode"
},
  "geometry": {"coordinates":[-1.54947191055907,50.76942974029708],"type":"Point"}
}