{
  "type": "Feature",
  "properties": {
    "iso:country": "GB",
    "wof:name": "B25 8UT",
    "wof:placetype": "postalcode"
  },
  "geometry": {"coordinates":[-1.807741,52.468057],"type":"Point"}
}
