{
  "type": "Feature",
  "properties": {
    "iso:country":"GB",
    "wof:name":"HX2 9DT",
    "wof:placetype":"postalcode"
},
  "geometry": {"coordinates":[-1.89164812198454,53.75980088300147],"type":"Point"}
}