{
  "type": "Feature",
  "properties": {
    "iso:country": "GB",
    "wof:name": "HX2 9DT",
    "wof:placetype": "postalcode"
  },
  "geometry": {"coordinates":[-1.891648,53.759801],"type":"Point"}
}
