{
  "type": "Feature",
  "properties": {
    "iso:country":"GB",
    "wof:name":"B29 6BE",
    "wof:placetype":"postalcode"
},
  "geometry": {"coordinates":[-1.9336024264224,52.44537727207868],"type":"Point"}
}