{
  "type": "Feature",
  "properties": {
    "iso:country":"GB",
    "wof:name":"WS3 4HY",
    "wof:placetype":"postalcode"
},
  "geometry": {"coordinates":[-1.96538180588317,52.63392626293417],"type":"Point"}
}