{
  "type": "Feature",
  "properties": {
    "iso:country": "GB",
    "wof:name": "NR10 3BB",
    "wof:placetype": "postalcode"
  },
  "geometry": {"coordinates":[1.24203,52.696117],"type":"Point"}
}
