{
  "type": "Feature",
  "properties": {
    "date:inception_lower":"1993-01-01",
    "date:inception_upper":"1993-01-31",
    "iso:country":"GB",
    "wof:name":"NR10 3BB",
    "wof:placetype":"postalcode"
},
  "geometry": {"coordinates":[1.24203,52.696117],"type":"Point"}
}