{
  "type": "Feature",
  "properties": {
    "iso:country": "GB",
    "wof:name": "CH7 4PB",
    "wof:placetype": "postalcode"
  },
  "geometry": {"coordinates":[-3.122285,53.115745],"type":"Point"}
}
