{
  "type": "Feature",
  "properties": {
    "iso:country":"GB",
    "wof:name":"CH7 4PB",
    "wof:placetype":"postalcode"
},
  "geometry": {"coordinates":[-3.12228521211607,53.1157450930671],"type":"Point"}
}