{
  "type": "Feature",
  "properties": {
    "iso:country":"GB",
    "wof:name":"SS16 6LX",
    "wof:placetype":"postalcode"
},
  "geometry": {"coordinates":[0.41893499480792,51.5588190947953],"type":"Point"}
}