{
  "type": "Feature",
  "properties": {
    "date:inception_lower":"1992-08-01",
    "date:inception_upper":"1992-08-31",
    "iso:country":"GB",
    "wof:name":"SS16 6LX",
    "wof:placetype":"postalcode"
},
  "geometry": {"coordinates":[0.418935,51.558819],"type":"Point"}
}