{
  "type": "Feature",
  "properties": {
    "iso:country":"GB",
    "wof:name":"DY6 8JQ",
    "wof:placetype":"postalcode"
},
  "geometry": {"coordinates":[-2.15243444305588,52.48292929230328],"type":"Point"}
}