{
  "type": "Feature",
  "properties": {
    "iso:country": "GB",
    "wof:name": "DY6 8JQ",
    "wof:placetype": "postalcode"
  },
  "geometry": {"coordinates":[-2.152561,52.482925],"type":"Point"}
}
