{
  "type": "Feature",
  "properties": {
    "iso:country":"GB",
    "wof:name":"RH10 7RT",
    "wof:placetype":"postalcode"
},
  "geometry": {"coordinates":[-0.14288778782459,51.11175862842483],"type":"Point"}
}