{
  "type": "Feature",
  "properties": {
    "iso:country":"GB",
    "wof:name":"SS8 8HL",
    "wof:placetype":"postalcode"
},
  "geometry": {"coordinates":[0.60596970119363,51.52738253879466],"type":"Point"}
}