{
  "type": "Feature",
  "properties": {
    "iso:country": "GB",
    "wof:name": "GL18 1EX",
    "wof:placetype": "postalcode"
  },
  "geometry": {"coordinates":[-2.395692,51.933032],"type":"Point"}
}
