{
  "type": "Feature",
  "properties": {
    "iso:country":"GB",
    "wof:name":"TR11 2HJ",
    "wof:placetype":"postalcode"
},
  "geometry": {"coordinates":[-5.09168736825376,50.15917095480287],"type":"Point"}
}