{
  "type": "Feature",
  "properties": {
    "iso:country":"GB",
    "wof:name":"N12 0QA",
    "wof:placetype":"postalcode"
},
  "geometry": {"coordinates":[-0.16684535296497,51.60828135708574],"type":"Point"}
}