{
  "type": "Feature",
  "properties": {
    "iso:country":"GB",
    "wof:name":"NR25 6JX",
    "wof:placetype":"postalcode"
},
  "geometry": {"coordinates":[1.11305016559245,52.89911396221127],"type":"Point"}
}