{
  "type": "Feature",
  "properties": {
    "iso:country":"GB",
    "wof:name":"KY3 0TT",
    "wof:placetype":"postalcode"
},
  "geometry": {"coordinates":[-3.30048837420957,56.0515091909479],"type":"Point"}
}