{
  "type": "Feature",
  "properties": {
    "iso:country":"GB",
    "wof:name":"GL15 4JW",
    "wof:placetype":"postalcode"
},
  "geometry": {"coordinates":[-2.5587164926316,51.77434477926833],"type":"Point"}
}