{
  "type": "Feature",
  "properties": {
    "iso:country":"GB",
    "wof:name":"BB6 7HB",
    "wof:placetype":"postalcode"
},
  "geometry": {"coordinates":[-2.40813882467608,53.78522833143968],"type":"Point"}
}