{
  "type": "Feature",
  "properties": {
    "date:inception_lower": "1980-01-01",
    "date:inception_upper": "1980-01-01",
    "iso:country": "GB",
    "wof:name": "TR4 9QJ",
    "wof:placetype": "postalcode"
  },
  "geometry": {"coordinates":[-5.111332,50.349627],"type":"Point"}
}
