{
  "type": "Feature",
  "properties": {
    "iso:country":"GB",
    "wof:name":"TR4 9QJ",
    "wof:placetype":"postalcode"
},
  "geometry": {"coordinates":[-5.11133238100699,50.34962689236826],"type":"Point"}
}