{
  "type": "Feature",
  "properties": {
    "iso:country": "GB",
    "wof:name": "DA16 2LP",
    "wof:placetype": "postalcode"
  },
  "geometry": {"coordinates":[0.098872,51.455162],"type":"Point"}
}
