{
  "type": "Feature",
  "properties": {
    "date:inception_lower":"1980-01-01",
    "date:inception_upper":"1980-01-31",
    "iso:country":"GB",
    "wof:name":"DA16 2LP",
    "wof:placetype":"postalcode"
},
  "geometry": {"coordinates":[0.098872,51.455162],"type":"Point"}
}