{
  "type": "Feature",
  "properties": {
    "date:inception_lower": "1980-01-01",
    "date:inception_upper": "1980-01-01",
    "iso:country": "GB",
    "wof:name": "EH1 2PA",
    "wof:placetype": "postalcode"
  },
  "geometry": {"coordinates":[-3.193488,55.949519],"type":"Point"}
}
