{
  "type": "Feature",
  "properties": {
    "iso:country": "GB",
    "wof:name": "LS27 8WA",
    "wof:placetype": "postalcode"
  },
  "geometry": {"coordinates":[-1.585123,53.745327],"type":"Point"}
}
