{
  "type": "Feature",
  "properties": {
    "iso:country": "GB",
    "wof:name": "CW12 1NW",
    "wof:placetype": "postalcode"
  },
  "geometry": {"coordinates":[-2.212883,53.16874],"type":"Point"}
}
