{
  "type": "Feature",
  "properties": {
    "iso:country":"GB",
    "wof:name":"CW12 1NW",
    "wof:placetype":"postalcode"
},
  "geometry": {"coordinates":[-2.21288300505374,53.16873961559906],"type":"Point"}
}