{
  "type": "Feature",
  "properties": {
    "iso:country": "GB",
    "wof:name": "TD14 5NR",
    "wof:placetype": "postalcode"
  },
  "geometry": {"coordinates":[-2.151744,55.888665],"type":"Point"}
}
