{
  "type": "Feature",
  "properties": {
    "iso:country":"GB",
    "wof:name":"NN6 9JP",
    "wof:placetype":"postalcode"
},
  "geometry": {"coordinates":[-0.87419782900088,52.34348162099093],"type":"Point"}
}