{
  "type": "Feature",
  "properties": {
    "iso:country": "GB",
    "wof:name": "NN6 9JP",
    "wof:placetype": "postalcode"
  },
  "geometry": {"coordinates":[-0.874198,52.343482],"type":"Point"}
}
