{
  "type": "Feature",
  "properties": {
    "date:inception_lower":"1980-01-01",
    "date:inception_upper":"1980-01-31",
    "iso:country":"GB",
    "wof:name":"NN6 9JP",
    "wof:placetype":"postalcode"
},
  "geometry": {"coordinates":[-0.874198,52.343482],"type":"Point"}
}