{
  "type": "Feature",
  "properties": {
    "iso:country":"GB",
    "wof:name":"CO13 9NP",
    "wof:placetype":"postalcode"
},
  "geometry": {"coordinates":[1.25794534669843,51.8408158749577],"type":"Point"}
}