{
  "type": "Feature",
  "properties": {
    "date:inception_lower":"2018-11-01",
    "date:inception_upper":"2018-11-30",
    "iso:country":"GB",
    "wof:name":"S11 8XY",
    "wof:placetype":"postalcode"
},
  "geometry": {"coordinates":[-1.497026,53.367107],"type":"Point"}
}