{
  "type": "Feature",
  "properties": {
    "iso:country": "GB",
    "wof:name": "S11 8XY",
    "wof:placetype": "postalcode"
  },
  "geometry": {"coordinates":[-1.497026,53.367098],"type":"Point"}
}
