{
  "type": "Feature",
  "properties": {
    "iso:country":"GB",
    "wof:name":"SK6 4JL",
    "wof:placetype":"postalcode"
},
  "geometry": {"coordinates":[-2.06427970526046,53.41575210742523],"type":"Point"}
}