{
  "type": "Feature",
  "properties": {
    "iso:country": "GB",
    "wof:name": "SK6 4JL",
    "wof:placetype": "postalcode"
  },
  "geometry": {"coordinates":[-2.064265,53.415752],"type":"Point"}
}
