{
  "type": "Feature",
  "properties": {
    "iso:country":"GB",
    "wof:name":"LS17 9DJ",
    "wof:placetype":"postalcode"
},
  "geometry": {"coordinates":[-1.44015973696961,53.88141926856718],"type":"Point"}
}