{
  "type": "Feature",
  "properties": {
    "date:inception_lower":"1985-10-01",
    "date:inception_upper":"1985-10-31",
    "iso:country":"GB",
    "wof:name":"BA11 4BG",
    "wof:placetype":"postalcode"
},
  "geometry": {"coordinates":[-2.327356,51.2221],"type":"Point"}
}