{
  "type": "Feature",
  "properties": {
    "iso:country": "GB",
    "wof:name": "BA11 4BG",
    "wof:placetype": "postalcode"
  },
  "geometry": {"coordinates":[-2.327356,51.2221],"type":"Point"}
}
