{
  "type": "Feature",
  "properties": {
    "date:inception_lower": "1985-10-01",
    "date:inception_upper": "1985-10-01",
    "iso:country": "GB",
    "wof:name": "BA11 4BG",
    "wof:placetype": "postalcode"
  },
  "geometry": {"coordinates":[-2.329402,51.221752],"type":"Point"}
}
