{
  "type": "Feature",
  "properties": {
    "iso:country":"GB",
    "wof:name":"BA11 4BG",
    "wof:placetype":"postalcode"
},
  "geometry": {"coordinates":[-2.32628139825433,51.22145168794665],"type":"Point"}
}