{
  "type": "Feature",
  "properties": {
    "iso:country": "GB",
    "wof:name": "WF10 4UZ",
    "wof:placetype": "postalcode"
  },
  "geometry": {"coordinates":[-1.340833,53.722967],"type":"Point"}
}
