{
  "type": "Feature",
  "properties": {
    "iso:country": "GB",
    "wof:name": "CF62 5BD",
    "wof:placetype": "postalcode"
  },
  "geometry": {"coordinates":[-3.279017,51.395308],"type":"Point"}
}
