{
  "type": "Feature",
  "properties": {
    "date:inception_lower": "2015-09-01",
    "date:inception_upper": "2015-09-01",
    "iso:country": "GB",
    "wof:name": "CF62 5BD",
    "wof:placetype": "postalcode"
  },
  "geometry": {"coordinates":[-3.279017,51.395308],"type":"Point"}
}
