{
  "type": "Feature",
  "properties": {
    "iso:country":"GB",
    "wof:name":"PE12 0NW",
    "wof:placetype":"postalcode"
},
  "geometry": {"coordinates":[-0.02385203208601,52.68181060740081],"type":"Point"}
}