{
  "type": "Feature",
  "properties": {
    "iso:country":"GB",
    "wof:name":"WS14 0AB",
    "wof:placetype":"postalcode"
},
  "geometry": {"coordinates":[-1.83391004841148,52.67230012657547],"type":"Point"}
}