{
  "type": "Feature",
  "properties": {
    "date:inception_lower": "1980-01-01",
    "date:inception_upper": "1980-01-01",
    "iso:country": "GB",
    "wof:name": "WS14 0AB",
    "wof:placetype": "postalcode"
  },
  "geometry": {"coordinates":[-1.83391,52.6723],"type":"Point"}
}
