{
  "type": "Feature",
  "properties": {
    "date:inception_lower": "1998-12-01",
    "date:inception_upper": "1998-12-01",
    "iso:country": "GB",
    "wof:name": "BN8 4JN",
    "wof:placetype": "postalcode"
  },
  "geometry": {"coordinates":[-0.03207,50.972286],"type":"Point"}
}
