{
  "type": "Feature",
  "properties": {
    "iso:country":"GB",
    "wof:name":"BN8 4JN",
    "wof:placetype":"postalcode"
},
  "geometry": {"coordinates":[-0.03206961052668,50.97228567198436],"type":"Point"}
}