{
  "type": "Feature",
  "properties": {
    "date:inception_lower": "1993-01-01",
    "date:inception_upper": "1993-01-01",
    "iso:country": "GB",
    "wof:name": "CF64 1DH",
    "wof:placetype": "postalcode"
  },
  "geometry": {"coordinates":[-3.175484,51.4429],"type":"Point"}
}
