{
  "type": "Feature",
  "properties": {
    "iso:country":"GB",
    "wof:name":"SG5 2BG",
    "wof:placetype":"postalcode"
},
  "geometry": {"coordinates":[-0.29052881076924,51.94576397723829],"type":"Point"}
}