{
  "type": "Feature",
  "properties": {
    "iso:country": "GB",
    "wof:name": "SG5 2BG",
    "wof:placetype": "postalcode"
  },
  "geometry": {"coordinates":[-0.290519,51.945771],"type":"Point"}
}
