{
  "type": "Feature",
  "properties": {
    "iso:country": "GB",
    "wof:name": "ME16 0TP",
    "wof:placetype": "postalcode"
  },
  "geometry": {"coordinates":[0.502387,51.288478],"type":"Point"}
}
