{
  "type": "Feature",
  "properties": {
    "iso:country":"GB",
    "wof:name":"DA6 8LF",
    "wof:placetype":"postalcode"
},
  "geometry": {"coordinates":[0.13094865639247,51.45808144572857],"type":"Point"}
}