{
  "type": "Feature",
  "properties": {
    "iso:country":"GB",
    "wof:name":"WA8 7DW",
    "wof:placetype":"postalcode"
},
  "geometry": {"coordinates":[-2.73988230177657,53.3734040985139],"type":"Point"}
}