{
  "type": "Feature",
  "properties": {
    "date:inception_lower": "1980-01-01",
    "date:inception_upper": "1980-01-01",
    "iso:country": "GB",
    "wof:name": "WA8 7DW",
    "wof:placetype": "postalcode"
  },
  "geometry": {"coordinates":[-2.739883,53.37342],"type":"Point"}
}
