{
  "type": "Feature",
  "properties": {
    "iso:country": "GB",
    "wof:name": "AL6 0NP",
    "wof:placetype": "postalcode"
  },
  "geometry": {"coordinates":[-0.159062,51.83425],"type":"Point"}
}
