{
  "type": "Feature",
  "properties": {
    "iso:country":"GB",
    "wof:name":"AL6 0NP",
    "wof:placetype":"postalcode"
},
  "geometry": {"coordinates":[-0.15906175135967,51.83425036838322],"type":"Point"}
}