{
  "type": "Feature",
  "properties": {
    "iso:country": "GB",
    "wof:name": "AB39 2TX",
    "wof:placetype": "postalcode"
  },
  "geometry": {"coordinates":[-2.22378,56.907234],"type":"Point"}
}
