{
  "type": "Feature",
  "properties": {
    "iso:country":"GB",
    "wof:name":"RH10 5LR",
    "wof:placetype":"postalcode"
},
  "geometry": {"coordinates":[-0.17675229896566,51.09855926873174],"type":"Point"}
}