{
  "type": "Feature",
  "properties": {
    "iso:country":"GB",
    "wof:name":"IP25 6PB",
    "wof:placetype":"postalcode"
},
  "geometry": {"coordinates":[0.87752976083104,52.58050567202225],"type":"Point"}
}