{
  "type": "Feature",
  "properties": {
    "iso:country": "GB",
    "wof:name": "IP25 6PB",
    "wof:placetype": "postalcode"
  },
  "geometry": {"coordinates":[0.87753,52.580506],"type":"Point"}
}
