{
  "type": "Feature",
  "properties": {
    "date:inception_lower": "1998-12-01",
    "date:inception_upper": "1998-12-01",
    "iso:country": "GB",
    "wof:name": "IP25 6PB",
    "wof:placetype": "postalcode"
  },
  "geometry": {"coordinates":[0.87753,52.580506],"type":"Point"}
}
