{
  "type": "Feature",
  "properties": {
    "iso:country":"GB",
    "wof:name":"DL15 0DJ",
    "wof:placetype":"postalcode"
},
  "geometry": {"coordinates":[-1.67971775641196,54.70804563277024],"type":"Point"}
}