{
  "type": "Feature",
  "properties": {
    "iso:country": "GB",
    "wof:name": "B78 3NR",
    "wof:placetype": "postalcode"
  },
  "geometry": {"coordinates":[-1.720791,52.616567],"type":"Point"}
}
