{
  "type": "Feature",
  "properties": {
    "iso:country": "GB",
    "wof:name": "SW18 3DL",
    "wof:placetype": "postalcode"
  },
  "geometry": {"coordinates":[-0.187841,51.442796],"type":"Point"}
}
