{
  "type": "Feature",
  "properties": {
    "date:inception_lower": "1999-12-01",
    "date:inception_upper": "1999-12-01",
    "iso:country": "GB",
    "wof:name": "SW18 3DL",
    "wof:placetype": "postalcode"
  },
  "geometry": {"coordinates":[-0.187876,51.442743],"type":"Point"}
}
