{
  "type": "Feature",
  "properties": {
    "iso:country":"GB",
    "wof:name":"G72 0ND",
    "wof:placetype":"postalcode"
},
  "geometry": {"coordinates":[-4.0853389082463,55.78321499608934],"type":"Point"}
}