{
  "type": "Feature",
  "properties": {
    "iso:country": "GB",
    "wof:name": "G72 0ND",
    "wof:placetype": "postalcode"
  },
  "geometry": {"coordinates":[-4.085101,55.78317],"type":"Point"}
}
