{
  "type": "Feature",
  "properties": {
    "date:inception_lower": "2021-05-01",
    "date:inception_upper": "2021-05-01",
    "iso:country": "GB",
    "wof:name": "HU16 5FG",
    "wof:placetype": "postalcode"
  },
  "geometry": {"coordinates":[-0.435308,53.774713],"type":"Point"}
}
