{
  "type": "Feature",
  "properties": {
    "iso:country":"GB",
    "wof:name":"LS22 5RF",
    "wof:placetype":"postalcode"
},
  "geometry": {"coordinates":[-1.3772402939911,53.93169368231094],"type":"Point"}
}