{
  "type": "Feature",
  "properties": {
    "iso:country": "GB",
    "wof:name": "LS22 5RF",
    "wof:placetype": "postalcode"
  },
  "geometry": {"coordinates":[-1.37724,53.931694],"type":"Point"}
}
