{
  "type": "Feature",
  "properties": {
    "iso:country": "GB",
    "wof:name": "B16 6WH",
    "wof:placetype": "postalcode"
  },
  "geometry": {"coordinates":[-1.930287,52.473385],"type":"Point"}
}
