{
  "type": "Feature",
  "properties": {
    "iso:country": "GB",
    "wof:name": "BL3 1FS",
    "wof:placetype": "postalcode"
  },
  "geometry": {"coordinates":[-2.382001,53.566108],"type":"Point"}
}
