{
  "type": "Feature",
  "properties": {
    "iso:country":"GB",
    "wof:name":"M50 3SG",
    "wof:placetype":"postalcode"
},
  "geometry": {"coordinates":[-2.28414528064821,53.46882275574249],"type":"Point"}
}