{
  "type": "Feature",
  "properties": {
    "iso:country":"GB",
    "wof:name":"CV5 7HF",
    "wof:placetype":"postalcode"
},
  "geometry": {"coordinates":[-1.56917782733114,52.41000918091704],"type":"Point"}
}