{
  "type": "Feature",
  "properties": {
    "date:inception_lower": "2018-09-01",
    "date:inception_upper": "2018-09-01",
    "iso:country": "GB",
    "wof:name": "CV37 8FS",
    "wof:placetype": "postalcode"
  },
  "geometry": {"coordinates":[-1.761802,52.123452],"type":"Point"}
}
