{
  "type": "Feature",
  "properties": {
    "iso:country": "GB",
    "wof:name": "CV37 8FS",
    "wof:placetype": "postalcode"
  },
  "geometry": {"coordinates":[-1.761802,52.123452],"type":"Point"}
}
