{
  "type": "Feature",
  "properties": {
    "iso:country":"GB",
    "wof:name":"M29 7FW",
    "wof:placetype":"postalcode"
},
  "geometry": {"coordinates":[-2.46222926691672,53.50581123463466],"type":"Point"}
}