{
  "type": "Feature",
  "properties": {
    "date:inception_lower": "2020-11-01",
    "date:inception_upper": "2020-11-01",
    "iso:country": "GB",
    "wof:name": "CF39 8QE",
    "wof:placetype": "postalcode"
  },
  "geometry": {"coordinates":[-3.452914,51.578209],"type":"Point"}
}
