{
  "type": "Feature",
  "properties": {
    "iso:country": "GB",
    "wof:name": "G61 4AZ",
    "wof:placetype": "postalcode"
  },
  "geometry": {"coordinates":[-4.345583,55.917763],"type":"Point"}
}
