{
  "type": "Feature",
  "properties": {
    "iso:country": "GB",
    "wof:name": "CV35 7JJ",
    "wof:placetype": "postalcode"
  },
  "geometry": {"coordinates":[-1.646068,52.300961],"type":"Point"}
}
