{
  "type": "Feature",
  "properties": {
    "iso:country":"GB",
    "wof:name":"LE10 2SE",
    "wof:placetype":"postalcode"
},
  "geometry": {"coordinates":[-1.36164489750508,52.53009625613235],"type":"Point"}
}