{
  "type": "Feature",
  "properties": {
    "date:inception_lower": "1998-12-01",
    "date:inception_upper": "1998-12-01",
    "iso:country": "GB",
    "wof:name": "KY13 8TR",
    "wof:placetype": "postalcode"
  },
  "geometry": {"coordinates":[-3.428104,56.207291],"type":"Point"}
}
