{
  "type": "Feature",
  "properties": {
    "iso:country": "GB",
    "wof:name": "KY13 8TR",
    "wof:placetype": "postalcode"
  },
  "geometry": {"coordinates":[-3.428104,56.207291],"type":"Point"}
}
