{
  "type": "Feature",
  "properties": {
    "iso:country":"GB",
    "wof:name":"LE12 8EB",
    "wof:placetype":"postalcode"
},
  "geometry": {"coordinates":[-1.17487084692944,52.74711039580379],"type":"Point"}
}