{
  "type": "Feature",
  "properties": {
    "iso:country": "GB",
    "wof:name": "LE12 8EB",
    "wof:placetype": "postalcode"
  },
  "geometry": {"coordinates":[-1.174871,52.74711],"type":"Point"}
}
