{
  "type": "Feature",
  "properties": {
    "iso:country":"GB",
    "wof:name":"ST4 8DP",
    "wof:placetype":"postalcode"
},
  "geometry": {"coordinates":[-2.17587030603588,52.97006971996397],"type":"Point"}
}