{
  "type": "Feature",
  "properties": {
    "iso:country": "GB",
    "wof:name": "CR3 0HL",
    "wof:placetype": "postalcode"
  },
  "geometry": {"coordinates":[-0.071819,51.300109],"type":"Point"}
}
