{
  "type": "Feature",
  "properties": {
    "date:inception_lower": "2012-02-01",
    "date:inception_upper": "2012-02-01",
    "iso:country": "GB",
    "wof:name": "CR3 0HL",
    "wof:placetype": "postalcode"
  },
  "geometry": {"coordinates":[-0.071819,51.300109],"type":"Point"}
}
