{
  "type": "Feature",
  "properties": {
    "iso:country":"GB",
    "wof:name":"DN22 9LJ",
    "wof:placetype":"postalcode"
},
  "geometry": {"coordinates":[-0.90607718142375,53.35339366585543],"type":"Point"}
}