{
  "type": "Feature",
  "properties": {
    "date:inception_lower": "1980-01-01",
    "date:inception_upper": "1980-01-01",
    "iso:country": "GB",
    "wof:name": "SL9 9RN",
    "wof:placetype": "postalcode"
  },
  "geometry": {"coordinates":[-0.557918,51.608153],"type":"Point"}
}
