{
  "type": "Feature",
  "properties": {
    "iso:country":"GB",
    "wof:name":"HG5 0RT",
    "wof:placetype":"postalcode"
},
  "geometry": {"coordinates":[-1.39843037041047,54.01609860329879],"type":"Point"}
}