{
  "type": "Feature",
  "properties": {
    "iso:country":"GB",
    "wof:name":"CA3 0LW",
    "wof:placetype":"postalcode"
},
  "geometry": {"coordinates":[-2.92516401049498,54.92403436127396],"type":"Point"}
}