{
  "type": "Feature",
  "properties": {
    "iso:country": "GB",
    "wof:name": "CA3 0LW",
    "wof:placetype": "postalcode"
  },
  "geometry": {"coordinates":[-2.925164,54.924034],"type":"Point"}
}
