{
  "type": "Feature",
  "properties": {
    "iso:country":"GB",
    "wof:name":"IP22 4DD",
    "wof:placetype":"postalcode"
},
  "geometry": {"coordinates":[1.11037325632433,52.37684084943393],"type":"Point"}
}