{
  "type": "Feature",
  "properties": {
    "date:inception_lower":"1999-12-01",
    "date:inception_upper":"1999-12-31",
    "iso:country":"GB",
    "wof:name":"IP22 4DD",
    "wof:placetype":"postalcode"
},
  "geometry": {"coordinates":[1.110373,52.376841],"type":"Point"}
}