{
  "type": "Feature",
  "properties": {
    "date:inception_lower":"1992-10-01",
    "date:inception_upper":"1992-10-31",
    "iso:country":"GB",
    "wof:name":"EH4 1Ht",
    "wof:placetype":"postalcode"
},
  "geometry": {"coordinates":[-3.222454,55.957025],"type":"Point"}
}