{
  "type": "Feature",
  "properties": {
    "iso:country":"GB",
    "wof:name":"DH4 4PZ",
    "wof:placetype":"postalcode"
},
  "geometry": {"coordinates":[-1.50432639877749,54.86207896112987],"type":"Point"}
}