{
  "type": "Feature",
  "properties": {
    "date:inception_lower": "2005-12-01",
    "date:inception_upper": "2005-12-01",
    "iso:country": "GB",
    "wof:name": "FK7 7DL",
    "wof:placetype": "postalcode"
  },
  "geometry": {"coordinates":[-3.866826,56.086457],"type":"Point"}
}
