{
  "type": "Feature",
  "properties": {
    "iso:country":"GB",
    "wof:name":"FK7 7DL",
    "wof:placetype":"postalcode"
},
  "geometry": {"coordinates":[-3.86682613884688,56.08645686600487],"type":"Point"}
}