{
  "type": "Feature",
  "properties": {
    "date:inception_lower": "1980-01-01",
    "date:inception_upper": "1980-01-01",
    "iso:country": "GB",
    "wof:name": "WV4 6AJ",
    "wof:placetype": "postalcode"
  },
  "geometry": {"coordinates":[-2.118006,52.564993],"type":"Point"}
}
