{
  "type": "Feature",
  "properties": {
    "iso:country":"GB",
    "wof:name":"WV4 6AJ",
    "wof:placetype":"postalcode"
},
  "geometry": {"coordinates":[-2.11800650898099,52.56499252151922],"type":"Point"}
}