{
  "type": "Feature",
  "properties": {
    "iso:country":"GB",
    "wof:name":"CF34 9PP",
    "wof:placetype":"postalcode"
},
  "geometry": {"coordinates":[-3.6714214583261,51.61134449557857],"type":"Point"}
}