{
  "type": "Feature",
  "properties": {
    "iso:country":"GB",
    "wof:name":"TA22 9EU",
    "wof:placetype":"postalcode"
},
  "geometry": {"coordinates":[-3.54341114446507,51.03630429655679],"type":"Point"}
}