{
  "type": "Feature",
  "properties": {
    "date:inception_lower":"1991-09-01",
    "date:inception_upper":"1991-09-30",
    "iso:country":"GB",
    "wof:name":"TA22 9EU",
    "wof:placetype":"postalcode"
},
  "geometry": {"coordinates":[-3.543411,51.036304],"type":"Point"}
}