{
  "type": "Feature",
  "properties": {
    "iso:country": "GB",
    "wof:name": "TA22 9EU",
    "wof:placetype": "postalcode"
  },
  "geometry": {"coordinates":[-3.543411,51.036304],"type":"Point"}
}
