{
  "type": "Feature",
  "properties": {
    "iso:country": "GB",
    "wof:name": "WA9 5DA",
    "wof:placetype": "postalcode"
  },
  "geometry": {"coordinates":[-2.765876,53.425706],"type":"Point"}
}
