{
  "type": "Feature",
  "properties": {
    "date:inception_lower": "1980-01-01",
    "date:inception_upper": "1980-01-01",
    "iso:country": "GB",
    "wof:name": "WA9 5DA",
    "wof:placetype": "postalcode"
  },
  "geometry": {"coordinates":[-2.765876,53.425706],"type":"Point"}
}
