{
  "type": "Feature",
  "properties": {
    "iso:country":"GB",
    "wof:name":"ZE1 0DP",
    "wof:placetype":"postalcode"
},
  "geometry": {"coordinates":[-1.1439071468969,60.15367664531092],"type":"Point"}
}