{
  "type": "Feature",
  "properties": {
    "iso:country":"GB",
    "wof:name":"CT9 1JH",
    "wof:placetype":"postalcode"
},
  "geometry": {"coordinates":[1.38666033296581,51.39098577708469],"type":"Point"}
}