{
  "type": "Feature",
  "properties": {
    "iso:country": "GB",
    "wof:name": "NE16 5UT",
    "wof:placetype": "postalcode"
  },
  "geometry": {"coordinates":[-1.699364,54.936837],"type":"Point"}
}
