{
  "type": "Feature",
  "properties": {
    "iso:country":"GB",
    "wof:name":"EH22 4QU",
    "wof:placetype":"postalcode"
},
  "geometry": {"coordinates":[-3.06126969035951,55.86134234861075],"type":"Point"}
}