{
  "type": "Feature",
  "properties": {
    "date:inception_lower": "1990-06-01",
    "date:inception_upper": "1990-06-01",
    "iso:country": "GB",
    "wof:name": "EH22 4QU",
    "wof:placetype": "postalcode"
  },
  "geometry": {"coordinates":[-3.06127,55.861342],"type":"Point"}
}
