{
  "type": "Feature",
  "properties": {
    "iso:country": "GB",
    "wof:name": "CV36 5EL",
    "wof:placetype": "postalcode"
  },
  "geometry": {"coordinates":[-1.569721,52.07983],"type":"Point"}
}
