{
  "type": "Feature",
  "properties": {
    "iso:country":"GB",
    "wof:name":"W12 8QX",
    "wof:placetype":"postalcode"
},
  "geometry": {"coordinates":[-0.2198111964721,51.50317558019206],"type":"Point"}
}