{
  "type": "Feature",
  "properties": {
    "date:inception_lower": "1980-01-01",
    "date:inception_upper": "1980-01-01",
    "iso:country": "GB",
    "wof:name": "NN2 6BT",
    "wof:placetype": "postalcode"
  },
  "geometry": {"coordinates":[-0.900002,52.247117],"type":"Point"}
}
