{
  "type": "Feature",
  "properties": {
    "iso:country":"GB",
    "wof:name":"NN2 6BT",
    "wof:placetype":"postalcode"
},
  "geometry": {"coordinates":[-0.90001608112048,52.24710217099837],"type":"Point"}
}