{
  "type": "Feature",
  "properties": {
    "iso:country":"GB",
    "wof:name":"S60 3AP",
    "wof:placetype":"postalcode"
},
  "geometry": {"coordinates":[-1.33969635140079,53.41459286450486],"type":"Point"}
}