{
  "type": "Feature",
  "properties": {
    "iso:country": "GB",
    "wof:name": "BN22 0PP",
    "wof:placetype": "postalcode"
  },
  "geometry": {"coordinates":[0.25426,50.80719],"type":"Point"}
}
