{
  "type": "Feature",
  "properties": {
    "date:inception_lower": "2005-12-01",
    "date:inception_upper": "2005-12-01",
    "iso:country": "GB",
    "wof:name": "SW9 7EN",
    "wof:placetype": "postalcode"
  },
  "geometry": {"coordinates":[-0.109137,51.469412],"type":"Point"}
}
