{
  "type": "Feature",
  "properties": {
    "iso:country":"GB",
    "wof:name":"SW9 7EN",
    "wof:placetype":"postalcode"
},
  "geometry": {"coordinates":[-0.10913673776267,51.46941185065607],"type":"Point"}
}