{
  "type": "Feature",
  "properties": {
    "iso:country":"GB",
    "wof:name":"NN18 8QB",
    "wof:placetype":"postalcode"
},
  "geometry": {"coordinates":[-0.70126696854614,52.47383431143714],"type":"Point"}
}