{
  "type": "Feature",
  "properties": {
    "iso:country": "GB",
    "wof:name": "NN18 8QB",
    "wof:placetype": "postalcode"
  },
  "geometry": {"coordinates":[-0.701267,52.473834],"type":"Point"}
}
