{
  "type": "Feature",
  "properties": {
    "iso:country":"GB",
    "wof:name":"GU47 8JU",
    "wof:placetype":"postalcode"
},
  "geometry": {"coordinates":[-0.809392390866,51.35223849082831],"type":"Point"}
}