{
  "type": "Feature",
  "properties": {
    "iso:country": "GB",
    "wof:name": "GU47 8JU",
    "wof:placetype": "postalcode"
  },
  "geometry": {"coordinates":[-0.809392,51.352238],"type":"Point"}
}
