{
  "type": "Feature",
  "properties": {
    "iso:country":"GB",
    "wof:name":"W8 4BX",
    "wof:placetype":"postalcode"
},
  "geometry": {"coordinates":[-0.19280830678492,51.50429132144436],"type":"Point"}
}