{
  "type": "Feature",
  "properties": {
    "iso:country": "GB",
    "wof:name": "KY15 4SS",
    "wof:placetype": "postalcode"
  },
  "geometry": {"coordinates":[-2.949919,56.345411],"type":"Point"}
}
