{
  "type": "Feature",
  "properties": {
    "iso:country": "GB",
    "wof:name": "HR9 6NU",
    "wof:placetype": "postalcode"
  },
  "geometry": {"coordinates":[-2.678912,51.903488],"type":"Point"}
}
