{
  "type": "Feature",
  "properties": {
    "iso:country": "GB",
    "wof:name": "HR9 6NU",
    "wof:placetype": "postalcode"
  },
  "geometry": {"coordinates":[-2.674245,51.902427],"type":"Point"}
}
