{
  "type": "Feature",
  "properties": {
    "iso:country": "GB",
    "wof:name": "DN11 9DH",
    "wof:placetype": "postalcode"
  },
  "geometry": {"coordinates":[-1.142804,53.486142],"type":"Point"}
}
