{
  "type": "Feature",
  "properties": {
    "date:inception_lower": "2012-05-01",
    "date:inception_upper": "2012-05-01",
    "iso:country": "GB",
    "wof:name": "W2 4AE",
    "wof:placetype": "postalcode"
  },
  "geometry": {"coordinates":[-0.189204,51.513075],"type":"Point"}
}
