{
  "type": "Feature",
  "properties": {
    "date:inception_lower": "1997-06-01",
    "date:inception_upper": "1997-06-01",
    "iso:country": "GB",
    "wof:name": "SA7 9XZ",
    "wof:placetype": "postalcode"
  },
  "geometry": {"coordinates":[-3.895154,51.653137],"type":"Point"}
}
