{
  "type": "Feature",
  "properties": {
    "iso:country": "GB",
    "wof:name": "SA7 9XZ",
    "wof:placetype": "postalcode"
  },
  "geometry": {"coordinates":[-3.895121,51.653096],"type":"Point"}
}
