{
  "type": "Feature",
  "properties": {
    "iso:country":"GB",
    "wof:name":"SA7 9XZ",
    "wof:placetype":"postalcode"
},
  "geometry": {"coordinates":[-3.8951208969957,51.65309591906274],"type":"Point"}
}