{
  "type": "Feature",
  "properties": {
    "date:inception_lower":"1991-09-01",
    "date:inception_upper":"1991-09-30",
    "iso:country":"GB",
    "wof:name":"HU15 2NN",
    "wof:placetype":"postalcode"
},
  "geometry": {"coordinates":[-0.648535,53.7824],"type":"Point"}
}