{
  "type": "Feature",
  "properties": {
    "iso:country": "GB",
    "wof:name": "HU15 2NN",
    "wof:placetype": "postalcode"
  },
  "geometry": {"coordinates":[-0.648535,53.7824],"type":"Point"}
}
