{
  "type": "Feature",
  "properties": {
    "iso:country":"GB",
    "wof:name":"IV2 4JN",
    "wof:placetype":"postalcode"
},
  "geometry": {"coordinates":[-4.2166527679603,57.4613868770175],"type":"Point"}
}