{
  "type": "Feature",
  "properties": {
    "iso:country": "GB",
    "wof:name": "IV2 4JN",
    "wof:placetype": "postalcode"
  },
  "geometry": {"coordinates":[-4.216653,57.461387],"type":"Point"}
}
