{
  "type": "Feature",
  "properties": {
    "date:inception_lower": "1994-05-01",
    "date:inception_upper": "1994-05-01",
    "iso:country": "GB",
    "wof:name": "ML10 6QT",
    "wof:placetype": "postalcode"
  },
  "geometry": {"coordinates":[-4.05895,55.673207],"type":"Point"}
}
