{
  "type": "Feature",
  "properties": {
    "iso:country": "GB",
    "wof:name": "BB3 1DS",
    "wof:placetype": "postalcode"
  },
  "geometry": {"coordinates":[-2.473415,53.701774],"type":"Point"}
}
