{
  "type": "Feature",
  "properties": {
    "iso:country":"GB",
    "wof:name":"BB3 1DS",
    "wof:placetype":"postalcode"
},
  "geometry": {"coordinates":[-2.47335636571355,53.70168649687155],"type":"Point"}
}