{
  "type": "Feature",
  "properties": {
    "date:inception_lower": "1980-01-01",
    "date:inception_upper": "1980-01-01",
    "iso:country": "GB",
    "wof:name": "BN16 2SJ",
    "wof:placetype": "postalcode"
  },
  "geometry": {"coordinates":[-0.512694,50.803905],"type":"Point"}
}
