{
  "type": "Feature",
  "properties": {
    "iso:country": "GB",
    "wof:name": "ST4 8BB",
    "wof:placetype": "postalcode"
  },
  "geometry": {"coordinates":[-2.18769,52.969359],"type":"Point"}
}
