{
  "type": "Feature",
  "properties": {
    "date:inception_lower": "1980-01-01",
    "date:inception_upper": "1980-01-01",
    "iso:country": "GB",
    "wof:name": "ST4 8BB",
    "wof:placetype": "postalcode"
  },
  "geometry": {"coordinates":[-2.18769,52.969359],"type":"Point"}
}
