{
  "type": "Feature",
  "properties": {
    "date:inception_lower": "1980-01-01",
    "date:inception_upper": "1980-01-01",
    "iso:country": "GB",
    "wof:name": "HU5 3NF",
    "wof:placetype": "postalcode"
  },
  "geometry": {"coordinates":[-0.372015,53.752923],"type":"Point"}
}
