{
  "type": "Feature",
  "properties": {
    "iso:country":"GB",
    "wof:name":"HU5 3NF",
    "wof:placetype":"postalcode"
},
  "geometry": {"coordinates":[-0.37201469775797,53.75292323147004],"type":"Point"}
}