{
  "type": "Feature",
  "properties": {
    "iso:country":"GB",
    "wof:name":"SP11 9EP",
    "wof:placetype":"postalcode"
},
  "geometry": {"coordinates":[-1.57690263561833,51.28292677887886],"type":"Point"}
}