{
  "type": "Feature",
  "properties": {
    "iso:country": "GB",
    "wof:name": "SP11 9EP",
    "wof:placetype": "postalcode"
  },
  "geometry": {"coordinates":[-1.576834,51.282923],"type":"Point"}
}
