{
  "type": "Feature",
  "properties": {
    "date:inception_lower": "1980-01-01",
    "date:inception_upper": "1980-01-01",
    "iso:country": "GB",
    "wof:name": "PL19 0DU",
    "wof:placetype": "postalcode"
  },
  "geometry": {"coordinates":[-4.147525,50.551004],"type":"Point"}
}
