{
  "type": "Feature",
  "properties": {
    "iso:country": "GB",
    "wof:name": "WA7 5DT",
    "wof:placetype": "postalcode"
  },
  "geometry": {"coordinates":[-2.722739,53.335603],"type":"Point"}
}
