{
  "type": "Feature",
  "properties": {
    "iso:country":"GB",
    "wof:name":"SP8 5EJ",
    "wof:placetype":"postalcode"
},
  "geometry": {"coordinates":[-2.33930575398766,51.01012746186009],"type":"Point"}
}