{
  "type": "Feature",
  "properties": {
    "iso:country": "GB",
    "wof:name": "SP8 5EJ",
    "wof:placetype": "postalcode"
  },
  "geometry": {"coordinates":[-2.339306,51.010127],"type":"Point"}
}
