{
  "type": "Feature",
  "properties": {
    "date:inception_lower": "1980-01-01",
    "date:inception_upper": "1980-01-01",
    "iso:country": "GB",
    "wof:name": "SP8 5EJ",
    "wof:placetype": "postalcode"
  },
  "geometry": {"coordinates":[-2.339306,51.010127],"type":"Point"}
}
