{
  "type": "Feature",
  "properties": {
    "iso:country":"GB",
    "wof:name":"PE27 3YB",
    "wof:placetype":"postalcode"
},
  "geometry": {"coordinates":[-0.07673540103371,52.33667142516627],"type":"Point"}
}