{
  "type": "Feature",
  "properties": {
    "date:inception_lower": "1980-01-01",
    "date:inception_upper": "1980-01-01",
    "iso:country": "GB",
    "wof:name": "NG19 0ND",
    "wof:placetype": "postalcode"
  },
  "geometry": {"coordinates":[-1.177414,53.156222],"type":"Point"}
}
