{
  "type": "Feature",
  "properties": {
    "iso:country": "GB",
    "wof:name": "NG19 0ND",
    "wof:placetype": "postalcode"
  },
  "geometry": {"coordinates":[-1.177414,53.156222],"type":"Point"}
}
