{
  "type": "Feature",
  "properties": {
    "iso:country":"GB",
    "wof:name":"CM20 2RL",
    "wof:placetype":"postalcode"
},
  "geometry": {"coordinates":[0.09482931395526,51.79988619635405],"type":"Point"}
}