{
  "type": "Feature",
  "properties": {
    "date:inception_lower":"2007-08-01",
    "date:inception_upper":"2007-08-31",
    "iso:country":"GB",
    "wof:name":"PL21 9RL",
    "wof:placetype":"postalcode"
},
  "geometry": {"coordinates":[-3.959063,50.387633],"type":"Point"}
}