{
  "type": "Feature",
  "properties": {
    "iso:country": "GB",
    "wof:name": "PL21 9RL",
    "wof:placetype": "postalcode"
  },
  "geometry": {"coordinates":[-3.959063,50.387633],"type":"Point"}
}
