{
  "type": "Feature",
  "properties": {
    "iso:country":"GB",
    "wof:name":"PL21 9RL",
    "wof:placetype":"postalcode"
},
  "geometry": {"coordinates":[-3.95906253905007,50.3876332542829],"type":"Point"}
}