{
  "type": "Feature",
  "properties": {
    "iso:country":"GB",
    "wof:name":"BA3 2XH",
    "wof:placetype":"postalcode"
},
  "geometry": {"coordinates":[-2.4733494890245,51.30059919644094],"type":"Point"}
}