{
  "type": "Feature",
  "properties": {
    "iso:country":"GB",
    "wof:name":"SE1 4QB",
    "wof:placetype":"postalcode"
},
  "geometry": {"coordinates":[-0.08406593668349,51.49835672652283],"type":"Point"}
}