{
  "type": "Feature",
  "properties": {
    "iso:country": "GB",
    "wof:name": "G82 5DD",
    "wof:placetype": "postalcode"
  },
  "geometry": {"coordinates":[-4.596155,55.94767],"type":"Point"}
}
