{
  "type": "Feature",
  "properties": {
    "date:inception_lower": "2019-12-01",
    "date:inception_upper": "2019-12-01",
    "iso:country": "GB",
    "wof:name": "G82 5DD",
    "wof:placetype": "postalcode"
  },
  "geometry": {"coordinates":[-4.596262,55.947586],"type":"Point"}
}
