{
  "type": "Feature",
  "properties": {
    "iso:country": "GB",
    "wof:name": "SS15 6SX",
    "wof:placetype": "postalcode"
  },
  "geometry": {"coordinates":[0.402949,51.572763],"type":"Point"}
}
