{
  "type": "Feature",
  "properties": {
    "date:inception_lower":"1998-06-01",
    "date:inception_upper":"1998-06-30",
    "iso:country":"GB",
    "wof:name":"YO26 8AL",
    "wof:placetype":"postalcode"
},
  "geometry": {"coordinates":[-1.320238,54.013777],"type":"Point"}
}