{
  "type": "Feature",
  "properties": {
    "iso:country": "GB",
    "wof:name": "RG9 2DS",
    "wof:placetype": "postalcode"
  },
  "geometry": {"coordinates":[-0.907593,51.53842],"type":"Point"}
}
