{
  "type": "Feature",
  "properties": {
    "iso:country":"GB",
    "wof:name":"RG9 2DS",
    "wof:placetype":"postalcode"
},
  "geometry": {"coordinates":[-0.90759339687862,51.53841953346105],"type":"Point"}
}