{
  "type": "Feature",
  "properties": {
    "iso:country": "GB",
    "wof:name": "EN11 9NE",
    "wof:placetype": "postalcode"
  },
  "geometry": {"coordinates":[-0.008784,51.774548],"type":"Point"}
}
