{
  "type": "Feature",
  "properties": {
    "date:inception_lower": "1994-05-01",
    "date:inception_upper": "1994-05-01",
    "iso:country": "GB",
    "wof:name": "M30 0EB",
    "wof:placetype": "postalcode"
  },
  "geometry": {"coordinates":[-2.336638,53.483373],"type":"Point"}
}
