{
  "type": "Feature",
  "properties": {
    "iso:country":"GB",
    "wof:name":"FY5 3PU",
    "wof:placetype":"postalcode"
},
  "geometry": {"coordinates":[-3.02869092389394,53.87336992317036],"type":"Point"}
}