{
  "type": "Feature",
  "properties": {
    "iso:country": "GB",
    "wof:name": "KT15 1DB",
    "wof:placetype": "postalcode"
  },
  "geometry": {"coordinates":[-0.508176,51.363349],"type":"Point"}
}
