{
  "type": "Feature",
  "properties": {
    "iso:country":"GB",
    "wof:name":"BL6 7QH",
    "wof:placetype":"postalcode"
},
  "geometry": {"coordinates":[-2.55413709454299,53.60137202354282],"type":"Point"}
}