{
  "type": "Feature",
  "properties": {
    "iso:country":"GB",
    "wof:name":"OX3 7PN",
    "wof:placetype":"postalcode"
},
  "geometry": {"coordinates":[-1.21875904476875,51.75654474808749],"type":"Point"}
}