{
  "type": "Feature",
  "properties": {
    "iso:country":"GB",
    "wof:name":"EH48 2PD",
    "wof:placetype":"postalcode"
},
  "geometry": {"coordinates":[-3.68319083742367,55.89996651193929],"type":"Point"}
}