{
  "type": "Feature",
  "properties": {
    "iso:country":"GB",
    "wof:name":"PO20 0BT",
    "wof:placetype":"postalcode"
},
  "geometry": {"coordinates":[-0.78642191894024,50.73116321942653],"type":"Point"}
}