{
  "type": "Feature",
  "properties": {
    "date:inception_lower": "2023-02-01",
    "date:inception_upper": "2023-02-01",
    "iso:country": "GB",
    "wof:name": "AB37 9AF",
    "wof:placetype": "postalcode"
  },
  "geometry": {"coordinates":[-3.381337,57.252598],"type":"Point"}
}
