{
  "type": "Feature",
  "properties": {
    "iso:country":"GB",
    "wof:name":"CB6 3FJ",
    "wof:placetype":"postalcode"
},
  "geometry": {"coordinates":[0.24117738862415,52.39609642536639],"type":"Point"}
}