{
  "type": "Feature",
  "properties": {
    "date:inception_lower":"1999-06-01",
    "date:inception_upper":"1999-06-30",
    "iso:country":"GB",
    "wof:name":"NP22 5JA",
    "wof:placetype":"postalcode"
},
  "geometry": {"coordinates":[-3.273789,51.753484],"type":"Point"}
}