{
  "type": "Feature",
  "properties": {
    "iso:country":"GB",
    "wof:name":"CM5 0PY",
    "wof:placetype":"postalcode"
},
  "geometry": {"coordinates":[0.28789212069836,51.73683621257887],"type":"Point"}
}