{
  "type": "Feature",
  "properties": {
    "iso:country": "GB",
    "wof:name": "CB2 1NX",
    "wof:placetype": "postalcode"
  },
  "geometry": {"coordinates":[0.131225,52.195941],"type":"Point"}
}
