{
  "type": "Feature",
  "properties": {
    "iso:country":"GB",
    "wof:name":"CB2 1NX",
    "wof:placetype":"postalcode"
},
  "geometry": {"coordinates":[0.13122516279273,52.19594076361899],"type":"Point"}
}