{
  "type": "Feature",
  "properties": {
    "date:inception_lower": "1990-07-01",
    "date:inception_upper": "1990-07-01",
    "iso:country": "GB",
    "wof:name": "CB6 3UP",
    "wof:placetype": "postalcode"
  },
  "geometry": {"coordinates":[0.149431,52.351403],"type":"Point"}
}
