{
  "type": "Feature",
  "properties": {
    "iso:country": "GB",
    "wof:name": "SA33 6NY",
    "wof:placetype": "postalcode"
  },
  "geometry": {"coordinates":[-4.425626,51.901518],"type":"Point"}
}
