{
  "type": "Feature",
  "properties": {
    "iso:country":"GB",
    "wof:name":"SA33 6NY",
    "wof:placetype":"postalcode"
},
  "geometry": {"coordinates":[-4.42562651606562,51.90151835165639],"type":"Point"}
}