{
  "type": "Feature",
  "properties": {
    "iso:country": "GB",
    "wof:name": "RH11 7QP",
    "wof:placetype": "postalcode"
  },
  "geometry": {"coordinates":[-0.190844,51.125775],"type":"Point"}
}
