{
  "type": "Feature",
  "properties": {
    "iso:country":"GB",
    "wof:name":"RH11 7QP",
    "wof:placetype":"postalcode"
},
  "geometry": {"coordinates":[-0.19084355162169,51.12577519457571],"type":"Point"}
}