{
  "type": "Feature",
  "properties": {
    "iso:country":"GB",
    "wof:name":"B31 2DR",
    "wof:placetype":"postalcode"
},
  "geometry": {"coordinates":[-1.9502030095734,52.41483725009964],"type":"Point"}
}