{
  "type": "Feature",
  "properties": {
    "iso:country":"GB",
    "wof:name":"IP14 4TQ",
    "wof:placetype":"postalcode"
},
  "geometry": {"coordinates":[1.02407027966107,52.27576656993735],"type":"Point"}
}