{
  "type": "Feature",
  "properties": {
    "iso:country":"GB",
    "wof:name":"SN4 7HJ",
    "wof:placetype":"postalcode"
},
  "geometry": {"coordinates":[-1.89809372145361,51.5481069358134],"type":"Point"}
}