{
  "type": "Feature",
  "properties": {
    "iso:country":"GB",
    "wof:name":"EN5 2EA",
    "wof:placetype":"postalcode"
},
  "geometry": {"coordinates":[-0.19584662630629,51.64793704279819],"type":"Point"}
}