{
  "type": "Feature",
  "properties": {
    "iso:country":"GB",
    "wof:name":"HS1 2RB",
    "wof:placetype":"postalcode"
},
  "geometry": {"coordinates":[-6.38076834387505,58.20634730926609],"type":"Point"}
}