{
  "type": "Feature",
  "properties": {
    "iso:country":"GB",
    "wof:name":"LL58 8LB",
    "wof:placetype":"postalcode"
},
  "geometry": {"coordinates":[-4.0913975727576,53.27746263500312],"type":"Point"}
}