{
  "type": "Feature",
  "properties": {
    "iso:country": "GB",
    "wof:name": "ST13 7TL",
    "wof:placetype": "postalcode"
  },
  "geometry": {"coordinates":[-1.888531,53.10547],"type":"Point"}
}
