{
  "type": "Feature",
  "properties": {
    "iso:country":"GB",
    "wof:name":"ST13 7TL",
    "wof:placetype":"postalcode"
},
  "geometry": {"coordinates":[-1.88853076544987,53.10547026963254],"type":"Point"}
}