{
  "type": "Feature",
  "properties": {
    "date:inception_lower":"1980-01-01",
    "date:inception_upper":"1980-01-31",
    "iso:country":"GB",
    "wof:name":"LD1 6RP",
    "wof:placetype":"postalcode"
},
  "geometry": {"coordinates":[-3.335232,52.278098],"type":"Point"}
}