{
  "type": "Feature",
  "properties": {
    "iso:country": "GB",
    "wof:name": "CO4 9WP",
    "wof:placetype": "postalcode"
  },
  "geometry": {"coordinates":[0.93254,51.919743],"type":"Point"}
}
