{
  "type": "Feature",
  "properties": {
    "date:inception_lower": "2002-06-01",
    "date:inception_upper": "2002-06-01",
    "iso:country": "GB",
    "wof:name": "CO4 9WP",
    "wof:placetype": "postalcode"
  },
  "geometry": {"coordinates":[0.93254,51.919743],"type":"Point"}
}
