{
  "type": "Feature",
  "properties": {
    "iso:country": "GB",
    "wof:name": "SR3 1YB",
    "wof:placetype": "postalcode"
  },
  "geometry": {"coordinates":[-1.396567,54.89016],"type":"Point"}
}
