{
  "type": "Feature",
  "properties": {
    "date:inception_lower": "1980-01-01",
    "date:inception_upper": "1980-01-01",
    "iso:country": "GB",
    "wof:name": "G31 2SA",
    "wof:placetype": "postalcode"
  },
  "geometry": {"coordinates":[-4.214572,55.859396],"type":"Point"}
}
