{
  "type": "Feature",
  "properties": {
    "iso:country": "GB",
    "wof:name": "G31 2SA",
    "wof:placetype": "postalcode"
  },
  "geometry": {"coordinates":[-4.214572,55.859396],"type":"Point"}
}
