{
  "type": "Feature",
  "properties": {
    "date:inception_lower":"1980-01-01",
    "date:inception_upper":"1980-01-31",
    "iso:country":"GB",
    "wof:name":"BS13 8PU",
    "wof:placetype":"postalcode"
},
  "geometry": {"coordinates":[-2.623869,51.408092],"type":"Point"}
}