{
  "type": "Feature",
  "properties": {
    "iso:country":"GB",
    "wof:name":"LL57 3RY",
    "wof:placetype":"postalcode"
},
  "geometry": {"coordinates":[-4.05886476941483,53.18415069176704],"type":"Point"}
}