{
  "type": "Feature",
  "properties": {
    "iso:country": "GB",
    "wof:name": "LL57 3RY",
    "wof:placetype": "postalcode"
  },
  "geometry": {"coordinates":[-4.058865,53.184151],"type":"Point"}
}
