{
  "type": "Feature",
  "properties": {
    "iso:country":"GB",
    "wof:name":"LA1 5EJ",
    "wof:placetype":"postalcode"
},
  "geometry": {"coordinates":[-2.81608723094954,54.04405934988937],"type":"Point"}
}