{
  "type": "Feature",
  "properties": {
    "iso:country":"GB",
    "wof:name":"BS22 8QP",
    "wof:placetype":"postalcode"
},
  "geometry": {"coordinates":[-2.94272327651753,51.3523056748457],"type":"Point"}
}