{
  "type": "Feature",
  "properties": {
    "date:inception_lower": "1980-01-01",
    "date:inception_upper": "1980-01-01",
    "iso:country": "GB",
    "wof:name": "SA9 1DP",
    "wof:placetype": "postalcode"
  },
  "geometry": {"coordinates":[-3.773087,51.776837],"type":"Point"}
}
