{
  "type": "Feature",
  "properties": {
    "iso:country": "GB",
    "wof:name": "M20 6JW",
    "wof:placetype": "postalcode"
  },
  "geometry": {"coordinates":[-2.221828,53.417496],"type":"Point"}
}
