{
  "type": "Feature",
  "properties": {
    "iso:country":"GB",
    "wof:name":"M20 6JW",
    "wof:placetype":"postalcode"
},
  "geometry": {"coordinates":[-2.22182836736165,53.41749559314136],"type":"Point"}
}