{
  "type": "Feature",
  "properties": {
    "iso:country":"GB",
    "wof:name":"CB6 3TE",
    "wof:placetype":"postalcode"
},
  "geometry": {"coordinates":[0.14136308827452,52.35886918210463],"type":"Point"}
}