{
  "type": "Feature",
  "properties": {
    "date:inception_lower":"1980-01-01",
    "date:inception_upper":"1980-01-31",
    "iso:country":"GB",
    "wof:name":"L5 3PD",
    "wof:placetype":"postalcode"
},
  "geometry": {"coordinates":[-2.973414,53.421374],"type":"Point"}
}