{
  "type": "Feature",
  "properties": {
    "iso:country": "GB",
    "wof:name": "L5 3PD",
    "wof:placetype": "postalcode"
  },
  "geometry": {"coordinates":[-2.973414,53.421374],"type":"Point"}
}
