{
  "type": "Feature",
  "properties": {
    "iso:country":"GB",
    "wof:name":"L5 3PD",
    "wof:placetype":"postalcode"
},
  "geometry": {"coordinates":[-2.97341402915725,53.42137357142654],"type":"Point"}
}