{
  "type": "Feature",
  "properties": {
    "iso:country": "GB",
    "wof:name": "YO25 9AE",
    "wof:placetype": "postalcode"
  },
  "geometry": {"coordinates":[-0.446584,53.97316],"type":"Point"}
}
