{
  "type": "Feature",
  "properties": {
    "iso:country":"GB",
    "wof:name":"YO25 9AE",
    "wof:placetype":"postalcode"
},
  "geometry": {"coordinates":[-0.44658435878113,53.97316010631763],"type":"Point"}
}