{
  "type": "Feature",
  "properties": {
    "iso:country":"GB",
    "wof:name":"W6 8HD",
    "wof:placetype":"postalcode"
},
  "geometry": {"coordinates":[-0.21562774991354,51.48743817102344],"type":"Point"}
}