{
  "type": "Feature",
  "properties": {
    "date:inception_lower": "1980-01-01",
    "date:inception_upper": "1980-01-01",
    "iso:country": "GB",
    "wof:name": "DL14 6TQ",
    "wof:placetype": "postalcode"
  },
  "geometry": {"coordinates":[-1.676177,54.649794],"type":"Point"}
}
