{
  "type": "Feature",
  "properties": {
    "iso:country": "GB",
    "wof:name": "LL54 5TJ",
    "wof:placetype": "postalcode"
  },
  "geometry": {"coordinates":[-4.315585,53.079859],"type":"Point"}
}
