{
  "type": "Feature",
  "properties": {
    "iso:country":"GB",
    "wof:name":"E2 8SH",
    "wof:placetype":"postalcode"
},
  "geometry": {"coordinates":[-0.06370161864262,51.53521561091955],"type":"Point"}
}