{
  "type": "Feature",
  "properties": {
    "iso:country": "GB",
    "wof:name": "NG7 4AP",
    "wof:placetype": "postalcode"
  },
  "geometry": {"coordinates":[-1.167949,52.960126],"type":"Point"}
}
