{
  "type": "Feature",
  "properties": {
    "iso:country":"GB",
    "wof:name":"NG7 4AP",
    "wof:placetype":"postalcode"
},
  "geometry": {"coordinates":[-1.16794929846146,52.96012558609809],"type":"Point"}
}