{
  "type": "Feature",
  "properties": {
    "date:inception_lower":"1998-12-01",
    "date:inception_upper":"1998-12-31",
    "iso:country":"GB",
    "wof:name":"NG7 4AP",
    "wof:placetype":"postalcode"
},
  "geometry": {"coordinates":[-1.167949,52.960126],"type":"Point"}
}