{
  "type": "Feature",
  "properties": {
    "iso:country": "GB",
    "wof:name": "GL8 8FU",
    "wof:placetype": "postalcode"
  },
  "geometry": {"coordinates":[-2.159226,51.637356],"type":"Point"}
}
