{
  "type": "Feature",
  "properties": {
    "date:inception_lower": "2019-08-01",
    "date:inception_upper": "2019-08-01",
    "iso:country": "GB",
    "wof:name": "GL8 8FU",
    "wof:placetype": "postalcode"
  },
  "geometry": {"coordinates":[-2.159226,51.637356],"type":"Point"}
}
