{
  "type": "Feature",
  "properties": {
    "iso:country":"GB",
    "wof:name":"LA5 9AF",
    "wof:placetype":"postalcode"
},
  "geometry": {"coordinates":[-2.76450021090008,54.12475813435293],"type":"Point"}
}