{
  "type": "Feature",
  "properties": {
    "date:inception_lower": "1980-01-01",
    "date:inception_upper": "1980-01-01",
    "iso:country": "GB",
    "wof:name": "WV6 9PH",
    "wof:placetype": "postalcode"
  },
  "geometry": {"coordinates":[-2.166895,52.603365],"type":"Point"}
}
