{
  "type": "Feature",
  "properties": {
    "iso:country":"GB",
    "wof:name":"WV6 9PH",
    "wof:placetype":"postalcode"
},
  "geometry": {"coordinates":[-2.16689486462556,52.60336503095954],"type":"Point"}
}