{
  "type": "Feature",
  "properties": {
    "iso:country":"GB",
    "wof:name":"NN9 6QZ",
    "wof:placetype":"postalcode"
},
  "geometry": {"coordinates":[-0.58317380823439,52.32282743224143],"type":"Point"}
}