{
  "type": "Feature",
  "properties": {
    "iso:country":"GB",
    "wof:name":"BH12 5BA",
    "wof:placetype":"postalcode"
},
  "geometry": {"coordinates":[-1.92953865774973,50.75227447497826],"type":"Point"}
}