{
  "type": "Feature",
  "properties": {
    "iso:country":"GB",
    "wof:name":"WA12 8HY",
    "wof:placetype":"postalcode"
},
  "geometry": {"coordinates":[-2.62169122828735,53.45041934337134],"type":"Point"}
}