{
  "type": "Feature",
  "properties": {
    "iso:country": "GB",
    "wof:name": "WA12 8HY",
    "wof:placetype": "postalcode"
  },
  "geometry": {"coordinates":[-2.621691,53.450419],"type":"Point"}
}
