{
  "type": "Feature",
  "properties": {
    "iso:country":"GB",
    "wof:name":"YO10 3AN",
    "wof:placetype":"postalcode"
},
  "geometry": {"coordinates":[-1.05457711814327,53.95531191810959],"type":"Point"}
}