{
  "type": "Feature",
  "properties": {
    "iso:country": "GB",
    "wof:name": "YO10 3AN",
    "wof:placetype": "postalcode"
  },
  "geometry": {"coordinates":[-1.054577,53.955312],"type":"Point"}
}
