{
  "type": "Feature",
  "properties": {
    "iso:country":"GB",
    "wof:name":"SW7 3RF",
    "wof:placetype":"postalcode"
},
  "geometry": {"coordinates":[-0.18091892287494,51.48986342267686],"type":"Point"}
}