{
  "type": "Feature",
  "properties": {
    "iso:country":"GB",
    "wof:name":"BN16 1DL",
    "wof:placetype":"postalcode"
},
  "geometry": {"coordinates":[-0.47459350266746,50.81770302575567],"type":"Point"}
}