{
  "type": "Feature",
  "properties": {
    "date:inception_lower": "1980-01-01",
    "date:inception_upper": "1980-01-01",
    "iso:country": "GB",
    "wof:name": "BN16 1DL",
    "wof:placetype": "postalcode"
  },
  "geometry": {"coordinates":[-0.474593,50.817703],"type":"Point"}
}
