{
  "type": "Feature",
  "properties": {
    "iso:country": "GB",
    "wof:name": "E3 4SA",
    "wof:placetype": "postalcode"
  },
  "geometry": {"coordinates":[-0.02625,51.520043],"type":"Point"}
}
