{
  "type": "Feature",
  "properties": {
    "iso:country":"GB",
    "wof:name":"LE67 1EZ",
    "wof:placetype":"postalcode"
},
  "geometry": {"coordinates":[-1.35991067011898,52.69083538545026],"type":"Point"}
}