{
  "type": "Feature",
  "properties": {
    "date:inception_lower":"1997-12-01",
    "date:inception_upper":"1997-12-31",
    "iso:country":"GB",
    "wof:name":"BS39 5TU",
    "wof:placetype":"postalcode"
},
  "geometry": {"coordinates":[-2.595955,51.340976],"type":"Point"}
}