{
  "type": "Feature",
  "properties": {
    "iso:country":"GB",
    "wof:name":"BS39 5TU",
    "wof:placetype":"postalcode"
},
  "geometry": {"coordinates":[-2.5931061688243,51.34066980963753],"type":"Point"}
}