{
  "type": "Feature",
  "properties": {
    "iso:country": "GB",
    "wof:name": "BS39 5TU",
    "wof:placetype": "postalcode"
  },
  "geometry": {"coordinates":[-2.595955,51.340976],"type":"Point"}
}
