{
  "type": "Feature",
  "properties": {
    "iso:country":"GB",
    "wof:name":"IP23 8BG",
    "wof:placetype":"postalcode"
},
  "geometry": {"coordinates":[1.03009089001875,52.30747575891372],"type":"Point"}
}