{
  "type": "Feature",
  "properties": {
    "date:inception_lower": "2007-07-01",
    "date:inception_upper": "2007-07-01",
    "iso:country": "GB",
    "wof:name": "IP23 8BG",
    "wof:placetype": "postalcode"
  },
  "geometry": {"coordinates":[1.030463,52.307557],"type":"Point"}
}
