{
  "type": "Feature",
  "properties": {
    "iso:country": "GB",
    "wof:name": "IP23 8BG",
    "wof:placetype": "postalcode"
  },
  "geometry": {"coordinates":[1.030463,52.307557],"type":"Point"}
}
