{
  "type": "Feature",
  "properties": {
    "iso:country":"GB",
    "wof:name":"DA2 7LE",
    "wof:placetype":"postalcode"
},
  "geometry": {"coordinates":[0.2568572316085,51.42262121401557],"type":"Point"}
}