{
  "type": "Feature",
  "properties": {
    "iso:country":"GB",
    "wof:name":"DN32 9NY",
    "wof:placetype":"postalcode"
},
  "geometry": {"coordinates":[-0.07541831822402,53.5630704257164],"type":"Point"}
}