{
  "type": "Feature",
  "properties": {
    "date:inception_lower":"2008-08-01",
    "date:inception_upper":"2008-08-31",
    "iso:country":"GB",
    "wof:name":"DN32 9NY",
    "wof:placetype":"postalcode"
},
  "geometry": {"coordinates":[-0.075418,53.56307],"type":"Point"}
}