{
  "type": "Feature",
  "properties": {
    "iso:country": "GB",
    "wof:name": "KA1 3RG",
    "wof:placetype": "postalcode"
  },
  "geometry": {"coordinates":[-4.485417,55.590167],"type":"Point"}
}
