{
  "type": "Feature",
  "properties": {
    "iso:country":"GB",
    "wof:name":"KA1 3RG",
    "wof:placetype":"postalcode"
},
  "geometry": {"coordinates":[-4.48541720665141,55.59016672511734],"type":"Point"}
}