{
  "type": "Feature",
  "properties": {
    "iso:country": "GB",
    "wof:name": "IG2 7QQ",
    "wof:placetype": "postalcode"
  },
  "geometry": {"coordinates":[0.098865,51.581043],"type":"Point"}
}
