{
  "type": "Feature",
  "properties": {
    "iso:country": "GB",
    "wof:name": "L20 3BW",
    "wof:placetype": "postalcode"
  },
  "geometry": {"coordinates":[-2.989241,53.448469],"type":"Point"}
}
