{
  "type": "Feature",
  "properties": {
    "iso:country":"GB",
    "wof:name":"BA7 7HZ",
    "wof:placetype":"postalcode"
},
  "geometry": {"coordinates":[-2.51187905979654,51.09297340050298],"type":"Point"}
}