{
  "type": "Feature",
  "properties": {
    "iso:country": "GB",
    "wof:name": "WA16 0RR",
    "wof:placetype": "postalcode"
  },
  "geometry": {"coordinates":[-2.431796,53.343518],"type":"Point"}
}
