{
  "type": "Feature",
  "properties": {
    "iso:country":"GB",
    "wof:name":"WA16 0RR",
    "wof:placetype":"postalcode"
},
  "geometry": {"coordinates":[-2.43179789904403,53.34350120918818],"type":"Point"}
}