{
  "type": "Feature",
  "properties": {
    "iso:country":"GB",
    "wof:name":"SY23 2DJ",
    "wof:placetype":"postalcode"
},
  "geometry": {"coordinates":[-4.08432870735328,52.42078001173645],"type":"Point"}
}