{
  "type": "Feature",
  "properties": {
    "date:inception_lower":"2000-12-01",
    "date:inception_upper":"2000-12-31",
    "iso:country":"GB",
    "wof:name":"SY23 2DJ",
    "wof:placetype":"postalcode"
},
  "geometry": {"coordinates":[-4.084329,52.42078],"type":"Point"}
}