{
  "type": "Feature",
  "properties": {
    "iso:country":"GB",
    "wof:name":"CV5 8HW",
    "wof:placetype":"postalcode"
},
  "geometry": {"coordinates":[-1.54896398585056,52.41867225002314],"type":"Point"}
}