{
  "type": "Feature",
  "properties": {
    "iso:country": "GB",
    "wof:name": "CV5 8HW",
    "wof:placetype": "postalcode"
  },
  "geometry": {"coordinates":[-1.548964,52.418672],"type":"Point"}
}
