{
  "type": "Feature",
  "properties": {
    "iso:country": "GB",
    "wof:name": "TF7 4LU",
    "wof:placetype": "postalcode"
  },
  "geometry": {"coordinates":[-2.435667,52.63713],"type":"Point"}
}
