{
  "type": "Feature",
  "properties": {
    "iso:country":"GB",
    "wof:name":"TF7 4LU",
    "wof:placetype":"postalcode"
},
  "geometry": {"coordinates":[-2.43566674332829,52.6371297865553],"type":"Point"}
}