{
  "type": "Feature",
  "properties": {
    "date:inception_lower": "1997-06-01",
    "date:inception_upper": "1997-06-01",
    "iso:country": "GB",
    "wof:name": "PA16 0HZ",
    "wof:placetype": "postalcode"
  },
  "geometry": {"coordinates":[-4.867367,55.902219],"type":"Point"}
}
