{
  "type": "Feature",
  "properties": {
    "date:inception_lower": "2017-08-01",
    "date:inception_upper": "2017-08-01",
    "iso:country": "GB",
    "wof:name": "DE11 0FT",
    "wof:placetype": "postalcode"
  },
  "geometry": {"coordinates":[-1.579146,52.784013],"type":"Point"}
}
