{
  "type": "Feature",
  "properties": {
    "date:inception_lower":"1980-01-01",
    "date:inception_upper":"1980-01-31",
    "iso:country":"GB",
    "wof:name":"PE7 2HL",
    "wof:placetype":"postalcode"
},
  "geometry": {"coordinates":[-0.069975,52.54222],"type":"Point"}
}