{
  "type": "Feature",
  "properties": {
    "iso:country":"GB",
    "wof:name":"PE7 2HL",
    "wof:placetype":"postalcode"
},
  "geometry": {"coordinates":[-0.0699746609497,52.54221975598875],"type":"Point"}
}