{
  "type": "Feature",
  "properties": {
    "iso:country":"GB",
    "wof:name":"NR4 7NG",
    "wof:placetype":"postalcode"
},
  "geometry": {"coordinates":[1.25181644327671,52.62624749516039],"type":"Point"}
}