{
  "type": "Feature",
  "properties": {
    "iso:country":"GB",
    "wof:name":"GU3 1BG",
    "wof:placetype":"postalcode"
},
  "geometry": {"coordinates":[-0.6922562060917,51.20519725988558],"type":"Point"}
}