{
  "type": "Feature",
  "properties": {
    "date:inception_lower": "2019-04-01",
    "date:inception_upper": "2019-04-01",
    "iso:country": "GB",
    "wof:name": "DY4 8ER",
    "wof:placetype": "postalcode"
  },
  "geometry": {"coordinates":[-2.076171,52.527276],"type":"Point"}
}
