{
  "type": "Feature",
  "properties": {
    "iso:country": "GB",
    "wof:name": "KY16 9EG",
    "wof:placetype": "postalcode"
  },
  "geometry": {"coordinates":[-2.800397,56.338552],"type":"Point"}
}
