{
  "type": "Feature",
  "properties": {
    "iso:country": "GB",
    "wof:name": "NN3 7AL",
    "wof:placetype": "postalcode"
  },
  "geometry": {"coordinates":[-0.85592,52.287222],"type":"Point"}
}
