{
  "type": "Feature",
  "properties": {
    "iso:country":"GB",
    "wof:name":"NN3 7AL",
    "wof:placetype":"postalcode"
},
  "geometry": {"coordinates":[-0.85592007712597,52.28722234480274],"type":"Point"}
}