{
  "type": "Feature",
  "properties": {
    "date:inception_lower":"1997-12-01",
    "date:inception_upper":"1997-12-31",
    "iso:country":"GB",
    "wof:name":"NN3 7AL",
    "wof:placetype":"postalcode"
},
  "geometry": {"coordinates":[-0.85592,52.287222],"type":"Point"}
}