{
  "type": "Feature",
  "properties": {
    "iso:country":"GB",
    "wof:name":"NG8 5LB",
    "wof:placetype":"postalcode"
},
  "geometry": {"coordinates":[-1.19796113296214,52.97866130607255],"type":"Point"}
}