{
  "type": "Feature",
  "properties": {
    "iso:country":"GB",
    "wof:name":"RH9 8JR",
    "wof:placetype":"postalcode"
},
  "geometry": {"coordinates":[-0.07612306750884,51.18849616801337],"type":"Point"}
}