{
  "type": "Feature",
  "properties": {
    "date:inception_lower":"1980-01-01",
    "date:inception_upper":"1980-01-31",
    "iso:country":"GB",
    "wof:name":"RH9 8JR",
    "wof:placetype":"postalcode"
},
  "geometry": {"coordinates":[-0.076123,51.188496],"type":"Point"}
}