{
  "type": "Feature",
  "properties": {
    "iso:country": "GB",
    "wof:name": "RH9 8JR",
    "wof:placetype": "postalcode"
  },
  "geometry": {"coordinates":[-0.076123,51.188496],"type":"Point"}
}
