{
  "type": "Feature",
  "properties": {
    "iso:country":"GB",
    "wof:name":"NR1 3PR",
    "wof:placetype":"postalcode"
},
  "geometry": {"coordinates":[1.29153933679904,52.62402529431611],"type":"Point"}
}