{
  "type": "Feature",
  "properties": {
    "date:inception_lower": "1983-07-01",
    "date:inception_upper": "1983-07-01",
    "iso:country": "GB",
    "wof:name": "NR1 3PR",
    "wof:placetype": "postalcode"
  },
  "geometry": {"coordinates":[1.291539,52.624025],"type":"Point"}
}
