{
  "type": "Feature",
  "properties": {
    "iso:country": "GB",
    "wof:name": "CW2 6XF",
    "wof:placetype": "postalcode"
  },
  "geometry": {"coordinates":[-2.456536,53.0789],"type":"Point"}
}
