{
  "type": "Feature",
  "properties": {
    "date:inception_lower":"1980-01-01",
    "date:inception_upper":"1980-01-31",
    "iso:country":"GB",
    "wof:name":"TA1 1SW",
    "wof:placetype":"postalcode"
},
  "geometry": {"coordinates":[-3.098959,51.017105],"type":"Point"}
}