{
  "type": "Feature",
  "properties": {
    "iso:country": "GB",
    "wof:name": "M30 0DG",
    "wof:placetype": "postalcode"
  },
  "geometry": {"coordinates":[-2.333458,53.48714],"type":"Point"}
}
