{
  "type": "Feature",
  "properties": {
    "iso:country":"GB",
    "wof:name":"M30 0DG",
    "wof:placetype":"postalcode"
},
  "geometry": {"coordinates":[-2.33345829903802,53.48713958580166],"type":"Point"}
}