{
  "type": "Feature",
  "properties": {
    "iso:country":"GB",
    "wof:name":"LE12 5GB",
    "wof:placetype":"postalcode"
},
  "geometry": {"coordinates":[-1.25828933993912,52.83439364553858],"type":"Point"}
}