{
  "type": "Feature",
  "properties": {
    "iso:country":"GB",
    "wof:name":"AB25 1UH",
    "wof:placetype":"postalcode"
},
  "geometry": {"coordinates":[-2.10002151336361,57.14902849935429],"type":"Point"}
}