{
  "type": "Feature",
  "properties": {
    "date:inception_lower": "1980-01-01",
    "date:inception_upper": "1980-01-01",
    "iso:country": "GB",
    "wof:name": "TN17 1LP",
    "wof:placetype": "postalcode"
  },
  "geometry": {"coordinates":[0.489365,51.130816],"type":"Point"}
}
