{
  "type": "Feature",
  "properties": {
    "iso:country": "GB",
    "wof:name": "NR21 0BF",
    "wof:placetype": "postalcode"
  },
  "geometry": {"coordinates":[0.945339,52.884985],"type":"Point"}
}
