{
  "type": "Feature",
  "properties": {
    "iso:country":"GB",
    "wof:name":"NR21 0BF",
    "wof:placetype":"postalcode"
},
  "geometry": {"coordinates":[0.94533722033898,52.88496817058255],"type":"Point"}
}