{
  "type": "Feature",
  "properties": {
    "iso:country":"GB",
    "wof:name":"BA2 0DY",
    "wof:placetype":"postalcode"
},
  "geometry": {"coordinates":[-2.44145705831679,51.33281558479866],"type":"Point"}
}