{
  "type": "Feature",
  "properties": {
    "date:inception_lower":"2001-06-01",
    "date:inception_upper":"2001-06-30",
    "iso:country":"GB",
    "wof:name":"BA2 0DY",
    "wof:placetype":"postalcode"
},
  "geometry": {"coordinates":[-2.441457,51.332816],"type":"Point"}
}