{
  "type": "Feature",
  "properties": {
    "iso:country": "GB",
    "wof:name": "BD19 3TZ",
    "wof:placetype": "postalcode"
  },
  "geometry": {"coordinates":[-1.718078,53.73064],"type":"Point"}
}
