{
  "type": "Feature",
  "properties": {
    "iso:country":"GB",
    "wof:name":"M12 4DU",
    "wof:placetype":"postalcode"
},
  "geometry": {"coordinates":[-2.20981040333119,53.46708897000736],"type":"Point"}
}