{
  "type": "Feature",
  "properties": {
    "iso:country":"GB",
    "wof:name":"CM2 7LG",
    "wof:placetype":"postalcode"
},
  "geometry": {"coordinates":[0.48486039506523,51.72516391069143],"type":"Point"}
}