{
  "type": "Feature",
  "properties": {
    "iso:country":"GB",
    "wof:name":"SY4 4UH",
    "wof:placetype":"postalcode"
},
  "geometry": {"coordinates":[-2.64180259696992,52.68233690641112],"type":"Point"}
}