{
  "type": "Feature",
  "properties": {
    "date:inception_lower": "1980-01-01",
    "date:inception_upper": "1980-01-01",
    "iso:country": "GB",
    "wof:name": "N15 6NR",
    "wof:placetype": "postalcode"
  },
  "geometry": {"coordinates":[-0.076258,51.576727],"type":"Point"}
}
