{
  "type": "Feature",
  "properties": {
    "iso:country":"GB",
    "wof:name":"N15 6NR",
    "wof:placetype":"postalcode"
},
  "geometry": {"coordinates":[-0.07637044861836,51.57671770755226],"type":"Point"}
}