{
  "type": "Feature",
  "properties": {
    "date:inception_lower": "2000-12-01",
    "date:inception_upper": "2000-12-01",
    "iso:country": "GB",
    "wof:name": "W1F 9RE",
    "wof:placetype": "postalcode"
  },
  "geometry": {"coordinates":[-0.137953,51.512066],"type":"Point"}
}
