{
  "type": "Feature",
  "properties": {
    "iso:country":"GB",
    "wof:name":"W1F 9RE",
    "wof:placetype":"postalcode"
},
  "geometry": {"coordinates":[-0.137952671639,51.51206603288331],"type":"Point"}
}