{
  "type": "Feature",
  "properties": {
    "iso:country": "GB",
    "wof:name": "PL20 7QB",
    "wof:placetype": "postalcode"
  },
  "geometry": {"coordinates":[-4.097384,50.510348],"type":"Point"}
}
