{
  "type": "Feature",
  "properties": {
    "date:inception_lower": "1980-01-01",
    "date:inception_upper": "1980-01-01",
    "iso:country": "GB",
    "wof:name": "B64 7HF",
    "wof:placetype": "postalcode"
  },
  "geometry": {"coordinates":[-2.065944,52.466468],"type":"Point"}
}
