{
  "type": "Feature",
  "properties": {
    "iso:country":"GB",
    "wof:name":"B64 7HF",
    "wof:placetype":"postalcode"
},
  "geometry": {"coordinates":[-2.06594404040701,52.46646776135668],"type":"Point"}
}