{
  "type": "Feature",
  "properties": {
    "iso:country":"GB",
    "wof:name":"WF8 1SZ",
    "wof:placetype":"postalcode"
},
  "geometry": {"coordinates":[-1.30344359262228,53.70565066238106],"type":"Point"}
}