{
  "type": "Feature",
  "properties": {
    "iso:country": "GB",
    "wof:name": "IP33 3PJ",
    "wof:placetype": "postalcode"
  },
  "geometry": {"coordinates":[0.711886,52.241528],"type":"Point"}
}
