{
  "type": "Feature",
  "properties": {
    "iso:country": "GB",
    "wof:name": "PO30 5WX",
    "wof:placetype": "postalcode"
  },
  "geometry": {"coordinates":[-1.300285,50.698229],"type":"Point"}
}
