{
  "type": "Feature",
  "properties": {
    "date:inception_lower": "1999-06-01",
    "date:inception_upper": "1999-06-01",
    "iso:country": "GB",
    "wof:name": "PO30 5WX",
    "wof:placetype": "postalcode"
  },
  "geometry": {"coordinates":[-1.300285,50.698229],"type":"Point"}
}
