{
  "type": "Feature",
  "properties": {
    "iso:country": "GB",
    "wof:name": "TN12 0BS",
    "wof:placetype": "postalcode"
  },
  "geometry": {"coordinates":[0.552887,51.165027],"type":"Point"}
}
