{
  "type": "Feature",
  "properties": {
    "iso:country":"GB",
    "wof:name":"TN12 0BS",
    "wof:placetype":"postalcode"
},
  "geometry": {"coordinates":[0.55288678741678,51.16502663880487],"type":"Point"}
}