{
  "type": "Feature",
  "properties": {
    "date:inception_lower":"2000-12-01",
    "date:inception_upper":"2000-12-31",
    "iso:country":"GB",
    "wof:name":"TN12 0BS",
    "wof:placetype":"postalcode"
},
  "geometry": {"coordinates":[0.552887,51.165027],"type":"Point"}
}