{
  "type": "Feature",
  "properties": {
    "date:inception_lower":"1980-01-01",
    "date:inception_upper":"1980-01-31",
    "iso:country":"GB",
    "wof:name":"PH7 4HX",
    "wof:placetype":"postalcode"
},
  "geometry": {"coordinates":[-3.908927,56.363668],"type":"Point"}
}