{
  "type": "Feature",
  "properties": {
    "iso:country":"GB",
    "wof:name":"SW2 1AF",
    "wof:placetype":"postalcode"
},
  "geometry": {"coordinates":[-0.1207423854139,51.45117260347791],"type":"Point"}
}