{
  "type": "Feature",
  "properties": {
    "iso:country":"GB",
    "wof:name":"BN5 9UZ",
    "wof:placetype":"postalcode"
},
  "geometry": {"coordinates":[-0.27825046667123,50.93092076107788],"type":"Point"}
}