{
  "type": "Feature",
  "properties": {
    "date:inception_lower": "1980-01-01",
    "date:inception_upper": "1980-01-01",
    "iso:country": "GB",
    "wof:name": "DN10 4LT",
    "wof:placetype": "postalcode"
  },
  "geometry": {"coordinates":[-0.855709,53.428361],"type":"Point"}
}
