{
  "type": "Feature",
  "properties": {
    "iso:country":"GB",
    "wof:name":"DN10 4LT",
    "wof:placetype":"postalcode"
},
  "geometry": {"coordinates":[-0.85622259067645,53.42817401784836],"type":"Point"}
}