{
  "type": "Feature",
  "properties": {
    "iso:country": "GB",
    "wof:name": "DN10 4LT",
    "wof:placetype": "postalcode"
  },
  "geometry": {"coordinates":[-0.856223,53.428174],"type":"Point"}
}
