{
  "type": "Feature",
  "properties": {
    "iso:country":"GB",
    "wof:name":"CV3 5LU",
    "wof:placetype":"postalcode"
},
  "geometry": {"coordinates":[-1.50089519984133,52.39149077521344],"type":"Point"}
}