{
  "type": "Feature",
  "properties": {
    "iso:country":"GB",
    "wof:name":"LL68 9AB",
    "wof:placetype":"postalcode"
},
  "geometry": {"coordinates":[-4.34624965943569,53.41099667643716],"type":"Point"}
}