{
  "type": "Feature",
  "properties": {
    "date:inception_lower": "2001-06-01",
    "date:inception_upper": "2001-06-01",
    "iso:country": "GB",
    "wof:name": "LL68 9AB",
    "wof:placetype": "postalcode"
  },
  "geometry": {"coordinates":[-4.346543,53.411288],"type":"Point"}
}
