{
  "type": "Feature",
  "properties": {
    "iso:country":"GB",
    "wof:name":"SA12 7AU",
    "wof:placetype":"postalcode"
},
  "geometry": {"coordinates":[-3.82180404503217,51.60312637861891],"type":"Point"}
}