{
  "type": "Feature",
  "properties": {
    "iso:country": "GB",
    "wof:name": "DE55 4EW",
    "wof:placetype": "postalcode"
  },
  "geometry": {"coordinates":[-1.367832,53.070639],"type":"Point"}
}
