{
  "type": "Feature",
  "properties": {
    "date:inception_lower":"1980-01-01",
    "date:inception_upper":"1980-01-31",
    "iso:country":"GB",
    "wof:name":"DE55 4EW",
    "wof:placetype":"postalcode"
},
  "geometry": {"coordinates":[-1.367832,53.070639],"type":"Point"}
}