{
  "type": "Feature",
  "properties": {
    "iso:country":"GB",
    "wof:name":"DE55 4EW",
    "wof:placetype":"postalcode"
},
  "geometry": {"coordinates":[-1.36783254314253,53.07063904903205],"type":"Point"}
}