{
  "type": "Feature",
  "properties": {
    "date:inception_lower": "2022-02-01",
    "date:inception_upper": "2022-02-01",
    "iso:country": "GB",
    "wof:name": "TN12 6FT",
    "wof:placetype": "postalcode"
  },
  "geometry": {"coordinates":[0.381322,51.172549],"type":"Point"}
}
