{
  "type": "Feature",
  "properties": {
    "iso:country":"GB",
    "wof:name":"BH20 5AW",
    "wof:placetype":"postalcode"
},
  "geometry": {"coordinates":[-2.11114859755473,50.6483406657556],"type":"Point"}
}