{
  "type": "Feature",
  "properties": {
    "iso:country": "GB",
    "wof:name": "BH20 5AW",
    "wof:placetype": "postalcode"
  },
  "geometry": {"coordinates":[-2.111149,50.648341],"type":"Point"}
}
