{
  "type": "Feature",
  "properties": {
    "iso:country":"GB",
    "wof:name":"LE16 8UF",
    "wof:placetype":"postalcode"
},
  "geometry": {"coordinates":[-0.83091289799156,52.56117038688278],"type":"Point"}
}