{
  "type": "Feature",
  "properties": {
    "iso:country":"GB",
    "wof:name":"EX33 1BS",
    "wof:placetype":"postalcode"
},
  "geometry": {"coordinates":[-4.17001667789286,51.11371591963145],"type":"Point"}
}