{
  "type": "Feature",
  "properties": {
    "iso:country":"GB",
    "wof:name":"LE5 2LN",
    "wof:placetype":"postalcode"
},
  "geometry": {"coordinates":[-1.05190784476321,52.63521045848032],"type":"Point"}
}