{
  "type": "Feature",
  "properties": {
    "iso:country":"GB",
    "wof:name":"IG6 2PE",
    "wof:placetype":"postalcode"
},
  "geometry": {"coordinates":[0.07766797184596,51.58909115529041],"type":"Point"}
}