{
  "type": "Feature",
  "properties": {
    "iso:country":"GB",
    "wof:name":"BB5 3PX",
    "wof:placetype":"postalcode"
},
  "geometry": {"coordinates":[-2.40533119097004,53.7411693280599],"type":"Point"}
}