{
  "type": "Feature",
  "properties": {
    "date:inception_lower": "1980-01-01",
    "date:inception_upper": "1980-01-01",
    "iso:country": "GB",
    "wof:name": "TN10 3EX",
    "wof:placetype": "postalcode"
  },
  "geometry": {"coordinates":[0.280429,51.214788],"type":"Point"}
}
