{
  "type": "Feature",
  "properties": {
    "iso:country": "GB",
    "wof:name": "S9 4PL",
    "wof:placetype": "postalcode"
  },
  "geometry": {"coordinates":[-1.408196,53.38537],"type":"Point"}
}
