{
  "type": "Feature",
  "properties": {
    "iso:country":"GB",
    "wof:name":"YO32 3QW",
    "wof:placetype":"postalcode"
},
  "geometry": {"coordinates":[-1.07168430442741,54.01803795247798],"type":"Point"}
}