{
  "type": "Feature",
  "properties": {
    "date:inception_lower": "2005-04-01",
    "date:inception_upper": "2005-04-01",
    "iso:country": "GB",
    "wof:name": "YO32 3QW",
    "wof:placetype": "postalcode"
  },
  "geometry": {"coordinates":[-1.071684,54.018038],"type":"Point"}
}
