{
  "type": "Feature",
  "properties": {
    "iso:country":"GB",
    "wof:name":"AB45 2PJ",
    "wof:placetype":"postalcode"
},
  "geometry": {"coordinates":[-2.69349655290206,57.68323216945321],"type":"Point"}
}