{
  "type": "Feature",
  "properties": {
    "iso:country": "GB",
    "wof:name": "RG1 3BJ",
    "wof:placetype": "postalcode"
  },
  "geometry": {"coordinates":[-0.964789,51.454613],"type":"Point"}
}
