{
  "type": "Feature",
  "properties": {
    "date:inception_lower": "2016-02-01",
    "date:inception_upper": "2016-02-01",
    "iso:country": "GB",
    "wof:name": "SW16 4DH",
    "wof:placetype": "postalcode"
  },
  "geometry": {"coordinates":[-0.120629,51.407296],"type":"Point"}
}
