{
  "type": "Feature",
  "properties": {
    "iso:country":"GB",
    "wof:name":"AL7 1NS",
    "wof:placetype":"postalcode"
},
  "geometry": {"coordinates":[-0.18869136656199,51.8116728777125],"type":"Point"}
}