{
  "type": "Feature",
  "properties": {
    "date:inception_lower":"1980-01-01",
    "date:inception_upper":"1980-01-31",
    "iso:country":"GB",
    "wof:name":"AL7 1NS",
    "wof:placetype":"postalcode"
},
  "geometry": {"coordinates":[-0.188691,51.811673],"type":"Point"}
}