{
  "type": "Feature",
  "properties": {
    "iso:country":"GB",
    "wof:name":"TR16 6SF",
    "wof:placetype":"postalcode"
},
  "geometry": {"coordinates":[-5.25414408282147,50.21179060191805],"type":"Point"}
}