{
  "type": "Feature",
  "properties": {
    "date:inception_lower":"1980-01-01",
    "date:inception_upper":"1980-01-31",
    "iso:country":"GB",
    "wof:name":"TR16 6SF",
    "wof:placetype":"postalcode"
},
  "geometry": {"coordinates":[-5.254144,50.211791],"type":"Point"}
}