{
  "type": "Feature",
  "properties": {
    "iso:country":"GB",
    "wof:name":"TA10 9JW",
    "wof:placetype":"postalcode"
},
  "geometry": {"coordinates":[-2.76004029885544,51.02400080065836],"type":"Point"}
}