{
  "type": "Feature",
  "properties": {
    "iso:country":"GB",
    "wof:name":"MK11 1JD",
    "wof:placetype":"postalcode"
},
  "geometry": {"coordinates":[-0.84672738835245,52.05648092888056],"type":"Point"}
}