{
  "type": "Feature",
  "properties": {
    "iso:country": "GB",
    "wof:name": "BH15 4FS",
    "wof:placetype": "postalcode"
  },
  "geometry": {"coordinates":[-2.014929,50.718931],"type":"Point"}
}
