{
  "type": "Feature",
  "properties": {
    "date:inception_lower": "2021-07-01",
    "date:inception_upper": "2021-07-01",
    "iso:country": "GB",
    "wof:name": "GU51 5EN",
    "wof:placetype": "postalcode"
  },
  "geometry": {"coordinates":[-0.861605,51.273383],"type":"Point"}
}
