{
  "type": "Feature",
  "properties": {
    "iso:country":"GB",
    "wof:name":"PE22 8JQ",
    "wof:placetype":"postalcode"
},
  "geometry": {"coordinates":[0.03790381780283,53.07585143818535],"type":"Point"}
}