{
  "type": "Feature",
  "properties": {
    "iso:country":"GB",
    "wof:name":"GU16 8TD",
    "wof:placetype":"postalcode"
},
  "geometry": {"coordinates":[-0.7358361737577,51.32046286589776],"type":"Point"}
}