{
  "type": "Feature",
  "properties": {
    "iso:country":"GB",
    "wof:name":"MK2 3QS",
    "wof:placetype":"postalcode"
},
  "geometry": {"coordinates":[-0.72522385735927,51.97986516111999],"type":"Point"}
}