{
  "type": "Feature",
  "properties": {
    "iso:country": "GB",
    "wof:name": "MK2 3QS",
    "wof:placetype": "postalcode"
  },
  "geometry": {"coordinates":[-0.725224,51.979865],"type":"Point"}
}
