{
  "type": "Feature",
  "properties": {
    "iso:country": "GB",
    "wof:name": "NE6 4AW",
    "wof:placetype": "postalcode"
  },
  "geometry": {"coordinates":[-1.545568,54.980842],"type":"Point"}
}
