{
  "type": "Feature",
  "properties": {
    "iso:country":"GB",
    "wof:name":"DY4 8XR",
    "wof:placetype":"postalcode"
},
  "geometry": {"coordinates":[-2.06074409496473,52.51684119843244],"type":"Point"}
}