{
  "type": "Feature",
  "properties": {
    "date:inception_lower": "1980-01-01",
    "date:inception_upper": "1980-01-01",
    "iso:country": "GB",
    "wof:name": "WF11 8QF",
    "wof:placetype": "postalcode"
  },
  "geometry": {"coordinates":[-1.277345,53.7099],"type":"Point"}
}
