{
  "type": "Feature",
  "properties": {
    "iso:country":"GB",
    "wof:name":"WF11 8QF",
    "wof:placetype":"postalcode"
},
  "geometry": {"coordinates":[-1.27734504787376,53.70990040752065],"type":"Point"}
}