{
  "type": "Feature",
  "properties": {
    "iso:country": "GB",
    "wof:name": "ST19 9QT",
    "wof:placetype": "postalcode"
  },
  "geometry": {"coordinates":[-2.233274,52.694424],"type":"Point"}
}
