{
  "type": "Feature",
  "properties": {
    "iso:country":"GB",
    "wof:name":"UB2 4BP",
    "wof:placetype":"postalcode"
},
  "geometry": {"coordinates":[-0.37705558366869,51.50226456142329],"type":"Point"}
}