{
  "type": "Feature",
  "properties": {
    "iso:country":"GB",
    "wof:name":"TF1 6SS",
    "wof:placetype":"postalcode"
},
  "geometry": {"coordinates":[-2.50211616317129,52.71169738267106],"type":"Point"}
}