{
  "type": "Feature",
  "properties": {
    "date:inception_lower": "1980-01-01",
    "date:inception_upper": "1980-01-01",
    "iso:country": "GB",
    "wof:name": "RG9 6HZ",
    "wof:placetype": "postalcode"
  },
  "geometry": {"coordinates":[-0.914652,51.57447],"type":"Point"}
}
