{
  "type": "Feature",
  "properties": {
    "date:inception_lower": "1980-01-01",
    "date:inception_upper": "1980-01-01",
    "iso:country": "GB",
    "wof:name": "BD21 4QL",
    "wof:placetype": "postalcode"
  },
  "geometry": {"coordinates":[-1.900871,53.864101],"type":"Point"}
}
