{
  "type": "Feature",
  "properties": {
    "iso:country":"GB",
    "wof:name":"BD21 4QL",
    "wof:placetype":"postalcode"
},
  "geometry": {"coordinates":[-1.90082219512862,53.86410483592322],"type":"Point"}
}