{
  "type": "Feature",
  "properties": {
    "date:inception_lower": "1980-01-01",
    "date:inception_upper": "1980-01-01",
    "iso:country": "GB",
    "wof:name": "PR2 3DP",
    "wof:placetype": "postalcode"
  },
  "geometry": {"coordinates":[-2.712542,53.776597],"type":"Point"}
}
