{
  "type": "Feature",
  "properties": {
    "iso:country":"GB",
    "wof:name":"PR2 3DP",
    "wof:placetype":"postalcode"
},
  "geometry": {"coordinates":[-2.71254212062514,53.77659668617142],"type":"Point"}
}