{
  "type": "Feature",
  "properties": {
    "date:inception_lower":"1980-01-01",
    "date:inception_upper":"1980-01-31",
    "iso:country":"GB",
    "wof:name":"BD10 8AS",
    "wof:placetype":"postalcode"
},
  "geometry": {"coordinates":[-1.719786,53.822547],"type":"Point"}
}