{
  "type": "Feature",
  "properties": {
    "iso:country":"GB",
    "wof:name":"G69 7ED",
    "wof:placetype":"postalcode"
},
  "geometry": {"coordinates":[-4.12074150708341,55.84389296414597],"type":"Point"}
}