{
  "type": "Feature",
  "properties": {
    "date:inception_lower": "1980-01-01",
    "date:inception_upper": "1980-01-01",
    "iso:country": "GB",
    "wof:name": "G69 7ED",
    "wof:placetype": "postalcode"
  },
  "geometry": {"coordinates":[-4.120357,55.843814],"type":"Point"}
}
