{
  "type": "Feature",
  "properties": {
    "iso:country": "GB",
    "wof:name": "S10 3LT",
    "wof:placetype": "postalcode"
  },
  "geometry": {"coordinates":[-1.535057,53.373149],"type":"Point"}
}
