{
  "type": "Feature",
  "properties": {
    "date:inception_lower": "2021-11-01",
    "date:inception_upper": "2021-11-01",
    "iso:country": "GB",
    "wof:name": "SG9 9UN",
    "wof:placetype": "postalcode"
  },
  "geometry": {"coordinates":[-0.012339,51.941557],"type":"Point"}
}
