{
  "type": "Feature",
  "properties": {
    "iso:country":"GB",
    "wof:name":"OL4 5SF",
    "wof:placetype":"postalcode"
},
  "geometry": {"coordinates":[-2.0545203268685,53.53664254769864],"type":"Point"}
}