{
  "type": "Feature",
  "properties": {
    "iso:country": "GB",
    "wof:name": "OL4 5SF",
    "wof:placetype": "postalcode"
  },
  "geometry": {"coordinates":[-2.054941,53.536848],"type":"Point"}
}
