{
  "type": "Feature",
  "properties": {
    "date:inception_lower": "1996-12-01",
    "date:inception_upper": "1996-12-01",
    "iso:country": "GB",
    "wof:name": "CH7 6GL",
    "wof:placetype": "postalcode"
  },
  "geometry": {"coordinates":[-3.091266,53.202359],"type":"Point"}
}
