{
  "type": "Feature",
  "properties": {
    "iso:country": "GB",
    "wof:name": "CH7 6GL",
    "wof:placetype": "postalcode"
  },
  "geometry": {"coordinates":[-3.091266,53.202359],"type":"Point"}
}
