{
  "type": "Feature",
  "properties": {
    "iso:country":"GB",
    "wof:name":"CH7 6GL",
    "wof:placetype":"postalcode"
},
  "geometry": {"coordinates":[-3.09126615519092,53.20235855815164],"type":"Point"}
}