{
  "type": "Feature",
  "properties": {
    "date:inception_lower": "1980-01-01",
    "date:inception_upper": "1980-01-01",
    "iso:country": "GB",
    "wof:name": "ML2 8TX",
    "wof:placetype": "postalcode"
  },
  "geometry": {"coordinates":[-3.906408,55.791459],"type":"Point"}
}
