{
  "type": "Feature",
  "properties": {
    "iso:country": "GB",
    "wof:name": "ML2 8TX",
    "wof:placetype": "postalcode"
  },
  "geometry": {"coordinates":[-3.906408,55.791459],"type":"Point"}
}
