{
  "type": "Feature",
  "properties": {
    "date:inception_lower": "2012-04-01",
    "date:inception_upper": "2012-04-01",
    "iso:country": "GB",
    "wof:name": "M40 8BS",
    "wof:placetype": "postalcode"
  },
  "geometry": {"coordinates":[-2.21466,53.494241],"type":"Point"}
}
