{
  "type": "Feature",
  "properties": {
    "date:inception_lower":"2013-02-01",
    "date:inception_upper":"2013-02-28",
    "iso:country":"GB",
    "wof:name":"WN5 0BF",
    "wof:placetype":"postalcode"
},
  "geometry": {"coordinates":[-2.653052,53.541315],"type":"Point"}
}