{
  "type": "Feature",
  "properties": {
    "iso:country":"GB",
    "wof:name":"CV2 3FW",
    "wof:placetype":"postalcode"
},
  "geometry": {"coordinates":[-1.48073349340865,52.41783506944182],"type":"Point"}
}