{
  "type": "Feature",
  "properties": {
    "date:inception_lower":"1980-01-01",
    "date:inception_upper":"1980-01-31",
    "iso:country":"GB",
    "wof:name":"CV2 3FW",
    "wof:placetype":"postalcode"
},
  "geometry": {"coordinates":[-1.480733,52.417835],"type":"Point"}
}