{
  "type": "Feature",
  "properties": {
    "iso:country": "GB",
    "wof:name": "BH15 1AN",
    "wof:placetype": "postalcode"
  },
  "geometry": {"coordinates":[-1.98424,50.715416],"type":"Point"}
}
