{
  "type": "Feature",
  "properties": {
    "iso:country":"GB",
    "wof:name":"OX33 1BY",
    "wof:placetype":"postalcode"
},
  "geometry": {"coordinates":[-1.12276474768403,51.8161901698091],"type":"Point"}
}