{
  "type": "Feature",
  "properties": {
    "iso:country":"GB",
    "wof:name":"CH63 3EJ",
    "wof:placetype":"postalcode"
},
  "geometry": {"coordinates":[-3.00586926275813,53.34216331171187],"type":"Point"}
}