{
  "type": "Feature",
  "properties": {
    "iso:country":"GB",
    "wof:name":"DT11 7XE",
    "wof:placetype":"postalcode"
},
  "geometry": {"coordinates":[-2.16601714443168,50.85738086954527],"type":"Point"}
}