{
  "type": "Feature",
  "properties": {
    "iso:country":"GB",
    "wof:name":"LS18 4BT",
    "wof:placetype":"postalcode"
},
  "geometry": {"coordinates":[-1.62489813328922,53.83694699623004],"type":"Point"}
}