{
  "type": "Feature",
  "properties": {
    "date:inception_lower": "1980-01-01",
    "date:inception_upper": "1980-01-01",
    "iso:country": "GB",
    "wof:name": "LS18 4BT",
    "wof:placetype": "postalcode"
  },
  "geometry": {"coordinates":[-1.624898,53.836947],"type":"Point"}
}
