{
  "type": "Feature",
  "properties": {
    "iso:country": "GB",
    "wof:name": "IP14 1TJ",
    "wof:placetype": "postalcode"
  },
  "geometry": {"coordinates":[0.981726,52.198854],"type":"Point"}
}
