{
  "type": "Feature",
  "properties": {
    "iso:country":"GB",
    "wof:name":"NG23 5ET",
    "wof:placetype":"postalcode"
},
  "geometry": {"coordinates":[-0.75029580780721,52.98813097826537],"type":"Point"}
}