{
  "type": "Feature",
  "properties": {
    "iso:country":"GB",
    "wof:name":"SK15 1UN",
    "wof:placetype":"postalcode"
},
  "geometry": {"coordinates":[-2.0681129550415,53.47932554084237],"type":"Point"}
}