{
  "type": "Feature",
  "properties": {
    "iso:country":"GB",
    "wof:name":"SG1 2UA",
    "wof:placetype":"postalcode"
},
  "geometry": {"coordinates":[-0.20865213633962,51.89981206206603],"type":"Point"}
}