{
  "type": "Feature",
  "properties": {
    "iso:country": "GB",
    "wof:name": "SK10 4NR",
    "wof:placetype": "postalcode"
  },
  "geometry": {"coordinates":[-2.128654,53.339611],"type":"Point"}
}
