{
  "type": "Feature",
  "properties": {
    "iso:country":"GB",
    "wof:name":"GU32 1EZ",
    "wof:placetype":"postalcode"
},
  "geometry": {"coordinates":[-1.02623160366835,50.98207877025606],"type":"Point"}
}