{
  "type": "Feature",
  "properties": {
    "iso:country": "GB",
    "wof:name": "GU32 1EZ",
    "wof:placetype": "postalcode"
  },
  "geometry": {"coordinates":[-1.026232,50.982079],"type":"Point"}
}
