{
  "type": "Feature",
  "properties": {
    "iso:country":"GB",
    "wof:name":"KY11 8EF",
    "wof:placetype":"postalcode"
},
  "geometry": {"coordinates":[-3.40204969580886,56.08082204700442],"type":"Point"}
}