{
  "type": "Feature",
  "properties": {
    "date:inception_lower": "1998-12-01",
    "date:inception_upper": "1998-12-01",
    "iso:country": "GB",
    "wof:name": "KY11 8EF",
    "wof:placetype": "postalcode"
  },
  "geometry": {"coordinates":[-3.40205,56.080822],"type":"Point"}
}
