{
  "type": "Feature",
  "properties": {
    "iso:country": "GB",
    "wof:name": "KY11 8EF",
    "wof:placetype": "postalcode"
  },
  "geometry": {"coordinates":[-3.40205,56.080822],"type":"Point"}
}
