{
  "type": "Feature",
  "properties": {
    "iso:country": "GB",
    "wof:name": "YO60 7RZ",
    "wof:placetype": "postalcode"
  },
  "geometry": {"coordinates":[-0.9432,54.033264],"type":"Point"}
}
