{
  "type": "Feature",
  "properties": {
    "date:inception_lower": "1998-06-01",
    "date:inception_upper": "1998-06-01",
    "iso:country": "GB",
    "wof:name": "TR9 6JR",
    "wof:placetype": "postalcode"
  },
  "geometry": {"coordinates":[-4.937656,50.387737],"type":"Point"}
}
