{
  "type": "Feature",
  "properties": {
    "iso:country":"GB",
    "wof:name":"ME1 1JT",
    "wof:placetype":"postalcode"
},
  "geometry": {"coordinates":[0.50495251399048,51.38798221963186],"type":"Point"}
}