{
  "type": "Feature",
  "properties": {
    "iso:country": "GB",
    "wof:name": "ME1 1JT",
    "wof:placetype": "postalcode"
  },
  "geometry": {"coordinates":[0.504953,51.387982],"type":"Point"}
}
