{
  "type": "Feature",
  "properties": {
    "iso:country": "GB",
    "wof:name": "HX3 6EH",
    "wof:placetype": "postalcode"
  },
  "geometry": {"coordinates":[-1.866364,53.730771],"type":"Point"}
}
