{
  "type": "Feature",
  "properties": {
    "iso:country":"GB",
    "wof:name":"HX3 6EH",
    "wof:placetype":"postalcode"
},
  "geometry": {"coordinates":[-1.86636400042189,53.73077100895956],"type":"Point"}
}