{
  "type": "Feature",
  "properties": {
    "iso:country":"GB",
    "wof:name":"BB9 7SR",
    "wof:placetype":"postalcode"
},
  "geometry": {"coordinates":[-2.2188503497275,53.83804247724466],"type":"Point"}
}