{
  "type": "Feature",
  "properties": {
    "iso:country": "GB",
    "wof:name": "TS5 4QU",
    "wof:placetype": "postalcode"
  },
  "geometry": {"coordinates":[-1.270333,54.549473],"type":"Point"}
}
