{
  "type": "Feature",
  "properties": {
    "iso:country": "GB",
    "wof:name": "TS5 4QU",
    "wof:placetype": "postalcode"
  },
  "geometry": {"coordinates":[-1.270303,54.549428],"type":"Point"}
}
