{
  "type": "Feature",
  "properties": {
    "iso:country":"GB",
    "wof:name":"TS5 4QU",
    "wof:placetype":"postalcode"
},
  "geometry": {"coordinates":[-1.27031965663374,54.54946027989433],"type":"Point"}
}