{
  "type": "Feature",
  "properties": {
    "iso:country":"GB",
    "wof:name":"CT19 4QQ",
    "wof:placetype":"postalcode"
},
  "geometry": {"coordinates":[1.13311733897235,51.09124275593199],"type":"Point"}
}