{
  "type": "Feature",
  "properties": {
    "iso:country":"GB",
    "wof:name":"BH21 7NZ",
    "wof:placetype":"postalcode"
},
  "geometry": {"coordinates":[-1.91348128482874,50.80441169229231],"type":"Point"}
}