{
  "type": "Feature",
  "properties": {
    "iso:country":"GB",
    "wof:name":"BS22 9RE",
    "wof:placetype":"postalcode"
},
  "geometry": {"coordinates":[-2.95103639901679,51.36055602431753],"type":"Point"}
}