{
  "type": "Feature",
  "properties": {
    "iso:country": "GB",
    "wof:name": "BS22 9RE",
    "wof:placetype": "postalcode"
  },
  "geometry": {"coordinates":[-2.951036,51.360556],"type":"Point"}
}
