{
  "type": "Feature",
  "properties": {
    "date:inception_lower": "1994-05-01",
    "date:inception_upper": "1994-05-01",
    "iso:country": "GB",
    "wof:name": "M20 6JB",
    "wof:placetype": "postalcode"
  },
  "geometry": {"coordinates":[-2.222919,53.416082],"type":"Point"}
}
