{
  "type": "Feature",
  "properties": {
    "iso:country": "GB",
    "wof:name": "EX11 1SP",
    "wof:placetype": "postalcode"
  },
  "geometry": {"coordinates":[-3.322632,50.723937],"type":"Point"}
}
