{
  "type": "Feature",
  "properties": {
    "iso:country":"GB",
    "wof:name":"HU7 4EG",
    "wof:placetype":"postalcode"
},
  "geometry": {"coordinates":[-0.30843565550373,53.78229139449037],"type":"Point"}
}