{
  "type": "Feature",
  "properties": {
    "iso:country": "GB",
    "wof:name": "HU7 4EG",
    "wof:placetype": "postalcode"
  },
  "geometry": {"coordinates":[-0.308443,53.782312],"type":"Point"}
}
