{
  "type": "Feature",
  "properties": {
    "date:inception_lower":"2014-11-01",
    "date:inception_upper":"2014-11-30",
    "iso:country":"GB",
    "wof:name":"HU7 4EG",
    "wof:placetype":"postalcode"
},
  "geometry": {"coordinates":[-0.308551,53.782251],"type":"Point"}
}