{
  "type": "Feature",
  "properties": {
    "iso:country":"GB",
    "wof:name":"AB54 7UP",
    "wof:placetype":"postalcode"
},
  "geometry": {"coordinates":[-2.66077433764544,57.52442413115708],"type":"Point"}
}