{
  "type": "Feature",
  "properties": {
    "iso:country": "GB",
    "wof:name": "AB54 7UP",
    "wof:placetype": "postalcode"
  },
  "geometry": {"coordinates":[-2.660774,57.524424],"type":"Point"}
}
