{
  "type": "Feature",
  "properties": {
    "iso:country":"GB",
    "wof:name":"PL20 6RN",
    "wof:placetype":"postalcode"
},
  "geometry": {"coordinates":[-4.00072106024514,50.55025668970681],"type":"Point"}
}