{
  "type": "Feature",
  "properties": {
    "iso:country": "GB",
    "wof:name": "BN16 3QH",
    "wof:placetype": "postalcode"
  },
  "geometry": {"coordinates":[-0.513663,50.815401],"type":"Point"}
}
