{
  "type": "Feature",
  "properties": {
    "iso:country":"GB",
    "wof:name":"IV3 5HT",
    "wof:placetype":"postalcode"
},
  "geometry": {"coordinates":[-4.23267250177834,57.47910190507466],"type":"Point"}
}