{
  "type": "Feature",
  "properties": {
    "iso:country": "GB",
    "wof:name": "PO5 4LL",
    "wof:placetype": "postalcode"
  },
  "geometry": {"coordinates":[-1.085382,50.796805],"type":"Point"}
}
