{
  "type": "Feature",
  "properties": {
    "date:inception_lower": "1980-01-01",
    "date:inception_upper": "1980-01-01",
    "iso:country": "GB",
    "wof:name": "SK8 7NG",
    "wof:placetype": "postalcode"
  },
  "geometry": {"coordinates":[-2.185013,53.355609],"type":"Point"}
}
