{
  "type": "Feature",
  "properties": {
    "iso:country": "GB",
    "wof:name": "GL2 9EB",
    "wof:placetype": "postalcode"
  },
  "geometry": {"coordinates":[-2.236409,51.879119],"type":"Point"}
}
