{
  "type": "Feature",
  "properties": {
    "iso:country":"GB",
    "wof:name":"SY16 1BL",
    "wof:placetype":"postalcode"
},
  "geometry": {"coordinates":[-3.31096123666789,52.51369252511306],"type":"Point"}
}