{
  "type": "Feature",
  "properties": {
    "date:inception_lower": "1980-01-01",
    "date:inception_upper": "1980-01-01",
    "iso:country": "GB",
    "wof:name": "LL12 8NL",
    "wof:placetype": "postalcode"
  },
  "geometry": {"coordinates":[-2.973742,53.087334],"type":"Point"}
}
