{
  "type": "Feature",
  "properties": {
    "iso:country":"GB",
    "wof:name":"LL12 8NL",
    "wof:placetype":"postalcode"
},
  "geometry": {"coordinates":[-2.97374155415045,53.08733423864724],"type":"Point"}
}