{
  "type": "Feature",
  "properties": {
    "iso:country":"GB",
    "wof:name":"NR7 0RJ",
    "wof:placetype":"postalcode"
},
  "geometry": {"coordinates":[1.35516729034855,52.62968549860059],"type":"Point"}
}