{
  "type": "Feature",
  "properties": {
    "iso:country": "GB",
    "wof:name": "CB25 0BU",
    "wof:placetype": "postalcode"
  },
  "geometry": {"coordinates":[0.325176,52.266975],"type":"Point"}
}
