{
  "type": "Feature",
  "properties": {
    "iso:country":"GB",
    "wof:name":"CB25 0BU",
    "wof:placetype":"postalcode"
},
  "geometry": {"coordinates":[0.32517602037731,52.26697516896247],"type":"Point"}
}