{
  "type": "Feature",
  "properties": {
    "iso:country": "GB",
    "wof:name": "NN6 8BY",
    "wof:placetype": "postalcode"
  },
  "geometry": {"coordinates":[-1.023888,52.309264],"type":"Point"}
}
