{
  "type": "Feature",
  "properties": {
    "iso:country":"GB",
    "wof:name":"NP15 1AQ",
    "wof:placetype":"postalcode"
},
  "geometry": {"coordinates":[-2.90370105242756,51.70068998886974],"type":"Point"}
}