{
  "type": "Feature",
  "properties": {
    "iso:country": "GB",
    "wof:name": "NP15 1AQ",
    "wof:placetype": "postalcode"
  },
  "geometry": {"coordinates":[-2.903701,51.70069],"type":"Point"}
}
