{
  "type": "Feature",
  "properties": {
    "iso:country":"GB",
    "wof:name":"IP22 4QA",
    "wof:placetype":"postalcode"
},
  "geometry": {"coordinates":[1.11651932361402,52.37313537598488],"type":"Point"}
}