{
  "type": "Feature",
  "properties": {
    "date:inception_lower": "1999-12-01",
    "date:inception_upper": "1999-12-01",
    "iso:country": "GB",
    "wof:name": "IP22 4QA",
    "wof:placetype": "postalcode"
  },
  "geometry": {"coordinates":[1.116519,52.373135],"type":"Point"}
}
