{
  "type": "Feature",
  "properties": {
    "date:inception_lower": "1980-01-01",
    "date:inception_upper": "1980-01-01",
    "iso:country": "GB",
    "wof:name": "SA43 2HR",
    "wof:placetype": "postalcode"
  },
  "geometry": {"coordinates":[-4.51768,52.121076],"type":"Point"}
}
