{
  "type": "Feature",
  "properties": {
    "iso:country":"GB",
    "wof:name":"BA1 9BL",
    "wof:placetype":"postalcode"
},
  "geometry": {"coordinates":[-2.39725751590074,51.41361154556692],"type":"Point"}
}