{
  "type": "Feature",
  "properties": {
    "iso:country":"GB",
    "wof:name":"BN7 3BP",
    "wof:placetype":"postalcode"
},
  "geometry": {"coordinates":[-0.06257120116176,50.93141717602226],"type":"Point"}
}