{
  "type": "Feature",
  "properties": {
    "iso:country": "GB",
    "wof:name": "CR7 7AZ",
    "wof:placetype": "postalcode"
  },
  "geometry": {"coordinates":[-0.0982,51.394083],"type":"Point"}
}
