{
  "type": "Feature",
  "properties": {
    "iso:country":"GB",
    "wof:name":"CR7 7AZ",
    "wof:placetype":"postalcode"
},
  "geometry": {"coordinates":[-0.09820039921155,51.39408324001209],"type":"Point"}
}