{
  "type": "Feature",
  "properties": {
    "date:inception_lower": "1993-08-01",
    "date:inception_upper": "1993-08-01",
    "iso:country": "GB",
    "wof:name": "LL53 7AS",
    "wof:placetype": "postalcode"
  },
  "geometry": {"coordinates":[-4.504382,52.825546],"type":"Point"}
}
