{
  "type": "Feature",
  "properties": {
    "iso:country":"GB",
    "wof:name":"LL53 7AS",
    "wof:placetype":"postalcode"
},
  "geometry": {"coordinates":[-4.50438176511777,52.82554590979257],"type":"Point"}
}