{
  "type": "Feature",
  "properties": {
    "iso:country":"GB",
    "wof:name":"DN21 3DZ",
    "wof:placetype":"postalcode"
},
  "geometry": {"coordinates":[-0.77296820303736,53.48701731335669],"type":"Point"}
}