{
  "type": "Feature",
  "properties": {
    "date:inception_lower": "1980-01-01",
    "date:inception_upper": "1980-01-01",
    "iso:country": "GB",
    "wof:name": "CA4 0AE",
    "wof:placetype": "postalcode"
  },
  "geometry": {"coordinates":[-2.87566,54.861564],"type":"Point"}
}
