{
  "type": "Feature",
  "properties": {
    "iso:country": "GB",
    "wof:name": "CA4 0AE",
    "wof:placetype": "postalcode"
  },
  "geometry": {"coordinates":[-2.871635,54.861342],"type":"Point"}
}
