{
  "type": "Feature",
  "properties": {
    "iso:country":"GB",
    "wof:name":"N13 4EP",
    "wof:placetype":"postalcode"
},
  "geometry": {"coordinates":[-0.09957870538109,51.62649128796199],"type":"Point"}
}