{
  "type": "Feature",
  "properties": {
    "date:inception_lower": "1980-01-01",
    "date:inception_upper": "1980-01-01",
    "iso:country": "GB",
    "wof:name": "N13 4EP",
    "wof:placetype": "postalcode"
  },
  "geometry": {"coordinates":[-0.099372,51.626329],"type":"Point"}
}
