{
  "type": "Feature",
  "properties": {
    "iso:country":"GB",
    "wof:name":"AB22 8QU",
    "wof:placetype":"postalcode"
},
  "geometry": {"coordinates":[-2.11512391282115,57.1851001827212],"type":"Point"}
}