{
  "type": "Feature",
  "properties": {
    "date:inception_lower": "1980-01-01",
    "date:inception_upper": "1980-01-01",
    "iso:country": "GB",
    "wof:name": "NE37 1EE",
    "wof:placetype": "postalcode"
  },
  "geometry": {"coordinates":[-1.536506,54.918353],"type":"Point"}
}
