{
  "type": "Feature",
  "properties": {
    "iso:country":"GB",
    "wof:name":"SN10 5JU",
    "wof:placetype":"postalcode"
},
  "geometry": {"coordinates":[-1.99338967139521,51.34255004287376],"type":"Point"}
}