{
  "type": "Feature",
  "properties": {
    "iso:country":"GB",
    "wof:name":"SW6 4SL",
    "wof:placetype":"postalcode"
},
  "geometry": {"coordinates":[-0.19530793882567,51.4742050096178],"type":"Point"}
}