{
  "type": "Feature",
  "properties": {
    "iso:country":"GB",
    "wof:name":"KA20 3HU",
    "wof:placetype":"postalcode"
},
  "geometry": {"coordinates":[-4.75750691295113,55.63557375836086],"type":"Point"}
}