{
  "type": "Feature",
  "properties": {
    "date:inception_lower": "1998-12-01",
    "date:inception_upper": "1998-12-01",
    "iso:country": "GB",
    "wof:name": "TQ12 6UE",
    "wof:placetype": "postalcode"
  },
  "geometry": {"coordinates":[-3.654394,50.573196],"type":"Point"}
}
