{
  "type": "Feature",
  "properties": {
    "date:inception_lower": "1980-01-01",
    "date:inception_upper": "1980-01-01",
    "iso:country": "GB",
    "wof:name": "PE8 4EJ",
    "wof:placetype": "postalcode"
  },
  "geometry": {"coordinates":[-0.472477,52.481233],"type":"Point"}
}
