{
  "type": "Feature",
  "properties": {
    "iso:country":"GB",
    "wof:name":"PE8 4EJ",
    "wof:placetype":"postalcode"
},
  "geometry": {"coordinates":[-0.47227653201622,52.48107867431004],"type":"Point"}
}