{
  "type": "Feature",
  "properties": {
    "date:inception_lower":"1990-02-01",
    "date:inception_upper":"1990-02-28",
    "iso:country":"GB",
    "wof:name":"SO24 9PD",
    "wof:placetype":"postalcode"
},
  "geometry": {"coordinates":[-1.165552,51.083862],"type":"Point"}
}