{
  "type": "Feature",
  "properties": {
    "iso:country":"GB",
    "wof:name":"NG25 0QE",
    "wof:placetype":"postalcode"
},
  "geometry": {"coordinates":[-0.9661036002809,53.06325196256579],"type":"Point"}
}