{
  "type": "Feature",
  "properties": {
    "iso:country": "GB",
    "wof:name": "NG25 0QE",
    "wof:placetype": "postalcode"
  },
  "geometry": {"coordinates":[-0.965308,53.063301],"type":"Point"}
}
