{
  "type": "Feature",
  "properties": {
    "iso:country":"GB",
    "wof:name":"PO16 9LW",
    "wof:placetype":"postalcode"
},
  "geometry": {"coordinates":[-1.12599683121521,50.83910307794564],"type":"Point"}
}