{
  "type": "Feature",
  "properties": {
    "date:inception_lower": "1980-01-01",
    "date:inception_upper": "1980-01-01",
    "iso:country": "GB",
    "wof:name": "GL2 8JQ",
    "wof:placetype": "postalcode"
  },
  "geometry": {"coordinates":[-2.30882,51.855133],"type":"Point"}
}
