{
  "type": "Feature",
  "properties": {
    "date:inception_lower":"2010-06-01",
    "date:inception_upper":"2010-06-30",
    "iso:country":"GB",
    "wof:name":"E12 5BN",
    "wof:placetype":"postalcode"
},
  "geometry": {"coordinates":[0.064093,51.552362],"type":"Point"}
}