{
  "type": "Feature",
  "properties": {
    "iso:country": "GB",
    "wof:name": "GL1 1QZ",
    "wof:placetype": "postalcode"
  },
  "geometry": {"coordinates":[-2.241819,51.861243],"type":"Point"}
}
