{
  "type": "Feature",
  "properties": {
    "iso:country":"GB",
    "wof:name":"WV11 3BZ",
    "wof:placetype":"postalcode"
},
  "geometry": {"coordinates":[-2.07231346513038,52.60700270893196],"type":"Point"}
}