{
  "type": "Feature",
  "properties": {
    "iso:country":"GB",
    "wof:name":"ST16 3WU",
    "wof:placetype":"postalcode"
},
  "geometry": {"coordinates":[-2.10324328383429,52.81697694683383],"type":"Point"}
}