{
  "type": "Feature",
  "properties": {
    "date:inception_lower": "2015-06-01",
    "date:inception_upper": "2015-06-01",
    "iso:country": "GB",
    "wof:name": "ST16 3WU",
    "wof:placetype": "postalcode"
  },
  "geometry": {"coordinates":[-2.103243,52.816977],"type":"Point"}
}
