{
  "type": "Feature",
  "properties": {
    "iso:country":"GB",
    "wof:name":"G63 9QL",
    "wof:placetype":"postalcode"
},
  "geometry": {"coordinates":[-4.41646058129794,56.02867243038735],"type":"Point"}
}