{
  "type": "Feature",
  "properties": {
    "iso:country": "GB",
    "wof:name": "G63 9QL",
    "wof:placetype": "postalcode"
  },
  "geometry": {"coordinates":[-4.416446,56.028666],"type":"Point"}
}
