{
  "type": "Feature",
  "properties": {
    "iso:country":"GB",
    "wof:name":"CW7 2EP",
    "wof:placetype":"postalcode"
},
  "geometry": {"coordinates":[-2.54427206714815,53.19278301240598],"type":"Point"}
}