{
  "type": "Feature",
  "properties": {
    "iso:country": "GB",
    "wof:name": "CW7 2EP",
    "wof:placetype": "postalcode"
  },
  "geometry": {"coordinates":[-2.544272,53.192783],"type":"Point"}
}
