{
  "type": "Feature",
  "properties": {
    "iso:country": "GB",
    "wof:name": "TS15 9ZH",
    "wof:placetype": "postalcode"
  },
  "geometry": {"coordinates":[-1.359078,54.491774],"type":"Point"}
}
