{
  "type": "Feature",
  "properties": {
    "date:inception_lower": "2017-03-01",
    "date:inception_upper": "2017-03-01",
    "iso:country": "GB",
    "wof:name": "TS15 9ZH",
    "wof:placetype": "postalcode"
  },
  "geometry": {"coordinates":[-1.358583,54.491861],"type":"Point"}
}
