{
  "type": "Feature",
  "properties": {
    "date:inception_lower": "1999-12-01",
    "date:inception_upper": "1999-12-01",
    "iso:country": "GB",
    "wof:name": "NR34 7QD",
    "wof:placetype": "postalcode"
  },
  "geometry": {"coordinates":[1.639124,52.447977],"type":"Point"}
}
