{
  "type": "Feature",
  "properties": {
    "iso:country":"GB",
    "wof:name":"EN9 1PX",
    "wof:placetype":"postalcode"
},
  "geometry": {"coordinates":[0.00312381357478,51.68825269713739],"type":"Point"}
}