{
  "type": "Feature",
  "properties": {
    "iso:country":"GB",
    "wof:name":"RG10 9YE",
    "wof:placetype":"postalcode"
},
  "geometry": {"coordinates":[-0.81188281115824,51.50731283150569],"type":"Point"}
}