{
  "type": "Feature",
  "properties": {
    "iso:country": "GB",
    "wof:name": "RG10 9YE",
    "wof:placetype": "postalcode"
  },
  "geometry": {"coordinates":[-0.811833,51.507377],"type":"Point"}
}
