{
  "type": "Feature",
  "properties": {
    "date:inception_lower": "1980-01-01",
    "date:inception_upper": "1980-01-01",
    "iso:country": "GB",
    "wof:name": "RG10 9YE",
    "wof:placetype": "postalcode"
  },
  "geometry": {"coordinates":[-0.811833,51.507377],"type":"Point"}
}
