{
  "type": "Feature",
  "properties": {
    "iso:country":"GB",
    "wof:name":"CA12 4HG",
    "wof:placetype":"postalcode"
},
  "geometry": {"coordinates":[-3.13259019104789,54.60100735600209],"type":"Point"}
}