{
  "type": "Feature",
  "properties": {
    "date:inception_lower":"1988-03-01",
    "date:inception_upper":"1988-03-31",
    "iso:country":"GB",
    "wof:name":"SA1 1XX",
    "wof:placetype":"postalcode"
},
  "geometry": {"coordinates":[-3.938718,51.614724],"type":"Point"}
}