{
  "type": "Feature",
  "properties": {
    "iso:country": "GB",
    "wof:name": "SA1 1XX",
    "wof:placetype": "postalcode"
  },
  "geometry": {"coordinates":[-3.938718,51.614724],"type":"Point"}
}
