{
  "type": "Feature",
  "properties": {
    "iso:country":"GB",
    "wof:name":"LE1 4PJ",
    "wof:placetype":"postalcode"
},
  "geometry": {"coordinates":[-1.14049244318392,52.63754015285539],"type":"Point"}
}