{
  "type": "Feature",
  "properties": {
    "date:inception_lower": "1980-01-01",
    "date:inception_upper": "1980-01-01",
    "iso:country": "GB",
    "wof:name": "LE1 4PJ",
    "wof:placetype": "postalcode"
  },
  "geometry": {"coordinates":[-1.140492,52.63754],"type":"Point"}
}
