{
  "type": "Feature",
  "properties": {
    "date:inception_lower":"1980-01-01",
    "date:inception_upper":"1980-01-31",
    "iso:country":"GB",
    "wof:name":"S45 0BL",
    "wof:placetype":"postalcode"
},
  "geometry": {"coordinates":[-1.459555,53.162771],"type":"Point"}
}