{
  "type": "Feature",
  "properties": {
    "iso:country":"GB",
    "wof:name":"S45 0BL",
    "wof:placetype":"postalcode"
},
  "geometry": {"coordinates":[-1.45923030008155,53.16258930690437],"type":"Point"}
}