{
  "type": "Feature",
  "properties": {
    "date:inception_lower":"1980-01-01",
    "date:inception_upper":"1980-01-31",
    "iso:country":"GB",
    "wof:name":"DG1 4RT",
    "wof:placetype":"postalcode"
},
  "geometry": {"coordinates":[-3.516311,54.984727],"type":"Point"}
}