{
  "type": "Feature",
  "properties": {
    "date:inception_lower":"2001-06-01",
    "date:inception_upper":"2001-06-30",
    "iso:country":"GB",
    "wof:name":"LU7 1EZ",
    "wof:placetype":"postalcode"
},
  "geometry": {"coordinates":[-0.65756,51.917658],"type":"Point"}
}