{
  "type": "Feature",
  "properties": {
    "iso:country":"GB",
    "wof:name":"LU7 1EZ",
    "wof:placetype":"postalcode"
},
  "geometry": {"coordinates":[-0.65752683794845,51.91766602869152],"type":"Point"}
}