{
  "type": "Feature",
  "properties": {
    "iso:country":"GB",
    "wof:name":"DE4 4ET",
    "wof:placetype":"postalcode"
},
  "geometry": {"coordinates":[-1.57387361025078,53.08250350305133],"type":"Point"}
}