{
  "type": "Feature",
  "properties": {
    "iso:country": "GB",
    "wof:name": "WA10 1BZ",
    "wof:placetype": "postalcode"
  },
  "geometry": {"coordinates":[-2.732079,53.452113],"type":"Point"}
}
