{
  "type": "Feature",
  "properties": {
    "iso:country":"GB",
    "wof:name":"PL32 9XX",
    "wof:placetype":"postalcode"
},
  "geometry": {"coordinates":[-4.61235070918833,50.65378809888531],"type":"Point"}
}