{
  "type": "Feature",
  "properties": {
    "date:inception_lower": "1980-01-01",
    "date:inception_upper": "1980-01-01",
    "iso:country": "GB",
    "wof:name": "GL6 0PP",
    "wof:placetype": "postalcode"
  },
  "geometry": {"coordinates":[-2.230919,51.681483],"type":"Point"}
}
