{
  "type": "Feature",
  "properties": {
    "iso:country": "GB",
    "wof:name": "GL6 0PP",
    "wof:placetype": "postalcode"
  },
  "geometry": {"coordinates":[-2.230919,51.681483],"type":"Point"}
}
