{
  "type": "Feature",
  "properties": {
    "iso:country":"GB",
    "wof:name":"GL6 0PP",
    "wof:placetype":"postalcode"
},
  "geometry": {"coordinates":[-2.23115359701611,51.681353710496],"type":"Point"}
}