{
  "type": "Feature",
  "properties": {
    "iso:country": "GB",
    "wof:name": "LL41 4SG",
    "wof:placetype": "postalcode"
  },
  "geometry": {"coordinates":[-3.92407,52.901424],"type":"Point"}
}
