{
  "type": "Feature",
  "properties": {
    "iso:country":"GB",
    "wof:name":"DN1 2QA",
    "wof:placetype":"postalcode"
},
  "geometry": {"coordinates":[-1.12781416438025,53.52628542669041],"type":"Point"}
}