{
  "type": "Feature",
  "properties": {
    "date:inception_lower": "2016-11-01",
    "date:inception_upper": "2016-11-01",
    "iso:country": "GB",
    "wof:name": "CM2 8FU",
    "wof:placetype": "postalcode"
  },
  "geometry": {"coordinates":[0.453976,51.696402],"type":"Point"}
}
