{
  "type": "Feature",
  "properties": {
    "date:inception_lower":"1994-12-01",
    "date:inception_upper":"1994-12-31",
    "iso:country":"GB",
    "wof:name":"SO41 3YL",
    "wof:placetype":"postalcode"
},
  "geometry": {"coordinates":[-1.534857,50.757448],"type":"Point"}
}