{
  "type": "Feature",
  "properties": {
    "date:inception_lower": "1981-06-01",
    "date:inception_upper": "1981-06-01",
    "iso:country": "GB",
    "wof:name": "CV8 2PW",
    "wof:placetype": "postalcode"
  },
  "geometry": {"coordinates":[-1.558183,52.350984],"type":"Point"}
}
