{
  "type": "Feature",
  "properties": {
    "iso:country": "GB",
    "wof:name": "NE16 5EQ",
    "wof:placetype": "postalcode"
  },
  "geometry": {"coordinates":[-1.67556,54.903696],"type":"Point"}
}
