{
  "type": "Feature",
  "properties": {
    "iso:country":"GB",
    "wof:name":"NE16 5EQ",
    "wof:placetype":"postalcode"
},
  "geometry": {"coordinates":[-1.6747230329126,54.90350651524177],"type":"Point"}
}