{
  "type": "Feature",
  "properties": {
    "iso:country":"GB",
    "wof:name":"LE9 7NU",
    "wof:placetype":"postalcode"
},
  "geometry": {"coordinates":[-1.27300860969456,52.5808553943196],"type":"Point"}
}