{
  "type": "Feature",
  "properties": {
    "date:inception_lower": "2012-02-01",
    "date:inception_upper": "2012-02-01",
    "iso:country": "GB",
    "wof:name": "LE9 7NU",
    "wof:placetype": "postalcode"
  },
  "geometry": {"coordinates":[-1.272998,52.580874],"type":"Point"}
}
