{
  "type": "Feature",
  "properties": {
    "iso:country":"GB",
    "wof:name":"SY24 5HF",
    "wof:placetype":"postalcode"
},
  "geometry": {"coordinates":[-3.98096864340884,52.48894098316734],"type":"Point"}
}