{
  "type": "Feature",
  "properties": {
    "iso:country": "GB",
    "wof:name": "CF34 9RW",
    "wof:placetype": "postalcode"
  },
  "geometry": {"coordinates":[-3.630639,51.584456],"type":"Point"}
}
