{
  "type": "Feature",
  "properties": {
    "iso:country":"GB",
    "wof:name":"ME10 3BD",
    "wof:placetype":"postalcode"
},
  "geometry": {"coordinates":[0.75969244277536,51.33779064328012],"type":"Point"}
}