{
  "type": "Feature",
  "properties": {
    "iso:country": "GB",
    "wof:name": "NG31 6LD",
    "wof:placetype": "postalcode"
  },
  "geometry": {"coordinates":[-0.644708,52.911297],"type":"Point"}
}
