{
  "type": "Feature",
  "properties": {
    "iso:country":"GB",
    "wof:name":"PO9 4RT",
    "wof:placetype":"postalcode"
},
  "geometry": {"coordinates":[-0.99404009501599,50.86774345448652],"type":"Point"}
}