{
  "type": "Feature",
  "properties": {
    "iso:country":"GB",
    "wof:name":"WA16 9NQ",
    "wof:placetype":"postalcode"
},
  "geometry": {"coordinates":[-2.35484765334191,53.24726959158542],"type":"Point"}
}