{
  "type": "Feature",
  "properties": {
    "iso:country":"GB",
    "wof:name":"OL2 6PZ",
    "wof:placetype":"postalcode"
},
  "geometry": {"coordinates":[-2.12041492455506,53.57012966887297],"type":"Point"}
}