{
  "type": "Feature",
  "properties": {
    "iso:country": "GB",
    "wof:name": "OL2 6PZ",
    "wof:placetype": "postalcode"
  },
  "geometry": {"coordinates":[-2.120292,53.570191],"type":"Point"}
}
