{
  "type": "Feature",
  "properties": {
    "iso:country":"GB",
    "wof:name":"CH43 0TF",
    "wof:placetype":"postalcode"
},
  "geometry": {"coordinates":[-3.05573876062485,53.36841194843554],"type":"Point"}
}