{
  "type": "Feature",
  "properties": {
    "iso:country":"GB",
    "wof:name":"TQ3 3AX",
    "wof:placetype":"postalcode"
},
  "geometry": {"coordinates":[-3.57092300798182,50.43831385455847],"type":"Point"}
}