{
  "type": "Feature",
  "properties": {
    "iso:country": "GB",
    "wof:name": "IP32 7LE",
    "wof:placetype": "postalcode"
  },
  "geometry": {"coordinates":[0.747648,52.247976],"type":"Point"}
}
