{
  "type": "Feature",
  "properties": {
    "iso:country":"GB",
    "wof:name":"IP32 7LE",
    "wof:placetype":"postalcode"
},
  "geometry": {"coordinates":[0.74764783417348,52.2479758960982],"type":"Point"}
}