{
  "type": "Feature",
  "properties": {
    "iso:country": "GB",
    "wof:name": "BD20 6JF",
    "wof:placetype": "postalcode"
  },
  "geometry": {"coordinates":[-1.918745,53.874158],"type":"Point"}
}
