{
  "type": "Feature",
  "properties": {
    "iso:country":"GB",
    "wof:name":"CT9 5TQ",
    "wof:placetype":"postalcode"
},
  "geometry": {"coordinates":[1.37431567765093,51.38422712878398],"type":"Point"}
}