{
  "type": "Feature",
  "properties": {
    "iso:country":"GB",
    "wof:name":"EX34 9BL",
    "wof:placetype":"postalcode"
},
  "geometry": {"coordinates":[-4.11626575867325,51.21056105311414],"type":"Point"}
}