{
  "type": "Feature",
  "properties": {
    "iso:country": "GB",
    "wof:name": "EX34 9BL",
    "wof:placetype": "postalcode"
  },
  "geometry": {"coordinates":[-4.116114,51.210483],"type":"Point"}
}
