{
  "type": "Feature",
  "properties": {
    "iso:country": "GB",
    "wof:name": "PO1 3BX",
    "wof:placetype": "postalcode"
  },
  "geometry": {"coordinates":[-1.102261,50.797853],"type":"Point"}
}
