{
  "type": "Feature",
  "properties": {
    "iso:country":"GB",
    "wof:name":"NW1 1NT",
    "wof:placetype":"postalcode"
},
  "geometry": {"coordinates":[-0.13489826845908,51.53321282414858],"type":"Point"}
}