{
  "type": "Feature",
  "properties": {
    "iso:country": "GB",
    "wof:name": "DE55 5RH",
    "wof:placetype": "postalcode"
  },
  "geometry": {"coordinates":[-1.345023,53.140633],"type":"Point"}
}
