{
  "type": "Feature",
  "properties": {
    "date:inception_lower": "1980-01-01",
    "date:inception_upper": "1980-01-01",
    "iso:country": "GB",
    "wof:name": "BS9 3JX",
    "wof:placetype": "postalcode"
  },
  "geometry": {"coordinates":[-2.621317,51.489166],"type":"Point"}
}
