{
  "type": "Feature",
  "properties": {
    "iso:country":"GB",
    "wof:name":"BS9 3JX",
    "wof:placetype":"postalcode"
},
  "geometry": {"coordinates":[-2.62131711301874,51.4891655117931],"type":"Point"}
}