{
  "type": "Feature",
  "properties": {
    "date:inception_lower": "2002-06-01",
    "date:inception_upper": "2002-06-01",
    "iso:country": "GB",
    "wof:name": "CM77 6SP",
    "wof:placetype": "postalcode"
  },
  "geometry": {"coordinates":[0.500236,51.86351],"type":"Point"}
}
