{
  "type": "Feature",
  "properties": {
    "iso:country":"GB",
    "wof:name":"CM77 6SP",
    "wof:placetype":"postalcode"
},
  "geometry": {"coordinates":[0.50023587040759,51.86350995015018],"type":"Point"}
}