{
  "type": "Feature",
  "properties": {
    "date:inception_lower": "1980-01-01",
    "date:inception_upper": "1980-01-01",
    "iso:country": "GB",
    "wof:name": "BB4 9NG",
    "wof:placetype": "postalcode"
  },
  "geometry": {"coordinates":[-2.250721,53.726852],"type":"Point"}
}
