{
  "type": "Feature",
  "properties": {
    "iso:country": "GB",
    "wof:name": "IP12 4UG",
    "wof:placetype": "postalcode"
  },
  "geometry": {"coordinates":[1.27571,52.069008],"type":"Point"}
}
