{
  "type": "Feature",
  "properties": {
    "iso:country":"GB",
    "wof:name":"IP12 4UG",
    "wof:placetype":"postalcode"
},
  "geometry": {"coordinates":[1.27598119924103,52.06892246222339],"type":"Point"}
}