{
  "type": "Feature",
  "properties": {
    "iso:country":"GB",
    "wof:name":"NR31 8BN",
    "wof:placetype":"postalcode"
},
  "geometry": {"coordinates":[1.72384336891005,52.58434323027662],"type":"Point"}
}