{
  "type": "Feature",
  "properties": {
    "iso:country":"GB",
    "wof:name":"CV37 0PP",
    "wof:placetype":"postalcode"
},
  "geometry": {"coordinates":[-1.65543548476255,52.25404171079675],"type":"Point"}
}