{
  "type": "Feature",
  "properties": {
    "date:inception_lower": "2009-09-01",
    "date:inception_upper": "2009-09-01",
    "iso:country": "GB",
    "wof:name": "MK10 9RT",
    "wof:placetype": "postalcode"
  },
  "geometry": {"coordinates":[-0.702153,52.03954],"type":"Point"}
}
