{
  "type": "Feature",
  "properties": {
    "iso:country":"GB",
    "wof:name":"MK10 9RT",
    "wof:placetype":"postalcode"
},
  "geometry": {"coordinates":[-0.70215312334087,52.03953978912321],"type":"Point"}
}