{
  "type": "Feature",
  "properties": {
    "iso:country":"GB",
    "wof:name":"CM2 6EU",
    "wof:placetype":"postalcode"
},
  "geometry": {"coordinates":[0.48812059407116,51.73205553877533],"type":"Point"}
}