{
  "type": "Feature",
  "properties": {
    "iso:country": "GB",
    "wof:name": "ST18 9AG",
    "wof:placetype": "postalcode"
  },
  "geometry": {"coordinates":[-2.116171,52.757571],"type":"Point"}
}
