{
  "type": "Feature",
  "properties": {
    "iso:country":"GB",
    "wof:name":"ST18 9AG",
    "wof:placetype":"postalcode"
},
  "geometry": {"coordinates":[-2.11617146829168,52.75757138637874],"type":"Point"}
}