{
  "type": "Feature",
  "properties": {
    "date:inception_lower": "1980-01-01",
    "date:inception_upper": "1980-01-01",
    "iso:country": "GB",
    "wof:name": "ST18 9AG",
    "wof:placetype": "postalcode"
  },
  "geometry": {"coordinates":[-2.116171,52.757571],"type":"Point"}
}
