{
  "type": "Feature",
  "properties": {
    "iso:country": "GB",
    "wof:name": "TF10 7RF",
    "wof:placetype": "postalcode"
  },
  "geometry": {"coordinates":[-2.37018,52.772225],"type":"Point"}
}
