{
  "type": "Feature",
  "properties": {
    "iso:country":"GB",
    "wof:name":"SG4 0FR",
    "wof:placetype":"postalcode"
},
  "geometry": {"coordinates":[-0.26740876929303,51.95822124899644],"type":"Point"}
}