{
  "type": "Feature",
  "properties": {
    "date:inception_lower": "1998-12-01",
    "date:inception_upper": "1998-12-01",
    "iso:country": "GB",
    "wof:name": "SG4 0FR",
    "wof:placetype": "postalcode"
  },
  "geometry": {"coordinates":[-0.267409,51.958221],"type":"Point"}
}
