{
  "type": "Feature",
  "properties": {
    "iso:country":"GB",
    "wof:name":"DN38 6BB",
    "wof:placetype":"postalcode"
},
  "geometry": {"coordinates":[-0.38162423595841,53.53616974184716],"type":"Point"}
}