{
  "type": "Feature",
  "properties": {
    "date:inception_lower": "1991-01-01",
    "date:inception_upper": "1991-01-01",
    "iso:country": "GB",
    "wof:name": "TQ12 6FE",
    "wof:placetype": "postalcode"
  },
  "geometry": {"coordinates":[-3.624792,50.522655],"type":"Point"}
}
