{
  "type": "Feature",
  "properties": {
    "iso:country": "GB",
    "wof:name": "CT3 2JT",
    "wof:placetype": "postalcode"
  },
  "geometry": {"coordinates":[1.245059,51.283901],"type":"Point"}
}
