{
  "type": "Feature",
  "properties": {
    "iso:country":"GB",
    "wof:name":"CT3 2JT",
    "wof:placetype":"postalcode"
},
  "geometry": {"coordinates":[1.24505893039339,51.28390053904243],"type":"Point"}
}