{
  "type": "Feature",
  "properties": {
    "iso:country":"GB",
    "wof:name":"CH47 7AZ",
    "wof:placetype":"postalcode"
},
  "geometry": {"coordinates":[-3.15256543824003,53.40540508606716],"type":"Point"}
}