{
  "type": "Feature",
  "properties": {
    "iso:country":"GB",
    "wof:name":"TR2 5JP",
    "wof:placetype":"postalcode"
},
  "geometry": {"coordinates":[-4.93963090873632,50.22300650463294],"type":"Point"}
}