{
  "type": "Feature",
  "properties": {
    "iso:country": "GB",
    "wof:name": "KT20 6SB",
    "wof:placetype": "postalcode"
  },
  "geometry": {"coordinates":[-0.216558,51.279076],"type":"Point"}
}
