{
  "type": "Feature",
  "properties": {
    "date:inception_lower": "2023-05-01",
    "date:inception_upper": "2023-05-01",
    "iso:country": "GB",
    "wof:name": "NG2 3JL",
    "wof:placetype": "postalcode"
  },
  "geometry": {"coordinates":[-1.139579,52.9485],"type":"Point"}
}
