{
  "type": "Feature",
  "properties": {
    "iso:country":"GB",
    "wof:name":"AB11 6JL",
    "wof:placetype":"postalcode"
},
  "geometry": {"coordinates":[-2.10116683334631,57.14479657872222],"type":"Point"}
}