{
  "type": "Feature",
  "properties": {
    "iso:country":"GB",
    "wof:name":"BA2 6PY",
    "wof:placetype":"postalcode"
},
  "geometry": {"coordinates":[-2.35712250511098,51.38739523480651],"type":"Point"}
}