{
  "type": "Feature",
  "properties": {
    "date:inception_lower":"1987-10-01",
    "date:inception_upper":"1987-10-31",
    "iso:country":"GB",
    "wof:name":"BA2 6PY",
    "wof:placetype":"postalcode"
},
  "geometry": {"coordinates":[-2.357122,51.387395],"type":"Point"}
}