{
  "type": "Feature",
  "properties": {
    "iso:country":"GB",
    "wof:name":"B69 2HH",
    "wof:placetype":"postalcode"
},
  "geometry": {"coordinates":[-2.03484322858242,52.50556038752381],"type":"Point"}
}