{
  "type": "Feature",
  "properties": {
    "iso:country": "GB",
    "wof:name": "S40 4PQ",
    "wof:placetype": "postalcode"
  },
  "geometry": {"coordinates":[-1.463696,53.247061],"type":"Point"}
}
