{
  "type": "Feature",
  "properties": {
    "iso:country":"GB",
    "wof:name":"KA24 4HW",
    "wof:placetype":"postalcode"
},
  "geometry": {"coordinates":[-4.69072390358457,55.71439692517311],"type":"Point"}
}