{
  "type": "Feature",
  "properties": {
    "date:inception_lower":"1980-01-01",
    "date:inception_upper":"1980-01-31",
    "iso:country":"GB",
    "wof:name":"KA24 4HW",
    "wof:placetype":"postalcode"
},
  "geometry": {"coordinates":[-4.690724,55.714397],"type":"Point"}
}