{
  "type": "Feature",
  "properties": {
    "date:inception_lower": "1980-01-01",
    "date:inception_upper": "1980-01-01",
    "iso:country": "GB",
    "wof:name": "CT12 4AD",
    "wof:placetype": "postalcode"
  },
  "geometry": {"coordinates":[1.314313,51.334499],"type":"Point"}
}
