{
  "type": "Feature",
  "properties": {
    "iso:country": "GB",
    "wof:name": "DA5 2EW",
    "wof:placetype": "postalcode"
  },
  "geometry": {"coordinates":[0.16484,51.42442],"type":"Point"}
}
