{
  "type": "Feature",
  "properties": {
    "iso:country":"GB",
    "wof:name":"DA5 2EW",
    "wof:placetype":"postalcode"
},
  "geometry": {"coordinates":[0.1648403117378,51.42442021243399],"type":"Point"}
}