{
  "type": "Feature",
  "properties": {
    "iso:country": "GB",
    "wof:name": "KY16 9SJ",
    "wof:placetype": "postalcode"
  },
  "geometry": {"coordinates":[-2.87076,56.346999],"type":"Point"}
}
