{
  "type": "Feature",
  "properties": {
    "iso:country":"GB",
    "wof:name":"KY16 9SJ",
    "wof:placetype":"postalcode"
},
  "geometry": {"coordinates":[-2.87076033893177,56.34699916074032],"type":"Point"}
}