{
  "type": "Feature",
  "properties": {
    "date:inception_lower": "1980-01-01",
    "date:inception_upper": "1980-01-01",
    "iso:country": "GB",
    "wof:name": "RG7 2EE",
    "wof:placetype": "postalcode"
  },
  "geometry": {"coordinates":[-1.026358,51.348857],"type":"Point"}
}
