{
  "type": "Feature",
  "properties": {
    "iso:country":"GB",
    "wof:name":"BS35 5RA",
    "wof:placetype":"postalcode"
},
  "geometry": {"coordinates":[-2.62262188350087,51.54156139761537],"type":"Point"}
}