{
  "type": "Feature",
  "properties": {
    "iso:country": "GB",
    "wof:name": "BS35 5RA",
    "wof:placetype": "postalcode"
  },
  "geometry": {"coordinates":[-2.622203,51.541239],"type":"Point"}
}
