{
  "type": "Feature",
  "properties": {
    "iso:country": "GB",
    "wof:name": "PE20 1FA",
    "wof:placetype": "postalcode"
  },
  "geometry": {"coordinates":[-0.059871,52.934676],"type":"Point"}
}
