{
  "type": "Feature",
  "properties": {
    "date:inception_lower": "2003-09-01",
    "date:inception_upper": "2003-09-01",
    "iso:country": "GB",
    "wof:name": "E3 5PE",
    "wof:placetype": "postalcode"
  },
  "geometry": {"coordinates":[-0.034072,51.535838],"type":"Point"}
}
