{
  "type": "Feature",
  "properties": {
    "date:inception_lower": "2002-11-01",
    "date:inception_upper": "2002-11-01",
    "iso:country": "GB",
    "wof:name": "TR6 0ZN",
    "wof:placetype": "postalcode"
  },
  "geometry": {"coordinates":[-5.153915,50.344709],"type":"Point"}
}
