{
  "type": "Feature",
  "properties": {
    "iso:country":"GB",
    "wof:name":"YO8 8EJ",
    "wof:placetype":"postalcode"
},
  "geometry": {"coordinates":[-1.02387381716646,53.75320796644632],"type":"Point"}
}