{
  "type": "Feature",
  "properties": {
    "iso:country":"GB",
    "wof:name":"NE34 0PQ",
    "wof:placetype":"postalcode"
},
  "geometry": {"coordinates":[-1.43030196916882,54.97426452952937],"type":"Point"}
}