{
  "type": "Feature",
  "properties": {
    "iso:country": "GB",
    "wof:name": "NE34 0PQ",
    "wof:placetype": "postalcode"
  },
  "geometry": {"coordinates":[-1.430302,54.974265],"type":"Point"}
}
