{
  "type": "Feature",
  "properties": {
    "date:inception_lower": "1980-01-01",
    "date:inception_upper": "1980-01-01",
    "iso:country": "GB",
    "wof:name": "NE34 0PQ",
    "wof:placetype": "postalcode"
  },
  "geometry": {"coordinates":[-1.430302,54.974265],"type":"Point"}
}
