{
  "type": "Feature",
  "properties": {
    "iso:country":"GB",
    "wof:name":"FK2 7JA",
    "wof:placetype":"postalcode"
},
  "geometry": {"coordinates":[-3.7918346700916,56.0138001801308],"type":"Point"}
}