{
  "type": "Feature",
  "properties": {
    "date:inception_lower": "2010-09-01",
    "date:inception_upper": "2010-09-01",
    "iso:country": "GB",
    "wof:name": "M40 7BZ",
    "wof:placetype": "postalcode"
  },
  "geometry": {"coordinates":[-2.210389,53.486539],"type":"Point"}
}
