{
  "type": "Feature",
  "properties": {
    "iso:country":"GB",
    "wof:name":"M40 7BZ",
    "wof:placetype":"postalcode"
},
  "geometry": {"coordinates":[-2.21038874035054,53.48653897542182],"type":"Point"}
}