{
  "type": "Feature",
  "properties": {
    "iso:country": "GB",
    "wof:name": "M40 7BZ",
    "wof:placetype": "postalcode"
  },
  "geometry": {"coordinates":[-2.210389,53.486539],"type":"Point"}
}
