{
  "type": "Feature",
  "properties": {
    "iso:country":"GB",
    "wof:name":"PO10 8AY",
    "wof:placetype":"postalcode"
},
  "geometry": {"coordinates":[-0.92480560214959,50.84607424124879],"type":"Point"}
}