{
  "type": "Feature",
  "properties": {
    "iso:country":"GB",
    "wof:name":"GL4 4XU",
    "wof:placetype":"postalcode"
},
  "geometry": {"coordinates":[-2.20956767803897,51.8519278134888],"type":"Point"}
}