{
  "type": "Feature",
  "properties": {
    "date:inception_lower": "1995-12-01",
    "date:inception_upper": "1995-12-01",
    "iso:country": "GB",
    "wof:name": "GL4 4XU",
    "wof:placetype": "postalcode"
  },
  "geometry": {"coordinates":[-2.209568,51.851928],"type":"Point"}
}
