{
  "type": "Feature",
  "properties": {
    "iso:country": "GB",
    "wof:name": "NN18 0AB",
    "wof:placetype": "postalcode"
  },
  "geometry": {"coordinates":[-0.720557,52.491001],"type":"Point"}
}
