{
  "type": "Feature",
  "properties": {
    "iso:country":"GB",
    "wof:name":"HA6 3JB",
    "wof:placetype":"postalcode"
},
  "geometry": {"coordinates":[-0.41383616044467,51.61971060988554],"type":"Point"}
}