{
  "type": "Feature",
  "properties": {
    "date:inception_lower": "1980-01-01",
    "date:inception_upper": "1980-01-01",
    "iso:country": "GB",
    "wof:name": "HA6 3JB",
    "wof:placetype": "postalcode"
  },
  "geometry": {"coordinates":[-0.413836,51.619711],"type":"Point"}
}
