{
  "type": "Feature",
  "properties": {
    "iso:country":"GB",
    "wof:name":"LD3 8RU",
    "wof:placetype":"postalcode"
},
  "geometry": {"coordinates":[-3.56751328590432,51.94358746932861],"type":"Point"}
}