{
  "type": "Feature",
  "properties": {
    "iso:country": "GB",
    "wof:name": "LD3 8RU",
    "wof:placetype": "postalcode"
  },
  "geometry": {"coordinates":[-3.567513,51.943587],"type":"Point"}
}
