{
  "type": "Feature",
  "properties": {
    "iso:country":"GB",
    "wof:name":"OX15 0TX",
    "wof:placetype":"postalcode"
},
  "geometry": {"coordinates":[-1.32186182257723,51.98408247274592],"type":"Point"}
}