{
  "type": "Feature",
  "properties": {
    "iso:country":"GB",
    "wof:name":"SA5 7NB",
    "wof:placetype":"postalcode"
},
  "geometry": {"coordinates":[-3.97372806734448,51.70713089112838],"type":"Point"}
}