{
  "type": "Feature",
  "properties": {
    "iso:country":"GB",
    "wof:name":"YO61 4AA",
    "wof:placetype":"postalcode"
},
  "geometry": {"coordinates":[-1.17993049348962,54.18677949875102],"type":"Point"}
}