{
  "type": "Feature",
  "properties": {
    "iso:country": "GB",
    "wof:name": "YO61 4AA",
    "wof:placetype": "postalcode"
  },
  "geometry": {"coordinates":[-1.17993,54.186779],"type":"Point"}
}
