{
  "type": "Feature",
  "properties": {
    "date:inception_lower": "1998-06-01",
    "date:inception_upper": "1998-06-01",
    "iso:country": "GB",
    "wof:name": "YO61 4AA",
    "wof:placetype": "postalcode"
  },
  "geometry": {"coordinates":[-1.179968,54.186938],"type":"Point"}
}
