{
  "type": "Feature",
  "properties": {
    "iso:country":"GB",
    "wof:name":"DE6 1QF",
    "wof:placetype":"postalcode"
},
  "geometry": {"coordinates":[-1.73425284597801,53.10956788648685],"type":"Point"}
}