{
  "type": "Feature",
  "properties": {
    "date:inception_lower": "1980-01-01",
    "date:inception_upper": "1980-01-01",
    "iso:country": "GB",
    "wof:name": "DE6 1QF",
    "wof:placetype": "postalcode"
  },
  "geometry": {"coordinates":[-1.734253,53.109568],"type":"Point"}
}
