{
  "type": "Feature",
  "properties": {
    "date:inception_lower": "1980-01-01",
    "date:inception_upper": "1980-01-01",
    "iso:country": "GB",
    "wof:name": "TN24 0RF",
    "wof:placetype": "postalcode"
  },
  "geometry": {"coordinates":[0.892739,51.147793],"type":"Point"}
}
