{
  "type": "Feature",
  "properties": {
    "date:inception_lower": "2008-04-01",
    "date:inception_upper": "2008-04-01",
    "iso:country": "GB",
    "wof:name": "SE18 6AH",
    "wof:placetype": "postalcode"
  },
  "geometry": {"coordinates":[0.068071,51.485818],"type":"Point"}
}
