{
  "type": "Feature",
  "properties": {
    "iso:country":"GB",
    "wof:name":"SE18 6AH",
    "wof:placetype":"postalcode"
},
  "geometry": {"coordinates":[0.06797092912198,51.48580112441751],"type":"Point"}
}