{
  "type": "Feature",
  "properties": {
    "iso:country":"GB",
    "wof:name":"LN4 2AR",
    "wof:placetype":"postalcode"
},
  "geometry": {"coordinates":[-0.48698253937501,53.14528152906873],"type":"Point"}
}