{
  "type": "Feature",
  "properties": {
    "date:inception_lower": "1980-01-01",
    "date:inception_upper": "1980-01-01",
    "iso:country": "GB",
    "wof:name": "LN4 2AR",
    "wof:placetype": "postalcode"
  },
  "geometry": {"coordinates":[-0.493762,53.145057],"type":"Point"}
}
