{
  "type": "Feature",
  "properties": {
    "iso:country":"GB",
    "wof:name":"DA12 3LB",
    "wof:placetype":"postalcode"
},
  "geometry": {"coordinates":[0.42828957432418,51.40332052563217],"type":"Point"}
}