{
  "type": "Feature",
  "properties": {
    "iso:country":"GB",
    "wof:name":"RG28 7EP",
    "wof:placetype":"postalcode"
},
  "geometry": {"coordinates":[-1.33680196560633,51.2365210498914],"type":"Point"}
}