{
  "type": "Feature",
  "properties": {
    "date:inception_lower": "1980-01-01",
    "date:inception_upper": "1980-01-01",
    "iso:country": "GB",
    "wof:name": "PO10 8NQ",
    "wof:placetype": "postalcode"
  },
  "geometry": {"coordinates":[-0.906223,50.850461],"type":"Point"}
}
