{
  "type": "Feature",
  "properties": {
    "iso:country": "GB",
    "wof:name": "L15 2JB",
    "wof:placetype": "postalcode"
  },
  "geometry": {"coordinates":[-2.940516,53.397366],"type":"Point"}
}
