{
  "type": "Feature",
  "properties": {
    "iso:country":"GB",
    "wof:name":"LU5 4SL",
    "wof:placetype":"postalcode"
},
  "geometry": {"coordinates":[-0.49160135909514,51.8934745018656],"type":"Point"}
}