{
  "type": "Feature",
  "properties": {
    "date:inception_lower": "2001-06-01",
    "date:inception_upper": "2001-06-01",
    "iso:country": "GB",
    "wof:name": "LU5 4SL",
    "wof:placetype": "postalcode"
  },
  "geometry": {"coordinates":[-0.491601,51.893474],"type":"Point"}
}
