{
  "type": "Feature",
  "properties": {
    "date:inception_lower": "1985-04-01",
    "date:inception_upper": "1985-04-01",
    "iso:country": "GB",
    "wof:name": "CR0 8XX",
    "wof:placetype": "postalcode"
  },
  "geometry": {"coordinates":[-0.052027,51.380924],"type":"Point"}
}
