{
  "type": "Feature",
  "properties": {
    "iso:country":"GB",
    "wof:name":"CR0 8XX",
    "wof:placetype":"postalcode"
},
  "geometry": {"coordinates":[-0.05202735748771,51.38092366325961],"type":"Point"}
}