{
  "type": "Feature",
  "properties": {
    "iso:country":"GB",
    "wof:name":"RH14 0BW",
    "wof:placetype":"postalcode"
},
  "geometry": {"coordinates":[-0.5071432711037,51.02362268469162],"type":"Point"}
}