{
  "type": "Feature",
  "properties": {
    "iso:country":"GB",
    "wof:name":"DT11 8HQ",
    "wof:placetype":"postalcode"
},
  "geometry": {"coordinates":[-2.22697277313454,50.90545957817965],"type":"Point"}
}