{
  "type": "Feature",
  "properties": {
    "iso:country":"GB",
    "wof:name":"SE12 0AR",
    "wof:placetype":"postalcode"
},
  "geometry": {"coordinates":[0.01715093401192,51.44425857860998],"type":"Point"}
}