{
  "type": "Feature",
  "properties": {
    "date:inception_lower": "1982-03-01",
    "date:inception_upper": "1982-03-01",
    "iso:country": "GB",
    "wof:name": "SE12 0AR",
    "wof:placetype": "postalcode"
  },
  "geometry": {"coordinates":[0.017151,51.444259],"type":"Point"}
}
