{
  "type": "Feature",
  "properties": {
    "date:inception_lower":"1986-07-01",
    "date:inception_upper":"1986-07-31",
    "iso:country":"GB",
    "wof:name":"CV10 0UJ",
    "wof:placetype":"postalcode"
},
  "geometry": {"coordinates":[-1.520269,52.552169],"type":"Point"}
}