{
  "type": "Feature",
  "properties": {
    "iso:country":"GB",
    "wof:name":"CV10 0UJ",
    "wof:placetype":"postalcode"
},
  "geometry": {"coordinates":[-1.52026854729556,52.55216921139958],"type":"Point"}
}