{
  "type": "Feature",
  "properties": {
    "iso:country": "GB",
    "wof:name": "CV10 0UJ",
    "wof:placetype": "postalcode"
  },
  "geometry": {"coordinates":[-1.520269,52.552169],"type":"Point"}
}
