{
  "type": "Feature",
  "properties": {
    "iso:country":"GB",
    "wof:name":"TA3 6SS",
    "wof:placetype":"postalcode"
},
  "geometry": {"coordinates":[-2.96128965028036,50.98772611065124],"type":"Point"}
}