{
  "type": "Feature",
  "properties": {
    "date:inception_lower": "1980-01-01",
    "date:inception_upper": "1980-01-01",
    "iso:country": "GB",
    "wof:name": "TA3 6SS",
    "wof:placetype": "postalcode"
  },
  "geometry": {"coordinates":[-2.96129,50.987726],"type":"Point"}
}
