{
  "type": "Feature",
  "properties": {
    "date:inception_lower": "1980-01-01",
    "date:inception_upper": "1980-01-01",
    "iso:country": "GB",
    "wof:name": "IP30 0BD",
    "wof:placetype": "postalcode"
  },
  "geometry": {"coordinates":[0.815545,52.206823],"type":"Point"}
}
