{
  "type": "Feature",
  "properties": {
    "iso:country":"GB",
    "wof:name":"HG4 3EX",
    "wof:placetype":"postalcode"
},
  "geometry": {"coordinates":[-1.64505823931148,54.11578098613023],"type":"Point"}
}