{
  "type": "Feature",
  "properties": {
    "date:inception_lower": "2019-06-01",
    "date:inception_upper": "2019-06-01",
    "iso:country": "GB",
    "wof:name": "WF1 2GH",
    "wof:placetype": "postalcode"
  },
  "geometry": {"coordinates":[-1.510525,53.696931],"type":"Point"}
}
