{
  "type": "Feature",
  "properties": {
    "date:inception_lower": "1980-01-01",
    "date:inception_upper": "1980-01-01",
    "iso:country": "GB",
    "wof:name": "SK6 7QP",
    "wof:placetype": "postalcode"
  },
  "geometry": {"coordinates":[-2.071546,53.388378],"type":"Point"}
}
