{
  "type": "Feature",
  "properties": {
    "iso:country":"GB",
    "wof:name":"CW2 6LU",
    "wof:placetype":"postalcode"
},
  "geometry": {"coordinates":[-2.44366724757773,53.08164644027544],"type":"Point"}
}