{
  "type": "Feature",
  "properties": {
    "iso:country": "GB",
    "wof:name": "DN21 2NF",
    "wof:placetype": "postalcode"
  },
  "geometry": {"coordinates":[-0.779278,53.400526],"type":"Point"}
}
