{
  "type": "Feature",
  "properties": {
    "iso:country":"GB",
    "wof:name":"DN21 2NF",
    "wof:placetype":"postalcode"
},
  "geometry": {"coordinates":[-0.77927802246394,53.40052605501255],"type":"Point"}
}