{
  "type": "Feature",
  "properties": {
    "date:inception_lower":"1990-02-01",
    "date:inception_upper":"1990-02-28",
    "iso:country":"GB",
    "wof:name":"CV5 6BN",
    "wof:placetype":"postalcode"
},
  "geometry": {"coordinates":[-1.549761,52.398133],"type":"Point"}
}