{
  "type": "Feature",
  "properties": {
    "iso:country": "GB",
    "wof:name": "LL21 9DW",
    "wof:placetype": "postalcode"
  },
  "geometry": {"coordinates":[-3.379335,53.008744],"type":"Point"}
}
