{
  "type": "Feature",
  "properties": {
    "iso:country":"GB",
    "wof:name":"LL21 9DW",
    "wof:placetype":"postalcode"
},
  "geometry": {"coordinates":[-3.3793347771449,53.00874398636483],"type":"Point"}
}