{
  "type": "Feature",
  "properties": {
    "date:inception_lower":"1980-01-01",
    "date:inception_upper":"1980-01-31",
    "iso:country":"GB",
    "wof:name":"LL21 9DW",
    "wof:placetype":"postalcode"
},
  "geometry": {"coordinates":[-3.379335,53.008744],"type":"Point"}
}