{
  "type": "Feature",
  "properties": {
    "iso:country":"GB",
    "wof:name":"SG2 0DF",
    "wof:placetype":"postalcode"
},
  "geometry": {"coordinates":[-0.17244774346371,51.90796853385415],"type":"Point"}
}