{
  "type": "Feature",
  "properties": {
    "iso:country": "GB",
    "wof:name": "NR33 7PQ",
    "wof:placetype": "postalcode"
  },
  "geometry": {"coordinates":[1.720912,52.432585],"type":"Point"}
}
