{
  "type": "Feature",
  "properties": {
    "iso:country":"GB",
    "wof:name":"DN11 8BY",
    "wof:placetype":"postalcode"
},
  "geometry": {"coordinates":[-1.04258641460711,53.41904420815683],"type":"Point"}
}