{
  "type": "Feature",
  "properties": {
    "iso:country":"GB",
    "wof:name":"CO9 4BP",
    "wof:placetype":"postalcode"
},
  "geometry": {"coordinates":[0.477417463201,52.04011651974135],"type":"Point"}
}