{
  "type": "Feature",
  "properties": {
    "date:inception_lower":"1980-01-01",
    "date:inception_upper":"1980-01-31",
    "iso:country":"GB",
    "wof:name":"CO9 4BP",
    "wof:placetype":"postalcode"
},
  "geometry": {"coordinates":[0.477418,52.040117],"type":"Point"}
}