{
  "type": "Feature",
  "properties": {
    "date:inception_lower":"1983-05-01",
    "date:inception_upper":"1983-05-31",
    "iso:country":"GB",
    "wof:name":"EH15 1TW",
    "wof:placetype":"postalcode"
},
  "geometry": {"coordinates":[-3.11901,55.957352],"type":"Point"}
}