{
  "type": "Feature",
  "properties": {
    "date:inception_lower": "2005-02-01",
    "date:inception_upper": "2005-02-01",
    "iso:country": "GB",
    "wof:name": "SS4 9SQ",
    "wof:placetype": "postalcode"
  },
  "geometry": {"coordinates":[0.707466,51.581878],"type":"Point"}
}
