{
  "type": "Feature",
  "properties": {
    "iso:country":"GB",
    "wof:name":"PO22 6JR",
    "wof:placetype":"postalcode"
},
  "geometry": {"coordinates":[-0.59789836950102,50.79456390677615],"type":"Point"}
}