{
  "type": "Feature",
  "properties": {
    "iso:country":"GB",
    "wof:name":"CO2 8GN",
    "wof:placetype":"postalcode"
},
  "geometry": {"coordinates":[0.93046920242224,51.87925099228138],"type":"Point"}
}