{
  "type": "Feature",
  "properties": {
    "date:inception_lower":"2007-10-01",
    "date:inception_upper":"2007-10-31",
    "iso:country":"GB",
    "wof:name":"CO2 8GN",
    "wof:placetype":"postalcode"
},
  "geometry": {"coordinates":[0.930469,51.879251],"type":"Point"}
}