{
  "type": "Feature",
  "properties": {
    "date:inception_lower": "1980-01-01",
    "date:inception_upper": "1980-01-01",
    "iso:country": "GB",
    "wof:name": "BN5 9UA",
    "wof:placetype": "postalcode"
  },
  "geometry": {"coordinates":[-0.27877,50.928846],"type":"Point"}
}
