{
  "type": "Feature",
  "properties": {
    "date:inception_lower": "1980-01-01",
    "date:inception_upper": "1980-01-01",
    "iso:country": "GB",
    "wof:name": "LS1 7BT",
    "wof:placetype": "postalcode"
  },
  "geometry": {"coordinates":[-1.540848,53.795301],"type":"Point"}
}
