{
  "type": "Feature",
  "properties": {
    "iso:country":"GB",
    "wof:name":"LS1 7BT",
    "wof:placetype":"postalcode"
},
  "geometry": {"coordinates":[-1.54089455345868,53.79524737316459],"type":"Point"}
}