{
  "type": "Feature",
  "properties": {
    "iso:country":"GB",
    "wof:name":"LL65 3LF",
    "wof:placetype":"postalcode"
},
  "geometry": {"coordinates":[-4.54731774646158,53.2555882312916],"type":"Point"}
}