{
  "type": "Feature",
  "properties": {
    "iso:country":"GB",
    "wof:name":"LS10 3LL",
    "wof:placetype":"postalcode"
},
  "geometry": {"coordinates":[-1.52240817221586,53.7547737846039],"type":"Point"}
}