{
  "type": "Feature",
  "properties": {
    "date:inception_lower":"1980-01-01",
    "date:inception_upper":"1980-01-31",
    "iso:country":"GB",
    "wof:name":"SL1 5PB",
    "wof:placetype":"postalcode"
},
  "geometry": {"coordinates":[-0.653758,51.519452],"type":"Point"}
}