{
  "type": "Feature",
  "properties": {
    "iso:country":"GB",
    "wof:name":"SL1 5PB",
    "wof:placetype":"postalcode"
},
  "geometry": {"coordinates":[-0.65375814678801,51.51945248155896],"type":"Point"}
}