{
  "type": "Feature",
  "properties": {
    "iso:country": "GB",
    "wof:name": "DL10 6BQ",
    "wof:placetype": "postalcode"
  },
  "geometry": {"coordinates":[-1.580858,54.374384],"type":"Point"}
}
