{
  "type": "Feature",
  "properties": {
    "iso:country":"GB",
    "wof:name":"DL10 6BQ",
    "wof:placetype":"postalcode"
},
  "geometry": {"coordinates":[-1.5808578223023,54.37438364699729],"type":"Point"}
}