{
  "type": "Feature",
  "properties": {
    "date:inception_lower":"1980-01-01",
    "date:inception_upper":"1980-01-31",
    "iso:country":"GB",
    "wof:name":"TA7 8NW",
    "wof:placetype":"postalcode"
},
  "geometry": {"coordinates":[-2.891994,51.196421],"type":"Point"}
}