{
  "type": "Feature",
  "properties": {
    "iso:country": "GB",
    "wof:name": "TA7 8NW",
    "wof:placetype": "postalcode"
  },
  "geometry": {"coordinates":[-2.891994,51.196421],"type":"Point"}
}
