{
  "type": "Feature",
  "properties": {
    "iso:country":"GB",
    "wof:name":"TA7 8NW",
    "wof:placetype":"postalcode"
},
  "geometry": {"coordinates":[-2.89199401430237,51.19642123774355],"type":"Point"}
}