{
  "type": "Feature",
  "properties": {
    "iso:country": "GB",
    "wof:name": "PE8 6BH",
    "wof:placetype": "postalcode"
  },
  "geometry": {"coordinates":[-0.44392,52.610184],"type":"Point"}
}
