{
  "type": "Feature",
  "properties": {
    "date:inception_lower": "1983-01-01",
    "date:inception_upper": "1983-01-01",
    "iso:country": "GB",
    "wof:name": "PE8 6BH",
    "wof:placetype": "postalcode"
  },
  "geometry": {"coordinates":[-0.44392,52.610184],"type":"Point"}
}
