{
  "type": "Feature",
  "properties": {
    "iso:country":"GB",
    "wof:name":"PE8 6BH",
    "wof:placetype":"postalcode"
},
  "geometry": {"coordinates":[-0.44392023999129,52.61018444215234],"type":"Point"}
}