{
  "type": "Feature",
  "properties": {
    "iso:country":"GB",
    "wof:name":"PL5 4DH",
    "wof:placetype":"postalcode"
},
  "geometry": {"coordinates":[-4.14137870250332,50.41651907100029],"type":"Point"}
}