{
  "type": "Feature",
  "properties": {
    "iso:country":"GB",
    "wof:name":"RH18 5EE",
    "wof:placetype":"postalcode"
},
  "geometry": {"coordinates":[0.03541627364634,51.1024230568242],"type":"Point"}
}