{
  "type": "Feature",
  "properties": {
    "iso:country":"GB",
    "wof:name":"SW1E 6AA",
    "wof:placetype":"postalcode"
},
  "geometry": {"coordinates":[-0.1371101642496,51.49809626046756],"type":"Point"}
}