{
  "type": "Feature",
  "properties": {
    "iso:country": "GB",
    "wof:name": "BH25 5XS",
    "wof:placetype": "postalcode"
  },
  "geometry": {"coordinates":[-1.637185,50.760374],"type":"Point"}
}
