{
  "type": "Feature",
  "properties": {
    "date:inception_lower":"1986-04-01",
    "date:inception_upper":"1986-04-30",
    "iso:country":"GB",
    "wof:name":"BH25 5XS",
    "wof:placetype":"postalcode"
},
  "geometry": {"coordinates":[-1.637185,50.760374],"type":"Point"}
}