{
  "type": "Feature",
  "properties": {
    "iso:country":"GB",
    "wof:name":"BH25 5XS",
    "wof:placetype":"postalcode"
},
  "geometry": {"coordinates":[-1.63683841444901,50.76034596535748],"type":"Point"}
}