{
  "type": "Feature",
  "properties": {
    "iso:country":"GB",
    "wof:name":"BH23 7JW",
    "wof:placetype":"postalcode"
},
  "geometry": {"coordinates":[-1.76279398580509,50.74928518258857],"type":"Point"}
}