{
  "type": "Feature",
  "properties": {
    "iso:country":"GB",
    "wof:name":"BS36 1AW",
    "wof:placetype":"postalcode"
},
  "geometry": {"coordinates":[-2.48543477732587,51.51575649376363],"type":"Point"}
}