{
  "type": "Feature",
  "properties": {
    "iso:country":"GB",
    "wof:name":"PE25 1EX",
    "wof:placetype":"postalcode"
},
  "geometry": {"coordinates":[0.34278833061261,53.16501295996505],"type":"Point"}
}