{
  "type": "Feature",
  "properties": {
    "date:inception_lower":"2015-08-01",
    "date:inception_upper":"2015-08-31",
    "iso:country":"GB",
    "wof:name":"FK2 8AD",
    "wof:placetype":"postalcode"
},
  "geometry": {"coordinates":[-3.811057,56.041794],"type":"Point"}
}