{
  "type": "Feature",
  "properties": {
    "iso:country": "GB",
    "wof:name": "FK2 8AD",
    "wof:placetype": "postalcode"
  },
  "geometry": {"coordinates":[-3.810946,56.041814],"type":"Point"}
}
