{
  "type": "Feature",
  "properties": {
    "iso:country": "GB",
    "wof:name": "CV2 4LG",
    "wof:placetype": "postalcode"
  },
  "geometry": {"coordinates":[-1.482118,52.412618],"type":"Point"}
}
