{
  "type": "Feature",
  "properties": {
    "date:inception_lower": "1999-12-01",
    "date:inception_upper": "1999-12-01",
    "iso:country": "GB",
    "wof:name": "CV2 4LG",
    "wof:placetype": "postalcode"
  },
  "geometry": {"coordinates":[-1.482118,52.412618],"type":"Point"}
}
