{
  "type": "Feature",
  "properties": {
    "date:inception_lower":"1981-09-01",
    "date:inception_upper":"1981-09-30",
    "iso:country":"GB",
    "wof:name":"SY22 5LA",
    "wof:placetype":"postalcode"
},
  "geometry": {"coordinates":[-3.267815,52.759544],"type":"Point"}
}