{
  "type": "Feature",
  "properties": {
    "iso:country":"GB",
    "wof:name":"SY22 5LA",
    "wof:placetype":"postalcode"
},
  "geometry": {"coordinates":[-3.26781499605203,52.75954389745545],"type":"Point"}
}