{
  "type": "Feature",
  "properties": {
    "iso:country":"GB",
    "wof:name":"SN1 1BB",
    "wof:placetype":"postalcode"
},
  "geometry": {"coordinates":[-1.78435943168187,51.5619079488897],"type":"Point"}
}