{
  "type": "Feature",
  "properties": {
    "date:inception_lower":"1994-05-01",
    "date:inception_upper":"1994-05-31",
    "iso:country":"GB",
    "wof:name":"M41 5SW",
    "wof:placetype":"postalcode"
},
  "geometry": {"coordinates":[-2.365419,53.453411],"type":"Point"}
}