{
  "type": "Feature",
  "properties": {
    "iso:country": "GB",
    "wof:name": "SE9 4SH",
    "wof:placetype": "postalcode"
  },
  "geometry": {"coordinates":[0.04518,51.435158],"type":"Point"}
}
