{
  "type": "Feature",
  "properties": {
    "iso:country":"GB",
    "wof:name":"PH15 2JH",
    "wof:placetype":"postalcode"
},
  "geometry": {"coordinates":[-3.96253421511784,56.61617318287175],"type":"Point"}
}