{
  "type": "Feature",
  "properties": {
    "iso:country": "GB",
    "wof:name": "NE65 9HG",
    "wof:placetype": "postalcode"
  },
  "geometry": {"coordinates":[-1.736687,55.324939],"type":"Point"}
}
