{
  "type": "Feature",
  "properties": {
    "iso:country":"GB",
    "wof:name":"NE65 9HG",
    "wof:placetype":"postalcode"
},
  "geometry": {"coordinates":[-1.73668739126429,55.32493889771222],"type":"Point"}
}