{
  "type": "Feature",
  "properties": {
    "date:inception_lower": "1991-01-01",
    "date:inception_upper": "1991-01-01",
    "iso:country": "GB",
    "wof:name": "NE65 9HG",
    "wof:placetype": "postalcode"
  },
  "geometry": {"coordinates":[-1.736687,55.324939],"type":"Point"}
}
