{
  "type": "Feature",
  "properties": {
    "iso:country":"GB",
    "wof:name":"YO21 1LX",
    "wof:placetype":"postalcode"
},
  "geometry": {"coordinates":[-0.63011520199551,54.47994951968435],"type":"Point"}
}