{
  "type": "Feature",
  "properties": {
    "iso:country":"GB",
    "wof:name":"CW1 3JU",
    "wof:placetype":"postalcode"
},
  "geometry": {"coordinates":[-2.45638316679602,53.1039002941895],"type":"Point"}
}