{
  "type": "Feature",
  "properties": {
    "iso:country":"GB",
    "wof:name":"N12 7NJ",
    "wof:placetype":"postalcode"
},
  "geometry": {"coordinates":[-0.18099159407,51.61459822173126],"type":"Point"}
}