{
  "type": "Feature",
  "properties": {
    "iso:country": "GB",
    "wof:name": "YO12 5AW",
    "wof:placetype": "postalcode"
  },
  "geometry": {"coordinates":[-0.411889,54.277157],"type":"Point"}
}
