{
  "type": "Feature",
  "properties": {
    "date:inception_lower": "1984-02-01",
    "date:inception_upper": "1984-02-01",
    "iso:country": "GB",
    "wof:name": "YO12 5AW",
    "wof:placetype": "postalcode"
  },
  "geometry": {"coordinates":[-0.411903,54.277193],"type":"Point"}
}
