{
  "type": "Feature",
  "properties": {
    "date:inception_lower": "1980-01-01",
    "date:inception_upper": "1980-01-01",
    "iso:country": "GB",
    "wof:name": "CV35 9HU",
    "wof:placetype": "postalcode"
  },
  "geometry": {"coordinates":[-1.584889,52.168756],"type":"Point"}
}
