{
  "type": "Feature",
  "properties": {
    "iso:country": "GB",
    "wof:name": "DN21 5LL",
    "wof:placetype": "postalcode"
  },
  "geometry": {"coordinates":[-0.659957,53.353674],"type":"Point"}
}
