{
  "type": "Feature",
  "properties": {
    "iso:country":"GB",
    "wof:name":"DN21 5LL",
    "wof:placetype":"postalcode"
},
  "geometry": {"coordinates":[-0.65995574137862,53.35365298753855],"type":"Point"}
}