{
  "type": "Feature",
  "properties": {
    "date:inception_lower": "2022-12-01",
    "date:inception_upper": "2022-12-01",
    "iso:country": "GB",
    "wof:name": "YO26 6SH",
    "wof:placetype": "postalcode"
  },
  "geometry": {"coordinates":[-1.136364,53.971395],"type":"Point"}
}
