{
  "type": "Feature",
  "properties": {
    "date:inception_lower": "2022-12-01",
    "date:inception_upper": "2022-12-01",
    "iso:country": "GB",
    "wof:name": "YO26 6SH",
    "wof:placetype": "postalcode"
  },
  "geometry": {"coordinates":[-1.135785,53.971364],"type":"Point"}
}
