{
  "type": "Feature",
  "properties": {
    "date:inception_lower": "1980-01-01",
    "date:inception_upper": "1980-01-01",
    "iso:country": "GB",
    "wof:name": "EX20 3SQ",
    "wof:placetype": "postalcode"
  },
  "geometry": {"coordinates":[-3.984755,50.799496],"type":"Point"}
}
