{
  "type": "Feature",
  "properties": {
    "date:inception_lower":"1980-01-01",
    "date:inception_upper":"1980-01-31",
    "iso:country":"GB",
    "wof:name":"DN14 6UT",
    "wof:placetype":"postalcode"
},
  "geometry": {"coordinates":[-0.889189,53.70863],"type":"Point"}
}