{
  "type": "Feature",
  "properties": {
    "iso:country":"GB",
    "wof:name":"AB25 1TW",
    "wof:placetype":"postalcode"
},
  "geometry": {"coordinates":[-2.11385451300056,57.14896278375227],"type":"Point"}
}