{
  "type": "Feature",
  "properties": {
    "iso:country":"GB",
    "wof:name":"BH21 1TZ",
    "wof:placetype":"postalcode"
},
  "geometry": {"coordinates":[-1.97061723270343,50.77801080485914],"type":"Point"}
}