{
  "type": "Feature",
  "properties": {
    "date:inception_lower": "1980-01-01",
    "date:inception_upper": "1980-01-01",
    "iso:country": "GB",
    "wof:name": "LE17 5QF",
    "wof:placetype": "postalcode"
  },
  "geometry": {"coordinates":[-1.114107,52.504652],"type":"Point"}
}
