{
  "type": "Feature",
  "properties": {
    "iso:country":"GB",
    "wof:name":"RG2 7QS",
    "wof:placetype":"postalcode"
},
  "geometry": {"coordinates":[-0.9626635157771,51.4296596750178],"type":"Point"}
}