{
  "type": "Feature",
  "properties": {
    "date:inception_lower": "1980-01-01",
    "date:inception_upper": "1980-01-01",
    "iso:country": "GB",
    "wof:name": "RG2 7QS",
    "wof:placetype": "postalcode"
  },
  "geometry": {"coordinates":[-0.962663,51.42966],"type":"Point"}
}
