{
  "type": "Feature",
  "properties": {
    "iso:country":"GB",
    "wof:name":"W1K 2AA",
    "wof:placetype":"postalcode"
},
  "geometry": {"coordinates":[-0.15220772211572,51.5098814893546],"type":"Point"}
}