{
  "type": "Feature",
  "properties": {
    "date:inception_lower": "1981-06-01",
    "date:inception_upper": "1981-06-01",
    "iso:country": "GB",
    "wof:name": "SG8 5TE",
    "wof:placetype": "postalcode"
  },
  "geometry": {"coordinates":[-0.020297,52.061727],"type":"Point"}
}
