{
  "type": "Feature",
  "properties": {
    "iso:country":"GB",
    "wof:name":"WA4 1NE",
    "wof:placetype":"postalcode"
},
  "geometry": {"coordinates":[-2.55611158689654,53.38102672477942],"type":"Point"}
}