{
  "type": "Feature",
  "properties": {
    "iso:country":"GB",
    "wof:name":"TN24 0AJ",
    "wof:placetype":"postalcode"
},
  "geometry": {"coordinates":[0.89852799342676,51.14478047094096],"type":"Point"}
}