{
  "type": "Feature",
  "properties": {
    "iso:country":"GB",
    "wof:name":"G33 5HA",
    "wof:placetype":"postalcode"
},
  "geometry": {"coordinates":[-4.14460020984117,55.87684875526408],"type":"Point"}
}