{
  "type": "Feature",
  "properties": {
    "date:inception_lower":"1995-12-01",
    "date:inception_upper":"1995-12-31",
    "iso:country":"GB",
    "wof:name":"G33 5HA",
    "wof:placetype":"postalcode"
},
  "geometry": {"coordinates":[-4.1446,55.876849],"type":"Point"}
}