{
  "type": "Feature",
  "properties": {
    "date:inception_lower": "1997-12-01",
    "date:inception_upper": "1997-12-01",
    "iso:country": "GB",
    "wof:name": "BS37 6XU",
    "wof:placetype": "postalcode"
  },
  "geometry": {"coordinates":[-2.407677,51.530862],"type":"Point"}
}
