{
  "type": "Feature",
  "properties": {
    "iso:country": "GB",
    "wof:name": "BN17 6PD",
    "wof:placetype": "postalcode"
  },
  "geometry": {"coordinates":[-0.522165,50.810959],"type":"Point"}
}
