{
  "type": "Feature",
  "properties": {
    "iso:country": "GB",
    "wof:name": "WS15 2RH",
    "wof:placetype": "postalcode"
  },
  "geometry": {"coordinates":[-1.948905,52.763056],"type":"Point"}
}
