{
  "type": "Feature",
  "properties": {
    "iso:country":"GB",
    "wof:name":"WS15 2RH",
    "wof:placetype":"postalcode"
},
  "geometry": {"coordinates":[-1.94890485538036,52.76305630147456],"type":"Point"}
}