{
  "type": "Feature",
  "properties": {
    "iso:country":"GB",
    "wof:name":"SP4 9JY",
    "wof:placetype":"postalcode"
},
  "geometry": {"coordinates":[-1.73106305926094,51.19260884919933],"type":"Point"}
}