{
  "type": "Feature",
  "properties": {
    "iso:country": "GB",
    "wof:name": "SP4 9JY",
    "wof:placetype": "postalcode"
  },
  "geometry": {"coordinates":[-1.731051,51.192604],"type":"Point"}
}
