{
  "type": "Feature",
  "properties": {
    "iso:country":"GB",
    "wof:name":"CO15 4HT",
    "wof:placetype":"postalcode"
},
  "geometry": {"coordinates":[1.16113007713841,51.80524355539367],"type":"Point"}
}