{
  "type": "Feature",
  "properties": {
    "iso:country": "GB",
    "wof:name": "LD6 5HA",
    "wof:placetype": "postalcode"
  },
  "geometry": {"coordinates":[-3.539728,52.317794],"type":"Point"}
}
