{
  "type": "Feature",
  "properties": {
    "iso:country":"GB",
    "wof:name":"LD6 5HA",
    "wof:placetype":"postalcode"
},
  "geometry": {"coordinates":[-3.53972836615929,52.31779412249394],"type":"Point"}
}