{
  "type": "Feature",
  "properties": {
    "date:inception_lower": "2022-06-01",
    "date:inception_upper": "2022-06-01",
    "iso:country": "GB",
    "wof:name": "S80 3GF",
    "wof:placetype": "postalcode"
  },
  "geometry": {"coordinates":[-1.151908,53.314334],"type":"Point"}
}
