{
  "type": "Feature",
  "properties": {
    "iso:country": "GB",
    "wof:name": "HR4 8PQ",
    "wof:placetype": "postalcode"
  },
  "geometry": {"coordinates":[-2.801549,52.157267],"type":"Point"}
}
