{
  "type": "Feature",
  "properties": {
    "iso:country":"GB",
    "wof:name":"HR4 8PQ",
    "wof:placetype":"postalcode"
},
  "geometry": {"coordinates":[-2.80154875509387,52.15726690053679],"type":"Point"}
}