{
  "type": "Feature",
  "properties": {
    "date:inception_lower": "2021-05-01",
    "date:inception_upper": "2021-05-01",
    "iso:country": "GB",
    "wof:name": "GU33 7FJ",
    "wof:placetype": "postalcode"
  },
  "geometry": {"coordinates":[-0.895077,51.038082],"type":"Point"}
}
