{
  "type": "Feature",
  "properties": {
    "iso:country":"GB",
    "wof:name":"NW9 0RD",
    "wof:placetype":"postalcode"
},
  "geometry": {"coordinates":[-0.27380728616423,51.59254798545671],"type":"Point"}
}