{
  "type": "Feature",
  "properties": {
    "iso:country":"GB",
    "wof:name":"CF35 5HG",
    "wof:placetype":"postalcode"
},
  "geometry": {"coordinates":[-3.5309072566106,51.5069300263991],"type":"Point"}
}