{
  "type": "Feature",
  "properties": {
    "iso:country": "GB",
    "wof:name": "CF35 5HG",
    "wof:placetype": "postalcode"
  },
  "geometry": {"coordinates":[-3.530936,51.506931],"type":"Point"}
}
