{
  "type": "Feature",
  "properties": {
    "iso:country":"GB",
    "wof:name":"NN1 5ED",
    "wof:placetype":"postalcode"
},
  "geometry": {"coordinates":[-0.88488488706853,52.23951590243062],"type":"Point"}
}