{
  "type": "Feature",
  "properties": {
    "date:inception_lower":"1980-01-01",
    "date:inception_upper":"1980-01-31",
    "iso:country":"GB",
    "wof:name":"PO8 0NL",
    "wof:placetype":"postalcode"
},
  "geometry": {"coordinates":[-1.003005,50.93978],"type":"Point"}
}