{
  "type": "Feature",
  "properties": {
    "iso:country": "GB",
    "wof:name": "PO8 0NL",
    "wof:placetype": "postalcode"
  },
  "geometry": {"coordinates":[-1.003005,50.93978],"type":"Point"}
}
