{
  "type": "Feature",
  "properties": {
    "iso:country":"GB",
    "wof:name":"PO8 0NL",
    "wof:placetype":"postalcode"
},
  "geometry": {"coordinates":[-1.00300486124283,50.93977964672688],"type":"Point"}
}