{
  "type": "Feature",
  "properties": {
    "iso:country": "GB",
    "wof:name": "BL4 0LX",
    "wof:placetype": "postalcode"
  },
  "geometry": {"coordinates":[-2.424486,53.55057],"type":"Point"}
}
