{
  "type": "Feature",
  "properties": {
    "date:inception_lower": "1996-06-01",
    "date:inception_upper": "1996-06-01",
    "iso:country": "GB",
    "wof:name": "AB11 6XN",
    "wof:placetype": "postalcode"
  },
  "geometry": {"coordinates":[-2.10996,57.139696],"type":"Point"}
}
