{
  "type": "Feature",
  "properties": {
    "iso:country":"GB",
    "wof:name":"EC1Y 8HQ",
    "wof:placetype":"postalcode"
},
  "geometry": {"coordinates":[-0.08961653550037,51.52169307223974],"type":"Point"}
}