{
  "type": "Feature",
  "properties": {
    "iso:country": "GB",
    "wof:name": "SL0 9NH",
    "wof:placetype": "postalcode"
  },
  "geometry": {"coordinates":[-0.507907,51.5191],"type":"Point"}
}
