{
  "type": "Feature",
  "properties": {
    "iso:country":"GB",
    "wof:name":"SL0 9NH",
    "wof:placetype":"postalcode"
},
  "geometry": {"coordinates":[-0.50790723060582,51.51909989070976],"type":"Point"}
}