{
  "type": "Feature",
  "properties": {
    "date:inception_lower": "2018-04-01",
    "date:inception_upper": "2018-04-01",
    "iso:country": "GB",
    "wof:name": "TW8 9FZ",
    "wof:placetype": "postalcode"
  },
  "geometry": {"coordinates":[-0.313406,51.491755],"type":"Point"}
}
