{
  "type": "Feature",
  "properties": {
    "iso:country": "GB",
    "wof:name": "RM7 0HG",
    "wof:placetype": "postalcode"
  },
  "geometry": {"coordinates":[0.177219,51.572136],"type":"Point"}
}
