{
  "type": "Feature",
  "properties": {
    "date:inception_lower": "2017-11-01",
    "date:inception_upper": "2017-11-01",
    "iso:country": "GB",
    "wof:name": "RM7 0HG",
    "wof:placetype": "postalcode"
  },
  "geometry": {"coordinates":[0.177272,51.572036],"type":"Point"}
}
