{
  "type": "Feature",
  "properties": {
    "date:inception_lower": "1980-01-01",
    "date:inception_upper": "1980-01-01",
    "iso:country": "GB",
    "wof:name": "TN39 5JJ",
    "wof:placetype": "postalcode"
  },
  "geometry": {"coordinates":[0.446099,50.868864],"type":"Point"}
}
