{
  "type": "Feature",
  "properties": {
    "iso:country":"GB",
    "wof:name":"TN39 5JJ",
    "wof:placetype":"postalcode"
},
  "geometry": {"coordinates":[0.44609924074115,50.86886438893652],"type":"Point"}
}