{
  "type": "Feature",
  "properties": {
    "date:inception_lower": "2007-05-01",
    "date:inception_upper": "2007-05-01",
    "iso:country": "GB",
    "wof:name": "SW95 9DU",
    "wof:placetype": "postalcode"
  },
  "geometry": {"coordinates":[-0.136555,51.480624],"type":"Point"}
}
