{
  "type": "Feature",
  "properties": {
    "date:inception_lower":"1980-01-01",
    "date:inception_upper":"1980-01-31",
    "iso:country":"GB",
    "wof:name":"TF9 1BA",
    "wof:placetype":"postalcode"
},
  "geometry": {"coordinates":[-2.495852,52.897834],"type":"Point"}
}