{
  "type": "Feature",
  "properties": {
    "iso:country":"GB",
    "wof:name":"TF9 1BA",
    "wof:placetype":"postalcode"
},
  "geometry": {"coordinates":[-2.49585222013063,52.89783445495983],"type":"Point"}
}