{
  "type": "Feature",
  "properties": {
    "iso:country":"GB",
    "wof:name":"WV6 7LE",
    "wof:placetype":"postalcode"
},
  "geometry": {"coordinates":[-2.19290560134786,52.60200397181256],"type":"Point"}
}