{
  "type": "Feature",
  "properties": {
    "iso:country": "GB",
    "wof:name": "WV6 7LE",
    "wof:placetype": "postalcode"
  },
  "geometry": {"coordinates":[-2.192906,52.602004],"type":"Point"}
}
