{
  "type": "Feature",
  "properties": {
    "iso:country":"GB",
    "wof:name":"DN14 7BF",
    "wof:placetype":"postalcode"
},
  "geometry": {"coordinates":[-0.79201610348667,53.75190495228408],"type":"Point"}
}