{
  "type": "Feature",
  "properties": {
    "iso:country": "GB",
    "wof:name": "DN14 7BF",
    "wof:placetype": "postalcode"
  },
  "geometry": {"coordinates":[-0.792016,53.751905],"type":"Point"}
}
