{
  "type": "Feature",
  "properties": {
    "date:inception_lower": "1980-01-01",
    "date:inception_upper": "1980-01-01",
    "iso:country": "GB",
    "wof:name": "BN22 7LP",
    "wof:placetype": "postalcode"
  },
  "geometry": {"coordinates":[0.303462,50.780434],"type":"Point"}
}
