{
  "type": "Feature",
  "properties": {
    "iso:country":"GB",
    "wof:name":"RH8 0AX",
    "wof:placetype":"postalcode"
},
  "geometry": {"coordinates":[-0.00285377602067,51.25762095797296],"type":"Point"}
}