{
  "type": "Feature",
  "properties": {
    "iso:country":"GB",
    "wof:name":"DL15 9LR",
    "wof:placetype":"postalcode"
},
  "geometry": {"coordinates":[-1.75585329969924,54.71398312709994],"type":"Point"}
}