{
  "type": "Feature",
  "properties": {
    "date:inception_lower":"1986-07-01",
    "date:inception_upper":"1986-07-31",
    "iso:country":"GB",
    "wof:name":"EX4 9JU",
    "wof:placetype":"postalcode"
},
  "geometry": {"coordinates":[-3.495414,50.74372],"type":"Point"}
}