{
  "type": "Feature",
  "properties": {
    "iso:country":"GB",
    "wof:name":"EX4 9JU",
    "wof:placetype":"postalcode"
},
  "geometry": {"coordinates":[-3.49541423504607,50.74371979354714],"type":"Point"}
}