{
  "type": "Feature",
  "properties": {
    "iso:country": "GB",
    "wof:name": "EX4 9JU",
    "wof:placetype": "postalcode"
  },
  "geometry": {"coordinates":[-3.495414,50.74372],"type":"Point"}
}
