{
  "type": "Feature",
  "properties": {
    "iso:country":"GB",
    "wof:name":"SY7 8PH",
    "wof:placetype":"postalcode"
},
  "geometry": {"coordinates":[-3.14860220194941,52.43021377813162],"type":"Point"}
}