{
  "type": "Feature",
  "properties": {
    "iso:country": "GB",
    "wof:name": "SY7 8PH",
    "wof:placetype": "postalcode"
  },
  "geometry": {"coordinates":[-3.148602,52.430214],"type":"Point"}
}
