{
  "type": "Feature",
  "properties": {
    "iso:country":"GB",
    "wof:name":"NR24 2DD",
    "wof:placetype":"postalcode"
},
  "geometry": {"coordinates":[1.03640316981404,52.85596469981424],"type":"Point"}
}