{
  "type": "Feature",
  "properties": {
    "iso:country": "GB",
    "wof:name": "NR24 2DD",
    "wof:placetype": "postalcode"
  },
  "geometry": {"coordinates":[1.036403,52.855965],"type":"Point"}
}
