{
  "type": "Feature",
  "properties": {
    "iso:country":"GB",
    "wof:name":"SG2 7AH",
    "wof:placetype":"postalcode"
},
  "geometry": {"coordinates":[-0.09698093942252,51.92755285648931],"type":"Point"}
}