{
  "type": "Feature",
  "properties": {
    "iso:country": "GB",
    "wof:name": "S70 4DH",
    "wof:placetype": "postalcode"
  },
  "geometry": {"coordinates":[-1.471606,53.542473],"type":"Point"}
}
