{
  "type": "Feature",
  "properties": {
    "iso:country":"GB",
    "wof:name":"ML1 2JQ",
    "wof:placetype":"postalcode"
},
  "geometry": {"coordinates":[-3.96423018457692,55.77814669297243],"type":"Point"}
}