{
  "type": "Feature",
  "properties": {
    "date:inception_lower":"1995-12-01",
    "date:inception_upper":"1995-12-31",
    "iso:country":"GB",
    "wof:name":"ML1 2JQ",
    "wof:placetype":"postalcode"
},
  "geometry": {"coordinates":[-3.96423,55.778147],"type":"Point"}
}