{
  "type": "Feature",
  "properties": {
    "date:inception_lower": "2023-07-01",
    "date:inception_upper": "2023-07-01",
    "iso:country": "GB",
    "wof:name": "MK8 1GA",
    "wof:placetype": "postalcode"
  },
  "geometry": {"coordinates":[-0.819552,52.025437],"type":"Point"}
}
