{
  "type": "Feature",
  "properties": {
    "iso:country": "GB",
    "wof:name": "HD8 0TW",
    "wof:placetype": "postalcode"
  },
  "geometry": {"coordinates":[-1.694639,53.614132],"type":"Point"}
}
