{
  "type": "Feature",
  "properties": {
    "iso:country":"GB",
    "wof:name":"NR34 9AS",
    "wof:placetype":"postalcode"
},
  "geometry": {"coordinates":[1.56333058547207,52.46042472058199],"type":"Point"}
}