{
  "type": "Feature",
  "properties": {
    "date:inception_lower":"1985-10-01",
    "date:inception_upper":"1985-10-31",
    "iso:country":"GB",
    "wof:name":"CM5 9PG",
    "wof:placetype":"postalcode"
},
  "geometry": {"coordinates":[0.232716,51.688492],"type":"Point"}
}