{
  "type": "Feature",
  "properties": {
    "iso:country": "GB",
    "wof:name": "CM5 9PG",
    "wof:placetype": "postalcode"
  },
  "geometry": {"coordinates":[0.232716,51.688492],"type":"Point"}
}
