{
  "type": "Feature",
  "properties": {
    "iso:country":"GB",
    "wof:name":"CM5 9PG",
    "wof:placetype":"postalcode"
},
  "geometry": {"coordinates":[0.23271556258021,51.6884917810149],"type":"Point"}
}