{
  "type": "Feature",
  "properties": {
    "iso:country":"GB",
    "wof:name":"ML1 4DY",
    "wof:placetype":"postalcode"
},
  "geometry": {"coordinates":[-3.96019268254754,55.80474952917467],"type":"Point"}
}