{
  "type": "Feature",
  "properties": {
    "date:inception_lower":"1980-01-01",
    "date:inception_upper":"1980-01-31",
    "iso:country":"GB",
    "wof:name":"NR28 9HS",
    "wof:placetype":"postalcode"
},
  "geometry": {"coordinates":[1.396563,52.816198],"type":"Point"}
}