{
  "type": "Feature",
  "properties": {
    "iso:country":"GB",
    "wof:name":"NR28 9HS",
    "wof:placetype":"postalcode"
},
  "geometry": {"coordinates":[1.39658736693684,52.8161865826258],"type":"Point"}
}