{
  "type": "Feature",
  "properties": {
    "date:inception_lower":"1980-01-01",
    "date:inception_upper":"1980-01-31",
    "iso:country":"GB",
    "wof:name":"LL71 8AN",
    "wof:placetype":"postalcode"
},
  "geometry": {"coordinates":[-4.369991,53.345074],"type":"Point"}
}