{
  "type": "Feature",
  "properties": {
    "iso:country":"GB",
    "wof:name":"WR9 0NL",
    "wof:placetype":"postalcode"
},
  "geometry": {"coordinates":[-2.15045510494653,52.33879401263545],"type":"Point"}
}