{
  "type": "Feature",
  "properties": {
    "iso:country": "GB",
    "wof:name": "WR9 0NL",
    "wof:placetype": "postalcode"
  },
  "geometry": {"coordinates":[-2.1492,52.338244],"type":"Point"}
}
