{
  "type": "Feature",
  "properties": {
    "iso:country":"GB",
    "wof:name":"EH51 9JA",
    "wof:placetype":"postalcode"
},
  "geometry": {"coordinates":[-3.60396615647752,56.00869517330563],"type":"Point"}
}