{
  "type": "Feature",
  "properties": {
    "iso:country":"GB",
    "wof:name":"NG5 8EP",
    "wof:placetype":"postalcode"
},
  "geometry": {"coordinates":[-1.11976490304096,53.01190860660495],"type":"Point"}
}