{
  "type": "Feature",
  "properties": {
    "date:inception_lower": "1994-05-01",
    "date:inception_upper": "1994-05-01",
    "iso:country": "GB",
    "wof:name": "BB7 9UG",
    "wof:placetype": "postalcode"
  },
  "geometry": {"coordinates":[-2.403456,53.822356],"type":"Point"}
}
