{
  "type": "Feature",
  "properties": {
    "iso:country": "GB",
    "wof:name": "PE15 0FH",
    "wof:placetype": "postalcode"
  },
  "geometry": {"coordinates":[0.048249,52.493945],"type":"Point"}
}
