{
  "type": "Feature",
  "properties": {
    "iso:country":"GB",
    "wof:name":"PE15 0FH",
    "wof:placetype":"postalcode"
},
  "geometry": {"coordinates":[0.04824855035003,52.49394514496724],"type":"Point"}
}