{
  "type": "Feature",
  "properties": {
    "iso:country":"GB",
    "wof:name":"M33 2DD",
    "wof:placetype":"postalcode"
},
  "geometry": {"coordinates":[-2.30835212669934,53.427109881741],"type":"Point"}
}