{
  "type": "Feature",
  "properties": {
    "date:inception_lower": "1980-01-01",
    "date:inception_upper": "1980-01-01",
    "iso:country": "GB",
    "wof:name": "M33 2DD",
    "wof:placetype": "postalcode"
  },
  "geometry": {"coordinates":[-2.308352,53.42711],"type":"Point"}
}
