{
  "type": "Feature",
  "properties": {
    "iso:country":"GB",
    "wof:name":"CT16 1EQ",
    "wof:placetype":"postalcode"
},
  "geometry": {"coordinates":[1.30577137925291,51.12998494514964],"type":"Point"}
}