{
  "type": "Feature",
  "properties": {
    "date:inception_lower": "2001-06-01",
    "date:inception_upper": "2001-06-01",
    "iso:country": "GB",
    "wof:name": "CT16 1EQ",
    "wof:placetype": "postalcode"
  },
  "geometry": {"coordinates":[1.305771,51.129985],"type":"Point"}
}
