{
  "type": "Feature",
  "properties": {
    "iso:country":"GB",
    "wof:name":"HG2 0BS",
    "wof:placetype":"postalcode"
},
  "geometry": {"coordinates":[-1.56176371178728,53.97907403806382],"type":"Point"}
}