{
  "type": "Feature",
  "properties": {
    "iso:country": "GB",
    "wof:name": "PO22 0JY",
    "wof:placetype": "postalcode"
  },
  "geometry": {"coordinates":[-0.63904,50.834342],"type":"Point"}
}
