{
  "type": "Feature",
  "properties": {
    "date:inception_lower": "1990-08-01",
    "date:inception_upper": "1990-08-01",
    "iso:country": "GB",
    "wof:name": "AB31 4JT",
    "wof:placetype": "postalcode"
  },
  "geometry": {"coordinates":[-2.628339,57.108197],"type":"Point"}
}
