{
  "type": "Feature",
  "properties": {
    "iso:country":"GB",
    "wof:name":"BH10 5EU",
    "wof:placetype":"postalcode"
},
  "geometry": {"coordinates":[-1.90170069262051,50.76461924214364],"type":"Point"}
}