{
  "type": "Feature",
  "properties": {
    "iso:country": "GB",
    "wof:name": "BL3 4RJ",
    "wof:placetype": "postalcode"
  },
  "geometry": {"coordinates":[-2.484364,53.558755],"type":"Point"}
}
