{
  "type": "Feature",
  "properties": {
    "date:inception_lower": "1998-06-01",
    "date:inception_upper": "1998-06-01",
    "iso:country": "GB",
    "wof:name": "MK18 1SU",
    "wof:placetype": "postalcode"
  },
  "geometry": {"coordinates":[-0.997792,51.999269],"type":"Point"}
}
