{
  "type": "Feature",
  "properties": {
    "iso:country": "GB",
    "wof:name": "MK18 1SU",
    "wof:placetype": "postalcode"
  },
  "geometry": {"coordinates":[-0.9974,51.998716],"type":"Point"}
}
