{
  "type": "Feature",
  "properties": {
    "iso:country":"GB",
    "wof:name":"MK18 1SU",
    "wof:placetype":"postalcode"
},
  "geometry": {"coordinates":[-0.99591497190849,51.99869447743988],"type":"Point"}
}