{
  "type": "Feature",
  "properties": {
    "iso:country": "GB",
    "wof:name": "AL10 9QX",
    "wof:placetype": "postalcode"
  },
  "geometry": {"coordinates":[-0.23508,51.74715],"type":"Point"}
}
