{
  "type": "Feature",
  "properties": {
    "iso:country":"GB",
    "wof:name":"UB4 0QU",
    "wof:placetype":"postalcode"
},
  "geometry": {"coordinates":[-0.4104923509173,51.52433975138683],"type":"Point"}
}