{
  "type": "Feature",
  "properties": {
    "iso:country": "GB",
    "wof:name": "UB4 0QU",
    "wof:placetype": "postalcode"
  },
  "geometry": {"coordinates":[-0.410492,51.52434],"type":"Point"}
}
