{
  "type": "Feature",
  "properties": {
    "iso:country":"GB",
    "wof:name":"WD4 8JR",
    "wof:placetype":"postalcode"
},
  "geometry": {"coordinates":[-0.44851681323336,51.71164028908174],"type":"Point"}
}