{
  "type": "Feature",
  "properties": {
    "iso:country":"GB",
    "wof:name":"SA35 0AR",
    "wof:placetype":"postalcode"
},
  "geometry": {"coordinates":[-4.55147761626742,51.98916228439327],"type":"Point"}
}