{
  "type": "Feature",
  "properties": {
    "iso:country": "GB",
    "wof:name": "E7 0HF",
    "wof:placetype": "postalcode"
  },
  "geometry": {"coordinates":[0.020911,51.551171],"type":"Point"}
}
