{
  "type": "Feature",
  "properties": {
    "iso:country":"GB",
    "wof:name":"E7 0HF",
    "wof:placetype":"postalcode"
},
  "geometry": {"coordinates":[0.02091057000271,51.55117122237125],"type":"Point"}
}