{
  "type": "Feature",
  "properties": {
    "iso:country":"GB",
    "wof:name":"DD4 0QE",
    "wof:placetype":"postalcode"
},
  "geometry": {"coordinates":[-2.9541132384867,56.56039611299642],"type":"Point"}
}