{
  "type": "Feature",
  "properties": {
    "date:inception_lower": "1980-01-01",
    "date:inception_upper": "1980-01-01",
    "iso:country": "GB",
    "wof:name": "LE12 6JE",
    "wof:placetype": "postalcode"
  },
  "geometry": {"coordinates":[-1.177599,52.851608],"type":"Point"}
}
