{
  "type": "Feature",
  "properties": {
    "iso:country": "GB",
    "wof:name": "WA7 3FA",
    "wof:placetype": "postalcode"
  },
  "geometry": {"coordinates":[-2.653238,53.317008],"type":"Point"}
}
