{
  "type": "Feature",
  "properties": {
    "iso:country":"GB",
    "wof:name":"WA7 3FA",
    "wof:placetype":"postalcode"
},
  "geometry": {"coordinates":[-2.65487237073261,53.31485341439266],"type":"Point"}
}