{
  "type": "Feature",
  "properties": {
    "date:inception_lower":"1996-06-01",
    "date:inception_upper":"1996-06-30",
    "iso:country":"GB",
    "wof:name":"WA7 3FA",
    "wof:placetype":"postalcode"
},
  "geometry": {"coordinates":[-2.653238,53.317008],"type":"Point"}
}