{
  "type": "Feature",
  "properties": {
    "iso:country":"GB",
    "wof:name":"SA33 6AS",
    "wof:placetype":"postalcode"
},
  "geometry": {"coordinates":[-4.36832186904618,51.94352180215149],"type":"Point"}
}