{
  "type": "Feature",
  "properties": {
    "date:inception_lower":"1980-01-01",
    "date:inception_upper":"1980-01-31",
    "iso:country":"GB",
    "wof:name":"DD5 4LP",
    "wof:placetype":"postalcode"
},
  "geometry": {"coordinates":[-2.831329,56.479898],"type":"Point"}
}