{
  "type": "Feature",
  "properties": {
    "iso:country": "GB",
    "wof:name": "NG5 4EP",
    "wof:placetype": "postalcode"
  },
  "geometry": {"coordinates":[-1.135166,52.981729],"type":"Point"}
}
