{
  "type": "Feature",
  "properties": {
    "iso:country":"GB",
    "wof:name":"EH6 8NZ",
    "wof:placetype":"postalcode"
},
  "geometry": {"coordinates":[-3.17406991005736,55.96560090360971],"type":"Point"}
}