{
  "type": "Feature",
  "properties": {
    "iso:country":"GB",
    "wof:name":"IG1 1NJ",
    "wof:placetype":"postalcode"
},
  "geometry": {"coordinates":[0.07890777100546,51.56058934824684],"type":"Point"}
}