{
  "type": "Feature",
  "properties": {
    "iso:country":"GB",
    "wof:name":"TW17 0QB",
    "wof:placetype":"postalcode"
},
  "geometry": {"coordinates":[-0.4622026328462,51.40645732902038],"type":"Point"}
}