{
  "type": "Feature",
  "properties": {
    "iso:country": "GB",
    "wof:name": "TW17 0QB",
    "wof:placetype": "postalcode"
  },
  "geometry": {"coordinates":[-0.462203,51.406457],"type":"Point"}
}
