{
  "type": "Feature",
  "properties": {
    "iso:country": "GB",
    "wof:name": "LA2 9PG",
    "wof:placetype": "postalcode"
  },
  "geometry": {"coordinates":[-2.702966,54.073706],"type":"Point"}
}
