{
  "type": "Feature",
  "properties": {
    "iso:country": "GB",
    "wof:name": "CB4 3AP",
    "wof:placetype": "postalcode"
  },
  "geometry": {"coordinates":[0.121508,52.21374],"type":"Point"}
}
