{
  "type": "Feature",
  "properties": {
    "iso:country":"GB",
    "wof:name":"CB4 3AP",
    "wof:placetype":"postalcode"
},
  "geometry": {"coordinates":[0.12150822333572,52.21374005397652],"type":"Point"}
}