{
  "type": "Feature",
  "properties": {
    "date:inception_lower":"1980-01-01",
    "date:inception_upper":"1980-01-31",
    "iso:country":"GB",
    "wof:name":"CB4 3AP",
    "wof:placetype":"postalcode"
},
  "geometry": {"coordinates":[0.121508,52.21374],"type":"Point"}
}