{
  "type": "Feature",
  "properties": {
    "date:inception_lower": "1980-01-01",
    "date:inception_upper": "1980-01-01",
    "iso:country": "GB",
    "wof:name": "DY2 8EB",
    "wof:placetype": "postalcode"
  },
  "geometry": {"coordinates":[-2.074763,52.502485],"type":"Point"}
}
