{
  "type": "Feature",
  "properties": {
    "iso:country":"GB",
    "wof:name":"DY2 8EB",
    "wof:placetype":"postalcode"
},
  "geometry": {"coordinates":[-2.07476344644129,52.50248523833022],"type":"Point"}
}