{
  "type": "Feature",
  "properties": {
    "iso:country":"GB",
    "wof:name":"BB12 7JA",
    "wof:placetype":"postalcode"
},
  "geometry": {"coordinates":[-2.34494332074124,53.80773513804035],"type":"Point"}
}