{
  "type": "Feature",
  "properties": {
    "iso:country": "GB",
    "wof:name": "BB12 7JA",
    "wof:placetype": "postalcode"
  },
  "geometry": {"coordinates":[-2.344943,53.807735],"type":"Point"}
}
