{
  "type": "Feature",
  "properties": {
    "iso:country":"GB",
    "wof:name":"EH14 6AP",
    "wof:placetype":"postalcode"
},
  "geometry": {"coordinates":[-3.30720293531243,55.8938848880486],"type":"Point"}
}