{
  "type": "Feature",
  "properties": {
    "iso:country":"GB",
    "wof:name":"CO10 0BH",
    "wof:placetype":"postalcode"
},
  "geometry": {"coordinates":[0.75271704617853,52.08668515569935],"type":"Point"}
}