{
  "type": "Feature",
  "properties": {
    "iso:country":"GB",
    "wof:name":"WV8 1SE",
    "wof:placetype":"postalcode"
},
  "geometry": {"coordinates":[-2.19783528715484,52.6277784780926],"type":"Point"}
}