{
  "type": "Feature",
  "properties": {
    "iso:country":"GB",
    "wof:name":"PE25 2ER",
    "wof:placetype":"postalcode"
},
  "geometry": {"coordinates":[0.32258385051483,53.14437884193439],"type":"Point"}
}