{
  "type": "Feature",
  "properties": {
    "date:inception_lower":"1995-01-01",
    "date:inception_upper":"1995-01-31",
    "iso:country":"GB",
    "wof:name":"BA14 0BH",
    "wof:placetype":"postalcode"
},
  "geometry": {"coordinates":[-2.205303,51.305854],"type":"Point"}
}