{
  "type": "Feature",
  "properties": {
    "iso:country": "GB",
    "wof:name": "BA14 0BH",
    "wof:placetype": "postalcode"
  },
  "geometry": {"coordinates":[-2.205303,51.305854],"type":"Point"}
}
