{
  "type": "Feature",
  "properties": {
    "date:inception_lower": "2020-04-01",
    "date:inception_upper": "2020-04-01",
    "iso:country": "GB",
    "wof:name": "CT3 3HW",
    "wof:placetype": "postalcode"
  },
  "geometry": {"coordinates":[1.193488,51.227362],"type":"Point"}
}
