{
  "type": "Feature",
  "properties": {
    "iso:country":"GB",
    "wof:name":"TW6 1RU",
    "wof:placetype":"postalcode"
},
  "geometry": {"coordinates":[-0.45546182985406,51.47292956145986],"type":"Point"}
}