{
  "type": "Feature",
  "properties": {
    "date:inception_lower": "1997-12-01",
    "date:inception_upper": "1997-12-01",
    "iso:country": "GB",
    "wof:name": "TW6 1RU",
    "wof:placetype": "postalcode"
  },
  "geometry": {"coordinates":[-0.455462,51.47293],"type":"Point"}
}
