{
  "type": "Feature",
  "properties": {
    "iso:country":"GB",
    "wof:name":"SO16 3PF",
    "wof:placetype":"postalcode"
},
  "geometry": {"coordinates":[-1.40329275986868,50.95130466771289],"type":"Point"}
}