{
  "type": "Feature",
  "properties": {
    "iso:country": "GB",
    "wof:name": "SO16 3PF",
    "wof:placetype": "postalcode"
  },
  "geometry": {"coordinates":[-1.403293,50.951305],"type":"Point"}
}
