{
  "type": "Feature",
  "properties": {
    "date:inception_lower": "2001-06-01",
    "date:inception_upper": "2001-06-01",
    "iso:country": "GB",
    "wof:name": "GL14 3JN",
    "wof:placetype": "postalcode"
  },
  "geometry": {"coordinates":[-2.513627,51.821538],"type":"Point"}
}
