{
  "type": "Feature",
  "properties": {
    "iso:country":"GB",
    "wof:name":"GL14 3JN",
    "wof:placetype":"postalcode"
},
  "geometry": {"coordinates":[-2.51361289604547,51.82155599145898],"type":"Point"}
}