{
  "type": "Feature",
  "properties": {
    "date:inception_lower":"1980-01-01",
    "date:inception_upper":"1980-01-31",
    "iso:country":"GB",
    "wof:name":"NG16 6FZ",
    "wof:placetype":"postalcode"
},
  "geometry": {"coordinates":[-1.314455,53.073795],"type":"Point"}
}