{
  "type": "Feature",
  "properties": {
    "date:inception_lower": "1980-01-01",
    "date:inception_upper": "1980-01-01",
    "iso:country": "GB",
    "wof:name": "SA31 2HX",
    "wof:placetype": "postalcode"
  },
  "geometry": {"coordinates":[-4.277632,51.852536],"type":"Point"}
}
