{
  "type": "Feature",
  "properties": {
    "iso:country":"GB",
    "wof:name":"SA31 2HX",
    "wof:placetype":"postalcode"
},
  "geometry": {"coordinates":[-4.27763188177537,51.85253621316341],"type":"Point"}
}