{
  "type": "Feature",
  "properties": {
    "date:inception_lower": "2018-07-01",
    "date:inception_upper": "2018-07-01",
    "iso:country": "GB",
    "wof:name": "L19 8AF",
    "wof:placetype": "postalcode"
  },
  "geometry": {"coordinates":[-2.897744,53.349514],"type":"Point"}
}
