{
  "type": "Feature",
  "properties": {
    "iso:country": "GB",
    "wof:name": "ML7 5SG",
    "wof:placetype": "postalcode"
  },
  "geometry": {"coordinates":[-3.754183,55.861861],"type":"Point"}
}
