{
  "type": "Feature",
  "properties": {
    "iso:country":"GB",
    "wof:name":"TN24 0EE",
    "wof:placetype":"postalcode"
},
  "geometry": {"coordinates":[0.89087831715526,51.1418128746182],"type":"Point"}
}