{
  "type": "Feature",
  "properties": {
    "date:inception_lower": "1980-01-01",
    "date:inception_upper": "1980-01-01",
    "iso:country": "GB",
    "wof:name": "TN24 0EE",
    "wof:placetype": "postalcode"
  },
  "geometry": {"coordinates":[0.890878,51.141813],"type":"Point"}
}
