{
  "type": "Feature",
  "properties": {
    "iso:country":"GB",
    "wof:name":"BL1 2AL",
    "wof:placetype":"postalcode"
},
  "geometry": {"coordinates":[-2.4302160221529,53.5812626928596],"type":"Point"}
}