{
  "type": "Feature",
  "properties": {
    "date:inception_lower":"1990-02-01",
    "date:inception_upper":"1990-02-28",
    "iso:country":"GB",
    "wof:name":"BL1 2AL",
    "wof:placetype":"postalcode"
},
  "geometry": {"coordinates":[-2.429655,53.581308],"type":"Point"}
}