{
  "type": "Feature",
  "properties": {
    "iso:country": "GB",
    "wof:name": "HR3 6AF",
    "wof:placetype": "postalcode"
  },
  "geometry": {"coordinates":[-3.040722,52.077466],"type":"Point"}
}
