{
  "type": "Feature",
  "properties": {
    "date:inception_lower": "1980-01-01",
    "date:inception_upper": "1980-01-01",
    "iso:country": "GB",
    "wof:name": "SA44 5EP",
    "wof:placetype": "postalcode"
  },
  "geometry": {"coordinates":[-4.371902,52.027566],"type":"Point"}
}
