{
  "type": "Feature",
  "properties": {
    "iso:country": "GB",
    "wof:name": "SA44 5EP",
    "wof:placetype": "postalcode"
  },
  "geometry": {"coordinates":[-4.371902,52.027566],"type":"Point"}
}
