{
  "type": "Feature",
  "properties": {
    "iso:country": "GB",
    "wof:name": "CF37 5RY",
    "wof:placetype": "postalcode"
  },
  "geometry": {"coordinates":[-3.31234,51.588385],"type":"Point"}
}
