{
  "type": "Feature",
  "properties": {
    "iso:country":"GB",
    "wof:name":"CF37 5RY",
    "wof:placetype":"postalcode"
},
  "geometry": {"coordinates":[-3.31233991708182,51.58838501578416],"type":"Point"}
}