{
  "type": "Feature",
  "properties": {
    "date:inception_lower": "1980-01-01",
    "date:inception_upper": "1980-01-01",
    "iso:country": "GB",
    "wof:name": "CF37 5RY",
    "wof:placetype": "postalcode"
  },
  "geometry": {"coordinates":[-3.31234,51.588385],"type":"Point"}
}
