{
  "type": "Feature",
  "properties": {
    "iso:country":"GB",
    "wof:name":"TA12 6EN",
    "wof:placetype":"postalcode"
},
  "geometry": {"coordinates":[-2.76500761957478,50.97495078274333],"type":"Point"}
}