{
  "type": "Feature",
  "properties": {
    "date:inception_lower":"1980-01-01",
    "date:inception_upper":"1980-01-31",
    "iso:country":"GB",
    "wof:name":"TA12 6EN",
    "wof:placetype":"postalcode"
},
  "geometry": {"coordinates":[-2.765008,50.974951],"type":"Point"}
}