{
  "type": "Feature",
  "properties": {
    "iso:country":"GB",
    "wof:name":"NW6 3JF",
    "wof:placetype":"postalcode"
},
  "geometry": {"coordinates":[-0.18318618119082,51.54405112320812],"type":"Point"}
}