{
  "type": "Feature",
  "properties": {
    "iso:country":"GB",
    "wof:name":"HU17 9RA",
    "wof:placetype":"postalcode"
},
  "geometry": {"coordinates":[-0.42392423305967,53.85436542551474],"type":"Point"}
}