{
  "type": "Feature",
  "properties": {
    "iso:country":"GB",
    "wof:name":"SS7 2JF",
    "wof:placetype":"postalcode"
},
  "geometry": {"coordinates":[0.61933660790699,51.55652949314563],"type":"Point"}
}