{
  "type": "Feature",
  "properties": {
    "iso:country": "GB",
    "wof:name": "SS7 2JF",
    "wof:placetype": "postalcode"
  },
  "geometry": {"coordinates":[0.619337,51.556529],"type":"Point"}
}
