{
  "type": "Feature",
  "properties": {
    "date:inception_lower":"1980-01-01",
    "date:inception_upper":"1980-01-31",
    "iso:country":"GB",
    "wof:name":"G53 5XX",
    "wof:placetype":"postalcode"
},
  "geometry": {"coordinates":[-4.343974,55.838079],"type":"Point"}
}