{
  "type": "Feature",
  "properties": {
    "iso:country": "GB",
    "wof:name": "G53 5XX",
    "wof:placetype": "postalcode"
  },
  "geometry": {"coordinates":[-4.343974,55.838079],"type":"Point"}
}
