{
  "type": "Feature",
  "properties": {
    "iso:country":"GB",
    "wof:name":"TN28 8JD",
    "wof:placetype":"postalcode"
},
  "geometry": {"coordinates":[0.94821092648657,50.99153754272408],"type":"Point"}
}