{
  "type": "Feature",
  "properties": {
    "iso:country":"GB",
    "wof:name":"NR23 1LQ",
    "wof:placetype":"postalcode"
},
  "geometry": {"coordinates":[0.85878634731315,52.95516533427021],"type":"Point"}
}