{
  "type": "Feature",
  "properties": {
    "iso:country":"GB",
    "wof:name":"B97 4RT",
    "wof:placetype":"postalcode"
},
  "geometry": {"coordinates":[-1.95223256087607,52.30470883557447],"type":"Point"}
}