{
  "type": "Feature",
  "properties": {
    "iso:country":"GB",
    "wof:name":"CH6 6HE",
    "wof:placetype":"postalcode"
},
  "geometry": {"coordinates":[-3.17780000710784,53.27273897869988],"type":"Point"}
}