{
  "type": "Feature",
  "properties": {
    "date:inception_lower":"1991-09-01",
    "date:inception_upper":"1991-09-30",
    "iso:country":"GB",
    "wof:name":"CH6 6HE",
    "wof:placetype":"postalcode"
},
  "geometry": {"coordinates":[-3.177664,53.272694],"type":"Point"}
}