{
  "type": "Feature",
  "properties": {
    "iso:country":"GB",
    "wof:name":"LL57 4HD",
    "wof:placetype":"postalcode"
},
  "geometry": {"coordinates":[-4.12321431185816,53.17126093036919],"type":"Point"}
}