{
  "type": "Feature",
  "properties": {
    "date:inception_lower": "2023-10-01",
    "date:inception_upper": "2023-10-01",
    "iso:country": "GB",
    "wof:name": "MK8 1GW",
    "wof:placetype": "postalcode"
  },
  "geometry": {"coordinates":[-0.818491,52.036953],"type":"Point"}
}
