{
  "type": "Feature",
  "properties": {
    "iso:country":"GB",
    "wof:name":"GL11 5ST",
    "wof:placetype":"postalcode"
},
  "geometry": {"coordinates":[-2.3055972060485,51.68336833949666],"type":"Point"}
}