{
  "type": "Feature",
  "properties": {
    "date:inception_lower":"1980-01-01",
    "date:inception_upper":"1980-01-31",
    "iso:country":"GB",
    "wof:name":"L36 8DX",
    "wof:placetype":"postalcode"
},
  "geometry": {"coordinates":[-2.843652,53.426469],"type":"Point"}
}