{
  "type": "Feature",
  "properties": {
    "iso:country":"GB",
    "wof:name":"L36 8DX",
    "wof:placetype":"postalcode"
},
  "geometry": {"coordinates":[-2.84365206744128,53.42646884884454],"type":"Point"}
}