{
  "type": "Feature",
  "properties": {
    "iso:country":"GB",
    "wof:name":"CB7 4QQ",
    "wof:placetype":"postalcode"
},
  "geometry": {"coordinates":[0.27123278021395,52.40059403155544],"type":"Point"}
}