{
  "type": "Feature",
  "properties": {
    "iso:country":"GB",
    "wof:name":"M24 2NR",
    "wof:placetype":"postalcode"
},
  "geometry": {"coordinates":[-2.17972362106291,53.56199261940876],"type":"Point"}
}