{
  "type": "Feature",
  "properties": {
    "iso:country": "GB",
    "wof:name": "M24 2NR",
    "wof:placetype": "postalcode"
  },
  "geometry": {"coordinates":[-2.179724,53.561993],"type":"Point"}
}
