{
  "type": "Feature",
  "properties": {
    "date:inception_lower": "1994-05-01",
    "date:inception_upper": "1994-05-01",
    "iso:country": "GB",
    "wof:name": "M23 2RF",
    "wof:placetype": "postalcode"
  },
  "geometry": {"coordinates":[-2.284979,53.386351],"type":"Point"}
}
