{
  "type": "Feature",
  "properties": {
    "iso:country": "GB",
    "wof:name": "PE8 4DH",
    "wof:placetype": "postalcode"
  },
  "geometry": {"coordinates":[-0.473178,52.480146],"type":"Point"}
}
