{
  "type": "Feature",
  "properties": {
    "iso:country": "GB",
    "wof:name": "M16 0GZ",
    "wof:placetype": "postalcode"
  },
  "geometry": {"coordinates":[-2.28467,53.454952],"type":"Point"}
}
