{
  "type": "Feature",
  "properties": {
    "date:inception_lower": "1994-05-01",
    "date:inception_upper": "1994-05-01",
    "iso:country": "GB",
    "wof:name": "M16 0GZ",
    "wof:placetype": "postalcode"
  },
  "geometry": {"coordinates":[-2.28467,53.454952],"type":"Point"}
}
