{
  "type": "Feature",
  "properties": {
    "iso:country":"GB",
    "wof:name":"M16 0GZ",
    "wof:placetype":"postalcode"
},
  "geometry": {"coordinates":[-2.28467002678689,53.45495225734583],"type":"Point"}
}