{
  "type": "Feature",
  "properties": {
    "date:inception_lower": "1994-05-01",
    "date:inception_upper": "1994-05-01",
    "iso:country": "GB",
    "wof:name": "M41 9BP",
    "wof:placetype": "postalcode"
  },
  "geometry": {"coordinates":[-2.351743,53.447707],"type":"Point"}
}
