{
  "type": "Feature",
  "properties": {
    "iso:country":"GB",
    "wof:name":"M41 9BP",
    "wof:placetype":"postalcode"
},
  "geometry": {"coordinates":[-2.35177457348239,53.44774436000031],"type":"Point"}
}