{
  "type": "Feature",
  "properties": {
    "date:inception_lower": "1980-01-01",
    "date:inception_upper": "1980-01-01",
    "iso:country": "GB",
    "wof:name": "EN11 9AY",
    "wof:placetype": "postalcode"
  },
  "geometry": {"coordinates":[-0.018914,51.7723],"type":"Point"}
}
