{
  "type": "Feature",
  "properties": {
    "iso:country":"GB",
    "wof:name":"TF2 7LR",
    "wof:placetype":"postalcode"
},
  "geometry": {"coordinates":[-2.43834659707127,52.71296624275524],"type":"Point"}
}