{
  "type": "Feature",
  "properties": {
    "date:inception_lower": "1980-01-01",
    "date:inception_upper": "1980-01-01",
    "iso:country": "GB",
    "wof:name": "TF2 7LR",
    "wof:placetype": "postalcode"
  },
  "geometry": {"coordinates":[-2.438347,52.712966],"type":"Point"}
}
