{
  "type": "Feature",
  "properties": {
    "iso:country":"GB",
    "wof:name":"CR2 0EQ",
    "wof:placetype":"postalcode"
},
  "geometry": {"coordinates":[-0.08378911200556,51.34506267052164],"type":"Point"}
}