{
  "type": "Feature",
  "properties": {
    "iso:country":"GB",
    "wof:name":"WF10 2AW",
    "wof:placetype":"postalcode"
},
  "geometry": {"coordinates":[-1.35582469114775,53.74556377569219],"type":"Point"}
}