{
  "type": "Feature",
  "properties": {
    "iso:country":"GB",
    "wof:name":"TS13 4QN",
    "wof:placetype":"postalcode"
},
  "geometry": {"coordinates":[-0.89822440808646,54.55121018281393],"type":"Point"}
}