{
  "type": "Feature",
  "properties": {
    "iso:country":"GB",
    "wof:name":"DT6 6NP",
    "wof:placetype":"postalcode"
},
  "geometry": {"coordinates":[-2.90463424859939,50.77671661967759],"type":"Point"}
}