{
  "type": "Feature",
  "properties": {
    "iso:country": "GB",
    "wof:name": "DT6 6NP",
    "wof:placetype": "postalcode"
  },
  "geometry": {"coordinates":[-2.904638,50.776688],"type":"Point"}
}
