{
  "type": "Feature",
  "properties": {
    "iso:country": "GB",
    "wof:name": "PL3 6AR",
    "wof:placetype": "postalcode"
  },
  "geometry": {"coordinates":[-4.10445,50.38431],"type":"Point"}
}
