{
  "type": "Feature",
  "properties": {
    "iso:country":"GB",
    "wof:name":"PL3 6AR",
    "wof:placetype":"postalcode"
},
  "geometry": {"coordinates":[-4.10444960389903,50.38431008831056],"type":"Point"}
}