{
  "type": "Feature",
  "properties": {
    "iso:country": "GB",
    "wof:name": "GU4 7NX",
    "wof:placetype": "postalcode"
  },
  "geometry": {"coordinates":[-0.570382,51.267978],"type":"Point"}
}
