{
  "type": "Feature",
  "properties": {
    "iso:country":"GB",
    "wof:name":"DL1 2JD",
    "wof:placetype":"postalcode"
},
  "geometry": {"coordinates":[-1.5497790235423,54.5374138450587],"type":"Point"}
}