{
  "type": "Feature",
  "properties": {
    "iso:country": "GB",
    "wof:name": "DL1 2JD",
    "wof:placetype": "postalcode"
  },
  "geometry": {"coordinates":[-1.549779,54.537414],"type":"Point"}
}
