{
  "type": "Feature",
  "properties": {
    "date:inception_lower": "1993-08-01",
    "date:inception_upper": "1993-08-01",
    "iso:country": "GB",
    "wof:name": "NG12 5QY",
    "wof:placetype": "postalcode"
  },
  "geometry": {"coordinates":[-1.10395,52.836826],"type":"Point"}
}
