{
  "type": "Feature",
  "properties": {
    "iso:country":"GB",
    "wof:name":"NG12 5QY",
    "wof:placetype":"postalcode"
},
  "geometry": {"coordinates":[-1.10395011422432,52.83682636618762],"type":"Point"}
}