{
  "type": "Feature",
  "properties": {
    "iso:country": "GB",
    "wof:name": "SP5 1LA",
    "wof:placetype": "postalcode"
  },
  "geometry": {"coordinates":[-1.608868,51.062338],"type":"Point"}
}
