{
  "type": "Feature",
  "properties": {
    "date:inception_lower": "1980-01-01",
    "date:inception_upper": "1980-01-01",
    "iso:country": "GB",
    "wof:name": "DA14 4AR",
    "wof:placetype": "postalcode"
  },
  "geometry": {"coordinates":[0.103248,51.428915],"type":"Point"}
}
