{
  "type": "Feature",
  "properties": {
    "iso:country":"GB",
    "wof:name":"DE11 0TB",
    "wof:placetype":"postalcode"
},
  "geometry": {"coordinates":[-1.58187601029597,52.77813498707572],"type":"Point"}
}