{
  "type": "Feature",
  "properties": {
    "iso:country": "GB",
    "wof:name": "DE11 0TB",
    "wof:placetype": "postalcode"
  },
  "geometry": {"coordinates":[-1.581876,52.778135],"type":"Point"}
}
