{
  "type": "Feature",
  "properties": {
    "date:inception_lower": "1981-06-01",
    "date:inception_upper": "1981-06-01",
    "iso:country": "GB",
    "wof:name": "SS13 1LG",
    "wof:placetype": "postalcode"
  },
  "geometry": {"coordinates":[0.514958,51.584283],"type":"Point"}
}
