{
  "type": "Feature",
  "properties": {
    "iso:country":"GB",
    "wof:name":"SS13 1LG",
    "wof:placetype":"postalcode"
},
  "geometry": {"coordinates":[0.51495768933497,51.58428314534105],"type":"Point"}
}