{
  "type": "Feature",
  "properties": {
    "iso:country": "GB",
    "wof:name": "HU9 5RG",
    "wof:placetype": "postalcode"
  },
  "geometry": {"coordinates":[-0.272735,53.748333],"type":"Point"}
}
