{
  "type": "Feature",
  "properties": {
    "iso:country":"GB",
    "wof:name":"HU9 5RG",
    "wof:placetype":"postalcode"
},
  "geometry": {"coordinates":[-0.27273470519398,53.74833345724124],"type":"Point"}
}