{
  "type": "Feature",
  "properties": {
    "iso:country":"GB",
    "wof:name":"NP25 3JZ",
    "wof:placetype":"postalcode"
},
  "geometry": {"coordinates":[-2.70145464172049,51.80741323817692],"type":"Point"}
}