{
  "type": "Feature",
  "properties": {
    "iso:country":"GB",
    "wof:name":"LS15 4JX",
    "wof:placetype":"postalcode"
},
  "geometry": {"coordinates":[-1.39563461639313,53.82962121185616],"type":"Point"}
}