{
  "type": "Feature",
  "properties": {
    "iso:country": "GB",
    "wof:name": "BS7 9JS",
    "wof:placetype": "postalcode"
  },
  "geometry": {"coordinates":[-2.581876,51.48079],"type":"Point"}
}
