{
  "type": "Feature",
  "properties": {
    "iso:country":"GB",
    "wof:name":"BS7 9JS",
    "wof:placetype":"postalcode"
},
  "geometry": {"coordinates":[-2.58187608598265,51.48078992945356],"type":"Point"}
}