{
  "type": "Feature",
  "properties": {
    "date:inception_lower": "1980-01-01",
    "date:inception_upper": "1980-01-01",
    "iso:country": "GB",
    "wof:name": "DL16 6NW",
    "wof:placetype": "postalcode"
  },
  "geometry": {"coordinates":[-1.597717,54.69806],"type":"Point"}
}
