{
  "type": "Feature",
  "properties": {
    "iso:country":"GB",
    "wof:name":"DL16 6NW",
    "wof:placetype":"postalcode"
},
  "geometry": {"coordinates":[-1.59771657223258,54.6980598783775],"type":"Point"}
}