{
  "type": "Feature",
  "properties": {
    "iso:country":"GB",
    "wof:name":"M9 8JB",
    "wof:placetype":"postalcode"
},
  "geometry": {"coordinates":[-2.22808637748018,53.52674761409069],"type":"Point"}
}