{
  "type": "Feature",
  "properties": {
    "iso:country": "GB",
    "wof:name": "TN29 9NY",
    "wof:placetype": "postalcode"
  },
  "geometry": {"coordinates":[0.962179,50.945554],"type":"Point"}
}
