{
  "type": "Feature",
  "properties": {
    "iso:country":"GB",
    "wof:name":"TN29 9NY",
    "wof:placetype":"postalcode"
},
  "geometry": {"coordinates":[0.96228094830715,50.94548794691502],"type":"Point"}
}