{
  "type": "Feature",
  "properties": {
    "iso:country":"GB",
    "wof:name":"NP19 9BB",
    "wof:placetype":"postalcode"
},
  "geometry": {"coordinates":[-2.94356651218138,51.59420466817929],"type":"Point"}
}