{
  "type": "Feature",
  "properties": {
    "iso:country":"GB",
    "wof:name":"KT19 8LZ",
    "wof:placetype":"postalcode"
},
  "geometry": {"coordinates":[-0.28352207334087,51.33935612835138],"type":"Point"}
}