{
  "type": "Feature",
  "properties": {
    "iso:country":"GB",
    "wof:name":"YO16 4DL",
    "wof:placetype":"postalcode"
},
  "geometry": {"coordinates":[-0.19227407833477,54.08963309480117],"type":"Point"}
}