{
  "type": "Feature",
  "properties": {
    "iso:country": "GB",
    "wof:name": "SY22 6BT",
    "wof:placetype": "postalcode"
  },
  "geometry": {"coordinates":[-3.243686,52.718319],"type":"Point"}
}
