{
  "type": "Feature",
  "properties": {
    "iso:country":"GB",
    "wof:name":"NG5 8AB",
    "wof:placetype":"postalcode"
},
  "geometry": {"coordinates":[-1.11109508906181,53.00586615608606],"type":"Point"}
}