{
  "type": "Feature",
  "properties": {
    "iso:country": "GB",
    "wof:name": "N15 4JR",
    "wof:placetype": "postalcode"
  },
  "geometry": {"coordinates":[-0.078706,51.589103],"type":"Point"}
}
