{
  "type": "Feature",
  "properties": {
    "iso:country":"GB",
    "wof:name":"MK19 6DH",
    "wof:placetype":"postalcode"
},
  "geometry": {"coordinates":[-0.86356886128903,52.04745566150589],"type":"Point"}
}