{
  "type": "Feature",
  "properties": {
    "date:inception_lower": "1980-01-01",
    "date:inception_upper": "1980-01-01",
    "iso:country": "GB",
    "wof:name": "MK19 6DH",
    "wof:placetype": "postalcode"
  },
  "geometry": {"coordinates":[-0.863569,52.047456],"type":"Point"}
}
