{
  "type": "Feature",
  "properties": {
    "iso:country":"GB",
    "wof:name":"BB11 4JL",
    "wof:placetype":"postalcode"
},
  "geometry": {"coordinates":[-2.25477527611646,53.78314492168695],"type":"Point"}
}