{
  "type": "Feature",
  "properties": {
    "iso:country":"GB",
    "wof:name":"UB7 7RN",
    "wof:placetype":"postalcode"
},
  "geometry": {"coordinates":[-0.47589485428503,51.51479475493961],"type":"Point"}
}