{
  "type": "Feature",
  "properties": {
    "iso:country":"GB",
    "wof:name":"BS22 9HE",
    "wof:placetype":"postalcode"
},
  "geometry": {"coordinates":[-2.93098405763696,51.35975499246327],"type":"Point"}
}