{
  "type": "Feature",
  "properties": {
    "iso:country": "GB",
    "wof:name": "BS22 9HE",
    "wof:placetype": "postalcode"
  },
  "geometry": {"coordinates":[-2.930946,51.359761],"type":"Point"}
}
