{
  "type": "Feature",
  "properties": {
    "iso:country":"GB",
    "wof:name":"RM3 8HP",
    "wof:placetype":"postalcode"
},
  "geometry": {"coordinates":[0.21975626209718,51.60603081612663],"type":"Point"}
}