{
  "type": "Feature",
  "properties": {
    "iso:country":"GB",
    "wof:name":"CV1 4BQ",
    "wof:placetype":"postalcode"
},
  "geometry": {"coordinates":[-1.51440833829037,52.41481355247185],"type":"Point"}
}