{
  "type": "Feature",
  "properties": {
    "iso:country":"GB",
    "wof:name":"GU51 3RW",
    "wof:placetype":"postalcode"
},
  "geometry": {"coordinates":[-0.83836727245455,51.28309196980209],"type":"Point"}
}