{
  "type": "Feature",
  "properties": {
    "iso:country":"GB",
    "wof:name":"LE15 9AP",
    "wof:placetype":"postalcode"
},
  "geometry": {"coordinates":[-0.7439105958723,52.61621746601056],"type":"Point"}
}