{
  "type": "Feature",
  "properties": {
    "date:inception_lower": "1980-01-01",
    "date:inception_upper": "1980-01-01",
    "iso:country": "GB",
    "wof:name": "LE15 9AP",
    "wof:placetype": "postalcode"
  },
  "geometry": {"coordinates":[-0.743911,52.616217],"type":"Point"}
}
