{
  "type": "Feature",
  "properties": {
    "iso:country": "GB",
    "wof:name": "WS5 3DB",
    "wof:placetype": "postalcode"
  },
  "geometry": {"coordinates":[-1.940559,52.578845],"type":"Point"}
}
