{
  "type": "Feature",
  "properties": {
    "iso:country":"GB",
    "wof:name":"WS5 3DB",
    "wof:placetype":"postalcode"
},
  "geometry": {"coordinates":[-1.94055900675336,52.57884516027546],"type":"Point"}
}