{
  "type": "Feature",
  "properties": {
    "iso:country":"GB",
    "wof:name":"CF81 8JX",
    "wof:placetype":"postalcode"
},
  "geometry": {"coordinates":[-3.22762234666611,51.67563151667784],"type":"Point"}
}