{
  "type": "Feature",
  "properties": {
    "date:inception_lower": "1995-07-01",
    "date:inception_upper": "1995-07-01",
    "iso:country": "GB",
    "wof:name": "CF81 8JX",
    "wof:placetype": "postalcode"
  },
  "geometry": {"coordinates":[-3.227622,51.675632],"type":"Point"}
}
