{
  "type": "Feature",
  "properties": {
    "iso:country": "GB",
    "wof:name": "YO7 3DS",
    "wof:placetype": "postalcode"
  },
  "geometry": {"coordinates":[-1.403027,54.133087],"type":"Point"}
}
