{
  "type": "Feature",
  "properties": {
    "iso:country":"GB",
    "wof:name":"YO7 3DS",
    "wof:placetype":"postalcode"
},
  "geometry": {"coordinates":[-1.40302740525204,54.13308730091541],"type":"Point"}
}