{
  "type": "Feature",
  "properties": {
    "date:inception_lower": "1980-01-01",
    "date:inception_upper": "1980-01-01",
    "iso:country": "GB",
    "wof:name": "SY7 9LL",
    "wof:placetype": "postalcode"
  },
  "geometry": {"coordinates":[-2.778063,52.44035],"type":"Point"}
}
