{
  "type": "Feature",
  "properties": {
    "iso:country":"GB",
    "wof:name":"AB37 9DT",
    "wof:placetype":"postalcode"
},
  "geometry": {"coordinates":[-3.3102681689008,57.35825821110809],"type":"Point"}
}