{
  "type": "Feature",
  "properties": {
    "iso:country": "GB",
    "wof:name": "PR4 0FG",
    "wof:placetype": "postalcode"
  },
  "geometry": {"coordinates":[-2.759739,53.789634],"type":"Point"}
}
