{
  "type": "Feature",
  "properties": {
    "iso:country":"GB",
    "wof:name":"DN18 5LF",
    "wof:placetype":"postalcode"
},
  "geometry": {"coordinates":[-0.44789633666527,53.68377920618368],"type":"Point"}
}