{
  "type": "Feature",
  "properties": {
    "iso:country":"GB",
    "wof:name":"TQ7 3AE",
    "wof:placetype":"postalcode"
},
  "geometry": {"coordinates":[-3.8590172036465,50.27871086194257],"type":"Point"}
}