{
  "type": "Feature",
  "properties": {
    "date:inception_lower":"1980-01-01",
    "date:inception_upper":"1980-01-31",
    "iso:country":"GB",
    "wof:name":"TQ7 3AE",
    "wof:placetype":"postalcode"
},
  "geometry": {"coordinates":[-3.859017,50.278711],"type":"Point"}
}