{
  "type": "Feature",
  "properties": {
    "date:inception_lower": "2022-11-01",
    "date:inception_upper": "2022-11-01",
    "iso:country": "GB",
    "wof:name": "SK7 3EG",
    "wof:placetype": "postalcode"
  },
  "geometry": {"coordinates":[-2.146732,53.377953],"type":"Point"}
}
