{
  "type": "Feature",
  "properties": {
    "iso:country":"GB",
    "wof:name":"BB4 4BW",
    "wof:placetype":"postalcode"
},
  "geometry": {"coordinates":[-2.32630005050338,53.69879805255756],"type":"Point"}
}