{
  "type": "Feature",
  "properties": {
    "iso:country":"GB",
    "wof:name":"NG18 4PF",
    "wof:placetype":"postalcode"
},
  "geometry": {"coordinates":[-1.17194079325477,53.12431712773263],"type":"Point"}
}