{
  "type": "Feature",
  "properties": {
    "date:inception_lower": "1980-01-01",
    "date:inception_upper": "1980-01-01",
    "iso:country": "GB",
    "wof:name": "NG18 4PF",
    "wof:placetype": "postalcode"
  },
  "geometry": {"coordinates":[-1.171941,53.124317],"type":"Point"}
}
