{
  "type": "Feature",
  "properties": {
    "date:inception_lower": "2002-06-01",
    "date:inception_upper": "2002-06-01",
    "iso:country": "GB",
    "wof:name": "CO3 0YW",
    "wof:placetype": "postalcode"
  },
  "geometry": {"coordinates":[0.846105,51.881179],"type":"Point"}
}
