{
  "type": "Feature",
  "properties": {
    "iso:country": "GB",
    "wof:name": "CF72 9NF",
    "wof:placetype": "postalcode"
  },
  "geometry": {"coordinates":[-3.420589,51.51482],"type":"Point"}
}
