{
  "type": "Feature",
  "properties": {
    "iso:country":"GB",
    "wof:name":"NE63 9SU",
    "wof:placetype":"postalcode"
},
  "geometry": {"coordinates":[-1.54440676008873,55.17161362062733],"type":"Point"}
}