{
  "type": "Feature",
  "properties": {
    "iso:country": "GB",
    "wof:name": "SG8 8RA",
    "wof:placetype": "postalcode"
  },
  "geometry": {"coordinates":[0.110969,52.017203],"type":"Point"}
}
