{
  "type": "Feature",
  "properties": {
    "iso:country": "GB",
    "wof:name": "SG8 8RA",
    "wof:placetype": "postalcode"
  },
  "geometry": {"coordinates":[0.111726,52.017505],"type":"Point"}
}
