{
  "type": "Feature",
  "properties": {
    "iso:country":"GB",
    "wof:name":"SG8 8RA",
    "wof:placetype":"postalcode"
},
  "geometry": {"coordinates":[0.11094231618659,52.01719333478341],"type":"Point"}
}