{
  "type": "Feature",
  "properties": {
    "iso:country":"GB",
    "wof:name":"N9 8AG",
    "wof:placetype":"postalcode"
},
  "geometry": {"coordinates":[-0.04803576452304,51.63876556507036],"type":"Point"}
}