{
  "type": "Feature",
  "properties": {
    "date:inception_lower": "2023-01-01",
    "date:inception_upper": "2023-01-01",
    "iso:country": "GB",
    "wof:name": "OL9 9GF",
    "wof:placetype": "postalcode"
  },
  "geometry": {"coordinates":[-2.152042,53.539154],"type":"Point"}
}
