{
  "type": "Feature",
  "properties": {
    "iso:country": "GB",
    "wof:name": "SL4 4NG",
    "wof:placetype": "postalcode"
  },
  "geometry": {"coordinates":[-0.643554,51.475769],"type":"Point"}
}
