{
  "type": "Feature",
  "properties": {
    "iso:country":"GB",
    "wof:name":"SL4 4NG",
    "wof:placetype":"postalcode"
},
  "geometry": {"coordinates":[-0.64355368074475,51.47576854934549],"type":"Point"}
}