{
  "type": "Feature",
  "properties": {
    "date:inception_lower": "1980-01-01",
    "date:inception_upper": "1980-01-01",
    "iso:country": "GB",
    "wof:name": "SE16 2PP",
    "wof:placetype": "postalcode"
  },
  "geometry": {"coordinates":[-0.047476,51.492843],"type":"Point"}
}
