{
  "type": "Feature",
  "properties": {
    "iso:country": "GB",
    "wof:name": "NG5 5FN",
    "wof:placetype": "postalcode"
  },
  "geometry": {"coordinates":[-1.171806,52.993602],"type":"Point"}
}
