{
  "type": "Feature",
  "properties": {
    "iso:country":"GB",
    "wof:name":"NG5 5FN",
    "wof:placetype":"postalcode"
},
  "geometry": {"coordinates":[-1.17180556369229,52.99360227709841],"type":"Point"}
}