{
  "type": "Feature",
  "properties": {
    "iso:country":"GB",
    "wof:name":"IG6 1DU",
    "wof:placetype":"postalcode"
},
  "geometry": {"coordinates":[0.07968675185731,51.58208607101363],"type":"Point"}
}