{
  "type": "Feature",
  "properties": {
    "iso:country":"GB",
    "wof:name":"CR0 8HZ",
    "wof:placetype":"postalcode"
},
  "geometry": {"coordinates":[-0.03003926926098,51.36320883584057],"type":"Point"}
}