{
  "type": "Feature",
  "properties": {
    "iso:country": "GB",
    "wof:name": "CR0 8HZ",
    "wof:placetype": "postalcode"
  },
  "geometry": {"coordinates":[-0.030039,51.363209],"type":"Point"}
}
