{
  "type": "Feature",
  "properties": {
    "iso:country": "GB",
    "wof:name": "KA22 7PR",
    "wof:placetype": "postalcode"
  },
  "geometry": {"coordinates":[-4.796326,55.65136],"type":"Point"}
}
