{
  "type": "Feature",
  "properties": {
    "iso:country":"GB",
    "wof:name":"KA22 7PR",
    "wof:placetype":"postalcode"
},
  "geometry": {"coordinates":[-4.79632592511614,55.65136024703738],"type":"Point"}
}