{
  "type": "Feature",
  "properties": {
    "iso:country":"GB",
    "wof:name":"S44 6RT",
    "wof:placetype":"postalcode"
},
  "geometry": {"coordinates":[-1.29951559658941,53.23363394306014],"type":"Point"}
}