{
  "type": "Feature",
  "properties": {
    "iso:country":"GB",
    "wof:name":"HU4 6AP",
    "wof:placetype":"postalcode"
},
  "geometry": {"coordinates":[-0.40494875986648,53.74556350522618],"type":"Point"}
}