{
  "type": "Feature",
  "properties": {
    "iso:country":"GB",
    "wof:name":"ST6 2BS",
    "wof:placetype":"postalcode"
},
  "geometry": {"coordinates":[-2.18745000614571,53.04110239287584],"type":"Point"}
}