{
  "type": "Feature",
  "properties": {
    "iso:country": "GB",
    "wof:name": "ST6 2BS",
    "wof:placetype": "postalcode"
  },
  "geometry": {"coordinates":[-2.187361,53.041201],"type":"Point"}
}
