{
  "type": "Feature",
  "properties": {
    "date:inception_lower": "1980-01-01",
    "date:inception_upper": "1980-01-01",
    "iso:country": "GB",
    "wof:name": "CM8 3HZ",
    "wof:placetype": "postalcode"
  },
  "geometry": {"coordinates":[0.628648,51.773951],"type":"Point"}
}
