{
  "type": "Feature",
  "properties": {
    "iso:country":"GB",
    "wof:name":"CM8 3HZ",
    "wof:placetype":"postalcode"
},
  "geometry": {"coordinates":[0.62913476744353,51.77430994966846],"type":"Point"}
}