{
  "type": "Feature",
  "properties": {
    "iso:country":"GB",
    "wof:name":"SK14 2QB",
    "wof:placetype":"postalcode"
},
  "geometry": {"coordinates":[-2.06603855417065,53.45350286978569],"type":"Point"}
}