{
  "type": "Feature",
  "properties": {
    "date:inception_lower": "1990-08-01",
    "date:inception_upper": "1990-08-01",
    "iso:country": "GB",
    "wof:name": "AB51 0AU",
    "wof:placetype": "postalcode"
  },
  "geometry": {"coordinates":[-2.313036,57.356913],"type":"Point"}
}
