{
  "type": "Feature",
  "properties": {
    "iso:country":"GB",
    "wof:name":"E2 6PP",
    "wof:placetype":"postalcode"
},
  "geometry": {"coordinates":[-0.0629127055891,51.52866498643238],"type":"Point"}
}