{
  "type": "Feature",
  "properties": {
    "iso:country": "GB",
    "wof:name": "E2 6PP",
    "wof:placetype": "postalcode"
  },
  "geometry": {"coordinates":[-0.062913,51.528665],"type":"Point"}
}
