{
  "type": "Feature",
  "properties": {
    "iso:country":"GB",
    "wof:name":"M32 8QL",
    "wof:placetype":"postalcode"
},
  "geometry": {"coordinates":[-2.29336721226717,53.44956505903058],"type":"Point"}
}