{
  "type": "Feature",
  "properties": {
    "iso:country":"GB",
    "wof:name":"NE62 5HF",
    "wof:placetype":"postalcode"
},
  "geometry": {"coordinates":[-1.60085571094708,55.1659524734911],"type":"Point"}
}