{
  "type": "Feature",
  "properties": {
    "date:inception_lower":"1980-01-01",
    "date:inception_upper":"1980-01-31",
    "iso:country":"GB",
    "wof:name":"HU9 3JG",
    "wof:placetype":"postalcode"
},
  "geometry": {"coordinates":[-0.287853,53.763679],"type":"Point"}
}