{
  "type": "Feature",
  "properties": {
    "iso:country":"GB",
    "wof:name":"AB15 6HL",
    "wof:placetype":"postalcode"
},
  "geometry": {"coordinates":[-2.15057234493003,57.14763944771406],"type":"Point"}
}