{
  "type": "Feature",
  "properties": {
    "date:inception_lower":"1980-01-01",
    "date:inception_upper":"1980-01-31",
    "iso:country":"GB",
    "wof:name":"ST18 0SR",
    "wof:placetype":"postalcode"
},
  "geometry": {"coordinates":[-2.005416,52.802019],"type":"Point"}
}