{
  "type": "Feature",
  "properties": {
    "date:inception_lower": "2019-01-01",
    "date:inception_upper": "2019-01-01",
    "iso:country": "GB",
    "wof:name": "BH24 3FQ",
    "wof:placetype": "postalcode"
  },
  "geometry": {"coordinates":[-1.773617,50.840311],"type":"Point"}
}
