{
  "type": "Feature",
  "properties": {
    "iso:country": "GB",
    "wof:name": "LE15 9BT",
    "wof:placetype": "postalcode"
  },
  "geometry": {"coordinates":[-0.675002,52.595292],"type":"Point"}
}
