{
  "type": "Feature",
  "properties": {
    "iso:country":"GB",
    "wof:name":"LE15 9BT",
    "wof:placetype":"postalcode"
},
  "geometry": {"coordinates":[-0.67500158508789,52.59529239123427],"type":"Point"}
}