{
  "type": "Feature",
  "properties": {
    "date:inception_lower":"1980-01-01",
    "date:inception_upper":"1980-01-31",
    "iso:country":"GB",
    "wof:name":"LE15 9BT",
    "wof:placetype":"postalcode"
},
  "geometry": {"coordinates":[-0.675002,52.595292],"type":"Point"}
}