{
  "type": "Feature",
  "properties": {
    "iso:country": "GB",
    "wof:name": "DA2 7HH",
    "wof:placetype": "postalcode"
  },
  "geometry": {"coordinates":[0.166048,51.413768],"type":"Point"}
}
