{
  "type": "Feature",
  "properties": {
    "date:inception_lower":"1980-01-01",
    "date:inception_upper":"1980-01-31",
    "iso:country":"GB",
    "wof:name":"DA2 7HH",
    "wof:placetype":"postalcode"
},
  "geometry": {"coordinates":[0.166048,51.413768],"type":"Point"}
}