{
  "type": "Feature",
  "properties": {
    "iso:country":"GB",
    "wof:name":"DA2 7HH",
    "wof:placetype":"postalcode"
},
  "geometry": {"coordinates":[0.16604837588992,51.41376814943283],"type":"Point"}
}