{
  "type": "Feature",
  "properties": {
    "iso:country":"GB",
    "wof:name":"WN7 3LS",
    "wof:placetype":"postalcode"
},
  "geometry": {"coordinates":[-2.52606059291188,53.48218607233358],"type":"Point"}
}