{
  "type": "Feature",
  "properties": {
    "iso:country": "GB",
    "wof:name": "BS40 5DF",
    "wof:placetype": "postalcode"
  },
  "geometry": {"coordinates":[-2.755482,51.335733],"type":"Point"}
}
