{
  "type": "Feature",
  "properties": {
    "iso:country":"GB",
    "wof:name":"BS40 5DF",
    "wof:placetype":"postalcode"
},
  "geometry": {"coordinates":[-2.75548168496708,51.33573339874938],"type":"Point"}
}