{
  "type": "Feature",
  "properties": {
    "date:inception_lower": "2002-05-01",
    "date:inception_upper": "2002-05-01",
    "iso:country": "GB",
    "wof:name": "SY4 4SF",
    "wof:placetype": "postalcode"
  },
  "geometry": {"coordinates":[-2.69894,52.720005],"type":"Point"}
}
