{
  "type": "Feature",
  "properties": {
    "iso:country": "GB",
    "wof:name": "SY4 4SF",
    "wof:placetype": "postalcode"
  },
  "geometry": {"coordinates":[-2.69894,52.720005],"type":"Point"}
}
