{
  "type": "Feature",
  "properties": {
    "iso:country":"GB",
    "wof:name":"KA6 7TD",
    "wof:placetype":"postalcode"
},
  "geometry": {"coordinates":[-4.39848670833828,55.31552705508353],"type":"Point"}
}