{
  "type": "Feature",
  "properties": {
    "iso:country": "GB",
    "wof:name": "KA6 7TD",
    "wof:placetype": "postalcode"
  },
  "geometry": {"coordinates":[-4.398487,55.315527],"type":"Point"}
}
