{
  "type": "Feature",
  "properties": {
    "date:inception_lower": "1997-12-01",
    "date:inception_upper": "1997-12-01",
    "iso:country": "GB",
    "wof:name": "BS20 6RH",
    "wof:placetype": "postalcode"
  },
  "geometry": {"coordinates":[-2.775393,51.475983],"type":"Point"}
}
