{
  "type": "Feature",
  "properties": {
    "iso:country": "GB",
    "wof:name": "WN1 1PL",
    "wof:placetype": "postalcode"
  },
  "geometry": {"coordinates":[-2.631815,53.54708],"type":"Point"}
}
