{
  "type": "Feature",
  "properties": {
    "iso:country":"GB",
    "wof:name":"W1J 7EL",
    "wof:placetype":"postalcode"
},
  "geometry": {"coordinates":[-0.14524543320869,51.50673212665522],"type":"Point"}
}