{
  "type": "Feature",
  "properties": {
    "iso:country": "GB",
    "wof:name": "B92 0JZ",
    "wof:placetype": "postalcode"
  },
  "geometry": {"coordinates":[-1.693601,52.400157],"type":"Point"}
}
