{
  "type": "Feature",
  "properties": {
    "iso:country":"GB",
    "wof:name":"B92 0JZ",
    "wof:placetype":"postalcode"
},
  "geometry": {"coordinates":[-1.69360060476907,52.40015706734196],"type":"Point"}
}