{
  "type": "Feature",
  "properties": {
    "date:inception_lower":"1980-01-01",
    "date:inception_upper":"1980-01-31",
    "iso:country":"GB",
    "wof:name":"B92 0JZ",
    "wof:placetype":"postalcode"
},
  "geometry": {"coordinates":[-1.693601,52.400157],"type":"Point"}
}