{
  "type": "Feature",
  "properties": {
    "iso:country": "GB",
    "wof:name": "WN7 2NS",
    "wof:placetype": "postalcode"
  },
  "geometry": {"coordinates":[-2.479137,53.491651],"type":"Point"}
}
