{
  "type": "Feature",
  "properties": {
    "date:inception_lower": "1980-01-01",
    "date:inception_upper": "1980-01-01",
    "iso:country": "GB",
    "wof:name": "WN7 2NS",
    "wof:placetype": "postalcode"
  },
  "geometry": {"coordinates":[-2.479137,53.491651],"type":"Point"}
}
