{
  "type": "Feature",
  "properties": {
    "iso:country":"GB",
    "wof:name":"AL5 2JU",
    "wof:placetype":"postalcode"
},
  "geometry": {"coordinates":[-0.3582441325206,51.80138492859453],"type":"Point"}
}