{
  "type": "Feature",
  "properties": {
    "iso:country": "GB",
    "wof:name": "BD23 4BN",
    "wof:placetype": "postalcode"
  },
  "geometry": {"coordinates":[-2.155639,54.050922],"type":"Point"}
}
