{
  "type": "Feature",
  "properties": {
    "iso:country":"GB",
    "wof:name":"BS5 7LW",
    "wof:placetype":"postalcode"
},
  "geometry": {"coordinates":[-2.53505703431625,51.45955004011577],"type":"Point"}
}