{
  "type": "Feature",
  "properties": {
    "iso:country": "GB",
    "wof:name": "BA21 5FJ",
    "wof:placetype": "postalcode"
  },
  "geometry": {"coordinates":[-2.606837,50.957571],"type":"Point"}
}
