{
  "type": "Feature",
  "properties": {
    "iso:country":"GB",
    "wof:name":"BA21 5FJ",
    "wof:placetype":"postalcode"
},
  "geometry": {"coordinates":[-2.60683694746506,50.9575714010534],"type":"Point"}
}