{
  "type": "Feature",
  "properties": {
    "date:inception_lower": "2012-02-01",
    "date:inception_upper": "2012-02-01",
    "iso:country": "GB",
    "wof:name": "BA21 5FJ",
    "wof:placetype": "postalcode"
  },
  "geometry": {"coordinates":[-2.606837,50.957571],"type":"Point"}
}
