{
  "type": "Feature",
  "properties": {
    "iso:country": "GB",
    "wof:name": "LL21 0SQ",
    "wof:placetype": "postalcode"
  },
  "geometry": {"coordinates":[-3.434789,52.92271],"type":"Point"}
}
