{
  "type": "Feature",
  "properties": {
    "iso:country": "GB",
    "wof:name": "PE9 3TN",
    "wof:placetype": "postalcode"
  },
  "geometry": {"coordinates":[-0.549839,52.634032],"type":"Point"}
}
