{
  "type": "Feature",
  "properties": {
    "iso:country":"GB",
    "wof:name":"NE1 7XZ",
    "wof:placetype":"postalcode"
},
  "geometry": {"coordinates":[-1.6161335393381,54.97395014954461],"type":"Point"}
}