{
  "type": "Feature",
  "properties": {
    "iso:country":"GB",
    "wof:name":"CF83 8EP",
    "wof:placetype":"postalcode"
},
  "geometry": {"coordinates":[-3.21110547234362,51.59425716340162],"type":"Point"}
}