{
  "type": "Feature",
  "properties": {
    "iso:country":"GB",
    "wof:name":"EX4 0BD",
    "wof:placetype":"postalcode"
},
  "geometry": {"coordinates":[-3.46549932706567,50.76160947544938],"type":"Point"}
}