{
  "type": "Feature",
  "properties": {
    "iso:country": "GB",
    "wof:name": "L35 6PQ",
    "wof:placetype": "postalcode"
  },
  "geometry": {"coordinates":[-2.749689,53.408031],"type":"Point"}
}
