{
  "type": "Feature",
  "properties": {
    "iso:country":"GB",
    "wof:name":"L35 6PQ",
    "wof:placetype":"postalcode"
},
  "geometry": {"coordinates":[-2.74968951545092,53.40803063990915],"type":"Point"}
}