{
  "type": "Feature",
  "properties": {
    "date:inception_lower": "1980-01-01",
    "date:inception_upper": "1980-01-01",
    "iso:country": "GB",
    "wof:name": "L35 6PQ",
    "wof:placetype": "postalcode"
  },
  "geometry": {"coordinates":[-2.749689,53.408031],"type":"Point"}
}
