{
  "type": "Feature",
  "properties": {
    "iso:country":"GB",
    "wof:name":"SG6 2LP",
    "wof:placetype":"postalcode"
},
  "geometry": {"coordinates":[-0.21211309573989,51.97076534592389],"type":"Point"}
}