{
  "type": "Feature",
  "properties": {
    "date:inception_lower": "1980-01-01",
    "date:inception_upper": "1980-01-01",
    "iso:country": "GB",
    "wof:name": "SG6 2LP",
    "wof:placetype": "postalcode"
  },
  "geometry": {"coordinates":[-0.212,51.970764],"type":"Point"}
}
