{
  "type": "Feature",
  "properties": {
    "iso:country": "GB",
    "wof:name": "PR4 6JG",
    "wof:placetype": "postalcode"
  },
  "geometry": {"coordinates":[-2.845638,53.694438],"type":"Point"}
}
