{
  "type": "Feature",
  "properties": {
    "date:inception_lower":"1994-05-01",
    "date:inception_upper":"1994-05-31",
    "iso:country":"GB",
    "wof:name":"BA13 3XS",
    "wof:placetype":"postalcode"
},
  "geometry": {"coordinates":[-2.197785,51.262176],"type":"Point"}
}