{
  "type": "Feature",
  "properties": {
    "iso:country":"GB",
    "wof:name":"OX27 8AW",
    "wof:placetype":"postalcode"
},
  "geometry": {"coordinates":[-1.14517831114858,51.9617502756454],"type":"Point"}
}