{
  "type": "Feature",
  "properties": {
    "date:inception_lower": "2000-10-01",
    "date:inception_upper": "2000-10-01",
    "iso:country": "GB",
    "wof:name": "OX27 8AW",
    "wof:placetype": "postalcode"
  },
  "geometry": {"coordinates":[-1.145178,51.96175],"type":"Point"}
}
