{
  "type": "Feature",
  "properties": {
    "iso:country": "GB",
    "wof:name": "SG12 7EW",
    "wof:placetype": "postalcode"
  },
  "geometry": {"coordinates":[-0.025288,51.813214],"type":"Point"}
}
