{
  "type": "Feature",
  "properties": {
    "date:inception_lower": "1980-01-01",
    "date:inception_upper": "1980-01-01",
    "iso:country": "GB",
    "wof:name": "SG12 7EW",
    "wof:placetype": "postalcode"
  },
  "geometry": {"coordinates":[-0.025288,51.813214],"type":"Point"}
}
