{
  "type": "Feature",
  "properties": {
    "date:inception_lower": "2001-12-01",
    "date:inception_upper": "2001-12-01",
    "iso:country": "GB",
    "wof:name": "LN9 5GB",
    "wof:placetype": "postalcode"
  },
  "geometry": {"coordinates":[-0.129434,53.210053],"type":"Point"}
}
