{
  "type": "Feature",
  "properties": {
    "iso:country":"GB",
    "wof:name":"SW16 4PH",
    "wof:placetype":"postalcode"
},
  "geometry": {"coordinates":[-0.12378305919427,51.40858719843059],"type":"Point"}
}