{
  "type": "Feature",
  "properties": {
    "date:inception_lower": "2017-10-01",
    "date:inception_upper": "2017-10-01",
    "iso:country": "GB",
    "wof:name": "AB21 0DA",
    "wof:placetype": "postalcode"
  },
  "geometry": {"coordinates":[-2.209153,57.221749],"type":"Point"}
}
