{
  "type": "Feature",
  "properties": {
    "iso:country":"GB",
    "wof:name":"RG17 9DS",
    "wof:placetype":"postalcode"
},
  "geometry": {"coordinates":[-1.48692554725877,51.37212571141175],"type":"Point"}
}