{
  "type": "Feature",
  "properties": {
    "iso:country":"GB",
    "wof:name":"SA33 4QN",
    "wof:placetype":"postalcode"
},
  "geometry": {"coordinates":[-4.46664832776935,51.77828968854062],"type":"Point"}
}