{
  "type": "Feature",
  "properties": {
    "iso:country": "GB",
    "wof:name": "IP31 2BB",
    "wof:placetype": "postalcode"
  },
  "geometry": {"coordinates":[0.901832,52.322516],"type":"Point"}
}
