{
  "type": "Feature",
  "properties": {
    "iso:country":"GB",
    "wof:name":"IP31 2BB",
    "wof:placetype":"postalcode"
},
  "geometry": {"coordinates":[0.90183164248862,52.32251564780224],"type":"Point"}
}