{
  "type": "Feature",
  "properties": {
    "iso:country":"GB",
    "wof:name":"ST19 5HX",
    "wof:placetype":"postalcode"
},
  "geometry": {"coordinates":[-2.10407010639086,52.71605982529191],"type":"Point"}
}