{
  "type": "Feature",
  "properties": {
    "date:inception_lower": "1980-01-01",
    "date:inception_upper": "1980-01-01",
    "iso:country": "GB",
    "wof:name": "ST19 5HX",
    "wof:placetype": "postalcode"
  },
  "geometry": {"coordinates":[-2.10407,52.71606],"type":"Point"}
}
