{
  "type": "Feature",
  "properties": {
    "date:inception_lower":"1980-01-01",
    "date:inception_upper":"1980-01-31",
    "iso:country":"GB",
    "wof:name":"WS13 6NT",
    "wof:placetype":"postalcode"
},
  "geometry": {"coordinates":[-1.828908,52.680842],"type":"Point"}
}