{
  "type": "Feature",
  "properties": {
    "date:inception_lower": "2006-10-01",
    "date:inception_upper": "2006-10-01",
    "iso:country": "GB",
    "wof:name": "NG15 6ST",
    "wof:placetype": "postalcode"
  },
  "geometry": {"coordinates":[-1.226385,53.020785],"type":"Point"}
}
