{
  "type": "Feature",
  "properties": {
    "iso:country":"GB",
    "wof:name":"EN7 5EL",
    "wof:placetype":"postalcode"
},
  "geometry": {"coordinates":[-0.08669462117527,51.70877789892428],"type":"Point"}
}