{
  "type": "Feature",
  "properties": {
    "date:inception_lower": "1984-10-01",
    "date:inception_upper": "1984-10-01",
    "iso:country": "GB",
    "wof:name": "EN7 5EL",
    "wof:placetype": "postalcode"
  },
  "geometry": {"coordinates":[-0.086695,51.708778],"type":"Point"}
}
