{
  "type": "Feature",
  "properties": {
    "iso:country":"GB",
    "wof:name":"LL68 0NY",
    "wof:placetype":"postalcode"
},
  "geometry": {"coordinates":[-4.43184832621477,53.37581901962454],"type":"Point"}
}