{
  "type": "Feature",
  "properties": {
    "date:inception_lower":"1984-02-01",
    "date:inception_upper":"1984-02-29",
    "iso:country":"GB",
    "wof:name":"LL68 0NY",
    "wof:placetype":"postalcode"
},
  "geometry": {"coordinates":[-4.431848,53.375819],"type":"Point"}
}