{
  "type": "Feature",
  "properties": {
    "iso:country": "GB",
    "wof:name": "CM22 6UF",
    "wof:placetype": "postalcode"
  },
  "geometry": {"coordinates":[0.225684,51.910562],"type":"Point"}
}
