{
  "type": "Feature",
  "properties": {
    "date:inception_lower": "1980-01-01",
    "date:inception_upper": "1980-01-01",
    "iso:country": "GB",
    "wof:name": "DY5 4LH",
    "wof:placetype": "postalcode"
  },
  "geometry": {"coordinates":[-2.138092,52.496908],"type":"Point"}
}
