{
  "type": "Feature",
  "properties": {
    "iso:country":"GB",
    "wof:name":"DY5 4LH",
    "wof:placetype":"postalcode"
},
  "geometry": {"coordinates":[-2.13809189033277,52.49690832433564],"type":"Point"}
}