{
  "type": "Feature",
  "properties": {
    "iso:country":"GB",
    "wof:name":"PR7 2NZ",
    "wof:placetype":"postalcode"
},
  "geometry": {"coordinates":[-2.64644032112438,53.64209361516111],"type":"Point"}
}