{
  "type": "Feature",
  "properties": {
    "iso:country": "GB",
    "wof:name": "PR7 2NZ",
    "wof:placetype": "postalcode"
  },
  "geometry": {"coordinates":[-2.64644,53.642094],"type":"Point"}
}
