{
  "type": "Feature",
  "properties": {
    "iso:country": "GB",
    "wof:name": "GU51 4QG",
    "wof:placetype": "postalcode"
  },
  "geometry": {"coordinates":[-0.833615,51.289465],"type":"Point"}
}
