{
  "type": "Feature",
  "properties": {
    "date:inception_lower": "2001-06-01",
    "date:inception_upper": "2001-06-01",
    "iso:country": "GB",
    "wof:name": "GU51 4QG",
    "wof:placetype": "postalcode"
  },
  "geometry": {"coordinates":[-0.833615,51.289465],"type":"Point"}
}
