{
  "type": "Feature",
  "properties": {
    "iso:country":"GB",
    "wof:name":"GU51 4QG",
    "wof:placetype":"postalcode"
},
  "geometry": {"coordinates":[-0.83336027492456,51.28942665644255],"type":"Point"}
}