{
  "type": "Feature",
  "properties": {
    "iso:country":"GB",
    "wof:name":"WR2 4TY",
    "wof:placetype":"postalcode"
},
  "geometry": {"coordinates":[-2.24079232382115,52.14674541858378],"type":"Point"}
}