{
  "type": "Feature",
  "properties": {
    "iso:country":"GB",
    "wof:name":"CB6 1DL",
    "wof:placetype":"postalcode"
},
  "geometry": {"coordinates":[0.26975501499107,52.40817559522752],"type":"Point"}
}