{
  "type": "Feature",
  "properties": {
    "iso:country":"GB",
    "wof:name":"LA3 1JH",
    "wof:placetype":"postalcode"
},
  "geometry": {"coordinates":[-2.88338414824791,54.05889010023123],"type":"Point"}
}