{
  "type": "Feature",
  "properties": {
    "iso:country": "GB",
    "wof:name": "N11 1JL",
    "wof:placetype": "postalcode"
  },
  "geometry": {"coordinates":[-0.141066,51.619593],"type":"Point"}
}
