{
  "type": "Feature",
  "properties": {
    "iso:country":"GB",
    "wof:name":"N11 1JL",
    "wof:placetype":"postalcode"
},
  "geometry": {"coordinates":[-0.14106623501988,51.61959298463604],"type":"Point"}
}