{
  "type": "Feature",
  "properties": {
    "date:inception_lower": "2018-08-01",
    "date:inception_upper": "2018-08-01",
    "iso:country": "GB",
    "wof:name": "SY8 9DR",
    "wof:placetype": "postalcode"
  },
  "geometry": {"coordinates":[-2.697402,52.368624],"type":"Point"}
}
