{
  "type": "Feature",
  "properties": {
    "iso:country":"GB",
    "wof:name":"S73 0QH",
    "wof:placetype":"postalcode"
},
  "geometry": {"coordinates":[-1.41809285876594,53.50743914946874],"type":"Point"}
}