{
  "type": "Feature",
  "properties": {
    "iso:country":"GB",
    "wof:name":"SA4 8LQ",
    "wof:placetype":"postalcode"
},
  "geometry": {"coordinates":[-4.03522903325699,51.71167447599586],"type":"Point"}
}