{
  "type": "Feature",
  "properties": {
    "iso:country": "GB",
    "wof:name": "CO10 0GY",
    "wof:placetype": "postalcode"
  },
  "geometry": {"coordinates":[0.757949,52.023809],"type":"Point"}
}
