{
  "type": "Feature",
  "properties": {
    "date:inception_lower": "1998-06-01",
    "date:inception_upper": "1998-06-01",
    "iso:country": "GB",
    "wof:name": "CO10 0GY",
    "wof:placetype": "postalcode"
  },
  "geometry": {"coordinates":[0.75795,52.023786],"type":"Point"}
}
