{
  "type": "Feature",
  "properties": {
    "iso:country":"GB",
    "wof:name":"CO10 0GY",
    "wof:placetype":"postalcode"
},
  "geometry": {"coordinates":[0.75794944823792,52.0238086222082],"type":"Point"}
}