{
  "type": "Feature",
  "properties": {
    "date:inception_lower": "1991-01-01",
    "date:inception_upper": "1991-01-01",
    "iso:country": "GB",
    "wof:name": "DE11 0PA",
    "wof:placetype": "postalcode"
  },
  "geometry": {"coordinates":[-1.561656,52.774555],"type":"Point"}
}
