{
  "type": "Feature",
  "properties": {
    "iso:country":"GB",
    "wof:name":"DE11 0PA",
    "wof:placetype":"postalcode"
},
  "geometry": {"coordinates":[-1.56167642968653,52.77454720792093],"type":"Point"}
}