{
  "type": "Feature",
  "properties": {
    "date:inception_lower": "2017-06-01",
    "date:inception_upper": "2017-06-01",
    "iso:country": "GB",
    "wof:name": "NR12 9GB",
    "wof:placetype": "postalcode"
  },
  "geometry": {"coordinates":[1.484629,52.76547],"type":"Point"}
}
