{
  "type": "Feature",
  "properties": {
    "iso:country":"GB",
    "wof:name":"TF13 6NL",
    "wof:placetype":"postalcode"
},
  "geometry": {"coordinates":[-2.56816102235462,52.61122586231343],"type":"Point"}
}