{
  "type": "Feature",
  "properties": {
    "iso:country":"GB",
    "wof:name":"DN34 5RN",
    "wof:placetype":"postalcode"
},
  "geometry": {"coordinates":[-0.12458570286183,53.55654287834076],"type":"Point"}
}