{
  "type": "Feature",
  "properties": {
    "iso:country": "GB",
    "wof:name": "L17 4JY",
    "wof:placetype": "postalcode"
  },
  "geometry": {"coordinates":[-2.951522,53.380363],"type":"Point"}
}
