{
  "type": "Feature",
  "properties": {
    "iso:country":"GB",
    "wof:name":"L17 4JY",
    "wof:placetype":"postalcode"
},
  "geometry": {"coordinates":[-2.95152157061562,53.38036284697503],"type":"Point"}
}