{
  "type": "Feature",
  "properties": {
    "iso:country":"GB",
    "wof:name":"M20 5PR",
    "wof:placetype":"postalcode"
},
  "geometry": {"coordinates":[-2.22042554096868,53.40518386771379],"type":"Point"}
}