{
  "type": "Feature",
  "properties": {
    "date:inception_lower": "1981-06-01",
    "date:inception_upper": "1981-06-01",
    "iso:country": "GB",
    "wof:name": "CF35 6SW",
    "wof:placetype": "postalcode"
  },
  "geometry": {"coordinates":[-3.498913,51.528718],"type":"Point"}
}
