{
  "type": "Feature",
  "properties": {
    "iso:country":"GB",
    "wof:name":"CF35 6SW",
    "wof:placetype":"postalcode"
},
  "geometry": {"coordinates":[-3.49891303639242,51.52871765762985],"type":"Point"}
}