{
  "type": "Feature",
  "properties": {
    "iso:country":"GB",
    "wof:name":"SW6 6QB",
    "wof:placetype":"postalcode"
},
  "geometry": {"coordinates":[-0.21335669962048,51.47478715732816],"type":"Point"}
}