{
  "type": "Feature",
  "properties": {
    "date:inception_lower": "2018-01-01",
    "date:inception_upper": "2018-01-01",
    "iso:country": "GB",
    "wof:name": "BB7 9BQ",
    "wof:placetype": "postalcode"
  },
  "geometry": {"coordinates":[-2.397823,53.840167],"type":"Point"}
}
