{
  "type": "Feature",
  "properties": {
    "iso:country": "GB",
    "wof:name": "BB7 9BQ",
    "wof:placetype": "postalcode"
  },
  "geometry": {"coordinates":[-2.39764,53.840122],"type":"Point"}
}
