{
  "type": "Feature",
  "properties": {
    "iso:country":"GB",
    "wof:name":"TN18 5JD",
    "wof:placetype":"postalcode"
},
  "geometry": {"coordinates":[0.56496667399048,51.02684847995165],"type":"Point"}
}