{
  "type": "Feature",
  "properties": {
    "iso:country": "GB",
    "wof:name": "TN18 5JD",
    "wof:placetype": "postalcode"
  },
  "geometry": {"coordinates":[0.564967,51.026848],"type":"Point"}
}
