{
  "type": "Feature",
  "properties": {
    "iso:country":"GB",
    "wof:name":"BB5 2LF",
    "wof:placetype":"postalcode"
},
  "geometry": {"coordinates":[-2.36031685434725,53.74469272504567],"type":"Point"}
}