{
  "type": "Feature",
  "properties": {
    "iso:country":"GB",
    "wof:name":"ME20 7LW",
    "wof:placetype":"postalcode"
},
  "geometry": {"coordinates":[0.46820894601951,51.29946545976686],"type":"Point"}
}