{
  "type": "Feature",
  "properties": {
    "iso:country":"GB",
    "wof:name":"LS10 4EB",
    "wof:placetype":"postalcode"
},
  "geometry": {"coordinates":[-1.54174629238583,53.74352420294231],"type":"Point"}
}