{
  "type": "Feature",
  "properties": {
    "iso:country":"GB",
    "wof:name":"KT20 7TW",
    "wof:placetype":"postalcode"
},
  "geometry": {"coordinates":[-0.24374761975593,51.27898317970917],"type":"Point"}
}