{
  "type": "Feature",
  "properties": {
    "iso:country": "GB",
    "wof:name": "KT20 7TW",
    "wof:placetype": "postalcode"
  },
  "geometry": {"coordinates":[-0.243748,51.278983],"type":"Point"}
}
