{
  "type": "Feature",
  "properties": {
    "iso:country":"GB",
    "wof:name":"DE11 9RX",
    "wof:placetype":"postalcode"
},
  "geometry": {"coordinates":[-1.58203967304092,52.76103738373151],"type":"Point"}
}