{
  "type": "Feature",
  "properties": {
    "date:inception_lower": "2008-01-01",
    "date:inception_upper": "2008-01-01",
    "iso:country": "GB",
    "wof:name": "DE11 9RX",
    "wof:placetype": "postalcode"
  },
  "geometry": {"coordinates":[-1.58204,52.761037],"type":"Point"}
}
