{
  "type": "Feature",
  "properties": {
    "iso:country":"GB",
    "wof:name":"IP11 9PL",
    "wof:placetype":"postalcode"
},
  "geometry": {"coordinates":[1.36924516377286,51.97051797355111],"type":"Point"}
}