{
  "type": "Feature",
  "properties": {
    "date:inception_lower":"2012-02-01",
    "date:inception_upper":"2012-02-29",
    "iso:country":"GB",
    "wof:name":"ME15 9ZF",
    "wof:placetype":"postalcode"
},
  "geometry": {"coordinates":[0.547698,51.243953],"type":"Point"}
}