{
  "type": "Feature",
  "properties": {
    "iso:country": "GB",
    "wof:name": "ME15 9ZF",
    "wof:placetype": "postalcode"
  },
  "geometry": {"coordinates":[0.547698,51.243953],"type":"Point"}
}
