{
  "type": "Feature",
  "properties": {
    "date:inception_lower": "1980-01-01",
    "date:inception_upper": "1980-01-01",
    "iso:country": "GB",
    "wof:name": "TS26 0BX",
    "wof:placetype": "postalcode"
  },
  "geometry": {"coordinates":[-1.25537,54.686826],"type":"Point"}
}
