{
  "type": "Feature",
  "properties": {
    "iso:country":"GB",
    "wof:name":"TS26 0BX",
    "wof:placetype":"postalcode"
},
  "geometry": {"coordinates":[-1.2556473356803,54.6861526617165],"type":"Point"}
}