{
  "type": "Feature",
  "properties": {
    "iso:country": "GB",
    "wof:name": "SM6 9NP",
    "wof:placetype": "postalcode"
  },
  "geometry": {"coordinates":[-0.145913,51.348113],"type":"Point"}
}
