{
  "type": "Feature",
  "properties": {
    "iso:country":"GB",
    "wof:name":"SM6 9NP",
    "wof:placetype":"postalcode"
},
  "geometry": {"coordinates":[-0.14591324872333,51.34811288472902],"type":"Point"}
}