{
  "type": "Feature",
  "properties": {
    "iso:country":"GB",
    "wof:name":"BS7 9PU",
    "wof:placetype":"postalcode"
},
  "geometry": {"coordinates":[-2.57856923742203,51.48575167294177],"type":"Point"}
}