{
  "type": "Feature",
  "properties": {
    "date:inception_lower": "1980-01-01",
    "date:inception_upper": "1980-01-01",
    "iso:country": "GB",
    "wof:name": "EX20 4BL",
    "wof:placetype": "postalcode"
  },
  "geometry": {"coordinates":[-4.118695,50.628648],"type":"Point"}
}
