{
  "type": "Feature",
  "properties": {
    "iso:country":"GB",
    "wof:name":"L32 8SS",
    "wof:placetype":"postalcode"
},
  "geometry": {"coordinates":[-2.88189255470454,53.48094322152254],"type":"Point"}
}