{
  "type": "Feature",
  "properties": {
    "date:inception_lower":"1980-01-01",
    "date:inception_upper":"1980-01-31",
    "iso:country":"GB",
    "wof:name":"L32 8SS",
    "wof:placetype":"postalcode"
},
  "geometry": {"coordinates":[-2.881893,53.480943],"type":"Point"}
}