{
  "type": "Feature",
  "properties": {
    "date:inception_lower":"1980-01-01",
    "date:inception_upper":"1980-01-31",
    "iso:country":"GB",
    "wof:name":"HX1 5TL",
    "wof:placetype":"postalcode"
},
  "geometry": {"coordinates":[-1.867785,53.727061],"type":"Point"}
}