{
  "type": "Feature",
  "properties": {
    "iso:country":"GB",
    "wof:name":"HX1 5TL",
    "wof:placetype":"postalcode"
},
  "geometry": {"coordinates":[-1.86778527203749,53.72706051081799],"type":"Point"}
}