{
  "type": "Feature",
  "properties": {
    "iso:country":"GB",
    "wof:name":"SL5 9DE",
    "wof:placetype":"postalcode"
},
  "geometry": {"coordinates":[-0.67059474477411,51.40294548744833],"type":"Point"}
}