{
  "type": "Feature",
  "properties": {
    "iso:country":"GB",
    "wof:name":"BL8 3HA",
    "wof:placetype":"postalcode"
},
  "geometry": {"coordinates":[-2.33757809308066,53.61101481178624],"type":"Point"}
}