{
  "type": "Feature",
  "properties": {
    "iso:country":"GB",
    "wof:name":"CB6 2RG",
    "wof:placetype":"postalcode"
},
  "geometry": {"coordinates":[0.12662357525443,52.38864615452346],"type":"Point"}
}