{
  "type": "Feature",
  "properties": {
    "iso:country": "GB",
    "wof:name": "CB6 2RG",
    "wof:placetype": "postalcode"
  },
  "geometry": {"coordinates":[0.126624,52.388646],"type":"Point"}
}
