{
  "type": "Feature",
  "properties": {
    "iso:country":"GB",
    "wof:name":"TR27 6LW",
    "wof:placetype":"postalcode"
},
  "geometry": {"coordinates":[-5.46408813418592,50.17284061041023],"type":"Point"}
}