{
  "type": "Feature",
  "properties": {
    "iso:country":"GB",
    "wof:name":"ST5 3PQ",
    "wof:placetype":"postalcode"
},
  "geometry": {"coordinates":[-2.23362123768666,52.99344096538404],"type":"Point"}
}