{
  "type": "Feature",
  "properties": {
    "date:inception_lower": "1983-07-01",
    "date:inception_upper": "1983-07-01",
    "iso:country": "GB",
    "wof:name": "ST5 3PQ",
    "wof:placetype": "postalcode"
  },
  "geometry": {"coordinates":[-2.233621,52.993441],"type":"Point"}
}
