{
  "type": "Feature",
  "properties": {
    "iso:country": "GB",
    "wof:name": "CA4 0PZ",
    "wof:placetype": "postalcode"
  },
  "geometry": {"coordinates":[-2.890222,54.806417],"type":"Point"}
}
