{
  "type": "Feature",
  "properties": {
    "iso:country":"GB",
    "wof:name":"CA4 0PZ",
    "wof:placetype":"postalcode"
},
  "geometry": {"coordinates":[-2.89022228615074,54.80641656190567],"type":"Point"}
}