{
  "type": "Feature",
  "properties": {
    "date:inception_lower":"1997-06-01",
    "date:inception_upper":"1997-06-30",
    "iso:country":"GB",
    "wof:name":"S36 6SX",
    "wof:placetype":"postalcode"
},
  "geometry": {"coordinates":[-1.612588,53.523427],"type":"Point"}
}