{
  "type": "Feature",
  "properties": {
    "iso:country":"GB",
    "wof:name":"S36 6SX",
    "wof:placetype":"postalcode"
},
  "geometry": {"coordinates":[-1.61258797829334,53.52342666526103],"type":"Point"}
}