{
  "type": "Feature",
  "properties": {
    "iso:country": "GB",
    "wof:name": "CF24 4PF",
    "wof:placetype": "postalcode"
  },
  "geometry": {"coordinates":[-3.177456,51.497155],"type":"Point"}
}
