{
  "type": "Feature",
  "properties": {
    "iso:country":"GB",
    "wof:name":"PR2 1DT",
    "wof:placetype":"postalcode"
},
  "geometry": {"coordinates":[-2.73198210143019,53.76709584253104],"type":"Point"}
}