{
  "type": "Feature",
  "properties": {
    "iso:country":"GB",
    "wof:name":"G13 2LJ",
    "wof:placetype":"postalcode"
},
  "geometry": {"coordinates":[-4.34258687277877,55.90127982103843],"type":"Point"}
}