{
  "type": "Feature",
  "properties": {
    "date:inception_lower": "1980-01-01",
    "date:inception_upper": "1980-01-01",
    "iso:country": "GB",
    "wof:name": "GU34 1RQ",
    "wof:placetype": "postalcode"
  },
  "geometry": {"coordinates":[-0.987159,51.140181],"type":"Point"}
}
