{
  "type": "Feature",
  "properties": {
    "iso:country":"GB",
    "wof:name":"NW8 7QT",
    "wof:placetype":"postalcode"
},
  "geometry": {"coordinates":[-0.16056857897647,51.53664860842845],"type":"Point"}
}