{
  "type": "Feature",
  "properties": {
    "iso:country": "GB",
    "wof:name": "SY3 0BE",
    "wof:placetype": "postalcode"
  },
  "geometry": {"coordinates":[-2.796567,52.659162],"type":"Point"}
}
