{
  "type": "Feature",
  "properties": {
    "iso:country":"GB",
    "wof:name":"SY3 0BE",
    "wof:placetype":"postalcode"
},
  "geometry": {"coordinates":[-2.79640185798867,52.65899588460832],"type":"Point"}
}