{
  "type": "Feature",
  "properties": {
    "date:inception_lower":"1980-01-01",
    "date:inception_upper":"1980-01-31",
    "iso:country":"GB",
    "wof:name":"SY3 0BE",
    "wof:placetype":"postalcode"
},
  "geometry": {"coordinates":[-2.796567,52.659162],"type":"Point"}
}