{
  "type": "Feature",
  "properties": {
    "date:inception_lower": "1992-08-01",
    "date:inception_upper": "1992-08-01",
    "iso:country": "GB",
    "wof:name": "HP27 0LH",
    "wof:placetype": "postalcode"
  },
  "geometry": {"coordinates":[-0.814493,51.72734],"type":"Point"}
}
