{
  "type": "Feature",
  "properties": {
    "iso:country":"GB",
    "wof:name":"HP27 0LH",
    "wof:placetype":"postalcode"
},
  "geometry": {"coordinates":[-0.81449303243861,51.72733968305963],"type":"Point"}
}