{
  "type": "Feature",
  "properties": {
    "iso:country": "GB",
    "wof:name": "EX16 6EZ",
    "wof:placetype": "postalcode"
  },
  "geometry": {"coordinates":[-3.470665,50.91127],"type":"Point"}
}
