{
  "type": "Feature",
  "properties": {
    "iso:country":"GB",
    "wof:name":"WV10 6NA",
    "wof:placetype":"postalcode"
},
  "geometry": {"coordinates":[-2.12259597786244,52.62883329800705],"type":"Point"}
}