{
  "type": "Feature",
  "properties": {
    "date:inception_lower":"2017-11-01",
    "date:inception_upper":"2017-11-30",
    "iso:country":"GB",
    "wof:name":"B13 8EQ",
    "wof:placetype":"postalcode"
},
  "geometry": {"coordinates":[-1.887258,52.448701],"type":"Point"}
}