{
  "type": "Feature",
  "properties": {
    "iso:country": "GB",
    "wof:name": "WD24 5AT",
    "wof:placetype": "postalcode"
  },
  "geometry": {"coordinates":[-0.399262,51.670965],"type":"Point"}
}
