{
  "type": "Feature",
  "properties": {
    "iso:country":"GB",
    "wof:name":"CV2 3HN",
    "wof:placetype":"postalcode"
},
  "geometry": {"coordinates":[-1.47569288564317,52.4200873448012],"type":"Point"}
}