{
  "type": "Feature",
  "properties": {
    "iso:country":"GB",
    "wof:name":"DL12 8XE",
    "wof:placetype":"postalcode"
},
  "geometry": {"coordinates":[-1.83860651048602,54.52845550245782],"type":"Point"}
}