{
  "type": "Feature",
  "properties": {
    "date:inception_lower":"1980-01-01",
    "date:inception_upper":"1980-01-31",
    "iso:country":"GB",
    "wof:name":"DL12 8XE",
    "wof:placetype":"postalcode"
},
  "geometry": {"coordinates":[-1.838631,54.528447],"type":"Point"}
}