{
  "type": "Feature",
  "properties": {
    "iso:country":"GB",
    "wof:name":"NR26 8JT",
    "wof:placetype":"postalcode"
},
  "geometry": {"coordinates":[1.21149008884772,52.94475731901756],"type":"Point"}
}