{
  "type": "Feature",
  "properties": {
    "iso:country": "GB",
    "wof:name": "LE3 3ET",
    "wof:placetype": "postalcode"
  },
  "geometry": {"coordinates":[-1.21748,52.61861],"type":"Point"}
}
