{
  "type": "Feature",
  "properties": {
    "iso:country":"GB",
    "wof:name":"LE3 3ET",
    "wof:placetype":"postalcode"
},
  "geometry": {"coordinates":[-1.21748010827033,52.61861019768184],"type":"Point"}
}