{
  "type": "Feature",
  "properties": {
    "iso:country":"GB",
    "wof:name":"TN4 8UR",
    "wof:placetype":"postalcode"
},
  "geometry": {"coordinates":[0.22853971171302,51.13655640388777],"type":"Point"}
}