{
  "type": "Feature",
  "properties": {
    "date:inception_lower":"1980-01-01",
    "date:inception_upper":"1980-01-31",
    "iso:country":"GB",
    "wof:name":"SN11 0JE",
    "wof:placetype":"postalcode"
},
  "geometry": {"coordinates":[-2.003188,51.435353],"type":"Point"}
}