{
  "type": "Feature",
  "properties": {
    "iso:country":"GB",
    "wof:name":"GL15 4DX",
    "wof:placetype":"postalcode"
},
  "geometry": {"coordinates":[-2.476878161473,51.76120073716022],"type":"Point"}
}