{
  "type": "Feature",
  "properties": {
    "iso:country": "GB",
    "wof:name": "GL15 4DX",
    "wof:placetype": "postalcode"
  },
  "geometry": {"coordinates":[-2.476878,51.761201],"type":"Point"}
}
