{
  "type": "Feature",
  "properties": {
    "iso:country": "GB",
    "wof:name": "BN25 2QS",
    "wof:placetype": "postalcode"
  },
  "geometry": {"coordinates":[0.082881,50.781021],"type":"Point"}
}
