{
  "type": "Feature",
  "properties": {
    "date:inception_lower":"2006-07-01",
    "date:inception_upper":"2006-07-31",
    "iso:country":"GB",
    "wof:name":"BN25 2QS",
    "wof:placetype":"postalcode"
},
  "geometry": {"coordinates":[0.082881,50.781021],"type":"Point"}
}