{
  "type": "Feature",
  "properties": {
    "iso:country": "GB",
    "wof:name": "NG17 7JJ",
    "wof:placetype": "postalcode"
  },
  "geometry": {"coordinates":[-1.240128,53.104906],"type":"Point"}
}
