{
  "type": "Feature",
  "properties": {
    "date:inception_lower":"1980-01-01",
    "date:inception_upper":"1980-01-31",
    "iso:country":"GB",
    "wof:name":"NG17 7JJ",
    "wof:placetype":"postalcode"
},
  "geometry": {"coordinates":[-1.240128,53.104906],"type":"Point"}
}