{
  "type": "Feature",
  "properties": {
    "iso:country": "GB",
    "wof:name": "WF1 3PW",
    "wof:placetype": "postalcode"
  },
  "geometry": {"coordinates":[-1.495489,53.688834],"type":"Point"}
}
