{
  "type": "Feature",
  "properties": {
    "iso:country": "GB",
    "wof:name": "GU24 8RJ",
    "wof:placetype": "postalcode"
  },
  "geometry": {"coordinates":[-0.601617,51.354808],"type":"Point"}
}
