{
  "type": "Feature",
  "properties": {
    "iso:country":"GB",
    "wof:name":"PA10 2PX",
    "wof:placetype":"postalcode"
},
  "geometry": {"coordinates":[-4.60543767260499,55.83589976798181],"type":"Point"}
}