{
  "type": "Feature",
  "properties": {
    "date:inception_lower": "1980-01-01",
    "date:inception_upper": "1980-01-01",
    "iso:country": "GB",
    "wof:name": "PA10 2PX",
    "wof:placetype": "postalcode"
  },
  "geometry": {"coordinates":[-4.605438,55.8359],"type":"Point"}
}
