{
  "type": "Feature",
  "properties": {
    "iso:country":"GB",
    "wof:name":"SR2 7HY",
    "wof:placetype":"postalcode"
},
  "geometry": {"coordinates":[-1.38689009389289,54.89810927708066],"type":"Point"}
}