{
  "type": "Feature",
  "properties": {
    "iso:country":"GB",
    "wof:name":"HS8 5TP",
    "wof:placetype":"postalcode"
},
  "geometry": {"coordinates":[-7.30637892983637,57.15295332525415],"type":"Point"}
}