{
  "type": "Feature",
  "properties": {
    "iso:country":"GB",
    "wof:name":"B10 9PG",
    "wof:placetype":"postalcode"
},
  "geometry": {"coordinates":[-1.84472727393522,52.47373854032525],"type":"Point"}
}