{
  "type": "Feature",
  "properties": {
    "iso:country":"GB",
    "wof:name":"ME10 1UE",
    "wof:placetype":"postalcode"
},
  "geometry": {"coordinates":[0.71746434878973,51.345577882805],"type":"Point"}
}