{
  "type": "Feature",
  "properties": {
    "iso:country":"GB",
    "wof:name":"BL1 5XR",
    "wof:placetype":"postalcode"
},
  "geometry": {"coordinates":[-2.47282319209844,53.5770570387891],"type":"Point"}
}