{
  "type": "Feature",
  "properties": {
    "iso:country":"GB",
    "wof:name":"NG7 7FG",
    "wof:placetype":"postalcode"
},
  "geometry": {"coordinates":[-1.17336330095289,52.97755796884785],"type":"Point"}
}