{
  "type": "Feature",
  "properties": {
    "iso:country": "GB",
    "wof:name": "EX6 8SD",
    "wof:placetype": "postalcode"
  },
  "geometry": {"coordinates":[-3.45193,50.627743],"type":"Point"}
}
