{
  "type": "Feature",
  "properties": {
    "date:inception_lower": "1984-02-01",
    "date:inception_upper": "1984-02-01",
    "iso:country": "GB",
    "wof:name": "EX6 8SD",
    "wof:placetype": "postalcode"
  },
  "geometry": {"coordinates":[-3.45193,50.627743],"type":"Point"}
}
