{
  "type": "Feature",
  "properties": {
    "iso:country":"GB",
    "wof:name":"EX6 8SD",
    "wof:placetype":"postalcode"
},
  "geometry": {"coordinates":[-3.45193007105156,50.62774343014533],"type":"Point"}
}