{
  "type": "Feature",
  "properties": {
    "date:inception_lower":"1980-01-01",
    "date:inception_upper":"1980-01-31",
    "iso:country":"GB",
    "wof:name":"WD7 8BE",
    "wof:placetype":"postalcode"
},
  "geometry": {"coordinates":[-0.32273,51.690966],"type":"Point"}
}