{
  "type": "Feature",
  "properties": {
    "iso:country":"GB",
    "wof:name":"B20 1EX",
    "wof:placetype":"postalcode"
},
  "geometry": {"coordinates":[-1.93573236318048,52.52887708421833],"type":"Point"}
}