{
  "type": "Feature",
  "properties": {
    "date:inception_lower":"1980-01-01",
    "date:inception_upper":"1980-01-31",
    "iso:country":"GB",
    "wof:name":"B20 1EX",
    "wof:placetype":"postalcode"
},
  "geometry": {"coordinates":[-1.935732,52.528877],"type":"Point"}
}