{
  "type": "Feature",
  "properties": {
    "date:inception_lower": "1980-01-01",
    "date:inception_upper": "1980-01-01",
    "iso:country": "GB",
    "wof:name": "BD15 7AJ",
    "wof:placetype": "postalcode"
  },
  "geometry": {"coordinates":[-1.814295,53.803684],"type":"Point"}
}
