{
  "type": "Feature",
  "properties": {
    "iso:country":"GB",
    "wof:name":"BD15 7AJ",
    "wof:placetype":"postalcode"
},
  "geometry": {"coordinates":[-1.81429504736188,53.80368443788731],"type":"Point"}
}