{
  "type": "Feature",
  "properties": {
    "date:inception_lower": "1980-01-01",
    "date:inception_upper": "1980-01-01",
    "iso:country": "GB",
    "wof:name": "GL54 2AG",
    "wof:placetype": "postalcode"
  },
  "geometry": {"coordinates":[-1.756443,51.883439],"type":"Point"}
}
