{
  "type": "Feature",
  "properties": {
    "iso:country":"GB",
    "wof:name":"BN21 4EB",
    "wof:placetype":"postalcode"
},
  "geometry": {"coordinates":[0.28470329002635,50.76142982754996],"type":"Point"}
}