{
  "type": "Feature",
  "properties": {
    "date:inception_lower": "1980-01-01",
    "date:inception_upper": "1980-01-01",
    "iso:country": "GB",
    "wof:name": "BN21 4EB",
    "wof:placetype": "postalcode"
  },
  "geometry": {"coordinates":[0.284703,50.76143],"type":"Point"}
}
