{
  "type": "Feature",
  "properties": {
    "iso:country":"GB",
    "wof:name":"CH49 2NJ",
    "wof:placetype":"postalcode"
},
  "geometry": {"coordinates":[-3.11539235983653,53.38458896866943],"type":"Point"}
}