{
  "type": "Feature",
  "properties": {
    "iso:country": "GB",
    "wof:name": "DE14 3LD",
    "wof:placetype": "postalcode"
  },
  "geometry": {"coordinates":[-1.645865,52.793814],"type":"Point"}
}
