{
  "type": "Feature",
  "properties": {
    "iso:country":"GB",
    "wof:name":"OL5 9SA",
    "wof:placetype":"postalcode"
},
  "geometry": {"coordinates":[-2.03478094807463,53.51339705302568],"type":"Point"}
}