{
  "type": "Feature",
  "properties": {
    "date:inception_lower":"1992-01-01",
    "date:inception_upper":"1992-01-31",
    "iso:country":"GB",
    "wof:name":"OL5 9SA",
    "wof:placetype":"postalcode"
},
  "geometry": {"coordinates":[-2.034781,53.513397],"type":"Point"}
}