{
  "type": "Feature",
  "properties": {
    "iso:country": "GB",
    "wof:name": "OL5 9SA",
    "wof:placetype": "postalcode"
  },
  "geometry": {"coordinates":[-2.034781,53.513397],"type":"Point"}
}
