{
  "type": "Feature",
  "properties": {
    "iso:country": "GB",
    "wof:name": "BA2 0ES",
    "wof:placetype": "postalcode"
  },
  "geometry": {"coordinates":[-2.483102,51.323668],"type":"Point"}
}
