{
  "type": "Feature",
  "properties": {
    "iso:country":"GB",
    "wof:name":"BA2 0ES",
    "wof:placetype":"postalcode"
},
  "geometry": {"coordinates":[-2.48310173556283,51.323668336943],"type":"Point"}
}