{
  "type": "Feature",
  "properties": {
    "iso:country":"GB",
    "wof:name":"HA9 8RQ",
    "wof:placetype":"postalcode"
},
  "geometry": {"coordinates":[-0.30512570553643,51.57108134780748],"type":"Point"}
}