{
  "type": "Feature",
  "properties": {
    "iso:country":"GB",
    "wof:name":"SP4 0BB",
    "wof:placetype":"postalcode"
},
  "geometry": {"coordinates":[-1.71054904170572,51.15494644515035],"type":"Point"}
}