{
  "type": "Feature",
  "properties": {
    "iso:country":"GB",
    "wof:name":"AL8 7AF",
    "wof:placetype":"postalcode"
},
  "geometry": {"coordinates":[-0.19997283776669,51.81580260854317],"type":"Point"}
}