{
  "type": "Feature",
  "properties": {
    "iso:country":"GB",
    "wof:name":"CB21 4XE",
    "wof:placetype":"postalcode"
},
  "geometry": {"coordinates":[0.28879703496808,52.10031463537316],"type":"Point"}
}