{
  "type": "Feature",
  "properties": {
    "iso:country":"GB",
    "wof:name":"SE5 7BN",
    "wof:placetype":"postalcode"
},
  "geometry": {"coordinates":[-0.09102332060579,51.4745948323024],"type":"Point"}
}