{
  "type": "Feature",
  "properties": {
    "iso:country":"GB",
    "wof:name":"WN2 4RS",
    "wof:placetype":"postalcode"
},
  "geometry": {"coordinates":[-2.5620235780254,53.52611100609302],"type":"Point"}
}