{
  "type": "Feature",
  "properties": {
    "iso:country": "GB",
    "wof:name": "TN26 3JF",
    "wof:placetype": "postalcode"
  },
  "geometry": {"coordinates":[0.708104,51.095103],"type":"Point"}
}
