{
  "type": "Feature",
  "properties": {
    "iso:country":"GB",
    "wof:name":"SA62 4DE",
    "wof:placetype":"postalcode"
},
  "geometry": {"coordinates":[-4.94453292187224,51.83283850139362],"type":"Point"}
}