{
  "type": "Feature",
  "properties": {
    "date:inception_lower":"1980-01-01",
    "date:inception_upper":"1980-01-31",
    "iso:country":"GB",
    "wof:name":"SA62 4DE",
    "wof:placetype":"postalcode"
},
  "geometry": {"coordinates":[-4.944533,51.832839],"type":"Point"}
}