{
  "type": "Feature",
  "properties": {
    "iso:country":"GB",
    "wof:name":"IV19 1NH",
    "wof:placetype":"postalcode"
},
  "geometry": {"coordinates":[-4.05777633405156,57.79379566070671],"type":"Point"}
}