{
  "type": "Feature",
  "properties": {
    "date:inception_lower": "1980-01-01",
    "date:inception_upper": "1980-01-01",
    "iso:country": "GB",
    "wof:name": "IV19 1NH",
    "wof:placetype": "postalcode"
  },
  "geometry": {"coordinates":[-4.057777,57.793781],"type":"Point"}
}
