{
  "type": "Feature",
  "properties": {
    "iso:country":"GB",
    "wof:name":"BR6 7JU",
    "wof:placetype":"postalcode"
},
  "geometry": {"coordinates":[0.05515952888476,51.32338998772776],"type":"Point"}
}