{
  "type": "Feature",
  "properties": {
    "iso:country":"GB",
    "wof:name":"CV6 3GJ",
    "wof:placetype":"postalcode"
},
  "geometry": {"coordinates":[-1.51623202812385,52.42685880789466],"type":"Point"}
}