{
  "type": "Feature",
  "properties": {
    "iso:country":"GB",
    "wof:name":"LS29 9AX",
    "wof:placetype":"postalcode"
},
  "geometry": {"coordinates":[-1.83836250453705,53.92590027150016],"type":"Point"}
}