{
  "type": "Feature",
  "properties": {
    "iso:country": "GB",
    "wof:name": "LS29 9AX",
    "wof:placetype": "postalcode"
  },
  "geometry": {"coordinates":[-1.838362,53.9259],"type":"Point"}
}
