{
  "type": "Feature",
  "properties": {
    "iso:country":"GB",
    "wof:name":"G65 0QN",
    "wof:placetype":"postalcode"
},
  "geometry": {"coordinates":[-4.0054883944555,55.98873505618557],"type":"Point"}
}