{
  "type": "Feature",
  "properties": {
    "iso:country": "GB",
    "wof:name": "G65 0QN",
    "wof:placetype": "postalcode"
  },
  "geometry": {"coordinates":[-4.005488,55.988735],"type":"Point"}
}
