{
  "type": "Feature",
  "properties": {
    "iso:country":"GB",
    "wof:name":"TN12 0EX",
    "wof:placetype":"postalcode"
},
  "geometry": {"coordinates":[0.54897118068866,51.14719624294685],"type":"Point"}
}