{
  "type": "Feature",
  "properties": {
    "date:inception_lower": "1980-01-01",
    "date:inception_upper": "1980-01-01",
    "iso:country": "GB",
    "wof:name": "TN12 0EX",
    "wof:placetype": "postalcode"
  },
  "geometry": {"coordinates":[0.548971,51.147196],"type":"Point"}
}
