{
  "type": "Feature",
  "properties": {
    "iso:country": "GB",
    "wof:name": "TN12 0EX",
    "wof:placetype": "postalcode"
  },
  "geometry": {"coordinates":[0.548971,51.147196],"type":"Point"}
}
