{
  "type": "Feature",
  "properties": {
    "date:inception_lower":"1980-01-01",
    "date:inception_upper":"1980-01-31",
    "iso:country":"GB",
    "wof:name":"RH20 3BU",
    "wof:placetype":"postalcode"
},
  "geometry": {"coordinates":[-0.400264,50.926103],"type":"Point"}
}