{
  "type": "Feature",
  "properties": {
    "iso:country":"GB",
    "wof:name":"RH20 3BU",
    "wof:placetype":"postalcode"
},
  "geometry": {"coordinates":[-0.39950454750881,50.92532536363066],"type":"Point"}
}