{
  "type": "Feature",
  "properties": {
    "iso:country": "GB",
    "wof:name": "KY5 8NP",
    "wof:placetype": "postalcode"
  },
  "geometry": {"coordinates":[-3.331796,56.164086],"type":"Point"}
}
