{
  "type": "Feature",
  "properties": {
    "iso:country":"GB",
    "wof:name":"KY5 8NP",
    "wof:placetype":"postalcode"
},
  "geometry": {"coordinates":[-3.33179562313745,56.16408620450956],"type":"Point"}
}