{
  "type": "Feature",
  "properties": {
    "iso:country":"GB",
    "wof:name":"HU8 7HA",
    "wof:placetype":"postalcode"
},
  "geometry": {"coordinates":[-0.32906171431231,53.74945559552435],"type":"Point"}
}