{
  "type": "Feature",
  "properties": {
    "date:inception_lower": "2005-03-01",
    "date:inception_upper": "2005-03-01",
    "iso:country": "GB",
    "wof:name": "HU8 7HA",
    "wof:placetype": "postalcode"
  },
  "geometry": {"coordinates":[-0.328909,53.748899],"type":"Point"}
}
