{
  "type": "Feature",
  "properties": {
    "date:inception_lower": "2018-08-01",
    "date:inception_upper": "2018-08-01",
    "iso:country": "GB",
    "wof:name": "OX11 8QJ",
    "wof:placetype": "postalcode"
  },
  "geometry": {"coordinates":[-1.250788,51.605746],"type":"Point"}
}
