{
  "type": "Feature",
  "properties": {
    "iso:country":"GB",
    "wof:name":"TF1 1PT",
    "wof:placetype":"postalcode"
},
  "geometry": {"coordinates":[-2.50758031451224,52.70041000496691],"type":"Point"}
}