{
  "type": "Feature",
  "properties": {
    "date:inception_lower": "1980-01-01",
    "date:inception_upper": "1980-01-01",
    "iso:country": "GB",
    "wof:name": "DN5 9RH",
    "wof:placetype": "postalcode"
  },
  "geometry": {"coordinates":[-1.152042,53.540554],"type":"Point"}
}
