{
  "type": "Feature",
  "properties": {
    "iso:country":"GB",
    "wof:name":"KA7 2QH",
    "wof:placetype":"postalcode"
},
  "geometry": {"coordinates":[-4.62612336567489,55.44545192627439],"type":"Point"}
}