{
  "type": "Feature",
  "properties": {
    "iso:country":"GB",
    "wof:name":"NG9 6JN",
    "wof:placetype":"postalcode"
},
  "geometry": {"coordinates":[-1.26632577057699,52.91243695531357],"type":"Point"}
}