{
  "type": "Feature",
  "properties": {
    "iso:country": "GB",
    "wof:name": "NG9 6JN",
    "wof:placetype": "postalcode"
  },
  "geometry": {"coordinates":[-1.266326,52.912437],"type":"Point"}
}
