{
  "type": "Feature",
  "properties": {
    "iso:country":"GB",
    "wof:name":"LS2 7PF",
    "wof:placetype":"postalcode"
},
  "geometry": {"coordinates":[-1.53858378326145,53.8010807375806],"type":"Point"}
}