{
  "type": "Feature",
  "properties": {
    "iso:country":"GB",
    "wof:name":"LD3 0EB",
    "wof:placetype":"postalcode"
},
  "geometry": {"coordinates":[-3.19043905359751,52.0002442411218],"type":"Point"}
}