{
  "type": "Feature",
  "properties": {
    "iso:country":"GB",
    "wof:name":"SE28 0DD",
    "wof:placetype":"postalcode"
},
  "geometry": {"coordinates":[0.08829263630366,51.49773412015909],"type":"Point"}
}