{
  "type": "Feature",
  "properties": {
    "iso:country": "GB",
    "wof:name": "CF39 8JP",
    "wof:placetype": "postalcode"
  },
  "geometry": {"coordinates":[-3.459118,51.582623],"type":"Point"}
}
