{
  "type": "Feature",
  "properties": {
    "date:inception_lower":"2006-07-01",
    "date:inception_upper":"2006-07-31",
    "iso:country":"GB",
    "wof:name":"CF39 8JP",
    "wof:placetype":"postalcode"
},
  "geometry": {"coordinates":[-3.459118,51.582623],"type":"Point"}
}