{
  "type": "Feature",
  "properties": {
    "iso:country":"GB",
    "wof:name":"DL14 8HU",
    "wof:placetype":"postalcode"
},
  "geometry": {"coordinates":[-1.62260842661914,54.66582373467883],"type":"Point"}
}