{
  "type": "Feature",
  "properties": {
    "iso:country": "GB",
    "wof:name": "DL14 8HU",
    "wof:placetype": "postalcode"
  },
  "geometry": {"coordinates":[-1.622608,54.665824],"type":"Point"}
}
