{
  "type": "Feature",
  "properties": {
    "date:inception_lower":"1980-01-01",
    "date:inception_upper":"1980-01-31",
    "iso:country":"GB",
    "wof:name":"TS11 8EA",
    "wof:placetype":"postalcode"
},
  "geometry": {"coordinates":[-1.061922,54.5911],"type":"Point"}
}