{
  "type": "Feature",
  "properties": {
    "iso:country":"GB",
    "wof:name":"DA11 9AE",
    "wof:placetype":"postalcode"
},
  "geometry": {"coordinates":[0.31802906246637,51.44952181359495],"type":"Point"}
}