{
  "type": "Feature",
  "properties": {
    "iso:country": "GB",
    "wof:name": "DA11 9AE",
    "wof:placetype": "postalcode"
  },
  "geometry": {"coordinates":[0.318029,51.449522],"type":"Point"}
}
