{
  "type": "Feature",
  "properties": {
    "date:inception_lower":"2006-05-01",
    "date:inception_upper":"2006-05-31",
    "iso:country":"GB",
    "wof:name":"DA11 9AE",
    "wof:placetype":"postalcode"
},
  "geometry": {"coordinates":[0.318029,51.449522],"type":"Point"}
}