{
  "type": "Feature",
  "properties": {
    "iso:country":"GB",
    "wof:name":"L21 5HP",
    "wof:placetype":"postalcode"
},
  "geometry": {"coordinates":[-2.98499774219625,53.47328817576109],"type":"Point"}
}