{
  "type": "Feature",
  "properties": {
    "iso:country": "GB",
    "wof:name": "L21 5HP",
    "wof:placetype": "postalcode"
  },
  "geometry": {"coordinates":[-2.984998,53.473288],"type":"Point"}
}
