{
  "type": "Feature",
  "properties": {
    "iso:country":"GB",
    "wof:name":"TA14 6QB",
    "wof:placetype":"postalcode"
},
  "geometry": {"coordinates":[-2.75469717050097,50.95309427387032],"type":"Point"}
}