{
  "type": "Feature",
  "properties": {
    "date:inception_lower": "1980-01-01",
    "date:inception_upper": "1980-01-01",
    "iso:country": "GB",
    "wof:name": "TA14 6QB",
    "wof:placetype": "postalcode"
  },
  "geometry": {"coordinates":[-2.754697,50.953094],"type":"Point"}
}
