{
  "type": "Feature",
  "properties": {
    "iso:country": "GB",
    "wof:name": "S6 1AE",
    "wof:placetype": "postalcode"
  },
  "geometry": {"coordinates":[-1.493141,53.426074],"type":"Point"}
}
