{
  "type": "Feature",
  "properties": {
    "iso:country":"GB",
    "wof:name":"G52 1AU",
    "wof:placetype":"postalcode"
},
  "geometry": {"coordinates":[-4.32624484394519,55.84983017376284],"type":"Point"}
}