{
  "type": "Feature",
  "properties": {
    "date:inception_lower":"1980-01-01",
    "date:inception_upper":"1980-01-31",
    "iso:country":"GB",
    "wof:name":"G52 1AU",
    "wof:placetype":"postalcode"
},
  "geometry": {"coordinates":[-4.326245,55.84983],"type":"Point"}
}