{
  "type": "Feature",
  "properties": {
    "iso:country":"GB",
    "wof:name":"N17 0SY",
    "wof:placetype":"postalcode"
},
  "geometry": {"coordinates":[-0.05788555361927,51.60440687733313],"type":"Point"}
}