{
  "type": "Feature",
  "properties": {
    "iso:country":"GB",
    "wof:name":"L23 1TN",
    "wof:placetype":"postalcode"
},
  "geometry": {"coordinates":[-2.9982668100874,53.50197821896064],"type":"Point"}
}