{
  "type": "Feature",
  "properties": {
    "iso:country": "GB",
    "wof:name": "L23 1TN",
    "wof:placetype": "postalcode"
  },
  "geometry": {"coordinates":[-2.998267,53.501978],"type":"Point"}
}
