{
  "type": "Feature",
  "properties": {
    "iso:country": "GB",
    "wof:name": "LA23 2LX",
    "wof:placetype": "postalcode"
  },
  "geometry": {"coordinates":[-2.895193,54.374279],"type":"Point"}
}
