{
  "type": "Feature",
  "properties": {
    "date:inception_lower":"1984-10-01",
    "date:inception_upper":"1984-10-31",
    "iso:country":"GB",
    "wof:name":"LA23 2LX",
    "wof:placetype":"postalcode"
},
  "geometry": {"coordinates":[-2.895193,54.374279],"type":"Point"}
}