{
  "type": "Feature",
  "properties": {
    "date:inception_lower": "2010-11-01",
    "date:inception_upper": "2010-11-01",
    "iso:country": "GB",
    "wof:name": "IP13 6GA",
    "wof:placetype": "postalcode"
  },
  "geometry": {"coordinates":[1.248771,52.108405],"type":"Point"}
}
