{
  "type": "Feature",
  "properties": {
    "iso:country":"GB",
    "wof:name":"IP13 6GA",
    "wof:placetype":"postalcode"
},
  "geometry": {"coordinates":[1.2487712458545,52.10840489022477],"type":"Point"}
}