{
  "type": "Feature",
  "properties": {
    "iso:country": "GB",
    "wof:name": "HU12 9HT",
    "wof:placetype": "postalcode"
  },
  "geometry": {"coordinates":[-0.114132,53.740432],"type":"Point"}
}
