{
  "type": "Feature",
  "properties": {
    "date:inception_lower":"1980-01-01",
    "date:inception_upper":"1980-01-31",
    "iso:country":"GB",
    "wof:name":"HU12 9HT",
    "wof:placetype":"postalcode"
},
  "geometry": {"coordinates":[-0.114132,53.740432],"type":"Point"}
}