{
  "type": "Feature",
  "properties": {
    "iso:country":"GB",
    "wof:name":"G41 3LG",
    "wof:placetype":"postalcode"
},
  "geometry": {"coordinates":[-4.28302721850993,55.82800935619547],"type":"Point"}
}