{
  "type": "Feature",
  "properties": {
    "iso:country": "GB",
    "wof:name": "CV7 9FN",
    "wof:placetype": "postalcode"
  },
  "geometry": {"coordinates":[-1.477292,52.467688],"type":"Point"}
}
