{
  "type": "Feature",
  "properties": {
    "iso:country":"GB",
    "wof:name":"LE3 2TT",
    "wof:placetype":"postalcode"
},
  "geometry": {"coordinates":[-1.17934661871639,52.60727657999146],"type":"Point"}
}