{
  "type": "Feature",
  "properties": {
    "iso:country": "GB",
    "wof:name": "SW1W 9NX",
    "wof:placetype": "postalcode"
  },
  "geometry": {"coordinates":[-0.14986,51.494198],"type":"Point"}
}
