{
  "type": "Feature",
  "properties": {
    "date:inception_lower": "1985-04-01",
    "date:inception_upper": "1985-04-01",
    "iso:country": "GB",
    "wof:name": "RH6 9XL",
    "wof:placetype": "postalcode"
  },
  "geometry": {"coordinates":[-0.152185,51.175927],"type":"Point"}
}
