{
  "type": "Feature",
  "properties": {
    "iso:country": "GB",
    "wof:name": "BH20 5HP",
    "wof:placetype": "postalcode"
  },
  "geometry": {"coordinates":[-2.105603,50.672995],"type":"Point"}
}
