{
  "type": "Feature",
  "properties": {
    "date:inception_lower": "1995-12-01",
    "date:inception_upper": "1995-12-01",
    "iso:country": "GB",
    "wof:name": "BH20 5HP",
    "wof:placetype": "postalcode"
  },
  "geometry": {"coordinates":[-2.105603,50.672995],"type":"Point"}
}
