{
  "type": "Feature",
  "properties": {
    "date:inception_lower": "1980-01-01",
    "date:inception_upper": "1980-01-01",
    "iso:country": "GB",
    "wof:name": "S5 6LB",
    "wof:placetype": "postalcode"
  },
  "geometry": {"coordinates":[-1.445171,53.423219],"type":"Point"}
}
