{
  "type": "Feature",
  "properties": {
    "iso:country": "GB",
    "wof:name": "CO6 1UP",
    "wof:placetype": "postalcode"
  },
  "geometry": {"coordinates":[0.682973,51.872882],"type":"Point"}
}
