{
  "type": "Feature",
  "properties": {
    "iso:country": "GB",
    "wof:name": "LL58 8UN",
    "wof:placetype": "postalcode"
  },
  "geometry": {"coordinates":[-4.148357,53.300301],"type":"Point"}
}
