{
  "type": "Feature",
  "properties": {
    "iso:country":"GB",
    "wof:name":"LL58 8UN",
    "wof:placetype":"postalcode"
},
  "geometry": {"coordinates":[-4.14835720759476,53.30030143715084],"type":"Point"}
}