{
  "type": "Feature",
  "properties": {
    "iso:country": "GB",
    "wof:name": "AB51 4EZ",
    "wof:placetype": "postalcode"
  },
  "geometry": {"coordinates":[-2.402035,57.288621],"type":"Point"}
}
