{
  "type": "Feature",
  "properties": {
    "iso:country":"GB",
    "wof:name":"SN12 6BU",
    "wof:placetype":"postalcode"
},
  "geometry": {"coordinates":[-2.14541070309338,51.35986757266055],"type":"Point"}
}