{
  "type": "Feature",
  "properties": {
    "iso:country": "GB",
    "wof:name": "SN12 6BU",
    "wof:placetype": "postalcode"
  },
  "geometry": {"coordinates":[-2.145411,51.359868],"type":"Point"}
}
