{
  "type": "Feature",
  "properties": {
    "iso:country": "GB",
    "wof:name": "L8 6TX",
    "wof:placetype": "postalcode"
  },
  "geometry": {"coordinates":[-2.978321,53.388012],"type":"Point"}
}
