{
  "type": "Feature",
  "properties": {
    "iso:country":"GB",
    "wof:name":"TS10 1QQ",
    "wof:placetype":"postalcode"
},
  "geometry": {"coordinates":[-1.07720659639293,54.61666894311325],"type":"Point"}
}