{
  "type": "Feature",
  "properties": {
    "iso:country": "GB",
    "wof:name": "TS10 1QQ",
    "wof:placetype": "postalcode"
  },
  "geometry": {"coordinates":[-1.077207,54.616669],"type":"Point"}
}
