{
  "type": "Feature",
  "properties": {
    "date:inception_lower":"1983-07-01",
    "date:inception_upper":"1983-07-31",
    "iso:country":"GB",
    "wof:name":"MK45 1DZ",
    "wof:placetype":"postalcode"
},
  "geometry": {"coordinates":[-0.493932,52.004954],"type":"Point"}
}