{
  "type": "Feature",
  "properties": {
    "iso:country":"GB",
    "wof:name":"MK45 1DZ",
    "wof:placetype":"postalcode"
},
  "geometry": {"coordinates":[-0.49393173504662,52.00495417595951],"type":"Point"}
}