{
  "type": "Feature",
  "properties": {
    "iso:country":"GB",
    "wof:name":"HP8 4EA",
    "wof:placetype":"postalcode"
},
  "geometry": {"coordinates":[-0.56921376480709,51.63102249810389],"type":"Point"}
}