{
  "type": "Feature",
  "properties": {
    "date:inception_lower": "2010-05-01",
    "date:inception_upper": "2010-05-01",
    "iso:country": "GB",
    "wof:name": "HP8 4EA",
    "wof:placetype": "postalcode"
  },
  "geometry": {"coordinates":[-0.569214,51.631022],"type":"Point"}
}
