{
  "type": "Feature",
  "properties": {
    "date:inception_lower": "1998-06-01",
    "date:inception_upper": "1998-06-01",
    "iso:country": "GB",
    "wof:name": "YO19 5RR",
    "wof:placetype": "postalcode"
  },
  "geometry": {"coordinates":[-0.98562,53.962498],"type":"Point"}
}
