{
  "type": "Feature",
  "properties": {
    "iso:country":"GB",
    "wof:name":"BN27 3EE",
    "wof:placetype":"postalcode"
},
  "geometry": {"coordinates":[0.25030284111655,50.86364022694009],"type":"Point"}
}