{
  "type": "Feature",
  "properties": {
    "date:inception_lower":"1999-12-01",
    "date:inception_upper":"1999-12-31",
    "iso:country":"GB",
    "wof:name":"LS21 1TB",
    "wof:placetype":"postalcode"
},
  "geometry": {"coordinates":[-1.680306,53.906377],"type":"Point"}
}