{
  "type": "Feature",
  "properties": {
    "iso:country": "GB",
    "wof:name": "GU32 2ES",
    "wof:placetype": "postalcode"
  },
  "geometry": {"coordinates":[-0.945546,51.009004],"type":"Point"}
}
