{
  "type": "Feature",
  "properties": {
    "date:inception_lower": "1984-02-01",
    "date:inception_upper": "1984-02-01",
    "iso:country": "GB",
    "wof:name": "GU32 2ES",
    "wof:placetype": "postalcode"
  },
  "geometry": {"coordinates":[-0.945546,51.009004],"type":"Point"}
}
