{
  "type": "Feature",
  "properties": {
    "iso:country":"GB",
    "wof:name":"SP10 2BX",
    "wof:placetype":"postalcode"
},
  "geometry": {"coordinates":[-1.481256024679,51.20230723967654],"type":"Point"}
}