{
  "type": "Feature",
  "properties": {
    "iso:country":"GB",
    "wof:name":"EH48 2LQ",
    "wof:placetype":"postalcode"
},
  "geometry": {"coordinates":[-3.68307587765413,55.89546596469445],"type":"Point"}
}