{
  "type": "Feature",
  "properties": {
    "iso:country": "GB",
    "wof:name": "EH48 2LQ",
    "wof:placetype": "postalcode"
  },
  "geometry": {"coordinates":[-3.683163,55.895442],"type":"Point"}
}
