{
  "type": "Feature",
  "properties": {
    "date:inception_lower": "1980-01-01",
    "date:inception_upper": "1980-01-01",
    "iso:country": "GB",
    "wof:name": "WF17 9AT",
    "wof:placetype": "postalcode"
  },
  "geometry": {"coordinates":[-1.660786,53.728317],"type":"Point"}
}
