{
  "type": "Feature",
  "properties": {
    "iso:country":"GB",
    "wof:name":"WF17 9AT",
    "wof:placetype":"postalcode"
},
  "geometry": {"coordinates":[-1.66078618292152,53.72831661305972],"type":"Point"}
}