{
  "type": "Feature",
  "properties": {
    "iso:country":"GB",
    "wof:name":"TN1 2TX",
    "wof:placetype":"postalcode"
},
  "geometry": {"coordinates":[0.26588856836751,51.13442654665584],"type":"Point"}
}