{
  "type": "Feature",
  "properties": {
    "iso:country": "GB",
    "wof:name": "IG8 8DH",
    "wof:placetype": "postalcode"
  },
  "geometry": {"coordinates":[0.056506,51.60512],"type":"Point"}
}
