{
  "type": "Feature",
  "properties": {
    "iso:country": "GB",
    "wof:name": "B60 3LT",
    "wof:placetype": "postalcode"
  },
  "geometry": {"coordinates":[-2.071572,52.32496],"type":"Point"}
}
