{
  "type": "Feature",
  "properties": {
    "iso:country":"GB",
    "wof:name":"WV16 6PQ",
    "wof:placetype":"postalcode"
},
  "geometry": {"coordinates":[-2.41822496518588,52.45520075372801],"type":"Point"}
}