{
  "type": "Feature",
  "properties": {
    "date:inception_lower": "1980-01-01",
    "date:inception_upper": "1980-01-01",
    "iso:country": "GB",
    "wof:name": "KA3 6JH",
    "wof:placetype": "postalcode"
  },
  "geometry": {"coordinates":[-4.400693,55.664117],"type":"Point"}
}
