{
  "type": "Feature",
  "properties": {
    "iso:country": "GB",
    "wof:name": "ME7 4DX",
    "wof:placetype": "postalcode"
  },
  "geometry": {"coordinates":[0.556534,51.38166],"type":"Point"}
}
