{
  "type": "Feature",
  "properties": {
    "iso:country":"GB",
    "wof:name":"ME7 4DX",
    "wof:placetype":"postalcode"
},
  "geometry": {"coordinates":[0.55653348229028,51.38166043659512],"type":"Point"}
}