{
  "type": "Feature",
  "properties": {
    "date:inception_lower": "1980-01-01",
    "date:inception_upper": "1980-01-01",
    "iso:country": "GB",
    "wof:name": "DE55 1AU",
    "wof:placetype": "postalcode"
  },
  "geometry": {"coordinates":[-1.389324,53.069601],"type":"Point"}
}
