{
  "type": "Feature",
  "properties": {
    "iso:country": "GB",
    "wof:name": "DE55 1AU",
    "wof:placetype": "postalcode"
  },
  "geometry": {"coordinates":[-1.389324,53.069601],"type":"Point"}
}
