{
  "type": "Feature",
  "properties": {
    "iso:country": "GB",
    "wof:name": "GL1 5JL",
    "wof:placetype": "postalcode"
  },
  "geometry": {"coordinates":[-2.243378,51.854119],"type":"Point"}
}
