{
  "type": "Feature",
  "properties": {
    "iso:country":"GB",
    "wof:name":"NE63 8AZ",
    "wof:placetype":"postalcode"
},
  "geometry": {"coordinates":[-1.57228414253358,55.18087123927509],"type":"Point"}
}