{
  "type": "Feature",
  "properties": {
    "iso:country":"GB",
    "wof:name":"HP27 0EE",
    "wof:placetype":"postalcode"
},
  "geometry": {"coordinates":[-0.83646151175681,51.71872951704745],"type":"Point"}
}