{
  "type": "Feature",
  "properties": {
    "iso:country": "GB",
    "wof:name": "BH20 4NB",
    "wof:placetype": "postalcode"
  },
  "geometry": {"coordinates":[-2.108994,50.68513],"type":"Point"}
}
