{
  "type": "Feature",
  "properties": {
    "iso:country":"GB",
    "wof:name":"LA22 9PT",
    "wof:placetype":"postalcode"
},
  "geometry": {"coordinates":[-3.02779441844153,54.4566175997705],"type":"Point"}
}