{
  "type": "Feature",
  "properties": {
    "iso:country":"GB",
    "wof:name":"SA11 4AA",
    "wof:placetype":"postalcode"
},
  "geometry": {"coordinates":[-3.69497145942205,51.70956935532213],"type":"Point"}
}