{
  "type": "Feature",
  "properties": {
    "iso:country":"GB",
    "wof:name":"NP18 3RQ",
    "wof:placetype":"postalcode"
},
  "geometry": {"coordinates":[-2.98022376045665,51.61111412246532],"type":"Point"}
}