{
  "type": "Feature",
  "properties": {
    "iso:country":"GB",
    "wof:name":"PO35 5TP",
    "wof:placetype":"postalcode"
},
  "geometry": {"coordinates":[-1.07508208800337,50.68300870263788],"type":"Point"}
}