{
  "type": "Feature",
  "properties": {
    "date:inception_lower": "1980-01-01",
    "date:inception_upper": "1980-01-01",
    "iso:country": "GB",
    "wof:name": "PO35 5TP",
    "wof:placetype": "postalcode"
  },
  "geometry": {"coordinates":[-1.075082,50.683009],"type":"Point"}
}
