{
  "type": "Feature",
  "properties": {
    "iso:country":"GB",
    "wof:name":"DY12 1RX",
    "wof:placetype":"postalcode"
},
  "geometry": {"coordinates":[-2.31506245551301,52.42784936831257],"type":"Point"}
}