{
  "type": "Feature",
  "properties": {
    "iso:country": "GB",
    "wof:name": "L26 9AD",
    "wof:placetype": "postalcode"
  },
  "geometry": {"coordinates":[-2.828619,53.359967],"type":"Point"}
}
