{
  "type": "Feature",
  "properties": {
    "iso:country":"GB",
    "wof:name":"BS36 2FL",
    "wof:placetype":"postalcode"
},
  "geometry": {"coordinates":[-2.48253338122985,51.52484988950202],"type":"Point"}
}