{
  "type": "Feature",
  "properties": {
    "date:inception_lower": "2012-02-01",
    "date:inception_upper": "2012-02-01",
    "iso:country": "GB",
    "wof:name": "BS36 2FL",
    "wof:placetype": "postalcode"
  },
  "geometry": {"coordinates":[-2.482518,51.524849],"type":"Point"}
}
