{
  "type": "Feature",
  "properties": {
    "iso:country": "GB",
    "wof:name": "DL14 6TZ",
    "wof:placetype": "postalcode"
  },
  "geometry": {"coordinates":[-1.685381,54.656073],"type":"Point"}
}
