{
  "type": "Feature",
  "properties": {
    "iso:country":"GB",
    "wof:name":"FK2 0QH",
    "wof:placetype":"postalcode"
},
  "geometry": {"coordinates":[-3.70878976139241,55.99282815000053],"type":"Point"}
}