{
  "type": "Feature",
  "properties": {
    "iso:country": "GB",
    "wof:name": "E13 9FG",
    "wof:placetype": "postalcode"
  },
  "geometry": {"coordinates":[0.040051,51.53184],"type":"Point"}
}
