{
  "type": "Feature",
  "properties": {
    "iso:country":"GB",
    "wof:name":"EH22 2BA",
    "wof:placetype":"postalcode"
},
  "geometry": {"coordinates":[-3.05818214727857,55.89350980347733],"type":"Point"}
}