{
  "type": "Feature",
  "properties": {
    "iso:country":"GB",
    "wof:name":"WA4 4SE",
    "wof:placetype":"postalcode"
},
  "geometry": {"coordinates":[-2.5512972288436,53.34583121256066],"type":"Point"}
}