{
  "type": "Feature",
  "properties": {
    "iso:country": "GB",
    "wof:name": "CH63 3HZ",
    "wof:placetype": "postalcode"
  },
  "geometry": {"coordinates":[-3.008162,53.347681],"type":"Point"}
}
