{
  "type": "Feature",
  "properties": {
    "iso:country":"GB",
    "wof:name":"BH25 7NF",
    "wof:placetype":"postalcode"
},
  "geometry": {"coordinates":[-1.66620930177579,50.73721461324278],"type":"Point"}
}