{
  "type": "Feature",
  "properties": {
    "date:inception_lower": "1993-01-01",
    "date:inception_upper": "1993-01-01",
    "iso:country": "GB",
    "wof:name": "BH25 7NF",
    "wof:placetype": "postalcode"
  },
  "geometry": {"coordinates":[-1.666209,50.737215],"type":"Point"}
}
