{
  "type": "Feature",
  "properties": {
    "date:inception_lower": "2023-07-01",
    "date:inception_upper": "2023-07-01",
    "iso:country": "GB",
    "wof:name": "LU3 2FG",
    "wof:placetype": "postalcode"
  },
  "geometry": {"coordinates":[-0.441645,51.909296],"type":"Point"}
}
