{
  "type": "Feature",
  "properties": {
    "iso:country":"GB",
    "wof:name":"NR19 1AG",
    "wof:placetype":"postalcode"
},
  "geometry": {"coordinates":[0.94307858995709,52.67541387306662],"type":"Point"}
}