{
  "type": "Feature",
  "properties": {
    "iso:country": "GB",
    "wof:name": "DN12 4DE",
    "wof:placetype": "postalcode"
  },
  "geometry": {"coordinates":[-1.253983,53.487715],"type":"Point"}
}
