{
  "type": "Feature",
  "properties": {
    "date:inception_lower":"2012-02-01",
    "date:inception_upper":"2012-02-29",
    "iso:country":"GB",
    "wof:name":"DN12 4DE",
    "wof:placetype":"postalcode"
},
  "geometry": {"coordinates":[-1.253983,53.487715],"type":"Point"}
}