{
  "type": "Feature",
  "properties": {
    "iso:country":"GB",
    "wof:name":"DN12 4DE",
    "wof:placetype":"postalcode"
},
  "geometry": {"coordinates":[-1.25398271874818,53.48771483523328],"type":"Point"}
}