{
  "type": "Feature",
  "properties": {
    "iso:country":"GB",
    "wof:name":"GU4 7HQ",
    "wof:placetype":"postalcode"
},
  "geometry": {"coordinates":[-0.5393558201074,51.25370179527992],"type":"Point"}
}