{
  "type": "Feature",
  "properties": {
    "date:inception_lower": "1980-01-01",
    "date:inception_upper": "1980-01-01",
    "iso:country": "GB",
    "wof:name": "LS7 2NW",
    "wof:placetype": "postalcode"
  },
  "geometry": {"coordinates":[-1.550822,53.830877],"type":"Point"}
}
