{
  "type": "Feature",
  "properties": {
    "iso:country":"GB",
    "wof:name":"BH18 9NN",
    "wof:placetype":"postalcode"
},
  "geometry": {"coordinates":[-2.01537276419802,50.75809478867379],"type":"Point"}
}