{
  "type": "Feature",
  "properties": {
    "date:inception_lower": "1989-07-01",
    "date:inception_upper": "1989-07-01",
    "iso:country": "GB",
    "wof:name": "KA3 1BB",
    "wof:placetype": "postalcode"
  },
  "geometry": {"coordinates":[-4.490216,55.616368],"type":"Point"}
}
