{
  "type": "Feature",
  "properties": {
    "iso:country":"GB",
    "wof:name":"RH16 2RW",
    "wof:placetype":"postalcode"
},
  "geometry": {"coordinates":[-0.0797718009626,51.00303641362715],"type":"Point"}
}