{
  "type": "Feature",
  "properties": {
    "iso:country":"GB",
    "wof:name":"ZE1 0UE",
    "wof:placetype":"postalcode"
},
  "geometry": {"coordinates":[-1.27763260410434,60.13877733377321],"type":"Point"}
}