{
  "type": "Feature",
  "properties": {
    "date:inception_lower": "1998-12-01",
    "date:inception_upper": "1998-12-01",
    "iso:country": "GB",
    "wof:name": "ZE1 0UE",
    "wof:placetype": "postalcode"
  },
  "geometry": {"coordinates":[-1.277633,60.138777],"type":"Point"}
}
