{
  "type": "Feature",
  "properties": {
    "iso:country": "GB",
    "wof:name": "NG14 5DZ",
    "wof:placetype": "postalcode"
  },
  "geometry": {"coordinates":[-1.036609,52.987838],"type":"Point"}
}
