{
  "type": "Feature",
  "properties": {
    "iso:country":"GB",
    "wof:name":"NG14 5DZ",
    "wof:placetype":"postalcode"
},
  "geometry": {"coordinates":[-1.03660907245438,52.98783755091891],"type":"Point"}
}