{
  "type": "Feature",
  "properties": {
    "iso:country": "GB",
    "wof:name": "AL2 2DZ",
    "wof:placetype": "postalcode"
  },
  "geometry": {"coordinates":[-0.32741,51.708635],"type":"Point"}
}
