{
  "type": "Feature",
  "properties": {
    "date:inception_lower": "1980-01-01",
    "date:inception_upper": "1980-01-01",
    "iso:country": "GB",
    "wof:name": "AL2 2DZ",
    "wof:placetype": "postalcode"
  },
  "geometry": {"coordinates":[-0.327613,51.709016],"type":"Point"}
}
