{
  "type": "Feature",
  "properties": {
    "iso:country":"GB",
    "wof:name":"AL2 2DZ",
    "wof:placetype":"postalcode"
},
  "geometry": {"coordinates":[-0.32743190274259,51.70863019331625],"type":"Point"}
}