{
  "type": "Feature",
  "properties": {
    "iso:country":"GB",
    "wof:name":"CM2 9PJ",
    "wof:placetype":"postalcode"
},
  "geometry": {"coordinates":[0.46834323660535,51.72659133665052],"type":"Point"}
}