{
  "type": "Feature",
  "properties": {
    "iso:country":"GB",
    "wof:name":"CO7 7NJ",
    "wof:placetype":"postalcode"
},
  "geometry": {"coordinates":[0.9848937585227,51.92577369521365],"type":"Point"}
}