{
  "type": "Feature",
  "properties": {
    "iso:country": "GB",
    "wof:name": "SE9 2JG",
    "wof:placetype": "postalcode"
  },
  "geometry": {"coordinates":[0.08755,51.447738],"type":"Point"}
}
