{
  "type": "Feature",
  "properties": {
    "iso:country": "GB",
    "wof:name": "ML1 3XX",
    "wof:placetype": "postalcode"
  },
  "geometry": {"coordinates":[-4.000871,55.803183],"type":"Point"}
}
