{
  "type": "Feature",
  "properties": {
    "iso:country": "GB",
    "wof:name": "DT8 3PY",
    "wof:placetype": "postalcode"
  },
  "geometry": {"coordinates":[-2.799564,50.818177],"type":"Point"}
}
