{
  "type": "Feature",
  "properties": {
    "iso:country":"GB",
    "wof:name":"DT8 3PY",
    "wof:placetype":"postalcode"
},
  "geometry": {"coordinates":[-2.79956393943841,50.81817652280587],"type":"Point"}
}