{
  "type": "Feature",
  "properties": {
    "date:inception_lower":"1983-03-01",
    "date:inception_upper":"1983-03-31",
    "iso:country":"GB",
    "wof:name":"NE2 4HQ",
    "wof:placetype":"postalcode"
},
  "geometry": {"coordinates":[-1.61116,54.981051],"type":"Point"}
}