{
  "type": "Feature",
  "properties": {
    "iso:country": "GB",
    "wof:name": "NE2 4HQ",
    "wof:placetype": "postalcode"
  },
  "geometry": {"coordinates":[-1.61116,54.981051],"type":"Point"}
}
