{
  "type": "Feature",
  "properties": {
    "iso:country": "GB",
    "wof:name": "DH6 3LG",
    "wof:placetype": "postalcode"
  },
  "geometry": {"coordinates":[-1.416613,54.740048],"type":"Point"}
}
