{
  "type": "Feature",
  "properties": {
    "date:inception_lower": "1980-01-01",
    "date:inception_upper": "1980-01-01",
    "iso:country": "GB",
    "wof:name": "DH6 3LG",
    "wof:placetype": "postalcode"
  },
  "geometry": {"coordinates":[-1.416613,54.740048],"type":"Point"}
}
