{
  "type": "Feature",
  "properties": {
    "iso:country":"GB",
    "wof:name":"DH6 3LG",
    "wof:placetype":"postalcode"
},
  "geometry": {"coordinates":[-1.41658306856527,54.7401275514767],"type":"Point"}
}