{
  "type": "Feature",
  "properties": {
    "date:inception_lower": "2017-10-01",
    "date:inception_upper": "2017-10-01",
    "iso:country": "GB",
    "wof:name": "CH3 6FW",
    "wof:placetype": "postalcode"
  },
  "geometry": {"coordinates":[-2.850525,53.173252],"type":"Point"}
}
