{
  "type": "Feature",
  "properties": {
    "iso:country":"GB",
    "wof:name":"PL21 0LZ",
    "wof:placetype":"postalcode"
},
  "geometry": {"coordinates":[-3.90110207101041,50.36440119449902],"type":"Point"}
}