{
  "type": "Feature",
  "properties": {
    "iso:country": "GB",
    "wof:name": "PL21 0LZ",
    "wof:placetype": "postalcode"
  },
  "geometry": {"coordinates":[-3.901102,50.364401],"type":"Point"}
}
