{
  "type": "Feature",
  "properties": {
    "date:inception_lower": "1992-01-01",
    "date:inception_upper": "1992-01-01",
    "iso:country": "GB",
    "wof:name": "PL21 0LZ",
    "wof:placetype": "postalcode"
  },
  "geometry": {"coordinates":[-3.901102,50.364401],"type":"Point"}
}
