{
  "type": "Feature",
  "properties": {
    "date:inception_lower": "1992-08-01",
    "date:inception_upper": "1992-08-01",
    "iso:country": "GB",
    "wof:name": "HD5 8NJ",
    "wof:placetype": "postalcode"
  },
  "geometry": {"coordinates":[-1.756187,53.633157],"type":"Point"}
}
