{
  "type": "Feature",
  "properties": {
    "iso:country": "GB",
    "wof:name": "HD5 8NJ",
    "wof:placetype": "postalcode"
  },
  "geometry": {"coordinates":[-1.756187,53.633157],"type":"Point"}
}
