{
  "type": "Feature",
  "properties": {
    "iso:country":"GB",
    "wof:name":"SS6 9BY",
    "wof:placetype":"postalcode"
},
  "geometry": {"coordinates":[0.59666843129577,51.59647878530205],"type":"Point"}
}