{
  "type": "Feature",
  "properties": {
    "iso:country": "GB",
    "wof:name": "SS6 9BY",
    "wof:placetype": "postalcode"
  },
  "geometry": {"coordinates":[0.596695,51.596475],"type":"Point"}
}
