{
  "type": "Feature",
  "properties": {
    "iso:country": "GB",
    "wof:name": "DL5 7HU",
    "wof:placetype": "postalcode"
  },
  "geometry": {"coordinates":[-1.597168,54.628033],"type":"Point"}
}
