{
  "type": "Feature",
  "properties": {
    "iso:country": "GB",
    "wof:name": "NE48 1NX",
    "wof:placetype": "postalcode"
  },
  "geometry": {"coordinates":[-2.331851,55.166372],"type":"Point"}
}
