{
  "type": "Feature",
  "properties": {
    "iso:country": "GB",
    "wof:name": "NE48 1NX",
    "wof:placetype": "postalcode"
  },
  "geometry": {"coordinates":[-2.332287,55.16603],"type":"Point"}
}
