{
  "type": "Feature",
  "properties": {
    "iso:country":"GB",
    "wof:name":"KA13 6WG",
    "wof:placetype":"postalcode"
},
  "geometry": {"coordinates":[-4.72298801784102,55.65817928331992],"type":"Point"}
}