{
  "type": "Feature",
  "properties": {
    "iso:country": "GB",
    "wof:name": "KA13 6WG",
    "wof:placetype": "postalcode"
  },
  "geometry": {"coordinates":[-4.722613,55.658346],"type":"Point"}
}
