{
  "type": "Feature",
  "properties": {
    "date:inception_lower":"2014-09-01",
    "date:inception_upper":"2014-09-30",
    "iso:country":"GB",
    "wof:name":"KA13 6WG",
    "wof:placetype":"postalcode"
},
  "geometry": {"coordinates":[-4.722613,55.658346],"type":"Point"}
}