{
  "type": "Feature",
  "properties": {
    "iso:country": "GB",
    "wof:name": "DH7 6DX",
    "wof:placetype": "postalcode"
  },
  "geometry": {"coordinates":[-1.634264,54.836991],"type":"Point"}
}
