{
  "type": "Feature",
  "properties": {
    "date:inception_lower": "1980-01-01",
    "date:inception_upper": "1980-01-01",
    "iso:country": "GB",
    "wof:name": "DH7 6DX",
    "wof:placetype": "postalcode"
  },
  "geometry": {"coordinates":[-1.634264,54.836991],"type":"Point"}
}
