{
  "type": "Feature",
  "properties": {
    "iso:country":"GB",
    "wof:name":"DH7 6DX",
    "wof:placetype":"postalcode"
},
  "geometry": {"coordinates":[-1.63426381265266,54.83699099696386],"type":"Point"}
}