{
  "type": "Feature",
  "properties": {
    "iso:country":"GB",
    "wof:name":"TF11 8JY",
    "wof:placetype":"postalcode"
},
  "geometry": {"coordinates":[-2.29135832441561,52.69526873551437],"type":"Point"}
}