{
  "type": "Feature",
  "properties": {
    "iso:country":"GB",
    "wof:name":"RG30 3JN",
    "wof:placetype":"postalcode"
},
  "geometry": {"coordinates":[-1.01595035945846,51.43939859626776],"type":"Point"}
}