{
  "type": "Feature",
  "properties": {
    "iso:country":"GB",
    "wof:name":"PA2 6BX",
    "wof:placetype":"postalcode"
},
  "geometry": {"coordinates":[-4.43118063975135,55.83987321975194],"type":"Point"}
}