{
  "type": "Feature",
  "properties": {
    "iso:country":"GB",
    "wof:name":"HP18 0DS",
    "wof:placetype":"postalcode"
},
  "geometry": {"coordinates":[-0.96046825976333,51.80438399779521],"type":"Point"}
}