{
  "type": "Feature",
  "properties": {
    "date:inception_lower": "1980-01-01",
    "date:inception_upper": "1980-01-01",
    "iso:country": "GB",
    "wof:name": "WF9 1ER",
    "wof:placetype": "postalcode"
  },
  "geometry": {"coordinates":[-1.260631,53.617533],"type":"Point"}
}
