{
  "type": "Feature",
  "properties": {
    "iso:country":"GB",
    "wof:name":"WF9 1ER",
    "wof:placetype":"postalcode"
},
  "geometry": {"coordinates":[-1.26063099126063,53.61753274545318],"type":"Point"}
}