{
  "type": "Feature",
  "properties": {
    "date:inception_lower": "1999-06-01",
    "date:inception_upper": "1999-06-01",
    "iso:country": "GB",
    "wof:name": "CH65 8BG",
    "wof:placetype": "postalcode"
  },
  "geometry": {"coordinates":[-2.903836,53.280956],"type":"Point"}
}
