{
  "type": "Feature",
  "properties": {
    "iso:country": "GB",
    "wof:name": "TN14 5BL",
    "wof:placetype": "postalcode"
  },
  "geometry": {"coordinates":[0.198548,51.291935],"type":"Point"}
}
