{
  "type": "Feature",
  "properties": {
    "iso:country":"GB",
    "wof:name":"TN14 5BL",
    "wof:placetype":"postalcode"
},
  "geometry": {"coordinates":[0.19854815531029,51.29193530658986],"type":"Point"}
}