{
  "type": "Feature",
  "properties": {
    "iso:country": "GB",
    "wof:name": "KY15 5BB",
    "wof:placetype": "postalcode"
  },
  "geometry": {"coordinates":[-3.017853,56.318016],"type":"Point"}
}
