{
  "type": "Feature",
  "properties": {
    "iso:country": "GB",
    "wof:name": "LS15 9DX",
    "wof:placetype": "postalcode"
  },
  "geometry": {"coordinates":[-1.446234,53.794623],"type":"Point"}
}
