{
  "type": "Feature",
  "properties": {
    "iso:country":"GB",
    "wof:name":"LS15 9DX",
    "wof:placetype":"postalcode"
},
  "geometry": {"coordinates":[-1.44623426934836,53.79462314276098],"type":"Point"}
}