{
  "type": "Feature",
  "properties": {
    "iso:country":"GB",
    "wof:name":"TN23 9UE",
    "wof:placetype":"postalcode"
},
  "geometry": {"coordinates":[0.8756170415649,51.14656063726332],"type":"Point"}
}