{
  "type": "Feature",
  "properties": {
    "date:inception_lower": "2018-09-01",
    "date:inception_upper": "2018-09-01",
    "iso:country": "GB",
    "wof:name": "LE1 6BB",
    "wof:placetype": "postalcode"
  },
  "geometry": {"coordinates":[-1.129738,52.631789],"type":"Point"}
}
