{
  "type": "Feature",
  "properties": {
    "iso:country": "GB",
    "wof:name": "LE1 6BB",
    "wof:placetype": "postalcode"
  },
  "geometry": {"coordinates":[-1.129723,52.63178],"type":"Point"}
}
