{
  "type": "Feature",
  "properties": {
    "iso:country":"GB",
    "wof:name":"BD1 1RJ",
    "wof:placetype":"postalcode"
},
  "geometry": {"coordinates":[-1.75364747483294,53.79385933230434],"type":"Point"}
}