{
  "type": "Feature",
  "properties": {
    "date:inception_lower": "2023-10-01",
    "date:inception_upper": "2023-10-01",
    "iso:country": "GB",
    "wof:name": "WN6 0FN",
    "wof:placetype": "postalcode"
  },
  "geometry": {"coordinates":[-2.645341,53.589991],"type":"Point"}
}
