{
  "type": "Feature",
  "properties": {
    "iso:country": "GB",
    "wof:name": "PA3 2NJ",
    "wof:placetype": "postalcode"
  },
  "geometry": {"coordinates":[-4.432513,55.855324],"type":"Point"}
}
