{
  "type": "Feature",
  "properties": {
    "iso:country":"GB",
    "wof:name":"PA3 2NJ",
    "wof:placetype":"postalcode"
},
  "geometry": {"coordinates":[-4.43251341334694,55.85532401555734],"type":"Point"}
}