{
  "type": "Feature",
  "properties": {
    "date:inception_lower": "2015-07-01",
    "date:inception_upper": "2015-07-01",
    "iso:country": "GB",
    "wof:name": "PA3 2NJ",
    "wof:placetype": "postalcode"
  },
  "geometry": {"coordinates":[-4.432513,55.855324],"type":"Point"}
}
