{
  "type": "Feature",
  "properties": {
    "iso:country":"GB",
    "wof:name":"AB38 7AX",
    "wof:placetype":"postalcode"
},
  "geometry": {"coordinates":[-3.20406972569646,57.52721010832684],"type":"Point"}
}