{
  "type": "Feature",
  "properties": {
    "date:inception_lower": "2006-07-01",
    "date:inception_upper": "2006-07-01",
    "iso:country": "GB",
    "wof:name": "AB38 7AX",
    "wof:placetype": "postalcode"
  },
  "geometry": {"coordinates":[-3.20407,57.52721],"type":"Point"}
}
