{
  "type": "Feature",
  "properties": {
    "date:inception_lower": "2022-11-01",
    "date:inception_upper": "2022-11-01",
    "iso:country": "GB",
    "wof:name": "LS23 7GE",
    "wof:placetype": "postalcode"
  },
  "geometry": {"coordinates":[-1.326405,53.920408],"type":"Point"}
}
