{
  "type": "Feature",
  "properties": {
    "iso:country": "GB",
    "wof:name": "S49 1PF",
    "wof:placetype": "postalcode"
  },
  "geometry": {"coordinates":[-1.432474,53.235033],"type":"Point"}
}
