{
  "type": "Feature",
  "properties": {
    "date:inception_lower": "1980-01-01",
    "date:inception_upper": "1980-01-01",
    "iso:country": "GB",
    "wof:name": "S49 1PF",
    "wof:placetype": "postalcode"
  },
  "geometry": {"coordinates":[-1.432474,53.235033],"type":"Point"}
}
