{
  "type": "Feature",
  "properties": {
    "iso:country": "GB",
    "wof:name": "SO20 6DG",
    "wof:placetype": "postalcode"
  },
  "geometry": {"coordinates":[-1.489214,51.114484],"type":"Point"}
}
