{
  "type": "Feature",
  "properties": {
    "date:inception_lower": "2009-06-01",
    "date:inception_upper": "2009-06-01",
    "iso:country": "GB",
    "wof:name": "SO20 6DG",
    "wof:placetype": "postalcode"
  },
  "geometry": {"coordinates":[-1.489243,51.114403],"type":"Point"}
}
