{
  "type": "Feature",
  "properties": {
    "iso:country":"GB",
    "wof:name":"SO20 6DG",
    "wof:placetype":"postalcode"
},
  "geometry": {"coordinates":[-1.48925476148055,51.11440897914479],"type":"Point"}
}