{
  "type": "Feature",
  "properties": {
    "date:inception_lower":"2009-06-01",
    "date:inception_upper":"2009-06-30",
    "iso:country":"GB",
    "wof:name":"SO20 6DG",
    "wof:placetype":"postalcode"
},
  "geometry": {"coordinates":[-1.489214,51.114484],"type":"Point"}
}