{
  "type": "Feature",
  "properties": {
    "iso:country":"GB",
    "wof:name":"SO45 6HA",
    "wof:placetype":"postalcode"
},
  "geometry": {"coordinates":[-1.39601153216578,50.86715160533522],"type":"Point"}
}