{
  "type": "Feature",
  "properties": {
    "iso:country":"GB",
    "wof:name":"CM18 7NZ",
    "wof:placetype":"postalcode"
},
  "geometry": {"coordinates":[0.09735326674673,51.75206433045749],"type":"Point"}
}