{
  "type": "Feature",
  "properties": {
    "iso:country": "GB",
    "wof:name": "DN14 6UH",
    "wof:placetype": "postalcode"
  },
  "geometry": {"coordinates":[-0.891128,53.705908],"type":"Point"}
}
