{
  "type": "Feature",
  "properties": {
    "iso:country":"GB",
    "wof:name":"DN14 6UH",
    "wof:placetype":"postalcode"
},
  "geometry": {"coordinates":[-0.89132212965423,53.7058632626124],"type":"Point"}
}