{
  "type": "Feature",
  "properties": {
    "iso:country":"GB",
    "wof:name":"BB4 8QY",
    "wof:placetype":"postalcode"
},
  "geometry": {"coordinates":[-2.28636905788281,53.73806143388757],"type":"Point"}
}