{
  "type": "Feature",
  "properties": {
    "iso:country":"GB",
    "wof:name":"TS3 0HE",
    "wof:placetype":"postalcode"
},
  "geometry": {"coordinates":[-1.19274018403102,54.55267037155909],"type":"Point"}
}