{
  "type": "Feature",
  "properties": {
    "iso:country":"GB",
    "wof:name":"NR8 6RW",
    "wof:placetype":"postalcode"
},
  "geometry": {"coordinates":[1.21754483541292,52.67658500318704],"type":"Point"}
}