{
  "type": "Feature",
  "properties": {
    "iso:country": "GB",
    "wof:name": "NR8 6RW",
    "wof:placetype": "postalcode"
  },
  "geometry": {"coordinates":[1.217545,52.676585],"type":"Point"}
}
