{
  "type": "Feature",
  "properties": {
    "iso:country":"GB",
    "wof:name":"NG21 9QF",
    "wof:placetype":"postalcode"
},
  "geometry": {"coordinates":[-1.05827730847399,53.19543164245658],"type":"Point"}
}