{
  "type": "Feature",
  "properties": {
    "iso:country": "GB",
    "wof:name": "NG21 9QF",
    "wof:placetype": "postalcode"
  },
  "geometry": {"coordinates":[-1.058277,53.195432],"type":"Point"}
}
