{
  "type": "Feature",
  "properties": {
    "iso:country":"GB",
    "wof:name":"SR8 1LW",
    "wof:placetype":"postalcode"
},
  "geometry": {"coordinates":[-1.34041391269939,54.74961377986915],"type":"Point"}
}