{
  "type": "Feature",
  "properties": {
    "iso:country":"GB",
    "wof:name":"SA14 6SB",
    "wof:placetype":"postalcode"
},
  "geometry": {"coordinates":[-4.06177460949523,51.79462522769821],"type":"Point"}
}