{
  "type": "Feature",
  "properties": {
    "iso:country": "GB",
    "wof:name": "SA14 6SB",
    "wof:placetype": "postalcode"
  },
  "geometry": {"coordinates":[-4.061775,51.794625],"type":"Point"}
}
