{
  "type": "Feature",
  "properties": {
    "iso:country":"GB",
    "wof:name":"DD8 3TY",
    "wof:placetype":"postalcode"
},
  "geometry": {"coordinates":[-2.93745847830833,56.72099891691413],"type":"Point"}
}