{
  "type": "Feature",
  "properties": {
    "iso:country":"GB",
    "wof:name":"NP18 3RX",
    "wof:placetype":"postalcode"
},
  "geometry": {"coordinates":[-2.98174394785283,51.61129023953831],"type":"Point"}
}