{
  "type": "Feature",
  "properties": {
    "iso:country": "GB",
    "wof:name": "NP18 3RX",
    "wof:placetype": "postalcode"
  },
  "geometry": {"coordinates":[-2.981744,51.61129],"type":"Point"}
}
