{
  "type": "Feature",
  "properties": {
    "iso:country": "GB",
    "wof:name": "RH1 2GH",
    "wof:placetype": "postalcode"
  },
  "geometry": {"coordinates":[-0.167778,51.249985],"type":"Point"}
}
