{
  "type": "Feature",
  "properties": {
    "iso:country":"GB",
    "wof:name":"KT9 1EG",
    "wof:placetype":"postalcode"
},
  "geometry": {"coordinates":[-0.30100981946046,51.37233499037939],"type":"Point"}
}