{
  "type": "Feature",
  "properties": {
    "iso:country": "GB",
    "wof:name": "NE12 9ET",
    "wof:placetype": "postalcode"
  },
  "geometry": {"coordinates":[-1.539958,55.023281],"type":"Point"}
}
