{
  "type": "Feature",
  "properties": {
    "date:inception_lower":"2013-11-01",
    "date:inception_upper":"2013-11-30",
    "iso:country":"GB",
    "wof:name":"NE12 9ET",
    "wof:placetype":"postalcode"
},
  "geometry": {"coordinates":[-1.539958,55.023281],"type":"Point"}
}