{
  "type": "Feature",
  "properties": {
    "iso:country":"GB",
    "wof:name":"NE12 9ET",
    "wof:placetype":"postalcode"
},
  "geometry": {"coordinates":[-1.53995812549185,55.02328119790735],"type":"Point"}
}