{
  "type": "Feature",
  "properties": {
    "iso:country":"GB",
    "wof:name":"IP25 6UP",
    "wof:placetype":"postalcode"
},
  "geometry": {"coordinates":[0.85406318244552,52.57105605111881],"type":"Point"}
}