{
  "type": "Feature",
  "properties": {
    "date:inception_lower": "1980-01-01",
    "date:inception_upper": "1980-01-01",
    "iso:country": "GB",
    "wof:name": "MK40 1SU",
    "wof:placetype": "postalcode"
  },
  "geometry": {"coordinates":[-0.467646,52.136761],"type":"Point"}
}
