{
  "type": "Feature",
  "properties": {
    "iso:country":"GB",
    "wof:name":"MK40 1SU",
    "wof:placetype":"postalcode"
},
  "geometry": {"coordinates":[-0.46764554499953,52.13676129958263],"type":"Point"}
}