{
  "type": "Feature",
  "properties": {
    "iso:country":"GB",
    "wof:name":"AB39 2NH",
    "wof:placetype":"postalcode"
},
  "geometry": {"coordinates":[-2.23522769277834,56.96374038045106],"type":"Point"}
}