{
  "type": "Feature",
  "properties": {
    "iso:country": "GB",
    "wof:name": "CT14 9JU",
    "wof:placetype": "postalcode"
  },
  "geometry": {"coordinates":[1.38131,51.208745],"type":"Point"}
}
