{
  "type": "Feature",
  "properties": {
    "iso:country":"GB",
    "wof:name":"LE15 6NR",
    "wof:placetype":"postalcode"
},
  "geometry": {"coordinates":[-0.73486633892709,52.67221160604996],"type":"Point"}
}