{
  "type": "Feature",
  "properties": {
    "iso:country":"GB",
    "wof:name":"DG5 4QB",
    "wof:placetype":"postalcode"
},
  "geometry": {"coordinates":[-3.76074132956434,54.87116334827081],"type":"Point"}
}