{
  "type": "Feature",
  "properties": {
    "iso:country": "GB",
    "wof:name": "GL50 2BA",
    "wof:placetype": "postalcode"
  },
  "geometry": {"coordinates":[-2.079842,51.889795],"type":"Point"}
}
