{
  "type": "Feature",
  "properties": {
    "iso:country": "GB",
    "wof:name": "TA13 5HA",
    "wof:placetype": "postalcode"
  },
  "geometry": {"coordinates":[-2.836155,50.964742],"type":"Point"}
}
