{
  "type": "Feature",
  "properties": {
    "iso:country":"GB",
    "wof:name":"NP13 3NE",
    "wof:placetype":"postalcode"
},
  "geometry": {"coordinates":[-3.15142918263978,51.76889033114871],"type":"Point"}
}