{
  "type": "Feature",
  "properties": {
    "date:inception_lower": "1999-06-01",
    "date:inception_upper": "1999-06-01",
    "iso:country": "GB",
    "wof:name": "NP13 3NE",
    "wof:placetype": "postalcode"
  },
  "geometry": {"coordinates":[-3.151429,51.76889],"type":"Point"}
}
