{
  "type": "Feature",
  "properties": {
    "iso:country": "GB",
    "wof:name": "BN16 2SG",
    "wof:placetype": "postalcode"
  },
  "geometry": {"coordinates":[-0.511721,50.804153],"type":"Point"}
}
