{
  "type": "Feature",
  "properties": {
    "iso:country":"GB",
    "wof:name":"BN16 2SG",
    "wof:placetype":"postalcode"
},
  "geometry": {"coordinates":[-0.51172132004937,50.8041532248951],"type":"Point"}
}