{
  "type": "Feature",
  "properties": {
    "date:inception_lower":"1980-01-01",
    "date:inception_upper":"1980-01-31",
    "iso:country":"GB",
    "wof:name":"SO22 4JP",
    "wof:placetype":"postalcode"
},
  "geometry": {"coordinates":[-1.349881,51.046078],"type":"Point"}
}