{
  "type": "Feature",
  "properties": {
    "iso:country": "GB",
    "wof:name": "SO22 4JP",
    "wof:placetype": "postalcode"
  },
  "geometry": {"coordinates":[-1.349881,51.046078],"type":"Point"}
}
