{
  "type": "Feature",
  "properties": {
    "iso:country":"GB",
    "wof:name":"SO22 4JP",
    "wof:placetype":"postalcode"
},
  "geometry": {"coordinates":[-1.34988054302064,51.04607791280559],"type":"Point"}
}