{
  "type": "Feature",
  "properties": {
    "iso:country":"GB",
    "wof:name":"HU17 9DH",
    "wof:placetype":"postalcode"
},
  "geometry": {"coordinates":[-0.42410338496318,53.84554965998561],"type":"Point"}
}