{
  "type": "Feature",
  "properties": {
    "iso:country": "GB",
    "wof:name": "HP18 0HQ",
    "wof:placetype": "postalcode"
  },
  "geometry": {"coordinates":[-0.982541,51.811228],"type":"Point"}
}
