{
  "type": "Feature",
  "properties": {
    "iso:country":"GB",
    "wof:name":"BN43 6AW",
    "wof:placetype":"postalcode"
},
  "geometry": {"coordinates":[-0.25973554021621,50.84088458604252],"type":"Point"}
}