{
  "type": "Feature",
  "properties": {
    "iso:country": "GB",
    "wof:name": "BN43 6AW",
    "wof:placetype": "postalcode"
  },
  "geometry": {"coordinates":[-0.259736,50.840885],"type":"Point"}
}
