{
  "type": "Feature",
  "properties": {
    "date:inception_lower": "1996-06-01",
    "date:inception_upper": "1996-06-01",
    "iso:country": "GB",
    "wof:name": "DL7 0HU",
    "wof:placetype": "postalcode"
  },
  "geometry": {"coordinates":[-1.562555,54.430866],"type":"Point"}
}
