{
  "type": "Feature",
  "properties": {
    "iso:country":"GB",
    "wof:name":"DL7 0HU",
    "wof:placetype":"postalcode"
},
  "geometry": {"coordinates":[-1.56255471761376,54.43086578069228],"type":"Point"}
}