{
  "type": "Feature",
  "properties": {
    "iso:country": "GB",
    "wof:name": "BS39 5DB",
    "wof:placetype": "postalcode"
  },
  "geometry": {"coordinates":[-2.542728,51.320877],"type":"Point"}
}
