{
  "type": "Feature",
  "properties": {
    "iso:country": "GB",
    "wof:name": "HP10 9PL",
    "wof:placetype": "postalcode"
  },
  "geometry": {"coordinates":[-0.70326,51.597322],"type":"Point"}
}
