{
  "type": "Feature",
  "properties": {
    "iso:country":"GB",
    "wof:name":"HP10 9PL",
    "wof:placetype":"postalcode"
},
  "geometry": {"coordinates":[-0.70326002143385,51.59732236045232],"type":"Point"}
}