{
  "type": "Feature",
  "properties": {
    "iso:country":"GB",
    "wof:name":"BS8 4AY",
    "wof:placetype":"postalcode"
},
  "geometry": {"coordinates":[-2.62354632568297,51.45514734821641],"type":"Point"}
}