{
  "type": "Feature",
  "properties": {
    "iso:country": "GB",
    "wof:name": "BS8 4AY",
    "wof:placetype": "postalcode"
  },
  "geometry": {"coordinates":[-2.623546,51.455147],"type":"Point"}
}
