{
  "type": "Feature",
  "properties": {
    "date:inception_lower": "2003-02-01",
    "date:inception_upper": "2003-02-01",
    "iso:country": "GB",
    "wof:name": "LN6 0FY",
    "wof:placetype": "postalcode"
  },
  "geometry": {"coordinates":[-0.604888,53.212318],"type":"Point"}
}
