{
  "type": "Feature",
  "properties": {
    "iso:country": "GB",
    "wof:name": "NR20 5DQ",
    "wof:placetype": "postalcode"
  },
  "geometry": {"coordinates":[1.041514,52.828962],"type":"Point"}
}
