{
  "type": "Feature",
  "properties": {
    "iso:country":"GB",
    "wof:name":"NR20 5DQ",
    "wof:placetype":"postalcode"
},
  "geometry": {"coordinates":[1.04148092672123,52.82894609099321],"type":"Point"}
}