{
  "type": "Feature",
  "properties": {
    "iso:country":"GB",
    "wof:name":"PL2 2BB",
    "wof:placetype":"postalcode"
},
  "geometry": {"coordinates":[-4.18072855586783,50.39057653066069],"type":"Point"}
}