{
  "type": "Feature",
  "properties": {
    "iso:country":"GB",
    "wof:name":"EC2M 3XD",
    "wof:placetype":"postalcode"
},
  "geometry": {"coordinates":[-0.08247788569518,51.51593824722362],"type":"Point"}
}