{
  "type": "Feature",
  "properties": {
    "iso:country":"GB",
    "wof:name":"SK12 2AR",
    "wof:placetype":"postalcode"
},
  "geometry": {"coordinates":[-2.02193820049011,53.35025869198144],"type":"Point"}
}