{
  "type": "Feature",
  "properties": {
    "iso:country":"GB",
    "wof:name":"WV8 1SP",
    "wof:placetype":"postalcode"
},
  "geometry": {"coordinates":[-2.18976431069953,52.63013802051186],"type":"Point"}
}