{
  "type": "Feature",
  "properties": {
    "date:inception_lower":"1995-12-01",
    "date:inception_upper":"1995-12-31",
    "iso:country":"GB",
    "wof:name":"HU17 8XL",
    "wof:placetype":"postalcode"
},
  "geometry": {"coordinates":[-0.436571,53.828751],"type":"Point"}
}