{
  "type": "Feature",
  "properties": {
    "iso:country": "GB",
    "wof:name": "LE16 7UJ",
    "wof:placetype": "postalcode"
  },
  "geometry": {"coordinates":[-0.872311,52.525332],"type":"Point"}
}
