{
  "type": "Feature",
  "properties": {
    "date:inception_lower": "1980-01-01",
    "date:inception_upper": "1980-01-01",
    "iso:country": "GB",
    "wof:name": "LE16 7UJ",
    "wof:placetype": "postalcode"
  },
  "geometry": {"coordinates":[-0.872311,52.525332],"type":"Point"}
}
