{
  "type": "Feature",
  "properties": {
    "iso:country":"GB",
    "wof:name":"LE16 7UJ",
    "wof:placetype":"postalcode"
},
  "geometry": {"coordinates":[-0.87231114809918,52.52533190342813],"type":"Point"}
}