{
  "type": "Feature",
  "properties": {
    "iso:country":"GB",
    "wof:name":"SM5 4PR",
    "wof:placetype":"postalcode"
},
  "geometry": {"coordinates":[-0.1578762771786,51.35023506936859],"type":"Point"}
}