{
  "type": "Feature",
  "properties": {
    "date:inception_lower": "1980-01-01",
    "date:inception_upper": "1980-01-01",
    "iso:country": "GB",
    "wof:name": "SM5 4PR",
    "wof:placetype": "postalcode"
  },
  "geometry": {"coordinates":[-0.157876,51.350235],"type":"Point"}
}
