{
  "type": "Feature",
  "properties": {
    "iso:country":"GB",
    "wof:name":"SL3 9NB",
    "wof:placetype":"postalcode"
},
  "geometry": {"coordinates":[-0.56993981874618,51.48325667941513],"type":"Point"}
}