{
  "type": "Feature",
  "properties": {
    "iso:country":"GB",
    "wof:name":"BB5 3BN",
    "wof:placetype":"postalcode"
},
  "geometry": {"coordinates":[-2.39318224943874,53.74067053790053],"type":"Point"}
}