{
  "type": "Feature",
  "properties": {
    "iso:country":"GB",
    "wof:name":"BA2 5HP",
    "wof:placetype":"postalcode"
},
  "geometry": {"coordinates":[-2.34884927810037,51.35963583295166],"type":"Point"}
}