{
  "type": "Feature",
  "properties": {
    "iso:country":"GB",
    "wof:name":"DE11 0UF",
    "wof:placetype":"postalcode"
},
  "geometry": {"coordinates":[-1.58660083182114,52.78014721518745],"type":"Point"}
}