{
  "type": "Feature",
  "properties": {
    "iso:country":"GB",
    "wof:name":"HP5 1QX",
    "wof:placetype":"postalcode"
},
  "geometry": {"coordinates":[-0.59685757875884,51.69456864715393],"type":"Point"}
}