{
  "type": "Feature",
  "properties": {
    "iso:country":"GB",
    "wof:name":"LE12 5NN",
    "wof:placetype":"postalcode"
},
  "geometry": {"coordinates":[-1.24277035260399,52.81430274086272],"type":"Point"}
}