{
  "type": "Feature",
  "properties": {
    "iso:country": "GB",
    "wof:name": "LE12 5NN",
    "wof:placetype": "postalcode"
  },
  "geometry": {"coordinates":[-1.24277,52.814303],"type":"Point"}
}
