{
  "type": "Feature",
  "properties": {
    "iso:country": "GB",
    "wof:name": "SO51 0NP",
    "wof:placetype": "postalcode"
  },
  "geometry": {"coordinates":[-1.507236,51.034222],"type":"Point"}
}
