{
  "type": "Feature",
  "properties": {
    "iso:country":"GB",
    "wof:name":"OX4 7YD",
    "wof:placetype":"postalcode"
},
  "geometry": {"coordinates":[-1.19140149598566,51.71701384064963],"type":"Point"}
}