{
  "type": "Feature",
  "properties": {
    "date:inception_lower": "1980-01-01",
    "date:inception_upper": "1980-01-01",
    "iso:country": "GB",
    "wof:name": "SE16 4HL",
    "wof:placetype": "postalcode"
  },
  "geometry": {"coordinates":[-0.054951,51.499991],"type":"Point"}
}
