{
  "type": "Feature",
  "properties": {
    "iso:country":"GB",
    "wof:name":"DL8 4RB",
    "wof:placetype":"postalcode"
},
  "geometry": {"coordinates":[-1.81262527962996,54.28636078462608],"type":"Point"}
}