{
  "type": "Feature",
  "properties": {
    "date:inception_lower": "1983-07-01",
    "date:inception_upper": "1983-07-01",
    "iso:country": "GB",
    "wof:name": "DL8 4RB",
    "wof:placetype": "postalcode"
  },
  "geometry": {"coordinates":[-1.812625,54.286361],"type":"Point"}
}
