{
  "type": "Feature",
  "properties": {
    "iso:country": "GB",
    "wof:name": "B23 7AZ",
    "wof:placetype": "postalcode"
  },
  "geometry": {"coordinates":[-1.861304,52.51612],"type":"Point"}
}
