{
  "type": "Feature",
  "properties": {
    "date:inception_lower":"2010-11-01",
    "date:inception_upper":"2010-11-30",
    "iso:country":"GB",
    "wof:name":"B23 7AZ",
    "wof:placetype":"postalcode"
},
  "geometry": {"coordinates":[-1.861304,52.51612],"type":"Point"}
}