{
  "type": "Feature",
  "properties": {
    "iso:country":"GB",
    "wof:name":"SW19 3EG",
    "wof:placetype":"postalcode"
},
  "geometry": {"coordinates":[-0.19361304463946,51.40845238687564],"type":"Point"}
}