{
  "type": "Feature",
  "properties": {
    "iso:country":"GB",
    "wof:name":"NE8 1HH",
    "wof:placetype":"postalcode"
},
  "geometry": {"coordinates":[-1.6035445890164,54.95940594451393],"type":"Point"}
}