{
  "type": "Feature",
  "properties": {
    "iso:country": "GB",
    "wof:name": "CR3 0HG",
    "wof:placetype": "postalcode"
  },
  "geometry": {"coordinates":[-0.071103,51.300061],"type":"Point"}
}
