{
  "type": "Feature",
  "properties": {
    "iso:country": "GB",
    "wof:name": "G69 9NQ",
    "wof:placetype": "postalcode"
  },
  "geometry": {"coordinates":[-4.109785,55.905499],"type":"Point"}
}
