{
  "type": "Feature",
  "properties": {
    "iso:country":"GB",
    "wof:name":"G69 9NQ",
    "wof:placetype":"postalcode"
},
  "geometry": {"coordinates":[-4.10978513648893,55.90549935960394],"type":"Point"}
}