{
  "type": "Feature",
  "properties": {
    "date:inception_lower": "2007-04-01",
    "date:inception_upper": "2007-04-01",
    "iso:country": "GB",
    "wof:name": "G69 9NQ",
    "wof:placetype": "postalcode"
  },
  "geometry": {"coordinates":[-4.109785,55.905499],"type":"Point"}
}
