{
  "type": "Feature",
  "properties": {
    "date:inception_lower":"1980-01-01",
    "date:inception_upper":"1980-01-31",
    "iso:country":"GB",
    "wof:name":"OX15 5NS",
    "wof:placetype":"postalcode"
},
  "geometry": {"coordinates":[-1.489706,51.995763],"type":"Point"}
}