{
  "type": "Feature",
  "properties": {
    "iso:country": "GB",
    "wof:name": "OX15 5NS",
    "wof:placetype": "postalcode"
  },
  "geometry": {"coordinates":[-1.489706,51.995763],"type":"Point"}
}
