{
  "type": "Feature",
  "properties": {
    "iso:country":"GB",
    "wof:name":"L37 6DL",
    "wof:placetype":"postalcode"
},
  "geometry": {"coordinates":[-3.05277988710679,53.54744323694909],"type":"Point"}
}