{
  "type": "Feature",
  "properties": {
    "date:inception_lower":"1980-01-01",
    "date:inception_upper":"1980-01-31",
    "iso:country":"GB",
    "wof:name":"LS12 2QT",
    "wof:placetype":"postalcode"
},
  "geometry": {"coordinates":[-1.604233,53.802933],"type":"Point"}
}