{
  "type": "Feature",
  "properties": {
    "iso:country":"GB",
    "wof:name":"LS12 2QT",
    "wof:placetype":"postalcode"
},
  "geometry": {"coordinates":[-1.60423292233066,53.80293303208821],"type":"Point"}
}