{
  "type": "Feature",
  "properties": {
    "date:inception_lower": "1980-01-01",
    "date:inception_upper": "1980-01-01",
    "iso:country": "GB",
    "wof:name": "WA1 4RT",
    "wof:placetype": "postalcode"
  },
  "geometry": {"coordinates":[-2.525813,53.40243],"type":"Point"}
}
