{
  "type": "Feature",
  "properties": {
    "iso:country":"GB",
    "wof:name":"WA1 4RT",
    "wof:placetype":"postalcode"
},
  "geometry": {"coordinates":[-2.52593204193589,53.4023408811547],"type":"Point"}
}