{
  "type": "Feature",
  "properties": {
    "iso:country":"GB",
    "wof:name":"S42 6RT",
    "wof:placetype":"postalcode"
},
  "geometry": {"coordinates":[-1.44620851781814,53.20515535637247],"type":"Point"}
}