{
  "type": "Feature",
  "properties": {
    "date:inception_lower": "1980-01-01",
    "date:inception_upper": "1980-01-01",
    "iso:country": "GB",
    "wof:name": "S42 6RT",
    "wof:placetype": "postalcode"
  },
  "geometry": {"coordinates":[-1.446222,53.205148],"type":"Point"}
}
