{
  "type": "Feature",
  "properties": {
    "iso:country":"GB",
    "wof:name":"SL5 7NW",
    "wof:placetype":"postalcode"
},
  "geometry": {"coordinates":[-0.6822796841705,51.42256336779903],"type":"Point"}
}