{
  "type": "Feature",
  "properties": {
    "iso:country": "GB",
    "wof:name": "SL5 7NW",
    "wof:placetype": "postalcode"
  },
  "geometry": {"coordinates":[-0.68228,51.422563],"type":"Point"}
}
