{
  "type": "Feature",
  "properties": {
    "iso:country":"GB",
    "wof:name":"N14 4HE",
    "wof:placetype":"postalcode"
},
  "geometry": {"coordinates":[-0.13863399167941,51.6451376634802],"type":"Point"}
}