{
  "type": "Feature",
  "properties": {
    "iso:country": "GB",
    "wof:name": "CB1 0WW",
    "wof:placetype": "postalcode"
  },
  "geometry": {"coordinates":[0.137179,52.192254],"type":"Point"}
}
