{
  "type": "Feature",
  "properties": {
    "iso:country":"GB",
    "wof:name":"RH13 6DW",
    "wof:placetype":"postalcode"
},
  "geometry": {"coordinates":[-0.29852854623744,51.05914435227426],"type":"Point"}
}