{
  "type": "Feature",
  "properties": {
    "iso:country": "GB",
    "wof:name": "RH13 6DW",
    "wof:placetype": "postalcode"
  },
  "geometry": {"coordinates":[-0.298529,51.059144],"type":"Point"}
}
