{
  "type": "Feature",
  "properties": {
    "iso:country":"GB",
    "wof:name":"SM4 6NY",
    "wof:placetype":"postalcode"
},
  "geometry": {"coordinates":[-0.19907983688014,51.38458922235962],"type":"Point"}
}