{
  "type": "Feature",
  "properties": {
    "iso:country":"GB",
    "wof:name":"CH62 5DB",
    "wof:placetype":"postalcode"
},
  "geometry": {"coordinates":[-3.00084367969704,53.35717230826354],"type":"Point"}
}