{
  "type": "Feature",
  "properties": {
    "iso:country": "GB",
    "wof:name": "CH62 5DB",
    "wof:placetype": "postalcode"
  },
  "geometry": {"coordinates":[-3.000844,53.357172],"type":"Point"}
}
