{
  "type": "Feature",
  "properties": {
    "iso:country":"GB",
    "wof:name":"DN34 4QW",
    "wof:placetype":"postalcode"
},
  "geometry": {"coordinates":[-0.10625902906538,53.56292447269425],"type":"Point"}
}