{
  "type": "Feature",
  "properties": {
    "iso:country":"GB",
    "wof:name":"S62 7LN",
    "wof:placetype":"postalcode"
},
  "geometry": {"coordinates":[-1.35792903563799,53.47366679243868],"type":"Point"}
}