{
  "type": "Feature",
  "properties": {
    "date:inception_lower": "1980-01-01",
    "date:inception_upper": "1980-01-01",
    "iso:country": "GB",
    "wof:name": "S62 7LN",
    "wof:placetype": "postalcode"
  },
  "geometry": {"coordinates":[-1.357929,53.473667],"type":"Point"}
}
