{
  "type": "Feature",
  "properties": {
    "iso:country": "GB",
    "wof:name": "NR34 8JG",
    "wof:placetype": "postalcode"
  },
  "geometry": {"coordinates":[1.476982,52.427335],"type":"Point"}
}
