{
  "type": "Feature",
  "properties": {
    "iso:country": "GB",
    "wof:name": "CA7 2PL",
    "wof:placetype": "postalcode"
  },
  "geometry": {"coordinates":[-3.370872,54.765126],"type":"Point"}
}
