{
  "type": "Feature",
  "properties": {
    "date:inception_lower": "1998-06-01",
    "date:inception_upper": "1998-06-01",
    "iso:country": "GB",
    "wof:name": "YO8 5DB",
    "wof:placetype": "postalcode"
  },
  "geometry": {"coordinates":[-0.982397,53.81671],"type":"Point"}
}
