{
  "type": "Feature",
  "properties": {
    "iso:country": "GB",
    "wof:name": "YO8 5DB",
    "wof:placetype": "postalcode"
  },
  "geometry": {"coordinates":[-0.984588,53.819047],"type":"Point"}
}
