{
  "type": "Feature",
  "properties": {
    "iso:country": "GB",
    "wof:name": "HR2 7SW",
    "wof:placetype": "postalcode"
  },
  "geometry": {"coordinates":[-2.718982,52.036955],"type":"Point"}
}
