{
  "type": "Feature",
  "properties": {
    "iso:country": "GB",
    "wof:name": "IP17 2NL",
    "wof:placetype": "postalcode"
  },
  "geometry": {"coordinates":[1.492262,52.224252],"type":"Point"}
}
