{
  "type": "Feature",
  "properties": {
    "iso:country":"GB",
    "wof:name":"SR7 0EB",
    "wof:placetype":"postalcode"
},
  "geometry": {"coordinates":[-1.3560582113085,54.84361725949255],"type":"Point"}
}