{
  "type": "Feature",
  "properties": {
    "date:inception_lower": "1996-12-01",
    "date:inception_upper": "1996-12-01",
    "iso:country": "GB",
    "wof:name": "ME6 5UA",
    "wof:placetype": "postalcode"
  },
  "geometry": {"coordinates":[0.447739,51.325905],"type":"Point"}
}
