{
  "type": "Feature",
  "properties": {
    "iso:country": "GB",
    "wof:name": "ME6 5UA",
    "wof:placetype": "postalcode"
  },
  "geometry": {"coordinates":[0.446634,51.325109],"type":"Point"}
}
