{
  "type": "Feature",
  "properties": {
    "iso:country":"GB",
    "wof:name":"M20 3LH",
    "wof:placetype":"postalcode"
},
  "geometry": {"coordinates":[-2.2295661205865,53.43221317145604],"type":"Point"}
}