{
  "type": "Feature",
  "properties": {
    "iso:country": "GB",
    "wof:name": "CF64 9FU",
    "wof:placetype": "postalcode"
  },
  "geometry": {"coordinates":[-3.17329,51.439487],"type":"Point"}
}
