{
  "type": "Feature",
  "properties": {
    "iso:country":"GB",
    "wof:name":"DH3 4AW",
    "wof:placetype":"postalcode"
},
  "geometry": {"coordinates":[-1.57721323872925,54.87022649950868],"type":"Point"}
}