{
  "type": "Feature",
  "properties": {
    "iso:country": "GB",
    "wof:name": "EH10 5FA",
    "wof:placetype": "postalcode"
  },
  "geometry": {"coordinates":[-3.228091,55.923116],"type":"Point"}
}
