{
  "type": "Feature",
  "properties": {
    "iso:country": "GB",
    "wof:name": "SG17 5BN",
    "wof:placetype": "postalcode"
  },
  "geometry": {"coordinates":[-0.352314,52.030914],"type":"Point"}
}
