{
  "type": "Feature",
  "properties": {
    "iso:country":"GB",
    "wof:name":"W1H 4AW",
    "wof:placetype":"postalcode"
},
  "geometry": {"coordinates":[-0.16523243452205,51.51927627550103],"type":"Point"}
}