{
  "type": "Feature",
  "properties": {
    "iso:country":"GB",
    "wof:name":"BL8 4AQ",
    "wof:placetype":"postalcode"
},
  "geometry": {"coordinates":[-2.3462394136279,53.61662570243305],"type":"Point"}
}