{
  "type": "Feature",
  "properties": {
    "date:inception_lower": "1980-01-01",
    "date:inception_upper": "1980-01-01",
    "iso:country": "GB",
    "wof:name": "BL8 4AQ",
    "wof:placetype": "postalcode"
  },
  "geometry": {"coordinates":[-2.346239,53.616626],"type":"Point"}
}
