{
  "type": "Feature",
  "properties": {
    "iso:country":"GB",
    "wof:name":"BD5 8AU",
    "wof:placetype":"postalcode"
},
  "geometry": {"coordinates":[-1.75323162445504,53.77675431583374],"type":"Point"}
}