{
  "type": "Feature",
  "properties": {
    "iso:country":"GB",
    "wof:name":"PE4 7ZP",
    "wof:placetype":"postalcode"
},
  "geometry": {"coordinates":[-0.25936372275441,52.61909740307013],"type":"Point"}
}