{
  "type": "Feature",
  "properties": {
    "iso:country": "GB",
    "wof:name": "PE4 7ZP",
    "wof:placetype": "postalcode"
  },
  "geometry": {"coordinates":[-0.259364,52.619097],"type":"Point"}
}
