{
  "type": "Feature",
  "properties": {
    "iso:country":"GB",
    "wof:name":"TA11 6HJ",
    "wof:placetype":"postalcode"
},
  "geometry": {"coordinates":[-2.74193942835749,51.05480800252206],"type":"Point"}
}