{
  "type": "Feature",
  "properties": {
    "iso:country":"GB",
    "wof:name":"M11 1BQ",
    "wof:placetype":"postalcode"
},
  "geometry": {"coordinates":[-2.16709841953903,53.47679204979658],"type":"Point"}
}