{
  "type": "Feature",
  "properties": {
    "iso:country":"GB",
    "wof:name":"CR2 6BZ",
    "wof:placetype":"postalcode"
},
  "geometry": {"coordinates":[-0.10885138746457,51.35016423724353],"type":"Point"}
}