{
  "type": "Feature",
  "properties": {
    "iso:country":"GB",
    "wof:name":"NG8 6GY",
    "wof:placetype":"postalcode"
},
  "geometry": {"coordinates":[-1.21409328106648,52.97769926522188],"type":"Point"}
}