{
  "type": "Feature",
  "properties": {
    "date:inception_lower":"2008-08-01",
    "date:inception_upper":"2008-08-31",
    "iso:country":"GB",
    "wof:name":"S71 2QX",
    "wof:placetype":"postalcode"
},
  "geometry": {"coordinates":[-1.44499,53.56992],"type":"Point"}
}