{
  "type": "Feature",
  "properties": {
    "iso:country":"GB",
    "wof:name":"S71 2QX",
    "wof:placetype":"postalcode"
},
  "geometry": {"coordinates":[-1.44498999757376,53.56992000415032],"type":"Point"}
}