{
  "type": "Feature",
  "properties": {
    "iso:country": "GB",
    "wof:name": "TN9 1LX",
    "wof:placetype": "postalcode"
  },
  "geometry": {"coordinates":[0.273586,51.203194],"type":"Point"}
}
