{
  "type": "Feature",
  "properties": {
    "iso:country":"GB",
    "wof:name":"TN9 1LX",
    "wof:placetype":"postalcode"
},
  "geometry": {"coordinates":[0.27358555249321,51.20319417973125],"type":"Point"}
}