{
  "type": "Feature",
  "properties": {
    "date:inception_lower": "1980-01-01",
    "date:inception_upper": "1980-01-01",
    "iso:country": "GB",
    "wof:name": "TN9 1LX",
    "wof:placetype": "postalcode"
  },
  "geometry": {"coordinates":[0.273586,51.203194],"type":"Point"}
}
