{
  "type": "Feature",
  "properties": {
    "iso:country":"GB",
    "wof:name":"HR8 2QN",
    "wof:placetype":"postalcode"
},
  "geometry": {"coordinates":[-2.50923739621526,52.03528845031642],"type":"Point"}
}