{
  "type": "Feature",
  "properties": {
    "iso:country": "GB",
    "wof:name": "HR8 2QN",
    "wof:placetype": "postalcode"
  },
  "geometry": {"coordinates":[-2.509237,52.035288],"type":"Point"}
}
