{
  "type": "Feature",
  "properties": {
    "iso:country":"GB",
    "wof:name":"NN11 7JG",
    "wof:placetype":"postalcode"
},
  "geometry": {"coordinates":[-1.18297620386304,52.28608029076291],"type":"Point"}
}