{
  "type": "Feature",
  "properties": {
    "date:inception_lower": "1980-01-01",
    "date:inception_upper": "1980-01-01",
    "iso:country": "GB",
    "wof:name": "NN11 7JG",
    "wof:placetype": "postalcode"
  },
  "geometry": {"coordinates":[-1.183155,52.286691],"type":"Point"}
}
