{
  "type": "Feature",
  "properties": {
    "iso:country":"GB",
    "wof:name":"CB7 5AT",
    "wof:placetype":"postalcode"
},
  "geometry": {"coordinates":[0.35946590556846,52.31982500335355],"type":"Point"}
}