{
  "type": "Feature",
  "properties": {
    "date:inception_lower": "2018-07-01",
    "date:inception_upper": "2018-07-01",
    "iso:country": "GB",
    "wof:name": "PE7 8QW",
    "wof:placetype": "postalcode"
  },
  "geometry": {"coordinates":[-0.25408,52.536861],"type":"Point"}
}
