{
  "type": "Feature",
  "properties": {
    "date:inception_lower": "2018-07-01",
    "date:inception_upper": "2018-07-01",
    "iso:country": "GB",
    "wof:name": "PE7 8QW",
    "wof:placetype": "postalcode"
  },
  "geometry": {"coordinates":[-0.253992,52.536096],"type":"Point"}
}
