{
  "type": "Feature",
  "properties": {
    "iso:country":"GB",
    "wof:name":"NN14 4LE",
    "wof:placetype":"postalcode"
},
  "geometry": {"coordinates":[-0.53610407671186,52.39788487532672],"type":"Point"}
}