{
  "type": "Feature",
  "properties": {
    "date:inception_lower":"1984-10-01",
    "date:inception_upper":"1984-10-31",
    "iso:country":"GB",
    "wof:name":"NG19 0QQ",
    "wof:placetype":"postalcode"
},
  "geometry": {"coordinates":[-1.177457,53.15162],"type":"Point"}
}