{
  "type": "Feature",
  "properties": {
    "iso:country":"GB",
    "wof:name":"NG19 0QQ",
    "wof:placetype":"postalcode"
},
  "geometry": {"coordinates":[-1.17745688307609,53.1516196344627],"type":"Point"}
}