{
  "type": "Feature",
  "properties": {
    "date:inception_lower": "1980-01-01",
    "date:inception_upper": "1980-01-01",
    "iso:country": "GB",
    "wof:name": "PO9 4DW",
    "wof:placetype": "postalcode"
  },
  "geometry": {"coordinates":[-1.00036,50.871916],"type":"Point"}
}
