{
  "type": "Feature",
  "properties": {
    "date:inception_lower": "1980-01-01",
    "date:inception_upper": "1980-01-01",
    "iso:country": "GB",
    "wof:name": "CT14 9RP",
    "wof:placetype": "postalcode"
  },
  "geometry": {"coordinates":[1.386568,51.220665],"type":"Point"}
}
