{
  "type": "Feature",
  "properties": {
    "iso:country":"GB",
    "wof:name":"BS14 8DT",
    "wof:placetype":"postalcode"
},
  "geometry": {"coordinates":[-2.55436235580355,51.41232605398017],"type":"Point"}
}