{
  "type": "Feature",
  "properties": {
    "iso:country":"GB",
    "wof:name":"KY6 1AH",
    "wof:placetype":"postalcode"
},
  "geometry": {"coordinates":[-3.18307959195043,56.19540315006758],"type":"Point"}
}