{
  "type": "Feature",
  "properties": {
    "iso:country": "GB",
    "wof:name": "KY6 1AH",
    "wof:placetype": "postalcode"
  },
  "geometry": {"coordinates":[-3.18308,56.195403],"type":"Point"}
}
