{
  "type": "Feature",
  "properties": {
    "iso:country": "GB",
    "wof:name": "S61 2LJ",
    "wof:placetype": "postalcode"
  },
  "geometry": {"coordinates":[-1.3988,53.429098],"type":"Point"}
}
