{
  "type": "Feature",
  "properties": {
    "iso:country":"GB",
    "wof:name":"S61 2LJ",
    "wof:placetype":"postalcode"
},
  "geometry": {"coordinates":[-1.39879988509346,53.42909798813623],"type":"Point"}
}