{
  "type": "Feature",
  "properties": {
    "iso:country":"GB",
    "wof:name":"SW7 1RH",
    "wof:placetype":"postalcode"
},
  "geometry": {"coordinates":[-0.16387586123727,51.50139597450196],"type":"Point"}
}