{
  "type": "Feature",
  "properties": {
    "date:inception_lower": "2005-10-01",
    "date:inception_upper": "2005-10-01",
    "iso:country": "GB",
    "wof:name": "SW7 1RH",
    "wof:placetype": "postalcode"
  },
  "geometry": {"coordinates":[-0.163876,51.501396],"type":"Point"}
}
