{
  "type": "Feature",
  "properties": {
    "date:inception_lower": "1980-01-01",
    "date:inception_upper": "1980-01-01",
    "iso:country": "GB",
    "wof:name": "DD4 0PP",
    "wof:placetype": "postalcode"
  },
  "geometry": {"coordinates":[-2.905866,56.519339],"type":"Point"}
}
