{
  "type": "Feature",
  "properties": {
    "date:inception_lower":"2009-10-01",
    "date:inception_upper":"2009-10-31",
    "iso:country":"GB",
    "wof:name":"PO17 5DZ",
    "wof:placetype":"postalcode"
},
  "geometry": {"coordinates":[-1.204097,50.879841],"type":"Point"}
}