{
  "type": "Feature",
  "properties": {
    "iso:country":"GB",
    "wof:name":"DN16 1HP",
    "wof:placetype":"postalcode"
},
  "geometry": {"coordinates":[-0.63773333306772,53.57625258788486],"type":"Point"}
}