{
  "type": "Feature",
  "properties": {
    "iso:country":"GB",
    "wof:name":"M13 9DF",
    "wof:placetype":"postalcode"
},
  "geometry": {"coordinates":[-2.21988489795862,53.46651354956659],"type":"Point"}
}