{
  "type": "Feature",
  "properties": {
    "iso:country":"GB",
    "wof:name":"TW20 9RQ",
    "wof:placetype":"postalcode"
},
  "geometry": {"coordinates":[-0.55604549053894,51.42429562828904],"type":"Point"}
}