{
  "type": "Feature",
  "properties": {
    "iso:country":"GB",
    "wof:name":"WN7 4TP",
    "wof:placetype":"postalcode"
},
  "geometry": {"coordinates":[-2.54111796739776,53.49902625177531],"type":"Point"}
}