{
  "type": "Feature",
  "properties": {
    "date:inception_lower":"1980-01-01",
    "date:inception_upper":"1980-01-31",
    "iso:country":"GB",
    "wof:name":"WN7 4TP",
    "wof:placetype":"postalcode"
},
  "geometry": {"coordinates":[-2.541118,53.499026],"type":"Point"}
}