{
  "type": "Feature",
  "properties": {
    "iso:country":"GB",
    "wof:name":"SP8 4NY",
    "wof:placetype":"postalcode"
},
  "geometry": {"coordinates":[-2.27734664857037,51.04399392191105],"type":"Point"}
}