{
  "type": "Feature",
  "properties": {
    "iso:country":"GB",
    "wof:name":"HA7 1QH",
    "wof:placetype":"postalcode"
},
  "geometry": {"coordinates":[-0.2872939476419,51.59286245732358],"type":"Point"}
}