{
  "type": "Feature",
  "properties": {
    "date:inception_lower": "1980-01-01",
    "date:inception_upper": "1980-01-01",
    "iso:country": "GB",
    "wof:name": "BD13 2JR",
    "wof:placetype": "postalcode"
  },
  "geometry": {"coordinates":[-1.856996,53.771233],"type":"Point"}
}
