{
  "type": "Feature",
  "properties": {
    "iso:country":"GB",
    "wof:name":"BD13 2JR",
    "wof:placetype":"postalcode"
},
  "geometry": {"coordinates":[-1.85699594953409,53.77123333570844],"type":"Point"}
}