{
  "type": "Feature",
  "properties": {
    "date:inception_lower": "1980-01-01",
    "date:inception_upper": "1980-01-01",
    "iso:country": "GB",
    "wof:name": "CA10 3RU",
    "wof:placetype": "postalcode"
  },
  "geometry": {"coordinates":[-2.584441,54.467934],"type":"Point"}
}
