{
  "type": "Feature",
  "properties": {
    "iso:country":"GB",
    "wof:name":"CA10 3RU",
    "wof:placetype":"postalcode"
},
  "geometry": {"coordinates":[-2.58444119971342,54.46793391254989],"type":"Point"}
}