{
  "type": "Feature",
  "properties": {
    "iso:country":"GB",
    "wof:name":"M33 2PL",
    "wof:placetype":"postalcode"
},
  "geometry": {"coordinates":[-2.2951832760857,53.41833439399793],"type":"Point"}
}