{
  "type": "Feature",
  "properties": {
    "iso:country":"GB",
    "wof:name":"GU6 8QU",
    "wof:placetype":"postalcode"
},
  "geometry": {"coordinates":[-0.4842631700019,51.16977505906602],"type":"Point"}
}