{
  "type": "Feature",
  "properties": {
    "iso:country": "GB",
    "wof:name": "SE9 6TT",
    "wof:placetype": "postalcode"
  },
  "geometry": {"coordinates":[0.049992,51.463248],"type":"Point"}
}
