{
  "type": "Feature",
  "properties": {
    "iso:country":"GB",
    "wof:name":"SE9 6TT",
    "wof:placetype":"postalcode"
},
  "geometry": {"coordinates":[0.04999188084409,51.46324818397215],"type":"Point"}
}