{
  "type": "Feature",
  "properties": {
    "date:inception_lower":"2000-10-01",
    "date:inception_upper":"2000-10-31",
    "iso:country":"GB",
    "wof:name":"OX26 3ZQ",
    "wof:placetype":"postalcode"
},
  "geometry": {"coordinates":[-1.157021,51.910758],"type":"Point"}
}