{
  "type": "Feature",
  "properties": {
    "iso:country":"GB",
    "wof:name":"EX20 2HL",
    "wof:placetype":"postalcode"
},
  "geometry": {"coordinates":[-3.89786121678943,50.79808306254751],"type":"Point"}
}