{
  "type": "Feature",
  "properties": {
    "date:inception_lower": "2021-10-01",
    "date:inception_upper": "2021-10-01",
    "iso:country": "GB",
    "wof:name": "TS14 7FA",
    "wof:placetype": "postalcode"
  },
  "geometry": {"coordinates":[-1.044609,54.526719],"type":"Point"}
}
