{
  "type": "Feature",
  "properties": {
    "iso:country": "GB",
    "wof:name": "EH10 5HQ",
    "wof:placetype": "postalcode"
  },
  "geometry": {"coordinates":[-3.21181,55.92702],"type":"Point"}
}
