{
  "type": "Feature",
  "properties": {
    "iso:country":"GB",
    "wof:name":"CR0 6AR",
    "wof:placetype":"postalcode"
},
  "geometry": {"coordinates":[-0.07371494987438,51.37710061350007],"type":"Point"}
}