{
  "type": "Feature",
  "properties": {
    "iso:country": "GB",
    "wof:name": "PH14 9QE",
    "wof:placetype": "postalcode"
  },
  "geometry": {"coordinates":[-3.161144,56.450917],"type":"Point"}
}
