{
  "type": "Feature",
  "properties": {
    "date:inception_lower":"2010-09-01",
    "date:inception_upper":"2010-09-30",
    "iso:country":"GB",
    "wof:name":"PH14 9QE",
    "wof:placetype":"postalcode"
},
  "geometry": {"coordinates":[-3.161144,56.450917],"type":"Point"}
}