{
  "type": "Feature",
  "properties": {
    "iso:country":"GB",
    "wof:name":"TS25 4EX",
    "wof:placetype":"postalcode"
},
  "geometry": {"coordinates":[-1.24473039630006,54.66256643043676],"type":"Point"}
}