{
  "type": "Feature",
  "properties": {
    "iso:country":"GB",
    "wof:name":"TN23 4NL",
    "wof:placetype":"postalcode"
},
  "geometry": {"coordinates":[0.86254850794665,51.13687964943917],"type":"Point"}
}