{
  "type": "Feature",
  "properties": {
    "iso:country": "GB",
    "wof:name": "WF6 2EB",
    "wof:placetype": "postalcode"
  },
  "geometry": {"coordinates":[-1.414703,53.70514],"type":"Point"}
}
