{
  "type": "Feature",
  "properties": {
    "date:inception_lower": "1983-07-01",
    "date:inception_upper": "1983-07-01",
    "iso:country": "GB",
    "wof:name": "WF6 2EB",
    "wof:placetype": "postalcode"
  },
  "geometry": {"coordinates":[-1.414703,53.70514],"type":"Point"}
}
