{
  "type": "Feature",
  "properties": {
    "iso:country":"GB",
    "wof:name":"WF6 2EB",
    "wof:placetype":"postalcode"
},
  "geometry": {"coordinates":[-1.41470349205671,53.70514006797482],"type":"Point"}
}