{
  "type": "Feature",
  "properties": {
    "iso:country":"GB",
    "wof:name":"PE33 9QE",
    "wof:placetype":"postalcode"
},
  "geometry": {"coordinates":[0.49086959557225,52.56958199618903],"type":"Point"}
}