{
  "type": "Feature",
  "properties": {
    "date:inception_lower":"1995-07-01",
    "date:inception_upper":"1995-07-31",
    "iso:country":"GB",
    "wof:name":"PE33 9QE",
    "wof:placetype":"postalcode"
},
  "geometry": {"coordinates":[0.49087,52.569582],"type":"Point"}
}