{
  "type": "Feature",
  "properties": {
    "iso:country": "GB",
    "wof:name": "TR14 8EL",
    "wof:placetype": "postalcode"
  },
  "geometry": {"coordinates":[-5.299098,50.213562],"type":"Point"}
}
