{
  "type": "Feature",
  "properties": {
    "date:inception_lower":"2008-10-01",
    "date:inception_upper":"2008-10-31",
    "iso:country":"GB",
    "wof:name":"TR14 8EL",
    "wof:placetype":"postalcode"
},
  "geometry": {"coordinates":[-5.299098,50.213562],"type":"Point"}
}