{
  "type": "Feature",
  "properties": {
    "iso:country": "GB",
    "wof:name": "EN8 9LX",
    "wof:placetype": "postalcode"
  },
  "geometry": {"coordinates":[-0.042152,51.702532],"type":"Point"}
}
