{
  "type": "Feature",
  "properties": {
    "iso:country":"GB",
    "wof:name":"EN8 9LX",
    "wof:placetype":"postalcode"
},
  "geometry": {"coordinates":[-0.04215193712882,51.70253167317956],"type":"Point"}
}