{
  "type": "Feature",
  "properties": {
    "date:inception_lower": "1980-01-01",
    "date:inception_upper": "1980-01-01",
    "iso:country": "GB",
    "wof:name": "EN8 9LX",
    "wof:placetype": "postalcode"
  },
  "geometry": {"coordinates":[-0.042152,51.702532],"type":"Point"}
}
