{
  "type": "Feature",
  "properties": {
    "iso:country":"GB",
    "wof:name":"HP3 9NG",
    "wof:placetype":"postalcode"
},
  "geometry": {"coordinates":[-0.46409922708176,51.74088872851129],"type":"Point"}
}