{
  "type": "Feature",
  "properties": {
    "iso:country":"GB",
    "wof:name":"HX2 8JG",
    "wof:placetype":"postalcode"
},
  "geometry": {"coordinates":[-1.89538720124536,53.75055551912281],"type":"Point"}
}