{
  "type": "Feature",
  "properties": {
    "iso:country": "GB",
    "wof:name": "PE28 4EW",
    "wof:placetype": "postalcode"
  },
  "geometry": {"coordinates":[-0.249669,52.379108],"type":"Point"}
}
