{
  "type": "Feature",
  "properties": {
    "date:inception_lower":"2015-11-01",
    "date:inception_upper":"2015-11-30",
    "iso:country":"GB",
    "wof:name":"TA6 7BQ",
    "wof:placetype":"postalcode"
},
  "geometry": {"coordinates":[-3.015649,51.121932],"type":"Point"}
}