{
  "type": "Feature",
  "properties": {
    "iso:country":"GB",
    "wof:name":"TA6 7BQ",
    "wof:placetype":"postalcode"
},
  "geometry": {"coordinates":[-3.01565561969567,51.12193685646542],"type":"Point"}
}