{
  "type": "Feature",
  "properties": {
    "iso:country": "GB",
    "wof:name": "TA6 7BQ",
    "wof:placetype": "postalcode"
  },
  "geometry": {"coordinates":[-3.015649,51.121932],"type":"Point"}
}
