{
  "type": "Feature",
  "properties": {
    "iso:country":"GB",
    "wof:name":"HU7 5XH",
    "wof:placetype":"postalcode"
},
  "geometry": {"coordinates":[-0.34608671817159,53.81677742526369],"type":"Point"}
}