{
  "type": "Feature",
  "properties": {
    "date:inception_lower": "1980-01-01",
    "date:inception_upper": "1980-01-01",
    "iso:country": "GB",
    "wof:name": "NG20 8XG",
    "wof:placetype": "postalcode"
  },
  "geometry": {"coordinates":[-1.17428,53.208859],"type":"Point"}
}
