{
  "type": "Feature",
  "properties": {
    "iso:country": "GB",
    "wof:name": "HP9 2RF",
    "wof:placetype": "postalcode"
  },
  "geometry": {"coordinates":[-0.593647,51.617452],"type":"Point"}
}
