{
  "type": "Feature",
  "properties": {
    "iso:country":"GB",
    "wof:name":"DD11 4QU",
    "wof:placetype":"postalcode"
},
  "geometry": {"coordinates":[-2.59969643222979,56.60034423892761],"type":"Point"}
}