{
  "type": "Feature",
  "properties": {
    "date:inception_lower":"1991-03-01",
    "date:inception_upper":"1991-03-31",
    "iso:country":"GB",
    "wof:name":"DD11 4QU",
    "wof:placetype":"postalcode"
},
  "geometry": {"coordinates":[-2.599696,56.600344],"type":"Point"}
}