{
  "type": "Feature",
  "properties": {
    "date:inception_lower": "1980-01-01",
    "date:inception_upper": "1980-01-01",
    "iso:country": "GB",
    "wof:name": "S8 0UQ",
    "wof:placetype": "postalcode"
  },
  "geometry": {"coordinates":[-1.484754,53.354093],"type":"Point"}
}
