{
  "type": "Feature",
  "properties": {
    "iso:country":"GB",
    "wof:name":"S8 0UQ",
    "wof:placetype":"postalcode"
},
  "geometry": {"coordinates":[-1.48483005592617,53.35408484679961],"type":"Point"}
}