{
  "type": "Feature",
  "properties": {
    "date:inception_lower": "2000-12-01",
    "date:inception_upper": "2000-12-01",
    "iso:country": "GB",
    "wof:name": "WC1X 0DG",
    "wof:placetype": "postalcode"
  },
  "geometry": {"coordinates":[-0.112088,51.524503],"type":"Point"}
}
