{
  "type": "Feature",
  "properties": {
    "iso:country":"GB",
    "wof:name":"WC1X 0DG",
    "wof:placetype":"postalcode"
},
  "geometry": {"coordinates":[-0.11208828375085,51.52450288507271],"type":"Point"}
}