{
  "type": "Feature",
  "properties": {
    "date:inception_lower": "1980-01-01",
    "date:inception_upper": "1980-01-01",
    "iso:country": "GB",
    "wof:name": "SE22 8LY",
    "wof:placetype": "postalcode"
  },
  "geometry": {"coordinates":[-0.076403,51.450741],"type":"Point"}
}
