{
  "type": "Feature",
  "properties": {
    "iso:country":"GB",
    "wof:name":"SE22 8LY",
    "wof:placetype":"postalcode"
},
  "geometry": {"coordinates":[-0.07640269614106,51.4507411742787],"type":"Point"}
}