{
  "type": "Feature",
  "properties": {
    "iso:country": "GB",
    "wof:name": "TS4 2JL",
    "wof:placetype": "postalcode"
  },
  "geometry": {"coordinates":[-1.221721,54.566143],"type":"Point"}
}
