{
  "type": "Feature",
  "properties": {
    "date:inception_lower": "1997-12-01",
    "date:inception_upper": "1997-12-01",
    "iso:country": "GB",
    "wof:name": "BB18 5EQ",
    "wof:placetype": "postalcode"
  },
  "geometry": {"coordinates":[-2.188261,53.9193],"type":"Point"}
}
