{
  "type": "Feature",
  "properties": {
    "iso:country": "GB",
    "wof:name": "BB18 5EQ",
    "wof:placetype": "postalcode"
  },
  "geometry": {"coordinates":[-2.188261,53.9193],"type":"Point"}
}
