{
  "type": "Feature",
  "properties": {
    "iso:country": "GB",
    "wof:name": "HP11 1NN",
    "wof:placetype": "postalcode"
  },
  "geometry": {"coordinates":[-0.719548,51.61829],"type":"Point"}
}
