{
  "type": "Feature",
  "properties": {
    "date:inception_lower": "1980-01-01",
    "date:inception_upper": "1980-01-01",
    "iso:country": "GB",
    "wof:name": "BS5 9SL",
    "wof:placetype": "postalcode"
  },
  "geometry": {"coordinates":[-2.561068,51.453818],"type":"Point"}
}
