{
  "type": "Feature",
  "properties": {
    "iso:country":"GB",
    "wof:name":"W1F 8QA",
    "wof:placetype":"postalcode"
},
  "geometry": {"coordinates":[-0.136827804551,51.51455707962381],"type":"Point"}
}