{
  "type": "Feature",
  "properties": {
    "iso:country": "GB",
    "wof:name": "BB2 5LY",
    "wof:placetype": "postalcode"
  },
  "geometry": {"coordinates":[-2.522882,53.731708],"type":"Point"}
}
