{
  "type": "Feature",
  "properties": {
    "iso:country":"GB",
    "wof:name":"BB2 5LY",
    "wof:placetype":"postalcode"
},
  "geometry": {"coordinates":[-2.52288163462233,53.73170775408235],"type":"Point"}
}