{
  "type": "Feature",
  "properties": {
    "date:inception_lower": "1980-01-01",
    "date:inception_upper": "1980-01-01",
    "iso:country": "GB",
    "wof:name": "TW18 1JD",
    "wof:placetype": "postalcode"
  },
  "geometry": {"coordinates":[-0.489387,51.425614],"type":"Point"}
}
