{
  "type": "Feature",
  "properties": {
    "iso:country": "GB",
    "wof:name": "PE8 5LR",
    "wof:placetype": "postalcode"
  },
  "geometry": {"coordinates":[-0.429444,52.471006],"type":"Point"}
}
