{
  "type": "Feature",
  "properties": {
    "iso:country": "GB",
    "wof:name": "LE16 8TR",
    "wof:placetype": "postalcode"
  },
  "geometry": {"coordinates":[-0.724553,52.517799],"type":"Point"}
}
