{
  "type": "Feature",
  "properties": {
    "iso:country":"GB",
    "wof:name":"DH1 1EB",
    "wof:placetype":"postalcode"
},
  "geometry": {"coordinates":[-1.54414077146074,54.78376459879704],"type":"Point"}
}