{
  "type": "Feature",
  "properties": {
    "iso:country":"GB",
    "wof:name":"CT3 4HG",
    "wof:placetype":"postalcode"
},
  "geometry": {"coordinates":[1.16953564401315,51.31670623764855],"type":"Point"}
}