{
  "type": "Feature",
  "properties": {
    "date:inception_lower": "2011-07-01",
    "date:inception_upper": "2011-07-01",
    "iso:country": "GB",
    "wof:name": "LU1 5FE",
    "wof:placetype": "postalcode"
  },
  "geometry": {"coordinates":[-0.423031,51.873378],"type":"Point"}
}
