{
  "type": "Feature",
  "properties": {
    "date:inception_lower":"2014-08-01",
    "date:inception_upper":"2014-08-31",
    "iso:country":"GB",
    "wof:name":"DY11 7EX",
    "wof:placetype":"postalcode"
},
  "geometry": {"coordinates":[-2.274661,52.366035],"type":"Point"}
}