{
  "type": "Feature",
  "properties": {
    "date:inception_lower": "2023-11-01",
    "date:inception_upper": "2023-11-01",
    "iso:country": "GB",
    "wof:name": "SN3 4TL",
    "wof:placetype": "postalcode"
  },
  "geometry": {"coordinates":[-1.743386,51.598916],"type":"Point"}
}
