{
  "type": "Feature",
  "properties": {
    "iso:country":"GB",
    "wof:name":"SG4 9EJ",
    "wof:placetype":"postalcode"
},
  "geometry": {"coordinates":[-0.26798605358371,51.93946394894179],"type":"Point"}
}