{
  "type": "Feature",
  "properties": {
    "date:inception_lower": "2014-09-01",
    "date:inception_upper": "2014-09-01",
    "iso:country": "GB",
    "wof:name": "WA16 8US",
    "wof:placetype": "postalcode"
  },
  "geometry": {"coordinates":[-2.329804,53.262632],"type":"Point"}
}
