{
  "type": "Feature",
  "properties": {
    "iso:country": "GB",
    "wof:name": "WA16 8US",
    "wof:placetype": "postalcode"
  },
  "geometry": {"coordinates":[-2.329804,53.262632],"type":"Point"}
}
