{
  "type": "Feature",
  "properties": {
    "iso:country":"GB",
    "wof:name":"HP10 0EF",
    "wof:placetype":"postalcode"
},
  "geometry": {"coordinates":[-0.68214781401394,51.58798749945745],"type":"Point"}
}