{
  "type": "Feature",
  "properties": {
    "iso:country":"GB",
    "wof:name":"BN20 8BU",
    "wof:placetype":"postalcode"
},
  "geometry": {"coordinates":[0.26093797807408,50.76733448848219],"type":"Point"}
}