{
  "type": "Feature",
  "properties": {
    "date:inception_lower":"1980-01-01",
    "date:inception_upper":"1980-01-31",
    "iso:country":"GB",
    "wof:name":"LL65 3NP",
    "wof:placetype":"postalcode"
},
  "geometry": {"coordinates":[-4.531011,53.274467],"type":"Point"}
}