{
  "type": "Feature",
  "properties": {
    "date:inception_lower": "2021-05-01",
    "date:inception_upper": "2021-05-01",
    "iso:country": "GB",
    "wof:name": "SS5 6FE",
    "wof:placetype": "postalcode"
  },
  "geometry": {"coordinates":[0.608506,51.6209],"type":"Point"}
}
