{
  "type": "Feature",
  "properties": {
    "iso:country":"GB",
    "wof:name":"CW1 3XT",
    "wof:placetype":"postalcode"
},
  "geometry": {"coordinates":[-2.4516966683699,53.11706020569322],"type":"Point"}
}