{
  "type": "Feature",
  "properties": {
    "iso:country": "GB",
    "wof:name": "CW1 3XT",
    "wof:placetype": "postalcode"
  },
  "geometry": {"coordinates":[-2.451697,53.11706],"type":"Point"}
}
