{
  "type": "Feature",
  "properties": {
    "iso:country":"GB",
    "wof:name":"HU10 7UW",
    "wof:placetype":"postalcode"
},
  "geometry": {"coordinates":[-0.45481012323057,53.75671585568758],"type":"Point"}
}