{
  "type": "Feature",
  "properties": {
    "iso:country": "GB",
    "wof:name": "OX10 8DD",
    "wof:placetype": "postalcode"
  },
  "geometry": {"coordinates":[-1.111514,51.586753],"type":"Point"}
}
