{
  "type": "Feature",
  "properties": {
    "iso:country": "GB",
    "wof:name": "TN31 7RE",
    "wof:placetype": "postalcode"
  },
  "geometry": {"coordinates":[0.79047,50.935599],"type":"Point"}
}
