{
  "type": "Feature",
  "properties": {
    "iso:country":"GB",
    "wof:name":"CT9 1RB",
    "wof:placetype":"postalcode"
},
  "geometry": {"coordinates":[1.3878634811362,51.38684020009698],"type":"Point"}
}