{
  "type": "Feature",
  "properties": {
    "date:inception_lower": "1991-09-01",
    "date:inception_upper": "1991-09-01",
    "iso:country": "GB",
    "wof:name": "CT9 1RB",
    "wof:placetype": "postalcode"
  },
  "geometry": {"coordinates":[1.387864,51.38684],"type":"Point"}
}
