{
  "type": "Feature",
  "properties": {
    "date:inception_lower": "1994-05-01",
    "date:inception_upper": "1994-05-01",
    "iso:country": "GB",
    "wof:name": "M35 0EA",
    "wof:placetype": "postalcode"
  },
  "geometry": {"coordinates":[-2.158184,53.50643],"type":"Point"}
}
