{
  "type": "Feature",
  "properties": {
    "iso:country":"GB",
    "wof:name":"M35 0EA",
    "wof:placetype":"postalcode"
},
  "geometry": {"coordinates":[-2.15818376982008,53.50643006012137],"type":"Point"}
}