{
  "type": "Feature",
  "properties": {
    "iso:country":"GB",
    "wof:name":"TA7 0QU",
    "wof:placetype":"postalcode"
},
  "geometry": {"coordinates":[-2.88041557313901,51.08146215527194],"type":"Point"}
}