{
  "type": "Feature",
  "properties": {
    "date:inception_lower": "2011-05-01",
    "date:inception_upper": "2011-05-01",
    "iso:country": "GB",
    "wof:name": "TA7 0QU",
    "wof:placetype": "postalcode"
  },
  "geometry": {"coordinates":[-2.880416,51.081462],"type":"Point"}
}
