{
  "type": "Feature",
  "properties": {
    "date:inception_lower": "1980-01-01",
    "date:inception_upper": "1980-01-01",
    "iso:country": "GB",
    "wof:name": "IP26 5AH",
    "wof:placetype": "postalcode"
  },
  "geometry": {"coordinates":[0.598237,52.559163],"type":"Point"}
}
