{
  "type": "Feature",
  "properties": {
    "iso:country":"GB",
    "wof:name":"IP26 5AH",
    "wof:placetype":"postalcode"
},
  "geometry": {"coordinates":[0.59823688208231,52.55916257964088],"type":"Point"}
}