{
  "type": "Feature",
  "properties": {
    "iso:country":"GB",
    "wof:name":"LL18 4NR",
    "wof:placetype":"postalcode"
},
  "geometry": {"coordinates":[-3.46381507524902,53.31508407333797],"type":"Point"}
}