{
  "type": "Feature",
  "properties": {
    "iso:country":"GB",
    "wof:name":"CF40 2PE",
    "wof:placetype":"postalcode"
},
  "geometry": {"coordinates":[-3.4340819480993,51.61807242152188],"type":"Point"}
}