{
  "type": "Feature",
  "properties": {
    "date:inception_lower": "2007-08-01",
    "date:inception_upper": "2007-08-01",
    "iso:country": "GB",
    "wof:name": "TA18 7DW",
    "wof:placetype": "postalcode"
  },
  "geometry": {"coordinates":[-2.796427,50.89076],"type":"Point"}
}
