{
  "type": "Feature",
  "properties": {
    "iso:country":"GB",
    "wof:name":"GU34 3RN",
    "wof:placetype":"postalcode"
},
  "geometry": {"coordinates":[-0.97210697929914,51.09385030065285],"type":"Point"}
}