{
  "type": "Feature",
  "properties": {
    "iso:country":"GB",
    "wof:name":"WD3 3LE",
    "wof:placetype":"postalcode"
},
  "geometry": {"coordinates":[-0.44905021818517,51.65370326738146],"type":"Point"}
}