{
  "type": "Feature",
  "properties": {
    "iso:country": "GB",
    "wof:name": "WD3 3LE",
    "wof:placetype": "postalcode"
  },
  "geometry": {"coordinates":[-0.44905,51.653703],"type":"Point"}
}
