{
  "type": "Feature",
  "properties": {
    "iso:country": "GB",
    "wof:name": "SW20 0QE",
    "wof:placetype": "postalcode"
  },
  "geometry": {"coordinates":[-0.237891,51.417408],"type":"Point"}
}
