{
  "type": "Feature",
  "properties": {
    "iso:country":"GB",
    "wof:name":"BN3 1AZ",
    "wof:placetype":"postalcode"
},
  "geometry": {"coordinates":[-0.15639259480632,50.82423348879903],"type":"Point"}
}