{
  "type": "Feature",
  "properties": {
    "iso:country":"GB",
    "wof:name":"GL52 6AP",
    "wof:placetype":"postalcode"
},
  "geometry": {"coordinates":[-2.06675009468099,51.89978351174039],"type":"Point"}
}