{
  "type": "Feature",
  "properties": {
    "iso:country":"GB",
    "wof:name":"CT4 6SH",
    "wof:placetype":"postalcode"
},
  "geometry": {"coordinates":[1.20009621538849,51.20575926590625],"type":"Point"}
}