{
  "type": "Feature",
  "properties": {
    "iso:country": "GB",
    "wof:name": "CW9 7JH",
    "wof:placetype": "postalcode"
  },
  "geometry": {"coordinates":[-2.483233,53.251133],"type":"Point"}
}
