{
  "type": "Feature",
  "properties": {
    "iso:country":"GB",
    "wof:name":"CW9 7JH",
    "wof:placetype":"postalcode"
},
  "geometry": {"coordinates":[-2.4832335217946,53.25113271219595],"type":"Point"}
}