{
  "type": "Feature",
  "properties": {
    "iso:country":"GB",
    "wof:name":"SN14 8AX",
    "wof:placetype":"postalcode"
},
  "geometry": {"coordinates":[-2.25457050385598,51.44137002415696],"type":"Point"}
}