{
  "type": "Feature",
  "properties": {
    "iso:country": "GB",
    "wof:name": "DH6 4BU",
    "wof:placetype": "postalcode"
  },
  "geometry": {"coordinates":[-1.511996,54.725659],"type":"Point"}
}
