{
  "type": "Feature",
  "properties": {
    "date:inception_lower": "2018-09-01",
    "date:inception_upper": "2018-09-01",
    "iso:country": "GB",
    "wof:name": "DH6 4BU",
    "wof:placetype": "postalcode"
  },
  "geometry": {"coordinates":[-1.511071,54.72641],"type":"Point"}
}
