{
  "type": "Feature",
  "properties": {
    "iso:country":"GB",
    "wof:name":"SW6 6DX",
    "wof:placetype":"postalcode"
},
  "geometry": {"coordinates":[-0.21782865508446,51.47236429633646],"type":"Point"}
}