{
  "type": "Feature",
  "properties": {
    "date:inception_lower": "1981-06-01",
    "date:inception_upper": "1981-06-01",
    "iso:country": "GB",
    "wof:name": "SW6 6DX",
    "wof:placetype": "postalcode"
  },
  "geometry": {"coordinates":[-0.217931,51.472457],"type":"Point"}
}
