{
  "type": "Feature",
  "properties": {
    "date:inception_lower":"1980-01-01",
    "date:inception_upper":"1980-01-31",
    "iso:country":"GB",
    "wof:name":"BD20 7ND",
    "wof:placetype":"postalcode"
},
  "geometry": {"coordinates":[-1.991203,53.890071],"type":"Point"}
}