{
  "type": "Feature",
  "properties": {
    "iso:country":"GB",
    "wof:name":"BD20 7ND",
    "wof:placetype":"postalcode"
},
  "geometry": {"coordinates":[-1.99119962549856,53.89005722218494],"type":"Point"}
}