{
  "type": "Feature",
  "properties": {
    "date:inception_lower": "1980-01-01",
    "date:inception_upper": "1980-01-01",
    "iso:country": "GB",
    "wof:name": "BD20 7ND",
    "wof:placetype": "postalcode"
  },
  "geometry": {"coordinates":[-1.991538,53.889766],"type":"Point"}
}
