{
  "type": "Feature",
  "properties": {
    "iso:country":"GB",
    "wof:name":"NE33 2NB",
    "wof:placetype":"postalcode"
},
  "geometry": {"coordinates":[-1.42296292920259,54.99908613609288],"type":"Point"}
}