{
  "type": "Feature",
  "properties": {
    "iso:country":"GB",
    "wof:name":"TN2 3BS",
    "wof:placetype":"postalcode"
},
  "geometry": {"coordinates":[0.28495618511831,51.15061253417245],"type":"Point"}
}