{
  "type": "Feature",
  "properties": {
    "iso:country":"GB",
    "wof:name":"BS24 9XG",
    "wof:placetype":"postalcode"
},
  "geometry": {"coordinates":[-2.95117981187971,51.3231032668987],"type":"Point"}
}