{
  "type": "Feature",
  "properties": {
    "iso:country": "GB",
    "wof:name": "DY2 7QD",
    "wof:placetype": "postalcode"
  },
  "geometry": {"coordinates":[-2.068908,52.51073],"type":"Point"}
}
