{
  "type": "Feature",
  "properties": {
    "iso:country":"GB",
    "wof:name":"DY2 7QD",
    "wof:placetype":"postalcode"
},
  "geometry": {"coordinates":[-2.06891316863976,52.51070558856147],"type":"Point"}
}