{
  "type": "Feature",
  "properties": {
    "iso:country": "GB",
    "wof:name": "SA2 7QE",
    "wof:placetype": "postalcode"
  },
  "geometry": {"coordinates":[-4.026956,51.624716],"type":"Point"}
}
