{
  "type": "Feature",
  "properties": {
    "date:inception_lower": "1980-01-01",
    "date:inception_upper": "1980-01-01",
    "iso:country": "GB",
    "wof:name": "GL53 9DF",
    "wof:placetype": "postalcode"
  },
  "geometry": {"coordinates":[-2.063333,51.878261],"type":"Point"}
}
