{
  "type": "Feature",
  "properties": {
    "iso:country": "GB",
    "wof:name": "GL53 9DF",
    "wof:placetype": "postalcode"
  },
  "geometry": {"coordinates":[-2.063333,51.878261],"type":"Point"}
}
