{
  "type": "Feature",
  "properties": {
    "iso:country": "GB",
    "wof:name": "WN7 2GN",
    "wof:placetype": "postalcode"
  },
  "geometry": {"coordinates":[-2.499367,53.499577],"type":"Point"}
}
