{
  "type": "Feature",
  "properties": {
    "date:inception_lower": "1980-01-01",
    "date:inception_upper": "1980-01-01",
    "iso:country": "GB",
    "wof:name": "DG2 0SR",
    "wof:placetype": "postalcode"
  },
  "geometry": {"coordinates":[-3.769298,55.145803],"type":"Point"}
}
