{
  "type": "Feature",
  "properties": {
    "iso:country":"GB",
    "wof:name":"SG8 5LZ",
    "wof:placetype":"postalcode"
},
  "geometry": {"coordinates":[-0.01979947274316,52.05845298873126],"type":"Point"}
}