{
  "type": "Feature",
  "properties": {
    "date:inception_lower":"1980-01-01",
    "date:inception_upper":"1980-01-31",
    "iso:country":"GB",
    "wof:name":"TN26 2HH",
    "wof:placetype":"postalcode"
},
  "geometry": {"coordinates":[0.857641,51.067815],"type":"Point"}
}