{
  "type": "Feature",
  "properties": {
    "iso:country":"GB",
    "wof:name":"TN26 2HH",
    "wof:placetype":"postalcode"
},
  "geometry": {"coordinates":[0.85764082929044,51.0678145315214],"type":"Point"}
}