{
  "type": "Feature",
  "properties": {
    "iso:country": "GB",
    "wof:name": "TN26 2HH",
    "wof:placetype": "postalcode"
  },
  "geometry": {"coordinates":[0.857641,51.067815],"type":"Point"}
}
