{
  "type": "Feature",
  "properties": {
    "iso:country": "GB",
    "wof:name": "SY3 5BX",
    "wof:placetype": "postalcode"
  },
  "geometry": {"coordinates":[-2.809438,52.714762],"type":"Point"}
}
