{
  "type": "Feature",
  "properties": {
    "date:inception_lower":"1983-03-01",
    "date:inception_upper":"1983-03-31",
    "iso:country":"GB",
    "wof:name":"SY3 5BX",
    "wof:placetype":"postalcode"
},
  "geometry": {"coordinates":[-2.809438,52.714762],"type":"Point"}
}