{
  "type": "Feature",
  "properties": {
    "iso:country":"GB",
    "wof:name":"SY3 5BX",
    "wof:placetype":"postalcode"
},
  "geometry": {"coordinates":[-2.80943777702602,52.71476165468162],"type":"Point"}
}