{
  "type": "Feature",
  "properties": {
    "iso:country": "GB",
    "wof:name": "EX2 8EA",
    "wof:placetype": "postalcode"
  },
  "geometry": {"coordinates":[-3.531944,50.714737],"type":"Point"}
}
