{
  "type": "Feature",
  "properties": {
    "iso:country":"GB",
    "wof:name":"CO10 7EA",
    "wof:placetype":"postalcode"
},
  "geometry": {"coordinates":[0.70735002871591,52.0136786073868],"type":"Point"}
}