{
  "type": "Feature",
  "properties": {
    "iso:country": "GB",
    "wof:name": "CO10 7EA",
    "wof:placetype": "postalcode"
  },
  "geometry": {"coordinates":[0.70735,52.013679],"type":"Point"}
}
