{
  "type": "Feature",
  "properties": {
    "iso:country": "GB",
    "wof:name": "LS27 8SU",
    "wof:placetype": "postalcode"
  },
  "geometry": {"coordinates":[-1.578397,53.746211],"type":"Point"}
}
