{
  "type": "Feature",
  "properties": {
    "iso:country":"GB",
    "wof:name":"LE2 3AN",
    "wof:placetype":"postalcode"
},
  "geometry": {"coordinates":[-1.12021292184124,52.61568047486708],"type":"Point"}
}