{
  "type": "Feature",
  "properties": {
    "iso:country": "GB",
    "wof:name": "LE2 3AN",
    "wof:placetype": "postalcode"
  },
  "geometry": {"coordinates":[-1.120213,52.61568],"type":"Point"}
}
