{
  "type": "Feature",
  "properties": {
    "date:inception_lower":"1980-01-01",
    "date:inception_upper":"1980-01-31",
    "iso:country":"GB",
    "wof:name":"LE2 3AN",
    "wof:placetype":"postalcode"
},
  "geometry": {"coordinates":[-1.120213,52.61568],"type":"Point"}
}