{
  "type": "Feature",
  "properties": {
    "iso:country":"GB",
    "wof:name":"BS5 9SA",
    "wof:placetype":"postalcode"
},
  "geometry": {"coordinates":[-2.55943740433202,51.45465265618593],"type":"Point"}
}