{
  "type": "Feature",
  "properties": {
    "iso:country":"GB",
    "wof:name":"LN13 0NP",
    "wof:placetype":"postalcode"
},
  "geometry": {"coordinates":[0.14631609559266,53.33851226956948],"type":"Point"}
}