{
  "type": "Feature",
  "properties": {
    "iso:country":"GB",
    "wof:name":"B35 6PF",
    "wof:placetype":"postalcode"
},
  "geometry": {"coordinates":[-1.78453129052311,52.52453643607237],"type":"Point"}
}