{
  "type": "Feature",
  "properties": {
    "date:inception_lower": "1980-01-01",
    "date:inception_upper": "1980-01-01",
    "iso:country": "GB",
    "wof:name": "B35 6PF",
    "wof:placetype": "postalcode"
  },
  "geometry": {"coordinates":[-1.784531,52.524536],"type":"Point"}
}
