{
  "type": "Feature",
  "properties": {
    "iso:country":"GB",
    "wof:name":"SE18 6DD",
    "wof:placetype":"postalcode"
},
  "geometry": {"coordinates":[0.06425293670328,51.49181986520435],"type":"Point"}
}