{
  "type": "Feature",
  "properties": {
    "date:inception_lower": "2007-03-01",
    "date:inception_upper": "2007-03-01",
    "iso:country": "GB",
    "wof:name": "CA11 7SZ",
    "wof:placetype": "postalcode"
  },
  "geometry": {"coordinates":[-2.74891,54.670116],"type":"Point"}
}
