{
  "type": "Feature",
  "properties": {
    "iso:country": "GB",
    "wof:name": "EX15 1GX",
    "wof:placetype": "postalcode"
  },
  "geometry": {"coordinates":[-3.40438,50.856035],"type":"Point"}
}
