{
  "type": "Feature",
  "properties": {
    "date:inception_lower": "1980-01-01",
    "date:inception_upper": "1980-01-01",
    "iso:country": "GB",
    "wof:name": "CT12 6NH",
    "wof:placetype": "postalcode"
  },
  "geometry": {"coordinates":[1.387905,51.347332],"type":"Point"}
}
