{
  "type": "Feature",
  "properties": {
    "iso:country":"GB",
    "wof:name":"PE30 5DP",
    "wof:placetype":"postalcode"
},
  "geometry": {"coordinates":[0.39967530103851,52.74193194708684],"type":"Point"}
}