{
  "type": "Feature",
  "properties": {
    "date:inception_lower":"2015-10-01",
    "date:inception_upper":"2015-10-31",
    "iso:country":"GB",
    "wof:name":"PE30 5DP",
    "wof:placetype":"postalcode"
},
  "geometry": {"coordinates":[0.39927,52.742106],"type":"Point"}
}