{
  "type": "Feature",
  "properties": {
    "date:inception_lower": "1980-01-01",
    "date:inception_upper": "1980-01-01",
    "iso:country": "GB",
    "wof:name": "FY2 0LS",
    "wof:placetype": "postalcode"
  },
  "geometry": {"coordinates":[-3.037198,53.84653],"type":"Point"}
}
