{
  "type": "Feature",
  "properties": {
    "iso:country":"GB",
    "wof:name":"FY2 0LS",
    "wof:placetype":"postalcode"
},
  "geometry": {"coordinates":[-3.03719821855529,53.84652950473117],"type":"Point"}
}