{
  "type": "Feature",
  "properties": {
    "iso:country": "GB",
    "wof:name": "LN5 8ND",
    "wof:placetype": "postalcode"
  },
  "geometry": {"coordinates":[-0.54979,53.210685],"type":"Point"}
}
