{
  "type": "Feature",
  "properties": {
    "iso:country":"GB",
    "wof:name":"DN5 7BQ",
    "wof:placetype":"postalcode"
},
  "geometry": {"coordinates":[-1.24861414279035,53.5416218579246],"type":"Point"}
}