{
  "type": "Feature",
  "properties": {
    "iso:country":"GB",
    "wof:name":"NE23 1PZ",
    "wof:placetype":"postalcode"
},
  "geometry": {"coordinates":[-1.5813085793739,55.09435805508705],"type":"Point"}
}