{
  "type": "Feature",
  "properties": {
    "iso:country":"GB",
    "wof:name":"N18 2AN",
    "wof:placetype":"postalcode"
},
  "geometry": {"coordinates":[-0.06109900065659,51.61134823708555],"type":"Point"}
}