{
  "type": "Feature",
  "properties": {
    "date:inception_lower":"1980-01-01",
    "date:inception_upper":"1980-01-31",
    "iso:country":"GB",
    "wof:name":"SW9 6SW",
    "wof:placetype":"postalcode"
},
  "geometry": {"coordinates":[-0.106973,51.471238],"type":"Point"}
}