{
  "type": "Feature",
  "properties": {
    "iso:country": "GB",
    "wof:name": "SW9 6SW",
    "wof:placetype": "postalcode"
  },
  "geometry": {"coordinates":[-0.106973,51.471238],"type":"Point"}
}
