{
  "type": "Feature",
  "properties": {
    "iso:country":"GB",
    "wof:name":"SW9 6SW",
    "wof:placetype":"postalcode"
},
  "geometry": {"coordinates":[-0.10697338327741,51.47123841034513],"type":"Point"}
}