{
  "type": "Feature",
  "properties": {
    "date:inception_lower": "1999-06-01",
    "date:inception_upper": "1999-06-01",
    "iso:country": "GB",
    "wof:name": "NP20 4NZ",
    "wof:placetype": "postalcode"
  },
  "geometry": {"coordinates":[-3.003179,51.587218],"type":"Point"}
}
