{
  "type": "Feature",
  "properties": {
    "iso:country": "GB",
    "wof:name": "DT11 0QL",
    "wof:placetype": "postalcode"
  },
  "geometry": {"coordinates":[-2.189205,50.872958],"type":"Point"}
}
