{
  "type": "Feature",
  "properties": {
    "date:inception_lower":"1980-01-01",
    "date:inception_upper":"1980-01-31",
    "iso:country":"GB",
    "wof:name":"RG22 6LR",
    "wof:placetype":"postalcode"
},
  "geometry": {"coordinates":[-1.12393,51.253295],"type":"Point"}
}