{
  "type": "Feature",
  "properties": {
    "iso:country":"GB",
    "wof:name":"NR14 7RA",
    "wof:placetype":"postalcode"
},
  "geometry": {"coordinates":[1.34408252676731,52.57292462811687],"type":"Point"}
}