{
  "type": "Feature",
  "properties": {
    "iso:country": "GB",
    "wof:name": "NR14 7RA",
    "wof:placetype": "postalcode"
  },
  "geometry": {"coordinates":[1.344083,52.572925],"type":"Point"}
}
