{
  "type": "Feature",
  "properties": {
    "iso:country":"GB",
    "wof:name":"DT11 9QL",
    "wof:placetype":"postalcode"
},
  "geometry": {"coordinates":[-2.16603069702165,50.84920669312998],"type":"Point"}
}