{
  "type": "Feature",
  "properties": {
    "date:inception_lower":"2004-09-01",
    "date:inception_upper":"2004-09-30",
    "iso:country":"GB",
    "wof:name":"LE12 7UX",
    "wof:placetype":"postalcode"
},
  "geometry": {"coordinates":[-1.124253,52.727725],"type":"Point"}
}