{
  "type": "Feature",
  "properties": {
    "iso:country":"GB",
    "wof:name":"LE12 7UX",
    "wof:placetype":"postalcode"
},
  "geometry": {"coordinates":[-1.12425334843858,52.72772507556904],"type":"Point"}
}