{
  "type": "Feature",
  "properties": {
    "iso:country": "GB",
    "wof:name": "IP26 4NE",
    "wof:placetype": "postalcode"
  },
  "geometry": {"coordinates":[0.551731,52.461503],"type":"Point"}
}
