{
  "type": "Feature",
  "properties": {
    "date:inception_lower": "1980-01-01",
    "date:inception_upper": "1980-01-01",
    "iso:country": "GB",
    "wof:name": "IP26 4NE",
    "wof:placetype": "postalcode"
  },
  "geometry": {"coordinates":[0.551731,52.461503],"type":"Point"}
}
