{
  "type": "Feature",
  "properties": {
    "iso:country":"GB",
    "wof:name":"IP26 4NE",
    "wof:placetype":"postalcode"
},
  "geometry": {"coordinates":[0.55173085054952,52.46150292791175],"type":"Point"}
}