{
  "type": "Feature",
  "properties": {
    "date:inception_lower": "1997-06-01",
    "date:inception_upper": "1997-06-01",
    "iso:country": "GB",
    "wof:name": "WC2N 6HG",
    "wof:placetype": "postalcode"
  },
  "geometry": {"coordinates":[-0.123437,51.509067],"type":"Point"}
}
