{
  "type": "Feature",
  "properties": {
    "iso:country":"GB",
    "wof:name":"SK14 2RT",
    "wof:placetype":"postalcode"
},
  "geometry": {"coordinates":[-2.07086905698751,53.45151363774645],"type":"Point"}
}