{
  "type": "Feature",
  "properties": {
    "date:inception_lower": "1996-06-01",
    "date:inception_upper": "1996-06-01",
    "iso:country": "GB",
    "wof:name": "AB24 1WG",
    "wof:placetype": "postalcode"
  },
  "geometry": {"coordinates":[-2.088794,57.167272],"type":"Point"}
}
