{
  "type": "Feature",
  "properties": {
    "iso:country": "GB",
    "wof:name": "AB24 1WG",
    "wof:placetype": "postalcode"
  },
  "geometry": {"coordinates":[-2.088794,57.167272],"type":"Point"}
}
