{
  "type": "Feature",
  "properties": {
    "iso:country": "GB",
    "wof:name": "M5 4LZ",
    "wof:placetype": "postalcode"
  },
  "geometry": {"coordinates":[-2.267429,53.479404],"type":"Point"}
}
