{
  "type": "Feature",
  "properties": {
    "iso:country": "GB",
    "wof:name": "CA20 1DE",
    "wof:placetype": "postalcode"
  },
  "geometry": {"coordinates":[-3.480411,54.439839],"type":"Point"}
}
