{
  "type": "Feature",
  "properties": {
    "iso:country":"GB",
    "wof:name":"SA43 2BZ",
    "wof:placetype":"postalcode"
},
  "geometry": {"coordinates":[-4.54885452932235,52.13103507764105],"type":"Point"}
}