{
  "type": "Feature",
  "properties": {
    "iso:country": "GB",
    "wof:name": "B98 7EJ",
    "wof:placetype": "postalcode"
  },
  "geometry": {"coordinates":[-1.938277,52.300126],"type":"Point"}
}
