{
  "type": "Feature",
  "properties": {
    "iso:country":"GB",
    "wof:name":"B98 7EJ",
    "wof:placetype":"postalcode"
},
  "geometry": {"coordinates":[-1.93827698425549,52.30012637139007],"type":"Point"}
}