{
  "type": "Feature",
  "properties": {
    "iso:country":"GB",
    "wof:name":"N1 3BE",
    "wof:placetype":"postalcode"
},
  "geometry": {"coordinates":[-0.08941250391612,51.54137442079557],"type":"Point"}
}