{
  "type": "Feature",
  "properties": {
    "date:inception_lower": "1980-01-01",
    "date:inception_upper": "1980-01-01",
    "iso:country": "GB",
    "wof:name": "N1 3BE",
    "wof:placetype": "postalcode"
  },
  "geometry": {"coordinates":[-0.089412,51.541374],"type":"Point"}
}
