{
  "type": "Feature",
  "properties": {
    "iso:country":"GB",
    "wof:name":"CH43 7NL",
    "wof:placetype":"postalcode"
},
  "geometry": {"coordinates":[-3.07968581654127,53.39416703328651],"type":"Point"}
}