{
  "type": "Feature",
  "properties": {
    "iso:country":"GB",
    "wof:name":"B21 0BB",
    "wof:placetype":"postalcode"
},
  "geometry": {"coordinates":[-1.95587570033821,52.5061508019223],"type":"Point"}
}