{
  "type": "Feature",
  "properties": {
    "date:inception_lower": "1980-01-01",
    "date:inception_upper": "1980-01-01",
    "iso:country": "GB",
    "wof:name": "B21 0BB",
    "wof:placetype": "postalcode"
  },
  "geometry": {"coordinates":[-1.955876,52.506151],"type":"Point"}
}
