{
  "type": "Feature",
  "properties": {
    "iso:country":"GB",
    "wof:name":"FY5 3FG",
    "wof:placetype":"postalcode"
},
  "geometry": {"coordinates":[-3.02430107307393,53.87049527396287],"type":"Point"}
}