{
  "type": "Feature",
  "properties": {
    "iso:country": "GB",
    "wof:name": "FY5 3FG",
    "wof:placetype": "postalcode"
  },
  "geometry": {"coordinates":[-3.024301,53.870495],"type":"Point"}
}
