{
  "type": "Feature",
  "properties": {
    "iso:country":"GB",
    "wof:name":"SO53 5EP",
    "wof:placetype":"postalcode"
},
  "geometry": {"coordinates":[-1.3922566720289,50.99958182506125],"type":"Point"}
}