{
  "type": "Feature",
  "properties": {
    "date:inception_lower": "2005-06-01",
    "date:inception_upper": "2005-06-01",
    "iso:country": "GB",
    "wof:name": "SO53 5EP",
    "wof:placetype": "postalcode"
  },
  "geometry": {"coordinates":[-1.392257,50.999582],"type":"Point"}
}
