{
  "type": "Feature",
  "properties": {
    "iso:country":"GB",
    "wof:name":"EX4 4BX",
    "wof:placetype":"postalcode"
},
  "geometry": {"coordinates":[-3.5426673601729,50.72898457427971],"type":"Point"}
}