{
  "type": "Feature",
  "properties": {
    "iso:country": "GB",
    "wof:name": "EX4 4BX",
    "wof:placetype": "postalcode"
  },
  "geometry": {"coordinates":[-3.542667,50.728985],"type":"Point"}
}
