{
  "type": "Feature",
  "properties": {
    "iso:country":"GB",
    "wof:name":"M6 8PL",
    "wof:placetype":"postalcode"
},
  "geometry": {"coordinates":[-2.31508823071191,53.49337352480929],"type":"Point"}
}