{
  "type": "Feature",
  "properties": {
    "iso:country":"GB",
    "wof:name":"N17 8EG",
    "wof:placetype":"postalcode"
},
  "geometry": {"coordinates":[-0.07359457126914,51.60822676914054],"type":"Point"}
}