{
  "type": "Feature",
  "properties": {
    "date:inception_lower": "1986-04-01",
    "date:inception_upper": "1986-04-01",
    "iso:country": "GB",
    "wof:name": "GL50 1JD",
    "wof:placetype": "postalcode"
  },
  "geometry": {"coordinates":[-2.076515,51.899013],"type":"Point"}
}
