{
  "type": "Feature",
  "properties": {
    "iso:country": "GB",
    "wof:name": "TS10 3AY",
    "wof:placetype": "postalcode"
  },
  "geometry": {"coordinates":[-1.051373,54.61149],"type":"Point"}
}
