{
  "type": "Feature",
  "properties": {
    "iso:country": "GB",
    "wof:name": "SK12 1DL",
    "wof:placetype": "postalcode"
  },
  "geometry": {"coordinates":[-2.111068,53.35153],"type":"Point"}
}
