{
  "type": "Feature",
  "properties": {
    "iso:country":"GB",
    "wof:name":"SK12 1DL",
    "wof:placetype":"postalcode"
},
  "geometry": {"coordinates":[-2.11106847500703,53.35153016116232],"type":"Point"}
}