{
  "type": "Feature",
  "properties": {
    "date:inception_lower":"1980-01-01",
    "date:inception_upper":"1980-01-31",
    "iso:country":"GB",
    "wof:name":"SK12 1DL",
    "wof:placetype":"postalcode"
},
  "geometry": {"coordinates":[-2.111068,53.35153],"type":"Point"}
}