{
  "type": "Feature",
  "properties": {
    "iso:country":"GB",
    "wof:name":"TW2 5DA",
    "wof:placetype":"postalcode"
},
  "geometry": {"coordinates":[-0.3532902015065,51.44365399217892],"type":"Point"}
}