{
  "type": "Feature",
  "properties": {
    "iso:country":"GB",
    "wof:name":"PO12 2LE",
    "wof:placetype":"postalcode"
},
  "geometry": {"coordinates":[-1.1516543582258,50.78532702372138],"type":"Point"}
}