{
  "type": "Feature",
  "properties": {
    "iso:country": "GB",
    "wof:name": "BS16 2SF",
    "wof:placetype": "postalcode"
  },
  "geometry": {"coordinates":[-2.510446,51.493279],"type":"Point"}
}
