{
  "type": "Feature",
  "properties": {
    "date:inception_lower":"1980-01-01",
    "date:inception_upper":"1980-01-31",
    "iso:country":"GB",
    "wof:name":"EX17 4QZ",
    "wof:placetype":"postalcode"
},
  "geometry": {"coordinates":[-3.68977,50.893222],"type":"Point"}
}