{
  "type": "Feature",
  "properties": {
    "iso:country":"GB",
    "wof:name":"EX17 4QZ",
    "wof:placetype":"postalcode"
},
  "geometry": {"coordinates":[-3.68976987418412,50.89322221858156],"type":"Point"}
}