{
  "type": "Feature",
  "properties": {
    "iso:country": "GB",
    "wof:name": "NR10 3SJ",
    "wof:placetype": "postalcode"
  },
  "geometry": {"coordinates":[1.23845,52.698148],"type":"Point"}
}
