{
  "type": "Feature",
  "properties": {
    "iso:country":"GB",
    "wof:name":"NR10 3SJ",
    "wof:placetype":"postalcode"
},
  "geometry": {"coordinates":[1.23845039216762,52.69814802901958],"type":"Point"}
}