{
  "type": "Feature",
  "properties": {
    "date:inception_lower": "2018-03-01",
    "date:inception_upper": "2018-03-01",
    "iso:country": "GB",
    "wof:name": "OX3 8GF",
    "wof:placetype": "postalcode"
  },
  "geometry": {"coordinates":[-1.186924,51.766243],"type":"Point"}
}
