{
  "type": "Feature",
  "properties": {
    "iso:country": "GB",
    "wof:name": "OX3 8GF",
    "wof:placetype": "postalcode"
  },
  "geometry": {"coordinates":[-1.186924,51.766243],"type":"Point"}
}
