{
  "type": "Feature",
  "properties": {
    "iso:country":"GB",
    "wof:name":"WN5 7DE",
    "wof:placetype":"postalcode"
},
  "geometry": {"coordinates":[-2.71360681327877,53.522371823459],"type":"Point"}
}