{
  "type": "Feature",
  "properties": {
    "iso:country":"GB",
    "wof:name":"CT20 2AF",
    "wof:placetype":"postalcode"
},
  "geometry": {"coordinates":[1.17802454063078,51.07812922286637],"type":"Point"}
}