{
  "type": "Feature",
  "properties": {
    "iso:country": "GB",
    "wof:name": "KY13 0UJ",
    "wof:placetype": "postalcode"
  },
  "geometry": {"coordinates":[-3.557365,56.184111],"type":"Point"}
}
