{
  "type": "Feature",
  "properties": {
    "iso:country":"GB",
    "wof:name":"KY13 0UJ",
    "wof:placetype":"postalcode"
},
  "geometry": {"coordinates":[-3.55736521907675,56.18411111474639],"type":"Point"}
}