{
  "type": "Feature",
  "properties": {
    "iso:country": "GB",
    "wof:name": "EN2 9JB",
    "wof:placetype": "postalcode"
  },
  "geometry": {"coordinates":[-0.091014,51.671485],"type":"Point"}
}
