{
  "type": "Feature",
  "properties": {
    "iso:country":"GB",
    "wof:name":"EN2 9JB",
    "wof:placetype":"postalcode"
},
  "geometry": {"coordinates":[-0.09101441531756,51.67148507981413],"type":"Point"}
}