{
  "type": "Feature",
  "properties": {
    "iso:country":"GB",
    "wof:name":"M33 5JW",
    "wof:placetype":"postalcode"
},
  "geometry": {"coordinates":[-2.35413694733017,53.42585025433878],"type":"Point"}
}