{
  "type": "Feature",
  "properties": {
    "iso:country": "GB",
    "wof:name": "TQ12 4QG",
    "wof:placetype": "postalcode"
  },
  "geometry": {"coordinates":[-3.531662,50.524205],"type":"Point"}
}
