{
  "type": "Feature",
  "properties": {
    "iso:country": "GB",
    "wof:name": "WN6 8RT",
    "wof:placetype": "postalcode"
  },
  "geometry": {"coordinates":[-2.64836,53.566119],"type":"Point"}
}
