{
  "type": "Feature",
  "properties": {
    "date:inception_lower": "1980-01-01",
    "date:inception_upper": "1980-01-01",
    "iso:country": "GB",
    "wof:name": "CV8 2DF",
    "wof:placetype": "postalcode"
  },
  "geometry": {"coordinates":[-1.554573,52.347842],"type":"Point"}
}
