{
  "type": "Feature",
  "properties": {
    "date:inception_lower": "1980-01-01",
    "date:inception_upper": "1980-01-01",
    "iso:country": "GB",
    "wof:name": "GL14 1EL",
    "wof:placetype": "postalcode"
  },
  "geometry": {"coordinates":[-2.42935,51.774592],"type":"Point"}
}
