{
  "type": "Feature",
  "properties": {
    "iso:country":"GB",
    "wof:name":"GL14 1EL",
    "wof:placetype":"postalcode"
},
  "geometry": {"coordinates":[-2.42935017312866,51.77459198221275],"type":"Point"}
}