{
  "type": "Feature",
  "properties": {
    "iso:country":"GB",
    "wof:name":"RH4 1NN",
    "wof:placetype":"postalcode"
},
  "geometry": {"coordinates":[-0.31224210787674,51.23827359904954],"type":"Point"}
}