{
  "type": "Feature",
  "properties": {
    "iso:country": "GB",
    "wof:name": "RH4 1NN",
    "wof:placetype": "postalcode"
  },
  "geometry": {"coordinates":[-0.312242,51.238274],"type":"Point"}
}
