{
  "type": "Feature",
  "properties": {
    "iso:country":"GB",
    "wof:name":"WA2 9RQ",
    "wof:placetype":"postalcode"
},
  "geometry": {"coordinates":[-2.59488076434279,53.41432266327806],"type":"Point"}
}