{
  "type": "Feature",
  "properties": {
    "iso:country": "GB",
    "wof:name": "WA2 9RQ",
    "wof:placetype": "postalcode"
  },
  "geometry": {"coordinates":[-2.594881,53.414323],"type":"Point"}
}
