{
  "type": "Feature",
  "properties": {
    "iso:country":"GB",
    "wof:name":"BL3 1XF",
    "wof:placetype":"postalcode"
},
  "geometry": {"coordinates":[-2.3693775363927,53.56751620192075],"type":"Point"}
}