{
  "type": "Feature",
  "properties": {
    "date:inception_lower": "2011-11-01",
    "date:inception_upper": "2011-11-01",
    "iso:country": "GB",
    "wof:name": "ST3 1PB",
    "wof:placetype": "postalcode"
  },
  "geometry": {"coordinates":[-2.129446,52.986219],"type":"Point"}
}
