{
  "type": "Feature",
  "properties": {
    "date:inception_lower":"2005-10-01",
    "date:inception_upper":"2005-10-31",
    "iso:country":"GB",
    "wof:name":"B97 5JL",
    "wof:placetype":"postalcode"
},
  "geometry": {"coordinates":[-1.939287,52.279629],"type":"Point"}
}