{
  "type": "Feature",
  "properties": {
    "iso:country":"GB",
    "wof:name":"B97 5JL",
    "wof:placetype":"postalcode"
},
  "geometry": {"coordinates":[-1.93928740231447,52.27962912238483],"type":"Point"}
}