{
  "type": "Feature",
  "properties": {
    "date:inception_lower": "1998-12-01",
    "date:inception_upper": "1998-12-01",
    "iso:country": "GB",
    "wof:name": "SA14 8WE",
    "wof:placetype": "postalcode"
  },
  "geometry": {"coordinates":[-4.126962,51.695058],"type":"Point"}
}
