{
  "type": "Feature",
  "properties": {
    "date:inception_lower": "1980-01-01",
    "date:inception_upper": "1980-01-01",
    "iso:country": "GB",
    "wof:name": "HG2 0DJ",
    "wof:placetype": "postalcode"
  },
  "geometry": {"coordinates":[-1.543578,53.985639],"type":"Point"}
}
