{
  "type": "Feature",
  "properties": {
    "iso:country": "GB",
    "wof:name": "CM23 2QJ",
    "wof:placetype": "postalcode"
  },
  "geometry": {"coordinates":[0.149356,51.874079],"type":"Point"}
}
