{
  "type": "Feature",
  "properties": {
    "iso:country": "GB",
    "wof:name": "NE25 9SD",
    "wof:placetype": "postalcode"
  },
  "geometry": {"coordinates":[-1.479369,55.038538],"type":"Point"}
}
