{
  "type": "Feature",
  "properties": {
    "iso:country": "GB",
    "wof:name": "CO16 8FL",
    "wof:placetype": "postalcode"
  },
  "geometry": {"coordinates":[1.135852,51.806856],"type":"Point"}
}
