{
  "type": "Feature",
  "properties": {
    "date:inception_lower":"1981-06-01",
    "date:inception_upper":"1981-06-30",
    "iso:country":"GB",
    "wof:name":"CO16 8FL",
    "wof:placetype":"postalcode"
},
  "geometry": {"coordinates":[1.135852,51.806856],"type":"Point"}
}