{
  "type": "Feature",
  "properties": {
    "iso:country":"GB",
    "wof:name":"CO16 8FL",
    "wof:placetype":"postalcode"
},
  "geometry": {"coordinates":[1.13585239525008,51.80685632750018],"type":"Point"}
}