{
  "type": "Feature",
  "properties": {
    "iso:country":"GB",
    "wof:name":"SE3 8LR",
    "wof:placetype":"postalcode"
},
  "geometry": {"coordinates":[0.04219481370401,51.46467024016084],"type":"Point"}
}