{
  "type": "Feature",
  "properties": {
    "iso:country":"GB",
    "wof:name":"G84 8PX",
    "wof:placetype":"postalcode"
},
  "geometry": {"coordinates":[-4.75865238639214,56.0082947655236],"type":"Point"}
}