{
  "type": "Feature",
  "properties": {
    "iso:country":"GB",
    "wof:name":"GU8 5LU",
    "wof:placetype":"postalcode"
},
  "geometry": {"coordinates":[-0.64836097781066,51.15598618760312],"type":"Point"}
}