{
  "type": "Feature",
  "properties": {
    "date:inception_lower": "1980-01-01",
    "date:inception_upper": "1980-01-01",
    "iso:country": "GB",
    "wof:name": "GU8 5LU",
    "wof:placetype": "postalcode"
  },
  "geometry": {"coordinates":[-0.648361,51.155986],"type":"Point"}
}
