{
  "type": "Feature",
  "properties": {
    "date:inception_lower": "1995-12-01",
    "date:inception_upper": "1995-12-01",
    "iso:country": "GB",
    "wof:name": "G77 5UH",
    "wof:placetype": "postalcode"
  },
  "geometry": {"coordinates":[-4.302861,55.772392],"type":"Point"}
}
