{
  "type": "Feature",
  "properties": {
    "iso:country":"GB",
    "wof:name":"SP5 2DS",
    "wof:placetype":"postalcode"
},
  "geometry": {"coordinates":[-1.66256527443202,50.97198016255084],"type":"Point"}
}