{
  "type": "Feature",
  "properties": {
    "iso:country":"GB",
    "wof:name":"LS26 0LU",
    "wof:placetype":"postalcode"
},
  "geometry": {"coordinates":[-1.47533669233173,53.75437936830486],"type":"Point"}
}