{
  "type": "Feature",
  "properties": {
    "date:inception_lower": "1980-01-01",
    "date:inception_upper": "1980-01-01",
    "iso:country": "GB",
    "wof:name": "LS26 0LU",
    "wof:placetype": "postalcode"
  },
  "geometry": {"coordinates":[-1.475337,53.754379],"type":"Point"}
}
