{
  "type": "Feature",
  "properties": {
    "iso:country":"GB",
    "wof:name":"OX2 7TS",
    "wof:placetype":"postalcode"
},
  "geometry": {"coordinates":[-1.26549888673211,51.78769486109929],"type":"Point"}
}