{
  "type": "Feature",
  "properties": {
    "date:inception_lower":"1980-01-01",
    "date:inception_upper":"1980-01-31",
    "iso:country":"GB",
    "wof:name":"WV14 8JR",
    "wof:placetype":"postalcode"
},
  "geometry": {"coordinates":[-2.079011,52.541136],"type":"Point"}
}