{
  "type": "Feature",
  "properties": {
    "iso:country":"GB",
    "wof:name":"WV14 8JR",
    "wof:placetype":"postalcode"
},
  "geometry": {"coordinates":[-2.07914946353734,52.54112993979002],"type":"Point"}
}