{
  "type": "Feature",
  "properties": {
    "iso:country":"GB",
    "wof:name":"BS15 4EB",
    "wof:placetype":"postalcode"
},
  "geometry": {"coordinates":[-2.49836899958796,51.46493591132874],"type":"Point"}
}