{
  "type": "Feature",
  "properties": {
    "iso:country": "GB",
    "wof:name": "BS15 4EB",
    "wof:placetype": "postalcode"
  },
  "geometry": {"coordinates":[-2.498369,51.464936],"type":"Point"}
}
