{
  "type": "Feature",
  "properties": {
    "date:inception_lower": "1980-01-01",
    "date:inception_upper": "1980-01-01",
    "iso:country": "GB",
    "wof:name": "IP33 3DT",
    "wof:placetype": "postalcode"
  },
  "geometry": {"coordinates":[0.702203,52.243936],"type":"Point"}
}
