{
  "type": "Feature",
  "properties": {
    "date:inception_lower": "2024-09-01",
    "date:inception_upper": "2024-09-01",
    "iso:country": "GB",
    "wof:name": "S66 9FW",
    "wof:placetype": "postalcode"
  },
  "geometry": {"coordinates":[-1.258547,53.399655],"type":"Point"}
}
