{
  "type": "Feature",
  "properties": {
    "iso:country": "GB",
    "wof:name": "WR14 4DT",
    "wof:placetype": "postalcode"
  },
  "geometry": {"coordinates":[-2.351811,52.113464],"type":"Point"}
}
