{
  "type": "Feature",
  "properties": {
    "date:inception_lower": "2024-07-01",
    "date:inception_upper": "2024-07-01",
    "iso:country": "GB",
    "wof:name": "M4 5GL",
    "wof:placetype": "postalcode"
  },
  "geometry": {"coordinates":[-2.235221,53.486347],"type":"Point"}
}
