{
  "type": "Feature",
  "properties": {
    "iso:country":"GB",
    "wof:name":"UB2 5BH",
    "wof:placetype":"postalcode"
},
  "geometry": {"coordinates":[-0.39154395930808,51.50366910332296],"type":"Point"}
}