{
  "type": "Feature",
  "properties": {
    "iso:country":"GB",
    "wof:name":"B33 0XJ",
    "wof:placetype":"postalcode"
},
  "geometry": {"coordinates":[-1.78171834141236,52.47644408189663],"type":"Point"}
}