{
  "type": "Feature",
  "properties": {
    "iso:country":"GB",
    "wof:name":"LN12 2HZ",
    "wof:placetype":"postalcode"
},
  "geometry": {"coordinates":[0.28066205136051,53.30379669194781],"type":"Point"}
}