{
  "type": "Feature",
  "properties": {
    "iso:country":"GB",
    "wof:name":"LA11 7LE",
    "wof:placetype":"postalcode"
},
  "geometry": {"coordinates":[-2.97605658107806,54.17345216676137],"type":"Point"}
}