{
  "type": "Feature",
  "properties": {
    "date:inception_lower": "1980-01-01",
    "date:inception_upper": "1980-01-01",
    "iso:country": "GB",
    "wof:name": "LA11 7LE",
    "wof:placetype": "postalcode"
  },
  "geometry": {"coordinates":[-2.976057,54.173452],"type":"Point"}
}
