{
  "type": "Feature",
  "properties": {
    "date:inception_lower": "2018-09-01",
    "date:inception_upper": "2018-09-01",
    "iso:country": "GB",
    "wof:name": "GU21 5FN",
    "wof:placetype": "postalcode"
  },
  "geometry": {"coordinates":[-0.550542,51.321571],"type":"Point"}
}
