{
  "type": "Feature",
  "properties": {
    "date:inception_lower": "1980-01-01",
    "date:inception_upper": "1980-01-01",
    "iso:country": "GB",
    "wof:name": "NE24 5DT",
    "wof:placetype": "postalcode"
  },
  "geometry": {"coordinates":[-1.528157,55.123782],"type":"Point"}
}
