{
  "type": "Feature",
  "properties": {
    "date:inception_lower":"1980-01-01",
    "date:inception_upper":"1980-01-31",
    "iso:country":"GB",
    "wof:name":"SW12 8AD",
    "wof:placetype":"postalcode"
},
  "geometry": {"coordinates":[-0.149983,51.449875],"type":"Point"}
}