{
  "type": "Feature",
  "properties": {
    "iso:country":"GB",
    "wof:name":"CV11 5PG",
    "wof:placetype":"postalcode"
},
  "geometry": {"coordinates":[-1.47666136709772,52.52083434174428],"type":"Point"}
}