{
  "type": "Feature",
  "properties": {
    "iso:country": "GB",
    "wof:name": "CV11 5PG",
    "wof:placetype": "postalcode"
  },
  "geometry": {"coordinates":[-1.476653,52.520851],"type":"Point"}
}
