{
  "type": "Feature",
  "properties": {
    "iso:country":"GB",
    "wof:name":"NW7 4TD",
    "wof:placetype":"postalcode"
},
  "geometry": {"coordinates":[-0.24540777365987,51.61657683585711],"type":"Point"}
}