{
  "type": "Feature",
  "properties": {
    "iso:country": "GB",
    "wof:name": "B36 8NN",
    "wof:placetype": "postalcode"
  },
  "geometry": {"coordinates":[-1.799515,52.50305],"type":"Point"}
}
