{
  "type": "Feature",
  "properties": {
    "iso:country":"GB",
    "wof:name":"B36 8NN",
    "wof:placetype":"postalcode"
},
  "geometry": {"coordinates":[-1.79951537282609,52.50304985139929],"type":"Point"}
}