{
  "type": "Feature",
  "properties": {
    "date:inception_lower": "1980-01-01",
    "date:inception_upper": "1980-01-01",
    "iso:country": "GB",
    "wof:name": "B36 8NN",
    "wof:placetype": "postalcode"
  },
  "geometry": {"coordinates":[-1.799515,52.50305],"type":"Point"}
}
