{
  "type": "Feature",
  "properties": {
    "date:inception_lower": "1983-03-01",
    "date:inception_upper": "1983-03-01",
    "iso:country": "GB",
    "wof:name": "L21 4PJ",
    "wof:placetype": "postalcode"
  },
  "geometry": {"coordinates":[-3.008714,53.463212],"type":"Point"}
}
