{
  "type": "Feature",
  "properties": {
    "iso:country":"GB",
    "wof:name":"W1W 5AQ",
    "wof:placetype":"postalcode"
},
  "geometry": {"coordinates":[-0.14328893996364,51.5233103187809],"type":"Point"}
}