{
  "type": "Feature",
  "properties": {
    "iso:country":"GB",
    "wof:name":"HP6 6UX",
    "wof:placetype":"postalcode"
},
  "geometry": {"coordinates":[-0.58641870067739,51.67481439441188],"type":"Point"}
}