{
  "type": "Feature",
  "properties": {
    "date:inception_lower":"1995-07-01",
    "date:inception_upper":"1995-07-31",
    "iso:country":"GB",
    "wof:name":"HP6 6UX",
    "wof:placetype":"postalcode"
},
  "geometry": {"coordinates":[-0.586419,51.674814],"type":"Point"}
}