{
  "type": "Feature",
  "properties": {
    "iso:country":"GB",
    "wof:name":"BN24 5AD",
    "wof:placetype":"postalcode"
},
  "geometry": {"coordinates":[0.3117220328614,50.82048263578506],"type":"Point"}
}