{
  "type": "Feature",
  "properties": {
    "date:inception_lower": "1982-06-01",
    "date:inception_upper": "1982-06-01",
    "iso:country": "GB",
    "wof:name": "FK1 2BS",
    "wof:placetype": "postalcode"
  },
  "geometry": {"coordinates":[-3.760077,55.975131],"type":"Point"}
}
