{
  "type": "Feature",
  "properties": {
    "iso:country":"GB",
    "wof:name":"TR1 3DP",
    "wof:placetype":"postalcode"
},
  "geometry": {"coordinates":[-5.05594949686463,50.26372198184248],"type":"Point"}
}