{
  "type": "Feature",
  "properties": {
    "date:inception_lower": "2015-06-01",
    "date:inception_upper": "2015-06-01",
    "iso:country": "GB",
    "wof:name": "WF13 9DR",
    "wof:placetype": "postalcode"
  },
  "geometry": {"coordinates":[-1.634174,53.687729],"type":"Point"}
}
