{
  "type": "Feature",
  "properties": {
    "iso:country": "GB",
    "wof:name": "PA34 5AF",
    "wof:placetype": "postalcode"
  },
  "geometry": {"coordinates":[-5.480199,56.420014],"type":"Point"}
}
