{
  "type": "Feature",
  "properties": {
    "iso:country":"GB",
    "wof:name":"PA34 5AF",
    "wof:placetype":"postalcode"
},
  "geometry": {"coordinates":[-5.48019858692903,56.42001399195563],"type":"Point"}
}