{
  "type": "Feature",
  "properties": {
    "iso:country":"GB",
    "wof:name":"HG4 1QN",
    "wof:placetype":"postalcode"
},
  "geometry": {"coordinates":[-1.51832471410103,54.1321925108446],"type":"Point"}
}