{
  "type": "Feature",
  "properties": {
    "date:inception_lower":"1980-01-01",
    "date:inception_upper":"1980-01-31",
    "iso:country":"GB",
    "wof:name":"HG4 1QN",
    "wof:placetype":"postalcode"
},
  "geometry": {"coordinates":[-1.518325,54.132193],"type":"Point"}
}