{
  "type": "Feature",
  "properties": {
    "date:inception_lower": "1980-01-01",
    "date:inception_upper": "1980-01-01",
    "iso:country": "GB",
    "wof:name": "NG17 2BT",
    "wof:placetype": "postalcode"
  },
  "geometry": {"coordinates":[-1.268635,53.134389],"type":"Point"}
}
