{
  "type": "Feature",
  "properties": {
    "date:inception_lower": "1980-01-01",
    "date:inception_upper": "1980-01-01",
    "iso:country": "GB",
    "wof:name": "LA6 2QF",
    "wof:placetype": "postalcode"
  },
  "geometry": {"coordinates":[-2.615511,54.190754],"type":"Point"}
}
