{
  "type": "Feature",
  "properties": {
    "iso:country":"GB",
    "wof:name":"M30 9PL",
    "wof:placetype":"postalcode"
},
  "geometry": {"coordinates":[-2.35360999217096,53.48922087880321],"type":"Point"}
}