{
  "type": "Feature",
  "properties": {
    "iso:country": "GB",
    "wof:name": "WF10 3TS",
    "wof:placetype": "postalcode"
  },
  "geometry": {"coordinates":[-1.312156,53.713916],"type":"Point"}
}
