{
  "type": "Feature",
  "properties": {
    "iso:country":"GB",
    "wof:name":"WF10 3TS",
    "wof:placetype":"postalcode"
},
  "geometry": {"coordinates":[-1.31215576486453,53.71391626855836],"type":"Point"}
}