{
  "type": "Feature",
  "properties": {
    "iso:country":"GB",
    "wof:name":"G64 1UH",
    "wof:placetype":"postalcode"
},
  "geometry": {"coordinates":[-4.20008575567323,55.91122514508145],"type":"Point"}
}