{
  "type": "Feature",
  "properties": {
    "iso:country": "GB",
    "wof:name": "G83 0QU",
    "wof:placetype": "postalcode"
  },
  "geometry": {"coordinates":[-4.578091,55.995648],"type":"Point"}
}
