{
  "type": "Feature",
  "properties": {
    "iso:country": "GB",
    "wof:name": "NE4 6TG",
    "wof:placetype": "postalcode"
  },
  "geometry": {"coordinates":[-1.640848,54.97044],"type":"Point"}
}
