{
  "type": "Feature",
  "properties": {
    "iso:country":"GB",
    "wof:name":"EX39 4AJ",
    "wof:placetype":"postalcode"
},
  "geometry": {"coordinates":[-4.19729197158358,51.01940388401168],"type":"Point"}
}