{
  "type": "Feature",
  "properties": {
    "iso:country":"GB",
    "wof:name":"GL11 5RH",
    "wof:placetype":"postalcode"
},
  "geometry": {"coordinates":[-2.36498981868642,51.69441073709294],"type":"Point"}
}