{
  "type": "Feature",
  "properties": {
    "iso:country": "GB",
    "wof:name": "B90 4XJ",
    "wof:placetype": "postalcode"
  },
  "geometry": {"coordinates":[-1.794267,52.386791],"type":"Point"}
}
