{
  "type": "Feature",
  "properties": {
    "date:inception_lower": "1987-04-01",
    "date:inception_upper": "1987-04-01",
    "iso:country": "GB",
    "wof:name": "B90 4XJ",
    "wof:placetype": "postalcode"
  },
  "geometry": {"coordinates":[-1.794267,52.386791],"type":"Point"}
}
