{
  "type": "Feature",
  "properties": {
    "iso:country":"GB",
    "wof:name":"B90 4XJ",
    "wof:placetype":"postalcode"
},
  "geometry": {"coordinates":[-1.79426738074616,52.38679082606749],"type":"Point"}
}