{
  "type": "Feature",
  "properties": {
    "date:inception_lower":"1988-03-01",
    "date:inception_upper":"1988-03-31",
    "iso:country":"GB",
    "wof:name":"AL3 6XT",
    "wof:placetype":"postalcode"
},
  "geometry": {"coordinates":[-0.325556,51.772885],"type":"Point"}
}