{
  "type": "Feature",
  "properties": {
    "date:inception_lower": "2022-08-01",
    "date:inception_upper": "2022-08-01",
    "iso:country": "GB",
    "wof:name": "SA16 0FH",
    "wof:placetype": "postalcode"
  },
  "geometry": {"coordinates":[-4.244314,51.683996],"type":"Point"}
}
