{
  "type": "Feature",
  "properties": {
    "iso:country":"GB",
    "wof:name":"SS7 1HW",
    "wof:placetype":"postalcode"
},
  "geometry": {"coordinates":[0.56904388263896,51.55859518716932],"type":"Point"}
}