{
  "type": "Feature",
  "properties": {
    "iso:country":"GB",
    "wof:name":"PA34 5AX",
    "wof:placetype":"postalcode"
},
  "geometry": {"coordinates":[-5.47576652756189,56.42050699066418],"type":"Point"}
}