{
  "type": "Feature",
  "properties": {
    "iso:country": "GB",
    "wof:name": "TS27 3AP",
    "wof:placetype": "postalcode"
  },
  "geometry": {"coordinates":[-1.274146,54.708256],"type":"Point"}
}
