{
  "type": "Feature",
  "properties": {
    "iso:country": "GB",
    "wof:name": "L36 0SY",
    "wof:placetype": "postalcode"
  },
  "geometry": {"coordinates":[-2.834309,53.403577],"type":"Point"}
}
