{
  "type": "Feature",
  "properties": {
    "date:inception_lower": "1980-01-01",
    "date:inception_upper": "1980-01-01",
    "iso:country": "GB",
    "wof:name": "SE18 3LJ",
    "wof:placetype": "postalcode"
  },
  "geometry": {"coordinates":[0.065283,51.475723],"type":"Point"}
}
