{
  "type": "Feature",
  "properties": {
    "iso:country":"GB",
    "wof:name":"YO43 3JR",
    "wof:placetype":"postalcode"
},
  "geometry": {"coordinates":[-0.66763064335883,53.86132749941559],"type":"Point"}
}