{
  "type": "Feature",
  "properties": {
    "iso:country":"GB",
    "wof:name":"DN6 9GL",
    "wof:placetype":"postalcode"
},
  "geometry": {"coordinates":[-1.18846640172916,53.60225229681623],"type":"Point"}
}