{
  "type": "Feature",
  "properties": {
    "iso:country": "GB",
    "wof:name": "DN6 9GL",
    "wof:placetype": "postalcode"
  },
  "geometry": {"coordinates":[-1.188466,53.602252],"type":"Point"}
}
