{
  "type": "Feature",
  "properties": {
    "iso:country": "GB",
    "wof:name": "SP10 3JZ",
    "wof:placetype": "postalcode"
  },
  "geometry": {"coordinates":[-1.493033,51.214309],"type":"Point"}
}
