{
  "type": "Feature",
  "properties": {
    "iso:country":"GB",
    "wof:name":"CV10 9PF",
    "wof:placetype":"postalcode"
},
  "geometry": {"coordinates":[-1.55407243977545,52.51861596391373],"type":"Point"}
}