{
  "type": "Feature",
  "properties": {
    "date:inception_lower":"1980-01-01",
    "date:inception_upper":"1980-01-31",
    "iso:country":"GB",
    "wof:name":"CV10 9PF",
    "wof:placetype":"postalcode"
},
  "geometry": {"coordinates":[-1.554072,52.518616],"type":"Point"}
}