{
  "type": "Feature",
  "properties": {
    "iso:country":"GB",
    "wof:name":"IP8 4EE",
    "wof:placetype":"postalcode"
},
  "geometry": {"coordinates":[1.09636011403148,52.07759566543254],"type":"Point"}
}