{
  "type": "Feature",
  "properties": {
    "iso:country":"GB",
    "wof:name":"NR1 2LY",
    "wof:placetype":"postalcode"
},
  "geometry": {"coordinates":[1.30083679629787,52.60755977380129],"type":"Point"}
}