{
  "type": "Feature",
  "properties": {
    "date:inception_lower": "1980-01-01",
    "date:inception_upper": "1980-01-01",
    "iso:country": "GB",
    "wof:name": "NR1 2LY",
    "wof:placetype": "postalcode"
  },
  "geometry": {"coordinates":[1.30086,52.607584],"type":"Point"}
}
