{
  "type": "Feature",
  "properties": {
    "iso:country":"GB",
    "wof:name":"W7 3EJ",
    "wof:placetype":"postalcode"
},
  "geometry": {"coordinates":[-0.3420795332207,51.51318660242191],"type":"Point"}
}