{
  "type": "Feature",
  "properties": {
    "date:inception_lower":"2017-08-01",
    "date:inception_upper":"2017-08-31",
    "iso:country":"GB",
    "wof:name":"NR15 2ZU",
    "wof:placetype":"postalcode"
},
  "geometry": {"coordinates":[1.224217,52.491916],"type":"Point"}
}