{
  "type": "Feature",
  "properties": {
    "iso:country": "GB",
    "wof:name": "NR15 2ZU",
    "wof:placetype": "postalcode"
  },
  "geometry": {"coordinates":[1.224217,52.491916],"type":"Point"}
}
