{
  "type": "Feature",
  "properties": {
    "iso:country": "GB",
    "wof:name": "NR6 5EB",
    "wof:placetype": "postalcode"
  },
  "geometry": {"coordinates":[1.251722,52.638651],"type":"Point"}
}
