{
  "type": "Feature",
  "properties": {
    "iso:country":"GB",
    "wof:name":"LS5 3EL",
    "wof:placetype":"postalcode"
},
  "geometry": {"coordinates":[-1.60509764538317,53.82403070701692],"type":"Point"}
}