{
  "type": "Feature",
  "properties": {
    "iso:country":"GB",
    "wof:name":"CH66 4PR",
    "wof:placetype":"postalcode"
},
  "geometry": {"coordinates":[-2.95272735882693,53.28551013873038],"type":"Point"}
}