{
  "type": "Feature",
  "properties": {
    "date:inception_lower":"1980-01-01",
    "date:inception_upper":"1980-01-31",
    "iso:country":"GB",
    "wof:name":"WF7 5JB",
    "wof:placetype":"postalcode"
},
  "geometry": {"coordinates":[-1.362268,53.672452],"type":"Point"}
}