{
  "type": "Feature",
  "properties": {
    "iso:country":"GB",
    "wof:name":"WF7 5JB",
    "wof:placetype":"postalcode"
},
  "geometry": {"coordinates":[-1.36226824188343,53.67245179677559],"type":"Point"}
}