{
  "type": "Feature",
  "properties": {
    "iso:country":"GB",
    "wof:name":"SE28 8ET",
    "wof:placetype":"postalcode"
},
  "geometry": {"coordinates":[0.12391095274902,51.50894694848688],"type":"Point"}
}