{
  "type": "Feature",
  "properties": {
    "iso:country": "GB",
    "wof:name": "SE28 8ET",
    "wof:placetype": "postalcode"
  },
  "geometry": {"coordinates":[0.123911,51.508947],"type":"Point"}
}
