{
  "type": "Feature",
  "properties": {
    "iso:country": "GB",
    "wof:name": "UB8 2JD",
    "wof:placetype": "postalcode"
  },
  "geometry": {"coordinates":[-0.483422,51.529433],"type":"Point"}
}
