{
  "type": "Feature",
  "properties": {
    "iso:country":"GB",
    "wof:name":"ST14 8XH",
    "wof:placetype":"postalcode"
},
  "geometry": {"coordinates":[-1.85905530352031,52.89617119534073],"type":"Point"}
}