{
  "type": "Feature",
  "properties": {
    "iso:country":"GB",
    "wof:name":"OX7 5SB",
    "wof:placetype":"postalcode"
},
  "geometry": {"coordinates":[-1.52131048663162,51.97950520379336],"type":"Point"}
}