{
  "type": "Feature",
  "properties": {
    "iso:country":"GB",
    "wof:name":"TF12 5EU",
    "wof:placetype":"postalcode"
},
  "geometry": {"coordinates":[-2.48108533180476,52.6123758193664],"type":"Point"}
}