{
  "type": "Feature",
  "properties": {
    "date:inception_lower":"1980-01-01",
    "date:inception_upper":"1980-01-31",
    "iso:country":"GB",
    "wof:name":"CW12 2NY",
    "wof:placetype":"postalcode"
},
  "geometry": {"coordinates":[-2.154424,53.20208],"type":"Point"}
}