{
  "type": "Feature",
  "properties": {
    "iso:country": "GB",
    "wof:name": "CW12 2NY",
    "wof:placetype": "postalcode"
  },
  "geometry": {"coordinates":[-2.154424,53.20208],"type":"Point"}
}
