{
  "type": "Feature",
  "properties": {
    "iso:country":"GB",
    "wof:name":"YO23 3FS",
    "wof:placetype":"postalcode"
},
  "geometry": {"coordinates":[-1.15363211240051,53.92150033686254],"type":"Point"}
}