{
  "type": "Feature",
  "properties": {
    "date:inception_lower": "2017-10-01",
    "date:inception_upper": "2017-10-01",
    "iso:country": "GB",
    "wof:name": "SO16 0BH",
    "wof:placetype": "postalcode"
  },
  "geometry": {"coordinates":[-1.463732,50.941257],"type":"Point"}
}
