{
  "type": "Feature",
  "properties": {
    "date:inception_lower": "1980-01-01",
    "date:inception_upper": "1980-01-01",
    "iso:country": "GB",
    "wof:name": "PO2 7JJ",
    "wof:placetype": "postalcode"
  },
  "geometry": {"coordinates":[-1.068616,50.812192],"type":"Point"}
}
