{
  "type": "Feature",
  "properties": {
    "iso:country":"GB",
    "wof:name":"WN7 1JY",
    "wof:placetype":"postalcode"
},
  "geometry": {"coordinates":[-2.50627720286633,53.5000778166291],"type":"Point"}
}