{
  "type": "Feature",
  "properties": {
    "iso:country":"GB",
    "wof:name":"BN1 2HQ",
    "wof:placetype":"postalcode"
},
  "geometry": {"coordinates":[-0.15136126621015,50.82328150743265],"type":"Point"}
}