{
  "type": "Feature",
  "properties": {
    "date:inception_lower": "1980-01-01",
    "date:inception_upper": "1980-01-01",
    "iso:country": "GB",
    "wof:name": "BN1 2HQ",
    "wof:placetype": "postalcode"
  },
  "geometry": {"coordinates":[-0.1513,50.823401],"type":"Point"}
}
