{
  "type": "Feature",
  "properties": {
    "date:inception_lower": "1984-02-01",
    "date:inception_upper": "1984-02-01",
    "iso:country": "GB",
    "wof:name": "L25 6JZ",
    "wof:placetype": "postalcode"
  },
  "geometry": {"coordinates":[-2.867674,53.38004],"type":"Point"}
}
