{
  "type": "Feature",
  "properties": {
    "iso:country":"GB",
    "wof:name":"M33 2SA",
    "wof:placetype":"postalcode"
},
  "geometry": {"coordinates":[-2.29312178550653,53.41831250993533],"type":"Point"}
}