{
  "type": "Feature",
  "properties": {
    "date:inception_lower": "1980-01-01",
    "date:inception_upper": "1980-01-01",
    "iso:country": "GB",
    "wof:name": "SE26 4ER",
    "wof:placetype": "postalcode"
  },
  "geometry": {"coordinates":[-0.043275,51.427432],"type":"Point"}
}
