{
  "type": "Feature",
  "properties": {
    "iso:country":"GB",
    "wof:name":"BL1 8DY",
    "wof:placetype":"postalcode"
},
  "geometry": {"coordinates":[-2.43201873719064,53.59510723644078],"type":"Point"}
}