{
  "type": "Feature",
  "properties": {
    "iso:country":"GB",
    "wof:name":"HR2 7TN",
    "wof:placetype":"postalcode"
},
  "geometry": {"coordinates":[-2.74048944475344,52.03822433760146],"type":"Point"}
}