{
  "type": "Feature",
  "properties": {
    "iso:country": "GB",
    "wof:name": "NW9 4BR",
    "wof:placetype": "postalcode"
  },
  "geometry": {"coordinates":[-0.245639,51.597574],"type":"Point"}
}
