{
  "type": "Feature",
  "properties": {
    "iso:country":"GB",
    "wof:name":"LL53 8PU",
    "wof:placetype":"postalcode"
},
  "geometry": {"coordinates":[-4.58632603840323,52.86279431877491],"type":"Point"}
}