{
  "type": "Feature",
  "properties": {
    "iso:country":"GB",
    "wof:name":"BR6 0HY",
    "wof:placetype":"postalcode"
},
  "geometry": {"coordinates":[0.10322397219981,51.38164766327017],"type":"Point"}
}