{
  "type": "Feature",
  "properties": {
    "date:inception_lower": "2015-06-01",
    "date:inception_upper": "2015-06-01",
    "iso:country": "GB",
    "wof:name": "NG7 3HB",
    "wof:placetype": "postalcode"
  },
  "geometry": {"coordinates":[-1.170139,52.956017],"type":"Point"}
}
