{
  "type": "Feature",
  "properties": {
    "iso:country":"GB",
    "wof:name":"NR9 4JD",
    "wof:placetype":"postalcode"
},
  "geometry": {"coordinates":[0.99026961515098,52.5808850237474],"type":"Point"}
}