{
  "type": "Feature",
  "properties": {
    "iso:country": "GB",
    "wof:name": "KT9 1ET",
    "wof:placetype": "postalcode"
  },
  "geometry": {"coordinates":[-0.303956,51.374022],"type":"Point"}
}
