{
  "type": "Feature",
  "properties": {
    "date:inception_lower":"2004-11-01",
    "date:inception_upper":"2004-11-30",
    "iso:country":"GB",
    "wof:name":"KT9 1ET",
    "wof:placetype":"postalcode"
},
  "geometry": {"coordinates":[-0.303956,51.374022],"type":"Point"}
}