{
  "type": "Feature",
  "properties": {
    "iso:country":"GB",
    "wof:name":"NR35 2PL",
    "wof:placetype":"postalcode"
},
  "geometry": {"coordinates":[1.48709342846028,52.48229779022257],"type":"Point"}
}