{
  "type": "Feature",
  "properties": {
    "iso:country":"GB",
    "wof:name":"B68 0JL",
    "wof:placetype":"postalcode"
},
  "geometry": {"coordinates":[-2.00797863302156,52.46814914688024],"type":"Point"}
}