{
  "type": "Feature",
  "properties": {
    "date:inception_lower": "1980-01-01",
    "date:inception_upper": "1980-01-01",
    "iso:country": "GB",
    "wof:name": "B68 0JL",
    "wof:placetype": "postalcode"
  },
  "geometry": {"coordinates":[-2.007979,52.468149],"type":"Point"}
}
