{
  "type": "Feature",
  "properties": {
    "iso:country":"GB",
    "wof:name":"ME18 6AX",
    "wof:placetype":"postalcode"
},
  "geometry": {"coordinates":[0.44435788266422,51.20881572274894],"type":"Point"}
}