{
  "type": "Feature",
  "properties": {
    "iso:country":"GB",
    "wof:name":"B36 8PF",
    "wof:placetype":"postalcode"
},
  "geometry": {"coordinates":[-1.79539784030493,52.51098991260585],"type":"Point"}
}