{
  "type": "Feature",
  "properties": {
    "iso:country":"GB",
    "wof:name":"PA2 8BL",
    "wof:placetype":"postalcode"
},
  "geometry": {"coordinates":[-4.42655817261522,55.82464914644522],"type":"Point"}
}