{
  "type": "Feature",
  "properties": {
    "iso:country":"GB",
    "wof:name":"SW2 3LS",
    "wof:placetype":"postalcode"
},
  "geometry": {"coordinates":[-0.12368669050604,51.44711014122083],"type":"Point"}
}