{
  "type": "Feature",
  "properties": {
    "iso:country":"GB",
    "wof:name":"SW14 7DA",
    "wof:placetype":"postalcode"
},
  "geometry": {"coordinates":[-0.27204772694392,51.47103564503976],"type":"Point"}
}