{
  "type": "Feature",
  "properties": {
    "date:inception_lower": "2015-06-01",
    "date:inception_upper": "2015-06-01",
    "iso:country": "GB",
    "wof:name": "CF62 5AZ",
    "wof:placetype": "postalcode"
  },
  "geometry": {"coordinates":[-3.279926,51.395281],"type":"Point"}
}
