{
  "type": "Feature",
  "properties": {
    "iso:country":"GB",
    "wof:name":"CF62 5AZ",
    "wof:placetype":"postalcode"
},
  "geometry": {"coordinates":[-3.2799564906642,51.39535224141022],"type":"Point"}
}