{
  "type": "Feature",
  "properties": {
    "iso:country": "GB",
    "wof:name": "FY4 4TB",
    "wof:placetype": "postalcode"
  },
  "geometry": {"coordinates":[-2.99069,53.797118],"type":"Point"}
}
