{
  "type": "Feature",
  "properties": {
    "iso:country":"GB",
    "wof:name":"FY4 4TB",
    "wof:placetype":"postalcode"
},
  "geometry": {"coordinates":[-2.99068981178933,53.79711831088985],"type":"Point"}
}