{
  "type": "Feature",
  "properties": {
    "iso:country": "GB",
    "wof:name": "YO23 3YD",
    "wof:placetype": "postalcode"
  },
  "geometry": {"coordinates":[-1.133631,53.917071],"type":"Point"}
}
