{
  "type": "Feature",
  "properties": {
    "iso:country": "GB",
    "wof:name": "YO23 3YD",
    "wof:placetype": "postalcode"
  },
  "geometry": {"coordinates":[-1.133624,53.917079],"type":"Point"}
}
