{
  "type": "Feature",
  "properties": {
    "iso:country":"GB",
    "wof:name":"YO23 3YD",
    "wof:placetype":"postalcode"
},
  "geometry": {"coordinates":[-1.13362388722231,53.91707937446431],"type":"Point"}
}