{
  "type": "Feature",
  "properties": {
    "date:inception_lower":"1980-01-01",
    "date:inception_upper":"1980-01-31",
    "iso:country":"GB",
    "wof:name":"UB4 0BN",
    "wof:placetype":"postalcode"
},
  "geometry": {"coordinates":[-0.408519,51.522218],"type":"Point"}
}