{
  "type": "Feature",
  "properties": {
    "iso:country":"GB",
    "wof:name":"UB4 0BN",
    "wof:placetype":"postalcode"
},
  "geometry": {"coordinates":[-0.4085193838243,51.52221781814546],"type":"Point"}
}