{
  "type": "Feature",
  "properties": {
    "iso:country":"GB",
    "wof:name":"IP7 5JH",
    "wof:placetype":"postalcode"
},
  "geometry": {"coordinates":[0.96653618841049,52.03989952883482],"type":"Point"}
}