{
  "type": "Feature",
  "properties": {
    "iso:country": "GB",
    "wof:name": "IP7 5JH",
    "wof:placetype": "postalcode"
  },
  "geometry": {"coordinates":[0.966582,52.039913],"type":"Point"}
}
