{
  "type": "Feature",
  "properties": {
    "iso:country":"GB",
    "wof:name":"FK6 5AU",
    "wof:placetype":"postalcode"
},
  "geometry": {"coordinates":[-3.91251902447154,56.01765769735731],"type":"Point"}
}