{
  "type": "Feature",
  "properties": {
    "iso:country":"GB",
    "wof:name":"ME12 3AP",
    "wof:placetype":"postalcode"
},
  "geometry": {"coordinates":[0.7769324290855,51.42481339770384],"type":"Point"}
}