{
  "type": "Feature",
  "properties": {
    "date:inception_lower": "1980-01-01",
    "date:inception_upper": "1980-01-01",
    "iso:country": "GB",
    "wof:name": "IP7 7NW",
    "wof:placetype": "postalcode"
  },
  "geometry": {"coordinates":[0.889431,52.119843],"type":"Point"}
}
