{
  "type": "Feature",
  "properties": {
    "iso:country":"GB",
    "wof:name":"IP7 7NW",
    "wof:placetype":"postalcode"
},
  "geometry": {"coordinates":[0.88943079978814,52.11984325811044],"type":"Point"}
}