{
  "type": "Feature",
  "properties": {
    "date:inception_lower": "1980-01-01",
    "date:inception_upper": "1980-01-01",
    "iso:country": "GB",
    "wof:name": "CT5 2PE",
    "wof:placetype": "postalcode"
  },
  "geometry": {"coordinates":[1.072834,51.365158],"type":"Point"}
}
