{
  "type": "Feature",
  "properties": {
    "iso:country":"GB",
    "wof:name":"CT5 2PE",
    "wof:placetype":"postalcode"
},
  "geometry": {"coordinates":[1.07283428180653,51.36515759936667],"type":"Point"}
}