{
  "type": "Feature",
  "properties": {
    "iso:country":"GB",
    "wof:name":"OL9 7AP",
    "wof:placetype":"postalcode"
},
  "geometry": {"coordinates":[-2.13229133770569,53.53397500951318],"type":"Point"}
}