{
  "type": "Feature",
  "properties": {
    "iso:country":"GB",
    "wof:name":"LS13 4UB",
    "wof:placetype":"postalcode"
},
  "geometry": {"coordinates":[-1.63299829811933,53.80207170892743],"type":"Point"}
}