{
  "type": "Feature",
  "properties": {
    "iso:country": "GB",
    "wof:name": "LN13 9EY",
    "wof:placetype": "postalcode"
  },
  "geometry": {"coordinates":[0.174631,53.261139],"type":"Point"}
}
