{
  "type": "Feature",
  "properties": {
    "iso:country":"GB",
    "wof:name":"YO25 8BW",
    "wof:placetype":"postalcode"
},
  "geometry": {"coordinates":[-0.3319884489351,53.97921056274124],"type":"Point"}
}