{
  "type": "Feature",
  "properties": {
    "iso:country": "GB",
    "wof:name": "YO25 8BW",
    "wof:placetype": "postalcode"
  },
  "geometry": {"coordinates":[-0.331988,53.979211],"type":"Point"}
}
