{
  "type": "Feature",
  "properties": {
    "date:inception_lower":"1980-01-01",
    "date:inception_upper":"1980-01-31",
    "iso:country":"GB",
    "wof:name":"HA2 9TA",
    "wof:placetype":"postalcode"
},
  "geometry": {"coordinates":[-0.377398,51.575754],"type":"Point"}
}