{
  "type": "Feature",
  "properties": {
    "iso:country":"GB",
    "wof:name":"HA2 9TA",
    "wof:placetype":"postalcode"
},
  "geometry": {"coordinates":[-0.37739784191857,51.57575368610516],"type":"Point"}
}