{
  "type": "Feature",
  "properties": {
    "date:inception_lower": "1994-12-01",
    "date:inception_upper": "1994-12-01",
    "iso:country": "GB",
    "wof:name": "SO50 4HT",
    "wof:placetype": "postalcode"
  },
  "geometry": {"coordinates":[-1.350942,50.982563],"type":"Point"}
}
