{
  "type": "Feature",
  "properties": {
    "iso:country":"GB",
    "wof:name":"DL1 2UF",
    "wof:placetype":"postalcode"
},
  "geometry": {"coordinates":[-1.5162708272088,54.53492998869051],"type":"Point"}
}