{
  "type": "Feature",
  "properties": {
    "iso:country": "GB",
    "wof:name": "SA44 5SW",
    "wof:placetype": "postalcode"
  },
  "geometry": {"coordinates":[-4.433639,52.109789],"type":"Point"}
}
