{
  "type": "Feature",
  "properties": {
    "iso:country":"GB",
    "wof:name":"SA44 5SW",
    "wof:placetype":"postalcode"
},
  "geometry": {"coordinates":[-4.43361823261625,52.10977580440434],"type":"Point"}
}