{
  "type": "Feature",
  "properties": {
    "date:inception_lower":"1980-01-01",
    "date:inception_upper":"1980-01-31",
    "iso:country":"GB",
    "wof:name":"SA44 5SW",
    "wof:placetype":"postalcode"
},
  "geometry": {"coordinates":[-4.433639,52.109789],"type":"Point"}
}