{
  "type": "Feature",
  "properties": {
    "iso:country":"GB",
    "wof:name":"CB7 5ES",
    "wof:placetype":"postalcode"
},
  "geometry": {"coordinates":[0.33370675806043,52.3422865193732],"type":"Point"}
}