{
  "type": "Feature",
  "properties": {
    "date:inception_lower": "1980-01-01",
    "date:inception_upper": "1980-01-01",
    "iso:country": "GB",
    "wof:name": "CB7 5ES",
    "wof:placetype": "postalcode"
  },
  "geometry": {"coordinates":[0.333707,52.342287],"type":"Point"}
}
