{
  "type": "Feature",
  "properties": {
    "iso:country": "GB",
    "wof:name": "CB7 5ES",
    "wof:placetype": "postalcode"
  },
  "geometry": {"coordinates":[0.333707,52.342287],"type":"Point"}
}
