{
  "type": "Feature",
  "properties": {
    "iso:country":"GB",
    "wof:name":"ST4 4LG",
    "wof:placetype":"postalcode"
},
  "geometry": {"coordinates":[-2.17119209178109,52.9919562822631],"type":"Point"}
}