{
  "type": "Feature",
  "properties": {
    "date:inception_lower": "2018-01-01",
    "date:inception_upper": "2018-01-01",
    "iso:country": "GB",
    "wof:name": "GL1 1AJ",
    "wof:placetype": "postalcode"
  },
  "geometry": {"coordinates":[-2.221328,51.861614],"type":"Point"}
}
