{
  "type": "Feature",
  "properties": {
    "iso:country":"GB",
    "wof:name":"LL11 3EU",
    "wof:placetype":"postalcode"
},
  "geometry": {"coordinates":[-3.05882745411193,53.05298680655649],"type":"Point"}
}