{
  "type": "Feature",
  "properties": {
    "date:inception_lower": "1987-04-01",
    "date:inception_upper": "1987-04-01",
    "iso:country": "GB",
    "wof:name": "W10 5GJ",
    "wof:placetype": "postalcode"
  },
  "geometry": {"coordinates":[-0.207949,51.521627],"type":"Point"}
}
