{
  "type": "Feature",
  "properties": {
    "iso:country":"GB",
    "wof:name":"W10 5GJ",
    "wof:placetype":"postalcode"
},
  "geometry": {"coordinates":[-0.20780807084725,51.52155315516213],"type":"Point"}
}