{
  "type": "Feature",
  "properties": {
    "date:inception_lower":"1995-01-01",
    "date:inception_upper":"1995-01-31",
    "iso:country":"GB",
    "wof:name":"LD3 7SB",
    "wof:placetype":"postalcode"
},
  "geometry": {"coordinates":[-3.231092,51.890699],"type":"Point"}
}