{
  "type": "Feature",
  "properties": {
    "iso:country": "GB",
    "wof:name": "LD3 7SB",
    "wof:placetype": "postalcode"
  },
  "geometry": {"coordinates":[-3.231092,51.890699],"type":"Point"}
}
