{
  "type": "Feature",
  "properties": {
    "iso:country":"GB",
    "wof:name":"CF31 1TS",
    "wof:placetype":"postalcode"
},
  "geometry": {"coordinates":[-3.56957017719206,51.50573546529993],"type":"Point"}
}