{
  "type": "Feature",
  "properties": {
    "iso:country":"GB",
    "wof:name":"G40 2RZ",
    "wof:placetype":"postalcode"
},
  "geometry": {"coordinates":[-4.22863919477479,55.85277892816598],"type":"Point"}
}