{
  "type": "Feature",
  "properties": {
    "date:inception_lower": "1980-01-01",
    "date:inception_upper": "1980-01-01",
    "iso:country": "GB",
    "wof:name": "WA4 6UH",
    "wof:placetype": "postalcode"
  },
  "geometry": {"coordinates":[-2.641599,53.35356],"type":"Point"}
}
