{
  "type": "Feature",
  "properties": {
    "iso:country":"GB",
    "wof:name":"RH19 1AT",
    "wof:placetype":"postalcode"
},
  "geometry": {"coordinates":[-0.01037672965139,51.12574839007306],"type":"Point"}
}