{
  "type": "Feature",
  "properties": {
    "date:inception_lower": "2003-07-01",
    "date:inception_upper": "2003-07-01",
    "iso:country": "GB",
    "wof:name": "RH19 1AT",
    "wof:placetype": "postalcode"
  },
  "geometry": {"coordinates":[-0.010377,51.125748],"type":"Point"}
}
