{
  "type": "Feature",
  "properties": {
    "iso:country":"GB",
    "wof:name":"PR7 5AN",
    "wof:placetype":"postalcode"
},
  "geometry": {"coordinates":[-2.66091764860887,53.62479280034096],"type":"Point"}
}