{
  "type": "Feature",
  "properties": {
    "iso:country":"GB",
    "wof:name":"PE36 5LF",
    "wof:placetype":"postalcode"
},
  "geometry": {"coordinates":[0.5442784381727,52.93087383495479],"type":"Point"}
}