{
  "type": "Feature",
  "properties": {
    "iso:country":"GB",
    "wof:name":"PO30 5DL",
    "wof:placetype":"postalcode"
},
  "geometry": {"coordinates":[-1.30078593832988,50.69980550933735],"type":"Point"}
}