{
  "type": "Feature",
  "properties": {
    "date:inception_lower": "1980-01-01",
    "date:inception_upper": "1980-01-01",
    "iso:country": "GB",
    "wof:name": "PO30 5DL",
    "wof:placetype": "postalcode"
  },
  "geometry": {"coordinates":[-1.300786,50.699806],"type":"Point"}
}
