{
  "type": "Feature",
  "properties": {
    "iso:country":"GB",
    "wof:name":"PO11 9PT",
    "wof:placetype":"postalcode"
},
  "geometry": {"coordinates":[-0.95932984962035,50.7811981820112],"type":"Point"}
}