{
  "type": "Feature",
  "properties": {
    "iso:country": "GB",
    "wof:name": "RH2 9JE",
    "wof:placetype": "postalcode"
  },
  "geometry": {"coordinates":[-0.217189,51.243985],"type":"Point"}
}
