{
  "type": "Feature",
  "properties": {
    "iso:country":"GB",
    "wof:name":"RH2 9JE",
    "wof:placetype":"postalcode"
},
  "geometry": {"coordinates":[-0.21718425191587,51.24401346085133],"type":"Point"}
}