{
  "type": "Feature",
  "properties": {
    "iso:country": "GB",
    "wof:name": "GU15 1AS",
    "wof:placetype": "postalcode"
  },
  "geometry": {"coordinates":[-0.704718,51.32934],"type":"Point"}
}
