{
  "type": "Feature",
  "properties": {
    "date:inception_lower": "2016-08-01",
    "date:inception_upper": "2016-08-01",
    "iso:country": "GB",
    "wof:name": "HP13 5DW",
    "wof:placetype": "postalcode"
  },
  "geometry": {"coordinates":[-0.762637,51.639275],"type":"Point"}
}
