{
  "type": "Feature",
  "properties": {
    "iso:country":"GB",
    "wof:name":"NE48 3NR",
    "wof:placetype":"postalcode"
},
  "geometry": {"coordinates":[-2.20357794241573,55.08597399337378],"type":"Point"}
}