{
  "type": "Feature",
  "properties": {
    "date:inception_lower": "1980-01-01",
    "date:inception_upper": "1980-01-01",
    "iso:country": "GB",
    "wof:name": "NE48 3NR",
    "wof:placetype": "postalcode"
  },
  "geometry": {"coordinates":[-2.203587,55.085979],"type":"Point"}
}
