{
  "type": "Feature",
  "properties": {
    "iso:country": "GB",
    "wof:name": "NE48 3NR",
    "wof:placetype": "postalcode"
  },
  "geometry": {"coordinates":[-2.203508,55.085916],"type":"Point"}
}
