{
  "type": "Feature",
  "properties": {
    "iso:country":"GB",
    "wof:name":"IG10 2BQ",
    "wof:placetype":"postalcode"
},
  "geometry": {"coordinates":[0.08873419446942,51.65374963112659],"type":"Point"}
}