{
  "type": "Feature",
  "properties": {
    "date:inception_lower":"2002-10-01",
    "date:inception_upper":"2002-10-31",
    "iso:country":"GB",
    "wof:name":"IG10 2BQ",
    "wof:placetype":"postalcode"
},
  "geometry": {"coordinates":[0.088734,51.65375],"type":"Point"}
}