{
  "type": "Feature",
  "properties": {
    "iso:country": "GB",
    "wof:name": "IG10 2BQ",
    "wof:placetype": "postalcode"
  },
  "geometry": {"coordinates":[0.088734,51.65375],"type":"Point"}
}
