{
  "type": "Feature",
  "properties": {
    "date:inception_lower": "1994-12-01",
    "date:inception_upper": "1994-12-01",
    "iso:country": "GB",
    "wof:name": "DE14 2AQ",
    "wof:placetype": "postalcode"
  },
  "geometry": {"coordinates":[-1.630079,52.824411],"type":"Point"}
}
