{
  "type": "Feature",
  "properties": {
    "iso:country": "GB",
    "wof:name": "DE14 2AQ",
    "wof:placetype": "postalcode"
  },
  "geometry": {"coordinates":[-1.630079,52.824411],"type":"Point"}
}
