{
  "type": "Feature",
  "properties": {
    "iso:country": "GB",
    "wof:name": "SN15 5HJ",
    "wof:placetype": "postalcode"
  },
  "geometry": {"coordinates":[-2.079757,51.538404],"type":"Point"}
}
