{
  "type": "Feature",
  "properties": {
    "iso:country":"GB",
    "wof:name":"LS10 1LG",
    "wof:placetype":"postalcode"
},
  "geometry": {"coordinates":[-1.53233370475422,53.78967767311981],"type":"Point"}
}