{
  "type": "Feature",
  "properties": {
    "iso:country":"GB",
    "wof:name":"TS7 9RF",
    "wof:placetype":"postalcode"
},
  "geometry": {"coordinates":[-1.16979909095737,54.54945955455472],"type":"Point"}
}