{
  "type": "Feature",
  "properties": {
    "iso:country": "GB",
    "wof:name": "TS7 9RF",
    "wof:placetype": "postalcode"
  },
  "geometry": {"coordinates":[-1.169799,54.54946],"type":"Point"}
}
