{
  "type": "Feature",
  "properties": {
    "iso:country":"GB",
    "wof:name":"BN25 3NQ",
    "wof:placetype":"postalcode"
},
  "geometry": {"coordinates":[0.11189881674534,50.77646085920627],"type":"Point"}
}