{
  "type": "Feature",
  "properties": {
    "iso:country": "GB",
    "wof:name": "SY8 3HW",
    "wof:placetype": "postalcode"
  },
  "geometry": {"coordinates":[-2.626948,52.388317],"type":"Point"}
}
