{
  "type": "Feature",
  "properties": {
    "iso:country":"GB",
    "wof:name":"SY8 3HW",
    "wof:placetype":"postalcode"
},
  "geometry": {"coordinates":[-2.62694846477228,52.38831715298133],"type":"Point"}
}