{
  "type": "Feature",
  "properties": {
    "iso:country": "GB",
    "wof:name": "HX2 9ST",
    "wof:placetype": "postalcode"
  },
  "geometry": {"coordinates":[-1.88292,53.756548],"type":"Point"}
}
