{
  "type": "Feature",
  "properties": {
    "iso:country":"GB",
    "wof:name":"DD3 8LR",
    "wof:placetype":"postalcode"
},
  "geometry": {"coordinates":[-2.98506782636845,56.48617683929804],"type":"Point"}
}