{
  "type": "Feature",
  "properties": {
    "iso:country":"GB",
    "wof:name":"LL12 9RH",
    "wof:placetype":"postalcode"
},
  "geometry": {"coordinates":[-3.03331310990121,53.12518061936424],"type":"Point"}
}