{
  "type": "Feature",
  "properties": {
    "iso:country":"GB",
    "wof:name":"SE26 6ND",
    "wof:placetype":"postalcode"
},
  "geometry": {"coordinates":[-0.06440831491168,51.43623636767302],"type":"Point"}
}