{
  "type": "Feature",
  "properties": {
    "date:inception_lower": "2011-12-01",
    "date:inception_upper": "2011-12-01",
    "iso:country": "GB",
    "wof:name": "SN2 2BF",
    "wof:placetype": "postalcode"
  },
  "geometry": {"coordinates":[-1.812593,51.582286],"type":"Point"}
}
