{
  "type": "Feature",
  "properties": {
    "iso:country":"GB",
    "wof:name":"S64 8TX",
    "wof:placetype":"postalcode"
},
  "geometry": {"coordinates":[-1.30742549263026,53.48582514501743],"type":"Point"}
}