{
  "type": "Feature",
  "properties": {
    "iso:country":"GB",
    "wof:name":"CF5 1EG",
    "wof:placetype":"postalcode"
},
  "geometry": {"coordinates":[-3.21713489193016,51.48382867867568],"type":"Point"}
}