{
  "type": "Feature",
  "properties": {
    "date:inception_lower": "1980-01-01",
    "date:inception_upper": "1980-01-01",
    "iso:country": "GB",
    "wof:name": "SE18 7QG",
    "wof:placetype": "postalcode"
  },
  "geometry": {"coordinates":[0.08539,51.488479],"type":"Point"}
}
