{
  "type": "Feature",
  "properties": {
    "iso:country":"GB",
    "wof:name":"SE18 7QG",
    "wof:placetype":"postalcode"
},
  "geometry": {"coordinates":[0.08535997480983,51.48840681215908],"type":"Point"}
}