{
  "type": "Feature",
  "properties": {
    "iso:country": "GB",
    "wof:name": "NW3 4NU",
    "wof:placetype": "postalcode"
  },
  "geometry": {"coordinates":[-0.170901,51.545425],"type":"Point"}
}
