{
  "type": "Feature",
  "properties": {
    "iso:country":"GB",
    "wof:name":"SW19 4LT",
    "wof:placetype":"postalcode"
},
  "geometry": {"coordinates":[-0.21631437516776,51.4173969921521],"type":"Point"}
}