{
  "type": "Feature",
  "properties": {
    "date:inception_lower": "1980-01-01",
    "date:inception_upper": "1980-01-01",
    "iso:country": "GB",
    "wof:name": "SW19 4LT",
    "wof:placetype": "postalcode"
  },
  "geometry": {"coordinates":[-0.216161,51.417394],"type":"Point"}
}
