{
  "type": "Feature",
  "properties": {
    "date:inception_lower": "1980-01-01",
    "date:inception_upper": "1980-01-01",
    "iso:country": "GB",
    "wof:name": "N17 9EJ",
    "wof:placetype": "postalcode"
  },
  "geometry": {"coordinates":[-0.069371,51.589642],"type":"Point"}
}
