{
  "type": "Feature",
  "properties": {
    "iso:country": "GB",
    "wof:name": "GL52 8FE",
    "wof:placetype": "postalcode"
  },
  "geometry": {"coordinates":[-2.058922,51.953661],"type":"Point"}
}
