{
  "type": "Feature",
  "properties": {
    "date:inception_lower": "2016-09-01",
    "date:inception_upper": "2016-09-01",
    "iso:country": "GB",
    "wof:name": "GL52 8FE",
    "wof:placetype": "postalcode"
  },
  "geometry": {"coordinates":[-2.058922,51.953661],"type":"Point"}
}
