{
  "type": "Feature",
  "properties": {
    "iso:country":"GB",
    "wof:name":"BH9 2JG",
    "wof:placetype":"postalcode"
},
  "geometry": {"coordinates":[-1.885820185758,50.74119701408515],"type":"Point"}
}