{
  "type": "Feature",
  "properties": {
    "iso:country":"GB",
    "wof:name":"SN15 3RE",
    "wof:placetype":"postalcode"
},
  "geometry": {"coordinates":[-2.0854365093156,51.45333163633389],"type":"Point"}
}