{
  "type": "Feature",
  "properties": {
    "iso:country": "GB",
    "wof:name": "GL3 4ZE",
    "wof:placetype": "postalcode"
  },
  "geometry": {"coordinates":[-2.174111,51.837427],"type":"Point"}
}
