{
  "type": "Feature",
  "properties": {
    "iso:country":"GB",
    "wof:name":"G46 6AS",
    "wof:placetype":"postalcode"
},
  "geometry": {"coordinates":[-4.29372503679904,55.81308856908837],"type":"Point"}
}