{
  "type": "Feature",
  "properties": {
    "iso:country": "GB",
    "wof:name": "G46 6AS",
    "wof:placetype": "postalcode"
  },
  "geometry": {"coordinates":[-4.293725,55.813089],"type":"Point"}
}
