{
  "type": "Feature",
  "properties": {
    "iso:country":"GB",
    "wof:name":"YO15 3BH",
    "wof:placetype":"postalcode"
},
  "geometry": {"coordinates":[-0.19645541551909,54.08312495812628],"type":"Point"}
}