{
  "type": "Feature",
  "properties": {
    "iso:country": "GB",
    "wof:name": "YO15 3BH",
    "wof:placetype": "postalcode"
  },
  "geometry": {"coordinates":[-0.196455,54.083125],"type":"Point"}
}
