{
  "type": "Feature",
  "properties": {
    "iso:country": "GB",
    "wof:name": "YO41 1HF",
    "wof:placetype": "postalcode"
  },
  "geometry": {"coordinates":[-0.861459,54.004016],"type":"Point"}
}
