{
  "type": "Feature",
  "properties": {
    "date:inception_lower": "1998-06-01",
    "date:inception_upper": "1998-06-01",
    "iso:country": "GB",
    "wof:name": "YO41 1HF",
    "wof:placetype": "postalcode"
  },
  "geometry": {"coordinates":[-0.861459,54.004016],"type":"Point"}
}
