{
  "type": "Feature",
  "properties": {
    "iso:country":"GB",
    "wof:name":"YO41 1HF",
    "wof:placetype":"postalcode"
},
  "geometry": {"coordinates":[-0.86145914178815,54.00401633988579],"type":"Point"}
}