{
  "type": "Feature",
  "properties": {
    "date:inception_lower": "2010-03-01",
    "date:inception_upper": "2010-03-01",
    "iso:country": "GB",
    "wof:name": "CH41 5FE",
    "wof:placetype": "postalcode"
  },
  "geometry": {"coordinates":[-3.018948,53.389873],"type":"Point"}
}
