{
  "type": "Feature",
  "properties": {
    "iso:country":"GB",
    "wof:name":"CH41 5FE",
    "wof:placetype":"postalcode"
},
  "geometry": {"coordinates":[-3.01897775107585,53.38984666910699],"type":"Point"}
}