{
  "type": "Feature",
  "properties": {
    "date:inception_lower": "2020-07-01",
    "date:inception_upper": "2020-07-01",
    "iso:country": "GB",
    "wof:name": "M3 5EY",
    "wof:placetype": "postalcode"
  },
  "geometry": {"coordinates":[-2.25192,53.484039],"type":"Point"}
}
