{
  "type": "Feature",
  "properties": {
    "iso:country":"GB",
    "wof:name":"EH10 6SH",
    "wof:placetype":"postalcode"
},
  "geometry": {"coordinates":[-3.21457961400671,55.9030014864563],"type":"Point"}
}