{
  "type": "Feature",
  "properties": {
    "iso:country":"GB",
    "wof:name":"NG7 7LA",
    "wof:placetype":"postalcode"
},
  "geometry": {"coordinates":[-1.16607645807497,52.97312922602001],"type":"Point"}
}