{
  "type": "Feature",
  "properties": {
    "iso:country":"GB",
    "wof:name":"DT6 5EA",
    "wof:placetype":"postalcode"
},
  "geometry": {"coordinates":[-2.76459216908922,50.73856447748667],"type":"Point"}
}