{
  "type": "Feature",
  "properties": {
    "iso:country": "GB",
    "wof:name": "PO38 1LR",
    "wof:placetype": "postalcode"
  },
  "geometry": {"coordinates":[-1.212952,50.593956],"type":"Point"}
}
