{
  "type": "Feature",
  "properties": {
    "iso:country":"GB",
    "wof:name":"PO38 1LR",
    "wof:placetype":"postalcode"
},
  "geometry": {"coordinates":[-1.21295231270465,50.5939563426767],"type":"Point"}
}