{
  "type": "Feature",
  "properties": {
    "iso:country":"GB",
    "wof:name":"TS16 0PG",
    "wof:placetype":"postalcode"
},
  "geometry": {"coordinates":[-1.36363557905654,54.52558711376004],"type":"Point"}
}