{
  "type": "Feature",
  "properties": {
    "date:inception_lower":"1980-01-01",
    "date:inception_upper":"1980-01-31",
    "iso:country":"GB",
    "wof:name":"DH8 9SU",
    "wof:placetype":"postalcode"
},
  "geometry": {"coordinates":[-2.062748,54.854588],"type":"Point"}
}