{
  "type": "Feature",
  "properties": {
    "iso:country": "GB",
    "wof:name": "DH8 9SU",
    "wof:placetype": "postalcode"
  },
  "geometry": {"coordinates":[-2.062748,54.854588],"type":"Point"}
}
