{
  "type": "Feature",
  "properties": {
    "iso:country":"GB",
    "wof:name":"DH8 9SU",
    "wof:placetype":"postalcode"
},
  "geometry": {"coordinates":[-2.06272436471104,54.85458982740452],"type":"Point"}
}