{
  "type": "Feature",
  "properties": {
    "iso:country":"GB",
    "wof:name":"CF23 7BN",
    "wof:placetype":"postalcode"
},
  "geometry": {"coordinates":[-3.14694715684329,51.52653728983678],"type":"Point"}
}