{
  "type": "Feature",
  "properties": {
    "iso:country": "GB",
    "wof:name": "NR12 9GB",
    "wof:placetype": "postalcode"
  },
  "geometry": {"coordinates":[1.484777,52.765466],"type":"Point"}
}
