{
  "type": "Feature",
  "properties": {
    "iso:country":"GB",
    "wof:name":"WA5 7XS",
    "wof:placetype":"postalcode"
},
  "geometry": {"coordinates":[-2.64085460842183,53.41406673682371],"type":"Point"}
}