{
  "type": "Feature",
  "properties": {
    "iso:country": "GB",
    "wof:name": "WA5 7XS",
    "wof:placetype": "postalcode"
  },
  "geometry": {"coordinates":[-2.640855,53.414067],"type":"Point"}
}
