{
  "type": "Feature",
  "properties": {
    "iso:country":"GB",
    "wof:name":"KT2 5BW",
    "wof:placetype":"postalcode"
},
  "geometry": {"coordinates":[-0.30091187834344,51.41378000341769],"type":"Point"}
}