{
  "type": "Feature",
  "properties": {
    "iso:country":"GB",
    "wof:name":"OX4 7FD",
    "wof:placetype":"postalcode"
},
  "geometry": {"coordinates":[-1.18935832461675,51.71794385785574],"type":"Point"}
}