{
  "type": "Feature",
  "properties": {
    "date:inception_lower": "1995-07-01",
    "date:inception_upper": "1995-07-01",
    "iso:country": "GB",
    "wof:name": "CF83 3LD",
    "wof:placetype": "postalcode"
  },
  "geometry": {"coordinates":[-3.231271,51.60073],"type":"Point"}
}
