{
  "type": "Feature",
  "properties": {
    "iso:country":"GB",
    "wof:name":"CF83 3LD",
    "wof:placetype":"postalcode"
},
  "geometry": {"coordinates":[-3.23115960878427,51.60072038344651],"type":"Point"}
}