{
  "type": "Feature",
  "properties": {
    "iso:country":"GB",
    "wof:name":"WV16 5JR",
    "wof:placetype":"postalcode"
},
  "geometry": {"coordinates":[-2.41470767096392,52.51464610802694],"type":"Point"}
}