{
  "type": "Feature",
  "properties": {
    "iso:country":"GB",
    "wof:name":"B94 5AD",
    "wof:placetype":"postalcode"
},
  "geometry": {"coordinates":[-1.83304286681929,52.3398513798753],"type":"Point"}
}