{
  "type": "Feature",
  "properties": {
    "iso:country":"GB",
    "wof:name":"BH19 3AE",
    "wof:placetype":"postalcode"
},
  "geometry": {"coordinates":[-1.9536472934809,50.64051611977969],"type":"Point"}
}