{
  "type": "Feature",
  "properties": {
    "iso:country":"GB",
    "wof:name":"G82 4JG",
    "wof:placetype":"postalcode"
},
  "geometry": {"coordinates":[-4.58495316640341,55.94757047865178],"type":"Point"}
}