{
  "type": "Feature",
  "properties": {
    "date:inception_lower": "2005-09-01",
    "date:inception_upper": "2005-09-01",
    "iso:country": "GB",
    "wof:name": "NR24 2DU",
    "wof:placetype": "postalcode"
  },
  "geometry": {"coordinates":[1.043188,52.854406],"type":"Point"}
}
