{
  "type": "Feature",
  "properties": {
    "iso:country": "GB",
    "wof:name": "NR24 2DU",
    "wof:placetype": "postalcode"
  },
  "geometry": {"coordinates":[1.043188,52.854406],"type":"Point"}
}
