{
  "type": "Feature",
  "properties": {
    "iso:country":"GB",
    "wof:name":"HD7 5AQ",
    "wof:placetype":"postalcode"
},
  "geometry": {"coordinates":[-1.88218603519099,53.62290288548999],"type":"Point"}
}