{
  "type": "Feature",
  "properties": {
    "iso:country": "GB",
    "wof:name": "HD7 5AQ",
    "wof:placetype": "postalcode"
  },
  "geometry": {"coordinates":[-1.882186,53.622903],"type":"Point"}
}
