{
  "type": "Feature",
  "properties": {
    "iso:country": "GB",
    "wof:name": "G34 0DF",
    "wof:placetype": "postalcode"
  },
  "geometry": {"coordinates":[-4.09682,55.869732],"type":"Point"}
}
