{
  "type": "Feature",
  "properties": {
    "iso:country": "GB",
    "wof:name": "LL11 3NY",
    "wof:placetype": "postalcode"
  },
  "geometry": {"coordinates":[-3.070665,53.055056],"type":"Point"}
}
