{
  "type": "Feature",
  "properties": {
    "iso:country":"GB",
    "wof:name":"LL11 3NY",
    "wof:placetype":"postalcode"
},
  "geometry": {"coordinates":[-3.0706650683772,53.05505630028888],"type":"Point"}
}