{
  "type": "Feature",
  "properties": {
    "iso:country":"GB",
    "wof:name":"PL9 9LY",
    "wof:placetype":"postalcode"
},
  "geometry": {"coordinates":[-4.09041999955061,50.34261361297926],"type":"Point"}
}