{
  "type": "Feature",
  "properties": {
    "iso:country":"GB",
    "wof:name":"OX7 4JP",
    "wof:placetype":"postalcode"
},
  "geometry": {"coordinates":[-1.41430852765064,51.94848896508783],"type":"Point"}
}