{
  "type": "Feature",
  "properties": {
    "iso:country":"GB",
    "wof:name":"BR5 4PW",
    "wof:placetype":"postalcode"
},
  "geometry": {"coordinates":[0.12130289065107,51.37201392568755],"type":"Point"}
}