{
  "type": "Feature",
  "properties": {
    "iso:country":"GB",
    "wof:name":"WF3 2AF",
    "wof:placetype":"postalcode"
},
  "geometry": {"coordinates":[-1.53964581513014,53.72205247983388],"type":"Point"}
}