{
  "type": "Feature",
  "properties": {
    "date:inception_lower":"1980-01-01",
    "date:inception_upper":"1980-01-31",
    "iso:country":"GB",
    "wof:name":"M6 5WN",
    "wof:placetype":"postalcode"
},
  "geometry": {"coordinates":[-2.293871,53.489859],"type":"Point"}
}