{
  "type": "Feature",
  "properties": {
    "iso:country": "GB",
    "wof:name": "WF11 0DD",
    "wof:placetype": "postalcode"
  },
  "geometry": {"coordinates":[-1.264049,53.701892],"type":"Point"}
}
