{
  "type": "Feature",
  "properties": {
    "iso:country": "GB",
    "wof:name": "MK45 3WR",
    "wof:placetype": "postalcode"
  },
  "geometry": {"coordinates":[-0.448148,52.074664],"type":"Point"}
}
