{
  "type": "Feature",
  "properties": {
    "iso:country":"GB",
    "wof:name":"SR2 9RN",
    "wof:placetype":"postalcode"
},
  "geometry": {"coordinates":[-1.36640803947761,54.88473118808781],"type":"Point"}
}