{
  "type": "Feature",
  "properties": {
    "iso:country":"GB",
    "wof:name":"NG4 1FQ",
    "wof:placetype":"postalcode"
},
  "geometry": {"coordinates":[-1.09796561237396,52.96652819039668],"type":"Point"}
}