{
  "type": "Feature",
  "properties": {
    "iso:country":"GB",
    "wof:name":"SE5 8TN",
    "wof:placetype":"postalcode"
},
  "geometry": {"coordinates":[-0.08819427303326,51.46579891166976],"type":"Point"}
}