{
  "type": "Feature",
  "properties": {
    "date:inception_lower": "1980-01-01",
    "date:inception_upper": "1980-01-01",
    "iso:country": "GB",
    "wof:name": "PA42 7AW",
    "wof:placetype": "postalcode"
  },
  "geometry": {"coordinates":[-6.224023,55.641885],"type":"Point"}
}
