{
  "type": "Feature",
  "properties": {
    "iso:country": "GB",
    "wof:name": "PA42 7AW",
    "wof:placetype": "postalcode"
  },
  "geometry": {"coordinates":[-6.224023,55.641885],"type":"Point"}
}
