{
  "type": "Feature",
  "properties": {
    "iso:country":"GB",
    "wof:name":"PA42 7AW",
    "wof:placetype":"postalcode"
},
  "geometry": {"coordinates":[-6.22402279993377,55.64188519435731],"type":"Point"}
}