{
  "type": "Feature",
  "properties": {
    "date:inception_lower": "1980-01-01",
    "date:inception_upper": "1980-01-01",
    "iso:country": "GB",
    "wof:name": "B75 6SH",
    "wof:placetype": "postalcode"
  },
  "geometry": {"coordinates":[-1.821554,52.575876],"type":"Point"}
}
