{
  "type": "Feature",
  "properties": {
    "iso:country":"GB",
    "wof:name":"B75 6SH",
    "wof:placetype":"postalcode"
},
  "geometry": {"coordinates":[-1.8215542153111,52.57587612940353],"type":"Point"}
}