{
  "type": "Feature",
  "properties": {
    "date:inception_lower": "1980-01-01",
    "date:inception_upper": "1980-01-01",
    "iso:country": "GB",
    "wof:name": "GU33 7BB",
    "wof:placetype": "postalcode"
  },
  "geometry": {"coordinates":[-0.88788,51.046319],"type":"Point"}
}
