{
  "type": "Feature",
  "properties": {
    "date:inception_lower": "1980-01-01",
    "date:inception_upper": "1980-01-01",
    "iso:country": "GB",
    "wof:name": "BA12 0EP",
    "wof:placetype": "postalcode"
  },
  "geometry": {"coordinates":[-2.12073,51.201643],"type":"Point"}
}
