{
  "type": "Feature",
  "properties": {
    "iso:country":"GB",
    "wof:name":"AL7 1EF",
    "wof:placetype":"postalcode"
},
  "geometry": {"coordinates":[-0.19353566180187,51.81315015759124],"type":"Point"}
}