{
  "type": "Feature",
  "properties": {
    "iso:country": "GB",
    "wof:name": "S8 7NP",
    "wof:placetype": "postalcode"
  },
  "geometry": {"coordinates":[-1.482634,53.323253],"type":"Point"}
}
