{
  "type": "Feature",
  "properties": {
    "iso:country": "GB",
    "wof:name": "IP3 0FF",
    "wof:placetype": "postalcode"
  },
  "geometry": {"coordinates":[1.16766,52.050121],"type":"Point"}
}
