{
  "type": "Feature",
  "properties": {
    "iso:country": "GB",
    "wof:name": "SR2 0BG",
    "wof:placetype": "postalcode"
  },
  "geometry": {"coordinates":[-1.385974,54.869123],"type":"Point"}
}
