{
  "type": "Feature",
  "properties": {
    "iso:country": "GB",
    "wof:name": "TN28 8TA",
    "wof:placetype": "postalcode"
  },
  "geometry": {"coordinates":[0.963284,50.952083],"type":"Point"}
}
