{
  "type": "Feature",
  "properties": {
    "date:inception_lower":"2001-06-01",
    "date:inception_upper":"2001-06-30",
    "iso:country":"GB",
    "wof:name":"PR26 7UN",
    "wof:placetype":"postalcode"
},
  "geometry": {"coordinates":[-2.734867,53.695127],"type":"Point"}
}