{
  "type": "Feature",
  "properties": {
    "iso:country":"GB",
    "wof:name":"PR26 7UN",
    "wof:placetype":"postalcode"
},
  "geometry": {"coordinates":[-2.734867132318,53.69512702578361],"type":"Point"}
}