{
  "type": "Feature",
  "properties": {
    "date:inception_lower": "2022-02-01",
    "date:inception_upper": "2022-02-01",
    "iso:country": "GB",
    "wof:name": "EH53 0TU",
    "wof:placetype": "postalcode"
  },
  "geometry": {"coordinates":[-3.433839,55.901807],"type":"Point"}
}
