{
  "type": "Feature",
  "properties": {
    "iso:country":"GB",
    "wof:name":"SO31 6NX",
    "wof:placetype":"postalcode"
},
  "geometry": {"coordinates":[-1.26323321801018,50.8569830352607],"type":"Point"}
}