{
  "type": "Feature",
  "properties": {
    "iso:country": "GB",
    "wof:name": "SO31 6NX",
    "wof:placetype": "postalcode"
  },
  "geometry": {"coordinates":[-1.263233,50.856983],"type":"Point"}
}
