{
  "type": "Feature",
  "properties": {
    "iso:country":"GB",
    "wof:name":"GU2 7UL",
    "wof:placetype":"postalcode"
},
  "geometry": {"coordinates":[-0.59506927166279,51.24058928017202],"type":"Point"}
}