{
  "type": "Feature",
  "properties": {
    "iso:country": "GB",
    "wof:name": "CW5 6EH",
    "wof:placetype": "postalcode"
  },
  "geometry": {"coordinates":[-2.536751,53.13829],"type":"Point"}
}
