{
  "type": "Feature",
  "properties": {
    "date:inception_lower": "1980-01-01",
    "date:inception_upper": "1980-01-01",
    "iso:country": "GB",
    "wof:name": "CW5 6EH",
    "wof:placetype": "postalcode"
  },
  "geometry": {"coordinates":[-2.536751,53.13829],"type":"Point"}
}
