{
  "type": "Feature",
  "properties": {
    "iso:country":"GB",
    "wof:name":"CW5 6EH",
    "wof:placetype":"postalcode"
},
  "geometry": {"coordinates":[-2.53675132364944,53.13828973017317],"type":"Point"}
}