{
  "type": "Feature",
  "properties": {
    "iso:country": "GB",
    "wof:name": "B69 2LG",
    "wof:placetype": "postalcode"
  },
  "geometry": {"coordinates":[-2.060091,52.513803],"type":"Point"}
}
