{
  "type": "Feature",
  "properties": {
    "date:inception_lower":"2015-09-01",
    "date:inception_upper":"2015-09-30",
    "iso:country":"GB",
    "wof:name":"WR6 5BF",
    "wof:placetype":"postalcode"
},
  "geometry": {"coordinates":[-2.493868,52.131392],"type":"Point"}
}