{
  "type": "Feature",
  "properties": {
    "iso:country":"GB",
    "wof:name":"WR6 5BF",
    "wof:placetype":"postalcode"
},
  "geometry": {"coordinates":[-2.49386853888379,52.13139199582684],"type":"Point"}
}