{
  "type": "Feature",
  "properties": {
    "iso:country":"GB",
    "wof:name":"SN3 5BE",
    "wof:placetype":"postalcode"
},
  "geometry": {"coordinates":[-1.73385223640352,51.56484347991618],"type":"Point"}
}