{
  "type": "Feature",
  "properties": {
    "date:inception_lower":"1980-01-01",
    "date:inception_upper":"1980-01-31",
    "iso:country":"GB",
    "wof:name":"SN3 5BE",
    "wof:placetype":"postalcode"
},
  "geometry": {"coordinates":[-1.733852,51.564843],"type":"Point"}
}