{
  "type": "Feature",
  "properties": {
    "iso:country":"GB",
    "wof:name":"PR5 6BQ",
    "wof:placetype":"postalcode"
},
  "geometry": {"coordinates":[-2.66882727154341,53.72426756962045],"type":"Point"}
}