{
  "type": "Feature",
  "properties": {
    "iso:country": "GB",
    "wof:name": "EX4 2HD",
    "wof:placetype": "postalcode"
  },
  "geometry": {"coordinates":[-3.581032,50.720808],"type":"Point"}
}
