{
  "type": "Feature",
  "properties": {
    "iso:country": "GB",
    "wof:name": "DT2 8PQ",
    "wof:placetype": "postalcode"
  },
  "geometry": {"coordinates":[-2.377928,50.68617],"type":"Point"}
}
