{
  "type": "Feature",
  "properties": {
    "iso:country":"GB",
    "wof:name":"DT2 8PQ",
    "wof:placetype":"postalcode"
},
  "geometry": {"coordinates":[-2.37792815889367,50.68617049437065],"type":"Point"}
}