{
  "type": "Feature",
  "properties": {
    "iso:country":"GB",
    "wof:name":"NP19 7JA",
    "wof:placetype":"postalcode"
},
  "geometry": {"coordinates":[-2.97981594195985,51.60424794758868],"type":"Point"}
}