{
  "type": "Feature",
  "properties": {
    "iso:country": "GB",
    "wof:name": "NP19 7JA",
    "wof:placetype": "postalcode"
  },
  "geometry": {"coordinates":[-2.979816,51.604248],"type":"Point"}
}
