{
  "type": "Feature",
  "properties": {
    "iso:country":"GB",
    "wof:name":"TW17 8LH",
    "wof:placetype":"postalcode"
},
  "geometry": {"coordinates":[-0.44007586108566,51.38995170072661],"type":"Point"}
}