{
  "type": "Feature",
  "properties": {
    "iso:country":"GB",
    "wof:name":"M27 6FA",
    "wof:placetype":"postalcode"
},
  "geometry": {"coordinates":[-2.34220539540198,53.51221959173979],"type":"Point"}
}