{
  "type": "Feature",
  "properties": {
    "date:inception_lower": "2015-06-01",
    "date:inception_upper": "2015-06-01",
    "iso:country": "GB",
    "wof:name": "M27 6FA",
    "wof:placetype": "postalcode"
  },
  "geometry": {"coordinates":[-2.342205,53.51222],"type":"Point"}
}
