{
  "type": "Feature",
  "properties": {
    "iso:country": "GB",
    "wof:name": "OX11 7QP",
    "wof:placetype": "postalcode"
  },
  "geometry": {"coordinates":[-1.228516,51.611435],"type":"Point"}
}
