{
  "type": "Feature",
  "properties": {
    "iso:country":"GB",
    "wof:name":"S20 1WA",
    "wof:placetype":"postalcode"
},
  "geometry": {"coordinates":[-1.34692079515258,53.34757647415469],"type":"Point"}
}