{
  "type": "Feature",
  "properties": {
    "iso:country": "GB",
    "wof:name": "WV3 0HP",
    "wof:placetype": "postalcode"
  },
  "geometry": {"coordinates":[-2.142402,52.576967],"type":"Point"}
}
