{
  "type": "Feature",
  "properties": {
    "date:inception_lower": "2000-06-01",
    "date:inception_upper": "2000-06-01",
    "iso:country": "GB",
    "wof:name": "PE28 3NF",
    "wof:placetype": "postalcode"
  },
  "geometry": {"coordinates":[0.014627,52.367392],"type":"Point"}
}
