{
  "type": "Feature",
  "properties": {
    "iso:country": "GB",
    "wof:name": "PE28 3NF",
    "wof:placetype": "postalcode"
  },
  "geometry": {"coordinates":[0.014627,52.367392],"type":"Point"}
}
