{
  "type": "Feature",
  "properties": {
    "iso:country":"GB",
    "wof:name":"TW7 6PH",
    "wof:placetype":"postalcode"
},
  "geometry": {"coordinates":[-0.33103132607705,51.47043325743267],"type":"Point"}
}