{
  "type": "Feature",
  "properties": {
    "date:inception_lower":"2012-06-01",
    "date:inception_upper":"2012-06-30",
    "iso:country":"GB",
    "wof:name":"YO14 9GP",
    "wof:placetype":"postalcode"
},
  "geometry": {"coordinates":[-0.28586,54.179489],"type":"Point"}
}