{
  "type": "Feature",
  "properties": {
    "iso:country":"GB",
    "wof:name":"YO14 9GP",
    "wof:placetype":"postalcode"
},
  "geometry": {"coordinates":[-0.28578927942756,54.17934281962776],"type":"Point"}
}