{
  "type": "Feature",
  "properties": {
    "date:inception_lower": "1997-12-01",
    "date:inception_upper": "1997-12-01",
    "iso:country": "GB",
    "wof:name": "BS30 5NY",
    "wof:placetype": "postalcode"
  },
  "geometry": {"coordinates":[-2.468696,51.453261],"type":"Point"}
}
