{
  "type": "Feature",
  "properties": {
    "iso:country": "GB",
    "wof:name": "CB22 7PA",
    "wof:placetype": "postalcode"
  },
  "geometry": {"coordinates":[0.097502,52.125464],"type":"Point"}
}
