{
  "type": "Feature",
  "properties": {
    "iso:country": "GB",
    "wof:name": "CA17 4NY",
    "wof:placetype": "postalcode"
  },
  "geometry": {"coordinates":[-2.459858,54.443686],"type":"Point"}
}
