{
  "type": "Feature",
  "properties": {
    "iso:country":"GB",
    "wof:name":"CA17 4NY",
    "wof:placetype":"postalcode"
},
  "geometry": {"coordinates":[-2.45985821199172,54.44368606202332],"type":"Point"}
}