{
  "type": "Feature",
  "properties": {
    "iso:country":"GB",
    "wof:name":"PR6 7TT",
    "wof:placetype":"postalcode"
},
  "geometry": {"coordinates":[-2.63594223669258,53.69831782788274],"type":"Point"}
}