{
  "type": "Feature",
  "properties": {
    "iso:country": "GB",
    "wof:name": "ML8 4BL",
    "wof:placetype": "postalcode"
  },
  "geometry": {"coordinates":[-3.837589,55.73643],"type":"Point"}
}
