{
  "type": "Feature",
  "properties": {
    "iso:country": "GB",
    "wof:name": "BN1 7DX",
    "wof:placetype": "postalcode"
  },
  "geometry": {"coordinates":[-0.13326,50.840315],"type":"Point"}
}
