{
  "type": "Feature",
  "properties": {
    "date:inception_lower":"2006-07-01",
    "date:inception_upper":"2006-07-31",
    "iso:country":"GB",
    "wof:name":"NG22 9US",
    "wof:placetype":"postalcode"
},
  "geometry": {"coordinates":[-0.97442,53.204891],"type":"Point"}
}