{
  "type": "Feature",
  "properties": {
    "iso:country":"GB",
    "wof:name":"NG22 9US",
    "wof:placetype":"postalcode"
},
  "geometry": {"coordinates":[-0.97442011716649,53.20495132195476],"type":"Point"}
}