{
  "type": "Feature",
  "properties": {
    "iso:country": "GB",
    "wof:name": "NG22 9US",
    "wof:placetype": "postalcode"
  },
  "geometry": {"coordinates":[-0.97442,53.204891],"type":"Point"}
}
