{
  "type": "Feature",
  "properties": {
    "iso:country": "GB",
    "wof:name": "DH3 3LA",
    "wof:placetype": "postalcode"
  },
  "geometry": {"coordinates":[-1.57381,54.848674],"type":"Point"}
}
