{
  "type": "Feature",
  "properties": {
    "iso:country":"GB",
    "wof:name":"DH3 3LA",
    "wof:placetype":"postalcode"
},
  "geometry": {"coordinates":[-1.57380978702387,54.84867410002121],"type":"Point"}
}