{
  "type": "Feature",
  "properties": {
    "date:inception_lower": "1980-01-01",
    "date:inception_upper": "1980-01-01",
    "iso:country": "GB",
    "wof:name": "TW15 2BH",
    "wof:placetype": "postalcode"
  },
  "geometry": {"coordinates":[-0.453722,51.427711],"type":"Point"}
}
