{
  "type": "Feature",
  "properties": {
    "iso:country": "GB",
    "wof:name": "GL52 8NN",
    "wof:placetype": "postalcode"
  },
  "geometry": {"coordinates":[-2.059487,51.946648],"type":"Point"}
}
