{
  "type": "Feature",
  "properties": {
    "iso:country":"GB",
    "wof:name":"NG31 9SY",
    "wof:placetype":"postalcode"
},
  "geometry": {"coordinates":[-0.60681396970383,52.91880605270143],"type":"Point"}
}