{
  "type": "Feature",
  "properties": {
    "iso:country": "GB",
    "wof:name": "NG31 9SY",
    "wof:placetype": "postalcode"
  },
  "geometry": {"coordinates":[-0.606814,52.918806],"type":"Point"}
}
