{
  "type": "Feature",
  "properties": {
    "date:inception_lower": "1980-01-01",
    "date:inception_upper": "1980-01-01",
    "iso:country": "GB",
    "wof:name": "NN1 5EW",
    "wof:placetype": "postalcode"
  },
  "geometry": {"coordinates":[-0.883732,52.239928],"type":"Point"}
}
