{
  "type": "Feature",
  "properties": {
    "date:inception_lower":"2008-01-01",
    "date:inception_upper":"2008-01-31",
    "iso:country":"GB",
    "wof:name":"KT23 4EB",
    "wof:placetype":"postalcode"
},
  "geometry": {"coordinates":[-0.362789,51.279252],"type":"Point"}
}