{
  "type": "Feature",
  "properties": {
    "iso:country": "GB",
    "wof:name": "KT23 4EB",
    "wof:placetype": "postalcode"
  },
  "geometry": {"coordinates":[-0.362789,51.279252],"type":"Point"}
}
