{
  "type": "Feature",
  "properties": {
    "iso:country": "GB",
    "wof:name": "M60 2UT",
    "wof:placetype": "postalcode"
  },
  "geometry": {"coordinates":[-2.244557,53.479274],"type":"Point"}
}
