{
  "type": "Feature",
  "properties": {
    "iso:country":"GB",
    "wof:name":"M60 2UT",
    "wof:placetype":"postalcode"
},
  "geometry": {"coordinates":[-2.24455667263432,53.47927412121379],"type":"Point"}
}