{
  "type": "Feature",
  "properties": {
    "date:inception_lower": "2018-02-01",
    "date:inception_upper": "2018-02-01",
    "iso:country": "GB",
    "wof:name": "KY7 9EA",
    "wof:placetype": "postalcode"
  },
  "geometry": {"coordinates":[-3.147191,56.187845],"type":"Point"}
}
