{
  "type": "Feature",
  "properties": {
    "iso:country":"GB",
    "wof:name":"ST18 0PQ",
    "wof:placetype":"postalcode"
},
  "geometry": {"coordinates":[-1.99989860292478,52.82807907979576],"type":"Point"}
}