{
  "type": "Feature",
  "properties": {
    "iso:country": "GB",
    "wof:name": "WR5 3TR",
    "wof:placetype": "postalcode"
  },
  "geometry": {"coordinates":[-2.202869,52.172449],"type":"Point"}
}
