{
  "type": "Feature",
  "properties": {
    "iso:country":"GB",
    "wof:name":"BS10 6AF",
    "wof:placetype":"postalcode"
},
  "geometry": {"coordinates":[-2.61127378014154,51.49959460026712],"type":"Point"}
}