{
  "type": "Feature",
  "properties": {
    "iso:country":"GB",
    "wof:name":"BS5 0JQ",
    "wof:placetype":"postalcode"
},
  "geometry": {"coordinates":[-2.56946709023871,51.46377580922812],"type":"Point"}
}