{
  "type": "Feature",
  "properties": {
    "iso:country":"GB",
    "wof:name":"B23 7TR",
    "wof:placetype":"postalcode"
},
  "geometry": {"coordinates":[-1.87561476711975,52.52579971923664],"type":"Point"}
}