{
  "type": "Feature",
  "properties": {
    "iso:country": "GB",
    "wof:name": "CH43 3BJ",
    "wof:placetype": "postalcode"
  },
  "geometry": {"coordinates":[-3.051181,53.366439],"type":"Point"}
}
