{
  "type": "Feature",
  "properties": {
    "date:inception_lower":"1980-01-01",
    "date:inception_upper":"1980-01-31",
    "iso:country":"GB",
    "wof:name":"SL5 8PY",
    "wof:placetype":"postalcode"
},
  "geometry": {"coordinates":[-0.686505,51.421181],"type":"Point"}
}