{
  "type": "Feature",
  "properties": {
    "iso:country":"GB",
    "wof:name":"SL5 8PY",
    "wof:placetype":"postalcode"
},
  "geometry": {"coordinates":[-0.68650465419422,51.42118103745858],"type":"Point"}
}