{
  "type": "Feature",
  "properties": {
    "iso:country": "GB",
    "wof:name": "SL5 8PY",
    "wof:placetype": "postalcode"
  },
  "geometry": {"coordinates":[-0.686505,51.421181],"type":"Point"}
}
