{
  "type": "Feature",
  "properties": {
    "iso:country": "GB",
    "wof:name": "CF31 4HU",
    "wof:placetype": "postalcode"
  },
  "geometry": {"coordinates":[-3.583893,51.507404],"type":"Point"}
}
