{
  "type": "Feature",
  "properties": {
    "iso:country":"GB",
    "wof:name":"WC2H 7AW",
    "wof:placetype":"postalcode"
},
  "geometry": {"coordinates":[-0.12897145258054,51.51107780603749],"type":"Point"}
}