{
  "type": "Feature",
  "properties": {
    "iso:country":"GB",
    "wof:name":"CF44 9TA",
    "wof:placetype":"postalcode"
},
  "geometry": {"coordinates":[-3.50783526937758,51.74081374026781],"type":"Point"}
}