{
  "type": "Feature",
  "properties": {
    "iso:country":"GB",
    "wof:name":"SL6 8FA",
    "wof:placetype":"postalcode"
},
  "geometry": {"coordinates":[-0.71245918844639,51.52725097364527],"type":"Point"}
}