{
  "type": "Feature",
  "properties": {
    "date:inception_lower": "2014-12-01",
    "date:inception_upper": "2014-12-01",
    "iso:country": "GB",
    "wof:name": "SL6 8FA",
    "wof:placetype": "postalcode"
  },
  "geometry": {"coordinates":[-0.71247,51.527218],"type":"Point"}
}
