{
  "type": "Feature",
  "properties": {
    "iso:country":"GB",
    "wof:name":"CA4 0PY",
    "wof:placetype":"postalcode"
},
  "geometry": {"coordinates":[-2.89920797923199,54.81731420349006],"type":"Point"}
}