{
  "type": "Feature",
  "properties": {
    "iso:country":"GB",
    "wof:name":"WS2 7DT",
    "wof:placetype":"postalcode"
},
  "geometry": {"coordinates":[-2.00878642324865,52.60270051850771],"type":"Point"}
}