{
  "type": "Feature",
  "properties": {
    "iso:country":"GB",
    "wof:name":"TA12 6BL",
    "wof:placetype":"postalcode"
},
  "geometry": {"coordinates":[-2.81948430958717,50.98037232776057],"type":"Point"}
}