{
  "type": "Feature",
  "properties": {
    "date:inception_lower":"1980-01-01",
    "date:inception_upper":"1980-01-31",
    "iso:country":"GB",
    "wof:name":"TA12 6BL",
    "wof:placetype":"postalcode"
},
  "geometry": {"coordinates":[-2.819484,50.980372],"type":"Point"}
}