{
  "type": "Feature",
  "properties": {
    "iso:country": "GB",
    "wof:name": "GU34 5LJ",
    "wof:placetype": "postalcode"
  },
  "geometry": {"coordinates":[-1.051817,51.112694],"type":"Point"}
}
