{
  "type": "Feature",
  "properties": {
    "iso:country": "GB",
    "wof:name": "DE21 2ES",
    "wof:placetype": "postalcode"
  },
  "geometry": {"coordinates":[-1.428255,52.946093],"type":"Point"}
}
