{
  "type": "Feature",
  "properties": {
    "iso:country":"GB",
    "wof:name":"DE21 2ES",
    "wof:placetype":"postalcode"
},
  "geometry": {"coordinates":[-1.42825457009637,52.94609252356661],"type":"Point"}
}