{
  "type": "Feature",
  "properties": {
    "date:inception_lower":"2013-07-01",
    "date:inception_upper":"2013-07-31",
    "iso:country":"GB",
    "wof:name":"PR2 0TG",
    "wof:placetype":"postalcode"
},
  "geometry": {"coordinates":[-2.708372,53.75425],"type":"Point"}
}