{
  "type": "Feature",
  "properties": {
    "iso:country": "GB",
    "wof:name": "CV36 4FG",
    "wof:placetype": "postalcode"
  },
  "geometry": {"coordinates":[-1.677331,52.080767],"type":"Point"}
}
