{
  "type": "Feature",
  "properties": {
    "iso:country":"GB",
    "wof:name":"CV36 4FG",
    "wof:placetype":"postalcode"
},
  "geometry": {"coordinates":[-1.67733102691966,52.08076723506103],"type":"Point"}
}