{
  "type": "Feature",
  "properties": {
    "date:inception_lower": "2010-01-01",
    "date:inception_upper": "2010-01-01",
    "iso:country": "GB",
    "wof:name": "CV36 4FG",
    "wof:placetype": "postalcode"
  },
  "geometry": {"coordinates":[-1.677331,52.080767],"type":"Point"}
}
