{
  "type": "Feature",
  "properties": {
    "iso:country": "GB",
    "wof:name": "WN2 3XF",
    "wof:placetype": "postalcode"
  },
  "geometry": {"coordinates":[-2.570636,53.529414],"type":"Point"}
}
