{
  "type": "Feature",
  "properties": {
    "iso:country":"GB",
    "wof:name":"WN2 3XF",
    "wof:placetype":"postalcode"
},
  "geometry": {"coordinates":[-2.5706360471813,53.52941391581738],"type":"Point"}
}