{
  "type": "Feature",
  "properties": {
    "iso:country":"GB",
    "wof:name":"DN22 9LE",
    "wof:placetype":"postalcode"
},
  "geometry": {"coordinates":[-0.91125851768106,53.35111286046282],"type":"Point"}
}