{
  "type": "Feature",
  "properties": {
    "date:inception_lower": "1980-01-01",
    "date:inception_upper": "1980-01-01",
    "iso:country": "GB",
    "wof:name": "DN22 9LE",
    "wof:placetype": "postalcode"
  },
  "geometry": {"coordinates":[-0.910848,53.351346],"type":"Point"}
}
