{
  "type": "Feature",
  "properties": {
    "iso:country": "GB",
    "wof:name": "DN22 9LE",
    "wof:placetype": "postalcode"
  },
  "geometry": {"coordinates":[-0.910667,53.351371],"type":"Point"}
}
