{
  "type": "Feature",
  "properties": {
    "date:inception_lower": "1980-01-01",
    "date:inception_upper": "1980-01-01",
    "iso:country": "GB",
    "wof:name": "RH11 7QF",
    "wof:placetype": "postalcode"
  },
  "geometry": {"coordinates":[-0.199622,51.12493],"type":"Point"}
}
