{
  "type": "Feature",
  "properties": {
    "iso:country": "GB",
    "wof:name": "TA24 7LS",
    "wof:placetype": "postalcode"
  },
  "geometry": {"coordinates":[-3.630508,51.134735],"type":"Point"}
}
