{
  "type": "Feature",
  "properties": {
    "iso:country":"GB",
    "wof:name":"TA24 7LS",
    "wof:placetype":"postalcode"
},
  "geometry": {"coordinates":[-3.6305078750929,51.13473516804572],"type":"Point"}
}