{
  "type": "Feature",
  "properties": {
    "date:inception_lower":"2009-10-01",
    "date:inception_upper":"2009-10-31",
    "iso:country":"GB",
    "wof:name":"TA24 7LS",
    "wof:placetype":"postalcode"
},
  "geometry": {"coordinates":[-3.630508,51.134735],"type":"Point"}
}