{
  "type": "Feature",
  "properties": {
    "iso:country": "GB",
    "wof:name": "DG7 3PJ",
    "wof:placetype": "postalcode"
  },
  "geometry": {"coordinates":[-4.161493,55.101488],"type":"Point"}
}
