{
  "type": "Feature",
  "properties": {
    "iso:country":"GB",
    "wof:name":"DG7 3PJ",
    "wof:placetype":"postalcode"
},
  "geometry": {"coordinates":[-4.16149263524779,55.10148833443925],"type":"Point"}
}