{
  "type": "Feature",
  "properties": {
    "date:inception_lower":"1987-04-01",
    "date:inception_upper":"1987-04-30",
    "iso:country":"GB",
    "wof:name":"CM14 5UB",
    "wof:placetype":"postalcode"
},
  "geometry": {"coordinates":[0.303131,51.60687],"type":"Point"}
}