{
  "type": "Feature",
  "properties": {
    "iso:country": "GB",
    "wof:name": "LA14 2PS",
    "wof:placetype": "postalcode"
  },
  "geometry": {"coordinates":[-3.238747,54.108892],"type":"Point"}
}
