{
  "type": "Feature",
  "properties": {
    "iso:country":"GB",
    "wof:name":"DL4 2HF",
    "wof:placetype":"postalcode"
},
  "geometry": {"coordinates":[-1.64124515838299,54.63574779479604],"type":"Point"}
}