{
  "type": "Feature",
  "properties": {
    "iso:country":"GB",
    "wof:name":"RG20 8SD",
    "wof:placetype":"postalcode"
},
  "geometry": {"coordinates":[-1.29271756310274,51.4852917608132],"type":"Point"}
}