{
  "type": "Feature",
  "properties": {
    "date:inception_lower":"1980-01-01",
    "date:inception_upper":"1980-01-31",
    "iso:country":"GB",
    "wof:name":"B30 2NY",
    "wof:placetype":"postalcode"
},
  "geometry": {"coordinates":[-1.921247,52.426814],"type":"Point"}
}