{
  "type": "Feature",
  "properties": {
    "iso:country":"GB",
    "wof:name":"B30 2NY",
    "wof:placetype":"postalcode"
},
  "geometry": {"coordinates":[-1.92124744238629,52.4268143026327],"type":"Point"}
}