{
  "type": "Feature",
  "properties": {
    "iso:country":"GB",
    "wof:name":"NE5 1HN",
    "wof:placetype":"postalcode"
},
  "geometry": {"coordinates":[-1.72281983729631,54.99630996042734],"type":"Point"}
}