{
  "type": "Feature",
  "properties": {
    "iso:country": "GB",
    "wof:name": "NE5 1HN",
    "wof:placetype": "postalcode"
  },
  "geometry": {"coordinates":[-1.72282,54.99631],"type":"Point"}
}
