{
  "type": "Feature",
  "properties": {
    "iso:country":"GB",
    "wof:name":"CB9 0AE",
    "wof:placetype":"postalcode"
},
  "geometry": {"coordinates":[0.44272570072763,52.08769248367687],"type":"Point"}
}