{
  "type": "Feature",
  "properties": {
    "iso:country": "GB",
    "wof:name": "WD25 7SX",
    "wof:placetype": "postalcode"
  },
  "geometry": {"coordinates":[-0.394464,51.700066],"type":"Point"}
}
