{
  "type": "Feature",
  "properties": {
    "date:inception_lower": "2021-06-01",
    "date:inception_upper": "2021-06-01",
    "iso:country": "GB",
    "wof:name": "HU13 0FW",
    "wof:placetype": "postalcode"
  },
  "geometry": {"coordinates":[-0.443447,53.730232],"type":"Point"}
}
