{
  "type": "Feature",
  "properties": {
    "iso:country":"GB",
    "wof:name":"EH13 9QA",
    "wof:placetype":"postalcode"
},
  "geometry": {"coordinates":[-3.22463209765356,55.90477090648571],"type":"Point"}
}