{
  "type": "Feature",
  "properties": {
    "iso:country": "GB",
    "wof:name": "B60 1FD",
    "wof:placetype": "postalcode"
  },
  "geometry": {"coordinates":[-2.01449,52.351143],"type":"Point"}
}
