{
  "type": "Feature",
  "properties": {
    "iso:country":"GB",
    "wof:name":"LD1 5PU",
    "wof:placetype":"postalcode"
},
  "geometry": {"coordinates":[-3.39450934527311,52.21082571372222],"type":"Point"}
}