{
  "type": "Feature",
  "properties": {
    "date:inception_lower": "1980-01-01",
    "date:inception_upper": "1980-01-01",
    "iso:country": "GB",
    "wof:name": "SW14 8HD",
    "wof:placetype": "postalcode"
  },
  "geometry": {"coordinates":[-0.262662,51.468712],"type":"Point"}
}
