{
  "type": "Feature",
  "properties": {
    "iso:country":"GB",
    "wof:name":"ME2 2GE",
    "wof:placetype":"postalcode"
},
  "geometry": {"coordinates":[0.47607431518372,51.38450419929696],"type":"Point"}
}