{
  "type": "Feature",
  "properties": {
    "iso:country":"GB",
    "wof:name":"TQ6 9NU",
    "wof:placetype":"postalcode"
},
  "geometry": {"coordinates":[-3.58043334218719,50.35258191177758],"type":"Point"}
}