{
  "type": "Feature",
  "properties": {
    "date:inception_lower":"1980-01-01",
    "date:inception_upper":"1980-01-31",
    "iso:country":"GB",
    "wof:name":"HD1 6SB",
    "wof:placetype":"postalcode"
},
  "geometry": {"coordinates":[-1.773994,53.645731],"type":"Point"}
}