{
  "type": "Feature",
  "properties": {
    "iso:country":"GB",
    "wof:name":"WA1 3PG",
    "wof:placetype":"postalcode"
},
  "geometry": {"coordinates":[-2.56309212116235,53.39507928257174],"type":"Point"}
}