{
  "type": "Feature",
  "properties": {
    "iso:country": "GB",
    "wof:name": "PO31 7EJ",
    "wof:placetype": "postalcode"
  },
  "geometry": {"coordinates":[-1.302174,50.755423],"type":"Point"}
}
