{
  "type": "Feature",
  "properties": {
    "iso:country": "GB",
    "wof:name": "G20 8NS",
    "wof:placetype": "postalcode"
  },
  "geometry": {"coordinates":[-4.285217,55.881921],"type":"Point"}
}
