{
  "type": "Feature",
  "properties": {
    "iso:country":"GB",
    "wof:name":"G20 8NS",
    "wof:placetype":"postalcode"
},
  "geometry": {"coordinates":[-4.28521685902907,55.88192083959107],"type":"Point"}
}