{
  "type": "Feature",
  "properties": {
    "iso:country":"GB",
    "wof:name":"SG16 6AY",
    "wof:placetype":"postalcode"
},
  "geometry": {"coordinates":[-0.28498566115769,52.03571702475021],"type":"Point"}
}