{
  "type": "Feature",
  "properties": {
    "date:inception_lower": "1980-01-01",
    "date:inception_upper": "1980-01-01",
    "iso:country": "GB",
    "wof:name": "NP7 6LH",
    "wof:placetype": "postalcode"
  },
  "geometry": {"coordinates":[-3.009726,51.839031],"type":"Point"}
}
