{
  "type": "Feature",
  "properties": {
    "iso:country":"GB",
    "wof:name":"NP7 6LH",
    "wof:placetype":"postalcode"
},
  "geometry": {"coordinates":[-3.00972568728391,51.83903081324683],"type":"Point"}
}