{
  "type": "Feature",
  "properties": {
    "iso:country": "GB",
    "wof:name": "NP7 6LH",
    "wof:placetype": "postalcode"
  },
  "geometry": {"coordinates":[-3.009726,51.839031],"type":"Point"}
}
