{
  "type": "Feature",
  "properties": {
    "iso:country":"GB",
    "wof:name":"TW1 2HU",
    "wof:placetype":"postalcode"
},
  "geometry": {"coordinates":[-0.30704973106125,51.45588147931991],"type":"Point"}
}