{
  "type": "Feature",
  "properties": {
    "date:inception_lower":"1980-01-01",
    "date:inception_upper":"1980-01-31",
    "iso:country":"GB",
    "wof:name":"PA16 8RH",
    "wof:placetype":"postalcode"
},
  "geometry": {"coordinates":[-4.778368,55.949938],"type":"Point"}
}