{
  "type": "Feature",
  "properties": {
    "iso:country":"GB",
    "wof:name":"PA16 8RH",
    "wof:placetype":"postalcode"
},
  "geometry": {"coordinates":[-4.77836769696319,55.94993793099673],"type":"Point"}
}