{
  "type": "Feature",
  "properties": {
    "iso:country": "GB",
    "wof:name": "SG17 5HA",
    "wof:placetype": "postalcode"
  },
  "geometry": {"coordinates":[-0.298492,52.039393],"type":"Point"}
}
