{
  "type": "Feature",
  "properties": {
    "iso:country": "GB",
    "wof:name": "S36 6DF",
    "wof:placetype": "postalcode"
  },
  "geometry": {"coordinates":[-1.616885,53.523593],"type":"Point"}
}
