{
  "type": "Feature",
  "properties": {
    "iso:country":"GB",
    "wof:name":"W11 4PJ",
    "wof:placetype":"postalcode"
},
  "geometry": {"coordinates":[-0.21240099751983,51.51138087125635],"type":"Point"}
}