{
  "type": "Feature",
  "properties": {
    "iso:country":"GB",
    "wof:name":"GU33 7HE",
    "wof:placetype":"postalcode"
},
  "geometry": {"coordinates":[-0.87409058257908,51.04727479229737],"type":"Point"}
}