{
  "type": "Feature",
  "properties": {
    "date:inception_lower": "2005-04-01",
    "date:inception_upper": "2005-04-01",
    "iso:country": "GB",
    "wof:name": "LE67 4GN",
    "wof:placetype": "postalcode"
  },
  "geometry": {"coordinates":[-1.34258,52.715831],"type":"Point"}
}
