{
  "type": "Feature",
  "properties": {
    "iso:country":"GB",
    "wof:name":"WF17 8LU",
    "wof:placetype":"postalcode"
},
  "geometry": {"coordinates":[-1.64606875036262,53.71931292934854],"type":"Point"}
}