{
  "type": "Feature",
  "properties": {
    "iso:country":"GB",
    "wof:name":"SL7 2PW",
    "wof:placetype":"postalcode"
},
  "geometry": {"coordinates":[-0.78483897827204,51.57491534917925],"type":"Point"}
}