{
  "type": "Feature",
  "properties": {
    "iso:country":"GB",
    "wof:name":"ST12 9EQ",
    "wof:placetype":"postalcode"
},
  "geometry": {"coordinates":[-2.17320055749574,52.94292613501606],"type":"Point"}
}