{
  "type": "Feature",
  "properties": {
    "iso:country":"GB",
    "wof:name":"DG2 9DT",
    "wof:placetype":"postalcode"
},
  "geometry": {"coordinates":[-3.62906245443781,55.07015873462288],"type":"Point"}
}