{
  "type": "Feature",
  "properties": {
    "iso:country":"GB",
    "wof:name":"SN12 8HD",
    "wof:placetype":"postalcode"
},
  "geometry": {"coordinates":[-2.18067012513522,51.39274590464332],"type":"Point"}
}