{
  "type": "Feature",
  "properties": {
    "iso:country": "GB",
    "wof:name": "SN12 8HD",
    "wof:placetype": "postalcode"
  },
  "geometry": {"coordinates":[-2.18067,51.392746],"type":"Point"}
}
