{
  "type": "Feature",
  "properties": {
    "date:inception_lower": "1996-06-01",
    "date:inception_upper": "1996-06-01",
    "iso:country": "GB",
    "wof:name": "M14 6ZT",
    "wof:placetype": "postalcode"
  },
  "geometry": {"coordinates":[-2.212576,53.441799],"type":"Point"}
}
