{
  "type": "Feature",
  "properties": {
    "iso:country":"GB",
    "wof:name":"M14 6ZT",
    "wof:placetype":"postalcode"
},
  "geometry": {"coordinates":[-2.21257610960794,53.44179944700294],"type":"Point"}
}