{
  "type": "Feature",
  "properties": {
    "iso:country":"GB",
    "wof:name":"LS17 8TW",
    "wof:placetype":"postalcode"
},
  "geometry": {"coordinates":[-1.50026146418093,53.85602378121997],"type":"Point"}
}