{
  "type": "Feature",
  "properties": {
    "iso:country": "GB",
    "wof:name": "BL3 5HH",
    "wof:placetype": "postalcode"
  },
  "geometry": {"coordinates":[-2.448215,53.572244],"type":"Point"}
}
