{
  "type": "Feature",
  "properties": {
    "iso:country":"GB",
    "wof:name":"BL3 5HH",
    "wof:placetype":"postalcode"
},
  "geometry": {"coordinates":[-2.44821533568713,53.57224416162118],"type":"Point"}
}