{
  "type": "Feature",
  "properties": {
    "date:inception_lower": "1980-01-01",
    "date:inception_upper": "1980-01-01",
    "iso:country": "GB",
    "wof:name": "DA5 3LG",
    "wof:placetype": "postalcode"
  },
  "geometry": {"coordinates":[0.127257,51.438742],"type":"Point"}
}
