{
  "type": "Feature",
  "properties": {
    "date:inception_lower": "2000-12-01",
    "date:inception_upper": "2000-12-01",
    "iso:country": "GB",
    "wof:name": "LA14 5UW",
    "wof:placetype": "postalcode"
  },
  "geometry": {"coordinates":[-3.235963,54.123382],"type":"Point"}
}
