{
  "type": "Feature",
  "properties": {
    "date:inception_lower":"2000-12-01",
    "date:inception_upper":"2000-12-31",
    "iso:country":"GB",
    "wof:name":"LA14 5UW",
    "wof:placetype":"postalcode"
},
  "geometry": {"coordinates":[-3.235026,54.123653],"type":"Point"}
}