{
  "type": "Feature",
  "properties": {
    "iso:country": "GB",
    "wof:name": "OL12 0RZ",
    "wof:placetype": "postalcode"
  },
  "geometry": {"coordinates":[-2.159535,53.625038],"type":"Point"}
}
