{
  "type": "Feature",
  "properties": {
    "iso:country":"GB",
    "wof:name":"TS11 8JY",
    "wof:placetype":"postalcode"
},
  "geometry": {"coordinates":[-1.04747513128214,54.57881850855744],"type":"Point"}
}