{
  "type": "Feature",
  "properties": {
    "iso:country":"GB",
    "wof:name":"PE25 1SP",
    "wof:placetype":"postalcode"
},
  "geometry": {"coordinates":[0.32415356870812,53.15849105858643],"type":"Point"}
}