{
  "type": "Feature",
  "properties": {
    "iso:country": "GB",
    "wof:name": "PE25 1SP",
    "wof:placetype": "postalcode"
  },
  "geometry": {"coordinates":[0.324154,53.158491],"type":"Point"}
}
