{
  "type": "Feature",
  "properties": {
    "date:inception_lower": "1997-06-01",
    "date:inception_upper": "1997-06-01",
    "iso:country": "GB",
    "wof:name": "PE25 1SP",
    "wof:placetype": "postalcode"
  },
  "geometry": {"coordinates":[0.324154,53.158491],"type":"Point"}
}
