{
  "type": "Feature",
  "properties": {
    "date:inception_lower": "1983-07-01",
    "date:inception_upper": "1983-07-01",
    "iso:country": "GB",
    "wof:name": "CV2 2PU",
    "wof:placetype": "postalcode"
  },
  "geometry": {"coordinates":[-1.440233,52.432322],"type":"Point"}
}
