{
  "type": "Feature",
  "properties": {
    "iso:country":"GB",
    "wof:name":"CV2 2PU",
    "wof:placetype":"postalcode"
},
  "geometry": {"coordinates":[-1.44023297474417,52.43232229357563],"type":"Point"}
}