{
  "type": "Feature",
  "properties": {
    "iso:country":"GB",
    "wof:name":"GL7 5UP",
    "wof:placetype":"postalcode"
},
  "geometry": {"coordinates":[-1.93463530534788,51.67073821333682],"type":"Point"}
}