{
  "type": "Feature",
  "properties": {
    "iso:country": "GB",
    "wof:name": "CM2 7AD",
    "wof:placetype": "postalcode"
  },
  "geometry": {"coordinates":[0.513849,51.709996],"type":"Point"}
}
