{
  "type": "Feature",
  "properties": {
    "iso:country":"GB",
    "wof:name":"CM2 7AD",
    "wof:placetype":"postalcode"
},
  "geometry": {"coordinates":[0.51384925866706,51.70999617108234],"type":"Point"}
}