{
  "type": "Feature",
  "properties": {
    "iso:country":"GB",
    "wof:name":"CH46 7TT",
    "wof:placetype":"postalcode"
},
  "geometry": {"coordinates":[-3.1151078312015,53.40361247087213],"type":"Point"}
}