{
  "type": "Feature",
  "properties": {
    "iso:country":"GB",
    "wof:name":"YO25 3HZ",
    "wof:placetype":"postalcode"
},
  "geometry": {"coordinates":[-0.32247620966517,54.12738377895075],"type":"Point"}
}