{
  "type": "Feature",
  "properties": {
    "iso:country":"GB",
    "wof:name":"EX38 7JX",
    "wof:placetype":"postalcode"
},
  "geometry": {"coordinates":[-4.08087542294812,50.96285369724433],"type":"Point"}
}