{
  "type": "Feature",
  "properties": {
    "date:inception_lower": "1994-12-01",
    "date:inception_upper": "1994-12-01",
    "iso:country": "GB",
    "wof:name": "BL9 0DP",
    "wof:placetype": "postalcode"
  },
  "geometry": {"coordinates":[-2.299564,53.591773],"type":"Point"}
}
