{
  "type": "Feature",
  "properties": {
    "iso:country":"GB",
    "wof:name":"BL9 0DP",
    "wof:placetype":"postalcode"
},
  "geometry": {"coordinates":[-2.2995643702193,53.5917732812182],"type":"Point"}
}