{
  "type": "Feature",
  "properties": {
    "iso:country": "GB",
    "wof:name": "IP12 4LQ",
    "wof:placetype": "postalcode"
  },
  "geometry": {"coordinates":[1.297989,52.0978],"type":"Point"}
}
