{
  "type": "Feature",
  "properties": {
    "iso:country":"GB",
    "wof:name":"EN5 2HA",
    "wof:placetype":"postalcode"
},
  "geometry": {"coordinates":[-0.197540878461,51.64749546491849],"type":"Point"}
}