{
  "type": "Feature",
  "properties": {
    "iso:country":"GB",
    "wof:name":"BS21 7EW",
    "wof:placetype":"postalcode"
},
  "geometry": {"coordinates":[-2.85735122357281,51.44449871093605],"type":"Point"}
}