{
  "type": "Feature",
  "properties": {
    "iso:country":"GB",
    "wof:name":"CM9 5FW",
    "wof:placetype":"postalcode"
},
  "geometry": {"coordinates":[0.67787515994387,51.73075153775577],"type":"Point"}
}