{
  "type": "Feature",
  "properties": {
    "iso:country": "GB",
    "wof:name": "CM9 5FW",
    "wof:placetype": "postalcode"
  },
  "geometry": {"coordinates":[0.677875,51.730752],"type":"Point"}
}
