{
  "type": "Feature",
  "properties": {
    "iso:country": "GB",
    "wof:name": "N1 0UJ",
    "wof:placetype": "postalcode"
  },
  "geometry": {"coordinates":[-0.120939,51.53852],"type":"Point"}
}
