{
  "type": "Feature",
  "properties": {
    "date:inception_lower": "1981-06-01",
    "date:inception_upper": "1981-06-01",
    "iso:country": "GB",
    "wof:name": "N1 0UJ",
    "wof:placetype": "postalcode"
  },
  "geometry": {"coordinates":[-0.120939,51.53852],"type":"Point"}
}
