{
  "type": "Feature",
  "properties": {
    "iso:country":"GB",
    "wof:name":"N1 0UJ",
    "wof:placetype":"postalcode"
},
  "geometry": {"coordinates":[-0.12093898570198,51.53852043657301],"type":"Point"}
}