{
  "type": "Feature",
  "properties": {
    "iso:country": "GB",
    "wof:name": "SL4 1HF",
    "wof:placetype": "postalcode"
  },
  "geometry": {"coordinates":[-0.606653,51.478915],"type":"Point"}
}
