{
  "type": "Feature",
  "properties": {
    "iso:country":"GB",
    "wof:name":"SL4 1HF",
    "wof:placetype":"postalcode"
},
  "geometry": {"coordinates":[-0.60665284254562,51.47891479516626],"type":"Point"}
}