{
  "type": "Feature",
  "properties": {
    "iso:country":"GB",
    "wof:name":"BH11 9LD",
    "wof:placetype":"postalcode"
},
  "geometry": {"coordinates":[-1.92262631679557,50.76632556211662],"type":"Point"}
}