{
  "type": "Feature",
  "properties": {
    "date:inception_lower": "2000-06-01",
    "date:inception_upper": "2000-06-01",
    "iso:country": "GB",
    "wof:name": "SN25 3DD",
    "wof:placetype": "postalcode"
  },
  "geometry": {"coordinates":[-1.794921,51.58401],"type":"Point"}
}
