{
  "type": "Feature",
  "properties": {
    "iso:country":"GB",
    "wof:name":"BS49 4EX",
    "wof:placetype":"postalcode"
},
  "geometry": {"coordinates":[-2.82202914550681,51.38295112315716],"type":"Point"}
}