{
  "type": "Feature",
  "properties": {
    "iso:country":"GB",
    "wof:name":"SW2 3LT",
    "wof:placetype":"postalcode"
},
  "geometry": {"coordinates":[-0.12276921271648,51.44737422348265],"type":"Point"}
}