{
  "type": "Feature",
  "properties": {
    "iso:country": "GB",
    "wof:name": "SW2 3LT",
    "wof:placetype": "postalcode"
  },
  "geometry": {"coordinates":[-0.122769,51.447374],"type":"Point"}
}
