{
  "type": "Feature",
  "properties": {
    "iso:country":"GB",
    "wof:name":"LA1 1NN",
    "wof:placetype":"postalcode"
},
  "geometry": {"coordinates":[-2.79735939863502,54.05019788907166],"type":"Point"}
}