{
  "type": "Feature",
  "properties": {
    "iso:country": "GB",
    "wof:name": "NN13 5SQ",
    "wof:placetype": "postalcode"
  },
  "geometry": {"coordinates":[-1.145904,52.009345],"type":"Point"}
}
