{
  "type": "Feature",
  "properties": {
    "iso:country":"GB",
    "wof:name":"GL5 3SD",
    "wof:placetype":"postalcode"
},
  "geometry": {"coordinates":[-2.22363729068269,51.74095265456069],"type":"Point"}
}