{
  "type": "Feature",
  "properties": {
    "iso:country":"GB",
    "wof:name":"MK18 1AD",
    "wof:placetype":"postalcode"
},
  "geometry": {"coordinates":[-0.98144370032301,51.99386794347567],"type":"Point"}
}