{
  "type": "Feature",
  "properties": {
    "iso:country":"GB",
    "wof:name":"OX17 2PJ",
    "wof:placetype":"postalcode"
},
  "geometry": {"coordinates":[-1.26905594290941,52.06678804625746],"type":"Point"}
}