{
  "type": "Feature",
  "properties": {
    "iso:country": "GB",
    "wof:name": "OX17 2PJ",
    "wof:placetype": "postalcode"
  },
  "geometry": {"coordinates":[-1.269056,52.066788],"type":"Point"}
}
