{
  "type": "Feature",
  "properties": {
    "iso:country":"GB",
    "wof:name":"TF2 8QL",
    "wof:placetype":"postalcode"
},
  "geometry": {"coordinates":[-2.43846237293211,52.72745714755391],"type":"Point"}
}