{
  "type": "Feature",
  "properties": {
    "iso:country":"GB",
    "wof:name":"EX16 9BJ",
    "wof:placetype":"postalcode"
},
  "geometry": {"coordinates":[-3.42502111899212,51.00628868228336],"type":"Point"}
}