{
  "type": "Feature",
  "properties": {
    "iso:country":"GB",
    "wof:name":"DA16 1SP",
    "wof:placetype":"postalcode"
},
  "geometry": {"coordinates":[0.11656797875961,51.46212799569263],"type":"Point"}
}