{
  "type": "Feature",
  "properties": {
    "date:inception_lower": "2017-04-01",
    "date:inception_upper": "2017-04-01",
    "iso:country": "GB",
    "wof:name": "ML10 6XL",
    "wof:placetype": "postalcode"
  },
  "geometry": {"coordinates":[-4.08414,55.674667],"type":"Point"}
}
