{
  "type": "Feature",
  "properties": {
    "iso:country": "GB",
    "wof:name": "SY6 6AD",
    "wof:placetype": "postalcode"
  },
  "geometry": {"coordinates":[-2.817667,52.533242],"type":"Point"}
}
