{
  "type": "Feature",
  "properties": {
    "iso:country":"GB",
    "wof:name":"HU5 3DP",
    "wof:placetype":"postalcode"
},
  "geometry": {"coordinates":[-0.36441842825672,53.75910320952245],"type":"Point"}
}