{
  "type": "Feature",
  "properties": {
    "iso:country":"GB",
    "wof:name":"M41 8PW",
    "wof:placetype":"postalcode"
},
  "geometry": {"coordinates":[-2.38719083915705,53.45468176901576],"type":"Point"}
}