{
  "type": "Feature",
  "properties": {
    "date:inception_lower": "2020-01-01",
    "date:inception_upper": "2020-01-01",
    "iso:country": "GB",
    "wof:name": "NP12 3PN",
    "wof:placetype": "postalcode"
  },
  "geometry": {"coordinates":[-3.215176,51.665792],"type":"Point"}
}
