{
  "type": "Feature",
  "properties": {
    "date:inception_lower": "2005-07-01",
    "date:inception_upper": "2005-07-01",
    "iso:country": "GB",
    "wof:name": "TQ5 0BJ",
    "wof:placetype": "postalcode"
  },
  "geometry": {"coordinates":[-3.577815,50.382048],"type":"Point"}
}
