{
  "type": "Feature",
  "properties": {
    "iso:country":"GB",
    "wof:name":"TQ5 0BJ",
    "wof:placetype":"postalcode"
},
  "geometry": {"coordinates":[-3.57771516681223,50.38210067831533],"type":"Point"}
}