{
  "type": "Feature",
  "properties": {
    "date:inception_lower": "2003-11-01",
    "date:inception_upper": "2003-11-01",
    "iso:country": "GB",
    "wof:name": "NW1 8AP",
    "wof:placetype": "postalcode"
  },
  "geometry": {"coordinates":[-0.151074,51.543576],"type":"Point"}
}
