{
  "type": "Feature",
  "properties": {
    "iso:country":"GB",
    "wof:name":"NW1 8AP",
    "wof:placetype":"postalcode"
},
  "geometry": {"coordinates":[-0.15107382141255,51.54357641173618],"type":"Point"}
}