{
  "type": "Feature",
  "properties": {
    "iso:country": "GB",
    "wof:name": "EX3 0JL",
    "wof:placetype": "postalcode"
  },
  "geometry": {"coordinates":[-3.466411,50.68324],"type":"Point"}
}
