{
  "type": "Feature",
  "properties": {
    "iso:country":"GB",
    "wof:name":"SS4 1LE",
    "wof:placetype":"postalcode"
},
  "geometry": {"coordinates":[0.71906072578804,51.57322748414101],"type":"Point"}
}