{
  "type": "Feature",
  "properties": {
    "iso:country":"GB",
    "wof:name":"BR6 9RF",
    "wof:placetype":"postalcode"
},
  "geometry": {"coordinates":[0.08450344194773,51.37068709773668],"type":"Point"}
}