{
  "type": "Feature",
  "properties": {
    "iso:country":"GB",
    "wof:name":"NR8 6LY",
    "wof:placetype":"postalcode"
},
  "geometry": {"coordinates":[1.20558951161708,52.68324955119714],"type":"Point"}
}