{
  "type": "Feature",
  "properties": {
    "iso:country":"GB",
    "wof:name":"GL3 1AY",
    "wof:placetype":"postalcode"
},
  "geometry": {"coordinates":[-2.21259262070842,51.88686105284457],"type":"Point"}
}