{
  "type": "Feature",
  "properties": {
    "iso:country":"GB",
    "wof:name":"HP21 8NN",
    "wof:placetype":"postalcode"
},
  "geometry": {"coordinates":[-0.81732743989614,51.80678115126245],"type":"Point"}
}