{
  "type": "Feature",
  "properties": {
    "iso:country": "GB",
    "wof:name": "PE2 7BB",
    "wof:placetype": "postalcode"
  },
  "geometry": {"coordinates":[-0.268819,52.556516],"type":"Point"}
}
