{
  "type": "Feature",
  "properties": {
    "iso:country":"GB",
    "wof:name":"PE2 7BB",
    "wof:placetype":"postalcode"
},
  "geometry": {"coordinates":[-0.26881920051616,52.55651570312185],"type":"Point"}
}