{
  "type": "Feature",
  "properties": {
    "iso:country":"GB",
    "wof:name":"N9 7QB",
    "wof:placetype":"postalcode"
},
  "geometry": {"coordinates":[-0.05698296796987,51.63095567102],"type":"Point"}
}