{
  "type": "Feature",
  "properties": {
    "iso:country":"GB",
    "wof:name":"TQ13 0EY",
    "wof:placetype":"postalcode"
},
  "geometry": {"coordinates":[-3.6343441515035,50.58514345986722],"type":"Point"}
}