{
  "type": "Feature",
  "properties": {
    "iso:country": "GB",
    "wof:name": "TQ13 0EY",
    "wof:placetype": "postalcode"
  },
  "geometry": {"coordinates":[-3.634344,50.585143],"type":"Point"}
}
