{
  "type": "Feature",
  "properties": {
    "date:inception_lower":"1980-01-01",
    "date:inception_upper":"1980-01-31",
    "iso:country":"GB",
    "wof:name":"SY23 1RW",
    "wof:placetype":"postalcode"
},
  "geometry": {"coordinates":[-4.072147,52.401878],"type":"Point"}
}