{
  "type": "Feature",
  "properties": {
    "iso:country":"GB",
    "wof:name":"SY23 1RW",
    "wof:placetype":"postalcode"
},
  "geometry": {"coordinates":[-4.07214735561952,52.4018781533179],"type":"Point"}
}