{
  "type": "Feature",
  "properties": {
    "iso:country": "GB",
    "wof:name": "NG7 1UR",
    "wof:placetype": "postalcode"
  },
  "geometry": {"coordinates":[-1.171211,52.949004],"type":"Point"}
}
