{
  "type": "Feature",
  "properties": {
    "iso:country": "GB",
    "wof:name": "NG32 1DY",
    "wof:placetype": "postalcode"
  },
  "geometry": {"coordinates":[-0.72609,52.915614],"type":"Point"}
}
