{
  "type": "Feature",
  "properties": {
    "iso:country": "GB",
    "wof:name": "BL4 9LU",
    "wof:placetype": "postalcode"
  },
  "geometry": {"coordinates":[-2.399586,53.539753],"type":"Point"}
}
