{
  "type": "Feature",
  "properties": {
    "iso:country":"GB",
    "wof:name":"BL4 9LU",
    "wof:placetype":"postalcode"
},
  "geometry": {"coordinates":[-2.39958593426168,53.53975278690083],"type":"Point"}
}