{
  "type": "Feature",
  "properties": {
    "iso:country": "GB",
    "wof:name": "GL51 8BN",
    "wof:placetype": "postalcode"
  },
  "geometry": {"coordinates":[-2.101619,51.904046],"type":"Point"}
}
