{
  "type": "Feature",
  "properties": {
    "date:inception_lower": "1980-01-01",
    "date:inception_upper": "1980-01-01",
    "iso:country": "GB",
    "wof:name": "GL51 8BN",
    "wof:placetype": "postalcode"
  },
  "geometry": {"coordinates":[-2.101619,51.904046],"type":"Point"}
}
