{
  "type": "Feature",
  "properties": {
    "date:inception_lower": "2019-03-01",
    "date:inception_upper": "2019-03-01",
    "iso:country": "GB",
    "wof:name": "IP23 7FA",
    "wof:placetype": "postalcode"
  },
  "geometry": {"coordinates":[1.143366,52.330767],"type":"Point"}
}
