{
  "type": "Feature",
  "properties": {
    "iso:country":"GB",
    "wof:name":"GL54 2DG",
    "wof:placetype":"postalcode"
},
  "geometry": {"coordinates":[-1.76015178291777,51.88261992284592],"type":"Point"}
}