{
  "type": "Feature",
  "properties": {
    "date:inception_lower": "1992-08-01",
    "date:inception_upper": "1992-08-01",
    "iso:country": "GB",
    "wof:name": "OL1 3RB",
    "wof:placetype": "postalcode"
  },
  "geometry": {"coordinates":[-2.104962,53.549597],"type":"Point"}
}
