{
  "type": "Feature",
  "properties": {
    "iso:country":"GB",
    "wof:name":"OL1 3RB",
    "wof:placetype":"postalcode"
},
  "geometry": {"coordinates":[-2.10496190488421,53.54959696096099],"type":"Point"}
}