{
  "type": "Feature",
  "properties": {
    "iso:country":"GB",
    "wof:name":"N9 8LG",
    "wof:placetype":"postalcode"
},
  "geometry": {"coordinates":[-0.04977920956518,51.62911866405238],"type":"Point"}
}