{
  "type": "Feature",
  "properties": {
    "iso:country": "GB",
    "wof:name": "IP14 6SL",
    "wof:placetype": "postalcode"
  },
  "geometry": {"coordinates":[1.176369,52.221157],"type":"Point"}
}
