{
  "type": "Feature",
  "properties": {
    "iso:country":"GB",
    "wof:name":"MK4 1DB",
    "wof:placetype":"postalcode"
},
  "geometry": {"coordinates":[-0.7607982375014,52.00718247189439],"type":"Point"}
}