{
  "type": "Feature",
  "properties": {
    "iso:country":"GB",
    "wof:name":"LL11 0ZY",
    "wof:placetype":"postalcode"
},
  "geometry": {"coordinates":[-2.99386134238039,53.04747951438672],"type":"Point"}
}