{
  "type": "Feature",
  "properties": {
    "iso:country":"GB",
    "wof:name":"PE8 6LD",
    "wof:placetype":"postalcode"
},
  "geometry": {"coordinates":[-0.41764550062837,52.58683822606464],"type":"Point"}
}