{
  "type": "Feature",
  "properties": {
    "iso:country": "GB",
    "wof:name": "BS4 2JD",
    "wof:placetype": "postalcode"
  },
  "geometry": {"coordinates":[-2.566643,51.438028],"type":"Point"}
}
