{
  "type": "Feature",
  "properties": {
    "iso:country":"GB",
    "wof:name":"BS4 2JD",
    "wof:placetype":"postalcode"
},
  "geometry": {"coordinates":[-2.56664340543998,51.43802845330711],"type":"Point"}
}