{
  "type": "Feature",
  "properties": {
    "iso:country":"GB",
    "wof:name":"SO50 5QT",
    "wof:placetype":"postalcode"
},
  "geometry": {"coordinates":[-1.35291643316906,50.96222311373199],"type":"Point"}
}