{
  "type": "Feature",
  "properties": {
    "iso:country":"GB",
    "wof:name":"S26 2GQ",
    "wof:placetype":"postalcode"
},
  "geometry": {"coordinates":[-1.30537625519164,53.35650159698227],"type":"Point"}
}