{
  "type": "Feature",
  "properties": {
    "iso:country":"GB",
    "wof:name":"NE38 7TJ",
    "wof:placetype":"postalcode"
},
  "geometry": {"coordinates":[-1.52498819125991,54.89886208410964],"type":"Point"}
}