{
  "type": "Feature",
  "properties": {
    "iso:country": "GB",
    "wof:name": "BA3 4WS",
    "wof:placetype": "postalcode"
  },
  "geometry": {"coordinates":[-2.480583,51.274867],"type":"Point"}
}
