{
  "type": "Feature",
  "properties": {
    "date:inception_lower": "1980-01-01",
    "date:inception_upper": "1980-01-01",
    "iso:country": "GB",
    "wof:name": "DY12 1DD",
    "wof:placetype": "postalcode"
  },
  "geometry": {"coordinates":[-2.306859,52.377517],"type":"Point"}
}
