{
  "type": "Feature",
  "properties": {
    "iso:country":"GB",
    "wof:name":"DY12 1DD",
    "wof:placetype":"postalcode"
},
  "geometry": {"coordinates":[-2.30685934550251,52.37751735620822],"type":"Point"}
}