{
  "type": "Feature",
  "properties": {
    "iso:country": "GB",
    "wof:name": "DY12 2PZ",
    "wof:placetype": "postalcode"
  },
  "geometry": {"coordinates":[-2.32965,52.378337],"type":"Point"}
}
