{
  "type": "Feature",
  "properties": {
    "date:inception_lower": "1980-01-01",
    "date:inception_upper": "1980-01-01",
    "iso:country": "GB",
    "wof:name": "DY12 2PZ",
    "wof:placetype": "postalcode"
  },
  "geometry": {"coordinates":[-2.329602,52.378342],"type":"Point"}
}
