{
  "type": "Feature",
  "properties": {
    "iso:country":"GB",
    "wof:name":"DY12 2PZ",
    "wof:placetype":"postalcode"
},
  "geometry": {"coordinates":[-2.32964971732023,52.37833697783346],"type":"Point"}
}