{
  "type": "Feature",
  "properties": {
    "date:inception_lower":"2018-09-01",
    "date:inception_upper":"2018-09-30",
    "iso:country":"GB",
    "wof:name":"M43 7FW",
    "wof:placetype":"postalcode"
},
  "geometry": {"coordinates":[-2.147167,53.477841],"type":"Point"}
}