{
  "type": "Feature",
  "properties": {
    "iso:country": "GB",
    "wof:name": "M43 7FW",
    "wof:placetype": "postalcode"
  },
  "geometry": {"coordinates":[-2.147167,53.477841],"type":"Point"}
}
