{
  "type": "Feature",
  "properties": {
    "date:inception_lower": "2018-09-01",
    "date:inception_upper": "2018-09-01",
    "iso:country": "GB",
    "wof:name": "M43 7FW",
    "wof:placetype": "postalcode"
  },
  "geometry": {"coordinates":[-2.147681,53.478335],"type":"Point"}
}
