{
  "type": "Feature",
  "properties": {
    "iso:country":"GB",
    "wof:name":"UB7 9DE",
    "wof:placetype":"postalcode"
},
  "geometry": {"coordinates":[-0.46915159314922,51.50700965469498],"type":"Point"}
}