{
  "type": "Feature",
  "properties": {
    "iso:country":"GB",
    "wof:name":"CH5 4TH",
    "wof:placetype":"postalcode"
},
  "geometry": {"coordinates":[-3.06967028606984,53.21228084806487],"type":"Point"}
}