{
  "type": "Feature",
  "properties": {
    "iso:country":"GB",
    "wof:name":"SN10 5UE",
    "wof:placetype":"postalcode"
},
  "geometry": {"coordinates":[-2.05299501537808,51.28966662584971],"type":"Point"}
}