{
  "type": "Feature",
  "properties": {
    "iso:country": "GB",
    "wof:name": "SN10 5UE",
    "wof:placetype": "postalcode"
  },
  "geometry": {"coordinates":[-2.052995,51.289667],"type":"Point"}
}
