{
  "type": "Feature",
  "properties": {
    "date:inception_lower":"1980-01-01",
    "date:inception_upper":"1980-01-31",
    "iso:country":"GB",
    "wof:name":"LE8 0QA",
    "wof:placetype":"postalcode"
},
  "geometry": {"coordinates":[-1.030925,52.521396],"type":"Point"}
}