{
  "type": "Feature",
  "properties": {
    "iso:country":"GB",
    "wof:name":"LE8 0QA",
    "wof:placetype":"postalcode"
},
  "geometry": {"coordinates":[-1.03092527261562,52.52139635265324],"type":"Point"}
}