{
  "type": "Feature",
  "properties": {
    "iso:country": "GB",
    "wof:name": "LL18 4JL",
    "wof:placetype": "postalcode"
  },
  "geometry": {"coordinates":[-3.468812,53.321585],"type":"Point"}
}
