{
  "type": "Feature",
  "properties": {
    "iso:country":"GB",
    "wof:name":"LL18 4JL",
    "wof:placetype":"postalcode"
},
  "geometry": {"coordinates":[-3.46881193379789,53.32158498943262],"type":"Point"}
}