{
  "type": "Feature",
  "properties": {
    "iso:country":"GB",
    "wof:name":"NR13 5PU",
    "wof:placetype":"postalcode"
},
  "geometry": {"coordinates":[1.43600457210305,52.61497255712314],"type":"Point"}
}