{
  "type": "Feature",
  "properties": {
    "iso:country": "GB",
    "wof:name": "WA15 7YA",
    "wof:placetype": "postalcode"
  },
  "geometry": {"coordinates":[-2.303034,53.390333],"type":"Point"}
}
