{
  "type": "Feature",
  "properties": {
    "date:inception_lower": "1980-01-01",
    "date:inception_upper": "1980-01-01",
    "iso:country": "GB",
    "wof:name": "NW11 9AB",
    "wof:placetype": "postalcode"
  },
  "geometry": {"coordinates":[-0.202629,51.576543],"type":"Point"}
}
