{
  "type": "Feature",
  "properties": {
    "iso:country": "GB",
    "wof:name": "PE37 7EQ",
    "wof:placetype": "postalcode"
  },
  "geometry": {"coordinates":[0.693493,52.643144],"type":"Point"}
}
