{
  "type": "Feature",
  "properties": {
    "iso:country":"GB",
    "wof:name":"DT4 8SB",
    "wof:placetype":"postalcode"
},
  "geometry": {"coordinates":[-2.45435320161202,50.60253382689132],"type":"Point"}
}