{
  "type": "Feature",
  "properties": {
    "iso:country":"GB",
    "wof:name":"SA18 3LG",
    "wof:placetype":"postalcode"
},
  "geometry": {"coordinates":[-4.0403213445187,51.7848832367162],"type":"Point"}
}