{
  "type": "Feature",
  "properties": {
    "iso:country": "GB",
    "wof:name": "BA2 1QQ",
    "wof:placetype": "postalcode"
  },
  "geometry": {"coordinates":[-2.405217,51.378724],"type":"Point"}
}
