{
  "type": "Feature",
  "properties": {
    "iso:country":"GB",
    "wof:name":"LL18 1NF",
    "wof:placetype":"postalcode"
},
  "geometry": {"coordinates":[-3.50166983093288,53.31625851859995],"type":"Point"}
}