{
  "type": "Feature",
  "properties": {
    "date:inception_lower":"1980-01-01",
    "date:inception_upper":"1980-01-31",
    "iso:country":"GB",
    "wof:name":"NE4 9AB",
    "wof:placetype":"postalcode"
},
  "geometry": {"coordinates":[-1.646707,54.975669],"type":"Point"}
}