{
  "type": "Feature",
  "properties": {
    "iso:country":"GB",
    "wof:name":"NE4 9AB",
    "wof:placetype":"postalcode"
},
  "geometry": {"coordinates":[-1.6467067512999,54.97566923905206],"type":"Point"}
}