{
  "type": "Feature",
  "properties": {
    "date:inception_lower":"1980-01-01",
    "date:inception_upper":"1980-01-31",
    "iso:country":"GB",
    "wof:name":"HP18 9NR",
    "wof:placetype":"postalcode"
},
  "geometry": {"coordinates":[-1.025174,51.825636],"type":"Point"}
}