{
  "type": "Feature",
  "properties": {
    "iso:country":"GB",
    "wof:name":"HP18 9NR",
    "wof:placetype":"postalcode"
},
  "geometry": {"coordinates":[-1.02515939282193,51.82564488320033],"type":"Point"}
}