{
  "type": "Feature",
  "properties": {
    "iso:country": "GB",
    "wof:name": "HP18 9NR",
    "wof:placetype": "postalcode"
  },
  "geometry": {"coordinates":[-1.025138,51.825651],"type":"Point"}
}
