{
  "type": "Feature",
  "properties": {
    "iso:country":"GB",
    "wof:name":"WS9 9AD",
    "wof:placetype":"postalcode"
},
  "geometry": {"coordinates":[-1.93084551637273,52.62797799561824],"type":"Point"}
}