{
  "type": "Feature",
  "properties": {
    "iso:country": "GB",
    "wof:name": "WS9 9AD",
    "wof:placetype": "postalcode"
  },
  "geometry": {"coordinates":[-1.930845,52.627978],"type":"Point"}
}
