{
  "type": "Feature",
  "properties": {
    "iso:country":"GB",
    "wof:name":"CF64 3LL",
    "wof:placetype":"postalcode"
},
  "geometry": {"coordinates":[-3.18459931914915,51.43372605215072],"type":"Point"}
}