{
  "type": "Feature",
  "properties": {
    "date:inception_lower": "1993-01-01",
    "date:inception_upper": "1993-01-01",
    "iso:country": "GB",
    "wof:name": "CF64 3LL",
    "wof:placetype": "postalcode"
  },
  "geometry": {"coordinates":[-3.184599,51.433726],"type":"Point"}
}
