{
  "type": "Feature",
  "properties": {
    "iso:country":"GB",
    "wof:name":"BR1 3JF",
    "wof:placetype":"postalcode"
},
  "geometry": {"coordinates":[0.02534353410957,51.41312804842922],"type":"Point"}
}