{
  "type": "Feature",
  "properties": {
    "iso:country":"GB",
    "wof:name":"GL52 8AS",
    "wof:placetype":"postalcode"
},
  "geometry": {"coordinates":[-2.05818421017303,51.94029171158223],"type":"Point"}
}