{
  "type": "Feature",
  "properties": {
    "iso:country":"GB",
    "wof:name":"B68 9SP",
    "wof:placetype":"postalcode"
},
  "geometry": {"coordinates":[-1.99103090495197,52.49269169694746],"type":"Point"}
}