{
  "type": "Feature",
  "properties": {
    "iso:country":"GB",
    "wof:name":"NN2 8QH",
    "wof:placetype":"postalcode"
},
  "geometry": {"coordinates":[-0.91622855956868,52.26944113688461],"type":"Point"}
}