{
  "type": "Feature",
  "properties": {
    "iso:country":"GB",
    "wof:name":"WF14 0EF",
    "wof:placetype":"postalcode"
},
  "geometry": {"coordinates":[-1.71460815354531,53.6811971728352],"type":"Point"}
}