{
  "type": "Feature",
  "properties": {
    "iso:country": "GB",
    "wof:name": "WF14 0EF",
    "wof:placetype": "postalcode"
  },
  "geometry": {"coordinates":[-1.714608,53.681197],"type":"Point"}
}
