{
  "type": "Feature",
  "properties": {
    "iso:country":"GB",
    "wof:name":"HG1 5EQ",
    "wof:placetype":"postalcode"
},
  "geometry": {"coordinates":[-1.5383281616679,53.99699781263553],"type":"Point"}
}