{
  "type": "Feature",
  "properties": {
    "iso:country":"GB",
    "wof:name":"NR10 4RF",
    "wof:placetype":"postalcode"
},
  "geometry": {"coordinates":[1.09259009538262,52.7437197983447],"type":"Point"}
}