{
  "type": "Feature",
  "properties": {
    "iso:country": "GB",
    "wof:name": "NR10 4RF",
    "wof:placetype": "postalcode"
  },
  "geometry": {"coordinates":[1.09259,52.74372],"type":"Point"}
}
