{
  "type": "Feature",
  "properties": {
    "date:inception_lower": "1996-12-01",
    "date:inception_upper": "1996-12-01",
    "iso:country": "GB",
    "wof:name": "HP22 4NT",
    "wof:placetype": "postalcode"
  },
  "geometry": {"coordinates":[-0.7698,51.871634],"type":"Point"}
}
