{
  "type": "Feature",
  "properties": {
    "iso:country":"GB",
    "wof:name":"M27 5QB",
    "wof:placetype":"postalcode"
},
  "geometry": {"coordinates":[-2.33719474644264,53.50219375214549],"type":"Point"}
}