{
  "type": "Feature",
  "properties": {
    "iso:country": "GB",
    "wof:name": "NN8 1DX",
    "wof:placetype": "postalcode"
  },
  "geometry": {"coordinates":[-0.688207,52.305312],"type":"Point"}
}
