{
  "type": "Feature",
  "properties": {
    "iso:country": "GB",
    "wof:name": "PL30 4AD",
    "wof:placetype": "postalcode"
  },
  "geometry": {"coordinates":[-4.70084,50.447928],"type":"Point"}
}
