{
  "type": "Feature",
  "properties": {
    "date:inception_lower":"1985-10-01",
    "date:inception_upper":"1985-10-31",
    "iso:country":"GB",
    "wof:name":"PL30 4AD",
    "wof:placetype":"postalcode"
},
  "geometry": {"coordinates":[-4.70084,50.447928],"type":"Point"}
}