{
  "type": "Feature",
  "properties": {
    "iso:country":"GB",
    "wof:name":"PL30 4AD",
    "wof:placetype":"postalcode"
},
  "geometry": {"coordinates":[-4.70084032124312,50.44792795912292],"type":"Point"}
}