{
  "type": "Feature",
  "properties": {
    "iso:country":"GB",
    "wof:name":"YO11 3RX",
    "wof:placetype":"postalcode"
},
  "geometry": {"coordinates":[-0.38343488501707,54.23415635947282],"type":"Point"}
}