{
  "type": "Feature",
  "properties": {
    "iso:country":"GB",
    "wof:name":"ME10 3AW",
    "wof:placetype":"postalcode"
},
  "geometry": {"coordinates":[0.75165778636355,51.33837550764577],"type":"Point"}
}