{
  "type": "Feature",
  "properties": {
    "iso:country": "GB",
    "wof:name": "ME10 3AW",
    "wof:placetype": "postalcode"
  },
  "geometry": {"coordinates":[0.75163,51.338352],"type":"Point"}
}
