{
  "type": "Feature",
  "properties": {
    "date:inception_lower":"1980-01-01",
    "date:inception_upper":"1980-01-31",
    "iso:country":"GB",
    "wof:name":"ME10 3AW",
    "wof:placetype":"postalcode"
},
  "geometry": {"coordinates":[0.75163,51.338352],"type":"Point"}
}