{
  "type": "Feature",
  "properties": {
    "date:inception_lower": "1980-01-01",
    "date:inception_upper": "1980-01-01",
    "iso:country": "GB",
    "wof:name": "LE16 9JG",
    "wof:placetype": "postalcode"
  },
  "geometry": {"coordinates":[-0.930087,52.466037],"type":"Point"}
}
