{
  "type": "Feature",
  "properties": {
    "iso:country":"GB",
    "wof:name":"LE16 9JG",
    "wof:placetype":"postalcode"
},
  "geometry": {"coordinates":[-0.93008718134751,52.46603747771448],"type":"Point"}
}