{
  "type": "Feature",
  "properties": {
    "iso:country":"GB",
    "wof:name":"LN8 5RU",
    "wof:placetype":"postalcode"
},
  "geometry": {"coordinates":[-0.24672789748793,53.3165454723465],"type":"Point"}
}