{
  "type": "Feature",
  "properties": {
    "iso:country": "GB",
    "wof:name": "HA7 4ZP",
    "wof:placetype": "postalcode"
  },
  "geometry": {"coordinates":[-0.30859,51.617058],"type":"Point"}
}
