{
  "type": "Feature",
  "properties": {
    "date:inception_lower": "1980-01-01",
    "date:inception_upper": "1980-01-01",
    "iso:country": "GB",
    "wof:name": "DL1 4XX",
    "wof:placetype": "postalcode"
  },
  "geometry": {"coordinates":[-1.505997,54.523909],"type":"Point"}
}
