{
  "type": "Feature",
  "properties": {
    "iso:country": "GB",
    "wof:name": "EX22 7RQ",
    "wof:placetype": "postalcode"
  },
  "geometry": {"coordinates":[-4.383318,50.899266],"type":"Point"}
}
