{
  "type": "Feature",
  "properties": {
    "iso:country":"GB",
    "wof:name":"EX22 7RQ",
    "wof:placetype":"postalcode"
},
  "geometry": {"coordinates":[-4.38331807806818,50.89926646555631],"type":"Point"}
}