{
  "type": "Feature",
  "properties": {
    "date:inception_lower": "2000-10-01",
    "date:inception_upper": "2000-10-01",
    "iso:country": "GB",
    "wof:name": "WD24 4EU",
    "wof:placetype": "postalcode"
  },
  "geometry": {"coordinates":[-0.389968,51.671261],"type":"Point"}
}
