{
  "type": "Feature",
  "properties": {
    "iso:country": "GB",
    "wof:name": "WD24 4EU",
    "wof:placetype": "postalcode"
  },
  "geometry": {"coordinates":[-0.389968,51.671261],"type":"Point"}
}
