{
  "type": "Feature",
  "properties": {
    "iso:country":"GB",
    "wof:name":"SP11 8NW",
    "wof:placetype":"postalcode"
},
  "geometry": {"coordinates":[-1.58499101938388,51.20947384711557],"type":"Point"}
}