{
  "type": "Feature",
  "properties": {
    "iso:country": "GB",
    "wof:name": "SP11 8NW",
    "wof:placetype": "postalcode"
  },
  "geometry": {"coordinates":[-1.584991,51.209474],"type":"Point"}
}
