{
  "type": "Feature",
  "properties": {
    "iso:country": "GB",
    "wof:name": "IP27 9AL",
    "wof:placetype": "postalcode"
  },
  "geometry": {"coordinates":[0.528491,52.406619],"type":"Point"}
}
