{
  "type": "Feature",
  "properties": {
    "date:inception_lower":"1980-01-01",
    "date:inception_upper":"1980-01-31",
    "iso:country":"GB",
    "wof:name":"GL50 1SS",
    "wof:placetype":"postalcode"
},
  "geometry": {"coordinates":[-2.083956,51.894961],"type":"Point"}
}