{
  "type": "Feature",
  "properties": {
    "iso:country":"GB",
    "wof:name":"GL50 1SS",
    "wof:placetype":"postalcode"
},
  "geometry": {"coordinates":[-2.08384683473936,51.89475563875796],"type":"Point"}
}