{
  "type": "Feature",
  "properties": {
    "iso:country": "GB",
    "wof:name": "GL50 1SS",
    "wof:placetype": "postalcode"
  },
  "geometry": {"coordinates":[-2.083956,51.894961],"type":"Point"}
}
