{
  "type": "Feature",
  "properties": {
    "iso:country":"GB",
    "wof:name":"L5 8XY",
    "wof:placetype":"postalcode"
},
  "geometry": {"coordinates":[-2.98848080903797,53.42153743155185],"type":"Point"}
}