{
  "type": "Feature",
  "properties": {
    "date:inception_lower": "1986-04-01",
    "date:inception_upper": "1986-04-01",
    "iso:country": "GB",
    "wof:name": "L5 8XY",
    "wof:placetype": "postalcode"
  },
  "geometry": {"coordinates":[-2.988481,53.421537],"type":"Point"}
}
