{
  "type": "Feature",
  "properties": {
    "date:inception_lower": "1996-06-01",
    "date:inception_upper": "1996-06-01",
    "iso:country": "GB",
    "wof:name": "B62 9QY",
    "wof:placetype": "postalcode"
  },
  "geometry": {"coordinates":[-2.045839,52.468752],"type":"Point"}
}
