{
  "type": "Feature",
  "properties": {
    "date:inception_lower": "1980-01-01",
    "date:inception_upper": "1980-01-01",
    "iso:country": "GB",
    "wof:name": "NE66 1RQ",
    "wof:placetype": "postalcode"
  },
  "geometry": {"coordinates":[-1.699337,55.406128],"type":"Point"}
}
