{
  "type": "Feature",
  "properties": {
    "iso:country":"GB",
    "wof:name":"NE66 1RQ",
    "wof:placetype":"postalcode"
},
  "geometry": {"coordinates":[-1.6993367524295,55.40612803726635],"type":"Point"}
}