{
  "type": "Feature",
  "properties": {
    "iso:country":"GB",
    "wof:name":"WA7 5ET",
    "wof:placetype":"postalcode"
},
  "geometry": {"coordinates":[-2.72420947021418,53.32846617022427],"type":"Point"}
}