{
  "type": "Feature",
  "properties": {
    "iso:country":"GB",
    "wof:name":"S60 5JQ",
    "wof:placetype":"postalcode"
},
  "geometry": {"coordinates":[-1.36198578193023,53.40101518352837],"type":"Point"}
}