{
  "type": "Feature",
  "properties": {
    "iso:country":"GB",
    "wof:name":"CO3 3UZ",
    "wof:placetype":"postalcode"
},
  "geometry": {"coordinates":[0.87822624070299,51.88762831785872],"type":"Point"}
}