{
  "type": "Feature",
  "properties": {
    "iso:country": "GB",
    "wof:name": "CO3 3UZ",
    "wof:placetype": "postalcode"
  },
  "geometry": {"coordinates":[0.878226,51.887628],"type":"Point"}
}
