{
  "type": "Feature",
  "properties": {
    "iso:country":"GB",
    "wof:name":"HD4 7BA",
    "wof:placetype":"postalcode"
},
  "geometry": {"coordinates":[-1.80735813361423,53.62056794339147],"type":"Point"}
}