{
  "type": "Feature",
  "properties": {
    "iso:country": "GB",
    "wof:name": "HD4 7BA",
    "wof:placetype": "postalcode"
  },
  "geometry": {"coordinates":[-1.807253,53.62061],"type":"Point"}
}
