{
  "type": "Feature",
  "properties": {
    "date:inception_lower": "1980-01-01",
    "date:inception_upper": "1980-01-01",
    "iso:country": "GB",
    "wof:name": "IG10 1HY",
    "wof:placetype": "postalcode"
  },
  "geometry": {"coordinates":[0.057548,51.653698],"type":"Point"}
}
