{
  "type": "Feature",
  "properties": {
    "date:inception_lower": "1990-02-01",
    "date:inception_upper": "1990-02-01",
    "iso:country": "GB",
    "wof:name": "PR3 1QR",
    "wof:placetype": "postalcode"
  },
  "geometry": {"coordinates":[-2.769375,53.896165],"type":"Point"}
}
