{
  "type": "Feature",
  "properties": {
    "date:inception_lower": "2005-11-01",
    "date:inception_upper": "2005-11-01",
    "iso:country": "GB",
    "wof:name": "M8 8EW",
    "wof:placetype": "postalcode"
  },
  "geometry": {"coordinates":[-2.251157,53.497147],"type":"Point"}
}
