{
  "type": "Feature",
  "properties": {
    "iso:country":"GB",
    "wof:name":"M8 8EW",
    "wof:placetype":"postalcode"
},
  "geometry": {"coordinates":[-2.25115657141644,53.49714743195755],"type":"Point"}
}