{
  "type": "Feature",
  "properties": {
    "iso:country":"GB",
    "wof:name":"DG11 1SF",
    "wof:placetype":"postalcode"
},
  "geometry": {"coordinates":[-3.52471188405659,55.15089336620674],"type":"Point"}
}