{
  "type": "Feature",
  "properties": {
    "iso:country": "GB",
    "wof:name": "BD4 9EG",
    "wof:placetype": "postalcode"
  },
  "geometry": {"coordinates":[-1.716031,53.778101],"type":"Point"}
}
