{
  "type": "Feature",
  "properties": {
    "iso:country": "GB",
    "wof:name": "NR33 8DF",
    "wof:placetype": "postalcode"
  },
  "geometry": {"coordinates":[1.69271,52.442896],"type":"Point"}
}
