{
  "type": "Feature",
  "properties": {
    "date:inception_lower": "1980-01-01",
    "date:inception_upper": "1980-01-01",
    "iso:country": "GB",
    "wof:name": "NR33 8DF",
    "wof:placetype": "postalcode"
  },
  "geometry": {"coordinates":[1.69271,52.442896],"type":"Point"}
}
