{
  "type": "Feature",
  "properties": {
    "iso:country":"GB",
    "wof:name":"NR33 8DF",
    "wof:placetype":"postalcode"
},
  "geometry": {"coordinates":[1.69271024436186,52.44289644726365],"type":"Point"}
}