{
  "type": "Feature",
  "properties": {
    "iso:country": "GB",
    "wof:name": "LE15 8QL",
    "wof:placetype": "postalcode"
  },
  "geometry": {"coordinates":[-0.6175,52.664204],"type":"Point"}
}
