{
  "type": "Feature",
  "properties": {
    "date:inception_lower":"2005-08-01",
    "date:inception_upper":"2005-08-31",
    "iso:country":"GB",
    "wof:name":"PO1 9AZ",
    "wof:placetype":"postalcode"
},
  "geometry": {"coordinates":[-1.088401,50.799149],"type":"Point"}
}