{
  "type": "Feature",
  "properties": {
    "date:inception_lower": "1980-01-01",
    "date:inception_upper": "1980-01-01",
    "iso:country": "GB",
    "wof:name": "B46 2NT",
    "wof:placetype": "postalcode"
  },
  "geometry": {"coordinates":[-1.634493,52.519349],"type":"Point"}
}
