{
  "type": "Feature",
  "properties": {
    "iso:country":"GB",
    "wof:name":"B46 2NT",
    "wof:placetype":"postalcode"
},
  "geometry": {"coordinates":[-1.63450159435762,52.51933199035064],"type":"Point"}
}