{
  "type": "Feature",
  "properties": {
    "iso:country": "GB",
    "wof:name": "B46 2NT",
    "wof:placetype": "postalcode"
  },
  "geometry": {"coordinates":[-1.634493,52.519349],"type":"Point"}
}
