{
  "type": "Feature",
  "properties": {
    "iso:country":"GB",
    "wof:name":"DL11 6HR",
    "wof:placetype":"postalcode"
},
  "geometry": {"coordinates":[-1.93031804810712,54.37872109863218],"type":"Point"}
}