{
  "type": "Feature",
  "properties": {
    "date:inception_lower": "1980-01-01",
    "date:inception_upper": "1980-01-01",
    "iso:country": "GB",
    "wof:name": "DL3 0LZ",
    "wof:placetype": "postalcode"
  },
  "geometry": {"coordinates":[-1.553042,54.542881],"type":"Point"}
}
