{
  "type": "Feature",
  "properties": {
    "iso:country":"GB",
    "wof:name":"DL3 0LZ",
    "wof:placetype":"postalcode"
},
  "geometry": {"coordinates":[-1.55304215944068,54.54288100428369],"type":"Point"}
}