{
  "type": "Feature",
  "properties": {
    "date:inception_lower": "1980-01-01",
    "date:inception_upper": "1980-01-01",
    "iso:country": "GB",
    "wof:name": "RH8 0RJ",
    "wof:placetype": "postalcode"
  },
  "geometry": {"coordinates":[0.025975,51.239246],"type":"Point"}
}
