{
  "type": "Feature",
  "properties": {
    "iso:country":"GB",
    "wof:name":"RH8 0RJ",
    "wof:placetype":"postalcode"
},
  "geometry": {"coordinates":[0.02742880152257,51.24097573713621],"type":"Point"}
}