{
  "type": "Feature",
  "properties": {
    "iso:country":"GB",
    "wof:name":"SR6 7EJ",
    "wof:placetype":"postalcode"
},
  "geometry": {"coordinates":[-1.36527975163906,54.95056013108795],"type":"Point"}
}