{
  "type": "Feature",
  "properties": {
    "date:inception_lower":"1980-01-01",
    "date:inception_upper":"1980-01-31",
    "iso:country":"GB",
    "wof:name":"SR6 7EJ",
    "wof:placetype":"postalcode"
},
  "geometry": {"coordinates":[-1.36528,54.95056],"type":"Point"}
}