{
  "type": "Feature",
  "properties": {
    "date:inception_lower":"1980-01-01",
    "date:inception_upper":"1980-01-31",
    "iso:country":"GB",
    "wof:name":"LN7 6PW",
    "wof:placetype":"postalcode"
},
  "geometry": {"coordinates":[-0.432852,53.470385],"type":"Point"}
}