{
  "type": "Feature",
  "properties": {
    "iso:country":"GB",
    "wof:name":"N16 6LR",
    "wof:placetype":"postalcode"
},
  "geometry": {"coordinates":[-0.06636803042591,51.56857695533969],"type":"Point"}
}