{
  "type": "Feature",
  "properties": {
    "iso:country": "GB",
    "wof:name": "TR8 5NS",
    "wof:placetype": "postalcode"
  },
  "geometry": {"coordinates":[-5.07225,50.379678],"type":"Point"}
}
