{
  "type": "Feature",
  "properties": {
    "iso:country":"GB",
    "wof:name":"TR8 5NS",
    "wof:placetype":"postalcode"
},
  "geometry": {"coordinates":[-5.07224969863978,50.37967787518858],"type":"Point"}
}