{
  "type": "Feature",
  "properties": {
    "date:inception_lower": "1995-07-01",
    "date:inception_upper": "1995-07-01",
    "iso:country": "GB",
    "wof:name": "L36 0YE",
    "wof:placetype": "postalcode"
  },
  "geometry": {"coordinates":[-2.821636,53.400025],"type":"Point"}
}
