{
  "type": "Feature",
  "properties": {
    "date:inception_lower": "2014-07-01",
    "date:inception_upper": "2014-07-01",
    "iso:country": "GB",
    "wof:name": "YO25 5AB",
    "wof:placetype": "postalcode"
  },
  "geometry": {"coordinates":[-0.433617,54.014412],"type":"Point"}
}
