{
  "type": "Feature",
  "properties": {
    "iso:country":"GB",
    "wof:name":"YO25 5AB",
    "wof:placetype":"postalcode"
},
  "geometry": {"coordinates":[-0.43361664848094,54.01441167013603],"type":"Point"}
}