{
  "type": "Feature",
  "properties": {
    "iso:country":"GB",
    "wof:name":"CM20 1SB",
    "wof:placetype":"postalcode"
},
  "geometry": {"coordinates":[0.07661743063934,51.77063329302236],"type":"Point"}
}