{
  "type": "Feature",
  "properties": {
    "date:inception_lower": "1990-02-01",
    "date:inception_upper": "1990-02-01",
    "iso:country": "GB",
    "wof:name": "LN6 7BX",
    "wof:placetype": "postalcode"
  },
  "geometry": {"coordinates":[-0.554003,53.221227],"type":"Point"}
}
