{
  "type": "Feature",
  "properties": {
    "iso:country":"GB",
    "wof:name":"LN6 7BX",
    "wof:placetype":"postalcode"
},
  "geometry": {"coordinates":[-0.55400224949629,53.2212229868184],"type":"Point"}
}