{
  "type": "Feature",
  "properties": {
    "iso:country":"GB",
    "wof:name":"TN34 1TF",
    "wof:placetype":"postalcode"
},
  "geometry": {"coordinates":[0.57738004952605,50.85941812380876],"type":"Point"}
}