{
  "type": "Feature",
  "properties": {
    "iso:country":"GB",
    "wof:name":"SN15 4BD",
    "wof:placetype":"postalcode"
},
  "geometry": {"coordinates":[-2.0560063335386,51.51213582400764],"type":"Point"}
}