{
  "type": "Feature",
  "properties": {
    "iso:country": "GB",
    "wof:name": "SP11 9SQ",
    "wof:placetype": "postalcode"
  },
  "geometry": {"coordinates":[-1.608886,51.25483],"type":"Point"}
}
