{
  "type": "Feature",
  "properties": {
    "iso:country": "GB",
    "wof:name": "WR11 8PU",
    "wof:placetype": "postalcode"
  },
  "geometry": {"coordinates":[-1.91869,52.136877],"type":"Point"}
}
