{
  "type": "Feature",
  "properties": {
    "iso:country":"GB",
    "wof:name":"AB30 1AN",
    "wof:placetype":"postalcode"
},
  "geometry": {"coordinates":[-2.46523301283274,56.83204490816121],"type":"Point"}
}