{
  "type": "Feature",
  "properties": {
    "iso:country": "GB",
    "wof:name": "AB30 1AN",
    "wof:placetype": "postalcode"
  },
  "geometry": {"coordinates":[-2.465233,56.832045],"type":"Point"}
}
