{
  "type": "Feature",
  "properties": {
    "date:inception_lower": "2020-09-01",
    "date:inception_upper": "2020-09-01",
    "iso:country": "GB",
    "wof:name": "SO16 8NG",
    "wof:placetype": "postalcode"
  },
  "geometry": {"coordinates":[-1.451115,50.952673],"type":"Point"}
}
