{
  "type": "Feature",
  "properties": {
    "iso:country": "GB",
    "wof:name": "HA9 0FR",
    "wof:placetype": "postalcode"
  },
  "geometry": {"coordinates":[-0.279056,51.55923],"type":"Point"}
}
