{
  "type": "Feature",
  "properties": {
    "iso:country": "GB",
    "wof:name": "CA11 9QY",
    "wof:placetype": "postalcode"
  },
  "geometry": {"coordinates":[-2.840317,54.757929],"type":"Point"}
}
