{
  "type": "Feature",
  "properties": {
    "iso:country":"GB",
    "wof:name":"CA11 9QY",
    "wof:placetype":"postalcode"
},
  "geometry": {"coordinates":[-2.84031731668329,54.75792918821176],"type":"Point"}
}