{
  "type": "Feature",
  "properties": {
    "iso:country":"GB",
    "wof:name":"PO18 0BS",
    "wof:placetype":"postalcode"
},
  "geometry": {"coordinates":[-0.78601458917656,50.87179070806855],"type":"Point"}
}