{
  "type": "Feature",
  "properties": {
    "iso:country":"GB",
    "wof:name":"WA13 0EQ",
    "wof:placetype":"postalcode"
},
  "geometry": {"coordinates":[-2.49596485351661,53.37984469424307],"type":"Point"}
}