{
  "type": "Feature",
  "properties": {
    "iso:country":"GB",
    "wof:name":"LS28 7ES",
    "wof:placetype":"postalcode"
},
  "geometry": {"coordinates":[-1.66310473799525,53.79285740482374],"type":"Point"}
}