{
  "type": "Feature",
  "properties": {
    "iso:country": "GB",
    "wof:name": "SE18 1ED",
    "wof:placetype": "postalcode"
  },
  "geometry": {"coordinates":[0.095716,51.489337],"type":"Point"}
}
