{
  "type": "Feature",
  "properties": {
    "iso:country":"GB",
    "wof:name":"SE18 1ED",
    "wof:placetype":"postalcode"
},
  "geometry": {"coordinates":[0.09571637181944,51.48933727362705],"type":"Point"}
}