{
  "type": "Feature",
  "properties": {
    "iso:country":"GB",
    "wof:name":"SK17 0ET",
    "wof:placetype":"postalcode"
},
  "geometry": {"coordinates":[-1.83628041592268,53.14521321554832],"type":"Point"}
}