{
  "type": "Feature",
  "properties": {
    "date:inception_lower": "2019-11-01",
    "date:inception_upper": "2019-11-01",
    "iso:country": "GB",
    "wof:name": "EH48 3EG",
    "wof:placetype": "postalcode"
  },
  "geometry": {"coordinates":[-3.80107,55.886288],"type":"Point"}
}
