{
  "type": "Feature",
  "properties": {
    "iso:country":"GB",
    "wof:name":"NE3 2AZ",
    "wof:placetype":"postalcode"
},
  "geometry": {"coordinates":[-1.64700787158034,55.01972952840787],"type":"Point"}
}