{
  "type": "Feature",
  "properties": {
    "iso:country":"GB",
    "wof:name":"PO13 9AS",
    "wof:placetype":"postalcode"
},
  "geometry": {"coordinates":[-1.19176952316598,50.7944966095689],"type":"Point"}
}