{
  "type": "Feature",
  "properties": {
    "iso:country": "GB",
    "wof:name": "PO13 9AS",
    "wof:placetype": "postalcode"
  },
  "geometry": {"coordinates":[-1.191769,50.794497],"type":"Point"}
}
