{
  "type": "Feature",
  "properties": {
    "iso:country": "GB",
    "wof:name": "YO42 2XJ",
    "wof:placetype": "postalcode"
  },
  "geometry": {"coordinates":[-0.790494,53.93245],"type":"Point"}
}
