{
  "type": "Feature",
  "properties": {
    "iso:country":"GB",
    "wof:name":"YO42 2XJ",
    "wof:placetype":"postalcode"
},
  "geometry": {"coordinates":[-0.79049454597378,53.93245049651939],"type":"Point"}
}