{
  "type": "Feature",
  "properties": {
    "date:inception_lower": "2018-07-01",
    "date:inception_upper": "2018-07-01",
    "iso:country": "GB",
    "wof:name": "YO32 4AA",
    "wof:placetype": "postalcode"
  },
  "geometry": {"coordinates":[-1.07545,53.989736],"type":"Point"}
}
