{
  "type": "Feature",
  "properties": {
    "iso:country":"GB",
    "wof:name":"ST4 4DT",
    "wof:placetype":"postalcode"
},
  "geometry": {"coordinates":[-2.18328166803287,53.00077460224707],"type":"Point"}
}