{
  "type": "Feature",
  "properties": {
    "date:inception_lower": "1998-12-01",
    "date:inception_upper": "1998-12-01",
    "iso:country": "GB",
    "wof:name": "WN4 0RB",
    "wof:placetype": "postalcode"
  },
  "geometry": {"coordinates":[-2.666565,53.49566],"type":"Point"}
}
