{
  "type": "Feature",
  "properties": {
    "iso:country":"GB",
    "wof:name":"TA21 8NA",
    "wof:placetype":"postalcode"
},
  "geometry": {"coordinates":[-3.23194634347945,50.97950126804854],"type":"Point"}
}