{
  "type": "Feature",
  "properties": {
    "iso:country": "GB",
    "wof:name": "TA21 8NA",
    "wof:placetype": "postalcode"
  },
  "geometry": {"coordinates":[-3.231946,50.979501],"type":"Point"}
}
