{
  "type": "Feature",
  "properties": {
    "date:inception_lower": "2017-02-01",
    "date:inception_upper": "2017-02-01",
    "iso:country": "GB",
    "wof:name": "SP9 7TH",
    "wof:placetype": "postalcode"
  },
  "geometry": {"coordinates":[-1.662636,51.227694],"type":"Point"}
}
