{
  "type": "Feature",
  "properties": {
    "iso:country":"GB",
    "wof:name":"TN27 9PJ",
    "wof:placetype":"postalcode"
},
  "geometry": {"coordinates":[0.61146533191499,51.1792205373962],"type":"Point"}
}