{
  "type": "Feature",
  "properties": {
    "iso:country":"GB",
    "wof:name":"LS24 9FF",
    "wof:placetype":"postalcode"
},
  "geometry": {"coordinates":[-1.27117073623684,53.88380219833303],"type":"Point"}
}