{
  "type": "Feature",
  "properties": {
    "date:inception_lower":"2016-03-01",
    "date:inception_upper":"2016-03-31",
    "iso:country":"GB",
    "wof:name":"LS24 9FF",
    "wof:placetype":"postalcode"
},
  "geometry": {"coordinates":[-1.319337,53.899031],"type":"Point"}
}