{
  "type": "Feature",
  "properties": {
    "iso:country":"GB",
    "wof:name":"S72 0EB",
    "wof:placetype":"postalcode"
},
  "geometry": {"coordinates":[-1.34496376852453,53.55052054083425],"type":"Point"}
}