{
  "type": "Feature",
  "properties": {
    "iso:country": "GB",
    "wof:name": "S72 0EB",
    "wof:placetype": "postalcode"
  },
  "geometry": {"coordinates":[-1.344964,53.550521],"type":"Point"}
}
