{
  "type": "Feature",
  "properties": {
    "iso:country":"GB",
    "wof:name":"NG34 8ED",
    "wof:placetype":"postalcode"
},
  "geometry": {"coordinates":[-0.49527702239041,53.04479883751812],"type":"Point"}
}