{
  "type": "Feature",
  "properties": {
    "iso:country":"GB",
    "wof:name":"S43 1EA",
    "wof:placetype":"postalcode"
},
  "geometry": {"coordinates":[-1.39045365285687,53.25899684209379],"type":"Point"}
}