{
  "type": "Feature",
  "properties": {
    "iso:country": "GB",
    "wof:name": "SY8 3LT",
    "wof:placetype": "postalcode"
  },
  "geometry": {"coordinates":[-2.615846,52.369775],"type":"Point"}
}
