{
  "type": "Feature",
  "properties": {
    "date:inception_lower":"2001-06-01",
    "date:inception_upper":"2001-06-30",
    "iso:country":"GB",
    "wof:name":"SY8 3LT",
    "wof:placetype":"postalcode"
},
  "geometry": {"coordinates":[-2.615846,52.369775],"type":"Point"}
}