{
  "type": "Feature",
  "properties": {
    "iso:country":"GB",
    "wof:name":"WF15 6BE",
    "wof:placetype":"postalcode"
},
  "geometry": {"coordinates":[-1.68279220135063,53.70836928657842],"type":"Point"}
}