{
  "type": "Feature",
  "properties": {
    "iso:country": "GB",
    "wof:name": "OX25 1AF",
    "wof:placetype": "postalcode"
  },
  "geometry": {"coordinates":[-1.085931,51.849589],"type":"Point"}
}
