{
  "type": "Feature",
  "properties": {
    "date:inception_lower": "2020-02-01",
    "date:inception_upper": "2020-02-01",
    "iso:country": "GB",
    "wof:name": "OX25 1AF",
    "wof:placetype": "postalcode"
  },
  "geometry": {"coordinates":[-1.113492,51.853],"type":"Point"}
}
