{
  "type": "Feature",
  "properties": {
    "date:inception_lower":"2006-07-01",
    "date:inception_upper":"2006-07-31",
    "iso:country":"GB",
    "wof:name":"SY23 2AL",
    "wof:placetype":"postalcode"
},
  "geometry": {"coordinates":[-4.078696,52.417337],"type":"Point"}
}