{
  "type": "Feature",
  "properties": {
    "iso:country":"GB",
    "wof:name":"SY23 2AL",
    "wof:placetype":"postalcode"
},
  "geometry": {"coordinates":[-4.07869573432676,52.41733654666314],"type":"Point"}
}