{
  "type": "Feature",
  "properties": {
    "iso:country":"GB",
    "wof:name":"SL6 2JH",
    "wof:placetype":"postalcode"
},
  "geometry": {"coordinates":[-0.73143685388217,51.49120217492885],"type":"Point"}
}