{
  "type": "Feature",
  "properties": {
    "iso:country": "GB",
    "wof:name": "SL6 2JH",
    "wof:placetype": "postalcode"
  },
  "geometry": {"coordinates":[-0.731437,51.491202],"type":"Point"}
}
