{
  "type": "Feature",
  "properties": {
    "iso:country":"GB",
    "wof:name":"DN12 1PN",
    "wof:placetype":"postalcode"
},
  "geometry": {"coordinates":[-1.19791388983156,53.47594519007689],"type":"Point"}
}