{
  "type": "Feature",
  "properties": {
    "date:inception_lower": "1993-08-01",
    "date:inception_upper": "1993-08-01",
    "iso:country": "GB",
    "wof:name": "NN12 6BH",
    "wof:placetype": "postalcode"
  },
  "geometry": {"coordinates":[-0.991501,52.121797],"type":"Point"}
}
