{
  "type": "Feature",
  "properties": {
    "iso:country":"GB",
    "wof:name":"NN12 6BH",
    "wof:placetype":"postalcode"
},
  "geometry": {"coordinates":[-0.99150092032973,52.12179668350346],"type":"Point"}
}