{
  "type": "Feature",
  "properties": {
    "date:inception_lower": "1985-10-01",
    "date:inception_upper": "1985-10-01",
    "iso:country": "GB",
    "wof:name": "BA10 0EZ",
    "wof:placetype": "postalcode"
  },
  "geometry": {"coordinates":[-2.456034,51.109124],"type":"Point"}
}
