{
  "type": "Feature",
  "properties": {
    "iso:country":"GB",
    "wof:name":"SO52 9ER",
    "wof:placetype":"postalcode"
},
  "geometry": {"coordinates":[-1.43977562910843,50.97533307621391],"type":"Point"}
}