{
  "type": "Feature",
  "properties": {
    "date:inception_lower": "1986-01-01",
    "date:inception_upper": "1986-01-01",
    "iso:country": "GB",
    "wof:name": "SO52 9ER",
    "wof:placetype": "postalcode"
  },
  "geometry": {"coordinates":[-1.439776,50.975333],"type":"Point"}
}
