{
  "type": "Feature",
  "properties": {
    "iso:country":"GB",
    "wof:name":"PA28 6PW",
    "wof:placetype":"postalcode"
},
  "geometry": {"coordinates":[-5.69416514906247,55.41485301102966],"type":"Point"}
}