{
  "type": "Feature",
  "properties": {
    "iso:country": "GB",
    "wof:name": "ML4 1RH",
    "wof:placetype": "postalcode"
  },
  "geometry": {"coordinates":[-4.024299,55.817506],"type":"Point"}
}
