{
  "type": "Feature",
  "properties": {
    "iso:country":"GB",
    "wof:name":"ML4 1RH",
    "wof:placetype":"postalcode"
},
  "geometry": {"coordinates":[-4.02429859502799,55.81750564978363],"type":"Point"}
}