{
  "type": "Feature",
  "properties": {
    "iso:country": "GB",
    "wof:name": "NW2 7FH",
    "wof:placetype": "postalcode"
  },
  "geometry": {"coordinates":[-0.240185,51.562239],"type":"Point"}
}
