{
  "type": "Feature",
  "properties": {
    "iso:country":"GB",
    "wof:name":"PH7 3SL",
    "wof:placetype":"postalcode"
},
  "geometry": {"coordinates":[-3.82212532842805,56.37381660842885],"type":"Point"}
}