{
  "type": "Feature",
  "properties": {
    "iso:country": "GB",
    "wof:name": "IV3 8QQ",
    "wof:placetype": "postalcode"
  },
  "geometry": {"coordinates":[-4.249194,57.481926],"type":"Point"}
}
