{
  "type": "Feature",
  "properties": {
    "date:inception_lower": "1998-12-01",
    "date:inception_upper": "1998-12-01",
    "iso:country": "GB",
    "wof:name": "IV3 8QQ",
    "wof:placetype": "postalcode"
  },
  "geometry": {"coordinates":[-4.249194,57.481926],"type":"Point"}
}
