{
  "type": "Feature",
  "properties": {
    "iso:country":"GB",
    "wof:name":"WC1H 8AT",
    "wof:placetype":"postalcode"
},
  "geometry": {"coordinates":[-0.12240955186719,51.529767303776],"type":"Point"}
}