{
  "type": "Feature",
  "properties": {
    "date:inception_lower": "2005-03-01",
    "date:inception_upper": "2005-03-01",
    "iso:country": "GB",
    "wof:name": "EX2 7QE",
    "wof:placetype": "postalcode"
  },
  "geometry": {"coordinates":[-3.477477,50.716924],"type":"Point"}
}
