{
  "type": "Feature",
  "properties": {
    "iso:country":"GB",
    "wof:name":"N15 3LX",
    "wof:placetype":"postalcode"
},
  "geometry": {"coordinates":[-0.09569799764816,51.58942455914276],"type":"Point"}
}