{
  "type": "Feature",
  "properties": {
    "iso:country":"GB",
    "wof:name":"SK11 9AG",
    "wof:placetype":"postalcode"
},
  "geometry": {"coordinates":[-2.27333197806982,53.26047335175708],"type":"Point"}
}