{
  "type": "Feature",
  "properties": {
    "date:inception_lower": "1980-01-01",
    "date:inception_upper": "1980-01-01",
    "iso:country": "GB",
    "wof:name": "SK11 9AG",
    "wof:placetype": "postalcode"
  },
  "geometry": {"coordinates":[-2.273332,53.260473],"type":"Point"}
}
