{
  "type": "Feature",
  "properties": {
    "iso:country": "GB",
    "wof:name": "SK11 9AG",
    "wof:placetype": "postalcode"
  },
  "geometry": {"coordinates":[-2.273332,53.260473],"type":"Point"}
}
