{
  "type": "Feature",
  "properties": {
    "date:inception_lower": "2011-06-01",
    "date:inception_upper": "2011-06-01",
    "iso:country": "GB",
    "wof:name": "TA5 2GG",
    "wof:placetype": "postalcode"
  },
  "geometry": {"coordinates":[-3.013645,51.114284],"type":"Point"}
}
