{
  "type": "Feature",
  "properties": {
    "date:inception_lower":"2017-08-01",
    "date:inception_upper":"2017-08-31",
    "iso:country":"GB",
    "wof:name":"LE16 8TS",
    "wof:placetype":"postalcode"
},
  "geometry": {"coordinates":[-0.756533,52.529908],"type":"Point"}
}