{
  "type": "Feature",
  "properties": {
    "iso:country": "GB",
    "wof:name": "LE16 8TS",
    "wof:placetype": "postalcode"
  },
  "geometry": {"coordinates":[-0.756533,52.529908],"type":"Point"}
}
