{
  "type": "Feature",
  "properties": {
    "iso:country": "GB",
    "wof:name": "BL5 3UB",
    "wof:placetype": "postalcode"
  },
  "geometry": {"coordinates":[-2.508554,53.550458],"type":"Point"}
}
