{
  "type": "Feature",
  "properties": {
    "iso:country":"GB",
    "wof:name":"BL5 3UB",
    "wof:placetype":"postalcode"
},
  "geometry": {"coordinates":[-2.50855396296721,53.55045751474051],"type":"Point"}
}