{
  "type": "Feature",
  "properties": {
    "iso:country":"GB",
    "wof:name":"CV37 8HR",
    "wof:placetype":"postalcode"
},
  "geometry": {"coordinates":[-1.71431744933091,52.16849328126828],"type":"Point"}
}