{
  "type": "Feature",
  "properties": {
    "iso:country":"GB",
    "wof:name":"PR6 0HF",
    "wof:placetype":"postalcode"
},
  "geometry": {"coordinates":[-2.62304472429269,53.65880118338871],"type":"Point"}
}