{
  "type": "Feature",
  "properties": {
    "iso:country":"GB",
    "wof:name":"AB42 4LB",
    "wof:placetype":"postalcode"
},
  "geometry": {"coordinates":[-2.13128773421585,57.51996021516845],"type":"Point"}
}