{
  "type": "Feature",
  "properties": {
    "date:inception_lower":"1996-06-01",
    "date:inception_upper":"1996-06-30",
    "iso:country":"GB",
    "wof:name":"AB42 4LB",
    "wof:placetype":"postalcode"
},
  "geometry": {"coordinates":[-2.131242,57.520008],"type":"Point"}
}