{
  "type": "Feature",
  "properties": {
    "date:inception_lower": "1980-01-01",
    "date:inception_upper": "1980-01-01",
    "iso:country": "GB",
    "wof:name": "PE32 2BH",
    "wof:placetype": "postalcode"
  },
  "geometry": {"coordinates":[0.702442,52.71174],"type":"Point"}
}
