{
  "type": "Feature",
  "properties": {
    "iso:country":"GB",
    "wof:name":"PE32 2BH",
    "wof:placetype":"postalcode"
},
  "geometry": {"coordinates":[0.70244155443798,52.7117398834927],"type":"Point"}
}