{
  "type": "Feature",
  "properties": {
    "iso:country":"GB",
    "wof:name":"L27 1YT",
    "wof:placetype":"postalcode"
},
  "geometry": {"coordinates":[-2.85369167600153,53.39349837344117],"type":"Point"}
}