{
  "type": "Feature",
  "properties": {
    "iso:country":"GB",
    "wof:name":"TN39 3TW",
    "wof:placetype":"postalcode"
},
  "geometry": {"coordinates":[0.43722219915841,50.84527875069489],"type":"Point"}
}