{
  "type": "Feature",
  "properties": {
    "iso:country":"GB",
    "wof:name":"PR4 1EQ",
    "wof:placetype":"postalcode"
},
  "geometry": {"coordinates":[-2.89546915292252,53.75513687445905],"type":"Point"}
}