{
  "type": "Feature",
  "properties": {
    "date:inception_lower": "1980-01-01",
    "date:inception_upper": "1980-01-01",
    "iso:country": "GB",
    "wof:name": "SA48 8LX",
    "wof:placetype": "postalcode"
  },
  "geometry": {"coordinates":[-4.07542,52.13824],"type":"Point"}
}
