{
  "type": "Feature",
  "properties": {
    "iso:country": "GB",
    "wof:name": "LE14 2AN",
    "wof:placetype": "postalcode"
  },
  "geometry": {"coordinates":[-0.737862,52.759143],"type":"Point"}
}
