{
  "type": "Feature",
  "properties": {
    "iso:country":"GB",
    "wof:name":"TF10 7ET",
    "wof:placetype":"postalcode"
},
  "geometry": {"coordinates":[-2.37223221059556,52.76259928074716],"type":"Point"}
}