{
  "type": "Feature",
  "properties": {
    "date:inception_lower":"1980-01-01",
    "date:inception_upper":"1980-01-31",
    "iso:country":"GB",
    "wof:name":"BD13 3PL",
    "wof:placetype":"postalcode"
},
  "geometry": {"coordinates":[-1.85694,53.792139],"type":"Point"}
}