{
  "type": "Feature",
  "properties": {
    "date:inception_lower": "1980-01-01",
    "date:inception_upper": "1980-01-01",
    "iso:country": "GB",
    "wof:name": "SA44 4RR",
    "wof:placetype": "postalcode"
  },
  "geometry": {"coordinates":[-4.322124,52.033306],"type":"Point"}
}
