{
  "type": "Feature",
  "properties": {
    "iso:country":"GB",
    "wof:name":"RH10 4XE",
    "wof:placetype":"postalcode"
},
  "geometry": {"coordinates":[-0.07709037205092,51.12500301350114],"type":"Point"}
}