{
  "type": "Feature",
  "properties": {
    "date:inception_lower":"1980-01-01",
    "date:inception_upper":"1980-01-31",
    "iso:country":"GB",
    "wof:name":"BD17 5BY",
    "wof:placetype":"postalcode"
},
  "geometry": {"coordinates":[-1.780387,53.847857],"type":"Point"}
}