{
  "type": "Feature",
  "properties": {
    "iso:country":"GB",
    "wof:name":"BD17 5BY",
    "wof:placetype":"postalcode"
},
  "geometry": {"coordinates":[-1.78038662557712,53.84785683747644],"type":"Point"}
}