{
  "type": "Feature",
  "properties": {
    "iso:country":"GB",
    "wof:name":"DL8 1RS",
    "wof:placetype":"postalcode"
},
  "geometry": {"coordinates":[-1.62933153281181,54.29067344034207],"type":"Point"}
}