{
  "type": "Feature",
  "properties": {
    "iso:country": "GB",
    "wof:name": "DL8 1RS",
    "wof:placetype": "postalcode"
  },
  "geometry": {"coordinates":[-1.629331,54.290673],"type":"Point"}
}
