{
  "type": "Feature",
  "properties": {
    "iso:country": "GB",
    "wof:name": "EX1 3FA",
    "wof:placetype": "postalcode"
  },
  "geometry": {"coordinates":[-3.47126,50.726912],"type":"Point"}
}
