{
  "type": "Feature",
  "properties": {
    "date:inception_lower":"1980-01-01",
    "date:inception_upper":"1980-01-31",
    "iso:country":"GB",
    "wof:name":"HU19 2QR",
    "wof:placetype":"postalcode"
},
  "geometry": {"coordinates":[0.064619,53.68725],"type":"Point"}
}