{
  "type": "Feature",
  "properties": {
    "iso:country":"GB",
    "wof:name":"HU19 2QR",
    "wof:placetype":"postalcode"
},
  "geometry": {"coordinates":[0.06461943669365,53.68725028021989],"type":"Point"}
}