{
  "type": "Feature",
  "properties": {
    "iso:country": "GB",
    "wof:name": "HU19 2QR",
    "wof:placetype": "postalcode"
  },
  "geometry": {"coordinates":[0.064619,53.68725],"type":"Point"}
}
