{
  "type": "Feature",
  "properties": {
    "date:inception_lower": "1993-01-01",
    "date:inception_upper": "1993-01-01",
    "iso:country": "GB",
    "wof:name": "DE65 5DN",
    "wof:placetype": "postalcode"
  },
  "geometry": {"coordinates":[-1.725361,52.882094],"type":"Point"}
}
