{
  "type": "Feature",
  "properties": {
    "date:inception_lower":"1990-02-01",
    "date:inception_upper":"1990-02-28",
    "iso:country":"GB",
    "wof:name":"PE10 9SN",
    "wof:placetype":"postalcode"
},
  "geometry": {"coordinates":[-0.383321,52.775654],"type":"Point"}
}