{
  "type": "Feature",
  "properties": {
    "iso:country":"GB",
    "wof:name":"UB1 3EB",
    "wof:placetype":"postalcode"
},
  "geometry": {"coordinates":[-0.35476556556111,51.51268180912538],"type":"Point"}
}