{
  "type": "Feature",
  "properties": {
    "iso:country": "GB",
    "wof:name": "NR13 4UN",
    "wof:placetype": "postalcode"
  },
  "geometry": {"coordinates":[1.490092,52.6234],"type":"Point"}
}
