{
  "type": "Feature",
  "properties": {
    "iso:country":"GB",
    "wof:name":"PO22 6HN",
    "wof:placetype":"postalcode"
},
  "geometry": {"coordinates":[-0.61214140723501,50.7956155386006],"type":"Point"}
}