{
  "type": "Feature",
  "properties": {
    "iso:country": "GB",
    "wof:name": "PO22 6HN",
    "wof:placetype": "postalcode"
  },
  "geometry": {"coordinates":[-0.612141,50.795616],"type":"Point"}
}
