{
  "type": "Feature",
  "properties": {
    "iso:country":"GB",
    "wof:name":"DD8 3DN",
    "wof:placetype":"postalcode"
},
  "geometry": {"coordinates":[-2.87843731305327,56.6480109563205],"type":"Point"}
}