{
  "type": "Feature",
  "properties": {
    "iso:country":"GB",
    "wof:name":"DN5 7UL",
    "wof:placetype":"postalcode"
},
  "geometry": {"coordinates":[-1.17421381984569,53.54886162001962],"type":"Point"}
}