{
  "type": "Feature",
  "properties": {
    "date:inception_lower": "1994-05-01",
    "date:inception_upper": "1994-05-01",
    "iso:country": "GB",
    "wof:name": "M40 7LY",
    "wof:placetype": "postalcode"
  },
  "geometry": {"coordinates":[-2.215031,53.490133],"type":"Point"}
}
