{
  "type": "Feature",
  "properties": {
    "iso:country":"GB",
    "wof:name":"M40 7LY",
    "wof:placetype":"postalcode"
},
  "geometry": {"coordinates":[-2.21509361331842,53.49009001378888],"type":"Point"}
}