{
  "type": "Feature",
  "properties": {
    "iso:country":"GB",
    "wof:name":"CV10 0DQ",
    "wof:placetype":"postalcode"
},
  "geometry": {"coordinates":[-1.47005947760179,52.54283042741645],"type":"Point"}
}