{
  "type": "Feature",
  "properties": {
    "iso:country": "GB",
    "wof:name": "CV10 0DQ",
    "wof:placetype": "postalcode"
  },
  "geometry": {"coordinates":[-1.471494,52.541712],"type":"Point"}
}
