{
  "type": "Feature",
  "properties": {
    "date:inception_lower": "1997-12-01",
    "date:inception_upper": "1997-12-01",
    "iso:country": "GB",
    "wof:name": "SK13 1LL",
    "wof:placetype": "postalcode"
  },
  "geometry": {"coordinates":[-1.968851,53.47224],"type":"Point"}
}
