{
  "type": "Feature",
  "properties": {
    "iso:country":"GB",
    "wof:name":"IP1 1DP",
    "wof:placetype":"postalcode"
},
  "geometry": {"coordinates":[1.15523247820683,52.05655230822696],"type":"Point"}
}