{
  "type": "Feature",
  "properties": {
    "iso:country":"GB",
    "wof:name":"PE30 1AD",
    "wof:placetype":"postalcode"
},
  "geometry": {"coordinates":[0.40188306465594,52.75621094405717],"type":"Point"}
}