{
  "type": "Feature",
  "properties": {
    "iso:country": "GB",
    "wof:name": "PE30 1AD",
    "wof:placetype": "postalcode"
  },
  "geometry": {"coordinates":[0.401796,52.756244],"type":"Point"}
}
