{
  "type": "Feature",
  "properties": {
    "date:inception_lower": "1980-01-01",
    "date:inception_upper": "1980-01-01",
    "iso:country": "GB",
    "wof:name": "LN9 6BP",
    "wof:placetype": "postalcode"
  },
  "geometry": {"coordinates":[-0.107778,53.203284],"type":"Point"}
}
