{
  "type": "Feature",
  "properties": {
    "iso:country": "GB",
    "wof:name": "WD24 7AB",
    "wof:placetype": "postalcode"
  },
  "geometry": {"coordinates":[-0.378957,51.672224],"type":"Point"}
}
