{
  "type": "Feature",
  "properties": {
    "iso:country":"GB",
    "wof:name":"WD24 7AB",
    "wof:placetype":"postalcode"
},
  "geometry": {"coordinates":[-0.37895673355165,51.67222442669595],"type":"Point"}
}