{
  "type": "Feature",
  "properties": {
    "iso:country": "GB",
    "wof:name": "CV47 0FD",
    "wof:placetype": "postalcode"
  },
  "geometry": {"coordinates":[-1.399645,52.245323],"type":"Point"}
}
