{
  "type": "Feature",
  "properties": {
    "iso:country":"GB",
    "wof:name":"KT12 3HN",
    "wof:placetype":"postalcode"
},
  "geometry": {"coordinates":[-0.41066345122018,51.3797457731245],"type":"Point"}
}