{
  "type": "Feature",
  "properties": {
    "iso:country": "GB",
    "wof:name": "KT12 3HN",
    "wof:placetype": "postalcode"
  },
  "geometry": {"coordinates":[-0.410663,51.379746],"type":"Point"}
}
