{
  "type": "Feature",
  "properties": {
    "date:inception_lower":"1992-08-01",
    "date:inception_upper":"1992-08-31",
    "iso:country":"GB",
    "wof:name":"KT12 3HN",
    "wof:placetype":"postalcode"
},
  "geometry": {"coordinates":[-0.410663,51.379746],"type":"Point"}
}