{
  "type": "Feature",
  "properties": {
    "iso:country": "GB",
    "wof:name": "ML4 3LF",
    "wof:placetype": "postalcode"
  },
  "geometry": {"coordinates":[-4.041383,55.827361],"type":"Point"}
}
