{
  "type": "Feature",
  "properties": {
    "iso:country":"GB",
    "wof:name":"ML4 3LF",
    "wof:placetype":"postalcode"
},
  "geometry": {"coordinates":[-4.04138338224788,55.82736054638783],"type":"Point"}
}