{
  "type": "Feature",
  "properties": {
    "iso:country":"GB",
    "wof:name":"RG6 7JA",
    "wof:placetype":"postalcode"
},
  "geometry": {"coordinates":[-0.91573903290923,51.43825402888681],"type":"Point"}
}