{
  "type": "Feature",
  "properties": {
    "iso:country":"GB",
    "wof:name":"TR4 9AL",
    "wof:placetype":"postalcode"
},
  "geometry": {"coordinates":[-5.11221393615033,50.26743608485825],"type":"Point"}
}