{
  "type": "Feature",
  "properties": {
    "date:inception_lower": "1980-01-01",
    "date:inception_upper": "1980-01-01",
    "iso:country": "GB",
    "wof:name": "ST7 4LL",
    "wof:placetype": "postalcode"
  },
  "geometry": {"coordinates":[-2.235486,53.07869],"type":"Point"}
}
