{
  "type": "Feature",
  "properties": {
    "iso:country":"GB",
    "wof:name":"ST7 4LL",
    "wof:placetype":"postalcode"
},
  "geometry": {"coordinates":[-2.2354861681839,53.07869019633727],"type":"Point"}
}