{
  "type": "Feature",
  "properties": {
    "iso:country":"GB",
    "wof:name":"WS11 8JZ",
    "wof:placetype":"postalcode"
},
  "geometry": {"coordinates":[-2.02197700827453,52.67134426275866],"type":"Point"}
}