{
  "type": "Feature",
  "properties": {
    "date:inception_lower": "2014-05-01",
    "date:inception_upper": "2014-05-01",
    "iso:country": "GB",
    "wof:name": "WS11 8JZ",
    "wof:placetype": "postalcode"
  },
  "geometry": {"coordinates":[-2.021977,52.671344],"type":"Point"}
}
