{
  "type": "Feature",
  "properties": {
    "date:inception_lower": "2008-11-01",
    "date:inception_upper": "2008-11-01",
    "iso:country": "GB",
    "wof:name": "MK45 2FQ",
    "wof:placetype": "postalcode"
  },
  "geometry": {"coordinates":[-0.509831,52.022789],"type":"Point"}
}
