{
  "type": "Feature",
  "properties": {
    "iso:country":"GB",
    "wof:name":"OX7 5EU",
    "wof:placetype":"postalcode"
},
  "geometry": {"coordinates":[-1.5473161502626,51.93879862386723],"type":"Point"}
}