{
  "type": "Feature",
  "properties": {
    "iso:country":"GB",
    "wof:name":"TR7 2LH",
    "wof:placetype":"postalcode"
},
  "geometry": {"coordinates":[-5.0729170216565,50.40760954512802],"type":"Point"}
}