{
  "type": "Feature",
  "properties": {
    "iso:country":"GB",
    "wof:name":"CF40 1DH",
    "wof:placetype":"postalcode"
},
  "geometry": {"coordinates":[-3.45177140417156,51.61881708432191],"type":"Point"}
}