{
  "type": "Feature",
  "properties": {
    "date:inception_lower":"1980-01-01",
    "date:inception_upper":"1980-01-31",
    "iso:country":"GB",
    "wof:name":"S43 3NW",
    "wof:placetype":"postalcode"
},
  "geometry": {"coordinates":[-1.365119,53.257788],"type":"Point"}
}