{
  "type": "Feature",
  "properties": {
    "iso:country":"GB",
    "wof:name":"S43 3NW",
    "wof:placetype":"postalcode"
},
  "geometry": {"coordinates":[-1.36576797148279,53.25773553687277],"type":"Point"}
}