{
  "type": "Feature",
  "properties": {
    "iso:country": "GB",
    "wof:name": "S43 3NW",
    "wof:placetype": "postalcode"
  },
  "geometry": {"coordinates":[-1.365119,53.257788],"type":"Point"}
}
