{
  "type": "Feature",
  "properties": {
    "iso:country": "GB",
    "wof:name": "SS13 3RB",
    "wof:placetype": "postalcode"
  },
  "geometry": {"coordinates":[0.507235,51.570653],"type":"Point"}
}
