{
  "type": "Feature",
  "properties": {
    "iso:country":"GB",
    "wof:name":"CH7 5RP",
    "wof:placetype":"postalcode"
},
  "geometry": {"coordinates":[-3.27744997383497,53.20587416919246],"type":"Point"}
}