{
  "type": "Feature",
  "properties": {
    "date:inception_lower": "1980-01-01",
    "date:inception_upper": "1980-01-01",
    "iso:country": "GB",
    "wof:name": "CH7 5RP",
    "wof:placetype": "postalcode"
  },
  "geometry": {"coordinates":[-3.27745,53.205874],"type":"Point"}
}
