{
  "type": "Feature",
  "properties": {
    "iso:country": "GB",
    "wof:name": "RH12 2AZ",
    "wof:placetype": "postalcode"
  },
  "geometry": {"coordinates":[-0.336997,51.070864],"type":"Point"}
}
