{
  "type": "Feature",
  "properties": {
    "iso:country": "GB",
    "wof:name": "WV14 9UL",
    "wof:placetype": "postalcode"
  },
  "geometry": {"coordinates":[-2.097888,52.546968],"type":"Point"}
}
