{
  "type": "Feature",
  "properties": {
    "iso:country":"GB",
    "wof:name":"WV14 9UL",
    "wof:placetype":"postalcode"
},
  "geometry": {"coordinates":[-2.09788805990288,52.54696828781805],"type":"Point"}
}