{
  "type": "Feature",
  "properties": {
    "iso:country":"GB",
    "wof:name":"AL7 2EA",
    "wof:placetype":"postalcode"
},
  "geometry": {"coordinates":[-0.16932176123476,51.80565395239192],"type":"Point"}
}