{
  "type": "Feature",
  "properties": {
    "iso:country":"GB",
    "wof:name":"S72 8RX",
    "wof:placetype":"postalcode"
},
  "geometry": {"coordinates":[-1.40579926592448,53.56386239341504],"type":"Point"}
}