{
  "type": "Feature",
  "properties": {
    "iso:country": "GB",
    "wof:name": "ME14 5LF",
    "wof:placetype": "postalcode"
  },
  "geometry": {"coordinates":[0.555248,51.282416],"type":"Point"}
}
