{
  "type": "Feature",
  "properties": {
    "iso:country":"GB",
    "wof:name":"ME14 5LF",
    "wof:placetype":"postalcode"
},
  "geometry": {"coordinates":[0.55524780601634,51.28241627178691],"type":"Point"}
}