{
  "type": "Feature",
  "properties": {
    "iso:country": "GB",
    "wof:name": "CF5 1NL",
    "wof:placetype": "postalcode"
  },
  "geometry": {"coordinates":[-3.210389,51.481965],"type":"Point"}
}
