{
  "type": "Feature",
  "properties": {
    "date:inception_lower":"2005-05-01",
    "date:inception_upper":"2005-05-31",
    "iso:country":"GB",
    "wof:name":"CF5 1NL",
    "wof:placetype":"postalcode"
},
  "geometry": {"coordinates":[-3.210389,51.481965],"type":"Point"}
}