{
  "type": "Feature",
  "properties": {
    "iso:country":"GB",
    "wof:name":"CF5 1NL",
    "wof:placetype":"postalcode"
},
  "geometry": {"coordinates":[-3.21038871516342,51.48196525265703],"type":"Point"}
}