{
  "type": "Feature",
  "properties": {
    "iso:country":"GB",
    "wof:name":"YO30 6DN",
    "wof:placetype":"postalcode"
},
  "geometry": {"coordinates":[-1.09204927429531,53.9729298410785],"type":"Point"}
}