{
  "type": "Feature",
  "properties": {
    "iso:country": "GB",
    "wof:name": "YO30 6DN",
    "wof:placetype": "postalcode"
  },
  "geometry": {"coordinates":[-1.091919,53.973045],"type":"Point"}
}
