{
  "type": "Feature",
  "properties": {
    "iso:country":"GB",
    "wof:name":"SG18 9PE",
    "wof:placetype":"postalcode"
},
  "geometry": {"coordinates":[-0.27036263974944,52.05309086719183],"type":"Point"}
}