{
  "type": "Feature",
  "properties": {
    "iso:country":"GB",
    "wof:name":"PR5 8EH",
    "wof:placetype":"postalcode"
},
  "geometry": {"coordinates":[-2.63795822397844,53.7154387263447],"type":"Point"}
}