{
  "type": "Feature",
  "properties": {
    "iso:country":"GB",
    "wof:name":"MK45 1PH",
    "wof:placetype":"postalcode"
},
  "geometry": {"coordinates":[-0.50300234069717,52.00469215571288],"type":"Point"}
}