{
  "type": "Feature",
  "properties": {
    "iso:country":"GB",
    "wof:name":"SO17 2TH",
    "wof:placetype":"postalcode"
},
  "geometry": {"coordinates":[-1.38550265749806,50.92932487487715],"type":"Point"}
}