{
  "type": "Feature",
  "properties": {
    "iso:country":"GB",
    "wof:name":"EH21 8NY",
    "wof:placetype":"postalcode"
},
  "geometry": {"coordinates":[-3.03401606239044,55.91738259908438],"type":"Point"}
}