{
  "type": "Feature",
  "properties": {
    "iso:country":"GB",
    "wof:name":"B19 3JB",
    "wof:placetype":"postalcode"
},
  "geometry": {"coordinates":[-1.90353824460738,52.48884117840245],"type":"Point"}
}