{
  "type": "Feature",
  "properties": {
    "date:inception_lower": "1980-01-01",
    "date:inception_upper": "1980-01-01",
    "iso:country": "GB",
    "wof:name": "LA14 3HZ",
    "wof:placetype": "postalcode"
  },
  "geometry": {"coordinates":[-3.256688,54.106298],"type":"Point"}
}
