{
  "type": "Feature",
  "properties": {
    "iso:country": "GB",
    "wof:name": "N20 0PH",
    "wof:placetype": "postalcode"
  },
  "geometry": {"coordinates":[-0.175507,51.627178],"type":"Point"}
}
