{
  "type": "Feature",
  "properties": {
    "iso:country":"GB",
    "wof:name":"N3 2LD",
    "wof:placetype":"postalcode"
},
  "geometry": {"coordinates":[-0.19375600333316,51.60087521556174],"type":"Point"}
}