{
  "type": "Feature",
  "properties": {
    "date:inception_lower": "2022-08-01",
    "date:inception_upper": "2022-08-01",
    "iso:country": "GB",
    "wof:name": "SN4 0GP",
    "wof:placetype": "postalcode"
  },
  "geometry": {"coordinates":[-1.78516,51.524569],"type":"Point"}
}
