{
  "type": "Feature",
  "properties": {
    "iso:country":"GB",
    "wof:name":"CH5 4RS",
    "wof:placetype":"postalcode"
},
  "geometry": {"coordinates":[-3.07448834552311,53.21212961989777],"type":"Point"}
}