{
  "type": "Feature",
  "properties": {
    "iso:country": "GB",
    "wof:name": "CH5 4RS",
    "wof:placetype": "postalcode"
  },
  "geometry": {"coordinates":[-3.074488,53.21213],"type":"Point"}
}
