{
  "type": "Feature",
  "properties": {
    "date:inception_lower":"1985-10-01",
    "date:inception_upper":"1985-10-31",
    "iso:country":"GB",
    "wof:name":"ME15 8QY",
    "wof:placetype":"postalcode"
},
  "geometry": {"coordinates":[0.559631,51.262201],"type":"Point"}
}