{
  "type": "Feature",
  "properties": {
    "iso:country": "GB",
    "wof:name": "ME15 8QY",
    "wof:placetype": "postalcode"
  },
  "geometry": {"coordinates":[0.559631,51.262201],"type":"Point"}
}
