{
  "type": "Feature",
  "properties": {
    "iso:country":"GB",
    "wof:name":"SN2 5LL",
    "wof:placetype":"postalcode"
},
  "geometry": {"coordinates":[-1.78504671373013,51.59363071943024],"type":"Point"}
}