{
  "type": "Feature",
  "properties": {
    "iso:country":"GB",
    "wof:name":"EH10 5SG",
    "wof:placetype":"postalcode"
},
  "geometry": {"coordinates":[-3.21435170529424,55.91924962182355],"type":"Point"}
}