{
  "type": "Feature",
  "properties": {
    "iso:country": "GB",
    "wof:name": "DH7 8QT",
    "wof:placetype": "postalcode"
  },
  "geometry": {"coordinates":[-1.62256,54.757973],"type":"Point"}
}
