{
  "type": "Feature",
  "properties": {
    "iso:country":"GB",
    "wof:name":"SA11 2JU",
    "wof:placetype":"postalcode"
},
  "geometry": {"coordinates":[-3.82756654317822,51.63298121725698],"type":"Point"}
}