{
  "type": "Feature",
  "properties": {
    "iso:country":"GB",
    "wof:name":"MK16 0NA",
    "wof:placetype":"postalcode"
},
  "geometry": {"coordinates":[-0.72733466161322,52.08052630919043],"type":"Point"}
}