{
  "type": "Feature",
  "properties": {
    "iso:country":"GB",
    "wof:name":"SY5 0NZ",
    "wof:placetype":"postalcode"
},
  "geometry": {"coordinates":[-2.92885260853165,52.61414216104733],"type":"Point"}
}