{
  "type": "Feature",
  "properties": {
    "iso:country":"GB",
    "wof:name":"PO38 1DT",
    "wof:placetype":"postalcode"
},
  "geometry": {"coordinates":[-1.20362908423542,50.59722941402457],"type":"Point"}
}