{
  "type": "Feature",
  "properties": {
    "date:inception_lower": "1980-01-01",
    "date:inception_upper": "1980-01-01",
    "iso:country": "GB",
    "wof:name": "PO38 1DT",
    "wof:placetype": "postalcode"
  },
  "geometry": {"coordinates":[-1.203629,50.597229],"type":"Point"}
}
