{
  "type": "Feature",
  "properties": {
    "date:inception_lower":"1980-01-01",
    "date:inception_upper":"1980-01-31",
    "iso:country":"GB",
    "wof:name":"NP44 8RZ",
    "wof:placetype":"postalcode"
},
  "geometry": {"coordinates":[-3.004335,51.648117],"type":"Point"}
}