{
  "type": "Feature",
  "properties": {
    "date:inception_lower": "1980-01-01",
    "date:inception_upper": "1980-01-01",
    "iso:country": "GB",
    "wof:name": "GL7 5NJ",
    "wof:placetype": "postalcode"
  },
  "geometry": {"coordinates":[-1.834975,51.758484],"type":"Point"}
}
