{
  "type": "Feature",
  "properties": {
    "iso:country": "GB",
    "wof:name": "GL7 5NJ",
    "wof:placetype": "postalcode"
  },
  "geometry": {"coordinates":[-1.834975,51.758484],"type":"Point"}
}
