{
  "type": "Feature",
  "properties": {
    "iso:country":"GB",
    "wof:name":"GL7 5NJ",
    "wof:placetype":"postalcode"
},
  "geometry": {"coordinates":[-1.83497480955838,51.75848415723654],"type":"Point"}
}