{
  "type": "Feature",
  "properties": {
    "iso:country":"GB",
    "wof:name":"TD8 6PN",
    "wof:placetype":"postalcode"
},
  "geometry": {"coordinates":[-2.51039055872216,55.41458741217595],"type":"Point"}
}