{
  "type": "Feature",
  "properties": {
    "date:inception_lower":"1980-01-01",
    "date:inception_upper":"1980-01-31",
    "iso:country":"GB",
    "wof:name":"TD8 6PN",
    "wof:placetype":"postalcode"
},
  "geometry": {"coordinates":[-2.510391,55.414587],"type":"Point"}
}