{
  "type": "Feature",
  "properties": {
    "date:inception_lower": "1985-04-01",
    "date:inception_upper": "1985-04-01",
    "iso:country": "GB",
    "wof:name": "PO14 4AW",
    "wof:placetype": "postalcode"
  },
  "geometry": {"coordinates":[-1.252534,50.857041],"type":"Point"}
}
