{
  "type": "Feature",
  "properties": {
    "iso:country":"GB",
    "wof:name":"NE4 8XU",
    "wof:placetype":"postalcode"
},
  "geometry": {"coordinates":[-1.6644513084214,54.96853044707105],"type":"Point"}
}