{
  "type": "Feature",
  "properties": {
    "iso:country":"GB",
    "wof:name":"EH17 7AD",
    "wof:placetype":"postalcode"
},
  "geometry": {"coordinates":[-3.13328957167003,55.90830526502482],"type":"Point"}
}