{
  "type": "Feature",
  "properties": {
    "iso:country":"GB",
    "wof:name":"CT19 5SA",
    "wof:placetype":"postalcode"
},
  "geometry": {"coordinates":[1.18153111711403,51.08698381030428],"type":"Point"}
}