{
  "type": "Feature",
  "properties": {
    "iso:country":"GB",
    "wof:name":"CM3 6UW",
    "wof:placetype":"postalcode"
},
  "geometry": {"coordinates":[0.72396746549239,51.67016356409385],"type":"Point"}
}