{
  "type": "Feature",
  "properties": {
    "date:inception_lower": "1988-03-01",
    "date:inception_upper": "1988-03-01",
    "iso:country": "GB",
    "wof:name": "CM3 6UW",
    "wof:placetype": "postalcode"
  },
  "geometry": {"coordinates":[0.723968,51.670164],"type":"Point"}
}
