{
  "type": "Feature",
  "properties": {
    "iso:country":"GB",
    "wof:name":"ZE2 9PZ",
    "wof:placetype":"postalcode"
},
  "geometry": {"coordinates":[-1.22219755230537,60.4016574121601],"type":"Point"}
}