{
  "type": "Feature",
  "properties": {
    "date:inception_lower": "1980-01-01",
    "date:inception_upper": "1980-01-01",
    "iso:country": "GB",
    "wof:name": "BA2 2JN",
    "wof:placetype": "postalcode"
  },
  "geometry": {"coordinates":[-2.384063,51.373094],"type":"Point"}
}
