{
  "type": "Feature",
  "properties": {
    "iso:country": "GB",
    "wof:name": "BA2 2JN",
    "wof:placetype": "postalcode"
  },
  "geometry": {"coordinates":[-2.384063,51.373094],"type":"Point"}
}
