{
  "type": "Feature",
  "properties": {
    "iso:country": "GB",
    "wof:name": "S81 8AP",
    "wof:placetype": "postalcode"
  },
  "geometry": {"coordinates":[-1.158106,53.322765],"type":"Point"}
}
