{
  "type": "Feature",
  "properties": {
    "iso:country":"GB",
    "wof:name":"S81 8AP",
    "wof:placetype":"postalcode"
},
  "geometry": {"coordinates":[-1.15791500330523,53.32257223485604],"type":"Point"}
}