{
  "type": "Feature",
  "properties": {
    "date:inception_lower":"2006-05-01",
    "date:inception_upper":"2006-05-31",
    "iso:country":"GB",
    "wof:name":"PH1 4QR",
    "wof:placetype":"postalcode"
},
  "geometry": {"coordinates":[-3.418263,56.531778],"type":"Point"}
}