{
  "type": "Feature",
  "properties": {
    "iso:country":"GB",
    "wof:name":"PH1 4QR",
    "wof:placetype":"postalcode"
},
  "geometry": {"coordinates":[-3.42137288128896,56.53230958278146],"type":"Point"}
}