{
  "type": "Feature",
  "properties": {
    "iso:country": "GB",
    "wof:name": "NG9 3LR",
    "wof:placetype": "postalcode"
  },
  "geometry": {"coordinates":[-1.24604,52.929705],"type":"Point"}
}
