{
  "type": "Feature",
  "properties": {
    "iso:country": "GB",
    "wof:name": "TQ12 5JJ",
    "wof:placetype": "postalcode"
  },
  "geometry": {"coordinates":[-3.573989,50.494213],"type":"Point"}
}
