{
  "type": "Feature",
  "properties": {
    "date:inception_lower":"1980-01-01",
    "date:inception_upper":"1980-01-31",
    "iso:country":"GB",
    "wof:name":"CV10 9HL",
    "wof:placetype":"postalcode"
},
  "geometry": {"coordinates":[-1.505671,52.528761],"type":"Point"}
}