{
  "type": "Feature",
  "properties": {
    "iso:country":"GB",
    "wof:name":"OL11 4QF",
    "wof:placetype":"postalcode"
},
  "geometry": {"coordinates":[-2.17344550179114,53.60676358443948],"type":"Point"}
}