{
  "type": "Feature",
  "properties": {
    "iso:country": "GB",
    "wof:name": "LA13 0RB",
    "wof:placetype": "postalcode"
  },
  "geometry": {"coordinates":[-3.182321,54.122385],"type":"Point"}
}
