{
  "type": "Feature",
  "properties": {
    "iso:country":"GB",
    "wof:name":"LA13 0RB",
    "wof:placetype":"postalcode"
},
  "geometry": {"coordinates":[-3.18232128747245,54.12238498091529],"type":"Point"}
}