{
  "type": "Feature",
  "properties": {
    "date:inception_lower":"1980-01-01",
    "date:inception_upper":"1980-01-31",
    "iso:country":"GB",
    "wof:name":"LA13 0RB",
    "wof:placetype":"postalcode"
},
  "geometry": {"coordinates":[-3.182321,54.122385],"type":"Point"}
}