{
  "type": "Feature",
  "properties": {
    "iso:country":"GB",
    "wof:name":"BD6 3XE",
    "wof:placetype":"postalcode"
},
  "geometry": {"coordinates":[-1.81976469387863,53.77095853043745],"type":"Point"}
}