{
  "type": "Feature",
  "properties": {
    "iso:country":"GB",
    "wof:name":"LA21 8HN",
    "wof:placetype":"postalcode"
},
  "geometry": {"coordinates":[-3.0785208313726,54.37123413984411],"type":"Point"}
}