{
  "type": "Feature",
  "properties": {
    "iso:country":"GB",
    "wof:name":"ME18 5LB",
    "wof:placetype":"postalcode"
},
  "geometry": {"coordinates":[0.42613989297696,51.26370526091085],"type":"Point"}
}