{
  "type": "Feature",
  "properties": {
    "iso:country":"GB",
    "wof:name":"BH21 7QN",
    "wof:placetype":"postalcode"
},
  "geometry": {"coordinates":[-1.91549390180747,50.81371144397485],"type":"Point"}
}