{
  "type": "Feature",
  "properties": {
    "iso:country": "GB",
    "wof:name": "ME15 8FW",
    "wof:placetype": "postalcode"
  },
  "geometry": {"coordinates":[0.572316,51.267059],"type":"Point"}
}
