{
  "type": "Feature",
  "properties": {
    "date:inception_lower": "2000-06-01",
    "date:inception_upper": "2000-06-01",
    "iso:country": "GB",
    "wof:name": "TF1 5SU",
    "wof:placetype": "postalcode"
  },
  "geometry": {"coordinates":[-2.473504,52.707608],"type":"Point"}
}
