{
  "type": "Feature",
  "properties": {
    "iso:country":"GB",
    "wof:name":"TF1 5SU",
    "wof:placetype":"postalcode"
},
  "geometry": {"coordinates":[-2.47350377555862,52.70760797972265],"type":"Point"}
}