{
  "type": "Feature",
  "properties": {
    "iso:country": "GB",
    "wof:name": "HA5 4JA",
    "wof:placetype": "postalcode"
  },
  "geometry": {"coordinates":[-0.375733,51.607464],"type":"Point"}
}
