{
  "type": "Feature",
  "properties": {
    "iso:country":"GB",
    "wof:name":"S80 4UW",
    "wof:placetype":"postalcode"
},
  "geometry": {"coordinates":[-1.19014582038347,53.28301016068705],"type":"Point"}
}