{
  "type": "Feature",
  "properties": {
    "date:inception_lower": "1980-01-01",
    "date:inception_upper": "1980-01-01",
    "iso:country": "GB",
    "wof:name": "S80 4UW",
    "wof:placetype": "postalcode"
  },
  "geometry": {"coordinates":[-1.190144,53.283041],"type":"Point"}
}
