{
  "type": "Feature",
  "properties": {
    "iso:country":"GB",
    "wof:name":"IV54 8LQ",
    "wof:placetype":"postalcode"
},
  "geometry": {"coordinates":[-5.81425884901604,57.40739042334706],"type":"Point"}
}