{
  "type": "Feature",
  "properties": {
    "iso:country": "GB",
    "wof:name": "IV54 8LQ",
    "wof:placetype": "postalcode"
  },
  "geometry": {"coordinates":[-5.814259,57.40739],"type":"Point"}
}
