{
  "type": "Feature",
  "properties": {
    "date:inception_lower":"1998-06-01",
    "date:inception_upper":"1998-06-30",
    "iso:country":"GB",
    "wof:name":"IV54 8LQ",
    "wof:placetype":"postalcode"
},
  "geometry": {"coordinates":[-5.814259,57.40739],"type":"Point"}
}