{
  "type": "Feature",
  "properties": {
    "iso:country":"GB",
    "wof:name":"HA4 0BP",
    "wof:placetype":"postalcode"
},
  "geometry": {"coordinates":[-0.41073208469141,51.5663004830208],"type":"Point"}
}