{
  "type": "Feature",
  "properties": {
    "iso:country": "GB",
    "wof:name": "TQ5 9TA",
    "wof:placetype": "postalcode"
  },
  "geometry": {"coordinates":[-3.504531,50.396759],"type":"Point"}
}
