{
  "type": "Feature",
  "properties": {
    "iso:country":"GB",
    "wof:name":"GU15 2AR",
    "wof:placetype":"postalcode"
},
  "geometry": {"coordinates":[-0.72916747976858,51.34003868099482],"type":"Point"}
}