{
  "type": "Feature",
  "properties": {
    "iso:country": "GB",
    "wof:name": "BA8 0JJ",
    "wof:placetype": "postalcode"
  },
  "geometry": {"coordinates":[-2.416746,51.000726],"type":"Point"}
}
