{
  "type": "Feature",
  "properties": {
    "iso:country":"GB",
    "wof:name":"BA8 0JJ",
    "wof:placetype":"postalcode"
},
  "geometry": {"coordinates":[-2.41683570195893,51.0009021376426],"type":"Point"}
}