{
  "type": "Feature",
  "properties": {
    "iso:country":"GB",
    "wof:name":"HD5 9TY",
    "wof:placetype":"postalcode"
},
  "geometry": {"coordinates":[-1.74613453174729,53.65006110718152],"type":"Point"}
}