{
  "type": "Feature",
  "properties": {
    "date:inception_lower": "1981-09-01",
    "date:inception_upper": "1981-09-01",
    "iso:country": "GB",
    "wof:name": "WS14 9UD",
    "wof:placetype": "postalcode"
  },
  "geometry": {"coordinates":[-1.806874,52.682975],"type":"Point"}
}
