{
  "type": "Feature",
  "properties": {
    "date:inception_lower": "2008-12-01",
    "date:inception_upper": "2008-12-01",
    "iso:country": "GB",
    "wof:name": "RG42 1ND",
    "wof:placetype": "postalcode"
  },
  "geometry": {"coordinates":[-0.760386,51.417984],"type":"Point"}
}
