{
  "type": "Feature",
  "properties": {
    "iso:country":"GB",
    "wof:name":"RG42 1ND",
    "wof:placetype":"postalcode"
},
  "geometry": {"coordinates":[-0.76038594825135,51.41798408707627],"type":"Point"}
}