{
  "type": "Feature",
  "properties": {
    "iso:country":"GB",
    "wof:name":"PO39 0DS",
    "wof:placetype":"postalcode"
},
  "geometry": {"coordinates":[-1.53757285414171,50.68317000013492],"type":"Point"}
}