{
  "type": "Feature",
  "properties": {
    "date:inception_lower": "1980-01-01",
    "date:inception_upper": "1980-01-01",
    "iso:country": "GB",
    "wof:name": "PO39 0DS",
    "wof:placetype": "postalcode"
  },
  "geometry": {"coordinates":[-1.537573,50.68317],"type":"Point"}
}
