{
  "type": "Feature",
  "properties": {
    "iso:country": "GB",
    "wof:name": "SP5 5HL",
    "wof:placetype": "postalcode"
  },
  "geometry": {"coordinates":[-1.967783,51.024105],"type":"Point"}
}
