{
  "type": "Feature",
  "properties": {
    "iso:country":"GB",
    "wof:name":"SP5 5HL",
    "wof:placetype":"postalcode"
},
  "geometry": {"coordinates":[-1.96778281186422,51.02410481758984],"type":"Point"}
}