{
  "type": "Feature",
  "properties": {
    "iso:country":"GB",
    "wof:name":"B63 2BJ",
    "wof:placetype":"postalcode"
},
  "geometry": {"coordinates":[-2.08073837952193,52.45907777763664],"type":"Point"}
}