{
  "type": "Feature",
  "properties": {
    "date:inception_lower":"1991-09-01",
    "date:inception_upper":"1991-09-30",
    "iso:country":"GB",
    "wof:name":"B63 2BJ",
    "wof:placetype":"postalcode"
},
  "geometry": {"coordinates":[-2.080924,52.459182],"type":"Point"}
}