{
  "type": "Feature",
  "properties": {
    "iso:country": "GB",
    "wof:name": "B63 2BJ",
    "wof:placetype": "postalcode"
  },
  "geometry": {"coordinates":[-2.080924,52.459182],"type":"Point"}
}
