{
  "type": "Feature",
  "properties": {
    "iso:country": "GB",
    "wof:name": "SN4 7AF",
    "wof:placetype": "postalcode"
  },
  "geometry": {"coordinates":[-1.904293,51.542214],"type":"Point"}
}
