{
  "type": "Feature",
  "properties": {
    "iso:country":"GB",
    "wof:name":"TS22 5DA",
    "wof:placetype":"postalcode"
},
  "geometry": {"coordinates":[-1.31043653767387,54.61370982609986],"type":"Point"}
}