{
  "type": "Feature",
  "properties": {
    "iso:country":"GB",
    "wof:name":"S36 9NR",
    "wof:placetype":"postalcode"
},
  "geometry": {"coordinates":[-1.66770401624585,53.52524628508728],"type":"Point"}
}