{
  "type": "Feature",
  "properties": {
    "iso:country":"GB",
    "wof:name":"HS3 3BD",
    "wof:placetype":"postalcode"
},
  "geometry": {"coordinates":[-6.68227912352761,57.91987520827572],"type":"Point"}
}