{
  "type": "Feature",
  "properties": {
    "iso:country":"GB",
    "wof:name":"LS1 4HG",
    "wof:placetype":"postalcode"
},
  "geometry": {"coordinates":[-1.55206430125864,53.7955682173861],"type":"Point"}
}