{
  "type": "Feature",
  "properties": {
    "iso:country":"GB",
    "wof:name":"CV2 5LL",
    "wof:placetype":"postalcode"
},
  "geometry": {"coordinates":[-1.47137280365782,52.40753584203886],"type":"Point"}
}