{
  "type": "Feature",
  "properties": {
    "iso:country": "GB",
    "wof:name": "DE23 1FJ",
    "wof:placetype": "postalcode"
  },
  "geometry": {"coordinates":[-1.509888,52.8968],"type":"Point"}
}
