{
  "type": "Feature",
  "properties": {
    "iso:country":"GB",
    "wof:name":"AL5 5UA",
    "wof:placetype":"postalcode"
},
  "geometry": {"coordinates":[-0.34083919386016,51.81167910044778],"type":"Point"}
}