{
  "type": "Feature",
  "properties": {
    "iso:country":"GB",
    "wof:name":"BA11 5HA",
    "wof:placetype":"postalcode"
},
  "geometry": {"coordinates":[-2.34419419554753,51.18109837348648],"type":"Point"}
}