{
  "type": "Feature",
  "properties": {
    "iso:country":"GB",
    "wof:name":"LE9 8DT",
    "wof:placetype":"postalcode"
},
  "geometry": {"coordinates":[-1.34577349548165,52.56549318741275],"type":"Point"}
}