{
  "type": "Feature",
  "properties": {
    "iso:country":"GB",
    "wof:name":"KW14 7JP",
    "wof:placetype":"postalcode"
},
  "geometry": {"coordinates":[-3.52981010991331,58.5962744296713],"type":"Point"}
}