{
  "type": "Feature",
  "properties": {
    "date:inception_lower": "1980-01-01",
    "date:inception_upper": "1980-01-01",
    "iso:country": "GB",
    "wof:name": "KW14 7JP",
    "wof:placetype": "postalcode"
  },
  "geometry": {"coordinates":[-3.52981,58.596274],"type":"Point"}
}
