{
  "type": "Feature",
  "properties": {
    "date:inception_lower":"1991-11-01",
    "date:inception_upper":"1991-11-30",
    "iso:country":"GB",
    "wof:name":"DD6 8AH",
    "wof:placetype":"postalcode"
},
  "geometry": {"coordinates":[-2.940298,56.440254],"type":"Point"}
}