{
  "type": "Feature",
  "properties": {
    "iso:country":"GB",
    "wof:name":"DD6 8AH",
    "wof:placetype":"postalcode"
},
  "geometry": {"coordinates":[-2.94029844137644,56.44025393165555],"type":"Point"}
}