{
  "type": "Feature",
  "properties": {
    "iso:country": "GB",
    "wof:name": "DD6 8AH",
    "wof:placetype": "postalcode"
  },
  "geometry": {"coordinates":[-2.940298,56.440254],"type":"Point"}
}
