{
  "type": "Feature",
  "properties": {
    "iso:country":"GB",
    "wof:name":"RM7 8EP",
    "wof:placetype":"postalcode"
},
  "geometry": {"coordinates":[0.15939333598346,51.58726499906522],"type":"Point"}
}