{
  "type": "Feature",
  "properties": {
    "iso:country":"GB",
    "wof:name":"NN1 1ET",
    "wof:placetype":"postalcode"
},
  "geometry": {"coordinates":[-0.90531340313565,52.23183118998867],"type":"Point"}
}