{
  "type": "Feature",
  "properties": {
    "iso:country":"GB",
    "wof:name":"TN12 6AE",
    "wof:placetype":"postalcode"
},
  "geometry": {"coordinates":[0.38601600255067,51.18007164565946],"type":"Point"}
}