{
  "type": "Feature",
  "properties": {
    "iso:country":"GB",
    "wof:name":"W3 7BU",
    "wof:placetype":"postalcode"
},
  "geometry": {"coordinates":[-0.25101376361065,51.50861782964999],"type":"Point"}
}