{
  "type": "Feature",
  "properties": {
    "date:inception_lower":"2000-10-01",
    "date:inception_upper":"2000-10-31",
    "iso:country":"GB",
    "wof:name":"W1F 9NG",
    "wof:placetype":"postalcode"
},
  "geometry": {"coordinates":[-0.136604,51.512629],"type":"Point"}
}