{
  "type": "Feature",
  "properties": {
    "iso:country":"GB",
    "wof:name":"W1F 9NG",
    "wof:placetype":"postalcode"
},
  "geometry": {"coordinates":[-0.13660382060905,51.51262912410807],"type":"Point"}
}