{
  "type": "Feature",
  "properties": {
    "iso:country":"GB",
    "wof:name":"RG41 2YB",
    "wof:placetype":"postalcode"
},
  "geometry": {"coordinates":[-0.84567025453252,51.41151739719315],"type":"Point"}
}