{
  "type": "Feature",
  "properties": {
    "iso:country":"GB",
    "wof:name":"LL12 8LU",
    "wof:placetype":"postalcode"
},
  "geometry": {"coordinates":[-2.95786349451269,53.08772381639012],"type":"Point"}
}