{
  "type": "Feature",
  "properties": {
    "date:inception_lower":"1983-03-01",
    "date:inception_upper":"1983-03-31",
    "iso:country":"GB",
    "wof:name":"NE40 4QJ",
    "wof:placetype":"postalcode"
},
  "geometry": {"coordinates":[-1.772083,54.955758],"type":"Point"}
}