{
  "type": "Feature",
  "properties": {
    "iso:country": "GB",
    "wof:name": "NE40 4QJ",
    "wof:placetype": "postalcode"
  },
  "geometry": {"coordinates":[-1.772083,54.955758],"type":"Point"}
}
