{
  "type": "Feature",
  "properties": {
    "iso:country":"GB",
    "wof:name":"NE40 4QJ",
    "wof:placetype":"postalcode"
},
  "geometry": {"coordinates":[-1.7720832924667,54.9557584782366],"type":"Point"}
}