{
  "type": "Feature",
  "properties": {
    "date:inception_lower": "1992-08-01",
    "date:inception_upper": "1992-08-01",
    "iso:country": "GB",
    "wof:name": "MK5 6JF",
    "wof:placetype": "postalcode"
  },
  "geometry": {"coordinates":[-0.788359,52.025146],"type":"Point"}
}
