{
  "type": "Feature",
  "properties": {
    "date:inception_lower":"1980-01-01",
    "date:inception_upper":"1980-01-31",
    "iso:country":"GB",
    "wof:name":"M18 7LJ",
    "wof:placetype":"postalcode"
},
  "geometry": {"coordinates":[-2.161069,53.4601],"type":"Point"}
}