{
  "type": "Feature",
  "properties": {
    "iso:country":"GB",
    "wof:name":"M18 7LJ",
    "wof:placetype":"postalcode"
},
  "geometry": {"coordinates":[-2.16106861657236,53.46009977638166],"type":"Point"}
}