{
  "type": "Feature",
  "properties": {
    "date:inception_lower": "1996-06-01",
    "date:inception_upper": "1996-06-01",
    "iso:country": "GB",
    "wof:name": "BH24 1EW",
    "wof:placetype": "postalcode"
  },
  "geometry": {"coordinates":[-1.789359,50.843713],"type":"Point"}
}
