{
  "type": "Feature",
  "properties": {
    "iso:country":"GB",
    "wof:name":"BH24 1EW",
    "wof:placetype":"postalcode"
},
  "geometry": {"coordinates":[-1.78935881457672,50.84371309284401],"type":"Point"}
}