{
  "type": "Feature",
  "properties": {
    "iso:country": "GB",
    "wof:name": "TQ13 9QP",
    "wof:placetype": "postalcode"
  },
  "geometry": {"coordinates":[-3.673721,50.592121],"type":"Point"}
}
