{
  "type": "Feature",
  "properties": {
    "iso:country":"GB",
    "wof:name":"FY8 4FB",
    "wof:placetype":"postalcode"
},
  "geometry": {"coordinates":[-2.98831398176513,53.75612389711002],"type":"Point"}
}