{
  "type": "Feature",
  "properties": {
    "iso:country": "GB",
    "wof:name": "FY8 4FB",
    "wof:placetype": "postalcode"
  },
  "geometry": {"coordinates":[-2.988314,53.756124],"type":"Point"}
}
