{
  "type": "Feature",
  "properties": {
    "iso:country": "GB",
    "wof:name": "NN18 0LR",
    "wof:placetype": "postalcode"
  },
  "geometry": {"coordinates":[-0.722902,52.482224],"type":"Point"}
}
