{
  "type": "Feature",
  "properties": {
    "iso:country":"GB",
    "wof:name":"NN18 0LR",
    "wof:placetype":"postalcode"
},
  "geometry": {"coordinates":[-0.72290246276213,52.4822242407625],"type":"Point"}
}