{
  "type": "Feature",
  "properties": {
    "date:inception_lower": "1980-01-01",
    "date:inception_upper": "1980-01-01",
    "iso:country": "GB",
    "wof:name": "NR18 9QR",
    "wof:placetype": "postalcode"
  },
  "geometry": {"coordinates":[1.058642,52.567159],"type":"Point"}
}
