{
  "type": "Feature",
  "properties": {
    "iso:country":"GB",
    "wof:name":"BL0 0LJ",
    "wof:placetype":"postalcode"
},
  "geometry": {"coordinates":[-2.30535402705099,53.6696687464238],"type":"Point"}
}