{
  "type": "Feature",
  "properties": {
    "iso:country": "GB",
    "wof:name": "SA65 9HU",
    "wof:placetype": "postalcode"
  },
  "geometry": {"coordinates":[-4.975002,51.990458],"type":"Point"}
}
