{
  "type": "Feature",
  "properties": {
    "iso:country": "GB",
    "wof:name": "HG4 3AT",
    "wof:placetype": "postalcode"
  },
  "geometry": {"coordinates":[-1.528012,54.117356],"type":"Point"}
}
