{
  "type": "Feature",
  "properties": {
    "date:inception_lower": "1990-02-01",
    "date:inception_upper": "1990-02-01",
    "iso:country": "GB",
    "wof:name": "HG4 3AT",
    "wof:placetype": "postalcode"
  },
  "geometry": {"coordinates":[-1.528012,54.117356],"type":"Point"}
}
