{
  "type": "Feature",
  "properties": {
    "iso:country":"GB",
    "wof:name":"W1U 1EX",
    "wof:placetype":"postalcode"
},
  "geometry": {"coordinates":[-0.15066861565905,51.51550451856464],"type":"Point"}
}