{
  "type": "Feature",
  "properties": {
    "iso:country":"GB",
    "wof:name":"CB7 4BH",
    "wof:placetype":"postalcode"
},
  "geometry": {"coordinates":[0.26661143446172,52.3964745585084],"type":"Point"}
}