{
  "type": "Feature",
  "properties": {
    "date:inception_lower": "1980-01-01",
    "date:inception_upper": "1980-01-01",
    "iso:country": "GB",
    "wof:name": "CV7 8DG",
    "wof:placetype": "postalcode"
  },
  "geometry": {"coordinates":[-1.567859,52.491489],"type":"Point"}
}
