{
  "type": "Feature",
  "properties": {
    "iso:country":"GB",
    "wof:name":"CF23 8FE",
    "wof:placetype":"postalcode"
},
  "geometry": {"coordinates":[-3.13941101357221,51.53185297645177],"type":"Point"}
}