{
  "type": "Feature",
  "properties": {
    "iso:country": "GB",
    "wof:name": "CF23 8FE",
    "wof:placetype": "postalcode"
  },
  "geometry": {"coordinates":[-3.139411,51.531853],"type":"Point"}
}
