{
  "type": "Feature",
  "properties": {
    "iso:country":"GB",
    "wof:name":"SW4 9HT",
    "wof:placetype":"postalcode"
},
  "geometry": {"coordinates":[-0.14073248960442,51.45438696801202],"type":"Point"}
}