{
  "type": "Feature",
  "properties": {
    "date:inception_lower":"1980-01-01",
    "date:inception_upper":"1980-01-31",
    "iso:country":"GB",
    "wof:name":"SW4 9HT",
    "wof:placetype":"postalcode"
},
  "geometry": {"coordinates":[-0.140732,51.454387],"type":"Point"}
}