{
  "type": "Feature",
  "properties": {
    "iso:country":"GB",
    "wof:name":"B12 8NH",
    "wof:placetype":"postalcode"
},
  "geometry": {"coordinates":[-1.8805314197807,52.4573193706681],"type":"Point"}
}