{
  "type": "Feature",
  "properties": {
    "iso:country": "GB",
    "wof:name": "BN27 4BD",
    "wof:placetype": "postalcode"
  },
  "geometry": {"coordinates":[0.221648,50.880581],"type":"Point"}
}
