{
  "type": "Feature",
  "properties": {
    "iso:country":"GB",
    "wof:name":"BN27 4BD",
    "wof:placetype":"postalcode"
},
  "geometry": {"coordinates":[0.22184851775716,50.88060823465173],"type":"Point"}
}