{
  "type": "Feature",
  "properties": {
    "iso:country":"GB",
    "wof:name":"MK41 0RZ",
    "wof:placetype":"postalcode"
},
  "geometry": {"coordinates":[-0.4278620957621,52.13786509775904],"type":"Point"}
}