{
  "type": "Feature",
  "properties": {
    "date:inception_lower": "1994-05-01",
    "date:inception_upper": "1994-05-01",
    "iso:country": "GB",
    "wof:name": "MK41 0RZ",
    "wof:placetype": "postalcode"
  },
  "geometry": {"coordinates":[-0.427854,52.137895],"type":"Point"}
}
