{
  "type": "Feature",
  "properties": {
    "iso:country":"GB",
    "wof:name":"LS12 1XD",
    "wof:placetype":"postalcode"
},
  "geometry": {"coordinates":[-1.59128303884368,53.79649914714386],"type":"Point"}
}