{
  "type": "Feature",
  "properties": {
    "date:inception_lower": "2018-11-01",
    "date:inception_upper": "2018-11-01",
    "iso:country": "GB",
    "wof:name": "IV12 5SW",
    "wof:placetype": "postalcode"
  },
  "geometry": {"coordinates":[-3.835261,57.589348],"type":"Point"}
}
