{
  "type": "Feature",
  "properties": {
    "iso:country":"GB",
    "wof:name":"NE30 4QN",
    "wof:placetype":"postalcode"
},
  "geometry": {"coordinates":[-1.43333833123534,55.03600557728577],"type":"Point"}
}