{
  "type": "Feature",
  "properties": {
    "iso:country": "GB",
    "wof:name": "HR7 4RY",
    "wof:placetype": "postalcode"
  },
  "geometry": {"coordinates":[-2.541662,52.187529],"type":"Point"}
}
