{
  "type": "Feature",
  "properties": {
    "iso:country":"GB",
    "wof:name":"HR7 4RY",
    "wof:placetype":"postalcode"
},
  "geometry": {"coordinates":[-2.54160546201034,52.18751709586251],"type":"Point"}
}