{
  "type": "Feature",
  "properties": {
    "iso:country":"GB",
    "wof:name":"EX12 2QB",
    "wof:placetype":"postalcode"
},
  "geometry": {"coordinates":[-3.08862503889278,50.70119488404442],"type":"Point"}
}