{
  "type": "Feature",
  "properties": {
    "iso:country":"GB",
    "wof:name":"DL2 3JD",
    "wof:placetype":"postalcode"
},
  "geometry": {"coordinates":[-1.74289403204761,54.58591378208592],"type":"Point"}
}