{
  "type": "Feature",
  "properties": {
    "iso:country": "GB",
    "wof:name": "DL2 3JD",
    "wof:placetype": "postalcode"
  },
  "geometry": {"coordinates":[-1.742894,54.585914],"type":"Point"}
}
