{
  "type": "Feature",
  "properties": {
    "iso:country":"GB",
    "wof:name":"HR6 0RJ",
    "wof:placetype":"postalcode"
},
  "geometry": {"coordinates":[-2.73244111385693,52.22074041426215],"type":"Point"}
}