{
  "type": "Feature",
  "properties": {
    "date:inception_lower": "1981-06-01",
    "date:inception_upper": "1981-06-01",
    "iso:country": "GB",
    "wof:name": "HR6 0RJ",
    "wof:placetype": "postalcode"
  },
  "geometry": {"coordinates":[-2.732575,52.220931],"type":"Point"}
}
