{
  "type": "Feature",
  "properties": {
    "iso:country":"GB",
    "wof:name":"UB6 8RQ",
    "wof:placetype":"postalcode"
},
  "geometry": {"coordinates":[-0.34811058813265,51.5341067745076],"type":"Point"}
}