{
  "type": "Feature",
  "properties": {
    "iso:country":"GB",
    "wof:name":"LU7 3AN",
    "wof:placetype":"postalcode"
},
  "geometry": {"coordinates":[-0.6571398482185,51.9379461986785],"type":"Point"}
}