{
  "type": "Feature",
  "properties": {
    "iso:country": "GB",
    "wof:name": "LU7 3AN",
    "wof:placetype": "postalcode"
  },
  "geometry": {"coordinates":[-0.657115,51.937956],"type":"Point"}
}
