{
  "type": "Feature",
  "properties": {
    "iso:country":"GB",
    "wof:name":"S8 7TD",
    "wof:placetype":"postalcode"
},
  "geometry": {"coordinates":[-1.48369957496685,53.3307541621307],"type":"Point"}
}