{
  "type": "Feature",
  "properties": {
    "iso:country": "GB",
    "wof:name": "G15 7SQ",
    "wof:placetype": "postalcode"
  },
  "geometry": {"coordinates":[-4.367037,55.91397],"type":"Point"}
}
