{
  "type": "Feature",
  "properties": {
    "iso:country": "GB",
    "wof:name": "SA1 6RX",
    "wof:placetype": "postalcode"
  },
  "geometry": {"coordinates":[-3.969591,51.632204],"type":"Point"}
}
