{
  "type": "Feature",
  "properties": {
    "iso:country": "GB",
    "wof:name": "S12 4XJ",
    "wof:placetype": "postalcode"
  },
  "geometry": {"coordinates":[-1.404786,53.34628],"type":"Point"}
}
