{
  "type": "Feature",
  "properties": {
    "iso:country":"GB",
    "wof:name":"S12 4XJ",
    "wof:placetype":"postalcode"
},
  "geometry": {"coordinates":[-1.40478747730043,53.34623403235246],"type":"Point"}
}