{
  "type": "Feature",
  "properties": {
    "date:inception_lower":"1984-02-01",
    "date:inception_upper":"1984-02-29",
    "iso:country":"GB",
    "wof:name":"GU35 9PS",
    "wof:placetype":"postalcode"
},
  "geometry": {"coordinates":[-0.86239,51.103859],"type":"Point"}
}