{
  "type": "Feature",
  "properties": {
    "date:inception_lower":"1980-01-01",
    "date:inception_upper":"1980-01-31",
    "iso:country":"GB",
    "wof:name":"WV12 4AW",
    "wof:placetype":"postalcode"
},
  "geometry": {"coordinates":[-2.031451,52.60311],"type":"Point"}
}