{
  "type": "Feature",
  "properties": {
    "date:inception_lower":"1980-01-01",
    "date:inception_upper":"1980-01-31",
    "iso:country":"GB",
    "wof:name":"BA11 2DW",
    "wof:placetype":"postalcode"
},
  "geometry": {"coordinates":[-2.302117,51.235571],"type":"Point"}
}