{
  "type": "Feature",
  "properties": {
    "iso:country":"GB",
    "wof:name":"NR12 8BL",
    "wof:placetype":"postalcode"
},
  "geometry": {"coordinates":[1.47859319031274,52.72759294492243],"type":"Point"}
}