{
  "type": "Feature",
  "properties": {
    "iso:country":"GB",
    "wof:name":"NW2 5UE",
    "wof:placetype":"postalcode"
},
  "geometry": {"coordinates":[-0.2283802300428,51.54933737726533],"type":"Point"}
}