{
  "type": "Feature",
  "properties": {
    "iso:country":"GB",
    "wof:name":"N11 2PP",
    "wof:placetype":"postalcode"
},
  "geometry": {"coordinates":[-0.1226580976524,51.60534385060022],"type":"Point"}
}