{
  "type": "Feature",
  "properties": {
    "date:inception_lower": "1980-01-01",
    "date:inception_upper": "1980-01-01",
    "iso:country": "GB",
    "wof:name": "N11 2PP",
    "wof:placetype": "postalcode"
  },
  "geometry": {"coordinates":[-0.12266,51.605392],"type":"Point"}
}
