{
  "type": "Feature",
  "properties": {
    "iso:country":"GB",
    "wof:name":"NG1 1EQ",
    "wof:placetype":"postalcode"
},
  "geometry": {"coordinates":[-1.14307362590892,52.95557101884814],"type":"Point"}
}