{
  "type": "Feature",
  "properties": {
    "iso:country":"GB",
    "wof:name":"PR7 4NZ",
    "wof:placetype":"postalcode"
},
  "geometry": {"coordinates":[-2.65507871840111,53.6275483918544],"type":"Point"}
}