{
  "type": "Feature",
  "properties": {
    "iso:country": "GB",
    "wof:name": "HA0 4LW",
    "wof:placetype": "postalcode"
  },
  "geometry": {"coordinates":[-0.297729,51.541183],"type":"Point"}
}
