{
  "type": "Feature",
  "properties": {
    "iso:country": "GB",
    "wof:name": "LL58 8TA",
    "wof:placetype": "postalcode"
  },
  "geometry": {"coordinates":[-4.090149,53.30843],"type":"Point"}
}
