{
  "type": "Feature",
  "properties": {
    "iso:country":"GB",
    "wof:name":"LL58 8TA",
    "wof:placetype":"postalcode"
},
  "geometry": {"coordinates":[-4.09014951044898,53.3084295669942],"type":"Point"}
}