{
  "type": "Feature",
  "properties": {
    "iso:country": "GB",
    "wof:name": "LS25 2BT",
    "wof:placetype": "postalcode"
  },
  "geometry": {"coordinates":[-1.379706,53.784734],"type":"Point"}
}
