{
  "type": "Feature",
  "properties": {
    "date:inception_lower": "1980-01-01",
    "date:inception_upper": "1980-01-01",
    "iso:country": "GB",
    "wof:name": "SR5 1ND",
    "wof:placetype": "postalcode"
  },
  "geometry": {"coordinates":[-1.386797,54.924781],"type":"Point"}
}
