{
  "type": "Feature",
  "properties": {
    "iso:country":"GB",
    "wof:name":"SR5 1ND",
    "wof:placetype":"postalcode"
},
  "geometry": {"coordinates":[-1.38679682597895,54.92478061978064],"type":"Point"}
}