{
  "type": "Feature",
  "properties": {
    "date:inception_lower": "1988-03-01",
    "date:inception_upper": "1988-03-01",
    "iso:country": "GB",
    "wof:name": "DL14 8QX",
    "wof:placetype": "postalcode"
  },
  "geometry": {"coordinates":[-1.635347,54.664712],"type":"Point"}
}
