{
  "type": "Feature",
  "properties": {
    "iso:country":"GB",
    "wof:name":"DL14 8QX",
    "wof:placetype":"postalcode"
},
  "geometry": {"coordinates":[-1.63534694663238,54.66471241516413],"type":"Point"}
}