{
  "type": "Feature",
  "properties": {
    "iso:country":"GB",
    "wof:name":"BD8 8EJ",
    "wof:placetype":"postalcode"
},
  "geometry": {"coordinates":[-1.76629356019502,53.79916954702273],"type":"Point"}
}