{
  "type": "Feature",
  "properties": {
    "iso:country":"GB",
    "wof:name":"EX31 4RE",
    "wof:placetype":"postalcode"
},
  "geometry": {"coordinates":[-3.93802660214239,51.12187580906134],"type":"Point"}
}