{
  "type": "Feature",
  "properties": {
    "date:inception_lower": "2003-04-01",
    "date:inception_upper": "2003-04-01",
    "iso:country": "GB",
    "wof:name": "G82 5QD",
    "wof:placetype": "postalcode"
  },
  "geometry": {"coordinates":[-4.650785,55.963698],"type":"Point"}
}
