{
  "type": "Feature",
  "properties": {
    "iso:country": "GB",
    "wof:name": "NG15 6EG",
    "wof:placetype": "postalcode"
  },
  "geometry": {"coordinates":[-1.219822,53.024123],"type":"Point"}
}
