{
  "type": "Feature",
  "properties": {
    "date:inception_lower": "2001-12-01",
    "date:inception_upper": "2001-12-01",
    "iso:country": "GB",
    "wof:name": "NG15 6EG",
    "wof:placetype": "postalcode"
  },
  "geometry": {"coordinates":[-1.219822,53.024123],"type":"Point"}
}
