{
  "type": "Feature",
  "properties": {
    "iso:country": "GB",
    "wof:name": "SW11 8LZ",
    "wof:placetype": "postalcode"
  },
  "geometry": {"coordinates":[-0.148207,51.478921],"type":"Point"}
}
