{
  "type": "Feature",
  "properties": {
    "iso:country":"GB",
    "wof:name":"NE21 6BX",
    "wof:placetype":"postalcode"
},
  "geometry": {"coordinates":[-1.7287084818668,54.9551752983411],"type":"Point"}
}