{
  "type": "Feature",
  "properties": {
    "date:inception_lower":"1997-06-01",
    "date:inception_upper":"1997-06-30",
    "iso:country":"GB",
    "wof:name":"CH5 3TZ",
    "wof:placetype":"postalcode"
},
  "geometry": {"coordinates":[-3.060424,53.183508],"type":"Point"}
}