{
  "type": "Feature",
  "properties": {
    "iso:country":"GB",
    "wof:name":"CH5 3TZ",
    "wof:placetype":"postalcode"
},
  "geometry": {"coordinates":[-3.06042416380996,53.18350786269811],"type":"Point"}
}