{
  "type": "Feature",
  "properties": {
    "iso:country": "GB",
    "wof:name": "OL9 7SN",
    "wof:placetype": "postalcode"
  },
  "geometry": {"coordinates":[-2.133395,53.534864],"type":"Point"}
}
