{
  "type": "Feature",
  "properties": {
    "date:inception_lower":"1980-01-01",
    "date:inception_upper":"1980-01-31",
    "iso:country":"GB",
    "wof:name":"OL9 7SN",
    "wof:placetype":"postalcode"
},
  "geometry": {"coordinates":[-2.133395,53.534864],"type":"Point"}
}