{
  "type": "Feature",
  "properties": {
    "iso:country":"GB",
    "wof:name":"CA3 9NS",
    "wof:placetype":"postalcode"
},
  "geometry": {"coordinates":[-2.94074230520874,54.90089084238564],"type":"Point"}
}