{
  "type": "Feature",
  "properties": {
    "iso:country":"GB",
    "wof:name":"ST14 5HU",
    "wof:placetype":"postalcode"
},
  "geometry": {"coordinates":[-1.85905641198978,52.95548249679466],"type":"Point"}
}