{
  "type": "Feature",
  "properties": {
    "iso:country":"GB",
    "wof:name":"NE1 3BA",
    "wof:placetype":"postalcode"
},
  "geometry": {"coordinates":[-1.61159167915222,54.96703428672775],"type":"Point"}
}