{
  "type": "Feature",
  "properties": {
    "iso:country":"GB",
    "wof:name":"S43 4ED",
    "wof:placetype":"postalcode"
},
  "geometry": {"coordinates":[-1.26594500330878,53.27284872350637],"type":"Point"}
}