{
  "type": "Feature",
  "properties": {
    "date:inception_lower": "2024-07-01",
    "date:inception_upper": "2024-07-01",
    "iso:country": "GB",
    "wof:name": "NN17 5DN",
    "wof:placetype": "postalcode"
  },
  "geometry": {"coordinates":[-0.64038,52.516583],"type":"Point"}
}
