{
  "type": "Feature",
  "properties": {
    "iso:country": "GB",
    "wof:name": "EX4 3FD",
    "wof:placetype": "postalcode"
  },
  "geometry": {"coordinates":[-3.535368,50.722838],"type":"Point"}
}
