{
  "type": "Feature",
  "properties": {
    "date:inception_lower":"2006-11-01",
    "date:inception_upper":"2006-11-30",
    "iso:country":"GB",
    "wof:name":"TW3 3RJ",
    "wof:placetype":"postalcode"
},
  "geometry": {"coordinates":[-0.370877,51.466228],"type":"Point"}
}