{
  "type": "Feature",
  "properties": {
    "iso:country":"GB",
    "wof:name":"TW3 3RJ",
    "wof:placetype":"postalcode"
},
  "geometry": {"coordinates":[-0.37087687415003,51.46622768688421],"type":"Point"}
}