{
  "type": "Feature",
  "properties": {
    "iso:country":"GB",
    "wof:name":"NE5 2SX",
    "wof:placetype":"postalcode"
},
  "geometry": {"coordinates":[-1.67943820905435,54.98921221642432],"type":"Point"}
}