{
  "type": "Feature",
  "properties": {
    "iso:country":"GB",
    "wof:name":"NE3 3UW",
    "wof:placetype":"postalcode"
},
  "geometry": {"coordinates":[-1.63894638513394,55.01004573989179],"type":"Point"}
}