{
  "type": "Feature",
  "properties": {
    "date:inception_lower":"1980-01-01",
    "date:inception_upper":"1980-01-31",
    "iso:country":"GB",
    "wof:name":"NR1 3HS",
    "wof:placetype":"postalcode"
},
  "geometry": {"coordinates":[1.295909,52.618849],"type":"Point"}
}