{
  "type": "Feature",
  "properties": {
    "iso:country": "GB",
    "wof:name": "KT2 5AH",
    "wof:placetype": "postalcode"
  },
  "geometry": {"coordinates":[-0.304908,51.413811],"type":"Point"}
}
