{
  "type": "Feature",
  "properties": {
    "iso:country":"GB",
    "wof:name":"KT2 5AH",
    "wof:placetype":"postalcode"
},
  "geometry": {"coordinates":[-0.30490849628793,51.41381089708557],"type":"Point"}
}