{
  "type": "Feature",
  "properties": {
    "date:inception_lower":"2015-10-01",
    "date:inception_upper":"2015-10-31",
    "iso:country":"GB",
    "wof:name":"SA8 4JZ",
    "wof:placetype":"postalcode"
},
  "geometry": {"coordinates":[-3.849263,51.725772],"type":"Point"}
}