{
  "type": "Feature",
  "properties": {
    "iso:country": "GB",
    "wof:name": "SA8 4JZ",
    "wof:placetype": "postalcode"
  },
  "geometry": {"coordinates":[-3.849263,51.725772],"type":"Point"}
}
