{
  "type": "Feature",
  "properties": {
    "iso:country":"GB",
    "wof:name":"SA8 4JZ",
    "wof:placetype":"postalcode"
},
  "geometry": {"coordinates":[-3.84876756200352,51.72571913774288],"type":"Point"}
}