{
  "type": "Feature",
  "properties": {
    "iso:country": "GB",
    "wof:name": "S41 0SG",
    "wof:placetype": "postalcode"
  },
  "geometry": {"coordinates":[-1.412959,53.224664],"type":"Point"}
}
