{
  "type": "Feature",
  "properties": {
    "iso:country": "GB",
    "wof:name": "TF9 4FD",
    "wof:placetype": "postalcode"
  },
  "geometry": {"coordinates":[-2.391876,52.920154],"type":"Point"}
}
