{
  "type": "Feature",
  "properties": {
    "iso:country":"GB",
    "wof:name":"EH4 4SN",
    "wof:placetype":"postalcode"
},
  "geometry": {"coordinates":[-3.26438524128063,55.97270442623385],"type":"Point"}
}