{
  "type": "Feature",
  "properties": {
    "date:inception_lower": "1980-01-01",
    "date:inception_upper": "1980-01-01",
    "iso:country": "GB",
    "wof:name": "EN9 1TD",
    "wof:placetype": "postalcode"
  },
  "geometry": {"coordinates":[0.010658,51.681374],"type":"Point"}
}
