{
  "type": "Feature",
  "properties": {
    "date:inception_lower": "1980-01-01",
    "date:inception_upper": "1980-01-01",
    "iso:country": "GB",
    "wof:name": "SM7 3EL",
    "wof:placetype": "postalcode"
  },
  "geometry": {"coordinates":[-0.186521,51.313974],"type":"Point"}
}
