{
  "type": "Feature",
  "properties": {
    "iso:country": "GB",
    "wof:name": "SM7 3EL",
    "wof:placetype": "postalcode"
  },
  "geometry": {"coordinates":[-0.186521,51.313974],"type":"Point"}
}
