{
  "type": "Feature",
  "properties": {
    "iso:country":"GB",
    "wof:name":"EH32 9DL",
    "wof:placetype":"postalcode"
},
  "geometry": {"coordinates":[-2.99089293539778,55.9555291955178],"type":"Point"}
}