{
  "type": "Feature",
  "properties": {
    "date:inception_lower": "2005-02-01",
    "date:inception_upper": "2005-02-01",
    "iso:country": "GB",
    "wof:name": "CM16 9TP",
    "wof:placetype": "postalcode"
  },
  "geometry": {"coordinates":[0.114367,51.701275],"type":"Point"}
}
