{
  "type": "Feature",
  "properties": {
    "iso:country":"GB",
    "wof:name":"W1U 2JE",
    "wof:placetype":"postalcode"
},
  "geometry": {"coordinates":[-0.15062446623185,51.51766202014863],"type":"Point"}
}