{
  "type": "Feature",
  "properties": {
    "iso:country":"GB",
    "wof:name":"SW6 4HD",
    "wof:placetype":"postalcode"
},
  "geometry": {"coordinates":[-0.20240407841622,51.47427804355104],"type":"Point"}
}