{
  "type": "Feature",
  "properties": {
    "date:inception_lower": "2009-01-01",
    "date:inception_upper": "2009-01-01",
    "iso:country": "GB",
    "wof:name": "SW6 4HD",
    "wof:placetype": "postalcode"
  },
  "geometry": {"coordinates":[-0.202404,51.474278],"type":"Point"}
}
