{
  "type": "Feature",
  "properties": {
    "iso:country":"GB",
    "wof:name":"CV34 5BP",
    "wof:placetype":"postalcode"
},
  "geometry": {"coordinates":[-1.58394552594686,52.28867611713817],"type":"Point"}
}