{
  "type": "Feature",
  "properties": {
    "iso:country":"GB",
    "wof:name":"NG32 2NF",
    "wof:placetype":"postalcode"
},
  "geometry": {"coordinates":[-0.61377448070145,52.96444863278267],"type":"Point"}
}