{
  "type": "Feature",
  "properties": {
    "date:inception_lower": "1980-01-01",
    "date:inception_upper": "1980-01-01",
    "iso:country": "GB",
    "wof:name": "BA11 2PU",
    "wof:placetype": "postalcode"
  },
  "geometry": {"coordinates":[-2.259493,51.254389],"type":"Point"}
}
