{
  "type": "Feature",
  "properties": {
    "date:inception_lower": "1980-01-01",
    "date:inception_upper": "1980-01-01",
    "iso:country": "GB",
    "wof:name": "OL10 2NH",
    "wof:placetype": "postalcode"
  },
  "geometry": {"coordinates":[-2.208772,53.580758],"type":"Point"}
}
