{
  "type": "Feature",
  "properties": {
    "date:inception_lower": "1980-01-01",
    "date:inception_upper": "1980-01-01",
    "iso:country": "GB",
    "wof:name": "SA18 2DZ",
    "wof:placetype": "postalcode"
  },
  "geometry": {"coordinates":[-3.921127,51.820019],"type":"Point"}
}
