{
  "type": "Feature",
  "properties": {
    "date:inception_lower": "1997-12-01",
    "date:inception_upper": "1997-12-01",
    "iso:country": "GB",
    "wof:name": "NP8 1BX",
    "wof:placetype": "postalcode"
  },
  "geometry": {"coordinates":[-3.13384,51.8592],"type":"Point"}
}
