{
  "type": "Feature",
  "properties": {
    "iso:country": "GB",
    "wof:name": "NP8 1BX",
    "wof:placetype": "postalcode"
  },
  "geometry": {"coordinates":[-3.13384,51.8592],"type":"Point"}
}
