{
  "type": "Feature",
  "properties": {
    "iso:country":"GB",
    "wof:name":"NP8 1BX",
    "wof:placetype":"postalcode"
},
  "geometry": {"coordinates":[-3.13383971384392,51.85920006599383],"type":"Point"}
}