{
  "type": "Feature",
  "properties": {
    "iso:country":"GB",
    "wof:name":"BN41 2WJ",
    "wof:placetype":"postalcode"
},
  "geometry": {"coordinates":[-0.23030307516275,50.85259190918382],"type":"Point"}
}