{
  "type": "Feature",
  "properties": {
    "iso:country":"GB",
    "wof:name":"BS8 3SQ",
    "wof:placetype":"postalcode"
},
  "geometry": {"coordinates":[-2.68749426033559,51.4563182756691],"type":"Point"}
}