{
  "type": "Feature",
  "properties": {
    "iso:country": "GB",
    "wof:name": "BS39 7SN",
    "wof:placetype": "postalcode"
  },
  "geometry": {"coordinates":[-2.494508,51.295422],"type":"Point"}
}
