{
  "type": "Feature",
  "properties": {
    "iso:country":"GB",
    "wof:name":"DE24 0NR",
    "wof:placetype":"postalcode"
},
  "geometry": {"coordinates":[-1.42188531693095,52.89021050230195],"type":"Point"}
}