{
  "type": "Feature",
  "properties": {
    "iso:country": "GB",
    "wof:name": "DE24 0NR",
    "wof:placetype": "postalcode"
  },
  "geometry": {"coordinates":[-1.421885,52.89021],"type":"Point"}
}
