{
  "type": "Feature",
  "properties": {
    "date:inception_lower":"1995-07-01",
    "date:inception_upper":"1995-07-31",
    "iso:country":"GB",
    "wof:name":"HS2 0RT",
    "wof:placetype":"postalcode"
},
  "geometry": {"coordinates":[-6.437781,58.413779],"type":"Point"}
}