{
  "type": "Feature",
  "properties": {
    "iso:country":"GB",
    "wof:name":"HS2 0RT",
    "wof:placetype":"postalcode"
},
  "geometry": {"coordinates":[-6.43778096051899,58.41377856551401],"type":"Point"}
}