{
  "type": "Feature",
  "properties": {
    "date:inception_lower": "1980-01-01",
    "date:inception_upper": "1980-01-01",
    "iso:country": "GB",
    "wof:name": "SN8 1JZ",
    "wof:placetype": "postalcode"
  },
  "geometry": {"coordinates":[-1.734444,51.423274],"type":"Point"}
}
