{
  "type": "Feature",
  "properties": {
    "iso:country":"GB",
    "wof:name":"DA15 8WN",
    "wof:placetype":"postalcode"
},
  "geometry": {"coordinates":[0.10113625623826,51.44052591986286],"type":"Point"}
}