{
  "type": "Feature",
  "properties": {
    "iso:country": "GB",
    "wof:name": "DA15 8WN",
    "wof:placetype": "postalcode"
  },
  "geometry": {"coordinates":[0.101136,51.440526],"type":"Point"}
}
