{
  "type": "Feature",
  "properties": {
    "iso:country":"GB",
    "wof:name":"TN25 7FB",
    "wof:placetype":"postalcode"
},
  "geometry": {"coordinates":[0.89332097078685,51.11891548589755],"type":"Point"}
}