{
  "type": "Feature",
  "properties": {
    "date:inception_lower": "2015-04-01",
    "date:inception_upper": "2015-04-01",
    "iso:country": "GB",
    "wof:name": "TN25 7FB",
    "wof:placetype": "postalcode"
  },
  "geometry": {"coordinates":[0.893663,51.118844],"type":"Point"}
}
