{
  "type": "Feature",
  "properties": {
    "iso:country":"GB",
    "wof:name":"DG1 3PQ",
    "wof:placetype":"postalcode"
},
  "geometry": {"coordinates":[-3.56793384445638,55.09775221813931],"type":"Point"}
}