{
  "type": "Feature",
  "properties": {
    "date:inception_lower": "1981-06-01",
    "date:inception_upper": "1981-06-01",
    "iso:country": "GB",
    "wof:name": "DG1 3PQ",
    "wof:placetype": "postalcode"
  },
  "geometry": {"coordinates":[-3.567915,55.097757],"type":"Point"}
}
