{
  "type": "Feature",
  "properties": {
    "iso:country": "GB",
    "wof:name": "DG1 3PQ",
    "wof:placetype": "postalcode"
  },
  "geometry": {"coordinates":[-3.567918,55.097752],"type":"Point"}
}
