{
  "type": "Feature",
  "properties": {
    "iso:country":"GB",
    "wof:name":"PR1 5EB",
    "wof:placetype":"postalcode"
},
  "geometry": {"coordinates":[-2.67943360398556,53.76638961440243],"type":"Point"}
}