{
  "type": "Feature",
  "properties": {
    "date:inception_lower":"1980-01-01",
    "date:inception_upper":"1980-01-31",
    "iso:country":"GB",
    "wof:name":"SK8 6SF",
    "wof:placetype":"postalcode"
},
  "geometry": {"coordinates":[-2.204626,53.369518],"type":"Point"}
}