{
  "type": "Feature",
  "properties": {
    "iso:country":"GB",
    "wof:name":"DL1 4SR",
    "wof:placetype":"postalcode"
},
  "geometry": {"coordinates":[-1.52221132054008,54.51719534654885],"type":"Point"}
}