{
  "type": "Feature",
  "properties": {
    "iso:country":"GB",
    "wof:name":"EH54 9BB",
    "wof:placetype":"postalcode"
},
  "geometry": {"coordinates":[-3.49740604493138,55.87066394465526],"type":"Point"}
}