{
  "type": "Feature",
  "properties": {
    "date:inception_lower": "1980-01-01",
    "date:inception_upper": "1980-01-01",
    "iso:country": "GB",
    "wof:name": "EH54 9BB",
    "wof:placetype": "postalcode"
  },
  "geometry": {"coordinates":[-3.497402,55.87066],"type":"Point"}
}
