{
  "type": "Feature",
  "properties": {
    "date:inception_lower": "1980-01-01",
    "date:inception_upper": "1980-01-01",
    "iso:country": "GB",
    "wof:name": "W8 4RS",
    "wof:placetype": "postalcode"
  },
  "geometry": {"coordinates":[-0.193143,51.507857],"type":"Point"}
}
