{
  "type": "Feature",
  "properties": {
    "iso:country":"GB",
    "wof:name":"W8 4RS",
    "wof:placetype":"postalcode"
},
  "geometry": {"coordinates":[-0.19314274231937,51.50785748725525],"type":"Point"}
}