{
  "type": "Feature",
  "properties": {
    "date:inception_lower": "1990-02-01",
    "date:inception_upper": "1990-02-01",
    "iso:country": "GB",
    "wof:name": "PE10 9SR",
    "wof:placetype": "postalcode"
  },
  "geometry": {"coordinates":[-0.38291,52.776331],"type":"Point"}
}
