{
  "type": "Feature",
  "properties": {
    "iso:country":"GB",
    "wof:name":"IP24 1HG",
    "wof:placetype":"postalcode"
},
  "geometry": {"coordinates":[0.74721646529829,52.42733814133958],"type":"Point"}
}