{
  "type": "Feature",
  "properties": {
    "iso:country": "GB",
    "wof:name": "TW20 9JN",
    "wof:placetype": "postalcode"
  },
  "geometry": {"coordinates":[-0.542287,51.432677],"type":"Point"}
}
