{
  "type": "Feature",
  "properties": {
    "iso:country":"GB",
    "wof:name":"TW20 9JN",
    "wof:placetype":"postalcode"
},
  "geometry": {"coordinates":[-0.54228722585727,51.43267694867531],"type":"Point"}
}