{
  "type": "Feature",
  "properties": {
    "iso:country": "GB",
    "wof:name": "EX1 2ZT",
    "wof:placetype": "postalcode"
  },
  "geometry": {"coordinates":[-3.521205,50.72735],"type":"Point"}
}
