{
  "type": "Feature",
  "properties": {
    "iso:country": "GB",
    "wof:name": "IG1 3FA",
    "wof:placetype": "postalcode"
  },
  "geometry": {"coordinates":[0.060595,51.559907],"type":"Point"}
}
