{
  "type": "Feature",
  "properties": {
    "date:inception_lower": "2018-08-01",
    "date:inception_upper": "2018-08-01",
    "iso:country": "GB",
    "wof:name": "IG1 3FA",
    "wof:placetype": "postalcode"
  },
  "geometry": {"coordinates":[0.060554,51.559944],"type":"Point"}
}
