{
  "type": "Feature",
  "properties": {
    "iso:country":"GB",
    "wof:name":"EX6 8QQ",
    "wof:placetype":"postalcode"
},
  "geometry": {"coordinates":[-3.44770018377125,50.62628519352036],"type":"Point"}
}