{
  "type": "Feature",
  "properties": {
    "date:inception_lower":"2009-03-01",
    "date:inception_upper":"2009-03-31",
    "iso:country":"GB",
    "wof:name":"CM92 1LN",
    "wof:placetype":"postalcode"
},
  "geometry": {"coordinates":[0.061253,51.769357],"type":"Point"}
}