{
  "type": "Feature",
  "properties": {
    "date:inception_lower": "1980-01-01",
    "date:inception_upper": "1980-01-01",
    "iso:country": "GB",
    "wof:name": "CV32 7LY",
    "wof:placetype": "postalcode"
  },
  "geometry": {"coordinates":[-1.498386,52.311069],"type":"Point"}
}
