{
  "type": "Feature",
  "properties": {
    "iso:country":"GB",
    "wof:name":"CV32 7LY",
    "wof:placetype":"postalcode"
},
  "geometry": {"coordinates":[-1.49869207695616,52.31089292988961],"type":"Point"}
}