{
  "type": "Feature",
  "properties": {
    "date:inception_lower": "2014-01-01",
    "date:inception_upper": "2014-01-01",
    "iso:country": "GB",
    "wof:name": "G13 2YT",
    "wof:placetype": "postalcode"
  },
  "geometry": {"coordinates":[-4.350319,55.886303],"type":"Point"}
}
