{
  "type": "Feature",
  "properties": {
    "iso:country":"GB",
    "wof:name":"EH48 2LT",
    "wof:placetype":"postalcode"
},
  "geometry": {"coordinates":[-3.68926035122744,55.89682803942939],"type":"Point"}
}