{
  "type": "Feature",
  "properties": {
    "iso:country":"GB",
    "wof:name":"BS4 1EE",
    "wof:placetype":"postalcode"
},
  "geometry": {"coordinates":[-2.57873617264368,51.42726926746408],"type":"Point"}
}