{
  "type": "Feature",
  "properties": {
    "iso:country":"GB",
    "wof:name":"WD18 7QG",
    "wof:placetype":"postalcode"
},
  "geometry": {"coordinates":[-0.41408355028057,51.64865934164975],"type":"Point"}
}