{
  "type": "Feature",
  "properties": {
    "date:inception_lower": "1980-01-01",
    "date:inception_upper": "1980-01-01",
    "iso:country": "GB",
    "wof:name": "GU14 8JA",
    "wof:placetype": "postalcode"
  },
  "geometry": {"coordinates":[-0.751545,51.307431],"type":"Point"}
}
