{
  "type": "Feature",
  "properties": {
    "iso:country": "GB",
    "wof:name": "GU14 8JA",
    "wof:placetype": "postalcode"
  },
  "geometry": {"coordinates":[-0.751545,51.307431],"type":"Point"}
}
