{
  "type": "Feature",
  "properties": {
    "iso:country":"GB",
    "wof:name":"GU14 8JA",
    "wof:placetype":"postalcode"
},
  "geometry": {"coordinates":[-0.75154503047089,51.30743077361253],"type":"Point"}
}