{
  "type": "Feature",
  "properties": {
    "iso:country":"GB",
    "wof:name":"CF23 8NH",
    "wof:placetype":"postalcode"
},
  "geometry": {"coordinates":[-3.13398934703992,51.53297554605967],"type":"Point"}
}