{
  "type": "Feature",
  "properties": {
    "iso:country": "GB",
    "wof:name": "CF23 8NH",
    "wof:placetype": "postalcode"
  },
  "geometry": {"coordinates":[-3.133989,51.532976],"type":"Point"}
}
