{
  "type": "Feature",
  "properties": {
    "iso:country":"GB",
    "wof:name":"KT22 8RF",
    "wof:placetype":"postalcode"
},
  "geometry": {"coordinates":[-0.31698511212339,51.2888627004708],"type":"Point"}
}