{
  "type": "Feature",
  "properties": {
    "iso:country":"GB",
    "wof:name":"KA4 8ET",
    "wof:placetype":"postalcode"
},
  "geometry": {"coordinates":[-4.38669030304779,55.59995794620956],"type":"Point"}
}