{
  "type": "Feature",
  "properties": {
    "iso:country": "GB",
    "wof:name": "KA4 8ET",
    "wof:placetype": "postalcode"
  },
  "geometry": {"coordinates":[-4.38669,55.599958],"type":"Point"}
}
