{
  "type": "Feature",
  "properties": {
    "iso:country":"GB",
    "wof:name":"NR19 2EA",
    "wof:placetype":"postalcode"
},
  "geometry": {"coordinates":[0.9354882405224,52.68378565789261],"type":"Point"}
}