{
  "type": "Feature",
  "properties": {
    "iso:country":"GB",
    "wof:name":"NG19 7HL",
    "wof:placetype":"postalcode"
},
  "geometry": {"coordinates":[-1.21612281260688,53.15836150639533],"type":"Point"}
}