{
  "type": "Feature",
  "properties": {
    "iso:country": "GB",
    "wof:name": "NG19 7HL",
    "wof:placetype": "postalcode"
  },
  "geometry": {"coordinates":[-1.216123,53.158362],"type":"Point"}
}
