{
  "type": "Feature",
  "properties": {
    "iso:country": "GB",
    "wof:name": "LS16 6FG",
    "wof:placetype": "postalcode"
  },
  "geometry": {"coordinates":[-1.615845,53.844855],"type":"Point"}
}
