{
  "type": "Feature",
  "properties": {
    "date:inception_lower":"2011-11-01",
    "date:inception_upper":"2011-11-30",
    "iso:country":"GB",
    "wof:name":"LS16 6FG",
    "wof:placetype":"postalcode"
},
  "geometry": {"coordinates":[-1.615845,53.844855],"type":"Point"}
}