{
  "type": "Feature",
  "properties": {
    "iso:country":"GB",
    "wof:name":"LS16 6FG",
    "wof:placetype":"postalcode"
},
  "geometry": {"coordinates":[-1.61584499294965,53.84485473336689],"type":"Point"}
}