{
  "type": "Feature",
  "properties": {
    "iso:country":"GB",
    "wof:name":"LE5 1AG",
    "wof:placetype":"postalcode"
},
  "geometry": {"coordinates":[-1.07314169244595,52.65619929312207],"type":"Point"}
}