{
  "type": "Feature",
  "properties": {
    "date:inception_lower": "2007-01-01",
    "date:inception_upper": "2007-01-01",
    "iso:country": "GB",
    "wof:name": "LE5 1AG",
    "wof:placetype": "postalcode"
  },
  "geometry": {"coordinates":[-1.073163,52.656236],"type":"Point"}
}
