{
  "type": "Feature",
  "properties": {
    "iso:country":"GB",
    "wof:name":"CA11 9HP",
    "wof:placetype":"postalcode"
},
  "geometry": {"coordinates":[-2.7605699050712,54.67007001738222],"type":"Point"}
}