{
  "type": "Feature",
  "properties": {
    "iso:country":"GB",
    "wof:name":"ME12 1TY",
    "wof:placetype":"postalcode"
},
  "geometry": {"coordinates":[0.76209762025136,51.43955433156287],"type":"Point"}
}