{
  "type": "Feature",
  "properties": {
    "date:inception_lower": "1980-01-01",
    "date:inception_upper": "1980-01-01",
    "iso:country": "GB",
    "wof:name": "ME10 2AH",
    "wof:placetype": "postalcode"
  },
  "geometry": {"coordinates":[0.730968,51.347793],"type":"Point"}
}
