{
  "type": "Feature",
  "properties": {
    "iso:country":"GB",
    "wof:name":"ME10 2AH",
    "wof:placetype":"postalcode"
},
  "geometry": {"coordinates":[0.73098277189636,51.34782660003339],"type":"Point"}
}