{
  "type": "Feature",
  "properties": {
    "iso:country":"GB",
    "wof:name":"DL8 5HU",
    "wof:placetype":"postalcode"
},
  "geometry": {"coordinates":[-1.82748866056433,54.31354228437228],"type":"Point"}
}