{
  "type": "Feature",
  "properties": {
    "iso:country":"GB",
    "wof:name":"HP9 2AG",
    "wof:placetype":"postalcode"
},
  "geometry": {"coordinates":[-0.64785245289968,51.62098429329826],"type":"Point"}
}