{
  "type": "Feature",
  "properties": {
    "iso:country":"GB",
    "wof:name":"L32 9QP",
    "wof:placetype":"postalcode"
},
  "geometry": {"coordinates":[-2.88162101925875,53.47729579437462],"type":"Point"}
}