{
  "type": "Feature",
  "properties": {
    "iso:country":"GB",
    "wof:name":"BD13 3JX",
    "wof:placetype":"postalcode"
},
  "geometry": {"coordinates":[-1.84999526285282,53.79006362480794],"type":"Point"}
}