{
  "type": "Feature",
  "properties": {
    "iso:country":"GB",
    "wof:name":"SE10 0BD",
    "wof:placetype":"postalcode"
},
  "geometry": {"coordinates":[0.01374070885414,51.49462265892846],"type":"Point"}
}