{
  "type": "Feature",
  "properties": {
    "date:inception_lower":"1994-05-01",
    "date:inception_upper":"1994-05-31",
    "iso:country":"GB",
    "wof:name":"M27 9RJ",
    "wof:placetype":"postalcode"
},
  "geometry": {"coordinates":[-2.352965,53.516808],"type":"Point"}
}