{
  "type": "Feature",
  "properties": {
    "iso:country":"GB",
    "wof:name":"M27 9RJ",
    "wof:placetype":"postalcode"
},
  "geometry": {"coordinates":[-2.35296510353577,53.51680834140846],"type":"Point"}
}