{
  "type": "Feature",
  "properties": {
    "iso:country": "GB",
    "wof:name": "SE22 8EA",
    "wof:placetype": "postalcode"
  },
  "geometry": {"coordinates":[-0.078796,51.46025],"type":"Point"}
}
