{
  "type": "Feature",
  "properties": {
    "date:inception_lower": "1983-03-01",
    "date:inception_upper": "1983-03-01",
    "iso:country": "GB",
    "wof:name": "SN3 4UT",
    "wof:placetype": "postalcode"
  },
  "geometry": {"coordinates":[-1.752792,51.591868],"type":"Point"}
}
