{
  "type": "Feature",
  "properties": {
    "iso:country":"GB",
    "wof:name":"M46 0AA",
    "wof:placetype":"postalcode"
},
  "geometry": {"coordinates":[-2.49141772175229,53.52263803624965],"type":"Point"}
}