{
  "type": "Feature",
  "properties": {
    "iso:country":"GB",
    "wof:name":"NE33 5BY",
    "wof:placetype":"postalcode"
},
  "geometry": {"coordinates":[-1.44229341423577,54.98827584354268],"type":"Point"}
}