{
  "type": "Feature",
  "properties": {
    "date:inception_lower":"2008-04-01",
    "date:inception_upper":"2008-04-30",
    "iso:country":"GB",
    "wof:name":"NE33 5BY",
    "wof:placetype":"postalcode"
},
  "geometry": {"coordinates":[-1.442307,54.988284],"type":"Point"}
}