{
  "type": "Feature",
  "properties": {
    "date:inception_lower":"1991-09-01",
    "date:inception_upper":"1991-09-30",
    "iso:country":"GB",
    "wof:name":"TS8 0UG",
    "wof:placetype":"postalcode"
},
  "geometry": {"coordinates":[-1.216942,54.516872],"type":"Point"}
}