{
  "type": "Feature",
  "properties": {
    "iso:country":"GB",
    "wof:name":"TS8 0UG",
    "wof:placetype":"postalcode"
},
  "geometry": {"coordinates":[-1.21694198824458,54.51687190393882],"type":"Point"}
}