{
  "type": "Feature",
  "properties": {
    "iso:country":"GB",
    "wof:name":"TR2 4LS",
    "wof:placetype":"postalcode"
},
  "geometry": {"coordinates":[-4.96095152705464,50.29211742346355],"type":"Point"}
}