{
  "type": "Feature",
  "properties": {
    "date:inception_lower": "1980-01-01",
    "date:inception_upper": "1980-01-01",
    "iso:country": "GB",
    "wof:name": "TR2 4LS",
    "wof:placetype": "postalcode"
  },
  "geometry": {"coordinates":[-4.961322,50.292142],"type":"Point"}
}
