{
  "type": "Feature",
  "properties": {
    "date:inception_lower": "2006-01-01",
    "date:inception_upper": "2006-01-01",
    "iso:country": "GB",
    "wof:name": "LN2 4QW",
    "wof:placetype": "postalcode"
  },
  "geometry": {"coordinates":[-0.494768,53.246254],"type":"Point"}
}
