{
  "type": "Feature",
  "properties": {
    "iso:country":"GB",
    "wof:name":"TA1 3DY",
    "wof:placetype":"postalcode"
},
  "geometry": {"coordinates":[-3.09300250737901,51.00933689688961],"type":"Point"}
}