{
  "type": "Feature",
  "properties": {
    "iso:country": "GB",
    "wof:name": "CO3 3NN",
    "wof:placetype": "postalcode"
  },
  "geometry": {"coordinates":[0.884231,51.886987],"type":"Point"}
}
