{
  "type": "Feature",
  "properties": {
    "iso:country":"GB",
    "wof:name":"CO3 3NN",
    "wof:placetype":"postalcode"
},
  "geometry": {"coordinates":[0.88423132281308,51.88698653905232],"type":"Point"}
}