{
  "type": "Feature",
  "properties": {
    "iso:country":"GB",
    "wof:name":"NG23 7PQ",
    "wof:placetype":"postalcode"
},
  "geometry": {"coordinates":[-0.75930279865476,53.15038047159944],"type":"Point"}
}