{
  "type": "Feature",
  "properties": {
    "iso:country":"GB",
    "wof:name":"CA1 3BL",
    "wof:placetype":"postalcode"
},
  "geometry": {"coordinates":[-2.90536860958948,54.87285152160713],"type":"Point"}
}