{
  "type": "Feature",
  "properties": {
    "iso:country": "GB",
    "wof:name": "HR7 4EP",
    "wof:placetype": "postalcode"
  },
  "geometry": {"coordinates":[-2.51252,52.185741],"type":"Point"}
}
