{
  "type": "Feature",
  "properties": {
    "iso:country":"GB",
    "wof:name":"W8 4JD",
    "wof:placetype":"postalcode"
},
  "geometry": {"coordinates":[-0.1943377502531,51.50387424797008],"type":"Point"}
}