{
  "type": "Feature",
  "properties": {
    "iso:country":"GB",
    "wof:name":"SS8 7NQ",
    "wof:placetype":"postalcode"
},
  "geometry": {"coordinates":[0.60990927954588,51.51433523880377],"type":"Point"}
}