{
  "type": "Feature",
  "properties": {
    "iso:country":"GB",
    "wof:name":"ME8 7LQ",
    "wof:placetype":"postalcode"
},
  "geometry": {"coordinates":[0.60676529809988,51.36852860296388],"type":"Point"}
}