{
  "type": "Feature",
  "properties": {
    "date:inception_lower": "2024-09-01",
    "date:inception_upper": "2024-09-01",
    "iso:country": "GB",
    "wof:name": "TD7 4YY",
    "wof:placetype": "postalcode"
  },
  "geometry": {"coordinates":[-2.906343,55.452893],"type":"Point"}
}
