{
  "type": "Feature",
  "properties": {
    "iso:country":"GB",
    "wof:name":"W8 6FT",
    "wof:placetype":"postalcode"
},
  "geometry": {"coordinates":[-0.19816658115386,51.49776430680012],"type":"Point"}
}