{
  "type": "Feature",
  "properties": {
    "iso:country":"GB",
    "wof:name":"KA6 6QQ",
    "wof:placetype":"postalcode"
},
  "geometry": {"coordinates":[-4.51471461679474,55.44118689699307],"type":"Point"}
}