{
  "type": "Feature",
  "properties": {
    "iso:country": "GB",
    "wof:name": "HX3 9FA",
    "wof:placetype": "postalcode"
  },
  "geometry": {"coordinates":[-1.850325,53.710508],"type":"Point"}
}
