{
  "type": "Feature",
  "properties": {
    "iso:country":"GB",
    "wof:name":"ML5 3LX",
    "wof:placetype":"postalcode"
},
  "geometry": {"coordinates":[-4.01175811606037,55.86305966833289],"type":"Point"}
}