{
  "type": "Feature",
  "properties": {
    "iso:country": "GB",
    "wof:name": "G12 8AJ",
    "wof:placetype": "postalcode"
  },
  "geometry": {"coordinates":[-4.292492,55.875692],"type":"Point"}
}
