{
  "type": "Feature",
  "properties": {
    "iso:country":"GB",
    "wof:name":"G12 8AJ",
    "wof:placetype":"postalcode"
},
  "geometry": {"coordinates":[-4.29249251862247,55.87569196141276],"type":"Point"}
}