{
  "type": "Feature",
  "properties": {
    "iso:country": "GB",
    "wof:name": "AL9 5FB",
    "wof:placetype": "postalcode"
  },
  "geometry": {"coordinates":[-0.215352,51.766704],"type":"Point"}
}
