{
  "type": "Feature",
  "properties": {
    "date:inception_lower": "2015-11-01",
    "date:inception_upper": "2015-11-01",
    "iso:country": "GB",
    "wof:name": "LS28 9FA",
    "wof:placetype": "postalcode"
  },
  "geometry": {"coordinates":[-1.654509,53.798855],"type":"Point"}
}
