{
  "type": "Feature",
  "properties": {
    "iso:country": "GB",
    "wof:name": "N2 8BY",
    "wof:placetype": "postalcode"
  },
  "geometry": {"coordinates":[-0.168792,51.592917],"type":"Point"}
}
