{
  "type": "Feature",
  "properties": {
    "iso:country":"GB",
    "wof:name":"N2 8BY",
    "wof:placetype":"postalcode"
},
  "geometry": {"coordinates":[-0.16879221510953,51.59291683622439],"type":"Point"}
}