{
  "type": "Feature",
  "properties": {
    "date:inception_lower":"2005-03-01",
    "date:inception_upper":"2005-03-31",
    "iso:country":"GB",
    "wof:name":"NR34 9DT",
    "wof:placetype":"postalcode"
},
  "geometry": {"coordinates":[1.566044,52.460478],"type":"Point"}
}