{
  "type": "Feature",
  "properties": {
    "iso:country":"GB",
    "wof:name":"NR8 6LR",
    "wof:placetype":"postalcode"
},
  "geometry": {"coordinates":[1.19976296710731,52.68755305117075],"type":"Point"}
}