{
  "type": "Feature",
  "properties": {
    "date:inception_lower":"1980-01-01",
    "date:inception_upper":"1980-01-31",
    "iso:country":"GB",
    "wof:name":"NR8 6LR",
    "wof:placetype":"postalcode"
},
  "geometry": {"coordinates":[1.199763,52.687553],"type":"Point"}
}