{
  "type": "Feature",
  "properties": {
    "iso:country":"GB",
    "wof:name":"RG26 5TN",
    "wof:placetype":"postalcode"
},
  "geometry": {"coordinates":[-1.20683423624889,51.27271497537962],"type":"Point"}
}