{
  "type": "Feature",
  "properties": {
    "iso:country":"GB",
    "wof:name":"NR4 7LF",
    "wof:placetype":"postalcode"
},
  "geometry": {"coordinates":[1.25058681260958,52.6102637624417],"type":"Point"}
}