{
  "type": "Feature",
  "properties": {
    "iso:country": "GB",
    "wof:name": "CO6 2EX",
    "wof:placetype": "postalcode"
  },
  "geometry": {"coordinates":[0.690055,51.941582],"type":"Point"}
}
