{
  "type": "Feature",
  "properties": {
    "iso:country":"GB",
    "wof:name":"YO25 4RH",
    "wof:placetype":"postalcode"
},
  "geometry": {"coordinates":[-0.37742927531991,54.06399421495608],"type":"Point"}
}