{
  "type": "Feature",
  "properties": {
    "iso:country":"GB",
    "wof:name":"NE70 7JG",
    "wof:placetype":"postalcode"
},
  "geometry": {"coordinates":[-1.76072983007295,55.56674373410552],"type":"Point"}
}