{
  "type": "Feature",
  "properties": {
    "date:inception_lower": "1980-01-01",
    "date:inception_upper": "1980-01-01",
    "iso:country": "GB",
    "wof:name": "NE70 7JG",
    "wof:placetype": "postalcode"
  },
  "geometry": {"coordinates":[-1.76073,55.566744],"type":"Point"}
}
