{
  "type": "Feature",
  "properties": {
    "iso:country":"GB",
    "wof:name":"CT10 2AH",
    "wof:placetype":"postalcode"
},
  "geometry": {"coordinates":[1.4294541809637,51.35917423252657],"type":"Point"}
}