{
  "type": "Feature",
  "properties": {
    "iso:country":"GB",
    "wof:name":"KT21 2JN",
    "wof:placetype":"postalcode"
},
  "geometry": {"coordinates":[-0.31648749380977,51.31305467186601],"type":"Point"}
}