{
  "type": "Feature",
  "properties": {
    "date:inception_lower": "1980-01-01",
    "date:inception_upper": "1980-01-01",
    "iso:country": "GB",
    "wof:name": "KT21 2JN",
    "wof:placetype": "postalcode"
  },
  "geometry": {"coordinates":[-0.316487,51.313055],"type":"Point"}
}
