{
  "type": "Feature",
  "properties": {
    "date:inception_lower":"2007-07-01",
    "date:inception_upper":"2007-07-31",
    "iso:country":"GB",
    "wof:name":"EH28 8QW",
    "wof:placetype":"postalcode"
},
  "geometry": {"coordinates":[-3.406454,55.939634],"type":"Point"}
}