{
  "type": "Feature",
  "properties": {
    "iso:country":"GB",
    "wof:name":"PL18 9NZ",
    "wof:placetype":"postalcode"
},
  "geometry": {"coordinates":[-4.22443478968578,50.52643575816341],"type":"Point"}
}