{
  "type": "Feature",
  "properties": {
    "iso:country": "GB",
    "wof:name": "GU10 5QS",
    "wof:placetype": "postalcode"
  },
  "geometry": {"coordinates":[-0.862007,51.234532],"type":"Point"}
}
