{
  "type": "Feature",
  "properties": {
    "iso:country":"GB",
    "wof:name":"PO3 6BZ",
    "wof:placetype":"postalcode"
},
  "geometry": {"coordinates":[-1.06220730685219,50.80476827473692],"type":"Point"}
}