{
  "type": "Feature",
  "properties": {
    "iso:country": "GB",
    "wof:name": "PO3 6BZ",
    "wof:placetype": "postalcode"
  },
  "geometry": {"coordinates":[-1.062207,50.804768],"type":"Point"}
}
