{
  "type": "Feature",
  "properties": {
    "iso:country": "GB",
    "wof:name": "EX12 3LN",
    "wof:placetype": "postalcode"
  },
  "geometry": {"coordinates":[-3.097714,50.699284],"type":"Point"}
}
