{
  "type": "Feature",
  "properties": {
    "iso:country": "GB",
    "wof:name": "M35 9YJ",
    "wof:placetype": "postalcode"
  },
  "geometry": {"coordinates":[-2.145096,53.506186],"type":"Point"}
}
