{
  "type": "Feature",
  "properties": {
    "iso:country":"GB",
    "wof:name":"M35 9YJ",
    "wof:placetype":"postalcode"
},
  "geometry": {"coordinates":[-2.14509573924881,53.50618602619815],"type":"Point"}
}