{
  "type": "Feature",
  "properties": {
    "date:inception_lower": "1997-12-01",
    "date:inception_upper": "1997-12-01",
    "iso:country": "GB",
    "wof:name": "E15 4DZ",
    "wof:placetype": "postalcode"
  },
  "geometry": {"coordinates":[0.006986,51.53695],"type":"Point"}
}
