{
  "type": "Feature",
  "properties": {
    "iso:country":"GB",
    "wof:name":"EH54 6BA",
    "wof:placetype":"postalcode"
},
  "geometry": {"coordinates":[-3.50953159128592,55.89318749078029],"type":"Point"}
}