{
  "type": "Feature",
  "properties": {
    "date:inception_lower": "1980-01-01",
    "date:inception_upper": "1980-01-01",
    "iso:country": "GB",
    "wof:name": "EH54 6BA",
    "wof:placetype": "postalcode"
  },
  "geometry": {"coordinates":[-3.509428,55.893],"type":"Point"}
}
