{
  "type": "Feature",
  "properties": {
    "iso:country":"GB",
    "wof:name":"BN21 1SB",
    "wof:placetype":"postalcode"
},
  "geometry": {"coordinates":[0.25673525206283,50.77695852423432],"type":"Point"}
}