{
  "type": "Feature",
  "properties": {
    "iso:country":"GB",
    "wof:name":"NN11 3EZ",
    "wof:placetype":"postalcode"
},
  "geometry": {"coordinates":[-1.15455699555361,52.22946466619605],"type":"Point"}
}