{
  "type": "Feature",
  "properties": {
    "iso:country":"GB",
    "wof:name":"TA7 8LN",
    "wof:placetype":"postalcode"
},
  "geometry": {"coordinates":[-2.91207279387052,51.1572582102189],"type":"Point"}
}