{
  "type": "Feature",
  "properties": {
    "iso:country":"GB",
    "wof:name":"LN11 0JW",
    "wof:placetype":"postalcode"
},
  "geometry": {"coordinates":[-0.00099472063188,53.368680432456],"type":"Point"}
}