{
  "type": "Feature",
  "properties": {
    "date:inception_lower": "1980-01-01",
    "date:inception_upper": "1980-01-01",
    "iso:country": "GB",
    "wof:name": "S63 8DG",
    "wof:placetype": "postalcode"
  },
  "geometry": {"coordinates":[-1.325394,53.519734],"type":"Point"}
}
