{
  "type": "Feature",
  "properties": {
    "iso:country":"GB",
    "wof:name":"S63 8DG",
    "wof:placetype":"postalcode"
},
  "geometry": {"coordinates":[-1.32539402906592,53.51973393584658],"type":"Point"}
}