{
  "type": "Feature",
  "properties": {
    "date:inception_lower": "1980-01-01",
    "date:inception_upper": "1980-01-01",
    "iso:country": "GB",
    "wof:name": "SW2 2AD",
    "wof:placetype": "postalcode"
  },
  "geometry": {"coordinates":[-0.120462,51.450647],"type":"Point"}
}
