{
  "type": "Feature",
  "properties": {
    "date:inception_lower": "1994-12-01",
    "date:inception_upper": "1994-12-01",
    "iso:country": "GB",
    "wof:name": "SO14 6QY",
    "wof:placetype": "postalcode"
  },
  "geometry": {"coordinates":[-1.4004,50.917578],"type":"Point"}
}
