{
  "type": "Feature",
  "properties": {
    "iso:country": "GB",
    "wof:name": "SO14 6QY",
    "wof:placetype": "postalcode"
  },
  "geometry": {"coordinates":[-1.4004,50.917578],"type":"Point"}
}
