{
  "type": "Feature",
  "properties": {
    "iso:country": "GB",
    "wof:name": "DN5 9BJ",
    "wof:placetype": "postalcode"
  },
  "geometry": {"coordinates":[-1.156625,53.533962],"type":"Point"}
}
