{
  "type": "Feature",
  "properties": {
    "iso:country": "GB",
    "wof:name": "WA10 5HL",
    "wof:placetype": "postalcode"
  },
  "geometry": {"coordinates":[-2.783918,53.458238],"type":"Point"}
}
