{
  "type": "Feature",
  "properties": {
    "iso:country":"GB",
    "wof:name":"CM0 8PL",
    "wof:placetype":"postalcode"
},
  "geometry": {"coordinates":[0.79097255922857,51.62771326916604],"type":"Point"}
}