{
  "type": "Feature",
  "properties": {
    "date:inception_lower":"1980-01-01",
    "date:inception_upper":"1980-01-31",
    "iso:country":"GB",
    "wof:name":"CM0 8PL",
    "wof:placetype":"postalcode"
},
  "geometry": {"coordinates":[0.790973,51.627713],"type":"Point"}
}