{
  "type": "Feature",
  "properties": {
    "iso:country": "GB",
    "wof:name": "CM0 8PL",
    "wof:placetype": "postalcode"
  },
  "geometry": {"coordinates":[0.790973,51.627713],"type":"Point"}
}
