{
  "type": "Feature",
  "properties": {
    "iso:country":"GB",
    "wof:name":"LU5 4NR",
    "wof:placetype":"postalcode"
},
  "geometry": {"coordinates":[-0.49594361679459,51.89356604474294],"type":"Point"}
}