{
  "type": "Feature",
  "properties": {
    "iso:country":"GB",
    "wof:name":"M13 9NQ",
    "wof:placetype":"postalcode"
},
  "geometry": {"coordinates":[-2.22847805831441,53.4622278817335],"type":"Point"}
}