{
  "type": "Feature",
  "properties": {
    "iso:country":"GB",
    "wof:name":"NG32 3DS",
    "wof:placetype":"postalcode"
},
  "geometry": {"coordinates":[-0.60232483975804,53.02258715323211],"type":"Point"}
}