{
  "type": "Feature",
  "properties": {
    "iso:country":"GB",
    "wof:name":"DE6 1DE",
    "wof:placetype":"postalcode"
},
  "geometry": {"coordinates":[-1.73464791031415,53.01368206684796],"type":"Point"}
}