{
  "type": "Feature",
  "properties": {
    "iso:country": "GB",
    "wof:name": "IG11 0FT",
    "wof:placetype": "postalcode"
  },
  "geometry": {"coordinates":[0.103464,51.52338],"type":"Point"}
}
