{
  "type": "Feature",
  "properties": {
    "iso:country":"GB",
    "wof:name":"IG11 0FT",
    "wof:placetype":"postalcode"
},
  "geometry": {"coordinates":[0.10346348650332,51.52338023418206],"type":"Point"}
}