{
  "type": "Feature",
  "properties": {
    "iso:country":"GB",
    "wof:name":"PL21 0ET",
    "wof:placetype":"postalcode"
},
  "geometry": {"coordinates":[-3.87536841378062,50.39501234766422],"type":"Point"}
}