{
  "type": "Feature",
  "properties": {
    "date:inception_lower": "1980-01-01",
    "date:inception_upper": "1980-01-01",
    "iso:country": "GB",
    "wof:name": "GU27 3JD",
    "wof:placetype": "postalcode"
  },
  "geometry": {"coordinates":[-0.710403,51.046267],"type":"Point"}
}
