{
  "type": "Feature",
  "properties": {
    "iso:country":"GB",
    "wof:name":"RM10 7YX",
    "wof:placetype":"postalcode"
},
  "geometry": {"coordinates":[0.15480702525175,51.55104538411565],"type":"Point"}
}