{
  "type": "Feature",
  "properties": {
    "iso:country":"GB",
    "wof:name":"SE6 1XY",
    "wof:placetype":"postalcode"
},
  "geometry": {"coordinates":[-0.00703529963895,51.4443575577648],"type":"Point"}
}