{
  "type": "Feature",
  "properties": {
    "iso:country": "GB",
    "wof:name": "CA11 0EL",
    "wof:placetype": "postalcode"
  },
  "geometry": {"coordinates":[-2.799111,54.645296],"type":"Point"}
}
