{
  "type": "Feature",
  "properties": {
    "iso:country":"GB",
    "wof:name":"SE23 2UW",
    "wof:placetype":"postalcode"
},
  "geometry": {"coordinates":[-0.0520220202643,51.43822539051529],"type":"Point"}
}