{
  "type": "Feature",
  "properties": {
    "iso:country": "GB",
    "wof:name": "OL12 0AX",
    "wof:placetype": "postalcode"
  },
  "geometry": {"coordinates":[-2.158304,53.63561],"type":"Point"}
}
