{
  "type": "Feature",
  "properties": {
    "iso:country":"GB",
    "wof:name":"OL12 0AX",
    "wof:placetype":"postalcode"
},
  "geometry": {"coordinates":[-2.15830442653551,53.63560986357547],"type":"Point"}
}