{
  "type": "Feature",
  "properties": {
    "date:inception_lower":"1997-12-01",
    "date:inception_upper":"1997-12-31",
    "iso:country":"GB",
    "wof:name":"SA4 4AY",
    "wof:placetype":"postalcode"
},
  "geometry": {"coordinates":[-4.040686,51.662463],"type":"Point"}
}