{
  "type": "Feature",
  "properties": {
    "iso:country":"GB",
    "wof:name":"SA4 4AY",
    "wof:placetype":"postalcode"
},
  "geometry": {"coordinates":[-4.04068597950863,51.66246279564496],"type":"Point"}
}