{
  "type": "Feature",
  "properties": {
    "iso:country": "GB",
    "wof:name": "HX3 6XR",
    "wof:placetype": "postalcode"
  },
  "geometry": {"coordinates":[-1.846507,53.735571],"type":"Point"}
}
