{
  "type": "Feature",
  "properties": {
    "iso:country":"GB",
    "wof:name":"SA72 6UG",
    "wof:placetype":"postalcode"
},
  "geometry": {"coordinates":[-4.92985771480694,51.69326169505193],"type":"Point"}
}