{
  "type": "Feature",
  "properties": {
    "iso:country":"GB",
    "wof:name":"SL7 3LY",
    "wof:placetype":"postalcode"
},
  "geometry": {"coordinates":[-0.77343446268448,51.58687272702683],"type":"Point"}
}