{
  "type": "Feature",
  "properties": {
    "iso:country": "GB",
    "wof:name": "SL7 3LY",
    "wof:placetype": "postalcode"
  },
  "geometry": {"coordinates":[-0.773434,51.586873],"type":"Point"}
}
