{
  "type": "Feature",
  "properties": {
    "iso:country":"GB",
    "wof:name":"SK9 6BR",
    "wof:placetype":"postalcode"
},
  "geometry": {"coordinates":[-2.2537120230666,53.31915935490375],"type":"Point"}
}