{
  "type": "Feature",
  "properties": {
    "iso:country": "GB",
    "wof:name": "SK9 6BR",
    "wof:placetype": "postalcode"
  },
  "geometry": {"coordinates":[-2.253712,53.319159],"type":"Point"}
}
