{
  "type": "Feature",
  "properties": {
    "iso:country": "GB",
    "wof:name": "PR9 0TB",
    "wof:placetype": "postalcode"
  },
  "geometry": {"coordinates":[-3.000126,53.648694],"type":"Point"}
}
