{
  "type": "Feature",
  "properties": {
    "date:inception_lower": "1980-01-01",
    "date:inception_upper": "1980-01-01",
    "iso:country": "GB",
    "wof:name": "PR9 0TB",
    "wof:placetype": "postalcode"
  },
  "geometry": {"coordinates":[-3.000126,53.648694],"type":"Point"}
}
