{
  "type": "Feature",
  "properties": {
    "iso:country":"GB",
    "wof:name":"ME17 1LQ",
    "wof:placetype":"postalcode"
},
  "geometry": {"coordinates":[0.67006751864524,51.2337678450445],"type":"Point"}
}