{
  "type": "Feature",
  "properties": {
    "date:inception_lower": "1980-01-01",
    "date:inception_upper": "1980-01-01",
    "iso:country": "GB",
    "wof:name": "LE7 9HR",
    "wof:placetype": "postalcode"
  },
  "geometry": {"coordinates":[-1.002727,52.626284],"type":"Point"}
}
