{
  "type": "Feature",
  "properties": {
    "iso:country":"GB",
    "wof:name":"HP1 3BS",
    "wof:placetype":"postalcode"
},
  "geometry": {"coordinates":[-0.51065530795104,51.79181479727591],"type":"Point"}
}