{
  "type": "Feature",
  "properties": {
    "iso:country":"GB",
    "wof:name":"BN8 4FE",
    "wof:placetype":"postalcode"
},
  "geometry": {"coordinates":[-0.00895116524072,50.90398430929053],"type":"Point"}
}