{
  "type": "Feature",
  "properties": {
    "date:inception_lower":"2013-07-01",
    "date:inception_upper":"2013-07-31",
    "iso:country":"GB",
    "wof:name":"BN8 4FE",
    "wof:placetype":"postalcode"
},
  "geometry": {"coordinates":[-0.008951,50.903984],"type":"Point"}
}