{
  "type": "Feature",
  "properties": {
    "iso:country": "GB",
    "wof:name": "YO17 8EQ",
    "wof:placetype": "postalcode"
  },
  "geometry": {"coordinates":[-0.516924,54.124436],"type":"Point"}
}
