{
  "type": "Feature",
  "properties": {
    "iso:country":"GB",
    "wof:name":"YO17 8EQ",
    "wof:placetype":"postalcode"
},
  "geometry": {"coordinates":[-0.51692393724447,54.12443557163819],"type":"Point"}
}