{
  "type": "Feature",
  "properties": {
    "iso:country": "GB",
    "wof:name": "PO20 3ST",
    "wof:placetype": "postalcode"
  },
  "geometry": {"coordinates":[-0.669761,50.830478],"type":"Point"}
}
