{
  "type": "Feature",
  "properties": {
    "iso:country":"GB",
    "wof:name":"IP21 4RZ",
    "wof:placetype":"postalcode"
},
  "geometry": {"coordinates":[1.21540314163085,52.39868851520634],"type":"Point"}
}