{
  "type": "Feature",
  "properties": {
    "date:inception_lower": "1980-01-01",
    "date:inception_upper": "1980-01-01",
    "iso:country": "GB",
    "wof:name": "LS14 3HB",
    "wof:placetype": "postalcode"
  },
  "geometry": {"coordinates":[-1.431095,53.858844],"type":"Point"}
}
