{
  "type": "Feature",
  "properties": {
    "iso:country":"GB",
    "wof:name":"LS14 3HB",
    "wof:placetype":"postalcode"
},
  "geometry": {"coordinates":[-1.43109530883654,53.85884380518763],"type":"Point"}
}