{
  "type": "Feature",
  "properties": {
    "date:inception_lower": "2017-09-01",
    "date:inception_upper": "2017-09-01",
    "iso:country": "GB",
    "wof:name": "G45 9BB",
    "wof:placetype": "postalcode"
  },
  "geometry": {"coordinates":[-4.237196,55.806738],"type":"Point"}
}
