{
  "type": "Feature",
  "properties": {
    "date:inception_lower":"2014-08-01",
    "date:inception_upper":"2014-08-31",
    "iso:country":"GB",
    "wof:name":"SE16 4EQ",
    "wof:placetype":"postalcode"
},
  "geometry": {"coordinates":[-0.062881,51.494152],"type":"Point"}
}