{
  "type": "Feature",
  "properties": {
    "iso:country":"GB",
    "wof:name":"CT10 1RL",
    "wof:placetype":"postalcode"
},
  "geometry": {"coordinates":[1.43468869600473,51.35060118437062],"type":"Point"}
}