{
  "type": "Feature",
  "properties": {
    "iso:country":"GB",
    "wof:name":"LL57 2TS",
    "wof:placetype":"postalcode"
},
  "geometry": {"coordinates":[-4.14375723116719,53.22343409603163],"type":"Point"}
}