{
  "type": "Feature",
  "properties": {
    "date:inception_lower":"2000-12-01",
    "date:inception_upper":"2000-12-31",
    "iso:country":"GB",
    "wof:name":"M26 1YP",
    "wof:placetype":"postalcode"
},
  "geometry": {"coordinates":[-2.332293,53.548147],"type":"Point"}
}