{
  "type": "Feature",
  "properties": {
    "iso:country": "GB",
    "wof:name": "CF83 3RD",
    "wof:placetype": "postalcode"
  },
  "geometry": {"coordinates":[-3.228234,51.58756],"type":"Point"}
}
