{
  "type": "Feature",
  "properties": {
    "iso:country":"GB",
    "wof:name":"CF83 3RD",
    "wof:placetype":"postalcode"
},
  "geometry": {"coordinates":[-3.22823438875608,51.58756008199979],"type":"Point"}
}