{
  "type": "Feature",
  "properties": {
    "iso:country":"GB",
    "wof:name":"HR7 4PG",
    "wof:placetype":"postalcode"
},
  "geometry": {"coordinates":[-2.49964545919264,52.20762522317649],"type":"Point"}
}