{
  "type": "Feature",
  "properties": {
    "date:inception_lower": "1997-06-01",
    "date:inception_upper": "1997-06-01",
    "iso:country": "GB",
    "wof:name": "S35 8QD",
    "wof:placetype": "postalcode"
  },
  "geometry": {"coordinates":[-1.518594,53.43756],"type":"Point"}
}
