{
  "type": "Feature",
  "properties": {
    "iso:country":"GB",
    "wof:name":"S35 8QD",
    "wof:placetype":"postalcode"
},
  "geometry": {"coordinates":[-1.51859434026243,53.43755954861142],"type":"Point"}
}