{
  "type": "Feature",
  "properties": {
    "iso:country": "GB",
    "wof:name": "CR3 6XX",
    "wof:placetype": "postalcode"
  },
  "geometry": {"coordinates":[-0.073999,51.279551],"type":"Point"}
}
