{
  "type": "Feature",
  "properties": {
    "iso:country": "GB",
    "wof:name": "TF8 7JJ",
    "wof:placetype": "postalcode"
  },
  "geometry": {"coordinates":[-2.443991,52.617426],"type":"Point"}
}
