{
  "type": "Feature",
  "properties": {
    "date:inception_lower": "2018-11-01",
    "date:inception_upper": "2018-11-01",
    "iso:country": "GB",
    "wof:name": "TF8 7JJ",
    "wof:placetype": "postalcode"
  },
  "geometry": {"coordinates":[-2.443991,52.617426],"type":"Point"}
}
