{
  "type": "Feature",
  "properties": {
    "date:inception_lower": "2018-11-01",
    "date:inception_upper": "2018-11-01",
    "iso:country": "GB",
    "wof:name": "TF8 7JJ",
    "wof:placetype": "postalcode"
  },
  "geometry": {"coordinates":[-2.443843,52.617391],"type":"Point"}
}
