{
  "type": "Feature",
  "properties": {
    "iso:country":"GB",
    "wof:name":"UB3 2RL",
    "wof:placetype":"postalcode"
},
  "geometry": {"coordinates":[-0.42287215622855,51.51899461906777],"type":"Point"}
}