{
  "type": "Feature",
  "properties": {
    "date:inception_lower": "1980-01-01",
    "date:inception_upper": "1980-01-01",
    "iso:country": "GB",
    "wof:name": "RH19 2PB",
    "wof:placetype": "postalcode"
  },
  "geometry": {"coordinates":[-0.056915,51.14196],"type":"Point"}
}
