{
  "type": "Feature",
  "properties": {
    "iso:country": "GB",
    "wof:name": "RH19 2PB",
    "wof:placetype": "postalcode"
  },
  "geometry": {"coordinates":[-0.056559,51.141903],"type":"Point"}
}
