{
  "type": "Feature",
  "properties": {
    "iso:country":"GB",
    "wof:name":"CM16 7PS",
    "wof:placetype":"postalcode"
},
  "geometry": {"coordinates":[0.1514627860956,51.68760736391615],"type":"Point"}
}