{
  "type": "Feature",
  "properties": {
    "iso:country": "GB",
    "wof:name": "CM16 7PS",
    "wof:placetype": "postalcode"
  },
  "geometry": {"coordinates":[0.151463,51.687607],"type":"Point"}
}
