{
  "type": "Feature",
  "properties": {
    "iso:country":"GB",
    "wof:name":"TD9 0LQ",
    "wof:placetype":"postalcode"
},
  "geometry": {"coordinates":[-2.9393194832349,55.3382337014791],"type":"Point"}
}