{
  "type": "Feature",
  "properties": {
    "date:inception_lower": "1980-01-01",
    "date:inception_upper": "1980-01-01",
    "iso:country": "GB",
    "wof:name": "FY3 9RJ",
    "wof:placetype": "postalcode"
  },
  "geometry": {"coordinates":[-3.02004,53.808503],"type":"Point"}
}
