{
  "type": "Feature",
  "properties": {
    "iso:country":"GB",
    "wof:name":"FY3 9RJ",
    "wof:placetype":"postalcode"
},
  "geometry": {"coordinates":[-3.02004003740423,53.80850314834235],"type":"Point"}
}