{
  "type": "Feature",
  "properties": {
    "date:inception_lower": "1980-01-01",
    "date:inception_upper": "1980-01-01",
    "iso:country": "GB",
    "wof:name": "ST18 9JN",
    "wof:placetype": "postalcode"
  },
  "geometry": {"coordinates":[-2.201715,52.793154],"type":"Point"}
}
