{
  "type": "Feature",
  "properties": {
    "iso:country":"GB",
    "wof:name":"ST18 9JN",
    "wof:placetype":"postalcode"
},
  "geometry": {"coordinates":[-2.20171476225665,52.79315397638442],"type":"Point"}
}