{
  "type": "Feature",
  "properties": {
    "date:inception_lower":"1981-06-01",
    "date:inception_upper":"1981-06-30",
    "iso:country":"GB",
    "wof:name":"BA5 1ET",
    "wof:placetype":"postalcode"
},
  "geometry": {"coordinates":[-2.716114,51.233958],"type":"Point"}
}