{
  "type": "Feature",
  "properties": {
    "iso:country":"GB",
    "wof:name":"BA5 1ET",
    "wof:placetype":"postalcode"
},
  "geometry": {"coordinates":[-2.71611452049398,51.23395812562038],"type":"Point"}
}