{
  "type": "Feature",
  "properties": {
    "iso:country": "GB",
    "wof:name": "LS16 6PE",
    "wof:placetype": "postalcode"
  },
  "geometry": {"coordinates":[-1.627138,53.84649],"type":"Point"}
}
