{
  "type": "Feature",
  "properties": {
    "iso:country": "GB",
    "wof:name": "DN21 3SF",
    "wof:placetype": "postalcode"
  },
  "geometry": {"coordinates":[-0.665239,53.495077],"type":"Point"}
}
