{
  "type": "Feature",
  "properties": {
    "iso:country":"GB",
    "wof:name":"UB5 5QS",
    "wof:placetype":"postalcode"
},
  "geometry": {"coordinates":[-0.36021765616404,51.54505830681526],"type":"Point"}
}