{
  "type": "Feature",
  "properties": {
    "date:inception_lower": "1980-01-01",
    "date:inception_upper": "1980-01-01",
    "iso:country": "GB",
    "wof:name": "YO7 4EX",
    "wof:placetype": "postalcode"
  },
  "geometry": {"coordinates":[-1.424665,54.259143],"type":"Point"}
}
