{
  "type": "Feature",
  "properties": {
    "iso:country":"GB",
    "wof:name":"YO7 4EX",
    "wof:placetype":"postalcode"
},
  "geometry": {"coordinates":[-1.4246649883234,54.25914340027344],"type":"Point"}
}