{
  "type": "Feature",
  "properties": {
    "iso:country":"GB",
    "wof:name":"PA13 4SY",
    "wof:placetype":"postalcode"
},
  "geometry": {"coordinates":[-4.64571067651605,55.8851232453642],"type":"Point"}
}