{
  "type": "Feature",
  "properties": {
    "date:inception_lower":"2000-12-01",
    "date:inception_upper":"2000-12-31",
    "iso:country":"GB",
    "wof:name":"G66 7GE",
    "wof:placetype":"postalcode"
},
  "geometry": {"coordinates":[-4.209468,55.97457],"type":"Point"}
}