{
  "type": "Feature",
  "properties": {
    "iso:country": "GB",
    "wof:name": "G66 7GE",
    "wof:placetype": "postalcode"
  },
  "geometry": {"coordinates":[-4.209468,55.97457],"type":"Point"}
}
