{
  "type": "Feature",
  "properties": {
    "date:inception_lower":"2005-06-01",
    "date:inception_upper":"2005-06-30",
    "iso:country":"GB",
    "wof:name":"KA12 8TH",
    "wof:placetype":"postalcode"
},
  "geometry": {"coordinates":[-4.680154,55.636094],"type":"Point"}
}