{
  "type": "Feature",
  "properties": {
    "iso:country": "GB",
    "wof:name": "KA12 8TH",
    "wof:placetype": "postalcode"
  },
  "geometry": {"coordinates":[-4.680154,55.636094],"type":"Point"}
}
