{
  "type": "Feature",
  "properties": {
    "iso:country":"GB",
    "wof:name":"KA12 8TH",
    "wof:placetype":"postalcode"
},
  "geometry": {"coordinates":[-4.68015432842944,55.63609361469281],"type":"Point"}
}