{
  "type": "Feature",
  "properties": {
    "iso:country":"GB",
    "wof:name":"B46 2RG",
    "wof:placetype":"postalcode"
},
  "geometry": {"coordinates":[-1.66860789900717,52.50897701672107],"type":"Point"}
}