{
  "type": "Feature",
  "properties": {
    "iso:country": "GB",
    "wof:name": "HP9 1PR",
    "wof:placetype": "postalcode"
  },
  "geometry": {"coordinates":[-0.655618,51.603099],"type":"Point"}
}
