{
  "type": "Feature",
  "properties": {
    "date:inception_lower": "1980-01-01",
    "date:inception_upper": "1980-01-01",
    "iso:country": "GB",
    "wof:name": "NE65 7XG",
    "wof:placetype": "postalcode"
  },
  "geometry": {"coordinates":[-1.900953,55.310197],"type":"Point"}
}
