{
  "type": "Feature",
  "properties": {
    "iso:country":"GB",
    "wof:name":"NE65 7XG",
    "wof:placetype":"postalcode"
},
  "geometry": {"coordinates":[-1.90314739205538,55.31022269496405],"type":"Point"}
}