{
  "type": "Feature",
  "properties": {
    "date:inception_lower": "2003-04-01",
    "date:inception_upper": "2003-04-01",
    "iso:country": "GB",
    "wof:name": "BS10 7UD",
    "wof:placetype": "postalcode"
  },
  "geometry": {"coordinates":[-2.605753,51.526381],"type":"Point"}
}
