{
  "type": "Feature",
  "properties": {
    "iso:country":"GB",
    "wof:name":"BS10 7UD",
    "wof:placetype":"postalcode"
},
  "geometry": {"coordinates":[-2.60608600718395,51.52661418557177],"type":"Point"}
}