{
  "type": "Feature",
  "properties": {
    "date:inception_lower": "2017-03-01",
    "date:inception_upper": "2017-03-01",
    "iso:country": "GB",
    "wof:name": "PH4 1AA",
    "wof:placetype": "postalcode"
  },
  "geometry": {"coordinates":[-3.78468,56.260826],"type":"Point"}
}
