{
  "type": "Feature",
  "properties": {
    "date:inception_lower": "2022-06-01",
    "date:inception_upper": "2022-06-01",
    "iso:country": "GB",
    "wof:name": "NN8 6BF",
    "wof:placetype": "postalcode"
  },
  "geometry": {"coordinates":[-0.718486,52.318723],"type":"Point"}
}
