{
  "type": "Feature",
  "properties": {
    "iso:country":"GB",
    "wof:name":"TW8 8JJ",
    "wof:placetype":"postalcode"
},
  "geometry": {"coordinates":[-0.31680729362679,51.48095783227181],"type":"Point"}
}