{
  "type": "Feature",
  "properties": {
    "iso:country": "GB",
    "wof:name": "N15 4DH",
    "wof:placetype": "postalcode"
  },
  "geometry": {"coordinates":[-0.069658,51.585258],"type":"Point"}
}
