{
  "type": "Feature",
  "properties": {
    "date:inception_lower":"1980-01-01",
    "date:inception_upper":"1980-01-31",
    "iso:country":"GB",
    "wof:name":"NG14 7DS",
    "wof:placetype":"postalcode"
},
  "geometry": {"coordinates":[-0.99498,53.012556],"type":"Point"}
}