{
  "type": "Feature",
  "properties": {
    "iso:country":"GB",
    "wof:name":"LL23 7NT",
    "wof:placetype":"postalcode"
},
  "geometry": {"coordinates":[-3.63451059861708,52.93983590165556],"type":"Point"}
}