{
  "type": "Feature",
  "properties": {
    "date:inception_lower":"2013-11-01",
    "date:inception_upper":"2013-11-30",
    "iso:country":"GB",
    "wof:name":"EX5 7AZ",
    "wof:placetype":"postalcode"
},
  "geometry": {"coordinates":[-3.416963,50.747479],"type":"Point"}
}