{
  "type": "Feature",
  "properties": {
    "iso:country":"GB",
    "wof:name":"NE42 5PA",
    "wof:placetype":"postalcode"
},
  "geometry": {"coordinates":[-1.83355340272667,54.93839774234363],"type":"Point"}
}