{
  "type": "Feature",
  "properties": {
    "iso:country":"GB",
    "wof:name":"NW10 1AL",
    "wof:placetype":"postalcode"
},
  "geometry": {"coordinates":[-0.24366646248133,51.55838867890063],"type":"Point"}
}