{
  "type": "Feature",
  "properties": {
    "date:inception_lower": "1980-01-01",
    "date:inception_upper": "1980-01-01",
    "iso:country": "GB",
    "wof:name": "LL31 9DN",
    "wof:placetype": "postalcode"
  },
  "geometry": {"coordinates":[-3.835565,53.301122],"type":"Point"}
}
