{
  "type": "Feature",
  "properties": {
    "iso:country": "GB",
    "wof:name": "PR25 5TG",
    "wof:placetype": "postalcode"
  },
  "geometry": {"coordinates":[-2.660918,53.700259],"type":"Point"}
}
