{
  "type": "Feature",
  "properties": {
    "iso:country":"GB",
    "wof:name":"BH22 8JZ",
    "wof:placetype":"postalcode"
},
  "geometry": {"coordinates":[-1.89982782450227,50.79182021838941],"type":"Point"}
}