{
  "type": "Feature",
  "properties": {
    "iso:country": "GB",
    "wof:name": "DL3 6RD",
    "wof:placetype": "postalcode"
  },
  "geometry": {"coordinates":[-1.558206,54.537049],"type":"Point"}
}
