{
  "type": "Feature",
  "properties": {
    "iso:country":"GB",
    "wof:name":"SW10 0LG",
    "wof:placetype":"postalcode"
},
  "geometry": {"coordinates":[-0.17922088316961,51.48258911494516],"type":"Point"}
}