{
  "type": "Feature",
  "properties": {
    "iso:country":"GB",
    "wof:name":"B60 1NX",
    "wof:placetype":"postalcode"
},
  "geometry": {"coordinates":[-2.01900600716479,52.37151381679647],"type":"Point"}
}