{
  "type": "Feature",
  "properties": {
    "iso:country": "GB",
    "wof:name": "DE73 6XA",
    "wof:placetype": "postalcode"
  },
  "geometry": {"coordinates":[-1.434461,52.862278],"type":"Point"}
}
