{
  "type": "Feature",
  "properties": {
    "iso:country":"GB",
    "wof:name":"BN3 4LQ",
    "wof:placetype":"postalcode"
},
  "geometry": {"coordinates":[-0.19643419419343,50.82788115418474],"type":"Point"}
}