{
  "type": "Feature",
  "properties": {
    "iso:country":"GB",
    "wof:name":"IV40 8EJ",
    "wof:placetype":"postalcode"
},
  "geometry": {"coordinates":[-5.51548692762854,57.27998688832678],"type":"Point"}
}