{
  "type": "Feature",
  "properties": {
    "date:inception_lower":"1980-01-01",
    "date:inception_upper":"1980-01-31",
    "iso:country":"GB",
    "wof:name":"IV40 8EJ",
    "wof:placetype":"postalcode"
},
  "geometry": {"coordinates":[-5.515487,57.279987],"type":"Point"}
}