{
  "type": "Feature",
  "properties": {
    "iso:country": "GB",
    "wof:name": "RH17 7AA",
    "wof:placetype": "postalcode"
  },
  "geometry": {"coordinates":[-0.093152,50.988875],"type":"Point"}
}
