{
  "type": "Feature",
  "properties": {
    "date:inception_lower": "1980-01-01",
    "date:inception_upper": "1980-01-01",
    "iso:country": "GB",
    "wof:name": "TN10 3EP",
    "wof:placetype": "postalcode"
  },
  "geometry": {"coordinates":[0.2786,51.208502],"type":"Point"}
}
