{
  "type": "Feature",
  "properties": {
    "iso:country":"GB",
    "wof:name":"TN10 4LU",
    "wof:placetype":"postalcode"
},
  "geometry": {"coordinates":[0.29909600469291,51.20836144476836],"type":"Point"}
}