{
  "type": "Feature",
  "properties": {
    "iso:country":"GB",
    "wof:name":"PA3 4SL",
    "wof:placetype":"postalcode"
},
  "geometry": {"coordinates":[-4.41192129529444,55.85437239178312],"type":"Point"}
}