{
  "type": "Feature",
  "properties": {
    "iso:country":"GB",
    "wof:name":"ML10 6PB",
    "wof:placetype":"postalcode"
},
  "geometry": {"coordinates":[-4.04852660612325,55.6651764184116],"type":"Point"}
}