{
  "type": "Feature",
  "properties": {
    "iso:country":"GB",
    "wof:name":"TN23 3LH",
    "wof:placetype":"postalcode"
},
  "geometry": {"coordinates":[0.84198541162623,51.15286076866457],"type":"Point"}
}