{
  "type": "Feature",
  "properties": {
    "iso:country": "GB",
    "wof:name": "TN23 3LH",
    "wof:placetype": "postalcode"
  },
  "geometry": {"coordinates":[0.841985,51.152861],"type":"Point"}
}
