{
  "type": "Feature",
  "properties": {
    "date:inception_lower":"1997-06-01",
    "date:inception_upper":"1997-06-30",
    "iso:country":"GB",
    "wof:name":"TN22 5NE",
    "wof:placetype":"postalcode"
},
  "geometry": {"coordinates":[0.102852,50.962259],"type":"Point"}
}