{
  "type": "Feature",
  "properties": {
    "iso:country": "GB",
    "wof:name": "NP7 5DJ",
    "wof:placetype": "postalcode"
  },
  "geometry": {"coordinates":[-3.02146,51.823267],"type":"Point"}
}
