{
  "type": "Feature",
  "properties": {
    "iso:country":"GB",
    "wof:name":"NP7 5DJ",
    "wof:placetype":"postalcode"
},
  "geometry": {"coordinates":[-3.02145956716358,51.82326664510668],"type":"Point"}
}