{
  "type": "Feature",
  "properties": {
    "iso:country": "GB",
    "wof:name": "HR2 6QP",
    "wof:placetype": "postalcode"
  },
  "geometry": {"coordinates":[-2.666351,51.96042],"type":"Point"}
}
