{
  "type": "Feature",
  "properties": {
    "iso:country":"GB",
    "wof:name":"HR2 6QP",
    "wof:placetype":"postalcode"
},
  "geometry": {"coordinates":[-2.66635133925868,51.96041978908815],"type":"Point"}
}