{
  "type": "Feature",
  "properties": {
    "iso:country": "GB",
    "wof:name": "G62 6DY",
    "wof:placetype": "postalcode"
  },
  "geometry": {"coordinates":[-4.327901,55.938641],"type":"Point"}
}
