{
  "type": "Feature",
  "properties": {
    "date:inception_lower": "2017-02-01",
    "date:inception_upper": "2017-02-01",
    "iso:country": "GB",
    "wof:name": "PL9 0FD",
    "wof:placetype": "postalcode"
  },
  "geometry": {"coordinates":[-4.074534,50.345393],"type":"Point"}
}
