{
  "type": "Feature",
  "properties": {
    "iso:country":"GB",
    "wof:name":"OL14 6JA",
    "wof:placetype":"postalcode"
},
  "geometry": {"coordinates":[-2.06566422864959,53.70727833099211],"type":"Point"}
}