{
  "type": "Feature",
  "properties": {
    "date:inception_lower": "1980-01-01",
    "date:inception_upper": "1980-01-01",
    "iso:country": "GB",
    "wof:name": "DL8 1DB",
    "wof:placetype": "postalcode"
  },
  "geometry": {"coordinates":[-1.578695,54.296145],"type":"Point"}
}
