{
  "type": "Feature",
  "properties": {
    "iso:country":"GB",
    "wof:name":"CM7 9BP",
    "wof:placetype":"postalcode"
},
  "geometry": {"coordinates":[0.55141384332359,51.88310359324419],"type":"Point"}
}