{
  "type": "Feature",
  "properties": {
    "iso:country":"GB",
    "wof:name":"DL8 5DQ",
    "wof:placetype":"postalcode"
},
  "geometry": {"coordinates":[-1.83401514756832,54.31125070418157],"type":"Point"}
}