{
  "type": "Feature",
  "properties": {
    "iso:country": "GB",
    "wof:name": "DL8 5DQ",
    "wof:placetype": "postalcode"
  },
  "geometry": {"coordinates":[-1.834282,54.311271],"type":"Point"}
}
