{
  "type": "Feature",
  "properties": {
    "iso:country":"GB",
    "wof:name":"HP3 0BE",
    "wof:placetype":"postalcode"
},
  "geometry": {"coordinates":[-0.49438737291539,51.73602042749778],"type":"Point"}
}