{
  "type": "Feature",
  "properties": {
    "date:inception_lower":"1980-01-01",
    "date:inception_upper":"1980-01-31",
    "iso:country":"GB",
    "wof:name":"HP3 0BE",
    "wof:placetype":"postalcode"
},
  "geometry": {"coordinates":[-0.494387,51.73602],"type":"Point"}
}