{
  "type": "Feature",
  "properties": {
    "iso:country": "GB",
    "wof:name": "HP3 0BE",
    "wof:placetype": "postalcode"
  },
  "geometry": {"coordinates":[-0.494387,51.73602],"type":"Point"}
}
