{
  "type": "Feature",
  "properties": {
    "date:inception_lower": "1980-01-01",
    "date:inception_upper": "1980-01-01",
    "iso:country": "GB",
    "wof:name": "NE26 2PH",
    "wof:placetype": "postalcode"
  },
  "geometry": {"coordinates":[-1.434941,55.03888],"type":"Point"}
}
