{
  "type": "Feature",
  "properties": {
    "iso:country":"GB",
    "wof:name":"NE26 2PH",
    "wof:placetype":"postalcode"
},
  "geometry": {"coordinates":[-1.43494078551651,55.03887963605983],"type":"Point"}
}