{
  "type": "Feature",
  "properties": {
    "iso:country":"GB",
    "wof:name":"SK6 6ER",
    "wof:placetype":"postalcode"
},
  "geometry": {"coordinates":[-2.08158749879722,53.39520266065062],"type":"Point"}
}