{
  "type": "Feature",
  "properties": {
    "iso:country": "GB",
    "wof:name": "SG14 3JJ",
    "wof:placetype": "postalcode"
  },
  "geometry": {"coordinates":[-0.07995,51.805784],"type":"Point"}
}
