{
  "type": "Feature",
  "properties": {
    "iso:country":"GB",
    "wof:name":"LS12 3PA",
    "wof:placetype":"postalcode"
},
  "geometry": {"coordinates":[-1.60080391319592,53.79947027770853],"type":"Point"}
}