{
  "type": "Feature",
  "properties": {
    "iso:country":"GB",
    "wof:name":"S12 2SA",
    "wof:placetype":"postalcode"
},
  "geometry": {"coordinates":[-1.43447888551196,53.35457610355203],"type":"Point"}
}