{
  "type": "Feature",
  "properties": {
    "iso:country": "GB",
    "wof:name": "E10 5TP",
    "wof:placetype": "postalcode"
  },
  "geometry": {"coordinates":[-0.016595,51.560408],"type":"Point"}
}
