{
  "type": "Feature",
  "properties": {
    "date:inception_lower": "1995-07-01",
    "date:inception_upper": "1995-07-01",
    "iso:country": "GB",
    "wof:name": "E10 5TP",
    "wof:placetype": "postalcode"
  },
  "geometry": {"coordinates":[-0.016524,51.5604],"type":"Point"}
}
