{
  "type": "Feature",
  "properties": {
    "iso:country":"GB",
    "wof:name":"S74 0HE",
    "wof:placetype":"postalcode"
},
  "geometry": {"coordinates":[-1.44382634643397,53.50433470328544],"type":"Point"}
}