{
  "type": "Feature",
  "properties": {
    "date:inception_lower": "1998-06-01",
    "date:inception_upper": "1998-06-01",
    "iso:country": "GB",
    "wof:name": "TR8 5RP",
    "wof:placetype": "postalcode"
  },
  "geometry": {"coordinates":[-5.110477,50.396887],"type":"Point"}
}
