{
  "type": "Feature",
  "properties": {
    "iso:country":"GB",
    "wof:name":"TR8 5RP",
    "wof:placetype":"postalcode"
},
  "geometry": {"coordinates":[-5.11013455633767,50.39708417393884],"type":"Point"}
}