{
  "type": "Feature",
  "properties": {
    "date:inception_lower":"1998-06-01",
    "date:inception_upper":"1998-06-30",
    "iso:country":"GB",
    "wof:name":"TR8 5RP",
    "wof:placetype":"postalcode"
},
  "geometry": {"coordinates":[-5.110135,50.397084],"type":"Point"}
}