{
  "type": "Feature",
  "properties": {
    "iso:country": "GB",
    "wof:name": "TR8 5RP",
    "wof:placetype": "postalcode"
  },
  "geometry": {"coordinates":[-5.110135,50.397084],"type":"Point"}
}
