{
  "type": "Feature",
  "properties": {
    "date:inception_lower": "1980-01-01",
    "date:inception_upper": "1980-01-01",
    "iso:country": "GB",
    "wof:name": "LL28 5TS",
    "wof:placetype": "postalcode"
  },
  "geometry": {"coordinates":[-3.79198,53.22466],"type":"Point"}
}
