{
  "type": "Feature",
  "properties": {
    "iso:country":"GB",
    "wof:name":"LL28 5TS",
    "wof:placetype":"postalcode"
},
  "geometry": {"coordinates":[-3.79198048393992,53.22465988758791],"type":"Point"}
}