{
  "type": "Feature",
  "properties": {
    "iso:country": "GB",
    "wof:name": "LL28 5TS",
    "wof:placetype": "postalcode"
  },
  "geometry": {"coordinates":[-3.79198,53.22466],"type":"Point"}
}
