{
  "type": "Feature",
  "properties": {
    "date:inception_lower": "2008-01-01",
    "date:inception_upper": "2008-01-01",
    "iso:country": "GB",
    "wof:name": "RG1 7AF",
    "wof:placetype": "postalcode"
  },
  "geometry": {"coordinates":[-0.983507,51.453617],"type":"Point"}
}
