{
  "type": "Feature",
  "properties": {
    "iso:country": "GB",
    "wof:name": "PO7 4QH",
    "wof:placetype": "postalcode"
  },
  "geometry": {"coordinates":[-1.113105,50.907064],"type":"Point"}
}
