{
  "type": "Feature",
  "properties": {
    "date:inception_lower": "2001-12-01",
    "date:inception_upper": "2001-12-01",
    "iso:country": "GB",
    "wof:name": "PO7 4QH",
    "wof:placetype": "postalcode"
  },
  "geometry": {"coordinates":[-1.116544,50.898943],"type":"Point"}
}
