{
  "type": "Feature",
  "properties": {
    "iso:country":"GB",
    "wof:name":"PO7 4QH",
    "wof:placetype":"postalcode"
},
  "geometry": {"coordinates":[-1.11277460062201,50.90724856097859],"type":"Point"}
}