{
  "type": "Feature",
  "properties": {
    "iso:country":"GB",
    "wof:name":"DN8 4PF",
    "wof:placetype":"postalcode"
},
  "geometry": {"coordinates":[-0.95373636583903,53.63319440961511],"type":"Point"}
}