{
  "type": "Feature",
  "properties": {
    "date:inception_lower": "1992-08-01",
    "date:inception_upper": "1992-08-01",
    "iso:country": "GB",
    "wof:name": "DN8 4PF",
    "wof:placetype": "postalcode"
  },
  "geometry": {"coordinates":[-0.953736,53.633194],"type":"Point"}
}
