{
  "type": "Feature",
  "properties": {
    "iso:country":"GB",
    "wof:name":"BL9 8QB",
    "wof:placetype":"postalcode"
},
  "geometry": {"coordinates":[-2.27295412096181,53.56048573722075],"type":"Point"}
}