{
  "type": "Feature",
  "properties": {
    "date:inception_lower": "1996-12-01",
    "date:inception_upper": "1996-12-01",
    "iso:country": "GB",
    "wof:name": "BL9 8QB",
    "wof:placetype": "postalcode"
  },
  "geometry": {"coordinates":[-2.269474,53.557292],"type":"Point"}
}
