{
  "type": "Feature",
  "properties": {
    "iso:country": "GB",
    "wof:name": "BL9 8QB",
    "wof:placetype": "postalcode"
  },
  "geometry": {"coordinates":[-2.269474,53.557292],"type":"Point"}
}
