{
  "type": "Feature",
  "properties": {
    "iso:country":"GB",
    "wof:name":"TR2 4JW",
    "wof:placetype":"postalcode"
},
  "geometry": {"coordinates":[-4.95100040513906,50.29241567005882],"type":"Point"}
}