{
  "type": "Feature",
  "properties": {
    "date:inception_lower": "2021-08-01",
    "date:inception_upper": "2021-08-01",
    "iso:country": "GB",
    "wof:name": "SA17 5BD",
    "wof:placetype": "postalcode"
  },
  "geometry": {"coordinates":[-4.309361,51.740281],"type":"Point"}
}
