{
  "type": "Feature",
  "properties": {
    "date:inception_lower": "1997-06-01",
    "date:inception_upper": "1997-06-01",
    "iso:country": "GB",
    "wof:name": "S32 5RB",
    "wof:placetype": "postalcode"
  },
  "geometry": {"coordinates":[-1.671628,53.284335],"type":"Point"}
}
