{
  "type": "Feature",
  "properties": {
    "iso:country": "GB",
    "wof:name": "S32 5RB",
    "wof:placetype": "postalcode"
  },
  "geometry": {"coordinates":[-1.671628,53.284335],"type":"Point"}
}
