{
  "type": "Feature",
  "properties": {
    "iso:country": "GB",
    "wof:name": "S43 4RR",
    "wof:placetype": "postalcode"
  },
  "geometry": {"coordinates":[-1.253765,53.277367],"type":"Point"}
}
