{
  "type": "Feature",
  "properties": {
    "iso:country":"GB",
    "wof:name":"DH9 7NJ",
    "wof:placetype":"postalcode"
},
  "geometry": {"coordinates":[-1.69954222622167,54.86682510546955],"type":"Point"}
}