{
  "type": "Feature",
  "properties": {
    "iso:country":"GB",
    "wof:name":"BH10 6LH",
    "wof:placetype":"postalcode"
},
  "geometry": {"coordinates":[-1.88102118310465,50.76150657069967],"type":"Point"}
}