{
  "type": "Feature",
  "properties": {
    "iso:country": "GB",
    "wof:name": "GU31 4BE",
    "wof:placetype": "postalcode"
  },
  "geometry": {"coordinates":[-0.918572,51.013532],"type":"Point"}
}
