{
  "type": "Feature",
  "properties": {
    "iso:country":"GB",
    "wof:name":"LE17 4EP",
    "wof:placetype":"postalcode"
},
  "geometry": {"coordinates":[-1.20739037598259,52.46144133998197],"type":"Point"}
}