{
  "type": "Feature",
  "properties": {
    "iso:country": "GB",
    "wof:name": "LE17 4EP",
    "wof:placetype": "postalcode"
  },
  "geometry": {"coordinates":[-1.20739,52.461441],"type":"Point"}
}
