{
  "type": "Feature",
  "properties": {
    "iso:country": "GB",
    "wof:name": "SN15 1HH",
    "wof:placetype": "postalcode"
  },
  "geometry": {"coordinates":[-2.118283,51.461018],"type":"Point"}
}
