{
  "type": "Feature",
  "properties": {
    "iso:country":"GB",
    "wof:name":"AB33 8PY",
    "wof:placetype":"postalcode"
},
  "geometry": {"coordinates":[-2.70707793806683,57.23170585330287],"type":"Point"}
}