{
  "type": "Feature",
  "properties": {
    "iso:country":"GB",
    "wof:name":"SN13 8AJ",
    "wof:placetype":"postalcode"
},
  "geometry": {"coordinates":[-2.26837242228701,51.41508375072326],"type":"Point"}
}