{
  "type": "Feature",
  "properties": {
    "iso:country":"GB",
    "wof:name":"LE12 8XZ",
    "wof:placetype":"postalcode"
},
  "geometry": {"coordinates":[-1.17833580156429,52.71095040537655],"type":"Point"}
}