{
  "type": "Feature",
  "properties": {
    "iso:country": "GB",
    "wof:name": "LE14 3SL",
    "wof:placetype": "postalcode"
  },
  "geometry": {"coordinates":[-0.958585,52.762382],"type":"Point"}
}
