{
  "type": "Feature",
  "properties": {
    "iso:country":"GB",
    "wof:name":"LE14 3SL",
    "wof:placetype":"postalcode"
},
  "geometry": {"coordinates":[-0.95858543483997,52.76238204103411],"type":"Point"}
}