{
  "type": "Feature",
  "properties": {
    "iso:country":"GB",
    "wof:name":"TS23 2LU",
    "wof:placetype":"postalcode"
},
  "geometry": {"coordinates":[-1.29042082981016,54.60716854781247],"type":"Point"}
}