{
  "type": "Feature",
  "properties": {
    "iso:country":"GB",
    "wof:name":"DH7 6JS",
    "wof:placetype":"postalcode"
},
  "geometry": {"coordinates":[-1.62719460035111,54.81847534896453],"type":"Point"}
}