{
  "type": "Feature",
  "properties": {
    "date:inception_lower":"1980-01-01",
    "date:inception_upper":"1980-01-31",
    "iso:country":"GB",
    "wof:name":"DH7 6JS",
    "wof:placetype":"postalcode"
},
  "geometry": {"coordinates":[-1.627195,54.818475],"type":"Point"}
}