{
  "type": "Feature",
  "properties": {
    "iso:country":"GB",
    "wof:name":"WF6 1AE",
    "wof:placetype":"postalcode"
},
  "geometry": {"coordinates":[-1.41617331269816,53.69854088051414],"type":"Point"}
}