{
  "type": "Feature",
  "properties": {
    "iso:country": "GB",
    "wof:name": "WF6 1AE",
    "wof:placetype": "postalcode"
  },
  "geometry": {"coordinates":[-1.416173,53.698541],"type":"Point"}
}
