{
  "type": "Feature",
  "properties": {
    "iso:country": "GB",
    "wof:name": "NR19 1LD",
    "wof:placetype": "postalcode"
  },
  "geometry": {"coordinates":[0.940694,52.666121],"type":"Point"}
}
