{
  "type": "Feature",
  "properties": {
    "date:inception_lower":"1998-06-01",
    "date:inception_upper":"1998-06-30",
    "iso:country":"GB",
    "wof:name":"YO41 5NN",
    "wof:placetype":"postalcode"
},
  "geometry": {"coordinates":[-0.889813,53.948743],"type":"Point"}
}