{
  "type": "Feature",
  "properties": {
    "iso:country":"GB",
    "wof:name":"EX17 3EH",
    "wof:placetype":"postalcode"
},
  "geometry": {"coordinates":[-3.65414568670127,50.78908729656447],"type":"Point"}
}