{
  "type": "Feature",
  "properties": {
    "iso:country":"GB",
    "wof:name":"SE15 3BT",
    "wof:placetype":"postalcode"
},
  "geometry": {"coordinates":[-0.04785820742128,51.46231051297931],"type":"Point"}
}