{
  "type": "Feature",
  "properties": {
    "date:inception_lower": "2018-07-01",
    "date:inception_upper": "2018-07-01",
    "iso:country": "GB",
    "wof:name": "B46 1HU",
    "wof:placetype": "postalcode"
  },
  "geometry": {"coordinates":[-1.705301,52.506887],"type":"Point"}
}
