{
  "type": "Feature",
  "properties": {
    "date:inception_lower": "1980-01-01",
    "date:inception_upper": "1980-01-01",
    "iso:country": "GB",
    "wof:name": "ML8 4LT",
    "wof:placetype": "postalcode"
  },
  "geometry": {"coordinates":[-3.824975,55.726904],"type":"Point"}
}
