{
  "type": "Feature",
  "properties": {
    "iso:country":"GB",
    "wof:name":"M40 3WN",
    "wof:placetype":"postalcode"
},
  "geometry": {"coordinates":[-2.17023358994312,53.51468281158991],"type":"Point"}
}