{
  "type": "Feature",
  "properties": {
    "iso:country": "GB",
    "wof:name": "M40 3WN",
    "wof:placetype": "postalcode"
  },
  "geometry": {"coordinates":[-2.170234,53.514683],"type":"Point"}
}
