{
  "type": "Feature",
  "properties": {
    "iso:country":"GB",
    "wof:name":"SR8 3LD",
    "wof:placetype":"postalcode"
},
  "geometry": {"coordinates":[-1.33451525630889,54.78910507646351],"type":"Point"}
}