{
  "type": "Feature",
  "properties": {
    "date:inception_lower": "1980-01-01",
    "date:inception_upper": "1980-01-01",
    "iso:country": "GB",
    "wof:name": "SR8 3LD",
    "wof:placetype": "postalcode"
  },
  "geometry": {"coordinates":[-1.334515,54.789105],"type":"Point"}
}
