{
  "type": "Feature",
  "properties": {
    "iso:country":"GB",
    "wof:name":"SA17 5LL",
    "wof:placetype":"postalcode"
},
  "geometry": {"coordinates":[-4.21039200645265,51.78244569626462],"type":"Point"}
}