{
  "type": "Feature",
  "properties": {
    "iso:country": "GB",
    "wof:name": "SA17 5LL",
    "wof:placetype": "postalcode"
  },
  "geometry": {"coordinates":[-4.210392,51.782446],"type":"Point"}
}
