{
  "type": "Feature",
  "properties": {
    "iso:country":"GB",
    "wof:name":"CT14 9ET",
    "wof:placetype":"postalcode"
},
  "geometry": {"coordinates":[1.3868846725373,51.21035573302005],"type":"Point"}
}