{
  "type": "Feature",
  "properties": {
    "iso:country":"GB",
    "wof:name":"SW8 4SU",
    "wof:placetype":"postalcode"
},
  "geometry": {"coordinates":[-0.13044613933238,51.4778648793111],"type":"Point"}
}