{
  "type": "Feature",
  "properties": {
    "iso:country":"GB",
    "wof:name":"ST14 7NA",
    "wof:placetype":"postalcode"
},
  "geometry": {"coordinates":[-1.8777957259661,52.90290693423606],"type":"Point"}
}