{
  "type": "Feature",
  "properties": {
    "iso:country": "GB",
    "wof:name": "EH49 6LQ",
    "wof:placetype": "postalcode"
  },
  "geometry": {"coordinates":[-3.66097,55.977806],"type":"Point"}
}
