{
  "type": "Feature",
  "properties": {
    "iso:country":"GB",
    "wof:name":"NR28 0NQ",
    "wof:placetype":"postalcode"
},
  "geometry": {"coordinates":[1.37525973055261,52.81910697577558],"type":"Point"}
}