{
  "type": "Feature",
  "properties": {
    "iso:country":"GB",
    "wof:name":"NW9 6HR",
    "wof:placetype":"postalcode"
},
  "geometry": {"coordinates":[-0.24971102805299,51.58881902184059],"type":"Point"}
}