{
  "type": "Feature",
  "properties": {
    "iso:country": "GB",
    "wof:name": "NG12 5QR",
    "wof:placetype": "postalcode"
  },
  "geometry": {"coordinates":[-1.108492,52.845572],"type":"Point"}
}
