{
  "type": "Feature",
  "properties": {
    "iso:country":"GB",
    "wof:name":"M40 3AS",
    "wof:placetype":"postalcode"
},
  "geometry": {"coordinates":[-2.18309502976622,53.50371590200093],"type":"Point"}
}