{
  "type": "Feature",
  "properties": {
    "date:inception_lower": "2009-06-01",
    "date:inception_upper": "2009-06-01",
    "iso:country": "GB",
    "wof:name": "M40 3AS",
    "wof:placetype": "postalcode"
  },
  "geometry": {"coordinates":[-2.183095,53.503716],"type":"Point"}
}
