{
  "type": "Feature",
  "properties": {
    "iso:country":"GB",
    "wof:name":"EN1 3EH",
    "wof:placetype":"postalcode"
},
  "geometry": {"coordinates":[-0.07939021890241,51.65943461719299],"type":"Point"}
}