{
  "type": "Feature",
  "properties": {
    "iso:country": "GB",
    "wof:name": "EC1N 8UB",
    "wof:placetype": "postalcode"
  },
  "geometry": {"coordinates":[-0.107915,51.52058],"type":"Point"}
}
