{
  "type": "Feature",
  "properties": {
    "iso:country":"GB",
    "wof:name":"EC1N 8UB",
    "wof:placetype":"postalcode"
},
  "geometry": {"coordinates":[-0.10896826516639,51.52047792831736],"type":"Point"}
}