{
  "type": "Feature",
  "properties": {
    "iso:country":"GB",
    "wof:name":"BB5 6BQ",
    "wof:placetype":"postalcode"
},
  "geometry": {"coordinates":[-2.36160982350757,53.7610561164967],"type":"Point"}
}