{
  "type": "Feature",
  "properties": {
    "iso:country":"GB",
    "wof:name":"TR10 9HF",
    "wof:placetype":"postalcode"
},
  "geometry": {"coordinates":[-5.13207102508411,50.16536560056447],"type":"Point"}
}