{
  "type": "Feature",
  "properties": {
    "iso:country":"GB",
    "wof:name":"BB2 3HN",
    "wof:placetype":"postalcode"
},
  "geometry": {"coordinates":[-2.47306260211376,53.73759537693923],"type":"Point"}
}