{
  "type": "Feature",
  "properties": {
    "date:inception_lower": "1980-01-01",
    "date:inception_upper": "1980-01-01",
    "iso:country": "GB",
    "wof:name": "TF11 8RQ",
    "wof:placetype": "postalcode"
  },
  "geometry": {"coordinates":[-2.353517,52.713411],"type":"Point"}
}
