{
  "type": "Feature",
  "properties": {
    "date:inception_lower":"1980-01-01",
    "date:inception_upper":"1980-01-31",
    "iso:country":"GB",
    "wof:name":"ML5 1LA",
    "wof:placetype":"postalcode"
},
  "geometry": {"coordinates":[-4.049569,55.863379],"type":"Point"}
}