{
  "type": "Feature",
  "properties": {
    "date:inception_lower": "2020-11-01",
    "date:inception_upper": "2020-11-01",
    "iso:country": "GB",
    "wof:name": "M30 0ZD",
    "wof:placetype": "postalcode"
  },
  "geometry": {"coordinates":[-2.34327,53.479974],"type":"Point"}
}
