{
  "type": "Feature",
  "properties": {
    "iso:country":"GB",
    "wof:name":"SP7 0PD",
    "wof:placetype":"postalcode"
},
  "geometry": {"coordinates":[-2.1913703042091,50.94925328679193],"type":"Point"}
}