{
  "type": "Feature",
  "properties": {
    "iso:country":"GB",
    "wof:name":"OX26 6XE",
    "wof:placetype":"postalcode"
},
  "geometry": {"coordinates":[-1.13735463184687,51.89312750340673],"type":"Point"}
}