{
  "type": "Feature",
  "properties": {
    "iso:country": "GB",
    "wof:name": "OX26 6XE",
    "wof:placetype": "postalcode"
  },
  "geometry": {"coordinates":[-1.137355,51.893127],"type":"Point"}
}
