{
  "type": "Feature",
  "properties": {
    "date:inception_lower": "2018-01-01",
    "date:inception_upper": "2018-01-01",
    "iso:country": "GB",
    "wof:name": "OL16 2BJ",
    "wof:placetype": "postalcode"
  },
  "geometry": {"coordinates":[-2.12488,53.635504],"type":"Point"}
}
