{
  "type": "Feature",
  "properties": {
    "date:inception_lower": "1980-01-01",
    "date:inception_upper": "1980-01-01",
    "iso:country": "GB",
    "wof:name": "HD8 9PW",
    "wof:placetype": "postalcode"
  },
  "geometry": {"coordinates":[-1.614564,53.595194],"type":"Point"}
}
