{
  "type": "Feature",
  "properties": {
    "iso:country":"GB",
    "wof:name":"HD8 9PW",
    "wof:placetype":"postalcode"
},
  "geometry": {"coordinates":[-1.61460657070907,53.59518738325684],"type":"Point"}
}