{
  "type": "Feature",
  "properties": {
    "iso:country": "GB",
    "wof:name": "HD8 9PW",
    "wof:placetype": "postalcode"
  },
  "geometry": {"coordinates":[-1.614607,53.595187],"type":"Point"}
}
