{
  "type": "Feature",
  "properties": {
    "iso:country":"GB",
    "wof:name":"CO1 2LB",
    "wof:placetype":"postalcode"
},
  "geometry": {"coordinates":[0.92219450034786,51.88005050846137],"type":"Point"}
}