{
  "type": "Feature",
  "properties": {
    "date:inception_lower":"1995-01-01",
    "date:inception_upper":"1995-01-31",
    "iso:country":"GB",
    "wof:name":"CO1 2LB",
    "wof:placetype":"postalcode"
},
  "geometry": {"coordinates":[0.922195,51.880051],"type":"Point"}
}