{
  "type": "Feature",
  "properties": {
    "iso:country": "GB",
    "wof:name": "M30 0RN",
    "wof:placetype": "postalcode"
  },
  "geometry": {"coordinates":[-2.357274,53.484087],"type":"Point"}
}
