{
  "type": "Feature",
  "properties": {
    "iso:country":"GB",
    "wof:name":"IP20 0NU",
    "wof:placetype":"postalcode"
},
  "geometry": {"coordinates":[1.37542300035181,52.40972025673528],"type":"Point"}
}