{
  "type": "Feature",
  "properties": {
    "iso:country": "GB",
    "wof:name": "IP20 0NU",
    "wof:placetype": "postalcode"
  },
  "geometry": {"coordinates":[1.375509,52.409731],"type":"Point"}
}
