{
  "type": "Feature",
  "properties": {
    "date:inception_lower": "1980-01-01",
    "date:inception_upper": "1980-01-01",
    "iso:country": "GB",
    "wof:name": "IP20 0NU",
    "wof:placetype": "postalcode"
  },
  "geometry": {"coordinates":[1.375509,52.409731],"type":"Point"}
}
