{
  "type": "Feature",
  "properties": {
    "iso:country":"GB",
    "wof:name":"NG17 2NF",
    "wof:placetype":"postalcode"
},
  "geometry": {"coordinates":[-1.29796161946847,53.12887507748209],"type":"Point"}
}