{
  "type": "Feature",
  "properties": {
    "date:inception_lower": "1995-07-01",
    "date:inception_upper": "1995-07-01",
    "iso:country": "GB",
    "wof:name": "HU8 9XZ",
    "wof:placetype": "postalcode"
  },
  "geometry": {"coordinates":[-0.300931,53.785844],"type":"Point"}
}
