{
  "type": "Feature",
  "properties": {
    "iso:country": "GB",
    "wof:name": "RM19 1NA",
    "wof:placetype": "postalcode"
  },
  "geometry": {"coordinates":[0.25255,51.482715],"type":"Point"}
}
