{
  "type": "Feature",
  "properties": {
    "iso:country":"GB",
    "wof:name":"LE17 4TR",
    "wof:placetype":"postalcode"
},
  "geometry": {"coordinates":[-1.21426315540855,52.45899689034279],"type":"Point"}
}