{
  "type": "Feature",
  "properties": {
    "date:inception_lower": "1980-01-01",
    "date:inception_upper": "1980-01-01",
    "iso:country": "GB",
    "wof:name": "LE17 4TR",
    "wof:placetype": "postalcode"
  },
  "geometry": {"coordinates":[-1.214263,52.458997],"type":"Point"}
}
