{
  "type": "Feature",
  "properties": {
    "iso:country": "GB",
    "wof:name": "SG5 2AE",
    "wof:placetype": "postalcode"
  },
  "geometry": {"coordinates":[-0.287984,51.938253],"type":"Point"}
}
