{
  "type": "Feature",
  "properties": {
    "iso:country":"GB",
    "wof:name":"SG5 2AE",
    "wof:placetype":"postalcode"
},
  "geometry": {"coordinates":[-0.28799269402646,51.93823700222772],"type":"Point"}
}