{
  "type": "Feature",
  "properties": {
    "iso:country": "GB",
    "wof:name": "SY13 9AJ",
    "wof:placetype": "postalcode"
  },
  "geometry": {"coordinates":[-2.683254,52.966276],"type":"Point"}
}
