{
  "type": "Feature",
  "properties": {
    "iso:country":"GB",
    "wof:name":"GL5 2TH",
    "wof:placetype":"postalcode"
},
  "geometry": {"coordinates":[-2.18326274182723,51.71670164862637],"type":"Point"}
}