{
  "type": "Feature",
  "properties": {
    "iso:country":"GB",
    "wof:name":"RG5 4HQ",
    "wof:placetype":"postalcode"
},
  "geometry": {"coordinates":[-0.90194355916978,51.44777397911184],"type":"Point"}
}