{
  "type": "Feature",
  "properties": {
    "iso:country":"GB",
    "wof:name":"E1 4FZ",
    "wof:placetype":"postalcode"
},
  "geometry": {"coordinates":[-0.04299354526643,51.523163599067],"type":"Point"}
}