{
  "type": "Feature",
  "properties": {
    "date:inception_lower": "2012-09-01",
    "date:inception_upper": "2012-09-01",
    "iso:country": "GB",
    "wof:name": "E1 4FZ",
    "wof:placetype": "postalcode"
  },
  "geometry": {"coordinates":[-0.042994,51.523164],"type":"Point"}
}
