{
  "type": "Feature",
  "properties": {
    "iso:country": "GB",
    "wof:name": "GL17 9HJ",
    "wof:placetype": "postalcode"
  },
  "geometry": {"coordinates":[-2.515769,51.85912],"type":"Point"}
}
