{
  "type": "Feature",
  "properties": {
    "iso:country": "GB",
    "wof:name": "CA14 1NS",
    "wof:placetype": "postalcode"
  },
  "geometry": {"coordinates":[-3.522369,54.663592],"type":"Point"}
}
