{
  "type": "Feature",
  "properties": {
    "iso:country":"GB",
    "wof:name":"CA14 1NS",
    "wof:placetype":"postalcode"
},
  "geometry": {"coordinates":[-3.52236954783376,54.66359169585015],"type":"Point"}
}