{
  "type": "Feature",
  "properties": {
    "date:inception_lower": "2023-01-01",
    "date:inception_upper": "2023-01-01",
    "iso:country": "GB",
    "wof:name": "SP2 7GQ",
    "wof:placetype": "postalcode"
  },
  "geometry": {"coordinates":[-1.805755,51.072482],"type":"Point"}
}
