{
  "type": "Feature",
  "properties": {
    "iso:country": "GB",
    "wof:name": "SY8 4PG",
    "wof:placetype": "postalcode"
  },
  "geometry": {"coordinates":[-2.744896,52.3019],"type":"Point"}
}
