{
  "type": "Feature",
  "properties": {
    "iso:country":"GB",
    "wof:name":"LL54 5SF",
    "wof:placetype":"postalcode"
},
  "geometry": {"coordinates":[-4.28861515452656,53.08723252095221],"type":"Point"}
}