{
  "type": "Feature",
  "properties": {
    "iso:country":"GB",
    "wof:name":"W10 4AJ",
    "wof:placetype":"postalcode"
},
  "geometry": {"coordinates":[-0.214266624421,51.53148035437945],"type":"Point"}
}