{
  "type": "Feature",
  "properties": {
    "date:inception_lower": "1980-01-01",
    "date:inception_upper": "1980-01-01",
    "iso:country": "GB",
    "wof:name": "PE25 3AR",
    "wof:placetype": "postalcode"
  },
  "geometry": {"coordinates":[0.336571,53.129342],"type":"Point"}
}
