{
  "type": "Feature",
  "properties": {
    "date:inception_lower": "2006-11-01",
    "date:inception_upper": "2006-11-01",
    "iso:country": "GB",
    "wof:name": "SA61 2AX",
    "wof:placetype": "postalcode"
  },
  "geometry": {"coordinates":[-4.980594,51.801],"type":"Point"}
}
