{
  "type": "Feature",
  "properties": {
    "iso:country":"GB",
    "wof:name":"SA61 2AX",
    "wof:placetype":"postalcode"
},
  "geometry": {"coordinates":[-4.98059383129688,51.80099955979597],"type":"Point"}
}