{
  "type": "Feature",
  "properties": {
    "iso:country":"GB",
    "wof:name":"CO3 3HE",
    "wof:placetype":"postalcode"
},
  "geometry": {"coordinates":[0.89046974987334,51.88590702386691],"type":"Point"}
}