{
  "type": "Feature",
  "properties": {
    "iso:country": "GB",
    "wof:name": "SE28 0BJ",
    "wof:placetype": "postalcode"
  },
  "geometry": {"coordinates":[0.083442,51.491193],"type":"Point"}
}
