{
  "type": "Feature",
  "properties": {
    "iso:country":"GB",
    "wof:name":"PE12 6HD",
    "wof:placetype":"postalcode"
},
  "geometry": {"coordinates":[-0.12298043928438,52.81433751513595],"type":"Point"}
}