{
  "type": "Feature",
  "properties": {
    "iso:country": "GB",
    "wof:name": "SK9 4LR",
    "wof:placetype": "postalcode"
  },
  "geometry": {"coordinates":[-2.27676,53.343304],"type":"Point"}
}
