{
  "type": "Feature",
  "properties": {
    "iso:country":"GB",
    "wof:name":"SK9 4LR",
    "wof:placetype":"postalcode"
},
  "geometry": {"coordinates":[-2.27676061985112,53.34328764519537],"type":"Point"}
}