{
  "type": "Feature",
  "properties": {
    "iso:country":"GB",
    "wof:name":"TN22 5YD",
    "wof:placetype":"postalcode"
},
  "geometry": {"coordinates":[0.10071124447621,50.96338038169133],"type":"Point"}
}