{
  "type": "Feature",
  "properties": {
    "date:inception_lower":"1990-07-01",
    "date:inception_upper":"1990-07-31",
    "iso:country":"GB",
    "wof:name":"TN22 5YD",
    "wof:placetype":"postalcode"
},
  "geometry": {"coordinates":[0.100711,50.96338],"type":"Point"}
}