{
  "type": "Feature",
  "properties": {
    "iso:country": "GB",
    "wof:name": "TN22 5YD",
    "wof:placetype": "postalcode"
  },
  "geometry": {"coordinates":[0.100711,50.96338],"type":"Point"}
}
