{
  "type": "Feature",
  "properties": {
    "iso:country": "GB",
    "wof:name": "PE7 8QQ",
    "wof:placetype": "postalcode"
  },
  "geometry": {"coordinates":[-0.259275,52.529268],"type":"Point"}
}
