{
  "type": "Feature",
  "properties": {
    "iso:country":"GB",
    "wof:name":"RH11 9DG",
    "wof:placetype":"postalcode"
},
  "geometry": {"coordinates":[-0.2029052180947,51.10257041596122],"type":"Point"}
}