{
  "type": "Feature",
  "properties": {
    "iso:country": "GB",
    "wof:name": "WN7 2AH",
    "wof:placetype": "postalcode"
  },
  "geometry": {"coordinates":[-2.504373,53.494639],"type":"Point"}
}
