{
  "type": "Feature",
  "properties": {
    "date:inception_lower":"2018-09-01",
    "date:inception_upper":"2018-09-30",
    "iso:country":"GB",
    "wof:name":"SE18 6NW",
    "wof:placetype":"postalcode"
},
  "geometry": {"coordinates":[0.068872,51.493025],"type":"Point"}
}