{
  "type": "Feature",
  "properties": {
    "iso:country":"GB",
    "wof:name":"MK46 5LD",
    "wof:placetype":"postalcode"
},
  "geometry": {"coordinates":[-0.73533933541002,52.14684056366873],"type":"Point"}
}