{
  "type": "Feature",
  "properties": {
    "iso:country":"GB",
    "wof:name":"CO15 3NB",
    "wof:placetype":"postalcode"
},
  "geometry": {"coordinates":[1.14840816369912,51.79736446464224],"type":"Point"}
}