{
  "type": "Feature",
  "properties": {
    "date:inception_lower": "2005-10-01",
    "date:inception_upper": "2005-10-01",
    "iso:country": "GB",
    "wof:name": "HP22 4FD",
    "wof:placetype": "postalcode"
  },
  "geometry": {"coordinates":[-0.916578,51.873455],"type":"Point"}
}
