{
  "type": "Feature",
  "properties": {
    "iso:country":"GB",
    "wof:name":"HP22 4FD",
    "wof:placetype":"postalcode"
},
  "geometry": {"coordinates":[-0.91657761738224,51.87345482340773],"type":"Point"}
}