{
  "type": "Feature",
  "properties": {
    "iso:country": "GB",
    "wof:name": "HP22 4FD",
    "wof:placetype": "postalcode"
  },
  "geometry": {"coordinates":[-0.916578,51.873455],"type":"Point"}
}
