{
  "type": "Feature",
  "properties": {
    "iso:country":"GB",
    "wof:name":"ST5 0FA",
    "wof:placetype":"postalcode"
},
  "geometry": {"coordinates":[-2.21757028225775,53.03376087443122],"type":"Point"}
}