{
  "type": "Feature",
  "properties": {
    "iso:country": "GB",
    "wof:name": "SO40 3HY",
    "wof:placetype": "postalcode"
  },
  "geometry": {"coordinates":[-1.493732,50.921301],"type":"Point"}
}
