{
  "type": "Feature",
  "properties": {
    "iso:country":"GB",
    "wof:name":"SO40 3HY",
    "wof:placetype":"postalcode"
},
  "geometry": {"coordinates":[-1.49373240401921,50.9213011993298],"type":"Point"}
}