{
  "type": "Feature",
  "properties": {
    "iso:country": "GB",
    "wof:name": "SG17 5PD",
    "wof:placetype": "postalcode"
  },
  "geometry": {"coordinates":[-0.354861,52.029044],"type":"Point"}
}
