{
  "type": "Feature",
  "properties": {
    "iso:country":"GB",
    "wof:name":"CF5 6EH",
    "wof:placetype":"postalcode"
},
  "geometry": {"coordinates":[-3.27364550538532,51.46307732149927],"type":"Point"}
}