{
  "type": "Feature",
  "properties": {
    "iso:country": "GB",
    "wof:name": "CF5 6EH",
    "wof:placetype": "postalcode"
  },
  "geometry": {"coordinates":[-3.273645,51.463077],"type":"Point"}
}
