{
  "type": "Feature",
  "properties": {
    "date:inception_lower": "1995-07-01",
    "date:inception_upper": "1995-07-01",
    "iso:country": "GB",
    "wof:name": "CF5 6EH",
    "wof:placetype": "postalcode"
  },
  "geometry": {"coordinates":[-3.273157,51.463254],"type":"Point"}
}
