{
  "type": "Feature",
  "properties": {
    "date:inception_lower": "1983-03-01",
    "date:inception_upper": "1983-03-01",
    "iso:country": "GB",
    "wof:name": "DE11 0TA",
    "wof:placetype": "postalcode"
  },
  "geometry": {"coordinates":[-1.586318,52.778663],"type":"Point"}
}
