{
  "type": "Feature",
  "properties": {
    "iso:country":"GB",
    "wof:name":"DE11 0TA",
    "wof:placetype":"postalcode"
},
  "geometry": {"coordinates":[-1.58631839066943,52.77866295356942],"type":"Point"}
}