{
  "type": "Feature",
  "properties": {
    "iso:country": "GB",
    "wof:name": "DE11 0TA",
    "wof:placetype": "postalcode"
  },
  "geometry": {"coordinates":[-1.586318,52.778663],"type":"Point"}
}
