{
  "type": "Feature",
  "properties": {
    "iso:country": "GB",
    "wof:name": "WN7 1QZ",
    "wof:placetype": "postalcode"
  },
  "geometry": {"coordinates":[-2.518876,53.501012],"type":"Point"}
}
