{
  "type": "Feature",
  "properties": {
    "iso:country":"GB",
    "wof:name":"BA2 1NZ",
    "wof:placetype":"postalcode"
},
  "geometry": {"coordinates":[-2.39602766263731,51.37280249238204],"type":"Point"}
}