{
  "type": "Feature",
  "properties": {
    "iso:country": "GB",
    "wof:name": "TW19 7NN",
    "wof:placetype": "postalcode"
  },
  "geometry": {"coordinates":[-0.486466,51.458011],"type":"Point"}
}
