{
  "type": "Feature",
  "properties": {
    "iso:country":"GB",
    "wof:name":"GU51 1JZ",
    "wof:placetype":"postalcode"
},
  "geometry": {"coordinates":[-0.85124558986394,51.29623069146587],"type":"Point"}
}