{
  "type": "Feature",
  "properties": {
    "date:inception_lower": "2005-03-01",
    "date:inception_upper": "2005-03-01",
    "iso:country": "GB",
    "wof:name": "GU51 1JZ",
    "wof:placetype": "postalcode"
  },
  "geometry": {"coordinates":[-0.851246,51.296231],"type":"Point"}
}
