{
  "type": "Feature",
  "properties": {
    "date:inception_lower": "1980-01-01",
    "date:inception_upper": "1980-01-01",
    "iso:country": "GB",
    "wof:name": "NN6 8PZ",
    "wof:placetype": "postalcode"
  },
  "geometry": {"coordinates":[-1.007611,52.35035],"type":"Point"}
}
