{
  "type": "Feature",
  "properties": {
    "iso:country":"GB",
    "wof:name":"NN6 8PZ",
    "wof:placetype":"postalcode"
},
  "geometry": {"coordinates":[-1.00761139359853,52.35035021773108],"type":"Point"}
}