{
  "type": "Feature",
  "properties": {
    "date:inception_lower":"1980-01-01",
    "date:inception_upper":"1980-01-31",
    "iso:country":"GB",
    "wof:name":"PE1 3PX",
    "wof:placetype":"postalcode"
},
  "geometry": {"coordinates":[-0.245224,52.591108],"type":"Point"}
}