{
  "type": "Feature",
  "properties": {
    "iso:country":"GB",
    "wof:name":"PE1 3PX",
    "wof:placetype":"postalcode"
},
  "geometry": {"coordinates":[-0.24523837502884,52.59108922688115],"type":"Point"}
}