{
  "type": "Feature",
  "properties": {
    "date:inception_lower": "1980-01-01",
    "date:inception_upper": "1980-01-01",
    "iso:country": "GB",
    "wof:name": "S42 7BT",
    "wof:placetype": "postalcode"
  },
  "geometry": {"coordinates":[-1.529506,53.234215],"type":"Point"}
}
