{
  "type": "Feature",
  "properties": {
    "iso:country": "GB",
    "wof:name": "S42 7BT",
    "wof:placetype": "postalcode"
  },
  "geometry": {"coordinates":[-1.52945,53.233855],"type":"Point"}
}
