{
  "type": "Feature",
  "properties": {
    "iso:country":"GB",
    "wof:name":"S42 7BT",
    "wof:placetype":"postalcode"
},
  "geometry": {"coordinates":[-1.5294927473443,53.23413381279506],"type":"Point"}
}