{
  "type": "Feature",
  "properties": {
    "iso:country":"GB",
    "wof:name":"UB9 6EE",
    "wof:placetype":"postalcode"
},
  "geometry": {"coordinates":[-0.48492138972643,51.60235070521983],"type":"Point"}
}