{
  "type": "Feature",
  "properties": {
    "iso:country": "GB",
    "wof:name": "PE11 1JG",
    "wof:placetype": "postalcode"
  },
  "geometry": {"coordinates":[-0.165005,52.783303],"type":"Point"}
}
