{
  "type": "Feature",
  "properties": {
    "date:inception_lower": "1980-01-01",
    "date:inception_upper": "1980-01-01",
    "iso:country": "GB",
    "wof:name": "SM6 0SY",
    "wof:placetype": "postalcode"
  },
  "geometry": {"coordinates":[-0.154565,51.355093],"type":"Point"}
}
