{
  "type": "Feature",
  "properties": {
    "iso:country":"GB",
    "wof:name":"SM6 0SY",
    "wof:placetype":"postalcode"
},
  "geometry": {"coordinates":[-0.15456480367763,51.35509296589414],"type":"Point"}
}