{
  "type": "Feature",
  "properties": {
    "iso:country": "GB",
    "wof:name": "SM6 0SY",
    "wof:placetype": "postalcode"
  },
  "geometry": {"coordinates":[-0.154565,51.355093],"type":"Point"}
}
