{
  "type": "Feature",
  "properties": {
    "iso:country": "GB",
    "wof:name": "LE4 9DX",
    "wof:placetype": "postalcode"
  },
  "geometry": {"coordinates":[-1.099124,52.647904],"type":"Point"}
}
