{
  "type": "Feature",
  "properties": {
    "iso:country":"GB",
    "wof:name":"LE4 9DX",
    "wof:placetype":"postalcode"
},
  "geometry": {"coordinates":[-1.09912453906379,52.64790406613662],"type":"Point"}
}