{
  "type": "Feature",
  "properties": {
    "date:inception_lower": "2005-01-01",
    "date:inception_upper": "2005-01-01",
    "iso:country": "GB",
    "wof:name": "ML10 6GG",
    "wof:placetype": "postalcode"
  },
  "geometry": {"coordinates":[-4.062146,55.674717],"type":"Point"}
}
