{
  "type": "Feature",
  "properties": {
    "iso:country": "GB",
    "wof:name": "ML10 6GG",
    "wof:placetype": "postalcode"
  },
  "geometry": {"coordinates":[-4.062146,55.674717],"type":"Point"}
}
