{
  "type": "Feature",
  "properties": {
    "date:inception_lower": "1980-01-01",
    "date:inception_upper": "1980-01-01",
    "iso:country": "GB",
    "wof:name": "KY8 5EJ",
    "wof:placetype": "postalcode"
  },
  "geometry": {"coordinates":[-3.044348,56.208845],"type":"Point"}
}
