{
  "type": "Feature",
  "properties": {
    "iso:country":"GB",
    "wof:name":"NE38 9EW",
    "wof:placetype":"postalcode"
},
  "geometry": {"coordinates":[-1.54883921631454,54.88130361365069],"type":"Point"}
}