{
  "type": "Feature",
  "properties": {
    "date:inception_lower": "1980-01-01",
    "date:inception_upper": "1980-01-01",
    "iso:country": "GB",
    "wof:name": "NE38 9EW",
    "wof:placetype": "postalcode"
  },
  "geometry": {"coordinates":[-1.548839,54.881304],"type":"Point"}
}
