{
  "type": "Feature",
  "properties": {
    "iso:country": "GB",
    "wof:name": "HA8 5EJ",
    "wof:placetype": "postalcode"
  },
  "geometry": {"coordinates":[-0.270325,51.602514],"type":"Point"}
}
