{
  "type": "Feature",
  "properties": {
    "date:inception_lower": "1999-12-01",
    "date:inception_upper": "1999-12-01",
    "iso:country": "GB",
    "wof:name": "EX14 1TD",
    "wof:placetype": "postalcode"
  },
  "geometry": {"coordinates":[-3.197336,50.800644],"type":"Point"}
}
