{
  "type": "Feature",
  "properties": {
    "iso:country":"GB",
    "wof:name":"EX14 1TD",
    "wof:placetype":"postalcode"
},
  "geometry": {"coordinates":[-3.19733606629297,50.8006436174034],"type":"Point"}
}