{
  "type": "Feature",
  "properties": {
    "iso:country":"GB",
    "wof:name":"NR3 3JL",
    "wof:placetype":"postalcode"
},
  "geometry": {"coordinates":[1.28666402150598,52.64513388825502],"type":"Point"}
}