{
  "type": "Feature",
  "properties": {
    "iso:country":"GB",
    "wof:name":"B62 8PF",
    "wof:placetype":"postalcode"
},
  "geometry": {"coordinates":[-2.02244282524027,52.45705361384165],"type":"Point"}
}