{
  "type": "Feature",
  "properties": {
    "date:inception_lower":"1980-01-01",
    "date:inception_upper":"1980-01-31",
    "iso:country":"GB",
    "wof:name":"B62 8PF",
    "wof:placetype":"postalcode"
},
  "geometry": {"coordinates":[-2.022443,52.457054],"type":"Point"}
}