{
  "type": "Feature",
  "properties": {
    "iso:country": "GB",
    "wof:name": "TQ13 9EP",
    "wof:placetype": "postalcode"
  },
  "geometry": {"coordinates":[-3.666545,50.594931],"type":"Point"}
}
