{
  "type": "Feature",
  "properties": {
    "iso:country":"GB",
    "wof:name":"OX12 7NS",
    "wof:placetype":"postalcode"
},
  "geometry": {"coordinates":[-1.41952701839333,51.60982750380979],"type":"Point"}
}