{
  "type": "Feature",
  "properties": {
    "date:inception_lower": "1980-01-01",
    "date:inception_upper": "1980-01-01",
    "iso:country": "GB",
    "wof:name": "PO21 1AG",
    "wof:placetype": "postalcode"
  },
  "geometry": {"coordinates":[-0.675661,50.7888],"type":"Point"}
}
