{
  "type": "Feature",
  "properties": {
    "iso:country":"GB",
    "wof:name":"PO21 1AG",
    "wof:placetype":"postalcode"
},
  "geometry": {"coordinates":[-0.67566094114214,50.78879972638408],"type":"Point"}
}