{
  "type": "Feature",
  "properties": {
    "iso:country": "GB",
    "wof:name": "PO21 1AG",
    "wof:placetype": "postalcode"
  },
  "geometry": {"coordinates":[-0.675661,50.7888],"type":"Point"}
}
