{
  "type": "Feature",
  "properties": {
    "iso:country":"GB",
    "wof:name":"RM9 6BD",
    "wof:placetype":"postalcode"
},
  "geometry": {"coordinates":[0.1308931454614,51.53472862358302],"type":"Point"}
}