{
  "type": "Feature",
  "properties": {
    "iso:country":"GB",
    "wof:name":"TA4 4RX",
    "wof:placetype":"postalcode"
},
  "geometry": {"coordinates":[-3.3157989590506,51.16585791989101],"type":"Point"}
}