{
  "type": "Feature",
  "properties": {
    "date:inception_lower": "1995-12-01",
    "date:inception_upper": "1995-12-01",
    "iso:country": "GB",
    "wof:name": "G77 5UB",
    "wof:placetype": "postalcode"
  },
  "geometry": {"coordinates":[-4.303766,55.773939],"type":"Point"}
}
