{
  "type": "Feature",
  "properties": {
    "iso:country":"GB",
    "wof:name":"TW16 6LZ",
    "wof:placetype":"postalcode"
},
  "geometry": {"coordinates":[-0.42452558754959,51.41544384854068],"type":"Point"}
}