{
  "type": "Feature",
  "properties": {
    "date:inception_lower": "2008-01-01",
    "date:inception_upper": "2008-01-01",
    "iso:country": "GB",
    "wof:name": "IP27 0AB",
    "wof:placetype": "postalcode"
  },
  "geometry": {"coordinates":[0.631908,52.442634],"type":"Point"}
}
