{
  "type": "Feature",
  "properties": {
    "iso:country":"GB",
    "wof:name":"IP27 0AB",
    "wof:placetype":"postalcode"
},
  "geometry": {"coordinates":[0.63186838220262,52.44261552998129],"type":"Point"}
}