{
  "type": "Feature",
  "properties": {
    "iso:country": "GB",
    "wof:name": "IP27 0AB",
    "wof:placetype": "postalcode"
  },
  "geometry": {"coordinates":[0.631908,52.442634],"type":"Point"}
}
