{
  "type": "Feature",
  "properties": {
    "date:inception_lower": "1980-01-01",
    "date:inception_upper": "1980-01-01",
    "iso:country": "GB",
    "wof:name": "DY11 6PJ",
    "wof:placetype": "postalcode"
  },
  "geometry": {"coordinates":[-2.266231,52.381334],"type":"Point"}
}
