{
  "type": "Feature",
  "properties": {
    "iso:country": "GB",
    "wof:name": "G33 1BN",
    "wof:placetype": "postalcode"
  },
  "geometry": {"coordinates":[-4.176581,55.893534],"type":"Point"}
}
