{
  "type": "Feature",
  "properties": {
    "date:inception_lower": "1984-06-01",
    "date:inception_upper": "1984-06-01",
    "iso:country": "GB",
    "wof:name": "G33 1BN",
    "wof:placetype": "postalcode"
  },
  "geometry": {"coordinates":[-4.176581,55.893534],"type":"Point"}
}
