{
  "type": "Feature",
  "properties": {
    "iso:country":"GB",
    "wof:name":"SW9 6UU",
    "wof:placetype":"postalcode"
},
  "geometry": {"coordinates":[-0.10296631323523,51.47689294094218],"type":"Point"}
}