{
  "type": "Feature",
  "properties": {
    "iso:country":"GB",
    "wof:name":"RG5 3PP",
    "wof:placetype":"postalcode"
},
  "geometry": {"coordinates":[-0.90352804459984,51.44470457952101],"type":"Point"}
}