{
  "type": "Feature",
  "properties": {
    "date:inception_lower": "1980-01-01",
    "date:inception_upper": "1980-01-01",
    "iso:country": "GB",
    "wof:name": "RG5 3PP",
    "wof:placetype": "postalcode"
  },
  "geometry": {"coordinates":[-0.903528,51.444705],"type":"Point"}
}
