{
  "type": "Feature",
  "properties": {
    "iso:country":"GB",
    "wof:name":"NG6 0HT",
    "wof:placetype":"postalcode"
},
  "geometry": {"coordinates":[-1.18709377429411,52.97998987254882],"type":"Point"}
}