{
  "type": "Feature",
  "properties": {
    "iso:country":"GB",
    "wof:name":"W8 5AB",
    "wof:placetype":"postalcode"
},
  "geometry": {"coordinates":[-0.18562359497656,51.49980105948231],"type":"Point"}
}