{
  "type": "Feature",
  "properties": {
    "date:inception_lower":"2004-04-01",
    "date:inception_upper":"2004-04-30",
    "iso:country":"GB",
    "wof:name":"NG22 8DZ",
    "wof:placetype":"postalcode"
},
  "geometry": {"coordinates":[-1.035603,53.099182],"type":"Point"}
}