{
  "type": "Feature",
  "properties": {
    "iso:country":"GB",
    "wof:name":"SO22 6DX",
    "wof:placetype":"postalcode"
},
  "geometry": {"coordinates":[-1.3347137009168,51.07617065247623],"type":"Point"}
}