{
  "type": "Feature",
  "properties": {
    "iso:country":"GB",
    "wof:name":"WD3 5DH",
    "wof:placetype":"postalcode"
},
  "geometry": {"coordinates":[-0.51712437120669,51.63861286193806],"type":"Point"}
}