{
  "type": "Feature",
  "properties": {
    "date:inception_lower": "1980-01-01",
    "date:inception_upper": "1980-01-01",
    "iso:country": "GB",
    "wof:name": "WD3 5DH",
    "wof:placetype": "postalcode"
  },
  "geometry": {"coordinates":[-0.517103,51.638616],"type":"Point"}
}
