{
  "type": "Feature",
  "properties": {
    "iso:country": "GB",
    "wof:name": "OX14 4RG",
    "wof:placetype": "postalcode"
  },
  "geometry": {"coordinates":[-1.211818,51.639686],"type":"Point"}
}
