{
  "type": "Feature",
  "properties": {
    "date:inception_lower": "1990-02-01",
    "date:inception_upper": "1990-02-01",
    "iso:country": "GB",
    "wof:name": "OX14 4RG",
    "wof:placetype": "postalcode"
  },
  "geometry": {"coordinates":[-1.211398,51.639782],"type":"Point"}
}
