{
  "type": "Feature",
  "properties": {
    "iso:country":"GB",
    "wof:name":"OX14 4RG",
    "wof:placetype":"postalcode"
},
  "geometry": {"coordinates":[-1.21141692553663,51.63977896408181],"type":"Point"}
}