{
  "type": "Feature",
  "properties": {
    "iso:country":"GB",
    "wof:name":"LN4 2JG",
    "wof:placetype":"postalcode"
},
  "geometry": {"coordinates":[-0.53718293865757,53.19787832916093],"type":"Point"}
}