{
  "type": "Feature",
  "properties": {
    "date:inception_lower": "2006-01-01",
    "date:inception_upper": "2006-01-01",
    "iso:country": "GB",
    "wof:name": "LN4 2JG",
    "wof:placetype": "postalcode"
  },
  "geometry": {"coordinates":[-0.537183,53.197878],"type":"Point"}
}
