{
  "type": "Feature",
  "properties": {
    "iso:country": "GB",
    "wof:name": "G82 2RD",
    "wof:placetype": "postalcode"
  },
  "geometry": {"coordinates":[-4.56706,55.947569],"type":"Point"}
}
