{
  "type": "Feature",
  "properties": {
    "iso:country":"GB",
    "wof:name":"G82 2RD",
    "wof:placetype":"postalcode"
},
  "geometry": {"coordinates":[-4.56741713570186,55.94762274976219],"type":"Point"}
}