{
  "type": "Feature",
  "properties": {
    "iso:country": "GB",
    "wof:name": "NE3 1BG",
    "wof:placetype": "postalcode"
  },
  "geometry": {"coordinates":[-1.610093,55.00716],"type":"Point"}
}
