{
  "type": "Feature",
  "properties": {
    "iso:country":"GB",
    "wof:name":"NE3 1BG",
    "wof:placetype":"postalcode"
},
  "geometry": {"coordinates":[-1.61006353953022,55.007099063521],"type":"Point"}
}