{
  "type": "Feature",
  "properties": {
    "iso:country":"GB",
    "wof:name":"NR34 9DP",
    "wof:placetype":"postalcode"
},
  "geometry": {"coordinates":[1.56867843977362,52.45991252729266],"type":"Point"}
}