{
  "type": "Feature",
  "properties": {
    "iso:country": "GB",
    "wof:name": "SP5 5AH",
    "wof:placetype": "postalcode"
  },
  "geometry": {"coordinates":[-2.124071,50.958897],"type":"Point"}
}
