{
  "type": "Feature",
  "properties": {
    "date:inception_lower": "1980-01-01",
    "date:inception_upper": "1980-01-01",
    "iso:country": "GB",
    "wof:name": "SP5 5AH",
    "wof:placetype": "postalcode"
  },
  "geometry": {"coordinates":[-2.124071,50.958897],"type":"Point"}
}
