{
  "type": "Feature",
  "properties": {
    "iso:country":"GB",
    "wof:name":"SP5 5AH",
    "wof:placetype":"postalcode"
},
  "geometry": {"coordinates":[-2.12407751752649,50.95890314170143],"type":"Point"}
}