{
  "type": "Feature",
  "properties": {
    "iso:country":"GB",
    "wof:name":"WN8 0LG",
    "wof:placetype":"postalcode"
},
  "geometry": {"coordinates":[-2.72424091421585,53.54625339344996],"type":"Point"}
}