{
  "type": "Feature",
  "properties": {
    "iso:country":"GB",
    "wof:name":"WF10 2AE",
    "wof:placetype":"postalcode"
},
  "geometry": {"coordinates":[-1.35605216376239,53.73861711174035],"type":"Point"}
}