{
  "type": "Feature",
  "properties": {
    "date:inception_lower":"1980-01-01",
    "date:inception_upper":"1980-01-31",
    "iso:country":"GB",
    "wof:name":"WF10 2AE",
    "wof:placetype":"postalcode"
},
  "geometry": {"coordinates":[-1.356052,53.738617],"type":"Point"}
}