{
  "type": "Feature",
  "properties": {
    "date:inception_lower": "2015-01-01",
    "date:inception_upper": "2015-01-01",
    "iso:country": "GB",
    "wof:name": "M19 3HB",
    "wof:placetype": "postalcode"
  },
  "geometry": {"coordinates":[-2.179072,53.447471],"type":"Point"}
}
