{
  "type": "Feature",
  "properties": {
    "iso:country": "GB",
    "wof:name": "M19 3HB",
    "wof:placetype": "postalcode"
  },
  "geometry": {"coordinates":[-2.179072,53.447471],"type":"Point"}
}
