{
  "type": "Feature",
  "properties": {
    "date:inception_lower": "1980-01-01",
    "date:inception_upper": "1980-01-01",
    "iso:country": "GB",
    "wof:name": "GL15 4AY",
    "wof:placetype": "postalcode"
  },
  "geometry": {"coordinates":[-2.465652,51.750232],"type":"Point"}
}
