{
  "type": "Feature",
  "properties": {
    "iso:country": "GB",
    "wof:name": "GL15 4AY",
    "wof:placetype": "postalcode"
  },
  "geometry": {"coordinates":[-2.465652,51.750232],"type":"Point"}
}
