{
  "type": "Feature",
  "properties": {
    "iso:country":"GB",
    "wof:name":"GL6 6DB",
    "wof:placetype":"postalcode"
},
  "geometry": {"coordinates":[-2.23820390308332,51.76514600415583],"type":"Point"}
}