{
  "type": "Feature",
  "properties": {
    "date:inception_lower":"1980-01-01",
    "date:inception_upper":"1980-01-31",
    "iso:country":"GB",
    "wof:name":"LS7 3PW",
    "wof:placetype":"postalcode"
},
  "geometry": {"coordinates":[-1.539325,53.827688],"type":"Point"}
}