{
  "type": "Feature",
  "properties": {
    "date:inception_lower": "2014-07-01",
    "date:inception_upper": "2014-07-01",
    "iso:country": "GB",
    "wof:name": "NG5 9AY",
    "wof:placetype": "postalcode"
  },
  "geometry": {"coordinates":[-1.172016,53.004436],"type":"Point"}
}
