{
  "type": "Feature",
  "properties": {
    "iso:country":"GB",
    "wof:name":"DL8 4SW",
    "wof:placetype":"postalcode"
},
  "geometry": {"coordinates":[-1.77856111456646,54.26800507594622],"type":"Point"}
}