{
  "type": "Feature",
  "properties": {
    "iso:country":"GB",
    "wof:name":"GL2 5FH",
    "wof:placetype":"postalcode"
},
  "geometry": {"coordinates":[-2.260611301607,51.85398352596558],"type":"Point"}
}