{
  "type": "Feature",
  "properties": {
    "date:inception_lower":"2013-08-01",
    "date:inception_upper":"2013-08-31",
    "iso:country":"GB",
    "wof:name":"GL2 5FH",
    "wof:placetype":"postalcode"
},
  "geometry": {"coordinates":[-2.260681,51.853972],"type":"Point"}
}