{
  "type": "Feature",
  "properties": {
    "iso:country":"GB",
    "wof:name":"BD4 7RT",
    "wof:placetype":"postalcode"
},
  "geometry": {"coordinates":[-1.73295782336386,53.7817172453459],"type":"Point"}
}