{
  "type": "Feature",
  "properties": {
    "date:inception_lower": "1980-01-01",
    "date:inception_upper": "1980-01-01",
    "iso:country": "GB",
    "wof:name": "L11 2TW",
    "wof:placetype": "postalcode"
  },
  "geometry": {"coordinates":[-2.910149,53.444453],"type":"Point"}
}
