{
  "type": "Feature",
  "properties": {
    "iso:country":"GB",
    "wof:name":"CF10 3EU",
    "wof:placetype":"postalcode"
},
  "geometry": {"coordinates":[-3.18448073684417,51.49140161667152],"type":"Point"}
}