{
  "type": "Feature",
  "properties": {
    "iso:country":"GB",
    "wof:name":"SO15 5DT",
    "wof:placetype":"postalcode"
},
  "geometry": {"coordinates":[-1.41880795298841,50.91606058840964],"type":"Point"}
}