{
  "type": "Feature",
  "properties": {
    "iso:country":"GB",
    "wof:name":"PL11 3DH",
    "wof:placetype":"postalcode"
},
  "geometry": {"coordinates":[-4.37934469029948,50.37369297218601],"type":"Point"}
}