{
  "type": "Feature",
  "properties": {
    "iso:country": "GB",
    "wof:name": "PL11 3DH",
    "wof:placetype": "postalcode"
  },
  "geometry": {"coordinates":[-4.379425,50.372662],"type":"Point"}
}
