{
  "type": "Feature",
  "properties": {
    "iso:country":"GB",
    "wof:name":"WF12 0QG",
    "wof:placetype":"postalcode"
},
  "geometry": {"coordinates":[-1.60994667091379,53.65822504557866],"type":"Point"}
}