{
  "type": "Feature",
  "properties": {
    "iso:country": "GB",
    "wof:name": "EC1V 7JW",
    "wof:placetype": "postalcode"
  },
  "geometry": {"coordinates":[-0.105042,51.531026],"type":"Point"}
}
