{
  "type": "Feature",
  "properties": {
    "iso:country":"GB",
    "wof:name":"EC1V 7JW",
    "wof:placetype":"postalcode"
},
  "geometry": {"coordinates":[-0.10504211158642,51.53102575024502],"type":"Point"}
}