{
  "type": "Feature",
  "properties": {
    "iso:country":"GB",
    "wof:name":"NP8 1BU",
    "wof:placetype":"postalcode"
},
  "geometry": {"coordinates":[-3.141246063923,51.85979379030707],"type":"Point"}
}