{
  "type": "Feature",
  "properties": {
    "iso:country": "GB",
    "wof:name": "NP8 1BU",
    "wof:placetype": "postalcode"
  },
  "geometry": {"coordinates":[-3.141246,51.859794],"type":"Point"}
}
