{
  "type": "Feature",
  "properties": {
    "iso:country":"GB",
    "wof:name":"SE15 2NS",
    "wof:placetype":"postalcode"
},
  "geometry": {"coordinates":[-0.05367038386245,51.47525767466494],"type":"Point"}
}