{
  "type": "Feature",
  "properties": {
    "date:inception_lower":"1980-01-01",
    "date:inception_upper":"1980-01-31",
    "iso:country":"GB",
    "wof:name":"EH19 3EB",
    "wof:placetype":"postalcode"
},
  "geometry": {"coordinates":[-3.107562,55.871088],"type":"Point"}
}