{
  "type": "Feature",
  "properties": {
    "iso:country":"GB",
    "wof:name":"LS9 7DW",
    "wof:placetype":"postalcode"
},
  "geometry": {"coordinates":[-1.52907007930314,53.79918325520245],"type":"Point"}
}