{
  "type": "Feature",
  "properties": {
    "iso:country":"GB",
    "wof:name":"TS27 4AL",
    "wof:placetype":"postalcode"
},
  "geometry": {"coordinates":[-1.27803107518327,54.74294990285571],"type":"Point"}
}