{
  "type": "Feature",
  "properties": {
    "date:inception_lower": "1980-01-01",
    "date:inception_upper": "1980-01-01",
    "iso:country": "GB",
    "wof:name": "TS27 4AL",
    "wof:placetype": "postalcode"
  },
  "geometry": {"coordinates":[-1.278031,54.74295],"type":"Point"}
}
