{
  "type": "Feature",
  "properties": {
    "iso:country":"GB",
    "wof:name":"NE15 6ER",
    "wof:placetype":"postalcode"
},
  "geometry": {"coordinates":[-1.69126571444977,54.97737197967822],"type":"Point"}
}