{
  "type": "Feature",
  "properties": {
    "iso:country":"GB",
    "wof:name":"CB23 6GR",
    "wof:placetype":"postalcode"
},
  "geometry": {"coordinates":[-0.06560469737941,52.22164961188199],"type":"Point"}
}