{
  "type": "Feature",
  "properties": {
    "iso:country":"GB",
    "wof:name":"NE66 2JA",
    "wof:placetype":"postalcode"
},
  "geometry": {"coordinates":[-1.72430315510155,55.36540107815016],"type":"Point"}
}