{
  "type": "Feature",
  "properties": {
    "iso:country":"GB",
    "wof:name":"AL2 3TA",
    "wof:placetype":"postalcode"
},
  "geometry": {"coordinates":[-0.35833070501476,51.70910196880539],"type":"Point"}
}