{
  "type": "Feature",
  "properties": {
    "iso:country":"GB",
    "wof:name":"UB5 4BS",
    "wof:placetype":"postalcode"
},
  "geometry": {"coordinates":[-0.36769055019805,51.55546758031196],"type":"Point"}
}