{
  "type": "Feature",
  "properties": {
    "iso:country":"GB",
    "wof:name":"LL54 7TW",
    "wof:placetype":"postalcode"
},
  "geometry": {"coordinates":[-4.27636569420713,53.07556347333714],"type":"Point"}
}