{
  "type": "Feature",
  "properties": {
    "date:inception_lower": "1980-01-01",
    "date:inception_upper": "1980-01-01",
    "iso:country": "GB",
    "wof:name": "LL54 7TW",
    "wof:placetype": "postalcode"
  },
  "geometry": {"coordinates":[-4.276366,53.075563],"type":"Point"}
}
