{
  "type": "Feature",
  "properties": {
    "iso:country": "GB",
    "wof:name": "LL54 7TW",
    "wof:placetype": "postalcode"
  },
  "geometry": {"coordinates":[-4.276366,53.075563],"type":"Point"}
}
