{
  "type": "Feature",
  "properties": {
    "iso:country":"GB",
    "wof:name":"NW10 7BD",
    "wof:placetype":"postalcode"
},
  "geometry": {"coordinates":[-0.26090489869042,51.53117387584562],"type":"Point"}
}