{
  "type": "Feature",
  "properties": {
    "iso:country":"GB",
    "wof:name":"BH22 9BL",
    "wof:placetype":"postalcode"
},
  "geometry": {"coordinates":[-1.89176329327593,50.8006257383434],"type":"Point"}
}