{
  "type": "Feature",
  "properties": {
    "date:inception_lower":"1980-01-01",
    "date:inception_upper":"1980-01-31",
    "iso:country":"GB",
    "wof:name":"MK44 2RW",
    "wof:placetype":"postalcode"
},
  "geometry": {"coordinates":[-0.423999,52.177339],"type":"Point"}
}