{
  "type": "Feature",
  "properties": {
    "iso:country":"GB",
    "wof:name":"MK44 2RW",
    "wof:placetype":"postalcode"
},
  "geometry": {"coordinates":[-0.4239989894778,52.17733924618869],"type":"Point"}
}