{
  "type": "Feature",
  "properties": {
    "date:inception_lower": "1980-01-01",
    "date:inception_upper": "1980-01-01",
    "iso:country": "GB",
    "wof:name": "SY5 9LB",
    "wof:placetype": "postalcode"
  },
  "geometry": {"coordinates":[-2.856266,52.714244],"type":"Point"}
}
