{
  "type": "Feature",
  "properties": {
    "iso:country":"GB",
    "wof:name":"SY5 9LB",
    "wof:placetype":"postalcode"
},
  "geometry": {"coordinates":[-2.85626568584101,52.7142438511189],"type":"Point"}
}