{
  "type": "Feature",
  "properties": {
    "iso:country":"GB",
    "wof:name":"OL2 7SB",
    "wof:placetype":"postalcode"
},
  "geometry": {"coordinates":[-2.09899446675538,53.57936236228517],"type":"Point"}
}