{
  "type": "Feature",
  "properties": {
    "iso:country":"GB",
    "wof:name":"LN8 2DR",
    "wof:placetype":"postalcode"
},
  "geometry": {"coordinates":[-0.47352913678064,53.37633321453875],"type":"Point"}
}