{
  "type": "Feature",
  "properties": {
    "date:inception_lower":"1994-05-01",
    "date:inception_upper":"1994-05-31",
    "iso:country":"GB",
    "wof:name":"PO9 3EN",
    "wof:placetype":"postalcode"
},
  "geometry": {"coordinates":[-0.990102,50.863888],"type":"Point"}
}