{
  "type": "Feature",
  "properties": {
    "iso:country": "GB",
    "wof:name": "PO9 3EN",
    "wof:placetype": "postalcode"
  },
  "geometry": {"coordinates":[-0.990102,50.863888],"type":"Point"}
}
