{
  "type": "Feature",
  "properties": {
    "iso:country":"GB",
    "wof:name":"PO9 3EN",
    "wof:placetype":"postalcode"
},
  "geometry": {"coordinates":[-0.99010171785009,50.86388754284327],"type":"Point"}
}