{
  "type": "Feature",
  "properties": {
    "iso:country":"GB",
    "wof:name":"IP21 4TH",
    "wof:placetype":"postalcode"
},
  "geometry": {"coordinates":[1.22654768594082,52.4313015533781],"type":"Point"}
}