{
  "type": "Feature",
  "properties": {
    "iso:country": "GB",
    "wof:name": "CM9 4DT",
    "wof:placetype": "postalcode"
  },
  "geometry": {"coordinates":[0.676909,51.745782],"type":"Point"}
}
