{
  "type": "Feature",
  "properties": {
    "iso:country":"GB",
    "wof:name":"OX2 8EY",
    "wof:placetype":"postalcode"
},
  "geometry": {"coordinates":[-1.27394082419476,51.79466149608329],"type":"Point"}
}