{
  "type": "Feature",
  "properties": {
    "date:inception_lower": "1980-01-01",
    "date:inception_upper": "1980-01-01",
    "iso:country": "GB",
    "wof:name": "SA63 4UR",
    "wof:placetype": "postalcode"
  },
  "geometry": {"coordinates":[-4.881309,51.85117],"type":"Point"}
}
