{
  "type": "Feature",
  "properties": {
    "date:inception_lower":"1980-01-01",
    "date:inception_upper":"1980-01-31",
    "iso:country":"GB",
    "wof:name":"BH8 8QQ",
    "wof:placetype":"postalcode"
},
  "geometry": {"coordinates":[-1.859427,50.733309],"type":"Point"}
}