{
  "type": "Feature",
  "properties": {
    "iso:country": "GB",
    "wof:name": "BH23 3SP",
    "wof:placetype": "postalcode"
  },
  "geometry": {"coordinates":[-1.76105,50.74108],"type":"Point"}
}
