{
  "type": "Feature",
  "properties": {
    "iso:country":"GB",
    "wof:name":"PL27 6HQ",
    "wof:placetype":"postalcode"
},
  "geometry": {"coordinates":[-4.82463568817361,50.52086932685143],"type":"Point"}
}