{
  "type": "Feature",
  "properties": {
    "iso:country": "GB",
    "wof:name": "PL27 6HQ",
    "wof:placetype": "postalcode"
  },
  "geometry": {"coordinates":[-4.824636,50.520869],"type":"Point"}
}
