{
  "type": "Feature",
  "properties": {
    "iso:country":"GB",
    "wof:name":"OX26 6QL",
    "wof:placetype":"postalcode"
},
  "geometry": {"coordinates":[-1.146845259153,51.89996695956012],"type":"Point"}
}