{
  "type": "Feature",
  "properties": {
    "date:inception_lower": "2021-09-01",
    "date:inception_upper": "2021-09-01",
    "iso:country": "GB",
    "wof:name": "SK2 6BG",
    "wof:placetype": "postalcode"
  },
  "geometry": {"coordinates":[-2.138687,53.395517],"type":"Point"}
}
