{
  "type": "Feature",
  "properties": {
    "iso:country": "GB",
    "wof:name": "RG10 9EP",
    "wof:placetype": "postalcode"
  },
  "geometry": {"coordinates":[-0.863687,51.476453],"type":"Point"}
}
