{
  "type": "Feature",
  "properties": {
    "date:inception_lower":"2000-06-01",
    "date:inception_upper":"2000-06-30",
    "iso:country":"GB",
    "wof:name":"RG10 9EP",
    "wof:placetype":"postalcode"
},
  "geometry": {"coordinates":[-0.863687,51.476453],"type":"Point"}
}