{
  "type": "Feature",
  "properties": {
    "date:inception_lower": "2022-09-01",
    "date:inception_upper": "2022-09-01",
    "iso:country": "GB",
    "wof:name": "BD1 3AT",
    "wof:placetype": "postalcode"
  },
  "geometry": {"coordinates":[-1.759583,53.799836],"type":"Point"}
}
