{
  "type": "Feature",
  "properties": {
    "iso:country":"GB",
    "wof:name":"G44 3TG",
    "wof:placetype":"postalcode"
},
  "geometry": {"coordinates":[-4.27512274073714,55.80256829414577],"type":"Point"}
}