{
  "type": "Feature",
  "properties": {
    "iso:country":"GB",
    "wof:name":"NE28 8EJ",
    "wof:placetype":"postalcode"
},
  "geometry": {"coordinates":[-1.54045406869923,54.99631536938655],"type":"Point"}
}