{
  "type": "Feature",
  "properties": {
    "iso:country": "GB",
    "wof:name": "NE28 8EJ",
    "wof:placetype": "postalcode"
  },
  "geometry": {"coordinates":[-1.540454,54.996315],"type":"Point"}
}
