{
  "type": "Feature",
  "properties": {
    "iso:country": "GB",
    "wof:name": "WD7 7HU",
    "wof:placetype": "postalcode"
  },
  "geometry": {"coordinates":[-0.321362,51.698388],"type":"Point"}
}
