{
  "type": "Feature",
  "properties": {
    "iso:country":"GB",
    "wof:name":"WD7 7HU",
    "wof:placetype":"postalcode"
},
  "geometry": {"coordinates":[-0.32092023201761,51.6972522994143],"type":"Point"}
}