{
  "type": "Feature",
  "properties": {
    "date:inception_lower":"1980-01-01",
    "date:inception_upper":"1980-01-31",
    "iso:country":"GB",
    "wof:name":"WD7 7HU",
    "wof:placetype":"postalcode"
},
  "geometry": {"coordinates":[-0.321362,51.698388],"type":"Point"}
}