{
  "type": "Feature",
  "properties": {
    "iso:country":"GB",
    "wof:name":"N20 8AX",
    "wof:placetype":"postalcode"
},
  "geometry": {"coordinates":[-0.20014449109617,51.63723027259874],"type":"Point"}
}