{
  "type": "Feature",
  "properties": {
    "iso:country":"GB",
    "wof:name":"NG8 1BW",
    "wof:placetype":"postalcode"
},
  "geometry": {"coordinates":[-1.19309792731486,52.94789343188593],"type":"Point"}
}