{
  "type": "Feature",
  "properties": {
    "iso:country":"GB",
    "wof:name":"IP14 2NZ",
    "wof:placetype":"postalcode"
},
  "geometry": {"coordinates":[0.98580381821063,52.16842465680013],"type":"Point"}
}