{
  "type": "Feature",
  "properties": {
    "iso:country": "GB",
    "wof:name": "IP14 2NZ",
    "wof:placetype": "postalcode"
  },
  "geometry": {"coordinates":[0.985854,52.168494],"type":"Point"}
}
