{
  "type": "Feature",
  "properties": {
    "date:inception_lower": "1990-07-01",
    "date:inception_upper": "1990-07-01",
    "iso:country": "GB",
    "wof:name": "IP14 2NZ",
    "wof:placetype": "postalcode"
  },
  "geometry": {"coordinates":[0.985854,52.168503],"type":"Point"}
}
