{
  "type": "Feature",
  "properties": {
    "iso:country":"GB",
    "wof:name":"UB8 2SX",
    "wof:placetype":"postalcode"
},
  "geometry": {"coordinates":[-0.48903045676912,51.53681555039239],"type":"Point"}
}