{
  "type": "Feature",
  "properties": {
    "iso:country":"GB",
    "wof:name":"SK10 5BL",
    "wof:placetype":"postalcode"
},
  "geometry": {"coordinates":[-2.09410093346174,53.29395432566291],"type":"Point"}
}