{
  "type": "Feature",
  "properties": {
    "iso:country":"GB",
    "wof:name":"HD9 1HT",
    "wof:placetype":"postalcode"
},
  "geometry": {"coordinates":[-1.75318681781854,53.55883588825634],"type":"Point"}
}