{
  "type": "Feature",
  "properties": {
    "iso:country": "GB",
    "wof:name": "HD9 1HT",
    "wof:placetype": "postalcode"
  },
  "geometry": {"coordinates":[-1.753187,53.558836],"type":"Point"}
}
