{
  "type": "Feature",
  "properties": {
    "iso:country":"GB",
    "wof:name":"PL8 2LA",
    "wof:placetype":"postalcode"
},
  "geometry": {"coordinates":[-4.00165354224523,50.34771092858687],"type":"Point"}
}