{
  "type": "Feature",
  "properties": {
    "iso:country": "GB",
    "wof:name": "MK43 0PS",
    "wof:placetype": "postalcode"
  },
  "geometry": {"coordinates":[-0.546296,52.061475],"type":"Point"}
}
