{
  "type": "Feature",
  "properties": {
    "date:inception_lower": "1980-01-01",
    "date:inception_upper": "1980-01-01",
    "iso:country": "GB",
    "wof:name": "CM6 1PB",
    "wof:placetype": "postalcode"
  },
  "geometry": {"coordinates":[0.316787,51.822277],"type":"Point"}
}
