{
  "type": "Feature",
  "properties": {
    "iso:country":"GB",
    "wof:name":"CM6 1PB",
    "wof:placetype":"postalcode"
},
  "geometry": {"coordinates":[0.31678713544511,51.82227662135647],"type":"Point"}
}