{
  "type": "Feature",
  "properties": {
    "iso:country":"GB",
    "wof:name":"FK2 7GE",
    "wof:placetype":"postalcode"
},
  "geometry": {"coordinates":[-3.7987341235966,56.0152094205168],"type":"Point"}
}