{
  "type": "Feature",
  "properties": {
    "date:inception_lower": "2004-03-01",
    "date:inception_upper": "2004-03-01",
    "iso:country": "GB",
    "wof:name": "FK2 7GE",
    "wof:placetype": "postalcode"
  },
  "geometry": {"coordinates":[-3.798734,56.015209],"type":"Point"}
}
