{
  "type": "Feature",
  "properties": {
    "iso:country":"GB",
    "wof:name":"SY4 5AW",
    "wof:placetype":"postalcode"
},
  "geometry": {"coordinates":[-2.725301561974,52.861307720878],"type":"Point"}
}