{
  "type": "Feature",
  "properties": {
    "date:inception_lower": "1992-08-01",
    "date:inception_upper": "1992-08-01",
    "iso:country": "GB",
    "wof:name": "DE56 1UT",
    "wof:placetype": "postalcode"
  },
  "geometry": {"coordinates":[-1.485219,53.02038],"type":"Point"}
}
