{
  "type": "Feature",
  "properties": {
    "iso:country":"GB",
    "wof:name":"NW5 2LY",
    "wof:placetype":"postalcode"
},
  "geometry": {"coordinates":[-0.14027984237279,51.55116629518675],"type":"Point"}
}