{
  "type": "Feature",
  "properties": {
    "iso:country": "GB",
    "wof:name": "NW5 2LY",
    "wof:placetype": "postalcode"
  },
  "geometry": {"coordinates":[-0.14028,51.551166],"type":"Point"}
}
