{
  "type": "Feature",
  "properties": {
    "iso:country":"GB",
    "wof:name":"BB4 9SP",
    "wof:placetype":"postalcode"
},
  "geometry": {"coordinates":[-2.24718033972518,53.69683044430151],"type":"Point"}
}