{
  "type": "Feature",
  "properties": {
    "date:inception_lower":"1995-07-01",
    "date:inception_upper":"1995-07-31",
    "iso:country":"GB",
    "wof:name":"TR12 6LX",
    "wof:placetype":"postalcode"
},
  "geometry": {"coordinates":[-5.091087,50.049769],"type":"Point"}
}