{
  "type": "Feature",
  "properties": {
    "iso:country": "GB",
    "wof:name": "NP12 2QQ",
    "wof:placetype": "postalcode"
  },
  "geometry": {"coordinates":[-3.203972,51.654224],"type":"Point"}
}
