{
  "type": "Feature",
  "properties": {
    "iso:country": "GB",
    "wof:name": "S13 7GD",
    "wof:placetype": "postalcode"
  },
  "geometry": {"coordinates":[-1.37662,53.358764],"type":"Point"}
}
