{
  "type": "Feature",
  "properties": {
    "iso:country":"GB",
    "wof:name":"EH5 1JL",
    "wof:placetype":"postalcode"
},
  "geometry": {"coordinates":[-3.23384386151341,55.97671600916497],"type":"Point"}
}