{
  "type": "Feature",
  "properties": {
    "date:inception_lower": "1980-01-01",
    "date:inception_upper": "1980-01-01",
    "iso:country": "GB",
    "wof:name": "EH5 1JL",
    "wof:placetype": "postalcode"
  },
  "geometry": {"coordinates":[-3.23384,55.976585],"type":"Point"}
}
