{
  "type": "Feature",
  "properties": {
    "iso:country": "GB",
    "wof:name": "PO20 2ED",
    "wof:placetype": "postalcode"
  },
  "geometry": {"coordinates":[-0.711218,50.849793],"type":"Point"}
}
