{
  "type": "Feature",
  "properties": {
    "iso:country":"GB",
    "wof:name":"RG24 8PZ",
    "wof:placetype":"postalcode"
},
  "geometry": {"coordinates":[-1.06404842557588,51.28148023239262],"type":"Point"}
}