{
  "type": "Feature",
  "properties": {
    "date:inception_lower": "2018-01-01",
    "date:inception_upper": "2018-01-01",
    "iso:country": "GB",
    "wof:name": "MK10 7JB",
    "wof:placetype": "postalcode"
  },
  "geometry": {"coordinates":[-0.679007,52.045507],"type":"Point"}
}
