{
  "type": "Feature",
  "properties": {
    "iso:country": "GB",
    "wof:name": "E2 0PD",
    "wof:placetype": "postalcode"
  },
  "geometry": {"coordinates":[-0.052242,51.530062],"type":"Point"}
}
