{
  "type": "Feature",
  "properties": {
    "date:inception_lower": "1980-01-01",
    "date:inception_upper": "1980-01-01",
    "iso:country": "GB",
    "wof:name": "DH1 2LG",
    "wof:placetype": "postalcode"
  },
  "geometry": {"coordinates":[-1.547279,54.779822],"type":"Point"}
}
