{
  "type": "Feature",
  "properties": {
    "iso:country":"GB",
    "wof:name":"DE5 3NB",
    "wof:placetype":"postalcode"
},
  "geometry": {"coordinates":[-1.38559425359179,53.04853766426151],"type":"Point"}
}