{
  "type": "Feature",
  "properties": {
    "date:inception_lower": "2009-06-01",
    "date:inception_upper": "2009-06-01",
    "iso:country": "GB",
    "wof:name": "BA4 4FH",
    "wof:placetype": "postalcode"
  },
  "geometry": {"coordinates":[-2.538425,51.200987],"type":"Point"}
}
