{
  "type": "Feature",
  "properties": {
    "iso:country":"GB",
    "wof:name":"BA4 4FH",
    "wof:placetype":"postalcode"
},
  "geometry": {"coordinates":[-2.53893991193792,51.20105359896162],"type":"Point"}
}