{
  "type": "Feature",
  "properties": {
    "iso:country":"GB",
    "wof:name":"NW1 1BU",
    "wof:placetype":"postalcode"
},
  "geometry": {"coordinates":[-0.1360657613912,51.53181056798098],"type":"Point"}
}