{
  "type": "Feature",
  "properties": {
    "iso:country": "GB",
    "wof:name": "FY2 0WL",
    "wof:placetype": "postalcode"
  },
  "geometry": {"coordinates":[-3.02414,53.845851],"type":"Point"}
}
