{
  "type": "Feature",
  "properties": {
    "iso:country": "GB",
    "wof:name": "RH10 3JJ",
    "wof:placetype": "postalcode"
  },
  "geometry": {"coordinates":[-0.124782,51.140095],"type":"Point"}
}
