{
  "type": "Feature",
  "properties": {
    "iso:country":"GB",
    "wof:name":"IV51 9HZ",
    "wof:placetype":"postalcode"
},
  "geometry": {"coordinates":[-6.24969170350535,57.6584626503484],"type":"Point"}
}