{
  "type": "Feature",
  "properties": {
    "iso:country":"GB",
    "wof:name":"PL35 0HG",
    "wof:placetype":"postalcode"
},
  "geometry": {"coordinates":[-4.68835286724941,50.69109526450767],"type":"Point"}
}