{
  "type": "Feature",
  "properties": {
    "iso:country":"GB",
    "wof:name":"NR5 0QN",
    "wof:placetype":"postalcode"
},
  "geometry": {"coordinates":[1.21540947679482,52.64893427814018],"type":"Point"}
}