{
  "type": "Feature",
  "properties": {
    "date:inception_lower": "1983-07-01",
    "date:inception_upper": "1983-07-01",
    "iso:country": "GB",
    "wof:name": "NR5 0QN",
    "wof:placetype": "postalcode"
  },
  "geometry": {"coordinates":[1.21541,52.648934],"type":"Point"}
}
