{
  "type": "Feature",
  "properties": {
    "date:inception_lower": "1994-12-01",
    "date:inception_upper": "1994-12-01",
    "iso:country": "GB",
    "wof:name": "DE11 7NH",
    "wof:placetype": "postalcode"
  },
  "geometry": {"coordinates":[-1.541985,52.777943],"type":"Point"}
}
