{
  "type": "Feature",
  "properties": {
    "iso:country": "GB",
    "wof:name": "DE11 7NH",
    "wof:placetype": "postalcode"
  },
  "geometry": {"coordinates":[-1.541985,52.777943],"type":"Point"}
}
