{
  "type": "Feature",
  "properties": {
    "iso:country": "GB",
    "wof:name": "GL51 8AY",
    "wof:placetype": "postalcode"
  },
  "geometry": {"coordinates":[-2.100725,51.904264],"type":"Point"}
}
