{
  "type": "Feature",
  "properties": {
    "iso:country": "GB",
    "wof:name": "M13 9AP",
    "wof:placetype": "postalcode"
  },
  "geometry": {"coordinates":[-2.212438,53.462437],"type":"Point"}
}
