{
  "type": "Feature",
  "properties": {
    "date:inception_lower": "1980-01-01",
    "date:inception_upper": "1980-01-01",
    "iso:country": "GB",
    "wof:name": "DH1 2SR",
    "wof:placetype": "postalcode"
  },
  "geometry": {"coordinates":[-1.485314,54.756912],"type":"Point"}
}
