{
  "type": "Feature",
  "properties": {
    "iso:country":"GB",
    "wof:name":"DH1 2SR",
    "wof:placetype":"postalcode"
},
  "geometry": {"coordinates":[-1.48530254248358,54.75690206607219],"type":"Point"}
}