{
  "type": "Feature",
  "properties": {
    "iso:country": "GB",
    "wof:name": "DH1 2SR",
    "wof:placetype": "postalcode"
  },
  "geometry": {"coordinates":[-1.490105,54.757723],"type":"Point"}
}
