{
  "type": "Feature",
  "properties": {
    "iso:country": "GB",
    "wof:name": "LL13 0HE",
    "wof:placetype": "postalcode"
  },
  "geometry": {"coordinates":[-2.932665,52.9733],"type":"Point"}
}
