{
  "type": "Feature",
  "properties": {
    "iso:country":"GB",
    "wof:name":"LL13 0HE",
    "wof:placetype":"postalcode"
},
  "geometry": {"coordinates":[-2.93266549409379,52.97329957148042],"type":"Point"}
}