{
  "type": "Feature",
  "properties": {
    "date:inception_lower": "2020-11-01",
    "date:inception_upper": "2020-11-01",
    "iso:country": "GB",
    "wof:name": "RH10 3WW",
    "wof:placetype": "postalcode"
  },
  "geometry": {"coordinates":[-0.15811,51.138201],"type":"Point"}
}
