{
  "type": "Feature",
  "properties": {
    "date:inception_lower": "1994-05-01",
    "date:inception_upper": "1994-05-01",
    "iso:country": "GB",
    "wof:name": "BB9 9RP",
    "wof:placetype": "postalcode"
  },
  "geometry": {"coordinates":[-2.203087,53.833828],"type":"Point"}
}
