{
  "type": "Feature",
  "properties": {
    "iso:country":"GB",
    "wof:name":"BB9 9RP",
    "wof:placetype":"postalcode"
},
  "geometry": {"coordinates":[-2.20308657423907,53.83382793250622],"type":"Point"}
}