{
  "type": "Feature",
  "properties": {
    "iso:country":"GB",
    "wof:name":"SO50 8GA",
    "wof:placetype":"postalcode"
},
  "geometry": {"coordinates":[-1.30367887431113,50.96778514988613],"type":"Point"}
}