{
  "type": "Feature",
  "properties": {
    "iso:country":"GB",
    "wof:name":"NE47 0LG",
    "wof:placetype":"postalcode"
},
  "geometry": {"coordinates":[-2.09613605212704,54.92041970059226],"type":"Point"}
}