{
  "type": "Feature",
  "properties": {
    "date:inception_lower": "1980-01-01",
    "date:inception_upper": "1980-01-01",
    "iso:country": "GB",
    "wof:name": "RG28 7JH",
    "wof:placetype": "postalcode"
  },
  "geometry": {"coordinates":[-1.329981,51.223857],"type":"Point"}
}
