{
  "type": "Feature",
  "properties": {
    "iso:country":"GB",
    "wof:name":"RG28 7JH",
    "wof:placetype":"postalcode"
},
  "geometry": {"coordinates":[-1.32998142420513,51.22385743566227],"type":"Point"}
}