{
  "type": "Feature",
  "properties": {
    "iso:country":"GB",
    "wof:name":"NN15 7BW",
    "wof:placetype":"postalcode"
},
  "geometry": {"coordinates":[-0.71942406540791,52.39555327245979],"type":"Point"}
}