{
  "type": "Feature",
  "properties": {
    "iso:country": "GB",
    "wof:name": "NN15 7BW",
    "wof:placetype": "postalcode"
  },
  "geometry": {"coordinates":[-0.719424,52.395553],"type":"Point"}
}
