{
  "type": "Feature",
  "properties": {
    "iso:country": "GB",
    "wof:name": "SP10 3SE",
    "wof:placetype": "postalcode"
  },
  "geometry": {"coordinates":[-1.515454,51.218599],"type":"Point"}
}
