{
  "type": "Feature",
  "properties": {
    "date:inception_lower": "1980-01-01",
    "date:inception_upper": "1980-01-01",
    "iso:country": "GB",
    "wof:name": "KY8 6EX",
    "wof:placetype": "postalcode"
  },
  "geometry": {"coordinates":[-2.925374,56.221662],"type":"Point"}
}
