{
  "type": "Feature",
  "properties": {
    "iso:country":"GB",
    "wof:name":"KY8 6EX",
    "wof:placetype":"postalcode"
},
  "geometry": {"coordinates":[-2.92537445716419,56.22166192926343],"type":"Point"}
}