{
  "type": "Feature",
  "properties": {
    "iso:country":"GB",
    "wof:name":"AL1 3AG",
    "wof:placetype":"postalcode"
},
  "geometry": {"coordinates":[-0.32871790891,51.74873482026584],"type":"Point"}
}