{
  "type": "Feature",
  "properties": {
    "iso:country":"GB",
    "wof:name":"HD1 6EN",
    "wof:placetype":"postalcode"
},
  "geometry": {"coordinates":[-1.78270182092396,53.6586268129342],"type":"Point"}
}