{
  "type": "Feature",
  "properties": {
    "iso:country": "GB",
    "wof:name": "YO26 7QX",
    "wof:placetype": "postalcode"
  },
  "geometry": {"coordinates":[-1.296438,53.966364],"type":"Point"}
}
