{
  "type": "Feature",
  "properties": {
    "iso:country":"GB",
    "wof:name":"S8 7SQ",
    "wof:placetype":"postalcode"
},
  "geometry": {"coordinates":[-1.48684008540772,53.32806208368733],"type":"Point"}
}