{
  "type": "Feature",
  "properties": {
    "iso:country": "GB",
    "wof:name": "EX36 4AB",
    "wof:placetype": "postalcode"
  },
  "geometry": {"coordinates":[-3.834852,51.01597],"type":"Point"}
}
