{
  "type": "Feature",
  "properties": {
    "iso:country":"GB",
    "wof:name":"RH1 1HG",
    "wof:placetype":"postalcode"
},
  "geometry": {"coordinates":[-0.16814957743682,51.23658355606768],"type":"Point"}
}