{
  "type": "Feature",
  "properties": {
    "iso:country":"GB",
    "wof:name":"DN11 8JX",
    "wof:placetype":"postalcode"
},
  "geometry": {"coordinates":[-1.0675536088529,53.41747987721848],"type":"Point"}
}