{
  "type": "Feature",
  "properties": {
    "date:inception_lower": "1980-01-01",
    "date:inception_upper": "1980-01-01",
    "iso:country": "GB",
    "wof:name": "DN11 8JX",
    "wof:placetype": "postalcode"
  },
  "geometry": {"coordinates":[-1.067498,53.417319],"type":"Point"}
}
