{
  "type": "Feature",
  "properties": {
    "iso:country":"GB",
    "wof:name":"B46 1SL",
    "wof:placetype":"postalcode"
},
  "geometry": {"coordinates":[-1.74134951833662,52.51639508126516],"type":"Point"}
}