{
  "type": "Feature",
  "properties": {
    "iso:country":"GB",
    "wof:name":"ME13 7GT",
    "wof:placetype":"postalcode"
},
  "geometry": {"coordinates":[0.88253042404985,51.32606096407516],"type":"Point"}
}