{
  "type": "Feature",
  "properties": {
    "iso:country":"GB",
    "wof:name":"BN15 0LE",
    "wof:placetype":"postalcode"
},
  "geometry": {"coordinates":[-0.33627784812232,50.83490535557797],"type":"Point"}
}