{
  "type": "Feature",
  "properties": {
    "iso:country": "GB",
    "wof:name": "CB11 3NU",
    "wof:placetype": "postalcode"
  },
  "geometry": {"coordinates":[0.208894,51.987647],"type":"Point"}
}
