{
  "type": "Feature",
  "properties": {
    "iso:country":"GB",
    "wof:name":"SK8 5LB",
    "wof:placetype":"postalcode"
},
  "geometry": {"coordinates":[-2.19817041756542,53.38717385627419],"type":"Point"}
}