{
  "type": "Feature",
  "properties": {
    "iso:country":"GB",
    "wof:name":"LU2 8AW",
    "wof:placetype":"postalcode"
},
  "geometry": {"coordinates":[-0.39184960742843,51.90196356361882],"type":"Point"}
}