{
  "type": "Feature",
  "properties": {
    "date:inception_lower":"1983-03-01",
    "date:inception_upper":"1983-03-31",
    "iso:country":"GB",
    "wof:name":"BA14 6LA",
    "wof:placetype":"postalcode"
},
  "geometry": {"coordinates":[-2.144698,51.34327],"type":"Point"}
}