{
  "type": "Feature",
  "properties": {
    "iso:country": "GB",
    "wof:name": "BA14 6LA",
    "wof:placetype": "postalcode"
  },
  "geometry": {"coordinates":[-2.144698,51.34327],"type":"Point"}
}
