{
  "type": "Feature",
  "properties": {
    "iso:country":"GB",
    "wof:name":"WS1 2DW",
    "wof:placetype":"postalcode"
},
  "geometry": {"coordinates":[-1.96490467794346,52.58351154133646],"type":"Point"}
}