{
  "type": "Feature",
  "properties": {
    "date:inception_lower": "1993-08-01",
    "date:inception_upper": "1993-08-01",
    "iso:country": "GB",
    "wof:name": "NN3 6DA",
    "wof:placetype": "postalcode"
  },
  "geometry": {"coordinates":[-0.870294,52.267374],"type":"Point"}
}
