{
  "type": "Feature",
  "properties": {
    "date:inception_lower": "2012-04-01",
    "date:inception_upper": "2012-04-01",
    "iso:country": "GB",
    "wof:name": "LS26 8FJ",
    "wof:placetype": "postalcode"
  },
  "geometry": {"coordinates":[-1.456518,53.754456],"type":"Point"}
}
