{
  "type": "Feature",
  "properties": {
    "iso:country": "GB",
    "wof:name": "LS26 8FJ",
    "wof:placetype": "postalcode"
  },
  "geometry": {"coordinates":[-1.456517,53.754501],"type":"Point"}
}
