{
  "type": "Feature",
  "properties": {
    "iso:country":"GB",
    "wof:name":"RG22 4QZ",
    "wof:placetype":"postalcode"
},
  "geometry": {"coordinates":[-1.1288289924983,51.23515834542714],"type":"Point"}
}