{
  "type": "Feature",
  "properties": {
    "date:inception_lower": "2022-10-01",
    "date:inception_upper": "2022-10-01",
    "iso:country": "GB",
    "wof:name": "GL15 5TW",
    "wof:placetype": "postalcode"
  },
  "geometry": {"coordinates":[-2.516708,51.731851],"type":"Point"}
}
