{
  "type": "Feature",
  "properties": {
    "iso:country":"GB",
    "wof:name":"WV11 1ST",
    "wof:placetype":"postalcode"
},
  "geometry": {"coordinates":[-2.08244522585228,52.60013687261889],"type":"Point"}
}