{
  "type": "Feature",
  "properties": {
    "iso:country":"GB",
    "wof:name":"OX11 9DL",
    "wof:placetype":"postalcode"
},
  "geometry": {"coordinates":[-1.19808413892747,51.57307067909631],"type":"Point"}
}