{
  "type": "Feature",
  "properties": {
    "iso:country": "GB",
    "wof:name": "CV36 5NJ",
    "wof:placetype": "postalcode"
  },
  "geometry": {"coordinates":[-1.640633,52.007765],"type":"Point"}
}
