{
  "type": "Feature",
  "properties": {
    "iso:country":"GB",
    "wof:name":"CV36 5NJ",
    "wof:placetype":"postalcode"
},
  "geometry": {"coordinates":[-1.64063290273195,52.00776481341395],"type":"Point"}
}