{
  "type": "Feature",
  "properties": {
    "date:inception_lower": "2023-06-01",
    "date:inception_upper": "2023-06-01",
    "iso:country": "GB",
    "wof:name": "CO10 1AS",
    "wof:placetype": "postalcode"
  },
  "geometry": {"coordinates":[0.744004,52.052684],"type":"Point"}
}
