{
  "type": "Feature",
  "properties": {
    "iso:country": "GB",
    "wof:name": "LS22 6XH",
    "wof:placetype": "postalcode"
  },
  "geometry": {"coordinates":[-1.405255,53.933453],"type":"Point"}
}
