{
  "type": "Feature",
  "properties": {
    "iso:country":"GB",
    "wof:name":"LS9 6NF",
    "wof:placetype":"postalcode"
},
  "geometry": {"coordinates":[-1.50569870687817,53.80612690149611],"type":"Point"}
}