{
  "type": "Feature",
  "properties": {
    "date:inception_lower": "1980-01-01",
    "date:inception_upper": "1980-01-01",
    "iso:country": "GB",
    "wof:name": "LS9 6NF",
    "wof:placetype": "postalcode"
  },
  "geometry": {"coordinates":[-1.505699,53.806127],"type":"Point"}
}
