{
  "type": "Feature",
  "properties": {
    "date:inception_lower":"1980-01-01",
    "date:inception_upper":"1980-01-31",
    "iso:country":"GB",
    "wof:name":"DA9 9DY",
    "wof:placetype":"postalcode"
},
  "geometry": {"coordinates":[0.260525,51.441265],"type":"Point"}
}