{
  "type": "Feature",
  "properties": {
    "iso:country":"GB",
    "wof:name":"KY10 2DD",
    "wof:placetype":"postalcode"
},
  "geometry": {"coordinates":[-2.77126023518076,56.20756186528865],"type":"Point"}
}