{
  "type": "Feature",
  "properties": {
    "date:inception_lower": "2010-02-01",
    "date:inception_upper": "2010-02-01",
    "iso:country": "GB",
    "wof:name": "DY10 1QT",
    "wof:placetype": "postalcode"
  },
  "geometry": {"coordinates":[-2.240893,52.384197],"type":"Point"}
}
