{
  "type": "Feature",
  "properties": {
    "iso:country":"GB",
    "wof:name":"NE66 3JE",
    "wof:placetype":"postalcode"
},
  "geometry": {"coordinates":[-1.76497294898952,55.43744250825157],"type":"Point"}
}