{
  "type": "Feature",
  "properties": {
    "iso:country":"GB",
    "wof:name":"RH12 5AA",
    "wof:placetype":"postalcode"
},
  "geometry": {"coordinates":[-0.32069916551564,51.07467206679777],"type":"Point"}
}