{
  "type": "Feature",
  "properties": {
    "iso:country": "GB",
    "wof:name": "TS4 2QY",
    "wof:placetype": "postalcode"
  },
  "geometry": {"coordinates":[-1.220933,54.560431],"type":"Point"}
}
