{
  "type": "Feature",
  "properties": {
    "date:inception_lower":"1983-07-01",
    "date:inception_upper":"1983-07-31",
    "iso:country":"GB",
    "wof:name":"TS4 2QY",
    "wof:placetype":"postalcode"
},
  "geometry": {"coordinates":[-1.220933,54.560431],"type":"Point"}
}