{
  "type": "Feature",
  "properties": {
    "iso:country":"GB",
    "wof:name":"TS4 2QY",
    "wof:placetype":"postalcode"
},
  "geometry": {"coordinates":[-1.22093265949189,54.56043124375329],"type":"Point"}
}