{
  "type": "Feature",
  "properties": {
    "iso:country":"GB",
    "wof:name":"EH16 5TQ",
    "wof:placetype":"postalcode"
},
  "geometry": {"coordinates":[-3.15448326880018,55.92115528571906],"type":"Point"}
}