{
  "type": "Feature",
  "properties": {
    "iso:country": "GB",
    "wof:name": "CV6 6GT",
    "wof:placetype": "postalcode"
  },
  "geometry": {"coordinates":[-1.501181,52.443687],"type":"Point"}
}
