{
  "type": "Feature",
  "properties": {
    "date:inception_lower": "2019-11-01",
    "date:inception_upper": "2019-11-01",
    "iso:country": "GB",
    "wof:name": "L3 5AF",
    "wof:placetype": "postalcode"
  },
  "geometry": {"coordinates":[-2.978317,53.40686],"type":"Point"}
}
