{
  "type": "Feature",
  "properties": {
    "iso:country":"GB",
    "wof:name":"N17 6YE",
    "wof:placetype":"postalcode"
},
  "geometry": {"coordinates":[-0.07655543634166,51.59147740613787],"type":"Point"}
}