{
  "type": "Feature",
  "properties": {
    "iso:country":"GB",
    "wof:name":"SE2 9JS",
    "wof:placetype":"postalcode"
},
  "geometry": {"coordinates":[0.1142102738557,51.49333981451546],"type":"Point"}
}