{
  "type": "Feature",
  "properties": {
    "iso:country":"GB",
    "wof:name":"DT11 0HE",
    "wof:placetype":"postalcode"
},
  "geometry": {"coordinates":[-2.33975289150136,50.85862269318072],"type":"Point"}
}