{
  "type": "Feature",
  "properties": {
    "iso:country": "GB",
    "wof:name": "PE15 8DX",
    "wof:placetype": "postalcode"
  },
  "geometry": {"coordinates":[0.074541,52.553325],"type":"Point"}
}
