{
  "type": "Feature",
  "properties": {
    "date:inception_lower": "1998-12-01",
    "date:inception_upper": "1998-12-01",
    "iso:country": "GB",
    "wof:name": "KY13 0QE",
    "wof:placetype": "postalcode"
  },
  "geometry": {"coordinates":[-3.595711,56.189112],"type":"Point"}
}
