{
  "type": "Feature",
  "properties": {
    "iso:country":"GB",
    "wof:name":"KY13 0QE",
    "wof:placetype":"postalcode"
},
  "geometry": {"coordinates":[-3.59571092482887,56.18911230973281],"type":"Point"}
}