{
  "type": "Feature",
  "properties": {
    "iso:country":"GB",
    "wof:name":"TS14 8HW",
    "wof:placetype":"postalcode"
},
  "geometry": {"coordinates":[-1.08527549795711,54.53163968584341],"type":"Point"}
}