{
  "type": "Feature",
  "properties": {
    "iso:country":"GB",
    "wof:name":"SW16 4BT",
    "wof:placetype":"postalcode"
},
  "geometry": {"coordinates":[-0.12345202020153,51.41210702383386],"type":"Point"}
}