{
  "type": "Feature",
  "properties": {
    "date:inception_lower": "1980-01-01",
    "date:inception_upper": "1980-01-01",
    "iso:country": "GB",
    "wof:name": "GU22 7EL",
    "wof:placetype": "postalcode"
  },
  "geometry": {"coordinates":[-0.538655,51.31557],"type":"Point"}
}
