{
  "type": "Feature",
  "properties": {
    "date:inception_lower":"1980-01-01",
    "date:inception_upper":"1980-01-31",
    "iso:country":"GB",
    "wof:name":"LL11 5DD",
    "wof:placetype":"postalcode"
},
  "geometry": {"coordinates":[-3.056002,53.079594],"type":"Point"}
}