{
  "type": "Feature",
  "properties": {
    "iso:country":"GB",
    "wof:name":"LL11 5DD",
    "wof:placetype":"postalcode"
},
  "geometry": {"coordinates":[-3.05600202626478,53.07959383766926],"type":"Point"}
}