{
  "type": "Feature",
  "properties": {
    "iso:country": "GB",
    "wof:name": "LL11 5DD",
    "wof:placetype": "postalcode"
  },
  "geometry": {"coordinates":[-3.056002,53.079594],"type":"Point"}
}
