{
  "type": "Feature",
  "properties": {
    "iso:country":"GB",
    "wof:name":"SW11 5PH",
    "wof:placetype":"postalcode"
},
  "geometry": {"coordinates":[-0.15579925948154,51.46482251988738],"type":"Point"}
}