{
  "type": "Feature",
  "properties": {
    "iso:country":"GB",
    "wof:name":"M46 9EW",
    "wof:placetype":"postalcode"
},
  "geometry": {"coordinates":[-2.48106605437172,53.52223972049771],"type":"Point"}
}