{
  "type": "Feature",
  "properties": {
    "iso:country":"GB",
    "wof:name":"CO5 0EY",
    "wof:placetype":"postalcode"
},
  "geometry": {"coordinates":[0.75918528059853,51.81464031118856],"type":"Point"}
}