{
  "type": "Feature",
  "properties": {
    "iso:country": "GB",
    "wof:name": "CO5 0EY",
    "wof:placetype": "postalcode"
  },
  "geometry": {"coordinates":[0.759185,51.81464],"type":"Point"}
}
