{
  "type": "Feature",
  "properties": {
    "date:inception_lower": "2021-10-01",
    "date:inception_upper": "2021-10-01",
    "iso:country": "GB",
    "wof:name": "TF7 4FB",
    "wof:placetype": "postalcode"
  },
  "geometry": {"coordinates":[-2.43439,52.644107],"type":"Point"}
}
