{
  "type": "Feature",
  "properties": {
    "iso:country":"GB",
    "wof:name":"PA20 0HZ",
    "wof:placetype":"postalcode"
},
  "geometry": {"coordinates":[-5.05933526908169,55.8359860970714],"type":"Point"}
}