{
  "type": "Feature",
  "properties": {
    "date:inception_lower": "1996-06-01",
    "date:inception_upper": "1996-06-01",
    "iso:country": "GB",
    "wof:name": "PA20 0HZ",
    "wof:placetype": "postalcode"
  },
  "geometry": {"coordinates":[-5.059335,55.835986],"type":"Point"}
}
