{
  "type": "Feature",
  "properties": {
    "iso:country":"GB",
    "wof:name":"LA19 5UY",
    "wof:placetype":"postalcode"
},
  "geometry": {"coordinates":[-3.39443288439225,54.29138372200737],"type":"Point"}
}