{
  "type": "Feature",
  "properties": {
    "iso:country": "GB",
    "wof:name": "SO15 5JH",
    "wof:placetype": "postalcode"
  },
  "geometry": {"coordinates":[-1.42427,50.926456],"type":"Point"}
}
