{
  "type": "Feature",
  "properties": {
    "date:inception_lower": "2000-12-01",
    "date:inception_upper": "2000-12-01",
    "iso:country": "GB",
    "wof:name": "HR7 4UT",
    "wof:placetype": "postalcode"
  },
  "geometry": {"coordinates":[-2.517281,52.190099],"type":"Point"}
}
