{
  "type": "Feature",
  "properties": {
    "iso:country":"GB",
    "wof:name":"SN3 1QX",
    "wof:placetype":"postalcode"
},
  "geometry": {"coordinates":[-1.77137817893618,51.55000577714567],"type":"Point"}
}