{
  "type": "Feature",
  "properties": {
    "iso:country":"GB",
    "wof:name":"SK23 0HP",
    "wof:placetype":"postalcode"
},
  "geometry": {"coordinates":[-1.91389184176404,53.32353357780462],"type":"Point"}
}