{
  "type": "Feature",
  "properties": {
    "iso:country":"GB",
    "wof:name":"BH10 4JA",
    "wof:placetype":"postalcode"
},
  "geometry": {"coordinates":[-1.89954129426694,50.74665015509321],"type":"Point"}
}