{
  "type": "Feature",
  "properties": {
    "date:inception_lower":"1980-01-01",
    "date:inception_upper":"1980-01-31",
    "iso:country":"GB",
    "wof:name":"M30 7AQ",
    "wof:placetype":"postalcode"
},
  "geometry": {"coordinates":[-2.357582,53.475933],"type":"Point"}
}