{
  "type": "Feature",
  "properties": {
    "iso:country": "GB",
    "wof:name": "M30 7AQ",
    "wof:placetype": "postalcode"
  },
  "geometry": {"coordinates":[-2.357582,53.475933],"type":"Point"}
}
