{
  "type": "Feature",
  "properties": {
    "iso:country":"GB",
    "wof:name":"M30 7AQ",
    "wof:placetype":"postalcode"
},
  "geometry": {"coordinates":[-2.35758250103659,53.47593306267257],"type":"Point"}
}