{
  "type": "Feature",
  "properties": {
    "iso:country": "GB",
    "wof:name": "BL5 2GG",
    "wof:placetype": "postalcode"
  },
  "geometry": {"coordinates":[-2.532642,53.541984],"type":"Point"}
}
