{
  "type": "Feature",
  "properties": {
    "iso:country":"GB",
    "wof:name":"BL5 2GG",
    "wof:placetype":"postalcode"
},
  "geometry": {"coordinates":[-2.5326419615878,53.54198436863316],"type":"Point"}
}