{
  "type": "Feature",
  "properties": {
    "date:inception_lower":"2009-07-01",
    "date:inception_upper":"2009-07-31",
    "iso:country":"GB",
    "wof:name":"BL5 2GG",
    "wof:placetype":"postalcode"
},
  "geometry": {"coordinates":[-2.532642,53.541984],"type":"Point"}
}