{
  "type": "Feature",
  "properties": {
    "iso:country": "GB",
    "wof:name": "PO8 9WJ",
    "wof:placetype": "postalcode"
  },
  "geometry": {"coordinates":[-1.027663,50.90998],"type":"Point"}
}
