{
  "type": "Feature",
  "properties": {
    "iso:country":"GB",
    "wof:name":"BB3 2TG",
    "wof:placetype":"postalcode"
},
  "geometry": {"coordinates":[-2.47159808815015,53.69480847643639],"type":"Point"}
}