{
  "type": "Feature",
  "properties": {
    "iso:country": "GB",
    "wof:name": "BB3 2TG",
    "wof:placetype": "postalcode"
  },
  "geometry": {"coordinates":[-2.471598,53.694808],"type":"Point"}
}
