{
  "type": "Feature",
  "properties": {
    "date:inception_lower": "1989-10-01",
    "date:inception_upper": "1989-10-01",
    "iso:country": "GB",
    "wof:name": "DD3 9TH",
    "wof:placetype": "postalcode"
  },
  "geometry": {"coordinates":[-2.998236,56.494778],"type":"Point"}
}
