{
  "type": "Feature",
  "properties": {
    "iso:country":"GB",
    "wof:name":"DD3 9TH",
    "wof:placetype":"postalcode"
},
  "geometry": {"coordinates":[-2.99823606829176,56.49477764077195],"type":"Point"}
}