{
  "type": "Feature",
  "properties": {
    "iso:country": "GB",
    "wof:name": "BN17 5TG",
    "wof:placetype": "postalcode"
  },
  "geometry": {"coordinates":[-0.58001,50.799573],"type":"Point"}
}
