{
  "type": "Feature",
  "properties": {
    "date:inception_lower": "1980-01-01",
    "date:inception_upper": "1980-01-01",
    "iso:country": "GB",
    "wof:name": "EH16 4SL",
    "wof:placetype": "postalcode"
  },
  "geometry": {"coordinates":[-3.111607,55.911329],"type":"Point"}
}
