{
  "type": "Feature",
  "properties": {
    "iso:country":"GB",
    "wof:name":"EH16 4SL",
    "wof:placetype":"postalcode"
},
  "geometry": {"coordinates":[-3.11118061764358,55.91104965464501],"type":"Point"}
}