{
  "type": "Feature",
  "properties": {
    "iso:country": "GB",
    "wof:name": "CM13 3BG",
    "wof:placetype": "postalcode"
  },
  "geometry": {"coordinates":[0.299105,51.600942],"type":"Point"}
}
