{
  "type": "Feature",
  "properties": {
    "date:inception_lower": "1980-01-01",
    "date:inception_upper": "1980-01-01",
    "iso:country": "GB",
    "wof:name": "CM13 3BG",
    "wof:placetype": "postalcode"
  },
  "geometry": {"coordinates":[0.299105,51.600942],"type":"Point"}
}
