{
  "type": "Feature",
  "properties": {
    "iso:country":"GB",
    "wof:name":"CM13 3BG",
    "wof:placetype":"postalcode"
},
  "geometry": {"coordinates":[0.29910478894477,51.60094191042268],"type":"Point"}
}