{
  "type": "Feature",
  "properties": {
    "date:inception_lower": "1980-01-01",
    "date:inception_upper": "1980-01-01",
    "iso:country": "GB",
    "wof:name": "TA19 0LN",
    "wof:placetype": "postalcode"
  },
  "geometry": {"coordinates":[-2.851814,50.951185],"type":"Point"}
}
