{
  "type": "Feature",
  "properties": {
    "iso:country": "GB",
    "wof:name": "TA19 0LN",
    "wof:placetype": "postalcode"
  },
  "geometry": {"coordinates":[-2.851814,50.951185],"type":"Point"}
}
