{
  "type": "Feature",
  "properties": {
    "iso:country":"GB",
    "wof:name":"WF4 1SZ",
    "wof:placetype":"postalcode"
},
  "geometry": {"coordinates":[-1.42064264940742,53.65319873996783],"type":"Point"}
}