{
  "type": "Feature",
  "properties": {
    "date:inception_lower": "1985-04-01",
    "date:inception_upper": "1985-04-01",
    "iso:country": "GB",
    "wof:name": "WF4 1SZ",
    "wof:placetype": "postalcode"
  },
  "geometry": {"coordinates":[-1.420643,53.653199],"type":"Point"}
}
