{
  "type": "Feature",
  "properties": {
    "iso:country":"GB",
    "wof:name":"CT10 3DG",
    "wof:placetype":"postalcode"
},
  "geometry": {"coordinates":[1.42622059971946,51.37108865013828],"type":"Point"}
}