{
  "type": "Feature",
  "properties": {
    "date:inception_lower":"2001-06-01",
    "date:inception_upper":"2001-06-30",
    "iso:country":"GB",
    "wof:name":"DN4 0BF",
    "wof:placetype":"postalcode"
},
  "geometry": {"coordinates":[-1.141313,53.521316],"type":"Point"}
}