{
  "type": "Feature",
  "properties": {
    "iso:country":"GB",
    "wof:name":"DN4 0BF",
    "wof:placetype":"postalcode"
},
  "geometry": {"coordinates":[-1.14250207516641,53.52129506091264],"type":"Point"}
}