{
  "type": "Feature",
  "properties": {
    "date:inception_lower": "2001-06-01",
    "date:inception_upper": "2001-06-01",
    "iso:country": "GB",
    "wof:name": "DN4 0BF",
    "wof:placetype": "postalcode"
  },
  "geometry": {"coordinates":[-1.142504,53.521315],"type":"Point"}
}
