{
  "type": "Feature",
  "properties": {
    "iso:country":"GB",
    "wof:name":"HU8 7HJ",
    "wof:placetype":"postalcode"
},
  "geometry": {"coordinates":[-0.32719030760024,53.75075089984783],"type":"Point"}
}