{
  "type": "Feature",
  "properties": {
    "iso:country":"GB",
    "wof:name":"M9 6RF",
    "wof:placetype":"postalcode"
},
  "geometry": {"coordinates":[-2.21110721456015,53.53101235956973],"type":"Point"}
}