{
  "type": "Feature",
  "properties": {
    "iso:country": "GB",
    "wof:name": "TW12 1NB",
    "wof:placetype": "postalcode"
  },
  "geometry": {"coordinates":[-0.358671,51.423407],"type":"Point"}
}
