{
  "type": "Feature",
  "properties": {
    "iso:country":"GB",
    "wof:name":"SA6 6EH",
    "wof:placetype":"postalcode"
},
  "geometry": {"coordinates":[-3.93073288322834,51.67397142931335],"type":"Point"}
}