{
  "type": "Feature",
  "properties": {
    "iso:country": "GB",
    "wof:name": "SA6 6EH",
    "wof:placetype": "postalcode"
  },
  "geometry": {"coordinates":[-3.930733,51.673971],"type":"Point"}
}
