{
  "type": "Feature",
  "properties": {
    "iso:country":"GB",
    "wof:name":"W1G 8PD",
    "wof:placetype":"postalcode"
},
  "geometry": {"coordinates":[-0.1485749427511,51.52021952413776],"type":"Point"}
}