{
  "type": "Feature",
  "properties": {
    "date:inception_lower": "1990-07-01",
    "date:inception_upper": "1990-07-01",
    "iso:country": "GB",
    "wof:name": "TS10 2JP",
    "wof:placetype": "postalcode"
  },
  "geometry": {"coordinates":[-1.051687,54.601311],"type":"Point"}
}
