{
  "type": "Feature",
  "properties": {
    "date:inception_lower":"1999-06-01",
    "date:inception_upper":"1999-06-30",
    "iso:country":"GB",
    "wof:name":"CF14 3BF",
    "wof:placetype":"postalcode"
},
  "geometry": {"coordinates":[-3.196894,51.50283],"type":"Point"}
}