{
  "type": "Feature",
  "properties": {
    "date:inception_lower": "2009-04-01",
    "date:inception_upper": "2009-04-01",
    "iso:country": "GB",
    "wof:name": "EC1V 7EX",
    "wof:placetype": "postalcode"
  },
  "geometry": {"coordinates":[-0.09974,51.525041],"type":"Point"}
}
