{
  "type": "Feature",
  "properties": {
    "iso:country": "GB",
    "wof:name": "TW4 5HA",
    "wof:placetype": "postalcode"
  },
  "geometry": {"coordinates":[-0.377987,51.464258],"type":"Point"}
}
