{
  "type": "Feature",
  "properties": {
    "date:inception_lower": "2005-01-01",
    "date:inception_upper": "2005-01-01",
    "iso:country": "GB",
    "wof:name": "CF45 3SQ",
    "wof:placetype": "postalcode"
  },
  "geometry": {"coordinates":[-3.361281,51.669195],"type":"Point"}
}
