{
  "type": "Feature",
  "properties": {
    "iso:country":"GB",
    "wof:name":"NW5 2BB",
    "wof:placetype":"postalcode"
},
  "geometry": {"coordinates":[-0.13382472765741,51.5495890333491],"type":"Point"}
}