{
  "type": "Feature",
  "properties": {
    "iso:country": "GB",
    "wof:name": "NW5 2BB",
    "wof:placetype": "postalcode"
  },
  "geometry": {"coordinates":[-0.133825,51.549589],"type":"Point"}
}
