{
  "type": "Feature",
  "properties": {
    "iso:country": "GB",
    "wof:name": "GL1 2DA",
    "wof:placetype": "postalcode"
  },
  "geometry": {"coordinates":[-2.243704,51.868675],"type":"Point"}
}
