{
  "type": "Feature",
  "properties": {
    "iso:country":"GB",
    "wof:name":"GL1 2DA",
    "wof:placetype":"postalcode"
},
  "geometry": {"coordinates":[-2.24370359462613,51.8686750121748],"type":"Point"}
}