{
  "type": "Feature",
  "properties": {
    "iso:country": "GB",
    "wof:name": "PL1 5LG",
    "wof:placetype": "postalcode"
  },
  "geometry": {"coordinates":[-4.154988,50.377673],"type":"Point"}
}
