{
  "type": "Feature",
  "properties": {
    "iso:country":"GB",
    "wof:name":"PL1 5LG",
    "wof:placetype":"postalcode"
},
  "geometry": {"coordinates":[-4.15498772293128,50.37767286421252],"type":"Point"}
}