{
  "type": "Feature",
  "properties": {
    "date:inception_lower": "1980-01-01",
    "date:inception_upper": "1980-01-01",
    "iso:country": "GB",
    "wof:name": "SG19 1PR",
    "wof:placetype": "postalcode"
  },
  "geometry": {"coordinates":[-0.304356,52.109045],"type":"Point"}
}
