{
  "type": "Feature",
  "properties": {
    "iso:country":"GB",
    "wof:name":"S64 0LU",
    "wof:placetype":"postalcode"
},
  "geometry": {"coordinates":[-1.27247489717016,53.49388712418364],"type":"Point"}
}