{
  "type": "Feature",
  "properties": {
    "iso:country": "GB",
    "wof:name": "TA24 7NB",
    "wof:placetype": "postalcode"
  },
  "geometry": {"coordinates":[-3.655298,51.123665],"type":"Point"}
}
