{
  "type": "Feature",
  "properties": {
    "iso:country":"GB",
    "wof:name":"NE6 5UH",
    "wof:placetype":"postalcode"
},
  "geometry": {"coordinates":[-1.56706779093698,54.99249491776092],"type":"Point"}
}