{
  "type": "Feature",
  "properties": {
    "iso:country":"GB",
    "wof:name":"SE2 0LE",
    "wof:placetype":"postalcode"
},
  "geometry": {"coordinates":[0.11718026624709,51.48499481358815],"type":"Point"}
}