{
  "type": "Feature",
  "properties": {
    "date:inception_lower": "1999-06-01",
    "date:inception_upper": "1999-06-01",
    "iso:country": "GB",
    "wof:name": "CH60 6RZ",
    "wof:placetype": "postalcode"
  },
  "geometry": {"coordinates":[-3.107197,53.332403],"type":"Point"}
}
