{
  "type": "Feature",
  "properties": {
    "date:inception_lower": "2022-07-01",
    "date:inception_upper": "2022-07-01",
    "iso:country": "GB",
    "wof:name": "TF1 6BJ",
    "wof:placetype": "postalcode"
  },
  "geometry": {"coordinates":[-2.486832,52.715211],"type":"Point"}
}
