{
  "type": "Feature",
  "properties": {
    "date:inception_lower": "1980-01-01",
    "date:inception_upper": "1980-01-01",
    "iso:country": "GB",
    "wof:name": "GU30 7HP",
    "wof:placetype": "postalcode"
  },
  "geometry": {"coordinates":[-0.800559,51.068998],"type":"Point"}
}
