{
  "type": "Feature",
  "properties": {
    "iso:country":"GB",
    "wof:name":"NN16 9ED",
    "wof:placetype":"postalcode"
},
  "geometry": {"coordinates":[-0.72817748374191,52.40496206690205],"type":"Point"}
}