{
  "type": "Feature",
  "properties": {
    "iso:country": "GB",
    "wof:name": "NG31 8XJ",
    "wof:placetype": "postalcode"
  },
  "geometry": {"coordinates":[-0.666258,52.921272],"type":"Point"}
}
