{
  "type": "Feature",
  "properties": {
    "date:inception_lower": "2019-03-01",
    "date:inception_upper": "2019-03-01",
    "iso:country": "GB",
    "wof:name": "NG31 8XJ",
    "wof:placetype": "postalcode"
  },
  "geometry": {"coordinates":[-0.666237,52.92147],"type":"Point"}
}
