{
  "type": "Feature",
  "properties": {
    "iso:country": "GB",
    "wof:name": "NG31 8XJ",
    "wof:placetype": "postalcode"
  },
  "geometry": {"coordinates":[-0.666675,52.921277],"type":"Point"}
}
