{
  "type": "Feature",
  "properties": {
    "iso:country": "GB",
    "wof:name": "PL20 7DX",
    "wof:placetype": "postalcode"
  },
  "geometry": {"coordinates":[-4.184931,50.482519],"type":"Point"}
}
