{
  "type": "Feature",
  "properties": {
    "iso:country":"GB",
    "wof:name":"PL20 7DX",
    "wof:placetype":"postalcode"
},
  "geometry": {"coordinates":[-4.18493099028094,50.48251873146837],"type":"Point"}
}