{
  "type": "Feature",
  "properties": {
    "iso:country":"GB",
    "wof:name":"B29 6SN",
    "wof:placetype":"postalcode"
},
  "geometry": {"coordinates":[-1.9424191025869,52.44240617848146],"type":"Point"}
}