{
  "type": "Feature",
  "properties": {
    "iso:country": "GB",
    "wof:name": "B29 6SN",
    "wof:placetype": "postalcode"
  },
  "geometry": {"coordinates":[-1.942413,52.442421],"type":"Point"}
}
