{
  "type": "Feature",
  "properties": {
    "iso:country": "GB",
    "wof:name": "OX7 5NT",
    "wof:placetype": "postalcode"
  },
  "geometry": {"coordinates":[-1.546546,51.943021],"type":"Point"}
}
