{
  "type": "Feature",
  "properties": {
    "iso:country": "GB",
    "wof:name": "CM4 0LS",
    "wof:placetype": "postalcode"
  },
  "geometry": {"coordinates":[0.343214,51.719343],"type":"Point"}
}
