{
  "type": "Feature",
  "properties": {
    "iso:country":"GB",
    "wof:name":"HP1 1NB",
    "wof:placetype":"postalcode"
},
  "geometry": {"coordinates":[-0.49151336933,51.7457846526185],"type":"Point"}
}