{
  "type": "Feature",
  "properties": {
    "date:inception_lower": "1980-01-01",
    "date:inception_upper": "1980-01-01",
    "iso:country": "GB",
    "wof:name": "HP1 1NB",
    "wof:placetype": "postalcode"
  },
  "geometry": {"coordinates":[-0.491513,51.745785],"type":"Point"}
}
