{
  "type": "Feature",
  "properties": {
    "iso:country":"GB",
    "wof:name":"CF5 4RP",
    "wof:placetype":"postalcode"
},
  "geometry": {"coordinates":[-3.26399918346637,51.47344160769384],"type":"Point"}
}