{
  "type": "Feature",
  "properties": {
    "iso:country":"GB",
    "wof:name":"CF72 9UW",
    "wof:placetype":"postalcode"
},
  "geometry": {"coordinates":[-3.39749901978123,51.52556383392128],"type":"Point"}
}