{
  "type": "Feature",
  "properties": {
    "date:inception_lower": "1980-01-01",
    "date:inception_upper": "1980-01-01",
    "iso:country": "GB",
    "wof:name": "IP17 3RF",
    "wof:placetype": "postalcode"
  },
  "geometry": {"coordinates":[1.571761,52.310443],"type":"Point"}
}
