{
  "type": "Feature",
  "properties": {
    "iso:country": "GB",
    "wof:name": "IP17 3RF",
    "wof:placetype": "postalcode"
  },
  "geometry": {"coordinates":[1.571761,52.310443],"type":"Point"}
}
