{
  "type": "Feature",
  "properties": {
    "iso:country":"GB",
    "wof:name":"NP20 5NE",
    "wof:placetype":"postalcode"
},
  "geometry": {"coordinates":[-2.99621852675767,51.59827429742071],"type":"Point"}
}