{
  "type": "Feature",
  "properties": {
    "date:inception_lower": "1999-06-01",
    "date:inception_upper": "1999-06-01",
    "iso:country": "GB",
    "wof:name": "NP20 5NE",
    "wof:placetype": "postalcode"
  },
  "geometry": {"coordinates":[-2.996218,51.598274],"type":"Point"}
}
