{
  "type": "Feature",
  "properties": {
    "iso:country": "GB",
    "wof:name": "ML6 0LD",
    "wof:placetype": "postalcode"
  },
  "geometry": {"coordinates":[-3.989645,55.873763],"type":"Point"}
}
