{
  "type": "Feature",
  "properties": {
    "iso:country": "GB",
    "wof:name": "CF48 1PH",
    "wof:placetype": "postalcode"
  },
  "geometry": {"coordinates":[-3.414092,51.751798],"type":"Point"}
}
