{
  "type": "Feature",
  "properties": {
    "iso:country":"GB",
    "wof:name":"CF48 1PH",
    "wof:placetype":"postalcode"
},
  "geometry": {"coordinates":[-3.41409219647259,51.75179837970504],"type":"Point"}
}