{
  "type": "Feature",
  "properties": {
    "iso:country": "GB",
    "wof:name": "HP17 8RJ",
    "wof:placetype": "postalcode"
  },
  "geometry": {"coordinates":[-0.931639,51.769842],"type":"Point"}
}
