{
  "type": "Feature",
  "properties": {
    "date:inception_lower":"1994-05-01",
    "date:inception_upper":"1994-05-31",
    "iso:country":"GB",
    "wof:name":"HP17 8RJ",
    "wof:placetype":"postalcode"
},
  "geometry": {"coordinates":[-0.931639,51.769842],"type":"Point"}
}