{
  "type": "Feature",
  "properties": {
    "iso:country":"GB",
    "wof:name":"HD9 7EH",
    "wof:placetype":"postalcode"
},
  "geometry": {"coordinates":[-1.75326928037555,53.57321738599988],"type":"Point"}
}