{
  "type": "Feature",
  "properties": {
    "iso:country": "GB",
    "wof:name": "HD9 7EH",
    "wof:placetype": "postalcode"
  },
  "geometry": {"coordinates":[-1.753269,53.573217],"type":"Point"}
}
