{
  "type": "Feature",
  "properties": {
    "iso:country":"GB",
    "wof:name":"SW20 9ED",
    "wof:placetype":"postalcode"
},
  "geometry": {"coordinates":[-0.22756650882904,51.40051781391382],"type":"Point"}
}