{
  "type": "Feature",
  "properties": {
    "iso:country":"GB",
    "wof:name":"NP23 8WQ",
    "wof:placetype":"postalcode"
},
  "geometry": {"coordinates":[-3.19835102867333,51.75176894154951],"type":"Point"}
}