{
  "type": "Feature",
  "properties": {
    "iso:country":"GB",
    "wof:name":"NW10 3UN",
    "wof:placetype":"postalcode"
},
  "geometry": {"coordinates":[-0.2419621013113,51.54010869850658],"type":"Point"}
}