{
  "type": "Feature",
  "properties": {
    "iso:country":"GB",
    "wof:name":"N20 0UD",
    "wof:placetype":"postalcode"
},
  "geometry": {"coordinates":[-0.16531959267708,51.62642203426849],"type":"Point"}
}