{
  "type": "Feature",
  "properties": {
    "date:inception_lower": "1984-02-01",
    "date:inception_upper": "1984-02-01",
    "iso:country": "GB",
    "wof:name": "TR13 9HD",
    "wof:placetype": "postalcode"
  },
  "geometry": {"coordinates":[-5.314777,50.08562],"type":"Point"}
}
