{
  "type": "Feature",
  "properties": {
    "iso:country": "GB",
    "wof:name": "PL31 2GT",
    "wof:placetype": "postalcode"
  },
  "geometry": {"coordinates":[-4.707085,50.475909],"type":"Point"}
}
