{
  "type": "Feature",
  "properties": {
    "date:inception_lower": "2012-11-01",
    "date:inception_upper": "2012-11-01",
    "iso:country": "GB",
    "wof:name": "NN8 4DF",
    "wof:placetype": "postalcode"
  },
  "geometry": {"coordinates":[-0.697208,52.305381],"type":"Point"}
}
