{
  "type": "Feature",
  "properties": {
    "iso:country":"GB",
    "wof:name":"NN8 4DF",
    "wof:placetype":"postalcode"
},
  "geometry": {"coordinates":[-0.69678064266783,52.30553326237473],"type":"Point"}
}