{
  "type": "Feature",
  "properties": {
    "date:inception_lower": "2008-03-01",
    "date:inception_upper": "2008-03-01",
    "iso:country": "GB",
    "wof:name": "CB22 5AD",
    "wof:placetype": "postalcode"
  },
  "geometry": {"coordinates":[0.14879,52.154217],"type":"Point"}
}
