{
  "type": "Feature",
  "properties": {
    "iso:country":"GB",
    "wof:name":"CB22 5AD",
    "wof:placetype":"postalcode"
},
  "geometry": {"coordinates":[0.14876174696896,52.15420553914221],"type":"Point"}
}