{
  "type": "Feature",
  "properties": {
    "iso:country": "GB",
    "wof:name": "CB22 5AD",
    "wof:placetype": "postalcode"
  },
  "geometry": {"coordinates":[0.14864,52.154121],"type":"Point"}
}
