{
  "type": "Feature",
  "properties": {
    "iso:country": "GB",
    "wof:name": "SG5 1RP",
    "wof:placetype": "postalcode"
  },
  "geometry": {"coordinates":[-0.272104,51.959234],"type":"Point"}
}
