{
  "type": "Feature",
  "properties": {
    "iso:country":"GB",
    "wof:name":"SG5 1RP",
    "wof:placetype":"postalcode"
},
  "geometry": {"coordinates":[-0.27186302718604,51.95933874506709],"type":"Point"}
}