{
  "type": "Feature",
  "properties": {
    "date:inception_lower":"2001-12-01",
    "date:inception_upper":"2001-12-31",
    "iso:country":"GB",
    "wof:name":"SG5 1RP",
    "wof:placetype":"postalcode"
},
  "geometry": {"coordinates":[-0.272104,51.959234],"type":"Point"}
}