{
  "type": "Feature",
  "properties": {
    "iso:country":"GB",
    "wof:name":"BL3 1NH",
    "wof:placetype":"postalcode"
},
  "geometry": {"coordinates":[-2.36570951793087,53.56239512538372],"type":"Point"}
}