{
  "type": "Feature",
  "properties": {
    "date:inception_lower": "1980-01-01",
    "date:inception_upper": "1980-01-01",
    "iso:country": "GB",
    "wof:name": "L7 6NX",
    "wof:placetype": "postalcode"
  },
  "geometry": {"coordinates":[-2.940188,53.398862],"type":"Point"}
}
