{
  "type": "Feature",
  "properties": {
    "iso:country":"GB",
    "wof:name":"NN8 2QU",
    "wof:placetype":"postalcode"
},
  "geometry": {"coordinates":[-0.69365918803578,52.28849713525973],"type":"Point"}
}