{
  "type": "Feature",
  "properties": {
    "date:inception_lower":"2017-09-01",
    "date:inception_upper":"2017-09-30",
    "iso:country":"GB",
    "wof:name":"DY9 0WL",
    "wof:placetype":"postalcode"
},
  "geometry": {"coordinates":[-2.137448,52.419744],"type":"Point"}
}