{
  "type": "Feature",
  "properties": {
    "date:inception_lower": "2017-09-01",
    "date:inception_upper": "2017-09-01",
    "iso:country": "GB",
    "wof:name": "DY9 0WL",
    "wof:placetype": "postalcode"
  },
  "geometry": {"coordinates":[-2.137066,52.419808],"type":"Point"}
}
