{
  "type": "Feature",
  "properties": {
    "iso:country": "GB",
    "wof:name": "DY9 0WL",
    "wof:placetype": "postalcode"
  },
  "geometry": {"coordinates":[-2.137448,52.419744],"type":"Point"}
}
