{
  "type": "Feature",
  "properties": {
    "iso:country": "GB",
    "wof:name": "TA2 6FA",
    "wof:placetype": "postalcode"
  },
  "geometry": {"coordinates":[-3.138805,51.028692],"type":"Point"}
}
