{
  "type": "Feature",
  "properties": {
    "date:inception_lower":"2014-08-01",
    "date:inception_upper":"2014-08-31",
    "iso:country":"GB",
    "wof:name":"TA2 6FA",
    "wof:placetype":"postalcode"
},
  "geometry": {"coordinates":[-3.138805,51.028692],"type":"Point"}
}