{
  "type": "Feature",
  "properties": {
    "iso:country":"GB",
    "wof:name":"LS8 2SD",
    "wof:placetype":"postalcode"
},
  "geometry": {"coordinates":[-1.50504631685145,53.82155666389916],"type":"Point"}
}