{
  "type": "Feature",
  "properties": {
    "iso:country":"GB",
    "wof:name":"BA2 6SL",
    "wof:placetype":"postalcode"
},
  "geometry": {"coordinates":[-2.33229025302261,51.39539898046488],"type":"Point"}
}