{
  "type": "Feature",
  "properties": {
    "date:inception_lower": "1980-01-01",
    "date:inception_upper": "1980-01-01",
    "iso:country": "GB",
    "wof:name": "BA2 6SL",
    "wof:placetype": "postalcode"
  },
  "geometry": {"coordinates":[-2.33229,51.395399],"type":"Point"}
}
