{
  "type": "Feature",
  "properties": {
    "iso:country":"GB",
    "wof:name":"AL4 0SX",
    "wof:placetype":"postalcode"
},
  "geometry": {"coordinates":[-0.28874689064693,51.7511000093163],"type":"Point"}
}