{
  "type": "Feature",
  "properties": {
    "iso:country":"GB",
    "wof:name":"DN22 7HB",
    "wof:placetype":"postalcode"
},
  "geometry": {"coordinates":[-0.92652289246245,53.31040458204552],"type":"Point"}
}