{
  "type": "Feature",
  "properties": {
    "iso:country": "GB",
    "wof:name": "NE36 0SJ",
    "wof:placetype": "postalcode"
  },
  "geometry": {"coordinates":[-1.432959,54.945169],"type":"Point"}
}
