{
  "type": "Feature",
  "properties": {
    "iso:country": "GB",
    "wof:name": "BH13 7QR",
    "wof:placetype": "postalcode"
  },
  "geometry": {"coordinates":[-1.948507,50.685864],"type":"Point"}
}
