{
  "type": "Feature",
  "properties": {
    "date:inception_lower": "1980-01-01",
    "date:inception_upper": "1980-01-01",
    "iso:country": "GB",
    "wof:name": "BH13 7QR",
    "wof:placetype": "postalcode"
  },
  "geometry": {"coordinates":[-1.948507,50.685864],"type":"Point"}
}
