{
  "type": "Feature",
  "properties": {
    "iso:country":"GB",
    "wof:name":"SE26 4PH",
    "wof:placetype":"postalcode"
},
  "geometry": {"coordinates":[-0.05091632983067,51.42769451823185],"type":"Point"}
}