{
  "type": "Feature",
  "properties": {
    "iso:country":"GB",
    "wof:name":"M7 3TH",
    "wof:placetype":"postalcode"
},
  "geometry": {"coordinates":[-2.27892490569778,53.50200247797488],"type":"Point"}
}