{
  "type": "Feature",
  "properties": {
    "iso:country": "GB",
    "wof:name": "YO22 4JW",
    "wof:placetype": "postalcode"
  },
  "geometry": {"coordinates":[-0.607209,54.471805],"type":"Point"}
}
