{
  "type": "Feature",
  "properties": {
    "iso:country":"GB",
    "wof:name":"YO22 4JW",
    "wof:placetype":"postalcode"
},
  "geometry": {"coordinates":[-0.60720896988943,54.4718054857329],"type":"Point"}
}