{
  "type": "Feature",
  "properties": {
    "iso:country": "GB",
    "wof:name": "NG25 0TS",
    "wof:placetype": "postalcode"
  },
  "geometry": {"coordinates":[-0.900228,53.066242],"type":"Point"}
}
