{
  "type": "Feature",
  "properties": {
    "iso:country":"GB",
    "wof:name":"NG25 0TS",
    "wof:placetype":"postalcode"
},
  "geometry": {"coordinates":[-0.90020253403824,53.06623904108044],"type":"Point"}
}