{
  "type": "Feature",
  "properties": {
    "iso:country":"GB",
    "wof:name":"PL1 4TA",
    "wof:placetype":"postalcode"
},
  "geometry": {"coordinates":[-4.17368070196672,50.37306149806732],"type":"Point"}
}