{
  "type": "Feature",
  "properties": {
    "iso:country": "GB",
    "wof:name": "PL1 4TA",
    "wof:placetype": "postalcode"
  },
  "geometry": {"coordinates":[-4.173681,50.373061],"type":"Point"}
}
