{
  "type": "Feature",
  "properties": {
    "iso:country":"GB",
    "wof:name":"AB42 1QB",
    "wof:placetype":"postalcode"
},
  "geometry": {"coordinates":[-1.78357424977761,57.50583095417227],"type":"Point"}
}