{
  "type": "Feature",
  "properties": {
    "date:inception_lower": "2000-12-01",
    "date:inception_upper": "2000-12-01",
    "iso:country": "GB",
    "wof:name": "WA14 5PP",
    "wof:placetype": "postalcode"
  },
  "geometry": {"coordinates":[-2.374657,53.396008],"type":"Point"}
}
