{
  "type": "Feature",
  "properties": {
    "iso:country":"GB",
    "wof:name":"BB1 7LG",
    "wof:placetype":"postalcode"
},
  "geometry": {"coordinates":[-2.48122711015047,53.75291458065208],"type":"Point"}
}