{
  "type": "Feature",
  "properties": {
    "iso:country":"GB",
    "wof:name":"LU4 0DB",
    "wof:placetype":"postalcode"
},
  "geometry": {"coordinates":[-0.47573425001489,51.88909794557875],"type":"Point"}
}