{
  "type": "Feature",
  "properties": {
    "iso:country": "GB",
    "wof:name": "LU4 0DB",
    "wof:placetype": "postalcode"
  },
  "geometry": {"coordinates":[-0.475734,51.889098],"type":"Point"}
}
