{
  "type": "Feature",
  "properties": {
    "iso:country": "GB",
    "wof:name": "HP18 0AJ",
    "wof:placetype": "postalcode"
  },
  "geometry": {"coordinates":[-0.928679,51.792653],"type":"Point"}
}
