{
  "type": "Feature",
  "properties": {
    "iso:country":"GB",
    "wof:name":"HP18 0AJ",
    "wof:placetype":"postalcode"
},
  "geometry": {"coordinates":[-0.92867893464509,51.79265271917561],"type":"Point"}
}