{
  "type": "Feature",
  "properties": {
    "iso:country": "GB",
    "wof:name": "W13 9BY",
    "wof:placetype": "postalcode"
  },
  "geometry": {"coordinates":[-0.32475,51.509451],"type":"Point"}
}
