{
  "type": "Feature",
  "properties": {
    "date:inception_lower": "1984-10-01",
    "date:inception_upper": "1984-10-01",
    "iso:country": "GB",
    "wof:name": "W13 9BY",
    "wof:placetype": "postalcode"
  },
  "geometry": {"coordinates":[-0.32475,51.509451],"type":"Point"}
}
