{
  "type": "Feature",
  "properties": {
    "iso:country":"GB",
    "wof:name":"W13 9BY",
    "wof:placetype":"postalcode"
},
  "geometry": {"coordinates":[-0.32474959503318,51.50945136125004],"type":"Point"}
}