{
  "type": "Feature",
  "properties": {
    "iso:country":"GB",
    "wof:name":"PL6 7NT",
    "wof:placetype":"postalcode"
},
  "geometry": {"coordinates":[-4.0993896747418,50.4264318775715],"type":"Point"}
}