{
  "type": "Feature",
  "properties": {
    "iso:country": "GB",
    "wof:name": "PL6 7NT",
    "wof:placetype": "postalcode"
  },
  "geometry": {"coordinates":[-4.099491,50.426507],"type":"Point"}
}
