{
  "type": "Feature",
  "properties": {
    "date:inception_lower": "1980-01-01",
    "date:inception_upper": "1980-01-01",
    "iso:country": "GB",
    "wof:name": "M6 6NA",
    "wof:placetype": "postalcode"
  },
  "geometry": {"coordinates":[-2.285475,53.494086],"type":"Point"}
}
