{
  "type": "Feature",
  "properties": {
    "date:inception_lower":"1994-05-01",
    "date:inception_upper":"1994-05-31",
    "iso:country":"GB",
    "wof:name":"SG1 5RF",
    "wof:placetype":"postalcode"
},
  "geometry": {"coordinates":[-0.165025,51.916737],"type":"Point"}
}