{
  "type": "Feature",
  "properties": {
    "iso:country": "GB",
    "wof:name": "SG1 5RF",
    "wof:placetype": "postalcode"
  },
  "geometry": {"coordinates":[-0.165025,51.916737],"type":"Point"}
}
