{
  "type": "Feature",
  "properties": {
    "date:inception_lower":"2018-07-01",
    "date:inception_upper":"2018-07-31",
    "iso:country":"GB",
    "wof:name":"EH54 7DD",
    "wof:placetype":"postalcode"
},
  "geometry": {"coordinates":[-3.52951,55.891391],"type":"Point"}
}