{
  "type": "Feature",
  "properties": {
    "date:inception_lower": "1980-01-01",
    "date:inception_upper": "1980-01-01",
    "iso:country": "GB",
    "wof:name": "TW13 7AH",
    "wof:placetype": "postalcode"
  },
  "geometry": {"coordinates":[-0.41071,51.441857],"type":"Point"}
}
