{
  "type": "Feature",
  "properties": {
    "iso:country":"GB",
    "wof:name":"TW13 7AH",
    "wof:placetype":"postalcode"
},
  "geometry": {"coordinates":[-0.41070990923441,51.44185667356538],"type":"Point"}
}