{
  "type": "Feature",
  "properties": {
    "iso:country":"GB",
    "wof:name":"WS10 8NA",
    "wof:placetype":"postalcode"
},
  "geometry": {"coordinates":[-2.02008447237236,52.57658377557976],"type":"Point"}
}