{
  "type": "Feature",
  "properties": {
    "date:inception_lower":"1980-01-01",
    "date:inception_upper":"1980-01-31",
    "iso:country":"GB",
    "wof:name":"WS10 8NA",
    "wof:placetype":"postalcode"
},
  "geometry": {"coordinates":[-2.020084,52.576584],"type":"Point"}
}