{
  "type": "Feature",
  "properties": {
    "iso:country": "GB",
    "wof:name": "CT11 9YE",
    "wof:placetype": "postalcode"
  },
  "geometry": {"coordinates":[1.412494,51.337883],"type":"Point"}
}
