{
  "type": "Feature",
  "properties": {
    "iso:country":"GB",
    "wof:name":"CT11 9YE",
    "wof:placetype":"postalcode"
},
  "geometry": {"coordinates":[1.4122357574807,51.33764826117747],"type":"Point"}
}