{
  "type": "Feature",
  "properties": {
    "date:inception_lower": "1990-07-01",
    "date:inception_upper": "1990-07-01",
    "iso:country": "GB",
    "wof:name": "CT11 9YE",
    "wof:placetype": "postalcode"
  },
  "geometry": {"coordinates":[1.412494,51.337883],"type":"Point"}
}
