{
  "type": "Feature",
  "properties": {
    "date:inception_lower":"1994-12-01",
    "date:inception_upper":"1994-12-31",
    "iso:country":"GB",
    "wof:name":"SO53 2HQ",
    "wof:placetype":"postalcode"
},
  "geometry": {"coordinates":[-1.375657,50.983732],"type":"Point"}
}