{
  "type": "Feature",
  "properties": {
    "iso:country":"GB",
    "wof:name":"SO53 2HQ",
    "wof:placetype":"postalcode"
},
  "geometry": {"coordinates":[-1.37556883226335,50.98365832008333],"type":"Point"}
}