{
  "type": "Feature",
  "properties": {
    "iso:country":"GB",
    "wof:name":"LE5 4GS",
    "wof:placetype":"postalcode"
},
  "geometry": {"coordinates":[-1.09618431966498,52.63565527746653],"type":"Point"}
}