{
  "type": "Feature",
  "properties": {
    "iso:country":"GB",
    "wof:name":"CF48 3PY",
    "wof:placetype":"postalcode"
},
  "geometry": {"coordinates":[-3.34406110114468,51.76349120541778],"type":"Point"}
}