{
  "type": "Feature",
  "properties": {
    "iso:country": "GB",
    "wof:name": "CF48 3PY",
    "wof:placetype": "postalcode"
  },
  "geometry": {"coordinates":[-3.344061,51.763491],"type":"Point"}
}
