{
  "type": "Feature",
  "properties": {
    "iso:country":"GB",
    "wof:name":"S41 7WT",
    "wof:placetype":"postalcode"
},
  "geometry": {"coordinates":[-1.43458258997404,53.23533962443287],"type":"Point"}
}