{
  "type": "Feature",
  "properties": {
    "date:inception_lower": "2011-01-01",
    "date:inception_upper": "2011-01-01",
    "iso:country": "GB",
    "wof:name": "CW2 5BQ",
    "wof:placetype": "postalcode"
  },
  "geometry": {"coordinates":[-2.388956,53.058727],"type":"Point"}
}
