{
  "type": "Feature",
  "properties": {
    "iso:country": "GB",
    "wof:name": "GL2 4DR",
    "wof:placetype": "postalcode"
  },
  "geometry": {"coordinates":[-2.269732,51.806488],"type":"Point"}
}
