{
  "type": "Feature",
  "properties": {
    "iso:country":"GB",
    "wof:name":"TS27 3AA",
    "wof:placetype":"postalcode"
},
  "geometry": {"coordinates":[-1.25251903016062,54.72133490111209],"type":"Point"}
}