{
  "type": "Feature",
  "properties": {
    "iso:country":"GB",
    "wof:name":"ME17 1TG",
    "wof:placetype":"postalcode"
},
  "geometry": {"coordinates":[0.59259853460623,51.25248179538197],"type":"Point"}
}