{
  "type": "Feature",
  "properties": {
    "iso:country":"GB",
    "wof:name":"N21 2EG",
    "wof:placetype":"postalcode"
},
  "geometry": {"coordinates":[-0.09423384330707,51.645774254339],"type":"Point"}
}