{
  "type": "Feature",
  "properties": {
    "iso:country":"GB",
    "wof:name":"LA14 4EU",
    "wof:placetype":"postalcode"
},
  "geometry": {"coordinates":[-3.21603531357106,54.1366816179896],"type":"Point"}
}