{
  "type": "Feature",
  "properties": {
    "iso:country": "GB",
    "wof:name": "LA14 4EU",
    "wof:placetype": "postalcode"
  },
  "geometry": {"coordinates":[-3.216035,54.136682],"type":"Point"}
}
