{
  "type": "Feature",
  "properties": {
    "iso:country":"GB",
    "wof:name":"EX1 2FB",
    "wof:placetype":"postalcode"
},
  "geometry": {"coordinates":[-3.50716593914042,50.72523118124694],"type":"Point"}
}