{
  "type": "Feature",
  "properties": {
    "iso:country": "GB",
    "wof:name": "NG34 9SQ",
    "wof:placetype": "postalcode"
  },
  "geometry": {"coordinates":[-0.356864,53.03552],"type":"Point"}
}
