{
  "type": "Feature",
  "properties": {
    "date:inception_lower":"1980-01-01",
    "date:inception_upper":"1980-01-31",
    "iso:country":"GB",
    "wof:name":"PO10 7SZ",
    "wof:placetype":"postalcode"
},
  "geometry": {"coordinates":[-0.936073,50.860278],"type":"Point"}
}