{
  "type": "Feature",
  "properties": {
    "iso:country":"GB",
    "wof:name":"PO10 7SZ",
    "wof:placetype":"postalcode"
},
  "geometry": {"coordinates":[-0.93607328648515,50.86027816475247],"type":"Point"}
}