{
  "type": "Feature",
  "properties": {
    "iso:country": "GB",
    "wof:name": "RG42 7PH",
    "wof:placetype": "postalcode"
  },
  "geometry": {"coordinates":[-0.711048,51.43104],"type":"Point"}
}
