{
  "type": "Feature",
  "properties": {
    "iso:country":"GB",
    "wof:name":"RG42 7PH",
    "wof:placetype":"postalcode"
},
  "geometry": {"coordinates":[-0.71106538329089,51.43103921433723],"type":"Point"}
}