{
  "type": "Feature",
  "properties": {
    "iso:country": "GB",
    "wof:name": "SM3 9SW",
    "wof:placetype": "postalcode"
  },
  "geometry": {"coordinates":[-0.214224,51.366953],"type":"Point"}
}
