{
  "type": "Feature",
  "properties": {
    "iso:country":"GB",
    "wof:name":"SM3 9SW",
    "wof:placetype":"postalcode"
},
  "geometry": {"coordinates":[-0.21422393856386,51.36695268416876],"type":"Point"}
}