{
  "type": "Feature",
  "properties": {
    "iso:country":"GB",
    "wof:name":"BA14 6FX",
    "wof:placetype":"postalcode"
},
  "geometry": {"coordinates":[-2.17940450918706,51.31910586194839],"type":"Point"}
}