{
  "type": "Feature",
  "properties": {
    "date:inception_lower": "2014-05-01",
    "date:inception_upper": "2014-05-01",
    "iso:country": "GB",
    "wof:name": "BA14 6FX",
    "wof:placetype": "postalcode"
  },
  "geometry": {"coordinates":[-2.179404,51.319106],"type":"Point"}
}
