{
  "type": "Feature",
  "properties": {
    "iso:country":"GB",
    "wof:name":"SA14 8QP",
    "wof:placetype":"postalcode"
},
  "geometry": {"coordinates":[-4.08495382788344,51.69849145708639],"type":"Point"}
}