{
  "type": "Feature",
  "properties": {
    "iso:country":"GB",
    "wof:name":"DY11 6RH",
    "wof:placetype":"postalcode"
},
  "geometry": {"coordinates":[-2.26267254216939,52.38754901190499],"type":"Point"}
}