{
  "type": "Feature",
  "properties": {
    "iso:country": "GB",
    "wof:name": "DY11 6RH",
    "wof:placetype": "postalcode"
  },
  "geometry": {"coordinates":[-2.262672,52.387549],"type":"Point"}
}
