{
  "type": "Feature",
  "properties": {
    "iso:country":"GB",
    "wof:name":"LE4 5DH",
    "wof:placetype":"postalcode"
},
  "geometry": {"coordinates":[-1.12044937889727,52.65473478307177],"type":"Point"}
}