{
  "type": "Feature",
  "properties": {
    "iso:country":"GB",
    "wof:name":"BH23 1QS",
    "wof:placetype":"postalcode"
},
  "geometry": {"coordinates":[-1.77994133084433,50.73799701605563],"type":"Point"}
}