{
  "type": "Feature",
  "properties": {
    "iso:country":"GB",
    "wof:name":"NE66 2AF",
    "wof:placetype":"postalcode"
},
  "geometry": {"coordinates":[-1.72317491156712,55.40276074567808],"type":"Point"}
}