{
  "type": "Feature",
  "properties": {
    "date:inception_lower": "2007-11-01",
    "date:inception_upper": "2007-11-01",
    "iso:country": "GB",
    "wof:name": "CV3 1NG",
    "wof:placetype": "postalcode"
  },
  "geometry": {"coordinates":[-1.481598,52.396739],"type":"Point"}
}
