{
  "type": "Feature",
  "properties": {
    "iso:country":"GB",
    "wof:name":"CV3 1NG",
    "wof:placetype":"postalcode"
},
  "geometry": {"coordinates":[-1.48159827989419,52.39673895019619],"type":"Point"}
}