{
  "type": "Feature",
  "properties": {
    "iso:country":"GB",
    "wof:name":"N17 9EL",
    "wof:placetype":"postalcode"
},
  "geometry": {"coordinates":[-0.07160371891396,51.59386008601219],"type":"Point"}
}