{
  "type": "Feature",
  "properties": {
    "iso:country":"GB",
    "wof:name":"TD15 1QB",
    "wof:placetype":"postalcode"
},
  "geometry": {"coordinates":[-2.01159796178004,55.78401255877741],"type":"Point"}
}