{
  "type": "Feature",
  "properties": {
    "iso:country":"GB",
    "wof:name":"NE34 0SX",
    "wof:placetype":"postalcode"
},
  "geometry": {"coordinates":[-1.42086550062323,54.97972861465006],"type":"Point"}
}