{
  "type": "Feature",
  "properties": {
    "date:inception_lower": "2019-09-01",
    "date:inception_upper": "2019-09-01",
    "iso:country": "GB",
    "wof:name": "NP44 3FR",
    "wof:placetype": "postalcode"
  },
  "geometry": {"coordinates":[-3.034554,51.650816],"type":"Point"}
}
