{
  "type": "Feature",
  "properties": {
    "iso:country":"GB",
    "wof:name":"PR7 1PP",
    "wof:placetype":"postalcode"
},
  "geometry": {"coordinates":[-2.63525616539889,53.66583777266613],"type":"Point"}
}