{
  "type": "Feature",
  "properties": {
    "date:inception_lower": "1980-01-01",
    "date:inception_upper": "1980-01-01",
    "iso:country": "GB",
    "wof:name": "SN16 0NX",
    "wof:placetype": "postalcode"
  },
  "geometry": {"coordinates":[-2.199044,51.579092],"type":"Point"}
}
