{
  "type": "Feature",
  "properties": {
    "date:inception_lower": "1993-01-01",
    "date:inception_upper": "1993-01-01",
    "iso:country": "GB",
    "wof:name": "TQ1 1TF",
    "wof:placetype": "postalcode"
  },
  "geometry": {"coordinates":[-3.526098,50.471958],"type":"Point"}
}
