{
  "type": "Feature",
  "properties": {
    "iso:country":"GB",
    "wof:name":"BS5 0NQ",
    "wof:placetype":"postalcode"
},
  "geometry": {"coordinates":[-2.56745002280722,51.46711248978873],"type":"Point"}
}