{
  "type": "Feature",
  "properties": {
    "date:inception_lower": "2020-08-01",
    "date:inception_upper": "2020-08-01",
    "iso:country": "GB",
    "wof:name": "CH66 4AT",
    "wof:placetype": "postalcode"
  },
  "geometry": {"coordinates":[-2.951344,53.277968],"type":"Point"}
}
