{
  "type": "Feature",
  "properties": {
    "iso:country": "GB",
    "wof:name": "HX2 0JN",
    "wof:placetype": "postalcode"
  },
  "geometry": {"coordinates":[-1.888724,53.72967],"type":"Point"}
}
