{
  "type": "Feature",
  "properties": {
    "date:inception_lower": "2023-08-01",
    "date:inception_upper": "2023-08-01",
    "iso:country": "GB",
    "wof:name": "BL6 5WT",
    "wof:placetype": "postalcode"
  },
  "geometry": {"coordinates":[-2.546744,53.591795],"type":"Point"}
}
