{
  "type": "Feature",
  "properties": {
    "iso:country": "GB",
    "wof:name": "CB24 5NA",
    "wof:placetype": "postalcode"
  },
  "geometry": {"coordinates":[0.015762,52.312938],"type":"Point"}
}
