{
  "type": "Feature",
  "properties": {
    "iso:country":"GB",
    "wof:name":"CB24 5NA",
    "wof:placetype":"postalcode"
},
  "geometry": {"coordinates":[0.01576177400459,52.31293796149131],"type":"Point"}
}