{
  "type": "Feature",
  "properties": {
    "date:inception_lower": "1996-12-01",
    "date:inception_upper": "1996-12-01",
    "iso:country": "GB",
    "wof:name": "GU35 8HZ",
    "wof:placetype": "postalcode"
  },
  "geometry": {"coordinates":[-0.805447,51.120854],"type":"Point"}
}
