{
  "type": "Feature",
  "properties": {
    "iso:country": "GB",
    "wof:name": "TA4 4AG",
    "wof:placetype": "postalcode"
  },
  "geometry": {"coordinates":[-3.236492,51.125381],"type":"Point"}
}
