{
  "type": "Feature",
  "properties": {
    "date:inception_lower": "1980-01-01",
    "date:inception_upper": "1980-01-01",
    "iso:country": "GB",
    "wof:name": "TA4 4AG",
    "wof:placetype": "postalcode"
  },
  "geometry": {"coordinates":[-3.236492,51.125381],"type":"Point"}
}
