{
  "type": "Feature",
  "properties": {
    "iso:country":"GB",
    "wof:name":"GL13 9SQ",
    "wof:placetype":"postalcode"
},
  "geometry": {"coordinates":[-2.45846243885012,51.71830528463133],"type":"Point"}
}