{
  "type": "Feature",
  "properties": {
    "date:inception_lower": "1980-01-01",
    "date:inception_upper": "1980-01-01",
    "iso:country": "GB",
    "wof:name": "GL13 9SQ",
    "wof:placetype": "postalcode"
  },
  "geometry": {"coordinates":[-2.458463,51.718381],"type":"Point"}
}
