{
  "type": "Feature",
  "properties": {
    "iso:country": "GB",
    "wof:name": "NW10 6UN",
    "wof:placetype": "postalcode"
  },
  "geometry": {"coordinates":[-0.240602,51.528254],"type":"Point"}
}
