{
  "type": "Feature",
  "properties": {
    "iso:country":"GB",
    "wof:name":"OX20 1LW",
    "wof:placetype":"postalcode"
},
  "geometry": {"coordinates":[-1.34381296253971,51.84887480306418],"type":"Point"}
}