{
  "type": "Feature",
  "properties": {
    "iso:country": "GB",
    "wof:name": "OX20 1LW",
    "wof:placetype": "postalcode"
  },
  "geometry": {"coordinates":[-1.344331,51.848984],"type":"Point"}
}
