{
  "type": "Feature",
  "properties": {
    "date:inception_lower": "2006-01-01",
    "date:inception_upper": "2006-01-01",
    "iso:country": "GB",
    "wof:name": "HD2 1ZF",
    "wof:placetype": "postalcode"
  },
  "geometry": {"coordinates":[-1.768145,53.67278],"type":"Point"}
}
