{
  "type": "Feature",
  "properties": {
    "iso:country":"GB",
    "wof:name":"HD2 1ZF",
    "wof:placetype":"postalcode"
},
  "geometry": {"coordinates":[-1.76814329027236,53.67276490808749],"type":"Point"}
}