{
  "type": "Feature",
  "properties": {
    "iso:country":"GB",
    "wof:name":"SA18 2JB",
    "wof:placetype":"postalcode"
},
  "geometry": {"coordinates":[-3.96284152856021,51.79627421537677],"type":"Point"}
}