{
  "type": "Feature",
  "properties": {
    "date:inception_lower": "1980-01-01",
    "date:inception_upper": "1980-01-01",
    "iso:country": "GB",
    "wof:name": "SA18 2JB",
    "wof:placetype": "postalcode"
  },
  "geometry": {"coordinates":[-3.962841,51.796274],"type":"Point"}
}
