{
  "type": "Feature",
  "properties": {
    "iso:country":"GB",
    "wof:name":"CV1 2JJ",
    "wof:placetype":"postalcode"
},
  "geometry": {"coordinates":[-1.49610437216798,52.40571988260707],"type":"Point"}
}