{
  "type": "Feature",
  "properties": {
    "iso:country": "GB",
    "wof:name": "EX34 9QH",
    "wof:placetype": "postalcode"
  },
  "geometry": {"coordinates":[-4.108763,51.206614],"type":"Point"}
}
