{
  "type": "Feature",
  "properties": {
    "iso:country":"GB",
    "wof:name":"EX34 9QH",
    "wof:placetype":"postalcode"
},
  "geometry": {"coordinates":[-4.1086533286096,51.20658864082966],"type":"Point"}
}