{
  "type": "Feature",
  "properties": {
    "iso:country":"GB",
    "wof:name":"RG7 2HG",
    "wof:placetype":"postalcode"
},
  "geometry": {"coordinates":[-1.07543314470634,51.35928848091822],"type":"Point"}
}