{
  "type": "Feature",
  "properties": {
    "iso:country": "GB",
    "wof:name": "RG7 2HG",
    "wof:placetype": "postalcode"
  },
  "geometry": {"coordinates":[-1.075433,51.359288],"type":"Point"}
}
