{
  "type": "Feature",
  "properties": {
    "iso:country":"GB",
    "wof:name":"SN7 8RB",
    "wof:placetype":"postalcode"
},
  "geometry": {"coordinates":[-1.50368977420614,51.67733346694909],"type":"Point"}
}