{
  "type": "Feature",
  "properties": {
    "iso:country": "GB",
    "wof:name": "SN7 8RB",
    "wof:placetype": "postalcode"
  },
  "geometry": {"coordinates":[-1.50369,51.677333],"type":"Point"}
}
