{
  "type": "Feature",
  "properties": {
    "date:inception_lower":"1980-01-01",
    "date:inception_upper":"1980-01-31",
    "iso:country":"GB",
    "wof:name":"SN7 8RB",
    "wof:placetype":"postalcode"
},
  "geometry": {"coordinates":[-1.50369,51.677333],"type":"Point"}
}