{
  "type": "Feature",
  "properties": {
    "iso:country":"GB",
    "wof:name":"CO15 6BT",
    "wof:placetype":"postalcode"
},
  "geometry": {"coordinates":[1.15895328964058,51.79237741851997],"type":"Point"}
}