{
  "type": "Feature",
  "properties": {
    "date:inception_lower": "1982-03-01",
    "date:inception_upper": "1982-03-01",
    "iso:country": "GB",
    "wof:name": "WV6 7QH",
    "wof:placetype": "postalcode"
  },
  "geometry": {"coordinates":[-2.202982,52.594819],"type":"Point"}
}
