{
  "type": "Feature",
  "properties": {
    "iso:country":"GB",
    "wof:name":"CA7 4HQ",
    "wof:placetype":"postalcode"
},
  "geometry": {"coordinates":[-3.39031671242793,54.86389969445884],"type":"Point"}
}