{
  "type": "Feature",
  "properties": {
    "date:inception_lower": "2000-06-01",
    "date:inception_upper": "2000-06-01",
    "iso:country": "GB",
    "wof:name": "CA7 4HQ",
    "wof:placetype": "postalcode"
  },
  "geometry": {"coordinates":[-3.390318,54.863915],"type":"Point"}
}
