{
  "type": "Feature",
  "properties": {
    "iso:country": "GB",
    "wof:name": "SA33 6LS",
    "wof:placetype": "postalcode"
  },
  "geometry": {"coordinates":[-4.31108,51.931927],"type":"Point"}
}
