{
  "type": "Feature",
  "properties": {
    "iso:country":"GB",
    "wof:name":"RM12 4BY",
    "wof:placetype":"postalcode"
},
  "geometry": {"coordinates":[0.18896641211474,51.56160005823274],"type":"Point"}
}