{
  "type": "Feature",
  "properties": {
    "iso:country":"GB",
    "wof:name":"BB2 7AY",
    "wof:placetype":"postalcode"
},
  "geometry": {"coordinates":[-2.50763232423516,53.75557395317596],"type":"Point"}
}