{
  "type": "Feature",
  "properties": {
    "iso:country": "GB",
    "wof:name": "CB24 6AQ",
    "wof:placetype": "postalcode"
  },
  "geometry": {"coordinates":[0.164558,52.242901],"type":"Point"}
}
