{
  "type": "Feature",
  "properties": {
    "iso:country":"GB",
    "wof:name":"CB24 6AQ",
    "wof:placetype":"postalcode"
},
  "geometry": {"coordinates":[0.16455812949159,52.24290127037042],"type":"Point"}
}