{
  "type": "Feature",
  "properties": {
    "date:inception_lower": "2018-04-01",
    "date:inception_upper": "2018-04-01",
    "iso:country": "GB",
    "wof:name": "LL61 6DY",
    "wof:placetype": "postalcode"
  },
  "geometry": {"coordinates":[-4.223402,53.209566],"type":"Point"}
}
