{
  "type": "Feature",
  "properties": {
    "date:inception_lower":"2005-09-01",
    "date:inception_upper":"2005-09-30",
    "iso:country":"GB",
    "wof:name":"G72 0DE",
    "wof:placetype":"postalcode"
},
  "geometry": {"coordinates":[-4.096948,55.777553],"type":"Point"}
}