{
  "type": "Feature",
  "properties": {
    "iso:country":"GB",
    "wof:name":"CA14 5LZ",
    "wof:placetype":"postalcode"
},
  "geometry": {"coordinates":[-3.56179826214088,54.61833945124945],"type":"Point"}
}