{
  "type": "Feature",
  "properties": {
    "date:inception_lower": "1980-01-01",
    "date:inception_upper": "1980-01-01",
    "iso:country": "GB",
    "wof:name": "CA14 5LZ",
    "wof:placetype": "postalcode"
  },
  "geometry": {"coordinates":[-3.561798,54.618339],"type":"Point"}
}
