{
  "type": "Feature",
  "properties": {
    "iso:country":"GB",
    "wof:name":"NG11 9FU",
    "wof:placetype":"postalcode"
},
  "geometry": {"coordinates":[-1.18771114633184,52.89458479522273],"type":"Point"}
}