{
  "type": "Feature",
  "properties": {
    "iso:country":"GB",
    "wof:name":"PA2 6UW",
    "wof:placetype":"postalcode"
},
  "geometry": {"coordinates":[-4.40925136225365,55.83369875927235],"type":"Point"}
}