{
  "type": "Feature",
  "properties": {
    "iso:country":"GB",
    "wof:name":"NE34 7LG",
    "wof:placetype":"postalcode"
},
  "geometry": {"coordinates":[-1.40097406621901,54.9819148599486],"type":"Point"}
}