{
  "type": "Feature",
  "properties": {
    "date:inception_lower": "2010-07-01",
    "date:inception_upper": "2010-07-01",
    "iso:country": "GB",
    "wof:name": "M7 1UJ",
    "wof:placetype": "postalcode"
  },
  "geometry": {"coordinates":[-2.2641,53.49632],"type":"Point"}
}
