{
  "type": "Feature",
  "properties": {
    "iso:country":"GB",
    "wof:name":"M7 1UJ",
    "wof:placetype":"postalcode"
},
  "geometry": {"coordinates":[-2.26410011703217,53.49631953663003],"type":"Point"}
}