{
  "type": "Feature",
  "properties": {
    "iso:country": "GB",
    "wof:name": "CB22 5JH",
    "wof:placetype": "postalcode"
  },
  "geometry": {"coordinates":[0.1309,52.156103],"type":"Point"}
}
