{
  "type": "Feature",
  "properties": {
    "iso:country":"GB",
    "wof:name":"G21 2JH",
    "wof:placetype":"postalcode"
},
  "geometry": {"coordinates":[-4.22660618531878,55.86723152575864],"type":"Point"}
}