{
  "type": "Feature",
  "properties": {
    "date:inception_lower": "1996-12-01",
    "date:inception_upper": "1996-12-01",
    "iso:country": "GB",
    "wof:name": "G21 2JH",
    "wof:placetype": "postalcode"
  },
  "geometry": {"coordinates":[-4.226606,55.867232],"type":"Point"}
}
