{
  "type": "Feature",
  "properties": {
    "iso:country":"GB",
    "wof:name":"LN5 7XJ",
    "wof:placetype":"postalcode"
},
  "geometry": {"coordinates":[-0.53857514120273,53.21944365368863],"type":"Point"}
}