{
  "type": "Feature",
  "properties": {
    "date:inception_lower": "1980-01-01",
    "date:inception_upper": "1980-01-01",
    "iso:country": "GB",
    "wof:name": "WR2 5HD",
    "wof:placetype": "postalcode"
  },
  "geometry": {"coordinates":[-2.252719,52.188889],"type":"Point"}
}
