{
  "type": "Feature",
  "properties": {
    "iso:country":"GB",
    "wof:name":"CW8 4XS",
    "wof:placetype":"postalcode"
},
  "geometry": {"coordinates":[-2.53152432925981,53.26205533447656],"type":"Point"}
}