{
  "type": "Feature",
  "properties": {
    "iso:country": "GB",
    "wof:name": "CW8 4XS",
    "wof:placetype": "postalcode"
  },
  "geometry": {"coordinates":[-2.531524,53.262055],"type":"Point"}
}
