{
  "type": "Feature",
  "properties": {
    "date:inception_lower": "2002-06-01",
    "date:inception_upper": "2002-06-01",
    "iso:country": "GB",
    "wof:name": "CW8 4XS",
    "wof:placetype": "postalcode"
  },
  "geometry": {"coordinates":[-2.531524,53.262055],"type":"Point"}
}
