{
  "type": "Feature",
  "properties": {
    "iso:country": "GB",
    "wof:name": "PE12 6AL",
    "wof:placetype": "postalcode"
  },
  "geometry": {"coordinates":[-0.130875,52.740962],"type":"Point"}
}
