{
  "type": "Feature",
  "properties": {
    "iso:country":"GB",
    "wof:name":"PE12 6AL",
    "wof:placetype":"postalcode"
},
  "geometry": {"coordinates":[-0.13087544767034,52.74096248023814],"type":"Point"}
}