{
  "type": "Feature",
  "properties": {
    "iso:country":"GB",
    "wof:name":"M11 1WS",
    "wof:placetype":"postalcode"
},
  "geometry": {"coordinates":[-2.16385383012678,53.47153830305218],"type":"Point"}
}