{
  "type": "Feature",
  "properties": {
    "iso:country": "GB",
    "wof:name": "OX7 6DG",
    "wof:placetype": "postalcode"
  },
  "geometry": {"coordinates":[-1.598685,51.856538],"type":"Point"}
}
