{
  "type": "Feature",
  "properties": {
    "iso:country": "GB",
    "wof:name": "CH48 9UR",
    "wof:placetype": "postalcode"
  },
  "geometry": {"coordinates":[-3.154856,53.371692],"type":"Point"}
}
