{
  "type": "Feature",
  "properties": {
    "date:inception_lower":"1999-06-01",
    "date:inception_upper":"1999-06-30",
    "iso:country":"GB",
    "wof:name":"CH48 9UR",
    "wof:placetype":"postalcode"
},
  "geometry": {"coordinates":[-3.154856,53.371692],"type":"Point"}
}