{
  "type": "Feature",
  "properties": {
    "iso:country": "GB",
    "wof:name": "SW11 3QX",
    "wof:placetype": "postalcode"
  },
  "geometry": {"coordinates":[-0.182767,51.463679],"type":"Point"}
}
