{
  "type": "Feature",
  "properties": {
    "iso:country":"GB",
    "wof:name":"EH55 8RF",
    "wof:placetype":"postalcode"
},
  "geometry": {"coordinates":[-3.52389114269208,55.84216750347056],"type":"Point"}
}