{
  "type": "Feature",
  "properties": {
    "iso:country":"GB",
    "wof:name":"DH3 1LG",
    "wof:placetype":"postalcode"
},
  "geometry": {"coordinates":[-1.57779182411923,54.8968822018786],"type":"Point"}
}