{
  "type": "Feature",
  "properties": {
    "date:inception_lower": "2003-01-01",
    "date:inception_upper": "2003-01-01",
    "iso:country": "GB",
    "wof:name": "G78 2YH",
    "wof:placetype": "postalcode"
  },
  "geometry": {"coordinates":[-4.398047,55.801121],"type":"Point"}
}
