{
  "type": "Feature",
  "properties": {
    "date:inception_lower": "1980-01-01",
    "date:inception_upper": "1980-01-01",
    "iso:country": "GB",
    "wof:name": "PO18 0PJ",
    "wof:placetype": "postalcode"
  },
  "geometry": {"coordinates":[-0.751548,50.865474],"type":"Point"}
}
