{
  "type": "Feature",
  "properties": {
    "iso:country":"GB",
    "wof:name":"PO18 0PJ",
    "wof:placetype":"postalcode"
},
  "geometry": {"coordinates":[-0.75154793183865,50.86547390595954],"type":"Point"}
}