{
  "type": "Feature",
  "properties": {
    "date:inception_lower": "1980-01-01",
    "date:inception_upper": "1980-01-01",
    "iso:country": "GB",
    "wof:name": "CB9 9HS",
    "wof:placetype": "postalcode"
  },
  "geometry": {"coordinates":[0.429778,52.088234],"type":"Point"}
}
