{
  "type": "Feature",
  "properties": {
    "date:inception_lower": "1980-01-01",
    "date:inception_upper": "1980-01-01",
    "iso:country": "GB",
    "wof:name": "WA12 8HT",
    "wof:placetype": "postalcode"
  },
  "geometry": {"coordinates":[-2.62158,53.451049],"type":"Point"}
}
