{
  "type": "Feature",
  "properties": {
    "iso:country":"GB",
    "wof:name":"WA12 8HT",
    "wof:placetype":"postalcode"
},
  "geometry": {"coordinates":[-2.62157996466278,53.45104912687475],"type":"Point"}
}