{
  "type": "Feature",
  "properties": {
    "date:inception_lower": "1980-01-01",
    "date:inception_upper": "1980-01-01",
    "iso:country": "GB",
    "wof:name": "CA13 0LH",
    "wof:placetype": "postalcode"
  },
  "geometry": {"coordinates":[-3.43198,54.669808],"type":"Point"}
}
