{
  "type": "Feature",
  "properties": {
    "iso:country":"GB",
    "wof:name":"CA13 0LH",
    "wof:placetype":"postalcode"
},
  "geometry": {"coordinates":[-3.43198004900388,54.66980806292315],"type":"Point"}
}