{
  "type": "Feature",
  "properties": {
    "iso:country": "GB",
    "wof:name": "G66 3TQ",
    "wof:placetype": "postalcode"
  },
  "geometry": {"coordinates":[-4.10648,55.942092],"type":"Point"}
}
