{
  "type": "Feature",
  "properties": {
    "date:inception_lower":"1980-01-01",
    "date:inception_upper":"1980-01-31",
    "iso:country":"GB",
    "wof:name":"G66 3TQ",
    "wof:placetype":"postalcode"
},
  "geometry": {"coordinates":[-4.11105,55.939866],"type":"Point"}
}