{
  "type": "Feature",
  "properties": {
    "date:inception_lower": "1980-01-01",
    "date:inception_upper": "1980-01-01",
    "iso:country": "GB",
    "wof:name": "LE2 2AL",
    "wof:placetype": "postalcode"
  },
  "geometry": {"coordinates":[-1.105507,52.617584],"type":"Point"}
}
