{
  "type": "Feature",
  "properties": {
    "iso:country":"GB",
    "wof:name":"BH23 2RS",
    "wof:placetype":"postalcode"
},
  "geometry": {"coordinates":[-1.79902874361431,50.75482968303685],"type":"Point"}
}