{
  "type": "Feature",
  "properties": {
    "iso:country": "GB",
    "wof:name": "BH23 2RS",
    "wof:placetype": "postalcode"
  },
  "geometry": {"coordinates":[-1.799029,50.75483],"type":"Point"}
}
