{
  "type": "Feature",
  "properties": {
    "date:inception_lower": "1980-01-01",
    "date:inception_upper": "1980-01-01",
    "iso:country": "GB",
    "wof:name": "SY25 6TF",
    "wof:placetype": "postalcode"
  },
  "geometry": {"coordinates":[-4.018121,52.212568],"type":"Point"}
}
