{
  "type": "Feature",
  "properties": {
    "iso:country":"GB",
    "wof:name":"NE20 0ET",
    "wof:placetype":"postalcode"
},
  "geometry": {"coordinates":[-1.84217590575008,55.1041854263807],"type":"Point"}
}