{
  "type": "Feature",
  "properties": {
    "iso:country":"GB",
    "wof:name":"DL13 4BF",
    "wof:placetype":"postalcode"
},
  "geometry": {"coordinates":[-1.8134604903801,54.74676948596723],"type":"Point"}
}