{
  "type": "Feature",
  "properties": {
    "date:inception_lower":"2008-11-01",
    "date:inception_upper":"2008-11-30",
    "iso:country":"GB",
    "wof:name":"DL13 4BF",
    "wof:placetype":"postalcode"
},
  "geometry": {"coordinates":[-1.81346,54.746769],"type":"Point"}
}