{
  "type": "Feature",
  "properties": {
    "iso:country": "GB",
    "wof:name": "DL13 4BF",
    "wof:placetype": "postalcode"
  },
  "geometry": {"coordinates":[-1.81346,54.746769],"type":"Point"}
}
