{
  "type": "Feature",
  "properties": {
    "date:inception_lower": "1980-01-01",
    "date:inception_upper": "1980-01-01",
    "iso:country": "GB",
    "wof:name": "B74 4SB",
    "wof:placetype": "postalcode"
  },
  "geometry": {"coordinates":[-1.840106,52.591239],"type":"Point"}
}
