{
  "type": "Feature",
  "properties": {
    "iso:country":"GB",
    "wof:name":"E5 0JG",
    "wof:placetype":"postalcode"
},
  "geometry": {"coordinates":[-0.04049297409383,51.55353479029102],"type":"Point"}
}