{
  "type": "Feature",
  "properties": {
    "iso:country":"GB",
    "wof:name":"LS9 9LH",
    "wof:placetype":"postalcode"
},
  "geometry": {"coordinates":[-1.51466653835548,53.79615980765406],"type":"Point"}
}