{
  "type": "Feature",
  "properties": {
    "iso:country":"GB",
    "wof:name":"RG8 7BB",
    "wof:placetype":"postalcode"
},
  "geometry": {"coordinates":[-1.08679976033139,51.48314126122214],"type":"Point"}
}