{
  "type": "Feature",
  "properties": {
    "iso:country": "GB",
    "wof:name": "RG8 7BB",
    "wof:placetype": "postalcode"
  },
  "geometry": {"coordinates":[-1.086779,51.483143],"type":"Point"}
}
