{
  "type": "Feature",
  "properties": {
    "iso:country":"GB",
    "wof:name":"M19 2PF",
    "wof:placetype":"postalcode"
},
  "geometry": {"coordinates":[-2.19231123427665,53.44147429108191],"type":"Point"}
}