{
  "type": "Feature",
  "properties": {
    "iso:country": "GB",
    "wof:name": "BN17 7JA",
    "wof:placetype": "postalcode"
  },
  "geometry": {"coordinates":[-0.553211,50.8191],"type":"Point"}
}
