{
  "type": "Feature",
  "properties": {
    "iso:country":"GB",
    "wof:name":"N20 9DH",
    "wof:placetype":"postalcode"
},
  "geometry": {"coordinates":[-0.16996580867829,51.63841835197459],"type":"Point"}
}