{
  "type": "Feature",
  "properties": {
    "iso:country":"GB",
    "wof:name":"RG41 2XP",
    "wof:placetype":"postalcode"
},
  "geometry": {"coordinates":[-0.8433779551014,51.41004708964647],"type":"Point"}
}