{
  "type": "Feature",
  "properties": {
    "iso:country": "GB",
    "wof:name": "CF71 7LZ",
    "wof:placetype": "postalcode"
  },
  "geometry": {"coordinates":[-3.44747,51.446681],"type":"Point"}
}
