{
  "type": "Feature",
  "properties": {
    "iso:country":"GB",
    "wof:name":"TW15 2PQ",
    "wof:placetype":"postalcode"
},
  "geometry": {"coordinates":[-0.46072331541426,51.43167032201364],"type":"Point"}
}