{
  "type": "Feature",
  "properties": {
    "iso:country":"GB",
    "wof:name":"LE8 5UA",
    "wof:placetype":"postalcode"
},
  "geometry": {"coordinates":[-1.15503052991597,52.55018060302425],"type":"Point"}
}