{
  "type": "Feature",
  "properties": {
    "date:inception_lower": "1980-01-01",
    "date:inception_upper": "1980-01-01",
    "iso:country": "GB",
    "wof:name": "CO15 5AP",
    "wof:placetype": "postalcode"
  },
  "geometry": {"coordinates":[1.174651,51.796568],"type":"Point"}
}
