{
  "type": "Feature",
  "properties": {
    "iso:country":"GB",
    "wof:name":"CO15 5AP",
    "wof:placetype":"postalcode"
},
  "geometry": {"coordinates":[1.17465140084993,51.79656829767797],"type":"Point"}
}