{
  "type": "Feature",
  "properties": {
    "iso:country":"GB",
    "wof:name":"LU7 9PU",
    "wof:placetype":"postalcode"
},
  "geometry": {"coordinates":[-0.57524326030074,51.90937079756281],"type":"Point"}
}