{
  "type": "Feature",
  "properties": {
    "date:inception_lower": "2017-05-01",
    "date:inception_upper": "2017-05-01",
    "iso:country": "GB",
    "wof:name": "SE10 0GX",
    "wof:placetype": "postalcode"
  },
  "geometry": {"coordinates":[0.018849,51.491937],"type":"Point"}
}
