{
  "type": "Feature",
  "properties": {
    "iso:country":"GB",
    "wof:name":"B37 6HH",
    "wof:placetype":"postalcode"
},
  "geometry": {"coordinates":[-1.7525054246987,52.49266748377013],"type":"Point"}
}