{
  "type": "Feature",
  "properties": {
    "iso:country":"GB",
    "wof:name":"N18 2BW",
    "wof:placetype":"postalcode"
},
  "geometry": {"coordinates":[-0.06168792233008,51.61074647595299],"type":"Point"}
}