{
  "type": "Feature",
  "properties": {
    "iso:country":"GB",
    "wof:name":"LD3 8BY",
    "wof:placetype":"postalcode"
},
  "geometry": {"coordinates":[-3.40002590887543,51.94547418521717],"type":"Point"}
}