{
  "type": "Feature",
  "properties": {
    "iso:country":"GB",
    "wof:name":"CF81 8SP",
    "wof:placetype":"postalcode"
},
  "geometry": {"coordinates":[-3.23197840368092,51.68905540528608],"type":"Point"}
}