{
  "type": "Feature",
  "properties": {
    "iso:country": "GB",
    "wof:name": "EX32 8NR",
    "wof:placetype": "postalcode"
  },
  "geometry": {"coordinates":[-4.057323,51.079493],"type":"Point"}
}
