{
  "type": "Feature",
  "properties": {
    "iso:country":"GB",
    "wof:name":"PE29 7HQ",
    "wof:placetype":"postalcode"
},
  "geometry": {"coordinates":[-0.18490833309797,52.33361759772297],"type":"Point"}
}