{
  "type": "Feature",
  "properties": {
    "date:inception_lower": "2000-06-01",
    "date:inception_upper": "2000-06-01",
    "iso:country": "GB",
    "wof:name": "PE29 7HQ",
    "wof:placetype": "postalcode"
  },
  "geometry": {"coordinates":[-0.184908,52.333618],"type":"Point"}
}
