{
  "type": "Feature",
  "properties": {
    "iso:country": "GB",
    "wof:name": "OL12 9RH",
    "wof:placetype": "postalcode"
  },
  "geometry": {"coordinates":[-2.143771,53.631251],"type":"Point"}
}
