{
  "type": "Feature",
  "properties": {
    "date:inception_lower": "1985-10-01",
    "date:inception_upper": "1985-10-01",
    "iso:country": "GB",
    "wof:name": "EX32 7EQ",
    "wof:placetype": "postalcode"
  },
  "geometry": {"coordinates":[-4.044369,51.080997],"type":"Point"}
}
