{
  "type": "Feature",
  "properties": {
    "iso:country":"GB",
    "wof:name":"G73 4PG",
    "wof:placetype":"postalcode"
},
  "geometry": {"coordinates":[-4.22194844034032,55.8167346243743],"type":"Point"}
}