{
  "type": "Feature",
  "properties": {
    "iso:country":"GB",
    "wof:name":"GU51 1DG",
    "wof:placetype":"postalcode"
},
  "geometry": {"coordinates":[-0.86055085121606,51.29288658355271],"type":"Point"}
}