{
  "type": "Feature",
  "properties": {
    "iso:country": "GB",
    "wof:name": "SK10 5SJ",
    "wof:placetype": "postalcode"
  },
  "geometry": {"coordinates":[-2.116907,53.306077],"type":"Point"}
}
