{
  "type": "Feature",
  "properties": {
    "date:inception_lower":"1980-01-01",
    "date:inception_upper":"1980-01-31",
    "iso:country":"GB",
    "wof:name":"SK10 5SJ",
    "wof:placetype":"postalcode"
},
  "geometry": {"coordinates":[-2.116907,53.306077],"type":"Point"}
}