{
  "type": "Feature",
  "properties": {
    "date:inception_lower": "1980-01-01",
    "date:inception_upper": "1980-01-01",
    "iso:country": "GB",
    "wof:name": "SK10 5SJ",
    "wof:placetype": "postalcode"
  },
  "geometry": {"coordinates":[-2.114732,53.30669],"type":"Point"}
}
