{
  "type": "Feature",
  "properties": {
    "iso:country":"GB",
    "wof:name":"BS16 7EX",
    "wof:placetype":"postalcode"
},
  "geometry": {"coordinates":[-2.48455714957721,51.49688691056762],"type":"Point"}
}