{
  "type": "Feature",
  "properties": {
    "iso:country":"GB",
    "wof:name":"RG12 8AS",
    "wof:placetype":"postalcode"
},
  "geometry": {"coordinates":[-0.78174330013846,51.40819083920496],"type":"Point"}
}