{
  "type": "Feature",
  "properties": {
    "date:inception_lower": "2007-07-01",
    "date:inception_upper": "2007-07-01",
    "iso:country": "GB",
    "wof:name": "RG12 8AS",
    "wof:placetype": "postalcode"
  },
  "geometry": {"coordinates":[-0.781743,51.408191],"type":"Point"}
}
