{
  "type": "Feature",
  "properties": {
    "iso:country": "GB",
    "wof:name": "RG12 8AS",
    "wof:placetype": "postalcode"
  },
  "geometry": {"coordinates":[-0.781743,51.408191],"type":"Point"}
}
