{
  "type": "Feature",
  "properties": {
    "iso:country": "GB",
    "wof:name": "YO12 7LB",
    "wof:placetype": "postalcode"
  },
  "geometry": {"coordinates":[-0.416116,54.282229],"type":"Point"}
}
