{
  "type": "Feature",
  "properties": {
    "iso:country": "GB",
    "wof:name": "TD1 2LF",
    "wof:placetype": "postalcode"
  },
  "geometry": {"coordinates":[-2.785116,55.612794],"type":"Point"}
}
