{
  "type": "Feature",
  "properties": {
    "iso:country":"GB",
    "wof:name":"TD1 2LF",
    "wof:placetype":"postalcode"
},
  "geometry": {"coordinates":[-2.78511611452507,55.61279431993513],"type":"Point"}
}