{
  "type": "Feature",
  "properties": {
    "date:inception_lower": "1980-01-01",
    "date:inception_upper": "1980-01-01",
    "iso:country": "GB",
    "wof:name": "TR3 6PE",
    "wof:placetype": "postalcode"
  },
  "geometry": {"coordinates":[-5.090686,50.215573],"type":"Point"}
}
