{
  "type": "Feature",
  "properties": {
    "iso:country":"GB",
    "wof:name":"CH47 1JE",
    "wof:placetype":"postalcode"
},
  "geometry": {"coordinates":[-3.1861784912463,53.39271579630191],"type":"Point"}
}