{
  "type": "Feature",
  "properties": {
    "iso:country": "GB",
    "wof:name": "CH47 1JE",
    "wof:placetype": "postalcode"
  },
  "geometry": {"coordinates":[-3.186178,53.392716],"type":"Point"}
}
