{
  "type": "Feature",
  "properties": {
    "iso:country":"GB",
    "wof:name":"GL8 8RJ",
    "wof:placetype":"postalcode"
},
  "geometry": {"coordinates":[-2.13428668901117,51.62635237610026],"type":"Point"}
}