{
  "type": "Feature",
  "properties": {
    "iso:country": "GB",
    "wof:name": "HD3 3QF",
    "wof:placetype": "postalcode"
  },
  "geometry": {"coordinates":[-1.829489,53.658496],"type":"Point"}
}
