{
  "type": "Feature",
  "properties": {
    "iso:country":"GB",
    "wof:name":"HD3 3QF",
    "wof:placetype":"postalcode"
},
  "geometry": {"coordinates":[-1.8294895095872,53.65849574334665],"type":"Point"}
}