{
  "type": "Feature",
  "properties": {
    "iso:country":"GB",
    "wof:name":"FK2 7FL",
    "wof:placetype":"postalcode"
},
  "geometry": {"coordinates":[-3.78009878925751,56.01011505862337],"type":"Point"}
}