{
  "type": "Feature",
  "properties": {
    "iso:country": "GB",
    "wof:name": "FK2 7FL",
    "wof:placetype": "postalcode"
  },
  "geometry": {"coordinates":[-3.780099,56.010115],"type":"Point"}
}
