{
  "type": "Feature",
  "properties": {
    "iso:country":"GB",
    "wof:name":"ST8 7JR",
    "wof:placetype":"postalcode"
},
  "geometry": {"coordinates":[-2.12882085470038,53.12594713435264],"type":"Point"}
}