{
  "type": "Feature",
  "properties": {
    "iso:country": "GB",
    "wof:name": "ST8 7JR",
    "wof:placetype": "postalcode"
  },
  "geometry": {"coordinates":[-2.128821,53.125947],"type":"Point"}
}
