{
  "type": "Feature",
  "properties": {
    "iso:country":"GB",
    "wof:name":"S44 6ND",
    "wof:placetype":"postalcode"
},
  "geometry": {"coordinates":[-1.29406017730028,53.23467146227567],"type":"Point"}
}