{
  "type": "Feature",
  "properties": {
    "iso:country":"GB",
    "wof:name":"BS9 2QZ",
    "wof:placetype":"postalcode"
},
  "geometry": {"coordinates":[-2.65119270394113,51.49348119378683],"type":"Point"}
}