{
  "type": "Feature",
  "properties": {
    "iso:country":"GB",
    "wof:name":"KY6 3NE",
    "wof:placetype":"postalcode"
},
  "geometry": {"coordinates":[-3.22279337627656,56.20209704638939],"type":"Point"}
}