{
  "type": "Feature",
  "properties": {
    "date:inception_lower": "1980-01-01",
    "date:inception_upper": "1980-01-01",
    "iso:country": "GB",
    "wof:name": "KY6 3NE",
    "wof:placetype": "postalcode"
  },
  "geometry": {"coordinates":[-3.222793,56.202097],"type":"Point"}
}
