{
  "type": "Feature",
  "properties": {
    "date:inception_lower":"1990-02-01",
    "date:inception_upper":"1990-02-28",
    "iso:country":"GB",
    "wof:name":"SY22 6XN",
    "wof:placetype":"postalcode"
},
  "geometry": {"coordinates":[-3.198851,52.775355],"type":"Point"}
}