{
  "type": "Feature",
  "properties": {
    "iso:country":"GB",
    "wof:name":"SY22 6XN",
    "wof:placetype":"postalcode"
},
  "geometry": {"coordinates":[-3.19885146441431,52.77535538832801],"type":"Point"}
}