{
  "type": "Feature",
  "properties": {
    "date:inception_lower": "1990-02-01",
    "date:inception_upper": "1990-02-01",
    "iso:country": "GB",
    "wof:name": "BA13 3QY",
    "wof:placetype": "postalcode"
  },
  "geometry": {"coordinates":[-2.190852,51.259562],"type":"Point"}
}
