{
  "type": "Feature",
  "properties": {
    "iso:country":"GB",
    "wof:name":"BA13 3QY",
    "wof:placetype":"postalcode"
},
  "geometry": {"coordinates":[-2.19085197411791,51.25956202649576],"type":"Point"}
}