{
  "type": "Feature",
  "properties": {
    "iso:country": "GB",
    "wof:name": "LL15 1NU",
    "wof:placetype": "postalcode"
  },
  "geometry": {"coordinates":[-3.31813,53.114076],"type":"Point"}
}
