{
  "type": "Feature",
  "properties": {
    "iso:country":"GB",
    "wof:name":"LL15 1NU",
    "wof:placetype":"postalcode"
},
  "geometry": {"coordinates":[-3.31815917743255,53.11406049170855],"type":"Point"}
}