{
  "type": "Feature",
  "properties": {
    "date:inception_lower":"1980-01-01",
    "date:inception_upper":"1980-01-31",
    "iso:country":"GB",
    "wof:name":"CT17 0SP",
    "wof:placetype":"postalcode"
},
  "geometry": {"coordinates":[1.302428,51.132975],"type":"Point"}
}