{
  "type": "Feature",
  "properties": {
    "iso:country":"GB",
    "wof:name":"CT17 0SP",
    "wof:placetype":"postalcode"
},
  "geometry": {"coordinates":[1.30239609817029,51.13296785720144],"type":"Point"}
}