{
  "type": "Feature",
  "properties": {
    "date:inception_lower": "1990-07-01",
    "date:inception_upper": "1990-07-01",
    "iso:country": "GB",
    "wof:name": "SY5 0DG",
    "wof:placetype": "postalcode"
  },
  "geometry": {"coordinates":[-2.924246,52.638871],"type":"Point"}
}
