{
  "type": "Feature",
  "properties": {
    "iso:country":"GB",
    "wof:name":"SY5 0DG",
    "wof:placetype":"postalcode"
},
  "geometry": {"coordinates":[-2.92426321365587,52.63886472077351],"type":"Point"}
}