{
  "type": "Feature",
  "properties": {
    "iso:country":"GB",
    "wof:name":"CA3 9PF",
    "wof:placetype":"postalcode"
},
  "geometry": {"coordinates":[-2.9533105717889,54.90613097272922],"type":"Point"}
}