{
  "type": "Feature",
  "properties": {
    "iso:country":"GB",
    "wof:name":"WD17 2NU",
    "wof:placetype":"postalcode"
},
  "geometry": {"coordinates":[-0.3918275785881,51.65222324858885],"type":"Point"}
}