{
  "type": "Feature",
  "properties": {
    "date:inception_lower":"1980-01-01",
    "date:inception_upper":"1980-01-31",
    "iso:country":"GB",
    "wof:name":"NN16 0RY",
    "wof:placetype":"postalcode"
},
  "geometry": {"coordinates":[-0.721964,52.399192],"type":"Point"}
}