{
  "type": "Feature",
  "properties": {
    "iso:country":"GB",
    "wof:name":"WF9 4QN",
    "wof:placetype":"postalcode"
},
  "geometry": {"coordinates":[-1.36031668285014,53.61437662463979],"type":"Point"}
}