{
  "type": "Feature",
  "properties": {
    "iso:country": "GB",
    "wof:name": "WF9 4QN",
    "wof:placetype": "postalcode"
  },
  "geometry": {"coordinates":[-1.360317,53.614377],"type":"Point"}
}
