{
  "type": "Feature",
  "properties": {
    "date:inception_lower": "1980-01-01",
    "date:inception_upper": "1980-01-01",
    "iso:country": "GB",
    "wof:name": "CO4 3DE",
    "wof:placetype": "postalcode"
  },
  "geometry": {"coordinates":[0.926861,51.894837],"type":"Point"}
}
