{
  "type": "Feature",
  "properties": {
    "iso:country":"GB",
    "wof:name":"CO4 3DE",
    "wof:placetype":"postalcode"
},
  "geometry": {"coordinates":[0.92686111586239,51.8948369296665],"type":"Point"}
}