{
  "type": "Feature",
  "properties": {
    "date:inception_lower":"1980-01-01",
    "date:inception_upper":"1980-01-31",
    "iso:country":"GB",
    "wof:name":"CV9 1LT",
    "wof:placetype":"postalcode"
},
  "geometry": {"coordinates":[-1.538945,52.579842],"type":"Point"}
}