{
  "type": "Feature",
  "properties": {
    "iso:country":"GB",
    "wof:name":"WF7 5BJ",
    "wof:placetype":"postalcode"
},
  "geometry": {"coordinates":[-1.35901993127885,53.67703647652259],"type":"Point"}
}