{
  "type": "Feature",
  "properties": {
    "iso:country": "GB",
    "wof:name": "WF7 5BJ",
    "wof:placetype": "postalcode"
  },
  "geometry": {"coordinates":[-1.359036,53.676974],"type":"Point"}
}
