{
  "type": "Feature",
  "properties": {
    "iso:country":"GB",
    "wof:name":"EH32 0RF",
    "wof:placetype":"postalcode"
},
  "geometry": {"coordinates":[-2.86351182943876,56.00841259887367],"type":"Point"}
}