{
  "type": "Feature",
  "properties": {
    "iso:country": "GB",
    "wof:name": "EH32 0RF",
    "wof:placetype": "postalcode"
  },
  "geometry": {"coordinates":[-2.863512,56.008413],"type":"Point"}
}
