{
  "type": "Feature",
  "properties": {
    "iso:country": "GB",
    "wof:name": "WR6 6SB",
    "wof:placetype": "postalcode"
  },
  "geometry": {"coordinates":[-2.392205,52.286342],"type":"Point"}
}
