{
  "type": "Feature",
  "properties": {
    "iso:country": "GB",
    "wof:name": "HU4 7JR",
    "wof:placetype": "postalcode"
  },
  "geometry": {"coordinates":[-0.416447,53.734174],"type":"Point"}
}
