{
  "type": "Feature",
  "properties": {
    "iso:country":"GB",
    "wof:name":"HU4 7JR",
    "wof:placetype":"postalcode"
},
  "geometry": {"coordinates":[-0.41644717293908,53.73417401086062],"type":"Point"}
}