{
  "type": "Feature",
  "properties": {
    "date:inception_lower":"1987-04-01",
    "date:inception_upper":"1987-04-30",
    "iso:country":"GB",
    "wof:name":"LN6 0EH",
    "wof:placetype":"postalcode"
},
  "geometry": {"coordinates":[-0.605299,53.219955],"type":"Point"}
}