{
  "type": "Feature",
  "properties": {
    "iso:country": "GB",
    "wof:name": "LN6 0EH",
    "wof:placetype": "postalcode"
  },
  "geometry": {"coordinates":[-0.605299,53.219955],"type":"Point"}
}
