{
  "type": "Feature",
  "properties": {
    "iso:country":"GB",
    "wof:name":"BA6 9AW",
    "wof:placetype":"postalcode"
},
  "geometry": {"coordinates":[-2.70265810098263,51.16014282890082],"type":"Point"}
}