{
  "type": "Feature",
  "properties": {
    "iso:country": "GB",
    "wof:name": "CV47 2XP",
    "wof:placetype": "postalcode"
  },
  "geometry": {"coordinates":[-1.380325,52.198023],"type":"Point"}
}
