{
  "type": "Feature",
  "properties": {
    "iso:country":"GB",
    "wof:name":"SL9 8AZ",
    "wof:placetype":"postalcode"
},
  "geometry": {"coordinates":[-0.54686209891637,51.58351327192428],"type":"Point"}
}