{
  "type": "Feature",
  "properties": {
    "iso:country": "GB",
    "wof:name": "SL9 8AZ",
    "wof:placetype": "postalcode"
  },
  "geometry": {"coordinates":[-0.546862,51.583513],"type":"Point"}
}
