{
  "type": "Feature",
  "properties": {
    "iso:country": "GB",
    "wof:name": "SS15 6JY",
    "wof:placetype": "postalcode"
  },
  "geometry": {"coordinates":[0.409211,51.573013],"type":"Point"}
}
