{
  "type": "Feature",
  "properties": {
    "iso:country":"GB",
    "wof:name":"SS15 6JY",
    "wof:placetype":"postalcode"
},
  "geometry": {"coordinates":[0.40921089903947,51.57301258077992],"type":"Point"}
}