{
  "type": "Feature",
  "properties": {
    "date:inception_lower": "2000-12-01",
    "date:inception_upper": "2000-12-01",
    "iso:country": "GB",
    "wof:name": "W1D 6PR",
    "wof:placetype": "postalcode"
  },
  "geometry": {"coordinates":[-0.132167,51.511165],"type":"Point"}
}
