{
  "type": "Feature",
  "properties": {
    "iso:country":"GB",
    "wof:name":"BN10 8LG",
    "wof:placetype":"postalcode"
},
  "geometry": {"coordinates":[-0.0041586058676,50.7907992655618],"type":"Point"}
}