{
  "type": "Feature",
  "properties": {
    "iso:country": "GB",
    "wof:name": "LD1 6AU",
    "wof:placetype": "postalcode"
  },
  "geometry": {"coordinates":[-3.381877,52.238586],"type":"Point"}
}
