{
  "type": "Feature",
  "properties": {
    "iso:country":"GB",
    "wof:name":"LD1 6AU",
    "wof:placetype":"postalcode"
},
  "geometry": {"coordinates":[-3.38187673352109,52.23858571690854],"type":"Point"}
}