{
  "type": "Feature",
  "properties": {
    "iso:country": "GB",
    "wof:name": "PE19 8JP",
    "wof:placetype": "postalcode"
  },
  "geometry": {"coordinates":[-0.290997,52.227646],"type":"Point"}
}
