{
  "type": "Feature",
  "properties": {
    "iso:country":"GB",
    "wof:name":"PE19 8JP",
    "wof:placetype":"postalcode"
},
  "geometry": {"coordinates":[-0.29099684841706,52.22764644873187],"type":"Point"}
}