{
  "type": "Feature",
  "properties": {
    "date:inception_lower": "2000-06-01",
    "date:inception_upper": "2000-06-01",
    "iso:country": "GB",
    "wof:name": "PE19 8JP",
    "wof:placetype": "postalcode"
  },
  "geometry": {"coordinates":[-0.290997,52.227646],"type":"Point"}
}
