{
  "type": "Feature",
  "properties": {
    "iso:country":"GB",
    "wof:name":"TA24 8AQ",
    "wof:placetype":"postalcode"
},
  "geometry": {"coordinates":[-3.49147960020113,51.20486342753657],"type":"Point"}
}