{
  "type": "Feature",
  "properties": {
    "iso:country": "GB",
    "wof:name": "TA24 8AQ",
    "wof:placetype": "postalcode"
  },
  "geometry": {"coordinates":[-3.49148,51.204863],"type":"Point"}
}
