{
  "type": "Feature",
  "properties": {
    "iso:country": "GB",
    "wof:name": "BA5 2ES",
    "wof:placetype": "postalcode"
  },
  "geometry": {"coordinates":[-2.663343,51.20473],"type":"Point"}
}
