{
  "type": "Feature",
  "properties": {
    "iso:country": "GB",
    "wof:name": "TF2 7EU",
    "wof:placetype": "postalcode"
  },
  "geometry": {"coordinates":[-2.453699,52.713187],"type":"Point"}
}
