{
  "type": "Feature",
  "properties": {
    "date:inception_lower":"1980-01-01",
    "date:inception_upper":"1980-01-31",
    "iso:country":"GB",
    "wof:name":"TF2 7EU",
    "wof:placetype":"postalcode"
},
  "geometry": {"coordinates":[-2.453699,52.713187],"type":"Point"}
}