{
  "type": "Feature",
  "properties": {
    "iso:country":"GB",
    "wof:name":"NG5 6HY",
    "wof:placetype":"postalcode"
},
  "geometry": {"coordinates":[-1.13726432226299,53.00213943755086],"type":"Point"}
}