{
  "type": "Feature",
  "properties": {
    "date:inception_lower":"1980-01-01",
    "date:inception_upper":"1980-01-31",
    "iso:country":"GB",
    "wof:name":"G84 9BT",
    "wof:placetype":"postalcode"
},
  "geometry": {"coordinates":[-4.726729,56.011989],"type":"Point"}
}