{
  "type": "Feature",
  "properties": {
    "iso:country": "GB",
    "wof:name": "G66 3LN",
    "wof:placetype": "postalcode"
  },
  "geometry": {"coordinates":[-4.121156,55.93471],"type":"Point"}
}
