{
  "type": "Feature",
  "properties": {
    "date:inception_lower": "1980-01-01",
    "date:inception_upper": "1980-01-01",
    "iso:country": "GB",
    "wof:name": "SP10 5ER",
    "wof:placetype": "postalcode"
  },
  "geometry": {"coordinates":[-1.466358,51.219433],"type":"Point"}
}
