{
  "type": "Feature",
  "properties": {
    "iso:country":"GB",
    "wof:name":"LS4 2AG",
    "wof:placetype":"postalcode"
},
  "geometry": {"coordinates":[-1.5736960476276,53.80317898099575],"type":"Point"}
}