{
  "type": "Feature",
  "properties": {
    "date:inception_lower":"2004-10-01",
    "date:inception_upper":"2004-10-31",
    "iso:country":"GB",
    "wof:name":"E7 0EQ",
    "wof:placetype":"postalcode"
},
  "geometry": {"coordinates":[0.022853,51.550409],"type":"Point"}
}