{
  "type": "Feature",
  "properties": {
    "iso:country": "GB",
    "wof:name": "E7 0EQ",
    "wof:placetype": "postalcode"
  },
  "geometry": {"coordinates":[0.022853,51.550409],"type":"Point"}
}
