{
  "type": "Feature",
  "properties": {
    "iso:country":"GB",
    "wof:name":"E7 0EQ",
    "wof:placetype":"postalcode"
},
  "geometry": {"coordinates":[0.02285290523796,51.55040934249026],"type":"Point"}
}