{
  "type": "Feature",
  "properties": {
    "iso:country":"GB",
    "wof:name":"CM3 1LX",
    "wof:placetype":"postalcode"
},
  "geometry": {"coordinates":[0.49554433249286,51.81495772866941],"type":"Point"}
}