{
  "type": "Feature",
  "properties": {
    "iso:country":"GB",
    "wof:name":"SE3 0HD",
    "wof:placetype":"postalcode"
},
  "geometry": {"coordinates":[0.01826453166998,51.46592098970963],"type":"Point"}
}