{
  "type": "Feature",
  "properties": {
    "iso:country":"GB",
    "wof:name":"OL2 5UB",
    "wof:placetype":"postalcode"
},
  "geometry": {"coordinates":[-2.12906262296724,53.56861059753264],"type":"Point"}
}