{
  "type": "Feature",
  "properties": {
    "iso:country":"GB",
    "wof:name":"SM1 2TB",
    "wof:placetype":"postalcode"
},
  "geometry": {"coordinates":[-0.20458252071861,51.36406256721396],"type":"Point"}
}