{
  "type": "Feature",
  "properties": {
    "date:inception_lower": "1980-01-01",
    "date:inception_upper": "1980-01-01",
    "iso:country": "GB",
    "wof:name": "SM1 2TB",
    "wof:placetype": "postalcode"
  },
  "geometry": {"coordinates":[-0.204582,51.364063],"type":"Point"}
}
