{
  "type": "Feature",
  "properties": {
    "iso:country":"GB",
    "wof:name":"IP7 7PS",
    "wof:placetype":"postalcode"
},
  "geometry": {"coordinates":[0.88359702932367,52.13108389473793],"type":"Point"}
}