{
  "type": "Feature",
  "properties": {
    "iso:country":"GB",
    "wof:name":"BH7 6BW",
    "wof:placetype":"postalcode"
},
  "geometry": {"coordinates":[-1.81452860848535,50.73553014006679],"type":"Point"}
}