{
  "type": "Feature",
  "properties": {
    "iso:country": "GB",
    "wof:name": "NR32 5BL",
    "wof:placetype": "postalcode"
  },
  "geometry": {"coordinates":[1.708302,52.513989],"type":"Point"}
}
