{
  "type": "Feature",
  "properties": {
    "iso:country":"GB",
    "wof:name":"W7 3JD",
    "wof:placetype":"postalcode"
},
  "geometry": {"coordinates":[-0.33939491566763,51.5101272163396],"type":"Point"}
}