{
  "type": "Feature",
  "properties": {
    "date:inception_lower":"1980-01-01",
    "date:inception_upper":"1980-01-31",
    "iso:country":"GB",
    "wof:name":"EH15 3DD",
    "wof:placetype":"postalcode"
},
  "geometry": {"coordinates":[-3.113937,55.941881],"type":"Point"}
}