{
  "type": "Feature",
  "properties": {
    "iso:country": "GB",
    "wof:name": "NN15 7PP",
    "wof:placetype": "postalcode"
  },
  "geometry": {"coordinates":[-0.725637,52.398252],"type":"Point"}
}
