{
  "type": "Feature",
  "properties": {
    "iso:country":"GB",
    "wof:name":"IP6 8RF",
    "wof:placetype":"postalcode"
},
  "geometry": {"coordinates":[1.07604695496039,52.12369910068332],"type":"Point"}
}