{
  "type": "Feature",
  "properties": {
    "date:inception_lower": "2000-06-01",
    "date:inception_upper": "2000-06-01",
    "iso:country": "GB",
    "wof:name": "IP6 8RF",
    "wof:placetype": "postalcode"
  },
  "geometry": {"coordinates":[1.076584,52.123854],"type":"Point"}
}
