{
  "type": "Feature",
  "properties": {
    "iso:country":"GB",
    "wof:name":"WR1 3NS",
    "wof:placetype":"postalcode"
},
  "geometry": {"coordinates":[-2.22697990772414,52.1922285580266],"type":"Point"}
}