{
  "type": "Feature",
  "properties": {
    "date:inception_lower": "1980-01-01",
    "date:inception_upper": "1980-01-01",
    "iso:country": "GB",
    "wof:name": "WR1 3NS",
    "wof:placetype": "postalcode"
  },
  "geometry": {"coordinates":[-2.22698,52.192229],"type":"Point"}
}
