{
  "type": "Feature",
  "properties": {
    "iso:country": "GB",
    "wof:name": "NG31 9BD",
    "wof:placetype": "postalcode"
  },
  "geometry": {"coordinates":[-0.631853,52.917182],"type":"Point"}
}
