{
  "type": "Feature",
  "properties": {
    "iso:country":"GB",
    "wof:name":"NG8 6JB",
    "wof:placetype":"postalcode"
},
  "geometry": {"coordinates":[-1.21597591111821,52.97571603798449],"type":"Point"}
}