{
  "type": "Feature",
  "properties": {
    "date:inception_lower": "1994-12-01",
    "date:inception_upper": "1994-12-01",
    "iso:country": "GB",
    "wof:name": "SO19 8AZ",
    "wof:placetype": "postalcode"
  },
  "geometry": {"coordinates":[-1.350404,50.907517],"type":"Point"}
}
