{
  "type": "Feature",
  "properties": {
    "date:inception_lower": "1980-01-01",
    "date:inception_upper": "1980-01-01",
    "iso:country": "GB",
    "wof:name": "FY7 6DN",
    "wof:placetype": "postalcode"
  },
  "geometry": {"coordinates":[-3.006544,53.927739],"type":"Point"}
}
