{
  "type": "Feature",
  "properties": {
    "iso:country":"GB",
    "wof:name":"HG3 3QU",
    "wof:placetype":"postalcode"
},
  "geometry": {"coordinates":[-1.49842029832043,54.08986060725682],"type":"Point"}
}