{
  "type": "Feature",
  "properties": {
    "date:inception_lower":"1980-01-01",
    "date:inception_upper":"1980-01-31",
    "iso:country":"GB",
    "wof:name":"HG3 3QU",
    "wof:placetype":"postalcode"
},
  "geometry": {"coordinates":[-1.49842,54.089861],"type":"Point"}
}