{
  "type": "Feature",
  "properties": {
    "iso:country":"GB",
    "wof:name":"SS14 2JX",
    "wof:placetype":"postalcode"
},
  "geometry": {"coordinates":[0.46360804464314,51.57732373341121],"type":"Point"}
}