{
  "type": "Feature",
  "properties": {
    "iso:country":"GB",
    "wof:name":"RH16 3JP",
    "wof:placetype":"postalcode"
},
  "geometry": {"coordinates":[-0.09753321610198,50.9988124083584],"type":"Point"}
}