{
  "type": "Feature",
  "properties": {
    "iso:country":"GB",
    "wof:name":"HA7 4SL",
    "wof:placetype":"postalcode"
},
  "geometry": {"coordinates":[-0.29840206153798,51.61857986194712],"type":"Point"}
}