{
  "type": "Feature",
  "properties": {
    "iso:country": "GB",
    "wof:name": "PL21 0YB",
    "wof:placetype": "postalcode"
  },
  "geometry": {"coordinates":[-3.915498,50.385994],"type":"Point"}
}
