{
  "type": "Feature",
  "properties": {
    "iso:country":"GB",
    "wof:name":"PL21 0YB",
    "wof:placetype":"postalcode"
},
  "geometry": {"coordinates":[-3.91549843939134,50.38599365752868],"type":"Point"}
}