{
  "type": "Feature",
  "properties": {
    "date:inception_lower":"1980-01-01",
    "date:inception_upper":"1980-01-31",
    "iso:country":"GB",
    "wof:name":"LN2 3PA",
    "wof:placetype":"postalcode"
},
  "geometry": {"coordinates":[-0.478093,53.315775],"type":"Point"}
}