{
  "type": "Feature",
  "properties": {
    "iso:country":"GB",
    "wof:name":"LN2 3PA",
    "wof:placetype":"postalcode"
},
  "geometry": {"coordinates":[-0.4780925655193,53.31577496583636],"type":"Point"}
}