{
  "type": "Feature",
  "properties": {
    "iso:country":"GB",
    "wof:name":"IP9 1AG",
    "wof:placetype":"postalcode"
},
  "geometry": {"coordinates":[1.15506599991181,52.00989614042334],"type":"Point"}
}