{
  "type": "Feature",
  "properties": {
    "iso:country":"GB",
    "wof:name":"BR8 7NW",
    "wof:placetype":"postalcode"
},
  "geometry": {"coordinates":[0.19396876544178,51.40398584646339],"type":"Point"}
}