{
  "type": "Feature",
  "properties": {
    "date:inception_lower": "1980-01-01",
    "date:inception_upper": "1980-01-01",
    "iso:country": "GB",
    "wof:name": "BR8 7NW",
    "wof:placetype": "postalcode"
  },
  "geometry": {"coordinates":[0.194008,51.40395],"type":"Point"}
}
