{
  "type": "Feature",
  "properties": {
    "iso:country": "GB",
    "wof:name": "SY8 1PN",
    "wof:placetype": "postalcode"
  },
  "geometry": {"coordinates":[-2.717598,52.363235],"type":"Point"}
}
