{
  "type": "Feature",
  "properties": {
    "iso:country":"GB",
    "wof:name":"SY8 1PN",
    "wof:placetype":"postalcode"
},
  "geometry": {"coordinates":[-2.71759910679902,52.36322193496786],"type":"Point"}
}