{
  "type": "Feature",
  "properties": {
    "iso:country": "GB",
    "wof:name": "SY8 1PN",
    "wof:placetype": "postalcode"
  },
  "geometry": {"coordinates":[-2.717465,52.363236],"type":"Point"}
}
