{
  "type": "Feature",
  "properties": {
    "date:inception_lower": "1980-01-01",
    "date:inception_upper": "1980-01-01",
    "iso:country": "GB",
    "wof:name": "KY8 5LJ",
    "wof:placetype": "postalcode"
  },
  "geometry": {"coordinates":[-3.054251,56.214889],"type":"Point"}
}
