{
  "type": "Feature",
  "properties": {
    "iso:country":"GB",
    "wof:name":"KY8 5LJ",
    "wof:placetype":"postalcode"
},
  "geometry": {"coordinates":[-3.05425104097842,56.21488914167568],"type":"Point"}
}