{
  "type": "Feature",
  "properties": {
    "iso:country":"GB",
    "wof:name":"DG9 8UB",
    "wof:placetype":"postalcode"
},
  "geometry": {"coordinates":[-5.11189431172031,54.84840024145776],"type":"Point"}
}