{
  "type": "Feature",
  "properties": {
    "iso:country": "GB",
    "wof:name": "DG9 8UB",
    "wof:placetype": "postalcode"
  },
  "geometry": {"coordinates":[-5.111894,54.8484],"type":"Point"}
}
