{
  "type": "Feature",
  "properties": {
    "date:inception_lower":"1986-02-01",
    "date:inception_upper":"1986-02-28",
    "iso:country":"GB",
    "wof:name":"DG9 8UB",
    "wof:placetype":"postalcode"
},
  "geometry": {"coordinates":[-5.111894,54.8484],"type":"Point"}
}