{
  "type": "Feature",
  "properties": {
    "iso:country": "GB",
    "wof:name": "WS15 4AG",
    "wof:placetype": "postalcode"
  },
  "geometry": {"coordinates":[-1.881924,52.740211],"type":"Point"}
}
