{
  "type": "Feature",
  "properties": {
    "date:inception_lower": "1980-01-01",
    "date:inception_upper": "1980-01-01",
    "iso:country": "GB",
    "wof:name": "NP4 7LL",
    "wof:placetype": "postalcode"
  },
  "geometry": {"coordinates":[-3.067421,51.73708],"type":"Point"}
}
