{
  "type": "Feature",
  "properties": {
    "iso:country":"GB",
    "wof:name":"NP4 7LL",
    "wof:placetype":"postalcode"
},
  "geometry": {"coordinates":[-3.06742093658684,51.73708043732077],"type":"Point"}
}