{
  "type": "Feature",
  "properties": {
    "iso:country":"GB",
    "wof:name":"E11 1EA",
    "wof:placetype":"postalcode"
},
  "geometry": {"coordinates":[-0.00486997950414,51.56920201950473],"type":"Point"}
}