{
  "type": "Feature",
  "properties": {
    "iso:country":"GB",
    "wof:name":"LL11 3DW",
    "wof:placetype":"postalcode"
},
  "geometry": {"coordinates":[-3.09380569882747,53.05798309579771],"type":"Point"}
}