{
  "type": "Feature",
  "properties": {
    "iso:country": "GB",
    "wof:name": "LL11 3DW",
    "wof:placetype": "postalcode"
  },
  "geometry": {"coordinates":[-3.093806,53.057983],"type":"Point"}
}
