{
  "type": "Feature",
  "properties": {
    "iso:country":"GB",
    "wof:name":"SO16 3NN",
    "wof:placetype":"postalcode"
},
  "geometry": {"coordinates":[-1.40452481024525,50.94623923052077],"type":"Point"}
}