{
  "type": "Feature",
  "properties": {
    "date:inception_lower":"1994-12-01",
    "date:inception_upper":"1994-12-31",
    "iso:country":"GB",
    "wof:name":"SO16 3NN",
    "wof:placetype":"postalcode"
},
  "geometry": {"coordinates":[-1.404525,50.946239],"type":"Point"}
}