{
  "type": "Feature",
  "properties": {
    "iso:country": "GB",
    "wof:name": "SO16 3NN",
    "wof:placetype": "postalcode"
  },
  "geometry": {"coordinates":[-1.404525,50.946239],"type":"Point"}
}
