{
  "type": "Feature",
  "properties": {
    "iso:country":"GB",
    "wof:name":"YO31 7QR",
    "wof:placetype":"postalcode"
},
  "geometry": {"coordinates":[-1.07867889194624,53.96462200521091],"type":"Point"}
}