{
  "type": "Feature",
  "properties": {
    "iso:country": "GB",
    "wof:name": "BN13 3FN",
    "wof:placetype": "postalcode"
  },
  "geometry": {"coordinates":[-0.42766,50.833349],"type":"Point"}
}
