{
  "type": "Feature",
  "properties": {
    "date:inception_lower": "1999-06-01",
    "date:inception_upper": "1999-06-01",
    "iso:country": "GB",
    "wof:name": "CH48 0RT",
    "wof:placetype": "postalcode"
  },
  "geometry": {"coordinates":[-3.18387,53.368046],"type":"Point"}
}
