{
  "type": "Feature",
  "properties": {
    "iso:country":"GB",
    "wof:name":"CT15 6EQ",
    "wof:placetype":"postalcode"
},
  "geometry": {"coordinates":[1.37831310878233,51.14883301491468],"type":"Point"}
}