{
  "type": "Feature",
  "properties": {
    "iso:country": "GB",
    "wof:name": "SW15 3SL",
    "wof:placetype": "postalcode"
  },
  "geometry": {"coordinates":[-0.214767,51.452687],"type":"Point"}
}
