{
  "type": "Feature",
  "properties": {
    "iso:country":"GB",
    "wof:name":"M33 4WZ",
    "wof:placetype":"postalcode"
},
  "geometry": {"coordinates":[-2.36356126894108,53.41041549119889],"type":"Point"}
}