{
  "type": "Feature",
  "properties": {
    "date:inception_lower": "2004-05-01",
    "date:inception_upper": "2004-05-01",
    "iso:country": "GB",
    "wof:name": "RH18 5BT",
    "wof:placetype": "postalcode"
  },
  "geometry": {"coordinates":[0.037621,51.090846],"type":"Point"}
}
