{
  "type": "Feature",
  "properties": {
    "iso:country": "GB",
    "wof:name": "EX15 1RH",
    "wof:placetype": "postalcode"
  },
  "geometry": {"coordinates":[-3.385151,50.827522],"type":"Point"}
}
