{
  "type": "Feature",
  "properties": {
    "iso:country":"GB",
    "wof:name":"EX15 1RH",
    "wof:placetype":"postalcode"
},
  "geometry": {"coordinates":[-3.38515128414574,50.82752178150997],"type":"Point"}
}