{
  "type": "Feature",
  "properties": {
    "iso:country":"GB",
    "wof:name":"WA4 1BW",
    "wof:placetype":"postalcode"
},
  "geometry": {"coordinates":[-2.58478815096244,53.38271435011536],"type":"Point"}
}