{
  "type": "Feature",
  "properties": {
    "iso:country": "GB",
    "wof:name": "TN12 0DE",
    "wof:placetype": "postalcode"
  },
  "geometry": {"coordinates":[0.554434,51.192766],"type":"Point"}
}
