{
  "type": "Feature",
  "properties": {
    "iso:country":"GB",
    "wof:name":"ME17 4DD",
    "wof:placetype":"postalcode"
},
  "geometry": {"coordinates":[0.53335641673842,51.20799222742907],"type":"Point"}
}