{
  "type": "Feature",
  "properties": {
    "date:inception_lower": "1980-01-01",
    "date:inception_upper": "1980-01-01",
    "iso:country": "GB",
    "wof:name": "ME17 4DD",
    "wof:placetype": "postalcode"
  },
  "geometry": {"coordinates":[0.533356,51.207992],"type":"Point"}
}
