{
  "type": "Feature",
  "properties": {
    "iso:country":"GB",
    "wof:name":"TS23 2DU",
    "wof:placetype":"postalcode"
},
  "geometry": {"coordinates":[-1.28930007071653,54.61374043253156],"type":"Point"}
}