{
  "type": "Feature",
  "properties": {
    "iso:country":"GB",
    "wof:name":"EX34 8EP",
    "wof:placetype":"postalcode"
},
  "geometry": {"coordinates":[-4.12260484897757,51.1958501480255],"type":"Point"}
}