{
  "type": "Feature",
  "properties": {
    "iso:country":"GB",
    "wof:name":"PH16 5QZ",
    "wof:placetype":"postalcode"
},
  "geometry": {"coordinates":[-3.73869908869897,56.7133192126543],"type":"Point"}
}