{
  "type": "Feature",
  "properties": {
    "iso:country": "GB",
    "wof:name": "RG10 0BN",
    "wof:placetype": "postalcode"
  },
  "geometry": {"coordinates":[-0.848694,51.469743],"type":"Point"}
}
