{
  "type": "Feature",
  "properties": {
    "iso:country":"GB",
    "wof:name":"BR1 2DB",
    "wof:placetype":"postalcode"
},
  "geometry": {"coordinates":[0.0411014241655,51.39819625868277],"type":"Point"}
}