{
  "type": "Feature",
  "properties": {
    "iso:country": "GB",
    "wof:name": "SO45 6JF",
    "wof:placetype": "postalcode"
  },
  "geometry": {"coordinates":[-1.397053,50.862436],"type":"Point"}
}
