{
  "type": "Feature",
  "properties": {
    "date:inception_lower":"1994-12-01",
    "date:inception_upper":"1994-12-31",
    "iso:country":"GB",
    "wof:name":"SO45 6JF",
    "wof:placetype":"postalcode"
},
  "geometry": {"coordinates":[-1.397053,50.862436],"type":"Point"}
}