{
  "type": "Feature",
  "properties": {
    "iso:country":"GB",
    "wof:name":"YO7 2QB",
    "wof:placetype":"postalcode"
},
  "geometry": {"coordinates":[-1.24666738383218,54.22979835340893],"type":"Point"}
}