{
  "type": "Feature",
  "properties": {
    "iso:country": "GB",
    "wof:name": "EH48 1HP",
    "wof:placetype": "postalcode"
  },
  "geometry": {"coordinates":[-3.603596,55.898288],"type":"Point"}
}
