{
  "type": "Feature",
  "properties": {
    "iso:country":"GB",
    "wof:name":"TS6 8DN",
    "wof:placetype":"postalcode"
},
  "geometry": {"coordinates":[-1.12840771527222,54.56636994312885],"type":"Point"}
}