{
  "type": "Feature",
  "properties": {
    "iso:country":"GB",
    "wof:name":"HD6 2PR",
    "wof:placetype":"postalcode"
},
  "geometry": {"coordinates":[-1.80041028829399,53.71540870661064],"type":"Point"}
}