{
  "type": "Feature",
  "properties": {
    "iso:country":"GB",
    "wof:name":"NG1 4GZ",
    "wof:placetype":"postalcode"
},
  "geometry": {"coordinates":[-1.15292000413208,52.96206906752852],"type":"Point"}
}