{
  "type": "Feature",
  "properties": {
    "date:inception_lower": "1980-01-01",
    "date:inception_upper": "1980-01-01",
    "iso:country": "GB",
    "wof:name": "NG1 4GZ",
    "wof:placetype": "postalcode"
  },
  "geometry": {"coordinates":[-1.15292,52.962069],"type":"Point"}
}
