{
  "type": "Feature",
  "properties": {
    "iso:country":"GB",
    "wof:name":"B20 3LP",
    "wof:placetype":"postalcode"
},
  "geometry": {"coordinates":[-1.90678709845497,52.51255920830395],"type":"Point"}
}