{
  "type": "Feature",
  "properties": {
    "iso:country":"GB",
    "wof:name":"WA16 8JJ",
    "wof:placetype":"postalcode"
},
  "geometry": {"coordinates":[-2.35528003548567,53.30844601638427],"type":"Point"}
}