{
  "type": "Feature",
  "properties": {
    "iso:country":"GB",
    "wof:name":"BN21 2JT",
    "wof:placetype":"postalcode"
},
  "geometry": {"coordinates":[0.27191283357298,50.77548557098349],"type":"Point"}
}