{
  "type": "Feature",
  "properties": {
    "date:inception_lower": "1998-12-01",
    "date:inception_upper": "1998-12-01",
    "iso:country": "GB",
    "wof:name": "BN21 2JT",
    "wof:placetype": "postalcode"
  },
  "geometry": {"coordinates":[0.271913,50.775486],"type":"Point"}
}
