{
  "type": "Feature",
  "properties": {
    "iso:country":"GB",
    "wof:name":"N19 4JU",
    "wof:placetype":"postalcode"
},
  "geometry": {"coordinates":[-0.12336009721355,51.56273995671839],"type":"Point"}
}