{
  "type": "Feature",
  "properties": {
    "iso:country": "GB",
    "wof:name": "N19 4JU",
    "wof:placetype": "postalcode"
  },
  "geometry": {"coordinates":[-0.12336,51.56274],"type":"Point"}
}
