{
  "type": "Feature",
  "properties": {
    "iso:country":"GB",
    "wof:name":"RG12 1DH",
    "wof:placetype":"postalcode"
},
  "geometry": {"coordinates":[-0.74755113486896,51.41613018016591],"type":"Point"}
}