{
  "type": "Feature",
  "properties": {
    "iso:country":"GB",
    "wof:name":"HA8 6NS",
    "wof:placetype":"postalcode"
},
  "geometry": {"coordinates":[-0.28348262210206,51.61047650260297],"type":"Point"}
}