{
  "type": "Feature",
  "properties": {
    "iso:country":"GB",
    "wof:name":"M27 4DD",
    "wof:placetype":"postalcode"
},
  "geometry": {"coordinates":[-2.32617244962328,53.51373854485086],"type":"Point"}
}