{
  "type": "Feature",
  "properties": {
    "iso:country": "GB",
    "wof:name": "BS9 4QP",
    "wof:placetype": "postalcode"
  },
  "geometry": {"coordinates":[-2.600982,51.49258],"type":"Point"}
}
