{
  "type": "Feature",
  "properties": {
    "iso:country":"GB",
    "wof:name":"CA8 9LE",
    "wof:placetype":"postalcode"
},
  "geometry": {"coordinates":[-2.76467035534434,54.89207079427764],"type":"Point"}
}