{
  "type": "Feature",
  "properties": {
    "iso:country": "GB",
    "wof:name": "CA8 9LE",
    "wof:placetype": "postalcode"
  },
  "geometry": {"coordinates":[-2.76467,54.892071],"type":"Point"}
}
