{
  "type": "Feature",
  "properties": {
    "date:inception_lower": "2000-06-01",
    "date:inception_upper": "2000-06-01",
    "iso:country": "GB",
    "wof:name": "CA8 9LE",
    "wof:placetype": "postalcode"
  },
  "geometry": {"coordinates":[-2.76467,54.892071],"type":"Point"}
}
