{
  "type": "Feature",
  "properties": {
    "iso:country":"GB",
    "wof:name":"BB5 3TF",
    "wof:placetype":"postalcode"
},
  "geometry": {"coordinates":[-2.38144497439565,53.73872212171987],"type":"Point"}
}