{
  "type": "Feature",
  "properties": {
    "date:inception_lower":"2012-10-01",
    "date:inception_upper":"2012-10-31",
    "iso:country":"GB",
    "wof:name":"BH31 6AF",
    "wof:placetype":"postalcode"
},
  "geometry": {"coordinates":[-1.868888,50.877047],"type":"Point"}
}