{
  "type": "Feature",
  "properties": {
    "iso:country": "GB",
    "wof:name": "BH31 6AF",
    "wof:placetype": "postalcode"
  },
  "geometry": {"coordinates":[-1.868888,50.877047],"type":"Point"}
}
