{
  "type": "Feature",
  "properties": {
    "iso:country":"GB",
    "wof:name":"BH31 6AF",
    "wof:placetype":"postalcode"
},
  "geometry": {"coordinates":[-1.86888825248187,50.87704749683849],"type":"Point"}
}