{
  "type": "Feature",
  "properties": {
    "iso:country": "GB",
    "wof:name": "NG8 9LT",
    "wof:placetype": "postalcode"
  },
  "geometry": {"coordinates":[-1.222128,52.959863],"type":"Point"}
}
