{
  "type": "Feature",
  "properties": {
    "iso:country":"GB",
    "wof:name":"SO30 3BS",
    "wof:placetype":"postalcode"
},
  "geometry": {"coordinates":[-1.33546406963263,50.92390725539201],"type":"Point"}
}