{
  "type": "Feature",
  "properties": {
    "iso:country":"GB",
    "wof:name":"KA11 4AU",
    "wof:placetype":"postalcode"
},
  "geometry": {"coordinates":[-4.61443200678829,55.60988163934776],"type":"Point"}
}