{
  "type": "Feature",
  "properties": {
    "iso:country": "GB",
    "wof:name": "HU13 0DU",
    "wof:placetype": "postalcode"
  },
  "geometry": {"coordinates":[-0.435983,53.719626],"type":"Point"}
}
