{
  "type": "Feature",
  "properties": {
    "iso:country":"GB",
    "wof:name":"SY8 4BZ",
    "wof:placetype":"postalcode"
},
  "geometry": {"coordinates":[-2.69910780204227,52.33331410152699],"type":"Point"}
}