{
  "type": "Feature",
  "properties": {
    "iso:country": "GB",
    "wof:name": "SY8 4BZ",
    "wof:placetype": "postalcode"
  },
  "geometry": {"coordinates":[-2.699091,52.333309],"type":"Point"}
}
