{
  "type": "Feature",
  "properties": {
    "iso:country": "GB",
    "wof:name": "SY8 4BZ",
    "wof:placetype": "postalcode"
  },
  "geometry": {"coordinates":[-2.699108,52.333314],"type":"Point"}
}
