{
  "type": "Feature",
  "properties": {
    "iso:country":"GB",
    "wof:name":"TN23 3DE",
    "wof:placetype":"postalcode"
},
  "geometry": {"coordinates":[0.85075229257331,51.15262930158661],"type":"Point"}
}