{
  "type": "Feature",
  "properties": {
    "iso:country":"GB",
    "wof:name":"L34 9EY",
    "wof:placetype":"postalcode"
},
  "geometry": {"coordinates":[-2.84925352033618,53.46435277900068],"type":"Point"}
}