{
  "type": "Feature",
  "properties": {
    "date:inception_lower": "1980-01-01",
    "date:inception_upper": "1980-01-01",
    "iso:country": "GB",
    "wof:name": "B66 2BD",
    "wof:placetype": "postalcode"
  },
  "geometry": {"coordinates":[-1.95825,52.496808],"type":"Point"}
}
