{
  "type": "Feature",
  "properties": {
    "iso:country":"GB",
    "wof:name":"B66 2BD",
    "wof:placetype":"postalcode"
},
  "geometry": {"coordinates":[-1.95886021281568,52.49700911624883],"type":"Point"}
}