{
  "type": "Feature",
  "properties": {
    "iso:country": "GB",
    "wof:name": "NR5 0AP",
    "wof:placetype": "postalcode"
  },
  "geometry": {"coordinates":[1.239891,52.648456],"type":"Point"}
}
