{
  "type": "Feature",
  "properties": {
    "iso:country":"GB",
    "wof:name":"HA4 7DD",
    "wof:placetype":"postalcode"
},
  "geometry": {"coordinates":[-0.42739964509132,51.5720731598877],"type":"Point"}
}