{
  "type": "Feature",
  "properties": {
    "iso:country": "GB",
    "wof:name": "GL15 4AT",
    "wof:placetype": "postalcode"
  },
  "geometry": {"coordinates":[-2.472714,51.749543],"type":"Point"}
}
