{
  "type": "Feature",
  "properties": {
    "iso:country":"GB",
    "wof:name":"UB10 9NY",
    "wof:placetype":"postalcode"
},
  "geometry": {"coordinates":[-0.45590776077344,51.54924306670406],"type":"Point"}
}