{
  "type": "Feature",
  "properties": {
    "date:inception_lower": "1981-09-01",
    "date:inception_upper": "1981-09-01",
    "iso:country": "GB",
    "wof:name": "UB10 9NY",
    "wof:placetype": "postalcode"
  },
  "geometry": {"coordinates":[-0.455908,51.549243],"type":"Point"}
}
