{
  "type": "Feature",
  "properties": {
    "iso:country":"GB",
    "wof:name":"TN34 2DQ",
    "wof:placetype":"postalcode"
},
  "geometry": {"coordinates":[0.58079937036244,50.86935317627094],"type":"Point"}
}