{
  "type": "Feature",
  "properties": {
    "iso:country":"GB",
    "wof:name":"G33 3HA",
    "wof:placetype":"postalcode"
},
  "geometry": {"coordinates":[-4.17682983645715,55.86685513867464],"type":"Point"}
}