{
  "type": "Feature",
  "properties": {
    "date:inception_lower":"2008-11-01",
    "date:inception_upper":"2008-11-30",
    "iso:country":"GB",
    "wof:name":"CF48 1BW",
    "wof:placetype":"postalcode"
},
  "geometry": {"coordinates":[-3.42489,51.75392],"type":"Point"}
}