{
  "type": "Feature",
  "properties": {
    "iso:country":"GB",
    "wof:name":"CF48 1BW",
    "wof:placetype":"postalcode"
},
  "geometry": {"coordinates":[-3.42476349413458,51.75391739885644],"type":"Point"}
}