{
  "type": "Feature",
  "properties": {
    "iso:country": "GB",
    "wof:name": "CF48 1BW",
    "wof:placetype": "postalcode"
  },
  "geometry": {"coordinates":[-3.42489,51.75392],"type":"Point"}
}
