{
  "type": "Feature",
  "properties": {
    "iso:country":"GB",
    "wof:name":"E17 7JS",
    "wof:placetype":"postalcode"
},
  "geometry": {"coordinates":[-0.0252422788467,51.58358403400162],"type":"Point"}
}