{
  "type": "Feature",
  "properties": {
    "date:inception_lower": "1980-01-01",
    "date:inception_upper": "1980-01-01",
    "iso:country": "GB",
    "wof:name": "E17 7JS",
    "wof:placetype": "postalcode"
  },
  "geometry": {"coordinates":[-0.025242,51.583584],"type":"Point"}
}
