{
  "type": "Feature",
  "properties": {
    "iso:country":"GB",
    "wof:name":"S2 2SD",
    "wof:placetype":"postalcode"
},
  "geometry": {"coordinates":[-1.44726722554917,53.37409658604729],"type":"Point"}
}