{
  "type": "Feature",
  "properties": {
    "iso:country":"GB",
    "wof:name":"G84 8JB",
    "wof:placetype":"postalcode"
},
  "geometry": {"coordinates":[-4.77988050711583,56.0235028947044],"type":"Point"}
}