{
  "type": "Feature",
  "properties": {
    "iso:country":"GB",
    "wof:name":"BR6 7JZ",
    "wof:placetype":"postalcode"
},
  "geometry": {"coordinates":[0.05538132381633,51.32417747868453],"type":"Point"}
}