{
  "type": "Feature",
  "properties": {
    "iso:country":"GB",
    "wof:name":"EX22 6BU",
    "wof:placetype":"postalcode"
},
  "geometry": {"coordinates":[-4.35268737642998,50.80903978548418],"type":"Point"}
}