{
  "type": "Feature",
  "properties": {
    "iso:country":"GB",
    "wof:name":"LL18 3HU",
    "wof:placetype":"postalcode"
},
  "geometry": {"coordinates":[-3.48162761121283,53.32228047853599],"type":"Point"}
}