{
  "type": "Feature",
  "properties": {
    "date:inception_lower": "1996-12-01",
    "date:inception_upper": "1996-12-01",
    "iso:country": "GB",
    "wof:name": "LL18 3HU",
    "wof:placetype": "postalcode"
  },
  "geometry": {"coordinates":[-3.481628,53.32228],"type":"Point"}
}
