{
  "type": "Feature",
  "properties": {
    "iso:country":"GB",
    "wof:name":"OX12 8RB",
    "wof:placetype":"postalcode"
},
  "geometry": {"coordinates":[-1.38115070104564,51.59223316220254],"type":"Point"}
}