{
  "type": "Feature",
  "properties": {
    "iso:country": "GB",
    "wof:name": "OX12 8RB",
    "wof:placetype": "postalcode"
  },
  "geometry": {"coordinates":[-1.381151,51.592233],"type":"Point"}
}
