{
  "type": "Feature",
  "properties": {
    "date:inception_lower": "2005-06-01",
    "date:inception_upper": "2005-06-01",
    "iso:country": "GB",
    "wof:name": "OX12 8RB",
    "wof:placetype": "postalcode"
  },
  "geometry": {"coordinates":[-1.381151,51.592233],"type":"Point"}
}
