{
  "type": "Feature",
  "properties": {
    "iso:country": "GB",
    "wof:name": "TQ12 5EY",
    "wof:placetype": "postalcode"
  },
  "geometry": {"coordinates":[-3.578862,50.496594],"type":"Point"}
}
