{
  "type": "Feature",
  "properties": {
    "iso:country":"GB",
    "wof:name":"TQ12 5EY",
    "wof:placetype":"postalcode"
},
  "geometry": {"coordinates":[-3.57886238601968,50.4965935188075],"type":"Point"}
}