{
  "type": "Feature",
  "properties": {
    "iso:country":"GB",
    "wof:name":"WD24 7PB",
    "wof:placetype":"postalcode"
},
  "geometry": {"coordinates":[-0.38739050862397,51.67419287615112],"type":"Point"}
}