{
  "type": "Feature",
  "properties": {
    "iso:country":"GB",
    "wof:name":"RG18 4QJ",
    "wof:placetype":"postalcode"
},
  "geometry": {"coordinates":[-1.25221624531859,51.40442984644901],"type":"Point"}
}