{
  "type": "Feature",
  "properties": {
    "iso:country":"GB",
    "wof:name":"OX2 9LU",
    "wof:placetype":"postalcode"
},
  "geometry": {"coordinates":[-1.34575816688001,51.75667256021483],"type":"Point"}
}