{
  "type": "Feature",
  "properties": {
    "iso:country": "GB",
    "wof:name": "OX2 9LU",
    "wof:placetype": "postalcode"
  },
  "geometry": {"coordinates":[-1.345741,51.756678],"type":"Point"}
}
