{
  "type": "Feature",
  "properties": {
    "iso:country": "GB",
    "wof:name": "S75 2SZ",
    "wof:placetype": "postalcode"
  },
  "geometry": {"coordinates":[-1.496364,53.55964],"type":"Point"}
}
