{
  "type": "Feature",
  "properties": {
    "iso:country":"GB",
    "wof:name":"BN1 8LH",
    "wof:placetype":"postalcode"
},
  "geometry": {"coordinates":[-0.13368349667616,50.86210353680383],"type":"Point"}
}