{
  "type": "Feature",
  "properties": {
    "date:inception_lower":"1985-10-01",
    "date:inception_upper":"1985-10-31",
    "iso:country":"GB",
    "wof:name":"BN22 0XB",
    "wof:placetype":"postalcode"
},
  "geometry": {"coordinates":[0.267751,50.809375],"type":"Point"}
}