{
  "type": "Feature",
  "properties": {
    "iso:country":"GB",
    "wof:name":"LL16 4AF",
    "wof:placetype":"postalcode"
},
  "geometry": {"coordinates":[-3.39811946512274,53.18343837584804],"type":"Point"}
}