{
  "type": "Feature",
  "properties": {
    "iso:country":"GB",
    "wof:name":"TW4 5PG",
    "wof:placetype":"postalcode"
},
  "geometry": {"coordinates":[-0.38390070190983,51.44803659177555],"type":"Point"}
}