{
  "type": "Feature",
  "properties": {
    "iso:country": "GB",
    "wof:name": "TW4 5PG",
    "wof:placetype": "postalcode"
  },
  "geometry": {"coordinates":[-0.383901,51.448037],"type":"Point"}
}
