{
  "type": "Feature",
  "properties": {
    "iso:country":"GB",
    "wof:name":"AB15 8LD",
    "wof:placetype":"postalcode"
},
  "geometry": {"coordinates":[-2.16414240240507,57.14058869048412],"type":"Point"}
}