{
  "type": "Feature",
  "properties": {
    "iso:country":"GB",
    "wof:name":"BB6 7BL",
    "wof:placetype":"postalcode"
},
  "geometry": {"coordinates":[-2.39920923283513,53.78466520016431],"type":"Point"}
}