{
  "type": "Feature",
  "properties": {
    "date:inception_lower":"2004-03-01",
    "date:inception_upper":"2004-03-31",
    "iso:country":"GB",
    "wof:name":"PE19 5QA",
    "wof:placetype":"postalcode"
},
  "geometry": {"coordinates":[-0.212601,52.289263],"type":"Point"}
}