{
  "type": "Feature",
  "properties": {
    "date:inception_lower":"2016-02-01",
    "date:inception_upper":"2016-02-29",
    "iso:country":"GB",
    "wof:name":"BH20 4FH",
    "wof:placetype":"postalcode"
},
  "geometry": {"coordinates":[-2.123212,50.685469],"type":"Point"}
}