{
  "type": "Feature",
  "properties": {
    "date:inception_lower":"1980-01-01",
    "date:inception_upper":"1980-01-31",
    "iso:country":"GB",
    "wof:name":"BS21 7AH",
    "wof:placetype":"postalcode"
},
  "geometry": {"coordinates":[-2.823677,51.453649],"type":"Point"}
}