{
  "type": "Feature",
  "properties": {
    "iso:country": "GB",
    "wof:name": "BS21 7AH",
    "wof:placetype": "postalcode"
  },
  "geometry": {"coordinates":[-2.823677,51.453649],"type":"Point"}
}
