{
  "type": "Feature",
  "properties": {
    "iso:country":"GB",
    "wof:name":"SW17 7RG",
    "wof:placetype":"postalcode"
},
  "geometry": {"coordinates":[-0.15992522330309,51.43740605210215],"type":"Point"}
}