{
  "type": "Feature",
  "properties": {
    "iso:country":"GB",
    "wof:name":"KY10 3LF",
    "wof:placetype":"postalcode"
},
  "geometry": {"coordinates":[-2.69143179337464,56.25769183368756],"type":"Point"}
}