{
  "type": "Feature",
  "properties": {
    "date:inception_lower": "2021-02-01",
    "date:inception_upper": "2021-02-01",
    "iso:country": "GB",
    "wof:name": "EX5 7HP",
    "wof:placetype": "postalcode"
  },
  "geometry": {"coordinates":[-3.387435,50.751763],"type":"Point"}
}
