{
  "type": "Feature",
  "properties": {
    "date:inception_lower":"1994-05-01",
    "date:inception_upper":"1994-05-31",
    "iso:country":"GB",
    "wof:name":"M43 7TU",
    "wof:placetype":"postalcode"
},
  "geometry": {"coordinates":[-2.132032,53.489348],"type":"Point"}
}