{
  "type": "Feature",
  "properties": {
    "iso:country":"GB",
    "wof:name":"TQ10 9LN",
    "wof:placetype":"postalcode"
},
  "geometry": {"coordinates":[-3.78781228911139,50.43130606440275],"type":"Point"}
}