{
  "type": "Feature",
  "properties": {
    "iso:country": "GB",
    "wof:name": "TQ10 9LN",
    "wof:placetype": "postalcode"
  },
  "geometry": {"coordinates":[-3.788605,50.431577],"type":"Point"}
}
