{
  "type": "Feature",
  "properties": {
    "date:inception_lower": "1980-01-01",
    "date:inception_upper": "1980-01-01",
    "iso:country": "GB",
    "wof:name": "TQ10 9LN",
    "wof:placetype": "postalcode"
  },
  "geometry": {"coordinates":[-3.788605,50.431577],"type":"Point"}
}
