{
  "type": "Feature",
  "properties": {
    "iso:country":"GB",
    "wof:name":"WS11 0YY",
    "wof:placetype":"postalcode"
},
  "geometry": {"coordinates":[-2.02747158153296,52.68413538477616],"type":"Point"}
}