{
  "type": "Feature",
  "properties": {
    "iso:country": "GB",
    "wof:name": "CF34 9SR",
    "wof:placetype": "postalcode"
  },
  "geometry": {"coordinates":[-3.63521,51.585934],"type":"Point"}
}
