{
  "type": "Feature",
  "properties": {
    "iso:country": "GB",
    "wof:name": "CF34 9SR",
    "wof:placetype": "postalcode"
  },
  "geometry": {"coordinates":[-3.635196,51.585939],"type":"Point"}
}
