{
  "type": "Feature",
  "properties": {
    "iso:country":"GB",
    "wof:name":"WA5 0LH",
    "wof:placetype":"postalcode"
},
  "geometry": {"coordinates":[-2.60182382430479,53.39779361466824],"type":"Point"}
}