{
  "type": "Feature",
  "properties": {
    "date:inception_lower": "1980-01-01",
    "date:inception_upper": "1980-01-01",
    "iso:country": "GB",
    "wof:name": "G46 6RE",
    "wof:placetype": "postalcode"
  },
  "geometry": {"coordinates":[-4.301699,55.793787],"type":"Point"}
}
