{
  "type": "Feature",
  "properties": {
    "iso:country": "GB",
    "wof:name": "G46 6RE",
    "wof:placetype": "postalcode"
  },
  "geometry": {"coordinates":[-4.301699,55.793787],"type":"Point"}
}
