{
  "type": "Feature",
  "properties": {
    "iso:country":"GB",
    "wof:name":"G46 6RE",
    "wof:placetype":"postalcode"
},
  "geometry": {"coordinates":[-4.30169920131497,55.79378686810894],"type":"Point"}
}