{
  "type": "Feature",
  "properties": {
    "iso:country":"GB",
    "wof:name":"W8 7BS",
    "wof:placetype":"postalcode"
},
  "geometry": {"coordinates":[-0.19714700217053,51.50169632820396],"type":"Point"}
}