{
  "type": "Feature",
  "properties": {
    "date:inception_lower": "1980-01-01",
    "date:inception_upper": "1980-01-01",
    "iso:country": "GB",
    "wof:name": "RG8 8PE",
    "wof:placetype": "postalcode"
  },
  "geometry": {"coordinates":[-1.142667,51.482097],"type":"Point"}
}
