{
  "type": "Feature",
  "properties": {
    "iso:country": "GB",
    "wof:name": "ST3 5XG",
    "wof:placetype": "postalcode"
  },
  "geometry": {"coordinates":[-2.121226,52.99218],"type":"Point"}
}
