{
  "type": "Feature",
  "properties": {
    "iso:country":"GB",
    "wof:name":"ST3 5XG",
    "wof:placetype":"postalcode"
},
  "geometry": {"coordinates":[-2.12122606441864,52.99217963541816],"type":"Point"}
}