{
  "type": "Feature",
  "properties": {
    "date:inception_lower": "2023-07-01",
    "date:inception_upper": "2023-07-01",
    "iso:country": "GB",
    "wof:name": "EH22 9DL",
    "wof:placetype": "postalcode"
  },
  "geometry": {"coordinates":[-3.072867,55.892992],"type":"Point"}
}
