{
  "type": "Feature",
  "properties": {
    "iso:country":"GB",
    "wof:name":"DL9 4UW",
    "wof:placetype":"postalcode"
},
  "geometry": {"coordinates":[-1.68431200460865,54.38133973409412],"type":"Point"}
}