{
  "type": "Feature",
  "properties": {
    "iso:country":"GB",
    "wof:name":"EX5 5HQ",
    "wof:placetype":"postalcode"
},
  "geometry": {"coordinates":[-3.52518085984035,50.78039528369425],"type":"Point"}
}