{
  "type": "Feature",
  "properties": {
    "date:inception_lower": "1980-01-01",
    "date:inception_upper": "1980-01-01",
    "iso:country": "GB",
    "wof:name": "EX5 5HQ",
    "wof:placetype": "postalcode"
  },
  "geometry": {"coordinates":[-3.525181,50.780395],"type":"Point"}
}
