{
  "type": "Feature",
  "properties": {
    "iso:country":"GB",
    "wof:name":"NP26 3NG",
    "wof:placetype":"postalcode"
},
  "geometry": {"coordinates":[-2.83567620139089,51.58042032524158],"type":"Point"}
}