{
  "type": "Feature",
  "properties": {
    "iso:country":"GB",
    "wof:name":"IP26 4JR",
    "wof:placetype":"postalcode"
},
  "geometry": {"coordinates":[0.46271198308096,52.47894697566048],"type":"Point"}
}