{
  "type": "Feature",
  "properties": {
    "iso:country":"GB",
    "wof:name":"BN25 1DF",
    "wof:placetype":"postalcode"
},
  "geometry": {"coordinates":[0.10499459744138,50.76832938801206],"type":"Point"}
}