{
  "type": "Feature",
  "properties": {
    "iso:country": "GB",
    "wof:name": "CV32 6RA",
    "wof:placetype": "postalcode"
  },
  "geometry": {"coordinates":[-1.524831,52.317699],"type":"Point"}
}
