{
  "type": "Feature",
  "properties": {
    "iso:country":"GB",
    "wof:name":"CV32 6RA",
    "wof:placetype":"postalcode"
},
  "geometry": {"coordinates":[-1.52483106266916,52.31769867319051],"type":"Point"}
}