{
  "type": "Feature",
  "properties": {
    "date:inception_lower": "1980-01-01",
    "date:inception_upper": "1980-01-01",
    "iso:country": "GB",
    "wof:name": "G15 6HG",
    "wof:placetype": "postalcode"
  },
  "geometry": {"coordinates":[-4.359364,55.901993],"type":"Point"}
}
