{
  "type": "Feature",
  "properties": {
    "iso:country": "GB",
    "wof:name": "CM15 0RU",
    "wof:placetype": "postalcode"
  },
  "geometry": {"coordinates":[0.310803,51.664404],"type":"Point"}
}
