{
  "type": "Feature",
  "properties": {
    "date:inception_lower": "2009-07-01",
    "date:inception_upper": "2009-07-01",
    "iso:country": "GB",
    "wof:name": "SL6 6FN",
    "wof:placetype": "postalcode"
  },
  "geometry": {"coordinates":[-0.813957,51.539375],"type":"Point"}
}
