{
  "type": "Feature",
  "properties": {
    "date:inception_lower": "2021-02-01",
    "date:inception_upper": "2021-02-01",
    "iso:country": "GB",
    "wof:name": "G15 7BG",
    "wof:placetype": "postalcode"
  },
  "geometry": {"coordinates":[-4.369649,55.914795],"type":"Point"}
}
