{
  "type": "Feature",
  "properties": {
    "iso:country":"GB",
    "wof:name":"LS10 1HY",
    "wof:placetype":"postalcode"
},
  "geometry": {"coordinates":[-1.53185077707766,53.79079030895088],"type":"Point"}
}