{
  "type": "Feature",
  "properties": {
    "date:inception_lower": "1980-01-01",
    "date:inception_upper": "1980-01-01",
    "iso:country": "GB",
    "wof:name": "B69 1PJ",
    "wof:placetype": "postalcode"
  },
  "geometry": {"coordinates":[-2.04761,52.499865],"type":"Point"}
}
