{
  "type": "Feature",
  "properties": {
    "iso:country":"GB",
    "wof:name":"B69 1PJ",
    "wof:placetype":"postalcode"
},
  "geometry": {"coordinates":[-2.04761023940198,52.49986528969338],"type":"Point"}
}