{
  "type": "Feature",
  "properties": {
    "iso:country": "GB",
    "wof:name": "SA48 7AR",
    "wof:placetype": "postalcode"
  },
  "geometry": {"coordinates":[-4.078428,52.11154],"type":"Point"}
}
