{
  "type": "Feature",
  "properties": {
    "iso:country":"GB",
    "wof:name":"N4 2QE",
    "wof:placetype":"postalcode"
},
  "geometry": {"coordinates":[-0.10517924692675,51.56070322394496],"type":"Point"}
}