{
  "type": "Feature",
  "properties": {
    "iso:country": "GB",
    "wof:name": "N4 2QE",
    "wof:placetype": "postalcode"
  },
  "geometry": {"coordinates":[-0.105179,51.560703],"type":"Point"}
}
