{
  "type": "Feature",
  "properties": {
    "iso:country": "GB",
    "wof:name": "B97 5AH",
    "wof:placetype": "postalcode"
  },
  "geometry": {"coordinates":[-1.955135,52.29127],"type":"Point"}
}
