{
  "type": "Feature",
  "properties": {
    "iso:country":"GB",
    "wof:name":"B97 5AH",
    "wof:placetype":"postalcode"
},
  "geometry": {"coordinates":[-1.95513524237491,52.2912695626306],"type":"Point"}
}