{
  "type": "Feature",
  "properties": {
    "date:inception_lower": "1980-01-01",
    "date:inception_upper": "1980-01-01",
    "iso:country": "GB",
    "wof:name": "PO9 2SS",
    "wof:placetype": "postalcode"
  },
  "geometry": {"coordinates":[-0.971808,50.849915],"type":"Point"}
}
