{
  "type": "Feature",
  "properties": {
    "iso:country": "GB",
    "wof:name": "PO9 2SS",
    "wof:placetype": "postalcode"
  },
  "geometry": {"coordinates":[-0.971808,50.849915],"type":"Point"}
}
