{
  "type": "Feature",
  "properties": {
    "iso:country":"GB",
    "wof:name":"PO9 2SS",
    "wof:placetype":"postalcode"
},
  "geometry": {"coordinates":[-0.97180846903432,50.84991499256142],"type":"Point"}
}