{
  "type": "Feature",
  "properties": {
    "iso:country":"GB",
    "wof:name":"BL3 5EN",
    "wof:placetype":"postalcode"
},
  "geometry": {"coordinates":[-2.44756098647124,53.57462853220031],"type":"Point"}
}