{
  "type": "Feature",
  "properties": {
    "iso:country":"GB",
    "wof:name":"BS16 5DA",
    "wof:placetype":"postalcode"
},
  "geometry": {"coordinates":[-2.51384209469124,51.48527099696562],"type":"Point"}
}