{
  "type": "Feature",
  "properties": {
    "date:inception_lower":"1997-06-01",
    "date:inception_upper":"1997-06-30",
    "iso:country":"GB",
    "wof:name":"BD6 2HX",
    "wof:placetype":"postalcode"
},
  "geometry": {"coordinates":[-1.798516,53.756787],"type":"Point"}
}