{
  "type": "Feature",
  "properties": {
    "iso:country":"GB",
    "wof:name":"BD13 4AT",
    "wof:placetype":"postalcode"
},
  "geometry": {"coordinates":[-1.89460180097771,53.8039345106117],"type":"Point"}
}