{
  "type": "Feature",
  "properties": {
    "date:inception_lower": "2003-01-01",
    "date:inception_upper": "2003-01-01",
    "iso:country": "GB",
    "wof:name": "BD13 4AT",
    "wof:placetype": "postalcode"
  },
  "geometry": {"coordinates":[-1.894602,53.803935],"type":"Point"}
}
