{
  "type": "Feature",
  "properties": {
    "iso:country": "GB",
    "wof:name": "CF23 7BT",
    "wof:placetype": "postalcode"
  },
  "geometry": {"coordinates":[-3.148375,51.528879],"type":"Point"}
}
