{
  "type": "Feature",
  "properties": {
    "date:inception_lower":"1999-06-01",
    "date:inception_upper":"1999-06-30",
    "iso:country":"GB",
    "wof:name":"CF23 7BT",
    "wof:placetype":"postalcode"
},
  "geometry": {"coordinates":[-3.148375,51.528879],"type":"Point"}
}