{
  "type": "Feature",
  "properties": {
    "iso:country":"GB",
    "wof:name":"CF23 7BT",
    "wof:placetype":"postalcode"
},
  "geometry": {"coordinates":[-3.14837553262093,51.52887917142219],"type":"Point"}
}