{
  "type": "Feature",
  "properties": {
    "iso:country":"GB",
    "wof:name":"SA44 6JJ",
    "wof:placetype":"postalcode"
},
  "geometry": {"coordinates":[-4.35298131993574,52.15517939689176],"type":"Point"}
}