{
  "type": "Feature",
  "properties": {
    "iso:country":"GB",
    "wof:name":"SL7 2BR",
    "wof:placetype":"postalcode"
},
  "geometry": {"coordinates":[-0.78166001216439,51.5702156460416],"type":"Point"}
}