{
  "type": "Feature",
  "properties": {
    "iso:country": "GB",
    "wof:name": "SL7 2BR",
    "wof:placetype": "postalcode"
  },
  "geometry": {"coordinates":[-0.78166,51.570216],"type":"Point"}
}
