{
  "type": "Feature",
  "properties": {
    "date:inception_lower": "2020-04-01",
    "date:inception_upper": "2020-04-01",
    "iso:country": "GB",
    "wof:name": "B60 4FQ",
    "wof:placetype": "postalcode"
  },
  "geometry": {"coordinates":[-2.079599,52.296326],"type":"Point"}
}
