{
  "type": "Feature",
  "properties": {
    "iso:country":"GB",
    "wof:name":"DE74 2TE",
    "wof:placetype":"postalcode"
},
  "geometry": {"coordinates":[-1.2896225361085,52.83727309315501],"type":"Point"}
}