{
  "type": "Feature",
  "properties": {
    "iso:country": "GB",
    "wof:name": "DE74 2TE",
    "wof:placetype": "postalcode"
  },
  "geometry": {"coordinates":[-1.289622,52.837273],"type":"Point"}
}
