{
  "type": "Feature",
  "properties": {
    "date:inception_lower": "1992-08-01",
    "date:inception_upper": "1992-08-01",
    "iso:country": "GB",
    "wof:name": "DE74 2TE",
    "wof:placetype": "postalcode"
  },
  "geometry": {"coordinates":[-1.289622,52.837273],"type":"Point"}
}
