{
  "type": "Feature",
  "properties": {
    "iso:country":"GB",
    "wof:name":"E14 3ND",
    "wof:placetype":"postalcode"
},
  "geometry": {"coordinates":[-0.0119707206168,51.49570885161064],"type":"Point"}
}