{
  "type": "Feature",
  "properties": {
    "iso:country":"GB",
    "wof:name":"EX4 6LX",
    "wof:placetype":"postalcode"
},
  "geometry": {"coordinates":[-3.51560922881447,50.73178571850006],"type":"Point"}
}