{
  "type": "Feature",
  "properties": {
    "iso:country": "GB",
    "wof:name": "ML7 5SE",
    "wof:placetype": "postalcode"
  },
  "geometry": {"coordinates":[-3.758453,55.861216],"type":"Point"}
}
