{
  "type": "Feature",
  "properties": {
    "iso:country":"GB",
    "wof:name":"ML7 5SE",
    "wof:placetype":"postalcode"
},
  "geometry": {"coordinates":[-3.75845271417878,55.86121638725651],"type":"Point"}
}