{
  "type": "Feature",
  "properties": {
    "date:inception_lower": "1980-01-01",
    "date:inception_upper": "1980-01-01",
    "iso:country": "GB",
    "wof:name": "BS3 3LR",
    "wof:placetype": "postalcode"
  },
  "geometry": {"coordinates":[-2.604347,51.437461],"type":"Point"}
}
