{
  "type": "Feature",
  "properties": {
    "iso:country":"GB",
    "wof:name":"BS3 3LR",
    "wof:placetype":"postalcode"
},
  "geometry": {"coordinates":[-2.60431560563798,51.4375075420223],"type":"Point"}
}