{
  "type": "Feature",
  "properties": {
    "iso:country":"GB",
    "wof:name":"BB5 2LJ",
    "wof:placetype":"postalcode"
},
  "geometry": {"coordinates":[-2.35944442853061,53.74551326238539],"type":"Point"}
}