{
  "type": "Feature",
  "properties": {
    "iso:country":"GB",
    "wof:name":"M40 3RD",
    "wof:placetype":"postalcode"
},
  "geometry": {"coordinates":[-2.15882769391916,53.52135892820974],"type":"Point"}
}