{
  "type": "Feature",
  "properties": {
    "iso:country": "GB",
    "wof:name": "DL1 3PQ",
    "wof:placetype": "postalcode"
  },
  "geometry": {"coordinates":[-1.528062,54.54701],"type":"Point"}
}
