{
  "type": "Feature",
  "properties": {
    "iso:country":"GB",
    "wof:name":"SK10 5QR",
    "wof:placetype":"postalcode"
},
  "geometry": {"coordinates":[-2.08920735661307,53.2998097509783],"type":"Point"}
}