{
  "type": "Feature",
  "properties": {
    "iso:country":"GB",
    "wof:name":"AL1 2NJ",
    "wof:placetype":"postalcode"
},
  "geometry": {"coordinates":[-0.34271436607081,51.73877210163878],"type":"Point"}
}