{
  "type": "Feature",
  "properties": {
    "iso:country":"GB",
    "wof:name":"TQ6 9AA",
    "wof:placetype":"postalcode"
},
  "geometry": {"coordinates":[-3.57792626082028,50.35031353570476],"type":"Point"}
}