{
  "type": "Feature",
  "properties": {
    "date:inception_lower": "2021-08-01",
    "date:inception_upper": "2021-08-01",
    "iso:country": "GB",
    "wof:name": "DL8 2BU",
    "wof:placetype": "postalcode"
  },
  "geometry": {"coordinates":[-1.530391,54.260809],"type":"Point"}
}
