{
  "type": "Feature",
  "properties": {
    "date:inception_lower":"1995-12-01",
    "date:inception_upper":"1995-12-31",
    "iso:country":"GB",
    "wof:name":"MK45 4RY",
    "wof:placetype":"postalcode"
},
  "geometry": {"coordinates":[-0.429412,51.972318],"type":"Point"}
}