{
  "type": "Feature",
  "properties": {
    "iso:country": "GB",
    "wof:name": "CR0 2QX",
    "wof:placetype": "postalcode"
  },
  "geometry": {"coordinates":[-0.09892,51.386775],"type":"Point"}
}
