{
  "type": "Feature",
  "properties": {
    "iso:country":"GB",
    "wof:name":"SO19 8GA",
    "wof:placetype":"postalcode"
},
  "geometry": {"coordinates":[-1.35146000479147,50.90109328510074],"type":"Point"}
}