{
  "type": "Feature",
  "properties": {
    "iso:country":"GB",
    "wof:name":"BS30 8DZ",
    "wof:placetype":"postalcode"
},
  "geometry": {"coordinates":[-2.47747805478907,51.44668001665534],"type":"Point"}
}