{
  "type": "Feature",
  "properties": {
    "iso:country":"GB",
    "wof:name":"EX39 6DJ",
    "wof:placetype":"postalcode"
},
  "geometry": {"coordinates":[-4.46372266188878,50.98386705298496],"type":"Point"}
}