{
  "type": "Feature",
  "properties": {
    "iso:country":"GB",
    "wof:name":"OL6 9RT",
    "wof:placetype":"postalcode"
},
  "geometry": {"coordinates":[-2.06922532994358,53.49615123253017],"type":"Point"}
}