{
  "type": "Feature",
  "properties": {
    "iso:country": "GB",
    "wof:name": "SS1 2SG",
    "wof:placetype": "postalcode"
  },
  "geometry": {"coordinates":[0.733114,51.535856],"type":"Point"}
}
