{
  "type": "Feature",
  "properties": {
    "iso:country": "GB",
    "wof:name": "SG17 5QJ",
    "wof:placetype": "postalcode"
  },
  "geometry": {"coordinates":[-0.353139,52.064806],"type":"Point"}
}
