{
  "type": "Feature",
  "properties": {
    "iso:country": "GB",
    "wof:name": "PH1 3BS",
    "wof:placetype": "postalcode"
  },
  "geometry": {"coordinates":[-3.44866,56.415646],"type":"Point"}
}
