{
  "type": "Feature",
  "properties": {
    "date:inception_lower": "1992-01-01",
    "date:inception_upper": "1992-01-01",
    "iso:country": "GB",
    "wof:name": "EN8 9SL",
    "wof:placetype": "postalcode"
  },
  "geometry": {"coordinates":[-0.026637,51.704264],"type":"Point"}
}
