{
  "type": "Feature",
  "properties": {
    "iso:country": "GB",
    "wof:name": "EN8 9SL",
    "wof:placetype": "postalcode"
  },
  "geometry": {"coordinates":[-0.026371,51.705325],"type":"Point"}
}
