{
  "type": "Feature",
  "properties": {
    "iso:country":"GB",
    "wof:name":"EN8 9SL",
    "wof:placetype":"postalcode"
},
  "geometry": {"coordinates":[-0.02637128898369,51.70532500402829],"type":"Point"}
}