{
  "type": "Feature",
  "properties": {
    "date:inception_lower": "1980-01-01",
    "date:inception_upper": "1980-01-01",
    "iso:country": "GB",
    "wof:name": "SK7 2PF",
    "wof:placetype": "postalcode"
  },
  "geometry": {"coordinates":[-2.164365,53.36212],"type":"Point"}
}
