{
  "type": "Feature",
  "properties": {
    "iso:country":"GB",
    "wof:name":"SR3 1UA",
    "wof:placetype":"postalcode"
},
  "geometry": {"coordinates":[-1.40482294679618,54.88852894843595],"type":"Point"}
}