{
  "type": "Feature",
  "properties": {
    "date:inception_lower":"1980-01-01",
    "date:inception_upper":"1980-01-31",
    "iso:country":"GB",
    "wof:name":"SR3 1UA",
    "wof:placetype":"postalcode"
},
  "geometry": {"coordinates":[-1.404823,54.888529],"type":"Point"}
}