{
  "type": "Feature",
  "properties": {
    "iso:country":"GB",
    "wof:name":"DE21 4TY",
    "wof:placetype":"postalcode"
},
  "geometry": {"coordinates":[-1.42655703759733,52.93265421642888],"type":"Point"}
}