{
  "type": "Feature",
  "properties": {
    "iso:country": "GB",
    "wof:name": "DE21 4TY",
    "wof:placetype": "postalcode"
  },
  "geometry": {"coordinates":[-1.426557,52.932654],"type":"Point"}
}
