{
  "type": "Feature",
  "properties": {
    "iso:country":"GB",
    "wof:name":"BH22 0NF",
    "wof:placetype":"postalcode"
},
  "geometry": {"coordinates":[-1.89019645573545,50.83957087842345],"type":"Point"}
}