{
  "type": "Feature",
  "properties": {
    "date:inception_lower": "1984-10-01",
    "date:inception_upper": "1984-10-01",
    "iso:country": "GB",
    "wof:name": "BH22 0NF",
    "wof:placetype": "postalcode"
  },
  "geometry": {"coordinates":[-1.890196,50.839571],"type":"Point"}
}
