{
  "type": "Feature",
  "properties": {
    "iso:country":"GB",
    "wof:name":"PE1 5DH",
    "wof:placetype":"postalcode"
},
  "geometry": {"coordinates":[-0.23475851629226,52.57230429815971],"type":"Point"}
}