{
  "type": "Feature",
  "properties": {
    "iso:country":"GB",
    "wof:name":"EX14 4TW",
    "wof:placetype":"postalcode"
},
  "geometry": {"coordinates":[-3.18192192654314,50.81232977197497],"type":"Point"}
}