{
  "type": "Feature",
  "properties": {
    "date:inception_lower":"1995-12-01",
    "date:inception_upper":"1995-12-31",
    "iso:country":"GB",
    "wof:name":"WR15 8JZ",
    "wof:placetype":"postalcode"
},
  "geometry": {"coordinates":[-2.53589,52.319037],"type":"Point"}
}