{
  "type": "Feature",
  "properties": {
    "date:inception_lower": "1980-01-01",
    "date:inception_upper": "1980-01-01",
    "iso:country": "GB",
    "wof:name": "WV6 8TU",
    "wof:placetype": "postalcode"
  },
  "geometry": {"coordinates":[-2.187037,52.603964],"type":"Point"}
}
