{
  "type": "Feature",
  "properties": {
    "iso:country": "GB",
    "wof:name": "WV6 8TU",
    "wof:placetype": "postalcode"
  },
  "geometry": {"coordinates":[-2.187037,52.603964],"type":"Point"}
}
