{
  "type": "Feature",
  "properties": {
    "date:inception_lower": "1994-12-01",
    "date:inception_upper": "1994-12-01",
    "iso:country": "GB",
    "wof:name": "NN6 7XF",
    "wof:placetype": "postalcode"
  },
  "geometry": {"coordinates":[-1.06954,52.304794],"type":"Point"}
}
