{
  "type": "Feature",
  "properties": {
    "iso:country": "GB",
    "wof:name": "NN6 7XF",
    "wof:placetype": "postalcode"
  },
  "geometry": {"coordinates":[-1.06954,52.304794],"type":"Point"}
}
