{
  "type": "Feature",
  "properties": {
    "iso:country": "GB",
    "wof:name": "WF9 1FN",
    "wof:placetype": "postalcode"
  },
  "geometry": {"coordinates":[-1.293059,53.616668],"type":"Point"}
}
