{
  "type": "Feature",
  "properties": {
    "date:inception_lower": "2016-04-01",
    "date:inception_upper": "2016-04-01",
    "iso:country": "GB",
    "wof:name": "WF9 1FN",
    "wof:placetype": "postalcode"
  },
  "geometry": {"coordinates":[-1.293075,53.616668],"type":"Point"}
}
