{
  "type": "Feature",
  "properties": {
    "iso:country":"GB",
    "wof:name":"WF9 1FN",
    "wof:placetype":"postalcode"
},
  "geometry": {"coordinates":[-1.29308523256766,53.61678497182869],"type":"Point"}
}