{
  "type": "Feature",
  "properties": {
    "date:inception_lower":"2016-04-01",
    "date:inception_upper":"2016-04-30",
    "iso:country":"GB",
    "wof:name":"WF9 1FN",
    "wof:placetype":"postalcode"
},
  "geometry": {"coordinates":[-1.293059,53.616668],"type":"Point"}
}