{
  "type": "Feature",
  "properties": {
    "iso:country":"GB",
    "wof:name":"B91 1EH",
    "wof:placetype":"postalcode"
},
  "geometry": {"coordinates":[-1.7971604863677,52.41919610343697],"type":"Point"}
}