{
  "type": "Feature",
  "properties": {
    "iso:country":"GB",
    "wof:name":"CV11 4TF",
    "wof:placetype":"postalcode"
},
  "geometry": {"coordinates":[-1.43207070608831,52.49976302892727],"type":"Point"}
}