{
  "type": "Feature",
  "properties": {
    "date:inception_lower":"2008-03-01",
    "date:inception_upper":"2008-03-31",
    "iso:country":"GB",
    "wof:name":"ME9 7FL",
    "wof:placetype":"postalcode"
},
  "geometry": {"coordinates":[0.634545,51.360371],"type":"Point"}
}