{
  "type": "Feature",
  "properties": {
    "iso:country":"GB",
    "wof:name":"N8 9LJ",
    "wof:placetype":"postalcode"
},
  "geometry": {"coordinates":[-0.11157379177612,51.57768516901217],"type":"Point"}
}