{
  "type": "Feature",
  "properties": {
    "date:inception_lower":"1980-01-01",
    "date:inception_upper":"1980-01-31",
    "iso:country":"GB",
    "wof:name":"N8 9LJ",
    "wof:placetype":"postalcode"
},
  "geometry": {"coordinates":[-0.111574,51.577685],"type":"Point"}
}