{
  "type": "Feature",
  "properties": {
    "date:inception_lower": "1980-01-01",
    "date:inception_upper": "1980-01-01",
    "iso:country": "GB",
    "wof:name": "DN21 5QT",
    "wof:placetype": "postalcode"
  },
  "geometry": {"coordinates":[-0.691985,53.411629],"type":"Point"}
}
