{
  "type": "Feature",
  "properties": {
    "iso:country":"GB",
    "wof:name":"DN21 5QT",
    "wof:placetype":"postalcode"
},
  "geometry": {"coordinates":[-0.69198553051192,53.41162942308156],"type":"Point"}
}