{
  "type": "Feature",
  "properties": {
    "iso:country": "GB",
    "wof:name": "AB21 0NT",
    "wof:placetype": "postalcode"
  },
  "geometry": {"coordinates":[-2.207983,57.209055],"type":"Point"}
}
