{
  "type": "Feature",
  "properties": {
    "iso:country": "GB",
    "wof:name": "LS17 8SE",
    "wof:placetype": "postalcode"
  },
  "geometry": {"coordinates":[-1.507047,53.85562],"type":"Point"}
}
