{
  "type": "Feature",
  "properties": {
    "date:inception_lower": "1995-12-01",
    "date:inception_upper": "1995-12-01",
    "iso:country": "GB",
    "wof:name": "LS17 8SE",
    "wof:placetype": "postalcode"
  },
  "geometry": {"coordinates":[-1.507047,53.85562],"type":"Point"}
}
