{
  "type": "Feature",
  "properties": {
    "iso:country":"GB",
    "wof:name":"LN4 2TN",
    "wof:placetype":"postalcode"
},
  "geometry": {"coordinates":[-0.52938577774118,53.1978093218525],"type":"Point"}
}