{
  "type": "Feature",
  "properties": {
    "iso:country":"GB",
    "wof:name":"E16 1DE",
    "wof:placetype":"postalcode"
},
  "geometry": {"coordinates":[0.01813911208079,51.50874653457223],"type":"Point"}
}