{
  "type": "Feature",
  "properties": {
    "iso:country": "GB",
    "wof:name": "PR1 8PD",
    "wof:placetype": "postalcode"
  },
  "geometry": {"coordinates":[-2.714024,53.757497],"type":"Point"}
}
