{
  "type": "Feature",
  "properties": {
    "iso:country":"GB",
    "wof:name":"PR1 8PD",
    "wof:placetype":"postalcode"
},
  "geometry": {"coordinates":[-2.71402360541634,53.75749690809437],"type":"Point"}
}