{
  "type": "Feature",
  "properties": {
    "iso:country":"GB",
    "wof:name":"GL54 4NB",
    "wof:placetype":"postalcode"
},
  "geometry": {"coordinates":[-1.96541051969597,51.87587288924537],"type":"Point"}
}