{
  "type": "Feature",
  "properties": {
    "iso:country":"GB",
    "wof:name":"SS0 9NB",
    "wof:placetype":"postalcode"
},
  "geometry": {"coordinates":[0.68868374956273,51.54958202273556],"type":"Point"}
}