{
  "type": "Feature",
  "properties": {
    "iso:country": "GB",
    "wof:name": "SS0 9NB",
    "wof:placetype": "postalcode"
  },
  "geometry": {"coordinates":[0.688684,51.549582],"type":"Point"}
}
