{
  "type": "Feature",
  "properties": {
    "iso:country": "GB",
    "wof:name": "HR6 9SD",
    "wof:placetype": "postalcode"
  },
  "geometry": {"coordinates":[-2.828097,52.248698],"type":"Point"}
}
