{
  "type": "Feature",
  "properties": {
    "iso:country":"GB",
    "wof:name":"HR6 9SD",
    "wof:placetype":"postalcode"
},
  "geometry": {"coordinates":[-2.82809730957163,52.24869781793097],"type":"Point"}
}