{
  "type": "Feature",
  "properties": {
    "date:inception_lower": "2023-03-01",
    "date:inception_upper": "2023-03-01",
    "iso:country": "GB",
    "wof:name": "PL26 8ZA",
    "wof:placetype": "postalcode"
  },
  "geometry": {"coordinates":[-4.77524,50.366387],"type":"Point"}
}
