{
  "type": "Feature",
  "properties": {
    "iso:country": "GB",
    "wof:name": "TS5 7YR",
    "wof:placetype": "postalcode"
  },
  "geometry": {"coordinates":[-1.240882,54.535394],"type":"Point"}
}
