{
  "type": "Feature",
  "properties": {
    "iso:country":"GB",
    "wof:name":"NW7 1AG",
    "wof:placetype":"postalcode"
},
  "geometry": {"coordinates":[-0.21662889721829,51.61781573412694],"type":"Point"}
}