{
  "type": "Feature",
  "properties": {
    "date:inception_lower": "1985-10-01",
    "date:inception_upper": "1985-10-01",
    "iso:country": "GB",
    "wof:name": "NW7 1AG",
    "wof:placetype": "postalcode"
  },
  "geometry": {"coordinates":[-0.216603,51.617846],"type":"Point"}
}
