{
  "type": "Feature",
  "properties": {
    "iso:country":"GB",
    "wof:name":"TN6 2FS",
    "wof:placetype":"postalcode"
},
  "geometry": {"coordinates":[0.1767002302882,51.05280566194033],"type":"Point"}
}