{
  "type": "Feature",
  "properties": {
    "date:inception_lower":"2012-05-01",
    "date:inception_upper":"2012-05-31",
    "iso:country":"GB",
    "wof:name":"TN6 2FS",
    "wof:placetype":"postalcode"
},
  "geometry": {"coordinates":[0.1767,51.052806],"type":"Point"}
}