{
  "type": "Feature",
  "properties": {
    "iso:country": "GB",
    "wof:name": "PE28 2EA",
    "wof:placetype": "postalcode"
  },
  "geometry": {"coordinates":[-0.118981,52.348744],"type":"Point"}
}
