{
  "type": "Feature",
  "properties": {
    "iso:country": "GB",
    "wof:name": "BR3 1TP",
    "wof:placetype": "postalcode"
  },
  "geometry": {"coordinates":[-0.032237,51.41481],"type":"Point"}
}
