{
  "type": "Feature",
  "properties": {
    "iso:country":"GB",
    "wof:name":"BR3 1TP",
    "wof:placetype":"postalcode"
},
  "geometry": {"coordinates":[-0.0322367092166,51.41481050539603],"type":"Point"}
}