{
  "type": "Feature",
  "properties": {
    "iso:country":"GB",
    "wof:name":"LA12 8JP",
    "wof:placetype":"postalcode"
},
  "geometry": {"coordinates":[-3.00875731550244,54.25684077773261],"type":"Point"}
}