{
  "type": "Feature",
  "properties": {
    "iso:country": "GB",
    "wof:name": "LA12 8JP",
    "wof:placetype": "postalcode"
  },
  "geometry": {"coordinates":[-3.008969,54.256722],"type":"Point"}
}
