{
  "type": "Feature",
  "properties": {
    "date:inception_lower": "1980-01-01",
    "date:inception_upper": "1980-01-01",
    "iso:country": "GB",
    "wof:name": "LA12 8JP",
    "wof:placetype": "postalcode"
  },
  "geometry": {"coordinates":[-3.008969,54.256722],"type":"Point"}
}
