{
  "type": "Feature",
  "properties": {
    "iso:country":"GB",
    "wof:name":"TR4 9EH",
    "wof:placetype":"postalcode"
},
  "geometry": {"coordinates":[-5.1016000707924,50.27752548049366],"type":"Point"}
}