{
  "type": "Feature",
  "properties": {
    "iso:country": "GB",
    "wof:name": "S42 6FE",
    "wof:placetype": "postalcode"
  },
  "geometry": {"coordinates":[-1.428092,53.193959],"type":"Point"}
}
