{
  "type": "Feature",
  "properties": {
    "iso:country":"GB",
    "wof:name":"S42 6FE",
    "wof:placetype":"postalcode"
},
  "geometry": {"coordinates":[-1.42809207957751,53.19395944061894],"type":"Point"}
}