{
  "type": "Feature",
  "properties": {
    "date:inception_lower":"2015-10-01",
    "date:inception_upper":"2015-10-31",
    "iso:country":"GB",
    "wof:name":"S42 6FE",
    "wof:placetype":"postalcode"
},
  "geometry": {"coordinates":[-1.428092,53.193959],"type":"Point"}
}