{
  "type": "Feature",
  "properties": {
    "iso:country": "GB",
    "wof:name": "WR5 2HZ",
    "wof:placetype": "postalcode"
  },
  "geometry": {"coordinates":[-2.203037,52.180351],"type":"Point"}
}
