{
  "type": "Feature",
  "properties": {
    "date:inception_lower": "1980-01-01",
    "date:inception_upper": "1980-01-01",
    "iso:country": "GB",
    "wof:name": "WR5 2HZ",
    "wof:placetype": "postalcode"
  },
  "geometry": {"coordinates":[-2.203037,52.180351],"type":"Point"}
}
