{
  "type": "Feature",
  "properties": {
    "iso:country":"GB",
    "wof:name":"SE8 3BJ",
    "wof:placetype":"postalcode"
},
  "geometry": {"coordinates":[-0.020824205565,51.48122752011413],"type":"Point"}
}