{
  "type": "Feature",
  "properties": {
    "iso:country": "GB",
    "wof:name": "FK21 8RH",
    "wof:placetype": "postalcode"
  },
  "geometry": {"coordinates":[-4.409861,56.427992],"type":"Point"}
}
