{
  "type": "Feature",
  "properties": {
    "iso:country":"GB",
    "wof:name":"LA10 5PG",
    "wof:placetype":"postalcode"
},
  "geometry": {"coordinates":[-2.39358298224208,54.3020220064555],"type":"Point"}
}