{
  "type": "Feature",
  "properties": {
    "iso:country": "GB",
    "wof:name": "LA10 5PG",
    "wof:placetype": "postalcode"
  },
  "geometry": {"coordinates":[-2.393583,54.302022],"type":"Point"}
}
