{
  "type": "Feature",
  "properties": {
    "date:inception_lower": "2019-06-01",
    "date:inception_upper": "2019-06-01",
    "iso:country": "GB",
    "wof:name": "TR18 2GD",
    "wof:placetype": "postalcode"
  },
  "geometry": {"coordinates":[-5.547866,50.122151],"type":"Point"}
}
