{
  "type": "Feature",
  "properties": {
    "iso:country":"GB",
    "wof:name":"LS6 2LQ",
    "wof:placetype":"postalcode"
},
  "geometry": {"coordinates":[-1.5531516242662,53.81610990952912],"type":"Point"}
}