{
  "type": "Feature",
  "properties": {
    "date:inception_lower":"1980-01-01",
    "date:inception_upper":"1980-01-31",
    "iso:country":"GB",
    "wof:name":"SG2 7EF",
    "wof:placetype":"postalcode"
},
  "geometry": {"coordinates":[-0.149409,51.886755],"type":"Point"}
}