{
  "type": "Feature",
  "properties": {
    "iso:country":"GB",
    "wof:name":"SG2 7EF",
    "wof:placetype":"postalcode"
},
  "geometry": {"coordinates":[-0.14953808658492,51.88668621798683],"type":"Point"}
}