{
  "type": "Feature",
  "properties": {
    "iso:country": "GB",
    "wof:name": "SG2 7EF",
    "wof:placetype": "postalcode"
  },
  "geometry": {"coordinates":[-0.149409,51.886755],"type":"Point"}
}
