{
  "type": "Feature",
  "properties": {
    "iso:country": "GB",
    "wof:name": "YO31 0SY",
    "wof:placetype": "postalcode"
  },
  "geometry": {"coordinates":[-1.055356,53.961286],"type":"Point"}
}
