{
  "type": "Feature",
  "properties": {
    "iso:country":"GB",
    "wof:name":"B68 9NX",
    "wof:placetype":"postalcode"
},
  "geometry": {"coordinates":[-1.9961272068479,52.48906002587102],"type":"Point"}
}