{
  "type": "Feature",
  "properties": {
    "iso:country":"GB",
    "wof:name":"DE55 5NX",
    "wof:placetype":"postalcode"
},
  "geometry": {"coordinates":[-1.34544322362886,53.14162235683762],"type":"Point"}
}