{
  "type": "Feature",
  "properties": {
    "iso:country":"GB",
    "wof:name":"B64 7BS",
    "wof:placetype":"postalcode"
},
  "geometry": {"coordinates":[-2.07932824787109,52.46874296835553],"type":"Point"}
}