{
  "type": "Feature",
  "properties": {
    "date:inception_lower": "1980-01-01",
    "date:inception_upper": "1980-01-01",
    "iso:country": "GB",
    "wof:name": "B64 7BS",
    "wof:placetype": "postalcode"
  },
  "geometry": {"coordinates":[-2.079322,52.468758],"type":"Point"}
}
