{
  "type": "Feature",
  "properties": {
    "iso:country": "GB",
    "wof:name": "NN3 7UJ",
    "wof:placetype": "postalcode"
  },
  "geometry": {"coordinates":[-0.856532,52.280539],"type":"Point"}
}
