{
  "type": "Feature",
  "properties": {
    "iso:country":"GB",
    "wof:name":"WD3 5RW",
    "wof:placetype":"postalcode"
},
  "geometry": {"coordinates":[-0.53127464271404,51.65463444772841],"type":"Point"}
}