{
  "type": "Feature",
  "properties": {
    "iso:country": "GB",
    "wof:name": "BS32 8SW",
    "wof:placetype": "postalcode"
  },
  "geometry": {"coordinates":[-2.550714,51.532156],"type":"Point"}
}
