{
  "type": "Feature",
  "properties": {
    "date:inception_lower": "1997-12-01",
    "date:inception_upper": "1997-12-01",
    "iso:country": "GB",
    "wof:name": "BS32 8SW",
    "wof:placetype": "postalcode"
  },
  "geometry": {"coordinates":[-2.550714,51.532156],"type":"Point"}
}
