{
  "type": "Feature",
  "properties": {
    "iso:country": "GB",
    "wof:name": "AB15 9LB",
    "wof:placetype": "postalcode"
  },
  "geometry": {"coordinates":[-2.176431,57.122282],"type":"Point"}
}
