{
  "type": "Feature",
  "properties": {
    "iso:country":"GB",
    "wof:name":"AB15 9LB",
    "wof:placetype":"postalcode"
},
  "geometry": {"coordinates":[-2.17643119635128,57.12228249786374],"type":"Point"}
}