{
  "type": "Feature",
  "properties": {
    "iso:country": "GB",
    "wof:name": "MK43 0XL",
    "wof:placetype": "postalcode"
  },
  "geometry": {"coordinates":[-0.571286,52.006538],"type":"Point"}
}
