{
  "type": "Feature",
  "properties": {
    "iso:country":"GB",
    "wof:name":"CT7 9NW",
    "wof:placetype":"postalcode"
},
  "geometry": {"coordinates":[1.29152093113231,51.38010794284222],"type":"Point"}
}