{
  "type": "Feature",
  "properties": {
    "iso:country":"GB",
    "wof:name":"IG8 7JD",
    "wof:placetype":"postalcode"
},
  "geometry": {"coordinates":[0.04194304731474,51.60691209001877],"type":"Point"}
}