{
  "type": "Feature",
  "properties": {
    "date:inception_lower": "2006-11-01",
    "date:inception_upper": "2006-11-01",
    "iso:country": "GB",
    "wof:name": "PL6 7PS",
    "wof:placetype": "postalcode"
  },
  "geometry": {"coordinates":[-4.089625,50.41764],"type":"Point"}
}
