{
  "type": "Feature",
  "properties": {
    "iso:country":"GB",
    "wof:name":"PL6 7PS",
    "wof:placetype":"postalcode"
},
  "geometry": {"coordinates":[-4.08962553285529,50.4176404608132],"type":"Point"}
}