{
  "type": "Feature",
  "properties": {
    "iso:country":"GB",
    "wof:name":"DE55 2BD",
    "wof:placetype":"postalcode"
},
  "geometry": {"coordinates":[-1.34947290141333,53.10147195832617],"type":"Point"}
}