{
  "type": "Feature",
  "properties": {
    "iso:country":"GB",
    "wof:name":"L20 6FB",
    "wof:placetype":"postalcode"
},
  "geometry": {"coordinates":[-2.98803699945128,53.46403153802414],"type":"Point"}
}