{
  "type": "Feature",
  "properties": {
    "iso:country": "GB",
    "wof:name": "TF1 5PP",
    "wof:placetype": "postalcode"
  },
  "geometry": {"coordinates":[-2.479836,52.703543],"type":"Point"}
}
