{
  "type": "Feature",
  "properties": {
    "date:inception_lower": "2019-06-01",
    "date:inception_upper": "2019-06-01",
    "iso:country": "GB",
    "wof:name": "TF1 5PP",
    "wof:placetype": "postalcode"
  },
  "geometry": {"coordinates":[-2.479836,52.703543],"type":"Point"}
}
