{
  "type": "Feature",
  "properties": {
    "date:inception_lower": "1999-12-01",
    "date:inception_upper": "1999-12-01",
    "iso:country": "GB",
    "wof:name": "CO5 0QW",
    "wof:placetype": "postalcode"
  },
  "geometry": {"coordinates":[0.756562,51.813982],"type":"Point"}
}
