{
  "type": "Feature",
  "properties": {
    "iso:country":"GB",
    "wof:name":"CO5 0QW",
    "wof:placetype":"postalcode"
},
  "geometry": {"coordinates":[0.75656229364601,51.81398238616809],"type":"Point"}
}