{
  "type": "Feature",
  "properties": {
    "iso:country":"GB",
    "wof:name":"NP19 8GT",
    "wof:placetype":"postalcode"
},
  "geometry": {"coordinates":[-2.97131034948203,51.59136174686421],"type":"Point"}
}