{
  "type": "Feature",
  "properties": {
    "iso:country": "GB",
    "wof:name": "NP19 8GT",
    "wof:placetype": "postalcode"
  },
  "geometry": {"coordinates":[-2.97131,51.591362],"type":"Point"}
}
