{
  "type": "Feature",
  "properties": {
    "iso:country": "GB",
    "wof:name": "CM8 3FY",
    "wof:placetype": "postalcode"
  },
  "geometry": {"coordinates":[0.623232,51.851721],"type":"Point"}
}
