{
  "type": "Feature",
  "properties": {
    "iso:country":"GB",
    "wof:name":"OL1 3AE",
    "wof:placetype":"postalcode"
},
  "geometry": {"coordinates":[-2.11410335737068,53.54223610630758],"type":"Point"}
}