{
  "type": "Feature",
  "properties": {
    "iso:country":"GB",
    "wof:name":"TA9 4BE",
    "wof:placetype":"postalcode"
},
  "geometry": {"coordinates":[-2.96288909144042,51.25655620822565],"type":"Point"}
}