{
  "type": "Feature",
  "properties": {
    "date:inception_lower": "1980-01-01",
    "date:inception_upper": "1980-01-01",
    "iso:country": "GB",
    "wof:name": "TA9 4BE",
    "wof:placetype": "postalcode"
  },
  "geometry": {"coordinates":[-2.962255,51.256683],"type":"Point"}
}
