{
  "type": "Feature",
  "properties": {
    "iso:country": "GB",
    "wof:name": "BN22 8QN",
    "wof:placetype": "postalcode"
  },
  "geometry": {"coordinates":[0.30152,50.784785],"type":"Point"}
}
