{
  "type": "Feature",
  "properties": {
    "iso:country":"GB",
    "wof:name":"BN22 8QN",
    "wof:placetype":"postalcode"
},
  "geometry": {"coordinates":[0.30149083917033,50.78478992830875],"type":"Point"}
}