{
  "type": "Feature",
  "properties": {
    "date:inception_lower": "2007-01-01",
    "date:inception_upper": "2007-01-01",
    "iso:country": "GB",
    "wof:name": "OL5 9GB",
    "wof:placetype": "postalcode"
  },
  "geometry": {"coordinates":[-2.037514,53.51745],"type":"Point"}
}
