{
  "type": "Feature",
  "properties": {
    "date:inception_lower": "1998-06-01",
    "date:inception_upper": "1998-06-01",
    "iso:country": "GB",
    "wof:name": "YO61 3ES",
    "wof:placetype": "postalcode"
  },
  "geometry": {"coordinates":[-1.169293,54.112412],"type":"Point"}
}
