{
  "type": "Feature",
  "properties": {
    "iso:country": "GB",
    "wof:name": "YO61 3ES",
    "wof:placetype": "postalcode"
  },
  "geometry": {"coordinates":[-1.169575,54.11209],"type":"Point"}
}
