{
  "type": "Feature",
  "properties": {
    "date:inception_lower": "1998-06-01",
    "date:inception_upper": "1998-06-01",
    "iso:country": "GB",
    "wof:name": "YO61 3ES",
    "wof:placetype": "postalcode"
  },
  "geometry": {"coordinates":[-1.16948,54.112242],"type":"Point"}
}
