{
  "type": "Feature",
  "properties": {
    "iso:country":"GB",
    "wof:name":"YO61 3ES",
    "wof:placetype":"postalcode"
},
  "geometry": {"coordinates":[-1.16947386244445,54.11206485560027],"type":"Point"}
}