{
  "type": "Feature",
  "properties": {
    "iso:country":"GB",
    "wof:name":"DT10 1BJ",
    "wof:placetype":"postalcode"
},
  "geometry": {"coordinates":[-2.29686225081775,50.93049931222168],"type":"Point"}
}