{
  "type": "Feature",
  "properties": {
    "iso:country":"GB",
    "wof:name":"SW9 6HY",
    "wof:placetype":"postalcode"
},
  "geometry": {"coordinates":[-0.10809349220492,51.47722757481585],"type":"Point"}
}