{
  "type": "Feature",
  "properties": {
    "iso:country":"GB",
    "wof:name":"L39 3RN",
    "wof:placetype":"postalcode"
},
  "geometry": {"coordinates":[-2.88732108264766,53.56770674885342],"type":"Point"}
}