{
  "type": "Feature",
  "properties": {
    "iso:country": "GB",
    "wof:name": "L39 3RN",
    "wof:placetype": "postalcode"
  },
  "geometry": {"coordinates":[-2.887319,53.567723],"type":"Point"}
}
