{
  "type": "Feature",
  "properties": {
    "date:inception_lower": "1984-02-01",
    "date:inception_upper": "1984-02-01",
    "iso:country": "GB",
    "wof:name": "RG2 0JS",
    "wof:placetype": "postalcode"
  },
  "geometry": {"coordinates":[-0.969372,51.436463],"type":"Point"}
}
