{
  "type": "Feature",
  "properties": {
    "iso:country":"GB",
    "wof:name":"NG7 2EY",
    "wof:placetype":"postalcode"
},
  "geometry": {"coordinates":[-1.17490605626135,52.94737303211776],"type":"Point"}
}