{
  "type": "Feature",
  "properties": {
    "iso:country": "GB",
    "wof:name": "NG7 2EY",
    "wof:placetype": "postalcode"
  },
  "geometry": {"coordinates":[-1.174906,52.947373],"type":"Point"}
}
