{
  "type": "Feature",
  "properties": {
    "iso:country":"GB",
    "wof:name":"TD15 2DN",
    "wof:placetype":"postalcode"
},
  "geometry": {"coordinates":[-2.00131260659911,55.75740849385583],"type":"Point"}
}