{
  "type": "Feature",
  "properties": {
    "iso:country":"GB",
    "wof:name":"WN7 3SD",
    "wof:placetype":"postalcode"
},
  "geometry": {"coordinates":[-2.48614763795722,53.48391917817792],"type":"Point"}
}