{
  "type": "Feature",
  "properties": {
    "iso:country": "GB",
    "wof:name": "WN7 3SD",
    "wof:placetype": "postalcode"
  },
  "geometry": {"coordinates":[-2.508391,53.479015],"type":"Point"}
}
