{
  "type": "Feature",
  "properties": {
    "iso:country":"GB",
    "wof:name":"LE8 5SF",
    "wof:placetype":"postalcode"
},
  "geometry": {"coordinates":[-1.1448298840759,52.55599589993131],"type":"Point"}
}