{
  "type": "Feature",
  "properties": {
    "iso:country":"GB",
    "wof:name":"PL1 5DF",
    "wof:placetype":"postalcode"
},
  "geometry": {"coordinates":[-4.14826119361196,50.37604345485982],"type":"Point"}
}