{
  "type": "Feature",
  "properties": {
    "iso:country": "GB",
    "wof:name": "WN2 5LY",
    "wof:placetype": "postalcode"
  },
  "geometry": {"coordinates":[-2.611765,53.505714],"type":"Point"}
}
