{
  "type": "Feature",
  "properties": {
    "iso:country":"GB",
    "wof:name":"ME7 4RB",
    "wof:placetype":"postalcode"
},
  "geometry": {"coordinates":[0.55603303213986,51.38480113770283],"type":"Point"}
}