{
  "type": "Feature",
  "properties": {
    "date:inception_lower": "1980-01-01",
    "date:inception_upper": "1980-01-01",
    "iso:country": "GB",
    "wof:name": "NR11 8HZ",
    "wof:placetype": "postalcode"
  },
  "geometry": {"coordinates":[1.37479,52.900452],"type":"Point"}
}
