{
  "type": "Feature",
  "properties": {
    "iso:country": "GB",
    "wof:name": "NR11 8HZ",
    "wof:placetype": "postalcode"
  },
  "geometry": {"coordinates":[1.374658,52.900474],"type":"Point"}
}
