{
  "type": "Feature",
  "properties": {
    "iso:country":"GB",
    "wof:name":"SE6 4NB",
    "wof:placetype":"postalcode"
},
  "geometry": {"coordinates":[-0.02978760283976,51.43865411341332],"type":"Point"}
}