{
  "type": "Feature",
  "properties": {
    "iso:country":"GB",
    "wof:name":"RG9 1HU",
    "wof:placetype":"postalcode"
},
  "geometry": {"coordinates":[-0.90238996412374,51.52935222205608],"type":"Point"}
}