{
  "type": "Feature",
  "properties": {
    "iso:country": "GB",
    "wof:name": "NR16 2SE",
    "wof:placetype": "postalcode"
  },
  "geometry": {"coordinates":[0.904699,52.427115],"type":"Point"}
}
