{
  "type": "Feature",
  "properties": {
    "iso:country":"GB",
    "wof:name":"NR16 2SE",
    "wof:placetype":"postalcode"
},
  "geometry": {"coordinates":[0.90469913193157,52.42711531453828],"type":"Point"}
}