{
  "type": "Feature",
  "properties": {
    "date:inception_lower": "1980-01-01",
    "date:inception_upper": "1980-01-01",
    "iso:country": "GB",
    "wof:name": "LL12 8NH",
    "wof:placetype": "postalcode"
  },
  "geometry": {"coordinates":[-2.968162,53.086193],"type":"Point"}
}
