{
  "type": "Feature",
  "properties": {
    "iso:country": "GB",
    "wof:name": "ST10 4HB",
    "wof:placetype": "postalcode"
  },
  "geometry": {"coordinates":[-1.957409,52.962147],"type":"Point"}
}
