{
  "type": "Feature",
  "properties": {
    "date:inception_lower": "2013-11-01",
    "date:inception_upper": "2013-11-01",
    "iso:country": "GB",
    "wof:name": "CV9 1BD",
    "wof:placetype": "postalcode"
  },
  "geometry": {"coordinates":[-1.549031,52.577814],"type":"Point"}
}
