{
  "type": "Feature",
  "properties": {
    "iso:country": "GB",
    "wof:name": "TA1 2NG",
    "wof:placetype": "postalcode"
  },
  "geometry": {"coordinates":[-3.071204,51.01626],"type":"Point"}
}
