{
  "type": "Feature",
  "properties": {
    "iso:country":"GB",
    "wof:name":"TA1 2NG",
    "wof:placetype":"postalcode"
},
  "geometry": {"coordinates":[-3.07113513984172,51.01607705020478],"type":"Point"}
}