{
  "type": "Feature",
  "properties": {
    "date:inception_lower":"2007-03-01",
    "date:inception_upper":"2007-03-31",
    "iso:country":"GB",
    "wof:name":"TA1 2NG",
    "wof:placetype":"postalcode"
},
  "geometry": {"coordinates":[-3.071204,51.01626],"type":"Point"}
}