{
  "type": "Feature",
  "properties": {
    "date:inception_lower": "1993-01-01",
    "date:inception_upper": "1993-01-01",
    "iso:country": "GB",
    "wof:name": "CF62 6SJ",
    "wof:placetype": "postalcode"
  },
  "geometry": {"coordinates":[-3.288398,51.392931],"type":"Point"}
}
