{
  "type": "Feature",
  "properties": {
    "iso:country":"GB",
    "wof:name":"AL1 1XB",
    "wof:placetype":"postalcode"
},
  "geometry": {"coordinates":[-0.31766754671522,51.73500824739666],"type":"Point"}
}