{
  "type": "Feature",
  "properties": {
    "iso:country":"GB",
    "wof:name":"PE13 3LN",
    "wof:placetype":"postalcode"
},
  "geometry": {"coordinates":[0.16197586862099,52.6760216084502],"type":"Point"}
}