{
  "type": "Feature",
  "properties": {
    "iso:country": "GB",
    "wof:name": "CM8 3UA",
    "wof:placetype": "postalcode"
  },
  "geometry": {"coordinates":[0.644674,51.807983],"type":"Point"}
}
