{
  "type": "Feature",
  "properties": {
    "iso:country":"GB",
    "wof:name":"CM8 3UA",
    "wof:placetype":"postalcode"
},
  "geometry": {"coordinates":[0.6446737626344,51.80798272240344],"type":"Point"}
}