{
  "type": "Feature",
  "properties": {
    "iso:country": "GB",
    "wof:name": "BH8 9PS",
    "wof:placetype": "postalcode"
  },
  "geometry": {"coordinates":[-1.85159,50.74917],"type":"Point"}
}
