{
  "type": "Feature",
  "properties": {
    "iso:country":"GB",
    "wof:name":"NE26 3AQ",
    "wof:placetype":"postalcode"
},
  "geometry": {"coordinates":[-1.46057751465682,55.04775745197799],"type":"Point"}
}