{
  "type": "Feature",
  "properties": {
    "iso:country": "GB",
    "wof:name": "DE1 2LY",
    "wof:placetype": "postalcode"
  },
  "geometry": {"coordinates":[-1.466525,52.9163],"type":"Point"}
}
