{
  "type": "Feature",
  "properties": {
    "iso:country":"GB",
    "wof:name":"PH10 6DF",
    "wof:placetype":"postalcode"
},
  "geometry": {"coordinates":[-3.34040877497353,56.59142208455405],"type":"Point"}
}