{
  "type": "Feature",
  "properties": {
    "date:inception_lower": "1980-01-01",
    "date:inception_upper": "1980-01-01",
    "iso:country": "GB",
    "wof:name": "PH10 6DF",
    "wof:placetype": "postalcode"
  },
  "geometry": {"coordinates":[-3.3402,56.591503],"type":"Point"}
}
