{
  "type": "Feature",
  "properties": {
    "iso:country": "GB",
    "wof:name": "BD4 6FF",
    "wof:placetype": "postalcode"
  },
  "geometry": {"coordinates":[-1.725928,53.765945],"type":"Point"}
}
