{
  "type": "Feature",
  "properties": {
    "iso:country": "GB",
    "wof:name": "GL1 5TD",
    "wof:placetype": "postalcode"
  },
  "geometry": {"coordinates":[-2.261011,51.847779],"type":"Point"}
}
