{
  "type": "Feature",
  "properties": {
    "date:inception_lower": "1980-01-01",
    "date:inception_upper": "1980-01-01",
    "iso:country": "GB",
    "wof:name": "WA4 4SA",
    "wof:placetype": "postalcode"
  },
  "geometry": {"coordinates":[-2.544486,53.346483],"type":"Point"}
}
