{
  "type": "Feature",
  "properties": {
    "iso:country":"GB",
    "wof:name":"WA4 4SA",
    "wof:placetype":"postalcode"
},
  "geometry": {"coordinates":[-2.54448605417121,53.34648272118548],"type":"Point"}
}