{
  "type": "Feature",
  "properties": {
    "iso:country": "GB",
    "wof:name": "SN16 9GW",
    "wof:placetype": "postalcode"
  },
  "geometry": {"coordinates":[-2.10199,51.596588],"type":"Point"}
}
