{
  "type": "Feature",
  "properties": {
    "iso:country":"GB",
    "wof:name":"CT14 7QW",
    "wof:placetype":"postalcode"
},
  "geometry": {"coordinates":[1.39526891845878,51.19935413102676],"type":"Point"}
}