{
  "type": "Feature",
  "properties": {
    "date:inception_lower": "1994-05-01",
    "date:inception_upper": "1994-05-01",
    "iso:country": "GB",
    "wof:name": "CT14 7QW",
    "wof:placetype": "postalcode"
  },
  "geometry": {"coordinates":[1.395312,51.199344],"type":"Point"}
}
