{
  "type": "Feature",
  "properties": {
    "iso:country":"GB",
    "wof:name":"M30 7BY",
    "wof:placetype":"postalcode"
},
  "geometry": {"coordinates":[-2.37057582061551,53.47660354208844],"type":"Point"}
}