{
  "type": "Feature",
  "properties": {
    "iso:country":"GB",
    "wof:name":"SE17 1DP",
    "wof:placetype":"postalcode"
},
  "geometry": {"coordinates":[-0.09395143868292,51.48829324283098],"type":"Point"}
}