{
  "type": "Feature",
  "properties": {
    "date:inception_lower": "1980-01-01",
    "date:inception_upper": "1980-01-01",
    "iso:country": "GB",
    "wof:name": "SE17 1DP",
    "wof:placetype": "postalcode"
  },
  "geometry": {"coordinates":[-0.093951,51.488293],"type":"Point"}
}
