{
  "type": "Feature",
  "properties": {
    "iso:country": "GB",
    "wof:name": "CB23 1JG",
    "wof:placetype": "postalcode"
  },
  "geometry": {"coordinates":[0.049611,52.150899],"type":"Point"}
}
