{
  "type": "Feature",
  "properties": {
    "iso:country": "GB",
    "wof:name": "SO14 2AR",
    "wof:placetype": "postalcode"
  },
  "geometry": {"coordinates":[-1.405026,50.896873],"type":"Point"}
}
