{
  "type": "Feature",
  "properties": {
    "iso:country": "GB",
    "wof:name": "WF1 2SQ",
    "wof:placetype": "postalcode"
  },
  "geometry": {"coordinates":[-1.50036,53.683047],"type":"Point"}
}
