{
  "type": "Feature",
  "properties": {
    "iso:country": "GB",
    "wof:name": "NW2 1TB",
    "wof:placetype": "postalcode"
  },
  "geometry": {"coordinates":[-0.213795,51.560474],"type":"Point"}
}
