{
  "type": "Feature",
  "properties": {
    "iso:country":"GB",
    "wof:name":"NW2 1TB",
    "wof:placetype":"postalcode"
},
  "geometry": {"coordinates":[-0.2137947726536,51.56047359195203],"type":"Point"}
}