{
  "type": "Feature",
  "properties": {
    "iso:country": "GB",
    "wof:name": "EN8 8BQ",
    "wof:placetype": "postalcode"
  },
  "geometry": {"coordinates":[-0.035466,51.686818],"type":"Point"}
}
