{
  "type": "Feature",
  "properties": {
    "iso:country":"GB",
    "wof:name":"EN8 8BQ",
    "wof:placetype":"postalcode"
},
  "geometry": {"coordinates":[-0.03546611922402,51.68681826443704],"type":"Point"}
}