{
  "type": "Feature",
  "properties": {
    "iso:country": "GB",
    "wof:name": "SN3 3NP",
    "wof:placetype": "postalcode"
  },
  "geometry": {"coordinates":[-1.743486,51.565503],"type":"Point"}
}
