{
  "type": "Feature",
  "properties": {
    "iso:country": "GB",
    "wof:name": "YO61 1NU",
    "wof:placetype": "postalcode"
  },
  "geometry": {"coordinates":[-1.085878,54.118272],"type":"Point"}
}
