{
  "type": "Feature",
  "properties": {
    "date:inception_lower":"2004-08-01",
    "date:inception_upper":"2004-08-31",
    "iso:country":"GB",
    "wof:name":"PR25 2YA",
    "wof:placetype":"postalcode"
},
  "geometry": {"coordinates":[-2.691105,53.695594],"type":"Point"}
}