{
  "type": "Feature",
  "properties": {
    "iso:country":"GB",
    "wof:name":"PR25 2YA",
    "wof:placetype":"postalcode"
},
  "geometry": {"coordinates":[-2.69110547211629,53.69559431718013],"type":"Point"}
}