{
  "type": "Feature",
  "properties": {
    "iso:country": "GB",
    "wof:name": "PR25 2YA",
    "wof:placetype": "postalcode"
  },
  "geometry": {"coordinates":[-2.691105,53.695594],"type":"Point"}
}
