{
  "type": "Feature",
  "properties": {
    "iso:country":"GB",
    "wof:name":"NR3 1UF",
    "wof:placetype":"postalcode"
},
  "geometry": {"coordinates":[1.2977474348973,52.63346669368515],"type":"Point"}
}