{
  "type": "Feature",
  "properties": {
    "iso:country":"GB",
    "wof:name":"B62 9TB",
    "wof:placetype":"postalcode"
},
  "geometry": {"coordinates":[-2.02158991692782,52.45835732334457],"type":"Point"}
}