{
  "type": "Feature",
  "properties": {
    "iso:country":"GB",
    "wof:name":"NR33 8JQ",
    "wof:placetype":"postalcode"
},
  "geometry": {"coordinates":[1.70187054100473,52.44996749256268],"type":"Point"}
}