{
  "type": "Feature",
  "properties": {
    "date:inception_lower": "1980-01-01",
    "date:inception_upper": "1980-01-01",
    "iso:country": "GB",
    "wof:name": "NR33 8JQ",
    "wof:placetype": "postalcode"
  },
  "geometry": {"coordinates":[1.701871,52.449967],"type":"Point"}
}
