{
  "type": "Feature",
  "properties": {
    "iso:country":"GB",
    "wof:name":"DA1 2ND",
    "wof:placetype":"postalcode"
},
  "geometry": {"coordinates":[0.2108455149564,51.44414639107519],"type":"Point"}
}