{
  "type": "Feature",
  "properties": {
    "iso:country":"GB",
    "wof:name":"LN5 8RB",
    "wof:placetype":"postalcode"
},
  "geometry": {"coordinates":[-0.55279134000011,53.20382230735372],"type":"Point"}
}