{
  "type": "Feature",
  "properties": {
    "iso:country":"GB",
    "wof:name":"LL65 2HH",
    "wof:placetype":"postalcode"
},
  "geometry": {"coordinates":[-4.62710373884215,53.30702192190672],"type":"Point"}
}