{
  "type": "Feature",
  "properties": {
    "iso:country":"GB",
    "wof:name":"WF9 1EP",
    "wof:placetype":"postalcode"
},
  "geometry": {"coordinates":[-1.26222479374786,53.61976272305716],"type":"Point"}
}