{
  "type": "Feature",
  "properties": {
    "iso:country": "GB",
    "wof:name": "WF9 1EP",
    "wof:placetype": "postalcode"
  },
  "geometry": {"coordinates":[-1.261729,53.61976],"type":"Point"}
}
