{
  "type": "Feature",
  "properties": {
    "iso:country":"GB",
    "wof:name":"DD1 5HA",
    "wof:placetype":"postalcode"
},
  "geometry": {"coordinates":[-2.98877626005994,56.45956220549222],"type":"Point"}
}