{
  "type": "Feature",
  "properties": {
    "iso:country": "GB",
    "wof:name": "DD1 5HA",
    "wof:placetype": "postalcode"
  },
  "geometry": {"coordinates":[-2.988776,56.459562],"type":"Point"}
}
