{
  "type": "Feature",
  "properties": {
    "iso:country":"GB",
    "wof:name":"RG1 4RF",
    "wof:placetype":"postalcode"
},
  "geometry": {"coordinates":[-0.96132224468652,51.45328745820652],"type":"Point"}
}