{
  "type": "Feature",
  "properties": {
    "iso:country":"GB",
    "wof:name":"IP12 3RQ",
    "wof:placetype":"postalcode"
},
  "geometry": {"coordinates":[1.4275446160247,52.04757232241528],"type":"Point"}
}