{
  "type": "Feature",
  "properties": {
    "iso:country":"GB",
    "wof:name":"SG5 4EQ",
    "wof:placetype":"postalcode"
},
  "geometry": {"coordinates":[-0.2293053665822,52.02026387652785],"type":"Point"}
}