{
  "type": "Feature",
  "properties": {
    "iso:country":"GB",
    "wof:name":"CF10 5JG",
    "wof:placetype":"postalcode"
},
  "geometry": {"coordinates":[-3.17092826140062,51.4701100151977],"type":"Point"}
}