{
  "type": "Feature",
  "properties": {
    "date:inception_lower": "1980-01-01",
    "date:inception_upper": "1980-01-01",
    "iso:country": "GB",
    "wof:name": "SR2 0EW",
    "wof:placetype": "postalcode"
  },
  "geometry": {"coordinates":[-1.376265,54.876299],"type":"Point"}
}
