{
  "type": "Feature",
  "properties": {
    "iso:country":"GB",
    "wof:name":"SR2 0EW",
    "wof:placetype":"postalcode"
},
  "geometry": {"coordinates":[-1.37626507001742,54.87629890513124],"type":"Point"}
}