{
  "type": "Feature",
  "properties": {
    "iso:country":"GB",
    "wof:name":"BB2 6JJ",
    "wof:placetype":"postalcode"
},
  "geometry": {"coordinates":[-2.5059725784037,53.75376537243616],"type":"Point"}
}