{
  "type": "Feature",
  "properties": {
    "iso:country": "GB",
    "wof:name": "BB2 6JJ",
    "wof:placetype": "postalcode"
  },
  "geometry": {"coordinates":[-2.505973,53.753765],"type":"Point"}
}
