{
  "type": "Feature",
  "properties": {
    "iso:country":"GB",
    "wof:name":"BN2 3EL",
    "wof:placetype":"postalcode"
},
  "geometry": {"coordinates":[-0.1183958201437,50.83167601116082],"type":"Point"}
}