{
  "type": "Feature",
  "properties": {
    "date:inception_lower": "1980-01-01",
    "date:inception_upper": "1980-01-01",
    "iso:country": "GB",
    "wof:name": "PO36 8NZ",
    "wof:placetype": "postalcode"
  },
  "geometry": {"coordinates":[-1.164559,50.649499],"type":"Point"}
}
