{
  "type": "Feature",
  "properties": {
    "date:inception_lower":"1980-01-01",
    "date:inception_upper":"1980-01-31",
    "iso:country":"GB",
    "wof:name":"TA2 7HG",
    "wof:placetype":"postalcode"
},
  "geometry": {"coordinates":[-3.089976,51.030435],"type":"Point"}
}