{
  "type": "Feature",
  "properties": {
    "iso:country":"GB",
    "wof:name":"LL12 7RY",
    "wof:placetype":"postalcode"
},
  "geometry": {"coordinates":[-2.97632517387636,53.06492943354674],"type":"Point"}
}