{
  "type": "Feature",
  "properties": {
    "iso:country": "GB",
    "wof:name": "SA18 1HE",
    "wof:placetype": "postalcode"
  },
  "geometry": {"coordinates":[-3.883853,51.789798],"type":"Point"}
}
