{
  "type": "Feature",
  "properties": {
    "iso:country": "GB",
    "wof:name": "SA18 1HE",
    "wof:placetype": "postalcode"
  },
  "geometry": {"coordinates":[-3.883829,51.789841],"type":"Point"}
}
