{
  "type": "Feature",
  "properties": {
    "date:inception_lower": "1992-08-01",
    "date:inception_upper": "1992-08-01",
    "iso:country": "GB",
    "wof:name": "OX33 1AQ",
    "wof:placetype": "postalcode"
  },
  "geometry": {"coordinates":[-1.169312,51.790199],"type":"Point"}
}
