{
  "type": "Feature",
  "properties": {
    "iso:country":"GB",
    "wof:name":"CW1 6XU",
    "wof:placetype":"postalcode"
},
  "geometry": {"coordinates":[-2.42242218864754,53.08758468353588],"type":"Point"}
}