{
  "type": "Feature",
  "properties": {
    "iso:country":"GB",
    "wof:name":"KW17 2AB",
    "wof:placetype":"postalcode"
},
  "geometry": {"coordinates":[-2.7621839187838,59.22502477055608],"type":"Point"}
}