{
  "type": "Feature",
  "properties": {
    "iso:country":"GB",
    "wof:name":"SO18 6BG",
    "wof:placetype":"postalcode"
},
  "geometry": {"coordinates":[-1.35821212798125,50.91784762499975],"type":"Point"}
}