{
  "type": "Feature",
  "properties": {
    "iso:country":"GB",
    "wof:name":"EX4 3HJ",
    "wof:placetype":"postalcode"
},
  "geometry": {"coordinates":[-3.53305579297212,50.72406614712409],"type":"Point"}
}