{
  "type": "Feature",
  "properties": {
    "date:inception_lower": "1980-01-01",
    "date:inception_upper": "1980-01-01",
    "iso:country": "GB",
    "wof:name": "BH20 7LE",
    "wof:placetype": "postalcode"
  },
  "geometry": {"coordinates":[-2.214874,50.752781],"type":"Point"}
}
