{
  "type": "Feature",
  "properties": {
    "iso:country":"GB",
    "wof:name":"LL30 1BP",
    "wof:placetype":"postalcode"
},
  "geometry": {"coordinates":[-3.80640784081064,53.32034754513734],"type":"Point"}
}