{
  "type": "Feature",
  "properties": {
    "iso:country": "GB",
    "wof:name": "OL1 2XQ",
    "wof:placetype": "postalcode"
  },
  "geometry": {"coordinates":[-2.118398,53.545405],"type":"Point"}
}
