{
  "type": "Feature",
  "properties": {
    "iso:country":"GB",
    "wof:name":"OL1 2XQ",
    "wof:placetype":"postalcode"
},
  "geometry": {"coordinates":[-2.11839781512211,53.5454048082706],"type":"Point"}
}