{
  "type": "Feature",
  "properties": {
    "iso:country": "GB",
    "wof:name": "NW6 4BX",
    "wof:placetype": "postalcode"
  },
  "geometry": {"coordinates":[-0.188023,51.53929],"type":"Point"}
}
