{
  "type": "Feature",
  "properties": {
    "iso:country":"GB",
    "wof:name":"GL15 6DD",
    "wof:placetype":"postalcode"
},
  "geometry": {"coordinates":[-2.55459048016435,51.71560693680188],"type":"Point"}
}