{
  "type": "Feature",
  "properties": {
    "iso:country": "GB",
    "wof:name": "MK45 2TD",
    "wof:placetype": "postalcode"
  },
  "geometry": {"coordinates":[-0.490081,52.027168],"type":"Point"}
}
