{
  "type": "Feature",
  "properties": {
    "iso:country": "GB",
    "wof:name": "WR11 4LJ",
    "wof:placetype": "postalcode"
  },
  "geometry": {"coordinates":[-1.949384,52.100581],"type":"Point"}
}
