{
  "type": "Feature",
  "properties": {
    "iso:country": "GB",
    "wof:name": "CM3 5PF",
    "wof:placetype": "postalcode"
  },
  "geometry": {"coordinates":[0.610659,51.650551],"type":"Point"}
}
