{
  "type": "Feature",
  "properties": {
    "iso:country":"GB",
    "wof:name":"CM3 5PF",
    "wof:placetype":"postalcode"
},
  "geometry": {"coordinates":[0.61065929748473,51.6505514335945],"type":"Point"}
}