{
  "type": "Feature",
  "properties": {
    "iso:country":"GB",
    "wof:name":"CH46 3SJ",
    "wof:placetype":"postalcode"
},
  "geometry": {"coordinates":[-3.11321504776037,53.41350009561424],"type":"Point"}
}