{
  "type": "Feature",
  "properties": {
    "iso:country":"GB",
    "wof:name":"ME14 4PX",
    "wof:placetype":"postalcode"
},
  "geometry": {"coordinates":[0.56570701085487,51.27760961222844],"type":"Point"}
}