{
  "type": "Feature",
  "properties": {
    "date:inception_lower": "1988-03-01",
    "date:inception_upper": "1988-03-01",
    "iso:country": "GB",
    "wof:name": "ME14 4PX",
    "wof:placetype": "postalcode"
  },
  "geometry": {"coordinates":[0.565707,51.27761],"type":"Point"}
}
