{
  "type": "Feature",
  "properties": {
    "iso:country":"GB",
    "wof:name":"EH32 0BW",
    "wof:placetype":"postalcode"
},
  "geometry": {"coordinates":[-2.95401480158009,55.96881285985294],"type":"Point"}
}