{
  "type": "Feature",
  "properties": {
    "iso:country":"GB",
    "wof:name":"NE44 6HE",
    "wof:placetype":"postalcode"
},
  "geometry": {"coordinates":[-1.97512993847579,54.94919346593513],"type":"Point"}
}