{
  "type": "Feature",
  "properties": {
    "date:inception_lower": "1980-01-01",
    "date:inception_upper": "1980-01-01",
    "iso:country": "GB",
    "wof:name": "L35 3JG",
    "wof:placetype": "postalcode"
  },
  "geometry": {"coordinates":[-2.79571,53.410663],"type":"Point"}
}
