{
  "type": "Feature",
  "properties": {
    "iso:country":"GB",
    "wof:name":"L35 3JG",
    "wof:placetype":"postalcode"
},
  "geometry": {"coordinates":[-2.79571000196102,53.41066310643757],"type":"Point"}
}