{
  "type": "Feature",
  "properties": {
    "iso:country":"GB",
    "wof:name":"W1T 4BN",
    "wof:placetype":"postalcode"
},
  "geometry": {"coordinates":[-0.13827388566158,51.52221467625905],"type":"Point"}
}