{
  "type": "Feature",
  "properties": {
    "date:inception_lower": "1995-12-01",
    "date:inception_upper": "1995-12-01",
    "iso:country": "GB",
    "wof:name": "LS5 3RX",
    "wof:placetype": "postalcode"
  },
  "geometry": {"coordinates":[-1.609385,53.815434],"type":"Point"}
}
