{
  "type": "Feature",
  "properties": {
    "iso:country":"GB",
    "wof:name":"M40 9DF",
    "wof:placetype":"postalcode"
},
  "geometry": {"coordinates":[-2.19201781787514,53.50983197907379],"type":"Point"}
}