{
  "type": "Feature",
  "properties": {
    "iso:country": "GB",
    "wof:name": "B14 6SE",
    "wof:placetype": "postalcode"
  },
  "geometry": {"coordinates":[-1.908058,52.4256],"type":"Point"}
}
