{
  "type": "Feature",
  "properties": {
    "iso:country":"GB",
    "wof:name":"B14 6SE",
    "wof:placetype":"postalcode"
},
  "geometry": {"coordinates":[-1.90805834229677,52.42560014766799],"type":"Point"}
}