{
  "type": "Feature",
  "properties": {
    "iso:country":"GB",
    "wof:name":"KT7 0EB",
    "wof:placetype":"postalcode"
},
  "geometry": {"coordinates":[-0.33512395704572,51.38643033962005],"type":"Point"}
}