{
  "type": "Feature",
  "properties": {
    "date:inception_lower": "1999-06-01",
    "date:inception_upper": "1999-06-01",
    "iso:country": "GB",
    "wof:name": "KT7 0EB",
    "wof:placetype": "postalcode"
  },
  "geometry": {"coordinates":[-0.335124,51.38643],"type":"Point"}
}
