{
  "type": "Feature",
  "properties": {
    "date:inception_lower": "1981-06-01",
    "date:inception_upper": "1981-06-01",
    "iso:country": "GB",
    "wof:name": "N19 3DH",
    "wof:placetype": "postalcode"
  },
  "geometry": {"coordinates":[-0.129017,51.56658],"type":"Point"}
}
