{
  "type": "Feature",
  "properties": {
    "iso:country": "GB",
    "wof:name": "PL19 9PU",
    "wof:placetype": "postalcode"
  },
  "geometry": {"coordinates":[-4.134718,50.550952],"type":"Point"}
}
