{
  "type": "Feature",
  "properties": {
    "iso:country": "GB",
    "wof:name": "FY4 4QY",
    "wof:placetype": "postalcode"
  },
  "geometry": {"coordinates":[-3.004732,53.798979],"type":"Point"}
}
