{
  "type": "Feature",
  "properties": {
    "iso:country":"GB",
    "wof:name":"B49 5AD",
    "wof:placetype":"postalcode"
},
  "geometry": {"coordinates":[-1.86970722165561,52.21467188779537],"type":"Point"}
}