{
  "type": "Feature",
  "properties": {
    "iso:country":"GB",
    "wof:name":"NE45 5AN",
    "wof:placetype":"postalcode"
},
  "geometry": {"coordinates":[-2.02187229051347,54.97492146342448],"type":"Point"}
}