{
  "type": "Feature",
  "properties": {
    "iso:country":"GB",
    "wof:name":"GU21 4SQ",
    "wof:placetype":"postalcode"
},
  "geometry": {"coordinates":[-0.58084086755821,51.32443360726342],"type":"Point"}
}