{
  "type": "Feature",
  "properties": {
    "iso:country": "GB",
    "wof:name": "BR1 4QW",
    "wof:placetype": "postalcode"
  },
  "geometry": {"coordinates":[0.010498,51.42351],"type":"Point"}
}
