{
  "type": "Feature",
  "properties": {
    "iso:country":"GB",
    "wof:name":"B92 7QW",
    "wof:placetype":"postalcode"
},
  "geometry": {"coordinates":[-1.79418572876552,52.44863336107105],"type":"Point"}
}