{
  "type": "Feature",
  "properties": {
    "iso:country":"GB",
    "wof:name":"DL13 2RU",
    "wof:placetype":"postalcode"
},
  "geometry": {"coordinates":[-1.954599072814,54.72633392554767],"type":"Point"}
}