{
  "type": "Feature",
  "properties": {
    "iso:country":"GB",
    "wof:name":"ME2 2DQ",
    "wof:placetype":"postalcode"
},
  "geometry": {"coordinates":[0.48637586370279,51.39530301497902],"type":"Point"}
}