{
  "type": "Feature",
  "properties": {
    "date:inception_lower": "1998-12-01",
    "date:inception_upper": "1998-12-01",
    "iso:country": "GB",
    "wof:name": "L8 7JZ",
    "wof:placetype": "postalcode"
  },
  "geometry": {"coordinates":[-2.967285,53.399976],"type":"Point"}
}
