{
  "type": "Feature",
  "properties": {
    "iso:country": "GB",
    "wof:name": "L8 7JZ",
    "wof:placetype": "postalcode"
  },
  "geometry": {"coordinates":[-2.967285,53.399976],"type":"Point"}
}
