{
  "type": "Feature",
  "properties": {
    "iso:country": "GB",
    "wof:name": "SK4 4EU",
    "wof:placetype": "postalcode"
  },
  "geometry": {"coordinates":[-2.189241,53.414684],"type":"Point"}
}
