{
  "type": "Feature",
  "properties": {
    "iso:country":"GB",
    "wof:name":"PE32 2LZ",
    "wof:placetype":"postalcode"
},
  "geometry": {"coordinates":[0.80928718152197,52.6979424717473],"type":"Point"}
}