{
  "type": "Feature",
  "properties": {
    "iso:country":"GB",
    "wof:name":"E6 1BJ",
    "wof:placetype":"postalcode"
},
  "geometry": {"coordinates":[0.04689281032383,51.53904825565544],"type":"Point"}
}