{
  "type": "Feature",
  "properties": {
    "iso:country":"GB",
    "wof:name":"SE20 8AN",
    "wof:placetype":"postalcode"
},
  "geometry": {"coordinates":[-0.0673168605602,51.41266050384478],"type":"Point"}
}