{
  "type": "Feature",
  "properties": {
    "iso:country":"GB",
    "wof:name":"DY8 4ET",
    "wof:placetype":"postalcode"
},
  "geometry": {"coordinates":[-2.14818199581233,52.47072632406157],"type":"Point"}
}