{
  "type": "Feature",
  "properties": {
    "iso:country":"GB",
    "wof:name":"DE21 7QA",
    "wof:placetype":"postalcode"
},
  "geometry": {"coordinates":[-1.39302415767273,52.92301290548346],"type":"Point"}
}