{
  "type": "Feature",
  "properties": {
    "iso:country":"GB",
    "wof:name":"NP7 8LR",
    "wof:placetype":"postalcode"
},
  "geometry": {"coordinates":[-2.83148245166194,51.89153180285174],"type":"Point"}
}