{
  "type": "Feature",
  "properties": {
    "iso:country":"GB",
    "wof:name":"EH14 1JS",
    "wof:placetype":"postalcode"
},
  "geometry": {"coordinates":[-3.24579068555865,55.92162227326826],"type":"Point"}
}