{
  "type": "Feature",
  "properties": {
    "date:inception_lower":"1980-01-01",
    "date:inception_upper":"1980-01-31",
    "iso:country":"GB",
    "wof:name":"EH14 1JS",
    "wof:placetype":"postalcode"
},
  "geometry": {"coordinates":[-3.245791,55.921622],"type":"Point"}
}