{
  "type": "Feature",
  "properties": {
    "iso:country": "GB",
    "wof:name": "WR5 1BL",
    "wof:placetype": "postalcode"
  },
  "geometry": {"coordinates":[-2.212158,52.192565],"type":"Point"}
}
