{
  "type": "Feature",
  "properties": {
    "iso:country":"GB",
    "wof:name":"WR5 1BL",
    "wof:placetype":"postalcode"
},
  "geometry": {"coordinates":[-2.21216228258462,52.19252587550378],"type":"Point"}
}