{
  "type": "Feature",
  "properties": {
    "iso:country":"GB",
    "wof:name":"HG1 5EH",
    "wof:placetype":"postalcode"
},
  "geometry": {"coordinates":[-1.53813169689436,53.99821040376591],"type":"Point"}
}