{
  "type": "Feature",
  "properties": {
    "iso:country":"GB",
    "wof:name":"MK45 4HT",
    "wof:placetype":"postalcode"
},
  "geometry": {"coordinates":[-0.41096354414296,52.01517549537365],"type":"Point"}
}