{
  "type": "Feature",
  "properties": {
    "iso:country":"GB",
    "wof:name":"BL4 8RF",
    "wof:placetype":"postalcode"
},
  "geometry": {"coordinates":[-2.35648460313057,53.53183551775768],"type":"Point"}
}