{
  "type": "Feature",
  "properties": {
    "iso:country":"GB",
    "wof:name":"WN3 5QH",
    "wof:placetype":"postalcode"
},
  "geometry": {"coordinates":[-2.64512794861391,53.52234759318083],"type":"Point"}
}