{
  "type": "Feature",
  "properties": {
    "iso:country":"GB",
    "wof:name":"WR15 8JB",
    "wof:placetype":"postalcode"
},
  "geometry": {"coordinates":[-2.52596235165778,52.32067276533159],"type":"Point"}
}