{
  "type": "Feature",
  "properties": {
    "date:inception_lower": "2006-04-01",
    "date:inception_upper": "2006-04-01",
    "iso:country": "GB",
    "wof:name": "WR15 8JB",
    "wof:placetype": "postalcode"
  },
  "geometry": {"coordinates":[-2.52596,52.320686],"type":"Point"}
}
