{
  "type": "Feature",
  "properties": {
    "iso:country":"GB",
    "wof:name":"WA14 4DZ",
    "wof:placetype":"postalcode"
},
  "geometry": {"coordinates":[-2.35139095921154,53.39216013851539],"type":"Point"}
}