{
  "type": "Feature",
  "properties": {
    "iso:country": "GB",
    "wof:name": "WA14 4DZ",
    "wof:placetype": "postalcode"
  },
  "geometry": {"coordinates":[-2.351391,53.39216],"type":"Point"}
}
