{
  "type": "Feature",
  "properties": {
    "iso:country": "GB",
    "wof:name": "AL3 6LL",
    "wof:placetype": "postalcode"
  },
  "geometry": {"coordinates":[-0.323204,51.767492],"type":"Point"}
}
