{
  "type": "Feature",
  "properties": {
    "date:inception_lower": "2019-05-01",
    "date:inception_upper": "2019-05-01",
    "iso:country": "GB",
    "wof:name": "AL3 6LL",
    "wof:placetype": "postalcode"
  },
  "geometry": {"coordinates":[-0.323204,51.767492],"type":"Point"}
}
