{
  "type": "Feature",
  "properties": {
    "iso:country":"GB",
    "wof:name":"AL3 6LL",
    "wof:placetype":"postalcode"
},
  "geometry": {"coordinates":[-0.32314217143911,51.76746658521512],"type":"Point"}
}