{
  "type": "Feature",
  "properties": {
    "date:inception_lower": "1992-08-01",
    "date:inception_upper": "1992-08-01",
    "iso:country": "GB",
    "wof:name": "DE15 9GP",
    "wof:placetype": "postalcode"
  },
  "geometry": {"coordinates":[-1.594237,52.80076],"type":"Point"}
}
