{
  "type": "Feature",
  "properties": {
    "iso:country":"GB",
    "wof:name":"NG7 1PX",
    "wof:placetype":"postalcode"
},
  "geometry": {"coordinates":[-1.17212453967605,52.95352947897129],"type":"Point"}
}