{
  "type": "Feature",
  "properties": {
    "date:inception_lower":"1980-01-01",
    "date:inception_upper":"1980-01-31",
    "iso:country":"GB",
    "wof:name":"NG7 1PX",
    "wof:placetype":"postalcode"
},
  "geometry": {"coordinates":[-1.172124,52.953529],"type":"Point"}
}