{
  "type": "Feature",
  "properties": {
    "iso:country":"GB",
    "wof:name":"LE8 5PE",
    "wof:placetype":"postalcode"
},
  "geometry": {"coordinates":[-1.15998085863489,52.55276001879167],"type":"Point"}
}