{
  "type": "Feature",
  "properties": {
    "iso:country":"GB",
    "wof:name":"S11 8PF",
    "wof:placetype":"postalcode"
},
  "geometry": {"coordinates":[-1.4906124249622,53.37062192333772],"type":"Point"}
}