{
  "type": "Feature",
  "properties": {
    "iso:country": "GB",
    "wof:name": "S11 8PF",
    "wof:placetype": "postalcode"
  },
  "geometry": {"coordinates":[-1.490627,53.370613],"type":"Point"}
}
