{
  "type": "Feature",
  "properties": {
    "iso:country":"GB",
    "wof:name":"PO16 8BQ",
    "wof:placetype":"postalcode"
},
  "geometry": {"coordinates":[-1.123445164861,50.84795073805974],"type":"Point"}
}