{
  "type": "Feature",
  "properties": {
    "iso:country": "GB",
    "wof:name": "RH10 6HW",
    "wof:placetype": "postalcode"
  },
  "geometry": {"coordinates":[-0.172556,51.110086],"type":"Point"}
}
