{
  "type": "Feature",
  "properties": {
    "date:inception_lower": "1992-08-01",
    "date:inception_upper": "1992-08-01",
    "iso:country": "GB",
    "wof:name": "M1 1LT",
    "wof:placetype": "postalcode"
  },
  "geometry": {"coordinates":[-2.237142,53.481662],"type":"Point"}
}
