{
  "type": "Feature",
  "properties": {
    "iso:country":"GB",
    "wof:name":"PE27 3FD",
    "wof:placetype":"postalcode"
},
  "geometry": {"coordinates":[-0.07188562316771,52.33950560004015],"type":"Point"}
}