{
  "type": "Feature",
  "properties": {
    "iso:country":"GB",
    "wof:name":"WR2 5UF",
    "wof:placetype":"postalcode"
},
  "geometry": {"coordinates":[-2.25569055784349,52.18611921853007],"type":"Point"}
}