{
  "type": "Feature",
  "properties": {
    "date:inception_lower":"1980-01-01",
    "date:inception_upper":"1980-01-31",
    "iso:country":"GB",
    "wof:name":"EH32 9HD",
    "wof:placetype":"postalcode"
},
  "geometry": {"coordinates":[-2.967603,55.956065],"type":"Point"}
}