{
  "type": "Feature",
  "properties": {
    "iso:country":"GB",
    "wof:name":"EH32 9HD",
    "wof:placetype":"postalcode"
},
  "geometry": {"coordinates":[-2.96760313217222,55.95606472363222],"type":"Point"}
}