{
  "type": "Feature",
  "properties": {
    "date:inception_lower":"2010-06-01",
    "date:inception_upper":"2010-06-30",
    "iso:country":"GB",
    "wof:name":"OX5 1FS",
    "wof:placetype":"postalcode"
},
  "geometry": {"coordinates":[-1.304832,51.804666],"type":"Point"}
}