{
  "type": "Feature",
  "properties": {
    "iso:country": "GB",
    "wof:name": "OX5 1FS",
    "wof:placetype": "postalcode"
  },
  "geometry": {"coordinates":[-1.304832,51.804666],"type":"Point"}
}
