{
  "type": "Feature",
  "properties": {
    "iso:country":"GB",
    "wof:name":"OX5 1FS",
    "wof:placetype":"postalcode"
},
  "geometry": {"coordinates":[-1.30483176950975,51.80466645793253],"type":"Point"}
}