{
  "type": "Feature",
  "properties": {
    "iso:country": "GB",
    "wof:name": "EH6 4QU",
    "wof:placetype": "postalcode"
  },
  "geometry": {"coordinates":[-3.192216,55.972714],"type":"Point"}
}
