{
  "type": "Feature",
  "properties": {
    "iso:country":"GB",
    "wof:name":"EH47 8JW",
    "wof:placetype":"postalcode"
},
  "geometry": {"coordinates":[-3.67638484473004,55.86565992544111],"type":"Point"}
}