{
  "type": "Feature",
  "properties": {
    "iso:country": "GB",
    "wof:name": "DG9 7BG",
    "wof:placetype": "postalcode"
  },
  "geometry": {"coordinates":[-5.034524,54.899269],"type":"Point"}
}
