{
  "type": "Feature",
  "properties": {
    "iso:country":"GB",
    "wof:name":"DG9 7BG",
    "wof:placetype":"postalcode"
},
  "geometry": {"coordinates":[-5.03452379657265,54.89926907710059],"type":"Point"}
}