{
  "type": "Feature",
  "properties": {
    "iso:country":"GB",
    "wof:name":"DA13 0HN",
    "wof:placetype":"postalcode"
},
  "geometry": {"coordinates":[0.35652407506989,51.38593608998339],"type":"Point"}
}