{
  "type": "Feature",
  "properties": {
    "iso:country":"GB",
    "wof:name":"LS9 8AS",
    "wof:placetype":"postalcode"
},
  "geometry": {"coordinates":[-1.52352698077742,53.79261807212593],"type":"Point"}
}