{
  "type": "Feature",
  "properties": {
    "iso:country": "GB",
    "wof:name": "LS9 8AS",
    "wof:placetype": "postalcode"
  },
  "geometry": {"coordinates":[-1.523527,53.792618],"type":"Point"}
}
