{
  "type": "Feature",
  "properties": {
    "date:inception_lower":"2007-01-01",
    "date:inception_upper":"2007-01-31",
    "iso:country":"GB",
    "wof:name":"LS9 8AS",
    "wof:placetype":"postalcode"
},
  "geometry": {"coordinates":[-1.523527,53.792618],"type":"Point"}
}