{
  "type": "Feature",
  "properties": {
    "iso:country":"GB",
    "wof:name":"M46 0HR",
    "wof:placetype":"postalcode"
},
  "geometry": {"coordinates":[-2.5016109087886,53.53002914804043],"type":"Point"}
}