{
  "type": "Feature",
  "properties": {
    "date:inception_lower":"1997-06-01",
    "date:inception_upper":"1997-06-30",
    "iso:country":"GB",
    "wof:name":"MK44 3US",
    "wof:placetype":"postalcode"
},
  "geometry": {"coordinates":[-0.422286,52.125293],"type":"Point"}
}