{
  "type": "Feature",
  "properties": {
    "iso:country": "GB",
    "wof:name": "CV22 7GG",
    "wof:placetype": "postalcode"
  },
  "geometry": {"coordinates":[-1.302644,52.360002],"type":"Point"}
}
