{
  "type": "Feature",
  "properties": {
    "date:inception_lower": "1980-01-01",
    "date:inception_upper": "1980-01-01",
    "iso:country": "GB",
    "wof:name": "ST10 4BW",
    "wof:placetype": "postalcode"
  },
  "geometry": {"coordinates":[-1.895234,52.976347],"type":"Point"}
}
