{
  "type": "Feature",
  "properties": {
    "iso:country": "GB",
    "wof:name": "BS34 5TS",
    "wof:placetype": "postalcode"
  },
  "geometry": {"coordinates":[-2.598875,51.528367],"type":"Point"}
}
