{
  "type": "Feature",
  "properties": {
    "iso:country":"GB",
    "wof:name":"BH22 8US",
    "wof:placetype":"postalcode"
},
  "geometry": {"coordinates":[-1.86895817665209,50.80632166396843],"type":"Point"}
}