{
  "type": "Feature",
  "properties": {
    "date:inception_lower": "2023-09-01",
    "date:inception_upper": "2023-09-01",
    "iso:country": "GB",
    "wof:name": "PE20 1FE",
    "wof:placetype": "postalcode"
  },
  "geometry": {"coordinates":[-0.091091,52.942095],"type":"Point"}
}
