{
  "type": "Feature",
  "properties": {
    "date:inception_lower":"2015-10-01",
    "date:inception_upper":"2015-10-31",
    "iso:country":"GB",
    "wof:name":"UB4 8QX",
    "wof:placetype":"postalcode"
},
  "geometry": {"coordinates":[-0.428604,51.523307],"type":"Point"}
}