{
  "type": "Feature",
  "properties": {
    "iso:country": "GB",
    "wof:name": "UB4 8QX",
    "wof:placetype": "postalcode"
  },
  "geometry": {"coordinates":[-0.428604,51.523307],"type":"Point"}
}
