{
  "type": "Feature",
  "properties": {
    "iso:country":"GB",
    "wof:name":"UB4 8QX",
    "wof:placetype":"postalcode"
},
  "geometry": {"coordinates":[-0.42860439773271,51.52330686661134],"type":"Point"}
}