{
  "type": "Feature",
  "properties": {
    "date:inception_lower": "2022-05-01",
    "date:inception_upper": "2022-05-01",
    "iso:country": "GB",
    "wof:name": "KA9 2FA",
    "wof:placetype": "postalcode"
  },
  "geometry": {"coordinates":[-4.591548,55.517956],"type":"Point"}
}
