{
  "type": "Feature",
  "properties": {
    "date:inception_lower":"1980-01-01",
    "date:inception_upper":"1980-01-31",
    "iso:country":"GB",
    "wof:name":"SA33 4UG",
    "wof:placetype":"postalcode"
},
  "geometry": {"coordinates":[-4.544284,51.746849],"type":"Point"}
}