{
  "type": "Feature",
  "properties": {
    "iso:country":"GB",
    "wof:name":"SA33 4UG",
    "wof:placetype":"postalcode"
},
  "geometry": {"coordinates":[-4.54428381618,51.74684879782144],"type":"Point"}
}