{
  "type": "Feature",
  "properties": {
    "date:inception_lower":"2007-02-01",
    "date:inception_upper":"2007-02-28",
    "iso:country":"GB",
    "wof:name":"SG1 6GX",
    "wof:placetype":"postalcode"
},
  "geometry": {"coordinates":[-0.177288,51.933131],"type":"Point"}
}