{
  "type": "Feature",
  "properties": {
    "iso:country":"GB",
    "wof:name":"SG1 6GX",
    "wof:placetype":"postalcode"
},
  "geometry": {"coordinates":[-0.17728765003338,51.93313099830402],"type":"Point"}
}