{
  "type": "Feature",
  "properties": {
    "iso:country":"GB",
    "wof:name":"GL54 5PG",
    "wof:placetype":"postalcode"
},
  "geometry": {"coordinates":[-1.90937852608403,51.97993877107089],"type":"Point"}
}