{
  "type": "Feature",
  "properties": {
    "date:inception_lower": "1980-01-01",
    "date:inception_upper": "1980-01-01",
    "iso:country": "GB",
    "wof:name": "GL54 5PG",
    "wof:placetype": "postalcode"
  },
  "geometry": {"coordinates":[-1.908947,51.979777],"type":"Point"}
}
