{
  "type": "Feature",
  "properties": {
    "iso:country":"GB",
    "wof:name":"B13 0ET",
    "wof:placetype":"postalcode"
},
  "geometry": {"coordinates":[-1.86331607501628,52.42300382317779],"type":"Point"}
}