{
  "type": "Feature",
  "properties": {
    "iso:country": "GB",
    "wof:name": "NR24 2HF",
    "wof:placetype": "postalcode"
  },
  "geometry": {"coordinates":[1.041421,52.85634],"type":"Point"}
}
