{
  "type": "Feature",
  "properties": {
    "iso:country":"GB",
    "wof:name":"WR11 1YZ",
    "wof:placetype":"postalcode"
},
  "geometry": {"coordinates":[-1.94813692823565,52.08058546235505],"type":"Point"}
}