{
  "type": "Feature",
  "properties": {
    "iso:country": "GB",
    "wof:name": "HR3 6QA",
    "wof:placetype": "postalcode"
  },
  "geometry": {"coordinates":[-2.964151,52.133312],"type":"Point"}
}
