{
  "type": "Feature",
  "properties": {
    "iso:country":"GB",
    "wof:name":"WR9 0BG",
    "wof:placetype":"postalcode"
},
  "geometry": {"coordinates":[-2.14454213714907,52.28544443892089],"type":"Point"}
}