{
  "type": "Feature",
  "properties": {
    "iso:country":"GB",
    "wof:name":"ME13 9BU",
    "wof:placetype":"postalcode"
},
  "geometry": {"coordinates":[0.93420893945165,51.31479314990395],"type":"Point"}
}