{
  "type": "Feature",
  "properties": {
    "date:inception_lower": "2016-11-01",
    "date:inception_upper": "2016-11-01",
    "iso:country": "GB",
    "wof:name": "NE25 9GJ",
    "wof:placetype": "postalcode"
  },
  "geometry": {"coordinates":[-1.483446,55.04745],"type":"Point"}
}
