{
  "type": "Feature",
  "properties": {
    "iso:country":"GB",
    "wof:name":"BH3 7DS",
    "wof:placetype":"postalcode"
},
  "geometry": {"coordinates":[-1.89505781756586,50.735989937329],"type":"Point"}
}