{
  "type": "Feature",
  "properties": {
    "iso:country": "GB",
    "wof:name": "NR10 3JW",
    "wof:placetype": "postalcode"
  },
  "geometry": {"coordinates":[1.277385,52.686896],"type":"Point"}
}
