{
  "type": "Feature",
  "properties": {
    "date:inception_lower":"1980-01-01",
    "date:inception_upper":"1980-01-31",
    "iso:country":"GB",
    "wof:name":"NR10 3JW",
    "wof:placetype":"postalcode"
},
  "geometry": {"coordinates":[1.277385,52.686896],"type":"Point"}
}