{
  "type": "Feature",
  "properties": {
    "date:inception_lower":"1980-01-01",
    "date:inception_upper":"1980-01-31",
    "iso:country":"GB",
    "wof:name":"CF41 7EN",
    "wof:placetype":"postalcode"
},
  "geometry": {"coordinates":[-3.490428,51.648869],"type":"Point"}
}