{
  "type": "Feature",
  "properties": {
    "iso:country":"GB",
    "wof:name":"CF41 7EN",
    "wof:placetype":"postalcode"
},
  "geometry": {"coordinates":[-3.49042853790423,51.64886922732973],"type":"Point"}
}