{
  "type": "Feature",
  "properties": {
    "date:inception_lower": "2015-03-01",
    "date:inception_upper": "2015-03-01",
    "iso:country": "GB",
    "wof:name": "ST55 9GY",
    "wof:placetype": "postalcode"
  },
  "geometry": {"coordinates":[-2.254153,53.016573],"type":"Point"}
}
