{
  "type": "Feature",
  "properties": {
    "date:inception_lower": "1980-01-01",
    "date:inception_upper": "1980-01-01",
    "iso:country": "GB",
    "wof:name": "MK16 8EU",
    "wof:placetype": "postalcode"
  },
  "geometry": {"coordinates":[-0.72784,52.087383],"type":"Point"}
}
