{
  "type": "Feature",
  "properties": {
    "iso:country": "GB",
    "wof:name": "PO6 1PQ",
    "wof:placetype": "postalcode"
  },
  "geometry": {"coordinates":[-1.038571,50.846617],"type":"Point"}
}
