{
  "type": "Feature",
  "properties": {
    "iso:country":"GB",
    "wof:name":"NG34 8FS",
    "wof:placetype":"postalcode"
},
  "geometry": {"coordinates":[-0.44742376770296,52.98163115859429],"type":"Point"}
}