{
  "type": "Feature",
  "properties": {
    "iso:country":"GB",
    "wof:name":"LE10 2NL",
    "wof:placetype":"postalcode"
},
  "geometry": {"coordinates":[-1.37605711415649,52.52729626443979],"type":"Point"}
}