{
  "type": "Feature",
  "properties": {
    "iso:country":"GB",
    "wof:name":"NG17 1BX",
    "wof:placetype":"postalcode"
},
  "geometry": {"coordinates":[-1.29932628875004,53.1102036180659],"type":"Point"}
}