{
  "type": "Feature",
  "properties": {
    "iso:country": "GB",
    "wof:name": "M26 1RQ",
    "wof:placetype": "postalcode"
  },
  "geometry": {"coordinates":[-2.361767,53.539208],"type":"Point"}
}
