{
  "type": "Feature",
  "properties": {
    "date:inception_lower":"2013-11-01",
    "date:inception_upper":"2013-11-30",
    "iso:country":"GB",
    "wof:name":"M26 1RQ",
    "wof:placetype":"postalcode"
},
  "geometry": {"coordinates":[-2.361767,53.539208],"type":"Point"}
}