{
  "type": "Feature",
  "properties": {
    "iso:country":"GB",
    "wof:name":"DN1 1HL",
    "wof:placetype":"postalcode"
},
  "geometry": {"coordinates":[-1.13125097312006,53.52346103128009],"type":"Point"}
}