{
  "type": "Feature",
  "properties": {
    "iso:country": "GB",
    "wof:name": "WV14 9HS",
    "wof:placetype": "postalcode"
  },
  "geometry": {"coordinates":[-2.100514,52.541132],"type":"Point"}
}
