{
  "type": "Feature",
  "properties": {
    "iso:country":"GB",
    "wof:name":"WV14 9HS",
    "wof:placetype":"postalcode"
},
  "geometry": {"coordinates":[-2.10051431632183,52.54113166000041],"type":"Point"}
}