{
  "type": "Feature",
  "properties": {
    "iso:country":"GB",
    "wof:name":"S80 1LA",
    "wof:placetype":"postalcode"
},
  "geometry": {"coordinates":[-1.12922977014017,53.30390301284108],"type":"Point"}
}