{
  "type": "Feature",
  "properties": {
    "iso:country": "GB",
    "wof:name": "S80 1LA",
    "wof:placetype": "postalcode"
  },
  "geometry": {"coordinates":[-1.12923,53.303903],"type":"Point"}
}
