{
  "type": "Feature",
  "properties": {
    "iso:country":"GB",
    "wof:name":"TS22 5FG",
    "wof:placetype":"postalcode"
},
  "geometry": {"coordinates":[-1.31441757576035,54.6311221305431],"type":"Point"}
}