{
  "type": "Feature",
  "properties": {
    "date:inception_lower":"2008-08-01",
    "date:inception_upper":"2008-08-31",
    "iso:country":"GB",
    "wof:name":"TS22 5FG",
    "wof:placetype":"postalcode"
},
  "geometry": {"coordinates":[-1.314418,54.631122],"type":"Point"}
}