{
  "type": "Feature",
  "properties": {
    "date:inception_lower": "1980-01-01",
    "date:inception_upper": "1980-01-01",
    "iso:country": "GB",
    "wof:name": "HA6 2BX",
    "wof:placetype": "postalcode"
  },
  "geometry": {"coordinates":[-0.429922,51.613834],"type":"Point"}
}
