{
  "type": "Feature",
  "properties": {
    "iso:country":"GB",
    "wof:name":"HA6 2BX",
    "wof:placetype":"postalcode"
},
  "geometry": {"coordinates":[-0.43053368555721,51.61388335551214],"type":"Point"}
}