{
  "type": "Feature",
  "properties": {
    "iso:country": "GB",
    "wof:name": "NE1 5BX",
    "wof:placetype": "postalcode"
  },
  "geometry": {"coordinates":[-1.619672,54.969756],"type":"Point"}
}
