{
  "type": "Feature",
  "properties": {
    "iso:country":"GB",
    "wof:name":"NE1 5BX",
    "wof:placetype":"postalcode"
},
  "geometry": {"coordinates":[-1.61967252597791,54.96975568795198],"type":"Point"}
}