{
  "type": "Feature",
  "properties": {
    "iso:country":"GB",
    "wof:name":"PL5 3PA",
    "wof:placetype":"postalcode"
},
  "geometry": {"coordinates":[-4.15491138994631,50.41166397787442],"type":"Point"}
}