{
  "type": "Feature",
  "properties": {
    "iso:country":"GB",
    "wof:name":"M19 2LQ",
    "wof:placetype":"postalcode"
},
  "geometry": {"coordinates":[-2.20326361231546,53.43680907270564],"type":"Point"}
}