{
  "type": "Feature",
  "properties": {
    "iso:country": "GB",
    "wof:name": "M19 2LQ",
    "wof:placetype": "postalcode"
  },
  "geometry": {"coordinates":[-2.203264,53.436809],"type":"Point"}
}
