{
  "type": "Feature",
  "properties": {
    "iso:country":"GB",
    "wof:name":"DL15 9GH",
    "wof:placetype":"postalcode"
},
  "geometry": {"coordinates":[-1.7543285187627,54.70944181162932],"type":"Point"}
}