{
  "type": "Feature",
  "properties": {
    "iso:country": "GB",
    "wof:name": "DL15 9GH",
    "wof:placetype": "postalcode"
  },
  "geometry": {"coordinates":[-1.754328,54.709442],"type":"Point"}
}
