{
  "type": "Feature",
  "properties": {
    "iso:country":"GB",
    "wof:name":"SW4 9AJ",
    "wof:placetype":"postalcode"
},
  "geometry": {"coordinates":[-0.15194754928775,51.45361108543209],"type":"Point"}
}