{
  "type": "Feature",
  "properties": {
    "iso:country":"GB",
    "wof:name":"IP29 4NJ",
    "wof:placetype":"postalcode"
},
  "geometry": {"coordinates":[0.62310219604253,52.14543372812308],"type":"Point"}
}