{
  "type": "Feature",
  "properties": {
    "date:inception_lower": "1980-01-01",
    "date:inception_upper": "1980-01-01",
    "iso:country": "GB",
    "wof:name": "IP29 4NJ",
    "wof:placetype": "postalcode"
  },
  "geometry": {"coordinates":[0.623178,52.14524],"type":"Point"}
}
