{
  "type": "Feature",
  "properties": {
    "iso:country": "GB",
    "wof:name": "IP29 4NJ",
    "wof:placetype": "postalcode"
  },
  "geometry": {"coordinates":[0.623102,52.145434],"type":"Point"}
}
