{
  "type": "Feature",
  "properties": {
    "date:inception_lower": "2015-04-01",
    "date:inception_upper": "2015-04-01",
    "iso:country": "GB",
    "wof:name": "LE17 4FY",
    "wof:placetype": "postalcode"
  },
  "geometry": {"coordinates":[-1.203735,52.470065],"type":"Point"}
}
