{
  "type": "Feature",
  "properties": {
    "iso:country":"GB",
    "wof:name":"LE17 4FY",
    "wof:placetype":"postalcode"
},
  "geometry": {"coordinates":[-1.20345658613903,52.46982076386448],"type":"Point"}
}