{
  "type": "Feature",
  "properties": {
    "iso:country":"GB",
    "wof:name":"HR2 9TL",
    "wof:placetype":"postalcode"
},
  "geometry": {"coordinates":[-2.81620776684686,52.03319260951836],"type":"Point"}
}