{
  "type": "Feature",
  "properties": {
    "iso:country": "GB",
    "wof:name": "HR2 9TL",
    "wof:placetype": "postalcode"
  },
  "geometry": {"coordinates":[-2.816208,52.033193],"type":"Point"}
}
