{
  "type": "Feature",
  "properties": {
    "iso:country":"GB",
    "wof:name":"WA7 2YE",
    "wof:placetype":"postalcode"
},
  "geometry": {"coordinates":[-2.70721468200279,53.32133211090074],"type":"Point"}
}