{
  "type": "Feature",
  "properties": {
    "iso:country": "GB",
    "wof:name": "IP16 4PP",
    "wof:placetype": "postalcode"
  },
  "geometry": {"coordinates":[1.579045,52.199186],"type":"Point"}
}
