{
  "type": "Feature",
  "properties": {
    "iso:country":"GB",
    "wof:name":"IP16 4PP",
    "wof:placetype":"postalcode"
},
  "geometry": {"coordinates":[1.57904478326111,52.19918646318882],"type":"Point"}
}