{
  "type": "Feature",
  "properties": {
    "iso:country":"GB",
    "wof:name":"LA10 5TE",
    "wof:placetype":"postalcode"
},
  "geometry": {"coordinates":[-2.43627648027053,54.27921808694443],"type":"Point"}
}