{
  "type": "Feature",
  "properties": {
    "date:inception_lower": "1980-01-01",
    "date:inception_upper": "1980-01-01",
    "iso:country": "GB",
    "wof:name": "LA10 5TE",
    "wof:placetype": "postalcode"
  },
  "geometry": {"coordinates":[-2.43203,54.278112],"type":"Point"}
}
