{
  "type": "Feature",
  "properties": {
    "iso:country": "GB",
    "wof:name": "NE1 6PZ",
    "wof:placetype": "postalcode"
  },
  "geometry": {"coordinates":[-1.60039,54.973585],"type":"Point"}
}
