{
  "type": "Feature",
  "properties": {
    "iso:country":"GB",
    "wof:name":"NE1 6PZ",
    "wof:placetype":"postalcode"
},
  "geometry": {"coordinates":[-1.60038995872278,54.9735849596443],"type":"Point"}
}