{
  "type": "Feature",
  "properties": {
    "iso:country":"GB",
    "wof:name":"FY1 5DD",
    "wof:placetype":"postalcode"
},
  "geometry": {"coordinates":[-3.05251169818776,53.80742254568575],"type":"Point"}
}