{
  "type": "Feature",
  "properties": {
    "date:inception_lower": "1996-06-01",
    "date:inception_upper": "1996-06-01",
    "iso:country": "GB",
    "wof:name": "FY1 5DD",
    "wof:placetype": "postalcode"
  },
  "geometry": {"coordinates":[-3.052512,53.807423],"type":"Point"}
}
