{
  "type": "Feature",
  "properties": {
    "iso:country": "GB",
    "wof:name": "OX11 7AD",
    "wof:placetype": "postalcode"
  },
  "geometry": {"coordinates":[-1.252664,51.609595],"type":"Point"}
}
