{
  "type": "Feature",
  "properties": {
    "date:inception_lower": "1980-01-01",
    "date:inception_upper": "1980-01-01",
    "iso:country": "GB",
    "wof:name": "LS15 4EW",
    "wof:placetype": "postalcode"
  },
  "geometry": {"coordinates":[-1.392957,53.827729],"type":"Point"}
}
