{
  "type": "Feature",
  "properties": {
    "iso:country":"GB",
    "wof:name":"LS15 4EW",
    "wof:placetype":"postalcode"
},
  "geometry": {"coordinates":[-1.39295752218708,53.8277291971449],"type":"Point"}
}