{
  "type": "Feature",
  "properties": {
    "iso:country": "GB",
    "wof:name": "RG42 2HB",
    "wof:placetype": "postalcode"
  },
  "geometry": {"coordinates":[-0.756891,51.42595],"type":"Point"}
}
