{
  "type": "Feature",
  "properties": {
    "iso:country":"GB",
    "wof:name":"NG10 4LW",
    "wof:placetype":"postalcode"
},
  "geometry": {"coordinates":[-1.27889833287718,52.9030659385947],"type":"Point"}
}