{
  "type": "Feature",
  "properties": {
    "iso:country": "GB",
    "wof:name": "NG10 4LW",
    "wof:placetype": "postalcode"
  },
  "geometry": {"coordinates":[-1.278898,52.903066],"type":"Point"}
}
