{
  "type": "Feature",
  "properties": {
    "iso:country":"GB",
    "wof:name":"CH7 2JH",
    "wof:placetype":"postalcode"
},
  "geometry": {"coordinates":[-3.09492974878526,53.16812048525851],"type":"Point"}
}