{
  "type": "Feature",
  "properties": {
    "date:inception_lower": "2001-06-01",
    "date:inception_upper": "2001-06-01",
    "iso:country": "GB",
    "wof:name": "CH7 2JH",
    "wof:placetype": "postalcode"
  },
  "geometry": {"coordinates":[-3.09493,53.16812],"type":"Point"}
}
