{
  "type": "Feature",
  "properties": {
    "iso:country":"GB",
    "wof:name":"S6 2NW",
    "wof:placetype":"postalcode"
},
  "geometry": {"coordinates":[-1.50012429190007,53.40160113519109],"type":"Point"}
}