{
  "type": "Feature",
  "properties": {
    "iso:country":"GB",
    "wof:name":"BL4 9QZ",
    "wof:placetype":"postalcode"
},
  "geometry": {"coordinates":[-2.40244448602501,53.54363517574433],"type":"Point"}
}