{
  "type": "Feature",
  "properties": {
    "iso:country":"GB",
    "wof:name":"BS24 9NX",
    "wof:placetype":"postalcode"
},
  "geometry": {"coordinates":[-2.95687860831358,51.32041318232162],"type":"Point"}
}