{
  "type": "Feature",
  "properties": {
    "iso:country":"GB",
    "wof:name":"PL25 5QD",
    "wof:placetype":"postalcode"
},
  "geometry": {"coordinates":[-4.79303778450141,50.338977141528],"type":"Point"}
}