{
  "type": "Feature",
  "properties": {
    "iso:country":"GB",
    "wof:name":"LA13 0JG",
    "wof:placetype":"postalcode"
},
  "geometry": {"coordinates":[-3.19066211482823,54.11550775422591],"type":"Point"}
}