{
  "type": "Feature",
  "properties": {
    "date:inception_lower": "1987-04-01",
    "date:inception_upper": "1987-04-01",
    "iso:country": "GB",
    "wof:name": "LL42 1PS",
    "wof:placetype": "postalcode"
  },
  "geometry": {"coordinates":[-4.057959,52.725733],"type":"Point"}
}
