{
  "type": "Feature",
  "properties": {
    "iso:country":"GB",
    "wof:name":"LL42 1PS",
    "wof:placetype":"postalcode"
},
  "geometry": {"coordinates":[-4.05795874523169,52.72573343567957],"type":"Point"}
}