{
  "type": "Feature",
  "properties": {
    "iso:country": "GB",
    "wof:name": "LL42 1PS",
    "wof:placetype": "postalcode"
  },
  "geometry": {"coordinates":[-4.057959,52.725733],"type":"Point"}
}
