{
  "type": "Feature",
  "properties": {
    "iso:country":"GB",
    "wof:name":"WN6 0JE",
    "wof:placetype":"postalcode"
},
  "geometry": {"coordinates":[-2.66784031634417,53.59113766164669],"type":"Point"}
}