{
  "type": "Feature",
  "properties": {
    "iso:country":"GB",
    "wof:name":"AL1 3QA",
    "wof:placetype":"postalcode"
},
  "geometry": {"coordinates":[-0.32774293894531,51.75787477152119],"type":"Point"}
}