{
  "type": "Feature",
  "properties": {
    "iso:country":"GB",
    "wof:name":"DY2 0BA",
    "wof:placetype":"postalcode"
},
  "geometry": {"coordinates":[-2.09114573154233,52.48152715235985],"type":"Point"}
}