{
  "type": "Feature",
  "properties": {
    "iso:country": "GB",
    "wof:name": "TF6 5BX",
    "wof:placetype": "postalcode"
  },
  "geometry": {"coordinates":[-2.519461,52.684051],"type":"Point"}
}
