{
  "type": "Feature",
  "properties": {
    "iso:country":"GB",
    "wof:name":"TF6 5BX",
    "wof:placetype":"postalcode"
},
  "geometry": {"coordinates":[-2.51946144605678,52.68405114650535],"type":"Point"}
}