{
  "type": "Feature",
  "properties": {
    "iso:country":"GB",
    "wof:name":"AL10 8BS",
    "wof:placetype":"postalcode"
},
  "geometry": {"coordinates":[-0.21874432090624,51.76028388363223],"type":"Point"}
}