{
  "type": "Feature",
  "properties": {
    "date:inception_lower":"1980-01-01",
    "date:inception_upper":"1980-01-31",
    "iso:country":"GB",
    "wof:name":"AL10 8BS",
    "wof:placetype":"postalcode"
},
  "geometry": {"coordinates":[-0.218744,51.760284],"type":"Point"}
}