{
  "type": "Feature",
  "properties": {
    "iso:country": "GB",
    "wof:name": "S80 4SR",
    "wof:placetype": "postalcode"
  },
  "geometry": {"coordinates":[-1.205249,53.287103],"type":"Point"}
}
