{
  "type": "Feature",
  "properties": {
    "date:inception_lower": "1980-01-01",
    "date:inception_upper": "1980-01-01",
    "iso:country": "GB",
    "wof:name": "S80 4SR",
    "wof:placetype": "postalcode"
  },
  "geometry": {"coordinates":[-1.205249,53.287103],"type":"Point"}
}
