{
  "type": "Feature",
  "properties": {
    "iso:country":"GB",
    "wof:name":"DE5 4BP",
    "wof:placetype":"postalcode"
},
  "geometry": {"coordinates":[-1.4081714218643,53.05018922188285],"type":"Point"}
}