{
  "type": "Feature",
  "properties": {
    "date:inception_lower": "2011-12-01",
    "date:inception_upper": "2011-12-01",
    "iso:country": "GB",
    "wof:name": "DE5 4BP",
    "wof:placetype": "postalcode"
  },
  "geometry": {"coordinates":[-1.408171,53.050189],"type":"Point"}
}
