{
  "type": "Feature",
  "properties": {
    "iso:country":"GB",
    "wof:name":"WA2 0SP",
    "wof:placetype":"postalcode"
},
  "geometry": {"coordinates":[-2.56517273181999,53.41249849345481],"type":"Point"}
}