{
  "type": "Feature",
  "properties": {
    "date:inception_lower":"1991-01-01",
    "date:inception_upper":"1991-01-31",
    "iso:country":"GB",
    "wof:name":"RG10 9YA",
    "wof:placetype":"postalcode"
},
  "geometry": {"coordinates":[-0.867487,51.477677],"type":"Point"}
}