{
  "type": "Feature",
  "properties": {
    "iso:country":"GB",
    "wof:name":"EH16 4JJ",
    "wof:placetype":"postalcode"
},
  "geometry": {"coordinates":[-3.12352550809409,55.92745286595756],"type":"Point"}
}