{
  "type": "Feature",
  "properties": {
    "iso:country": "GB",
    "wof:name": "WF8 4GG",
    "wof:placetype": "postalcode"
  },
  "geometry": {"coordinates":[-1.312925,53.698452],"type":"Point"}
}
