{
  "type": "Feature",
  "properties": {
    "iso:country":"GB",
    "wof:name":"NW5 3ER",
    "wof:placetype":"postalcode"
},
  "geometry": {"coordinates":[-0.14776951008176,51.54965714183823],"type":"Point"}
}