{
  "type": "Feature",
  "properties": {
    "iso:country": "GB",
    "wof:name": "EC1Y 0TP",
    "wof:placetype": "postalcode"
  },
  "geometry": {"coordinates":[-0.09587,51.522802],"type":"Point"}
}
