{
  "type": "Feature",
  "properties": {
    "iso:country":"GB",
    "wof:name":"BD16 3EU",
    "wof:placetype":"postalcode"
},
  "geometry": {"coordinates":[-1.81045195153875,53.85795648532797],"type":"Point"}
}