{
  "type": "Feature",
  "properties": {
    "iso:country":"GB",
    "wof:name":"SA67 7DL",
    "wof:placetype":"postalcode"
},
  "geometry": {"coordinates":[-4.73941871933596,51.80058398630024],"type":"Point"}
}