{
  "type": "Feature",
  "properties": {
    "iso:country": "GB",
    "wof:name": "PA5 8WR",
    "wof:placetype": "postalcode"
  },
  "geometry": {"coordinates":[-4.523394,55.845569],"type":"Point"}
}
