{
  "type": "Feature",
  "properties": {
    "iso:country":"GB",
    "wof:name":"M40 5QW",
    "wof:placetype":"postalcode"
},
  "geometry": {"coordinates":[-2.17903236541639,53.5234695738531],"type":"Point"}
}