{
  "type": "Feature",
  "properties": {
    "iso:country":"GB",
    "wof:name":"NW10 5JU",
    "wof:placetype":"postalcode"
},
  "geometry": {"coordinates":[-0.22092302202303,51.52937835525968],"type":"Point"}
}