{
  "type": "Feature",
  "properties": {
    "iso:country": "GB",
    "wof:name": "DY12 1NZ",
    "wof:placetype": "postalcode"
  },
  "geometry": {"coordinates":[-2.312501,52.407211],"type":"Point"}
}
