{
  "type": "Feature",
  "properties": {
    "iso:country": "GB",
    "wof:name": "CH6 5RW",
    "wof:placetype": "postalcode"
  },
  "geometry": {"coordinates":[-3.147467,53.242076],"type":"Point"}
}
