{
  "type": "Feature",
  "properties": {
    "date:inception_lower":"1993-08-01",
    "date:inception_upper":"1993-08-31",
    "iso:country":"GB",
    "wof:name":"CH6 5RW",
    "wof:placetype":"postalcode"
},
  "geometry": {"coordinates":[-3.147467,53.242076],"type":"Point"}
}