{
  "type": "Feature",
  "properties": {
    "iso:country":"GB",
    "wof:name":"KY14 7HF",
    "wof:placetype":"postalcode"
},
  "geometry": {"coordinates":[-3.21366036070763,56.28135468847379],"type":"Point"}
}