{
  "type": "Feature",
  "properties": {
    "iso:country":"GB",
    "wof:name":"HA1 1GN",
    "wof:placetype":"postalcode"
},
  "geometry": {"coordinates":[-0.34085406275207,51.58020644081239],"type":"Point"}
}