{
  "type": "Feature",
  "properties": {
    "date:inception_lower":"1980-01-01",
    "date:inception_upper":"1980-01-31",
    "iso:country":"GB",
    "wof:name":"LA2 0ND",
    "wof:placetype":"postalcode"
},
  "geometry": {"coordinates":[-2.792863,53.993984],"type":"Point"}
}