{
  "type": "Feature",
  "properties": {
    "iso:country":"GB",
    "wof:name":"W1H 4QD",
    "wof:placetype":"postalcode"
},
  "geometry": {"coordinates":[-0.16372204229551,51.51955838385773],"type":"Point"}
}