{
  "type": "Feature",
  "properties": {
    "date:inception_lower": "1980-01-01",
    "date:inception_upper": "1980-01-01",
    "iso:country": "GB",
    "wof:name": "HU10 6BT",
    "wof:placetype": "postalcode"
  },
  "geometry": {"coordinates":[-0.447794,53.757758],"type":"Point"}
}
