{
  "type": "Feature",
  "properties": {
    "iso:country": "GB",
    "wof:name": "TF1 5GP",
    "wof:placetype": "postalcode"
  },
  "geometry": {"coordinates":[-2.470596,52.69896],"type":"Point"}
}
