{
  "type": "Feature",
  "properties": {
    "iso:country":"GB",
    "wof:name":"L40 0RR",
    "wof:placetype":"postalcode"
},
  "geometry": {"coordinates":[-2.86627704810887,53.60708718832063],"type":"Point"}
}