{
  "type": "Feature",
  "properties": {
    "iso:country":"GB",
    "wof:name":"E14 7AJ",
    "wof:placetype":"postalcode"
},
  "geometry": {"coordinates":[-0.02772391276086,51.5162442934343],"type":"Point"}
}