{
  "type": "Feature",
  "properties": {
    "date:inception_lower": "1980-01-01",
    "date:inception_upper": "1980-01-01",
    "iso:country": "GB",
    "wof:name": "HP16 0LJ",
    "wof:placetype": "postalcode"
  },
  "geometry": {"coordinates":[-0.737544,51.694312],"type":"Point"}
}
