{
  "type": "Feature",
  "properties": {
    "iso:country":"GB",
    "wof:name":"HP16 0LJ",
    "wof:placetype":"postalcode"
},
  "geometry": {"coordinates":[-0.73754433076462,51.69431226919701],"type":"Point"}
}