{
  "type": "Feature",
  "properties": {
    "iso:country": "GB",
    "wof:name": "OL11 2QH",
    "wof:placetype": "postalcode"
  },
  "geometry": {"coordinates":[-2.177945,53.587837],"type":"Point"}
}
