{
  "type": "Feature",
  "properties": {
    "date:inception_lower": "1980-01-01",
    "date:inception_upper": "1980-01-01",
    "iso:country": "GB",
    "wof:name": "SY4 3HX",
    "wof:placetype": "postalcode"
  },
  "geometry": {"coordinates":[-2.781648,52.746844],"type":"Point"}
}
