{
  "type": "Feature",
  "properties": {
    "date:inception_lower":"1980-01-01",
    "date:inception_upper":"1980-01-31",
    "iso:country":"GB",
    "wof:name":"LA14 2QQ",
    "wof:placetype":"postalcode"
},
  "geometry": {"coordinates":[-3.236782,54.106072],"type":"Point"}
}