{
  "type": "Feature",
  "properties": {
    "iso:country":"GB",
    "wof:name":"LA14 2QQ",
    "wof:placetype":"postalcode"
},
  "geometry": {"coordinates":[-3.2367819223381,54.10607238068002],"type":"Point"}
}