{
  "type": "Feature",
  "properties": {
    "iso:country":"GB",
    "wof:name":"DY4 8BJ",
    "wof:placetype":"postalcode"
},
  "geometry": {"coordinates":[-2.07100435250734,52.52824364121145],"type":"Point"}
}