{
  "type": "Feature",
  "properties": {
    "date:inception_lower": "2008-05-01",
    "date:inception_upper": "2008-05-01",
    "iso:country": "GB",
    "wof:name": "DY4 8BJ",
    "wof:placetype": "postalcode"
  },
  "geometry": {"coordinates":[-2.071004,52.528244],"type":"Point"}
}
