{
  "type": "Feature",
  "properties": {
    "date:inception_lower": "1980-01-01",
    "date:inception_upper": "1980-01-01",
    "iso:country": "GB",
    "wof:name": "G83 9HT",
    "wof:placetype": "postalcode"
  },
  "geometry": {"coordinates":[-4.573256,55.980092],"type":"Point"}
}
