{
  "type": "Feature",
  "properties": {
    "date:inception_lower": "1990-07-01",
    "date:inception_upper": "1990-07-01",
    "iso:country": "GB",
    "wof:name": "PL12 4UN",
    "wof:placetype": "postalcode"
  },
  "geometry": {"coordinates":[-4.237476,50.406831],"type":"Point"}
}
