{
  "type": "Feature",
  "properties": {
    "date:inception_lower":"1980-01-01",
    "date:inception_upper":"1980-01-31",
    "iso:country":"GB",
    "wof:name":"TN36 4AY",
    "wof:placetype":"postalcode"
},
  "geometry": {"coordinates":[0.653857,50.92156],"type":"Point"}
}