{
  "type": "Feature",
  "properties": {
    "iso:country": "GB",
    "wof:name": "NP4 0QD",
    "wof:placetype": "postalcode"
  },
  "geometry": {"coordinates":[-3.011998,51.696201],"type":"Point"}
}
