{
  "type": "Feature",
  "properties": {
    "iso:country":"GB",
    "wof:name":"NP4 0QD",
    "wof:placetype":"postalcode"
},
  "geometry": {"coordinates":[-3.01199762382565,51.69620121944808],"type":"Point"}
}