{
  "type": "Feature",
  "properties": {
    "date:inception_lower": "2023-06-01",
    "date:inception_upper": "2023-06-01",
    "iso:country": "GB",
    "wof:name": "EH33 2FD",
    "wof:placetype": "postalcode"
  },
  "geometry": {"coordinates":[-2.946682,55.934092],"type":"Point"}
}
