{
  "type": "Feature",
  "properties": {
    "date:inception_lower": "1980-01-01",
    "date:inception_upper": "1980-01-01",
    "iso:country": "GB",
    "wof:name": "S43 4HT",
    "wof:placetype": "postalcode"
  },
  "geometry": {"coordinates":[-1.292655,53.288094],"type":"Point"}
}
