{
  "type": "Feature",
  "properties": {
    "iso:country": "GB",
    "wof:name": "S43 4HT",
    "wof:placetype": "postalcode"
  },
  "geometry": {"coordinates":[-1.292655,53.288094],"type":"Point"}
}
