{
  "type": "Feature",
  "properties": {
    "iso:country":"GB",
    "wof:name":"S43 4HT",
    "wof:placetype":"postalcode"
},
  "geometry": {"coordinates":[-1.29265519349633,53.28809352128999],"type":"Point"}
}