{
  "type": "Feature",
  "properties": {
    "iso:country":"GB",
    "wof:name":"RM8 2TS",
    "wof:placetype":"postalcode"
},
  "geometry": {"coordinates":[0.11900693026337,51.55511476933297],"type":"Point"}
}