{
  "type": "Feature",
  "properties": {
    "date:inception_lower": "2023-05-01",
    "date:inception_upper": "2023-05-01",
    "iso:country": "GB",
    "wof:name": "PE28 4DG",
    "wof:placetype": "postalcode"
  },
  "geometry": {"coordinates":[-0.231213,52.374374],"type":"Point"}
}
