{
  "type": "Feature",
  "properties": {
    "date:inception_lower":"1980-01-01",
    "date:inception_upper":"1980-01-31",
    "iso:country":"GB",
    "wof:name":"BR5 3AX",
    "wof:placetype":"postalcode"
},
  "geometry": {"coordinates":[0.109003,51.399512],"type":"Point"}
}