{
  "type": "Feature",
  "properties": {
    "iso:country":"GB",
    "wof:name":"RG26 5XH",
    "wof:placetype":"postalcode"
},
  "geometry": {"coordinates":[-1.04304163813987,51.32156784507583],"type":"Point"}
}