{
  "type": "Feature",
  "properties": {
    "iso:country": "GB",
    "wof:name": "RG26 5XH",
    "wof:placetype": "postalcode"
  },
  "geometry": {"coordinates":[-1.043042,51.321568],"type":"Point"}
}
