{
  "type": "Feature",
  "properties": {
    "date:inception_lower": "1998-06-01",
    "date:inception_upper": "1998-06-01",
    "iso:country": "GB",
    "wof:name": "LS6 4RB",
    "wof:placetype": "postalcode"
  },
  "geometry": {"coordinates":[-1.569215,53.828518],"type":"Point"}
}
