{
  "type": "Feature",
  "properties": {
    "iso:country":"GB",
    "wof:name":"LS6 4RB",
    "wof:placetype":"postalcode"
},
  "geometry": {"coordinates":[-1.56921534283215,53.82851814246187],"type":"Point"}
}