{
  "type": "Feature",
  "properties": {
    "iso:country":"GB",
    "wof:name":"M16 0BQ",
    "wof:placetype":"postalcode"
},
  "geometry": {"coordinates":[-2.27020999240035,53.44970961175662],"type":"Point"}
}