{
  "type": "Feature",
  "properties": {
    "iso:country": "GB",
    "wof:name": "M16 0BQ",
    "wof:placetype": "postalcode"
  },
  "geometry": {"coordinates":[-2.27021,53.44971],"type":"Point"}
}
