{
  "type": "Feature",
  "properties": {
    "iso:country":"GB",
    "wof:name":"BR6 0HT",
    "wof:placetype":"postalcode"
},
  "geometry": {"coordinates":[0.10438803283316,51.38227425344768],"type":"Point"}
}