{
  "type": "Feature",
  "properties": {
    "date:inception_lower":"2008-12-01",
    "date:inception_upper":"2008-12-31",
    "iso:country":"GB",
    "wof:name":"S3 7RA",
    "wof:placetype":"postalcode"
},
  "geometry": {"coordinates":[-1.483611,53.381594],"type":"Point"}
}