{
  "type": "Feature",
  "properties": {
    "iso:country":"GB",
    "wof:name":"SA6 6DS",
    "wof:placetype":"postalcode"
},
  "geometry": {"coordinates":[-3.93130885595873,51.66949274612995],"type":"Point"}
}