{
  "type": "Feature",
  "properties": {
    "iso:country": "GB",
    "wof:name": "CR9 2AA",
    "wof:placetype": "postalcode"
  },
  "geometry": {"coordinates":[-0.09814,51.375081],"type":"Point"}
}
