{
  "type": "Feature",
  "properties": {
    "iso:country":"GB",
    "wof:name":"CR9 2AA",
    "wof:placetype":"postalcode"
},
  "geometry": {"coordinates":[-0.09814028003178,51.37508062026302],"type":"Point"}
}