{
  "type": "Feature",
  "properties": {
    "iso:country": "GB",
    "wof:name": "BN16 3JD",
    "wof:placetype": "postalcode"
  },
  "geometry": {"coordinates":[-0.495807,50.815343],"type":"Point"}
}
