{
  "type": "Feature",
  "properties": {
    "iso:country":"GB",
    "wof:name":"LN13 0AL",
    "wof:placetype":"postalcode"
},
  "geometry": {"coordinates":[0.14213618283999,53.25717840076909],"type":"Point"}
}