{
  "type": "Feature",
  "properties": {
    "iso:country": "GB",
    "wof:name": "LN13 0AL",
    "wof:placetype": "postalcode"
  },
  "geometry": {"coordinates":[0.142136,53.257178],"type":"Point"}
}
