{
  "type": "Feature",
  "properties": {
    "iso:country": "GB",
    "wof:name": "OL16 2AL",
    "wof:placetype": "postalcode"
  },
  "geometry": {"coordinates":[-2.143022,53.624823],"type":"Point"}
}
