{
  "type": "Feature",
  "properties": {
    "iso:country":"GB",
    "wof:name":"OL16 2AL",
    "wof:placetype":"postalcode"
},
  "geometry": {"coordinates":[-2.1430534296848,53.62474436152004],"type":"Point"}
}