{
  "type": "Feature",
  "properties": {
    "date:inception_lower":"2012-10-01",
    "date:inception_upper":"2012-10-31",
    "iso:country":"GB",
    "wof:name":"OL16 2AL",
    "wof:placetype":"postalcode"
},
  "geometry": {"coordinates":[-2.143022,53.624823],"type":"Point"}
}