{
  "type": "Feature",
  "properties": {
    "iso:country": "GB",
    "wof:name": "DG1 4BB",
    "wof:placetype": "postalcode"
  },
  "geometry": {"coordinates":[-3.581961,55.059672],"type":"Point"}
}
