{
  "type": "Feature",
  "properties": {
    "iso:country":"GB",
    "wof:name":"HA2 7NW",
    "wof:placetype":"postalcode"
},
  "geometry": {"coordinates":[-0.36556330061521,51.5830170008777],"type":"Point"}
}