{
  "type": "Feature",
  "properties": {
    "date:inception_lower":"1980-01-01",
    "date:inception_upper":"1980-01-31",
    "iso:country":"GB",
    "wof:name":"HA2 7NW",
    "wof:placetype":"postalcode"
},
  "geometry": {"coordinates":[-0.365563,51.583017],"type":"Point"}
}