{
  "type": "Feature",
  "properties": {
    "date:inception_lower": "1985-04-01",
    "date:inception_upper": "1985-04-01",
    "iso:country": "GB",
    "wof:name": "GU17 9JF",
    "wof:placetype": "postalcode"
  },
  "geometry": {"coordinates":[-0.787422,51.325522],"type":"Point"}
}
