{
  "type": "Feature",
  "properties": {
    "iso:country": "GB",
    "wof:name": "SN10 3HW",
    "wof:placetype": "postalcode"
  },
  "geometry": {"coordinates":[-1.972461,51.337314],"type":"Point"}
}
