{
  "type": "Feature",
  "properties": {
    "date:inception_lower": "1980-01-01",
    "date:inception_upper": "1980-01-01",
    "iso:country": "GB",
    "wof:name": "SN10 3HW",
    "wof:placetype": "postalcode"
  },
  "geometry": {"coordinates":[-1.972798,51.337877],"type":"Point"}
}
