{
  "type": "Feature",
  "properties": {
    "iso:country": "GB",
    "wof:name": "SN10 3HW",
    "wof:placetype": "postalcode"
  },
  "geometry": {"coordinates":[-1.972425,51.337319],"type":"Point"}
}
