{
  "type": "Feature",
  "properties": {
    "iso:country":"GB",
    "wof:name":"SN10 3HW",
    "wof:placetype":"postalcode"
},
  "geometry": {"coordinates":[-1.97246065188356,51.33731386396461],"type":"Point"}
}