{
  "type": "Feature",
  "properties": {
    "iso:country":"GB",
    "wof:name":"NE2 3BG",
    "wof:placetype":"postalcode"
},
  "geometry": {"coordinates":[-1.61048529775076,54.98776204903942],"type":"Point"}
}