{
  "type": "Feature",
  "properties": {
    "iso:country": "GB",
    "wof:name": "NE2 3BG",
    "wof:placetype": "postalcode"
  },
  "geometry": {"coordinates":[-1.610485,54.987762],"type":"Point"}
}
