{
  "type": "Feature",
  "properties": {
    "date:inception_lower": "1980-01-01",
    "date:inception_upper": "1980-01-01",
    "iso:country": "GB",
    "wof:name": "PO30 4AP",
    "wof:placetype": "postalcode"
  },
  "geometry": {"coordinates":[-1.39969,50.64816],"type":"Point"}
}
