{
  "type": "Feature",
  "properties": {
    "date:inception_lower": "2023-08-01",
    "date:inception_upper": "2023-08-01",
    "iso:country": "GB",
    "wof:name": "BH13 7DP",
    "wof:placetype": "postalcode"
  },
  "geometry": {"coordinates":[-1.918226,50.706762],"type":"Point"}
}
