{
  "type": "Feature",
  "properties": {
    "iso:country":"GB",
    "wof:name":"RH15 8NX",
    "wof:placetype":"postalcode"
},
  "geometry": {"coordinates":[-0.14264929756588,50.96147007297478],"type":"Point"}
}