{
  "type": "Feature",
  "properties": {
    "iso:country":"GB",
    "wof:name":"TN34 3BY",
    "wof:placetype":"postalcode"
},
  "geometry": {"coordinates":[0.59453272590285,50.85788660409792],"type":"Point"}
}