{
  "type": "Feature",
  "properties": {
    "iso:country":"GB",
    "wof:name":"G73 2DZ",
    "wof:placetype":"postalcode"
},
  "geometry": {"coordinates":[-4.22698218501842,55.82381552162276],"type":"Point"}
}