{
  "type": "Feature",
  "properties": {
    "date:inception_lower": "1980-01-01",
    "date:inception_upper": "1980-01-01",
    "iso:country": "GB",
    "wof:name": "NN14 4LN",
    "wof:placetype": "postalcode"
  },
  "geometry": {"coordinates":[-0.538038,52.39719],"type":"Point"}
}
