{
  "type": "Feature",
  "properties": {
    "iso:country": "GB",
    "wof:name": "NN14 4LN",
    "wof:placetype": "postalcode"
  },
  "geometry": {"coordinates":[-0.538038,52.39719],"type":"Point"}
}
