{
  "type": "Feature",
  "properties": {
    "iso:country":"GB",
    "wof:name":"RG14 3AL",
    "wof:placetype":"postalcode"
},
  "geometry": {"coordinates":[-1.32560052831473,51.42739020743555],"type":"Point"}
}