{
  "type": "Feature",
  "properties": {
    "iso:country": "GB",
    "wof:name": "RG14 3AL",
    "wof:placetype": "postalcode"
  },
  "geometry": {"coordinates":[-1.3256,51.42739],"type":"Point"}
}
