{
  "type": "Feature",
  "properties": {
    "date:inception_lower": "2002-06-01",
    "date:inception_upper": "2002-06-01",
    "iso:country": "GB",
    "wof:name": "CO3 9BB",
    "wof:placetype": "postalcode"
  },
  "geometry": {"coordinates":[0.851231,51.885471],"type":"Point"}
}
