{
  "type": "Feature",
  "properties": {
    "iso:country":"GB",
    "wof:name":"CO3 9BB",
    "wof:placetype":"postalcode"
},
  "geometry": {"coordinates":[0.85123068815829,51.88547097653404],"type":"Point"}
}