{
  "type": "Feature",
  "properties": {
    "iso:country":"GB",
    "wof:name":"CF32 8SF",
    "wof:placetype":"postalcode"
},
  "geometry": {"coordinates":[-3.58575561324679,51.5738672480777],"type":"Point"}
}