{
  "type": "Feature",
  "properties": {
    "iso:country":"GB",
    "wof:name":"TD12 4XQ",
    "wof:placetype":"postalcode"
},
  "geometry": {"coordinates":[-2.16075508171876,55.67061469058635],"type":"Point"}
}