{
  "type": "Feature",
  "properties": {
    "iso:country": "GB",
    "wof:name": "TD12 4XQ",
    "wof:placetype": "postalcode"
  },
  "geometry": {"coordinates":[-2.160755,55.670615],"type":"Point"}
}
