{
  "type": "Feature",
  "properties": {
    "iso:country": "GB",
    "wof:name": "BH21 1ED",
    "wof:placetype": "postalcode"
  },
  "geometry": {"coordinates":[-1.985886,50.799029],"type":"Point"}
}
