{
  "type": "Feature",
  "properties": {
    "iso:country":"GB",
    "wof:name":"BH21 1ED",
    "wof:placetype":"postalcode"
},
  "geometry": {"coordinates":[-1.98588632912395,50.79902924113016],"type":"Point"}
}