{
  "type": "Feature",
  "properties": {
    "date:inception_lower": "1981-06-01",
    "date:inception_upper": "1981-06-01",
    "iso:country": "GB",
    "wof:name": "BH21 1ED",
    "wof:placetype": "postalcode"
  },
  "geometry": {"coordinates":[-1.985886,50.799029],"type":"Point"}
}
