{
  "type": "Feature",
  "properties": {
    "date:inception_lower": "2019-07-01",
    "date:inception_upper": "2019-07-01",
    "iso:country": "GB",
    "wof:name": "BS49 4FZ",
    "wof:placetype": "postalcode"
  },
  "geometry": {"coordinates":[-2.815407,51.384416],"type":"Point"}
}
