{
  "type": "Feature",
  "properties": {
    "iso:country":"GB",
    "wof:name":"PR4 0BA",
    "wof:placetype":"postalcode"
},
  "geometry": {"coordinates":[-2.75647237120993,53.80950291398557],"type":"Point"}
}