{
  "type": "Feature",
  "properties": {
    "iso:country":"GB",
    "wof:name":"CO2 7RS",
    "wof:placetype":"postalcode"
},
  "geometry": {"coordinates":[0.90286610024977,51.87755237496358],"type":"Point"}
}