{
  "type": "Feature",
  "properties": {
    "iso:country":"GB",
    "wof:name":"WR15 8JR",
    "wof:placetype":"postalcode"
},
  "geometry": {"coordinates":[-2.44800239499512,52.3166430093114],"type":"Point"}
}