{
  "type": "Feature",
  "properties": {
    "iso:country": "GB",
    "wof:name": "PA13 4NP",
    "wof:placetype": "postalcode"
  },
  "geometry": {"coordinates":[-4.621318,55.891461],"type":"Point"}
}
