{
  "type": "Feature",
  "properties": {
    "date:inception_lower": "1980-01-01",
    "date:inception_upper": "1980-01-01",
    "iso:country": "GB",
    "wof:name": "PA13 4NP",
    "wof:placetype": "postalcode"
  },
  "geometry": {"coordinates":[-4.621318,55.891461],"type":"Point"}
}
