{
  "type": "Feature",
  "properties": {
    "iso:country":"GB",
    "wof:name":"HA6 1BS",
    "wof:placetype":"postalcode"
},
  "geometry": {"coordinates":[-0.41577969892423,51.60454923860949],"type":"Point"}
}