{
  "type": "Feature",
  "properties": {
    "iso:country":"GB",
    "wof:name":"IV26 2TJ",
    "wof:placetype":"postalcode"
},
  "geometry": {"coordinates":[-5.21300358002894,57.92346844473511],"type":"Point"}
}