{
  "type": "Feature",
  "properties": {
    "date:inception_lower": "1980-01-01",
    "date:inception_upper": "1980-01-01",
    "iso:country": "GB",
    "wof:name": "IV26 2TJ",
    "wof:placetype": "postalcode"
  },
  "geometry": {"coordinates":[-5.212388,57.923346],"type":"Point"}
}
