{
  "type": "Feature",
  "properties": {
    "iso:country": "GB",
    "wof:name": "YO24 3BA",
    "wof:placetype": "postalcode"
  },
  "geometry": {"coordinates":[-1.121912,53.95061],"type":"Point"}
}
