{
  "type": "Feature",
  "properties": {
    "iso:country":"GB",
    "wof:name":"GL52 6SU",
    "wof:placetype":"postalcode"
},
  "geometry": {"coordinates":[-2.05866775729448,51.89854709892759],"type":"Point"}
}