{
  "type": "Feature",
  "properties": {
    "iso:country":"GB",
    "wof:name":"EX2 5DL",
    "wof:placetype":"postalcode"
},
  "geometry": {"coordinates":[-3.5018184596974,50.71795269617845],"type":"Point"}
}