{
  "type": "Feature",
  "properties": {
    "iso:country": "GB",
    "wof:name": "B50 4GS",
    "wof:placetype": "postalcode"
  },
  "geometry": {"coordinates":[-1.867649,52.165604],"type":"Point"}
}
