{
  "type": "Feature",
  "properties": {
    "date:inception_lower": "2017-10-01",
    "date:inception_upper": "2017-10-01",
    "iso:country": "GB",
    "wof:name": "B50 4GS",
    "wof:placetype": "postalcode"
  },
  "geometry": {"coordinates":[-1.867678,52.165739],"type":"Point"}
}
