{
  "type": "Feature",
  "properties": {
    "date:inception_lower": "1980-01-01",
    "date:inception_upper": "1980-01-01",
    "iso:country": "GB",
    "wof:name": "SY22 6EA",
    "wof:placetype": "postalcode"
  },
  "geometry": {"coordinates":[-3.08871,52.781416],"type":"Point"}
}
