{
  "type": "Feature",
  "properties": {
    "iso:country":"GB",
    "wof:name":"SY22 6EA",
    "wof:placetype":"postalcode"
},
  "geometry": {"coordinates":[-3.08870955415645,52.7814159030602],"type":"Point"}
}