{
  "type": "Feature",
  "properties": {
    "iso:country": "GB",
    "wof:name": "EX1 3RB",
    "wof:placetype": "postalcode"
  },
  "geometry": {"coordinates":[-3.484154,50.730976],"type":"Point"}
}
