{
  "type": "Feature",
  "properties": {
    "iso:country":"GB",
    "wof:name":"LL32 8LR",
    "wof:placetype":"postalcode"
},
  "geometry": {"coordinates":[-3.83455999015197,53.2752193851289],"type":"Point"}
}