{
  "type": "Feature",
  "properties": {
    "date:inception_lower": "1980-01-01",
    "date:inception_upper": "1980-01-01",
    "iso:country": "GB",
    "wof:name": "SP11 7JY",
    "wof:placetype": "postalcode"
  },
  "geometry": {"coordinates":[-1.458997,51.156032],"type":"Point"}
}
