{
  "type": "Feature",
  "properties": {
    "iso:country":"GB",
    "wof:name":"HR6 9AP",
    "wof:placetype":"postalcode"
},
  "geometry": {"coordinates":[-2.78235838349578,52.23155926904089],"type":"Point"}
}