{
  "type": "Feature",
  "properties": {
    "date:inception_lower": "1980-01-01",
    "date:inception_upper": "1980-01-01",
    "iso:country": "GB",
    "wof:name": "HR6 9AP",
    "wof:placetype": "postalcode"
  },
  "geometry": {"coordinates":[-2.782358,52.231559],"type":"Point"}
}
