{
  "type": "Feature",
  "properties": {
    "date:inception_lower": "1980-01-01",
    "date:inception_upper": "1980-01-01",
    "iso:country": "GB",
    "wof:name": "GL53 9JG",
    "wof:placetype": "postalcode"
  },
  "geometry": {"coordinates":[-2.059003,51.877598],"type":"Point"}
}
