{
  "type": "Feature",
  "properties": {
    "iso:country":"GB",
    "wof:name":"GL53 9JG",
    "wof:placetype":"postalcode"
},
  "geometry": {"coordinates":[-2.0590035285006,51.87759821021038],"type":"Point"}
}