{
  "type": "Feature",
  "properties": {
    "iso:country":"GB",
    "wof:name":"PE15 9ED",
    "wof:placetype":"postalcode"
},
  "geometry": {"coordinates":[0.10079600706404,52.54401421202488],"type":"Point"}
}