{
  "type": "Feature",
  "properties": {
    "date:inception_lower": "2020-01-01",
    "date:inception_upper": "2020-01-01",
    "iso:country": "GB",
    "wof:name": "M40 3BB",
    "wof:placetype": "postalcode"
  },
  "geometry": {"coordinates":[-2.157827,53.520316],"type":"Point"}
}
