{
  "type": "Feature",
  "properties": {
    "iso:country":"GB",
    "wof:name":"GL7 5JB",
    "wof:placetype":"postalcode"
},
  "geometry": {"coordinates":[-1.86356299823117,51.69971884848123],"type":"Point"}
}