{
  "type": "Feature",
  "properties": {
    "iso:country":"GB",
    "wof:name":"RH13 9XZ",
    "wof:placetype":"postalcode"
},
  "geometry": {"coordinates":[-0.34710561288082,51.02663945330121],"type":"Point"}
}