{
  "type": "Feature",
  "properties": {
    "iso:country": "GB",
    "wof:name": "RH13 9XZ",
    "wof:placetype": "postalcode"
  },
  "geometry": {"coordinates":[-0.347106,51.026639],"type":"Point"}
}
