{
  "type": "Feature",
  "properties": {
    "iso:country":"GB",
    "wof:name":"WF6 1WS",
    "wof:placetype":"postalcode"
},
  "geometry": {"coordinates":[-1.40137435968809,53.69755107554278],"type":"Point"}
}