{
  "type": "Feature",
  "properties": {
    "iso:country": "GB",
    "wof:name": "WF6 1WS",
    "wof:placetype": "postalcode"
  },
  "geometry": {"coordinates":[-1.401374,53.697551],"type":"Point"}
}
