{
  "type": "Feature",
  "properties": {
    "iso:country":"GB",
    "wof:name":"ME15 9DL",
    "wof:placetype":"postalcode"
},
  "geometry": {"coordinates":[0.54241249650731,51.24449938486705],"type":"Point"}
}