{
  "type": "Feature",
  "properties": {
    "iso:country": "GB",
    "wof:name": "ME15 9DL",
    "wof:placetype": "postalcode"
  },
  "geometry": {"coordinates":[0.542413,51.244499],"type":"Point"}
}
