{
  "type": "Feature",
  "properties": {
    "date:inception_lower": "1994-12-01",
    "date:inception_upper": "1994-12-01",
    "iso:country": "GB",
    "wof:name": "SO51 5BN",
    "wof:placetype": "postalcode"
  },
  "geometry": {"coordinates":[-1.482791,50.990647],"type":"Point"}
}
