{
  "type": "Feature",
  "properties": {
    "iso:country": "GB",
    "wof:name": "SO51 5BN",
    "wof:placetype": "postalcode"
  },
  "geometry": {"coordinates":[-1.482791,50.990647],"type":"Point"}
}
