{
  "type": "Feature",
  "properties": {
    "iso:country":"GB",
    "wof:name":"CR0 9AE",
    "wof:placetype":"postalcode"
},
  "geometry": {"coordinates":[-0.0361308990504,51.35009164167883],"type":"Point"}
}