{
  "type": "Feature",
  "properties": {
    "iso:country": "GB",
    "wof:name": "SS14 3PT",
    "wof:placetype": "postalcode"
  },
  "geometry": {"coordinates":[0.491719,51.580112],"type":"Point"}
}
