{
  "type": "Feature",
  "properties": {
    "iso:country":"GB",
    "wof:name":"WR8 9BL",
    "wof:placetype":"postalcode"
},
  "geometry": {"coordinates":[-2.12164208646754,52.08686308280438],"type":"Point"}
}