{
  "type": "Feature",
  "properties": {
    "date:inception_lower":"1980-01-01",
    "date:inception_upper":"1980-01-31",
    "iso:country":"GB",
    "wof:name":"WR8 9BL",
    "wof:placetype":"postalcode"
},
  "geometry": {"coordinates":[-2.121642,52.086863],"type":"Point"}
}