{
  "type": "Feature",
  "properties": {
    "iso:country": "GB",
    "wof:name": "MK11 3EW",
    "wof:placetype": "postalcode"
  },
  "geometry": {"coordinates":[-0.823984,52.044442],"type":"Point"}
}
