{
  "type": "Feature",
  "properties": {
    "iso:country":"GB",
    "wof:name":"MK11 3EW",
    "wof:placetype":"postalcode"
},
  "geometry": {"coordinates":[-0.82398426269102,52.04444193378787],"type":"Point"}
}