{
  "type": "Feature",
  "properties": {
    "iso:country":"GB",
    "wof:name":"ML1 2QF",
    "wof:placetype":"postalcode"
},
  "geometry": {"coordinates":[-3.98528636183731,55.7804954199316],"type":"Point"}
}