{
  "type": "Feature",
  "properties": {
    "date:inception_lower": "2023-07-01",
    "date:inception_upper": "2023-07-01",
    "iso:country": "GB",
    "wof:name": "NG32 3FR",
    "wof:placetype": "postalcode"
  },
  "geometry": {"coordinates":[-0.603896,53.023652],"type":"Point"}
}
