{
  "type": "Feature",
  "properties": {
    "iso:country": "GB",
    "wof:name": "SO22 4JD",
    "wof:placetype": "postalcode"
  },
  "geometry": {"coordinates":[-1.346839,51.049307],"type":"Point"}
}
