{
  "type": "Feature",
  "properties": {
    "iso:country":"GB",
    "wof:name":"SO22 4JD",
    "wof:placetype":"postalcode"
},
  "geometry": {"coordinates":[-1.34683947489029,51.04930717915145],"type":"Point"}
}