{
  "type": "Feature",
  "properties": {
    "date:inception_lower": "1980-01-01",
    "date:inception_upper": "1980-01-01",
    "iso:country": "GB",
    "wof:name": "NG16 1DW",
    "wof:placetype": "postalcode"
  },
  "geometry": {"coordinates":[-1.232997,52.995927],"type":"Point"}
}
