{
  "type": "Feature",
  "properties": {
    "iso:country": "GB",
    "wof:name": "SG6 4QY",
    "wof:placetype": "postalcode"
  },
  "geometry": {"coordinates":[-0.228335,51.995396],"type":"Point"}
}
