{
  "type": "Feature",
  "properties": {
    "date:inception_lower": "1980-01-01",
    "date:inception_upper": "1980-01-01",
    "iso:country": "GB",
    "wof:name": "SG6 4QY",
    "wof:placetype": "postalcode"
  },
  "geometry": {"coordinates":[-0.228335,51.995396],"type":"Point"}
}
