{
  "type": "Feature",
  "properties": {
    "date:inception_lower": "2015-10-01",
    "date:inception_upper": "2015-10-01",
    "iso:country": "GB",
    "wof:name": "B90 9FR",
    "wof:placetype": "postalcode"
  },
  "geometry": {"coordinates":[-1.82573,52.408076],"type":"Point"}
}
