{
  "type": "Feature",
  "properties": {
    "iso:country":"GB",
    "wof:name":"N11 2DY",
    "wof:placetype":"postalcode"
},
  "geometry": {"coordinates":[-0.12951641069406,51.60888843589489],"type":"Point"}
}