{
  "type": "Feature",
  "properties": {
    "iso:country": "GB",
    "wof:name": "CT17 9QQ",
    "wof:placetype": "postalcode"
  },
  "geometry": {"coordinates":[1.297613,51.12122],"type":"Point"}
}
