{
  "type": "Feature",
  "properties": {
    "iso:country":"GB",
    "wof:name":"BS4 5DB",
    "wof:placetype":"postalcode"
},
  "geometry": {"coordinates":[-2.5491601469077,51.43055869922419],"type":"Point"}
}