{
  "type": "Feature",
  "properties": {
    "iso:country": "GB",
    "wof:name": "MK18 2LN",
    "wof:placetype": "postalcode"
  },
  "geometry": {"coordinates":[-0.991928,51.936883],"type":"Point"}
}
