{
  "type": "Feature",
  "properties": {
    "iso:country":"GB",
    "wof:name":"MK18 2LN",
    "wof:placetype":"postalcode"
},
  "geometry": {"coordinates":[-0.9919275745781,51.93688273849602],"type":"Point"}
}