{
  "type": "Feature",
  "properties": {
    "iso:country":"GB",
    "wof:name":"W5 1BU",
    "wof:placetype":"postalcode"
},
  "geometry": {"coordinates":[-0.31561916505428,51.52413992861199],"type":"Point"}
}