{
  "type": "Feature",
  "properties": {
    "iso:country": "GB",
    "wof:name": "LS19 6RS",
    "wof:placetype": "postalcode"
  },
  "geometry": {"coordinates":[-1.683224,53.858569],"type":"Point"}
}
