{
  "type": "Feature",
  "properties": {
    "iso:country":"GB",
    "wof:name":"BA1 8AG",
    "wof:placetype":"postalcode"
},
  "geometry": {"coordinates":[-2.35006267373774,51.42453406668893],"type":"Point"}
}