{
  "type": "Feature",
  "properties": {
    "iso:country":"GB",
    "wof:name":"ST8 6RN",
    "wof:placetype":"postalcode"
},
  "geometry": {"coordinates":[-2.1791925824249,53.12492904028752],"type":"Point"}
}