{
  "type": "Feature",
  "properties": {
    "date:inception_lower": "1984-10-01",
    "date:inception_upper": "1984-10-01",
    "iso:country": "GB",
    "wof:name": "HU17 5LL",
    "wof:placetype": "postalcode"
  },
  "geometry": {"coordinates":[-0.322565,53.892992],"type":"Point"}
}
