{
  "type": "Feature",
  "properties": {
    "iso:country": "GB",
    "wof:name": "RG4 8PS",
    "wof:placetype": "postalcode"
  },
  "geometry": {"coordinates":[-0.975445,51.477899],"type":"Point"}
}
