{
  "type": "Feature",
  "properties": {
    "iso:country":"GB",
    "wof:name":"NN1 4HU",
    "wof:placetype":"postalcode"
},
  "geometry": {"coordinates":[-0.87958315069888,52.24243265735777],"type":"Point"}
}