{
  "type": "Feature",
  "properties": {
    "iso:country":"GB",
    "wof:name":"BS37 8SQ",
    "wof:placetype":"postalcode"
},
  "geometry": {"coordinates":[-2.43061140759135,51.52765060548413],"type":"Point"}
}