{
  "type": "Feature",
  "properties": {
    "date:inception_lower": "1997-12-01",
    "date:inception_upper": "1997-12-01",
    "iso:country": "GB",
    "wof:name": "BS37 8SQ",
    "wof:placetype": "postalcode"
  },
  "geometry": {"coordinates":[-2.430611,51.527651],"type":"Point"}
}
