{
  "type": "Feature",
  "properties": {
    "iso:country": "GB",
    "wof:name": "FY8 5FT",
    "wof:placetype": "postalcode"
  },
  "geometry": {"coordinates":[-2.947077,53.737506],"type":"Point"}
}
