{
  "type": "Feature",
  "properties": {
    "date:inception_lower": "2015-01-01",
    "date:inception_upper": "2015-01-01",
    "iso:country": "GB",
    "wof:name": "FY8 5FT",
    "wof:placetype": "postalcode"
  },
  "geometry": {"coordinates":[-2.947077,53.737506],"type":"Point"}
}
