{
  "type": "Feature",
  "properties": {
    "iso:country": "GB",
    "wof:name": "BA1 5NL",
    "wof:placetype": "postalcode"
  },
  "geometry": {"coordinates":[-2.355425,51.390853],"type":"Point"}
}
