{
  "type": "Feature",
  "properties": {
    "iso:country":"GB",
    "wof:name":"BA1 5NL",
    "wof:placetype":"postalcode"
},
  "geometry": {"coordinates":[-2.35542481499305,51.39085320225595],"type":"Point"}
}