{
  "type": "Feature",
  "properties": {
    "iso:country": "GB",
    "wof:name": "RH16 1EL",
    "wof:placetype": "postalcode"
  },
  "geometry": {"coordinates":[-0.100437,51.00797],"type":"Point"}
}
