{
  "type": "Feature",
  "properties": {
    "iso:country":"GB",
    "wof:name":"RH16 1EL",
    "wof:placetype":"postalcode"
},
  "geometry": {"coordinates":[-0.10043717307457,51.00796983497674],"type":"Point"}
}