{
  "type": "Feature",
  "properties": {
    "date:inception_lower": "1980-01-01",
    "date:inception_upper": "1980-01-01",
    "iso:country": "GB",
    "wof:name": "RH16 1EL",
    "wof:placetype": "postalcode"
  },
  "geometry": {"coordinates":[-0.100437,51.00797],"type":"Point"}
}
