{
  "type": "Feature",
  "properties": {
    "iso:country":"GB",
    "wof:name":"WV10 6PZ",
    "wof:placetype":"postalcode"
},
  "geometry": {"coordinates":[-2.12716142065488,52.62892736311065],"type":"Point"}
}