{
  "type": "Feature",
  "properties": {
    "date:inception_lower": "1980-01-01",
    "date:inception_upper": "1980-01-01",
    "iso:country": "GB",
    "wof:name": "NR14 7RY",
    "wof:placetype": "postalcode"
  },
  "geometry": {"coordinates":[1.344633,52.575389],"type":"Point"}
}
