{
  "type": "Feature",
  "properties": {
    "iso:country":"GB",
    "wof:name":"NR14 7RY",
    "wof:placetype":"postalcode"
},
  "geometry": {"coordinates":[1.34437398144131,52.57520081781954],"type":"Point"}
}