{
  "type": "Feature",
  "properties": {
    "iso:country": "GB",
    "wof:name": "NR14 7RY",
    "wof:placetype": "postalcode"
  },
  "geometry": {"coordinates":[1.344633,52.575389],"type":"Point"}
}
