{
  "type": "Feature",
  "properties": {
    "iso:country":"GB",
    "wof:name":"W13 8AX",
    "wof:placetype":"postalcode"
},
  "geometry": {"coordinates":[-0.31604734745015,51.52152032388648],"type":"Point"}
}