{
  "type": "Feature",
  "properties": {
    "iso:country": "GB",
    "wof:name": "RG26 4BJ",
    "wof:placetype": "postalcode"
  },
  "geometry": {"coordinates":[-1.146461,51.353542],"type":"Point"}
}
