{
  "type": "Feature",
  "properties": {
    "date:inception_lower": "1995-07-01",
    "date:inception_upper": "1995-07-01",
    "iso:country": "GB",
    "wof:name": "RG26 4BJ",
    "wof:placetype": "postalcode"
  },
  "geometry": {"coordinates":[-1.146461,51.353542],"type":"Point"}
}
