{
  "type": "Feature",
  "properties": {
    "iso:country": "GB",
    "wof:name": "OX3 7TF",
    "wof:placetype": "postalcode"
  },
  "geometry": {"coordinates":[-1.226775,51.764789],"type":"Point"}
}
