{
  "type": "Feature",
  "properties": {
    "iso:country":"GB",
    "wof:name":"OX3 7TF",
    "wof:placetype":"postalcode"
},
  "geometry": {"coordinates":[-1.22677499602154,51.76478876441598],"type":"Point"}
}