{
  "type": "Feature",
  "properties": {
    "iso:country":"GB",
    "wof:name":"ST14 7PU",
    "wof:placetype":"postalcode"
},
  "geometry": {"coordinates":[-1.87559815583544,52.90194280121847],"type":"Point"}
}