{
  "type": "Feature",
  "properties": {
    "iso:country":"GB",
    "wof:name":"GU5 9SW",
    "wof:placetype":"postalcode"
},
  "geometry": {"coordinates":[-0.4391481261217,51.19942413994934],"type":"Point"}
}