{
  "type": "Feature",
  "properties": {
    "date:inception_lower":"1980-01-01",
    "date:inception_upper":"1980-01-31",
    "iso:country":"GB",
    "wof:name":"GU5 9SW",
    "wof:placetype":"postalcode"
},
  "geometry": {"coordinates":[-0.439148,51.199424],"type":"Point"}
}