{
  "type": "Feature",
  "properties": {
    "date:inception_lower":"2016-05-01",
    "date:inception_upper":"2016-05-31",
    "iso:country":"GB",
    "wof:name":"BR1 1QF",
    "wof:placetype":"postalcode"
},
  "geometry": {"coordinates":[0.017578,51.408226],"type":"Point"}
}