{
  "type": "Feature",
  "properties": {
    "iso:country": "GB",
    "wof:name": "BH20 7LD",
    "wof:placetype": "postalcode"
  },
  "geometry": {"coordinates":[-2.215492,50.753643],"type":"Point"}
}
