{
  "type": "Feature",
  "properties": {
    "iso:country":"GB",
    "wof:name":"BH20 7LD",
    "wof:placetype":"postalcode"
},
  "geometry": {"coordinates":[-2.21549160961456,50.75364275882321],"type":"Point"}
}