{
  "type": "Feature",
  "properties": {
    "iso:country":"GB",
    "wof:name":"B74 2RR",
    "wof:placetype":"postalcode"
},
  "geometry": {"coordinates":[-1.82479818655166,52.57277048660266],"type":"Point"}
}