{
  "type": "Feature",
  "properties": {
    "date:inception_lower": "1995-12-01",
    "date:inception_upper": "1995-12-01",
    "iso:country": "GB",
    "wof:name": "KT12 2TJ",
    "wof:placetype": "postalcode"
  },
  "geometry": {"coordinates":[-0.417146,51.385768],"type":"Point"}
}
