{
  "type": "Feature",
  "properties": {
    "date:inception_lower": "1995-12-01",
    "date:inception_upper": "1995-12-01",
    "iso:country": "GB",
    "wof:name": "KT12 2TJ",
    "wof:placetype": "postalcode"
  },
  "geometry": {"coordinates":[-0.418179,51.385404],"type":"Point"}
}
