{
  "type": "Feature",
  "properties": {
    "iso:country":"GB",
    "wof:name":"IP1 1XG",
    "wof:placetype":"postalcode"
},
  "geometry": {"coordinates":[1.15261587828441,52.05399616836842],"type":"Point"}
}