{
  "type": "Feature",
  "properties": {
    "iso:country": "GB",
    "wof:name": "IP1 1XG",
    "wof:placetype": "postalcode"
  },
  "geometry": {"coordinates":[1.152616,52.053996],"type":"Point"}
}
