{
  "type": "Feature",
  "properties": {
    "date:inception_lower": "1980-01-01",
    "date:inception_upper": "1980-01-01",
    "iso:country": "GB",
    "wof:name": "NE66 4ED",
    "wof:placetype": "postalcode"
  },
  "geometry": {"coordinates":[-1.933019,55.505633],"type":"Point"}
}
