{
  "type": "Feature",
  "properties": {
    "iso:country":"GB",
    "wof:name":"B17 0AL",
    "wof:placetype":"postalcode"
},
  "geometry": {"coordinates":[-1.96029727071986,52.45482868995397],"type":"Point"}
}