{
  "type": "Feature",
  "properties": {
    "date:inception_lower": "1983-07-01",
    "date:inception_upper": "1983-07-01",
    "iso:country": "GB",
    "wof:name": "SN5 7EP",
    "wof:placetype": "postalcode"
  },
  "geometry": {"coordinates":[-1.829585,51.561668],"type":"Point"}
}
