{
  "type": "Feature",
  "properties": {
    "date:inception_lower": "1980-01-01",
    "date:inception_upper": "1980-01-01",
    "iso:country": "GB",
    "wof:name": "W2 4PU",
    "wof:placetype": "postalcode"
  },
  "geometry": {"coordinates":[-0.192379,51.513673],"type":"Point"}
}
