{
  "type": "Feature",
  "properties": {
    "iso:country":"GB",
    "wof:name":"W2 4PU",
    "wof:placetype":"postalcode"
},
  "geometry": {"coordinates":[-0.19237939800142,51.51367283356814],"type":"Point"}
}