{
  "type": "Feature",
  "properties": {
    "iso:country":"GB",
    "wof:name":"HP13 5LX",
    "wof:placetype":"postalcode"
},
  "geometry": {"coordinates":[-0.77125636628935,51.64298549086891],"type":"Point"}
}