{
  "type": "Feature",
  "properties": {
    "iso:country": "GB",
    "wof:name": "HP13 5LX",
    "wof:placetype": "postalcode"
  },
  "geometry": {"coordinates":[-0.771256,51.642985],"type":"Point"}
}
