{
  "type": "Feature",
  "properties": {
    "date:inception_lower": "1992-08-01",
    "date:inception_upper": "1992-08-01",
    "iso:country": "GB",
    "wof:name": "DE22 2NA",
    "wof:placetype": "postalcode"
  },
  "geometry": {"coordinates":[-1.506883,52.945528],"type":"Point"}
}
