{
  "type": "Feature",
  "properties": {
    "iso:country": "GB",
    "wof:name": "EX4 4LA",
    "wof:placetype": "postalcode"
  },
  "geometry": {"coordinates":[-3.538758,50.73034],"type":"Point"}
}
