{
  "type": "Feature",
  "properties": {
    "iso:country":"GB",
    "wof:name":"EX4 4LA",
    "wof:placetype":"postalcode"
},
  "geometry": {"coordinates":[-3.5387585243623,50.73034027040196],"type":"Point"}
}