{
  "type": "Feature",
  "properties": {
    "iso:country":"GB",
    "wof:name":"RH4 2QJ",
    "wof:placetype":"postalcode"
},
  "geometry": {"coordinates":[-0.32226705012921,51.22693404880431],"type":"Point"}
}