{
  "type": "Feature",
  "properties": {
    "iso:country":"GB",
    "wof:name":"L35 1RB",
    "wof:placetype":"postalcode"
},
  "geometry": {"coordinates":[-2.80705956382305,53.40226328595801],"type":"Point"}
}