{
  "type": "Feature",
  "properties": {
    "iso:country": "GB",
    "wof:name": "SG4 7BL",
    "wof:placetype": "postalcode"
  },
  "geometry": {"coordinates":[-0.232513,51.933818],"type":"Point"}
}
