{
  "type": "Feature",
  "properties": {
    "iso:country": "GB",
    "wof:name": "CF83 1QN",
    "wof:placetype": "postalcode"
  },
  "geometry": {"coordinates":[-3.209517,51.579041],"type":"Point"}
}
