{
  "type": "Feature",
  "properties": {
    "iso:country": "GB",
    "wof:name": "NE34 7EX",
    "wof:placetype": "postalcode"
  },
  "geometry": {"coordinates":[-1.38721,54.974576],"type":"Point"}
}
