{
  "type": "Feature",
  "properties": {
    "iso:country":"GB",
    "wof:name":"NE34 7EX",
    "wof:placetype":"postalcode"
},
  "geometry": {"coordinates":[-1.38721034782557,54.97457636581141],"type":"Point"}
}