{
  "type": "Feature",
  "properties": {
    "date:inception_lower":"1990-02-01",
    "date:inception_upper":"1990-02-28",
    "iso:country":"GB",
    "wof:name":"NE34 7EX",
    "wof:placetype":"postalcode"
},
  "geometry": {"coordinates":[-1.38721,54.974576],"type":"Point"}
}