{
  "type": "Feature",
  "properties": {
    "iso:country":"GB",
    "wof:name":"WN4 9NF",
    "wof:placetype":"postalcode"
},
  "geometry": {"coordinates":[-2.65121289663752,53.48834679912745],"type":"Point"}
}