{
  "type": "Feature",
  "properties": {
    "iso:country":"GB",
    "wof:name":"G32 0JR",
    "wof:placetype":"postalcode"
},
  "geometry": {"coordinates":[-4.15265887624044,55.85925485403687],"type":"Point"}
}