{
  "type": "Feature",
  "properties": {
    "iso:country":"GB",
    "wof:name":"HX2 8RA",
    "wof:placetype":"postalcode"
},
  "geometry": {"coordinates":[-1.90945697153635,53.75197806193261],"type":"Point"}
}