{
  "type": "Feature",
  "properties": {
    "date:inception_lower": "2024-10-01",
    "date:inception_upper": "2024-10-01",
    "iso:country": "GB",
    "wof:name": "IG10 9JJ",
    "wof:placetype": "postalcode"
  },
  "geometry": {"coordinates":[0.086895,51.646483],"type":"Point"}
}
