{
  "type": "Feature",
  "properties": {
    "iso:country": "GB",
    "wof:name": "CV7 9GZ",
    "wof:placetype": "postalcode"
  },
  "geometry": {"coordinates":[-1.501019,52.462576],"type":"Point"}
}
