{
  "type": "Feature",
  "properties": {
    "iso:country":"GB",
    "wof:name":"CV7 9GZ",
    "wof:placetype":"postalcode"
},
  "geometry": {"coordinates":[-1.50101936815375,52.46257622388916],"type":"Point"}
}