{
  "type": "Feature",
  "properties": {
    "iso:country":"GB",
    "wof:name":"G51 1BU",
    "wof:placetype":"postalcode"
},
  "geometry": {"coordinates":[-4.28780512639443,55.85253746508691],"type":"Point"}
}