{
  "type": "Feature",
  "properties": {
    "date:inception_lower": "1990-02-01",
    "date:inception_upper": "1990-02-01",
    "iso:country": "GB",
    "wof:name": "SG2 7QR",
    "wof:placetype": "postalcode"
  },
  "geometry": {"coordinates":[-0.162365,51.910653],"type":"Point"}
}
