{
  "type": "Feature",
  "properties": {
    "iso:country":"GB",
    "wof:name":"SG2 7QR",
    "wof:placetype":"postalcode"
},
  "geometry": {"coordinates":[-0.16236504468568,51.91065297199607],"type":"Point"}
}