{
  "type": "Feature",
  "properties": {
    "iso:country": "GB",
    "wof:name": "RM3 9UR",
    "wof:placetype": "postalcode"
  },
  "geometry": {"coordinates":[0.220356,51.614233],"type":"Point"}
}
