{
  "type": "Feature",
  "properties": {
    "iso:country":"GB",
    "wof:name":"RM3 9UR",
    "wof:placetype":"postalcode"
},
  "geometry": {"coordinates":[0.22034412241209,51.61423015225019],"type":"Point"}
}