{
  "type": "Feature",
  "properties": {
    "iso:country":"GB",
    "wof:name":"SM7 2HA",
    "wof:placetype":"postalcode"
},
  "geometry": {"coordinates":[-0.20424141063383,51.31437279643395],"type":"Point"}
}