{
  "type": "Feature",
  "properties": {
    "date:inception_lower": "1980-01-01",
    "date:inception_upper": "1980-01-01",
    "iso:country": "GB",
    "wof:name": "SM5 1LG",
    "wof:placetype": "postalcode"
  },
  "geometry": {"coordinates":[-0.169133,51.38738],"type":"Point"}
}
