{
  "type": "Feature",
  "properties": {
    "date:inception_lower": "2002-06-01",
    "date:inception_upper": "2002-06-01",
    "iso:country": "GB",
    "wof:name": "TN37 6DS",
    "wof:placetype": "postalcode"
  },
  "geometry": {"coordinates":[0.560738,50.85446],"type":"Point"}
}
