{
  "type": "Feature",
  "properties": {
    "iso:country":"GB",
    "wof:name":"TN37 6DS",
    "wof:placetype":"postalcode"
},
  "geometry": {"coordinates":[0.56073755393894,50.85446003346608],"type":"Point"}
}