{
  "type": "Feature",
  "properties": {
    "iso:country": "GB",
    "wof:name": "YO16 7SZ",
    "wof:placetype": "postalcode"
  },
  "geometry": {"coordinates":[-0.195031,54.094106],"type":"Point"}
}
