{
  "type": "Feature",
  "properties": {
    "date:inception_lower":"2002-09-01",
    "date:inception_upper":"2002-09-30",
    "iso:country":"GB",
    "wof:name":"YO16 7SZ",
    "wof:placetype":"postalcode"
},
  "geometry": {"coordinates":[-0.195031,54.094106],"type":"Point"}
}