{
  "type": "Feature",
  "properties": {
    "iso:country":"GB",
    "wof:name":"HP1 1JW",
    "wof:placetype":"postalcode"
},
  "geometry": {"coordinates":[-0.47572373822732,51.74752317359098],"type":"Point"}
}