{
  "type": "Feature",
  "properties": {
    "date:inception_lower":"1980-01-01",
    "date:inception_upper":"1980-01-31",
    "iso:country":"GB",
    "wof:name":"S74 0JU",
    "wof:placetype":"postalcode"
},
  "geometry": {"coordinates":[-1.429644,53.506191],"type":"Point"}
}