{
  "type": "Feature",
  "properties": {
    "iso:country":"GB",
    "wof:name":"WN2 2JZ",
    "wof:placetype":"postalcode"
},
  "geometry": {"coordinates":[-2.59160172613227,53.54430478221236],"type":"Point"}
}