{
  "type": "Feature",
  "properties": {
    "iso:country":"GB",
    "wof:name":"RH17 7JD",
    "wof:placetype":"postalcode"
},
  "geometry": {"coordinates":[0.00799234330838,51.03353211294547],"type":"Point"}
}