{
  "type": "Feature",
  "properties": {
    "iso:country":"GB",
    "wof:name":"BH6 3DB",
    "wof:placetype":"postalcode"
},
  "geometry": {"coordinates":[-1.80653204392811,50.72283750509043],"type":"Point"}
}