{
  "type": "Feature",
  "properties": {
    "date:inception_lower": "1980-01-01",
    "date:inception_upper": "1980-01-01",
    "iso:country": "GB",
    "wof:name": "SW19 5BH",
    "wof:placetype": "postalcode"
  },
  "geometry": {"coordinates":[-0.214577,51.429618],"type":"Point"}
}
