{
  "type": "Feature",
  "properties": {
    "iso:country":"GB",
    "wof:name":"SW19 5BH",
    "wof:placetype":"postalcode"
},
  "geometry": {"coordinates":[-0.21457114740325,51.42965427038033],"type":"Point"}
}