{
  "type": "Feature",
  "properties": {
    "iso:country": "GB",
    "wof:name": "SK15 1ST",
    "wof:placetype": "postalcode"
  },
  "geometry": {"coordinates":[-2.070178,53.479558],"type":"Point"}
}
