{
  "type": "Feature",
  "properties": {
    "date:inception_lower": "1980-01-01",
    "date:inception_upper": "1980-01-01",
    "iso:country": "GB",
    "wof:name": "SK15 1ST",
    "wof:placetype": "postalcode"
  },
  "geometry": {"coordinates":[-2.070178,53.479558],"type":"Point"}
}
