{
  "type": "Feature",
  "properties": {
    "iso:country":"GB",
    "wof:name":"MK13 8AF",
    "wof:placetype":"postalcode"
},
  "geometry": {"coordinates":[-0.76644372385823,52.04506751658081],"type":"Point"}
}