{
  "type": "Feature",
  "properties": {
    "iso:country":"GB",
    "wof:name":"SP3 6SG",
    "wof:placetype":"postalcode"
},
  "geometry": {"coordinates":[-2.10553575318318,51.07007421146572],"type":"Point"}
}