{
  "type": "Feature",
  "properties": {
    "date:inception_lower":"1980-01-01",
    "date:inception_upper":"1980-01-31",
    "iso:country":"GB",
    "wof:name":"SP3 6SG",
    "wof:placetype":"postalcode"
},
  "geometry": {"coordinates":[-2.104874,51.070437],"type":"Point"}
}