{
  "type": "Feature",
  "properties": {
    "iso:country":"GB",
    "wof:name":"TS26 0AJ",
    "wof:placetype":"postalcode"
},
  "geometry": {"coordinates":[-1.24997315789224,54.68093225998183],"type":"Point"}
}