{
  "type": "Feature",
  "properties": {
    "iso:country": "GB",
    "wof:name": "TS26 0AJ",
    "wof:placetype": "postalcode"
  },
  "geometry": {"coordinates":[-1.249973,54.680932],"type":"Point"}
}
