{
  "type": "Feature",
  "properties": {
    "iso:country": "GB",
    "wof:name": "GU22 2TH",
    "wof:placetype": "postalcode"
  },
  "geometry": {"coordinates":[-0.555831,51.317679],"type":"Point"}
}
