{
  "type": "Feature",
  "properties": {
    "date:inception_lower": "1980-01-01",
    "date:inception_upper": "1980-01-01",
    "iso:country": "GB",
    "wof:name": "PL20 7EY",
    "wof:placetype": "postalcode"
  },
  "geometry": {"coordinates":[-4.199542,50.491786],"type":"Point"}
}
