{
  "type": "Feature",
  "properties": {
    "iso:country":"GB",
    "wof:name":"PL20 7EY",
    "wof:placetype":"postalcode"
},
  "geometry": {"coordinates":[-4.19954253332385,50.49178633046623],"type":"Point"}
}