{
  "type": "Feature",
  "properties": {
    "iso:country":"GB",
    "wof:name":"M30 7HN",
    "wof:placetype":"postalcode"
},
  "geometry": {"coordinates":[-2.36024589987423,53.47730928592767],"type":"Point"}
}