{
  "type": "Feature",
  "properties": {
    "iso:country":"GB",
    "wof:name":"SA1 5SW",
    "wof:placetype":"postalcode"
},
  "geometry": {"coordinates":[-3.95178323596386,51.62028925444396],"type":"Point"}
}