{
  "type": "Feature",
  "properties": {
    "iso:country":"GB",
    "wof:name":"SS7 1RN",
    "wof:placetype":"postalcode"
},
  "geometry": {"coordinates":[0.5951640223743,51.55767840294051],"type":"Point"}
}