{
  "type": "Feature",
  "properties": {
    "iso:country":"GB",
    "wof:name":"PA2 9AE",
    "wof:placetype":"postalcode"
},
  "geometry": {"coordinates":[-4.45446112018333,55.83645369032519],"type":"Point"}
}