{
  "type": "Feature",
  "properties": {
    "iso:country":"GB",
    "wof:name":"DT11 8DZ",
    "wof:placetype":"postalcode"
},
  "geometry": {"coordinates":[-2.24243854696936,50.91219073458128],"type":"Point"}
}