{
  "type": "Feature",
  "properties": {
    "iso:country": "GB",
    "wof:name": "DT11 8DZ",
    "wof:placetype": "postalcode"
  },
  "geometry": {"coordinates":[-2.242439,50.912191],"type":"Point"}
}
