{
  "type": "Feature",
  "properties": {
    "date:inception_lower":"2010-11-01",
    "date:inception_upper":"2010-11-30",
    "iso:country":"GB",
    "wof:name":"BS36 1LS",
    "wof:placetype":"postalcode"
},
  "geometry": {"coordinates":[-2.501153,51.521957],"type":"Point"}
}