{
  "type": "Feature",
  "properties": {
    "iso:country": "GB",
    "wof:name": "PO35 5AL",
    "wof:placetype": "postalcode"
  },
  "geometry": {"coordinates":[-1.076209,50.683402],"type":"Point"}
}
