{
  "type": "Feature",
  "properties": {
    "date:inception_lower": "2018-08-01",
    "date:inception_upper": "2018-08-01",
    "iso:country": "GB",
    "wof:name": "PO35 5AL",
    "wof:placetype": "postalcode"
  },
  "geometry": {"coordinates":[-1.076322,50.683385],"type":"Point"}
}
