{
  "type": "Feature",
  "properties": {
    "iso:country":"GB",
    "wof:name":"N1 5AW",
    "wof:placetype":"postalcode"
},
  "geometry": {"coordinates":[-0.08039172847659,51.53984230778349],"type":"Point"}
}