{
  "type": "Feature",
  "properties": {
    "date:inception_lower":"2003-02-01",
    "date:inception_upper":"2003-02-28",
    "iso:country":"GB",
    "wof:name":"N1 5AW",
    "wof:placetype":"postalcode"
},
  "geometry": {"coordinates":[-0.080392,51.539842],"type":"Point"}
}