{
  "type": "Feature",
  "properties": {
    "iso:country":"GB",
    "wof:name":"OX26 4HP",
    "wof:placetype":"postalcode"
},
  "geometry": {"coordinates":[-1.14984548624761,51.90425942676836],"type":"Point"}
}