{
  "type": "Feature",
  "properties": {
    "iso:country":"GB",
    "wof:name":"SP5 3SE",
    "wof:placetype":"postalcode"
},
  "geometry": {"coordinates":[-1.70242995832818,51.04322611469311],"type":"Point"}
}