{
  "type": "Feature",
  "properties": {
    "date:inception_lower": "1980-01-01",
    "date:inception_upper": "1980-01-01",
    "iso:country": "GB",
    "wof:name": "SP5 3SE",
    "wof:placetype": "postalcode"
  },
  "geometry": {"coordinates":[-1.703189,51.043339],"type":"Point"}
}
