{
  "type": "Feature",
  "properties": {
    "iso:country":"GB",
    "wof:name":"SA2 9LT",
    "wof:placetype":"postalcode"
},
  "geometry": {"coordinates":[-3.99620124663339,51.62348982429604],"type":"Point"}
}