{
  "type": "Feature",
  "properties": {
    "iso:country":"GB",
    "wof:name":"NE23 6XP",
    "wof:placetype":"postalcode"
},
  "geometry": {"coordinates":[-1.55971378583343,55.07890672222037],"type":"Point"}
}