{
  "type": "Feature",
  "properties": {
    "iso:country": "GB",
    "wof:name": "NE23 6XP",
    "wof:placetype": "postalcode"
  },
  "geometry": {"coordinates":[-1.559714,55.078907],"type":"Point"}
}
