{
  "type": "Feature",
  "properties": {
    "iso:country":"GB",
    "wof:name":"OX10 9BN",
    "wof:placetype":"postalcode"
},
  "geometry": {"coordinates":[-1.13169649435414,51.59639911604135],"type":"Point"}
}