{
  "type": "Feature",
  "properties": {
    "date:inception_lower":"2013-05-01",
    "date:inception_upper":"2013-05-31",
    "iso:country":"GB",
    "wof:name":"PL3 6PN",
    "wof:placetype":"postalcode"
},
  "geometry": {"coordinates":[-4.111868,50.389806],"type":"Point"}
}