{
  "type": "Feature",
  "properties": {
    "iso:country":"GB",
    "wof:name":"PL3 6PN",
    "wof:placetype":"postalcode"
},
  "geometry": {"coordinates":[-4.11186809810446,50.38980601694269],"type":"Point"}
}