{
  "type": "Feature",
  "properties": {
    "iso:country": "GB",
    "wof:name": "DY14 8DP",
    "wof:placetype": "postalcode"
  },
  "geometry": {"coordinates":[-2.485599,52.378316],"type":"Point"}
}
