{
  "type": "Feature",
  "properties": {
    "iso:country":"GB",
    "wof:name":"DY14 8DP",
    "wof:placetype":"postalcode"
},
  "geometry": {"coordinates":[-2.48573428060424,52.37829273477364],"type":"Point"}
}