{
  "type": "Feature",
  "properties": {
    "date:inception_lower":"1980-01-01",
    "date:inception_upper":"1980-01-31",
    "iso:country":"GB",
    "wof:name":"DY14 8DP",
    "wof:placetype":"postalcode"
},
  "geometry": {"coordinates":[-2.485688,52.378316],"type":"Point"}
}