{
  "type": "Feature",
  "properties": {
    "iso:country":"GB",
    "wof:name":"RH11 0RJ",
    "wof:placetype":"postalcode"
},
  "geometry": {"coordinates":[-0.22505895253843,51.11264824769372],"type":"Point"}
}