{
  "type": "Feature",
  "properties": {
    "iso:country":"GB",
    "wof:name":"SW1V 3AE",
    "wof:placetype":"postalcode"
},
  "geometry": {"coordinates":[-0.14260147543575,51.4856387765952],"type":"Point"}
}