{
  "type": "Feature",
  "properties": {
    "iso:country":"GB",
    "wof:name":"NG4 2LA",
    "wof:placetype":"postalcode"
},
  "geometry": {"coordinates":[-1.0782686985324,52.96434549834898],"type":"Point"}
}