{
  "type": "Feature",
  "properties": {
    "iso:country": "GB",
    "wof:name": "NG4 2LA",
    "wof:placetype": "postalcode"
  },
  "geometry": {"coordinates":[-1.078383,52.964412],"type":"Point"}
}
