{
  "type": "Feature",
  "properties": {
    "iso:country":"GB",
    "wof:name":"NE64 6NS",
    "wof:placetype":"postalcode"
},
  "geometry": {"coordinates":[-1.51696730599627,55.18303711596406],"type":"Point"}
}