{
  "type": "Feature",
  "properties": {
    "date:inception_lower": "1980-01-01",
    "date:inception_upper": "1980-01-01",
    "iso:country": "GB",
    "wof:name": "NE64 6NS",
    "wof:placetype": "postalcode"
  },
  "geometry": {"coordinates":[-1.516967,55.183037],"type":"Point"}
}
