{
  "type": "Feature",
  "properties": {
    "date:inception_lower": "1980-01-01",
    "date:inception_upper": "1980-01-01",
    "iso:country": "GB",
    "wof:name": "ME17 3JZ",
    "wof:placetype": "postalcode"
  },
  "geometry": {"coordinates":[0.590127,51.236815],"type":"Point"}
}
