{
  "type": "Feature",
  "properties": {
    "iso:country":"GB",
    "wof:name":"ME17 3JZ",
    "wof:placetype":"postalcode"
},
  "geometry": {"coordinates":[0.59012711092098,51.23681530138595],"type":"Point"}
}