{
  "type": "Feature",
  "properties": {
    "iso:country": "GB",
    "wof:name": "NG9 5FX",
    "wof:placetype": "postalcode"
  },
  "geometry": {"coordinates":[-1.246102,52.918396],"type":"Point"}
}
