{
  "type": "Feature",
  "properties": {
    "iso:country":"GB",
    "wof:name":"NG9 5FX",
    "wof:placetype":"postalcode"
},
  "geometry": {"coordinates":[-1.24610232168825,52.91839628825359],"type":"Point"}
}