{
  "type": "Feature",
  "properties": {
    "date:inception_lower": "1980-01-01",
    "date:inception_upper": "1980-01-01",
    "iso:country": "GB",
    "wof:name": "NG9 5FX",
    "wof:placetype": "postalcode"
  },
  "geometry": {"coordinates":[-1.246102,52.918396],"type":"Point"}
}
