{
  "type": "Feature",
  "properties": {
    "date:inception_lower": "1980-01-01",
    "date:inception_upper": "1980-01-01",
    "iso:country": "GB",
    "wof:name": "LN5 9HT",
    "wof:placetype": "postalcode"
  },
  "geometry": {"coordinates":[-0.647016,53.110838],"type":"Point"}
}
