{
  "type": "Feature",
  "properties": {
    "iso:country":"GB",
    "wof:name":"LN5 9HT",
    "wof:placetype":"postalcode"
},
  "geometry": {"coordinates":[-0.64702356609477,53.1106821915188],"type":"Point"}
}