{
  "type": "Feature",
  "properties": {
    "iso:country":"GB",
    "wof:name":"CR0 3LP",
    "wof:placetype":"postalcode"
},
  "geometry": {"coordinates":[-0.11186583005446,51.3809320781844],"type":"Point"}
}