{
  "type": "Feature",
  "properties": {
    "date:inception_lower": "1999-06-01",
    "date:inception_upper": "1999-06-01",
    "iso:country": "GB",
    "wof:name": "L3 8LB",
    "wof:placetype": "postalcode"
  },
  "geometry": {"coordinates":[-2.972064,53.409699],"type":"Point"}
}
