{
  "type": "Feature",
  "properties": {
    "iso:country":"GB",
    "wof:name":"SO40 3PN",
    "wof:placetype":"postalcode"
},
  "geometry": {"coordinates":[-1.50445560720039,50.92702139336115],"type":"Point"}
}