{
  "type": "Feature",
  "properties": {
    "iso:country":"GB",
    "wof:name":"MK13 7AZ",
    "wof:placetype":"postalcode"
},
  "geometry": {"coordinates":[-0.77780249858246,52.06057863805521],"type":"Point"}
}