{
  "type": "Feature",
  "properties": {
    "date:inception_lower": "2023-04-01",
    "date:inception_upper": "2023-04-01",
    "iso:country": "GB",
    "wof:name": "PE26 2AG",
    "wof:placetype": "postalcode"
  },
  "geometry": {"coordinates":[-0.112324,52.455176],"type":"Point"}
}
