{
  "type": "Feature",
  "properties": {
    "iso:country": "GB",
    "wof:name": "NE28 8UN",
    "wof:placetype": "postalcode"
  },
  "geometry": {"coordinates":[-1.55569,55.000919],"type":"Point"}
}
