{
  "type": "Feature",
  "properties": {
    "iso:country":"GB",
    "wof:name":"LE3 2PQ",
    "wof:placetype":"postalcode"
},
  "geometry": {"coordinates":[-1.17999306540388,52.61219858552419],"type":"Point"}
}