{
  "type": "Feature",
  "properties": {
    "iso:country": "GB",
    "wof:name": "KA21 6BD",
    "wof:placetype": "postalcode"
  },
  "geometry": {"coordinates":[-4.78816,55.645182],"type":"Point"}
}
