{
  "type": "Feature",
  "properties": {
    "iso:country":"GB",
    "wof:name":"KA21 6BD",
    "wof:placetype":"postalcode"
},
  "geometry": {"coordinates":[-4.78816035309172,55.64518193028368],"type":"Point"}
}