{
  "type": "Feature",
  "properties": {
    "iso:country":"GB",
    "wof:name":"EN9 2AT",
    "wof:placetype":"postalcode"
},
  "geometry": {"coordinates":[0.03666051240907,51.70308004347],"type":"Point"}
}