{
  "type": "Feature",
  "properties": {
    "iso:country":"GB",
    "wof:name":"GU21 7RU",
    "wof:placetype":"postalcode"
},
  "geometry": {"coordinates":[-0.59201113684578,51.31304023845298],"type":"Point"}
}