{
  "type": "Feature",
  "properties": {
    "date:inception_lower": "2021-10-01",
    "date:inception_upper": "2021-10-01",
    "iso:country": "GB",
    "wof:name": "G66 4BQ",
    "wof:placetype": "postalcode"
  },
  "geometry": {"coordinates":[-4.154019,55.932516],"type":"Point"}
}
