{
  "type": "Feature",
  "properties": {
    "iso:country":"GB",
    "wof:name":"GU52 6QQ",
    "wof:placetype":"postalcode"
},
  "geometry": {"coordinates":[-0.8499918647482,51.26545609145126],"type":"Point"}
}