{
  "type": "Feature",
  "properties": {
    "date:inception_lower": "1980-01-01",
    "date:inception_upper": "1980-01-01",
    "iso:country": "GB",
    "wof:name": "LE11 2DN",
    "wof:placetype": "postalcode"
  },
  "geometry": {"coordinates":[-1.206112,52.766786],"type":"Point"}
}
