{
  "type": "Feature",
  "properties": {
    "date:inception_lower": "2004-05-01",
    "date:inception_upper": "2004-05-01",
    "iso:country": "GB",
    "wof:name": "BS30 8XJ",
    "wof:placetype": "postalcode"
  },
  "geometry": {"coordinates":[-2.475699,51.456902],"type":"Point"}
}
