{
  "type": "Feature",
  "properties": {
    "iso:country":"GB",
    "wof:name":"BN22 9HX",
    "wof:placetype":"postalcode"
},
  "geometry": {"coordinates":[0.27810674844489,50.80515279325436],"type":"Point"}
}