{
  "type": "Feature",
  "properties": {
    "iso:country":"GB",
    "wof:name":"DE5 3AT",
    "wof:placetype":"postalcode"
},
  "geometry": {"coordinates":[-1.40186145697523,53.05016666980791],"type":"Point"}
}