{
  "type": "Feature",
  "properties": {
    "iso:country":"GB",
    "wof:name":"HU8 7SR",
    "wof:placetype":"postalcode"
},
  "geometry": {"coordinates":[-0.31438862236264,53.75418519969933],"type":"Point"}
}