{
  "type": "Feature",
  "properties": {
    "iso:country":"GB",
    "wof:name":"WA2 8XG",
    "wof:placetype":"postalcode"
},
  "geometry": {"coordinates":[-2.59927322238205,53.42710954520651],"type":"Point"}
}