{
  "type": "Feature",
  "properties": {
    "iso:country":"GB",
    "wof:name":"BD12 0UF",
    "wof:placetype":"postalcode"
},
  "geometry": {"coordinates":[-1.76382287422928,53.75515941885673],"type":"Point"}
}