{
  "type": "Feature",
  "properties": {
    "iso:country":"GB",
    "wof:name":"HP2 5SL",
    "wof:placetype":"postalcode"
},
  "geometry": {"coordinates":[-0.46229769914945,51.76152839567823],"type":"Point"}
}