{
  "type": "Feature",
  "properties": {
    "iso:country":"GB",
    "wof:name":"B91 2NJ",
    "wof:placetype":"postalcode"
},
  "geometry": {"coordinates":[-1.77090763022226,52.42612450413175],"type":"Point"}
}