{
  "type": "Feature",
  "properties": {
    "date:inception_lower": "2014-07-01",
    "date:inception_upper": "2014-07-01",
    "iso:country": "GB",
    "wof:name": "DT1 3UZ",
    "wof:placetype": "postalcode"
  },
  "geometry": {"coordinates":[-2.464241,50.711155],"type":"Point"}
}
