{
  "type": "Feature",
  "properties": {
    "iso:country":"GB",
    "wof:name":"DT1 3UZ",
    "wof:placetype":"postalcode"
},
  "geometry": {"coordinates":[-2.46424074159412,50.71115515278722],"type":"Point"}
}