{
  "type": "Feature",
  "properties": {
    "date:inception_lower":"2002-05-01",
    "date:inception_upper":"2002-05-31",
    "iso:country":"GB",
    "wof:name":"SE1 2RJ",
    "wof:placetype":"postalcode"
},
  "geometry": {"coordinates":[-0.075369,51.502],"type":"Point"}
}