{
  "type": "Feature",
  "properties": {
    "iso:country":"GB",
    "wof:name":"LD3 8DS",
    "wof:placetype":"postalcode"
},
  "geometry": {"coordinates":[-3.40135242152504,51.94415464247153],"type":"Point"}
}