{
  "type": "Feature",
  "properties": {
    "iso:country":"GB",
    "wof:name":"M40 0HS",
    "wof:placetype":"postalcode"
},
  "geometry": {"coordinates":[-2.17450912788827,53.52390771306472],"type":"Point"}
}