{
  "type": "Feature",
  "properties": {
    "iso:country":"GB",
    "wof:name":"LS10 3BL",
    "wof:placetype":"postalcode"
},
  "geometry": {"coordinates":[-1.53348089935042,53.76971963077474],"type":"Point"}
}