{
  "type": "Feature",
  "properties": {
    "date:inception_lower": "1980-01-01",
    "date:inception_upper": "1980-01-01",
    "iso:country": "GB",
    "wof:name": "LS10 3BL",
    "wof:placetype": "postalcode"
  },
  "geometry": {"coordinates":[-1.533481,53.76972],"type":"Point"}
}
