{
  "type": "Feature",
  "properties": {
    "iso:country": "GB",
    "wof:name": "SK7 1SE",
    "wof:placetype": "postalcode"
  },
  "geometry": {"coordinates":[-2.157424,53.342237],"type":"Point"}
}
