{
  "type": "Feature",
  "properties": {
    "date:inception_lower": "1995-12-01",
    "date:inception_upper": "1995-12-01",
    "iso:country": "GB",
    "wof:name": "PE15 8SS",
    "wof:placetype": "postalcode"
  },
  "geometry": {"coordinates":[0.09009,52.56483],"type":"Point"}
}
