{
  "type": "Feature",
  "properties": {
    "iso:country":"GB",
    "wof:name":"BL7 9DE",
    "wof:placetype":"postalcode"
},
  "geometry": {"coordinates":[-2.4243918124055,53.61500771928802],"type":"Point"}
}