{
  "type": "Feature",
  "properties": {
    "date:inception_lower":"1980-01-01",
    "date:inception_upper":"1980-01-31",
    "iso:country":"GB",
    "wof:name":"SA8 4PN",
    "wof:placetype":"postalcode"
},
  "geometry": {"coordinates":[-3.838072,51.730113],"type":"Point"}
}