{
  "type": "Feature",
  "properties": {
    "iso:country":"GB",
    "wof:name":"OL4 5PE",
    "wof:placetype":"postalcode"
},
  "geometry": {"coordinates":[-2.06869582832803,53.53212305953259],"type":"Point"}
}