{
  "type": "Feature",
  "properties": {
    "iso:country": "GB",
    "wof:name": "IV2 5BN",
    "wof:placetype": "postalcode"
  },
  "geometry": {"coordinates":[-4.153773,57.469793],"type":"Point"}
}
