{
  "type": "Feature",
  "properties": {
    "iso:country":"GB",
    "wof:name":"IV2 5BN",
    "wof:placetype":"postalcode"
},
  "geometry": {"coordinates":[-4.15375792413847,57.46980927720136],"type":"Point"}
}