{
  "type": "Feature",
  "properties": {
    "iso:country":"GB",
    "wof:name":"DY3 2ED",
    "wof:placetype":"postalcode"
},
  "geometry": {"coordinates":[-2.1229202136088,52.52324756776365],"type":"Point"}
}