{
  "type": "Feature",
  "properties": {
    "date:inception_lower":"2004-01-01",
    "date:inception_upper":"2004-01-31",
    "iso:country":"GB",
    "wof:name":"DY3 2ED",
    "wof:placetype":"postalcode"
},
  "geometry": {"coordinates":[-2.122885,52.523263],"type":"Point"}
}