{
  "type": "Feature",
  "properties": {
    "iso:country":"GB",
    "wof:name":"SS17 0QE",
    "wof:placetype":"postalcode"
},
  "geometry": {"coordinates":[0.40725512495604,51.49198800123494],"type":"Point"}
}