{
  "type": "Feature",
  "properties": {
    "iso:country": "GB",
    "wof:name": "EX2 7AR",
    "wof:placetype": "postalcode"
  },
  "geometry": {"coordinates":[-3.494167,50.698751],"type":"Point"}
}
