{
  "type": "Feature",
  "properties": {
    "iso:country":"GB",
    "wof:name":"SL6 4JF",
    "wof:placetype":"postalcode"
},
  "geometry": {"coordinates":[-0.73786647010215,51.51760894334878],"type":"Point"}
}