{
  "type": "Feature",
  "properties": {
    "iso:country":"GB",
    "wof:name":"BN2 8QG",
    "wof:placetype":"postalcode"
},
  "geometry": {"coordinates":[-0.03377601006126,50.81027884739242],"type":"Point"}
}