{
  "type": "Feature",
  "properties": {
    "iso:country":"GB",
    "wof:name":"WS9 9PL",
    "wof:placetype":"postalcode"
},
  "geometry": {"coordinates":[-1.93310424097152,52.62906704500588],"type":"Point"}
}