{
  "type": "Feature",
  "properties": {
    "iso:country": "GB",
    "wof:name": "GU19 5PJ",
    "wof:placetype": "postalcode"
  },
  "geometry": {"coordinates":[-0.694869,51.366728],"type":"Point"}
}
