{
  "type": "Feature",
  "properties": {
    "iso:country":"GB",
    "wof:name":"M22 4WX",
    "wof:placetype":"postalcode"
},
  "geometry": {"coordinates":[-2.24818813433227,53.39154758552444],"type":"Point"}
}