{
  "type": "Feature",
  "properties": {
    "date:inception_lower": "1991-01-01",
    "date:inception_upper": "1991-01-01",
    "iso:country": "GB",
    "wof:name": "M22 4WX",
    "wof:placetype": "postalcode"
  },
  "geometry": {"coordinates":[-2.248188,53.391548],"type":"Point"}
}
