{
  "type": "Feature",
  "properties": {
    "iso:country":"GB",
    "wof:name":"NW9 9AU",
    "wof:placetype":"postalcode"
},
  "geometry": {"coordinates":[-0.27025816031003,51.5883053439338],"type":"Point"}
}