{
  "type": "Feature",
  "properties": {
    "date:inception_lower": "2018-01-01",
    "date:inception_upper": "2018-01-01",
    "iso:country": "GB",
    "wof:name": "N1 7FW",
    "wof:placetype": "postalcode"
  },
  "geometry": {"coordinates":[-0.095333,51.535718],"type":"Point"}
}
