{
  "type": "Feature",
  "properties": {
    "iso:country":"GB",
    "wof:name":"BA14 8RB",
    "wof:placetype":"postalcode"
},
  "geometry": {"coordinates":[-2.20356854196076,51.32872344055123],"type":"Point"}
}