{
  "type": "Feature",
  "properties": {
    "date:inception_lower": "2004-05-01",
    "date:inception_upper": "2004-05-01",
    "iso:country": "GB",
    "wof:name": "BA14 8RB",
    "wof:placetype": "postalcode"
  },
  "geometry": {"coordinates":[-2.203569,51.328723],"type":"Point"}
}
