{
  "type": "Feature",
  "properties": {
    "iso:country":"GB",
    "wof:name":"TN8 5HD",
    "wof:placetype":"postalcode"
},
  "geometry": {"coordinates":[0.05687233773589,51.19538828988847],"type":"Point"}
}