{
  "type": "Feature",
  "properties": {
    "date:inception_lower": "2002-07-01",
    "date:inception_upper": "2002-07-01",
    "iso:country": "GB",
    "wof:name": "LE12 5DZ",
    "wof:placetype": "postalcode"
  },
  "geometry": {"coordinates":[-1.298946,52.808652],"type":"Point"}
}
