{
  "type": "Feature",
  "properties": {
    "iso:country": "GB",
    "wof:name": "TS25 1TY",
    "wof:placetype": "postalcode"
  },
  "geometry": {"coordinates":[-1.215509,54.678602],"type":"Point"}
}
