{
  "type": "Feature",
  "properties": {
    "date:inception_lower": "1999-12-01",
    "date:inception_upper": "1999-12-01",
    "iso:country": "GB",
    "wof:name": "CB9 7WG",
    "wof:placetype": "postalcode"
  },
  "geometry": {"coordinates":[0.407774,52.087072],"type":"Point"}
}
