{
  "type": "Feature",
  "properties": {
    "iso:country":"GB",
    "wof:name":"CB9 7WG",
    "wof:placetype":"postalcode"
},
  "geometry": {"coordinates":[0.4077742853175,52.08707196986568],"type":"Point"}
}