{
  "type": "Feature",
  "properties": {
    "date:inception_lower": "1985-10-01",
    "date:inception_upper": "1985-10-01",
    "iso:country": "GB",
    "wof:name": "TN9 2NR",
    "wof:placetype": "postalcode"
  },
  "geometry": {"coordinates":[0.260785,51.185608],"type":"Point"}
}
