{
  "type": "Feature",
  "properties": {
    "date:inception_lower": "1986-07-01",
    "date:inception_upper": "1986-07-01",
    "iso:country": "GB",
    "wof:name": "IV20 1SW",
    "wof:placetype": "postalcode"
  },
  "geometry": {"coordinates":[-3.90584,57.759219],"type":"Point"}
}
