{
  "type": "Feature",
  "properties": {
    "iso:country": "GB",
    "wof:name": "ML11 8LJ",
    "wof:placetype": "postalcode"
  },
  "geometry": {"coordinates":[-3.625174,55.741543],"type":"Point"}
}
