{
  "type": "Feature",
  "properties": {
    "iso:country": "GB",
    "wof:name": "NN11 6DD",
    "wof:placetype": "postalcode"
  },
  "geometry": {"coordinates":[-1.209325,52.246261],"type":"Point"}
}
