{
  "type": "Feature",
  "properties": {
    "iso:country":"GB",
    "wof:name":"WS13 8DZ",
    "wof:placetype":"postalcode"
},
  "geometry": {"coordinates":[-1.85248987203223,52.69273118247974],"type":"Point"}
}