{
  "type": "Feature",
  "properties": {
    "iso:country":"GB",
    "wof:name":"CT20 3TD",
    "wof:placetype":"postalcode"
},
  "geometry": {"coordinates":[1.12877503545064,51.07368410310168],"type":"Point"}
}