{
  "type": "Feature",
  "properties": {
    "date:inception_lower": "1990-02-01",
    "date:inception_upper": "1990-02-01",
    "iso:country": "GB",
    "wof:name": "CT20 3TD",
    "wof:placetype": "postalcode"
  },
  "geometry": {"coordinates":[1.128775,51.073684],"type":"Point"}
}
