{
  "type": "Feature",
  "properties": {
    "iso:country":"GB",
    "wof:name":"NW10 5UJ",
    "wof:placetype":"postalcode"
},
  "geometry": {"coordinates":[-0.23584181109609,51.53579041412887],"type":"Point"}
}