{
  "type": "Feature",
  "properties": {
    "iso:country":"GB",
    "wof:name":"M15 4QX",
    "wof:placetype":"postalcode"
},
  "geometry": {"coordinates":[-2.25003719993748,53.47344723145311],"type":"Point"}
}