{
  "type": "Feature",
  "properties": {
    "date:inception_lower": "1980-01-01",
    "date:inception_upper": "1980-01-01",
    "iso:country": "GB",
    "wof:name": "SK7 2NU",
    "wof:placetype": "postalcode"
  },
  "geometry": {"coordinates":[-2.156321,53.36898],"type":"Point"}
}
