{
  "type": "Feature",
  "properties": {
    "iso:country": "GB",
    "wof:name": "EH3 9GZ",
    "wof:placetype": "postalcode"
  },
  "geometry": {"coordinates":[-3.196639,55.943113],"type":"Point"}
}
