{
  "type": "Feature",
  "properties": {
    "iso:country":"GB",
    "wof:name":"ST17 4EN",
    "wof:placetype":"postalcode"
},
  "geometry": {"coordinates":[-2.10938674311548,52.78774666426196],"type":"Point"}
}