{
  "type": "Feature",
  "properties": {
    "iso:country":"GB",
    "wof:name":"MK15 9EN",
    "wof:placetype":"postalcode"
},
  "geometry": {"coordinates":[-0.73272971124185,52.05542726247519],"type":"Point"}
}