{
  "type": "Feature",
  "properties": {
    "iso:country": "GB",
    "wof:name": "LA6 3AE",
    "wof:placetype": "postalcode"
  },
  "geometry": {"coordinates":[-2.464424,54.153136],"type":"Point"}
}
