{
  "type": "Feature",
  "properties": {
    "iso:country":"GB",
    "wof:name":"LA6 3AE",
    "wof:placetype":"postalcode"
},
  "geometry": {"coordinates":[-2.46442361137896,54.1531362649989],"type":"Point"}
}