{
  "type": "Feature",
  "properties": {
    "date:inception_lower":"1980-01-01",
    "date:inception_upper":"1980-01-31",
    "iso:country":"GB",
    "wof:name":"TQ1 3RQ",
    "wof:placetype":"postalcode"
},
  "geometry": {"coordinates":[-3.519024,50.474213],"type":"Point"}
}