{
  "type": "Feature",
  "properties": {
    "iso:country":"GB",
    "wof:name":"TQ1 3RQ",
    "wof:placetype":"postalcode"
},
  "geometry": {"coordinates":[-3.51902428240211,50.47421340534537],"type":"Point"}
}