{
  "type": "Feature",
  "properties": {
    "iso:country": "GB",
    "wof:name": "LL55 2UE",
    "wof:placetype": "postalcode"
  },
  "geometry": {"coordinates":[-4.2691,53.115955],"type":"Point"}
}
