{
  "type": "Feature",
  "properties": {
    "iso:country":"GB",
    "wof:name":"LL55 2UE",
    "wof:placetype":"postalcode"
},
  "geometry": {"coordinates":[-4.26910027638926,53.11595493351927],"type":"Point"}
}