{
  "type": "Feature",
  "properties": {
    "iso:country": "GB",
    "wof:name": "TA4 1DU",
    "wof:placetype": "postalcode"
  },
  "geometry": {"coordinates":[-3.217265,51.027613],"type":"Point"}
}
