{
  "type": "Feature",
  "properties": {
    "iso:country":"GB",
    "wof:name":"TA4 1DU",
    "wof:placetype":"postalcode"
},
  "geometry": {"coordinates":[-3.21726485562176,51.02761303706039],"type":"Point"}
}