{
  "type": "Feature",
  "properties": {
    "iso:country":"GB",
    "wof:name":"BS11 8AP",
    "wof:placetype":"postalcode"
},
  "geometry": {"coordinates":[-2.68710833256316,51.51971150873623],"type":"Point"}
}