{
  "type": "Feature",
  "properties": {
    "date:inception_lower":"1981-06-01",
    "date:inception_upper":"1981-06-30",
    "iso:country":"GB",
    "wof:name":"BS11 8AP",
    "wof:placetype":"postalcode"
},
  "geometry": {"coordinates":[-2.687108,51.519712],"type":"Point"}
}