{
  "type": "Feature",
  "properties": {
    "iso:country":"GB",
    "wof:name":"SS6 9NY",
    "wof:placetype":"postalcode"
},
  "geometry": {"coordinates":[0.61194224035631,51.600438609203],"type":"Point"}
}