{
  "type": "Feature",
  "properties": {
    "date:inception_lower": "1980-01-01",
    "date:inception_upper": "1980-01-01",
    "iso:country": "GB",
    "wof:name": "SS6 9NY",
    "wof:placetype": "postalcode"
  },
  "geometry": {"coordinates":[0.611914,51.600457],"type":"Point"}
}
