{
  "type": "Feature",
  "properties": {
    "iso:country": "GB",
    "wof:name": "TN13 1RB",
    "wof:placetype": "postalcode"
  },
  "geometry": {"coordinates":[0.194088,51.261865],"type":"Point"}
}
