{
  "type": "Feature",
  "properties": {
    "date:inception_lower":"1990-02-01",
    "date:inception_upper":"1990-02-28",
    "iso:country":"GB",
    "wof:name":"TN13 1RB",
    "wof:placetype":"postalcode"
},
  "geometry": {"coordinates":[0.194088,51.261865],"type":"Point"}
}