{
  "type": "Feature",
  "properties": {
    "iso:country":"GB",
    "wof:name":"RH12 5AH",
    "wof:placetype":"postalcode"
},
  "geometry": {"coordinates":[-0.31966441389977,51.07486403410011],"type":"Point"}
}