{
  "type": "Feature",
  "properties": {
    "date:inception_lower": "1991-01-01",
    "date:inception_upper": "1991-01-01",
    "iso:country": "GB",
    "wof:name": "RH12 5AH",
    "wof:placetype": "postalcode"
  },
  "geometry": {"coordinates":[-0.319652,51.07486],"type":"Point"}
}
