{
  "type": "Feature",
  "properties": {
    "date:inception_lower": "2018-08-01",
    "date:inception_upper": "2018-08-01",
    "iso:country": "GB",
    "wof:name": "M44 0AN",
    "wof:placetype": "postalcode"
  },
  "geometry": {"coordinates":[-2.428273,53.438405],"type":"Point"}
}
