{
  "type": "Feature",
  "properties": {
    "iso:country":"GB",
    "wof:name":"DY9 0UR",
    "wof:placetype":"postalcode"
},
  "geometry": {"coordinates":[-2.12791959445584,52.44322263702341],"type":"Point"}
}