{
  "type": "Feature",
  "properties": {
    "date:inception_lower": "1980-01-01",
    "date:inception_upper": "1980-01-01",
    "iso:country": "GB",
    "wof:name": "DY9 0UR",
    "wof:placetype": "postalcode"
  },
  "geometry": {"coordinates":[-2.127869,52.443228],"type":"Point"}
}
