{
  "type": "Feature",
  "properties": {
    "iso:country": "GB",
    "wof:name": "PL1 4RW",
    "wof:placetype": "postalcode"
  },
  "geometry": {"coordinates":[-4.179814,50.371818],"type":"Point"}
}
