{
  "type": "Feature",
  "properties": {
    "iso:country":"GB",
    "wof:name":"PL1 4RW",
    "wof:placetype":"postalcode"
},
  "geometry": {"coordinates":[-4.17902480445453,50.37152234129162],"type":"Point"}
}