{
  "type": "Feature",
  "properties": {
    "date:inception_lower": "2013-10-01",
    "date:inception_upper": "2013-10-01",
    "iso:country": "GB",
    "wof:name": "PL1 4RW",
    "wof:placetype": "postalcode"
  },
  "geometry": {"coordinates":[-4.180352,50.371592],"type":"Point"}
}
