{
  "type": "Feature",
  "properties": {
    "iso:country": "GB",
    "wof:name": "ME17 3GS",
    "wof:placetype": "postalcode"
  },
  "geometry": {"coordinates":[0.595733,51.199447],"type":"Point"}
}
