{
  "type": "Feature",
  "properties": {
    "iso:country": "GB",
    "wof:name": "CM9 8TN",
    "wof:placetype": "postalcode"
  },
  "geometry": {"coordinates":[0.807123,51.771406],"type":"Point"}
}
