{
  "type": "Feature",
  "properties": {
    "date:inception_lower":"1980-01-01",
    "date:inception_upper":"1980-01-31",
    "iso:country":"GB",
    "wof:name":"CM9 8TN",
    "wof:placetype":"postalcode"
},
  "geometry": {"coordinates":[0.807123,51.771406],"type":"Point"}
}