{
  "type": "Feature",
  "properties": {
    "iso:country":"GB",
    "wof:name":"CM9 8TN",
    "wof:placetype":"postalcode"
},
  "geometry": {"coordinates":[0.80678311997823,51.77174721194746],"type":"Point"}
}