{
  "type": "Feature",
  "properties": {
    "iso:country":"GB",
    "wof:name":"CF14 0YW",
    "wof:placetype":"postalcode"
},
  "geometry": {"coordinates":[-3.18084534276256,51.52740579756538],"type":"Point"}
}