{
  "type": "Feature",
  "properties": {
    "iso:country":"GB",
    "wof:name":"EH12 9DN",
    "wof:placetype":"postalcode"
},
  "geometry": {"coordinates":[-3.3639062493405,55.94850503182108],"type":"Point"}
}