{
  "type": "Feature",
  "properties": {
    "iso:country":"GB",
    "wof:name":"HP19 9RB",
    "wof:placetype":"postalcode"
},
  "geometry": {"coordinates":[-0.82090480713103,51.83310797491733],"type":"Point"}
}