{
  "type": "Feature",
  "properties": {
    "iso:country": "GB",
    "wof:name": "HP19 9RB",
    "wof:placetype": "postalcode"
  },
  "geometry": {"coordinates":[-0.821347,51.833093],"type":"Point"}
}
