{
  "type": "Feature",
  "properties": {
    "date:inception_lower": "2007-08-01",
    "date:inception_upper": "2007-08-01",
    "iso:country": "GB",
    "wof:name": "HP19 9RB",
    "wof:placetype": "postalcode"
  },
  "geometry": {"coordinates":[-0.821318,51.833102],"type":"Point"}
}
