{
  "type": "Feature",
  "properties": {
    "iso:country":"GB",
    "wof:name":"OX3 9TN",
    "wof:placetype":"postalcode"
},
  "geometry": {"coordinates":[-1.22536409072637,51.80235378042646],"type":"Point"}
}