{
  "type": "Feature",
  "properties": {
    "iso:country":"GB",
    "wof:name":"HP4 3AF",
    "wof:placetype":"postalcode"
},
  "geometry": {"coordinates":[-0.5630923150397,51.75880237089564],"type":"Point"}
}