{
  "type": "Feature",
  "properties": {
    "iso:country": "GB",
    "wof:name": "PL19 8RG",
    "wof:placetype": "postalcode"
  },
  "geometry": {"coordinates":[-4.154685,50.547679],"type":"Point"}
}
