{
  "type": "Feature",
  "properties": {
    "date:inception_lower":"2001-06-01",
    "date:inception_upper":"2001-06-30",
    "iso:country":"GB",
    "wof:name":"PL19 8RG",
    "wof:placetype":"postalcode"
},
  "geometry": {"coordinates":[-4.154685,50.547679],"type":"Point"}
}