{
  "type": "Feature",
  "properties": {
    "iso:country":"GB",
    "wof:name":"PL19 8RG",
    "wof:placetype":"postalcode"
},
  "geometry": {"coordinates":[-4.15468551836928,50.5476792017878],"type":"Point"}
}