{
  "type": "Feature",
  "properties": {
    "iso:country":"GB",
    "wof:name":"CB22 4NE",
    "wof:placetype":"postalcode"
},
  "geometry": {"coordinates":[0.15550495407561,52.11312367303515],"type":"Point"}
}