{
  "type": "Feature",
  "properties": {
    "date:inception_lower": "1980-01-01",
    "date:inception_upper": "1980-01-01",
    "iso:country": "GB",
    "wof:name": "NG6 7DQ",
    "wof:placetype": "postalcode"
  },
  "geometry": {"coordinates":[-1.211218,53.001457],"type":"Point"}
}
