{
  "type": "Feature",
  "properties": {
    "iso:country": "GB",
    "wof:name": "SK13 8NJ",
    "wof:placetype": "postalcode"
  },
  "geometry": {"coordinates":[-1.945909,53.435209],"type":"Point"}
}
