{
  "type": "Feature",
  "properties": {
    "iso:country":"GB",
    "wof:name":"SK13 8NJ",
    "wof:placetype":"postalcode"
},
  "geometry": {"coordinates":[-1.94590873397294,53.43520857297943],"type":"Point"}
}