{
  "type": "Feature",
  "properties": {
    "iso:country": "GB",
    "wof:name": "TS17 5AX",
    "wof:placetype": "postalcode"
  },
  "geometry": {"coordinates":[-1.313004,54.52833],"type":"Point"}
}
