{
  "type": "Feature",
  "properties": {
    "iso:country":"GB",
    "wof:name":"TS17 5AX",
    "wof:placetype":"postalcode"
},
  "geometry": {"coordinates":[-1.31300364515103,54.52832989150762],"type":"Point"}
}