{
  "type": "Feature",
  "properties": {
    "date:inception_lower": "2002-06-01",
    "date:inception_upper": "2002-06-01",
    "iso:country": "GB",
    "wof:name": "TS17 5AX",
    "wof:placetype": "postalcode"
  },
  "geometry": {"coordinates":[-1.313004,54.52833],"type":"Point"}
}
