{
  "type": "Feature",
  "properties": {
    "iso:country": "GB",
    "wof:name": "DA3 7HX",
    "wof:placetype": "postalcode"
  },
  "geometry": {"coordinates":[0.331529,51.395528],"type":"Point"}
}
