{
  "type": "Feature",
  "properties": {
    "iso:country":"GB",
    "wof:name":"DA3 7HX",
    "wof:placetype":"postalcode"
},
  "geometry": {"coordinates":[0.33152850424883,51.39552846339886],"type":"Point"}
}