{
  "type": "Feature",
  "properties": {
    "date:inception_lower":"2004-08-01",
    "date:inception_upper":"2004-08-31",
    "iso:country":"GB",
    "wof:name":"AL4 0PL",
    "wof:placetype":"postalcode"
},
  "geometry": {"coordinates":[-0.253505,51.737408],"type":"Point"}
}