{
  "type": "Feature",
  "properties": {
    "iso:country":"GB",
    "wof:name":"ML1 2HR",
    "wof:placetype":"postalcode"
},
  "geometry": {"coordinates":[-3.96653346285648,55.77860413639726],"type":"Point"}
}