{
  "type": "Feature",
  "properties": {
    "iso:country":"GB",
    "wof:name":"LL14 2AX",
    "wof:placetype":"postalcode"
},
  "geometry": {"coordinates":[-3.04342695232471,53.00836404193177],"type":"Point"}
}