{
  "type": "Feature",
  "properties": {
    "iso:country":"GB",
    "wof:name":"BD21 3LG",
    "wof:placetype":"postalcode"
},
  "geometry": {"coordinates":[-1.90570589635183,53.876476042479],"type":"Point"}
}