{
  "type": "Feature",
  "properties": {
    "iso:country":"GB",
    "wof:name":"FK2 8QQ",
    "wof:placetype":"postalcode"
},
  "geometry": {"coordinates":[-3.7811398205686,56.03586366525614],"type":"Point"}
}