{
  "type": "Feature",
  "properties": {
    "iso:country":"GB",
    "wof:name":"HP3 9PN",
    "wof:placetype":"postalcode"
},
  "geometry": {"coordinates":[-0.46396679462591,51.73924149035395],"type":"Point"}
}