{
  "type": "Feature",
  "properties": {
    "iso:country":"GB",
    "wof:name":"LL14 3DR",
    "wof:placetype":"postalcode"
},
  "geometry": {"coordinates":[-3.07398486150695,52.9773384648542],"type":"Point"}
}