{
  "type": "Feature",
  "properties": {
    "date:inception_lower": "1980-01-01",
    "date:inception_upper": "1980-01-01",
    "iso:country": "GB",
    "wof:name": "LL14 3DR",
    "wof:placetype": "postalcode"
  },
  "geometry": {"coordinates":[-3.073985,52.977338],"type":"Point"}
}
