{
  "type": "Feature",
  "properties": {
    "iso:country":"GB",
    "wof:name":"IP31 2RU",
    "wof:placetype":"postalcode"
},
  "geometry": {"coordinates":[0.76780917756232,52.27433951247053],"type":"Point"}
}