{
  "type": "Feature",
  "properties": {
    "iso:country":"GB",
    "wof:name":"SL1 2JG",
    "wof:placetype":"postalcode"
},
  "geometry": {"coordinates":[-0.60665376774248,51.50676324544883],"type":"Point"}
}