{
  "type": "Feature",
  "properties": {
    "iso:country": "GB",
    "wof:name": "SL1 2JG",
    "wof:placetype": "postalcode"
  },
  "geometry": {"coordinates":[-0.606654,51.506763],"type":"Point"}
}
