{
  "type": "Feature",
  "properties": {
    "date:inception_lower":"1980-01-01",
    "date:inception_upper":"1980-01-31",
    "iso:country":"GB",
    "wof:name":"IP2 9LH",
    "wof:placetype":"postalcode"
},
  "geometry": {"coordinates":[1.116635,52.038225],"type":"Point"}
}