{
  "type": "Feature",
  "properties": {
    "iso:country":"GB",
    "wof:name":"IP2 9LH",
    "wof:placetype":"postalcode"
},
  "geometry": {"coordinates":[1.11663544127472,52.03822544211903],"type":"Point"}
}