{
  "type": "Feature",
  "properties": {
    "date:inception_lower":"2001-12-01",
    "date:inception_upper":"2001-12-31",
    "iso:country":"GB",
    "wof:name":"IP14 5TY",
    "wof:placetype":"postalcode"
},
  "geometry": {"coordinates":[1.080429,52.249558],"type":"Point"}
}