{
  "type": "Feature",
  "properties": {
    "date:inception_lower": "2001-12-01",
    "date:inception_upper": "2001-12-01",
    "iso:country": "GB",
    "wof:name": "IP14 5TY",
    "wof:placetype": "postalcode"
  },
  "geometry": {"coordinates":[1.080445,52.249585],"type":"Point"}
}
