{
  "type": "Feature",
  "properties": {
    "iso:country":"GB",
    "wof:name":"IP14 5TY",
    "wof:placetype":"postalcode"
},
  "geometry": {"coordinates":[1.08042913200751,52.24955838880302],"type":"Point"}
}