{
  "type": "Feature",
  "properties": {
    "date:inception_lower": "1980-01-01",
    "date:inception_upper": "1980-01-01",
    "iso:country": "GB",
    "wof:name": "WA14 5DX",
    "wof:placetype": "postalcode"
  },
  "geometry": {"coordinates":[-2.35029,53.399164],"type":"Point"}
}
