{
  "type": "Feature",
  "properties": {
    "iso:country": "GB",
    "wof:name": "TF2 6TL",
    "wof:placetype": "postalcode"
  },
  "geometry": {"coordinates":[-2.45772,52.698545],"type":"Point"}
}
