{
  "type": "Feature",
  "properties": {
    "iso:country": "GB",
    "wof:name": "S80 3EE",
    "wof:placetype": "postalcode"
  },
  "geometry": {"coordinates":[-1.20082,53.293684],"type":"Point"}
}
