{
  "type": "Feature",
  "properties": {
    "iso:country":"GB",
    "wof:name":"S80 3EE",
    "wof:placetype":"postalcode"
},
  "geometry": {"coordinates":[-1.20082145188396,53.29366217736903],"type":"Point"}
}