{
  "type": "Feature",
  "properties": {
    "iso:country": "GB",
    "wof:name": "B79 8PB",
    "wof:placetype": "postalcode"
  },
  "geometry": {"coordinates":[-1.695913,52.642972],"type":"Point"}
}
