{
  "type": "Feature",
  "properties": {
    "iso:country":"GB",
    "wof:name":"DE72 3AD",
    "wof:placetype":"postalcode"
},
  "geometry": {"coordinates":[-1.30972253318617,52.90000376720273],"type":"Point"}
}