{
  "type": "Feature",
  "properties": {
    "date:inception_lower":"1992-08-01",
    "date:inception_upper":"1992-08-31",
    "iso:country":"GB",
    "wof:name":"DE72 3AD",
    "wof:placetype":"postalcode"
},
  "geometry": {"coordinates":[-1.309722,52.900004],"type":"Point"}
}