{
  "type": "Feature",
  "properties": {
    "iso:country": "GB",
    "wof:name": "DE72 3AD",
    "wof:placetype": "postalcode"
  },
  "geometry": {"coordinates":[-1.309722,52.900004],"type":"Point"}
}
