{
  "type": "Feature",
  "properties": {
    "date:inception_lower": "1980-01-01",
    "date:inception_upper": "1980-01-01",
    "iso:country": "GB",
    "wof:name": "IP31 3EG",
    "wof:placetype": "postalcode"
  },
  "geometry": {"coordinates":[0.895586,52.281706],"type":"Point"}
}
