{
  "type": "Feature",
  "properties": {
    "iso:country":"GB",
    "wof:name":"IP31 3EG",
    "wof:placetype":"postalcode"
},
  "geometry": {"coordinates":[0.89548403062093,52.28172582662589],"type":"Point"}
}