{
  "type": "Feature",
  "properties": {
    "iso:country": "GB",
    "wof:name": "PE8 5QJ",
    "wof:placetype": "postalcode"
  },
  "geometry": {"coordinates":[-0.393758,52.454747],"type":"Point"}
}
