{
  "type": "Feature",
  "properties": {
    "iso:country":"GB",
    "wof:name":"PE8 5QJ",
    "wof:placetype":"postalcode"
},
  "geometry": {"coordinates":[-0.39377521248227,52.45472959164485],"type":"Point"}
}