{
  "type": "Feature",
  "properties": {
    "iso:country": "GB",
    "wof:name": "S61 2ET",
    "wof:placetype": "postalcode"
  },
  "geometry": {"coordinates":[-1.40635,53.430565],"type":"Point"}
}
