{
  "type": "Feature",
  "properties": {
    "iso:country":"GB",
    "wof:name":"S61 2ET",
    "wof:placetype":"postalcode"
},
  "geometry": {"coordinates":[-1.40634973379573,53.43056492808076],"type":"Point"}
}