{
  "type": "Feature",
  "properties": {
    "iso:country":"GB",
    "wof:name":"PE31 6PL",
    "wof:placetype":"postalcode"
},
  "geometry": {"coordinates":[0.50930552351742,52.84641275644346],"type":"Point"}
}