{
  "type": "Feature",
  "properties": {
    "iso:country":"GB",
    "wof:name":"WF4 1RF",
    "wof:placetype":"postalcode"
},
  "geometry": {"coordinates":[-1.36140015473183,53.65978263039767],"type":"Point"}
}