{
  "type": "Feature",
  "properties": {
    "iso:country":"GB",
    "wof:name":"CH44 6PB",
    "wof:placetype":"postalcode"
},
  "geometry": {"coordinates":[-3.01843466103337,53.41118211983094],"type":"Point"}
}