{
  "type": "Feature",
  "properties": {
    "iso:country": "GB",
    "wof:name": "CH44 6PB",
    "wof:placetype": "postalcode"
  },
  "geometry": {"coordinates":[-3.018435,53.411182],"type":"Point"}
}
