{
  "type": "Feature",
  "properties": {
    "iso:country":"GB",
    "wof:name":"CV6 2JW",
    "wof:placetype":"postalcode"
},
  "geometry": {"coordinates":[-1.52678799948897,52.43266415888738],"type":"Point"}
}