{
  "type": "Feature",
  "properties": {
    "iso:country":"GB",
    "wof:name":"E2 6HW",
    "wof:placetype":"postalcode"
},
  "geometry": {"coordinates":[-0.06286651261175,51.5239790896761],"type":"Point"}
}