{
  "type": "Feature",
  "properties": {
    "iso:country":"GB",
    "wof:name":"IP21 5HN",
    "wof:placetype":"postalcode"
},
  "geometry": {"coordinates":[1.27003487999058,52.32307916878968],"type":"Point"}
}