{
  "type": "Feature",
  "properties": {
    "iso:country":"GB",
    "wof:name":"WF2 9EF",
    "wof:placetype":"postalcode"
},
  "geometry": {"coordinates":[-1.51904618490714,53.68124610591491],"type":"Point"}
}