{
  "type": "Feature",
  "properties": {
    "date:inception_lower": "2005-02-01",
    "date:inception_upper": "2005-02-01",
    "iso:country": "GB",
    "wof:name": "PE30 9SL",
    "wof:placetype": "postalcode"
  },
  "geometry": {"coordinates":[0.397196,52.756683],"type":"Point"}
}
