{
  "type": "Feature",
  "properties": {
    "iso:country": "GB",
    "wof:name": "DH6 1PD",
    "wof:placetype": "postalcode"
  },
  "geometry": {"coordinates":[-1.478389,54.7725],"type":"Point"}
}
