{
  "type": "Feature",
  "properties": {
    "iso:country":"GB",
    "wof:name":"SE26 4BY",
    "wof:placetype":"postalcode"
},
  "geometry": {"coordinates":[-0.05782708120648,51.4360375747226],"type":"Point"}
}