{
  "type": "Feature",
  "properties": {
    "iso:country":"GB",
    "wof:name":"PL9 0JU",
    "wof:placetype":"postalcode"
},
  "geometry": {"coordinates":[-4.07388985327671,50.32224969310404],"type":"Point"}
}