{
  "type": "Feature",
  "properties": {
    "date:inception_lower": "1980-01-01",
    "date:inception_upper": "1980-01-01",
    "iso:country": "GB",
    "wof:name": "PL9 0JU",
    "wof:placetype": "postalcode"
  },
  "geometry": {"coordinates":[-4.07389,50.32225],"type":"Point"}
}
