{
  "type": "Feature",
  "properties": {
    "iso:country":"GB",
    "wof:name":"SP4 7HB",
    "wof:placetype":"postalcode"
},
  "geometry": {"coordinates":[-1.78311107801465,51.17079435959764],"type":"Point"}
}