{
  "type": "Feature",
  "properties": {
    "iso:country": "GB",
    "wof:name": "RM4 1BY",
    "wof:placetype": "postalcode"
  },
  "geometry": {"coordinates":[0.122886,51.651977],"type":"Point"}
}
