{
  "type": "Feature",
  "properties": {
    "iso:country":"GB",
    "wof:name":"RM4 1BY",
    "wof:placetype":"postalcode"
},
  "geometry": {"coordinates":[0.12288573425124,51.65197705952268],"type":"Point"}
}