{
  "type": "Feature",
  "properties": {
    "iso:country": "GB",
    "wof:name": "S42 6NW",
    "wof:placetype": "postalcode"
  },
  "geometry": {"coordinates":[-1.415488,53.197253],"type":"Point"}
}
