{
  "type": "Feature",
  "properties": {
    "date:inception_lower":"1980-01-01",
    "date:inception_upper":"1980-01-31",
    "iso:country":"GB",
    "wof:name":"DA16 2PB",
    "wof:placetype":"postalcode"
},
  "geometry": {"coordinates":[0.088354,51.457463],"type":"Point"}
}