{
  "type": "Feature",
  "properties": {
    "iso:country":"GB",
    "wof:name":"DA16 2PB",
    "wof:placetype":"postalcode"
},
  "geometry": {"coordinates":[0.08835403748249,51.45746312177457],"type":"Point"}
}