{
  "type": "Feature",
  "properties": {
    "iso:country":"GB",
    "wof:name":"SL6 7HB",
    "wof:placetype":"postalcode"
},
  "geometry": {"coordinates":[-0.7239364941443,51.53592767182603],"type":"Point"}
}