{
  "type": "Feature",
  "properties": {
    "iso:country": "GB",
    "wof:name": "ME17 4PL",
    "wof:placetype": "postalcode"
  },
  "geometry": {"coordinates":[0.497979,51.23157],"type":"Point"}
}
