{
  "type": "Feature",
  "properties": {
    "iso:country":"GB",
    "wof:name":"TS19 9HA",
    "wof:placetype":"postalcode"
},
  "geometry": {"coordinates":[-1.3372790222463,54.58744702443601],"type":"Point"}
}