{
  "type": "Feature",
  "properties": {
    "date:inception_lower": "1983-03-01",
    "date:inception_upper": "1983-03-01",
    "iso:country": "GB",
    "wof:name": "TN6 2XJ",
    "wof:placetype": "postalcode"
  },
  "geometry": {"coordinates":[0.177595,51.050595],"type":"Point"}
}
