{
  "type": "Feature",
  "properties": {
    "iso:country": "GB",
    "wof:name": "WF15 7BD",
    "wof:placetype": "postalcode"
  },
  "geometry": {"coordinates":[-1.681842,53.703837],"type":"Point"}
}
