{
  "type": "Feature",
  "properties": {
    "date:inception_lower": "1980-01-01",
    "date:inception_upper": "1980-01-01",
    "iso:country": "GB",
    "wof:name": "WF15 7BD",
    "wof:placetype": "postalcode"
  },
  "geometry": {"coordinates":[-1.681842,53.703837],"type":"Point"}
}
