{
  "type": "Feature",
  "properties": {
    "date:inception_lower": "1990-07-01",
    "date:inception_upper": "1990-07-01",
    "iso:country": "GB",
    "wof:name": "CT13 9QX",
    "wof:placetype": "postalcode"
  },
  "geometry": {"coordinates":[1.349747,51.278494],"type":"Point"}
}
