{
  "type": "Feature",
  "properties": {
    "date:inception_lower": "1980-01-01",
    "date:inception_upper": "1980-01-01",
    "iso:country": "GB",
    "wof:name": "SS16 5NG",
    "wof:placetype": "postalcode"
  },
  "geometry": {"coordinates":[0.446925,51.553715],"type":"Point"}
}
