{
  "type": "Feature",
  "properties": {
    "iso:country":"GB",
    "wof:name":"SS16 5NG",
    "wof:placetype":"postalcode"
},
  "geometry": {"coordinates":[0.44692477613628,51.55371495403786],"type":"Point"}
}