{
  "type": "Feature",
  "properties": {
    "iso:country": "GB",
    "wof:name": "SS16 5NG",
    "wof:placetype": "postalcode"
  },
  "geometry": {"coordinates":[0.446925,51.553715],"type":"Point"}
}
