{
  "type": "Feature",
  "properties": {
    "date:inception_lower":"1980-01-01",
    "date:inception_upper":"1980-01-31",
    "iso:country":"GB",
    "wof:name":"DN17 2BS",
    "wof:placetype":"postalcode"
},
  "geometry": {"coordinates":[-0.68929,53.549601],"type":"Point"}
}