{
  "type": "Feature",
  "properties": {
    "date:inception_lower": "2017-07-01",
    "date:inception_upper": "2017-07-01",
    "iso:country": "GB",
    "wof:name": "LE67 4ET",
    "wof:placetype": "postalcode"
  },
  "geometry": {"coordinates":[-1.350389,52.713708],"type":"Point"}
}
