{
  "type": "Feature",
  "properties": {
    "iso:country":"GB",
    "wof:name":"KA20 3JG",
    "wof:placetype":"postalcode"
},
  "geometry": {"coordinates":[-4.76127572256627,55.63832046629096],"type":"Point"}
}