{
  "type": "Feature",
  "properties": {
    "iso:country":"GB",
    "wof:name":"PL10 1NL",
    "wof:placetype":"postalcode"
},
  "geometry": {"coordinates":[-4.20103931905729,50.33485988486493],"type":"Point"}
}