{
  "type": "Feature",
  "properties": {
    "iso:country":"GB",
    "wof:name":"WA10 2JZ",
    "wof:placetype":"postalcode"
},
  "geometry": {"coordinates":[-2.74101135900057,53.45483519206375],"type":"Point"}
}