{
  "type": "Feature",
  "properties": {
    "date:inception_lower":"2014-04-01",
    "date:inception_upper":"2014-04-30",
    "iso:country":"GB",
    "wof:name":"ML6 7HW",
    "wof:placetype":"postalcode"
},
  "geometry": {"coordinates":[-3.954774,55.873815],"type":"Point"}
}