{
  "type": "Feature",
  "properties": {
    "iso:country": "GB",
    "wof:name": "ML6 7HW",
    "wof:placetype": "postalcode"
  },
  "geometry": {"coordinates":[-3.954774,55.873815],"type":"Point"}
}
