{
  "type": "Feature",
  "properties": {
    "date:inception_lower":"1996-06-01",
    "date:inception_upper":"1996-06-30",
    "iso:country":"GB",
    "wof:name":"CF37 1DW",
    "wof:placetype":"postalcode"
},
  "geometry": {"coordinates":[-3.351888,51.600902],"type":"Point"}
}