{
  "type": "Feature",
  "properties": {
    "iso:country": "GB",
    "wof:name": "CF37 1DW",
    "wof:placetype": "postalcode"
  },
  "geometry": {"coordinates":[-3.351888,51.600902],"type":"Point"}
}
