{
  "type": "Feature",
  "properties": {
    "iso:country": "GB",
    "wof:name": "WV1 4AU",
    "wof:placetype": "postalcode"
  },
  "geometry": {"coordinates":[-2.136679,52.591906],"type":"Point"}
}
