{
  "type": "Feature",
  "properties": {
    "iso:country":"GB",
    "wof:name":"WV1 4AU",
    "wof:placetype":"postalcode"
},
  "geometry": {"coordinates":[-2.13667855910273,52.59190588236105],"type":"Point"}
}