{
  "type": "Feature",
  "properties": {
    "iso:country":"GB",
    "wof:name":"SA12 6SW",
    "wof:placetype":"postalcode"
},
  "geometry": {"coordinates":[-3.81491568330443,51.59442962196545],"type":"Point"}
}