{
  "type": "Feature",
  "properties": {
    "iso:country": "GB",
    "wof:name": "SA12 6SW",
    "wof:placetype": "postalcode"
  },
  "geometry": {"coordinates":[-3.814916,51.59443],"type":"Point"}
}
