{
  "type": "Feature",
  "properties": {
    "date:inception_lower": "1980-01-01",
    "date:inception_upper": "1980-01-01",
    "iso:country": "GB",
    "wof:name": "SA12 6SW",
    "wof:placetype": "postalcode"
  },
  "geometry": {"coordinates":[-3.814916,51.59443],"type":"Point"}
}
