{
  "type": "Feature",
  "properties": {
    "iso:country": "GB",
    "wof:name": "NG20 8BT",
    "wof:placetype": "postalcode"
  },
  "geometry": {"coordinates":[-1.214766,53.19413],"type":"Point"}
}
