{
  "type": "Feature",
  "properties": {
    "iso:country":"GB",
    "wof:name":"ME8 9ET",
    "wof:placetype":"postalcode"
},
  "geometry": {"coordinates":[0.59386116554571,51.3529952110577],"type":"Point"}
}