{
  "type": "Feature",
  "properties": {
    "iso:country": "GB",
    "wof:name": "LN9 5BT",
    "wof:placetype": "postalcode"
  },
  "geometry": {"coordinates":[-0.115455,53.211598],"type":"Point"}
}
