{
  "type": "Feature",
  "properties": {
    "date:inception_lower": "2008-01-01",
    "date:inception_upper": "2008-01-01",
    "iso:country": "GB",
    "wof:name": "LN9 5BT",
    "wof:placetype": "postalcode"
  },
  "geometry": {"coordinates":[-0.115455,53.211598],"type":"Point"}
}
