{
  "type": "Feature",
  "properties": {
    "iso:country":"GB",
    "wof:name":"NR12 9LW",
    "wof:placetype":"postalcode"
},
  "geometry": {"coordinates":[1.47664154267531,52.76670206498594],"type":"Point"}
}