{
  "type": "Feature",
  "properties": {
    "date:inception_lower": "1981-06-01",
    "date:inception_upper": "1981-06-01",
    "iso:country": "GB",
    "wof:name": "AL6 0XD",
    "wof:placetype": "postalcode"
  },
  "geometry": {"coordinates":[-0.201288,51.840459],"type":"Point"}
}
