{
  "type": "Feature",
  "properties": {
    "iso:country":"GB",
    "wof:name":"AL6 0XD",
    "wof:placetype":"postalcode"
},
  "geometry": {"coordinates":[-0.20129793387267,51.84045197406457],"type":"Point"}
}