{
  "type": "Feature",
  "properties": {
    "iso:country":"GB",
    "wof:name":"SA10 9NS",
    "wof:placetype":"postalcode"
},
  "geometry": {"coordinates":[-3.67528821377211,51.79063563947864],"type":"Point"}
}