{
  "type": "Feature",
  "properties": {
    "iso:country":"GB",
    "wof:name":"CH5 1ED",
    "wof:placetype":"postalcode"
},
  "geometry": {"coordinates":[-3.04234231449985,53.21477938367649],"type":"Point"}
}