{
  "type": "Feature",
  "properties": {
    "date:inception_lower":"1988-03-01",
    "date:inception_upper":"1988-03-31",
    "iso:country":"GB",
    "wof:name":"CH5 1ED",
    "wof:placetype":"postalcode"
},
  "geometry": {"coordinates":[-3.042341,53.214795],"type":"Point"}
}