{
  "type": "Feature",
  "properties": {
    "date:inception_lower": "1988-03-01",
    "date:inception_upper": "1988-03-01",
    "iso:country": "GB",
    "wof:name": "CH5 1ED",
    "wof:placetype": "postalcode"
  },
  "geometry": {"coordinates":[-3.042582,53.214847],"type":"Point"}
}
