{
  "type": "Feature",
  "properties": {
    "date:inception_lower": "2005-08-01",
    "date:inception_upper": "2005-08-01",
    "iso:country": "GB",
    "wof:name": "LS25 4DU",
    "wof:placetype": "postalcode"
  },
  "geometry": {"coordinates":[-1.333433,53.798013],"type":"Point"}
}
