{
  "type": "Feature",
  "properties": {
    "iso:country":"GB",
    "wof:name":"LS25 4DU",
    "wof:placetype":"postalcode"
},
  "geometry": {"coordinates":[-1.33343257708461,53.79801323732593],"type":"Point"}
}