{
  "type": "Feature",
  "properties": {
    "iso:country":"GB",
    "wof:name":"HA3 6DF",
    "wof:placetype":"postalcode"
},
  "geometry": {"coordinates":[-0.33805064758521,51.61036250443727],"type":"Point"}
}