{
  "type": "Feature",
  "properties": {
    "iso:country":"GB",
    "wof:name":"CF14 9AE",
    "wof:placetype":"postalcode"
},
  "geometry": {"coordinates":[-3.20387246707159,51.53799789316145],"type":"Point"}
}