{
  "type": "Feature",
  "properties": {
    "date:inception_lower": "1980-01-01",
    "date:inception_upper": "1980-01-01",
    "iso:country": "GB",
    "wof:name": "BN11 3LX",
    "wof:placetype": "postalcode"
  },
  "geometry": {"coordinates":[-0.379828,50.808917],"type":"Point"}
}
