{
  "type": "Feature",
  "properties": {
    "iso:country": "GB",
    "wof:name": "CM15 0RR",
    "wof:placetype": "postalcode"
  },
  "geometry": {"coordinates":[0.303978,51.663518],"type":"Point"}
}
