{
  "type": "Feature",
  "properties": {
    "iso:country": "GB",
    "wof:name": "TW2 5EF",
    "wof:placetype": "postalcode"
  },
  "geometry": {"coordinates":[-0.34813,51.442691],"type":"Point"}
}
