{
  "type": "Feature",
  "properties": {
    "iso:country":"GB",
    "wof:name":"TW2 5EF",
    "wof:placetype":"postalcode"
},
  "geometry": {"coordinates":[-0.34813024466143,51.44269115363861],"type":"Point"}
}