{
  "type": "Feature",
  "properties": {
    "date:inception_lower": "2018-01-01",
    "date:inception_upper": "2018-01-01",
    "iso:country": "GB",
    "wof:name": "DH5 9RT",
    "wof:placetype": "postalcode"
  },
  "geometry": {"coordinates":[-1.476855,54.827375],"type":"Point"}
}
