{
  "type": "Feature",
  "properties": {
    "iso:country":"GB",
    "wof:name":"DN34 5RX",
    "wof:placetype":"postalcode"
},
  "geometry": {"coordinates":[-0.12900317569299,53.55257568311823],"type":"Point"}
}