{
  "type": "Feature",
  "properties": {
    "iso:country": "GB",
    "wof:name": "DN34 5RX",
    "wof:placetype": "postalcode"
  },
  "geometry": {"coordinates":[-0.129003,53.552576],"type":"Point"}
}
