{
  "type": "Feature",
  "properties": {
    "iso:country":"GB",
    "wof:name":"PA34 4GH",
    "wof:placetype":"postalcode"
},
  "geometry": {"coordinates":[-5.61588784590363,56.29126966578308],"type":"Point"}
}