{
  "type": "Feature",
  "properties": {
    "date:inception_lower": "2013-08-01",
    "date:inception_upper": "2013-08-01",
    "iso:country": "GB",
    "wof:name": "PA34 4GH",
    "wof:placetype": "postalcode"
  },
  "geometry": {"coordinates":[-5.615888,56.29127],"type":"Point"}
}
