{
  "type": "Feature",
  "properties": {
    "iso:country": "GB",
    "wof:name": "HU15 2JU",
    "wof:placetype": "postalcode"
  },
  "geometry": {"coordinates":[-0.682534,53.767033],"type":"Point"}
}
