{
  "type": "Feature",
  "properties": {
    "iso:country":"GB",
    "wof:name":"RH16 2PP",
    "wof:placetype":"postalcode"
},
  "geometry": {"coordinates":[-0.08306809121074,51.01781252575157],"type":"Point"}
}