{
  "type": "Feature",
  "properties": {
    "iso:country": "GB",
    "wof:name": "CO15 5HA",
    "wof:placetype": "postalcode"
  },
  "geometry": {"coordinates":[1.180411,51.801728],"type":"Point"}
}
