{
  "type": "Feature",
  "properties": {
    "iso:country":"GB",
    "wof:name":"LS22 5EF",
    "wof:placetype":"postalcode"
},
  "geometry": {"coordinates":[-1.34786885071362,53.93897987038289],"type":"Point"}
}