{
  "type": "Feature",
  "properties": {
    "iso:country":"GB",
    "wof:name":"KA24 5DQ",
    "wof:placetype":"postalcode"
},
  "geometry": {"coordinates":[-4.72297333061908,55.70807666386677],"type":"Point"}
}