{
  "type": "Feature",
  "properties": {
    "iso:country": "GB",
    "wof:name": "NR26 8PP",
    "wof:placetype": "postalcode"
  },
  "geometry": {"coordinates":[1.216126,52.935],"type":"Point"}
}
