{
  "type": "Feature",
  "properties": {
    "date:inception_lower": "1980-01-01",
    "date:inception_upper": "1980-01-01",
    "iso:country": "GB",
    "wof:name": "NR26 8PP",
    "wof:placetype": "postalcode"
  },
  "geometry": {"coordinates":[1.216287,52.934953],"type":"Point"}
}
