{
  "type": "Feature",
  "properties": {
    "iso:country":"GB",
    "wof:name":"KA12 9DD",
    "wof:placetype":"postalcode"
},
  "geometry": {"coordinates":[-4.6727175024539,55.62699753086559],"type":"Point"}
}