{
  "type": "Feature",
  "properties": {
    "date:inception_lower":"1980-01-01",
    "date:inception_upper":"1980-01-31",
    "iso:country":"GB",
    "wof:name":"G34 0DX",
    "wof:placetype":"postalcode"
},
  "geometry": {"coordinates":[-4.096215,55.867482],"type":"Point"}
}