{
  "type": "Feature",
  "properties": {
    "iso:country":"GB",
    "wof:name":"BA2 6XQ",
    "wof:placetype":"postalcode"
},
  "geometry": {"coordinates":[-2.31893927901525,51.39153372356984],"type":"Point"}
}