{
  "type": "Feature",
  "properties": {
    "iso:country":"GB",
    "wof:name":"CV11 5XL",
    "wof:placetype":"postalcode"
},
  "geometry": {"coordinates":[-1.47673301433237,52.51852422992243],"type":"Point"}
}