{
  "type": "Feature",
  "properties": {
    "iso:country":"GB",
    "wof:name":"HD6 4BB",
    "wof:placetype":"postalcode"
},
  "geometry": {"coordinates":[-1.78170961033327,53.71013607468984],"type":"Point"}
}