{
  "type": "Feature",
  "properties": {
    "iso:country":"GB",
    "wof:name":"CH3 9JU",
    "wof:placetype":"postalcode"
},
  "geometry": {"coordinates":[-2.75290083418443,53.07728657591448],"type":"Point"}
}