{
  "type": "Feature",
  "properties": {
    "date:inception_lower": "1980-01-01",
    "date:inception_upper": "1980-01-01",
    "iso:country": "GB",
    "wof:name": "CH3 9JU",
    "wof:placetype": "postalcode"
  },
  "geometry": {"coordinates":[-2.752784,53.077429],"type":"Point"}
}
