{
  "type": "Feature",
  "properties": {
    "iso:country":"GB",
    "wof:name":"TS6 6JE",
    "wof:placetype":"postalcode"
},
  "geometry": {"coordinates":[-1.17772356811221,54.57669067068787],"type":"Point"}
}