{
  "type": "Feature",
  "properties": {
    "iso:country":"GB",
    "wof:name":"WS3 2UP",
    "wof:placetype":"postalcode"
},
  "geometry": {"coordinates":[-2.02047326014511,52.61870081860348],"type":"Point"}
}