{
  "type": "Feature",
  "properties": {
    "iso:country": "GB",
    "wof:name": "WS3 2UP",
    "wof:placetype": "postalcode"
  },
  "geometry": {"coordinates":[-2.020473,52.618701],"type":"Point"}
}
