{
  "type": "Feature",
  "properties": {
    "date:inception_lower": "1980-01-01",
    "date:inception_upper": "1980-01-01",
    "iso:country": "GB",
    "wof:name": "CV9 2EZ",
    "wof:placetype": "postalcode"
  },
  "geometry": {"coordinates":[-1.602172,52.586427],"type":"Point"}
}
