{
  "type": "Feature",
  "properties": {
    "iso:country":"GB",
    "wof:name":"CV9 2EZ",
    "wof:placetype":"postalcode"
},
  "geometry": {"coordinates":[-1.6021661111241,52.58643630374298],"type":"Point"}
}