{
  "type": "Feature",
  "properties": {
    "date:inception_lower": "1980-01-01",
    "date:inception_upper": "1980-01-01",
    "iso:country": "GB",
    "wof:name": "KA7 1PX",
    "wof:placetype": "postalcode"
  },
  "geometry": {"coordinates":[-4.629225,55.462356],"type":"Point"}
}
