{
  "type": "Feature",
  "properties": {
    "iso:country":"GB",
    "wof:name":"WD6 5QX",
    "wof:placetype":"postalcode"
},
  "geometry": {"coordinates":[-0.25835912534389,51.66273781347684],"type":"Point"}
}