{
  "type": "Feature",
  "properties": {
    "iso:country": "GB",
    "wof:name": "HU17 7EG",
    "wof:placetype": "postalcode"
  },
  "geometry": {"coordinates":[-0.449423,53.851839],"type":"Point"}
}
