{
  "type": "Feature",
  "properties": {
    "iso:country": "GB",
    "wof:name": "SN3 4JU",
    "wof:placetype": "postalcode"
  },
  "geometry": {"coordinates":[-1.746866,51.577604],"type":"Point"}
}
