{
  "type": "Feature",
  "properties": {
    "iso:country": "GB",
    "wof:name": "GU28 9HD",
    "wof:placetype": "postalcode"
  },
  "geometry": {"coordinates":[-0.64382,51.059623],"type":"Point"}
}
