{
  "type": "Feature",
  "properties": {
    "iso:country":"GB",
    "wof:name":"S26 6PU",
    "wof:placetype":"postalcode"
},
  "geometry": {"coordinates":[-1.26348627388402,53.34260547457409],"type":"Point"}
}