{
  "type": "Feature",
  "properties": {
    "iso:country": "GB",
    "wof:name": "L15 1EW",
    "wof:placetype": "postalcode"
  },
  "geometry": {"coordinates":[-2.932848,53.39954],"type":"Point"}
}
