{
  "type": "Feature",
  "properties": {
    "iso:country":"GB",
    "wof:name":"L15 1EW",
    "wof:placetype":"postalcode"
},
  "geometry": {"coordinates":[-2.93284844437294,53.39953979686268],"type":"Point"}
}