{
  "type": "Feature",
  "properties": {
    "iso:country":"GB",
    "wof:name":"M22 4NL",
    "wof:placetype":"postalcode"
},
  "geometry": {"coordinates":[-2.2585793473734,53.40654543676362],"type":"Point"}
}