{
  "type": "Feature",
  "properties": {
    "iso:country": "GB",
    "wof:name": "M22 4NL",
    "wof:placetype": "postalcode"
  },
  "geometry": {"coordinates":[-2.258563,53.406303],"type":"Point"}
}
