{
  "type": "Feature",
  "properties": {
    "iso:country": "GB",
    "wof:name": "SY13 4BP",
    "wof:placetype": "postalcode"
  },
  "geometry": {"coordinates":[-2.645326,52.939879],"type":"Point"}
}
