{
  "type": "Feature",
  "properties": {
    "iso:country":"GB",
    "wof:name":"SY13 4BP",
    "wof:placetype":"postalcode"
},
  "geometry": {"coordinates":[-2.64532570226763,52.93987895496601],"type":"Point"}
}