{
  "type": "Feature",
  "properties": {
    "date:inception_lower": "2009-02-01",
    "date:inception_upper": "2009-02-01",
    "iso:country": "GB",
    "wof:name": "MK18 9AP",
    "wof:placetype": "postalcode"
  },
  "geometry": {"coordinates":[-0.986261,52.000482],"type":"Point"}
}
