{
  "type": "Feature",
  "properties": {
    "iso:country":"GB",
    "wof:name":"TW20 9NF",
    "wof:placetype":"postalcode"
},
  "geometry": {"coordinates":[-0.54943616272102,51.42543697095149],"type":"Point"}
}