{
  "type": "Feature",
  "properties": {
    "date:inception_lower":"1980-01-01",
    "date:inception_upper":"1980-01-31",
    "iso:country":"GB",
    "wof:name":"TW20 9NF",
    "wof:placetype":"postalcode"
},
  "geometry": {"coordinates":[-0.549436,51.425437],"type":"Point"}
}