{
  "type": "Feature",
  "properties": {
    "iso:country":"GB",
    "wof:name":"UB3 3PF",
    "wof:placetype":"postalcode"
},
  "geometry": {"coordinates":[-0.40502704681989,51.51201817175675],"type":"Point"}
}