{
  "type": "Feature",
  "properties": {
    "iso:country":"GB",
    "wof:name":"SS0 7PN",
    "wof:placetype":"postalcode"
},
  "geometry": {"coordinates":[0.7032498628505,51.53687189005491],"type":"Point"}
}