{
  "type": "Feature",
  "properties": {
    "iso:country": "GB",
    "wof:name": "SS0 7PN",
    "wof:placetype": "postalcode"
  },
  "geometry": {"coordinates":[0.70325,51.536872],"type":"Point"}
}
