{
  "type": "Feature",
  "properties": {
    "iso:country":"GB",
    "wof:name":"B31 3ET",
    "wof:placetype":"postalcode"
},
  "geometry": {"coordinates":[-1.95131330901419,52.40787940070607],"type":"Point"}
}