{
  "type": "Feature",
  "properties": {
    "iso:country":"GB",
    "wof:name":"BS30 7DR",
    "wof:placetype":"postalcode"
},
  "geometry": {"coordinates":[-2.49437459605495,51.44032480483979],"type":"Point"}
}