{
  "type": "Feature",
  "properties": {
    "iso:country":"GB",
    "wof:name":"CV47 2RR",
    "wof:placetype":"postalcode"
},
  "geometry": {"coordinates":[-1.42572911269334,52.21814858847654],"type":"Point"}
}