{
  "type": "Feature",
  "properties": {
    "iso:country": "GB",
    "wof:name": "B17 9PD",
    "wof:placetype": "postalcode"
  },
  "geometry": {"coordinates":[-1.945514,52.46224],"type":"Point"}
}
