{
  "type": "Feature",
  "properties": {
    "iso:country":"GB",
    "wof:name":"SW7 1AP",
    "wof:placetype":"postalcode"
},
  "geometry": {"coordinates":[-0.16928712051977,51.49975401052543],"type":"Point"}
}