{
  "type": "Feature",
  "properties": {
    "iso:country": "GB",
    "wof:name": "G69 6DQ",
    "wof:placetype": "postalcode"
  },
  "geometry": {"coordinates":[-4.112124,55.853756],"type":"Point"}
}
