{
  "type": "Feature",
  "properties": {
    "iso:country":"GB",
    "wof:name":"G69 6DQ",
    "wof:placetype":"postalcode"
},
  "geometry": {"coordinates":[-4.11212400087775,55.85375637176685],"type":"Point"}
}