{
  "type": "Feature",
  "properties": {
    "iso:country":"GB",
    "wof:name":"NG23 6HX",
    "wof:placetype":"postalcode"
},
  "geometry": {"coordinates":[-0.79335589411701,53.14115649586974],"type":"Point"}
}