{
  "type": "Feature",
  "properties": {
    "iso:country": "GB",
    "wof:name": "NG23 6HX",
    "wof:placetype": "postalcode"
  },
  "geometry": {"coordinates":[-0.793356,53.141156],"type":"Point"}
}
