{
  "type": "Feature",
  "properties": {
    "date:inception_lower": "1991-09-01",
    "date:inception_upper": "1991-09-01",
    "iso:country": "GB",
    "wof:name": "IP14 2QE",
    "wof:placetype": "postalcode"
  },
  "geometry": {"coordinates":[0.957665,52.150345],"type":"Point"}
}
