{
  "type": "Feature",
  "properties": {
    "iso:country":"GB",
    "wof:name":"IP14 2QE",
    "wof:placetype":"postalcode"
},
  "geometry": {"coordinates":[0.9576458741924,52.15030230711493],"type":"Point"}
}