{
  "type": "Feature",
  "properties": {
    "date:inception_lower":"1991-09-01",
    "date:inception_upper":"1991-09-30",
    "iso:country":"GB",
    "wof:name":"IP14 2QE",
    "wof:placetype":"postalcode"
},
  "geometry": {"coordinates":[0.957646,52.150302],"type":"Point"}
}