{
  "type": "Feature",
  "properties": {
    "iso:country":"GB",
    "wof:name":"MK7 7BP",
    "wof:placetype":"postalcode"
},
  "geometry": {"coordinates":[-0.6909551732136,52.0165962193253],"type":"Point"}
}