{
  "type": "Feature",
  "properties": {
    "iso:country":"GB",
    "wof:name":"M30 8ES",
    "wof:placetype":"postalcode"
},
  "geometry": {"coordinates":[-2.37097906302619,53.49345569577229],"type":"Point"}
}