{
  "type": "Feature",
  "properties": {
    "iso:country": "GB",
    "wof:name": "CO6 2DX",
    "wof:placetype": "postalcode"
  },
  "geometry": {"coordinates":[0.752117,51.918805],"type":"Point"}
}
