{
  "type": "Feature",
  "properties": {
    "iso:country":"GB",
    "wof:name":"RG31 6NA",
    "wof:placetype":"postalcode"
},
  "geometry": {"coordinates":[-1.04294564707738,51.46810809342247],"type":"Point"}
}