{
  "type": "Feature",
  "properties": {
    "date:inception_lower": "1995-07-01",
    "date:inception_upper": "1995-07-01",
    "iso:country": "GB",
    "wof:name": "RG31 6NA",
    "wof:placetype": "postalcode"
  },
  "geometry": {"coordinates":[-1.042946,51.468108],"type":"Point"}
}
