{
  "type": "Feature",
  "properties": {
    "iso:country":"GB",
    "wof:name":"AL3 7BE",
    "wof:placetype":"postalcode"
},
  "geometry": {"coordinates":[-0.39790197144832,51.80163522780588],"type":"Point"}
}