{
  "type": "Feature",
  "properties": {
    "date:inception_lower": "1980-01-01",
    "date:inception_upper": "1980-01-01",
    "iso:country": "GB",
    "wof:name": "IG1 4DL",
    "wof:placetype": "postalcode"
  },
  "geometry": {"coordinates":[0.070537,51.559245],"type":"Point"}
}
