{
  "type": "Feature",
  "properties": {
    "iso:country":"GB",
    "wof:name":"IG1 4DL",
    "wof:placetype":"postalcode"
},
  "geometry": {"coordinates":[0.07053648627398,51.5592445975422],"type":"Point"}
}