{
  "type": "Feature",
  "properties": {
    "iso:country":"GB",
    "wof:name":"G61 2RH",
    "wof:placetype":"postalcode"
},
  "geometry": {"coordinates":[-4.33079272014692,55.91694439020721],"type":"Point"}
}