{
  "type": "Feature",
  "properties": {
    "iso:country": "GB",
    "wof:name": "CH47 6AB",
    "wof:placetype": "postalcode"
  },
  "geometry": {"coordinates":[-3.157279,53.400622],"type":"Point"}
}
