{
  "type": "Feature",
  "properties": {
    "iso:country":"GB",
    "wof:name":"NG7 5NS",
    "wof:placetype":"postalcode"
},
  "geometry": {"coordinates":[-1.17816520246134,52.96780172935218],"type":"Point"}
}