{
  "type": "Feature",
  "properties": {
    "iso:country":"GB",
    "wof:name":"PL4 7AE",
    "wof:placetype":"postalcode"
},
  "geometry": {"coordinates":[-4.1301500989354,50.38493035387683],"type":"Point"}
}