{
  "type": "Feature",
  "properties": {
    "date:inception_lower":"2008-01-01",
    "date:inception_upper":"2008-01-31",
    "iso:country":"GB",
    "wof:name":"PL4 7AE",
    "wof:placetype":"postalcode"
},
  "geometry": {"coordinates":[-4.130179,50.384916],"type":"Point"}
}