{
  "type": "Feature",
  "properties": {
    "iso:country": "GB",
    "wof:name": "PL4 7AE",
    "wof:placetype": "postalcode"
  },
  "geometry": {"coordinates":[-4.130179,50.384916],"type":"Point"}
}
