{
  "type": "Feature",
  "properties": {
    "iso:country":"GB",
    "wof:name":"OX3 8NG",
    "wof:placetype":"postalcode"
},
  "geometry": {"coordinates":[-1.2069396744261,51.75638470316287],"type":"Point"}
}