{
  "type": "Feature",
  "properties": {
    "iso:country": "GB",
    "wof:name": "TN12 6XH",
    "wof:placetype": "postalcode"
  },
  "geometry": {"coordinates":[0.390246,51.172772],"type":"Point"}
}
