{
  "type": "Feature",
  "properties": {
    "iso:country":"GB",
    "wof:name":"CM18 6NQ",
    "wof:placetype":"postalcode"
},
  "geometry": {"coordinates":[0.11488302749959,51.75854847020638],"type":"Point"}
}