{
  "type": "Feature",
  "properties": {
    "date:inception_lower": "1980-01-01",
    "date:inception_upper": "1980-01-01",
    "iso:country": "GB",
    "wof:name": "CM18 6NQ",
    "wof:placetype": "postalcode"
  },
  "geometry": {"coordinates":[0.115265,51.75808],"type":"Point"}
}
