{
  "type": "Feature",
  "properties": {
    "iso:country": "GB",
    "wof:name": "CM18 6NQ",
    "wof:placetype": "postalcode"
  },
  "geometry": {"coordinates":[0.115265,51.75808],"type":"Point"}
}
