{
  "type": "Feature",
  "properties": {
    "iso:country": "GB",
    "wof:name": "PE26 1LD",
    "wof:placetype": "postalcode"
  },
  "geometry": {"coordinates":[-0.117895,52.450508],"type":"Point"}
}
