{
  "type": "Feature",
  "properties": {
    "iso:country": "GB",
    "wof:name": "DY5 2NR",
    "wof:placetype": "postalcode"
  },
  "geometry": {"coordinates":[-2.120011,52.46937],"type":"Point"}
}
