{
  "type": "Feature",
  "properties": {
    "iso:country": "GB",
    "wof:name": "FY4 5ND",
    "wof:placetype": "postalcode"
  },
  "geometry": {"coordinates":[-3.015954,53.788386],"type":"Point"}
}
