{
  "type": "Feature",
  "properties": {
    "date:inception_lower": "1991-09-01",
    "date:inception_upper": "1991-09-01",
    "iso:country": "GB",
    "wof:name": "FY4 5ND",
    "wof:placetype": "postalcode"
  },
  "geometry": {"coordinates":[-3.015954,53.788386],"type":"Point"}
}
