{
  "type": "Feature",
  "properties": {
    "iso:country":"GB",
    "wof:name":"FY4 5ND",
    "wof:placetype":"postalcode"
},
  "geometry": {"coordinates":[-3.01595437544376,53.78838588617658],"type":"Point"}
}