{
  "type": "Feature",
  "properties": {
    "iso:country":"GB",
    "wof:name":"PE14 0EG",
    "wof:placetype":"postalcode"
},
  "geometry": {"coordinates":[0.18540101797661,52.63409652607061],"type":"Point"}
}