{
  "type": "Feature",
  "properties": {
    "iso:country": "GB",
    "wof:name": "PE14 0EG",
    "wof:placetype": "postalcode"
  },
  "geometry": {"coordinates":[0.185401,52.634097],"type":"Point"}
}
