{
  "type": "Feature",
  "properties": {
    "iso:country":"GB",
    "wof:name":"PL21 9SN",
    "wof:placetype":"postalcode"
},
  "geometry": {"coordinates":[-3.98142806284639,50.413885998968],"type":"Point"}
}