{
  "type": "Feature",
  "properties": {
    "date:inception_lower": "1980-01-01",
    "date:inception_upper": "1980-01-01",
    "iso:country": "GB",
    "wof:name": "PL21 9SN",
    "wof:placetype": "postalcode"
  },
  "geometry": {"coordinates":[-3.981428,50.413886],"type":"Point"}
}
