{
  "type": "Feature",
  "properties": {
    "iso:country": "GB",
    "wof:name": "SN15 2PS",
    "wof:placetype": "postalcode"
  },
  "geometry": {"coordinates":[-2.074138,51.403065],"type":"Point"}
}
