{
  "type": "Feature",
  "properties": {
    "iso:country":"GB",
    "wof:name":"SN15 2PS",
    "wof:placetype":"postalcode"
},
  "geometry": {"coordinates":[-2.07257564101798,51.40225918294441],"type":"Point"}
}