{
  "type": "Feature",
  "properties": {
    "iso:country":"GB",
    "wof:name":"WN8 8BJ",
    "wof:placetype":"postalcode"
},
  "geometry": {"coordinates":[-2.80804737787594,53.54630059161573],"type":"Point"}
}