{
  "type": "Feature",
  "properties": {
    "iso:country": "GB",
    "wof:name": "CF61 1RN",
    "wof:placetype": "postalcode"
  },
  "geometry": {"coordinates":[-3.481846,51.403494],"type":"Point"}
}
