{
  "type": "Feature",
  "properties": {
    "iso:country":"GB",
    "wof:name":"CF61 1RN",
    "wof:placetype":"postalcode"
},
  "geometry": {"coordinates":[-3.48171465220515,51.4034232612901],"type":"Point"}
}