{
  "type": "Feature",
  "properties": {
    "iso:country":"GB",
    "wof:name":"MK44 1BX",
    "wof:placetype":"postalcode"
},
  "geometry": {"coordinates":[-0.50431199991318,52.25081726065766],"type":"Point"}
}