{
  "type": "Feature",
  "properties": {
    "iso:country": "GB",
    "wof:name": "NE15 8TQ",
    "wof:placetype": "postalcode"
  },
  "geometry": {"coordinates":[-1.713292,54.986538],"type":"Point"}
}
