{
  "type": "Feature",
  "properties": {
    "iso:country":"GB",
    "wof:name":"NE15 8TQ",
    "wof:placetype":"postalcode"
},
  "geometry": {"coordinates":[-1.71329209862004,54.98653786958651],"type":"Point"}
}