{
  "type": "Feature",
  "properties": {
    "iso:country":"GB",
    "wof:name":"G62 8NP",
    "wof:placetype":"postalcode"
},
  "geometry": {"coordinates":[-4.31655997989799,55.9474290528322],"type":"Point"}
}