{
  "type": "Feature",
  "properties": {
    "iso:country": "GB",
    "wof:name": "KY10 3EN",
    "wof:placetype": "postalcode"
  },
  "geometry": {"coordinates":[-2.696701,56.225786],"type":"Point"}
}
