{
  "type": "Feature",
  "properties": {
    "iso:country":"GB",
    "wof:name":"PE1 3XD",
    "wof:placetype":"postalcode"
},
  "geometry": {"coordinates":[-0.23554307853291,52.60164433003025],"type":"Point"}
}