{
  "type": "Feature",
  "properties": {
    "iso:country":"GB",
    "wof:name":"DN21 1YH",
    "wof:placetype":"postalcode"
},
  "geometry": {"coordinates":[-0.76616543961634,53.40717810983881],"type":"Point"}
}