{
  "type": "Feature",
  "properties": {
    "date:inception_lower":"2007-01-01",
    "date:inception_upper":"2007-01-31",
    "iso:country":"GB",
    "wof:name":"EH27 8DW",
    "wof:placetype":"postalcode"
},
  "geometry": {"coordinates":[-3.443443,55.882514],"type":"Point"}
}