{
  "type": "Feature",
  "properties": {
    "iso:country":"GB",
    "wof:name":"EH27 8DW",
    "wof:placetype":"postalcode"
},
  "geometry": {"coordinates":[-3.44344285650032,55.88251418844942],"type":"Point"}
}