{
  "type": "Feature",
  "properties": {
    "iso:country":"GB",
    "wof:name":"BL3 4SG",
    "wof:placetype":"postalcode"
},
  "geometry": {"coordinates":[-2.48949099818642,53.5569728010753],"type":"Point"}
}