{
  "type": "Feature",
  "properties": {
    "iso:country":"GB",
    "wof:name":"CT21 6JT",
    "wof:placetype":"postalcode"
},
  "geometry": {"coordinates":[1.07156760624859,51.07007544778429],"type":"Point"}
}