{
  "type": "Feature",
  "properties": {
    "iso:country":"GB",
    "wof:name":"W2 3NW",
    "wof:placetype":"postalcode"
},
  "geometry": {"coordinates":[-0.17793197649425,51.51166878071026],"type":"Point"}
}