{
  "type": "Feature",
  "properties": {
    "iso:country": "GB",
    "wof:name": "W2 3NW",
    "wof:placetype": "postalcode"
  },
  "geometry": {"coordinates":[-0.177932,51.511669],"type":"Point"}
}
