{
  "type": "Feature",
  "properties": {
    "date:inception_lower":"1987-10-01",
    "date:inception_upper":"1987-10-31",
    "iso:country":"GB",
    "wof:name":"W2 3NW",
    "wof:placetype":"postalcode"
},
  "geometry": {"coordinates":[-0.177932,51.511669],"type":"Point"}
}