{
  "type": "Feature",
  "properties": {
    "iso:country":"GB",
    "wof:name":"BD3 8QQ",
    "wof:placetype":"postalcode"
},
  "geometry": {"coordinates":[-1.72225053477526,53.79906674636783],"type":"Point"}
}