{
  "type": "Feature",
  "properties": {
    "iso:country": "GB",
    "wof:name": "BD3 8QQ",
    "wof:placetype": "postalcode"
  },
  "geometry": {"coordinates":[-1.722801,53.799074],"type":"Point"}
}
