{
  "type": "Feature",
  "properties": {
    "date:inception_lower":"1984-10-01",
    "date:inception_upper":"1984-10-31",
    "iso:country":"GB",
    "wof:name":"BD3 8QQ",
    "wof:placetype":"postalcode"
},
  "geometry": {"coordinates":[-1.722801,53.799074],"type":"Point"}
}