{
  "type": "Feature",
  "properties": {
    "date:inception_lower": "1980-01-01",
    "date:inception_upper": "1980-01-01",
    "iso:country": "GB",
    "wof:name": "CW7 1BW",
    "wof:placetype": "postalcode"
  },
  "geometry": {"coordinates":[-2.530751,53.188673],"type":"Point"}
}
