{
  "type": "Feature",
  "properties": {
    "iso:country":"GB",
    "wof:name":"CW7 1BW",
    "wof:placetype":"postalcode"
},
  "geometry": {"coordinates":[-2.53075069624784,53.1886731512535],"type":"Point"}
}