{
  "type": "Feature",
  "properties": {
    "iso:country":"GB",
    "wof:name":"SM4 6AS",
    "wof:placetype":"postalcode"
},
  "geometry": {"coordinates":[-0.17180667494082,51.3913429808384],"type":"Point"}
}