{
  "type": "Feature",
  "properties": {
    "date:inception_lower": "1980-01-01",
    "date:inception_upper": "1980-01-01",
    "iso:country": "GB",
    "wof:name": "CA1 3LW",
    "wof:placetype": "postalcode"
  },
  "geometry": {"coordinates":[-2.907374,54.878002],"type":"Point"}
}
