{
  "type": "Feature",
  "properties": {
    "iso:country":"GB",
    "wof:name":"M26 4FA",
    "wof:placetype":"postalcode"
},
  "geometry": {"coordinates":[-2.33422804673833,53.56578602298057],"type":"Point"}
}