{
  "type": "Feature",
  "properties": {
    "iso:country":"GB",
    "wof:name":"BL3 4PU",
    "wof:placetype":"postalcode"
},
  "geometry": {"coordinates":[-2.48018393483798,53.57356717815482],"type":"Point"}
}