{
  "type": "Feature",
  "properties": {
    "iso:country":"GB",
    "wof:name":"RG5 3DD",
    "wof:placetype":"postalcode"
},
  "geometry": {"coordinates":[-0.90637520375844,51.45562935595995],"type":"Point"}
}