{
  "type": "Feature",
  "properties": {
    "iso:country": "GB",
    "wof:name": "RG5 3DD",
    "wof:placetype": "postalcode"
  },
  "geometry": {"coordinates":[-0.906375,51.455629],"type":"Point"}
}
