{
  "type": "Feature",
  "properties": {
    "iso:country":"GB",
    "wof:name":"EH38 5YW",
    "wof:placetype":"postalcode"
},
  "geometry": {"coordinates":[-2.95622030068767,55.78005003320262],"type":"Point"}
}