{
  "type": "Feature",
  "properties": {
    "date:inception_lower": "1980-01-01",
    "date:inception_upper": "1980-01-01",
    "iso:country": "GB",
    "wof:name": "EH38 5YW",
    "wof:placetype": "postalcode"
  },
  "geometry": {"coordinates":[-2.95622,55.78005],"type":"Point"}
}
