{
  "type": "Feature",
  "properties": {
    "iso:country": "GB",
    "wof:name": "EH38 5YW",
    "wof:placetype": "postalcode"
  },
  "geometry": {"coordinates":[-2.95622,55.78005],"type":"Point"}
}
