{
  "type": "Feature",
  "properties": {
    "iso:country":"GB",
    "wof:name":"M33 5PZ",
    "wof:placetype":"postalcode"
},
  "geometry": {"coordinates":[-2.34679896742253,53.43211885053914],"type":"Point"}
}