{
  "type": "Feature",
  "properties": {
    "iso:country": "GB",
    "wof:name": "M33 5PZ",
    "wof:placetype": "postalcode"
  },
  "geometry": {"coordinates":[-2.346799,53.432119],"type":"Point"}
}
