{
  "type": "Feature",
  "properties": {
    "date:inception_lower": "1980-01-01",
    "date:inception_upper": "1980-01-01",
    "iso:country": "GB",
    "wof:name": "M33 5PZ",
    "wof:placetype": "postalcode"
  },
  "geometry": {"coordinates":[-2.346799,53.432119],"type":"Point"}
}
