{
  "type": "Feature",
  "properties": {
    "iso:country":"GB",
    "wof:name":"SL1 8LW",
    "wof:placetype":"postalcode"
},
  "geometry": {"coordinates":[-0.67163448213469,51.54656018177262],"type":"Point"}
}