{
  "type": "Feature",
  "properties": {
    "iso:country":"GB",
    "wof:name":"BS35 2BU",
    "wof:placetype":"postalcode"
},
  "geometry": {"coordinates":[-2.52050893892632,51.60517890583564],"type":"Point"}
}