{
  "type": "Feature",
  "properties": {
    "iso:country":"GB",
    "wof:name":"WS5 3NL",
    "wof:placetype":"postalcode"
},
  "geometry": {"coordinates":[-1.95438450703791,52.56647228388608],"type":"Point"}
}