{
  "type": "Feature",
  "properties": {
    "iso:country": "GB",
    "wof:name": "WS5 3NL",
    "wof:placetype": "postalcode"
  },
  "geometry": {"coordinates":[-1.954384,52.566472],"type":"Point"}
}
