{
  "type": "Feature",
  "properties": {
    "iso:country":"GB",
    "wof:name":"GU4 8SG",
    "wof:placetype":"postalcode"
},
  "geometry": {"coordinates":[-0.49993635672269,51.24613519173352],"type":"Point"}
}