{
  "type": "Feature",
  "properties": {
    "date:inception_lower": "1980-01-01",
    "date:inception_upper": "1980-01-01",
    "iso:country": "GB",
    "wof:name": "GU4 8SG",
    "wof:placetype": "postalcode"
  },
  "geometry": {"coordinates":[-0.499936,51.246135],"type":"Point"}
}
