{
  "type": "Feature",
  "properties": {
    "iso:country":"GB",
    "wof:name":"CT11 0AP",
    "wof:placetype":"postalcode"
},
  "geometry": {"coordinates":[1.40297592955801,51.33361820893554],"type":"Point"}
}