{
  "type": "Feature",
  "properties": {
    "date:inception_lower": "2007-05-01",
    "date:inception_upper": "2007-05-01",
    "iso:country": "GB",
    "wof:name": "CT11 0AP",
    "wof:placetype": "postalcode"
  },
  "geometry": {"coordinates":[1.402976,51.333618],"type":"Point"}
}
