{
  "type": "Feature",
  "properties": {
    "date:inception_lower": "1990-07-01",
    "date:inception_upper": "1990-07-01",
    "iso:country": "GB",
    "wof:name": "NE47 9HA",
    "wof:placetype": "postalcode"
  },
  "geometry": {"coordinates":[-2.250458,54.896718],"type":"Point"}
}
