{
  "type": "Feature",
  "properties": {
    "iso:country":"GB",
    "wof:name":"B94 6JT",
    "wof:placetype":"postalcode"
},
  "geometry": {"coordinates":[-1.74387545873734,52.33755227832535],"type":"Point"}
}