{
  "type": "Feature",
  "properties": {
    "iso:country":"GB",
    "wof:name":"GL52 6SG",
    "wof:placetype":"postalcode"
},
  "geometry": {"coordinates":[-2.05720229541684,51.9004269111135],"type":"Point"}
}