{
  "type": "Feature",
  "properties": {
    "date:inception_lower": "1993-01-01",
    "date:inception_upper": "1993-01-01",
    "iso:country": "GB",
    "wof:name": "GL52 6SG",
    "wof:placetype": "postalcode"
  },
  "geometry": {"coordinates":[-2.057202,51.900427],"type":"Point"}
}
