{
  "type": "Feature",
  "properties": {
    "iso:country":"GB",
    "wof:name":"B19 3HN",
    "wof:placetype":"postalcode"
},
  "geometry": {"coordinates":[-1.90443628257104,52.48898574424439],"type":"Point"}
}