{
  "type": "Feature",
  "properties": {
    "iso:country":"GB",
    "wof:name":"BA16 0FG",
    "wof:placetype":"postalcode"
},
  "geometry": {"coordinates":[-2.74826240089151,51.12394513445194],"type":"Point"}
}