{
  "type": "Feature",
  "properties": {
    "iso:country": "GB",
    "wof:name": "BA16 0FG",
    "wof:placetype": "postalcode"
  },
  "geometry": {"coordinates":[-2.748262,51.123945],"type":"Point"}
}
