{
  "type": "Feature",
  "properties": {
    "iso:country":"GB",
    "wof:name":"E11 3NT",
    "wof:placetype":"postalcode"
},
  "geometry": {"coordinates":[0.01358457610372,51.55839238061484],"type":"Point"}
}