{
  "type": "Feature",
  "properties": {
    "date:inception_lower": "1980-01-01",
    "date:inception_upper": "1980-01-01",
    "iso:country": "GB",
    "wof:name": "E11 3NT",
    "wof:placetype": "postalcode"
  },
  "geometry": {"coordinates":[0.013585,51.558392],"type":"Point"}
}
