{
  "type": "Feature",
  "properties": {
    "iso:country":"GB",
    "wof:name":"LL61 6SF",
    "wof:placetype":"postalcode"
},
  "geometry": {"coordinates":[-4.35938528939001,53.16302943672563],"type":"Point"}
}