{
  "type": "Feature",
  "properties": {
    "iso:country":"GB",
    "wof:name":"S61 2NU",
    "wof:placetype":"postalcode"
},
  "geometry": {"coordinates":[-1.39059781397555,53.42802274617566],"type":"Point"}
}