{
  "type": "Feature",
  "properties": {
    "iso:country":"GB",
    "wof:name":"LE11 1EH",
    "wof:placetype":"postalcode"
},
  "geometry": {"coordinates":[-1.19528129204385,52.77706962335746],"type":"Point"}
}