{
  "type": "Feature",
  "properties": {
    "date:inception_lower":"2010-08-01",
    "date:inception_upper":"2010-08-31",
    "iso:country":"GB",
    "wof:name":"LE11 1EH",
    "wof:placetype":"postalcode"
},
  "geometry": {"coordinates":[-1.195281,52.77707],"type":"Point"}
}