{
  "type": "Feature",
  "properties": {
    "iso:country":"GB",
    "wof:name":"BS30 6LG",
    "wof:placetype":"postalcode"
},
  "geometry": {"coordinates":[-2.45621168940635,51.42515786447044],"type":"Point"}
}