{
  "type": "Feature",
  "properties": {
    "date:inception_lower":"1997-12-01",
    "date:inception_upper":"1997-12-31",
    "iso:country":"GB",
    "wof:name":"BS30 6LG",
    "wof:placetype":"postalcode"
},
  "geometry": {"coordinates":[-2.456212,51.425158],"type":"Point"}
}