{
  "type": "Feature",
  "properties": {
    "iso:country": "GB",
    "wof:name": "BS30 6LG",
    "wof:placetype": "postalcode"
  },
  "geometry": {"coordinates":[-2.456212,51.425158],"type":"Point"}
}
