{
  "type": "Feature",
  "properties": {
    "iso:country":"GB",
    "wof:name":"LL20 7LD",
    "wof:placetype":"postalcode"
},
  "geometry": {"coordinates":[-3.25466976046357,52.88622713578149],"type":"Point"}
}