{
  "type": "Feature",
  "properties": {
    "date:inception_lower": "1980-01-01",
    "date:inception_upper": "1980-01-01",
    "iso:country": "GB",
    "wof:name": "LL20 7LD",
    "wof:placetype": "postalcode"
  },
  "geometry": {"coordinates":[-3.25467,52.886227],"type":"Point"}
}
