{
  "type": "Feature",
  "properties": {
    "iso:country": "GB",
    "wof:name": "LL20 7LD",
    "wof:placetype": "postalcode"
  },
  "geometry": {"coordinates":[-3.25467,52.886227],"type":"Point"}
}
