{
  "type": "Feature",
  "properties": {
    "iso:country": "GB",
    "wof:name": "CV23 1AB",
    "wof:placetype": "postalcode"
  },
  "geometry": {"coordinates":[-1.183811,52.358781],"type":"Point"}
}
