{
  "type": "Feature",
  "properties": {
    "date:inception_lower": "2018-12-01",
    "date:inception_upper": "2018-12-01",
    "iso:country": "GB",
    "wof:name": "CV23 1AB",
    "wof:placetype": "postalcode"
  },
  "geometry": {"coordinates":[-1.183811,52.358781],"type":"Point"}
}
