{
  "type": "Feature",
  "properties": {
    "iso:country":"GB",
    "wof:name":"PR3 0AQ",
    "wof:placetype":"postalcode"
},
  "geometry": {"coordinates":[-2.79558575635351,53.95012917584809],"type":"Point"}
}