{
  "type": "Feature",
  "properties": {
    "date:inception_lower": "2016-04-01",
    "date:inception_upper": "2016-04-01",
    "iso:country": "GB",
    "wof:name": "PL6 7FF",
    "wof:placetype": "postalcode"
  },
  "geometry": {"coordinates":[-4.094784,50.433737],"type":"Point"}
}
