{
  "type": "Feature",
  "properties": {
    "iso:country":"GB",
    "wof:name":"PL6 7FF",
    "wof:placetype":"postalcode"
},
  "geometry": {"coordinates":[-4.09478426628257,50.43373730764232],"type":"Point"}
}