{
  "type": "Feature",
  "properties": {
    "iso:country":"GB",
    "wof:name":"WS4 1BF",
    "wof:placetype":"postalcode"
},
  "geometry": {"coordinates":[-1.95292514872566,52.62076102692629],"type":"Point"}
}