{
  "type": "Feature",
  "properties": {
    "date:inception_lower":"2016-01-01",
    "date:inception_upper":"2016-01-31",
    "iso:country":"GB",
    "wof:name":"WS4 1BF",
    "wof:placetype":"postalcode"
},
  "geometry": {"coordinates":[-1.952925,52.620761],"type":"Point"}
}