{
  "type": "Feature",
  "properties": {
    "iso:country": "GB",
    "wof:name": "DE74 2LT",
    "wof:placetype": "postalcode"
  },
  "geometry": {"coordinates":[-1.339092,52.837819],"type":"Point"}
}
