{
  "type": "Feature",
  "properties": {
    "iso:country":"GB",
    "wof:name":"RM15 4XJ",
    "wof:placetype":"postalcode"
},
  "geometry": {"coordinates":[0.25373883630481,51.5196713983508],"type":"Point"}
}