{
  "type": "Feature",
  "properties": {
    "iso:country":"GB",
    "wof:name":"BB5 0HJ",
    "wof:placetype":"postalcode"
},
  "geometry": {"coordinates":[-2.38553381483582,53.74981831805275],"type":"Point"}
}