{
  "type": "Feature",
  "properties": {
    "iso:country": "GB",
    "wof:name": "TR13 8NU",
    "wof:placetype": "postalcode"
  },
  "geometry": {"coordinates":[-5.275749,50.105648],"type":"Point"}
}
