{
  "type": "Feature",
  "properties": {
    "iso:country":"GB",
    "wof:name":"PL14 4QA",
    "wof:placetype":"postalcode"
},
  "geometry": {"coordinates":[-4.50207968792875,50.40481024957494],"type":"Point"}
}