{
  "type": "Feature",
  "properties": {
    "date:inception_lower": "1980-01-01",
    "date:inception_upper": "1980-01-01",
    "iso:country": "GB",
    "wof:name": "PL14 4QA",
    "wof:placetype": "postalcode"
  },
  "geometry": {"coordinates":[-4.50208,50.40481],"type":"Point"}
}
