{
  "type": "Feature",
  "properties": {
    "date:inception_lower":"1998-06-01",
    "date:inception_upper":"1998-06-30",
    "iso:country":"GB",
    "wof:name":"YO61 1RS",
    "wof:placetype":"postalcode"
},
  "geometry": {"coordinates":[-1.243096,54.083122],"type":"Point"}
}