{
  "type": "Feature",
  "properties": {
    "iso:country":"GB",
    "wof:name":"YO61 1RS",
    "wof:placetype":"postalcode"
},
  "geometry": {"coordinates":[-1.24285940992313,54.08312283517142],"type":"Point"}
}