{
  "type": "Feature",
  "properties": {
    "iso:country":"GB",
    "wof:name":"SE3 8SD",
    "wof:placetype":"postalcode"
},
  "geometry": {"coordinates":[0.03168700376446,51.47443911073984],"type":"Point"}
}