{
  "type": "Feature",
  "properties": {
    "date:inception_lower":"1980-01-01",
    "date:inception_upper":"1980-01-31",
    "iso:country":"GB",
    "wof:name":"SE3 8SD",
    "wof:placetype":"postalcode"
},
  "geometry": {"coordinates":[0.031687,51.474439],"type":"Point"}
}