{
  "type": "Feature",
  "properties": {
    "iso:country": "GB",
    "wof:name": "CV36 5NQ",
    "wof:placetype": "postalcode"
  },
  "geometry": {"coordinates":[-1.638747,52.008786],"type":"Point"}
}
