{
  "type": "Feature",
  "properties": {
    "iso:country": "GB",
    "wof:name": "N9 7EE",
    "wof:placetype": "postalcode"
  },
  "geometry": {"coordinates":[-0.056439,51.628548],"type":"Point"}
}
