{
  "type": "Feature",
  "properties": {
    "iso:country":"GB",
    "wof:name":"WR4 0EA",
    "wof:placetype":"postalcode"
},
  "geometry": {"coordinates":[-2.17412234281604,52.21002958984245],"type":"Point"}
}