{
  "type": "Feature",
  "properties": {
    "date:inception_lower": "2009-07-01",
    "date:inception_upper": "2009-07-01",
    "iso:country": "GB",
    "wof:name": "FY7 8GX",
    "wof:placetype": "postalcode"
  },
  "geometry": {"coordinates":[-3.032467,53.912418],"type":"Point"}
}
