{
  "type": "Feature",
  "properties": {
    "iso:country":"GB",
    "wof:name":"FY7 8GX",
    "wof:placetype":"postalcode"
},
  "geometry": {"coordinates":[-3.03246708050139,53.91241843180705],"type":"Point"}
}