{
  "type": "Feature",
  "properties": {
    "iso:country": "GB",
    "wof:name": "FY7 8GX",
    "wof:placetype": "postalcode"
  },
  "geometry": {"coordinates":[-3.032467,53.912418],"type":"Point"}
}
