{
  "type": "Feature",
  "properties": {
    "iso:country":"GB",
    "wof:name":"S63 8EE",
    "wof:placetype":"postalcode"
},
  "geometry": {"coordinates":[-1.32479505057898,53.51756431327097],"type":"Point"}
}