{
  "type": "Feature",
  "properties": {
    "date:inception_lower": "1980-01-01",
    "date:inception_upper": "1980-01-01",
    "iso:country": "GB",
    "wof:name": "S63 8EE",
    "wof:placetype": "postalcode"
  },
  "geometry": {"coordinates":[-1.324795,53.517564],"type":"Point"}
}
