{
  "type": "Feature",
  "properties": {
    "iso:country":"GB",
    "wof:name":"GU47 0EA",
    "wof:placetype":"postalcode"
},
  "geometry": {"coordinates":[-0.78370424280424,51.34888135015787],"type":"Point"}
}