{
  "type": "Feature",
  "properties": {
    "iso:country":"GB",
    "wof:name":"WF6 1RE",
    "wof:placetype":"postalcode"
},
  "geometry": {"coordinates":[-1.40472472833345,53.71236240625531],"type":"Point"}
}