{
  "type": "Feature",
  "properties": {
    "iso:country":"GB",
    "wof:name":"NE5 1HY",
    "wof:placetype":"postalcode"
},
  "geometry": {"coordinates":[-1.7176565055373,54.99927252960651],"type":"Point"}
}