{
  "type": "Feature",
  "properties": {
    "iso:country":"GB",
    "wof:name":"PO20 9JN",
    "wof:placetype":"postalcode"
},
  "geometry": {"coordinates":[-0.79791369377442,50.73503234001274],"type":"Point"}
}