{
  "type": "Feature",
  "properties": {
    "date:inception_lower":"2000-06-01",
    "date:inception_upper":"2000-06-30",
    "iso:country":"GB",
    "wof:name":"PO20 9JN",
    "wof:placetype":"postalcode"
},
  "geometry": {"coordinates":[-0.797914,50.735032],"type":"Point"}
}