{
  "type": "Feature",
  "properties": {
    "iso:country": "GB",
    "wof:name": "AB51 5RX",
    "wof:placetype": "postalcode"
  },
  "geometry": {"coordinates":[-2.413168,57.288711],"type":"Point"}
}
