{
  "type": "Feature",
  "properties": {
    "date:inception_lower": "2010-01-01",
    "date:inception_upper": "2010-01-01",
    "iso:country": "GB",
    "wof:name": "AB51 5RX",
    "wof:placetype": "postalcode"
  },
  "geometry": {"coordinates":[-2.413168,57.288711],"type":"Point"}
}
