{
  "type": "Feature",
  "properties": {
    "iso:country":"GB",
    "wof:name":"TW7 6NE",
    "wof:placetype":"postalcode"
},
  "geometry": {"coordinates":[-0.34673837687133,51.46847962117566],"type":"Point"}
}