{
  "type": "Feature",
  "properties": {
    "date:inception_lower": "1990-07-01",
    "date:inception_upper": "1990-07-01",
    "iso:country": "GB",
    "wof:name": "TW7 6NE",
    "wof:placetype": "postalcode"
  },
  "geometry": {"coordinates":[-0.346738,51.46848],"type":"Point"}
}
