{
  "type": "Feature",
  "properties": {
    "iso:country":"GB",
    "wof:name":"AB12 3BB",
    "wof:placetype":"postalcode"
},
  "geometry": {"coordinates":[-2.0894856283539,57.12519552099763],"type":"Point"}
}