{
  "type": "Feature",
  "properties": {
    "iso:country":"GB",
    "wof:name":"S40 4LX",
    "wof:placetype":"postalcode"
},
  "geometry": {"coordinates":[-1.45764429088032,53.24568510183369],"type":"Point"}
}