{
  "type": "Feature",
  "properties": {
    "iso:country":"GB",
    "wof:name":"ML9 2AU",
    "wof:placetype":"postalcode"
},
  "geometry": {"coordinates":[-3.97396675782195,55.74490958755297],"type":"Point"}
}