{
  "type": "Feature",
  "properties": {
    "date:inception_lower": "1980-01-01",
    "date:inception_upper": "1980-01-01",
    "iso:country": "GB",
    "wof:name": "ML9 2AU",
    "wof:placetype": "postalcode"
  },
  "geometry": {"coordinates":[-3.973967,55.74491],"type":"Point"}
}
