{
  "type": "Feature",
  "properties": {
    "date:inception_lower": "2014-05-01",
    "date:inception_upper": "2014-05-01",
    "iso:country": "GB",
    "wof:name": "FK10 1PF",
    "wof:placetype": "postalcode"
  },
  "geometry": {"coordinates":[-3.800001,56.113411],"type":"Point"}
}
