{
  "type": "Feature",
  "properties": {
    "date:inception_lower": "2020-11-01",
    "date:inception_upper": "2020-11-01",
    "iso:country": "GB",
    "wof:name": "CM8 2GG",
    "wof:placetype": "postalcode"
  },
  "geometry": {"coordinates":[0.651764,51.813642],"type":"Point"}
}
