{
  "type": "Feature",
  "properties": {
    "iso:country": "GB",
    "wof:name": "LS15 0PE",
    "wof:placetype": "postalcode"
  },
  "geometry": {"coordinates":[-1.486213,53.793965],"type":"Point"}
}
