{
  "type": "Feature",
  "properties": {
    "iso:country":"GB",
    "wof:name":"LS15 0PE",
    "wof:placetype":"postalcode"
},
  "geometry": {"coordinates":[-1.48621324784978,53.79396510514258],"type":"Point"}
}