{
  "type": "Feature",
  "properties": {
    "iso:country": "GB",
    "wof:name": "SE10 8NB",
    "wof:placetype": "postalcode"
  },
  "geometry": {"coordinates":[-0.011404,51.478937],"type":"Point"}
}
