{
  "type": "Feature",
  "properties": {
    "date:inception_lower": "1980-01-01",
    "date:inception_upper": "1980-01-01",
    "iso:country": "GB",
    "wof:name": "SE10 8NB",
    "wof:placetype": "postalcode"
  },
  "geometry": {"coordinates":[-0.011378,51.478937],"type":"Point"}
}
