{
  "type": "Feature",
  "properties": {
    "iso:country":"GB",
    "wof:name":"OX2 6LF",
    "wof:placetype":"postalcode"
},
  "geometry": {"coordinates":[-1.26131337531594,51.76522658436265],"type":"Point"}
}