{
  "type": "Feature",
  "properties": {
    "iso:country":"GB",
    "wof:name":"LA3 1HL",
    "wof:placetype":"postalcode"
},
  "geometry": {"coordinates":[-2.88221000218161,54.06043564983903],"type":"Point"}
}