{
  "type": "Feature",
  "properties": {
    "date:inception_lower": "1980-01-01",
    "date:inception_upper": "1980-01-01",
    "iso:country": "GB",
    "wof:name": "LA3 1HL",
    "wof:placetype": "postalcode"
  },
  "geometry": {"coordinates":[-2.88221,54.060436],"type":"Point"}
}
