{
  "type": "Feature",
  "properties": {
    "iso:country":"GB",
    "wof:name":"CH7 2DY",
    "wof:placetype":"postalcode"
},
  "geometry": {"coordinates":[-3.0844794366942,53.16540244473153],"type":"Point"}
}