{
  "type": "Feature",
  "properties": {
    "date:inception_lower": "1993-01-01",
    "date:inception_upper": "1993-01-01",
    "iso:country": "GB",
    "wof:name": "CH7 2DY",
    "wof:placetype": "postalcode"
  },
  "geometry": {"coordinates":[-3.084479,53.165402],"type":"Point"}
}
