{
  "type": "Feature",
  "properties": {
    "iso:country":"GB",
    "wof:name":"DY8 5SX",
    "wof:placetype":"postalcode"
},
  "geometry": {"coordinates":[-2.15642067775401,52.47758404082235],"type":"Point"}
}