{
  "type": "Feature",
  "properties": {
    "iso:country":"GB",
    "wof:name":"GU17 0SD",
    "wof:placetype":"postalcode"
},
  "geometry": {"coordinates":[-0.80528736132091,51.3378003052971],"type":"Point"}
}