{
  "type": "Feature",
  "properties": {
    "date:inception_lower":"2013-09-01",
    "date:inception_upper":"2013-09-30",
    "iso:country":"GB",
    "wof:name":"GU17 0SD",
    "wof:placetype":"postalcode"
},
  "geometry": {"coordinates":[-0.805287,51.3378],"type":"Point"}
}