{
  "type": "Feature",
  "properties": {
    "date:inception_lower": "2015-05-01",
    "date:inception_upper": "2015-05-01",
    "iso:country": "GB",
    "wof:name": "NR32 4FA",
    "wof:placetype": "postalcode"
  },
  "geometry": {"coordinates":[1.753244,52.490002],"type":"Point"}
}
