{
  "type": "Feature",
  "properties": {
    "iso:country":"GB",
    "wof:name":"NR32 4FA",
    "wof:placetype":"postalcode"
},
  "geometry": {"coordinates":[1.75324369074249,52.4900019542855],"type":"Point"}
}