{
  "type": "Feature",
  "properties": {
    "iso:country":"GB",
    "wof:name":"CO4 3NH",
    "wof:placetype":"postalcode"
},
  "geometry": {"coordinates":[0.9340606267782,51.89445066981055],"type":"Point"}
}