{
  "type": "Feature",
  "properties": {
    "iso:country":"GB",
    "wof:name":"CV47 0RA",
    "wof:placetype":"postalcode"
},
  "geometry": {"coordinates":[-1.39460579387524,52.24750880373276],"type":"Point"}
}