{
  "type": "Feature",
  "properties": {
    "date:inception_lower":"1986-07-01",
    "date:inception_upper":"1986-07-31",
    "iso:country":"GB",
    "wof:name":"TN6 3LW",
    "wof:placetype":"postalcode"
},
  "geometry": {"coordinates":[0.216879,51.043171],"type":"Point"}
}