{
  "type": "Feature",
  "properties": {
    "iso:country": "GB",
    "wof:name": "TN6 3LW",
    "wof:placetype": "postalcode"
  },
  "geometry": {"coordinates":[0.216879,51.043171],"type":"Point"}
}
