{
  "type": "Feature",
  "properties": {
    "iso:country":"GB",
    "wof:name":"TN6 3LW",
    "wof:placetype":"postalcode"
},
  "geometry": {"coordinates":[0.21686411123738,51.04316489443344],"type":"Point"}
}