{
  "type": "Feature",
  "properties": {
    "iso:country": "GB",
    "wof:name": "EX4 4BQ",
    "wof:placetype": "postalcode"
  },
  "geometry": {"coordinates":[-3.541639,50.728737],"type":"Point"}
}
