{
  "type": "Feature",
  "properties": {
    "iso:country":"GB",
    "wof:name":"DY3 3SU",
    "wof:placetype":"postalcode"
},
  "geometry": {"coordinates":[-2.1268796811288,52.54186142894922],"type":"Point"}
}