{
  "type": "Feature",
  "properties": {
    "date:inception_lower": "1986-07-01",
    "date:inception_upper": "1986-07-01",
    "iso:country": "GB",
    "wof:name": "MK9 2HR",
    "wof:placetype": "postalcode"
  },
  "geometry": {"coordinates":[-0.76408,52.039605],"type":"Point"}
}
