{
  "type": "Feature",
  "properties": {
    "iso:country": "GB",
    "wof:name": "MK9 2HR",
    "wof:placetype": "postalcode"
  },
  "geometry": {"coordinates":[-0.764372,52.039822],"type":"Point"}
}
