{
  "type": "Feature",
  "properties": {
    "iso:country": "GB",
    "wof:name": "MK9 2HR",
    "wof:placetype": "postalcode"
  },
  "geometry": {"coordinates":[-0.764123,52.039641],"type":"Point"}
}
