{
  "type": "Feature",
  "properties": {
    "iso:country":"GB",
    "wof:name":"MK9 2HR",
    "wof:placetype":"postalcode"
},
  "geometry": {"coordinates":[-0.76424376342025,52.03971272606386],"type":"Point"}
}