{
  "type": "Feature",
  "properties": {
    "iso:country":"GB",
    "wof:name":"NP4 8AR",
    "wof:placetype":"postalcode"
},
  "geometry": {"coordinates":[-3.03132606868048,51.69865860166276],"type":"Point"}
}