{
  "type": "Feature",
  "properties": {
    "date:inception_lower": "1980-01-01",
    "date:inception_upper": "1980-01-01",
    "iso:country": "GB",
    "wof:name": "NP4 8AR",
    "wof:placetype": "postalcode"
  },
  "geometry": {"coordinates":[-3.03126,51.698635],"type":"Point"}
}
