{
  "type": "Feature",
  "properties": {
    "iso:country":"GB",
    "wof:name":"KA9 1DR",
    "wof:placetype":"postalcode"
},
  "geometry": {"coordinates":[-4.59712965722369,55.49296544795713],"type":"Point"}
}