{
  "type": "Feature",
  "properties": {
    "iso:country": "GB",
    "wof:name": "KA9 1DR",
    "wof:placetype": "postalcode"
  },
  "geometry": {"coordinates":[-4.59713,55.492965],"type":"Point"}
}
