{
  "type": "Feature",
  "properties": {
    "iso:country":"GB",
    "wof:name":"M34 3AF",
    "wof:placetype":"postalcode"
},
  "geometry": {"coordinates":[-2.11242679682314,53.4563714024686],"type":"Point"}
}