{
  "type": "Feature",
  "properties": {
    "date:inception_lower": "1980-01-01",
    "date:inception_upper": "1980-01-01",
    "iso:country": "GB",
    "wof:name": "M34 3AF",
    "wof:placetype": "postalcode"
  },
  "geometry": {"coordinates":[-2.112427,53.456371],"type":"Point"}
}
