{
  "type": "Feature",
  "properties": {
    "iso:country":"GB",
    "wof:name":"GU1 2PH",
    "wof:placetype":"postalcode"
},
  "geometry": {"coordinates":[-0.54552010755129,51.24726799533519],"type":"Point"}
}