{
  "type": "Feature",
  "properties": {
    "iso:country":"GB",
    "wof:name":"PE12 8TD",
    "wof:placetype":"postalcode"
},
  "geometry": {"coordinates":[0.07259521080696,52.81485903093301],"type":"Point"}
}