{
  "type": "Feature",
  "properties": {
    "date:inception_lower":"1980-01-01",
    "date:inception_upper":"1980-01-31",
    "iso:country":"GB",
    "wof:name":"TS10 2NE",
    "wof:placetype":"postalcode"
},
  "geometry": {"coordinates":[-1.049199,54.603142],"type":"Point"}
}