{
  "type": "Feature",
  "properties": {
    "date:inception_lower": "1980-01-01",
    "date:inception_upper": "1980-01-01",
    "iso:country": "GB",
    "wof:name": "S66 7RQ",
    "wof:placetype": "postalcode"
  },
  "geometry": {"coordinates":[-1.188307,53.450334],"type":"Point"}
}
