{
  "type": "Feature",
  "properties": {
    "iso:country":"GB",
    "wof:name":"S66 7RQ",
    "wof:placetype":"postalcode"
},
  "geometry": {"coordinates":[-1.18830750031629,53.45033439861582],"type":"Point"}
}