{
  "type": "Feature",
  "properties": {
    "iso:country": "GB",
    "wof:name": "S66 7RQ",
    "wof:placetype": "postalcode"
  },
  "geometry": {"coordinates":[-1.188307,53.450334],"type":"Point"}
}
