{
  "type": "Feature",
  "properties": {
    "iso:country": "GB",
    "wof:name": "TW11 9FG",
    "wof:placetype": "postalcode"
  },
  "geometry": {"coordinates":[-0.32107,51.429376],"type":"Point"}
}
