{
  "type": "Feature",
  "properties": {
    "iso:country":"GB",
    "wof:name":"G52 3LS",
    "wof:placetype":"postalcode"
},
  "geometry": {"coordinates":[-4.36619554563958,55.84446631467603],"type":"Point"}
}