{
  "type": "Feature",
  "properties": {
    "date:inception_lower":"1980-01-01",
    "date:inception_upper":"1980-01-31",
    "iso:country":"GB",
    "wof:name":"TR2 5EE",
    "wof:placetype":"postalcode"
},
  "geometry": {"coordinates":[-4.97871,50.178031],"type":"Point"}
}