{
  "type": "Feature",
  "properties": {
    "iso:country":"GB",
    "wof:name":"S20 3GU",
    "wof:placetype":"postalcode"
},
  "geometry": {"coordinates":[-1.34727403542629,53.32738951994715],"type":"Point"}
}