{
  "type": "Feature",
  "properties": {
    "iso:country": "GB",
    "wof:name": "WD24 5JX",
    "wof:placetype": "postalcode"
  },
  "geometry": {"coordinates":[-0.40926,51.677018],"type":"Point"}
}
