{
  "type": "Feature",
  "properties": {
    "iso:country":"GB",
    "wof:name":"WD24 5JX",
    "wof:placetype":"postalcode"
},
  "geometry": {"coordinates":[-0.40926029964717,51.67701784341757],"type":"Point"}
}