{
  "type": "Feature",
  "properties": {
    "iso:country": "GB",
    "wof:name": "BN1 8UA",
    "wof:placetype": "postalcode"
  },
  "geometry": {"coordinates":[-0.14713,50.865951],"type":"Point"}
}
