{
  "type": "Feature",
  "properties": {
    "iso:country":"GB",
    "wof:name":"BN1 8UA",
    "wof:placetype":"postalcode"
},
  "geometry": {"coordinates":[-0.14713014027586,50.86595114619186],"type":"Point"}
}