{
  "type": "Feature",
  "properties": {
    "iso:country": "GB",
    "wof:name": "KA7 1SQ",
    "wof:placetype": "postalcode"
  },
  "geometry": {"coordinates":[-4.629913,55.459141],"type":"Point"}
}
