{
  "type": "Feature",
  "properties": {
    "date:inception_lower": "2005-10-01",
    "date:inception_upper": "2005-10-01",
    "iso:country": "GB",
    "wof:name": "IP14 2BF",
    "wof:placetype": "postalcode"
  },
  "geometry": {"coordinates":[0.982335,52.169671],"type":"Point"}
}
