{
  "type": "Feature",
  "properties": {
    "iso:country": "GB",
    "wof:name": "IP14 2BF",
    "wof:placetype": "postalcode"
  },
  "geometry": {"coordinates":[0.982269,52.169809],"type":"Point"}
}
