{
  "type": "Feature",
  "properties": {
    "date:inception_lower": "1980-01-01",
    "date:inception_upper": "1980-01-01",
    "iso:country": "GB",
    "wof:name": "SE9 1PN",
    "wof:placetype": "postalcode"
  },
  "geometry": {"coordinates":[0.060239,51.458707],"type":"Point"}
}
