{
  "type": "Feature",
  "properties": {
    "iso:country": "GB",
    "wof:name": "SE9 1PN",
    "wof:placetype": "postalcode"
  },
  "geometry": {"coordinates":[0.060239,51.458707],"type":"Point"}
}
