{
  "type": "Feature",
  "properties": {
    "iso:country":"GB",
    "wof:name":"PL14 4QP",
    "wof:placetype":"postalcode"
},
  "geometry": {"coordinates":[-4.49910128734691,50.42549926841749],"type":"Point"}
}