{
  "type": "Feature",
  "properties": {
    "iso:country":"GB",
    "wof:name":"LS12 5HU",
    "wof:placetype":"postalcode"
},
  "geometry": {"coordinates":[-1.63450353282268,53.77037552831337],"type":"Point"}
}