{
  "type": "Feature",
  "properties": {
    "date:inception_lower": "2007-08-01",
    "date:inception_upper": "2007-08-01",
    "iso:country": "GB",
    "wof:name": "EH7 5GU",
    "wof:placetype": "postalcode"
  },
  "geometry": {"coordinates":[-3.173066,55.961001],"type":"Point"}
}
