{
  "type": "Feature",
  "properties": {
    "iso:country":"GB",
    "wof:name":"EH7 5GU",
    "wof:placetype":"postalcode"
},
  "geometry": {"coordinates":[-3.17306560690073,55.96100094085013],"type":"Point"}
}