{
  "type": "Feature",
  "properties": {
    "iso:country":"GB",
    "wof:name":"YO16 7JS",
    "wof:placetype":"postalcode"
},
  "geometry": {"coordinates":[-0.20401738364687,54.09175056973565],"type":"Point"}
}