{
  "type": "Feature",
  "properties": {
    "iso:country":"GB",
    "wof:name":"CV32 5PR",
    "wof:placetype":"postalcode"
},
  "geometry": {"coordinates":[-1.53530988480768,52.29346652616471],"type":"Point"}
}