{
  "type": "Feature",
  "properties": {
    "date:inception_lower": "1992-01-01",
    "date:inception_upper": "1992-01-01",
    "iso:country": "GB",
    "wof:name": "CV32 5PR",
    "wof:placetype": "postalcode"
  },
  "geometry": {"coordinates":[-1.53531,52.293467],"type":"Point"}
}
