{
  "type": "Feature",
  "properties": {
    "iso:country": "GB",
    "wof:name": "CV32 5PR",
    "wof:placetype": "postalcode"
  },
  "geometry": {"coordinates":[-1.53531,52.293467],"type":"Point"}
}
