{
  "type": "Feature",
  "properties": {
    "iso:country": "GB",
    "wof:name": "TR11 4FN",
    "wof:placetype": "postalcode"
  },
  "geometry": {"coordinates":[-5.100285,50.158858],"type":"Point"}
}
