{
  "type": "Feature",
  "properties": {
    "date:inception_lower": "1980-01-01",
    "date:inception_upper": "1980-01-01",
    "iso:country": "GB",
    "wof:name": "CW1 4HX",
    "wof:placetype": "postalcode"
  },
  "geometry": {"coordinates":[-2.428452,53.108353],"type":"Point"}
}
