{
  "type": "Feature",
  "properties": {
    "iso:country": "GB",
    "wof:name": "CW1 4HX",
    "wof:placetype": "postalcode"
  },
  "geometry": {"coordinates":[-2.428194,53.107995],"type":"Point"}
}
