{
  "type": "Feature",
  "properties": {
    "date:inception_lower":"1980-01-01",
    "date:inception_upper":"1980-01-31",
    "iso:country":"GB",
    "wof:name":"EX23 9PR",
    "wof:placetype":"postalcode"
},
  "geometry": {"coordinates":[-4.502657,50.92408],"type":"Point"}
}