{
  "type": "Feature",
  "properties": {
    "iso:country": "GB",
    "wof:name": "PA14 6EH",
    "wof:placetype": "postalcode"
  },
  "geometry": {"coordinates":[-4.646041,55.921009],"type":"Point"}
}
