{
  "type": "Feature",
  "properties": {
    "iso:country":"GB",
    "wof:name":"PA14 6EH",
    "wof:placetype":"postalcode"
},
  "geometry": {"coordinates":[-4.65007526157623,55.92191766113762],"type":"Point"}
}