{
  "type": "Feature",
  "properties": {
    "iso:country": "GB",
    "wof:name": "PA14 6EH",
    "wof:placetype": "postalcode"
  },
  "geometry": {"coordinates":[-4.650075,55.921918],"type":"Point"}
}
