{
  "type": "Feature",
  "properties": {
    "iso:country": "GB",
    "wof:name": "TR1 2PY",
    "wof:placetype": "postalcode"
  },
  "geometry": {"coordinates":[-5.053143,50.261088],"type":"Point"}
}
