{
  "type": "Feature",
  "properties": {
    "iso:country":"GB",
    "wof:name":"TR1 2PY",
    "wof:placetype":"postalcode"
},
  "geometry": {"coordinates":[-5.05314264884728,50.26108811110933],"type":"Point"}
}