{
  "type": "Feature",
  "properties": {
    "date:inception_lower":"1980-01-01",
    "date:inception_upper":"1980-01-31",
    "iso:country":"GB",
    "wof:name":"TR1 2PY",
    "wof:placetype":"postalcode"
},
  "geometry": {"coordinates":[-5.053143,50.261088],"type":"Point"}
}