{
  "type": "Feature",
  "properties": {
    "iso:country":"GB",
    "wof:name":"HA6 2LH",
    "wof:placetype":"postalcode"
},
  "geometry": {"coordinates":[-0.4368666960529,51.6284000713891],"type":"Point"}
}