{
  "type": "Feature",
  "properties": {
    "date:inception_lower":"1994-12-01",
    "date:inception_upper":"1994-12-31",
    "iso:country":"GB",
    "wof:name":"SO31 6LA",
    "wof:placetype":"postalcode"
},
  "geometry": {"coordinates":[-1.267985,50.870178],"type":"Point"}
}