{
  "type": "Feature",
  "properties": {
    "date:inception_lower":"1994-05-01",
    "date:inception_upper":"1994-05-31",
    "iso:country":"GB",
    "wof:name":"BN43 5UX",
    "wof:placetype":"postalcode"
},
  "geometry": {"coordinates":[-0.267831,50.836293],"type":"Point"}
}