{
  "type": "Feature",
  "properties": {
    "iso:country":"GB",
    "wof:name":"WA3 6JZ",
    "wof:placetype":"postalcode"
},
  "geometry": {"coordinates":[-2.45582250615311,53.41596835300389],"type":"Point"}
}