{
  "type": "Feature",
  "properties": {
    "date:inception_lower": "1980-01-01",
    "date:inception_upper": "1980-01-01",
    "iso:country": "GB",
    "wof:name": "WA3 6JZ",
    "wof:placetype": "postalcode"
  },
  "geometry": {"coordinates":[-2.45575,53.416264],"type":"Point"}
}
