{
  "type": "Feature",
  "properties": {
    "iso:country":"GB",
    "wof:name":"M21 0QZ",
    "wof:placetype":"postalcode"
},
  "geometry": {"coordinates":[-2.2695087863957,53.44598096408719],"type":"Point"}
}