{
  "type": "Feature",
  "properties": {
    "iso:country": "GB",
    "wof:name": "W1T 5NR",
    "wof:placetype": "postalcode"
  },
  "geometry": {"coordinates":[-0.139879,51.524218],"type":"Point"}
}
