{
  "type": "Feature",
  "properties": {
    "iso:country":"GB",
    "wof:name":"SS5 6JL",
    "wof:placetype":"postalcode"
},
  "geometry": {"coordinates":[0.6158704497474,51.6248042273422],"type":"Point"}
}