{
  "type": "Feature",
  "properties": {
    "iso:country": "GB",
    "wof:name": "SS5 6JL",
    "wof:placetype": "postalcode"
  },
  "geometry": {"coordinates":[0.61587,51.624804],"type":"Point"}
}
