{
  "type": "Feature",
  "properties": {
    "iso:country": "GB",
    "wof:name": "WA8 4NX",
    "wof:placetype": "postalcode"
  },
  "geometry": {"coordinates":[-2.75756,53.382794],"type":"Point"}
}
