{
  "type": "Feature",
  "properties": {
    "iso:country":"GB",
    "wof:name":"WA8 4NX",
    "wof:placetype":"postalcode"
},
  "geometry": {"coordinates":[-2.75755981898479,53.38279436399208],"type":"Point"}
}