{
  "type": "Feature",
  "properties": {
    "iso:country": "GB",
    "wof:name": "NE65 8XQ",
    "wof:placetype": "postalcode"
  },
  "geometry": {"coordinates":[-1.765683,55.261118],"type":"Point"}
}
