{
  "type": "Feature",
  "properties": {
    "iso:country":"GB",
    "wof:name":"NE15 9AY",
    "wof:placetype":"postalcode"
},
  "geometry": {"coordinates":[-1.74563165035959,54.99034797741491],"type":"Point"}
}