{
  "type": "Feature",
  "properties": {
    "iso:country":"GB",
    "wof:name":"SL6 6EL",
    "wof:placetype":"postalcode"
},
  "geometry": {"coordinates":[-0.73891986206463,51.52278163381836],"type":"Point"}
}