{
  "type": "Feature",
  "properties": {
    "date:inception_lower": "1980-01-01",
    "date:inception_upper": "1980-01-01",
    "iso:country": "GB",
    "wof:name": "SL6 6EL",
    "wof:placetype": "postalcode"
  },
  "geometry": {"coordinates":[-0.73892,51.522782],"type":"Point"}
}
