{
  "type": "Feature",
  "properties": {
    "iso:country":"GB",
    "wof:name":"PR3 5DB",
    "wof:placetype":"postalcode"
},
  "geometry": {"coordinates":[-2.71228410144737,53.81331489069646],"type":"Point"}
}