{
  "type": "Feature",
  "properties": {
    "iso:country": "GB",
    "wof:name": "PR3 5DB",
    "wof:placetype": "postalcode"
  },
  "geometry": {"coordinates":[-2.712284,53.813315],"type":"Point"}
}
