{
  "type": "Feature",
  "properties": {
    "iso:country": "GB",
    "wof:name": "OX16 1PF",
    "wof:placetype": "postalcode"
  },
  "geometry": {"coordinates":[-1.350308,52.069008],"type":"Point"}
}
