{
  "type": "Feature",
  "properties": {
    "iso:country":"GB",
    "wof:name":"CF38 1LF",
    "wof:placetype":"postalcode"
},
  "geometry": {"coordinates":[-3.31293992220895,51.56713948500224],"type":"Point"}
}