{
  "type": "Feature",
  "properties": {
    "date:inception_lower": "1993-08-01",
    "date:inception_upper": "1993-08-01",
    "iso:country": "GB",
    "wof:name": "CF38 1LF",
    "wof:placetype": "postalcode"
  },
  "geometry": {"coordinates":[-3.31294,51.567139],"type":"Point"}
}
