{
  "type": "Feature",
  "properties": {
    "date:inception_lower": "1980-01-01",
    "date:inception_upper": "1980-01-01",
    "iso:country": "GB",
    "wof:name": "SA6 8AU",
    "wof:placetype": "postalcode"
  },
  "geometry": {"coordinates":[-3.926044,51.665304],"type":"Point"}
}
