{
  "type": "Feature",
  "properties": {
    "iso:country":"GB",
    "wof:name":"SA6 8AU",
    "wof:placetype":"postalcode"
},
  "geometry": {"coordinates":[-3.92598296527769,51.66530885884601],"type":"Point"}
}