{
  "type": "Feature",
  "properties": {
    "iso:country": "GB",
    "wof:name": "CW12 4FD",
    "wof:placetype": "postalcode"
  },
  "geometry": {"coordinates":[-2.233722,53.161005],"type":"Point"}
}
