{
  "type": "Feature",
  "properties": {
    "date:inception_lower":"1991-09-01",
    "date:inception_upper":"1991-09-30",
    "iso:country":"GB",
    "wof:name":"CW12 4FD",
    "wof:placetype":"postalcode"
},
  "geometry": {"coordinates":[-2.233768,53.160979],"type":"Point"}
}