{
  "type": "Feature",
  "properties": {
    "date:inception_lower": "1991-09-01",
    "date:inception_upper": "1991-09-01",
    "iso:country": "GB",
    "wof:name": "CW12 4FD",
    "wof:placetype": "postalcode"
  },
  "geometry": {"coordinates":[-2.233722,53.161005],"type":"Point"}
}
