{
  "type": "Feature",
  "properties": {
    "date:inception_lower":"2011-12-01",
    "date:inception_upper":"2011-12-31",
    "iso:country":"GB",
    "wof:name":"NE63 8SG",
    "wof:placetype":"postalcode"
},
  "geometry": {"coordinates":[-1.591988,55.187355],"type":"Point"}
}