{
  "type": "Feature",
  "properties": {
    "iso:country":"GB",
    "wof:name":"NE63 8SG",
    "wof:placetype":"postalcode"
},
  "geometry": {"coordinates":[-1.59198812718877,55.18735468329835],"type":"Point"}
}