{
  "type": "Feature",
  "properties": {
    "iso:country": "GB",
    "wof:name": "TW13 6QD",
    "wof:placetype": "postalcode"
  },
  "geometry": {"coordinates":[-0.38791,51.43758],"type":"Point"}
}
