{
  "type": "Feature",
  "properties": {
    "iso:country":"GB",
    "wof:name":"TW10 6AF",
    "wof:placetype":"postalcode"
},
  "geometry": {"coordinates":[-0.30296466909773,51.45736012266406],"type":"Point"}
}