{
  "type": "Feature",
  "properties": {
    "iso:country":"GB",
    "wof:name":"SY4 3EL",
    "wof:placetype":"postalcode"
},
  "geometry": {"coordinates":[-2.75073910391598,52.81105040628576],"type":"Point"}
}