{
  "type": "Feature",
  "properties": {
    "iso:country":"GB",
    "wof:name":"S63 7LZ",
    "wof:placetype":"postalcode"
},
  "geometry": {"coordinates":[-1.34098876522843,53.49934492486143],"type":"Point"}
}