{
  "type": "Feature",
  "properties": {
    "date:inception_lower": "1980-01-01",
    "date:inception_upper": "1980-01-01",
    "iso:country": "GB",
    "wof:name": "S63 7LZ",
    "wof:placetype": "postalcode"
  },
  "geometry": {"coordinates":[-1.340989,53.499345],"type":"Point"}
}
