{
  "type": "Feature",
  "properties": {
    "iso:country":"GB",
    "wof:name":"BH15 3JH",
    "wof:placetype":"postalcode"
},
  "geometry": {"coordinates":[-1.96549936991674,50.73603189244022],"type":"Point"}
}