{
  "type": "Feature",
  "properties": {
    "iso:country": "GB",
    "wof:name": "TN8 7DU",
    "wof:placetype": "postalcode"
  },
  "geometry": {"coordinates":[0.107712,51.149895],"type":"Point"}
}
