{
  "type": "Feature",
  "properties": {
    "iso:country":"GB",
    "wof:name":"TN8 7DU",
    "wof:placetype":"postalcode"
},
  "geometry": {"coordinates":[0.10771179670237,51.14989470115523],"type":"Point"}
}