{
  "type": "Feature",
  "properties": {
    "iso:country":"GB",
    "wof:name":"BH23 4NL",
    "wof:placetype":"postalcode"
},
  "geometry": {"coordinates":[-1.71672454329723,50.7472940297623],"type":"Point"}
}