{
  "type": "Feature",
  "properties": {
    "iso:country": "GB",
    "wof:name": "BH23 4NL",
    "wof:placetype": "postalcode"
  },
  "geometry": {"coordinates":[-1.716725,50.747294],"type":"Point"}
}
