{
  "type": "Feature",
  "properties": {
    "date:inception_lower": "1995-12-01",
    "date:inception_upper": "1995-12-01",
    "iso:country": "GB",
    "wof:name": "ME2 3QP",
    "wof:placetype": "postalcode"
  },
  "geometry": {"coordinates":[0.47957,51.403694],"type":"Point"}
}
