{
  "type": "Feature",
  "properties": {
    "iso:country": "GB",
    "wof:name": "ME2 3QP",
    "wof:placetype": "postalcode"
  },
  "geometry": {"coordinates":[0.47957,51.403694],"type":"Point"}
}
