{
  "type": "Feature",
  "properties": {
    "iso:country":"GB",
    "wof:name":"ME2 3QP",
    "wof:placetype":"postalcode"
},
  "geometry": {"coordinates":[0.47956976833189,51.4036943016774],"type":"Point"}
}