{
  "type": "Feature",
  "properties": {
    "iso:country":"GB",
    "wof:name":"LE19 2TR",
    "wof:placetype":"postalcode"
},
  "geometry": {"coordinates":[-1.21864453853108,52.57060228756642],"type":"Point"}
}