{
  "type": "Feature",
  "properties": {
    "iso:country": "GB",
    "wof:name": "LE19 2TR",
    "wof:placetype": "postalcode"
  },
  "geometry": {"coordinates":[-1.218664,52.57063],"type":"Point"}
}
