{
  "type": "Feature",
  "properties": {
    "iso:country": "GB",
    "wof:name": "HP21 8BA",
    "wof:placetype": "postalcode"
  },
  "geometry": {"coordinates":[-0.80723,51.798623],"type":"Point"}
}
