{
  "type": "Feature",
  "properties": {
    "iso:country":"GB",
    "wof:name":"LN6 7PU",
    "wof:placetype":"postalcode"
},
  "geometry": {"coordinates":[-0.56010388141357,53.20230174236108],"type":"Point"}
}