{
  "type": "Feature",
  "properties": {
    "iso:country":"GB",
    "wof:name":"L17 7BT",
    "wof:placetype":"postalcode"
},
  "geometry": {"coordinates":[-2.95367294159595,53.37976139367309],"type":"Point"}
}