{
  "type": "Feature",
  "properties": {
    "date:inception_lower": "1980-01-01",
    "date:inception_upper": "1980-01-01",
    "iso:country": "GB",
    "wof:name": "L17 7BT",
    "wof:placetype": "postalcode"
  },
  "geometry": {"coordinates":[-2.953629,53.379824],"type":"Point"}
}
