{
  "type": "Feature",
  "properties": {
    "iso:country": "GB",
    "wof:name": "CF32 8TG",
    "wof:placetype": "postalcode"
  },
  "geometry": {"coordinates":[-3.585781,51.567545],"type":"Point"}
}
