{
  "type": "Feature",
  "properties": {
    "iso:country":"GB",
    "wof:name":"CF32 8TG",
    "wof:placetype":"postalcode"
},
  "geometry": {"coordinates":[-3.58578087706828,51.56754543559727],"type":"Point"}
}