{
  "type": "Feature",
  "properties": {
    "date:inception_lower": "2013-11-01",
    "date:inception_upper": "2013-11-01",
    "iso:country": "GB",
    "wof:name": "YO61 3FS",
    "wof:placetype": "postalcode"
  },
  "geometry": {"coordinates":[-1.194568,54.112961],"type":"Point"}
}
