{
  "type": "Feature",
  "properties": {
    "iso:country": "GB",
    "wof:name": "NG11 0JF",
    "wof:placetype": "postalcode"
  },
  "geometry": {"coordinates":[-1.20495,52.867975],"type":"Point"}
}
