{
  "type": "Feature",
  "properties": {
    "date:inception_lower":"2009-03-01",
    "date:inception_upper":"2009-03-31",
    "iso:country":"GB",
    "wof:name":"NG11 0JF",
    "wof:placetype":"postalcode"
},
  "geometry": {"coordinates":[-1.20495,52.867975],"type":"Point"}
}