{
  "type": "Feature",
  "properties": {
    "iso:country":"GB",
    "wof:name":"TN3 0RQ",
    "wof:placetype":"postalcode"
},
  "geometry": {"coordinates":[0.20100495137611,51.13860687562973],"type":"Point"}
}