{
  "type": "Feature",
  "properties": {
    "iso:country": "GB",
    "wof:name": "CT1 1AW",
    "wof:placetype": "postalcode"
  },
  "geometry": {"coordinates":[1.10722,51.280924],"type":"Point"}
}
