{
  "type": "Feature",
  "properties": {
    "date:inception_lower": "1986-07-01",
    "date:inception_upper": "1986-07-01",
    "iso:country": "GB",
    "wof:name": "CT1 1AW",
    "wof:placetype": "postalcode"
  },
  "geometry": {"coordinates":[1.10722,51.280924],"type":"Point"}
}
