{
  "type": "Feature",
  "properties": {
    "iso:country":"GB",
    "wof:name":"CA11 9LD",
    "wof:placetype":"postalcode"
},
  "geometry": {"coordinates":[-2.75359961279605,54.67129985655899],"type":"Point"}
}