{
  "type": "Feature",
  "properties": {
    "iso:country":"GB",
    "wof:name":"W4 2HW",
    "wof:placetype":"postalcode"
},
  "geometry": {"coordinates":[-0.25396326840371,51.49177404947478],"type":"Point"}
}