{
  "type": "Feature",
  "properties": {
    "iso:country": "GB",
    "wof:name": "W4 2HW",
    "wof:placetype": "postalcode"
  },
  "geometry": {"coordinates":[-0.253963,51.491774],"type":"Point"}
}
