{
  "type": "Feature",
  "properties": {
    "iso:country":"GB",
    "wof:name":"LL45 2HU",
    "wof:placetype":"postalcode"
},
  "geometry": {"coordinates":[-4.11151622064539,52.82998774831533],"type":"Point"}
}