{
  "type": "Feature",
  "properties": {
    "iso:country":"GB",
    "wof:name":"TS10 4SJ",
    "wof:placetype":"postalcode"
},
  "geometry": {"coordinates":[-1.07334150276725,54.5932099882079],"type":"Point"}
}