{
  "type": "Feature",
  "properties": {
    "date:inception_lower": "1999-06-01",
    "date:inception_upper": "1999-06-01",
    "iso:country": "GB",
    "wof:name": "CV7 8RA",
    "wof:placetype": "postalcode"
  },
  "geometry": {"coordinates":[-1.576518,52.456207],"type":"Point"}
}
