{
  "type": "Feature",
  "properties": {
    "iso:country": "GB",
    "wof:name": "CV7 8RA",
    "wof:placetype": "postalcode"
  },
  "geometry": {"coordinates":[-1.576689,52.456137],"type":"Point"}
}
