{
  "type": "Feature",
  "properties": {
    "iso:country":"GB",
    "wof:name":"CV7 8RA",
    "wof:placetype":"postalcode"
},
  "geometry": {"coordinates":[-1.57668954334119,52.45613748898618],"type":"Point"}
}