{
  "type": "Feature",
  "properties": {
    "iso:country":"GB",
    "wof:name":"GL14 2TZ",
    "wof:placetype":"postalcode"
},
  "geometry": {"coordinates":[-2.49944882335167,51.79105637118926],"type":"Point"}
}