{
  "type": "Feature",
  "properties": {
    "date:inception_lower": "2011-03-01",
    "date:inception_upper": "2011-03-01",
    "iso:country": "GB",
    "wof:name": "PE19 6GQ",
    "wof:placetype": "postalcode"
  },
  "geometry": {"coordinates":[-0.243776,52.230622],"type":"Point"}
}
