{
  "type": "Feature",
  "properties": {
    "iso:country": "GB",
    "wof:name": "PE32 1SE",
    "wof:placetype": "postalcode"
  },
  "geometry": {"coordinates":[0.462753,52.706847],"type":"Point"}
}
