{
  "type": "Feature",
  "properties": {
    "iso:country":"GB",
    "wof:name":"SK10 4TA",
    "wof:placetype":"postalcode"
},
  "geometry": {"coordinates":[-2.25661102622439,53.26193976408904],"type":"Point"}
}