{
  "type": "Feature",
  "properties": {
    "date:inception_lower": "1980-01-01",
    "date:inception_upper": "1980-01-01",
    "iso:country": "GB",
    "wof:name": "SK10 4TA",
    "wof:placetype": "postalcode"
  },
  "geometry": {"coordinates":[-2.256611,53.26194],"type":"Point"}
}
