{
  "type": "Feature",
  "properties": {
    "iso:country":"GB",
    "wof:name":"N2 0DW",
    "wof:placetype":"postalcode"
},
  "geometry": {"coordinates":[-0.18027762076518,51.5858566273259],"type":"Point"}
}