{
  "type": "Feature",
  "properties": {
    "date:inception_lower": "1980-01-01",
    "date:inception_upper": "1980-01-01",
    "iso:country": "GB",
    "wof:name": "N2 0DW",
    "wof:placetype": "postalcode"
  },
  "geometry": {"coordinates":[-0.180269,51.585806],"type":"Point"}
}
