{
  "type": "Feature",
  "properties": {
    "iso:country": "GB",
    "wof:name": "PH12 8TB",
    "wof:placetype": "postalcode"
  },
  "geometry": {"coordinates":[-3.148177,56.557794],"type":"Point"}
}
