{
  "type": "Feature",
  "properties": {
    "iso:country":"GB",
    "wof:name":"KA8 8LD",
    "wof:placetype":"postalcode"
},
  "geometry": {"coordinates":[-4.62450807120417,55.47493403649233],"type":"Point"}
}