{
  "type": "Feature",
  "properties": {
    "iso:country": "GB",
    "wof:name": "KA8 8LD",
    "wof:placetype": "postalcode"
  },
  "geometry": {"coordinates":[-4.624508,55.474934],"type":"Point"}
}
