{
  "type": "Feature",
  "properties": {
    "iso:country":"GB",
    "wof:name":"NP23 7RN",
    "wof:placetype":"postalcode"
},
  "geometry": {"coordinates":[-3.18379999042305,51.74155819592342],"type":"Point"}
}