{
  "type": "Feature",
  "properties": {
    "iso:country":"GB",
    "wof:name":"TW7 7BB",
    "wof:placetype":"postalcode"
},
  "geometry": {"coordinates":[-0.32790743001448,51.46726840135907],"type":"Point"}
}