{
  "type": "Feature",
  "properties": {
    "iso:country": "GB",
    "wof:name": "TW7 7BB",
    "wof:placetype": "postalcode"
  },
  "geometry": {"coordinates":[-0.327907,51.467268],"type":"Point"}
}
