{
  "type": "Feature",
  "properties": {
    "iso:country":"GB",
    "wof:name":"CT2 7EN",
    "wof:placetype":"postalcode"
},
  "geometry": {"coordinates":[1.07527896338855,51.28648090335603],"type":"Point"}
}