{
  "type": "Feature",
  "properties": {
    "iso:country":"GB",
    "wof:name":"M16 9FX",
    "wof:placetype":"postalcode"
},
  "geometry": {"coordinates":[-2.27511740627387,53.46347777399685],"type":"Point"}
}