{
  "type": "Feature",
  "properties": {
    "iso:country":"GB",
    "wof:name":"SK10 2BH",
    "wof:placetype":"postalcode"
},
  "geometry": {"coordinates":[-2.11818116662551,53.2672812207808],"type":"Point"}
}