{
  "type": "Feature",
  "properties": {
    "iso:country": "GB",
    "wof:name": "SK10 2BH",
    "wof:placetype": "postalcode"
  },
  "geometry": {"coordinates":[-2.118181,53.267281],"type":"Point"}
}
