{
  "type": "Feature",
  "properties": {
    "iso:country":"GB",
    "wof:name":"S5 0JN",
    "wof:placetype":"postalcode"
},
  "geometry": {"coordinates":[-1.45067715092245,53.43033646401977],"type":"Point"}
}