{
  "type": "Feature",
  "properties": {
    "date:inception_lower": "1980-01-01",
    "date:inception_upper": "1980-01-01",
    "iso:country": "GB",
    "wof:name": "SM1 1JG",
    "wof:placetype": "postalcode"
  },
  "geometry": {"coordinates":[-0.193801,51.363258],"type":"Point"}
}
