{
  "type": "Feature",
  "properties": {
    "iso:country":"GB",
    "wof:name":"DL13 2RL",
    "wof:placetype":"postalcode"
},
  "geometry": {"coordinates":[-1.95709827066718,54.72690997013565],"type":"Point"}
}