{
  "type": "Feature",
  "properties": {
    "iso:country": "GB",
    "wof:name": "PA20 0EL",
    "wof:placetype": "postalcode"
  },
  "geometry": {"coordinates":[-5.062725,55.8344],"type":"Point"}
}
