{
  "type": "Feature",
  "properties": {
    "iso:country": "GB",
    "wof:name": "M40 5AG",
    "wof:placetype": "postalcode"
  },
  "geometry": {"coordinates":[-2.196517,53.504486],"type":"Point"}
}
