{
  "type": "Feature",
  "properties": {
    "date:inception_lower": "2014-04-01",
    "date:inception_upper": "2014-04-01",
    "iso:country": "GB",
    "wof:name": "M40 5AG",
    "wof:placetype": "postalcode"
  },
  "geometry": {"coordinates":[-2.196517,53.504486],"type":"Point"}
}
