{
  "type": "Feature",
  "properties": {
    "date:inception_lower": "2001-12-01",
    "date:inception_upper": "2001-12-01",
    "iso:country": "GB",
    "wof:name": "KT1 1HU",
    "wof:placetype": "postalcode"
  },
  "geometry": {"coordinates":[-0.30682,51.409558],"type":"Point"}
}
