{
  "type": "Feature",
  "properties": {
    "iso:country":"GB",
    "wof:name":"KT1 1HU",
    "wof:placetype":"postalcode"
},
  "geometry": {"coordinates":[-0.30682002328189,51.40955811311191],"type":"Point"}
}