{
  "type": "Feature",
  "properties": {
    "iso:country":"GB",
    "wof:name":"IV9 8RW",
    "wof:placetype":"postalcode"
},
  "geometry": {"coordinates":[-4.18450011382058,57.56904335762082],"type":"Point"}
}