{
  "type": "Feature",
  "properties": {
    "iso:country":"GB",
    "wof:name":"SG12 7SE",
    "wof:placetype":"postalcode"
},
  "geometry": {"coordinates":[-0.02102876549433,51.81870008733294],"type":"Point"}
}