{
  "type": "Feature",
  "properties": {
    "date:inception_lower": "2006-07-01",
    "date:inception_upper": "2006-07-01",
    "iso:country": "GB",
    "wof:name": "SG12 7SE",
    "wof:placetype": "postalcode"
  },
  "geometry": {"coordinates":[-0.021029,51.8187],"type":"Point"}
}
