{
  "type": "Feature",
  "properties": {
    "date:inception_lower": "1995-12-01",
    "date:inception_upper": "1995-12-01",
    "iso:country": "GB",
    "wof:name": "TR11 3DZ",
    "wof:placetype": "postalcode"
  },
  "geometry": {"coordinates":[-5.0737,50.151858],"type":"Point"}
}
