{
  "type": "Feature",
  "properties": {
    "date:inception_lower": "1980-01-01",
    "date:inception_upper": "1980-01-01",
    "iso:country": "GB",
    "wof:name": "YO13 9EX",
    "wof:placetype": "postalcode"
  },
  "geometry": {"coordinates":[-0.474311,54.25543],"type":"Point"}
}
