{
  "type": "Feature",
  "properties": {
    "iso:country":"GB",
    "wof:name":"YO13 9EX",
    "wof:placetype":"postalcode"
},
  "geometry": {"coordinates":[-0.47431056892454,54.2554297945475],"type":"Point"}
}