{
  "type": "Feature",
  "properties": {
    "iso:country":"GB",
    "wof:name":"WF1 1RF",
    "wof:placetype":"postalcode"
},
  "geometry": {"coordinates":[-1.4972730317081,53.67886474592877],"type":"Point"}
}