{
  "type": "Feature",
  "properties": {
    "date:inception_lower": "2000-12-01",
    "date:inception_upper": "2000-12-01",
    "iso:country": "GB",
    "wof:name": "WF1 1RF",
    "wof:placetype": "postalcode"
  },
  "geometry": {"coordinates":[-1.497273,53.678865],"type":"Point"}
}
