{
  "type": "Feature",
  "properties": {
    "iso:country": "GB",
    "wof:name": "WF1 1RF",
    "wof:placetype": "postalcode"
  },
  "geometry": {"coordinates":[-1.497273,53.678865],"type":"Point"}
}
