{
  "type": "Feature",
  "properties": {
    "iso:country": "GB",
    "wof:name": "BL3 3RA",
    "wof:placetype": "postalcode"
  },
  "geometry": {"coordinates":[-2.468132,53.557085],"type":"Point"}
}
