{
  "type": "Feature",
  "properties": {
    "iso:country": "GB",
    "wof:name": "DN32 9SS",
    "wof:placetype": "postalcode"
  },
  "geometry": {"coordinates":[-0.064277,53.554413],"type":"Point"}
}
