{
  "type": "Feature",
  "properties": {
    "iso:country":"GB",
    "wof:name":"CR5 3AL",
    "wof:placetype":"postalcode"
},
  "geometry": {"coordinates":[-0.1577804056459,51.31573742364711],"type":"Point"}
}