{
  "type": "Feature",
  "properties": {
    "iso:country":"GB",
    "wof:name":"ME1 2RE",
    "wof:placetype":"postalcode"
},
  "geometry": {"coordinates":[0.51313070582505,51.36856082522772],"type":"Point"}
}