{
  "type": "Feature",
  "properties": {
    "date:inception_lower":"2004-03-01",
    "date:inception_upper":"2004-03-31",
    "iso:country":"GB",
    "wof:name":"TR13 8GJ",
    "wof:placetype":"postalcode"
},
  "geometry": {"coordinates":[-5.274314,50.102801],"type":"Point"}
}