{
  "type": "Feature",
  "properties": {
    "iso:country":"GB",
    "wof:name":"TR13 8GJ",
    "wof:placetype":"postalcode"
},
  "geometry": {"coordinates":[-5.2743141988144,50.1028014258023],"type":"Point"}
}