{
  "type": "Feature",
  "properties": {
    "date:inception_lower":"1994-05-01",
    "date:inception_upper":"1994-05-31",
    "iso:country":"GB",
    "wof:name":"M6 6QL",
    "wof:placetype":"postalcode"
},
  "geometry": {"coordinates":[-2.279645,53.494648],"type":"Point"}
}