{
  "type": "Feature",
  "properties": {
    "iso:country":"GB",
    "wof:name":"WR7 4AA",
    "wof:placetype":"postalcode"
},
  "geometry": {"coordinates":[-2.11746331818591,52.2069620663674],"type":"Point"}
}