{
  "type": "Feature",
  "properties": {
    "date:inception_lower": "2024-10-01",
    "date:inception_upper": "2024-10-01",
    "iso:country": "GB",
    "wof:name": "BS24 7PW",
    "wof:placetype": "postalcode"
  },
  "geometry": {"coordinates":[-2.905721,51.33694],"type":"Point"}
}
