{
  "type": "Feature",
  "properties": {
    "iso:country":"GB",
    "wof:name":"HD5 8EA",
    "wof:placetype":"postalcode"
},
  "geometry": {"coordinates":[-1.75048944217341,53.64272688477617],"type":"Point"}
}