{
  "type": "Feature",
  "properties": {
    "iso:country":"GB",
    "wof:name":"UB2 5HA",
    "wof:placetype":"postalcode"
},
  "geometry": {"coordinates":[-0.38411238680944,51.50072540213466],"type":"Point"}
}