{
  "type": "Feature",
  "properties": {
    "iso:country":"GB",
    "wof:name":"M28 1EY",
    "wof:placetype":"postalcode"
},
  "geometry": {"coordinates":[-2.40966319004908,53.5020031709599],"type":"Point"}
}