{
  "type": "Feature",
  "properties": {
    "iso:country": "GB",
    "wof:name": "NR29 3AP",
    "wof:placetype": "postalcode"
  },
  "geometry": {"coordinates":[1.554923,52.688802],"type":"Point"}
}
