{
  "type": "Feature",
  "properties": {
    "iso:country":"GB",
    "wof:name":"NR29 3AP",
    "wof:placetype":"postalcode"
},
  "geometry": {"coordinates":[1.55460858540533,52.68846901359449],"type":"Point"}
}