{
  "type": "Feature",
  "properties": {
    "iso:country": "GB",
    "wof:name": "G23 5AL",
    "wof:placetype": "postalcode"
  },
  "geometry": {"coordinates":[-4.279078,55.897754],"type":"Point"}
}
