{
  "type": "Feature",
  "properties": {
    "iso:country":"GB",
    "wof:name":"G23 5AL",
    "wof:placetype":"postalcode"
},
  "geometry": {"coordinates":[-4.27907781794864,55.89775379543034],"type":"Point"}
}