{
  "type": "Feature",
  "properties": {
    "iso:country":"GB",
    "wof:name":"HP4 3SF",
    "wof:placetype":"postalcode"
},
  "geometry": {"coordinates":[-0.59767154871128,51.77352573218683],"type":"Point"}
}