{
  "type": "Feature",
  "properties": {
    "iso:country": "GB",
    "wof:name": "HP4 3SF",
    "wof:placetype": "postalcode"
  },
  "geometry": {"coordinates":[-0.597672,51.773526],"type":"Point"}
}
