{
  "type": "Feature",
  "properties": {
    "iso:country":"GB",
    "wof:name":"BA12 0AB",
    "wof:placetype":"postalcode"
},
  "geometry": {"coordinates":[-2.17894676452239,51.20891159055751],"type":"Point"}
}