{
  "type": "Feature",
  "properties": {
    "date:inception_lower":"2000-06-01",
    "date:inception_upper":"2000-06-30",
    "iso:country":"GB",
    "wof:name":"HP4 3AW",
    "wof:placetype":"postalcode"
},
  "geometry": {"coordinates":[-0.564588,51.757778],"type":"Point"}
}