{
  "type": "Feature",
  "properties": {
    "iso:country": "GB",
    "wof:name": "HP4 3AW",
    "wof:placetype": "postalcode"
  },
  "geometry": {"coordinates":[-0.564588,51.757778],"type":"Point"}
}
