{
  "type": "Feature",
  "properties": {
    "iso:country":"GB",
    "wof:name":"HP4 3AW",
    "wof:placetype":"postalcode"
},
  "geometry": {"coordinates":[-0.5645882394429,51.75777760736501],"type":"Point"}
}