{
  "type": "Feature",
  "properties": {
    "date:inception_lower": "2014-09-01",
    "date:inception_upper": "2014-09-01",
    "iso:country": "GB",
    "wof:name": "RM15 4EF",
    "wof:placetype": "postalcode"
  },
  "geometry": {"coordinates":[0.261097,51.501751],"type":"Point"}
}
