{
  "type": "Feature",
  "properties": {
    "iso:country":"GB",
    "wof:name":"ME16 9HP",
    "wof:placetype":"postalcode"
},
  "geometry": {"coordinates":[0.47250211000635,51.2696329735051],"type":"Point"}
}