{
  "type": "Feature",
  "properties": {
    "date:inception_lower": "1980-01-01",
    "date:inception_upper": "1980-01-01",
    "iso:country": "GB",
    "wof:name": "KT20 5DH",
    "wof:placetype": "postalcode"
  },
  "geometry": {"coordinates":[-0.243409,51.293483],"type":"Point"}
}
