{
  "type": "Feature",
  "properties": {
    "iso:country":"GB",
    "wof:name":"KT20 5DH",
    "wof:placetype":"postalcode"
},
  "geometry": {"coordinates":[-0.24340953862443,51.29348334866361],"type":"Point"}
}