{
  "type": "Feature",
  "properties": {
    "iso:country": "GB",
    "wof:name": "DY13 9JT",
    "wof:placetype": "postalcode"
  },
  "geometry": {"coordinates":[-2.258412,52.352398],"type":"Point"}
}
