{
  "type": "Feature",
  "properties": {
    "iso:country":"GB",
    "wof:name":"LN7 6UT",
    "wof:placetype":"postalcode"
},
  "geometry": {"coordinates":[-0.31612107691677,53.49618782951067],"type":"Point"}
}