{
  "type": "Feature",
  "properties": {
    "iso:country":"GB",
    "wof:name":"GL54 5DU",
    "wof:placetype":"postalcode"
},
  "geometry": {"coordinates":[-1.93676456641264,51.99071848601638],"type":"Point"}
}