{
  "type": "Feature",
  "properties": {
    "iso:country": "GB",
    "wof:name": "GL54 5DU",
    "wof:placetype": "postalcode"
  },
  "geometry": {"coordinates":[-1.936654,51.990719],"type":"Point"}
}
