{
  "type": "Feature",
  "properties": {
    "iso:country":"GB",
    "wof:name":"ME3 7RB",
    "wof:placetype":"postalcode"
},
  "geometry": {"coordinates":[0.49939239141024,51.45998586716804],"type":"Point"}
}