{
  "type": "Feature",
  "properties": {
    "iso:country":"GB",
    "wof:name":"EH6 7JW",
    "wof:placetype":"postalcode"
},
  "geometry": {"coordinates":[-3.16205068749428,55.97348721453137],"type":"Point"}
}