{
  "type": "Feature",
  "properties": {
    "iso:country": "GB",
    "wof:name": "EH6 7JW",
    "wof:placetype": "postalcode"
  },
  "geometry": {"coordinates":[-3.162085,55.97349],"type":"Point"}
}
