{
  "type": "Feature",
  "properties": {
    "date:inception_lower": "2013-04-01",
    "date:inception_upper": "2013-04-01",
    "iso:country": "GB",
    "wof:name": "EH6 7JW",
    "wof:placetype": "postalcode"
  },
  "geometry": {"coordinates":[-3.162085,55.97349],"type":"Point"}
}
