{
  "type": "Feature",
  "properties": {
    "iso:country":"GB",
    "wof:name":"NN18 0LZ",
    "wof:placetype":"postalcode"
},
  "geometry": {"coordinates":[-0.72786339785043,52.48330260087852],"type":"Point"}
}