{
  "type": "Feature",
  "properties": {
    "iso:country":"GB",
    "wof:name":"CB5 8TX",
    "wof:placetype":"postalcode"
},
  "geometry": {"coordinates":[0.17115618583416,52.21482409598519],"type":"Point"}
}