{
  "type": "Feature",
  "properties": {
    "iso:country":"GB",
    "wof:name":"CR0 0TN",
    "wof:placetype":"postalcode"
},
  "geometry": {"coordinates":[-0.01808182056147,51.35102864003336],"type":"Point"}
}