{
  "type": "Feature",
  "properties": {
    "iso:country":"GB",
    "wof:name":"PO30 2RA",
    "wof:placetype":"postalcode"
},
  "geometry": {"coordinates":[-1.28750727259228,50.70333126747596],"type":"Point"}
}