{
  "type": "Feature",
  "properties": {
    "date:inception_lower": "1995-12-01",
    "date:inception_upper": "1995-12-01",
    "iso:country": "GB",
    "wof:name": "PO30 2RA",
    "wof:placetype": "postalcode"
  },
  "geometry": {"coordinates":[-1.287507,50.703331],"type":"Point"}
}
