{
  "type": "Feature",
  "properties": {
    "iso:country":"GB",
    "wof:name":"KA12 9HY",
    "wof:placetype":"postalcode"
},
  "geometry": {"coordinates":[-4.65964729262009,55.6261312323078],"type":"Point"}
}