{
  "type": "Feature",
  "properties": {
    "date:inception_lower":"1980-01-01",
    "date:inception_upper":"1980-01-31",
    "iso:country":"GB",
    "wof:name":"KA12 9HY",
    "wof:placetype":"postalcode"
},
  "geometry": {"coordinates":[-4.659647,55.626131],"type":"Point"}
}