{
  "type": "Feature",
  "properties": {
    "date:inception_lower": "1980-01-01",
    "date:inception_upper": "1980-01-01",
    "iso:country": "GB",
    "wof:name": "WR9 7PN",
    "wof:placetype": "postalcode"
  },
  "geometry": {"coordinates":[-2.115294,52.290367],"type":"Point"}
}
