{
  "type": "Feature",
  "properties": {
    "iso:country":"GB",
    "wof:name":"WR9 7PN",
    "wof:placetype":"postalcode"
},
  "geometry": {"coordinates":[-2.11529452299322,52.2903673777319],"type":"Point"}
}