{
  "type": "Feature",
  "properties": {
    "iso:country":"GB",
    "wof:name":"DN20 0LH",
    "wof:placetype":"postalcode"
},
  "geometry": {"coordinates":[-0.54657573166002,53.56634356455477],"type":"Point"}
}