{
  "type": "Feature",
  "properties": {
    "iso:country":"GB",
    "wof:name":"CB1 3UJ",
    "wof:placetype":"postalcode"
},
  "geometry": {"coordinates":[0.15731041915844,52.19433361971016],"type":"Point"}
}