{
  "type": "Feature",
  "properties": {
    "date:inception_lower": "1991-09-01",
    "date:inception_upper": "1991-09-01",
    "iso:country": "GB",
    "wof:name": "CB1 3UJ",
    "wof:placetype": "postalcode"
  },
  "geometry": {"coordinates":[0.157572,52.194325],"type":"Point"}
}
