{
  "type": "Feature",
  "properties": {
    "iso:country":"GB",
    "wof:name":"LE8 6EY",
    "wof:placetype":"postalcode"
},
  "geometry": {"coordinates":[-1.17473915596569,52.56169204156654],"type":"Point"}
}