{
  "type": "Feature",
  "properties": {
    "date:inception_lower": "1994-05-01",
    "date:inception_upper": "1994-05-01",
    "iso:country": "GB",
    "wof:name": "LE8 6EY",
    "wof:placetype": "postalcode"
  },
  "geometry": {"coordinates":[-1.174739,52.561692],"type":"Point"}
}
