{
  "type": "Feature",
  "properties": {
    "iso:country": "GB",
    "wof:name": "M41 5SZ",
    "wof:placetype": "postalcode"
  },
  "geometry": {"coordinates":[-2.365518,53.452674],"type":"Point"}
}
