{
  "type": "Feature",
  "properties": {
    "iso:country":"GB",
    "wof:name":"M41 5SZ",
    "wof:placetype":"postalcode"
},
  "geometry": {"coordinates":[-2.36551851489674,53.45267373141264],"type":"Point"}
}