{
  "type": "Feature",
  "properties": {
    "iso:country":"GB",
    "wof:name":"S17 4QG",
    "wof:placetype":"postalcode"
},
  "geometry": {"coordinates":[-1.50544755739524,53.31988892784389],"type":"Point"}
}