{
  "type": "Feature",
  "properties": {
    "date:inception_lower": "1980-01-01",
    "date:inception_upper": "1980-01-01",
    "iso:country": "GB",
    "wof:name": "S17 4QG",
    "wof:placetype": "postalcode"
  },
  "geometry": {"coordinates":[-1.505448,53.319889],"type":"Point"}
}
