{
  "type": "Feature",
  "properties": {
    "iso:country":"GB",
    "wof:name":"UB5 5EY",
    "wof:placetype":"postalcode"
},
  "geometry": {"coordinates":[-0.37108438005628,51.54849183088679],"type":"Point"}
}