{
  "type": "Feature",
  "properties": {
    "iso:country":"GB",
    "wof:name":"ME5 0AA",
    "wof:placetype":"postalcode"
},
  "geometry": {"coordinates":[0.54527959236814,51.36844211055353],"type":"Point"}
}