{
  "type": "Feature",
  "properties": {
    "iso:country": "GB",
    "wof:name": "ME5 0AA",
    "wof:placetype": "postalcode"
  },
  "geometry": {"coordinates":[0.54528,51.368442],"type":"Point"}
}
