{
  "type": "Feature",
  "properties": {
    "iso:country":"GB",
    "wof:name":"NG11 8SG",
    "wof:placetype":"postalcode"
},
  "geometry": {"coordinates":[-1.19405303923782,52.90528959489547],"type":"Point"}
}