{
  "type": "Feature",
  "properties": {
    "iso:country":"GB",
    "wof:name":"HR1 1HE",
    "wof:placetype":"postalcode"
},
  "geometry": {"coordinates":[-2.71257674182658,52.06973836202053],"type":"Point"}
}