{
  "type": "Feature",
  "properties": {
    "iso:country": "GB",
    "wof:name": "HR1 1HE",
    "wof:placetype": "postalcode"
  },
  "geometry": {"coordinates":[-2.712577,52.069738],"type":"Point"}
}
