{
  "type": "Feature",
  "properties": {
    "iso:country":"GB",
    "wof:name":"GU17 0BL",
    "wof:placetype":"postalcode"
},
  "geometry": {"coordinates":[-0.8046619608082,51.33203895275928],"type":"Point"}
}