{
  "type": "Feature",
  "properties": {
    "iso:country": "GB",
    "wof:name": "GU17 0BL",
    "wof:placetype": "postalcode"
  },
  "geometry": {"coordinates":[-0.804662,51.332039],"type":"Point"}
}
