{
  "type": "Feature",
  "properties": {
    "iso:country":"GB",
    "wof:name":"NR24 2PL",
    "wof:placetype":"postalcode"
},
  "geometry": {"coordinates":[1.02335033964829,52.89406757340439],"type":"Point"}
}