{
  "type": "Feature",
  "properties": {
    "iso:country": "GB",
    "wof:name": "NR24 2PL",
    "wof:placetype": "postalcode"
  },
  "geometry": {"coordinates":[1.02335,52.894068],"type":"Point"}
}
