{
  "type": "Feature",
  "properties": {
    "date:inception_lower": "1980-01-01",
    "date:inception_upper": "1980-01-01",
    "iso:country": "GB",
    "wof:name": "NR24 2PL",
    "wof:placetype": "postalcode"
  },
  "geometry": {"coordinates":[1.02335,52.894068],"type":"Point"}
}
