{
  "type": "Feature",
  "properties": {
    "iso:country":"GB",
    "wof:name":"NG24 3ER",
    "wof:placetype":"postalcode"
},
  "geometry": {"coordinates":[-0.79234241084312,53.06104020265187],"type":"Point"}
}