{
  "type": "Feature",
  "properties": {
    "iso:country":"GB",
    "wof:name":"SA18 1EL",
    "wof:placetype":"postalcode"
},
  "geometry": {"coordinates":[-3.88554560382443,51.79491397718473],"type":"Point"}
}