{
  "type": "Feature",
  "properties": {
    "iso:country": "GB",
    "wof:name": "NN4 5EZ",
    "wof:placetype": "postalcode"
  },
  "geometry": {"coordinates":[-0.891778,52.185007],"type":"Point"}
}
