{
  "type": "Feature",
  "properties": {
    "iso:country":"GB",
    "wof:name":"HA8 5RS",
    "wof:placetype":"postalcode"
},
  "geometry": {"coordinates":[-0.27912054109628,51.60055715992733],"type":"Point"}
}