{
  "type": "Feature",
  "properties": {
    "iso:country":"GB",
    "wof:name":"WN7 5PL",
    "wof:placetype":"postalcode"
},
  "geometry": {"coordinates":[-2.53223161242093,53.51769934019451],"type":"Point"}
}