{
  "type": "Feature",
  "properties": {
    "iso:country":"GB",
    "wof:name":"L25 6EE",
    "wof:placetype":"postalcode"
},
  "geometry": {"coordinates":[-2.88166045488913,53.38104321171129],"type":"Point"}
}