{
  "type": "Feature",
  "properties": {
    "iso:country": "GB",
    "wof:name": "L25 6EE",
    "wof:placetype": "postalcode"
  },
  "geometry": {"coordinates":[-2.88166,53.381043],"type":"Point"}
}
