{
  "type": "Feature",
  "properties": {
    "iso:country":"GB",
    "wof:name":"WF3 1WG",
    "wof:placetype":"postalcode"
},
  "geometry": {"coordinates":[-1.57185284019441,53.71871137399533],"type":"Point"}
}