{
  "type": "Feature",
  "properties": {
    "iso:country":"GB",
    "wof:name":"TW1 3HE",
    "wof:placetype":"postalcode"
},
  "geometry": {"coordinates":[-0.32732970083107,51.44959912530195],"type":"Point"}
}