{
  "type": "Feature",
  "properties": {
    "iso:country": "GB",
    "wof:name": "DA15 8QN",
    "wof:placetype": "postalcode"
  },
  "geometry": {"coordinates":[0.093907,51.450143],"type":"Point"}
}
