{
  "type": "Feature",
  "properties": {
    "iso:country":"GB",
    "wof:name":"DA15 8QN",
    "wof:placetype":"postalcode"
},
  "geometry": {"coordinates":[0.09390652522622,51.45014279485348],"type":"Point"}
}