{
  "type": "Feature",
  "properties": {
    "iso:country": "GB",
    "wof:name": "NP12 3PB",
    "wof:placetype": "postalcode"
  },
  "geometry": {"coordinates":[-3.215889,51.665206],"type":"Point"}
}
