{
  "type": "Feature",
  "properties": {
    "iso:country":"GB",
    "wof:name":"NP12 3PB",
    "wof:placetype":"postalcode"
},
  "geometry": {"coordinates":[-3.21588875103504,51.66520637187433],"type":"Point"}
}