{
  "type": "Feature",
  "properties": {
    "date:inception_lower":"2000-06-01",
    "date:inception_upper":"2000-06-30",
    "iso:country":"GB",
    "wof:name":"NP12 3PB",
    "wof:placetype":"postalcode"
},
  "geometry": {"coordinates":[-3.215889,51.665206],"type":"Point"}
}