{
  "type": "Feature",
  "properties": {
    "iso:country": "GB",
    "wof:name": "SW19 3JE",
    "wof:placetype": "postalcode"
  },
  "geometry": {"coordinates":[-0.201683,51.407992],"type":"Point"}
}
