{
  "type": "Feature",
  "properties": {
    "iso:country":"GB",
    "wof:name":"LS11 0AN",
    "wof:placetype":"postalcode"
},
  "geometry": {"coordinates":[-1.5612045890248,53.78234461746029],"type":"Point"}
}