{
  "type": "Feature",
  "properties": {
    "iso:country":"GB",
    "wof:name":"SR8 2JR",
    "wof:placetype":"postalcode"
},
  "geometry": {"coordinates":[-1.35628022132149,54.75621435817813],"type":"Point"}
}