{
  "type": "Feature",
  "properties": {
    "iso:country":"GB",
    "wof:name":"L12 2AS",
    "wof:placetype":"postalcode"
},
  "geometry": {"coordinates":[-2.90357687326209,53.42279442440525],"type":"Point"}
}