{
  "type": "Feature",
  "properties": {
    "iso:country": "GB",
    "wof:name": "L12 2AS",
    "wof:placetype": "postalcode"
  },
  "geometry": {"coordinates":[-2.903577,53.422794],"type":"Point"}
}
