{
  "type": "Feature",
  "properties": {
    "iso:country":"GB",
    "wof:name":"CT16 2RW",
    "wof:placetype":"postalcode"
},
  "geometry": {"coordinates":[1.2998991223056,51.14185369437292],"type":"Point"}
}