{
  "type": "Feature",
  "properties": {
    "iso:country": "GB",
    "wof:name": "CT16 2RW",
    "wof:placetype": "postalcode"
  },
  "geometry": {"coordinates":[1.299899,51.141854],"type":"Point"}
}
