{
  "type": "Feature",
  "properties": {
    "iso:country":"GB",
    "wof:name":"SO41 8NF",
    "wof:placetype":"postalcode"
},
  "geometry": {"coordinates":[-1.55034057374503,50.78088971456948],"type":"Point"}
}