{
  "type": "Feature",
  "properties": {
    "iso:country": "GB",
    "wof:name": "SO41 8NF",
    "wof:placetype": "postalcode"
  },
  "geometry": {"coordinates":[-1.550341,50.78089],"type":"Point"}
}
