{
  "type": "Feature",
  "properties": {
    "iso:country": "GB",
    "wof:name": "BL4 7TE",
    "wof:placetype": "postalcode"
  },
  "geometry": {"coordinates":[-2.397454,53.553755],"type":"Point"}
}
