{
  "type": "Feature",
  "properties": {
    "iso:country":"GB",
    "wof:name":"WV5 8JB",
    "wof:placetype":"postalcode"
},
  "geometry": {"coordinates":[-2.20608442233004,52.52835493491335],"type":"Point"}
}