{
  "type": "Feature",
  "properties": {
    "iso:country": "GB",
    "wof:name": "RG42 2DF",
    "wof:placetype": "postalcode"
  },
  "geometry": {"coordinates":[-0.751749,51.422523],"type":"Point"}
}
