{
  "type": "Feature",
  "properties": {
    "iso:country":"GB",
    "wof:name":"RG42 2DF",
    "wof:placetype":"postalcode"
},
  "geometry": {"coordinates":[-0.75174869982067,51.42252334618301],"type":"Point"}
}