{
  "type": "Feature",
  "properties": {
    "iso:country":"GB",
    "wof:name":"ML5 2RY",
    "wof:placetype":"postalcode"
},
  "geometry": {"coordinates":[-4.05719592657425,55.89638696141471],"type":"Point"}
}