{
  "type": "Feature",
  "properties": {
    "iso:country":"GB",
    "wof:name":"SL6 6BY",
    "wof:placetype":"postalcode"
},
  "geometry": {"coordinates":[-0.72704230426958,51.52434385028904],"type":"Point"}
}