{
  "type": "Feature",
  "properties": {
    "iso:country": "GB",
    "wof:name": "SL6 6BY",
    "wof:placetype": "postalcode"
  },
  "geometry": {"coordinates":[-0.727024,51.524346],"type":"Point"}
}
