{
  "type": "Feature",
  "properties": {
    "iso:country":"GB",
    "wof:name":"NG22 0LQ",
    "wof:placetype":"postalcode"
},
  "geometry": {"coordinates":[-0.90171169255974,53.2337973789778],"type":"Point"}
}