{
  "type": "Feature",
  "properties": {
    "date:inception_lower": "1980-01-01",
    "date:inception_upper": "1980-01-01",
    "iso:country": "GB",
    "wof:name": "WV8 1RL",
    "wof:placetype": "postalcode"
  },
  "geometry": {"coordinates":[-2.235487,52.6356],"type":"Point"}
}
