{
  "type": "Feature",
  "properties": {
    "iso:country":"GB",
    "wof:name":"WV8 1RL",
    "wof:placetype":"postalcode"
},
  "geometry": {"coordinates":[-2.23710725876756,52.63662413576144],"type":"Point"}
}