{
  "type": "Feature",
  "properties": {
    "iso:country": "GB",
    "wof:name": "WV8 1RL",
    "wof:placetype": "postalcode"
  },
  "geometry": {"coordinates":[-2.235487,52.6356],"type":"Point"}
}
