{
  "type": "Feature",
  "properties": {
    "iso:country":"GB",
    "wof:name":"WN3 6JQ",
    "wof:placetype":"postalcode"
},
  "geometry": {"coordinates":[-2.67167517218985,53.52047554809604],"type":"Point"}
}