{
  "type": "Feature",
  "properties": {
    "iso:country":"GB",
    "wof:name":"KA3 5PB",
    "wof:placetype":"postalcode"
},
  "geometry": {"coordinates":[-4.50732986236966,55.68256980117666],"type":"Point"}
}