{
  "type": "Feature",
  "properties": {
    "iso:country":"GB",
    "wof:name":"HU18 1JQ",
    "wof:placetype":"postalcode"
},
  "geometry": {"coordinates":[-0.1680784907449,53.91918507749573],"type":"Point"}
}