{
  "type": "Feature",
  "properties": {
    "iso:country":"GB",
    "wof:name":"AB22 8YY",
    "wof:placetype":"postalcode"
},
  "geometry": {"coordinates":[-2.12910235958676,57.18019982408324],"type":"Point"}
}