{
  "type": "Feature",
  "properties": {
    "iso:country":"GB",
    "wof:name":"NE27 0EY",
    "wof:placetype":"postalcode"
},
  "geometry": {"coordinates":[-1.51353193754194,55.02909143605461],"type":"Point"}
}