{
  "type": "Feature",
  "properties": {
    "date:inception_lower":"2000-12-01",
    "date:inception_upper":"2000-12-31",
    "iso:country":"GB",
    "wof:name":"NE27 0EY",
    "wof:placetype":"postalcode"
},
  "geometry": {"coordinates":[-1.513532,55.029091],"type":"Point"}
}