{
  "type": "Feature",
  "properties": {
    "iso:country":"GB",
    "wof:name":"RG24 8XP",
    "wof:placetype":"postalcode"
},
  "geometry": {"coordinates":[-1.06250347618878,51.293984812395],"type":"Point"}
}