{
  "type": "Feature",
  "properties": {
    "iso:country":"GB",
    "wof:name":"L22 3XG",
    "wof:placetype":"postalcode"
},
  "geometry": {"coordinates":[-3.02006753166589,53.47498041253552],"type":"Point"}
}