{
  "type": "Feature",
  "properties": {
    "iso:country":"GB",
    "wof:name":"BS23 3AD",
    "wof:placetype":"postalcode"
},
  "geometry": {"coordinates":[-2.97219624708341,51.34918729319433],"type":"Point"}
}