{
  "type": "Feature",
  "properties": {
    "iso:country": "GB",
    "wof:name": "NN4 6JR",
    "wof:placetype": "postalcode"
  },
  "geometry": {"coordinates":[-0.888268,52.203729],"type":"Point"}
}
