{
  "type": "Feature",
  "properties": {
    "iso:country": "GB",
    "wof:name": "HD3 3QX",
    "wof:placetype": "postalcode"
  },
  "geometry": {"coordinates":[-1.832009,53.667874],"type":"Point"}
}
