{
  "type": "Feature",
  "properties": {
    "date:inception_lower":"1993-01-01",
    "date:inception_upper":"1993-01-31",
    "iso:country":"GB",
    "wof:name":"CF31 2EB",
    "wof:placetype":"postalcode"
},
  "geometry": {"coordinates":[-3.548008,51.516175],"type":"Point"}
}