{
  "type": "Feature",
  "properties": {
    "iso:country":"GB",
    "wof:name":"SE23 1AH",
    "wof:placetype":"postalcode"
},
  "geometry": {"coordinates":[-0.04832256839183,51.44332566765017],"type":"Point"}
}