{
  "type": "Feature",
  "properties": {
    "iso:country":"GB",
    "wof:name":"NR9 3LR",
    "wof:placetype":"postalcode"
},
  "geometry": {"coordinates":[1.18848263162999,52.6322783075558],"type":"Point"}
}