{
  "type": "Feature",
  "properties": {
    "date:inception_lower": "1980-01-01",
    "date:inception_upper": "1980-01-01",
    "iso:country": "GB",
    "wof:name": "PL21 0RF",
    "wof:placetype": "postalcode"
  },
  "geometry": {"coordinates":[-3.887598,50.35017],"type":"Point"}
}
