{
  "type": "Feature",
  "properties": {
    "iso:country":"GB",
    "wof:name":"BS13 8BL",
    "wof:placetype":"postalcode"
},
  "geometry": {"coordinates":[-2.62804591055234,51.41806860324814],"type":"Point"}
}