{
  "type": "Feature",
  "properties": {
    "iso:country":"GB",
    "wof:name":"G31 4PH",
    "wof:placetype":"postalcode"
},
  "geometry": {"coordinates":[-4.19877056577727,55.84671079557551],"type":"Point"}
}