{
  "type": "Feature",
  "properties": {
    "iso:country": "GB",
    "wof:name": "G31 4PH",
    "wof:placetype": "postalcode"
  },
  "geometry": {"coordinates":[-4.198771,55.846711],"type":"Point"}
}
