{
  "type": "Feature",
  "properties": {
    "iso:country": "GB",
    "wof:name": "NG19 6PL",
    "wof:placetype": "postalcode"
  },
  "geometry": {"coordinates":[-1.238018,53.14049],"type":"Point"}
}
