{
  "type": "Feature",
  "properties": {
    "iso:country":"GB",
    "wof:name":"BN27 3NH",
    "wof:placetype":"postalcode"
},
  "geometry": {"coordinates":[0.2447505979677,50.8560394496091],"type":"Point"}
}