{
  "type": "Feature",
  "properties": {
    "iso:country": "GB",
    "wof:name": "TS24 9AL",
    "wof:placetype": "postalcode"
  },
  "geometry": {"coordinates":[-1.224296,54.701692],"type":"Point"}
}
