{
  "type": "Feature",
  "properties": {
    "date:inception_lower":"1980-01-01",
    "date:inception_upper":"1980-01-31",
    "iso:country":"GB",
    "wof:name":"KT16 8LA",
    "wof:placetype":"postalcode"
},
  "geometry": {"coordinates":[-0.490769,51.389347],"type":"Point"}
}