{
  "type": "Feature",
  "properties": {
    "iso:country":"GB",
    "wof:name":"KT16 8LA",
    "wof:placetype":"postalcode"
},
  "geometry": {"coordinates":[-0.49085949710396,51.38936675901343],"type":"Point"}
}