{
  "type": "Feature",
  "properties": {
    "iso:country":"GB",
    "wof:name":"SM1 3RQ",
    "wof:placetype":"postalcode"
},
  "geometry": {"coordinates":[-0.17231348702264,51.36743941422851],"type":"Point"}
}