{
  "type": "Feature",
  "properties": {
    "date:inception_lower": "2022-11-01",
    "date:inception_upper": "2022-11-01",
    "iso:country": "GB",
    "wof:name": "B31 5FD",
    "wof:placetype": "postalcode"
  },
  "geometry": {"coordinates":[-1.991613,52.409045],"type":"Point"}
}
