{
  "type": "Feature",
  "properties": {
    "iso:country":"GB",
    "wof:name":"LN4 2EZ",
    "wof:placetype":"postalcode"
},
  "geometry": {"coordinates":[-0.42226538495967,53.1502941261648],"type":"Point"}
}