{
  "type": "Feature",
  "properties": {
    "iso:country": "GB",
    "wof:name": "SN7 7SU",
    "wof:placetype": "postalcode"
  },
  "geometry": {"coordinates":[-1.608687,51.618558],"type":"Point"}
}
