{
  "type": "Feature",
  "properties": {
    "iso:country":"GB",
    "wof:name":"SN7 7SU",
    "wof:placetype":"postalcode"
},
  "geometry": {"coordinates":[-1.60868698880113,51.61855828168197],"type":"Point"}
}