{
  "type": "Feature",
  "properties": {
    "iso:country":"GB",
    "wof:name":"HP7 0LT",
    "wof:placetype":"postalcode"
},
  "geometry": {"coordinates":[-0.63019014321722,51.64050768847314],"type":"Point"}
}