{
  "type": "Feature",
  "properties": {
    "iso:country": "GB",
    "wof:name": "HP7 0LT",
    "wof:placetype": "postalcode"
  },
  "geometry": {"coordinates":[-0.63019,51.640508],"type":"Point"}
}
