{
  "type": "Feature",
  "properties": {
    "date:inception_lower": "1980-01-01",
    "date:inception_upper": "1980-01-01",
    "iso:country": "GB",
    "wof:name": "HP7 0LT",
    "wof:placetype": "postalcode"
  },
  "geometry": {"coordinates":[-0.63019,51.640508],"type":"Point"}
}
