{
  "type": "Feature",
  "properties": {
    "iso:country":"GB",
    "wof:name":"NW9 9SB",
    "wof:placetype":"postalcode"
},
  "geometry": {"coordinates":[-0.28056475169078,51.58296252228913],"type":"Point"}
}