{
  "type": "Feature",
  "properties": {
    "iso:country": "GB",
    "wof:name": "NW9 9SB",
    "wof:placetype": "postalcode"
  },
  "geometry": {"coordinates":[-0.280565,51.582963],"type":"Point"}
}
