{
  "type": "Feature",
  "properties": {
    "iso:country":"GB",
    "wof:name":"HP2 5YN",
    "wof:placetype":"postalcode"
},
  "geometry": {"coordinates":[-0.46781290232753,51.76340776637537],"type":"Point"}
}