{
  "type": "Feature",
  "properties": {
    "iso:country": "GB",
    "wof:name": "HP2 5YN",
    "wof:placetype": "postalcode"
  },
  "geometry": {"coordinates":[-0.467813,51.763408],"type":"Point"}
}
