{
  "type": "Feature",
  "properties": {
    "iso:country":"GB",
    "wof:name":"EX19 8JW",
    "wof:placetype":"postalcode"
},
  "geometry": {"coordinates":[-3.94563280011122,50.85283992660849],"type":"Point"}
}