{
  "type": "Feature",
  "properties": {
    "date:inception_lower":"1999-06-01",
    "date:inception_upper":"1999-06-30",
    "iso:country":"GB",
    "wof:name":"EX19 8JW",
    "wof:placetype":"postalcode"
},
  "geometry": {"coordinates":[-3.945633,50.85284],"type":"Point"}
}