{
  "type": "Feature",
  "properties": {
    "iso:country": "GB",
    "wof:name": "EX19 8JW",
    "wof:placetype": "postalcode"
  },
  "geometry": {"coordinates":[-3.945633,50.85284],"type":"Point"}
}
