{
  "type": "Feature",
  "properties": {
    "iso:country": "GB",
    "wof:name": "WA7 3GL",
    "wof:placetype": "postalcode"
  },
  "geometry": {"coordinates":[-2.657013,53.318434],"type":"Point"}
}
