{
  "type": "Feature",
  "properties": {
    "iso:country":"GB",
    "wof:name":"NP19 7JG",
    "wof:placetype":"postalcode"
},
  "geometry": {"coordinates":[-2.98257113061837,51.60010675622964],"type":"Point"}
}