{
  "type": "Feature",
  "properties": {
    "date:inception_lower": "2007-11-01",
    "date:inception_upper": "2007-11-01",
    "iso:country": "GB",
    "wof:name": "DD5 3UT",
    "wof:placetype": "postalcode"
  },
  "geometry": {"coordinates":[-2.843695,56.48331],"type":"Point"}
}
