{
  "type": "Feature",
  "properties": {
    "iso:country":"GB",
    "wof:name":"DD5 3UT",
    "wof:placetype":"postalcode"
},
  "geometry": {"coordinates":[-2.84369522471018,56.48330977532529],"type":"Point"}
}