{
  "type": "Feature",
  "properties": {
    "iso:country":"GB",
    "wof:name":"CW9 8JH",
    "wof:placetype":"postalcode"
},
  "geometry": {"coordinates":[-2.51238525461476,53.2323859293892],"type":"Point"}
}