{
  "type": "Feature",
  "properties": {
    "iso:country":"GB",
    "wof:name":"SO16 0XQ",
    "wof:placetype":"postalcode"
},
  "geometry": {"coordinates":[-1.46834795012643,50.93661944327113],"type":"Point"}
}