{
  "type": "Feature",
  "properties": {
    "iso:country": "GB",
    "wof:name": "LN2 3PQ",
    "wof:placetype": "postalcode"
  },
  "geometry": {"coordinates":[-0.514145,53.328905],"type":"Point"}
}
