{
  "type": "Feature",
  "properties": {
    "iso:country": "GB",
    "wof:name": "BS23 2RF",
    "wof:placetype": "postalcode"
  },
  "geometry": {"coordinates":[-2.970664,51.349799],"type":"Point"}
}
