{
  "type": "Feature",
  "properties": {
    "iso:country":"GB",
    "wof:name":"WF13 3HG",
    "wof:placetype":"postalcode"
},
  "geometry": {"coordinates":[-1.66134791157814,53.68099562941337],"type":"Point"}
}