{
  "type": "Feature",
  "properties": {
    "iso:country":"GB",
    "wof:name":"BR3 5BY",
    "wof:placetype":"postalcode"
},
  "geometry": {"coordinates":[-0.01276187082011,51.41288115846037],"type":"Point"}
}