{
  "type": "Feature",
  "properties": {
    "iso:country":"GB",
    "wof:name":"SG12 9NE",
    "wof:placetype":"postalcode"
},
  "geometry": {"coordinates":[-0.02798071594398,51.80569721853333],"type":"Point"}
}