{
  "type": "Feature",
  "properties": {
    "iso:country":"GB",
    "wof:name":"SN3 4LT",
    "wof:placetype":"postalcode"
},
  "geometry": {"coordinates":[-1.74322088422018,51.57920557051869],"type":"Point"}
}