{
  "type": "Feature",
  "properties": {
    "iso:country": "GB",
    "wof:name": "SN3 4LT",
    "wof:placetype": "postalcode"
  },
  "geometry": {"coordinates":[-1.743221,51.579206],"type":"Point"}
}
