{
  "type": "Feature",
  "properties": {
    "iso:country":"GB",
    "wof:name":"LE2 0NN",
    "wof:placetype":"postalcode"
},
  "geometry": {"coordinates":[-1.11818989074797,52.62962693611682],"type":"Point"}
}