{
  "type": "Feature",
  "properties": {
    "iso:country":"GB",
    "wof:name":"GL14 3DQ",
    "wof:placetype":"postalcode"
},
  "geometry": {"coordinates":[-2.50072003594614,51.81418500521992],"type":"Point"}
}