{
  "type": "Feature",
  "properties": {
    "date:inception_lower":"2018-12-01",
    "date:inception_upper":"2018-12-31",
    "iso:country":"GB",
    "wof:name":"NN6 7XP",
    "wof:placetype":"postalcode"
},
  "geometry": {"coordinates":[-1.08508,52.295817],"type":"Point"}
}