{
  "type": "Feature",
  "properties": {
    "date:inception_lower": "2021-02-01",
    "date:inception_upper": "2021-02-01",
    "iso:country": "GB",
    "wof:name": "CH65 1AX",
    "wof:placetype": "postalcode"
  },
  "geometry": {"coordinates":[-2.935865,53.307396],"type":"Point"}
}
