{
  "type": "Feature",
  "properties": {
    "iso:country":"GB",
    "wof:name":"RG21 3HS",
    "wof:placetype":"postalcode"
},
  "geometry": {"coordinates":[-1.09027706640781,51.25149153440605],"type":"Point"}
}