{
  "type": "Feature",
  "properties": {
    "iso:country":"GB",
    "wof:name":"OX17 3AG",
    "wof:placetype":"postalcode"
},
  "geometry": {"coordinates":[-1.25111334831701,51.996043476453],"type":"Point"}
}