{
  "type": "Feature",
  "properties": {
    "iso:country": "GB",
    "wof:name": "WR11 2PX",
    "wof:placetype": "postalcode"
  },
  "geometry": {"coordinates":[-1.977214,52.090853],"type":"Point"}
}
