{
  "type": "Feature",
  "properties": {
    "iso:country":"GB",
    "wof:name":"HR2 7TB",
    "wof:placetype":"postalcode"
},
  "geometry": {"coordinates":[-2.73843697107105,52.036645847911],"type":"Point"}
}