{
  "type": "Feature",
  "properties": {
    "date:inception_lower":"1980-01-01",
    "date:inception_upper":"1980-01-31",
    "iso:country":"GB",
    "wof:name":"HR2 7TB",
    "wof:placetype":"postalcode"
},
  "geometry": {"coordinates":[-2.738437,52.036646],"type":"Point"}
}