{
  "type": "Feature",
  "properties": {
    "iso:country":"GB",
    "wof:name":"TQ3 2AU",
    "wof:placetype":"postalcode"
},
  "geometry": {"coordinates":[-3.56441198056125,50.44029928210275],"type":"Point"}
}