{
  "type": "Feature",
  "properties": {
    "iso:country": "GB",
    "wof:name": "HU6 8PH",
    "wof:placetype": "postalcode"
  },
  "geometry": {"coordinates":[-0.382869,53.774779],"type":"Point"}
}
