{
  "type": "Feature",
  "properties": {
    "iso:country":"GB",
    "wof:name":"PO21 5AQ",
    "wof:placetype":"postalcode"
},
  "geometry": {"coordinates":[-0.68756623704353,50.79581393584975],"type":"Point"}
}