{
  "type": "Feature",
  "properties": {
    "iso:country": "GB",
    "wof:name": "IV19 1NR",
    "wof:placetype": "postalcode"
  },
  "geometry": {"coordinates":[-4.071395,57.807132],"type":"Point"}
}
