{
  "type": "Feature",
  "properties": {
    "iso:country":"GB",
    "wof:name":"IV19 1NR",
    "wof:placetype":"postalcode"
},
  "geometry": {"coordinates":[-4.07139543731302,57.80713157723178],"type":"Point"}
}