{
  "type": "Feature",
  "properties": {
    "iso:country":"GB",
    "wof:name":"CB10 2EZ",
    "wof:placetype":"postalcode"
},
  "geometry": {"coordinates":[0.31824267257338,52.05288884981022],"type":"Point"}
}