{
  "type": "Feature",
  "properties": {
    "date:inception_lower": "2014-02-01",
    "date:inception_upper": "2014-02-01",
    "iso:country": "GB",
    "wof:name": "SR6 7UH",
    "wof:placetype": "postalcode"
  },
  "geometry": {"coordinates":[-1.398607,54.954162],"type":"Point"}
}
