{
  "type": "Feature",
  "properties": {
    "iso:country":"GB",
    "wof:name":"HP1 2SG",
    "wof:placetype":"postalcode"
},
  "geometry": {"coordinates":[-0.50784079869385,51.76769023007143],"type":"Point"}
}