{
  "type": "Feature",
  "properties": {
    "iso:country": "GB",
    "wof:name": "NR25 6RA",
    "wof:placetype": "postalcode"
  },
  "geometry": {"coordinates":[1.126104,52.915976],"type":"Point"}
}
