{
  "type": "Feature",
  "properties": {
    "iso:country":"GB",
    "wof:name":"TS23 3AX",
    "wof:placetype":"postalcode"
},
  "geometry": {"coordinates":[-1.27948160013968,54.61119303584613],"type":"Point"}
}