{
  "type": "Feature",
  "properties": {
    "iso:country":"GB",
    "wof:name":"EH16 6BX",
    "wof:placetype":"postalcode"
},
  "geometry": {"coordinates":[-3.15760645424698,55.91641757681172],"type":"Point"}
}