{
  "type": "Feature",
  "properties": {
    "iso:country":"GB",
    "wof:name":"WF2 0UJ",
    "wof:placetype":"postalcode"
},
  "geometry": {"coordinates":[-1.53134037486531,53.69347384080202],"type":"Point"}
}