{
  "type": "Feature",
  "properties": {
    "date:inception_lower":"1996-06-01",
    "date:inception_upper":"1996-06-30",
    "iso:country":"GB",
    "wof:name":"WF2 0UJ",
    "wof:placetype":"postalcode"
},
  "geometry": {"coordinates":[-1.53134,53.693474],"type":"Point"}
}