{
  "type": "Feature",
  "properties": {
    "iso:country":"GB",
    "wof:name":"B80 7AN",
    "wof:placetype":"postalcode"
},
  "geometry": {"coordinates":[-1.89436041447414,52.27405058220322],"type":"Point"}
}