{
  "type": "Feature",
  "properties": {
    "date:inception_lower": "2005-02-01",
    "date:inception_upper": "2005-02-01",
    "iso:country": "GB",
    "wof:name": "DL1 9SJ",
    "wof:placetype": "postalcode"
  },
  "geometry": {"coordinates":[-1.552836,54.523576],"type":"Point"}
}
