{
  "type": "Feature",
  "properties": {
    "iso:country": "GB",
    "wof:name": "CT13 0JR",
    "wof:placetype": "postalcode"
  },
  "geometry": {"coordinates":[1.306008,51.24481],"type":"Point"}
}
