{
  "type": "Feature",
  "properties": {
    "date:inception_lower": "1980-01-01",
    "date:inception_upper": "1980-01-01",
    "iso:country": "GB",
    "wof:name": "CT13 0JR",
    "wof:placetype": "postalcode"
  },
  "geometry": {"coordinates":[1.306008,51.24481],"type":"Point"}
}
