{
  "type": "Feature",
  "properties": {
    "date:inception_lower": "1994-05-01",
    "date:inception_upper": "1994-05-01",
    "iso:country": "GB",
    "wof:name": "M19 1DF",
    "wof:placetype": "postalcode"
  },
  "geometry": {"coordinates":[-2.208537,53.428531],"type":"Point"}
}
