{
  "type": "Feature",
  "properties": {
    "iso:country":"GB",
    "wof:name":"M19 1DF",
    "wof:placetype":"postalcode"
},
  "geometry": {"coordinates":[-2.20853666318502,53.4285305299338],"type":"Point"}
}