{
  "type": "Feature",
  "properties": {
    "iso:country":"GB",
    "wof:name":"ST2 8DB",
    "wof:placetype":"postalcode"
},
  "geometry": {"coordinates":[-2.14318796686092,53.03793690603244],"type":"Point"}
}