{
  "type": "Feature",
  "properties": {
    "iso:country": "GB",
    "wof:name": "WA6 0QD",
    "wof:placetype": "postalcode"
  },
  "geometry": {"coordinates":[-2.76298,53.278938],"type":"Point"}
}
