{
  "type": "Feature",
  "properties": {
    "date:inception_lower":"1985-10-01",
    "date:inception_upper":"1985-10-31",
    "iso:country":"GB",
    "wof:name":"WA6 0QD",
    "wof:placetype":"postalcode"
},
  "geometry": {"coordinates":[-2.76298,53.278938],"type":"Point"}
}