{
  "type": "Feature",
  "properties": {
    "iso:country":"GB",
    "wof:name":"PE29 7JH",
    "wof:placetype":"postalcode"
},
  "geometry": {"coordinates":[-0.18019546585086,52.34723886696683],"type":"Point"}
}