{
  "type": "Feature",
  "properties": {
    "iso:country":"GB",
    "wof:name":"DE21 6EF",
    "wof:placetype":"postalcode"
},
  "geometry": {"coordinates":[-1.45466817371691,52.93441355709833],"type":"Point"}
}