{
  "type": "Feature",
  "properties": {
    "iso:country": "GB",
    "wof:name": "LU4 0TH",
    "wof:placetype": "postalcode"
  },
  "geometry": {"coordinates":[-0.493618,51.896611],"type":"Point"}
}
