{
  "type": "Feature",
  "properties": {
    "date:inception_lower":"1980-01-01",
    "date:inception_upper":"1980-01-31",
    "iso:country":"GB",
    "wof:name":"LU4 0TH",
    "wof:placetype":"postalcode"
},
  "geometry": {"coordinates":[-0.493618,51.896611],"type":"Point"}
}