{
  "type": "Feature",
  "properties": {
    "iso:country":"GB",
    "wof:name":"BH8 0HL",
    "wof:placetype":"postalcode"
},
  "geometry": {"coordinates":[-1.83476064492879,50.75259258011149],"type":"Point"}
}