{
  "type": "Feature",
  "properties": {
    "iso:country":"GB",
    "wof:name":"WD6 1TH",
    "wof:placetype":"postalcode"
},
  "geometry": {"coordinates":[-0.26857469929517,51.66102748980183],"type":"Point"}
}