{
  "type": "Feature",
  "properties": {
    "iso:country":"GB",
    "wof:name":"BR6 9BY",
    "wof:placetype":"postalcode"
},
  "geometry": {"coordinates":[0.11000136760399,51.36996079689862],"type":"Point"}
}