{
  "type": "Feature",
  "properties": {
    "date:inception_lower":"1980-01-01",
    "date:inception_upper":"1980-01-31",
    "iso:country":"GB",
    "wof:name":"BR6 9BY",
    "wof:placetype":"postalcode"
},
  "geometry": {"coordinates":[0.110001,51.369961],"type":"Point"}
}