{
  "type": "Feature",
  "properties": {
    "iso:country": "GB",
    "wof:name": "S1 2GE",
    "wof:placetype": "postalcode"
  },
  "geometry": {"coordinates":[-1.467558,53.382602],"type":"Point"}
}
