{
  "type": "Feature",
  "properties": {
    "date:inception_lower": "1980-01-01",
    "date:inception_upper": "1980-01-01",
    "iso:country": "GB",
    "wof:name": "AL2 3AF",
    "wof:placetype": "postalcode"
  },
  "geometry": {"coordinates":[-0.360659,51.731974],"type":"Point"}
}
