{
  "type": "Feature",
  "properties": {
    "iso:country":"GB",
    "wof:name":"BS41 9NG",
    "wof:placetype":"postalcode"
},
  "geometry": {"coordinates":[-2.65038327470798,51.43052614272762],"type":"Point"}
}