{
  "type": "Feature",
  "properties": {
    "date:inception_lower": "1997-12-01",
    "date:inception_upper": "1997-12-01",
    "iso:country": "GB",
    "wof:name": "BS41 9NG",
    "wof:placetype": "postalcode"
  },
  "geometry": {"coordinates":[-2.650383,51.430526],"type":"Point"}
}
