{
  "type": "Feature",
  "properties": {
    "date:inception_lower": "1999-12-01",
    "date:inception_upper": "1999-12-01",
    "iso:country": "GB",
    "wof:name": "CV47 2QG",
    "wof:placetype": "postalcode"
  },
  "geometry": {"coordinates":[-1.439802,52.21649],"type":"Point"}
}
