{
  "type": "Feature",
  "properties": {
    "iso:country":"GB",
    "wof:name":"B32 3BJ",
    "wof:placetype":"postalcode"
},
  "geometry": {"coordinates":[-1.98384684760431,52.44245495931912],"type":"Point"}
}