{
  "type": "Feature",
  "properties": {
    "iso:country":"GB",
    "wof:name":"TA20 2BY",
    "wof:placetype":"postalcode"
},
  "geometry": {"coordinates":[-2.96048217076477,50.86914725377861],"type":"Point"}
}