{
  "type": "Feature",
  "properties": {
    "iso:country": "GB",
    "wof:name": "LL22 8FD",
    "wof:placetype": "postalcode"
  },
  "geometry": {"coordinates":[-3.642607,53.245924],"type":"Point"}
}
