{
  "type": "Feature",
  "properties": {
    "iso:country": "GB",
    "wof:name": "TQ14 9UG",
    "wof:placetype": "postalcode"
  },
  "geometry": {"coordinates":[-3.514432,50.554487],"type":"Point"}
}
