{
  "type": "Feature",
  "properties": {
    "iso:country":"GB",
    "wof:name":"BB5 2RR",
    "wof:placetype":"postalcode"
},
  "geometry": {"coordinates":[-2.34357309643041,53.72931835372339],"type":"Point"}
}