{
  "type": "Feature",
  "properties": {
    "iso:country":"GB",
    "wof:name":"DE22 1GD",
    "wof:placetype":"postalcode"
},
  "geometry": {"coordinates":[-1.49382856509958,52.93429007093398],"type":"Point"}
}