{
  "type": "Feature",
  "properties": {
    "iso:country":"GB",
    "wof:name":"CF10 5FJ",
    "wof:placetype":"postalcode"
},
  "geometry": {"coordinates":[-3.16924777500952,51.46519921016924],"type":"Point"}
}