{
  "type": "Feature",
  "properties": {
    "date:inception_lower": "1999-06-01",
    "date:inception_upper": "1999-06-01",
    "iso:country": "GB",
    "wof:name": "CH64 0UA",
    "wof:placetype": "postalcode"
  },
  "geometry": {"coordinates":[-3.060159,53.278266],"type":"Point"}
}
