{
  "type": "Feature",
  "properties": {
    "iso:country":"GB",
    "wof:name":"PL4 7QR",
    "wof:placetype":"postalcode"
},
  "geometry": {"coordinates":[-4.12912537571251,50.37901285226748],"type":"Point"}
}