{
  "type": "Feature",
  "properties": {
    "iso:country":"GB",
    "wof:name":"WS4 1QT",
    "wof:placetype":"postalcode"
},
  "geometry": {"coordinates":[-1.94406289261545,52.60871092494542],"type":"Point"}
}