{
  "type": "Feature",
  "properties": {
    "iso:country":"GB",
    "wof:name":"GU12 6LZ",
    "wof:placetype":"postalcode"
},
  "geometry": {"coordinates":[-0.72183546201824,51.24431713481155],"type":"Point"}
}