{
  "type": "Feature",
  "properties": {
    "iso:country":"GB",
    "wof:name":"BN6 9SH",
    "wof:placetype":"postalcode"
},
  "geometry": {"coordinates":[-0.17709591647029,50.93893616367578],"type":"Point"}
}