{
  "type": "Feature",
  "properties": {
    "iso:country":"GB",
    "wof:name":"SE10 0PP",
    "wof:placetype":"postalcode"
},
  "geometry": {"coordinates":[0.01189771679686,51.4962819750324],"type":"Point"}
}