{
  "type": "Feature",
  "properties": {
    "date:inception_lower": "2015-11-01",
    "date:inception_upper": "2015-11-01",
    "iso:country": "GB",
    "wof:name": "SE10 0PP",
    "wof:placetype": "postalcode"
  },
  "geometry": {"coordinates":[0.011566,51.496316],"type":"Point"}
}
