{
  "type": "Feature",
  "properties": {
    "iso:country": "GB",
    "wof:name": "SE10 0PP",
    "wof:placetype": "postalcode"
  },
  "geometry": {"coordinates":[0.011566,51.496316],"type":"Point"}
}
