{
  "type": "Feature",
  "properties": {
    "date:inception_lower": "2017-12-01",
    "date:inception_upper": "2017-12-01",
    "iso:country": "GB",
    "wof:name": "BD1 1SY",
    "wof:placetype": "postalcode"
  },
  "geometry": {"coordinates":[-1.75526,53.793797],"type":"Point"}
}
