{
  "type": "Feature",
  "properties": {
    "iso:country":"GB",
    "wof:name":"SA1 6JB",
    "wof:placetype":"postalcode"
},
  "geometry": {"coordinates":[-3.95531618859016,51.622829267782],"type":"Point"}
}