{
  "type": "Feature",
  "properties": {
    "iso:country":"GB",
    "wof:name":"CR2 8SN",
    "wof:placetype":"postalcode"
},
  "geometry": {"coordinates":[-0.04962865565167,51.3457308297065],"type":"Point"}
}