{
  "type": "Feature",
  "properties": {
    "iso:country": "GB",
    "wof:name": "CR2 8SN",
    "wof:placetype": "postalcode"
  },
  "geometry": {"coordinates":[-0.049629,51.345731],"type":"Point"}
}
