{
  "type": "Feature",
  "properties": {
    "iso:country":"GB",
    "wof:name":"TN34 3LX",
    "wof:placetype":"postalcode"
},
  "geometry": {"coordinates":[0.5883501918853,50.86145978044152],"type":"Point"}
}