{
  "type": "Feature",
  "properties": {
    "iso:country": "GB",
    "wof:name": "WV14 8XG",
    "wof:placetype": "postalcode"
  },
  "geometry": {"coordinates":[-2.085812,52.55049],"type":"Point"}
}
