{
  "type": "Feature",
  "properties": {
    "date:inception_lower": "2019-09-01",
    "date:inception_upper": "2019-09-01",
    "iso:country": "GB",
    "wof:name": "WV14 8XG",
    "wof:placetype": "postalcode"
  },
  "geometry": {"coordinates":[-2.085972,52.549564],"type":"Point"}
}
