{
  "type": "Feature",
  "properties": {
    "date:inception_lower":"1980-01-01",
    "date:inception_upper":"1980-01-31",
    "iso:country":"GB",
    "wof:name":"BH16 6BA",
    "wof:placetype":"postalcode"
},
  "geometry": {"coordinates":[-2.051204,50.742293],"type":"Point"}
}