{
  "type": "Feature",
  "properties": {
    "iso:country":"GB",
    "wof:name":"BH16 6BA",
    "wof:placetype":"postalcode"
},
  "geometry": {"coordinates":[-2.05218890825018,50.74363289449501],"type":"Point"}
}