{
  "type": "Feature",
  "properties": {
    "iso:country":"GB",
    "wof:name":"SP4 0EG",
    "wof:placetype":"postalcode"
},
  "geometry": {"coordinates":[-1.6681503430647,51.19135945378331],"type":"Point"}
}