{
  "type": "Feature",
  "properties": {
    "iso:country": "GB",
    "wof:name": "SP4 0EG",
    "wof:placetype": "postalcode"
  },
  "geometry": {"coordinates":[-1.66815,51.191359],"type":"Point"}
}
