{
  "type": "Feature",
  "properties": {
    "iso:country":"GB",
    "wof:name":"IV2 4DZ",
    "wof:placetype":"postalcode"
},
  "geometry": {"coordinates":[-4.21520985682576,57.45434972919994],"type":"Point"}
}