{
  "type": "Feature",
  "properties": {
    "date:inception_lower": "1980-01-01",
    "date:inception_upper": "1980-01-01",
    "iso:country": "GB",
    "wof:name": "ML5 1NG",
    "wof:placetype": "postalcode"
  },
  "geometry": {"coordinates":[-4.043889,55.86324],"type":"Point"}
}
