{
  "type": "Feature",
  "properties": {
    "iso:country":"GB",
    "wof:name":"M7 3JJ",
    "wof:placetype":"postalcode"
},
  "geometry": {"coordinates":[-2.27074662831262,53.51506349808166],"type":"Point"}
}