{
  "type": "Feature",
  "properties": {
    "date:inception_lower": "1997-12-01",
    "date:inception_upper": "1997-12-01",
    "iso:country": "GB",
    "wof:name": "M7 3JJ",
    "wof:placetype": "postalcode"
  },
  "geometry": {"coordinates":[-2.270747,53.515063],"type":"Point"}
}
