{
  "type": "Feature",
  "properties": {
    "date:inception_lower": "2000-06-01",
    "date:inception_upper": "2000-06-01",
    "iso:country": "GB",
    "wof:name": "NG19 7PX",
    "wof:placetype": "postalcode"
  },
  "geometry": {"coordinates":[-1.252109,53.171115],"type":"Point"}
}
