{
  "type": "Feature",
  "properties": {
    "date:inception_lower": "1980-01-01",
    "date:inception_upper": "1980-01-01",
    "iso:country": "GB",
    "wof:name": "TN31 6PU",
    "wof:placetype": "postalcode"
  },
  "geometry": {"coordinates":[0.601975,50.999308],"type":"Point"}
}
