{
  "type": "Feature",
  "properties": {
    "iso:country":"GB",
    "wof:name":"MK6 3NA",
    "wof:placetype":"postalcode"
},
  "geometry": {"coordinates":[-0.73585451523869,52.041344713471],"type":"Point"}
}