{
  "type": "Feature",
  "properties": {
    "date:inception_lower":"1983-03-01",
    "date:inception_upper":"1983-03-31",
    "iso:country":"GB",
    "wof:name":"EX8 4AR",
    "wof:placetype":"postalcode"
},
  "geometry": {"coordinates":[-3.389508,50.628244],"type":"Point"}
}