{
  "type": "Feature",
  "properties": {
    "iso:country":"GB",
    "wof:name":"EX8 4AR",
    "wof:placetype":"postalcode"
},
  "geometry": {"coordinates":[-3.38950794947413,50.62824400368262],"type":"Point"}
}