{
  "type": "Feature",
  "properties": {
    "date:inception_lower":"1994-05-01",
    "date:inception_upper":"1994-05-31",
    "iso:country":"GB",
    "wof:name":"TQ13 0QG",
    "wof:placetype":"postalcode"
},
  "geometry": {"coordinates":[-3.606329,50.602504],"type":"Point"}
}