{
  "type": "Feature",
  "properties": {
    "iso:country": "GB",
    "wof:name": "TQ13 0QG",
    "wof:placetype": "postalcode"
  },
  "geometry": {"coordinates":[-3.606329,50.602504],"type":"Point"}
}
