{
  "type": "Feature",
  "properties": {
    "iso:country":"GB",
    "wof:name":"DH7 8JX",
    "wof:placetype":"postalcode"
},
  "geometry": {"coordinates":[-1.6056262362991,54.76083048989342],"type":"Point"}
}