{
  "type": "Feature",
  "properties": {
    "date:inception_lower": "1980-01-01",
    "date:inception_upper": "1980-01-01",
    "iso:country": "GB",
    "wof:name": "G51 4DN",
    "wof:placetype": "postalcode"
  },
  "geometry": {"coordinates":[-4.332823,55.854559],"type":"Point"}
}
