{
  "type": "Feature",
  "properties": {
    "date:inception_lower": "1980-01-01",
    "date:inception_upper": "1980-01-01",
    "iso:country": "GB",
    "wof:name": "DN37 7DB",
    "wof:placetype": "postalcode"
  },
  "geometry": {"coordinates":[-0.167358,53.540809],"type":"Point"}
}
