{
  "type": "Feature",
  "properties": {
    "iso:country": "GB",
    "wof:name": "DN37 7DB",
    "wof:placetype": "postalcode"
  },
  "geometry": {"coordinates":[-0.167358,53.540809],"type":"Point"}
}
