{
  "type": "Feature",
  "properties": {
    "date:inception_lower": "1980-01-01",
    "date:inception_upper": "1980-01-01",
    "iso:country": "GB",
    "wof:name": "GU10 4HG",
    "wof:placetype": "postalcode"
  },
  "geometry": {"coordinates":[-0.830847,51.148789],"type":"Point"}
}
