{
  "type": "Feature",
  "properties": {
    "iso:country":"GB",
    "wof:name":"GU10 4HG",
    "wof:placetype":"postalcode"
},
  "geometry": {"coordinates":[-0.83084718508812,51.14878901706988],"type":"Point"}
}