{
  "type": "Feature",
  "properties": {
    "iso:country":"GB",
    "wof:name":"EX15 2RB",
    "wof:placetype":"postalcode"
},
  "geometry": {"coordinates":[-3.36194121129301,50.88231949549063],"type":"Point"}
}