{
  "type": "Feature",
  "properties": {
    "iso:country":"GB",
    "wof:name":"N22 7TZ",
    "wof:placetype":"postalcode"
},
  "geometry": {"coordinates":[-0.11242264063682,51.59794979255867],"type":"Point"}
}