{
  "type": "Feature",
  "properties": {
    "iso:country": "GB",
    "wof:name": "N22 7TZ",
    "wof:placetype": "postalcode"
  },
  "geometry": {"coordinates":[-0.113352,51.598597],"type":"Point"}
}
