{
  "type": "Feature",
  "properties": {
    "iso:country":"GB",
    "wof:name":"NW4 2PT",
    "wof:placetype":"postalcode"
},
  "geometry": {"coordinates":[-0.21830250740767,51.57949797846086],"type":"Point"}
}