{
  "type": "Feature",
  "properties": {
    "date:inception_lower":"1980-01-01",
    "date:inception_upper":"1980-01-31",
    "iso:country":"GB",
    "wof:name":"NW4 2PT",
    "wof:placetype":"postalcode"
},
  "geometry": {"coordinates":[-0.218302,51.579498],"type":"Point"}
}