{
  "type": "Feature",
  "properties": {
    "date:inception_lower": "1980-01-01",
    "date:inception_upper": "1980-01-01",
    "iso:country": "GB",
    "wof:name": "NW4 2PT",
    "wof:placetype": "postalcode"
  },
  "geometry": {"coordinates":[-0.218335,51.579493],"type":"Point"}
}
