{
  "type": "Feature",
  "properties": {
    "date:inception_lower": "2016-11-01",
    "date:inception_upper": "2016-11-01",
    "iso:country": "GB",
    "wof:name": "ME17 1GE",
    "wof:placetype": "postalcode"
  },
  "geometry": {"coordinates":[0.67401,51.240936],"type":"Point"}
}
