{
  "type": "Feature",
  "properties": {
    "date:inception_lower": "2009-05-01",
    "date:inception_upper": "2009-05-01",
    "iso:country": "GB",
    "wof:name": "LE13 9DG",
    "wof:placetype": "postalcode"
  },
  "geometry": {"coordinates":[-0.867598,52.768408],"type":"Point"}
}
