{
  "type": "Feature",
  "properties": {
    "iso:country":"GB",
    "wof:name":"SA73 1TA",
    "wof:placetype":"postalcode"
},
  "geometry": {"coordinates":[-4.94739769345978,51.70995595278982],"type":"Point"}
}