{
  "type": "Feature",
  "properties": {
    "date:inception_lower": "1980-01-01",
    "date:inception_upper": "1980-01-01",
    "iso:country": "GB",
    "wof:name": "PA3 4NX",
    "wof:placetype": "postalcode"
  },
  "geometry": {"coordinates":[-4.407258,55.858008],"type":"Point"}
}
