{
  "type": "Feature",
  "properties": {
    "iso:country": "GB",
    "wof:name": "PA3 4NX",
    "wof:placetype": "postalcode"
  },
  "geometry": {"coordinates":[-4.407258,55.858008],"type":"Point"}
}
