{
  "type": "Feature",
  "properties": {
    "iso:country":"GB",
    "wof:name":"FY6 7SE",
    "wof:placetype":"postalcode"
},
  "geometry": {"coordinates":[-2.99792553416025,53.84734801296305],"type":"Point"}
}