{
  "type": "Feature",
  "properties": {
    "iso:country":"GB",
    "wof:name":"NR1 1YR",
    "wof:placetype":"postalcode"
},
  "geometry": {"coordinates":[1.31836390844995,52.62384285607533],"type":"Point"}
}