{
  "type": "Feature",
  "properties": {
    "iso:country":"GB",
    "wof:name":"SN25 2GH",
    "wof:placetype":"postalcode"
},
  "geometry": {"coordinates":[-1.81752250442506,51.6020205768389],"type":"Point"}
}