{
  "type": "Feature",
  "properties": {
    "iso:country": "GB",
    "wof:name": "BR5 1NJ",
    "wof:placetype": "postalcode"
  },
  "geometry": {"coordinates":[0.073189,51.394386],"type":"Point"}
}
