{
  "type": "Feature",
  "properties": {
    "iso:country":"GB",
    "wof:name":"MK41 0LX",
    "wof:placetype":"postalcode"
},
  "geometry": {"coordinates":[-0.41050246849933,52.1624933896957],"type":"Point"}
}