{
  "type": "Feature",
  "properties": {
    "date:inception_lower": "1980-01-01",
    "date:inception_upper": "1980-01-01",
    "iso:country": "GB",
    "wof:name": "MK41 0LX",
    "wof:placetype": "postalcode"
  },
  "geometry": {"coordinates":[-0.410326,52.162755],"type":"Point"}
}
