{
  "type": "Feature",
  "properties": {
    "iso:country": "GB",
    "wof:name": "NE15 0EB",
    "wof:placetype": "postalcode"
  },
  "geometry": {"coordinates":[-1.7876,54.995209],"type":"Point"}
}
