{
  "type": "Feature",
  "properties": {
    "date:inception_lower":"1980-01-01",
    "date:inception_upper":"1980-01-31",
    "iso:country":"GB",
    "wof:name":"NE15 0EB",
    "wof:placetype":"postalcode"
},
  "geometry": {"coordinates":[-1.7876,54.995209],"type":"Point"}
}