{
  "type": "Feature",
  "properties": {
    "iso:country":"GB",
    "wof:name":"WN7 3DU",
    "wof:placetype":"postalcode"
},
  "geometry": {"coordinates":[-2.49846152978255,53.48537850231402],"type":"Point"}
}