{
  "type": "Feature",
  "properties": {
    "iso:country":"GB",
    "wof:name":"PE1 1ED",
    "wof:placetype":"postalcode"
},
  "geometry": {"coordinates":[-0.24154326917571,52.56980688165779],"type":"Point"}
}