{
  "type": "Feature",
  "properties": {
    "iso:country": "GB",
    "wof:name": "PE1 1ED",
    "wof:placetype": "postalcode"
  },
  "geometry": {"coordinates":[-0.241543,52.569807],"type":"Point"}
}
