{
  "type": "Feature",
  "properties": {
    "iso:country":"GB",
    "wof:name":"EX8 2RR",
    "wof:placetype":"postalcode"
},
  "geometry": {"coordinates":[-3.37591267289186,50.62264966567787],"type":"Point"}
}