{
  "type": "Feature",
  "properties": {
    "iso:country": "GB",
    "wof:name": "EX8 2RR",
    "wof:placetype": "postalcode"
  },
  "geometry": {"coordinates":[-3.375913,50.62265],"type":"Point"}
}
