{
  "type": "Feature",
  "properties": {
    "iso:country":"GB",
    "wof:name":"CF14 1HG",
    "wof:placetype":"postalcode"
},
  "geometry": {"coordinates":[-3.20866887755825,51.50787073256554],"type":"Point"}
}