{
  "type": "Feature",
  "properties": {
    "iso:country": "GB",
    "wof:name": "YO43 3JD",
    "wof:placetype": "postalcode"
  },
  "geometry": {"coordinates":[-0.648059,53.8772],"type":"Point"}
}
