{
  "type": "Feature",
  "properties": {
    "iso:country":"GB",
    "wof:name":"IP4 5QY",
    "wof:placetype":"postalcode"
},
  "geometry": {"coordinates":[1.22020151852457,52.05492831402167],"type":"Point"}
}