{
  "type": "Feature",
  "properties": {
    "iso:country":"GB",
    "wof:name":"TN34 2PU",
    "wof:placetype":"postalcode"
},
  "geometry": {"coordinates":[0.56936233334107,50.87823113226052],"type":"Point"}
}