{
  "type": "Feature",
  "properties": {
    "date:inception_lower": "1991-09-01",
    "date:inception_upper": "1991-09-01",
    "iso:country": "GB",
    "wof:name": "NG14 5HX",
    "wof:placetype": "postalcode"
  },
  "geometry": {"coordinates":[-1.037759,52.972295],"type":"Point"}
}
