{
  "type": "Feature",
  "properties": {
    "iso:country":"GB",
    "wof:name":"NG14 5HX",
    "wof:placetype":"postalcode"
},
  "geometry": {"coordinates":[-1.03775879653574,52.97229495144008],"type":"Point"}
}