{
  "type": "Feature",
  "properties": {
    "date:inception_lower": "2018-09-01",
    "date:inception_upper": "2018-09-01",
    "iso:country": "GB",
    "wof:name": "CT10 3BQ",
    "wof:placetype": "postalcode"
  },
  "geometry": {"coordinates":[1.423364,51.368491],"type":"Point"}
}
