{
  "type": "Feature",
  "properties": {
    "iso:country":"GB",
    "wof:name":"AB15 7SG",
    "wof:placetype":"postalcode"
},
  "geometry": {"coordinates":[-2.15427198771759,57.13519344855153],"type":"Point"}
}