{
  "type": "Feature",
  "properties": {
    "iso:country":"GB",
    "wof:name":"TS17 8EY",
    "wof:placetype":"postalcode"
},
  "geometry": {"coordinates":[-1.28808033152677,54.54784053990397],"type":"Point"}
}