{
  "type": "Feature",
  "properties": {
    "iso:country":"GB",
    "wof:name":"KA3 5HL",
    "wof:placetype":"postalcode"
},
  "geometry": {"coordinates":[-4.51471965010664,55.67972207301335],"type":"Point"}
}