{
  "type": "Feature",
  "properties": {
    "date:inception_lower": "2016-08-01",
    "date:inception_upper": "2016-08-01",
    "iso:country": "GB",
    "wof:name": "EN2 0AG",
    "wof:placetype": "postalcode"
  },
  "geometry": {"coordinates":[-0.085681,51.658776],"type":"Point"}
}
