{
  "type": "Feature",
  "properties": {
    "iso:country": "GB",
    "wof:name": "EN2 0AG",
    "wof:placetype": "postalcode"
  },
  "geometry": {"coordinates":[-0.085781,51.658805],"type":"Point"}
}
