{
  "type": "Feature",
  "properties": {
    "date:inception_lower":"2016-08-01",
    "date:inception_upper":"2016-08-31",
    "iso:country":"GB",
    "wof:name":"EN2 0AG",
    "wof:placetype":"postalcode"
},
  "geometry": {"coordinates":[-0.085781,51.658805],"type":"Point"}
}