{
  "type": "Feature",
  "properties": {
    "iso:country":"GB",
    "wof:name":"HP7 0LW",
    "wof:placetype":"postalcode"
},
  "geometry": {"coordinates":[-0.63453304340544,51.64603428728354],"type":"Point"}
}