{
  "type": "Feature",
  "properties": {
    "date:inception_lower":"1980-01-01",
    "date:inception_upper":"1980-01-31",
    "iso:country":"GB",
    "wof:name":"HP7 0LW",
    "wof:placetype":"postalcode"
},
  "geometry": {"coordinates":[-0.634533,51.646034],"type":"Point"}
}