{
  "type": "Feature",
  "properties": {
    "iso:country":"GB",
    "wof:name":"LE4 3LQ",
    "wof:placetype":"postalcode"
},
  "geometry": {"coordinates":[-1.12827284829382,52.68653605354643],"type":"Point"}
}