{
  "type": "Feature",
  "properties": {
    "iso:country":"GB",
    "wof:name":"IP11 9RB",
    "wof:placetype":"postalcode"
},
  "geometry": {"coordinates":[1.34509096361019,51.9817217384035],"type":"Point"}
}