{
  "type": "Feature",
  "properties": {
    "date:inception_lower": "1980-01-01",
    "date:inception_upper": "1980-01-01",
    "iso:country": "GB",
    "wof:name": "NW5 1RX",
    "wof:placetype": "postalcode"
  },
  "geometry": {"coordinates":[-0.147885,51.558885],"type":"Point"}
}
