{
  "type": "Feature",
  "properties": {
    "date:inception_lower": "2004-05-01",
    "date:inception_upper": "2004-05-01",
    "iso:country": "GB",
    "wof:name": "PE11 3TL",
    "wof:placetype": "postalcode"
  },
  "geometry": {"coordinates":[-0.205782,52.72352],"type":"Point"}
}
