{
  "type": "Feature",
  "properties": {
    "iso:country": "GB",
    "wof:name": "PE11 3TL",
    "wof:placetype": "postalcode"
  },
  "geometry": {"coordinates":[-0.205782,52.72352],"type":"Point"}
}
