{
  "type": "Feature",
  "properties": {
    "iso:country": "GB",
    "wof:name": "SN15 2BF",
    "wof:placetype": "postalcode"
  },
  "geometry": {"coordinates":[-2.097474,51.408949],"type":"Point"}
}
