{
  "type": "Feature",
  "properties": {
    "iso:country":"GB",
    "wof:name":"SN15 2BF",
    "wof:placetype":"postalcode"
},
  "geometry": {"coordinates":[-2.09747376959242,51.40894880780917],"type":"Point"}
}