{
  "type": "Feature",
  "properties": {
    "date:inception_lower":"2008-05-01",
    "date:inception_upper":"2008-05-31",
    "iso:country":"GB",
    "wof:name":"SN15 2BF",
    "wof:placetype":"postalcode"
},
  "geometry": {"coordinates":[-2.097474,51.408949],"type":"Point"}
}