{
  "type": "Feature",
  "properties": {
    "iso:country":"GB",
    "wof:name":"DT7 3SJ",
    "wof:placetype":"postalcode"
},
  "geometry": {"coordinates":[-2.97244882615179,50.74343674823371],"type":"Point"}
}