{
  "type": "Feature",
  "properties": {
    "iso:country":"GB",
    "wof:name":"FK9 5LF",
    "wof:placetype":"postalcode"
},
  "geometry": {"coordinates":[-3.92165977661467,56.13956078102561],"type":"Point"}
}