{
  "type": "Feature",
  "properties": {
    "iso:country":"GB",
    "wof:name":"B37 7EA",
    "wof:placetype":"postalcode"
},
  "geometry": {"coordinates":[-1.74435259854224,52.45845225628461],"type":"Point"}
}