{
  "type": "Feature",
  "properties": {
    "iso:country": "GB",
    "wof:name": "CR0 5DY",
    "wof:placetype": "postalcode"
  },
  "geometry": {"coordinates":[-0.054546,51.36896],"type":"Point"}
}
