{
  "type": "Feature",
  "properties": {
    "iso:country":"GB",
    "wof:name":"CR0 5DY",
    "wof:placetype":"postalcode"
},
  "geometry": {"coordinates":[-0.05454649607258,51.36896013837602],"type":"Point"}
}