{
  "type": "Feature",
  "properties": {
    "date:inception_lower": "1993-08-01",
    "date:inception_upper": "1993-08-01",
    "iso:country": "GB",
    "wof:name": "CR0 5DY",
    "wof:placetype": "postalcode"
  },
  "geometry": {"coordinates":[-0.054546,51.36896],"type":"Point"}
}
