{
  "type": "Feature",
  "properties": {
    "date:inception_lower": "1980-01-01",
    "date:inception_upper": "1980-01-01",
    "iso:country": "GB",
    "wof:name": "PE6 0LT",
    "wof:placetype": "postalcode"
  },
  "geometry": {"coordinates":[-0.129081,52.681154],"type":"Point"}
}
