{
  "type": "Feature",
  "properties": {
    "iso:country":"GB",
    "wof:name":"PE6 0LT",
    "wof:placetype":"postalcode"
},
  "geometry": {"coordinates":[-0.12908076576189,52.68115384754117],"type":"Point"}
}