{
  "type": "Feature",
  "properties": {
    "iso:country": "GB",
    "wof:name": "HP13 5PB",
    "wof:placetype": "postalcode"
  },
  "geometry": {"coordinates":[-0.750254,51.638358],"type":"Point"}
}
