{
  "type": "Feature",
  "properties": {
    "iso:country": "GB",
    "wof:name": "FK4 1LA",
    "wof:placetype": "postalcode"
  },
  "geometry": {"coordinates":[-3.947351,55.988661],"type":"Point"}
}
