{
  "type": "Feature",
  "properties": {
    "iso:country":"GB",
    "wof:name":"FK4 1LA",
    "wof:placetype":"postalcode"
},
  "geometry": {"coordinates":[-3.94735139951569,55.98866085329039],"type":"Point"}
}