{
  "type": "Feature",
  "properties": {
    "iso:country":"GB",
    "wof:name":"DA5 1AR",
    "wof:placetype":"postalcode"
},
  "geometry": {"coordinates":[0.14776777051116,51.44501349508931],"type":"Point"}
}