{
  "type": "Feature",
  "properties": {
    "date:inception_lower": "1980-01-01",
    "date:inception_upper": "1980-01-01",
    "iso:country": "GB",
    "wof:name": "NG11 9HL",
    "wof:placetype": "postalcode"
  },
  "geometry": {"coordinates":[-1.188928,52.898656],"type":"Point"}
}
