{
  "type": "Feature",
  "properties": {
    "iso:country":"GB",
    "wof:name":"EN4 9NX",
    "wof:placetype":"postalcode"
},
  "geometry": {"coordinates":[-0.16580543632304,51.64983659519428],"type":"Point"}
}