{
  "type": "Feature",
  "properties": {
    "iso:country": "GB",
    "wof:name": "LE19 4BN",
    "wof:placetype": "postalcode"
  },
  "geometry": {"coordinates":[-1.222855,52.61078],"type":"Point"}
}
