{
  "type": "Feature",
  "properties": {
    "date:inception_lower": "2018-03-01",
    "date:inception_upper": "2018-03-01",
    "iso:country": "GB",
    "wof:name": "LE19 4BN",
    "wof:placetype": "postalcode"
  },
  "geometry": {"coordinates":[-1.222855,52.61078],"type":"Point"}
}
