{
  "type": "Feature",
  "properties": {
    "iso:country":"GB",
    "wof:name":"LA9 5QT",
    "wof:placetype":"postalcode"
},
  "geometry": {"coordinates":[-2.74609673090764,54.31632664232338],"type":"Point"}
}