{
  "type": "Feature",
  "properties": {
    "iso:country":"GB",
    "wof:name":"CT5 2PB",
    "wof:placetype":"postalcode"
},
  "geometry": {"coordinates":[1.07081402422125,51.36610106611869],"type":"Point"}
}