{
  "type": "Feature",
  "properties": {
    "iso:country":"GB",
    "wof:name":"OX4 1DF",
    "wof:placetype":"postalcode"
},
  "geometry": {"coordinates":[-1.2375100234194,51.74944785509956],"type":"Point"}
}