{
  "type": "Feature",
  "properties": {
    "date:inception_lower": "1993-08-01",
    "date:inception_upper": "1993-08-01",
    "iso:country": "GB",
    "wof:name": "OX4 1DF",
    "wof:placetype": "postalcode"
  },
  "geometry": {"coordinates":[-1.23751,51.749448],"type":"Point"}
}
