{
  "type": "Feature",
  "properties": {
    "iso:country": "GB",
    "wof:name": "DL6 2DF",
    "wof:placetype": "postalcode"
  },
  "geometry": {"coordinates":[-1.346949,54.392527],"type":"Point"}
}
