{
  "type": "Feature",
  "properties": {
    "iso:country": "GB",
    "wof:name": "SA73 1EX",
    "wof:placetype": "postalcode"
  },
  "geometry": {"coordinates":[-5.018616,51.722092],"type":"Point"}
}
