{
  "type": "Feature",
  "properties": {
    "date:inception_lower": "2015-04-01",
    "date:inception_upper": "2015-04-01",
    "iso:country": "GB",
    "wof:name": "SA73 1EX",
    "wof:placetype": "postalcode"
  },
  "geometry": {"coordinates":[-5.018616,51.722092],"type":"Point"}
}
