{
  "type": "Feature",
  "properties": {
    "iso:country":"GB",
    "wof:name":"WR2 5SS",
    "wof:placetype":"postalcode"
},
  "geometry": {"coordinates":[-2.26357895160345,52.17946690099247],"type":"Point"}
}