{
  "type": "Feature",
  "properties": {
    "date:inception_lower": "1996-12-01",
    "date:inception_upper": "1996-12-01",
    "iso:country": "GB",
    "wof:name": "TF2 8SH",
    "wof:placetype": "postalcode"
  },
  "geometry": {"coordinates":[-2.425254,52.72132],"type":"Point"}
}
