{
  "type": "Feature",
  "properties": {
    "iso:country":"GB",
    "wof:name":"TF2 8SH",
    "wof:placetype":"postalcode"
},
  "geometry": {"coordinates":[-2.42525364254963,52.72132039620564],"type":"Point"}
}