{
  "type": "Feature",
  "properties": {
    "iso:country":"GB",
    "wof:name":"N17 7HP",
    "wof:placetype":"postalcode"
},
  "geometry": {"coordinates":[-0.08316194236716,51.59984057365831],"type":"Point"}
}