{
  "type": "Feature",
  "properties": {
    "iso:country": "GB",
    "wof:name": "PL26 8WD",
    "wof:placetype": "postalcode"
  },
  "geometry": {"coordinates":[-4.790541,50.399448],"type":"Point"}
}
