{
  "type": "Feature",
  "properties": {
    "date:inception_lower": "2016-02-01",
    "date:inception_upper": "2016-02-01",
    "iso:country": "GB",
    "wof:name": "PL26 8WD",
    "wof:placetype": "postalcode"
  },
  "geometry": {"coordinates":[-4.790511,50.399421],"type":"Point"}
}
