{
  "type": "Feature",
  "properties": {
    "date:inception_lower": "1980-01-01",
    "date:inception_upper": "1980-01-01",
    "iso:country": "GB",
    "wof:name": "TW16 7PE",
    "wof:placetype": "postalcode"
  },
  "geometry": {"coordinates":[-0.422912,51.421807],"type":"Point"}
}
