{
  "type": "Feature",
  "properties": {
    "iso:country":"GB",
    "wof:name":"LA8 8AF",
    "wof:placetype":"postalcode"
},
  "geometry": {"coordinates":[-2.77316437762088,54.29156648045343],"type":"Point"}
}