{
  "type": "Feature",
  "properties": {
    "iso:country": "GB",
    "wof:name": "LA8 8AF",
    "wof:placetype": "postalcode"
  },
  "geometry": {"coordinates":[-2.773164,54.291566],"type":"Point"}
}
