{
  "type": "Feature",
  "properties": {
    "iso:country":"GB",
    "wof:name":"SY5 8HG",
    "wof:placetype":"postalcode"
},
  "geometry": {"coordinates":[-2.80198761531047,52.64511371687036],"type":"Point"}
}