{
  "type": "Feature",
  "properties": {
    "iso:country": "GB",
    "wof:name": "SY5 8HG",
    "wof:placetype": "postalcode"
  },
  "geometry": {"coordinates":[-2.801988,52.645114],"type":"Point"}
}
