{
  "type": "Feature",
  "properties": {
    "iso:country":"GB",
    "wof:name":"TR8 5PN",
    "wof:placetype":"postalcode"
},
  "geometry": {"coordinates":[-5.09469146253085,50.37584393735425],"type":"Point"}
}