{
  "type": "Feature",
  "properties": {
    "iso:country": "GB",
    "wof:name": "DN11 8DR",
    "wof:placetype": "postalcode"
  },
  "geometry": {"coordinates":[-1.052321,53.417738],"type":"Point"}
}
