{
  "type": "Feature",
  "properties": {
    "iso:country": "GB",
    "wof:name": "CF72 8FP",
    "wof:placetype": "postalcode"
  },
  "geometry": {"coordinates":[-3.385009,51.538249],"type":"Point"}
}
