{
  "type": "Feature",
  "properties": {
    "date:inception_lower": "2018-11-01",
    "date:inception_upper": "2018-11-01",
    "iso:country": "GB",
    "wof:name": "CF72 8FP",
    "wof:placetype": "postalcode"
  },
  "geometry": {"coordinates":[-3.385009,51.538249],"type":"Point"}
}
