{
  "type": "Feature",
  "properties": {
    "iso:country": "GB",
    "wof:name": "B44 9LT",
    "wof:placetype": "postalcode"
  },
  "geometry": {"coordinates":[-1.891381,52.557756],"type":"Point"}
}
