{
  "type": "Feature",
  "properties": {
    "iso:country":"GB",
    "wof:name":"BD13 1JG",
    "wof:placetype":"postalcode"
},
  "geometry": {"coordinates":[-1.86071812433881,53.77431160558881],"type":"Point"}
}