{
  "type": "Feature",
  "properties": {
    "date:inception_lower":"1980-01-01",
    "date:inception_upper":"1980-01-31",
    "iso:country":"GB",
    "wof:name":"BD13 1JG",
    "wof:placetype":"postalcode"
},
  "geometry": {"coordinates":[-1.860796,53.774317],"type":"Point"}
}