{
  "type": "Feature",
  "properties": {
    "iso:country": "GB",
    "wof:name": "BD13 1JG",
    "wof:placetype": "postalcode"
  },
  "geometry": {"coordinates":[-1.860796,53.774317],"type":"Point"}
}
