{
  "type": "Feature",
  "properties": {
    "iso:country":"GB",
    "wof:name":"EH11 4QP",
    "wof:placetype":"postalcode"
},
  "geometry": {"coordinates":[-3.2790344333604,55.92182062483941],"type":"Point"}
}