{
  "type": "Feature",
  "properties": {
    "iso:country":"GB",
    "wof:name":"NP19 9PA",
    "wof:placetype":"postalcode"
},
  "geometry": {"coordinates":[-2.94134822711222,51.58746080119228],"type":"Point"}
}