{
  "type": "Feature",
  "properties": {
    "date:inception_lower":"1999-06-01",
    "date:inception_upper":"1999-06-30",
    "iso:country":"GB",
    "wof:name":"NP19 9PA",
    "wof:placetype":"postalcode"
},
  "geometry": {"coordinates":[-2.941348,51.587461],"type":"Point"}
}