{
  "type": "Feature",
  "properties": {
    "iso:country":"GB",
    "wof:name":"HU7 4FH",
    "wof:placetype":"postalcode"
},
  "geometry": {"coordinates":[-0.30393918440543,53.77786812578027],"type":"Point"}
}