{
  "type": "Feature",
  "properties": {
    "iso:country":"GB",
    "wof:name":"NW1 4LE",
    "wof:placetype":"postalcode"
},
  "geometry": {"coordinates":[-0.1450062133487,51.52574747506297],"type":"Point"}
}