{
  "type": "Feature",
  "properties": {
    "iso:country": "GB",
    "wof:name": "NP12 2NW",
    "wof:placetype": "postalcode"
  },
  "geometry": {"coordinates":[-3.195122,51.651914],"type":"Point"}
}
