{
  "type": "Feature",
  "properties": {
    "date:inception_lower": "1999-06-01",
    "date:inception_upper": "1999-06-01",
    "iso:country": "GB",
    "wof:name": "NP12 2NW",
    "wof:placetype": "postalcode"
  },
  "geometry": {"coordinates":[-3.195122,51.651914],"type":"Point"}
}
