{
  "type": "Feature",
  "properties": {
    "iso:country":"GB",
    "wof:name":"NP12 2NW",
    "wof:placetype":"postalcode"
},
  "geometry": {"coordinates":[-3.19512250346529,51.65191408948645],"type":"Point"}
}