{
  "type": "Feature",
  "properties": {
    "iso:country":"GB",
    "wof:name":"TN14 6AS",
    "wof:placetype":"postalcode"
},
  "geometry": {"coordinates":[0.12228497239042,51.26454670839824],"type":"Point"}
}