{
  "type": "Feature",
  "properties": {
    "iso:country":"GB",
    "wof:name":"WV10 7DX",
    "wof:placetype":"postalcode"
},
  "geometry": {"coordinates":[-2.09462092173927,52.66617526906646],"type":"Point"}
}