{
  "type": "Feature",
  "properties": {
    "date:inception_lower": "1980-01-01",
    "date:inception_upper": "1980-01-01",
    "iso:country": "GB",
    "wof:name": "WV10 7DX",
    "wof:placetype": "postalcode"
  },
  "geometry": {"coordinates":[-2.094053,52.66621],"type":"Point"}
}
