{
  "type": "Feature",
  "properties": {
    "iso:country":"GB",
    "wof:name":"BA12 9PY",
    "wof:placetype":"postalcode"
},
  "geometry": {"coordinates":[-2.18365056669642,51.20024506403078],"type":"Point"}
}