{
  "type": "Feature",
  "properties": {
    "iso:country":"GB",
    "wof:name":"FY2 0RS",
    "wof:placetype":"postalcode"
},
  "geometry": {"coordinates":[-3.03853897370079,53.84174509952845],"type":"Point"}
}