{
  "type": "Feature",
  "properties": {
    "iso:country":"GB",
    "wof:name":"PL22 0RS",
    "wof:placetype":"postalcode"
},
  "geometry": {"coordinates":[-4.59154672235369,50.41689127382237],"type":"Point"}
}