{
  "type": "Feature",
  "properties": {
    "iso:country": "GB",
    "wof:name": "PL22 0RS",
    "wof:placetype": "postalcode"
  },
  "geometry": {"coordinates":[-4.591574,50.416924],"type":"Point"}
}
