{
  "type": "Feature",
  "properties": {
    "iso:country":"GB",
    "wof:name":"ME1 2UJ",
    "wof:placetype":"postalcode"
},
  "geometry": {"coordinates":[0.50067151983348,51.36034660183245],"type":"Point"}
}