{
  "type": "Feature",
  "properties": {
    "iso:country": "GB",
    "wof:name": "CT14 6JQ",
    "wof:placetype": "postalcode"
  },
  "geometry": {"coordinates":[1.40412,51.225984],"type":"Point"}
}
