{
  "type": "Feature",
  "properties": {
    "iso:country":"GB",
    "wof:name":"CT14 6JQ",
    "wof:placetype":"postalcode"
},
  "geometry": {"coordinates":[1.40402068594636,51.22598660704212],"type":"Point"}
}