{
  "type": "Feature",
  "properties": {
    "iso:country":"GB",
    "wof:name":"TN21 0SR",
    "wof:placetype":"postalcode"
},
  "geometry": {"coordinates":[0.22159479559396,50.97323952719933],"type":"Point"}
}