{
  "type": "Feature",
  "properties": {
    "iso:country":"GB",
    "wof:name":"WF2 8NX",
    "wof:placetype":"postalcode"
},
  "geometry": {"coordinates":[-1.53267998400563,53.67095459532106],"type":"Point"}
}