{
  "type": "Feature",
  "properties": {
    "iso:country": "GB",
    "wof:name": "WF2 8NX",
    "wof:placetype": "postalcode"
  },
  "geometry": {"coordinates":[-1.53268,53.670955],"type":"Point"}
}
