{
  "type": "Feature",
  "properties": {
    "iso:country":"GB",
    "wof:name":"SE17 3JH",
    "wof:placetype":"postalcode"
},
  "geometry": {"coordinates":[-0.1018324150219,51.48165865209887],"type":"Point"}
}