{
  "type": "Feature",
  "properties": {
    "date:inception_lower": "1990-07-01",
    "date:inception_upper": "1990-07-01",
    "iso:country": "GB",
    "wof:name": "LN1 2NL",
    "wof:placetype": "postalcode"
  },
  "geometry": {"coordinates":[-0.733439,53.293876],"type":"Point"}
}
