{
  "type": "Feature",
  "properties": {
    "iso:country":"GB",
    "wof:name":"LN1 2NL",
    "wof:placetype":"postalcode"
},
  "geometry": {"coordinates":[-0.73343913155336,53.29387647285323],"type":"Point"}
}