{
  "type": "Feature",
  "properties": {
    "iso:country":"GB",
    "wof:name":"SA10 7QP",
    "wof:placetype":"postalcode"
},
  "geometry": {"coordinates":[-3.82189261100456,51.66986580853629],"type":"Point"}
}