{
  "type": "Feature",
  "properties": {
    "date:inception_lower": "1997-06-01",
    "date:inception_upper": "1997-06-01",
    "iso:country": "GB",
    "wof:name": "SA10 7QP",
    "wof:placetype": "postalcode"
  },
  "geometry": {"coordinates":[-3.821893,51.669866],"type":"Point"}
}
