{
  "type": "Feature",
  "properties": {
    "iso:country":"GB",
    "wof:name":"ME8 9AG",
    "wof:placetype":"postalcode"
},
  "geometry": {"coordinates":[0.60190413903143,51.35729563862957],"type":"Point"}
}