{
  "type": "Feature",
  "properties": {
    "iso:country":"GB",
    "wof:name":"DG8 6QB",
    "wof:placetype":"postalcode"
},
  "geometry": {"coordinates":[-4.47902453618073,54.95799516438952],"type":"Point"}
}