{
  "type": "Feature",
  "properties": {
    "iso:country": "GB",
    "wof:name": "LL41 4BD",
    "wof:placetype": "postalcode"
  },
  "geometry": {"coordinates":[-3.930236,52.978057],"type":"Point"}
}
