{
  "type": "Feature",
  "properties": {
    "date:inception_lower": "1980-01-01",
    "date:inception_upper": "1980-01-01",
    "iso:country": "GB",
    "wof:name": "LL41 4BD",
    "wof:placetype": "postalcode"
  },
  "geometry": {"coordinates":[-3.930131,52.978041],"type":"Point"}
}
