{
  "type": "Feature",
  "properties": {
    "iso:country": "GB",
    "wof:name": "DE11 7NA",
    "wof:placetype": "postalcode"
  },
  "geometry": {"coordinates":[-1.542925,52.778809],"type":"Point"}
}
