{
  "type": "Feature",
  "properties": {
    "date:inception_lower": "1980-01-01",
    "date:inception_upper": "1980-01-01",
    "iso:country": "GB",
    "wof:name": "DE11 7NA",
    "wof:placetype": "postalcode"
  },
  "geometry": {"coordinates":[-1.542925,52.778809],"type":"Point"}
}
