{
  "type": "Feature",
  "properties": {
    "date:inception_lower":"1980-01-01",
    "date:inception_upper":"1980-01-31",
    "iso:country":"GB",
    "wof:name":"GU34 4LD",
    "wof:placetype":"postalcode"
},
  "geometry": {"coordinates":[-0.912915,51.187553],"type":"Point"}
}