{
  "type": "Feature",
  "properties": {
    "iso:country": "GB",
    "wof:name": "GU34 4LD",
    "wof:placetype": "postalcode"
  },
  "geometry": {"coordinates":[-0.912915,51.187553],"type":"Point"}
}
