{
  "type": "Feature",
  "properties": {
    "iso:country": "GB",
    "wof:name": "NN11 6JF",
    "wof:placetype": "postalcode"
  },
  "geometry": {"coordinates":[-1.21031,52.24773],"type":"Point"}
}
