{
  "type": "Feature",
  "properties": {
    "date:inception_lower": "1980-01-01",
    "date:inception_upper": "1980-01-01",
    "iso:country": "GB",
    "wof:name": "N16 6AS",
    "wof:placetype": "postalcode"
  },
  "geometry": {"coordinates":[-0.060686,51.565841],"type":"Point"}
}
