{
  "type": "Feature",
  "properties": {
    "iso:country":"GB",
    "wof:name":"N16 6AS",
    "wof:placetype":"postalcode"
},
  "geometry": {"coordinates":[-0.06072514173776,51.5658849892243],"type":"Point"}
}