{
  "type": "Feature",
  "properties": {
    "iso:country":"GB",
    "wof:name":"SR5 5QS",
    "wof:placetype":"postalcode"
},
  "geometry": {"coordinates":[-1.43167009204462,54.92602306141806],"type":"Point"}
}