{
  "type": "Feature",
  "properties": {
    "iso:country":"GB",
    "wof:name":"LU2 7PT",
    "wof:placetype":"postalcode"
},
  "geometry": {"coordinates":[-0.41765953657825,51.88722539317168],"type":"Point"}
}