{
  "type": "Feature",
  "properties": {
    "iso:country":"GB",
    "wof:name":"YO23 3PP",
    "wof:placetype":"postalcode"
},
  "geometry": {"coordinates":[-1.18463902189617,53.90640812774858],"type":"Point"}
}