{
  "type": "Feature",
  "properties": {
    "iso:country":"GB",
    "wof:name":"NN3 2TD",
    "wof:placetype":"postalcode"
},
  "geometry": {"coordinates":[-0.84912048865269,52.2554100167233],"type":"Point"}
}