{
  "type": "Feature",
  "properties": {
    "date:inception_lower": "1980-01-01",
    "date:inception_upper": "1980-01-01",
    "iso:country": "GB",
    "wof:name": "NN3 2TD",
    "wof:placetype": "postalcode"
  },
  "geometry": {"coordinates":[-0.84912,52.25541],"type":"Point"}
}
