{
  "type": "Feature",
  "properties": {
    "date:inception_lower": "1980-01-01",
    "date:inception_upper": "1980-01-01",
    "iso:country": "GB",
    "wof:name": "CT3 1TA",
    "wof:placetype": "postalcode"
  },
  "geometry": {"coordinates":[1.161626,51.274947],"type":"Point"}
}
