{
  "type": "Feature",
  "properties": {
    "iso:country":"GB",
    "wof:name":"L8 0QP",
    "wof:placetype":"postalcode"
},
  "geometry": {"coordinates":[-2.94814521539854,53.39687541330545],"type":"Point"}
}