{
  "type": "Feature",
  "properties": {
    "date:inception_lower":"1997-12-01",
    "date:inception_upper":"1997-12-31",
    "iso:country":"GB",
    "wof:name":"BS25 5NN",
    "wof:placetype":"postalcode"
},
  "geometry": {"coordinates":[-2.7892,51.332292],"type":"Point"}
}