{
  "type": "Feature",
  "properties": {
    "iso:country":"GB",
    "wof:name":"BS25 5NN",
    "wof:placetype":"postalcode"
},
  "geometry": {"coordinates":[-2.78919964361517,51.33229190253993],"type":"Point"}
}