{
  "type": "Feature",
  "properties": {
    "iso:country":"GB",
    "wof:name":"CF14 2JQ",
    "wof:placetype":"postalcode"
},
  "geometry": {"coordinates":[-3.22811194892419,51.50215667037837],"type":"Point"}
}