{
  "type": "Feature",
  "properties": {
    "iso:country":"GB",
    "wof:name":"NE8 1NQ",
    "wof:placetype":"postalcode"
},
  "geometry": {"coordinates":[-1.60201005040383,54.95666011697703],"type":"Point"}
}