{
  "type": "Feature",
  "properties": {
    "iso:country": "GB",
    "wof:name": "CT2 7QE",
    "wof:placetype": "postalcode"
  },
  "geometry": {"coordinates":[1.089018,51.291566],"type":"Point"}
}
