{
  "type": "Feature",
  "properties": {
    "iso:country":"GB",
    "wof:name":"CH4 8SS",
    "wof:placetype":"postalcode"
},
  "geometry": {"coordinates":[-2.93039098566361,53.17630657741356],"type":"Point"}
}