{
  "type": "Feature",
  "properties": {
    "iso:country": "GB",
    "wof:name": "ML8 5DS",
    "wof:placetype": "postalcode"
  },
  "geometry": {"coordinates":[-3.839897,55.739101],"type":"Point"}
}
