{
  "type": "Feature",
  "properties": {
    "iso:country": "GB",
    "wof:name": "S73 8FY",
    "wof:placetype": "postalcode"
  },
  "geometry": {"coordinates":[-1.405698,53.527028],"type":"Point"}
}
