{
  "type": "Feature",
  "properties": {
    "date:inception_lower": "1998-12-01",
    "date:inception_upper": "1998-12-01",
    "iso:country": "GB",
    "wof:name": "CV3 1NX",
    "wof:placetype": "postalcode"
  },
  "geometry": {"coordinates":[-1.472439,52.395025],"type":"Point"}
}
