{
  "type": "Feature",
  "properties": {
    "iso:country": "GB",
    "wof:name": "SY3 8FT",
    "wof:placetype": "postalcode"
  },
  "geometry": {"coordinates":[-2.7576,52.710708],"type":"Point"}
}
