{
  "type": "Feature",
  "properties": {
    "iso:country":"GB",
    "wof:name":"SY3 8FT",
    "wof:placetype":"postalcode"
},
  "geometry": {"coordinates":[-2.75760010529379,52.71070828186485],"type":"Point"}
}