{
  "type": "Feature",
  "properties": {
    "date:inception_lower": "2005-01-01",
    "date:inception_upper": "2005-01-01",
    "iso:country": "GB",
    "wof:name": "CF63 2RE",
    "wof:placetype": "postalcode"
  },
  "geometry": {"coordinates":[-3.243529,51.413225],"type":"Point"}
}
