{
  "type": "Feature",
  "properties": {
    "iso:country":"GB",
    "wof:name":"CF63 2RE",
    "wof:placetype":"postalcode"
},
  "geometry": {"coordinates":[-3.24352879009765,51.41322515607127],"type":"Point"}
}