{
  "type": "Feature",
  "properties": {
    "date:inception_lower": "1993-01-01",
    "date:inception_upper": "1993-01-01",
    "iso:country": "GB",
    "wof:name": "GL8 8EH",
    "wof:placetype": "postalcode"
  },
  "geometry": {"coordinates":[-2.159539,51.638756],"type":"Point"}
}
