{
  "type": "Feature",
  "properties": {
    "iso:country":"GB",
    "wof:name":"YO61 4SL",
    "wof:placetype":"postalcode"
},
  "geometry": {"coordinates":[-1.10342280235097,54.16236309811037],"type":"Point"}
}