{
  "type": "Feature",
  "properties": {
    "iso:country":"GB",
    "wof:name":"OX11 9DP",
    "wof:placetype":"postalcode"
},
  "geometry": {"coordinates":[-1.19331418930591,51.56048578015193],"type":"Point"}
}