{
  "type": "Feature",
  "properties": {
    "date:inception_lower": "1980-01-01",
    "date:inception_upper": "1980-01-01",
    "iso:country": "GB",
    "wof:name": "OX11 9DP",
    "wof:placetype": "postalcode"
  },
  "geometry": {"coordinates":[-1.193726,51.560581],"type":"Point"}
}
