{
  "type": "Feature",
  "properties": {
    "iso:country": "GB",
    "wof:name": "PH10 7PH",
    "wof:placetype": "postalcode"
  },
  "geometry": {"coordinates":[-3.56966,56.759509],"type":"Point"}
}
