{
  "type": "Feature",
  "properties": {
    "date:inception_lower": "2007-04-01",
    "date:inception_upper": "2007-04-01",
    "iso:country": "GB",
    "wof:name": "SR3 1LH",
    "wof:placetype": "postalcode"
  },
  "geometry": {"coordinates":[-1.402054,54.89131],"type":"Point"}
}
