{
  "type": "Feature",
  "properties": {
    "iso:country":"GB",
    "wof:name":"SR3 1LH",
    "wof:placetype":"postalcode"
},
  "geometry": {"coordinates":[-1.40205364295882,54.89131015334521],"type":"Point"}
}