{
  "type": "Feature",
  "properties": {
    "iso:country": "GB",
    "wof:name": "CT1 2ST",
    "wof:placetype": "postalcode"
  },
  "geometry": {"coordinates":[1.079623,51.276999],"type":"Point"}
}
