{
  "type": "Feature",
  "properties": {
    "iso:country":"GB",
    "wof:name":"W10 6DQ",
    "wof:placetype":"postalcode"
},
  "geometry": {"coordinates":[-0.22112830337751,51.52152211142914],"type":"Point"}
}