{
  "type": "Feature",
  "properties": {
    "iso:country":"GB",
    "wof:name":"PE6 7SH",
    "wof:placetype":"postalcode"
},
  "geometry": {"coordinates":[-0.22840327026926,52.63475901806746],"type":"Point"}
}