{
  "type": "Feature",
  "properties": {
    "iso:country": "GB",
    "wof:name": "FY7 7DJ",
    "wof:placetype": "postalcode"
  },
  "geometry": {"coordinates":[-3.028967,53.918048],"type":"Point"}
}
