{
  "type": "Feature",
  "properties": {
    "date:inception_lower": "2008-07-01",
    "date:inception_upper": "2008-07-01",
    "iso:country": "GB",
    "wof:name": "IV6 7PD",
    "wof:placetype": "postalcode"
  },
  "geometry": {"coordinates":[-4.471657,57.52306],"type":"Point"}
}
