{
  "type": "Feature",
  "properties": {
    "iso:country": "GB",
    "wof:name": "IV6 7PD",
    "wof:placetype": "postalcode"
  },
  "geometry": {"coordinates":[-4.471657,57.52306],"type":"Point"}
}
