{
  "type": "Feature",
  "properties": {
    "iso:country":"GB",
    "wof:name":"PA3 3AJ",
    "wof:placetype":"postalcode"
},
  "geometry": {"coordinates":[-4.48736332051957,55.84996663023456],"type":"Point"}
}