{
  "type": "Feature",
  "properties": {
    "date:inception_lower": "1980-01-01",
    "date:inception_upper": "1980-01-01",
    "iso:country": "GB",
    "wof:name": "PA3 3AJ",
    "wof:placetype": "postalcode"
  },
  "geometry": {"coordinates":[-4.486902,55.849252],"type":"Point"}
}
