{
  "type": "Feature",
  "properties": {
    "iso:country":"GB",
    "wof:name":"LS16 8JR",
    "wof:placetype":"postalcode"
},
  "geometry": {"coordinates":[-1.57799726629714,53.85721194249269],"type":"Point"}
}