{
  "type": "Feature",
  "properties": {
    "iso:country":"GB",
    "wof:name":"NE40 4PE",
    "wof:placetype":"postalcode"
},
  "geometry": {"coordinates":[-1.79319225779823,54.96844877580763],"type":"Point"}
}