{
  "type": "Feature",
  "properties": {
    "iso:country":"GB",
    "wof:name":"LS19 7YF",
    "wof:placetype":"postalcode"
},
  "geometry": {"coordinates":[-1.69361967724375,53.87161063481613],"type":"Point"}
}