{
  "type": "Feature",
  "properties": {
    "iso:country":"GB",
    "wof:name":"LN4 2RH",
    "wof:placetype":"postalcode"
},
  "geometry": {"coordinates":[-0.51880921575116,53.21539700912879],"type":"Point"}
}