{
  "type": "Feature",
  "properties": {
    "iso:country": "GB",
    "wof:name": "LS27 7TQ",
    "wof:placetype": "postalcode"
  },
  "geometry": {"coordinates":[-1.603901,53.757578],"type":"Point"}
}
