{
  "type": "Feature",
  "properties": {
    "iso:country":"GB",
    "wof:name":"LS27 7TQ",
    "wof:placetype":"postalcode"
},
  "geometry": {"coordinates":[-1.60390078575432,53.75757825485064],"type":"Point"}
}