{
  "type": "Feature",
  "properties": {
    "date:inception_lower": "1988-03-01",
    "date:inception_upper": "1988-03-01",
    "iso:country": "GB",
    "wof:name": "LS27 7TQ",
    "wof:placetype": "postalcode"
  },
  "geometry": {"coordinates":[-1.603901,53.757578],"type":"Point"}
}
