{
  "type": "Feature",
  "properties": {
    "iso:country":"GB",
    "wof:name":"GL56 0HZ",
    "wof:placetype":"postalcode"
},
  "geometry": {"coordinates":[-1.69135351434317,51.98766138295739],"type":"Point"}
}