{
  "type": "Feature",
  "properties": {
    "iso:country":"GB",
    "wof:name":"OL7 9SF",
    "wof:placetype":"postalcode"
},
  "geometry": {"coordinates":[-2.11746610722878,53.49786619672957],"type":"Point"}
}