{
  "type": "Feature",
  "properties": {
    "date:inception_lower": "1982-03-01",
    "date:inception_upper": "1982-03-01",
    "iso:country": "GB",
    "wof:name": "OL7 9SF",
    "wof:placetype": "postalcode"
  },
  "geometry": {"coordinates":[-2.117466,53.497866],"type":"Point"}
}
