{
  "type": "Feature",
  "properties": {
    "date:inception_lower": "2021-12-01",
    "date:inception_upper": "2021-12-01",
    "iso:country": "GB",
    "wof:name": "CM7 5XD",
    "wof:placetype": "postalcode"
  },
  "geometry": {"coordinates":[0.555096,51.894248],"type":"Point"}
}
