{
  "type": "Feature",
  "properties": {
    "date:inception_lower": "2002-12-01",
    "date:inception_upper": "2002-12-01",
    "iso:country": "GB",
    "wof:name": "AB33 8JJ",
    "wof:placetype": "postalcode"
  },
  "geometry": {"coordinates":[-2.693018,57.173371],"type":"Point"}
}
