{
  "type": "Feature",
  "properties": {
    "iso:country":"GB",
    "wof:name":"AB39 2EU",
    "wof:placetype":"postalcode"
},
  "geometry": {"coordinates":[-2.21865461645675,56.96714819623064],"type":"Point"}
}