{
  "type": "Feature",
  "properties": {
    "iso:country":"GB",
    "wof:name":"S42 5LU",
    "wof:placetype":"postalcode"
},
  "geometry": {"coordinates":[-1.39213998074224,53.17910245845569],"type":"Point"}
}