{
  "type": "Feature",
  "properties": {
    "date:inception_lower": "1980-01-01",
    "date:inception_upper": "1980-01-01",
    "iso:country": "GB",
    "wof:name": "S42 5LU",
    "wof:placetype": "postalcode"
  },
  "geometry": {"coordinates":[-1.39211,53.179111],"type":"Point"}
}
