{
  "type": "Feature",
  "properties": {
    "iso:country":"GB",
    "wof:name":"RH14 9LH",
    "wof:placetype":"postalcode"
},
  "geometry": {"coordinates":[-0.45558670172184,51.02135192413087],"type":"Point"}
}