{
  "type": "Feature",
  "properties": {
    "iso:country": "GB",
    "wof:name": "RH14 9LH",
    "wof:placetype": "postalcode"
  },
  "geometry": {"coordinates":[-0.455587,51.021352],"type":"Point"}
}
