{
  "type": "Feature",
  "properties": {
    "date:inception_lower": "2013-05-01",
    "date:inception_upper": "2013-05-01",
    "iso:country": "GB",
    "wof:name": "SA73 2DF",
    "wof:placetype": "postalcode"
  },
  "geometry": {"coordinates":[-5.033066,51.71232],"type":"Point"}
}
