{
  "type": "Feature",
  "properties": {
    "iso:country":"GB",
    "wof:name":"SA73 2DF",
    "wof:placetype":"postalcode"
},
  "geometry": {"coordinates":[-5.03301659626717,51.71233495699041],"type":"Point"}
}