{
  "type": "Feature",
  "properties": {
    "iso:country": "GB",
    "wof:name": "DY9 8TR",
    "wof:placetype": "postalcode"
  },
  "geometry": {"coordinates":[-2.108569,52.455717],"type":"Point"}
}
