{
  "type": "Feature",
  "properties": {
    "iso:country":"GB",
    "wof:name":"DY9 8TR",
    "wof:placetype":"postalcode"
},
  "geometry": {"coordinates":[-2.10858959241279,52.4557111488222],"type":"Point"}
}