{
  "type": "Feature",
  "properties": {
    "iso:country":"GB",
    "wof:name":"RG8 7JY",
    "wof:placetype":"postalcode"
},
  "geometry": {"coordinates":[-1.07715346522041,51.4823014728815],"type":"Point"}
}