{
  "type": "Feature",
  "properties": {
    "iso:country": "GB",
    "wof:name": "DE72 2AD",
    "wof:placetype": "postalcode"
  },
  "geometry": {"coordinates":[-1.37282,52.866733],"type":"Point"}
}
