{
  "type": "Feature",
  "properties": {
    "iso:country":"GB",
    "wof:name":"SW4 8PG",
    "wof:placetype":"postalcode"
},
  "geometry": {"coordinates":[-0.14109083856262,51.44875429611437],"type":"Point"}
}