{
  "type": "Feature",
  "properties": {
    "iso:country":"GB",
    "wof:name":"BD21 2NH",
    "wof:placetype":"postalcode"
},
  "geometry": {"coordinates":[-1.92163265475648,53.86740973738563],"type":"Point"}
}