{
  "type": "Feature",
  "properties": {
    "iso:country": "GB",
    "wof:name": "HS2 0QN",
    "wof:placetype": "postalcode"
  },
  "geometry": {"coordinates":[-6.524789,58.348497],"type":"Point"}
}
