{
  "type": "Feature",
  "properties": {
    "date:inception_lower":"1995-07-01",
    "date:inception_upper":"1995-07-31",
    "iso:country":"GB",
    "wof:name":"HS2 0QN",
    "wof:placetype":"postalcode"
},
  "geometry": {"coordinates":[-6.524789,58.348497],"type":"Point"}
}