{
  "type": "Feature",
  "properties": {
    "iso:country": "GB",
    "wof:name": "CF72 8ED",
    "wof:placetype": "postalcode"
  },
  "geometry": {"coordinates":[-3.375949,51.54231],"type":"Point"}
}
