{
  "type": "Feature",
  "properties": {
    "iso:country": "GB",
    "wof:name": "HU9 4BN",
    "wof:placetype": "postalcode"
  },
  "geometry": {"coordinates":[-0.258049,53.774837],"type":"Point"}
}
