{
  "type": "Feature",
  "properties": {
    "iso:country":"GB",
    "wof:name":"HU9 4BN",
    "wof:placetype":"postalcode"
},
  "geometry": {"coordinates":[-0.25804935806103,53.77483698759558],"type":"Point"}
}