{
  "type": "Feature",
  "properties": {
    "iso:country":"GB",
    "wof:name":"CR0 9BE",
    "wof:placetype":"postalcode"
},
  "geometry": {"coordinates":[-0.03290371147447,51.35167418704489],"type":"Point"}
}