{
  "type": "Feature",
  "properties": {
    "iso:country": "GB",
    "wof:name": "CR0 9BE",
    "wof:placetype": "postalcode"
  },
  "geometry": {"coordinates":[-0.032904,51.351674],"type":"Point"}
}
