{
  "type": "Feature",
  "properties": {
    "date:inception_lower": "2002-06-01",
    "date:inception_upper": "2002-06-01",
    "iso:country": "GB",
    "wof:name": "DY10 3DB",
    "wof:placetype": "postalcode"
  },
  "geometry": {"coordinates":[-2.228983,52.382243],"type":"Point"}
}
