{
  "type": "Feature",
  "properties": {
    "iso:country":"GB",
    "wof:name":"DY10 3DB",
    "wof:placetype":"postalcode"
},
  "geometry": {"coordinates":[-2.22898258293846,52.38224305351622],"type":"Point"}
}