{
  "type": "Feature",
  "properties": {
    "iso:country":"GB",
    "wof:name":"LN6 7SP",
    "wof:placetype":"postalcode"
},
  "geometry": {"coordinates":[-0.55142898251789,53.21358650060886],"type":"Point"}
}