{
  "type": "Feature",
  "properties": {
    "iso:country":"GB",
    "wof:name":"LD2 3LS",
    "wof:placetype":"postalcode"
},
  "geometry": {"coordinates":[-3.57939323444691,52.17202690786468],"type":"Point"}
}