{
  "type": "Feature",
  "properties": {
    "iso:country":"GB",
    "wof:name":"CO2 7LL",
    "wof:placetype":"postalcode"
},
  "geometry": {"coordinates":[0.91095852728926,51.88067995714879],"type":"Point"}
}