{
  "type": "Feature",
  "properties": {
    "iso:country": "GB",
    "wof:name": "SA18 3US",
    "wof:placetype": "postalcode"
  },
  "geometry": {"coordinates":[-4.008833,51.814965],"type":"Point"}
}
