{
  "type": "Feature",
  "properties": {
    "iso:country":"GB",
    "wof:name":"SA18 3US",
    "wof:placetype":"postalcode"
},
  "geometry": {"coordinates":[-4.00880410608387,51.81496591297331],"type":"Point"}
}