{
  "type": "Feature",
  "properties": {
    "date:inception_lower":"1980-01-01",
    "date:inception_upper":"1980-01-31",
    "iso:country":"GB",
    "wof:name":"SA18 3US",
    "wof:placetype":"postalcode"
},
  "geometry": {"coordinates":[-4.008833,51.814965],"type":"Point"}
}