{
  "type": "Feature",
  "properties": {
    "date:inception_lower": "1991-01-01",
    "date:inception_upper": "1991-01-01",
    "iso:country": "GB",
    "wof:name": "RH10 7AG",
    "wof:placetype": "postalcode"
  },
  "geometry": {"coordinates":[-0.157225,51.118038],"type":"Point"}
}
