{
  "type": "Feature",
  "properties": {
    "iso:country":"GB",
    "wof:name":"RH10 7AG",
    "wof:placetype":"postalcode"
},
  "geometry": {"coordinates":[-0.15722470617795,51.1180377946655],"type":"Point"}
}