{
  "type": "Feature",
  "properties": {
    "date:inception_lower": "2006-11-01",
    "date:inception_upper": "2006-11-01",
    "iso:country": "GB",
    "wof:name": "WF7 7RW",
    "wof:placetype": "postalcode"
  },
  "geometry": {"coordinates":[-1.350324,53.642034],"type":"Point"}
}
