{
  "type": "Feature",
  "properties": {
    "iso:country":"GB",
    "wof:name":"WF7 7RW",
    "wof:placetype":"postalcode"
},
  "geometry": {"coordinates":[-1.35032368031729,53.64203400255123],"type":"Point"}
}