{
  "type": "Feature",
  "properties": {
    "date:inception_lower": "2004-07-01",
    "date:inception_upper": "2004-07-01",
    "iso:country": "GB",
    "wof:name": "DN14 6FE",
    "wof:placetype": "postalcode"
  },
  "geometry": {"coordinates":[-0.86395,53.717004],"type":"Point"}
}
