{
  "type": "Feature",
  "properties": {
    "iso:country": "GB",
    "wof:name": "DN14 6FE",
    "wof:placetype": "postalcode"
  },
  "geometry": {"coordinates":[-0.86395,53.717004],"type":"Point"}
}
