{
  "type": "Feature",
  "properties": {
    "date:inception_lower": "1980-01-01",
    "date:inception_upper": "1980-01-01",
    "iso:country": "GB",
    "wof:name": "S62 5HG",
    "wof:placetype": "postalcode"
  },
  "geometry": {"coordinates":[-1.329285,53.462382],"type":"Point"}
}
