{
  "type": "Feature",
  "properties": {
    "iso:country": "GB",
    "wof:name": "SE11 5UL",
    "wof:placetype": "postalcode"
  },
  "geometry": {"coordinates":[-0.113206,51.489441],"type":"Point"}
}
