{
  "type": "Feature",
  "properties": {
    "iso:country":"GB",
    "wof:name":"SE11 5UL",
    "wof:placetype":"postalcode"
},
  "geometry": {"coordinates":[-0.11320572518783,51.48944094030116],"type":"Point"}
}