{
  "type": "Feature",
  "properties": {
    "iso:country":"GB",
    "wof:name":"G31 3DT",
    "wof:placetype":"postalcode"
},
  "geometry": {"coordinates":[-4.21358588975618,55.86452762481606],"type":"Point"}
}