{
  "type": "Feature",
  "properties": {
    "iso:country": "GB",
    "wof:name": "NE29 8NB",
    "wof:placetype": "postalcode"
  },
  "geometry": {"coordinates":[-1.472185,55.014865],"type":"Point"}
}
