{
  "type": "Feature",
  "properties": {
    "iso:country":"GB",
    "wof:name":"G20 9TW",
    "wof:placetype":"postalcode"
},
  "geometry": {"coordinates":[-4.2801375750541,55.88473827554383],"type":"Point"}
}