{
  "type": "Feature",
  "properties": {
    "iso:country":"GB",
    "wof:name":"ST2 9LA",
    "wof:placetype":"postalcode"
},
  "geometry": {"coordinates":[-2.13799521152471,53.01372633192408],"type":"Point"}
}