{
  "type": "Feature",
  "properties": {
    "date:inception_lower": "1980-01-01",
    "date:inception_upper": "1980-01-01",
    "iso:country": "GB",
    "wof:name": "ST2 9LA",
    "wof:placetype": "postalcode"
  },
  "geometry": {"coordinates":[-2.137995,53.013726],"type":"Point"}
}
