{
  "type": "Feature",
  "properties": {
    "iso:country": "GB",
    "wof:name": "SP2 0FW",
    "wof:placetype": "postalcode"
  },
  "geometry": {"coordinates":[-1.854323,51.082992],"type":"Point"}
}
