{
  "type": "Feature",
  "properties": {
    "iso:country":"GB",
    "wof:name":"ME17 1AX",
    "wof:placetype":"postalcode"
},
  "geometry": {"coordinates":[0.68710344689662,51.24486308413895],"type":"Point"}
}