{
  "type": "Feature",
  "properties": {
    "date:inception_lower": "1980-01-01",
    "date:inception_upper": "1980-01-01",
    "iso:country": "GB",
    "wof:name": "ME17 1AX",
    "wof:placetype": "postalcode"
  },
  "geometry": {"coordinates":[0.687103,51.244863],"type":"Point"}
}
