{
  "type": "Feature",
  "properties": {
    "date:inception_lower":"1980-01-01",
    "date:inception_upper":"1980-01-31",
    "iso:country":"GB",
    "wof:name":"RM10 8BW",
    "wof:placetype":"postalcode"
},
  "geometry": {"coordinates":[0.151667,51.547164],"type":"Point"}
}