{
  "type": "Feature",
  "properties": {
    "iso:country":"GB",
    "wof:name":"HP16 9LL",
    "wof:placetype":"postalcode"
},
  "geometry": {"coordinates":[-0.68030283143644,51.71930960505358],"type":"Point"}
}