{
  "type": "Feature",
  "properties": {
    "date:inception_lower":"1980-01-01",
    "date:inception_upper":"1980-01-31",
    "iso:country":"GB",
    "wof:name":"KT12 1BN",
    "wof:placetype":"postalcode"
},
  "geometry": {"coordinates":[-0.424682,51.384117],"type":"Point"}
}