{
  "type": "Feature",
  "properties": {
    "iso:country": "GB",
    "wof:name": "KT12 1BN",
    "wof:placetype": "postalcode"
  },
  "geometry": {"coordinates":[-0.424682,51.384117],"type":"Point"}
}
