{
  "type": "Feature",
  "properties": {
    "date:inception_lower": "2021-05-01",
    "date:inception_upper": "2021-05-01",
    "iso:country": "GB",
    "wof:name": "CO16 8GY",
    "wof:placetype": "postalcode"
  },
  "geometry": {"coordinates":[1.117436,51.79688],"type":"Point"}
}
