{
  "type": "Feature",
  "properties": {
    "iso:country":"GB",
    "wof:name":"B10 9AP",
    "wof:placetype":"postalcode"
},
  "geometry": {"coordinates":[-1.85271169897325,52.47221144614518],"type":"Point"}
}