{
  "type": "Feature",
  "properties": {
    "iso:country":"GB",
    "wof:name":"W9 2NA",
    "wof:placetype":"postalcode"
},
  "geometry": {"coordinates":[-0.19370307722916,51.52866563084416],"type":"Point"}
}