{
  "type": "Feature",
  "properties": {
    "iso:country":"GB",
    "wof:name":"NR14 7LR",
    "wof:placetype":"postalcode"
},
  "geometry": {"coordinates":[1.34215612873829,52.56351757489271],"type":"Point"}
}