{
  "type": "Feature",
  "properties": {
    "date:inception_lower": "2017-02-01",
    "date:inception_upper": "2017-02-01",
    "iso:country": "GB",
    "wof:name": "PO14 1FQ",
    "wof:placetype": "postalcode"
  },
  "geometry": {"coordinates":[-1.19841,50.850163],"type":"Point"}
}
