{
  "type": "Feature",
  "properties": {
    "iso:country": "GB",
    "wof:name": "NR20 5TB",
    "wof:placetype": "postalcode"
  },
  "geometry": {"coordinates":[0.845348,52.774382],"type":"Point"}
}
