{
  "type": "Feature",
  "properties": {
    "iso:country":"GB",
    "wof:name":"NR20 5TB",
    "wof:placetype":"postalcode"
},
  "geometry": {"coordinates":[0.84534805480071,52.77438163682344],"type":"Point"}
}