{
  "type": "Feature",
  "properties": {
    "iso:country":"GB",
    "wof:name":"OX5 2UH",
    "wof:placetype":"postalcode"
},
  "geometry": {"coordinates":[-1.18729494619053,51.83782787956622],"type":"Point"}
}