{
  "type": "Feature",
  "properties": {
    "iso:country":"GB",
    "wof:name":"SA70 8QA",
    "wof:placetype":"postalcode"
},
  "geometry": {"coordinates":[-4.81968256981671,51.66366363420838],"type":"Point"}
}