{
  "type": "Feature",
  "properties": {
    "date:inception_lower": "1980-01-01",
    "date:inception_upper": "1980-01-01",
    "iso:country": "GB",
    "wof:name": "SA70 8QA",
    "wof:placetype": "postalcode"
  },
  "geometry": {"coordinates":[-4.814771,51.662992],"type":"Point"}
}
