{
  "type": "Feature",
  "properties": {
    "date:inception_lower":"1986-04-01",
    "date:inception_upper":"1986-04-30",
    "iso:country":"GB",
    "wof:name":"PR5 5BE",
    "wof:placetype":"postalcode"
},
  "geometry": {"coordinates":[-2.675526,53.725219],"type":"Point"}
}