{
  "type": "Feature",
  "properties": {
    "iso:country": "GB",
    "wof:name": "KA1 4UJ",
    "wof:placetype": "postalcode"
  },
  "geometry": {"coordinates":[-4.505912,55.588006],"type":"Point"}
}
