{
  "type": "Feature",
  "properties": {
    "date:inception_lower": "1980-01-01",
    "date:inception_upper": "1980-01-01",
    "iso:country": "GB",
    "wof:name": "WS2 9QJ",
    "wof:placetype": "postalcode"
  },
  "geometry": {"coordinates":[-1.999361,52.573302],"type":"Point"}
}
