{
  "type": "Feature",
  "properties": {
    "iso:country":"GB",
    "wof:name":"WS2 9QJ",
    "wof:placetype":"postalcode"
},
  "geometry": {"coordinates":[-1.99858443843691,52.57317837914414],"type":"Point"}
}