{
  "type": "Feature",
  "properties": {
    "date:inception_lower": "1993-08-01",
    "date:inception_upper": "1993-08-01",
    "iso:country": "GB",
    "wof:name": "RG24 8AX",
    "wof:placetype": "postalcode"
  },
  "geometry": {"coordinates":[-1.055057,51.275977],"type":"Point"}
}
