{
  "type": "Feature",
  "properties": {
    "iso:country":"GB",
    "wof:name":"RG24 8AX",
    "wof:placetype":"postalcode"
},
  "geometry": {"coordinates":[-1.05505661733583,51.27597681811935],"type":"Point"}
}