{
  "type": "Feature",
  "properties": {
    "iso:country":"GB",
    "wof:name":"OX13 5NG",
    "wof:placetype":"postalcode"
},
  "geometry": {"coordinates":[-1.4270183396147,51.68122856901151],"type":"Point"}
}