{
  "type": "Feature",
  "properties": {
    "iso:country": "GB",
    "wof:name": "OX13 5NG",
    "wof:placetype": "postalcode"
  },
  "geometry": {"coordinates":[-1.427018,51.681229],"type":"Point"}
}
