{
  "type": "Feature",
  "properties": {
    "date:inception_lower": "2019-08-01",
    "date:inception_upper": "2019-08-01",
    "iso:country": "GB",
    "wof:name": "EH11 4FW",
    "wof:placetype": "postalcode"
  },
  "geometry": {"coordinates":[-3.305653,55.924888],"type":"Point"}
}
