{
  "type": "Feature",
  "properties": {
    "iso:country":"GB",
    "wof:name":"SA32 8BL",
    "wof:placetype":"postalcode"
},
  "geometry": {"coordinates":[-4.15650983105869,51.82424583804767],"type":"Point"}
}