{
  "type": "Feature",
  "properties": {
    "iso:country":"GB",
    "wof:name":"DG11 1AR",
    "wof:placetype":"postalcode"
},
  "geometry": {"coordinates":[-3.29171521779507,55.04820656716485],"type":"Point"}
}