{
  "type": "Feature",
  "properties": {
    "date:inception_lower": "2014-11-01",
    "date:inception_upper": "2014-11-01",
    "iso:country": "GB",
    "wof:name": "NP20 2QS",
    "wof:placetype": "postalcode"
  },
  "geometry": {"coordinates":[-3.002174,51.573355],"type":"Point"}
}
