{
  "type": "Feature",
  "properties": {
    "iso:country":"GB",
    "wof:name":"IP22 1SN",
    "wof:placetype":"postalcode"
},
  "geometry": {"coordinates":[1.07797344137819,52.3656925032903],"type":"Point"}
}