{
  "type": "Feature",
  "properties": {
    "date:inception_lower":"1980-01-01",
    "date:inception_upper":"1980-01-31",
    "iso:country":"GB",
    "wof:name":"IP22 1SN",
    "wof:placetype":"postalcode"
},
  "geometry": {"coordinates":[1.078003,52.36573],"type":"Point"}
}