{
  "type": "Feature",
  "properties": {
    "date:inception_lower": "1980-01-01",
    "date:inception_upper": "1980-01-01",
    "iso:country": "GB",
    "wof:name": "IP22 1SN",
    "wof:placetype": "postalcode"
  },
  "geometry": {"coordinates":[1.078049,52.365746],"type":"Point"}
}
