{
  "type": "Feature",
  "properties": {
    "iso:country":"GB",
    "wof:name":"TA10 0PX",
    "wof:placetype":"postalcode"
},
  "geometry": {"coordinates":[-2.86082158132284,51.02645794575871],"type":"Point"}
}