{
  "type": "Feature",
  "properties": {
    "date:inception_lower": "1980-01-01",
    "date:inception_upper": "1980-01-01",
    "iso:country": "GB",
    "wof:name": "TA10 0PX",
    "wof:placetype": "postalcode"
  },
  "geometry": {"coordinates":[-2.860822,51.026458],"type":"Point"}
}
