{
  "type": "Feature",
  "properties": {
    "iso:country":"GB",
    "wof:name":"BA6 8LD",
    "wof:placetype":"postalcode"
},
  "geometry": {"coordinates":[-2.68913146611958,51.13912776077236],"type":"Point"}
}