{
  "type": "Feature",
  "properties": {
    "iso:country":"GB",
    "wof:name":"PL19 0NW",
    "wof:placetype":"postalcode"
},
  "geometry": {"coordinates":[-4.15400819021677,50.60123374649098],"type":"Point"}
}