{
  "type": "Feature",
  "properties": {
    "iso:country": "GB",
    "wof:name": "PL19 0NW",
    "wof:placetype": "postalcode"
  },
  "geometry": {"coordinates":[-4.154008,50.601234],"type":"Point"}
}
