{
  "type": "Feature",
  "properties": {
    "iso:country": "GB",
    "wof:name": "EH26 8NA",
    "wof:placetype": "postalcode"
  },
  "geometry": {"coordinates":[-3.220703,55.824982],"type":"Point"}
}
