{
  "type": "Feature",
  "properties": {
    "iso:country":"GB",
    "wof:name":"SY4 5QQ",
    "wof:placetype":"postalcode"
},
  "geometry": {"coordinates":[-2.67395536025499,52.83933421991085],"type":"Point"}
}