{
  "type": "Feature",
  "properties": {
    "iso:country": "GB",
    "wof:name": "SY4 5QQ",
    "wof:placetype": "postalcode"
  },
  "geometry": {"coordinates":[-2.673955,52.839334],"type":"Point"}
}
