{
  "type": "Feature",
  "properties": {
    "iso:country":"GB",
    "wof:name":"SN10 3EJ",
    "wof:placetype":"postalcode"
},
  "geometry": {"coordinates":[-1.97809722486801,51.34789827976211],"type":"Point"}
}