{
  "type": "Feature",
  "properties": {
    "iso:country": "GB",
    "wof:name": "CF82 7PY",
    "wof:placetype": "postalcode"
  },
  "geometry": {"coordinates":[-3.224686,51.640244],"type":"Point"}
}
