{
  "type": "Feature",
  "properties": {
    "iso:country":"GB",
    "wof:name":"CF82 7PY",
    "wof:placetype":"postalcode"
},
  "geometry": {"coordinates":[-3.22468640243778,51.64024389974679],"type":"Point"}
}