{
  "type": "Feature",
  "properties": {
    "iso:country": "GB",
    "wof:name": "CM2 7FR",
    "wof:placetype": "postalcode"
  },
  "geometry": {"coordinates":[0.500522,51.718039],"type":"Point"}
}
