{
  "type": "Feature",
  "properties": {
    "date:inception_lower": "2017-08-01",
    "date:inception_upper": "2017-08-01",
    "iso:country": "GB",
    "wof:name": "CM2 7FR",
    "wof:placetype": "postalcode"
  },
  "geometry": {"coordinates":[0.500522,51.718039],"type":"Point"}
}
