{
  "type": "Feature",
  "properties": {
    "iso:country": "GB",
    "wof:name": "KW14 8AN",
    "wof:placetype": "postalcode"
  },
  "geometry": {"coordinates":[-3.520234,58.595678],"type":"Point"}
}
