{
  "type": "Feature",
  "properties": {
    "date:inception_lower": "2010-05-01",
    "date:inception_upper": "2010-05-01",
    "iso:country": "GB",
    "wof:name": "PH16 5FH",
    "wof:placetype": "postalcode"
  },
  "geometry": {"coordinates":[-3.721798,56.708556],"type":"Point"}
}
