{
  "type": "Feature",
  "properties": {
    "iso:country": "GB",
    "wof:name": "PH16 5FH",
    "wof:placetype": "postalcode"
  },
  "geometry": {"coordinates":[-3.721825,56.70843],"type":"Point"}
}
