{
  "type": "Feature",
  "properties": {
    "iso:country":"GB",
    "wof:name":"FK1 4LW",
    "wof:placetype":"postalcode"
},
  "geometry": {"coordinates":[-3.81612052504539,56.00350593867577],"type":"Point"}
}