{
  "type": "Feature",
  "properties": {
    "date:inception_lower":"1992-02-01",
    "date:inception_upper":"1992-02-29",
    "iso:country":"GB",
    "wof:name":"FK1 4LW",
    "wof:placetype":"postalcode"
},
  "geometry": {"coordinates":[-3.81612,56.003506],"type":"Point"}
}