{
  "type": "Feature",
  "properties": {
    "iso:country":"GB",
    "wof:name":"NG24 4LX",
    "wof:placetype":"postalcode"
},
  "geometry": {"coordinates":[-0.81364206347378,53.0608409269863],"type":"Point"}
}