{
  "type": "Feature",
  "properties": {
    "iso:country":"GB",
    "wof:name":"HU3 5BS",
    "wof:placetype":"postalcode"
},
  "geometry": {"coordinates":[-0.3783900932295,53.73743151953123],"type":"Point"}
}