{
  "type": "Feature",
  "properties": {
    "iso:country":"GB",
    "wof:name":"DN35 8EQ",
    "wof:placetype":"postalcode"
},
  "geometry": {"coordinates":[-0.03836355018042,53.5565260792207],"type":"Point"}
}