{
  "type": "Feature",
  "properties": {
    "date:inception_lower": "1995-07-01",
    "date:inception_upper": "1995-07-01",
    "iso:country": "GB",
    "wof:name": "RG17 8NU",
    "wof:placetype": "postalcode"
  },
  "geometry": {"coordinates":[-1.53432,51.507953],"type":"Point"}
}
