{
  "type": "Feature",
  "properties": {
    "iso:country":"GB",
    "wof:name":"B94 6BT",
    "wof:placetype":"postalcode"
},
  "geometry": {"coordinates":[-1.81282276006469,52.36986624455042],"type":"Point"}
}