{
  "type": "Feature",
  "properties": {
    "iso:country": "GB",
    "wof:name": "LU4 9DN",
    "wof:placetype": "postalcode"
  },
  "geometry": {"coordinates":[-0.454813,51.899561],"type":"Point"}
}
