{
  "type": "Feature",
  "properties": {
    "iso:country": "GB",
    "wof:name": "WV6 8DX",
    "wof:placetype": "postalcode"
  },
  "geometry": {"coordinates":[-2.195918,52.585503],"type":"Point"}
}
