{
  "type": "Feature",
  "properties": {
    "iso:country":"GB",
    "wof:name":"SA10 6YF",
    "wof:placetype":"postalcode"
},
  "geometry": {"coordinates":[-3.83716559963919,51.66096825777043],"type":"Point"}
}