{
  "type": "Feature",
  "properties": {
    "date:inception_lower": "1980-01-01",
    "date:inception_upper": "1980-01-01",
    "iso:country": "GB",
    "wof:name": "SW11 2SE",
    "wof:placetype": "postalcode"
  },
  "geometry": {"coordinates":[-0.172061,51.467145],"type":"Point"}
}
