{
  "type": "Feature",
  "properties": {
    "iso:country":"GB",
    "wof:name":"SW11 2SE",
    "wof:placetype":"postalcode"
},
  "geometry": {"coordinates":[-0.17206110788656,51.46714546878636],"type":"Point"}
}