{
  "type": "Feature",
  "properties": {
    "date:inception_lower": "1998-06-01",
    "date:inception_upper": "1998-06-01",
    "iso:country": "GB",
    "wof:name": "TR13 8BW",
    "wof:placetype": "postalcode"
  },
  "geometry": {"coordinates":[-5.267963,50.094569],"type":"Point"}
}
