{
  "type": "Feature",
  "properties": {
    "iso:country": "GB",
    "wof:name": "BS30 7DG",
    "wof:placetype": "postalcode"
  },
  "geometry": {"coordinates":[-2.495986,51.441631],"type":"Point"}
}
