{
  "type": "Feature",
  "properties": {
    "iso:country": "GB",
    "wof:name": "CV3 2TJ",
    "wof:placetype": "postalcode"
  },
  "geometry": {"coordinates":[-1.436943,52.39382],"type":"Point"}
}
