{
  "type": "Feature",
  "properties": {
    "iso:country": "GB",
    "wof:name": "HP21 9XS",
    "wof:placetype": "postalcode"
  },
  "geometry": {"coordinates":[-0.788524,51.799124],"type":"Point"}
}
