{
  "type": "Feature",
  "properties": {
    "iso:country":"GB",
    "wof:name":"M34 5UG",
    "wof:placetype":"postalcode"
},
  "geometry": {"coordinates":[-2.13691482730975,53.47070038163647],"type":"Point"}
}