{
  "type": "Feature",
  "properties": {
    "date:inception_lower":"2014-08-01",
    "date:inception_upper":"2014-08-31",
    "iso:country":"GB",
    "wof:name":"M34 5UG",
    "wof:placetype":"postalcode"
},
  "geometry": {"coordinates":[-2.137847,53.470329],"type":"Point"}
}