{
  "type": "Feature",
  "properties": {
    "iso:country": "GB",
    "wof:name": "M34 5UG",
    "wof:placetype": "postalcode"
  },
  "geometry": {"coordinates":[-2.138237,53.469987],"type":"Point"}
}
