{
  "type": "Feature",
  "properties": {
    "iso:country":"GB",
    "wof:name":"IP1 5EQ",
    "wof:placetype":"postalcode"
},
  "geometry": {"coordinates":[1.12985657656857,52.07296881117107],"type":"Point"}
}