{
  "type": "Feature",
  "properties": {
    "date:inception_lower":"1995-12-01",
    "date:inception_upper":"1995-12-31",
    "iso:country":"GB",
    "wof:name":"M28 0HN",
    "wof:placetype":"postalcode"
},
  "geometry": {"coordinates":[-2.416793,53.523353],"type":"Point"}
}