{
  "type": "Feature",
  "properties": {
    "iso:country":"GB",
    "wof:name":"M28 0HN",
    "wof:placetype":"postalcode"
},
  "geometry": {"coordinates":[-2.4167926143281,53.52335305866582],"type":"Point"}
}