{
  "type": "Feature",
  "properties": {
    "iso:country": "GB",
    "wof:name": "PR2 6EE",
    "wof:placetype": "postalcode"
  },
  "geometry": {"coordinates":[-2.656431,53.776836],"type":"Point"}
}
