{
  "type": "Feature",
  "properties": {
    "iso:country": "GB",
    "wof:name": "CF72 9DJ",
    "wof:placetype": "postalcode"
  },
  "geometry": {"coordinates":[-3.401326,51.518289],"type":"Point"}
}
