{
  "type": "Feature",
  "properties": {
    "iso:country": "GB",
    "wof:name": "SS14 3AR",
    "wof:placetype": "postalcode"
  },
  "geometry": {"coordinates":[0.449041,51.58423],"type":"Point"}
}
