{
  "type": "Feature",
  "properties": {
    "iso:country":"GB",
    "wof:name":"CH7 6PQ",
    "wof:placetype":"postalcode"
},
  "geometry": {"coordinates":[-3.17552956594668,53.20691450772163],"type":"Point"}
}