{
  "type": "Feature",
  "properties": {
    "date:inception_lower": "1985-10-01",
    "date:inception_upper": "1985-10-01",
    "iso:country": "GB",
    "wof:name": "ST4 8UF",
    "wof:placetype": "postalcode"
  },
  "geometry": {"coordinates":[-2.182699,52.97219],"type":"Point"}
}
