{
  "type": "Feature",
  "properties": {
    "iso:country":"GB",
    "wof:name":"TQ3 1BP",
    "wof:placetype":"postalcode"
},
  "geometry": {"coordinates":[-3.57595395993826,50.44986571468983],"type":"Point"}
}