{
  "type": "Feature",
  "properties": {
    "date:inception_lower": "1980-01-01",
    "date:inception_upper": "1980-01-01",
    "iso:country": "GB",
    "wof:name": "TQ3 1BP",
    "wof:placetype": "postalcode"
  },
  "geometry": {"coordinates":[-3.575954,50.449866],"type":"Point"}
}
