{
  "type": "Feature",
  "properties": {
    "iso:country":"GB",
    "wof:name":"TR13 8DH",
    "wof:placetype":"postalcode"
},
  "geometry": {"coordinates":[-5.26776092631599,50.09591522399925],"type":"Point"}
}