{
  "type": "Feature",
  "properties": {
    "iso:country": "GB",
    "wof:name": "DN11 8NW",
    "wof:placetype": "postalcode"
  },
  "geometry": {"coordinates":[-1.061291,53.421736],"type":"Point"}
}
