{
  "type": "Feature",
  "properties": {
    "date:inception_lower":"1980-01-01",
    "date:inception_upper":"1980-01-31",
    "iso:country":"GB",
    "wof:name":"DN11 8NW",
    "wof:placetype":"postalcode"
},
  "geometry": {"coordinates":[-1.061291,53.421736],"type":"Point"}
}