{
  "type": "Feature",
  "properties": {
    "iso:country":"GB",
    "wof:name":"CM9 6EH",
    "wof:placetype":"postalcode"
},
  "geometry": {"coordinates":[0.67469501823176,51.72766732293154],"type":"Point"}
}