{
  "type": "Feature",
  "properties": {
    "iso:country": "GB",
    "wof:name": "CM9 6EH",
    "wof:placetype": "postalcode"
  },
  "geometry": {"coordinates":[0.674695,51.727667],"type":"Point"}
}
