{
  "type": "Feature",
  "properties": {
    "iso:country":"GB",
    "wof:name":"OX28 6EG",
    "wof:placetype":"postalcode"
},
  "geometry": {"coordinates":[-1.49483039451914,51.79243680618099],"type":"Point"}
}