{
  "type": "Feature",
  "properties": {
    "iso:country": "GB",
    "wof:name": "AL5 5BE",
    "wof:placetype": "postalcode"
  },
  "geometry": {"coordinates":[-0.337787,51.825636],"type":"Point"}
}
