{
  "type": "Feature",
  "properties": {
    "iso:country":"GB",
    "wof:name":"HP13 6AJ",
    "wof:placetype":"postalcode"
},
  "geometry": {"coordinates":[-0.74375096130897,51.63105918155754],"type":"Point"}
}