{
  "type": "Feature",
  "properties": {
    "iso:country":"GB",
    "wof:name":"LA1 2QP",
    "wof:placetype":"postalcode"
},
  "geometry": {"coordinates":[-2.80997578144418,54.05804982645065],"type":"Point"}
}