{
  "type": "Feature",
  "properties": {
    "iso:country": "GB",
    "wof:name": "BS15 9NJ",
    "wof:placetype": "postalcode"
  },
  "geometry": {"coordinates":[-2.50303,51.451608],"type":"Point"}
}
