{
  "type": "Feature",
  "properties": {
    "date:inception_lower":"1997-12-01",
    "date:inception_upper":"1997-12-31",
    "iso:country":"GB",
    "wof:name":"BS15 9NJ",
    "wof:placetype":"postalcode"
},
  "geometry": {"coordinates":[-2.50303,51.451608],"type":"Point"}
}