{
  "type": "Feature",
  "properties": {
    "iso:country":"GB",
    "wof:name":"PR8 4SU",
    "wof:placetype":"postalcode"
},
  "geometry": {"coordinates":[-3.01329326766369,53.63123535612588],"type":"Point"}
}