{
  "type": "Feature",
  "properties": {
    "date:inception_lower": "1993-08-01",
    "date:inception_upper": "1993-08-01",
    "iso:country": "GB",
    "wof:name": "L8 0YB",
    "wof:placetype": "postalcode"
  },
  "geometry": {"coordinates":[-2.953501,53.395628],"type":"Point"}
}
