{
  "type": "Feature",
  "properties": {
    "iso:country":"GB",
    "wof:name":"YO7 2JF",
    "wof:placetype":"postalcode"
},
  "geometry": {"coordinates":[-1.28471986149512,54.27365540360014],"type":"Point"}
}