{
  "type": "Feature",
  "properties": {
    "date:inception_lower": "1980-01-01",
    "date:inception_upper": "1980-01-01",
    "iso:country": "GB",
    "wof:name": "YO7 2JF",
    "wof:placetype": "postalcode"
  },
  "geometry": {"coordinates":[-1.28472,54.273655],"type":"Point"}
}
