{
  "type": "Feature",
  "properties": {
    "iso:country":"GB",
    "wof:name":"N1 9RJ",
    "wof:placetype":"postalcode"
},
  "geometry": {"coordinates":[-0.11927370089226,51.53449208869704],"type":"Point"}
}