{
  "type": "Feature",
  "properties": {
    "date:inception_lower": "1980-01-01",
    "date:inception_upper": "1980-01-01",
    "iso:country": "GB",
    "wof:name": "OX5 3JL",
    "wof:placetype": "postalcode"
  },
  "geometry": {"coordinates":[-1.272477,51.878405],"type":"Point"}
}
