{
  "type": "Feature",
  "properties": {
    "iso:country":"GB",
    "wof:name":"CH1 3DR",
    "wof:placetype":"postalcode"
},
  "geometry": {"coordinates":[-2.88125076481194,53.19648350911162],"type":"Point"}
}