{
  "type": "Feature",
  "properties": {
    "date:inception_lower": "1980-01-01",
    "date:inception_upper": "1980-01-01",
    "iso:country": "GB",
    "wof:name": "CH1 3DR",
    "wof:placetype": "postalcode"
  },
  "geometry": {"coordinates":[-2.881251,53.196484],"type":"Point"}
}
