{
  "type": "Feature",
  "properties": {
    "date:inception_lower": "1980-01-01",
    "date:inception_upper": "1980-01-01",
    "iso:country": "GB",
    "wof:name": "SW19 3SJ",
    "wof:placetype": "postalcode"
  },
  "geometry": {"coordinates":[-0.203627,51.416106],"type":"Point"}
}
