{
  "type": "Feature",
  "properties": {
    "iso:country": "GB",
    "wof:name": "SW19 3SJ",
    "wof:placetype": "postalcode"
  },
  "geometry": {"coordinates":[-0.203666,51.416107],"type":"Point"}
}
