{
  "type": "Feature",
  "properties": {
    "iso:country":"GB",
    "wof:name":"NP23 6UD",
    "wof:placetype":"postalcode"
},
  "geometry": {"coordinates":[-3.19308784769272,51.75489760204756],"type":"Point"}
}