{
  "type": "Feature",
  "properties": {
    "iso:country": "GB",
    "wof:name": "DA11 9BY",
    "wof:placetype": "postalcode"
  },
  "geometry": {"coordinates":[0.318742,51.44967],"type":"Point"}
}
