{
  "type": "Feature",
  "properties": {
    "iso:country":"GB",
    "wof:name":"DA11 9BY",
    "wof:placetype":"postalcode"
},
  "geometry": {"coordinates":[0.31874180242484,51.4496695919788],"type":"Point"}
}