{
  "type": "Feature",
  "properties": {
    "date:inception_lower":"1980-01-01",
    "date:inception_upper":"1980-01-31",
    "iso:country":"GB",
    "wof:name":"BB11 5DU",
    "wof:placetype":"postalcode"
},
  "geometry": {"coordinates":[-2.279662,53.784968],"type":"Point"}
}