{
  "type": "Feature",
  "properties": {
    "iso:country":"GB",
    "wof:name":"M22 1GX",
    "wof:placetype":"postalcode"
},
  "geometry": {"coordinates":[-2.27841440532409,53.37577776000266],"type":"Point"}
}