{
  "type": "Feature",
  "properties": {
    "iso:country": "GB",
    "wof:name": "M22 1GX",
    "wof:placetype": "postalcode"
  },
  "geometry": {"coordinates":[-2.278414,53.375778],"type":"Point"}
}
