{
  "type": "Feature",
  "properties": {
    "iso:country": "GB",
    "wof:name": "PE19 5GH",
    "wof:placetype": "postalcode"
  },
  "geometry": {"coordinates":[-0.215541,52.276675],"type":"Point"}
}
