{
  "type": "Feature",
  "properties": {
    "iso:country":"GB",
    "wof:name":"CF43 3LF",
    "wof:placetype":"postalcode"
},
  "geometry": {"coordinates":[-3.43169269032596,51.63761403125341],"type":"Point"}
}