{
  "type": "Feature",
  "properties": {
    "iso:country": "GB",
    "wof:name": "WF10 5SH",
    "wof:placetype": "postalcode"
  },
  "geometry": {"coordinates":[-1.358254,53.718441],"type":"Point"}
}
