{
  "type": "Feature",
  "properties": {
    "date:inception_lower": "1980-01-01",
    "date:inception_upper": "1980-01-01",
    "iso:country": "GB",
    "wof:name": "RH5 6NL",
    "wof:placetype": "postalcode"
  },
  "geometry": {"coordinates":[-0.415407,51.195517],"type":"Point"}
}
