{
  "type": "Feature",
  "properties": {
    "iso:country": "GB",
    "wof:name": "RH5 6NL",
    "wof:placetype": "postalcode"
  },
  "geometry": {"coordinates":[-0.415407,51.195517],"type":"Point"}
}
