{
  "type": "Feature",
  "properties": {
    "iso:country":"GB",
    "wof:name":"RH5 6NL",
    "wof:placetype":"postalcode"
},
  "geometry": {"coordinates":[-0.41540748638674,51.19551696868795],"type":"Point"}
}