{
  "type": "Feature",
  "properties": {
    "iso:country":"GB",
    "wof:name":"LN11 0ZA",
    "wof:placetype":"postalcode"
},
  "geometry": {"coordinates":[-0.00971734995802,53.38051341992757],"type":"Point"}
}