{
  "type": "Feature",
  "properties": {
    "iso:country": "GB",
    "wof:name": "LN11 0ZA",
    "wof:placetype": "postalcode"
  },
  "geometry": {"coordinates":[-0.009717,53.380513],"type":"Point"}
}
