{
  "type": "Feature",
  "properties": {
    "iso:country":"GB",
    "wof:name":"BD16 1BX",
    "wof:placetype":"postalcode"
},
  "geometry": {"coordinates":[-1.87436234915251,53.83930951420014],"type":"Point"}
}