{
  "type": "Feature",
  "properties": {
    "iso:country": "GB",
    "wof:name": "IP20 9EA",
    "wof:placetype": "postalcode"
  },
  "geometry": {"coordinates":[1.304162,52.397264],"type":"Point"}
}
