{
  "type": "Feature",
  "properties": {
    "date:inception_lower":"1983-01-01",
    "date:inception_upper":"1983-01-31",
    "iso:country":"GB",
    "wof:name":"IP20 9EA",
    "wof:placetype":"postalcode"
},
  "geometry": {"coordinates":[1.304162,52.397264],"type":"Point"}
}