{
  "type": "Feature",
  "properties": {
    "iso:country":"GB",
    "wof:name":"LA22 9JG",
    "wof:placetype":"postalcode"
},
  "geometry": {"coordinates":[-3.04713789685865,54.4403100065067],"type":"Point"}
}