{
  "type": "Feature",
  "properties": {
    "date:inception_lower": "1980-01-01",
    "date:inception_upper": "1980-01-01",
    "iso:country": "GB",
    "wof:name": "LA22 9JG",
    "wof:placetype": "postalcode"
  },
  "geometry": {"coordinates":[-3.047138,54.44031],"type":"Point"}
}
