{
  "type": "Feature",
  "properties": {
    "iso:country":"GB",
    "wof:name":"BD18 4LN",
    "wof:placetype":"postalcode"
},
  "geometry": {"coordinates":[-1.79601264438774,53.83208363917717],"type":"Point"}
}