{
  "type": "Feature",
  "properties": {
    "date:inception_lower":"1980-01-01",
    "date:inception_upper":"1980-01-31",
    "iso:country":"GB",
    "wof:name":"DG7 2LA",
    "wof:placetype":"postalcode"
},
  "geometry": {"coordinates":[-4.191698,54.882404],"type":"Point"}
}