{
  "type": "Feature",
  "properties": {
    "date:inception_lower": "2022-12-01",
    "date:inception_upper": "2022-12-01",
    "iso:country": "GB",
    "wof:name": "DD9 7FE",
    "wof:placetype": "postalcode"
  },
  "geometry": {"coordinates":[-2.640236,56.726949],"type":"Point"}
}
