{
  "type": "Feature",
  "properties": {
    "iso:country":"GB",
    "wof:name":"SW1E 5NH",
    "wof:placetype":"postalcode"
},
  "geometry": {"coordinates":[-0.13954254739081,51.49674103146715],"type":"Point"}
}