{
  "type": "Feature",
  "properties": {
    "date:inception_lower": "1980-01-01",
    "date:inception_upper": "1980-01-01",
    "iso:country": "GB",
    "wof:name": "SW1E 5NH",
    "wof:placetype": "postalcode"
  },
  "geometry": {"coordinates":[-0.139543,51.496741],"type":"Point"}
}
