{
  "type": "Feature",
  "properties": {
    "date:inception_lower": "2019-03-01",
    "date:inception_upper": "2019-03-01",
    "iso:country": "GB",
    "wof:name": "BS8 2BF",
    "wof:placetype": "postalcode"
  },
  "geometry": {"coordinates":[-2.60902,51.462236],"type":"Point"}
}
