{
  "type": "Feature",
  "properties": {
    "iso:country":"GB",
    "wof:name":"SR2 8HZ",
    "wof:placetype":"postalcode"
},
  "geometry": {"coordinates":[-1.37780574097171,54.89769467508962],"type":"Point"}
}