{
  "type": "Feature",
  "properties": {
    "iso:country":"GB",
    "wof:name":"BR7 5LG",
    "wof:placetype":"postalcode"
},
  "geometry": {"coordinates":[0.05185043282903,51.40837731410384],"type":"Point"}
}