{
  "type": "Feature",
  "properties": {
    "iso:country":"GB",
    "wof:name":"S75 2TD",
    "wof:placetype":"postalcode"
},
  "geometry": {"coordinates":[-1.49435128882709,53.55988294251232],"type":"Point"}
}