{
  "type": "Feature",
  "properties": {
    "iso:country":"GB",
    "wof:name":"WD23 1HQ",
    "wof:placetype":"postalcode"
},
  "geometry": {"coordinates":[-0.34711466502289,51.63358226280291],"type":"Point"}
}