{
  "type": "Feature",
  "properties": {
    "iso:country": "GB",
    "wof:name": "WD23 1HQ",
    "wof:placetype": "postalcode"
  },
  "geometry": {"coordinates":[-0.347115,51.633582],"type":"Point"}
}
