{
  "type": "Feature",
  "properties": {
    "date:inception_lower": "1991-03-01",
    "date:inception_upper": "1991-03-01",
    "iso:country": "GB",
    "wof:name": "KY8 5BP",
    "wof:placetype": "postalcode"
  },
  "geometry": {"coordinates":[-3.050699,56.189862],"type":"Point"}
}
