{
  "type": "Feature",
  "properties": {
    "iso:country":"GB",
    "wof:name":"NE68 7YJ",
    "wof:placetype":"postalcode"
},
  "geometry": {"coordinates":[-1.65537571484733,55.57977342367418],"type":"Point"}
}