{
  "type": "Feature",
  "properties": {
    "iso:country":"GB",
    "wof:name":"DA4 9JQ",
    "wof:placetype":"postalcode"
},
  "geometry": {"coordinates":[0.24467411298394,51.38592940699346],"type":"Point"}
}