{
  "type": "Feature",
  "properties": {
    "iso:country":"GB",
    "wof:name":"PE11 3JW",
    "wof:placetype":"postalcode"
},
  "geometry": {"coordinates":[-0.28488315376143,52.75106664564633],"type":"Point"}
}