{
  "type": "Feature",
  "properties": {
    "date:inception_lower": "1980-01-01",
    "date:inception_upper": "1980-01-01",
    "iso:country": "GB",
    "wof:name": "PE11 3JW",
    "wof:placetype": "postalcode"
  },
  "geometry": {"coordinates":[-0.284842,52.751078],"type":"Point"}
}
