{
  "type": "Feature",
  "properties": {
    "iso:country": "GB",
    "wof:name": "PE11 3JW",
    "wof:placetype": "postalcode"
  },
  "geometry": {"coordinates":[-0.284842,52.751078],"type":"Point"}
}
