{
  "type": "Feature",
  "properties": {
    "date:inception_lower": "1999-06-01",
    "date:inception_upper": "1999-06-01",
    "iso:country": "GB",
    "wof:name": "CH60 7RY",
    "wof:placetype": "postalcode"
  },
  "geometry": {"coordinates":[-3.09898,53.335211],"type":"Point"}
}
