{
  "type": "Feature",
  "properties": {
    "date:inception_lower": "2004-03-01",
    "date:inception_upper": "2004-03-01",
    "iso:country": "GB",
    "wof:name": "DN4 9BB",
    "wof:placetype": "postalcode"
  },
  "geometry": {"coordinates":[-1.163925,53.490501],"type":"Point"}
}
