{
  "type": "Feature",
  "properties": {
    "date:inception_lower":"2004-03-01",
    "date:inception_upper":"2004-03-31",
    "iso:country":"GB",
    "wof:name":"DN4 9BB",
    "wof:placetype":"postalcode"
},
  "geometry": {"coordinates":[-1.165128,53.490653],"type":"Point"}
}