{
  "type": "Feature",
  "properties": {
    "iso:country":"GB",
    "wof:name":"DN4 9BB",
    "wof:placetype":"postalcode"
},
  "geometry": {"coordinates":[-1.1651260448999,53.49063296544618],"type":"Point"}
}