{
  "type": "Feature",
  "properties": {
    "iso:country": "GB",
    "wof:name": "GU6 7EJ",
    "wof:placetype": "postalcode"
  },
  "geometry": {"coordinates":[-0.4738,51.144846],"type":"Point"}
}
