{
  "type": "Feature",
  "properties": {
    "iso:country":"GB",
    "wof:name":"SW18 1NJ",
    "wof:placetype":"postalcode"
},
  "geometry": {"coordinates":[-0.20028038897334,51.46054988444548],"type":"Point"}
}