{
  "type": "Feature",
  "properties": {
    "iso:country":"GB",
    "wof:name":"BN6 9HS",
    "wof:placetype":"postalcode"
},
  "geometry": {"coordinates":[-0.19479012775099,50.95505713883286],"type":"Point"}
}