{
  "type": "Feature",
  "properties": {
    "iso:country": "GB",
    "wof:name": "BN6 9HS",
    "wof:placetype": "postalcode"
  },
  "geometry": {"coordinates":[-0.19479,50.955057],"type":"Point"}
}
