{
  "type": "Feature",
  "properties": {
    "date:inception_lower": "2000-06-01",
    "date:inception_upper": "2000-06-01",
    "iso:country": "GB",
    "wof:name": "BN6 9HS",
    "wof:placetype": "postalcode"
  },
  "geometry": {"coordinates":[-0.19479,50.955057],"type":"Point"}
}
