{
  "type": "Feature",
  "properties": {
    "date:inception_lower": "1980-01-01",
    "date:inception_upper": "1980-01-01",
    "iso:country": "GB",
    "wof:name": "BL1 3NL",
    "wof:placetype": "postalcode"
  },
  "geometry": {"coordinates":[-2.434904,53.590648],"type":"Point"}
}
