{
  "type": "Feature",
  "properties": {
    "iso:country":"GB",
    "wof:name":"NG31 9UN",
    "wof:placetype":"postalcode"
},
  "geometry": {"coordinates":[-0.61005367405614,52.91517606998938],"type":"Point"}
}