{
  "type": "Feature",
  "properties": {
    "date:inception_lower": "1983-07-01",
    "date:inception_upper": "1983-07-01",
    "iso:country": "GB",
    "wof:name": "NG31 9UN",
    "wof:placetype": "postalcode"
  },
  "geometry": {"coordinates":[-0.610049,52.91518],"type":"Point"}
}
