{
  "type": "Feature",
  "properties": {
    "iso:country":"GB",
    "wof:name":"WA11 0AB",
    "wof:placetype":"postalcode"
},
  "geometry": {"coordinates":[-2.7021004997403,53.46413084021873],"type":"Point"}
}