{
  "type": "Feature",
  "properties": {
    "iso:country": "GB",
    "wof:name": "PA23 8RX",
    "wof:placetype": "postalcode"
  },
  "geometry": {"coordinates":[-4.913067,55.986835],"type":"Point"}
}
