{
  "type": "Feature",
  "properties": {
    "iso:country":"GB",
    "wof:name":"PA23 8RX",
    "wof:placetype":"postalcode"
},
  "geometry": {"coordinates":[-4.91306663605223,55.98683512003776],"type":"Point"}
}