{
  "type": "Feature",
  "properties": {
    "iso:country":"GB",
    "wof:name":"E6 3SD",
    "wof:placetype":"postalcode"
},
  "geometry": {"coordinates":[0.05064683584495,51.52118610785671],"type":"Point"}
}