{
  "type": "Feature",
  "properties": {
    "iso:country": "GB",
    "wof:name": "SO40 3JW",
    "wof:placetype": "postalcode"
  },
  "geometry": {"coordinates":[-1.495874,50.920618],"type":"Point"}
}
