{
  "type": "Feature",
  "properties": {
    "iso:country":"GB",
    "wof:name":"BN20 7NJ",
    "wof:placetype":"postalcode"
},
  "geometry": {"coordinates":[0.27213122818769,50.75599129927102],"type":"Point"}
}