{
  "type": "Feature",
  "properties": {
    "iso:country":"GB",
    "wof:name":"FY8 2RR",
    "wof:placetype":"postalcode"
},
  "geometry": {"coordinates":[-3.02622589312633,53.7633195701989],"type":"Point"}
}