{
  "type": "Feature",
  "properties": {
    "iso:country":"GB",
    "wof:name":"CR8 2JB",
    "wof:placetype":"postalcode"
},
  "geometry": {"coordinates":[-0.12297979519573,51.34179441714578],"type":"Point"}
}