{
  "type": "Feature",
  "properties": {
    "date:inception_lower": "1990-07-01",
    "date:inception_upper": "1990-07-01",
    "iso:country": "GB",
    "wof:name": "CR8 2JB",
    "wof:placetype": "postalcode"
  },
  "geometry": {"coordinates":[-0.12319,51.342004],"type":"Point"}
}
