{
  "type": "Feature",
  "properties": {
    "iso:country":"GB",
    "wof:name":"NG19 6SY",
    "wof:placetype":"postalcode"
},
  "geometry": {"coordinates":[-1.21777235299918,53.14824155808532],"type":"Point"}
}