{
  "type": "Feature",
  "properties": {
    "iso:country": "GB",
    "wof:name": "NN29 7EQ",
    "wof:placetype": "postalcode"
  },
  "geometry": {"coordinates":[-0.64123,52.279859],"type":"Point"}
}
