{
  "type": "Feature",
  "properties": {
    "date:inception_lower": "1982-03-01",
    "date:inception_upper": "1982-03-01",
    "iso:country": "GB",
    "wof:name": "MK4 1BJ",
    "wof:placetype": "postalcode"
  },
  "geometry": {"coordinates":[-0.759076,52.009925],"type":"Point"}
}
