{
  "type": "Feature",
  "properties": {
    "iso:country":"GB",
    "wof:name":"MK4 1BJ",
    "wof:placetype":"postalcode"
},
  "geometry": {"coordinates":[-0.75907607305614,52.00992464011381],"type":"Point"}
}