{
  "type": "Feature",
  "properties": {
    "iso:country": "GB",
    "wof:name": "CO16 9NT",
    "wof:placetype": "postalcode"
  },
  "geometry": {"coordinates":[1.128418,51.818288],"type":"Point"}
}
