{
  "type": "Feature",
  "properties": {
    "iso:country":"GB",
    "wof:name":"LL29 8AF",
    "wof:placetype":"postalcode"
},
  "geometry": {"coordinates":[-3.71190251206607,53.28712166113782],"type":"Point"}
}