{
  "type": "Feature",
  "properties": {
    "iso:country":"GB",
    "wof:name":"SW3 2TR",
    "wof:placetype":"postalcode"
},
  "geometry": {"coordinates":[-0.16174298088832,51.4913808810407],"type":"Point"}
}