{
  "type": "Feature",
  "properties": {
    "iso:country": "GB",
    "wof:name": "SW3 2TR",
    "wof:placetype": "postalcode"
  },
  "geometry": {"coordinates":[-0.161743,51.491381],"type":"Point"}
}
