{
  "type": "Feature",
  "properties": {
    "iso:country":"GB",
    "wof:name":"DD5 3WH",
    "wof:placetype":"postalcode"
},
  "geometry": {"coordinates":[-2.87383369907147,56.48268802921361],"type":"Point"}
}