{
  "type": "Feature",
  "properties": {
    "iso:country":"GB",
    "wof:name":"LE2 1BT",
    "wof:placetype":"postalcode"
},
  "geometry": {"coordinates":[-1.11087694024119,52.62887107585975],"type":"Point"}
}