{
  "type": "Feature",
  "properties": {
    "iso:country":"GB",
    "wof:name":"TW2 6HD",
    "wof:placetype":"postalcode"
},
  "geometry": {"coordinates":[-0.36493044813409,51.45012955413677],"type":"Point"}
}