{
  "type": "Feature",
  "properties": {
    "iso:country":"GB",
    "wof:name":"TW16 5EQ",
    "wof:placetype":"postalcode"
},
  "geometry": {"coordinates":[-0.41025923841907,51.41380344875142],"type":"Point"}
}