{
  "type": "Feature",
  "properties": {
    "iso:country":"GB",
    "wof:name":"LE14 2SB",
    "wof:placetype":"postalcode"
},
  "geometry": {"coordinates":[-0.79762789765758,52.76609232475614],"type":"Point"}
}