{
  "type": "Feature",
  "properties": {
    "iso:country":"GB",
    "wof:name":"BH4 8AU",
    "wof:placetype":"postalcode"
},
  "geometry": {"coordinates":[-1.90422636056534,50.72194227960063],"type":"Point"}
}