{
  "type": "Feature",
  "properties": {
    "iso:country":"GB",
    "wof:name":"OX12 0PY",
    "wof:placetype":"postalcode"
},
  "geometry": {"coordinates":[-1.43127135019293,51.6072145123725],"type":"Point"}
}