{
  "type": "Feature",
  "properties": {
    "iso:country": "GB",
    "wof:name": "OX12 0PY",
    "wof:placetype": "postalcode"
  },
  "geometry": {"coordinates":[-1.431271,51.607215],"type":"Point"}
}
