{
  "type": "Feature",
  "properties": {
    "iso:country":"GB",
    "wof:name":"DG11 1QD",
    "wof:placetype":"postalcode"
},
  "geometry": {"coordinates":[-3.44214717377176,55.13425706024205],"type":"Point"}
}