{
  "type": "Feature",
  "properties": {
    "iso:country":"GB",
    "wof:name":"OX16 9ER",
    "wof:placetype":"postalcode"
},
  "geometry": {"coordinates":[-1.33905681796761,52.04454452231435],"type":"Point"}
}