{
  "type": "Feature",
  "properties": {
    "iso:country": "GB",
    "wof:name": "OX16 9ER",
    "wof:placetype": "postalcode"
  },
  "geometry": {"coordinates":[-1.339057,52.044545],"type":"Point"}
}
