{
  "type": "Feature",
  "properties": {
    "iso:country":"GB",
    "wof:name":"CF45 3NZ",
    "wof:placetype":"postalcode"
},
  "geometry": {"coordinates":[-3.36105067950539,51.66488127364096],"type":"Point"}
}