{
  "type": "Feature",
  "properties": {
    "iso:country": "GB",
    "wof:name": "CF45 3NZ",
    "wof:placetype": "postalcode"
  },
  "geometry": {"coordinates":[-3.361051,51.664881],"type":"Point"}
}
