{
  "type": "Feature",
  "properties": {
    "date:inception_lower":"2014-11-01",
    "date:inception_upper":"2014-11-30",
    "iso:country":"GB",
    "wof:name":"CF45 3NZ",
    "wof:placetype":"postalcode"
},
  "geometry": {"coordinates":[-3.361051,51.664881],"type":"Point"}
}