{
  "type": "Feature",
  "properties": {
    "iso:country": "GB",
    "wof:name": "CT5 4FG",
    "wof:placetype": "postalcode"
  },
  "geometry": {"coordinates":[1.023634,51.351135],"type":"Point"}
}
