{
  "type": "Feature",
  "properties": {
    "iso:country":"GB",
    "wof:name":"CT5 4FG",
    "wof:placetype":"postalcode"
},
  "geometry": {"coordinates":[1.02358883648113,51.35112228094376],"type":"Point"}
}