{
  "type": "Feature",
  "properties": {
    "iso:country":"GB",
    "wof:name":"SM6 8SL",
    "wof:placetype":"postalcode"
},
  "geometry": {"coordinates":[-0.14656003750274,51.3616211918854],"type":"Point"}
}