{
  "type": "Feature",
  "properties": {
    "date:inception_lower":"2013-04-01",
    "date:inception_upper":"2013-04-30",
    "iso:country":"GB",
    "wof:name":"PR4 9BE",
    "wof:placetype":"postalcode"
},
  "geometry": {"coordinates":[-2.872576,53.777507],"type":"Point"}
}