{
  "type": "Feature",
  "properties": {
    "iso:country":"GB",
    "wof:name":"PA2 6AR",
    "wof:placetype":"postalcode"
},
  "geometry": {"coordinates":[-4.43790831967635,55.83966811779274],"type":"Point"}
}