{
  "type": "Feature",
  "properties": {
    "iso:country":"GB",
    "wof:name":"EH14 5BL",
    "wof:placetype":"postalcode"
},
  "geometry": {"coordinates":[-3.2781582505841,55.90638341738249],"type":"Point"}
}