{
  "type": "Feature",
  "properties": {
    "iso:country": "GB",
    "wof:name": "HR4 0NU",
    "wof:placetype": "postalcode"
  },
  "geometry": {"coordinates":[-2.741653,52.067023],"type":"Point"}
}
