{
  "type": "Feature",
  "properties": {
    "iso:country": "GB",
    "wof:name": "BH14 8LY",
    "wof:placetype": "postalcode"
  },
  "geometry": {"coordinates":[-1.939645,50.702531],"type":"Point"}
}
