{
  "type": "Feature",
  "properties": {
    "iso:country":"GB",
    "wof:name":"YO26 5HB",
    "wof:placetype":"postalcode"
},
  "geometry": {"coordinates":[-1.13196159873104,53.96345473162979],"type":"Point"}
}