{
  "type": "Feature",
  "properties": {
    "iso:country": "GB",
    "wof:name": "ME6 9JG",
    "wof:placetype": "postalcode"
  },
  "geometry": {"coordinates":[0.446671,51.326341],"type":"Point"}
}
