{
  "type": "Feature",
  "properties": {
    "iso:country":"GB",
    "wof:name":"NR4 7RY",
    "wof:placetype":"postalcode"
},
  "geometry": {"coordinates":[1.23740524250238,52.60941995029031],"type":"Point"}
}