{
  "type": "Feature",
  "properties": {
    "iso:country":"GB",
    "wof:name":"M25 1JH",
    "wof:placetype":"postalcode"
},
  "geometry": {"coordinates":[-2.26679275759362,53.52661350360454],"type":"Point"}
}