{
  "type": "Feature",
  "properties": {
    "iso:country":"GB",
    "wof:name":"RM7 9EL",
    "wof:placetype":"postalcode"
},
  "geometry": {"coordinates":[0.16618448596907,51.57464883336708],"type":"Point"}
}