{
  "type": "Feature",
  "properties": {
    "iso:country":"GB",
    "wof:name":"NE4 6JU",
    "wof:placetype":"postalcode"
},
  "geometry": {"coordinates":[-1.63391271430555,54.97039244582422],"type":"Point"}
}