{
  "type": "Feature",
  "properties": {
    "iso:country": "GB",
    "wof:name": "TN28 8AF",
    "wof:placetype": "postalcode"
  },
  "geometry": {"coordinates":[0.945473,50.982738],"type":"Point"}
}
