{
  "type": "Feature",
  "properties": {
    "iso:country": "GB",
    "wof:name": "SG5 2HH",
    "wof:placetype": "postalcode"
  },
  "geometry": {"coordinates":[-0.287718,51.94788],"type":"Point"}
}
