{
  "type": "Feature",
  "properties": {
    "iso:country":"GB",
    "wof:name":"CV6 7HN",
    "wof:placetype":"postalcode"
},
  "geometry": {"coordinates":[-1.47295948101987,52.43352444316425],"type":"Point"}
}