{
  "type": "Feature",
  "properties": {
    "date:inception_lower": "1980-01-01",
    "date:inception_upper": "1980-01-01",
    "iso:country": "GB",
    "wof:name": "SY24 5LN",
    "wof:placetype": "postalcode"
  },
  "geometry": {"coordinates":[-4.051769,52.479363],"type":"Point"}
}
