{
  "type": "Feature",
  "properties": {
    "iso:country":"GB",
    "wof:name":"SY24 5LN",
    "wof:placetype":"postalcode"
},
  "geometry": {"coordinates":[-4.05176900542498,52.47936280178457],"type":"Point"}
}