{
  "type": "Feature",
  "properties": {
    "iso:country":"GB",
    "wof:name":"KW15 1SQ",
    "wof:placetype":"postalcode"
},
  "geometry": {"coordinates":[-2.96987936256314,58.97676716063904],"type":"Point"}
}