{
  "type": "Feature",
  "properties": {
    "iso:country":"GB",
    "wof:name":"LE67 4TN",
    "wof:placetype":"postalcode"
},
  "geometry": {"coordinates":[-1.32781356689547,52.7240098720124],"type":"Point"}
}