{
  "type": "Feature",
  "properties": {
    "iso:country": "GB",
    "wof:name": "LE67 4TN",
    "wof:placetype": "postalcode"
  },
  "geometry": {"coordinates":[-1.327814,52.72401],"type":"Point"}
}
