{
  "type": "Feature",
  "properties": {
    "date:inception_lower": "1980-01-01",
    "date:inception_upper": "1980-01-01",
    "iso:country": "GB",
    "wof:name": "FK7 8ED",
    "wof:placetype": "postalcode"
  },
  "geometry": {"coordinates":[-3.869342,56.062749],"type":"Point"}
}
