{
  "type": "Feature",
  "properties": {
    "iso:country":"GB",
    "wof:name":"HA9 7LU",
    "wof:placetype":"postalcode"
},
  "geometry": {"coordinates":[-0.30519752240239,51.56371773221618],"type":"Point"}
}