{
  "type": "Feature",
  "properties": {
    "iso:country":"GB",
    "wof:name":"KT10 0BZ",
    "wof:placetype":"postalcode"
},
  "geometry": {"coordinates":[-0.33629355218232,51.37359669374355],"type":"Point"}
}