{
  "type": "Feature",
  "properties": {
    "iso:country": "GB",
    "wof:name": "BS40 6HD",
    "wof:placetype": "postalcode"
  },
  "geometry": {"coordinates":[-2.629182,51.308934],"type":"Point"}
}
