{
  "type": "Feature",
  "properties": {
    "iso:country":"GB",
    "wof:name":"NN14 1HN",
    "wof:placetype":"postalcode"
},
  "geometry": {"coordinates":[-0.69770137906217,52.35761795982982],"type":"Point"}
}