{
  "type": "Feature",
  "properties": {
    "date:inception_lower": "2014-06-01",
    "date:inception_upper": "2014-06-01",
    "iso:country": "GB",
    "wof:name": "GL52 7SD",
    "wof:placetype": "postalcode"
  },
  "geometry": {"coordinates":[-2.119573,51.954199],"type":"Point"}
}
