{
  "type": "Feature",
  "properties": {
    "iso:country":"GB",
    "wof:name":"GL52 7SD",
    "wof:placetype":"postalcode"
},
  "geometry": {"coordinates":[-2.11988480409094,51.95409970573302],"type":"Point"}
}