{
  "type": "Feature",
  "properties": {
    "iso:country":"GB",
    "wof:name":"OX12 9AQ",
    "wof:placetype":"postalcode"
},
  "geometry": {"coordinates":[-1.42759488392235,51.58951953331108],"type":"Point"}
}