{
  "type": "Feature",
  "properties": {
    "iso:country":"GB",
    "wof:name":"RH2 8AR",
    "wof:placetype":"postalcode"
},
  "geometry": {"coordinates":[-0.19994614168151,51.22461287029346],"type":"Point"}
}