{
  "type": "Feature",
  "properties": {
    "iso:country":"GB",
    "wof:name":"AB22 8GF",
    "wof:placetype":"postalcode"
},
  "geometry": {"coordinates":[-2.13006295927524,57.19464343102862],"type":"Point"}
}