{
  "type": "Feature",
  "properties": {
    "date:inception_lower":"1990-08-01",
    "date:inception_upper":"1990-08-31",
    "iso:country":"GB",
    "wof:name":"AB22 8GF",
    "wof:placetype":"postalcode"
},
  "geometry": {"coordinates":[-2.130063,57.194643],"type":"Point"}
}