{
  "type": "Feature",
  "properties": {
    "iso:country": "GB",
    "wof:name": "AB22 8GF",
    "wof:placetype": "postalcode"
  },
  "geometry": {"coordinates":[-2.130063,57.194643],"type":"Point"}
}
