{
  "type": "Feature",
  "properties": {
    "date:inception_lower": "2018-09-01",
    "date:inception_upper": "2018-09-01",
    "iso:country": "GB",
    "wof:name": "DN8 5BB",
    "wof:placetype": "postalcode"
  },
  "geometry": {"coordinates":[-0.960346,53.611852],"type":"Point"}
}
