{
  "type": "Feature",
  "properties": {
    "date:inception_lower": "1987-10-01",
    "date:inception_upper": "1987-10-01",
    "iso:country": "GB",
    "wof:name": "BA2 1BN",
    "wof:placetype": "postalcode"
  },
  "geometry": {"coordinates":[-2.386759,51.3759],"type":"Point"}
}
