{
  "type": "Feature",
  "properties": {
    "iso:country": "GB",
    "wof:name": "LA22 0AD",
    "wof:placetype": "postalcode"
  },
  "geometry": {"coordinates":[-2.962397,54.430426],"type":"Point"}
}
