{
  "type": "Feature",
  "properties": {
    "iso:country":"GB",
    "wof:name":"LA22 0AD",
    "wof:placetype":"postalcode"
},
  "geometry": {"coordinates":[-2.96214486318629,54.43032190702387],"type":"Point"}
}