{
  "type": "Feature",
  "properties": {
    "iso:country": "GB",
    "wof:name": "PO20 7EG",
    "wof:placetype": "postalcode"
  },
  "geometry": {"coordinates":[-0.805544,50.821461],"type":"Point"}
}
