{
  "type": "Feature",
  "properties": {
    "iso:country":"GB",
    "wof:name":"B12 8RL",
    "wof:placetype":"postalcode"
},
  "geometry": {"coordinates":[-1.88255221023917,52.45557733005735],"type":"Point"}
}