{
  "type": "Feature",
  "properties": {
    "iso:country":"GB",
    "wof:name":"NW1 9NL",
    "wof:placetype":"postalcode"
},
  "geometry": {"coordinates":[-0.1389343921967,51.54278197123429],"type":"Point"}
}