{
  "type": "Feature",
  "properties": {
    "iso:country":"GB",
    "wof:name":"EX13 5UG",
    "wof:placetype":"postalcode"
},
  "geometry": {"coordinates":[-2.94181462834589,50.77914706635568],"type":"Point"}
}