{
  "type": "Feature",
  "properties": {
    "date:inception_lower":"1980-01-01",
    "date:inception_upper":"1980-01-31",
    "iso:country":"GB",
    "wof:name":"EX13 5UG",
    "wof:placetype":"postalcode"
},
  "geometry": {"coordinates":[-2.941815,50.779147],"type":"Point"}
}