{
  "type": "Feature",
  "properties": {
    "iso:country": "GB",
    "wof:name": "LL29 8RB",
    "wof:placetype": "postalcode"
  },
  "geometry": {"coordinates":[-3.717188,53.285751],"type":"Point"}
}
