{
  "type": "Feature",
  "properties": {
    "iso:country":"GB",
    "wof:name":"CW1 4SW",
    "wof:placetype":"postalcode"
},
  "geometry": {"coordinates":[-2.44413172026573,53.11079633607481],"type":"Point"}
}