{
  "type": "Feature",
  "properties": {
    "iso:country": "GB",
    "wof:name": "CW1 4SW",
    "wof:placetype": "postalcode"
  },
  "geometry": {"coordinates":[-2.444132,53.110796],"type":"Point"}
}
