{
  "type": "Feature",
  "properties": {
    "iso:country":"GB",
    "wof:name":"DN10 4FD",
    "wof:placetype":"postalcode"
},
  "geometry": {"coordinates":[-0.83268481285656,53.40339718377209],"type":"Point"}
}