{
  "type": "Feature",
  "properties": {
    "date:inception_lower": "2000-06-01",
    "date:inception_upper": "2000-06-01",
    "iso:country": "GB",
    "wof:name": "DN10 4FD",
    "wof:placetype": "postalcode"
  },
  "geometry": {"coordinates":[-0.832685,53.403397],"type":"Point"}
}
