{
  "type": "Feature",
  "properties": {
    "iso:country": "GB",
    "wof:name": "DN10 4FD",
    "wof:placetype": "postalcode"
  },
  "geometry": {"coordinates":[-0.832685,53.403397],"type":"Point"}
}
