{
  "type": "Feature",
  "properties": {
    "iso:country":"GB",
    "wof:name":"S11 7GN",
    "wof:placetype":"postalcode"
},
  "geometry": {"coordinates":[-1.51058866898934,53.36126731170704],"type":"Point"}
}