{
  "type": "Feature",
  "properties": {
    "iso:country": "GB",
    "wof:name": "S11 7GN",
    "wof:placetype": "postalcode"
  },
  "geometry": {"coordinates":[-1.510589,53.361267],"type":"Point"}
}
