{
  "type": "Feature",
  "properties": {
    "iso:country":"GB",
    "wof:name":"LL15 1EU",
    "wof:placetype":"postalcode"
},
  "geometry": {"coordinates":[-3.30582866971302,53.11441217344301],"type":"Point"}
}