{
  "type": "Feature",
  "properties": {
    "iso:country": "GB",
    "wof:name": "PL30 4AB",
    "wof:placetype": "postalcode"
  },
  "geometry": {"coordinates":[-4.693961,50.45011],"type":"Point"}
}
