{
  "type": "Feature",
  "properties": {
    "iso:country":"GB",
    "wof:name":"PL30 4AB",
    "wof:placetype":"postalcode"
},
  "geometry": {"coordinates":[-4.69392134029464,50.45012132230571],"type":"Point"}
}