{
  "type": "Feature",
  "properties": {
    "date:inception_lower":"1995-07-01",
    "date:inception_upper":"1995-07-31",
    "iso:country":"GB",
    "wof:name":"PL30 4AB",
    "wof:placetype":"postalcode"
},
  "geometry": {"coordinates":[-4.693961,50.45011],"type":"Point"}
}