{
  "type": "Feature",
  "properties": {
    "date:inception_lower": "1995-07-01",
    "date:inception_upper": "1995-07-01",
    "iso:country": "GB",
    "wof:name": "PL30 4AB",
    "wof:placetype": "postalcode"
  },
  "geometry": {"coordinates":[-4.694107,50.450206],"type":"Point"}
}
