{
  "type": "Feature",
  "properties": {
    "iso:country":"GB",
    "wof:name":"NW1 8SS",
    "wof:placetype":"postalcode"
},
  "geometry": {"coordinates":[-0.14632221093761,51.54587543889969],"type":"Point"}
}