{
  "type": "Feature",
  "properties": {
    "date:inception_lower": "2018-07-01",
    "date:inception_upper": "2018-07-01",
    "iso:country": "GB",
    "wof:name": "CR5 3GQ",
    "wof:placetype": "postalcode"
  },
  "geometry": {"coordinates":[-0.140612,51.316661],"type":"Point"}
}
