{
  "type": "Feature",
  "properties": {
    "iso:country":"GB",
    "wof:name":"S6 1AX",
    "wof:placetype":"postalcode"
},
  "geometry": {"coordinates":[-1.49538399579382,53.43106392330598],"type":"Point"}
}