{
  "type": "Feature",
  "properties": {
    "iso:country": "GB",
    "wof:name": "CH60 0DB",
    "wof:placetype": "postalcode"
  },
  "geometry": {"coordinates":[-3.096093,53.328047],"type":"Point"}
}
