{
  "type": "Feature",
  "properties": {
    "iso:country":"GB",
    "wof:name":"CH60 0DB",
    "wof:placetype":"postalcode"
},
  "geometry": {"coordinates":[-3.0960934985767,53.32804657464555],"type":"Point"}
}