{
  "type": "Feature",
  "properties": {
    "iso:country":"GB",
    "wof:name":"AL9 5AN",
    "wof:placetype":"postalcode"
},
  "geometry": {"coordinates":[-0.21299365509498,51.76206694324529],"type":"Point"}
}