{
  "type": "Feature",
  "properties": {
    "date:inception_lower": "1980-01-01",
    "date:inception_upper": "1980-01-01",
    "iso:country": "GB",
    "wof:name": "AL9 5AN",
    "wof:placetype": "postalcode"
  },
  "geometry": {"coordinates":[-0.212969,51.762082],"type":"Point"}
}
