{
  "type": "Feature",
  "properties": {
    "iso:country":"GB",
    "wof:name":"SP5 1LG",
    "wof:placetype":"postalcode"
},
  "geometry": {"coordinates":[-1.58196000553545,51.06016758327404],"type":"Point"}
}