{
  "type": "Feature",
  "properties": {
    "iso:country": "GB",
    "wof:name": "M18 8FJ",
    "wof:placetype": "postalcode"
  },
  "geometry": {"coordinates":[-2.17395,53.464828],"type":"Point"}
}
