{
  "type": "Feature",
  "properties": {
    "iso:country":"GB",
    "wof:name":"M18 8FJ",
    "wof:placetype":"postalcode"
},
  "geometry": {"coordinates":[-2.17395006356773,53.46482760454894],"type":"Point"}
}