{
  "type": "Feature",
  "properties": {
    "iso:country": "GB",
    "wof:name": "DN33 3BB",
    "wof:placetype": "postalcode"
  },
  "geometry": {"coordinates":[-0.104056,53.535324],"type":"Point"}
}
