{
  "type": "Feature",
  "properties": {
    "date:inception_lower": "2017-10-01",
    "date:inception_upper": "2017-10-01",
    "iso:country": "GB",
    "wof:name": "DN33 3BB",
    "wof:placetype": "postalcode"
  },
  "geometry": {"coordinates":[-0.104088,53.53528],"type":"Point"}
}
