{
  "type": "Feature",
  "properties": {
    "iso:country":"GB",
    "wof:name":"LL65 4NG",
    "wof:placetype":"postalcode"
},
  "geometry": {"coordinates":[-4.5162042459649,53.32725283428729],"type":"Point"}
}