{
  "type": "Feature",
  "properties": {
    "iso:country": "GB",
    "wof:name": "LL65 4NG",
    "wof:placetype": "postalcode"
  },
  "geometry": {"coordinates":[-4.516204,53.327253],"type":"Point"}
}
