{
  "type": "Feature",
  "properties": {
    "iso:country":"GB",
    "wof:name":"SE14 6RN",
    "wof:placetype":"postalcode"
},
  "geometry": {"coordinates":[-0.03610741039764,51.46708721504012],"type":"Point"}
}