{
  "type": "Feature",
  "properties": {
    "date:inception_lower": "1980-01-01",
    "date:inception_upper": "1980-01-01",
    "iso:country": "GB",
    "wof:name": "S44 6HL",
    "wof:placetype": "postalcode"
  },
  "geometry": {"coordinates":[-1.284594,53.225456],"type":"Point"}
}
