{
  "type": "Feature",
  "properties": {
    "date:inception_lower": "2020-02-01",
    "date:inception_upper": "2020-02-01",
    "iso:country": "GB",
    "wof:name": "PA3 2DX",
    "wof:placetype": "postalcode"
  },
  "geometry": {"coordinates":[-4.422755,55.847935],"type":"Point"}
}
