{
  "type": "Feature",
  "properties": {
    "iso:country": "GB",
    "wof:name": "WF10 1WY",
    "wof:placetype": "postalcode"
  },
  "geometry": {"coordinates":[-1.390333,53.716434],"type":"Point"}
}
