{
  "type": "Feature",
  "properties": {
    "iso:country":"GB",
    "wof:name":"NG2 4NN",
    "wof:placetype":"postalcode"
},
  "geometry": {"coordinates":[-1.11954314472185,52.95099422656862],"type":"Point"}
}