{
  "type": "Feature",
  "properties": {
    "date:inception_lower": "1980-01-01",
    "date:inception_upper": "1980-01-01",
    "iso:country": "GB",
    "wof:name": "CH4 8BQ",
    "wof:placetype": "postalcode"
  },
  "geometry": {"coordinates":[-2.911314,53.180535],"type":"Point"}
}
