{
  "type": "Feature",
  "properties": {
    "iso:country":"GB",
    "wof:name":"MK6 2TT",
    "wof:placetype":"postalcode"
},
  "geometry": {"coordinates":[-0.75565376498384,52.02824852689312],"type":"Point"}
}