{
  "type": "Feature",
  "properties": {
    "iso:country":"GB",
    "wof:name":"SR4 7AR",
    "wof:placetype":"postalcode"
},
  "geometry": {"coordinates":[-1.39738835452457,54.90514425694352],"type":"Point"}
}