{
  "type": "Feature",
  "properties": {
    "date:inception_lower": "2018-08-01",
    "date:inception_upper": "2018-08-01",
    "iso:country": "GB",
    "wof:name": "B91 2PW",
    "wof:placetype": "postalcode"
  },
  "geometry": {"coordinates":[-1.765279,52.4157],"type":"Point"}
}
