{
  "type": "Feature",
  "properties": {
    "iso:country": "GB",
    "wof:name": "NE3 3AW",
    "wof:placetype": "postalcode"
  },
  "geometry": {"coordinates":[-1.64848,55.010521],"type":"Point"}
}
