{
  "type": "Feature",
  "properties": {
    "iso:country":"GB",
    "wof:name":"SS8 9EE",
    "wof:placetype":"postalcode"
},
  "geometry": {"coordinates":[0.58299649578599,51.52296241988402],"type":"Point"}
}