{
  "type": "Feature",
  "properties": {
    "date:inception_lower": "1995-07-01",
    "date:inception_upper": "1995-07-01",
    "iso:country": "GB",
    "wof:name": "N11 2JN",
    "wof:placetype": "postalcode"
  },
  "geometry": {"coordinates":[-0.126677,51.603226],"type":"Point"}
}
