{
  "type": "Feature",
  "properties": {
    "iso:country":"GB",
    "wof:name":"N11 2JN",
    "wof:placetype":"postalcode"
},
  "geometry": {"coordinates":[-0.12591781685173,51.60263527554608],"type":"Point"}
}