{
  "type": "Feature",
  "properties": {
    "iso:country": "GB",
    "wof:name": "OL14 6QX",
    "wof:placetype": "postalcode"
  },
  "geometry": {"coordinates":[-2.096385,53.69356],"type":"Point"}
}
