{
  "type": "Feature",
  "properties": {
    "iso:country": "GB",
    "wof:name": "DL14 6TT",
    "wof:placetype": "postalcode"
  },
  "geometry": {"coordinates":[-1.685065,54.656782],"type":"Point"}
}
