{
  "type": "Feature",
  "properties": {
    "date:inception_lower":"1980-01-01",
    "date:inception_upper":"1980-01-31",
    "iso:country":"GB",
    "wof:name":"DL14 6TT",
    "wof:placetype":"postalcode"
},
  "geometry": {"coordinates":[-1.685065,54.656782],"type":"Point"}
}