{
  "type": "Feature",
  "properties": {
    "iso:country":"GB",
    "wof:name":"OL3 6JJ",
    "wof:placetype":"postalcode"
},
  "geometry": {"coordinates":[-2.00192351619514,53.54465470163547],"type":"Point"}
}