{
  "type": "Feature",
  "properties": {
    "date:inception_lower":"1980-01-01",
    "date:inception_upper":"1980-01-31",
    "iso:country":"GB",
    "wof:name":"OL3 6JJ",
    "wof:placetype":"postalcode"
},
  "geometry": {"coordinates":[-2.001923,53.544655],"type":"Point"}
}