{
  "type": "Feature",
  "properties": {
    "iso:country":"GB",
    "wof:name":"OX12 7EY",
    "wof:placetype":"postalcode"
},
  "geometry": {"coordinates":[-1.419027894241,51.61159634148108],"type":"Point"}
}