{
  "type": "Feature",
  "properties": {
    "iso:country": "GB",
    "wof:name": "OX12 7EY",
    "wof:placetype": "postalcode"
  },
  "geometry": {"coordinates":[-1.419028,51.611596],"type":"Point"}
}
