{
  "type": "Feature",
  "properties": {
    "iso:country": "GB",
    "wof:name": "DY1 2DZ",
    "wof:placetype": "postalcode"
  },
  "geometry": {"coordinates":[-2.097098,52.505693],"type":"Point"}
}
