{
  "type": "Feature",
  "properties": {
    "iso:country": "GB",
    "wof:name": "LL32 8UL",
    "wof:placetype": "postalcode"
  },
  "geometry": {"coordinates":[-3.851661,53.217246],"type":"Point"}
}
