{
  "type": "Feature",
  "properties": {
    "date:inception_lower":"1980-01-01",
    "date:inception_upper":"1980-01-31",
    "iso:country":"GB",
    "wof:name":"LL32 8UL",
    "wof:placetype":"postalcode"
},
  "geometry": {"coordinates":[-3.851661,53.217246],"type":"Point"}
}