{
  "type": "Feature",
  "properties": {
    "iso:country":"GB",
    "wof:name":"LL32 8UL",
    "wof:placetype":"postalcode"
},
  "geometry": {"coordinates":[-3.85165630333871,53.21722947023198],"type":"Point"}
}