{
  "type": "Feature",
  "properties": {
    "iso:country":"GB",
    "wof:name":"WN1 1SU",
    "wof:placetype":"postalcode"
},
  "geometry": {"coordinates":[-2.63357194940829,53.5504895202959],"type":"Point"}
}