{
  "type": "Feature",
  "properties": {
    "date:inception_lower": "1984-10-01",
    "date:inception_upper": "1984-10-01",
    "iso:country": "GB",
    "wof:name": "CW8 4AX",
    "wof:placetype": "postalcode"
  },
  "geometry": {"coordinates":[-2.538442,53.253053],"type":"Point"}
}
