{
  "type": "Feature",
  "properties": {
    "iso:country":"GB",
    "wof:name":"CW8 4AX",
    "wof:placetype":"postalcode"
},
  "geometry": {"coordinates":[-2.53845416330373,53.25281061884429],"type":"Point"}
}