{
  "type": "Feature",
  "properties": {
    "iso:country": "GB",
    "wof:name": "B8 2RH",
    "wof:placetype": "postalcode"
  },
  "geometry": {"coordinates":[-1.824064,52.497965],"type":"Point"}
}
