{
  "type": "Feature",
  "properties": {
    "date:inception_lower": "1980-01-01",
    "date:inception_upper": "1980-01-01",
    "iso:country": "GB",
    "wof:name": "B8 2RH",
    "wof:placetype": "postalcode"
  },
  "geometry": {"coordinates":[-1.824064,52.497965],"type":"Point"}
}
