{
  "type": "Feature",
  "properties": {
    "iso:country":"GB",
    "wof:name":"B8 2RH",
    "wof:placetype":"postalcode"
},
  "geometry": {"coordinates":[-1.82406412187235,52.49796457448649],"type":"Point"}
}