{
  "type": "Feature",
  "properties": {
    "iso:country":"GB",
    "wof:name":"DN21 4NA",
    "wof:placetype":"postalcode"
},
  "geometry": {"coordinates":[-0.58964119861991,53.47641902269083],"type":"Point"}
}