{
  "type": "Feature",
  "properties": {
    "iso:country": "GB",
    "wof:name": "GL14 1LW",
    "wof:placetype": "postalcode"
  },
  "geometry": {"coordinates":[-2.414705,51.827602],"type":"Point"}
}
