{
  "type": "Feature",
  "properties": {
    "iso:country": "GB",
    "wof:name": "IP14 5JB",
    "wof:placetype": "postalcode"
  },
  "geometry": {"coordinates":[1.005964,52.192338],"type":"Point"}
}
