{
  "type": "Feature",
  "properties": {
    "date:inception_lower":"2016-08-01",
    "date:inception_upper":"2016-08-31",
    "iso:country":"GB",
    "wof:name":"IP14 5JB",
    "wof:placetype":"postalcode"
},
  "geometry": {"coordinates":[1.005964,52.192338],"type":"Point"}
}