{
  "type": "Feature",
  "properties": {
    "iso:country":"GB",
    "wof:name":"RG6 3AX",
    "wof:placetype":"postalcode"
},
  "geometry": {"coordinates":[-0.90740459352941,51.42938255861116],"type":"Point"}
}