{
  "type": "Feature",
  "properties": {
    "iso:country":"GB",
    "wof:name":"WD4 9BS",
    "wof:placetype":"postalcode"
},
  "geometry": {"coordinates":[-0.49254853987298,51.70335645730752],"type":"Point"}
}