{
  "type": "Feature",
  "properties": {
    "iso:country": "GB",
    "wof:name": "WD4 9BS",
    "wof:placetype": "postalcode"
  },
  "geometry": {"coordinates":[-0.492527,51.703371],"type":"Point"}
}
