{
  "type": "Feature",
  "properties": {
    "iso:country":"GB",
    "wof:name":"NE33 4QL",
    "wof:placetype":"postalcode"
},
  "geometry": {"coordinates":[-1.43391709283763,54.98936944939818],"type":"Point"}
}