{
  "type": "Feature",
  "properties": {
    "iso:country": "GB",
    "wof:name": "NE33 4QL",
    "wof:placetype": "postalcode"
  },
  "geometry": {"coordinates":[-1.433917,54.989369],"type":"Point"}
}
