{
  "type": "Feature",
  "properties": {
    "iso:country":"GB",
    "wof:name":"UB6 7QR",
    "wof:placetype":"postalcode"
},
  "geometry": {"coordinates":[-0.32613053502989,51.55118626556778],"type":"Point"}
}