{
  "type": "Feature",
  "properties": {
    "date:inception_lower": "1980-01-01",
    "date:inception_upper": "1980-01-01",
    "iso:country": "GB",
    "wof:name": "UB6 7QR",
    "wof:placetype": "postalcode"
  },
  "geometry": {"coordinates":[-0.32613,51.551186],"type":"Point"}
}
