{
  "type": "Feature",
  "properties": {
    "iso:country": "GB",
    "wof:name": "PE29 7JW",
    "wof:placetype": "postalcode"
  },
  "geometry": {"coordinates":[-0.177304,52.349361],"type":"Point"}
}
