{
  "type": "Feature",
  "properties": {
    "iso:country":"GB",
    "wof:name":"PE29 7JW",
    "wof:placetype":"postalcode"
},
  "geometry": {"coordinates":[-0.17730393464833,52.34936119937888],"type":"Point"}
}