{
  "type": "Feature",
  "properties": {
    "iso:country":"GB",
    "wof:name":"SE17 3UX",
    "wof:placetype":"postalcode"
},
  "geometry": {"coordinates":[-0.09968666237245,51.48269401553069],"type":"Point"}
}