{
  "type": "Feature",
  "properties": {
    "date:inception_lower":"1980-01-01",
    "date:inception_upper":"1980-01-31",
    "iso:country":"GB",
    "wof:name":"GU26 6RU",
    "wof:placetype":"postalcode"
},
  "geometry": {"coordinates":[-0.754463,51.126275],"type":"Point"}
}