{
  "type": "Feature",
  "properties": {
    "iso:country":"GB",
    "wof:name":"GU26 6RU",
    "wof:placetype":"postalcode"
},
  "geometry": {"coordinates":[-0.75446255350797,51.12627484742458],"type":"Point"}
}