{
  "type": "Feature",
  "properties": {
    "iso:country": "GB",
    "wof:name": "GU26 6RU",
    "wof:placetype": "postalcode"
  },
  "geometry": {"coordinates":[-0.754463,51.126275],"type":"Point"}
}
