{
  "type": "Feature",
  "properties": {
    "iso:country":"GB",
    "wof:name":"NP44 8TP",
    "wof:placetype":"postalcode"
},
  "geometry": {"coordinates":[-3.01033709919006,51.6508712916453],"type":"Point"}
}