{
  "type": "Feature",
  "properties": {
    "iso:country": "GB",
    "wof:name": "NP44 8TP",
    "wof:placetype": "postalcode"
  },
  "geometry": {"coordinates":[-3.010286,51.650848],"type":"Point"}
}
