{
  "type": "Feature",
  "properties": {
    "iso:country":"GB",
    "wof:name":"LA3 3ER",
    "wof:placetype":"postalcode"
},
  "geometry": {"coordinates":[-2.84274249905131,54.04812672518401],"type":"Point"}
}