{
  "type": "Feature",
  "properties": {
    "date:inception_lower": "1980-01-01",
    "date:inception_upper": "1980-01-01",
    "iso:country": "GB",
    "wof:name": "LA3 3ER",
    "wof:placetype": "postalcode"
  },
  "geometry": {"coordinates":[-2.842742,54.048127],"type":"Point"}
}
