{
  "type": "Feature",
  "properties": {
    "iso:country": "GB",
    "wof:name": "LA3 3ER",
    "wof:placetype": "postalcode"
  },
  "geometry": {"coordinates":[-2.842742,54.048127],"type":"Point"}
}
