{
  "type": "Feature",
  "properties": {
    "iso:country":"GB",
    "wof:name":"GU16 6JG",
    "wof:placetype":"postalcode"
},
  "geometry": {"coordinates":[-0.73022972307977,51.2922205369135],"type":"Point"}
}