{
  "type": "Feature",
  "properties": {
    "date:inception_lower": "1980-01-01",
    "date:inception_upper": "1980-01-01",
    "iso:country": "GB",
    "wof:name": "RM3 9YL",
    "wof:placetype": "postalcode"
  },
  "geometry": {"coordinates":[0.244,51.605929],"type":"Point"}
}
