{
  "type": "Feature",
  "properties": {
    "iso:country":"GB",
    "wof:name":"RM3 9YL",
    "wof:placetype":"postalcode"
},
  "geometry": {"coordinates":[0.24399968745037,51.6059294731906],"type":"Point"}
}