{
  "type": "Feature",
  "properties": {
    "date:inception_lower": "1980-01-01",
    "date:inception_upper": "1980-01-01",
    "iso:country": "GB",
    "wof:name": "SR8 4DR",
    "wof:placetype": "postalcode"
  },
  "geometry": {"coordinates":[-1.313631,54.766073],"type":"Point"}
}
