{
  "type": "Feature",
  "properties": {
    "iso:country":"GB",
    "wof:name":"SR8 4DR",
    "wof:placetype":"postalcode"
},
  "geometry": {"coordinates":[-1.31363123142072,54.7660727055697],"type":"Point"}
}