{
  "type": "Feature",
  "properties": {
    "iso:country": "GB",
    "wof:name": "TA23 0LD",
    "wof:placetype": "postalcode"
  },
  "geometry": {"coordinates":[-3.374072,51.148234],"type":"Point"}
}
