{
  "type": "Feature",
  "properties": {
    "iso:country":"GB",
    "wof:name":"TA23 0LD",
    "wof:placetype":"postalcode"
},
  "geometry": {"coordinates":[-3.37381888870512,51.14832969463363],"type":"Point"}
}