{
  "type": "Feature",
  "properties": {
    "date:inception_lower":"1980-01-01",
    "date:inception_upper":"1980-01-31",
    "iso:country":"GB",
    "wof:name":"TA23 0LD",
    "wof:placetype":"postalcode"
},
  "geometry": {"coordinates":[-3.374072,51.148234],"type":"Point"}
}