{
  "type": "Feature",
  "properties": {
    "iso:country": "GB",
    "wof:name": "PE28 2JQ",
    "wof:placetype": "postalcode"
  },
  "geometry": {"coordinates":[-0.074593,52.401005],"type":"Point"}
}
