{
  "type": "Feature",
  "properties": {
    "date:inception_lower": "2019-07-01",
    "date:inception_upper": "2019-07-01",
    "iso:country": "GB",
    "wof:name": "PE28 2JQ",
    "wof:placetype": "postalcode"
  },
  "geometry": {"coordinates":[-0.074595,52.40096],"type":"Point"}
}
