{
  "type": "Feature",
  "properties": {
    "iso:country": "GB",
    "wof:name": "ME14 4EN",
    "wof:placetype": "postalcode"
  },
  "geometry": {"coordinates":[0.5819,51.273584],"type":"Point"}
}
