{
  "type": "Feature",
  "properties": {
    "iso:country":"GB",
    "wof:name":"ME14 4EN",
    "wof:placetype":"postalcode"
},
  "geometry": {"coordinates":[0.58190010644392,51.27358399825934],"type":"Point"}
}