{
  "type": "Feature",
  "properties": {
    "iso:country":"GB",
    "wof:name":"GL8 8ER",
    "wof:placetype":"postalcode"
},
  "geometry": {"coordinates":[-2.15904895279399,51.64329689666566],"type":"Point"}
}