{
  "type": "Feature",
  "properties": {
    "iso:country":"GB",
    "wof:name":"B72 1EL",
    "wof:placetype":"postalcode"
},
  "geometry": {"coordinates":[-1.8222805354248,52.54216528935256],"type":"Point"}
}