{
  "type": "Feature",
  "properties": {
    "iso:country":"GB",
    "wof:name":"YO1 6EN",
    "wof:placetype":"postalcode"
},
  "geometry": {"coordinates":[-1.08717291823106,53.95607625765886],"type":"Point"}
}