{
  "type": "Feature",
  "properties": {
    "iso:country": "GB",
    "wof:name": "YO1 6EN",
    "wof:placetype": "postalcode"
  },
  "geometry": {"coordinates":[-1.087173,53.956076],"type":"Point"}
}
