{
  "type": "Feature",
  "properties": {
    "iso:country": "GB",
    "wof:name": "IV36 1DP",
    "wof:placetype": "postalcode"
  },
  "geometry": {"coordinates":[-3.606842,57.60543],"type":"Point"}
}
