{
  "type": "Feature",
  "properties": {
    "iso:country":"GB",
    "wof:name":"EH2 1EX",
    "wof:placetype":"postalcode"
},
  "geometry": {"coordinates":[-3.20112115321727,55.95347038622668],"type":"Point"}
}