{
  "type": "Feature",
  "properties": {
    "iso:country":"GB",
    "wof:name":"LL49 9UH",
    "wof:placetype":"postalcode"
},
  "geometry": {"coordinates":[-4.13771950211205,52.91672275034013],"type":"Point"}
}