{
  "type": "Feature",
  "properties": {
    "iso:country":"GB",
    "wof:name":"AB53 8NE",
    "wof:placetype":"postalcode"
},
  "geometry": {"coordinates":[-2.32420987748664,57.45973388780327],"type":"Point"}
}