{
  "type": "Feature",
  "properties": {
    "iso:country": "GB",
    "wof:name": "AB53 8NE",
    "wof:placetype": "postalcode"
  },
  "geometry": {"coordinates":[-2.32421,57.459734],"type":"Point"}
}
