{
  "type": "Feature",
  "properties": {
    "date:inception_lower":"1980-01-01",
    "date:inception_upper":"1980-01-31",
    "iso:country":"GB",
    "wof:name":"RH1 6DU",
    "wof:placetype":"postalcode"
},
  "geometry": {"coordinates":[-0.167779,51.230409],"type":"Point"}
}