{
  "type": "Feature",
  "properties": {
    "iso:country": "GB",
    "wof:name": "RH1 6DU",
    "wof:placetype": "postalcode"
  },
  "geometry": {"coordinates":[-0.167779,51.230409],"type":"Point"}
}
