{
  "type": "Feature",
  "properties": {
    "iso:country":"GB",
    "wof:name":"RH1 6DU",
    "wof:placetype":"postalcode"
},
  "geometry": {"coordinates":[-0.16777889251462,51.23040864859563],"type":"Point"}
}