{
  "type": "Feature",
  "properties": {
    "iso:country": "GB",
    "wof:name": "E17 8JW",
    "wof:placetype": "postalcode"
  },
  "geometry": {"coordinates":[-0.022836,51.573166],"type":"Point"}
}
