{
  "type": "Feature",
  "properties": {
    "date:inception_lower": "1982-03-01",
    "date:inception_upper": "1982-03-01",
    "iso:country": "GB",
    "wof:name": "DA11 0SS",
    "wof:placetype": "postalcode"
  },
  "geometry": {"coordinates":[0.362512,51.438822],"type":"Point"}
}
