{
  "type": "Feature",
  "properties": {
    "iso:country":"GB",
    "wof:name":"DA11 0SS",
    "wof:placetype":"postalcode"
},
  "geometry": {"coordinates":[0.3625121408714,51.43882192834082],"type":"Point"}
}