{
  "type": "Feature",
  "properties": {
    "iso:country": "GB",
    "wof:name": "DA11 0SS",
    "wof:placetype": "postalcode"
  },
  "geometry": {"coordinates":[0.362512,51.438822],"type":"Point"}
}
