{
  "type": "Feature",
  "properties": {
    "iso:country":"GB",
    "wof:name":"WV16 4QN",
    "wof:placetype":"postalcode"
},
  "geometry": {"coordinates":[-2.4218839901194,52.53616964265827],"type":"Point"}
}