{
  "type": "Feature",
  "properties": {
    "iso:country": "GB",
    "wof:name": "WV16 4QN",
    "wof:placetype": "postalcode"
  },
  "geometry": {"coordinates":[-2.421925,52.536148],"type":"Point"}
}
