{
  "type": "Feature",
  "properties": {
    "iso:country": "GB",
    "wof:name": "YO32 3NU",
    "wof:placetype": "postalcode"
  },
  "geometry": {"coordinates":[-1.069764,54.013546],"type":"Point"}
}
