{
  "type": "Feature",
  "properties": {
    "iso:country":"GB",
    "wof:name":"YO32 3NU",
    "wof:placetype":"postalcode"
},
  "geometry": {"coordinates":[-1.06974011682899,54.01351095664561],"type":"Point"}
}