{
  "type": "Feature",
  "properties": {
    "iso:country":"GB",
    "wof:name":"SE14 5QB",
    "wof:placetype":"postalcode"
},
  "geometry": {"coordinates":[-0.04361172160946,51.4781207968997],"type":"Point"}
}