{
  "type": "Feature",
  "properties": {
    "date:inception_lower": "1981-09-01",
    "date:inception_upper": "1981-09-01",
    "iso:country": "GB",
    "wof:name": "SE14 5QB",
    "wof:placetype": "postalcode"
  },
  "geometry": {"coordinates":[-0.043612,51.478121],"type":"Point"}
}
