{
  "type": "Feature",
  "properties": {
    "iso:country": "GB",
    "wof:name": "SE14 5QB",
    "wof:placetype": "postalcode"
  },
  "geometry": {"coordinates":[-0.043612,51.478121],"type":"Point"}
}
