{
  "type": "Feature",
  "properties": {
    "iso:country":"GB",
    "wof:name":"NG6 0QS",
    "wof:placetype":"postalcode"
},
  "geometry": {"coordinates":[-1.18356277664098,52.98400194376022],"type":"Point"}
}