{
  "type": "Feature",
  "properties": {
    "iso:country":"GB",
    "wof:name":"LS18 5QS",
    "wof:placetype":"postalcode"
},
  "geometry": {"coordinates":[-1.62503899959808,53.84159420684446],"type":"Point"}
}