{
  "type": "Feature",
  "properties": {
    "iso:country":"GB",
    "wof:name":"SW19 3DA",
    "wof:placetype":"postalcode"
},
  "geometry": {"coordinates":[-0.1920985200768,51.40456221560195],"type":"Point"}
}