{
  "type": "Feature",
  "properties": {
    "date:inception_lower":"1991-01-01",
    "date:inception_upper":"1991-01-31",
    "iso:country":"GB",
    "wof:name":"KT2 7LF",
    "wof:placetype":"postalcode"
},
  "geometry": {"coordinates":[-0.271296,51.423104],"type":"Point"}
}