{
  "type": "Feature",
  "properties": {
    "iso:country": "GB",
    "wof:name": "MK2 2NH",
    "wof:placetype": "postalcode"
  },
  "geometry": {"coordinates":[-0.718726,51.996851],"type":"Point"}
}
