{
  "type": "Feature",
  "properties": {
    "iso:country":"GB",
    "wof:name":"MK2 2NH",
    "wof:placetype":"postalcode"
},
  "geometry": {"coordinates":[-0.71872577246646,51.99685105849245],"type":"Point"}
}