{
  "type": "Feature",
  "properties": {
    "iso:country":"GB",
    "wof:name":"BN11 2PD",
    "wof:placetype":"postalcode"
},
  "geometry": {"coordinates":[-0.34600671109392,50.816400639756],"type":"Point"}
}