{
  "type": "Feature",
  "properties": {
    "iso:country":"GB",
    "wof:name":"S41 8BG",
    "wof:placetype":"postalcode"
},
  "geometry": {"coordinates":[-1.45941391316029,53.25390898793803],"type":"Point"}
}