{
  "type": "Feature",
  "properties": {
    "date:inception_lower":"1987-10-01",
    "date:inception_upper":"1987-10-31",
    "iso:country":"GB",
    "wof:name":"PO19 1SF",
    "wof:placetype":"postalcode"
},
  "geometry": {"coordinates":[-0.785753,50.835897],"type":"Point"}
}