{
  "type": "Feature",
  "properties": {
    "date:inception_lower": "1980-01-01",
    "date:inception_upper": "1980-01-01",
    "iso:country": "GB",
    "wof:name": "LL20 8EU",
    "wof:placetype": "postalcode"
  },
  "geometry": {"coordinates":[-3.168281,52.968184],"type":"Point"}
}
