{
  "type": "Feature",
  "properties": {
    "date:inception_lower":"1990-12-01",
    "date:inception_upper":"1990-12-31",
    "iso:country":"GB",
    "wof:name":"FK2 7RD",
    "wof:placetype":"postalcode"
},
  "geometry": {"coordinates":[-3.783009,56.010621],"type":"Point"}
}