{
  "type": "Feature",
  "properties": {
    "iso:country":"GB",
    "wof:name":"FK2 7RD",
    "wof:placetype":"postalcode"
},
  "geometry": {"coordinates":[-3.78300940501645,56.01062116404242],"type":"Point"}
}