{
  "type": "Feature",
  "properties": {
    "iso:country": "GB",
    "wof:name": "KY16 0EU",
    "wof:placetype": "postalcode"
  },
  "geometry": {"coordinates":[-2.890074,56.382207],"type":"Point"}
}
