{
  "type": "Feature",
  "properties": {
    "iso:country":"GB",
    "wof:name":"G81 3NE",
    "wof:placetype":"postalcode"
},
  "geometry": {"coordinates":[-4.41302663487687,55.91752595533301],"type":"Point"}
}