{
  "type": "Feature",
  "properties": {
    "iso:country":"GB",
    "wof:name":"NG9 3RG",
    "wof:placetype":"postalcode"
},
  "geometry": {"coordinates":[-1.27810551186548,52.94540154656491],"type":"Point"}
}