{
  "type": "Feature",
  "properties": {
    "iso:country": "GB",
    "wof:name": "NG9 3RG",
    "wof:placetype": "postalcode"
  },
  "geometry": {"coordinates":[-1.278105,52.945402],"type":"Point"}
}
