{
  "type": "Feature",
  "properties": {
    "date:inception_lower":"1980-01-01",
    "date:inception_upper":"1980-01-31",
    "iso:country":"GB",
    "wof:name":"TD2 6SQ",
    "wof:placetype":"postalcode"
},
  "geometry": {"coordinates":[-2.649987,55.719406],"type":"Point"}
}