{
  "type": "Feature",
  "properties": {
    "iso:country": "GB",
    "wof:name": "RH6 9QZ",
    "wof:placetype": "postalcode"
  },
  "geometry": {"coordinates":[-0.125567,51.172599],"type":"Point"}
}
