{
  "type": "Feature",
  "properties": {
    "date:inception_lower":"1993-08-01",
    "date:inception_upper":"1993-08-31",
    "iso:country":"GB",
    "wof:name":"RH6 9QZ",
    "wof:placetype":"postalcode"
},
  "geometry": {"coordinates":[-0.125567,51.172599],"type":"Point"}
}