{
  "type": "Feature",
  "properties": {
    "iso:country":"GB",
    "wof:name":"GL16 7AG",
    "wof:placetype":"postalcode"
},
  "geometry": {"coordinates":[-2.61897408020263,51.8119854222166],"type":"Point"}
}