{
  "type": "Feature",
  "properties": {
    "date:inception_lower":"1980-01-01",
    "date:inception_upper":"1980-01-31",
    "iso:country":"GB",
    "wof:name":"GL16 7AG",
    "wof:placetype":"postalcode"
},
  "geometry": {"coordinates":[-2.618974,51.811985],"type":"Point"}
}