{
  "type": "Feature",
  "properties": {
    "date:inception_lower": "1980-01-01",
    "date:inception_upper": "1980-01-01",
    "iso:country": "GB",
    "wof:name": "LL35 0PY",
    "wof:placetype": "postalcode"
  },
  "geometry": {"coordinates":[-4.029086,52.546749],"type":"Point"}
}
