{
  "type": "Feature",
  "properties": {
    "date:inception_lower": "2018-04-01",
    "date:inception_upper": "2018-04-01",
    "iso:country": "GB",
    "wof:name": "S72 7FS",
    "wof:placetype": "postalcode"
  },
  "geometry": {"coordinates":[-1.377721,53.586423],"type":"Point"}
}
