{
  "type": "Feature",
  "properties": {
    "iso:country": "GB",
    "wof:name": "S72 7FS",
    "wof:placetype": "postalcode"
  },
  "geometry": {"coordinates":[-1.377856,53.586469],"type":"Point"}
}
