{
  "type": "Feature",
  "properties": {
    "iso:country":"GB",
    "wof:name":"NN12 8PE",
    "wof:placetype":"postalcode"
},
  "geometry": {"coordinates":[-1.06282280723849,52.11625321837139],"type":"Point"}
}