{
  "type": "Feature",
  "properties": {
    "date:inception_lower":"2005-01-01",
    "date:inception_upper":"2005-01-31",
    "iso:country":"GB",
    "wof:name":"PH1 3FT",
    "wof:placetype":"postalcode"
},
  "geometry": {"coordinates":[-3.462982,56.41546],"type":"Point"}
}