{
  "type": "Feature",
  "properties": {
    "iso:country": "GB",
    "wof:name": "PH1 3FT",
    "wof:placetype": "postalcode"
  },
  "geometry": {"coordinates":[-3.462982,56.41546],"type":"Point"}
}
