{
  "type": "Feature",
  "properties": {
    "iso:country":"GB",
    "wof:name":"LL32 8PR",
    "wof:placetype":"postalcode"
},
  "geometry": {"coordinates":[-3.83613447022976,53.28255799637151],"type":"Point"}
}