{
  "type": "Feature",
  "properties": {
    "iso:country":"GB",
    "wof:name":"CH6 6LJ",
    "wof:placetype":"postalcode"
},
  "geometry": {"coordinates":[-3.18866183848765,53.27723368896599],"type":"Point"}
}