{
  "type": "Feature",
  "properties": {
    "date:inception_lower":"1980-01-01",
    "date:inception_upper":"1980-01-31",
    "iso:country":"GB",
    "wof:name":"DD8 1LB",
    "wof:placetype":"postalcode"
},
  "geometry": {"coordinates":[-2.898434,56.639926],"type":"Point"}
}