{
  "type": "Feature",
  "properties": {
    "iso:country":"GB",
    "wof:name":"DD8 1LB",
    "wof:placetype":"postalcode"
},
  "geometry": {"coordinates":[-2.89843448030595,56.6399262038033],"type":"Point"}
}