{
  "type": "Feature",
  "properties": {
    "iso:country":"GB",
    "wof:name":"SK3 0NF",
    "wof:placetype":"postalcode"
},
  "geometry": {"coordinates":[-2.19256053252553,53.40342540945407],"type":"Point"}
}