{
  "type": "Feature",
  "properties": {
    "iso:country": "GB",
    "wof:name": "LA5 9JY",
    "wof:placetype": "postalcode"
  },
  "geometry": {"coordinates":[-2.766996,54.129067],"type":"Point"}
}
