{
  "type": "Feature",
  "properties": {
    "iso:country":"GB",
    "wof:name":"LA5 9JY",
    "wof:placetype":"postalcode"
},
  "geometry": {"coordinates":[-2.76701254184486,54.12905624842384],"type":"Point"}
}