{
  "type": "Feature",
  "properties": {
    "iso:country":"GB",
    "wof:name":"CB7 4UY",
    "wof:placetype":"postalcode"
},
  "geometry": {"coordinates":[0.34082975861488,52.41482806270925],"type":"Point"}
}