{
  "type": "Feature",
  "properties": {
    "date:inception_lower": "1992-01-01",
    "date:inception_upper": "1992-01-01",
    "iso:country": "GB",
    "wof:name": "CB7 4UY",
    "wof:placetype": "postalcode"
  },
  "geometry": {"coordinates":[0.34083,52.414828],"type":"Point"}
}
