{
  "type": "Feature",
  "properties": {
    "iso:country":"GB",
    "wof:name":"B15 1JB",
    "wof:placetype":"postalcode"
},
  "geometry": {"coordinates":[-1.91831916025653,52.46764494956115],"type":"Point"}
}