{
  "type": "Feature",
  "properties": {
    "date:inception_lower":"1996-06-01",
    "date:inception_upper":"1996-06-30",
    "iso:country":"GB",
    "wof:name":"M33 4ZP",
    "wof:placetype":"postalcode"
},
  "geometry": {"coordinates":[-2.352266,53.417964],"type":"Point"}
}