{
  "type": "Feature",
  "properties": {
    "iso:country":"GB",
    "wof:name":"M33 4ZP",
    "wof:placetype":"postalcode"
},
  "geometry": {"coordinates":[-2.35226583290801,53.4179638243732],"type":"Point"}
}