{
  "type": "Feature",
  "properties": {
    "iso:country":"GB",
    "wof:name":"B63 2ES",
    "wof:placetype":"postalcode"
},
  "geometry": {"coordinates":[-2.08921633339686,52.45225725007982],"type":"Point"}
}