{
  "type": "Feature",
  "properties": {
    "iso:country": "GB",
    "wof:name": "B63 2ES",
    "wof:placetype": "postalcode"
  },
  "geometry": {"coordinates":[-2.089216,52.452257],"type":"Point"}
}
