{
  "type": "Feature",
  "properties": {
    "iso:country": "GB",
    "wof:name": "LN4 1PL",
    "wof:placetype": "postalcode"
  },
  "geometry": {"coordinates":[-0.473208,53.197229],"type":"Point"}
}
