{
  "type": "Feature",
  "properties": {
    "iso:country": "GB",
    "wof:name": "SN12 8NN",
    "wof:placetype": "postalcode"
  },
  "geometry": {"coordinates":[-2.215828,51.369836],"type":"Point"}
}
