{
  "type": "Feature",
  "properties": {
    "iso:country":"GB",
    "wof:name":"DH6 4SF",
    "wof:placetype":"postalcode"
},
  "geometry": {"coordinates":[-1.50260624814353,54.71302045644615],"type":"Point"}
}