{
  "type": "Feature",
  "properties": {
    "date:inception_lower":"2012-02-01",
    "date:inception_upper":"2012-02-29",
    "iso:country":"GB",
    "wof:name":"W3 8FS",
    "wof:placetype":"postalcode"
},
  "geometry": {"coordinates":[-0.270737,51.501123],"type":"Point"}
}