{
  "type": "Feature",
  "properties": {
    "iso:country":"GB",
    "wof:name":"HU17 0GR",
    "wof:placetype":"postalcode"
},
  "geometry": {"coordinates":[-0.41527118497942,53.83952760798781],"type":"Point"}
}