{
  "type": "Feature",
  "properties": {
    "date:inception_lower":"2006-01-01",
    "date:inception_upper":"2006-01-31",
    "iso:country":"GB",
    "wof:name":"HU17 0GR",
    "wof:placetype":"postalcode"
},
  "geometry": {"coordinates":[-0.415271,53.839528],"type":"Point"}
}