{
  "type": "Feature",
  "properties": {
    "iso:country": "GB",
    "wof:name": "NP20 5PF",
    "wof:placetype": "postalcode"
  },
  "geometry": {"coordinates":[-3.003117,51.599171],"type":"Point"}
}
