{
  "type": "Feature",
  "properties": {
    "iso:country":"GB",
    "wof:name":"NP20 5PF",
    "wof:placetype":"postalcode"
},
  "geometry": {"coordinates":[-3.00311059537862,51.5991686995953],"type":"Point"}
}