{
  "type": "Feature",
  "properties": {
    "iso:country":"GB",
    "wof:name":"TA24 6TR",
    "wof:placetype":"postalcode"
},
  "geometry": {"coordinates":[-3.45796452823799,51.19204891153453],"type":"Point"}
}