{
  "type": "Feature",
  "properties": {
    "date:inception_lower":"2001-06-01",
    "date:inception_upper":"2001-06-30",
    "iso:country":"GB",
    "wof:name":"BA12 0DX",
    "wof:placetype":"postalcode"
},
  "geometry": {"coordinates":[-2.185781,51.213828],"type":"Point"}
}