{
  "type": "Feature",
  "properties": {
    "iso:country": "GB",
    "wof:name": "BA12 0DX",
    "wof:placetype": "postalcode"
  },
  "geometry": {"coordinates":[-2.185781,51.213828],"type":"Point"}
}
