{
  "type": "Feature",
  "properties": {
    "iso:country":"GB",
    "wof:name":"M4 6EE",
    "wof:placetype":"postalcode"
},
  "geometry": {"coordinates":[-2.21939723744174,53.48292738019197],"type":"Point"}
}