{
  "type": "Feature",
  "properties": {
    "iso:country": "GB",
    "wof:name": "HP20 2AG",
    "wof:placetype": "postalcode"
  },
  "geometry": {"coordinates":[-0.812184,51.827526],"type":"Point"}
}
