{
  "type": "Feature",
  "properties": {
    "date:inception_lower":"1994-05-01",
    "date:inception_upper":"1994-05-31",
    "iso:country":"GB",
    "wof:name":"M46 0RX",
    "wof:placetype":"postalcode"
},
  "geometry": {"coordinates":[-2.51009,53.522569],"type":"Point"}
}