{
  "type": "Feature",
  "properties": {
    "iso:country":"GB",
    "wof:name":"M46 0RX",
    "wof:placetype":"postalcode"
},
  "geometry": {"coordinates":[-2.5100900419662,53.52256878415613],"type":"Point"}
}