{
  "type": "Feature",
  "properties": {
    "date:inception_lower": "2023-07-01",
    "date:inception_upper": "2023-07-01",
    "iso:country": "GB",
    "wof:name": "AL10 0FS",
    "wof:placetype": "postalcode"
  },
  "geometry": {"coordinates":[-0.225112,51.763956],"type":"Point"}
}
