{
  "type": "Feature",
  "properties": {
    "iso:country":"GB",
    "wof:name":"EC3A 8BN",
    "wof:placetype":"postalcode"
},
  "geometry": {"coordinates":[-0.08111419214456,51.51374873425349],"type":"Point"}
}