{
  "type": "Feature",
  "properties": {
    "date:inception_lower":"2011-08-01",
    "date:inception_upper":"2011-08-31",
    "iso:country":"GB",
    "wof:name":"EC3A 8BN",
    "wof:placetype":"postalcode"
},
  "geometry": {"coordinates":[-0.081114,51.513749],"type":"Point"}
}