{
  "type": "Feature",
  "properties": {
    "iso:country":"GB",
    "wof:name":"HR9 7TJ",
    "wof:placetype":"postalcode"
},
  "geometry": {"coordinates":[-2.55677367316665,51.92951206286534],"type":"Point"}
}