{
  "type": "Feature",
  "properties": {
    "iso:country": "GB",
    "wof:name": "HR9 7TJ",
    "wof:placetype": "postalcode"
  },
  "geometry": {"coordinates":[-2.556774,51.929512],"type":"Point"}
}
