{
  "type": "Feature",
  "properties": {
    "iso:country": "GB",
    "wof:name": "E4 9LR",
    "wof:placetype": "postalcode"
  },
  "geometry": {"coordinates":[-0.003327,51.607043],"type":"Point"}
}
