{
  "type": "Feature",
  "properties": {
    "iso:country":"GB",
    "wof:name":"EH19 3QJ",
    "wof:placetype":"postalcode"
},
  "geometry": {"coordinates":[-3.09182951050413,55.87996243459204],"type":"Point"}
}