{
  "type": "Feature",
  "properties": {
    "iso:country":"GB",
    "wof:name":"HX4 0ER",
    "wof:placetype":"postalcode"
},
  "geometry": {"coordinates":[-1.90970844589602,53.66268152534019],"type":"Point"}
}