{
  "type": "Feature",
  "properties": {
    "iso:country":"GB",
    "wof:name":"SW1V 3BT",
    "wof:placetype":"postalcode"
},
  "geometry": {"coordinates":[-0.14337156208647,51.48689194261737],"type":"Point"}
}