{
  "type": "Feature",
  "properties": {
    "date:inception_lower": "1980-01-01",
    "date:inception_upper": "1980-01-01",
    "iso:country": "GB",
    "wof:name": "SW1V 3BT",
    "wof:placetype": "postalcode"
  },
  "geometry": {"coordinates":[-0.143372,51.486892],"type":"Point"}
}
