{
  "type": "Feature",
  "properties": {
    "iso:country": "GB",
    "wof:name": "TW7 7AH",
    "wof:placetype": "postalcode"
  },
  "geometry": {"coordinates":[-0.326977,51.467894],"type":"Point"}
}
