{
  "type": "Feature",
  "properties": {
    "date:inception_lower":"2014-05-01",
    "date:inception_upper":"2014-05-31",
    "iso:country":"GB",
    "wof:name":"B37 7FW",
    "wof:placetype":"postalcode"
},
  "geometry": {"coordinates":[-1.741661,52.460748],"type":"Point"}
}