{
  "type": "Feature",
  "properties": {
    "iso:country":"GB",
    "wof:name":"B37 7FW",
    "wof:placetype":"postalcode"
},
  "geometry": {"coordinates":[-1.74166069229528,52.46074785720741],"type":"Point"}
}