{
  "type": "Feature",
  "properties": {
    "iso:country":"GB",
    "wof:name":"CB4 1TF",
    "wof:placetype":"postalcode"
},
  "geometry": {"coordinates":[0.15242663245708,52.22740529015785],"type":"Point"}
}