{
  "type": "Feature",
  "properties": {
    "iso:country":"GB",
    "wof:name":"SL4 3TR",
    "wof:placetype":"postalcode"
},
  "geometry": {"coordinates":[-0.62890706398765,51.4748878563643],"type":"Point"}
}