{
  "type": "Feature",
  "properties": {
    "date:inception_lower":"2002-06-01",
    "date:inception_upper":"2002-06-30",
    "iso:country":"GB",
    "wof:name":"SL4 3TR",
    "wof:placetype":"postalcode"
},
  "geometry": {"coordinates":[-0.628907,51.474888],"type":"Point"}
}