{
  "type": "Feature",
  "properties": {
    "iso:country":"GB",
    "wof:name":"NW6 3DB",
    "wof:placetype":"postalcode"
},
  "geometry": {"coordinates":[-0.18736437203269,51.54488010670849],"type":"Point"}
}