{
  "type": "Feature",
  "properties": {
    "date:inception_lower":"2003-08-01",
    "date:inception_upper":"2003-08-31",
    "iso:country":"GB",
    "wof:name":"PE2 7DZ",
    "wof:placetype":"postalcode"
},
  "geometry": {"coordinates":[-0.280001,52.559915],"type":"Point"}
}