{
  "type": "Feature",
  "properties": {
    "date:inception_lower": "1994-05-01",
    "date:inception_upper": "1994-05-01",
    "iso:country": "GB",
    "wof:name": "M4 7DD",
    "wof:placetype": "postalcode"
  },
  "geometry": {"coordinates":[-2.21537,53.479213],"type":"Point"}
}
