{
  "type": "Feature",
  "properties": {
    "date:inception_lower":"1994-05-01",
    "date:inception_upper":"1994-05-31",
    "iso:country":"GB",
    "wof:name":"LE4 9WU",
    "wof:placetype":"postalcode"
},
  "geometry": {"coordinates":[-1.078257,52.667423],"type":"Point"}
}