{
  "type": "Feature",
  "properties": {
    "iso:country": "GB",
    "wof:name": "LL15 1DU",
    "wof:placetype": "postalcode"
  },
  "geometry": {"coordinates":[-3.303511,53.114339],"type":"Point"}
}
