{
  "type": "Feature",
  "properties": {
    "date:inception_lower":"1980-01-01",
    "date:inception_upper":"1980-01-31",
    "iso:country":"GB",
    "wof:name":"LL15 1DU",
    "wof:placetype":"postalcode"
},
  "geometry": {"coordinates":[-3.303511,53.114339],"type":"Point"}
}