{
  "type": "Feature",
  "properties": {
    "iso:country":"GB",
    "wof:name":"LL15 1DU",
    "wof:placetype":"postalcode"
},
  "geometry": {"coordinates":[-3.30351059342853,53.11433869890769],"type":"Point"}
}