{
  "type": "Feature",
  "properties": {
    "iso:country":"GB",
    "wof:name":"IP28 7DZ",
    "wof:placetype":"postalcode"
},
  "geometry": {"coordinates":[0.50995204089254,52.34189173410952],"type":"Point"}
}