{
  "type": "Feature",
  "properties": {
    "date:inception_lower": "2017-10-01",
    "date:inception_upper": "2017-10-01",
    "iso:country": "GB",
    "wof:name": "DD11 1PH",
    "wof:placetype": "postalcode"
  },
  "geometry": {"coordinates":[-2.58908,56.557262],"type":"Point"}
}
