{
  "type": "Feature",
  "properties": {
    "iso:country": "GB",
    "wof:name": "NG15 9EE",
    "wof:placetype": "postalcode"
  },
  "geometry": {"coordinates":[-1.158769,53.08407],"type":"Point"}
}
