{
  "type": "Feature",
  "properties": {
    "date:inception_lower":"1984-10-01",
    "date:inception_upper":"1984-10-31",
    "iso:country":"GB",
    "wof:name":"SG8 7EF",
    "wof:placetype":"postalcode"
},
  "geometry": {"coordinates":[-0.02283,52.050278],"type":"Point"}
}