{
  "type": "Feature",
  "properties": {
    "iso:country":"GB",
    "wof:name":"SG8 7EF",
    "wof:placetype":"postalcode"
},
  "geometry": {"coordinates":[-0.02288948389426,52.05025030370223],"type":"Point"}
}