{
  "type": "Feature",
  "properties": {
    "iso:country":"GB",
    "wof:name":"ML4 1QA",
    "wof:placetype":"postalcode"
},
  "geometry": {"coordinates":[-4.00843294428162,55.81937451791824],"type":"Point"}
}