{
  "type": "Feature",
  "properties": {
    "iso:country": "GB",
    "wof:name": "ML4 1QA",
    "wof:placetype": "postalcode"
  },
  "geometry": {"coordinates":[-4.008433,55.819375],"type":"Point"}
}
