{
  "type": "Feature",
  "properties": {
    "iso:country":"GB",
    "wof:name":"RH10 1PQ",
    "wof:placetype":"postalcode"
},
  "geometry": {"coordinates":[-0.17917216446192,51.11694275800134],"type":"Point"}
}