{
  "type": "Feature",
  "properties": {
    "iso:country":"GB",
    "wof:name":"SW19 4HS",
    "wof:placetype":"postalcode"
},
  "geometry": {"coordinates":[-0.21591095525722,51.41852391372445],"type":"Point"}
}