{
  "type": "Feature",
  "properties": {
    "date:inception_lower":"1986-01-01",
    "date:inception_upper":"1986-01-31",
    "iso:country":"GB",
    "wof:name":"SO51 8BY",
    "wof:placetype":"postalcode"
},
  "geometry": {"coordinates":[-1.493325,50.988931],"type":"Point"}
}