{
  "type": "Feature",
  "properties": {
    "iso:country":"GB",
    "wof:name":"SO51 8BY",
    "wof:placetype":"postalcode"
},
  "geometry": {"coordinates":[-1.49332513154583,50.98893111309212],"type":"Point"}
}