{
  "type": "Feature",
  "properties": {
    "iso:country": "GB",
    "wof:name": "SO51 8BY",
    "wof:placetype": "postalcode"
  },
  "geometry": {"coordinates":[-1.493325,50.988931],"type":"Point"}
}
