{
  "type": "Feature",
  "properties": {
    "iso:country":"GB",
    "wof:name":"WS13 6DF",
    "wof:placetype":"postalcode"
},
  "geometry": {"coordinates":[-1.8119551829351,52.68807120948041],"type":"Point"}
}