{
  "type": "Feature",
  "properties": {
    "iso:country": "GB",
    "wof:name": "RH10 8EY",
    "wof:placetype": "postalcode"
  },
  "geometry": {"coordinates":[-0.187088,51.120213],"type":"Point"}
}
