{
  "type": "Feature",
  "properties": {
    "iso:country":"GB",
    "wof:name":"NE47 0LH",
    "wof:placetype":"postalcode"
},
  "geometry": {"coordinates":[-2.10181941393402,54.90369157496641],"type":"Point"}
}