{
  "type": "Feature",
  "properties": {
    "date:inception_lower": "1980-01-01",
    "date:inception_upper": "1980-01-01",
    "iso:country": "GB",
    "wof:name": "NE47 0LH",
    "wof:placetype": "postalcode"
  },
  "geometry": {"coordinates":[-2.101828,54.903699],"type":"Point"}
}
