{
  "type": "Feature",
  "properties": {
    "date:inception_lower": "2021-01-01",
    "date:inception_upper": "2021-01-01",
    "iso:country": "GB",
    "wof:name": "PA17 5BQ",
    "wof:placetype": "postalcode"
  },
  "geometry": {"coordinates":[-4.88976,55.87373],"type":"Point"}
}
