{
  "type": "Feature",
  "properties": {
    "iso:country": "GB",
    "wof:name": "AB22 9AH",
    "wof:placetype": "postalcode"
  },
  "geometry": {"coordinates":[-2.132053,57.189398],"type":"Point"}
}
