{
  "type": "Feature",
  "properties": {
    "iso:country": "GB",
    "wof:name": "OX11 7UX",
    "wof:placetype": "postalcode"
  },
  "geometry": {"coordinates":[-1.237085,51.619763],"type":"Point"}
}
