{
  "type": "Feature",
  "properties": {
    "date:inception_lower": "2005-03-01",
    "date:inception_upper": "2005-03-01",
    "iso:country": "GB",
    "wof:name": "TS24 0YE",
    "wof:placetype": "postalcode"
  },
  "geometry": {"coordinates":[-1.19201,54.69433],"type":"Point"}
}
