{
  "type": "Feature",
  "properties": {
    "iso:country":"GB",
    "wof:name":"RM13 9DW",
    "wof:placetype":"postalcode"
},
  "geometry": {"coordinates":[0.21351694850458,51.50679516861518],"type":"Point"}
}