{
  "type": "Feature",
  "properties": {
    "date:inception_lower": "1980-01-01",
    "date:inception_upper": "1980-01-01",
    "iso:country": "GB",
    "wof:name": "RM13 9DW",
    "wof:placetype": "postalcode"
  },
  "geometry": {"coordinates":[0.213531,51.506787],"type":"Point"}
}
