{
  "type": "Feature",
  "properties": {
    "iso:country":"GB",
    "wof:name":"NE66 3ET",
    "wof:placetype":"postalcode"
},
  "geometry": {"coordinates":[-1.66165961916863,55.50005437986842],"type":"Point"}
}