{
  "type": "Feature",
  "properties": {
    "date:inception_lower":"2000-06-01",
    "date:inception_upper":"2000-06-30",
    "iso:country":"GB",
    "wof:name":"ST15 8ZB",
    "wof:placetype":"postalcode"
},
  "geometry": {"coordinates":[-2.146771,52.902905],"type":"Point"}
}