{
  "type": "Feature",
  "properties": {
    "iso:country":"GB",
    "wof:name":"ST15 8ZB",
    "wof:placetype":"postalcode"
},
  "geometry": {"coordinates":[-2.14677056828553,52.90290549587809],"type":"Point"}
}