{
  "type": "Feature",
  "properties": {
    "date:inception_lower": "1980-01-01",
    "date:inception_upper": "1980-01-01",
    "iso:country": "GB",
    "wof:name": "RH4 1JH",
    "wof:placetype": "postalcode"
  },
  "geometry": {"coordinates":[-0.327255,51.237896],"type":"Point"}
}
