{
  "type": "Feature",
  "properties": {
    "iso:country":"GB",
    "wof:name":"KT11 2BF",
    "wof:placetype":"postalcode"
},
  "geometry": {"coordinates":[-0.37937003195372,51.33975926415631],"type":"Point"}
}