{
  "type": "Feature",
  "properties": {
    "iso:country":"GB",
    "wof:name":"AB23 8QH",
    "wof:placetype":"postalcode"
},
  "geometry": {"coordinates":[-2.10227185158414,57.19180363780161],"type":"Point"}
}