{
  "type": "Feature",
  "properties": {
    "iso:country":"GB",
    "wof:name":"ME5 0TL",
    "wof:placetype":"postalcode"
},
  "geometry": {"coordinates":[0.51851586786692,51.35149222813995],"type":"Point"}
}