{
  "type": "Feature",
  "properties": {
    "date:inception_lower": "2020-02-01",
    "date:inception_upper": "2020-02-01",
    "iso:country": "GB",
    "wof:name": "NG24 4FN",
    "wof:placetype": "postalcode"
  },
  "geometry": {"coordinates":[-0.81469,53.063317],"type":"Point"}
}
