{
  "type": "Feature",
  "properties": {
    "iso:country":"GB",
    "wof:name":"W1G 7DY",
    "wof:placetype":"postalcode"
},
  "geometry": {"coordinates":[-0.14593773546167,51.52020484554657],"type":"Point"}
}