{
  "type": "Feature",
  "properties": {
    "iso:country": "GB",
    "wof:name": "M25 9LJ",
    "wof:placetype": "postalcode"
  },
  "geometry": {"coordinates":[-2.286433,53.526694],"type":"Point"}
}
