{
  "type": "Feature",
  "properties": {
    "date:inception_lower": "1980-01-01",
    "date:inception_upper": "1980-01-01",
    "iso:country": "GB",
    "wof:name": "SE3 7RG",
    "wof:placetype": "postalcode"
  },
  "geometry": {"coordinates":[0.009758,51.480051],"type":"Point"}
}
