{
  "type": "Feature",
  "properties": {
    "iso:country":"GB",
    "wof:name":"SE3 7RG",
    "wof:placetype":"postalcode"
},
  "geometry": {"coordinates":[0.00975751855885,51.48005084505496],"type":"Point"}
}