{
  "type": "Feature",
  "properties": {
    "iso:country":"GB",
    "wof:name":"CM7 5JQ",
    "wof:placetype":"postalcode"
},
  "geometry": {"coordinates":[0.53116057185215,51.92918930549438],"type":"Point"}
}