{
  "type": "Feature",
  "properties": {
    "iso:country": "GB",
    "wof:name": "CM7 5JQ",
    "wof:placetype": "postalcode"
  },
  "geometry": {"coordinates":[0.531161,51.929189],"type":"Point"}
}
