{
  "type": "Feature",
  "properties": {
    "date:inception_lower": "1995-07-01",
    "date:inception_upper": "1995-07-01",
    "iso:country": "GB",
    "wof:name": "RG17 7RZ",
    "wof:placetype": "postalcode"
  },
  "geometry": {"coordinates":[-1.552443,51.477381],"type":"Point"}
}
