{
  "type": "Feature",
  "properties": {
    "iso:country": "GB",
    "wof:name": "S40 1DU",
    "wof:placetype": "postalcode"
  },
  "geometry": {"coordinates":[-1.449211,53.23486],"type":"Point"}
}
