{
  "type": "Feature",
  "properties": {
    "date:inception_lower": "1980-01-01",
    "date:inception_upper": "1980-01-01",
    "iso:country": "GB",
    "wof:name": "S40 1DU",
    "wof:placetype": "postalcode"
  },
  "geometry": {"coordinates":[-1.449407,53.234682],"type":"Point"}
}
