{
  "type": "Feature",
  "properties": {
    "iso:country":"GB",
    "wof:name":"GU29 0HH",
    "wof:placetype":"postalcode"
},
  "geometry": {"coordinates":[-0.75018250099164,50.95157448581122],"type":"Point"}
}