{
  "type": "Feature",
  "properties": {
    "iso:country": "GB",
    "wof:name": "TD12 4LG",
    "wof:placetype": "postalcode"
  },
  "geometry": {"coordinates":[-2.261208,55.647664],"type":"Point"}
}
