{
  "type": "Feature",
  "properties": {
    "date:inception_lower":"1980-01-01",
    "date:inception_upper":"1980-01-31",
    "iso:country":"GB",
    "wof:name":"TD12 4LG",
    "wof:placetype":"postalcode"
},
  "geometry": {"coordinates":[-2.261208,55.647664],"type":"Point"}
}