{
  "type": "Feature",
  "properties": {
    "iso:country":"GB",
    "wof:name":"TD12 4LG",
    "wof:placetype":"postalcode"
},
  "geometry": {"coordinates":[-2.26120791663303,55.64766432566201],"type":"Point"}
}