{
  "type": "Feature",
  "properties": {
    "iso:country":"GB",
    "wof:name":"UB6 9DG",
    "wof:placetype":"postalcode"
},
  "geometry": {"coordinates":[-0.36145020412806,51.52077849170124],"type":"Point"}
}