{
  "type": "Feature",
  "properties": {
    "date:inception_lower": "1996-06-01",
    "date:inception_upper": "1996-06-01",
    "iso:country": "GB",
    "wof:name": "AB34 5AZ",
    "wof:placetype": "postalcode"
  },
  "geometry": {"coordinates":[-2.675377,57.085947],"type":"Point"}
}
