{
  "type": "Feature",
  "properties": {
    "iso:country": "GB",
    "wof:name": "SA33 5RH",
    "wof:placetype": "postalcode"
  },
  "geometry": {"coordinates":[-4.410642,51.894903],"type":"Point"}
}
