{
  "type": "Feature",
  "properties": {
    "iso:country":"GB",
    "wof:name":"SA33 5RH",
    "wof:placetype":"postalcode"
},
  "geometry": {"coordinates":[-4.41061809297095,51.89489351316533],"type":"Point"}
}