{
  "type": "Feature",
  "properties": {
    "date:inception_lower": "1984-10-01",
    "date:inception_upper": "1984-10-01",
    "iso:country": "GB",
    "wof:name": "EX4 9AW",
    "wof:placetype": "postalcode"
  },
  "geometry": {"coordinates":[-3.504541,50.740158],"type":"Point"}
}
