{
  "type": "Feature",
  "properties": {
    "iso:country": "GB",
    "wof:name": "EX4 9AW",
    "wof:placetype": "postalcode"
  },
  "geometry": {"coordinates":[-3.504541,50.740158],"type":"Point"}
}
