{
  "type": "Feature",
  "properties": {
    "iso:country":"GB",
    "wof:name":"EX4 9AW",
    "wof:placetype":"postalcode"
},
  "geometry": {"coordinates":[-3.50454136653846,50.74015793647404],"type":"Point"}
}