{
  "type": "Feature",
  "properties": {
    "date:inception_lower": "1980-01-01",
    "date:inception_upper": "1980-01-01",
    "iso:country": "GB",
    "wof:name": "SY16 3JL",
    "wof:placetype": "postalcode"
  },
  "geometry": {"coordinates":[-3.36618,52.537028],"type":"Point"}
}
