{
  "type": "Feature",
  "properties": {
    "iso:country": "GB",
    "wof:name": "SY16 3JL",
    "wof:placetype": "postalcode"
  },
  "geometry": {"coordinates":[-3.36618,52.537028],"type":"Point"}
}
