{
  "type": "Feature",
  "properties": {
    "iso:country":"GB",
    "wof:name":"SY16 3JL",
    "wof:placetype":"postalcode"
},
  "geometry": {"coordinates":[-3.36618049928104,52.53702758216468],"type":"Point"}
}