{
  "type": "Feature",
  "properties": {
    "iso:country":"GB",
    "wof:name":"RH12 2ES",
    "wof:placetype":"postalcode"
},
  "geometry": {"coordinates":[-0.32081005627244,51.06648109503774],"type":"Point"}
}