{
  "type": "Feature",
  "properties": {
    "iso:country": "GB",
    "wof:name": "TS12 3JH",
    "wof:placetype": "postalcode"
  },
  "geometry": {"coordinates":[-0.936707,54.520948],"type":"Point"}
}
