{
  "type": "Feature",
  "properties": {
    "iso:country":"GB",
    "wof:name":"TS12 3JH",
    "wof:placetype":"postalcode"
},
  "geometry": {"coordinates":[-0.9366901275088,54.52093439012938],"type":"Point"}
}