{
  "type": "Feature",
  "properties": {
    "iso:country":"GB",
    "wof:name":"LE67 8NY",
    "wof:placetype":"postalcode"
},
  "geometry": {"coordinates":[-1.37282120009376,52.75524385296024],"type":"Point"}
}