{
  "type": "Feature",
  "properties": {
    "iso:country":"GB",
    "wof:name":"DH2 2AZ",
    "wof:placetype":"postalcode"
},
  "geometry": {"coordinates":[-1.5817306726155,54.85529768063695],"type":"Point"}
}