{
  "type": "Feature",
  "properties": {
    "iso:country":"GB",
    "wof:name":"CA8 1AL",
    "wof:placetype":"postalcode"
},
  "geometry": {"coordinates":[-2.74140022621806,54.94250369990917],"type":"Point"}
}