{
  "type": "Feature",
  "properties": {
    "iso:country":"GB",
    "wof:name":"S66 8PL",
    "wof:placetype":"postalcode"
},
  "geometry": {"coordinates":[-1.21950410599229,53.41600743955339],"type":"Point"}
}