{
  "type": "Feature",
  "properties": {
    "iso:country":"GB",
    "wof:name":"CM12 0XH",
    "wof:placetype":"postalcode"
},
  "geometry": {"coordinates":[0.40694566046445,51.63936526640754],"type":"Point"}
}