{
  "type": "Feature",
  "properties": {
    "iso:country":"GB",
    "wof:name":"NG7 4HA",
    "wof:placetype":"postalcode"
},
  "geometry": {"coordinates":[-1.16041239409269,52.95879609760274],"type":"Point"}
}