{
  "type": "Feature",
  "properties": {
    "iso:country": "GB",
    "wof:name": "SA12 6JU",
    "wof:placetype": "postalcode"
  },
  "geometry": {"coordinates":[-3.81244,51.593825],"type":"Point"}
}
