{
  "type": "Feature",
  "properties": {
    "iso:country":"GB",
    "wof:name":"SA12 6JU",
    "wof:placetype":"postalcode"
},
  "geometry": {"coordinates":[-3.81242259924541,51.59382070939385],"type":"Point"}
}