{
  "type": "Feature",
  "properties": {
    "iso:country":"GB",
    "wof:name":"TN4 8TG",
    "wof:placetype":"postalcode"
},
  "geometry": {"coordinates":[0.23305636884241,51.13772931121719],"type":"Point"}
}