{
  "type": "Feature",
  "properties": {
    "date:inception_lower": "2016-08-01",
    "date:inception_upper": "2016-08-01",
    "iso:country": "GB",
    "wof:name": "CT17 0FQ",
    "wof:placetype": "postalcode"
  },
  "geometry": {"coordinates":[1.29731,51.133785],"type":"Point"}
}
