{
  "type": "Feature",
  "properties": {
    "date:inception_lower": "1980-01-01",
    "date:inception_upper": "1980-01-01",
    "iso:country": "GB",
    "wof:name": "MK2 2PG",
    "wof:placetype": "postalcode"
  },
  "geometry": {"coordinates":[-0.72458,51.999226],"type":"Point"}
}
