{
  "type": "Feature",
  "properties": {
    "iso:country":"GB",
    "wof:name":"PR8 2QE",
    "wof:placetype":"postalcode"
},
  "geometry": {"coordinates":[-3.04977645877401,53.60717280682437],"type":"Point"}
}