{
  "type": "Feature",
  "properties": {
    "date:inception_lower": "1980-01-01",
    "date:inception_upper": "1980-01-01",
    "iso:country": "GB",
    "wof:name": "NN5 6HJ",
    "wof:placetype": "postalcode"
  },
  "geometry": {"coordinates":[-0.945983,52.240194],"type":"Point"}
}
