{
  "type": "Feature",
  "properties": {
    "iso:country":"GB",
    "wof:name":"TN13 1AH",
    "wof:placetype":"postalcode"
},
  "geometry": {"coordinates":[0.19246571953612,51.26993503412443],"type":"Point"}
}