{
  "type": "Feature",
  "properties": {
    "date:inception_lower": "1999-06-01",
    "date:inception_upper": "1999-06-01",
    "iso:country": "GB",
    "wof:name": "BD14 6NG",
    "wof:placetype": "postalcode"
  },
  "geometry": {"coordinates":[-1.818337,53.778354],"type":"Point"}
}
