{
  "type": "Feature",
  "properties": {
    "iso:country":"GB",
    "wof:name":"BD14 6NG",
    "wof:placetype":"postalcode"
},
  "geometry": {"coordinates":[-1.81833698380526,53.77835350597492],"type":"Point"}
}