{
  "type": "Feature",
  "properties": {
    "iso:country": "GB",
    "wof:name": "WS5 4SJ",
    "wof:placetype": "postalcode"
  },
  "geometry": {"coordinates":[-1.963777,52.554249],"type":"Point"}
}
