{
  "type": "Feature",
  "properties": {
    "iso:country": "GB",
    "wof:name": "CO9 4SW",
    "wof:placetype": "postalcode"
  },
  "geometry": {"coordinates":[0.527664,52.038482],"type":"Point"}
}
