{
  "type": "Feature",
  "properties": {
    "iso:country":"GB",
    "wof:name":"CO9 4SW",
    "wof:placetype":"postalcode"
},
  "geometry": {"coordinates":[0.52766406395751,52.03848233906732],"type":"Point"}
}