{
  "type": "Feature",
  "properties": {
    "date:inception_lower":"1980-01-01",
    "date:inception_upper":"1980-01-31",
    "iso:country":"GB",
    "wof:name":"CO9 4SW",
    "wof:placetype":"postalcode"
},
  "geometry": {"coordinates":[0.527664,52.038482],"type":"Point"}
}