{
  "type": "Feature",
  "properties": {
    "iso:country": "GB",
    "wof:name": "OX4 4DH",
    "wof:placetype": "postalcode"
  },
  "geometry": {"coordinates":[-1.232273,51.73536],"type":"Point"}
}
