{
  "type": "Feature",
  "properties": {
    "iso:country":"GB",
    "wof:name":"DN34 5UQ",
    "wof:placetype":"postalcode"
},
  "geometry": {"coordinates":[-0.13765453804088,53.55289052112722],"type":"Point"}
}