{
  "type": "Feature",
  "properties": {
    "iso:country":"GB",
    "wof:name":"LS11 5AL",
    "wof:placetype":"postalcode"
},
  "geometry": {"coordinates":[-1.55224323869609,53.76591726373983],"type":"Point"}
}