{
  "type": "Feature",
  "properties": {
    "iso:country": "GB",
    "wof:name": "LS11 5AL",
    "wof:placetype": "postalcode"
  },
  "geometry": {"coordinates":[-1.552243,53.765917],"type":"Point"}
}
