{
  "type": "Feature",
  "properties": {
    "date:inception_lower":"1997-12-01",
    "date:inception_upper":"1997-12-31",
    "iso:country":"GB",
    "wof:name":"LS11 5AL",
    "wof:placetype":"postalcode"
},
  "geometry": {"coordinates":[-1.552243,53.765917],"type":"Point"}
}