{
  "type": "Feature",
  "properties": {
    "iso:country": "GB",
    "wof:name": "RG22 4UZ",
    "wof:placetype": "postalcode"
  },
  "geometry": {"coordinates":[-1.128416,51.232008],"type":"Point"}
}
