{
  "type": "Feature",
  "properties": {
    "iso:country":"GB",
    "wof:name":"WN2 2NR",
    "wof:placetype":"postalcode"
},
  "geometry": {"coordinates":[-2.59952211652984,53.5452001250593],"type":"Point"}
}