{
  "type": "Feature",
  "properties": {
    "iso:country": "GB",
    "wof:name": "E14 9XQ",
    "wof:placetype": "postalcode"
  },
  "geometry": {"coordinates":[-0.021064,51.501294],"type":"Point"}
}
