{
  "type": "Feature",
  "properties": {
    "date:inception_lower":"1990-02-01",
    "date:inception_upper":"1990-02-28",
    "iso:country":"GB",
    "wof:name":"E14 9XQ",
    "wof:placetype":"postalcode"
},
  "geometry": {"coordinates":[-0.021064,51.501294],"type":"Point"}
}