{
  "type": "Feature",
  "properties": {
    "date:inception_lower": "1980-01-01",
    "date:inception_upper": "1980-01-01",
    "iso:country": "GB",
    "wof:name": "KY7 5LP",
    "wof:placetype": "postalcode"
  },
  "geometry": {"coordinates":[-3.169694,56.196098],"type":"Point"}
}
