{
  "type": "Feature",
  "properties": {
    "iso:country": "GB",
    "wof:name": "OL11 1JA",
    "wof:placetype": "postalcode"
  },
  "geometry": {"coordinates":[-2.150215,53.606739],"type":"Point"}
}
