{
  "type": "Feature",
  "properties": {
    "date:inception_lower": "2020-04-01",
    "date:inception_upper": "2020-04-01",
    "iso:country": "GB",
    "wof:name": "OL11 1JA",
    "wof:placetype": "postalcode"
  },
  "geometry": {"coordinates":[-2.150215,53.606739],"type":"Point"}
}
