{
  "type": "Feature",
  "properties": {
    "iso:country":"GB",
    "wof:name":"TS17 8QD",
    "wof:placetype":"postalcode"
},
  "geometry": {"coordinates":[-1.30740450404061,54.54509478574761],"type":"Point"}
}