{
  "type": "Feature",
  "properties": {
    "date:inception_lower": "1980-01-01",
    "date:inception_upper": "1980-01-01",
    "iso:country": "GB",
    "wof:name": "TS17 8QD",
    "wof:placetype": "postalcode"
  },
  "geometry": {"coordinates":[-1.307404,54.545095],"type":"Point"}
}
