{
  "type": "Feature",
  "properties": {
    "iso:country":"GB",
    "wof:name":"BS9 1RG",
    "wof:placetype":"postalcode"
},
  "geometry": {"coordinates":[-2.6396577359467,51.47722491994327],"type":"Point"}
}