{
  "type": "Feature",
  "properties": {
    "date:inception_lower": "1997-06-01",
    "date:inception_upper": "1997-06-01",
    "iso:country": "GB",
    "wof:name": "ME12 1HB",
    "wof:placetype": "postalcode"
  },
  "geometry": {"coordinates":[0.751514,51.436794],"type":"Point"}
}
