{
  "type": "Feature",
  "properties": {
    "iso:country":"GB",
    "wof:name":"CW7 3DF",
    "wof:placetype":"postalcode"
},
  "geometry": {"coordinates":[-2.51074021143439,53.18983933103829],"type":"Point"}
}