{
  "type": "Feature",
  "properties": {
    "iso:country": "GB",
    "wof:name": "CW7 3DF",
    "wof:placetype": "postalcode"
  },
  "geometry": {"coordinates":[-2.51074,53.189839],"type":"Point"}
}
