{
  "type": "Feature",
  "properties": {
    "iso:country":"GB",
    "wof:name":"CM15 8PX",
    "wof:placetype":"postalcode"
},
  "geometry": {"coordinates":[0.33006468600229,51.63701360737294],"type":"Point"}
}