{
  "type": "Feature",
  "properties": {
    "iso:country": "GB",
    "wof:name": "DL13 4PB",
    "wof:placetype": "postalcode"
  },
  "geometry": {"coordinates":[-1.820745,54.729508],"type":"Point"}
}
