{
  "type": "Feature",
  "properties": {
    "iso:country": "GB",
    "wof:name": "HP4 2FN",
    "wof:placetype": "postalcode"
  },
  "geometry": {"coordinates":[-0.563222,51.762482],"type":"Point"}
}
