{
  "type": "Feature",
  "properties": {
    "iso:country":"GB",
    "wof:name":"KY15 5LJ",
    "wof:placetype":"postalcode"
},
  "geometry": {"coordinates":[-2.89571206417415,56.26910408810829],"type":"Point"}
}