{
  "type": "Feature",
  "properties": {
    "date:inception_lower": "2013-09-01",
    "date:inception_upper": "2013-09-01",
    "iso:country": "GB",
    "wof:name": "CA6 4DA",
    "wof:placetype": "postalcode"
  },
  "geometry": {"coordinates":[-2.96779,54.934972],"type":"Point"}
}
