{
  "type": "Feature",
  "properties": {
    "iso:country":"GB",
    "wof:name":"CH7 6BL",
    "wof:placetype":"postalcode"
},
  "geometry": {"coordinates":[-3.13408018023841,53.20674997690252],"type":"Point"}
}