{
  "type": "Feature",
  "properties": {
    "date:inception_lower":"1980-01-01",
    "date:inception_upper":"1980-01-31",
    "iso:country":"GB",
    "wof:name":"CH7 6BL",
    "wof:placetype":"postalcode"
},
  "geometry": {"coordinates":[-3.13408,53.20675],"type":"Point"}
}