{
  "type": "Feature",
  "properties": {
    "iso:country":"GB",
    "wof:name":"B93 9EU",
    "wof:placetype":"postalcode"
},
  "geometry": {"coordinates":[-1.75208923689771,52.38839114315167],"type":"Point"}
}