{
  "type": "Feature",
  "properties": {
    "iso:country": "GB",
    "wof:name": "TQ5 0PH",
    "wof:placetype": "postalcode"
  },
  "geometry": {"coordinates":[-3.566088,50.396783],"type":"Point"}
}
