{
  "type": "Feature",
  "properties": {
    "date:inception_lower":"1980-01-01",
    "date:inception_upper":"1980-01-31",
    "iso:country":"GB",
    "wof:name":"TQ5 0PH",
    "wof:placetype":"postalcode"
},
  "geometry": {"coordinates":[-3.566088,50.396783],"type":"Point"}
}