{
  "type": "Feature",
  "properties": {
    "iso:country":"GB",
    "wof:name":"CA14 4SG",
    "wof:placetype":"postalcode"
},
  "geometry": {"coordinates":[-3.44536757524095,54.55724923839307],"type":"Point"}
}