{
  "type": "Feature",
  "properties": {
    "iso:country":"GB",
    "wof:name":"PL9 9GD",
    "wof:placetype":"postalcode"
},
  "geometry": {"coordinates":[-4.09531359452867,50.35224840230402],"type":"Point"}
}