{
  "type": "Feature",
  "properties": {
    "iso:country":"GB",
    "wof:name":"BN10 8BW",
    "wof:placetype":"postalcode"
},
  "geometry": {"coordinates":[0.00855951423777,50.80283028998694],"type":"Point"}
}