{
  "type": "Feature",
  "properties": {
    "iso:country":"GB",
    "wof:name":"SK2 6DZ",
    "wof:placetype":"postalcode"
},
  "geometry": {"coordinates":[-2.1444398312023,53.3976328699172],"type":"Point"}
}