{
  "type": "Feature",
  "properties": {
    "date:inception_lower":"1980-01-01",
    "date:inception_upper":"1980-01-31",
    "iso:country":"GB",
    "wof:name":"LU3 2JX",
    "wof:placetype":"postalcode"
},
  "geometry": {"coordinates":[-0.443158,51.908768],"type":"Point"}
}