{
  "type": "Feature",
  "properties": {
    "iso:country":"GB",
    "wof:name":"ST7 2TS",
    "wof:placetype":"postalcode"
},
  "geometry": {"coordinates":[-2.33911935116702,53.1022068967839],"type":"Point"}
}