{
  "type": "Feature",
  "properties": {
    "iso:country": "GB",
    "wof:name": "ST7 2TS",
    "wof:placetype": "postalcode"
  },
  "geometry": {"coordinates":[-2.339119,53.102207],"type":"Point"}
}
