{
  "type": "Feature",
  "properties": {
    "iso:country":"GB",
    "wof:name":"M24 5NJ",
    "wof:placetype":"postalcode"
},
  "geometry": {"coordinates":[-2.20415804320784,53.56035343670781],"type":"Point"}
}