{
  "type": "Feature",
  "properties": {
    "date:inception_lower":"1994-05-01",
    "date:inception_upper":"1994-05-31",
    "iso:country":"GB",
    "wof:name":"M24 5NJ",
    "wof:placetype":"postalcode"
},
  "geometry": {"coordinates":[-2.204158,53.560353],"type":"Point"}
}