{
  "type": "Feature",
  "properties": {
    "iso:country": "GB",
    "wof:name": "BN44 3DL",
    "wof:placetype": "postalcode"
  },
  "geometry": {"coordinates":[-0.375088,50.916825],"type":"Point"}
}
