{
  "type": "Feature",
  "properties": {
    "iso:country": "GB",
    "wof:name": "OL2 6QJ",
    "wof:placetype": "postalcode"
  },
  "geometry": {"coordinates":[-2.122322,53.566469],"type":"Point"}
}
