{
  "type": "Feature",
  "properties": {
    "date:inception_lower": "1980-01-01",
    "date:inception_upper": "1980-01-01",
    "iso:country": "GB",
    "wof:name": "OL2 6QJ",
    "wof:placetype": "postalcode"
  },
  "geometry": {"coordinates":[-2.122322,53.566469],"type":"Point"}
}
