{
  "type": "Feature",
  "properties": {
    "iso:country":"GB",
    "wof:name":"OL2 6QJ",
    "wof:placetype":"postalcode"
},
  "geometry": {"coordinates":[-2.12232204710135,53.56646948850876],"type":"Point"}
}