{
  "type": "Feature",
  "properties": {
    "date:inception_lower": "1980-01-01",
    "date:inception_upper": "1980-01-01",
    "iso:country": "GB",
    "wof:name": "ST1 6DT",
    "wof:placetype": "postalcode"
  },
  "geometry": {"coordinates":[-2.166674,53.041241],"type":"Point"}
}
