{
  "type": "Feature",
  "properties": {
    "iso:country":"GB",
    "wof:name":"ST1 6DT",
    "wof:placetype":"postalcode"
},
  "geometry": {"coordinates":[-2.16667454170203,53.04124122845831],"type":"Point"}
}