{
  "type": "Feature",
  "properties": {
    "date:inception_lower": "1982-08-01",
    "date:inception_upper": "1982-08-01",
    "iso:country": "GB",
    "wof:name": "ML8 5UR",
    "wof:placetype": "postalcode"
  },
  "geometry": {"coordinates":[-3.852418,55.73406],"type":"Point"}
}
