{
  "type": "Feature",
  "properties": {
    "iso:country":"GB",
    "wof:name":"CH41 9EJ",
    "wof:placetype":"postalcode"
},
  "geometry": {"coordinates":[-3.02130804614441,53.38166474973582],"type":"Point"}
}