{
  "type": "Feature",
  "properties": {
    "iso:country":"GB",
    "wof:name":"CO16 0HR",
    "wof:placetype":"postalcode"
},
  "geometry": {"coordinates":[1.18828182282946,51.85031755763021],"type":"Point"}
}