{
  "type": "Feature",
  "properties": {
    "iso:country":"GB",
    "wof:name":"SE7 8AZ",
    "wof:placetype":"postalcode"
},
  "geometry": {"coordinates":[0.03749347874611,51.48517462865757],"type":"Point"}
}