{
  "type": "Feature",
  "properties": {
    "iso:country":"GB",
    "wof:name":"DE12 6AB",
    "wof:placetype":"postalcode"
},
  "geometry": {"coordinates":[-1.53273793854435,52.73466676765926],"type":"Point"}
}