{
  "type": "Feature",
  "properties": {
    "iso:country": "GB",
    "wof:name": "DE12 6AB",
    "wof:placetype": "postalcode"
  },
  "geometry": {"coordinates":[-1.595447,52.749505],"type":"Point"}
}
