{
  "type": "Feature",
  "properties": {
    "iso:country":"GB",
    "wof:name":"ML1 5ND",
    "wof:placetype":"postalcode"
},
  "geometry": {"coordinates":[-3.90811985360172,55.82906027927618],"type":"Point"}
}