{
  "type": "Feature",
  "properties": {
    "iso:country": "GB",
    "wof:name": "ML1 5ND",
    "wof:placetype": "postalcode"
  },
  "geometry": {"coordinates":[-3.90812,55.82906],"type":"Point"}
}
