{
  "type": "Feature",
  "properties": {
    "iso:country":"GB",
    "wof:name":"SE6 1XA",
    "wof:placetype":"postalcode"
},
  "geometry": {"coordinates":[-0.00090689266964,51.43838091973683],"type":"Point"}
}