{
  "type": "Feature",
  "properties": {
    "iso:country": "GB",
    "wof:name": "PL22 0JT",
    "wof:placetype": "postalcode"
  },
  "geometry": {"coordinates":[-4.674721,50.409431],"type":"Point"}
}
