{
  "type": "Feature",
  "properties": {
    "iso:country":"GB",
    "wof:name":"CT6 8NY",
    "wof:placetype":"postalcode"
},
  "geometry": {"coordinates":[1.10893314340897,51.36417751753616],"type":"Point"}
}