{
  "type": "Feature",
  "properties": {
    "iso:country":"GB",
    "wof:name":"LE3 3GA",
    "wof:placetype":"postalcode"
},
  "geometry": {"coordinates":[-1.20833536078223,52.62442889765907],"type":"Point"}
}