{
  "type": "Feature",
  "properties": {
    "iso:country": "GB",
    "wof:name": "DD2 2PW",
    "wof:placetype": "postalcode"
  },
  "geometry": {"coordinates":[-3.002218,56.467154],"type":"Point"}
}
