{
  "type": "Feature",
  "properties": {
    "iso:country":"GB",
    "wof:name":"CW11 1BG",
    "wof:placetype":"postalcode"
},
  "geometry": {"coordinates":[-2.36872952217651,53.15019210033694],"type":"Point"}
}