{
  "type": "Feature",
  "properties": {
    "iso:country": "GB",
    "wof:name": "LA3 2GW",
    "wof:placetype": "postalcode"
  },
  "geometry": {"coordinates":[-2.891443,54.039264],"type":"Point"}
}
