{
  "type": "Feature",
  "properties": {
    "date:inception_lower":"2011-06-01",
    "date:inception_upper":"2011-06-30",
    "iso:country":"GB",
    "wof:name":"LA3 2GW",
    "wof:placetype":"postalcode"
},
  "geometry": {"coordinates":[-2.891443,54.039264],"type":"Point"}
}