{
  "type": "Feature",
  "properties": {
    "date:inception_lower": "1980-01-01",
    "date:inception_upper": "1980-01-01",
    "iso:country": "GB",
    "wof:name": "LE8 0QP",
    "wof:placetype": "postalcode"
  },
  "geometry": {"coordinates":[-1.031925,52.510265],"type":"Point"}
}
