{
  "type": "Feature",
  "properties": {
    "iso:country":"GB",
    "wof:name":"LE8 0QP",
    "wof:placetype":"postalcode"
},
  "geometry": {"coordinates":[-1.03193667146485,52.51024774659173],"type":"Point"}
}