{
  "type": "Feature",
  "properties": {
    "iso:country":"GB",
    "wof:name":"SE19 3XQ",
    "wof:placetype":"postalcode"
},
  "geometry": {"coordinates":[-0.10317852917219,51.41412772647218],"type":"Point"}
}