{
  "type": "Feature",
  "properties": {
    "iso:country":"GB",
    "wof:name":"N13 5JA",
    "wof:placetype":"postalcode"
},
  "geometry": {"coordinates":[-0.10707279631308,51.61375323440608],"type":"Point"}
}