{
  "type": "Feature",
  "properties": {
    "iso:country":"GB",
    "wof:name":"PR1 1JN",
    "wof:placetype":"postalcode"
},
  "geometry": {"coordinates":[-2.70892631661715,53.76283920987535],"type":"Point"}
}