{
  "type": "Feature",
  "properties": {
    "iso:country": "GB",
    "wof:name": "PR1 1JN",
    "wof:placetype": "postalcode"
  },
  "geometry": {"coordinates":[-2.708926,53.762839],"type":"Point"}
}
