{
  "type": "Feature",
  "properties": {
    "date:inception_lower": "1998-06-01",
    "date:inception_upper": "1998-06-01",
    "iso:country": "GB",
    "wof:name": "PR1 1JN",
    "wof:placetype": "postalcode"
  },
  "geometry": {"coordinates":[-2.708926,53.762839],"type":"Point"}
}
