{
  "type": "Feature",
  "properties": {
    "iso:country":"GB",
    "wof:name":"HU6 7XA",
    "wof:placetype":"postalcode"
},
  "geometry": {"coordinates":[-0.36673415371887,53.79050670282493],"type":"Point"}
}