{
  "type": "Feature",
  "properties": {
    "iso:country": "GB",
    "wof:name": "AL8 7RX",
    "wof:placetype": "postalcode"
  },
  "geometry": {"coordinates":[-0.205878,51.809589],"type":"Point"}
}
