{
  "type": "Feature",
  "properties": {
    "date:inception_lower": "1980-01-01",
    "date:inception_upper": "1980-01-01",
    "iso:country": "GB",
    "wof:name": "AL8 7RX",
    "wof:placetype": "postalcode"
  },
  "geometry": {"coordinates":[-0.205839,51.809614],"type":"Point"}
}
