{
  "type": "Feature",
  "properties": {
    "iso:country":"GB",
    "wof:name":"PL8 2JY",
    "wof:placetype":"postalcode"
},
  "geometry": {"coordinates":[-3.99957360051822,50.34939267744473],"type":"Point"}
}