{
  "type": "Feature",
  "properties": {
    "iso:country": "GB",
    "wof:name": "CH66 1JD",
    "wof:placetype": "postalcode"
  },
  "geometry": {"coordinates":[-2.934943,53.287826],"type":"Point"}
}
