{
  "type": "Feature",
  "properties": {
    "iso:country": "GB",
    "wof:name": "GL4 0QP",
    "wof:placetype": "postalcode"
  },
  "geometry": {"coordinates":[-2.257439,51.829931],"type":"Point"}
}
