{
  "type": "Feature",
  "properties": {
    "iso:country":"GB",
    "wof:name":"GL4 0QP",
    "wof:placetype":"postalcode"
},
  "geometry": {"coordinates":[-2.25743947401246,51.82993071222015],"type":"Point"}
}