{
  "type": "Feature",
  "properties": {
    "date:inception_lower": "1980-01-01",
    "date:inception_upper": "1980-01-01",
    "iso:country": "GB",
    "wof:name": "L10 7NW",
    "wof:placetype": "postalcode"
  },
  "geometry": {"coordinates":[-2.919532,53.466907],"type":"Point"}
}
