{
  "type": "Feature",
  "properties": {
    "iso:country":"GB",
    "wof:name":"S42 5QJ",
    "wof:placetype":"postalcode"
},
  "geometry": {"coordinates":[-1.38471578681407,53.18347797852222],"type":"Point"}
}