{
  "type": "Feature",
  "properties": {
    "iso:country": "GB",
    "wof:name": "S42 5QJ",
    "wof:placetype": "postalcode"
  },
  "geometry": {"coordinates":[-1.384716,53.183478],"type":"Point"}
}
