{
  "type": "Feature",
  "properties": {
    "iso:country":"GB",
    "wof:name":"BD4 6LW",
    "wof:placetype":"postalcode"
},
  "geometry": {"coordinates":[-1.72452625952924,53.76452207711298],"type":"Point"}
}