{
  "type": "Feature",
  "properties": {
    "iso:country":"GB",
    "wof:name":"S70 6PS",
    "wof:placetype":"postalcode"
},
  "geometry": {"coordinates":[-1.51017609714033,53.55172435418928],"type":"Point"}
}