{
  "type": "Feature",
  "properties": {
    "iso:country":"GB",
    "wof:name":"CR8 2JJ",
    "wof:placetype":"postalcode"
},
  "geometry": {"coordinates":[-0.12057187601446,51.34484931442926],"type":"Point"}
}