{
  "type": "Feature",
  "properties": {
    "date:inception_lower":"1980-01-01",
    "date:inception_upper":"1980-01-31",
    "iso:country":"GB",
    "wof:name":"SA12 6HE",
    "wof:placetype":"postalcode"
},
  "geometry": {"coordinates":[-3.790375,51.598916],"type":"Point"}
}