{
  "type": "Feature",
  "properties": {
    "date:inception_lower": "1994-05-01",
    "date:inception_upper": "1994-05-01",
    "iso:country": "GB",
    "wof:name": "LE67 3QQ",
    "wof:placetype": "postalcode"
  },
  "geometry": {"coordinates":[-1.373246,52.722506],"type":"Point"}
}
