{
  "type": "Feature",
  "properties": {
    "iso:country": "GB",
    "wof:name": "LE67 3QQ",
    "wof:placetype": "postalcode"
  },
  "geometry": {"coordinates":[-1.373246,52.722506],"type":"Point"}
}
