{
  "type": "Feature",
  "properties": {
    "iso:country": "GB",
    "wof:name": "CH2 1LH",
    "wof:placetype": "postalcode"
  },
  "geometry": {"coordinates":[-2.876315,53.227449],"type":"Point"}
}
