{
  "type": "Feature",
  "properties": {
    "iso:country":"GB",
    "wof:name":"CH2 1LH",
    "wof:placetype":"postalcode"
},
  "geometry": {"coordinates":[-2.87760823677187,53.22553633843145],"type":"Point"}
}