{
  "type": "Feature",
  "properties": {
    "date:inception_lower": "2023-10-01",
    "date:inception_upper": "2023-10-01",
    "iso:country": "GB",
    "wof:name": "ML3 0FL",
    "wof:placetype": "postalcode"
  },
  "geometry": {"coordinates":[-4.058794,55.782086],"type":"Point"}
}
