{
  "type": "Feature",
  "properties": {
    "date:inception_lower":"1980-01-01",
    "date:inception_upper":"1980-01-31",
    "iso:country":"GB",
    "wof:name":"NW7 1PU",
    "wof:placetype":"postalcode"
},
  "geometry": {"coordinates":[-0.202128,51.60982],"type":"Point"}
}