{
  "type": "Feature",
  "properties": {
    "iso:country":"GB",
    "wof:name":"NW7 1PU",
    "wof:placetype":"postalcode"
},
  "geometry": {"coordinates":[-0.20210856199672,51.60985188355332],"type":"Point"}
}