{
  "type": "Feature",
  "properties": {
    "iso:country":"GB",
    "wof:name":"S43 4PF",
    "wof:placetype":"postalcode"
},
  "geometry": {"coordinates":[-1.26338112268426,53.2780644918106],"type":"Point"}
}