{
  "type": "Feature",
  "properties": {
    "iso:country": "GB",
    "wof:name": "BH8 0HQ",
    "wof:placetype": "postalcode"
  },
  "geometry": {"coordinates":[-1.84442,50.75498],"type":"Point"}
}
