{
  "type": "Feature",
  "properties": {
    "iso:country":"GB",
    "wof:name":"CB9 9EX",
    "wof:placetype":"postalcode"
},
  "geometry": {"coordinates":[0.4263137907922,52.0884272374599],"type":"Point"}
}