{
  "type": "Feature",
  "properties": {
    "iso:country":"GB",
    "wof:name":"BN18 9EY",
    "wof:placetype":"postalcode"
},
  "geometry": {"coordinates":[-0.55608325459474,50.85302150441488],"type":"Point"}
}