{
  "type": "Feature",
  "properties": {
    "iso:country":"GB",
    "wof:name":"NE29 6TH",
    "wof:placetype":"postalcode"
},
  "geometry": {"coordinates":[-1.45085981123697,55.00413967012326],"type":"Point"}
}