{
  "type": "Feature",
  "properties": {
    "iso:country":"GB",
    "wof:name":"ST8 6RD",
    "wof:placetype":"postalcode"
},
  "geometry": {"coordinates":[-2.17435916336799,53.12697672625856],"type":"Point"}
}