{
  "type": "Feature",
  "properties": {
    "iso:country":"GB",
    "wof:name":"BS22 6EL",
    "wof:placetype":"postalcode"
},
  "geometry": {"coordinates":[-2.93192599172971,51.35945975937629],"type":"Point"}
}