{
  "type": "Feature",
  "properties": {
    "iso:country":"GB",
    "wof:name":"TF1 3DG",
    "wof:placetype":"postalcode"
},
  "geometry": {"coordinates":[-2.51151345542641,52.70646114807488],"type":"Point"}
}