{
  "type": "Feature",
  "properties": {
    "iso:country":"GB",
    "wof:name":"BD8 7LN",
    "wof:placetype":"postalcode"
},
  "geometry": {"coordinates":[-1.7686484482616,53.80715542416493],"type":"Point"}
}