{
  "type": "Feature",
  "properties": {
    "iso:country":"GB",
    "wof:name":"PE2 5NA",
    "wof:placetype":"postalcode"
},
  "geometry": {"coordinates":[-0.27236749513116,52.55105611208398],"type":"Point"}
}