{
  "type": "Feature",
  "properties": {
    "iso:country":"GB",
    "wof:name":"PR6 9JP",
    "wof:placetype":"postalcode"
},
  "geometry": {"coordinates":[-2.60595275268769,53.62449055432587],"type":"Point"}
}