{
  "type": "Feature",
  "properties": {
    "date:inception_lower":"1980-01-01",
    "date:inception_upper":"1980-01-31",
    "iso:country":"GB",
    "wof:name":"PR6 9JP",
    "wof:placetype":"postalcode"
},
  "geometry": {"coordinates":[-2.605953,53.624491],"type":"Point"}
}