{
  "type": "Feature",
  "properties": {
    "iso:country":"GB",
    "wof:name":"IP31 3RX",
    "wof:placetype":"postalcode"
},
  "geometry": {"coordinates":[0.81916294794125,52.25145967971802],"type":"Point"}
}