{
  "type": "Feature",
  "properties": {
    "iso:country": "GB",
    "wof:name": "IP31 3RX",
    "wof:placetype": "postalcode"
  },
  "geometry": {"coordinates":[0.819163,52.25146],"type":"Point"}
}
