{
  "type": "Feature",
  "properties": {
    "iso:country":"GB",
    "wof:name":"WS6 7LL",
    "wof:placetype":"postalcode"
},
  "geometry": {"coordinates":[-2.03926504149383,52.65547297642199],"type":"Point"}
}