{
  "type": "Feature",
  "properties": {
    "iso:country":"GB",
    "wof:name":"LE19 3FL",
    "wof:placetype":"postalcode"
},
  "geometry": {"coordinates":[-1.20918805935329,52.57462999859264],"type":"Point"}
}