{
  "type": "Feature",
  "properties": {
    "iso:country":"GB",
    "wof:name":"SO43 7HF",
    "wof:placetype":"postalcode"
},
  "geometry": {"coordinates":[-1.60881241604122,50.92137448314845],"type":"Point"}
}