{
  "type": "Feature",
  "properties": {
    "iso:country": "GB",
    "wof:name": "SO43 7HF",
    "wof:placetype": "postalcode"
  },
  "geometry": {"coordinates":[-1.608812,50.921374],"type":"Point"}
}
