{
  "type": "Feature",
  "properties": {
    "iso:country": "GB",
    "wof:name": "SY14 8EW",
    "wof:placetype": "postalcode"
  },
  "geometry": {"coordinates":[-2.762448,53.024618],"type":"Point"}
}
