{
  "type": "Feature",
  "properties": {
    "date:inception_lower":"1980-01-01",
    "date:inception_upper":"1980-01-31",
    "iso:country":"GB",
    "wof:name":"CM0 8TF",
    "wof:placetype":"postalcode"
},
  "geometry": {"coordinates":[0.805185,51.635801],"type":"Point"}
}