{
  "type": "Feature",
  "properties": {
    "iso:country":"GB",
    "wof:name":"DG8 0BL",
    "wof:placetype":"postalcode"
},
  "geometry": {"coordinates":[-4.60507008874773,54.9075257082139],"type":"Point"}
}