{
  "type": "Feature",
  "properties": {
    "iso:country":"GB",
    "wof:name":"B95 5NA",
    "wof:placetype":"postalcode"
},
  "geometry": {"coordinates":[-1.8226232357124,52.30275159843384],"type":"Point"}
}