{
  "type": "Feature",
  "properties": {
    "date:inception_lower": "1980-01-01",
    "date:inception_upper": "1980-01-01",
    "iso:country": "GB",
    "wof:name": "BD15 7RL",
    "wof:placetype": "postalcode"
  },
  "geometry": {"coordinates":[-1.815855,53.801188],"type":"Point"}
}
