{
  "type": "Feature",
  "properties": {
    "date:inception_lower": "1998-06-01",
    "date:inception_upper": "1998-06-01",
    "iso:country": "GB",
    "wof:name": "YO26 4XU",
    "wof:placetype": "postalcode"
  },
  "geometry": {"coordinates":[-1.107359,53.962807],"type":"Point"}
}
