{
  "type": "Feature",
  "properties": {
    "iso:country":"GB",
    "wof:name":"YO26 4XU",
    "wof:placetype":"postalcode"
},
  "geometry": {"coordinates":[-1.10735897257597,53.96280714279322],"type":"Point"}
}