{
  "type": "Feature",
  "properties": {
    "iso:country":"GB",
    "wof:name":"SN15 3PA",
    "wof:placetype":"postalcode"
},
  "geometry": {"coordinates":[-2.1112454164843,51.46129441404167],"type":"Point"}
}