{
  "type": "Feature",
  "properties": {
    "iso:country": "GB",
    "wof:name": "KY11 2NP",
    "wof:placetype": "postalcode"
  },
  "geometry": {"coordinates":[-3.411951,56.04093],"type":"Point"}
}
