{
  "type": "Feature",
  "properties": {
    "iso:country":"GB",
    "wof:name":"IV4 7HA",
    "wof:placetype":"postalcode"
},
  "geometry": {"coordinates":[-4.49282247051928,57.43840705332133],"type":"Point"}
}