{
  "type": "Feature",
  "properties": {
    "date:inception_lower": "2006-04-01",
    "date:inception_upper": "2006-04-01",
    "iso:country": "GB",
    "wof:name": "IV4 7HA",
    "wof:placetype": "postalcode"
  },
  "geometry": {"coordinates":[-4.492822,57.438407],"type":"Point"}
}
