{
  "type": "Feature",
  "properties": {
    "iso:country": "GB",
    "wof:name": "EX23 9LX",
    "wof:placetype": "postalcode"
  },
  "geometry": {"coordinates":[-4.467153,50.835365],"type":"Point"}
}
