{
  "type": "Feature",
  "properties": {
    "iso:country":"GB",
    "wof:name":"EX23 9LX",
    "wof:placetype":"postalcode"
},
  "geometry": {"coordinates":[-4.46715351134597,50.83536529076412],"type":"Point"}
}