{
  "type": "Feature",
  "properties": {
    "iso:country":"GB",
    "wof:name":"UB3 5BW",
    "wof:placetype":"postalcode"
},
  "geometry": {"coordinates":[-0.44150882616126,51.48435393366352],"type":"Point"}
}