{
  "type": "Feature",
  "properties": {
    "date:inception_lower": "2023-12-01",
    "date:inception_upper": "2023-12-01",
    "iso:country": "GB",
    "wof:name": "SY16 4BD",
    "wof:placetype": "postalcode"
  },
  "geometry": {"coordinates":[-3.17752,52.51022],"type":"Point"}
}
