{
  "type": "Feature",
  "properties": {
    "date:inception_lower": "1995-12-01",
    "date:inception_upper": "1995-12-01",
    "iso:country": "GB",
    "wof:name": "CW1 5RW",
    "wof:placetype": "postalcode"
  },
  "geometry": {"coordinates":[-2.395684,53.097601],"type":"Point"}
}
