{
  "type": "Feature",
  "properties": {
    "iso:country":"GB",
    "wof:name":"G45 0ES",
    "wof:placetype":"postalcode"
},
  "geometry": {"coordinates":[-4.21562816261707,55.80411350527267],"type":"Point"}
}