{
  "type": "Feature",
  "properties": {
    "iso:country":"GB",
    "wof:name":"ME12 4HW",
    "wof:placetype":"postalcode"
},
  "geometry": {"coordinates":[0.84497207968805,51.40986955379891],"type":"Point"}
}