{
  "type": "Feature",
  "properties": {
    "iso:country":"GB",
    "wof:name":"RM4 1AP",
    "wof:placetype":"postalcode"
},
  "geometry": {"coordinates":[0.13680266917311,51.63527699662088],"type":"Point"}
}