{
  "type": "Feature",
  "properties": {
    "iso:country":"GB",
    "wof:name":"G14 9SR",
    "wof:placetype":"postalcode"
},
  "geometry": {"coordinates":[-4.35728180275813,55.88350027728184],"type":"Point"}
}