{
  "type": "Feature",
  "properties": {
    "iso:country":"GB",
    "wof:name":"PL2 1PL",
    "wof:placetype":"postalcode"
},
  "geometry": {"coordinates":[-4.16668593585857,50.38653076825354],"type":"Point"}
}