{
  "type": "Feature",
  "properties": {
    "date:inception_lower": "2014-12-01",
    "date:inception_upper": "2014-12-01",
    "iso:country": "GB",
    "wof:name": "LE13 1NF",
    "wof:placetype": "postalcode"
  },
  "geometry": {"coordinates":[-0.884134,52.781126],"type":"Point"}
}
