{
  "type": "Feature",
  "properties": {
    "iso:country":"GB",
    "wof:name":"LE13 1NF",
    "wof:placetype":"postalcode"
},
  "geometry": {"coordinates":[-0.88458885204324,52.78098399261292],"type":"Point"}
}