{
  "type": "Feature",
  "properties": {
    "date:inception_lower": "2021-08-01",
    "date:inception_upper": "2021-08-01",
    "iso:country": "GB",
    "wof:name": "ME13 8US",
    "wof:placetype": "postalcode"
  },
  "geometry": {"coordinates":[0.883778,51.304736],"type":"Point"}
}
