{
  "type": "Feature",
  "properties": {
    "iso:country":"GB",
    "wof:name":"BS20 7GS",
    "wof:placetype":"postalcode"
},
  "geometry": {"coordinates":[-2.75302452077393,51.48694587854692],"type":"Point"}
}