{
  "type": "Feature",
  "properties": {
    "iso:country":"GB",
    "wof:name":"N17 6EF",
    "wof:placetype":"postalcode"
},
  "geometry": {"coordinates":[-0.08012653004454,51.59203945731972],"type":"Point"}
}