{
  "type": "Feature",
  "properties": {
    "iso:country":"GB",
    "wof:name":"S12 4WS",
    "wof:placetype":"postalcode"
},
  "geometry": {"coordinates":[-1.40751272424158,53.34793747682572],"type":"Point"}
}