{
  "type": "Feature",
  "properties": {
    "iso:country":"GB",
    "wof:name":"CF72 8DQ",
    "wof:placetype":"postalcode"
},
  "geometry": {"coordinates":[-3.37070831417491,51.5387565455074],"type":"Point"}
}