{
  "type": "Feature",
  "properties": {
    "iso:country": "GB",
    "wof:name": "CF72 8DQ",
    "wof:placetype": "postalcode"
  },
  "geometry": {"coordinates":[-3.370708,51.538757],"type":"Point"}
}
