{
  "type": "Feature",
  "properties": {
    "iso:country":"GB",
    "wof:name":"SG2 9DA",
    "wof:placetype":"postalcode"
},
  "geometry": {"coordinates":[-0.16153055753586,51.89868964858827],"type":"Point"}
}