{
  "type": "Feature",
  "properties": {
    "iso:country": "GB",
    "wof:name": "L30 2PX",
    "wof:placetype": "postalcode"
  },
  "geometry": {"coordinates":[-2.99415,53.484556],"type":"Point"}
}
