{
  "type": "Feature",
  "properties": {
    "iso:country":"GB",
    "wof:name":"L30 2PX",
    "wof:placetype":"postalcode"
},
  "geometry": {"coordinates":[-2.9941503126036,53.48455626638883],"type":"Point"}
}