{
  "type": "Feature",
  "properties": {
    "iso:country": "GB",
    "wof:name": "G69 9NH",
    "wof:placetype": "postalcode"
  },
  "geometry": {"coordinates":[-4.098351,55.905596],"type":"Point"}
}
