{
  "type": "Feature",
  "properties": {
    "iso:country":"GB",
    "wof:name":"G69 9NH",
    "wof:placetype":"postalcode"
},
  "geometry": {"coordinates":[-4.09835147366488,55.90559593685172],"type":"Point"}
}