{
  "type": "Feature",
  "properties": {
    "iso:country":"GB",
    "wof:name":"NE37 2AP",
    "wof:placetype":"postalcode"
},
  "geometry": {"coordinates":[-1.51935296076914,54.91247230822161],"type":"Point"}
}