{
  "type": "Feature",
  "properties": {
    "iso:country": "GB",
    "wof:name": "BB7 4DQ",
    "wof:placetype": "postalcode"
  },
  "geometry": {"coordinates":[-2.255851,53.936804],"type":"Point"}
}
