{
  "type": "Feature",
  "properties": {
    "iso:country":"GB",
    "wof:name":"PR8 1HY",
    "wof:placetype":"postalcode"
},
  "geometry": {"coordinates":[-3.00690773270522,53.64186884871379],"type":"Point"}
}