{
  "type": "Feature",
  "properties": {
    "iso:country": "GB",
    "wof:name": "L27 6PN",
    "wof:placetype": "postalcode"
  },
  "geometry": {"coordinates":[-2.835581,53.386355],"type":"Point"}
}
