{
  "type": "Feature",
  "properties": {
    "iso:country": "GB",
    "wof:name": "WS14 9RF",
    "wof:placetype": "postalcode"
  },
  "geometry": {"coordinates":[-1.819541,52.678104],"type":"Point"}
}
