{
  "type": "Feature",
  "properties": {
    "date:inception_lower":"1997-12-01",
    "date:inception_upper":"1997-12-31",
    "iso:country":"GB",
    "wof:name":"LE14 2QL",
    "wof:placetype":"postalcode"
},
  "geometry": {"coordinates":[-0.843855,52.685461],"type":"Point"}
}