{
  "type": "Feature",
  "properties": {
    "iso:country":"GB",
    "wof:name":"W1D 6BR",
    "wof:placetype":"postalcode"
},
  "geometry": {"coordinates":[-0.13198942242526,51.51022666004351],"type":"Point"}
}