{
  "type": "Feature",
  "properties": {
    "date:inception_lower": "2000-12-01",
    "date:inception_upper": "2000-12-01",
    "iso:country": "GB",
    "wof:name": "W1D 6BR",
    "wof:placetype": "postalcode"
  },
  "geometry": {"coordinates":[-0.131989,51.510227],"type":"Point"}
}
