{
  "type": "Feature",
  "properties": {
    "iso:country": "GB",
    "wof:name": "WR12 7BU",
    "wof:placetype": "postalcode"
  },
  "geometry": {"coordinates":[-1.865748,52.036853],"type":"Point"}
}
