{
  "type": "Feature",
  "properties": {
    "iso:country": "GB",
    "wof:name": "M27 5RY",
    "wof:placetype": "postalcode"
  },
  "geometry": {"coordinates":[-2.342767,53.507246],"type":"Point"}
}
