{
  "type": "Feature",
  "properties": {
    "iso:country":"GB",
    "wof:name":"RG40 2JJ",
    "wof:placetype":"postalcode"
},
  "geometry": {"coordinates":[-0.81802441172099,51.40519027355047],"type":"Point"}
}