{
  "type": "Feature",
  "properties": {
    "iso:country":"GB",
    "wof:name":"BS21 5HS",
    "wof:placetype":"postalcode"
},
  "geometry": {"coordinates":[-2.8608150314781,51.42439465404339],"type":"Point"}
}