{
  "type": "Feature",
  "properties": {
    "iso:country":"GB",
    "wof:name":"LL14 4LG",
    "wof:placetype":"postalcode"
},
  "geometry": {"coordinates":[-3.06393720399558,53.03329909214715],"type":"Point"}
}