{
  "type": "Feature",
  "properties": {
    "iso:country":"GB",
    "wof:name":"EH10 7ER",
    "wof:placetype":"postalcode"
},
  "geometry": {"coordinates":[-3.1967120401479,55.90087615708427],"type":"Point"}
}