{
  "type": "Feature",
  "properties": {
    "date:inception_lower": "2003-05-01",
    "date:inception_upper": "2003-05-01",
    "iso:country": "GB",
    "wof:name": "EH10 7ER",
    "wof:placetype": "postalcode"
  },
  "geometry": {"coordinates":[-3.196712,55.900876],"type":"Point"}
}
