{
  "type": "Feature",
  "properties": {
    "iso:country": "GB",
    "wof:name": "EX23 0EL",
    "wof:placetype": "postalcode"
  },
  "geometry": {"coordinates":[-4.523732,50.807585],"type":"Point"}
}
