{
  "type": "Feature",
  "properties": {
    "iso:country": "GB",
    "wof:name": "TW20 9PG",
    "wof:placetype": "postalcode"
  },
  "geometry": {"coordinates":[-0.554013,51.431275],"type":"Point"}
}
