{
  "type": "Feature",
  "properties": {
    "iso:country":"GB",
    "wof:name":"TF7 5TR",
    "wof:placetype":"postalcode"
},
  "geometry": {"coordinates":[-2.46716236964577,52.63076181656464],"type":"Point"}
}