{
  "type": "Feature",
  "properties": {
    "date:inception_lower": "1991-09-01",
    "date:inception_upper": "1991-09-01",
    "iso:country": "GB",
    "wof:name": "TF7 5TR",
    "wof:placetype": "postalcode"
  },
  "geometry": {"coordinates":[-2.467162,52.630762],"type":"Point"}
}
