{
  "type": "Feature",
  "properties": {
    "iso:country":"GB",
    "wof:name":"B68 9SZ",
    "wof:placetype":"postalcode"
},
  "geometry": {"coordinates":[-1.99372653127629,52.49019266113476],"type":"Point"}
}