{
  "type": "Feature",
  "properties": {
    "iso:country":"GB",
    "wof:name":"TA6 6EX",
    "wof:placetype":"postalcode"
},
  "geometry": {"coordinates":[-2.99984922167394,51.10723573562816],"type":"Point"}
}