{
  "type": "Feature",
  "properties": {
    "date:inception_lower": "2021-01-01",
    "date:inception_upper": "2021-01-01",
    "iso:country": "GB",
    "wof:name": "LN4 2GT",
    "wof:placetype": "postalcode"
  },
  "geometry": {"coordinates":[-0.390931,53.164785],"type":"Point"}
}
