{
  "type": "Feature",
  "properties": {
    "iso:country":"GB",
    "wof:name":"RG21 8AY",
    "wof:placetype":"postalcode"
},
  "geometry": {"coordinates":[-1.09939769420011,51.26210974867246],"type":"Point"}
}