{
  "type": "Feature",
  "properties": {
    "iso:country":"GB",
    "wof:name":"EX14 3QA",
    "wof:placetype":"postalcode"
},
  "geometry": {"coordinates":[-3.25071961398085,50.81545231122251],"type":"Point"}
}