{
  "type": "Feature",
  "properties": {
    "iso:country": "GB",
    "wof:name": "EX14 3QA",
    "wof:placetype": "postalcode"
  },
  "geometry": {"coordinates":[-3.25072,50.815452],"type":"Point"}
}
