{
  "type": "Feature",
  "properties": {
    "date:inception_lower": "1980-01-01",
    "date:inception_upper": "1980-01-01",
    "iso:country": "GB",
    "wof:name": "SG2 8SQ",
    "wof:placetype": "postalcode"
  },
  "geometry": {"coordinates":[-0.179929,51.87984],"type":"Point"}
}
