{
  "type": "Feature",
  "properties": {
    "iso:country":"GB",
    "wof:name":"YO12 5TP",
    "wof:placetype":"postalcode"
},
  "geometry": {"coordinates":[-0.43733227306657,54.27606969599029],"type":"Point"}
}