{
  "type": "Feature",
  "properties": {
    "iso:country": "GB",
    "wof:name": "YO12 5TP",
    "wof:placetype": "postalcode"
  },
  "geometry": {"coordinates":[-0.437332,54.27607],"type":"Point"}
}
