{
  "type": "Feature",
  "properties": {
    "iso:country":"GB",
    "wof:name":"TA24 6TU",
    "wof:placetype":"postalcode"
},
  "geometry": {"coordinates":[-3.45999680957341,51.18118751338692],"type":"Point"}
}