{
  "type": "Feature",
  "properties": {
    "iso:country":"GB",
    "wof:name":"PO33 2LR",
    "wof:placetype":"postalcode"
},
  "geometry": {"coordinates":[-1.15579126669426,50.72729046353408],"type":"Point"}
}