{
  "type": "Feature",
  "properties": {
    "iso:country": "GB",
    "wof:name": "PO33 2LR",
    "wof:placetype": "postalcode"
  },
  "geometry": {"coordinates":[-1.155791,50.72729],"type":"Point"}
}
