{
  "type": "Feature",
  "properties": {
    "date:inception_lower": "2021-11-01",
    "date:inception_upper": "2021-11-01",
    "iso:country": "GB",
    "wof:name": "RG28 7GF",
    "wof:placetype": "postalcode"
  },
  "geometry": {"coordinates":[-1.38037,51.240029],"type":"Point"}
}
