{
  "type": "Feature",
  "properties": {
    "iso:country":"GB",
    "wof:name":"HU9 4PH",
    "wof:placetype":"postalcode"
},
  "geometry": {"coordinates":[-0.26448197929503,53.76310943381093],"type":"Point"}
}