{
  "type": "Feature",
  "properties": {
    "iso:country": "GB",
    "wof:name": "BN42 4AR",
    "wof:placetype": "postalcode"
  },
  "geometry": {"coordinates":[-0.227175,50.832408],"type":"Point"}
}
