{
  "type": "Feature",
  "properties": {
    "date:inception_lower": "1980-01-01",
    "date:inception_upper": "1980-01-01",
    "iso:country": "GB",
    "wof:name": "BN22 7DX",
    "wof:placetype": "postalcode"
  },
  "geometry": {"coordinates":[0.298072,50.775243],"type":"Point"}
}
