{
  "type": "Feature",
  "properties": {
    "iso:country":"GB",
    "wof:name":"BB4 8BW",
    "wof:placetype":"postalcode"
},
  "geometry": {"coordinates":[-2.28719247025614,53.72987131593195],"type":"Point"}
}