{
  "type": "Feature",
  "properties": {
    "iso:country": "GB",
    "wof:name": "YO11 2XU",
    "wof:placetype": "postalcode"
  },
  "geometry": {"coordinates":[-0.393548,54.265697],"type":"Point"}
}
