{
  "type": "Feature",
  "properties": {
    "date:inception_lower": "2012-07-01",
    "date:inception_upper": "2012-07-01",
    "iso:country": "GB",
    "wof:name": "BS5 0EE",
    "wof:placetype": "postalcode"
  },
  "geometry": {"coordinates":[-2.578102,51.459085],"type":"Point"}
}
