{
  "type": "Feature",
  "properties": {
    "iso:country":"GB",
    "wof:name":"TQ7 3PU",
    "wof:placetype":"postalcode"
},
  "geometry": {"coordinates":[-3.79390883851541,50.27915871534664],"type":"Point"}
}