{
  "type": "Feature",
  "properties": {
    "iso:country": "GB",
    "wof:name": "TQ7 3PU",
    "wof:placetype": "postalcode"
  },
  "geometry": {"coordinates":[-3.793909,50.279159],"type":"Point"}
}
