{
  "type": "Feature",
  "properties": {
    "iso:country":"GB",
    "wof:name":"CW1 4QH",
    "wof:placetype":"postalcode"
},
  "geometry": {"coordinates":[-2.47663590177753,53.11325942266497],"type":"Point"}
}