{
  "type": "Feature",
  "properties": {
    "date:inception_lower": "1980-01-01",
    "date:inception_upper": "1980-01-01",
    "iso:country": "GB",
    "wof:name": "CW1 4QH",
    "wof:placetype": "postalcode"
  },
  "geometry": {"coordinates":[-2.476636,53.113259],"type":"Point"}
}
