{
  "type": "Feature",
  "properties": {
    "date:inception_lower": "2000-12-01",
    "date:inception_upper": "2000-12-01",
    "iso:country": "GB",
    "wof:name": "HD1 6BZ",
    "wof:placetype": "postalcode"
  },
  "geometry": {"coordinates":[-1.777501,53.655172],"type":"Point"}
}
