{
  "type": "Feature",
  "properties": {
    "iso:country":"GB",
    "wof:name":"B91 2PU",
    "wof:placetype":"postalcode"
},
  "geometry": {"coordinates":[-1.76534499888931,52.41573008163525],"type":"Point"}
}