{
  "type": "Feature",
  "properties": {
    "iso:country":"GB",
    "wof:name":"M25 2RU",
    "wof:placetype":"postalcode"
},
  "geometry": {"coordinates":[-2.25399772920314,53.55376829690007],"type":"Point"}
}