{
  "type": "Feature",
  "properties": {
    "iso:country": "GB",
    "wof:name": "M25 2RU",
    "wof:placetype": "postalcode"
  },
  "geometry": {"coordinates":[-2.253998,53.553768],"type":"Point"}
}
