{
  "type": "Feature",
  "properties": {
    "iso:country":"GB",
    "wof:name":"BR3 3HJ",
    "wof:placetype":"postalcode"
},
  "geometry": {"coordinates":[-0.03786104360954,51.39832213748385],"type":"Point"}
}