{
  "type": "Feature",
  "properties": {
    "iso:country":"GB",
    "wof:name":"TS18 1NW",
    "wof:placetype":"postalcode"
},
  "geometry": {"coordinates":[-1.31347093194981,54.56402907184096],"type":"Point"}
}