{
  "type": "Feature",
  "properties": {
    "date:inception_lower": "2009-07-01",
    "date:inception_upper": "2009-07-01",
    "iso:country": "GB",
    "wof:name": "SA15 5HB",
    "wof:placetype": "postalcode"
  },
  "geometry": {"coordinates":[-4.191643,51.729892],"type":"Point"}
}
