{
  "type": "Feature",
  "properties": {
    "iso:country":"GB",
    "wof:name":"SA15 5HB",
    "wof:placetype":"postalcode"
},
  "geometry": {"coordinates":[-4.19162092789262,51.72988482926583],"type":"Point"}
}