{
  "type": "Feature",
  "properties": {
    "iso:country":"GB",
    "wof:name":"NR34 8LW",
    "wof:placetype":"postalcode"
},
  "geometry": {"coordinates":[1.54701532442371,52.42234747436942],"type":"Point"}
}