{
  "type": "Feature",
  "properties": {
    "date:inception_lower": "1980-01-01",
    "date:inception_upper": "1980-01-01",
    "iso:country": "GB",
    "wof:name": "NR34 8LW",
    "wof:placetype": "postalcode"
  },
  "geometry": {"coordinates":[1.547015,52.422347],"type":"Point"}
}
