{
  "type": "Feature",
  "properties": {
    "date:inception_lower": "1980-01-01",
    "date:inception_upper": "1980-01-01",
    "iso:country": "GB",
    "wof:name": "NP4 5BU",
    "wof:placetype": "postalcode"
  },
  "geometry": {"coordinates":[-3.034186,51.677512],"type":"Point"}
}
