{
  "type": "Feature",
  "properties": {
    "iso:country": "GB",
    "wof:name": "HP5 2BD",
    "wof:placetype": "postalcode"
  },
  "geometry": {"coordinates":[-0.60965,51.714517],"type":"Point"}
}
