{
  "type": "Feature",
  "properties": {
    "iso:country":"GB",
    "wof:name":"HP5 2BD",
    "wof:placetype":"postalcode"
},
  "geometry": {"coordinates":[-0.60960087705761,51.71452000079916],"type":"Point"}
}