{
  "type": "Feature",
  "properties": {
    "iso:country": "GB",
    "wof:name": "G43 1AX",
    "wof:placetype": "postalcode"
  },
  "geometry": {"coordinates":[-4.331546,55.821198],"type":"Point"}
}
