{
  "type": "Feature",
  "properties": {
    "iso:country": "GB",
    "wof:name": "SY10 0LU",
    "wof:placetype": "postalcode"
  },
  "geometry": {"coordinates":[-3.451515,52.760422],"type":"Point"}
}
