{
  "type": "Feature",
  "properties": {
    "date:inception_lower": "1980-01-01",
    "date:inception_upper": "1980-01-01",
    "iso:country": "GB",
    "wof:name": "SY10 0LU",
    "wof:placetype": "postalcode"
  },
  "geometry": {"coordinates":[-3.451515,52.760422],"type":"Point"}
}
