{
  "type": "Feature",
  "properties": {
    "iso:country":"GB",
    "wof:name":"B18 5QQ",
    "wof:placetype":"postalcode"
},
  "geometry": {"coordinates":[-1.92003993913412,52.49289891791821],"type":"Point"}
}