{
  "type": "Feature",
  "properties": {
    "date:inception_lower": "1999-12-01",
    "date:inception_upper": "1999-12-01",
    "iso:country": "GB",
    "wof:name": "SE16 7JU",
    "wof:placetype": "postalcode"
  },
  "geometry": {"coordinates":[-0.051012,51.500456],"type":"Point"}
}
