{
  "type": "Feature",
  "properties": {
    "iso:country":"GB",
    "wof:name":"SE16 7JU",
    "wof:placetype":"postalcode"
},
  "geometry": {"coordinates":[-0.05101208797759,51.50045587437299],"type":"Point"}
}