{
  "type": "Feature",
  "properties": {
    "date:inception_lower": "1980-01-01",
    "date:inception_upper": "1980-01-01",
    "iso:country": "GB",
    "wof:name": "TR6 0HB",
    "wof:placetype": "postalcode"
  },
  "geometry": {"coordinates":[-5.153196,50.341086],"type":"Point"}
}
