{
  "type": "Feature",
  "properties": {
    "iso:country":"GB",
    "wof:name":"TR6 0HB",
    "wof:placetype":"postalcode"
},
  "geometry": {"coordinates":[-5.15319649829011,50.34108564185688],"type":"Point"}
}