{
  "type": "Feature",
  "properties": {
    "date:inception_lower": "1980-01-01",
    "date:inception_upper": "1980-01-01",
    "iso:country": "GB",
    "wof:name": "FK1 3EY",
    "wof:placetype": "postalcode"
  },
  "geometry": {"coordinates":[-3.83351,55.937391],"type":"Point"}
}
