{
  "type": "Feature",
  "properties": {
    "date:inception_lower": "1980-01-01",
    "date:inception_upper": "1980-01-01",
    "iso:country": "GB",
    "wof:name": "LL22 9HL",
    "wof:placetype": "postalcode"
  },
  "geometry": {"coordinates":[-3.535921,53.305583],"type":"Point"}
}
