{
  "type": "Feature",
  "properties": {
    "iso:country":"GB",
    "wof:name":"LL22 9HL",
    "wof:placetype":"postalcode"
},
  "geometry": {"coordinates":[-3.535902732222,53.30555642012769],"type":"Point"}
}