{
  "type": "Feature",
  "properties": {
    "iso:country": "GB",
    "wof:name": "LL22 9HL",
    "wof:placetype": "postalcode"
  },
  "geometry": {"coordinates":[-3.536106,53.305733],"type":"Point"}
}
