{
  "type": "Feature",
  "properties": {
    "iso:country":"GB",
    "wof:name":"SE26 5TL",
    "wof:placetype":"postalcode"
},
  "geometry": {"coordinates":[-0.03804272536756,51.42497973747174],"type":"Point"}
}