{
  "type": "Feature",
  "properties": {
    "iso:country":"GB",
    "wof:name":"ME3 9EN",
    "wof:placetype":"postalcode"
},
  "geometry": {"coordinates":[0.55994917570298,51.42147244287833],"type":"Point"}
}