{
  "type": "Feature",
  "properties": {
    "iso:country":"GB",
    "wof:name":"SY25 6RD",
    "wof:placetype":"postalcode"
},
  "geometry": {"coordinates":[-4.06410678392138,52.24524912563323],"type":"Point"}
}