{
  "type": "Feature",
  "properties": {
    "iso:country": "GB",
    "wof:name": "SY25 6RD",
    "wof:placetype": "postalcode"
  },
  "geometry": {"coordinates":[-4.064107,52.245249],"type":"Point"}
}
