{
  "type": "Feature",
  "properties": {
    "iso:country": "GB",
    "wof:name": "SR3 2SE",
    "wof:placetype": "postalcode"
  },
  "geometry": {"coordinates":[-1.41561,54.863779],"type":"Point"}
}
