{
  "type": "Feature",
  "properties": {
    "iso:country":"GB",
    "wof:name":"SR3 2SE",
    "wof:placetype":"postalcode"
},
  "geometry": {"coordinates":[-1.41561023024549,54.86377856016163],"type":"Point"}
}