{
  "type": "Feature",
  "properties": {
    "date:inception_lower":"1998-06-01",
    "date:inception_upper":"1998-06-30",
    "iso:country":"GB",
    "wof:name":"YO62 5AN",
    "wof:placetype":"postalcode"
},
  "geometry": {"coordinates":[-1.060393,54.247877],"type":"Point"}
}