{
  "type": "Feature",
  "properties": {
    "iso:country":"GB",
    "wof:name":"YO62 5AN",
    "wof:placetype":"postalcode"
},
  "geometry": {"coordinates":[-1.06039349693431,54.24787688632269],"type":"Point"}
}