{
  "type": "Feature",
  "properties": {
    "iso:country": "GB",
    "wof:name": "YO62 5AN",
    "wof:placetype": "postalcode"
  },
  "geometry": {"coordinates":[-1.060393,54.247877],"type":"Point"}
}
