{
  "type": "Feature",
  "properties": {
    "date:inception_lower":"1994-05-01",
    "date:inception_upper":"1994-05-31",
    "iso:country":"GB",
    "wof:name":"CO10 9TS",
    "wof:placetype":"postalcode"
},
  "geometry": {"coordinates":[0.713416,52.068846],"type":"Point"}
}