{
  "type": "Feature",
  "properties": {
    "iso:country": "GB",
    "wof:name": "SR2 7BG",
    "wof:placetype": "postalcode"
  },
  "geometry": {"coordinates":[-1.382489,54.898339],"type":"Point"}
}
