{
  "type": "Feature",
  "properties": {
    "iso:country":"GB",
    "wof:name":"EH22 3LX",
    "wof:placetype":"postalcode"
},
  "geometry": {"coordinates":[-3.07151790400056,55.8795748611544],"type":"Point"}
}