{
  "type": "Feature",
  "properties": {
    "date:inception_lower":"2008-08-01",
    "date:inception_upper":"2008-08-31",
    "iso:country":"GB",
    "wof:name":"EC1V 2DW",
    "wof:placetype":"postalcode"
},
  "geometry": {"coordinates":[-0.08892,51.527302],"type":"Point"}
}