{
  "type": "Feature",
  "properties": {
    "iso:country":"GB",
    "wof:name":"AL10 8SW",
    "wof:placetype":"postalcode"
},
  "geometry": {"coordinates":[-0.22936065693389,51.74745075270229],"type":"Point"}
}