{
  "type": "Feature",
  "properties": {
    "iso:country":"GB",
    "wof:name":"M28 1HQ",
    "wof:placetype":"postalcode"
},
  "geometry": {"coordinates":[-2.42197045082517,53.50253559687236],"type":"Point"}
}