{
  "type": "Feature",
  "properties": {
    "iso:country":"GB",
    "wof:name":"TW3 2DZ",
    "wof:placetype":"postalcode"
},
  "geometry": {"coordinates":[-0.36073738906722,51.4607179451855],"type":"Point"}
}