{
  "type": "Feature",
  "properties": {
    "date:inception_lower": "2008-03-01",
    "date:inception_upper": "2008-03-01",
    "iso:country": "GB",
    "wof:name": "KA6 6PT",
    "wof:placetype": "postalcode"
  },
  "geometry": {"coordinates":[-4.583212,55.430078],"type":"Point"}
}
