{
  "type": "Feature",
  "properties": {
    "iso:country":"GB",
    "wof:name":"KA6 6PT",
    "wof:placetype":"postalcode"
},
  "geometry": {"coordinates":[-4.58321219486311,55.43007823885952],"type":"Point"}
}