{
  "type": "Feature",
  "properties": {
    "date:inception_lower": "2012-03-01",
    "date:inception_upper": "2012-03-01",
    "iso:country": "GB",
    "wof:name": "SW14 7BA",
    "wof:placetype": "postalcode"
  },
  "geometry": {"coordinates":[-0.271988,51.470702],"type":"Point"}
}
