{
  "type": "Feature",
  "properties": {
    "iso:country":"GB",
    "wof:name":"NN7 4SE",
    "wof:placetype":"postalcode"
},
  "geometry": {"coordinates":[-1.04062960938191,52.19760302322982],"type":"Point"}
}