{
  "type": "Feature",
  "properties": {
    "iso:country": "GB",
    "wof:name": "NN7 4SE",
    "wof:placetype": "postalcode"
  },
  "geometry": {"coordinates":[-1.04063,52.197603],"type":"Point"}
}
