{
  "type": "Feature",
  "properties": {
    "iso:country":"GB",
    "wof:name":"TS17 9PE",
    "wof:placetype":"postalcode"
},
  "geometry": {"coordinates":[-1.29594366881693,54.53108971938384],"type":"Point"}
}