{
  "type": "Feature",
  "properties": {
    "iso:country":"GB",
    "wof:name":"DA1 5EE",
    "wof:placetype":"postalcode"
},
  "geometry": {"coordinates":[0.23545905515545,51.45190816314423],"type":"Point"}
}