{
  "type": "Feature",
  "properties": {
    "date:inception_lower": "1980-01-01",
    "date:inception_upper": "1980-01-01",
    "iso:country": "GB",
    "wof:name": "RM12 6RA",
    "wof:placetype": "postalcode"
  },
  "geometry": {"coordinates":[0.214143,51.545293],"type":"Point"}
}
