{
  "type": "Feature",
  "properties": {
    "date:inception_lower": "1995-01-01",
    "date:inception_upper": "1995-01-01",
    "iso:country": "GB",
    "wof:name": "DN21 1FJ",
    "wof:placetype": "postalcode"
  },
  "geometry": {"coordinates":[-0.745972,53.391582],"type":"Point"}
}
