{
  "type": "Feature",
  "properties": {
    "iso:country":"GB",
    "wof:name":"BH23 5JU",
    "wof:placetype":"postalcode"
},
  "geometry": {"coordinates":[-1.69339773338318,50.74023879987109],"type":"Point"}
}