{
  "type": "Feature",
  "properties": {
    "iso:country": "GB",
    "wof:name": "G76 7RU",
    "wof:placetype": "postalcode"
  },
  "geometry": {"coordinates":[-4.29093,55.788883],"type":"Point"}
}
