{
  "type": "Feature",
  "properties": {
    "iso:country": "GB",
    "wof:name": "ML6 8SW",
    "wof:placetype": "postalcode"
  },
  "geometry": {"coordinates":[-3.948462,55.843549],"type":"Point"}
}
