{
  "type": "Feature",
  "properties": {
    "iso:country":"GB",
    "wof:name":"BN16 1HZ",
    "wof:placetype":"postalcode"
},
  "geometry": {"coordinates":[-0.48537871993329,50.81299622224276],"type":"Point"}
}