{
  "type": "Feature",
  "properties": {
    "iso:country":"GB",
    "wof:name":"KY13 8EQ",
    "wof:placetype":"postalcode"
},
  "geometry": {"coordinates":[-3.42459504817192,56.20395305863143],"type":"Point"}
}