{
  "type": "Feature",
  "properties": {
    "iso:country":"GB",
    "wof:name":"NE42 6PN",
    "wof:placetype":"postalcode"
},
  "geometry": {"coordinates":[-1.86570898109376,54.96113667811244],"type":"Point"}
}