{
  "type": "Feature",
  "properties": {
    "iso:country":"GB",
    "wof:name":"BS20 6JZ",
    "wof:placetype":"postalcode"
},
  "geometry": {"coordinates":[-2.78075581379979,51.48565850728263],"type":"Point"}
}