{
  "type": "Feature",
  "properties": {
    "date:inception_lower": "1997-12-01",
    "date:inception_upper": "1997-12-01",
    "iso:country": "GB",
    "wof:name": "BS20 6JZ",
    "wof:placetype": "postalcode"
  },
  "geometry": {"coordinates":[-2.780971,51.485594],"type":"Point"}
}
