{
  "type": "Feature",
  "properties": {
    "iso:country": "GB",
    "wof:name": "BS20 6JZ",
    "wof:placetype": "postalcode"
  },
  "geometry": {"coordinates":[-2.780971,51.485594],"type":"Point"}
}
