{
  "type": "Feature",
  "properties": {
    "iso:country":"GB",
    "wof:name":"TN5 6HT",
    "wof:placetype":"postalcode"
},
  "geometry": {"coordinates":[0.32697652126049,51.06460510384179],"type":"Point"}
}