{
  "type": "Feature",
  "properties": {
    "date:inception_lower": "1990-02-01",
    "date:inception_upper": "1990-02-01",
    "iso:country": "GB",
    "wof:name": "TN5 6HT",
    "wof:placetype": "postalcode"
  },
  "geometry": {"coordinates":[0.327033,51.064611],"type":"Point"}
}
