{
  "type": "Feature",
  "properties": {
    "date:inception_lower": "2001-06-01",
    "date:inception_upper": "2001-06-01",
    "iso:country": "GB",
    "wof:name": "YO21 1EN",
    "wof:placetype": "postalcode"
  },
  "geometry": {"coordinates":[-0.615779,54.482608],"type":"Point"}
}
