{
  "type": "Feature",
  "properties": {
    "iso:country": "GB",
    "wof:name": "YO21 1EN",
    "wof:placetype": "postalcode"
  },
  "geometry": {"coordinates":[-0.615779,54.482608],"type":"Point"}
}
