{
  "type": "Feature",
  "properties": {
    "iso:country":"GB",
    "wof:name":"RG26 4DB",
    "wof:placetype":"postalcode"
},
  "geometry": {"coordinates":[-1.15210661969439,51.35344807958848],"type":"Point"}
}