{
  "type": "Feature",
  "properties": {
    "iso:country":"GB",
    "wof:name":"RG22 4RY",
    "wof:placetype":"postalcode"
},
  "geometry": {"coordinates":[-1.13424255936988,51.22832853881271],"type":"Point"}
}