{
  "type": "Feature",
  "properties": {
    "iso:country":"GB",
    "wof:name":"RM1 4JS",
    "wof:placetype":"postalcode"
},
  "geometry": {"coordinates":[0.18231154945801,51.58924208871663],"type":"Point"}
}