{
  "type": "Feature",
  "properties": {
    "iso:country":"GB",
    "wof:name":"B27 6TS",
    "wof:placetype":"postalcode"
},
  "geometry": {"coordinates":[-1.82132331640959,52.45452990593481],"type":"Point"}
}