{
  "type": "Feature",
  "properties": {
    "iso:country": "GB",
    "wof:name": "EX39 3QQ",
    "wof:placetype": "postalcode"
  },
  "geometry": {"coordinates":[-4.212688,51.034659],"type":"Point"}
}
