{
  "type": "Feature",
  "properties": {
    "iso:country":"GB",
    "wof:name":"B97 5UY",
    "wof:placetype":"postalcode"
},
  "geometry": {"coordinates":[-1.96432318355612,52.2972691666548],"type":"Point"}
}