{
  "type": "Feature",
  "properties": {
    "iso:country": "GB",
    "wof:name": "NG34 9NY",
    "wof:placetype": "postalcode"
  },
  "geometry": {"coordinates":[-0.362457,53.003601],"type":"Point"}
}
