{
  "type": "Feature",
  "properties": {
    "iso:country":"GB",
    "wof:name":"SR6 7HB",
    "wof:placetype":"postalcode"
},
  "geometry": {"coordinates":[-1.36623989084848,54.95900337434163],"type":"Point"}
}