{
  "type": "Feature",
  "properties": {
    "iso:country":"GB",
    "wof:name":"CM13 2TD",
    "wof:placetype":"postalcode"
},
  "geometry": {"coordinates":[0.35201488786586,51.62885984507169],"type":"Point"}
}