{
  "type": "Feature",
  "properties": {
    "iso:country":"GB",
    "wof:name":"E7 8HR",
    "wof:placetype":"postalcode"
},
  "geometry": {"coordinates":[0.03006297228093,51.54096839516084],"type":"Point"}
}