{
  "type": "Feature",
  "properties": {
    "iso:country":"GB",
    "wof:name":"WF9 5LT",
    "wof:placetype":"postalcode"
},
  "geometry": {"coordinates":[-1.36816741647195,53.62818851247971],"type":"Point"}
}