{
  "type": "Feature",
  "properties": {
    "iso:country": "GB",
    "wof:name": "PL1 4PZ",
    "wof:placetype": "postalcode"
  },
  "geometry": {"coordinates":[-4.171658,50.370356],"type":"Point"}
}
