{
  "type": "Feature",
  "properties": {
    "iso:country": "GB",
    "wof:name": "SS8 9RU",
    "wof:placetype": "postalcode"
  },
  "geometry": {"coordinates":[0.590003,51.527529],"type":"Point"}
}
