{
  "type": "Feature",
  "properties": {
    "iso:country":"GB",
    "wof:name":"SS8 9RU",
    "wof:placetype":"postalcode"
},
  "geometry": {"coordinates":[0.59000274985054,51.52752945433681],"type":"Point"}
}