{
  "type": "Feature",
  "properties": {
    "date:inception_lower": "2001-06-01",
    "date:inception_upper": "2001-06-01",
    "iso:country": "GB",
    "wof:name": "WA5 9RB",
    "wof:placetype": "postalcode"
  },
  "geometry": {"coordinates":[-2.617876,53.413738],"type":"Point"}
}
