{
  "type": "Feature",
  "properties": {
    "iso:country":"GB",
    "wof:name":"WA5 9RB",
    "wof:placetype":"postalcode"
},
  "geometry": {"coordinates":[-2.6178761703057,53.41373844557619],"type":"Point"}
}