{
  "type": "Feature",
  "properties": {
    "iso:country":"GB",
    "wof:name":"HU7 3AW",
    "wof:placetype":"postalcode"
},
  "geometry": {"coordinates":[-0.35681189244913,53.80200300405851],"type":"Point"}
}