{
  "type": "Feature",
  "properties": {
    "date:inception_lower": "2011-06-01",
    "date:inception_upper": "2011-06-01",
    "iso:country": "GB",
    "wof:name": "HU7 3AW",
    "wof:placetype": "postalcode"
  },
  "geometry": {"coordinates":[-0.356812,53.802003],"type":"Point"}
}
