{
  "type": "Feature",
  "properties": {
    "iso:country":"GB",
    "wof:name":"SG6 1PZ",
    "wof:placetype":"postalcode"
},
  "geometry": {"coordinates":[-0.21696454300879,51.97911134592086],"type":"Point"}
}