{
  "type": "Feature",
  "properties": {
    "iso:country":"GB",
    "wof:name":"CF5 4QX",
    "wof:placetype":"postalcode"
},
  "geometry": {"coordinates":[-3.26246820414104,51.47848462635852],"type":"Point"}
}