{
  "type": "Feature",
  "properties": {
    "iso:country": "GB",
    "wof:name": "CF5 4QX",
    "wof:placetype": "postalcode"
  },
  "geometry": {"coordinates":[-3.262468,51.478485],"type":"Point"}
}
