{
  "type": "Feature",
  "properties": {
    "date:inception_lower":"1998-12-01",
    "date:inception_upper":"1998-12-31",
    "iso:country":"GB",
    "wof:name":"CF5 4QX",
    "wof:placetype":"postalcode"
},
  "geometry": {"coordinates":[-3.262468,51.478485],"type":"Point"}
}