{
  "type": "Feature",
  "properties": {
    "date:inception_lower":"1990-02-01",
    "date:inception_upper":"1990-02-28",
    "iso:country":"GB",
    "wof:name":"RG5 4XQ",
    "wof:placetype":"postalcode"
},
  "geometry": {"coordinates":[-0.883208,51.457794],"type":"Point"}
}