{
  "type": "Feature",
  "properties": {
    "iso:country": "GB",
    "wof:name": "RG5 4XQ",
    "wof:placetype": "postalcode"
  },
  "geometry": {"coordinates":[-0.883208,51.457794],"type":"Point"}
}
