{
  "type": "Feature",
  "properties": {
    "iso:country":"GB",
    "wof:name":"RG5 4XQ",
    "wof:placetype":"postalcode"
},
  "geometry": {"coordinates":[-0.88320758878539,51.4577938722062],"type":"Point"}
}