{
  "type": "Feature",
  "properties": {
    "iso:country": "GB",
    "wof:name": "NE28 8UB",
    "wof:placetype": "postalcode"
  },
  "geometry": {"coordinates":[-1.552022,55.004653],"type":"Point"}
}
