{
  "type": "Feature",
  "properties": {
    "iso:country":"GB",
    "wof:name":"NE28 8UB",
    "wof:placetype":"postalcode"
},
  "geometry": {"coordinates":[-1.55202193088485,55.00465279306248],"type":"Point"}
}