{
  "type": "Feature",
  "properties": {
    "iso:country":"GB",
    "wof:name":"WS2 7RF",
    "wof:placetype":"postalcode"
},
  "geometry": {"coordinates":[-2.01036515156958,52.59795378674927],"type":"Point"}
}