{
  "type": "Feature",
  "properties": {
    "date:inception_lower": "1980-01-01",
    "date:inception_upper": "1980-01-01",
    "iso:country": "GB",
    "wof:name": "SA1 1QE",
    "wof:placetype": "postalcode"
  },
  "geometry": {"coordinates":[-3.942888,51.628836],"type":"Point"}
}
