{
  "type": "Feature",
  "properties": {
    "iso:country": "GB",
    "wof:name": "SA1 1QE",
    "wof:placetype": "postalcode"
  },
  "geometry": {"coordinates":[-3.942888,51.628836],"type":"Point"}
}
