{
  "type": "Feature",
  "properties": {
    "iso:country":"GB",
    "wof:name":"HS2 0BR",
    "wof:placetype":"postalcode"
},
  "geometry": {"coordinates":[-6.41050222142641,58.21789453243383],"type":"Point"}
}