{
  "type": "Feature",
  "properties": {
    "iso:country":"GB",
    "wof:name":"L30 9TA",
    "wof:placetype":"postalcode"
},
  "geometry": {"coordinates":[-2.98220628916148,53.47049765448651],"type":"Point"}
}