{
  "type": "Feature",
  "properties": {
    "date:inception_lower": "2011-02-01",
    "date:inception_upper": "2011-02-01",
    "iso:country": "GB",
    "wof:name": "L30 9TA",
    "wof:placetype": "postalcode"
  },
  "geometry": {"coordinates":[-2.982206,53.470498],"type":"Point"}
}
