{
  "type": "Feature",
  "properties": {
    "iso:country": "GB",
    "wof:name": "L30 9TA",
    "wof:placetype": "postalcode"
  },
  "geometry": {"coordinates":[-2.982206,53.470498],"type":"Point"}
}
