{
  "type": "Feature",
  "properties": {
    "iso:country":"GB",
    "wof:name":"G32 8HA",
    "wof:placetype":"postalcode"
},
  "geometry": {"coordinates":[-4.16593142099729,55.84277289319171],"type":"Point"}
}