{
  "type": "Feature",
  "properties": {
    "iso:country":"GB",
    "wof:name":"SR8 5QZ",
    "wof:placetype":"postalcode"
},
  "geometry": {"coordinates":[-1.3286392788462,54.75796976273285],"type":"Point"}
}