{
  "type": "Feature",
  "properties": {
    "iso:country":"GB",
    "wof:name":"M34 5RA",
    "wof:placetype":"postalcode"
},
  "geometry": {"coordinates":[-2.12775008496916,53.4789259936255],"type":"Point"}
}