{
  "type": "Feature",
  "properties": {
    "iso:country": "GB",
    "wof:name": "NE20 9JA",
    "wof:placetype": "postalcode"
  },
  "geometry": {"coordinates":[-1.763255,55.033832],"type":"Point"}
}
