{
  "type": "Feature",
  "properties": {
    "iso:country":"GB",
    "wof:name":"NE20 9JA",
    "wof:placetype":"postalcode"
},
  "geometry": {"coordinates":[-1.76325494851453,55.03383160509925],"type":"Point"}
}