{
  "type": "Feature",
  "properties": {
    "iso:country":"GB",
    "wof:name":"WV4 4SE",
    "wof:placetype":"postalcode"
},
  "geometry": {"coordinates":[-2.1738074834371,52.5667126168451],"type":"Point"}
}