{
  "type": "Feature",
  "properties": {
    "date:inception_lower": "2007-08-01",
    "date:inception_upper": "2007-08-01",
    "iso:country": "GB",
    "wof:name": "WV4 4SE",
    "wof:placetype": "postalcode"
  },
  "geometry": {"coordinates":[-2.173807,52.566713],"type":"Point"}
}
