{
  "type": "Feature",
  "properties": {
    "date:inception_lower": "2004-11-01",
    "date:inception_upper": "2004-11-01",
    "iso:country": "GB",
    "wof:name": "DN20 8WA",
    "wof:placetype": "postalcode"
  },
  "geometry": {"coordinates":[-0.482285,53.550569],"type":"Point"}
}
