{
  "type": "Feature",
  "properties": {
    "iso:country":"GB",
    "wof:name":"DN20 8WA",
    "wof:placetype":"postalcode"
},
  "geometry": {"coordinates":[-0.48228511209298,53.55056907280927],"type":"Point"}
}