{
  "type": "Feature",
  "properties": {
    "iso:country":"GB",
    "wof:name":"BA1 9BE",
    "wof:placetype":"postalcode"
},
  "geometry": {"coordinates":[-2.37246207705896,51.40580734043877],"type":"Point"}
}