{
  "type": "Feature",
  "properties": {
    "iso:country": "GB",
    "wof:name": "WS13 6RA",
    "wof:placetype": "postalcode"
  },
  "geometry": {"coordinates":[-1.835339,52.681723],"type":"Point"}
}
