{
  "type": "Feature",
  "properties": {
    "iso:country":"GB",
    "wof:name":"SY4 3QY",
    "wof:placetype":"postalcode"
},
  "geometry": {"coordinates":[-2.76012040597145,52.79687688487746],"type":"Point"}
}