{
  "type": "Feature",
  "properties": {
    "iso:country": "GB",
    "wof:name": "EH48 3SE",
    "wof:placetype": "postalcode"
  },
  "geometry": {"coordinates":[-3.769334,55.884749],"type":"Point"}
}
