{
  "type": "Feature",
  "properties": {
    "iso:country": "GB",
    "wof:name": "DN16 3PQ",
    "wof:placetype": "postalcode"
  },
  "geometry": {"coordinates":[-0.653705,53.554617],"type":"Point"}
}
