{
  "type": "Feature",
  "properties": {
    "iso:country":"GB",
    "wof:name":"DN16 3PQ",
    "wof:placetype":"postalcode"
},
  "geometry": {"coordinates":[-0.65370525267358,53.55461699224539],"type":"Point"}
}