{
  "type": "Feature",
  "properties": {
    "iso:country":"GB",
    "wof:name":"CF31 3NA",
    "wof:placetype":"postalcode"
},
  "geometry": {"coordinates":[-3.58086538663298,51.49320142238109],"type":"Point"}
}