{
  "type": "Feature",
  "properties": {
    "date:inception_lower":"1980-01-01",
    "date:inception_upper":"1980-01-31",
    "iso:country":"GB",
    "wof:name":"NR19 1SE",
    "wof:placetype":"postalcode"
},
  "geometry": {"coordinates":[0.941673,52.667274],"type":"Point"}
}