{
  "type": "Feature",
  "properties": {
    "date:inception_lower":"1980-01-01",
    "date:inception_upper":"1980-01-31",
    "iso:country":"GB",
    "wof:name":"CF35 6SG",
    "wof:placetype":"postalcode"
},
  "geometry": {"coordinates":[-3.498321,51.528698],"type":"Point"}
}