{
  "type": "Feature",
  "properties": {
    "date:inception_lower": "1980-01-01",
    "date:inception_upper": "1980-01-01",
    "iso:country": "GB",
    "wof:name": "CO3 3SE",
    "wof:placetype": "postalcode"
  },
  "geometry": {"coordinates":[0.875364,51.889461],"type":"Point"}
}
