{
  "type": "Feature",
  "properties": {
    "iso:country":"GB",
    "wof:name":"CO3 3SE",
    "wof:placetype":"postalcode"
},
  "geometry": {"coordinates":[0.87536378815469,51.88946108061302],"type":"Point"}
}