{
  "type": "Feature",
  "properties": {
    "iso:country": "GB",
    "wof:name": "SN25 2LW",
    "wof:placetype": "postalcode"
  },
  "geometry": {"coordinates":[-1.832044,51.599111],"type":"Point"}
}
