{
  "type": "Feature",
  "properties": {
    "iso:country":"GB",
    "wof:name":"WS10 0RQ",
    "wof:placetype":"postalcode"
},
  "geometry": {"coordinates":[-2.00250838575014,52.55795857521516],"type":"Point"}
}