{
  "type": "Feature",
  "properties": {
    "date:inception_lower":"2003-05-01",
    "date:inception_upper":"2003-05-31",
    "iso:country":"GB",
    "wof:name":"FK4 2FG",
    "wof:placetype":"postalcode"
},
  "geometry": {"coordinates":[-3.888089,55.992441],"type":"Point"}
}