{
  "type": "Feature",
  "properties": {
    "date:inception_lower": "2013-12-01",
    "date:inception_upper": "2013-12-01",
    "iso:country": "GB",
    "wof:name": "FK2 8RG",
    "wof:placetype": "postalcode"
  },
  "geometry": {"coordinates":[-3.818359,56.040024],"type":"Point"}
}
