{
  "type": "Feature",
  "properties": {
    "iso:country": "GB",
    "wof:name": "FK2 8RG",
    "wof:placetype": "postalcode"
  },
  "geometry": {"coordinates":[-3.818146,56.039947],"type":"Point"}
}
