{
  "type": "Feature",
  "properties": {
    "date:inception_lower": "2018-12-01",
    "date:inception_upper": "2018-12-01",
    "iso:country": "GB",
    "wof:name": "CV8 1TU",
    "wof:placetype": "postalcode"
  },
  "geometry": {"coordinates":[-1.575354,52.3396],"type":"Point"}
}
