{
  "type": "Feature",
  "properties": {
    "iso:country": "GB",
    "wof:name": "CV8 1TU",
    "wof:placetype": "postalcode"
  },
  "geometry": {"coordinates":[-1.575354,52.3396],"type":"Point"}
}
