{
  "type": "Feature",
  "properties": {
    "iso:country": "GB",
    "wof:name": "GL51 7LR",
    "wof:placetype": "postalcode"
  },
  "geometry": {"coordinates":[-2.1107,51.908344],"type":"Point"}
}
