{
  "type": "Feature",
  "properties": {
    "iso:country":"GB",
    "wof:name":"SR8 4AH",
    "wof:placetype":"postalcode"
},
  "geometry": {"coordinates":[-1.32931661412818,54.77246008325151],"type":"Point"}
}