{
  "type": "Feature",
  "properties": {
    "iso:country":"GB",
    "wof:name":"BS23 1SX",
    "wof:placetype":"postalcode"
},
  "geometry": {"coordinates":[-2.9801285045451,51.34677426834151],"type":"Point"}
}