{
  "type": "Feature",
  "properties": {
    "iso:country":"GB",
    "wof:name":"B79 0NR",
    "wof:placetype":"postalcode"
},
  "geometry": {"coordinates":[-1.58130521800872,52.661339376906],"type":"Point"}
}