{
  "type": "Feature",
  "properties": {
    "date:inception_lower": "1992-08-01",
    "date:inception_upper": "1992-08-01",
    "iso:country": "GB",
    "wof:name": "B43 6PN",
    "wof:placetype": "postalcode"
  },
  "geometry": {"coordinates":[-1.931061,52.546971],"type":"Point"}
}
