{
  "type": "Feature",
  "properties": {
    "date:inception_lower": "1980-01-01",
    "date:inception_upper": "1980-01-01",
    "iso:country": "GB",
    "wof:name": "CH3 8AP",
    "wof:placetype": "postalcode"
  },
  "geometry": {"coordinates":[-2.736587,53.237242],"type":"Point"}
}
