{
  "type": "Feature",
  "properties": {
    "iso:country":"GB",
    "wof:name":"CH3 8AP",
    "wof:placetype":"postalcode"
},
  "geometry": {"coordinates":[-2.73658741051966,53.23724246023865],"type":"Point"}
}