{
  "type": "Feature",
  "properties": {
    "iso:country":"GB",
    "wof:name":"LA5 9EL",
    "wof:placetype":"postalcode"
},
  "geometry": {"coordinates":[-2.77639122042729,54.11912758735127],"type":"Point"}
}