{
  "type": "Feature",
  "properties": {
    "iso:country":"GB",
    "wof:name":"SE6 1UP",
    "wof:placetype":"postalcode"
},
  "geometry": {"coordinates":[-0.00790450112714,51.44224104934455],"type":"Point"}
}