{
  "type": "Feature",
  "properties": {
    "iso:country": "GB",
    "wof:name": "B97 6RJ",
    "wof:placetype": "postalcode"
  },
  "geometry": {"coordinates":[-1.941982,52.326703],"type":"Point"}
}
