{
  "type": "Feature",
  "properties": {
    "iso:country":"GB",
    "wof:name":"G76 8SP",
    "wof:placetype":"postalcode"
},
  "geometry": {"coordinates":[-4.30045812919086,55.78383381448212],"type":"Point"}
}