{
  "type": "Feature",
  "properties": {
    "date:inception_lower": "2023-09-01",
    "date:inception_upper": "2023-09-01",
    "iso:country": "GB",
    "wof:name": "CV10 0GR",
    "wof:placetype": "postalcode"
  },
  "geometry": {"coordinates":[-1.525725,52.536431],"type":"Point"}
}
