{
  "type": "Feature",
  "properties": {
    "iso:country": "GB",
    "wof:name": "KA21 6HX",
    "wof:placetype": "postalcode"
  },
  "geometry": {"coordinates":[-4.794004,55.649346],"type":"Point"}
}
