{
  "type": "Feature",
  "properties": {
    "iso:country": "GB",
    "wof:name": "B42 2HF",
    "wof:placetype": "postalcode"
  },
  "geometry": {"coordinates":[-1.916714,52.535542],"type":"Point"}
}
