{
  "type": "Feature",
  "properties": {
    "iso:country":"GB",
    "wof:name":"WA15 9HS",
    "wof:placetype":"postalcode"
},
  "geometry": {"coordinates":[-2.34450191077268,53.38073771001979],"type":"Point"}
}