{
  "type": "Feature",
  "properties": {
    "iso:country":"GB",
    "wof:name":"CH66 1JZ",
    "wof:placetype":"postalcode"
},
  "geometry": {"coordinates":[-2.92698587336607,53.2889131640789],"type":"Point"}
}