{
  "type": "Feature",
  "properties": {
    "date:inception_lower":"1999-06-01",
    "date:inception_upper":"1999-06-30",
    "iso:country":"GB",
    "wof:name":"CH66 1JZ",
    "wof:placetype":"postalcode"
},
  "geometry": {"coordinates":[-2.926986,53.288913],"type":"Point"}
}