{
  "type": "Feature",
  "properties": {
    "iso:country": "GB",
    "wof:name": "CH66 1JZ",
    "wof:placetype": "postalcode"
  },
  "geometry": {"coordinates":[-2.926986,53.288913],"type":"Point"}
}
