{
  "type": "Feature",
  "properties": {
    "date:inception_lower":"1996-12-01",
    "date:inception_upper":"1996-12-31",
    "iso:country":"GB",
    "wof:name":"WR4 0QW",
    "wof:placetype":"postalcode"
},
  "geometry": {"coordinates":[-2.172791,52.198964],"type":"Point"}
}