{
  "type": "Feature",
  "properties": {
    "iso:country": "GB",
    "wof:name": "WR4 0QW",
    "wof:placetype": "postalcode"
  },
  "geometry": {"coordinates":[-2.172791,52.198964],"type":"Point"}
}
