{
  "type": "Feature",
  "properties": {
    "iso:country":"GB",
    "wof:name":"WR4 0QW",
    "wof:placetype":"postalcode"
},
  "geometry": {"coordinates":[-2.17279149908575,52.19896437867876],"type":"Point"}
}