{
  "type": "Feature",
  "properties": {
    "iso:country":"GB",
    "wof:name":"LA12 8HH",
    "wof:placetype":"postalcode"
},
  "geometry": {"coordinates":[-3.02918267509835,54.2830829582788],"type":"Point"}
}