{
  "type": "Feature",
  "properties": {
    "iso:country": "GB",
    "wof:name": "RG41 5PP",
    "wof:placetype": "postalcode"
  },
  "geometry": {"coordinates":[-0.881304,51.430251],"type":"Point"}
}
