{
  "type": "Feature",
  "properties": {
    "date:inception_lower": "2005-03-01",
    "date:inception_upper": "2005-03-01",
    "iso:country": "GB",
    "wof:name": "RG41 5PP",
    "wof:placetype": "postalcode"
  },
  "geometry": {"coordinates":[-0.881304,51.430251],"type":"Point"}
}
