{
  "type": "Feature",
  "properties": {
    "date:inception_lower": "1988-03-01",
    "date:inception_upper": "1988-03-01",
    "iso:country": "GB",
    "wof:name": "WR5 3RW",
    "wof:placetype": "postalcode"
  },
  "geometry": {"coordinates":[-2.204917,52.169334],"type":"Point"}
}
