{
  "type": "Feature",
  "properties": {
    "iso:country": "GB",
    "wof:name": "ML7 5UB",
    "wof:placetype": "postalcode"
  },
  "geometry": {"coordinates":[-3.782968,55.818606],"type":"Point"}
}
