{
  "type": "Feature",
  "properties": {
    "date:inception_lower": "2019-04-01",
    "date:inception_upper": "2019-04-01",
    "iso:country": "GB",
    "wof:name": "ML7 5UB",
    "wof:placetype": "postalcode"
  },
  "geometry": {"coordinates":[-3.783364,55.818528],"type":"Point"}
}
