{
  "type": "Feature",
  "properties": {
    "iso:country":"GB",
    "wof:name":"DG7 3NA",
    "wof:placetype":"postalcode"
},
  "geometry": {"coordinates":[-4.00997768436407,54.99877146992098],"type":"Point"}
}