{
  "type": "Feature",
  "properties": {
    "iso:country": "GB",
    "wof:name": "GU14 9XF",
    "wof:placetype": "postalcode"
  },
  "geometry": {"coordinates":[-0.795584,51.296103],"type":"Point"}
}
