{
  "type": "Feature",
  "properties": {
    "date:inception_lower": "2012-02-01",
    "date:inception_upper": "2012-02-01",
    "iso:country": "GB",
    "wof:name": "PR6 8EE",
    "wof:placetype": "postalcode"
  },
  "geometry": {"coordinates":[-2.617766,53.715823],"type":"Point"}
}
