{
  "type": "Feature",
  "properties": {
    "iso:country": "GB",
    "wof:name": "PR6 8EE",
    "wof:placetype": "postalcode"
  },
  "geometry": {"coordinates":[-2.617766,53.715823],"type":"Point"}
}
