{
  "type": "Feature",
  "properties": {
    "date:inception_lower": "2015-12-01",
    "date:inception_upper": "2015-12-01",
    "iso:country": "GB",
    "wof:name": "PL12 6FB",
    "wof:placetype": "postalcode"
  },
  "geometry": {"coordinates":[-4.237796,50.41506],"type":"Point"}
}
