{
  "type": "Feature",
  "properties": {
    "iso:country":"GB",
    "wof:name":"PL12 6FB",
    "wof:placetype":"postalcode"
},
  "geometry": {"coordinates":[-4.23779740944451,50.41515322601825],"type":"Point"}
}