{
  "type": "Feature",
  "properties": {
    "iso:country": "GB",
    "wof:name": "MK15 9HS",
    "wof:placetype": "postalcode"
  },
  "geometry": {"coordinates":[-0.720027,52.065621],"type":"Point"}
}
