{
  "type": "Feature",
  "properties": {
    "iso:country":"GB",
    "wof:name":"IP5 1DF",
    "wof:placetype":"postalcode"
},
  "geometry": {"coordinates":[1.2133091268651,52.07231322966624],"type":"Point"}
}