{
  "type": "Feature",
  "properties": {
    "date:inception_lower": "1980-01-01",
    "date:inception_upper": "1980-01-01",
    "iso:country": "GB",
    "wof:name": "WN5 0DE",
    "wof:placetype": "postalcode"
  },
  "geometry": {"coordinates":[-2.687251,53.543461],"type":"Point"}
}
