{
  "type": "Feature",
  "properties": {
    "iso:country":"GB",
    "wof:name":"WN5 0DE",
    "wof:placetype":"postalcode"
},
  "geometry": {"coordinates":[-2.6872507244002,53.54346059898379],"type":"Point"}
}