{
  "type": "Feature",
  "properties": {
    "iso:country": "GB",
    "wof:name": "DH2 1JW",
    "wof:placetype": "postalcode"
  },
  "geometry": {"coordinates":[-1.597412,54.88231],"type":"Point"}
}
