{
  "type": "Feature",
  "properties": {
    "iso:country":"GB",
    "wof:name":"DH2 1JW",
    "wof:placetype":"postalcode"
},
  "geometry": {"coordinates":[-1.59741196917879,54.8823099123033],"type":"Point"}
}