{
  "type": "Feature",
  "properties": {
    "date:inception_lower": "2021-04-01",
    "date:inception_upper": "2021-04-01",
    "iso:country": "GB",
    "wof:name": "TN4 0FJ",
    "wof:placetype": "postalcode"
  },
  "geometry": {"coordinates":[0.262139,51.156307],"type":"Point"}
}
