{
  "type": "Feature",
  "properties": {
    "iso:country":"GB",
    "wof:name":"NP4 5JZ",
    "wof:placetype":"postalcode"
},
  "geometry": {"coordinates":[-3.03499438617233,51.69645039073647],"type":"Point"}
}