{
  "type": "Feature",
  "properties": {
    "iso:country":"GB",
    "wof:name":"SS1 2LT",
    "wof:placetype":"postalcode"
},
  "geometry": {"coordinates":[0.71837120653277,51.53990394070301],"type":"Point"}
}