{
  "type": "Feature",
  "properties": {
    "date:inception_lower": "2003-01-01",
    "date:inception_upper": "2003-01-01",
    "iso:country": "GB",
    "wof:name": "SS9 5BA",
    "wof:placetype": "postalcode"
  },
  "geometry": {"coordinates":[0.646112,51.574626],"type":"Point"}
}
