{
  "type": "Feature",
  "properties": {
    "iso:country":"GB",
    "wof:name":"SS4 1HN",
    "wof:placetype":"postalcode"
},
  "geometry": {"coordinates":[0.71262710760012,51.57304368417595],"type":"Point"}
}