{
  "type": "Feature",
  "properties": {
    "iso:country": "GB",
    "wof:name": "YO8 8GT",
    "wof:placetype": "postalcode"
  },
  "geometry": {"coordinates":[-1.06482,53.767234],"type":"Point"}
}
