{
  "type": "Feature",
  "properties": {
    "date:inception_lower": "1984-10-01",
    "date:inception_upper": "1984-10-01",
    "iso:country": "GB",
    "wof:name": "NR10 4SW",
    "wof:placetype": "postalcode"
  },
  "geometry": {"coordinates":[1.11457,52.768828],"type":"Point"}
}
