{
  "type": "Feature",
  "properties": {
    "iso:country":"GB",
    "wof:name":"NR10 4SW",
    "wof:placetype":"postalcode"
},
  "geometry": {"coordinates":[1.11462747218339,52.76887189274658],"type":"Point"}
}