{
  "type": "Feature",
  "properties": {
    "date:inception_lower": "1995-12-01",
    "date:inception_upper": "1995-12-01",
    "iso:country": "GB",
    "wof:name": "WD3 5GH",
    "wof:placetype": "postalcode"
  },
  "geometry": {"coordinates":[-0.499732,51.653723],"type":"Point"}
}
