{
  "type": "Feature",
  "properties": {
    "iso:country":"GB",
    "wof:name":"PR4 0WD",
    "wof:placetype":"postalcode"
},
  "geometry": {"coordinates":[-2.75798187905373,53.7803806110943],"type":"Point"}
}