{
  "type": "Feature",
  "properties": {
    "iso:country": "GB",
    "wof:name": "SK13 8PG",
    "wof:placetype": "postalcode"
  },
  "geometry": {"coordinates":[-1.942516,53.439593],"type":"Point"}
}
