{
  "type": "Feature",
  "properties": {
    "iso:country":"GB",
    "wof:name":"SK13 8PG",
    "wof:placetype":"postalcode"
},
  "geometry": {"coordinates":[-1.94251610316326,53.43959338482017],"type":"Point"}
}