{
  "type": "Feature",
  "properties": {
    "date:inception_lower": "1980-01-01",
    "date:inception_upper": "1980-01-01",
    "iso:country": "GB",
    "wof:name": "WV10 9UF",
    "wof:placetype": "postalcode"
  },
  "geometry": {"coordinates":[-2.121123,52.614604],"type":"Point"}
}
