{
  "type": "Feature",
  "properties": {
    "iso:country": "GB",
    "wof:name": "WV10 9UF",
    "wof:placetype": "postalcode"
  },
  "geometry": {"coordinates":[-2.121123,52.614604],"type":"Point"}
}
