{
  "type": "Feature",
  "properties": {
    "date:inception_lower": "1980-01-01",
    "date:inception_upper": "1980-01-01",
    "iso:country": "GB",
    "wof:name": "SA47 0PA",
    "wof:placetype": "postalcode"
  },
  "geometry": {"coordinates":[-4.308258,52.191583],"type":"Point"}
}
