{
  "type": "Feature",
  "properties": {
    "iso:country":"GB",
    "wof:name":"SA47 0PA",
    "wof:placetype":"postalcode"
},
  "geometry": {"coordinates":[-4.3082583675287,52.19158290140619],"type":"Point"}
}