{
  "type": "Feature",
  "properties": {
    "date:inception_lower": "2023-11-01",
    "date:inception_upper": "2023-11-01",
    "iso:country": "GB",
    "wof:name": "HR8 9SS",
    "wof:placetype": "postalcode"
  },
  "geometry": {"coordinates":[-2.423403,52.044683],"type":"Point"}
}
