{
  "type": "Feature",
  "properties": {
    "iso:country": "GB",
    "wof:name": "BL8 2TZ",
    "wof:placetype": "postalcode"
  },
  "geometry": {"coordinates":[-2.338893,53.592091],"type":"Point"}
}
