{
  "type": "Feature",
  "properties": {
    "iso:country":"GB",
    "wof:name":"BL8 2TZ",
    "wof:placetype":"postalcode"
},
  "geometry": {"coordinates":[-2.33889259705345,53.5920907263444],"type":"Point"}
}