{
  "type": "Feature",
  "properties": {
    "iso:country": "GB",
    "wof:name": "GL55 6UH",
    "wof:placetype": "postalcode"
  },
  "geometry": {"coordinates":[-1.762723,52.095763],"type":"Point"}
}
