{
  "type": "Feature",
  "properties": {
    "iso:country": "GB",
    "wof:name": "WA16 8QZ",
    "wof:placetype": "postalcode"
  },
  "geometry": {"coordinates":[-2.351459,53.298273],"type":"Point"}
}
