{
  "type": "Feature",
  "properties": {
    "iso:country":"GB",
    "wof:name":"G63 9RG",
    "wof:placetype":"postalcode"
},
  "geometry": {"coordinates":[-4.36572825060832,56.03607335924483],"type":"Point"}
}