{
  "type": "Feature",
  "properties": {
    "date:inception_lower": "2019-09-01",
    "date:inception_upper": "2019-09-01",
    "iso:country": "GB",
    "wof:name": "OX26 6GQ",
    "wof:placetype": "postalcode"
  },
  "geometry": {"coordinates":[-1.141877,51.899561],"type":"Point"}
}
