{
  "type": "Feature",
  "properties": {
    "date:inception_lower":"2009-10-01",
    "date:inception_upper":"2009-10-31",
    "iso:country":"GB",
    "wof:name":"IV27 4JN",
    "wof:placetype":"postalcode"
},
  "geometry": {"coordinates":[-5.232048,58.159421],"type":"Point"}
}