{
  "type": "Feature",
  "properties": {
    "iso:country":"GB",
    "wof:name":"IV27 4JN",
    "wof:placetype":"postalcode"
},
  "geometry": {"coordinates":[-5.23204133622869,58.15944200468435],"type":"Point"}
}