{
  "type": "Feature",
  "properties": {
    "iso:country": "GB",
    "wof:name": "PO18 9AW",
    "wof:placetype": "postalcode"
  },
  "geometry": {"coordinates":[-0.814735,50.860674],"type":"Point"}
}
