{
  "type": "Feature",
  "properties": {
    "date:inception_lower": "2017-04-01",
    "date:inception_upper": "2017-04-01",
    "iso:country": "GB",
    "wof:name": "HA8 8FZ",
    "wof:placetype": "postalcode"
  },
  "geometry": {"coordinates":[-0.289343,51.620313],"type":"Point"}
}
