{
  "type": "Feature",
  "properties": {
    "iso:country":"GB",
    "wof:name":"OX17 1QN",
    "wof:placetype":"postalcode"
},
  "geometry": {"coordinates":[-1.33341241056645,52.10639590760631],"type":"Point"}
}