{
  "type": "Feature",
  "properties": {
    "iso:country":"GB",
    "wof:name":"BS8 2HG",
    "wof:placetype":"postalcode"
},
  "geometry": {"coordinates":[-2.61394101994981,51.46651853092047],"type":"Point"}
}