{
  "type": "Feature",
  "properties": {
    "iso:country": "GB",
    "wof:name": "PH1 1QY",
    "wof:placetype": "postalcode"
  },
  "geometry": {"coordinates":[-3.479871,56.398287],"type":"Point"}
}
