{
  "type": "Feature",
  "properties": {
    "date:inception_lower": "1987-04-01",
    "date:inception_upper": "1987-04-01",
    "iso:country": "GB",
    "wof:name": "PH1 1QY",
    "wof:placetype": "postalcode"
  },
  "geometry": {"coordinates":[-3.479871,56.398287],"type":"Point"}
}
