{
  "type": "Feature",
  "properties": {
    "iso:country":"GB",
    "wof:name":"HP3 0NL",
    "wof:placetype":"postalcode"
},
  "geometry": {"coordinates":[-0.55667932886243,51.70952087041053],"type":"Point"}
}