{
  "type": "Feature",
  "properties": {
    "iso:country": "GB",
    "wof:name": "CR8 5JT",
    "wof:placetype": "postalcode"
  },
  "geometry": {"coordinates":[-0.106271,51.318],"type":"Point"}
}
