{
  "type": "Feature",
  "properties": {
    "iso:country":"GB",
    "wof:name":"CR8 5JT",
    "wof:placetype":"postalcode"
},
  "geometry": {"coordinates":[-0.10627106153062,51.31800029226573],"type":"Point"}
}