{
  "type": "Feature",
  "properties": {
    "iso:country":"GB",
    "wof:name":"LE15 7BE",
    "wof:placetype":"postalcode"
},
  "geometry": {"coordinates":[-0.65335474656613,52.7224143865709],"type":"Point"}
}