{
  "type": "Feature",
  "properties": {
    "date:inception_lower": "1980-01-01",
    "date:inception_upper": "1980-01-01",
    "iso:country": "GB",
    "wof:name": "LE15 7BE",
    "wof:placetype": "postalcode"
  },
  "geometry": {"coordinates":[-0.653355,52.722414],"type":"Point"}
}
