{
  "type": "Feature",
  "properties": {
    "iso:country":"GB",
    "wof:name":"TS18 2SZ",
    "wof:placetype":"postalcode"
},
  "geometry": {"coordinates":[-1.29697940971995,54.56794263259728],"type":"Point"}
}