{
  "type": "Feature",
  "properties": {
    "date:inception_lower": "2000-06-01",
    "date:inception_upper": "2000-06-01",
    "iso:country": "GB",
    "wof:name": "TS18 2SZ",
    "wof:placetype": "postalcode"
  },
  "geometry": {"coordinates":[-1.296993,54.567955],"type":"Point"}
}
