{
  "type": "Feature",
  "properties": {
    "iso:country": "GB",
    "wof:name": "TR7 1JX",
    "wof:placetype": "postalcode"
  },
  "geometry": {"coordinates":[-5.089949,50.412151],"type":"Point"}
}
