{
  "type": "Feature",
  "properties": {
    "iso:country":"GB",
    "wof:name":"G65 0PT",
    "wof:placetype":"postalcode"
},
  "geometry": {"coordinates":[-4.04162803173559,55.97935254968223],"type":"Point"}
}