{
  "type": "Feature",
  "properties": {
    "iso:country":"GB",
    "wof:name":"LS24 9SF",
    "wof:placetype":"postalcode"
},
  "geometry": {"coordinates":[-1.27340942143536,53.86699012021145],"type":"Point"}
}