{
  "type": "Feature",
  "properties": {
    "date:inception_lower": "1980-01-01",
    "date:inception_upper": "1980-01-01",
    "iso:country": "GB",
    "wof:name": "LS24 9SF",
    "wof:placetype": "postalcode"
  },
  "geometry": {"coordinates":[-1.273409,53.86699],"type":"Point"}
}
