{
  "type": "Feature",
  "properties": {
    "iso:country":"GB",
    "wof:name":"RG25 2HL",
    "wof:placetype":"postalcode"
},
  "geometry": {"coordinates":[-1.12797335984517,51.19705234059462],"type":"Point"}
}