{
  "type": "Feature",
  "properties": {
    "iso:country":"GB",
    "wof:name":"NE63 9HS",
    "wof:placetype":"postalcode"
},
  "geometry": {"coordinates":[-1.5561293872928,55.18477636395487],"type":"Point"}
}