{
  "type": "Feature",
  "properties": {
    "date:inception_lower":"1980-01-01",
    "date:inception_upper":"1980-01-31",
    "iso:country":"GB",
    "wof:name":"SE5 8NJ",
    "wof:placetype":"postalcode"
},
  "geometry": {"coordinates":[-0.081631,51.471582],"type":"Point"}
}