{
  "type": "Feature",
  "properties": {
    "iso:country":"GB",
    "wof:name":"PO21 1JP",
    "wof:placetype":"postalcode"
},
  "geometry": {"coordinates":[-0.65732537424527,50.78701635321682],"type":"Point"}
}