{
  "type": "Feature",
  "properties": {
    "iso:country":"GB",
    "wof:name":"E1 2BT",
    "wof:placetype":"postalcode"
},
  "geometry": {"coordinates":[-0.05908734674595,51.51487905892503],"type":"Point"}
}