{
  "type": "Feature",
  "properties": {
    "date:inception_lower":"1980-01-01",
    "date:inception_upper":"1980-01-31",
    "iso:country":"GB",
    "wof:name":"E1 2BT",
    "wof:placetype":"postalcode"
},
  "geometry": {"coordinates":[-0.059061,51.51488],"type":"Point"}
}