{
  "type": "Feature",
  "properties": {
    "iso:country": "GB",
    "wof:name": "E1 2BT",
    "wof:placetype": "postalcode"
  },
  "geometry": {"coordinates":[-0.059061,51.51488],"type":"Point"}
}
