{
  "type": "Feature",
  "properties": {
    "date:inception_lower": "1999-06-01",
    "date:inception_upper": "1999-06-01",
    "iso:country": "GB",
    "wof:name": "CF11 6ST",
    "wof:placetype": "postalcode"
  },
  "geometry": {"coordinates":[-3.189939,51.474792],"type":"Point"}
}
