{
  "type": "Feature",
  "properties": {
    "iso:country":"GB",
    "wof:name":"CF11 6ST",
    "wof:placetype":"postalcode"
},
  "geometry": {"coordinates":[-3.18993952529593,51.47479221240702],"type":"Point"}
}