{
  "type": "Feature",
  "properties": {
    "iso:country":"GB",
    "wof:name":"DH4 5LR",
    "wof:placetype":"postalcode"
},
  "geometry": {"coordinates":[-1.48647403705371,54.84848915020126],"type":"Point"}
}