{
  "type": "Feature",
  "properties": {
    "iso:country":"GB",
    "wof:name":"L13 2AR",
    "wof:placetype":"postalcode"
},
  "geometry": {"coordinates":[-2.92250238059284,53.41420915717907],"type":"Point"}
}