{
  "type": "Feature",
  "properties": {
    "iso:country":"GB",
    "wof:name":"MK19 6FD",
    "wof:placetype":"postalcode"
},
  "geometry": {"coordinates":[-0.88972878010308,52.05042028456329],"type":"Point"}
}