{
  "type": "Feature",
  "properties": {
    "date:inception_lower": "2008-01-01",
    "date:inception_upper": "2008-01-01",
    "iso:country": "GB",
    "wof:name": "MK19 6FD",
    "wof:placetype": "postalcode"
  },
  "geometry": {"coordinates":[-0.889729,52.05042],"type":"Point"}
}
