{
  "type": "Feature",
  "properties": {
    "date:inception_lower": "1980-01-01",
    "date:inception_upper": "1980-01-01",
    "iso:country": "GB",
    "wof:name": "HX5 9AH",
    "wof:placetype": "postalcode"
  },
  "geometry": {"coordinates":[-1.834849,53.684874],"type":"Point"}
}
