{
  "type": "Feature",
  "properties": {
    "iso:country":"GB",
    "wof:name":"HX5 9AH",
    "wof:placetype":"postalcode"
},
  "geometry": {"coordinates":[-1.83484906611096,53.68487449508653],"type":"Point"}
}