{
  "type": "Feature",
  "properties": {
    "iso:country":"GB",
    "wof:name":"WR6 6EA",
    "wof:placetype":"postalcode"
},
  "geometry": {"coordinates":[-2.42334080323116,52.25346914810444],"type":"Point"}
}