{
  "type": "Feature",
  "properties": {
    "iso:country": "GB",
    "wof:name": "TN1 2RT",
    "wof:placetype": "postalcode"
  },
  "geometry": {"coordinates":[0.268445,51.137579],"type":"Point"}
}
