{
  "type": "Feature",
  "properties": {
    "iso:country": "GB",
    "wof:name": "KY4 9DP",
    "wof:placetype": "postalcode"
  },
  "geometry": {"coordinates":[-3.360492,56.108971],"type":"Point"}
}
