{
  "type": "Feature",
  "properties": {
    "iso:country":"GB",
    "wof:name":"WR9 8PS",
    "wof:placetype":"postalcode"
},
  "geometry": {"coordinates":[-2.13961701750178,52.26697535656567],"type":"Point"}
}