{
  "type": "Feature",
  "properties": {
    "iso:country": "GB",
    "wof:name": "LE8 9GB",
    "wof:placetype": "postalcode"
  },
  "geometry": {"coordinates":[-1.028484,52.576603],"type":"Point"}
}
