{
  "type": "Feature",
  "properties": {
    "date:inception_lower": "1980-01-01",
    "date:inception_upper": "1980-01-01",
    "iso:country": "GB",
    "wof:name": "EX20 2ER",
    "wof:placetype": "postalcode"
  },
  "geometry": {"coordinates":[-3.89724,50.799568],"type":"Point"}
}
