{
  "type": "Feature",
  "properties": {
    "date:inception_lower": "2020-12-01",
    "date:inception_upper": "2020-12-01",
    "iso:country": "GB",
    "wof:name": "TW3 1DU",
    "wof:placetype": "postalcode"
  },
  "geometry": {"coordinates":[-0.353466,51.46977],"type":"Point"}
}
