{
  "type": "Feature",
  "properties": {
    "date:inception_lower": "1997-12-01",
    "date:inception_upper": "1997-12-01",
    "iso:country": "GB",
    "wof:name": "RG21 3JT",
    "wof:placetype": "postalcode"
  },
  "geometry": {"coordinates":[-1.092542,51.25436],"type":"Point"}
}
