{
  "type": "Feature",
  "properties": {
    "iso:country":"GB",
    "wof:name":"DD11 5EH",
    "wof:placetype":"postalcode"
},
  "geometry": {"coordinates":[-2.57292663643606,56.57063458873078],"type":"Point"}
}