{
  "type": "Feature",
  "properties": {
    "date:inception_lower":"1980-01-01",
    "date:inception_upper":"1980-01-31",
    "iso:country":"GB",
    "wof:name":"DD11 5EH",
    "wof:placetype":"postalcode"
},
  "geometry": {"coordinates":[-2.572927,56.570635],"type":"Point"}
}