{
  "type": "Feature",
  "properties": {
    "date:inception_lower": "1980-01-01",
    "date:inception_upper": "1980-01-01",
    "iso:country": "GB",
    "wof:name": "DL13 5EF",
    "wof:placetype": "postalcode"
  },
  "geometry": {"coordinates":[-1.810467,54.61237],"type":"Point"}
}
