{
  "type": "Feature",
  "properties": {
    "iso:country":"GB",
    "wof:name":"DL13 5EF",
    "wof:placetype":"postalcode"
},
  "geometry": {"coordinates":[-1.81046714117434,54.61236953212523],"type":"Point"}
}