{
  "type": "Feature",
  "properties": {
    "iso:country":"GB",
    "wof:name":"SY16 3NG",
    "wof:placetype":"postalcode"
},
  "geometry": {"coordinates":[-3.33256863343629,52.60045192764638],"type":"Point"}
}