{
  "type": "Feature",
  "properties": {
    "iso:country":"GB",
    "wof:name":"AB11 8TE",
    "wof:placetype":"postalcode"
},
  "geometry": {"coordinates":[-2.07222957404189,57.13553717192032],"type":"Point"}
}