{
  "type": "Feature",
  "properties": {
    "iso:country":"GB",
    "wof:name":"KA11 1ER",
    "wof:placetype":"postalcode"
},
  "geometry": {"coordinates":[-4.6266523290793,55.61665848172799],"type":"Point"}
}