{
  "type": "Feature",
  "properties": {
    "iso:country": "GB",
    "wof:name": "MK3 7NJ",
    "wof:placetype": "postalcode"
  },
  "geometry": {"coordinates":[-0.751012,52.005785],"type":"Point"}
}
