{
  "type": "Feature",
  "properties": {
    "iso:country": "GB",
    "wof:name": "NE31 1HD",
    "wof:placetype": "postalcode"
  },
  "geometry": {"coordinates":[-1.508867,54.978121],"type":"Point"}
}
