{
  "type": "Feature",
  "properties": {
    "iso:country": "GB",
    "wof:name": "LN11 9BJ",
    "wof:placetype": "postalcode"
  },
  "geometry": {"coordinates":[-0.001146,53.366741],"type":"Point"}
}
