{
  "type": "Feature",
  "properties": {
    "iso:country":"GB",
    "wof:name":"ME8 7DQ",
    "wof:placetype":"postalcode"
},
  "geometry": {"coordinates":[0.60322017285878,51.36910211681987],"type":"Point"}
}