{
  "type": "Feature",
  "properties": {
    "date:inception_lower": "2008-12-01",
    "date:inception_upper": "2008-12-01",
    "iso:country": "GB",
    "wof:name": "SL1 1SU",
    "wof:placetype": "postalcode"
  },
  "geometry": {"coordinates":[-0.579629,51.508284],"type":"Point"}
}
