{
  "type": "Feature",
  "properties": {
    "iso:country":"GB",
    "wof:name":"SL1 1SU",
    "wof:placetype":"postalcode"
},
  "geometry": {"coordinates":[-0.57964679731977,51.5082827234446],"type":"Point"}
}