{
  "type": "Feature",
  "properties": {
    "date:inception_lower": "1980-01-01",
    "date:inception_upper": "1980-01-01",
    "iso:country": "GB",
    "wof:name": "CB3 9EX",
    "wof:placetype": "postalcode"
  },
  "geometry": {"coordinates":[0.113555,52.200071],"type":"Point"}
}
