{
  "type": "Feature",
  "properties": {
    "iso:country":"GB",
    "wof:name":"CB3 9EX",
    "wof:placetype":"postalcode"
},
  "geometry": {"coordinates":[0.11355479832988,52.20007124666365],"type":"Point"}
}