{
  "type": "Feature",
  "properties": {
    "iso:country": "GB",
    "wof:name": "EH48 2GE",
    "wof:placetype": "postalcode"
  },
  "geometry": {"coordinates":[-3.686313,55.897839],"type":"Point"}
}
