{
  "type": "Feature",
  "properties": {
    "date:inception_lower":"2007-11-01",
    "date:inception_upper":"2007-11-30",
    "iso:country":"GB",
    "wof:name":"EH48 2GE",
    "wof:placetype":"postalcode"
},
  "geometry": {"coordinates":[-3.686313,55.897839],"type":"Point"}
}