{
  "type": "Feature",
  "properties": {
    "iso:country":"GB",
    "wof:name":"SA4 4XJ",
    "wof:placetype":"postalcode"
},
  "geometry": {"coordinates":[-4.04993083058789,51.67282298388733],"type":"Point"}
}