{
  "type": "Feature",
  "properties": {
    "iso:country":"GB",
    "wof:name":"TR14 0PA",
    "wof:placetype":"postalcode"
},
  "geometry": {"coordinates":[-5.31697300558111,50.15394750101758],"type":"Point"}
}