{
  "type": "Feature",
  "properties": {
    "date:inception_lower": "1980-01-01",
    "date:inception_upper": "1980-01-01",
    "iso:country": "GB",
    "wof:name": "TR14 0PA",
    "wof:placetype": "postalcode"
  },
  "geometry": {"coordinates":[-5.316973,50.153948],"type":"Point"}
}
