{
  "type": "Feature",
  "properties": {
    "date:inception_lower": "1980-01-01",
    "date:inception_upper": "1980-01-01",
    "iso:country": "GB",
    "wof:name": "BS21 7LW",
    "wof:placetype": "postalcode"
  },
  "geometry": {"coordinates":[-2.850578,51.439297],"type":"Point"}
}
