{
  "type": "Feature",
  "properties": {
    "iso:country":"GB",
    "wof:name":"BS21 7LW",
    "wof:placetype":"postalcode"
},
  "geometry": {"coordinates":[-2.85057803886877,51.43929686626767],"type":"Point"}
}