{
  "type": "Feature",
  "properties": {
    "iso:country":"GB",
    "wof:name":"DH7 9NP",
    "wof:placetype":"postalcode"
},
  "geometry": {"coordinates":[-1.7022395995107,54.77127866767567],"type":"Point"}
}