{
  "type": "Feature",
  "properties": {
    "date:inception_lower":"2007-07-01",
    "date:inception_upper":"2007-07-31",
    "iso:country":"GB",
    "wof:name":"BS16 9QY",
    "wof:placetype":"postalcode"
},
  "geometry": {"coordinates":[-2.485257,51.473254],"type":"Point"}
}