{
  "type": "Feature",
  "properties": {
    "iso:country":"GB",
    "wof:name":"BS16 9QY",
    "wof:placetype":"postalcode"
},
  "geometry": {"coordinates":[-2.48525685554749,51.47325419935407],"type":"Point"}
}