{
  "type": "Feature",
  "properties": {
    "iso:country": "GB",
    "wof:name": "BS16 9QY",
    "wof:placetype": "postalcode"
  },
  "geometry": {"coordinates":[-2.485257,51.473254],"type":"Point"}
}
