{
  "type": "Feature",
  "properties": {
    "iso:country":"GB",
    "wof:name":"SM6 0RW",
    "wof:placetype":"postalcode"
},
  "geometry": {"coordinates":[-0.15274296819438,51.35039703113473],"type":"Point"}
}