{
  "type": "Feature",
  "properties": {
    "date:inception_lower": "2017-05-01",
    "date:inception_upper": "2017-05-01",
    "iso:country": "GB",
    "wof:name": "SE10 9FU",
    "wof:placetype": "postalcode"
  },
  "geometry": {"coordinates":[-0.012616,51.48126],"type":"Point"}
}
