{
  "type": "Feature",
  "properties": {
    "iso:country": "GB",
    "wof:name": "NN14 1NL",
    "wof:placetype": "postalcode"
  },
  "geometry": {"coordinates":[-0.77213,52.37796],"type":"Point"}
}
