{
  "type": "Feature",
  "properties": {
    "iso:country":"GB",
    "wof:name":"NN14 1NL",
    "wof:placetype":"postalcode"
},
  "geometry": {"coordinates":[-0.77213023666497,52.37796032978742],"type":"Point"}
}