{
  "type": "Feature",
  "properties": {
    "iso:country":"GB",
    "wof:name":"PL17 8HG",
    "wof:placetype":"postalcode"
},
  "geometry": {"coordinates":[-4.31171069811787,50.52946571290155],"type":"Point"}
}