{
  "type": "Feature",
  "properties": {
    "date:inception_lower": "1980-01-01",
    "date:inception_upper": "1980-01-01",
    "iso:country": "GB",
    "wof:name": "PL17 8HG",
    "wof:placetype": "postalcode"
  },
  "geometry": {"coordinates":[-4.311711,50.529466],"type":"Point"}
}
