{
  "type": "Feature",
  "properties": {
    "iso:country":"GB",
    "wof:name":"W4 4AD",
    "wof:placetype":"postalcode"
},
  "geometry": {"coordinates":[-0.27827827238498,51.49026312508583],"type":"Point"}
}