{
  "type": "Feature",
  "properties": {
    "iso:country":"GB",
    "wof:name":"ML11 8LL",
    "wof:placetype":"postalcode"
},
  "geometry": {"coordinates":[-3.60126702956439,55.75235532902341],"type":"Point"}
}