{
  "type": "Feature",
  "properties": {
    "iso:country": "GB",
    "wof:name": "ML11 8LL",
    "wof:placetype": "postalcode"
  },
  "geometry": {"coordinates":[-3.602026,55.752352],"type":"Point"}
}
