{
  "type": "Feature",
  "properties": {
    "iso:country":"GB",
    "wof:name":"DD4 8RW",
    "wof:placetype":"postalcode"
},
  "geometry": {"coordinates":[-2.91010016105228,56.4810259093361],"type":"Point"}
}