{
  "type": "Feature",
  "properties": {
    "iso:country": "GB",
    "wof:name": "BB3 1QS",
    "wof:placetype": "postalcode"
  },
  "geometry": {"coordinates":[-2.479175,53.704549],"type":"Point"}
}
