{
  "type": "Feature",
  "properties": {
    "date:inception_lower": "2000-10-01",
    "date:inception_upper": "2000-10-01",
    "iso:country": "GB",
    "wof:name": "W1T 4JE",
    "wof:placetype": "postalcode"
  },
  "geometry": {"coordinates":[-0.13801,51.520196],"type":"Point"}
}
