{
  "type": "Feature",
  "properties": {
    "iso:country":"GB",
    "wof:name":"M11 4WE",
    "wof:placetype":"postalcode"
},
  "geometry": {"coordinates":[-2.1789749924555,53.48485544220378],"type":"Point"}
}