{
  "type": "Feature",
  "properties": {
    "iso:country": "GB",
    "wof:name": "M11 4WE",
    "wof:placetype": "postalcode"
  },
  "geometry": {"coordinates":[-2.178748,53.484971],"type":"Point"}
}
