{
  "type": "Feature",
  "properties": {
    "iso:country":"GB",
    "wof:name":"DH4 6LN",
    "wof:placetype":"postalcode"
},
  "geometry": {"coordinates":[-1.4980913253815,54.84227410465337],"type":"Point"}
}