{
  "type": "Feature",
  "properties": {
    "iso:country": "GB",
    "wof:name": "WV14 6AP",
    "wof:placetype": "postalcode"
  },
  "geometry": {"coordinates":[-2.077826,52.568289],"type":"Point"}
}
