{
  "type": "Feature",
  "properties": {
    "iso:country":"GB",
    "wof:name":"WS13 7LE",
    "wof:placetype":"postalcode"
},
  "geometry": {"coordinates":[-1.83263292881167,52.68531536659636],"type":"Point"}
}