{
  "type": "Feature",
  "properties": {
    "iso:country":"GB",
    "wof:name":"SG17 5YS",
    "wof:placetype":"postalcode"
},
  "geometry": {"coordinates":[-0.33845373897499,52.03516141855923],"type":"Point"}
}