{
  "type": "Feature",
  "properties": {
    "date:inception_lower":"2002-06-01",
    "date:inception_upper":"2002-06-30",
    "iso:country":"GB",
    "wof:name":"SG17 5YS",
    "wof:placetype":"postalcode"
},
  "geometry": {"coordinates":[-0.338454,52.035161],"type":"Point"}
}