{
  "type": "Feature",
  "properties": {
    "iso:country":"GB",
    "wof:name":"SG4 7LR",
    "wof:placetype":"postalcode"
},
  "geometry": {"coordinates":[-0.20783217456822,51.93647740545588],"type":"Point"}
}