{
  "type": "Feature",
  "properties": {
    "iso:country": "GB",
    "wof:name": "SG4 7LR",
    "wof:placetype": "postalcode"
  },
  "geometry": {"coordinates":[-0.207795,51.936458],"type":"Point"}
}
