{
  "type": "Feature",
  "properties": {
    "date:inception_lower":"1995-01-01",
    "date:inception_upper":"1995-01-31",
    "iso:country":"GB",
    "wof:name":"TQ12 3BW",
    "wof:placetype":"postalcode"
},
  "geometry": {"coordinates":[-3.595016,50.54457],"type":"Point"}
}