{
  "type": "Feature",
  "properties": {
    "iso:country": "GB",
    "wof:name": "TQ12 3BW",
    "wof:placetype": "postalcode"
  },
  "geometry": {"coordinates":[-3.595016,50.54457],"type":"Point"}
}
