{
  "type": "Feature",
  "properties": {
    "date:inception_lower": "1980-01-01",
    "date:inception_upper": "1980-01-01",
    "iso:country": "GB",
    "wof:name": "CF35 5EW",
    "wof:placetype": "postalcode"
  },
  "geometry": {"coordinates":[-3.533978,51.503114],"type":"Point"}
}
