{
  "type": "Feature",
  "properties": {
    "iso:country":"GB",
    "wof:name":"CF35 5EW",
    "wof:placetype":"postalcode"
},
  "geometry": {"coordinates":[-3.53396385070765,51.5031223571816],"type":"Point"}
}