{
  "type": "Feature",
  "properties": {
    "iso:country":"GB",
    "wof:name":"WD5 0HE",
    "wof:placetype":"postalcode"
},
  "geometry": {"coordinates":[-0.43064743604152,51.69848157715297],"type":"Point"}
}