{
  "type": "Feature",
  "properties": {
    "iso:country":"GB",
    "wof:name":"HU9 1NQ",
    "wof:placetype":"postalcode"
},
  "geometry": {"coordinates":[-0.31059955824264,53.74768659846472],"type":"Point"}
}