{
  "type": "Feature",
  "properties": {
    "iso:country": "GB",
    "wof:name": "PO7 7XY",
    "wof:placetype": "postalcode"
  },
  "geometry": {"coordinates":[-1.039642,50.882902],"type":"Point"}
}
