{
  "type": "Feature",
  "properties": {
    "date:inception_lower":"1980-01-01",
    "date:inception_upper":"1980-01-31",
    "iso:country":"GB",
    "wof:name":"SA72 6DA",
    "wof:placetype":"postalcode"
},
  "geometry": {"coordinates":[-4.941104,51.694401],"type":"Point"}
}