{
  "type": "Feature",
  "properties": {
    "iso:country":"GB",
    "wof:name":"KA15 2LP",
    "wof:placetype":"postalcode"
},
  "geometry": {"coordinates":[-4.57484186339754,55.75600900970696],"type":"Point"}
}