{
  "type": "Feature",
  "properties": {
    "iso:country":"GB",
    "wof:name":"B30 1HD",
    "wof:placetype":"postalcode"
},
  "geometry": {"coordinates":[-1.94930040036313,52.41988927921103],"type":"Point"}
}