{
  "type": "Feature",
  "properties": {
    "date:inception_lower":"1980-01-01",
    "date:inception_upper":"1980-01-31",
    "iso:country":"GB",
    "wof:name":"B30 1HD",
    "wof:placetype":"postalcode"
},
  "geometry": {"coordinates":[-1.9493,52.419889],"type":"Point"}
}