{
  "type": "Feature",
  "properties": {
    "iso:country": "GB",
    "wof:name": "B30 1HD",
    "wof:placetype": "postalcode"
  },
  "geometry": {"coordinates":[-1.9493,52.419889],"type":"Point"}
}
