{
  "type": "Feature",
  "properties": {
    "iso:country":"GB",
    "wof:name":"IG11 9TD",
    "wof:placetype":"postalcode"
},
  "geometry": {"coordinates":[0.08526546753378,51.53966733846702],"type":"Point"}
}