{
  "type": "Feature",
  "properties": {
    "iso:country":"GB",
    "wof:name":"RH8 9LE",
    "wof:placetype":"postalcode"
},
  "geometry": {"coordinates":[-0.01116693621411,51.25727689320998],"type":"Point"}
}