{
  "type": "Feature",
  "properties": {
    "iso:country":"GB",
    "wof:name":"ME14 4RG",
    "wof:placetype":"postalcode"
},
  "geometry": {"coordinates":[0.56743031835373,51.27534136293252],"type":"Point"}
}