{
  "type": "Feature",
  "properties": {
    "iso:country":"GB",
    "wof:name":"CM20 3HZ",
    "wof:placetype":"postalcode"
},
  "geometry": {"coordinates":[0.11996295657637,51.76985941748839],"type":"Point"}
}