{
  "type": "Feature",
  "properties": {
    "iso:country":"GB",
    "wof:name":"B21 0TJ",
    "wof:placetype":"postalcode"
},
  "geometry": {"coordinates":[-1.93679079078979,52.49995712231841],"type":"Point"}
}