{
  "type": "Feature",
  "properties": {
    "iso:country": "GB",
    "wof:name": "CH4 0BR",
    "wof:placetype": "postalcode"
  },
  "geometry": {"coordinates":[-2.948738,53.181223],"type":"Point"}
}
