{
  "type": "Feature",
  "properties": {
    "iso:country":"GB",
    "wof:name":"CH4 0BR",
    "wof:placetype":"postalcode"
},
  "geometry": {"coordinates":[-2.94873812831316,53.18122276913951],"type":"Point"}
}