{
  "type": "Feature",
  "properties": {
    "iso:country":"GB",
    "wof:name":"YO25 3TN",
    "wof:placetype":"postalcode"
},
  "geometry": {"coordinates":[-0.45871259562526,54.08898170841256],"type":"Point"}
}