{
  "type": "Feature",
  "properties": {
    "iso:country": "GB",
    "wof:name": "YO25 3TN",
    "wof:placetype": "postalcode"
  },
  "geometry": {"coordinates":[-0.458309,54.088663],"type":"Point"}
}
