{
  "type": "Feature",
  "properties": {
    "iso:country":"GB",
    "wof:name":"HG3 2PX",
    "wof:placetype":"postalcode"
},
  "geometry": {"coordinates":[-1.6827462862849,54.03025244420166],"type":"Point"}
}