{
  "type": "Feature",
  "properties": {
    "date:inception_lower": "1980-01-01",
    "date:inception_upper": "1980-01-01",
    "iso:country": "GB",
    "wof:name": "HG3 2PX",
    "wof:placetype": "postalcode"
  },
  "geometry": {"coordinates":[-1.682746,54.030252],"type":"Point"}
}
