{
  "type": "Feature",
  "properties": {
    "date:inception_lower": "2013-07-01",
    "date:inception_upper": "2013-07-01",
    "iso:country": "GB",
    "wof:name": "ST2 0GA",
    "wof:placetype": "postalcode"
  },
  "geometry": {"coordinates":[-2.114816,53.00745],"type":"Point"}
}
