{
  "type": "Feature",
  "properties": {
    "iso:country":"GB",
    "wof:name":"ST2 0GA",
    "wof:placetype":"postalcode"
},
  "geometry": {"coordinates":[-2.11481595281149,53.00744962182366],"type":"Point"}
}