{
  "type": "Feature",
  "properties": {
    "iso:country": "GB",
    "wof:name": "ST2 0GA",
    "wof:placetype": "postalcode"
  },
  "geometry": {"coordinates":[-2.114816,53.00745],"type":"Point"}
}
