{
  "type": "Feature",
  "properties": {
    "iso:country":"GB",
    "wof:name":"KA18 2RY",
    "wof:placetype":"postalcode"
},
  "geometry": {"coordinates":[-4.34973608331444,55.43898513438011],"type":"Point"}
}