{
  "type": "Feature",
  "properties": {
    "iso:country":"GB",
    "wof:name":"PE14 7EB",
    "wof:placetype":"postalcode"
},
  "geometry": {"coordinates":[0.20467334796192,52.6969850921897],"type":"Point"}
}