{
  "type": "Feature",
  "properties": {
    "iso:country": "GB",
    "wof:name": "PE14 7EB",
    "wof:placetype": "postalcode"
  },
  "geometry": {"coordinates":[0.20498,52.696631],"type":"Point"}
}
