{
  "type": "Feature",
  "properties": {
    "iso:country":"GB",
    "wof:name":"OX18 2JR",
    "wof:placetype":"postalcode"
},
  "geometry": {"coordinates":[-1.54164889171785,51.72653472241908],"type":"Point"}
}