{
  "type": "Feature",
  "properties": {
    "date:inception_lower": "1991-09-01",
    "date:inception_upper": "1991-09-01",
    "iso:country": "GB",
    "wof:name": "OX18 2JR",
    "wof:placetype": "postalcode"
  },
  "geometry": {"coordinates":[-1.541634,51.726539],"type":"Point"}
}
