{
  "type": "Feature",
  "properties": {
    "iso:country": "GB",
    "wof:name": "DN36 5FP",
    "wof:placetype": "postalcode"
  },
  "geometry": {"coordinates":[-0.065408,53.512204],"type":"Point"}
}
