{
  "type": "Feature",
  "properties": {
    "iso:country":"GB",
    "wof:name":"SE6 2RE",
    "wof:placetype":"postalcode"
},
  "geometry": {"coordinates":[-0.0158148152199,51.43270800749336],"type":"Point"}
}