{
  "type": "Feature",
  "properties": {
    "iso:country": "GB",
    "wof:name": "SE6 2RE",
    "wof:placetype": "postalcode"
  },
  "geometry": {"coordinates":[-0.015815,51.432708],"type":"Point"}
}
