{
  "type": "Feature",
  "properties": {
    "iso:country":"GB",
    "wof:name":"CH7 4TB",
    "wof:placetype":"postalcode"
},
  "geometry": {"coordinates":[-3.19923063505449,53.10225646136379],"type":"Point"}
}