{
  "type": "Feature",
  "properties": {
    "date:inception_lower": "1992-08-01",
    "date:inception_upper": "1992-08-01",
    "iso:country": "GB",
    "wof:name": "CH7 4TB",
    "wof:placetype": "postalcode"
  },
  "geometry": {"coordinates":[-3.199231,53.102256],"type":"Point"}
}
