{
  "type": "Feature",
  "properties": {
    "iso:country":"GB",
    "wof:name":"WC2B 5TD",
    "wof:placetype":"postalcode"
},
  "geometry": {"coordinates":[-0.12174893648346,51.51464030880958],"type":"Point"}
}