{
  "type": "Feature",
  "properties": {
    "iso:country":"GB",
    "wof:name":"RM7 0DS",
    "wof:placetype":"postalcode"
},
  "geometry": {"coordinates":[0.15179617112924,51.56946395974456],"type":"Point"}
}