{
  "type": "Feature",
  "properties": {
    "iso:country": "GB",
    "wof:name": "RM7 0DS",
    "wof:placetype": "postalcode"
  },
  "geometry": {"coordinates":[0.15179,51.569367],"type":"Point"}
}
