{
  "type": "Feature",
  "properties": {
    "iso:country":"GB",
    "wof:name":"EH42 1XE",
    "wof:placetype":"postalcode"
},
  "geometry": {"coordinates":[-2.53809760557525,56.0038111427762],"type":"Point"}
}