{
  "type": "Feature",
  "properties": {
    "iso:country": "GB",
    "wof:name": "DE7 4SJ",
    "wof:placetype": "postalcode"
  },
  "geometry": {"coordinates":[-1.310489,52.955447],"type":"Point"}
}
