{
  "type": "Feature",
  "properties": {
    "iso:country":"GB",
    "wof:name":"RG40 3HT",
    "wof:placetype":"postalcode"
},
  "geometry": {"coordinates":[-0.84866735088883,51.38950743612271],"type":"Point"}
}