{
  "type": "Feature",
  "properties": {
    "date:inception_lower":"1995-07-01",
    "date:inception_upper":"1995-07-31",
    "iso:country":"GB",
    "wof:name":"RG40 3HT",
    "wof:placetype":"postalcode"
},
  "geometry": {"coordinates":[-0.848667,51.389507],"type":"Point"}
}