{
  "type": "Feature",
  "properties": {
    "iso:country": "GB",
    "wof:name": "RG40 3HT",
    "wof:placetype": "postalcode"
  },
  "geometry": {"coordinates":[-0.848667,51.389507],"type":"Point"}
}
