{
  "type": "Feature",
  "properties": {
    "iso:country": "GB",
    "wof:name": "SN6 6AE",
    "wof:placetype": "postalcode"
  },
  "geometry": {"coordinates":[-1.85646,51.640614],"type":"Point"}
}
