{
  "type": "Feature",
  "properties": {
    "iso:country":"GB",
    "wof:name":"SO50 4PR",
    "wof:placetype":"postalcode"
},
  "geometry": {"coordinates":[-1.35595569523006,50.98443313584182],"type":"Point"}
}