{
  "type": "Feature",
  "properties": {
    "iso:country":"GB",
    "wof:name":"M23 9GF",
    "wof:placetype":"postalcode"
},
  "geometry": {"coordinates":[-2.29152105890755,53.39108102362013],"type":"Point"}
}