{
  "type": "Feature",
  "properties": {
    "iso:country":"GB",
    "wof:name":"NW6 7DL",
    "wof:placetype":"postalcode"
},
  "geometry": {"coordinates":[-0.21704447768786,51.54451660495469],"type":"Point"}
}