{
  "type": "Feature",
  "properties": {
    "date:inception_lower": "1980-01-01",
    "date:inception_upper": "1980-01-01",
    "iso:country": "GB",
    "wof:name": "DN20 8RF",
    "wof:placetype": "postalcode"
  },
  "geometry": {"coordinates":[-0.471065,53.560875],"type":"Point"}
}
