{
  "type": "Feature",
  "properties": {
    "iso:country":"GB",
    "wof:name":"NR28 0NN",
    "wof:placetype":"postalcode"
},
  "geometry": {"coordinates":[1.34659875430482,52.84658523364531],"type":"Point"}
}