{
  "type": "Feature",
  "properties": {
    "iso:country":"GB",
    "wof:name":"AB38 9NT",
    "wof:placetype":"postalcode"
},
  "geometry": {"coordinates":[-3.29405328222215,57.43403204770143],"type":"Point"}
}