{
  "type": "Feature",
  "properties": {
    "date:inception_lower": "1990-08-01",
    "date:inception_upper": "1990-08-01",
    "iso:country": "GB",
    "wof:name": "AB38 9NT",
    "wof:placetype": "postalcode"
  },
  "geometry": {"coordinates":[-3.294053,57.434032],"type":"Point"}
}
