{
  "type": "Feature",
  "properties": {
    "iso:country": "GB",
    "wof:name": "AB38 9NT",
    "wof:placetype": "postalcode"
  },
  "geometry": {"coordinates":[-3.294053,57.434032],"type":"Point"}
}
