{
  "type": "Feature",
  "properties": {
    "iso:country": "GB",
    "wof:name": "IP7 7AG",
    "wof:placetype": "postalcode"
  },
  "geometry": {"coordinates":[0.854578,52.08174],"type":"Point"}
}
