{
  "type": "Feature",
  "properties": {
    "iso:country":"GB",
    "wof:name":"BD23 6PZ",
    "wof:placetype":"postalcode"
},
  "geometry": {"coordinates":[-1.99906446520096,53.975791686231],"type":"Point"}
}