{
  "type": "Feature",
  "properties": {
    "date:inception_lower": "1984-10-01",
    "date:inception_upper": "1984-10-01",
    "iso:country": "GB",
    "wof:name": "BD23 6PZ",
    "wof:placetype": "postalcode"
  },
  "geometry": {"coordinates":[-1.999064,53.975792],"type":"Point"}
}
