{
  "type": "Feature",
  "properties": {
    "iso:country": "GB",
    "wof:name": "L13 1DU",
    "wof:placetype": "postalcode"
  },
  "geometry": {"coordinates":[-2.917561,53.406903],"type":"Point"}
}
