{
  "type": "Feature",
  "properties": {
    "date:inception_lower":"1980-01-01",
    "date:inception_upper":"1980-01-31",
    "iso:country":"GB",
    "wof:name":"L13 1DU",
    "wof:placetype":"postalcode"
},
  "geometry": {"coordinates":[-2.917561,53.406903],"type":"Point"}
}