{
  "type": "Feature",
  "properties": {
    "iso:country":"GB",
    "wof:name":"TQ8 8AH",
    "wof:placetype":"postalcode"
},
  "geometry": {"coordinates":[-3.7750197560936,50.23772484451742],"type":"Point"}
}