{
  "type": "Feature",
  "properties": {
    "iso:country": "GB",
    "wof:name": "NG18 3AP",
    "wof:placetype": "postalcode"
  },
  "geometry": {"coordinates":[-1.174183,53.141448],"type":"Point"}
}
