{
  "type": "Feature",
  "properties": {
    "iso:country":"GB",
    "wof:name":"AB15 6FE",
    "wof:placetype":"postalcode"
},
  "geometry": {"coordinates":[-2.14658539855458,57.14244300600273],"type":"Point"}
}