{
  "type": "Feature",
  "properties": {
    "iso:country":"GB",
    "wof:name":"NN8 4QU",
    "wof:placetype":"postalcode"
},
  "geometry": {"coordinates":[-0.69565324168768,52.30746283391288],"type":"Point"}
}