{
  "type": "Feature",
  "properties": {
    "date:inception_lower": "1990-07-01",
    "date:inception_upper": "1990-07-01",
    "iso:country": "GB",
    "wof:name": "BN10 7SH",
    "wof:placetype": "postalcode"
  },
  "geometry": {"coordinates":[0.002431,50.803565],"type":"Point"}
}
