{
  "type": "Feature",
  "properties": {
    "date:inception_lower":"1980-01-01",
    "date:inception_upper":"1980-01-31",
    "iso:country":"GB",
    "wof:name":"LL11 2LA",
    "wof:placetype":"postalcode"
},
  "geometry": {"coordinates":[-3.001846,53.061778],"type":"Point"}
}