{
  "type": "Feature",
  "properties": {
    "iso:country":"GB",
    "wof:name":"LL11 2LA",
    "wof:placetype":"postalcode"
},
  "geometry": {"coordinates":[-3.00184565017109,53.06177768585948],"type":"Point"}
}