{
  "type": "Feature",
  "properties": {
    "date:inception_lower":"1980-01-01",
    "date:inception_upper":"1980-01-31",
    "iso:country":"GB",
    "wof:name":"OX17 1DG",
    "wof:placetype":"postalcode"
},
  "geometry": {"coordinates":[-1.405806,52.132752],"type":"Point"}
}