{
  "type": "Feature",
  "properties": {
    "iso:country":"GB",
    "wof:name":"OX17 1DG",
    "wof:placetype":"postalcode"
},
  "geometry": {"coordinates":[-1.40581893106786,52.13273880895076],"type":"Point"}
}