{
  "type": "Feature",
  "properties": {
    "date:inception_lower": "1980-01-01",
    "date:inception_upper": "1980-01-01",
    "iso:country": "GB",
    "wof:name": "OX17 1DG",
    "wof:placetype": "postalcode"
  },
  "geometry": {"coordinates":[-1.405574,52.13258],"type":"Point"}
}
