{
  "type": "Feature",
  "properties": {
    "date:inception_lower": "1980-01-01",
    "date:inception_upper": "1980-01-01",
    "iso:country": "GB",
    "wof:name": "PE11 2XJ",
    "wof:placetype": "postalcode"
  },
  "geometry": {"coordinates":[-0.153448,52.785994],"type":"Point"}
}
