{
  "type": "Feature",
  "properties": {
    "date:inception_lower":"1980-01-01",
    "date:inception_upper":"1980-01-31",
    "iso:country":"GB",
    "wof:name":"BB6 8DT",
    "wof:placetype":"postalcode"
},
  "geometry": {"coordinates":[-2.443095,53.798469],"type":"Point"}
}