{
  "type": "Feature",
  "properties": {
    "iso:country": "GB",
    "wof:name": "WA5 2QF",
    "wof:placetype": "postalcode"
  },
  "geometry": {"coordinates":[-2.65915,53.384949],"type":"Point"}
}
