{
  "type": "Feature",
  "properties": {
    "iso:country":"GB",
    "wof:name":"HP7 0DS",
    "wof:placetype":"postalcode"
},
  "geometry": {"coordinates":[-0.62029110912127,51.66716046642077],"type":"Point"}
}