{
  "type": "Feature",
  "properties": {
    "date:inception_lower": "2020-04-01",
    "date:inception_upper": "2020-04-01",
    "iso:country": "GB",
    "wof:name": "CW11 3TQ",
    "wof:placetype": "postalcode"
  },
  "geometry": {"coordinates":[-2.404059,53.162723],"type":"Point"}
}
