{
  "type": "Feature",
  "properties": {
    "date:inception_lower": "1991-09-01",
    "date:inception_upper": "1991-09-01",
    "iso:country": "GB",
    "wof:name": "OX20 1XA",
    "wof:placetype": "postalcode"
  },
  "geometry": {"coordinates":[-1.347201,51.834427],"type":"Point"}
}
