{
  "type": "Feature",
  "properties": {
    "iso:country": "GB",
    "wof:name": "OX20 1XA",
    "wof:placetype": "postalcode"
  },
  "geometry": {"coordinates":[-1.347201,51.834427],"type":"Point"}
}
