{
  "type": "Feature",
  "properties": {
    "iso:country": "GB",
    "wof:name": "TR26 1EQ",
    "wof:placetype": "postalcode"
  },
  "geometry": {"coordinates":[-5.48865,50.211914],"type":"Point"}
}
