{
  "type": "Feature",
  "properties": {
    "iso:country":"GB",
    "wof:name":"TR26 1EQ",
    "wof:placetype":"postalcode"
},
  "geometry": {"coordinates":[-5.4886498021062,50.21191410653482],"type":"Point"}
}