{
  "type": "Feature",
  "properties": {
    "iso:country":"GB",
    "wof:name":"BR1 2LS",
    "wof:placetype":"postalcode"
},
  "geometry": {"coordinates":[0.05471765063929,51.39471183327412],"type":"Point"}
}