{
  "type": "Feature",
  "properties": {
    "iso:country":"GB",
    "wof:name":"EX19 8BG",
    "wof:placetype":"postalcode"
},
  "geometry": {"coordinates":[-4.03332760331918,50.85590403534222],"type":"Point"}
}