{
  "type": "Feature",
  "properties": {
    "iso:country": "GB",
    "wof:name": "CW12 3AS",
    "wof:placetype": "postalcode"
  },
  "geometry": {"coordinates":[-2.206998,53.158152],"type":"Point"}
}
