{
  "type": "Feature",
  "properties": {
    "iso:country":"GB",
    "wof:name":"CW12 3AS",
    "wof:placetype":"postalcode"
},
  "geometry": {"coordinates":[-2.20699806276475,53.15815204879367],"type":"Point"}
}