{
  "type": "Feature",
  "properties": {
    "date:inception_lower":"1980-01-01",
    "date:inception_upper":"1980-01-31",
    "iso:country":"GB",
    "wof:name":"NE66 3XQ",
    "wof:placetype":"postalcode"
},
  "geometry": {"coordinates":[-1.621653,55.500575],"type":"Point"}
}