{
  "type": "Feature",
  "properties": {
    "date:inception_lower": "1980-01-01",
    "date:inception_upper": "1980-01-01",
    "iso:country": "GB",
    "wof:name": "NE66 3XQ",
    "wof:placetype": "postalcode"
  },
  "geometry": {"coordinates":[-1.622898,55.49969],"type":"Point"}
}
