{
  "type": "Feature",
  "properties": {
    "iso:country":"GB",
    "wof:name":"NE66 3XQ",
    "wof:placetype":"postalcode"
},
  "geometry": {"coordinates":[-1.62165270001466,55.50057538275858],"type":"Point"}
}