{
  "type": "Feature",
  "properties": {
    "iso:country": "GB",
    "wof:name": "BA4 4HT",
    "wof:placetype": "postalcode"
  },
  "geometry": {"coordinates":[-2.539023,51.18244],"type":"Point"}
}
