{
  "type": "Feature",
  "properties": {
    "iso:country": "GB",
    "wof:name": "CT11 9FH",
    "wof:placetype": "postalcode"
  },
  "geometry": {"coordinates":[1.416628,51.335109],"type":"Point"}
}
