{
  "type": "Feature",
  "properties": {
    "iso:country":"GB",
    "wof:name":"CT11 9FH",
    "wof:placetype":"postalcode"
},
  "geometry": {"coordinates":[1.41662791489694,51.33510938288619],"type":"Point"}
}