{
  "type": "Feature",
  "properties": {
    "iso:country": "GB",
    "wof:name": "CV7 9EL",
    "wof:placetype": "postalcode"
  },
  "geometry": {"coordinates":[-1.476935,52.464234],"type":"Point"}
}
