{
  "type": "Feature",
  "properties": {
    "date:inception_lower": "1980-01-01",
    "date:inception_upper": "1980-01-01",
    "iso:country": "GB",
    "wof:name": "CV7 9EL",
    "wof:placetype": "postalcode"
  },
  "geometry": {"coordinates":[-1.477291,52.464613],"type":"Point"}
}
