{
  "type": "Feature",
  "properties": {
    "iso:country":"GB",
    "wof:name":"NW11 6ES",
    "wof:placetype":"postalcode"
},
  "geometry": {"coordinates":[-0.19675534642926,51.58384489218837],"type":"Point"}
}