{
  "type": "Feature",
  "properties": {
    "iso:country": "GB",
    "wof:name": "CF48 4NT",
    "wof:placetype": "postalcode"
  },
  "geometry": {"coordinates":[-3.341777,51.688868],"type":"Point"}
}
