{
  "type": "Feature",
  "properties": {
    "iso:country":"GB",
    "wof:name":"CF48 4NT",
    "wof:placetype":"postalcode"
},
  "geometry": {"coordinates":[-3.34177684965234,51.68886832607654],"type":"Point"}
}