{
  "type": "Feature",
  "properties": {
    "date:inception_lower": "1980-01-01",
    "date:inception_upper": "1980-01-01",
    "iso:country": "GB",
    "wof:name": "BD22 0QE",
    "wof:placetype": "postalcode"
  },
  "geometry": {"coordinates":[-1.99826,53.862896],"type":"Point"}
}
