{
  "type": "Feature",
  "properties": {
    "iso:country": "GB",
    "wof:name": "BD22 0QE",
    "wof:placetype": "postalcode"
  },
  "geometry": {"coordinates":[-1.99826,53.862896],"type":"Point"}
}
