{
  "type": "Feature",
  "properties": {
    "date:inception_lower": "1980-01-01",
    "date:inception_upper": "1980-01-01",
    "iso:country": "GB",
    "wof:name": "LA13 9DH",
    "wof:placetype": "postalcode"
  },
  "geometry": {"coordinates":[-3.201297,54.118349],"type":"Point"}
}
