{
  "type": "Feature",
  "properties": {
    "iso:country":"GB",
    "wof:name":"BB12 7AT",
    "wof:placetype":"postalcode"
},
  "geometry": {"coordinates":[-2.31561170543185,53.79648211271075],"type":"Point"}
}