{
  "type": "Feature",
  "properties": {
    "date:inception_lower": "1991-01-01",
    "date:inception_upper": "1991-01-01",
    "iso:country": "GB",
    "wof:name": "HP20 1JW",
    "wof:placetype": "postalcode"
  },
  "geometry": {"coordinates":[-0.7895,51.813574],"type":"Point"}
}
