{
  "type": "Feature",
  "properties": {
    "iso:country": "GB",
    "wof:name": "HP20 1JW",
    "wof:placetype": "postalcode"
  },
  "geometry": {"coordinates":[-0.7895,51.813574],"type":"Point"}
}
