{
  "type": "Feature",
  "properties": {
    "iso:country":"GB",
    "wof:name":"HP20 1JW",
    "wof:placetype":"postalcode"
},
  "geometry": {"coordinates":[-0.78949995038464,51.81357430671348],"type":"Point"}
}