{
  "type": "Feature",
  "properties": {
    "date:inception_lower": "2000-06-01",
    "date:inception_upper": "2000-06-01",
    "iso:country": "GB",
    "wof:name": "NP20 2DT",
    "wof:placetype": "postalcode"
  },
  "geometry": {"coordinates":[-2.988626,51.577748],"type":"Point"}
}
