{
  "type": "Feature",
  "properties": {
    "iso:country":"GB",
    "wof:name":"NP20 2DT",
    "wof:placetype":"postalcode"
},
  "geometry": {"coordinates":[-2.98862607911323,51.57774766786893],"type":"Point"}
}