{
  "type": "Feature",
  "properties": {
    "date:inception_lower": "1995-01-01",
    "date:inception_upper": "1995-01-01",
    "iso:country": "GB",
    "wof:name": "PR5 4LZ",
    "wof:placetype": "postalcode"
  },
  "geometry": {"coordinates":[-2.665318,53.739073],"type":"Point"}
}
