{
  "type": "Feature",
  "properties": {
    "iso:country":"GB",
    "wof:name":"PR5 4LZ",
    "wof:placetype":"postalcode"
},
  "geometry": {"coordinates":[-2.66531767702543,53.73907276374604],"type":"Point"}
}