{
  "type": "Feature",
  "properties": {
    "date:inception_lower": "2017-05-01",
    "date:inception_upper": "2017-05-01",
    "iso:country": "GB",
    "wof:name": "EX17 6FL",
    "wof:placetype": "postalcode"
  },
  "geometry": {"coordinates":[-3.744885,50.846681],"type":"Point"}
}
