{
  "type": "Feature",
  "properties": {
    "iso:country":"GB",
    "wof:name":"BA4 6TW",
    "wof:placetype":"postalcode"
},
  "geometry": {"coordinates":[-2.56217121964928,51.13650708668734],"type":"Point"}
}