{
  "type": "Feature",
  "properties": {
    "iso:country":"GB",
    "wof:name":"WF1 4RL",
    "wof:placetype":"postalcode"
},
  "geometry": {"coordinates":[-1.47904824741982,53.68846723634562],"type":"Point"}
}