{
  "type": "Feature",
  "properties": {
    "iso:country": "GB",
    "wof:name": "KY14 7DH",
    "wof:placetype": "postalcode"
  },
  "geometry": {"coordinates":[-3.228369,56.291228],"type":"Point"}
}
