{
  "type": "Feature",
  "properties": {
    "date:inception_lower": "1980-01-01",
    "date:inception_upper": "1980-01-01",
    "iso:country": "GB",
    "wof:name": "EH15 2LF",
    "wof:placetype": "postalcode"
  },
  "geometry": {"coordinates":[-3.087244,55.946917],"type":"Point"}
}
