{
  "type": "Feature",
  "properties": {
    "iso:country":"GB",
    "wof:name":"RG22 6HZ",
    "wof:placetype":"postalcode"
},
  "geometry": {"coordinates":[-1.11289317750258,51.26312995175331],"type":"Point"}
}