{
  "type": "Feature",
  "properties": {
    "iso:country":"GB",
    "wof:name":"SS9 1LE",
    "wof:placetype":"postalcode"
},
  "geometry": {"coordinates":[0.6724015441463,51.5439914285589],"type":"Point"}
}