{
  "type": "Feature",
  "properties": {
    "iso:country": "GB",
    "wof:name": "NN14 4AB",
    "wof:placetype": "postalcode"
  },
  "geometry": {"coordinates":[-0.643257,52.383321],"type":"Point"}
}
