{
  "type": "Feature",
  "properties": {
    "date:inception_lower": "1980-01-01",
    "date:inception_upper": "1980-01-01",
    "iso:country": "GB",
    "wof:name": "MK19 7LZ",
    "wof:placetype": "postalcode"
  },
  "geometry": {"coordinates":[-0.830273,52.117431],"type":"Point"}
}
