{
  "type": "Feature",
  "properties": {
    "iso:country":"GB",
    "wof:name":"NE65 7QR",
    "wof:placetype":"postalcode"
},
  "geometry": {"coordinates":[-1.909424522039,55.30712743011416],"type":"Point"}
}