{
  "type": "Feature",
  "properties": {
    "date:inception_lower": "2007-07-01",
    "date:inception_upper": "2007-07-01",
    "iso:country": "GB",
    "wof:name": "HU14 3BJ",
    "wof:placetype": "postalcode"
  },
  "geometry": {"coordinates":[-0.493183,53.73902],"type":"Point"}
}
