{
  "type": "Feature",
  "properties": {
    "iso:country":"GB",
    "wof:name":"CA7 3SX",
    "wof:placetype":"postalcode"
},
  "geometry": {"coordinates":[-3.29486582536339,54.77240500157185],"type":"Point"}
}