{
  "type": "Feature",
  "properties": {
    "iso:country": "GB",
    "wof:name": "CA7 3SX",
    "wof:placetype": "postalcode"
  },
  "geometry": {"coordinates":[-3.294866,54.772405],"type":"Point"}
}
