{
  "type": "Feature",
  "properties": {
    "date:inception_lower":"2000-06-01",
    "date:inception_upper":"2000-06-30",
    "iso:country":"GB",
    "wof:name":"CA7 3SX",
    "wof:placetype":"postalcode"
},
  "geometry": {"coordinates":[-3.294866,54.772405],"type":"Point"}
}