{
  "type": "Feature",
  "properties": {
    "iso:country": "GB",
    "wof:name": "E9 5HF",
    "wof:placetype": "postalcode"
  },
  "geometry": {"coordinates":[-0.029804,51.545856],"type":"Point"}
}
