{
  "type": "Feature",
  "properties": {
    "iso:country":"GB",
    "wof:name":"TQ13 8DE",
    "wof:placetype":"postalcode"
},
  "geometry": {"coordinates":[-3.83140350513449,50.68724804881688],"type":"Point"}
}