{
  "type": "Feature",
  "properties": {
    "iso:country": "GB",
    "wof:name": "TQ13 8DE",
    "wof:placetype": "postalcode"
  },
  "geometry": {"coordinates":[-3.831223,50.687584],"type":"Point"}
}
