{
  "type": "Feature",
  "properties": {
    "date:inception_lower": "1980-01-01",
    "date:inception_upper": "1980-01-01",
    "iso:country": "GB",
    "wof:name": "TQ13 8DE",
    "wof:placetype": "postalcode"
  },
  "geometry": {"coordinates":[-3.831422,50.687239],"type":"Point"}
}
