{
  "type": "Feature",
  "properties": {
    "date:inception_lower": "1980-01-01",
    "date:inception_upper": "1980-01-01",
    "iso:country": "GB",
    "wof:name": "BN25 4AL",
    "wof:placetype": "postalcode"
  },
  "geometry": {"coordinates":[0.161177,50.77679],"type":"Point"}
}
