{
  "type": "Feature",
  "properties": {
    "date:inception_lower": "2022-02-01",
    "date:inception_upper": "2022-02-01",
    "iso:country": "GB",
    "wof:name": "CT3 2EH",
    "wof:placetype": "postalcode"
  },
  "geometry": {"coordinates":[1.278491,51.28347],"type":"Point"}
}
