{
  "type": "Feature",
  "properties": {
    "iso:country": "GB",
    "wof:name": "RG29 1BZ",
    "wof:placetype": "postalcode"
  },
  "geometry": {"coordinates":[-0.972671,51.255761],"type":"Point"}
}
