{
  "type": "Feature",
  "properties": {
    "iso:country":"GB",
    "wof:name":"SE7 7TS",
    "wof:placetype":"postalcode"
},
  "geometry": {"coordinates":[0.03242266910798,51.48062237320053],"type":"Point"}
}