{
  "type": "Feature",
  "properties": {
    "iso:country":"GB",
    "wof:name":"B73 5LW",
    "wof:placetype":"postalcode"
},
  "geometry": {"coordinates":[-1.838399170887,52.54149613298173],"type":"Point"}
}