{
  "type": "Feature",
  "properties": {
    "date:inception_lower":"1980-01-01",
    "date:inception_upper":"1980-01-31",
    "iso:country":"GB",
    "wof:name":"B73 5LW",
    "wof:placetype":"postalcode"
},
  "geometry": {"coordinates":[-1.838399,52.541496],"type":"Point"}
}