{
  "type": "Feature",
  "properties": {
    "iso:country":"GB",
    "wof:name":"RG9 6SR",
    "wof:placetype":"postalcode"
},
  "geometry": {"coordinates":[-0.88200280161089,51.60066215079905],"type":"Point"}
}