{
  "type": "Feature",
  "properties": {
    "date:inception_lower": "1980-01-01",
    "date:inception_upper": "1980-01-01",
    "iso:country": "GB",
    "wof:name": "PE12 9QQ",
    "wof:placetype": "postalcode"
  },
  "geometry": {"coordinates":[0.20097,52.798926],"type":"Point"}
}
