{
  "type": "Feature",
  "properties": {
    "iso:country":"GB",
    "wof:name":"PE12 9QQ",
    "wof:placetype":"postalcode"
},
  "geometry": {"coordinates":[0.20097038841546,52.7989255313861],"type":"Point"}
}