{
  "type": "Feature",
  "properties": {
    "date:inception_lower": "1987-04-01",
    "date:inception_upper": "1987-04-01",
    "iso:country": "GB",
    "wof:name": "GU14 9XA",
    "wof:placetype": "postalcode"
  },
  "geometry": {"coordinates":[-0.795374,51.297549],"type":"Point"}
}
