{
  "type": "Feature",
  "properties": {
    "iso:country": "GB",
    "wof:name": "GU14 9XA",
    "wof:placetype": "postalcode"
  },
  "geometry": {"coordinates":[-0.795374,51.297549],"type":"Point"}
}
