{
  "type": "Feature",
  "properties": {
    "iso:country":"GB",
    "wof:name":"GU14 9XA",
    "wof:placetype":"postalcode"
},
  "geometry": {"coordinates":[-0.79537401615881,51.29754871847719],"type":"Point"}
}