{
  "type": "Feature",
  "properties": {
    "iso:country": "GB",
    "wof:name": "WD17 2RB",
    "wof:placetype": "postalcode"
  },
  "geometry": {"coordinates":[-0.391352,51.657081],"type":"Point"}
}
