{
  "type": "Feature",
  "properties": {
    "iso:country":"GB",
    "wof:name":"WD17 2RB",
    "wof:placetype":"postalcode"
},
  "geometry": {"coordinates":[-0.39135201865358,51.65708142772804],"type":"Point"}
}