{
  "type": "Feature",
  "properties": {
    "iso:country":"GB",
    "wof:name":"EH5 1FT",
    "wof:placetype":"postalcode"
},
  "geometry": {"coordinates":[-3.22823193157614,55.98470624002847],"type":"Point"}
}