{
  "type": "Feature",
  "properties": {
    "iso:country": "GB",
    "wof:name": "S18 2XB",
    "wof:placetype": "postalcode"
  },
  "geometry": {"coordinates":[-1.46674,53.301098],"type":"Point"}
}
