{
  "type": "Feature",
  "properties": {
    "iso:country":"GB",
    "wof:name":"S18 2XB",
    "wof:placetype":"postalcode"
},
  "geometry": {"coordinates":[-1.46662161265987,53.30106100244536],"type":"Point"}
}