{
  "type": "Feature",
  "properties": {
    "iso:country":"GB",
    "wof:name":"LS10 4JX",
    "wof:placetype":"postalcode"
},
  "geometry": {"coordinates":[-1.55242322893953,53.74612613810454],"type":"Point"}
}