{
  "type": "Feature",
  "properties": {
    "date:inception_lower": "1980-01-01",
    "date:inception_upper": "1980-01-01",
    "iso:country": "GB",
    "wof:name": "LS10 4JX",
    "wof:placetype": "postalcode"
  },
  "geometry": {"coordinates":[-1.552423,53.746126],"type":"Point"}
}
