{
  "type": "Feature",
  "properties": {
    "iso:country": "GB",
    "wof:name": "LS10 4JX",
    "wof:placetype": "postalcode"
  },
  "geometry": {"coordinates":[-1.552423,53.746126],"type":"Point"}
}
