{
  "type": "Feature",
  "properties": {
    "iso:country": "GB",
    "wof:name": "DT9 5LP",
    "wof:placetype": "postalcode"
  },
  "geometry": {"coordinates":[-2.430674,50.900929],"type":"Point"}
}
