{
  "type": "Feature",
  "properties": {
    "iso:country":"GB",
    "wof:name":"BB9 9DU",
    "wof:placetype":"postalcode"
},
  "geometry": {"coordinates":[-2.2126333151712,53.83470117662359],"type":"Point"}
}