{
  "type": "Feature",
  "properties": {
    "iso:country":"GB",
    "wof:name":"NE46 4BY",
    "wof:placetype":"postalcode"
},
  "geometry": {"coordinates":[-2.17353146665309,55.06078771310064],"type":"Point"}
}