{
  "type": "Feature",
  "properties": {
    "iso:country": "GB",
    "wof:name": "NE46 4BY",
    "wof:placetype": "postalcode"
  },
  "geometry": {"coordinates":[-2.173531,55.060788],"type":"Point"}
}
