{
  "type": "Feature",
  "properties": {
    "date:inception_lower": "1980-01-01",
    "date:inception_upper": "1980-01-01",
    "iso:country": "GB",
    "wof:name": "BD11 2PA",
    "wof:placetype": "postalcode"
  },
  "geometry": {"coordinates":[-1.683716,53.74276],"type":"Point"}
}
