{
  "type": "Feature",
  "properties": {
    "iso:country":"GB",
    "wof:name":"BD11 2PA",
    "wof:placetype":"postalcode"
},
  "geometry": {"coordinates":[-1.68371611024794,53.74276021752948],"type":"Point"}
}