{
  "type": "Feature",
  "properties": {
    "iso:country":"GB",
    "wof:name":"BL7 0PB",
    "wof:placetype":"postalcode"
},
  "geometry": {"coordinates":[-2.39352435949828,53.64421728002059],"type":"Point"}
}