{
  "type": "Feature",
  "properties": {
    "date:inception_lower": "1981-06-01",
    "date:inception_upper": "1981-06-01",
    "iso:country": "GB",
    "wof:name": "BL7 0PB",
    "wof:placetype": "postalcode"
  },
  "geometry": {"coordinates":[-2.393524,53.644217],"type":"Point"}
}
