{
  "type": "Feature",
  "properties": {
    "iso:country":"GB",
    "wof:name":"RG27 0NL",
    "wof:placetype":"postalcode"
},
  "geometry": {"coordinates":[-0.86066798002446,51.34840512014289],"type":"Point"}
}