{
  "type": "Feature",
  "properties": {
    "iso:country":"GB",
    "wof:name":"CF39 0HR",
    "wof:placetype":"postalcode"
},
  "geometry": {"coordinates":[-3.40886392326972,51.62979754587025],"type":"Point"}
}