{
  "type": "Feature",
  "properties": {
    "date:inception_lower":"1980-01-01",
    "date:inception_upper":"1980-01-31",
    "iso:country":"GB",
    "wof:name":"BR5 2TJ",
    "wof:placetype":"postalcode"
},
  "geometry": {"coordinates":[0.095261,51.408032],"type":"Point"}
}