{
  "type": "Feature",
  "properties": {
    "iso:country": "GB",
    "wof:name": "CH66 7NH",
    "wof:placetype": "postalcode"
  },
  "geometry": {"coordinates":[-2.981133,53.295813],"type":"Point"}
}
