{
  "type": "Feature",
  "properties": {
    "date:inception_lower": "2019-06-01",
    "date:inception_upper": "2019-06-01",
    "iso:country": "GB",
    "wof:name": "CH66 7NH",
    "wof:placetype": "postalcode"
  },
  "geometry": {"coordinates":[-2.980313,53.295388],"type":"Point"}
}
