{
  "type": "Feature",
  "properties": {
    "iso:country":"GB",
    "wof:name":"CV22 6NQ",
    "wof:placetype":"postalcode"
},
  "geometry": {"coordinates":[-1.28760465151666,52.33637552049063],"type":"Point"}
}