{
  "type": "Feature",
  "properties": {
    "iso:country":"GB",
    "wof:name":"OX2 6DJ",
    "wof:placetype":"postalcode"
},
  "geometry": {"coordinates":[-1.26907031846606,51.76046474683766],"type":"Point"}
}