{
  "type": "Feature",
  "properties": {
    "date:inception_lower": "1990-02-01",
    "date:inception_upper": "1990-02-01",
    "iso:country": "GB",
    "wof:name": "MK5 8HG",
    "wof:placetype": "postalcode"
  },
  "geometry": {"coordinates":[-0.783305,52.028753],"type":"Point"}
}
