{
  "type": "Feature",
  "properties": {
    "iso:country":"GB",
    "wof:name":"NE15 7HB",
    "wof:placetype":"postalcode"
},
  "geometry": {"coordinates":[-1.69323417001844,54.97738594189246],"type":"Point"}
}