{
  "type": "Feature",
  "properties": {
    "iso:country":"GB",
    "wof:name":"IP17 1RF",
    "wof:placetype":"postalcode"
},
  "geometry": {"coordinates":[1.49439756920927,52.17239508583808],"type":"Point"}
}