{
  "type": "Feature",
  "properties": {
    "iso:country": "GB",
    "wof:name": "IP17 1RF",
    "wof:placetype": "postalcode"
  },
  "geometry": {"coordinates":[1.494398,52.172395],"type":"Point"}
}
