{
  "type": "Feature",
  "properties": {
    "iso:country":"GB",
    "wof:name":"HR6 8QZ",
    "wof:placetype":"postalcode"
},
  "geometry": {"coordinates":[-2.75095566215547,52.22575762395488],"type":"Point"}
}