{
  "type": "Feature",
  "properties": {
    "iso:country": "GB",
    "wof:name": "CF36 5SR",
    "wof:placetype": "postalcode"
  },
  "geometry": {"coordinates":[-3.670888,51.489759],"type":"Point"}
}
