{
  "type": "Feature",
  "properties": {
    "date:inception_lower": "1995-01-01",
    "date:inception_upper": "1995-01-01",
    "iso:country": "GB",
    "wof:name": "CF36 5SR",
    "wof:placetype": "postalcode"
  },
  "geometry": {"coordinates":[-3.670905,51.48976],"type":"Point"}
}
