{
  "type": "Feature",
  "properties": {
    "iso:country":"GB",
    "wof:name":"DL2 3XQ",
    "wof:placetype":"postalcode"
},
  "geometry": {"coordinates":[-1.73405585115746,54.57922649417392],"type":"Point"}
}