{
  "type": "Feature",
  "properties": {
    "iso:country": "GB",
    "wof:name": "DL2 3XQ",
    "wof:placetype": "postalcode"
  },
  "geometry": {"coordinates":[-1.734056,54.579226],"type":"Point"}
}
