{
  "type": "Feature",
  "properties": {
    "iso:country": "GB",
    "wof:name": "YO26 7SD",
    "wof:placetype": "postalcode"
  },
  "geometry": {"coordinates":[-1.291767,53.963495],"type":"Point"}
}
