{
  "type": "Feature",
  "properties": {
    "iso:country": "GB",
    "wof:name": "M3 7AS",
    "wof:placetype": "postalcode"
  },
  "geometry": {"coordinates":[-2.253279,53.489098],"type":"Point"}
}
