{
  "type": "Feature",
  "properties": {
    "iso:country": "GB",
    "wof:name": "TQ1 4TP",
    "wof:placetype": "postalcode"
  },
  "geometry": {"coordinates":[-3.516187,50.515446],"type":"Point"}
}
