{
  "type": "Feature",
  "properties": {
    "iso:country":"GB",
    "wof:name":"TQ1 4TP",
    "wof:placetype":"postalcode"
},
  "geometry": {"coordinates":[-3.51576401594724,50.51546468320949],"type":"Point"}
}