{
  "type": "Feature",
  "properties": {
    "iso:country":"GB",
    "wof:name":"PA3 3TQ",
    "wof:placetype":"postalcode"
},
  "geometry": {"coordinates":[-4.5083174483656,55.85430471038845],"type":"Point"}
}