{
  "type": "Feature",
  "properties": {
    "date:inception_lower":"1980-01-01",
    "date:inception_upper":"1980-01-31",
    "iso:country":"GB",
    "wof:name":"PA3 3TQ",
    "wof:placetype":"postalcode"
},
  "geometry": {"coordinates":[-4.508317,55.854305],"type":"Point"}
}