{
  "type": "Feature",
  "properties": {
    "iso:country":"GB",
    "wof:name":"SW11 5TU",
    "wof:placetype":"postalcode"
},
  "geometry": {"coordinates":[-0.15682980693022,51.46604372785001],"type":"Point"}
}