{
  "type": "Feature",
  "properties": {
    "iso:country": "GB",
    "wof:name": "ST10 2PH",
    "wof:placetype": "postalcode"
  },
  "geometry": {"coordinates":[-2.047774,52.986749],"type":"Point"}
}
