{
  "type": "Feature",
  "properties": {
    "iso:country":"GB",
    "wof:name":"ST10 2PH",
    "wof:placetype":"postalcode"
},
  "geometry": {"coordinates":[-2.04777438212968,52.98674859398294],"type":"Point"}
}