{
  "type": "Feature",
  "properties": {
    "iso:country": "GB",
    "wof:name": "ST10 2PH",
    "wof:placetype": "postalcode"
  },
  "geometry": {"coordinates":[-2.05577,52.985019],"type":"Point"}
}
