{
  "type": "Feature",
  "properties": {
    "iso:country":"GB",
    "wof:name":"CF23 6HQ",
    "wof:placetype":"postalcode"
},
  "geometry": {"coordinates":[-3.17097591877829,51.50962893825322],"type":"Point"}
}