{
  "type": "Feature",
  "properties": {
    "date:inception_lower": "1999-06-01",
    "date:inception_upper": "1999-06-01",
    "iso:country": "GB",
    "wof:name": "CF23 6HQ",
    "wof:placetype": "postalcode"
  },
  "geometry": {"coordinates":[-3.170976,51.509629],"type":"Point"}
}
