{
  "type": "Feature",
  "properties": {
    "date:inception_lower": "2012-12-01",
    "date:inception_upper": "2012-12-01",
    "iso:country": "GB",
    "wof:name": "ST6 6QP",
    "wof:placetype": "postalcode"
  },
  "geometry": {"coordinates":[-2.184969,53.074618],"type":"Point"}
}
