{
  "type": "Feature",
  "properties": {
    "iso:country":"GB",
    "wof:name":"ST6 6QP",
    "wof:placetype":"postalcode"
},
  "geometry": {"coordinates":[-2.18496872512312,53.07461760709403],"type":"Point"}
}