{
  "type": "Feature",
  "properties": {
    "iso:country":"GB",
    "wof:name":"W14 9BS",
    "wof:placetype":"postalcode"
},
  "geometry": {"coordinates":[-0.21022563690976,51.49187006218881],"type":"Point"}
}