{
  "type": "Feature",
  "properties": {
    "date:inception_lower":"1980-01-01",
    "date:inception_upper":"1980-01-31",
    "iso:country":"GB",
    "wof:name":"S10 1EN",
    "wof:placetype":"postalcode"
},
  "geometry": {"coordinates":[-1.495883,53.385008],"type":"Point"}
}