{
  "type": "Feature",
  "properties": {
    "iso:country":"GB",
    "wof:name":"S10 1EN",
    "wof:placetype":"postalcode"
},
  "geometry": {"coordinates":[-1.4958833512245,53.38500821426651],"type":"Point"}
}