{
  "type": "Feature",
  "properties": {
    "date:inception_lower": "1980-01-01",
    "date:inception_upper": "1980-01-01",
    "iso:country": "GB",
    "wof:name": "BR5 1RF",
    "wof:placetype": "postalcode"
  },
  "geometry": {"coordinates":[0.09538,51.391779],"type":"Point"}
}
