{
  "type": "Feature",
  "properties": {
    "iso:country": "GB",
    "wof:name": "BR5 1RF",
    "wof:placetype": "postalcode"
  },
  "geometry": {"coordinates":[0.09538,51.391779],"type":"Point"}
}
