{
  "type": "Feature",
  "properties": {
    "iso:country":"GB",
    "wof:name":"BR5 1RF",
    "wof:placetype":"postalcode"
},
  "geometry": {"coordinates":[0.09538029557466,51.39177940215608],"type":"Point"}
}