{
  "type": "Feature",
  "properties": {
    "iso:country":"GB",
    "wof:name":"NE66 3DH",
    "wof:placetype":"postalcode"
},
  "geometry": {"coordinates":[-1.62896979175188,55.5187214371709],"type":"Point"}
}