{
  "type": "Feature",
  "properties": {
    "date:inception_lower": "1988-03-01",
    "date:inception_upper": "1988-03-01",
    "iso:country": "GB",
    "wof:name": "NE66 3DH",
    "wof:placetype": "postalcode"
  },
  "geometry": {"coordinates":[-1.62897,55.518721],"type":"Point"}
}
