{
  "type": "Feature",
  "properties": {
    "iso:country":"GB",
    "wof:name":"LU4 8AJ",
    "wof:placetype":"postalcode"
},
  "geometry": {"coordinates":[-0.43584955756387,51.88688412774049],"type":"Point"}
}