{
  "type": "Feature",
  "properties": {
    "iso:country": "GB",
    "wof:name": "LU4 8AJ",
    "wof:placetype": "postalcode"
  },
  "geometry": {"coordinates":[-0.43585,51.886884],"type":"Point"}
}
