{
  "type": "Feature",
  "properties": {
    "iso:country":"GB",
    "wof:name":"LS29 9JP",
    "wof:placetype":"postalcode"
},
  "geometry": {"coordinates":[-1.81776635716055,53.92065792041586],"type":"Point"}
}