{
  "type": "Feature",
  "properties": {
    "iso:country":"GB",
    "wof:name":"IV40 8DR",
    "wof:placetype":"postalcode"
},
  "geometry": {"coordinates":[-5.52531599871165,57.28140143688331],"type":"Point"}
}