{
  "type": "Feature",
  "properties": {
    "iso:country": "GB",
    "wof:name": "IV40 8DR",
    "wof:placetype": "postalcode"
  },
  "geometry": {"coordinates":[-5.525363,57.281297],"type":"Point"}
}
