{
  "type": "Feature",
  "properties": {
    "date:inception_lower": "1998-12-01",
    "date:inception_upper": "1998-12-01",
    "iso:country": "GB",
    "wof:name": "IV40 8DR",
    "wof:placetype": "postalcode"
  },
  "geometry": {"coordinates":[-5.527885,57.281289],"type":"Point"}
}
