{
  "type": "Feature",
  "properties": {
    "iso:country":"GB",
    "wof:name":"CM8 3EB",
    "wof:placetype":"postalcode"
},
  "geometry": {"coordinates":[0.6882875571446,51.78439298400239],"type":"Point"}
}