{
  "type": "Feature",
  "properties": {
    "date:inception_lower":"2016-08-01",
    "date:inception_upper":"2016-08-31",
    "iso:country":"GB",
    "wof:name":"ML1 3RU",
    "wof:placetype":"postalcode"
},
  "geometry": {"coordinates":[-4.000157,55.783306],"type":"Point"}
}