{
  "type": "Feature",
  "properties": {
    "iso:country":"GB",
    "wof:name":"CW5 5TQ",
    "wof:placetype":"postalcode"
},
  "geometry": {"coordinates":[-2.52111477657337,53.07648721005757],"type":"Point"}
}