{
  "type": "Feature",
  "properties": {
    "date:inception_lower": "2022-05-01",
    "date:inception_upper": "2022-05-01",
    "iso:country": "GB",
    "wof:name": "TF2 8FD",
    "wof:placetype": "postalcode"
  },
  "geometry": {"coordinates":[-2.443605,52.717879],"type":"Point"}
}
