{
  "type": "Feature",
  "properties": {
    "iso:country": "GB",
    "wof:name": "DE45 1QJ",
    "wof:placetype": "postalcode"
  },
  "geometry": {"coordinates":[-1.706712,53.225191],"type":"Point"}
}
