{
  "type": "Feature",
  "properties": {
    "date:inception_lower":"1985-04-01",
    "date:inception_upper":"1985-04-30",
    "iso:country":"GB",
    "wof:name":"UB3 5EZ",
    "wof:placetype":"postalcode"
},
  "geometry": {"coordinates":[-0.435637,51.488026],"type":"Point"}
}