{
  "type": "Feature",
  "properties": {
    "iso:country": "GB",
    "wof:name": "FK4 1JF",
    "wof:placetype": "postalcode"
  },
  "geometry": {"coordinates":[-3.951489,55.990276],"type":"Point"}
}
