{
  "type": "Feature",
  "properties": {
    "iso:country":"GB",
    "wof:name":"FK4 1JF",
    "wof:placetype":"postalcode"
},
  "geometry": {"coordinates":[-3.95148893966181,55.99027591115492],"type":"Point"}
}