{
  "type": "Feature",
  "properties": {
    "iso:country":"GB",
    "wof:name":"B37 5BA",
    "wof:placetype":"postalcode"
},
  "geometry": {"coordinates":[-1.75784136804068,52.47846536958841],"type":"Point"}
}