{
  "type": "Feature",
  "properties": {
    "iso:country":"GB",
    "wof:name":"NP18 1BL",
    "wof:placetype":"postalcode"
},
  "geometry": {"coordinates":[-2.95160247404851,51.61122379428408],"type":"Point"}
}