{
  "type": "Feature",
  "properties": {
    "iso:country":"GB",
    "wof:name":"BD18 3BL",
    "wof:placetype":"postalcode"
},
  "geometry": {"coordinates":[-1.77576889630527,53.82165750802945],"type":"Point"}
}