{
  "type": "Feature",
  "properties": {
    "iso:country":"GB",
    "wof:name":"BH8 9NP",
    "wof:placetype":"postalcode"
},
  "geometry": {"coordinates":[-1.84222029522141,50.74737817460262],"type":"Point"}
}