{
  "type": "Feature",
  "properties": {
    "iso:country":"GB",
    "wof:name":"TD6 9RW",
    "wof:placetype":"postalcode"
},
  "geometry": {"coordinates":[-2.6960398636054,55.599440739923],"type":"Point"}
}