{
  "type": "Feature",
  "properties": {
    "iso:country":"GB",
    "wof:name":"DY12 2JY",
    "wof:placetype":"postalcode"
},
  "geometry": {"coordinates":[-2.33300142735694,52.37083877397902],"type":"Point"}
}