{
  "type": "Feature",
  "properties": {
    "iso:country": "GB",
    "wof:name": "SO50 4LF",
    "wof:placetype": "postalcode"
  },
  "geometry": {"coordinates":[-1.350813,50.984694],"type":"Point"}
}
