{
  "type": "Feature",
  "properties": {
    "iso:country":"GB",
    "wof:name":"AL3 8QH",
    "wof:placetype":"postalcode"
},
  "geometry": {"coordinates":[-0.46428562935875,51.84382893174428],"type":"Point"}
}