{
  "type": "Feature",
  "properties": {
    "iso:country":"GB",
    "wof:name":"BR6 8BE",
    "wof:placetype":"postalcode"
},
  "geometry": {"coordinates":[0.07970564107137,51.37578145520482],"type":"Point"}
}