{
  "type": "Feature",
  "properties": {
    "date:inception_lower": "2021-12-01",
    "date:inception_upper": "2021-12-01",
    "iso:country": "GB",
    "wof:name": "SY8 2EY",
    "wof:placetype": "postalcode"
  },
  "geometry": {"coordinates":[-2.702621,52.377269],"type":"Point"}
}
