{
  "type": "Feature",
  "properties": {
    "iso:country":"GB",
    "wof:name":"LL18 2RA",
    "wof:placetype":"postalcode"
},
  "geometry": {"coordinates":[-3.47408488594149,53.31340238794549],"type":"Point"}
}