{
  "type": "Feature",
  "properties": {
    "iso:country": "GB",
    "wof:name": "B45 8QD",
    "wof:placetype": "postalcode"
  },
  "geometry": {"coordinates":[-1.990528,52.392818],"type":"Point"}
}
