{
  "type": "Feature",
  "properties": {
    "date:inception_lower": "2016-08-01",
    "date:inception_upper": "2016-08-01",
    "iso:country": "GB",
    "wof:name": "B45 8QD",
    "wof:placetype": "postalcode"
  },
  "geometry": {"coordinates":[-1.990542,52.392818],"type":"Point"}
}
