{
  "type": "Feature",
  "properties": {
    "iso:country":"GB",
    "wof:name":"CF5 4LH",
    "wof:placetype":"postalcode"
},
  "geometry": {"coordinates":[-3.25346898418414,51.47746618454588],"type":"Point"}
}