{
  "type": "Feature",
  "properties": {
    "iso:country":"GB",
    "wof:name":"S5 7SP",
    "wof:placetype":"postalcode"
},
  "geometry": {"coordinates":[-1.46272692442841,53.42363179407001],"type":"Point"}
}