{
  "type": "Feature",
  "properties": {
    "iso:country":"GB",
    "wof:name":"DH7 7RJ",
    "wof:placetype":"postalcode"
},
  "geometry": {"coordinates":[-1.60843389582596,54.76941277066869],"type":"Point"}
}