{
  "type": "Feature",
  "properties": {
    "date:inception_lower": "1985-10-01",
    "date:inception_upper": "1985-10-01",
    "iso:country": "GB",
    "wof:name": "DL5 4RS",
    "wof:placetype": "postalcode"
  },
  "geometry": {"coordinates":[-1.568874,54.631998],"type":"Point"}
}
