{
  "type": "Feature",
  "properties": {
    "iso:country":"GB",
    "wof:name":"DA11 8EA",
    "wof:placetype":"postalcode"
},
  "geometry": {"coordinates":[0.33476775861553,51.43315465518327],"type":"Point"}
}