{
  "type": "Feature",
  "properties": {
    "iso:country": "GB",
    "wof:name": "E16 1TL",
    "wof:placetype": "postalcode"
  },
  "geometry": {"coordinates":[0.021991,51.503626],"type":"Point"}
}
