{
  "type": "Feature",
  "properties": {
    "iso:country":"GB",
    "wof:name":"E16 1TL",
    "wof:placetype":"postalcode"
},
  "geometry": {"coordinates":[0.02199070352916,51.50362628771516],"type":"Point"}
}