{
  "type": "Feature",
  "properties": {
    "date:inception_lower": "2000-12-01",
    "date:inception_upper": "2000-12-01",
    "iso:country": "GB",
    "wof:name": "W1B 5SD",
    "wof:placetype": "postalcode"
  },
  "geometry": {"coordinates":[-0.138457,51.511013],"type":"Point"}
}
