{
  "type": "Feature",
  "properties": {
    "iso:country": "GB",
    "wof:name": "S41 9LZ",
    "wof:placetype": "postalcode"
  },
  "geometry": {"coordinates":[-1.418776,53.271705],"type":"Point"}
}
