{
  "type": "Feature",
  "properties": {
    "iso:country":"GB",
    "wof:name":"BL0 0RS",
    "wof:placetype":"postalcode"
},
  "geometry": {"coordinates":[-2.27390108058164,53.64385886679467],"type":"Point"}
}