{
  "type": "Feature",
  "properties": {
    "iso:country": "GB",
    "wof:name": "GL2 4QQ",
    "wof:placetype": "postalcode"
  },
  "geometry": {"coordinates":[-2.291068,51.817409],"type":"Point"}
}
