{
  "type": "Feature",
  "properties": {
    "date:inception_lower": "1995-12-01",
    "date:inception_upper": "1995-12-01",
    "iso:country": "GB",
    "wof:name": "GL2 4QQ",
    "wof:placetype": "postalcode"
  },
  "geometry": {"coordinates":[-2.291068,51.817409],"type":"Point"}
}
