{
  "type": "Feature",
  "properties": {
    "iso:country": "GB",
    "wof:name": "TN21 8YL",
    "wof:placetype": "postalcode"
  },
  "geometry": {"coordinates":[0.26238,50.962734],"type":"Point"}
}
