{
  "type": "Feature",
  "properties": {
    "iso:country":"GB",
    "wof:name":"DN8 5EL",
    "wof:placetype":"postalcode"
},
  "geometry": {"coordinates":[-0.9682305288818,53.61124405958889],"type":"Point"}
}