{
  "type": "Feature",
  "properties": {
    "iso:country":"GB",
    "wof:name":"CA28 9DT",
    "wof:placetype":"postalcode"
},
  "geometry": {"coordinates":[-3.59094816931246,54.53859650714281],"type":"Point"}
}