{
  "type": "Feature",
  "properties": {
    "date:inception_lower": "1980-01-01",
    "date:inception_upper": "1980-01-01",
    "iso:country": "GB",
    "wof:name": "CA28 9DT",
    "wof:placetype": "postalcode"
  },
  "geometry": {"coordinates":[-3.590948,54.538597],"type":"Point"}
}
