{
  "type": "Feature",
  "properties": {
    "date:inception_lower": "1980-01-01",
    "date:inception_upper": "1980-01-01",
    "iso:country": "GB",
    "wof:name": "PR3 5AE",
    "wof:placetype": "postalcode"
  },
  "geometry": {"coordinates":[-2.738945,53.830923],"type":"Point"}
}
