{
  "type": "Feature",
  "properties": {
    "iso:country":"GB",
    "wof:name":"PR3 5AE",
    "wof:placetype":"postalcode"
},
  "geometry": {"coordinates":[-2.73894460012359,53.83092311558372],"type":"Point"}
}