{
  "type": "Feature",
  "properties": {
    "iso:country":"GB",
    "wof:name":"BS4 4DJ",
    "wof:placetype":"postalcode"
},
  "geometry": {"coordinates":[-2.55041607484873,51.45126956143018],"type":"Point"}
}