{
  "type": "Feature",
  "properties": {
    "date:inception_lower": "2006-10-01",
    "date:inception_upper": "2006-10-01",
    "iso:country": "GB",
    "wof:name": "DN16 3EY",
    "wof:placetype": "postalcode"
  },
  "geometry": {"coordinates":[-0.640358,53.566008],"type":"Point"}
}
