{
  "type": "Feature",
  "properties": {
    "iso:country":"GB",
    "wof:name":"DN16 3EY",
    "wof:placetype":"postalcode"
},
  "geometry": {"coordinates":[-0.64035771306887,53.56600796635065],"type":"Point"}
}