{
  "type": "Feature",
  "properties": {
    "date:inception_lower": "2015-01-01",
    "date:inception_upper": "2015-01-01",
    "iso:country": "GB",
    "wof:name": "YO42 2FL",
    "wof:placetype": "postalcode"
  },
  "geometry": {"coordinates":[-0.782353,53.924342],"type":"Point"}
}
