{
  "type": "Feature",
  "properties": {
    "iso:country":"GB",
    "wof:name":"IP13 6UN",
    "wof:placetype":"postalcode"
},
  "geometry": {"coordinates":[1.25089609280529,52.1046856772553],"type":"Point"}
}