{
  "type": "Feature",
  "properties": {
    "iso:country":"GB",
    "wof:name":"M33 6LQ",
    "wof:placetype":"postalcode"
},
  "geometry": {"coordinates":[-2.32947204941037,53.43172749637895],"type":"Point"}
}