{
  "type": "Feature",
  "properties": {
    "iso:country": "GB",
    "wof:name": "M33 6LQ",
    "wof:placetype": "postalcode"
  },
  "geometry": {"coordinates":[-2.329472,53.431727],"type":"Point"}
}
