{
  "type": "Feature",
  "properties": {
    "iso:country":"GB",
    "wof:name":"HD4 5BD",
    "wof:placetype":"postalcode"
},
  "geometry": {"coordinates":[-1.80373824871356,53.63832280364691],"type":"Point"}
}