{
  "type": "Feature",
  "properties": {
    "iso:country":"GB",
    "wof:name":"CB6 3JW",
    "wof:placetype":"postalcode"
},
  "geometry": {"coordinates":[0.22188675279873,52.35091703285219],"type":"Point"}
}