{
  "type": "Feature",
  "properties": {
    "date:inception_lower": "1990-02-01",
    "date:inception_upper": "1990-02-01",
    "iso:country": "GB",
    "wof:name": "CB6 3JW",
    "wof:placetype": "postalcode"
  },
  "geometry": {"coordinates":[0.221887,52.350917],"type":"Point"}
}
