{
  "type": "Feature",
  "properties": {
    "date:inception_lower": "1980-01-01",
    "date:inception_upper": "1980-01-01",
    "iso:country": "GB",
    "wof:name": "CT20 3BH",
    "wof:placetype": "postalcode"
  },
  "geometry": {"coordinates":[1.144878,51.076175],"type":"Point"}
}
