{
  "type": "Feature",
  "properties": {
    "iso:country":"GB",
    "wof:name":"HP14 4QR",
    "wof:placetype":"postalcode"
},
  "geometry": {"coordinates":[-0.7654783370734,51.66310228591666],"type":"Point"}
}