{
  "type": "Feature",
  "properties": {
    "iso:country":"GB",
    "wof:name":"S10 3BW",
    "wof:placetype":"postalcode"
},
  "geometry": {"coordinates":[-1.51255968984643,53.37553144769627],"type":"Point"}
}