{
  "type": "Feature",
  "properties": {
    "iso:country": "GB",
    "wof:name": "S10 3BW",
    "wof:placetype": "postalcode"
  },
  "geometry": {"coordinates":[-1.51256,53.375531],"type":"Point"}
}
