{
  "type": "Feature",
  "properties": {
    "iso:country": "GB",
    "wof:name": "PO18 0HR",
    "wof:placetype": "postalcode"
  },
  "geometry": {"coordinates":[-0.74977,50.910689],"type":"Point"}
}
