{
  "type": "Feature",
  "properties": {
    "iso:country":"GB",
    "wof:name":"EX5 1BQ",
    "wof:placetype":"postalcode"
},
  "geometry": {"coordinates":[-3.45392229921608,50.70968367648533],"type":"Point"}
}