{
  "type": "Feature",
  "properties": {
    "iso:country": "GB",
    "wof:name": "EX5 1BQ",
    "wof:placetype": "postalcode"
  },
  "geometry": {"coordinates":[-3.453922,50.709684],"type":"Point"}
}
