{
  "type": "Feature",
  "properties": {
    "iso:country":"GB",
    "wof:name":"B23 5LF",
    "wof:placetype":"postalcode"
},
  "geometry": {"coordinates":[-1.85118566428127,52.54064984029151],"type":"Point"}
}