{
  "type": "Feature",
  "properties": {
    "iso:country": "GB",
    "wof:name": "LL26 9AG",
    "wof:placetype": "postalcode"
  },
  "geometry": {"coordinates":[-3.799275,53.139115],"type":"Point"}
}
