{
  "type": "Feature",
  "properties": {
    "iso:country":"GB",
    "wof:name":"B67 7HF",
    "wof:placetype":"postalcode"
},
  "geometry": {"coordinates":[-1.99008855106902,52.49150495187684],"type":"Point"}
}