{
  "type": "Feature",
  "properties": {
    "iso:country":"GB",
    "wof:name":"HP20 1NQ",
    "wof:placetype":"postalcode"
},
  "geometry": {"coordinates":[-0.78493571952603,51.81499285048669],"type":"Point"}
}