{
  "type": "Feature",
  "properties": {
    "iso:country":"GB",
    "wof:name":"EX10 8NX",
    "wof:placetype":"postalcode"
},
  "geometry": {"coordinates":[-3.24214705954992,50.67948809968685],"type":"Point"}
}