{
  "type": "Feature",
  "properties": {
    "iso:country":"GB",
    "wof:name":"WN2 5BW",
    "wof:placetype":"postalcode"
},
  "geometry": {"coordinates":[-2.59847248247279,53.52214988683721],"type":"Point"}
}