{
  "type": "Feature",
  "properties": {
    "iso:country": "GB",
    "wof:name": "WN2 5BW",
    "wof:placetype": "postalcode"
  },
  "geometry": {"coordinates":[-2.598472,53.52215],"type":"Point"}
}
