{
  "type": "Feature",
  "properties": {
    "iso:country":"GB",
    "wof:name":"SW19 1EW",
    "wof:placetype":"postalcode"
},
  "geometry": {"coordinates":[-0.19243589360041,51.42007064222508],"type":"Point"}
}