{
  "type": "Feature",
  "properties": {
    "date:inception_lower":"1992-01-01",
    "date:inception_upper":"1992-01-31",
    "iso:country":"GB",
    "wof:name":"LL11 4QU",
    "wof:placetype":"postalcode"
},
  "geometry": {"coordinates":[-3.019421,53.068595],"type":"Point"}
}