{
  "type": "Feature",
  "properties": {
    "iso:country":"GB",
    "wof:name":"LL11 4QU",
    "wof:placetype":"postalcode"
},
  "geometry": {"coordinates":[-3.01942102083846,53.06859519303212],"type":"Point"}
}