{
  "type": "Feature",
  "properties": {
    "iso:country":"GB",
    "wof:name":"BD12 9EU",
    "wof:placetype":"postalcode"
},
  "geometry": {"coordinates":[-1.7629779351127,53.73819729243444],"type":"Point"}
}