{
  "type": "Feature",
  "properties": {
    "iso:country": "GB",
    "wof:name": "NN16 9QQ",
    "wof:placetype": "postalcode"
  },
  "geometry": {"coordinates":[-0.734749,52.40701],"type":"Point"}
}
