{
  "type": "Feature",
  "properties": {
    "date:inception_lower": "1998-06-01",
    "date:inception_upper": "1998-06-01",
    "iso:country": "GB",
    "wof:name": "NN16 9QQ",
    "wof:placetype": "postalcode"
  },
  "geometry": {"coordinates":[-0.734734,52.407025],"type":"Point"}
}
