{
  "type": "Feature",
  "properties": {
    "date:inception_lower": "2007-05-01",
    "date:inception_upper": "2007-05-01",
    "iso:country": "GB",
    "wof:name": "GU32 2JN",
    "wof:placetype": "postalcode"
  },
  "geometry": {"coordinates":[-0.93828,51.003875],"type":"Point"}
}
