{
  "type": "Feature",
  "properties": {
    "iso:country":"GB",
    "wof:name":"M45 7FL",
    "wof:placetype":"postalcode"
},
  "geometry": {"coordinates":[-2.29010481176363,53.54076980901289],"type":"Point"}
}