{
  "type": "Feature",
  "properties": {
    "iso:country": "GB",
    "wof:name": "M45 7FL",
    "wof:placetype": "postalcode"
  },
  "geometry": {"coordinates":[-2.290105,53.54077],"type":"Point"}
}
