{
  "type": "Feature",
  "properties": {
    "iso:country": "GB",
    "wof:name": "NG18 5SZ",
    "wof:placetype": "postalcode"
  },
  "geometry": {"coordinates":[-1.202669,53.14176],"type":"Point"}
}
