{
  "type": "Feature",
  "properties": {
    "iso:country": "GB",
    "wof:name": "SS7 1TB",
    "wof:placetype": "postalcode"
  },
  "geometry": {"coordinates":[0.579604,51.561637],"type":"Point"}
}
