{
  "type": "Feature",
  "properties": {
    "iso:country":"GB",
    "wof:name":"SS7 1TB",
    "wof:placetype":"postalcode"
},
  "geometry": {"coordinates":[0.57960419618587,51.56163701484315],"type":"Point"}
}