{
  "type": "Feature",
  "properties": {
    "iso:country":"GB",
    "wof:name":"BS2 8HX",
    "wof:placetype":"postalcode"
},
  "geometry": {"coordinates":[-2.59303633018191,51.46192354172576],"type":"Point"}
}