{
  "type": "Feature",
  "properties": {
    "iso:country":"GB",
    "wof:name":"KA24 5DG",
    "wof:placetype":"postalcode"
},
  "geometry": {"coordinates":[-4.72199693295452,55.70891630578116],"type":"Point"}
}