{
  "type": "Feature",
  "properties": {
    "iso:country": "GB",
    "wof:name": "ME13 7NN",
    "wof:placetype": "postalcode"
  },
  "geometry": {"coordinates":[0.872276,51.314279],"type":"Point"}
}
