{
  "type": "Feature",
  "properties": {
    "iso:country":"GB",
    "wof:name":"ME13 7NN",
    "wof:placetype":"postalcode"
},
  "geometry": {"coordinates":[0.87227621137314,51.31427879251169],"type":"Point"}
}