{
  "type": "Feature",
  "properties": {
    "date:inception_lower":"1980-01-01",
    "date:inception_upper":"1980-01-31",
    "iso:country":"GB",
    "wof:name":"TS18 4BL",
    "wof:placetype":"postalcode"
},
  "geometry": {"coordinates":[-1.326324,54.561885],"type":"Point"}
}