{
  "type": "Feature",
  "properties": {
    "iso:country":"GB",
    "wof:name":"RG7 4LL",
    "wof:placetype":"postalcode"
},
  "geometry": {"coordinates":[-1.15212828899834,51.38417349784525],"type":"Point"}
}