{
  "type": "Feature",
  "properties": {
    "iso:country":"GB",
    "wof:name":"BA5 3DQ",
    "wof:placetype":"postalcode"
},
  "geometry": {"coordinates":[-2.61823086343169,51.21583990834184],"type":"Point"}
}