{
  "type": "Feature",
  "properties": {
    "iso:country":"GB",
    "wof:name":"DY8 4LS",
    "wof:placetype":"postalcode"
},
  "geometry": {"coordinates":[-2.15507314957956,52.46285123837314],"type":"Point"}
}