{
  "type": "Feature",
  "properties": {
    "date:inception_lower":"2010-10-01",
    "date:inception_upper":"2010-10-31",
    "iso:country":"GB",
    "wof:name":"PE7 3FW",
    "wof:placetype":"postalcode"
},
  "geometry": {"coordinates":[-0.237007,52.525792],"type":"Point"}
}