{
  "type": "Feature",
  "properties": {
    "iso:country":"GB",
    "wof:name":"PE7 3FW",
    "wof:placetype":"postalcode"
},
  "geometry": {"coordinates":[-0.23700731703774,52.52579161844027],"type":"Point"}
}