{
  "type": "Feature",
  "properties": {
    "iso:country": "GB",
    "wof:name": "PE7 3FW",
    "wof:placetype": "postalcode"
  },
  "geometry": {"coordinates":[-0.237007,52.525792],"type":"Point"}
}
