{
  "type": "Feature",
  "properties": {
    "iso:country":"GB",
    "wof:name":"DT11 9AN",
    "wof:placetype":"postalcode"
},
  "geometry": {"coordinates":[-2.21023244006646,50.81684324399421],"type":"Point"}
}