{
  "type": "Feature",
  "properties": {
    "date:inception_lower": "1980-01-01",
    "date:inception_upper": "1980-01-01",
    "iso:country": "GB",
    "wof:name": "DT11 9AN",
    "wof:placetype": "postalcode"
  },
  "geometry": {"coordinates":[-2.210256,50.816826],"type":"Point"}
}
