{
  "type": "Feature",
  "properties": {
    "date:inception_lower": "1980-01-01",
    "date:inception_upper": "1980-01-01",
    "iso:country": "GB",
    "wof:name": "BA12 0JW",
    "wof:placetype": "postalcode"
  },
  "geometry": {"coordinates":[-2.079254,51.166175],"type":"Point"}
}
