{
  "type": "Feature",
  "properties": {
    "iso:country": "GB",
    "wof:name": "BA12 0JW",
    "wof:placetype": "postalcode"
  },
  "geometry": {"coordinates":[-2.079254,51.166175],"type":"Point"}
}
