{
  "type": "Feature",
  "properties": {
    "iso:country":"GB",
    "wof:name":"BA12 0JW",
    "wof:placetype":"postalcode"
},
  "geometry": {"coordinates":[-2.07925400727862,51.166175159846],"type":"Point"}
}