{
  "type": "Feature",
  "properties": {
    "iso:country":"GB",
    "wof:name":"KT9 2HB",
    "wof:placetype":"postalcode"
},
  "geometry": {"coordinates":[-0.29956798594473,51.36161295274293],"type":"Point"}
}