{
  "type": "Feature",
  "properties": {
    "date:inception_lower": "1982-03-01",
    "date:inception_upper": "1982-03-01",
    "iso:country": "GB",
    "wof:name": "DY3 4NE",
    "wof:placetype": "postalcode"
  },
  "geometry": {"coordinates":[-2.205118,52.513955],"type":"Point"}
}
