{
  "type": "Feature",
  "properties": {
    "iso:country": "GB",
    "wof:name": "DY3 4NE",
    "wof:placetype": "postalcode"
  },
  "geometry": {"coordinates":[-2.205118,52.513955],"type":"Point"}
}
