{
  "type": "Feature",
  "properties": {
    "iso:country":"GB",
    "wof:name":"B31 2PD",
    "wof:placetype":"postalcode"
},
  "geometry": {"coordinates":[-1.97193463817682,52.41245300068937],"type":"Point"}
}