{
  "type": "Feature",
  "properties": {
    "date:inception_lower": "1993-08-01",
    "date:inception_upper": "1993-08-01",
    "iso:country": "GB",
    "wof:name": "CA14 5AW",
    "wof:placetype": "postalcode"
  },
  "geometry": {"coordinates":[-3.55526,54.629631],"type":"Point"}
}
