{
  "type": "Feature",
  "properties": {
    "date:inception_lower": "2018-10-01",
    "date:inception_upper": "2018-10-01",
    "iso:country": "GB",
    "wof:name": "KY11 1FD",
    "wof:placetype": "postalcode"
  },
  "geometry": {"coordinates":[-3.388706,56.031107],"type":"Point"}
}
