{
  "type": "Feature",
  "properties": {
    "iso:country": "GB",
    "wof:name": "KY11 1FD",
    "wof:placetype": "postalcode"
  },
  "geometry": {"coordinates":[-3.389242,56.032179],"type":"Point"}
}
