{
  "type": "Feature",
  "properties": {
    "iso:country": "GB",
    "wof:name": "L35 4AD",
    "wof:placetype": "postalcode"
  },
  "geometry": {"coordinates":[-2.765725,53.418877],"type":"Point"}
}
