{
  "type": "Feature",
  "properties": {
    "date:inception_lower":"2013-05-01",
    "date:inception_upper":"2013-05-31",
    "iso:country":"GB",
    "wof:name":"L35 4AD",
    "wof:placetype":"postalcode"
},
  "geometry": {"coordinates":[-2.765725,53.418877],"type":"Point"}
}