{
  "type": "Feature",
  "properties": {
    "iso:country":"GB",
    "wof:name":"DE23 1LH",
    "wof:placetype":"postalcode"
},
  "geometry": {"coordinates":[-1.49886796466065,52.88824976901042],"type":"Point"}
}