{
  "type": "Feature",
  "properties": {
    "iso:country": "GB",
    "wof:name": "SY5 6HQ",
    "wof:placetype": "postalcode"
  },
  "geometry": {"coordinates":[-2.7078,52.648132],"type":"Point"}
}
