{
  "type": "Feature",
  "properties": {
    "date:inception_lower": "1980-01-01",
    "date:inception_upper": "1980-01-01",
    "iso:country": "GB",
    "wof:name": "SS8 9HJ",
    "wof:placetype": "postalcode"
  },
  "geometry": {"coordinates":[0.578211,51.522726],"type":"Point"}
}
