{
  "type": "Feature",
  "properties": {
    "iso:country":"GB",
    "wof:name":"TS25 5RG",
    "wof:placetype":"postalcode"
},
  "geometry": {"coordinates":[-1.22089880843225,54.67572520294875],"type":"Point"}
}