{
  "type": "Feature",
  "properties": {
    "iso:country": "GB",
    "wof:name": "BS16 6RZ",
    "wof:placetype": "postalcode"
  },
  "geometry": {"coordinates":[-2.494199,51.495965],"type":"Point"}
}
