{
  "type": "Feature",
  "properties": {
    "iso:country":"GB",
    "wof:name":"BS16 6RZ",
    "wof:placetype":"postalcode"
},
  "geometry": {"coordinates":[-2.49419872455618,51.49596549068959],"type":"Point"}
}