{
  "type": "Feature",
  "properties": {
    "iso:country": "GB",
    "wof:name": "PL12 5NN",
    "wof:placetype": "postalcode"
  },
  "geometry": {"coordinates":[-4.305253,50.3908],"type":"Point"}
}
