{
  "type": "Feature",
  "properties": {
    "iso:country": "GB",
    "wof:name": "HP11 1FD",
    "wof:placetype": "postalcode"
  },
  "geometry": {"coordinates":[-0.743172,51.619403],"type":"Point"}
}
