{
  "type": "Feature",
  "properties": {
    "date:inception_lower": "2006-10-01",
    "date:inception_upper": "2006-10-01",
    "iso:country": "GB",
    "wof:name": "SY23 3UF",
    "wof:placetype": "postalcode"
  },
  "geometry": {"coordinates":[-4.064129,52.41779],"type":"Point"}
}
