{
  "type": "Feature",
  "properties": {
    "iso:country":"GB",
    "wof:name":"SY23 3UF",
    "wof:placetype":"postalcode"
},
  "geometry": {"coordinates":[-4.06412887614876,52.4177896818775],"type":"Point"}
}