{
  "type": "Feature",
  "properties": {
    "date:inception_lower":"2009-07-01",
    "date:inception_upper":"2009-07-31",
    "iso:country":"GB",
    "wof:name":"AB51 3SW",
    "wof:placetype":"postalcode"
},
  "geometry": {"coordinates":[-2.376784,57.283687],"type":"Point"}
}