{
  "type": "Feature",
  "properties": {
    "iso:country": "GB",
    "wof:name": "AB51 3SW",
    "wof:placetype": "postalcode"
  },
  "geometry": {"coordinates":[-2.376784,57.283687],"type":"Point"}
}
