{
  "type": "Feature",
  "properties": {
    "iso:country":"GB",
    "wof:name":"LS24 9QL",
    "wof:placetype":"postalcode"
},
  "geometry": {"coordinates":[-1.28785299853173,53.82955138554144],"type":"Point"}
}