{
  "type": "Feature",
  "properties": {
    "date:inception_lower": "1980-01-01",
    "date:inception_upper": "1980-01-01",
    "iso:country": "GB",
    "wof:name": "LS24 9QL",
    "wof:placetype": "postalcode"
  },
  "geometry": {"coordinates":[-1.287853,53.829551],"type":"Point"}
}
