{
  "type": "Feature",
  "properties": {
    "iso:country": "GB",
    "wof:name": "LS24 9QL",
    "wof:placetype": "postalcode"
  },
  "geometry": {"coordinates":[-1.287853,53.829551],"type":"Point"}
}
