{
  "type": "Feature",
  "properties": {
    "iso:country":"GB",
    "wof:name":"NP4 6EW",
    "wof:placetype":"postalcode"
},
  "geometry": {"coordinates":[-3.03820445509388,51.70015353079143],"type":"Point"}
}