{
  "type": "Feature",
  "properties": {
    "date:inception_lower": "2022-07-01",
    "date:inception_upper": "2022-07-01",
    "iso:country": "GB",
    "wof:name": "MK44 1FL",
    "wof:placetype": "postalcode"
  },
  "geometry": {"coordinates":[-0.557205,52.224255],"type":"Point"}
}
