{
  "type": "Feature",
  "properties": {
    "date:inception_lower": "1981-06-01",
    "date:inception_upper": "1981-06-01",
    "iso:country": "GB",
    "wof:name": "NE37 1UP",
    "wof:placetype": "postalcode"
  },
  "geometry": {"coordinates":[-1.527853,54.908597],"type":"Point"}
}
