{
  "type": "Feature",
  "properties": {
    "iso:country":"GB",
    "wof:name":"NE37 1UP",
    "wof:placetype":"postalcode"
},
  "geometry": {"coordinates":[-1.52785266849657,54.90859652682043],"type":"Point"}
}