{
  "type": "Feature",
  "properties": {
    "iso:country": "GB",
    "wof:name": "DN37 0XN",
    "wof:placetype": "postalcode"
  },
  "geometry": {"coordinates":[-0.117301,53.517269],"type":"Point"}
}
