{
  "type": "Feature",
  "properties": {
    "iso:country":"GB",
    "wof:name":"S63 8HG",
    "wof:placetype":"postalcode"
},
  "geometry": {"coordinates":[-1.31473536550398,53.52412268221977],"type":"Point"}
}