{
  "type": "Feature",
  "properties": {
    "iso:country":"GB",
    "wof:name":"YO10 3WG",
    "wof:placetype":"postalcode"
},
  "geometry": {"coordinates":[-1.0696258502513,53.95429687081904],"type":"Point"}
}