{
  "type": "Feature",
  "properties": {
    "date:inception_lower": "2004-10-01",
    "date:inception_upper": "2004-10-01",
    "iso:country": "GB",
    "wof:name": "YO10 3WG",
    "wof:placetype": "postalcode"
  },
  "geometry": {"coordinates":[-1.069626,53.954297],"type":"Point"}
}
