{
  "type": "Feature",
  "properties": {
    "date:inception_lower": "2000-06-01",
    "date:inception_upper": "2000-06-01",
    "iso:country": "GB",
    "wof:name": "HG3 2WJ",
    "wof:placetype": "postalcode"
  },
  "geometry": {"coordinates":[-1.579754,54.003504],"type":"Point"}
}
