{
  "type": "Feature",
  "properties": {
    "iso:country":"GB",
    "wof:name":"HG3 2WJ",
    "wof:placetype":"postalcode"
},
  "geometry": {"coordinates":[-1.57975416981727,54.00350401292329],"type":"Point"}
}