{
  "type": "Feature",
  "properties": {
    "iso:country": "GB",
    "wof:name": "SK6 1EU",
    "wof:placetype": "postalcode"
  },
  "geometry": {"coordinates":[-2.099548,53.423134],"type":"Point"}
}
