{
  "type": "Feature",
  "properties": {
    "date:inception_lower": "2007-04-01",
    "date:inception_upper": "2007-04-01",
    "iso:country": "GB",
    "wof:name": "SS8 8QW",
    "wof:placetype": "postalcode"
  },
  "geometry": {"coordinates":[0.609201,51.524136],"type":"Point"}
}
