{
  "type": "Feature",
  "properties": {
    "iso:country":"GB",
    "wof:name":"SS8 8QW",
    "wof:placetype":"postalcode"
},
  "geometry": {"coordinates":[0.60920113384093,51.52413596354938],"type":"Point"}
}