{
  "type": "Feature",
  "properties": {
    "iso:country":"GB",
    "wof:name":"HU18 1LU",
    "wof:placetype":"postalcode"
},
  "geometry": {"coordinates":[-0.1670491668601,53.91591528591358],"type":"Point"}
}