{
  "type": "Feature",
  "properties": {
    "iso:country": "GB",
    "wof:name": "HU18 1LU",
    "wof:placetype": "postalcode"
  },
  "geometry": {"coordinates":[-0.167049,53.915915],"type":"Point"}
}
