{
  "type": "Feature",
  "properties": {
    "iso:country": "GB",
    "wof:name": "SG7 5BP",
    "wof:placetype": "postalcode"
  },
  "geometry": {"coordinates":[-0.189903,51.99126],"type":"Point"}
}
