{
  "type": "Feature",
  "properties": {
    "iso:country":"GB",
    "wof:name":"SG7 5BP",
    "wof:placetype":"postalcode"
},
  "geometry": {"coordinates":[-0.18994455553292,51.99126065545596],"type":"Point"}
}