{
  "type": "Feature",
  "properties": {
    "iso:country":"GB",
    "wof:name":"BD18 1JL",
    "wof:placetype":"postalcode"
},
  "geometry": {"coordinates":[-1.75913191919651,53.83022674978609],"type":"Point"}
}