{
  "type": "Feature",
  "properties": {
    "iso:country":"GB",
    "wof:name":"BN25 1BZ",
    "wof:placetype":"postalcode"
},
  "geometry": {"coordinates":[0.10125040117992,50.76959309583081],"type":"Point"}
}