{
  "type": "Feature",
  "properties": {
    "date:inception_lower": "1991-09-01",
    "date:inception_upper": "1991-09-01",
    "iso:country": "GB",
    "wof:name": "BN25 1BZ",
    "wof:placetype": "postalcode"
  },
  "geometry": {"coordinates":[0.10125,50.769593],"type":"Point"}
}
