{
  "type": "Feature",
  "properties": {
    "iso:country":"GB",
    "wof:name":"B28 0AA",
    "wof:placetype":"postalcode"
},
  "geometry": {"coordinates":[-1.85021951166108,52.43436039529167],"type":"Point"}
}