{
  "type": "Feature",
  "properties": {
    "date:inception_lower": "1981-06-01",
    "date:inception_upper": "1981-06-01",
    "iso:country": "GB",
    "wof:name": "SE11 4EU",
    "wof:placetype": "postalcode"
  },
  "geometry": {"coordinates":[-0.107846,51.489121],"type":"Point"}
}
