{
  "type": "Feature",
  "properties": {
    "iso:country":"GB",
    "wof:name":"SE11 4EU",
    "wof:placetype":"postalcode"
},
  "geometry": {"coordinates":[-0.10784607300331,51.48912077324798],"type":"Point"}
}