{
  "type": "Feature",
  "properties": {
    "iso:country":"GB",
    "wof:name":"BH3 7AD",
    "wof:placetype":"postalcode"
},
  "geometry": {"coordinates":[-1.87616178986901,50.73316573703212],"type":"Point"}
}