{
  "type": "Feature",
  "properties": {
    "iso:country":"GB",
    "wof:name":"RM3 9EX",
    "wof:placetype":"postalcode"
},
  "geometry": {"coordinates":[0.2292433333223,51.61101288435722],"type":"Point"}
}