{
  "type": "Feature",
  "properties": {
    "date:inception_lower": "2017-01-01",
    "date:inception_upper": "2017-01-01",
    "iso:country": "GB",
    "wof:name": "DE4 3FR",
    "wof:placetype": "postalcode"
  },
  "geometry": {"coordinates":[-1.570139,53.143994],"type":"Point"}
}
