{
  "type": "Feature",
  "properties": {
    "iso:country":"GB",
    "wof:name":"AB51 8TX",
    "wof:placetype":"postalcode"
},
  "geometry": {"coordinates":[-2.40697781081717,57.38762313150377],"type":"Point"}
}