{
  "type": "Feature",
  "properties": {
    "iso:country": "GB",
    "wof:name": "SW1W 9ES",
    "wof:placetype": "postalcode"
  },
  "geometry": {"coordinates":[-0.152832,51.493723],"type":"Point"}
}
