{
  "type": "Feature",
  "properties": {
    "iso:country":"GB",
    "wof:name":"B95 5EL",
    "wof:placetype":"postalcode"
},
  "geometry": {"coordinates":[-1.73192588183513,52.29911054545985],"type":"Point"}
}