{
  "type": "Feature",
  "properties": {
    "iso:country": "GB",
    "wof:name": "B95 5EL",
    "wof:placetype": "postalcode"
  },
  "geometry": {"coordinates":[-1.731916,52.299125],"type":"Point"}
}
