{
  "type": "Feature",
  "properties": {
    "iso:country":"GB",
    "wof:name":"CF14 4SQ",
    "wof:placetype":"postalcode"
},
  "geometry": {"coordinates":[-3.2032129248369,51.52447190821976],"type":"Point"}
}