{
  "type": "Feature",
  "properties": {
    "iso:country": "GB",
    "wof:name": "CF14 4SQ",
    "wof:placetype": "postalcode"
  },
  "geometry": {"coordinates":[-3.203213,51.524472],"type":"Point"}
}
