{
  "type": "Feature",
  "properties": {
    "iso:country":"GB",
    "wof:name":"NW7 3AN",
    "wof:placetype":"postalcode"
},
  "geometry": {"coordinates":[-0.25373902357792,51.62569328993583],"type":"Point"}
}