{
  "type": "Feature",
  "properties": {
    "iso:country":"GB",
    "wof:name":"CH41 7BW",
    "wof:placetype":"postalcode"
},
  "geometry": {"coordinates":[-3.06229441376075,53.40294353209067],"type":"Point"}
}