{
  "type": "Feature",
  "properties": {
    "iso:country": "GB",
    "wof:name": "WV15 6BY",
    "wof:placetype": "postalcode"
  },
  "geometry": {"coordinates":[-2.412944,52.526141],"type":"Point"}
}
