{
  "type": "Feature",
  "properties": {
    "date:inception_lower": "1995-01-01",
    "date:inception_upper": "1995-01-01",
    "iso:country": "GB",
    "wof:name": "WV15 6BY",
    "wof:placetype": "postalcode"
  },
  "geometry": {"coordinates":[-2.413132,52.526074],"type":"Point"}
}
