{
  "type": "Feature",
  "properties": {
    "iso:country":"GB",
    "wof:name":"OX17 1RL",
    "wof:placetype":"postalcode"
},
  "geometry": {"coordinates":[-1.33214146050343,52.10546267813168],"type":"Point"}
}