{
  "type": "Feature",
  "properties": {
    "iso:country":"GB",
    "wof:name":"RG9 1XW",
    "wof:placetype":"postalcode"
},
  "geometry": {"coordinates":[-0.9174863415203,51.53105702977925],"type":"Point"}
}