{
  "type": "Feature",
  "properties": {
    "date:inception_lower": "1980-01-01",
    "date:inception_upper": "1980-01-01",
    "iso:country": "GB",
    "wof:name": "BS1 4XE",
    "wof:placetype": "postalcode"
  },
  "geometry": {"coordinates":[-2.597492,51.454652],"type":"Point"}
}
