{
  "type": "Feature",
  "properties": {
    "iso:country":"GB",
    "wof:name":"S43 3RZ",
    "wof:placetype":"postalcode"
},
  "geometry": {"coordinates":[-1.36770874186376,53.26030768425932],"type":"Point"}
}