{
  "type": "Feature",
  "properties": {
    "iso:country":"GB",
    "wof:name":"LL11 2AF",
    "wof:placetype":"postalcode"
},
  "geometry": {"coordinates":[-3.00687004824221,53.05199068557197],"type":"Point"}
}