{
  "type": "Feature",
  "properties": {
    "date:inception_lower": "1980-01-01",
    "date:inception_upper": "1980-01-01",
    "iso:country": "GB",
    "wof:name": "KA25 6DB",
    "wof:placetype": "postalcode"
  },
  "geometry": {"coordinates":[-4.690261,55.7454],"type":"Point"}
}
