{
  "type": "Feature",
  "properties": {
    "iso:country": "GB",
    "wof:name": "KA25 6DB",
    "wof:placetype": "postalcode"
  },
  "geometry": {"coordinates":[-4.690261,55.7454],"type":"Point"}
}
