{
  "type": "Feature",
  "properties": {
    "iso:country": "GB",
    "wof:name": "BA12 8GD",
    "wof:placetype": "postalcode"
  },
  "geometry": {"coordinates":[-2.206978,51.197881],"type":"Point"}
}
