{
  "type": "Feature",
  "properties": {
    "iso:country":"GB",
    "wof:name":"SW20 0NP",
    "wof:placetype":"postalcode"
},
  "geometry": {"coordinates":[-0.24431104634145,51.41751398071143],"type":"Point"}
}