{
  "type": "Feature",
  "properties": {
    "iso:country":"GB",
    "wof:name":"NP4 7UE",
    "wof:placetype":"postalcode"
},
  "geometry": {"coordinates":[-3.08137194624736,51.74031566930776],"type":"Point"}
}