{
  "type": "Feature",
  "properties": {
    "iso:country": "GB",
    "wof:name": "NP4 7UE",
    "wof:placetype": "postalcode"
  },
  "geometry": {"coordinates":[-3.081372,51.740316],"type":"Point"}
}
