{
  "type": "Feature",
  "properties": {
    "iso:country": "GB",
    "wof:name": "NR9 3NA",
    "wof:placetype": "postalcode"
  },
  "geometry": {"coordinates":[1.179478,52.633258],"type":"Point"}
}
