{
  "type": "Feature",
  "properties": {
    "iso:country":"GB",
    "wof:name":"NR9 3NA",
    "wof:placetype":"postalcode"
},
  "geometry": {"coordinates":[1.17947807393173,52.63325796025657],"type":"Point"}
}