{
  "type": "Feature",
  "properties": {
    "iso:country":"GB",
    "wof:name":"IP8 4LF",
    "wof:placetype":"postalcode"
},
  "geometry": {"coordinates":[1.0413984510264,52.08201366475855],"type":"Point"}
}