{
  "type": "Feature",
  "properties": {
    "iso:country": "GB",
    "wof:name": "IP8 4LF",
    "wof:placetype": "postalcode"
  },
  "geometry": {"coordinates":[1.041946,52.082348],"type":"Point"}
}
