{
  "type": "Feature",
  "properties": {
    "iso:country":"GB",
    "wof:name":"FK4 2EB",
    "wof:placetype":"postalcode"
},
  "geometry": {"coordinates":[-3.89429928661066,55.98600089213866],"type":"Point"}
}