{
  "type": "Feature",
  "properties": {
    "date:inception_lower":"1980-01-01",
    "date:inception_upper":"1980-01-31",
    "iso:country":"GB",
    "wof:name":"OL2 8SB",
    "wof:placetype":"postalcode"
},
  "geometry": {"coordinates":[-2.099975,53.572692],"type":"Point"}
}