{
  "type": "Feature",
  "properties": {
    "iso:country":"GB",
    "wof:name":"OL2 8SB",
    "wof:placetype":"postalcode"
},
  "geometry": {"coordinates":[-2.09991521214898,53.57273722195332],"type":"Point"}
}