{
  "type": "Feature",
  "properties": {
    "iso:country":"GB",
    "wof:name":"IP21 5LW",
    "wof:placetype":"postalcode"
},
  "geometry": {"coordinates":[1.30375624567142,52.29381795833805],"type":"Point"}
}