{
  "type": "Feature",
  "properties": {
    "date:inception_lower": "1980-01-01",
    "date:inception_upper": "1980-01-01",
    "iso:country": "GB",
    "wof:name": "HP8 4DU",
    "wof:placetype": "postalcode"
  },
  "geometry": {"coordinates":[-0.579371,51.625472],"type":"Point"}
}
