{
  "type": "Feature",
  "properties": {
    "iso:country":"GB",
    "wof:name":"HP8 4DU",
    "wof:placetype":"postalcode"
},
  "geometry": {"coordinates":[-0.57937115237907,51.62547193655399],"type":"Point"}
}