{
  "type": "Feature",
  "properties": {
    "iso:country":"GB",
    "wof:name":"TN31 7NH",
    "wof:placetype":"postalcode"
},
  "geometry": {"coordinates":[0.73436421594948,50.95689667140832],"type":"Point"}
}