{
  "type": "Feature",
  "properties": {
    "iso:country":"GB",
    "wof:name":"SP11 0ES",
    "wof:placetype":"postalcode"
},
  "geometry": {"coordinates":[-1.42015240799792,51.29352265955032],"type":"Point"}
}