{
  "type": "Feature",
  "properties": {
    "date:inception_lower": "1993-01-01",
    "date:inception_upper": "1993-01-01",
    "iso:country": "GB",
    "wof:name": "SP11 0ES",
    "wof:placetype": "postalcode"
  },
  "geometry": {"coordinates":[-1.420152,51.293523],"type":"Point"}
}
