{
  "type": "Feature",
  "properties": {
    "iso:country": "GB",
    "wof:name": "SS17 0HS",
    "wof:placetype": "postalcode"
  },
  "geometry": {"coordinates":[0.424708,51.51573],"type":"Point"}
}
