{
  "type": "Feature",
  "properties": {
    "iso:country":"GB",
    "wof:name":"SS17 0HS",
    "wof:placetype":"postalcode"
},
  "geometry": {"coordinates":[0.42470833803914,51.51573027776113],"type":"Point"}
}