{
  "type": "Feature",
  "properties": {
    "iso:country":"GB",
    "wof:name":"W14 9LP",
    "wof:placetype":"postalcode"
},
  "geometry": {"coordinates":[-0.20434547234753,51.49047626533872],"type":"Point"}
}