{
  "type": "Feature",
  "properties": {
    "iso:country":"GB",
    "wof:name":"TW4 7NB",
    "wof:placetype":"postalcode"
},
  "geometry": {"coordinates":[-0.39576723255059,51.47243384168907],"type":"Point"}
}