{
  "type": "Feature",
  "properties": {
    "date:inception_lower": "2014-08-01",
    "date:inception_upper": "2014-08-01",
    "iso:country": "GB",
    "wof:name": "TW4 7NB",
    "wof:placetype": "postalcode"
  },
  "geometry": {"coordinates":[-0.395767,51.472434],"type":"Point"}
}
