{
  "type": "Feature",
  "properties": {
    "iso:country":"GB",
    "wof:name":"IP2 8PR",
    "wof:placetype":"postalcode"
},
  "geometry": {"coordinates":[1.14813766257543,52.04135360891189],"type":"Point"}
}