{
  "type": "Feature",
  "properties": {
    "date:inception_lower": "1980-01-01",
    "date:inception_upper": "1980-01-01",
    "iso:country": "GB",
    "wof:name": "DN15 9DL",
    "wof:placetype": "postalcode"
  },
  "geometry": {"coordinates":[-0.690889,53.653252],"type":"Point"}
}
