{
  "type": "Feature",
  "properties": {
    "iso:country":"GB",
    "wof:name":"LE4 2GQ",
    "wof:placetype":"postalcode"
},
  "geometry": {"coordinates":[-1.14416823862545,52.66499511883072],"type":"Point"}
}