{
  "type": "Feature",
  "properties": {
    "date:inception_lower": "2006-10-01",
    "date:inception_upper": "2006-10-01",
    "iso:country": "GB",
    "wof:name": "TW8 9RR",
    "wof:placetype": "postalcode"
  },
  "geometry": {"coordinates":[-0.312722,51.489793],"type":"Point"}
}
