{
  "type": "Feature",
  "properties": {
    "iso:country":"GB",
    "wof:name":"TW8 9RR",
    "wof:placetype":"postalcode"
},
  "geometry": {"coordinates":[-0.31272242567542,51.48979257067609],"type":"Point"}
}