{
  "type": "Feature",
  "properties": {
    "iso:country":"GB",
    "wof:name":"CH7 4DU",
    "wof:placetype":"postalcode"
},
  "geometry": {"coordinates":[-3.1671253600152,53.14227329843865],"type":"Point"}
}