{
  "type": "Feature",
  "properties": {
    "iso:country": "GB",
    "wof:name": "CH7 4DU",
    "wof:placetype": "postalcode"
  },
  "geometry": {"coordinates":[-3.167125,53.142273],"type":"Point"}
}
