{
  "type": "Feature",
  "properties": {
    "iso:country":"GB",
    "wof:name":"M32 9PN",
    "wof:placetype":"postalcode"
},
  "geometry": {"coordinates":[-2.33330561259247,53.45422414675303],"type":"Point"}
}