{
  "type": "Feature",
  "properties": {
    "iso:country": "GB",
    "wof:name": "M32 9PN",
    "wof:placetype": "postalcode"
  },
  "geometry": {"coordinates":[-2.333306,53.454224],"type":"Point"}
}
