{
  "type": "Feature",
  "properties": {
    "iso:country":"GB",
    "wof:name":"RM5 3JT",
    "wof:placetype":"postalcode"
},
  "geometry": {"coordinates":[0.16621672864922,51.59960322829433],"type":"Point"}
}