{
  "type": "Feature",
  "properties": {
    "date:inception_lower": "1980-01-01",
    "date:inception_upper": "1980-01-01",
    "iso:country": "GB",
    "wof:name": "RM5 3JT",
    "wof:placetype": "postalcode"
  },
  "geometry": {"coordinates":[0.166217,51.599603],"type":"Point"}
}
