{
  "type": "Feature",
  "properties": {
    "iso:country":"GB",
    "wof:name":"OL2 6LB",
    "wof:placetype":"postalcode"
},
  "geometry": {"coordinates":[-2.10528362406989,53.56364542819635],"type":"Point"}
}