{
  "type": "Feature",
  "properties": {
    "iso:country":"GB",
    "wof:name":"SO30 0PU",
    "wof:placetype":"postalcode"
},
  "geometry": {"coordinates":[-1.29490934313579,50.91298641339365],"type":"Point"}
}