{
  "type": "Feature",
  "properties": {
    "iso:country": "GB",
    "wof:name": "DY10 1ND",
    "wof:placetype": "postalcode"
  },
  "geometry": {"coordinates":[-2.242485,52.382441],"type":"Point"}
}
