{
  "type": "Feature",
  "properties": {
    "iso:country": "GB",
    "wof:name": "HA4 7YJ",
    "wof:placetype": "postalcode"
  },
  "geometry": {"coordinates":[-0.440423,51.583649],"type":"Point"}
}
