{
  "type": "Feature",
  "properties": {
    "date:inception_lower": "1981-06-01",
    "date:inception_upper": "1981-06-01",
    "iso:country": "GB",
    "wof:name": "HA4 7YJ",
    "wof:placetype": "postalcode"
  },
  "geometry": {"coordinates":[-0.440423,51.583649],"type":"Point"}
}
