{
  "type": "Feature",
  "properties": {
    "iso:country": "GB",
    "wof:name": "HD9 3XN",
    "wof:placetype": "postalcode"
  },
  "geometry": {"coordinates":[-1.792198,53.58616],"type":"Point"}
}
