{
  "type": "Feature",
  "properties": {
    "date:inception_lower": "2001-06-01",
    "date:inception_upper": "2001-06-01",
    "iso:country": "GB",
    "wof:name": "HD9 3XN",
    "wof:placetype": "postalcode"
  },
  "geometry": {"coordinates":[-1.792198,53.58616],"type":"Point"}
}
