{
  "type": "Feature",
  "properties": {
    "iso:country":"GB",
    "wof:name":"HD9 3XN",
    "wof:placetype":"postalcode"
},
  "geometry": {"coordinates":[-1.79360393332518,53.58576045636207],"type":"Point"}
}