{
  "type": "Feature",
  "properties": {
    "iso:country": "GB",
    "wof:name": "SA32 8JQ",
    "wof:placetype": "postalcode"
  },
  "geometry": {"coordinates":[-4.101121,51.858808],"type":"Point"}
}
