{
  "type": "Feature",
  "properties": {
    "iso:country":"GB",
    "wof:name":"WA7 5JP",
    "wof:placetype":"postalcode"
},
  "geometry": {"coordinates":[-2.71857967775772,53.33208677732589],"type":"Point"}
}