{
  "type": "Feature",
  "properties": {
    "iso:country": "GB",
    "wof:name": "WA7 5JP",
    "wof:placetype": "postalcode"
  },
  "geometry": {"coordinates":[-2.71858,53.332087],"type":"Point"}
}
