{
  "type": "Feature",
  "properties": {
    "iso:country": "GB",
    "wof:name": "SP8 4RG",
    "wof:placetype": "postalcode"
  },
  "geometry": {"coordinates":[-2.277548,51.044326],"type":"Point"}
}
