{
  "type": "Feature",
  "properties": {
    "iso:country":"GB",
    "wof:name":"SP8 4RG",
    "wof:placetype":"postalcode"
},
  "geometry": {"coordinates":[-2.27754833588548,51.04432615373793],"type":"Point"}
}