{
  "type": "Feature",
  "properties": {
    "date:inception_lower":"1980-01-01",
    "date:inception_upper":"1980-01-31",
    "iso:country":"GB",
    "wof:name":"SP8 4RG",
    "wof:placetype":"postalcode"
},
  "geometry": {"coordinates":[-2.277548,51.044326],"type":"Point"}
}