{
  "type": "Feature",
  "properties": {
    "iso:country": "GB",
    "wof:name": "SK17 6EH",
    "wof:placetype": "postalcode"
  },
  "geometry": {"coordinates":[-1.914594,53.256692],"type":"Point"}
}
