{
  "type": "Feature",
  "properties": {
    "iso:country":"GB",
    "wof:name":"SP2 8LW",
    "wof:placetype":"postalcode"
},
  "geometry": {"coordinates":[-1.81479110416755,51.06391509148214],"type":"Point"}
}