{
  "type": "Feature",
  "properties": {
    "iso:country": "GB",
    "wof:name": "SP2 8LW",
    "wof:placetype": "postalcode"
  },
  "geometry": {"coordinates":[-1.814791,51.063915],"type":"Point"}
}
