{
  "type": "Feature",
  "properties": {
    "iso:country":"GB",
    "wof:name":"EX1 2AX",
    "wof:placetype":"postalcode"
},
  "geometry": {"coordinates":[-3.52054920262347,50.72592970665626],"type":"Point"}
}