{
  "type": "Feature",
  "properties": {
    "iso:country":"GB",
    "wof:name":"TN5 6SL",
    "wof:placetype":"postalcode"
},
  "geometry": {"coordinates":[0.33319992035333,51.06688231736332],"type":"Point"}
}