{
  "type": "Feature",
  "properties": {
    "date:inception_lower": "1987-04-01",
    "date:inception_upper": "1987-04-01",
    "iso:country": "GB",
    "wof:name": "BS1 2NN",
    "wof:placetype": "postalcode"
  },
  "geometry": {"coordinates":[-2.596228,51.457113],"type":"Point"}
}
