{
  "type": "Feature",
  "properties": {
    "iso:country":"GB",
    "wof:name":"BS1 2NN",
    "wof:placetype":"postalcode"
},
  "geometry": {"coordinates":[-2.59622676308632,51.45711481429945],"type":"Point"}
}