{
  "type": "Feature",
  "properties": {
    "date:inception_lower": "1980-01-01",
    "date:inception_upper": "1980-01-01",
    "iso:country": "GB",
    "wof:name": "BA11 2PA",
    "wof:placetype": "postalcode"
  },
  "geometry": {"coordinates":[-2.331223,51.246008],"type":"Point"}
}
