{
  "type": "Feature",
  "properties": {
    "iso:country": "GB",
    "wof:name": "LS12 5HF",
    "wof:placetype": "postalcode"
  },
  "geometry": {"coordinates":[-1.636998,53.781987],"type":"Point"}
}
