{
  "type": "Feature",
  "properties": {
    "iso:country":"GB",
    "wof:name":"LS12 5HF",
    "wof:placetype":"postalcode"
},
  "geometry": {"coordinates":[-1.63699782570229,53.78198666291262],"type":"Point"}
}