{
  "type": "Feature",
  "properties": {
    "date:inception_lower": "1994-12-01",
    "date:inception_upper": "1994-12-01",
    "iso:country": "GB",
    "wof:name": "SN5 5BE",
    "wof:placetype": "postalcode"
  },
  "geometry": {"coordinates":[-1.836199,51.57975],"type":"Point"}
}
