{
  "type": "Feature",
  "properties": {
    "iso:country":"GB",
    "wof:name":"BS6 6DN",
    "wof:placetype":"postalcode"
},
  "geometry": {"coordinates":[-2.59678372943396,51.46450310191845],"type":"Point"}
}