{
  "type": "Feature",
  "properties": {
    "date:inception_lower": "2021-11-01",
    "date:inception_upper": "2021-11-01",
    "iso:country": "GB",
    "wof:name": "TR13 9FN",
    "wof:placetype": "postalcode"
  },
  "geometry": {"coordinates":[-5.352627,50.108049],"type":"Point"}
}
