{
  "type": "Feature",
  "properties": {
    "date:inception_lower": "2022-08-01",
    "date:inception_upper": "2022-08-01",
    "iso:country": "GB",
    "wof:name": "PE29 1AW",
    "wof:placetype": "postalcode"
  },
  "geometry": {"coordinates":[-0.159596,52.338636],"type":"Point"}
}
