{
  "type": "Feature",
  "properties": {
    "iso:country": "GB",
    "wof:name": "AB45 3XS",
    "wof:placetype": "postalcode"
  },
  "geometry": {"coordinates":[-2.579683,57.572125],"type":"Point"}
}
