{
  "type": "Feature",
  "properties": {
    "iso:country":"GB",
    "wof:name":"AB45 3XS",
    "wof:placetype":"postalcode"
},
  "geometry": {"coordinates":[-2.57984905104113,57.57414554895657],"type":"Point"}
}