{
  "type": "Feature",
  "properties": {
    "date:inception_lower": "1980-01-01",
    "date:inception_upper": "1980-01-01",
    "iso:country": "GB",
    "wof:name": "L7 9LX",
    "wof:placetype": "postalcode"
  },
  "geometry": {"coordinates":[-2.933194,53.410529],"type":"Point"}
}
