{
  "type": "Feature",
  "properties": {
    "iso:country": "GB",
    "wof:name": "SY3 0BU",
    "wof:placetype": "postalcode"
  },
  "geometry": {"coordinates":[-2.769627,52.668226],"type":"Point"}
}
