{
  "type": "Feature",
  "properties": {
    "iso:country":"GB",
    "wof:name":"SY3 0BU",
    "wof:placetype":"postalcode"
},
  "geometry": {"coordinates":[-2.76962661596739,52.66822566975417],"type":"Point"}
}