{
  "type": "Feature",
  "properties": {
    "date:inception_lower": "1993-01-01",
    "date:inception_upper": "1993-01-01",
    "iso:country": "GB",
    "wof:name": "LS22 7TW",
    "wof:placetype": "postalcode"
  },
  "geometry": {"coordinates":[-1.379457,53.938329],"type":"Point"}
}
