{
  "type": "Feature",
  "properties": {
    "iso:country": "GB",
    "wof:name": "NW11 8SG",
    "wof:placetype": "postalcode"
  },
  "geometry": {"coordinates":[-0.200986,51.569291],"type":"Point"}
}
