{
  "type": "Feature",
  "properties": {
    "iso:country":"GB",
    "wof:name":"SM6 9QE",
    "wof:placetype":"postalcode"
},
  "geometry": {"coordinates":[-0.14672495497241,51.35112930085153],"type":"Point"}
}