{
  "type": "Feature",
  "properties": {
    "date:inception_lower":"1980-01-01",
    "date:inception_upper":"1980-01-31",
    "iso:country":"GB",
    "wof:name":"SE12 8TJ",
    "wof:placetype":"postalcode"
},
  "geometry": {"coordinates":[0.013954,51.45533],"type":"Point"}
}