{
  "type": "Feature",
  "properties": {
    "iso:country":"GB",
    "wof:name":"NE71 6HY",
    "wof:placetype":"postalcode"
},
  "geometry": {"coordinates":[-2.10753314333945,55.59766803860289],"type":"Point"}
}