{
  "type": "Feature",
  "properties": {
    "iso:country": "GB",
    "wof:name": "OL12 9BJ",
    "wof:placetype": "postalcode"
  },
  "geometry": {"coordinates":[-2.145519,53.62493],"type":"Point"}
}
