{
  "type": "Feature",
  "properties": {
    "iso:country":"GB",
    "wof:name":"AL7 3JD",
    "wof:placetype":"postalcode"
},
  "geometry": {"coordinates":[-0.18842425864716,51.79047449433529],"type":"Point"}
}