{
  "type": "Feature",
  "properties": {
    "date:inception_lower":"2009-09-01",
    "date:inception_upper":"2009-09-30",
    "iso:country":"GB",
    "wof:name":"YO24 1UJ",
    "wof:placetype":"postalcode"
},
  "geometry": {"coordinates":[-1.108341,53.933217],"type":"Point"}
}