{
  "type": "Feature",
  "properties": {
    "iso:country":"GB",
    "wof:name":"LD2 3RT",
    "wof:placetype":"postalcode"
},
  "geometry": {"coordinates":[-3.43229808073591,52.18757159582889],"type":"Point"}
}