{
  "type": "Feature",
  "properties": {
    "date:inception_lower": "1980-01-01",
    "date:inception_upper": "1980-01-01",
    "iso:country": "GB",
    "wof:name": "LD2 3RT",
    "wof:placetype": "postalcode"
  },
  "geometry": {"coordinates":[-3.432306,52.187581],"type":"Point"}
}
