{
  "type": "Feature",
  "properties": {
    "iso:country": "GB",
    "wof:name": "LD2 3RT",
    "wof:placetype": "postalcode"
  },
  "geometry": {"coordinates":[-3.432298,52.187572],"type":"Point"}
}
