{
  "type": "Feature",
  "properties": {
    "iso:country":"GB",
    "wof:name":"CF82 8FY",
    "wof:placetype":"postalcode"
},
  "geometry": {"coordinates":[-3.26932559775596,51.66452396532078],"type":"Point"}
}