{
  "type": "Feature",
  "properties": {
    "iso:country":"GB",
    "wof:name":"LE17 4FG",
    "wof:placetype":"postalcode"
},
  "geometry": {"coordinates":[-1.20070911854119,52.4597691690648],"type":"Point"}
}