{
  "type": "Feature",
  "properties": {
    "date:inception_lower": "2000-06-01",
    "date:inception_upper": "2000-06-01",
    "iso:country": "GB",
    "wof:name": "LE17 4FG",
    "wof:placetype": "postalcode"
  },
  "geometry": {"coordinates":[-1.200709,52.459769],"type":"Point"}
}
