{
  "type": "Feature",
  "properties": {
    "date:inception_lower": "1980-01-01",
    "date:inception_upper": "1980-01-01",
    "iso:country": "GB",
    "wof:name": "L17 9QR",
    "wof:placetype": "postalcode"
  },
  "geometry": {"coordinates":[-2.942684,53.371623],"type":"Point"}
}
