{
  "type": "Feature",
  "properties": {
    "date:inception_lower":"2005-03-01",
    "date:inception_upper":"2005-03-31",
    "iso:country":"GB",
    "wof:name":"G43 1SA",
    "wof:placetype":"postalcode"
},
  "geometry": {"coordinates":[-4.291539,55.824238],"type":"Point"}
}