{
  "type": "Feature",
  "properties": {
    "iso:country":"GB",
    "wof:name":"NG10 5PX",
    "wof:placetype":"postalcode"
},
  "geometry": {"coordinates":[-1.28868220546587,52.92842130089822],"type":"Point"}
}