{
  "type": "Feature",
  "properties": {
    "iso:country":"GB",
    "wof:name":"AB11 6XB",
    "wof:placetype":"postalcode"
},
  "geometry": {"coordinates":[-2.1097976178389,57.14078287727136],"type":"Point"}
}