{
  "type": "Feature",
  "properties": {
    "date:inception_lower":"2001-12-01",
    "date:inception_upper":"2001-12-31",
    "iso:country":"GB",
    "wof:name":"AB11 6XB",
    "wof:placetype":"postalcode"
},
  "geometry": {"coordinates":[-2.109805,57.140767],"type":"Point"}
}