{
  "type": "Feature",
  "properties": {
    "date:inception_lower": "1980-01-01",
    "date:inception_upper": "1980-01-01",
    "iso:country": "GB",
    "wof:name": "TR13 9JQ",
    "wof:placetype": "postalcode"
  },
  "geometry": {"coordinates":[-5.315701,50.082796],"type":"Point"}
}
