{
  "type": "Feature",
  "properties": {
    "iso:country":"GB",
    "wof:name":"TR13 9JQ",
    "wof:placetype":"postalcode"
},
  "geometry": {"coordinates":[-5.31562141950897,50.08281656317957],"type":"Point"}
}