{
  "type": "Feature",
  "properties": {
    "iso:country":"GB",
    "wof:name":"EN11 8HP",
    "wof:placetype":"postalcode"
},
  "geometry": {"coordinates":[-0.01056417849672,51.7620969107797],"type":"Point"}
}