{
  "type": "Feature",
  "properties": {
    "iso:country":"GB",
    "wof:name":"PE9 1EG",
    "wof:placetype":"postalcode"
},
  "geometry": {"coordinates":[-0.47934657365268,52.6542217423211],"type":"Point"}
}