{
  "type": "Feature",
  "properties": {
    "iso:country":"GB",
    "wof:name":"PE16 6BP",
    "wof:placetype":"postalcode"
},
  "geometry": {"coordinates":[0.04857867304931,52.4566698955221],"type":"Point"}
}