{
  "type": "Feature",
  "properties": {
    "iso:country": "GB",
    "wof:name": "PE16 6BP",
    "wof:placetype": "postalcode"
  },
  "geometry": {"coordinates":[0.048579,52.45667],"type":"Point"}
}
