{
  "type": "Feature",
  "properties": {
    "iso:country": "GB",
    "wof:name": "SA2 8NB",
    "wof:placetype": "postalcode"
  },
  "geometry": {"coordinates":[-3.999576,51.612848],"type":"Point"}
}
