{
  "type": "Feature",
  "properties": {
    "iso:country":"GB",
    "wof:name":"WR13 6DJ",
    "wof:placetype":"postalcode"
},
  "geometry": {"coordinates":[-2.34212350282425,52.08546691697671],"type":"Point"}
}