{
  "type": "Feature",
  "properties": {
    "iso:country":"GB",
    "wof:name":"AL6 0AN",
    "wof:placetype":"postalcode"
},
  "geometry": {"coordinates":[-0.18287568004672,51.82713936593252],"type":"Point"}
}