{
  "type": "Feature",
  "properties": {
    "iso:country": "GB",
    "wof:name": "AL6 0AN",
    "wof:placetype": "postalcode"
  },
  "geometry": {"coordinates":[-0.182876,51.827139],"type":"Point"}
}
