{
  "type": "Feature",
  "properties": {
    "iso:country":"GB",
    "wof:name":"CV11 4DR",
    "wof:placetype":"postalcode"
},
  "geometry": {"coordinates":[-1.46399954128013,52.52220711628689],"type":"Point"}
}