{
  "type": "Feature",
  "properties": {
    "date:inception_lower":"1980-01-01",
    "date:inception_upper":"1980-01-31",
    "iso:country":"GB",
    "wof:name":"RM17 5TB",
    "wof:placetype":"postalcode"
},
  "geometry": {"coordinates":[0.347082,51.48587],"type":"Point"}
}