{
  "type": "Feature",
  "properties": {
    "iso:country":"GB",
    "wof:name":"M22 4NH",
    "wof:placetype":"postalcode"
},
  "geometry": {"coordinates":[-2.25809691720728,53.40636670996521],"type":"Point"}
}