{
  "type": "Feature",
  "properties": {
    "iso:country":"GB",
    "wof:name":"LS26 8EP",
    "wof:placetype":"postalcode"
},
  "geometry": {"coordinates":[-1.44922480070954,53.74012392474828],"type":"Point"}
}