{
  "type": "Feature",
  "properties": {
    "iso:country": "GB",
    "wof:name": "CM3 2PT",
    "wof:placetype": "postalcode"
  },
  "geometry": {"coordinates":[0.5647,51.806562],"type":"Point"}
}
