{
  "type": "Feature",
  "properties": {
    "date:inception_lower": "2000-06-01",
    "date:inception_upper": "2000-06-01",
    "iso:country": "GB",
    "wof:name": "IP12 3SD",
    "wof:placetype": "postalcode"
  },
  "geometry": {"coordinates":[1.48443,52.116951],"type":"Point"}
}
