{
  "type": "Feature",
  "properties": {
    "iso:country":"GB",
    "wof:name":"HR7 4RA",
    "wof:placetype":"postalcode"
},
  "geometry": {"coordinates":[-2.56115013990453,52.13891271470347],"type":"Point"}
}