{
  "type": "Feature",
  "properties": {
    "date:inception_lower": "1980-01-01",
    "date:inception_upper": "1980-01-01",
    "iso:country": "GB",
    "wof:name": "GU5 0PF",
    "wof:placetype": "postalcode"
  },
  "geometry": {"coordinates":[-0.547185,51.197137],"type":"Point"}
}
