{
  "type": "Feature",
  "properties": {
    "iso:country":"GB",
    "wof:name":"YO19 5UE",
    "wof:placetype":"postalcode"
},
  "geometry": {"coordinates":[-0.97174642067655,53.97961873763153],"type":"Point"}
}