{
  "type": "Feature",
  "properties": {
    "iso:country": "GB",
    "wof:name": "YO19 5UE",
    "wof:placetype": "postalcode"
  },
  "geometry": {"coordinates":[-0.971755,53.979628],"type":"Point"}
}
