{
  "type": "Feature",
  "properties": {
    "iso:country": "GB",
    "wof:name": "YO19 5UE",
    "wof:placetype": "postalcode"
  },
  "geometry": {"coordinates":[-0.971746,53.979619],"type":"Point"}
}
