{
  "type": "Feature",
  "properties": {
    "iso:country":"GB",
    "wof:name":"NG25 0AH",
    "wof:placetype":"postalcode"
},
  "geometry": {"coordinates":[-0.96235036082422,53.0797149645883],"type":"Point"}
}