{
  "type": "Feature",
  "properties": {
    "iso:country":"GB",
    "wof:name":"CF5 4UD",
    "wof:placetype":"postalcode"
},
  "geometry": {"coordinates":[-3.27498402586808,51.47442866937971],"type":"Point"}
}