{
  "type": "Feature",
  "properties": {
    "iso:country":"GB",
    "wof:name":"NG18 5HJ",
    "wof:placetype":"postalcode"
},
  "geometry": {"coordinates":[-1.22304738529821,53.13597888027574],"type":"Point"}
}