{
  "type": "Feature",
  "properties": {
    "date:inception_lower": "1980-01-01",
    "date:inception_upper": "1980-01-01",
    "iso:country": "GB",
    "wof:name": "NG18 5HJ",
    "wof:placetype": "postalcode"
  },
  "geometry": {"coordinates":[-1.223047,53.135979],"type":"Point"}
}
