{
  "type": "Feature",
  "properties": {
    "iso:country":"GB",
    "wof:name":"NP25 4SF",
    "wof:placetype":"postalcode"
},
  "geometry": {"coordinates":[-2.69688213958336,51.7761421723967],"type":"Point"}
}