{
  "type": "Feature",
  "properties": {
    "iso:country":"GB",
    "wof:name":"OX16 9HP",
    "wof:placetype":"postalcode"
},
  "geometry": {"coordinates":[-1.34000051234676,52.05175141162065],"type":"Point"}
}