{
  "type": "Feature",
  "properties": {
    "iso:country": "GB",
    "wof:name": "OX16 9HP",
    "wof:placetype": "postalcode"
  },
  "geometry": {"coordinates":[-1.34,52.051751],"type":"Point"}
}
