{
  "type": "Feature",
  "properties": {
    "iso:country":"GB",
    "wof:name":"M40 9DN",
    "wof:placetype":"postalcode"
},
  "geometry": {"coordinates":[-2.19503133174192,53.50935070892696],"type":"Point"}
}