{
  "type": "Feature",
  "properties": {
    "date:inception_lower": "1994-05-01",
    "date:inception_upper": "1994-05-01",
    "iso:country": "GB",
    "wof:name": "M40 9DN",
    "wof:placetype": "postalcode"
  },
  "geometry": {"coordinates":[-2.195031,53.509351],"type":"Point"}
}
