{
  "type": "Feature",
  "properties": {
    "date:inception_lower":"1980-01-01",
    "date:inception_upper":"1980-01-31",
    "iso:country":"GB",
    "wof:name":"NG7 4EL",
    "wof:placetype":"postalcode"
},
  "geometry": {"coordinates":[-1.167134,52.959158],"type":"Point"}
}