{
  "type": "Feature",
  "properties": {
    "iso:country":"GB",
    "wof:name":"BS23 2QJ",
    "wof:placetype":"postalcode"
},
  "geometry": {"coordinates":[-2.97942392960955,51.35278680787105],"type":"Point"}
}