{
  "type": "Feature",
  "properties": {
    "iso:country": "GB",
    "wof:name": "NP20 6QP",
    "wof:placetype": "postalcode"
  },
  "geometry": {"coordinates":[-3.006131,51.619536],"type":"Point"}
}
