{
  "type": "Feature",
  "properties": {
    "iso:country":"GB",
    "wof:name":"B29 7NX",
    "wof:placetype":"postalcode"
},
  "geometry": {"coordinates":[-1.91437265349694,52.44561667720284],"type":"Point"}
}