{
  "type": "Feature",
  "properties": {
    "iso:country":"GB",
    "wof:name":"YO32 2HU",
    "wof:placetype":"postalcode"
},
  "geometry": {"coordinates":[-1.07668253338683,54.0163237748401],"type":"Point"}
}