{
  "type": "Feature",
  "properties": {
    "iso:country": "GB",
    "wof:name": "LL55 9DA",
    "wof:placetype": "postalcode"
  },
  "geometry": {"coordinates":[-4.248185,53.140294],"type":"Point"}
}
