{
  "type": "Feature",
  "properties": {
    "iso:country": "GB",
    "wof:name": "IP14 6NB",
    "wof:placetype": "postalcode"
  },
  "geometry": {"coordinates":[1.24124,52.224941],"type":"Point"}
}
