{
  "type": "Feature",
  "properties": {
    "iso:country":"GB",
    "wof:name":"IP14 6NB",
    "wof:placetype":"postalcode"
},
  "geometry": {"coordinates":[1.24114738124535,52.22486231866084],"type":"Point"}
}