{
  "type": "Feature",
  "properties": {
    "iso:country":"GB",
    "wof:name":"CO7 7EP",
    "wof:placetype":"postalcode"
},
  "geometry": {"coordinates":[0.98000735005459,51.86980359146263],"type":"Point"}
}