{
  "type": "Feature",
  "properties": {
    "iso:country": "GB",
    "wof:name": "CO7 7EP",
    "wof:placetype": "postalcode"
  },
  "geometry": {"coordinates":[0.980007,51.869804],"type":"Point"}
}
