{
  "type": "Feature",
  "properties": {
    "date:inception_lower": "2004-01-01",
    "date:inception_upper": "2004-01-01",
    "iso:country": "GB",
    "wof:name": "CO7 7EP",
    "wof:placetype": "postalcode"
  },
  "geometry": {"coordinates":[0.980024,51.869401],"type":"Point"}
}
