{
  "type": "Feature",
  "properties": {
    "iso:country":"GB",
    "wof:name":"B26 1LY",
    "wof:placetype":"postalcode"
},
  "geometry": {"coordinates":[-1.79488423300458,52.45981814776194],"type":"Point"}
}