{
  "type": "Feature",
  "properties": {
    "iso:country": "GB",
    "wof:name": "OX14 5FT",
    "wof:placetype": "postalcode"
  },
  "geometry": {"coordinates":[-1.284032,51.67005],"type":"Point"}
}
