{
  "type": "Feature",
  "properties": {
    "date:inception_lower": "2020-08-01",
    "date:inception_upper": "2020-08-01",
    "iso:country": "GB",
    "wof:name": "NR6 7GD",
    "wof:placetype": "postalcode"
  },
  "geometry": {"coordinates":[1.308593,52.669533],"type":"Point"}
}
