{
  "type": "Feature",
  "properties": {
    "iso:country":"GB",
    "wof:name":"M24 1WU",
    "wof:placetype":"postalcode"
},
  "geometry": {"coordinates":[-2.20034895431231,53.53381728705931],"type":"Point"}
}