{
  "type": "Feature",
  "properties": {
    "iso:country":"GB",
    "wof:name":"NE42 6EY",
    "wof:placetype":"postalcode"
},
  "geometry": {"coordinates":[-1.85462985556174,54.95862579323067],"type":"Point"}
}