{
  "type": "Feature",
  "properties": {
    "iso:country": "GB",
    "wof:name": "NE42 6EY",
    "wof:placetype": "postalcode"
  },
  "geometry": {"coordinates":[-1.85463,54.958626],"type":"Point"}
}
