{
  "type": "Feature",
  "properties": {
    "iso:country":"GB",
    "wof:name":"SW16 5LP",
    "wof:placetype":"postalcode"
},
  "geometry": {"coordinates":[-0.13058927665167,51.41622282433031],"type":"Point"}
}