{
  "type": "Feature",
  "properties": {
    "iso:country":"GB",
    "wof:name":"TW9 4BS",
    "wof:placetype":"postalcode"
},
  "geometry": {"coordinates":[-0.27720463250271,51.47632712589919],"type":"Point"}
}