{
  "type": "Feature",
  "properties": {
    "date:inception_lower": "2002-06-01",
    "date:inception_upper": "2002-06-01",
    "iso:country": "GB",
    "wof:name": "TW9 4BS",
    "wof:placetype": "postalcode"
  },
  "geometry": {"coordinates":[-0.277205,51.476327],"type":"Point"}
}
