{
  "type": "Feature",
  "properties": {
    "date:inception_lower": "1980-01-01",
    "date:inception_upper": "1980-01-01",
    "iso:country": "GB",
    "wof:name": "NG19 8JX",
    "wof:placetype": "postalcode"
  },
  "geometry": {"coordinates":[-1.185138,53.170019],"type":"Point"}
}
