{
  "type": "Feature",
  "properties": {
    "iso:country":"GB",
    "wof:name":"NG19 8JX",
    "wof:placetype":"postalcode"
},
  "geometry": {"coordinates":[-1.18513848864346,53.17001932770454],"type":"Point"}
}