{
  "type": "Feature",
  "properties": {
    "iso:country":"GB",
    "wof:name":"NP22 4HG",
    "wof:placetype":"postalcode"
},
  "geometry": {"coordinates":[-3.27730141501761,51.80708051733198],"type":"Point"}
}