{
  "type": "Feature",
  "properties": {
    "iso:country": "GB",
    "wof:name": "NE24 4AT",
    "wof:placetype": "postalcode"
  },
  "geometry": {"coordinates":[-1.53163,55.107063],"type":"Point"}
}
