{
  "type": "Feature",
  "properties": {
    "iso:country": "GB",
    "wof:name": "WS11 1JU",
    "wof:placetype": "postalcode"
  },
  "geometry": {"coordinates":[-2.02759,52.692701],"type":"Point"}
}
