{
  "type": "Feature",
  "properties": {
    "iso:country":"GB",
    "wof:name":"LN6 8SN",
    "wof:placetype":"postalcode"
},
  "geometry": {"coordinates":[-0.58637620341727,53.19830127993186],"type":"Point"}
}