{
  "type": "Feature",
  "properties": {
    "iso:country": "GB",
    "wof:name": "LN6 8SN",
    "wof:placetype": "postalcode"
  },
  "geometry": {"coordinates":[-0.586376,53.198301],"type":"Point"}
}
