{
  "type": "Feature",
  "properties": {
    "iso:country": "GB",
    "wof:name": "B45 9AL",
    "wof:placetype": "postalcode"
  },
  "geometry": {"coordinates":[-2.025502,52.394001],"type":"Point"}
}
