{
  "type": "Feature",
  "properties": {
    "date:inception_lower": "1980-01-01",
    "date:inception_upper": "1980-01-01",
    "iso:country": "GB",
    "wof:name": "B45 9AL",
    "wof:placetype": "postalcode"
  },
  "geometry": {"coordinates":[-2.025502,52.394001],"type":"Point"}
}
