{
  "type": "Feature",
  "properties": {
    "date:inception_lower":"1981-06-01",
    "date:inception_upper":"1981-06-30",
    "iso:country":"GB",
    "wof:name":"PL17 7HG",
    "wof:placetype":"postalcode"
},
  "geometry": {"coordinates":[-4.307023,50.501065],"type":"Point"}
}