{
  "type": "Feature",
  "properties": {
    "date:inception_lower": "1980-01-01",
    "date:inception_upper": "1980-01-01",
    "iso:country": "GB",
    "wof:name": "NG11 0JA",
    "wof:placetype": "postalcode"
  },
  "geometry": {"coordinates":[-1.202682,52.866935],"type":"Point"}
}
