{
  "type": "Feature",
  "properties": {
    "iso:country":"GB",
    "wof:name":"NG11 0JA",
    "wof:placetype":"postalcode"
},
  "geometry": {"coordinates":[-1.20268158239245,52.86693535268236],"type":"Point"}
}