{
  "type": "Feature",
  "properties": {
    "iso:country":"GB",
    "wof:name":"DA11 7AS",
    "wof:placetype":"postalcode"
},
  "geometry": {"coordinates":[0.35112288667455,51.43280067593987],"type":"Point"}
}