{
  "type": "Feature",
  "properties": {
    "iso:country":"GB",
    "wof:name":"BA1 8AE",
    "wof:placetype":"postalcode"
},
  "geometry": {"coordinates":[-2.36757944116646,51.43335513336753],"type":"Point"}
}