{
  "type": "Feature",
  "properties": {
    "iso:country": "GB",
    "wof:name": "SP4 0DY",
    "wof:placetype": "postalcode"
  },
  "geometry": {"coordinates":[-1.656435,51.177316],"type":"Point"}
}
