{
  "type": "Feature",
  "properties": {
    "date:inception_lower":"1980-01-01",
    "date:inception_upper":"1980-01-31",
    "iso:country":"GB",
    "wof:name":"SP4 0DY",
    "wof:placetype":"postalcode"
},
  "geometry": {"coordinates":[-1.656435,51.177316],"type":"Point"}
}