{
  "type": "Feature",
  "properties": {
    "iso:country":"GB",
    "wof:name":"SP4 0DY",
    "wof:placetype":"postalcode"
},
  "geometry": {"coordinates":[-1.65643481322182,51.17731615377949],"type":"Point"}
}