{
  "type": "Feature",
  "properties": {
    "iso:country":"GB",
    "wof:name":"G41 5SU",
    "wof:placetype":"postalcode"
},
  "geometry": {"coordinates":[-4.27797767366476,55.84514338745663],"type":"Point"}
}