{
  "type": "Feature",
  "properties": {
    "date:inception_lower": "1993-08-01",
    "date:inception_upper": "1993-08-01",
    "iso:country": "GB",
    "wof:name": "SY23 3YA",
    "wof:placetype": "postalcode"
  },
  "geometry": {"coordinates":[-4.061804,52.400432],"type":"Point"}
}
