{
  "type": "Feature",
  "properties": {
    "iso:country":"GB",
    "wof:name":"SY23 3YA",
    "wof:placetype":"postalcode"
},
  "geometry": {"coordinates":[-4.06180422731233,52.40043160777254],"type":"Point"}
}