{
  "type": "Feature",
  "properties": {
    "iso:country": "GB",
    "wof:name": "SY23 3YA",
    "wof:placetype": "postalcode"
  },
  "geometry": {"coordinates":[-4.061804,52.400432],"type":"Point"}
}
