{
  "type": "Feature",
  "properties": {
    "iso:country":"GB",
    "wof:name":"LE17 6JE",
    "wof:placetype":"postalcode"
},
  "geometry": {"coordinates":[-1.11449664076302,52.44635322744734],"type":"Point"}
}