{
  "type": "Feature",
  "properties": {
    "date:inception_lower": "1980-01-01",
    "date:inception_upper": "1980-01-01",
    "iso:country": "GB",
    "wof:name": "LE17 6JE",
    "wof:placetype": "postalcode"
  },
  "geometry": {"coordinates":[-1.114497,52.446353],"type":"Point"}
}
