{
  "type": "Feature",
  "properties": {
    "iso:country": "GB",
    "wof:name": "CV35 9DE",
    "wof:placetype": "postalcode"
  },
  "geometry": {"coordinates":[-1.543875,52.191756],"type":"Point"}
}
