{
  "type": "Feature",
  "properties": {
    "iso:country":"GB",
    "wof:name":"SP2 0JL",
    "wof:placetype":"postalcode"
},
  "geometry": {"coordinates":[-1.87330283110894,51.08896414510794],"type":"Point"}
}