{
  "type": "Feature",
  "properties": {
    "date:inception_lower": "1997-06-01",
    "date:inception_upper": "1997-06-01",
    "iso:country": "GB",
    "wof:name": "GL7 1FA",
    "wof:placetype": "postalcode"
  },
  "geometry": {"coordinates":[-1.965351,51.706078],"type":"Point"}
}
