{
  "type": "Feature",
  "properties": {
    "iso:country":"GB",
    "wof:name":"BL1 6DY",
    "wof:placetype":"postalcode"
},
  "geometry": {"coordinates":[-2.45133149946181,53.59117092214174],"type":"Point"}
}