{
  "type": "Feature",
  "properties": {
    "iso:country": "GB",
    "wof:name": "GL8 8YB",
    "wof:placetype": "postalcode"
  },
  "geometry": {"coordinates":[-2.277125,51.665753],"type":"Point"}
}
