{
  "type": "Feature",
  "properties": {
    "iso:country":"GB",
    "wof:name":"GL8 8YB",
    "wof:placetype":"postalcode"
},
  "geometry": {"coordinates":[-2.27712505400774,51.66575329129201],"type":"Point"}
}