{
  "type": "Feature",
  "properties": {
    "date:inception_lower": "1980-01-01",
    "date:inception_upper": "1980-01-01",
    "iso:country": "GB",
    "wof:name": "GL8 8YB",
    "wof:placetype": "postalcode"
  },
  "geometry": {"coordinates":[-2.277125,51.665753],"type":"Point"}
}
