{
  "type": "Feature",
  "properties": {
    "iso:country":"GB",
    "wof:name":"SE20 8UT",
    "wof:placetype":"postalcode"
},
  "geometry": {"coordinates":[-0.06100951518064,51.41354551384509],"type":"Point"}
}