{
  "type": "Feature",
  "properties": {
    "iso:country": "GB",
    "wof:name": "SE20 8UT",
    "wof:placetype": "postalcode"
  },
  "geometry": {"coordinates":[-0.060983,51.413545],"type":"Point"}
}
