{
  "type": "Feature",
  "properties": {
    "date:inception_lower":"2003-04-01",
    "date:inception_upper":"2003-04-30",
    "iso:country":"GB",
    "wof:name":"LA1 3RN",
    "wof:placetype":"postalcode"
},
  "geometry": {"coordinates":[-2.774709,54.046122],"type":"Point"}
}