{
  "type": "Feature",
  "properties": {
    "iso:country": "GB",
    "wof:name": "LA1 3RN",
    "wof:placetype": "postalcode"
  },
  "geometry": {"coordinates":[-2.774709,54.046122],"type":"Point"}
}
