{
  "type": "Feature",
  "properties": {
    "iso:country":"GB",
    "wof:name":"CV21 2JW",
    "wof:placetype":"postalcode"
},
  "geometry": {"coordinates":[-1.27450145359882,52.37565548151572],"type":"Point"}
}