{
  "type": "Feature",
  "properties": {
    "iso:country":"GB",
    "wof:name":"EH6 8LS",
    "wof:placetype":"postalcode"
},
  "geometry": {"coordinates":[-3.17217469179585,55.9696803589346],"type":"Point"}
}