{
  "type": "Feature",
  "properties": {
    "iso:country": "GB",
    "wof:name": "EH6 8LS",
    "wof:placetype": "postalcode"
  },
  "geometry": {"coordinates":[-3.172175,55.96968],"type":"Point"}
}
