{
  "type": "Feature",
  "properties": {
    "iso:country": "GB",
    "wof:name": "PA10 2AT",
    "wof:placetype": "postalcode"
  },
  "geometry": {"coordinates":[-4.543275,55.830262],"type":"Point"}
}
