{
  "type": "Feature",
  "properties": {
    "iso:country":"GB",
    "wof:name":"PA10 2AT",
    "wof:placetype":"postalcode"
},
  "geometry": {"coordinates":[-4.54327458222555,55.83026245157303],"type":"Point"}
}