{
  "type": "Feature",
  "properties": {
    "date:inception_lower":"1980-01-01",
    "date:inception_upper":"1980-01-31",
    "iso:country":"GB",
    "wof:name":"PA10 2AT",
    "wof:placetype":"postalcode"
},
  "geometry": {"coordinates":[-4.543275,55.830262],"type":"Point"}
}