{
  "type": "Feature",
  "properties": {
    "iso:country":"GB",
    "wof:name":"SG5 2SZ",
    "wof:placetype":"postalcode"
},
  "geometry": {"coordinates":[-0.28760098421248,51.9615108987428],"type":"Point"}
}