{
  "type": "Feature",
  "properties": {
    "iso:country":"GB",
    "wof:name":"PR8 2SJ",
    "wof:placetype":"postalcode"
},
  "geometry": {"coordinates":[-3.05241142069194,53.6019092480128],"type":"Point"}
}