{
  "type": "Feature",
  "properties": {
    "iso:country": "GB",
    "wof:name": "PR8 2SJ",
    "wof:placetype": "postalcode"
  },
  "geometry": {"coordinates":[-3.052411,53.601909],"type":"Point"}
}
