{
  "type": "Feature",
  "properties": {
    "date:inception_lower": "1980-01-01",
    "date:inception_upper": "1980-01-01",
    "iso:country": "GB",
    "wof:name": "TA24 6JS",
    "wof:placetype": "postalcode"
  },
  "geometry": {"coordinates":[-3.390872,51.181038],"type":"Point"}
}
