{
  "type": "Feature",
  "properties": {
    "iso:country":"GB",
    "wof:name":"EN4 9TU",
    "wof:placetype":"postalcode"
},
  "geometry": {"coordinates":[-0.15586740816423,51.65286421099962],"type":"Point"}
}