{
  "type": "Feature",
  "properties": {
    "date:inception_lower": "1995-07-01",
    "date:inception_upper": "1995-07-01",
    "iso:country": "GB",
    "wof:name": "EN4 9TU",
    "wof:placetype": "postalcode"
  },
  "geometry": {"coordinates":[-0.155867,51.652864],"type":"Point"}
}
