{
  "type": "Feature",
  "properties": {
    "iso:country": "GB",
    "wof:name": "EN4 9TU",
    "wof:placetype": "postalcode"
  },
  "geometry": {"coordinates":[-0.155867,51.652864],"type":"Point"}
}
