{
  "type": "Feature",
  "properties": {
    "iso:country":"GB",
    "wof:name":"HX2 9ES",
    "wof:placetype":"postalcode"
},
  "geometry": {"coordinates":[-1.88907032418112,53.75374060410017],"type":"Point"}
}