{
  "type": "Feature",
  "properties": {
    "iso:country": "GB",
    "wof:name": "HX2 9ES",
    "wof:placetype": "postalcode"
  },
  "geometry": {"coordinates":[-1.88907,53.753741],"type":"Point"}
}
