{
  "type": "Feature",
  "properties": {
    "date:inception_lower": "2011-08-01",
    "date:inception_upper": "2011-08-01",
    "iso:country": "GB",
    "wof:name": "RG14 1DP",
    "wof:placetype": "postalcode"
  },
  "geometry": {"coordinates":[-1.32369,51.403848],"type":"Point"}
}
