{
  "type": "Feature",
  "properties": {
    "date:inception_lower": "2017-02-01",
    "date:inception_upper": "2017-02-01",
    "iso:country": "GB",
    "wof:name": "L8 5AF",
    "wof:placetype": "postalcode"
  },
  "geometry": {"coordinates":[-2.977736,53.392654],"type":"Point"}
}
