{
  "type": "Feature",
  "properties": {
    "iso:country":"GB",
    "wof:name":"EX8 4RY",
    "wof:placetype":"postalcode"
},
  "geometry": {"coordinates":[-3.38476726278438,50.62906489254445],"type":"Point"}
}