{
  "type": "Feature",
  "properties": {
    "date:inception_lower": "1980-01-01",
    "date:inception_upper": "1980-01-01",
    "iso:country": "GB",
    "wof:name": "NE16 5RW",
    "wof:placetype": "postalcode"
  },
  "geometry": {"coordinates":[-1.692085,54.93557],"type":"Point"}
}
