{
  "type": "Feature",
  "properties": {
    "iso:country": "GB",
    "wof:name": "HU9 3SH",
    "wof:placetype": "postalcode"
  },
  "geometry": {"coordinates":[-0.284733,53.760947],"type":"Point"}
}
