{
  "type": "Feature",
  "properties": {
    "date:inception_lower":"1997-06-01",
    "date:inception_upper":"1997-06-30",
    "iso:country":"GB",
    "wof:name":"S25 1YB",
    "wof:placetype":"postalcode"
},
  "geometry": {"coordinates":[-1.224701,53.38752],"type":"Point"}
}