{
  "type": "Feature",
  "properties": {
    "iso:country": "GB",
    "wof:name": "S25 1YB",
    "wof:placetype": "postalcode"
  },
  "geometry": {"coordinates":[-1.224701,53.38752],"type":"Point"}
}
