{
  "type": "Feature",
  "properties": {
    "iso:country":"GB",
    "wof:name":"PO20 1LH",
    "wof:placetype":"postalcode"
},
  "geometry": {"coordinates":[-0.74495070001049,50.81636477866227],"type":"Point"}
}