{
  "type": "Feature",
  "properties": {
    "iso:country": "GB",
    "wof:name": "PO20 1LH",
    "wof:placetype": "postalcode"
  },
  "geometry": {"coordinates":[-0.744951,50.816365],"type":"Point"}
}
