{
  "type": "Feature",
  "properties": {
    "iso:country": "GB",
    "wof:name": "AB51 4WX",
    "wof:placetype": "postalcode"
  },
  "geometry": {"coordinates":[-2.3915,57.293245],"type":"Point"}
}
