{
  "type": "Feature",
  "properties": {
    "iso:country":"GB",
    "wof:name":"BB5 5HS",
    "wof:placetype":"postalcode"
},
  "geometry": {"coordinates":[-2.38679677920144,53.77338097014628],"type":"Point"}
}