{
  "type": "Feature",
  "properties": {
    "date:inception_lower": "2006-08-01",
    "date:inception_upper": "2006-08-01",
    "iso:country": "GB",
    "wof:name": "SP5 4EF",
    "wof:placetype": "postalcode"
  },
  "geometry": {"coordinates":[-1.756983,51.039126],"type":"Point"}
}
