{
  "type": "Feature",
  "properties": {
    "iso:country": "GB",
    "wof:name": "SP5 4EF",
    "wof:placetype": "postalcode"
  },
  "geometry": {"coordinates":[-1.756983,51.039126],"type":"Point"}
}
