{
  "type": "Feature",
  "properties": {
    "iso:country":"GB",
    "wof:name":"BH21 1NZ",
    "wof:placetype":"postalcode"
},
  "geometry": {"coordinates":[-1.98598361078476,50.80599847364825],"type":"Point"}
}