{
  "type": "Feature",
  "properties": {
    "iso:country":"GB",
    "wof:name":"BD5 7EY",
    "wof:placetype":"postalcode"
},
  "geometry": {"coordinates":[-1.75233763259976,53.77911632135595],"type":"Point"}
}