{
  "type": "Feature",
  "properties": {
    "iso:country":"GB",
    "wof:name":"KY6 2LG",
    "wof:placetype":"postalcode"
},
  "geometry": {"coordinates":[-3.20471428803327,56.18996486959436],"type":"Point"}
}