{
  "type": "Feature",
  "properties": {
    "iso:country":"GB",
    "wof:name":"BH5 2AN",
    "wof:placetype":"postalcode"
},
  "geometry": {"coordinates":[-1.82371494023526,50.72692040495755],"type":"Point"}
}