{
  "type": "Feature",
  "properties": {
    "iso:country":"GB",
    "wof:name":"L3 2BB",
    "wof:placetype":"postalcode"
},
  "geometry": {"coordinates":[-2.98814222172612,53.41212883737789],"type":"Point"}
}