{
  "type": "Feature",
  "properties": {
    "date:inception_lower":"2008-10-01",
    "date:inception_upper":"2008-10-31",
    "iso:country":"GB",
    "wof:name":"L3 2BB",
    "wof:placetype":"postalcode"
},
  "geometry": {"coordinates":[-2.988142,53.412129],"type":"Point"}
}