{
  "type": "Feature",
  "properties": {
    "iso:country": "GB",
    "wof:name": "L3 2BB",
    "wof:placetype": "postalcode"
  },
  "geometry": {"coordinates":[-2.988142,53.412129],"type":"Point"}
}
