{
  "type": "Feature",
  "properties": {
    "date:inception_lower": "1980-01-01",
    "date:inception_upper": "1980-01-01",
    "iso:country": "GB",
    "wof:name": "CO7 8QU",
    "wof:placetype": "postalcode"
  },
  "geometry": {"coordinates":[1.076667,51.84977],"type":"Point"}
}
