{
  "type": "Feature",
  "properties": {
    "iso:country":"GB",
    "wof:name":"CO7 8QU",
    "wof:placetype":"postalcode"
},
  "geometry": {"coordinates":[1.07663545884085,51.84975831964608],"type":"Point"}
}