{
  "type": "Feature",
  "properties": {
    "iso:country":"GB",
    "wof:name":"AL4 8AL",
    "wof:placetype":"postalcode"
},
  "geometry": {"coordinates":[-0.30042643966408,51.80812562634732],"type":"Point"}
}