{
  "type": "Feature",
  "properties": {
    "iso:country": "GB",
    "wof:name": "SL9 7EB",
    "wof:placetype": "postalcode"
  },
  "geometry": {"coordinates":[-0.550601,51.57758],"type":"Point"}
}
