{
  "type": "Feature",
  "properties": {
    "date:inception_lower":"1990-07-01",
    "date:inception_upper":"1990-07-31",
    "iso:country":"GB",
    "wof:name":"IG7 5PT",
    "wof:placetype":"postalcode"
},
  "geometry": {"coordinates":[0.086489,51.6121],"type":"Point"}
}