{
  "type": "Feature",
  "properties": {
    "iso:country":"GB",
    "wof:name":"IG7 5PT",
    "wof:placetype":"postalcode"
},
  "geometry": {"coordinates":[0.08648928323494,51.61209974936093],"type":"Point"}
}