{
  "type": "Feature",
  "properties": {
    "iso:country":"GB",
    "wof:name":"ME3 8AU",
    "wof:placetype":"postalcode"
},
  "geometry": {"coordinates":[0.50645955407464,51.41028988490796],"type":"Point"}
}