{
  "type": "Feature",
  "properties": {
    "date:inception_lower": "1980-01-01",
    "date:inception_upper": "1980-01-01",
    "iso:country": "GB",
    "wof:name": "ME3 8AU",
    "wof:placetype": "postalcode"
  },
  "geometry": {"coordinates":[0.50646,51.41029],"type":"Point"}
}
