{
  "type": "Feature",
  "properties": {
    "iso:country": "GB",
    "wof:name": "S64 9HF",
    "wof:placetype": "postalcode"
  },
  "geometry": {"coordinates":[-1.301678,53.499922],"type":"Point"}
}
