{
  "type": "Feature",
  "properties": {
    "iso:country":"GB",
    "wof:name":"S64 9HF",
    "wof:placetype":"postalcode"
},
  "geometry": {"coordinates":[-1.30167826051078,53.49992181168663],"type":"Point"}
}