{
  "type": "Feature",
  "properties": {
    "iso:country":"GB",
    "wof:name":"N11 2BP",
    "wof:placetype":"postalcode"
},
  "geometry": {"coordinates":[-0.12173276415473,51.61166868684372],"type":"Point"}
}