{
  "type": "Feature",
  "properties": {
    "date:inception_lower":"1980-01-01",
    "date:inception_upper":"1980-01-31",
    "iso:country":"GB",
    "wof:name":"N11 2BP",
    "wof:placetype":"postalcode"
},
  "geometry": {"coordinates":[-0.121733,51.611669],"type":"Point"}
}