{
  "type": "Feature",
  "properties": {
    "iso:country":"GB",
    "wof:name":"BD18 4HA",
    "wof:placetype":"postalcode"
},
  "geometry": {"coordinates":[-1.80088966278303,53.8353544352196],"type":"Point"}
}