{
  "type": "Feature",
  "properties": {
    "iso:country": "GB",
    "wof:name": "LN6 9GP",
    "wof:placetype": "postalcode"
  },
  "geometry": {"coordinates":[-0.619415,53.179652],"type":"Point"}
}
