{
  "type": "Feature",
  "properties": {
    "iso:country":"GB",
    "wof:name":"DA17 6AQ",
    "wof:placetype":"postalcode"
},
  "geometry": {"coordinates":[0.16126676061848,51.49650172025596],"type":"Point"}
}