{
  "type": "Feature",
  "properties": {
    "iso:country":"GB",
    "wof:name":"W1S 4HR",
    "wof:placetype":"postalcode"
},
  "geometry": {"coordinates":[-0.14202191762379,51.50945979047494],"type":"Point"}
}