{
  "type": "Feature",
  "properties": {
    "iso:country": "GB",
    "wof:name": "TA3 6SG",
    "wof:placetype": "postalcode"
  },
  "geometry": {"coordinates":[-2.996986,50.979379],"type":"Point"}
}
