{
  "type": "Feature",
  "properties": {
    "iso:country":"GB",
    "wof:name":"TA3 6SG",
    "wof:placetype":"postalcode"
},
  "geometry": {"coordinates":[-2.99698583421126,50.97937850778286],"type":"Point"}
}