{
  "type": "Feature",
  "properties": {
    "iso:country":"GB",
    "wof:name":"CW5 5JX",
    "wof:placetype":"postalcode"
},
  "geometry": {"coordinates":[-2.53221442176537,53.06148009097031],"type":"Point"}
}