{
  "type": "Feature",
  "properties": {
    "date:inception_lower":"1980-01-01",
    "date:inception_upper":"1980-01-31",
    "iso:country":"GB",
    "wof:name":"CW5 5JX",
    "wof:placetype":"postalcode"
},
  "geometry": {"coordinates":[-2.532245,53.061496],"type":"Point"}
}