{
  "type": "Feature",
  "properties": {
    "iso:country": "GB",
    "wof:name": "OL7 0FU",
    "wof:placetype": "postalcode"
  },
  "geometry": {"coordinates":[-2.110242,53.479167],"type":"Point"}
}
