{
  "type": "Feature",
  "properties": {
    "date:inception_lower": "2019-06-01",
    "date:inception_upper": "2019-06-01",
    "iso:country": "GB",
    "wof:name": "OL7 0FU",
    "wof:placetype": "postalcode"
  },
  "geometry": {"coordinates":[-2.114846,53.488097],"type":"Point"}
}
