{
  "type": "Feature",
  "properties": {
    "iso:country":"GB",
    "wof:name":"WA4 2UY",
    "wof:placetype":"postalcode"
},
  "geometry": {"coordinates":[-2.57119857657156,53.37493302046443],"type":"Point"}
}