{
  "type": "Feature",
  "properties": {
    "iso:country": "GB",
    "wof:name": "WA4 2UY",
    "wof:placetype": "postalcode"
  },
  "geometry": {"coordinates":[-2.571242,53.374859],"type":"Point"}
}
