{
  "type": "Feature",
  "properties": {
    "iso:country":"GB",
    "wof:name":"EC1R 0AL",
    "wof:placetype":"postalcode"
},
  "geometry": {"coordinates":[-0.10616097135363,51.52386778295983],"type":"Point"}
}