{
  "type": "Feature",
  "properties": {
    "date:inception_lower": "1985-04-01",
    "date:inception_upper": "1985-04-01",
    "iso:country": "GB",
    "wof:name": "RM17 6HS",
    "wof:placetype": "postalcode"
  },
  "geometry": {"coordinates":[0.338863,51.476699],"type":"Point"}
}
