{
  "type": "Feature",
  "properties": {
    "iso:country": "GB",
    "wof:name": "WN5 7QP",
    "wof:placetype": "postalcode"
  },
  "geometry": {"coordinates":[-2.720033,53.488626],"type":"Point"}
}
