{
  "type": "Feature",
  "properties": {
    "iso:country":"GB",
    "wof:name":"WN5 7QP",
    "wof:placetype":"postalcode"
},
  "geometry": {"coordinates":[-2.72003318331009,53.4886260155796],"type":"Point"}
}