{
  "type": "Feature",
  "properties": {
    "date:inception_lower":"1985-10-01",
    "date:inception_upper":"1985-10-31",
    "iso:country":"GB",
    "wof:name":"SL0 9PJ",
    "wof:placetype":"postalcode"
},
  "geometry": {"coordinates":[-0.508816,51.520856],"type":"Point"}
}