{
  "type": "Feature",
  "properties": {
    "iso:country": "GB",
    "wof:name": "SL0 9PJ",
    "wof:placetype": "postalcode"
  },
  "geometry": {"coordinates":[-0.508816,51.520856],"type":"Point"}
}
