{
  "type": "Feature",
  "properties": {
    "iso:country":"GB",
    "wof:name":"EH39 4JH",
    "wof:placetype":"postalcode"
},
  "geometry": {"coordinates":[-2.72078471728911,56.05869258026355],"type":"Point"}
}