{
  "type": "Feature",
  "properties": {
    "iso:country":"GB",
    "wof:name":"NE64 6ST",
    "wof:placetype":"postalcode"
},
  "geometry": {"coordinates":[-1.52323039379177,55.1793235737344],"type":"Point"}
}