{
  "type": "Feature",
  "properties": {
    "iso:country": "GB",
    "wof:name": "RG42 1TZ",
    "wof:placetype": "postalcode"
  },
  "geometry": {"coordinates":[-0.765857,51.420955],"type":"Point"}
}
