{
  "type": "Feature",
  "properties": {
    "iso:country":"GB",
    "wof:name":"TA7 0PG",
    "wof:placetype":"postalcode"
},
  "geometry": {"coordinates":[-2.8937717622566,51.0892830215025],"type":"Point"}
}