{
  "type": "Feature",
  "properties": {
    "date:inception_lower": "1980-01-01",
    "date:inception_upper": "1980-01-01",
    "iso:country": "GB",
    "wof:name": "TA7 0PG",
    "wof:placetype": "postalcode"
  },
  "geometry": {"coordinates":[-2.893332,51.089118],"type":"Point"}
}
