{
  "type": "Feature",
  "properties": {
    "iso:country": "GB",
    "wof:name": "W11 1LY",
    "wof:placetype": "postalcode"
  },
  "geometry": {"coordinates":[-0.206928,51.51692],"type":"Point"}
}
