{
  "type": "Feature",
  "properties": {
    "date:inception_lower":"1997-12-01",
    "date:inception_upper":"1997-12-31",
    "iso:country":"GB",
    "wof:name":"ST2 8PG",
    "wof:placetype":"postalcode"
},
  "geometry": {"coordinates":[-2.141227,53.035593],"type":"Point"}
}