{
  "type": "Feature",
  "properties": {
    "iso:country": "GB",
    "wof:name": "ST2 8PG",
    "wof:placetype": "postalcode"
  },
  "geometry": {"coordinates":[-2.141227,53.035593],"type":"Point"}
}
