{
  "type": "Feature",
  "properties": {
    "date:inception_lower": "1980-01-01",
    "date:inception_upper": "1980-01-01",
    "iso:country": "GB",
    "wof:name": "SE15 5EX",
    "wof:placetype": "postalcode"
  },
  "geometry": {"coordinates":[-0.069131,51.47136],"type":"Point"}
}
