{
  "type": "Feature",
  "properties": {
    "iso:country": "GB",
    "wof:name": "LA9 7LN",
    "wof:placetype": "postalcode"
  },
  "geometry": {"coordinates":[-2.739467,54.314381],"type":"Point"}
}
