{
  "type": "Feature",
  "properties": {
    "date:inception_lower": "1980-01-01",
    "date:inception_upper": "1980-01-01",
    "iso:country": "GB",
    "wof:name": "LA9 7LN",
    "wof:placetype": "postalcode"
  },
  "geometry": {"coordinates":[-2.739467,54.314381],"type":"Point"}
}
