{
  "type": "Feature",
  "properties": {
    "iso:country":"GB",
    "wof:name":"LA9 7LN",
    "wof:placetype":"postalcode"
},
  "geometry": {"coordinates":[-2.73946708825804,54.31438125438689],"type":"Point"}
}