{
  "type": "Feature",
  "properties": {
    "iso:country":"GB",
    "wof:name":"YO25 9QJ",
    "wof:placetype":"postalcode"
},
  "geometry": {"coordinates":[-0.43614896692999,53.9545978460016],"type":"Point"}
}