{
  "type": "Feature",
  "properties": {
    "iso:country":"GB",
    "wof:name":"HA5 5SR",
    "wof:placetype":"postalcode"
},
  "geometry": {"coordinates":[-0.36782294407327,51.59407282893408],"type":"Point"}
}