{
  "type": "Feature",
  "properties": {
    "date:inception_lower": "1980-01-01",
    "date:inception_upper": "1980-01-01",
    "iso:country": "GB",
    "wof:name": "SK13 8RA",
    "wof:placetype": "postalcode"
  },
  "geometry": {"coordinates":[-1.928206,53.445186],"type":"Point"}
}
