{
  "type": "Feature",
  "properties": {
    "iso:country":"GB",
    "wof:name":"SK13 8RA",
    "wof:placetype":"postalcode"
},
  "geometry": {"coordinates":[-1.92820566631068,53.44518550555643],"type":"Point"}
}