{
  "type": "Feature",
  "properties": {
    "iso:country":"GB",
    "wof:name":"EX33 1BZ",
    "wof:placetype":"postalcode"
},
  "geometry": {"coordinates":[-4.17456764693008,51.11204848692441],"type":"Point"}
}