{
  "type": "Feature",
  "properties": {
    "date:inception_lower": "1980-01-01",
    "date:inception_upper": "1980-01-01",
    "iso:country": "GB",
    "wof:name": "EX33 1BZ",
    "wof:placetype": "postalcode"
  },
  "geometry": {"coordinates":[-4.174568,51.112048],"type":"Point"}
}
