{
  "type": "Feature",
  "properties": {
    "date:inception_lower": "1980-01-01",
    "date:inception_upper": "1980-01-01",
    "iso:country": "GB",
    "wof:name": "KT15 3DL",
    "wof:placetype": "postalcode"
  },
  "geometry": {"coordinates":[-0.509948,51.343282],"type":"Point"}
}
