{
  "type": "Feature",
  "properties": {
    "iso:country":"GB",
    "wof:name":"EH19 2EU",
    "wof:placetype":"postalcode"
},
  "geometry": {"coordinates":[-3.10761855270457,55.87925527136661],"type":"Point"}
}