{
  "type": "Feature",
  "properties": {
    "iso:country": "GB",
    "wof:name": "EH19 2EU",
    "wof:placetype": "postalcode"
  },
  "geometry": {"coordinates":[-3.107618,55.879255],"type":"Point"}
}
