{
  "type": "Feature",
  "properties": {
    "date:inception_lower":"1980-01-01",
    "date:inception_upper":"1980-01-31",
    "iso:country":"GB",
    "wof:name":"EH19 2EU",
    "wof:placetype":"postalcode"
},
  "geometry": {"coordinates":[-3.107618,55.879255],"type":"Point"}
}