{
  "type": "Feature",
  "properties": {
    "iso:country": "GB",
    "wof:name": "CW1 3XY",
    "wof:placetype": "postalcode"
  },
  "geometry": {"coordinates":[-2.449985,53.117714],"type":"Point"}
}
