{
  "type": "Feature",
  "properties": {
    "date:inception_lower": "1980-01-01",
    "date:inception_upper": "1980-01-01",
    "iso:country": "GB",
    "wof:name": "SW19 7QN",
    "wof:placetype": "postalcode"
  },
  "geometry": {"coordinates":[-0.209248,51.42353],"type":"Point"}
}
