{
  "type": "Feature",
  "properties": {
    "iso:country":"GB",
    "wof:name":"SE26 4LT",
    "wof:placetype":"postalcode"
},
  "geometry": {"coordinates":[-0.05747956181793,51.43066316611081],"type":"Point"}
}