{
  "type": "Feature",
  "properties": {
    "iso:country":"GB",
    "wof:name":"CM14 5TE",
    "wof:placetype":"postalcode"
},
  "geometry": {"coordinates":[0.25995210768359,51.65783590522953],"type":"Point"}
}