{
  "type": "Feature",
  "properties": {
    "iso:country": "GB",
    "wof:name": "CM14 5TE",
    "wof:placetype": "postalcode"
  },
  "geometry": {"coordinates":[0.260006,51.657497],"type":"Point"}
}
