{
  "type": "Feature",
  "properties": {
    "iso:country":"GB",
    "wof:name":"DH9 8UQ",
    "wof:placetype":"postalcode"
},
  "geometry": {"coordinates":[-1.74750744179454,54.86058978656308],"type":"Point"}
}