{
  "type": "Feature",
  "properties": {
    "date:inception_lower": "1990-07-01",
    "date:inception_upper": "1990-07-01",
    "iso:country": "GB",
    "wof:name": "CR8 5JU",
    "wof:placetype": "postalcode"
  },
  "geometry": {"coordinates":[-0.104447,51.32083],"type":"Point"}
}
