{
  "type": "Feature",
  "properties": {
    "iso:country": "GB",
    "wof:name": "RG25 2LF",
    "wof:placetype": "postalcode"
  },
  "geometry": {"coordinates":[-1.023814,51.245012],"type":"Point"}
}
