{
  "type": "Feature",
  "properties": {
    "date:inception_lower":"1980-01-01",
    "date:inception_upper":"1980-01-31",
    "iso:country":"GB",
    "wof:name":"RG25 2LF",
    "wof:placetype":"postalcode"
},
  "geometry": {"coordinates":[-1.023814,51.245012],"type":"Point"}
}