{
  "type": "Feature",
  "properties": {
    "iso:country":"GB",
    "wof:name":"RG25 2LF",
    "wof:placetype":"postalcode"
},
  "geometry": {"coordinates":[-1.02381403163676,51.24501248677983],"type":"Point"}
}