{
  "type": "Feature",
  "properties": {
    "date:inception_lower": "1990-02-01",
    "date:inception_upper": "1990-02-01",
    "iso:country": "GB",
    "wof:name": "RG27 8UH",
    "wof:placetype": "postalcode"
  },
  "geometry": {"coordinates":[-0.8991,51.307939],"type":"Point"}
}
