{
  "type": "Feature",
  "properties": {
    "iso:country":"GB",
    "wof:name":"B77 3NZ",
    "wof:placetype":"postalcode"
},
  "geometry": {"coordinates":[-1.68267906168141,52.62963246200885],"type":"Point"}
}