{
  "type": "Feature",
  "properties": {
    "iso:country": "GB",
    "wof:name": "B77 3NZ",
    "wof:placetype": "postalcode"
  },
  "geometry": {"coordinates":[-1.682679,52.629632],"type":"Point"}
}
