{
  "type": "Feature",
  "properties": {
    "iso:country": "GB",
    "wof:name": "NR6 6QZ",
    "wof:placetype": "postalcode"
  },
  "geometry": {"coordinates":[1.280908,52.655735],"type":"Point"}
}
