{
  "type": "Feature",
  "properties": {
    "date:inception_lower": "1986-07-01",
    "date:inception_upper": "1986-07-01",
    "iso:country": "GB",
    "wof:name": "NR6 6QZ",
    "wof:placetype": "postalcode"
  },
  "geometry": {"coordinates":[1.280908,52.655735],"type":"Point"}
}
