{
  "type": "Feature",
  "properties": {
    "iso:country":"GB",
    "wof:name":"NR6 6QZ",
    "wof:placetype":"postalcode"
},
  "geometry": {"coordinates":[1.2809080522727,52.655735104446],"type":"Point"}
}