{
  "type": "Feature",
  "properties": {
    "iso:country":"GB",
    "wof:name":"TW8 9PB",
    "wof:placetype":"postalcode"
},
  "geometry": {"coordinates":[-0.30786471502099,51.49260912619433],"type":"Point"}
}