{
  "type": "Feature",
  "properties": {
    "iso:country":"GB",
    "wof:name":"NR34 7DN",
    "wof:placetype":"postalcode"
},
  "geometry": {"coordinates":[1.59053516729004,52.45346683271013],"type":"Point"}
}