{
  "type": "Feature",
  "properties": {
    "iso:country": "GB",
    "wof:name": "BN3 6UR",
    "wof:placetype": "postalcode"
  },
  "geometry": {"coordinates":[-0.173195,50.846658],"type":"Point"}
}
