{
  "type": "Feature",
  "properties": {
    "iso:country":"GB",
    "wof:name":"BN3 6UR",
    "wof:placetype":"postalcode"
},
  "geometry": {"coordinates":[-0.17319458653337,50.84665756039063],"type":"Point"}
}