{
  "type": "Feature",
  "properties": {
    "iso:country":"GB",
    "wof:name":"EH5 2NS",
    "wof:placetype":"postalcode"
},
  "geometry": {"coordinates":[-3.23810981238103,55.9743100420366],"type":"Point"}
}