{
  "type": "Feature",
  "properties": {
    "date:inception_lower":"1980-01-01",
    "date:inception_upper":"1980-01-31",
    "iso:country":"GB",
    "wof:name":"TW20 9RL",
    "wof:placetype":"postalcode"
},
  "geometry": {"coordinates":[-0.554233,51.426575],"type":"Point"}
}