{
  "type": "Feature",
  "properties": {
    "date:inception_lower": "2024-06-01",
    "date:inception_upper": "2024-06-01",
    "iso:country": "GB",
    "wof:name": "B30 2DR",
    "wof:placetype": "postalcode"
  },
  "geometry": {"coordinates":[-1.919926,52.430469],"type":"Point"}
}
