{
  "type": "Feature",
  "properties": {
    "date:inception_lower": "2009-05-01",
    "date:inception_upper": "2009-05-01",
    "iso:country": "GB",
    "wof:name": "SK14 4HR",
    "wof:placetype": "postalcode"
  },
  "geometry": {"coordinates":[-2.07577,53.464201],"type":"Point"}
}
