{
  "type": "Feature",
  "properties": {
    "iso:country": "GB",
    "wof:name": "SK14 4HR",
    "wof:placetype": "postalcode"
  },
  "geometry": {"coordinates":[-2.075695,53.464139],"type":"Point"}
}
