{
  "type": "Feature",
  "properties": {
    "iso:country":"GB",
    "wof:name":"SK14 4HR",
    "wof:placetype":"postalcode"
},
  "geometry": {"coordinates":[-2.07569507050499,53.46413946967049],"type":"Point"}
}