{
  "type": "Feature",
  "properties": {
    "iso:country":"GB",
    "wof:name":"HU15 2HF",
    "wof:placetype":"postalcode"
},
  "geometry": {"coordinates":[-0.61636985986525,53.76359735763783],"type":"Point"}
}