{
  "type": "Feature",
  "properties": {
    "iso:country": "GB",
    "wof:name": "CH1 4JS",
    "wof:placetype": "postalcode"
  },
  "geometry": {"coordinates":[-2.901756,53.194218],"type":"Point"}
}
