{
  "type": "Feature",
  "properties": {
    "iso:country":"GB",
    "wof:name":"PR7 4DR",
    "wof:placetype":"postalcode"
},
  "geometry": {"coordinates":[-2.61576227571269,53.60765916082806],"type":"Point"}
}