{
  "type": "Feature",
  "properties": {
    "iso:country": "GB",
    "wof:name": "PR7 4DR",
    "wof:placetype": "postalcode"
  },
  "geometry": {"coordinates":[-2.615762,53.607659],"type":"Point"}
}
