{
  "type": "Feature",
  "properties": {
    "iso:country":"GB",
    "wof:name":"PL6 6LJ",
    "wof:placetype":"postalcode"
},
  "geometry": {"coordinates":[-4.12269639769636,50.42024345802653],"type":"Point"}
}