{
  "type": "Feature",
  "properties": {
    "date:inception_lower":"1980-01-01",
    "date:inception_upper":"1980-01-31",
    "iso:country":"GB",
    "wof:name":"YO15 1BB",
    "wof:placetype":"postalcode"
},
  "geometry": {"coordinates":[-0.112925,54.125144],"type":"Point"}
}