{
  "type": "Feature",
  "properties": {
    "iso:country": "GB",
    "wof:name": "AB56 1FU",
    "wof:placetype": "postalcode"
  },
  "geometry": {"coordinates":[-2.964928,57.675248],"type":"Point"}
}
