{
  "type": "Feature",
  "properties": {
    "date:inception_lower": "2000-10-01",
    "date:inception_upper": "2000-10-01",
    "iso:country": "GB",
    "wof:name": "WD3 9TU",
    "wof:placetype": "postalcode"
  },
  "geometry": {"coordinates":[-0.517963,51.620433],"type":"Point"}
}
