{
  "type": "Feature",
  "properties": {
    "iso:country":"GB",
    "wof:name":"WD3 9TU",
    "wof:placetype":"postalcode"
},
  "geometry": {"coordinates":[-0.51796258568116,51.6204327271173],"type":"Point"}
}