{
  "type": "Feature",
  "properties": {
    "iso:country":"GB",
    "wof:name":"NR32 5PG",
    "wof:placetype":"postalcode"
},
  "geometry": {"coordinates":[1.71105874808495,52.50664345837215],"type":"Point"}
}