{
  "type": "Feature",
  "properties": {
    "date:inception_lower":"1980-01-01",
    "date:inception_upper":"1980-01-31",
    "iso:country":"GB",
    "wof:name":"NR32 5PG",
    "wof:placetype":"postalcode"
},
  "geometry": {"coordinates":[1.711059,52.506643],"type":"Point"}
}