{
  "type": "Feature",
  "properties": {
    "iso:country":"GB",
    "wof:name":"LA3 3BA",
    "wof:placetype":"postalcode"
},
  "geometry": {"coordinates":[-2.84485557311005,54.0626902209529],"type":"Point"}
}