{
  "type": "Feature",
  "properties": {
    "iso:country": "GB",
    "wof:name": "LA3 3BA",
    "wof:placetype": "postalcode"
  },
  "geometry": {"coordinates":[-2.844856,54.06269],"type":"Point"}
}
