{
  "type": "Feature",
  "properties": {
    "iso:country": "GB",
    "wof:name": "DG11 2FF",
    "wof:placetype": "postalcode"
  },
  "geometry": {"coordinates":[-3.366095,55.132792],"type":"Point"}
}
