{
  "type": "Feature",
  "properties": {
    "iso:country":"GB",
    "wof:name":"TW11 9HF",
    "wof:placetype":"postalcode"
},
  "geometry": {"coordinates":[-0.32422002143853,51.42603955659905],"type":"Point"}
}