{
  "type": "Feature",
  "properties": {
    "iso:country": "GB",
    "wof:name": "CB21 4UR",
    "wof:placetype": "postalcode"
  },
  "geometry": {"coordinates":[0.293666,52.095607],"type":"Point"}
}
