{
  "type": "Feature",
  "properties": {
    "iso:country":"GB",
    "wof:name":"CB21 4UR",
    "wof:placetype":"postalcode"
},
  "geometry": {"coordinates":[0.29366603064885,52.09560692398445],"type":"Point"}
}