{
  "type": "Feature",
  "properties": {
    "iso:country": "GB",
    "wof:name": "WF4 4DL",
    "wof:placetype": "postalcode"
  },
  "geometry": {"coordinates":[-1.641822,53.630434],"type":"Point"}
}
