{
  "type": "Feature",
  "properties": {
    "iso:country":"GB",
    "wof:name":"TS17 8QW",
    "wof:placetype":"postalcode"
},
  "geometry": {"coordinates":[-1.30331016634725,54.5431570440153],"type":"Point"}
}