{
  "type": "Feature",
  "properties": {
    "iso:country": "GB",
    "wof:name": "TS17 8QW",
    "wof:placetype": "postalcode"
  },
  "geometry": {"coordinates":[-1.30331,54.543157],"type":"Point"}
}
