{
  "type": "Feature",
  "properties": {
    "iso:country":"GB",
    "wof:name":"TN13 1EL",
    "wof:placetype":"postalcode"
},
  "geometry": {"coordinates":[0.18624236197414,51.270510102359],"type":"Point"}
}