{
  "type": "Feature",
  "properties": {
    "iso:country": "GB",
    "wof:name": "TN13 1EL",
    "wof:placetype": "postalcode"
  },
  "geometry": {"coordinates":[0.186242,51.27051],"type":"Point"}
}
