{
  "type": "Feature",
  "properties": {
    "date:inception_lower": "2002-06-01",
    "date:inception_upper": "2002-06-01",
    "iso:country": "GB",
    "wof:name": "S72 8WG",
    "wof:placetype": "postalcode"
  },
  "geometry": {"coordinates":[-1.411024,53.592058],"type":"Point"}
}
