{
  "type": "Feature",
  "properties": {
    "iso:country":"GB",
    "wof:name":"S72 8WG",
    "wof:placetype":"postalcode"
},
  "geometry": {"coordinates":[-1.41102415426643,53.59205795158705],"type":"Point"}
}