{
  "type": "Feature",
  "properties": {
    "date:inception_lower":"1980-01-01",
    "date:inception_upper":"1980-01-31",
    "iso:country":"GB",
    "wof:name":"LA5 8HJ",
    "wof:placetype":"postalcode"
},
  "geometry": {"coordinates":[-2.79269,54.107391],"type":"Point"}
}