{
  "type": "Feature",
  "properties": {
    "iso:country":"GB",
    "wof:name":"CW8 1NF",
    "wof:placetype":"postalcode"
},
  "geometry": {"coordinates":[-2.54269363584073,53.23961365374262],"type":"Point"}
}