{
  "type": "Feature",
  "properties": {
    "date:inception_lower":"2011-08-01",
    "date:inception_upper":"2011-08-31",
    "iso:country":"GB",
    "wof:name":"HS1 2HY",
    "wof:placetype":"postalcode"
},
  "geometry": {"coordinates":[-6.382262,58.216242],"type":"Point"}
}