{
  "type": "Feature",
  "properties": {
    "iso:country":"GB",
    "wof:name":"PO38 2NP",
    "wof:placetype":"postalcode"
},
  "geometry": {"coordinates":[-1.29469225149295,50.58009992229636],"type":"Point"}
}