{
  "type": "Feature",
  "properties": {
    "date:inception_lower": "2000-12-01",
    "date:inception_upper": "2000-12-01",
    "iso:country": "GB",
    "wof:name": "PO38 2NP",
    "wof:placetype": "postalcode"
  },
  "geometry": {"coordinates":[-1.293745,50.579489],"type":"Point"}
}
