{
  "type": "Feature",
  "properties": {
    "iso:country":"GB",
    "wof:name":"IV63 7YF",
    "wof:placetype":"postalcode"
},
  "geometry": {"coordinates":[-4.62053784335582,57.21216350009717],"type":"Point"}
}