{
  "type": "Feature",
  "properties": {
    "iso:country": "GB",
    "wof:name": "IV63 7YF",
    "wof:placetype": "postalcode"
  },
  "geometry": {"coordinates":[-4.620224,57.213105],"type":"Point"}
}
