{
  "type": "Feature",
  "properties": {
    "iso:country":"GB",
    "wof:name":"LL12 7EB",
    "wof:placetype":"postalcode"
},
  "geometry": {"coordinates":[-2.98001386657295,53.05321283092959],"type":"Point"}
}