{
  "type": "Feature",
  "properties": {
    "date:inception_lower": "2022-08-01",
    "date:inception_upper": "2022-08-01",
    "iso:country": "GB",
    "wof:name": "HD6 3FG",
    "wof:placetype": "postalcode"
  },
  "geometry": {"coordinates":[-1.799875,53.681627],"type":"Point"}
}
