{
  "type": "Feature",
  "properties": {
    "iso:country":"GB",
    "wof:name":"DE21 2HD",
    "wof:placetype":"postalcode"
},
  "geometry": {"coordinates":[-1.42221516201889,52.94365417842169],"type":"Point"}
}