{
  "type": "Feature",
  "properties": {
    "date:inception_lower":"1992-08-01",
    "date:inception_upper":"1992-08-31",
    "iso:country":"GB",
    "wof:name":"DE21 2HD",
    "wof:placetype":"postalcode"
},
  "geometry": {"coordinates":[-1.422215,52.943654],"type":"Point"}
}