{
  "type": "Feature",
  "properties": {
    "iso:country":"GB",
    "wof:name":"S73 0HJ",
    "wof:placetype":"postalcode"
},
  "geometry": {"coordinates":[-1.38972288082973,53.5185154442283],"type":"Point"}
}