{
  "type": "Feature",
  "properties": {
    "iso:country":"GB",
    "wof:name":"LU6 3RB",
    "wof:placetype":"postalcode"
},
  "geometry": {"coordinates":[-0.49956960808864,51.85581157649881],"type":"Point"}
}