{
  "type": "Feature",
  "properties": {
    "iso:country":"GB",
    "wof:name":"E18 2NG",
    "wof:placetype":"postalcode"
},
  "geometry": {"coordinates":[0.01871366564217,51.5960192473414],"type":"Point"}
}