{
  "type": "Feature",
  "properties": {
    "date:inception_lower": "1981-06-01",
    "date:inception_upper": "1981-06-01",
    "iso:country": "GB",
    "wof:name": "NG5 9PR",
    "wof:placetype": "postalcode"
  },
  "geometry": {"coordinates":[-1.157611,53.014061],"type":"Point"}
}
