{
  "type": "Feature",
  "properties": {
    "iso:country":"GB",
    "wof:name":"NG5 9PR",
    "wof:placetype":"postalcode"
},
  "geometry": {"coordinates":[-1.15761137739995,53.01406141118034],"type":"Point"}
}