{
  "type": "Feature",
  "properties": {
    "iso:country": "GB",
    "wof:name": "NG5 9PR",
    "wof:placetype": "postalcode"
  },
  "geometry": {"coordinates":[-1.157611,53.014061],"type":"Point"}
}
