{
  "type": "Feature",
  "properties": {
    "iso:country":"GB",
    "wof:name":"NG2 6EP",
    "wof:placetype":"postalcode"
},
  "geometry": {"coordinates":[-1.12989192195347,52.92703238813528],"type":"Point"}
}