{
  "type": "Feature",
  "properties": {
    "iso:country":"GB",
    "wof:name":"BD2 2DB",
    "wof:placetype":"postalcode"
},
  "geometry": {"coordinates":[-1.72393872527933,53.81943737907799],"type":"Point"}
}