{
  "type": "Feature",
  "properties": {
    "date:inception_lower": "2006-01-01",
    "date:inception_upper": "2006-01-01",
    "iso:country": "GB",
    "wof:name": "BD2 2DB",
    "wof:placetype": "postalcode"
  },
  "geometry": {"coordinates":[-1.723939,53.819437],"type":"Point"}
}
