{
  "type": "Feature",
  "properties": {
    "iso:country":"GB",
    "wof:name":"BA2 0JH",
    "wof:placetype":"postalcode"
},
  "geometry": {"coordinates":[-2.4743746956363,51.32767840159649],"type":"Point"}
}