{
  "type": "Feature",
  "properties": {
    "iso:country": "GB",
    "wof:name": "BA2 0JH",
    "wof:placetype": "postalcode"
  },
  "geometry": {"coordinates":[-2.474375,51.327678],"type":"Point"}
}
