{
  "type": "Feature",
  "properties": {
    "iso:country":"GB",
    "wof:name":"TR26 2SD",
    "wof:placetype":"postalcode"
},
  "geometry": {"coordinates":[-5.46618721832719,50.19330784984043],"type":"Point"}
}