{
  "type": "Feature",
  "properties": {
    "iso:country":"GB",
    "wof:name":"ST13 7HY",
    "wof:placetype":"postalcode"
},
  "geometry": {"coordinates":[-2.03899707675267,53.06481338380138],"type":"Point"}
}