{
  "type": "Feature",
  "properties": {
    "iso:country":"GB",
    "wof:name":"OX18 2JL",
    "wof:placetype":"postalcode"
},
  "geometry": {"coordinates":[-1.54595817207346,51.72705494691518],"type":"Point"}
}