{
  "type": "Feature",
  "properties": {
    "iso:country":"GB",
    "wof:name":"NP4 7TD",
    "wof:placetype":"postalcode"
},
  "geometry": {"coordinates":[-3.06488550678933,51.71732220316994],"type":"Point"}
}