{
  "type": "Feature",
  "properties": {
    "iso:country":"GB",
    "wof:name":"B75 5ER",
    "wof:placetype":"postalcode"
},
  "geometry": {"coordinates":[-1.82285432341812,52.59015389901812],"type":"Point"}
}