{
  "type": "Feature",
  "properties": {
    "iso:country": "GB",
    "wof:name": "BN25 2HL",
    "wof:placetype": "postalcode"
  },
  "geometry": {"coordinates":[0.101475,50.78093],"type":"Point"}
}
