{
  "type": "Feature",
  "properties": {
    "iso:country": "GB",
    "wof:name": "SY20 9BG",
    "wof:placetype": "postalcode"
  },
  "geometry": {"coordinates":[-3.859504,52.662759],"type":"Point"}
}
