{
  "type": "Feature",
  "properties": {
    "iso:country":"GB",
    "wof:name":"SY20 9BG",
    "wof:placetype":"postalcode"
},
  "geometry": {"coordinates":[-3.85950436918157,52.6627589704424],"type":"Point"}
}