{
  "type": "Feature",
  "properties": {
    "iso:country":"GB",
    "wof:name":"TW7 5XD",
    "wof:placetype":"postalcode"
},
  "geometry": {"coordinates":[-0.32096284110007,51.47917397224096],"type":"Point"}
}