{
  "type": "Feature",
  "properties": {
    "date:inception_lower": "1999-06-01",
    "date:inception_upper": "1999-06-01",
    "iso:country": "GB",
    "wof:name": "TW7 5XD",
    "wof:placetype": "postalcode"
  },
  "geometry": {"coordinates":[-0.320963,51.479174],"type":"Point"}
}
