{
  "type": "Feature",
  "properties": {
    "iso:country":"GB",
    "wof:name":"WN7 2YP",
    "wof:placetype":"postalcode"
},
  "geometry": {"coordinates":[-2.47809689403281,53.50502971562411],"type":"Point"}
}