{
  "type": "Feature",
  "properties": {
    "date:inception_lower":"1993-01-01",
    "date:inception_upper":"1993-01-31",
    "iso:country":"GB",
    "wof:name":"CA10 3AG",
    "wof:placetype":"postalcode"
},
  "geometry": {"coordinates":[-2.637821,54.616901],"type":"Point"}
}