{
  "type": "Feature",
  "properties": {
    "iso:country":"GB",
    "wof:name":"N19 5DW",
    "wof:placetype":"postalcode"
},
  "geometry": {"coordinates":[-0.13835850919819,51.56430976010247],"type":"Point"}
}