{
  "type": "Feature",
  "properties": {
    "iso:country": "GB",
    "wof:name": "DN17 2JQ",
    "wof:placetype": "postalcode"
  },
  "geometry": {"coordinates":[-0.671334,53.561933],"type":"Point"}
}
