{
  "type": "Feature",
  "properties": {
    "iso:country":"GB",
    "wof:name":"DN17 2JQ",
    "wof:placetype":"postalcode"
},
  "geometry": {"coordinates":[-0.6713342932878,53.5619334201852],"type":"Point"}
}