{
  "type": "Feature",
  "properties": {
    "iso:country":"GB",
    "wof:name":"DL8 1QX",
    "wof:placetype":"postalcode"
},
  "geometry": {"coordinates":[-1.71881898765596,54.32663925987628],"type":"Point"}
}