{
  "type": "Feature",
  "properties": {
    "date:inception_lower": "1980-01-01",
    "date:inception_upper": "1980-01-01",
    "iso:country": "GB",
    "wof:name": "LE12 7TE",
    "wof:placetype": "postalcode"
  },
  "geometry": {"coordinates":[-1.105398,52.7385],"type":"Point"}
}
