{
  "type": "Feature",
  "properties": {
    "date:inception_lower":"2004-11-01",
    "date:inception_upper":"2004-11-30",
    "iso:country":"GB",
    "wof:name":"CM5 9JX",
    "wof:placetype":"postalcode"
},
  "geometry": {"coordinates":[0.24458,51.704003],"type":"Point"}
}