{
  "type": "Feature",
  "properties": {
    "iso:country": "GB",
    "wof:name": "CM5 9JX",
    "wof:placetype": "postalcode"
  },
  "geometry": {"coordinates":[0.24458,51.704003],"type":"Point"}
}
