{
  "type": "Feature",
  "properties": {
    "iso:country":"GB",
    "wof:name":"CM5 9JX",
    "wof:placetype":"postalcode"
},
  "geometry": {"coordinates":[0.24458036465452,51.70400292949952],"type":"Point"}
}