{
  "type": "Feature",
  "properties": {
    "iso:country":"GB",
    "wof:name":"CF81 8JN",
    "wof:placetype":"postalcode"
},
  "geometry": {"coordinates":[-3.22571570746484,51.6778633832695],"type":"Point"}
}