{
  "type": "Feature",
  "properties": {
    "iso:country": "GB",
    "wof:name": "GU28 9DZ",
    "wof:placetype": "postalcode"
  },
  "geometry": {"coordinates":[-0.701699,51.022835],"type":"Point"}
}
