{
  "type": "Feature",
  "properties": {
    "iso:country":"GB",
    "wof:name":"CO13 0QB",
    "wof:placetype":"postalcode"
},
  "geometry": {"coordinates":[1.22680351023048,51.84066771281355],"type":"Point"}
}