{
  "type": "Feature",
  "properties": {
    "iso:country":"GB",
    "wof:name":"SK17 9EY",
    "wof:placetype":"postalcode"
},
  "geometry": {"coordinates":[-1.90603476739746,53.25055714335198],"type":"Point"}
}