{
  "type": "Feature",
  "properties": {
    "iso:country": "GB",
    "wof:name": "AB51 4ZZ",
    "wof:placetype": "postalcode"
  },
  "geometry": {"coordinates":[-2.395235,57.295021],"type":"Point"}
}
