{
  "type": "Feature",
  "properties": {
    "iso:country":"GB",
    "wof:name":"AB51 4ZZ",
    "wof:placetype":"postalcode"
},
  "geometry": {"coordinates":[-2.39523536591176,57.29502073902984],"type":"Point"}
}