{
  "type": "Feature",
  "properties": {
    "date:inception_lower":"1980-01-01",
    "date:inception_upper":"1980-01-31",
    "iso:country":"GB",
    "wof:name":"TN26 2DA",
    "wof:placetype":"postalcode"
},
  "geometry": {"coordinates":[0.790091,51.028567],"type":"Point"}
}