{
  "type": "Feature",
  "properties": {
    "iso:country":"GB",
    "wof:name":"TN26 2DA",
    "wof:placetype":"postalcode"
},
  "geometry": {"coordinates":[0.79005692026195,51.0285687444029],"type":"Point"}
}