{
  "type": "Feature",
  "properties": {
    "iso:country": "GB",
    "wof:name": "HA8 8LH",
    "wof:placetype": "postalcode"
  },
  "geometry": {"coordinates":[-0.276494,51.615769],"type":"Point"}
}
