{
  "type": "Feature",
  "properties": {
    "iso:country":"GB",
    "wof:name":"HA8 8LH",
    "wof:placetype":"postalcode"
},
  "geometry": {"coordinates":[-0.27649413959454,51.61576943628231],"type":"Point"}
}