{
  "type": "Feature",
  "properties": {
    "iso:country": "GB",
    "wof:name": "GU51 1LE",
    "wof:placetype": "postalcode"
  },
  "geometry": {"coordinates":[-0.849812,51.289886],"type":"Point"}
}
