{
  "type": "Feature",
  "properties": {
    "date:inception_lower": "1980-01-01",
    "date:inception_upper": "1980-01-01",
    "iso:country": "GB",
    "wof:name": "KT17 4EL",
    "wof:placetype": "postalcode"
  },
  "geometry": {"coordinates":[-0.25409,51.33027],"type":"Point"}
}
