{
  "type": "Feature",
  "properties": {
    "iso:country":"GB",
    "wof:name":"DL7 8QZ",
    "wof:placetype":"postalcode"
},
  "geometry": {"coordinates":[-1.43588488306804,54.33348577600144],"type":"Point"}
}