{
  "type": "Feature",
  "properties": {
    "iso:country": "GB",
    "wof:name": "DL7 8QZ",
    "wof:placetype": "postalcode"
  },
  "geometry": {"coordinates":[-1.435526,54.333442],"type":"Point"}
}
