{
  "type": "Feature",
  "properties": {
    "iso:country": "GB",
    "wof:name": "DL7 8QZ",
    "wof:placetype": "postalcode"
  },
  "geometry": {"coordinates":[-1.435885,54.333486],"type":"Point"}
}
