{
  "type": "Feature",
  "properties": {
    "iso:country":"GB",
    "wof:name":"YO10 4QP",
    "wof:placetype":"postalcode"
},
  "geometry": {"coordinates":[-1.07497785404244,53.94107176969393],"type":"Point"}
}