{
  "type": "Feature",
  "properties": {
    "iso:country": "GB",
    "wof:name": "YO10 4QP",
    "wof:placetype": "postalcode"
  },
  "geometry": {"coordinates":[-1.074978,53.941072],"type":"Point"}
}
