{
  "type": "Feature",
  "properties": {
    "iso:country":"GB",
    "wof:name":"RG31 7AF",
    "wof:placetype":"postalcode"
},
  "geometry": {"coordinates":[-1.05649028264198,51.44029827476873],"type":"Point"}
}