{
  "type": "Feature",
  "properties": {
    "iso:country": "GB",
    "wof:name": "L11 5AH",
    "wof:placetype": "postalcode"
  },
  "geometry": {"coordinates":[-2.929616,53.449237],"type":"Point"}
}
