{
  "type": "Feature",
  "properties": {
    "iso:country":"GB",
    "wof:name":"L32 5TQ",
    "wof:placetype":"postalcode"
},
  "geometry": {"coordinates":[-2.89551007766291,53.47928687304037],"type":"Point"}
}