{
  "type": "Feature",
  "properties": {
    "iso:country": "GB",
    "wof:name": "TA6 6FL",
    "wof:placetype": "postalcode"
  },
  "geometry": {"coordinates":[-3.001833,51.10649],"type":"Point"}
}
