{
  "type": "Feature",
  "properties": {
    "date:inception_lower":"2008-07-01",
    "date:inception_upper":"2008-07-31",
    "iso:country":"GB",
    "wof:name":"TA6 6FL",
    "wof:placetype":"postalcode"
},
  "geometry": {"coordinates":[-3.001833,51.10649],"type":"Point"}
}