{
  "type": "Feature",
  "properties": {
    "iso:country": "GB",
    "wof:name": "EX22 7NG",
    "wof:placetype": "postalcode"
  },
  "geometry": {"coordinates":[-4.354129,50.854907],"type":"Point"}
}
