{
  "type": "Feature",
  "properties": {
    "iso:country":"GB",
    "wof:name":"NP11 7QZ",
    "wof:placetype":"postalcode"
},
  "geometry": {"coordinates":[-3.15883000274189,51.61409025887648],"type":"Point"}
}