{
  "type": "Feature",
  "properties": {
    "iso:country": "GB",
    "wof:name": "CW8 1TA",
    "wof:placetype": "postalcode"
  },
  "geometry": {"coordinates":[-2.523442,53.256985],"type":"Point"}
}
