{
  "type": "Feature",
  "properties": {
    "iso:country":"GB",
    "wof:name":"CW8 1TA",
    "wof:placetype":"postalcode"
},
  "geometry": {"coordinates":[-2.52344194528964,53.25698542535147],"type":"Point"}
}