{
  "type": "Feature",
  "properties": {
    "iso:country": "GB",
    "wof:name": "LS27 7AE",
    "wof:placetype": "postalcode"
  },
  "geometry": {"coordinates":[-1.63378,53.759846],"type":"Point"}
}
