{
  "type": "Feature",
  "properties": {
    "iso:country":"GB",
    "wof:name":"LS27 7AE",
    "wof:placetype":"postalcode"
},
  "geometry": {"coordinates":[-1.63386672929679,53.75985755697889],"type":"Point"}
}