{
  "type": "Feature",
  "properties": {
    "iso:country":"GB",
    "wof:name":"EN8 8LB",
    "wof:placetype":"postalcode"
},
  "geometry": {"coordinates":[-0.03320480565013,51.69993628260442],"type":"Point"}
}