{
  "type": "Feature",
  "properties": {
    "date:inception_lower": "2004-06-01",
    "date:inception_upper": "2004-06-01",
    "iso:country": "GB",
    "wof:name": "GL14 2YE",
    "wof:placetype": "postalcode"
  },
  "geometry": {"coordinates":[-2.513934,51.834374],"type":"Point"}
}
