{
  "type": "Feature",
  "properties": {
    "iso:country": "GB",
    "wof:name": "EH54 6EU",
    "wof:placetype": "postalcode"
  },
  "geometry": {"coordinates":[-3.513541,55.899231],"type":"Point"}
}
