{
  "type": "Feature",
  "properties": {
    "date:inception_lower": "2023-03-01",
    "date:inception_upper": "2023-03-01",
    "iso:country": "GB",
    "wof:name": "LE67 2LU",
    "wof:placetype": "postalcode"
  },
  "geometry": {"coordinates":[-1.35983,52.714964],"type":"Point"}
}
