{
  "type": "Feature",
  "properties": {
    "iso:country": "GB",
    "wof:name": "SL0 9RH",
    "wof:placetype": "postalcode"
  },
  "geometry": {"coordinates":[-0.525087,51.518247],"type":"Point"}
}
