{
  "type": "Feature",
  "properties": {
    "iso:country":"GB",
    "wof:name":"SL0 9RH",
    "wof:placetype":"postalcode"
},
  "geometry": {"coordinates":[-0.52508656206138,51.51824707389974],"type":"Point"}
}