{
  "type": "Feature",
  "properties": {
    "iso:country":"GB",
    "wof:name":"SE25 6RH",
    "wof:placetype":"postalcode"
},
  "geometry": {"coordinates":[-0.0864125087126,51.40064485974342],"type":"Point"}
}