{
  "type": "Feature",
  "properties": {
    "date:inception_lower": "1980-01-01",
    "date:inception_upper": "1980-01-01",
    "iso:country": "GB",
    "wof:name": "NR2 1AB",
    "wof:placetype": "postalcode"
  },
  "geometry": {"coordinates":[1.285973,52.629423],"type":"Point"}
}
