{
  "type": "Feature",
  "properties": {
    "iso:country":"GB",
    "wof:name":"NR2 1AB",
    "wof:placetype":"postalcode"
},
  "geometry": {"coordinates":[1.28597339269803,52.62942323383586],"type":"Point"}
}