{
  "type": "Feature",
  "properties": {
    "iso:country": "GB",
    "wof:name": "IP6 8PB",
    "wof:placetype": "postalcode"
  },
  "geometry": {"coordinates":[1.088558,52.158365],"type":"Point"}
}
