{
  "type": "Feature",
  "properties": {
    "iso:country":"GB",
    "wof:name":"DE55 1DW",
    "wof:placetype":"postalcode"
},
  "geometry": {"coordinates":[-1.38998535363066,53.0766874879821],"type":"Point"}
}