{
  "type": "Feature",
  "properties": {
    "iso:country":"GB",
    "wof:name":"PA3 3AB",
    "wof:placetype":"postalcode"
},
  "geometry": {"coordinates":[-4.4665409308192,55.85519457788209],"type":"Point"}
}