{
  "type": "Feature",
  "properties": {
    "iso:country":"GB",
    "wof:name":"EH5 3HF",
    "wof:placetype":"postalcode"
},
  "geometry": {"coordinates":[-3.20582038331873,55.97634642080514],"type":"Point"}
}