{
  "type": "Feature",
  "properties": {
    "iso:country": "GB",
    "wof:name": "EH5 3HF",
    "wof:placetype": "postalcode"
  },
  "geometry": {"coordinates":[-3.20582,55.976346],"type":"Point"}
}
