{
  "type": "Feature",
  "properties": {
    "date:inception_lower":"1980-01-01",
    "date:inception_upper":"1980-01-31",
    "iso:country":"GB",
    "wof:name":"SY21 8TD",
    "wof:placetype":"postalcode"
},
  "geometry": {"coordinates":[-3.059456,52.689881],"type":"Point"}
}