{
  "type": "Feature",
  "properties": {
    "iso:country":"GB",
    "wof:name":"SY21 8TD",
    "wof:placetype":"postalcode"
},
  "geometry": {"coordinates":[-3.0594584806168,52.68986614666233],"type":"Point"}
}