{
  "type": "Feature",
  "properties": {
    "date:inception_lower": "1980-01-01",
    "date:inception_upper": "1980-01-01",
    "iso:country": "GB",
    "wof:name": "SA46 0JA",
    "wof:placetype": "postalcode"
  },
  "geometry": {"coordinates":[-4.258679,52.243893],"type":"Point"}
}
