{
  "type": "Feature",
  "properties": {
    "iso:country":"GB",
    "wof:name":"B70 0QA",
    "wof:placetype":"postalcode"
},
  "geometry": {"coordinates":[-2.01012866796414,52.53441371702101],"type":"Point"}
}