{
  "type": "Feature",
  "properties": {
    "iso:country":"GB",
    "wof:name":"SM1 1LD",
    "wof:placetype":"postalcode"
},
  "geometry": {"coordinates":[-0.19525442021189,51.36784902330102],"type":"Point"}
}