{
  "type": "Feature",
  "properties": {
    "iso:country": "GB",
    "wof:name": "M9 4PJ",
    "wof:placetype": "postalcode"
  },
  "geometry": {"coordinates":[-2.20414,53.509659],"type":"Point"}
}
