{
  "type": "Feature",
  "properties": {
    "iso:country": "GB",
    "wof:name": "LA12 9EP",
    "wof:placetype": "postalcode"
  },
  "geometry": {"coordinates":[-3.077099,54.188544],"type":"Point"}
}
