{
  "type": "Feature",
  "properties": {
    "iso:country": "GB",
    "wof:name": "BB2 5NQ",
    "wof:placetype": "postalcode"
  },
  "geometry": {"coordinates":[-2.526894,53.731376],"type":"Point"}
}
