{
  "type": "Feature",
  "properties": {
    "iso:country": "GB",
    "wof:name": "NE66 3DA",
    "wof:placetype": "postalcode"
  },
  "geometry": {"coordinates":[-1.586884,55.417886],"type":"Point"}
}
