{
  "type": "Feature",
  "properties": {
    "date:inception_lower": "1980-01-01",
    "date:inception_upper": "1980-01-01",
    "iso:country": "GB",
    "wof:name": "IP31 2JX",
    "wof:placetype": "postalcode"
  },
  "geometry": {"coordinates":[0.82005,52.270513],"type":"Point"}
}
