{
  "type": "Feature",
  "properties": {
    "iso:country": "GB",
    "wof:name": "NG11 0DH",
    "wof:placetype": "postalcode"
  },
  "geometry": {"coordinates":[-1.247506,52.846803],"type":"Point"}
}
