{
  "type": "Feature",
  "properties": {
    "iso:country":"GB",
    "wof:name":"TS3 0HH",
    "wof:placetype":"postalcode"
},
  "geometry": {"coordinates":[-1.19008100728501,54.55344347165643],"type":"Point"}
}