{
  "type": "Feature",
  "properties": {
    "date:inception_lower": "1980-01-01",
    "date:inception_upper": "1980-01-01",
    "iso:country": "GB",
    "wof:name": "TS3 0HH",
    "wof:placetype": "postalcode"
  },
  "geometry": {"coordinates":[-1.190081,54.553443],"type":"Point"}
}
