{
  "type": "Feature",
  "properties": {
    "iso:country":"GB",
    "wof:name":"L1 5AY",
    "wof:placetype":"postalcode"
},
  "geometry": {"coordinates":[-2.98188670974373,53.40116002384789],"type":"Point"}
}