{
  "type": "Feature",
  "properties": {
    "iso:country": "GB",
    "wof:name": "L1 5AY",
    "wof:placetype": "postalcode"
  },
  "geometry": {"coordinates":[-2.981887,53.40116],"type":"Point"}
}
