{
  "type": "Feature",
  "properties": {
    "iso:country":"GB",
    "wof:name":"NR31 7JZ",
    "wof:placetype":"postalcode"
},
  "geometry": {"coordinates":[1.70961995628756,52.57278221478046],"type":"Point"}
}