{
  "type": "Feature",
  "properties": {
    "date:inception_lower":"1980-01-01",
    "date:inception_upper":"1980-01-31",
    "iso:country":"GB",
    "wof:name":"BD10 0NX",
    "wof:placetype":"postalcode"
},
  "geometry": {"coordinates":[-1.702288,53.841622],"type":"Point"}
}