{
  "type": "Feature",
  "properties": {
    "iso:country":"GB",
    "wof:name":"BD10 0NX",
    "wof:placetype":"postalcode"
},
  "geometry": {"coordinates":[-1.70228833557452,53.84162182022227],"type":"Point"}
}