{
  "type": "Feature",
  "properties": {
    "iso:country": "GB",
    "wof:name": "BD10 0NX",
    "wof:placetype": "postalcode"
  },
  "geometry": {"coordinates":[-1.702288,53.841622],"type":"Point"}
}
