{
  "type": "Feature",
  "properties": {
    "date:inception_lower": "2014-09-01",
    "date:inception_upper": "2014-09-01",
    "iso:country": "GB",
    "wof:name": "SW2 3FE",
    "wof:placetype": "postalcode"
  },
  "geometry": {"coordinates":[-0.117728,51.437051],"type":"Point"}
}
