{
  "type": "Feature",
  "properties": {
    "iso:country":"GB",
    "wof:name":"SW2 3FE",
    "wof:placetype":"postalcode"
},
  "geometry": {"coordinates":[-0.11775378262633,51.43705119271412],"type":"Point"}
}