{
  "type": "Feature",
  "properties": {
    "iso:country": "GB",
    "wof:name": "SW2 3FE",
    "wof:placetype": "postalcode"
  },
  "geometry": {"coordinates":[-0.117613,51.43704],"type":"Point"}
}
