{
  "type": "Feature",
  "properties": {
    "date:inception_lower":"2005-08-01",
    "date:inception_upper":"2005-08-31",
    "iso:country":"GB",
    "wof:name":"RH13 9LB",
    "wof:placetype":"postalcode"
},
  "geometry": {"coordinates":[-0.351734,51.024789],"type":"Point"}
}