{
  "type": "Feature",
  "properties": {
    "iso:country": "GB",
    "wof:name": "LS20 8HR",
    "wof:placetype": "postalcode"
  },
  "geometry": {"coordinates":[-1.732661,53.871452],"type":"Point"}
}
