{
  "type": "Feature",
  "properties": {
    "date:inception_lower": "1990-07-01",
    "date:inception_upper": "1990-07-01",
    "iso:country": "GB",
    "wof:name": "MK9 3JT",
    "wof:placetype": "postalcode"
  },
  "geometry": {"coordinates":[-0.750289,52.042928],"type":"Point"}
}
