{
  "type": "Feature",
  "properties": {
    "iso:country":"GB",
    "wof:name":"CF14 0RY",
    "wof:placetype":"postalcode"
},
  "geometry": {"coordinates":[-3.17790665482305,51.53474571724269],"type":"Point"}
}