{
  "type": "Feature",
  "properties": {
    "iso:country":"GB",
    "wof:name":"PA2 9DP",
    "wof:placetype":"postalcode"
},
  "geometry": {"coordinates":[-4.44646571695961,55.83706242868359],"type":"Point"}
}