{
  "type": "Feature",
  "properties": {
    "iso:country": "GB",
    "wof:name": "BS29 6DQ",
    "wof:placetype": "postalcode"
  },
  "geometry": {"coordinates":[-2.872279,51.330713],"type":"Point"}
}
