{
  "type": "Feature",
  "properties": {
    "iso:country":"GB",
    "wof:name":"BS29 6DQ",
    "wof:placetype":"postalcode"
},
  "geometry": {"coordinates":[-2.87227856446924,51.33071338267995],"type":"Point"}
}