{
  "type": "Feature",
  "properties": {
    "iso:country":"GB",
    "wof:name":"NE33 1LZ",
    "wof:placetype":"postalcode"
},
  "geometry": {"coordinates":[-1.4315039710778,54.99756270729558],"type":"Point"}
}