{
  "type": "Feature",
  "properties": {
    "date:inception_lower": "1980-01-01",
    "date:inception_upper": "1980-01-01",
    "iso:country": "GB",
    "wof:name": "B10 9NL",
    "wof:placetype": "postalcode"
  },
  "geometry": {"coordinates":[-1.846464,52.46965],"type":"Point"}
}
