{
  "type": "Feature",
  "properties": {
    "date:inception_lower": "1980-01-01",
    "date:inception_upper": "1980-01-01",
    "iso:country": "GB",
    "wof:name": "PL11 3EX",
    "wof:placetype": "postalcode"
  },
  "geometry": {"coordinates":[-4.321713,50.388094],"type":"Point"}
}
