{
  "type": "Feature",
  "properties": {
    "iso:country": "GB",
    "wof:name": "PL11 3EX",
    "wof:placetype": "postalcode"
  },
  "geometry": {"coordinates":[-4.321713,50.388094],"type":"Point"}
}
