{
  "type": "Feature",
  "properties": {
    "iso:country":"GB",
    "wof:name":"PL11 3EX",
    "wof:placetype":"postalcode"
},
  "geometry": {"coordinates":[-4.32179038237941,50.38833066932423],"type":"Point"}
}