{
  "type": "Feature",
  "properties": {
    "iso:country":"GB",
    "wof:name":"IG8 8DU",
    "wof:placetype":"postalcode"
},
  "geometry": {"coordinates":[0.05501332460198,51.60755625337066],"type":"Point"}
}