{
  "type": "Feature",
  "properties": {
    "iso:country":"GB",
    "wof:name":"EN5 5YR",
    "wof:placetype":"postalcode"
},
  "geometry": {"coordinates":[-0.19903937913754,51.65491008617915],"type":"Point"}
}