{
  "type": "Feature",
  "properties": {
    "date:inception_lower": "2004-01-01",
    "date:inception_upper": "2004-01-01",
    "iso:country": "GB",
    "wof:name": "EN5 5YR",
    "wof:placetype": "postalcode"
  },
  "geometry": {"coordinates":[-0.1991,51.654941],"type":"Point"}
}
