{
  "type": "Feature",
  "properties": {
    "iso:country":"GB",
    "wof:name":"WF2 0JB",
    "wof:placetype":"postalcode"
},
  "geometry": {"coordinates":[-1.52358257065504,53.69784747511212],"type":"Point"}
}