{
  "type": "Feature",
  "properties": {
    "date:inception_lower":"1992-01-01",
    "date:inception_upper":"1992-01-31",
    "iso:country":"GB",
    "wof:name":"DT1 1BE",
    "wof:placetype":"postalcode"
},
  "geometry": {"coordinates":[-2.437422,50.714847],"type":"Point"}
}