{
  "type": "Feature",
  "properties": {
    "iso:country":"GB",
    "wof:name":"WS4 1AR",
    "wof:placetype":"postalcode"
},
  "geometry": {"coordinates":[-1.95283686693071,52.62043736124033],"type":"Point"}
}