{
  "type": "Feature",
  "properties": {
    "date:inception_lower": "1980-01-01",
    "date:inception_upper": "1980-01-01",
    "iso:country": "GB",
    "wof:name": "LS21 1EN",
    "wof:placetype": "postalcode"
  },
  "geometry": {"coordinates":[-1.638821,53.895471],"type":"Point"}
}
