{
  "type": "Feature",
  "properties": {
    "iso:country":"GB",
    "wof:name":"LS21 1EN",
    "wof:placetype":"postalcode"
},
  "geometry": {"coordinates":[-1.6388158225141,53.89545599852624],"type":"Point"}
}