{
  "type": "Feature",
  "properties": {
    "iso:country": "GB",
    "wof:name": "LS21 1EN",
    "wof:placetype": "postalcode"
  },
  "geometry": {"coordinates":[-1.638821,53.895471],"type":"Point"}
}
