{
  "type": "Feature",
  "properties": {
    "date:inception_lower":"1980-01-01",
    "date:inception_upper":"1980-01-31",
    "iso:country":"GB",
    "wof:name":"B92 7AE",
    "wof:placetype":"postalcode"
},
  "geometry": {"coordinates":[-1.800568,52.432984],"type":"Point"}
}