{
  "type": "Feature",
  "properties": {
    "iso:country":"GB",
    "wof:name":"B92 7AE",
    "wof:placetype":"postalcode"
},
  "geometry": {"coordinates":[-1.8005684693578,52.43298364568298],"type":"Point"}
}