{
  "type": "Feature",
  "properties": {
    "iso:country": "GB",
    "wof:name": "CM15 9DL",
    "wof:placetype": "postalcode"
  },
  "geometry": {"coordinates":[0.30038,51.625881],"type":"Point"}
}
