{
  "type": "Feature",
  "properties": {
    "iso:country":"GB",
    "wof:name":"BS6 7AN",
    "wof:placetype":"postalcode"
},
  "geometry": {"coordinates":[-2.59689443445357,51.47077869076153],"type":"Point"}
}