{
  "type": "Feature",
  "properties": {
    "date:inception_lower": "1980-01-01",
    "date:inception_upper": "1980-01-01",
    "iso:country": "GB",
    "wof:name": "NE8 4BB",
    "wof:placetype": "postalcode"
  },
  "geometry": {"coordinates":[-1.598408,54.952693],"type":"Point"}
}
