{
  "type": "Feature",
  "properties": {
    "iso:country":"GB",
    "wof:name":"NE8 4BB",
    "wof:placetype":"postalcode"
},
  "geometry": {"coordinates":[-1.59701571392388,54.95327381865658],"type":"Point"}
}