{
  "type": "Feature",
  "properties": {
    "date:inception_lower": "1980-01-01",
    "date:inception_upper": "1980-01-01",
    "iso:country": "GB",
    "wof:name": "TN33 0HL",
    "wof:placetype": "postalcode"
  },
  "geometry": {"coordinates":[0.479774,50.925122],"type":"Point"}
}
