{
  "type": "Feature",
  "properties": {
    "iso:country":"GB",
    "wof:name":"OL11 5LD",
    "wof:placetype":"postalcode"
},
  "geometry": {"coordinates":[-2.18627864157779,53.61409666050616],"type":"Point"}
}