{
  "type": "Feature",
  "properties": {
    "iso:country":"GB",
    "wof:name":"CH46 0SX",
    "wof:placetype":"postalcode"
},
  "geometry": {"coordinates":[-3.11254556627046,53.39707437488656],"type":"Point"}
}