{
  "type": "Feature",
  "properties": {
    "iso:country": "GB",
    "wof:name": "GL52 3NG",
    "wof:placetype": "postalcode"
  },
  "geometry": {"coordinates":[-2.030464,51.91804],"type":"Point"}
}
