{
  "type": "Feature",
  "properties": {
    "iso:country":"GB",
    "wof:name":"DL7 0LS",
    "wof:placetype":"postalcode"
},
  "geometry": {"coordinates":[-1.47116327162009,54.3454816825555],"type":"Point"}
}