{
  "type": "Feature",
  "properties": {
    "iso:country":"GB",
    "wof:name":"RG42 7PN",
    "wof:placetype":"postalcode"
},
  "geometry": {"coordinates":[-0.70874106284777,51.42622985114293],"type":"Point"}
}