{
  "type": "Feature",
  "properties": {
    "iso:country":"GB",
    "wof:name":"HA5 5RS",
    "wof:placetype":"postalcode"
},
  "geometry": {"coordinates":[-0.369208716828,51.5904502700442],"type":"Point"}
}