{
  "type": "Feature",
  "properties": {
    "iso:country": "GB",
    "wof:name": "HA5 5RS",
    "wof:placetype": "postalcode"
  },
  "geometry": {"coordinates":[-0.369209,51.59045],"type":"Point"}
}
