{
  "type": "Feature",
  "properties": {
    "date:inception_lower": "1980-01-01",
    "date:inception_upper": "1980-01-01",
    "iso:country": "GB",
    "wof:name": "DN14 0LY",
    "wof:placetype": "postalcode"
  },
  "geometry": {"coordinates":[-1.14829,53.706293],"type":"Point"}
}
