{
  "type": "Feature",
  "properties": {
    "iso:country": "GB",
    "wof:name": "TQ7 4LX",
    "wof:placetype": "postalcode"
  },
  "geometry": {"coordinates":[-3.83867,50.314139],"type":"Point"}
}
