{
  "type": "Feature",
  "properties": {
    "date:inception_lower": "2000-06-01",
    "date:inception_upper": "2000-06-01",
    "iso:country": "GB",
    "wof:name": "CA7 2HF",
    "wof:placetype": "postalcode"
  },
  "geometry": {"coordinates":[-3.32471,54.733246],"type":"Point"}
}
