{
  "type": "Feature",
  "properties": {
    "iso:country": "GB",
    "wof:name": "CA7 2HF",
    "wof:placetype": "postalcode"
  },
  "geometry": {"coordinates":[-3.321606,54.736174],"type":"Point"}
}
