{
  "type": "Feature",
  "properties": {
    "iso:country":"GB",
    "wof:name":"TA11 7JL",
    "wof:placetype":"postalcode"
},
  "geometry": {"coordinates":[-2.70930113156082,51.0533651078136],"type":"Point"}
}