{
  "type": "Feature",
  "properties": {
    "iso:country": "GB",
    "wof:name": "TA11 7JL",
    "wof:placetype": "postalcode"
  },
  "geometry": {"coordinates":[-2.709449,51.053412],"type":"Point"}
}
