{
  "type": "Feature",
  "properties": {
    "date:inception_lower": "1980-01-01",
    "date:inception_upper": "1980-01-01",
    "iso:country": "GB",
    "wof:name": "TA11 7JL",
    "wof:placetype": "postalcode"
  },
  "geometry": {"coordinates":[-2.709449,51.053412],"type":"Point"}
}
