{
  "type": "Feature",
  "properties": {
    "date:inception_lower": "1980-01-01",
    "date:inception_upper": "1980-01-01",
    "iso:country": "GB",
    "wof:name": "RG17 0JY",
    "wof:placetype": "postalcode"
  },
  "geometry": {"coordinates":[-1.520254,51.410633],"type":"Point"}
}
