{
  "type": "Feature",
  "properties": {
    "iso:country":"GB",
    "wof:name":"RG17 0JY",
    "wof:placetype":"postalcode"
},
  "geometry": {"coordinates":[-1.52036974541452,51.4106438818085],"type":"Point"}
}