{
  "type": "Feature",
  "properties": {
    "iso:country":"GB",
    "wof:name":"TW13 6RU",
    "wof:placetype":"postalcode"
},
  "geometry": {"coordinates":[-0.39233671451686,51.43074340011732],"type":"Point"}
}