{
  "type": "Feature",
  "properties": {
    "iso:country":"GB",
    "wof:name":"PL7 1WT",
    "wof:placetype":"postalcode"
},
  "geometry": {"coordinates":[-4.07422414530583,50.38667910970567],"type":"Point"}
}