{
  "type": "Feature",
  "properties": {
    "iso:country":"GB",
    "wof:name":"HX4 8JH",
    "wof:placetype":"postalcode"
},
  "geometry": {"coordinates":[-1.87808450475107,53.68746984859434],"type":"Point"}
}