{
  "type": "Feature",
  "properties": {
    "date:inception_lower": "1980-01-01",
    "date:inception_upper": "1980-01-01",
    "iso:country": "GB",
    "wof:name": "HX4 8JH",
    "wof:placetype": "postalcode"
  },
  "geometry": {"coordinates":[-1.878084,53.68747],"type":"Point"}
}
