{
  "type": "Feature",
  "properties": {
    "iso:country":"GB",
    "wof:name":"TN23 5DY",
    "wof:placetype":"postalcode"
},
  "geometry": {"coordinates":[0.8499186622582,51.13678355095418],"type":"Point"}
}