{
  "type": "Feature",
  "properties": {
    "date:inception_lower": "1994-12-01",
    "date:inception_upper": "1994-12-01",
    "iso:country": "GB",
    "wof:name": "TN23 5DY",
    "wof:placetype": "postalcode"
  },
  "geometry": {"coordinates":[0.849919,51.136784],"type":"Point"}
}
