{
  "type": "Feature",
  "properties": {
    "iso:country":"GB",
    "wof:name":"DL13 2XF",
    "wof:placetype":"postalcode"
},
  "geometry": {"coordinates":[-2.00316829611093,54.74568132898081],"type":"Point"}
}