{
  "type": "Feature",
  "properties": {
    "iso:country":"GB",
    "wof:name":"N3 2DE",
    "wof:placetype":"postalcode"
},
  "geometry": {"coordinates":[-0.18729026579363,51.60188159589619],"type":"Point"}
}