{
  "type": "Feature",
  "properties": {
    "date:inception_lower": "1980-01-01",
    "date:inception_upper": "1980-01-01",
    "iso:country": "GB",
    "wof:name": "N3 2DE",
    "wof:placetype": "postalcode"
  },
  "geometry": {"coordinates":[-0.18729,51.601882],"type":"Point"}
}
