{
  "type": "Feature",
  "properties": {
    "iso:country":"GB",
    "wof:name":"WV13 2NL",
    "wof:placetype":"postalcode"
},
  "geometry": {"coordinates":[-2.05655750799578,52.58423120629098],"type":"Point"}
}