{
  "type": "Feature",
  "properties": {
    "iso:country":"GB",
    "wof:name":"LS14 2ES",
    "wof:placetype":"postalcode"
},
  "geometry": {"coordinates":[-1.45396903781378,53.83611148732767],"type":"Point"}
}