{
  "type": "Feature",
  "properties": {
    "date:inception_lower": "1980-01-01",
    "date:inception_upper": "1980-01-01",
    "iso:country": "GB",
    "wof:name": "PL9 0JJ",
    "wof:placetype": "postalcode"
  },
  "geometry": {"coordinates":[-4.072758,50.324644],"type":"Point"}
}
