{
  "type": "Feature",
  "properties": {
    "iso:country":"GB",
    "wof:name":"CF40 1HS",
    "wof:placetype":"postalcode"
},
  "geometry": {"coordinates":[-3.43156682249844,51.61434450142414],"type":"Point"}
}