{
  "type": "Feature",
  "properties": {
    "iso:country":"GB",
    "wof:name":"W12 0PH",
    "wof:placetype":"postalcode"
},
  "geometry": {"coordinates":[-0.23962829712907,51.50827664464562],"type":"Point"}
}