{
  "type": "Feature",
  "properties": {
    "date:inception_lower": "2001-06-01",
    "date:inception_upper": "2001-06-01",
    "iso:country": "GB",
    "wof:name": "CW5 6RP",
    "wof:placetype": "postalcode"
  },
  "geometry": {"coordinates":[-2.481473,53.071477],"type":"Point"}
}
