{
  "type": "Feature",
  "properties": {
    "iso:country":"GB",
    "wof:name":"CW5 6RP",
    "wof:placetype":"postalcode"
},
  "geometry": {"coordinates":[-2.48147261344426,53.07147653470446],"type":"Point"}
}