{
  "type": "Feature",
  "properties": {
    "iso:country":"GB",
    "wof:name":"S60 1LW",
    "wof:placetype":"postalcode"
},
  "geometry": {"coordinates":[-1.36716174271312,53.43230537792438],"type":"Point"}
}