{
  "type": "Feature",
  "properties": {
    "iso:country":"GB",
    "wof:name":"TN13 2HU",
    "wof:placetype":"postalcode"
},
  "geometry": {"coordinates":[0.17727590230745,51.28008414901134],"type":"Point"}
}