{
  "type": "Feature",
  "properties": {
    "iso:country":"GB",
    "wof:name":"EN8 8HN",
    "wof:placetype":"postalcode"
},
  "geometry": {"coordinates":[-0.04893084602904,51.68187208792833],"type":"Point"}
}