{
  "type": "Feature",
  "properties": {
    "iso:country":"GB",
    "wof:name":"EN1 2PR",
    "wof:placetype":"postalcode"
},
  "geometry": {"coordinates":[-0.07147079885042,51.64129304559942],"type":"Point"}
}