{
  "type": "Feature",
  "properties": {
    "date:inception_lower": "1980-01-01",
    "date:inception_upper": "1980-01-01",
    "iso:country": "GB",
    "wof:name": "RH11 7AZ",
    "wof:placetype": "postalcode"
  },
  "geometry": {"coordinates":[-0.196926,51.114547],"type":"Point"}
}
