{
  "type": "Feature",
  "properties": {
    "iso:country":"GB",
    "wof:name":"OX9 3HP",
    "wof:placetype":"postalcode"
},
  "geometry": {"coordinates":[-0.97286104448845,51.74470021669791],"type":"Point"}
}