{
  "type": "Feature",
  "properties": {
    "iso:country":"GB",
    "wof:name":"WN3 5JB",
    "wof:placetype":"postalcode"
},
  "geometry": {"coordinates":[-2.64892811634464,53.52722577288577],"type":"Point"}
}