{
  "type": "Feature",
  "properties": {
    "iso:country": "GB",
    "wof:name": "WN3 5JB",
    "wof:placetype": "postalcode"
  },
  "geometry": {"coordinates":[-2.648928,53.527226],"type":"Point"}
}
