{
  "type": "Feature",
  "properties": {
    "iso:country": "GB",
    "wof:name": "NR14 6UA",
    "wof:placetype": "postalcode"
  },
  "geometry": {"coordinates":[1.478461,52.528558],"type":"Point"}
}
