{
  "type": "Feature",
  "properties": {
    "iso:country":"GB",
    "wof:name":"NR14 6UA",
    "wof:placetype":"postalcode"
},
  "geometry": {"coordinates":[1.47846097329621,52.52855757256663],"type":"Point"}
}