{
  "type": "Feature",
  "properties": {
    "iso:country":"GB",
    "wof:name":"SE14 6AD",
    "wof:placetype":"postalcode"
},
  "geometry": {"coordinates":[-0.03824104672719,51.47339983118486],"type":"Point"}
}