{
  "type": "Feature",
  "properties": {
    "iso:country":"GB",
    "wof:name":"HP19 9JL",
    "wof:placetype":"postalcode"
},
  "geometry": {"coordinates":[-0.82802798727999,51.82594107980789],"type":"Point"}
}