{
  "type": "Feature",
  "properties": {
    "date:inception_lower": "1980-01-01",
    "date:inception_upper": "1980-01-01",
    "iso:country": "GB",
    "wof:name": "OL16 5BU",
    "wof:placetype": "postalcode"
  },
  "geometry": {"coordinates":[-2.131823,53.616183],"type":"Point"}
}
