{
  "type": "Feature",
  "properties": {
    "date:inception_lower":"1980-01-01",
    "date:inception_upper":"1980-01-31",
    "iso:country":"GB",
    "wof:name":"OX7 4AT",
    "wof:placetype":"postalcode"
},
  "geometry": {"coordinates":[-1.47123,51.979102],"type":"Point"}
}