{
  "type": "Feature",
  "properties": {
    "iso:country":"GB",
    "wof:name":"OX7 4AT",
    "wof:placetype":"postalcode"
},
  "geometry": {"coordinates":[-1.4712302543549,51.97910231364315],"type":"Point"}
}