{
  "type": "Feature",
  "properties": {
    "date:inception_lower": "1980-01-01",
    "date:inception_upper": "1980-01-01",
    "iso:country": "GB",
    "wof:name": "WC1E 6BP",
    "wof:placetype": "postalcode"
  },
  "geometry": {"coordinates":[-0.135188,51.525052],"type":"Point"}
}
