{
  "type": "Feature",
  "properties": {
    "iso:country":"GB",
    "wof:name":"B65 9PB",
    "wof:placetype":"postalcode"
},
  "geometry": {"coordinates":[-2.0365058878902,52.48535050949177],"type":"Point"}
}