{
  "type": "Feature",
  "properties": {
    "date:inception_lower": "1980-01-01",
    "date:inception_upper": "1980-01-01",
    "iso:country": "GB",
    "wof:name": "B65 9PB",
    "wof:placetype": "postalcode"
  },
  "geometry": {"coordinates":[-2.036506,52.485351],"type":"Point"}
}
