{
  "type": "Feature",
  "properties": {
    "iso:country":"GB",
    "wof:name":"ME2 3BU",
    "wof:placetype":"postalcode"
},
  "geometry": {"coordinates":[0.49585790130579,51.40284477432118],"type":"Point"}
}