{
  "type": "Feature",
  "properties": {
    "iso:country": "GB",
    "wof:name": "ME2 3BU",
    "wof:placetype": "postalcode"
  },
  "geometry": {"coordinates":[0.495858,51.402845],"type":"Point"}
}
