{
  "type": "Feature",
  "properties": {
    "iso:country": "GB",
    "wof:name": "NG16 2DR",
    "wof:placetype": "postalcode"
  },
  "geometry": {"coordinates":[-1.281297,53.01054],"type":"Point"}
}
