{
  "type": "Feature",
  "properties": {
    "iso:country":"GB",
    "wof:name":"AL2 2PP",
    "wof:placetype":"postalcode"
},
  "geometry": {"coordinates":[-0.34180527565035,51.72324811116238],"type":"Point"}
}