{
  "type": "Feature",
  "properties": {
    "iso:country":"GB",
    "wof:name":"WN7 3BS",
    "wof:placetype":"postalcode"
},
  "geometry": {"coordinates":[-2.49707847758371,53.49082232118441],"type":"Point"}
}