{
  "type": "Feature",
  "properties": {
    "date:inception_lower":"2007-02-01",
    "date:inception_upper":"2007-02-28",
    "iso:country":"GB",
    "wof:name":"PE2 9ST",
    "wof:placetype":"postalcode"
},
  "geometry": {"coordinates":[-0.259444,52.566025],"type":"Point"}
}