{
  "type": "Feature",
  "properties": {
    "iso:country":"GB",
    "wof:name":"PE2 9ST",
    "wof:placetype":"postalcode"
},
  "geometry": {"coordinates":[-0.25944440553536,52.56602548951655],"type":"Point"}
}