{
  "type": "Feature",
  "properties": {
    "date:inception_lower": "2008-02-01",
    "date:inception_upper": "2008-02-01",
    "iso:country": "GB",
    "wof:name": "MK18 2FY",
    "wof:placetype": "postalcode"
  },
  "geometry": {"coordinates":[-0.93034,51.924363],"type":"Point"}
}
