{
  "type": "Feature",
  "properties": {
    "iso:country": "GB",
    "wof:name": "LU7 1HH",
    "wof:placetype": "postalcode"
  },
  "geometry": {"coordinates":[-0.664191,51.917499],"type":"Point"}
}
