{
  "type": "Feature",
  "properties": {
    "date:inception_lower": "2016-10-01",
    "date:inception_upper": "2016-10-01",
    "iso:country": "GB",
    "wof:name": "E2 6FA",
    "wof:placetype": "postalcode"
  },
  "geometry": {"coordinates":[-0.055215,51.524619],"type":"Point"}
}
