{
  "type": "Feature",
  "properties": {
    "date:inception_lower": "2015-08-01",
    "date:inception_upper": "2015-08-01",
    "iso:country": "GB",
    "wof:name": "FY2 0XX",
    "wof:placetype": "postalcode"
  },
  "geometry": {"coordinates":[-3.020227,53.855192],"type":"Point"}
}
