{
  "type": "Feature",
  "properties": {
    "iso:country":"GB",
    "wof:name":"FY2 0XX",
    "wof:placetype":"postalcode"
},
  "geometry": {"coordinates":[-3.02131143476962,53.85266102003173],"type":"Point"}
}