{
  "type": "Feature",
  "properties": {
    "iso:country":"GB",
    "wof:name":"LS19 7YB",
    "wof:placetype":"postalcode"
},
  "geometry": {"coordinates":[-1.68091495316712,53.86035168125934],"type":"Point"}
}