{
  "type": "Feature",
  "properties": {
    "iso:country":"GB",
    "wof:name":"TW17 0SG",
    "wof:placetype":"postalcode"
},
  "geometry": {"coordinates":[-0.44371500708982,51.41316437362502],"type":"Point"}
}