{
  "type": "Feature",
  "properties": {
    "iso:country":"GB",
    "wof:name":"BS29 6DN",
    "wof:placetype":"postalcode"
},
  "geometry": {"coordinates":[-2.86539045277354,51.32850751194925],"type":"Point"}
}