{
  "type": "Feature",
  "properties": {
    "iso:country": "GB",
    "wof:name": "ST7 3FE",
    "wof:placetype": "postalcode"
  },
  "geometry": {"coordinates":[-2.284645,53.103993],"type":"Point"}
}
