{
  "type": "Feature",
  "properties": {
    "date:inception_lower": "1980-01-01",
    "date:inception_upper": "1980-01-01",
    "iso:country": "GB",
    "wof:name": "NP7 7ET",
    "wof:placetype": "postalcode"
  },
  "geometry": {"coordinates":[-3.067712,51.838164],"type":"Point"}
}
