{
  "type": "Feature",
  "properties": {
    "iso:country":"GB",
    "wof:name":"NP7 7ET",
    "wof:placetype":"postalcode"
},
  "geometry": {"coordinates":[-3.06776453702506,51.83819443852026],"type":"Point"}
}