{
  "type": "Feature",
  "properties": {
    "iso:country":"GB",
    "wof:name":"WD25 9NZ",
    "wof:placetype":"postalcode"
},
  "geometry": {"coordinates":[-0.38313325222955,51.69504975025141],"type":"Point"}
}