{
  "type": "Feature",
  "properties": {
    "iso:country":"GB",
    "wof:name":"M43 6JF",
    "wof:placetype":"postalcode"
},
  "geometry": {"coordinates":[-2.1693970953684,53.48647835206462],"type":"Point"}
}