{
  "type": "Feature",
  "properties": {
    "iso:country": "GB",
    "wof:name": "S9 2SU",
    "wof:placetype": "postalcode"
  },
  "geometry": {"coordinates":[-1.426909,53.40369],"type":"Point"}
}
