{
  "type": "Feature",
  "properties": {
    "iso:country":"GB",
    "wof:name":"CM22 7NA",
    "wof:placetype":"postalcode"
},
  "geometry": {"coordinates":[0.17985473235089,51.80326818607653],"type":"Point"}
}