{
  "type": "Feature",
  "properties": {
    "date:inception_lower": "1980-01-01",
    "date:inception_upper": "1980-01-01",
    "iso:country": "GB",
    "wof:name": "GL5 1LF",
    "wof:placetype": "postalcode"
  },
  "geometry": {"coordinates":[-2.209555,51.746122],"type":"Point"}
}
