{
  "type": "Feature",
  "properties": {
    "iso:country":"GB",
    "wof:name":"LA13 9DN",
    "wof:placetype":"postalcode"
},
  "geometry": {"coordinates":[-3.20258759862391,54.11683623955393],"type":"Point"}
}