{
  "type": "Feature",
  "properties": {
    "iso:country": "GB",
    "wof:name": "LA13 9DN",
    "wof:placetype": "postalcode"
  },
  "geometry": {"coordinates":[-3.202588,54.116836],"type":"Point"}
}
