{
  "type": "Feature",
  "properties": {
    "iso:country": "GB",
    "wof:name": "LU1 5BP",
    "wof:placetype": "postalcode"
  },
  "geometry": {"coordinates":[-0.420224,51.876245],"type":"Point"}
}
