{
  "type": "Feature",
  "properties": {
    "iso:country":"GB",
    "wof:name":"LU1 5BP",
    "wof:placetype":"postalcode"
},
  "geometry": {"coordinates":[-0.42022412754556,51.87624503633054],"type":"Point"}
}