{
  "type": "Feature",
  "properties": {
    "date:inception_lower": "1980-01-01",
    "date:inception_upper": "1980-01-01",
    "iso:country": "GB",
    "wof:name": "WF16 9BZ",
    "wof:placetype": "postalcode"
  },
  "geometry": {"coordinates":[-1.678598,53.718038],"type":"Point"}
}
