{
  "type": "Feature",
  "properties": {
    "iso:country":"GB",
    "wof:name":"WS6 7QD",
    "wof:placetype":"postalcode"
},
  "geometry": {"coordinates":[-2.02562245447288,52.65903665759043],"type":"Point"}
}