{
  "type": "Feature",
  "properties": {
    "date:inception_lower":"1995-12-01",
    "date:inception_upper":"1995-12-31",
    "iso:country":"GB",
    "wof:name":"WS6 7QD",
    "wof:placetype":"postalcode"
},
  "geometry": {"coordinates":[-2.025622,52.659037],"type":"Point"}
}