{
  "type": "Feature",
  "properties": {
    "iso:country":"GB",
    "wof:name":"CV7 7JW",
    "wof:placetype":"postalcode"
},
  "geometry": {"coordinates":[-1.6528753660615,52.44865398913465],"type":"Point"}
}