{
  "type": "Feature",
  "properties": {
    "iso:country": "GB",
    "wof:name": "CV7 7JW",
    "wof:placetype": "postalcode"
  },
  "geometry": {"coordinates":[-1.652875,52.448654],"type":"Point"}
}
