{
  "type": "Feature",
  "properties": {
    "iso:country":"GB",
    "wof:name":"EX17 4RY",
    "wof:placetype":"postalcode"
},
  "geometry": {"coordinates":[-3.66114736354649,50.86607802982456],"type":"Point"}
}