{
  "type": "Feature",
  "properties": {
    "iso:country":"GB",
    "wof:name":"DN21 5JF",
    "wof:placetype":"postalcode"
},
  "geometry": {"coordinates":[-0.69089006490347,53.36399237205851],"type":"Point"}
}