{
  "type": "Feature",
  "properties": {
    "iso:country": "GB",
    "wof:name": "DN21 5JF",
    "wof:placetype": "postalcode"
  },
  "geometry": {"coordinates":[-0.69089,53.363992],"type":"Point"}
}
