{
  "type": "Feature",
  "properties": {
    "date:inception_lower": "2005-02-01",
    "date:inception_upper": "2005-02-01",
    "iso:country": "GB",
    "wof:name": "DN21 5JF",
    "wof:placetype": "postalcode"
  },
  "geometry": {"coordinates":[-0.69089,53.363992],"type":"Point"}
}
