{
  "type": "Feature",
  "properties": {
    "iso:country":"GB",
    "wof:name":"NN5 6RN",
    "wof:placetype":"postalcode"
},
  "geometry": {"coordinates":[-0.94954459925864,52.25680459763592],"type":"Point"}
}