{
  "type": "Feature",
  "properties": {
    "iso:country":"GB",
    "wof:name":"OX18 2PB",
    "wof:placetype":"postalcode"
},
  "geometry": {"coordinates":[-1.58958606196628,51.71852983457657],"type":"Point"}
}