{
  "type": "Feature",
  "properties": {
    "iso:country": "GB",
    "wof:name": "M40 8NL",
    "wof:placetype": "postalcode"
  },
  "geometry": {"coordinates":[-2.217958,53.496563],"type":"Point"}
}
