{
  "type": "Feature",
  "properties": {
    "date:inception_lower":"1995-07-01",
    "date:inception_upper":"1995-07-31",
    "iso:country":"GB",
    "wof:name":"CF83 2EU",
    "wof:placetype":"postalcode"
},
  "geometry": {"coordinates":[-3.246363,51.59173],"type":"Point"}
}