{
  "type": "Feature",
  "properties": {
    "iso:country":"GB",
    "wof:name":"CH42 1QB",
    "wof:placetype":"postalcode"
},
  "geometry": {"coordinates":[-3.00339044608457,53.36772199385418],"type":"Point"}
}