{
  "type": "Feature",
  "properties": {
    "iso:country":"GB",
    "wof:name":"NR30 5QS",
    "wof:placetype":"postalcode"
},
  "geometry": {"coordinates":[1.71857253717949,52.65559437277334],"type":"Point"}
}