{
  "type": "Feature",
  "properties": {
    "iso:country":"GB",
    "wof:name":"OX4 7UH",
    "wof:placetype":"postalcode"
},
  "geometry": {"coordinates":[-1.18677494010492,51.72074030092975],"type":"Point"}
}