{
  "type": "Feature",
  "properties": {
    "date:inception_lower": "1980-01-01",
    "date:inception_upper": "1980-01-01",
    "iso:country": "GB",
    "wof:name": "B20 2JG",
    "wof:placetype": "postalcode"
  },
  "geometry": {"coordinates":[-1.933513,52.514825],"type":"Point"}
}
