{
  "type": "Feature",
  "properties": {
    "iso:country":"GB",
    "wof:name":"B20 2JG",
    "wof:placetype":"postalcode"
},
  "geometry": {"coordinates":[-1.93351295026561,52.51482465692141],"type":"Point"}
}