{
  "type": "Feature",
  "properties": {
    "iso:country":"GB",
    "wof:name":"TN22 1RX",
    "wof:placetype":"postalcode"
},
  "geometry": {"coordinates":[0.10299943682997,50.97872712491247],"type":"Point"}
}