{
  "type": "Feature",
  "properties": {
    "iso:country":"GB",
    "wof:name":"HA9 0TF",
    "wof:placetype":"postalcode"
},
  "geometry": {"coordinates":[-0.27523707481732,51.55974722078781],"type":"Point"}
}