{
  "type": "Feature",
  "properties": {
    "iso:country": "GB",
    "wof:name": "HA9 0TF",
    "wof:placetype": "postalcode"
  },
  "geometry": {"coordinates":[-0.275847,51.559786],"type":"Point"}
}
