{
  "type": "Feature",
  "properties": {
    "date:inception_lower":"1987-04-01",
    "date:inception_upper":"1987-04-30",
    "iso:country":"GB",
    "wof:name":"HA9 0TF",
    "wof:placetype":"postalcode"
},
  "geometry": {"coordinates":[-0.275847,51.559786],"type":"Point"}
}