{
  "type": "Feature",
  "properties": {
    "iso:country":"GB",
    "wof:name":"CO8 5JT",
    "wof:placetype":"postalcode"
},
  "geometry": {"coordinates":[0.76647448223691,51.99329250184031],"type":"Point"}
}