{
  "type": "Feature",
  "properties": {
    "iso:country": "GB",
    "wof:name": "MK45 1FY",
    "wof:placetype": "postalcode"
  },
  "geometry": {"coordinates":[-0.509025,52.009509],"type":"Point"}
}
