{
  "type": "Feature",
  "properties": {
    "iso:country": "GB",
    "wof:name": "NP26 3NL",
    "wof:placetype": "postalcode"
  },
  "geometry": {"coordinates":[-2.822792,51.584603],"type":"Point"}
}
