{
  "type": "Feature",
  "properties": {
    "iso:country":"GB",
    "wof:name":"NP26 3NL",
    "wof:placetype":"postalcode"
},
  "geometry": {"coordinates":[-2.82279190197532,51.58460253756971],"type":"Point"}
}