{
  "type": "Feature",
  "properties": {
    "iso:country":"GB",
    "wof:name":"OX28 6DT",
    "wof:placetype":"postalcode"
},
  "geometry": {"coordinates":[-1.49571303696145,51.79129872382515],"type":"Point"}
}