{
  "type": "Feature",
  "properties": {
    "date:inception_lower": "2001-06-01",
    "date:inception_upper": "2001-06-01",
    "iso:country": "GB",
    "wof:name": "OX28 6DT",
    "wof:placetype": "postalcode"
  },
  "geometry": {"coordinates":[-1.495713,51.791299],"type":"Point"}
}
