{
  "type": "Feature",
  "properties": {
    "iso:country": "GB",
    "wof:name": "SL6 0HL",
    "wof:placetype": "postalcode"
  },
  "geometry": {"coordinates":[-0.681397,51.551943],"type":"Point"}
}
