{
  "type": "Feature",
  "properties": {
    "iso:country":"GB",
    "wof:name":"SL6 0HL",
    "wof:placetype":"postalcode"
},
  "geometry": {"coordinates":[-0.68153999386734,51.55162644377746],"type":"Point"}
}