{
  "type": "Feature",
  "properties": {
    "iso:country": "GB",
    "wof:name": "M5 3EE",
    "wof:placetype": "postalcode"
  },
  "geometry": {"coordinates":[-2.282892,53.46612],"type":"Point"}
}
