{
  "type": "Feature",
  "properties": {
    "date:inception_lower":"1992-08-01",
    "date:inception_upper":"1992-08-31",
    "iso:country":"GB",
    "wof:name":"M5 3EE",
    "wof:placetype":"postalcode"
},
  "geometry": {"coordinates":[-2.282892,53.46612],"type":"Point"}
}