{
  "type": "Feature",
  "properties": {
    "iso:country":"GB",
    "wof:name":"LE4 3AT",
    "wof:placetype":"postalcode"
},
  "geometry": {"coordinates":[-1.12971864658649,52.67631614056565],"type":"Point"}
}