{
  "type": "Feature",
  "properties": {
    "iso:country":"GB",
    "wof:name":"G62 6NR",
    "wof:placetype":"postalcode"
},
  "geometry": {"coordinates":[-4.31725245903368,55.93435718523444],"type":"Point"}
}