{
  "type": "Feature",
  "properties": {
    "iso:country":"GB",
    "wof:name":"NE12 8QF",
    "wof:placetype":"postalcode"
},
  "geometry": {"coordinates":[-1.58581669734469,55.01134137381683],"type":"Point"}
}