{
  "type": "Feature",
  "properties": {
    "iso:country":"GB",
    "wof:name":"SN4 8BX",
    "wof:placetype":"postalcode"
},
  "geometry": {"coordinates":[-1.89737508056864,51.54059849335601],"type":"Point"}
}