{
  "type": "Feature",
  "properties": {
    "iso:country":"GB",
    "wof:name":"CF45 4NL",
    "wof:placetype":"postalcode"
},
  "geometry": {"coordinates":[-3.33498936590041,51.64206259290514],"type":"Point"}
}