{
  "type": "Feature",
  "properties": {
    "date:inception_lower": "2003-09-01",
    "date:inception_upper": "2003-09-01",
    "iso:country": "GB",
    "wof:name": "CT12 5JQ",
    "wof:placetype": "postalcode"
  },
  "geometry": {"coordinates":[1.364899,51.327819],"type":"Point"}
}
