{
  "type": "Feature",
  "properties": {
    "iso:country": "GB",
    "wof:name": "KA11 1QN",
    "wof:placetype": "postalcode"
  },
  "geometry": {"coordinates":[-4.629245,55.629052],"type":"Point"}
}
