{
  "type": "Feature",
  "properties": {
    "iso:country":"GB",
    "wof:name":"KA11 1QN",
    "wof:placetype":"postalcode"
},
  "geometry": {"coordinates":[-4.62924538662802,55.62905218259471],"type":"Point"}
}