{
  "type": "Feature",
  "properties": {
    "date:inception_lower":"1987-02-01",
    "date:inception_upper":"1987-02-28",
    "iso:country":"GB",
    "wof:name":"KA11 1QN",
    "wof:placetype":"postalcode"
},
  "geometry": {"coordinates":[-4.629245,55.629052],"type":"Point"}
}