{
  "type": "Feature",
  "properties": {
    "iso:country": "GB",
    "wof:name": "WD24 5FN",
    "wof:placetype": "postalcode"
  },
  "geometry": {"coordinates":[-0.406576,51.683201],"type":"Point"}
}
