{
  "type": "Feature",
  "properties": {
    "iso:country":"GB",
    "wof:name":"LE8 6AN",
    "wof:placetype":"postalcode"
},
  "geometry": {"coordinates":[-1.179130438612,52.57222295347664],"type":"Point"}
}