{
  "type": "Feature",
  "properties": {
    "iso:country":"GB",
    "wof:name":"BB2 2QZ",
    "wof:placetype":"postalcode"
},
  "geometry": {"coordinates":[-2.50325707461712,53.73721167065681],"type":"Point"}
}