{
  "type": "Feature",
  "properties": {
    "iso:country":"GB",
    "wof:name":"AB34 4YJ",
    "wof:placetype":"postalcode"
},
  "geometry": {"coordinates":[-2.9074519476891,57.13347782594636],"type":"Point"}
}