{
  "type": "Feature",
  "properties": {
    "date:inception_lower": "1980-01-01",
    "date:inception_upper": "1980-01-01",
    "iso:country": "GB",
    "wof:name": "B93 9BG",
    "wof:placetype": "postalcode"
  },
  "geometry": {"coordinates":[-1.762157,52.386485],"type":"Point"}
}
