{
  "type": "Feature",
  "properties": {
    "iso:country":"GB",
    "wof:name":"B93 9BG",
    "wof:placetype":"postalcode"
},
  "geometry": {"coordinates":[-1.761652277567,52.38612729956463],"type":"Point"}
}