{
  "type": "Feature",
  "properties": {
    "iso:country": "GB",
    "wof:name": "NE10 8QX",
    "wof:placetype": "postalcode"
  },
  "geometry": {"coordinates":[-1.553289,54.934133],"type":"Point"}
}
