{
  "type": "Feature",
  "properties": {
    "iso:country":"GB",
    "wof:name":"NE10 8QX",
    "wof:placetype":"postalcode"
},
  "geometry": {"coordinates":[-1.55328941666945,54.93413302610571],"type":"Point"}
}