{
  "type": "Feature",
  "properties": {
    "iso:country":"GB",
    "wof:name":"EH22 4QB",
    "wof:placetype":"postalcode"
},
  "geometry": {"coordinates":[-3.05977955912475,55.86470676359411],"type":"Point"}
}