{
  "type": "Feature",
  "properties": {
    "date:inception_lower": "1980-01-01",
    "date:inception_upper": "1980-01-01",
    "iso:country": "GB",
    "wof:name": "EH22 4QB",
    "wof:placetype": "postalcode"
  },
  "geometry": {"coordinates":[-3.05978,55.864707],"type":"Point"}
}
