{
  "type": "Feature",
  "properties": {
    "iso:country":"GB",
    "wof:name":"N17 0PQ",
    "wof:placetype":"postalcode"
},
  "geometry": {"coordinates":[-0.06003867521496,51.60267995892045],"type":"Point"}
}