{
  "type": "Feature",
  "properties": {
    "iso:country": "GB",
    "wof:name": "N17 0PQ",
    "wof:placetype": "postalcode"
  },
  "geometry": {"coordinates":[-0.060039,51.60268],"type":"Point"}
}
