{
  "type": "Feature",
  "properties": {
    "date:inception_lower": "2018-07-01",
    "date:inception_upper": "2018-07-01",
    "iso:country": "GB",
    "wof:name": "AB15 8AW",
    "wof:placetype": "postalcode"
  },
  "geometry": {"coordinates":[-2.216951,57.147941],"type":"Point"}
}
