{
  "type": "Feature",
  "properties": {
    "date:inception_lower": "1998-12-01",
    "date:inception_upper": "1998-12-01",
    "iso:country": "GB",
    "wof:name": "CM3 6UD",
    "wof:placetype": "postalcode"
  },
  "geometry": {"coordinates":[0.710449,51.674605],"type":"Point"}
}
