{
  "type": "Feature",
  "properties": {
    "iso:country": "GB",
    "wof:name": "CM3 6UD",
    "wof:placetype": "postalcode"
  },
  "geometry": {"coordinates":[0.710449,51.674605],"type":"Point"}
}
