{
  "type": "Feature",
  "properties": {
    "iso:country":"GB",
    "wof:name":"CM3 6UD",
    "wof:placetype":"postalcode"
},
  "geometry": {"coordinates":[0.71044867371645,51.6746045075328],"type":"Point"}
}