{
  "type": "Feature",
  "properties": {
    "date:inception_lower":"1980-01-01",
    "date:inception_upper":"1980-01-31",
    "iso:country":"GB",
    "wof:name":"ML10 6QN",
    "wof:placetype":"postalcode"
},
  "geometry": {"coordinates":[-4.211911,55.637435],"type":"Point"}
}