{
  "type": "Feature",
  "properties": {
    "date:inception_lower":"1980-01-01",
    "date:inception_upper":"1980-01-31",
    "iso:country":"GB",
    "wof:name":"EH8 8DY",
    "wof:placetype":"postalcode"
},
  "geometry": {"coordinates":[-3.174682,55.953564],"type":"Point"}
}