{
  "type": "Feature",
  "properties": {
    "iso:country":"GB",
    "wof:name":"LU4 9QT",
    "wof:placetype":"postalcode"
},
  "geometry": {"coordinates":[-0.46310012873177,51.90206138755253],"type":"Point"}
}