{
  "type": "Feature",
  "properties": {
    "iso:country": "GB",
    "wof:name": "SE28 8DD",
    "wof:placetype": "postalcode"
  },
  "geometry": {"coordinates":[0.110432,51.502913],"type":"Point"}
}
