{
  "type": "Feature",
  "properties": {
    "iso:country":"GB",
    "wof:name":"KA6 6JH",
    "wof:placetype":"postalcode"
},
  "geometry": {"coordinates":[-4.51977104757144,55.44287154569759],"type":"Point"}
}