{
  "type": "Feature",
  "properties": {
    "date:inception_lower":"1981-06-01",
    "date:inception_upper":"1981-06-30",
    "iso:country":"GB",
    "wof:name":"WV6 7RZ",
    "wof:placetype":"postalcode"
},
  "geometry": {"coordinates":[-2.195872,52.591814],"type":"Point"}
}