{
  "type": "Feature",
  "properties": {
    "iso:country":"GB",
    "wof:name":"WV6 7RZ",
    "wof:placetype":"postalcode"
},
  "geometry": {"coordinates":[-2.19587214768853,52.59181366163801],"type":"Point"}
}