{
  "type": "Feature",
  "properties": {
    "iso:country": "GB",
    "wof:name": "WV6 7RZ",
    "wof:placetype": "postalcode"
  },
  "geometry": {"coordinates":[-2.195872,52.591814],"type":"Point"}
}
