{
  "type": "Feature",
  "properties": {
    "date:inception_lower": "1992-01-01",
    "date:inception_upper": "1992-01-01",
    "iso:country": "GB",
    "wof:name": "TF4 2NT",
    "wof:placetype": "postalcode"
  },
  "geometry": {"coordinates":[-2.467362,52.670244],"type":"Point"}
}
