{
  "type": "Feature",
  "properties": {
    "iso:country": "GB",
    "wof:name": "TF4 2NT",
    "wof:placetype": "postalcode"
  },
  "geometry": {"coordinates":[-2.467362,52.670244],"type":"Point"}
}
