{
  "type": "Feature",
  "properties": {
    "iso:country":"GB",
    "wof:name":"TF4 2NT",
    "wof:placetype":"postalcode"
},
  "geometry": {"coordinates":[-2.46736176268659,52.67024412585293],"type":"Point"}
}