{
  "type": "Feature",
  "properties": {
    "iso:country":"GB",
    "wof:name":"TA6 6RT",
    "wof:placetype":"postalcode"
},
  "geometry": {"coordinates":[-3.01613701555167,51.08917346421352],"type":"Point"}
}