{
  "type": "Feature",
  "properties": {
    "iso:country":"GB",
    "wof:name":"LS10 3PD",
    "wof:placetype":"postalcode"
},
  "geometry": {"coordinates":[-1.52737178379706,53.75439796959712],"type":"Point"}
}