{
  "type": "Feature",
  "properties": {
    "date:inception_lower":"1980-01-01",
    "date:inception_upper":"1980-01-31",
    "iso:country":"GB",
    "wof:name":"LS10 3PD",
    "wof:placetype":"postalcode"
},
  "geometry": {"coordinates":[-1.527372,53.754398],"type":"Point"}
}