{
  "type": "Feature",
  "properties": {
    "iso:country":"GB",
    "wof:name":"BD12 9BA",
    "wof:placetype":"postalcode"
},
  "geometry": {"coordinates":[-1.76465577673033,53.73636702895686],"type":"Point"}
}