{
  "type": "Feature",
  "properties": {
    "iso:country": "GB",
    "wof:name": "BD12 9BA",
    "wof:placetype": "postalcode"
  },
  "geometry": {"coordinates":[-1.764656,53.736367],"type":"Point"}
}
