{
  "type": "Feature",
  "properties": {
    "iso:country":"GB",
    "wof:name":"SW11 3HW",
    "wof:placetype":"postalcode"
},
  "geometry": {"coordinates":[-0.17232898340543,51.47089053805818],"type":"Point"}
}