{
  "type": "Feature",
  "properties": {
    "date:inception_lower":"1980-01-01",
    "date:inception_upper":"1980-01-31",
    "iso:country":"GB",
    "wof:name":"MK40 1JA",
    "wof:placetype":"postalcode"
},
  "geometry": {"coordinates":[-0.475128,52.13631],"type":"Point"}
}