{
  "type": "Feature",
  "properties": {
    "iso:country":"GB",
    "wof:name":"MK40 1JA",
    "wof:placetype":"postalcode"
},
  "geometry": {"coordinates":[-0.47512766405063,52.13630981141647],"type":"Point"}
}