{
  "type": "Feature",
  "properties": {
    "iso:country": "GB",
    "wof:name": "CA7 5BE",
    "wof:placetype": "postalcode"
  },
  "geometry": {"coordinates":[-3.219555,54.908861],"type":"Point"}
}
