{
  "type": "Feature",
  "properties": {
    "iso:country":"GB",
    "wof:name":"CA7 5BE",
    "wof:placetype":"postalcode"
},
  "geometry": {"coordinates":[-3.21955209517116,54.90885459659066],"type":"Point"}
}