{
  "type": "Feature",
  "properties": {
    "iso:country": "GB",
    "wof:name": "BS24 9BQ",
    "wof:placetype": "postalcode"
  },
  "geometry": {"coordinates":[-2.951979,51.32842],"type":"Point"}
}
