{
  "type": "Feature",
  "properties": {
    "date:inception_lower": "1993-08-01",
    "date:inception_upper": "1993-08-01",
    "iso:country": "GB",
    "wof:name": "BS24 9BQ",
    "wof:placetype": "postalcode"
  },
  "geometry": {"coordinates":[-2.951979,51.32842],"type":"Point"}
}
