{
  "type": "Feature",
  "properties": {
    "iso:country": "GB",
    "wof:name": "NR31 8LX",
    "wof:placetype": "postalcode"
  },
  "geometry": {"coordinates":[1.703839,52.5823],"type":"Point"}
}
