{
  "type": "Feature",
  "properties": {
    "iso:country": "GB",
    "wof:name": "TS16 0PY",
    "wof:placetype": "postalcode"
  },
  "geometry": {"coordinates":[-1.36173,54.542778],"type":"Point"}
}
