{
  "type": "Feature",
  "properties": {
    "date:inception_lower":"1980-01-01",
    "date:inception_upper":"1980-01-31",
    "iso:country":"GB",
    "wof:name":"TS16 0PY",
    "wof:placetype":"postalcode"
},
  "geometry": {"coordinates":[-1.36173,54.542778],"type":"Point"}
}