{
  "type": "Feature",
  "properties": {
    "iso:country":"GB",
    "wof:name":"TS16 0PY",
    "wof:placetype":"postalcode"
},
  "geometry": {"coordinates":[-1.36172973860732,54.54277825213571],"type":"Point"}
}