{
  "type": "Feature",
  "properties": {
    "iso:country":"GB",
    "wof:name":"IP21 5QE",
    "wof:placetype":"postalcode"
},
  "geometry": {"coordinates":[1.32982643271084,52.34720222682036],"type":"Point"}
}