{
  "type": "Feature",
  "properties": {
    "date:inception_lower": "2017-03-01",
    "date:inception_upper": "2017-03-01",
    "iso:country": "GB",
    "wof:name": "KY16 9HE",
    "wof:placetype": "postalcode"
  },
  "geometry": {"coordinates":[-2.790886,56.337562],"type":"Point"}
}
