{
  "type": "Feature",
  "properties": {
    "iso:country":"GB",
    "wof:name":"B73 6BP",
    "wof:placetype":"postalcode"
},
  "geometry": {"coordinates":[-1.82816013354572,52.56578131621905],"type":"Point"}
}