{
  "type": "Feature",
  "properties": {
    "date:inception_lower": "1980-01-01",
    "date:inception_upper": "1980-01-01",
    "iso:country": "GB",
    "wof:name": "NW6 4QZ",
    "wof:placetype": "postalcode"
  },
  "geometry": {"coordinates":[-0.192743,51.542724],"type":"Point"}
}
