{
  "type": "Feature",
  "properties": {
    "date:inception_lower": "2006-01-01",
    "date:inception_upper": "2006-01-01",
    "iso:country": "GB",
    "wof:name": "GL5 2AL",
    "wof:placetype": "postalcode"
  },
  "geometry": {"coordinates":[-2.214907,51.744646],"type":"Point"}
}
