{
  "type": "Feature",
  "properties": {
    "date:inception_lower": "1980-01-01",
    "date:inception_upper": "1980-01-01",
    "iso:country": "GB",
    "wof:name": "ME17 4BQ",
    "wof:placetype": "postalcode"
  },
  "geometry": {"coordinates":[0.497045,51.220374],"type":"Point"}
}
