{
  "type": "Feature",
  "properties": {
    "iso:country":"GB",
    "wof:name":"ME17 4BQ",
    "wof:placetype":"postalcode"
},
  "geometry": {"coordinates":[0.4970997664317,51.22035583188601],"type":"Point"}
}