{
  "type": "Feature",
  "properties": {
    "date:inception_lower": "1984-02-01",
    "date:inception_upper": "1984-02-01",
    "iso:country": "GB",
    "wof:name": "NE25 0NX",
    "wof:placetype": "postalcode"
  },
  "geometry": {"coordinates":[-1.518022,55.064245],"type":"Point"}
}
