{
  "type": "Feature",
  "properties": {
    "date:inception_lower":"1980-01-01",
    "date:inception_upper":"1980-01-31",
    "iso:country":"GB",
    "wof:name":"DT8 3EU",
    "wof:placetype":"postalcode"
},
  "geometry": {"coordinates":[-2.732723,50.809515],"type":"Point"}
}