{
  "type": "Feature",
  "properties": {
    "iso:country": "GB",
    "wof:name": "DT8 3EU",
    "wof:placetype": "postalcode"
  },
  "geometry": {"coordinates":[-2.732723,50.809515],"type":"Point"}
}
