{
  "type": "Feature",
  "properties": {
    "date:inception_lower": "1980-01-01",
    "date:inception_upper": "1980-01-01",
    "iso:country": "GB",
    "wof:name": "CA4 8DF",
    "wof:placetype": "postalcode"
  },
  "geometry": {"coordinates":[-2.871394,54.879065],"type":"Point"}
}
