{
  "type": "Feature",
  "properties": {
    "iso:country":"GB",
    "wof:name":"CA4 8DF",
    "wof:placetype":"postalcode"
},
  "geometry": {"coordinates":[-2.87115509292318,54.87900604014881],"type":"Point"}
}