{
  "type": "Feature",
  "properties": {
    "iso:country":"GB",
    "wof:name":"SO41 8NL",
    "wof:placetype":"postalcode"
},
  "geometry": {"coordinates":[-1.57015383156331,50.78110824479623],"type":"Point"}
}