{
  "type": "Feature",
  "properties": {
    "date:inception_lower": "1986-01-01",
    "date:inception_upper": "1986-01-01",
    "iso:country": "GB",
    "wof:name": "SO41 8NL",
    "wof:placetype": "postalcode"
  },
  "geometry": {"coordinates":[-1.570154,50.781108],"type":"Point"}
}
