{
  "type": "Feature",
  "properties": {
    "iso:country": "GB",
    "wof:name": "SO41 8NL",
    "wof:placetype": "postalcode"
  },
  "geometry": {"coordinates":[-1.570154,50.781108],"type":"Point"}
}
