{
  "type": "Feature",
  "properties": {
    "date:inception_lower": "2024-03-01",
    "date:inception_upper": "2024-03-01",
    "iso:country": "GB",
    "wof:name": "KT24 6FD",
    "wof:placetype": "postalcode"
  },
  "geometry": {"coordinates":[-0.452218,51.279783],"type":"Point"}
}
