{
  "type": "Feature",
  "properties": {
    "iso:country": "GB",
    "wof:name": "HP18 0UH",
    "wof:placetype": "postalcode"
  },
  "geometry": {"coordinates":[-1.007736,51.880003],"type":"Point"}
}
