{
  "type": "Feature",
  "properties": {
    "iso:country": "GB",
    "wof:name": "HP18 0UH",
    "wof:placetype": "postalcode"
  },
  "geometry": {"coordinates":[-1.00765,51.879966],"type":"Point"}
}
