{
  "type": "Feature",
  "properties": {
    "iso:country":"GB",
    "wof:name":"HP18 0UH",
    "wof:placetype":"postalcode"
},
  "geometry": {"coordinates":[-1.00775702352099,51.87999528409524],"type":"Point"}
}