{
  "type": "Feature",
  "properties": {
    "date:inception_lower": "2000-12-01",
    "date:inception_upper": "2000-12-01",
    "iso:country": "GB",
    "wof:name": "HP18 0UH",
    "wof:placetype": "postalcode"
  },
  "geometry": {"coordinates":[-1.00765,51.879966],"type":"Point"}
}
