{
  "type": "Feature",
  "properties": {
    "iso:country":"GB",
    "wof:name":"GL13 9EB",
    "wof:placetype":"postalcode"
},
  "geometry": {"coordinates":[-2.51198778657602,51.65376067365906],"type":"Point"}
}