{
  "type": "Feature",
  "properties": {
    "iso:country":"GB",
    "wof:name":"OX2 9HD",
    "wof:placetype":"postalcode"
},
  "geometry": {"coordinates":[-1.30351294822925,51.74715098489186],"type":"Point"}
}