{
  "type": "Feature",
  "properties": {
    "iso:country": "GB",
    "wof:name": "DL8 1AB",
    "wof:placetype": "postalcode"
  },
  "geometry": {"coordinates":[-1.593655,54.289633],"type":"Point"}
}
