{
  "type": "Feature",
  "properties": {
    "iso:country":"GB",
    "wof:name":"W4 3BT",
    "wof:placetype":"postalcode"
},
  "geometry": {"coordinates":[-0.2822563820016,51.48943121514573],"type":"Point"}
}