{
  "type": "Feature",
  "properties": {
    "date:inception_lower": "2002-08-01",
    "date:inception_upper": "2002-08-01",
    "iso:country": "GB",
    "wof:name": "WV8 2HF",
    "wof:placetype": "postalcode"
  },
  "geometry": {"coordinates":[-2.202193,52.614925],"type":"Point"}
}
