{
  "type": "Feature",
  "properties": {
    "iso:country": "GB",
    "wof:name": "WV8 2HF",
    "wof:placetype": "postalcode"
  },
  "geometry": {"coordinates":[-2.202193,52.614925],"type":"Point"}
}
