{
  "type": "Feature",
  "properties": {
    "iso:country":"GB",
    "wof:name":"E15 3HY",
    "wof:placetype":"postalcode"
},
  "geometry": {"coordinates":[0.0111791562166,51.53623980064904],"type":"Point"}
}