{
  "type": "Feature",
  "properties": {
    "date:inception_lower": "1996-12-01",
    "date:inception_upper": "1996-12-01",
    "iso:country": "GB",
    "wof:name": "E15 3HY",
    "wof:placetype": "postalcode"
  },
  "geometry": {"coordinates":[0.011179,51.53624],"type":"Point"}
}
