{
  "type": "Feature",
  "properties": {
    "iso:country":"GB",
    "wof:name":"IP12 2PR",
    "wof:placetype":"postalcode"
},
  "geometry": {"coordinates":[1.37145395821406,52.10099074362186],"type":"Point"}
}