{
  "type": "Feature",
  "properties": {
    "iso:country":"GB",
    "wof:name":"S80 4HG",
    "wof:placetype":"postalcode"
},
  "geometry": {"coordinates":[-1.21261661840566,53.26493091715025],"type":"Point"}
}