{
  "type": "Feature",
  "properties": {
    "iso:country":"GB",
    "wof:name":"KY11 8BL",
    "wof:placetype":"postalcode"
},
  "geometry": {"coordinates":[-3.42574630995227,56.05719695488878],"type":"Point"}
}