{
  "type": "Feature",
  "properties": {
    "date:inception_lower": "1980-01-01",
    "date:inception_upper": "1980-01-01",
    "iso:country": "GB",
    "wof:name": "LA5 9DY",
    "wof:placetype": "postalcode"
  },
  "geometry": {"coordinates":[-2.769751,54.125713],"type":"Point"}
}
