{
  "type": "Feature",
  "properties": {
    "date:inception_lower":"1993-01-01",
    "date:inception_upper":"1993-01-31",
    "iso:country":"GB",
    "wof:name":"ST9 0HD",
    "wof:placetype":"postalcode"
},
  "geometry": {"coordinates":[-2.092431,53.027821],"type":"Point"}
}