{
  "type": "Feature",
  "properties": {
    "iso:country":"GB",
    "wof:name":"ST9 0HD",
    "wof:placetype":"postalcode"
},
  "geometry": {"coordinates":[-2.09243064690827,53.02782059054472],"type":"Point"}
}