{
  "type": "Feature",
  "properties": {
    "iso:country":"GB",
    "wof:name":"RH5 4HB",
    "wof:placetype":"postalcode"
},
  "geometry": {"coordinates":[-0.32400357403113,51.20672529746987],"type":"Point"}
}