{
  "type": "Feature",
  "properties": {
    "iso:country":"GB",
    "wof:name":"WV2 2LA",
    "wof:placetype":"postalcode"
},
  "geometry": {"coordinates":[-2.10161229000067,52.56957459389704],"type":"Point"}
}