{
  "type": "Feature",
  "properties": {
    "iso:country":"GB",
    "wof:name":"S63 8DW",
    "wof:placetype":"postalcode"
},
  "geometry": {"coordinates":[-1.32672018484337,53.51885154093266],"type":"Point"}
}