{
  "type": "Feature",
  "properties": {
    "date:inception_lower": "1980-01-01",
    "date:inception_upper": "1980-01-01",
    "iso:country": "GB",
    "wof:name": "DD5 4QT",
    "wof:placetype": "postalcode"
  },
  "geometry": {"coordinates":[-2.839323,56.477795],"type":"Point"}
}
