{
  "type": "Feature",
  "properties": {
    "iso:country":"GB",
    "wof:name":"DD5 4QT",
    "wof:placetype":"postalcode"
},
  "geometry": {"coordinates":[-2.83953250586973,56.4778934769146],"type":"Point"}
}