{
  "type": "Feature",
  "properties": {
    "iso:country":"GB",
    "wof:name":"SR1 3JU",
    "wof:placetype":"postalcode"
},
  "geometry": {"coordinates":[-1.38593332312384,54.90462862893436],"type":"Point"}
}