{
  "type": "Feature",
  "properties": {
    "iso:country":"GB",
    "wof:name":"SM6 9LP",
    "wof:placetype":"postalcode"
},
  "geometry": {"coordinates":[-0.14014743580696,51.351132961373],"type":"Point"}
}