{
  "type": "Feature",
  "properties": {
    "iso:country":"GB",
    "wof:name":"LL11 4FD",
    "wof:placetype":"postalcode"
},
  "geometry": {"coordinates":[-3.01542306274122,53.06867433353554],"type":"Point"}
}