{
  "type": "Feature",
  "properties": {
    "date:inception_lower": "2007-10-01",
    "date:inception_upper": "2007-10-01",
    "iso:country": "GB",
    "wof:name": "LL11 4FD",
    "wof:placetype": "postalcode"
  },
  "geometry": {"coordinates":[-3.015423,53.068674],"type":"Point"}
}
