{
  "type": "Feature",
  "properties": {
    "iso:country":"GB",
    "wof:name":"BD21 2LL",
    "wof:placetype":"postalcode"
},
  "geometry": {"coordinates":[-1.9120251187571,53.86586617790581],"type":"Point"}
}