{
  "type": "Feature",
  "properties": {
    "date:inception_lower":"1980-01-01",
    "date:inception_upper":"1980-01-31",
    "iso:country":"GB",
    "wof:name":"BD21 2LL",
    "wof:placetype":"postalcode"
},
  "geometry": {"coordinates":[-1.912025,53.865866],"type":"Point"}
}