{
  "type": "Feature",
  "properties": {
    "iso:country": "GB",
    "wof:name": "SG12 9FF",
    "wof:placetype": "postalcode"
  },
  "geometry": {"coordinates":[-0.02425,51.808404],"type":"Point"}
}
