{
  "type": "Feature",
  "properties": {
    "date:inception_lower":"2000-12-01",
    "date:inception_upper":"2000-12-31",
    "iso:country":"GB",
    "wof:name":"SG12 9FF",
    "wof:placetype":"postalcode"
},
  "geometry": {"coordinates":[-0.02425,51.808404],"type":"Point"}
}