{
  "type": "Feature",
  "properties": {
    "iso:country":"GB",
    "wof:name":"CH1 3BT",
    "wof:placetype":"postalcode"
},
  "geometry": {"coordinates":[-2.87941839601248,53.19398907430076],"type":"Point"}
}