{
  "type": "Feature",
  "properties": {
    "iso:country":"GB",
    "wof:name":"WF12 7QB",
    "wof:placetype":"postalcode"
},
  "geometry": {"coordinates":[-1.61577952523917,53.69738748572063],"type":"Point"}
}