{
  "type": "Feature",
  "properties": {
    "iso:country": "GB",
    "wof:name": "WF12 7QB",
    "wof:placetype": "postalcode"
  },
  "geometry": {"coordinates":[-1.615779,53.697387],"type":"Point"}
}
