{
  "type": "Feature",
  "properties": {
    "iso:country": "GB",
    "wof:name": "EH12 8XY",
    "wof:placetype": "postalcode"
  },
  "geometry": {"coordinates":[-3.307044,55.955699],"type":"Point"}
}
