{
  "type": "Feature",
  "properties": {
    "iso:country": "GB",
    "wof:name": "PO6 1NX",
    "wof:placetype": "postalcode"
  },
  "geometry": {"coordinates":[-1.038258,50.846606],"type":"Point"}
}
