{
  "type": "Feature",
  "properties": {
    "iso:country":"GB",
    "wof:name":"SL6 3UP",
    "wof:placetype":"postalcode"
},
  "geometry": {"coordinates":[-0.75531101528622,51.50630363512981],"type":"Point"}
}