{
  "type": "Feature",
  "properties": {
    "date:inception_lower": "1983-03-01",
    "date:inception_upper": "1983-03-01",
    "iso:country": "GB",
    "wof:name": "SL6 3UP",
    "wof:placetype": "postalcode"
  },
  "geometry": {"coordinates":[-0.755311,51.506304],"type":"Point"}
}
