{
  "type": "Feature",
  "properties": {
    "iso:country": "GB",
    "wof:name": "SL6 3UP",
    "wof:placetype": "postalcode"
  },
  "geometry": {"coordinates":[-0.755311,51.506304],"type":"Point"}
}
