{
  "type": "Feature",
  "properties": {
    "iso:country": "GB",
    "wof:name": "FK7 9AX",
    "wof:placetype": "postalcode"
  },
  "geometry": {"coordinates":[-3.962792,56.072938],"type":"Point"}
}
