{
  "type": "Feature",
  "properties": {
    "iso:country":"GB",
    "wof:name":"FK7 9AX",
    "wof:placetype":"postalcode"
},
  "geometry": {"coordinates":[-3.96313670895388,56.07292951376964],"type":"Point"}
}