{
  "type": "Feature",
  "properties": {
    "date:inception_lower":"2000-12-01",
    "date:inception_upper":"2000-12-31",
    "iso:country":"GB",
    "wof:name":"FK7 9AX",
    "wof:placetype":"postalcode"
},
  "geometry": {"coordinates":[-3.962792,56.072938],"type":"Point"}
}