{
  "type": "Feature",
  "properties": {
    "iso:country":"GB",
    "wof:name":"PR4 2YP",
    "wof:placetype":"postalcode"
},
  "geometry": {"coordinates":[-2.86589695125107,53.78108773691191],"type":"Point"}
}