{
  "type": "Feature",
  "properties": {
    "iso:country":"GB",
    "wof:name":"TA19 0LE",
    "wof:placetype":"postalcode"
},
  "geometry": {"coordinates":[-2.85122177931141,50.94918413489935],"type":"Point"}
}