{
  "type": "Feature",
  "properties": {
    "iso:country":"GB",
    "wof:name":"LU2 9NU",
    "wof:placetype":"postalcode"
},
  "geometry": {"coordinates":[-0.38480468373143,51.87872242419697],"type":"Point"}
}