{
  "type": "Feature",
  "properties": {
    "iso:country": "GB",
    "wof:name": "LU2 9NU",
    "wof:placetype": "postalcode"
  },
  "geometry": {"coordinates":[-0.384805,51.878722],"type":"Point"}
}
