{
  "type": "Feature",
  "properties": {
    "iso:country": "GB",
    "wof:name": "LU2 9NU",
    "wof:placetype": "postalcode"
  },
  "geometry": {"coordinates":[-0.38478,51.87873],"type":"Point"}
}
