{
  "type": "Feature",
  "properties": {
    "date:inception_lower": "2019-11-01",
    "date:inception_upper": "2019-11-01",
    "iso:country": "GB",
    "wof:name": "LU2 9NU",
    "wof:placetype": "postalcode"
  },
  "geometry": {"coordinates":[-0.38478,51.87873],"type":"Point"}
}
