{
  "type": "Feature",
  "properties": {
    "iso:country":"GB",
    "wof:name":"G67 3DP",
    "wof:placetype":"postalcode"
},
  "geometry": {"coordinates":[-3.95830566095224,55.95893909331698],"type":"Point"}
}