{
  "type": "Feature",
  "properties": {
    "iso:country":"GB",
    "wof:name":"RM15 6PT",
    "wof:placetype":"postalcode"
},
  "geometry": {"coordinates":[0.297144001879,51.52486353389476],"type":"Point"}
}