{
  "type": "Feature",
  "properties": {
    "date:inception_lower": "1980-01-01",
    "date:inception_upper": "1980-01-01",
    "iso:country": "GB",
    "wof:name": "RM15 6PT",
    "wof:placetype": "postalcode"
  },
  "geometry": {"coordinates":[0.297205,51.524936],"type":"Point"}
}
