{
  "type": "Feature",
  "properties": {
    "iso:country":"GB",
    "wof:name":"PO6 3SP",
    "wof:placetype":"postalcode"
},
  "geometry": {"coordinates":[-1.08406973022404,50.85012141978368],"type":"Point"}
}