{
  "type": "Feature",
  "properties": {
    "date:inception_lower": "1980-01-01",
    "date:inception_upper": "1980-01-01",
    "iso:country": "GB",
    "wof:name": "PO6 3SP",
    "wof:placetype": "postalcode"
  },
  "geometry": {"coordinates":[-1.08407,50.850121],"type":"Point"}
}
