{
  "type": "Feature",
  "properties": {
    "date:inception_lower": "2022-10-01",
    "date:inception_upper": "2022-10-01",
    "iso:country": "GB",
    "wof:name": "NG2 1AY",
    "wof:placetype": "postalcode"
  },
  "geometry": {"coordinates":[-1.159632,52.94209],"type":"Point"}
}
