{
  "type": "Feature",
  "properties": {
    "iso:country":"GB",
    "wof:name":"WF12 0EN",
    "wof:placetype":"postalcode"
},
  "geometry": {"coordinates":[-1.62647930546617,53.66064162191247],"type":"Point"}
}