{
  "type": "Feature",
  "properties": {
    "iso:country":"GB",
    "wof:name":"HS2 0HY",
    "wof:placetype":"postalcode"
},
  "geometry": {"coordinates":[-6.35005696205102,58.24144683153911],"type":"Point"}
}