{
  "type": "Feature",
  "properties": {
    "date:inception_lower": "1980-01-01",
    "date:inception_upper": "1980-01-01",
    "iso:country": "GB",
    "wof:name": "WR3 7YB",
    "wof:placetype": "postalcode"
  },
  "geometry": {"coordinates":[-2.231085,52.224973],"type":"Point"}
}
