{
  "type": "Feature",
  "properties": {
    "iso:country":"GB",
    "wof:name":"UB4 8PE",
    "wof:placetype":"postalcode"
},
  "geometry": {"coordinates":[-0.43400430701816,51.53607602245807],"type":"Point"}
}