{
  "type": "Feature",
  "properties": {
    "iso:country": "GB",
    "wof:name": "YO8 5BA",
    "wof:placetype": "postalcode"
  },
  "geometry": {"coordinates":[-1.044616,53.7902],"type":"Point"}
}
