{
  "type": "Feature",
  "properties": {
    "iso:country":"GB",
    "wof:name":"YO8 5BA",
    "wof:placetype":"postalcode"
},
  "geometry": {"coordinates":[-1.04461599936424,53.79020039485346],"type":"Point"}
}