{
  "type": "Feature",
  "properties": {
    "date:inception_lower": "1980-01-01",
    "date:inception_upper": "1980-01-01",
    "iso:country": "GB",
    "wof:name": "WF14 8LN",
    "wof:placetype": "postalcode"
  },
  "geometry": {"coordinates":[-1.692577,53.673233],"type":"Point"}
}
