{
  "type": "Feature",
  "properties": {
    "iso:country":"GB",
    "wof:name":"WF14 8LN",
    "wof:placetype":"postalcode"
},
  "geometry": {"coordinates":[-1.69233467210919,53.67326843838239],"type":"Point"}
}