{
  "type": "Feature",
  "properties": {
    "date:inception_lower": "1980-01-01",
    "date:inception_upper": "1980-01-01",
    "iso:country": "GB",
    "wof:name": "SK4 4HF",
    "wof:placetype": "postalcode"
  },
  "geometry": {"coordinates":[-2.181722,53.418903],"type":"Point"}
}
