{
  "type": "Feature",
  "properties": {
    "iso:country":"GB",
    "wof:name":"SK4 4HF",
    "wof:placetype":"postalcode"
},
  "geometry": {"coordinates":[-2.18172187045183,53.41890272980871],"type":"Point"}
}