{
  "type": "Feature",
  "properties": {
    "date:inception_lower": "2020-10-01",
    "date:inception_upper": "2020-10-01",
    "iso:country": "GB",
    "wof:name": "HD8 9UZ",
    "wof:placetype": "postalcode"
  },
  "geometry": {"coordinates":[-1.619332,53.596001],"type":"Point"}
}
