{
  "type": "Feature",
  "properties": {
    "iso:country": "GB",
    "wof:name": "CH60 3RY",
    "wof:placetype": "postalcode"
  },
  "geometry": {"coordinates":[-3.084604,53.322037],"type":"Point"}
}
