{
  "type": "Feature",
  "properties": {
    "iso:country":"GB",
    "wof:name":"RH5 4DU",
    "wof:placetype":"postalcode"
},
  "geometry": {"coordinates":[-0.30484320432107,51.20649424944556],"type":"Point"}
}