{
  "type": "Feature",
  "properties": {
    "iso:country": "GB",
    "wof:name": "RH5 4DU",
    "wof:placetype": "postalcode"
  },
  "geometry": {"coordinates":[-0.304843,51.206494],"type":"Point"}
}
