{
  "type": "Feature",
  "properties": {
    "iso:country":"GB",
    "wof:name":"LS15 7HU",
    "wof:placetype":"postalcode"
},
  "geometry": {"coordinates":[-1.47210208625023,53.79705866466627],"type":"Point"}
}