{
  "type": "Feature",
  "properties": {
    "iso:country": "GB",
    "wof:name": "LS15 7HU",
    "wof:placetype": "postalcode"
  },
  "geometry": {"coordinates":[-1.472102,53.797059],"type":"Point"}
}
