{
  "type": "Feature",
  "properties": {
    "iso:country":"GB",
    "wof:name":"TW18 2RW",
    "wof:placetype":"postalcode"
},
  "geometry": {"coordinates":[-0.49993582451292,51.42297956690935],"type":"Point"}
}