{
  "type": "Feature",
  "properties": {
    "iso:country":"GB",
    "wof:name":"TW11 9DE",
    "wof:placetype":"postalcode"
},
  "geometry": {"coordinates":[-0.32070982136864,51.42055788779193],"type":"Point"}
}