{
  "type": "Feature",
  "properties": {
    "iso:country":"GB",
    "wof:name":"BA6 9AB",
    "wof:placetype":"postalcode"
},
  "geometry": {"coordinates":[-2.69811407156641,51.16794823390154],"type":"Point"}
}