{
  "type": "Feature",
  "properties": {
    "date:inception_lower": "1980-01-01",
    "date:inception_upper": "1980-01-01",
    "iso:country": "GB",
    "wof:name": "W3 8SA",
    "wof:placetype": "postalcode"
  },
  "geometry": {"coordinates":[-0.2738,51.507391],"type":"Point"}
}
