{
  "type": "Feature",
  "properties": {
    "iso:country":"GB",
    "wof:name":"W3 8SA",
    "wof:placetype":"postalcode"
},
  "geometry": {"coordinates":[-0.27379968673427,51.50739071832436],"type":"Point"}
}