{
  "type": "Feature",
  "properties": {
    "date:inception_lower": "2017-07-01",
    "date:inception_upper": "2017-07-01",
    "iso:country": "GB",
    "wof:name": "GU52 8BJ",
    "wof:placetype": "postalcode"
  },
  "geometry": {"coordinates":[-0.829591,51.256494],"type":"Point"}
}
