{
  "type": "Feature",
  "properties": {
    "iso:country":"GB",
    "wof:name":"B30 2AX",
    "wof:placetype":"postalcode"
},
  "geometry": {"coordinates":[-1.93058960244845,52.43390428201904],"type":"Point"}
}