{
  "type": "Feature",
  "properties": {
    "iso:country":"GB",
    "wof:name":"BD3 0HX",
    "wof:placetype":"postalcode"
},
  "geometry": {"coordinates":[-1.74312023829109,53.80251067119079],"type":"Point"}
}