{
  "type": "Feature",
  "properties": {
    "date:inception_lower": "1999-06-01",
    "date:inception_upper": "1999-06-01",
    "iso:country": "GB",
    "wof:name": "IP24 1RZ",
    "wof:placetype": "postalcode"
  },
  "geometry": {"coordinates":[0.879974,52.469133],"type":"Point"}
}
