{
  "type": "Feature",
  "properties": {
    "iso:country":"GB",
    "wof:name":"IP24 1RZ",
    "wof:placetype":"postalcode"
},
  "geometry": {"coordinates":[0.87997435854367,52.46913289592836],"type":"Point"}
}