{
  "type": "Feature",
  "properties": {
    "iso:country": "GB",
    "wof:name": "IP24 1RZ",
    "wof:placetype": "postalcode"
  },
  "geometry": {"coordinates":[0.879974,52.469133],"type":"Point"}
}
