{
  "type": "Feature",
  "properties": {
    "iso:country":"GB",
    "wof:name":"LA4 5PZ",
    "wof:placetype":"postalcode"
},
  "geometry": {"coordinates":[-2.85860812854326,54.07388156537923],"type":"Point"}
}