{
  "type": "Feature",
  "properties": {
    "iso:country": "GB",
    "wof:name": "EN6 2AD",
    "wof:placetype": "postalcode"
  },
  "geometry": {"coordinates":[-0.196116,51.699404],"type":"Point"}
}
