{
  "type": "Feature",
  "properties": {
    "iso:country":"GB",
    "wof:name":"BN5 9NA",
    "wof:placetype":"postalcode"
},
  "geometry": {"coordinates":[-0.22983178662533,50.88867490094447],"type":"Point"}
}