{
  "type": "Feature",
  "properties": {
    "iso:country": "GB",
    "wof:name": "BN5 9NA",
    "wof:placetype": "postalcode"
  },
  "geometry": {"coordinates":[-0.229832,50.888675],"type":"Point"}
}
