{
  "type": "Feature",
  "properties": {
    "date:inception_lower":"1980-01-01",
    "date:inception_upper":"1980-01-31",
    "iso:country":"GB",
    "wof:name":"BN5 9NA",
    "wof:placetype":"postalcode"
},
  "geometry": {"coordinates":[-0.229832,50.888675],"type":"Point"}
}