{
  "type": "Feature",
  "properties": {
    "date:inception_lower": "1980-01-01",
    "date:inception_upper": "1980-01-01",
    "iso:country": "GB",
    "wof:name": "TW20 0QR",
    "wof:placetype": "postalcode"
  },
  "geometry": {"coordinates":[-0.568138,51.429822],"type":"Point"}
}
