{
  "type": "Feature",
  "properties": {
    "iso:country":"GB",
    "wof:name":"WN2 1AN",
    "wof:placetype":"postalcode"
},
  "geometry": {"coordinates":[-2.60715597346203,53.55451860289949],"type":"Point"}
}