{
  "type": "Feature",
  "properties": {
    "date:inception_lower": "1999-06-01",
    "date:inception_upper": "1999-06-01",
    "iso:country": "GB",
    "wof:name": "NP11 6PD",
    "wof:placetype": "postalcode"
  },
  "geometry": {"coordinates":[-3.080157,51.606065],"type":"Point"}
}
