{
  "type": "Feature",
  "properties": {
    "iso:country":"GB",
    "wof:name":"LS2 9AU",
    "wof:placetype":"postalcode"
},
  "geometry": {"coordinates":[-1.54981367366838,53.8086913103061],"type":"Point"}
}