{
  "type": "Feature",
  "properties": {
    "iso:country":"GB",
    "wof:name":"OX16 1AF",
    "wof:placetype":"postalcode"
},
  "geometry": {"coordinates":[-1.36340322446062,52.07763853884908],"type":"Point"}
}