{
  "type": "Feature",
  "properties": {
    "iso:country":"GB",
    "wof:name":"RG6 5TL",
    "wof:placetype":"postalcode"
},
  "geometry": {"coordinates":[-0.94278379048882,51.43341157322243],"type":"Point"}
}