{
  "type": "Feature",
  "properties": {
    "iso:country":"GB",
    "wof:name":"S40 2HG",
    "wof:placetype":"postalcode"
},
  "geometry": {"coordinates":[-1.43674535307989,53.21894504029521],"type":"Point"}
}