{
  "type": "Feature",
  "properties": {
    "iso:country":"GB",
    "wof:name":"M25 1PF",
    "wof:placetype":"postalcode"
},
  "geometry": {"coordinates":[-2.2714387122819,53.53366791134975],"type":"Point"}
}