{
  "type": "Feature",
  "properties": {
    "iso:country":"GB",
    "wof:name":"ML5 1AB",
    "wof:placetype":"postalcode"
},
  "geometry": {"coordinates":[-4.04558919679085,55.8578914654147],"type":"Point"}
}