{
  "type": "Feature",
  "properties": {
    "iso:country": "GB",
    "wof:name": "ML5 1AB",
    "wof:placetype": "postalcode"
  },
  "geometry": {"coordinates":[-4.045589,55.857891],"type":"Point"}
}
