{
  "type": "Feature",
  "properties": {
    "iso:country":"GB",
    "wof:name":"BA22 9QX",
    "wof:placetype":"postalcode"
},
  "geometry": {"coordinates":[-2.68949975467412,50.86595543547557],"type":"Point"}
}