{
  "type": "Feature",
  "properties": {
    "date:inception_lower":"1980-01-01",
    "date:inception_upper":"1980-01-31",
    "iso:country":"GB",
    "wof:name":"BA22 9QX",
    "wof:placetype":"postalcode"
},
  "geometry": {"coordinates":[-2.689672,50.866062],"type":"Point"}
}