{
  "type": "Feature",
  "properties": {
    "iso:country":"GB",
    "wof:name":"TN4 8XU",
    "wof:placetype":"postalcode"
},
  "geometry": {"coordinates":[0.24431836920722,51.13708198385001],"type":"Point"}
}