{
  "type": "Feature",
  "properties": {
    "iso:country":"GB",
    "wof:name":"LN4 4HZ",
    "wof:placetype":"postalcode"
},
  "geometry": {"coordinates":[-0.27536599935495,53.0791142566873],"type":"Point"}
}