{
  "type": "Feature",
  "properties": {
    "iso:country":"GB",
    "wof:name":"CR0 5PT",
    "wof:placetype":"postalcode"
},
  "geometry": {"coordinates":[-0.08232754330433,51.37112682550027],"type":"Point"}
}