{
  "type": "Feature",
  "properties": {
    "iso:country": "GB",
    "wof:name": "RM6 4AF",
    "wof:placetype": "postalcode"
  },
  "geometry": {"coordinates":[0.124916,51.57356],"type":"Point"}
}
