{
  "type": "Feature",
  "properties": {
    "date:inception_lower": "1980-01-01",
    "date:inception_upper": "1980-01-01",
    "iso:country": "GB",
    "wof:name": "RM6 4AF",
    "wof:placetype": "postalcode"
  },
  "geometry": {"coordinates":[0.124916,51.57356],"type":"Point"}
}
