{
  "type": "Feature",
  "properties": {
    "iso:country":"GB",
    "wof:name":"RM6 4AF",
    "wof:placetype":"postalcode"
},
  "geometry": {"coordinates":[0.1249158088137,51.57355996347081],"type":"Point"}
}