{
  "type": "Feature",
  "properties": {
    "iso:country":"GB",
    "wof:name":"DH8 0AA",
    "wof:placetype":"postalcode"
},
  "geometry": {"coordinates":[-1.84709738851638,54.86113319924579],"type":"Point"}
}