{
  "type": "Feature",
  "properties": {
    "iso:country": "GB",
    "wof:name": "NP23 4LQ",
    "wof:placetype": "postalcode"
  },
  "geometry": {"coordinates":[-3.163693,51.780306],"type":"Point"}
}
