{
  "type": "Feature",
  "properties": {
    "date:inception_lower": "1999-06-01",
    "date:inception_upper": "1999-06-01",
    "iso:country": "GB",
    "wof:name": "NP23 4LQ",
    "wof:placetype": "postalcode"
  },
  "geometry": {"coordinates":[-3.163701,51.780309],"type":"Point"}
}
