{
  "type": "Feature",
  "properties": {
    "date:inception_lower": "1980-01-01",
    "date:inception_upper": "1980-01-01",
    "iso:country": "GB",
    "wof:name": "S10 1DB",
    "wof:placetype": "postalcode"
  },
  "geometry": {"coordinates":[-1.498252,53.380434],"type":"Point"}
}
