{
  "type": "Feature",
  "properties": {
    "date:inception_lower":"1984-02-01",
    "date:inception_upper":"1984-02-29",
    "iso:country":"GB",
    "wof:name":"PE30 1AX",
    "wof:placetype":"postalcode"
},
  "geometry": {"coordinates":[0.395819,52.756433],"type":"Point"}
}