{
  "type": "Feature",
  "properties": {
    "iso:country": "GB",
    "wof:name": "PE30 1AX",
    "wof:placetype": "postalcode"
  },
  "geometry": {"coordinates":[0.395819,52.756433],"type":"Point"}
}
