{
  "type": "Feature",
  "properties": {
    "iso:country":"GB",
    "wof:name":"PE30 1AX",
    "wof:placetype":"postalcode"
},
  "geometry": {"coordinates":[0.39581881175467,52.75643253582457],"type":"Point"}
}