{
  "type": "Feature",
  "properties": {
    "iso:country":"GB",
    "wof:name":"B75 5TL",
    "wof:placetype":"postalcode"
},
  "geometry": {"coordinates":[-1.82572500878683,52.58464740128206],"type":"Point"}
}