{
  "type": "Feature",
  "properties": {
    "iso:country":"GB",
    "wof:name":"TR16 6NP",
    "wof:placetype":"postalcode"
},
  "geometry": {"coordinates":[-5.21891366225939,50.18199759012008],"type":"Point"}
}