{
  "type": "Feature",
  "properties": {
    "iso:country":"GB",
    "wof:name":"LE7 9XA",
    "wof:placetype":"postalcode"
},
  "geometry": {"coordinates":[-0.84508711426582,52.59552649050477],"type":"Point"}
}