{
  "type": "Feature",
  "properties": {
    "iso:country": "GB",
    "wof:name": "LE7 9XA",
    "wof:placetype": "postalcode"
  },
  "geometry": {"coordinates":[-0.845087,52.595526],"type":"Point"}
}
