{
  "type": "Feature",
  "properties": {
    "date:inception_lower": "2021-06-01",
    "date:inception_upper": "2021-06-01",
    "iso:country": "GB",
    "wof:name": "BS35 1BZ",
    "wof:placetype": "postalcode"
  },
  "geometry": {"coordinates":[-2.513943,51.620872],"type":"Point"}
}
