{
  "type": "Feature",
  "properties": {
    "date:inception_lower":"1980-01-01",
    "date:inception_upper":"1980-01-31",
    "iso:country":"GB",
    "wof:name":"PE15 8NE",
    "wof:placetype":"postalcode"
},
  "geometry": {"coordinates":[0.086748,52.559081],"type":"Point"}
}