{
  "type": "Feature",
  "properties": {
    "iso:country":"GB",
    "wof:name":"PR4 3BZ",
    "wof:placetype":"postalcode"
},
  "geometry": {"coordinates":[-2.93836546861521,53.80497260204171],"type":"Point"}
}