{
  "type": "Feature",
  "properties": {
    "date:inception_lower":"2010-10-01",
    "date:inception_upper":"2010-10-31",
    "iso:country":"GB",
    "wof:name":"PR4 3BZ",
    "wof:placetype":"postalcode"
},
  "geometry": {"coordinates":[-2.938365,53.804973],"type":"Point"}
}