{
  "type": "Feature",
  "properties": {
    "date:inception_lower": "2022-06-01",
    "date:inception_upper": "2022-06-01",
    "iso:country": "GB",
    "wof:name": "CM6 2FY",
    "wof:placetype": "postalcode"
  },
  "geometry": {"coordinates":[0.351643,51.885774],"type":"Point"}
}
