{
  "type": "Feature",
  "properties": {
    "iso:country":"GB",
    "wof:name":"TA18 7RH",
    "wof:placetype":"postalcode"
},
  "geometry": {"coordinates":[-2.75096532286852,50.89555726690735],"type":"Point"}
}