{
  "type": "Feature",
  "properties": {
    "date:inception_lower": "1980-01-01",
    "date:inception_upper": "1980-01-01",
    "iso:country": "GB",
    "wof:name": "DN11 9NJ",
    "wof:placetype": "postalcode"
  },
  "geometry": {"coordinates":[-1.119129,53.429314],"type":"Point"}
}
