{
  "type": "Feature",
  "properties": {
    "iso:country":"GB",
    "wof:name":"B8 2AP",
    "wof:placetype":"postalcode"
},
  "geometry": {"coordinates":[-1.81681882578475,52.49040204069778],"type":"Point"}
}