{
  "type": "Feature",
  "properties": {
    "date:inception_lower":"2018-07-01",
    "date:inception_upper":"2018-07-31",
    "iso:country":"GB",
    "wof:name":"PE7 3HH",
    "wof:placetype":"postalcode"
},
  "geometry": {"coordinates":[-0.301245,52.53236],"type":"Point"}
}