{
  "type": "Feature",
  "properties": {
    "iso:country":"GB",
    "wof:name":"WR9 0NA",
    "wof:placetype":"postalcode"
},
  "geometry": {"coordinates":[-2.15846287050387,52.30432405551905],"type":"Point"}
}