{
  "type": "Feature",
  "properties": {
    "iso:country": "GB",
    "wof:name": "G69 8DY",
    "wof:placetype": "postalcode"
  },
  "geometry": {"coordinates":[-4.079785,55.892592],"type":"Point"}
}
