{
  "type": "Feature",
  "properties": {
    "iso:country":"GB",
    "wof:name":"G69 8DY",
    "wof:placetype":"postalcode"
},
  "geometry": {"coordinates":[-4.07978505556847,55.8925922596574],"type":"Point"}
}