{
  "type": "Feature",
  "properties": {
    "iso:country":"GB",
    "wof:name":"SW11 5NG",
    "wof:placetype":"postalcode"
},
  "geometry": {"coordinates":[-0.16115157290894,51.46633640335654],"type":"Point"}
}