{
  "type": "Feature",
  "properties": {
    "iso:country": "GB",
    "wof:name": "PL9 7FF",
    "wof:placetype": "postalcode"
  },
  "geometry": {"coordinates":[-4.099914,50.367918],"type":"Point"}
}
