{
  "type": "Feature",
  "properties": {
    "iso:country":"GB",
    "wof:name":"KT22 8AZ",
    "wof:placetype":"postalcode"
},
  "geometry": {"coordinates":[-0.32512663014874,51.29450091252981],"type":"Point"}
}