{
  "type": "Feature",
  "properties": {
    "iso:country": "GB",
    "wof:name": "NG16 4GS",
    "wof:placetype": "postalcode"
  },
  "geometry": {"coordinates":[-1.338942,53.02159],"type":"Point"}
}
