{
  "type": "Feature",
  "properties": {
    "iso:country":"GB",
    "wof:name":"EN7 5SS",
    "wof:placetype":"postalcode"
},
  "geometry": {"coordinates":[-0.08803103257148,51.7107240088562],"type":"Point"}
}