{
  "type": "Feature",
  "properties": {
    "iso:country":"GB",
    "wof:name":"TN15 8LR",
    "wof:placetype":"postalcode"
},
  "geometry": {"coordinates":[0.32007896053705,51.29078574624133],"type":"Point"}
}