{
  "type": "Feature",
  "properties": {
    "date:inception_lower":"2002-06-01",
    "date:inception_upper":"2002-06-30",
    "iso:country":"GB",
    "wof:name":"TN15 8LR",
    "wof:placetype":"postalcode"
},
  "geometry": {"coordinates":[0.320079,51.290786],"type":"Point"}
}