{
  "type": "Feature",
  "properties": {
    "iso:country": "GB",
    "wof:name": "SN3 3JN",
    "wof:placetype": "postalcode"
  },
  "geometry": {"coordinates":[-1.756051,51.568263],"type":"Point"}
}
