{
  "type": "Feature",
  "properties": {
    "iso:country":"GB",
    "wof:name":"SW3 4JU",
    "wof:placetype":"postalcode"
},
  "geometry": {"coordinates":[-0.16232566987738,51.48692073358205],"type":"Point"}
}