{
  "type": "Feature",
  "properties": {
    "date:inception_lower":"2005-01-01",
    "date:inception_upper":"2005-01-31",
    "iso:country":"GB",
    "wof:name":"DN16 3FR",
    "wof:placetype":"postalcode"
},
  "geometry": {"coordinates":[-0.625289,53.55806],"type":"Point"}
}