{
  "type": "Feature",
  "properties": {
    "iso:country": "GB",
    "wof:name": "DN16 3FR",
    "wof:placetype": "postalcode"
  },
  "geometry": {"coordinates":[-0.625289,53.55806],"type":"Point"}
}
