{
  "type": "Feature",
  "properties": {
    "iso:country":"GB",
    "wof:name":"DN16 3FR",
    "wof:placetype":"postalcode"
},
  "geometry": {"coordinates":[-0.62528907505929,53.55806020756545],"type":"Point"}
}