{
  "type": "Feature",
  "properties": {
    "date:inception_lower":"1980-01-01",
    "date:inception_upper":"1980-01-31",
    "iso:country":"GB",
    "wof:name":"TQ8 8EX",
    "wof:placetype":"postalcode"
},
  "geometry": {"coordinates":[-3.768584,50.237364],"type":"Point"}
}