{
  "type": "Feature",
  "properties": {
    "iso:country":"GB",
    "wof:name":"TQ8 8EX",
    "wof:placetype":"postalcode"
},
  "geometry": {"coordinates":[-3.76858365746217,50.23736431102908],"type":"Point"}
}