{
  "type": "Feature",
  "properties": {
    "iso:country": "GB",
    "wof:name": "TQ8 8EX",
    "wof:placetype": "postalcode"
  },
  "geometry": {"coordinates":[-3.768584,50.237364],"type":"Point"}
}
