{
  "type": "Feature",
  "properties": {
    "iso:country":"GB",
    "wof:name":"TN6 3LG",
    "wof:placetype":"postalcode"
},
  "geometry": {"coordinates":[0.21846340400577,51.04648014741359],"type":"Point"}
}