{
  "type": "Feature",
  "properties": {
    "iso:country": "GB",
    "wof:name": "NW8 7AH",
    "wof:placetype": "postalcode"
  },
  "geometry": {"coordinates":[-0.168845,51.532446],"type":"Point"}
}
