{
  "type": "Feature",
  "properties": {
    "iso:country":"GB",
    "wof:name":"NW8 7AH",
    "wof:placetype":"postalcode"
},
  "geometry": {"coordinates":[-0.16886985177166,51.53244411848496],"type":"Point"}
}