{
  "type": "Feature",
  "properties": {
    "iso:country":"GB",
    "wof:name":"SK6 1NB",
    "wof:placetype":"postalcode"
},
  "geometry": {"coordinates":[-2.09829205542875,53.42656006115746],"type":"Point"}
}