{
  "type": "Feature",
  "properties": {
    "date:inception_lower":"2002-07-01",
    "date:inception_upper":"2002-07-31",
    "iso:country":"GB",
    "wof:name":"MK45 3FB",
    "wof:placetype":"postalcode"
},
  "geometry": {"coordinates":[-0.451563,52.075896],"type":"Point"}
}