{
  "type": "Feature",
  "properties": {
    "iso:country": "GB",
    "wof:name": "MK45 3FB",
    "wof:placetype": "postalcode"
  },
  "geometry": {"coordinates":[-0.451563,52.075896],"type":"Point"}
}
