{
  "type": "Feature",
  "properties": {
    "iso:country":"GB",
    "wof:name":"NG6 9DD",
    "wof:placetype":"postalcode"
},
  "geometry": {"coordinates":[-1.18670110023646,52.99138579053083],"type":"Point"}
}