{
  "type": "Feature",
  "properties": {
    "iso:country": "GB",
    "wof:name": "EX11 1AZ",
    "wof:placetype": "postalcode"
  },
  "geometry": {"coordinates":[-3.277671,50.749258],"type":"Point"}
}
