{
  "type": "Feature",
  "properties": {
    "iso:country":"GB",
    "wof:name":"EX11 1AZ",
    "wof:placetype":"postalcode"
},
  "geometry": {"coordinates":[-3.27765943434595,50.74926845554008],"type":"Point"}
}