{
  "type": "Feature",
  "properties": {
    "iso:country":"GB",
    "wof:name":"PA34 4QY",
    "wof:placetype":"postalcode"
},
  "geometry": {"coordinates":[-5.57385590910996,56.29909074026642],"type":"Point"}
}