{
  "type": "Feature",
  "properties": {
    "iso:country":"GB",
    "wof:name":"E17 4BZ",
    "wof:placetype":"postalcode"
},
  "geometry": {"coordinates":[0.00134706411537,51.59772851707736],"type":"Point"}
}