{
  "type": "Feature",
  "properties": {
    "date:inception_lower":"1980-01-01",
    "date:inception_upper":"1980-01-31",
    "iso:country":"GB",
    "wof:name":"WA11 0SL",
    "wof:placetype":"postalcode"
},
  "geometry": {"coordinates":[-2.674273,53.466599],"type":"Point"}
}