{
  "type": "Feature",
  "properties": {
    "iso:country": "GB",
    "wof:name": "EX5 3LD",
    "wof:placetype": "postalcode"
  },
  "geometry": {"coordinates":[-3.452169,50.793594],"type":"Point"}
}
