{
  "type": "Feature",
  "properties": {
    "date:inception_lower":"2016-09-01",
    "date:inception_upper":"2016-09-30",
    "iso:country":"GB",
    "wof:name":"WA5 7YU",
    "wof:placetype":"postalcode"
},
  "geometry": {"coordinates":[-2.629645,53.413046],"type":"Point"}
}