{
  "type": "Feature",
  "properties": {
    "iso:country": "GB",
    "wof:name": "DY11 7JF",
    "wof:placetype": "postalcode"
  },
  "geometry": {"coordinates":[-2.266929,52.3728],"type":"Point"}
}
