{
  "type": "Feature",
  "properties": {
    "iso:country":"GB",
    "wof:name":"DY11 7JF",
    "wof:placetype":"postalcode"
},
  "geometry": {"coordinates":[-2.26712408991733,52.37286712567457],"type":"Point"}
}