{
  "type": "Feature",
  "properties": {
    "iso:country":"GB",
    "wof:name":"KA6 5BH",
    "wof:placetype":"postalcode"
},
  "geometry": {"coordinates":[-4.53063239863701,55.48974750507104],"type":"Point"}
}