{
  "type": "Feature",
  "properties": {
    "date:inception_lower": "1995-12-01",
    "date:inception_upper": "1995-12-01",
    "iso:country": "GB",
    "wof:name": "SY16 4DH",
    "wof:placetype": "postalcode"
  },
  "geometry": {"coordinates":[-3.260997,52.502098],"type":"Point"}
}
