{
  "type": "Feature",
  "properties": {
    "iso:country":"GB",
    "wof:name":"S61 4NZ",
    "wof:placetype":"postalcode"
},
  "geometry": {"coordinates":[-1.36259134171299,53.44805617986569],"type":"Point"}
}