{
  "type": "Feature",
  "properties": {
    "iso:country":"GB",
    "wof:name":"E16 1AR",
    "wof:placetype":"postalcode"
},
  "geometry": {"coordinates":[0.02150217816344,51.50756452445383],"type":"Point"}
}