{
  "type": "Feature",
  "properties": {
    "iso:country": "GB",
    "wof:name": "IV26 2XP",
    "wof:placetype": "postalcode"
  },
  "geometry": {"coordinates":[-5.157022,57.900786],"type":"Point"}
}
