{
  "type": "Feature",
  "properties": {
    "date:inception_lower": "1992-10-01",
    "date:inception_upper": "1992-10-01",
    "iso:country": "GB",
    "wof:name": "IV26 2XP",
    "wof:placetype": "postalcode"
  },
  "geometry": {"coordinates":[-5.157022,57.900786],"type":"Point"}
}
