{
  "type": "Feature",
  "properties": {
    "iso:country":"GB",
    "wof:name":"YO25 9RJ",
    "wof:placetype":"postalcode"
},
  "geometry": {"coordinates":[-0.43028160347142,53.95459323589155],"type":"Point"}
}