{
  "type": "Feature",
  "properties": {
    "date:inception_lower":"1990-02-01",
    "date:inception_upper":"1990-02-28",
    "iso:country":"GB",
    "wof:name":"YO25 9RJ",
    "wof:placetype":"postalcode"
},
  "geometry": {"coordinates":[-0.430282,53.954593],"type":"Point"}
}