{
  "type": "Feature",
  "properties": {
    "date:inception_lower":"1998-06-01",
    "date:inception_upper":"1998-06-30",
    "iso:country":"GB",
    "wof:name":"YO10 4PW",
    "wof:placetype":"postalcode"
},
  "geometry": {"coordinates":[-1.070223,53.933602],"type":"Point"}
}