{
  "type": "Feature",
  "properties": {
    "iso:country":"GB",
    "wof:name":"EX32 0PG",
    "wof:placetype":"postalcode"
},
  "geometry": {"coordinates":[-3.97068196934664,51.05308925972814],"type":"Point"}
}