{
  "type": "Feature",
  "properties": {
    "date:inception_lower": "1980-01-01",
    "date:inception_upper": "1980-01-01",
    "iso:country": "GB",
    "wof:name": "SE25 6RE",
    "wof:placetype": "postalcode"
  },
  "geometry": {"coordinates":[-0.091689,51.39788],"type":"Point"}
}
