{
  "type": "Feature",
  "properties": {
    "iso:country":"GB",
    "wof:name":"SE25 6RE",
    "wof:placetype":"postalcode"
},
  "geometry": {"coordinates":[-0.09168880990864,51.39788021352277],"type":"Point"}
}