{
  "type": "Feature",
  "properties": {
    "iso:country": "GB",
    "wof:name": "IV49 9BU",
    "wof:placetype": "postalcode"
  },
  "geometry": {"coordinates":[-5.899062,57.238215],"type":"Point"}
}
