{
  "type": "Feature",
  "properties": {
    "date:inception_lower":"1996-12-01",
    "date:inception_upper":"1996-12-31",
    "iso:country":"GB",
    "wof:name":"IV49 9BU",
    "wof:placetype":"postalcode"
},
  "geometry": {"coordinates":[-5.899062,57.238215],"type":"Point"}
}