{
  "type": "Feature",
  "properties": {
    "date:inception_lower": "1980-01-01",
    "date:inception_upper": "1980-01-01",
    "iso:country": "GB",
    "wof:name": "EX1 1QT",
    "wof:placetype": "postalcode"
  },
  "geometry": {"coordinates":[-3.525186,50.723423],"type":"Point"}
}
