{
  "type": "Feature",
  "properties": {
    "iso:country":"GB",
    "wof:name":"EX1 1QT",
    "wof:placetype":"postalcode"
},
  "geometry": {"coordinates":[-3.52518588590062,50.72342295067333],"type":"Point"}
}