{
  "type": "Feature",
  "properties": {
    "iso:country": "GB",
    "wof:name": "SL6 9BT",
    "wof:placetype": "postalcode"
  },
  "geometry": {"coordinates":[-0.720886,51.557808],"type":"Point"}
}
