{
  "type": "Feature",
  "properties": {
    "iso:country":"GB",
    "wof:name":"SL6 9BT",
    "wof:placetype":"postalcode"
},
  "geometry": {"coordinates":[-0.72088645885553,51.55780771545029],"type":"Point"}
}