{
  "type": "Feature",
  "properties": {
    "iso:country":"GB",
    "wof:name":"TD5 7DS",
    "wof:placetype":"postalcode"
},
  "geometry": {"coordinates":[-2.43668769042343,55.60041435478557],"type":"Point"}
}