{
  "type": "Feature",
  "properties": {
    "iso:country":"GB",
    "wof:name":"PA4 8AT",
    "wof:placetype":"postalcode"
},
  "geometry": {"coordinates":[-4.41135575123395,55.86458466550994],"type":"Point"}
}