{
  "type": "Feature",
  "properties": {
    "iso:country":"GB",
    "wof:name":"ML7 5QX",
    "wof:placetype":"postalcode"
},
  "geometry": {"coordinates":[-3.74320785540643,55.86190961007333],"type":"Point"}
}