{
  "type": "Feature",
  "properties": {
    "iso:country":"GB",
    "wof:name":"SW4 6DN",
    "wof:placetype":"postalcode"
},
  "geometry": {"coordinates":[-0.13456656272031,51.46546680172072],"type":"Point"}
}