{
  "type": "Feature",
  "properties": {
    "iso:country": "GB",
    "wof:name": "FK15 0DZ",
    "wof:placetype": "postalcode"
  },
  "geometry": {"coordinates":[-3.948424,56.1904],"type":"Point"}
}
