{
  "type": "Feature",
  "properties": {
    "iso:country":"GB",
    "wof:name":"TW9 1XW",
    "wof:placetype":"postalcode"
},
  "geometry": {"coordinates":[-0.29074516400304,51.46349529070515],"type":"Point"}
}