{
  "type": "Feature",
  "properties": {
    "iso:country":"GB",
    "wof:name":"E14 0RT",
    "wof:placetype":"postalcode"
},
  "geometry": {"coordinates":[-0.01261946748398,51.51589939576171],"type":"Point"}
}