{
  "type": "Feature",
  "properties": {
    "iso:country":"GB",
    "wof:name":"SO19 9PQ",
    "wof:placetype":"postalcode"
},
  "geometry": {"coordinates":[-1.36649379726013,50.88937762085482],"type":"Point"}
}