{
  "type": "Feature",
  "properties": {
    "iso:country":"GB",
    "wof:name":"CA11 0JJ",
    "wof:placetype":"postalcode"
},
  "geometry": {"coordinates":[-2.86557616027594,54.58771783016408],"type":"Point"}
}