{
  "type": "Feature",
  "properties": {
    "iso:country": "GB",
    "wof:name": "DN7 5EB",
    "wof:placetype": "postalcode"
  },
  "geometry": {"coordinates":[-1.024134,53.598482],"type":"Point"}
}
