{
  "type": "Feature",
  "properties": {
    "iso:country":"GB",
    "wof:name":"DN7 5EB",
    "wof:placetype":"postalcode"
},
  "geometry": {"coordinates":[-1.02413425292384,53.59848158359013],"type":"Point"}
}