{
  "type": "Feature",
  "properties": {
    "iso:country":"GB",
    "wof:name":"PR25 4SZ",
    "wof:placetype":"postalcode"
},
  "geometry": {"coordinates":[-2.68107134748275,53.69885164123796],"type":"Point"}
}