{
  "type": "Feature",
  "properties": {
    "date:inception_lower": "2001-06-01",
    "date:inception_upper": "2001-06-01",
    "iso:country": "GB",
    "wof:name": "PR25 4SZ",
    "wof:placetype": "postalcode"
  },
  "geometry": {"coordinates":[-2.681071,53.698852],"type":"Point"}
}
