{
  "type": "Feature",
  "properties": {
    "date:inception_lower": "2021-12-01",
    "date:inception_upper": "2021-12-01",
    "iso:country": "GB",
    "wof:name": "WS7 0AP",
    "wof:placetype": "postalcode"
  },
  "geometry": {"coordinates":[-1.916152,52.675469],"type":"Point"}
}
