{
  "type": "Feature",
  "properties": {
    "iso:country":"GB",
    "wof:name":"M28 2PU",
    "wof:placetype":"postalcode"
},
  "geometry": {"coordinates":[-2.38146173446621,53.49759332951059],"type":"Point"}
}