{
  "type": "Feature",
  "properties": {
    "iso:country":"GB",
    "wof:name":"SS16 5JT",
    "wof:placetype":"postalcode"
},
  "geometry": {"coordinates":[0.4621949656902,51.55358425601606],"type":"Point"}
}