{
  "type": "Feature",
  "properties": {
    "date:inception_lower":"1980-01-01",
    "date:inception_upper":"1980-01-31",
    "iso:country":"GB",
    "wof:name":"DT9 4SN",
    "wof:placetype":"postalcode"
},
  "geometry": {"coordinates":[-2.581493,50.965463],"type":"Point"}
}