{
  "type": "Feature",
  "properties": {
    "iso:country":"GB",
    "wof:name":"DT9 4SN",
    "wof:placetype":"postalcode"
},
  "geometry": {"coordinates":[-2.58147835453075,50.96548786901796],"type":"Point"}
}