{
  "type": "Feature",
  "properties": {
    "iso:country": "GB",
    "wof:name": "DN33 1BS",
    "wof:placetype": "postalcode"
  },
  "geometry": {"coordinates":[-0.093986,53.54819],"type":"Point"}
}
