{
  "type": "Feature",
  "properties": {
    "iso:country":"GB",
    "wof:name":"HD5 8JW",
    "wof:placetype":"postalcode"
},
  "geometry": {"coordinates":[-1.76570941448156,53.63668156791116],"type":"Point"}
}