{
  "type": "Feature",
  "properties": {
    "iso:country":"GB",
    "wof:name":"BL5 3LG",
    "wof:placetype":"postalcode"
},
  "geometry": {"coordinates":[-2.5271487734157,53.56259224281679],"type":"Point"}
}