{
  "type": "Feature",
  "properties": {
    "iso:country":"GB",
    "wof:name":"LA3 3FA",
    "wof:placetype":"postalcode"
},
  "geometry": {"coordinates":[-2.84946667079847,54.05730096698434],"type":"Point"}
}