{
  "type": "Feature",
  "properties": {
    "date:inception_lower": "2015-04-01",
    "date:inception_upper": "2015-04-01",
    "iso:country": "GB",
    "wof:name": "LA3 3FA",
    "wof:placetype": "postalcode"
  },
  "geometry": {"coordinates":[-2.849467,54.057301],"type":"Point"}
}
