{
  "type": "Feature",
  "properties": {
    "iso:country": "GB",
    "wof:name": "ST6 1DP",
    "wof:placetype": "postalcode"
  },
  "geometry": {"coordinates":[-2.195587,53.04623],"type":"Point"}
}
