{
  "type": "Feature",
  "properties": {
    "date:inception_lower": "1991-01-01",
    "date:inception_upper": "1991-01-01",
    "iso:country": "GB",
    "wof:name": "CW8 3JF",
    "wof:placetype": "postalcode"
  },
  "geometry": {"coordinates":[-2.584638,53.263029],"type":"Point"}
}
