{
  "type": "Feature",
  "properties": {
    "iso:country": "GB",
    "wof:name": "CW8 3JF",
    "wof:placetype": "postalcode"
  },
  "geometry": {"coordinates":[-2.584638,53.263029],"type":"Point"}
}
