{
  "type": "Feature",
  "properties": {
    "date:inception_lower":"1980-01-01",
    "date:inception_upper":"1980-01-31",
    "iso:country":"GB",
    "wof:name":"LL42 1PF",
    "wof:placetype":"postalcode"
},
  "geometry": {"coordinates":[-4.057637,52.724552],"type":"Point"}
}