{
  "type": "Feature",
  "properties": {
    "iso:country":"GB",
    "wof:name":"LL42 1PF",
    "wof:placetype":"postalcode"
},
  "geometry": {"coordinates":[-4.05763654784194,52.72455220088292],"type":"Point"}
}