{
  "type": "Feature",
  "properties": {
    "iso:country": "GB",
    "wof:name": "LL42 1PF",
    "wof:placetype": "postalcode"
  },
  "geometry": {"coordinates":[-4.057637,52.724552],"type":"Point"}
}
