{
  "type": "Feature",
  "properties": {
    "date:inception_lower": "1980-01-01",
    "date:inception_upper": "1980-01-01",
    "iso:country": "GB",
    "wof:name": "B98 0PE",
    "wof:placetype": "postalcode"
  },
  "geometry": {"coordinates":[-1.8914,52.303905],"type":"Point"}
}
