{
  "type": "Feature",
  "properties": {
    "iso:country":"GB",
    "wof:name":"B98 0PE",
    "wof:placetype":"postalcode"
},
  "geometry": {"coordinates":[-1.89140043043014,52.30390453847542],"type":"Point"}
}