{
  "type": "Feature",
  "properties": {
    "date:inception_lower": "2002-12-01",
    "date:inception_upper": "2002-12-01",
    "iso:country": "GB",
    "wof:name": "PA77 6UD",
    "wof:placetype": "postalcode"
  },
  "geometry": {"coordinates":[-6.898272,56.447145],"type":"Point"}
}
