{
  "type": "Feature",
  "properties": {
    "iso:country":"GB",
    "wof:name":"LU6 3LS",
    "wof:placetype":"postalcode"
},
  "geometry": {"coordinates":[-0.51112195541377,51.87447208850954],"type":"Point"}
}