{
  "type": "Feature",
  "properties": {
    "iso:country": "GB",
    "wof:name": "LU6 3LS",
    "wof:placetype": "postalcode"
  },
  "geometry": {"coordinates":[-0.511122,51.874472],"type":"Point"}
}
