{
  "type": "Feature",
  "properties": {
    "date:inception_lower": "1980-01-01",
    "date:inception_upper": "1980-01-01",
    "iso:country": "GB",
    "wof:name": "LU6 3LS",
    "wof:placetype": "postalcode"
  },
  "geometry": {"coordinates":[-0.511122,51.874472],"type":"Point"}
}
