{
  "type": "Feature",
  "properties": {
    "iso:country":"GB",
    "wof:name":"NE26 3TX",
    "wof:placetype":"postalcode"
},
  "geometry": {"coordinates":[-1.46184392771376,55.05603036958416],"type":"Point"}
}