{
  "type": "Feature",
  "properties": {
    "iso:country":"GB",
    "wof:name":"NP25 5LD",
    "wof:placetype":"postalcode"
},
  "geometry": {"coordinates":[-2.71414793881088,51.83139708913434],"type":"Point"}
}