{
  "type": "Feature",
  "properties": {
    "iso:country":"GB",
    "wof:name":"WF17 5PG",
    "wof:placetype":"postalcode"
},
  "geometry": {"coordinates":[-1.62788257541425,53.71094384703912],"type":"Point"}
}