{
  "type": "Feature",
  "properties": {
    "date:inception_lower":"1980-01-01",
    "date:inception_upper":"1980-01-31",
    "iso:country":"GB",
    "wof:name":"WF17 5PG",
    "wof:placetype":"postalcode"
},
  "geometry": {"coordinates":[-1.627883,53.710944],"type":"Point"}
}