{
  "type": "Feature",
  "properties": {
    "iso:country": "GB",
    "wof:name": "ST9 9QP",
    "wof:placetype": "postalcode"
  },
  "geometry": {"coordinates":[-2.074164,53.104852],"type":"Point"}
}
