{
  "type": "Feature",
  "properties": {
    "iso:country":"GB",
    "wof:name":"ST9 9QP",
    "wof:placetype":"postalcode"
},
  "geometry": {"coordinates":[-2.07416440459769,53.10485173552233],"type":"Point"}
}