{
  "type": "Feature",
  "properties": {
    "iso:country":"GB",
    "wof:name":"NN16 8QB",
    "wof:placetype":"postalcode"
},
  "geometry": {"coordinates":[-0.72548413653991,52.40456444921536],"type":"Point"}
}