{
  "type": "Feature",
  "properties": {
    "date:inception_lower": "1980-01-01",
    "date:inception_upper": "1980-01-01",
    "iso:country": "GB",
    "wof:name": "CR4 1QN",
    "wof:placetype": "postalcode"
  },
  "geometry": {"coordinates":[-0.130216,51.39575],"type":"Point"}
}
