{
  "type": "Feature",
  "properties": {
    "iso:country": "GB",
    "wof:name": "CR4 1QN",
    "wof:placetype": "postalcode"
  },
  "geometry": {"coordinates":[-0.130216,51.39575],"type":"Point"}
}
