{
  "type": "Feature",
  "properties": {
    "iso:country":"GB",
    "wof:name":"L12 7NA",
    "wof:placetype":"postalcode"
},
  "geometry": {"coordinates":[-2.9124499509501,53.43026858816296],"type":"Point"}
}