{
  "type": "Feature",
  "properties": {
    "date:inception_lower":"2000-12-01",
    "date:inception_upper":"2000-12-31",
    "iso:country":"GB",
    "wof:name":"L12 7NA",
    "wof:placetype":"postalcode"
},
  "geometry": {"coordinates":[-2.91245,53.430269],"type":"Point"}
}