{
  "type": "Feature",
  "properties": {
    "date:inception_lower": "2013-03-01",
    "date:inception_upper": "2013-03-01",
    "iso:country": "GB",
    "wof:name": "PE7 0LU",
    "wof:placetype": "postalcode"
  },
  "geometry": {"coordinates":[-0.248081,52.549422],"type":"Point"}
}
