{
  "type": "Feature",
  "properties": {
    "iso:country":"GB",
    "wof:name":"PE7 0LU",
    "wof:placetype":"postalcode"
},
  "geometry": {"coordinates":[-0.248080913773,52.54942246286254],"type":"Point"}
}