{
  "type": "Feature",
  "properties": {
    "iso:country":"GB",
    "wof:name":"LA3 1RY",
    "wof:placetype":"postalcode"
},
  "geometry": {"coordinates":[-2.88236967776698,54.06364315433654],"type":"Point"}
}