{
  "type": "Feature",
  "properties": {
    "date:inception_lower": "2023-03-01",
    "date:inception_upper": "2023-03-01",
    "iso:country": "GB",
    "wof:name": "SA19 6BJ",
    "wof:placetype": "postalcode"
  },
  "geometry": {"coordinates":[-3.995465,51.883659],"type":"Point"}
}
