{
  "type": "Feature",
  "properties": {
    "iso:country":"GB",
    "wof:name":"L2 4SX",
    "wof:placetype":"postalcode"
},
  "geometry": {"coordinates":[-2.99076596554129,53.40656092200429],"type":"Point"}
}