{
  "type": "Feature",
  "properties": {
    "date:inception_lower": "1986-01-01",
    "date:inception_upper": "1986-01-01",
    "iso:country": "GB",
    "wof:name": "SO41 8HF",
    "wof:placetype": "postalcode"
  },
  "geometry": {"coordinates":[-1.562835,50.755209],"type":"Point"}
}
