{
  "type": "Feature",
  "properties": {
    "iso:country": "GB",
    "wof:name": "SO41 8HF",
    "wof:placetype": "postalcode"
  },
  "geometry": {"coordinates":[-1.562835,50.755209],"type":"Point"}
}
