{
  "type": "Feature",
  "properties": {
    "iso:country":"GB",
    "wof:name":"BN20 0DA",
    "wof:placetype":"postalcode"
},
  "geometry": {"coordinates":[0.20567932971179,50.75908421597509],"type":"Point"}
}