{
  "type": "Feature",
  "properties": {
    "date:inception_lower":"1980-01-01",
    "date:inception_upper":"1980-01-31",
    "iso:country":"GB",
    "wof:name":"BN13 2JG",
    "wof:placetype":"postalcode"
},
  "geometry": {"coordinates":[-0.404375,50.835731],"type":"Point"}
}