{
  "type": "Feature",
  "properties": {
    "iso:country":"GB",
    "wof:name":"W1U 7JL",
    "wof:placetype":"postalcode"
},
  "geometry": {"coordinates":[-0.1546975969851,51.51780710320784],"type":"Point"}
}