{
  "type": "Feature",
  "properties": {
    "iso:country":"GB",
    "wof:name":"M20 4AR",
    "wof:placetype":"postalcode"
},
  "geometry": {"coordinates":[-2.22343757704561,53.43169448225335],"type":"Point"}
}