{
  "type": "Feature",
  "properties": {
    "iso:country":"GB",
    "wof:name":"NN18 9NH",
    "wof:placetype":"postalcode"
},
  "geometry": {"coordinates":[-0.69271089139949,52.48532891361246],"type":"Point"}
}