{
  "type": "Feature",
  "properties": {
    "iso:country":"GB",
    "wof:name":"PO40 9RA",
    "wof:placetype":"postalcode"
},
  "geometry": {"coordinates":[-1.51184834540645,50.67004359187346],"type":"Point"}
}