{
  "type": "Feature",
  "properties": {
    "date:inception_lower":"1980-01-01",
    "date:inception_upper":"1980-01-31",
    "iso:country":"GB",
    "wof:name":"GL54 3JU",
    "wof:placetype":"postalcode"
},
  "geometry": {"coordinates":[-1.875665,51.79823],"type":"Point"}
}