{
  "type": "Feature",
  "properties": {
    "iso:country":"GB",
    "wof:name":"GL54 3JU",
    "wof:placetype":"postalcode"
},
  "geometry": {"coordinates":[-1.8756648240308,51.79822958501996],"type":"Point"}
}