{
  "type": "Feature",
  "properties": {
    "iso:country": "GB",
    "wof:name": "GL54 3JU",
    "wof:placetype": "postalcode"
  },
  "geometry": {"coordinates":[-1.875665,51.79823],"type":"Point"}
}
