{
  "type": "Feature",
  "properties": {
    "iso:country": "GB",
    "wof:name": "TW7 4AN",
    "wof:placetype": "postalcode"
  },
  "geometry": {"coordinates":[-0.348485,51.475536],"type":"Point"}
}
