{
  "type": "Feature",
  "properties": {
    "iso:country": "GB",
    "wof:name": "FY8 5RS",
    "wof:placetype": "postalcode"
  },
  "geometry": {"coordinates":[-2.962542,53.736092],"type":"Point"}
}
