{
  "type": "Feature",
  "properties": {
    "date:inception_lower": "1992-01-01",
    "date:inception_upper": "1992-01-01",
    "iso:country": "GB",
    "wof:name": "FY8 5RS",
    "wof:placetype": "postalcode"
  },
  "geometry": {"coordinates":[-2.962542,53.736092],"type":"Point"}
}
