{
  "type": "Feature",
  "properties": {
    "iso:country":"GB",
    "wof:name":"FY8 5RS",
    "wof:placetype":"postalcode"
},
  "geometry": {"coordinates":[-2.96254159691852,53.73609177049554],"type":"Point"}
}