{
  "type": "Feature",
  "properties": {
    "iso:country":"GB",
    "wof:name":"EN2 7BL",
    "wof:placetype":"postalcode"
},
  "geometry": {"coordinates":[-0.09596421339048,51.65173729293739],"type":"Point"}
}