{
  "type": "Feature",
  "properties": {
    "iso:country":"GB",
    "wof:name":"RH2 0EP",
    "wof:placetype":"postalcode"
},
  "geometry": {"coordinates":[-0.19441983069455,51.24505837110428],"type":"Point"}
}