{
  "type": "Feature",
  "properties": {
    "iso:country":"GB",
    "wof:name":"PA15 1EL",
    "wof:placetype":"postalcode"
},
  "geometry": {"coordinates":[-4.75088928691658,55.94580887877218],"type":"Point"}
}