{
  "type": "Feature",
  "properties": {
    "date:inception_lower": "2000-12-01",
    "date:inception_upper": "2000-12-01",
    "iso:country": "GB",
    "wof:name": "HP2 7BL",
    "wof:placetype": "postalcode"
  },
  "geometry": {"coordinates":[-0.436601,51.763535],"type":"Point"}
}
