{
  "type": "Feature",
  "properties": {
    "iso:country":"GB",
    "wof:name":"HP2 7BL",
    "wof:placetype":"postalcode"
},
  "geometry": {"coordinates":[-0.43663350225288,51.76367161455295],"type":"Point"}
}