{
  "type": "Feature",
  "properties": {
    "iso:country":"GB",
    "wof:name":"CH43 5SX",
    "wof:placetype":"postalcode"
},
  "geometry": {"coordinates":[-3.04485057943629,53.37856650152348],"type":"Point"}
}