{
  "type": "Feature",
  "properties": {
    "iso:country": "GB",
    "wof:name": "CB22 7PT",
    "wof:placetype": "postalcode"
  },
  "geometry": {"coordinates":[0.083234,52.137487],"type":"Point"}
}
