{
  "type": "Feature",
  "properties": {
    "iso:country":"GB",
    "wof:name":"BL3 4DD",
    "wof:placetype":"postalcode"
},
  "geometry": {"coordinates":[-2.45283867737279,53.56823589902675],"type":"Point"}
}