{
  "type": "Feature",
  "properties": {
    "date:inception_lower": "2022-04-01",
    "date:inception_upper": "2022-04-01",
    "iso:country": "GB",
    "wof:name": "WR9 7UH",
    "wof:placetype": "postalcode"
  },
  "geometry": {"coordinates":[-2.173893,52.25407],"type":"Point"}
}
