{
  "type": "Feature",
  "properties": {
    "date:inception_lower": "2011-10-01",
    "date:inception_upper": "2011-10-01",
    "iso:country": "GB",
    "wof:name": "YO11 3AT",
    "wof:placetype": "postalcode"
  },
  "geometry": {"coordinates":[-0.363936,54.222865],"type":"Point"}
}
