{
  "type": "Feature",
  "properties": {
    "iso:country": "GB",
    "wof:name": "OX17 3RW",
    "wof:placetype": "postalcode"
  },
  "geometry": {"coordinates":[-1.277125,52.022227],"type":"Point"}
}
