{
  "type": "Feature",
  "properties": {
    "iso:country":"GB",
    "wof:name":"OX17 3RW",
    "wof:placetype":"postalcode"
},
  "geometry": {"coordinates":[-1.27714212628131,52.02221656459744],"type":"Point"}
}