{
  "type": "Feature",
  "properties": {
    "date:inception_lower": "1980-01-01",
    "date:inception_upper": "1980-01-01",
    "iso:country": "GB",
    "wof:name": "WA6 6XU",
    "wof:placetype": "postalcode"
  },
  "geometry": {"coordinates":[-2.746608,53.285295],"type":"Point"}
}
