{
  "type": "Feature",
  "properties": {
    "date:inception_lower":"2014-02-01",
    "date:inception_upper":"2014-02-28",
    "iso:country":"GB",
    "wof:name":"S44 6JY",
    "wof:placetype":"postalcode"
},
  "geometry": {"coordinates":[-1.292161,53.245339],"type":"Point"}
}