{
  "type": "Feature",
  "properties": {
    "iso:country":"GB",
    "wof:name":"S44 6JY",
    "wof:placetype":"postalcode"
},
  "geometry": {"coordinates":[-1.29216132021815,53.24533912989831],"type":"Point"}
}