{
  "type": "Feature",
  "properties": {
    "date:inception_lower": "2014-02-01",
    "date:inception_upper": "2014-02-01",
    "iso:country": "GB",
    "wof:name": "S44 6JY",
    "wof:placetype": "postalcode"
  },
  "geometry": {"coordinates":[-1.29216,53.245358],"type":"Point"}
}
