{
  "type": "Feature",
  "properties": {
    "iso:country": "GB",
    "wof:name": "DN11 9DU",
    "wof:placetype": "postalcode"
  },
  "geometry": {"coordinates":[-1.151043,53.474437],"type":"Point"}
}
