{
  "type": "Feature",
  "properties": {
    "iso:country":"GB",
    "wof:name":"DN11 9DU",
    "wof:placetype":"postalcode"
},
  "geometry": {"coordinates":[-1.15133908478147,53.47380789125766],"type":"Point"}
}