{
  "type": "Feature",
  "properties": {
    "iso:country": "GB",
    "wof:name": "CF83 8FR",
    "wof:placetype": "postalcode"
  },
  "geometry": {"coordinates":[-3.184182,51.594298],"type":"Point"}
}
