{
  "type": "Feature",
  "properties": {
    "iso:country":"GB",
    "wof:name":"CF83 8FR",
    "wof:placetype":"postalcode"
},
  "geometry": {"coordinates":[-3.18418215058831,51.59429815402753],"type":"Point"}
}