{
  "type": "Feature",
  "properties": {
    "iso:country": "GB",
    "wof:name": "RH11 8XT",
    "wof:placetype": "postalcode"
  },
  "geometry": {"coordinates":[-0.223311,51.104195],"type":"Point"}
}
