{
  "type": "Feature",
  "properties": {
    "iso:country":"GB",
    "wof:name":"RH11 8XT",
    "wof:placetype":"postalcode"
},
  "geometry": {"coordinates":[-0.22331152782615,51.10419528533274],"type":"Point"}
}