{
  "type": "Feature",
  "properties": {
    "iso:country":"GB",
    "wof:name":"OL12 7QW",
    "wof:placetype":"postalcode"
},
  "geometry": {"coordinates":[-2.20140080426388,53.62495689676274],"type":"Point"}
}