{
  "type": "Feature",
  "properties": {
    "date:inception_lower": "2021-04-01",
    "date:inception_upper": "2021-04-01",
    "iso:country": "GB",
    "wof:name": "DN9 3QY",
    "wof:placetype": "postalcode"
  },
  "geometry": {"coordinates":[-1.029463,53.49655],"type":"Point"}
}
