{
  "type": "Feature",
  "properties": {
    "iso:country":"GB",
    "wof:name":"M14 6PD",
    "wof:placetype":"postalcode"
},
  "geometry": {"coordinates":[-2.20625277818523,53.44171167145895],"type":"Point"}
}