{
  "type": "Feature",
  "properties": {
    "date:inception_lower": "1980-01-01",
    "date:inception_upper": "1980-01-01",
    "iso:country": "GB",
    "wof:name": "CA25 5JU",
    "wof:placetype": "postalcode"
  },
  "geometry": {"coordinates":[-3.52856,54.526117],"type":"Point"}
}
