{
  "type": "Feature",
  "properties": {
    "iso:country": "GB",
    "wof:name": "CA25 5JU",
    "wof:placetype": "postalcode"
  },
  "geometry": {"coordinates":[-3.52856,54.526117],"type":"Point"}
}
