{
  "type": "Feature",
  "properties": {
    "date:inception_lower": "2014-09-01",
    "date:inception_upper": "2014-09-01",
    "iso:country": "GB",
    "wof:name": "FK1 5ED",
    "wof:placetype": "postalcode"
  },
  "geometry": {"coordinates":[-3.814918,55.997709],"type":"Point"}
}
