{
  "type": "Feature",
  "properties": {
    "iso:country":"GB",
    "wof:name":"FK1 5ED",
    "wof:placetype":"postalcode"
},
  "geometry": {"coordinates":[-3.81491852824809,55.99770946307885],"type":"Point"}
}