{
  "type": "Feature",
  "properties": {
    "iso:country": "GB",
    "wof:name": "FK1 5ED",
    "wof:placetype": "postalcode"
  },
  "geometry": {"coordinates":[-3.814918,55.997709],"type":"Point"}
}
