{
  "type": "Feature",
  "properties": {
    "iso:country":"GB",
    "wof:name":"NE16 5BN",
    "wof:placetype":"postalcode"
},
  "geometry": {"coordinates":[-1.6896738617415,54.93861018684356],"type":"Point"}
}