{
  "type": "Feature",
  "properties": {
    "iso:country":"GB",
    "wof:name":"HU8 9RG",
    "wof:placetype":"postalcode"
},
  "geometry": {"coordinates":[-0.26543301963079,53.77794644785114],"type":"Point"}
}