{
  "type": "Feature",
  "properties": {
    "date:inception_lower": "1980-01-01",
    "date:inception_upper": "1980-01-01",
    "iso:country": "GB",
    "wof:name": "HU8 9RG",
    "wof:placetype": "postalcode"
  },
  "geometry": {"coordinates":[-0.265433,53.777946],"type":"Point"}
}
