{
  "type": "Feature",
  "properties": {
    "iso:country":"GB",
    "wof:name":"TN21 0DZ",
    "wof:placetype":"postalcode"
},
  "geometry": {"coordinates":[0.19805236152075,50.97151757684509],"type":"Point"}
}