{
  "type": "Feature",
  "properties": {
    "iso:country":"GB",
    "wof:name":"M33 2EW",
    "wof:placetype":"postalcode"
},
  "geometry": {"coordinates":[-2.30661261173291,53.42588293151505],"type":"Point"}
}