{
  "type": "Feature",
  "properties": {
    "iso:country":"GB",
    "wof:name":"DN11 0SE",
    "wof:placetype":"postalcode"
},
  "geometry": {"coordinates":[-1.07622773812936,53.46920606985059],"type":"Point"}
}