{
  "type": "Feature",
  "properties": {
    "iso:country":"GB",
    "wof:name":"DY1 3NH",
    "wof:placetype":"postalcode"
},
  "geometry": {"coordinates":[-2.10436782417534,52.52470380469322],"type":"Point"}
}