{
  "type": "Feature",
  "properties": {
    "iso:country":"GB",
    "wof:name":"TS11 7AY",
    "wof:placetype":"postalcode"
},
  "geometry": {"coordinates":[-1.01500488347999,54.59148226988732],"type":"Point"}
}