{
  "type": "Feature",
  "properties": {
    "iso:country": "GB",
    "wof:name": "L25 9SU",
    "wof:placetype": "postalcode"
  },
  "geometry": {"coordinates":[-2.851002,53.365733],"type":"Point"}
}
