{
  "type": "Feature",
  "properties": {
    "iso:country":"GB",
    "wof:name":"L25 9SU",
    "wof:placetype":"postalcode"
},
  "geometry": {"coordinates":[-2.85100235010519,53.36573297111177],"type":"Point"}
}