{
  "type": "Feature",
  "properties": {
    "iso:country":"GB",
    "wof:name":"DL8 2QP",
    "wof:placetype":"postalcode"
},
  "geometry": {"coordinates":[-1.57571332851829,54.21914632642362],"type":"Point"}
}