{
  "type": "Feature",
  "properties": {
    "iso:country":"GB",
    "wof:name":"PO37 7BD",
    "wof:placetype":"postalcode"
},
  "geometry": {"coordinates":[-1.1786532018674,50.63270435496923],"type":"Point"}
}