{
  "type": "Feature",
  "properties": {
    "iso:country":"GB",
    "wof:name":"G64 3NH",
    "wof:placetype":"postalcode"
},
  "geometry": {"coordinates":[-4.22733051004804,55.9167117749099],"type":"Point"}
}