{
  "type": "Feature",
  "properties": {
    "date:inception_lower": "1980-01-01",
    "date:inception_upper": "1980-01-01",
    "iso:country": "GB",
    "wof:name": "SY20 8BE",
    "wof:placetype": "postalcode"
  },
  "geometry": {"coordinates":[-3.852818,52.592411],"type":"Point"}
}
