{
  "type": "Feature",
  "properties": {
    "iso:country":"GB",
    "wof:name":"DL15 8BF",
    "wof:placetype":"postalcode"
},
  "geometry": {"coordinates":[-1.75037545474737,54.69350944150575],"type":"Point"}
}