{
  "type": "Feature",
  "properties": {
    "iso:country": "GB",
    "wof:name": "IV3 8AX",
    "wof:placetype": "postalcode"
  },
  "geometry": {"coordinates":[-4.255656,57.466079],"type":"Point"}
}
