{
  "type": "Feature",
  "properties": {
    "iso:country": "GB",
    "wof:name": "DA7 4JZ",
    "wof:placetype": "postalcode"
  },
  "geometry": {"coordinates":[0.144425,51.462134],"type":"Point"}
}
