{
  "type": "Feature",
  "properties": {
    "iso:country": "GB",
    "wof:name": "CA14 1WJ",
    "wof:placetype": "postalcode"
  },
  "geometry": {"coordinates":[-3.522859,54.648071],"type":"Point"}
}
