{
  "type": "Feature",
  "properties": {
    "iso:country":"GB",
    "wof:name":"B12 8HT",
    "wof:placetype":"postalcode"
},
  "geometry": {"coordinates":[-1.87413053637163,52.45703405724158],"type":"Point"}
}