{
  "type": "Feature",
  "properties": {
    "iso:country":"GB",
    "wof:name":"CW10 9LA",
    "wof:placetype":"postalcode"
},
  "geometry": {"coordinates":[-2.45824144175152,53.20554087298268],"type":"Point"}
}