{
  "type": "Feature",
  "properties": {
    "iso:country": "GB",
    "wof:name": "CW10 9LA",
    "wof:placetype": "postalcode"
  },
  "geometry": {"coordinates":[-2.458241,53.205541],"type":"Point"}
}
