{
  "type": "Feature",
  "properties": {
    "iso:country": "GB",
    "wof:name": "PO31 7LD",
    "wof:placetype": "postalcode"
  },
  "geometry": {"coordinates":[-1.30504,50.756178],"type":"Point"}
}
