{
  "type": "Feature",
  "properties": {
    "iso:country":"GB",
    "wof:name":"EH14 2PQ",
    "wof:placetype":"postalcode"
},
  "geometry": {"coordinates":[-3.27983818515139,55.91950296831087],"type":"Point"}
}