{
  "type": "Feature",
  "properties": {
    "date:inception_lower":"2004-09-01",
    "date:inception_upper":"2004-09-30",
    "iso:country":"GB",
    "wof:name":"OL14 5RL",
    "wof:placetype":"postalcode"
},
  "geometry": {"coordinates":[-2.075727,53.717066],"type":"Point"}
}