{
  "type": "Feature",
  "properties": {
    "iso:country": "GB",
    "wof:name": "OL14 5RL",
    "wof:placetype": "postalcode"
  },
  "geometry": {"coordinates":[-2.075727,53.717066],"type":"Point"}
}
