{
  "type": "Feature",
  "properties": {
    "iso:country": "GB",
    "wof:name": "TA4 1AG",
    "wof:placetype": "postalcode"
  },
  "geometry": {"coordinates":[-3.151778,51.015876],"type":"Point"}
}
