{
  "type": "Feature",
  "properties": {
    "iso:country":"GB",
    "wof:name":"TA4 1AG",
    "wof:placetype":"postalcode"
},
  "geometry": {"coordinates":[-3.1517777887437,51.01587627477734],"type":"Point"}
}