{
  "type": "Feature",
  "properties": {
    "iso:country":"GB",
    "wof:name":"W1U 5LF",
    "wof:placetype":"postalcode"
},
  "geometry": {"coordinates":[-0.15339731467296,51.52144658011476],"type":"Point"}
}