{
  "type": "Feature",
  "properties": {
    "iso:country": "GB",
    "wof:name": "W1U 5LF",
    "wof:placetype": "postalcode"
  },
  "geometry": {"coordinates":[-0.153397,51.521447],"type":"Point"}
}
