{
  "type": "Feature",
  "properties": {
    "date:inception_lower": "2006-03-01",
    "date:inception_upper": "2006-03-01",
    "iso:country": "GB",
    "wof:name": "E1 2AQ",
    "wof:placetype": "postalcode"
  },
  "geometry": {"coordinates":[-0.059616,51.516003],"type":"Point"}
}
