{
  "type": "Feature",
  "properties": {
    "iso:country":"GB",
    "wof:name":"ML5 4HY",
    "wof:placetype":"postalcode"
},
  "geometry": {"coordinates":[-4.01816913180717,55.84832391191085],"type":"Point"}
}