{
  "type": "Feature",
  "properties": {
    "iso:country":"GB",
    "wof:name":"BS39 5XS",
    "wof:placetype":"postalcode"
},
  "geometry": {"coordinates":[-2.59675306659461,51.33406926700236],"type":"Point"}
}