{
  "type": "Feature",
  "properties": {
    "date:inception_lower":"1993-01-01",
    "date:inception_upper":"1993-01-31",
    "iso:country":"GB",
    "wof:name":"SY21 9NW",
    "wof:placetype":"postalcode"
},
  "geometry": {"coordinates":[-3.16106,52.694974],"type":"Point"}
}