{
  "type": "Feature",
  "properties": {
    "iso:country":"GB",
    "wof:name":"SY21 9NW",
    "wof:placetype":"postalcode"
},
  "geometry": {"coordinates":[-3.1610603775128,52.69497364151293],"type":"Point"}
}