{
  "type": "Feature",
  "properties": {
    "iso:country": "GB",
    "wof:name": "CO6 4EN",
    "wof:placetype": "postalcode"
  },
  "geometry": {"coordinates":[0.880379,51.930133],"type":"Point"}
}
