{
  "type": "Feature",
  "properties": {
    "date:inception_lower": "1980-01-01",
    "date:inception_upper": "1980-01-01",
    "iso:country": "GB",
    "wof:name": "CO6 4EN",
    "wof:placetype": "postalcode"
  },
  "geometry": {"coordinates":[0.880379,51.930133],"type":"Point"}
}
