{
  "type": "Feature",
  "properties": {
    "iso:country": "GB",
    "wof:name": "BS5 7FS",
    "wof:placetype": "postalcode"
  },
  "geometry": {"coordinates":[-2.540356,51.467005],"type":"Point"}
}
