{
  "type": "Feature",
  "properties": {
    "iso:country": "GB",
    "wof:name": "BS4 3DE",
    "wof:placetype": "postalcode"
  },
  "geometry": {"coordinates":[-2.572159,51.43952],"type":"Point"}
}
