{
  "type": "Feature",
  "properties": {
    "iso:country": "GB",
    "wof:name": "SP7 8RP",
    "wof:placetype": "postalcode"
  },
  "geometry": {"coordinates":[-2.184709,51.010349],"type":"Point"}
}
