{
  "type": "Feature",
  "properties": {
    "date:inception_lower":"1997-06-01",
    "date:inception_upper":"1997-06-30",
    "iso:country":"GB",
    "wof:name":"SP7 8RP",
    "wof:placetype":"postalcode"
},
  "geometry": {"coordinates":[-2.184709,51.010349],"type":"Point"}
}