{
  "type": "Feature",
  "properties": {
    "iso:country":"GB",
    "wof:name":"CA20 1PX",
    "wof:placetype":"postalcode"
},
  "geometry": {"coordinates":[-3.48134911486041,54.3961909928011],"type":"Point"}
}