{
  "type": "Feature",
  "properties": {
    "iso:country": "GB",
    "wof:name": "CA20 1PX",
    "wof:placetype": "postalcode"
  },
  "geometry": {"coordinates":[-3.481349,54.396191],"type":"Point"}
}
