{
  "type": "Feature",
  "properties": {
    "date:inception_lower": "1980-01-01",
    "date:inception_upper": "1980-01-01",
    "iso:country": "GB",
    "wof:name": "SA14 8BB",
    "wof:placetype": "postalcode"
  },
  "geometry": {"coordinates":[-4.145387,51.697888],"type":"Point"}
}
