{
  "type": "Feature",
  "properties": {
    "iso:country":"GB",
    "wof:name":"EX5 7BJ",
    "wof:placetype":"postalcode"
},
  "geometry": {"coordinates":[-3.41407226811279,50.74940232600193],"type":"Point"}
}