{
  "type": "Feature",
  "properties": {
    "date:inception_lower": "1980-01-01",
    "date:inception_upper": "1980-01-01",
    "iso:country": "GB",
    "wof:name": "PR1 2AU",
    "wof:placetype": "postalcode"
  },
  "geometry": {"coordinates":[-2.700964,53.759495],"type":"Point"}
}
