{
  "type": "Feature",
  "properties": {
    "iso:country": "GB",
    "wof:name": "SY11 4DP",
    "wof:placetype": "postalcode"
  },
  "geometry": {"coordinates":[-2.998845,52.877058],"type":"Point"}
}
