{
  "type": "Feature",
  "properties": {
    "iso:country": "GB",
    "wof:name": "HU7 3NH",
    "wof:placetype": "postalcode"
  },
  "geometry": {"coordinates":[-0.344866,53.803998],"type":"Point"}
}
