{
  "type": "Feature",
  "properties": {
    "date:inception_lower":"1998-06-01",
    "date:inception_upper":"1998-06-30",
    "iso:country":"GB",
    "wof:name":"YO62 5UP",
    "wof:placetype":"postalcode"
},
  "geometry": {"coordinates":[-0.979681,54.205635],"type":"Point"}
}