{
  "type": "Feature",
  "properties": {
    "iso:country":"GB",
    "wof:name":"YO62 5UP",
    "wof:placetype":"postalcode"
},
  "geometry": {"coordinates":[-0.97968092989289,54.2056345420247],"type":"Point"}
}