{
  "type": "Feature",
  "properties": {
    "iso:country":"GB",
    "wof:name":"IP10 0JJ",
    "wof:placetype":"postalcode"
},
  "geometry": {"coordinates":[1.20866561368026,52.01998652577804],"type":"Point"}
}