{
  "type": "Feature",
  "properties": {
    "date:inception_lower":"1980-01-01",
    "date:inception_upper":"1980-01-31",
    "iso:country":"GB",
    "wof:name":"IP10 0JJ",
    "wof:placetype":"postalcode"
},
  "geometry": {"coordinates":[1.208696,52.02],"type":"Point"}
}