{
  "type": "Feature",
  "properties": {
    "date:inception_lower": "1980-01-01",
    "date:inception_upper": "1980-01-01",
    "iso:country": "GB",
    "wof:name": "IP10 0JJ",
    "wof:placetype": "postalcode"
  },
  "geometry": {"coordinates":[1.20859,52.019949],"type":"Point"}
}
