{
  "type": "Feature",
  "properties": {
    "iso:country": "GB",
    "wof:name": "IP10 0JJ",
    "wof:placetype": "postalcode"
  },
  "geometry": {"coordinates":[1.208696,52.02],"type":"Point"}
}
