{
  "type": "Feature",
  "properties": {
    "iso:country":"GB",
    "wof:name":"BS11 9YE",
    "wof:placetype":"postalcode"
},
  "geometry": {"coordinates":[-2.69185627518731,51.50680763539727],"type":"Point"}
}