{
  "type": "Feature",
  "properties": {
    "date:inception_lower": "2023-03-01",
    "date:inception_upper": "2023-03-01",
    "iso:country": "GB",
    "wof:name": "EH52 6FW",
    "wof:placetype": "postalcode"
  },
  "geometry": {"coordinates":[-3.466059,55.961282],"type":"Point"}
}
