{
  "type": "Feature",
  "properties": {
    "iso:country":"GB",
    "wof:name":"BH25 7EB",
    "wof:placetype":"postalcode"
},
  "geometry": {"coordinates":[-1.66389020612596,50.73652451402287],"type":"Point"}
}