{
  "type": "Feature",
  "properties": {
    "iso:country": "GB",
    "wof:name": "BS20 6QT",
    "wof:placetype": "postalcode"
  },
  "geometry": {"coordinates":[-2.770605,51.478955],"type":"Point"}
}
