{
  "type": "Feature",
  "properties": {
    "iso:country": "GB",
    "wof:name": "BS4 3QY",
    "wof:placetype": "postalcode"
  },
  "geometry": {"coordinates":[-2.55378,51.443818],"type":"Point"}
}
