{
  "type": "Feature",
  "properties": {
    "date:inception_lower": "1980-01-01",
    "date:inception_upper": "1980-01-01",
    "iso:country": "GB",
    "wof:name": "SR1 2AQ",
    "wof:placetype": "postalcode"
  },
  "geometry": {"coordinates":[-1.375122,54.904843],"type":"Point"}
}
