{
  "type": "Feature",
  "properties": {
    "iso:country":"GB",
    "wof:name":"SR1 2AQ",
    "wof:placetype":"postalcode"
},
  "geometry": {"coordinates":[-1.3751222790914,54.90484313669455],"type":"Point"}
}