{
  "type": "Feature",
  "properties": {
    "iso:country":"GB",
    "wof:name":"KA3 6DH",
    "wof:placetype":"postalcode"
},
  "geometry": {"coordinates":[-4.44255826359251,55.66128016907382],"type":"Point"}
}