{
  "type": "Feature",
  "properties": {
    "iso:country":"GB",
    "wof:name":"OX4 2EX",
    "wof:placetype":"postalcode"
},
  "geometry": {"coordinates":[-1.21239358508303,51.73518395350474],"type":"Point"}
}