{
  "type": "Feature",
  "properties": {
    "date:inception_lower": "1982-12-01",
    "date:inception_upper": "1982-12-01",
    "iso:country": "GB",
    "wof:name": "G3 8RX",
    "wof:placetype": "postalcode"
  },
  "geometry": {"coordinates":[-4.291322,55.866412],"type":"Point"}
}
