{
  "type": "Feature",
  "properties": {
    "iso:country":"GB",
    "wof:name":"G3 8RX",
    "wof:placetype":"postalcode"
},
  "geometry": {"coordinates":[-4.29132220952881,55.86641167134361],"type":"Point"}
}