{
  "type": "Feature",
  "properties": {
    "iso:country":"GB",
    "wof:name":"PO12 1NP",
    "wof:placetype":"postalcode"
},
  "geometry": {"coordinates":[-1.12123119440921,50.79413060950981],"type":"Point"}
}