{
  "type": "Feature",
  "properties": {
    "iso:country": "GB",
    "wof:name": "PO12 1NP",
    "wof:placetype": "postalcode"
  },
  "geometry": {"coordinates":[-1.121217,50.794122],"type":"Point"}
}
