{
  "type": "Feature",
  "properties": {
    "iso:country": "GB",
    "wof:name": "NG7 1LP",
    "wof:placetype": "postalcode"
  },
  "geometry": {"coordinates":[-1.164685,52.955698],"type":"Point"}
}
