{
  "type": "Feature",
  "properties": {
    "iso:country":"GB",
    "wof:name":"NG7 1LP",
    "wof:placetype":"postalcode"
},
  "geometry": {"coordinates":[-1.1646850067411,52.95569784853751],"type":"Point"}
}