{
  "type": "Feature",
  "properties": {
    "iso:country":"GB",
    "wof:name":"CT9 3UH",
    "wof:placetype":"postalcode"
},
  "geometry": {"coordinates":[1.41749915888209,51.37882761359386],"type":"Point"}
}