{
  "type": "Feature",
  "properties": {
    "iso:country": "GB",
    "wof:name": "CT9 3UH",
    "wof:placetype": "postalcode"
  },
  "geometry": {"coordinates":[1.417499,51.378828],"type":"Point"}
}
