{
  "type": "Feature",
  "properties": {
    "date:inception_lower": "1980-01-01",
    "date:inception_upper": "1980-01-01",
    "iso:country": "GB",
    "wof:name": "CT9 3UH",
    "wof:placetype": "postalcode"
  },
  "geometry": {"coordinates":[1.417499,51.378828],"type":"Point"}
}
