{
  "type": "Feature",
  "properties": {
    "date:inception_lower": "1999-06-01",
    "date:inception_upper": "1999-06-01",
    "iso:country": "GB",
    "wof:name": "WA12 9WF",
    "wof:placetype": "postalcode"
  },
  "geometry": {"coordinates":[-2.639346,53.457913],"type":"Point"}
}
