{
  "type": "Feature",
  "properties": {
    "date:inception_lower": "1980-01-01",
    "date:inception_upper": "1980-01-01",
    "iso:country": "GB",
    "wof:name": "TN1 1XF",
    "wof:placetype": "postalcode"
  },
  "geometry": {"coordinates":[0.261851,51.128434],"type":"Point"}
}
