{
  "type": "Feature",
  "properties": {
    "iso:country":"GB",
    "wof:name":"TN1 1XF",
    "wof:placetype":"postalcode"
},
  "geometry": {"coordinates":[0.26185055609274,51.12843411387007],"type":"Point"}
}