{
  "type": "Feature",
  "properties": {
    "iso:country":"GB",
    "wof:name":"W3 6PL",
    "wof:placetype":"postalcode"
},
  "geometry": {"coordinates":[-0.26708963881247,51.51637406403454],"type":"Point"}
}