{
  "type": "Feature",
  "properties": {
    "iso:country": "GB",
    "wof:name": "BD20 8BA",
    "wof:placetype": "postalcode"
  },
  "geometry": {"coordinates":[-1.96883,53.898723],"type":"Point"}
}
