{
  "type": "Feature",
  "properties": {
    "date:inception_lower": "2019-05-01",
    "date:inception_upper": "2019-05-01",
    "iso:country": "GB",
    "wof:name": "BD20 8BA",
    "wof:placetype": "postalcode"
  },
  "geometry": {"coordinates":[-1.968861,53.898642],"type":"Point"}
}
