{
  "type": "Feature",
  "properties": {
    "iso:country":"GB",
    "wof:name":"UB3 3HP",
    "wof:placetype":"postalcode"
},
  "geometry": {"coordinates":[-0.40792495558056,51.5053673212938],"type":"Point"}
}