{
  "type": "Feature",
  "properties": {
    "iso:country": "GB",
    "wof:name": "LL32 8HP",
    "wof:placetype": "postalcode"
  },
  "geometry": {"coordinates":[-3.834515,53.274177],"type":"Point"}
}
