{
  "type": "Feature",
  "properties": {
    "date:inception_lower": "1980-01-01",
    "date:inception_upper": "1980-01-01",
    "iso:country": "GB",
    "wof:name": "LL32 8HP",
    "wof:placetype": "postalcode"
  },
  "geometry": {"coordinates":[-3.834515,53.274177],"type":"Point"}
}
