{
  "type": "Feature",
  "properties": {
    "date:inception_lower": "1996-12-01",
    "date:inception_upper": "1996-12-01",
    "iso:country": "GB",
    "wof:name": "AB12 3JT",
    "wof:placetype": "postalcode"
  },
  "geometry": {"coordinates":[-2.089927,57.116616],"type":"Point"}
}
