{
  "type": "Feature",
  "properties": {
    "iso:country":"GB",
    "wof:name":"S65 2EP",
    "wof:placetype":"postalcode"
},
  "geometry": {"coordinates":[-1.33082349120546,53.43256583717799],"type":"Point"}
}