{
  "type": "Feature",
  "properties": {
    "date:inception_lower": "2018-03-01",
    "date:inception_upper": "2018-03-01",
    "iso:country": "GB",
    "wof:name": "CH65 4FJ",
    "wof:placetype": "postalcode"
  },
  "geometry": {"coordinates":[-2.892977,53.281],"type":"Point"}
}
