{
  "type": "Feature",
  "properties": {
    "iso:country": "GB",
    "wof:name": "SA48 8QY",
    "wof:placetype": "postalcode"
  },
  "geometry": {"coordinates":[-4.129858,52.190363],"type":"Point"}
}
