{
  "type": "Feature",
  "properties": {
    "date:inception_lower":"1980-01-01",
    "date:inception_upper":"1980-01-31",
    "iso:country":"GB",
    "wof:name":"SA48 8QY",
    "wof:placetype":"postalcode"
},
  "geometry": {"coordinates":[-4.129858,52.190363],"type":"Point"}
}