{
  "type": "Feature",
  "properties": {
    "iso:country":"GB",
    "wof:name":"SA48 8QY",
    "wof:placetype":"postalcode"
},
  "geometry": {"coordinates":[-4.12985850810278,52.19036291281547],"type":"Point"}
}