{
  "type": "Feature",
  "properties": {
    "iso:country":"GB",
    "wof:name":"TF7 5BT",
    "wof:placetype":"postalcode"
},
  "geometry": {"coordinates":[-2.45259710581986,52.6353132807105],"type":"Point"}
}