{
  "type": "Feature",
  "properties": {
    "date:inception_lower": "1980-01-01",
    "date:inception_upper": "1980-01-01",
    "iso:country": "GB",
    "wof:name": "TF7 5BT",
    "wof:placetype": "postalcode"
  },
  "geometry": {"coordinates":[-2.452597,52.635313],"type":"Point"}
}
