{
  "type": "Feature",
  "properties": {
    "iso:country":"GB",
    "wof:name":"TR6 0AE",
    "wof:placetype":"postalcode"
},
  "geometry": {"coordinates":[-5.14248584864189,50.35683957708551],"type":"Point"}
}