{
  "type": "Feature",
  "properties": {
    "date:inception_lower":"1980-01-01",
    "date:inception_upper":"1980-01-31",
    "iso:country":"GB",
    "wof:name":"TR6 0AE",
    "wof:placetype":"postalcode"
},
  "geometry": {"coordinates":[-5.142532,50.35683],"type":"Point"}
}