{
  "type": "Feature",
  "properties": {
    "date:inception_lower": "1980-01-01",
    "date:inception_upper": "1980-01-01",
    "iso:country": "GB",
    "wof:name": "BA12 6QB",
    "wof:placetype": "postalcode"
  },
  "geometry": {"coordinates":[-2.326942,51.102503],"type":"Point"}
}
