{
  "type": "Feature",
  "properties": {
    "iso:country":"GB",
    "wof:name":"BA12 6QB",
    "wof:placetype":"postalcode"
},
  "geometry": {"coordinates":[-2.32694232007339,51.10250343691683],"type":"Point"}
}