{
  "type": "Feature",
  "properties": {
    "iso:country":"GB",
    "wof:name":"DY8 1NH",
    "wof:placetype":"postalcode"
},
  "geometry": {"coordinates":[-2.13529226864139,52.44868034689298],"type":"Point"}
}