{
  "type": "Feature",
  "properties": {
    "iso:country":"GB",
    "wof:name":"SM6 7LH",
    "wof:placetype":"postalcode"
},
  "geometry": {"coordinates":[-0.13384956507849,51.3711135487568],"type":"Point"}
}