{
  "type": "Feature",
  "properties": {
    "iso:country":"GB",
    "wof:name":"E8 1EN",
    "wof:placetype":"postalcode"
},
  "geometry": {"coordinates":[-0.0560509073206,51.54590713457602],"type":"Point"}
}