{
  "type": "Feature",
  "properties": {
    "iso:country": "GB",
    "wof:name": "E8 1EN",
    "wof:placetype": "postalcode"
  },
  "geometry": {"coordinates":[-0.056051,51.545907],"type":"Point"}
}
