{
  "type": "Feature",
  "properties": {
    "iso:country":"GB",
    "wof:name":"CW11 1RZ",
    "wof:placetype":"postalcode"
},
  "geometry": {"coordinates":[-2.32875294028996,53.18033235273722],"type":"Point"}
}