{
  "type": "Feature",
  "properties": {
    "iso:country": "GB",
    "wof:name": "CW11 1RZ",
    "wof:placetype": "postalcode"
  },
  "geometry": {"coordinates":[-2.328753,53.180332],"type":"Point"}
}
