{
  "type": "Feature",
  "properties": {
    "date:inception_lower": "1997-12-01",
    "date:inception_upper": "1997-12-01",
    "iso:country": "GB",
    "wof:name": "CW11 1RZ",
    "wof:placetype": "postalcode"
  },
  "geometry": {"coordinates":[-2.328753,53.180332],"type":"Point"}
}
