{
  "type": "Feature",
  "properties": {
    "iso:country":"GB",
    "wof:name":"WR8 0QY",
    "wof:placetype":"postalcode"
},
  "geometry": {"coordinates":[-2.23294041701449,52.04515883342638],"type":"Point"}
}