{
  "type": "Feature",
  "properties": {
    "iso:country":"GB",
    "wof:name":"PL32 9NH",
    "wof:placetype":"postalcode"
},
  "geometry": {"coordinates":[-4.67574949668813,50.62488774816148],"type":"Point"}
}