{
  "type": "Feature",
  "properties": {
    "date:inception_lower":"2005-04-01",
    "date:inception_upper":"2005-04-30",
    "iso:country":"GB",
    "wof:name":"PL32 9NH",
    "wof:placetype":"postalcode"
},
  "geometry": {"coordinates":[-4.675749,50.624888],"type":"Point"}
}