{
  "type": "Feature",
  "properties": {
    "iso:country": "GB",
    "wof:name": "HU16 5UB",
    "wof:placetype": "postalcode"
  },
  "geometry": {"coordinates":[-0.463439,53.78792],"type":"Point"}
}
