{
  "type": "Feature",
  "properties": {
    "iso:country":"GB",
    "wof:name":"HU16 5UB",
    "wof:placetype":"postalcode"
},
  "geometry": {"coordinates":[-0.46343947339003,53.78791961257318],"type":"Point"}
}