{
  "type": "Feature",
  "properties": {
    "iso:country":"GB",
    "wof:name":"LS25 1BD",
    "wof:placetype":"postalcode"
},
  "geometry": {"coordinates":[-1.39428009119442,53.78973423361759],"type":"Point"}
}