{
  "type": "Feature",
  "properties": {
    "date:inception_lower":"1980-01-01",
    "date:inception_upper":"1980-01-31",
    "iso:country":"GB",
    "wof:name":"CR0 8SH",
    "wof:placetype":"postalcode"
},
  "geometry": {"coordinates":[-0.054083,51.376506],"type":"Point"}
}