{
  "type": "Feature",
  "properties": {
    "iso:country":"GB",
    "wof:name":"LD1 6NW",
    "wof:placetype":"postalcode"
},
  "geometry": {"coordinates":[-3.50748256934225,52.27554777105465],"type":"Point"}
}