{
  "type": "Feature",
  "properties": {
    "iso:country":"GB",
    "wof:name":"WF7 6NH",
    "wof:placetype":"postalcode"
},
  "geometry": {"coordinates":[-1.35519241032818,53.68976134511966],"type":"Point"}
}