{
  "type": "Feature",
  "properties": {
    "date:inception_lower":"1985-04-01",
    "date:inception_upper":"1985-04-30",
    "iso:country":"GB",
    "wof:name":"WF7 6NH",
    "wof:placetype":"postalcode"
},
  "geometry": {"coordinates":[-1.355192,53.689761],"type":"Point"}
}