{
  "type": "Feature",
  "properties": {
    "iso:country": "GB",
    "wof:name": "WF7 6NH",
    "wof:placetype": "postalcode"
  },
  "geometry": {"coordinates":[-1.355192,53.689761],"type":"Point"}
}
