{
  "type": "Feature",
  "properties": {
    "date:inception_lower": "2019-02-01",
    "date:inception_upper": "2019-02-01",
    "iso:country": "GB",
    "wof:name": "SN6 6FQ",
    "wof:placetype": "postalcode"
  },
  "geometry": {"coordinates":[-1.864884,51.660522],"type":"Point"}
}
