{
  "type": "Feature",
  "properties": {
    "iso:country":"GB",
    "wof:name":"EC1V 8EN",
    "wof:placetype":"postalcode"
},
  "geometry": {"coordinates":[-0.09822791478452,51.52951263853159],"type":"Point"}
}