{
  "type": "Feature",
  "properties": {
    "iso:country":"GB",
    "wof:name":"PE12 9AY",
    "wof:placetype":"postalcode"
},
  "geometry": {"coordinates":[0.11407099148354,52.77752451359349],"type":"Point"}
}