{
  "type": "Feature",
  "properties": {
    "iso:country": "GB",
    "wof:name": "KY3 9SU",
    "wof:placetype": "postalcode"
  },
  "geometry": {"coordinates":[-3.173236,56.069255],"type":"Point"}
}
