{
  "type": "Feature",
  "properties": {
    "iso:country":"GB",
    "wof:name":"KY3 9SU",
    "wof:placetype":"postalcode"
},
  "geometry": {"coordinates":[-3.17323596332274,56.06925494726973],"type":"Point"}
}