{
  "type": "Feature",
  "properties": {
    "iso:country":"GB",
    "wof:name":"CV2 4GB",
    "wof:placetype":"postalcode"
},
  "geometry": {"coordinates":[-1.48862091741733,52.41092903081415],"type":"Point"}
}