{
  "type": "Feature",
  "properties": {
    "iso:country": "GB",
    "wof:name": "NG34 0EH",
    "wof:placetype": "postalcode"
  },
  "geometry": {"coordinates":[-0.462919,52.920637],"type":"Point"}
}
