{
  "type": "Feature",
  "properties": {
    "iso:country":"GB",
    "wof:name":"NG34 0EH",
    "wof:placetype":"postalcode"
},
  "geometry": {"coordinates":[-0.46291925900159,52.92063674309797],"type":"Point"}
}