{
  "type": "Feature",
  "properties": {
    "date:inception_lower": "1980-01-01",
    "date:inception_upper": "1980-01-01",
    "iso:country": "GB",
    "wof:name": "NG34 0EH",
    "wof:placetype": "postalcode"
  },
  "geometry": {"coordinates":[-0.462919,52.920637],"type":"Point"}
}
