{
  "type": "Feature",
  "properties": {
    "iso:country": "GB",
    "wof:name": "DE21 7AR",
    "wof:placetype": "postalcode"
  },
  "geometry": {"coordinates":[-1.404727,52.92737],"type":"Point"}
}
