{
  "type": "Feature",
  "properties": {
    "iso:country":"GB",
    "wof:name":"L25 9QR",
    "wof:placetype":"postalcode"
},
  "geometry": {"coordinates":[-2.85284737418208,53.3663130656108],"type":"Point"}
}