{
  "type": "Feature",
  "properties": {
    "iso:country":"GB",
    "wof:name":"M40 2TF",
    "wof:placetype":"postalcode"
},
  "geometry": {"coordinates":[-2.18290691159624,53.49854785055945],"type":"Point"}
}