{
  "type": "Feature",
  "properties": {
    "iso:country":"GB",
    "wof:name":"SP11 0NE",
    "wof:placetype":"postalcode"
},
  "geometry": {"coordinates":[-1.42441316876836,51.26472462118163],"type":"Point"}
}