{
  "type": "Feature",
  "properties": {
    "iso:country": "GB",
    "wof:name": "SP11 0NE",
    "wof:placetype": "postalcode"
  },
  "geometry": {"coordinates":[-1.424413,51.264725],"type":"Point"}
}
