{
  "type": "Feature",
  "properties": {
    "iso:country":"GB",
    "wof:name":"RM10 8NB",
    "wof:placetype":"postalcode"
},
  "geometry": {"coordinates":[0.15283740692998,51.54446282889833],"type":"Point"}
}