{
  "type": "Feature",
  "properties": {
    "iso:country":"GB",
    "wof:name":"W10 5BB",
    "wof:placetype":"postalcode"
},
  "geometry": {"coordinates":[-0.21218621955522,51.52459645427844],"type":"Point"}
}