{
  "type": "Feature",
  "properties": {
    "iso:country":"GB",
    "wof:name":"PE21 6NS",
    "wof:placetype":"postalcode"
},
  "geometry": {"coordinates":[-0.02644590863012,52.98003562987036],"type":"Point"}
}