{
  "type": "Feature",
  "properties": {
    "iso:country": "GB",
    "wof:name": "PE21 6NS",
    "wof:placetype": "postalcode"
  },
  "geometry": {"coordinates":[-0.026562,52.979954],"type":"Point"}
}
