{
  "type": "Feature",
  "properties": {
    "iso:country":"GB",
    "wof:name":"GL10 3NP",
    "wof:placetype":"postalcode"
},
  "geometry": {"coordinates":[-2.28604916031912,51.72814869068655],"type":"Point"}
}