{
  "type": "Feature",
  "properties": {
    "iso:country": "GB",
    "wof:name": "IP28 6JW",
    "wof:placetype": "postalcode"
  },
  "geometry": {"coordinates":[0.692851,52.275768],"type":"Point"}
}
