{
  "type": "Feature",
  "properties": {
    "iso:country": "GB",
    "wof:name": "TA8 2FB",
    "wof:placetype": "postalcode"
  },
  "geometry": {"coordinates":[-2.985115,51.241804],"type":"Point"}
}
