{
  "type": "Feature",
  "properties": {
    "date:inception_lower":"2001-06-01",
    "date:inception_upper":"2001-06-30",
    "iso:country":"GB",
    "wof:name":"TR1 2GA",
    "wof:placetype":"postalcode"
},
  "geometry": {"coordinates":[-5.048722,50.263498],"type":"Point"}
}