{
  "type": "Feature",
  "properties": {
    "date:inception_lower": "1980-01-01",
    "date:inception_upper": "1980-01-01",
    "iso:country": "GB",
    "wof:name": "ME2 4XB",
    "wof:placetype": "postalcode"
  },
  "geometry": {"coordinates":[0.532683,51.413279],"type":"Point"}
}
