{
  "type": "Feature",
  "properties": {
    "iso:country": "GB",
    "wof:name": "ME2 4XB",
    "wof:placetype": "postalcode"
  },
  "geometry": {"coordinates":[0.531995,51.41279],"type":"Point"}
}
