{
  "type": "Feature",
  "properties": {
    "iso:country":"GB",
    "wof:name":"TD5 8HW",
    "wof:placetype":"postalcode"
},
  "geometry": {"coordinates":[-2.38327346427455,55.61068354884604],"type":"Point"}
}