{
  "type": "Feature",
  "properties": {
    "iso:country": "GB",
    "wof:name": "CH43 7YP",
    "wof:placetype": "postalcode"
  },
  "geometry": {"coordinates":[-3.082967,53.400878],"type":"Point"}
}
