{
  "type": "Feature",
  "properties": {
    "iso:country":"GB",
    "wof:name":"AB51 5HR",
    "wof:placetype":"postalcode"
},
  "geometry": {"coordinates":[-2.49434882068937,57.31518700652577],"type":"Point"}
}