{
  "type": "Feature",
  "properties": {
    "date:inception_lower": "1994-05-01",
    "date:inception_upper": "1994-05-01",
    "iso:country": "GB",
    "wof:name": "AB51 5HR",
    "wof:placetype": "postalcode"
  },
  "geometry": {"coordinates":[-2.494349,57.315187],"type":"Point"}
}
