{
  "type": "Feature",
  "properties": {
    "iso:country": "GB",
    "wof:name": "PR4 0PN",
    "wof:placetype": "postalcode"
  },
  "geometry": {"coordinates":[-2.752273,53.790589],"type":"Point"}
}
