{
  "type": "Feature",
  "properties": {
    "iso:country": "GB",
    "wof:name": "M9 8JE",
    "wof:placetype": "postalcode"
  },
  "geometry": {"coordinates":[-2.229158,53.526826],"type":"Point"}
}
