{
  "type": "Feature",
  "properties": {
    "date:inception_lower":"1980-01-01",
    "date:inception_upper":"1980-01-31",
    "iso:country":"GB",
    "wof:name":"SS15 5HU",
    "wof:placetype":"postalcode"
},
  "geometry": {"coordinates":[0.44436,51.574219],"type":"Point"}
}