{
  "type": "Feature",
  "properties": {
    "iso:country":"GB",
    "wof:name":"NR12 9QQ",
    "wof:placetype":"postalcode"
},
  "geometry": {"coordinates":[1.5301071245464,52.75968900173692],"type":"Point"}
}