{
  "type": "Feature",
  "properties": {
    "iso:country": "GB",
    "wof:name": "EX2 7DD",
    "wof:placetype": "postalcode"
  },
  "geometry": {"coordinates":[-3.49519,50.696616],"type":"Point"}
}
