{
  "type": "Feature",
  "properties": {
    "iso:country":"GB",
    "wof:name":"OL11 5NU",
    "wof:placetype":"postalcode"
},
  "geometry": {"coordinates":[-2.22737192015354,53.62132401869093],"type":"Point"}
}