{
  "type": "Feature",
  "properties": {
    "iso:country": "GB",
    "wof:name": "OL11 5NU",
    "wof:placetype": "postalcode"
  },
  "geometry": {"coordinates":[-2.22737,53.62134],"type":"Point"}
}
