{
  "type": "Feature",
  "properties": {
    "date:inception_lower": "2009-04-01",
    "date:inception_upper": "2009-04-01",
    "iso:country": "GB",
    "wof:name": "OL11 5NU",
    "wof:placetype": "postalcode"
  },
  "geometry": {"coordinates":[-2.22737,53.62134],"type":"Point"}
}
