{
  "type": "Feature",
  "properties": {
    "iso:country":"GB",
    "wof:name":"NE3 1HN",
    "wof:placetype":"postalcode"
},
  "geometry": {"coordinates":[-1.62058806223885,55.00853415992994],"type":"Point"}
}