{
  "type": "Feature",
  "properties": {
    "iso:country":"GB",
    "wof:name":"WC1H 9PW",
    "wof:placetype":"postalcode"
},
  "geometry": {"coordinates":[-0.1257856802464,51.52724943869168],"type":"Point"}
}