{
  "type": "Feature",
  "properties": {
    "date:inception_lower": "1980-01-01",
    "date:inception_upper": "1980-01-01",
    "iso:country": "GB",
    "wof:name": "WC1H 9PW",
    "wof:placetype": "postalcode"
  },
  "geometry": {"coordinates":[-0.125786,51.527249],"type":"Point"}
}
