{
  "type": "Feature",
  "properties": {
    "iso:country":"GB",
    "wof:name":"CH47 4AF",
    "wof:placetype":"postalcode"
},
  "geometry": {"coordinates":[-3.18403304349506,53.38531207934133],"type":"Point"}
}