{
  "type": "Feature",
  "properties": {
    "iso:country":"GB",
    "wof:name":"PE33 9BL",
    "wof:placetype":"postalcode"
},
  "geometry": {"coordinates":[0.58055489850067,52.5791614730738],"type":"Point"}
}