{
  "type": "Feature",
  "properties": {
    "date:inception_lower": "2023-06-01",
    "date:inception_upper": "2023-06-01",
    "iso:country": "GB",
    "wof:name": "CO15 9JF",
    "wof:placetype": "postalcode"
  },
  "geometry": {"coordinates":[1.160473,51.801829],"type":"Point"}
}
