{
  "type": "Feature",
  "properties": {
    "iso:country":"GB",
    "wof:name":"PE19 5UR",
    "wof:placetype":"postalcode"
},
  "geometry": {"coordinates":[-0.25206918181584,52.28935937142121],"type":"Point"}
}