{
  "type": "Feature",
  "properties": {
    "date:inception_lower": "2019-10-01",
    "date:inception_upper": "2019-10-01",
    "iso:country": "GB",
    "wof:name": "B77 5GP",
    "wof:placetype": "postalcode"
  },
  "geometry": {"coordinates":[-1.662621,52.604845],"type":"Point"}
}
