{
  "type": "Feature",
  "properties": {
    "date:inception_lower": "2006-09-01",
    "date:inception_upper": "2006-09-01",
    "iso:country": "GB",
    "wof:name": "CB21 4YL",
    "wof:placetype": "postalcode"
  },
  "geometry": {"coordinates":[0.286518,52.098291],"type":"Point"}
}
