{
  "type": "Feature",
  "properties": {
    "date:inception_lower":"1980-01-01",
    "date:inception_upper":"1980-01-31",
    "iso:country":"GB",
    "wof:name":"LD3 7PA",
    "wof:placetype":"postalcode"
},
  "geometry": {"coordinates":[-3.386663,51.949508],"type":"Point"}
}