{
  "type": "Feature",
  "properties": {
    "iso:country":"GB",
    "wof:name":"TA4 3HH",
    "wof:placetype":"postalcode"
},
  "geometry": {"coordinates":[-3.20610477485814,51.10193534152495],"type":"Point"}
}