{
  "type": "Feature",
  "properties": {
    "date:inception_lower":"1980-01-01",
    "date:inception_upper":"1980-01-31",
    "iso:country":"GB",
    "wof:name":"IV30 1QU",
    "wof:placetype":"postalcode"
},
  "geometry": {"coordinates":[-3.307378,57.647628],"type":"Point"}
}