{
  "type": "Feature",
  "properties": {
    "iso:country": "GB",
    "wof:name": "HA3 8JB",
    "wof:placetype": "postalcode"
  },
  "geometry": {"coordinates":[-0.309441,51.589499],"type":"Point"}
}
