{
  "type": "Feature",
  "properties": {
    "date:inception_lower": "1980-01-01",
    "date:inception_upper": "1980-01-01",
    "iso:country": "GB",
    "wof:name": "HA3 8JB",
    "wof:placetype": "postalcode"
  },
  "geometry": {"coordinates":[-0.309441,51.589499],"type":"Point"}
}
