{
  "type": "Feature",
  "properties": {
    "iso:country":"GB",
    "wof:name":"HA3 8JB",
    "wof:placetype":"postalcode"
},
  "geometry": {"coordinates":[-0.30942283550776,51.5894425133862],"type":"Point"}
}