{
  "type": "Feature",
  "properties": {
    "iso:country":"GB",
    "wof:name":"LS28 5NN",
    "wof:placetype":"postalcode"
},
  "geometry": {"coordinates":[-1.68333014551905,53.82840599399295],"type":"Point"}
}