{
  "type": "Feature",
  "properties": {
    "iso:country": "GB",
    "wof:name": "SK22 1BW",
    "wof:placetype": "postalcode"
  },
  "geometry": {"coordinates":[-1.970768,53.379075],"type":"Point"}
}
