{
  "type": "Feature",
  "properties": {
    "date:inception_lower": "1996-12-01",
    "date:inception_upper": "1996-12-01",
    "iso:country": "GB",
    "wof:name": "SK22 1BW",
    "wof:placetype": "postalcode"
  },
  "geometry": {"coordinates":[-1.970768,53.379075],"type":"Point"}
}
