{
  "type": "Feature",
  "properties": {
    "iso:country":"GB",
    "wof:name":"LD3 8YT",
    "wof:placetype":"postalcode"
},
  "geometry": {"coordinates":[-3.62243953697707,51.90940308114479],"type":"Point"}
}