{
  "type": "Feature",
  "properties": {
    "iso:country": "GB",
    "wof:name": "LD3 8YT",
    "wof:placetype": "postalcode"
  },
  "geometry": {"coordinates":[-3.622439,51.909403],"type":"Point"}
}
