{
  "type": "Feature",
  "properties": {
    "iso:country": "GB",
    "wof:name": "CB23 1LS",
    "wof:placetype": "postalcode"
  },
  "geometry": {"coordinates":[0.056197,52.151702],"type":"Point"}
}
