{
  "type": "Feature",
  "properties": {
    "date:inception_lower": "2006-09-01",
    "date:inception_upper": "2006-09-01",
    "iso:country": "GB",
    "wof:name": "CB23 1LS",
    "wof:placetype": "postalcode"
  },
  "geometry": {"coordinates":[0.056197,52.151702],"type":"Point"}
}
