{
  "type": "Feature",
  "properties": {
    "iso:country":"GB",
    "wof:name":"CV36 4RH",
    "wof:placetype":"postalcode"
},
  "geometry": {"coordinates":[-1.62769508666626,52.06932880779405],"type":"Point"}
}