{
  "type": "Feature",
  "properties": {
    "iso:country": "GB",
    "wof:name": "CV36 4RH",
    "wof:placetype": "postalcode"
  },
  "geometry": {"coordinates":[-1.627695,52.069329],"type":"Point"}
}
