{
  "type": "Feature",
  "properties": {
    "date:inception_lower": "1980-01-01",
    "date:inception_upper": "1980-01-01",
    "iso:country": "GB",
    "wof:name": "S71 1UP",
    "wof:placetype": "postalcode"
  },
  "geometry": {"coordinates":[-1.469971,53.571912],"type":"Point"}
}
