{
  "type": "Feature",
  "properties": {
    "iso:country":"GB",
    "wof:name":"EN10 6BL",
    "wof:placetype":"postalcode"
},
  "geometry": {"coordinates":[-0.02377318366672,51.72242977690149],"type":"Point"}
}