{
  "type": "Feature",
  "properties": {
    "iso:country":"GB",
    "wof:name":"AL5 5JA",
    "wof:placetype":"postalcode"
},
  "geometry": {"coordinates":[-0.3429508960004,51.82806505881766],"type":"Point"}
}