{
  "type": "Feature",
  "properties": {
    "iso:country":"GB",
    "wof:name":"NE34 8RT",
    "wof:placetype":"postalcode"
},
  "geometry": {"coordinates":[-1.43459414350429,54.96008611243733],"type":"Point"}
}