{
  "type": "Feature",
  "properties": {
    "iso:country":"GB",
    "wof:name":"SE17 2GP",
    "wof:placetype":"postalcode"
},
  "geometry": {"coordinates":[-0.09169229290218,51.48547778628502],"type":"Point"}
}