{
  "type": "Feature",
  "properties": {
    "iso:country": "GB",
    "wof:name": "GU19 5AT",
    "wof:placetype": "postalcode"
  },
  "geometry": {"coordinates":[-0.69066,51.362788],"type":"Point"}
}
