{
  "type": "Feature",
  "properties": {
    "iso:country":"GB",
    "wof:name":"CW4 7LR",
    "wof:placetype":"postalcode"
},
  "geometry": {"coordinates":[-2.39888162207054,53.1945812480807],"type":"Point"}
}