{
  "type": "Feature",
  "properties": {
    "iso:country": "GB",
    "wof:name": "CW4 7LR",
    "wof:placetype": "postalcode"
  },
  "geometry": {"coordinates":[-2.398882,53.194581],"type":"Point"}
}
