{
  "type": "Feature",
  "properties": {
    "iso:country": "GB",
    "wof:name": "PR8 5LR",
    "wof:placetype": "postalcode"
  },
  "geometry": {"coordinates":[-2.938564,53.62131],"type":"Point"}
}
