{
  "type": "Feature",
  "properties": {
    "iso:country":"GB",
    "wof:name":"PR4 2XQ",
    "wof:placetype":"postalcode"
},
  "geometry": {"coordinates":[-2.87991312468739,53.77859477865351],"type":"Point"}
}