{
  "type": "Feature",
  "properties": {
    "date:inception_lower":"1980-01-01",
    "date:inception_upper":"1980-01-31",
    "iso:country":"GB",
    "wof:name":"EX13 5TE",
    "wof:placetype":"postalcode"
},
  "geometry": {"coordinates":[-2.954865,50.76807],"type":"Point"}
}