{
  "type": "Feature",
  "properties": {
    "iso:country":"GB",
    "wof:name":"PO4 8LA",
    "wof:placetype":"postalcode"
},
  "geometry": {"coordinates":[-1.04733741883864,50.7934517957221],"type":"Point"}
}