{
  "type": "Feature",
  "properties": {
    "iso:country": "GB",
    "wof:name": "PO4 8LA",
    "wof:placetype": "postalcode"
  },
  "geometry": {"coordinates":[-1.047337,50.793452],"type":"Point"}
}
