{
  "type": "Feature",
  "properties": {
    "iso:country":"GB",
    "wof:name":"GL1 5DU",
    "wof:placetype":"postalcode"
},
  "geometry": {"coordinates":[-2.24241678462876,51.84816036977978],"type":"Point"}
}