{
  "type": "Feature",
  "properties": {
    "iso:country": "GB",
    "wof:name": "GL1 5DU",
    "wof:placetype": "postalcode"
  },
  "geometry": {"coordinates":[-2.242417,51.84816],"type":"Point"}
}
