{
  "type": "Feature",
  "properties": {
    "iso:country":"GB",
    "wof:name":"TR19 6QW",
    "wof:placetype":"postalcode"
},
  "geometry": {"coordinates":[-5.53927559948388,50.08405038682886],"type":"Point"}
}