{
  "type": "Feature",
  "properties": {
    "iso:country": "GB",
    "wof:name": "DE21 4BT",
    "wof:placetype": "postalcode"
  },
  "geometry": {"coordinates":[-1.452093,52.939238],"type":"Point"}
}
