{
  "type": "Feature",
  "properties": {
    "date:inception_lower":"1999-06-01",
    "date:inception_upper":"1999-06-30",
    "iso:country":"GB",
    "wof:name":"FK7 9NR",
    "wof:placetype":"postalcode"
},
  "geometry": {"coordinates":[-3.963681,56.110143],"type":"Point"}
}