{
  "type": "Feature",
  "properties": {
    "iso:country":"GB",
    "wof:name":"BD21 1QB",
    "wof:placetype":"postalcode"
},
  "geometry": {"coordinates":[-1.91501067978217,53.86333374673015],"type":"Point"}
}