{
  "type": "Feature",
  "properties": {
    "iso:country":"GB",
    "wof:name":"N15 6HX",
    "wof:placetype":"postalcode"
},
  "geometry": {"coordinates":[-0.08176186958212,51.57789405476539],"type":"Point"}
}