{
  "type": "Feature",
  "properties": {
    "date:inception_lower":"2008-12-01",
    "date:inception_upper":"2008-12-31",
    "iso:country":"GB",
    "wof:name":"L8 8DE",
    "wof:placetype":"postalcode"
},
  "geometry": {"coordinates":[-2.962046,53.392423],"type":"Point"}
}