{
  "type": "Feature",
  "properties": {
    "iso:country":"GB",
    "wof:name":"BB3 2LH",
    "wof:placetype":"postalcode"
},
  "geometry": {"coordinates":[-2.46447460561443,53.67781265051433],"type":"Point"}
}