{
  "type": "Feature",
  "properties": {
    "date:inception_lower": "1980-01-01",
    "date:inception_upper": "1980-01-01",
    "iso:country": "GB",
    "wof:name": "BB3 2LH",
    "wof:placetype": "postalcode"
  },
  "geometry": {"coordinates":[-2.464475,53.677813],"type":"Point"}
}
