{
  "type": "Feature",
  "properties": {
    "iso:country": "GB",
    "wof:name": "ST6 5QJ",
    "wof:placetype": "postalcode"
  },
  "geometry": {"coordinates":[-2.221385,53.076901],"type":"Point"}
}
