{
  "type": "Feature",
  "properties": {
    "iso:country":"GB",
    "wof:name":"ST6 5QJ",
    "wof:placetype":"postalcode"
},
  "geometry": {"coordinates":[-2.22138535259408,53.07690150152439],"type":"Point"}
}