{
  "type": "Feature",
  "properties": {
    "iso:country":"GB",
    "wof:name":"W12 9SR",
    "wof:placetype":"postalcode"
},
  "geometry": {"coordinates":[-0.2421560060261,51.49951098950955],"type":"Point"}
}