{
  "type": "Feature",
  "properties": {
    "iso:country": "GB",
    "wof:name": "TW11 0LJ",
    "wof:placetype": "postalcode"
  },
  "geometry": {"coordinates":[-0.34239,51.42557],"type":"Point"}
}
