{
  "type": "Feature",
  "properties": {
    "date:inception_lower": "1980-01-01",
    "date:inception_upper": "1980-01-01",
    "iso:country": "GB",
    "wof:name": "TW11 0LJ",
    "wof:placetype": "postalcode"
  },
  "geometry": {"coordinates":[-0.34239,51.42557],"type":"Point"}
}
