{
  "type": "Feature",
  "properties": {
    "date:inception_lower": "1980-01-01",
    "date:inception_upper": "1980-01-01",
    "iso:country": "GB",
    "wof:name": "ME20 7LL",
    "wof:placetype": "postalcode"
  },
  "geometry": {"coordinates":[0.467718,51.299674],"type":"Point"}
}
