{
  "type": "Feature",
  "properties": {
    "iso:country":"GB",
    "wof:name":"ME20 7LL",
    "wof:placetype":"postalcode"
},
  "geometry": {"coordinates":[0.46771799874922,51.29967367005024],"type":"Point"}
}