{
  "type": "Feature",
  "properties": {
    "iso:country":"GB",
    "wof:name":"GU10 4RJ",
    "wof:placetype":"postalcode"
},
  "geometry": {"coordinates":[-0.80677397740736,51.19079218980045],"type":"Point"}
}