{
  "type": "Feature",
  "properties": {
    "iso:country": "GB",
    "wof:name": "GU10 4RJ",
    "wof:placetype": "postalcode"
  },
  "geometry": {"coordinates":[-0.806774,51.190792],"type":"Point"}
}
