{
  "type": "Feature",
  "properties": {
    "iso:country":"GB",
    "wof:name":"DD1 1NG",
    "wof:placetype":"postalcode"
},
  "geometry": {"coordinates":[-2.97784492763588,56.46168829574058],"type":"Point"}
}