{
  "type": "Feature",
  "properties": {
    "iso:country":"GB",
    "wof:name":"CW5 7LT",
    "wof:placetype":"postalcode"
},
  "geometry": {"coordinates":[-2.45997441557795,53.04571779739728],"type":"Point"}
}