{
  "type": "Feature",
  "properties": {
    "iso:country": "GB",
    "wof:name": "CW5 7LT",
    "wof:placetype": "postalcode"
  },
  "geometry": {"coordinates":[-2.459974,53.045718],"type":"Point"}
}
