{
  "type": "Feature",
  "properties": {
    "date:inception_lower":"1980-01-01",
    "date:inception_upper":"1980-01-31",
    "iso:country":"GB",
    "wof:name":"CW5 7LT",
    "wof:placetype":"postalcode"
},
  "geometry": {"coordinates":[-2.459974,53.045718],"type":"Point"}
}