{
  "type": "Feature",
  "properties": {
    "iso:country":"GB",
    "wof:name":"LU2 9TS",
    "wof:placetype":"postalcode"
},
  "geometry": {"coordinates":[-0.3698639965726,51.88891981674079],"type":"Point"}
}