{
  "type": "Feature",
  "properties": {
    "iso:country":"GB",
    "wof:name":"PO12 1DD",
    "wof:placetype":"postalcode"
},
  "geometry": {"coordinates":[-1.12105561095898,50.79592784029278],"type":"Point"}
}