{
  "type": "Feature",
  "properties": {
    "iso:country":"GB",
    "wof:name":"SO31 4NR",
    "wof:placetype":"postalcode"
},
  "geometry": {"coordinates":[-1.32206540818961,50.85799592532567],"type":"Point"}
}