{
  "type": "Feature",
  "properties": {
    "iso:country":"GB",
    "wof:name":"NE28 9XL",
    "wof:placetype":"postalcode"
},
  "geometry": {"coordinates":[-1.50868549656508,55.01348086192593],"type":"Point"}
}