{
  "type": "Feature",
  "properties": {
    "iso:country": "GB",
    "wof:name": "SG6 3QB",
    "wof:placetype": "postalcode"
  },
  "geometry": {"coordinates":[-0.241757,51.969944],"type":"Point"}
}
