{
  "type": "Feature",
  "properties": {
    "iso:country":"GB",
    "wof:name":"SG6 3QB",
    "wof:placetype":"postalcode"
},
  "geometry": {"coordinates":[-0.241756813803,51.96994388248882],"type":"Point"}
}