{
  "type": "Feature",
  "properties": {
    "iso:country":"GB",
    "wof:name":"NR33 8BW",
    "wof:placetype":"postalcode"
},
  "geometry": {"coordinates":[1.68585929248214,52.45743912623802],"type":"Point"}
}