{
  "type": "Feature",
  "properties": {
    "date:inception_lower": "1980-01-01",
    "date:inception_upper": "1980-01-01",
    "iso:country": "GB",
    "wof:name": "SW8 3RH",
    "wof:placetype": "postalcode"
  },
  "geometry": {"coordinates":[-0.14995,51.46991],"type":"Point"}
}
