{
  "type": "Feature",
  "properties": {
    "iso:country": "GB",
    "wof:name": "HU12 9LD",
    "wof:placetype": "postalcode"
  },
  "geometry": {"coordinates":[-0.177901,53.719592],"type":"Point"}
}
