{
  "type": "Feature",
  "properties": {
    "iso:country":"GB",
    "wof:name":"HU12 9LD",
    "wof:placetype":"postalcode"
},
  "geometry": {"coordinates":[-0.17790130795172,53.7195923633329],"type":"Point"}
}