{
  "type": "Feature",
  "properties": {
    "iso:country":"GB",
    "wof:name":"OL7 0ST",
    "wof:placetype":"postalcode"
},
  "geometry": {"coordinates":[-2.10673523420902,53.48072636628117],"type":"Point"}
}