{
  "type": "Feature",
  "properties": {
    "iso:country": "GB",
    "wof:name": "OL7 0ST",
    "wof:placetype": "postalcode"
  },
  "geometry": {"coordinates":[-2.106735,53.480726],"type":"Point"}
}
