{
  "type": "Feature",
  "properties": {
    "iso:country": "GB",
    "wof:name": "WV16 6LA",
    "wof:placetype": "postalcode"
  },
  "geometry": {"coordinates":[-2.381777,52.452151],"type":"Point"}
}
