{
  "type": "Feature",
  "properties": {
    "date:inception_lower":"1995-07-01",
    "date:inception_upper":"1995-07-31",
    "iso:country":"GB",
    "wof:name":"WV16 6LA",
    "wof:placetype":"postalcode"
},
  "geometry": {"coordinates":[-2.381777,52.452151],"type":"Point"}
}