{
  "type": "Feature",
  "properties": {
    "iso:country":"GB",
    "wof:name":"S65 2TW",
    "wof:placetype":"postalcode"
},
  "geometry": {"coordinates":[-1.34173746530062,53.42856357149972],"type":"Point"}
}