{
  "type": "Feature",
  "properties": {
    "iso:country":"GB",
    "wof:name":"TN37 7HT",
    "wof:placetype":"postalcode"
},
  "geometry": {"coordinates":[0.56704227782405,50.87999111226713],"type":"Point"}
}