{
  "type": "Feature",
  "properties": {
    "iso:country":"GB",
    "wof:name":"AB51 5PT",
    "wof:placetype":"postalcode"
},
  "geometry": {"coordinates":[-2.4065847681882,57.27096424363481],"type":"Point"}
}