{
  "type": "Feature",
  "properties": {
    "iso:country":"GB",
    "wof:name":"SE10 0SR",
    "wof:placetype":"postalcode"
},
  "geometry": {"coordinates":[0.01491904023573,51.49586139785117],"type":"Point"}
}