{
  "type": "Feature",
  "properties": {
    "date:inception_lower": "1980-01-01",
    "date:inception_upper": "1980-01-01",
    "iso:country": "GB",
    "wof:name": "SP6 2JX",
    "wof:placetype": "postalcode"
  },
  "geometry": {"coordinates":[-1.761624,50.929475],"type":"Point"}
}
