{
  "type": "Feature",
  "properties": {
    "iso:country":"GB",
    "wof:name":"SP6 2JX",
    "wof:placetype":"postalcode"
},
  "geometry": {"coordinates":[-1.75994375939095,50.92963297157901],"type":"Point"}
}