{
  "type": "Feature",
  "properties": {
    "iso:country":"GB",
    "wof:name":"HA5 4BY",
    "wof:placetype":"postalcode"
},
  "geometry": {"coordinates":[-0.36283229585047,51.61160993715175],"type":"Point"}
}