{
  "type": "Feature",
  "properties": {
    "iso:country":"GB",
    "wof:name":"DH9 9UR",
    "wof:placetype":"postalcode"
},
  "geometry": {"coordinates":[-1.71862592356103,54.87840928157532],"type":"Point"}
}