{
  "type": "Feature",
  "properties": {
    "iso:country":"GB",
    "wof:name":"PE2 8RX",
    "wof:placetype":"postalcode"
},
  "geometry": {"coordinates":[-0.21519154705303,52.55084621646493],"type":"Point"}
}