{
  "type": "Feature",
  "properties": {
    "date:inception_lower": "1986-07-01",
    "date:inception_upper": "1986-07-01",
    "iso:country": "GB",
    "wof:name": "KT23 4LN",
    "wof:placetype": "postalcode"
  },
  "geometry": {"coordinates":[-0.369544,51.271918],"type":"Point"}
}
