{
  "type": "Feature",
  "properties": {
    "iso:country":"GB",
    "wof:name":"KT23 4LN",
    "wof:placetype":"postalcode"
},
  "geometry": {"coordinates":[-0.36954366074521,51.27191795223801],"type":"Point"}
}