{
  "type": "Feature",
  "properties": {
    "iso:country":"GB",
    "wof:name":"SW15 6BT",
    "wof:placetype":"postalcode"
},
  "geometry": {"coordinates":[-0.22516754843828,51.45726932992923],"type":"Point"}
}