{
  "type": "Feature",
  "properties": {
    "date:inception_lower":"1991-09-01",
    "date:inception_upper":"1991-09-30",
    "iso:country":"GB",
    "wof:name":"WA14 4QB",
    "wof:placetype":"postalcode"
},
  "geometry": {"coordinates":[-2.370885,53.389396],"type":"Point"}
}