{
  "type": "Feature",
  "properties": {
    "iso:country":"GB",
    "wof:name":"WA14 4QB",
    "wof:placetype":"postalcode"
},
  "geometry": {"coordinates":[-2.37088503226632,53.38939555909017],"type":"Point"}
}