{
  "type": "Feature",
  "properties": {
    "iso:country":"GB",
    "wof:name":"PL31 1HQ",
    "wof:placetype":"postalcode"
},
  "geometry": {"coordinates":[-4.70708757332909,50.46728379236181],"type":"Point"}
}