{
  "type": "Feature",
  "properties": {
    "iso:country":"GB",
    "wof:name":"NW10 5JX",
    "wof:placetype":"postalcode"
},
  "geometry": {"coordinates":[-0.21895008664171,51.52895275200125],"type":"Point"}
}