{
  "type": "Feature",
  "properties": {
    "iso:country": "GB",
    "wof:name": "LN6 8RG",
    "wof:placetype": "postalcode"
  },
  "geometry": {"coordinates":[-0.592167,53.192446],"type":"Point"}
}
