{
  "type": "Feature",
  "properties": {
    "iso:country":"GB",
    "wof:name":"LN6 8RG",
    "wof:placetype":"postalcode"
},
  "geometry": {"coordinates":[-0.59216695666566,53.1924456697795],"type":"Point"}
}