{
  "type": "Feature",
  "properties": {
    "date:inception_lower": "1990-02-01",
    "date:inception_upper": "1990-02-01",
    "iso:country": "GB",
    "wof:name": "LN6 8RG",
    "wof:placetype": "postalcode"
  },
  "geometry": {"coordinates":[-0.592167,53.192446],"type":"Point"}
}
