{
  "type": "Feature",
  "properties": {
    "date:inception_lower": "1980-01-01",
    "date:inception_upper": "1980-01-01",
    "iso:country": "GB",
    "wof:name": "HU6 9LX",
    "wof:placetype": "postalcode"
  },
  "geometry": {"coordinates":[-0.372342,53.786043],"type":"Point"}
}
