{
  "type": "Feature",
  "properties": {
    "date:inception_lower":"1984-02-01",
    "date:inception_upper":"1984-02-29",
    "iso:country":"GB",
    "wof:name":"ME5 9BU",
    "wof:placetype":"postalcode"
},
  "geometry": {"coordinates":[0.516354,51.33642],"type":"Point"}
}