{
  "type": "Feature",
  "properties": {
    "date:inception_lower": "1980-01-01",
    "date:inception_upper": "1980-01-01",
    "iso:country": "GB",
    "wof:name": "IP24 1AZ",
    "wof:placetype": "postalcode"
  },
  "geometry": {"coordinates":[0.742056,52.417431],"type":"Point"}
}
