{
  "type": "Feature",
  "properties": {
    "iso:country":"GB",
    "wof:name":"G20 7DS",
    "wof:placetype":"postalcode"
},
  "geometry": {"coordinates":[-4.26949563813972,55.87857188551295],"type":"Point"}
}