{
  "type": "Feature",
  "properties": {
    "iso:country":"GB",
    "wof:name":"BA11 3EN",
    "wof:placetype":"postalcode"
},
  "geometry": {"coordinates":[-2.33654024861575,51.23802168979658],"type":"Point"}
}