{
  "type": "Feature",
  "properties": {
    "date:inception_lower": "1980-01-01",
    "date:inception_upper": "1980-01-01",
    "iso:country": "GB",
    "wof:name": "BA11 3EN",
    "wof:placetype": "postalcode"
  },
  "geometry": {"coordinates":[-2.33654,51.238022],"type":"Point"}
}
