{
  "type": "Feature",
  "properties": {
    "iso:country":"GB",
    "wof:name":"YO23 3PD",
    "wof:placetype":"postalcode"
},
  "geometry": {"coordinates":[-1.18556107590063,53.92552298670459],"type":"Point"}
}