{
  "type": "Feature",
  "properties": {
    "date:inception_lower": "1998-06-01",
    "date:inception_upper": "1998-06-01",
    "iso:country": "GB",
    "wof:name": "YO23 3PD",
    "wof:placetype": "postalcode"
  },
  "geometry": {"coordinates":[-1.185895,53.925974],"type":"Point"}
}
