{
  "type": "Feature",
  "properties": {
    "iso:country":"GB",
    "wof:name":"PE24 4TG",
    "wof:placetype":"postalcode"
},
  "geometry": {"coordinates":[0.31571601060671,53.19292001572943],"type":"Point"}
}