{
  "type": "Feature",
  "properties": {
    "date:inception_lower": "2024-01-01",
    "date:inception_upper": "2024-01-01",
    "iso:country": "GB",
    "wof:name": "S40 1FU",
    "wof:placetype": "postalcode"
  },
  "geometry": {"coordinates":[-1.426666,53.235662],"type":"Point"}
}
