{
  "type": "Feature",
  "properties": {
    "iso:country": "GB",
    "wof:name": "TA8 2DQ",
    "wof:placetype": "postalcode"
  },
  "geometry": {"coordinates":[-2.99206,51.247217],"type":"Point"}
}
