{
  "type": "Feature",
  "properties": {
    "iso:country":"GB",
    "wof:name":"TA8 2DQ",
    "wof:placetype":"postalcode"
},
  "geometry": {"coordinates":[-2.99202264926458,51.24723081677615],"type":"Point"}
}