{
  "type": "Feature",
  "properties": {
    "iso:country":"GB",
    "wof:name":"HP3 8TA",
    "wof:placetype":"postalcode"
},
  "geometry": {"coordinates":[-0.43853529797936,51.74424752310613],"type":"Point"}
}