{
  "type": "Feature",
  "properties": {
    "iso:country":"GB",
    "wof:name":"GL4 5TD",
    "wof:placetype":"postalcode"
},
  "geometry": {"coordinates":[-2.20421582994878,51.84991427647498],"type":"Point"}
}