{
  "type": "Feature",
  "properties": {
    "date:inception_lower": "2002-12-01",
    "date:inception_upper": "2002-12-01",
    "iso:country": "GB",
    "wof:name": "GL4 5TD",
    "wof:placetype": "postalcode"
  },
  "geometry": {"coordinates":[-2.204216,51.849914],"type":"Point"}
}
