{
  "type": "Feature",
  "properties": {
    "date:inception_lower":"1980-01-01",
    "date:inception_upper":"1980-01-31",
    "iso:country":"GB",
    "wof:name":"CF36 5EA",
    "wof:placetype":"postalcode"
},
  "geometry": {"coordinates":[-3.691172,51.487885],"type":"Point"}
}