{
  "type": "Feature",
  "properties": {
    "iso:country":"GB",
    "wof:name":"CF36 5EA",
    "wof:placetype":"postalcode"
},
  "geometry": {"coordinates":[-3.69117187147658,51.4878853943941],"type":"Point"}
}