{
  "type": "Feature",
  "properties": {
    "iso:country": "GB",
    "wof:name": "PO14 4HB",
    "wof:placetype": "postalcode"
  },
  "geometry": {"coordinates":[-1.244168,50.834056],"type":"Point"}
}
