{
  "type": "Feature",
  "properties": {
    "iso:country": "GB",
    "wof:name": "SO40 7JA",
    "wof:placetype": "postalcode"
  },
  "geometry": {"coordinates":[-1.517545,50.914757],"type":"Point"}
}
