{
  "type": "Feature",
  "properties": {
    "iso:country":"GB",
    "wof:name":"SO40 7JA",
    "wof:placetype":"postalcode"
},
  "geometry": {"coordinates":[-1.51754461477944,50.91475655315301],"type":"Point"}
}