{
  "type": "Feature",
  "properties": {
    "iso:country": "GB",
    "wof:name": "GU46 6QH",
    "wof:placetype": "postalcode"
  },
  "geometry": {"coordinates":[-0.838484,51.340409],"type":"Point"}
}
