{
  "type": "Feature",
  "properties": {
    "iso:country":"GB",
    "wof:name":"BB9 0QD",
    "wof:placetype":"postalcode"
},
  "geometry": {"coordinates":[-2.21592148178802,53.82701960933333],"type":"Point"}
}