{
  "type": "Feature",
  "properties": {
    "iso:country": "GB",
    "wof:name": "BB9 0QD",
    "wof:placetype": "postalcode"
  },
  "geometry": {"coordinates":[-2.215921,53.82702],"type":"Point"}
}
