{
  "type": "Feature",
  "properties": {
    "iso:country":"GB",
    "wof:name":"MK45 2FE",
    "wof:placetype":"postalcode"
},
  "geometry": {"coordinates":[-0.45804357762619,52.02840713887142],"type":"Point"}
}