{
  "type": "Feature",
  "properties": {
    "date:inception_lower": "2008-05-01",
    "date:inception_upper": "2008-05-01",
    "iso:country": "GB",
    "wof:name": "MK45 2FE",
    "wof:placetype": "postalcode"
  },
  "geometry": {"coordinates":[-0.458044,52.028407],"type":"Point"}
}
