{
  "type": "Feature",
  "properties": {
    "iso:country":"GB",
    "wof:name":"NG4 3EZ",
    "wof:placetype":"postalcode"
},
  "geometry": {"coordinates":[-1.08333720186974,52.97038069741178],"type":"Point"}
}