{
  "type": "Feature",
  "properties": {
    "iso:country":"GB",
    "wof:name":"LL12 0ET",
    "wof:placetype":"postalcode"
},
  "geometry": {"coordinates":[-2.92913217316626,53.10418640908618],"type":"Point"}
}