{
  "type": "Feature",
  "properties": {
    "date:inception_lower":"1980-01-01",
    "date:inception_upper":"1980-01-31",
    "iso:country":"GB",
    "wof:name":"LL12 0ET",
    "wof:placetype":"postalcode"
},
  "geometry": {"coordinates":[-2.929132,53.104186],"type":"Point"}
}