{
  "type": "Feature",
  "properties": {
    "iso:country":"GB",
    "wof:name":"ME1 3HE",
    "wof:placetype":"postalcode"
},
  "geometry": {"coordinates":[0.49031842789022,51.37419242918697],"type":"Point"}
}