{
  "type": "Feature",
  "properties": {
    "date:inception_lower": "1980-01-01",
    "date:inception_upper": "1980-01-01",
    "iso:country": "GB",
    "wof:name": "OL6 7HN",
    "wof:placetype": "postalcode"
  },
  "geometry": {"coordinates":[-2.103933,53.487263],"type":"Point"}
}
