{
  "type": "Feature",
  "properties": {
    "iso:country":"GB",
    "wof:name":"OL6 7HN",
    "wof:placetype":"postalcode"
},
  "geometry": {"coordinates":[-2.10393348057921,53.48726343319331],"type":"Point"}
}