{
  "type": "Feature",
  "properties": {
    "iso:country": "GB",
    "wof:name": "DA3 8JB",
    "wof:placetype": "postalcode"
  },
  "geometry": {"coordinates":[0.30493,51.365999],"type":"Point"}
}
