{
  "type": "Feature",
  "properties": {
    "date:inception_lower": "1980-01-01",
    "date:inception_upper": "1980-01-01",
    "iso:country": "GB",
    "wof:name": "DA3 8JB",
    "wof:placetype": "postalcode"
  },
  "geometry": {"coordinates":[0.30476,51.366065],"type":"Point"}
}
