{
  "type": "Feature",
  "properties": {
    "date:inception_lower": "1980-01-01",
    "date:inception_upper": "1980-01-01",
    "iso:country": "GB",
    "wof:name": "NW2 4ER",
    "wof:placetype": "postalcode"
  },
  "geometry": {"coordinates":[-0.214325,51.548783],"type":"Point"}
}
