{
  "type": "Feature",
  "properties": {
    "iso:country":"GB",
    "wof:name":"NW2 4ER",
    "wof:placetype":"postalcode"
},
  "geometry": {"coordinates":[-0.21432481183443,51.5487825912202],"type":"Point"}
}