{
  "type": "Feature",
  "properties": {
    "iso:country": "GB",
    "wof:name": "KA20 4JF",
    "wof:placetype": "postalcode"
  },
  "geometry": {"coordinates":[-4.739364,55.647702],"type":"Point"}
}
