{
  "type": "Feature",
  "properties": {
    "iso:country":"GB",
    "wof:name":"KA20 4JF",
    "wof:placetype":"postalcode"
},
  "geometry": {"coordinates":[-4.73936423488158,55.64770204741813],"type":"Point"}
}