{
  "type": "Feature",
  "properties": {
    "iso:country":"GB",
    "wof:name":"GU8 6HU",
    "wof:placetype":"postalcode"
},
  "geometry": {"coordinates":[-0.69080858338598,51.18354527060905],"type":"Point"}
}