{
  "type": "Feature",
  "properties": {
    "iso:country":"GB",
    "wof:name":"CA14 3UW",
    "wof:placetype":"postalcode"
},
  "geometry": {"coordinates":[-3.55365558955368,54.6375343202951],"type":"Point"}
}