{
  "type": "Feature",
  "properties": {
    "iso:country":"GB",
    "wof:name":"ML3 9JN",
    "wof:placetype":"postalcode"
},
  "geometry": {"coordinates":[-4.07105461297202,55.77910678212259],"type":"Point"}
}