{
  "type": "Feature",
  "properties": {
    "iso:country":"GB",
    "wof:name":"BR6 0NR",
    "wof:placetype":"postalcode"
},
  "geometry": {"coordinates":[0.09940535397188,51.37514228948149],"type":"Point"}
}