{
  "type": "Feature",
  "properties": {
    "iso:country": "GB",
    "wof:name": "BR6 0NR",
    "wof:placetype": "postalcode"
  },
  "geometry": {"coordinates":[0.099405,51.375142],"type":"Point"}
}
