{
  "type": "Feature",
  "properties": {
    "iso:country":"GB",
    "wof:name":"PO7 6XB",
    "wof:placetype":"postalcode"
},
  "geometry": {"coordinates":[-1.04330614940944,50.88871483267832],"type":"Point"}
}