{
  "type": "Feature",
  "properties": {
    "date:inception_lower": "1980-01-01",
    "date:inception_upper": "1980-01-01",
    "iso:country": "GB",
    "wof:name": "RG9 6BN",
    "wof:placetype": "postalcode"
  },
  "geometry": {"coordinates":[-0.946573,51.572291],"type":"Point"}
}
