{
  "type": "Feature",
  "properties": {
    "iso:country":"GB",
    "wof:name":"RG9 6BN",
    "wof:placetype":"postalcode"
},
  "geometry": {"coordinates":[-0.94673358790162,51.57245134706607],"type":"Point"}
}