{
  "type": "Feature",
  "properties": {
    "iso:country":"GB",
    "wof:name":"NR33 7TR",
    "wof:placetype":"postalcode"
},
  "geometry": {"coordinates":[1.71508646036293,52.41897898706495],"type":"Point"}
}