{
  "type": "Feature",
  "properties": {
    "date:inception_lower": "2003-08-01",
    "date:inception_upper": "2003-08-01",
    "iso:country": "GB",
    "wof:name": "LU7 1RU",
    "wof:placetype": "postalcode"
  },
  "geometry": {"coordinates":[-0.659144,51.915104],"type":"Point"}
}
