{
  "type": "Feature",
  "properties": {
    "iso:country":"GB",
    "wof:name":"LU7 1RU",
    "wof:placetype":"postalcode"
},
  "geometry": {"coordinates":[-0.6591444377462,51.91510393097815],"type":"Point"}
}