{
  "type": "Feature",
  "properties": {
    "iso:country":"GB",
    "wof:name":"BH19 1AX",
    "wof:placetype":"postalcode"
},
  "geometry": {"coordinates":[-1.97470548294534,50.61183545839605],"type":"Point"}
}