{
  "type": "Feature",
  "properties": {
    "iso:country": "GB",
    "wof:name": "BH19 1AX",
    "wof:placetype": "postalcode"
  },
  "geometry": {"coordinates":[-1.974705,50.611835],"type":"Point"}
}
