{
  "type": "Feature",
  "properties": {
    "iso:country":"GB",
    "wof:name":"ME4 4RF",
    "wof:placetype":"postalcode"
},
  "geometry": {"coordinates":[0.52332849115632,51.38234454261895],"type":"Point"}
}