{
  "type": "Feature",
  "properties": {
    "date:inception_lower": "2001-06-01",
    "date:inception_upper": "2001-06-01",
    "iso:country": "GB",
    "wof:name": "ME4 4RF",
    "wof:placetype": "postalcode"
  },
  "geometry": {"coordinates":[0.523329,51.382345],"type":"Point"}
}
