{
  "type": "Feature",
  "properties": {
    "iso:country":"GB",
    "wof:name":"OX2 6HR",
    "wof:placetype":"postalcode"
},
  "geometry": {"coordinates":[-1.26373978495666,51.76393807283879],"type":"Point"}
}