{
  "type": "Feature",
  "properties": {
    "date:inception_lower":"1980-01-01",
    "date:inception_upper":"1980-01-31",
    "iso:country":"GB",
    "wof:name":"G32 8AJ",
    "wof:placetype":"postalcode"
},
  "geometry": {"coordinates":[-4.153884,55.831436],"type":"Point"}
}