{
  "type": "Feature",
  "properties": {
    "iso:country":"GB",
    "wof:name":"G32 8AJ",
    "wof:placetype":"postalcode"
},
  "geometry": {"coordinates":[-4.15388370785094,55.83143585047983],"type":"Point"}
}