{
  "type": "Feature",
  "properties": {
    "iso:country":"GB",
    "wof:name":"BA1 7EE",
    "wof:placetype":"postalcode"
},
  "geometry": {"coordinates":[-2.32084231048225,51.40880148272784],"type":"Point"}
}