{
  "type": "Feature",
  "properties": {
    "date:inception_lower": "2017-06-01",
    "date:inception_upper": "2017-06-01",
    "iso:country": "GB",
    "wof:name": "DH4 4ZL",
    "wof:placetype": "postalcode"
  },
  "geometry": {"coordinates":[-1.489136,54.863157],"type":"Point"}
}
