{
  "type": "Feature",
  "properties": {
    "iso:country":"GB",
    "wof:name":"NW10 3EP",
    "wof:placetype":"postalcode"
},
  "geometry": {"coordinates":[-0.21880915553022,51.53847355346225],"type":"Point"}
}