{
  "type": "Feature",
  "properties": {
    "iso:country": "GB",
    "wof:name": "B44 8NH",
    "wof:placetype": "postalcode"
  },
  "geometry": {"coordinates":[-1.897853,52.533858],"type":"Point"}
}
