{
  "type": "Feature",
  "properties": {
    "iso:country":"GB",
    "wof:name":"S1 2DW",
    "wof:placetype":"postalcode"
},
  "geometry": {"coordinates":[-1.46977471378822,53.38448169757724],"type":"Point"}
}