{
  "type": "Feature",
  "properties": {
    "date:inception_lower": "1980-01-01",
    "date:inception_upper": "1980-01-01",
    "iso:country": "GB",
    "wof:name": "S1 2DW",
    "wof:placetype": "postalcode"
  },
  "geometry": {"coordinates":[-1.469774,53.3845],"type":"Point"}
}
