{
  "type": "Feature",
  "properties": {
    "iso:country":"GB",
    "wof:name":"BN43 5JN",
    "wof:placetype":"postalcode"
},
  "geometry": {"coordinates":[-0.26477812891941,50.83053642343234],"type":"Point"}
}