{
  "type": "Feature",
  "properties": {
    "iso:country": "GB",
    "wof:name": "BN43 5JN",
    "wof:placetype": "postalcode"
  },
  "geometry": {"coordinates":[-0.264778,50.830536],"type":"Point"}
}
