{
  "type": "Feature",
  "properties": {
    "date:inception_lower": "1984-02-01",
    "date:inception_upper": "1984-02-01",
    "iso:country": "GB",
    "wof:name": "BD23 4PG",
    "wof:placetype": "postalcode"
  },
  "geometry": {"coordinates":[-2.255444,54.019653],"type":"Point"}
}
