{
  "type": "Feature",
  "properties": {
    "iso:country":"GB",
    "wof:name":"CF23 6HL",
    "wof:placetype":"postalcode"
},
  "geometry": {"coordinates":[-3.16833584552388,51.51063538479568],"type":"Point"}
}