{
  "type": "Feature",
  "properties": {
    "date:inception_lower": "2022-02-01",
    "date:inception_upper": "2022-02-01",
    "iso:country": "GB",
    "wof:name": "OX49 5EE",
    "wof:placetype": "postalcode"
  },
  "geometry": {"coordinates":[-0.999929,51.65068],"type":"Point"}
}
