{
  "type": "Feature",
  "properties": {
    "iso:country":"GB",
    "wof:name":"CT18 8BA",
    "wof:placetype":"postalcode"
},
  "geometry": {"coordinates":[1.1200355165352,51.09868986906175],"type":"Point"}
}