{
  "type": "Feature",
  "properties": {
    "iso:country":"GB",
    "wof:name":"W11 1TR",
    "wof:placetype":"postalcode"
},
  "geometry": {"coordinates":[-0.21433934061186,51.51525016196252],"type":"Point"}
}