{
  "type": "Feature",
  "properties": {
    "iso:country":"GB",
    "wof:name":"IP19 8AY",
    "wof:placetype":"postalcode"
},
  "geometry": {"coordinates":[1.50134840888009,52.34327327350866],"type":"Point"}
}