{
  "type": "Feature",
  "properties": {
    "iso:country":"GB",
    "wof:name":"LL42 1PW",
    "wof:placetype":"postalcode"
},
  "geometry": {"coordinates":[-4.05788641320317,52.72482658789004],"type":"Point"}
}