{
  "type": "Feature",
  "properties": {
    "date:inception_lower": "1980-01-01",
    "date:inception_upper": "1980-01-01",
    "iso:country": "GB",
    "wof:name": "SS12 9LG",
    "wof:placetype": "postalcode"
  },
  "geometry": {"coordinates":[0.531474,51.594702],"type":"Point"}
}
