{
  "type": "Feature",
  "properties": {
    "iso:country":"GB",
    "wof:name":"SS12 9LG",
    "wof:placetype":"postalcode"
},
  "geometry": {"coordinates":[0.53147431199264,51.59470191290259],"type":"Point"}
}