{
  "type": "Feature",
  "properties": {
    "iso:country": "GB",
    "wof:name": "WV11 2BE",
    "wof:placetype": "postalcode"
  },
  "geometry": {"coordinates":[-2.088274,52.635444],"type":"Point"}
}
