{
  "type": "Feature",
  "properties": {
    "iso:country":"GB",
    "wof:name":"SN10 1PL",
    "wof:placetype":"postalcode"
},
  "geometry": {"coordinates":[-2.01310420916975,51.35194577801009],"type":"Point"}
}