{
  "type": "Feature",
  "properties": {
    "iso:country":"GB",
    "wof:name":"LA19 5TP",
    "wof:placetype":"postalcode"
},
  "geometry": {"coordinates":[-3.35470378554269,54.31765915338222],"type":"Point"}
}