{
  "type": "Feature",
  "properties": {
    "date:inception_lower":"1980-01-01",
    "date:inception_upper":"1980-01-31",
    "iso:country":"GB",
    "wof:name":"LA19 5TP",
    "wof:placetype":"postalcode"
},
  "geometry": {"coordinates":[-3.354781,54.318107],"type":"Point"}
}