{
  "type": "Feature",
  "properties": {
    "iso:country": "GB",
    "wof:name": "LA19 5TP",
    "wof:placetype": "postalcode"
  },
  "geometry": {"coordinates":[-3.354781,54.318107],"type":"Point"}
}
