{
  "type": "Feature",
  "properties": {
    "date:inception_lower": "1980-01-01",
    "date:inception_upper": "1980-01-01",
    "iso:country": "GB",
    "wof:name": "LA19 5TP",
    "wof:placetype": "postalcode"
  },
  "geometry": {"coordinates":[-3.354705,54.317667],"type":"Point"}
}
