{
  "type": "Feature",
  "properties": {
    "date:inception_lower": "1980-01-01",
    "date:inception_upper": "1980-01-01",
    "iso:country": "GB",
    "wof:name": "SR7 7DU",
    "wof:placetype": "postalcode"
  },
  "geometry": {"coordinates":[-1.345657,54.838754],"type":"Point"}
}
