{
  "type": "Feature",
  "properties": {
    "iso:country":"GB",
    "wof:name":"SR7 7DU",
    "wof:placetype":"postalcode"
},
  "geometry": {"coordinates":[-1.34565687713813,54.83875385375656],"type":"Point"}
}