{
  "type": "Feature",
  "properties": {
    "date:inception_lower": "1989-10-01",
    "date:inception_upper": "1989-10-01",
    "iso:country": "GB",
    "wof:name": "ML4 3HR",
    "wof:placetype": "postalcode"
  },
  "geometry": {"coordinates":[-4.037968,55.819455],"type":"Point"}
}
