{
  "type": "Feature",
  "properties": {
    "iso:country":"GB",
    "wof:name":"ML4 3HR",
    "wof:placetype":"postalcode"
},
  "geometry": {"coordinates":[-4.03796822284619,55.81945468533449],"type":"Point"}
}