{
  "type": "Feature",
  "properties": {
    "iso:country":"GB",
    "wof:name":"DL3 6PT",
    "wof:placetype":"postalcode"
},
  "geometry": {"coordinates":[-1.56070239576771,54.53484777126259],"type":"Point"}
}