{
  "type": "Feature",
  "properties": {
    "iso:country":"GB",
    "wof:name":"M22 8AH",
    "wof:placetype":"postalcode"
},
  "geometry": {"coordinates":[-2.25728491832594,53.38897554888452],"type":"Point"}
}