{
  "type": "Feature",
  "properties": {
    "date:inception_lower": "2005-01-01",
    "date:inception_upper": "2005-01-01",
    "iso:country": "GB",
    "wof:name": "M22 8AH",
    "wof:placetype": "postalcode"
  },
  "geometry": {"coordinates":[-2.257285,53.388976],"type":"Point"}
}
