{
  "type": "Feature",
  "properties": {
    "iso:country": "GB",
    "wof:name": "SN12 8AX",
    "wof:placetype": "postalcode"
  },
  "geometry": {"coordinates":[-2.142552,51.378223],"type":"Point"}
}
