{
  "type": "Feature",
  "properties": {
    "date:inception_lower": "1980-01-01",
    "date:inception_upper": "1980-01-01",
    "iso:country": "GB",
    "wof:name": "DN12 1BY",
    "wof:placetype": "postalcode"
  },
  "geometry": {"coordinates":[-1.184925,53.488713],"type":"Point"}
}
