{
  "type": "Feature",
  "properties": {
    "iso:country": "GB",
    "wof:name": "SA3 5JY",
    "wof:placetype": "postalcode"
  },
  "geometry": {"coordinates":[-4.0099,51.589449],"type":"Point"}
}
