{
  "type": "Feature",
  "properties": {
    "iso:country":"GB",
    "wof:name":"SA3 5JY",
    "wof:placetype":"postalcode"
},
  "geometry": {"coordinates":[-4.00985143170484,51.58943582320082],"type":"Point"}
}