{
  "type": "Feature",
  "properties": {
    "date:inception_lower": "1980-01-01",
    "date:inception_upper": "1980-01-01",
    "iso:country": "GB",
    "wof:name": "SA3 5JY",
    "wof:placetype": "postalcode"
  },
  "geometry": {"coordinates":[-4.0099,51.589449],"type":"Point"}
}
