{
  "type": "Feature",
  "properties": {
    "iso:country":"GB",
    "wof:name":"TR1 1XT",
    "wof:placetype":"postalcode"
},
  "geometry": {"coordinates":[-5.04419272726961,50.26795292909174],"type":"Point"}
}