{
  "type": "Feature",
  "properties": {
    "iso:country":"GB",
    "wof:name":"HU9 1RD",
    "wof:placetype":"postalcode"
},
  "geometry": {"coordinates":[-0.30518702984801,53.74802368585032],"type":"Point"}
}