{
  "type": "Feature",
  "properties": {
    "date:inception_lower":"1997-12-01",
    "date:inception_upper":"1997-12-31",
    "iso:country":"GB",
    "wof:name":"HU9 1RD",
    "wof:placetype":"postalcode"
},
  "geometry": {"coordinates":[-0.305187,53.748024],"type":"Point"}
}