{
  "type": "Feature",
  "properties": {
    "date:inception_lower": "1994-05-01",
    "date:inception_upper": "1994-05-01",
    "iso:country": "GB",
    "wof:name": "HU17 7DD",
    "wof:placetype": "postalcode"
  },
  "geometry": {"coordinates":[-0.449587,53.852336],"type":"Point"}
}
