{
  "type": "Feature",
  "properties": {
    "iso:country":"GB",
    "wof:name":"B90 1JZ",
    "wof:placetype":"postalcode"
},
  "geometry": {"coordinates":[-1.86568143539552,52.4091708230147],"type":"Point"}
}