{
  "type": "Feature",
  "properties": {
    "iso:country": "GB",
    "wof:name": "B90 1JZ",
    "wof:placetype": "postalcode"
  },
  "geometry": {"coordinates":[-1.865681,52.409171],"type":"Point"}
}
