{
  "type": "Feature",
  "properties": {
    "iso:country":"GB",
    "wof:name":"WN6 0AS",
    "wof:placetype":"postalcode"
},
  "geometry": {"coordinates":[-2.64818967390612,53.57565080988751],"type":"Point"}
}