{
  "type": "Feature",
  "properties": {
    "iso:country": "GB",
    "wof:name": "WN6 0AS",
    "wof:placetype": "postalcode"
  },
  "geometry": {"coordinates":[-2.64819,53.575651],"type":"Point"}
}
