{
  "type": "Feature",
  "properties": {
    "iso:country": "GB",
    "wof:name": "DN35 0JW",
    "wof:placetype": "postalcode"
  },
  "geometry": {"coordinates":[-0.031325,53.548778],"type":"Point"}
}
