{
  "type": "Feature",
  "properties": {
    "iso:country":"GB",
    "wof:name":"CV32 5GB",
    "wof:placetype":"postalcode"
},
  "geometry": {"coordinates":[-1.53073770286121,52.29601069931807],"type":"Point"}
}