{
  "type": "Feature",
  "properties": {
    "date:inception_lower": "1986-07-01",
    "date:inception_upper": "1986-07-01",
    "iso:country": "GB",
    "wof:name": "CV32 5GB",
    "wof:placetype": "postalcode"
  },
  "geometry": {"coordinates":[-1.530727,52.296026],"type":"Point"}
}
