{
  "type": "Feature",
  "properties": {
    "date:inception_lower": "2005-12-01",
    "date:inception_upper": "2005-12-01",
    "iso:country": "GB",
    "wof:name": "TD6 0DN",
    "wof:placetype": "postalcode"
  },
  "geometry": {"coordinates":[-2.638527,55.569158],"type":"Point"}
}
