{
  "type": "Feature",
  "properties": {
    "iso:country":"GB",
    "wof:name":"TD6 0DN",
    "wof:placetype":"postalcode"
},
  "geometry": {"coordinates":[-2.63852673000933,55.56915819872265],"type":"Point"}
}