{
  "type": "Feature",
  "properties": {
    "iso:country": "GB",
    "wof:name": "L34 1BJ",
    "wof:placetype": "postalcode"
  },
  "geometry": {"coordinates":[-2.805045,53.422284],"type":"Point"}
}
