{
  "type": "Feature",
  "properties": {
    "date:inception_lower": "2019-04-01",
    "date:inception_upper": "2019-04-01",
    "iso:country": "GB",
    "wof:name": "L34 1BJ",
    "wof:placetype": "postalcode"
  },
  "geometry": {"coordinates":[-2.805045,53.422284],"type":"Point"}
}
