{
  "type": "Feature",
  "properties": {
    "iso:country":"GB",
    "wof:name":"LS16 8LJ",
    "wof:placetype":"postalcode"
},
  "geometry": {"coordinates":[-1.57663816392781,53.85177844048643],"type":"Point"}
}