{
  "type": "Feature",
  "properties": {
    "iso:country":"GB",
    "wof:name":"NR30 2RY",
    "wof:placetype":"postalcode"
},
  "geometry": {"coordinates":[1.72801195752319,52.60212050562281],"type":"Point"}
}