{
  "type": "Feature",
  "properties": {
    "date:inception_lower": "1980-01-01",
    "date:inception_upper": "1980-01-01",
    "iso:country": "GB",
    "wof:name": "NR30 2RY",
    "wof:placetype": "postalcode"
  },
  "geometry": {"coordinates":[1.728012,52.60212],"type":"Point"}
}
