{
  "type": "Feature",
  "properties": {
    "iso:country": "GB",
    "wof:name": "G71 8QD",
    "wof:placetype": "postalcode"
  },
  "geometry": {"coordinates":[-4.072105,55.809929],"type":"Point"}
}
