{
  "type": "Feature",
  "properties": {
    "iso:country": "GB",
    "wof:name": "CA7 5AH",
    "wof:placetype": "postalcode"
  },
  "geometry": {"coordinates":[-3.261223,54.910565],"type":"Point"}
}
