{
  "type": "Feature",
  "properties": {
    "date:inception_lower": "2000-06-01",
    "date:inception_upper": "2000-06-01",
    "iso:country": "GB",
    "wof:name": "CA7 5AH",
    "wof:placetype": "postalcode"
  },
  "geometry": {"coordinates":[-3.261223,54.910565],"type":"Point"}
}
