{
  "type": "Feature",
  "properties": {
    "date:inception_lower": "1995-07-01",
    "date:inception_upper": "1995-07-01",
    "iso:country": "GB",
    "wof:name": "M40 7FP",
    "wof:placetype": "postalcode"
  },
  "geometry": {"coordinates":[-2.212095,53.484574],"type":"Point"}
}
