{
  "type": "Feature",
  "properties": {
    "iso:country": "GB",
    "wof:name": "G78 2FF",
    "wof:placetype": "postalcode"
  },
  "geometry": {"coordinates":[-4.384774,55.7996],"type":"Point"}
}
