{
  "type": "Feature",
  "properties": {
    "iso:country":"GB",
    "wof:name":"NR31 7JT",
    "wof:placetype":"postalcode"
},
  "geometry": {"coordinates":[1.71021578452855,52.57074870069135],"type":"Point"}
}