{
  "type": "Feature",
  "properties": {
    "iso:country": "GB",
    "wof:name": "NR31 7JT",
    "wof:placetype": "postalcode"
  },
  "geometry": {"coordinates":[1.710216,52.570749],"type":"Point"}
}
