{
  "type": "Feature",
  "properties": {
    "iso:country":"GB",
    "wof:name":"TA23 0LY",
    "wof:placetype":"postalcode"
},
  "geometry": {"coordinates":[-3.36202902513943,51.14462780410125],"type":"Point"}
}