{
  "type": "Feature",
  "properties": {
    "date:inception_lower": "1980-01-01",
    "date:inception_upper": "1980-01-01",
    "iso:country": "GB",
    "wof:name": "TA23 0LY",
    "wof:placetype": "postalcode"
  },
  "geometry": {"coordinates":[-3.362091,51.144372],"type":"Point"}
}
