{
  "type": "Feature",
  "properties": {
    "iso:country":"GB",
    "wof:name":"BS16 9QS",
    "wof:placetype":"postalcode"
},
  "geometry": {"coordinates":[-2.48431797561684,51.47432808022936],"type":"Point"}
}