{
  "type": "Feature",
  "properties": {
    "iso:country":"GB",
    "wof:name":"FK8 2AN",
    "wof:placetype":"postalcode"
},
  "geometry": {"coordinates":[-3.93940618907308,56.10555727387861],"type":"Point"}
}