{
  "type": "Feature",
  "properties": {
    "iso:country":"GB",
    "wof:name":"HA3 0AH",
    "wof:placetype":"postalcode"
},
  "geometry": {"coordinates":[-0.32064053743061,51.58001785823414],"type":"Point"}
}