{
  "type": "Feature",
  "properties": {
    "iso:country": "GB",
    "wof:name": "HA3 0AH",
    "wof:placetype": "postalcode"
  },
  "geometry": {"coordinates":[-0.320618,51.58002],"type":"Point"}
}
