{
  "type": "Feature",
  "properties": {
    "date:inception_lower":"1980-01-01",
    "date:inception_upper":"1980-01-31",
    "iso:country":"GB",
    "wof:name":"WS8 7JF",
    "wof:placetype":"postalcode"
},
  "geometry": {"coordinates":[-1.939919,52.647706],"type":"Point"}
}