{
  "type": "Feature",
  "properties": {
    "iso:country": "GB",
    "wof:name": "WS8 7JF",
    "wof:placetype": "postalcode"
  },
  "geometry": {"coordinates":[-1.939919,52.647706],"type":"Point"}
}
