{
  "type": "Feature",
  "properties": {
    "iso:country":"GB",
    "wof:name":"BA13 3UZ",
    "wof:placetype":"postalcode"
},
  "geometry": {"coordinates":[-2.18709035443112,51.26843405970059],"type":"Point"}
}