{
  "type": "Feature",
  "properties": {
    "date:inception_lower": "2001-12-01",
    "date:inception_upper": "2001-12-01",
    "iso:country": "GB",
    "wof:name": "BA13 3UZ",
    "wof:placetype": "postalcode"
  },
  "geometry": {"coordinates":[-2.18709,51.268434],"type":"Point"}
}
