{
  "type": "Feature",
  "properties": {
    "date:inception_lower": "1995-07-01",
    "date:inception_upper": "1995-07-01",
    "iso:country": "GB",
    "wof:name": "RG41 5TH",
    "wof:placetype": "postalcode"
  },
  "geometry": {"coordinates":[-0.869627,51.430715],"type":"Point"}
}
