{
  "type": "Feature",
  "properties": {
    "date:inception_lower":"2004-07-01",
    "date:inception_upper":"2004-07-31",
    "iso:country":"GB",
    "wof:name":"LS27 7GH",
    "wof:placetype":"postalcode"
},
  "geometry": {"coordinates":[-1.589727,53.766132],"type":"Point"}
}