{
  "type": "Feature",
  "properties": {
    "iso:country": "GB",
    "wof:name": "LS27 7GH",
    "wof:placetype": "postalcode"
  },
  "geometry": {"coordinates":[-1.589727,53.766132],"type":"Point"}
}
