{
  "type": "Feature",
  "properties": {
    "iso:country":"GB",
    "wof:name":"LS27 7GH",
    "wof:placetype":"postalcode"
},
  "geometry": {"coordinates":[-1.58972703675048,53.76613220682608],"type":"Point"}
}