{
  "type": "Feature",
  "properties": {
    "iso:country":"GB",
    "wof:name":"S20 5BE",
    "wof:placetype":"postalcode"
},
  "geometry": {"coordinates":[-1.36850367792551,53.32439358721717],"type":"Point"}
}