{
  "type": "Feature",
  "properties": {
    "iso:country":"GB",
    "wof:name":"BN3 5AH",
    "wof:placetype":"postalcode"
},
  "geometry": {"coordinates":[-0.17944384257693,50.83573831788503],"type":"Point"}
}