{
  "type": "Feature",
  "properties": {
    "iso:country": "GB",
    "wof:name": "LL18 2SB",
    "wof:placetype": "postalcode"
  },
  "geometry": {"coordinates":[-3.464441,53.295668],"type":"Point"}
}
