{
  "type": "Feature",
  "properties": {
    "iso:country":"GB",
    "wof:name":"SA15 1DD",
    "wof:placetype":"postalcode"
},
  "geometry": {"coordinates":[-4.15492482934509,51.67538509552488],"type":"Point"}
}