{
  "type": "Feature",
  "properties": {
    "iso:country": "GB",
    "wof:name": "SA15 1DD",
    "wof:placetype": "postalcode"
  },
  "geometry": {"coordinates":[-4.154925,51.675385],"type":"Point"}
}
