{
  "type": "Feature",
  "properties": {
    "date:inception_lower": "1980-01-01",
    "date:inception_upper": "1980-01-01",
    "iso:country": "GB",
    "wof:name": "B70 6EG",
    "wof:placetype": "postalcode"
  },
  "geometry": {"coordinates":[-1.988494,52.508676],"type":"Point"}
}
