{
  "type": "Feature",
  "properties": {
    "iso:country":"GB",
    "wof:name":"B70 6EG",
    "wof:placetype":"postalcode"
},
  "geometry": {"coordinates":[-1.98849355450895,52.50867557191938],"type":"Point"}
}