{
  "type": "Feature",
  "properties": {
    "iso:country":"GB",
    "wof:name":"B5 6JX",
    "wof:placetype":"postalcode"
},
  "geometry": {"coordinates":[-1.89016240173454,52.47253973869731],"type":"Point"}
}