{
  "type": "Feature",
  "properties": {
    "iso:country":"GB",
    "wof:name":"GL8 8XF",
    "wof:placetype":"postalcode"
},
  "geometry": {"coordinates":[-2.15022037780115,51.61749460598561],"type":"Point"}
}