{
  "type": "Feature",
  "properties": {
    "date:inception_lower":"1980-01-01",
    "date:inception_upper":"1980-01-31",
    "iso:country":"GB",
    "wof:name":"SA18 1RW",
    "wof:placetype":"postalcode"
},
  "geometry": {"coordinates":[-3.879968,51.771696],"type":"Point"}
}