{
  "type": "Feature",
  "properties": {
    "iso:country":"GB",
    "wof:name":"SA18 1RW",
    "wof:placetype":"postalcode"
},
  "geometry": {"coordinates":[-3.87996827146244,51.77169564497917],"type":"Point"}
}