{
  "type": "Feature",
  "properties": {
    "iso:country":"GB",
    "wof:name":"TA19 0DG",
    "wof:placetype":"postalcode"
},
  "geometry": {"coordinates":[-2.91038781239829,50.92747934571989],"type":"Point"}
}