{
  "type": "Feature",
  "properties": {
    "iso:country":"GB",
    "wof:name":"PE6 7XE",
    "wof:placetype":"postalcode"
},
  "geometry": {"coordinates":[-0.19122226710678,52.60752113018388],"type":"Point"}
}