{
  "type": "Feature",
  "properties": {
    "iso:country":"GB",
    "wof:name":"CH66 2PS",
    "wof:placetype":"postalcode"
},
  "geometry": {"coordinates":[-2.91139688309807,53.25989077901329],"type":"Point"}
}