{
  "type": "Feature",
  "properties": {
    "iso:country": "GB",
    "wof:name": "TR14 0TH",
    "wof:placetype": "postalcode"
  },
  "geometry": {"coordinates":[-5.301829,50.243739],"type":"Point"}
}
