{
  "type": "Feature",
  "properties": {
    "date:inception_lower":"1998-06-01",
    "date:inception_upper":"1998-06-30",
    "iso:country":"GB",
    "wof:name":"TR14 0TH",
    "wof:placetype":"postalcode"
},
  "geometry": {"coordinates":[-5.301829,50.243739],"type":"Point"}
}