{
  "type": "Feature",
  "properties": {
    "iso:country":"GB",
    "wof:name":"CA3 8SY",
    "wof:placetype":"postalcode"
},
  "geometry": {"coordinates":[-2.93882401227703,54.89552264125665],"type":"Point"}
}