{
  "type": "Feature",
  "properties": {
    "date:inception_lower": "1980-01-01",
    "date:inception_upper": "1980-01-01",
    "iso:country": "GB",
    "wof:name": "CA3 8SY",
    "wof:placetype": "postalcode"
  },
  "geometry": {"coordinates":[-2.938828,54.895538],"type":"Point"}
}
