{
  "type": "Feature",
  "properties": {
    "iso:country": "GB",
    "wof:name": "CA3 8SY",
    "wof:placetype": "postalcode"
  },
  "geometry": {"coordinates":[-2.938828,54.895538],"type":"Point"}
}
