{
  "type": "Feature",
  "properties": {
    "iso:country":"GB",
    "wof:name":"DG2 8EN",
    "wof:placetype":"postalcode"
},
  "geometry": {"coordinates":[-3.57691677982019,54.92410940135044],"type":"Point"}
}