{
  "type": "Feature",
  "properties": {
    "date:inception_lower":"2008-08-01",
    "date:inception_upper":"2008-08-31",
    "iso:country":"GB",
    "wof:name":"DG2 8EN",
    "wof:placetype":"postalcode"
},
  "geometry": {"coordinates":[-3.576915,54.924116],"type":"Point"}
}