{
  "type": "Feature",
  "properties": {
    "iso:country":"GB",
    "wof:name":"SS5 6ET",
    "wof:placetype":"postalcode"
},
  "geometry": {"coordinates":[0.61283519266819,51.62277638216155],"type":"Point"}
}