{
  "type": "Feature",
  "properties": {
    "iso:country": "GB",
    "wof:name": "SS5 6ET",
    "wof:placetype": "postalcode"
  },
  "geometry": {"coordinates":[0.612862,51.622782],"type":"Point"}
}
