{
  "type": "Feature",
  "properties": {
    "iso:country":"GB",
    "wof:name":"PL2 1AF",
    "wof:placetype":"postalcode"
},
  "geometry": {"coordinates":[-4.17106791459588,50.3792894806092],"type":"Point"}
}