{
  "type": "Feature",
  "properties": {
    "date:inception_lower": "1980-01-01",
    "date:inception_upper": "1980-01-01",
    "iso:country": "GB",
    "wof:name": "PL2 1AF",
    "wof:placetype": "postalcode"
  },
  "geometry": {"coordinates":[-4.171167,50.379274],"type":"Point"}
}
