{
  "type": "Feature",
  "properties": {
    "iso:country":"GB",
    "wof:name":"NE3 5PA",
    "wof:placetype":"postalcode"
},
  "geometry": {"coordinates":[-1.62857237935622,55.02775328067226],"type":"Point"}
}