{
  "type": "Feature",
  "properties": {
    "date:inception_lower": "1980-01-01",
    "date:inception_upper": "1980-01-01",
    "iso:country": "GB",
    "wof:name": "DL5 5RL",
    "wof:placetype": "postalcode"
  },
  "geometry": {"coordinates":[-1.561585,54.622608],"type":"Point"}
}
