{
  "type": "Feature",
  "properties": {
    "iso:country":"GB",
    "wof:name":"DL5 5RL",
    "wof:placetype":"postalcode"
},
  "geometry": {"coordinates":[-1.56158549221726,54.62260774255086],"type":"Point"}
}