{
  "type": "Feature",
  "properties": {
    "iso:country": "GB",
    "wof:name": "DL5 5RL",
    "wof:placetype": "postalcode"
  },
  "geometry": {"coordinates":[-1.561585,54.622608],"type":"Point"}
}
