{
  "type": "Feature",
  "properties": {
    "date:inception_lower": "2008-06-01",
    "date:inception_upper": "2008-06-01",
    "iso:country": "GB",
    "wof:name": "BN3 7AU",
    "wof:placetype": "postalcode"
  },
  "geometry": {"coordinates":[-0.174294,50.84323],"type":"Point"}
}
