{
  "type": "Feature",
  "properties": {
    "iso:country":"GB",
    "wof:name":"WA10 6TP",
    "wof:placetype":"postalcode"
},
  "geometry": {"coordinates":[-2.75520696708367,53.46216194870065],"type":"Point"}
}