{
  "type": "Feature",
  "properties": {
    "iso:country":"GB",
    "wof:name":"SW6 6QE",
    "wof:placetype":"postalcode"
},
  "geometry": {"coordinates":[-0.21363539229611,51.47539389949151],"type":"Point"}
}