{
  "type": "Feature",
  "properties": {
    "iso:country": "GB",
    "wof:name": "EH54 7BN",
    "wof:placetype": "postalcode"
  },
  "geometry": {"coordinates":[-3.551761,55.883479],"type":"Point"}
}
