{
  "type": "Feature",
  "properties": {
    "iso:country": "GB",
    "wof:name": "NG22 0HN",
    "wof:placetype": "postalcode"
  },
  "geometry": {"coordinates":[-0.898337,53.211116],"type":"Point"}
}
