{
  "type": "Feature",
  "properties": {
    "iso:country":"GB",
    "wof:name":"NG22 0HN",
    "wof:placetype":"postalcode"
},
  "geometry": {"coordinates":[-0.89829435018615,53.21108585710446],"type":"Point"}
}