{
  "type": "Feature",
  "properties": {
    "date:inception_lower": "2001-06-01",
    "date:inception_upper": "2001-06-01",
    "iso:country": "GB",
    "wof:name": "NG22 0HN",
    "wof:placetype": "postalcode"
  },
  "geometry": {"coordinates":[-0.898337,53.211116],"type":"Point"}
}
