{
  "type": "Feature",
  "properties": {
    "iso:country":"GB",
    "wof:name":"BS1 3RJ",
    "wof:placetype":"postalcode"
},
  "geometry": {"coordinates":[-2.58952825937022,51.46336191625207],"type":"Point"}
}