{
  "type": "Feature",
  "properties": {
    "iso:country":"GB",
    "wof:name":"PL24 2JD",
    "wof:placetype":"postalcode"
},
  "geometry": {"coordinates":[-4.70996875144749,50.35125266456195],"type":"Point"}
}