{
  "type": "Feature",
  "properties": {
    "date:inception_lower": "1991-01-01",
    "date:inception_upper": "1991-01-01",
    "iso:country": "GB",
    "wof:name": "CV37 9EF",
    "wof:placetype": "postalcode"
  },
  "geometry": {"coordinates":[-1.731356,52.201699],"type":"Point"}
}
