{
  "type": "Feature",
  "properties": {
    "iso:country": "GB",
    "wof:name": "CF11 8FJ",
    "wof:placetype": "postalcode"
  },
  "geometry": {"coordinates":[-3.22135,51.479541],"type":"Point"}
}
