{
  "type": "Feature",
  "properties": {
    "iso:country": "GB",
    "wof:name": "SA8 4JX",
    "wof:placetype": "postalcode"
  },
  "geometry": {"coordinates":[-3.851205,51.725474],"type":"Point"}
}
