{
  "type": "Feature",
  "properties": {
    "date:inception_lower":"1980-01-01",
    "date:inception_upper":"1980-01-31",
    "iso:country":"GB",
    "wof:name":"SA8 4JX",
    "wof:placetype":"postalcode"
},
  "geometry": {"coordinates":[-3.851205,51.725474],"type":"Point"}
}