{
  "type": "Feature",
  "properties": {
    "iso:country": "GB",
    "wof:name": "IV17 0PE",
    "wof:placetype": "postalcode"
  },
  "geometry": {"coordinates":[-4.26023,57.693469],"type":"Point"}
}
