{
  "type": "Feature",
  "properties": {
    "date:inception_lower": "1996-06-01",
    "date:inception_upper": "1996-06-01",
    "iso:country": "GB",
    "wof:name": "IV17 0PE",
    "wof:placetype": "postalcode"
  },
  "geometry": {"coordinates":[-4.26023,57.693469],"type":"Point"}
}
