{
  "type": "Feature",
  "properties": {
    "iso:country":"GB",
    "wof:name":"LE18 3XF",
    "wof:placetype":"postalcode"
},
  "geometry": {"coordinates":[-1.09579608976335,52.58278181519292],"type":"Point"}
}