{
  "type": "Feature",
  "properties": {
    "date:inception_lower": "2023-05-01",
    "date:inception_upper": "2023-05-01",
    "iso:country": "GB",
    "wof:name": "SK8 3TB",
    "wof:placetype": "postalcode"
  },
  "geometry": {"coordinates":[-2.214471,53.364017],"type":"Point"}
}
