{
  "type": "Feature",
  "properties": {
    "date:inception_lower": "2009-01-01",
    "date:inception_upper": "2009-01-01",
    "iso:country": "GB",
    "wof:name": "GL20 5GD",
    "wof:placetype": "postalcode"
  },
  "geometry": {"coordinates":[-2.149999,52.002076],"type":"Point"}
}
