{
  "type": "Feature",
  "properties": {
    "iso:country": "GB",
    "wof:name": "RH10 8JR",
    "wof:placetype": "postalcode"
  },
  "geometry": {"coordinates":[-0.179329,51.12458],"type":"Point"}
}
