{
  "type": "Feature",
  "properties": {
    "iso:country":"GB",
    "wof:name":"RH10 8JR",
    "wof:placetype":"postalcode"
},
  "geometry": {"coordinates":[-0.17932915665669,51.12458026686429],"type":"Point"}
}