{
  "type": "Feature",
  "properties": {
    "iso:country": "GB",
    "wof:name": "CW9 7XS",
    "wof:placetype": "postalcode"
  },
  "geometry": {"coordinates":[-2.472592,53.251263],"type":"Point"}
}
