{
  "type": "Feature",
  "properties": {
    "iso:country":"GB",
    "wof:name":"CW9 7XS",
    "wof:placetype":"postalcode"
},
  "geometry": {"coordinates":[-2.47217342761377,53.25120401825069],"type":"Point"}
}