{
  "type": "Feature",
  "properties": {
    "date:inception_lower": "2015-07-01",
    "date:inception_upper": "2015-07-01",
    "iso:country": "GB",
    "wof:name": "CW9 7XS",
    "wof:placetype": "postalcode"
  },
  "geometry": {"coordinates":[-2.472592,53.251263],"type":"Point"}
}
