{
  "type": "Feature",
  "properties": {
    "iso:country":"GB",
    "wof:name":"HX2 7JS",
    "wof:placetype":"postalcode"
},
  "geometry": {"coordinates":[-1.89642731919547,53.71600632873059],"type":"Point"}
}