{
  "type": "Feature",
  "properties": {
    "date:inception_lower": "1980-01-01",
    "date:inception_upper": "1980-01-01",
    "iso:country": "GB",
    "wof:name": "HX2 7JS",
    "wof:placetype": "postalcode"
  },
  "geometry": {"coordinates":[-1.896429,53.716021],"type":"Point"}
}
