{
  "type": "Feature",
  "properties": {
    "iso:country":"GB",
    "wof:name":"PA4 8SY",
    "wof:placetype":"postalcode"
},
  "geometry": {"coordinates":[-4.38999639198373,55.88659010532707],"type":"Point"}
}