{
  "type": "Feature",
  "properties": {
    "date:inception_lower":"2001-12-01",
    "date:inception_upper":"2001-12-31",
    "iso:country":"GB",
    "wof:name":"TR1 1JG",
    "wof:placetype":"postalcode"
},
  "geometry": {"coordinates":[-5.044814,50.267136],"type":"Point"}
}