{
  "type": "Feature",
  "properties": {
    "iso:country":"GB",
    "wof:name":"M5 4TJ",
    "wof:placetype":"postalcode"
},
  "geometry": {"coordinates":[-2.26526619519754,53.47546373680861],"type":"Point"}
}