{
  "type": "Feature",
  "properties": {
    "iso:country":"GB",
    "wof:name":"M31 4LF",
    "wof:placetype":"postalcode"
},
  "geometry": {"coordinates":[-2.4399553227881,53.41216278881035],"type":"Point"}
}