{
  "type": "Feature",
  "properties": {
    "iso:country": "GB",
    "wof:name": "G5 9PS",
    "wof:placetype": "postalcode"
  },
  "geometry": {"coordinates":[-4.252422,55.851514],"type":"Point"}
}
