{
  "type": "Feature",
  "properties": {
    "iso:country":"GB",
    "wof:name":"G5 9PS",
    "wof:placetype":"postalcode"
},
  "geometry": {"coordinates":[-4.25213293287222,55.85124553524921],"type":"Point"}
}