{
  "type": "Feature",
  "properties": {
    "iso:country":"GB",
    "wof:name":"LE3 6AT",
    "wof:placetype":"postalcode"
},
  "geometry": {"coordinates":[-1.15406229852509,52.63502169953409],"type":"Point"}
}