{
  "type": "Feature",
  "properties": {
    "date:inception_lower":"1980-01-01",
    "date:inception_upper":"1980-01-31",
    "iso:country":"GB",
    "wof:name":"ST16 3NF",
    "wof:placetype":"postalcode"
},
  "geometry": {"coordinates":[-2.116881,52.813375],"type":"Point"}
}