{
  "type": "Feature",
  "properties": {
    "iso:country":"GB",
    "wof:name":"B61 7EQ",
    "wof:placetype":"postalcode"
},
  "geometry": {"coordinates":[-2.07952435378745,52.3328487677574],"type":"Point"}
}