{
  "type": "Feature",
  "properties": {
    "date:inception_lower": "1980-01-01",
    "date:inception_upper": "1980-01-01",
    "iso:country": "GB",
    "wof:name": "B61 7EQ",
    "wof:placetype": "postalcode"
  },
  "geometry": {"coordinates":[-2.079518,52.332862],"type":"Point"}
}
