{
  "type": "Feature",
  "properties": {
    "date:inception_lower": "1984-02-01",
    "date:inception_upper": "1984-02-01",
    "iso:country": "GB",
    "wof:name": "NN16 8AE",
    "wof:placetype": "postalcode"
  },
  "geometry": {"coordinates":[-0.721426,52.401554],"type":"Point"}
}
