{
  "type": "Feature",
  "properties": {
    "date:inception_lower": "2023-07-01",
    "date:inception_upper": "2023-07-01",
    "iso:country": "GB",
    "wof:name": "HA2 0WQ",
    "wof:placetype": "postalcode"
  },
  "geometry": {"coordinates":[-0.349639,51.569775],"type":"Point"}
}
