{
  "type": "Feature",
  "properties": {
    "iso:country":"GB",
    "wof:name":"UB3 4JN",
    "wof:placetype":"postalcode"
},
  "geometry": {"coordinates":[-0.42477743996773,51.4980234020056],"type":"Point"}
}