{
  "type": "Feature",
  "properties": {
    "date:inception_lower": "2006-10-01",
    "date:inception_upper": "2006-10-01",
    "iso:country": "GB",
    "wof:name": "CR8 2JZ",
    "wof:placetype": "postalcode"
  },
  "geometry": {"coordinates":[-0.124732,51.34318],"type":"Point"}
}
