{
  "type": "Feature",
  "properties": {
    "iso:country":"GB",
    "wof:name":"CR8 2JZ",
    "wof:placetype":"postalcode"
},
  "geometry": {"coordinates":[-0.12473235670053,51.3431803969608],"type":"Point"}
}