{
  "type": "Feature",
  "properties": {
    "date:inception_lower": "1980-01-01",
    "date:inception_upper": "1980-01-01",
    "iso:country": "GB",
    "wof:name": "DN4 0SB",
    "wof:placetype": "postalcode"
  },
  "geometry": {"coordinates":[-1.167197,53.504157],"type":"Point"}
}
