{
  "type": "Feature",
  "properties": {
    "iso:country":"GB",
    "wof:name":"DE4 2AB",
    "wof:placetype":"postalcode"
},
  "geometry": {"coordinates":[-1.64142286409765,53.1423233840698],"type":"Point"}
}