{
  "type": "Feature",
  "properties": {
    "date:inception_lower": "2001-06-01",
    "date:inception_upper": "2001-06-01",
    "iso:country": "GB",
    "wof:name": "DE4 2AB",
    "wof:placetype": "postalcode"
  },
  "geometry": {"coordinates":[-1.641423,53.142323],"type":"Point"}
}
