{
  "type": "Feature",
  "properties": {
    "iso:country":"GB",
    "wof:name":"SR8 4NU",
    "wof:placetype":"postalcode"
},
  "geometry": {"coordinates":[-1.32027138265413,54.76585845106511],"type":"Point"}
}