{
  "type": "Feature",
  "properties": {
    "iso:country": "GB",
    "wof:name": "SR8 4NU",
    "wof:placetype": "postalcode"
  },
  "geometry": {"coordinates":[-1.31983,54.763358],"type":"Point"}
}
