{
  "type": "Feature",
  "properties": {
    "date:inception_lower": "1980-01-01",
    "date:inception_upper": "1980-01-01",
    "iso:country": "GB",
    "wof:name": "SR8 4NU",
    "wof:placetype": "postalcode"
  },
  "geometry": {"coordinates":[-1.31983,54.763358],"type":"Point"}
}
