{
  "type": "Feature",
  "properties": {
    "iso:country":"GB",
    "wof:name":"B9 5LU",
    "wof:placetype":"postalcode"
},
  "geometry": {"coordinates":[-1.84588509020549,52.47945767340281],"type":"Point"}
}