{
  "type": "Feature",
  "properties": {
    "date:inception_lower": "1980-01-01",
    "date:inception_upper": "1980-01-01",
    "iso:country": "GB",
    "wof:name": "B9 5LU",
    "wof:placetype": "postalcode"
  },
  "geometry": {"coordinates":[-1.845885,52.479458],"type":"Point"}
}
