{
  "type": "Feature",
  "properties": {
    "iso:country":"GB",
    "wof:name":"NR5 8XJ",
    "wof:placetype":"postalcode"
},
  "geometry": {"coordinates":[1.2444968733706,52.64136860371683],"type":"Point"}
}