{
  "type": "Feature",
  "properties": {
    "iso:country":"GB",
    "wof:name":"DH7 7AW",
    "wof:placetype":"postalcode"
},
  "geometry": {"coordinates":[-1.62488655053122,54.78201893502375],"type":"Point"}
}