{
  "type": "Feature",
  "properties": {
    "date:inception_lower":"1994-05-01",
    "date:inception_upper":"1994-05-31",
    "iso:country":"GB",
    "wof:name":"DH7 7AW",
    "wof:placetype":"postalcode"
},
  "geometry": {"coordinates":[-1.624759,54.781857],"type":"Point"}
}