{
  "type": "Feature",
  "properties": {
    "iso:country": "GB",
    "wof:name": "PR7 5HL",
    "wof:placetype": "postalcode"
  },
  "geometry": {"coordinates":[-2.679195,53.62461],"type":"Point"}
}
