{
  "type": "Feature",
  "properties": {
    "iso:country":"GB",
    "wof:name":"PR3 2AG",
    "wof:placetype":"postalcode"
},
  "geometry": {"coordinates":[-2.60958777680636,53.82916969366334],"type":"Point"}
}