{
  "type": "Feature",
  "properties": {
    "date:inception_lower":"2009-10-01",
    "date:inception_upper":"2009-10-31",
    "iso:country":"GB",
    "wof:name":"PR3 2AG",
    "wof:placetype":"postalcode"
},
  "geometry": {"coordinates":[-2.609587,53.829184],"type":"Point"}
}