{
  "type": "Feature",
  "properties": {
    "iso:country":"GB",
    "wof:name":"EX22 7JX",
    "wof:placetype":"postalcode"
},
  "geometry": {"coordinates":[-4.4344376805988,50.83279698030002],"type":"Point"}
}