{
  "type": "Feature",
  "properties": {
    "iso:country": "GB",
    "wof:name": "MK43 7RQ",
    "wof:placetype": "postalcode"
  },
  "geometry": {"coordinates":[-0.522586,52.17429],"type":"Point"}
}
