{
  "type": "Feature",
  "properties": {
    "iso:country":"GB",
    "wof:name":"MK43 7RQ",
    "wof:placetype":"postalcode"
},
  "geometry": {"coordinates":[-0.52258636228516,52.17429026462131],"type":"Point"}
}