{
  "type": "Feature",
  "properties": {
    "iso:country": "GB",
    "wof:name": "W13 0EB",
    "wof:placetype": "postalcode"
  },
  "geometry": {"coordinates":[-0.326005,51.518066],"type":"Point"}
}
