{
  "type": "Feature",
  "properties": {
    "iso:country":"GB",
    "wof:name":"W13 0EB",
    "wof:placetype":"postalcode"
},
  "geometry": {"coordinates":[-0.32600458465374,51.51806592148608],"type":"Point"}
}