{
  "type": "Feature",
  "properties": {
    "iso:country": "GB",
    "wof:name": "LE10 0QN",
    "wof:placetype": "postalcode"
  },
  "geometry": {"coordinates":[-1.379011,52.53525],"type":"Point"}
}
