{
  "type": "Feature",
  "properties": {
    "iso:country":"GB",
    "wof:name":"LE10 0QN",
    "wof:placetype":"postalcode"
},
  "geometry": {"coordinates":[-1.37901092472832,52.53524997562949],"type":"Point"}
}