{
  "type": "Feature",
  "properties": {
    "iso:country":"GB",
    "wof:name":"UB1 1PG",
    "wof:placetype":"postalcode"
},
  "geometry": {"coordinates":[-0.38656368177284,51.51290768116316],"type":"Point"}
}