{
  "type": "Feature",
  "properties": {
    "iso:country": "GB",
    "wof:name": "DA4 9EW",
    "wof:placetype": "postalcode"
  },
  "geometry": {"coordinates":[0.239473,51.402441],"type":"Point"}
}
