{
  "type": "Feature",
  "properties": {
    "iso:country": "GB",
    "wof:name": "IP12 4TQ",
    "wof:placetype": "postalcode"
  },
  "geometry": {"coordinates":[1.273516,52.073326],"type":"Point"}
}
