{
  "type": "Feature",
  "properties": {
    "iso:country":"GB",
    "wof:name":"IP12 4TQ",
    "wof:placetype":"postalcode"
},
  "geometry": {"coordinates":[1.27351603121428,52.07332620872815],"type":"Point"}
}