{
  "type": "Feature",
  "properties": {
    "iso:country":"GB",
    "wof:name":"ME7 2RP",
    "wof:placetype":"postalcode"
},
  "geometry": {"coordinates":[0.57071283735714,51.39078439427522],"type":"Point"}
}