{
  "type": "Feature",
  "properties": {
    "iso:country":"GB",
    "wof:name":"NR20 4EA",
    "wof:placetype":"postalcode"
},
  "geometry": {"coordinates":[0.9107290578543,52.71265170185753],"type":"Point"}
}