{
  "type": "Feature",
  "properties": {
    "iso:country": "GB",
    "wof:name": "NR20 4EA",
    "wof:placetype": "postalcode"
  },
  "geometry": {"coordinates":[0.910729,52.712652],"type":"Point"}
}
