{
  "type": "Feature",
  "properties": {
    "iso:country": "GB",
    "wof:name": "BH18 8JN",
    "wof:placetype": "postalcode"
  },
  "geometry": {"coordinates":[-1.996503,50.752718],"type":"Point"}
}
