{
  "type": "Feature",
  "properties": {
    "iso:country":"GB",
    "wof:name":"BH18 8JN",
    "wof:placetype":"postalcode"
},
  "geometry": {"coordinates":[-1.99650331119937,50.75271820785387],"type":"Point"}
}