{
  "type": "Feature",
  "properties": {
    "iso:country":"GB",
    "wof:name":"DA14 6PY",
    "wof:placetype":"postalcode"
},
  "geometry": {"coordinates":[0.08875406187143,51.42743775999271],"type":"Point"}
}