{
  "type": "Feature",
  "properties": {
    "iso:country": "GB",
    "wof:name": "DA14 6PY",
    "wof:placetype": "postalcode"
  },
  "geometry": {"coordinates":[0.088754,51.427438],"type":"Point"}
}
