{
  "type": "Feature",
  "properties": {
    "date:inception_lower":"1980-01-01",
    "date:inception_upper":"1980-01-31",
    "iso:country":"GB",
    "wof:name":"DA14 6PY",
    "wof:placetype":"postalcode"
},
  "geometry": {"coordinates":[0.088754,51.427438],"type":"Point"}
}