{
  "type": "Feature",
  "properties": {
    "iso:country": "GB",
    "wof:name": "PE30 4JE",
    "wof:placetype": "postalcode"
  },
  "geometry": {"coordinates":[0.413293,52.744911],"type":"Point"}
}
