{
  "type": "Feature",
  "properties": {
    "date:inception_lower": "2007-04-01",
    "date:inception_upper": "2007-04-01",
    "iso:country": "GB",
    "wof:name": "PE30 4JE",
    "wof:placetype": "postalcode"
  },
  "geometry": {"coordinates":[0.413293,52.744911],"type":"Point"}
}
