{
  "type": "Feature",
  "properties": {
    "iso:country":"GB",
    "wof:name":"PL14 6LS",
    "wof:placetype":"postalcode"
},
  "geometry": {"coordinates":[-4.51627353526609,50.45724911832819],"type":"Point"}
}