{
  "type": "Feature",
  "properties": {
    "date:inception_lower": "1980-01-01",
    "date:inception_upper": "1980-01-01",
    "iso:country": "GB",
    "wof:name": "CH6 5QJ",
    "wof:placetype": "postalcode"
  },
  "geometry": {"coordinates":[-3.13123,53.240074],"type":"Point"}
}
