{
  "type": "Feature",
  "properties": {
    "iso:country": "GB",
    "wof:name": "CH6 5QJ",
    "wof:placetype": "postalcode"
  },
  "geometry": {"coordinates":[-3.13123,53.240074],"type":"Point"}
}
