{
  "type": "Feature",
  "properties": {
    "iso:country":"GB",
    "wof:name":"CH6 5QJ",
    "wof:placetype":"postalcode"
},
  "geometry": {"coordinates":[-3.13123002089846,53.24007351570056],"type":"Point"}
}