{
  "type": "Feature",
  "properties": {
    "iso:country": "GB",
    "wof:name": "EH4 5AU",
    "wof:placetype": "postalcode"
  },
  "geometry": {"coordinates":[-3.269456,55.964614],"type":"Point"}
}
