{
  "type": "Feature",
  "properties": {
    "iso:country":"GB",
    "wof:name":"EH4 5AU",
    "wof:placetype":"postalcode"
},
  "geometry": {"coordinates":[-3.26945626659546,55.96461921618914],"type":"Point"}
}