{
  "type": "Feature",
  "properties": {
    "date:inception_lower":"2008-02-01",
    "date:inception_upper":"2008-02-29",
    "iso:country":"GB",
    "wof:name":"DL1 4EA",
    "wof:placetype":"postalcode"
},
  "geometry": {"coordinates":[-1.532752,54.515394],"type":"Point"}
}