{
  "type": "Feature",
  "properties": {
    "iso:country":"GB",
    "wof:name":"BR2 7EG",
    "wof:placetype":"postalcode"
},
  "geometry": {"coordinates":[0.01722240291526,51.37008441620122],"type":"Point"}
}