{
  "type": "Feature",
  "properties": {
    "iso:country":"GB",
    "wof:name":"BR3 1SN",
    "wof:placetype":"postalcode"
},
  "geometry": {"coordinates":[-0.02841013349662,51.41650877260862],"type":"Point"}
}