{
  "type": "Feature",
  "properties": {
    "date:inception_lower": "1992-08-01",
    "date:inception_upper": "1992-08-01",
    "iso:country": "GB",
    "wof:name": "BR3 1SN",
    "wof:placetype": "postalcode"
  },
  "geometry": {"coordinates":[-0.02841,51.416509],"type":"Point"}
}
