{
  "type": "Feature",
  "properties": {
    "iso:country":"GB",
    "wof:name":"SA44 6NR",
    "wof:placetype":"postalcode"
},
  "geometry": {"coordinates":[-4.35029818024165,52.19496988037002],"type":"Point"}
}