{
  "type": "Feature",
  "properties": {
    "iso:country":"GB",
    "wof:name":"TW7 5AD",
    "wof:placetype":"postalcode"
},
  "geometry": {"coordinates":[-0.33495207354518,51.4754527758668],"type":"Point"}
}