{
  "type": "Feature",
  "properties": {
    "iso:country":"GB",
    "wof:name":"MK45 1FJ",
    "wof:placetype":"postalcode"
},
  "geometry": {"coordinates":[-0.49985091308239,52.01180024728922],"type":"Point"}
}