{
  "type": "Feature",
  "properties": {
    "iso:country":"GB",
    "wof:name":"SL3 7UF",
    "wof:placetype":"postalcode"
},
  "geometry": {"coordinates":[-0.55562126201497,51.50158698499087],"type":"Point"}
}