{
  "type": "Feature",
  "properties": {
    "iso:country":"GB",
    "wof:name":"G67 4BU",
    "wof:placetype":"postalcode"
},
  "geometry": {"coordinates":[-4.02620740150877,55.93519413189203],"type":"Point"}
}