{
  "type": "Feature",
  "properties": {
    "date:inception_lower": "1980-01-01",
    "date:inception_upper": "1980-01-01",
    "iso:country": "GB",
    "wof:name": "G67 4BU",
    "wof:placetype": "postalcode"
  },
  "geometry": {"coordinates":[-4.026207,55.935194],"type":"Point"}
}
