{
  "type": "Feature",
  "properties": {
    "iso:country": "GB",
    "wof:name": "GU31 4FR",
    "wof:placetype": "postalcode"
  },
  "geometry": {"coordinates":[-0.937467,50.999383],"type":"Point"}
}
