{
  "type": "Feature",
  "properties": {
    "iso:country":"GB",
    "wof:name":"BB3 2AB",
    "wof:placetype":"postalcode"
},
  "geometry": {"coordinates":[-2.46508688537681,53.69353065754319],"type":"Point"}
}