{
  "type": "Feature",
  "properties": {
    "date:inception_lower": "1980-01-01",
    "date:inception_upper": "1980-01-01",
    "iso:country": "GB",
    "wof:name": "SA18 3QT",
    "wof:placetype": "postalcode"
  },
  "geometry": {"coordinates":[-4.024392,51.774952],"type":"Point"}
}
