{
  "type": "Feature",
  "properties": {
    "iso:country":"GB",
    "wof:name":"SA18 3QT",
    "wof:placetype":"postalcode"
},
  "geometry": {"coordinates":[-4.02439186382971,51.77495241666337],"type":"Point"}
}