{
  "type": "Feature",
  "properties": {
    "iso:country":"GB",
    "wof:name":"NW3 1LN",
    "wof:placetype":"postalcode"
},
  "geometry": {"coordinates":[-0.17580861287128,51.55831551251951],"type":"Point"}
}