{
  "type": "Feature",
  "properties": {
    "date:inception_lower": "2015-06-01",
    "date:inception_upper": "2015-06-01",
    "iso:country": "GB",
    "wof:name": "LE15 7TE",
    "wof:placetype": "postalcode"
  },
  "geometry": {"coordinates":[-0.742949,52.68278],"type":"Point"}
}
