{
  "type": "Feature",
  "properties": {
    "iso:country":"GB",
    "wof:name":"LE15 7TE",
    "wof:placetype":"postalcode"
},
  "geometry": {"coordinates":[-0.74294870512624,52.68278019493584],"type":"Point"}
}