{
  "type": "Feature",
  "properties": {
    "iso:country":"GB",
    "wof:name":"PA23 7LF",
    "wof:placetype":"postalcode"
},
  "geometry": {"coordinates":[-4.93526082170838,55.94369080702327],"type":"Point"}
}