{
  "type": "Feature",
  "properties": {
    "iso:country":"GB",
    "wof:name":"LL18 4UN",
    "wof:placetype":"postalcode"
},
  "geometry": {"coordinates":[-3.46124481471669,53.31015337612117],"type":"Point"}
}