{
  "type": "Feature",
  "properties": {
    "iso:country":"GB",
    "wof:name":"NR25 6RX",
    "wof:placetype":"postalcode"
},
  "geometry": {"coordinates":[1.09893209872301,52.91029286128652],"type":"Point"}
}