{
  "type": "Feature",
  "properties": {
    "iso:country":"GB",
    "wof:name":"WF8 2DG",
    "wof:placetype":"postalcode"
},
  "geometry": {"coordinates":[-1.2904711145324,53.70234776522948],"type":"Point"}
}