{
  "type": "Feature",
  "properties": {
    "date:inception_lower":"1992-08-01",
    "date:inception_upper":"1992-08-31",
    "iso:country":"GB",
    "wof:name":"WF8 2DG",
    "wof:placetype":"postalcode"
},
  "geometry": {"coordinates":[-1.290471,53.702348],"type":"Point"}
}