{
  "type": "Feature",
  "properties": {
    "iso:country": "GB",
    "wof:name": "HU10 6LY",
    "wof:placetype": "postalcode"
  },
  "geometry": {"coordinates":[-0.434534,53.75292],"type":"Point"}
}
