{
  "type": "Feature",
  "properties": {
    "date:inception_lower": "1980-01-01",
    "date:inception_upper": "1980-01-01",
    "iso:country": "GB",
    "wof:name": "HU10 6LY",
    "wof:placetype": "postalcode"
  },
  "geometry": {"coordinates":[-0.434539,53.75294],"type":"Point"}
}
