{
  "type": "Feature",
  "properties": {
    "iso:country":"GB",
    "wof:name":"HU10 6LY",
    "wof:placetype":"postalcode"
},
  "geometry": {"coordinates":[-0.43453438485632,53.75292008805624],"type":"Point"}
}