{
  "type": "Feature",
  "properties": {
    "date:inception_lower": "2019-07-01",
    "date:inception_upper": "2019-07-01",
    "iso:country": "GB",
    "wof:name": "G75 0BF",
    "wof:placetype": "postalcode"
  },
  "geometry": {"coordinates":[-4.182532,55.752421],"type":"Point"}
}
