{
  "type": "Feature",
  "properties": {
    "iso:country":"GB",
    "wof:name":"S74 9BA",
    "wof:placetype":"postalcode"
},
  "geometry": {"coordinates":[-1.4392940566633,53.49703283211652],"type":"Point"}
}