{
  "type": "Feature",
  "properties": {
    "iso:country":"GB",
    "wof:name":"NE17 7TW",
    "wof:placetype":"postalcode"
},
  "geometry": {"coordinates":[-1.81356288353871,54.90716839210102],"type":"Point"}
}