{
  "type": "Feature",
  "properties": {
    "iso:country": "GB",
    "wof:name": "MK10 7FU",
    "wof:placetype": "postalcode"
  },
  "geometry": {"coordinates":[-0.689054,52.053223],"type":"Point"}
}
