{
  "type": "Feature",
  "properties": {
    "iso:country":"GB",
    "wof:name":"SM3 8AZ",
    "wof:placetype":"postalcode"
},
  "geometry": {"coordinates":[-0.21572225556113,51.35871128461613],"type":"Point"}
}