{
  "type": "Feature",
  "properties": {
    "iso:country":"GB",
    "wof:name":"CR7 7LX",
    "wof:placetype":"postalcode"
},
  "geometry": {"coordinates":[-0.11006000411566,51.39755746573228],"type":"Point"}
}