{
  "type": "Feature",
  "properties": {
    "date:inception_lower": "2010-10-01",
    "date:inception_upper": "2010-10-01",
    "iso:country": "GB",
    "wof:name": "SE15 6FG",
    "wof:placetype": "postalcode"
  },
  "geometry": {"coordinates":[-0.079937,51.477365],"type":"Point"}
}
