{
  "type": "Feature",
  "properties": {
    "date:inception_lower": "1980-01-01",
    "date:inception_upper": "1980-01-01",
    "iso:country": "GB",
    "wof:name": "L40 9RH",
    "wof:placetype": "postalcode"
  },
  "geometry": {"coordinates":[-2.93001,53.60294],"type":"Point"}
}
