{
  "type": "Feature",
  "properties": {
    "date:inception_lower":"1980-01-01",
    "date:inception_upper":"1980-01-31",
    "iso:country":"GB",
    "wof:name":"L40 9RH",
    "wof:placetype":"postalcode"
},
  "geometry": {"coordinates":[-2.926576,53.60064],"type":"Point"}
}