{
  "type": "Feature",
  "properties": {
    "iso:country":"GB",
    "wof:name":"L40 9RH",
    "wof:placetype":"postalcode"
},
  "geometry": {"coordinates":[-2.9265758618534,53.6006399818688],"type":"Point"}
}