{
  "type": "Feature",
  "properties": {
    "date:inception_lower": "1980-01-01",
    "date:inception_upper": "1980-01-01",
    "iso:country": "GB",
    "wof:name": "DE13 9ND",
    "wof:placetype": "postalcode"
  },
  "geometry": {"coordinates":[-1.688657,52.857238],"type":"Point"}
}
