{
  "type": "Feature",
  "properties": {
    "iso:country":"GB",
    "wof:name":"WS14 0QP",
    "wof:placetype":"postalcode"
},
  "geometry": {"coordinates":[-1.83481226292158,52.65263194637952],"type":"Point"}
}