{
  "type": "Feature",
  "properties": {
    "iso:country":"GB",
    "wof:name":"IG10 4EE",
    "wof:placetype":"postalcode"
},
  "geometry": {"coordinates":[0.044785680358,51.6444515764832],"type":"Point"}
}