{
  "type": "Feature",
  "properties": {
    "iso:country":"GB",
    "wof:name":"SP6 3LE",
    "wof:placetype":"postalcode"
},
  "geometry": {"coordinates":[-1.90199979160249,50.97465595429754],"type":"Point"}
}