{
  "type": "Feature",
  "properties": {
    "date:inception_lower": "1980-01-01",
    "date:inception_upper": "1980-01-01",
    "iso:country": "GB",
    "wof:name": "HU3 6PB",
    "wof:placetype": "postalcode"
  },
  "geometry": {"coordinates":[-0.375711,53.744002],"type":"Point"}
}
