{
  "type": "Feature",
  "properties": {
    "iso:country":"GB",
    "wof:name":"HU3 6PB",
    "wof:placetype":"postalcode"
},
  "geometry": {"coordinates":[-0.37571084112325,53.74400224163259],"type":"Point"}
}