{
  "type": "Feature",
  "properties": {
    "date:inception_lower": "1980-01-01",
    "date:inception_upper": "1980-01-01",
    "iso:country": "GB",
    "wof:name": "GU34 4JG",
    "wof:placetype": "postalcode"
  },
  "geometry": {"coordinates":[-0.922793,51.172636],"type":"Point"}
}
