{
  "type": "Feature",
  "properties": {
    "iso:country":"GB",
    "wof:name":"GU34 4JG",
    "wof:placetype":"postalcode"
},
  "geometry": {"coordinates":[-0.9223365211379,51.1726429698212],"type":"Point"}
}