{
  "type": "Feature",
  "properties": {
    "date:inception_lower": "2000-10-01",
    "date:inception_upper": "2000-10-01",
    "iso:country": "GB",
    "wof:name": "OX26 4FB",
    "wof:placetype": "postalcode"
  },
  "geometry": {"coordinates":[-1.13486,51.905715],"type":"Point"}
}
