{
  "type": "Feature",
  "properties": {
    "iso:country":"GB",
    "wof:name":"GL5 5HW",
    "wof:placetype":"postalcode"
},
  "geometry": {"coordinates":[-2.23264382631477,51.70681379180336],"type":"Point"}
}