{
  "type": "Feature",
  "properties": {
    "iso:country":"GB",
    "wof:name":"W5 2RE",
    "wof:placetype":"postalcode"
},
  "geometry": {"coordinates":[-0.30721729424355,51.52252626480978],"type":"Point"}
}