{
  "type": "Feature",
  "properties": {
    "iso:country":"GB",
    "wof:name":"SK9 2DJ",
    "wof:placetype":"postalcode"
},
  "geometry": {"coordinates":[-2.21051969668678,53.32735127768055],"type":"Point"}
}