{
  "type": "Feature",
  "properties": {
    "date:inception_lower":"1985-10-01",
    "date:inception_upper":"1985-10-31",
    "iso:country":"GB",
    "wof:name":"SK9 2DJ",
    "wof:placetype":"postalcode"
},
  "geometry": {"coordinates":[-2.21052,53.327351],"type":"Point"}
}