{
  "type": "Feature",
  "properties": {
    "iso:country":"GB",
    "wof:name":"BS3 3EU",
    "wof:placetype":"postalcode"
},
  "geometry": {"coordinates":[-2.61200809225255,51.43717988635959],"type":"Point"}
}