{
  "type": "Feature",
  "properties": {
    "iso:country":"GB",
    "wof:name":"N17 7JD",
    "wof:placetype":"postalcode"
},
  "geometry": {"coordinates":[-0.09345849128049,51.60257112717605],"type":"Point"}
}