{
  "type": "Feature",
  "properties": {
    "iso:country": "GB",
    "wof:name": "WF8 3QW",
    "wof:placetype": "postalcode"
  },
  "geometry": {"coordinates":[-1.312627,53.678469],"type":"Point"}
}
