{
  "type": "Feature",
  "properties": {
    "iso:country":"GB",
    "wof:name":"WF8 3QW",
    "wof:placetype":"postalcode"
},
  "geometry": {"coordinates":[-1.31262722144318,53.67846911279494],"type":"Point"}
}