{
  "type": "Feature",
  "properties": {
    "iso:country":"GB",
    "wof:name":"AL1 3BA",
    "wof:placetype":"postalcode"
},
  "geometry": {"coordinates":[-0.33233839704779,51.74994621192564],"type":"Point"}
}