{
  "type": "Feature",
  "properties": {
    "iso:country": "GB",
    "wof:name": "ME15 0EB",
    "wof:placetype": "postalcode"
  },
  "geometry": {"coordinates":[0.514579,51.242556],"type":"Point"}
}
