{
  "type": "Feature",
  "properties": {
    "iso:country": "GB",
    "wof:name": "HA8 8HS",
    "wof:placetype": "postalcode"
  },
  "geometry": {"coordinates":[-0.279031,51.620869],"type":"Point"}
}
