{
  "type": "Feature",
  "properties": {
    "iso:country":"GB",
    "wof:name":"UB9 6EB",
    "wof:placetype":"postalcode"
},
  "geometry": {"coordinates":[-0.48181614524844,51.60280514878953],"type":"Point"}
}