{
  "type": "Feature",
  "properties": {
    "date:inception_lower": "1996-12-01",
    "date:inception_upper": "1996-12-01",
    "iso:country": "GB",
    "wof:name": "UB9 6EB",
    "wof:placetype": "postalcode"
  },
  "geometry": {"coordinates":[-0.48238,51.6026],"type":"Point"}
}
