{
  "type": "Feature",
  "properties": {
    "iso:country":"GB",
    "wof:name":"DE11 0UH",
    "wof:placetype":"postalcode"
},
  "geometry": {"coordinates":[-1.58909485023609,52.77821412703965],"type":"Point"}
}