{
  "type": "Feature",
  "properties": {
    "iso:country": "GB",
    "wof:name": "DE11 0UH",
    "wof:placetype": "postalcode"
  },
  "geometry": {"coordinates":[-1.58909,52.778231],"type":"Point"}
}
