{
  "type": "Feature",
  "properties": {
    "iso:country": "GB",
    "wof:name": "RH5 6JA",
    "wof:placetype": "postalcode"
  },
  "geometry": {"coordinates":[-0.403723,51.201191],"type":"Point"}
}
