{
  "type": "Feature",
  "properties": {
    "iso:country":"GB",
    "wof:name":"RH5 6JA",
    "wof:placetype":"postalcode"
},
  "geometry": {"coordinates":[-0.40374722186888,51.20119472002026],"type":"Point"}
}