{
  "type": "Feature",
  "properties": {
    "iso:country":"GB",
    "wof:name":"NE27 0PA",
    "wof:placetype":"postalcode"
},
  "geometry": {"coordinates":[-1.50591954991512,55.03495575113197],"type":"Point"}
}