{
  "type": "Feature",
  "properties": {
    "date:inception_lower": "2003-09-01",
    "date:inception_upper": "2003-09-01",
    "iso:country": "GB",
    "wof:name": "KY2 6PF",
    "wof:placetype": "postalcode"
  },
  "geometry": {"coordinates":[-3.186967,56.135489],"type":"Point"}
}
