{
  "type": "Feature",
  "properties": {
    "iso:country":"GB",
    "wof:name":"HA9 8RF",
    "wof:placetype":"postalcode"
},
  "geometry": {"coordinates":[-0.30681631107448,51.57218482134658],"type":"Point"}
}