{
  "type": "Feature",
  "properties": {
    "iso:country": "GB",
    "wof:name": "HA9 8RF",
    "wof:placetype": "postalcode"
  },
  "geometry": {"coordinates":[-0.306816,51.572185],"type":"Point"}
}
