{
  "type": "Feature",
  "properties": {
    "date:inception_lower":"2015-02-01",
    "date:inception_upper":"2015-02-28",
    "iso:country":"GB",
    "wof:name":"HU17 7FE",
    "wof:placetype":"postalcode"
},
  "geometry": {"coordinates":[-0.455361,53.877192],"type":"Point"}
}