{
  "type": "Feature",
  "properties": {
    "iso:country":"GB",
    "wof:name":"HU17 7FE",
    "wof:placetype":"postalcode"
},
  "geometry": {"coordinates":[-0.45536136055478,53.87719237580722],"type":"Point"}
}