{
  "type": "Feature",
  "properties": {
    "iso:country": "GB",
    "wof:name": "HU17 7FE",
    "wof:placetype": "postalcode"
  },
  "geometry": {"coordinates":[-0.455361,53.877192],"type":"Point"}
}
