{
  "type": "Feature",
  "properties": {
    "date:inception_lower": "2015-02-01",
    "date:inception_upper": "2015-02-01",
    "iso:country": "GB",
    "wof:name": "HU17 7FE",
    "wof:placetype": "postalcode"
  },
  "geometry": {"coordinates":[-0.455059,53.876974],"type":"Point"}
}
