{
  "type": "Feature",
  "properties": {
    "iso:country":"GB",
    "wof:name":"BN8 6QD",
    "wof:placetype":"postalcode"
},
  "geometry": {"coordinates":[0.17573040631325,50.93124836919046],"type":"Point"}
}