{
  "type": "Feature",
  "properties": {
    "date:inception_lower": "2009-06-01",
    "date:inception_upper": "2009-06-01",
    "iso:country": "GB",
    "wof:name": "BN8 6QD",
    "wof:placetype": "postalcode"
  },
  "geometry": {"coordinates":[0.175771,50.931216],"type":"Point"}
}
