{
  "type": "Feature",
  "properties": {
    "date:inception_lower": "2001-06-01",
    "date:inception_upper": "2001-06-01",
    "iso:country": "GB",
    "wof:name": "NR15 1EW",
    "wof:placetype": "postalcode"
  },
  "geometry": {"coordinates":[1.38198,52.523763],"type":"Point"}
}
