{
  "type": "Feature",
  "properties": {
    "iso:country": "GB",
    "wof:name": "PO4 0SB",
    "wof:placetype": "postalcode"
  },
  "geometry": {"coordinates":[-1.077902,50.780305],"type":"Point"}
}
