{
  "type": "Feature",
  "properties": {
    "iso:country":"GB",
    "wof:name":"PO4 0SB",
    "wof:placetype":"postalcode"
},
  "geometry": {"coordinates":[-1.07788894409377,50.78025299547895],"type":"Point"}
}