{
  "type": "Feature",
  "properties": {
    "iso:country":"GB",
    "wof:name":"PH1 2SQ",
    "wof:placetype":"postalcode"
},
  "geometry": {"coordinates":[-3.48007714191637,56.40276792099618],"type":"Point"}
}