{
  "type": "Feature",
  "properties": {
    "iso:country":"GB",
    "wof:name":"TQ5 8RX",
    "wof:placetype":"postalcode"
},
  "geometry": {"coordinates":[-3.52422892718849,50.39544136688129],"type":"Point"}
}