{
  "type": "Feature",
  "properties": {
    "iso:country": "GB",
    "wof:name": "KY15 4JW",
    "wof:placetype": "postalcode"
  },
  "geometry": {"coordinates":[-3.017116,56.322524],"type":"Point"}
}
