{
  "type": "Feature",
  "properties": {
    "iso:country":"GB",
    "wof:name":"NW8 9XY",
    "wof:placetype":"postalcode"
},
  "geometry": {"coordinates":[-0.18387087115299,51.5315622557809],"type":"Point"}
}