{
  "type": "Feature",
  "properties": {
    "iso:country": "GB",
    "wof:name": "NW8 9XY",
    "wof:placetype": "postalcode"
  },
  "geometry": {"coordinates":[-0.183871,51.531562],"type":"Point"}
}
