{
  "type": "Feature",
  "properties": {
    "date:inception_lower": "1996-06-01",
    "date:inception_upper": "1996-06-01",
    "iso:country": "GB",
    "wof:name": "AB16 5LT",
    "wof:placetype": "postalcode"
  },
  "geometry": {"coordinates":[-2.149785,57.161259],"type":"Point"}
}
