{
  "type": "Feature",
  "properties": {
    "iso:country": "GB",
    "wof:name": "NG34 8WL",
    "wof:placetype": "postalcode"
  },
  "geometry": {"coordinates":[-0.412456,53.010279],"type":"Point"}
}
