{
  "type": "Feature",
  "properties": {
    "iso:country":"GB",
    "wof:name":"S72 8FF",
    "wof:placetype":"postalcode"
},
  "geometry": {"coordinates":[-1.41915179804763,53.57335681593224],"type":"Point"}
}