{
  "type": "Feature",
  "properties": {
    "iso:country":"GB",
    "wof:name":"W14 0PR",
    "wof:placetype":"postalcode"
},
  "geometry": {"coordinates":[-0.21234833130533,51.497630630755],"type":"Point"}
}