{
  "type": "Feature",
  "properties": {
    "iso:country": "GB",
    "wof:name": "IP12 2AA",
    "wof:placetype": "postalcode"
  },
  "geometry": {"coordinates":[1.528941,52.102241],"type":"Point"}
}
