{
  "type": "Feature",
  "properties": {
    "iso:country":"GB",
    "wof:name":"IP12 2AA",
    "wof:placetype":"postalcode"
},
  "geometry": {"coordinates":[1.52894130407966,52.102241496518],"type":"Point"}
}