{
  "type": "Feature",
  "properties": {
    "iso:country": "GB",
    "wof:name": "EH47 0LY",
    "wof:placetype": "postalcode"
  },
  "geometry": {"coordinates":[-3.699931,55.862515],"type":"Point"}
}
