{
  "type": "Feature",
  "properties": {
    "iso:country":"GB",
    "wof:name":"EH47 0LY",
    "wof:placetype":"postalcode"
},
  "geometry": {"coordinates":[-3.69993072582449,55.86251516236572],"type":"Point"}
}