{
  "type": "Feature",
  "properties": {
    "iso:country": "GB",
    "wof:name": "SG7 6DQ",
    "wof:placetype": "postalcode"
  },
  "geometry": {"coordinates":[-0.183318,51.987346],"type":"Point"}
}
