{
  "type": "Feature",
  "properties": {
    "iso:country":"GB",
    "wof:name":"SG7 6DQ",
    "wof:placetype":"postalcode"
},
  "geometry": {"coordinates":[-0.18325638409331,51.98737212358689],"type":"Point"}
}