{
  "type": "Feature",
  "properties": {
    "iso:country":"GB",
    "wof:name":"TN16 1HW",
    "wof:placetype":"postalcode"
},
  "geometry": {"coordinates":[0.10263691440359,51.27532437133613],"type":"Point"}
}