{
  "type": "Feature",
  "properties": {
    "iso:country":"GB",
    "wof:name":"G32 9BL",
    "wof:placetype":"postalcode"
},
  "geometry": {"coordinates":[-4.15865135048453,55.84859881248549],"type":"Point"}
}