{
  "type": "Feature",
  "properties": {
    "iso:country":"GB",
    "wof:name":"BL8 4BA",
    "wof:placetype":"postalcode"
},
  "geometry": {"coordinates":[-2.33935395148344,53.62324282792328],"type":"Point"}
}