{
  "type": "Feature",
  "properties": {
    "iso:country": "GB",
    "wof:name": "BB12 9AW",
    "wof:placetype": "postalcode"
  },
  "geometry": {"coordinates":[-2.31662,53.811489],"type":"Point"}
}
