{
  "type": "Feature",
  "properties": {
    "iso:country":"GB",
    "wof:name":"NW10 4NS",
    "wof:placetype":"postalcode"
},
  "geometry": {"coordinates":[-0.24631388214618,51.53606432344996],"type":"Point"}
}