{
  "type": "Feature",
  "properties": {
    "iso:country":"GB",
    "wof:name":"BS4 4UB",
    "wof:placetype":"postalcode"
},
  "geometry": {"coordinates":[-2.54949832261736,51.43476521044901],"type":"Point"}
}