{
  "type": "Feature",
  "properties": {
    "iso:country":"GB",
    "wof:name":"CF24 4PE",
    "wof:placetype":"postalcode"
},
  "geometry": {"coordinates":[-3.17647298008912,51.49647274276314],"type":"Point"}
}