{
  "type": "Feature",
  "properties": {
    "date:inception_lower":"1999-06-01",
    "date:inception_upper":"1999-06-30",
    "iso:country":"GB",
    "wof:name":"CF24 4PE",
    "wof:placetype":"postalcode"
},
  "geometry": {"coordinates":[-3.176276,51.496664],"type":"Point"}
}