{
  "type": "Feature",
  "properties": {
    "iso:country":"GB",
    "wof:name":"HX2 6QS",
    "wof:placetype":"postalcode"
},
  "geometry": {"coordinates":[-1.94025801897832,53.73011141882111],"type":"Point"}
}