{
  "type": "Feature",
  "properties": {
    "iso:country":"GB",
    "wof:name":"S20 6RF",
    "wof:placetype":"postalcode"
},
  "geometry": {"coordinates":[-1.38421748655823,53.34144655345378],"type":"Point"}
}