{
  "type": "Feature",
  "properties": {
    "date:inception_lower": "1980-01-01",
    "date:inception_upper": "1980-01-01",
    "iso:country": "GB",
    "wof:name": "BL9 7ES",
    "wof:placetype": "postalcode"
  },
  "geometry": {"coordinates":[-2.283254,53.590804],"type":"Point"}
}
