{
  "type": "Feature",
  "properties": {
    "date:inception_lower": "1994-05-01",
    "date:inception_upper": "1994-05-01",
    "iso:country": "GB",
    "wof:name": "M33 7EZ",
    "wof:placetype": "postalcode"
  },
  "geometry": {"coordinates":[-2.325295,53.426795],"type":"Point"}
}
