{
  "type": "Feature",
  "properties": {
    "iso:country":"GB",
    "wof:name":"M33 7EZ",
    "wof:placetype":"postalcode"
},
  "geometry": {"coordinates":[-2.32529533006916,53.42679524760582],"type":"Point"}
}