{
  "type": "Feature",
  "properties": {
    "iso:country":"GB",
    "wof:name":"HA4 8QE",
    "wof:placetype":"postalcode"
},
  "geometry": {"coordinates":[-0.41610049759362,51.5770647059732],"type":"Point"}
}