{
  "type": "Feature",
  "properties": {
    "iso:country": "GB",
    "wof:name": "S9 3TE",
    "wof:placetype": "postalcode"
  },
  "geometry": {"coordinates":[-1.429485,53.39439],"type":"Point"}
}
