{
  "type": "Feature",
  "properties": {
    "iso:country":"GB",
    "wof:name":"S9 3TE",
    "wof:placetype":"postalcode"
},
  "geometry": {"coordinates":[-1.42948520384662,53.39439037117663],"type":"Point"}
}