{
  "type": "Feature",
  "properties": {
    "date:inception_lower": "2022-07-01",
    "date:inception_upper": "2022-07-01",
    "iso:country": "GB",
    "wof:name": "SG9 9UZ",
    "wof:placetype": "postalcode"
  },
  "geometry": {"coordinates":[-0.010012,51.945825],"type":"Point"}
}
