{
  "type": "Feature",
  "properties": {
    "iso:country":"GB",
    "wof:name":"PR7 2AA",
    "wof:placetype":"postalcode"
},
  "geometry": {"coordinates":[-2.63075101163904,53.65198361947787],"type":"Point"}
}