{
  "type": "Feature",
  "properties": {
    "date:inception_lower": "1996-06-01",
    "date:inception_upper": "1996-06-01",
    "iso:country": "GB",
    "wof:name": "AB42 5HE",
    "wof:placetype": "postalcode"
  },
  "geometry": {"coordinates":[-1.99703,57.52205],"type":"Point"}
}
