{
  "type": "Feature",
  "properties": {
    "date:inception_lower":"1980-01-01",
    "date:inception_upper":"1980-01-31",
    "iso:country":"GB",
    "wof:name":"CF37 5BJ",
    "wof:placetype":"postalcode"
},
  "geometry": {"coordinates":[-3.281647,51.580678],"type":"Point"}
}