{
  "type": "Feature",
  "properties": {
    "iso:country":"GB",
    "wof:name":"CF37 5BJ",
    "wof:placetype":"postalcode"
},
  "geometry": {"coordinates":[-3.28299871098696,51.58241520642778],"type":"Point"}
}