{
  "type": "Feature",
  "properties": {
    "iso:country":"GB",
    "wof:name":"EN4 8DR",
    "wof:placetype":"postalcode"
},
  "geometry": {"coordinates":[-0.16617569282988,51.63851208525885],"type":"Point"}
}