{
  "type": "Feature",
  "properties": {
    "iso:country":"GB",
    "wof:name":"B60 3HU",
    "wof:placetype":"postalcode"
},
  "geometry": {"coordinates":[-2.06402869468182,52.32365225959761],"type":"Point"}
}