{
  "type": "Feature",
  "properties": {
    "date:inception_lower":"1980-01-01",
    "date:inception_upper":"1980-01-31",
    "iso:country":"GB",
    "wof:name":"OX12 9SH",
    "wof:placetype":"postalcode"
},
  "geometry": {"coordinates":[-1.45204,51.591336],"type":"Point"}
}