{
  "type": "Feature",
  "properties": {
    "iso:country":"GB",
    "wof:name":"SY23 4JX",
    "wof:placetype":"postalcode"
},
  "geometry": {"coordinates":[-3.99883165202005,52.36275126469712],"type":"Point"}
}