{
  "type": "Feature",
  "properties": {
    "date:inception_lower": "1991-01-01",
    "date:inception_upper": "1991-01-01",
    "iso:country": "GB",
    "wof:name": "NE5 4BW",
    "wof:placetype": "postalcode"
  },
  "geometry": {"coordinates":[-1.682752,55.008973],"type":"Point"}
}
