{
  "type": "Feature",
  "properties": {
    "iso:country":"GB",
    "wof:name":"NE5 4BW",
    "wof:placetype":"postalcode"
},
  "geometry": {"coordinates":[-1.68275190747165,55.00897256864344],"type":"Point"}
}