{
  "type": "Feature",
  "properties": {
    "iso:country":"GB",
    "wof:name":"LS16 9DH",
    "wof:placetype":"postalcode"
},
  "geometry": {"coordinates":[-1.60960662278024,53.87991446951703],"type":"Point"}
}