{
  "type": "Feature",
  "properties": {
    "iso:country": "GB",
    "wof:name": "LS16 9DH",
    "wof:placetype": "postalcode"
  },
  "geometry": {"coordinates":[-1.609746,53.8802],"type":"Point"}
}
