{
  "type": "Feature",
  "properties": {
    "date:inception_lower": "2020-01-01",
    "date:inception_upper": "2020-01-01",
    "iso:country": "GB",
    "wof:name": "TF10 8FA",
    "wof:placetype": "postalcode"
  },
  "geometry": {"coordinates":[-2.474632,52.776209],"type":"Point"}
}
