{
  "type": "Feature",
  "properties": {
    "iso:country":"GB",
    "wof:name":"GU28 9BQ",
    "wof:placetype":"postalcode"
},
  "geometry": {"coordinates":[-0.63639307068296,50.99616476189724],"type":"Point"}
}