{
  "type": "Feature",
  "properties": {
    "iso:country":"GB",
    "wof:name":"PO13 8NH",
    "wof:placetype":"postalcode"
},
  "geometry": {"coordinates":[-1.16702863198799,50.79987114958026],"type":"Point"}
}