{
  "type": "Feature",
  "properties": {
    "iso:country":"GB",
    "wof:name":"BN20 8NS",
    "wof:placetype":"postalcode"
},
  "geometry": {"coordinates":[0.25351157078236,50.77776737104854],"type":"Point"}
}