{
  "type": "Feature",
  "properties": {
    "iso:country":"GB",
    "wof:name":"IP17 2BE",
    "wof:placetype":"postalcode"
},
  "geometry": {"coordinates":[1.43597914747159,52.22447252391701],"type":"Point"}
}