{
  "type": "Feature",
  "properties": {
    "date:inception_lower": "1990-07-01",
    "date:inception_upper": "1990-07-01",
    "iso:country": "GB",
    "wof:name": "LL14 6EN",
    "wof:placetype": "postalcode"
  },
  "geometry": {"coordinates":[-3.054182,52.984327],"type":"Point"}
}
