{
  "type": "Feature",
  "properties": {
    "iso:country":"GB",
    "wof:name":"M28 2SL",
    "wof:placetype":"postalcode"
},
  "geometry": {"coordinates":[-2.36494342503507,53.50322676905687],"type":"Point"}
}