{
  "type": "Feature",
  "properties": {
    "date:inception_lower": "1983-03-01",
    "date:inception_upper": "1983-03-01",
    "iso:country": "GB",
    "wof:name": "MK14 5PW",
    "wof:placetype": "postalcode"
  },
  "geometry": {"coordinates":[-0.743243,52.065916],"type":"Point"}
}
