{
  "type": "Feature",
  "properties": {
    "iso:country":"GB",
    "wof:name":"E17 9JZ",
    "wof:placetype":"postalcode"
},
  "geometry": {"coordinates":[-0.00927179402992,51.58371886156925],"type":"Point"}
}