{
  "type": "Feature",
  "properties": {
    "date:inception_lower": "1984-10-01",
    "date:inception_upper": "1984-10-01",
    "iso:country": "GB",
    "wof:name": "E17 9JZ",
    "wof:placetype": "postalcode"
  },
  "geometry": {"coordinates":[-0.009272,51.583719],"type":"Point"}
}
