{
  "type": "Feature",
  "properties": {
    "iso:country": "GB",
    "wof:name": "CT15 7DP",
    "wof:placetype": "postalcode"
  },
  "geometry": {"coordinates":[1.243237,51.125216],"type":"Point"}
}
