{
  "type": "Feature",
  "properties": {
    "iso:country": "GB",
    "wof:name": "N13 5HZ",
    "wof:placetype": "postalcode"
  },
  "geometry": {"coordinates":[-0.1059,51.614157],"type":"Point"}
}
