{
  "type": "Feature",
  "properties": {
    "iso:country": "GB",
    "wof:name": "NP23 4DW",
    "wof:placetype": "postalcode"
  },
  "geometry": {"coordinates":[-3.172982,51.800291],"type":"Point"}
}
