{
  "type": "Feature",
  "properties": {
    "iso:country": "GB",
    "wof:name": "GL6 9HJ",
    "wof:placetype": "postalcode"
  },
  "geometry": {"coordinates":[-2.206553,51.700946],"type":"Point"}
}
