{
  "type": "Feature",
  "properties": {
    "iso:country":"GB",
    "wof:name":"IP13 7NQ",
    "wof:placetype":"postalcode"
},
  "geometry": {"coordinates":[1.29141542553033,52.26211725809063],"type":"Point"}
}