{
  "type": "Feature",
  "properties": {
    "iso:country": "GB",
    "wof:name": "IP13 7NQ",
    "wof:placetype": "postalcode"
  },
  "geometry": {"coordinates":[1.291592,52.262132],"type":"Point"}
}
