{
  "type": "Feature",
  "properties": {
    "iso:country":"GB",
    "wof:name":"UB6 8PN",
    "wof:placetype":"postalcode"
},
  "geometry": {"coordinates":[-0.34905274874945,51.53994701298303],"type":"Point"}
}