{
  "type": "Feature",
  "properties": {
    "iso:country":"GB",
    "wof:name":"HU9 4JA",
    "wof:placetype":"postalcode"
},
  "geometry": {"coordinates":[-0.26048675694466,53.76617079249576],"type":"Point"}
}