{
  "type": "Feature",
  "properties": {
    "date:inception_lower": "1980-01-01",
    "date:inception_upper": "1980-01-01",
    "iso:country": "GB",
    "wof:name": "N1 7AD",
    "wof:placetype": "postalcode"
  },
  "geometry": {"coordinates":[-0.093414,51.53742],"type":"Point"}
}
