{
  "type": "Feature",
  "properties": {
    "date:inception_lower": "2020-11-01",
    "date:inception_upper": "2020-11-01",
    "iso:country": "GB",
    "wof:name": "PH1 3WD",
    "wof:placetype": "postalcode"
  },
  "geometry": {"coordinates":[-3.487027,56.403611],"type":"Point"}
}
