{
  "type": "Feature",
  "properties": {
    "iso:country": "GB",
    "wof:name": "G43 2EE",
    "wof:placetype": "postalcode"
  },
  "geometry": {"coordinates":[-4.278284,55.821177],"type":"Point"}
}
