{
  "type": "Feature",
  "properties": {
    "iso:country":"GB",
    "wof:name":"G43 2EE",
    "wof:placetype":"postalcode"
},
  "geometry": {"coordinates":[-4.27828453703187,55.82117691085308],"type":"Point"}
}