{
  "type": "Feature",
  "properties": {
    "iso:country":"GB",
    "wof:name":"DL14 7EP",
    "wof:placetype":"postalcode"
},
  "geometry": {"coordinates":[-1.67450819481266,54.66472500854027],"type":"Point"}
}