{
  "type": "Feature",
  "properties": {
    "date:inception_lower":"1980-01-01",
    "date:inception_upper":"1980-01-31",
    "iso:country":"GB",
    "wof:name":"DL14 7EP",
    "wof:placetype":"postalcode"
},
  "geometry": {"coordinates":[-1.674508,54.664725],"type":"Point"}
}