{
  "type": "Feature",
  "properties": {
    "iso:country":"GB",
    "wof:name":"HX4 9BH",
    "wof:placetype":"postalcode"
},
  "geometry": {"coordinates":[-1.8631590377924,53.6767039482691],"type":"Point"}
}