{
  "type": "Feature",
  "properties": {
    "iso:country":"GB",
    "wof:name":"SW20 9HJ",
    "wof:placetype":"postalcode"
},
  "geometry": {"coordinates":[-0.22575426002535,51.39533764572746],"type":"Point"}
}