{
  "type": "Feature",
  "properties": {
    "date:inception_lower": "1980-01-01",
    "date:inception_upper": "1980-01-01",
    "iso:country": "GB",
    "wof:name": "SW20 9HJ",
    "wof:placetype": "postalcode"
  },
  "geometry": {"coordinates":[-0.225754,51.395338],"type":"Point"}
}
