{
  "type": "Feature",
  "properties": {
    "date:inception_lower":"2002-06-01",
    "date:inception_upper":"2002-06-30",
    "iso:country":"GB",
    "wof:name":"LN1 2UZ",
    "wof:placetype":"postalcode"
},
  "geometry": {"coordinates":[-0.596627,53.247434],"type":"Point"}
}