{
  "type": "Feature",
  "properties": {
    "iso:country": "GB",
    "wof:name": "LN1 2UZ",
    "wof:placetype": "postalcode"
  },
  "geometry": {"coordinates":[-0.596627,53.247434],"type":"Point"}
}
