{
  "type": "Feature",
  "properties": {
    "iso:country":"GB",
    "wof:name":"UB9 6AS",
    "wof:placetype":"postalcode"
},
  "geometry": {"coordinates":[-0.4815457670935,51.59056349597203],"type":"Point"}
}