{
  "type": "Feature",
  "properties": {
    "iso:country":"GB",
    "wof:name":"CV6 1AF",
    "wof:placetype":"postalcode"
},
  "geometry": {"coordinates":[-1.52852309730884,52.41478074331766],"type":"Point"}
}