{
  "type": "Feature",
  "properties": {
    "date:inception_lower": "1980-01-01",
    "date:inception_upper": "1980-01-01",
    "iso:country": "GB",
    "wof:name": "CV6 1AF",
    "wof:placetype": "postalcode"
  },
  "geometry": {"coordinates":[-1.528523,52.414781],"type":"Point"}
}
