{
  "type": "Feature",
  "properties": {
    "iso:country":"GB",
    "wof:name":"NG2 6GR",
    "wof:placetype":"postalcode"
},
  "geometry": {"coordinates":[-1.11205025762765,52.92076055971078],"type":"Point"}
}