{
  "type": "Feature",
  "properties": {
    "iso:country":"GB",
    "wof:name":"AB12 3NW",
    "wof:placetype":"postalcode"
},
  "geometry": {"coordinates":[-2.08163105074007,57.10604003187066],"type":"Point"}
}