{
  "type": "Feature",
  "properties": {
    "iso:country":"GB",
    "wof:name":"TW14 8AU",
    "wof:placetype":"postalcode"
},
  "geometry": {"coordinates":[-0.42529087204827,51.45091984189843],"type":"Point"}
}