{
  "type": "Feature",
  "properties": {
    "date:inception_lower": "1980-01-01",
    "date:inception_upper": "1980-01-01",
    "iso:country": "GB",
    "wof:name": "TS22 5AJ",
    "wof:placetype": "postalcode"
  },
  "geometry": {"coordinates":[-1.303809,54.61103],"type":"Point"}
}
