{
  "type": "Feature",
  "properties": {
    "date:inception_lower": "1995-12-01",
    "date:inception_upper": "1995-12-01",
    "iso:country": "GB",
    "wof:name": "BD23 6XB",
    "wof:placetype": "postalcode"
  },
  "geometry": {"coordinates":[-2.003745,53.970498],"type":"Point"}
}
