{
  "type": "Feature",
  "properties": {
    "iso:country":"GB",
    "wof:name":"BD23 6XB",
    "wof:placetype":"postalcode"
},
  "geometry": {"coordinates":[-2.00374458352577,53.97049787130751],"type":"Point"}
}