{
  "type": "Feature",
  "properties": {
    "iso:country":"GB",
    "wof:name":"AL5 5AW",
    "wof:placetype":"postalcode"
},
  "geometry": {"coordinates":[-0.33982441411983,51.82547627392722],"type":"Point"}
}