{
  "type": "Feature",
  "properties": {
    "iso:country": "GB",
    "wof:name": "AL5 5AW",
    "wof:placetype": "postalcode"
  },
  "geometry": {"coordinates":[-0.339824,51.825476],"type":"Point"}
}
