{
  "type": "Feature",
  "properties": {
    "iso:country":"GB",
    "wof:name":"NW10 8AL",
    "wof:placetype":"postalcode"
},
  "geometry": {"coordinates":[-0.25287187956583,51.53575751577103],"type":"Point"}
}