{
  "type": "Feature",
  "properties": {
    "iso:country": "GB",
    "wof:name": "BA22 7EE",
    "wof:placetype": "postalcode"
  },
  "geometry": {"coordinates":[-2.490846,51.033688],"type":"Point"}
}
