{
  "type": "Feature",
  "properties": {
    "iso:country":"GB",
    "wof:name":"WF1 3AJ",
    "wof:placetype":"postalcode"
},
  "geometry": {"coordinates":[-1.49792779341486,53.69637655181254],"type":"Point"}
}