{
  "type": "Feature",
  "properties": {
    "iso:country": "GB",
    "wof:name": "WF1 3AJ",
    "wof:placetype": "postalcode"
  },
  "geometry": {"coordinates":[-1.497928,53.696377],"type":"Point"}
}
