{
  "type": "Feature",
  "properties": {
    "iso:country": "GB",
    "wof:name": "PA16 0NP",
    "wof:placetype": "postalcode"
  },
  "geometry": {"coordinates":[-4.822425,55.939192],"type":"Point"}
}
