{
  "type": "Feature",
  "properties": {
    "iso:country":"GB",
    "wof:name":"PA16 0NP",
    "wof:placetype":"postalcode"
},
  "geometry": {"coordinates":[-4.82242502273763,55.93919205462177],"type":"Point"}
}