{
  "type": "Feature",
  "properties": {
    "iso:country":"GB",
    "wof:name":"CR5 3TD",
    "wof:placetype":"postalcode"
},
  "geometry": {"coordinates":[-0.16965988015859,51.30930503871735],"type":"Point"}
}