{
  "type": "Feature",
  "properties": {
    "iso:country":"GB",
    "wof:name":"N17 9FS",
    "wof:placetype":"postalcode"
},
  "geometry": {"coordinates":[-0.05576535497576,51.59352683456093],"type":"Point"}
}