{
  "type": "Feature",
  "properties": {
    "iso:country":"GB",
    "wof:name":"BN18 9LJ",
    "wof:placetype":"postalcode"
},
  "geometry": {"coordinates":[-0.56708021648749,50.85902049297996],"type":"Point"}
}