{
  "type": "Feature",
  "properties": {
    "date:inception_lower":"1980-01-01",
    "date:inception_upper":"1980-01-31",
    "iso:country":"GB",
    "wof:name":"BN18 9LJ",
    "wof:placetype":"postalcode"
},
  "geometry": {"coordinates":[-0.56708,50.85902],"type":"Point"}
}