{
  "type": "Feature",
  "properties": {
    "iso:country":"GB",
    "wof:name":"TQ7 4QF",
    "wof:placetype":"postalcode"
},
  "geometry": {"coordinates":[-3.91563864112589,50.31579181459267],"type":"Point"}
}