{
  "type": "Feature",
  "properties": {
    "date:inception_lower": "1980-01-01",
    "date:inception_upper": "1980-01-01",
    "iso:country": "GB",
    "wof:name": "OX17 1ET",
    "wof:placetype": "postalcode"
  },
  "geometry": {"coordinates":[-1.306758,52.149248],"type":"Point"}
}
