{
  "type": "Feature",
  "properties": {
    "iso:country": "GB",
    "wof:name": "OX17 1ET",
    "wof:placetype": "postalcode"
  },
  "geometry": {"coordinates":[-1.306758,52.149248],"type":"Point"}
}
