{
  "type": "Feature",
  "properties": {
    "iso:country":"GB",
    "wof:name":"OX17 1ET",
    "wof:placetype":"postalcode"
},
  "geometry": {"coordinates":[-1.3067422396666,52.14933439641662],"type":"Point"}
}