{
  "type": "Feature",
  "properties": {
    "iso:country": "GB",
    "wof:name": "SE1 4UH",
    "wof:placetype": "postalcode"
  },
  "geometry": {"coordinates":[-0.083795,51.496239],"type":"Point"}
}
