{
  "type": "Feature",
  "properties": {
    "iso:country":"GB",
    "wof:name":"SE1 4UH",
    "wof:placetype":"postalcode"
},
  "geometry": {"coordinates":[-0.08379457079349,51.49623903304229],"type":"Point"}
}