{
  "type": "Feature",
  "properties": {
    "date:inception_lower":"1980-01-01",
    "date:inception_upper":"1980-01-31",
    "iso:country":"GB",
    "wof:name":"KT5 9RQ",
    "wof:placetype":"postalcode"
},
  "geometry": {"coordinates":[-0.275486,51.380559],"type":"Point"}
}