{
  "type": "Feature",
  "properties": {
    "iso:country":"GB",
    "wof:name":"KT5 9RQ",
    "wof:placetype":"postalcode"
},
  "geometry": {"coordinates":[-0.27548590737918,51.38055896147367],"type":"Point"}
}