{
  "type": "Feature",
  "properties": {
    "iso:country":"GB",
    "wof:name":"CM7 3XE",
    "wof:placetype":"postalcode"
},
  "geometry": {"coordinates":[0.57701285337312,51.87004514970126],"type":"Point"}
}