{
  "type": "Feature",
  "properties": {
    "iso:country":"GB",
    "wof:name":"SL6 3AP",
    "wof:placetype":"postalcode"
},
  "geometry": {"coordinates":[-0.75258174164965,51.50757847572585],"type":"Point"}
}