{
  "type": "Feature",
  "properties": {
    "iso:country":"GB",
    "wof:name":"W14 9BU",
    "wof:placetype":"postalcode"
},
  "geometry": {"coordinates":[-0.2104531987809,51.4915767838539],"type":"Point"}
}