{
  "type": "Feature",
  "properties": {
    "iso:country": "GB",
    "wof:name": "SS16 4AA",
    "wof:placetype": "postalcode"
  },
  "geometry": {"coordinates":[0.472492,51.564432],"type":"Point"}
}
