{
  "type": "Feature",
  "properties": {
    "iso:country": "GB",
    "wof:name": "PR6 9QF",
    "wof:placetype": "postalcode"
  },
  "geometry": {"coordinates":[-2.600802,53.614243],"type":"Point"}
}
