{
  "type": "Feature",
  "properties": {
    "iso:country": "GB",
    "wof:name": "CT2 7FS",
    "wof:placetype": "postalcode"
  },
  "geometry": {"coordinates":[1.063437,51.297743],"type":"Point"}
}
