{
  "type": "Feature",
  "properties": {
    "date:inception_lower": "1996-06-01",
    "date:inception_upper": "1996-06-01",
    "iso:country": "GB",
    "wof:name": "SE26 4TD",
    "wof:placetype": "postalcode"
  },
  "geometry": {"coordinates":[-0.052648,51.42695],"type":"Point"}
}
