{
  "type": "Feature",
  "properties": {
    "iso:country":"GB",
    "wof:name":"SE26 4TD",
    "wof:placetype":"postalcode"
},
  "geometry": {"coordinates":[-0.05319804708073,51.42714791401522],"type":"Point"}
}