{
  "type": "Feature",
  "properties": {
    "date:inception_lower": "2003-08-01",
    "date:inception_upper": "2003-08-01",
    "iso:country": "GB",
    "wof:name": "HP10 9UT",
    "wof:placetype": "postalcode"
  },
  "geometry": {"coordinates":[-0.695124,51.603113],"type":"Point"}
}
