{
  "type": "Feature",
  "properties": {
    "iso:country":"GB",
    "wof:name":"SY10 8LX",
    "wof:placetype":"postalcode"
},
  "geometry": {"coordinates":[-3.09352362425335,52.80606692371499],"type":"Point"}
}