{
  "type": "Feature",
  "properties": {
    "iso:country":"GB",
    "wof:name":"OL4 1JF",
    "wof:placetype":"postalcode"
},
  "geometry": {"coordinates":[-2.09621607557802,53.53982501989263],"type":"Point"}
}