{
  "type": "Feature",
  "properties": {
    "date:inception_lower": "1996-12-01",
    "date:inception_upper": "1996-12-01",
    "iso:country": "GB",
    "wof:name": "OL4 1JF",
    "wof:placetype": "postalcode"
  },
  "geometry": {"coordinates":[-2.096216,53.539825],"type":"Point"}
}
