{
  "type": "Feature",
  "properties": {
    "iso:country":"GB",
    "wof:name":"LS16 8JT",
    "wof:placetype":"postalcode"
},
  "geometry": {"coordinates":[-1.57718067013763,53.85526767476239],"type":"Point"}
}