{
  "type": "Feature",
  "properties": {
    "iso:country":"GB",
    "wof:name":"G46 6SJ",
    "wof:placetype":"postalcode"
},
  "geometry": {"coordinates":[-4.30173985917777,55.78528378762906],"type":"Point"}
}