{
  "type": "Feature",
  "properties": {
    "iso:country": "GB",
    "wof:name": "G46 6SJ",
    "wof:placetype": "postalcode"
  },
  "geometry": {"coordinates":[-4.30174,55.785284],"type":"Point"}
}
