{
  "type": "Feature",
  "properties": {
    "iso:country": "GB",
    "wof:name": "SN2 9TG",
    "wof:placetype": "postalcode"
  },
  "geometry": {"coordinates":[-1.777894,51.560126],"type":"Point"}
}
