{
  "type": "Feature",
  "properties": {
    "iso:country":"GB",
    "wof:name":"FY3 0BP",
    "wof:placetype":"postalcode"
},
  "geometry": {"coordinates":[-2.98904227537024,53.81871292896942],"type":"Point"}
}