{
  "type": "Feature",
  "properties": {
    "iso:country":"GB",
    "wof:name":"SG19 3LQ",
    "wof:placetype":"postalcode"
},
  "geometry": {"coordinates":[-0.1997279774232,52.15278400681709],"type":"Point"}
}