{
  "type": "Feature",
  "properties": {
    "iso:country":"GB",
    "wof:name":"LE7 4SG",
    "wof:placetype":"postalcode"
},
  "geometry": {"coordinates":[-1.07631002821317,52.72960891316132],"type":"Point"}
}