{
  "type": "Feature",
  "properties": {
    "iso:country":"GB",
    "wof:name":"SN16 0JJ",
    "wof:placetype":"postalcode"
},
  "geometry": {"coordinates":[-2.15193173170623,51.57208621008683],"type":"Point"}
}