{
  "type": "Feature",
  "properties": {
    "iso:country": "GB",
    "wof:name": "ST18 9TD",
    "wof:placetype": "postalcode"
  },
  "geometry": {"coordinates":[-2.089918,52.845376],"type":"Point"}
}
