{
  "type": "Feature",
  "properties": {
    "date:inception_lower": "1980-01-01",
    "date:inception_upper": "1980-01-01",
    "iso:country": "GB",
    "wof:name": "ST18 9TD",
    "wof:placetype": "postalcode"
  },
  "geometry": {"coordinates":[-2.089918,52.845376],"type":"Point"}
}
