{
  "type": "Feature",
  "properties": {
    "iso:country":"GB",
    "wof:name":"CW11 1ED",
    "wof:placetype":"postalcode"
},
  "geometry": {"coordinates":[-2.35506039593788,53.14987410559166],"type":"Point"}
}