{
  "type": "Feature",
  "properties": {
    "iso:country": "GB",
    "wof:name": "CW11 1ED",
    "wof:placetype": "postalcode"
  },
  "geometry": {"coordinates":[-2.35506,53.149874],"type":"Point"}
}
