{
  "type": "Feature",
  "properties": {
    "date:inception_lower": "1980-01-01",
    "date:inception_upper": "1980-01-01",
    "iso:country": "GB",
    "wof:name": "PH25 3DS",
    "wof:placetype": "postalcode"
  },
  "geometry": {"coordinates":[-3.641133,57.26423],"type":"Point"}
}
