{
  "type": "Feature",
  "properties": {
    "iso:country":"GB",
    "wof:name":"PO14 2SH",
    "wof:placetype":"postalcode"
},
  "geometry": {"coordinates":[-1.21114881153195,50.81907139953169],"type":"Point"}
}