{
  "type": "Feature",
  "properties": {
    "iso:country":"GB",
    "wof:name":"TF1 3QX",
    "wof:placetype":"postalcode"
},
  "geometry": {"coordinates":[-2.52171769278439,52.71447144049639],"type":"Point"}
}