{
  "type": "Feature",
  "properties": {
    "date:inception_lower": "1991-09-01",
    "date:inception_upper": "1991-09-01",
    "iso:country": "GB",
    "wof:name": "TF1 3QX",
    "wof:placetype": "postalcode"
  },
  "geometry": {"coordinates":[-2.521718,52.714471],"type":"Point"}
}
