{
  "type": "Feature",
  "properties": {
    "iso:country":"GB",
    "wof:name":"SG19 1RT",
    "wof:placetype":"postalcode"
},
  "geometry": {"coordinates":[-0.29178064043635,52.11978780487128],"type":"Point"}
}