{
  "type": "Feature",
  "properties": {
    "date:inception_lower": "1988-03-01",
    "date:inception_upper": "1988-03-01",
    "iso:country": "GB",
    "wof:name": "SG19 1RT",
    "wof:placetype": "postalcode"
  },
  "geometry": {"coordinates":[-0.291781,52.119788],"type":"Point"}
}
