{
  "type": "Feature",
  "properties": {
    "iso:country":"GB",
    "wof:name":"SL3 6BQ",
    "wof:placetype":"postalcode"
},
  "geometry": {"coordinates":[-0.55790107542179,51.52019268499089],"type":"Point"}
}