{
  "type": "Feature",
  "properties": {
    "iso:country":"GB",
    "wof:name":"DG9 7PX",
    "wof:placetype":"postalcode"
},
  "geometry": {"coordinates":[-5.0305089726843,54.8998188970739],"type":"Point"}
}