{
  "type": "Feature",
  "properties": {
    "iso:country": "GB",
    "wof:name": "DG9 7PX",
    "wof:placetype": "postalcode"
  },
  "geometry": {"coordinates":[-5.030509,54.899819],"type":"Point"}
}
