{
  "type": "Feature",
  "properties": {
    "iso:country":"GB",
    "wof:name":"E12 6TX",
    "wof:placetype":"postalcode"
},
  "geometry": {"coordinates":[0.04693868665573,51.54585492358051],"type":"Point"}
}