{
  "type": "Feature",
  "properties": {
    "iso:country":"GB",
    "wof:name":"NE24 3LR",
    "wof:placetype":"postalcode"
},
  "geometry": {"coordinates":[-1.52136709073169,55.1133047907681],"type":"Point"}
}