{
  "type": "Feature",
  "properties": {
    "date:inception_lower": "2004-10-01",
    "date:inception_upper": "2004-10-01",
    "iso:country": "GB",
    "wof:name": "NN8 2QA",
    "wof:placetype": "postalcode"
  },
  "geometry": {"coordinates":[-0.695036,52.288036],"type":"Point"}
}
