{
  "type": "Feature",
  "properties": {
    "iso:country": "GB",
    "wof:name": "CV11 6HX",
    "wof:placetype": "postalcode"
  },
  "geometry": {"coordinates":[-1.440809,52.53091],"type":"Point"}
}
