{
  "type": "Feature",
  "properties": {
    "iso:country": "GB",
    "wof:name": "CV37 6SU",
    "wof:placetype": "postalcode"
  },
  "geometry": {"coordinates":[-1.707087,52.200859],"type":"Point"}
}
