{
  "type": "Feature",
  "properties": {
    "date:inception_lower":"1980-01-01",
    "date:inception_upper":"1980-01-31",
    "iso:country":"GB",
    "wof:name":"CV37 6SU",
    "wof:placetype":"postalcode"
},
  "geometry": {"coordinates":[-1.707087,52.200859],"type":"Point"}
}