{
  "type": "Feature",
  "properties": {
    "iso:country": "GB",
    "wof:name": "UB9 6AX",
    "wof:placetype": "postalcode"
  },
  "geometry": {"coordinates":[-0.481735,51.587904],"type":"Point"}
}
