{
  "type": "Feature",
  "properties": {
    "iso:country":"GB",
    "wof:name":"UB9 6AX",
    "wof:placetype":"postalcode"
},
  "geometry": {"coordinates":[-0.48173546584899,51.58790430514703],"type":"Point"}
}