{
  "type": "Feature",
  "properties": {
    "date:inception_lower":"1997-12-01",
    "date:inception_upper":"1997-12-31",
    "iso:country":"GB",
    "wof:name":"PR8 3QJ",
    "wof:placetype":"postalcode"
},
  "geometry": {"coordinates":[-3.035652,53.595718],"type":"Point"}
}