{
  "type": "Feature",
  "properties": {
    "date:inception_lower": "1993-08-01",
    "date:inception_upper": "1993-08-01",
    "iso:country": "GB",
    "wof:name": "HU17 0RZ",
    "wof:placetype": "postalcode"
  },
  "geometry": {"coordinates":[-0.413835,53.836093],"type":"Point"}
}
