{
  "type": "Feature",
  "properties": {
    "iso:country":"GB",
    "wof:name":"HU17 0RZ",
    "wof:placetype":"postalcode"
},
  "geometry": {"coordinates":[-0.41383554576461,53.83609284058314],"type":"Point"}
}