{
  "type": "Feature",
  "properties": {
    "iso:country": "GB",
    "wof:name": "OL12 0SG",
    "wof:placetype": "postalcode"
  },
  "geometry": {"coordinates":[-2.160331,53.631535],"type":"Point"}
}
