{
  "type": "Feature",
  "properties": {
    "iso:country": "GB",
    "wof:name": "E14 3NW",
    "wof:placetype": "postalcode"
  },
  "geometry": {"coordinates":[-0.013481,51.497147],"type":"Point"}
}
