{
  "type": "Feature",
  "properties": {
    "date:inception_lower":"1980-01-01",
    "date:inception_upper":"1980-01-31",
    "iso:country":"GB",
    "wof:name":"SA15 1QD",
    "wof:placetype":"postalcode"
},
  "geometry": {"coordinates":[-4.139925,51.684416],"type":"Point"}
}