{
  "type": "Feature",
  "properties": {
    "iso:country":"GB",
    "wof:name":"SA15 1QD",
    "wof:placetype":"postalcode"
},
  "geometry": {"coordinates":[-4.13996060175593,51.68440864385101],"type":"Point"}
}