{
  "type": "Feature",
  "properties": {
    "iso:country": "GB",
    "wof:name": "SA15 1QD",
    "wof:placetype": "postalcode"
  },
  "geometry": {"coordinates":[-4.139925,51.684416],"type":"Point"}
}
