{
  "type": "Feature",
  "properties": {
    "iso:country": "GB",
    "wof:name": "OX11 9AL",
    "wof:placetype": "postalcode"
  },
  "geometry": {"coordinates":[-1.18726,51.58857],"type":"Point"}
}
