{
  "type": "Feature",
  "properties": {
    "iso:country":"GB",
    "wof:name":"EH3 7AA",
    "wof:placetype":"postalcode"
},
  "geometry": {"coordinates":[-3.21472228760746,55.94746051967],"type":"Point"}
}