{
  "type": "Feature",
  "properties": {
    "date:inception_lower": "1994-12-01",
    "date:inception_upper": "1994-12-01",
    "iso:country": "GB",
    "wof:name": "BB7 4BF",
    "wof:placetype": "postalcode"
  },
  "geometry": {"coordinates":[-2.354842,53.893698],"type":"Point"}
}
