{
  "type": "Feature",
  "properties": {
    "iso:country":"GB",
    "wof:name":"BB7 4BF",
    "wof:placetype":"postalcode"
},
  "geometry": {"coordinates":[-2.35487269674006,53.89371163213361],"type":"Point"}
}