{
  "type": "Feature",
  "properties": {
    "date:inception_lower": "1997-06-01",
    "date:inception_upper": "1997-06-01",
    "iso:country": "GB",
    "wof:name": "TW1 2ER",
    "wof:placetype": "postalcode"
  },
  "geometry": {"coordinates":[-0.311757,51.455095],"type":"Point"}
}
