{
  "type": "Feature",
  "properties": {
    "iso:country":"GB",
    "wof:name":"TW1 2ER",
    "wof:placetype":"postalcode"
},
  "geometry": {"coordinates":[-0.31175668201447,51.45509507385467],"type":"Point"}
}