{
  "type": "Feature",
  "properties": {
    "iso:country":"GB",
    "wof:name":"BR2 9NA",
    "wof:placetype":"postalcode"
},
  "geometry": {"coordinates":[0.0308766576903,51.39487570255368],"type":"Point"}
}