{
  "type": "Feature",
  "properties": {
    "iso:country": "GB",
    "wof:name": "RH6 0BL",
    "wof:placetype": "postalcode"
  },
  "geometry": {"coordinates":[-0.21948,51.15519],"type":"Point"}
}
