{
  "type": "Feature",
  "properties": {
    "iso:country":"GB",
    "wof:name":"RH6 0BL",
    "wof:placetype":"postalcode"
},
  "geometry": {"coordinates":[-0.21948021964375,51.15518999972923],"type":"Point"}
}