{
  "type": "Feature",
  "properties": {
    "iso:country":"GB",
    "wof:name":"EN7 5AG",
    "wof:placetype":"postalcode"
},
  "geometry": {"coordinates":[-0.052495002002,51.70129180701404],"type":"Point"}
}