{
  "type": "Feature",
  "properties": {
    "iso:country":"GB",
    "wof:name":"PR4 2AJ",
    "wof:placetype":"postalcode"
},
  "geometry": {"coordinates":[-2.87497466456063,53.78192963509924],"type":"Point"}
}