{
  "type": "Feature",
  "properties": {
    "date:inception_lower": "1980-01-01",
    "date:inception_upper": "1980-01-01",
    "iso:country": "GB",
    "wof:name": "PR4 2AJ",
    "wof:placetype": "postalcode"
  },
  "geometry": {"coordinates":[-2.874971,53.781945],"type":"Point"}
}
