{
  "type": "Feature",
  "properties": {
    "iso:country": "GB",
    "wof:name": "NW1 4BF",
    "wof:placetype": "postalcode"
  },
  "geometry": {"coordinates":[-0.144832,51.53117],"type":"Point"}
}
