{
  "type": "Feature",
  "properties": {
    "iso:country":"GB",
    "wof:name":"CV6 3GY",
    "wof:placetype":"postalcode"
},
  "geometry": {"coordinates":[-1.51266798305009,52.4313212611062],"type":"Point"}
}