{
  "type": "Feature",
  "properties": {
    "date:inception_lower": "1980-01-01",
    "date:inception_upper": "1980-01-01",
    "iso:country": "GB",
    "wof:name": "ST6 7DA",
    "wof:placetype": "postalcode"
  },
  "geometry": {"coordinates":[-2.182436,53.051151],"type":"Point"}
}
