{
  "type": "Feature",
  "properties": {
    "iso:country":"GB",
    "wof:name":"ST6 7DA",
    "wof:placetype":"postalcode"
},
  "geometry": {"coordinates":[-2.18243644946417,53.05115103010434],"type":"Point"}
}