{
  "type": "Feature",
  "properties": {
    "date:inception_lower": "2019-08-01",
    "date:inception_upper": "2019-08-01",
    "iso:country": "GB",
    "wof:name": "CM15 8FG",
    "wof:placetype": "postalcode"
  },
  "geometry": {"coordinates":[0.3079,51.618354],"type":"Point"}
}
