{
  "type": "Feature",
  "properties": {
    "iso:country":"GB",
    "wof:name":"PO7 5DL",
    "wof:placetype":"postalcode"
},
  "geometry": {"coordinates":[-1.04714017990539,50.85896241309214],"type":"Point"}
}