{
  "type": "Feature",
  "properties": {
    "iso:country":"GB",
    "wof:name":"BB11 1BW",
    "wof:placetype":"postalcode"
},
  "geometry": {"coordinates":[-2.2469299954608,53.79105281175818],"type":"Point"}
}