{
  "type": "Feature",
  "properties": {
    "date:inception_lower":"1995-12-01",
    "date:inception_upper":"1995-12-31",
    "iso:country":"GB",
    "wof:name":"BB11 1BW",
    "wof:placetype":"postalcode"
},
  "geometry": {"coordinates":[-2.24693,53.791053],"type":"Point"}
}