{
  "type": "Feature",
  "properties": {
    "date:inception_lower":"1980-01-01",
    "date:inception_upper":"1980-01-31",
    "iso:country":"GB",
    "wof:name":"IV22 2JA",
    "wof:placetype":"postalcode"
},
  "geometry": {"coordinates":[-5.585422,57.840286],"type":"Point"}
}