{
  "type": "Feature",
  "properties": {
    "iso:country":"GB",
    "wof:name":"IV22 2JA",
    "wof:placetype":"postalcode"
},
  "geometry": {"coordinates":[-5.585419434696,57.84078603611106],"type":"Point"}
}