{
  "type": "Feature",
  "properties": {
    "iso:country": "GB",
    "wof:name": "TF10 7JR",
    "wof:placetype": "postalcode"
  },
  "geometry": {"coordinates":[-2.378841,52.776225],"type":"Point"}
}
