{
  "type": "Feature",
  "properties": {
    "iso:country":"GB",
    "wof:name":"PO21 2TH",
    "wof:placetype":"postalcode"
},
  "geometry": {"coordinates":[-0.68377094540919,50.78645439560562],"type":"Point"}
}