{
  "type": "Feature",
  "properties": {
    "date:inception_lower": "1980-01-01",
    "date:inception_upper": "1980-01-01",
    "iso:country": "GB",
    "wof:name": "PO21 2TH",
    "wof:placetype": "postalcode"
  },
  "geometry": {"coordinates":[-0.683771,50.786454],"type":"Point"}
}
