{
  "type": "Feature",
  "properties": {
    "iso:country":"GB",
    "wof:name":"TS15 9QX",
    "wof:placetype":"postalcode"
},
  "geometry": {"coordinates":[-1.35892008721147,54.51196480848228],"type":"Point"}
}