{
  "type": "Feature",
  "properties": {
    "iso:country": "GB",
    "wof:name": "TS15 9QX",
    "wof:placetype": "postalcode"
  },
  "geometry": {"coordinates":[-1.35892,54.511965],"type":"Point"}
}
