{
  "type": "Feature",
  "properties": {
    "iso:country":"GB",
    "wof:name":"TS1 5LL",
    "wof:placetype":"postalcode"
},
  "geometry": {"coordinates":[-1.24430733835456,54.57419482076863],"type":"Point"}
}