{
  "type": "Feature",
  "properties": {
    "date:inception_lower":"2016-03-01",
    "date:inception_upper":"2016-03-31",
    "iso:country":"GB",
    "wof:name":"LL11 0ZZ",
    "wof:placetype":"postalcode"
},
  "geometry": {"coordinates":[-2.993861,53.04748],"type":"Point"}
}