{
  "type": "Feature",
  "properties": {
    "iso:country": "GB",
    "wof:name": "LL11 0ZZ",
    "wof:placetype": "postalcode"
  },
  "geometry": {"coordinates":[-2.993861,53.04748],"type":"Point"}
}
