{
  "type": "Feature",
  "properties": {
    "iso:country":"GB",
    "wof:name":"SO31 8EA",
    "wof:placetype":"postalcode"
},
  "geometry": {"coordinates":[-1.32362711015644,50.88361580464107],"type":"Point"}
}