{
  "type": "Feature",
  "properties": {
    "iso:country": "GB",
    "wof:name": "SO31 8EA",
    "wof:placetype": "postalcode"
  },
  "geometry": {"coordinates":[-1.323645,50.883597],"type":"Point"}
}
