{
  "type": "Feature",
  "properties": {
    "date:inception_lower":"2000-06-01",
    "date:inception_upper":"2000-06-30",
    "iso:country":"GB",
    "wof:name":"SO31 8EA",
    "wof:placetype":"postalcode"
},
  "geometry": {"coordinates":[-1.323645,50.883597],"type":"Point"}
}