{
  "type": "Feature",
  "properties": {
    "iso:country": "GB",
    "wof:name": "W1W 6LN",
    "wof:placetype": "postalcode"
  },
  "geometry": {"coordinates":[-0.142326,51.519707],"type":"Point"}
}
