{
  "type": "Feature",
  "properties": {
    "iso:country":"GB",
    "wof:name":"W1W 6LN",
    "wof:placetype":"postalcode"
},
  "geometry": {"coordinates":[-0.14232560601143,51.51970706149542],"type":"Point"}
}