{
  "type": "Feature",
  "properties": {
    "iso:country": "GB",
    "wof:name": "CM6 2AY",
    "wof:placetype": "postalcode"
  },
  "geometry": {"coordinates":[0.360198,51.877905],"type":"Point"}
}
