{
  "type": "Feature",
  "properties": {
    "iso:country":"GB",
    "wof:name":"CM6 2AY",
    "wof:placetype":"postalcode"
},
  "geometry": {"coordinates":[0.36019816548072,51.8779054384911],"type":"Point"}
}