{
  "type": "Feature",
  "properties": {
    "iso:country":"GB",
    "wof:name":"BA1 3PW",
    "wof:placetype":"postalcode"
},
  "geometry": {"coordinates":[-2.38817390580601,51.38522833920193],"type":"Point"}
}