{
  "type": "Feature",
  "properties": {
    "iso:country":"GB",
    "wof:name":"TS12 2NZ",
    "wof:placetype":"postalcode"
},
  "geometry": {"coordinates":[-0.94588691632044,54.56755127512028],"type":"Point"}
}