{
  "type": "Feature",
  "properties": {
    "iso:country": "GB",
    "wof:name": "KT20 5LW",
    "wof:placetype": "postalcode"
  },
  "geometry": {"coordinates":[-0.229159,51.304878],"type":"Point"}
}
