{
  "type": "Feature",
  "properties": {
    "iso:country":"GB",
    "wof:name":"SS0 0HS",
    "wof:placetype":"postalcode"
},
  "geometry": {"coordinates":[0.67459283790596,51.5611822006301],"type":"Point"}
}