{
  "type": "Feature",
  "properties": {
    "iso:country": "GB",
    "wof:name": "HU5 1JD",
    "wof:placetype": "postalcode"
  },
  "geometry": {"coordinates":[-0.346745,53.759112],"type":"Point"}
}
