{
  "type": "Feature",
  "properties": {
    "iso:country": "GB",
    "wof:name": "G31 2HU",
    "wof:placetype": "postalcode"
  },
  "geometry": {"coordinates":[-4.222772,55.859158],"type":"Point"}
}
