{
  "type": "Feature",
  "properties": {
    "date:inception_lower": "2007-01-01",
    "date:inception_upper": "2007-01-01",
    "iso:country": "GB",
    "wof:name": "ST16 1JS",
    "wof:placetype": "postalcode"
  },
  "geometry": {"coordinates":[-2.151043,52.810471],"type":"Point"}
}
