{
  "type": "Feature",
  "properties": {
    "iso:country": "GB",
    "wof:name": "ST16 1JS",
    "wof:placetype": "postalcode"
  },
  "geometry": {"coordinates":[-2.151043,52.810471],"type":"Point"}
}
