{
  "type": "Feature",
  "properties": {
    "iso:country":"GB",
    "wof:name":"ST16 1JS",
    "wof:placetype":"postalcode"
},
  "geometry": {"coordinates":[-2.15104269021546,52.81047121241586],"type":"Point"}
}