{
  "type": "Feature",
  "properties": {
    "iso:country": "GB",
    "wof:name": "NG19 6RS",
    "wof:placetype": "postalcode"
  },
  "geometry": {"coordinates":[-1.227355,53.137499],"type":"Point"}
}
