{
  "type": "Feature",
  "properties": {
    "iso:country":"GB",
    "wof:name":"BN18 9PD",
    "wof:placetype":"postalcode"
},
  "geometry": {"coordinates":[-0.54222662812809,50.86958529714837],"type":"Point"}
}