{
  "type": "Feature",
  "properties": {
    "date:inception_lower":"1980-01-01",
    "date:inception_upper":"1980-01-31",
    "iso:country":"GB",
    "wof:name":"BN18 9PD",
    "wof:placetype":"postalcode"
},
  "geometry": {"coordinates":[-0.542227,50.869585],"type":"Point"}
}