{
  "type": "Feature",
  "properties": {
    "iso:country":"GB",
    "wof:name":"E3 2PA",
    "wof:placetype":"postalcode"
},
  "geometry": {"coordinates":[-0.02112242325211,51.54018837476234],"type":"Point"}
}