{
  "type": "Feature",
  "properties": {
    "iso:country": "GB",
    "wof:name": "WR9 9AX",
    "wof:placetype": "postalcode"
  },
  "geometry": {"coordinates":[-2.159102,52.278036],"type":"Point"}
}
