{
  "type": "Feature",
  "properties": {
    "iso:country":"GB",
    "wof:name":"EH41 3RS",
    "wof:placetype":"postalcode"
},
  "geometry": {"coordinates":[-2.7946148553612,55.95607985125378],"type":"Point"}
}