{
  "type": "Feature",
  "properties": {
    "date:inception_lower":"1980-01-01",
    "date:inception_upper":"1980-01-31",
    "iso:country":"GB",
    "wof:name":"EH41 3RS",
    "wof:placetype":"postalcode"
},
  "geometry": {"coordinates":[-2.794615,55.95608],"type":"Point"}
}