{
  "type": "Feature",
  "properties": {
    "iso:country":"GB",
    "wof:name":"PH33 6EE",
    "wof:placetype":"postalcode"
},
  "geometry": {"coordinates":[-5.11539794927543,56.81542974117727],"type":"Point"}
}