{
  "type": "Feature",
  "properties": {
    "date:inception_lower":"1980-01-01",
    "date:inception_upper":"1980-01-31",
    "iso:country":"GB",
    "wof:name":"PH33 6EE",
    "wof:placetype":"postalcode"
},
  "geometry": {"coordinates":[-5.1154,56.815412],"type":"Point"}
}