{
  "type": "Feature",
  "properties": {
    "date:inception_lower": "1980-01-01",
    "date:inception_upper": "1980-01-01",
    "iso:country": "GB",
    "wof:name": "NN2 8PQ",
    "wof:placetype": "postalcode"
  },
  "geometry": {"coordinates":[-0.890307,52.273417],"type":"Point"}
}
