{
  "type": "Feature",
  "properties": {
    "iso:country":"GB",
    "wof:name":"BS4 4BX",
    "wof:placetype":"postalcode"
},
  "geometry": {"coordinates":[-2.54060049401936,51.45118936794439],"type":"Point"}
}