{
  "type": "Feature",
  "properties": {
    "iso:country": "GB",
    "wof:name": "BS4 4BX",
    "wof:placetype": "postalcode"
  },
  "geometry": {"coordinates":[-2.5406,51.451189],"type":"Point"}
}
