{
  "type": "Feature",
  "properties": {
    "date:inception_lower":"1986-07-01",
    "date:inception_upper":"1986-07-31",
    "iso:country":"GB",
    "wof:name":"ME19 5QX",
    "wof:placetype":"postalcode"
},
  "geometry": {"coordinates":[0.426448,51.303828],"type":"Point"}
}