{
  "type": "Feature",
  "properties": {
    "iso:country":"GB",
    "wof:name":"B12 9DB",
    "wof:placetype":"postalcode"
},
  "geometry": {"coordinates":[-1.88570196734856,52.46106430572198],"type":"Point"}
}