{
  "type": "Feature",
  "properties": {
    "iso:country":"GB",
    "wof:name":"NE3 3QU",
    "wof:placetype":"postalcode"
},
  "geometry": {"coordinates":[-1.65498370287256,55.00521272543714],"type":"Point"}
}