{
  "type": "Feature",
  "properties": {
    "iso:country": "GB",
    "wof:name": "NE3 3QU",
    "wof:placetype": "postalcode"
  },
  "geometry": {"coordinates":[-1.654984,55.005213],"type":"Point"}
}
