{
  "type": "Feature",
  "properties": {
    "iso:country": "GB",
    "wof:name": "PO12 4DS",
    "wof:placetype": "postalcode"
  },
  "geometry": {"coordinates":[-1.152319,50.814486],"type":"Point"}
}
