{
  "type": "Feature",
  "properties": {
    "iso:country":"GB",
    "wof:name":"PO12 4DS",
    "wof:placetype":"postalcode"
},
  "geometry": {"coordinates":[-1.15231871934978,50.81448632768357],"type":"Point"}
}