{
  "type": "Feature",
  "properties": {
    "iso:country":"GB",
    "wof:name":"LL29 7NE",
    "wof:placetype":"postalcode"
},
  "geometry": {"coordinates":[-3.74559778598502,53.29817609565753],"type":"Point"}
}