{
  "type": "Feature",
  "properties": {
    "iso:country": "GB",
    "wof:name": "LL29 7NE",
    "wof:placetype": "postalcode"
  },
  "geometry": {"coordinates":[-3.745598,53.298176],"type":"Point"}
}
