{
  "type": "Feature",
  "properties": {
    "iso:country":"GB",
    "wof:name":"BN25 3JT",
    "wof:placetype":"postalcode"
},
  "geometry": {"coordinates":[0.12641731321049,50.78194405984937],"type":"Point"}
}