{
  "type": "Feature",
  "properties": {
    "date:inception_lower":"1980-01-01",
    "date:inception_upper":"1980-01-31",
    "iso:country":"GB",
    "wof:name":"SR8 4EH",
    "wof:placetype":"postalcode"
},
  "geometry": {"coordinates":[-1.311396,54.762241],"type":"Point"}
}