{
  "type": "Feature",
  "properties": {
    "iso:country":"GB",
    "wof:name":"SR8 4EH",
    "wof:placetype":"postalcode"
},
  "geometry": {"coordinates":[-1.3113960059866,54.76224068629841],"type":"Point"}
}