{
  "type": "Feature",
  "properties": {
    "date:inception_lower": "1980-01-01",
    "date:inception_upper": "1980-01-01",
    "iso:country": "GB",
    "wof:name": "SR8 4EH",
    "wof:placetype": "postalcode"
  },
  "geometry": {"coordinates":[-1.311365,54.762151],"type":"Point"}
}
