{
  "type": "Feature",
  "properties": {
    "date:inception_lower": "1993-01-01",
    "date:inception_upper": "1993-01-01",
    "iso:country": "GB",
    "wof:name": "SG14 3BQ",
    "wof:placetype": "postalcode"
  },
  "geometry": {"coordinates":[-0.084363,51.80297],"type":"Point"}
}
