{
  "type": "Feature",
  "properties": {
    "iso:country":"GB",
    "wof:name":"W9 2AY",
    "wof:placetype":"postalcode"
},
  "geometry": {"coordinates":[-0.19519474197456,51.52412043753231],"type":"Point"}
}