{
  "type": "Feature",
  "properties": {
    "date:inception_lower": "1993-01-01",
    "date:inception_upper": "1993-01-01",
    "iso:country": "GB",
    "wof:name": "PE12 9RP",
    "wof:placetype": "postalcode"
  },
  "geometry": {"coordinates":[0.114131,52.782424],"type":"Point"}
}
