{
  "type": "Feature",
  "properties": {
    "iso:country": "GB",
    "wof:name": "PE12 9RP",
    "wof:placetype": "postalcode"
  },
  "geometry": {"coordinates":[0.114131,52.782424],"type":"Point"}
}
