{
  "type": "Feature",
  "properties": {
    "iso:country":"GB",
    "wof:name":"NW1 6RB",
    "wof:placetype":"postalcode"
},
  "geometry": {"coordinates":[-0.16288696600553,51.52562421614724],"type":"Point"}
}