{
  "type": "Feature",
  "properties": {
    "iso:country": "GB",
    "wof:name": "BN22 8RA",
    "wof:placetype": "postalcode"
  },
  "geometry": {"coordinates":[0.300602,50.782577],"type":"Point"}
}
