{
  "type": "Feature",
  "properties": {
    "date:inception_lower": "1980-01-01",
    "date:inception_upper": "1980-01-01",
    "iso:country": "GB",
    "wof:name": "BN22 8RA",
    "wof:placetype": "postalcode"
  },
  "geometry": {"coordinates":[0.300602,50.782577],"type":"Point"}
}
