{
  "type": "Feature",
  "properties": {
    "iso:country":"GB",
    "wof:name":"M22 9NG",
    "wof:placetype":"postalcode"
},
  "geometry": {"coordinates":[-2.26236824831642,53.38672631382285],"type":"Point"}
}