{
  "type": "Feature",
  "properties": {
    "iso:country": "GB",
    "wof:name": "SA62 3EY",
    "wof:placetype": "postalcode"
  },
  "geometry": {"coordinates":[-4.998734,51.753257],"type":"Point"}
}
