{
  "type": "Feature",
  "properties": {
    "iso:country":"GB",
    "wof:name":"SA62 3EY",
    "wof:placetype":"postalcode"
},
  "geometry": {"coordinates":[-4.9987345137207,51.75325686320657],"type":"Point"}
}