{
  "type": "Feature",
  "properties": {
    "date:inception_lower":"1990-07-01",
    "date:inception_upper":"1990-07-31",
    "iso:country":"GB",
    "wof:name":"HP9 1TL",
    "wof:placetype":"postalcode"
},
  "geometry": {"coordinates":[-0.650636,51.613832],"type":"Point"}
}