{
  "type": "Feature",
  "properties": {
    "iso:country":"GB",
    "wof:name":"BS39 5SU",
    "wof:placetype":"postalcode"
},
  "geometry": {"coordinates":[-2.54087423414564,51.32816335839247],"type":"Point"}
}