{
  "type": "Feature",
  "properties": {
    "date:inception_lower": "1980-01-01",
    "date:inception_upper": "1980-01-01",
    "iso:country": "GB",
    "wof:name": "SG11 2HF",
    "wof:placetype": "postalcode"
  },
  "geometry": {"coordinates":[0.103107,51.869582],"type":"Point"}
}
