{
  "type": "Feature",
  "properties": {
    "iso:country":"GB",
    "wof:name":"B33 9JE",
    "wof:placetype":"postalcode"
},
  "geometry": {"coordinates":[-1.79679131080919,52.48996483823611],"type":"Point"}
}