{
  "type": "Feature",
  "properties": {
    "date:inception_lower": "2019-01-01",
    "date:inception_upper": "2019-01-01",
    "iso:country": "GB",
    "wof:name": "TA3 6FD",
    "wof:placetype": "postalcode"
  },
  "geometry": {"coordinates":[-2.99706,51.000468],"type":"Point"}
}
