{
  "type": "Feature",
  "properties": {
    "iso:country":"GB",
    "wof:name":"WR5 2LW",
    "wof:placetype":"postalcode"
},
  "geometry": {"coordinates":[-2.18649234582038,52.17948823325177],"type":"Point"}
}