{
  "type": "Feature",
  "properties": {
    "iso:country":"GB",
    "wof:name":"CF24 0JQ",
    "wof:placetype":"postalcode"
},
  "geometry": {"coordinates":[-3.16101136819092,51.48213192598867],"type":"Point"}
}