{
  "type": "Feature",
  "properties": {
    "iso:country":"GB",
    "wof:name":"SY18 6JL",
    "wof:placetype":"postalcode"
},
  "geometry": {"coordinates":[-3.51456225415591,52.4189797743166],"type":"Point"}
}