{
  "type": "Feature",
  "properties": {
    "iso:country": "GB",
    "wof:name": "EH3 1EH",
    "wof:placetype": "postalcode"
  },
  "geometry": {"coordinates":[-3.232954,55.943218],"type":"Point"}
}
