{
  "type": "Feature",
  "properties": {
    "iso:country": "GB",
    "wof:name": "SS14 2GD",
    "wof:placetype": "postalcode"
  },
  "geometry": {"coordinates":[0.469123,51.581075],"type":"Point"}
}
