{
  "type": "Feature",
  "properties": {
    "iso:country":"GB",
    "wof:name":"BB3 0NF",
    "wof:placetype":"postalcode"
},
  "geometry": {"coordinates":[-2.52242608642276,53.70108697861684],"type":"Point"}
}