{
  "type": "Feature",
  "properties": {
    "iso:country": "GB",
    "wof:name": "BB3 0NF",
    "wof:placetype": "postalcode"
  },
  "geometry": {"coordinates":[-2.522499,53.701085],"type":"Point"}
}
