{
  "type": "Feature",
  "properties": {
    "iso:country":"GB",
    "wof:name":"M30 7BT",
    "wof:placetype":"postalcode"
},
  "geometry": {"coordinates":[-2.36678720360845,53.47755902982491],"type":"Point"}
}