{
  "type": "Feature",
  "properties": {
    "iso:country":"GB",
    "wof:name":"S66 9BW",
    "wof:placetype":"postalcode"
},
  "geometry": {"coordinates":[-1.23654101438427,53.38546576950024],"type":"Point"}
}