{
  "type": "Feature",
  "properties": {
    "date:inception_lower": "1980-01-01",
    "date:inception_upper": "1980-01-01",
    "iso:country": "GB",
    "wof:name": "S66 9BW",
    "wof:placetype": "postalcode"
  },
  "geometry": {"coordinates":[-1.236541,53.385466],"type":"Point"}
}
