{
  "type": "Feature",
  "properties": {
    "iso:country": "GB",
    "wof:name": "S66 9BW",
    "wof:placetype": "postalcode"
  },
  "geometry": {"coordinates":[-1.236541,53.385466],"type":"Point"}
}
