{
  "type": "Feature",
  "properties": {
    "date:inception_lower": "1988-03-01",
    "date:inception_upper": "1988-03-01",
    "iso:country": "GB",
    "wof:name": "CB8 8AY",
    "wof:placetype": "postalcode"
  },
  "geometry": {"coordinates":[0.419796,52.24244],"type":"Point"}
}
