{
  "type": "Feature",
  "properties": {
    "iso:country":"GB",
    "wof:name":"CB8 8AY",
    "wof:placetype":"postalcode"
},
  "geometry": {"coordinates":[0.41979645516723,52.24243954186824],"type":"Point"}
}