{
  "type": "Feature",
  "properties": {
    "iso:country": "GB",
    "wof:name": "BS6 5QX",
    "wof:placetype": "postalcode"
  },
  "geometry": {"coordinates":[-2.59234,51.468067],"type":"Point"}
}
