{
  "type": "Feature",
  "properties": {
    "date:inception_lower": "1980-01-01",
    "date:inception_upper": "1980-01-01",
    "iso:country": "GB",
    "wof:name": "PE9 3RP",
    "wof:placetype": "postalcode"
  },
  "geometry": {"coordinates":[-0.55621,52.628113],"type":"Point"}
}
