{
  "type": "Feature",
  "properties": {
    "iso:country":"GB",
    "wof:name":"PE9 3RP",
    "wof:placetype":"postalcode"
},
  "geometry": {"coordinates":[-0.55621034897534,52.62811282127669],"type":"Point"}
}