{
  "type": "Feature",
  "properties": {
    "iso:country":"GB",
    "wof:name":"S25 4AF",
    "wof:placetype":"postalcode"
},
  "geometry": {"coordinates":[-1.22308721702911,53.35392705701454],"type":"Point"}
}