{
  "type": "Feature",
  "properties": {
    "iso:country": "GB",
    "wof:name": "S61 3BB",
    "wof:placetype": "postalcode"
  },
  "geometry": {"coordinates":[-1.404327,53.447148],"type":"Point"}
}
