{
  "type": "Feature",
  "properties": {
    "date:inception_lower": "2003-01-01",
    "date:inception_upper": "2003-01-01",
    "iso:country": "GB",
    "wof:name": "PO33 1RF",
    "wof:placetype": "postalcode"
  },
  "geometry": {"coordinates":[-1.143337,50.713474],"type":"Point"}
}
