{
  "type": "Feature",
  "properties": {
    "iso:country": "GB",
    "wof:name": "PO33 1RF",
    "wof:placetype": "postalcode"
  },
  "geometry": {"coordinates":[-1.143337,50.713474],"type":"Point"}
}
