{
  "type": "Feature",
  "properties": {
    "iso:country":"GB",
    "wof:name":"PO33 1RF",
    "wof:placetype":"postalcode"
},
  "geometry": {"coordinates":[-1.14357416237242,50.71352324204687],"type":"Point"}
}