{
  "type": "Feature",
  "properties": {
    "iso:country":"GB",
    "wof:name":"SO16 3DX",
    "wof:placetype":"postalcode"
},
  "geometry": {"coordinates":[-1.38171961042208,50.94313529187676],"type":"Point"}
}