{
  "type": "Feature",
  "properties": {
    "iso:country": "GB",
    "wof:name": "SO16 3DX",
    "wof:placetype": "postalcode"
  },
  "geometry": {"coordinates":[-1.38172,50.943135],"type":"Point"}
}
