{
  "type": "Feature",
  "properties": {
    "iso:country":"GB",
    "wof:name":"NP20 2HH",
    "wof:placetype":"postalcode"
},
  "geometry": {"coordinates":[-2.9946588824576,51.57314690391882],"type":"Point"}
}