{
  "type": "Feature",
  "properties": {
    "iso:country":"GB",
    "wof:name":"SK8 3BX",
    "wof:placetype":"postalcode"
},
  "geometry": {"coordinates":[-2.22218485436365,53.36469595278533],"type":"Point"}
}