{
  "type": "Feature",
  "properties": {
    "iso:country":"GB",
    "wof:name":"SP11 8BY",
    "wof:placetype":"postalcode"
},
  "geometry": {"coordinates":[-1.53881239324818,51.20344729916078],"type":"Point"}
}