{
  "type": "Feature",
  "properties": {
    "iso:country": "GB",
    "wof:name": "SP11 8BY",
    "wof:placetype": "postalcode"
  },
  "geometry": {"coordinates":[-1.538812,51.203447],"type":"Point"}
}
