{
  "type": "Feature",
  "properties": {
    "iso:country":"GB",
    "wof:name":"CO15 4BH",
    "wof:placetype":"postalcode"
},
  "geometry": {"coordinates":[1.17836037372079,51.8066045318214],"type":"Point"}
}