{
  "type": "Feature",
  "properties": {
    "iso:country":"GB",
    "wof:name":"TS8 0TQ",
    "wof:placetype":"postalcode"
},
  "geometry": {"coordinates":[-1.22359591061045,54.52115672008613],"type":"Point"}
}