{
  "type": "Feature",
  "properties": {
    "iso:country": "GB",
    "wof:name": "TS8 0TQ",
    "wof:placetype": "postalcode"
  },
  "geometry": {"coordinates":[-1.223579,54.52116],"type":"Point"}
}
