{
  "type": "Feature",
  "properties": {
    "iso:country": "GB",
    "wof:name": "HP2 7NS",
    "wof:placetype": "postalcode"
  },
  "geometry": {"coordinates":[-0.440046,51.779444],"type":"Point"}
}
