{
  "type": "Feature",
  "properties": {
    "iso:country":"GB",
    "wof:name":"HP2 7NS",
    "wof:placetype":"postalcode"
},
  "geometry": {"coordinates":[-0.44004592056226,51.77944364630135],"type":"Point"}
}