{
  "type": "Feature",
  "properties": {
    "iso:country":"GB",
    "wof:name":"ME1 3HX",
    "wof:placetype":"postalcode"
},
  "geometry": {"coordinates":[0.48511165873445,51.3743659797297],"type":"Point"}
}