{
  "type": "Feature",
  "properties": {
    "iso:country":"GB",
    "wof:name":"M23 0ET",
    "wof:placetype":"postalcode"
},
  "geometry": {"coordinates":[-2.28314391249085,53.41345581220781],"type":"Point"}
}