{
  "type": "Feature",
  "properties": {
    "iso:country":"GB",
    "wof:name":"SL1 2XY",
    "wof:placetype":"postalcode"
},
  "geometry": {"coordinates":[-0.61749452881036,51.50945424026524],"type":"Point"}
}