{
  "type": "Feature",
  "properties": {
    "date:inception_lower": "1980-01-01",
    "date:inception_upper": "1980-01-01",
    "iso:country": "GB",
    "wof:name": "SL1 2XY",
    "wof:placetype": "postalcode"
  },
  "geometry": {"coordinates":[-0.617494,51.509454],"type":"Point"}
}
