{
  "type": "Feature",
  "properties": {
    "iso:country":"GB",
    "wof:name":"SA63 4TS",
    "wof:placetype":"postalcode"
},
  "geometry": {"coordinates":[-4.83846673688049,51.90855645642077],"type":"Point"}
}