{
  "type": "Feature",
  "properties": {
    "date:inception_lower":"1980-01-01",
    "date:inception_upper":"1980-01-31",
    "iso:country":"GB",
    "wof:name":"SA63 4TS",
    "wof:placetype":"postalcode"
},
  "geometry": {"coordinates":[-4.838495,51.90857],"type":"Point"}
}