{
  "type": "Feature",
  "properties": {
    "iso:country":"GB",
    "wof:name":"HG3 2XL",
    "wof:placetype":"postalcode"
},
  "geometry": {"coordinates":[-1.55671065940401,53.99976329073476],"type":"Point"}
}