{
  "type": "Feature",
  "properties": {
    "iso:country":"GB",
    "wof:name":"SW11 3DR",
    "wof:placetype":"postalcode"
},
  "geometry": {"coordinates":[-0.17129736317796,51.47364415152861],"type":"Point"}
}