{
  "type": "Feature",
  "properties": {
    "date:inception_lower":"1980-01-01",
    "date:inception_upper":"1980-01-31",
    "iso:country":"GB",
    "wof:name":"SW11 3DR",
    "wof:placetype":"postalcode"
},
  "geometry": {"coordinates":[-0.171201,51.473626],"type":"Point"}
}