{
  "type": "Feature",
  "properties": {
    "iso:country": "GB",
    "wof:name": "SW11 3DR",
    "wof:placetype": "postalcode"
  },
  "geometry": {"coordinates":[-0.171201,51.473626],"type":"Point"}
}
