{
  "type": "Feature",
  "properties": {
    "iso:country":"GB",
    "wof:name":"UB8 1QZ",
    "wof:placetype":"postalcode"
},
  "geometry": {"coordinates":[-0.47262969507537,51.55036113223209],"type":"Point"}
}