{
  "type": "Feature",
  "properties": {
    "iso:country":"GB",
    "wof:name":"CF23 6EW",
    "wof:placetype":"postalcode"
},
  "geometry": {"coordinates":[-3.16914907076285,51.51369350591902],"type":"Point"}
}