{
  "type": "Feature",
  "properties": {
    "date:inception_lower": "1980-01-01",
    "date:inception_upper": "1980-01-01",
    "iso:country": "GB",
    "wof:name": "DT9 4BS",
    "wof:placetype": "postalcode"
  },
  "geometry": {"coordinates":[-2.529508,50.953568],"type":"Point"}
}
