{
  "type": "Feature",
  "properties": {
    "date:inception_lower": "2013-07-01",
    "date:inception_upper": "2013-07-01",
    "iso:country": "GB",
    "wof:name": "E4 9BW",
    "wof:placetype": "postalcode"
  },
  "geometry": {"coordinates":[-0.001493,51.607769],"type":"Point"}
}
