{
  "type": "Feature",
  "properties": {
    "iso:country":"GB",
    "wof:name":"E4 9BW",
    "wof:placetype":"postalcode"
},
  "geometry": {"coordinates":[-0.00143092183374,51.60779355751747],"type":"Point"}
}