{
  "type": "Feature",
  "properties": {
    "iso:country": "GB",
    "wof:name": "NR13 3RH",
    "wof:placetype": "postalcode"
  },
  "geometry": {"coordinates":[1.555482,52.641673],"type":"Point"}
}
