{
  "type": "Feature",
  "properties": {
    "date:inception_lower": "1990-07-01",
    "date:inception_upper": "1990-07-01",
    "iso:country": "GB",
    "wof:name": "NR13 3RH",
    "wof:placetype": "postalcode"
  },
  "geometry": {"coordinates":[1.555482,52.641673],"type":"Point"}
}
