{
  "type": "Feature",
  "properties": {
    "iso:country":"GB",
    "wof:name":"TW1 1QR",
    "wof:placetype":"postalcode"
},
  "geometry": {"coordinates":[-0.31878745736432,51.4596113676608],"type":"Point"}
}