{
  "type": "Feature",
  "properties": {
    "iso:country": "GB",
    "wof:name": "TW1 1QR",
    "wof:placetype": "postalcode"
  },
  "geometry": {"coordinates":[-0.318787,51.459611],"type":"Point"}
}
