{
  "type": "Feature",
  "properties": {
    "iso:country":"GB",
    "wof:name":"EH49 6PH",
    "wof:placetype":"postalcode"
},
  "geometry": {"coordinates":[-3.57101074026834,55.95824096659547],"type":"Point"}
}