{
  "type": "Feature",
  "properties": {
    "iso:country":"GB",
    "wof:name":"GU3 3AA",
    "wof:placetype":"postalcode"
},
  "geometry": {"coordinates":[-0.60462643044325,51.2537875804008],"type":"Point"}
}