{
  "type": "Feature",
  "properties": {
    "date:inception_lower": "1999-06-01",
    "date:inception_upper": "1999-06-01",
    "iso:country": "GB",
    "wof:name": "MK41 0UZ",
    "wof:placetype": "postalcode"
  },
  "geometry": {"coordinates":[-0.428596,52.14567],"type":"Point"}
}
