{
  "type": "Feature",
  "properties": {
    "date:inception_lower":"2003-06-01",
    "date:inception_upper":"2003-06-30",
    "iso:country":"GB",
    "wof:name":"L3 4EY",
    "wof:placetype":"postalcode"
},
  "geometry": {"coordinates":[-2.988578,53.398498],"type":"Point"}
}