{
  "type": "Feature",
  "properties": {
    "iso:country": "GB",
    "wof:name": "L3 4EY",
    "wof:placetype": "postalcode"
  },
  "geometry": {"coordinates":[-2.988578,53.398498],"type":"Point"}
}
