{
  "type": "Feature",
  "properties": {
    "iso:country":"GB",
    "wof:name":"S66 1NQ",
    "wof:placetype":"postalcode"
},
  "geometry": {"coordinates":[-1.27963047026817,53.41402107431668],"type":"Point"}
}