{
  "type": "Feature",
  "properties": {
    "iso:country":"GB",
    "wof:name":"BR5 2LH",
    "wof:placetype":"postalcode"
},
  "geometry": {"coordinates":[0.11132622208031,51.39687991741739],"type":"Point"}
}