{
  "type": "Feature",
  "properties": {
    "iso:country": "GB",
    "wof:name": "BR5 2LH",
    "wof:placetype": "postalcode"
  },
  "geometry": {"coordinates":[0.111311,51.396916],"type":"Point"}
}
