{
  "type": "Feature",
  "properties": {
    "iso:country":"GB",
    "wof:name":"B79 7EN",
    "wof:placetype":"postalcode"
},
  "geometry": {"coordinates":[-1.69969989619528,52.63815412494745],"type":"Point"}
}