{
  "type": "Feature",
  "properties": {
    "date:inception_lower":"1980-01-01",
    "date:inception_upper":"1980-01-31",
    "iso:country":"GB",
    "wof:name":"B79 7EN",
    "wof:placetype":"postalcode"
},
  "geometry": {"coordinates":[-1.6997,52.638154],"type":"Point"}
}