{
  "type": "Feature",
  "properties": {
    "iso:country": "GB",
    "wof:name": "BN27 3YP",
    "wof:placetype": "postalcode"
  },
  "geometry": {"coordinates":[0.245039,50.855247],"type":"Point"}
}
