{
  "type": "Feature",
  "properties": {
    "iso:country":"GB",
    "wof:name":"SL4 4LA",
    "wof:placetype":"postalcode"
},
  "geometry": {"coordinates":[-0.65298612444553,51.47867379459439],"type":"Point"}
}