{
  "type": "Feature",
  "properties": {
    "iso:country": "GB",
    "wof:name": "SL4 4LA",
    "wof:placetype": "postalcode"
  },
  "geometry": {"coordinates":[-0.652868,51.478665],"type":"Point"}
}
