{
  "type": "Feature",
  "properties": {
    "iso:country":"GB",
    "wof:name":"RM11 2FA",
    "wof:placetype":"postalcode"
},
  "geometry": {"coordinates":[0.21682012432226,51.58489017325279],"type":"Point"}
}