{
  "type": "Feature",
  "properties": {
    "date:inception_lower": "2015-11-01",
    "date:inception_upper": "2015-11-01",
    "iso:country": "GB",
    "wof:name": "RM11 2FA",
    "wof:placetype": "postalcode"
  },
  "geometry": {"coordinates":[0.215667,51.584977],"type":"Point"}
}
