{
  "type": "Feature",
  "properties": {
    "date:inception_lower": "2022-08-01",
    "date:inception_upper": "2022-08-01",
    "iso:country": "GB",
    "wof:name": "NE13 9NY",
    "wof:placetype": "postalcode"
  },
  "geometry": {"coordinates":[-1.644312,55.030737],"type":"Point"}
}
