{
  "type": "Feature",
  "properties": {
    "iso:country":"GB",
    "wof:name":"PL5 3QJ",
    "wof:placetype":"postalcode"
},
  "geometry": {"coordinates":[-4.16372413836586,50.41355103682212],"type":"Point"}
}