{
  "type": "Feature",
  "properties": {
    "date:inception_lower":"1980-01-01",
    "date:inception_upper":"1980-01-31",
    "iso:country":"GB",
    "wof:name":"PL5 3QJ",
    "wof:placetype":"postalcode"
},
  "geometry": {"coordinates":[-4.163724,50.413551],"type":"Point"}
}