{
  "type": "Feature",
  "properties": {
    "iso:country":"GB",
    "wof:name":"NW9 5WL",
    "wof:placetype":"postalcode"
},
  "geometry": {"coordinates":[-0.25080740894862,51.60387043849739],"type":"Point"}
}