{
  "type": "Feature",
  "properties": {
    "iso:country": "GB",
    "wof:name": "LA12 9QX",
    "wof:placetype": "postalcode"
  },
  "geometry": {"coordinates":[-3.079259,54.161462],"type":"Point"}
}
