{
  "type": "Feature",
  "properties": {
    "iso:country":"GB",
    "wof:name":"LA12 9QX",
    "wof:placetype":"postalcode"
},
  "geometry": {"coordinates":[-3.07925942903582,54.16145330649513],"type":"Point"}
}