{
  "type": "Feature",
  "properties": {
    "iso:country":"GB",
    "wof:name":"SN5 3LZ",
    "wof:placetype":"postalcode"
},
  "geometry": {"coordinates":[-1.85828544946286,51.56843117900596],"type":"Point"}
}