{
  "type": "Feature",
  "properties": {
    "iso:country": "GB",
    "wof:name": "SN5 3LZ",
    "wof:placetype": "postalcode"
  },
  "geometry": {"coordinates":[-1.858285,51.568431],"type":"Point"}
}
