{
  "type": "Feature",
  "properties": {
    "iso:country":"GB",
    "wof:name":"WR13 6NZ",
    "wof:placetype":"postalcode"
},
  "geometry": {"coordinates":[-2.26039242302951,52.10716341962662],"type":"Point"}
}