{
  "type": "Feature",
  "properties": {
    "iso:country": "GB",
    "wof:name": "CM18 6ST",
    "wof:placetype": "postalcode"
  },
  "geometry": {"coordinates":[0.09754,51.75796],"type":"Point"}
}
