{
  "type": "Feature",
  "properties": {
    "iso:country":"GB",
    "wof:name":"CO16 8UN",
    "wof:placetype":"postalcode"
},
  "geometry": {"coordinates":[1.13525198316777,51.80197053410896],"type":"Point"}
}