{
  "type": "Feature",
  "properties": {
    "date:inception_lower": "1980-01-01",
    "date:inception_upper": "1980-01-01",
    "iso:country": "GB",
    "wof:name": "CO16 8UN",
    "wof:placetype": "postalcode"
  },
  "geometry": {"coordinates":[1.135252,51.801971],"type":"Point"}
}
