{
  "type": "Feature",
  "properties": {
    "iso:country":"GB",
    "wof:name":"CT2 7NP",
    "wof:placetype":"postalcode"
},
  "geometry": {"coordinates":[1.06508917069141,51.29522119853286],"type":"Point"}
}