{
  "type": "Feature",
  "properties": {
    "date:inception_lower":"1992-08-01",
    "date:inception_upper":"1992-08-31",
    "iso:country":"GB",
    "wof:name":"SS13 1NS",
    "wof:placetype":"postalcode"
},
  "geometry": {"coordinates":[0.510671,51.579321],"type":"Point"}
}