{
  "type": "Feature",
  "properties": {
    "iso:country":"GB",
    "wof:name":"SS13 1NS",
    "wof:placetype":"postalcode"
},
  "geometry": {"coordinates":[0.51067087318391,51.57932072975223],"type":"Point"}
}