{
  "type": "Feature",
  "properties": {
    "iso:country": "GB",
    "wof:name": "L37 4ED",
    "wof:placetype": "postalcode"
  },
  "geometry": {"coordinates":[-3.063199,53.556088],"type":"Point"}
}
