{
  "type": "Feature",
  "properties": {
    "iso:country":"GB",
    "wof:name":"L37 4ED",
    "wof:placetype":"postalcode"
},
  "geometry": {"coordinates":[-3.06319931172093,53.55608813127875],"type":"Point"}
}