{
  "type": "Feature",
  "properties": {
    "iso:country":"GB",
    "wof:name":"DN33 1JT",
    "wof:placetype":"postalcode"
},
  "geometry": {"coordinates":[-0.10685008004378,53.54495430249082],"type":"Point"}
}