{
  "type": "Feature",
  "properties": {
    "iso:country":"GB",
    "wof:name":"TA24 5HY",
    "wof:placetype":"postalcode"
},
  "geometry": {"coordinates":[-3.48168836625942,51.20130090568679],"type":"Point"}
}