{
  "type": "Feature",
  "properties": {
    "iso:country":"GB",
    "wof:name":"G72 7HU",
    "wof:placetype":"postalcode"
},
  "geometry": {"coordinates":[-4.16654911192782,55.82085997636437],"type":"Point"}
}