{
  "type": "Feature",
  "properties": {
    "iso:country":"GB",
    "wof:name":"EN2 0EA",
    "wof:placetype":"postalcode"
},
  "geometry": {"coordinates":[-0.07955396880959,51.66787213975365],"type":"Point"}
}