{
  "type": "Feature",
  "properties": {
    "iso:country":"GB",
    "wof:name":"AB10 7ND",
    "wof:placetype":"postalcode"
},
  "geometry": {"coordinates":[-2.13644640299792,57.1308573652903],"type":"Point"}
}