{
  "type": "Feature",
  "properties": {
    "iso:country":"GB",
    "wof:name":"WN8 9DY",
    "wof:placetype":"postalcode"
},
  "geometry": {"coordinates":[-2.75096949881806,53.53862797560831],"type":"Point"}
}