{
  "type": "Feature",
  "properties": {
    "date:inception_lower": "1980-01-01",
    "date:inception_upper": "1980-01-01",
    "iso:country": "GB",
    "wof:name": "G76 0EP",
    "wof:placetype": "postalcode"
  },
  "geometry": {"coordinates":[-4.282946,55.762842],"type":"Point"}
}
