{
  "type": "Feature",
  "properties": {
    "iso:country": "GB",
    "wof:name": "G76 0EP",
    "wof:placetype": "postalcode"
  },
  "geometry": {"coordinates":[-4.282946,55.762842],"type":"Point"}
}
