{
  "type": "Feature",
  "properties": {
    "iso:country":"GB",
    "wof:name":"G76 0EP",
    "wof:placetype":"postalcode"
},
  "geometry": {"coordinates":[-4.2829459148692,55.76284176738422],"type":"Point"}
}