{
  "type": "Feature",
  "properties": {
    "iso:country": "GB",
    "wof:name": "OL16 1EA",
    "wof:placetype": "postalcode"
  },
  "geometry": {"coordinates":[-2.158978,53.617803],"type":"Point"}
}
