{
  "type": "Feature",
  "properties": {
    "date:inception_lower":"1980-01-01",
    "date:inception_upper":"1980-01-31",
    "iso:country":"GB",
    "wof:name":"OL16 1EA",
    "wof:placetype":"postalcode"
},
  "geometry": {"coordinates":[-2.158978,53.617803],"type":"Point"}
}