{
  "type": "Feature",
  "properties": {
    "iso:country":"GB",
    "wof:name":"WN2 1DA",
    "wof:placetype":"postalcode"
},
  "geometry": {"coordinates":[-2.60909612518159,53.55717830995459],"type":"Point"}
}