{
  "type": "Feature",
  "properties": {
    "iso:country":"GB",
    "wof:name":"M33 7LA",
    "wof:placetype":"postalcode"
},
  "geometry": {"coordinates":[-2.31959729778951,53.43155659792743],"type":"Point"}
}