{
  "type": "Feature",
  "properties": {
    "iso:country": "GB",
    "wof:name": "S43 3RA",
    "wof:placetype": "postalcode"
  },
  "geometry": {"coordinates":[-1.361901,53.25971],"type":"Point"}
}
