{
  "type": "Feature",
  "properties": {
    "iso:country":"GB",
    "wof:name":"S43 3RA",
    "wof:placetype":"postalcode"
},
  "geometry": {"coordinates":[-1.36190113420436,53.25971045581367],"type":"Point"}
}