{
  "type": "Feature",
  "properties": {
    "date:inception_lower":"1980-01-01",
    "date:inception_upper":"1980-01-31",
    "iso:country":"GB",
    "wof:name":"S43 3RA",
    "wof:placetype":"postalcode"
},
  "geometry": {"coordinates":[-1.361901,53.25971],"type":"Point"}
}