{
  "type": "Feature",
  "properties": {
    "iso:country": "GB",
    "wof:name": "HU16 5LT",
    "wof:placetype": "postalcode"
  },
  "geometry": {"coordinates":[-0.440606,53.775474],"type":"Point"}
}
