{
  "type": "Feature",
  "properties": {
    "date:inception_lower": "1980-01-01",
    "date:inception_upper": "1980-01-01",
    "iso:country": "GB",
    "wof:name": "PA4 8LY",
    "wof:placetype": "postalcode"
  },
  "geometry": {"coordinates":[-4.390527,55.877514],"type":"Point"}
}
