{
  "type": "Feature",
  "properties": {
    "iso:country":"GB",
    "wof:name":"PA4 8LY",
    "wof:placetype":"postalcode"
},
  "geometry": {"coordinates":[-4.39054198731005,55.87751985529659],"type":"Point"}
}