{
  "type": "Feature",
  "properties": {
    "iso:country":"GB",
    "wof:name":"SE20 8AP",
    "wof:placetype":"postalcode"
},
  "geometry": {"coordinates":[-0.06871338866578,51.41364574897641],"type":"Point"}
}