{
  "type": "Feature",
  "properties": {
    "iso:country": "GB",
    "wof:name": "CA7 8PR",
    "wof:placetype": "postalcode"
  },
  "geometry": {"coordinates":[-3.1907,54.786881],"type":"Point"}
}
