{
  "type": "Feature",
  "properties": {
    "iso:country":"GB",
    "wof:name":"E14 7AT",
    "wof:placetype":"postalcode"
},
  "geometry": {"coordinates":[-0.02571931465737,51.51760442558732],"type":"Point"}
}