{
  "type": "Feature",
  "properties": {
    "date:inception_lower": "2021-06-01",
    "date:inception_upper": "2021-06-01",
    "iso:country": "GB",
    "wof:name": "LE7 9HY",
    "wof:placetype": "postalcode"
  },
  "geometry": {"coordinates":[-1.033753,52.635262],"type":"Point"}
}
