{
  "type": "Feature",
  "properties": {
    "date:inception_lower": "1993-01-01",
    "date:inception_upper": "1993-01-01",
    "iso:country": "GB",
    "wof:name": "CF61 2GG",
    "wof:placetype": "postalcode"
  },
  "geometry": {"coordinates":[-3.471694,51.411939],"type":"Point"}
}
