{
  "type": "Feature",
  "properties": {
    "iso:country": "GB",
    "wof:name": "ML3 8AJ",
    "wof:placetype": "postalcode"
  },
  "geometry": {"coordinates":[-4.05619,55.756655],"type":"Point"}
}
