{
  "type": "Feature",
  "properties": {
    "iso:country":"GB",
    "wof:name":"ML3 8AJ",
    "wof:placetype":"postalcode"
},
  "geometry": {"coordinates":[-4.05618992711999,55.75665489841845],"type":"Point"}
}