{
  "type": "Feature",
  "properties": {
    "iso:country":"GB",
    "wof:name":"BN1 9BA",
    "wof:placetype":"postalcode"
},
  "geometry": {"coordinates":[-0.11197529882823,50.85916422612593],"type":"Point"}
}