{
  "type": "Feature",
  "properties": {
    "date:inception_lower": "1980-01-01",
    "date:inception_upper": "1980-01-01",
    "iso:country": "GB",
    "wof:name": "BN1 9BA",
    "wof:placetype": "postalcode"
  },
  "geometry": {"coordinates":[-0.111975,50.859164],"type":"Point"}
}
