{
  "type": "Feature",
  "properties": {
    "iso:country": "GB",
    "wof:name": "B38 9UQ",
    "wof:placetype": "postalcode"
  },
  "geometry": {"coordinates":[-1.9462,52.393691],"type":"Point"}
}
