{
  "type": "Feature",
  "properties": {
    "iso:country":"GB",
    "wof:name":"B38 9UQ",
    "wof:placetype":"postalcode"
},
  "geometry": {"coordinates":[-1.94620015793978,52.3936908497945],"type":"Point"}
}