{
  "type": "Feature",
  "properties": {
    "iso:country":"GB",
    "wof:name":"FK5 4BD",
    "wof:placetype":"postalcode"
},
  "geometry": {"coordinates":[-3.82580757345386,56.02764400620473],"type":"Point"}
}