{
  "type": "Feature",
  "properties": {
    "iso:country":"GB",
    "wof:name":"SW6 4SR",
    "wof:placetype":"postalcode"
},
  "geometry": {"coordinates":[-0.19751404133043,51.47303394898481],"type":"Point"}
}