{
  "type": "Feature",
  "properties": {
    "iso:country": "GB",
    "wof:name": "LL31 9NL",
    "wof:placetype": "postalcode"
  },
  "geometry": {"coordinates":[-3.807369,53.284112],"type":"Point"}
}
