{
  "type": "Feature",
  "properties": {
    "iso:country":"GB",
    "wof:name":"LL31 9NL",
    "wof:placetype":"postalcode"
},
  "geometry": {"coordinates":[-3.80736884443217,53.2841123518195],"type":"Point"}
}