{
  "type": "Feature",
  "properties": {
    "date:inception_lower":"1980-01-01",
    "date:inception_upper":"1980-01-31",
    "iso:country":"GB",
    "wof:name":"LL31 9NL",
    "wof:placetype":"postalcode"
},
  "geometry": {"coordinates":[-3.807369,53.284112],"type":"Point"}
}