{
  "type": "Feature",
  "properties": {
    "iso:country":"GB",
    "wof:name":"NW7 1JY",
    "wof:placetype":"postalcode"
},
  "geometry": {"coordinates":[-0.20634820933729,51.60415267651485],"type":"Point"}
}