{
  "type": "Feature",
  "properties": {
    "iso:country": "GB",
    "wof:name": "M60 7LH",
    "wof:placetype": "postalcode"
  },
  "geometry": {"coordinates":[-2.232696,53.476161],"type":"Point"}
}
