{
  "type": "Feature",
  "properties": {
    "date:inception_lower": "1995-12-01",
    "date:inception_upper": "1995-12-01",
    "iso:country": "GB",
    "wof:name": "M60 7LH",
    "wof:placetype": "postalcode"
  },
  "geometry": {"coordinates":[-2.232696,53.476161],"type":"Point"}
}
