{
  "type": "Feature",
  "properties": {
    "iso:country":"GB",
    "wof:name":"M60 7LH",
    "wof:placetype":"postalcode"
},
  "geometry": {"coordinates":[-2.23269632266789,53.47616085507207],"type":"Point"}
}