{
  "type": "Feature",
  "properties": {
    "date:inception_lower":"1990-07-01",
    "date:inception_upper":"1990-07-31",
    "iso:country":"GB",
    "wof:name":"DN31 2UD",
    "wof:placetype":"postalcode"
},
  "geometry": {"coordinates":[-0.100317,53.57873],"type":"Point"}
}