{
  "type": "Feature",
  "properties": {
    "iso:country": "GB",
    "wof:name": "B98 8HY",
    "wof:placetype": "postalcode"
  },
  "geometry": {"coordinates":[-1.934839,52.314895],"type":"Point"}
}
