{
  "type": "Feature",
  "properties": {
    "iso:country":"GB",
    "wof:name":"DG10 9BZ",
    "wof:placetype":"postalcode"
},
  "geometry": {"coordinates":[-3.43750230084956,55.33513982899258],"type":"Point"}
}