{
  "type": "Feature",
  "properties": {
    "iso:country":"GB",
    "wof:name":"ME8 9BE",
    "wof:placetype":"postalcode"
},
  "geometry": {"coordinates":[0.59855764838613,51.35654252866869],"type":"Point"}
}