{
  "type": "Feature",
  "properties": {
    "date:inception_lower":"1997-12-01",
    "date:inception_upper":"1997-12-31",
    "iso:country":"GB",
    "wof:name":"CA25 5NG",
    "wof:placetype":"postalcode"
},
  "geometry": {"coordinates":[-3.523326,54.528304],"type":"Point"}
}