{
  "type": "Feature",
  "properties": {
    "iso:country": "GB",
    "wof:name": "CA25 5NG",
    "wof:placetype": "postalcode"
  },
  "geometry": {"coordinates":[-3.523326,54.528304],"type":"Point"}
}
