{
  "type": "Feature",
  "properties": {
    "iso:country": "GB",
    "wof:name": "OX17 3BS",
    "wof:placetype": "postalcode"
  },
  "geometry": {"coordinates":[-1.252825,51.99556],"type":"Point"}
}
