{
  "type": "Feature",
  "properties": {
    "date:inception_lower": "1990-02-01",
    "date:inception_upper": "1990-02-01",
    "iso:country": "GB",
    "wof:name": "OX17 3BS",
    "wof:placetype": "postalcode"
  },
  "geometry": {"coordinates":[-1.252825,51.99556],"type":"Point"}
}
