{
  "type": "Feature",
  "properties": {
    "iso:country":"GB",
    "wof:name":"OX17 3BS",
    "wof:placetype":"postalcode"
},
  "geometry": {"coordinates":[-1.25282551470003,51.99555984728863],"type":"Point"}
}