{
  "type": "Feature",
  "properties": {
    "iso:country":"GB",
    "wof:name":"UB4 0PX",
    "wof:placetype":"postalcode"
},
  "geometry": {"coordinates":[-0.4138803645287,51.52017725622217],"type":"Point"}
}