{
  "type": "Feature",
  "properties": {
    "date:inception_lower":"1981-06-01",
    "date:inception_upper":"1981-06-30",
    "iso:country":"GB",
    "wof:name":"AL10 8TW",
    "wof:placetype":"postalcode"
},
  "geometry": {"coordinates":[-0.225979,51.745754],"type":"Point"}
}