{
  "type": "Feature",
  "properties": {
    "iso:country":"GB",
    "wof:name":"AL10 8TW",
    "wof:placetype":"postalcode"
},
  "geometry": {"coordinates":[-0.22597937309242,51.745754208617],"type":"Point"}
}