{
  "type": "Feature",
  "properties": {
    "iso:country": "GB",
    "wof:name": "LL41 4AP",
    "wof:placetype": "postalcode"
  },
  "geometry": {"coordinates":[-3.930818,52.981889],"type":"Point"}
}
