{
  "type": "Feature",
  "properties": {
    "iso:country":"GB",
    "wof:name":"LL41 4AP",
    "wof:placetype":"postalcode"
},
  "geometry": {"coordinates":[-3.93081803681202,52.98188872456423],"type":"Point"}
}