{
  "type": "Feature",
  "properties": {
    "iso:country": "GB",
    "wof:name": "GL19 4RA",
    "wof:placetype": "postalcode"
  },
  "geometry": {"coordinates":[-2.200513,51.986662],"type":"Point"}
}
