{
  "type": "Feature",
  "properties": {
    "date:inception_lower": "1980-01-01",
    "date:inception_upper": "1980-01-01",
    "iso:country": "GB",
    "wof:name": "GL19 4RA",
    "wof:placetype": "postalcode"
  },
  "geometry": {"coordinates":[-2.200513,51.986662],"type":"Point"}
}
