{
  "type": "Feature",
  "properties": {
    "iso:country":"GB",
    "wof:name":"GL19 4RA",
    "wof:placetype":"postalcode"
},
  "geometry": {"coordinates":[-2.20051315080984,51.98666222617135],"type":"Point"}
}