{
  "type": "Feature",
  "properties": {
    "iso:country": "GB",
    "wof:name": "MK41 8LP",
    "wof:placetype": "postalcode"
  },
  "geometry": {"coordinates":[-0.43701,52.154953],"type":"Point"}
}
