{
  "type": "Feature",
  "properties": {
    "date:inception_lower": "1980-01-01",
    "date:inception_upper": "1980-01-01",
    "iso:country": "GB",
    "wof:name": "MK41 8LP",
    "wof:placetype": "postalcode"
  },
  "geometry": {"coordinates":[-0.43701,52.154953],"type":"Point"}
}
