{
  "type": "Feature",
  "properties": {
    "iso:country": "GB",
    "wof:name": "W14 8YW",
    "wof:placetype": "postalcode"
  },
  "geometry": {"coordinates":[-0.213481,51.494815],"type":"Point"}
}
