{
  "type": "Feature",
  "properties": {
    "iso:country":"GB",
    "wof:name":"W14 8YW",
    "wof:placetype":"postalcode"
},
  "geometry": {"coordinates":[-0.21348130661657,51.49481527392542],"type":"Point"}
}