{
  "type": "Feature",
  "properties": {
    "iso:country":"GB",
    "wof:name":"SY13 3PF",
    "wof:placetype":"postalcode"
},
  "geometry": {"coordinates":[-2.7196207580493,52.96134140704866],"type":"Point"}
}