{
  "type": "Feature",
  "properties": {
    "iso:country": "GB",
    "wof:name": "SY13 3PF",
    "wof:placetype": "postalcode"
  },
  "geometry": {"coordinates":[-2.719815,52.96148],"type":"Point"}
}
