{
  "type": "Feature",
  "properties": {
    "date:inception_lower":"1980-01-01",
    "date:inception_upper":"1980-01-31",
    "iso:country":"GB",
    "wof:name":"SY13 3PF",
    "wof:placetype":"postalcode"
},
  "geometry": {"coordinates":[-2.719815,52.96148],"type":"Point"}
}