{
  "type": "Feature",
  "properties": {
    "iso:country":"GB",
    "wof:name":"PO22 7HR",
    "wof:placetype":"postalcode"
},
  "geometry": {"coordinates":[-0.64437748626811,50.79127321375565],"type":"Point"}
}