{
  "type": "Feature",
  "properties": {
    "iso:country": "GB",
    "wof:name": "S25 3RH",
    "wof:placetype": "postalcode"
  },
  "geometry": {"coordinates":[-1.232566,53.377404],"type":"Point"}
}
