{
  "type": "Feature",
  "properties": {
    "iso:country":"GB",
    "wof:name":"B78 3AX",
    "wof:placetype":"postalcode"
},
  "geometry": {"coordinates":[-1.72496174568935,52.63221923525433],"type":"Point"}
}