{
  "type": "Feature",
  "properties": {
    "iso:country":"GB",
    "wof:name":"BS10 5PD",
    "wof:placetype":"postalcode"
},
  "geometry": {"coordinates":[-2.59960329599242,51.50058099770089],"type":"Point"}
}