{
  "type": "Feature",
  "properties": {
    "iso:country":"GB",
    "wof:name":"KA11 1BW",
    "wof:placetype":"postalcode"
},
  "geometry": {"coordinates":[-4.64130152960415,55.63042896815706],"type":"Point"}
}