{
  "type": "Feature",
  "properties": {
    "iso:country":"GB",
    "wof:name":"CO8 5HS",
    "wof:placetype":"postalcode"
},
  "geometry": {"coordinates":[0.74555100324629,51.98585038178703],"type":"Point"}
}