{
  "type": "Feature",
  "properties": {
    "iso:country": "GB",
    "wof:name": "CO8 5HS",
    "wof:placetype": "postalcode"
  },
  "geometry": {"coordinates":[0.745551,51.98585],"type":"Point"}
}
