{
  "type": "Feature",
  "properties": {
    "date:inception_lower": "2001-06-01",
    "date:inception_upper": "2001-06-01",
    "iso:country": "GB",
    "wof:name": "GU51 4AB",
    "wof:placetype": "postalcode"
  },
  "geometry": {"coordinates":[-0.846235,51.278619],"type":"Point"}
}
