{
  "type": "Feature",
  "properties": {
    "iso:country":"GB",
    "wof:name":"TW19 7EE",
    "wof:placetype":"postalcode"
},
  "geometry": {"coordinates":[-0.47790605869575,51.45529253186944],"type":"Point"}
}