{
  "type": "Feature",
  "properties": {
    "iso:country":"GB",
    "wof:name":"B65 0QQ",
    "wof:placetype":"postalcode"
},
  "geometry": {"coordinates":[-2.02928900633964,52.4835635318105],"type":"Point"}
}