{
  "type": "Feature",
  "properties": {
    "iso:country":"GB",
    "wof:name":"HR9 5JS",
    "wof:placetype":"postalcode"
},
  "geometry": {"coordinates":[-2.58160354387919,51.90959393130928],"type":"Point"}
}