{
  "type": "Feature",
  "properties": {
    "iso:country":"GB",
    "wof:name":"KT3 6RQ",
    "wof:placetype":"postalcode"
},
  "geometry": {"coordinates":[-0.24878988632832,51.39326516716464],"type":"Point"}
}