{
  "type": "Feature",
  "properties": {
    "iso:country": "GB",
    "wof:name": "KT3 6RQ",
    "wof:placetype": "postalcode"
  },
  "geometry": {"coordinates":[-0.24879,51.393265],"type":"Point"}
}
