{
  "type": "Feature",
  "properties": {
    "iso:country":"GB",
    "wof:name":"M16 7FS",
    "wof:placetype":"postalcode"
},
  "geometry": {"coordinates":[-2.25654214184418,53.45540252840063],"type":"Point"}
}