{
  "type": "Feature",
  "properties": {
    "date:inception_lower":"1996-06-01",
    "date:inception_upper":"1996-06-30",
    "iso:country":"GB",
    "wof:name":"M16 7FS",
    "wof:placetype":"postalcode"
},
  "geometry": {"coordinates":[-2.256542,53.455403],"type":"Point"}
}