{
  "type": "Feature",
  "properties": {
    "iso:country":"GB",
    "wof:name":"KY8 2JP",
    "wof:placetype":"postalcode"
},
  "geometry": {"coordinates":[-3.03153102111002,56.19022840951276],"type":"Point"}
}