{
  "type": "Feature",
  "properties": {
    "iso:country":"GB",
    "wof:name":"TN32 5UX",
    "wof:placetype":"postalcode"
},
  "geometry": {"coordinates":[0.52350195516958,51.01073501176312],"type":"Point"}
}