{
  "type": "Feature",
  "properties": {
    "iso:country": "GB",
    "wof:name": "TN32 5UX",
    "wof:placetype": "postalcode"
  },
  "geometry": {"coordinates":[0.523502,51.010735],"type":"Point"}
}
