{
  "type": "Feature",
  "properties": {
    "iso:country":"GB",
    "wof:name":"SL4 5NP",
    "wof:placetype":"postalcode"
},
  "geometry": {"coordinates":[-0.63783288945096,51.48026121953727],"type":"Point"}
}