{
  "type": "Feature",
  "properties": {
    "iso:country": "GB",
    "wof:name": "SL4 5NP",
    "wof:placetype": "postalcode"
  },
  "geometry": {"coordinates":[-0.637973,51.480301],"type":"Point"}
}
