{
  "type": "Feature",
  "properties": {
    "iso:country":"GB",
    "wof:name":"BS40 8SH",
    "wof:placetype":"postalcode"
},
  "geometry": {"coordinates":[-2.61016700581692,51.36593903166073],"type":"Point"}
}