{
  "type": "Feature",
  "properties": {
    "date:inception_lower": "1999-06-01",
    "date:inception_upper": "1999-06-01",
    "iso:country": "GB",
    "wof:name": "NP12 2HS",
    "wof:placetype": "postalcode"
  },
  "geometry": {"coordinates":[-3.193084,51.644978],"type":"Point"}
}
