{
  "type": "Feature",
  "properties": {
    "iso:country":"GB",
    "wof:name":"CH5 4XL",
    "wof:placetype":"postalcode"
},
  "geometry": {"coordinates":[-3.06865012239835,53.21641608269792],"type":"Point"}
}