{
  "type": "Feature",
  "properties": {
    "iso:country": "GB",
    "wof:name": "PE6 8PS",
    "wof:placetype": "postalcode"
  },
  "geometry": {"coordinates":[-0.292359,52.674277],"type":"Point"}
}
