{
  "type": "Feature",
  "properties": {
    "date:inception_lower": "1980-01-01",
    "date:inception_upper": "1980-01-01",
    "iso:country": "GB",
    "wof:name": "PE6 8PS",
    "wof:placetype": "postalcode"
  },
  "geometry": {"coordinates":[-0.292359,52.674277],"type":"Point"}
}
