{
  "type": "Feature",
  "properties": {
    "iso:country":"GB",
    "wof:name":"CH7 4PY",
    "wof:placetype":"postalcode"
},
  "geometry": {"coordinates":[-3.21313326656648,53.09682967518692],"type":"Point"}
}