{
  "type": "Feature",
  "properties": {
    "date:inception_lower":"1993-08-01",
    "date:inception_upper":"1993-08-31",
    "iso:country":"GB",
    "wof:name":"CH7 4PY",
    "wof:placetype":"postalcode"
},
  "geometry": {"coordinates":[-3.213133,53.09683],"type":"Point"}
}