{
  "type": "Feature",
  "properties": {
    "iso:country": "GB",
    "wof:name": "MK18 3HS",
    "wof:placetype": "postalcode"
  },
  "geometry": {"coordinates":[-0.875014,51.941749],"type":"Point"}
}
