{
  "type": "Feature",
  "properties": {
    "iso:country":"GB",
    "wof:name":"NP25 5NL",
    "wof:placetype":"postalcode"
},
  "geometry": {"coordinates":[-2.81014001972696,51.8376171417064],"type":"Point"}
}