{
  "type": "Feature",
  "properties": {
    "date:inception_lower": "1999-06-01",
    "date:inception_upper": "1999-06-01",
    "iso:country": "GB",
    "wof:name": "NP25 5NL",
    "wof:placetype": "postalcode"
  },
  "geometry": {"coordinates":[-2.81014,51.837617],"type":"Point"}
}
