{
  "type": "Feature",
  "properties": {
    "iso:country":"GB",
    "wof:name":"TW14 9SL",
    "wof:placetype":"postalcode"
},
  "geometry": {"coordinates":[-0.42243752591281,51.45645670545499],"type":"Point"}
}