{
  "type": "Feature",
  "properties": {
    "date:inception_lower":"1980-01-01",
    "date:inception_upper":"1980-01-31",
    "iso:country":"GB",
    "wof:name":"TW14 9SL",
    "wof:placetype":"postalcode"
},
  "geometry": {"coordinates":[-0.422437,51.456457],"type":"Point"}
}