{
  "type": "Feature",
  "properties": {
    "iso:country":"GB",
    "wof:name":"S18 3BY",
    "wof:placetype":"postalcode"
},
  "geometry": {"coordinates":[-1.45229115731114,53.31048828628298],"type":"Point"}
}