{
  "type": "Feature",
  "properties": {
    "iso:country":"GB",
    "wof:name":"EN9 3RG",
    "wof:placetype":"postalcode"
},
  "geometry": {"coordinates":[0.04353804253334,51.68098295664967],"type":"Point"}
}