{
  "type": "Feature",
  "properties": {
    "date:inception_lower": "1998-06-01",
    "date:inception_upper": "1998-06-01",
    "iso:country": "GB",
    "wof:name": "IP6 0NE",
    "wof:placetype": "postalcode"
  },
  "geometry": {"coordinates":[1.092562,52.112787],"type":"Point"}
}
