{
  "type": "Feature",
  "properties": {
    "iso:country":"GB",
    "wof:name":"IP6 0NE",
    "wof:placetype":"postalcode"
},
  "geometry": {"coordinates":[1.09251647527489,52.1127633038509],"type":"Point"}
}