{
  "type": "Feature",
  "properties": {
    "date:inception_lower": "1980-01-01",
    "date:inception_upper": "1980-01-01",
    "iso:country": "GB",
    "wof:name": "SY21 0AR",
    "wof:placetype": "postalcode"
  },
  "geometry": {"coordinates":[-3.409839,52.614301],"type":"Point"}
}
