{
  "type": "Feature",
  "properties": {
    "date:inception_lower": "1980-01-01",
    "date:inception_upper": "1980-01-01",
    "iso:country": "GB",
    "wof:name": "S63 7BL",
    "wof:placetype": "postalcode"
  },
  "geometry": {"coordinates":[-1.338354,53.4973],"type":"Point"}
}
