{
  "type": "Feature",
  "properties": {
    "iso:country":"GB",
    "wof:name":"S63 7BL",
    "wof:placetype":"postalcode"
},
  "geometry": {"coordinates":[-1.33839654068944,53.49736211187376],"type":"Point"}
}