{
  "type": "Feature",
  "properties": {
    "date:inception_lower": "1980-01-01",
    "date:inception_upper": "1980-01-01",
    "iso:country": "GB",
    "wof:name": "HA3 0UH",
    "wof:placetype": "postalcode"
  },
  "geometry": {"coordinates":[-0.293328,51.585163],"type":"Point"}
}
