{
  "type": "Feature",
  "properties": {
    "iso:country":"GB",
    "wof:name":"TR7 3LY",
    "wof:placetype":"postalcode"
},
  "geometry": {"coordinates":[-5.05317849549042,50.42811782531834],"type":"Point"}
}