{
  "type": "Feature",
  "properties": {
    "iso:country": "GB",
    "wof:name": "TR7 3LY",
    "wof:placetype": "postalcode"
  },
  "geometry": {"coordinates":[-5.053178,50.428118],"type":"Point"}
}
