{
  "type": "Feature",
  "properties": {
    "iso:country":"GB",
    "wof:name":"W9 2HG",
    "wof:placetype":"postalcode"
},
  "geometry": {"coordinates":[-0.19044820880523,51.524218167528],"type":"Point"}
}