{
  "type": "Feature",
  "properties": {
    "date:inception_lower": "2020-10-01",
    "date:inception_upper": "2020-10-01",
    "iso:country": "GB",
    "wof:name": "NE12 5AR",
    "wof:placetype": "postalcode"
  },
  "geometry": {"coordinates":[-1.591165,55.04032],"type":"Point"}
}
