{
  "type": "Feature",
  "properties": {
    "date:inception_lower": "1980-01-01",
    "date:inception_upper": "1980-01-01",
    "iso:country": "GB",
    "wof:name": "TQ7 3AD",
    "wof:placetype": "postalcode"
  },
  "geometry": {"coordinates":[-3.855722,50.283494],"type":"Point"}
}
