{
  "type": "Feature",
  "properties": {
    "iso:country":"GB",
    "wof:name":"TQ7 3AD",
    "wof:placetype":"postalcode"
},
  "geometry": {"coordinates":[-3.85572242593775,50.2834944886089],"type":"Point"}
}