{
  "type": "Feature",
  "properties": {
    "date:inception_lower": "1980-01-01",
    "date:inception_upper": "1980-01-01",
    "iso:country": "GB",
    "wof:name": "B23 5AU",
    "wof:placetype": "postalcode"
  },
  "geometry": {"coordinates":[-1.865171,52.538042],"type":"Point"}
}
