{
  "type": "Feature",
  "properties": {
    "date:inception_lower": "1980-01-01",
    "date:inception_upper": "1980-01-01",
    "iso:country": "GB",
    "wof:name": "PE8 5SG",
    "wof:placetype": "postalcode"
  },
  "geometry": {"coordinates":[-0.482786,52.44098],"type":"Point"}
}
