{
  "type": "Feature",
  "properties": {
    "iso:country":"GB",
    "wof:name":"PE8 5SG",
    "wof:placetype":"postalcode"
},
  "geometry": {"coordinates":[-0.48278563062551,52.44098009968565],"type":"Point"}
}