{
  "type": "Feature",
  "properties": {
    "iso:country": "GB",
    "wof:name": "G75 9DG",
    "wof:placetype": "postalcode"
  },
  "geometry": {"coordinates":[-4.20365,55.742351],"type":"Point"}
}
