{
  "type": "Feature",
  "properties": {
    "iso:country": "GB",
    "wof:name": "LN4 1HF",
    "wof:placetype": "postalcode"
  },
  "geometry": {"coordinates":[-0.481985,53.222934],"type":"Point"}
}
