{
  "type": "Feature",
  "properties": {
    "iso:country":"GB",
    "wof:name":"LN4 1HF",
    "wof:placetype":"postalcode"
},
  "geometry": {"coordinates":[-0.48198518428996,53.22293450258272],"type":"Point"}
}