{
  "type": "Feature",
  "properties": {
    "iso:country":"GB",
    "wof:name":"M33 4FX",
    "wof:placetype":"postalcode"
},
  "geometry": {"coordinates":[-2.33988304377182,53.40856171998863],"type":"Point"}
}