{
  "type": "Feature",
  "properties": {
    "iso:country": "GB",
    "wof:name": "LS15 4DJ",
    "wof:placetype": "postalcode"
  },
  "geometry": {"coordinates":[-1.423309,53.822799],"type":"Point"}
}
