{
  "type": "Feature",
  "properties": {
    "iso:country":"GB",
    "wof:name":"LS15 4DJ",
    "wof:placetype":"postalcode"
},
  "geometry": {"coordinates":[-1.42366819678162,53.82285627254139],"type":"Point"}
}