{
  "type": "Feature",
  "properties": {
    "iso:country":"GB",
    "wof:name":"CB24 4RB",
    "wof:placetype":"postalcode"
},
  "geometry": {"coordinates":[-0.01485113600054,52.28911627399153],"type":"Point"}
}