{
  "type": "Feature",
  "properties": {
    "iso:country": "GB",
    "wof:name": "CB24 4RB",
    "wof:placetype": "postalcode"
  },
  "geometry": {"coordinates":[-0.014851,52.289116],"type":"Point"}
}
