{
  "type": "Feature",
  "properties": {
    "iso:country":"GB",
    "wof:name":"E17 9HS",
    "wof:placetype":"postalcode"
},
  "geometry": {"coordinates":[-0.00727422160071,51.5838468237457],"type":"Point"}
}