{
  "type": "Feature",
  "properties": {
    "iso:country": "GB",
    "wof:name": "SN16 9QD",
    "wof:placetype": "postalcode"
  },
  "geometry": {"coordinates":[-1.958432,51.612827],"type":"Point"}
}
