{
  "type": "Feature",
  "properties": {
    "iso:country": "GB",
    "wof:name": "PL20 7ET",
    "wof:placetype": "postalcode"
  },
  "geometry": {"coordinates":[-4.202962,50.484976],"type":"Point"}
}
