{
  "type": "Feature",
  "properties": {
    "iso:country":"GB",
    "wof:name":"PL20 7ET",
    "wof:placetype":"postalcode"
},
  "geometry": {"coordinates":[-4.20296197552987,50.4849759133404],"type":"Point"}
}