{
  "type": "Feature",
  "properties": {
    "iso:country":"GB",
    "wof:name":"DA15 7NG",
    "wof:placetype":"postalcode"
},
  "geometry": {"coordinates":[0.08634092973164,51.43288547359705],"type":"Point"}
}