{
  "type": "Feature",
  "properties": {
    "iso:country":"GB",
    "wof:name":"M14 7NF",
    "wof:placetype":"postalcode"
},
  "geometry": {"coordinates":[-2.23388694157224,53.45432551080027],"type":"Point"}
}