{
  "type": "Feature",
  "properties": {
    "iso:country":"GB",
    "wof:name":"HA3 0BQ",
    "wof:placetype":"postalcode"
},
  "geometry": {"coordinates":[-0.31367131930635,51.58152753510524],"type":"Point"}
}