{
  "type": "Feature",
  "properties": {
    "date:inception_lower": "1990-07-01",
    "date:inception_upper": "1990-07-01",
    "iso:country": "GB",
    "wof:name": "HA3 0BQ",
    "wof:placetype": "postalcode"
  },
  "geometry": {"coordinates":[-0.313671,51.581528],"type":"Point"}
}
