{
  "type": "Feature",
  "properties": {
    "iso:country":"GB",
    "wof:name":"GU4 7SS",
    "wof:placetype":"postalcode"
},
  "geometry": {"coordinates":[-0.54288970670724,51.26385336406703],"type":"Point"}
}