{
  "type": "Feature",
  "properties": {
    "iso:country":"GB",
    "wof:name":"CA14 1XB",
    "wof:placetype":"postalcode"
},
  "geometry": {"coordinates":[-3.48585372157126,54.65247806565955],"type":"Point"}
}