{
  "type": "Feature",
  "properties": {
    "iso:country":"GB",
    "wof:name":"HU5 4RJ",
    "wof:placetype":"postalcode"
},
  "geometry": {"coordinates":[-0.38990469816229,53.7673945909355],"type":"Point"}
}