{
  "type": "Feature",
  "properties": {
    "iso:country": "GB",
    "wof:name": "HU5 4RJ",
    "wof:placetype": "postalcode"
  },
  "geometry": {"coordinates":[-0.389932,53.767254],"type":"Point"}
}
