{
  "type": "Feature",
  "properties": {
    "iso:country": "GB",
    "wof:name": "BA21 4NF",
    "wof:placetype": "postalcode"
  },
  "geometry": {"coordinates":[-2.628953,50.956888],"type":"Point"}
}
