{
  "type": "Feature",
  "properties": {
    "iso:country": "GB",
    "wof:name": "B29 6UH",
    "wof:placetype": "postalcode"
  },
  "geometry": {"coordinates":[-1.933652,52.437813],"type":"Point"}
}
