{
  "type": "Feature",
  "properties": {
    "date:inception_lower": "2018-07-01",
    "date:inception_upper": "2018-07-01",
    "iso:country": "GB",
    "wof:name": "B29 6UH",
    "wof:placetype": "postalcode"
  },
  "geometry": {"coordinates":[-1.933696,52.437786],"type":"Point"}
}
