{
  "type": "Feature",
  "properties": {
    "iso:country":"GB",
    "wof:name":"CT9 3QY",
    "wof:placetype":"postalcode"
},
  "geometry": {"coordinates":[1.40962754311927,51.38160279637244],"type":"Point"}
}