{
  "type": "Feature",
  "properties": {
    "iso:country": "GB",
    "wof:name": "SP11 9LE",
    "wof:placetype": "postalcode"
  },
  "geometry": {"coordinates":[-1.630549,51.240891],"type":"Point"}
}
