{
  "type": "Feature",
  "properties": {
    "iso:country": "GB",
    "wof:name": "AB16 5NN",
    "wof:placetype": "postalcode"
  },
  "geometry": {"coordinates":[-2.1569,57.158878],"type":"Point"}
}
