{
  "type": "Feature",
  "properties": {
    "iso:country":"GB",
    "wof:name":"EX8 2LS",
    "wof:placetype":"postalcode"
},
  "geometry": {"coordinates":[-3.39331686585096,50.62317122999103],"type":"Point"}
}