{
  "type": "Feature",
  "properties": {
    "iso:country": "GB",
    "wof:name": "PE4 7UR",
    "wof:placetype": "postalcode"
  },
  "geometry": {"coordinates":[-0.254865,52.605563],"type":"Point"}
}
