{
  "type": "Feature",
  "properties": {
    "date:inception_lower": "1992-01-01",
    "date:inception_upper": "1992-01-01",
    "iso:country": "GB",
    "wof:name": "PE4 7UR",
    "wof:placetype": "postalcode"
  },
  "geometry": {"coordinates":[-0.254865,52.605563],"type":"Point"}
}
