{
  "type": "Feature",
  "properties": {
    "iso:country":"GB",
    "wof:name":"PE4 7UR",
    "wof:placetype":"postalcode"
},
  "geometry": {"coordinates":[-0.25486454923149,52.60556291532212],"type":"Point"}
}