{
  "type": "Feature",
  "properties": {
    "iso:country":"GB",
    "wof:name":"DL12 9SU",
    "wof:placetype":"postalcode"
},
  "geometry": {"coordinates":[-1.95692457604573,54.50839768968348],"type":"Point"}
}