{
  "type": "Feature",
  "properties": {
    "iso:country":"GB",
    "wof:name":"S66 8RG",
    "wof:placetype":"postalcode"
},
  "geometry": {"coordinates":[-1.22198894114314,53.42907532963912],"type":"Point"}
}