{
  "type": "Feature",
  "properties": {
    "iso:country":"GB",
    "wof:name":"BH21 3XH",
    "wof:placetype":"postalcode"
},
  "geometry": {"coordinates":[-2.01440081331376,50.77816639058684],"type":"Point"}
}