{
  "type": "Feature",
  "properties": {
    "iso:country": "GB",
    "wof:name": "BH21 3XH",
    "wof:placetype": "postalcode"
  },
  "geometry": {"coordinates":[-2.014401,50.778166],"type":"Point"}
}
