{
  "type": "Feature",
  "properties": {
    "iso:country":"GB",
    "wof:name":"BA20 2BT",
    "wof:placetype":"postalcode"
},
  "geometry": {"coordinates":[-2.64123706995511,50.93594057053442],"type":"Point"}
}