{
  "type": "Feature",
  "properties": {
    "date:inception_lower": "2001-12-01",
    "date:inception_upper": "2001-12-01",
    "iso:country": "GB",
    "wof:name": "BA20 2BT",
    "wof:placetype": "postalcode"
  },
  "geometry": {"coordinates":[-2.641568,50.936129],"type":"Point"}
}
