{
  "type": "Feature",
  "properties": {
    "date:inception_lower": "1980-01-01",
    "date:inception_upper": "1980-01-01",
    "iso:country": "GB",
    "wof:name": "CT4 6JE",
    "wof:placetype": "postalcode"
  },
  "geometry": {"coordinates":[1.143431,51.217865],"type":"Point"}
}
