{
  "type": "Feature",
  "properties": {
    "iso:country":"GB",
    "wof:name":"CT4 6JE",
    "wof:placetype":"postalcode"
},
  "geometry": {"coordinates":[1.14343080770534,51.21786542978478],"type":"Point"}
}