{
  "type": "Feature",
  "properties": {
    "iso:country": "GB",
    "wof:name": "LA12 7RB",
    "wof:placetype": "postalcode"
  },
  "geometry": {"coordinates":[-3.054042,54.233993],"type":"Point"}
}
