{
  "type": "Feature",
  "properties": {
    "iso:country":"GB",
    "wof:name":"WS9 8DG",
    "wof:placetype":"postalcode"
},
  "geometry": {"coordinates":[-1.93874941530746,52.60674854009544],"type":"Point"}
}