{
  "type": "Feature",
  "properties": {
    "iso:country": "GB",
    "wof:name": "WS9 8DG",
    "wof:placetype": "postalcode"
  },
  "geometry": {"coordinates":[-1.938749,52.606749],"type":"Point"}
}
