{
  "type": "Feature",
  "properties": {
    "iso:country": "GB",
    "wof:name": "DN11 0XQ",
    "wof:placetype": "postalcode"
  },
  "geometry": {"coordinates":[-1.059333,53.476337],"type":"Point"}
}
