{
  "type": "Feature",
  "properties": {
    "iso:country": "GB",
    "wof:name": "PL20 6AD",
    "wof:placetype": "postalcode"
  },
  "geometry": {"coordinates":[-4.091739,50.492722],"type":"Point"}
}
