{
  "type": "Feature",
  "properties": {
    "iso:country":"GB",
    "wof:name":"TR8 5RZ",
    "wof:placetype":"postalcode"
},
  "geometry": {"coordinates":[-5.11336239477879,50.40059600643353],"type":"Point"}
}