{
  "type": "Feature",
  "properties": {
    "iso:country": "GB",
    "wof:name": "BH21 4JB",
    "wof:placetype": "postalcode"
  },
  "geometry": {"coordinates":[-2.008382,50.829811],"type":"Point"}
}
