{
  "type": "Feature",
  "properties": {
    "iso:country": "GB",
    "wof:name": "KA17 0HA",
    "wof:placetype": "postalcode"
  },
  "geometry": {"coordinates":[-4.290066,55.609028],"type":"Point"}
}
