{
  "type": "Feature",
  "properties": {
    "iso:country":"GB",
    "wof:name":"KW14 8ST",
    "wof:placetype":"postalcode"
},
  "geometry": {"coordinates":[-3.43867456355355,58.59692252562013],"type":"Point"}
}