{
  "type": "Feature",
  "properties": {
    "date:inception_lower": "1980-01-01",
    "date:inception_upper": "1980-01-01",
    "iso:country": "GB",
    "wof:name": "KW14 8ST",
    "wof:placetype": "postalcode"
  },
  "geometry": {"coordinates":[-3.438675,58.596923],"type":"Point"}
}
