{
  "type": "Feature",
  "properties": {
    "iso:country": "GB",
    "wof:name": "CB1 3LB",
    "wof:placetype": "postalcode"
  },
  "geometry": {"coordinates":[0.17721,52.19493],"type":"Point"}
}
