{
  "type": "Feature",
  "properties": {
    "iso:country":"GB",
    "wof:name":"PE12 9GG",
    "wof:placetype":"postalcode"
},
  "geometry": {"coordinates":[0.11145397749432,52.77890181484614],"type":"Point"}
}