{
  "type": "Feature",
  "properties": {
    "iso:country": "GB",
    "wof:name": "G14 9PT",
    "wof:placetype": "postalcode"
  },
  "geometry": {"coordinates":[-4.339883,55.87551],"type":"Point"}
}
