{
  "type": "Feature",
  "properties": {
    "date:inception_lower": "1980-01-01",
    "date:inception_upper": "1980-01-01",
    "iso:country": "GB",
    "wof:name": "B11 1XG",
    "wof:placetype": "postalcode"
  },
  "geometry": {"coordinates":[-1.876225,52.460704],"type":"Point"}
}
