{
  "type": "Feature",
  "properties": {
    "iso:country":"GB",
    "wof:name":"B14 6UB",
    "wof:placetype":"postalcode"
},
  "geometry": {"coordinates":[-1.90350611508269,52.42255789519609],"type":"Point"}
}