{
  "type": "Feature",
  "properties": {
    "iso:country":"GB",
    "wof:name":"SA10 8HN",
    "wof:placetype":"postalcode"
},
  "geometry": {"coordinates":[-3.74372035735545,51.69037692465252],"type":"Point"}
}