{
  "type": "Feature",
  "properties": {
    "iso:country":"GB",
    "wof:name":"DG1 3PS",
    "wof:placetype":"postalcode"
},
  "geometry": {"coordinates":[-3.51741263276647,55.09336841870896],"type":"Point"}
}