{
  "type": "Feature",
  "properties": {
    "iso:country":"GB",
    "wof:name":"LS19 7NG",
    "wof:placetype":"postalcode"
},
  "geometry": {"coordinates":[-1.69923245644369,53.86300543319154],"type":"Point"}
}