{
  "type": "Feature",
  "properties": {
    "iso:country":"GB",
    "wof:name":"E16 4QJ",
    "wof:placetype":"postalcode"
},
  "geometry": {"coordinates":[0.00916727767119,51.51707493402527],"type":"Point"}
}