{
  "type": "Feature",
  "properties": {
    "iso:country":"GB",
    "wof:name":"EH14 2BS",
    "wof:placetype":"postalcode"
},
  "geometry": {"coordinates":[-3.26251568257614,55.92415661126505],"type":"Point"}
}