{
  "type": "Feature",
  "properties": {
    "iso:country":"GB",
    "wof:name":"EX34 0HT",
    "wof:placetype":"postalcode"
},
  "geometry": {"coordinates":[-4.02442730078339,51.19967722670066],"type":"Point"}
}