{
  "type": "Feature",
  "properties": {
    "iso:country":"GB",
    "wof:name":"W1W 5PR",
    "wof:placetype":"postalcode"
},
  "geometry": {"coordinates":[-0.14389608340053,51.52220485895959],"type":"Point"}
}