{
  "type": "Feature",
  "properties": {
    "iso:country":"GB",
    "wof:name":"IP14 3QQ",
    "wof:placetype":"postalcode"
},
  "geometry": {"coordinates":[0.97963742330584,52.2059123754936],"type":"Point"}
}