{
  "type": "Feature",
  "properties": {
    "iso:country": "GB",
    "wof:name": "IP14 3QQ",
    "wof:placetype": "postalcode"
  },
  "geometry": {"coordinates":[0.9797,52.205946],"type":"Point"}
}
