{
  "type": "Feature",
  "properties": {
    "iso:country": "GB",
    "wof:name": "IP14 3QQ",
    "wof:placetype": "postalcode"
  },
  "geometry": {"coordinates":[0.979637,52.205912],"type":"Point"}
}
