{
  "type": "Feature",
  "properties": {
    "iso:country": "GB",
    "wof:name": "NN7 3BF",
    "wof:placetype": "postalcode"
  },
  "geometry": {"coordinates":[-0.932306,52.172906],"type":"Point"}
}
