{
  "type": "Feature",
  "properties": {
    "iso:country": "GB",
    "wof:name": "TF1 1JX",
    "wof:placetype": "postalcode"
  },
  "geometry": {"coordinates":[-2.5117,52.697129],"type":"Point"}
}
