{
  "type": "Feature",
  "properties": {
    "date:inception_lower": "1980-01-01",
    "date:inception_upper": "1980-01-01",
    "iso:country": "GB",
    "wof:name": "TF1 1JX",
    "wof:placetype": "postalcode"
  },
  "geometry": {"coordinates":[-2.5117,52.697129],"type":"Point"}
}
