{
  "type": "Feature",
  "properties": {
    "iso:country":"GB",
    "wof:name":"CO12 3ES",
    "wof:placetype":"postalcode"
},
  "geometry": {"coordinates":[1.28910420411277,51.94542509581263],"type":"Point"}
}