{
  "type": "Feature",
  "properties": {
    "date:inception_lower": "1980-01-01",
    "date:inception_upper": "1980-01-01",
    "iso:country": "GB",
    "wof:name": "SE26 6AD",
    "wof:placetype": "postalcode"
  },
  "geometry": {"coordinates":[-0.065073,51.430717],"type":"Point"}
}
