{
  "type": "Feature",
  "properties": {
    "iso:country": "GB",
    "wof:name": "SE26 6AD",
    "wof:placetype": "postalcode"
  },
  "geometry": {"coordinates":[-0.065073,51.430717],"type":"Point"}
}
