{
  "type": "Feature",
  "properties": {
    "iso:country":"GB",
    "wof:name":"SE26 6AD",
    "wof:placetype":"postalcode"
},
  "geometry": {"coordinates":[-0.06507318913834,51.43071683243794],"type":"Point"}
}