{
  "type": "Feature",
  "properties": {
    "iso:country": "GB",
    "wof:name": "NN29 7UW",
    "wof:placetype": "postalcode"
  },
  "geometry": {"coordinates":[-0.646442,52.277662],"type":"Point"}
}
