{
  "type": "Feature",
  "properties": {
    "date:inception_lower": "1980-01-01",
    "date:inception_upper": "1980-01-01",
    "iso:country": "GB",
    "wof:name": "GU1 1JT",
    "wof:placetype": "postalcode"
  },
  "geometry": {"coordinates":[-0.57853,51.26127],"type":"Point"}
}
