{
  "type": "Feature",
  "properties": {
    "iso:country":"GB",
    "wof:name":"CA4 8BH",
    "wof:placetype":"postalcode"
},
  "geometry": {"coordinates":[-2.8728954677168,54.89462137122001],"type":"Point"}
}