{
  "type": "Feature",
  "properties": {
    "date:inception_lower": "1998-06-01",
    "date:inception_upper": "1998-06-01",
    "iso:country": "GB",
    "wof:name": "YO23 1AD",
    "wof:placetype": "postalcode"
  },
  "geometry": {"coordinates":[-1.08976,53.953831],"type":"Point"}
}
