{
  "type": "Feature",
  "properties": {
    "iso:country": "GB",
    "wof:name": "BN27 1PH",
    "wof:placetype": "postalcode"
  },
  "geometry": {"coordinates":[0.272626,50.879941],"type":"Point"}
}
