{
  "type": "Feature",
  "properties": {
    "iso:country":"GB",
    "wof:name":"BN27 1PH",
    "wof:placetype":"postalcode"
},
  "geometry": {"coordinates":[0.27255515291527,50.87994651847087],"type":"Point"}
}