{
  "type": "Feature",
  "properties": {
    "iso:country": "GB",
    "wof:name": "GU6 7AS",
    "wof:placetype": "postalcode"
  },
  "geometry": {"coordinates":[-0.484436,51.14574],"type":"Point"}
}
