{
  "type": "Feature",
  "properties": {
    "iso:country":"GB",
    "wof:name":"CH65 5ES",
    "wof:placetype":"postalcode"
},
  "geometry": {"coordinates":[-2.89250377264576,53.27047904524154],"type":"Point"}
}