{
  "type": "Feature",
  "properties": {
    "iso:country": "GB",
    "wof:name": "TN21 9EL",
    "wof:placetype": "postalcode"
  },
  "geometry": {"coordinates":[0.266502,50.937108],"type":"Point"}
}
