{
  "type": "Feature",
  "properties": {
    "iso:country":"GB",
    "wof:name":"TN21 9EL",
    "wof:placetype":"postalcode"
},
  "geometry": {"coordinates":[0.26651858264427,50.93715665920967],"type":"Point"}
}