{
  "type": "Feature",
  "properties": {
    "iso:country":"GB",
    "wof:name":"IP4 1JG",
    "wof:placetype":"postalcode"
},
  "geometry": {"coordinates":[1.16057793785296,52.05477205084555],"type":"Point"}
}