{
  "type": "Feature",
  "properties": {
    "iso:country":"GB",
    "wof:name":"B74 4TB",
    "wof:placetype":"postalcode"
},
  "geometry": {"coordinates":[-1.85866858370837,52.58888945965513],"type":"Point"}
}