{
  "type": "Feature",
  "properties": {
    "iso:country": "GB",
    "wof:name": "B74 4TB",
    "wof:placetype": "postalcode"
  },
  "geometry": {"coordinates":[-1.858669,52.588889],"type":"Point"}
}
