{
  "type": "Feature",
  "properties": {
    "iso:country": "GB",
    "wof:name": "CH5 4XG",
    "wof:placetype": "postalcode"
  },
  "geometry": {"coordinates":[-3.066861,53.220963],"type":"Point"}
}
