{
  "type": "Feature",
  "properties": {
    "iso:country":"GB",
    "wof:name":"CH5 4XG",
    "wof:placetype":"postalcode"
},
  "geometry": {"coordinates":[-3.06686116153181,53.22096270858972],"type":"Point"}
}