{
  "type": "Feature",
  "properties": {
    "iso:country": "GB",
    "wof:name": "NW1 2EB",
    "wof:placetype": "postalcode"
  },
  "geometry": {"coordinates":[-0.134878,51.527091],"type":"Point"}
}
