{
  "type": "Feature",
  "properties": {
    "iso:country":"GB",
    "wof:name":"NW1 2EB",
    "wof:placetype":"postalcode"
},
  "geometry": {"coordinates":[-0.13490345048628,51.52708902107785],"type":"Point"}
}