{
  "type": "Feature",
  "properties": {
    "iso:country": "GB",
    "wof:name": "DL13 2SG",
    "wof:placetype": "postalcode"
  },
  "geometry": {"coordinates":[-1.942223,54.723147],"type":"Point"}
}
