{
  "type": "Feature",
  "properties": {
    "iso:country":"GB",
    "wof:name":"ML6 8GL",
    "wof:placetype":"postalcode"
},
  "geometry": {"coordinates":[-3.94205153774052,55.83809106866281],"type":"Point"}
}