{
  "type": "Feature",
  "properties": {
    "date:inception_lower":"1999-06-01",
    "date:inception_upper":"1999-06-30",
    "iso:country":"GB",
    "wof:name":"ML6 8GL",
    "wof:placetype":"postalcode"
},
  "geometry": {"coordinates":[-3.942051,55.838091],"type":"Point"}
}