{
  "type": "Feature",
  "properties": {
    "iso:country": "GB",
    "wof:name": "G81 2JF",
    "wof:placetype": "postalcode"
  },
  "geometry": {"coordinates":[-4.402502,55.9078],"type":"Point"}
}
