{
  "type": "Feature",
  "properties": {
    "iso:country": "GB",
    "wof:name": "CB25 0JD",
    "wof:placetype": "postalcode"
  },
  "geometry": {"coordinates":[0.29527,52.271661],"type":"Point"}
}
