{
  "type": "Feature",
  "properties": {
    "date:inception_lower":"2006-09-01",
    "date:inception_upper":"2006-09-30",
    "iso:country":"GB",
    "wof:name":"CB25 0JD",
    "wof:placetype":"postalcode"
},
  "geometry": {"coordinates":[0.29527,52.271661],"type":"Point"}
}