{
  "type": "Feature",
  "properties": {
    "iso:country":"GB",
    "wof:name":"EH48 4NE",
    "wof:placetype":"postalcode"
},
  "geometry": {"coordinates":[-3.66749007915183,55.93848840129309],"type":"Point"}
}