{
  "type": "Feature",
  "properties": {
    "iso:country": "GB",
    "wof:name": "LS9 6SR",
    "wof:placetype": "postalcode"
  },
  "geometry": {"coordinates":[-1.495037,53.812608],"type":"Point"}
}
