{
  "type": "Feature",
  "properties": {
    "iso:country":"GB",
    "wof:name":"LS9 6SR",
    "wof:placetype":"postalcode"
},
  "geometry": {"coordinates":[-1.49503699700455,53.81260783176645],"type":"Point"}
}