{
  "type": "Feature",
  "properties": {
    "iso:country":"GB",
    "wof:name":"NG16 1LB",
    "wof:placetype":"postalcode"
},
  "geometry": {"coordinates":[-1.25309917213872,53.00442437697997],"type":"Point"}
}