{
  "type": "Feature",
  "properties": {
    "iso:country":"GB",
    "wof:name":"DE11 0RL",
    "wof:placetype":"postalcode"
},
  "geometry": {"coordinates":[-1.57306264011235,52.78042293054482],"type":"Point"}
}