{
  "type": "Feature",
  "properties": {
    "iso:country": "GB",
    "wof:name": "SE13 7QT",
    "wof:placetype": "postalcode"
  },
  "geometry": {"coordinates":[-0.016416,51.471953],"type":"Point"}
}
