{
  "type": "Feature",
  "properties": {
    "iso:country":"GB",
    "wof:name":"SE13 7QT",
    "wof:placetype":"postalcode"
},
  "geometry": {"coordinates":[-0.01641627497051,51.47195349671997],"type":"Point"}
}