{
  "type": "Feature",
  "properties": {
    "iso:country": "GB",
    "wof:name": "EX16 7NP",
    "wof:placetype": "postalcode"
  },
  "geometry": {"coordinates":[-3.416837,50.976748],"type":"Point"}
}
