{
  "type": "Feature",
  "properties": {
    "iso:country":"GB",
    "wof:name":"CA8 7AW",
    "wof:placetype":"postalcode"
},
  "geometry": {"coordinates":[-2.57369387518304,55.0023794751024],"type":"Point"}
}