{
  "type": "Feature",
  "properties": {
    "iso:country": "GB",
    "wof:name": "CA8 7AW",
    "wof:placetype": "postalcode"
  },
  "geometry": {"coordinates":[-2.573859,55.002483],"type":"Point"}
}
