{
  "type": "Feature",
  "properties": {
    "iso:country":"GB",
    "wof:name":"E2 9LS",
    "wof:placetype":"postalcode"
},
  "geometry": {"coordinates":[-0.05648269153699,51.53137330240551],"type":"Point"}
}