{
  "type": "Feature",
  "properties": {
    "iso:country": "GB",
    "wof:name": "B37 6PH",
    "wof:placetype": "postalcode"
  },
  "geometry": {"coordinates":[-1.74284,52.488215],"type":"Point"}
}
