{
  "type": "Feature",
  "properties": {
    "iso:country":"GB",
    "wof:name":"B37 6PH",
    "wof:placetype":"postalcode"
},
  "geometry": {"coordinates":[-1.74284010548095,52.4882148421943],"type":"Point"}
}