{
  "type": "Feature",
  "properties": {
    "iso:country":"GB",
    "wof:name":"SA4 4HJ",
    "wof:placetype":"postalcode"
},
  "geometry": {"coordinates":[-4.0348835849043,51.66172721312024],"type":"Point"}
}