{
  "type": "Feature",
  "properties": {
    "iso:country":"GB",
    "wof:name":"M18 8SD",
    "wof:placetype":"postalcode"
},
  "geometry": {"coordinates":[-2.1592733693145,53.46733790547194],"type":"Point"}
}