{
  "type": "Feature",
  "properties": {
    "iso:country": "GB",
    "wof:name": "M18 8SD",
    "wof:placetype": "postalcode"
  },
  "geometry": {"coordinates":[-2.159273,53.467338],"type":"Point"}
}
