{
  "type": "Feature",
  "properties": {
    "iso:country": "GB",
    "wof:name": "EX17 5LZ",
    "wof:placetype": "postalcode"
  },
  "geometry": {"coordinates":[-3.743669,50.81077],"type":"Point"}
}
