{
  "type": "Feature",
  "properties": {
    "date:inception_lower": "2018-11-01",
    "date:inception_upper": "2018-11-01",
    "iso:country": "GB",
    "wof:name": "SW13 0BQ",
    "wof:placetype": "postalcode"
  },
  "geometry": {"coordinates":[-0.245314,51.470316],"type":"Point"}
}
