{
  "type": "Feature",
  "properties": {
    "iso:country":"GB",
    "wof:name":"NG17 4LT",
    "wof:placetype":"postalcode"
},
  "geometry": {"coordinates":[-1.24599526086006,53.12640904159191],"type":"Point"}
}