{
  "type": "Feature",
  "properties": {
    "date:inception_lower": "1980-01-01",
    "date:inception_upper": "1980-01-01",
    "iso:country": "GB",
    "wof:name": "NG17 4LT",
    "wof:placetype": "postalcode"
  },
  "geometry": {"coordinates":[-1.245995,53.126409],"type":"Point"}
}
