{
  "type": "Feature",
  "properties": {
    "iso:country": "GB",
    "wof:name": "GL11 5RS",
    "wof:placetype": "postalcode"
  },
  "geometry": {"coordinates":[-2.361584,51.693729],"type":"Point"}
}
