{
  "type": "Feature",
  "properties": {
    "iso:country": "GB",
    "wof:name": "HR3 6AL",
    "wof:placetype": "postalcode"
  },
  "geometry": {"coordinates":[-3.004716,52.069784],"type":"Point"}
}
