{
  "type": "Feature",
  "properties": {
    "iso:country":"GB",
    "wof:name":"RH20 4AN",
    "wof:placetype":"postalcode"
},
  "geometry": {"coordinates":[-0.40616440322209,50.90406689137086],"type":"Point"}
}