{
  "type": "Feature",
  "properties": {
    "iso:country": "GB",
    "wof:name": "RH20 4AN",
    "wof:placetype": "postalcode"
  },
  "geometry": {"coordinates":[-0.406164,50.904067],"type":"Point"}
}
