{
  "type": "Feature",
  "properties": {
    "date:inception_lower": "1980-01-01",
    "date:inception_upper": "1980-01-01",
    "iso:country": "GB",
    "wof:name": "RH20 4AN",
    "wof:placetype": "postalcode"
  },
  "geometry": {"coordinates":[-0.406164,50.904067],"type":"Point"}
}
