{
  "type": "Feature",
  "properties": {
    "iso:country":"GB",
    "wof:name":"LS17 8LN",
    "wof:placetype":"postalcode"
},
  "geometry": {"coordinates":[-1.47951286951961,53.84961707939737],"type":"Point"}
}