{
  "type": "Feature",
  "properties": {
    "iso:country":"GB",
    "wof:name":"SA61 2TT",
    "wof:placetype":"postalcode"
},
  "geometry": {"coordinates":[-4.98644908817921,51.80289246656154],"type":"Point"}
}