{
  "type": "Feature",
  "properties": {
    "iso:country":"GB",
    "wof:name":"CT12 5EE",
    "wof:placetype":"postalcode"
},
  "geometry": {"coordinates":[1.36617715524068,51.33407091013623],"type":"Point"}
}