{
  "type": "Feature",
  "properties": {
    "iso:country":"GB",
    "wof:name":"NW10 5EP",
    "wof:placetype":"postalcode"
},
  "geometry": {"coordinates":[-0.22548226802,51.53188434825238],"type":"Point"}
}