{
  "type": "Feature",
  "properties": {
    "iso:country":"GB",
    "wof:name":"KT22 9RB",
    "wof:placetype":"postalcode"
},
  "geometry": {"coordinates":[-0.35700506805847,51.29467378610563],"type":"Point"}
}