{
  "type": "Feature",
  "properties": {
    "iso:country":"GB",
    "wof:name":"SG16 6LL",
    "wof:placetype":"postalcode"
},
  "geometry": {"coordinates":[-0.32367429573974,52.00309484859718],"type":"Point"}
}