{
  "type": "Feature",
  "properties": {
    "iso:country":"GB",
    "wof:name":"WA15 7AN",
    "wof:placetype":"postalcode"
},
  "geometry": {"coordinates":[-2.316835114395,53.39004571018154],"type":"Point"}
}