{
  "type": "Feature",
  "properties": {
    "iso:country":"GB",
    "wof:name":"SR8 5RH",
    "wof:placetype":"postalcode"
},
  "geometry": {"coordinates":[-1.32235504469142,54.75742258840467],"type":"Point"}
}