{
  "type": "Feature",
  "properties": {
    "iso:country": "GB",
    "wof:name": "SR8 5RH",
    "wof:placetype": "postalcode"
  },
  "geometry": {"coordinates":[-1.322355,54.757423],"type":"Point"}
}
