{
  "type": "Feature",
  "properties": {
    "date:inception_lower":"1980-01-01",
    "date:inception_upper":"1980-01-31",
    "iso:country":"GB",
    "wof:name":"NR34 0EY",
    "wof:placetype":"postalcode"
},
  "geometry": {"coordinates":[1.561532,52.503949],"type":"Point"}
}