{
  "type": "Feature",
  "properties": {
    "iso:country":"GB",
    "wof:name":"NR34 0EY",
    "wof:placetype":"postalcode"
},
  "geometry": {"coordinates":[1.56153223759029,52.50394907735916],"type":"Point"}
}