{
  "type": "Feature",
  "properties": {
    "date:inception_lower": "1992-01-01",
    "date:inception_upper": "1992-01-01",
    "iso:country": "GB",
    "wof:name": "HU12 9HQ",
    "wof:placetype": "postalcode"
  },
  "geometry": {"coordinates":[-0.145023,53.733831],"type":"Point"}
}
