{
  "type": "Feature",
  "properties": {
    "iso:country":"GB",
    "wof:name":"LE7 4TT",
    "wof:placetype":"postalcode"
},
  "geometry": {"coordinates":[-1.03857106161329,52.73866753711841],"type":"Point"}
}