{
  "type": "Feature",
  "properties": {
    "iso:country": "GB",
    "wof:name": "LE7 4TT",
    "wof:placetype": "postalcode"
  },
  "geometry": {"coordinates":[-1.038565,52.738678],"type":"Point"}
}
