{
  "type": "Feature",
  "properties": {
    "iso:country":"GB",
    "wof:name":"DT11 8QU",
    "wof:placetype":"postalcode"
},
  "geometry": {"coordinates":[-2.20303673204584,50.93471093540523],"type":"Point"}
}