{
  "type": "Feature",
  "properties": {
    "iso:country": "GB",
    "wof:name": "DT11 8QU",
    "wof:placetype": "postalcode"
  },
  "geometry": {"coordinates":[-2.203037,50.934711],"type":"Point"}
}
