{
  "type": "Feature",
  "properties": {
    "iso:country":"GB",
    "wof:name":"CV2 1TE",
    "wof:placetype":"postalcode"
},
  "geometry": {"coordinates":[-1.45963187524388,52.45289196798546],"type":"Point"}
}