{
  "type": "Feature",
  "properties": {
    "iso:country": "GB",
    "wof:name": "CV2 1TE",
    "wof:placetype": "postalcode"
  },
  "geometry": {"coordinates":[-1.459632,52.452892],"type":"Point"}
}
