{
  "type": "Feature",
  "properties": {
    "iso:country":"GB",
    "wof:name":"NN8 4NE",
    "wof:placetype":"postalcode"
},
  "geometry": {"coordinates":[-0.69922363411951,52.30174808549083],"type":"Point"}
}