{
  "type": "Feature",
  "properties": {
    "iso:country":"GB",
    "wof:name":"PE9 4SR",
    "wof:placetype":"postalcode"
},
  "geometry": {"coordinates":[-0.42757239395467,52.66454153963574],"type":"Point"}
}