{
  "type": "Feature",
  "properties": {
    "iso:country":"GB",
    "wof:name":"GL4 6NP",
    "wof:placetype":"postalcode"
},
  "geometry": {"coordinates":[-2.21189758403275,51.83488578628133],"type":"Point"}
}