{
  "type": "Feature",
  "properties": {
    "iso:country": "GB",
    "wof:name": "S4 7GB",
    "wof:placetype": "postalcode"
  },
  "geometry": {"coordinates":[-1.456755,53.396261],"type":"Point"}
}
