{
  "type": "Feature",
  "properties": {
    "iso:country": "GB",
    "wof:name": "IP13 9QU",
    "wof:placetype": "postalcode"
  },
  "geometry": {"coordinates":[1.296803,52.243467],"type":"Point"}
}
