{
  "type": "Feature",
  "properties": {
    "iso:country":"GB",
    "wof:name":"OL9 8QR",
    "wof:placetype":"postalcode"
},
  "geometry": {"coordinates":[-2.13951370479492,53.53722057195777],"type":"Point"}
}