{
  "type": "Feature",
  "properties": {
    "iso:country":"GB",
    "wof:name":"AL4 0RW",
    "wof:placetype":"postalcode"
},
  "geometry": {"coordinates":[-0.28921250819142,51.73954305406418],"type":"Point"}
}