{
  "type": "Feature",
  "properties": {
    "iso:country":"GB",
    "wof:name":"WA3 5QF",
    "wof:placetype":"postalcode"
},
  "geometry": {"coordinates":[-2.48119432433346,53.47234402942076],"type":"Point"}
}