{
  "type": "Feature",
  "properties": {
    "iso:country":"GB",
    "wof:name":"HP12 4EL",
    "wof:placetype":"postalcode"
},
  "geometry": {"coordinates":[-0.78662185332008,51.64179648574807],"type":"Point"}
}