{
  "type": "Feature",
  "properties": {
    "iso:country": "GB",
    "wof:name": "HP12 4EL",
    "wof:placetype": "postalcode"
  },
  "geometry": {"coordinates":[-0.786622,51.641796],"type":"Point"}
}
