{
  "type": "Feature",
  "properties": {
    "iso:country":"GB",
    "wof:name":"BN1 8AF",
    "wof:placetype":"postalcode"
},
  "geometry": {"coordinates":[-0.12387684605369,50.86709951801049],"type":"Point"}
}