{
  "type": "Feature",
  "properties": {
    "iso:country":"GB",
    "wof:name":"DD8 3PN",
    "wof:placetype":"postalcode"
},
  "geometry": {"coordinates":[-2.86181271905717,56.6877380968231],"type":"Point"}
}