{
  "type": "Feature",
  "properties": {
    "iso:country":"GB",
    "wof:name":"E17 6DA",
    "wof:placetype":"postalcode"
},
  "geometry": {"coordinates":[-0.03579643866571,51.59155768549729],"type":"Point"}
}