{
  "type": "Feature",
  "properties": {
    "iso:country":"GB",
    "wof:name":"DN6 8PR",
    "wof:placetype":"postalcode"
},
  "geometry": {"coordinates":[-1.19399064810016,53.59069442769403],"type":"Point"}
}