{
  "type": "Feature",
  "properties": {
    "iso:country":"GB",
    "wof:name":"B61 9HT",
    "wof:placetype":"postalcode"
},
  "geometry": {"coordinates":[-2.06824783135701,52.35747091872339],"type":"Point"}
}