{
  "type": "Feature",
  "properties": {
    "iso:country": "GB",
    "wof:name": "B61 9HT",
    "wof:placetype": "postalcode"
  },
  "geometry": {"coordinates":[-2.068248,52.357471],"type":"Point"}
}
