{
  "type": "Feature",
  "properties": {
    "iso:country":"GB",
    "wof:name":"BB7 4AH",
    "wof:placetype":"postalcode"
},
  "geometry": {"coordinates":[-2.35651550550024,53.89364384654344],"type":"Point"}
}