{
  "type": "Feature",
  "properties": {
    "iso:country": "GB",
    "wof:name": "BB7 4AH",
    "wof:placetype": "postalcode"
  },
  "geometry": {"coordinates":[-2.3565,53.893631],"type":"Point"}
}
