{
  "type": "Feature",
  "properties": {
    "iso:country":"GB",
    "wof:name":"CV1 2AT",
    "wof:placetype":"postalcode"
},
  "geometry": {"coordinates":[-1.49214947991013,52.4032216846777],"type":"Point"}
}