{
  "type": "Feature",
  "properties": {
    "iso:country":"GB",
    "wof:name":"CM9 5DU",
    "wof:placetype":"postalcode"
},
  "geometry": {"coordinates":[0.68369534938506,51.7265626696548],"type":"Point"}
}