{
  "type": "Feature",
  "properties": {
    "iso:country":"GB",
    "wof:name":"TS10 3HF",
    "wof:placetype":"postalcode"
},
  "geometry": {"coordinates":[-1.06500628405468,54.61656638602436],"type":"Point"}
}