{
  "type": "Feature",
  "properties": {
    "date:inception_lower": "1980-01-01",
    "date:inception_upper": "1980-01-01",
    "iso:country": "GB",
    "wof:name": "SG1 2JF",
    "wof:placetype": "postalcode"
  },
  "geometry": {"coordinates":[-0.22578,51.91516],"type":"Point"}
}
