{
  "type": "Feature",
  "properties": {
    "iso:country":"GB",
    "wof:name":"SG1 2JF",
    "wof:placetype":"postalcode"
},
  "geometry": {"coordinates":[-0.22578052920387,51.91515990004122],"type":"Point"}
}