{
  "type": "Feature",
  "properties": {
    "iso:country": "GB",
    "wof:name": "SG1 2JF",
    "wof:placetype": "postalcode"
  },
  "geometry": {"coordinates":[-0.22578,51.91516],"type":"Point"}
}
