{
  "type": "Feature",
  "properties": {
    "iso:country":"GB",
    "wof:name":"NR13 4DX",
    "wof:placetype":"postalcode"
},
  "geometry": {"coordinates":[1.48870589090375,52.61897991717404],"type":"Point"}
}