{
  "type": "Feature",
  "properties": {
    "iso:country": "GB",
    "wof:name": "M8 8EB",
    "wof:placetype": "postalcode"
  },
  "geometry": {"coordinates":[-2.251736,53.49578],"type":"Point"}
}
