{
  "type": "Feature",
  "properties": {
    "iso:country":"GB",
    "wof:name":"SE24 9HJ",
    "wof:placetype":"postalcode"
},
  "geometry": {"coordinates":[-0.09623245573652,51.4515055292326],"type":"Point"}
}