{
  "type": "Feature",
  "properties": {
    "iso:country":"GB",
    "wof:name":"L35 3JF",
    "wof:placetype":"postalcode"
},
  "geometry": {"coordinates":[-2.79556287979985,53.41003487155857],"type":"Point"}
}