{
  "type": "Feature",
  "properties": {
    "date:inception_lower": "1980-01-01",
    "date:inception_upper": "1980-01-01",
    "iso:country": "GB",
    "wof:name": "NE20 9NA",
    "wof:placetype": "postalcode"
  },
  "geometry": {"coordinates":[-1.77746,55.033966],"type":"Point"}
}
