{
  "type": "Feature",
  "properties": {
    "iso:country":"GB",
    "wof:name":"NE20 9NA",
    "wof:placetype":"postalcode"
},
  "geometry": {"coordinates":[-1.77746025559438,55.03396620662654],"type":"Point"}
}