{
  "type": "Feature",
  "properties": {
    "iso:country":"GB",
    "wof:name":"DL15 8GH",
    "wof:placetype":"postalcode"
},
  "geometry": {"coordinates":[-1.74508856740275,54.69791088803248],"type":"Point"}
}