{
  "type": "Feature",
  "properties": {
    "iso:country":"GB",
    "wof:name":"YO19 6PY",
    "wof:placetype":"postalcode"
},
  "geometry": {"coordinates":[-1.06201665562946,53.83420960738395],"type":"Point"}
}