{
  "type": "Feature",
  "properties": {
    "iso:country": "GB",
    "wof:name": "M25 9WF",
    "wof:placetype": "postalcode"
  },
  "geometry": {"coordinates":[-2.275826,53.519249],"type":"Point"}
}
