{
  "type": "Feature",
  "properties": {
    "iso:country":"GB",
    "wof:name":"SM3 9TB",
    "wof:placetype":"postalcode"
},
  "geometry": {"coordinates":[-0.21087547776288,51.37066950709962],"type":"Point"}
}