{
  "type": "Feature",
  "properties": {
    "date:inception_lower": "1997-12-01",
    "date:inception_upper": "1997-12-01",
    "iso:country": "GB",
    "wof:name": "G21 3PJ",
    "wof:placetype": "postalcode"
  },
  "geometry": {"coordinates":[-4.193833,55.891744],"type":"Point"}
}
