{
  "type": "Feature",
  "properties": {
    "iso:country": "GB",
    "wof:name": "G21 3PJ",
    "wof:placetype": "postalcode"
  },
  "geometry": {"coordinates":[-4.193833,55.891744],"type":"Point"}
}
