{
  "type": "Feature",
  "properties": {
    "iso:country":"GB",
    "wof:name":"LE16 8NA",
    "wof:placetype":"postalcode"
},
  "geometry": {"coordinates":[-0.91843634926243,52.44470519894515],"type":"Point"}
}