{
  "type": "Feature",
  "properties": {
    "iso:country": "GB",
    "wof:name": "LE16 8NA",
    "wof:placetype": "postalcode"
  },
  "geometry": {"coordinates":[-0.918439,52.444668],"type":"Point"}
}
