{
  "type": "Feature",
  "properties": {
    "iso:country":"GB",
    "wof:name":"MK43 8RL",
    "wof:placetype":"postalcode"
},
  "geometry": {"coordinates":[-0.52896174226537,52.11532471998822],"type":"Point"}
}