{
  "type": "Feature",
  "properties": {
    "date:inception_lower": "2017-11-01",
    "date:inception_upper": "2017-11-01",
    "iso:country": "GB",
    "wof:name": "ST16 1FU",
    "wof:placetype": "postalcode"
  },
  "geometry": {"coordinates":[-2.144746,52.809605],"type":"Point"}
}
