{
  "type": "Feature",
  "properties": {
    "iso:country": "GB",
    "wof:name": "G2 4AA",
    "wof:placetype": "postalcode"
  },
  "geometry": {"coordinates":[-4.269724,55.86523],"type":"Point"}
}
