{
  "type": "Feature",
  "properties": {
    "iso:country":"GB",
    "wof:name":"NE47 5DN",
    "wof:placetype":"postalcode"
},
  "geometry": {"coordinates":[-2.18601740049097,55.00520806381075],"type":"Point"}
}