{
  "type": "Feature",
  "properties": {
    "date:inception_lower": "1980-01-01",
    "date:inception_upper": "1980-01-01",
    "iso:country": "GB",
    "wof:name": "EH55 8EG",
    "wof:placetype": "postalcode"
  },
  "geometry": {"coordinates":[-3.575739,55.849176],"type":"Point"}
}
