{
  "type": "Feature",
  "properties": {
    "iso:country":"GB",
    "wof:name":"SG9 9PB",
    "wof:placetype":"postalcode"
},
  "geometry": {"coordinates":[-0.02169372139354,51.93624769911534],"type":"Point"}
}