{
  "type": "Feature",
  "properties": {
    "date:inception_lower": "1980-01-01",
    "date:inception_upper": "1980-01-01",
    "iso:country": "GB",
    "wof:name": "BD24 0AS",
    "wof:placetype": "postalcode"
  },
  "geometry": {"coordinates":[-2.287034,54.070128],"type":"Point"}
}
