{
  "type": "Feature",
  "properties": {
    "iso:country": "GB",
    "wof:name": "BD24 0AS",
    "wof:placetype": "postalcode"
  },
  "geometry": {"coordinates":[-2.287034,54.070128],"type":"Point"}
}
