{
  "type": "Feature",
  "properties": {
    "iso:country":"GB",
    "wof:name":"G78 1SN",
    "wof:placetype":"postalcode"
},
  "geometry": {"coordinates":[-4.3872873359105,55.80156429379327],"type":"Point"}
}