{
  "type": "Feature",
  "properties": {
    "iso:country":"GB",
    "wof:name":"TR4 8BT",
    "wof:placetype":"postalcode"
},
  "geometry": {"coordinates":[-5.2105047500108,50.2925213235048],"type":"Point"}
}