{
  "type": "Feature",
  "properties": {
    "date:inception_lower": "2000-12-01",
    "date:inception_upper": "2000-12-01",
    "iso:country": "GB",
    "wof:name": "WD18 9EU",
    "wof:placetype": "postalcode"
  },
  "geometry": {"coordinates":[-0.435082,51.639104],"type":"Point"}
}
