{
  "type": "Feature",
  "properties": {
    "iso:country": "GB",
    "wof:name": "WD18 9EU",
    "wof:placetype": "postalcode"
  },
  "geometry": {"coordinates":[-0.435082,51.639104],"type":"Point"}
}
