{
  "type": "Feature",
  "properties": {
    "iso:country":"GB",
    "wof:name":"WV4 6SN",
    "wof:placetype":"postalcode"
},
  "geometry": {"coordinates":[-2.11894621761364,52.55790758659338],"type":"Point"}
}