{
  "type": "Feature",
  "properties": {
    "iso:country":"GB",
    "wof:name":"L33 4DB",
    "wof:placetype":"postalcode"
},
  "geometry": {"coordinates":[-2.8781419127506,53.50071009248285],"type":"Point"}
}