{
  "type": "Feature",
  "properties": {
    "iso:country": "GB",
    "wof:name": "L33 4DB",
    "wof:placetype": "postalcode"
  },
  "geometry": {"coordinates":[-2.878142,53.50071],"type":"Point"}
}
