{
  "type": "Feature",
  "properties": {
    "date:inception_lower": "1985-10-01",
    "date:inception_upper": "1985-10-01",
    "iso:country": "GB",
    "wof:name": "DY4 8DF",
    "wof:placetype": "postalcode"
  },
  "geometry": {"coordinates":[-2.076209,52.528789],"type":"Point"}
}
