{
  "type": "Feature",
  "properties": {
    "iso:country":"GB",
    "wof:name":"HA9 9EL",
    "wof:placetype":"postalcode"
},
  "geometry": {"coordinates":[-0.26629110740012,51.56358098855044],"type":"Point"}
}