{
  "type": "Feature",
  "properties": {
    "date:inception_lower":"1980-01-01",
    "date:inception_upper":"1980-01-31",
    "iso:country":"GB",
    "wof:name":"HA9 9EL",
    "wof:placetype":"postalcode"
},
  "geometry": {"coordinates":[-0.266291,51.563581],"type":"Point"}
}