{
  "type": "Feature",
  "properties": {
    "iso:country":"GB",
    "wof:name":"BA22 7EB",
    "wof:placetype":"postalcode"
},
  "geometry": {"coordinates":[-2.48766404865139,51.03352157408226],"type":"Point"}
}