{
  "type": "Feature",
  "properties": {
    "iso:country": "GB",
    "wof:name": "IV36 1PG",
    "wof:placetype": "postalcode"
  },
  "geometry": {"coordinates":[-3.611153,57.610559],"type":"Point"}
}
