{
  "type": "Feature",
  "properties": {
    "date:inception_lower":"1998-12-01",
    "date:inception_upper":"1998-12-31",
    "iso:country":"GB",
    "wof:name":"IV36 1PG",
    "wof:placetype":"postalcode"
},
  "geometry": {"coordinates":[-3.611153,57.610559],"type":"Point"}
}