{
  "type": "Feature",
  "properties": {
    "iso:country": "GB",
    "wof:name": "EH54 5NH",
    "wof:placetype": "postalcode"
  },
  "geometry": {"coordinates":[-3.485413,55.897686],"type":"Point"}
}
