{
  "type": "Feature",
  "properties": {
    "iso:country":"GB",
    "wof:name":"EH54 5NH",
    "wof:placetype":"postalcode"
},
  "geometry": {"coordinates":[-3.48541260480585,55.89768632540378],"type":"Point"}
}