{
  "type": "Feature",
  "properties": {
    "date:inception_lower":"1980-01-01",
    "date:inception_upper":"1980-01-31",
    "iso:country":"GB",
    "wof:name":"EH54 5NH",
    "wof:placetype":"postalcode"
},
  "geometry": {"coordinates":[-3.485413,55.897686],"type":"Point"}
}