{
  "type": "Feature",
  "properties": {
    "date:inception_lower": "2016-09-01",
    "date:inception_upper": "2016-09-01",
    "iso:country": "GB",
    "wof:name": "L33 2AF",
    "wof:placetype": "postalcode"
  },
  "geometry": {"coordinates":[-2.896505,53.494396],"type":"Point"}
}
