{
  "type": "Feature",
  "properties": {
    "iso:country": "GB",
    "wof:name": "L33 2AF",
    "wof:placetype": "postalcode"
  },
  "geometry": {"coordinates":[-2.896505,53.494396],"type":"Point"}
}
