{
  "type": "Feature",
  "properties": {
    "date:inception_lower": "1980-01-01",
    "date:inception_upper": "1980-01-01",
    "iso:country": "GB",
    "wof:name": "SG1 3LU",
    "wof:placetype": "postalcode"
  },
  "geometry": {"coordinates":[-0.197524,51.908373],"type":"Point"}
}
