{
  "type": "Feature",
  "properties": {
    "iso:country":"GB",
    "wof:name":"EH26 9JS",
    "wof:placetype":"postalcode"
},
  "geometry": {"coordinates":[-3.2418463197737,55.83176977310727],"type":"Point"}
}