{
  "type": "Feature",
  "properties": {
    "iso:country":"GB",
    "wof:name":"DA11 8SP",
    "wof:placetype":"postalcode"
},
  "geometry": {"coordinates":[0.34592992502982,51.42832718927006],"type":"Point"}
}