{
  "type": "Feature",
  "properties": {
    "date:inception_lower": "1980-01-01",
    "date:inception_upper": "1980-01-01",
    "iso:country": "GB",
    "wof:name": "LS17 8JY",
    "wof:placetype": "postalcode"
  },
  "geometry": {"coordinates":[-1.469336,53.85261],"type":"Point"}
}
