{
  "type": "Feature",
  "properties": {
    "iso:country":"GB",
    "wof:name":"LS17 8JY",
    "wof:placetype":"postalcode"
},
  "geometry": {"coordinates":[-1.46933619527747,53.85261047138651],"type":"Point"}
}