{
  "type": "Feature",
  "properties": {
    "iso:country":"GB",
    "wof:name":"PA1 2SN",
    "wof:placetype":"postalcode"
},
  "geometry": {"coordinates":[-4.43188390244944,55.84704064349549],"type":"Point"}
}