{
  "type": "Feature",
  "properties": {
    "date:inception_lower": "1989-04-01",
    "date:inception_upper": "1989-04-01",
    "iso:country": "GB",
    "wof:name": "PA1 2SN",
    "wof:placetype": "postalcode"
  },
  "geometry": {"coordinates":[-4.431884,55.847041],"type":"Point"}
}
