{
  "type": "Feature",
  "properties": {
    "iso:country": "GB",
    "wof:name": "PA1 2SN",
    "wof:placetype": "postalcode"
  },
  "geometry": {"coordinates":[-4.431884,55.847041],"type":"Point"}
}
