{
  "type": "Feature",
  "properties": {
    "iso:country":"GB",
    "wof:name":"DE22 3AT",
    "wof:placetype":"postalcode"
},
  "geometry": {"coordinates":[-1.49626074079201,52.92727071727911],"type":"Point"}
}