{
  "type": "Feature",
  "properties": {
    "iso:country": "GB",
    "wof:name": "DE22 3AT",
    "wof:placetype": "postalcode"
  },
  "geometry": {"coordinates":[-1.496261,52.927271],"type":"Point"}
}
