{
  "type": "Feature",
  "properties": {
    "date:inception_lower": "1985-10-01",
    "date:inception_upper": "1985-10-01",
    "iso:country": "GB",
    "wof:name": "TN17 3QL",
    "wof:placetype": "postalcode"
  },
  "geometry": {"coordinates":[0.512762,51.086802],"type":"Point"}
}
