{
  "type": "Feature",
  "properties": {
    "iso:country": "GB",
    "wof:name": "TN17 3QL",
    "wof:placetype": "postalcode"
  },
  "geometry": {"coordinates":[0.512702,51.08675],"type":"Point"}
}
