{
  "type": "Feature",
  "properties": {
    "iso:country":"GB",
    "wof:name":"PE12 6LE",
    "wof:placetype":"postalcode"
},
  "geometry": {"coordinates":[-0.03994682021996,52.82773112263688],"type":"Point"}
}