{
  "type": "Feature",
  "properties": {
    "date:inception_lower": "1980-01-01",
    "date:inception_upper": "1980-01-01",
    "iso:country": "GB",
    "wof:name": "CT5 2QD",
    "wof:placetype": "postalcode"
  },
  "geometry": {"coordinates":[1.061998,51.361889],"type":"Point"}
}
