{
  "type": "Feature",
  "properties": {
    "iso:country":"GB",
    "wof:name":"CT5 2QD",
    "wof:placetype":"postalcode"
},
  "geometry": {"coordinates":[1.06199790483796,51.36188870097428],"type":"Point"}
}