{
  "type": "Feature",
  "properties": {
    "iso:country":"GB",
    "wof:name":"BL7 0AB",
    "wof:placetype":"postalcode"
},
  "geometry": {"coordinates":[-2.39645635552359,53.64072015833919],"type":"Point"}
}