{
  "type": "Feature",
  "properties": {
    "iso:country":"GB",
    "wof:name":"HG5 0EF",
    "wof:placetype":"postalcode"
},
  "geometry": {"coordinates":[-1.46790668555805,54.00957734236798],"type":"Point"}
}