{
  "type": "Feature",
  "properties": {
    "iso:country":"GB",
    "wof:name":"SG18 8QQ",
    "wof:placetype":"postalcode"
},
  "geometry": {"coordinates":[-0.25900350763055,52.08265880758791],"type":"Point"}
}