{
  "type": "Feature",
  "properties": {
    "date:inception_lower":"1990-02-01",
    "date:inception_upper":"1990-02-28",
    "iso:country":"GB",
    "wof:name":"SG18 8QQ",
    "wof:placetype":"postalcode"
},
  "geometry": {"coordinates":[-0.259003,52.082659],"type":"Point"}
}