{
  "type": "Feature",
  "properties": {
    "iso:country":"GB",
    "wof:name":"NR14 8DF",
    "wof:placetype":"postalcode"
},
  "geometry": {"coordinates":[1.24494798354626,52.57358088038862],"type":"Point"}
}