{
  "type": "Feature",
  "properties": {
    "iso:country": "GB",
    "wof:name": "NR14 8DF",
    "wof:placetype": "postalcode"
  },
  "geometry": {"coordinates":[1.244948,52.573581],"type":"Point"}
}
