{
  "type": "Feature",
  "properties": {
    "date:inception_lower": "1980-01-01",
    "date:inception_upper": "1980-01-01",
    "iso:country": "GB",
    "wof:name": "NR14 8DF",
    "wof:placetype": "postalcode"
  },
  "geometry": {"coordinates":[1.244948,52.573581],"type":"Point"}
}
