{
  "type": "Feature",
  "properties": {
    "iso:country": "GB",
    "wof:name": "B77 1LG",
    "wof:placetype": "postalcode"
  },
  "geometry": {"coordinates":[-1.68365,52.599456],"type":"Point"}
}
