{
  "type": "Feature",
  "properties": {
    "iso:country":"GB",
    "wof:name":"B77 1LG",
    "wof:placetype":"postalcode"
},
  "geometry": {"coordinates":[-1.68379874482746,52.59929491843232],"type":"Point"}
}