{
  "type": "Feature",
  "properties": {
    "iso:country":"GB",
    "wof:name":"CM9 8ED",
    "wof:placetype":"postalcode"
},
  "geometry": {"coordinates":[0.69927932006215,51.77833128312792],"type":"Point"}
}