{
  "type": "Feature",
  "properties": {
    "date:inception_lower": "1980-01-01",
    "date:inception_upper": "1980-01-01",
    "iso:country": "GB",
    "wof:name": "CM9 8ED",
    "wof:placetype": "postalcode"
  },
  "geometry": {"coordinates":[0.699279,51.778331],"type":"Point"}
}
