{
  "type": "Feature",
  "properties": {
    "iso:country":"GB",
    "wof:name":"PE30 2JF",
    "wof:placetype":"postalcode"
},
  "geometry": {"coordinates":[0.37816563136154,52.78005813024495],"type":"Point"}
}