{
  "type": "Feature",
  "properties": {
    "iso:country": "GB",
    "wof:name": "CH41 3PS",
    "wof:placetype": "postalcode"
  },
  "geometry": {"coordinates":[-3.02972,53.396999],"type":"Point"}
}
