{
  "type": "Feature",
  "properties": {
    "iso:country": "GB",
    "wof:name": "BH17 9HW",
    "wof:placetype": "postalcode"
  },
  "geometry": {"coordinates":[-1.972232,50.757157],"type":"Point"}
}
