{
  "type": "Feature",
  "properties": {
    "date:inception_lower":"1992-01-01",
    "date:inception_upper":"1992-01-31",
    "iso:country":"GB",
    "wof:name":"DT2 8US",
    "wof:placetype":"postalcode"
},
  "geometry": {"coordinates":[-2.388594,50.677034],"type":"Point"}
}