{
  "type": "Feature",
  "properties": {
    "iso:country": "GB",
    "wof:name": "DT2 8US",
    "wof:placetype": "postalcode"
  },
  "geometry": {"coordinates":[-2.388594,50.677034],"type":"Point"}
}
