{
  "type": "Feature",
  "properties": {
    "iso:country":"GB",
    "wof:name":"LN5 9HU",
    "wof:placetype":"postalcode"
},
  "geometry": {"coordinates":[-0.64821043318933,53.11047093117961],"type":"Point"}
}