{
  "type": "Feature",
  "properties": {
    "iso:country": "GB",
    "wof:name": "LN5 9HU",
    "wof:placetype": "postalcode"
  },
  "geometry": {"coordinates":[-0.648329,53.110413],"type":"Point"}
}
