{
  "type": "Feature",
  "properties": {
    "iso:country":"GB",
    "wof:name":"SN13 0NG",
    "wof:placetype":"postalcode"
},
  "geometry": {"coordinates":[-2.22011374471078,51.42979576116173],"type":"Point"}
}