{
  "type": "Feature",
  "properties": {
    "date:inception_lower": "1980-01-01",
    "date:inception_upper": "1980-01-01",
    "iso:country": "GB",
    "wof:name": "SA67 8RX",
    "wof:placetype": "postalcode"
  },
  "geometry": {"coordinates":[-4.740253,51.774879],"type":"Point"}
}
