{
  "type": "Feature",
  "properties": {
    "iso:country":"GB",
    "wof:name":"SA67 8RX",
    "wof:placetype":"postalcode"
},
  "geometry": {"coordinates":[-4.74025283691479,51.77487929738907],"type":"Point"}
}