{
  "type": "Feature",
  "properties": {
    "iso:country": "GB",
    "wof:name": "WF5 0RS",
    "wof:placetype": "postalcode"
  },
  "geometry": {"coordinates":[-1.573993,53.677796],"type":"Point"}
}
