{
  "type": "Feature",
  "properties": {
    "iso:country":"GB",
    "wof:name":"WF5 0RS",
    "wof:placetype":"postalcode"
},
  "geometry": {"coordinates":[-1.57399341000492,53.67779581715955],"type":"Point"}
}