{
  "type": "Feature",
  "properties": {
    "iso:country": "GB",
    "wof:name": "PO17 5PA",
    "wof:placetype": "postalcode"
  },
  "geometry": {"coordinates":[-1.20234,50.902796],"type":"Point"}
}
