{
  "type": "Feature",
  "properties": {
    "iso:country":"GB",
    "wof:name":"LU2 8UQ",
    "wof:placetype":"postalcode"
},
  "geometry": {"coordinates":[-0.3657421464884,51.89118251031042],"type":"Point"}
}