{
  "type": "Feature",
  "properties": {
    "iso:country":"GB",
    "wof:name":"NW10 5JB",
    "wof:placetype":"postalcode"
},
  "geometry": {"coordinates":[-0.22392507560713,51.53410887924966],"type":"Point"}
}