{
  "type": "Feature",
  "properties": {
    "iso:country":"GB",
    "wof:name":"SK17 1AU",
    "wof:placetype":"postalcode"
},
  "geometry": {"coordinates":[-1.91230556228802,53.26226529518355],"type":"Point"}
}