{
  "type": "Feature",
  "properties": {
    "iso:country": "GB",
    "wof:name": "OX14 1YB",
    "wof:placetype": "postalcode"
  },
  "geometry": {"coordinates":[-1.281649,51.687227],"type":"Point"}
}
