{
  "type": "Feature",
  "properties": {
    "iso:country":"GB",
    "wof:name":"AB54 7TT",
    "wof:placetype":"postalcode"
},
  "geometry": {"coordinates":[-2.61758895294495,57.55264185591644],"type":"Point"}
}