{
  "type": "Feature",
  "properties": {
    "date:inception_lower":"1993-01-01",
    "date:inception_upper":"1993-01-31",
    "iso:country":"GB",
    "wof:name":"PL19 8SF",
    "wof:placetype":"postalcode"
},
  "geometry": {"coordinates":[-4.192192,50.572324],"type":"Point"}
}