{
  "type": "Feature",
  "properties": {
    "iso:country": "GB",
    "wof:name": "PL19 8SF",
    "wof:placetype": "postalcode"
  },
  "geometry": {"coordinates":[-4.192192,50.572324],"type":"Point"}
}
