{
  "type": "Feature",
  "properties": {
    "iso:country":"GB",
    "wof:name":"HG4 2LB",
    "wof:placetype":"postalcode"
},
  "geometry": {"coordinates":[-1.53532503948868,54.1255545795874],"type":"Point"}
}