{
  "type": "Feature",
  "properties": {
    "iso:country":"GB",
    "wof:name":"SE9 3LF",
    "wof:placetype":"postalcode"
},
  "geometry": {"coordinates":[0.0650842431668,51.4279471635388],"type":"Point"}
}