{
  "type": "Feature",
  "properties": {
    "iso:country": "GB",
    "wof:name": "SE9 3LF",
    "wof:placetype": "postalcode"
  },
  "geometry": {"coordinates":[0.065084,51.427947],"type":"Point"}
}
