{
  "type": "Feature",
  "properties": {
    "iso:country":"GB",
    "wof:name":"CV35 9DJ",
    "wof:placetype":"postalcode"
},
  "geometry": {"coordinates":[-1.55455457672147,52.21660104574454],"type":"Point"}
}