{
  "type": "Feature",
  "properties": {
    "date:inception_lower": "2014-06-01",
    "date:inception_upper": "2014-06-01",
    "iso:country": "GB",
    "wof:name": "CV35 9DJ",
    "wof:placetype": "postalcode"
  },
  "geometry": {"coordinates":[-1.554555,52.216601],"type":"Point"}
}
