{
  "type": "Feature",
  "properties": {
    "iso:country":"GB",
    "wof:name":"CW9 5QQ",
    "wof:placetype":"postalcode"
},
  "geometry": {"coordinates":[-2.50664793498634,53.26032096771752],"type":"Point"}
}