{
  "type": "Feature",
  "properties": {
    "date:inception_lower": "2013-04-01",
    "date:inception_upper": "2013-04-01",
    "iso:country": "GB",
    "wof:name": "HR9 5GT",
    "wof:placetype": "postalcode"
  },
  "geometry": {"coordinates":[-2.585178,51.907248],"type":"Point"}
}
