{
  "type": "Feature",
  "properties": {
    "iso:country": "GB",
    "wof:name": "HR9 5GT",
    "wof:placetype": "postalcode"
  },
  "geometry": {"coordinates":[-2.585178,51.907248],"type":"Point"}
}
