{
  "type": "Feature",
  "properties": {
    "iso:country":"GB",
    "wof:name":"HR9 5GT",
    "wof:placetype":"postalcode"
},
  "geometry": {"coordinates":[-2.58517821370181,51.90724755034228],"type":"Point"}
}