{
  "type": "Feature",
  "properties": {
    "iso:country":"GB",
    "wof:name":"HA1 1JZ",
    "wof:placetype":"postalcode"
},
  "geometry": {"coordinates":[-0.33568046271426,51.5823632537805],"type":"Point"}
}