{
  "type": "Feature",
  "properties": {
    "iso:country":"GB",
    "wof:name":"SA40 9QR",
    "wof:placetype":"postalcode"
},
  "geometry": {"coordinates":[-4.11990811578838,52.07464426812285],"type":"Point"}
}