{
  "type": "Feature",
  "properties": {
    "date:inception_lower": "1980-01-01",
    "date:inception_upper": "1980-01-01",
    "iso:country": "GB",
    "wof:name": "CO12 4SP",
    "wof:placetype": "postalcode"
  },
  "geometry": {"coordinates":[1.254106,51.947694],"type":"Point"}
}
