{
  "type": "Feature",
  "properties": {
    "date:inception_lower": "2013-07-01",
    "date:inception_upper": "2013-07-01",
    "iso:country": "GB",
    "wof:name": "TN23 1LQ",
    "wof:placetype": "postalcode"
  },
  "geometry": {"coordinates":[0.869375,51.149638],"type":"Point"}
}
