{
  "type": "Feature",
  "properties": {
    "date:inception_lower": "1980-01-01",
    "date:inception_upper": "1980-01-01",
    "iso:country": "GB",
    "wof:name": "LE2 4FQ",
    "wof:placetype": "postalcode"
  },
  "geometry": {"coordinates":[-1.079808,52.602014],"type":"Point"}
}
