{
  "type": "Feature",
  "properties": {
    "iso:country":"GB",
    "wof:name":"LE2 4FQ",
    "wof:placetype":"postalcode"
},
  "geometry": {"coordinates":[-1.07980786785333,52.60201435515031],"type":"Point"}
}