{
  "type": "Feature",
  "properties": {
    "iso:country": "GB",
    "wof:name": "SY3 9LE",
    "wof:placetype": "postalcode"
  },
  "geometry": {"coordinates":[-2.756302,52.687995],"type":"Point"}
}
