{
  "type": "Feature",
  "properties": {
    "iso:country": "GB",
    "wof:name": "TA6 6XS",
    "wof:placetype": "postalcode"
  },
  "geometry": {"coordinates":[-2.996708,51.109286],"type":"Point"}
}
