{
  "type": "Feature",
  "properties": {
    "date:inception_lower": "2015-04-01",
    "date:inception_upper": "2015-04-01",
    "iso:country": "GB",
    "wof:name": "TA6 6XS",
    "wof:placetype": "postalcode"
  },
  "geometry": {"coordinates":[-2.996708,51.109286],"type":"Point"}
}
