{
  "type": "Feature",
  "properties": {
    "iso:country":"GB",
    "wof:name":"G81 2LW",
    "wof:placetype":"postalcode"
},
  "geometry": {"coordinates":[-4.39072642358527,55.90833522120699],"type":"Point"}
}