{
  "type": "Feature",
  "properties": {
    "date:inception_lower": "1980-01-01",
    "date:inception_upper": "1980-01-01",
    "iso:country": "GB",
    "wof:name": "PA15 4DX",
    "wof:placetype": "postalcode"
  },
  "geometry": {"coordinates":[-4.770777,55.945545],"type":"Point"}
}
