{
  "type": "Feature",
  "properties": {
    "iso:country": "GB",
    "wof:name": "DH9 9NG",
    "wof:placetype": "postalcode"
  },
  "geometry": {"coordinates":[-1.710606,54.879613],"type":"Point"}
}
