{
  "type": "Feature",
  "properties": {
    "iso:country":"GB",
    "wof:name":"DH9 9NG",
    "wof:placetype":"postalcode"
},
  "geometry": {"coordinates":[-1.71060652062659,54.87961260726262],"type":"Point"}
}