{
  "type": "Feature",
  "properties": {
    "iso:country":"GB",
    "wof:name":"SA15 2RG",
    "wof:placetype":"postalcode"
},
  "geometry": {"coordinates":[-4.16524356514126,51.67520423100049],"type":"Point"}
}