{
  "type": "Feature",
  "properties": {
    "date:inception_lower": "1980-01-01",
    "date:inception_upper": "1980-01-01",
    "iso:country": "GB",
    "wof:name": "SA15 2RG",
    "wof:placetype": "postalcode"
  },
  "geometry": {"coordinates":[-4.165244,51.675204],"type":"Point"}
}
