{
  "type": "Feature",
  "properties": {
    "iso:country":"GB",
    "wof:name":"RG24 8UU",
    "wof:placetype":"postalcode"
},
  "geometry": {"coordinates":[-1.05411117609579,51.27943113353037],"type":"Point"}
}