{
  "type": "Feature",
  "properties": {
    "iso:country":"GB",
    "wof:name":"ME12 4NB",
    "wof:placetype":"postalcode"
},
  "geometry": {"coordinates":[0.90821474769288,51.4029378077506],"type":"Point"}
}