{
  "type": "Feature",
  "properties": {
    "iso:country": "GB",
    "wof:name": "GL18 2AL",
    "wof:placetype": "postalcode"
  },
  "geometry": {"coordinates":[-2.442208,51.980545],"type":"Point"}
}
