{
  "type": "Feature",
  "properties": {
    "iso:country":"GB",
    "wof:name":"RH6 9BS",
    "wof:placetype":"postalcode"
},
  "geometry": {"coordinates":[-0.15297624712888,51.16937477293158],"type":"Point"}
}