{
  "type": "Feature",
  "properties": {
    "iso:country":"GB",
    "wof:name":"SE8 4RL",
    "wof:placetype":"postalcode"
},
  "geometry": {"coordinates":[-0.0228517228793,51.47697221248358],"type":"Point"}
}