{
  "type": "Feature",
  "properties": {
    "iso:country": "GB",
    "wof:name": "SE8 4RL",
    "wof:placetype": "postalcode"
  },
  "geometry": {"coordinates":[-0.022852,51.476972],"type":"Point"}
}
