{
  "type": "Feature",
  "properties": {
    "iso:country":"GB",
    "wof:name":"HR5 3PD",
    "wof:placetype":"postalcode"
},
  "geometry": {"coordinates":[-3.11179177102406,52.18044579032045],"type":"Point"}
}