{
  "type": "Feature",
  "properties": {
    "iso:country":"GB",
    "wof:name":"SG18 9AY",
    "wof:placetype":"postalcode"
},
  "geometry": {"coordinates":[-0.27796157788326,52.09176700995355],"type":"Point"}
}