{
  "type": "Feature",
  "properties": {
    "date:inception_lower":"1991-09-01",
    "date:inception_upper":"1991-09-30",
    "iso:country":"GB",
    "wof:name":"SG18 9AY",
    "wof:placetype":"postalcode"
},
  "geometry": {"coordinates":[-0.277962,52.091767],"type":"Point"}
}