{
  "type": "Feature",
  "properties": {
    "iso:country":"GB",
    "wof:name":"NE34 8BZ",
    "wof:placetype":"postalcode"
},
  "geometry": {"coordinates":[-1.41282823670953,54.9715844121279],"type":"Point"}
}