{
  "type": "Feature",
  "properties": {
    "date:inception_lower":"2009-05-01",
    "date:inception_upper":"2009-05-31",
    "iso:country":"GB",
    "wof:name":"NE34 8BZ",
    "wof:placetype":"postalcode"
},
  "geometry": {"coordinates":[-1.412828,54.971584],"type":"Point"}
}