{
  "type": "Feature",
  "properties": {
    "iso:country": "GB",
    "wof:name": "NE34 8BZ",
    "wof:placetype": "postalcode"
  },
  "geometry": {"coordinates":[-1.412828,54.971584],"type":"Point"}
}
