{
  "type": "Feature",
  "properties": {
    "date:inception_lower": "2022-10-01",
    "date:inception_upper": "2022-10-01",
    "iso:country": "GB",
    "wof:name": "RG14 2GL",
    "wof:placetype": "postalcode"
  },
  "geometry": {"coordinates":[-1.321354,51.419533],"type":"Point"}
}
