{
  "type": "Feature",
  "properties": {
    "iso:country":"GB",
    "wof:name":"SA61 1QH",
    "wof:placetype":"postalcode"
},
  "geometry": {"coordinates":[-4.97161719668311,51.79950014683566],"type":"Point"}
}