{
  "type": "Feature",
  "properties": {
    "iso:country":"GB",
    "wof:name":"CA16 6DB",
    "wof:placetype":"postalcode"
},
  "geometry": {"coordinates":[-2.48292610598171,54.620315533506],"type":"Point"}
}