{
  "type": "Feature",
  "properties": {
    "date:inception_lower": "1980-01-01",
    "date:inception_upper": "1980-01-01",
    "iso:country": "GB",
    "wof:name": "BD23 3BB",
    "wof:placetype": "postalcode"
  },
  "geometry": {"coordinates":[-2.097979,53.935253],"type":"Point"}
}
