{
  "type": "Feature",
  "properties": {
    "iso:country":"GB",
    "wof:name":"TR7 1FL",
    "wof:placetype":"postalcode"
},
  "geometry": {"coordinates":[-5.09187410040181,50.41900796352227],"type":"Point"}
}