{
  "type": "Feature",
  "properties": {
    "iso:country":"GB",
    "wof:name":"CO3 9AZ",
    "wof:placetype":"postalcode"
},
  "geometry": {"coordinates":[0.84907556947041,51.88632363259327],"type":"Point"}
}