{
  "type": "Feature",
  "properties": {
    "iso:country":"GB",
    "wof:name":"S75 3NP",
    "wof:placetype":"postalcode"
},
  "geometry": {"coordinates":[-1.51986817384762,53.53820908006266],"type":"Point"}
}