{
  "type": "Feature",
  "properties": {
    "iso:country":"GB",
    "wof:name":"SA32 7BQ",
    "wof:placetype":"postalcode"
},
  "geometry": {"coordinates":[-4.09658129765517,51.97010572496014],"type":"Point"}
}