{
  "type": "Feature",
  "properties": {
    "date:inception_lower": "1980-01-01",
    "date:inception_upper": "1980-01-01",
    "iso:country": "GB",
    "wof:name": "G2 4RU",
    "wof:placetype": "postalcode"
  },
  "geometry": {"coordinates":[-4.261737,55.863889],"type":"Point"}
}
