{
  "type": "Feature",
  "properties": {
    "iso:country": "GB",
    "wof:name": "G2 4RU",
    "wof:placetype": "postalcode"
  },
  "geometry": {"coordinates":[-4.261755,55.863957],"type":"Point"}
}
