{
  "type": "Feature",
  "properties": {
    "iso:country":"GB",
    "wof:name":"WF10 1BU",
    "wof:placetype":"postalcode"
},
  "geometry": {"coordinates":[-1.36438057976295,53.72922392417812],"type":"Point"}
}