{
  "type": "Feature",
  "properties": {
    "date:inception_lower":"2016-02-01",
    "date:inception_upper":"2016-02-29",
    "iso:country":"GB",
    "wof:name":"WF10 1BU",
    "wof:placetype":"postalcode"
},
  "geometry": {"coordinates":[-1.363859,53.729841],"type":"Point"}
}