{
  "type": "Feature",
  "properties": {
    "iso:country":"GB",
    "wof:name":"AB51 8TB",
    "wof:placetype":"postalcode"
},
  "geometry": {"coordinates":[-2.32770360444533,57.39943320573585],"type":"Point"}
}