{
  "type": "Feature",
  "properties": {
    "iso:country":"GB",
    "wof:name":"SY16 2HT",
    "wof:placetype":"postalcode"
},
  "geometry": {"coordinates":[-3.30889916726703,52.51620572797569],"type":"Point"}
}