{
  "type": "Feature",
  "properties": {
    "iso:country": "GB",
    "wof:name": "GL7 5SA",
    "wof:placetype": "postalcode"
  },
  "geometry": {"coordinates":[-1.899461,51.719697],"type":"Point"}
}
