{
  "type": "Feature",
  "properties": {
    "date:inception_lower":"1980-01-01",
    "date:inception_upper":"1980-01-31",
    "iso:country":"GB",
    "wof:name":"GL7 5SA",
    "wof:placetype":"postalcode"
},
  "geometry": {"coordinates":[-1.899461,51.719697],"type":"Point"}
}