{
  "type": "Feature",
  "properties": {
    "iso:country":"GB",
    "wof:name":"GL7 5SA",
    "wof:placetype":"postalcode"
},
  "geometry": {"coordinates":[-1.89946105367988,51.71969732545546],"type":"Point"}
}