{
  "type": "Feature",
  "properties": {
    "iso:country":"GB",
    "wof:name":"BD21 4DH",
    "wof:placetype":"postalcode"
},
  "geometry": {"coordinates":[-1.89095807774406,53.87413573267469],"type":"Point"}
}