{
  "type": "Feature",
  "properties": {
    "iso:country":"GB",
    "wof:name":"LA8 0JW",
    "wof:placetype":"postalcode"
},
  "geometry": {"coordinates":[-2.74701044313957,54.27766597483524],"type":"Point"}
}