{
  "type": "Feature",
  "properties": {
    "date:inception_lower": "1980-01-01",
    "date:inception_upper": "1980-01-01",
    "iso:country": "GB",
    "wof:name": "LA8 0JW",
    "wof:placetype": "postalcode"
  },
  "geometry": {"coordinates":[-2.747043,54.277712],"type":"Point"}
}
