{
  "type": "Feature",
  "properties": {
    "date:inception_lower": "2015-05-01",
    "date:inception_upper": "2015-05-01",
    "iso:country": "GB",
    "wof:name": "BS16 1GZ",
    "wof:placetype": "postalcode"
  },
  "geometry": {"coordinates":[-2.559038,51.497237],"type":"Point"}
}
