{
  "type": "Feature",
  "properties": {
    "iso:country":"GB",
    "wof:name":"BS16 1GZ",
    "wof:placetype":"postalcode"
},
  "geometry": {"coordinates":[-2.55903689363321,51.49723876840497],"type":"Point"}
}