{
  "type": "Feature",
  "properties": {
    "iso:country":"GB",
    "wof:name":"SM2 5BY",
    "wof:placetype":"postalcode"
},
  "geometry": {"coordinates":[-0.19242870161292,51.35606104705426],"type":"Point"}
}