{
  "type": "Feature",
  "properties": {
    "iso:country": "GB",
    "wof:name": "NN15 5RU",
    "wof:placetype": "postalcode"
  },
  "geometry": {"coordinates":[-0.680835,52.364327],"type":"Point"}
}
