{
  "type": "Feature",
  "properties": {
    "iso:country": "GB",
    "wof:name": "M28 2UL",
    "wof:placetype": "postalcode"
  },
  "geometry": {"coordinates":[-2.375185,53.496966],"type":"Point"}
}
