{
  "type": "Feature",
  "properties": {
    "iso:country":"GB",
    "wof:name":"RG2 9HZ",
    "wof:placetype":"postalcode"
},
  "geometry": {"coordinates":[-0.91914772812965,51.40354064461032],"type":"Point"}
}