{
  "type": "Feature",
  "properties": {
    "date:inception_lower":"2001-12-01",
    "date:inception_upper":"2001-12-31",
    "iso:country":"GB",
    "wof:name":"SY16 1WE",
    "wof:placetype":"postalcode"
},
  "geometry": {"coordinates":[-3.313264,52.514305],"type":"Point"}
}