{
  "type": "Feature",
  "properties": {
    "iso:country":"GB",
    "wof:name":"W4 3LW",
    "wof:placetype":"postalcode"
},
  "geometry": {"coordinates":[-0.27365754879116,51.48522240139575],"type":"Point"}
}