{
  "type": "Feature",
  "properties": {
    "iso:country":"GB",
    "wof:name":"TQ2 6BS",
    "wof:placetype":"postalcode"
},
  "geometry": {"coordinates":[-3.55351982238919,50.47021442358327],"type":"Point"}
}