{
  "type": "Feature",
  "properties": {
    "iso:country":"GB",
    "wof:name":"PL9 9LZ",
    "wof:placetype":"postalcode"
},
  "geometry": {"coordinates":[-4.08874657826851,50.34291352887277],"type":"Point"}
}