{
  "type": "Feature",
  "properties": {
    "date:inception_lower": "2020-10-01",
    "date:inception_upper": "2020-10-01",
    "iso:country": "GB",
    "wof:name": "E9 5TU",
    "wof:placetype": "postalcode"
  },
  "geometry": {"coordinates":[-0.024685,51.54454],"type":"Point"}
}
