{
  "type": "Feature",
  "properties": {
    "date:inception_lower": "2024-10-01",
    "date:inception_upper": "2024-10-01",
    "iso:country": "GB",
    "wof:name": "CO16 0FP",
    "wof:placetype": "postalcode"
  },
  "geometry": {"coordinates":[1.109714,51.890939],"type":"Point"}
}
