{
  "type": "Feature",
  "properties": {
    "iso:country": "GB",
    "wof:name": "DL6 3RQ",
    "wof:placetype": "postalcode"
  },
  "geometry": {"coordinates":[-1.389551,54.334411],"type":"Point"}
}
