{
  "type": "Feature",
  "properties": {
    "iso:country":"GB",
    "wof:name":"DL6 3RQ",
    "wof:placetype":"postalcode"
},
  "geometry": {"coordinates":[-1.38955079742156,54.33441075885866],"type":"Point"}
}