{
  "type": "Feature",
  "properties": {
    "iso:country":"GB",
    "wof:name":"HG4 2PL",
    "wof:placetype":"postalcode"
},
  "geometry": {"coordinates":[-1.53274836559645,54.12336962287005],"type":"Point"}
}