{
  "type": "Feature",
  "properties": {
    "iso:country": "GB",
    "wof:name": "YO8 5NA",
    "wof:placetype": "postalcode"
  },
  "geometry": {"coordinates":[-1.039994,53.808052],"type":"Point"}
}
