{
  "type": "Feature",
  "properties": {
    "iso:country":"GB",
    "wof:name":"HP11 1RY",
    "wof:placetype":"postalcode"
},
  "geometry": {"coordinates":[-0.71742135015985,51.61687326321159],"type":"Point"}
}