{
  "type": "Feature",
  "properties": {
    "iso:country":"GB",
    "wof:name":"CV37 8UH",
    "wof:placetype":"postalcode"
},
  "geometry": {"coordinates":[-1.64139395945603,52.11304756831966],"type":"Point"}
}