{
  "type": "Feature",
  "properties": {
    "iso:country": "GB",
    "wof:name": "CV37 8UH",
    "wof:placetype": "postalcode"
  },
  "geometry": {"coordinates":[-1.641394,52.113048],"type":"Point"}
}
