{
  "type": "Feature",
  "properties": {
    "date:inception_lower": "1993-01-01",
    "date:inception_upper": "1993-01-01",
    "iso:country": "GB",
    "wof:name": "CV37 8UH",
    "wof:placetype": "postalcode"
  },
  "geometry": {"coordinates":[-1.641688,52.11317],"type":"Point"}
}
