{
  "type": "Feature",
  "properties": {
    "iso:country":"GB",
    "wof:name":"KY5 8AR",
    "wof:placetype":"postalcode"
},
  "geometry": {"coordinates":[-3.323173149362,56.14982921639344],"type":"Point"}
}