{
  "type": "Feature",
  "properties": {
    "date:inception_lower":"1980-01-01",
    "date:inception_upper":"1980-01-31",
    "iso:country":"GB",
    "wof:name":"WC1E 7ER",
    "wof:placetype":"postalcode"
},
  "geometry": {"coordinates":[-0.133961,51.520878],"type":"Point"}
}