{
  "type": "Feature",
  "properties": {
    "iso:country":"GB",
    "wof:name":"PO31 8LX",
    "wof:placetype":"postalcode"
},
  "geometry": {"coordinates":[-1.33108526846894,50.7388141123971],"type":"Point"}
}