{
  "type": "Feature",
  "properties": {
    "date:inception_lower": "1980-01-01",
    "date:inception_upper": "1980-01-01",
    "iso:country": "GB",
    "wof:name": "PO31 8LX",
    "wof:placetype": "postalcode"
  },
  "geometry": {"coordinates":[-1.331075,50.738794],"type":"Point"}
}
