{
  "type": "Feature",
  "properties": {
    "iso:country":"GB",
    "wof:name":"SY4 5AL",
    "wof:placetype":"postalcode"
},
  "geometry": {"coordinates":[-2.72326165318908,52.86100553250338],"type":"Point"}
}