{
  "type": "Feature",
  "properties": {
    "iso:country":"GB",
    "wof:name":"NN8 2DB",
    "wof:placetype":"postalcode"
},
  "geometry": {"coordinates":[-0.68973971066834,52.29561941467373],"type":"Point"}
}