{
  "type": "Feature",
  "properties": {
    "date:inception_lower":"2016-08-01",
    "date:inception_upper":"2016-08-31",
    "iso:country":"GB",
    "wof:name":"SN8 1XN",
    "wof:placetype":"postalcode"
},
  "geometry": {"coordinates":[-1.733606,51.419647],"type":"Point"}
}