{
  "type": "Feature",
  "properties": {
    "date:inception_lower": "2021-12-01",
    "date:inception_upper": "2021-12-01",
    "iso:country": "GB",
    "wof:name": "RH20 2RZ",
    "wof:placetype": "postalcode"
  },
  "geometry": {"coordinates":[-0.493233,50.973806],"type":"Point"}
}
