{
  "type": "Feature",
  "properties": {
    "iso:country":"GB",
    "wof:name":"SL2 4AS",
    "wof:placetype":"postalcode"
},
  "geometry": {"coordinates":[-0.59165774482514,51.56643504407476],"type":"Point"}
}