{
  "type": "Feature",
  "properties": {
    "iso:country": "GB",
    "wof:name": "SL2 4AS",
    "wof:placetype": "postalcode"
  },
  "geometry": {"coordinates":[-0.591658,51.566435],"type":"Point"}
}
