{
  "type": "Feature",
  "properties": {
    "date:inception_lower": "1980-01-01",
    "date:inception_upper": "1980-01-01",
    "iso:country": "GB",
    "wof:name": "SL2 4AS",
    "wof:placetype": "postalcode"
  },
  "geometry": {"coordinates":[-0.591658,51.566435],"type":"Point"}
}
