{
  "type": "Feature",
  "properties": {
    "date:inception_lower":"1995-01-01",
    "date:inception_upper":"1995-01-31",
    "iso:country":"GB",
    "wof:name":"TN22 3LY",
    "wof:placetype":"postalcode"
},
  "geometry": {"coordinates":[0.05612,51.034269],"type":"Point"}
}