{
  "type": "Feature",
  "properties": {
    "iso:country": "GB",
    "wof:name": "TN22 3LY",
    "wof:placetype": "postalcode"
  },
  "geometry": {"coordinates":[0.05612,51.034269],"type":"Point"}
}
