{
  "type": "Feature",
  "properties": {
    "iso:country":"GB",
    "wof:name":"OX17 2SF",
    "wof:placetype":"postalcode"
},
  "geometry": {"coordinates":[-1.1819762904817,52.10767253326605],"type":"Point"}
}