{
  "type": "Feature",
  "properties": {
    "date:inception_lower":"1982-03-01",
    "date:inception_upper":"1982-03-31",
    "iso:country":"GB",
    "wof:name":"SG6 1ND",
    "wof:placetype":"postalcode"
},
  "geometry": {"coordinates":[-0.211954,51.980969],"type":"Point"}
}