{
  "type": "Feature",
  "properties": {
    "iso:country":"GB",
    "wof:name":"SG6 1ND",
    "wof:placetype":"postalcode"
},
  "geometry": {"coordinates":[-0.21195440221337,51.98096860959778],"type":"Point"}
}