{
  "type": "Feature",
  "properties": {
    "iso:country":"GB",
    "wof:name":"DH7 6RW",
    "wof:placetype":"postalcode"
},
  "geometry": {"coordinates":[-1.63242347961408,54.8099001960363],"type":"Point"}
}