{
  "type": "Feature",
  "properties": {
    "iso:country":"GB",
    "wof:name":"HP15 6LT",
    "wof:placetype":"postalcode"
},
  "geometry": {"coordinates":[-0.73590080684585,51.67228295431565],"type":"Point"}
}