{
  "type": "Feature",
  "properties": {
    "iso:country": "GB",
    "wof:name": "HP15 6LT",
    "wof:placetype": "postalcode"
  },
  "geometry": {"coordinates":[-0.735901,51.672283],"type":"Point"}
}
