{
  "type": "Feature",
  "properties": {
    "iso:country": "GB",
    "wof:name": "NR12 8NF",
    "wof:placetype": "postalcode"
  },
  "geometry": {"coordinates":[1.489672,52.701724],"type":"Point"}
}
