{
  "type": "Feature",
  "properties": {
    "iso:country":"GB",
    "wof:name":"FK3 8HE",
    "wof:placetype":"postalcode"
},
  "geometry": {"coordinates":[-3.74643886655505,56.02026561996696],"type":"Point"}
}