{
  "type": "Feature",
  "properties": {
    "iso:country":"GB",
    "wof:name":"L23 2RN",
    "wof:placetype":"postalcode"
},
  "geometry": {"coordinates":[-3.01230003745319,53.48856570004579],"type":"Point"}
}