{
  "type": "Feature",
  "properties": {
    "iso:country": "GB",
    "wof:name": "TD12 4JW",
    "wof:placetype": "postalcode"
  },
  "geometry": {"coordinates":[-2.334948,55.699536],"type":"Point"}
}
