{
  "type": "Feature",
  "properties": {
    "date:inception_lower": "1980-01-01",
    "date:inception_upper": "1980-01-01",
    "iso:country": "GB",
    "wof:name": "TD12 4JW",
    "wof:placetype": "postalcode"
  },
  "geometry": {"coordinates":[-2.334948,55.699536],"type":"Point"}
}
