{
  "type": "Feature",
  "properties": {
    "iso:country":"GB",
    "wof:name":"TD12 4JW",
    "wof:placetype":"postalcode"
},
  "geometry": {"coordinates":[-2.33494828697094,55.69953640517252],"type":"Point"}
}