{
  "type": "Feature",
  "properties": {
    "iso:country":"GB",
    "wof:name":"NE66 2LR",
    "wof:placetype":"postalcode"
},
  "geometry": {"coordinates":[-1.77455617743532,55.46144285061265],"type":"Point"}
}