{
  "type": "Feature",
  "properties": {
    "iso:country": "GB",
    "wof:name": "NE66 2LR",
    "wof:placetype": "postalcode"
  },
  "geometry": {"coordinates":[-1.774556,55.461443],"type":"Point"}
}
