{
  "type": "Feature",
  "properties": {
    "date:inception_lower": "2000-06-01",
    "date:inception_upper": "2000-06-01",
    "iso:country": "GB",
    "wof:name": "NR11 8LZ",
    "wof:placetype": "postalcode"
  },
  "geometry": {"coordinates":[1.440532,52.873307],"type":"Point"}
}
