{
  "type": "Feature",
  "properties": {
    "iso:country":"GB",
    "wof:name":"TQ13 9GL",
    "wof:placetype":"postalcode"
},
  "geometry": {"coordinates":[-3.67870646545902,50.59840746576849],"type":"Point"}
}