{
  "type": "Feature",
  "properties": {
    "iso:country": "GB",
    "wof:name": "TS7 0RS",
    "wof:placetype": "postalcode"
  },
  "geometry": {"coordinates":[-1.176569,54.517183],"type":"Point"}
}
