{
  "type": "Feature",
  "properties": {
    "date:inception_lower": "2017-06-01",
    "date:inception_upper": "2017-06-01",
    "iso:country": "GB",
    "wof:name": "TS7 0RS",
    "wof:placetype": "postalcode"
  },
  "geometry": {"coordinates":[-1.175381,54.517094],"type":"Point"}
}
