{
  "type": "Feature",
  "properties": {
    "iso:country":"GB",
    "wof:name":"TQ14 8QR",
    "wof:placetype":"postalcode"
},
  "geometry": {"coordinates":[-3.50150084290448,50.56025755041027],"type":"Point"}
}