{
  "type": "Feature",
  "properties": {
    "date:inception_lower": "1995-07-01",
    "date:inception_upper": "1995-07-01",
    "iso:country": "GB",
    "wof:name": "PR5 8BF",
    "wof:placetype": "postalcode"
  },
  "geometry": {"coordinates":[-2.647444,53.718435],"type":"Point"}
}
