{
  "type": "Feature",
  "properties": {
    "date:inception_lower":"1983-01-01",
    "date:inception_upper":"1983-01-31",
    "iso:country":"GB",
    "wof:name":"EX12 3DT",
    "wof:placetype":"postalcode"
},
  "geometry": {"coordinates":[-3.129244,50.693236],"type":"Point"}
}