{
  "type": "Feature",
  "properties": {
    "iso:country": "GB",
    "wof:name": "EX12 3DT",
    "wof:placetype": "postalcode"
  },
  "geometry": {"coordinates":[-3.129244,50.693236],"type":"Point"}
}
