{
  "type": "Feature",
  "properties": {
    "date:inception_lower": "1980-01-01",
    "date:inception_upper": "1980-01-01",
    "iso:country": "GB",
    "wof:name": "WV6 0RG",
    "wof:placetype": "postalcode"
  },
  "geometry": {"coordinates":[-2.149241,52.596215],"type":"Point"}
}
