{
  "type": "Feature",
  "properties": {
    "iso:country":"GB",
    "wof:name":"TF8 7HG",
    "wof:placetype":"postalcode"
},
  "geometry": {"coordinates":[-2.47431799102701,52.62709249770952],"type":"Point"}
}