{
  "type": "Feature",
  "properties": {
    "iso:country": "GB",
    "wof:name": "TF8 7HG",
    "wof:placetype": "postalcode"
  },
  "geometry": {"coordinates":[-2.474318,52.627092],"type":"Point"}
}
