{
  "type": "Feature",
  "properties": {
    "iso:country": "GB",
    "wof:name": "LE15 8BP",
    "wof:placetype": "postalcode"
  },
  "geometry": {"coordinates":[-0.705764,52.658206],"type":"Point"}
}
