{
  "type": "Feature",
  "properties": {
    "iso:country":"GB",
    "wof:name":"B91 1NR",
    "wof:placetype":"postalcode"
},
  "geometry": {"coordinates":[-1.80189089475739,52.41028596186923],"type":"Point"}
}