{
  "type": "Feature",
  "properties": {
    "date:inception_lower": "1980-01-01",
    "date:inception_upper": "1980-01-01",
    "iso:country": "GB",
    "wof:name": "B91 1NR",
    "wof:placetype": "postalcode"
  },
  "geometry": {"coordinates":[-1.801891,52.410286],"type":"Point"}
}
