{
  "type": "Feature",
  "properties": {
    "iso:country":"GB",
    "wof:name":"RG19 3TJ",
    "wof:placetype":"postalcode"
},
  "geometry": {"coordinates":[-1.28252374742856,51.40061789086849],"type":"Point"}
}