{
  "type": "Feature",
  "properties": {
    "date:inception_lower": "2002-06-01",
    "date:inception_upper": "2002-06-01",
    "iso:country": "GB",
    "wof:name": "LE1 5TN",
    "wof:placetype": "postalcode"
  },
  "geometry": {"coordinates":[-1.134815,52.630586],"type":"Point"}
}
