{
  "type": "Feature",
  "properties": {
    "iso:country":"GB",
    "wof:name":"NP19 9QE",
    "wof:placetype":"postalcode"
},
  "geometry": {"coordinates":[-2.95064800955033,51.58973263660711],"type":"Point"}
}