{
  "type": "Feature",
  "properties": {
    "iso:country": "GB",
    "wof:name": "LL15 2BD",
    "wof:placetype": "postalcode"
  },
  "geometry": {"coordinates":[-3.379754,53.094706],"type":"Point"}
}
