{
  "type": "Feature",
  "properties": {
    "iso:country":"GB",
    "wof:name":"LL15 2BD",
    "wof:placetype":"postalcode"
},
  "geometry": {"coordinates":[-3.37532803000078,53.09033693196817],"type":"Point"}
}