{
  "type": "Feature",
  "properties": {
    "iso:country":"GB",
    "wof:name":"IV2 4SS",
    "wof:placetype":"postalcode"
},
  "geometry": {"coordinates":[-4.22505087236712,57.47172486180948],"type":"Point"}
}