{
  "type": "Feature",
  "properties": {
    "iso:country": "GB",
    "wof:name": "IV2 4SS",
    "wof:placetype": "postalcode"
  },
  "geometry": {"coordinates":[-4.225051,57.471725],"type":"Point"}
}
