{
  "type": "Feature",
  "properties": {
    "iso:country":"GB",
    "wof:name":"HU16 4DJ",
    "wof:placetype":"postalcode"
},
  "geometry": {"coordinates":[-0.40964492230927,53.78182480277562],"type":"Point"}
}