{
  "type": "Feature",
  "properties": {
    "iso:country": "GB",
    "wof:name": "B75 5NB",
    "wof:placetype": "postalcode"
  },
  "geometry": {"coordinates":[-1.814825,52.589989],"type":"Point"}
}
