{
  "type": "Feature",
  "properties": {
    "date:inception_lower": "1980-01-01",
    "date:inception_upper": "1980-01-01",
    "iso:country": "GB",
    "wof:name": "B75 5NB",
    "wof:placetype": "postalcode"
  },
  "geometry": {"coordinates":[-1.814825,52.589989],"type":"Point"}
}
