{
  "type": "Feature",
  "properties": {
    "iso:country":"GB",
    "wof:name":"B75 5NB",
    "wof:placetype":"postalcode"
},
  "geometry": {"coordinates":[-1.81482502881616,52.58998880907876],"type":"Point"}
}