{
  "type": "Feature",
  "properties": {
    "iso:country":"GB",
    "wof:name":"S36 9AD",
    "wof:placetype":"postalcode"
},
  "geometry": {"coordinates":[-1.66684670470426,53.52492930702364],"type":"Point"}
}