{
  "type": "Feature",
  "properties": {
    "iso:country": "GB",
    "wof:name": "S36 9AD",
    "wof:placetype": "postalcode"
  },
  "geometry": {"coordinates":[-1.666847,53.524929],"type":"Point"}
}
