{
  "type": "Feature",
  "properties": {
    "date:inception_lower":"2008-05-01",
    "date:inception_upper":"2008-05-31",
    "iso:country":"GB",
    "wof:name":"S36 9AD",
    "wof:placetype":"postalcode"
},
  "geometry": {"coordinates":[-1.666847,53.524929],"type":"Point"}
}