{
  "type": "Feature",
  "properties": {
    "iso:country":"GB",
    "wof:name":"SL1 4JG",
    "wof:placetype":"postalcode"
},
  "geometry": {"coordinates":[-0.63928418530518,51.52681180297952],"type":"Point"}
}