{
  "type": "Feature",
  "properties": {
    "date:inception_lower":"1980-01-01",
    "date:inception_upper":"1980-01-31",
    "iso:country":"GB",
    "wof:name":"NW11 9QL",
    "wof:placetype":"postalcode"
},
  "geometry": {"coordinates":[-0.209691,51.582316],"type":"Point"}
}