{
  "type": "Feature",
  "properties": {
    "iso:country":"GB",
    "wof:name":"N13 6HX",
    "wof:placetype":"postalcode"
},
  "geometry": {"coordinates":[-0.10782151498049,51.61103161378822],"type":"Point"}
}