{
  "type": "Feature",
  "properties": {
    "date:inception_lower":"2002-06-01",
    "date:inception_upper":"2002-06-30",
    "iso:country":"GB",
    "wof:name":"LS28 6LD",
    "wof:placetype":"postalcode"
},
  "geometry": {"coordinates":[-1.652055,53.807431],"type":"Point"}
}