{
  "type": "Feature",
  "properties": {
    "date:inception_lower": "1986-07-01",
    "date:inception_upper": "1986-07-01",
    "iso:country": "GB",
    "wof:name": "BH7 7RW",
    "wof:placetype": "postalcode"
  },
  "geometry": {"coordinates":[-1.834471,50.742152],"type":"Point"}
}
