{
  "type": "Feature",
  "properties": {
    "iso:country":"GB",
    "wof:name":"BH7 7RW",
    "wof:placetype":"postalcode"
},
  "geometry": {"coordinates":[-1.83447136840935,50.74215171996568],"type":"Point"}
}