{
  "type": "Feature",
  "properties": {
    "iso:country": "GB",
    "wof:name": "BH7 7RW",
    "wof:placetype": "postalcode"
  },
  "geometry": {"coordinates":[-1.834471,50.742152],"type":"Point"}
}
