{
  "type": "Feature",
  "properties": {
    "iso:country":"GB",
    "wof:name":"DH2 2AX",
    "wof:placetype":"postalcode"
},
  "geometry": {"coordinates":[-1.5823495174107,54.85721392250796],"type":"Point"}
}