{
  "type": "Feature",
  "properties": {
    "iso:country":"GB",
    "wof:name":"SO32 1BA",
    "wof:placetype":"postalcode"
},
  "geometry": {"coordinates":[-1.21498732545005,50.95412092655495],"type":"Point"}
}