{
  "type": "Feature",
  "properties": {
    "date:inception_lower": "2000-10-01",
    "date:inception_upper": "2000-10-01",
    "iso:country": "GB",
    "wof:name": "W1W 6XD",
    "wof:placetype": "postalcode"
  },
  "geometry": {"coordinates":[-0.143316,51.520172],"type":"Point"}
}
