{
  "type": "Feature",
  "properties": {
    "iso:country":"GB",
    "wof:name":"SW6 2DJ",
    "wof:placetype":"postalcode"
},
  "geometry": {"coordinates":[-0.19263023712243,51.47928948984067],"type":"Point"}
}