{
  "type": "Feature",
  "properties": {
    "date:inception_lower":"1980-01-01",
    "date:inception_upper":"1980-01-31",
    "iso:country":"GB",
    "wof:name":"NR33 8JZ",
    "wof:placetype":"postalcode"
},
  "geometry": {"coordinates":[1.691872,52.448886],"type":"Point"}
}