{
  "type": "Feature",
  "properties": {
    "iso:country": "GB",
    "wof:name": "NR33 8JZ",
    "wof:placetype": "postalcode"
  },
  "geometry": {"coordinates":[1.691872,52.448886],"type":"Point"}
}
