{
  "type": "Feature",
  "properties": {
    "iso:country":"GB",
    "wof:name":"SA5 4NP",
    "wof:placetype":"postalcode"
},
  "geometry": {"coordinates":[-4.0011915125781,51.65381749103748],"type":"Point"}
}