{
  "type": "Feature",
  "properties": {
    "iso:country": "GB",
    "wof:name": "RH2 8NS",
    "wof:placetype": "postalcode"
  },
  "geometry": {"coordinates":[-0.269393,51.208143],"type":"Point"}
}
