{
  "type": "Feature",
  "properties": {
    "iso:country":"GB",
    "wof:name":"N9 7JD",
    "wof:placetype":"postalcode"
},
  "geometry": {"coordinates":[-0.06085396443693,51.629634838995],"type":"Point"}
}