{
  "type": "Feature",
  "properties": {
    "date:inception_lower": "1980-01-01",
    "date:inception_upper": "1980-01-01",
    "iso:country": "GB",
    "wof:name": "SM7 1DY",
    "wof:placetype": "postalcode"
  },
  "geometry": {"coordinates":[-0.219896,51.318461],"type":"Point"}
}
