{
  "type": "Feature",
  "properties": {
    "iso:country":"GB",
    "wof:name":"BN13 2DS",
    "wof:placetype":"postalcode"
},
  "geometry": {"coordinates":[-0.39464885166417,50.83235057051964],"type":"Point"}
}