{
  "type": "Feature",
  "properties": {
    "iso:country":"GB",
    "wof:name":"SO31 5EP",
    "wof:placetype":"postalcode"
},
  "geometry": {"coordinates":[-1.35210396310524,50.87722170420435],"type":"Point"}
}