{
  "type": "Feature",
  "properties": {
    "iso:country":"GB",
    "wof:name":"B97 6SS",
    "wof:placetype":"postalcode"
},
  "geometry": {"coordinates":[-1.96310708271351,52.31387374200144],"type":"Point"}
}