{
  "type": "Feature",
  "properties": {
    "date:inception_lower": "1997-12-01",
    "date:inception_upper": "1997-12-01",
    "iso:country": "GB",
    "wof:name": "B97 6SS",
    "wof:placetype": "postalcode"
  },
  "geometry": {"coordinates":[-1.963107,52.313874],"type":"Point"}
}
