{
  "type": "Feature",
  "properties": {
    "iso:country":"GB",
    "wof:name":"S26 6NU",
    "wof:placetype":"postalcode"
},
  "geometry": {"coordinates":[-1.25395232249564,53.3389507273538],"type":"Point"}
}