{
  "type": "Feature",
  "properties": {
    "iso:country": "GB",
    "wof:name": "SW8 3TX",
    "wof:placetype": "postalcode"
  },
  "geometry": {"coordinates":[-0.146341,51.469421],"type":"Point"}
}
