{
  "type": "Feature",
  "properties": {
    "iso:country":"GB",
    "wof:name":"CH62 7HZ",
    "wof:placetype":"postalcode"
},
  "geometry": {"coordinates":[-2.97614041596184,53.32817164709301],"type":"Point"}
}