{
  "type": "Feature",
  "properties": {
    "date:inception_lower": "2000-12-01",
    "date:inception_upper": "2000-12-01",
    "iso:country": "GB",
    "wof:name": "M8 8DE",
    "wof:placetype": "postalcode"
  },
  "geometry": {"coordinates":[-2.250275,53.498533],"type":"Point"}
}
