{
  "type": "Feature",
  "properties": {
    "iso:country":"GB",
    "wof:name":"M8 8DE",
    "wof:placetype":"postalcode"
},
  "geometry": {"coordinates":[-2.25027536726669,53.49853350089798],"type":"Point"}
}