{
  "type": "Feature",
  "properties": {
    "iso:country": "GB",
    "wof:name": "M8 8DE",
    "wof:placetype": "postalcode"
  },
  "geometry": {"coordinates":[-2.250275,53.498533],"type":"Point"}
}
