{
  "type": "Feature",
  "properties": {
    "iso:country":"GB",
    "wof:name":"SL6 6QH",
    "wof:placetype":"postalcode"
},
  "geometry": {"coordinates":[-0.76456470545134,51.52962754263774],"type":"Point"}
}