{
  "type": "Feature",
  "properties": {
    "date:inception_lower": "1980-01-01",
    "date:inception_upper": "1980-01-01",
    "iso:country": "GB",
    "wof:name": "KY3 9RY",
    "wof:placetype": "postalcode"
  },
  "geometry": {"coordinates":[-3.178007,56.062929],"type":"Point"}
}
