{
  "type": "Feature",
  "properties": {
    "iso:country": "GB",
    "wof:name": "BN12 6HL",
    "wof:placetype": "postalcode"
  },
  "geometry": {"coordinates":[-0.422324,50.820623],"type":"Point"}
}
