{
  "type": "Feature",
  "properties": {
    "iso:country":"GB",
    "wof:name":"EX13 7UG",
    "wof:placetype":"postalcode"
},
  "geometry": {"coordinates":[-3.03910368894959,50.77856349988872],"type":"Point"}
}