{
  "type": "Feature",
  "properties": {
    "date:inception_lower":"1990-02-01",
    "date:inception_upper":"1990-02-28",
    "iso:country":"GB",
    "wof:name":"EX13 7UG",
    "wof:placetype":"postalcode"
},
  "geometry": {"coordinates":[-3.039104,50.778563],"type":"Point"}
}