{
  "type": "Feature",
  "properties": {
    "iso:country":"GB",
    "wof:name":"RM17 6PR",
    "wof:placetype":"postalcode"
},
  "geometry": {"coordinates":[0.32907165857905,51.47389923606485],"type":"Point"}
}