{
  "type": "Feature",
  "properties": {
    "iso:country":"GB",
    "wof:name":"ST5 6LJ",
    "wof:placetype":"postalcode"
},
  "geometry": {"coordinates":[-2.27399990631552,53.01533324935472],"type":"Point"}
}