{
  "type": "Feature",
  "properties": {
    "date:inception_lower": "2008-06-01",
    "date:inception_upper": "2008-06-01",
    "iso:country": "GB",
    "wof:name": "CT12 5FD",
    "wof:placetype": "postalcode"
  },
  "geometry": {"coordinates":[1.320282,51.350348],"type":"Point"}
}
