{
  "type": "Feature",
  "properties": {
    "iso:country":"GB",
    "wof:name":"CT12 5FD",
    "wof:placetype":"postalcode"
},
  "geometry": {"coordinates":[1.32025477501128,51.35034161208218],"type":"Point"}
}