{
  "type": "Feature",
  "properties": {
    "iso:country":"GB",
    "wof:name":"BS48 1QN",
    "wof:placetype":"postalcode"
},
  "geometry": {"coordinates":[-2.74756056848011,51.4337679921505],"type":"Point"}
}