{
  "type": "Feature",
  "properties": {
    "iso:country": "GB",
    "wof:name": "WR11 1AT",
    "wof:placetype": "postalcode"
  },
  "geometry": {"coordinates":[-1.937004,52.090146],"type":"Point"}
}
