{
  "type": "Feature",
  "properties": {
    "iso:country":"GB",
    "wof:name":"WR11 1AT",
    "wof:placetype":"postalcode"
},
  "geometry": {"coordinates":[-1.93700417951129,52.09014602385282],"type":"Point"}
}