{
  "type": "Feature",
  "properties": {
    "iso:country":"GB",
    "wof:name":"TS5 4BU",
    "wof:placetype":"postalcode"
},
  "geometry": {"coordinates":[-1.25964689908139,54.56854688169183],"type":"Point"}
}