{
  "type": "Feature",
  "properties": {
    "iso:country": "GB",
    "wof:name": "SG3 6EA",
    "wof:placetype": "postalcode"
  },
  "geometry": {"coordinates":[-0.191452,51.859875],"type":"Point"}
}
