{
  "type": "Feature",
  "properties": {
    "iso:country":"GB",
    "wof:name":"SG3 6EA",
    "wof:placetype":"postalcode"
},
  "geometry": {"coordinates":[-0.19143259104317,51.85986723852502],"type":"Point"}
}