{
  "type": "Feature",
  "properties": {
    "date:inception_lower":"1990-02-01",
    "date:inception_upper":"1990-02-28",
    "iso:country":"GB",
    "wof:name":"SG3 6EA",
    "wof:placetype":"postalcode"
},
  "geometry": {"coordinates":[-0.191452,51.859875],"type":"Point"}
}