{
  "type": "Feature",
  "properties": {
    "date:inception_lower": "1996-12-01",
    "date:inception_upper": "1996-12-01",
    "iso:country": "GB",
    "wof:name": "TN13 2QY",
    "wof:placetype": "postalcode"
  },
  "geometry": {"coordinates":[0.163141,51.289016],"type":"Point"}
}
