{
  "type": "Feature",
  "properties": {
    "date:inception_lower": "2008-09-01",
    "date:inception_upper": "2008-09-01",
    "iso:country": "GB",
    "wof:name": "TA21 0BF",
    "wof:placetype": "postalcode"
  },
  "geometry": {"coordinates":[-3.268236,50.99753],"type":"Point"}
}
