{
  "type": "Feature",
  "properties": {
    "iso:country":"GB",
    "wof:name":"IV2 3SS",
    "wof:placetype":"postalcode"
},
  "geometry": {"coordinates":[-4.19994280575697,57.46521089710984],"type":"Point"}
}