{
  "type": "Feature",
  "properties": {
    "iso:country": "GB",
    "wof:name": "IV2 3SS",
    "wof:placetype": "postalcode"
  },
  "geometry": {"coordinates":[-4.199943,57.465211],"type":"Point"}
}
