{
  "type": "Feature",
  "properties": {
    "iso:country":"GB",
    "wof:name":"NW7 4PE",
    "wof:placetype":"postalcode"
},
  "geometry": {"coordinates":[-0.24154270136509,51.62650938568716],"type":"Point"}
}