{
  "type": "Feature",
  "properties": {
    "iso:country":"GB",
    "wof:name":"LS17 9EN",
    "wof:placetype":"postalcode"
},
  "geometry": {"coordinates":[-1.45110196745217,53.89500562077387],"type":"Point"}
}