{
  "type": "Feature",
  "properties": {
    "date:inception_lower":"1980-01-01",
    "date:inception_upper":"1980-01-31",
    "iso:country":"GB",
    "wof:name":"LS17 9EN",
    "wof:placetype":"postalcode"
},
  "geometry": {"coordinates":[-1.451102,53.895006],"type":"Point"}
}