{
  "type": "Feature",
  "properties": {
    "iso:country":"GB",
    "wof:name":"HP5 2UT",
    "wof:placetype":"postalcode"
},
  "geometry": {"coordinates":[-0.64758066852492,51.74228000584556],"type":"Point"}
}