{
  "type": "Feature",
  "properties": {
    "iso:country":"GB",
    "wof:name":"BS7 0QQ",
    "wof:placetype":"postalcode"
},
  "geometry": {"coordinates":[-2.56805694638114,51.50321076585843],"type":"Point"}
}