{
  "type": "Feature",
  "properties": {
    "iso:country":"GB",
    "wof:name":"TF2 6EB",
    "wof:placetype":"postalcode"
},
  "geometry": {"coordinates":[-2.44773952156823,52.69641707178972],"type":"Point"}
}