{
  "type": "Feature",
  "properties": {
    "iso:country": "GB",
    "wof:name": "TF2 6EB",
    "wof:placetype": "postalcode"
  },
  "geometry": {"coordinates":[-2.447739,52.696417],"type":"Point"}
}
