{
  "type": "Feature",
  "properties": {
    "iso:country":"GB",
    "wof:name":"PO22 8HP",
    "wof:placetype":"postalcode"
},
  "geometry": {"coordinates":[-0.64932077025511,50.79303923165484],"type":"Point"}
}