{
  "type": "Feature",
  "properties": {
    "iso:country": "GB",
    "wof:name": "PE33 9NH",
    "wof:placetype": "postalcode"
  },
  "geometry": {"coordinates":[0.536504,52.65441],"type":"Point"}
}
