{
  "type": "Feature",
  "properties": {
    "iso:country":"GB",
    "wof:name":"PE33 9NH",
    "wof:placetype":"postalcode"
},
  "geometry": {"coordinates":[0.53651529682283,52.65440583019019],"type":"Point"}
}