{
  "type": "Feature",
  "properties": {
    "date:inception_lower": "1988-03-01",
    "date:inception_upper": "1988-03-01",
    "iso:country": "GB",
    "wof:name": "CV36 4QT",
    "wof:placetype": "postalcode"
  },
  "geometry": {"coordinates":[-1.622734,52.062762],"type":"Point"}
}
