{
  "type": "Feature",
  "properties": {
    "iso:country": "GB",
    "wof:name": "CV36 4QT",
    "wof:placetype": "postalcode"
  },
  "geometry": {"coordinates":[-1.622557,52.062767],"type":"Point"}
}
