{
  "type": "Feature",
  "properties": {
    "iso:country":"GB",
    "wof:name":"CV36 4QT",
    "wof:placetype":"postalcode"
},
  "geometry": {"coordinates":[-1.62255678366113,52.06276729180234],"type":"Point"}
}