{
  "type": "Feature",
  "properties": {
    "date:inception_lower":"1988-03-01",
    "date:inception_upper":"1988-03-31",
    "iso:country":"GB",
    "wof:name":"CV36 4QT",
    "wof:placetype":"postalcode"
},
  "geometry": {"coordinates":[-1.622557,52.062767],"type":"Point"}
}