{
  "type": "Feature",
  "properties": {
    "iso:country":"GB",
    "wof:name":"S72 8LF",
    "wof:placetype":"postalcode"
},
  "geometry": {"coordinates":[-1.41405518762218,53.57280165586995],"type":"Point"}
}