{
  "type": "Feature",
  "properties": {
    "date:inception_lower":"1991-09-01",
    "date:inception_upper":"1991-09-30",
    "iso:country":"GB",
    "wof:name":"IP7 7RR",
    "wof:placetype":"postalcode"
},
  "geometry": {"coordinates":[0.962708,52.120857],"type":"Point"}
}