{
  "type": "Feature",
  "properties": {
    "iso:country":"GB",
    "wof:name":"IP7 7RR",
    "wof:placetype":"postalcode"
},
  "geometry": {"coordinates":[0.96270779659743,52.12085654355459],"type":"Point"}
}