{
  "type": "Feature",
  "properties": {
    "iso:country":"GB",
    "wof:name":"KA6 6PQ",
    "wof:placetype":"postalcode"
},
  "geometry": {"coordinates":[-4.46255556638278,55.44884584266582],"type":"Point"}
}