{
  "type": "Feature",
  "properties": {
    "iso:country":"GB",
    "wof:name":"E14 0NN",
    "wof:placetype":"postalcode"
},
  "geometry": {"coordinates":[-0.00347136139406,51.51250666318822],"type":"Point"}
}