{
  "type": "Feature",
  "properties": {
    "iso:country":"GB",
    "wof:name":"NG5 9PD",
    "wof:placetype":"postalcode"
},
  "geometry": {"coordinates":[-1.16657710921718,53.01290199996879],"type":"Point"}
}