{
  "type": "Feature",
  "properties": {
    "iso:country":"GB",
    "wof:name":"AB12 4UP",
    "wof:placetype":"postalcode"
},
  "geometry": {"coordinates":[-2.14508068707174,57.05361096524894],"type":"Point"}
}