{
  "type": "Feature",
  "properties": {
    "date:inception_lower": "1983-03-01",
    "date:inception_upper": "1983-03-01",
    "iso:country": "GB",
    "wof:name": "KT12 3PA",
    "wof:placetype": "postalcode"
  },
  "geometry": {"coordinates":[-0.390354,51.377032],"type":"Point"}
}
