{
  "type": "Feature",
  "properties": {
    "date:inception_lower": "1995-07-01",
    "date:inception_upper": "1995-07-01",
    "iso:country": "GB",
    "wof:name": "GU9 7XQ",
    "wof:placetype": "postalcode"
  },
  "geometry": {"coordinates":[-0.804649,51.211525],"type":"Point"}
}
