{
  "type": "Feature",
  "properties": {
    "iso:country": "GB",
    "wof:name": "GU9 7XQ",
    "wof:placetype": "postalcode"
  },
  "geometry": {"coordinates":[-0.804649,51.211525],"type":"Point"}
}
