{
  "type": "Feature",
  "properties": {
    "iso:country":"GB",
    "wof:name":"HD3 4BX",
    "wof:placetype":"postalcode"
},
  "geometry": {"coordinates":[-1.82367000914296,53.65338204089441],"type":"Point"}
}