{
  "type": "Feature",
  "properties": {
    "iso:country":"GB",
    "wof:name":"BS21 6NZ",
    "wof:placetype":"postalcode"
},
  "geometry": {"coordinates":[-2.85801839990555,51.43249879057424],"type":"Point"}
}