{
  "type": "Feature",
  "properties": {
    "iso:country": "GB",
    "wof:name": "BS21 6NZ",
    "wof:placetype": "postalcode"
  },
  "geometry": {"coordinates":[-2.858018,51.432499],"type":"Point"}
}
