{
  "type": "Feature",
  "properties": {
    "date:inception_lower": "2024-10-01",
    "date:inception_upper": "2024-10-01",
    "iso:country": "GB",
    "wof:name": "CA14 9DD",
    "wof:placetype": "postalcode"
  },
  "geometry": {"coordinates":[-3.561765,54.643334],"type":"Point"}
}
