{
  "type": "Feature",
  "properties": {
    "iso:country":"GB",
    "wof:name":"BH23 7LD",
    "wof:placetype":"postalcode"
},
  "geometry": {"coordinates":[-1.77401712097991,50.75287752087976],"type":"Point"}
}