{
  "type": "Feature",
  "properties": {
    "date:inception_lower": "2002-12-01",
    "date:inception_upper": "2002-12-01",
    "iso:country": "GB",
    "wof:name": "CW5 7GJ",
    "wof:placetype": "postalcode"
  },
  "geometry": {"coordinates":[-2.511323,53.060178],"type":"Point"}
}
