{
  "type": "Feature",
  "properties": {
    "iso:country":"GB",
    "wof:name":"S63 0BJ",
    "wof:placetype":"postalcode"
},
  "geometry": {"coordinates":[-1.295057583821,53.54370224934749],"type":"Point"}
}