{
  "type": "Feature",
  "properties": {
    "iso:country":"GB",
    "wof:name":"HR6 9TA",
    "wof:placetype":"postalcode"
},
  "geometry": {"coordinates":[-2.87610005209453,52.29635171999748],"type":"Point"}
}