{
  "type": "Feature",
  "properties": {
    "date:inception_lower":"1980-01-01",
    "date:inception_upper":"1980-01-31",
    "iso:country":"GB",
    "wof:name":"HR6 9TA",
    "wof:placetype":"postalcode"
},
  "geometry": {"coordinates":[-2.8761,52.296352],"type":"Point"}
}