{
  "type": "Feature",
  "properties": {
    "iso:country":"GB",
    "wof:name":"IP23 7HF",
    "wof:placetype":"postalcode"
},
  "geometry": {"coordinates":[1.14672098845826,52.32258187524588],"type":"Point"}
}