{
  "type": "Feature",
  "properties": {
    "date:inception_lower": "1992-08-01",
    "date:inception_upper": "1992-08-01",
    "iso:country": "GB",
    "wof:name": "IP23 7HF",
    "wof:placetype": "postalcode"
  },
  "geometry": {"coordinates":[1.146794,52.3226],"type":"Point"}
}
