{
  "type": "Feature",
  "properties": {
    "iso:country":"GB",
    "wof:name":"M13 9BB",
    "wof:placetype":"postalcode"
},
  "geometry": {"coordinates":[-2.21515411637762,53.4633582273416],"type":"Point"}
}