{
  "type": "Feature",
  "properties": {
    "iso:country":"GB",
    "wof:name":"NR3 3XP",
    "wof:placetype":"postalcode"
},
  "geometry": {"coordinates":[1.2905157531312,52.63125765510932],"type":"Point"}
}