{
  "type": "Feature",
  "properties": {
    "iso:country":"GB",
    "wof:name":"SN8 3RE",
    "wof:placetype":"postalcode"
},
  "geometry": {"coordinates":[-1.52735313206699,51.36501236007689],"type":"Point"}
}