{
  "type": "Feature",
  "properties": {
    "iso:country": "GB",
    "wof:name": "NN3 6QU",
    "wof:placetype": "postalcode"
  },
  "geometry": {"coordinates":[-0.864749,52.265883],"type":"Point"}
}
