{
  "type": "Feature",
  "properties": {
    "iso:country":"GB",
    "wof:name":"SP8 4XQ",
    "wof:placetype":"postalcode"
},
  "geometry": {"coordinates":[-2.28091604474985,51.04689885860009],"type":"Point"}
}