{
  "type": "Feature",
  "properties": {
    "date:inception_lower": "1999-06-01",
    "date:inception_upper": "1999-06-01",
    "iso:country": "GB",
    "wof:name": "SP8 4XQ",
    "wof:placetype": "postalcode"
  },
  "geometry": {"coordinates":[-2.280916,51.046899],"type":"Point"}
}
