{
  "type": "Feature",
  "properties": {
    "date:inception_lower":"1980-01-01",
    "date:inception_upper":"1980-01-31",
    "iso:country":"GB",
    "wof:name":"N4 1RU",
    "wof:placetype":"postalcode"
},
  "geometry": {"coordinates":[-0.103925,51.576986],"type":"Point"}
}