{
  "type": "Feature",
  "properties": {
    "iso:country":"GB",
    "wof:name":"SK15 2RP",
    "wof:placetype":"postalcode"
},
  "geometry": {"coordinates":[-2.03923800530168,53.47387359991252],"type":"Point"}
}