{
  "type": "Feature",
  "properties": {
    "iso:country":"GB",
    "wof:name":"UB3 4NT",
    "wof:placetype":"postalcode"
},
  "geometry": {"coordinates":[-0.42255084324217,51.50034044852037],"type":"Point"}
}