{
  "type": "Feature",
  "properties": {
    "date:inception_lower": "1980-01-01",
    "date:inception_upper": "1980-01-01",
    "iso:country": "GB",
    "wof:name": "UB3 4NT",
    "wof:placetype": "postalcode"
  },
  "geometry": {"coordinates":[-0.422551,51.50034],"type":"Point"}
}
