{
  "type": "Feature",
  "properties": {
    "iso:country":"GB",
    "wof:name":"NG12 3DF",
    "wof:placetype":"postalcode"
},
  "geometry": {"coordinates":[-0.98574703673956,52.91738549930911],"type":"Point"}
}