{
  "type": "Feature",
  "properties": {
    "iso:country":"GB",
    "wof:name":"RH9 8DU",
    "wof:placetype":"postalcode"
},
  "geometry": {"coordinates":[-0.0663091233529,51.24720252179443],"type":"Point"}
}