{
  "type": "Feature",
  "properties": {
    "iso:country": "GB",
    "wof:name": "BS31 1HE",
    "wof:placetype": "postalcode"
  },
  "geometry": {"coordinates":[-2.496687,51.41343],"type":"Point"}
}
