{
  "type": "Feature",
  "properties": {
    "iso:country":"GB",
    "wof:name":"BS31 1HE",
    "wof:placetype":"postalcode"
},
  "geometry": {"coordinates":[-2.49668691113253,51.41342998809848],"type":"Point"}
}