{
  "type": "Feature",
  "properties": {
    "iso:country":"GB",
    "wof:name":"DG3 4AP",
    "wof:placetype":"postalcode"
},
  "geometry": {"coordinates":[-3.8444953487498,55.28434010557856],"type":"Point"}
}