{
  "type": "Feature",
  "properties": {
    "iso:country": "GB",
    "wof:name": "NR1 4DA",
    "wof:placetype": "postalcode"
  },
  "geometry": {"coordinates":[1.311145,52.627076],"type":"Point"}
}
