{
  "type": "Feature",
  "properties": {
    "iso:country":"GB",
    "wof:name":"NG3 4FP",
    "wof:placetype":"postalcode"
},
  "geometry": {"coordinates":[-1.14793219544079,52.96436170740976],"type":"Point"}
}