{
  "type": "Feature",
  "properties": {
    "iso:country":"GB",
    "wof:name":"BA2 7PJ",
    "wof:placetype":"postalcode"
},
  "geometry": {"coordinates":[-2.3231403820574,51.37993194093196],"type":"Point"}
}