{
  "type": "Feature",
  "properties": {
    "date:inception_lower":"2014-10-01",
    "date:inception_upper":"2014-10-31",
    "iso:country":"GB",
    "wof:name":"BA2 7PJ",
    "wof:placetype":"postalcode"
},
  "geometry": {"coordinates":[-2.32314,51.379932],"type":"Point"}
}