{
  "type": "Feature",
  "properties": {
    "date:inception_lower": "1980-01-01",
    "date:inception_upper": "1980-01-01",
    "iso:country": "GB",
    "wof:name": "FK2 9JT",
    "wof:placetype": "postalcode"
  },
  "geometry": {"coordinates":[-3.751871,55.992466],"type":"Point"}
}
