{
  "type": "Feature",
  "properties": {
    "iso:country": "GB",
    "wof:name": "FK2 9JT",
    "wof:placetype": "postalcode"
  },
  "geometry": {"coordinates":[-3.751871,55.992466],"type":"Point"}
}
