{
  "type": "Feature",
  "properties": {
    "iso:country":"GB",
    "wof:name":"FK2 9JT",
    "wof:placetype":"postalcode"
},
  "geometry": {"coordinates":[-3.75187062098383,55.9924660168849],"type":"Point"}
}