{
  "type": "Feature",
  "properties": {
    "iso:country":"GB",
    "wof:name":"WR11 7SB",
    "wof:placetype":"postalcode"
},
  "geometry": {"coordinates":[-1.90201394809496,52.07237482363855],"type":"Point"}
}