{
  "type": "Feature",
  "properties": {
    "iso:country":"GB",
    "wof:name":"NG9 8PG",
    "wof:placetype":"postalcode"
},
  "geometry": {"coordinates":[-1.26673832940765,52.93644141181985],"type":"Point"}
}