{
  "type": "Feature",
  "properties": {
    "date:inception_lower": "2010-10-01",
    "date:inception_upper": "2010-10-01",
    "iso:country": "GB",
    "wof:name": "TQ2 6FD",
    "wof:placetype": "postalcode"
  },
  "geometry": {"coordinates":[-3.543512,50.461048],"type":"Point"}
}
