{
  "type": "Feature",
  "properties": {
    "iso:country":"GB",
    "wof:name":"TQ2 6FD",
    "wof:placetype":"postalcode"
},
  "geometry": {"coordinates":[-3.54351199011975,50.46104815385947],"type":"Point"}
}