{
  "type": "Feature",
  "properties": {
    "date:inception_lower":"1980-01-01",
    "date:inception_upper":"1980-01-31",
    "iso:country":"GB",
    "wof:name":"SY7 8QJ",
    "wof:placetype":"postalcode"
},
  "geometry": {"coordinates":[-3.095568,52.436899],"type":"Point"}
}