{
  "type": "Feature",
  "properties": {
    "iso:country": "GB",
    "wof:name": "SY7 8QJ",
    "wof:placetype": "postalcode"
  },
  "geometry": {"coordinates":[-3.095568,52.436899],"type":"Point"}
}
