{
  "type": "Feature",
  "properties": {
    "date:inception_lower": "2018-04-01",
    "date:inception_upper": "2018-04-01",
    "iso:country": "GB",
    "wof:name": "EX15 2FJ",
    "wof:placetype": "postalcode"
  },
  "geometry": {"coordinates":[-3.372772,50.886178],"type":"Point"}
}
