{
  "type": "Feature",
  "properties": {
    "iso:country":"GB",
    "wof:name":"M19 1SY",
    "wof:placetype":"postalcode"
},
  "geometry": {"coordinates":[-2.21604078554993,53.41553772236153],"type":"Point"}
}