{
  "type": "Feature",
  "properties": {
    "date:inception_lower": "2017-09-01",
    "date:inception_upper": "2017-09-01",
    "iso:country": "GB",
    "wof:name": "TR1 2FG",
    "wof:placetype": "postalcode"
  },
  "geometry": {"coordinates":[-5.054323,50.261245],"type":"Point"}
}
