{
  "type": "Feature",
  "properties": {
    "iso:country":"GB",
    "wof:name":"TR1 2FG",
    "wof:placetype":"postalcode"
},
  "geometry": {"coordinates":[-5.05427602934564,50.26125620923214],"type":"Point"}
}