{
  "type": "Feature",
  "properties": {
    "iso:country": "GB",
    "wof:name": "TR1 2FG",
    "wof:placetype": "postalcode"
  },
  "geometry": {"coordinates":[-5.054323,50.261245],"type":"Point"}
}
