{
  "type": "Feature",
  "properties": {
    "iso:country":"GB",
    "wof:name":"EH52 6WD",
    "wof:placetype":"postalcode"
},
  "geometry": {"coordinates":[-3.47674702840896,55.95960453288392],"type":"Point"}
}