{
  "type": "Feature",
  "properties": {
    "iso:country": "GB",
    "wof:name": "EH52 6WD",
    "wof:placetype": "postalcode"
  },
  "geometry": {"coordinates":[-3.476747,55.959605],"type":"Point"}
}
