{
  "type": "Feature",
  "properties": {
    "date:inception_lower":"2013-10-01",
    "date:inception_upper":"2013-10-31",
    "iso:country":"GB",
    "wof:name":"EH52 6WD",
    "wof:placetype":"postalcode"
},
  "geometry": {"coordinates":[-3.476747,55.959605],"type":"Point"}
}