{
  "type": "Feature",
  "properties": {
    "iso:country":"GB",
    "wof:name":"IV14 9DG",
    "wof:placetype":"postalcode"
},
  "geometry": {"coordinates":[-4.53759421117772,57.58928122303465],"type":"Point"}
}