{
  "type": "Feature",
  "properties": {
    "date:inception_lower":"1980-01-01",
    "date:inception_upper":"1980-01-31",
    "iso:country":"GB",
    "wof:name":"IV14 9DG",
    "wof:placetype":"postalcode"
},
  "geometry": {"coordinates":[-4.537594,57.589281],"type":"Point"}
}