{
  "type": "Feature",
  "properties": {
    "iso:country":"GB",
    "wof:name":"WS15 2XZ",
    "wof:placetype":"postalcode"
},
  "geometry": {"coordinates":[-1.95650199822889,52.76830919413568],"type":"Point"}
}