{
  "type": "Feature",
  "properties": {
    "iso:country": "GB",
    "wof:name": "EX19 8JL",
    "wof:placetype": "postalcode"
  },
  "geometry": {"coordinates":[-3.940448,50.854563],"type":"Point"}
}
