{
  "type": "Feature",
  "properties": {
    "iso:country":"GB",
    "wof:name":"EX19 8JL",
    "wof:placetype":"postalcode"
},
  "geometry": {"coordinates":[-3.94044754993841,50.85456311400458],"type":"Point"}
}