{
  "type": "Feature",
  "properties": {
    "iso:country":"GB",
    "wof:name":"SA4 0TS",
    "wof:placetype":"postalcode"
},
  "geometry": {"coordinates":[-4.05422661909386,51.72297996982048],"type":"Point"}
}