{
  "type": "Feature",
  "properties": {
    "iso:country": "GB",
    "wof:name": "SA4 0TS",
    "wof:placetype": "postalcode"
  },
  "geometry": {"coordinates":[-4.054227,51.72298],"type":"Point"}
}
