{
  "type": "Feature",
  "properties": {
    "iso:country":"GB",
    "wof:name":"LS26 8UB",
    "wof:placetype":"postalcode"
},
  "geometry": {"coordinates":[-1.41835946962008,53.76738308117274],"type":"Point"}
}