{
  "type": "Feature",
  "properties": {
    "date:inception_lower": "1980-01-01",
    "date:inception_upper": "1980-01-01",
    "iso:country": "GB",
    "wof:name": "LS26 8UB",
    "wof:placetype": "postalcode"
  },
  "geometry": {"coordinates":[-1.418359,53.767383],"type":"Point"}
}
