{
  "type": "Feature",
  "properties": {
    "date:inception_lower": "1980-01-01",
    "date:inception_upper": "1980-01-01",
    "iso:country": "GB",
    "wof:name": "LA22 0NG",
    "wof:placetype": "postalcode"
  },
  "geometry": {"coordinates":[-3.001845,54.402776],"type":"Point"}
}
