{
  "type": "Feature",
  "properties": {
    "date:inception_lower": "2009-11-01",
    "date:inception_upper": "2009-11-01",
    "iso:country": "GB",
    "wof:name": "BH8 9AS",
    "wof:placetype": "postalcode"
  },
  "geometry": {"coordinates":[-1.860663,50.741835],"type":"Point"}
}
