{
  "type": "Feature",
  "properties": {
    "iso:country":"GB",
    "wof:name":"BH8 9AS",
    "wof:placetype":"postalcode"
},
  "geometry": {"coordinates":[-1.86066285084784,50.74183518217855],"type":"Point"}
}