{
  "type": "Feature",
  "properties": {
    "iso:country":"GB",
    "wof:name":"SW18 4LR",
    "wof:placetype":"postalcode"
},
  "geometry": {"coordinates":[-0.19179541694225,51.44722728454548],"type":"Point"}
}