{
  "type": "Feature",
  "properties": {
    "iso:country": "GB",
    "wof:name": "ME8 7NS",
    "wof:placetype": "postalcode"
  },
  "geometry": {"coordinates":[0.610447,51.370605],"type":"Point"}
}
