{
  "type": "Feature",
  "properties": {
    "iso:country":"GB",
    "wof:name":"ME8 7NS",
    "wof:placetype":"postalcode"
},
  "geometry": {"coordinates":[0.61044673474414,51.37060508932691],"type":"Point"}
}