{
  "type": "Feature",
  "properties": {
    "date:inception_lower": "1998-06-01",
    "date:inception_upper": "1998-06-01",
    "iso:country": "GB",
    "wof:name": "YO25 4EE",
    "wof:placetype": "postalcode"
  },
  "geometry": {"coordinates":[-0.385653,54.097794],"type":"Point"}
}
