{
  "type": "Feature",
  "properties": {
    "date:inception_lower": "2003-06-01",
    "date:inception_upper": "2003-06-01",
    "iso:country": "GB",
    "wof:name": "PO13 8FL",
    "wof:placetype": "postalcode"
  },
  "geometry": {"coordinates":[-1.190004,50.802218],"type":"Point"}
}
