{
  "type": "Feature",
  "properties": {
    "iso:country": "GB",
    "wof:name": "IP3 8LX",
    "wof:placetype": "postalcode"
  },
  "geometry": {"coordinates":[1.196947,52.052081],"type":"Point"}
}
