{
  "type": "Feature",
  "properties": {
    "iso:country":"GB",
    "wof:name":"IP3 8LX",
    "wof:placetype":"postalcode"
},
  "geometry": {"coordinates":[1.19694667036031,52.05208133681059],"type":"Point"}
}