{
  "type": "Feature",
  "properties": {
    "date:inception_lower":"1980-01-01",
    "date:inception_upper":"1980-01-31",
    "iso:country":"GB",
    "wof:name":"G13 4JA",
    "wof:placetype":"postalcode"
},
  "geometry": {"coordinates":[-4.380803,55.895765],"type":"Point"}
}