{
  "type": "Feature",
  "properties": {
    "iso:country":"GB",
    "wof:name":"G13 4JA",
    "wof:placetype":"postalcode"
},
  "geometry": {"coordinates":[-4.38080343791851,55.89576502031939],"type":"Point"}
}