{
  "type": "Feature",
  "properties": {
    "date:inception_lower": "2000-06-01",
    "date:inception_upper": "2000-06-01",
    "iso:country": "GB",
    "wof:name": "SN26 7AS",
    "wof:placetype": "postalcode"
  },
  "geometry": {"coordinates":[-1.788736,51.613589],"type":"Point"}
}
