{
  "type": "Feature",
  "properties": {
    "iso:country":"GB",
    "wof:name":"B97 4BB",
    "wof:placetype":"postalcode"
},
  "geometry": {"coordinates":[-1.94367548584434,52.31014416940423],"type":"Point"}
}