{
  "type": "Feature",
  "properties": {
    "iso:country":"GB",
    "wof:name":"M33 7XN",
    "wof:placetype":"postalcode"
},
  "geometry": {"coordinates":[-2.32362416209619,53.42472343352341],"type":"Point"}
}