{
  "type": "Feature",
  "properties": {
    "iso:country":"GB",
    "wof:name":"CR0 5BD",
    "wof:placetype":"postalcode"
},
  "geometry": {"coordinates":[-0.04765380154056,51.35570695596829],"type":"Point"}
}