{
  "type": "Feature",
  "properties": {
    "iso:country":"GB",
    "wof:name":"TN33 0PE",
    "wof:placetype":"postalcode"
},
  "geometry": {"coordinates":[0.53565751317111,50.9465777142244],"type":"Point"}
}