{
  "type": "Feature",
  "properties": {
    "iso:country":"GB",
    "wof:name":"OL5 0RQ",
    "wof:placetype":"postalcode"
},
  "geometry": {"coordinates":[-2.0365705525495,53.52513533515549],"type":"Point"}
}