{
  "type": "Feature",
  "properties": {
    "date:inception_lower":"1980-01-01",
    "date:inception_upper":"1980-01-31",
    "iso:country":"GB",
    "wof:name":"OL5 0RQ",
    "wof:placetype":"postalcode"
},
  "geometry": {"coordinates":[-2.036571,53.525135],"type":"Point"}
}