{
  "type": "Feature",
  "properties": {
    "date:inception_lower": "2021-05-01",
    "date:inception_upper": "2021-05-01",
    "iso:country": "GB",
    "wof:name": "EN7 5FD",
    "wof:placetype": "postalcode"
  },
  "geometry": {"coordinates":[-0.096228,51.710708],"type":"Point"}
}
