{
  "type": "Feature",
  "properties": {
    "iso:country": "GB",
    "wof:name": "PR26 6QA",
    "wof:placetype": "postalcode"
  },
  "geometry": {"coordinates":[-2.714172,53.700996],"type":"Point"}
}
