{
  "type": "Feature",
  "properties": {
    "iso:country":"GB",
    "wof:name":"NG7 2NW",
    "wof:placetype":"postalcode"
},
  "geometry": {"coordinates":[-1.17867562550067,52.9432190165756],"type":"Point"}
}