{
  "type": "Feature",
  "properties": {
    "iso:country":"GB",
    "wof:name":"NG34 9NS",
    "wof:placetype":"postalcode"
},
  "geometry": {"coordinates":[-0.36067580069588,52.98978047802092],"type":"Point"}
}