{
  "type": "Feature",
  "properties": {
    "iso:country": "GB",
    "wof:name": "OL9 6JH",
    "wof:placetype": "postalcode"
  },
  "geometry": {"coordinates":[-2.1322,53.543341],"type":"Point"}
}
