{
  "type": "Feature",
  "properties": {
    "iso:country":"GB",
    "wof:name":"OL9 6JH",
    "wof:placetype":"postalcode"
},
  "geometry": {"coordinates":[-2.13219987136006,53.54334097565369],"type":"Point"}
}