{
  "type": "Feature",
  "properties": {
    "iso:country":"GB",
    "wof:name":"N15 5AS",
    "wof:placetype":"postalcode"
},
  "geometry": {"coordinates":[-0.0873804260447,51.58466717333859],"type":"Point"}
}