{
  "type": "Feature",
  "properties": {
    "iso:country":"GB",
    "wof:name":"PE30 4DB",
    "wof:placetype":"postalcode"
},
  "geometry": {"coordinates":[0.42814043791238,52.76331908881982],"type":"Point"}
}