{
  "type": "Feature",
  "properties": {
    "date:inception_lower": "2017-06-01",
    "date:inception_upper": "2017-06-01",
    "iso:country": "GB",
    "wof:name": "E13 9DP",
    "wof:placetype": "postalcode"
  },
  "geometry": {"coordinates":[0.03744,51.532461],"type":"Point"}
}
