{
  "type": "Feature",
  "properties": {
    "iso:country":"GB",
    "wof:name":"M17 8AA",
    "wof:placetype":"postalcode"
},
  "geometry": {"coordinates":[-2.34982942126769,53.46570913784613],"type":"Point"}
}