{
  "type": "Feature",
  "properties": {
    "date:inception_lower":"1980-01-01",
    "date:inception_upper":"1980-01-31",
    "iso:country":"GB",
    "wof:name":"B95 5NL",
    "wof:placetype":"postalcode"
},
  "geometry": {"coordinates":[-1.822974,52.303157],"type":"Point"}
}