{
  "type": "Feature",
  "properties": {
    "iso:country": "GB",
    "wof:name": "AB51 5TF",
    "wof:placetype": "postalcode"
  },
  "geometry": {"coordinates":[-2.403005,57.281327],"type":"Point"}
}
