{
  "type": "Feature",
  "properties": {
    "iso:country":"GB",
    "wof:name":"LN2 4EH",
    "wof:placetype":"postalcode"
},
  "geometry": {"coordinates":[-0.51890760871037,53.24293357372137],"type":"Point"}
}