{
  "type": "Feature",
  "properties": {
    "date:inception_lower":"1984-02-01",
    "date:inception_upper":"1984-02-29",
    "iso:country":"GB",
    "wof:name":"BD5 8LQ",
    "wof:placetype":"postalcode"
},
  "geometry": {"coordinates":[-1.736156,53.770274],"type":"Point"}
}