{
  "type": "Feature",
  "properties": {
    "iso:country":"GB",
    "wof:name":"BD5 8LQ",
    "wof:placetype":"postalcode"
},
  "geometry": {"coordinates":[-1.73615577783435,53.77027358410636],"type":"Point"}
}