{
  "type": "Feature",
  "properties": {
    "iso:country": "GB",
    "wof:name": "DE65 9DY",
    "wof:placetype": "postalcode"
  },
  "geometry": {"coordinates":[-1.683457,52.865027],"type":"Point"}
}
