{
  "type": "Feature",
  "properties": {
    "iso:country":"GB",
    "wof:name":"PR7 1TJ",
    "wof:placetype":"postalcode"
},
  "geometry": {"coordinates":[-2.64619271845821,53.66348721117505],"type":"Point"}
}