{
  "type": "Feature",
  "properties": {
    "iso:country":"GB",
    "wof:name":"KT12 3AL",
    "wof:placetype":"postalcode"
},
  "geometry": {"coordinates":[-0.39886220448655,51.37985488227339],"type":"Point"}
}