{
  "type": "Feature",
  "properties": {
    "iso:country":"GB",
    "wof:name":"LL61 6TX",
    "wof:placetype":"postalcode"
},
  "geometry": {"coordinates":[-4.28629034120799,53.17570337874126],"type":"Point"}
}