{
  "type": "Feature",
  "properties": {
    "iso:country":"GB",
    "wof:name":"IP3 8DZ",
    "wof:placetype":"postalcode"
},
  "geometry": {"coordinates":[1.17776227721764,52.04878722298974],"type":"Point"}
}