{
  "type": "Feature",
  "properties": {
    "iso:country":"GB",
    "wof:name":"BB18 6NN",
    "wof:placetype":"postalcode"
},
  "geometry": {"coordinates":[-2.14548652578467,53.91350812507217],"type":"Point"}
}