{
  "type": "Feature",
  "properties": {
    "iso:country": "GB",
    "wof:name": "HR8 2FP",
    "wof:placetype": "postalcode"
  },
  "geometry": {"coordinates":[-2.434011,52.040705],"type":"Point"}
}
