{
  "type": "Feature",
  "properties": {
    "iso:country":"GB",
    "wof:name":"HR8 2FP",
    "wof:placetype":"postalcode"
},
  "geometry": {"coordinates":[-2.43401072722607,52.0407054175741],"type":"Point"}
}