{
  "type": "Feature",
  "properties": {
    "iso:country":"GB",
    "wof:name":"CV12 0JZ",
    "wof:placetype":"postalcode"
},
  "geometry": {"coordinates":[-1.51723363513975,52.4724965745702],"type":"Point"}
}