{
  "type": "Feature",
  "properties": {
    "iso:country":"GB",
    "wof:name":"WF2 6LZ",
    "wof:placetype":"postalcode"
},
  "geometry": {"coordinates":[-1.45563363482598,53.6488507298304],"type":"Point"}
}