{
  "type": "Feature",
  "properties": {
    "date:inception_lower": "1980-01-01",
    "date:inception_upper": "1980-01-01",
    "iso:country": "GB",
    "wof:name": "WF2 6LZ",
    "wof:placetype": "postalcode"
  },
  "geometry": {"coordinates":[-1.455634,53.648851],"type":"Point"}
}
