{
  "type": "Feature",
  "properties": {
    "iso:country": "GB",
    "wof:name": "TN25 6DX",
    "wof:placetype": "postalcode"
  },
  "geometry": {"coordinates":[1.019771,51.121545],"type":"Point"}
}
