{
  "type": "Feature",
  "properties": {
    "iso:country":"GB",
    "wof:name":"CH4 7EH",
    "wof:placetype":"postalcode"
},
  "geometry": {"coordinates":[-2.88241210003728,53.17504470221486],"type":"Point"}
}