{
  "type": "Feature",
  "properties": {
    "iso:country": "GB",
    "wof:name": "CH4 7EH",
    "wof:placetype": "postalcode"
  },
  "geometry": {"coordinates":[-2.882412,53.175045],"type":"Point"}
}
