{
  "type": "Feature",
  "properties": {
    "iso:country":"GB",
    "wof:name":"B77 1EN",
    "wof:placetype":"postalcode"
},
  "geometry": {"coordinates":[-1.68446763291162,52.61511874671014],"type":"Point"}
}