{
  "type": "Feature",
  "properties": {
    "date:inception_lower":"1980-01-01",
    "date:inception_upper":"1980-01-31",
    "iso:country":"GB",
    "wof:name":"ME12 2AE",
    "wof:placetype":"postalcode"
},
  "geometry": {"coordinates":[0.767393,51.438593],"type":"Point"}
}