{
  "type": "Feature",
  "properties": {
    "iso:country": "GB",
    "wof:name": "SN25 4EH",
    "wof:placetype": "postalcode"
  },
  "geometry": {"coordinates":[-1.796648,51.608057],"type":"Point"}
}
