{
  "type": "Feature",
  "properties": {
    "date:inception_lower":"1980-01-01",
    "date:inception_upper":"1980-01-31",
    "iso:country":"GB",
    "wof:name":"SN7 7RT",
    "wof:placetype":"postalcode"
},
  "geometry": {"coordinates":[-1.562206,51.600618],"type":"Point"}
}