{
  "type": "Feature",
  "properties": {
    "iso:country": "GB",
    "wof:name": "ST15 0NF",
    "wof:placetype": "postalcode"
  },
  "geometry": {"coordinates":[-2.192305,52.89199],"type":"Point"}
}
