{
  "type": "Feature",
  "properties": {
    "date:inception_lower":"1980-01-01",
    "date:inception_upper":"1980-01-31",
    "iso:country":"GB",
    "wof:name":"ST15 0NF",
    "wof:placetype":"postalcode"
},
  "geometry": {"coordinates":[-2.192305,52.89199],"type":"Point"}
}