{
  "type": "Feature",
  "properties": {
    "iso:country":"GB",
    "wof:name":"ST15 0NF",
    "wof:placetype":"postalcode"
},
  "geometry": {"coordinates":[-2.19230462568312,52.89199028919472],"type":"Point"}
}