{
  "type": "Feature",
  "properties": {
    "iso:country":"GB",
    "wof:name":"BD19 6NB",
    "wof:placetype":"postalcode"
},
  "geometry": {"coordinates":[-1.7499360083204,53.72866143332886],"type":"Point"}
}