{
  "type": "Feature",
  "properties": {
    "iso:country":"GB",
    "wof:name":"SW19 1TS",
    "wof:placetype":"postalcode"
},
  "geometry": {"coordinates":[-0.17871228601238,51.42339227252138],"type":"Point"}
}