{
  "type": "Feature",
  "properties": {
    "date:inception_lower":"1995-07-01",
    "date:inception_upper":"1995-07-31",
    "iso:country":"GB",
    "wof:name":"RM15 5JE",
    "wof:placetype":"postalcode"
},
  "geometry": {"coordinates":[0.290338,51.509917],"type":"Point"}
}