{
  "type": "Feature",
  "properties": {
    "iso:country":"GB",
    "wof:name":"RM15 5JE",
    "wof:placetype":"postalcode"
},
  "geometry": {"coordinates":[0.290310080197,51.50991584699027],"type":"Point"}
}