{
  "type": "Feature",
  "properties": {
    "iso:country": "GB",
    "wof:name": "RM15 5JE",
    "wof:placetype": "postalcode"
  },
  "geometry": {"coordinates":[0.290338,51.509917],"type":"Point"}
}
