{
  "type": "Feature",
  "properties": {
    "iso:country":"GB",
    "wof:name":"RG30 6AW",
    "wof:placetype":"postalcode"
},
  "geometry": {"coordinates":[-1.02201328918177,51.46742289142786],"type":"Point"}
}