{
  "type": "Feature",
  "properties": {
    "iso:country": "GB",
    "wof:name": "RG30 6AW",
    "wof:placetype": "postalcode"
  },
  "geometry": {"coordinates":[-1.021993,51.467425],"type":"Point"}
}
