{
  "type": "Feature",
  "properties": {
    "iso:country":"GB",
    "wof:name":"B32 1RG",
    "wof:placetype":"postalcode"
},
  "geometry": {"coordinates":[-2.0067104060308,52.45363039931313],"type":"Point"}
}