{
  "type": "Feature",
  "properties": {
    "date:inception_lower": "1993-01-01",
    "date:inception_upper": "1993-01-01",
    "iso:country": "GB",
    "wof:name": "B32 1RG",
    "wof:placetype": "postalcode"
  },
  "geometry": {"coordinates":[-2.00671,52.45363],"type":"Point"}
}
