{
  "type": "Feature",
  "properties": {
    "iso:country": "GB",
    "wof:name": "B32 1RG",
    "wof:placetype": "postalcode"
  },
  "geometry": {"coordinates":[-2.00671,52.45363],"type":"Point"}
}
