{
  "type": "Feature",
  "properties": {
    "iso:country":"GB",
    "wof:name":"HA3 9AL",
    "wof:placetype":"postalcode"
},
  "geometry": {"coordinates":[-0.30394091260921,51.59399441705935],"type":"Point"}
}