{
  "type": "Feature",
  "properties": {
    "date:inception_lower": "2003-04-01",
    "date:inception_upper": "2003-04-01",
    "iso:country": "GB",
    "wof:name": "E14 6GQ",
    "wof:placetype": "postalcode"
  },
  "geometry": {"coordinates":[-0.01432,51.518907],"type":"Point"}
}
