{
  "type": "Feature",
  "properties": {
    "iso:country":"GB",
    "wof:name":"E14 6GQ",
    "wof:placetype":"postalcode"
},
  "geometry": {"coordinates":[-0.01434802806302,51.51890524076212],"type":"Point"}
}