{
  "type": "Feature",
  "properties": {
    "iso:country":"GB",
    "wof:name":"WN2 5EU",
    "wof:placetype":"postalcode"
},
  "geometry": {"coordinates":[-2.60337776218548,53.52131625623974],"type":"Point"}
}