{
  "type": "Feature",
  "properties": {
    "iso:country":"GB",
    "wof:name":"CF71 7DG",
    "wof:placetype":"postalcode"
},
  "geometry": {"coordinates":[-3.44290330380101,51.45976722553495],"type":"Point"}
}