{
  "type": "Feature",
  "properties": {
    "iso:country": "GB",
    "wof:name": "KA22 8LD",
    "wof:placetype": "postalcode"
  },
  "geometry": {"coordinates":[-4.811557,55.64738],"type":"Point"}
}
