{
  "type": "Feature",
  "properties": {
    "iso:country":"GB",
    "wof:name":"KA22 8LD",
    "wof:placetype":"postalcode"
},
  "geometry": {"coordinates":[-4.81155656984418,55.64738036944098],"type":"Point"}
}