{
  "type": "Feature",
  "properties": {
    "iso:country":"GB",
    "wof:name":"SA47 0QZ",
    "wof:placetype":"postalcode"
},
  "geometry": {"coordinates":[-4.2954708772269,52.19840579785767],"type":"Point"}
}