{
  "type": "Feature",
  "properties": {
    "iso:country": "GB",
    "wof:name": "SA47 0QZ",
    "wof:placetype": "postalcode"
  },
  "geometry": {"coordinates":[-4.295471,52.198406],"type":"Point"}
}
