{
  "type": "Feature",
  "properties": {
    "date:inception_lower":"2018-01-01",
    "date:inception_upper":"2018-01-31",
    "iso:country":"GB",
    "wof:name":"PR1 6AA",
    "wof:placetype":"postalcode"
},
  "geometry": {"coordinates":[-2.693478,53.774657],"type":"Point"}
}