{
  "type": "Feature",
  "properties": {
    "date:inception_lower": "1980-01-01",
    "date:inception_upper": "1980-01-01",
    "iso:country": "GB",
    "wof:name": "CV37 8JW",
    "wof:placetype": "postalcode"
  },
  "geometry": {"coordinates":[-1.754187,52.160851],"type":"Point"}
}
