{
  "type": "Feature",
  "properties": {
    "iso:country":"GB",
    "wof:name":"CV37 8JW",
    "wof:placetype":"postalcode"
},
  "geometry": {"coordinates":[-1.75418737438551,52.16085120455674],"type":"Point"}
}