{
  "type": "Feature",
  "properties": {
    "iso:country": "GB",
    "wof:name": "CV37 8JW",
    "wof:placetype": "postalcode"
  },
  "geometry": {"coordinates":[-1.754187,52.160851],"type":"Point"}
}
