{
  "type": "Feature",
  "properties": {
    "iso:country": "GB",
    "wof:name": "NE37 2DS",
    "wof:placetype": "postalcode"
  },
  "geometry": {"coordinates":[-1.520355,54.908199],"type":"Point"}
}
