{
  "type": "Feature",
  "properties": {
    "iso:country":"GB",
    "wof:name":"MK43 8SH",
    "wof:placetype":"postalcode"
},
  "geometry": {"coordinates":[-0.56704772795865,52.13182499762446],"type":"Point"}
}