{
  "type": "Feature",
  "properties": {
    "date:inception_lower": "1980-01-01",
    "date:inception_upper": "1980-01-01",
    "iso:country": "GB",
    "wof:name": "DD4 8BA",
    "wof:placetype": "postalcode"
  },
  "geometry": {"coordinates":[-2.946247,56.483828],"type":"Point"}
}
