{
  "type": "Feature",
  "properties": {
    "iso:country":"GB",
    "wof:name":"CF48 2PP",
    "wof:placetype":"postalcode"
},
  "geometry": {"coordinates":[-3.40674596311216,51.76247878099087],"type":"Point"}
}