{
  "type": "Feature",
  "properties": {
    "iso:country": "GB",
    "wof:name": "NG9 5JB",
    "wof:placetype": "postalcode"
  },
  "geometry": {"coordinates":[-1.234423,52.91273],"type":"Point"}
}
