{
  "type": "Feature",
  "properties": {
    "iso:country":"GB",
    "wof:name":"NG9 5JB",
    "wof:placetype":"postalcode"
},
  "geometry": {"coordinates":[-1.23442302659693,52.91273015768675],"type":"Point"}
}