{
  "type": "Feature",
  "properties": {
    "iso:country": "GB",
    "wof:name": "NG3 2HZ",
    "wof:placetype": "postalcode"
  },
  "geometry": {"coordinates":[-1.121994,52.962258],"type":"Point"}
}
