{
  "type": "Feature",
  "properties": {
    "iso:country": "GB",
    "wof:name": "BN1 5NR",
    "wof:placetype": "postalcode"
  },
  "geometry": {"coordinates":[-0.155657,50.842901],"type":"Point"}
}
