{
  "type": "Feature",
  "properties": {
    "iso:country":"GB",
    "wof:name":"BN1 5NR",
    "wof:placetype":"postalcode"
},
  "geometry": {"coordinates":[-0.15565690471995,50.84290122067286],"type":"Point"}
}