{
  "type": "Feature",
  "properties": {
    "date:inception_lower":"1980-01-01",
    "date:inception_upper":"1980-01-31",
    "iso:country":"GB",
    "wof:name":"SP9 7HR",
    "wof:placetype":"postalcode"
},
  "geometry": {"coordinates":[-1.666981,51.244453],"type":"Point"}
}