{
  "type": "Feature",
  "properties": {
    "iso:country":"GB",
    "wof:name":"SP9 7HR",
    "wof:placetype":"postalcode"
},
  "geometry": {"coordinates":[-1.66698077953536,51.24445349259049],"type":"Point"}
}