{
  "type": "Feature",
  "properties": {
    "iso:country":"GB",
    "wof:name":"LS15 8EB",
    "wof:placetype":"postalcode"
},
  "geometry": {"coordinates":[-1.44601917454584,53.8063426032548],"type":"Point"}
}