{
  "type": "Feature",
  "properties": {
    "iso:country":"GB",
    "wof:name":"G51 4RR",
    "wof:placetype":"postalcode"
},
  "geometry": {"coordinates":[-4.3298170195386,55.86226435822911],"type":"Point"}
}