{
  "type": "Feature",
  "properties": {
    "iso:country":"GB",
    "wof:name":"M14 6LU",
    "wof:placetype":"postalcode"
},
  "geometry": {"coordinates":[-2.22222313229804,53.44411888368305],"type":"Point"}
}