{
  "type": "Feature",
  "properties": {
    "iso:country": "GB",
    "wof:name": "M14 6LU",
    "wof:placetype": "postalcode"
  },
  "geometry": {"coordinates":[-2.222223,53.444119],"type":"Point"}
}
