{
  "type": "Feature",
  "properties": {
    "date:inception_lower": "1998-12-01",
    "date:inception_upper": "1998-12-01",
    "iso:country": "GB",
    "wof:name": "CF5 4QR",
    "wof:placetype": "postalcode"
  },
  "geometry": {"coordinates":[-3.263736,51.477482],"type":"Point"}
}
