{
  "type": "Feature",
  "properties": {
    "iso:country":"GB",
    "wof:name":"CF5 4QR",
    "wof:placetype":"postalcode"
},
  "geometry": {"coordinates":[-3.26373649641686,51.47748184326396],"type":"Point"}
}