{
  "type": "Feature",
  "properties": {
    "iso:country": "GB",
    "wof:name": "SG9 9JN",
    "wof:placetype": "postalcode"
  },
  "geometry": {"coordinates":[-0.013555,51.940346],"type":"Point"}
}
