{
  "type": "Feature",
  "properties": {
    "iso:country":"GB",
    "wof:name":"SG9 9JN",
    "wof:placetype":"postalcode"
},
  "geometry": {"coordinates":[-0.01355519275844,51.94034589743841],"type":"Point"}
}