{
  "type": "Feature",
  "properties": {
    "iso:country":"GB",
    "wof:name":"SR2 7BW",
    "wof:placetype":"postalcode"
},
  "geometry": {"coordinates":[-1.38404833365503,54.90040443678954],"type":"Point"}
}