{
  "type": "Feature",
  "properties": {
    "iso:country":"GB",
    "wof:name":"RH1 4JQ",
    "wof:placetype":"postalcode"
},
  "geometry": {"coordinates":[-0.13192689846873,51.22688315892449],"type":"Point"}
}