{
  "type": "Feature",
  "properties": {
    "iso:country":"GB",
    "wof:name":"SG9 9AE",
    "wof:placetype":"postalcode"
},
  "geometry": {"coordinates":[-0.02054870121027,51.94870943547193],"type":"Point"}
}