{
  "type": "Feature",
  "properties": {
    "date:inception_lower": "1980-01-01",
    "date:inception_upper": "1980-01-01",
    "iso:country": "GB",
    "wof:name": "ME3 7SA",
    "wof:placetype": "postalcode"
  },
  "geometry": {"coordinates":[0.500654,51.452773],"type":"Point"}
}
