{
  "type": "Feature",
  "properties": {
    "iso:country": "GB",
    "wof:name": "IP32 6LS",
    "wof:placetype": "postalcode"
  },
  "geometry": {"coordinates":[0.699313,52.26027],"type":"Point"}
}
