{
  "type": "Feature",
  "properties": {
    "iso:country":"GB",
    "wof:name":"B17 8EN",
    "wof:placetype":"postalcode"
},
  "geometry": {"coordinates":[-1.96258467776975,52.48210501751498],"type":"Point"}
}