{
  "type": "Feature",
  "properties": {
    "iso:country":"GB",
    "wof:name":"SK7 2PP",
    "wof:placetype":"postalcode"
},
  "geometry": {"coordinates":[-2.16247756369163,53.36767763272402],"type":"Point"}
}