{
  "type": "Feature",
  "properties": {
    "date:inception_lower": "2017-04-01",
    "date:inception_upper": "2017-04-01",
    "iso:country": "GB",
    "wof:name": "SW6 1FY",
    "wof:placetype": "postalcode"
  },
  "geometry": {"coordinates":[-0.194967,51.48626],"type":"Point"}
}
