{
  "type": "Feature",
  "properties": {
    "iso:country": "GB",
    "wof:name": "SW6 1FY",
    "wof:placetype": "postalcode"
  },
  "geometry": {"coordinates":[-0.194967,51.48626],"type":"Point"}
}
