{
  "type": "Feature",
  "properties": {
    "date:inception_lower": "2007-02-01",
    "date:inception_upper": "2007-02-01",
    "iso:country": "GB",
    "wof:name": "NE26 4JZ",
    "wof:placetype": "postalcode"
  },
  "geometry": {"coordinates":[-1.486754,55.089998],"type":"Point"}
}
