{
  "type": "Feature",
  "properties": {
    "iso:country":"GB",
    "wof:name":"NE26 4JZ",
    "wof:placetype":"postalcode"
},
  "geometry": {"coordinates":[-1.48675381519595,55.08999775080945],"type":"Point"}
}