{
  "type": "Feature",
  "properties": {
    "iso:country":"GB",
    "wof:name":"OX4 4XS",
    "wof:placetype":"postalcode"
},
  "geometry": {"coordinates":[-1.23347310605634,51.71663936001987],"type":"Point"}
}