{
  "type": "Feature",
  "properties": {
    "iso:country": "GB",
    "wof:name": "OX4 4XS",
    "wof:placetype": "postalcode"
  },
  "geometry": {"coordinates":[-1.233473,51.716639],"type":"Point"}
}
