{
  "type": "Feature",
  "properties": {
    "date:inception_lower":"1990-02-01",
    "date:inception_upper":"1990-02-28",
    "iso:country":"GB",
    "wof:name":"OX4 4XS",
    "wof:placetype":"postalcode"
},
  "geometry": {"coordinates":[-1.233473,51.716639],"type":"Point"}
}