{
  "type": "Feature",
  "properties": {
    "iso:country":"GB",
    "wof:name":"TW12 2LJ",
    "wof:placetype":"postalcode"
},
  "geometry": {"coordinates":[-0.37099745948525,51.41754472337877],"type":"Point"}
}