{
  "type": "Feature",
  "properties": {
    "date:inception_lower": "1984-02-01",
    "date:inception_upper": "1984-02-01",
    "iso:country": "GB",
    "wof:name": "OX12 0DQ",
    "wof:placetype": "postalcode"
  },
  "geometry": {"coordinates":[-1.411964,51.618485],"type":"Point"}
}
