{
  "type": "Feature",
  "properties": {
    "iso:country":"GB",
    "wof:name":"PL14 5JY",
    "wof:placetype":"postalcode"
},
  "geometry": {"coordinates":[-4.45512526634445,50.4926096556158],"type":"Point"}
}