{
  "type": "Feature",
  "properties": {
    "iso:country":"GB",
    "wof:name":"AL1 1RL",
    "wof:placetype":"postalcode"
},
  "geometry": {"coordinates":[-0.33708031274439,51.74784633775852],"type":"Point"}
}