{
  "type": "Feature",
  "properties": {
    "date:inception_lower":"1980-01-01",
    "date:inception_upper":"1980-01-31",
    "iso:country":"GB",
    "wof:name":"TN15 7DY",
    "wof:placetype":"postalcode"
},
  "geometry": {"coordinates":[0.28523,51.329567],"type":"Point"}
}