{
  "type": "Feature",
  "properties": {
    "iso:country": "GB",
    "wof:name": "TN15 7DY",
    "wof:placetype": "postalcode"
  },
  "geometry": {"coordinates":[0.28523,51.329567],"type":"Point"}
}
