{
  "type": "Feature",
  "properties": {
    "date:inception_lower": "1980-01-01",
    "date:inception_upper": "1980-01-01",
    "iso:country": "GB",
    "wof:name": "B96 6AF",
    "wof:placetype": "postalcode"
  },
  "geometry": {"coordinates":[-1.940725,52.256902],"type":"Point"}
}
