{
  "type": "Feature",
  "properties": {
    "date:inception_lower": "1994-12-01",
    "date:inception_upper": "1994-12-01",
    "iso:country": "GB",
    "wof:name": "DE14 1DB",
    "wof:placetype": "postalcode"
  },
  "geometry": {"coordinates":[-1.626856,52.817776],"type":"Point"}
}
