{
  "type": "Feature",
  "properties": {
    "iso:country": "GB",
    "wof:name": "TA24 7UD",
    "wof:placetype": "postalcode"
  },
  "geometry": {"coordinates":[-3.519994,51.168292],"type":"Point"}
}
