{
  "type": "Feature",
  "properties": {
    "iso:country":"GB",
    "wof:name":"PA19 1SU",
    "wof:placetype":"postalcode"
},
  "geometry": {"coordinates":[-4.82715282718613,55.9517578371466],"type":"Point"}
}