{
  "type": "Feature",
  "properties": {
    "iso:country":"GB",
    "wof:name":"BB2 3RT",
    "wof:placetype":"postalcode"
},
  "geometry": {"coordinates":[-2.48630999687866,53.73868382130113],"type":"Point"}
}