{
  "type": "Feature",
  "properties": {
    "iso:country":"GB",
    "wof:name":"BR3 5EW",
    "wof:placetype":"postalcode"
},
  "geometry": {"coordinates":[-0.02018925940671,51.410722708535],"type":"Point"}
}