{
  "type": "Feature",
  "properties": {
    "iso:country":"GB",
    "wof:name":"BD9 4AZ",
    "wof:placetype":"postalcode"
},
  "geometry": {"coordinates":[-1.78346860546106,53.81610809918118],"type":"Point"}
}