{
  "type": "Feature",
  "properties": {
    "iso:country":"GB",
    "wof:name":"BS6 5NP",
    "wof:placetype":"postalcode"
},
  "geometry": {"coordinates":[-2.58742910852799,51.46467624122751],"type":"Point"}
}