{
  "type": "Feature",
  "properties": {
    "iso:country":"GB",
    "wof:name":"M15 5TH",
    "wof:placetype":"postalcode"
},
  "geometry": {"coordinates":[-2.25379791600816,53.46744398236581],"type":"Point"}
}