{
  "type": "Feature",
  "properties": {
    "date:inception_lower": "1997-06-01",
    "date:inception_upper": "1997-06-01",
    "iso:country": "GB",
    "wof:name": "S66 3XT",
    "wof:placetype": "postalcode"
  },
  "geometry": {"coordinates":[-1.271124,53.431992],"type":"Point"}
}
