{
  "type": "Feature",
  "properties": {
    "iso:country": "GB",
    "wof:name": "GL20 7AR",
    "wof:placetype": "postalcode"
  },
  "geometry": {"coordinates":[-2.021589,52.008571],"type":"Point"}
}
