{
  "type": "Feature",
  "properties": {
    "iso:country":"GB",
    "wof:name":"GL20 7AR",
    "wof:placetype":"postalcode"
},
  "geometry": {"coordinates":[-2.02158867642773,52.00857082883079],"type":"Point"}
}