{
  "type": "Feature",
  "properties": {
    "iso:country":"GB",
    "wof:name":"IV30 5ND",
    "wof:placetype":"postalcode"
},
  "geometry": {"coordinates":[-3.33039742934127,57.66176158410153],"type":"Point"}
}