{
  "type": "Feature",
  "properties": {
    "iso:country": "GB",
    "wof:name": "IV30 5ND",
    "wof:placetype": "postalcode"
  },
  "geometry": {"coordinates":[-3.331366,57.661296],"type":"Point"}
}
