{
  "type": "Feature",
  "properties": {
    "iso:country":"GB",
    "wof:name":"B66 4SG",
    "wof:placetype":"postalcode"
},
  "geometry": {"coordinates":[-1.95797133801061,52.48683219356649],"type":"Point"}
}