{
  "type": "Feature",
  "properties": {
    "iso:country": "GB",
    "wof:name": "B66 4SG",
    "wof:placetype": "postalcode"
  },
  "geometry": {"coordinates":[-1.957898,52.486868],"type":"Point"}
}
