{
  "type": "Feature",
  "properties": {
    "iso:country": "GB",
    "wof:name": "IP27 9NB",
    "wof:placetype": "postalcode"
  },
  "geometry": {"coordinates":[0.518877,52.420834],"type":"Point"}
}
