{
  "type": "Feature",
  "properties": {
    "date:inception_lower":"2013-07-01",
    "date:inception_upper":"2013-07-31",
    "iso:country":"GB",
    "wof:name":"IP27 9NB",
    "wof:placetype":"postalcode"
},
  "geometry": {"coordinates":[0.518877,52.420834],"type":"Point"}
}