{
  "type": "Feature",
  "properties": {
    "iso:country":"GB",
    "wof:name":"NE39 1PZ",
    "wof:placetype":"postalcode"
},
  "geometry": {"coordinates":[-1.74242558511542,54.91981713438855],"type":"Point"}
}