{
  "type": "Feature",
  "properties": {
    "date:inception_lower": "1980-01-01",
    "date:inception_upper": "1980-01-01",
    "iso:country": "GB",
    "wof:name": "NE39 1PZ",
    "wof:placetype": "postalcode"
  },
  "geometry": {"coordinates":[-1.742363,54.919835],"type":"Point"}
}
