{
  "type": "Feature",
  "properties": {
    "iso:country": "GB",
    "wof:name": "NE39 1PZ",
    "wof:placetype": "postalcode"
  },
  "geometry": {"coordinates":[-1.742363,54.919835],"type":"Point"}
}
