{
  "type": "Feature",
  "properties": {
    "date:inception_lower": "2014-04-01",
    "date:inception_upper": "2014-04-01",
    "iso:country": "GB",
    "wof:name": "CV37 8WE",
    "wof:placetype": "postalcode"
  },
  "geometry": {"coordinates":[-1.757761,52.119215],"type":"Point"}
}
