{
  "type": "Feature",
  "properties": {
    "iso:country": "GB",
    "wof:name": "CV37 8WE",
    "wof:placetype": "postalcode"
  },
  "geometry": {"coordinates":[-1.757761,52.119215],"type":"Point"}
}
