{
  "type": "Feature",
  "properties": {
    "iso:country":"GB",
    "wof:name":"CV37 8WE",
    "wof:placetype":"postalcode"
},
  "geometry": {"coordinates":[-1.75776076726738,52.11921459976131],"type":"Point"}
}