{
  "type": "Feature",
  "properties": {
    "iso:country":"GB",
    "wof:name":"SW11 5RA",
    "wof:placetype":"postalcode"
},
  "geometry": {"coordinates":[-0.15921049726423,51.46519985994782],"type":"Point"}
}