{
  "type": "Feature",
  "properties": {
    "iso:country":"GB",
    "wof:name":"DE14 1SE",
    "wof:placetype":"postalcode"
},
  "geometry": {"coordinates":[-1.62747413890958,52.80967824084806],"type":"Point"}
}