{
  "type": "Feature",
  "properties": {
    "date:inception_lower": "1991-01-01",
    "date:inception_upper": "1991-01-01",
    "iso:country": "GB",
    "wof:name": "DE14 1SE",
    "wof:placetype": "postalcode"
  },
  "geometry": {"coordinates":[-1.627469,52.809696],"type":"Point"}
}
