{
  "type": "Feature",
  "properties": {
    "iso:country":"GB",
    "wof:name":"RM13 9XT",
    "wof:placetype":"postalcode"
},
  "geometry": {"coordinates":[0.21280438777746,51.52123330729019],"type":"Point"}
}