{
  "type": "Feature",
  "properties": {
    "date:inception_lower":"1980-01-01",
    "date:inception_upper":"1980-01-31",
    "iso:country":"GB",
    "wof:name":"CV11 4HY",
    "wof:placetype":"postalcode"
},
  "geometry": {"coordinates":[-1.460945,52.520126],"type":"Point"}
}