{
  "type": "Feature",
  "properties": {
    "iso:country":"GB",
    "wof:name":"UB9 5HE",
    "wof:placetype":"postalcode"
},
  "geometry": {"coordinates":[-0.50100673808348,51.59753966049994],"type":"Point"}
}