{
  "type": "Feature",
  "properties": {
    "date:inception_lower": "1997-12-01",
    "date:inception_upper": "1997-12-01",
    "iso:country": "GB",
    "wof:name": "UB9 5HE",
    "wof:placetype": "postalcode"
  },
  "geometry": {"coordinates":[-0.501007,51.59754],"type":"Point"}
}
