{
  "type": "Feature",
  "properties": {
    "iso:country": "GB",
    "wof:name": "SP6 2JH",
    "wof:placetype": "postalcode"
  },
  "geometry": {"coordinates":[-1.758679,50.925171],"type":"Point"}
}
