{
  "type": "Feature",
  "properties": {
    "date:inception_lower": "1981-06-01",
    "date:inception_upper": "1981-06-01",
    "iso:country": "GB",
    "wof:name": "PR4 1EB",
    "wof:placetype": "postalcode"
  },
  "geometry": {"coordinates":[-2.8871,53.75022],"type":"Point"}
}
