{
  "type": "Feature",
  "properties": {
    "date:inception_lower": "2016-09-01",
    "date:inception_upper": "2016-09-01",
    "iso:country": "GB",
    "wof:name": "HP13 7PR",
    "wof:placetype": "postalcode"
  },
  "geometry": {"coordinates":[-0.711985,51.625539],"type":"Point"}
}
