{
  "type": "Feature",
  "properties": {
    "iso:country":"GB",
    "wof:name":"BS39 5RL",
    "wof:placetype":"postalcode"
},
  "geometry": {"coordinates":[-2.55072983169451,51.33856589815225],"type":"Point"}
}