{
  "type": "Feature",
  "properties": {
    "iso:country":"GB",
    "wof:name":"BS49 5JF",
    "wof:placetype":"postalcode"
},
  "geometry": {"coordinates":[-2.80690416751993,51.36778811820096],"type":"Point"}
}