{
  "type": "Feature",
  "properties": {
    "date:inception_lower": "1983-07-01",
    "date:inception_upper": "1983-07-01",
    "iso:country": "GB",
    "wof:name": "OL2 8DH",
    "wof:placetype": "postalcode"
  },
  "geometry": {"coordinates":[-2.086588,53.583516],"type":"Point"}
}
