{
  "type": "Feature",
  "properties": {
    "iso:country":"GB",
    "wof:name":"N1 2LT",
    "wof:placetype":"postalcode"
},
  "geometry": {"coordinates":[-0.09549312234772,51.54702167608855],"type":"Point"}
}