{
  "type": "Feature",
  "properties": {
    "iso:country":"GB",
    "wof:name":"NW2 2LX",
    "wof:placetype":"postalcode"
},
  "geometry": {"coordinates":[-0.20487600191609,51.56274743875124],"type":"Point"}
}