{
  "type": "Feature",
  "properties": {
    "iso:country":"GB",
    "wof:name":"CB2 8BH",
    "wof:placetype":"postalcode"
},
  "geometry": {"coordinates":[0.13205507197167,52.19126794288159],"type":"Point"}
}