{
  "type": "Feature",
  "properties": {
    "iso:country":"GB",
    "wof:name":"SK7 5AU",
    "wof:placetype":"postalcode"
},
  "geometry": {"coordinates":[-2.13527608999937,53.37711369880091],"type":"Point"}
}