{
  "type": "Feature",
  "properties": {
    "date:inception_lower": "1980-01-01",
    "date:inception_upper": "1980-01-01",
    "iso:country": "GB",
    "wof:name": "LN11 8LR",
    "wof:placetype": "postalcode"
  },
  "geometry": {"coordinates":[0.065019,53.34623],"type":"Point"}
}
