{
  "type": "Feature",
  "properties": {
    "iso:country":"GB",
    "wof:name":"LN11 8LR",
    "wof:placetype":"postalcode"
},
  "geometry": {"coordinates":[0.06506400778713,53.34621266275445],"type":"Point"}
}