{
  "type": "Feature",
  "properties": {
    "iso:country": "GB",
    "wof:name": "LN11 8LR",
    "wof:placetype": "postalcode"
  },
  "geometry": {"coordinates":[0.065019,53.34623],"type":"Point"}
}
