{
  "type": "Feature",
  "properties": {
    "date:inception_lower": "2001-06-01",
    "date:inception_upper": "2001-06-01",
    "iso:country": "GB",
    "wof:name": "HD9 7AZ",
    "wof:placetype": "postalcode"
  },
  "geometry": {"coordinates":[-1.777404,53.598789],"type":"Point"}
}
