{
  "type": "Feature",
  "properties": {
    "iso:country":"GB",
    "wof:name":"PO30 2ND",
    "wof:placetype":"postalcode"
},
  "geometry": {"coordinates":[-1.25482097632899,50.70441297070045],"type":"Point"}
}