{
  "type": "Feature",
  "properties": {
    "iso:country":"GB",
    "wof:name":"WF4 5NE",
    "wof:placetype":"postalcode"
},
  "geometry": {"coordinates":[-1.56347435999595,53.65852315527594],"type":"Point"}
}