{
  "type": "Feature",
  "properties": {
    "date:inception_lower": "1980-01-01",
    "date:inception_upper": "1980-01-01",
    "iso:country": "GB",
    "wof:name": "YO8 9QA",
    "wof:placetype": "postalcode"
  },
  "geometry": {"coordinates":[-1.168915,53.768997],"type":"Point"}
}
