{
  "type": "Feature",
  "properties": {
    "date:inception_lower": "2023-04-01",
    "date:inception_upper": "2023-04-01",
    "iso:country": "GB",
    "wof:name": "ME13 3DZ",
    "wof:placetype": "postalcode"
  },
  "geometry": {"coordinates":[0.892608,51.314852],"type":"Point"}
}
