{
  "type": "Feature",
  "properties": {
    "date:inception_lower": "2021-05-01",
    "date:inception_upper": "2021-05-01",
    "iso:country": "GB",
    "wof:name": "DL17 8BU",
    "wof:placetype": "postalcode"
  },
  "geometry": {"coordinates":[-1.554693,54.681851],"type":"Point"}
}
