{
  "type": "Feature",
  "properties": {
    "iso:country":"GB",
    "wof:name":"SO30 0LY",
    "wof:placetype":"postalcode"
},
  "geometry": {"coordinates":[-1.29964628886856,50.9082308957648],"type":"Point"}
}