{
  "type": "Feature",
  "properties": {
    "iso:country": "GB",
    "wof:name": "SO30 0LY",
    "wof:placetype": "postalcode"
  },
  "geometry": {"coordinates":[-1.299635,50.908222],"type":"Point"}
}
