{
  "type": "Feature",
  "properties": {
    "iso:country":"GB",
    "wof:name":"IV51 9PR",
    "wof:placetype":"postalcode"
},
  "geometry": {"coordinates":[-6.42649864778669,57.47478695512905],"type":"Point"}
}