{
  "type": "Feature",
  "properties": {
    "iso:country":"GB",
    "wof:name":"CM3 2BN",
    "wof:placetype":"postalcode"
},
  "geometry": {"coordinates":[0.56526715975932,51.82447333398619],"type":"Point"}
}