{
  "type": "Feature",
  "properties": {
    "date:inception_lower": "1980-01-01",
    "date:inception_upper": "1980-01-01",
    "iso:country": "GB",
    "wof:name": "CM3 2BN",
    "wof:placetype": "postalcode"
  },
  "geometry": {"coordinates":[0.565267,51.824473],"type":"Point"}
}
