{
  "type": "Feature",
  "properties": {
    "iso:country":"GB",
    "wof:name":"ZE1 0PB",
    "wof:placetype":"postalcode"
},
  "geometry": {"coordinates":[-1.15886353369427,60.15766941046994],"type":"Point"}
}