{
  "type": "Feature",
  "properties": {
    "date:inception_lower":"1980-01-01",
    "date:inception_upper":"1980-01-31",
    "iso:country":"GB",
    "wof:name":"LL16 4AS",
    "wof:placetype":"postalcode"
},
  "geometry": {"coordinates":[-3.400897,53.181419],"type":"Point"}
}