{
  "type": "Feature",
  "properties": {
    "iso:country":"GB",
    "wof:name":"LL16 4AS",
    "wof:placetype":"postalcode"
},
  "geometry": {"coordinates":[-3.40089701731197,53.18141902594441],"type":"Point"}
}