{
  "type": "Feature",
  "properties": {
    "date:inception_lower": "1980-01-01",
    "date:inception_upper": "1980-01-01",
    "iso:country": "GB",
    "wof:name": "PE31 8HS",
    "wof:placetype": "postalcode"
  },
  "geometry": {"coordinates":[0.757907,52.939009],"type":"Point"}
}
