{
  "type": "Feature",
  "properties": {
    "iso:country":"GB",
    "wof:name":"PE31 8HS",
    "wof:placetype":"postalcode"
},
  "geometry": {"coordinates":[0.75790645786414,52.93900870642831],"type":"Point"}
}