{
  "type": "Feature",
  "properties": {
    "iso:country":"GB",
    "wof:name":"NG5 8GN",
    "wof:placetype":"postalcode"
},
  "geometry": {"coordinates":[-1.10914631467345,53.01148796240188],"type":"Point"}
}