{
  "type": "Feature",
  "properties": {
    "date:inception_lower": "1992-08-01",
    "date:inception_upper": "1992-08-01",
    "iso:country": "GB",
    "wof:name": "NG5 8GN",
    "wof:placetype": "postalcode"
  },
  "geometry": {"coordinates":[-1.109146,53.011488],"type":"Point"}
}
