{
  "type": "Feature",
  "properties": {
    "date:inception_lower": "1980-01-01",
    "date:inception_upper": "1980-01-01",
    "iso:country": "GB",
    "wof:name": "AL6 0DH",
    "wof:placetype": "postalcode"
  },
  "geometry": {"coordinates":[-0.196097,51.824214],"type":"Point"}
}
