{
  "type": "Feature",
  "properties": {
    "iso:country":"GB",
    "wof:name":"AL6 0DH",
    "wof:placetype":"postalcode"
},
  "geometry": {"coordinates":[-0.19609688291201,51.82421369317196],"type":"Point"}
}