{
  "type": "Feature",
  "properties": {
    "iso:country": "GB",
    "wof:name": "OX3 8AP",
    "wof:placetype": "postalcode"
  },
  "geometry": {"coordinates":[-1.197941,51.762177],"type":"Point"}
}
