{
  "type": "Feature",
  "properties": {
    "iso:country":"GB",
    "wof:name":"OX3 8AP",
    "wof:placetype":"postalcode"
},
  "geometry": {"coordinates":[-1.19794150612152,51.76217698499995],"type":"Point"}
}