{
  "type": "Feature",
  "properties": {
    "iso:country":"GB",
    "wof:name":"RG4 9TG",
    "wof:placetype":"postalcode"
},
  "geometry": {"coordinates":[-0.98561832474724,51.5219906500891],"type":"Point"}
}