{
  "type": "Feature",
  "properties": {
    "iso:country": "GB",
    "wof:name": "WA7 1PH",
    "wof:placetype": "postalcode"
  },
  "geometry": {"coordinates":[-2.70992,53.342276],"type":"Point"}
}
