{
  "type": "Feature",
  "properties": {
    "iso:country": "GB",
    "wof:name": "WA7 1PH",
    "wof:placetype": "postalcode"
  },
  "geometry": {"coordinates":[-2.712716,53.342403],"type":"Point"}
}
