{
  "type": "Feature",
  "properties": {
    "date:inception_lower":"1983-07-01",
    "date:inception_upper":"1983-07-31",
    "iso:country":"GB",
    "wof:name":"WA7 1PH",
    "wof:placetype":"postalcode"
},
  "geometry": {"coordinates":[-2.712716,53.342403],"type":"Point"}
}