{
  "type": "Feature",
  "properties": {
    "date:inception_lower":"2018-04-01",
    "date:inception_upper":"2018-04-30",
    "iso:country":"GB",
    "wof:name":"BD1 9AR",
    "wof:placetype":"postalcode"
},
  "geometry": {"coordinates":[-1.755847,53.802651],"type":"Point"}
}