{
  "type": "Feature",
  "properties": {
    "iso:country": "GB",
    "wof:name": "KT4 7QF",
    "wof:placetype": "postalcode"
  },
  "geometry": {"coordinates":[-0.264503,51.37421],"type":"Point"}
}
