{
  "type": "Feature",
  "properties": {
    "iso:country":"GB",
    "wof:name":"TF2 7AY",
    "wof:placetype":"postalcode"
},
  "geometry": {"coordinates":[-2.44003404460632,52.70708074050989],"type":"Point"}
}