{
  "type": "Feature",
  "properties": {
    "iso:country":"GB",
    "wof:name":"EN11 8GZ",
    "wof:placetype":"postalcode"
},
  "geometry": {"coordinates":[-0.0097420831762,51.76167833710333],"type":"Point"}
}