{
  "type": "Feature",
  "properties": {
    "iso:country": "GB",
    "wof:name": "EN11 8GZ",
    "wof:placetype": "postalcode"
  },
  "geometry": {"coordinates":[-0.009742,51.761678],"type":"Point"}
}
