{
  "type": "Feature",
  "properties": {
    "iso:country":"GB",
    "wof:name":"RH15 8SA",
    "wof:placetype":"postalcode"
},
  "geometry": {"coordinates":[-0.13324469314603,50.96587971049028],"type":"Point"}
}