{
  "type": "Feature",
  "properties": {
    "date:inception_lower": "1983-01-01",
    "date:inception_upper": "1983-01-01",
    "iso:country": "GB",
    "wof:name": "RH15 8SA",
    "wof:placetype": "postalcode"
  },
  "geometry": {"coordinates":[-0.132935,50.965816],"type":"Point"}
}
