{
  "type": "Feature",
  "properties": {
    "date:inception_lower": "1980-01-01",
    "date:inception_upper": "1980-01-01",
    "iso:country": "GB",
    "wof:name": "B37 6RU",
    "wof:placetype": "postalcode"
  },
  "geometry": {"coordinates":[-1.728798,52.482277],"type":"Point"}
}
