{
  "type": "Feature",
  "properties": {
    "iso:country":"GB",
    "wof:name":"B37 6RU",
    "wof:placetype":"postalcode"
},
  "geometry": {"coordinates":[-1.72879769043639,52.48227710739376],"type":"Point"}
}