{
  "type": "Feature",
  "properties": {
    "iso:country": "GB",
    "wof:name": "NE42 6DY",
    "wof:placetype": "postalcode"
  },
  "geometry": {"coordinates":[-1.897864,54.96762],"type":"Point"}
}
