{
  "type": "Feature",
  "properties": {
    "iso:country":"GB",
    "wof:name":"NE42 6DY",
    "wof:placetype":"postalcode"
},
  "geometry": {"coordinates":[-1.89786389003174,54.96761996462568],"type":"Point"}
}