{
  "type": "Feature",
  "properties": {
    "iso:country": "GB",
    "wof:name": "E2 6LQ",
    "wof:placetype": "postalcode"
  },
  "geometry": {"coordinates":[-0.064931,51.527997],"type":"Point"}
}
