{
  "type": "Feature",
  "properties": {
    "iso:country":"GB",
    "wof:name":"E2 6LQ",
    "wof:placetype":"postalcode"
},
  "geometry": {"coordinates":[-0.06493058796508,51.52799687174478],"type":"Point"}
}