{
  "type": "Feature",
  "properties": {
    "iso:country": "GB",
    "wof:name": "NG7 5DT",
    "wof:placetype": "postalcode"
  },
  "geometry": {"coordinates":[-1.170322,52.964484],"type":"Point"}
}
