{
  "type": "Feature",
  "properties": {
    "date:inception_lower":"2010-06-01",
    "date:inception_upper":"2010-06-30",
    "iso:country":"GB",
    "wof:name":"NG7 5DT",
    "wof:placetype":"postalcode"
},
  "geometry": {"coordinates":[-1.170322,52.964484],"type":"Point"}
}