{
  "type": "Feature",
  "properties": {
    "date:inception_lower": "1980-01-01",
    "date:inception_upper": "1980-01-01",
    "iso:country": "GB",
    "wof:name": "SK13 0HL",
    "wof:placetype": "postalcode"
  },
  "geometry": {"coordinates":[-1.986109,53.448703],"type":"Point"}
}
