{
  "type": "Feature",
  "properties": {
    "date:inception_lower": "2022-04-01",
    "date:inception_upper": "2022-04-01",
    "iso:country": "GB",
    "wof:name": "B90 8DW",
    "wof:placetype": "postalcode"
  },
  "geometry": {"coordinates":[-1.803984,52.370766],"type":"Point"}
}
