{
  "type": "Feature",
  "properties": {
    "iso:country":"GB",
    "wof:name":"DN14 7XP",
    "wof:placetype":"postalcode"
},
  "geometry": {"coordinates":[-0.76780949260859,53.74210364867844],"type":"Point"}
}