{
  "type": "Feature",
  "properties": {
    "iso:country": "GB",
    "wof:name": "DN14 7XP",
    "wof:placetype": "postalcode"
  },
  "geometry": {"coordinates":[-0.767809,53.742104],"type":"Point"}
}
