{
  "type": "Feature",
  "properties": {
    "date:inception_lower":"1980-01-01",
    "date:inception_upper":"1980-01-31",
    "iso:country":"GB",
    "wof:name":"DN14 7XP",
    "wof:placetype":"postalcode"
},
  "geometry": {"coordinates":[-0.767809,53.742104],"type":"Point"}
}