{
  "type": "Feature",
  "properties": {
    "iso:country":"GB",
    "wof:name":"CT20 3JJ",
    "wof:placetype":"postalcode"
},
  "geometry": {"coordinates":[1.12545294348451,51.08518760969798],"type":"Point"}
}