{
  "type": "Feature",
  "properties": {
    "iso:country": "GB",
    "wof:name": "PR5 4BN",
    "wof:placetype": "postalcode"
  },
  "geometry": {"coordinates":[-2.659444,53.748363],"type":"Point"}
}
