{
  "type": "Feature",
  "properties": {
    "iso:country": "GB",
    "wof:name": "BH19 3JU",
    "wof:placetype": "postalcode"
  },
  "geometry": {"coordinates":[-2.016297,50.605623],"type":"Point"}
}
