{
  "type": "Feature",
  "properties": {
    "iso:country":"GB",
    "wof:name":"BH19 3JU",
    "wof:placetype":"postalcode"
},
  "geometry": {"coordinates":[-2.01629723087237,50.60562291395176],"type":"Point"}
}