{
  "type": "Feature",
  "properties": {
    "iso:country": "GB",
    "wof:name": "LE5 1WF",
    "wof:placetype": "postalcode"
  },
  "geometry": {"coordinates":[-1.062249,52.662263],"type":"Point"}
}
