{
  "type": "Feature",
  "properties": {
    "iso:country":"GB",
    "wof:name":"LE5 1WF",
    "wof:placetype":"postalcode"
},
  "geometry": {"coordinates":[-1.06224940644243,52.66226278624086],"type":"Point"}
}