{
  "type": "Feature",
  "properties": {
    "iso:country":"GB",
    "wof:name":"KY6 2PQ",
    "wof:placetype":"postalcode"
},
  "geometry": {"coordinates":[-3.1988814190387,56.18791006388322],"type":"Point"}
}