{
  "type": "Feature",
  "properties": {
    "iso:country":"GB",
    "wof:name":"M34 2WY",
    "wof:placetype":"postalcode"
},
  "geometry": {"coordinates":[-2.14324268378642,53.45303060428384],"type":"Point"}
}