{
  "type": "Feature",
  "properties": {
    "iso:country":"GB",
    "wof:name":"BS5 8AG",
    "wof:placetype":"postalcode"
},
  "geometry": {"coordinates":[-2.55080397981911,51.45480144904457],"type":"Point"}
}