{
  "type": "Feature",
  "properties": {
    "iso:country":"GB",
    "wof:name":"TN10 4RA",
    "wof:placetype":"postalcode"
},
  "geometry": {"coordinates":[0.28787596447625,51.21250256874044],"type":"Point"}
}