{
  "type": "Feature",
  "properties": {
    "iso:country":"GB",
    "wof:name":"EH39 5JB",
    "wof:placetype":"postalcode"
},
  "geometry": {"coordinates":[-2.74582697287497,56.04410503137514],"type":"Point"}
}