{
  "type": "Feature",
  "properties": {
    "iso:country":"GB",
    "wof:name":"BD11 2NU",
    "wof:placetype":"postalcode"
},
  "geometry": {"coordinates":[-1.68384676802129,53.74353353671749],"type":"Point"}
}