{
  "type": "Feature",
  "properties": {
    "iso:country": "GB",
    "wof:name": "BD11 2NU",
    "wof:placetype": "postalcode"
  },
  "geometry": {"coordinates":[-1.683847,53.743534],"type":"Point"}
}
