{
  "type": "Feature",
  "properties": {
    "iso:country":"GB",
    "wof:name":"CR2 6QB",
    "wof:placetype":"postalcode"
},
  "geometry": {"coordinates":[-0.10500993247147,51.34685576073674],"type":"Point"}
}