{
  "type": "Feature",
  "properties": {
    "iso:country": "GB",
    "wof:name": "CR2 6QB",
    "wof:placetype": "postalcode"
  },
  "geometry": {"coordinates":[-0.10501,51.346856],"type":"Point"}
}
