{
  "type": "Feature",
  "properties": {
    "iso:country":"GB",
    "wof:name":"LU3 4EW",
    "wof:placetype":"postalcode"
},
  "geometry": {"coordinates":[-0.43174711361666,51.92249936550561],"type":"Point"}
}