{
  "type": "Feature",
  "properties": {
    "iso:country":"GB",
    "wof:name":"NR28 9HA",
    "wof:placetype":"postalcode"
},
  "geometry": {"coordinates":[1.39447580090406,52.81956572479849],"type":"Point"}
}