{
  "type": "Feature",
  "properties": {
    "iso:country": "GB",
    "wof:name": "TA12 6PD",
    "wof:placetype": "postalcode"
  },
  "geometry": {"coordinates":[-2.737581,50.978041],"type":"Point"}
}
