{
  "type": "Feature",
  "properties": {
    "date:inception_lower": "1980-01-01",
    "date:inception_upper": "1980-01-01",
    "iso:country": "GB",
    "wof:name": "TA12 6PD",
    "wof:placetype": "postalcode"
  },
  "geometry": {"coordinates":[-2.737581,50.978041],"type":"Point"}
}
