{
  "type": "Feature",
  "properties": {
    "date:inception_lower":"2011-10-01",
    "date:inception_upper":"2011-10-31",
    "iso:country":"GB",
    "wof:name":"PE31 8FH",
    "wof:placetype":"postalcode"
},
  "geometry": {"coordinates":[0.682473,52.966408],"type":"Point"}
}