{
  "type": "Feature",
  "properties": {
    "date:inception_lower": "2011-10-01",
    "date:inception_upper": "2011-10-01",
    "iso:country": "GB",
    "wof:name": "PE31 8FH",
    "wof:placetype": "postalcode"
  },
  "geometry": {"coordinates":[0.683471,52.966475],"type":"Point"}
}
