{
  "type": "Feature",
  "properties": {
    "date:inception_lower":"1984-10-01",
    "date:inception_upper":"1984-10-31",
    "iso:country":"GB",
    "wof:name":"WV6 7PG",
    "wof:placetype":"postalcode"
},
  "geometry": {"coordinates":[-2.19528,52.594862],"type":"Point"}
}