{
  "type": "Feature",
  "properties": {
    "iso:country":"GB",
    "wof:name":"WV6 7PG",
    "wof:placetype":"postalcode"
},
  "geometry": {"coordinates":[-2.19528049397562,52.59486218151378],"type":"Point"}
}