{
  "type": "Feature",
  "properties": {
    "iso:country": "GB",
    "wof:name": "WV6 7PG",
    "wof:placetype": "postalcode"
  },
  "geometry": {"coordinates":[-2.19528,52.594862],"type":"Point"}
}
