{
  "type": "Feature",
  "properties": {
    "iso:country":"GB",
    "wof:name":"TN13 1NX",
    "wof:placetype":"postalcode"
},
  "geometry": {"coordinates":[0.18637474911319,51.26635275362268],"type":"Point"}
}