{
  "type": "Feature",
  "properties": {
    "iso:country": "GB",
    "wof:name": "NR13 4RZ",
    "wof:placetype": "postalcode"
  },
  "geometry": {"coordinates":[1.453699,52.650317],"type":"Point"}
}
