{
  "type": "Feature",
  "properties": {
    "iso:country": "GB",
    "wof:name": "L37 6BX",
    "wof:placetype": "postalcode"
  },
  "geometry": {"coordinates":[-3.053394,53.549694],"type":"Point"}
}
