{
  "type": "Feature",
  "properties": {
    "iso:country":"GB",
    "wof:name":"L37 6BX",
    "wof:placetype":"postalcode"
},
  "geometry": {"coordinates":[-3.05339400237388,53.54968502225124],"type":"Point"}
}