{
  "type": "Feature",
  "properties": {
    "iso:country":"GB",
    "wof:name":"DN16 3FT",
    "wof:placetype":"postalcode"
},
  "geometry": {"coordinates":[-0.62632247908008,53.55878221644153],"type":"Point"}
}