{
  "type": "Feature",
  "properties": {
    "iso:country":"GB",
    "wof:name":"CR0 1XJ",
    "wof:placetype":"postalcode"
},
  "geometry": {"coordinates":[-0.10469904071744,51.37631100159143],"type":"Point"}
}