{
  "type": "Feature",
  "properties": {
    "iso:country": "GB",
    "wof:name": "NG9 6RD",
    "wof:placetype": "postalcode"
  },
  "geometry": {"coordinates":[-1.244773,52.906755],"type":"Point"}
}
