{
  "type": "Feature",
  "properties": {
    "date:inception_lower": "2004-11-01",
    "date:inception_upper": "2004-11-01",
    "iso:country": "GB",
    "wof:name": "NG9 6RD",
    "wof:placetype": "postalcode"
  },
  "geometry": {"coordinates":[-1.244773,52.906755],"type":"Point"}
}
