{
  "type": "Feature",
  "properties": {
    "iso:country":"GB",
    "wof:name":"TW3 4JN",
    "wof:placetype":"postalcode"
},
  "geometry": {"coordinates":[-0.37377360203664,51.47545804499401],"type":"Point"}
}