{
  "type": "Feature",
  "properties": {
    "date:inception_lower": "1980-01-01",
    "date:inception_upper": "1980-01-01",
    "iso:country": "GB",
    "wof:name": "TW3 4JN",
    "wof:placetype": "postalcode"
  },
  "geometry": {"coordinates":[-0.373774,51.475458],"type":"Point"}
}
