{
  "type": "Feature",
  "properties": {
    "iso:country":"GB",
    "wof:name":"PA4 0LF",
    "wof:placetype":"postalcode"
},
  "geometry": {"coordinates":[-4.39599179140105,55.86554998021165],"type":"Point"}
}