{
  "type": "Feature",
  "properties": {
    "date:inception_lower": "1980-01-01",
    "date:inception_upper": "1980-01-01",
    "iso:country": "GB",
    "wof:name": "PA4 0LF",
    "wof:placetype": "postalcode"
  },
  "geometry": {"coordinates":[-4.395992,55.86555],"type":"Point"}
}
