{
  "type": "Feature",
  "properties": {
    "iso:country":"GB",
    "wof:name":"HP9 2TW",
    "wof:placetype":"postalcode"
},
  "geometry": {"coordinates":[-0.65850549774432,51.62516180408841],"type":"Point"}
}