{
  "type": "Feature",
  "properties": {
    "iso:country":"GB",
    "wof:name":"BR1 1PP",
    "wof:placetype":"postalcode"
},
  "geometry": {"coordinates":[0.0159876592763,51.40738108506088],"type":"Point"}
}