{
  "type": "Feature",
  "properties": {
    "iso:country": "GB",
    "wof:name": "MK45 5EZ",
    "wof:placetype": "postalcode"
  },
  "geometry": {"coordinates":[-0.456265,51.99454],"type":"Point"}
}
