{
  "type": "Feature",
  "properties": {
    "iso:country":"GB",
    "wof:name":"MK45 5EZ",
    "wof:placetype":"postalcode"
},
  "geometry": {"coordinates":[-0.45626506160979,51.9945399794852],"type":"Point"}
}