{
  "type": "Feature",
  "properties": {
    "iso:country":"GB",
    "wof:name":"HU10 7QB",
    "wof:placetype":"postalcode"
},
  "geometry": {"coordinates":[-0.44770729803526,53.75353186703148],"type":"Point"}
}