{
  "type": "Feature",
  "properties": {
    "iso:country":"GB",
    "wof:name":"PO5 4EE",
    "wof:placetype":"postalcode"
},
  "geometry": {"coordinates":[-1.09369237917436,50.79261601379975],"type":"Point"}
}