{
  "type": "Feature",
  "properties": {
    "iso:country":"GB",
    "wof:name":"LE67 2RH",
    "wof:placetype":"postalcode"
},
  "geometry": {"coordinates":[-1.42653025329005,52.68767020950578],"type":"Point"}
}