{
  "type": "Feature",
  "properties": {
    "date:inception_lower": "1992-08-01",
    "date:inception_upper": "1992-08-01",
    "iso:country": "GB",
    "wof:name": "LE67 2RH",
    "wof:placetype": "postalcode"
  },
  "geometry": {"coordinates":[-1.42653,52.68767],"type":"Point"}
}
