{
  "type": "Feature",
  "properties": {
    "iso:country":"GB",
    "wof:name":"SK12 1XU",
    "wof:placetype":"postalcode"
},
  "geometry": {"coordinates":[-2.12818362351151,53.3429647693534],"type":"Point"}
}