{
  "type": "Feature",
  "properties": {
    "iso:country":"GB",
    "wof:name":"HA0 4JG",
    "wof:placetype":"postalcode"
},
  "geometry": {"coordinates":[-0.29153678255967,51.54325102828906],"type":"Point"}
}