{
  "type": "Feature",
  "properties": {
    "iso:country":"GB",
    "wof:name":"IG3 9JF",
    "wof:placetype":"postalcode"
},
  "geometry": {"coordinates":[0.09478667008275,51.55889504455415],"type":"Point"}
}