{
  "type": "Feature",
  "properties": {
    "iso:country":"GB",
    "wof:name":"SK9 4JJ",
    "wof:placetype":"postalcode"
},
  "geometry": {"coordinates":[-2.24425649946333,53.35357877379158],"type":"Point"}
}