{
  "type": "Feature",
  "properties": {
    "iso:country": "GB",
    "wof:name": "B74 2UU",
    "wof:placetype": "postalcode"
  },
  "geometry": {"coordinates":[-1.829249,52.579886],"type":"Point"}
}
