{
  "type": "Feature",
  "properties": {
    "date:inception_lower":"1994-05-01",
    "date:inception_upper":"1994-05-31",
    "iso:country":"GB",
    "wof:name":"M19 1GR",
    "wof:placetype":"postalcode"
},
  "geometry": {"coordinates":[-2.201798,53.432443],"type":"Point"}
}