{
  "type": "Feature",
  "properties": {
    "date:inception_lower": "2020-05-01",
    "date:inception_upper": "2020-05-01",
    "iso:country": "GB",
    "wof:name": "DT5 1GD",
    "wof:placetype": "postalcode"
  },
  "geometry": {"coordinates":[-2.427786,50.552802],"type":"Point"}
}
