{
  "type": "Feature",
  "properties": {
    "iso:country":"GB",
    "wof:name":"BB10 2DP",
    "wof:placetype":"postalcode"
},
  "geometry": {"coordinates":[-2.21156566609372,53.80981546876562],"type":"Point"}
}