{
  "type": "Feature",
  "properties": {
    "date:inception_lower": "1994-05-01",
    "date:inception_upper": "1994-05-01",
    "iso:country": "GB",
    "wof:name": "M30 0DH",
    "wof:placetype": "postalcode"
  },
  "geometry": {"coordinates":[-2.332203,53.482784],"type":"Point"}
}
