{
  "type": "Feature",
  "properties": {
    "iso:country":"GB",
    "wof:name":"M30 0DH",
    "wof:placetype":"postalcode"
},
  "geometry": {"coordinates":[-2.33220351766346,53.48278367361863],"type":"Point"}
}