{
  "type": "Feature",
  "properties": {
    "iso:country": "GB",
    "wof:name": "HP9 1RF",
    "wof:placetype": "postalcode"
  },
  "geometry": {"coordinates":[-0.640023,51.610355],"type":"Point"}
}
