{
  "type": "Feature",
  "properties": {
    "date:inception_lower":"1980-01-01",
    "date:inception_upper":"1980-01-31",
    "iso:country":"GB",
    "wof:name":"HP9 1RF",
    "wof:placetype":"postalcode"
},
  "geometry": {"coordinates":[-0.640023,51.610355],"type":"Point"}
}