{
  "type": "Feature",
  "properties": {
    "iso:country":"GB",
    "wof:name":"HP9 1RF",
    "wof:placetype":"postalcode"
},
  "geometry": {"coordinates":[-0.64002296780469,51.61035540786783],"type":"Point"}
}