{
  "type": "Feature",
  "properties": {
    "date:inception_lower":"2007-10-01",
    "date:inception_upper":"2007-10-31",
    "iso:country":"GB",
    "wof:name":"HD1 3NA",
    "wof:placetype":"postalcode"
},
  "geometry": {"coordinates":[-1.790276,53.638695],"type":"Point"}
}