{
  "type": "Feature",
  "properties": {
    "iso:country": "GB",
    "wof:name": "HD1 3NA",
    "wof:placetype": "postalcode"
  },
  "geometry": {"coordinates":[-1.790276,53.638695],"type":"Point"}
}
