{
  "type": "Feature",
  "properties": {
    "date:inception_lower": "2012-07-01",
    "date:inception_upper": "2012-07-01",
    "iso:country": "GB",
    "wof:name": "DN16 3EZ",
    "wof:placetype": "postalcode"
  },
  "geometry": {"coordinates":[-0.61884,53.563227],"type":"Point"}
}
