{
  "type": "Feature",
  "properties": {
    "iso:country": "GB",
    "wof:name": "DN16 3EZ",
    "wof:placetype": "postalcode"
  },
  "geometry": {"coordinates":[-0.61884,53.563227],"type":"Point"}
}
