{
  "type": "Feature",
  "properties": {
    "iso:country":"GB",
    "wof:name":"RG17 0JG",
    "wof:placetype":"postalcode"
},
  "geometry": {"coordinates":[-1.51857038204664,51.41495250996391],"type":"Point"}
}