{
  "type": "Feature",
  "properties": {
    "date:inception_lower": "1980-01-01",
    "date:inception_upper": "1980-01-01",
    "iso:country": "GB",
    "wof:name": "PE30 1EG",
    "wof:placetype": "postalcode"
  },
  "geometry": {"coordinates":[0.396903,52.75566],"type":"Point"}
}
