{
  "type": "Feature",
  "properties": {
    "iso:country":"GB",
    "wof:name":"FY5 2UP",
    "wof:placetype":"postalcode"
},
  "geometry": {"coordinates":[-3.02287851161571,53.8907220208608],"type":"Point"}
}