{
  "type": "Feature",
  "properties": {
    "iso:country":"GB",
    "wof:name":"YO13 0AN",
    "wof:placetype":"postalcode"
},
  "geometry": {"coordinates":[-0.45133965261066,54.33747825806928],"type":"Point"}
}