{
  "type": "Feature",
  "properties": {
    "iso:country": "GB",
    "wof:name": "YO13 0AN",
    "wof:placetype": "postalcode"
  },
  "geometry": {"coordinates":[-0.45134,54.337478],"type":"Point"}
}
