{
  "type": "Feature",
  "properties": {
    "iso:country": "GB",
    "wof:name": "EN7 6HA",
    "wof:placetype": "postalcode"
  },
  "geometry": {"coordinates":[-0.063515,51.7157],"type":"Point"}
}
