{
  "type": "Feature",
  "properties": {
    "date:inception_lower": "1980-01-01",
    "date:inception_upper": "1980-01-01",
    "iso:country": "GB",
    "wof:name": "OL5 0PX",
    "wof:placetype": "postalcode"
  },
  "geometry": {"coordinates":[-2.04533,53.521106],"type":"Point"}
}
