{
  "type": "Feature",
  "properties": {
    "iso:country":"GB",
    "wof:name":"OL5 0PX",
    "wof:placetype":"postalcode"
},
  "geometry": {"coordinates":[-2.045330053552,53.52110552575994],"type":"Point"}
}