{
  "type": "Feature",
  "properties": {
    "iso:country":"GB",
    "wof:name":"YO26 5JP",
    "wof:placetype":"postalcode"
},
  "geometry": {"coordinates":[-1.12348179908497,53.96151468918715],"type":"Point"}
}