{
  "type": "Feature",
  "properties": {
    "iso:country": "GB",
    "wof:name": "YO26 5JP",
    "wof:placetype": "postalcode"
  },
  "geometry": {"coordinates":[-1.123482,53.961515],"type":"Point"}
}
