{
  "type": "Feature",
  "properties": {
    "iso:country": "GB",
    "wof:name": "RH2 0TL",
    "wof:placetype": "postalcode"
  },
  "geometry": {"coordinates":[-0.176344,51.260848],"type":"Point"}
}
