{
  "type": "Feature",
  "properties": {
    "iso:country":"GB",
    "wof:name":"RH2 0TL",
    "wof:placetype":"postalcode"
},
  "geometry": {"coordinates":[-0.1763438108487,51.26084829633918],"type":"Point"}
}