{
  "type": "Feature",
  "properties": {
    "date:inception_lower": "2014-12-01",
    "date:inception_upper": "2014-12-01",
    "iso:country": "GB",
    "wof:name": "CV21 1FG",
    "wof:placetype": "postalcode"
  },
  "geometry": {"coordinates":[-1.250534,52.383094],"type":"Point"}
}
