{
  "type": "Feature",
  "properties": {
    "iso:country":"GB",
    "wof:name":"WF1 1TZ",
    "wof:placetype":"postalcode"
},
  "geometry": {"coordinates":[-1.49274227747845,53.6804725242535],"type":"Point"}
}