{
  "type": "Feature",
  "properties": {
    "date:inception_lower": "1980-01-01",
    "date:inception_upper": "1980-01-01",
    "iso:country": "GB",
    "wof:name": "WF1 1TZ",
    "wof:placetype": "postalcode"
  },
  "geometry": {"coordinates":[-1.492742,53.680473],"type":"Point"}
}
