{
  "type": "Feature",
  "properties": {
    "iso:country":"GB",
    "wof:name":"CH44 6PY",
    "wof:placetype":"postalcode"
},
  "geometry": {"coordinates":[-3.02591426548651,53.41378779917459],"type":"Point"}
}