{
  "type": "Feature",
  "properties": {
    "iso:country":"GB",
    "wof:name":"WD5 0DB",
    "wof:placetype":"postalcode"
},
  "geometry": {"coordinates":[-0.43250331577222,51.70172546490426],"type":"Point"}
}