{
  "type": "Feature",
  "properties": {
    "iso:country":"GB",
    "wof:name":"CF47 9DH",
    "wof:placetype":"postalcode"
},
  "geometry": {"coordinates":[-3.39258659446902,51.7628812148749],"type":"Point"}
}