{
  "type": "Feature",
  "properties": {
    "iso:country": "GB",
    "wof:name": "CF47 9DH",
    "wof:placetype": "postalcode"
  },
  "geometry": {"coordinates":[-3.392587,51.762881],"type":"Point"}
}
