{
  "type": "Feature",
  "properties": {
    "iso:country": "GB",
    "wof:name": "SL9 0BG",
    "wof:placetype": "postalcode"
  },
  "geometry": {"coordinates":[-0.546517,51.596406],"type":"Point"}
}
