{
  "type": "Feature",
  "properties": {
    "iso:country":"GB",
    "wof:name":"SL9 0BG",
    "wof:placetype":"postalcode"
},
  "geometry": {"coordinates":[-0.54588106511606,51.59661143257661],"type":"Point"}
}