{
  "type": "Feature",
  "properties": {
    "date:inception_lower": "2002-06-01",
    "date:inception_upper": "2002-06-01",
    "iso:country": "GB",
    "wof:name": "SL9 0BG",
    "wof:placetype": "postalcode"
  },
  "geometry": {"coordinates":[-0.546209,51.597014],"type":"Point"}
}
