{
  "type": "Feature",
  "properties": {
    "date:inception_lower":"2000-10-01",
    "date:inception_upper":"2000-10-31",
    "iso:country":"GB",
    "wof:name":"WD18 7PE",
    "wof:placetype":"postalcode"
},
  "geometry": {"coordinates":[-0.424074,51.654009],"type":"Point"}
}