{
  "type": "Feature",
  "properties": {
    "iso:country":"GB",
    "wof:name":"BS31 2QW",
    "wof:placetype":"postalcode"
},
  "geometry": {"coordinates":[-2.51001591445731,51.40822947858673],"type":"Point"}
}