{
  "type": "Feature",
  "properties": {
    "date:inception_lower":"1997-12-01",
    "date:inception_upper":"1997-12-31",
    "iso:country":"GB",
    "wof:name":"BS31 2QW",
    "wof:placetype":"postalcode"
},
  "geometry": {"coordinates":[-2.510016,51.408229],"type":"Point"}
}