{
  "type": "Feature",
  "properties": {
    "date:inception_lower": "2020-11-01",
    "date:inception_upper": "2020-11-01",
    "iso:country": "GB",
    "wof:name": "BS40 6DS",
    "wof:placetype": "postalcode"
  },
  "geometry": {"coordinates":[-2.627451,51.296697],"type":"Point"}
}
