{
  "type": "Feature",
  "properties": {
    "iso:country":"GB",
    "wof:name":"G32 6PX",
    "wof:placetype":"postalcode"
},
  "geometry": {"coordinates":[-4.18299205369787,55.85932244623149],"type":"Point"}
}