{
  "type": "Feature",
  "properties": {
    "iso:country": "GB",
    "wof:name": "FY5 3QS",
    "wof:placetype": "postalcode"
  },
  "geometry": {"coordinates":[-3.035199,53.868361],"type":"Point"}
}
