{
  "type": "Feature",
  "properties": {
    "iso:country":"GB",
    "wof:name":"B44 0HL",
    "wof:placetype":"postalcode"
},
  "geometry": {"coordinates":[-1.87427181302928,52.53673000353614],"type":"Point"}
}