{
  "type": "Feature",
  "properties": {
    "date:inception_lower": "1980-01-01",
    "date:inception_upper": "1980-01-01",
    "iso:country": "GB",
    "wof:name": "GU8 4UU",
    "wof:placetype": "postalcode"
  },
  "geometry": {"coordinates":[-0.623954,51.12006],"type":"Point"}
}
