{
  "type": "Feature",
  "properties": {
    "iso:country":"GB",
    "wof:name":"S20 1BT",
    "wof:placetype":"postalcode"
},
  "geometry": {"coordinates":[-1.3462730364186,53.34867855186658],"type":"Point"}
}