{
  "type": "Feature",
  "properties": {
    "date:inception_lower":"1997-06-01",
    "date:inception_upper":"1997-06-30",
    "iso:country":"GB",
    "wof:name":"S20 1BT",
    "wof:placetype":"postalcode"
},
  "geometry": {"coordinates":[-1.346273,53.348706],"type":"Point"}
}