{
  "type": "Feature",
  "properties": {
    "iso:country": "GB",
    "wof:name": "S20 1BT",
    "wof:placetype": "postalcode"
  },
  "geometry": {"coordinates":[-1.346273,53.348706],"type":"Point"}
}
