{
  "type": "Feature",
  "properties": {
    "iso:country": "GB",
    "wof:name": "CT16 2AX",
    "wof:placetype": "postalcode"
  },
  "geometry": {"coordinates":[1.295025,51.142044],"type":"Point"}
}
