{
  "type": "Feature",
  "properties": {
    "iso:country":"GB",
    "wof:name":"CT16 2AX",
    "wof:placetype":"postalcode"
},
  "geometry": {"coordinates":[1.2950210907234,51.14202733462337],"type":"Point"}
}