{
  "type": "Feature",
  "properties": {
    "date:inception_lower": "1980-01-01",
    "date:inception_upper": "1980-01-01",
    "iso:country": "GB",
    "wof:name": "PL8 2LJ",
    "wof:placetype": "postalcode"
  },
  "geometry": {"coordinates":[-3.983827,50.365501],"type":"Point"}
}
