{
  "type": "Feature",
  "properties": {
    "iso:country":"GB",
    "wof:name":"PL8 2LJ",
    "wof:placetype":"postalcode"
},
  "geometry": {"coordinates":[-3.98382696483376,50.36550133436339],"type":"Point"}
}