{
  "type": "Feature",
  "properties": {
    "iso:country": "GB",
    "wof:name": "WS9 8HY",
    "wof:placetype": "postalcode"
  },
  "geometry": {"coordinates":[-1.918098,52.610853],"type":"Point"}
}
