{
  "type": "Feature",
  "properties": {
    "iso:country":"GB",
    "wof:name":"NN14 3EQ",
    "wof:placetype":"postalcode"
},
  "geometry": {"coordinates":[-0.50218192253231,52.39091460316351],"type":"Point"}
}