{
  "type": "Feature",
  "properties": {
    "iso:country":"GB",
    "wof:name":"GU8 5LT",
    "wof:placetype":"postalcode"
},
  "geometry": {"coordinates":[-0.64775869673637,51.15213042444397],"type":"Point"}
}