{
  "type": "Feature",
  "properties": {
    "date:inception_lower": "1980-01-01",
    "date:inception_upper": "1980-01-01",
    "iso:country": "GB",
    "wof:name": "GU8 5LT",
    "wof:placetype": "postalcode"
  },
  "geometry": {"coordinates":[-0.647759,51.15213],"type":"Point"}
}
