{
  "type": "Feature",
  "properties": {
    "iso:country":"GB",
    "wof:name":"WF1 2PA",
    "wof:placetype":"postalcode"
},
  "geometry": {"coordinates":[-1.50866644628667,53.71454125049516],"type":"Point"}
}