{
  "type": "Feature",
  "properties": {
    "iso:country": "GB",
    "wof:name": "GU8 4PJ",
    "wof:placetype": "postalcode"
  },
  "geometry": {"coordinates":[-0.578253,51.086991],"type":"Point"}
}
