{
  "type": "Feature",
  "properties": {
    "date:inception_lower":"1980-01-01",
    "date:inception_upper":"1980-01-31",
    "iso:country":"GB",
    "wof:name":"BA13 4BD",
    "wof:placetype":"postalcode"
},
  "geometry": {"coordinates":[-2.232661,51.246637],"type":"Point"}
}