{
  "type": "Feature",
  "properties": {
    "iso:country":"GB",
    "wof:name":"BA13 4BD",
    "wof:placetype":"postalcode"
},
  "geometry": {"coordinates":[-2.23266153943749,51.2466369390911],"type":"Point"}
}