{
  "type": "Feature",
  "properties": {
    "date:inception_lower": "1980-01-01",
    "date:inception_upper": "1980-01-01",
    "iso:country": "GB",
    "wof:name": "WA6 7DS",
    "wof:placetype": "postalcode"
  },
  "geometry": {"coordinates":[-2.722442,53.294948],"type":"Point"}
}
