{
  "type": "Feature",
  "properties": {
    "date:inception_lower": "1980-01-01",
    "date:inception_upper": "1980-01-01",
    "iso:country": "GB",
    "wof:name": "MK45 2SD",
    "wof:placetype": "postalcode"
  },
  "geometry": {"coordinates":[-0.490222,52.025733],"type":"Point"}
}
