{
  "type": "Feature",
  "properties": {
    "iso:country":"GB",
    "wof:name":"MK45 2SD",
    "wof:placetype":"postalcode"
},
  "geometry": {"coordinates":[-0.49013085151148,52.02568470090571],"type":"Point"}
}