{
  "type": "Feature",
  "properties": {
    "iso:country": "GB",
    "wof:name": "RG40 1JX",
    "wof:placetype": "postalcode"
  },
  "geometry": {"coordinates":[-0.836733,51.411825],"type":"Point"}
}
