{
  "type": "Feature",
  "properties": {
    "iso:country":"GB",
    "wof:name":"W1U 4DP",
    "wof:placetype":"postalcode"
},
  "geometry": {"coordinates":[-0.15180386217165,51.51843597878766],"type":"Point"}
}