{
  "type": "Feature",
  "properties": {
    "iso:country":"GB",
    "wof:name":"RH1 2JW",
    "wof:placetype":"postalcode"
},
  "geometry": {"coordinates":[-0.16600737798496,51.2475842367766],"type":"Point"}
}