{
  "type": "Feature",
  "properties": {
    "iso:country":"GB",
    "wof:name":"BH23 7HY",
    "wof:placetype":"postalcode"
},
  "geometry": {"coordinates":[-1.76686781296953,50.7538436623391],"type":"Point"}
}