{
  "type": "Feature",
  "properties": {
    "iso:country":"GB",
    "wof:name":"PE3 6FU",
    "wof:placetype":"postalcode"
},
  "geometry": {"coordinates":[-0.25957143095295,52.57362466764462],"type":"Point"}
}