{
  "type": "Feature",
  "properties": {
    "iso:country":"GB",
    "wof:name":"DG16 5DR",
    "wof:placetype":"postalcode"
},
  "geometry": {"coordinates":[-3.0646184977131,54.99746455482278],"type":"Point"}
}