{
  "type": "Feature",
  "properties": {
    "iso:country": "GB",
    "wof:name": "ST9 9JL",
    "wof:placetype": "postalcode"
  },
  "geometry": {"coordinates":[-2.113682,53.052297],"type":"Point"}
}
