{
  "type": "Feature",
  "properties": {
    "date:inception_lower": "2006-10-01",
    "date:inception_upper": "2006-10-01",
    "iso:country": "GB",
    "wof:name": "ST9 9JL",
    "wof:placetype": "postalcode"
  },
  "geometry": {"coordinates":[-2.113935,53.052422],"type":"Point"}
}
