{
  "type": "Feature",
  "properties": {
    "date:inception_lower": "1980-01-01",
    "date:inception_upper": "1980-01-01",
    "iso:country": "GB",
    "wof:name": "SK17 7PP",
    "wof:placetype": "postalcode"
  },
  "geometry": {"coordinates":[-1.901085,53.258679],"type":"Point"}
}
