{
  "type": "Feature",
  "properties": {
    "iso:country":"GB",
    "wof:name":"SK17 7PP",
    "wof:placetype":"postalcode"
},
  "geometry": {"coordinates":[-1.90108526271964,53.25867900887113],"type":"Point"}
}