{
  "type": "Feature",
  "properties": {
    "iso:country":"GB",
    "wof:name":"EC1N 8JR",
    "wof:placetype":"postalcode"
},
  "geometry": {"coordinates":[-0.108695550048,51.5197541285248],"type":"Point"}
}