{
  "type": "Feature",
  "properties": {
    "date:inception_lower": "1980-01-01",
    "date:inception_upper": "1980-01-01",
    "iso:country": "GB",
    "wof:name": "ST13 7PH",
    "wof:placetype": "postalcode"
  },
  "geometry": {"coordinates":[-1.926195,53.072419],"type":"Point"}
}
