{
  "type": "Feature",
  "properties": {
    "iso:country": "GB",
    "wof:name": "NW6 5FN",
    "wof:placetype": "postalcode"
  },
  "geometry": {"coordinates":[-0.195492,51.530206],"type":"Point"}
}
