{
  "type": "Feature",
  "properties": {
    "iso:country":"GB",
    "wof:name":"B90 4RT",
    "wof:placetype":"postalcode"
},
  "geometry": {"coordinates":[-1.80976223173367,52.3985398381466],"type":"Point"}
}