{
  "type": "Feature",
  "properties": {
    "date:inception_lower": "2022-05-01",
    "date:inception_upper": "2022-05-01",
    "iso:country": "GB",
    "wof:name": "BN18 0ZB",
    "wof:placetype": "postalcode"
  },
  "geometry": {"coordinates":[-0.652398,50.852519],"type":"Point"}
}
