{
  "type": "Feature",
  "properties": {
    "iso:country":"GB",
    "wof:name":"G2 4TB",
    "wof:placetype":"postalcode"
},
  "geometry": {"coordinates":[-4.26073599763258,55.86457790201173],"type":"Point"}
}