{
  "type": "Feature",
  "properties": {
    "date:inception_lower": "1980-01-01",
    "date:inception_upper": "1980-01-01",
    "iso:country": "GB",
    "wof:name": "GL54 5RD",
    "wof:placetype": "postalcode"
  },
  "geometry": {"coordinates":[-1.973223,51.95352],"type":"Point"}
}
