{
  "type": "Feature",
  "properties": {
    "iso:country":"GB",
    "wof:name":"NE15 6NG",
    "wof:placetype":"postalcode"
},
  "geometry": {"coordinates":[-1.67424851367324,54.97390387710043],"type":"Point"}
}