{
  "type": "Feature",
  "properties": {
    "date:inception_lower": "1987-04-01",
    "date:inception_upper": "1987-04-01",
    "iso:country": "GB",
    "wof:name": "NE15 6NG",
    "wof:placetype": "postalcode"
  },
  "geometry": {"coordinates":[-1.674248,54.973904],"type":"Point"}
}
