{
  "type": "Feature",
  "properties": {
    "iso:country":"GB",
    "wof:name":"ST16 1UR",
    "wof:placetype":"postalcode"
},
  "geometry": {"coordinates":[-2.14627289822899,52.81262567767624],"type":"Point"}
}