{
  "type": "Feature",
  "properties": {
    "date:inception_lower":"1995-01-01",
    "date:inception_upper":"1995-01-31",
    "iso:country":"GB",
    "wof:name":"ST16 1UR",
    "wof:placetype":"postalcode"
},
  "geometry": {"coordinates":[-2.146273,52.812626],"type":"Point"}
}