{
  "type": "Feature",
  "properties": {
    "iso:country":"GB",
    "wof:name":"RH1 4ET",
    "wof:placetype":"postalcode"
},
  "geometry": {"coordinates":[-0.14191616865199,51.24911973296651],"type":"Point"}
}