{
  "type": "Feature",
  "properties": {
    "iso:country":"GB",
    "wof:name":"UB4 0RA",
    "wof:placetype":"postalcode"
},
  "geometry": {"coordinates":[-0.41334742295779,51.52141097367005],"type":"Point"}
}