{
  "type": "Feature",
  "properties": {
    "date:inception_lower":"1993-01-01",
    "date:inception_upper":"1993-01-31",
    "iso:country":"GB",
    "wof:name":"L26 7XT",
    "wof:placetype":"postalcode"
},
  "geometry": {"coordinates":[-2.841386,53.373424],"type":"Point"}
}