{
  "type": "Feature",
  "properties": {
    "iso:country":"GB",
    "wof:name":"SW4 6RZ",
    "wof:placetype":"postalcode"
},
  "geometry": {"coordinates":[-0.12353109820888,51.47196319759553],"type":"Point"}
}