{
  "type": "Feature",
  "properties": {
    "iso:country":"GB",
    "wof:name":"HP22 6HJ",
    "wof:placetype":"postalcode"
},
  "geometry": {"coordinates":[-0.73717833878415,51.76617831346217],"type":"Point"}
}