{
  "type": "Feature",
  "properties": {
    "iso:country": "GB",
    "wof:name": "HP22 6HJ",
    "wof:placetype": "postalcode"
  },
  "geometry": {"coordinates":[-0.737178,51.766178],"type":"Point"}
}
