{
  "type": "Feature",
  "properties": {
    "date:inception_lower": "1992-01-01",
    "date:inception_upper": "1992-01-01",
    "iso:country": "GB",
    "wof:name": "PE2 5XH",
    "wof:placetype": "postalcode"
  },
  "geometry": {"coordinates":[-0.302417,52.549405],"type":"Point"}
}
