{
  "type": "Feature",
  "properties": {
    "iso:country":"GB",
    "wof:name":"PE2 5XH",
    "wof:placetype":"postalcode"
},
  "geometry": {"coordinates":[-0.30241711340108,52.54940495956072],"type":"Point"}
}