{
  "type": "Feature",
  "properties": {
    "iso:country":"GB",
    "wof:name":"OL2 6TR",
    "wof:placetype":"postalcode"
},
  "geometry": {"coordinates":[-2.13047411759435,53.57585363553238],"type":"Point"}
}