{
  "type": "Feature",
  "properties": {
    "date:inception_lower": "1980-01-01",
    "date:inception_upper": "1980-01-01",
    "iso:country": "GB",
    "wof:name": "OL2 6TR",
    "wof:placetype": "postalcode"
  },
  "geometry": {"coordinates":[-2.130474,53.575854],"type":"Point"}
}
