{
  "type": "Feature",
  "properties": {
    "iso:country": "GB",
    "wof:name": "OL9 9JG",
    "wof:placetype": "postalcode"
  },
  "geometry": {"coordinates":[-2.149552,53.542925],"type":"Point"}
}
