{
  "type": "Feature",
  "properties": {
    "iso:country": "GB",
    "wof:name": "CT15 5EJ",
    "wof:placetype": "postalcode"
  },
  "geometry": {"coordinates":[1.318444,51.146185],"type":"Point"}
}
