{
  "type": "Feature",
  "properties": {
    "iso:country":"GB",
    "wof:name":"CT15 5EJ",
    "wof:placetype":"postalcode"
},
  "geometry": {"coordinates":[1.31837393258857,51.14583708361086],"type":"Point"}
}