{
  "type": "Feature",
  "properties": {
    "iso:country": "GB",
    "wof:name": "ME19 6NG",
    "wof:placetype": "postalcode"
  },
  "geometry": {"coordinates":[0.401919,51.293209],"type":"Point"}
}
