{
  "type": "Feature",
  "properties": {
    "iso:country":"GB",
    "wof:name":"ME19 6NG",
    "wof:placetype":"postalcode"
},
  "geometry": {"coordinates":[0.40191886350868,51.29320900979554],"type":"Point"}
}