{
  "type": "Feature",
  "properties": {
    "iso:country":"GB",
    "wof:name":"B31 4HE",
    "wof:placetype":"postalcode"
},
  "geometry": {"coordinates":[-1.9667676877146,52.40170853953248],"type":"Point"}
}