{
  "type": "Feature",
  "properties": {
    "iso:country":"GB",
    "wof:name":"NG12 3TD",
    "wof:placetype":"postalcode"
},
  "geometry": {"coordinates":[-1.03395279666195,52.90385318310749],"type":"Point"}
}