{
  "type": "Feature",
  "properties": {
    "date:inception_lower": "1990-02-01",
    "date:inception_upper": "1990-02-01",
    "iso:country": "GB",
    "wof:name": "NG12 3TD",
    "wof:placetype": "postalcode"
  },
  "geometry": {"coordinates":[-1.033953,52.903853],"type":"Point"}
}
