{
  "type": "Feature",
  "properties": {
    "iso:country": "GB",
    "wof:name": "LE5 3QW",
    "wof:placetype": "postalcode"
  },
  "geometry": {"coordinates":[-1.104594,52.638479],"type":"Point"}
}
