{
  "type": "Feature",
  "properties": {
    "iso:country":"GB",
    "wof:name":"ME10 4EE",
    "wof:placetype":"postalcode"
},
  "geometry": {"coordinates":[0.73423548538749,51.33250593135686],"type":"Point"}
}