{
  "type": "Feature",
  "properties": {
    "iso:country": "GB",
    "wof:name": "ME10 4EE",
    "wof:placetype": "postalcode"
  },
  "geometry": {"coordinates":[0.734236,51.332506],"type":"Point"}
}
