{
  "type": "Feature",
  "properties": {
    "iso:country": "GB",
    "wof:name": "CH64 2UX",
    "wof:placetype": "postalcode"
  },
  "geometry": {"coordinates":[-3.015742,53.294968],"type":"Point"}
}
