{
  "type": "Feature",
  "properties": {
    "iso:country": "GB",
    "wof:name": "N7 8ST",
    "wof:placetype": "postalcode"
  },
  "geometry": {"coordinates":[-0.11679,51.546808],"type":"Point"}
}
