{
  "type": "Feature",
  "properties": {
    "date:inception_lower": "2020-10-01",
    "date:inception_upper": "2020-10-01",
    "iso:country": "GB",
    "wof:name": "CA11 9SB",
    "wof:placetype": "postalcode"
  },
  "geometry": {"coordinates":[-2.882807,54.711541],"type":"Point"}
}
