{
  "type": "Feature",
  "properties": {
    "date:inception_lower": "1980-01-01",
    "date:inception_upper": "1980-01-01",
    "iso:country": "GB",
    "wof:name": "SA5 8AN",
    "wof:placetype": "postalcode"
  },
  "geometry": {"coordinates":[-3.958751,51.640523],"type":"Point"}
}
