{
  "type": "Feature",
  "properties": {
    "iso:country": "GB",
    "wof:name": "SA5 8AN",
    "wof:placetype": "postalcode"
  },
  "geometry": {"coordinates":[-3.958751,51.640523],"type":"Point"}
}
