{
  "type": "Feature",
  "properties": {
    "iso:country":"GB",
    "wof:name":"KT21 2HQ",
    "wof:placetype":"postalcode"
},
  "geometry": {"coordinates":[-0.31438606337446,51.31753872686878],"type":"Point"}
}