{
  "type": "Feature",
  "properties": {
    "date:inception_lower":"1980-01-01",
    "date:inception_upper":"1980-01-31",
    "iso:country":"GB",
    "wof:name":"KT21 2HQ",
    "wof:placetype":"postalcode"
},
  "geometry": {"coordinates":[-0.314386,51.317539],"type":"Point"}
}