{
  "type": "Feature",
  "properties": {
    "iso:country":"GB",
    "wof:name":"IP12 1BU",
    "wof:placetype":"postalcode"
},
  "geometry": {"coordinates":[1.31853606446113,52.09170052994726],"type":"Point"}
}