{
  "type": "Feature",
  "properties": {
    "iso:country":"GB",
    "wof:name":"CO11 2ES",
    "wof:placetype":"postalcode"
},
  "geometry": {"coordinates":[1.0490389819712,51.93876139518441],"type":"Point"}
}