{
  "type": "Feature",
  "properties": {
    "iso:country": "GB",
    "wof:name": "SA2 8EJ",
    "wof:placetype": "postalcode"
  },
  "geometry": {"coordinates":[-3.996975,51.599979],"type":"Point"}
}
