{
  "type": "Feature",
  "properties": {
    "iso:country":"GB",
    "wof:name":"N1 4ST",
    "wof:placetype":"postalcode"
},
  "geometry": {"coordinates":[-0.08020925590753,51.54589129859865],"type":"Point"}
}