{
  "type": "Feature",
  "properties": {
    "date:inception_lower": "1994-05-01",
    "date:inception_upper": "1994-05-01",
    "iso:country": "GB",
    "wof:name": "N1 4ST",
    "wof:placetype": "postalcode"
  },
  "geometry": {"coordinates":[-0.080209,51.545891],"type":"Point"}
}
