{
  "type": "Feature",
  "properties": {
    "date:inception_lower": "2008-09-01",
    "date:inception_upper": "2008-09-01",
    "iso:country": "GB",
    "wof:name": "DD6 8SP",
    "wof:placetype": "postalcode"
  },
  "geometry": {"coordinates":[-2.931268,56.407897],"type":"Point"}
}
