{
  "type": "Feature",
  "properties": {
    "iso:country":"GB",
    "wof:name":"DD6 8SP",
    "wof:placetype":"postalcode"
},
  "geometry": {"coordinates":[-2.93126783202195,56.40789691664846],"type":"Point"}
}