{
  "type": "Feature",
  "properties": {
    "iso:country":"GB",
    "wof:name":"PE28 2NR",
    "wof:placetype":"postalcode"
},
  "geometry": {"coordinates":[-0.1605086854731,52.35392025431676],"type":"Point"}
}