{
  "type": "Feature",
  "properties": {
    "iso:country":"GB",
    "wof:name":"LL30 1HJ",
    "wof:placetype":"postalcode"
},
  "geometry": {"coordinates":[-3.81837356680919,53.31469080220554],"type":"Point"}
}