{
  "type": "Feature",
  "properties": {
    "date:inception_lower": "2018-02-01",
    "date:inception_upper": "2018-02-01",
    "iso:country": "GB",
    "wof:name": "CW10 9RJ",
    "wof:placetype": "postalcode"
  },
  "geometry": {"coordinates":[-2.406862,53.228189],"type":"Point"}
}
