{
  "type": "Feature",
  "properties": {
    "iso:country":"GB",
    "wof:name":"N1 4JL",
    "wof:placetype":"postalcode"
},
  "geometry": {"coordinates":[-0.07674147225521,51.54433274613315],"type":"Point"}
}