{
  "type": "Feature",
  "properties": {
    "date:inception_lower":"2000-10-01",
    "date:inception_upper":"2000-10-31",
    "iso:country":"GB",
    "wof:name":"W1T 7PL",
    "wof:placetype":"postalcode"
},
  "geometry": {"coordinates":[-0.134168,51.520747],"type":"Point"}
}