{
  "type": "Feature",
  "properties": {
    "iso:country":"GB",
    "wof:name":"W1T 7PL",
    "wof:placetype":"postalcode"
},
  "geometry": {"coordinates":[-0.13416799155194,51.52074660556976],"type":"Point"}
}