{
  "type": "Feature",
  "properties": {
    "iso:country":"GB",
    "wof:name":"TN30 6PE",
    "wof:placetype":"postalcode"
},
  "geometry": {"coordinates":[0.69642517913983,51.08463451105],"type":"Point"}
}