{
  "type": "Feature",
  "properties": {
    "date:inception_lower":"1995-07-01",
    "date:inception_upper":"1995-07-31",
    "iso:country":"GB",
    "wof:name":"RG31 5UZ",
    "wof:placetype":"postalcode"
},
  "geometry": {"coordinates":[-1.05105,51.461889],"type":"Point"}
}