{
  "type": "Feature",
  "properties": {
    "iso:country":"GB",
    "wof:name":"DD2 2LD",
    "wof:placetype":"postalcode"
},
  "geometry": {"coordinates":[-2.99342165598902,56.46470019752812],"type":"Point"}
}