{
  "type": "Feature",
  "properties": {
    "iso:country": "GB",
    "wof:name": "DD2 2LD",
    "wof:placetype": "postalcode"
  },
  "geometry": {"coordinates":[-2.993422,56.4647],"type":"Point"}
}
