{
  "type": "Feature",
  "properties": {
    "iso:country": "GB",
    "wof:name": "SG8 5AX",
    "wof:placetype": "postalcode"
  },
  "geometry": {"coordinates":[-0.024703,52.048482],"type":"Point"}
}
