{
  "type": "Feature",
  "properties": {
    "date:inception_lower":"2004-10-01",
    "date:inception_upper":"2004-10-31",
    "iso:country":"GB",
    "wof:name":"SG8 5AX",
    "wof:placetype":"postalcode"
},
  "geometry": {"coordinates":[-0.024703,52.048482],"type":"Point"}
}