{
  "type": "Feature",
  "properties": {
    "iso:country":"GB",
    "wof:name":"GU1 1HQ",
    "wof:placetype":"postalcode"
},
  "geometry": {"coordinates":[-0.57374612938128,51.24449492036623],"type":"Point"}
}