{
  "type": "Feature",
  "properties": {
    "iso:country":"GB",
    "wof:name":"PL34 0DE",
    "wof:placetype":"postalcode"
},
  "geometry": {"coordinates":[-4.75216811103538,50.66586767217136],"type":"Point"}
}