{
  "type": "Feature",
  "properties": {
    "iso:country":"GB",
    "wof:name":"HA2 7PB",
    "wof:placetype":"postalcode"
},
  "geometry": {"coordinates":[-0.37120961263137,51.58213333316868],"type":"Point"}
}