{
  "type": "Feature",
  "properties": {
    "date:inception_lower": "1990-08-01",
    "date:inception_upper": "1990-08-01",
    "iso:country": "GB",
    "wof:name": "AB32 6RR",
    "wof:placetype": "postalcode"
  },
  "geometry": {"coordinates":[-2.318078,57.148701],"type":"Point"}
}
