{
  "type": "Feature",
  "properties": {
    "iso:country":"GB",
    "wof:name":"CA2 5JW",
    "wof:placetype":"postalcode"
},
  "geometry": {"coordinates":[-2.94024286720088,54.88548248043791],"type":"Point"}
}