{
  "type": "Feature",
  "properties": {
    "date:inception_lower": "1980-01-01",
    "date:inception_upper": "1980-01-01",
    "iso:country": "GB",
    "wof:name": "L36 3RX",
    "wof:placetype": "postalcode"
  },
  "geometry": {"coordinates":[-2.853043,53.421216],"type":"Point"}
}
