{
  "type": "Feature",
  "properties": {
    "date:inception_lower":"1987-04-01",
    "date:inception_upper":"1987-04-30",
    "iso:country":"GB",
    "wof:name":"BD21 1SP",
    "wof:placetype":"postalcode"
},
  "geometry": {"coordinates":[-1.912782,53.860276],"type":"Point"}
}