{
  "type": "Feature",
  "properties": {
    "iso:country":"GB",
    "wof:name":"BD21 1SP",
    "wof:placetype":"postalcode"
},
  "geometry": {"coordinates":[-1.91278182149297,53.86027627958624],"type":"Point"}
}