{
  "type": "Feature",
  "properties": {
    "iso:country":"GB",
    "wof:name":"PE32 2AG",
    "wof:placetype":"postalcode"
},
  "geometry": {"coordinates":[0.68953406143211,52.70265462603169],"type":"Point"}
}