{
  "type": "Feature",
  "properties": {
    "iso:country": "GB",
    "wof:name": "PE32 2AG",
    "wof:placetype": "postalcode"
  },
  "geometry": {"coordinates":[0.689534,52.702655],"type":"Point"}
}
