{
  "type": "Feature",
  "properties": {
    "iso:country": "GB",
    "wof:name": "CM16 6HF",
    "wof:placetype": "postalcode"
  },
  "geometry": {"coordinates":[0.167741,51.717622],"type":"Point"}
}
