{
  "type": "Feature",
  "properties": {
    "iso:country":"GB",
    "wof:name":"CM16 6HF",
    "wof:placetype":"postalcode"
},
  "geometry": {"coordinates":[0.16774129776234,51.7176222076365],"type":"Point"}
}