{
  "type": "Feature",
  "properties": {
    "date:inception_lower": "2005-09-01",
    "date:inception_upper": "2005-09-01",
    "iso:country": "GB",
    "wof:name": "CM16 6HF",
    "wof:placetype": "postalcode"
  },
  "geometry": {"coordinates":[0.167741,51.717622],"type":"Point"}
}
