{
  "type": "Feature",
  "properties": {
    "iso:country":"GB",
    "wof:name":"WF17 8EE",
    "wof:placetype":"postalcode"
},
  "geometry": {"coordinates":[-1.65345972269577,53.71979290982175],"type":"Point"}
}