{
  "type": "Feature",
  "properties": {
    "iso:country":"GB",
    "wof:name":"M20 2JD",
    "wof:placetype":"postalcode"
},
  "geometry": {"coordinates":[-2.24553814471258,53.42747138118774],"type":"Point"}
}