{
  "type": "Feature",
  "properties": {
    "iso:country": "GB",
    "wof:name": "M20 2JD",
    "wof:placetype": "postalcode"
  },
  "geometry": {"coordinates":[-2.245538,53.427471],"type":"Point"}
}
