{
  "type": "Feature",
  "properties": {
    "date:inception_lower":"2009-06-01",
    "date:inception_upper":"2009-06-30",
    "iso:country":"GB",
    "wof:name":"M20 2JD",
    "wof:placetype":"postalcode"
},
  "geometry": {"coordinates":[-2.245538,53.427471],"type":"Point"}
}