{
  "type": "Feature",
  "properties": {
    "iso:country":"GB",
    "wof:name":"RG6 5UR",
    "wof:placetype":"postalcode"
},
  "geometry": {"coordinates":[-0.93466800984727,51.42979530193255],"type":"Point"}
}