{
  "type": "Feature",
  "properties": {
    "date:inception_lower": "1992-10-01",
    "date:inception_upper": "1992-10-01",
    "iso:country": "GB",
    "wof:name": "G52 4DZ",
    "wof:placetype": "postalcode"
  },
  "geometry": {"coordinates":[-4.370116,55.862379],"type":"Point"}
}
