{
  "type": "Feature",
  "properties": {
    "iso:country": "GB",
    "wof:name": "CH2 4BF",
    "wof:placetype": "postalcode"
  },
  "geometry": {"coordinates":[-2.823862,53.223889],"type":"Point"}
}
