{
  "type": "Feature",
  "properties": {
    "iso:country": "GB",
    "wof:name": "LL61 5YU",
    "wof:placetype": "postalcode"
  },
  "geometry": {"coordinates":[-4.192869,53.224598],"type":"Point"}
}
