{
  "type": "Feature",
  "properties": {
    "iso:country":"GB",
    "wof:name":"LL61 5YU",
    "wof:placetype":"postalcode"
},
  "geometry": {"coordinates":[-4.19267411134644,53.22469249425388],"type":"Point"}
}