{
  "type": "Feature",
  "properties": {
    "iso:country":"GB",
    "wof:name":"SA38 9BE",
    "wof:placetype":"postalcode"
},
  "geometry": {"coordinates":[-4.47147479697857,52.03688499340845],"type":"Point"}
}