{
  "type": "Feature",
  "properties": {
    "iso:country":"GB",
    "wof:name":"IG7 4AE",
    "wof:placetype":"postalcode"
},
  "geometry": {"coordinates":[0.11260337274004,51.60991501302985],"type":"Point"}
}