{
  "type": "Feature",
  "properties": {
    "date:inception_lower": "1980-01-01",
    "date:inception_upper": "1980-01-01",
    "iso:country": "GB",
    "wof:name": "IG7 4AE",
    "wof:placetype": "postalcode"
  },
  "geometry": {"coordinates":[0.112603,51.609915],"type":"Point"}
}
