{
  "type": "Feature",
  "properties": {
    "iso:country":"GB",
    "wof:name":"TA18 7TE",
    "wof:placetype":"postalcode"
},
  "geometry": {"coordinates":[-2.7198790681482,50.88059171792617],"type":"Point"}
}