{
  "type": "Feature",
  "properties": {
    "date:inception_lower": "1980-01-01",
    "date:inception_upper": "1980-01-01",
    "iso:country": "GB",
    "wof:name": "TA18 7TE",
    "wof:placetype": "postalcode"
  },
  "geometry": {"coordinates":[-2.719879,50.880592],"type":"Point"}
}
