{
  "type": "Feature",
  "properties": {
    "iso:country":"GB",
    "wof:name":"KT17 4PY",
    "wof:placetype":"postalcode"
},
  "geometry": {"coordinates":[-0.25902594157485,51.33033469222933],"type":"Point"}
}