{
  "type": "Feature",
  "properties": {
    "date:inception_lower": "1980-01-01",
    "date:inception_upper": "1980-01-01",
    "iso:country": "GB",
    "wof:name": "BN2 4BR",
    "wof:placetype": "postalcode"
  },
  "geometry": {"coordinates":[-0.115886,50.839334],"type":"Point"}
}
