{
  "type": "Feature",
  "properties": {
    "iso:country":"GB",
    "wof:name":"BN2 4BR",
    "wof:placetype":"postalcode"
},
  "geometry": {"coordinates":[-0.11588629838171,50.83933392265579],"type":"Point"}
}