{
  "type": "Feature",
  "properties": {
    "iso:country": "GB",
    "wof:name": "SY20 9SX",
    "wof:placetype": "postalcode"
  },
  "geometry": {"coordinates":[-3.841454,52.654437],"type":"Point"}
}
