{
  "type": "Feature",
  "properties": {
    "iso:country": "GB",
    "wof:name": "GL56 0BY",
    "wof:placetype": "postalcode"
  },
  "geometry": {"coordinates":[-1.703802,51.990184],"type":"Point"}
}
