{
  "type": "Feature",
  "properties": {
    "iso:country":"GB",
    "wof:name":"BA3 5TH",
    "wof:placetype":"postalcode"
},
  "geometry": {"coordinates":[-2.44635116303847,51.24258178699321],"type":"Point"}
}