{
  "type": "Feature",
  "properties": {
    "iso:country":"GB",
    "wof:name":"IP13 0BD",
    "wof:placetype":"postalcode"
},
  "geometry": {"coordinates":[1.42084639390363,52.17395943385343],"type":"Point"}
}