{
  "type": "Feature",
  "properties": {
    "iso:country": "GB",
    "wof:name": "EH14 5BD",
    "wof:placetype": "postalcode"
  },
  "geometry": {"coordinates":[-3.275556,55.907507],"type":"Point"}
}
