{
  "type": "Feature",
  "properties": {
    "date:inception_lower": "1980-01-01",
    "date:inception_upper": "1980-01-01",
    "iso:country": "GB",
    "wof:name": "PH21 1EN",
    "wof:placetype": "postalcode"
  },
  "geometry": {"coordinates":[-4.053279,57.078692],"type":"Point"}
}
