{
  "type": "Feature",
  "properties": {
    "iso:country":"GB",
    "wof:name":"PH21 1EN",
    "wof:placetype":"postalcode"
},
  "geometry": {"coordinates":[-4.05378934722459,57.07861675759321],"type":"Point"}
}