{
  "type": "Feature",
  "properties": {
    "iso:country":"GB",
    "wof:name":"GU46 7TB",
    "wof:placetype":"postalcode"
},
  "geometry": {"coordinates":[-0.83000604389219,51.34578298892684],"type":"Point"}
}