{
  "type": "Feature",
  "properties": {
    "date:inception_lower": "1980-01-01",
    "date:inception_upper": "1980-01-01",
    "iso:country": "GB",
    "wof:name": "WA5 1RF",
    "wof:placetype": "postalcode"
  },
  "geometry": {"coordinates":[-2.651927,53.391373],"type":"Point"}
}
