{
  "type": "Feature",
  "properties": {
    "iso:country":"GB",
    "wof:name":"SW7 5BW",
    "wof:placetype":"postalcode"
},
  "geometry": {"coordinates":[-0.18216081049687,51.49485552651934],"type":"Point"}
}