{
  "type": "Feature",
  "properties": {
    "date:inception_lower": "1986-07-01",
    "date:inception_upper": "1986-07-01",
    "iso:country": "GB",
    "wof:name": "TA1 2RA",
    "wof:placetype": "postalcode"
  },
  "geometry": {"coordinates":[-3.073912,51.01223],"type":"Point"}
}
