{
  "type": "Feature",
  "properties": {
    "iso:country":"GB",
    "wof:name":"ML6 6GA",
    "wof:placetype":"postalcode"
},
  "geometry": {"coordinates":[-3.97751394080943,55.88133692673929],"type":"Point"}
}