{
  "type": "Feature",
  "properties": {
    "date:inception_lower": "2005-01-01",
    "date:inception_upper": "2005-01-01",
    "iso:country": "GB",
    "wof:name": "ML6 6GA",
    "wof:placetype": "postalcode"
  },
  "geometry": {"coordinates":[-3.977514,55.881337],"type":"Point"}
}
