{
  "type": "Feature",
  "properties": {
    "date:inception_lower": "1980-01-01",
    "date:inception_upper": "1980-01-01",
    "iso:country": "GB",
    "wof:name": "PE13 2DX",
    "wof:placetype": "postalcode"
  },
  "geometry": {"coordinates":[0.168259,52.666079],"type":"Point"}
}
