{
  "type": "Feature",
  "properties": {
    "date:inception_lower":"2007-09-01",
    "date:inception_upper":"2007-09-30",
    "iso:country":"GB",
    "wof:name":"DD2 1EG",
    "wof:placetype":"postalcode"
},
  "geometry": {"coordinates":[-3.056666,56.470431],"type":"Point"}
}