{
  "type": "Feature",
  "properties": {
    "date:inception_lower": "2022-02-01",
    "date:inception_upper": "2022-02-01",
    "iso:country": "GB",
    "wof:name": "CB5 8XB",
    "wof:placetype": "postalcode"
  },
  "geometry": {"coordinates":[0.180631,52.211929],"type":"Point"}
}
