{
  "type": "Feature",
  "properties": {
    "iso:country":"GB",
    "wof:name":"TW17 8AA",
    "wof:placetype":"postalcode"
},
  "geometry": {"coordinates":[-0.44399232443785,51.39694587003503],"type":"Point"}
}