{
  "type": "Feature",
  "properties": {
    "iso:country":"GB",
    "wof:name":"AL2 1DA",
    "wof:placetype":"postalcode"
},
  "geometry": {"coordinates":[-0.28260398190281,51.71443078001955],"type":"Point"}
}