{
  "type": "Feature",
  "properties": {
    "date:inception_lower":"1980-01-01",
    "date:inception_upper":"1980-01-31",
    "iso:country":"GB",
    "wof:name":"AL2 1DA",
    "wof:placetype":"postalcode"
},
  "geometry": {"coordinates":[-0.282604,51.714431],"type":"Point"}
}