{
  "type": "Feature",
  "properties": {
    "date:inception_lower": "2019-10-01",
    "date:inception_upper": "2019-10-01",
    "iso:country": "GB",
    "wof:name": "LL65 2ZA",
    "wof:placetype": "postalcode"
  },
  "geometry": {"coordinates":[-4.629376,53.287739],"type":"Point"}
}
