{
  "type": "Feature",
  "properties": {
    "iso:country": "GB",
    "wof:name": "LL65 2ZA",
    "wof:placetype": "postalcode"
  },
  "geometry": {"coordinates":[-4.619889,53.274937],"type":"Point"}
}
