{
  "type": "Feature",
  "properties": {
    "date:inception_lower": "1998-06-01",
    "date:inception_upper": "1998-06-01",
    "iso:country": "GB",
    "wof:name": "YO42 2XG",
    "wof:placetype": "postalcode"
  },
  "geometry": {"coordinates":[-0.788344,53.932537],"type":"Point"}
}
