{
  "type": "Feature",
  "properties": {
    "iso:country":"GB",
    "wof:name":"YO42 2XG",
    "wof:placetype":"postalcode"
},
  "geometry": {"coordinates":[-0.78834439700574,53.93253668837615],"type":"Point"}
}