{
  "type": "Feature",
  "properties": {
    "iso:country":"GB",
    "wof:name":"SK6 3DX",
    "wof:placetype":"postalcode"
},
  "geometry": {"coordinates":[-2.10139927907194,53.41061179984502],"type":"Point"}
}