{
  "type": "Feature",
  "properties": {
    "iso:country":"GB",
    "wof:name":"L15 8JR",
    "wof:placetype":"postalcode"
},
  "geometry": {"coordinates":[-2.91719316146393,53.39751276765389],"type":"Point"}
}