{
  "type": "Feature",
  "properties": {
    "iso:country":"GB",
    "wof:name":"ZE2 9UA",
    "wof:placetype":"postalcode"
},
  "geometry": {"coordinates":[-1.36633947447767,60.39402579919157],"type":"Point"}
}