{
  "type": "Feature",
  "properties": {
    "date:inception_lower": "2009-02-01",
    "date:inception_upper": "2009-02-01",
    "iso:country": "GB",
    "wof:name": "ZE2 9UA",
    "wof:placetype": "postalcode"
  },
  "geometry": {"coordinates":[-1.366339,60.394026],"type":"Point"}
}
