{
  "type": "Feature",
  "properties": {
    "iso:country":"GB",
    "wof:name":"SA61 1HZ",
    "wof:placetype":"postalcode"
},
  "geometry": {"coordinates":[-4.98984612260426,51.79832711139442],"type":"Point"}
}