{
  "type": "Feature",
  "properties": {
    "date:inception_lower":"2010-09-01",
    "date:inception_upper":"2010-09-30",
    "iso:country":"GB",
    "wof:name":"WC1H 9NA",
    "wof:placetype":"postalcode"
},
  "geometry": {"coordinates":[-0.127938,51.525036],"type":"Point"}
}