{
  "type": "Feature",
  "properties": {
    "iso:country":"GB",
    "wof:name":"HP1 2PG",
    "wof:placetype":"postalcode"
},
  "geometry": {"coordinates":[-0.4977353441797,51.75865067393792],"type":"Point"}
}