{
  "type": "Feature",
  "properties": {
    "date:inception_lower":"1980-01-01",
    "date:inception_upper":"1980-01-31",
    "iso:country":"GB",
    "wof:name":"WA11 7HT",
    "wof:placetype":"postalcode"
},
  "geometry": {"coordinates":[-2.795059,53.46851],"type":"Point"}
}