{
  "type": "Feature",
  "properties": {
    "iso:country":"GB",
    "wof:name":"NP20 5LD",
    "wof:placetype":"postalcode"
},
  "geometry": {"coordinates":[-2.99452117194936,51.59525851741441],"type":"Point"}
}