{
  "type": "Feature",
  "properties": {
    "date:inception_lower": "1980-01-01",
    "date:inception_upper": "1980-01-01",
    "iso:country": "GB",
    "wof:name": "SG4 7JR",
    "wof:placetype": "postalcode"
  },
  "geometry": {"coordinates":[-0.238295,51.924724],"type":"Point"}
}
