{
  "type": "Feature",
  "properties": {
    "iso:country": "GB",
    "wof:name": "SA61 1ST",
    "wof:placetype": "postalcode"
  },
  "geometry": {"coordinates":[-4.973225,51.799644],"type":"Point"}
}
