{
  "type": "Feature",
  "properties": {
    "date:inception_lower": "2005-10-01",
    "date:inception_upper": "2005-10-01",
    "iso:country": "GB",
    "wof:name": "NN14 1RR",
    "wof:placetype": "postalcode"
  },
  "geometry": {"coordinates":[-0.771007,52.436406],"type":"Point"}
}
