{
  "type": "Feature",
  "properties": {
    "iso:country":"GB",
    "wof:name":"NN14 1RR",
    "wof:placetype":"postalcode"
},
  "geometry": {"coordinates":[-0.77100666900862,52.43640550890134],"type":"Point"}
}