{
  "type": "Feature",
  "properties": {
    "iso:country":"GB",
    "wof:name":"TQ12 5SL",
    "wof:placetype":"postalcode"
},
  "geometry": {"coordinates":[-3.63849979465683,50.49075058235412],"type":"Point"}
}