{
  "type": "Feature",
  "properties": {
    "iso:country":"GB",
    "wof:name":"BL9 0RW",
    "wof:placetype":"postalcode"
},
  "geometry": {"coordinates":[-2.29006375773923,53.58989118918171],"type":"Point"}
}