{
  "type": "Feature",
  "properties": {
    "iso:country": "GB",
    "wof:name": "CT14 0JL",
    "wof:placetype": "postalcode"
  },
  "geometry": {"coordinates":[1.289682,51.217683],"type":"Point"}
}
