{
  "type": "Feature",
  "properties": {
    "iso:country":"GB",
    "wof:name":"NP8 1EF",
    "wof:placetype":"postalcode"
},
  "geometry": {"coordinates":[-3.10669970542116,51.84086452770596],"type":"Point"}
}