{
  "type": "Feature",
  "properties": {
    "date:inception_lower": "1980-01-01",
    "date:inception_upper": "1980-01-01",
    "iso:country": "GB",
    "wof:name": "NP8 1EF",
    "wof:placetype": "postalcode"
  },
  "geometry": {"coordinates":[-3.1067,51.840865],"type":"Point"}
}
