{
  "type": "Feature",
  "properties": {
    "date:inception_lower": "1980-01-01",
    "date:inception_upper": "1980-01-01",
    "iso:country": "GB",
    "wof:name": "L7 0JQ",
    "wof:placetype": "postalcode"
  },
  "geometry": {"coordinates":[-2.934984,53.412575],"type":"Point"}
}
