{
  "type": "Feature",
  "properties": {
    "iso:country":"GB",
    "wof:name":"BS24 7JS",
    "wof:placetype":"postalcode"
},
  "geometry": {"coordinates":[-2.89818118677375,51.33631737775956],"type":"Point"}
}