{
  "type": "Feature",
  "properties": {
    "date:inception_lower":"2014-06-01",
    "date:inception_upper":"2014-06-30",
    "iso:country":"GB",
    "wof:name":"BS24 7JS",
    "wof:placetype":"postalcode"
},
  "geometry": {"coordinates":[-2.898244,51.336296],"type":"Point"}
}