{
  "type": "Feature",
  "properties": {
    "iso:country":"GB",
    "wof:name":"M8 5ED",
    "wof:placetype":"postalcode"
},
  "geometry": {"coordinates":[-2.24222846168253,53.51754261968397],"type":"Point"}
}