{
  "type": "Feature",
  "properties": {
    "date:inception_lower":"1994-12-01",
    "date:inception_upper":"1994-12-31",
    "iso:country":"GB",
    "wof:name":"BN2 4BW",
    "wof:placetype":"postalcode"
},
  "geometry": {"coordinates":[-0.112844,50.83834],"type":"Point"}
}