{
  "type": "Feature",
  "properties": {
    "iso:country":"GB",
    "wof:name":"BN2 4BW",
    "wof:placetype":"postalcode"
},
  "geometry": {"coordinates":[-0.11284425447773,50.83834044478211],"type":"Point"}
}