{
  "type": "Feature",
  "properties": {
    "date:inception_lower": "2022-03-01",
    "date:inception_upper": "2022-03-01",
    "iso:country": "GB",
    "wof:name": "NE15 9FE",
    "wof:placetype": "postalcode"
  },
  "geometry": {"coordinates":[-1.730541,54.998491],"type":"Point"}
}
