{
  "type": "Feature",
  "properties": {
    "iso:country":"GB",
    "wof:name":"S36 9AX",
    "wof:placetype":"postalcode"
},
  "geometry": {"coordinates":[-1.63491367842072,53.51616230953383],"type":"Point"}
}