{
  "type": "Feature",
  "properties": {
    "iso:country":"GB",
    "wof:name":"CW4 8PA",
    "wof:placetype":"postalcode"
},
  "geometry": {"coordinates":[-2.33959685989093,53.22711609938499],"type":"Point"}
}