{
  "type": "Feature",
  "properties": {
    "iso:country": "GB",
    "wof:name": "S74 9DR",
    "wof:placetype": "postalcode"
  },
  "geometry": {"coordinates":[-1.444735,53.498281],"type":"Point"}
}
