{
  "type": "Feature",
  "properties": {
    "iso:country":"GB",
    "wof:name":"SA14 9NA",
    "wof:placetype":"postalcode"
},
  "geometry": {"coordinates":[-4.10298898823888,51.67766678670181],"type":"Point"}
}