{
  "type": "Feature",
  "properties": {
    "date:inception_lower": "1980-01-01",
    "date:inception_upper": "1980-01-01",
    "iso:country": "GB",
    "wof:name": "PH6 2JJ",
    "wof:placetype": "postalcode"
  },
  "geometry": {"coordinates":[-4.062976,56.328911],"type":"Point"}
}
