{
  "type": "Feature",
  "properties": {
    "iso:country":"GB",
    "wof:name":"PH6 2JJ",
    "wof:placetype":"postalcode"
},
  "geometry": {"coordinates":[-4.06297580217954,56.328910644472],"type":"Point"}
}