{
  "type": "Feature",
  "properties": {
    "iso:country": "GB",
    "wof:name": "PH6 2JJ",
    "wof:placetype": "postalcode"
  },
  "geometry": {"coordinates":[-4.062976,56.328911],"type":"Point"}
}
