{
  "type": "Feature",
  "properties": {
    "iso:country":"GB",
    "wof:name":"L32 9QH",
    "wof:placetype":"postalcode"
},
  "geometry": {"coordinates":[-2.88136606352717,53.47299206313163],"type":"Point"}
}