{
  "type": "Feature",
  "properties": {
    "iso:country":"GB",
    "wof:name":"CH3 5HL",
    "wof:placetype":"postalcode"
},
  "geometry": {"coordinates":[-2.85615610788245,53.1976463418787],"type":"Point"}
}