{
  "type": "Feature",
  "properties": {
    "iso:country": "GB",
    "wof:name": "PH1 1EQ",
    "wof:placetype": "postalcode"
  },
  "geometry": {"coordinates":[-3.473838,56.393111],"type":"Point"}
}
