{
  "type": "Feature",
  "properties": {
    "iso:country":"GB",
    "wof:name":"SA19 8NH",
    "wof:placetype":"postalcode"
},
  "geometry": {"coordinates":[-3.9033601380145,51.97147349568457],"type":"Point"}
}