{
  "type": "Feature",
  "properties": {
    "iso:country":"GB",
    "wof:name":"EN10 7LU",
    "wof:placetype":"postalcode"
},
  "geometry": {"coordinates":[-0.01768754337738,51.75099485997061],"type":"Point"}
}