{
  "type": "Feature",
  "properties": {
    "iso:country": "GB",
    "wof:name": "M40 2AU",
    "wof:placetype": "postalcode"
  },
  "geometry": {"coordinates":[-2.200914,53.497162],"type":"Point"}
}
