{
  "type": "Feature",
  "properties": {
    "date:inception_lower":"1994-05-01",
    "date:inception_upper":"1994-05-31",
    "iso:country":"GB",
    "wof:name":"M40 2AU",
    "wof:placetype":"postalcode"
},
  "geometry": {"coordinates":[-2.200914,53.497162],"type":"Point"}
}