{
  "type": "Feature",
  "properties": {
    "date:inception_lower":"1980-01-01",
    "date:inception_upper":"1980-01-31",
    "iso:country":"GB",
    "wof:name":"NE9 5JA",
    "wof:placetype":"postalcode"
},
  "geometry": {"coordinates":[-1.597594,54.932552],"type":"Point"}
}