{
  "type": "Feature",
  "properties": {
    "date:inception_lower": "1980-01-01",
    "date:inception_upper": "1980-01-01",
    "iso:country": "GB",
    "wof:name": "BB5 1SF",
    "wof:placetype": "postalcode"
  },
  "geometry": {"coordinates":[-2.384385,53.753597],"type":"Point"}
}
