{
  "type": "Feature",
  "properties": {
    "iso:country":"GB",
    "wof:name":"BB5 1SF",
    "wof:placetype":"postalcode"
},
  "geometry": {"coordinates":[-2.38438550015355,53.75359700437006],"type":"Point"}
}