{
  "type": "Feature",
  "properties": {
    "iso:country":"GB",
    "wof:name":"BH23 5NJ",
    "wof:placetype":"postalcode"
},
  "geometry": {"coordinates":[-1.70923096139281,50.74886730335511],"type":"Point"}
}