{
  "type": "Feature",
  "properties": {
    "date:inception_lower":"1980-01-01",
    "date:inception_upper":"1980-01-31",
    "iso:country":"GB",
    "wof:name":"BH23 5NJ",
    "wof:placetype":"postalcode"
},
  "geometry": {"coordinates":[-1.709231,50.748867],"type":"Point"}
}