{
  "type": "Feature",
  "properties": {
    "iso:country":"GB",
    "wof:name":"NG2 4PD",
    "wof:placetype":"postalcode"
},
  "geometry": {"coordinates":[-1.13597272758617,52.95260702488163],"type":"Point"}
}