{
  "type": "Feature",
  "properties": {
    "iso:country": "GB",
    "wof:name": "NG2 4PD",
    "wof:placetype": "postalcode"
  },
  "geometry": {"coordinates":[-1.135973,52.952607],"type":"Point"}
}
