{
  "type": "Feature",
  "properties": {
    "iso:country":"GB",
    "wof:name":"BD6 3BY",
    "wof:placetype":"postalcode"
},
  "geometry": {"coordinates":[-1.77901344203884,53.77079156737211],"type":"Point"}
}