{
  "type": "Feature",
  "properties": {
    "date:inception_lower": "2019-06-01",
    "date:inception_upper": "2019-06-01",
    "iso:country": "GB",
    "wof:name": "BL6 5WG",
    "wof:placetype": "postalcode"
  },
  "geometry": {"coordinates":[-2.550935,53.594607],"type":"Point"}
}
