{
  "type": "Feature",
  "properties": {
    "iso:country": "GB",
    "wof:name": "BL6 5WG",
    "wof:placetype": "postalcode"
  },
  "geometry": {"coordinates":[-2.55045,53.59452],"type":"Point"}
}
