{
  "type": "Feature",
  "properties": {
    "date:inception_lower": "1996-06-01",
    "date:inception_upper": "1996-06-01",
    "iso:country": "GB",
    "wof:name": "LA9 6BF",
    "wof:placetype": "postalcode"
  },
  "geometry": {"coordinates":[-2.730208,54.326104],"type":"Point"}
}
