{
  "type": "Feature",
  "properties": {
    "iso:country":"GB",
    "wof:name":"BD1 4TY",
    "wof:placetype":"postalcode"
},
  "geometry": {"coordinates":[-1.74878129931946,53.79527833811861],"type":"Point"}
}