{
  "type": "Feature",
  "properties": {
    "iso:country": "GB",
    "wof:name": "BH12 3NL",
    "wof:placetype": "postalcode"
  },
  "geometry": {"coordinates":[-1.938886,50.740983],"type":"Point"}
}
