{
  "type": "Feature",
  "properties": {
    "iso:country":"GB",
    "wof:name":"PO30 2NA",
    "wof:placetype":"postalcode"
},
  "geometry": {"coordinates":[-1.26781784919848,50.703703921939],"type":"Point"}
}