{
  "type": "Feature",
  "properties": {
    "iso:country": "GB",
    "wof:name": "PO30 2NA",
    "wof:placetype": "postalcode"
  },
  "geometry": {"coordinates":[-1.267818,50.703704],"type":"Point"}
}
