{
  "type": "Feature",
  "properties": {
    "iso:country": "GB",
    "wof:name": "UB1 2NZ",
    "wof:placetype": "postalcode"
  },
  "geometry": {"coordinates":[-0.372533,51.524853],"type":"Point"}
}
