{
  "type": "Feature",
  "properties": {
    "iso:country":"GB",
    "wof:name":"E13 8EJ",
    "wof:placetype":"postalcode"
},
  "geometry": {"coordinates":[0.01371083417193,51.52009049428715],"type":"Point"}
}