{
  "type": "Feature",
  "properties": {
    "iso:country":"GB",
    "wof:name":"SY3 8UJ",
    "wof:placetype":"postalcode"
},
  "geometry": {"coordinates":[-2.78682908687913,52.70796474618255],"type":"Point"}
}