{
  "type": "Feature",
  "properties": {
    "date:inception_lower": "1980-01-01",
    "date:inception_upper": "1980-01-01",
    "iso:country": "GB",
    "wof:name": "SY3 8UJ",
    "wof:placetype": "postalcode"
  },
  "geometry": {"coordinates":[-2.786829,52.707965],"type":"Point"}
}
