{
  "type": "Feature",
  "properties": {
    "iso:country": "GB",
    "wof:name": "SY3 8UJ",
    "wof:placetype": "postalcode"
  },
  "geometry": {"coordinates":[-2.786829,52.707965],"type":"Point"}
}
