{
  "type": "Feature",
  "properties": {
    "iso:country": "GB",
    "wof:name": "NR8 5EW",
    "wof:placetype": "postalcode"
  },
  "geometry": {"coordinates":[1.21014,52.65834],"type":"Point"}
}
