{
  "type": "Feature",
  "properties": {
    "iso:country":"GB",
    "wof:name":"NR8 5EW",
    "wof:placetype":"postalcode"
},
  "geometry": {"coordinates":[1.21013987061809,52.65834049534789],"type":"Point"}
}