{
  "type": "Feature",
  "properties": {
    "iso:country":"GB",
    "wof:name":"WN7 1DP",
    "wof:placetype":"postalcode"
},
  "geometry": {"coordinates":[-2.51813877496905,53.49738434236983],"type":"Point"}
}