{
  "type": "Feature",
  "properties": {
    "date:inception_lower": "1980-01-01",
    "date:inception_upper": "1980-01-01",
    "iso:country": "GB",
    "wof:name": "WN7 1DP",
    "wof:placetype": "postalcode"
  },
  "geometry": {"coordinates":[-2.518195,53.497184],"type":"Point"}
}
