{
  "type": "Feature",
  "properties": {
    "date:inception_lower": "2004-08-01",
    "date:inception_upper": "2004-08-01",
    "iso:country": "GB",
    "wof:name": "LU6 2BA",
    "wof:placetype": "postalcode"
  },
  "geometry": {"coordinates":[-0.607526,51.86863],"type":"Point"}
}
