{
  "type": "Feature",
  "properties": {
    "iso:country": "GB",
    "wof:name": "LU6 2BA",
    "wof:placetype": "postalcode"
  },
  "geometry": {"coordinates":[-0.607526,51.86863],"type":"Point"}
}
