{
  "type": "Feature",
  "properties": {
    "iso:country":"GB",
    "wof:name":"N1 2NN",
    "wof:placetype":"postalcode"
},
  "geometry": {"coordinates":[-0.09701171377219,51.54450143753007],"type":"Point"}
}