{
  "type": "Feature",
  "properties": {
    "iso:country":"GB",
    "wof:name":"LA17 7TQ",
    "wof:placetype":"postalcode"
},
  "geometry": {"coordinates":[-3.17583133303149,54.23029534634733],"type":"Point"}
}