{
  "type": "Feature",
  "properties": {
    "date:inception_lower": "1980-01-01",
    "date:inception_upper": "1980-01-01",
    "iso:country": "GB",
    "wof:name": "SW12 0NF",
    "wof:placetype": "postalcode"
  },
  "geometry": {"coordinates":[-0.140547,51.446911],"type":"Point"}
}
