{
  "type": "Feature",
  "properties": {
    "iso:country":"GB",
    "wof:name":"SW12 0NF",
    "wof:placetype":"postalcode"
},
  "geometry": {"coordinates":[-0.1405468741487,51.44691117923284],"type":"Point"}
}