{
  "type": "Feature",
  "properties": {
    "iso:country":"GB",
    "wof:name":"TN23 3JX",
    "wof:placetype":"postalcode"
},
  "geometry": {"coordinates":[0.85005564900205,51.15107227505482],"type":"Point"}
}