{
  "type": "Feature",
  "properties": {
    "date:inception_lower":"1980-01-01",
    "date:inception_upper":"1980-01-31",
    "iso:country":"GB",
    "wof:name":"PH15 2NE",
    "wof:placetype":"postalcode"
},
  "geometry": {"coordinates":[-3.994561,56.618081],"type":"Point"}
}