{
  "type": "Feature",
  "properties": {
    "iso:country":"GB",
    "wof:name":"CH8 9BJ",
    "wof:placetype":"postalcode"
},
  "geometry": {"coordinates":[-3.32730370827341,53.32427748952906],"type":"Point"}
}