{
  "type": "Feature",
  "properties": {
    "iso:country": "GB",
    "wof:name": "GL16 8LB",
    "wof:placetype": "postalcode"
  },
  "geometry": {"coordinates":[-2.627451,51.771687],"type":"Point"}
}
