{
  "type": "Feature",
  "properties": {
    "iso:country":"GB",
    "wof:name":"B25 8NB",
    "wof:placetype":"postalcode"
},
  "geometry": {"coordinates":[-1.81732590416185,52.46038529172775],"type":"Point"}
}