{
  "type": "Feature",
  "properties": {
    "date:inception_lower": "1980-01-01",
    "date:inception_upper": "1980-01-01",
    "iso:country": "GB",
    "wof:name": "SY1 1NP",
    "wof:placetype": "postalcode"
  },
  "geometry": {"coordinates":[-2.756217,52.70606],"type":"Point"}
}
