{
  "type": "Feature",
  "properties": {
    "iso:country":"GB",
    "wof:name":"SY1 1NP",
    "wof:placetype":"postalcode"
},
  "geometry": {"coordinates":[-2.75621714139577,52.70606038822626],"type":"Point"}
}