{
  "type": "Feature",
  "properties": {
    "iso:country": "GB",
    "wof:name": "SA73 3LD",
    "wof:placetype": "postalcode"
  },
  "geometry": {"coordinates":[-5.043955,51.715676],"type":"Point"}
}
