{
  "type": "Feature",
  "properties": {
    "date:inception_lower":"1980-01-01",
    "date:inception_upper":"1980-01-31",
    "iso:country":"GB",
    "wof:name":"EX17 4DF",
    "wof:placetype":"postalcode"
},
  "geometry": {"coordinates":[-3.637767,50.859008],"type":"Point"}
}