{
  "type": "Feature",
  "properties": {
    "iso:country":"GB",
    "wof:name":"EX17 4DF",
    "wof:placetype":"postalcode"
},
  "geometry": {"coordinates":[-3.63774998440382,50.85901640136897],"type":"Point"}
}