{
  "type": "Feature",
  "properties": {
    "iso:country":"GB",
    "wof:name":"BH22 9RX",
    "wof:placetype":"postalcode"
},
  "geometry": {"coordinates":[-1.89269528777346,50.8088277962487],"type":"Point"}
}