{
  "type": "Feature",
  "properties": {
    "iso:country":"GB",
    "wof:name":"FY7 7BJ",
    "wof:placetype":"postalcode"
},
  "geometry": {"coordinates":[-3.02597721222269,53.92341273052708],"type":"Point"}
}