{
  "type": "Feature",
  "properties": {
    "iso:country": "GB",
    "wof:name": "EH51 9QD",
    "wof:placetype": "postalcode"
  },
  "geometry": {"coordinates":[-3.59658,56.01199],"type":"Point"}
}
