{
  "type": "Feature",
  "properties": {
    "iso:country":"GB",
    "wof:name":"EH51 9QD",
    "wof:placetype":"postalcode"
},
  "geometry": {"coordinates":[-3.59657962585768,56.01199005022131],"type":"Point"}
}