{
  "type": "Feature",
  "properties": {
    "date:inception_lower":"1992-01-01",
    "date:inception_upper":"1992-01-31",
    "iso:country":"GB",
    "wof:name":"WV6 7AS",
    "wof:placetype":"postalcode"
},
  "geometry": {"coordinates":[-2.250508,52.580165],"type":"Point"}
}