{
  "type": "Feature",
  "properties": {
    "iso:country": "GB",
    "wof:name": "WV6 7AS",
    "wof:placetype": "postalcode"
  },
  "geometry": {"coordinates":[-2.250508,52.580165],"type":"Point"}
}
