{
  "type": "Feature",
  "properties": {
    "date:inception_lower": "1992-01-01",
    "date:inception_upper": "1992-01-01",
    "iso:country": "GB",
    "wof:name": "WV6 7AS",
    "wof:placetype": "postalcode"
  },
  "geometry": {"coordinates":[-2.252773,52.584079],"type":"Point"}
}
