{
  "type": "Feature",
  "properties": {
    "date:inception_lower": "2005-01-01",
    "date:inception_upper": "2005-01-01",
    "iso:country": "GB",
    "wof:name": "DT1 3TP",
    "wof:placetype": "postalcode"
  },
  "geometry": {"coordinates":[-2.469238,50.712556],"type":"Point"}
}
