{
  "type": "Feature",
  "properties": {
    "iso:country":"GB",
    "wof:name":"DT1 3TP",
    "wof:placetype":"postalcode"
},
  "geometry": {"coordinates":[-2.46921182224792,50.71255609503206],"type":"Point"}
}