{
  "type": "Feature",
  "properties": {
    "date:inception_lower":"1992-08-01",
    "date:inception_upper":"1992-08-31",
    "iso:country":"GB",
    "wof:name":"PR9 9TW",
    "wof:placetype":"postalcode"
},
  "geometry": {"coordinates":[-2.972882,53.667876],"type":"Point"}
}