{
  "type": "Feature",
  "properties": {
    "iso:country":"GB",
    "wof:name":"BN5 9XZ",
    "wof:placetype":"postalcode"
},
  "geometry": {"coordinates":[-0.27069759916889,50.90356873762481],"type":"Point"}
}