{
  "type": "Feature",
  "properties": {
    "iso:country":"GB",
    "wof:name":"HA1 3SZ",
    "wof:placetype":"postalcode"
},
  "geometry": {"coordinates":[-0.32936221996099,51.56297618806955],"type":"Point"}
}