{
  "type": "Feature",
  "properties": {
    "date:inception_lower": "2019-07-01",
    "date:inception_upper": "2019-07-01",
    "iso:country": "GB",
    "wof:name": "EX14 3FH",
    "wof:placetype": "postalcode"
  },
  "geometry": {"coordinates":[-3.21588,50.787484],"type":"Point"}
}
