{
  "type": "Feature",
  "properties": {
    "date:inception_lower":"1993-01-01",
    "date:inception_upper":"1993-01-31",
    "iso:country":"GB",
    "wof:name":"GL7 1PL",
    "wof:placetype":"postalcode"
},
  "geometry": {"coordinates":[-1.950073,51.702817],"type":"Point"}
}