{
  "type": "Feature",
  "properties": {
    "iso:country":"GB",
    "wof:name":"GL7 1PL",
    "wof:placetype":"postalcode"
},
  "geometry": {"coordinates":[-1.95007268743277,51.70281728096131],"type":"Point"}
}