{
  "type": "Feature",
  "properties": {
    "iso:country": "GB",
    "wof:name": "GL7 1PL",
    "wof:placetype": "postalcode"
  },
  "geometry": {"coordinates":[-1.950073,51.702817],"type":"Point"}
}
