{
  "type": "Feature",
  "properties": {
    "date:inception_lower": "1999-06-01",
    "date:inception_upper": "1999-06-01",
    "iso:country": "GB",
    "wof:name": "CH65 3BA",
    "wof:placetype": "postalcode"
  },
  "geometry": {"coordinates":[-2.918712,53.285759],"type":"Point"}
}
