{
  "type": "Feature",
  "properties": {
    "date:inception_lower": "2022-07-01",
    "date:inception_upper": "2022-07-01",
    "iso:country": "GB",
    "wof:name": "DT11 9GG",
    "wof:placetype": "postalcode"
  },
  "geometry": {"coordinates":[-2.163797,50.853555],"type":"Point"}
}
