{
  "type": "Feature",
  "properties": {
    "iso:country":"GB",
    "wof:name":"MK5 7BY",
    "wof:placetype":"postalcode"
},
  "geometry": {"coordinates":[-0.77550176359832,52.0156080879193],"type":"Point"}
}