{
  "type": "Feature",
  "properties": {
    "iso:country": "GB",
    "wof:name": "MK5 7BY",
    "wof:placetype": "postalcode"
  },
  "geometry": {"coordinates":[-0.775502,52.015608],"type":"Point"}
}
