{
  "type": "Feature",
  "properties": {
    "iso:country":"GB",
    "wof:name":"DH1 5NQ",
    "wof:placetype":"postalcode"
},
  "geometry": {"coordinates":[-1.57703105736225,54.80271942958409],"type":"Point"}
}