{
  "type": "Feature",
  "properties": {
    "iso:country": "GB",
    "wof:name": "DH1 5NQ",
    "wof:placetype": "postalcode"
  },
  "geometry": {"coordinates":[-1.577031,54.802719],"type":"Point"}
}
