{
  "type": "Feature",
  "properties": {
    "date:inception_lower":"2018-12-01",
    "date:inception_upper":"2018-12-31",
    "iso:country":"GB",
    "wof:name":"N21 2DX",
    "wof:placetype":"postalcode"
},
  "geometry": {"coordinates":[-0.099528,51.632959],"type":"Point"}
}