{
  "type": "Feature",
  "properties": {
    "iso:country":"GB",
    "wof:name":"KY4 9BD",
    "wof:placetype":"postalcode"
},
  "geometry": {"coordinates":[-3.34425505931466,56.11554689900466],"type":"Point"}
}