{
  "type": "Feature",
  "properties": {
    "date:inception_lower": "1980-01-01",
    "date:inception_upper": "1980-01-01",
    "iso:country": "GB",
    "wof:name": "DN11 8AJ",
    "wof:placetype": "postalcode"
  },
  "geometry": {"coordinates":[-1.048542,53.418536],"type":"Point"}
}
