{
  "type": "Feature",
  "properties": {
    "iso:country":"GB",
    "wof:name":"B6 4EP",
    "wof:placetype":"postalcode"
},
  "geometry": {"coordinates":[-1.89295712057518,52.4917718153711],"type":"Point"}
}