{
  "type": "Feature",
  "properties": {
    "iso:country":"GB",
    "wof:name":"L36 0XH",
    "wof:placetype":"postalcode"
},
  "geometry": {"coordinates":[-2.83706721519337,53.40613756247586],"type":"Point"}
}