{
  "type": "Feature",
  "properties": {
    "iso:country": "GB",
    "wof:name": "PO4 0DY",
    "wof:placetype": "postalcode"
  },
  "geometry": {"coordinates":[-1.075444,50.791331],"type":"Point"}
}
