{
  "type": "Feature",
  "properties": {
    "iso:country":"GB",
    "wof:name":"SY23 5JG",
    "wof:placetype":"postalcode"
},
  "geometry": {"coordinates":[-4.16959891692342,52.25648469067369],"type":"Point"}
}