{
  "type": "Feature",
  "properties": {
    "iso:country": "GB",
    "wof:name": "SY23 5JG",
    "wof:placetype": "postalcode"
  },
  "geometry": {"coordinates":[-4.169599,52.256485],"type":"Point"}
}
