{
  "type": "Feature",
  "properties": {
    "iso:country":"GB",
    "wof:name":"NE22 6HW",
    "wof:placetype":"postalcode"
},
  "geometry": {"coordinates":[-1.60459064049246,55.13588847882423],"type":"Point"}
}