{
  "type": "Feature",
  "properties": {
    "iso:country":"GB",
    "wof:name":"LS15 8HG",
    "wof:placetype":"postalcode"
},
  "geometry": {"coordinates":[-1.44031588729961,53.81157415781447],"type":"Point"}
}