{
  "type": "Feature",
  "properties": {
    "iso:country": "GB",
    "wof:name": "NR33 8LZ",
    "wof:placetype": "postalcode"
  },
  "geometry": {"coordinates":[1.706698,52.460106],"type":"Point"}
}
