{
  "type": "Feature",
  "properties": {
    "iso:country": "GB",
    "wof:name": "S41 0XY",
    "wof:placetype": "postalcode"
  },
  "geometry": {"coordinates":[-1.41682,53.218301],"type":"Point"}
}
