{
  "type": "Feature",
  "properties": {
    "date:inception_lower": "2001-06-01",
    "date:inception_upper": "2001-06-01",
    "iso:country": "GB",
    "wof:name": "S41 0XY",
    "wof:placetype": "postalcode"
  },
  "geometry": {"coordinates":[-1.41682,53.218301],"type":"Point"}
}
