{
  "type": "Feature",
  "properties": {
    "iso:country":"GB",
    "wof:name":"S41 0XY",
    "wof:placetype":"postalcode"
},
  "geometry": {"coordinates":[-1.41682041961566,53.21830092780814],"type":"Point"}
}