{
  "type": "Feature",
  "properties": {
    "iso:country":"GB",
    "wof:name":"CB5 8DQ",
    "wof:placetype":"postalcode"
},
  "geometry": {"coordinates":[0.13000987703171,52.20847048017406],"type":"Point"}
}