{
  "type": "Feature",
  "properties": {
    "iso:country": "GB",
    "wof:name": "CB5 8DQ",
    "wof:placetype": "postalcode"
  },
  "geometry": {"coordinates":[0.13001,52.20847],"type":"Point"}
}
