{
  "type": "Feature",
  "properties": {
    "iso:country": "GB",
    "wof:name": "B70 0FG",
    "wof:placetype": "postalcode"
  },
  "geometry": {"coordinates":[-2.015816,52.539795],"type":"Point"}
}
