{
  "type": "Feature",
  "properties": {
    "iso:country": "GB",
    "wof:name": "LA22 0LW",
    "wof:placetype": "postalcode"
  },
  "geometry": {"coordinates":[-2.948648,54.347852],"type":"Point"}
}
