{
  "type": "Feature",
  "properties": {
    "iso:country":"GB",
    "wof:name":"LA22 0LW",
    "wof:placetype":"postalcode"
},
  "geometry": {"coordinates":[-2.94882639534748,54.34758983348611],"type":"Point"}
}