{
  "type": "Feature",
  "properties": {
    "iso:country":"GB",
    "wof:name":"CM23 1BZ",
    "wof:placetype":"postalcode"
},
  "geometry": {"coordinates":[0.15733381159409,51.92054903833286],"type":"Point"}
}