{
  "type": "Feature",
  "properties": {
    "date:inception_lower": "1980-01-01",
    "date:inception_upper": "1980-01-01",
    "iso:country": "GB",
    "wof:name": "SW7 5NP",
    "wof:placetype": "postalcode"
  },
  "geometry": {"coordinates":[-0.182894,51.49743],"type":"Point"}
}
