{
  "type": "Feature",
  "properties": {
    "iso:country":"GB",
    "wof:name":"SW7 5NP",
    "wof:placetype":"postalcode"
},
  "geometry": {"coordinates":[-0.18289399760299,51.49742974675961],"type":"Point"}
}