{
  "type": "Feature",
  "properties": {
    "date:inception_lower": "1980-01-01",
    "date:inception_upper": "1980-01-01",
    "iso:country": "GB",
    "wof:name": "KY12 0NY",
    "wof:placetype": "postalcode"
  },
  "geometry": {"coordinates":[-3.463321,56.0852],"type":"Point"}
}
