{
  "type": "Feature",
  "properties": {
    "iso:country": "GB",
    "wof:name": "KY12 0NY",
    "wof:placetype": "postalcode"
  },
  "geometry": {"coordinates":[-3.463321,56.0852],"type":"Point"}
}
