{
  "type": "Feature",
  "properties": {
    "date:inception_lower": "1980-01-01",
    "date:inception_upper": "1980-01-01",
    "iso:country": "GB",
    "wof:name": "LL65 4UT",
    "wof:placetype": "postalcode"
  },
  "geometry": {"coordinates":[-4.531599,53.314249],"type":"Point"}
}
