{
  "type": "Feature",
  "properties": {
    "iso:country":"GB",
    "wof:name":"LL65 4UT",
    "wof:placetype":"postalcode"
},
  "geometry": {"coordinates":[-4.53154767597445,53.31423249290302],"type":"Point"}
}