{
  "type": "Feature",
  "properties": {
    "date:inception_lower": "2019-12-01",
    "date:inception_upper": "2019-12-01",
    "iso:country": "GB",
    "wof:name": "DE14 1PU",
    "wof:placetype": "postalcode"
  },
  "geometry": {"coordinates":[-1.630806,52.811594],"type":"Point"}
}
