{
  "type": "Feature",
  "properties": {
    "date:inception_lower": "1980-01-01",
    "date:inception_upper": "1980-01-01",
    "iso:country": "GB",
    "wof:name": "PA16 7TQ",
    "wof:placetype": "postalcode"
  },
  "geometry": {"coordinates":[-4.788534,55.959696],"type":"Point"}
}
