{
  "type": "Feature",
  "properties": {
    "iso:country":"GB",
    "wof:name":"LE12 6TU",
    "wof:placetype":"postalcode"
},
  "geometry": {"coordinates":[-1.1052479821029,52.80399666046385],"type":"Point"}
}