{
  "type": "Feature",
  "properties": {
    "iso:country": "GB",
    "wof:name": "WV5 0AE",
    "wof:placetype": "postalcode"
  },
  "geometry": {"coordinates":[-2.199163,52.526569],"type":"Point"}
}
