{
  "type": "Feature",
  "properties": {
    "iso:country":"GB",
    "wof:name":"WV5 0AE",
    "wof:placetype":"postalcode"
},
  "geometry": {"coordinates":[-2.1991631373126,52.5265688181878],"type":"Point"}
}