{
  "type": "Feature",
  "properties": {
    "date:inception_lower": "2020-02-01",
    "date:inception_upper": "2020-02-01",
    "iso:country": "GB",
    "wof:name": "CB8 1GH",
    "wof:placetype": "postalcode"
  },
  "geometry": {"coordinates":[0.40419,52.242919],"type":"Point"}
}
