{
  "type": "Feature",
  "properties": {
    "iso:country":"GB",
    "wof:name":"CO3 9UE",
    "wof:placetype":"postalcode"
},
  "geometry": {"coordinates":[0.81100855081247,51.9016292198387],"type":"Point"}
}