{
  "type": "Feature",
  "properties": {
    "iso:country": "GB",
    "wof:name": "SY13 4RB",
    "wof:placetype": "postalcode"
  },
  "geometry": {"coordinates":[-2.730193,52.993243],"type":"Point"}
}
