{
  "type": "Feature",
  "properties": {
    "date:inception_lower":"1980-01-01",
    "date:inception_upper":"1980-01-31",
    "iso:country":"GB",
    "wof:name":"SY13 4RB",
    "wof:placetype":"postalcode"
},
  "geometry": {"coordinates":[-2.730193,52.993243],"type":"Point"}
}