{
  "type": "Feature",
  "properties": {
    "iso:country":"GB",
    "wof:name":"WF1 1RS",
    "wof:placetype":"postalcode"
},
  "geometry": {"coordinates":[-1.49943630723967,53.67772330720203],"type":"Point"}
}