{
  "type": "Feature",
  "properties": {
    "date:inception_lower": "1995-12-01",
    "date:inception_upper": "1995-12-01",
    "iso:country": "GB",
    "wof:name": "WF1 1RS",
    "wof:placetype": "postalcode"
  },
  "geometry": {"coordinates":[-1.498213,53.677627],"type":"Point"}
}
