{
  "type": "Feature",
  "properties": {
    "iso:country": "GB",
    "wof:name": "CF81 8TA",
    "wof:placetype": "postalcode"
  },
  "geometry": {"coordinates":[-3.234937,51.691461],"type":"Point"}
}
