{
  "type": "Feature",
  "properties": {
    "date:inception_lower":"1995-07-01",
    "date:inception_upper":"1995-07-31",
    "iso:country":"GB",
    "wof:name":"CF81 8TA",
    "wof:placetype":"postalcode"
},
  "geometry": {"coordinates":[-3.234937,51.691461],"type":"Point"}
}