{
  "type": "Feature",
  "properties": {
    "iso:country":"GB",
    "wof:name":"CF81 8TA",
    "wof:placetype":"postalcode"
},
  "geometry": {"coordinates":[-3.23493725958087,51.69146106675433],"type":"Point"}
}