{
  "type": "Feature",
  "properties": {
    "date:inception_lower": "2017-06-01",
    "date:inception_upper": "2017-06-01",
    "iso:country": "GB",
    "wof:name": "TN23 3SZ",
    "wof:placetype": "postalcode"
  },
  "geometry": {"coordinates":[0.850194,51.158399],"type":"Point"}
}
