{
  "type": "Feature",
  "properties": {
    "date:inception_lower":"2003-11-01",
    "date:inception_upper":"2003-11-30",
    "iso:country":"GB",
    "wof:name":"BN2 0GX",
    "wof:placetype":"postalcode"
},
  "geometry": {"coordinates":[-0.132903,50.824346],"type":"Point"}
}