{
  "type": "Feature",
  "properties": {
    "iso:country": "GB",
    "wof:name": "WD17 3TY",
    "wof:placetype": "postalcode"
  },
  "geometry": {"coordinates":[-0.423867,51.675821],"type":"Point"}
}
