{
  "type": "Feature",
  "properties": {
    "iso:country":"GB",
    "wof:name":"WD17 3TY",
    "wof:placetype":"postalcode"
},
  "geometry": {"coordinates":[-0.42386661440798,51.6758209862066],"type":"Point"}
}