{
  "type": "Feature",
  "properties": {
    "iso:country":"GB",
    "wof:name":"GU52 6DQ",
    "wof:placetype":"postalcode"
},
  "geometry": {"coordinates":[-0.85330806777953,51.2554532945564],"type":"Point"}
}