{
  "type": "Feature",
  "properties": {
    "iso:country":"GB",
    "wof:name":"AB14 0ND",
    "wof:placetype":"postalcode"
},
  "geometry": {"coordinates":[-2.28671326247773,57.10218107856243],"type":"Point"}
}