{
  "type": "Feature",
  "properties": {
    "iso:country": "GB",
    "wof:name": "AB14 0ND",
    "wof:placetype": "postalcode"
  },
  "geometry": {"coordinates":[-2.286713,57.102181],"type":"Point"}
}
