{
  "type": "Feature",
  "properties": {
    "iso:country": "GB",
    "wof:name": "ME10 4LS",
    "wof:placetype": "postalcode"
  },
  "geometry": {"coordinates":[0.753743,51.330277],"type":"Point"}
}
