{
  "type": "Feature",
  "properties": {
    "date:inception_lower": "2021-08-01",
    "date:inception_upper": "2021-08-01",
    "iso:country": "GB",
    "wof:name": "PA2 7FL",
    "wof:placetype": "postalcode"
  },
  "geometry": {"coordinates":[-4.400464,55.841388],"type":"Point"}
}
