{
  "type": "Feature",
  "properties": {
    "iso:country":"GB",
    "wof:name":"GL17 9EY",
    "wof:placetype":"postalcode"
},
  "geometry": {"coordinates":[-2.50552303880788,51.85576594306969],"type":"Point"}
}