{
  "type": "Feature",
  "properties": {
    "iso:country":"GB",
    "wof:name":"LU7 2LE",
    "wof:placetype":"postalcode"
},
  "geometry": {"coordinates":[-0.6778369828338,51.91033413520592],"type":"Point"}
}