{
  "type": "Feature",
  "properties": {
    "iso:country": "GB",
    "wof:name": "TN14 7QU",
    "wof:placetype": "postalcode"
  },
  "geometry": {"coordinates":[0.074475,51.334435],"type":"Point"}
}
