{
  "type": "Feature",
  "properties": {
    "iso:country":"GB",
    "wof:name":"TN14 7QU",
    "wof:placetype":"postalcode"
},
  "geometry": {"coordinates":[0.07447446929134,51.334434558453],"type":"Point"}
}