{
  "type": "Feature",
  "properties": {
    "date:inception_lower":"1980-01-01",
    "date:inception_upper":"1980-01-31",
    "iso:country":"GB",
    "wof:name":"SP11 8DP",
    "wof:placetype":"postalcode"
},
  "geometry": {"coordinates":[-1.558586,51.217722],"type":"Point"}
}