{
  "type": "Feature",
  "properties": {
    "iso:country":"GB",
    "wof:name":"YO7 2BY",
    "wof:placetype":"postalcode"
},
  "geometry": {"coordinates":[-1.24564874860946,54.19141502101548],"type":"Point"}
}