{
  "type": "Feature",
  "properties": {
    "iso:country": "GB",
    "wof:name": "TQ12 3GJ",
    "wof:placetype": "postalcode"
  },
  "geometry": {"coordinates":[-3.58672,50.542953],"type":"Point"}
}
