{
  "type": "Feature",
  "properties": {
    "iso:country": "GB",
    "wof:name": "TQ12 3GJ",
    "wof:placetype": "postalcode"
  },
  "geometry": {"coordinates":[-3.586354,50.542994],"type":"Point"}
}
