{
  "type": "Feature",
  "properties": {
    "iso:country":"GB",
    "wof:name":"WA5 3NR",
    "wof:placetype":"postalcode"
},
  "geometry": {"coordinates":[-2.66191363287793,53.39443731085764],"type":"Point"}
}