{
  "type": "Feature",
  "properties": {
    "date:inception_lower": "2020-08-01",
    "date:inception_upper": "2020-08-01",
    "iso:country": "GB",
    "wof:name": "NR5 0WR",
    "wof:placetype": "postalcode"
  },
  "geometry": {"coordinates":[1.191893,52.646754],"type":"Point"}
}
