{
  "type": "Feature",
  "properties": {
    "iso:country":"GB",
    "wof:name":"N13 5NG",
    "wof:placetype":"postalcode"
},
  "geometry": {"coordinates":[-0.08584996748936,51.62244646429401],"type":"Point"}
}