{
  "type": "Feature",
  "properties": {
    "date:inception_lower": "1980-01-01",
    "date:inception_upper": "1980-01-01",
    "iso:country": "GB",
    "wof:name": "N13 5NG",
    "wof:placetype": "postalcode"
  },
  "geometry": {"coordinates":[-0.08585,51.622446],"type":"Point"}
}
