{
  "type": "Feature",
  "properties": {
    "iso:country":"GB",
    "wof:name":"HR9 6DX",
    "wof:placetype":"postalcode"
},
  "geometry": {"coordinates":[-2.65583982562396,51.82844605057007],"type":"Point"}
}