{
  "type": "Feature",
  "properties": {
    "iso:country": "GB",
    "wof:name": "HR9 6DX",
    "wof:placetype": "postalcode"
  },
  "geometry": {"coordinates":[-2.655843,51.828452],"type":"Point"}
}
