{
  "type": "Feature",
  "properties": {
    "iso:country":"GB",
    "wof:name":"TF6 6RT",
    "wof:placetype":"postalcode"
},
  "geometry": {"coordinates":[-2.55392991854038,52.80325082768888],"type":"Point"}
}