{
  "type": "Feature",
  "properties": {
    "iso:country": "GB",
    "wof:name": "TF6 6RT",
    "wof:placetype": "postalcode"
  },
  "geometry": {"coordinates":[-2.559275,52.809686],"type":"Point"}
}
