{
  "type": "Feature",
  "properties": {
    "iso:country": "GB",
    "wof:name": "PO15 5AP",
    "wof:placetype": "postalcode"
  },
  "geometry": {"coordinates":[-1.244066,50.861447],"type":"Point"}
}
