{
  "type": "Feature",
  "properties": {
    "iso:country":"GB",
    "wof:name":"PO15 5AP",
    "wof:placetype":"postalcode"
},
  "geometry": {"coordinates":[-1.2440663556296,50.86144674107308],"type":"Point"}
}