{
  "type": "Feature",
  "properties": {
    "date:inception_lower": "1980-01-01",
    "date:inception_upper": "1980-01-01",
    "iso:country": "GB",
    "wof:name": "SY25 6JS",
    "wof:placetype": "postalcode"
  },
  "geometry": {"coordinates":[-3.921702,52.205771],"type":"Point"}
}
