{
  "type": "Feature",
  "properties": {
    "iso:country": "GB",
    "wof:name": "G12 8LS",
    "wof:placetype": "postalcode"
  },
  "geometry": {"coordinates":[-4.286239,55.872663],"type":"Point"}
}
