{
  "type": "Feature",
  "properties": {
    "iso:country":"GB",
    "wof:name":"L10 6LZ",
    "wof:placetype":"postalcode"
},
  "geometry": {"coordinates":[-2.93162370573105,53.48111409654637],"type":"Point"}
}