{
  "type": "Feature",
  "properties": {
    "date:inception_lower":"1980-01-01",
    "date:inception_upper":"1980-01-31",
    "iso:country":"GB",
    "wof:name":"L10 6LZ",
    "wof:placetype":"postalcode"
},
  "geometry": {"coordinates":[-2.931624,53.481114],"type":"Point"}
}