{
  "type": "Feature",
  "properties": {
    "iso:country":"GB",
    "wof:name":"L23 2TR",
    "wof:placetype":"postalcode"
},
  "geometry": {"coordinates":[-3.02256910565705,53.49629854273644],"type":"Point"}
}