{
  "type": "Feature",
  "properties": {
    "date:inception_lower": "2021-11-01",
    "date:inception_upper": "2021-11-01",
    "iso:country": "GB",
    "wof:name": "BA6 8FT",
    "wof:placetype": "postalcode"
  },
  "geometry": {"coordinates":[-2.700273,51.158191],"type":"Point"}
}
