{
  "type": "Feature",
  "properties": {
    "iso:country": "GB",
    "wof:name": "MK11 4AP",
    "wof:placetype": "postalcode"
  },
  "geometry": {"coordinates":[-0.831377,52.04485],"type":"Point"}
}
