{
  "type": "Feature",
  "properties": {
    "iso:country":"GB",
    "wof:name":"ME13 8SX",
    "wof:placetype":"postalcode"
},
  "geometry": {"coordinates":[0.8802976581951,51.30899092263265],"type":"Point"}
}