{
  "type": "Feature",
  "properties": {
    "date:inception_lower": "1990-02-01",
    "date:inception_upper": "1990-02-01",
    "iso:country": "GB",
    "wof:name": "LE9 6UT",
    "wof:placetype": "postalcode"
  },
  "geometry": {"coordinates":[-1.210624,52.528332],"type":"Point"}
}
