{
  "type": "Feature",
  "properties": {
    "iso:country":"GB",
    "wof:name":"CH44 1DD",
    "wof:placetype":"postalcode"
},
  "geometry": {"coordinates":[-3.03440428653566,53.42202932388032],"type":"Point"}
}