{
  "type": "Feature",
  "properties": {
    "date:inception_lower": "1999-06-01",
    "date:inception_upper": "1999-06-01",
    "iso:country": "GB",
    "wof:name": "CH44 1DD",
    "wof:placetype": "postalcode"
  },
  "geometry": {"coordinates":[-3.034404,53.422029],"type":"Point"}
}
