{
  "type": "Feature",
  "properties": {
    "iso:country": "GB",
    "wof:name": "CH44 1DD",
    "wof:placetype": "postalcode"
  },
  "geometry": {"coordinates":[-3.034404,53.422029],"type":"Point"}
}
