{
  "type": "Feature",
  "properties": {
    "iso:country": "GB",
    "wof:name": "PO14 3PE",
    "wof:placetype": "postalcode"
  },
  "geometry": {"coordinates":[-1.221141,50.825128],"type":"Point"}
}
