{
  "type": "Feature",
  "properties": {
    "date:inception_lower": "1980-01-01",
    "date:inception_upper": "1980-01-01",
    "iso:country": "GB",
    "wof:name": "PO14 3PE",
    "wof:placetype": "postalcode"
  },
  "geometry": {"coordinates":[-1.221141,50.825128],"type":"Point"}
}
