{
  "type": "Feature",
  "properties": {
    "iso:country":"GB",
    "wof:name":"SS9 5XN",
    "wof:placetype":"postalcode"
},
  "geometry": {"coordinates":[0.65547876654834,51.569674742005],"type":"Point"}
}