{
  "type": "Feature",
  "properties": {
    "iso:country": "GB",
    "wof:name": "LE3 2FW",
    "wof:placetype": "postalcode"
  },
  "geometry": {"coordinates":[-1.165161,52.61241],"type":"Point"}
}
