{
  "type": "Feature",
  "properties": {
    "iso:country":"GB",
    "wof:name":"LE3 2FW",
    "wof:placetype":"postalcode"
},
  "geometry": {"coordinates":[-1.16516117112178,52.61240966826517],"type":"Point"}
}