{
  "type": "Feature",
  "properties": {
    "iso:country": "GB",
    "wof:name": "G43 2RU",
    "wof:placetype": "postalcode"
  },
  "geometry": {"coordinates":[-4.282423,55.815788],"type":"Point"}
}
