{
  "type": "Feature",
  "properties": {
    "iso:country":"GB",
    "wof:name":"EC4V 4AA",
    "wof:placetype":"postalcode"
},
  "geometry": {"coordinates":[-0.10160927198702,51.51199598487877],"type":"Point"}
}