{
  "type": "Feature",
  "properties": {
    "iso:country": "GB",
    "wof:name": "EC4V 4AA",
    "wof:placetype": "postalcode"
  },
  "geometry": {"coordinates":[-0.101609,51.511996],"type":"Point"}
}
