{
  "type": "Feature",
  "properties": {
    "iso:country":"GB",
    "wof:name":"W14 9XD",
    "wof:placetype":"postalcode"
},
  "geometry": {"coordinates":[-0.20673007544447,51.48770710513391],"type":"Point"}
}