{
  "type": "Feature",
  "properties": {
    "date:inception_lower": "1980-01-01",
    "date:inception_upper": "1980-01-01",
    "iso:country": "GB",
    "wof:name": "W14 9XD",
    "wof:placetype": "postalcode"
  },
  "geometry": {"coordinates":[-0.20673,51.487707],"type":"Point"}
}
