{
  "type": "Feature",
  "properties": {
    "iso:country": "GB",
    "wof:name": "ME8 9BU",
    "wof:placetype": "postalcode"
  },
  "geometry": {"coordinates":[0.601688,51.359063],"type":"Point"}
}
