{
  "type": "Feature",
  "properties": {
    "iso:country":"GB",
    "wof:name":"ME8 9BU",
    "wof:placetype":"postalcode"
},
  "geometry": {"coordinates":[0.60168830245878,51.35906320311724],"type":"Point"}
}