{
  "type": "Feature",
  "properties": {
    "iso:country":"GB",
    "wof:name":"SY1 2RN",
    "wof:placetype":"postalcode"
},
  "geometry": {"coordinates":[-2.75200339275461,52.71664123459946],"type":"Point"}
}