{
  "type": "Feature",
  "properties": {
    "date:inception_lower": "2009-06-01",
    "date:inception_upper": "2009-06-01",
    "iso:country": "GB",
    "wof:name": "SY1 2RN",
    "wof:placetype": "postalcode"
  },
  "geometry": {"coordinates":[-2.752003,52.716641],"type":"Point"}
}
