{
  "type": "Feature",
  "properties": {
    "iso:country": "GB",
    "wof:name": "SY3 0EA",
    "wof:placetype": "postalcode"
  },
  "geometry": {"coordinates":[-2.758965,52.674237],"type":"Point"}
}
