{
  "type": "Feature",
  "properties": {
    "date:inception_lower": "1980-01-01",
    "date:inception_upper": "1980-01-01",
    "iso:country": "GB",
    "wof:name": "SY3 0EA",
    "wof:placetype": "postalcode"
  },
  "geometry": {"coordinates":[-2.758965,52.674237],"type":"Point"}
}
