{
  "type": "Feature",
  "properties": {
    "iso:country":"GB",
    "wof:name":"SY3 0EA",
    "wof:placetype":"postalcode"
},
  "geometry": {"coordinates":[-2.75896541150252,52.6742367489241],"type":"Point"}
}