{
  "type": "Feature",
  "properties": {
    "iso:country":"GB",
    "wof:name":"DG6 4LE",
    "wof:placetype":"postalcode"
},
  "geometry": {"coordinates":[-4.05770924452972,54.83121425029115],"type":"Point"}
}