{
  "type": "Feature",
  "properties": {
    "date:inception_lower": "1980-01-01",
    "date:inception_upper": "1980-01-01",
    "iso:country": "GB",
    "wof:name": "EX16 7AD",
    "wof:placetype": "postalcode"
  },
  "geometry": {"coordinates":[-3.412784,50.907464],"type":"Point"}
}
