{
  "type": "Feature",
  "properties": {
    "iso:country":"GB",
    "wof:name":"EX16 7AD",
    "wof:placetype":"postalcode"
},
  "geometry": {"coordinates":[-3.41281309112949,50.90748848581683],"type":"Point"}
}