{
  "type": "Feature",
  "properties": {
    "iso:country":"GB",
    "wof:name":"B77 3LZ",
    "wof:placetype":"postalcode"
},
  "geometry": {"coordinates":[-1.67890355510067,52.63477343251846],"type":"Point"}
}