{
  "type": "Feature",
  "properties": {
    "date:inception_lower":"1980-01-01",
    "date:inception_upper":"1980-01-31",
    "iso:country":"GB",
    "wof:name":"SA32 7QW",
    "wof:placetype":"postalcode"
},
  "geometry": {"coordinates":[-4.184942,51.949813],"type":"Point"}
}