{
  "type": "Feature",
  "properties": {
    "iso:country":"GB",
    "wof:name":"NR34 7UX",
    "wof:placetype":"postalcode"
},
  "geometry": {"coordinates":[1.66343867987744,52.43463327123552],"type":"Point"}
}