{
  "type": "Feature",
  "properties": {
    "date:inception_lower": "2024-09-01",
    "date:inception_upper": "2024-09-01",
    "iso:country": "GB",
    "wof:name": "PE25 2FJ",
    "wof:placetype": "postalcode"
  },
  "geometry": {"coordinates":[0.334385,53.147745],"type":"Point"}
}
