{
  "type": "Feature",
  "properties": {
    "iso:country":"GB",
    "wof:name":"HP8 4JS",
    "wof:placetype":"postalcode"
},
  "geometry": {"coordinates":[-0.57837286093123,51.6306032199768],"type":"Point"}
}