{
  "type": "Feature",
  "properties": {
    "date:inception_lower":"1980-01-01",
    "date:inception_upper":"1980-01-31",
    "iso:country":"GB",
    "wof:name":"L37 4DG",
    "wof:placetype":"postalcode"
},
  "geometry": {"coordinates":[-3.063599,53.550943],"type":"Point"}
}