{
  "type": "Feature",
  "properties": {
    "iso:country":"GB",
    "wof:name":"L37 4DG",
    "wof:placetype":"postalcode"
},
  "geometry": {"coordinates":[-3.06359859023475,53.55094299873032],"type":"Point"}
}