{
  "type": "Feature",
  "properties": {
    "date:inception_lower": "1980-01-01",
    "date:inception_upper": "1980-01-01",
    "iso:country": "GB",
    "wof:name": "NG12 2HY",
    "wof:placetype": "postalcode"
  },
  "geometry": {"coordinates":[-1.016213,52.94924],"type":"Point"}
}
