{
  "type": "Feature",
  "properties": {
    "iso:country": "GB",
    "wof:name": "NG12 2HY",
    "wof:placetype": "postalcode"
  },
  "geometry": {"coordinates":[-1.016213,52.94924],"type":"Point"}
}
