{
  "type": "Feature",
  "properties": {
    "iso:country":"GB",
    "wof:name":"NG12 2HY",
    "wof:placetype":"postalcode"
},
  "geometry": {"coordinates":[-1.0162130193969,52.94924014586481],"type":"Point"}
}