{
  "type": "Feature",
  "properties": {
    "iso:country":"GB",
    "wof:name":"TW10 6EY",
    "wof:placetype":"postalcode"
},
  "geometry": {"coordinates":[-0.29444282641412,51.45930471916594],"type":"Point"}
}