{
  "type": "Feature",
  "properties": {
    "iso:country": "GB",
    "wof:name": "TW10 6EY",
    "wof:placetype": "postalcode"
  },
  "geometry": {"coordinates":[-0.294443,51.459305],"type":"Point"}
}
