{
  "type": "Feature",
  "properties": {
    "iso:country":"GB",
    "wof:name":"EN9 1BP",
    "wof:placetype":"postalcode"
},
  "geometry": {"coordinates":[-0.00842451100323,51.68686641779943],"type":"Point"}
}