{
  "type": "Feature",
  "properties": {
    "iso:country":"GB",
    "wof:name":"DL12 8LN",
    "wof:placetype":"postalcode"
},
  "geometry": {"coordinates":[-1.91055218351636,54.54823809830767],"type":"Point"}
}