{
  "type": "Feature",
  "properties": {
    "iso:country": "GB",
    "wof:name": "NR21 0PA",
    "wof:placetype": "postalcode"
  },
  "geometry": {"coordinates":[0.89878,52.84224],"type":"Point"}
}
