{
  "type": "Feature",
  "properties": {
    "iso:country":"GB",
    "wof:name":"NR21 0PA",
    "wof:placetype":"postalcode"
},
  "geometry": {"coordinates":[0.89877951891031,52.84224003587953],"type":"Point"}
}