{
  "type": "Feature",
  "properties": {
    "iso:country":"GB",
    "wof:name":"DL7 9QE",
    "wof:placetype":"postalcode"
},
  "geometry": {"coordinates":[-1.48695504444533,54.32376468522997],"type":"Point"}
}