{
  "type": "Feature",
  "properties": {
    "date:inception_lower": "2005-10-01",
    "date:inception_upper": "2005-10-01",
    "iso:country": "GB",
    "wof:name": "DL7 9QE",
    "wof:placetype": "postalcode"
  },
  "geometry": {"coordinates":[-1.486979,54.323768],"type":"Point"}
}
