{
  "type": "Feature",
  "properties": {
    "iso:country":"GB",
    "wof:name":"WA14 4UN",
    "wof:placetype":"postalcode"
},
  "geometry": {"coordinates":[-2.36797232108303,53.39337754911425],"type":"Point"}
}