{
  "type": "Feature",
  "properties": {
    "iso:country":"GB",
    "wof:name":"WV15 6PL",
    "wof:placetype":"postalcode"
},
  "geometry": {"coordinates":[-2.35218152497792,52.45908390673645],"type":"Point"}
}