{
  "type": "Feature",
  "properties": {
    "date:inception_lower":"1980-01-01",
    "date:inception_upper":"1980-01-31",
    "iso:country":"GB",
    "wof:name":"WV15 6PL",
    "wof:placetype":"postalcode"
},
  "geometry": {"coordinates":[-2.352181,52.459084],"type":"Point"}
}