{
  "type": "Feature",
  "properties": {
    "iso:country": "GB",
    "wof:name": "WV15 6PL",
    "wof:placetype": "postalcode"
  },
  "geometry": {"coordinates":[-2.352181,52.459084],"type":"Point"}
}
