{
  "type": "Feature",
  "properties": {
    "iso:country":"GB",
    "wof:name":"B92 8QZ",
    "wof:placetype":"postalcode"
},
  "geometry": {"coordinates":[-1.78802129395975,52.43623422510895],"type":"Point"}
}