{
  "type": "Feature",
  "properties": {
    "iso:country":"GB",
    "wof:name":"PO19 8RD",
    "wof:placetype":"postalcode"
},
  "geometry": {"coordinates":[-0.78938385761113,50.82509871087211],"type":"Point"}
}