{
  "type": "Feature",
  "properties": {
    "date:inception_lower": "2002-06-01",
    "date:inception_upper": "2002-06-01",
    "iso:country": "GB",
    "wof:name": "PO19 8RD",
    "wof:placetype": "postalcode"
  },
  "geometry": {"coordinates":[-0.789384,50.825099],"type":"Point"}
}
