{
  "type": "Feature",
  "properties": {
    "date:inception_lower": "2024-07-01",
    "date:inception_upper": "2024-07-01",
    "iso:country": "GB",
    "wof:name": "PE22 0FA",
    "wof:placetype": "postalcode"
  },
  "geometry": {"coordinates":[0.071386,52.983503],"type":"Point"}
}
