{
  "type": "Feature",
  "properties": {
    "date:inception_lower":"1985-08-01",
    "date:inception_upper":"1985-08-31",
    "iso:country":"GB",
    "wof:name":"ML1 3UR",
    "wof:placetype":"postalcode"
},
  "geometry": {"coordinates":[-4.009061,55.802451],"type":"Point"}
}