{
  "type": "Feature",
  "properties": {
    "iso:country":"GB",
    "wof:name":"ML1 3UR",
    "wof:placetype":"postalcode"
},
  "geometry": {"coordinates":[-4.00906107247474,55.80245074209011],"type":"Point"}
}