{
  "type": "Feature",
  "properties": {
    "iso:country":"GB",
    "wof:name":"PL1 5JF",
    "wof:placetype":"postalcode"
},
  "geometry": {"coordinates":[-4.15418614953863,50.3717784065408],"type":"Point"}
}