{
  "type": "Feature",
  "properties": {
    "iso:country":"GB",
    "wof:name":"HP22 6BA",
    "wof:placetype":"postalcode"
},
  "geometry": {"coordinates":[-0.75160854549568,51.77313003512879],"type":"Point"}
}