{
  "type": "Feature",
  "properties": {
    "date:inception_lower": "1980-01-01",
    "date:inception_upper": "1980-01-01",
    "iso:country": "GB",
    "wof:name": "HP22 6BA",
    "wof:placetype": "postalcode"
  },
  "geometry": {"coordinates":[-0.751609,51.77313],"type":"Point"}
}
