{
  "type": "Feature",
  "properties": {
    "iso:country":"GB",
    "wof:name":"SL5 8JD",
    "wof:placetype":"postalcode"
},
  "geometry": {"coordinates":[-0.69280021612812,51.4203072365798],"type":"Point"}
}