{
  "type": "Feature",
  "properties": {
    "iso:country": "GB",
    "wof:name": "SL5 8JD",
    "wof:placetype": "postalcode"
  },
  "geometry": {"coordinates":[-0.6928,51.420307],"type":"Point"}
}
