{
  "type": "Feature",
  "properties": {
    "date:inception_lower": "2004-07-01",
    "date:inception_upper": "2004-07-01",
    "iso:country": "GB",
    "wof:name": "SL5 8JD",
    "wof:placetype": "postalcode"
  },
  "geometry": {"coordinates":[-0.6928,51.420307],"type":"Point"}
}
