{
  "type": "Feature",
  "properties": {
    "iso:country":"GB",
    "wof:name":"PE14 0LA",
    "wof:placetype":"postalcode"
},
  "geometry": {"coordinates":[0.1773498962555,52.62314936806241],"type":"Point"}
}