{
  "type": "Feature",
  "properties": {
    "iso:country": "GB",
    "wof:name": "PE14 0LA",
    "wof:placetype": "postalcode"
  },
  "geometry": {"coordinates":[0.17735,52.623149],"type":"Point"}
}
