{
  "type": "Feature",
  "properties": {
    "date:inception_lower": "2007-05-01",
    "date:inception_upper": "2007-05-01",
    "iso:country": "GB",
    "wof:name": "DL8 1BF",
    "wof:placetype": "postalcode"
  },
  "geometry": {"coordinates":[-1.654363,54.339539],"type":"Point"}
}
