{
  "type": "Feature",
  "properties": {
    "date:inception_lower":"2000-06-01",
    "date:inception_upper":"2000-06-30",
    "iso:country":"GB",
    "wof:name":"WA14 2EH",
    "wof:placetype":"postalcode"
},
  "geometry": {"coordinates":[-2.34897,53.379314],"type":"Point"}
}