{
  "type": "Feature",
  "properties": {
    "iso:country":"GB",
    "wof:name":"DA1 4RA",
    "wof:placetype":"postalcode"
},
  "geometry": {"coordinates":[0.18178005948786,51.46385510884565],"type":"Point"}
}