{
  "type": "Feature",
  "properties": {
    "iso:country":"GB",
    "wof:name":"SY24 5NJ",
    "wof:placetype":"postalcode"
},
  "geometry": {"coordinates":[-4.05388813805015,52.47806721079157],"type":"Point"}
}