{
  "type": "Feature",
  "properties": {
    "date:inception_lower": "1980-01-01",
    "date:inception_upper": "1980-01-01",
    "iso:country": "GB",
    "wof:name": "SY24 5NJ",
    "wof:placetype": "postalcode"
  },
  "geometry": {"coordinates":[-4.053888,52.478067],"type":"Point"}
}
