{
  "type": "Feature",
  "properties": {
    "iso:country":"GB",
    "wof:name":"TW3 2LE",
    "wof:placetype":"postalcode"
},
  "geometry": {"coordinates":[-0.36484161013821,51.45986702784823],"type":"Point"}
}