{
  "type": "Feature",
  "properties": {
    "iso:country":"GB",
    "wof:name":"L15 9ER",
    "wof:placetype":"postalcode"
},
  "geometry": {"coordinates":[-2.90962573969264,53.39245599534563],"type":"Point"}
}