{
  "type": "Feature",
  "properties": {
    "iso:country":"GB",
    "wof:name":"NE29 6HT",
    "wof:placetype":"postalcode"
},
  "geometry": {"coordinates":[-1.47477506980074,55.0009202752289],"type":"Point"}
}