{
  "type": "Feature",
  "properties": {
    "iso:country": "GB",
    "wof:name": "CM2 9EJ",
    "wof:placetype": "postalcode"
  },
  "geometry": {"coordinates":[0.476675,51.720319],"type":"Point"}
}
