{
  "type": "Feature",
  "properties": {
    "iso:country": "GB",
    "wof:name": "DA12 3JY",
    "wof:placetype": "postalcode"
  },
  "geometry": {"coordinates":[0.435897,51.406859],"type":"Point"}
}
