{
  "type": "Feature",
  "properties": {
    "iso:country":"GB",
    "wof:name":"DA12 3JY",
    "wof:placetype":"postalcode"
},
  "geometry": {"coordinates":[0.43589701067967,51.40685888235576],"type":"Point"}
}