{
  "type": "Feature",
  "properties": {
    "iso:country":"GB",
    "wof:name":"HU3 2QQ",
    "wof:placetype":"postalcode"
},
  "geometry": {"coordinates":[-0.35930138561585,53.74132468855827],"type":"Point"}
}