{
  "type": "Feature",
  "properties": {
    "iso:country":"GB",
    "wof:name":"LE3 5QN",
    "wof:placetype":"postalcode"
},
  "geometry": {"coordinates":[-1.15156698163788,52.63339465640652],"type":"Point"}
}