{
  "type": "Feature",
  "properties": {
    "iso:country":"GB",
    "wof:name":"CM15 8BE",
    "wof:placetype":"postalcode"
},
  "geometry": {"coordinates":[0.31739240579985,51.61636485705628],"type":"Point"}
}