{
  "type": "Feature",
  "properties": {
    "iso:country": "GB",
    "wof:name": "G84 0HH",
    "wof:placetype": "postalcode"
  },
  "geometry": {"coordinates":[-4.822519,55.98426],"type":"Point"}
}
