{
  "type": "Feature",
  "properties": {
    "iso:country":"GB",
    "wof:name":"B77 2FJ",
    "wof:placetype":"postalcode"
},
  "geometry": {"coordinates":[-1.68338938922426,52.62742287807165],"type":"Point"}
}