{
  "type": "Feature",
  "properties": {
    "date:inception_lower": "2000-12-01",
    "date:inception_upper": "2000-12-01",
    "iso:country": "GB",
    "wof:name": "B77 2FJ",
    "wof:placetype": "postalcode"
  },
  "geometry": {"coordinates":[-1.683389,52.627423],"type":"Point"}
}
