{
  "type": "Feature",
  "properties": {
    "iso:country": "GB",
    "wof:name": "SL3 0JL",
    "wof:placetype": "postalcode"
  },
  "geometry": {"coordinates":[-0.52129,51.482366],"type":"Point"}
}
