{
  "type": "Feature",
  "properties": {
    "iso:country":"GB",
    "wof:name":"SL3 0JL",
    "wof:placetype":"postalcode"
},
  "geometry": {"coordinates":[-0.52129016607796,51.482365628464],"type":"Point"}
}