{
  "type": "Feature",
  "properties": {
    "iso:country":"GB",
    "wof:name":"NG2 1JU",
    "wof:placetype":"postalcode"
},
  "geometry": {"coordinates":[-1.15420875940886,52.93950559093874],"type":"Point"}
}