{
  "type": "Feature",
  "properties": {
    "iso:country":"GB",
    "wof:name":"BS21 6YR",
    "wof:placetype":"postalcode"
},
  "geometry": {"coordinates":[-2.84172155055864,51.43650142460937],"type":"Point"}
}