{
  "type": "Feature",
  "properties": {
    "iso:country":"GB",
    "wof:name":"LE14 3AU",
    "wof:placetype":"postalcode"
},
  "geometry": {"coordinates":[-0.92502504201593,52.80063151826404],"type":"Point"}
}