{
  "type": "Feature",
  "properties": {
    "date:inception_lower": "2013-09-01",
    "date:inception_upper": "2013-09-01",
    "iso:country": "GB",
    "wof:name": "LE14 3AU",
    "wof:placetype": "postalcode"
  },
  "geometry": {"coordinates":[-0.92473,52.800281],"type":"Point"}
}
