{
  "type": "Feature",
  "properties": {
    "date:inception_lower":"2011-10-01",
    "date:inception_upper":"2011-10-31",
    "iso:country":"GB",
    "wof:name":"NE3 4BF",
    "wof:placetype":"postalcode"
},
  "geometry": {"coordinates":[-1.626611,55.0014],"type":"Point"}
}