{
  "type": "Feature",
  "properties": {
    "date:inception_lower": "2000-06-01",
    "date:inception_upper": "2000-06-01",
    "iso:country": "GB",
    "wof:name": "PE28 2RH",
    "wof:placetype": "postalcode"
  },
  "geometry": {"coordinates":[-0.083498,52.403461],"type":"Point"}
}
