{
  "type": "Feature",
  "properties": {
    "iso:country":"GB",
    "wof:name":"LE12 8JW",
    "wof:placetype":"postalcode"
},
  "geometry": {"coordinates":[-1.14751480515833,52.75438753044908],"type":"Point"}
}