{
  "type": "Feature",
  "properties": {
    "date:inception_lower": "2017-04-01",
    "date:inception_upper": "2017-04-01",
    "iso:country": "GB",
    "wof:name": "LS27 8WT",
    "wof:placetype": "postalcode"
  },
  "geometry": {"coordinates":[-1.588281,53.748382],"type":"Point"}
}
