{
  "type": "Feature",
  "properties": {
    "iso:country": "GB",
    "wof:name": "WA3 2EQ",
    "wof:placetype": "postalcode"
  },
  "geometry": {"coordinates":[-2.578844,53.477493],"type":"Point"}
}
