{
  "type": "Feature",
  "properties": {
    "date:inception_lower": "1980-01-01",
    "date:inception_upper": "1980-01-01",
    "iso:country": "GB",
    "wof:name": "AL6 0JN",
    "wof:placetype": "postalcode"
  },
  "geometry": {"coordinates":[-0.161217,51.814553],"type":"Point"}
}
