{
  "type": "Feature",
  "properties": {
    "iso:country":"GB",
    "wof:name":"AL6 0JN",
    "wof:placetype":"postalcode"
},
  "geometry": {"coordinates":[-0.15960367254088,51.81454826683174],"type":"Point"}
}