{
  "type": "Feature",
  "properties": {
    "iso:country":"GB",
    "wof:name":"BA7 7LD",
    "wof:placetype":"postalcode"
},
  "geometry": {"coordinates":[-2.51707799603718,51.09436228255293],"type":"Point"}
}