{
  "type": "Feature",
  "properties": {
    "iso:country": "GB",
    "wof:name": "BA7 7LD",
    "wof:placetype": "postalcode"
  },
  "geometry": {"coordinates":[-2.517078,51.094362],"type":"Point"}
}
