{
  "type": "Feature",
  "properties": {
    "iso:country":"GB",
    "wof:name":"WD6 1SP",
    "wof:placetype":"postalcode"
},
  "geometry": {"coordinates":[-0.26995193353006,51.65219949877378],"type":"Point"}
}