{
  "type": "Feature",
  "properties": {
    "iso:country":"GB",
    "wof:name":"N15 3BP",
    "wof:placetype":"postalcode"
},
  "geometry": {"coordinates":[-0.09012146958864,51.58573695537574],"type":"Point"}
}