{
  "type": "Feature",
  "properties": {
    "date:inception_lower": "1980-01-01",
    "date:inception_upper": "1980-01-01",
    "iso:country": "GB",
    "wof:name": "WR6 5SG",
    "wof:placetype": "postalcode"
  },
  "geometry": {"coordinates":[-2.433868,52.20642],"type":"Point"}
}
