{
  "type": "Feature",
  "properties": {
    "iso:country":"GB",
    "wof:name":"WR6 5SG",
    "wof:placetype":"postalcode"
},
  "geometry": {"coordinates":[-2.43386844068743,52.20642007879272],"type":"Point"}
}