{
  "type": "Feature",
  "properties": {
    "iso:country": "GB",
    "wof:name": "NG3 6GN",
    "wof:placetype": "postalcode"
  },
  "geometry": {"coordinates":[-1.124026,52.978735],"type":"Point"}
}
