{
  "type": "Feature",
  "properties": {
    "iso:country":"GB",
    "wof:name":"NG3 6GN",
    "wof:placetype":"postalcode"
},
  "geometry": {"coordinates":[-1.12401245759056,52.97878683275113],"type":"Point"}
}