{
  "type": "Feature",
  "properties": {
    "iso:country": "GB",
    "wof:name": "NG3 6GN",
    "wof:placetype": "postalcode"
  },
  "geometry": {"coordinates":[-1.12401,52.978807],"type":"Point"}
}
