{
  "type": "Feature",
  "properties": {
    "iso:country": "GB",
    "wof:name": "CF33 6LH",
    "wof:placetype": "postalcode"
  },
  "geometry": {"coordinates":[-3.688496,51.532004],"type":"Point"}
}
