{
  "type": "Feature",
  "properties": {
    "date:inception_lower": "1980-01-01",
    "date:inception_upper": "1980-01-01",
    "iso:country": "GB",
    "wof:name": "CF33 6LH",
    "wof:placetype": "postalcode"
  },
  "geometry": {"coordinates":[-3.688496,51.532004],"type":"Point"}
}
