{
  "type": "Feature",
  "properties": {
    "date:inception_lower": "1980-01-01",
    "date:inception_upper": "1980-01-01",
    "iso:country": "GB",
    "wof:name": "DN17 4AP",
    "wof:placetype": "postalcode"
  },
  "geometry": {"coordinates":[-0.712827,53.617022],"type":"Point"}
}
