{
  "type": "Feature",
  "properties": {
    "iso:country":"GB",
    "wof:name":"DN17 4AP",
    "wof:placetype":"postalcode"
},
  "geometry": {"coordinates":[-0.71282743661804,53.61702184171094],"type":"Point"}
}