{
  "type": "Feature",
  "properties": {
    "iso:country": "GB",
    "wof:name": "DN17 4AP",
    "wof:placetype": "postalcode"
  },
  "geometry": {"coordinates":[-0.712827,53.617022],"type":"Point"}
}
