{
  "type": "Feature",
  "properties": {
    "date:inception_lower": "2019-06-01",
    "date:inception_upper": "2019-06-01",
    "iso:country": "GB",
    "wof:name": "RH19 2SX",
    "wof:placetype": "postalcode"
  },
  "geometry": {"coordinates":[-0.041896,51.139119],"type":"Point"}
}
