{
  "type": "Feature",
  "properties": {
    "iso:country": "GB",
    "wof:name": "N1 3FW",
    "wof:placetype": "postalcode"
  },
  "geometry": {"coordinates":[-0.084936,51.544316],"type":"Point"}
}
