{
  "type": "Feature",
  "properties": {
    "iso:country":"GB",
    "wof:name":"NN29 7JX",
    "wof:placetype":"postalcode"
},
  "geometry": {"coordinates":[-0.67546355550051,52.22015242672839],"type":"Point"}
}