{
  "type": "Feature",
  "properties": {
    "iso:country":"GB",
    "wof:name":"DD3 0JF",
    "wof:placetype":"postalcode"
},
  "geometry": {"coordinates":[-2.98776539708405,56.491249610448],"type":"Point"}
}