{
  "type": "Feature",
  "properties": {
    "iso:country":"GB",
    "wof:name":"B75 5BP",
    "wof:placetype":"postalcode"
},
  "geometry": {"coordinates":[-1.82740052661618,52.58643882280865],"type":"Point"}
}