{
  "type": "Feature",
  "properties": {
    "iso:country": "GB",
    "wof:name": "NW11 8NE",
    "wof:placetype": "postalcode"
  },
  "geometry": {"coordinates":[-0.196908,51.569157],"type":"Point"}
}
