{
  "type": "Feature",
  "properties": {
    "iso:country": "GB",
    "wof:name": "SL6 7GY",
    "wof:placetype": "postalcode"
  },
  "geometry": {"coordinates":[-0.724109,51.534755],"type":"Point"}
}
