{
  "type": "Feature",
  "properties": {
    "iso:country":"GB",
    "wof:name":"WS2 7EH",
    "wof:placetype":"postalcode"
},
  "geometry": {"coordinates":[-2.00178771035739,52.60261094877861],"type":"Point"}
}