{
  "type": "Feature",
  "properties": {
    "iso:country":"GB",
    "wof:name":"ML2 0BU",
    "wof:placetype":"postalcode"
},
  "geometry": {"coordinates":[-3.95440376625407,55.76724046086862],"type":"Point"}
}