{
  "type": "Feature",
  "properties": {
    "iso:country":"GB",
    "wof:name":"M31 4LR",
    "wof:placetype":"postalcode"
},
  "geometry": {"coordinates":[-2.43544595872827,53.41548713427662],"type":"Point"}
}