{
  "type": "Feature",
  "properties": {
    "iso:country":"GB",
    "wof:name":"CO14 8JR",
    "wof:placetype":"postalcode"
},
  "geometry": {"coordinates":[1.28159542209043,51.85972069440493],"type":"Point"}
}