{
  "type": "Feature",
  "properties": {
    "iso:country": "GB",
    "wof:name": "YO22 5HU",
    "wof:placetype": "postalcode"
  },
  "geometry": {"coordinates":[-0.643674,54.45313],"type":"Point"}
}
