{
  "type": "Feature",
  "properties": {
    "date:inception_lower":"1989-07-01",
    "date:inception_upper":"1989-07-31",
    "iso:country":"GB",
    "wof:name":"PA8 7BJ",
    "wof:placetype":"postalcode"
},
  "geometry": {"coordinates":[-4.430308,55.896481],"type":"Point"}
}