{
  "type": "Feature",
  "properties": {
    "iso:country":"GB",
    "wof:name":"PA8 7BJ",
    "wof:placetype":"postalcode"
},
  "geometry": {"coordinates":[-4.43036938814754,55.89645887198376],"type":"Point"}
}