{
  "type": "Feature",
  "properties": {
    "iso:country": "GB",
    "wof:name": "ST6 2DZ",
    "wof:placetype": "postalcode"
  },
  "geometry": {"coordinates":[-2.181084,53.045354],"type":"Point"}
}
