{
  "type": "Feature",
  "properties": {
    "iso:country":"GB",
    "wof:name":"GU6 7AN",
    "wof:placetype":"postalcode"
},
  "geometry": {"coordinates":[-0.4867374365648,51.14355751653608],"type":"Point"}
}