{
  "type": "Feature",
  "properties": {
    "date:inception_lower":"1980-01-01",
    "date:inception_upper":"1980-01-31",
    "iso:country":"GB",
    "wof:name":"BH6 3LD",
    "wof:placetype":"postalcode"
},
  "geometry": {"coordinates":[-1.791786,50.729008],"type":"Point"}
}