{
  "type": "Feature",
  "properties": {
    "iso:country": "GB",
    "wof:name": "BH6 3LD",
    "wof:placetype": "postalcode"
  },
  "geometry": {"coordinates":[-1.791786,50.729008],"type":"Point"}
}
