{
  "type": "Feature",
  "properties": {
    "iso:country":"GB",
    "wof:name":"BH6 3LD",
    "wof:placetype":"postalcode"
},
  "geometry": {"coordinates":[-1.79178568363194,50.72900809115648],"type":"Point"}
}