{
  "type": "Feature",
  "properties": {
    "iso:country":"GB",
    "wof:name":"DT11 9JW",
    "wof:placetype":"postalcode"
},
  "geometry": {"coordinates":[-2.08405657084386,50.81861231001113],"type":"Point"}
}