{
  "type": "Feature",
  "properties": {
    "iso:country": "GB",
    "wof:name": "DT11 9JW",
    "wof:placetype": "postalcode"
  },
  "geometry": {"coordinates":[-2.084057,50.818612],"type":"Point"}
}
