{
  "type": "Feature",
  "properties": {
    "date:inception_lower": "1980-01-01",
    "date:inception_upper": "1980-01-01",
    "iso:country": "GB",
    "wof:name": "DT11 9JW",
    "wof:placetype": "postalcode"
  },
  "geometry": {"coordinates":[-2.084057,50.818612],"type":"Point"}
}
