{
  "type": "Feature",
  "properties": {
    "iso:country":"GB",
    "wof:name":"LA14 5QR",
    "wof:placetype":"postalcode"
},
  "geometry": {"coordinates":[-3.22611276850829,54.11667072652823],"type":"Point"}
}