{
  "type": "Feature",
  "properties": {
    "date:inception_lower": "1980-01-01",
    "date:inception_upper": "1980-01-01",
    "iso:country": "GB",
    "wof:name": "LA14 5QR",
    "wof:placetype": "postalcode"
  },
  "geometry": {"coordinates":[-3.226113,54.116671],"type":"Point"}
}
