{
  "type": "Feature",
  "properties": {
    "iso:country": "GB",
    "wof:name": "OX9 7BD",
    "wof:placetype": "postalcode"
  },
  "geometry": {"coordinates":[-1.017277,51.72368],"type":"Point"}
}
