{
  "type": "Feature",
  "properties": {
    "date:inception_lower": "2008-05-01",
    "date:inception_upper": "2008-05-01",
    "iso:country": "GB",
    "wof:name": "EX10 8TD",
    "wof:placetype": "postalcode"
  },
  "geometry": {"coordinates":[-3.238042,50.683237],"type":"Point"}
}
