{
  "type": "Feature",
  "properties": {
    "date:inception_lower":"1980-01-01",
    "date:inception_upper":"1980-01-31",
    "iso:country":"GB",
    "wof:name":"G78 4BN",
    "wof:placetype":"postalcode"
},
  "geometry": {"coordinates":[-4.544912,55.769765],"type":"Point"}
}