{
  "type": "Feature",
  "properties": {
    "iso:country":"GB",
    "wof:name":"G78 4BN",
    "wof:placetype":"postalcode"
},
  "geometry": {"coordinates":[-4.54491218474431,55.7697647156449],"type":"Point"}
}