{
  "type": "Feature",
  "properties": {
    "iso:country": "GB",
    "wof:name": "G78 4BN",
    "wof:placetype": "postalcode"
  },
  "geometry": {"coordinates":[-4.544912,55.769765],"type":"Point"}
}
