{
  "type": "Feature",
  "properties": {
    "iso:country": "GB",
    "wof:name": "M16 8JR",
    "wof:placetype": "postalcode"
  },
  "geometry": {"coordinates":[-2.262607,53.447408],"type":"Point"}
}
