{
  "type": "Feature",
  "properties": {
    "iso:country":"GB",
    "wof:name":"M16 8JR",
    "wof:placetype":"postalcode"
},
  "geometry": {"coordinates":[-2.26260687367352,53.44740754601823],"type":"Point"}
}