{
  "type": "Feature",
  "properties": {
    "iso:country":"GB",
    "wof:name":"CR5 3TE",
    "wof:placetype":"postalcode"
},
  "geometry": {"coordinates":[-0.17128131203459,51.30966310385694],"type":"Point"}
}