{
  "type": "Feature",
  "properties": {
    "iso:country":"GB",
    "wof:name":"G45 9AR",
    "wof:placetype":"postalcode"
},
  "geometry": {"coordinates":[-4.23553815687389,55.80431022490519],"type":"Point"}
}