{
  "type": "Feature",
  "properties": {
    "iso:country":"GB",
    "wof:name":"IP13 7NE",
    "wof:placetype":"postalcode"
},
  "geometry": {"coordinates":[1.29213948569144,52.24637550464885],"type":"Point"}
}