{
  "type": "Feature",
  "properties": {
    "iso:country": "GB",
    "wof:name": "TF4 3GL",
    "wof:placetype": "postalcode"
  },
  "geometry": {"coordinates":[-2.451626,52.66311],"type":"Point"}
}
