{
  "type": "Feature",
  "properties": {
    "iso:country": "GB",
    "wof:name": "SA10 7ED",
    "wof:placetype": "postalcode"
  },
  "geometry": {"coordinates":[-3.818825,51.677044],"type":"Point"}
}
