{
  "type": "Feature",
  "properties": {
    "iso:country": "GB",
    "wof:name": "KA1 5FA",
    "wof:placetype": "postalcode"
  },
  "geometry": {"coordinates":[-4.451113,55.598263],"type":"Point"}
}
