{
  "type": "Feature",
  "properties": {
    "iso:country":"GB",
    "wof:name":"IG10 3JQ",
    "wof:placetype":"postalcode"
},
  "geometry": {"coordinates":[0.07031779100496,51.64554185091773],"type":"Point"}
}