{
  "type": "Feature",
  "properties": {
    "iso:country":"GB",
    "wof:name":"TA3 5HU",
    "wof:placetype":"postalcode"
},
  "geometry": {"coordinates":[-3.04593756902088,51.0119709893442],"type":"Point"}
}