{
  "type": "Feature",
  "properties": {
    "iso:country":"GB",
    "wof:name":"ME9 0JT",
    "wof:placetype":"postalcode"
},
  "geometry": {"coordinates":[0.78724032495515,51.29649379707406],"type":"Point"}
}