{
  "type": "Feature",
  "properties": {
    "iso:country": "GB",
    "wof:name": "ME9 0JT",
    "wof:placetype": "postalcode"
  },
  "geometry": {"coordinates":[0.78724,51.296494],"type":"Point"}
}
