{
  "type": "Feature",
  "properties": {
    "iso:country":"GB",
    "wof:name":"EN7 6LF",
    "wof:placetype":"postalcode"
},
  "geometry": {"coordinates":[-0.05017913615523,51.70971519062566],"type":"Point"}
}