{
  "type": "Feature",
  "properties": {
    "iso:country":"GB",
    "wof:name":"BN1 8LG",
    "wof:placetype":"postalcode"
},
  "geometry": {"coordinates":[-0.13743142308256,50.86147991768176],"type":"Point"}
}