{
  "type": "Feature",
  "properties": {
    "date:inception_lower": "1984-10-01",
    "date:inception_upper": "1984-10-01",
    "iso:country": "GB",
    "wof:name": "PO20 8QX",
    "wof:placetype": "postalcode"
  },
  "geometry": {"coordinates":[-0.87111,50.769065],"type":"Point"}
}
