{
  "type": "Feature",
  "properties": {
    "date:inception_lower": "1980-01-01",
    "date:inception_upper": "1980-01-01",
    "iso:country": "GB",
    "wof:name": "NE46 3JT",
    "wof:placetype": "postalcode"
  },
  "geometry": {"coordinates":[-2.113021,54.972103],"type":"Point"}
}
