{
  "type": "Feature",
  "properties": {
    "iso:country": "GB",
    "wof:name": "NE46 3JT",
    "wof:placetype": "postalcode"
  },
  "geometry": {"coordinates":[-2.113021,54.972103],"type":"Point"}
}
