{
  "type": "Feature",
  "properties": {
    "iso:country":"GB",
    "wof:name":"NE46 3JT",
    "wof:placetype":"postalcode"
},
  "geometry": {"coordinates":[-2.11302154929856,54.97210297635462],"type":"Point"}
}