{
  "type": "Feature",
  "properties": {
    "iso:country": "GB",
    "wof:name": "NG17 5BN",
    "wof:placetype": "postalcode"
  },
  "geometry": {"coordinates":[-1.263436,53.116738],"type":"Point"}
}
