{
  "type": "Feature",
  "properties": {
    "iso:country":"GB",
    "wof:name":"FK2 7QB",
    "wof:placetype":"postalcode"
},
  "geometry": {"coordinates":[-3.79021421447827,56.01864936076924],"type":"Point"}
}