{
  "type": "Feature",
  "properties": {
    "iso:country": "GB",
    "wof:name": "FK2 7QB",
    "wof:placetype": "postalcode"
  },
  "geometry": {"coordinates":[-3.790214,56.018649],"type":"Point"}
}
