{
  "type": "Feature",
  "properties": {
    "date:inception_lower": "2019-09-01",
    "date:inception_upper": "2019-09-01",
    "iso:country": "GB",
    "wof:name": "CO16 0EW",
    "wof:placetype": "postalcode"
  },
  "geometry": {"coordinates":[1.172513,51.859832],"type":"Point"}
}
