{
  "type": "Feature",
  "properties": {
    "iso:country": "GB",
    "wof:name": "NE61 2GE",
    "wof:placetype": "postalcode"
  },
  "geometry": {"coordinates":[-1.68224,55.174175],"type":"Point"}
}
