{
  "type": "Feature",
  "properties": {
    "iso:country":"GB",
    "wof:name":"DD3 7LL",
    "wof:placetype":"postalcode"
},
  "geometry": {"coordinates":[-2.96640478827832,56.47705152969925],"type":"Point"}
}