{
  "type": "Feature",
  "properties": {
    "iso:country":"GB",
    "wof:name":"SN8 2DR",
    "wof:placetype":"postalcode"
},
  "geometry": {"coordinates":[-1.61315751437155,51.4730376507046],"type":"Point"}
}