{
  "type": "Feature",
  "properties": {
    "iso:country": "GB",
    "wof:name": "G61 4NX",
    "wof:placetype": "postalcode"
  },
  "geometry": {"coordinates":[-4.340346,55.923836],"type":"Point"}
}
