{
  "type": "Feature",
  "properties": {
    "iso:country":"GB",
    "wof:name":"HA4 0SE",
    "wof:placetype":"postalcode"
},
  "geometry": {"coordinates":[-0.39699932421799,51.56088026407725],"type":"Point"}
}