{
  "type": "Feature",
  "properties": {
    "iso:country":"GB",
    "wof:name":"AL8 6XS",
    "wof:placetype":"postalcode"
},
  "geometry": {"coordinates":[-0.22001733342689,51.7927554797127],"type":"Point"}
}