{
  "type": "Feature",
  "properties": {
    "date:inception_lower": "1980-01-01",
    "date:inception_upper": "1980-01-01",
    "iso:country": "GB",
    "wof:name": "AL8 6XS",
    "wof:placetype": "postalcode"
  },
  "geometry": {"coordinates":[-0.219997,51.792672],"type":"Point"}
}
