{
  "type": "Feature",
  "properties": {
    "iso:country":"GB",
    "wof:name":"RH19 3TD",
    "wof:placetype":"postalcode"
},
  "geometry": {"coordinates":[0.02026718930578,51.11174205081283],"type":"Point"}
}