{
  "type": "Feature",
  "properties": {
    "iso:country":"GB",
    "wof:name":"WD7 9LD",
    "wof:placetype":"postalcode"
},
  "geometry": {"coordinates":[-0.28877351699463,51.69364119952585],"type":"Point"}
}