{
  "type": "Feature",
  "properties": {
    "iso:country":"GB",
    "wof:name":"NE6 4YD",
    "wof:placetype":"postalcode"
},
  "geometry": {"coordinates":[-1.5488075997788,54.98457461146998],"type":"Point"}
}