{
  "type": "Feature",
  "properties": {
    "iso:country":"GB",
    "wof:name":"TA1 3BU",
    "wof:placetype":"postalcode"
},
  "geometry": {"coordinates":[-3.08699023410049,51.00336798445159],"type":"Point"}
}