{
  "type": "Feature",
  "properties": {
    "date:inception_lower": "1991-09-01",
    "date:inception_upper": "1991-09-01",
    "iso:country": "GB",
    "wof:name": "BB9 0YE",
    "wof:placetype": "postalcode"
  },
  "geometry": {"coordinates":[-2.220826,53.817915],"type":"Point"}
}
