{
  "type": "Feature",
  "properties": {
    "date:inception_lower": "1991-09-01",
    "date:inception_upper": "1991-09-01",
    "iso:country": "GB",
    "wof:name": "BB9 0YE",
    "wof:placetype": "postalcode"
  },
  "geometry": {"coordinates":[-2.220828,53.817938],"type":"Point"}
}
