{
  "type": "Feature",
  "properties": {
    "iso:country":"GB",
    "wof:name":"LS25 3AE",
    "wof:placetype":"postalcode"
},
  "geometry": {"coordinates":[-1.34160714418865,53.83249181674339],"type":"Point"}
}