{
  "type": "Feature",
  "properties": {
    "iso:country":"GB",
    "wof:name":"BN20 9ND",
    "wof:placetype":"postalcode"
},
  "geometry": {"coordinates":[0.24885844268396,50.81145857229485],"type":"Point"}
}