{
  "type": "Feature",
  "properties": {
    "date:inception_lower": "1980-01-01",
    "date:inception_upper": "1980-01-01",
    "iso:country": "GB",
    "wof:name": "SA19 6DU",
    "wof:placetype": "postalcode"
  },
  "geometry": {"coordinates":[-3.995221,51.885777],"type":"Point"}
}
