{
  "type": "Feature",
  "properties": {
    "iso:country":"GB",
    "wof:name":"SA19 6DU",
    "wof:placetype":"postalcode"
},
  "geometry": {"coordinates":[-3.99522077003998,51.88577712875314],"type":"Point"}
}