{
  "type": "Feature",
  "properties": {
    "iso:country":"GB",
    "wof:name":"BH14 8AY",
    "wof:placetype":"postalcode"
},
  "geometry": {"coordinates":[-1.95484355128033,50.72077672807252],"type":"Point"}
}