{
  "type": "Feature",
  "properties": {
    "iso:country": "GB",
    "wof:name": "G73 3JG",
    "wof:placetype": "postalcode"
  },
  "geometry": {"coordinates":[-4.197016,55.825523],"type":"Point"}
}
