{
  "type": "Feature",
  "properties": {
    "iso:country": "GB",
    "wof:name": "PL10 1NS",
    "wof:placetype": "postalcode"
  },
  "geometry": {"coordinates":[-4.202009,50.336074],"type":"Point"}
}
