{
  "type": "Feature",
  "properties": {
    "iso:country":"GB",
    "wof:name":"BL9 6ST",
    "wof:placetype":"postalcode"
},
  "geometry": {"coordinates":[-2.27939579681261,53.61013125165906],"type":"Point"}
}