{
  "type": "Feature",
  "properties": {
    "date:inception_lower": "1980-01-01",
    "date:inception_upper": "1980-01-01",
    "iso:country": "GB",
    "wof:name": "BL9 6ST",
    "wof:placetype": "postalcode"
  },
  "geometry": {"coordinates":[-2.279396,53.610131],"type":"Point"}
}
