{
  "type": "Feature",
  "properties": {
    "iso:country":"GB",
    "wof:name":"OX15 6HZ",
    "wof:placetype":"postalcode"
},
  "geometry": {"coordinates":[-1.44620350160167,52.08880028632584],"type":"Point"}
}