{
  "type": "Feature",
  "properties": {
    "date:inception_lower": "1980-01-01",
    "date:inception_upper": "1980-01-01",
    "iso:country": "GB",
    "wof:name": "OX15 6HZ",
    "wof:placetype": "postalcode"
  },
  "geometry": {"coordinates":[-1.446203,52.0888],"type":"Point"}
}
