{
  "type": "Feature",
  "properties": {
    "iso:country": "GB",
    "wof:name": "OX15 6HZ",
    "wof:placetype": "postalcode"
  },
  "geometry": {"coordinates":[-1.446203,52.0888],"type":"Point"}
}
