{
  "type": "Feature",
  "properties": {
    "iso:country":"GB",
    "wof:name":"KY12 7HU",
    "wof:placetype":"postalcode"
},
  "geometry": {"coordinates":[-3.45491769926008,56.06892417948215],"type":"Point"}
}