{
  "type": "Feature",
  "properties": {
    "iso:country": "GB",
    "wof:name": "SP10 3DH",
    "wof:placetype": "postalcode"
  },
  "geometry": {"coordinates":[-1.4976,51.211703],"type":"Point"}
}
