{
  "type": "Feature",
  "properties": {
    "iso:country": "GB",
    "wof:name": "S6 2LZ",
    "wof:placetype": "postalcode"
  },
  "geometry": {"coordinates":[-1.499932,53.402625],"type":"Point"}
}
