{
  "type": "Feature",
  "properties": {
    "iso:country":"GB",
    "wof:name":"S6 2LZ",
    "wof:placetype":"postalcode"
},
  "geometry": {"coordinates":[-1.49993180724384,53.40262503605407],"type":"Point"}
}