{
  "type": "Feature",
  "properties": {
    "date:inception_lower": "2000-06-01",
    "date:inception_upper": "2000-06-01",
    "iso:country": "GB",
    "wof:name": "BH21 3YH",
    "wof:placetype": "postalcode"
  },
  "geometry": {"coordinates":[-1.984908,50.79795],"type":"Point"}
}
