{
  "type": "Feature",
  "properties": {
    "iso:country":"GB",
    "wof:name":"W14 9JB",
    "wof:placetype":"postalcode"
},
  "geometry": {"coordinates":[-0.20953882940174,51.48844244302533],"type":"Point"}
}