{
  "type": "Feature",
  "properties": {
    "iso:country": "GB",
    "wof:name": "SO19 4EB",
    "wof:placetype": "postalcode"
  },
  "geometry": {"coordinates":[-1.367555,50.912863],"type":"Point"}
}
