{
  "type": "Feature",
  "properties": {
    "iso:country":"GB",
    "wof:name":"SO19 4EB",
    "wof:placetype":"postalcode"
},
  "geometry": {"coordinates":[-1.36755491709923,50.91286279345159],"type":"Point"}
}