{
  "type": "Feature",
  "properties": {
    "iso:country": "GB",
    "wof:name": "SG7 5PH",
    "wof:placetype": "postalcode"
  },
  "geometry": {"coordinates":[-0.158355,52.039461],"type":"Point"}
}
