{
  "type": "Feature",
  "properties": {
    "iso:country":"GB",
    "wof:name":"SG7 5PH",
    "wof:placetype":"postalcode"
},
  "geometry": {"coordinates":[-0.15835543861205,52.03946145880859],"type":"Point"}
}