{
  "type": "Feature",
  "properties": {
    "date:inception_lower": "1994-05-01",
    "date:inception_upper": "1994-05-01",
    "iso:country": "GB",
    "wof:name": "CA14 4PF",
    "wof:placetype": "postalcode"
  },
  "geometry": {"coordinates":[-3.552786,54.613908],"type":"Point"}
}
