{
  "type": "Feature",
  "properties": {
    "date:inception_lower":"2015-07-01",
    "date:inception_upper":"2015-07-31",
    "iso:country":"GB",
    "wof:name":"EX22 7FH",
    "wof:placetype":"postalcode"
},
  "geometry": {"coordinates":[-4.322239,50.943395],"type":"Point"}
}