{
  "type": "Feature",
  "properties": {
    "iso:country":"GB",
    "wof:name":"EX22 7FH",
    "wof:placetype":"postalcode"
},
  "geometry": {"coordinates":[-4.38506096459109,50.90275648978102],"type":"Point"}
}