{
  "type": "Feature",
  "properties": {
    "iso:country": "GB",
    "wof:name": "EX22 7FH",
    "wof:placetype": "postalcode"
  },
  "geometry": {"coordinates":[-4.322239,50.943395],"type":"Point"}
}
