{
  "type": "Feature",
  "properties": {
    "date:inception_lower": "1980-01-01",
    "date:inception_upper": "1980-01-01",
    "iso:country": "GB",
    "wof:name": "PL5 1PS",
    "wof:placetype": "postalcode"
  },
  "geometry": {"coordinates":[-4.181107,50.40586],"type":"Point"}
}
