{
  "type": "Feature",
  "properties": {
    "date:inception_lower":"1995-12-01",
    "date:inception_upper":"1995-12-31",
    "iso:country":"GB",
    "wof:name":"DN9 3QE",
    "wof:placetype":"postalcode"
},
  "geometry": {"coordinates":[-1.026753,53.503519],"type":"Point"}
}