{
  "type": "Feature",
  "properties": {
    "iso:country": "GB",
    "wof:name": "DN9 3QE",
    "wof:placetype": "postalcode"
  },
  "geometry": {"coordinates":[-1.026753,53.503519],"type":"Point"}
}
