{
  "type": "Feature",
  "properties": {
    "iso:country":"GB",
    "wof:name":"DN9 3QE",
    "wof:placetype":"postalcode"
},
  "geometry": {"coordinates":[-1.0267533328664,53.50351922913573],"type":"Point"}
}