{
  "type": "Feature",
  "properties": {
    "iso:country":"GB",
    "wof:name":"RG9 3JE",
    "wof:placetype":"postalcode"
},
  "geometry": {"coordinates":[-0.89273565046193,51.5363020914332],"type":"Point"}
}