{
  "type": "Feature",
  "properties": {
    "iso:country": "GB",
    "wof:name": "GU7 1BF",
    "wof:placetype": "postalcode"
  },
  "geometry": {"coordinates":[-0.614722,51.18436],"type":"Point"}
}
