{
  "type": "Feature",
  "properties": {
    "iso:country":"GB",
    "wof:name":"GU7 1BF",
    "wof:placetype":"postalcode"
},
  "geometry": {"coordinates":[-0.61472212927508,51.18435978519145],"type":"Point"}
}