{
  "type": "Feature",
  "properties": {
    "date:inception_lower": "2022-07-01",
    "date:inception_upper": "2022-07-01",
    "iso:country": "GB",
    "wof:name": "BN18 0RF",
    "wof:placetype": "postalcode"
  },
  "geometry": {"coordinates":[-0.618226,50.822388],"type":"Point"}
}
