{
  "type": "Feature",
  "properties": {
    "date:inception_lower": "1991-09-01",
    "date:inception_upper": "1991-09-01",
    "iso:country": "GB",
    "wof:name": "MK43 8HN",
    "wof:placetype": "postalcode"
  },
  "geometry": {"coordinates":[-0.525189,52.152618],"type":"Point"}
}
