{
  "type": "Feature",
  "properties": {
    "iso:country": "GB",
    "wof:name": "SO15 9JS",
    "wof:placetype": "postalcode"
  },
  "geometry": {"coordinates":[-1.430781,50.919231],"type":"Point"}
}
