{
  "type": "Feature",
  "properties": {
    "iso:country": "GB",
    "wof:name": "DY8 3LR",
    "wof:placetype": "postalcode"
  },
  "geometry": {"coordinates":[-2.170948,52.453588],"type":"Point"}
}
