{
  "type": "Feature",
  "properties": {
    "iso:country":"GB",
    "wof:name":"BA15 1PN",
    "wof:placetype":"postalcode"
},
  "geometry": {"coordinates":[-2.26274466355079,51.3489628040307],"type":"Point"}
}