{
  "type": "Feature",
  "properties": {
    "iso:country":"GB",
    "wof:name":"SE2 9BS",
    "wof:placetype":"postalcode"
},
  "geometry": {"coordinates":[0.12176330225996,51.50025377817688],"type":"Point"}
}