{
  "type": "Feature",
  "properties": {
    "iso:country": "GB",
    "wof:name": "SE2 9BS",
    "wof:placetype": "postalcode"
  },
  "geometry": {"coordinates":[0.121763,51.500254],"type":"Point"}
}
