{
  "type": "Feature",
  "properties": {
    "iso:country":"GB",
    "wof:name":"FY7 6HN",
    "wof:placetype":"postalcode"
},
  "geometry": {"coordinates":[-3.00994611678952,53.92673047319072],"type":"Point"}
}