{
  "type": "Feature",
  "properties": {
    "iso:country":"GB",
    "wof:name":"CW5 7BS",
    "wof:placetype":"postalcode"
},
  "geometry": {"coordinates":[-2.51748838979127,53.0616259805138],"type":"Point"}
}