{
  "type": "Feature",
  "properties": {
    "iso:country": "GB",
    "wof:name": "TQ13 7EP",
    "wof:placetype": "postalcode"
  },
  "geometry": {"coordinates":[-3.746732,50.525142],"type":"Point"}
}
