{
  "type": "Feature",
  "properties": {
    "iso:country":"GB",
    "wof:name":"LS17 9AE",
    "wof:placetype":"postalcode"
},
  "geometry": {"coordinates":[-1.44243187212712,53.89129860886934],"type":"Point"}
}