{
  "type": "Feature",
  "properties": {
    "iso:country": "GB",
    "wof:name": "LS17 9AE",
    "wof:placetype": "postalcode"
  },
  "geometry": {"coordinates":[-1.442432,53.891299],"type":"Point"}
}
