{
  "type": "Feature",
  "properties": {
    "date:inception_lower": "1980-01-01",
    "date:inception_upper": "1980-01-01",
    "iso:country": "GB",
    "wof:name": "LS17 9AE",
    "wof:placetype": "postalcode"
  },
  "geometry": {"coordinates":[-1.442432,53.891299],"type":"Point"}
}
