{
  "type": "Feature",
  "properties": {
    "iso:country": "GB",
    "wof:name": "HP1 1PE",
    "wof:placetype": "postalcode"
  },
  "geometry": {"coordinates":[-0.487548,51.747415],"type":"Point"}
}
