{
  "type": "Feature",
  "properties": {
    "iso:country": "GB",
    "wof:name": "LL59 5DU",
    "wof:placetype": "postalcode"
  },
  "geometry": {"coordinates":[-4.164671,53.222265],"type":"Point"}
}
