{
  "type": "Feature",
  "properties": {
    "iso:country":"GB",
    "wof:name":"GL5 2PP",
    "wof:placetype":"postalcode"
},
  "geometry": {"coordinates":[-2.20496084332865,51.71354583008296],"type":"Point"}
}