{
  "type": "Feature",
  "properties": {
    "iso:country": "GB",
    "wof:name": "GL5 2PP",
    "wof:placetype": "postalcode"
  },
  "geometry": {"coordinates":[-2.204961,51.713546],"type":"Point"}
}
