{
  "type": "Feature",
  "properties": {
    "iso:country": "GB",
    "wof:name": "NE49 0ER",
    "wof:placetype": "postalcode"
  },
  "geometry": {"coordinates":[-2.449102,54.97076],"type":"Point"}
}
