{
  "type": "Feature",
  "properties": {
    "iso:country":"GB",
    "wof:name":"NE49 0ER",
    "wof:placetype":"postalcode"
},
  "geometry": {"coordinates":[-2.44910220051925,54.97075950990091],"type":"Point"}
}