{
  "type": "Feature",
  "properties": {
    "date:inception_lower": "1980-01-01",
    "date:inception_upper": "1980-01-01",
    "iso:country": "GB",
    "wof:name": "WV10 8NZ",
    "wof:placetype": "postalcode"
  },
  "geometry": {"coordinates":[-2.095217,52.62075],"type":"Point"}
}
