{
  "type": "Feature",
  "properties": {
    "iso:country": "GB",
    "wof:name": "SP3 6JB",
    "wof:placetype": "postalcode"
  },
  "geometry": {"coordinates":[-2.086212,51.062896],"type":"Point"}
}
