{
  "type": "Feature",
  "properties": {
    "iso:country":"GB",
    "wof:name":"SP3 6JB",
    "wof:placetype":"postalcode"
},
  "geometry": {"coordinates":[-2.08621198009971,51.06289639424051],"type":"Point"}
}