{
  "type": "Feature",
  "properties": {
    "iso:country":"GB",
    "wof:name":"PR5 6AS",
    "wof:placetype":"postalcode"
},
  "geometry": {"coordinates":[-2.66600381224444,53.71918696268376],"type":"Point"}
}