{
  "type": "Feature",
  "properties": {
    "date:inception_lower": "1980-01-01",
    "date:inception_upper": "1980-01-01",
    "iso:country": "GB",
    "wof:name": "PR5 6AS",
    "wof:placetype": "postalcode"
  },
  "geometry": {"coordinates":[-2.666004,53.719187],"type":"Point"}
}
