{
  "type": "Feature",
  "properties": {
    "iso:country":"GB",
    "wof:name":"NW3 4SQ",
    "wof:placetype":"postalcode"
},
  "geometry": {"coordinates":[-0.15772225011551,51.54500289112178],"type":"Point"}
}