{
  "type": "Feature",
  "properties": {
    "iso:country":"GB",
    "wof:name":"HP2 4RW",
    "wof:placetype":"postalcode"
},
  "geometry": {"coordinates":[-0.44749152825374,51.75003103647757],"type":"Point"}
}