{
  "type": "Feature",
  "properties": {
    "iso:country":"GB",
    "wof:name":"NR10 4EW",
    "wof:placetype":"postalcode"
},
  "geometry": {"coordinates":[1.13901883521294,52.77382221459393],"type":"Point"}
}