{
  "type": "Feature",
  "properties": {
    "date:inception_lower": "2000-06-01",
    "date:inception_upper": "2000-06-01",
    "iso:country": "GB",
    "wof:name": "CA8 9JX",
    "wof:placetype": "postalcode"
  },
  "geometry": {"coordinates":[-2.759179,54.896615],"type":"Point"}
}
