{
  "type": "Feature",
  "properties": {
    "iso:country": "GB",
    "wof:name": "CA8 9JX",
    "wof:placetype": "postalcode"
  },
  "geometry": {"coordinates":[-2.759179,54.896615],"type":"Point"}
}
