{
  "type": "Feature",
  "properties": {
    "iso:country":"GB",
    "wof:name":"CA8 9JX",
    "wof:placetype":"postalcode"
},
  "geometry": {"coordinates":[-2.75917417755196,54.89660754758071],"type":"Point"}
}