{
  "type": "Feature",
  "properties": {
    "iso:country":"GB",
    "wof:name":"MK19 6DA",
    "wof:placetype":"postalcode"
},
  "geometry": {"coordinates":[-0.91684924053676,52.03732097463609],"type":"Point"}
}