{
  "type": "Feature",
  "properties": {
    "date:inception_lower": "1980-01-01",
    "date:inception_upper": "1980-01-01",
    "iso:country": "GB",
    "wof:name": "UB7 8HY",
    "wof:placetype": "postalcode"
  },
  "geometry": {"coordinates":[-0.456542,51.508572],"type":"Point"}
}
