{
  "type": "Feature",
  "properties": {
    "iso:country": "GB",
    "wof:name": "BS26 2XH",
    "wof:placetype": "postalcode"
  },
  "geometry": {"coordinates":[-2.897733,51.298653],"type":"Point"}
}
