{
  "type": "Feature",
  "properties": {
    "iso:country":"GB",
    "wof:name":"DD9 7EW",
    "wof:placetype":"postalcode"
},
  "geometry": {"coordinates":[-2.64235844627989,56.72628358010829],"type":"Point"}
}