{
  "type": "Feature",
  "properties": {
    "date:inception_lower":"1995-12-01",
    "date:inception_upper":"1995-12-31",
    "iso:country":"GB",
    "wof:name":"NE22 7DA",
    "wof:placetype":"postalcode"
},
  "geometry": {"coordinates":[-1.572454,55.144416],"type":"Point"}
}