{
  "type": "Feature",
  "properties": {
    "iso:country":"GB",
    "wof:name":"NE22 7DA",
    "wof:placetype":"postalcode"
},
  "geometry": {"coordinates":[-1.57245425030525,55.14441563648627],"type":"Point"}
}