{
  "type": "Feature",
  "properties": {
    "iso:country":"GB",
    "wof:name":"AB15 6JH",
    "wof:placetype":"postalcode"
},
  "geometry": {"coordinates":[-2.16199485807629,57.14825400875596],"type":"Point"}
}