{
  "type": "Feature",
  "properties": {
    "iso:country":"GB",
    "wof:name":"RH16 2ET",
    "wof:placetype":"postalcode"
},
  "geometry": {"coordinates":[-0.08786204557513,51.00664052242082],"type":"Point"}
}