{
  "type": "Feature",
  "properties": {
    "iso:country":"GB",
    "wof:name":"CF35 6EB",
    "wof:placetype":"postalcode"
},
  "geometry": {"coordinates":[-3.53414492664292,51.57153213554418],"type":"Point"}
}