{
  "type": "Feature",
  "properties": {
    "iso:country":"GB",
    "wof:name":"OL15 0BX",
    "wof:placetype":"postalcode"
},
  "geometry": {"coordinates":[-2.10632609971548,53.6299689003349],"type":"Point"}
}