{
  "type": "Feature",
  "properties": {
    "date:inception_lower": "1980-01-01",
    "date:inception_upper": "1980-01-01",
    "iso:country": "GB",
    "wof:name": "OL15 0BX",
    "wof:placetype": "postalcode"
  },
  "geometry": {"coordinates":[-2.106326,53.629969],"type":"Point"}
}
