{
  "type": "Feature",
  "properties": {
    "date:inception_lower": "1980-01-01",
    "date:inception_upper": "1980-01-01",
    "iso:country": "GB",
    "wof:name": "DH6 5NG",
    "wof:placetype": "postalcode"
  },
  "geometry": {"coordinates":[-1.531004,54.740121],"type":"Point"}
}
