{
  "type": "Feature",
  "properties": {
    "iso:country":"GB",
    "wof:name":"DH6 5NG",
    "wof:placetype":"postalcode"
},
  "geometry": {"coordinates":[-1.53102534482306,54.74004871199341],"type":"Point"}
}