{
  "type": "Feature",
  "properties": {
    "date:inception_lower": "1980-01-01",
    "date:inception_upper": "1980-01-01",
    "iso:country": "GB",
    "wof:name": "LS15 8RR",
    "wof:placetype": "postalcode"
  },
  "geometry": {"coordinates":[-1.447719,53.804488],"type":"Point"}
}
