{
  "type": "Feature",
  "properties": {
    "iso:country":"GB",
    "wof:name":"LS15 8RR",
    "wof:placetype":"postalcode"
},
  "geometry": {"coordinates":[-1.4477881280608,53.80461605924489],"type":"Point"}
}