{
  "type": "Feature",
  "properties": {
    "iso:country":"GB",
    "wof:name":"EC3N 2AP",
    "wof:placetype":"postalcode"
},
  "geometry": {"coordinates":[-0.07866555080048,51.51131662081849],"type":"Point"}
}