{
  "type": "Feature",
  "properties": {
    "date:inception_lower": "1980-01-01",
    "date:inception_upper": "1980-01-01",
    "iso:country": "GB",
    "wof:name": "EC3N 2AP",
    "wof:placetype": "postalcode"
  },
  "geometry": {"coordinates":[-0.078639,51.511318],"type":"Point"}
}
