{
  "type": "Feature",
  "properties": {
    "iso:country": "GB",
    "wof:name": "NW9 0FR",
    "wof:placetype": "postalcode"
  },
  "geometry": {"coordinates":[-0.260139,51.592187],"type":"Point"}
}
