{
  "type": "Feature",
  "properties": {
    "date:inception_lower": "2024-07-01",
    "date:inception_upper": "2024-07-01",
    "iso:country": "GB",
    "wof:name": "SP7 8TT",
    "wof:placetype": "postalcode"
  },
  "geometry": {"coordinates":[-2.197361,51.006913],"type":"Point"}
}
