{
  "type": "Feature",
  "properties": {
    "date:inception_lower": "2022-07-01",
    "date:inception_upper": "2022-07-01",
    "iso:country": "GB",
    "wof:name": "PO8 0AF",
    "wof:placetype": "postalcode"
  },
  "geometry": {"coordinates":[-0.985685,50.918031],"type":"Point"}
}
