{
  "type": "Feature",
  "properties": {
    "date:inception_lower": "2018-12-01",
    "date:inception_upper": "2018-12-01",
    "iso:country": "GB",
    "wof:name": "TN17 4BX",
    "wof:placetype": "postalcode"
  },
  "geometry": {"coordinates":[0.631936,51.056161],"type":"Point"}
}
