{
  "type": "Feature",
  "properties": {
    "iso:country":"GB",
    "wof:name":"SA4 9DY",
    "wof:placetype":"postalcode"
},
  "geometry": {"coordinates":[-4.01595674897806,51.70276265544251],"type":"Point"}
}