{
  "type": "Feature",
  "properties": {
    "iso:country":"GB",
    "wof:name":"NP23 6XQ",
    "wof:placetype":"postalcode"
},
  "geometry": {"coordinates":[-3.22549421123153,51.78848912392495],"type":"Point"}
}