{
  "type": "Feature",
  "properties": {
    "iso:country": "GB",
    "wof:name": "BS30 9AY",
    "wof:placetype": "postalcode"
  },
  "geometry": {"coordinates":[-2.471127,51.440564],"type":"Point"}
}
