{
  "type": "Feature",
  "properties": {
    "iso:country":"GB",
    "wof:name":"BS30 9AY",
    "wof:placetype":"postalcode"
},
  "geometry": {"coordinates":[-2.47112688499208,51.44056444828719],"type":"Point"}
}