{
  "type": "Feature",
  "properties": {
    "iso:country": "GB",
    "wof:name": "WD19 5RH",
    "wof:placetype": "postalcode"
  },
  "geometry": {"coordinates":[-0.374495,51.632188],"type":"Point"}
}
