{
  "type": "Feature",
  "properties": {
    "date:inception_lower":"2009-01-01",
    "date:inception_upper":"2009-01-31",
    "iso:country":"GB",
    "wof:name":"WD19 5RH",
    "wof:placetype":"postalcode"
},
  "geometry": {"coordinates":[-0.374495,51.632188],"type":"Point"}
}