{
  "type": "Feature",
  "properties": {
    "iso:country":"GB",
    "wof:name":"WD19 5RH",
    "wof:placetype":"postalcode"
},
  "geometry": {"coordinates":[-0.3745354095727,51.63210370310849],"type":"Point"}
}