{
  "type": "Feature",
  "properties": {
    "iso:country":"GB",
    "wof:name":"SA32 7TN",
    "wof:placetype":"postalcode"
},
  "geometry": {"coordinates":[-4.0686887455471,51.95750668079849],"type":"Point"}
}