{
  "type": "Feature",
  "properties": {
    "date:inception_lower": "2021-01-01",
    "date:inception_upper": "2021-01-01",
    "iso:country": "GB",
    "wof:name": "WD6 1SB",
    "wof:placetype": "postalcode"
  },
  "geometry": {"coordinates":[-0.264819,51.662937],"type":"Point"}
}
