{
  "type": "Feature",
  "properties": {
    "iso:country":"GB",
    "wof:name":"RG30 2NR",
    "wof:placetype":"postalcode"
},
  "geometry": {"coordinates":[-1.00998010061303,51.45401404029543],"type":"Point"}
}