{
  "type": "Feature",
  "properties": {
    "iso:country": "GB",
    "wof:name": "EX20 4NR",
    "wof:placetype": "postalcode"
  },
  "geometry": {"coordinates":[-4.122946,50.679045],"type":"Point"}
}
