{
  "type": "Feature",
  "properties": {
    "date:inception_lower": "1980-01-01",
    "date:inception_upper": "1980-01-01",
    "iso:country": "GB",
    "wof:name": "EX20 4NR",
    "wof:placetype": "postalcode"
  },
  "geometry": {"coordinates":[-4.122946,50.679045],"type":"Point"}
}
