{
  "type": "Feature",
  "properties": {
    "date:inception_lower": "1980-01-01",
    "date:inception_upper": "1980-01-01",
    "iso:country": "GB",
    "wof:name": "TF2 8AU",
    "wof:placetype": "postalcode"
  },
  "geometry": {"coordinates":[-2.441515,52.717386],"type":"Point"}
}
