{
  "type": "Feature",
  "properties": {
    "iso:country":"GB",
    "wof:name":"TF2 8AU",
    "wof:placetype":"postalcode"
},
  "geometry": {"coordinates":[-2.44151458021436,52.71738638941259],"type":"Point"}
}