{
  "type": "Feature",
  "properties": {
    "iso:country":"GB",
    "wof:name":"CM17 0EF",
    "wof:placetype":"postalcode"
},
  "geometry": {"coordinates":[0.14117280505304,51.78220829867745],"type":"Point"}
}