{
  "type": "Feature",
  "properties": {
    "date:inception_lower": "2006-11-01",
    "date:inception_upper": "2006-11-01",
    "iso:country": "GB",
    "wof:name": "CM17 0EF",
    "wof:placetype": "postalcode"
  },
  "geometry": {"coordinates":[0.141288,51.78224],"type":"Point"}
}
