{
  "type": "Feature",
  "properties": {
    "iso:country": "GB",
    "wof:name": "WV8 1PA",
    "wof:placetype": "postalcode"
  },
  "geometry": {"coordinates":[-2.189601,52.62647],"type":"Point"}
}
