{
  "type": "Feature",
  "properties": {
    "iso:country":"GB",
    "wof:name":"WV8 1PA",
    "wof:placetype":"postalcode"
},
  "geometry": {"coordinates":[-2.1896006925742,52.62647046723109],"type":"Point"}
}