{
  "type": "Feature",
  "properties": {
    "iso:country":"GB",
    "wof:name":"WR14 4PQ",
    "wof:placetype":"postalcode"
},
  "geometry": {"coordinates":[-2.33132186656591,52.08124523903265],"type":"Point"}
}