{
  "type": "Feature",
  "properties": {
    "iso:country": "GB",
    "wof:name": "GU14 6EF",
    "wof:placetype": "postalcode"
  },
  "geometry": {"coordinates":[-0.748983,51.274356],"type":"Point"}
}
