{
  "type": "Feature",
  "properties": {
    "date:inception_lower": "2020-02-01",
    "date:inception_upper": "2020-02-01",
    "iso:country": "GB",
    "wof:name": "SK14 3GE",
    "wof:placetype": "postalcode"
  },
  "geometry": {"coordinates":[-2.039061,53.446619],"type":"Point"}
}
