{
  "type": "Feature",
  "properties": {
    "iso:country":"GB",
    "wof:name":"SO16 5DE",
    "wof:placetype":"postalcode"
},
  "geometry": {"coordinates":[-1.44262133330611,50.93271373590778],"type":"Point"}
}