{
  "type": "Feature",
  "properties": {
    "date:inception_lower": "1980-01-01",
    "date:inception_upper": "1980-01-01",
    "iso:country": "GB",
    "wof:name": "PO2 8JU",
    "wof:placetype": "postalcode"
  },
  "geometry": {"coordinates":[-1.086633,50.818505],"type":"Point"}
}
