{
  "type": "Feature",
  "properties": {
    "iso:country": "GB",
    "wof:name": "PO2 8JU",
    "wof:placetype": "postalcode"
  },
  "geometry": {"coordinates":[-1.086633,50.818505],"type":"Point"}
}
