{
  "type": "Feature",
  "properties": {
    "iso:country":"GB",
    "wof:name":"PO2 8JU",
    "wof:placetype":"postalcode"
},
  "geometry": {"coordinates":[-1.08663301561439,50.81850510257231],"type":"Point"}
}