{
  "type": "Feature",
  "properties": {
    "iso:country": "GB",
    "wof:name": "GU7 2RW",
    "wof:placetype": "postalcode"
  },
  "geometry": {"coordinates":[-0.640112,51.197733],"type":"Point"}
}
