{
  "type": "Feature",
  "properties": {
    "iso:country":"GB",
    "wof:name":"M30 8PB",
    "wof:placetype":"postalcode"
},
  "geometry": {"coordinates":[-2.36138199078231,53.48333712847435],"type":"Point"}
}