{
  "type": "Feature",
  "properties": {
    "iso:country": "GB",
    "wof:name": "ME17 2JP",
    "wof:placetype": "postalcode"
  },
  "geometry": {"coordinates":[0.750123,51.217406],"type":"Point"}
}
