{
  "type": "Feature",
  "properties": {
    "iso:country":"GB",
    "wof:name":"SK14 8JU",
    "wof:placetype":"postalcode"
},
  "geometry": {"coordinates":[-1.98926677813449,53.46484627526318],"type":"Point"}
}