{
  "type": "Feature",
  "properties": {
    "iso:country":"GB",
    "wof:name":"PH8 0BD",
    "wof:placetype":"postalcode"
},
  "geometry": {"coordinates":[-3.56509460667699,56.55441994516448],"type":"Point"}
}