{
  "type": "Feature",
  "properties": {
    "iso:country": "GB",
    "wof:name": "E1 7QU",
    "wof:placetype": "postalcode"
  },
  "geometry": {"coordinates":[-0.069558,51.515726],"type":"Point"}
}
