{
  "type": "Feature",
  "properties": {
    "iso:country":"GB",
    "wof:name":"PL25 3JF",
    "wof:placetype":"postalcode"
},
  "geometry": {"coordinates":[-4.76351590550718,50.34080745143812],"type":"Point"}
}