{
  "type": "Feature",
  "properties": {
    "iso:country":"GB",
    "wof:name":"AB21 9NY",
    "wof:placetype":"postalcode"
},
  "geometry": {"coordinates":[-2.15995003156425,57.17605902663777],"type":"Point"}
}