{
  "type": "Feature",
  "properties": {
    "iso:country":"GB",
    "wof:name":"CH4 7QT",
    "wof:placetype":"postalcode"
},
  "geometry": {"coordinates":[-2.90200948842789,53.17280339167619],"type":"Point"}
}