{
  "type": "Feature",
  "properties": {
    "iso:country":"GB",
    "wof:name":"NG6 9ER",
    "wof:placetype":"postalcode"
},
  "geometry": {"coordinates":[-1.18387740748422,52.99655334636796],"type":"Point"}
}