{
  "type": "Feature",
  "properties": {
    "iso:country":"GB",
    "wof:name":"SE6 1LU",
    "wof:placetype":"postalcode"
},
  "geometry": {"coordinates":[-0.00268790793023,51.43614510381243],"type":"Point"}
}