{
  "type": "Feature",
  "properties": {
    "date:inception_lower": "2015-06-01",
    "date:inception_upper": "2015-06-01",
    "iso:country": "GB",
    "wof:name": "CV34 6WP",
    "wof:placetype": "postalcode"
  },
  "geometry": {"coordinates":[-1.554331,52.269955],"type":"Point"}
}
