{
  "type": "Feature",
  "properties": {
    "iso:country":"GB",
    "wof:name":"TF10 7RZ",
    "wof:placetype":"postalcode"
},
  "geometry": {"coordinates":[-2.37035219206445,52.76283889769404],"type":"Point"}
}