{
  "type": "Feature",
  "properties": {
    "date:inception_lower":"1984-10-01",
    "date:inception_upper":"1984-10-31",
    "iso:country":"GB",
    "wof:name":"TF10 7RZ",
    "wof:placetype":"postalcode"
},
  "geometry": {"coordinates":[-2.370352,52.762839],"type":"Point"}
}