{
  "type": "Feature",
  "properties": {
    "iso:country":"GB",
    "wof:name":"RH16 3RG",
    "wof:placetype":"postalcode"
},
  "geometry": {"coordinates":[-0.08528821430459,50.99818066102403],"type":"Point"}
}