{
  "type": "Feature",
  "properties": {
    "date:inception_lower": "2017-02-01",
    "date:inception_upper": "2017-02-01",
    "iso:country": "GB",
    "wof:name": "NP25 5UZ",
    "wof:placetype": "postalcode"
  },
  "geometry": {"coordinates":[-2.738546,51.806552],"type":"Point"}
}
