{
  "type": "Feature",
  "properties": {
    "iso:country": "GB",
    "wof:name": "NR20 5TL",
    "wof:placetype": "postalcode"
  },
  "geometry": {"coordinates":[0.843732,52.774609],"type":"Point"}
}
