{
  "type": "Feature",
  "properties": {
    "iso:country": "GB",
    "wof:name": "CH7 4JN",
    "wof:placetype": "postalcode"
  },
  "geometry": {"coordinates":[-3.116085,53.113466],"type":"Point"}
}
