{
  "type": "Feature",
  "properties": {
    "iso:country":"GB",
    "wof:name":"CH7 4JN",
    "wof:placetype":"postalcode"
},
  "geometry": {"coordinates":[-3.11608535644933,53.11346613276952],"type":"Point"}
}