{
  "type": "Feature",
  "properties": {
    "date:inception_lower": "2001-12-01",
    "date:inception_upper": "2001-12-01",
    "iso:country": "GB",
    "wof:name": "CH7 4JN",
    "wof:placetype": "postalcode"
  },
  "geometry": {"coordinates":[-3.116085,53.113466],"type":"Point"}
}
