{
  "type": "Feature",
  "properties": {
    "iso:country": "GB",
    "wof:name": "BR6 8NN",
    "wof:placetype": "postalcode"
  },
  "geometry": {"coordinates":[0.054857,51.367381],"type":"Point"}
}
