{
  "type": "Feature",
  "properties": {
    "iso:country":"GB",
    "wof:name":"S81 8HE",
    "wof:placetype":"postalcode"
},
  "geometry": {"coordinates":[-1.06252053226944,53.37743984868522],"type":"Point"}
}