{
  "type": "Feature",
  "properties": {
    "iso:country":"GB",
    "wof:name":"CM16 4LL",
    "wof:placetype":"postalcode"
},
  "geometry": {"coordinates":[0.11499192673089,51.7003918111269],"type":"Point"}
}