{
  "type": "Feature",
  "properties": {
    "iso:country":"GB",
    "wof:name":"BA11 5DR",
    "wof:placetype":"postalcode"
},
  "geometry": {"coordinates":[-2.34963699317333,51.19137804505124],"type":"Point"}
}