{
  "type": "Feature",
  "properties": {
    "iso:country": "GB",
    "wof:name": "EH12 9LJ",
    "wof:placetype": "postalcode"
  },
  "geometry": {"coordinates":[-3.302893,55.932303],"type":"Point"}
}
