{
  "type": "Feature",
  "properties": {
    "iso:country":"GB",
    "wof:name":"CH41 0BH",
    "wof:placetype":"postalcode"
},
  "geometry": {"coordinates":[-3.05218308819647,53.39853858584119],"type":"Point"}
}