{
  "type": "Feature",
  "properties": {
    "iso:country": "GB",
    "wof:name": "CH41 0BH",
    "wof:placetype": "postalcode"
  },
  "geometry": {"coordinates":[-3.052183,53.398539],"type":"Point"}
}
