{
  "type": "Feature",
  "properties": {
    "date:inception_lower": "1999-06-01",
    "date:inception_upper": "1999-06-01",
    "iso:country": "GB",
    "wof:name": "CH41 0BH",
    "wof:placetype": "postalcode"
  },
  "geometry": {"coordinates":[-3.052183,53.398539],"type":"Point"}
}
