{
  "type": "Feature",
  "properties": {
    "iso:country":"GB",
    "wof:name":"TA22 9DN",
    "wof:placetype":"postalcode"
},
  "geometry": {"coordinates":[-3.54883661476305,51.04074690933324],"type":"Point"}
}