{
  "type": "Feature",
  "properties": {
    "iso:country":"GB",
    "wof:name":"ME13 7EX",
    "wof:placetype":"postalcode"
},
  "geometry": {"coordinates":[0.89165687434406,51.32189637406361],"type":"Point"}
}