{
  "type": "Feature",
  "properties": {
    "iso:country": "GB",
    "wof:name": "OX26 1AZ",
    "wof:placetype": "postalcode"
  },
  "geometry": {"coordinates":[-1.169527,51.889779],"type":"Point"}
}
