{
  "type": "Feature",
  "properties": {
    "iso:country":"GB",
    "wof:name":"OX26 1AZ",
    "wof:placetype":"postalcode"
},
  "geometry": {"coordinates":[-1.16953213240929,51.88976247119237],"type":"Point"}
}