{
  "type": "Feature",
  "properties": {
    "date:inception_lower": "1980-01-01",
    "date:inception_upper": "1980-01-01",
    "iso:country": "GB",
    "wof:name": "TS24 9BG",
    "wof:placetype": "postalcode"
  },
  "geometry": {"coordinates":[-1.232005,54.704329],"type":"Point"}
}
