{
  "type": "Feature",
  "properties": {
    "iso:country":"GB",
    "wof:name":"TS24 9BG",
    "wof:placetype":"postalcode"
},
  "geometry": {"coordinates":[-1.23200546804502,54.70432943570773],"type":"Point"}
}