{
  "type": "Feature",
  "properties": {
    "date:inception_lower": "1980-01-01",
    "date:inception_upper": "1980-01-01",
    "iso:country": "GB",
    "wof:name": "FY7 6BP",
    "wof:placetype": "postalcode"
  },
  "geometry": {"coordinates":[-3.008139,53.926961],"type":"Point"}
}
