{
  "type": "Feature",
  "properties": {
    "date:inception_lower": "1981-06-01",
    "date:inception_upper": "1981-06-01",
    "iso:country": "GB",
    "wof:name": "OL16 4BY",
    "wof:placetype": "postalcode"
  },
  "geometry": {"coordinates":[-2.115173,53.608254],"type":"Point"}
}
