{
  "type": "Feature",
  "properties": {
    "iso:country":"GB",
    "wof:name":"SW1V 3BA",
    "wof:placetype":"postalcode"
},
  "geometry": {"coordinates":[-0.13825897956514,51.48687383145028],"type":"Point"}
}