{
  "type": "Feature",
  "properties": {
    "iso:country":"GB",
    "wof:name":"DD2 3UY",
    "wof:placetype":"postalcode"
},
  "geometry": {"coordinates":[-3.01509647581236,56.47230544200791],"type":"Point"}
}