{
  "type": "Feature",
  "properties": {
    "iso:country":"GB",
    "wof:name":"B97 5SB",
    "wof:placetype":"postalcode"
},
  "geometry": {"coordinates":[-1.97501054082996,52.30136244413198],"type":"Point"}
}