{
  "type": "Feature",
  "properties": {
    "date:inception_lower": "1980-01-01",
    "date:inception_upper": "1980-01-01",
    "iso:country": "GB",
    "wof:name": "B97 5SB",
    "wof:placetype": "postalcode"
  },
  "geometry": {"coordinates":[-1.97501,52.301362],"type":"Point"}
}
