{
  "type": "Feature",
  "properties": {
    "date:inception_lower": "1985-04-01",
    "date:inception_upper": "1985-04-01",
    "iso:country": "GB",
    "wof:name": "S72 8JH",
    "wof:placetype": "postalcode"
  },
  "geometry": {"coordinates":[-1.412735,53.567816],"type":"Point"}
}
