{
  "type": "Feature",
  "properties": {
    "date:inception_lower": "2021-08-01",
    "date:inception_upper": "2021-08-01",
    "iso:country": "GB",
    "wof:name": "DT11 9FQ",
    "wof:placetype": "postalcode"
  },
  "geometry": {"coordinates":[-2.161446,50.847569],"type":"Point"}
}
