{
  "type": "Feature",
  "properties": {
    "iso:country": "GB",
    "wof:name": "DN17 1RG",
    "wof:placetype": "postalcode"
  },
  "geometry": {"coordinates":[-0.677969,53.565603],"type":"Point"}
}
