{
  "type": "Feature",
  "properties": {
    "iso:country":"GB",
    "wof:name":"DN17 1RG",
    "wof:placetype":"postalcode"
},
  "geometry": {"coordinates":[-0.6779688406921,53.56560252988039],"type":"Point"}
}