{
  "type": "Feature",
  "properties": {
    "date:inception_lower": "1980-01-01",
    "date:inception_upper": "1980-01-01",
    "iso:country": "GB",
    "wof:name": "DN17 1RG",
    "wof:placetype": "postalcode"
  },
  "geometry": {"coordinates":[-0.677969,53.565603],"type":"Point"}
}
