{
  "type": "Feature",
  "properties": {
    "iso:country":"GB",
    "wof:name":"WN7 1BT",
    "wof:placetype":"postalcode"
},
  "geometry": {"coordinates":[-2.51355119054703,53.4969727009306],"type":"Point"}
}