{
  "type": "Feature",
  "properties": {
    "iso:country":"GB",
    "wof:name":"EX6 7JF",
    "wof:placetype":"postalcode"
},
  "geometry": {"coordinates":[-3.67500909795191,50.66695561886998],"type":"Point"}
}