{
  "type": "Feature",
  "properties": {
    "iso:country": "GB",
    "wof:name": "EX6 7JF",
    "wof:placetype": "postalcode"
  },
  "geometry": {"coordinates":[-3.675009,50.666956],"type":"Point"}
}
