{
  "type": "Feature",
  "properties": {
    "iso:country":"GB",
    "wof:name":"PA31 8NT",
    "wof:placetype":"postalcode"
},
  "geometry": {"coordinates":[-5.43465695676694,56.03953827441956],"type":"Point"}
}