{
  "type": "Feature",
  "properties": {
    "iso:country":"GB",
    "wof:name":"OL6 9ER",
    "wof:placetype":"postalcode"
},
  "geometry": {"coordinates":[-2.07073115800281,53.5042489024999],"type":"Point"}
}