{
  "type": "Feature",
  "properties": {
    "iso:country":"GB",
    "wof:name":"SW4 6RJ",
    "wof:placetype":"postalcode"
},
  "geometry": {"coordinates":[-0.12998678534813,51.47149081334997],"type":"Point"}
}