{
  "type": "Feature",
  "properties": {
    "date:inception_lower": "1980-01-01",
    "date:inception_upper": "1980-01-01",
    "iso:country": "GB",
    "wof:name": "WV16 4SN",
    "wof:placetype": "postalcode"
  },
  "geometry": {"coordinates":[-2.438872,52.567875],"type":"Point"}
}
