{
  "type": "Feature",
  "properties": {
    "date:inception_lower": "1980-01-01",
    "date:inception_upper": "1980-01-01",
    "iso:country": "GB",
    "wof:name": "ME14 4DS",
    "wof:placetype": "postalcode"
  },
  "geometry": {"coordinates":[0.57274,51.267985],"type":"Point"}
}
