{
  "type": "Feature",
  "properties": {
    "iso:country": "GB",
    "wof:name": "ME14 4DS",
    "wof:placetype": "postalcode"
  },
  "geometry": {"coordinates":[0.57274,51.267985],"type":"Point"}
}
