{
  "type": "Feature",
  "properties": {
    "iso:country":"GB",
    "wof:name":"ME14 4DS",
    "wof:placetype":"postalcode"
},
  "geometry": {"coordinates":[0.5727404578533,51.26798474680462],"type":"Point"}
}