{
  "type": "Feature",
  "properties": {
    "iso:country": "GB",
    "wof:name": "LN13 9SL",
    "wof:placetype": "postalcode"
  },
  "geometry": {"coordinates":[0.298405,53.243182],"type":"Point"}
}
