{
  "type": "Feature",
  "properties": {
    "iso:country": "GB",
    "wof:name": "HG3 1BY",
    "wof:placetype": "postalcode"
  },
  "geometry": {"coordinates":[-1.458253,53.947381],"type":"Point"}
}
