{
  "type": "Feature",
  "properties": {
    "iso:country":"GB",
    "wof:name":"HG3 1BY",
    "wof:placetype":"postalcode"
},
  "geometry": {"coordinates":[-1.45814025236805,53.94732913184394],"type":"Point"}
}