{
  "type": "Feature",
  "properties": {
    "iso:country":"GB",
    "wof:name":"FK6 6HA",
    "wof:placetype":"postalcode"
},
  "geometry": {"coordinates":[-3.90658153626873,56.02186547498951],"type":"Point"}
}