{
  "type": "Feature",
  "properties": {
    "date:inception_lower": "2024-01-01",
    "date:inception_upper": "2024-01-01",
    "iso:country": "GB",
    "wof:name": "S81 9GL",
    "wof:placetype": "postalcode"
  },
  "geometry": {"coordinates":[-1.12515,53.367714],"type":"Point"}
}
