{
  "type": "Feature",
  "properties": {
    "iso:country": "GB",
    "wof:name": "LE11 2BB",
    "wof:placetype": "postalcode"
  },
  "geometry": {"coordinates":[-1.199209,52.753293],"type":"Point"}
}
