{
  "type": "Feature",
  "properties": {
    "iso:country":"GB",
    "wof:name":"TA6 7LN",
    "wof:placetype":"postalcode"
},
  "geometry": {"coordinates":[-3.01977108633531,51.1238973309454],"type":"Point"}
}