{
  "type": "Feature",
  "properties": {
    "iso:country":"GB",
    "wof:name":"AB24 1SN",
    "wof:placetype":"postalcode"
},
  "geometry": {"coordinates":[-2.09631847803939,57.16768909098325],"type":"Point"}
}