{
  "type": "Feature",
  "properties": {
    "date:inception_lower": "2012-07-01",
    "date:inception_upper": "2012-07-01",
    "iso:country": "GB",
    "wof:name": "TA1 1AP",
    "wof:placetype": "postalcode"
  },
  "geometry": {"coordinates":[-3.099184,51.019971],"type":"Point"}
}
