{
  "type": "Feature",
  "properties": {
    "iso:country":"GB",
    "wof:name":"CO13 0DT",
    "wof:placetype":"postalcode"
},
  "geometry": {"coordinates":[1.22828769491505,51.85166296539975],"type":"Point"}
}