{
  "type": "Feature",
  "properties": {
    "iso:country": "GB",
    "wof:name": "NG34 7NT",
    "wof:placetype": "postalcode"
  },
  "geometry": {"coordinates":[-0.410631,52.991385],"type":"Point"}
}
