{
  "type": "Feature",
  "properties": {
    "iso:country": "GB",
    "wof:name": "GL2 8AS",
    "wof:placetype": "postalcode"
  },
  "geometry": {"coordinates":[-2.374106,51.869787],"type":"Point"}
}
