{
  "type": "Feature",
  "properties": {
    "iso:country": "GB",
    "wof:name": "GL2 8AS",
    "wof:placetype": "postalcode"
  },
  "geometry": {"coordinates":[-2.373822,51.870634],"type":"Point"}
}
