{
  "type": "Feature",
  "properties": {
    "iso:country": "GB",
    "wof:name": "BD23 1TN",
    "wof:placetype": "postalcode"
  },
  "geometry": {"coordinates":[-2.039923,53.958412],"type":"Point"}
}
