{
  "type": "Feature",
  "properties": {
    "iso:country":"GB",
    "wof:name":"PO32 6DA",
    "wof:placetype":"postalcode"
},
  "geometry": {"coordinates":[-1.28574094851745,50.75528083090401],"type":"Point"}
}