{
  "type": "Feature",
  "properties": {
    "iso:country":"GB",
    "wof:name":"EH26 9LQ",
    "wof:placetype":"postalcode"
},
  "geometry": {"coordinates":[-3.27249586123318,55.82919208322874],"type":"Point"}
}