{
  "type": "Feature",
  "properties": {
    "iso:country":"GB",
    "wof:name":"CF23 8ET",
    "wof:placetype":"postalcode"
},
  "geometry": {"coordinates":[-3.14207409440244,51.53226767438188],"type":"Point"}
}