{
  "type": "Feature",
  "properties": {
    "iso:country": "GB",
    "wof:name": "DT4 8SR",
    "wof:placetype": "postalcode"
  },
  "geometry": {"coordinates":[-2.460663,50.604811],"type":"Point"}
}
