{
  "type": "Feature",
  "properties": {
    "date:inception_lower": "1980-01-01",
    "date:inception_upper": "1980-01-01",
    "iso:country": "GB",
    "wof:name": "DT4 8SR",
    "wof:placetype": "postalcode"
  },
  "geometry": {"coordinates":[-2.460663,50.604811],"type":"Point"}
}
