{
  "type": "Feature",
  "properties": {
    "iso:country":"GB",
    "wof:name":"DT4 8SR",
    "wof:placetype":"postalcode"
},
  "geometry": {"coordinates":[-2.46066350931138,50.60481121585146],"type":"Point"}
}