{
  "type": "Feature",
  "properties": {
    "iso:country":"GB",
    "wof:name":"NW7 1BF",
    "wof:placetype":"postalcode"
},
  "geometry": {"coordinates":[-0.21421756386042,51.60932633091987],"type":"Point"}
}