{
  "type": "Feature",
  "properties": {
    "date:inception_lower": "1980-01-01",
    "date:inception_upper": "1980-01-01",
    "iso:country": "GB",
    "wof:name": "SN11 0HQ",
    "wof:placetype": "postalcode"
  },
  "geometry": {"coordinates":[-2.005361,51.440604],"type":"Point"}
}
