{
  "type": "Feature",
  "properties": {
    "iso:country":"GB",
    "wof:name":"SN11 0HQ",
    "wof:placetype":"postalcode"
},
  "geometry": {"coordinates":[-2.00536084894561,51.44060381766356],"type":"Point"}
}