{
  "type": "Feature",
  "properties": {
    "date:inception_lower":"1980-01-01",
    "date:inception_upper":"1980-01-31",
    "iso:country":"GB",
    "wof:name":"WV13 2PD",
    "wof:placetype":"postalcode"
},
  "geometry": {"coordinates":[-2.058877,52.585947],"type":"Point"}
}