{
  "type": "Feature",
  "properties": {
    "iso:country":"GB",
    "wof:name":"FK13 6QA",
    "wof:placetype":"postalcode"
},
  "geometry": {"coordinates":[-3.73284000684635,56.15283170829371],"type":"Point"}
}