{
  "type": "Feature",
  "properties": {
    "iso:country": "GB",
    "wof:name": "FK13 6QA",
    "wof:placetype": "postalcode"
  },
  "geometry": {"coordinates":[-3.73284,56.152832],"type":"Point"}
}
