{
  "type": "Feature",
  "properties": {
    "date:inception_lower": "1980-01-01",
    "date:inception_upper": "1980-01-01",
    "iso:country": "GB",
    "wof:name": "FK13 6QA",
    "wof:placetype": "postalcode"
  },
  "geometry": {"coordinates":[-3.73284,56.152832],"type":"Point"}
}
