{
  "type": "Feature",
  "properties": {
    "date:inception_lower":"1980-01-01",
    "date:inception_upper":"1980-01-31",
    "iso:country":"GB",
    "wof:name":"M1 2AW",
    "wof:placetype":"postalcode"
},
  "geometry": {"coordinates":[-2.233973,53.480922],"type":"Point"}
}