{
  "type": "Feature",
  "properties": {
    "date:inception_lower":"1980-01-01",
    "date:inception_upper":"1980-01-31",
    "iso:country":"GB",
    "wof:name":"CF44 9NH",
    "wof:placetype":"postalcode"
},
  "geometry": {"coordinates":[-3.511795,51.738061],"type":"Point"}
}