{
  "type": "Feature",
  "properties": {
    "iso:country":"GB",
    "wof:name":"CF44 9NH",
    "wof:placetype":"postalcode"
},
  "geometry": {"coordinates":[-3.51181494346243,51.73811001038192],"type":"Point"}
}