{
  "type": "Feature",
  "properties": {
    "iso:country":"GB",
    "wof:name":"GU47 0HH",
    "wof:placetype":"postalcode"
},
  "geometry": {"coordinates":[-0.78431001250594,51.34715215388017],"type":"Point"}
}