{
  "type": "Feature",
  "properties": {
    "iso:country": "GB",
    "wof:name": "GU47 0HH",
    "wof:placetype": "postalcode"
  },
  "geometry": {"coordinates":[-0.78431,51.347152],"type":"Point"}
}
