{
  "type": "Feature",
  "properties": {
    "iso:country":"GB",
    "wof:name":"SS5 5LX",
    "wof:placetype":"postalcode"
},
  "geometry": {"coordinates":[0.64935538409218,51.61945736482882],"type":"Point"}
}