{
  "type": "Feature",
  "properties": {
    "iso:country": "GB",
    "wof:name": "SS5 5LX",
    "wof:placetype": "postalcode"
  },
  "geometry": {"coordinates":[0.649355,51.619457],"type":"Point"}
}
