{
  "type": "Feature",
  "properties": {
    "date:inception_lower": "1993-08-01",
    "date:inception_upper": "1993-08-01",
    "iso:country": "GB",
    "wof:name": "NN4 8TN",
    "wof:placetype": "postalcode"
  },
  "geometry": {"coordinates":[-0.927422,52.228851],"type":"Point"}
}
