{
  "type": "Feature",
  "properties": {
    "date:inception_lower": "2021-01-01",
    "date:inception_upper": "2021-01-01",
    "iso:country": "GB",
    "wof:name": "EC1N 8QN",
    "wof:placetype": "postalcode"
  },
  "geometry": {"coordinates":[-0.106492,51.51875],"type":"Point"}
}
