{
  "type": "Feature",
  "properties": {
    "iso:country": "GB",
    "wof:name": "IG11 0XS",
    "wof:placetype": "postalcode"
  },
  "geometry": {"coordinates":[0.115485,51.525214],"type":"Point"}
}
