{
  "type": "Feature",
  "properties": {
    "iso:country": "GB",
    "wof:name": "RH10 6GN",
    "wof:placetype": "postalcode"
  },
  "geometry": {"coordinates":[-0.170546,51.103085],"type":"Point"}
}
