{
  "type": "Feature",
  "properties": {
    "date:inception_lower": "2020-01-01",
    "date:inception_upper": "2020-01-01",
    "iso:country": "GB",
    "wof:name": "DE65 6SL",
    "wof:placetype": "postalcode"
  },
  "geometry": {"coordinates":[-1.54111,52.839625],"type":"Point"}
}
