{
  "type": "Feature",
  "properties": {
    "iso:country":"GB",
    "wof:name":"PR8 1DL",
    "wof:placetype":"postalcode"
},
  "geometry": {"coordinates":[-3.00638961649985,53.64678996981943],"type":"Point"}
}