{
  "type": "Feature",
  "properties": {
    "date:inception_lower": "1993-01-01",
    "date:inception_upper": "1993-01-01",
    "iso:country": "GB",
    "wof:name": "PO21 1RT",
    "wof:placetype": "postalcode"
  },
  "geometry": {"coordinates":[-0.677049,50.78485],"type":"Point"}
}
