{
  "type": "Feature",
  "properties": {
    "iso:country": "GB",
    "wof:name": "PO21 1RT",
    "wof:placetype": "postalcode"
  },
  "geometry": {"coordinates":[-0.677049,50.78485],"type":"Point"}
}
