{
  "type": "Feature",
  "properties": {
    "iso:country":"GB",
    "wof:name":"CB8 0HG",
    "wof:placetype":"postalcode"
},
  "geometry": {"coordinates":[0.40258726206714,52.25198131208901],"type":"Point"}
}