{
  "type": "Feature",
  "properties": {
    "date:inception_lower": "1988-03-01",
    "date:inception_upper": "1988-03-01",
    "iso:country": "GB",
    "wof:name": "CB8 0HG",
    "wof:placetype": "postalcode"
  },
  "geometry": {"coordinates":[0.402587,52.251981],"type":"Point"}
}
