{
  "type": "Feature",
  "properties": {
    "iso:country": "GB",
    "wof:name": "CB8 0HG",
    "wof:placetype": "postalcode"
  },
  "geometry": {"coordinates":[0.402587,52.251981],"type":"Point"}
}
