{
  "type": "Feature",
  "properties": {
    "iso:country":"GB",
    "wof:name":"M9 8PL",
    "wof:placetype":"postalcode"
},
  "geometry": {"coordinates":[-2.23792548300895,53.53282254379582],"type":"Point"}
}