{
  "type": "Feature",
  "properties": {
    "iso:country": "GB",
    "wof:name": "M9 8PL",
    "wof:placetype": "postalcode"
  },
  "geometry": {"coordinates":[-2.237925,53.532823],"type":"Point"}
}
