{
  "type": "Feature",
  "properties": {
    "iso:country":"GB",
    "wof:name":"OL4 3BQ",
    "wof:placetype":"postalcode"
},
  "geometry": {"coordinates":[-2.08228627217814,53.5385860656162],"type":"Point"}
}