{
  "type": "Feature",
  "properties": {
    "iso:country":"GB",
    "wof:name":"HU3 2PW",
    "wof:placetype":"postalcode"
},
  "geometry": {"coordinates":[-0.3600702017402,53.74299820266594],"type":"Point"}
}