{
  "type": "Feature",
  "properties": {
    "iso:country": "GB",
    "wof:name": "M45 8RL",
    "wof:placetype": "postalcode"
  },
  "geometry": {"coordinates":[-2.275146,53.55622],"type":"Point"}
}
