{
  "type": "Feature",
  "properties": {
    "iso:country":"GB",
    "wof:name":"M45 8RL",
    "wof:placetype":"postalcode"
},
  "geometry": {"coordinates":[-2.27514562705185,53.55622023491313],"type":"Point"}
}