{
  "type": "Feature",
  "properties": {
    "date:inception_lower": "2015-12-01",
    "date:inception_upper": "2015-12-01",
    "iso:country": "GB",
    "wof:name": "TA6 6XR",
    "wof:placetype": "postalcode"
  },
  "geometry": {"coordinates":[-2.998135,51.109564],"type":"Point"}
}
