{
  "type": "Feature",
  "properties": {
    "date:inception_lower": "1990-02-01",
    "date:inception_upper": "1990-02-01",
    "iso:country": "GB",
    "wof:name": "DA9 9PP",
    "wof:placetype": "postalcode"
  },
  "geometry": {"coordinates":[0.266443,51.449775],"type":"Point"}
}
