{
  "type": "Feature",
  "properties": {
    "iso:country":"GB",
    "wof:name":"DA9 9PP",
    "wof:placetype":"postalcode"
},
  "geometry": {"coordinates":[0.26644333561231,51.4497752936462],"type":"Point"}
}