{
  "type": "Feature",
  "properties": {
    "date:inception_lower": "1987-04-01",
    "date:inception_upper": "1987-04-01",
    "iso:country": "GB",
    "wof:name": "PO7 7SD",
    "wof:placetype": "postalcode"
  },
  "geometry": {"coordinates":[-1.028086,50.884282],"type":"Point"}
}
