{
  "type": "Feature",
  "properties": {
    "iso:country":"GB",
    "wof:name":"PO7 7SD",
    "wof:placetype":"postalcode"
},
  "geometry": {"coordinates":[-1.02808645844489,50.88428164920272],"type":"Point"}
}