{
  "type": "Feature",
  "properties": {
    "date:inception_lower": "1998-12-01",
    "date:inception_upper": "1998-12-01",
    "iso:country": "GB",
    "wof:name": "IV3 8RN",
    "wof:placetype": "postalcode"
  },
  "geometry": {"coordinates":[-4.374269,57.460404],"type":"Point"}
}
