{
  "type": "Feature",
  "properties": {
    "iso:country":"GB",
    "wof:name":"IV3 8RN",
    "wof:placetype":"postalcode"
},
  "geometry": {"coordinates":[-4.3758983345005,57.4598062676278],"type":"Point"}
}