{
  "type": "Feature",
  "properties": {
    "iso:country":"GB",
    "wof:name":"GU11 1HG",
    "wof:placetype":"postalcode"
},
  "geometry": {"coordinates":[-0.76173727201852,51.24693112474353],"type":"Point"}
}