{
  "type": "Feature",
  "properties": {
    "iso:country": "GB",
    "wof:name": "GU11 1HG",
    "wof:placetype": "postalcode"
  },
  "geometry": {"coordinates":[-0.761737,51.246931],"type":"Point"}
}
