{
  "type": "Feature",
  "properties": {
    "iso:country":"GB",
    "wof:name":"GL1 2EF",
    "wof:placetype":"postalcode"
},
  "geometry": {"coordinates":[-2.2521470254,51.87478900406418],"type":"Point"}
}