{
  "type": "Feature",
  "properties": {
    "date:inception_lower": "1980-01-01",
    "date:inception_upper": "1980-01-01",
    "iso:country": "GB",
    "wof:name": "G41 2AY",
    "wof:placetype": "postalcode"
  },
  "geometry": {"coordinates":[-4.272336,55.835491],"type":"Point"}
}
