{
  "type": "Feature",
  "properties": {
    "iso:country":"GB",
    "wof:name":"G41 2AY",
    "wof:placetype":"postalcode"
},
  "geometry": {"coordinates":[-4.2721655841345,55.83560729559095],"type":"Point"}
}