{
  "type": "Feature",
  "properties": {
    "iso:country": "GB",
    "wof:name": "HR2 9FH",
    "wof:placetype": "postalcode"
  },
  "geometry": {"coordinates":[-2.799585,52.03523],"type":"Point"}
}
