{
  "type": "Feature",
  "properties": {
    "iso:country": "GB",
    "wof:name": "DL2 2UW",
    "wof:placetype": "postalcode"
  },
  "geometry": {"coordinates":[-1.69286,54.597399],"type":"Point"}
}
