{
  "type": "Feature",
  "properties": {
    "date:inception_lower":"1980-01-01",
    "date:inception_upper":"1980-01-31",
    "iso:country":"GB",
    "wof:name":"DL2 2UW",
    "wof:placetype":"postalcode"
},
  "geometry": {"coordinates":[-1.69286,54.597399],"type":"Point"}
}