{
  "type": "Feature",
  "properties": {
    "iso:country":"GB",
    "wof:name":"DL2 2UW",
    "wof:placetype":"postalcode"
},
  "geometry": {"coordinates":[-1.6928597614344,54.59739924018497],"type":"Point"}
}