{
  "type": "Feature",
  "properties": {
    "iso:country":"GB",
    "wof:name":"TQ5 8EA",
    "wof:placetype":"postalcode"
},
  "geometry": {"coordinates":[-3.51401319142787,50.39496324241539],"type":"Point"}
}