{
  "type": "Feature",
  "properties": {
    "iso:country":"GB",
    "wof:name":"TW18 4HB",
    "wof:placetype":"postalcode"
},
  "geometry": {"coordinates":[-0.50241365272424,51.43605900839014],"type":"Point"}
}