{
  "type": "Feature",
  "properties": {
    "date:inception_lower": "1988-03-01",
    "date:inception_upper": "1988-03-01",
    "iso:country": "GB",
    "wof:name": "DT11 7XB",
    "wof:placetype": "postalcode"
  },
  "geometry": {"coordinates":[-2.159074,50.871266],"type":"Point"}
}
