{
  "type": "Feature",
  "properties": {
    "iso:country": "GB",
    "wof:name": "DT11 7XB",
    "wof:placetype": "postalcode"
  },
  "geometry": {"coordinates":[-2.159074,50.871266],"type":"Point"}
}
