{
  "type": "Feature",
  "properties": {
    "iso:country":"GB",
    "wof:name":"DT11 7XB",
    "wof:placetype":"postalcode"
},
  "geometry": {"coordinates":[-2.15907448773621,50.87126591112778],"type":"Point"}
}