{
  "type": "Feature",
  "properties": {
    "iso:country":"GB",
    "wof:name":"B90 3QX",
    "wof:placetype":"postalcode"
},
  "geometry": {"coordinates":[-1.81564698444796,52.41123415704376],"type":"Point"}
}