{
  "type": "Feature",
  "properties": {
    "iso:country": "GB",
    "wof:name": "RM5 2RD",
    "wof:placetype": "postalcode"
  },
  "geometry": {"coordinates":[0.156324,51.600496],"type":"Point"}
}
