{
  "type": "Feature",
  "properties": {
    "iso:country":"GB",
    "wof:name":"CW2 7JZ",
    "wof:placetype":"postalcode"
},
  "geometry": {"coordinates":[-2.44561721921598,53.09409805224928],"type":"Point"}
}