{
  "type": "Feature",
  "properties": {
    "date:inception_lower": "1983-07-01",
    "date:inception_upper": "1983-07-01",
    "iso:country": "GB",
    "wof:name": "HP11 1TU",
    "wof:placetype": "postalcode"
  },
  "geometry": {"coordinates":[-0.771592,51.615034],"type":"Point"}
}
