{
  "type": "Feature",
  "properties": {
    "iso:country": "GB",
    "wof:name": "YO41 5RW",
    "wof:placetype": "postalcode"
  },
  "geometry": {"coordinates":[-0.890241,53.948109],"type":"Point"}
}
