{
  "type": "Feature",
  "properties": {
    "date:inception_lower": "1998-06-01",
    "date:inception_upper": "1998-06-01",
    "iso:country": "GB",
    "wof:name": "YO41 5RW",
    "wof:placetype": "postalcode"
  },
  "geometry": {"coordinates":[-0.890241,53.948109],"type":"Point"}
}
