{
  "type": "Feature",
  "properties": {
    "iso:country":"GB",
    "wof:name":"YO41 5RW",
    "wof:placetype":"postalcode"
},
  "geometry": {"coordinates":[-0.89024140033144,53.94810918147445],"type":"Point"}
}