{
  "type": "Feature",
  "properties": {
    "date:inception_lower":"1983-01-01",
    "date:inception_upper":"1983-01-31",
    "iso:country":"GB",
    "wof:name":"PO16 8BB",
    "wof:placetype":"postalcode"
},
  "geometry": {"coordinates":[-1.154267,50.849653],"type":"Point"}
}