{
  "type": "Feature",
  "properties": {
    "iso:country":"GB",
    "wof:name":"PO16 8BB",
    "wof:placetype":"postalcode"
},
  "geometry": {"coordinates":[-1.15426704196179,50.84965290393755],"type":"Point"}
}