{
  "type": "Feature",
  "properties": {
    "iso:country":"GB",
    "wof:name":"DE22 3FL",
    "wof:placetype":"postalcode"
},
  "geometry": {"coordinates":[-1.49378272418388,52.92673880869309],"type":"Point"}
}