{
  "type": "Feature",
  "properties": {
    "date:inception_lower": "2011-02-01",
    "date:inception_upper": "2011-02-01",
    "iso:country": "GB",
    "wof:name": "DE22 3FL",
    "wof:placetype": "postalcode"
  },
  "geometry": {"coordinates":[-1.493719,52.926784],"type":"Point"}
}
