{
  "type": "Feature",
  "properties": {
    "date:inception_lower": "2020-12-01",
    "date:inception_upper": "2020-12-01",
    "iso:country": "GB",
    "wof:name": "G32 7BF",
    "wof:placetype": "postalcode"
  },
  "geometry": {"coordinates":[-4.175011,55.84428],"type":"Point"}
}
