{
  "type": "Feature",
  "properties": {
    "iso:country":"GB",
    "wof:name":"SN14 6HP",
    "wof:placetype":"postalcode"
},
  "geometry": {"coordinates":[-2.13040820441789,51.47291864365958],"type":"Point"}
}