{
  "type": "Feature",
  "properties": {
    "iso:country":"GB",
    "wof:name":"E16 1LP",
    "wof:placetype":"postalcode"
},
  "geometry": {"coordinates":[0.01704094682053,51.51390025740405],"type":"Point"}
}