{
  "type": "Feature",
  "properties": {
    "date:inception_lower": "1980-01-01",
    "date:inception_upper": "1980-01-01",
    "iso:country": "GB",
    "wof:name": "DH3 1PQ",
    "wof:placetype": "postalcode"
  },
  "geometry": {"coordinates":[-1.581259,54.905368],"type":"Point"}
}
