{
  "type": "Feature",
  "properties": {
    "iso:country":"GB",
    "wof:name":"DH3 1PQ",
    "wof:placetype":"postalcode"
},
  "geometry": {"coordinates":[-1.5812589010021,54.90536835005688],"type":"Point"}
}