{
  "type": "Feature",
  "properties": {
    "iso:country":"GB",
    "wof:name":"SP1 3AU",
    "wof:placetype":"postalcode"
},
  "geometry": {"coordinates":[-1.78924380482386,51.0740779633877],"type":"Point"}
}