{
  "type": "Feature",
  "properties": {
    "iso:country":"GB",
    "wof:name":"HA0 3LG",
    "wof:placetype":"postalcode"
},
  "geometry": {"coordinates":[-0.3172210740279,51.56201139058513],"type":"Point"}
}