{
  "type": "Feature",
  "properties": {
    "iso:country":"GB",
    "wof:name":"BS14 0BF",
    "wof:placetype":"postalcode"
},
  "geometry": {"coordinates":[-2.57493302553612,51.41992380248594],"type":"Point"}
}