{
  "type": "Feature",
  "properties": {
    "iso:country":"GB",
    "wof:name":"EH47 9HU",
    "wof:placetype":"postalcode"
},
  "geometry": {"coordinates":[-3.70828804187811,55.82829610113701],"type":"Point"}
}