{
  "type": "Feature",
  "properties": {
    "date:inception_lower": "1980-01-01",
    "date:inception_upper": "1980-01-01",
    "iso:country": "GB",
    "wof:name": "CV33 9BS",
    "wof:placetype": "postalcode"
  },
  "geometry": {"coordinates":[-1.464728,52.32893],"type":"Point"}
}
