{
  "type": "Feature",
  "properties": {
    "iso:country": "GB",
    "wof:name": "WS15 1FJ",
    "wof:placetype": "postalcode"
  },
  "geometry": {"coordinates":[-1.912815,52.747689],"type":"Point"}
}
