{
  "type": "Feature",
  "properties": {
    "iso:country":"GB",
    "wof:name":"TQ14 8BZ",
    "wof:placetype":"postalcode"
},
  "geometry": {"coordinates":[-3.49774771811429,50.54474710373664],"type":"Point"}
}