{
  "type": "Feature",
  "properties": {
    "iso:country":"GB",
    "wof:name":"PE37 8LZ",
    "wof:placetype":"postalcode"
},
  "geometry": {"coordinates":[0.77235395677263,52.65026223214643],"type":"Point"}
}