{
  "type": "Feature",
  "properties": {
    "date:inception_lower": "1980-01-01",
    "date:inception_upper": "1980-01-01",
    "iso:country": "GB",
    "wof:name": "PE37 8LZ",
    "wof:placetype": "postalcode"
  },
  "geometry": {"coordinates":[0.772354,52.650262],"type":"Point"}
}
