{
  "type": "Feature",
  "properties": {
    "iso:country":"GB",
    "wof:name":"B69 4NB",
    "wof:placetype":"postalcode"
},
  "geometry": {"coordinates":[-2.00394784812134,52.49469669810257],"type":"Point"}
}