{
  "type": "Feature",
  "properties": {
    "iso:country": "GB",
    "wof:name": "B69 4NB",
    "wof:placetype": "postalcode"
  },
  "geometry": {"coordinates":[-2.003756,52.494885],"type":"Point"}
}
