{
  "type": "Feature",
  "properties": {
    "iso:country":"GB",
    "wof:name":"SY8 3AQ",
    "wof:placetype":"postalcode"
},
  "geometry": {"coordinates":[-2.60675830362319,52.35182323189622],"type":"Point"}
}