{
  "type": "Feature",
  "properties": {
    "date:inception_lower": "1980-01-01",
    "date:inception_upper": "1980-01-01",
    "iso:country": "GB",
    "wof:name": "SY8 3AQ",
    "wof:placetype": "postalcode"
  },
  "geometry": {"coordinates":[-2.604005,52.352498],"type":"Point"}
}
