{
  "type": "Feature",
  "properties": {
    "iso:country": "GB",
    "wof:name": "SY8 3AQ",
    "wof:placetype": "postalcode"
  },
  "geometry": {"coordinates":[-2.606756,52.351837],"type":"Point"}
}
