{
  "type": "Feature",
  "properties": {
    "date:inception_lower":"2016-02-01",
    "date:inception_upper":"2016-02-29",
    "iso:country":"GB",
    "wof:name":"LU7 0FR",
    "wof:placetype":"postalcode"
},
  "geometry": {"coordinates":[-0.648531,51.957414],"type":"Point"}
}