{
  "type": "Feature",
  "properties": {
    "iso:country": "GB",
    "wof:name": "LU7 0FR",
    "wof:placetype": "postalcode"
  },
  "geometry": {"coordinates":[-0.648531,51.957414],"type":"Point"}
}
