{
  "type": "Feature",
  "properties": {
    "iso:country":"GB",
    "wof:name":"HU2 0PY",
    "wof:placetype":"postalcode"
},
  "geometry": {"coordinates":[-0.33353444530933,53.75332028516139],"type":"Point"}
}