{
  "type": "Feature",
  "properties": {
    "date:inception_lower":"1993-08-01",
    "date:inception_upper":"1993-08-31",
    "iso:country":"GB",
    "wof:name":"CB10 1NQ",
    "wof:placetype":"postalcode"
},
  "geometry": {"coordinates":[0.241502,52.021401],"type":"Point"}
}