{
  "type": "Feature",
  "properties": {
    "date:inception_lower": "1980-01-01",
    "date:inception_upper": "1980-01-01",
    "iso:country": "GB",
    "wof:name": "PR2 1RU",
    "wof:placetype": "postalcode"
  },
  "geometry": {"coordinates":[-2.765478,53.763696],"type":"Point"}
}
