{
  "type": "Feature",
  "properties": {
    "date:inception_lower":"1993-01-01",
    "date:inception_upper":"1993-01-31",
    "iso:country":"GB",
    "wof:name":"TR1 2SU",
    "wof:placetype":"postalcode"
},
  "geometry": {"coordinates":[-5.04322,50.252838],"type":"Point"}
}