{
  "type": "Feature",
  "properties": {
    "iso:country":"GB",
    "wof:name":"HA3 6NP",
    "wof:placetype":"postalcode"
},
  "geometry": {"coordinates":[-0.35700203566036,51.60428082071358],"type":"Point"}
}