{
  "type": "Feature",
  "properties": {
    "iso:country":"GB",
    "wof:name":"AL9 7SA",
    "wof:placetype":"postalcode"
},
  "geometry": {"coordinates":[-0.19958606960853,51.71806169083364],"type":"Point"}
}