{
  "type": "Feature",
  "properties": {
    "iso:country":"GB",
    "wof:name":"SY21 8HE",
    "wof:placetype":"postalcode"
},
  "geometry": {"coordinates":[-3.11100552877163,52.66831233477871],"type":"Point"}
}