{
  "type": "Feature",
  "properties": {
    "date:inception_lower": "2014-01-01",
    "date:inception_upper": "2014-01-01",
    "iso:country": "GB",
    "wof:name": "B37 7FE",
    "wof:placetype": "postalcode"
  },
  "geometry": {"coordinates":[-1.743552,52.461975],"type":"Point"}
}
