{
  "type": "Feature",
  "properties": {
    "iso:country": "GB",
    "wof:name": "B37 7FE",
    "wof:placetype": "postalcode"
  },
  "geometry": {"coordinates":[-1.743552,52.461975],"type":"Point"}
}
