{
  "type": "Feature",
  "properties": {
    "iso:country":"GB",
    "wof:name":"CR4 1AL",
    "wof:placetype":"postalcode"
},
  "geometry": {"coordinates":[-0.14872606258556,51.41119607606439],"type":"Point"}
}