{
  "type": "Feature",
  "properties": {
    "date:inception_lower": "2018-05-01",
    "date:inception_upper": "2018-05-01",
    "iso:country": "GB",
    "wof:name": "DE12 7RZ",
    "wof:placetype": "postalcode"
  },
  "geometry": {"coordinates":[-1.518952,52.715085],"type":"Point"}
}
