{
  "type": "Feature",
  "properties": {
    "iso:country": "GB",
    "wof:name": "EH13 0JU",
    "wof:placetype": "postalcode"
  },
  "geometry": {"coordinates":[-3.260339,55.906882],"type":"Point"}
}
