{
  "type": "Feature",
  "properties": {
    "iso:country":"GB",
    "wof:name":"DL8 3JQ",
    "wof:placetype":"postalcode"
},
  "geometry": {"coordinates":[-2.12017872747658,54.31247274121351],"type":"Point"}
}