{
  "type": "Feature",
  "properties": {
    "iso:country": "GB",
    "wof:name": "DL8 3JQ",
    "wof:placetype": "postalcode"
  },
  "geometry": {"coordinates":[-2.120179,54.312473],"type":"Point"}
}
