{
  "type": "Feature",
  "properties": {
    "date:inception_lower": "1980-01-01",
    "date:inception_upper": "1980-01-01",
    "iso:country": "GB",
    "wof:name": "S2 5BG",
    "wof:placetype": "postalcode"
  },
  "geometry": {"coordinates":[-1.439716,53.381423],"type":"Point"}
}
