{
  "type": "Feature",
  "properties": {
    "iso:country":"GB",
    "wof:name":"S2 5BG",
    "wof:placetype":"postalcode"
},
  "geometry": {"coordinates":[-1.4397158241034,53.38142315685588],"type":"Point"}
}