{
  "type": "Feature",
  "properties": {
    "iso:country":"GB",
    "wof:name":"SW12 0JN",
    "wof:placetype":"postalcode"
},
  "geometry": {"coordinates":[-0.13388772711918,51.44681435348891],"type":"Point"}
}