{
  "type": "Feature",
  "properties": {
    "iso:country":"GB",
    "wof:name":"LS29 0AF",
    "wof:placetype":"postalcode"
},
  "geometry": {"coordinates":[-1.82217349752168,53.92983204893243],"type":"Point"}
}