{
  "type": "Feature",
  "properties": {
    "date:inception_lower": "2010-11-01",
    "date:inception_upper": "2010-11-01",
    "iso:country": "GB",
    "wof:name": "LS29 0AF",
    "wof:placetype": "postalcode"
  },
  "geometry": {"coordinates":[-1.822177,53.929846],"type":"Point"}
}
