{
  "type": "Feature",
  "properties": {
    "date:inception_lower": "1980-01-01",
    "date:inception_upper": "1980-01-01",
    "iso:country": "GB",
    "wof:name": "PH7 4EJ",
    "wof:placetype": "postalcode"
  },
  "geometry": {"coordinates":[-3.848805,56.371786],"type":"Point"}
}
