{
  "type": "Feature",
  "properties": {
    "iso:country": "GB",
    "wof:name": "PH7 4EJ",
    "wof:placetype": "postalcode"
  },
  "geometry": {"coordinates":[-3.849254,56.371582],"type":"Point"}
}
