{
  "type": "Feature",
  "properties": {
    "iso:country":"GB",
    "wof:name":"HR4 9YA",
    "wof:placetype":"postalcode"
},
  "geometry": {"coordinates":[-2.72148593511248,52.06039668078784],"type":"Point"}
}