{
  "type": "Feature",
  "properties": {
    "date:inception_lower": "1988-03-01",
    "date:inception_upper": "1988-03-01",
    "iso:country": "GB",
    "wof:name": "HR4 9YA",
    "wof:placetype": "postalcode"
  },
  "geometry": {"coordinates":[-2.721486,52.060397],"type":"Point"}
}
