{
  "type": "Feature",
  "properties": {
    "iso:country":"GB",
    "wof:name":"RM9 5XA",
    "wof:placetype":"postalcode"
},
  "geometry": {"coordinates":[0.14685421071065,51.54971637614324],"type":"Point"}
}