{
  "type": "Feature",
  "properties": {
    "iso:country":"GB",
    "wof:name":"GL6 6TL",
    "wof:placetype":"postalcode"
},
  "geometry": {"coordinates":[-2.19037857398405,51.79788875179199],"type":"Point"}
}