{
  "type": "Feature",
  "properties": {
    "iso:country":"GB",
    "wof:name":"WA6 6LR",
    "wof:placetype":"postalcode"
},
  "geometry": {"coordinates":[-2.66630897336047,53.26081171823093],"type":"Point"}
}