{
  "type": "Feature",
  "properties": {
    "iso:country":"GB",
    "wof:name":"N4 3AR",
    "wof:placetype":"postalcode"
},
  "geometry": {"coordinates":[-0.11168863394201,51.57073584860623],"type":"Point"}
}