{
  "type": "Feature",
  "properties": {
    "date:inception_lower": "1980-01-01",
    "date:inception_upper": "1980-01-01",
    "iso:country": "GB",
    "wof:name": "N4 3AR",
    "wof:placetype": "postalcode"
  },
  "geometry": {"coordinates":[-0.111689,51.570736],"type":"Point"}
}
