{
  "type": "Feature",
  "properties": {
    "iso:country": "GB",
    "wof:name": "N4 3AR",
    "wof:placetype": "postalcode"
  },
  "geometry": {"coordinates":[-0.111689,51.570736],"type":"Point"}
}
