{
  "type": "Feature",
  "properties": {
    "iso:country": "GB",
    "wof:name": "NN18 0AE",
    "wof:placetype": "postalcode"
  },
  "geometry": {"coordinates":[-0.725963,52.488946],"type":"Point"}
}
