{
  "type": "Feature",
  "properties": {
    "date:inception_lower":"1981-09-01",
    "date:inception_upper":"1981-09-30",
    "iso:country":"GB",
    "wof:name":"WS2 0LL",
    "wof:placetype":"postalcode"
},
  "geometry": {"coordinates":[-2.021391,52.592621],"type":"Point"}
}