{
  "type": "Feature",
  "properties": {
    "iso:country":"GB",
    "wof:name":"SS7 3QF",
    "wof:placetype":"postalcode"
},
  "geometry": {"coordinates":[0.58799252605075,51.56731595478167],"type":"Point"}
}