{
  "type": "Feature",
  "properties": {
    "iso:country": "GB",
    "wof:name": "SS7 3QF",
    "wof:placetype": "postalcode"
  },
  "geometry": {"coordinates":[0.587993,51.567316],"type":"Point"}
}
