{
  "type": "Feature",
  "properties": {
    "iso:country": "GB",
    "wof:name": "PE7 8HN",
    "wof:placetype": "postalcode"
  },
  "geometry": {"coordinates":[-0.278861,52.539274],"type":"Point"}
}
