{
  "type": "Feature",
  "properties": {
    "iso:country":"GB",
    "wof:name":"PE7 8HN",
    "wof:placetype":"postalcode"
},
  "geometry": {"coordinates":[-0.27886107656331,52.53927370892266],"type":"Point"}
}