{
  "type": "Feature",
  "properties": {
    "date:inception_lower": "2007-07-01",
    "date:inception_upper": "2007-07-01",
    "iso:country": "GB",
    "wof:name": "PE7 8HN",
    "wof:placetype": "postalcode"
  },
  "geometry": {"coordinates":[-0.278861,52.539274],"type":"Point"}
}
