{
  "type": "Feature",
  "properties": {
    "iso:country":"GB",
    "wof:name":"BS5 8HY",
    "wof:placetype":"postalcode"
},
  "geometry": {"coordinates":[-2.53893503320721,51.45884890888301],"type":"Point"}
}