{
  "type": "Feature",
  "properties": {
    "iso:country":"GB",
    "wof:name":"SE26 5JQ",
    "wof:placetype":"postalcode"
},
  "geometry": {"coordinates":[-0.05562665344828,51.42076742183444],"type":"Point"}
}