{
  "type": "Feature",
  "properties": {
    "date:inception_lower": "1980-01-01",
    "date:inception_upper": "1980-01-01",
    "iso:country": "GB",
    "wof:name": "SE26 5JQ",
    "wof:placetype": "postalcode"
  },
  "geometry": {"coordinates":[-0.055627,51.420767],"type":"Point"}
}
