{
  "type": "Feature",
  "properties": {
    "date:inception_lower": "2002-12-01",
    "date:inception_upper": "2002-12-01",
    "iso:country": "GB",
    "wof:name": "SE10 0SX",
    "wof:placetype": "postalcode"
  },
  "geometry": {"coordinates":[0.015187,51.495722],"type":"Point"}
}
