{
  "type": "Feature",
  "properties": {
    "iso:country":"GB",
    "wof:name":"SE10 0SX",
    "wof:placetype":"postalcode"
},
  "geometry": {"coordinates":[0.01518661784548,51.49572190905609],"type":"Point"}
}