{
  "type": "Feature",
  "properties": {
    "iso:country":"GB",
    "wof:name":"BN16 3AT",
    "wof:placetype":"postalcode"
},
  "geometry": {"coordinates":[-0.49155521404576,50.8116193502986],"type":"Point"}
}