{
  "type": "Feature",
  "properties": {
    "iso:country": "GB",
    "wof:name": "BN16 3AT",
    "wof:placetype": "postalcode"
  },
  "geometry": {"coordinates":[-0.491555,50.811619],"type":"Point"}
}
