{
  "type": "Feature",
  "properties": {
    "iso:country": "GB",
    "wof:name": "WV2 2JN",
    "wof:placetype": "postalcode"
  },
  "geometry": {"coordinates":[-2.105331,52.575963],"type":"Point"}
}
