{
  "type": "Feature",
  "properties": {
    "date:inception_lower":"1994-05-01",
    "date:inception_upper":"1994-05-31",
    "iso:country":"GB",
    "wof:name":"M22 0NN",
    "wof:placetype":"postalcode"
},
  "geometry": {"coordinates":[-2.262964,53.373611],"type":"Point"}
}