{
  "type": "Feature",
  "properties": {
    "iso:country":"GB",
    "wof:name":"BR6 7DF",
    "wof:placetype":"postalcode"
},
  "geometry": {"coordinates":[0.07030237736535,51.36100172123142],"type":"Point"}
}