{
  "type": "Feature",
  "properties": {
    "date:inception_lower": "1996-12-01",
    "date:inception_upper": "1996-12-01",
    "iso:country": "GB",
    "wof:name": "LN4 3BF",
    "wof:placetype": "postalcode"
  },
  "geometry": {"coordinates":[-0.358966,53.143982],"type":"Point"}
}
