{
  "type": "Feature",
  "properties": {
    "iso:country":"GB",
    "wof:name":"LN4 3BF",
    "wof:placetype":"postalcode"
},
  "geometry": {"coordinates":[-0.3589664594154,53.14398179153793],"type":"Point"}
}