{
  "type": "Feature",
  "properties": {
    "iso:country":"GB",
    "wof:name":"TS17 0XH",
    "wof:placetype":"postalcode"
},
  "geometry": {"coordinates":[-1.30674390251856,54.51383397363775],"type":"Point"}
}