{
  "type": "Feature",
  "properties": {
    "date:inception_lower": "1991-09-01",
    "date:inception_upper": "1991-09-01",
    "iso:country": "GB",
    "wof:name": "OX7 7EG",
    "wof:placetype": "postalcode"
  },
  "geometry": {"coordinates":[-1.368887,51.939857],"type":"Point"}
}
