{
  "type": "Feature",
  "properties": {
    "iso:country":"GB",
    "wof:name":"OX7 7EG",
    "wof:placetype":"postalcode"
},
  "geometry": {"coordinates":[-1.36890405961683,51.93984795275205],"type":"Point"}
}