{
  "type": "Feature",
  "properties": {
    "iso:country":"GB",
    "wof:name":"SO24 9XF",
    "wof:placetype":"postalcode"
},
  "geometry": {"coordinates":[-1.16250344616283,51.08033364492328],"type":"Point"}
}