{
  "type": "Feature",
  "properties": {
    "iso:country": "GB",
    "wof:name": "ST4 8NU",
    "wof:placetype": "postalcode"
  },
  "geometry": {"coordinates":[-2.198463,52.967947],"type":"Point"}
}
