{
  "type": "Feature",
  "properties": {
    "iso:country": "GB",
    "wof:name": "LL31 9RA",
    "wof:placetype": "postalcode"
  },
  "geometry": {"coordinates":[-3.814313,53.290812],"type":"Point"}
}
