{
  "type": "Feature",
  "properties": {
    "iso:country":"GB",
    "wof:name":"BA21 5QP",
    "wof:placetype":"postalcode"
},
  "geometry": {"coordinates":[-2.61191825028334,50.95311161980958],"type":"Point"}
}