{
  "type": "Feature",
  "properties": {
    "iso:country":"GB",
    "wof:name":"AL5 2AU",
    "wof:placetype":"postalcode"
},
  "geometry": {"coordinates":[-0.36483895872632,51.80029889047146],"type":"Point"}
}