{
  "type": "Feature",
  "properties": {
    "iso:country": "GB",
    "wof:name": "OX16 5DB",
    "wof:placetype": "postalcode"
  },
  "geometry": {"coordinates":[-1.336936,52.059799],"type":"Point"}
}
