{
  "type": "Feature",
  "properties": {
    "date:inception_lower":"1980-01-01",
    "date:inception_upper":"1980-01-31",
    "iso:country":"GB",
    "wof:name":"DN16 3BG",
    "wof:placetype":"postalcode"
},
  "geometry": {"coordinates":[-0.634187,53.561155],"type":"Point"}
}