{
  "type": "Feature",
  "properties": {
    "iso:country":"GB",
    "wof:name":"DN16 3BG",
    "wof:placetype":"postalcode"
},
  "geometry": {"coordinates":[-0.6341872054328,53.56115549681146],"type":"Point"}
}