{
  "type": "Feature",
  "properties": {
    "iso:country": "GB",
    "wof:name": "DN16 3BG",
    "wof:placetype": "postalcode"
  },
  "geometry": {"coordinates":[-0.634187,53.561155],"type":"Point"}
}
