{
  "type": "Feature",
  "properties": {
    "date:inception_lower":"1980-01-01",
    "date:inception_upper":"1980-01-31",
    "iso:country":"GB",
    "wof:name":"BN25 1HB",
    "wof:placetype":"postalcode"
},
  "geometry": {"coordinates":[0.101263,50.770501],"type":"Point"}
}