{
  "type": "Feature",
  "properties": {
    "date:inception_lower":"1980-01-01",
    "date:inception_upper":"1980-01-31",
    "iso:country":"GB",
    "wof:name":"NR19 1DW",
    "wof:placetype":"postalcode"
},
  "geometry": {"coordinates":[0.939798,52.680756],"type":"Point"}
}