{
  "type": "Feature",
  "properties": {
    "iso:country":"GB",
    "wof:name":"IP17 2RF",
    "wof:placetype":"postalcode"
},
  "geometry": {"coordinates":[1.48826797282047,52.24111496088517],"type":"Point"}
}