{
  "type": "Feature",
  "properties": {
    "iso:country":"GB",
    "wof:name":"HA3 0AG",
    "wof:placetype":"postalcode"
},
  "geometry": {"coordinates":[-0.32016019655938,51.58012788277937],"type":"Point"}
}