{
  "type": "Feature",
  "properties": {
    "date:inception_lower": "1990-02-01",
    "date:inception_upper": "1990-02-01",
    "iso:country": "GB",
    "wof:name": "HP20 2DP",
    "wof:placetype": "postalcode"
  },
  "geometry": {"coordinates":[-0.801996,51.825931],"type":"Point"}
}
