{
  "type": "Feature",
  "properties": {
    "iso:country":"GB",
    "wof:name":"CF34 0TL",
    "wof:placetype":"postalcode"
},
  "geometry": {"coordinates":[-3.65790994322617,51.62461072535827],"type":"Point"}
}