{
  "type": "Feature",
  "properties": {
    "iso:country": "GB",
    "wof:name": "CF34 0TL",
    "wof:placetype": "postalcode"
  },
  "geometry": {"coordinates":[-3.6579,51.624695],"type":"Point"}
}
