{
  "type": "Feature",
  "properties": {
    "iso:country":"GB",
    "wof:name":"SW6 2PJ",
    "wof:placetype":"postalcode"
},
  "geometry": {"coordinates":[-0.18679509317993,51.47136693079513],"type":"Point"}
}