{
  "type": "Feature",
  "properties": {
    "iso:country":"GB",
    "wof:name":"DD10 9TN",
    "wof:placetype":"postalcode"
},
  "geometry": {"coordinates":[-2.54675688679948,56.66975539448975],"type":"Point"}
}