{
  "type": "Feature",
  "properties": {
    "date:inception_lower":"1980-01-01",
    "date:inception_upper":"1980-01-31",
    "iso:country":"GB",
    "wof:name":"DD10 9TN",
    "wof:placetype":"postalcode"
},
  "geometry": {"coordinates":[-2.546757,56.669755],"type":"Point"}
}