{
  "type": "Feature",
  "properties": {
    "iso:country":"GB",
    "wof:name":"YO62 6BY",
    "wof:placetype":"postalcode"
},
  "geometry": {"coordinates":[-0.94075987214512,54.27131395973633],"type":"Point"}
}