{
  "type": "Feature",
  "properties": {
    "iso:country": "GB",
    "wof:name": "CW9 6QT",
    "wof:placetype": "postalcode"
  },
  "geometry": {"coordinates":[-2.492934,53.273583],"type":"Point"}
}
