{
  "type": "Feature",
  "properties": {
    "iso:country":"GB",
    "wof:name":"CW9 6QT",
    "wof:placetype":"postalcode"
},
  "geometry": {"coordinates":[-2.49293396608528,53.27358310689348],"type":"Point"}
}