{
  "type": "Feature",
  "properties": {
    "date:inception_lower":"1992-08-01",
    "date:inception_upper":"1992-08-31",
    "iso:country":"GB",
    "wof:name":"CW9 6QT",
    "wof:placetype":"postalcode"
},
  "geometry": {"coordinates":[-2.492934,53.273583],"type":"Point"}
}