{
  "type": "Feature",
  "properties": {
    "iso:country": "GB",
    "wof:name": "KA27 8NY",
    "wof:placetype": "postalcode"
  },
  "geometry": {"coordinates":[-5.2508,55.47184],"type":"Point"}
}
