{
  "type": "Feature",
  "properties": {
    "iso:country":"GB",
    "wof:name":"KA27 8NY",
    "wof:placetype":"postalcode"
},
  "geometry": {"coordinates":[-5.24913586529261,55.46853947331687],"type":"Point"}
}