{
  "type": "Feature",
  "properties": {
    "date:inception_lower": "1980-01-01",
    "date:inception_upper": "1980-01-01",
    "iso:country": "GB",
    "wof:name": "NE33 2NX",
    "wof:placetype": "postalcode"
  },
  "geometry": {"coordinates":[-1.426023,54.999361],"type":"Point"}
}
