{
  "type": "Feature",
  "properties": {
    "iso:country": "GB",
    "wof:name": "PO33 1DX",
    "wof:placetype": "postalcode"
  },
  "geometry": {"coordinates":[-1.153378,50.722048],"type":"Point"}
}
