{
  "type": "Feature",
  "properties": {
    "date:inception_lower": "1980-01-01",
    "date:inception_upper": "1980-01-01",
    "iso:country": "GB",
    "wof:name": "PO33 1DX",
    "wof:placetype": "postalcode"
  },
  "geometry": {"coordinates":[-1.153382,50.722001],"type":"Point"}
}
