{
  "type": "Feature",
  "properties": {
    "date:inception_lower":"1980-01-01",
    "date:inception_upper":"1980-01-31",
    "iso:country":"GB",
    "wof:name":"YO25 8JX",
    "wof:placetype":"postalcode"
},
  "geometry": {"coordinates":[-0.330411,53.962595],"type":"Point"}
}