{
  "type": "Feature",
  "properties": {
    "iso:country": "GB",
    "wof:name": "YO25 8JX",
    "wof:placetype": "postalcode"
  },
  "geometry": {"coordinates":[-0.330411,53.962595],"type":"Point"}
}
