{
  "type": "Feature",
  "properties": {
    "date:inception_lower": "2021-06-01",
    "date:inception_upper": "2021-06-01",
    "iso:country": "GB",
    "wof:name": "SS14 3UB",
    "wof:placetype": "postalcode"
  },
  "geometry": {"coordinates":[0.486287,51.577658],"type":"Point"}
}
