{
  "type": "Feature",
  "properties": {
    "iso:country":"GB",
    "wof:name":"DA4 9EF",
    "wof:placetype":"postalcode"
},
  "geometry": {"coordinates":[0.23689741352017,51.4059439996071],"type":"Point"}
}