{
  "type": "Feature",
  "properties": {
    "iso:country":"GB",
    "wof:name":"SA62 6RJ",
    "wof:placetype":"postalcode"
},
  "geometry": {"coordinates":[-5.27029823402743,51.88027615881808],"type":"Point"}
}