{
  "type": "Feature",
  "properties": {
    "date:inception_lower":"1980-01-01",
    "date:inception_upper":"1980-01-31",
    "iso:country":"GB",
    "wof:name":"SA62 6RJ",
    "wof:placetype":"postalcode"
},
  "geometry": {"coordinates":[-5.270301,51.880256],"type":"Point"}
}