{
  "type": "Feature",
  "properties": {
    "iso:country":"GB",
    "wof:name":"RG25 3AH",
    "wof:placetype":"postalcode"
},
  "geometry": {"coordinates":[-1.23525826453722,51.24609884641699],"type":"Point"}
}