{
  "type": "Feature",
  "properties": {
    "iso:country":"GB",
    "wof:name":"RH11 9LX",
    "wof:placetype":"postalcode"
},
  "geometry": {"coordinates":[-0.20190024332092,51.09902070967497],"type":"Point"}
}