{
  "type": "Feature",
  "properties": {
    "iso:country":"GB",
    "wof:name":"PL1 2QL",
    "wof:placetype":"postalcode"
},
  "geometry": {"coordinates":[-4.14493567853086,50.36561740839506],"type":"Point"}
}