{
  "type": "Feature",
  "properties": {
    "iso:country": "GB",
    "wof:name": "PL1 2QL",
    "wof:placetype": "postalcode"
  },
  "geometry": {"coordinates":[-4.144936,50.365617],"type":"Point"}
}
