{
  "type": "Feature",
  "properties": {
    "iso:country":"GB",
    "wof:name":"W4 1RP",
    "wof:placetype":"postalcode"
},
  "geometry": {"coordinates":[-0.25548411795092,51.49419765559819],"type":"Point"}
}