{
  "type": "Feature",
  "properties": {
    "iso:country": "GB",
    "wof:name": "NN5 5BW",
    "wof:placetype": "postalcode"
  },
  "geometry": {"coordinates":[-0.919679,52.242024],"type":"Point"}
}
