{
  "type": "Feature",
  "properties": {
    "iso:country":"GB",
    "wof:name":"NN5 5BW",
    "wof:placetype":"postalcode"
},
  "geometry": {"coordinates":[-0.91967921517464,52.24202414519309],"type":"Point"}
}