{
  "type": "Feature",
  "properties": {
    "iso:country":"GB",
    "wof:name":"E6 2SA",
    "wof:placetype":"postalcode"
},
  "geometry": {"coordinates":[0.06144678975984,51.5337035109502],"type":"Point"}
}