{
  "type": "Feature",
  "properties": {
    "iso:country":"GB",
    "wof:name":"WA9 2HZ",
    "wof:placetype":"postalcode"
},
  "geometry": {"coordinates":[-2.6906984302983,53.4530244156047],"type":"Point"}
}