{
  "type": "Feature",
  "properties": {
    "iso:country": "GB",
    "wof:name": "CB4 1UN",
    "wof:placetype": "postalcode"
  },
  "geometry": {"coordinates":[0.160664,52.223078],"type":"Point"}
}
