{
  "type": "Feature",
  "properties": {
    "iso:country":"GB",
    "wof:name":"CB4 1UN",
    "wof:placetype":"postalcode"
},
  "geometry": {"coordinates":[0.16069280380895,52.22303699660413],"type":"Point"}
}