{
  "type": "Feature",
  "properties": {
    "date:inception_lower":"1980-01-01",
    "date:inception_upper":"1980-01-31",
    "iso:country":"GB",
    "wof:name":"HG4 3EZ",
    "wof:placetype":"postalcode"
},
  "geometry": {"coordinates":[-1.640771,54.100301],"type":"Point"}
}