{
  "type": "Feature",
  "properties": {
    "iso:country":"GB",
    "wof:name":"HG4 3EZ",
    "wof:placetype":"postalcode"
},
  "geometry": {"coordinates":[-1.64077092487888,54.10030071518101],"type":"Point"}
}