{
  "type": "Feature",
  "properties": {
    "iso:country": "GB",
    "wof:name": "YO21 1JH",
    "wof:placetype": "postalcode"
  },
  "geometry": {"coordinates":[-0.628049,54.484968],"type":"Point"}
}
