{
  "type": "Feature",
  "properties": {
    "iso:country":"GB",
    "wof:name":"YO21 1JH",
    "wof:placetype":"postalcode"
},
  "geometry": {"coordinates":[-0.62804876098625,54.48496822016865],"type":"Point"}
}