{
  "type": "Feature",
  "properties": {
    "iso:country":"GB",
    "wof:name":"SW19 6SE",
    "wof:placetype":"postalcode"
},
  "geometry": {"coordinates":[-0.21339794060307,51.44497765103523],"type":"Point"}
}