{
  "type": "Feature",
  "properties": {
    "date:inception_lower":"1980-01-01",
    "date:inception_upper":"1980-01-31",
    "iso:country":"GB",
    "wof:name":"PR5 4BL",
    "wof:placetype":"postalcode"
},
  "geometry": {"coordinates":[-2.658846,53.748906],"type":"Point"}
}