{
  "type": "Feature",
  "properties": {
    "date:inception_lower": "2021-02-01",
    "date:inception_upper": "2021-02-01",
    "iso:country": "GB",
    "wof:name": "RH10 2AD",
    "wof:placetype": "postalcode"
  },
  "geometry": {"coordinates":[-0.158595,51.134639],"type":"Point"}
}
