{
  "type": "Feature",
  "properties": {
    "date:inception_lower": "2023-05-01",
    "date:inception_upper": "2023-05-01",
    "iso:country": "GB",
    "wof:name": "L26 6AQ",
    "wof:placetype": "postalcode"
  },
  "geometry": {"coordinates":[-2.820372,53.368723],"type":"Point"}
}
