{
  "type": "Feature",
  "properties": {
    "iso:country": "GB",
    "wof:name": "EH32 0UH",
    "wof:placetype": "postalcode"
  },
  "geometry": {"coordinates":[-2.862454,56.005563],"type":"Point"}
}
