{
  "type": "Feature",
  "properties": {
    "iso:country": "GB",
    "wof:name": "NG24 4TZ",
    "wof:placetype": "postalcode"
  },
  "geometry": {"coordinates":[-0.818196,53.073813],"type":"Point"}
}
