{
  "type": "Feature",
  "properties": {
    "iso:country":"GB",
    "wof:name":"BS23 4JW",
    "wof:placetype":"postalcode"
},
  "geometry": {"coordinates":[-2.97684441459458,51.33210878347256],"type":"Point"}
}