{
  "type": "Feature",
  "properties": {
    "date:inception_lower": "1980-01-01",
    "date:inception_upper": "1980-01-01",
    "iso:country": "GB",
    "wof:name": "HD6 3EW",
    "wof:placetype": "postalcode"
  },
  "geometry": {"coordinates":[-1.785104,53.692211],"type":"Point"}
}
