{
  "type": "Feature",
  "properties": {
    "iso:country":"GB",
    "wof:name":"HD6 3EW",
    "wof:placetype":"postalcode"
},
  "geometry": {"coordinates":[-1.7851035661825,53.69221090317424],"type":"Point"}
}