{
  "type": "Feature",
  "properties": {
    "date:inception_lower": "1980-01-01",
    "date:inception_upper": "1980-01-01",
    "iso:country": "GB",
    "wof:name": "RH11 0NX",
    "wof:placetype": "postalcode"
  },
  "geometry": {"coordinates":[-0.213054,51.132759],"type":"Point"}
}
