{
  "type": "Feature",
  "properties": {
    "iso:country":"GB",
    "wof:name":"BS35 2ET",
    "wof:placetype":"postalcode"
},
  "geometry": {"coordinates":[-2.51316058759534,51.6053011865251],"type":"Point"}
}