{
  "type": "Feature",
  "properties": {
    "iso:country":"GB",
    "wof:name":"N7 8JB",
    "wof:placetype":"postalcode"
},
  "geometry": {"coordinates":[-0.11464701108816,51.54945327517335],"type":"Point"}
}