{
  "type": "Feature",
  "properties": {
    "iso:country":"GB",
    "wof:name":"NP22 5NJ",
    "wof:placetype":"postalcode"
},
  "geometry": {"coordinates":[-3.28597219733836,51.76263064928913],"type":"Point"}
}