{
  "type": "Feature",
  "properties": {
    "iso:country":"GB",
    "wof:name":"LE12 5SH",
    "wof:placetype":"postalcode"
},
  "geometry": {"coordinates":[-1.148369188209,52.7918720378582],"type":"Point"}
}