{
  "type": "Feature",
  "properties": {
    "iso:country":"GB",
    "wof:name":"CB9 7YB",
    "wof:placetype":"postalcode"
},
  "geometry": {"coordinates":[0.41482350125324,52.08650506952595],"type":"Point"}
}