{
  "type": "Feature",
  "properties": {
    "iso:country":"GB",
    "wof:name":"CR6 9RL",
    "wof:placetype":"postalcode"
},
  "geometry": {"coordinates":[-0.05817056732374,51.31214055895488],"type":"Point"}
}