{
  "type": "Feature",
  "properties": {
    "date:inception_lower": "1990-07-01",
    "date:inception_upper": "1990-07-01",
    "iso:country": "GB",
    "wof:name": "CR6 9RL",
    "wof:placetype": "postalcode"
  },
  "geometry": {"coordinates":[-0.05841,51.312279],"type":"Point"}
}
