{
  "type": "Feature",
  "properties": {
    "iso:country": "GB",
    "wof:name": "CR6 9RL",
    "wof:placetype": "postalcode"
  },
  "geometry": {"coordinates":[-0.05841,51.312279],"type":"Point"}
}
