{
  "type": "Feature",
  "properties": {
    "iso:country": "GB",
    "wof:name": "LD5 4SA",
    "wof:placetype": "postalcode"
  },
  "geometry": {"coordinates":[-3.633744,52.109606],"type":"Point"}
}
