{
  "type": "Feature",
  "properties": {
    "date:inception_lower": "1980-01-01",
    "date:inception_upper": "1980-01-01",
    "iso:country": "GB",
    "wof:name": "LD5 4SA",
    "wof:placetype": "postalcode"
  },
  "geometry": {"coordinates":[-3.633744,52.109606],"type":"Point"}
}
