{
  "type": "Feature",
  "properties": {
    "iso:country":"GB",
    "wof:name":"LD5 4SA",
    "wof:placetype":"postalcode"
},
  "geometry": {"coordinates":[-3.63374406067538,52.10960563268733],"type":"Point"}
}