{
  "type": "Feature",
  "properties": {
    "iso:country":"GB",
    "wof:name":"SM4 5BU",
    "wof:placetype":"postalcode"
},
  "geometry": {"coordinates":[-0.19848867883438,51.40183695004605],"type":"Point"}
}