{
  "type": "Feature",
  "properties": {
    "date:inception_lower": "1980-01-01",
    "date:inception_upper": "1980-01-01",
    "iso:country": "GB",
    "wof:name": "SM4 5BU",
    "wof:placetype": "postalcode"
  },
  "geometry": {"coordinates":[-0.198489,51.401837],"type":"Point"}
}
