{
  "type": "Feature",
  "properties": {
    "iso:country":"GB",
    "wof:name":"BA3 3BS",
    "wof:placetype":"postalcode"
},
  "geometry": {"coordinates":[-2.45585267114593,51.30085747842926],"type":"Point"}
}