{
  "type": "Feature",
  "properties": {
    "date:inception_lower": "1984-10-01",
    "date:inception_upper": "1984-10-01",
    "iso:country": "GB",
    "wof:name": "RH4 1EB",
    "wof:placetype": "postalcode"
  },
  "geometry": {"coordinates":[-0.3372,51.232228],"type":"Point"}
}
