{
  "type": "Feature",
  "properties": {
    "iso:country":"GB",
    "wof:name":"PA60 7XZ",
    "wof:placetype":"postalcode"
},
  "geometry": {"coordinates":[-5.91030901834319,55.8776126251763],"type":"Point"}
}