{
  "type": "Feature",
  "properties": {
    "date:inception_lower": "1980-01-01",
    "date:inception_upper": "1980-01-01",
    "iso:country": "GB",
    "wof:name": "PA60 7XZ",
    "wof:placetype": "postalcode"
  },
  "geometry": {"coordinates":[-5.910309,55.877613],"type":"Point"}
}
