{
  "type": "Feature",
  "properties": {
    "iso:country":"GB",
    "wof:name":"WA4 3HP",
    "wof:placetype":"postalcode"
},
  "geometry": {"coordinates":[-2.54664950691369,53.35120989856038],"type":"Point"}
}