{
  "type": "Feature",
  "properties": {
    "iso:country":"GB",
    "wof:name":"AB21 9UU",
    "wof:placetype":"postalcode"
},
  "geometry": {"coordinates":[-2.19085064192169,57.17389580173919],"type":"Point"}
}