{
  "type": "Feature",
  "properties": {
    "iso:country":"GB",
    "wof:name":"WN2 2RB",
    "wof:placetype":"postalcode"
},
  "geometry": {"coordinates":[-2.57537744596335,53.53975490904134],"type":"Point"}
}