{
  "type": "Feature",
  "properties": {
    "iso:country":"GB",
    "wof:name":"RH7 6LT",
    "wof:placetype":"postalcode"
},
  "geometry": {"coordinates":[0.00479263101378,51.20901764100048],"type":"Point"}
}