{
  "type": "Feature",
  "properties": {
    "iso:country":"GB",
    "wof:name":"TS3 9LG",
    "wof:placetype":"postalcode"
},
  "geometry": {"coordinates":[-1.18183588864815,54.56137755886814],"type":"Point"}
}