{
  "type": "Feature",
  "properties": {
    "iso:country": "GB",
    "wof:name": "MK16 0EA",
    "wof:placetype": "postalcode"
  },
  "geometry": {"coordinates":[-0.72692,52.084316],"type":"Point"}
}
