{
  "type": "Feature",
  "properties": {
    "iso:country":"GB",
    "wof:name":"MK16 0EA",
    "wof:placetype":"postalcode"
},
  "geometry": {"coordinates":[-0.72692038956057,52.08431608377582],"type":"Point"}
}