{
  "type": "Feature",
  "properties": {
    "iso:country":"GB",
    "wof:name":"CH5 2NH",
    "wof:placetype":"postalcode"
},
  "geometry": {"coordinates":[-3.05325409613288,53.22798751731975],"type":"Point"}
}