{
  "type": "Feature",
  "properties": {
    "iso:country":"GB",
    "wof:name":"SE1 9HB",
    "wof:placetype":"postalcode"
},
  "geometry": {"coordinates":[-0.09540374741952,51.50667069735982],"type":"Point"}
}