{
  "type": "Feature",
  "properties": {
    "date:inception_lower": "2000-06-01",
    "date:inception_upper": "2000-06-01",
    "iso:country": "GB",
    "wof:name": "SE1 9HB",
    "wof:placetype": "postalcode"
  },
  "geometry": {"coordinates":[-0.095404,51.506671],"type":"Point"}
}
