{
  "type": "Feature",
  "properties": {
    "iso:country": "GB",
    "wof:name": "DN9 1DU",
    "wof:placetype": "postalcode"
  },
  "geometry": {"coordinates":[-0.832413,53.526957],"type":"Point"}
}
