{
  "type": "Feature",
  "properties": {
    "iso:country":"GB",
    "wof:name":"DN9 1DU",
    "wof:placetype":"postalcode"
},
  "geometry": {"coordinates":[-0.83241332086456,53.52695732176358],"type":"Point"}
}