{
  "type": "Feature",
  "properties": {
    "iso:country": "GB",
    "wof:name": "WF13 3RR",
    "wof:placetype": "postalcode"
  },
  "geometry": {"coordinates":[-1.649207,53.682695],"type":"Point"}
}
