{
  "type": "Feature",
  "properties": {
    "date:inception_lower":"1980-01-01",
    "date:inception_upper":"1980-01-31",
    "iso:country":"GB",
    "wof:name":"WF13 3RR",
    "wof:placetype":"postalcode"
},
  "geometry": {"coordinates":[-1.649207,53.682695],"type":"Point"}
}