{
  "type": "Feature",
  "properties": {
    "date:inception_lower":"2006-08-01",
    "date:inception_upper":"2006-08-31",
    "iso:country":"GB",
    "wof:name":"BH21 5HT",
    "wof:placetype":"postalcode"
},
  "geometry": {"coordinates":[-2.027511,50.906891],"type":"Point"}
}