{
  "type": "Feature",
  "properties": {
    "iso:country":"GB",
    "wof:name":"BH21 5HT",
    "wof:placetype":"postalcode"
},
  "geometry": {"coordinates":[-2.02751153903251,50.90689137558517],"type":"Point"}
}