{
  "type": "Feature",
  "properties": {
    "iso:country": "GB",
    "wof:name": "SN10 3AF",
    "wof:placetype": "postalcode"
  },
  "geometry": {"coordinates":[-1.984629,51.350237],"type":"Point"}
}
