{
  "type": "Feature",
  "properties": {
    "iso:country":"GB",
    "wof:name":"SN10 3AF",
    "wof:placetype":"postalcode"
},
  "geometry": {"coordinates":[-1.98462953305342,51.35023714528788],"type":"Point"}
}