{
  "type": "Feature",
  "properties": {
    "date:inception_lower":"2016-05-01",
    "date:inception_upper":"2016-05-31",
    "iso:country":"GB",
    "wof:name":"LA23 3BN",
    "wof:placetype":"postalcode"
},
  "geometry": {"coordinates":[-2.925801,54.352513],"type":"Point"}
}