{
  "type": "Feature",
  "properties": {
    "iso:country":"GB",
    "wof:name":"GU4 7EB",
    "wof:placetype":"postalcode"
},
  "geometry": {"coordinates":[-0.53006334610438,51.2525603389003],"type":"Point"}
}