{
  "type": "Feature",
  "properties": {
    "iso:country": "GB",
    "wof:name": "PR6 7JQ",
    "wof:placetype": "postalcode"
  },
  "geometry": {"coordinates":[-2.635705,53.70266],"type":"Point"}
}
