{
  "type": "Feature",
  "properties": {
    "iso:country":"GB",
    "wof:name":"KT9 1NY",
    "wof:placetype":"postalcode"
},
  "geometry": {"coordinates":[-0.30686106159255,51.3679504077941],"type":"Point"}
}