{
  "type": "Feature",
  "properties": {
    "date:inception_lower": "1980-01-01",
    "date:inception_upper": "1980-01-01",
    "iso:country": "GB",
    "wof:name": "KT9 1NY",
    "wof:placetype": "postalcode"
  },
  "geometry": {"coordinates":[-0.306783,51.367858],"type":"Point"}
}
