{
  "type": "Feature",
  "properties": {
    "iso:country":"GB",
    "wof:name":"HA4 6JY",
    "wof:placetype":"postalcode"
},
  "geometry": {"coordinates":[-0.41592603723874,51.56630776239793],"type":"Point"}
}