{
  "type": "Feature",
  "properties": {
    "iso:country":"GB",
    "wof:name":"AB24 2RQ",
    "wof:placetype":"postalcode"
},
  "geometry": {"coordinates":[-2.1254514910863,57.17184038208107],"type":"Point"}
}