{
  "type": "Feature",
  "properties": {
    "iso:country": "GB",
    "wof:name": "DT3 5DA",
    "wof:placetype": "postalcode"
  },
  "geometry": {"coordinates":[-2.464754,50.629867],"type":"Point"}
}
