{
  "type": "Feature",
  "properties": {
    "date:inception_lower": "2003-02-01",
    "date:inception_upper": "2003-02-01",
    "iso:country": "GB",
    "wof:name": "DT3 5DA",
    "wof:placetype": "postalcode"
  },
  "geometry": {"coordinates":[-2.464754,50.629867],"type":"Point"}
}
