{
  "type": "Feature",
  "properties": {
    "iso:country": "GB",
    "wof:name": "WA10 6SH",
    "wof:placetype": "postalcode"
  },
  "geometry": {"coordinates":[-2.754894,53.460645],"type":"Point"}
}
