{
  "type": "Feature",
  "properties": {
    "iso:country":"GB",
    "wof:name":"SK14 6LY",
    "wof:placetype":"postalcode"
},
  "geometry": {"coordinates":[-2.01181423947904,53.46011819249539],"type":"Point"}
}