{
  "type": "Feature",
  "properties": {
    "iso:country": "GB",
    "wof:name": "SK14 6LY",
    "wof:placetype": "postalcode"
  },
  "geometry": {"coordinates":[-2.011814,53.460118],"type":"Point"}
}
