{
  "type": "Feature",
  "properties": {
    "iso:country":"GB",
    "wof:name":"DD5 1DQ",
    "wof:placetype":"postalcode"
},
  "geometry": {"coordinates":[-2.8784849669695,56.46755243838273],"type":"Point"}
}