{
  "type": "Feature",
  "properties": {
    "iso:country":"GB",
    "wof:name":"SS7 4DT",
    "wof:placetype":"postalcode"
},
  "geometry": {"coordinates":[0.55121360369946,51.57204276376434],"type":"Point"}
}