{
  "type": "Feature",
  "properties": {
    "date:inception_lower": "1980-01-01",
    "date:inception_upper": "1980-01-01",
    "iso:country": "GB",
    "wof:name": "SS7 4DT",
    "wof:placetype": "postalcode"
  },
  "geometry": {"coordinates":[0.551214,51.572043],"type":"Point"}
}
