{
  "type": "Feature",
  "properties": {
    "iso:country":"GB",
    "wof:name":"AB52 6HP",
    "wof:placetype":"postalcode"
},
  "geometry": {"coordinates":[-2.6244471545205,57.34390173183379],"type":"Point"}
}