{
  "type": "Feature",
  "properties": {
    "iso:country": "GB",
    "wof:name": "SO18 3AG",
    "wof:placetype": "postalcode"
  },
  "geometry": {"coordinates":[-1.352724,50.936342],"type":"Point"}
}
