{
  "type": "Feature",
  "properties": {
    "iso:country":"GB",
    "wof:name":"SO18 3AG",
    "wof:placetype":"postalcode"
},
  "geometry": {"coordinates":[-1.35272026294583,50.93635978967553],"type":"Point"}
}