{
  "type": "Feature",
  "properties": {
    "iso:country":"GB",
    "wof:name":"HU7 3HJ",
    "wof:placetype":"postalcode"
},
  "geometry": {"coordinates":[-0.34227987580859,53.80161423940452],"type":"Point"}
}