{
  "type": "Feature",
  "properties": {
    "iso:country":"GB",
    "wof:name":"AB23 8JE",
    "wof:placetype":"postalcode"
},
  "geometry": {"coordinates":[-2.10038381342117,57.20332129694905],"type":"Point"}
}