{
  "type": "Feature",
  "properties": {
    "iso:country": "GB",
    "wof:name": "AB23 8JE",
    "wof:placetype": "postalcode"
  },
  "geometry": {"coordinates":[-2.100291,57.203135],"type":"Point"}
}
