{
  "type": "Feature",
  "properties": {
    "iso:country":"GB",
    "wof:name":"CB8 9XA",
    "wof:placetype":"postalcode"
},
  "geometry": {"coordinates":[0.37565835403707,52.2001644936278],"type":"Point"}
}