{
  "type": "Feature",
  "properties": {
    "iso:country": "GB",
    "wof:name": "CB8 9XA",
    "wof:placetype": "postalcode"
  },
  "geometry": {"coordinates":[0.375658,52.200164],"type":"Point"}
}
