{
  "type": "Feature",
  "properties": {
    "iso:country":"GB",
    "wof:name":"TN10 3HY",
    "wof:placetype":"postalcode"
},
  "geometry": {"coordinates":[0.2764227867093,51.21340950250223],"type":"Point"}
}