{
  "type": "Feature",
  "properties": {
    "iso:country": "GB",
    "wof:name": "CV22 7QA",
    "wof:placetype": "postalcode"
  },
  "geometry": {"coordinates":[-1.283321,52.359868],"type":"Point"}
}
