{
  "type": "Feature",
  "properties": {
    "iso:country":"GB",
    "wof:name":"CV22 7QA",
    "wof:placetype":"postalcode"
},
  "geometry": {"coordinates":[-1.28332097497889,52.35986834636238],"type":"Point"}
}