{
  "type": "Feature",
  "properties": {
    "date:inception_lower": "2015-10-01",
    "date:inception_upper": "2015-10-01",
    "iso:country": "GB",
    "wof:name": "CV21 1FW",
    "wof:placetype": "postalcode"
  },
  "geometry": {"coordinates":[-1.259949,52.383368],"type":"Point"}
}
