{
  "type": "Feature",
  "properties": {
    "date:inception_lower":"1992-01-01",
    "date:inception_upper":"1992-01-31",
    "iso:country":"GB",
    "wof:name":"YO8 8PZ",
    "wof:placetype":"postalcode"
},
  "geometry": {"coordinates":[-1.14949,53.734176],"type":"Point"}
}