{
  "type": "Feature",
  "properties": {
    "iso:country": "GB",
    "wof:name": "YO8 8PZ",
    "wof:placetype": "postalcode"
  },
  "geometry": {"coordinates":[-1.14949,53.734176],"type":"Point"}
}
