{
  "type": "Feature",
  "properties": {
    "iso:country":"GB",
    "wof:name":"YO8 8PZ",
    "wof:placetype":"postalcode"
},
  "geometry": {"coordinates":[-1.14945155378221,53.73435427065336],"type":"Point"}
}