{
  "type": "Feature",
  "properties": {
    "iso:country": "GB",
    "wof:name": "MK45 5EJ",
    "wof:placetype": "postalcode"
  },
  "geometry": {"coordinates":[-0.459006,52.011866],"type":"Point"}
}
