{
  "type": "Feature",
  "properties": {
    "iso:country":"GB",
    "wof:name":"MK45 5EJ",
    "wof:placetype":"postalcode"
},
  "geometry": {"coordinates":[-0.45900565443181,52.01186646891303],"type":"Point"}
}