{
  "type": "Feature",
  "properties": {
    "iso:country":"GB",
    "wof:name":"NR3 3AT",
    "wof:placetype":"postalcode"
},
  "geometry": {"coordinates":[1.29374636311245,52.63176138176233],"type":"Point"}
}