{
  "type": "Feature",
  "properties": {
    "iso:country": "GB",
    "wof:name": "TS10 2DZ",
    "wof:placetype": "postalcode"
  },
  "geometry": {"coordinates":[-1.059066,54.608225],"type":"Point"}
}
