{
  "type": "Feature",
  "properties": {
    "iso:country":"GB",
    "wof:name":"TS10 2DZ",
    "wof:placetype":"postalcode"
},
  "geometry": {"coordinates":[-1.05906637919912,54.60822526407949],"type":"Point"}
}