{
  "type": "Feature",
  "properties": {
    "iso:country":"GB",
    "wof:name":"HP3 0JB",
    "wof:placetype":"postalcode"
},
  "geometry": {"coordinates":[-0.53702612540325,51.71753230030507],"type":"Point"}
}