{
  "type": "Feature",
  "properties": {
    "iso:country": "GB",
    "wof:name": "HP3 0JB",
    "wof:placetype": "postalcode"
  },
  "geometry": {"coordinates":[-0.537026,51.717532],"type":"Point"}
}
