{
  "type": "Feature",
  "properties": {
    "iso:country": "GB",
    "wof:name": "MK43 8DX",
    "wof:placetype": "postalcode"
  },
  "geometry": {"coordinates":[-0.621352,52.16404],"type":"Point"}
}
