{
  "type": "Feature",
  "properties": {
    "iso:country":"GB",
    "wof:name":"BH24 3EL",
    "wof:placetype":"postalcode"
},
  "geometry": {"coordinates":[-1.76366201614767,50.84718899877338],"type":"Point"}
}