{
  "type": "Feature",
  "properties": {
    "iso:country": "GB",
    "wof:name": "BH24 3EL",
    "wof:placetype": "postalcode"
  },
  "geometry": {"coordinates":[-1.763662,50.847189],"type":"Point"}
}
