{
  "type": "Feature",
  "properties": {
    "date:inception_lower":"2000-06-01",
    "date:inception_upper":"2000-06-30",
    "iso:country":"GB",
    "wof:name":"M26 4TS",
    "wof:placetype":"postalcode"
},
  "geometry": {"coordinates":[-2.327587,53.564079],"type":"Point"}
}