{
  "type": "Feature",
  "properties": {
    "iso:country":"GB",
    "wof:name":"M26 4TS",
    "wof:placetype":"postalcode"
},
  "geometry": {"coordinates":[-2.32764709908085,53.56409645653023],"type":"Point"}
}