{
  "type": "Feature",
  "properties": {
    "date:inception_lower": "1980-01-01",
    "date:inception_upper": "1980-01-01",
    "iso:country": "GB",
    "wof:name": "RH20 4LR",
    "wof:placetype": "postalcode"
  },
  "geometry": {"coordinates":[-0.460942,50.917817],"type":"Point"}
}
