{
  "type": "Feature",
  "properties": {
    "date:inception_lower": "2018-04-01",
    "date:inception_upper": "2018-04-01",
    "iso:country": "GB",
    "wof:name": "OX16 1GF",
    "wof:placetype": "postalcode"
  },
  "geometry": {"coordinates":[-1.360085,52.081057],"type":"Point"}
}
