{
  "type": "Feature",
  "properties": {
    "iso:country":"GB",
    "wof:name":"CM6 3FD",
    "wof:placetype":"postalcode"
},
  "geometry": {"coordinates":[0.41252470690386,51.86063878652705],"type":"Point"}
}