{
  "type": "Feature",
  "properties": {
    "iso:country": "GB",
    "wof:name": "GU14 9EJ",
    "wof:placetype": "postalcode"
  },
  "geometry": {"coordinates":[-0.778331,51.314961],"type":"Point"}
}
