{
  "type": "Feature",
  "properties": {
    "iso:country":"GB",
    "wof:name":"GU14 9EJ",
    "wof:placetype":"postalcode"
},
  "geometry": {"coordinates":[-0.77833086988172,51.31496093639596],"type":"Point"}
}