{
  "type": "Feature",
  "properties": {
    "date:inception_lower":"1980-01-01",
    "date:inception_upper":"1980-01-31",
    "iso:country":"GB",
    "wof:name":"GU14 9EJ",
    "wof:placetype":"postalcode"
},
  "geometry": {"coordinates":[-0.778331,51.314961],"type":"Point"}
}