{
  "type": "Feature",
  "properties": {
    "iso:country":"GB",
    "wof:name":"EN2 6PG",
    "wof:placetype":"postalcode"
},
  "geometry": {"coordinates":[-0.0854293572099,51.6526810467858],"type":"Point"}
}