{
  "type": "Feature",
  "properties": {
    "iso:country":"GB",
    "wof:name":"YO42 1TQ",
    "wof:placetype":"postalcode"
},
  "geometry": {"coordinates":[-0.65603168198748,53.98592290069635],"type":"Point"}
}