{
  "type": "Feature",
  "properties": {
    "iso:country":"GB",
    "wof:name":"BA2 8QF",
    "wof:placetype":"postalcode"
},
  "geometry": {"coordinates":[-2.36595102389157,51.32315805262753],"type":"Point"}
}