{
  "type": "Feature",
  "properties": {
    "iso:country": "GB",
    "wof:name": "BA2 8QF",
    "wof:placetype": "postalcode"
  },
  "geometry": {"coordinates":[-2.365951,51.323158],"type":"Point"}
}
