{
  "type": "Feature",
  "properties": {
    "iso:country":"GB",
    "wof:name":"PR3 2EU",
    "wof:placetype":"postalcode"
},
  "geometry": {"coordinates":[-2.67146546218682,53.8896253768485],"type":"Point"}
}