{
  "type": "Feature",
  "properties": {
    "iso:country": "GB",
    "wof:name": "PR3 2EU",
    "wof:placetype": "postalcode"
  },
  "geometry": {"coordinates":[-2.671465,53.889625],"type":"Point"}
}
