{
  "type": "Feature",
  "properties": {
    "iso:country": "GB",
    "wof:name": "WF5 0BD",
    "wof:placetype": "postalcode"
  },
  "geometry": {"coordinates":[-1.571109,53.671152],"type":"Point"}
}
