{
  "type": "Feature",
  "properties": {
    "iso:country":"GB",
    "wof:name":"WF5 0BD",
    "wof:placetype":"postalcode"
},
  "geometry": {"coordinates":[-1.57110881598881,53.67115222523336],"type":"Point"}
}