{
  "type": "Feature",
  "properties": {
    "iso:country":"GB",
    "wof:name":"DD8 2LP",
    "wof:placetype":"postalcode"
},
  "geometry": {"coordinates":[-2.84383548158018,56.60875606367378],"type":"Point"}
}