{
  "type": "Feature",
  "properties": {
    "iso:country": "GB",
    "wof:name": "WS11 4AJ",
    "wof:placetype": "postalcode"
  },
  "geometry": {"coordinates":[-2.035247,52.695892],"type":"Point"}
}
