{
  "type": "Feature",
  "properties": {
    "iso:country":"GB",
    "wof:name":"WS11 4AJ",
    "wof:placetype":"postalcode"
},
  "geometry": {"coordinates":[-2.03524726321943,52.69589175620622],"type":"Point"}
}