{
  "type": "Feature",
  "properties": {
    "iso:country":"GB",
    "wof:name":"AL1 5EG",
    "wof:placetype":"postalcode"
},
  "geometry": {"coordinates":[-0.32129049282245,51.7501845780719],"type":"Point"}
}