{
  "type": "Feature",
  "properties": {
    "iso:country": "GB",
    "wof:name": "AL1 5EG",
    "wof:placetype": "postalcode"
  },
  "geometry": {"coordinates":[-0.32129,51.750185],"type":"Point"}
}
