{
  "type": "Feature",
  "properties": {
    "iso:country":"GB",
    "wof:name":"WF10 4RA",
    "wof:placetype":"postalcode"
},
  "geometry": {"coordinates":[-1.33279027333937,53.71597436942137],"type":"Point"}
}