{
  "type": "Feature",
  "properties": {
    "iso:country": "GB",
    "wof:name": "WF10 4RA",
    "wof:placetype": "postalcode"
  },
  "geometry": {"coordinates":[-1.33279,53.715974],"type":"Point"}
}
