{
  "type": "Feature",
  "properties": {
    "iso:country":"GB",
    "wof:name":"B75 6JL",
    "wof:placetype":"postalcode"
},
  "geometry": {"coordinates":[-1.80214185096065,52.58092457937682],"type":"Point"}
}