{
  "type": "Feature",
  "properties": {
    "iso:country":"GB",
    "wof:name":"DY2 8AS",
    "wof:placetype":"postalcode"
},
  "geometry": {"coordinates":[-2.07275790846054,52.50125487293041],"type":"Point"}
}