{
  "type": "Feature",
  "properties": {
    "iso:country": "GB",
    "wof:name": "DY2 8AS",
    "wof:placetype": "postalcode"
  },
  "geometry": {"coordinates":[-2.072758,52.501255],"type":"Point"}
}
