{
  "type": "Feature",
  "properties": {
    "iso:country":"GB",
    "wof:name":"SR6 8PB",
    "wof:placetype":"postalcode"
},
  "geometry": {"coordinates":[-1.38916860838743,54.93404858149292],"type":"Point"}
}