{
  "type": "Feature",
  "properties": {
    "iso:country": "GB",
    "wof:name": "ST4 3LA",
    "wof:placetype": "postalcode"
  },
  "geometry": {"coordinates":[-2.152579,52.998795],"type":"Point"}
}
