{
  "type": "Feature",
  "properties": {
    "date:inception_lower": "1980-01-01",
    "date:inception_upper": "1980-01-01",
    "iso:country": "GB",
    "wof:name": "ST4 3LA",
    "wof:placetype": "postalcode"
  },
  "geometry": {"coordinates":[-2.152518,52.998687],"type":"Point"}
}
