{
  "type": "Feature",
  "properties": {
    "iso:country":"GB",
    "wof:name":"ST4 3LA",
    "wof:placetype":"postalcode"
},
  "geometry": {"coordinates":[-2.1525792978333,52.99879546182324],"type":"Point"}
}