{
  "type": "Feature",
  "properties": {
    "iso:country": "GB",
    "wof:name": "GU6 7FZ",
    "wof:placetype": "postalcode"
  },
  "geometry": {"coordinates":[-0.481409,51.150994],"type":"Point"}
}
