{
  "type": "Feature",
  "properties": {
    "date:inception_lower": "2018-06-01",
    "date:inception_upper": "2018-06-01",
    "iso:country": "GB",
    "wof:name": "GU6 7FZ",
    "wof:placetype": "postalcode"
  },
  "geometry": {"coordinates":[-0.481573,51.150798],"type":"Point"}
}
