{
  "type": "Feature",
  "properties": {
    "date:inception_lower": "2017-01-01",
    "date:inception_upper": "2017-01-01",
    "iso:country": "GB",
    "wof:name": "LE10 9TD",
    "wof:placetype": "postalcode"
  },
  "geometry": {"coordinates":[-1.369595,52.540369],"type":"Point"}
}
