{
  "type": "Feature",
  "properties": {
    "date:inception_lower": "2020-04-01",
    "date:inception_upper": "2020-04-01",
    "iso:country": "GB",
    "wof:name": "IP28 8HQ",
    "wof:placetype": "postalcode"
  },
  "geometry": {"coordinates":[0.495744,52.365743],"type":"Point"}
}
