{
  "type": "Feature",
  "properties": {
    "iso:country": "GB",
    "wof:name": "IP28 8HQ",
    "wof:placetype": "postalcode"
  },
  "geometry": {"coordinates":[0.478244,52.370131],"type":"Point"}
}
