{
  "type": "Feature",
  "properties": {
    "iso:country": "GB",
    "wof:name": "BD8 9RA",
    "wof:placetype": "postalcode"
  },
  "geometry": {"coordinates":[-1.79223,53.7988],"type":"Point"}
}
