{
  "type": "Feature",
  "properties": {
    "iso:country":"GB",
    "wof:name":"LA7 7QW",
    "wof:placetype":"postalcode"
},
  "geometry": {"coordinates":[-2.77178422468045,54.22267697468617],"type":"Point"}
}