{
  "type": "Feature",
  "properties": {
    "date:inception_lower": "1980-01-01",
    "date:inception_upper": "1980-01-01",
    "iso:country": "GB",
    "wof:name": "CM16 5HW",
    "wof:placetype": "postalcode"
  },
  "geometry": {"coordinates":[0.063931,51.676454],"type":"Point"}
}
