{
  "type": "Feature",
  "properties": {
    "iso:country":"GB",
    "wof:name":"CM16 5HW",
    "wof:placetype":"postalcode"
},
  "geometry": {"coordinates":[0.06393116729793,51.67645379955825],"type":"Point"}
}