{
  "type": "Feature",
  "properties": {
    "date:inception_lower": "1980-01-01",
    "date:inception_upper": "1980-01-01",
    "iso:country": "GB",
    "wof:name": "LA1 2RJ",
    "wof:placetype": "postalcode"
  },
  "geometry": {"coordinates":[-2.813142,54.059998],"type":"Point"}
}
