{
  "type": "Feature",
  "properties": {
    "iso:country":"GB",
    "wof:name":"LA1 2RJ",
    "wof:placetype":"postalcode"
},
  "geometry": {"coordinates":[-2.81314541370842,54.05998778315745],"type":"Point"}
}