{
  "type": "Feature",
  "properties": {
    "iso:country":"GB",
    "wof:name":"NN11 4PP",
    "wof:placetype":"postalcode"
},
  "geometry": {"coordinates":[-1.18065954577203,52.25190929592106],"type":"Point"}
}