{
  "type": "Feature",
  "properties": {
    "date:inception_lower": "2020-11-01",
    "date:inception_upper": "2020-11-01",
    "iso:country": "GB",
    "wof:name": "SA67 8UX",
    "wof:placetype": "postalcode"
  },
  "geometry": {"coordinates":[-4.737938,51.767057],"type":"Point"}
}
