{
  "type": "Feature",
  "properties": {
    "iso:country":"GB",
    "wof:name":"SE7 8ND",
    "wof:placetype":"postalcode"
},
  "geometry": {"coordinates":[0.03494307906591,51.4925929743149],"type":"Point"}
}