{
  "type": "Feature",
  "properties": {
    "date:inception_lower": "1980-01-01",
    "date:inception_upper": "1980-01-01",
    "iso:country": "GB",
    "wof:name": "SE18 5PD",
    "wof:placetype": "postalcode"
  },
  "geometry": {"coordinates":[0.048515,51.491404],"type":"Point"}
}
