{
  "type": "Feature",
  "properties": {
    "iso:country":"GB",
    "wof:name":"EX39 5JZ",
    "wof:placetype":"postalcode"
},
  "geometry": {"coordinates":[-4.18907442288837,50.97420347201607],"type":"Point"}
}