{
  "type": "Feature",
  "properties": {
    "iso:country":"GB",
    "wof:name":"YO8 6EQ",
    "wof:placetype":"postalcode"
},
  "geometry": {"coordinates":[-0.9751792536496,53.80784667448778],"type":"Point"}
}