{
  "type": "Feature",
  "properties": {
    "iso:country": "GB",
    "wof:name": "YO8 6EQ",
    "wof:placetype": "postalcode"
  },
  "geometry": {"coordinates":[-0.975179,53.807847],"type":"Point"}
}
