{
  "type": "Feature",
  "properties": {
    "iso:country":"GB",
    "wof:name":"S71 2FN",
    "wof:placetype":"postalcode"
},
  "geometry": {"coordinates":[-1.46129144480387,53.57163936640654],"type":"Point"}
}