{
  "type": "Feature",
  "properties": {
    "date:inception_lower":"2011-09-01",
    "date:inception_upper":"2011-09-30",
    "iso:country":"GB",
    "wof:name":"S71 2FN",
    "wof:placetype":"postalcode"
},
  "geometry": {"coordinates":[-1.461291,53.571639],"type":"Point"}
}