{
  "type": "Feature",
  "properties": {
    "date:inception_lower": "2020-10-01",
    "date:inception_upper": "2020-10-01",
    "iso:country": "GB",
    "wof:name": "LE7 9HX",
    "wof:placetype": "postalcode"
  },
  "geometry": {"coordinates":[-0.997468,52.629144],"type":"Point"}
}
