{
  "type": "Feature",
  "properties": {
    "iso:country": "GB",
    "wof:name": "LS20 9NG",
    "wof:placetype": "postalcode"
  },
  "geometry": {"coordinates":[-1.699786,53.876974],"type":"Point"}
}
