{
  "type": "Feature",
  "properties": {
    "iso:country":"GB",
    "wof:name":"UB6 8LF",
    "wof:placetype":"postalcode"
},
  "geometry": {"coordinates":[-0.33235942513584,51.53822719984443],"type":"Point"}
}