{
  "type": "Feature",
  "properties": {
    "iso:country": "GB",
    "wof:name": "EH11 3AY",
    "wof:placetype": "postalcode"
  },
  "geometry": {"coordinates":[-3.250961,55.93707],"type":"Point"}
}
