{
  "type": "Feature",
  "properties": {
    "iso:country":"GB",
    "wof:name":"AB21 0XY",
    "wof:placetype":"postalcode"
},
  "geometry": {"coordinates":[-2.2623997635843,57.23748264284128],"type":"Point"}
}