{
  "type": "Feature",
  "properties": {
    "iso:country":"GB",
    "wof:name":"L14 5PA",
    "wof:placetype":"postalcode"
},
  "geometry": {"coordinates":[-2.89207387653512,53.40741111289463],"type":"Point"}
}