{
  "type": "Feature",
  "properties": {
    "date:inception_lower": "2007-11-01",
    "date:inception_upper": "2007-11-01",
    "iso:country": "GB",
    "wof:name": "E1W 3DD",
    "wof:placetype": "postalcode"
  },
  "geometry": {"coordinates":[-0.058501,51.509357],"type":"Point"}
}
