{
  "type": "Feature",
  "properties": {
    "iso:country":"GB",
    "wof:name":"E1W 3DD",
    "wof:placetype":"postalcode"
},
  "geometry": {"coordinates":[-0.05850062709822,51.50935688173169],"type":"Point"}
}