{
  "type": "Feature",
  "properties": {
    "iso:country":"GB",
    "wof:name":"IP17 2DP",
    "wof:placetype":"postalcode"
},
  "geometry": {"coordinates":[1.42041414812067,52.21671325025225],"type":"Point"}
}