{
  "type": "Feature",
  "properties": {
    "date:inception_lower": "1980-01-01",
    "date:inception_upper": "1980-01-01",
    "iso:country": "GB",
    "wof:name": "IP17 2DP",
    "wof:placetype": "postalcode"
  },
  "geometry": {"coordinates":[1.420414,52.216713],"type":"Point"}
}
