{
  "type": "Feature",
  "properties": {
    "iso:country":"GB",
    "wof:name":"S45 9DP",
    "wof:placetype":"postalcode"
},
  "geometry": {"coordinates":[-1.41533296378018,53.17132612028464],"type":"Point"}
}