{
  "type": "Feature",
  "properties": {
    "date:inception_lower": "1980-01-01",
    "date:inception_upper": "1980-01-01",
    "iso:country": "GB",
    "wof:name": "S10 5TY",
    "wof:placetype": "postalcode"
  },
  "geometry": {"coordinates":[-1.535971,53.377638],"type":"Point"}
}
