{
  "type": "Feature",
  "properties": {
    "iso:country":"GB",
    "wof:name":"S10 5TY",
    "wof:placetype":"postalcode"
},
  "geometry": {"coordinates":[-1.53597056718355,53.37763815228912],"type":"Point"}
}