{
  "type": "Feature",
  "properties": {
    "iso:country": "GB",
    "wof:name": "KT15 1AS",
    "wof:placetype": "postalcode"
  },
  "geometry": {"coordinates":[-0.513937,51.365553],"type":"Point"}
}
