{
  "type": "Feature",
  "properties": {
    "iso:country":"GB",
    "wof:name":"SA34 0QP",
    "wof:placetype":"postalcode"
},
  "geometry": {"coordinates":[-4.61529008451151,51.81451898181896],"type":"Point"}
}