{
  "type": "Feature",
  "properties": {
    "iso:country":"GB",
    "wof:name":"NW5 2HP",
    "wof:placetype":"postalcode"
},
  "geometry": {"coordinates":[-0.13873716101592,51.55609667348131],"type":"Point"}
}