{
  "type": "Feature",
  "properties": {
    "iso:country": "GB",
    "wof:name": "NW5 2HP",
    "wof:placetype": "postalcode"
  },
  "geometry": {"coordinates":[-0.138692,51.55615],"type":"Point"}
}
