{
  "type": "Feature",
  "properties": {
    "iso:country":"GB",
    "wof:name":"TR18 2SX",
    "wof:placetype":"postalcode"
},
  "geometry": {"coordinates":[-5.53825653929992,50.12010415470529],"type":"Point"}
}