{
  "type": "Feature",
  "properties": {
    "iso:country":"GB",
    "wof:name":"N21 1DD",
    "wof:placetype":"postalcode"
},
  "geometry": {"coordinates":[-0.09946156777271,51.64588596654766],"type":"Point"}
}