{
  "type": "Feature",
  "properties": {
    "iso:country": "GB",
    "wof:name": "LA2 7DS",
    "wof:placetype": "postalcode"
  },
  "geometry": {"coordinates":[-2.537087,54.119439],"type":"Point"}
}
