{
  "type": "Feature",
  "properties": {
    "iso:country":"GB",
    "wof:name":"BS13 8JU",
    "wof:placetype":"postalcode"
},
  "geometry": {"coordinates":[-2.61865209662767,51.41462979657247],"type":"Point"}
}