{
  "type": "Feature",
  "properties": {
    "date:inception_lower": "2009-07-01",
    "date:inception_upper": "2009-07-01",
    "iso:country": "GB",
    "wof:name": "L39 4AA",
    "wof:placetype": "postalcode"
  },
  "geometry": {"coordinates":[-2.872463,53.558189],"type":"Point"}
}
