{
  "type": "Feature",
  "properties": {
    "iso:country": "GB",
    "wof:name": "L39 4AA",
    "wof:placetype": "postalcode"
  },
  "geometry": {"coordinates":[-2.872463,53.558189],"type":"Point"}
}
