{
  "type": "Feature",
  "properties": {
    "iso:country":"GB",
    "wof:name":"L39 4AA",
    "wof:placetype":"postalcode"
},
  "geometry": {"coordinates":[-2.87246332958924,53.55818926193905],"type":"Point"}
}