{
  "type": "Feature",
  "properties": {
    "date:inception_lower": "1980-01-01",
    "date:inception_upper": "1980-01-01",
    "iso:country": "GB",
    "wof:name": "DN7 5BQ",
    "wof:placetype": "postalcode"
  },
  "geometry": {"coordinates":[-1.02423,53.600244],"type":"Point"}
}
