{
  "type": "Feature",
  "properties": {
    "iso:country":"GB",
    "wof:name":"DN7 5BQ",
    "wof:placetype":"postalcode"
},
  "geometry": {"coordinates":[-1.02422964148145,53.60024413454465],"type":"Point"}
}