{
  "type": "Feature",
  "properties": {
    "date:inception_lower": "2001-06-01",
    "date:inception_upper": "2001-06-01",
    "iso:country": "GB",
    "wof:name": "LS27 7WE",
    "wof:placetype": "postalcode"
  },
  "geometry": {"coordinates":[-1.638182,53.764248],"type":"Point"}
}
