{
  "type": "Feature",
  "properties": {
    "date:inception_lower": "1999-06-01",
    "date:inception_upper": "1999-06-01",
    "iso:country": "GB",
    "wof:name": "CH63 8PA",
    "wof:placetype": "postalcode"
  },
  "geometry": {"coordinates":[-3.0157,53.362054],"type":"Point"}
}
