{
  "type": "Feature",
  "properties": {
    "iso:country":"GB",
    "wof:name":"CH63 8PA",
    "wof:placetype":"postalcode"
},
  "geometry": {"coordinates":[-3.01569963760081,53.36205365619684],"type":"Point"}
}