{
  "type": "Feature",
  "properties": {
    "iso:country":"GB",
    "wof:name":"SN3 3TP",
    "wof:placetype":"postalcode"
},
  "geometry": {"coordinates":[-1.73644974808533,51.55972424402565],"type":"Point"}
}