{
  "type": "Feature",
  "properties": {
    "date:inception_lower": "2020-08-01",
    "date:inception_upper": "2020-08-01",
    "iso:country": "GB",
    "wof:name": "GL7 7FD",
    "wof:placetype": "postalcode"
  },
  "geometry": {"coordinates":[-1.97247,51.765669],"type":"Point"}
}
