{
  "type": "Feature",
  "properties": {
    "iso:country":"GB",
    "wof:name":"EH18 1BW",
    "wof:placetype":"postalcode"
},
  "geometry": {"coordinates":[-3.12285648546111,55.87442676590503],"type":"Point"}
}