{
  "type": "Feature",
  "properties": {
    "iso:country": "GB",
    "wof:name": "EH16 6AA",
    "wof:placetype": "postalcode"
  },
  "geometry": {"coordinates":[-3.167778,55.919979],"type":"Point"}
}
