{
  "type": "Feature",
  "properties": {
    "iso:country":"GB",
    "wof:name":"KT1 2JD",
    "wof:placetype":"postalcode"
},
  "geometry": {"coordinates":[-0.30563635932014,51.40267974670191],"type":"Point"}
}