{
  "type": "Feature",
  "properties": {
    "iso:country": "GB",
    "wof:name": "BH3 7LA",
    "wof:placetype": "postalcode"
  },
  "geometry": {"coordinates":[-1.867921,50.736106],"type":"Point"}
}
