{
  "type": "Feature",
  "properties": {
    "date:inception_lower": "2014-05-01",
    "date:inception_upper": "2014-05-01",
    "iso:country": "GB",
    "wof:name": "NE31 1TL",
    "wof:placetype": "postalcode"
  },
  "geometry": {"coordinates":[-1.529017,54.972942],"type":"Point"}
}
