{
  "type": "Feature",
  "properties": {
    "iso:country":"GB",
    "wof:name":"NE31 1TL",
    "wof:placetype":"postalcode"
},
  "geometry": {"coordinates":[-1.52909918072064,54.97285372896945],"type":"Point"}
}