{
  "type": "Feature",
  "properties": {
    "iso:country": "GB",
    "wof:name": "B38 0BD",
    "wof:placetype": "postalcode"
  },
  "geometry": {"coordinates":[-1.913788,52.405656],"type":"Point"}
}
