{
  "type": "Feature",
  "properties": {
    "date:inception_lower": "1981-09-01",
    "date:inception_upper": "1981-09-01",
    "iso:country": "GB",
    "wof:name": "B38 0BD",
    "wof:placetype": "postalcode"
  },
  "geometry": {"coordinates":[-1.913788,52.405656],"type":"Point"}
}
