{
  "type": "Feature",
  "properties": {
    "iso:country":"GB",
    "wof:name":"B38 0BD",
    "wof:placetype":"postalcode"
},
  "geometry": {"coordinates":[-1.91378833636838,52.40565551030198],"type":"Point"}
}