{
  "type": "Feature",
  "properties": {
    "date:inception_lower": "1980-01-01",
    "date:inception_upper": "1980-01-01",
    "iso:country": "GB",
    "wof:name": "TR8 4AF",
    "wof:placetype": "postalcode"
  },
  "geometry": {"coordinates":[-5.007284,50.450534],"type":"Point"}
}
