{
  "type": "Feature",
  "properties": {
    "date:inception_lower": "2007-04-01",
    "date:inception_upper": "2007-04-01",
    "iso:country": "GB",
    "wof:name": "PE11 4US",
    "wof:placetype": "postalcode"
  },
  "geometry": {"coordinates":[-0.206627,52.903694],"type":"Point"}
}
