{
  "type": "Feature",
  "properties": {
    "iso:country": "GB",
    "wof:name": "PE11 4US",
    "wof:placetype": "postalcode"
  },
  "geometry": {"coordinates":[-0.206627,52.903694],"type":"Point"}
}
