{
  "type": "Feature",
  "properties": {
    "iso:country":"GB",
    "wof:name":"PE11 4US",
    "wof:placetype":"postalcode"
},
  "geometry": {"coordinates":[-0.20662668729889,52.90369362061337],"type":"Point"}
}