{
  "type": "Feature",
  "properties": {
    "date:inception_lower": "1980-01-01",
    "date:inception_upper": "1980-01-01",
    "iso:country": "GB",
    "wof:name": "E11 2DD",
    "wof:placetype": "postalcode"
  },
  "geometry": {"coordinates":[0.032886,51.584228],"type":"Point"}
}
