{
  "type": "Feature",
  "properties": {
    "iso:country": "GB",
    "wof:name": "E11 2DD",
    "wof:placetype": "postalcode"
  },
  "geometry": {"coordinates":[0.032886,51.584228],"type":"Point"}
}
