{
  "type": "Feature",
  "properties": {
    "iso:country":"GB",
    "wof:name":"E11 2DD",
    "wof:placetype":"postalcode"
},
  "geometry": {"coordinates":[0.03288562776603,51.58422810534096],"type":"Point"}
}