{
  "type": "Feature",
  "properties": {
    "iso:country":"GB",
    "wof:name":"CR8 1BF",
    "wof:placetype":"postalcode"
},
  "geometry": {"coordinates":[-0.10795584468736,51.33285665763476],"type":"Point"}
}