{
  "type": "Feature",
  "properties": {
    "iso:country": "GB",
    "wof:name": "WV6 7RE",
    "wof:placetype": "postalcode"
  },
  "geometry": {"coordinates":[-2.211295,52.600354],"type":"Point"}
}
