{
  "type": "Feature",
  "properties": {
    "iso:country":"GB",
    "wof:name":"WV6 7RE",
    "wof:placetype":"postalcode"
},
  "geometry": {"coordinates":[-2.21129484171515,52.60035439399683],"type":"Point"}
}