{
  "type": "Feature",
  "properties": {
    "iso:country":"GB",
    "wof:name":"TW7 5PY",
    "wof:placetype":"postalcode"
},
  "geometry": {"coordinates":[-0.33310397081223,51.4862533007686],"type":"Point"}
}