{
  "type": "Feature",
  "properties": {
    "iso:country": "GB",
    "wof:name": "TW7 5PY",
    "wof:placetype": "postalcode"
  },
  "geometry": {"coordinates":[-0.333104,51.486253],"type":"Point"}
}
