{
  "type": "Feature",
  "properties": {
    "iso:country": "GB",
    "wof:name": "LL65 4TY",
    "wof:placetype": "postalcode"
  },
  "geometry": {"coordinates":[-4.439437,53.3013],"type":"Point"}
}
