{
  "type": "Feature",
  "properties": {
    "iso:country":"GB",
    "wof:name":"LL65 4TY",
    "wof:placetype":"postalcode"
},
  "geometry": {"coordinates":[-4.43943694460422,53.30129964419106],"type":"Point"}
}