{
  "type": "Feature",
  "properties": {
    "date:inception_lower": "2022-02-01",
    "date:inception_upper": "2022-02-01",
    "iso:country": "GB",
    "wof:name": "FY6 7YH",
    "wof:placetype": "postalcode"
  },
  "geometry": {"coordinates":[-2.972301,53.849047],"type":"Point"}
}
