{
  "type": "Feature",
  "properties": {
    "date:inception_lower":"2000-12-01",
    "date:inception_upper":"2000-12-31",
    "iso:country":"GB",
    "wof:name":"DY5 2BJ",
    "wof:placetype":"postalcode"
},
  "geometry": {"coordinates":[-2.125171,52.467216],"type":"Point"}
}