{
  "type": "Feature",
  "properties": {
    "iso:country":"GB",
    "wof:name":"DY5 2BJ",
    "wof:placetype":"postalcode"
},
  "geometry": {"coordinates":[-2.12497190368165,52.4672830381275],"type":"Point"}
}