{
  "type": "Feature",
  "properties": {
    "iso:country": "GB",
    "wof:name": "SS6 8FE",
    "wof:placetype": "postalcode"
  },
  "geometry": {"coordinates":[0.614753,51.593064],"type":"Point"}
}
