{
  "type": "Feature",
  "properties": {
    "iso:country":"GB",
    "wof:name":"SS6 8FE",
    "wof:placetype":"postalcode"
},
  "geometry": {"coordinates":[0.61475336715152,51.59306432225659],"type":"Point"}
}