{
  "type": "Feature",
  "properties": {
    "date:inception_lower": "2011-05-01",
    "date:inception_upper": "2011-05-01",
    "iso:country": "GB",
    "wof:name": "SS6 8FE",
    "wof:placetype": "postalcode"
  },
  "geometry": {"coordinates":[0.614753,51.593064],"type":"Point"}
}
