{
  "type": "Feature",
  "properties": {
    "iso:country":"GB",
    "wof:name":"RM8 2DZ",
    "wof:placetype":"postalcode"
},
  "geometry": {"coordinates":[0.12127522949559,51.54557740210661],"type":"Point"}
}