{
  "type": "Feature",
  "properties": {
    "iso:country": "GB",
    "wof:name": "RM8 2DZ",
    "wof:placetype": "postalcode"
  },
  "geometry": {"coordinates":[0.121275,51.545577],"type":"Point"}
}
