{
  "type": "Feature",
  "properties": {
    "iso:country":"GB",
    "wof:name":"BB5 2JF",
    "wof:placetype":"postalcode"
},
  "geometry": {"coordinates":[-2.36385135866274,53.74663245529921],"type":"Point"}
}