{
  "type": "Feature",
  "properties": {
    "iso:country":"GB",
    "wof:name":"WR10 1AS",
    "wof:placetype":"postalcode"
},
  "geometry": {"coordinates":[-2.07358663270352,52.10684401390893],"type":"Point"}
}