{
  "type": "Feature",
  "properties": {
    "iso:country": "GB",
    "wof:name": "WR10 1AS",
    "wof:placetype": "postalcode"
  },
  "geometry": {"coordinates":[-2.073587,52.106844],"type":"Point"}
}
