{
  "type": "Feature",
  "properties": {
    "iso:country":"GB",
    "wof:name":"SO50 8JP",
    "wof:placetype":"postalcode"
},
  "geometry": {"coordinates":[-1.31250857405884,50.96584111506705],"type":"Point"}
}