{
  "type": "Feature",
  "properties": {
    "iso:country":"GB",
    "wof:name":"AB51 4FT",
    "wof:placetype":"postalcode"
},
  "geometry": {"coordinates":[-2.39412580201113,57.28591557175655],"type":"Point"}
}