{
  "type": "Feature",
  "properties": {
    "iso:country":"GB",
    "wof:name":"TN39 4JB",
    "wof:placetype":"postalcode"
},
  "geometry": {"coordinates":[0.45433766841873,50.84657480927437],"type":"Point"}
}