{
  "type": "Feature",
  "properties": {
    "iso:country":"GB",
    "wof:name":"NE47 0BB",
    "wof:placetype":"postalcode"
},
  "geometry": {"coordinates":[-2.03057545754582,54.91561939634219],"type":"Point"}
}