{
  "type": "Feature",
  "properties": {
    "date:inception_lower": "1992-01-01",
    "date:inception_upper": "1992-01-01",
    "iso:country": "GB",
    "wof:name": "NE47 0BB",
    "wof:placetype": "postalcode"
  },
  "geometry": {"coordinates":[-2.030575,54.915619],"type":"Point"}
}
