{
  "type": "Feature",
  "properties": {
    "iso:country":"GB",
    "wof:name":"N1 5QE",
    "wof:placetype":"postalcode"
},
  "geometry": {"coordinates":[-0.08177992097793,51.53632195407106],"type":"Point"}
}