{
  "type": "Feature",
  "properties": {
    "iso:country": "GB",
    "wof:name": "CF23 8NU",
    "wof:placetype": "postalcode"
  },
  "geometry": {"coordinates":[-3.130705,51.534257],"type":"Point"}
}
