{
  "type": "Feature",
  "properties": {
    "iso:country": "GB",
    "wof:name": "AB10 6AS",
    "wof:placetype": "postalcode"
  },
  "geometry": {"coordinates":[-2.115688,57.132702],"type":"Point"}
}
