{
  "type": "Feature",
  "properties": {
    "iso:country":"GB",
    "wof:name":"AB10 6AS",
    "wof:placetype":"postalcode"
},
  "geometry": {"coordinates":[-2.11568774602561,57.13270182686323],"type":"Point"}
}