{
  "type": "Feature",
  "properties": {
    "iso:country":"GB",
    "wof:name":"SO24 9PN",
    "wof:placetype":"postalcode"
},
  "geometry": {"coordinates":[-1.16897662063372,51.07998416306037],"type":"Point"}
}