{
  "type": "Feature",
  "properties": {
    "iso:country":"GB",
    "wof:name":"AB42 1RP",
    "wof:placetype":"postalcode"
},
  "geometry": {"coordinates":[-1.79984048098341,57.50973821329232],"type":"Point"}
}