{
  "type": "Feature",
  "properties": {
    "iso:country":"GB",
    "wof:name":"TN2 5JL",
    "wof:placetype":"postalcode"
},
  "geometry": {"coordinates":[0.27148580469196,51.11769787757605],"type":"Point"}
}