{
  "type": "Feature",
  "properties": {
    "iso:country": "GB",
    "wof:name": "YO16 6ZF",
    "wof:placetype": "postalcode"
  },
  "geometry": {"coordinates":[-0.17326,54.108951],"type":"Point"}
}
