{
  "type": "Feature",
  "properties": {
    "date:inception_lower":"1998-06-01",
    "date:inception_upper":"1998-06-30",
    "iso:country":"GB",
    "wof:name":"YO16 6ZF",
    "wof:placetype":"postalcode"
},
  "geometry": {"coordinates":[-0.17326,54.108951],"type":"Point"}
}