{
  "type": "Feature",
  "properties": {
    "iso:country":"GB",
    "wof:name":"YO16 6ZF",
    "wof:placetype":"postalcode"
},
  "geometry": {"coordinates":[-0.17326023275334,54.10895074399871],"type":"Point"}
}