{
  "type": "Feature",
  "properties": {
    "iso:country":"GB",
    "wof:name":"W2 2TT",
    "wof:placetype":"postalcode"
},
  "geometry": {"coordinates":[-0.1720943530278,51.51349334505419],"type":"Point"}
}