{
  "type": "Feature",
  "properties": {
    "iso:country": "GB",
    "wof:name": "FY2 9AX",
    "wof:placetype": "postalcode"
  },
  "geometry": {"coordinates":[-3.051493,53.85285],"type":"Point"}
}
