{
  "type": "Feature",
  "properties": {
    "iso:country":"GB",
    "wof:name":"BD4 6HL",
    "wof:placetype":"postalcode"
},
  "geometry": {"coordinates":[-1.7222474504799,53.76963101529737],"type":"Point"}
}