{
  "type": "Feature",
  "properties": {
    "iso:country": "GB",
    "wof:name": "N8 7FH",
    "wof:placetype": "postalcode"
  },
  "geometry": {"coordinates":[-0.116643,51.588848],"type":"Point"}
}
