{
  "type": "Feature",
  "properties": {
    "iso:country":"GB",
    "wof:name":"SR2 0TG",
    "wof:placetype":"postalcode"
},
  "geometry": {"coordinates":[-1.37656301289789,54.8771900990721],"type":"Point"}
}