{
  "type": "Feature",
  "properties": {
    "iso:country":"GB",
    "wof:name":"SO24 0AT",
    "wof:placetype":"postalcode"
},
  "geometry": {"coordinates":[-1.12779659989407,51.08426136373017],"type":"Point"}
}