{
  "type": "Feature",
  "properties": {
    "iso:country": "GB",
    "wof:name": "SO24 0AT",
    "wof:placetype": "postalcode"
  },
  "geometry": {"coordinates":[-1.127797,51.084261],"type":"Point"}
}
