{
  "type": "Feature",
  "properties": {
    "date:inception_lower":"1980-01-01",
    "date:inception_upper":"1980-01-31",
    "iso:country":"GB",
    "wof:name":"SO24 0AT",
    "wof:placetype":"postalcode"
},
  "geometry": {"coordinates":[-1.127797,51.084261],"type":"Point"}
}