{
  "type": "Feature",
  "properties": {
    "iso:country": "GB",
    "wof:name": "CO13 9HE",
    "wof:placetype": "postalcode"
  },
  "geometry": {"coordinates":[1.252065,51.833576],"type":"Point"}
}
