{
  "type": "Feature",
  "properties": {
    "date:inception_lower":"1993-01-01",
    "date:inception_upper":"1993-01-31",
    "iso:country":"GB",
    "wof:name":"CO13 9HE",
    "wof:placetype":"postalcode"
},
  "geometry": {"coordinates":[1.252065,51.833576],"type":"Point"}
}