{
  "type": "Feature",
  "properties": {
    "date:inception_lower":"1980-01-01",
    "date:inception_upper":"1980-01-31",
    "iso:country":"GB",
    "wof:name":"HA4 0DH",
    "wof:placetype":"postalcode"
},
  "geometry": {"coordinates":[-0.406996,51.564209],"type":"Point"}
}