{
  "type": "Feature",
  "properties": {
    "iso:country":"GB",
    "wof:name":"NE24 5RJ",
    "wof:placetype":"postalcode"
},
  "geometry": {"coordinates":[-1.52895296473857,55.11744097769787],"type":"Point"}
}