{
  "type": "Feature",
  "properties": {
    "iso:country":"GB",
    "wof:name":"KT19 9AP",
    "wof:placetype":"postalcode"
},
  "geometry": {"coordinates":[-0.26633645652817,51.3412612497082],"type":"Point"}
}