{
  "type": "Feature",
  "properties": {
    "date:inception_lower": "1980-01-01",
    "date:inception_upper": "1980-01-01",
    "iso:country": "GB",
    "wof:name": "BS11 9QG",
    "wof:placetype": "postalcode"
  },
  "geometry": {"coordinates":[-2.685004,51.488028],"type":"Point"}
}
