{
  "type": "Feature",
  "properties": {
    "iso:country":"GB",
    "wof:name":"B10 9QN",
    "wof:placetype":"postalcode"
},
  "geometry": {"coordinates":[-1.85856954313442,52.47262312976186],"type":"Point"}
}