{
  "type": "Feature",
  "properties": {
    "iso:country":"GB",
    "wof:name":"BS26 2TR",
    "wof:placetype":"postalcode"
},
  "geometry": {"coordinates":[-2.90545812178051,51.26629446983336],"type":"Point"}
}