{
  "type": "Feature",
  "properties": {
    "iso:country":"GB",
    "wof:name":"SA18 2RW",
    "wof:placetype":"postalcode"
},
  "geometry": {"coordinates":[-3.9829517194998,51.76873496350476],"type":"Point"}
}