{
  "type": "Feature",
  "properties": {
    "iso:country": "GB",
    "wof:name": "HD3 4HL",
    "wof:placetype": "postalcode"
  },
  "geometry": {"coordinates":[-1.825903,53.643858],"type":"Point"}
}
