{
  "type": "Feature",
  "properties": {
    "iso:country":"GB",
    "wof:name":"HD3 4HL",
    "wof:placetype":"postalcode"
},
  "geometry": {"coordinates":[-1.82590300531726,53.64385781903258],"type":"Point"}
}