{
  "type": "Feature",
  "properties": {
    "date:inception_lower": "1992-01-01",
    "date:inception_upper": "1992-01-01",
    "iso:country": "GB",
    "wof:name": "LE7 9EX",
    "wof:placetype": "postalcode"
  },
  "geometry": {"coordinates":[-0.894989,52.582571],"type":"Point"}
}
