{
  "type": "Feature",
  "properties": {
    "iso:country":"GB",
    "wof:name":"LE7 9EX",
    "wof:placetype":"postalcode"
},
  "geometry": {"coordinates":[-0.89498897261005,52.58257109646917],"type":"Point"}
}