{
  "type": "Feature",
  "properties": {
    "iso:country":"GB",
    "wof:name":"LA2 6BT",
    "wof:placetype":"postalcode"
},
  "geometry": {"coordinates":[-2.80823541877492,54.08485423176469],"type":"Point"}
}