{
  "type": "Feature",
  "properties": {
    "iso:country":"GB",
    "wof:name":"GU51 4DJ",
    "wof:placetype":"postalcode"
},
  "geometry": {"coordinates":[-0.84526109724632,51.28093008505991],"type":"Point"}
}