{
  "type": "Feature",
  "properties": {
    "iso:country": "GB",
    "wof:name": "GU51 4DJ",
    "wof:placetype": "postalcode"
  },
  "geometry": {"coordinates":[-0.845261,51.28093],"type":"Point"}
}
