{
  "type": "Feature",
  "properties": {
    "iso:country": "GB",
    "wof:name": "S2 3NP",
    "wof:placetype": "postalcode"
  },
  "geometry": {"coordinates":[-1.456056,53.357858],"type":"Point"}
}
