{
  "type": "Feature",
  "properties": {
    "iso:country":"GB",
    "wof:name":"S2 3NP",
    "wof:placetype":"postalcode"
},
  "geometry": {"coordinates":[-1.45605670619609,53.3578493703877],"type":"Point"}
}