{
  "type": "Feature",
  "properties": {
    "iso:country": "GB",
    "wof:name": "PE11 4TU",
    "wof:placetype": "postalcode"
  },
  "geometry": {"coordinates":[-0.194783,52.904224],"type":"Point"}
}
