{
  "type": "Feature",
  "properties": {
    "date:inception_lower": "1980-01-01",
    "date:inception_upper": "1980-01-01",
    "iso:country": "GB",
    "wof:name": "CA10 2QU",
    "wof:placetype": "postalcode"
  },
  "geometry": {"coordinates":[-2.716921,54.557998],"type":"Point"}
}
