{
  "type": "Feature",
  "properties": {
    "iso:country":"GB",
    "wof:name":"CA10 2QU",
    "wof:placetype":"postalcode"
},
  "geometry": {"coordinates":[-2.71716075648084,54.55777313184622],"type":"Point"}
}