{
  "type": "Feature",
  "properties": {
    "iso:country":"GB",
    "wof:name":"CO4 3XB",
    "wof:placetype":"postalcode"
},
  "geometry": {"coordinates":[0.93742842524447,51.88992372185785],"type":"Point"}
}