{
  "type": "Feature",
  "properties": {
    "date:inception_lower":"2018-01-01",
    "date:inception_upper":"2018-01-31",
    "iso:country":"GB",
    "wof:name":"PE20 1EQ",
    "wof:placetype":"postalcode"
},
  "geometry": {"coordinates":[-0.061207,52.935075],"type":"Point"}
}