{
  "type": "Feature",
  "properties": {
    "iso:country": "GB",
    "wof:name": "PE20 1EQ",
    "wof:placetype": "postalcode"
  },
  "geometry": {"coordinates":[-0.061207,52.935075],"type":"Point"}
}
