{
  "type": "Feature",
  "properties": {
    "date:inception_lower": "2018-01-01",
    "date:inception_upper": "2018-01-01",
    "iso:country": "GB",
    "wof:name": "PE20 1EQ",
    "wof:placetype": "postalcode"
  },
  "geometry": {"coordinates":[-0.061063,52.935289],"type":"Point"}
}
