{
  "type": "Feature",
  "properties": {
    "iso:country":"GB",
    "wof:name":"N14 5BT",
    "wof:placetype":"postalcode"
},
  "geometry": {"coordinates":[-0.12902565288002,51.63311505480559],"type":"Point"}
}