{
  "type": "Feature",
  "properties": {
    "iso:country":"GB",
    "wof:name":"OL14 8JA",
    "wof:placetype":"postalcode"
},
  "geometry": {"coordinates":[-2.12187972930832,53.72721471933412],"type":"Point"}
}