{
  "type": "Feature",
  "properties": {
    "date:inception_lower": "2012-06-01",
    "date:inception_upper": "2012-06-01",
    "iso:country": "GB",
    "wof:name": "S7 2AB",
    "wof:placetype": "postalcode"
  },
  "geometry": {"coordinates":[-1.5097,53.335268],"type":"Point"}
}
