{
  "type": "Feature",
  "properties": {
    "date:inception_lower":"1980-01-01",
    "date:inception_upper":"1980-01-31",
    "iso:country":"GB",
    "wof:name":"HU5 2AR",
    "wof:placetype":"postalcode"
},
  "geometry": {"coordinates":[-0.361864,53.762367],"type":"Point"}
}