{
  "type": "Feature",
  "properties": {
    "iso:country":"GB",
    "wof:name":"B67 6PN",
    "wof:placetype":"postalcode"
},
  "geometry": {"coordinates":[-1.98499380799514,52.48814218819188],"type":"Point"}
}