{
  "type": "Feature",
  "properties": {
    "iso:country": "GB",
    "wof:name": "LE7 3RT",
    "wof:placetype": "postalcode"
  },
  "geometry": {"coordinates":[-0.984505,52.685248],"type":"Point"}
}
