{
  "type": "Feature",
  "properties": {
    "date:inception_lower": "1992-08-01",
    "date:inception_upper": "1992-08-01",
    "iso:country": "GB",
    "wof:name": "LE7 3RT",
    "wof:placetype": "postalcode"
  },
  "geometry": {"coordinates":[-0.984505,52.685248],"type":"Point"}
}
