{
  "type": "Feature",
  "properties": {
    "iso:country":"GB",
    "wof:name":"LE7 3RT",
    "wof:placetype":"postalcode"
},
  "geometry": {"coordinates":[-0.98450505007066,52.68524809615752],"type":"Point"}
}