{
  "type": "Feature",
  "properties": {
    "iso:country":"GB",
    "wof:name":"N11 2HJ",
    "wof:placetype":"postalcode"
},
  "geometry": {"coordinates":[-0.12642263627672,51.61422553506079],"type":"Point"}
}