{
  "type": "Feature",
  "properties": {
    "iso:country":"GB",
    "wof:name":"B70 9UA",
    "wof:placetype":"postalcode"
},
  "geometry": {"coordinates":[-2.00857805675779,52.52111780338248],"type":"Point"}
}