{
  "type": "Feature",
  "properties": {
    "iso:country": "GB",
    "wof:name": "SK10 4HY",
    "wof:placetype": "postalcode"
  },
  "geometry": {"coordinates":[-2.149456,53.297143],"type":"Point"}
}
