{
  "type": "Feature",
  "properties": {
    "date:inception_lower": "2019-06-01",
    "date:inception_upper": "2019-06-01",
    "iso:country": "GB",
    "wof:name": "DL5 4DG",
    "wof:placetype": "postalcode"
  },
  "geometry": {"coordinates":[-1.569983,54.6291],"type":"Point"}
}
