{
  "type": "Feature",
  "properties": {
    "date:inception_lower": "2020-09-01",
    "date:inception_upper": "2020-09-01",
    "iso:country": "GB",
    "wof:name": "YO21 1TJ",
    "wof:placetype": "postalcode"
  },
  "geometry": {"coordinates":[-0.619401,54.484192],"type":"Point"}
}
