{
  "type": "Feature",
  "properties": {
    "iso:country": "GB",
    "wof:name": "SL1 3ER",
    "wof:placetype": "postalcode"
  },
  "geometry": {"coordinates":[-0.604208,51.519377],"type":"Point"}
}
