{
  "type": "Feature",
  "properties": {
    "iso:country":"GB",
    "wof:name":"SL1 3ER",
    "wof:placetype":"postalcode"
},
  "geometry": {"coordinates":[-0.60420781360845,51.51937697857574],"type":"Point"}
}