{
  "type": "Feature",
  "properties": {
    "date:inception_lower": "2011-06-01",
    "date:inception_upper": "2011-06-01",
    "iso:country": "GB",
    "wof:name": "CF46 6SJ",
    "wof:placetype": "postalcode"
  },
  "geometry": {"coordinates":[-3.313401,51.70514],"type":"Point"}
}
