{
  "type": "Feature",
  "properties": {
    "iso:country":"GB",
    "wof:name":"CF46 6SJ",
    "wof:placetype":"postalcode"
},
  "geometry": {"coordinates":[-3.31340093760985,51.70514038427145],"type":"Point"}
}