{
  "type": "Feature",
  "properties": {
    "iso:country": "GB",
    "wof:name": "NE21 5AD",
    "wof:placetype": "postalcode"
  },
  "geometry": {"coordinates":[-1.708584,54.963378],"type":"Point"}
}
