{
  "type": "Feature",
  "properties": {
    "iso:country":"GB",
    "wof:name":"EX16 4PL",
    "wof:placetype":"postalcode"
},
  "geometry": {"coordinates":[-3.47577068544882,50.89639443700759],"type":"Point"}
}