{
  "type": "Feature",
  "properties": {
    "iso:country": "GB",
    "wof:name": "LL53 7DD",
    "wof:placetype": "postalcode"
  },
  "geometry": {"coordinates":[-4.526348,52.791576],"type":"Point"}
}
