{
  "type": "Feature",
  "properties": {
    "iso:country":"GB",
    "wof:name":"LL53 7DD",
    "wof:placetype":"postalcode"
},
  "geometry": {"coordinates":[-4.52996248179269,52.79214700570983],"type":"Point"}
}