{
  "type": "Feature",
  "properties": {
    "date:inception_lower": "1995-01-01",
    "date:inception_upper": "1995-01-01",
    "iso:country": "GB",
    "wof:name": "M34 7BS",
    "wof:placetype": "postalcode"
  },
  "geometry": {"coordinates":[-2.098912,53.440815],"type":"Point"}
}
