{
  "type": "Feature",
  "properties": {
    "date:inception_lower": "2001-06-01",
    "date:inception_upper": "2001-06-01",
    "iso:country": "GB",
    "wof:name": "HD9 1HX",
    "wof:placetype": "postalcode"
  },
  "geometry": {"coordinates":[-1.752059,53.558175],"type":"Point"}
}
