{
  "type": "Feature",
  "properties": {
    "iso:country":"GB",
    "wof:name":"HD9 1HX",
    "wof:placetype":"postalcode"
},
  "geometry": {"coordinates":[-1.752043573109,53.55814142410775],"type":"Point"}
}