{
  "type": "Feature",
  "properties": {
    "iso:country":"GB",
    "wof:name":"NE46 2DA",
    "wof:placetype":"postalcode"
},
  "geometry": {"coordinates":[-2.11224889209216,54.9639352307074],"type":"Point"}
}