{
  "type": "Feature",
  "properties": {
    "date:inception_lower":"1987-04-01",
    "date:inception_upper":"1987-04-30",
    "iso:country":"GB",
    "wof:name":"NE46 2DA",
    "wof:placetype":"postalcode"
},
  "geometry": {"coordinates":[-2.112249,54.963935],"type":"Point"}
}