{
  "type": "Feature",
  "properties": {
    "iso:country":"GB",
    "wof:name":"NG1 5DJ",
    "wof:placetype":"postalcode"
},
  "geometry": {"coordinates":[-1.15736215238702,52.9525897455603],"type":"Point"}
}