{
  "type": "Feature",
  "properties": {
    "date:inception_lower": "2007-07-01",
    "date:inception_upper": "2007-07-01",
    "iso:country": "GB",
    "wof:name": "NG1 5DJ",
    "wof:placetype": "postalcode"
  },
  "geometry": {"coordinates":[-1.157362,52.95259],"type":"Point"}
}
