{
  "type": "Feature",
  "properties": {
    "iso:country": "GB",
    "wof:name": "SA10 8PG",
    "wof:placetype": "postalcode"
  },
  "geometry": {"coordinates":[-3.748918,51.738111],"type":"Point"}
}
