{
  "type": "Feature",
  "properties": {
    "iso:country":"GB",
    "wof:name":"GL54 4AJ",
    "wof:placetype":"postalcode"
},
  "geometry": {"coordinates":[-1.91868588676273,51.80012824415401],"type":"Point"}
}