{
  "type": "Feature",
  "properties": {
    "iso:country":"GB",
    "wof:name":"CT14 9XB",
    "wof:placetype":"postalcode"
},
  "geometry": {"coordinates":[1.38502203954073,51.20566017106945],"type":"Point"}
}