{
  "type": "Feature",
  "properties": {
    "date:inception_lower": "1996-12-01",
    "date:inception_upper": "1996-12-01",
    "iso:country": "GB",
    "wof:name": "CT14 9XB",
    "wof:placetype": "postalcode"
  },
  "geometry": {"coordinates":[1.385094,51.205649],"type":"Point"}
}
