{
  "type": "Feature",
  "properties": {
    "iso:country": "GB",
    "wof:name": "SA62 5QF",
    "wof:placetype": "postalcode"
  },
  "geometry": {"coordinates":[-5.034082,51.919897],"type":"Point"}
}
