{
  "type": "Feature",
  "properties": {
    "date:inception_lower":"1980-01-01",
    "date:inception_upper":"1980-01-31",
    "iso:country":"GB",
    "wof:name":"SA62 5QF",
    "wof:placetype":"postalcode"
},
  "geometry": {"coordinates":[-5.034082,51.919897],"type":"Point"}
}