{
  "type": "Feature",
  "properties": {
    "date:inception_lower": "1980-01-01",
    "date:inception_upper": "1980-01-01",
    "iso:country": "GB",
    "wof:name": "SA62 5QF",
    "wof:placetype": "postalcode"
  },
  "geometry": {"coordinates":[-5.034974,51.919737],"type":"Point"}
}
