{
  "type": "Feature",
  "properties": {
    "iso:country":"GB",
    "wof:name":"G64 2DD",
    "wof:placetype":"postalcode"
},
  "geometry": {"coordinates":[-4.23266272634182,55.9047968309201],"type":"Point"}
}