{
  "type": "Feature",
  "properties": {
    "iso:country":"GB",
    "wof:name":"NP44 4YZ",
    "wof:placetype":"postalcode"
},
  "geometry": {"coordinates":[-3.05138741115435,51.64773245114401],"type":"Point"}
}