{
  "type": "Feature",
  "properties": {
    "date:inception_lower":"1983-03-01",
    "date:inception_upper":"1983-03-31",
    "iso:country":"GB",
    "wof:name":"NP44 4YZ",
    "wof:placetype":"postalcode"
},
  "geometry": {"coordinates":[-3.051387,51.647732],"type":"Point"}
}