{
  "type": "Feature",
  "properties": {
    "iso:country":"GB",
    "wof:name":"RM11 3YD",
    "wof:placetype":"postalcode"
},
  "geometry": {"coordinates":[0.22060883492726,51.56222841478796],"type":"Point"}
}