{
  "type": "Feature",
  "properties": {
    "iso:country": "GB",
    "wof:name": "SY4 2ER",
    "wof:placetype": "postalcode"
  },
  "geometry": {"coordinates":[-2.882328,52.808604],"type":"Point"}
}
