{
  "type": "Feature",
  "properties": {
    "iso:country":"GB",
    "wof:name":"SY4 2ER",
    "wof:placetype":"postalcode"
},
  "geometry": {"coordinates":[-2.88234504592488,52.80859845520639],"type":"Point"}
}