{
  "type": "Feature",
  "properties": {
    "date:inception_lower":"1994-05-01",
    "date:inception_upper":"1994-05-31",
    "iso:country":"GB",
    "wof:name":"M20 4BY",
    "wof:placetype":"postalcode"
},
  "geometry": {"coordinates":[-2.228971,53.430722],"type":"Point"}
}