{
  "type": "Feature",
  "properties": {
    "iso:country": "GB",
    "wof:name": "M20 4BY",
    "wof:placetype": "postalcode"
  },
  "geometry": {"coordinates":[-2.228971,53.430722],"type":"Point"}
}
