{
  "type": "Feature",
  "properties": {
    "iso:country":"GB",
    "wof:name":"TS1 2RQ",
    "wof:placetype":"postalcode"
},
  "geometry": {"coordinates":[-1.22965497049524,54.57517193172463],"type":"Point"}
}