{
  "type": "Feature",
  "properties": {
    "date:inception_lower": "1980-01-01",
    "date:inception_upper": "1980-01-01",
    "iso:country": "GB",
    "wof:name": "DT10 1HF",
    "wof:placetype": "postalcode"
  },
  "geometry": {"coordinates":[-2.28164,50.964043],"type":"Point"}
}
