{
  "type": "Feature",
  "properties": {
    "iso:country":"GB",
    "wof:name":"DT10 1HF",
    "wof:placetype":"postalcode"
},
  "geometry": {"coordinates":[-2.28164021646448,50.96404251304902],"type":"Point"}
}