{
  "type": "Feature",
  "properties": {
    "iso:country":"GB",
    "wof:name":"SE18 1HY",
    "wof:placetype":"postalcode"
},
  "geometry": {"coordinates":[0.09605632210399,51.48795529436685],"type":"Point"}
}