{
  "type": "Feature",
  "properties": {
    "date:inception_lower": "2002-07-01",
    "date:inception_upper": "2002-07-01",
    "iso:country": "GB",
    "wof:name": "TW9 1EZ",
    "wof:placetype": "postalcode"
  },
  "geometry": {"coordinates":[-0.302032,51.463093],"type":"Point"}
}
