{
  "type": "Feature",
  "properties": {
    "iso:country":"GB",
    "wof:name":"S80 4NA",
    "wof:placetype":"postalcode"
},
  "geometry": {"coordinates":[-1.26732707497281,53.25427701493816],"type":"Point"}
}