{
  "type": "Feature",
  "properties": {
    "iso:country": "GB",
    "wof:name": "S80 4NA",
    "wof:placetype": "postalcode"
  },
  "geometry": {"coordinates":[-1.267327,53.254277],"type":"Point"}
}
