{
  "type": "Feature",
  "properties": {
    "iso:country": "GB",
    "wof:name": "CW1 4TL",
    "wof:placetype": "postalcode"
  },
  "geometry": {"coordinates":[-2.456869,53.120115],"type":"Point"}
}
