{
  "type": "Feature",
  "properties": {
    "iso:country":"GB",
    "wof:name":"CW1 4TL",
    "wof:placetype":"postalcode"
},
  "geometry": {"coordinates":[-2.45686875889964,53.12011471944543],"type":"Point"}
}