{
  "type": "Feature",
  "properties": {
    "iso:country": "GB",
    "wof:name": "HD7 5UW",
    "wof:placetype": "postalcode"
  },
  "geometry": {"coordinates":[-1.853895,53.628364],"type":"Point"}
}
