{
  "type": "Feature",
  "properties": {
    "iso:country":"GB",
    "wof:name":"HD7 5UW",
    "wof:placetype":"postalcode"
},
  "geometry": {"coordinates":[-1.8538948898369,53.6283635643849],"type":"Point"}
}