{
  "type": "Feature",
  "properties": {
    "date:inception_lower": "2021-07-01",
    "date:inception_upper": "2021-07-01",
    "iso:country": "GB",
    "wof:name": "BN52 9LP",
    "wof:placetype": "postalcode"
  },
  "geometry": {"coordinates":[-0.168035,50.834403],"type":"Point"}
}
