{
  "type": "Feature",
  "properties": {
    "date:inception_lower": "2008-01-01",
    "date:inception_upper": "2008-01-01",
    "iso:country": "GB",
    "wof:name": "PE20 3JX",
    "wof:placetype": "postalcode"
  },
  "geometry": {"coordinates":[-0.160456,52.943733],"type":"Point"}
}
