{
  "type": "Feature",
  "properties": {
    "iso:country":"GB",
    "wof:name":"PE20 3JX",
    "wof:placetype":"postalcode"
},
  "geometry": {"coordinates":[-0.16045586254449,52.94373269657906],"type":"Point"}
}