{
  "type": "Feature",
  "properties": {
    "iso:country":"GB",
    "wof:name":"TR4 9RB",
    "wof:placetype":"postalcode"
},
  "geometry": {"coordinates":[-5.02829105676016,50.31170972579731],"type":"Point"}
}