{
  "type": "Feature",
  "properties": {
    "date:inception_lower":"1987-04-01",
    "date:inception_upper":"1987-04-30",
    "iso:country":"GB",
    "wof:name":"TR4 9RB",
    "wof:placetype":"postalcode"
},
  "geometry": {"coordinates":[-5.028291,50.31171],"type":"Point"}
}