{
  "type": "Feature",
  "properties": {
    "date:inception_lower": "1980-01-01",
    "date:inception_upper": "1980-01-01",
    "iso:country": "GB",
    "wof:name": "CA8 1UB",
    "wof:placetype": "postalcode"
  },
  "geometry": {"coordinates":[-2.725201,54.9425],"type":"Point"}
}
