{
  "type": "Feature",
  "properties": {
    "iso:country":"GB",
    "wof:name":"CA8 1UB",
    "wof:placetype":"postalcode"
},
  "geometry": {"coordinates":[-2.72513407477686,54.94249400042932],"type":"Point"}
}