{
  "type": "Feature",
  "properties": {
    "iso:country":"GB",
    "wof:name":"TN3 9QT",
    "wof:placetype":"postalcode"
},
  "geometry": {"coordinates":[0.17388195707053,51.11051525977376],"type":"Point"}
}