{
  "type": "Feature",
  "properties": {
    "date:inception_lower": "1985-10-01",
    "date:inception_upper": "1985-10-01",
    "iso:country": "GB",
    "wof:name": "DL13 2PN",
    "wof:placetype": "postalcode"
  },
  "geometry": {"coordinates":[-2.011857,54.735102],"type":"Point"}
}
