{
  "type": "Feature",
  "properties": {
    "date:inception_lower":"1985-10-01",
    "date:inception_upper":"1985-10-31",
    "iso:country":"GB",
    "wof:name":"DL13 2PN",
    "wof:placetype":"postalcode"
},
  "geometry": {"coordinates":[-2.016221,54.733556],"type":"Point"}
}