{
  "type": "Feature",
  "properties": {
    "date:inception_lower": "1994-12-01",
    "date:inception_upper": "1994-12-01",
    "iso:country": "GB",
    "wof:name": "SO53 2PD",
    "wof:placetype": "postalcode"
  },
  "geometry": {"coordinates":[-1.36251,50.99062],"type":"Point"}
}
