{
  "type": "Feature",
  "properties": {
    "iso:country": "GB",
    "wof:name": "SO53 2PD",
    "wof:placetype": "postalcode"
  },
  "geometry": {"coordinates":[-1.36251,50.99062],"type":"Point"}
}
