{
  "type": "Feature",
  "properties": {
    "iso:country":"GB",
    "wof:name":"DE7 4HR",
    "wof:placetype":"postalcode"
},
  "geometry": {"coordinates":[-1.32437994012116,52.96122518119292],"type":"Point"}
}