{
  "type": "Feature",
  "properties": {
    "iso:country":"GB",
    "wof:name":"GL20 7RS",
    "wof:placetype":"postalcode"
},
  "geometry": {"coordinates":[-2.14546183329704,51.98875712313643],"type":"Point"}
}