{
  "type": "Feature",
  "properties": {
    "date:inception_lower": "1998-06-01",
    "date:inception_upper": "1998-06-01",
    "iso:country": "GB",
    "wof:name": "GL20 7RS",
    "wof:placetype": "postalcode"
  },
  "geometry": {"coordinates":[-2.145462,51.988757],"type":"Point"}
}
