{
  "type": "Feature",
  "properties": {
    "iso:country": "GB",
    "wof:name": "PE19 1DP",
    "wof:placetype": "postalcode"
  },
  "geometry": {"coordinates":[-0.265162,52.230803],"type":"Point"}
}
