{
  "type": "Feature",
  "properties": {
    "iso:country": "GB",
    "wof:name": "BD23 6SD",
    "wof:placetype": "postalcode"
  },
  "geometry": {"coordinates":[-1.981407,53.980859],"type":"Point"}
}
