{
  "type": "Feature",
  "properties": {
    "iso:country":"GB",
    "wof:name":"AB14 0PL",
    "wof:placetype":"postalcode"
},
  "geometry": {"coordinates":[-2.29207480958506,57.10808856724782],"type":"Point"}
}