{
  "type": "Feature",
  "properties": {
    "iso:country":"GB",
    "wof:name":"KT15 1LU",
    "wof:placetype":"postalcode"
},
  "geometry": {"coordinates":[-0.49183558846947,51.36710530748501],"type":"Point"}
}