{
  "type": "Feature",
  "properties": {
    "iso:country":"GB",
    "wof:name":"IG1 3QH",
    "wof:placetype":"postalcode"
},
  "geometry": {"coordinates":[0.06035423780251,51.57367724974346],"type":"Point"}
}