{
  "type": "Feature",
  "properties": {
    "iso:country":"GB",
    "wof:name":"NW3 6XS",
    "wof:placetype":"postalcode"
},
  "geometry": {"coordinates":[-0.18248392061686,51.55733102357058],"type":"Point"}
}