{
  "type": "Feature",
  "properties": {
    "iso:country":"GB",
    "wof:name":"DA12 4LH",
    "wof:placetype":"postalcode"
},
  "geometry": {"coordinates":[0.40201593795439,51.41558950152209],"type":"Point"}
}