{
  "type": "Feature",
  "properties": {
    "iso:country": "GB",
    "wof:name": "DA12 4LH",
    "wof:placetype": "postalcode"
  },
  "geometry": {"coordinates":[0.402016,51.415589],"type":"Point"}
}
