{
  "type": "Feature",
  "properties": {
    "date:inception_lower":"1981-06-01",
    "date:inception_upper":"1981-06-30",
    "iso:country":"GB",
    "wof:name":"TF2 9HP",
    "wof:placetype":"postalcode"
},
  "geometry": {"coordinates":[-2.439367,52.695217],"type":"Point"}
}