{
  "type": "Feature",
  "properties": {
    "iso:country":"GB",
    "wof:name":"SL4 6AS",
    "wof:placetype":"postalcode"
},
  "geometry": {"coordinates":[-0.60914019477621,51.48993264125081],"type":"Point"}
}