{
  "type": "Feature",
  "properties": {
    "date:inception_lower": "1980-01-01",
    "date:inception_upper": "1980-01-01",
    "iso:country": "GB",
    "wof:name": "DL15 9PQ",
    "wof:placetype": "postalcode"
  },
  "geometry": {"coordinates":[-1.754186,54.715076],"type":"Point"}
}
