{
  "type": "Feature",
  "properties": {
    "iso:country":"GB",
    "wof:name":"TS12 2DB",
    "wof:placetype":"postalcode"
},
  "geometry": {"coordinates":[-0.985851253308,54.55457359531616],"type":"Point"}
}