{
  "type": "Feature",
  "properties": {
    "date:inception_lower": "2018-05-01",
    "date:inception_upper": "2018-05-01",
    "iso:country": "GB",
    "wof:name": "LA5 8LS",
    "wof:placetype": "postalcode"
  },
  "geometry": {"coordinates":[-2.792432,54.104347],"type":"Point"}
}
