{
  "type": "Feature",
  "properties": {
    "iso:country":"GB",
    "wof:name":"AB35 5TF",
    "wof:placetype":"postalcode"
},
  "geometry": {"coordinates":[-3.04043956018235,57.05132220389886],"type":"Point"}
}