{
  "type": "Feature",
  "properties": {
    "date:inception_lower":"1990-09-01",
    "date:inception_upper":"1990-09-30",
    "iso:country":"GB",
    "wof:name":"AB35 5TF",
    "wof:placetype":"postalcode"
},
  "geometry": {"coordinates":[-3.040424,57.051301],"type":"Point"}
}