{
  "type": "Feature",
  "properties": {
    "date:inception_lower": "1980-01-01",
    "date:inception_upper": "1980-01-01",
    "iso:country": "GB",
    "wof:name": "S10 3TF",
    "wof:placetype": "postalcode"
  },
  "geometry": {"coordinates":[-1.543424,53.363788],"type":"Point"}
}
