{
  "type": "Feature",
  "properties": {
    "iso:country":"GB",
    "wof:name":"ML1 4JS",
    "wof:placetype":"postalcode"
},
  "geometry": {"coordinates":[-3.97841813108015,55.81267161132237],"type":"Point"}
}