{
  "type": "Feature",
  "properties": {
    "date:inception_lower":"1980-01-01",
    "date:inception_upper":"1980-01-31",
    "iso:country":"GB",
    "wof:name":"WA11 8EA",
    "wof:placetype":"postalcode"
},
  "geometry": {"coordinates":[-2.793019,53.504496],"type":"Point"}
}