{
  "type": "Feature",
  "properties": {
    "date:inception_lower":"1980-01-01",
    "date:inception_upper":"1980-01-31",
    "iso:country":"GB",
    "wof:name":"HD5 8DU",
    "wof:placetype":"postalcode"
},
  "geometry": {"coordinates":[-1.753977,53.643822],"type":"Point"}
}