{
  "type": "Feature",
  "properties": {
    "iso:country":"GB",
    "wof:name":"PL25 4DH",
    "wof:placetype":"postalcode"
},
  "geometry": {"coordinates":[-4.7835361902934,50.34569970813272],"type":"Point"}
}