{
  "type": "Feature",
  "properties": {
    "iso:country":"GB",
    "wof:name":"DE21 7HJ",
    "wof:placetype":"postalcode"
},
  "geometry": {"coordinates":[-1.39705436117131,52.91449346327155],"type":"Point"}
}