{
  "type": "Feature",
  "properties": {
    "iso:country":"GB",
    "wof:name":"YO15 3DS",
    "wof:placetype":"postalcode"
},
  "geometry": {"coordinates":[-0.19880661899566,54.0803736221581],"type":"Point"}
}