{
  "type": "Feature",
  "properties": {
    "iso:country":"GB",
    "wof:name":"PA6 7BD",
    "wof:placetype":"postalcode"
},
  "geometry": {"coordinates":[-4.52187053542319,55.867168152027],"type":"Point"}
}