{
  "type": "Feature",
  "properties": {
    "date:inception_lower": "1980-01-01",
    "date:inception_upper": "1980-01-01",
    "iso:country": "GB",
    "wof:name": "PA6 7BD",
    "wof:placetype": "postalcode"
  },
  "geometry": {"coordinates":[-4.52187,55.867168],"type":"Point"}
}
