{
  "type": "Feature",
  "properties": {
    "iso:country": "GB",
    "wof:name": "MK10 0DG",
    "wof:placetype": "postalcode"
  },
  "geometry": {"coordinates":[-0.683479,52.03249],"type":"Point"}
}
