{
  "type": "Feature",
  "properties": {
    "date:inception_lower":"1997-12-01",
    "date:inception_upper":"1997-12-31",
    "iso:country":"GB",
    "wof:name":"MK10 0DG",
    "wof:placetype":"postalcode"
},
  "geometry": {"coordinates":[-0.683479,52.03249],"type":"Point"}
}