{
  "type": "Feature",
  "properties": {
    "iso:country":"GB",
    "wof:name":"MK10 0DG",
    "wof:placetype":"postalcode"
},
  "geometry": {"coordinates":[-0.68347927271675,52.03249033613515],"type":"Point"}
}