{
  "type": "Feature",
  "properties": {
    "date:inception_lower": "2021-06-01",
    "date:inception_upper": "2021-06-01",
    "iso:country": "GB",
    "wof:name": "MK10 0DG",
    "wof:placetype": "postalcode"
  },
  "geometry": {"coordinates":[-0.681375,52.032442],"type":"Point"}
}
