{
  "type": "Feature",
  "properties": {
    "iso:country":"GB",
    "wof:name":"HP17 8QL",
    "wof:placetype":"postalcode"
},
  "geometry": {"coordinates":[-0.84667878889515,51.80131812692397],"type":"Point"}
}