{
  "type": "Feature",
  "properties": {
    "iso:country":"GB",
    "wof:name":"PE7 8BU",
    "wof:placetype":"postalcode"
},
  "geometry": {"coordinates":[-0.27328856286908,52.54149422505821],"type":"Point"}
}