{
  "type": "Feature",
  "properties": {
    "iso:country": "GB",
    "wof:name": "IP3 8AW",
    "wof:placetype": "postalcode"
  },
  "geometry": {"coordinates":[1.170036,52.053591],"type":"Point"}
}
