{
  "type": "Feature",
  "properties": {
    "iso:country":"GB",
    "wof:name":"IP3 8AW",
    "wof:placetype":"postalcode"
},
  "geometry": {"coordinates":[1.17003571958175,52.05359142404158],"type":"Point"}
}