{
  "type": "Feature",
  "properties": {
    "iso:country":"GB",
    "wof:name":"SG11 1SS",
    "wof:placetype":"postalcode"
},
  "geometry": {"coordinates":[0.01695940556324,51.89018129349849],"type":"Point"}
}