{
  "type": "Feature",
  "properties": {
    "iso:country": "GB",
    "wof:name": "SG11 1SS",
    "wof:placetype": "postalcode"
  },
  "geometry": {"coordinates":[0.017074,51.890152],"type":"Point"}
}
