{
  "type": "Feature",
  "properties": {
    "iso:country":"GB",
    "wof:name":"FK19 8PS",
    "wof:placetype":"postalcode"
},
  "geometry": {"coordinates":[-4.28104520292433,56.38593631116876],"type":"Point"}
}