{
  "type": "Feature",
  "properties": {
    "iso:country": "GB",
    "wof:name": "KT23 4FE",
    "wof:placetype": "postalcode"
  },
  "geometry": {"coordinates":[-0.367365,51.278127],"type":"Point"}
}
