{
  "type": "Feature",
  "properties": {
    "date:inception_lower": "1980-01-01",
    "date:inception_upper": "1980-01-01",
    "iso:country": "GB",
    "wof:name": "PO5 3PJ",
    "wof:placetype": "postalcode"
  },
  "geometry": {"coordinates":[-1.092336,50.787174],"type":"Point"}
}
