{
  "type": "Feature",
  "properties": {
    "iso:country":"GB",
    "wof:name":"NN5 6LF",
    "wof:placetype":"postalcode"
},
  "geometry": {"coordinates":[-0.94645296409504,52.25001606109161],"type":"Point"}
}