{
  "type": "Feature",
  "properties": {
    "date:inception_lower": "1980-01-01",
    "date:inception_upper": "1980-01-01",
    "iso:country": "GB",
    "wof:name": "DD1 2PP",
    "wof:placetype": "postalcode"
  },
  "geometry": {"coordinates":[-2.967355,56.466541],"type":"Point"}
}
