{
  "type": "Feature",
  "properties": {
    "iso:country":"GB",
    "wof:name":"S2 2NF",
    "wof:placetype":"postalcode"
},
  "geometry": {"coordinates":[-1.44246463960131,53.36893271453675],"type":"Point"}
}