{
  "type": "Feature",
  "properties": {
    "iso:country":"GB",
    "wof:name":"BB12 7BX",
    "wof:placetype":"postalcode"
},
  "geometry": {"coordinates":[-2.30990244779036,53.79427697813472],"type":"Point"}
}