{
  "type": "Feature",
  "properties": {
    "date:inception_lower":"1980-01-01",
    "date:inception_upper":"1980-01-31",
    "iso:country":"GB",
    "wof:name":"BB12 7BX",
    "wof:placetype":"postalcode"
},
  "geometry": {"coordinates":[-2.309902,53.794277],"type":"Point"}
}