{
  "type": "Feature",
  "properties": {
    "iso:country": "GB",
    "wof:name": "LL36 9YW",
    "wof:placetype": "postalcode"
  },
  "geometry": {"coordinates":[-3.956554,52.644185],"type":"Point"}
}
