{
  "type": "Feature",
  "properties": {
    "date:inception_lower": "2024-06-01",
    "date:inception_upper": "2024-06-01",
    "iso:country": "GB",
    "wof:name": "LL36 9YW",
    "wof:placetype": "postalcode"
  },
  "geometry": {"coordinates":[-3.956562,52.6442],"type":"Point"}
}
