{
  "type": "Feature",
  "properties": {
    "date:inception_lower": "1992-08-01",
    "date:inception_upper": "1992-08-01",
    "iso:country": "GB",
    "wof:name": "WD3 1LD",
    "wof:placetype": "postalcode"
  },
  "geometry": {"coordinates":[-0.467922,51.634424],"type":"Point"}
}
