{
  "type": "Feature",
  "properties": {
    "iso:country":"GB",
    "wof:name":"DN32 8JW",
    "wof:placetype":"postalcode"
},
  "geometry": {"coordinates":[-0.05243332412252,53.56082844459505],"type":"Point"}
}