{
  "type": "Feature",
  "properties": {
    "iso:country":"GB",
    "wof:name":"S61 3AU",
    "wof:placetype":"postalcode"
},
  "geometry": {"coordinates":[-1.39948416952134,53.44889441519411],"type":"Point"}
}