{
  "type": "Feature",
  "properties": {
    "iso:country": "GB",
    "wof:name": "S61 3AU",
    "wof:placetype": "postalcode"
  },
  "geometry": {"coordinates":[-1.399485,53.448913],"type":"Point"}
}
