{
  "type": "Feature",
  "properties": {
    "iso:country":"GB",
    "wof:name":"ST5 1DF",
    "wof:placetype":"postalcode"
},
  "geometry": {"coordinates":[-2.21720360688379,53.01126170797173],"type":"Point"}
}