{
  "type": "Feature",
  "properties": {
    "iso:country":"GB",
    "wof:name":"B66 2BY",
    "wof:placetype":"postalcode"
},
  "geometry": {"coordinates":[-1.96930173794148,52.49974520104598],"type":"Point"}
}