{
  "type": "Feature",
  "properties": {
    "iso:country": "GB",
    "wof:name": "WS2 9UE",
    "wof:placetype": "postalcode"
  },
  "geometry": {"coordinates":[-2.002761,52.585279],"type":"Point"}
}
