{
  "type": "Feature",
  "properties": {
    "iso:country":"GB",
    "wof:name":"LE9 8LQ",
    "wof:placetype":"postalcode"
},
  "geometry": {"coordinates":[-1.33830490992355,52.57651836168959],"type":"Point"}
}