{
  "type": "Feature",
  "properties": {
    "iso:country":"GB",
    "wof:name":"NW6 6QG",
    "wof:placetype":"postalcode"
},
  "geometry": {"coordinates":[-0.19660689673637,51.53872785840812],"type":"Point"}
}