{
  "type": "Feature",
  "properties": {
    "date:inception_lower":"2004-03-01",
    "date:inception_upper":"2004-03-31",
    "iso:country":"GB",
    "wof:name":"CM8 1SR",
    "wof:placetype":"postalcode"
},
  "geometry": {"coordinates":[0.632233,51.788675],"type":"Point"}
}