{
  "type": "Feature",
  "properties": {
    "iso:country":"GB",
    "wof:name":"AL9 7LZ",
    "wof:placetype":"postalcode"
},
  "geometry": {"coordinates":[-0.22320703743661,51.73740363002806],"type":"Point"}
}