{
  "type": "Feature",
  "properties": {
    "iso:country":"GB",
    "wof:name":"CO9 2RQ",
    "wof:placetype":"postalcode"
},
  "geometry": {"coordinates":[0.62958631798245,51.97946910499223],"type":"Point"}
}