{
  "type": "Feature",
  "properties": {
    "date:inception_lower":"1980-01-01",
    "date:inception_upper":"1980-01-31",
    "iso:country":"GB",
    "wof:name":"SW10 9JP",
    "wof:placetype":"postalcode"
},
  "geometry": {"coordinates":[-0.186463,51.487737],"type":"Point"}
}