{
  "type": "Feature",
  "properties": {
    "iso:country":"GB",
    "wof:name":"SW10 9JP",
    "wof:placetype":"postalcode"
},
  "geometry": {"coordinates":[-0.18646263090555,51.48773713411988],"type":"Point"}
}