{
  "type": "Feature",
  "properties": {
    "iso:country":"GB",
    "wof:name":"DE7 8QG",
    "wof:placetype":"postalcode"
},
  "geometry": {"coordinates":[-1.31361713043853,52.99032508565764],"type":"Point"}
}