{
  "type": "Feature",
  "properties": {
    "iso:country":"GB",
    "wof:name":"B94 6HN",
    "wof:placetype":"postalcode"
},
  "geometry": {"coordinates":[-1.76530294645763,52.34599357040704],"type":"Point"}
}