{
  "type": "Feature",
  "properties": {
    "date:inception_lower": "2023-01-01",
    "date:inception_upper": "2023-01-01",
    "iso:country": "GB",
    "wof:name": "LS11 9DZ",
    "wof:placetype": "postalcode"
  },
  "geometry": {"coordinates":[-1.558337,53.785595],"type":"Point"}
}
