{
  "type": "Feature",
  "properties": {
    "iso:country":"GB",
    "wof:name":"BD8 8AS",
    "wof:placetype":"postalcode"
},
  "geometry": {"coordinates":[-1.77013106447883,53.80538764244999],"type":"Point"}
}