{
  "type": "Feature",
  "properties": {
    "iso:country": "GB",
    "wof:name": "BD8 8AS",
    "wof:placetype": "postalcode"
  },
  "geometry": {"coordinates":[-1.770131,53.805388],"type":"Point"}
}
