{
  "type": "Feature",
  "properties": {
    "date:inception_lower": "1980-01-01",
    "date:inception_upper": "1980-01-01",
    "iso:country": "GB",
    "wof:name": "NG1 5GE",
    "wof:placetype": "postalcode"
  },
  "geometry": {"coordinates":[-1.159534,52.955751],"type":"Point"}
}
