{
  "type": "Feature",
  "properties": {
    "iso:country":"GB",
    "wof:name":"NG1 5GE",
    "wof:placetype":"postalcode"
},
  "geometry": {"coordinates":[-1.15953355429772,52.95575143975988],"type":"Point"}
}