{
  "type": "Feature",
  "properties": {
    "iso:country":"GB",
    "wof:name":"S80 3RA",
    "wof:placetype":"postalcode"
},
  "geometry": {"coordinates":[-1.14584566795518,53.30296241351768],"type":"Point"}
}