{
  "type": "Feature",
  "properties": {
    "date:inception_lower": "2011-06-01",
    "date:inception_upper": "2011-06-01",
    "iso:country": "GB",
    "wof:name": "PO1 4QY",
    "wof:placetype": "postalcode"
  },
  "geometry": {"coordinates":[-1.088147,50.808526],"type":"Point"}
}
