{
  "type": "Feature",
  "properties": {
    "date:inception_lower":"2015-06-01",
    "date:inception_upper":"2015-06-30",
    "iso:country":"GB",
    "wof:name":"NG15 0EJ",
    "wof:placetype":"postalcode"
},
  "geometry": {"coordinates":[-1.229209,53.072978],"type":"Point"}
}