{
  "type": "Feature",
  "properties": {
    "iso:country": "GB",
    "wof:name": "NG15 0EJ",
    "wof:placetype": "postalcode"
  },
  "geometry": {"coordinates":[-1.229209,53.072978],"type":"Point"}
}
