{
  "type": "Feature",
  "properties": {
    "iso:country":"GB",
    "wof:name":"SL8 5EU",
    "wof:placetype":"postalcode"
},
  "geometry": {"coordinates":[-0.70138440180026,51.57094649318616],"type":"Point"}
}