{
  "type": "Feature",
  "properties": {
    "iso:country":"GB",
    "wof:name":"DG7 3SF",
    "wof:placetype":"postalcode"
},
  "geometry": {"coordinates":[-4.18518658660397,55.09761392622337],"type":"Point"}
}