{
  "type": "Feature",
  "properties": {
    "iso:country":"GB",
    "wof:name":"BA16 0RZ",
    "wof:placetype":"postalcode"
},
  "geometry": {"coordinates":[-2.74315939471835,51.11404129134379],"type":"Point"}
}