{
  "type": "Feature",
  "properties": {
    "iso:country": "GB",
    "wof:name": "PA43 7AE",
    "wof:placetype": "postalcode"
  },
  "geometry": {"coordinates":[-6.292007,55.752696],"type":"Point"}
}
