{
  "type": "Feature",
  "properties": {
    "iso:country":"GB",
    "wof:name":"BH21 4HY",
    "wof:placetype":"postalcode"
},
  "geometry": {"coordinates":[-1.99360229366025,50.82313887448183],"type":"Point"}
}