{
  "type": "Feature",
  "properties": {
    "iso:country":"GB",
    "wof:name":"TS17 8JA",
    "wof:placetype":"postalcode"
},
  "geometry": {"coordinates":[-1.29599963890515,54.54580186810487],"type":"Point"}
}