{
  "type": "Feature",
  "properties": {
    "iso:country":"GB",
    "wof:name":"NN5 6GE",
    "wof:placetype":"postalcode"
},
  "geometry": {"coordinates":[-0.96385929342395,52.24858772234155],"type":"Point"}
}