{
  "type": "Feature",
  "properties": {
    "iso:country": "GB",
    "wof:name": "NN5 6GE",
    "wof:placetype": "postalcode"
  },
  "geometry": {"coordinates":[-0.963859,52.248588],"type":"Point"}
}
