{
  "type": "Feature",
  "properties": {
    "iso:country":"GB",
    "wof:name":"SE2 9RZ",
    "wof:placetype":"postalcode"
},
  "geometry": {"coordinates":[0.12283195150166,51.49255454110019],"type":"Point"}
}