{
  "type": "Feature",
  "properties": {
    "iso:country":"GB",
    "wof:name":"NR2 2LU",
    "wof:placetype":"postalcode"
},
  "geometry": {"coordinates":[1.2880955930888,52.61968715393987],"type":"Point"}
}