{
  "type": "Feature",
  "properties": {
    "iso:country":"GB",
    "wof:name":"NE9 6HE",
    "wof:placetype":"postalcode"
},
  "geometry": {"coordinates":[-1.60543008879378,54.93430433501656],"type":"Point"}
}