{
  "type": "Feature",
  "properties": {
    "iso:country":"GB",
    "wof:name":"DD5 3LT",
    "wof:placetype":"postalcode"
},
  "geometry": {"coordinates":[-2.88339097288841,56.47612467839903],"type":"Point"}
}