{
  "type": "Feature",
  "properties": {
    "iso:country":"GB",
    "wof:name":"G61 2TW",
    "wof:placetype":"postalcode"
},
  "geometry": {"coordinates":[-4.3021780499798,55.90831558334649],"type":"Point"}
}