{
  "type": "Feature",
  "properties": {
    "iso:country":"GB",
    "wof:name":"SR3 2QF",
    "wof:placetype":"postalcode"
},
  "geometry": {"coordinates":[-1.42524372788238,54.86560383573418],"type":"Point"}
}