{
  "type": "Feature",
  "properties": {
    "iso:country": "GB",
    "wof:name": "TR27 6HU",
    "wof:placetype": "postalcode"
  },
  "geometry": {"coordinates":[-5.426986,50.164344],"type":"Point"}
}
