{
  "type": "Feature",
  "properties": {
    "iso:country": "GB",
    "wof:name": "N19 5EP",
    "wof:placetype": "postalcode"
  },
  "geometry": {"coordinates":[-0.136817,51.55684],"type":"Point"}
}
