{
  "type": "Feature",
  "properties": {
    "iso:country":"GB",
    "wof:name":"L15 4LB",
    "wof:placetype":"postalcode"
},
  "geometry": {"coordinates":[-2.92856918499181,53.39986979518695],"type":"Point"}
}