{
  "type": "Feature",
  "properties": {
    "iso:country": "GB",
    "wof:name": "L15 4LB",
    "wof:placetype": "postalcode"
  },
  "geometry": {"coordinates":[-2.928569,53.39987],"type":"Point"}
}
