{
  "type": "Feature",
  "properties": {
    "iso:country": "GB",
    "wof:name": "WA8 6TY",
    "wof:placetype": "postalcode"
  },
  "geometry": {"coordinates":[-2.722807,53.377813],"type":"Point"}
}
