{
  "type": "Feature",
  "properties": {
    "date:inception_lower":"2008-02-01",
    "date:inception_upper":"2008-02-29",
    "iso:country":"GB",
    "wof:name":"E2 0LX",
    "wof:placetype":"postalcode"
},
  "geometry": {"coordinates":[-0.050854,51.527782],"type":"Point"}
}