{
  "type": "Feature",
  "properties": {
    "iso:country": "GB",
    "wof:name": "E2 0LX",
    "wof:placetype": "postalcode"
  },
  "geometry": {"coordinates":[-0.050854,51.527782],"type":"Point"}
}
