{
  "type": "Feature",
  "properties": {
    "iso:country":"GB",
    "wof:name":"E2 0LX",
    "wof:placetype":"postalcode"
},
  "geometry": {"coordinates":[-0.05085450929752,51.52778179889881],"type":"Point"}
}