{
  "type": "Feature",
  "properties": {
    "iso:country":"GB",
    "wof:name":"NG1 1NG",
    "wof:placetype":"postalcode"
},
  "geometry": {"coordinates":[-1.14381203894995,52.95285251770449],"type":"Point"}
}