{
  "type": "Feature",
  "properties": {
    "date:inception_lower": "1980-01-01",
    "date:inception_upper": "1980-01-01",
    "iso:country": "GB",
    "wof:name": "CB9 8BG",
    "wof:placetype": "postalcode"
  },
  "geometry": {"coordinates":[0.435386,52.081316],"type":"Point"}
}
