{
  "type": "Feature",
  "properties": {
    "iso:country":"GB",
    "wof:name":"TN34 3SB",
    "wof:placetype":"postalcode"
},
  "geometry": {"coordinates":[0.58382796542951,50.86551752676758],"type":"Point"}
}