{
  "type": "Feature",
  "properties": {
    "iso:country": "GB",
    "wof:name": "TN34 3SB",
    "wof:placetype": "postalcode"
  },
  "geometry": {"coordinates":[0.583828,50.865518],"type":"Point"}
}
