{
  "type": "Feature",
  "properties": {
    "iso:country": "GB",
    "wof:name": "AL3 4QY",
    "wof:placetype": "postalcode"
  },
  "geometry": {"coordinates":[-0.34775,51.75359],"type":"Point"}
}
