{
  "type": "Feature",
  "properties": {
    "iso:country":"GB",
    "wof:name":"AL3 4QY",
    "wof:placetype":"postalcode"
},
  "geometry": {"coordinates":[-0.34774992901489,51.7535898090808],"type":"Point"}
}