{
  "type": "Feature",
  "properties": {
    "iso:country":"GB",
    "wof:name":"KT16 9JB",
    "wof:placetype":"postalcode"
},
  "geometry": {"coordinates":[-0.51708888596715,51.38937787726793],"type":"Point"}
}