{
  "type": "Feature",
  "properties": {
    "date:inception_lower":"1980-01-01",
    "date:inception_upper":"1980-01-31",
    "iso:country":"GB",
    "wof:name":"SA12 9NN",
    "wof:placetype":"postalcode"
},
  "geometry": {"coordinates":[-3.758496,51.616915],"type":"Point"}
}