{
  "type": "Feature",
  "properties": {
    "iso:country":"GB",
    "wof:name":"SA12 9NN",
    "wof:placetype":"postalcode"
},
  "geometry": {"coordinates":[-3.75849608629251,51.61691513271762],"type":"Point"}
}