{
  "type": "Feature",
  "properties": {
    "date:inception_lower":"1996-12-01",
    "date:inception_upper":"1996-12-31",
    "iso:country":"GB",
    "wof:name":"MK40 1HB",
    "wof:placetype":"postalcode"
},
  "geometry": {"coordinates":[-0.47114,52.138416],"type":"Point"}
}