{
  "type": "Feature",
  "properties": {
    "iso:country":"GB",
    "wof:name":"SN16 9TB",
    "wof:placetype":"postalcode"
},
  "geometry": {"coordinates":[-2.01454788304255,51.64244195935169],"type":"Point"}
}