{
  "type": "Feature",
  "properties": {
    "iso:country": "GB",
    "wof:name": "SN16 9TB",
    "wof:placetype": "postalcode"
  },
  "geometry": {"coordinates":[-2.014548,51.642442],"type":"Point"}
}
