{
  "type": "Feature",
  "properties": {
    "iso:country":"GB",
    "wof:name":"YO17 9ED",
    "wof:placetype":"postalcode"
},
  "geometry": {"coordinates":[-0.79545695473007,54.12961197707696],"type":"Point"}
}