{
  "type": "Feature",
  "properties": {
    "iso:country": "GB",
    "wof:name": "EH54 9DG",
    "wof:placetype": "postalcode"
  },
  "geometry": {"coordinates":[-3.501848,55.874779],"type":"Point"}
}
