{
  "type": "Feature",
  "properties": {
    "date:inception_lower": "1980-01-01",
    "date:inception_upper": "1980-01-01",
    "iso:country": "GB",
    "wof:name": "SY18 6JP",
    "wof:placetype": "postalcode"
  },
  "geometry": {"coordinates":[-3.506422,52.424334],"type":"Point"}
}
