{
  "type": "Feature",
  "properties": {
    "iso:country":"GB",
    "wof:name":"DN10 4QT",
    "wof:placetype":"postalcode"
},
  "geometry": {"coordinates":[-0.89611480547541,53.40751501039016],"type":"Point"}
}