{
  "type": "Feature",
  "properties": {
    "iso:country":"GB",
    "wof:name":"B12 8JY",
    "wof:placetype":"postalcode"
},
  "geometry": {"coordinates":[-1.87761248628121,52.45382827302242],"type":"Point"}
}