{
  "type": "Feature",
  "properties": {
    "iso:country": "GB",
    "wof:name": "CA12 5JU",
    "wof:placetype": "postalcode"
  },
  "geometry": {"coordinates":[-3.138537,54.602201],"type":"Point"}
}
