{
  "type": "Feature",
  "properties": {
    "iso:country": "GB",
    "wof:name": "SG8 7HS",
    "wof:placetype": "postalcode"
  },
  "geometry": {"coordinates":[-0.015722,52.051076],"type":"Point"}
}
