{
  "type": "Feature",
  "properties": {
    "iso:country":"GB",
    "wof:name":"LE2 4DB",
    "wof:placetype":"postalcode"
},
  "geometry": {"coordinates":[-1.08245151441215,52.60269113350226],"type":"Point"}
}