{
  "type": "Feature",
  "properties": {
    "iso:country": "GB",
    "wof:name": "LE2 4DB",
    "wof:placetype": "postalcode"
  },
  "geometry": {"coordinates":[-1.082451,52.602691],"type":"Point"}
}
