{
  "type": "Feature",
  "properties": {
    "date:inception_lower":"1981-07-01",
    "date:inception_upper":"1981-07-31",
    "iso:country":"GB",
    "wof:name":"IV30 1PP",
    "wof:placetype":"postalcode"
},
  "geometry": {"coordinates":[-3.313455,57.649793],"type":"Point"}
}