{
  "type": "Feature",
  "properties": {
    "date:inception_lower": "1991-01-01",
    "date:inception_upper": "1991-01-01",
    "iso:country": "GB",
    "wof:name": "KT20 5UJ",
    "wof:placetype": "postalcode"
  },
  "geometry": {"coordinates":[-0.235228,51.291031],"type":"Point"}
}
