{
  "type": "Feature",
  "properties": {
    "iso:country":"GB",
    "wof:name":"KT20 5UJ",
    "wof:placetype":"postalcode"
},
  "geometry": {"coordinates":[-0.23522770316334,51.29103120274548],"type":"Point"}
}