{
  "type": "Feature",
  "properties": {
    "iso:country": "GB",
    "wof:name": "LE15 9US",
    "wof:placetype": "postalcode"
  },
  "geometry": {"coordinates":[-0.716304,52.585498],"type":"Point"}
}
