{
  "type": "Feature",
  "properties": {
    "iso:country":"GB",
    "wof:name":"LE15 9US",
    "wof:placetype":"postalcode"
},
  "geometry": {"coordinates":[-0.71621392671372,52.58546123607338],"type":"Point"}
}