{
  "type": "Feature",
  "properties": {
    "date:inception_lower": "2000-06-01",
    "date:inception_upper": "2000-06-01",
    "iso:country": "GB",
    "wof:name": "PE28 9BE",
    "wof:placetype": "postalcode"
  },
  "geometry": {"coordinates":[-0.107157,52.31757],"type":"Point"}
}
