{
  "type": "Feature",
  "properties": {
    "iso:country":"GB",
    "wof:name":"SO18 5RE",
    "wof:placetype":"postalcode"
},
  "geometry": {"coordinates":[-1.33207089905084,50.91644212537923],"type":"Point"}
}