{
  "type": "Feature",
  "properties": {
    "iso:country": "GB",
    "wof:name": "CB8 9PX",
    "wof:placetype": "postalcode"
  },
  "geometry": {"coordinates":[0.526823,52.189883],"type":"Point"}
}
