{
  "type": "Feature",
  "properties": {
    "iso:country":"GB",
    "wof:name":"SY4 3BU",
    "wof:placetype":"postalcode"
},
  "geometry": {"coordinates":[-2.70338883597733,52.8105225120493],"type":"Point"}
}