{
  "type": "Feature",
  "properties": {
    "date:inception_lower": "1980-01-01",
    "date:inception_upper": "1980-01-01",
    "iso:country": "GB",
    "wof:name": "SY4 3BU",
    "wof:placetype": "postalcode"
  },
  "geometry": {"coordinates":[-2.703389,52.810523],"type":"Point"}
}
