{
  "type": "Feature",
  "properties": {
    "iso:country":"GB",
    "wof:name":"LS20 9EN",
    "wof:placetype":"postalcode"
},
  "geometry": {"coordinates":[-1.71022445643387,53.87863541090477],"type":"Point"}
}