{
  "type": "Feature",
  "properties": {
    "iso:country": "GB",
    "wof:name": "LS20 9EN",
    "wof:placetype": "postalcode"
  },
  "geometry": {"coordinates":[-1.710224,53.878635],"type":"Point"}
}
