{
  "type": "Feature",
  "properties": {
    "iso:country":"GB",
    "wof:name":"SW4 7AH",
    "wof:placetype":"postalcode"
},
  "geometry": {"coordinates":[-0.13875975392328,51.45971524581401],"type":"Point"}
}