{
  "type": "Feature",
  "properties": {
    "iso:country": "GB",
    "wof:name": "S45 8AT",
    "wof:placetype": "postalcode"
  },
  "geometry": {"coordinates":[-1.373503,53.167286],"type":"Point"}
}
