{
  "type": "Feature",
  "properties": {
    "iso:country": "GB",
    "wof:name": "SK17 0LL",
    "wof:placetype": "postalcode"
  },
  "geometry": {"coordinates":[-1.876758,53.148174],"type":"Point"}
}
