{
  "type": "Feature",
  "properties": {
    "date:inception_lower":"1980-01-01",
    "date:inception_upper":"1980-01-31",
    "iso:country":"GB",
    "wof:name":"MK41 7AQ",
    "wof:placetype":"postalcode"
},
  "geometry": {"coordinates":[-0.458148,52.15917],"type":"Point"}
}