{
  "type": "Feature",
  "properties": {
    "date:inception_lower": "2022-10-01",
    "date:inception_upper": "2022-10-01",
    "iso:country": "GB",
    "wof:name": "ME13 7UP",
    "wof:placetype": "postalcode"
  },
  "geometry": {"coordinates":[0.866062,51.315397],"type":"Point"}
}
