{
  "type": "Feature",
  "properties": {
    "iso:country":"GB",
    "wof:name":"SS9 1QF",
    "wof:placetype":"postalcode"
},
  "geometry": {"coordinates":[0.65678796740116,51.54213377857469],"type":"Point"}
}