{
  "type": "Feature",
  "properties": {
    "date:inception_lower": "1980-01-01",
    "date:inception_upper": "1980-01-01",
    "iso:country": "GB",
    "wof:name": "G46 6DU",
    "wof:placetype": "postalcode"
  },
  "geometry": {"coordinates":[-4.289898,55.809888],"type":"Point"}
}
