{
  "type": "Feature",
  "properties": {
    "iso:country":"GB",
    "wof:name":"G46 6DU",
    "wof:placetype":"postalcode"
},
  "geometry": {"coordinates":[-4.28989787411413,55.8098884357721],"type":"Point"}
}