{
  "type": "Feature",
  "properties": {
    "date:inception_lower": "1999-12-01",
    "date:inception_upper": "1999-12-01",
    "iso:country": "GB",
    "wof:name": "SP4 8JG",
    "wof:placetype": "postalcode"
  },
  "geometry": {"coordinates":[-1.773965,51.201323],"type":"Point"}
}
