{
  "type": "Feature",
  "properties": {
    "iso:country": "GB",
    "wof:name": "SP4 8JG",
    "wof:placetype": "postalcode"
  },
  "geometry": {"coordinates":[-1.773965,51.201323],"type":"Point"}
}
