{
  "type": "Feature",
  "properties": {
    "iso:country":"GB",
    "wof:name":"LL11 2NT",
    "wof:placetype":"postalcode"
},
  "geometry": {"coordinates":[-2.99638159509452,53.05261837986668],"type":"Point"}
}