{
  "type": "Feature",
  "properties": {
    "iso:country":"GB",
    "wof:name":"CM12 9XB",
    "wof:placetype":"postalcode"
},
  "geometry": {"coordinates":[0.42204105714663,51.60015053990369],"type":"Point"}
}