{
  "type": "Feature",
  "properties": {
    "date:inception_lower":"1980-01-01",
    "date:inception_upper":"1980-01-31",
    "iso:country":"GB",
    "wof:name":"CM12 9XB",
    "wof:placetype":"postalcode"
},
  "geometry": {"coordinates":[0.422041,51.600151],"type":"Point"}
}