{
  "type": "Feature",
  "properties": {
    "iso:country": "GB",
    "wof:name": "CM12 9XB",
    "wof:placetype": "postalcode"
  },
  "geometry": {"coordinates":[0.422041,51.600151],"type":"Point"}
}
