{
  "type": "Feature",
  "properties": {
    "iso:country": "GB",
    "wof:name": "CM7 5AX",
    "wof:placetype": "postalcode"
  },
  "geometry": {"coordinates":[0.49831,51.912607],"type":"Point"}
}
