{
  "type": "Feature",
  "properties": {
    "iso:country": "GB",
    "wof:name": "L39 5AA",
    "wof:placetype": "postalcode"
  },
  "geometry": {"coordinates":[-2.900769,53.553943],"type":"Point"}
}
