{
  "type": "Feature",
  "properties": {
    "iso:country":"GB",
    "wof:name":"L39 5AA",
    "wof:placetype":"postalcode"
},
  "geometry": {"coordinates":[-2.90076930341222,53.55394347484479],"type":"Point"}
}