{
  "type": "Feature",
  "properties": {
    "iso:country": "GB",
    "wof:name": "NR31 6LH",
    "wof:placetype": "postalcode"
  },
  "geometry": {"coordinates":[1.727351,52.579842],"type":"Point"}
}
