{
  "type": "Feature",
  "properties": {
    "iso:country":"GB",
    "wof:name":"NR31 6LH",
    "wof:placetype":"postalcode"
},
  "geometry": {"coordinates":[1.7273279265273,52.57981703094441],"type":"Point"}
}