{
  "type": "Feature",
  "properties": {
    "iso:country":"GB",
    "wof:name":"NE47 6HD",
    "wof:placetype":"postalcode"
},
  "geometry": {"coordinates":[-2.24863356131694,54.97503726548788],"type":"Point"}
}