{
  "type": "Feature",
  "properties": {
    "date:inception_lower": "1980-01-01",
    "date:inception_upper": "1980-01-01",
    "iso:country": "GB",
    "wof:name": "DL15 0RS",
    "wof:placetype": "postalcode"
  },
  "geometry": {"coordinates":[-1.717244,54.712668],"type":"Point"}
}
