{
  "type": "Feature",
  "properties": {
    "date:inception_lower":"1980-01-01",
    "date:inception_upper":"1980-01-31",
    "iso:country":"GB",
    "wof:name":"PH3 1DA",
    "wof:placetype":"postalcode"
},
  "geometry": {"coordinates":[-3.703965,56.297718],"type":"Point"}
}