{
  "type": "Feature",
  "properties": {
    "date:inception_lower": "1999-06-01",
    "date:inception_upper": "1999-06-01",
    "iso:country": "GB",
    "wof:name": "EX34 9RZ",
    "wof:placetype": "postalcode"
  },
  "geometry": {"coordinates":[-4.054102,51.208081],"type":"Point"}
}
