{
  "type": "Feature",
  "properties": {
    "iso:country":"GB",
    "wof:name":"W14 8HT",
    "wof:placetype":"postalcode"
},
  "geometry": {"coordinates":[-0.21044303446565,51.49919323633872],"type":"Point"}
}