{
  "type": "Feature",
  "properties": {
    "date:inception_lower": "1980-01-01",
    "date:inception_upper": "1980-01-01",
    "iso:country": "GB",
    "wof:name": "W14 8HT",
    "wof:placetype": "postalcode"
  },
  "geometry": {"coordinates":[-0.210443,51.499193],"type":"Point"}
}
