{
  "type": "Feature",
  "properties": {
    "iso:country": "GB",
    "wof:name": "PA3 3SN",
    "wof:placetype": "postalcode"
  },
  "geometry": {"coordinates":[-4.516753,55.850582],"type":"Point"}
}
