{
  "type": "Feature",
  "properties": {
    "iso:country":"GB",
    "wof:name":"PA3 3SN",
    "wof:placetype":"postalcode"
},
  "geometry": {"coordinates":[-4.51675332013362,55.85058207073173],"type":"Point"}
}