{
  "type": "Feature",
  "properties": {
    "date:inception_lower": "1999-06-01",
    "date:inception_upper": "1999-06-01",
    "iso:country": "GB",
    "wof:name": "CH65 7AJ",
    "wof:placetype": "postalcode"
  },
  "geometry": {"coordinates":[-2.916375,53.274685],"type":"Point"}
}
