{
  "type": "Feature",
  "properties": {
    "date:inception_lower": "1985-04-01",
    "date:inception_upper": "1985-04-01",
    "iso:country": "GB",
    "wof:name": "IP23 8HW",
    "wof:placetype": "postalcode"
  },
  "geometry": {"coordinates":[1.043442,52.30555],"type":"Point"}
}
