{
  "type": "Feature",
  "properties": {
    "date:inception_lower": "1980-01-01",
    "date:inception_upper": "1980-01-01",
    "iso:country": "GB",
    "wof:name": "NE29 6NQ",
    "wof:placetype": "postalcode"
  },
  "geometry": {"coordinates":[-1.445986,55.006086],"type":"Point"}
}
