{
  "type": "Feature",
  "properties": {
    "iso:country":"GB",
    "wof:name":"ST6 3PB",
    "wof:placetype":"postalcode"
},
  "geometry": {"coordinates":[-2.20414833560316,53.03983437540985],"type":"Point"}
}