{
  "type": "Feature",
  "properties": {
    "iso:country":"GB",
    "wof:name":"TR14 9BE",
    "wof:placetype":"postalcode"
},
  "geometry": {"coordinates":[-5.27493912217122,50.21616253180356],"type":"Point"}
}