{
  "type": "Feature",
  "properties": {
    "iso:country": "GB",
    "wof:name": "TR14 9BE",
    "wof:placetype": "postalcode"
  },
  "geometry": {"coordinates":[-5.274975,50.216171],"type":"Point"}
}
