{
  "type": "Feature",
  "properties": {
    "date:inception_lower": "1995-01-01",
    "date:inception_upper": "1995-01-01",
    "iso:country": "GB",
    "wof:name": "S40 3AZ",
    "wof:placetype": "postalcode"
  },
  "geometry": {"coordinates":[-1.461401,53.230422],"type":"Point"}
}
