{
  "type": "Feature",
  "properties": {
    "iso:country": "GB",
    "wof:name": "S40 3AZ",
    "wof:placetype": "postalcode"
  },
  "geometry": {"coordinates":[-1.461401,53.230422],"type":"Point"}
}
