{
  "type": "Feature",
  "properties": {
    "iso:country":"GB",
    "wof:name":"TA20 3LB",
    "wof:placetype":"postalcode"
},
  "geometry": {"coordinates":[-3.03854090725804,50.93671512648444],"type":"Point"}
}