{
  "type": "Feature",
  "properties": {
    "iso:country": "GB",
    "wof:name": "ME15 8PF",
    "wof:placetype": "postalcode"
  },
  "geometry": {"coordinates":[0.569131,51.262911],"type":"Point"}
}
