{
  "type": "Feature",
  "properties": {
    "iso:country":"GB",
    "wof:name":"ME15 8PF",
    "wof:placetype":"postalcode"
},
  "geometry": {"coordinates":[0.56913128949712,51.26291060637116],"type":"Point"}
}