{
  "type": "Feature",
  "properties": {
    "iso:country":"GB",
    "wof:name":"ST15 0EG",
    "wof:placetype":"postalcode"
},
  "geometry": {"coordinates":[-2.1536929393902,52.89710760131848],"type":"Point"}
}