{
  "type": "Feature",
  "properties": {
    "iso:country": "GB",
    "wof:name": "TQ5 9NY",
    "wof:placetype": "postalcode"
  },
  "geometry": {"coordinates":[-3.513392,50.384736],"type":"Point"}
}
