{
  "type": "Feature",
  "properties": {
    "date:inception_lower":"1993-08-01",
    "date:inception_upper":"1993-08-31",
    "iso:country":"GB",
    "wof:name":"GL51 9RR",
    "wof:placetype":"postalcode"
},
  "geometry": {"coordinates":[-2.104014,51.918538],"type":"Point"}
}