{
  "type": "Feature",
  "properties": {
    "date:inception_lower": "1980-01-01",
    "date:inception_upper": "1980-01-01",
    "iso:country": "GB",
    "wof:name": "M4 4EX",
    "wof:placetype": "postalcode"
  },
  "geometry": {"coordinates":[-2.240898,53.490919],"type":"Point"}
}
