{
  "type": "Feature",
  "properties": {
    "iso:country":"GB",
    "wof:name":"BN2 8BS",
    "wof:placetype":"postalcode"
},
  "geometry": {"coordinates":[-0.03579985311867,50.80229964998229],"type":"Point"}
}