{
  "type": "Feature",
  "properties": {
    "iso:country": "GB",
    "wof:name": "BN2 8BS",
    "wof:placetype": "postalcode"
  },
  "geometry": {"coordinates":[-0.0358,50.8023],"type":"Point"}
}
