{
  "type": "Feature",
  "properties": {
    "iso:country":"GB",
    "wof:name":"CM6 1RH",
    "wof:placetype":"postalcode"
},
  "geometry": {"coordinates":[0.24801920464008,51.80307251643923],"type":"Point"}
}