{
  "type": "Feature",
  "properties": {
    "date:inception_lower":"1980-01-01",
    "date:inception_upper":"1980-01-31",
    "iso:country":"GB",
    "wof:name":"CB8 8UA",
    "wof:placetype":"postalcode"
},
  "geometry": {"coordinates":[0.552008,52.221102],"type":"Point"}
}