{
  "type": "Feature",
  "properties": {
    "iso:country":"GB",
    "wof:name":"CB8 8UA",
    "wof:placetype":"postalcode"
},
  "geometry": {"coordinates":[0.55200777150015,52.22110242187794],"type":"Point"}
}