{
  "type": "Feature",
  "properties": {
    "date:inception_lower": "1994-12-01",
    "date:inception_upper": "1994-12-01",
    "iso:country": "GB",
    "wof:name": "SY10 8NH",
    "wof:placetype": "postalcode"
  },
  "geometry": {"coordinates":[-3.040043,52.84894],"type":"Point"}
}
