{
  "type": "Feature",
  "properties": {
    "iso:country":"GB",
    "wof:name":"NW8 0BD",
    "wof:placetype":"postalcode"
},
  "geometry": {"coordinates":[-0.1858913072747,51.53804108698937],"type":"Point"}
}