{
  "type": "Feature",
  "properties": {
    "iso:country":"GB",
    "wof:name":"RH7 6BU",
    "wof:placetype":"postalcode"
},
  "geometry": {"coordinates":[-0.02494704969605,51.18350649892354],"type":"Point"}
}