{
  "type": "Feature",
  "properties": {
    "iso:country":"GB",
    "wof:name":"LA14 2UL",
    "wof:placetype":"postalcode"
},
  "geometry": {"coordinates":[-3.21300367389181,54.10993667678319],"type":"Point"}
}