{
  "type": "Feature",
  "properties": {
    "date:inception_lower": "2000-10-01",
    "date:inception_upper": "2000-10-01",
    "iso:country": "GB",
    "wof:name": "OX26 4XH",
    "wof:placetype": "postalcode"
  },
  "geometry": {"coordinates":[-1.136664,51.90945],"type":"Point"}
}
