{
  "type": "Feature",
  "properties": {
    "date:inception_lower":"1992-08-01",
    "date:inception_upper":"1992-08-31",
    "iso:country":"GB",
    "wof:name":"LE67 6JL",
    "wof:placetype":"postalcode"
},
  "geometry": {"coordinates":[-1.406477,52.687104],"type":"Point"}
}