{
  "type": "Feature",
  "properties": {
    "iso:country":"GB",
    "wof:name":"LE67 6JL",
    "wof:placetype":"postalcode"
},
  "geometry": {"coordinates":[-1.40647718863847,52.68710408449466],"type":"Point"}
}