{
  "type": "Feature",
  "properties": {
    "iso:country": "GB",
    "wof:name": "LE67 6JL",
    "wof:placetype": "postalcode"
  },
  "geometry": {"coordinates":[-1.406477,52.687104],"type":"Point"}
}
