{
  "type": "Feature",
  "properties": {
    "date:inception_lower": "1980-01-01",
    "date:inception_upper": "1980-01-01",
    "iso:country": "GB",
    "wof:name": "EX16 9QH",
    "wof:placetype": "postalcode"
  },
  "geometry": {"coordinates":[-3.587517,50.94751],"type":"Point"}
}
