{
  "type": "Feature",
  "properties": {
    "iso:country":"GB",
    "wof:name":"NE10 9SL",
    "wof:placetype":"postalcode"
},
  "geometry": {"coordinates":[-1.57593821478215,54.94272414352577],"type":"Point"}
}