{
  "type": "Feature",
  "properties": {
    "iso:country":"GB",
    "wof:name":"LU3 3AF",
    "wof:placetype":"postalcode"
},
  "geometry": {"coordinates":[-0.46683215904336,51.912414440024],"type":"Point"}
}