{
  "type": "Feature",
  "properties": {
    "iso:country":"GB",
    "wof:name":"KY16 9RU",
    "wof:placetype":"postalcode"
},
  "geometry": {"coordinates":[-2.87721397831309,56.33634284610711],"type":"Point"}
}