{
  "type": "Feature",
  "properties": {
    "date:inception_lower":"1980-01-01",
    "date:inception_upper":"1980-01-31",
    "iso:country":"GB",
    "wof:name":"KY16 9RU",
    "wof:placetype":"postalcode"
},
  "geometry": {"coordinates":[-2.877214,56.336343],"type":"Point"}
}