{
  "type": "Feature",
  "properties": {
    "iso:country": "GB",
    "wof:name": "SA13 2TA",
    "wof:placetype": "postalcode"
  },
  "geometry": {"coordinates":[-3.731626,51.562947],"type":"Point"}
}
