{
  "type": "Feature",
  "properties": {
    "iso:country":"GB",
    "wof:name":"M40 7DJ",
    "wof:placetype":"postalcode"
},
  "geometry": {"coordinates":[-2.211674773682,53.48755239603884],"type":"Point"}
}