{
  "type": "Feature",
  "properties": {
    "date:inception_lower":"1980-01-01",
    "date:inception_upper":"1980-01-31",
    "iso:country":"GB",
    "wof:name":"CM5 0LL",
    "wof:placetype":"postalcode"
},
  "geometry": {"coordinates":[0.219284,51.738071],"type":"Point"}
}