{
  "type": "Feature",
  "properties": {
    "iso:country":"GB",
    "wof:name":"SG4 9LE",
    "wof:placetype":"postalcode"
},
  "geometry": {"coordinates":[-0.26577852995616,51.94502432788728],"type":"Point"}
}