{
  "type": "Feature",
  "properties": {
    "date:inception_lower": "1980-01-01",
    "date:inception_upper": "1980-01-01",
    "iso:country": "GB",
    "wof:name": "SG4 9LE",
    "wof:placetype": "postalcode"
  },
  "geometry": {"coordinates":[-0.2662,51.94519],"type":"Point"}
}
