{
  "type": "Feature",
  "properties": {
    "iso:country":"GB",
    "wof:name":"NN14 1LG",
    "wof:placetype":"postalcode"
},
  "geometry": {"coordinates":[-0.80114344133455,52.39754296470001],"type":"Point"}
}