{
  "type": "Feature",
  "properties": {
    "iso:country":"GB",
    "wof:name":"PL8 1HH",
    "wof:placetype":"postalcode"
},
  "geometry": {"coordinates":[-3.98262718147773,50.312410713429],"type":"Point"}
}