{
  "type": "Feature",
  "properties": {
    "date:inception_lower": "2009-07-01",
    "date:inception_upper": "2009-07-01",
    "iso:country": "GB",
    "wof:name": "PL8 1HH",
    "wof:placetype": "postalcode"
  },
  "geometry": {"coordinates":[-3.982627,50.312411],"type":"Point"}
}
