{
  "type": "Feature",
  "properties": {
    "iso:country":"GB",
    "wof:name":"CO3 3EG",
    "wof:placetype":"postalcode"
},
  "geometry": {"coordinates":[0.89398717652183,51.88726848029201],"type":"Point"}
}