{
  "type": "Feature",
  "properties": {
    "iso:country": "GB",
    "wof:name": "TN4 0SD",
    "wof:placetype": "postalcode"
  },
  "geometry": {"coordinates":[0.254178,51.161939],"type":"Point"}
}
