{
  "type": "Feature",
  "properties": {
    "iso:country":"GB",
    "wof:name":"IG3 8AP",
    "wof:placetype":"postalcode"
},
  "geometry": {"coordinates":[0.09476031589095,51.56240267972826],"type":"Point"}
}