{
  "type": "Feature",
  "properties": {
    "iso:country": "GB",
    "wof:name": "IG3 8AP",
    "wof:placetype": "postalcode"
  },
  "geometry": {"coordinates":[0.09476,51.562403],"type":"Point"}
}
