{
  "type": "Feature",
  "properties": {
    "iso:country":"GB",
    "wof:name":"GU14 9FL",
    "wof:placetype":"postalcode"
},
  "geometry": {"coordinates":[-0.76538160984256,51.31467229539973],"type":"Point"}
}