{
  "type": "Feature",
  "properties": {
    "iso:country": "GB",
    "wof:name": "GU14 9FL",
    "wof:placetype": "postalcode"
  },
  "geometry": {"coordinates":[-0.765382,51.314672],"type":"Point"}
}
