{
  "type": "Feature",
  "properties": {
    "iso:country":"GB",
    "wof:name":"BR3 1RP",
    "wof:placetype":"postalcode"
},
  "geometry": {"coordinates":[-0.0271735827113,51.42218038486514],"type":"Point"}
}