{
  "type": "Feature",
  "properties": {
    "iso:country": "GB",
    "wof:name": "EH28 8AG",
    "wof:placetype": "postalcode"
  },
  "geometry": {"coordinates":[-3.394823,55.92126],"type":"Point"}
}
