{
  "type": "Feature",
  "properties": {
    "iso:country":"GB",
    "wof:name":"DN4 0HD",
    "wof:placetype":"postalcode"
},
  "geometry": {"coordinates":[-1.15559103374316,53.5146287152651],"type":"Point"}
}