{
  "type": "Feature",
  "properties": {
    "iso:country": "GB",
    "wof:name": "BD17 7RQ",
    "wof:placetype": "postalcode"
  },
  "geometry": {"coordinates":[-1.731924,53.856384],"type":"Point"}
}
