{
  "type": "Feature",
  "properties": {
    "date:inception_lower": "1980-01-01",
    "date:inception_upper": "1980-01-01",
    "iso:country": "GB",
    "wof:name": "EX16 7QJ",
    "wof:placetype": "postalcode"
  },
  "geometry": {"coordinates":[-3.455413,50.964028],"type":"Point"}
}
