{
  "type": "Feature",
  "properties": {
    "iso:country": "GB",
    "wof:name": "CF47 0EJ",
    "wof:placetype": "postalcode"
  },
  "geometry": {"coordinates":[-3.373815,51.752281],"type":"Point"}
}
