{
  "type": "Feature",
  "properties": {
    "iso:country":"GB",
    "wof:name":"CF47 0EJ",
    "wof:placetype":"postalcode"
},
  "geometry": {"coordinates":[-3.37376063757641,51.75229481904825],"type":"Point"}
}