{
  "type": "Feature",
  "properties": {
    "date:inception_lower": "1980-01-01",
    "date:inception_upper": "1980-01-01",
    "iso:country": "GB",
    "wof:name": "CF47 0EJ",
    "wof:placetype": "postalcode"
  },
  "geometry": {"coordinates":[-3.373772,51.752299],"type":"Point"}
}
