{
  "type": "Feature",
  "properties": {
    "iso:country":"GB",
    "wof:name":"B32 2HR",
    "wof:placetype":"postalcode"
},
  "geometry": {"coordinates":[-1.97509850569959,52.45977719482357],"type":"Point"}
}