{
  "type": "Feature",
  "properties": {
    "iso:country":"GB",
    "wof:name":"LE2 9UH",
    "wof:placetype":"postalcode"
},
  "geometry": {"coordinates":[-1.14961633885612,52.58002489089235],"type":"Point"}
}