{
  "type": "Feature",
  "properties": {
    "date:inception_lower":"1995-07-01",
    "date:inception_upper":"1995-07-31",
    "iso:country":"GB",
    "wof:name":"N12 8LR",
    "wof:placetype":"postalcode"
},
  "geometry": {"coordinates":[-0.180974,51.621549],"type":"Point"}
}