{
  "type": "Feature",
  "properties": {
    "iso:country":"GB",
    "wof:name":"BN16 4JS",
    "wof:placetype":"postalcode"
},
  "geometry": {"coordinates":[-0.4858490045183,50.82918099385136],"type":"Point"}
}