{
  "type": "Feature",
  "properties": {
    "date:inception_lower": "1980-01-01",
    "date:inception_upper": "1980-01-01",
    "iso:country": "GB",
    "wof:name": "BN16 4JS",
    "wof:placetype": "postalcode"
  },
  "geometry": {"coordinates":[-0.485849,50.829181],"type":"Point"}
}
