{
  "type": "Feature",
  "properties": {
    "iso:country":"GB",
    "wof:name":"EN6 1BZ",
    "wof:placetype":"postalcode"
},
  "geometry": {"coordinates":[-0.18661090486825,51.70259342208375],"type":"Point"}
}