{
  "type": "Feature",
  "properties": {
    "date:inception_lower": "2022-12-01",
    "date:inception_upper": "2022-12-01",
    "iso:country": "GB",
    "wof:name": "B62 0FG",
    "wof:placetype": "postalcode"
  },
  "geometry": {"coordinates":[-2.071551,52.397857],"type":"Point"}
}
