{
  "type": "Feature",
  "properties": {
    "iso:country": "GB",
    "wof:name": "SN2 8BX",
    "wof:placetype": "postalcode"
  },
  "geometry": {"coordinates":[-1.774131,51.570745],"type":"Point"}
}
