{
  "type": "Feature",
  "properties": {
    "date:inception_lower":"1981-06-01",
    "date:inception_upper":"1981-06-30",
    "iso:country":"GB",
    "wof:name":"LE2 3QJ",
    "wof:placetype":"postalcode"
},
  "geometry": {"coordinates":[-1.104542,52.60553],"type":"Point"}
}