{
  "type": "Feature",
  "properties": {
    "iso:country": "GB",
    "wof:name": "LE2 3QJ",
    "wof:placetype": "postalcode"
  },
  "geometry": {"coordinates":[-1.104542,52.60553],"type":"Point"}
}
