{
  "type": "Feature",
  "properties": {
    "iso:country":"GB",
    "wof:name":"LE2 3QJ",
    "wof:placetype":"postalcode"
},
  "geometry": {"coordinates":[-1.10454216110379,52.60553019819469],"type":"Point"}
}