{
  "type": "Feature",
  "properties": {
    "date:inception_lower": "2022-08-01",
    "date:inception_upper": "2022-08-01",
    "iso:country": "GB",
    "wof:name": "CH4 7FE",
    "wof:placetype": "postalcode"
  },
  "geometry": {"coordinates":[-2.905239,53.167679],"type":"Point"}
}
