{
  "type": "Feature",
  "properties": {
    "iso:country":"GB",
    "wof:name":"SL3 9JB",
    "wof:placetype":"postalcode"
},
  "geometry": {"coordinates":[-0.56632567878995,51.48139614690216],"type":"Point"}
}