{
  "type": "Feature",
  "properties": {
    "iso:country": "GB",
    "wof:name": "SL3 9JB",
    "wof:placetype": "postalcode"
  },
  "geometry": {"coordinates":[-0.566326,51.481396],"type":"Point"}
}
