{
  "type": "Feature",
  "properties": {
    "iso:country":"GB",
    "wof:name":"LE9 7SE",
    "wof:placetype":"postalcode"
},
  "geometry": {"coordinates":[-1.30831601813901,52.55421368781733],"type":"Point"}
}