{
  "type": "Feature",
  "properties": {
    "date:inception_lower":"2003-11-01",
    "date:inception_upper":"2003-11-30",
    "iso:country":"GB",
    "wof:name":"PR9 8DQ",
    "wof:placetype":"postalcode"
},
  "geometry": {"coordinates":[-2.935292,53.675698],"type":"Point"}
}