{
  "type": "Feature",
  "properties": {
    "date:inception_lower": "1981-06-01",
    "date:inception_upper": "1981-06-01",
    "iso:country": "GB",
    "wof:name": "CV32 4TA",
    "wof:placetype": "postalcode"
  },
  "geometry": {"coordinates":[-1.526818,52.29272],"type":"Point"}
}
