{
  "type": "Feature",
  "properties": {
    "date:inception_lower": "2011-02-01",
    "date:inception_upper": "2011-02-01",
    "iso:country": "GB",
    "wof:name": "G21 3HA",
    "wof:placetype": "postalcode"
  },
  "geometry": {"coordinates":[-4.202214,55.879861],"type":"Point"}
}
