{
  "type": "Feature",
  "properties": {
    "iso:country":"GB",
    "wof:name":"G21 3HA",
    "wof:placetype":"postalcode"
},
  "geometry": {"coordinates":[-4.20272104932618,55.8792551467139],"type":"Point"}
}