{
  "type": "Feature",
  "properties": {
    "date:inception_lower": "2015-08-01",
    "date:inception_upper": "2015-08-01",
    "iso:country": "GB",
    "wof:name": "OX26 2BY",
    "wof:placetype": "postalcode"
  },
  "geometry": {"coordinates":[-1.166053,51.899529],"type":"Point"}
}
