{
  "type": "Feature",
  "properties": {
    "iso:country":"GB",
    "wof:name":"OX26 2BY",
    "wof:placetype":"postalcode"
},
  "geometry": {"coordinates":[-1.16605290838111,51.89952916210306],"type":"Point"}
}