{
  "type": "Feature",
  "properties": {
    "iso:country":"GB",
    "wof:name":"BD21 4NJ",
    "wof:placetype":"postalcode"
},
  "geometry": {"coordinates":[-1.88746217879653,53.86761632225049],"type":"Point"}
}