{
  "type": "Feature",
  "properties": {
    "iso:country":"GB",
    "wof:name":"LN1 1AQ",
    "wof:placetype":"postalcode"
},
  "geometry": {"coordinates":[-0.55696285853258,53.24677139425184],"type":"Point"}
}