{
  "type": "Feature",
  "properties": {
    "iso:country":"GB",
    "wof:name":"CV34 4AE",
    "wof:placetype":"postalcode"
},
  "geometry": {"coordinates":[-1.5828647874454,52.28354782824891],"type":"Point"}
}