{
  "type": "Feature",
  "properties": {
    "iso:country":"GB",
    "wof:name":"L39 3NN",
    "wof:placetype":"postalcode"
},
  "geometry": {"coordinates":[-2.89943173426558,53.5648927198691],"type":"Point"}
}