{
  "type": "Feature",
  "properties": {
    "iso:country":"GB",
    "wof:name":"LL77 7RQ",
    "wof:placetype":"postalcode"
},
  "geometry": {"coordinates":[-4.31800679258218,53.2792406740739],"type":"Point"}
}