{
  "type": "Feature",
  "properties": {
    "iso:country": "GB",
    "wof:name": "LL77 7RQ",
    "wof:placetype": "postalcode"
  },
  "geometry": {"coordinates":[-4.320244,53.279188],"type":"Point"}
}
