{
  "type": "Feature",
  "properties": {
    "iso:country": "GB",
    "wof:name": "KY11 8EN",
    "wof:placetype": "postalcode"
  },
  "geometry": {"coordinates":[-3.403308,56.079622],"type":"Point"}
}
