{
  "type": "Feature",
  "properties": {
    "date:inception_lower":"1980-01-01",
    "date:inception_upper":"1980-01-31",
    "iso:country":"GB",
    "wof:name":"LN8 3JX",
    "wof:placetype":"postalcode"
},
  "geometry": {"coordinates":[-0.370717,53.386607],"type":"Point"}
}