{
  "type": "Feature",
  "properties": {
    "iso:country":"GB",
    "wof:name":"FK8 2JQ",
    "wof:placetype":"postalcode"
},
  "geometry": {"coordinates":[-3.94251939586498,56.11276939403212],"type":"Point"}
}