{
  "type": "Feature",
  "properties": {
    "iso:country": "GB",
    "wof:name": "LA4 4FD",
    "wof:placetype": "postalcode"
  },
  "geometry": {"coordinates":[-2.875359,54.067379],"type":"Point"}
}
