{
  "type": "Feature",
  "properties": {
    "date:inception_lower":"1999-12-01",
    "date:inception_upper":"1999-12-31",
    "iso:country":"GB",
    "wof:name":"LA4 4FD",
    "wof:placetype":"postalcode"
},
  "geometry": {"coordinates":[-2.875359,54.067379],"type":"Point"}
}