{
  "type": "Feature",
  "properties": {
    "iso:country":"GB",
    "wof:name":"LA4 4FD",
    "wof:placetype":"postalcode"
},
  "geometry": {"coordinates":[-2.87535879555748,54.06737942348674],"type":"Point"}
}