{
  "type": "Feature",
  "properties": {
    "iso:country":"GB",
    "wof:name":"CB2 1QT",
    "wof:placetype":"postalcode"
},
  "geometry": {"coordinates":[0.12202114760324,52.19931680266124],"type":"Point"}
}