{
  "type": "Feature",
  "properties": {
    "iso:country":"GB",
    "wof:name":"NE30 3NA",
    "wof:placetype":"postalcode"
},
  "geometry": {"coordinates":[-1.44382858414851,55.03323225443936],"type":"Point"}
}