{
  "type": "Feature",
  "properties": {
    "date:inception_lower": "2012-02-01",
    "date:inception_upper": "2012-02-01",
    "iso:country": "GB",
    "wof:name": "HU11 4LJ",
    "wof:placetype": "postalcode"
  },
  "geometry": {"coordinates":[-0.19941,53.80237],"type":"Point"}
}
