{
  "type": "Feature",
  "properties": {
    "iso:country":"GB",
    "wof:name":"HU11 4LJ",
    "wof:placetype":"postalcode"
},
  "geometry": {"coordinates":[-0.19940143390639,53.80234970255523],"type":"Point"}
}