{
  "type": "Feature",
  "properties": {
    "iso:country": "GB",
    "wof:name": "CH8 7FD",
    "wof:placetype": "postalcode"
  },
  "geometry": {"coordinates":[-3.221288,53.272678],"type":"Point"}
}
