{
  "type": "Feature",
  "properties": {
    "date:inception_lower": "2016-11-01",
    "date:inception_upper": "2016-11-01",
    "iso:country": "GB",
    "wof:name": "CH8 7FD",
    "wof:placetype": "postalcode"
  },
  "geometry": {"coordinates":[-3.221288,53.272678],"type":"Point"}
}
