{
  "type": "Feature",
  "properties": {
    "iso:country": "GB",
    "wof:name": "KW15 1QZ",
    "wof:placetype": "postalcode"
  },
  "geometry": {"coordinates":[-2.969885,58.985631],"type":"Point"}
}
