{
  "type": "Feature",
  "properties": {
    "iso:country":"GB",
    "wof:name":"KT21 2HN",
    "wof:placetype":"postalcode"
},
  "geometry": {"coordinates":[-0.32079181376068,51.31463621812738],"type":"Point"}
}