{
  "type": "Feature",
  "properties": {
    "iso:country":"GB",
    "wof:name":"BR6 6LH",
    "wof:placetype":"postalcode"
},
  "geometry": {"coordinates":[0.09755019516404,51.35687477954862],"type":"Point"}
}