{
  "type": "Feature",
  "properties": {
    "iso:country":"GB",
    "wof:name":"E2 7QX",
    "wof:placetype":"postalcode"
},
  "geometry": {"coordinates":[-0.07369292832853,51.53011945983842],"type":"Point"}
}