{
  "type": "Feature",
  "properties": {
    "date:inception_lower": "2013-12-01",
    "date:inception_upper": "2013-12-01",
    "iso:country": "GB",
    "wof:name": "CF44 0YZ",
    "wof:placetype": "postalcode"
  },
  "geometry": {"coordinates":[-3.426132,51.723311],"type":"Point"}
}
