{
  "type": "Feature",
  "properties": {
    "iso:country": "GB",
    "wof:name": "CF44 0YZ",
    "wof:placetype": "postalcode"
  },
  "geometry": {"coordinates":[-3.426132,51.723311],"type":"Point"}
}
