{
  "type": "Feature",
  "properties": {
    "iso:country":"GB",
    "wof:name":"CF44 0YZ",
    "wof:placetype":"postalcode"
},
  "geometry": {"coordinates":[-3.42613186343908,51.72331088933512],"type":"Point"}
}