{
  "type": "Feature",
  "properties": {
    "iso:country":"GB",
    "wof:name":"NE9 7NP",
    "wof:placetype":"postalcode"
},
  "geometry": {"coordinates":[-1.54873630769496,54.91981892607238],"type":"Point"}
}