{
  "type": "Feature",
  "properties": {
    "iso:country":"GB",
    "wof:name":"M13 9TD",
    "wof:placetype":"postalcode"
},
  "geometry": {"coordinates":[-2.23013950830791,53.46865145212092],"type":"Point"}
}