{
  "type": "Feature",
  "properties": {
    "iso:country":"GB",
    "wof:name":"LS2 9ER",
    "wof:placetype":"postalcode"
},
  "geometry": {"coordinates":[-1.54901941464642,53.80628852582359],"type":"Point"}
}