{
  "type": "Feature",
  "properties": {
    "date:inception_lower": "1998-06-01",
    "date:inception_upper": "1998-06-01",
    "iso:country": "GB",
    "wof:name": "LS2 9ER",
    "wof:placetype": "postalcode"
  },
  "geometry": {"coordinates":[-1.549024,53.806304],"type":"Point"}
}
