{
  "type": "Feature",
  "properties": {
    "iso:country": "GB",
    "wof:name": "SM5 2RH",
    "wof:placetype": "postalcode"
  },
  "geometry": {"coordinates":[-0.169849,51.37125],"type":"Point"}
}
