{
  "type": "Feature",
  "properties": {
    "iso:country": "GB",
    "wof:name": "SK5 8DQ",
    "wof:placetype": "postalcode"
  },
  "geometry": {"coordinates":[-2.131874,53.424029],"type":"Point"}
}
