{
  "type": "Feature",
  "properties": {
    "iso:country":"GB",
    "wof:name":"PE30 3JB",
    "wof:placetype":"postalcode"
},
  "geometry": {"coordinates":[0.43870964875824,52.77738100264545],"type":"Point"}
}