{
  "type": "Feature",
  "properties": {
    "iso:country":"GB",
    "wof:name":"N14 5JS",
    "wof:placetype":"postalcode"
},
  "geometry": {"coordinates":[-0.14271271515197,51.63410571679506],"type":"Point"}
}