{
  "type": "Feature",
  "properties": {
    "date:inception_lower": "2002-12-01",
    "date:inception_upper": "2002-12-01",
    "iso:country": "GB",
    "wof:name": "ME13 7AU",
    "wof:placetype": "postalcode"
  },
  "geometry": {"coordinates":[0.896355,51.321487],"type":"Point"}
}
