{
  "type": "Feature",
  "properties": {
    "iso:country":"GB",
    "wof:name":"ME13 7AU",
    "wof:placetype":"postalcode"
},
  "geometry": {"coordinates":[0.89617633344368,51.32140687078456],"type":"Point"}
}