{
  "type": "Feature",
  "properties": {
    "iso:country":"GB",
    "wof:name":"MK18 7DF",
    "wof:placetype":"postalcode"
},
  "geometry": {"coordinates":[-0.97117905725004,51.9981663832788],"type":"Point"}
}