{
  "type": "Feature",
  "properties": {
    "iso:country":"GB",
    "wof:name":"SY15 6UF",
    "wof:placetype":"postalcode"
},
  "geometry": {"coordinates":[-3.11011149096297,52.57465198722957],"type":"Point"}
}