{
  "type": "Feature",
  "properties": {
    "iso:country":"GB",
    "wof:name":"SY23 1PS",
    "wof:placetype":"postalcode"
},
  "geometry": {"coordinates":[-4.08460476443806,52.41385163063556],"type":"Point"}
}