{
  "type": "Feature",
  "properties": {
    "iso:country":"GB",
    "wof:name":"LN2 3SY",
    "wof:placetype":"postalcode"
},
  "geometry": {"coordinates":[-0.48275051157259,53.30718631013759],"type":"Point"}
}