{
  "type": "Feature",
  "properties": {
    "date:inception_lower": "1995-01-01",
    "date:inception_upper": "1995-01-01",
    "iso:country": "GB",
    "wof:name": "LN2 3SY",
    "wof:placetype": "postalcode"
  },
  "geometry": {"coordinates":[-0.48275,53.307186],"type":"Point"}
}
