{
  "type": "Feature",
  "properties": {
    "iso:country":"GB",
    "wof:name":"SW13 0AD",
    "wof:placetype":"postalcode"
},
  "geometry": {"coordinates":[-0.24764261748466,51.47140183997433],"type":"Point"}
}