{
  "type": "Feature",
  "properties": {
    "iso:country": "GB",
    "wof:name": "SW13 0AD",
    "wof:placetype": "postalcode"
  },
  "geometry": {"coordinates":[-0.247643,51.471402],"type":"Point"}
}
