{
  "type": "Feature",
  "properties": {
    "iso:country": "GB",
    "wof:name": "CB24 1BD",
    "wof:placetype": "postalcode"
  },
  "geometry": {"coordinates":[0.052428,52.288647],"type":"Point"}
}
