{
  "type": "Feature",
  "properties": {
    "iso:country":"GB",
    "wof:name":"EX39 5ES",
    "wof:placetype":"postalcode"
},
  "geometry": {"coordinates":[-4.26998013385952,50.97961952135781],"type":"Point"}
}