{
  "type": "Feature",
  "properties": {
    "iso:country": "GB",
    "wof:name": "MK43 0HF",
    "wof:placetype": "postalcode"
  },
  "geometry": {"coordinates":[-0.593593,52.076615],"type":"Point"}
}
