{
  "type": "Feature",
  "properties": {
    "iso:country":"GB",
    "wof:name":"NW10 5RA",
    "wof:placetype":"postalcode"
},
  "geometry": {"coordinates":[-0.21994918405115,51.53253789682152],"type":"Point"}
}