{
  "type": "Feature",
  "properties": {
    "iso:country": "GB",
    "wof:name": "IV30 5UJ",
    "wof:placetype": "postalcode"
  },
  "geometry": {"coordinates":[-3.489908,57.700715],"type":"Point"}
}
