{
  "type": "Feature",
  "properties": {
    "iso:country":"GB",
    "wof:name":"NE66 1BD",
    "wof:placetype":"postalcode"
},
  "geometry": {"coordinates":[-1.70161048687231,55.40407589834071],"type":"Point"}
}