{
  "type": "Feature",
  "properties": {
    "iso:country":"GB",
    "wof:name":"LL58 8RU",
    "wof:placetype":"postalcode"
},
  "geometry": {"coordinates":[-4.07103197435921,53.29769601071082],"type":"Point"}
}