{
  "type": "Feature",
  "properties": {
    "iso:country":"GB",
    "wof:name":"EN7 5LY",
    "wof:placetype":"postalcode"
},
  "geometry": {"coordinates":[-0.06510164833057,51.69955779213286],"type":"Point"}
}