{
  "type": "Feature",
  "properties": {
    "iso:country":"GB",
    "wof:name":"HU15 2UA",
    "wof:placetype":"postalcode"
},
  "geometry": {"coordinates":[-0.74007066250982,53.75346462410862],"type":"Point"}
}