{
  "type": "Feature",
  "properties": {
    "iso:country":"GB",
    "wof:name":"SS6 8AF",
    "wof:placetype":"postalcode"
},
  "geometry": {"coordinates":[0.60603474250429,51.59109089363551],"type":"Point"}
}