{
  "type": "Feature",
  "properties": {
    "date:inception_lower": "1996-12-01",
    "date:inception_upper": "1996-12-01",
    "iso:country": "GB",
    "wof:name": "SK12 2RA",
    "wof:placetype": "postalcode"
  },
  "geometry": {"coordinates":[-2.012235,53.358132],"type":"Point"}
}
