{
  "type": "Feature",
  "properties": {
    "date:inception_lower": "1980-01-01",
    "date:inception_upper": "1980-01-01",
    "iso:country": "GB",
    "wof:name": "CA24 3JF",
    "wof:placetype": "postalcode"
  },
  "geometry": {"coordinates":[-3.53882,54.513386],"type":"Point"}
}
