{
  "type": "Feature",
  "properties": {
    "iso:country":"GB",
    "wof:name":"LU3 3AD",
    "wof:placetype":"postalcode"
},
  "geometry": {"coordinates":[-0.47043810302,51.915401605001],"type":"Point"}
}