{
  "type": "Feature",
  "properties": {
    "date:inception_lower": "1980-01-01",
    "date:inception_upper": "1980-01-01",
    "iso:country": "GB",
    "wof:name": "KT18 6BB",
    "wof:placetype": "postalcode"
  },
  "geometry": {"coordinates":[-0.260285,51.298688],"type":"Point"}
}
