{
  "type": "Feature",
  "properties": {
    "iso:country":"GB",
    "wof:name":"KT18 6BB",
    "wof:placetype":"postalcode"
},
  "geometry": {"coordinates":[-0.26030942654322,51.298690633867],"type":"Point"}
}