{
  "type": "Feature",
  "properties": {
    "iso:country":"GB",
    "wof:name":"YO8 3YW",
    "wof:placetype":"postalcode"
},
  "geometry": {"coordinates":[-1.09863413669641,53.81455428366911],"type":"Point"}
}