{
  "type": "Feature",
  "properties": {
    "iso:country":"GB",
    "wof:name":"E13 8PB",
    "wof:placetype":"postalcode"
},
  "geometry": {"coordinates":[0.02822880484361,51.51917487369845],"type":"Point"}
}