{
  "type": "Feature",
  "properties": {
    "date:inception_lower": "2000-10-01",
    "date:inception_upper": "2000-10-01",
    "iso:country": "GB",
    "wof:name": "OX27 8DN",
    "wof:placetype": "postalcode"
  },
  "geometry": {"coordinates":[-1.11786,51.956559],"type":"Point"}
}
