{
  "type": "Feature",
  "properties": {
    "iso:country":"GB",
    "wof:name":"OX27 8DN",
    "wof:placetype":"postalcode"
},
  "geometry": {"coordinates":[-1.11786026639881,51.95655883894556],"type":"Point"}
}