{
  "type": "Feature",
  "properties": {
    "iso:country": "GB",
    "wof:name": "BA7 7EB",
    "wof:placetype": "postalcode"
  },
  "geometry": {"coordinates":[-2.519085,51.084885],"type":"Point"}
}
