{
  "type": "Feature",
  "properties": {
    "date:inception_lower":"2016-09-01",
    "date:inception_upper":"2016-09-30",
    "iso:country":"GB",
    "wof:name":"WR1 1WH",
    "wof:placetype":"postalcode"
},
  "geometry": {"coordinates":[-2.216947,52.196683],"type":"Point"}
}