{
  "type": "Feature",
  "properties": {
    "iso:country": "GB",
    "wof:name": "B74 3NY",
    "wof:placetype": "postalcode"
  },
  "geometry": {"coordinates":[-1.890707,52.58306],"type":"Point"}
}
