{
  "type": "Feature",
  "properties": {
    "iso:country":"GB",
    "wof:name":"HX3 8BQ",
    "wof:placetype":"postalcode"
},
  "geometry": {"coordinates":[-1.80334150744658,53.72369157696878],"type":"Point"}
}