{
  "type": "Feature",
  "properties": {
    "iso:country":"GB",
    "wof:name":"B79 0NB",
    "wof:placetype":"postalcode"
},
  "geometry": {"coordinates":[-1.59254049591591,52.66307757086707],"type":"Point"}
}