{
  "type": "Feature",
  "properties": {
    "iso:country": "GB",
    "wof:name": "B79 0NB",
    "wof:placetype": "postalcode"
  },
  "geometry": {"coordinates":[-1.59254,52.663078],"type":"Point"}
}
