{
  "type": "Feature",
  "properties": {
    "date:inception_lower": "1980-01-01",
    "date:inception_upper": "1980-01-01",
    "iso:country": "GB",
    "wof:name": "BR8 8JN",
    "wof:placetype": "postalcode"
  },
  "geometry": {"coordinates":[0.161457,51.383196],"type":"Point"}
}
