{
  "type": "Feature",
  "properties": {
    "iso:country":"GB",
    "wof:name":"BR8 8JN",
    "wof:placetype":"postalcode"
},
  "geometry": {"coordinates":[0.16145699509531,51.38319568369774],"type":"Point"}
}