{
  "type": "Feature",
  "properties": {
    "date:inception_lower":"1980-01-01",
    "date:inception_upper":"1980-01-31",
    "iso:country":"GB",
    "wof:name":"NW2 5QS",
    "wof:placetype":"postalcode"
},
  "geometry": {"coordinates":[-0.220369,51.548389],"type":"Point"}
}