{
  "type": "Feature",
  "properties": {
    "iso:country":"GB",
    "wof:name":"NW2 5QS",
    "wof:placetype":"postalcode"
},
  "geometry": {"coordinates":[-0.22036904548423,51.54838883891504],"type":"Point"}
}