{
  "type": "Feature",
  "properties": {
    "date:inception_lower":"1991-09-01",
    "date:inception_upper":"1991-09-30",
    "iso:country":"GB",
    "wof:name":"DN31 1RY",
    "wof:placetype":"postalcode"
},
  "geometry": {"coordinates":[-0.091524,53.568579],"type":"Point"}
}