{
  "type": "Feature",
  "properties": {
    "iso:country":"GB",
    "wof:name":"DN31 1RY",
    "wof:placetype":"postalcode"
},
  "geometry": {"coordinates":[-0.09152363894267,53.56857853938531],"type":"Point"}
}