{
  "type": "Feature",
  "properties": {
    "iso:country": "GB",
    "wof:name": "SK16 4RE",
    "wof:placetype": "postalcode"
  },
  "geometry": {"coordinates":[-2.099886,53.471032],"type":"Point"}
}
