{
  "type": "Feature",
  "properties": {
    "date:inception_lower": "2012-06-01",
    "date:inception_upper": "2012-06-01",
    "iso:country": "GB",
    "wof:name": "WA16 9TD",
    "wof:placetype": "postalcode"
  },
  "geometry": {"coordinates":[-2.394621,53.270057],"type":"Point"}
}
