{
  "type": "Feature",
  "properties": {
    "iso:country":"GB",
    "wof:name":"WA16 9TD",
    "wof:placetype":"postalcode"
},
  "geometry": {"coordinates":[-2.39462113877081,53.27005702031021],"type":"Point"}
}