{
  "type": "Feature",
  "properties": {
    "iso:country": "GB",
    "wof:name": "ML6 8NH",
    "wof:placetype": "postalcode"
  },
  "geometry": {"coordinates":[-3.935529,55.861416],"type":"Point"}
}
