{
  "type": "Feature",
  "properties": {
    "date:inception_lower":"1980-01-01",
    "date:inception_upper":"1980-01-31",
    "iso:country":"GB",
    "wof:name":"SA6 8LR",
    "wof:placetype":"postalcode"
},
  "geometry": {"coordinates":[-3.931151,51.652859],"type":"Point"}
}