{
  "type": "Feature",
  "properties": {
    "iso:country":"GB",
    "wof:name":"SA6 8LR",
    "wof:placetype":"postalcode"
},
  "geometry": {"coordinates":[-3.93115085915227,51.65285942578815],"type":"Point"}
}