{
  "type": "Feature",
  "properties": {
    "date:inception_lower": "2000-06-01",
    "date:inception_upper": "2000-06-01",
    "iso:country": "GB",
    "wof:name": "HP4 2WQ",
    "wof:placetype": "postalcode"
  },
  "geometry": {"coordinates":[-0.555693,51.758199],"type":"Point"}
}
