{
  "type": "Feature",
  "properties": {
    "iso:country":"GB",
    "wof:name":"NR19 2LX",
    "wof:placetype":"postalcode"
},
  "geometry": {"coordinates":[0.84997882998569,52.67932717146098],"type":"Point"}
}