{
  "type": "Feature",
  "properties": {
    "date:inception_lower":"1992-08-01",
    "date:inception_upper":"1992-08-31",
    "iso:country":"GB",
    "wof:name":"NR33 8TN",
    "wof:placetype":"postalcode"
},
  "geometry": {"coordinates":[1.705885,52.451659],"type":"Point"}
}