{
  "type": "Feature",
  "properties": {
    "iso:country": "GB",
    "wof:name": "NR33 8TN",
    "wof:placetype": "postalcode"
  },
  "geometry": {"coordinates":[1.705885,52.451659],"type":"Point"}
}
