{
  "type": "Feature",
  "properties": {
    "iso:country":"GB",
    "wof:name":"OL1 3AA",
    "wof:placetype":"postalcode"
},
  "geometry": {"coordinates":[-2.11499462476426,53.54258579621699],"type":"Point"}
}