{
  "type": "Feature",
  "properties": {
    "iso:country": "GB",
    "wof:name": "SA1 8RF",
    "wof:placetype": "postalcode"
  },
  "geometry": {"coordinates":[-3.917965,51.620555],"type":"Point"}
}
