{
  "type": "Feature",
  "properties": {
    "iso:country":"GB",
    "wof:name":"B97 5DN",
    "wof:placetype":"postalcode"
},
  "geometry": {"coordinates":[-1.94949326372785,52.28890286172755],"type":"Point"}
}