{
  "type": "Feature",
  "properties": {
    "date:inception_lower": "1984-10-01",
    "date:inception_upper": "1984-10-01",
    "iso:country": "GB",
    "wof:name": "SP7 8PS",
    "wof:placetype": "postalcode"
  },
  "geometry": {"coordinates":[-2.187135,51.011001],"type":"Point"}
}
