{
  "type": "Feature",
  "properties": {
    "iso:country":"GB",
    "wof:name":"SP7 8PS",
    "wof:placetype":"postalcode"
},
  "geometry": {"coordinates":[-2.1871345920389,51.01100113845519],"type":"Point"}
}