{
  "type": "Feature",
  "properties": {
    "iso:country": "GB",
    "wof:name": "PR4 5ST",
    "wof:placetype": "postalcode"
  },
  "geometry": {"coordinates":[-2.762444,53.736049],"type":"Point"}
}
