{
  "type": "Feature",
  "properties": {
    "iso:country":"GB",
    "wof:name":"PR4 5ST",
    "wof:placetype":"postalcode"
},
  "geometry": {"coordinates":[-2.76244423813032,53.73604920439629],"type":"Point"}
}