{
  "type": "Feature",
  "properties": {
    "iso:country":"GB",
    "wof:name":"HP7 0HJ",
    "wof:placetype":"postalcode"
},
  "geometry": {"coordinates":[-0.61384283607487,51.66570880111583],"type":"Point"}
}