{
  "type": "Feature",
  "properties": {
    "iso:country": "GB",
    "wof:name": "HP7 0HJ",
    "wof:placetype": "postalcode"
  },
  "geometry": {"coordinates":[-0.613821,51.665712],"type":"Point"}
}
