{
  "type": "Feature",
  "properties": {
    "date:inception_lower": "1996-06-01",
    "date:inception_upper": "1996-06-01",
    "iso:country": "GB",
    "wof:name": "AB41 7EJ",
    "wof:placetype": "postalcode"
  },
  "geometry": {"coordinates":[-2.232293,57.420674],"type":"Point"}
}
