{
  "type": "Feature",
  "properties": {
    "iso:country": "GB",
    "wof:name": "CF11 6DW",
    "wof:placetype": "postalcode"
  },
  "geometry": {"coordinates":[-3.196238,51.479413],"type":"Point"}
}
