{
  "type": "Feature",
  "properties": {
    "iso:country":"GB",
    "wof:name":"CF11 6DW",
    "wof:placetype":"postalcode"
},
  "geometry": {"coordinates":[-3.19623756195364,51.47941291604013],"type":"Point"}
}