{
  "type": "Feature",
  "properties": {
    "iso:country":"GB",
    "wof:name":"BR1 5QP",
    "wof:placetype":"postalcode"
},
  "geometry": {"coordinates":[-0.0084620008098,51.42446282044236],"type":"Point"}
}