{
  "type": "Feature",
  "properties": {
    "date:inception_lower":"1980-01-01",
    "date:inception_upper":"1980-01-31",
    "iso:country":"GB",
    "wof:name":"BR1 5QP",
    "wof:placetype":"postalcode"
},
  "geometry": {"coordinates":[-0.008462,51.424463],"type":"Point"}
}