{
  "type": "Feature",
  "properties": {
    "iso:country":"GB",
    "wof:name":"N19 3TW",
    "wof:placetype":"postalcode"
},
  "geometry": {"coordinates":[-0.13526548724082,51.57078915611125],"type":"Point"}
}