{
  "type": "Feature",
  "properties": {
    "iso:country": "GB",
    "wof:name": "BD15 0NF",
    "wof:placetype": "postalcode"
  },
  "geometry": {"coordinates":[-1.857491,53.817855],"type":"Point"}
}
