{
  "type": "Feature",
  "properties": {
    "date:inception_lower":"1986-04-01",
    "date:inception_upper":"1986-04-30",
    "iso:country":"GB",
    "wof:name":"CM11 2JW",
    "wof:placetype":"postalcode"
},
  "geometry": {"coordinates":[0.437668,51.626339],"type":"Point"}
}