{
  "type": "Feature",
  "properties": {
    "iso:country": "GB",
    "wof:name": "CM11 2JW",
    "wof:placetype": "postalcode"
  },
  "geometry": {"coordinates":[0.437668,51.626339],"type":"Point"}
}
