{
  "type": "Feature",
  "properties": {
    "date:inception_lower": "1980-01-01",
    "date:inception_upper": "1980-01-01",
    "iso:country": "GB",
    "wof:name": "NE22 5DN",
    "wof:placetype": "postalcode"
  },
  "geometry": {"coordinates":[-1.592659,55.130781],"type":"Point"}
}
