{
  "type": "Feature",
  "properties": {
    "iso:country":"GB",
    "wof:name":"NE22 5DN",
    "wof:placetype":"postalcode"
},
  "geometry": {"coordinates":[-1.59265895824745,55.13078109002036],"type":"Point"}
}