{
  "type": "Feature",
  "properties": {
    "iso:country":"GB",
    "wof:name":"AL4 9LE",
    "wof:placetype":"postalcode"
},
  "geometry": {"coordinates":[-0.31108734919175,51.77553962394894],"type":"Point"}
}