{
  "type": "Feature",
  "properties": {
    "iso:country":"GB",
    "wof:name":"SY11 3BE",
    "wof:placetype":"postalcode"
},
  "geometry": {"coordinates":[-3.0007072827826,52.92500225772356],"type":"Point"}
}