{
  "type": "Feature",
  "properties": {
    "date:inception_lower": "1997-06-01",
    "date:inception_upper": "1997-06-01",
    "iso:country": "GB",
    "wof:name": "CV21 3HU",
    "wof:placetype": "postalcode"
  },
  "geometry": {"coordinates":[-1.254233,52.376356],"type":"Point"}
}
