{
  "type": "Feature",
  "properties": {
    "iso:country": "GB",
    "wof:name": "CV21 3HU",
    "wof:placetype": "postalcode"
  },
  "geometry": {"coordinates":[-1.254233,52.376356],"type":"Point"}
}
