{
  "type": "Feature",
  "properties": {
    "iso:country":"GB",
    "wof:name":"EX4 6QP",
    "wof:placetype":"postalcode"
},
  "geometry": {"coordinates":[-3.52286757663691,50.72926292887048],"type":"Point"}
}