{
  "type": "Feature",
  "properties": {
    "iso:country": "GB",
    "wof:name": "EX4 6QP",
    "wof:placetype": "postalcode"
  },
  "geometry": {"coordinates":[-3.522868,50.729263],"type":"Point"}
}
