{
  "type": "Feature",
  "properties": {
    "iso:country": "GB",
    "wof:name": "CF36 3EB",
    "wof:placetype": "postalcode"
  },
  "geometry": {"coordinates":[-3.705737,51.481784],"type":"Point"}
}
