{
  "type": "Feature",
  "properties": {
    "iso:country":"GB",
    "wof:name":"CF36 3EB",
    "wof:placetype":"postalcode"
},
  "geometry": {"coordinates":[-3.7057367858911,51.4817843771187],"type":"Point"}
}