{
  "type": "Feature",
  "properties": {
    "iso:country":"GB",
    "wof:name":"SP8 5EH",
    "wof:placetype":"postalcode"
},
  "geometry": {"coordinates":[-2.3369911238223,51.00936982385117],"type":"Point"}
}