{
  "type": "Feature",
  "properties": {
    "iso:country": "GB",
    "wof:name": "SP8 5EH",
    "wof:placetype": "postalcode"
  },
  "geometry": {"coordinates":[-2.336322,51.010013],"type":"Point"}
}
