{
  "type": "Feature",
  "properties": {
    "iso:country":"GB",
    "wof:name":"CO16 0BB",
    "wof:placetype":"postalcode"
},
  "geometry": {"coordinates":[1.17880890215995,51.8743547687333],"type":"Point"}
}