{
  "type": "Feature",
  "properties": {
    "iso:country":"GB",
    "wof:name":"KT18 7LL",
    "wof:placetype":"postalcode"
},
  "geometry": {"coordinates":[-0.2898722236479,51.32650866716502],"type":"Point"}
}