{
  "type": "Feature",
  "properties": {
    "iso:country": "GB",
    "wof:name": "LL54 5UW",
    "wof:placetype": "postalcode"
  },
  "geometry": {"coordinates":[-4.295986,53.106187],"type":"Point"}
}
