{
  "type": "Feature",
  "properties": {
    "iso:country":"GB",
    "wof:name":"LL54 5UW",
    "wof:placetype":"postalcode"
},
  "geometry": {"coordinates":[-4.29598647150404,53.10618740745938],"type":"Point"}
}