{
  "type": "Feature",
  "properties": {
    "date:inception_lower": "1980-01-01",
    "date:inception_upper": "1980-01-01",
    "iso:country": "GB",
    "wof:name": "NE32 4BX",
    "wof:placetype": "postalcode"
  },
  "geometry": {"coordinates":[-1.482628,54.960426],"type":"Point"}
}
