{
  "type": "Feature",
  "properties": {
    "iso:country":"GB",
    "wof:name":"NE32 4BX",
    "wof:placetype":"postalcode"
},
  "geometry": {"coordinates":[-1.48262755233903,54.96042565410284],"type":"Point"}
}