{
  "type": "Feature",
  "properties": {
    "iso:country":"GB",
    "wof:name":"FK17 8BG",
    "wof:placetype":"postalcode"
},
  "geometry": {"coordinates":[-4.20984849379618,56.24241305054374],"type":"Point"}
}