{
  "type": "Feature",
  "properties": {
    "iso:country":"GB",
    "wof:name":"GU8 5JT",
    "wof:placetype":"postalcode"
},
  "geometry": {"coordinates":[-0.64321840961474,51.17043158999446],"type":"Point"}
}