{
  "type": "Feature",
  "properties": {
    "iso:country": "GB",
    "wof:name": "GU8 5JT",
    "wof:placetype": "postalcode"
  },
  "geometry": {"coordinates":[-0.643218,51.170432],"type":"Point"}
}
