{
  "type": "Feature",
  "properties": {
    "iso:country":"GB",
    "wof:name":"NR32 1DT",
    "wof:placetype":"postalcode"
},
  "geometry": {"coordinates":[1.75279680983944,52.47507555522947],"type":"Point"}
}