{
  "type": "Feature",
  "properties": {
    "iso:country": "GB",
    "wof:name": "NR32 1DT",
    "wof:placetype": "postalcode"
  },
  "geometry": {"coordinates":[1.752797,52.475076],"type":"Point"}
}
