{
  "type": "Feature",
  "properties": {
    "iso:country": "GB",
    "wof:name": "SO17 2AQ",
    "wof:placetype": "postalcode"
  },
  "geometry": {"coordinates":[-1.389709,50.927557],"type":"Point"}
}
