{
  "type": "Feature",
  "properties": {
    "date:inception_lower":"1980-01-01",
    "date:inception_upper":"1980-01-31",
    "iso:country":"GB",
    "wof:name":"AL5 1HJ",
    "wof:placetype":"postalcode"
},
  "geometry": {"coordinates":[-0.334493,51.804396],"type":"Point"}
}