{
  "type": "Feature",
  "properties": {
    "iso:country":"GB",
    "wof:name":"AL5 1HJ",
    "wof:placetype":"postalcode"
},
  "geometry": {"coordinates":[-0.33449259725098,51.80439587847538],"type":"Point"}
}