{
  "type": "Feature",
  "properties": {
    "date:inception_lower":"2003-09-01",
    "date:inception_upper":"2003-09-30",
    "iso:country":"GB",
    "wof:name":"SE16 2RS",
    "wof:placetype":"postalcode"
},
  "geometry": {"coordinates":[-0.048855,51.488541],"type":"Point"}
}