{
  "type": "Feature",
  "properties": {
    "iso:country":"GB",
    "wof:name":"SE16 2RS",
    "wof:placetype":"postalcode"
},
  "geometry": {"coordinates":[-0.04885544438148,51.4885407350889],"type":"Point"}
}