{
  "type": "Feature",
  "properties": {
    "iso:country":"GB",
    "wof:name":"WN8 9PA",
    "wof:placetype":"postalcode"
},
  "geometry": {"coordinates":[-2.76459807206909,53.52623620414261],"type":"Point"}
}