{
  "type": "Feature",
  "properties": {
    "iso:country":"GB",
    "wof:name":"CW10 9GA",
    "wof:placetype":"postalcode"
},
  "geometry": {"coordinates":[-2.45103782281862,53.19392769521773],"type":"Point"}
}