{
  "type": "Feature",
  "properties": {
    "date:inception_lower": "2009-01-01",
    "date:inception_upper": "2009-01-01",
    "iso:country": "GB",
    "wof:name": "CW10 9GA",
    "wof:placetype": "postalcode"
  },
  "geometry": {"coordinates":[-2.451038,53.193928],"type":"Point"}
}
