{
  "type": "Feature",
  "properties": {
    "iso:country":"GB",
    "wof:name":"IP14 2HF",
    "wof:placetype":"postalcode"
},
  "geometry": {"coordinates":[0.99868305333257,52.14963409288101],"type":"Point"}
}