{
  "type": "Feature",
  "properties": {
    "date:inception_lower": "1980-01-01",
    "date:inception_upper": "1980-01-01",
    "iso:country": "GB",
    "wof:name": "CV8 3BS",
    "wof:placetype": "postalcode"
  },
  "geometry": {"coordinates":[-1.482779,52.348494],"type":"Point"}
}
