{
  "type": "Feature",
  "properties": {
    "iso:country": "GB",
    "wof:name": "CV8 3BS",
    "wof:placetype": "postalcode"
  },
  "geometry": {"coordinates":[-1.482779,52.348494],"type":"Point"}
}
