{
  "type": "Feature",
  "properties": {
    "iso:country":"GB",
    "wof:name":"CV8 3BS",
    "wof:placetype":"postalcode"
},
  "geometry": {"coordinates":[-1.48277912538486,52.34849363621456],"type":"Point"}
}