{
  "type": "Feature",
  "properties": {
    "iso:country":"GB",
    "wof:name":"WD23 3AE",
    "wof:placetype":"postalcode"
},
  "geometry": {"coordinates":[-0.36776292979819,51.64607337095776],"type":"Point"}
}