{
  "type": "Feature",
  "properties": {
    "date:inception_lower":"2015-03-01",
    "date:inception_upper":"2015-03-31",
    "iso:country":"GB",
    "wof:name":"NN8 9TE",
    "wof:placetype":"postalcode"
},
  "geometry": {"coordinates":[-0.69095,52.299261],"type":"Point"}
}