{
  "type": "Feature",
  "properties": {
    "date:inception_lower": "2015-03-01",
    "date:inception_upper": "2015-03-01",
    "iso:country": "GB",
    "wof:name": "NN8 9TE",
    "wof:placetype": "postalcode"
  },
  "geometry": {"coordinates":[-0.691067,52.299271],"type":"Point"}
}
