{
  "type": "Feature",
  "properties": {
    "date:inception_lower": "1987-04-01",
    "date:inception_upper": "1987-04-01",
    "iso:country": "GB",
    "wof:name": "CM23 2TF",
    "wof:placetype": "postalcode"
  },
  "geometry": {"coordinates":[0.159238,51.879302],"type":"Point"}
}
