{
  "type": "Feature",
  "properties": {
    "iso:country":"GB",
    "wof:name":"NP4 5LA",
    "wof:placetype":"postalcode"
},
  "geometry": {"coordinates":[-3.03370588030677,51.6964167808785],"type":"Point"}
}