{
  "type": "Feature",
  "properties": {
    "iso:country": "GB",
    "wof:name": "NP4 5LA",
    "wof:placetype": "postalcode"
  },
  "geometry": {"coordinates":[-3.033706,51.696417],"type":"Point"}
}
