{
  "type": "Feature",
  "properties": {
    "iso:country":"GB",
    "wof:name":"AB11 5DB",
    "wof:placetype":"postalcode"
},
  "geometry": {"coordinates":[-2.084346572402,57.14586006094062],"type":"Point"}
}