{
  "type": "Feature",
  "properties": {
    "date:inception_lower": "1980-01-01",
    "date:inception_upper": "1980-01-01",
    "iso:country": "GB",
    "wof:name": "GU9 9JU",
    "wof:placetype": "postalcode"
  },
  "geometry": {"coordinates":[-0.766031,51.228893],"type":"Point"}
}
