{
  "type": "Feature",
  "properties": {
    "iso:country": "GB",
    "wof:name": "GU9 9JU",
    "wof:placetype": "postalcode"
  },
  "geometry": {"coordinates":[-0.766031,51.228893],"type":"Point"}
}
