{
  "type": "Feature",
  "properties": {
    "iso:country":"GB",
    "wof:name":"GU9 9JU",
    "wof:placetype":"postalcode"
},
  "geometry": {"coordinates":[-0.76603105215047,51.22889291273931],"type":"Point"}
}