{
  "type": "Feature",
  "properties": {
    "iso:country":"GB",
    "wof:name":"GU47 0PZ",
    "wof:placetype":"postalcode"
},
  "geometry": {"coordinates":[-0.78150485059953,51.34247407346734],"type":"Point"}
}