{
  "type": "Feature",
  "properties": {
    "date:inception_lower": "1996-06-01",
    "date:inception_upper": "1996-06-01",
    "iso:country": "GB",
    "wof:name": "GU47 0PZ",
    "wof:placetype": "postalcode"
  },
  "geometry": {"coordinates":[-0.781505,51.342474],"type":"Point"}
}
