{
  "type": "Feature",
  "properties": {
    "date:inception_lower": "1992-08-01",
    "date:inception_upper": "1992-08-01",
    "iso:country": "GB",
    "wof:name": "LN4 4FB",
    "wof:placetype": "postalcode"
  },
  "geometry": {"coordinates":[-0.166817,53.102197],"type":"Point"}
}
