{
  "type": "Feature",
  "properties": {
    "iso:country": "GB",
    "wof:name": "LN4 4FB",
    "wof:placetype": "postalcode"
  },
  "geometry": {"coordinates":[-0.166817,53.102197],"type":"Point"}
}
