{
  "type": "Feature",
  "properties": {
    "date:inception_lower": "1994-05-01",
    "date:inception_upper": "1994-05-01",
    "iso:country": "GB",
    "wof:name": "DN5 7XY",
    "wof:placetype": "postalcode"
  },
  "geometry": {"coordinates":[-1.158455,53.549714],"type":"Point"}
}
