{
  "type": "Feature",
  "properties": {
    "iso:country":"GB",
    "wof:name":"DN5 7XY",
    "wof:placetype":"postalcode"
},
  "geometry": {"coordinates":[-1.1584549828194,53.54971358805508],"type":"Point"}
}