{
  "type": "Feature",
  "properties": {
    "iso:country":"GB",
    "wof:name":"YO10 3HY",
    "wof:placetype":"postalcode"
},
  "geometry": {"coordinates":[-1.05508581837058,53.95303294323884],"type":"Point"}
}