{
  "type": "Feature",
  "properties": {
    "iso:country":"GB",
    "wof:name":"RM18 8RW",
    "wof:placetype":"postalcode"
},
  "geometry": {"coordinates":[0.41993083577553,51.48324637821899],"type":"Point"}
}