{
  "type": "Feature",
  "properties": {
    "iso:country":"GB",
    "wof:name":"E8 1FP",
    "wof:placetype":"postalcode"
},
  "geometry": {"coordinates":[-0.05883676627486,51.54991898059444],"type":"Point"}
}