{
  "type": "Feature",
  "properties": {
    "date:inception_lower": "1980-01-01",
    "date:inception_upper": "1980-01-01",
    "iso:country": "GB",
    "wof:name": "NG17 8DB",
    "wof:placetype": "postalcode"
  },
  "geometry": {"coordinates":[-1.252701,53.099906],"type":"Point"}
}
