{
  "type": "Feature",
  "properties": {
    "iso:country": "GB",
    "wof:name": "NG17 8DB",
    "wof:placetype": "postalcode"
  },
  "geometry": {"coordinates":[-1.252701,53.099906],"type":"Point"}
}
