{
  "type": "Feature",
  "properties": {
    "iso:country":"GB",
    "wof:name":"NG17 8DB",
    "wof:placetype":"postalcode"
},
  "geometry": {"coordinates":[-1.25270153091082,53.09990618393749],"type":"Point"}
}