{
  "type": "Feature",
  "properties": {
    "iso:country": "GB",
    "wof:name": "CT1 3YB",
    "wof:placetype": "postalcode"
  },
  "geometry": {"coordinates":[1.094927,51.271517],"type":"Point"}
}
