{
  "type": "Feature",
  "properties": {
    "date:inception_lower": "1980-01-01",
    "date:inception_upper": "1980-01-01",
    "iso:country": "GB",
    "wof:name": "SN1 3HE",
    "wof:placetype": "postalcode"
  },
  "geometry": {"coordinates":[-1.774923,51.553465],"type":"Point"}
}
