{
  "type": "Feature",
  "properties": {
    "iso:country": "GB",
    "wof:name": "SN1 3HE",
    "wof:placetype": "postalcode"
  },
  "geometry": {"coordinates":[-1.774923,51.553465],"type":"Point"}
}
