{
  "type": "Feature",
  "properties": {
    "iso:country":"GB",
    "wof:name":"SN1 3HE",
    "wof:placetype":"postalcode"
},
  "geometry": {"coordinates":[-1.77492335335209,51.55346531985857],"type":"Point"}
}