{
  "type": "Feature",
  "properties": {
    "iso:country":"GB",
    "wof:name":"DN9 3AJ",
    "wof:placetype":"postalcode"
},
  "geometry": {"coordinates":[-0.99157638251101,53.49535352334117],"type":"Point"}
}