{
  "type": "Feature",
  "properties": {
    "date:inception_lower":"1980-01-01",
    "date:inception_upper":"1980-01-31",
    "iso:country":"GB",
    "wof:name":"DN9 3AJ",
    "wof:placetype":"postalcode"
},
  "geometry": {"coordinates":[-0.991576,53.495354],"type":"Point"}
}