{
  "type": "Feature",
  "properties": {
    "iso:country": "GB",
    "wof:name": "G71 6TT",
    "wof:placetype": "postalcode"
  },
  "geometry": {"coordinates":[-4.07328,55.832983],"type":"Point"}
}
