{
  "type": "Feature",
  "properties": {
    "iso:country":"GB",
    "wof:name":"G71 6TT",
    "wof:placetype":"postalcode"
},
  "geometry": {"coordinates":[-4.07327960858802,55.83298304005957],"type":"Point"}
}