{
  "type": "Feature",
  "properties": {
    "iso:country": "GB",
    "wof:name": "SN15 4NL",
    "wof:placetype": "postalcode"
  },
  "geometry": {"coordinates":[-2.013751,51.496117],"type":"Point"}
}
