{
  "type": "Feature",
  "properties": {
    "date:inception_lower": "1980-01-01",
    "date:inception_upper": "1980-01-01",
    "iso:country": "GB",
    "wof:name": "SN15 4NL",
    "wof:placetype": "postalcode"
  },
  "geometry": {"coordinates":[-2.013751,51.496117],"type":"Point"}
}
