{
  "type": "Feature",
  "properties": {
    "iso:country":"GB",
    "wof:name":"CH4 7NH",
    "wof:placetype":"postalcode"
},
  "geometry": {"coordinates":[-2.91539840032405,53.1664357330299],"type":"Point"}
}