{
  "type": "Feature",
  "properties": {
    "iso:country": "GB",
    "wof:name": "CH4 7NH",
    "wof:placetype": "postalcode"
  },
  "geometry": {"coordinates":[-2.915398,53.166436],"type":"Point"}
}
