{
  "type": "Feature",
  "properties": {
    "date:inception_lower": "2016-10-01",
    "date:inception_upper": "2016-10-01",
    "iso:country": "GB",
    "wof:name": "ME19 5FU",
    "wof:placetype": "postalcode"
  },
  "geometry": {"coordinates":[0.408224,51.307334],"type":"Point"}
}
