{
  "type": "Feature",
  "properties": {
    "iso:country":"GB",
    "wof:name":"SS16 4JQ",
    "wof:placetype":"postalcode"
},
  "geometry": {"coordinates":[0.48358621991181,51.56518425828759],"type":"Point"}
}