{
  "type": "Feature",
  "properties": {
    "iso:country": "GB",
    "wof:name": "SA4 9JJ",
    "wof:placetype": "postalcode"
  },
  "geometry": {"coordinates":[-3.994994,51.684183],"type":"Point"}
}
