{
  "type": "Feature",
  "properties": {
    "date:inception_lower": "2002-06-01",
    "date:inception_upper": "2002-06-01",
    "iso:country": "GB",
    "wof:name": "SA4 9JJ",
    "wof:placetype": "postalcode"
  },
  "geometry": {"coordinates":[-3.994994,51.684183],"type":"Point"}
}
