{
  "type": "Feature",
  "properties": {
    "date:inception_lower": "1980-01-01",
    "date:inception_upper": "1980-01-01",
    "iso:country": "GB",
    "wof:name": "B68 8BL",
    "wof:placetype": "postalcode"
  },
  "geometry": {"coordinates":[-2.018295,52.476838],"type":"Point"}
}
