{
  "type": "Feature",
  "properties": {
    "iso:country":"GB",
    "wof:name":"B68 8BL",
    "wof:placetype":"postalcode"
},
  "geometry": {"coordinates":[-2.01777110739309,52.47690428948081],"type":"Point"}
}