{
  "type": "Feature",
  "properties": {
    "date:inception_lower": "1980-01-01",
    "date:inception_upper": "1980-01-01",
    "iso:country": "GB",
    "wof:name": "ML5 2DN",
    "wof:placetype": "postalcode"
  },
  "geometry": {"coordinates":[-4.02557,55.867655],"type":"Point"}
}
