{
  "type": "Feature",
  "properties": {
    "iso:country":"GB",
    "wof:name":"ML5 2DN",
    "wof:placetype":"postalcode"
},
  "geometry": {"coordinates":[-4.02583381722957,55.86760076493896],"type":"Point"}
}