{
  "type": "Feature",
  "properties": {
    "date:inception_lower":"2011-07-01",
    "date:inception_upper":"2011-07-31",
    "iso:country":"GB",
    "wof:name":"GL20 7DZ",
    "wof:placetype":"postalcode"
},
  "geometry": {"coordinates":[-2.13924,51.982948],"type":"Point"}
}