{
  "type": "Feature",
  "properties": {
    "iso:country":"GB",
    "wof:name":"SR4 7RJ",
    "wof:placetype":"postalcode"
},
  "geometry": {"coordinates":[-1.41020612075449,54.89887165868512],"type":"Point"}
}