{
  "type": "Feature",
  "properties": {
    "date:inception_lower": "1980-01-01",
    "date:inception_upper": "1980-01-01",
    "iso:country": "GB",
    "wof:name": "BS23 4TL",
    "wof:placetype": "postalcode"
  },
  "geometry": {"coordinates":[-2.97935,51.32172],"type":"Point"}
}
