{
  "type": "Feature",
  "properties": {
    "iso:country":"GB",
    "wof:name":"BS23 4TL",
    "wof:placetype":"postalcode"
},
  "geometry": {"coordinates":[-2.9793502786089,51.3217200560684],"type":"Point"}
}