{
  "type": "Feature",
  "properties": {
    "iso:country": "GB",
    "wof:name": "BN10 7RY",
    "wof:placetype": "postalcode"
  },
  "geometry": {"coordinates":[-0.004507,50.801607],"type":"Point"}
}
