{
  "type": "Feature",
  "properties": {
    "iso:country":"GB",
    "wof:name":"KT3 4SR",
    "wof:placetype":"postalcode"
},
  "geometry": {"coordinates":[-0.26007756368866,51.41550996567538],"type":"Point"}
}