{
  "type": "Feature",
  "properties": {
    "iso:country":"GB",
    "wof:name":"KW1 5SR",
    "wof:placetype":"postalcode"
},
  "geometry": {"coordinates":[-3.11244739697312,58.44157648719728],"type":"Point"}
}