{
  "type": "Feature",
  "properties": {
    "iso:country":"GB",
    "wof:name":"BB1 2PJ",
    "wof:placetype":"postalcode"
},
  "geometry": {"coordinates":[-2.42407167996901,53.72169907409049],"type":"Point"}
}