{
  "type": "Feature",
  "properties": {
    "iso:country":"GB",
    "wof:name":"SL5 7QW",
    "wof:placetype":"postalcode"
},
  "geometry": {"coordinates":[-0.68407300002158,51.40969780762128],"type":"Point"}
}