{
  "type": "Feature",
  "properties": {
    "date:inception_lower": "2007-02-01",
    "date:inception_upper": "2007-02-01",
    "iso:country": "GB",
    "wof:name": "SL5 7QW",
    "wof:placetype": "postalcode"
  },
  "geometry": {"coordinates":[-0.684676,51.409606],"type":"Point"}
}
