{
  "type": "Feature",
  "properties": {
    "iso:country":"GB",
    "wof:name":"BB2 6JD",
    "wof:placetype":"postalcode"
},
  "geometry": {"coordinates":[-2.50966603603863,53.75318346550142],"type":"Point"}
}