{
  "type": "Feature",
  "properties": {
    "iso:country":"GB",
    "wof:name":"SG19 1QU",
    "wof:placetype":"postalcode"
},
  "geometry": {"coordinates":[-0.28431567010396,52.1327440513522],"type":"Point"}
}