{
  "type": "Feature",
  "properties": {
    "iso:country":"GB",
    "wof:name":"HA3 8AB",
    "wof:placetype":"postalcode"
},
  "geometry": {"coordinates":[-0.32186469682043,51.58008932185285],"type":"Point"}
}