{
  "type": "Feature",
  "properties": {
    "date:inception_lower": "1980-01-01",
    "date:inception_upper": "1980-01-01",
    "iso:country": "GB",
    "wof:name": "HA3 8AB",
    "wof:placetype": "postalcode"
  },
  "geometry": {"coordinates":[-0.32177,51.58009],"type":"Point"}
}
