{
  "type": "Feature",
  "properties": {
    "iso:country":"GB",
    "wof:name":"DA12 5JQ",
    "wof:placetype":"postalcode"
},
  "geometry": {"coordinates":[0.37752273878087,51.41170933750435],"type":"Point"}
}