{
  "type": "Feature",
  "properties": {
    "date:inception_lower":"1981-06-01",
    "date:inception_upper":"1981-06-30",
    "iso:country":"GB",
    "wof:name":"DA12 5JQ",
    "wof:placetype":"postalcode"
},
  "geometry": {"coordinates":[0.377523,51.411709],"type":"Point"}
}