{
  "type": "Feature",
  "properties": {
    "iso:country":"GB",
    "wof:name":"NN8 6UW",
    "wof:placetype":"postalcode"
},
  "geometry": {"coordinates":[-0.73251589120807,52.31147839242397],"type":"Point"}
}