{
  "type": "Feature",
  "properties": {
    "iso:country":"GB",
    "wof:name":"SA31 2NW",
    "wof:placetype":"postalcode"
},
  "geometry": {"coordinates":[-4.29847354165528,51.85289498858029],"type":"Point"}
}