{
  "type": "Feature",
  "properties": {
    "iso:country": "GB",
    "wof:name": "TR8 4HX",
    "wof:placetype": "postalcode"
  },
  "geometry": {"coordinates":[-4.976723,50.423561],"type":"Point"}
}
