{
  "type": "Feature",
  "properties": {
    "date:inception_lower":"1980-01-01",
    "date:inception_upper":"1980-01-31",
    "iso:country":"GB",
    "wof:name":"TR8 4HX",
    "wof:placetype":"postalcode"
},
  "geometry": {"coordinates":[-4.976723,50.423561],"type":"Point"}
}