{
  "type": "Feature",
  "properties": {
    "iso:country":"GB",
    "wof:name":"TR8 4HX",
    "wof:placetype":"postalcode"
},
  "geometry": {"coordinates":[-4.97672257821461,50.42356113131006],"type":"Point"}
}