{
  "type": "Feature",
  "properties": {
    "iso:country": "GB",
    "wof:name": "BS37 8TF",
    "wof:placetype": "postalcode"
  },
  "geometry": {"coordinates":[-2.421104,51.528351],"type":"Point"}
}
