{
  "type": "Feature",
  "properties": {
    "iso:country": "GB",
    "wof:name": "RG12 0TW",
    "wof:placetype": "postalcode"
  },
  "geometry": {"coordinates":[-0.738361,51.397877],"type":"Point"}
}
