{
  "type": "Feature",
  "properties": {
    "iso:country":"GB",
    "wof:name":"TF2 6PY",
    "wof:placetype":"postalcode"
},
  "geometry": {"coordinates":[-2.45450201055092,52.70783520510258],"type":"Point"}
}