{
  "type": "Feature",
  "properties": {
    "iso:country": "GB",
    "wof:name": "TF2 6PY",
    "wof:placetype": "postalcode"
  },
  "geometry": {"coordinates":[-2.454517,52.707862],"type":"Point"}
}
