{
  "type": "Feature",
  "properties": {
    "iso:country":"GB",
    "wof:name":"M24 1FS",
    "wof:placetype":"postalcode"
},
  "geometry": {"coordinates":[-2.19094572983972,53.54299183256153],"type":"Point"}
}