{
  "type": "Feature",
  "properties": {
    "iso:country": "GB",
    "wof:name": "OL9 6TP",
    "wof:placetype": "postalcode"
  },
  "geometry": {"coordinates":[-2.124839,53.53934],"type":"Point"}
}
