{
  "type": "Feature",
  "properties": {
    "date:inception_lower":"1983-01-01",
    "date:inception_upper":"1983-01-31",
    "iso:country":"GB",
    "wof:name":"OL9 6TP",
    "wof:placetype":"postalcode"
},
  "geometry": {"coordinates":[-2.124839,53.53934],"type":"Point"}
}