{
  "type": "Feature",
  "properties": {
    "date:inception_lower":"1980-01-01",
    "date:inception_upper":"1980-01-31",
    "iso:country":"GB",
    "wof:name":"OL14 8BX",
    "wof:placetype":"postalcode"
},
  "geometry": {"coordinates":[-2.094766,53.720777],"type":"Point"}
}