{
  "type": "Feature",
  "properties": {
    "iso:country":"GB",
    "wof:name":"OL14 8BX",
    "wof:placetype":"postalcode"
},
  "geometry": {"coordinates":[-2.09476578736928,53.72077686429731],"type":"Point"}
}