{
  "type": "Feature",
  "properties": {
    "date:inception_lower": "2017-07-01",
    "date:inception_upper": "2017-07-01",
    "iso:country": "GB",
    "wof:name": "LE9 1WE",
    "wof:placetype": "postalcode"
  },
  "geometry": {"coordinates":[-1.191373,52.5487],"type":"Point"}
}
