{
  "type": "Feature",
  "properties": {
    "iso:country": "GB",
    "wof:name": "LE9 1WE",
    "wof:placetype": "postalcode"
  },
  "geometry": {"coordinates":[-1.191373,52.5487],"type":"Point"}
}
