{
  "type": "Feature",
  "properties": {
    "iso:country":"GB",
    "wof:name":"EN10 7PH",
    "wof:placetype":"postalcode"
},
  "geometry": {"coordinates":[-0.02354095862172,51.7483328099753],"type":"Point"}
}