{
  "type": "Feature",
  "properties": {
    "iso:country": "GB",
    "wof:name": "EN10 7PH",
    "wof:placetype": "postalcode"
  },
  "geometry": {"coordinates":[-0.023541,51.748333],"type":"Point"}
}
