{
  "type": "Feature",
  "properties": {
    "date:inception_lower": "1983-09-01",
    "date:inception_upper": "1983-09-01",
    "iso:country": "GB",
    "wof:name": "PH10 7EQ",
    "wof:placetype": "postalcode"
  },
  "geometry": {"coordinates":[-3.331992,56.591486],"type":"Point"}
}
