{
  "type": "Feature",
  "properties": {
    "date:inception_lower": "1991-09-01",
    "date:inception_upper": "1991-09-01",
    "iso:country": "GB",
    "wof:name": "IP25 6HR",
    "wof:placetype": "postalcode"
  },
  "geometry": {"coordinates":[0.850889,52.569901],"type":"Point"}
}
