{
  "type": "Feature",
  "properties": {
    "iso:country":"GB",
    "wof:name":"B70 7AQ",
    "wof:placetype":"postalcode"
},
  "geometry": {"coordinates":[-1.99837960988711,52.51658721708705],"type":"Point"}
}