{
  "type": "Feature",
  "properties": {
    "iso:country":"GB",
    "wof:name":"G62 6HN",
    "wof:placetype":"postalcode"
},
  "geometry": {"coordinates":[-4.30908958134188,55.93924693536646],"type":"Point"}
}