{
  "type": "Feature",
  "properties": {
    "iso:country": "GB",
    "wof:name": "CT9 1XE",
    "wof:placetype": "postalcode"
  },
  "geometry": {"coordinates":[1.380281,51.38598],"type":"Point"}
}
