{
  "type": "Feature",
  "properties": {
    "iso:country":"GB",
    "wof:name":"CT9 1XE",
    "wof:placetype":"postalcode"
},
  "geometry": {"coordinates":[1.38028131681108,51.38597997009133],"type":"Point"}
}