{
  "type": "Feature",
  "properties": {
    "iso:country":"GB",
    "wof:name":"CR7 7JX",
    "wof:placetype":"postalcode"
},
  "geometry": {"coordinates":[-0.10859305382628,51.39234500459498],"type":"Point"}
}