{
  "type": "Feature",
  "properties": {
    "date:inception_lower": "1980-01-01",
    "date:inception_upper": "1980-01-01",
    "iso:country": "GB",
    "wof:name": "TR21 0NB",
    "wof:placetype": "postalcode"
  },
  "geometry": {"coordinates":[-6.310502,49.91478],"type":"Point"}
}
