{
  "type": "Feature",
  "properties": {
    "iso:country": "GB",
    "wof:name": "SK3 0UN",
    "wof:placetype": "postalcode"
  },
  "geometry": {"coordinates":[-2.186125,53.400451],"type":"Point"}
}
