{
  "type": "Feature",
  "properties": {
    "iso:country":"GB",
    "wof:name":"SK3 0UN",
    "wof:placetype":"postalcode"
},
  "geometry": {"coordinates":[-2.18612503563241,53.40045142288899],"type":"Point"}
}