{
  "type": "Feature",
  "properties": {
    "iso:country":"GB",
    "wof:name":"SO40 7BZ",
    "wof:placetype":"postalcode"
},
  "geometry": {"coordinates":[-1.51594571399448,50.89884230119795],"type":"Point"}
}