{
  "type": "Feature",
  "properties": {
    "iso:country":"GB",
    "wof:name":"OX3 8LE",
    "wof:placetype":"postalcode"
},
  "geometry": {"coordinates":[-1.19373069803028,51.75941484231375],"type":"Point"}
}