{
  "type": "Feature",
  "properties": {
    "iso:country": "GB",
    "wof:name": "WV14 9XR",
    "wof:placetype": "postalcode"
  },
  "geometry": {"coordinates":[-2.096,52.553703],"type":"Point"}
}
