{
  "type": "Feature",
  "properties": {
    "iso:country":"GB",
    "wof:name":"WV14 9XR",
    "wof:placetype":"postalcode"
},
  "geometry": {"coordinates":[-2.09600049657162,52.55370323796377],"type":"Point"}
}