{
  "type": "Feature",
  "properties": {
    "iso:country": "GB",
    "wof:name": "NE29 6UY",
    "wof:placetype": "postalcode"
  },
  "geometry": {"coordinates":[-1.449441,54.996871],"type":"Point"}
}
