{
  "type": "Feature",
  "properties": {
    "iso:country":"GB",
    "wof:name":"WF8 1HU",
    "wof:placetype":"postalcode"
},
  "geometry": {"coordinates":[-1.30894828446198,53.69513026758175],"type":"Point"}
}