{
  "type": "Feature",
  "properties": {
    "date:inception_lower": "1992-08-01",
    "date:inception_upper": "1992-08-01",
    "iso:country": "GB",
    "wof:name": "WF8 1HU",
    "wof:placetype": "postalcode"
  },
  "geometry": {"coordinates":[-1.308948,53.69513],"type":"Point"}
}
