{
  "type": "Feature",
  "properties": {
    "iso:country":"GB",
    "wof:name":"S41 8NN",
    "wof:placetype":"postalcode"
},
  "geometry": {"coordinates":[-1.43404346972795,53.26259144210866],"type":"Point"}
}