{
  "type": "Feature",
  "properties": {
    "date:inception_lower": "2007-05-01",
    "date:inception_upper": "2007-05-01",
    "iso:country": "GB",
    "wof:name": "WA4 1DE",
    "wof:placetype": "postalcode"
  },
  "geometry": {"coordinates":[-2.556711,53.379703],"type":"Point"}
}
