{
  "type": "Feature",
  "properties": {
    "iso:country": "GB",
    "wof:name": "M11 2PA",
    "wof:placetype": "postalcode"
  },
  "geometry": {"coordinates":[-2.180768,53.47446],"type":"Point"}
}
