{
  "type": "Feature",
  "properties": {
    "date:inception_lower":"1980-01-01",
    "date:inception_upper":"1980-01-31",
    "iso:country":"GB",
    "wof:name":"AL1 5LD",
    "wof:placetype":"postalcode"
},
  "geometry": {"coordinates":[-0.308848,51.748585],"type":"Point"}
}