{
  "type": "Feature",
  "properties": {
    "iso:country":"GB",
    "wof:name":"AL1 5LD",
    "wof:placetype":"postalcode"
},
  "geometry": {"coordinates":[-0.30884788473924,51.74858546347672],"type":"Point"}
}