{
  "type": "Feature",
  "properties": {
    "iso:country":"GB",
    "wof:name":"KY13 0LG",
    "wof:placetype":"postalcode"
},
  "geometry": {"coordinates":[-3.44608123493147,56.17048427141417],"type":"Point"}
}