{
  "type": "Feature",
  "properties": {
    "date:inception_lower": "2010-05-01",
    "date:inception_upper": "2010-05-01",
    "iso:country": "GB",
    "wof:name": "L6 1HD",
    "wof:placetype": "postalcode"
  },
  "geometry": {"coordinates":[-2.96749,53.410977],"type":"Point"}
}
