{
  "type": "Feature",
  "properties": {
    "iso:country": "GB",
    "wof:name": "L6 1HD",
    "wof:placetype": "postalcode"
  },
  "geometry": {"coordinates":[-2.96749,53.410977],"type":"Point"}
}
