{
  "type": "Feature",
  "properties": {
    "date:inception_lower": "1996-06-01",
    "date:inception_upper": "1996-06-01",
    "iso:country": "GB",
    "wof:name": "DL16 7XL",
    "wof:placetype": "postalcode"
  },
  "geometry": {"coordinates":[-1.591785,54.690249],"type":"Point"}
}
