{
  "type": "Feature",
  "properties": {
    "iso:country":"GB",
    "wof:name":"DL16 7XL",
    "wof:placetype":"postalcode"
},
  "geometry": {"coordinates":[-1.59179031524796,54.69023963509392],"type":"Point"}
}