{
  "type": "Feature",
  "properties": {
    "date:inception_lower": "1980-01-01",
    "date:inception_upper": "1980-01-01",
    "iso:country": "GB",
    "wof:name": "KW17 2DP",
    "wof:placetype": "postalcode"
  },
  "geometry": {"coordinates":[-2.976982,59.290396],"type":"Point"}
}
