{
  "type": "Feature",
  "properties": {
    "iso:country":"GB",
    "wof:name":"KW17 2DP",
    "wof:placetype":"postalcode"
},
  "geometry": {"coordinates":[-2.97698197994801,59.29039554508723],"type":"Point"}
}