{
  "type": "Feature",
  "properties": {
    "iso:country":"GB",
    "wof:name":"EN4 8BX",
    "wof:placetype":"postalcode"
},
  "geometry": {"coordinates":[-0.16828372085182,51.64358067797887],"type":"Point"}
}