{
  "type": "Feature",
  "properties": {
    "date:inception_lower": "1980-01-01",
    "date:inception_upper": "1980-01-01",
    "iso:country": "GB",
    "wof:name": "EN4 8BX",
    "wof:placetype": "postalcode"
  },
  "geometry": {"coordinates":[-0.168225,51.643691],"type":"Point"}
}
