{
  "type": "Feature",
  "properties": {
    "iso:country":"GB",
    "wof:name":"NG22 9SG",
    "wof:placetype":"postalcode"
},
  "geometry": {"coordinates":[-1.00493065897589,53.21281483680433],"type":"Point"}
}