{
  "type": "Feature",
  "properties": {
    "iso:country":"GB",
    "wof:name":"W1T 6NF",
    "wof:placetype":"postalcode"
},
  "geometry": {"coordinates":[-0.14048489224806,51.52207889088969],"type":"Point"}
}