{
  "type": "Feature",
  "properties": {
    "iso:country":"GB",
    "wof:name":"BN1 9GP",
    "wof:placetype":"postalcode"
},
  "geometry": {"coordinates":[-0.1062992883855,50.86072704723633],"type":"Point"}
}