{
  "type": "Feature",
  "properties": {
    "iso:country":"GB",
    "wof:name":"BS1 5LH",
    "wof:placetype":"postalcode"
},
  "geometry": {"coordinates":[-2.60272258064565,51.4552832608459],"type":"Point"}
}