{
  "type": "Feature",
  "properties": {
    "iso:country": "GB",
    "wof:name": "OX17 1NA",
    "wof:placetype": "postalcode"
  },
  "geometry": {"coordinates":[-1.333235,52.14768],"type":"Point"}
}
