{
  "type": "Feature",
  "properties": {
    "iso:country":"GB",
    "wof:name":"OX17 1NA",
    "wof:placetype":"postalcode"
},
  "geometry": {"coordinates":[-1.33323476586109,52.14767995828597],"type":"Point"}
}