{
  "type": "Feature",
  "properties": {
    "iso:country":"GB",
    "wof:name":"OL9 6PL",
    "wof:placetype":"postalcode"
},
  "geometry": {"coordinates":[-2.13466164732882,53.54397639636169],"type":"Point"}
}