{
  "type": "Feature",
  "properties": {
    "iso:country":"GB",
    "wof:name":"NE37 2NB",
    "wof:placetype":"postalcode"
},
  "geometry": {"coordinates":[-1.5237550756514,54.91879807018832],"type":"Point"}
}