{
  "type": "Feature",
  "properties": {
    "iso:country": "GB",
    "wof:name": "EN8 9JU",
    "wof:placetype": "postalcode"
  },
  "geometry": {"coordinates":[-0.031653,51.708687],"type":"Point"}
}
