{
  "type": "Feature",
  "properties": {
    "iso:country":"GB",
    "wof:name":"EN8 9JU",
    "wof:placetype":"postalcode"
},
  "geometry": {"coordinates":[-0.03165282837612,51.70868684433291],"type":"Point"}
}