{
  "type": "Feature",
  "properties": {
    "iso:country":"GB",
    "wof:name":"PE38 9QB",
    "wof:placetype":"postalcode"
},
  "geometry": {"coordinates":[0.3807904320551,52.61092584136766],"type":"Point"}
}