{
  "type": "Feature",
  "properties": {
    "iso:country": "GB",
    "wof:name": "PE38 9QB",
    "wof:placetype": "postalcode"
  },
  "geometry": {"coordinates":[0.38079,52.610926],"type":"Point"}
}
