{
  "type": "Feature",
  "properties": {
    "date:inception_lower": "1986-07-01",
    "date:inception_upper": "1986-07-01",
    "iso:country": "GB",
    "wof:name": "PE38 9QB",
    "wof:placetype": "postalcode"
  },
  "geometry": {"coordinates":[0.38079,52.610926],"type":"Point"}
}
