{
  "type": "Feature",
  "properties": {
    "iso:country":"GB",
    "wof:name":"TN24 0FN",
    "wof:placetype":"postalcode"
},
  "geometry": {"coordinates":[0.91037845542665,51.12631712255259],"type":"Point"}
}