{
  "type": "Feature",
  "properties": {
    "iso:country": "GB",
    "wof:name": "TN24 0FN",
    "wof:placetype": "postalcode"
  },
  "geometry": {"coordinates":[0.910378,51.126317],"type":"Point"}
}
