{
  "type": "Feature",
  "properties": {
    "date:inception_lower":"2000-06-01",
    "date:inception_upper":"2000-06-30",
    "iso:country":"GB",
    "wof:name":"PE28 0RP",
    "wof:placetype":"postalcode"
},
  "geometry": {"coordinates":[-0.446973,52.329591],"type":"Point"}
}