{
  "type": "Feature",
  "properties": {
    "date:inception_lower":"1988-03-01",
    "date:inception_upper":"1988-03-31",
    "iso:country":"GB",
    "wof:name":"CV32 4XT",
    "wof:placetype":"postalcode"
},
  "geometry": {"coordinates":[-1.534646,52.291063],"type":"Point"}
}