{
  "type": "Feature",
  "properties": {
    "iso:country": "GB",
    "wof:name": "GL3 4HR",
    "wof:placetype": "postalcode"
  },
  "geometry": {"coordinates":[-2.159691,51.850226],"type":"Point"}
}
