{
  "type": "Feature",
  "properties": {
    "iso:country":"GB",
    "wof:name":"GL3 4HR",
    "wof:placetype":"postalcode"
},
  "geometry": {"coordinates":[-2.15969140751816,51.85022599474988],"type":"Point"}
}