{
  "type": "Feature",
  "properties": {
    "iso:country":"GB",
    "wof:name":"CR8 3PY",
    "wof:placetype":"postalcode"
},
  "geometry": {"coordinates":[-0.14602110270205,51.3393916391401],"type":"Point"}
}