{
  "type": "Feature",
  "properties": {
    "date:inception_lower": "1990-07-01",
    "date:inception_upper": "1990-07-01",
    "iso:country": "GB",
    "wof:name": "CR8 3PY",
    "wof:placetype": "postalcode"
  },
  "geometry": {"coordinates":[-0.145981,51.33939],"type":"Point"}
}
