{
  "type": "Feature",
  "properties": {
    "date:inception_lower": "2013-10-01",
    "date:inception_upper": "2013-10-01",
    "iso:country": "GB",
    "wof:name": "LD3 7BH",
    "wof:placetype": "postalcode"
  },
  "geometry": {"coordinates":[-3.390042,51.947265],"type":"Point"}
}
