{
  "type": "Feature",
  "properties": {
    "iso:country":"GB",
    "wof:name":"LD3 7BH",
    "wof:placetype":"postalcode"
},
  "geometry": {"coordinates":[-3.39004215835575,51.94726492185853],"type":"Point"}
}