{
  "type": "Feature",
  "properties": {
    "iso:country":"GB",
    "wof:name":"TF2 8PX",
    "wof:placetype":"postalcode"
},
  "geometry": {"coordinates":[-2.42085158928642,52.7254264007794],"type":"Point"}
}