{
  "type": "Feature",
  "properties": {
    "iso:country": "GB",
    "wof:name": "PO39 0AR",
    "wof:placetype": "postalcode"
  },
  "geometry": {"coordinates":[-1.542679,50.682129],"type":"Point"}
}
