{
  "type": "Feature",
  "properties": {
    "iso:country":"GB",
    "wof:name":"SM2 6RD",
    "wof:placetype":"postalcode"
},
  "geometry": {"coordinates":[-0.19988382922269,51.35237195081318],"type":"Point"}
}