{
  "type": "Feature",
  "properties": {
    "iso:country":"GB",
    "wof:name":"SR4 7ST",
    "wof:placetype":"postalcode"
},
  "geometry": {"coordinates":[-1.4142928242661,54.9020097185711],"type":"Point"}
}