{
  "type": "Feature",
  "properties": {
    "iso:country":"GB",
    "wof:name":"GL9 1HQ",
    "wof:placetype":"postalcode"
},
  "geometry": {"coordinates":[-2.27433671774176,51.5272662580053],"type":"Point"}
}