{
  "type": "Feature",
  "properties": {
    "iso:country": "GB",
    "wof:name": "BS34 8ND",
    "wof:placetype": "postalcode"
  },
  "geometry": {"coordinates":[-2.555831,51.521441],"type":"Point"}
}
