{
  "type": "Feature",
  "properties": {
    "iso:country":"GB",
    "wof:name":"S75 2TB",
    "wof:placetype":"postalcode"
},
  "geometry": {"coordinates":[-1.49674096830862,53.56078286824609],"type":"Point"}
}