{
  "type": "Feature",
  "properties": {
    "iso:country":"GB",
    "wof:name":"WD18 6LD",
    "wof:placetype":"postalcode"
},
  "geometry": {"coordinates":[-0.41564264739918,51.64498466442121],"type":"Point"}
}