{
  "type": "Feature",
  "properties": {
    "iso:country":"GB",
    "wof:name":"NE63 8EX",
    "wof:placetype":"postalcode"
},
  "geometry": {"coordinates":[-1.58129262738291,55.17086514506443],"type":"Point"}
}