{
  "type": "Feature",
  "properties": {
    "iso:country": "GB",
    "wof:name": "NE63 8EX",
    "wof:placetype": "postalcode"
  },
  "geometry": {"coordinates":[-1.581293,55.170865],"type":"Point"}
}
