{
  "type": "Feature",
  "properties": {
    "date:inception_lower":"1980-01-01",
    "date:inception_upper":"1980-01-31",
    "iso:country":"GB",
    "wof:name":"EX4 2HL",
    "wof:placetype":"postalcode"
},
  "geometry": {"coordinates":[-3.637806,50.739206],"type":"Point"}
}