{
  "type": "Feature",
  "properties": {
    "iso:country": "GB",
    "wof:name": "G64 1FF",
    "wof:placetype": "postalcode"
  },
  "geometry": {"coordinates":[-4.197143,55.90079],"type":"Point"}
}
