{
  "type": "Feature",
  "properties": {
    "iso:country":"GB",
    "wof:name":"G64 1FF",
    "wof:placetype":"postalcode"
},
  "geometry": {"coordinates":[-4.1971432017416,55.90078955695789],"type":"Point"}
}