{
  "type": "Feature",
  "properties": {
    "date:inception_lower":"1980-01-01",
    "date:inception_upper":"1980-01-31",
    "iso:country":"GB",
    "wof:name":"NE16 6LG",
    "wof:placetype":"postalcode"
},
  "geometry": {"coordinates":[-1.744895,54.904321],"type":"Point"}
}