{
  "type": "Feature",
  "properties": {
    "iso:country":"GB",
    "wof:name":"NE16 6LG",
    "wof:placetype":"postalcode"
},
  "geometry": {"coordinates":[-1.74489487960012,54.90432094299808],"type":"Point"}
}