{
  "type": "Feature",
  "properties": {
    "date:inception_lower": "1984-10-01",
    "date:inception_upper": "1984-10-01",
    "iso:country": "GB",
    "wof:name": "DN7 6RN",
    "wof:placetype": "postalcode"
  },
  "geometry": {"coordinates":[-1.006581,53.582131],"type":"Point"}
}
