{
  "type": "Feature",
  "properties": {
    "iso:country":"GB",
    "wof:name":"DN7 6RN",
    "wof:placetype":"postalcode"
},
  "geometry": {"coordinates":[-1.00658121091125,53.58213061672198],"type":"Point"}
}