{
  "type": "Feature",
  "properties": {
    "date:inception_lower": "1980-01-01",
    "date:inception_upper": "1980-01-01",
    "iso:country": "GB",
    "wof:name": "UB10 8AJ",
    "wof:placetype": "postalcode"
  },
  "geometry": {"coordinates":[-0.465906,51.566102],"type":"Point"}
}
