{
  "type": "Feature",
  "properties": {
    "iso:country":"GB",
    "wof:name":"E3 4PG",
    "wof:placetype":"postalcode"
},
  "geometry": {"coordinates":[-0.02700436104075,51.52589027574412],"type":"Point"}
}