{
  "type": "Feature",
  "properties": {
    "date:inception_lower":"2009-02-01",
    "date:inception_upper":"2009-02-28",
    "iso:country":"GB",
    "wof:name":"E3 4PG",
    "wof:placetype":"postalcode"
},
  "geometry": {"coordinates":[-0.027004,51.52589],"type":"Point"}
}