{
  "type": "Feature",
  "properties": {
    "iso:country": "GB",
    "wof:name": "UB9 6DW",
    "wof:placetype": "postalcode"
  },
  "geometry": {"coordinates":[-0.483398,51.595209],"type":"Point"}
}
