{
  "type": "Feature",
  "properties": {
    "iso:country":"GB",
    "wof:name":"UB9 6DW",
    "wof:placetype":"postalcode"
},
  "geometry": {"coordinates":[-0.48339764845645,51.59520934400515],"type":"Point"}
}