{
  "type": "Feature",
  "properties": {
    "iso:country":"GB",
    "wof:name":"PE29 2EG",
    "wof:placetype":"postalcode"
},
  "geometry": {"coordinates":[-0.16450857320372,52.31513984902295],"type":"Point"}
}