{
  "type": "Feature",
  "properties": {
    "iso:country": "GB",
    "wof:name": "DY13 0HJ",
    "wof:placetype": "postalcode"
  },
  "geometry": {"coordinates":[-2.278121,52.327756],"type":"Point"}
}
