{
  "type": "Feature",
  "properties": {
    "iso:country":"GB",
    "wof:name":"SP1 1QP",
    "wof:placetype":"postalcode"
},
  "geometry": {"coordinates":[-1.77467241640734,51.07663156197336],"type":"Point"}
}