{
  "type": "Feature",
  "properties": {
    "date:inception_lower": "1980-01-01",
    "date:inception_upper": "1980-01-01",
    "iso:country": "GB",
    "wof:name": "SP1 1QP",
    "wof:placetype": "postalcode"
  },
  "geometry": {"coordinates":[-1.774663,51.076509],"type":"Point"}
}
