{
  "type": "Feature",
  "properties": {
    "iso:country": "GB",
    "wof:name": "SP1 1QP",
    "wof:placetype": "postalcode"
  },
  "geometry": {"coordinates":[-1.774672,51.076632],"type":"Point"}
}
