{
  "type": "Feature",
  "properties": {
    "date:inception_lower": "1995-07-01",
    "date:inception_upper": "1995-07-01",
    "iso:country": "GB",
    "wof:name": "RG40 1XG",
    "wof:placetype": "postalcode"
  },
  "geometry": {"coordinates":[-0.831432,51.410918],"type":"Point"}
}
