{
  "type": "Feature",
  "properties": {
    "date:inception_lower":"1995-12-01",
    "date:inception_upper":"1995-12-31",
    "iso:country":"GB",
    "wof:name":"DL13 2QT",
    "wof:placetype":"postalcode"
},
  "geometry": {"coordinates":[-1.959521,54.726623],"type":"Point"}
}