{
  "type": "Feature",
  "properties": {
    "iso:country": "GB",
    "wof:name": "DL13 2QT",
    "wof:placetype": "postalcode"
  },
  "geometry": {"coordinates":[-1.959521,54.726623],"type":"Point"}
}
