{
  "type": "Feature",
  "properties": {
    "iso:country":"GB",
    "wof:name":"LL77 7TQ",
    "wof:placetype":"postalcode"
},
  "geometry": {"coordinates":[-4.31334037368998,53.26394802072656],"type":"Point"}
}