{
  "type": "Feature",
  "properties": {
    "iso:country":"GB",
    "wof:name":"BS30 9SQ",
    "wof:placetype":"postalcode"
},
  "geometry": {"coordinates":[-2.47561029426645,51.44280323335342],"type":"Point"}
}