{
  "type": "Feature",
  "properties": {
    "iso:country":"GB",
    "wof:name":"RM10 9EA",
    "wof:placetype":"postalcode"
},
  "geometry": {"coordinates":[0.16056397885178,51.52885306933711],"type":"Point"}
}