{
  "type": "Feature",
  "properties": {
    "iso:country": "GB",
    "wof:name": "RM10 9EA",
    "wof:placetype": "postalcode"
  },
  "geometry": {"coordinates":[0.160564,51.528853],"type":"Point"}
}
