{
  "type": "Feature",
  "properties": {
    "iso:country":"GB",
    "wof:name":"GU10 1QP",
    "wof:placetype":"postalcode"
},
  "geometry": {"coordinates":[-0.76782099266112,51.21227593741279],"type":"Point"}
}