{
  "type": "Feature",
  "properties": {
    "iso:country": "GB",
    "wof:name": "CW8 2NX",
    "wof:placetype": "postalcode"
  },
  "geometry": {"coordinates":[-2.601307,53.233013],"type":"Point"}
}
