{
  "type": "Feature",
  "properties": {
    "iso:country": "GB",
    "wof:name": "SE27 0QU",
    "wof:placetype": "postalcode"
  },
  "geometry": {"coordinates":[-0.10607,51.425577],"type":"Point"}
}
