{
  "type": "Feature",
  "properties": {
    "iso:country":"GB",
    "wof:name":"SE27 0QU",
    "wof:placetype":"postalcode"
},
  "geometry": {"coordinates":[-0.10607041998393,51.42557720945013],"type":"Point"}
}