{
  "type": "Feature",
  "properties": {
    "iso:country":"GB",
    "wof:name":"CV2 2FL",
    "wof:placetype":"postalcode"
},
  "geometry": {"coordinates":[-1.45457480706866,52.4381879109504],"type":"Point"}
}