{
  "type": "Feature",
  "properties": {
    "iso:country": "GB",
    "wof:name": "CV2 2FL",
    "wof:placetype": "postalcode"
  },
  "geometry": {"coordinates":[-1.454575,52.438188],"type":"Point"}
}
