{
  "type": "Feature",
  "properties": {
    "iso:country": "GB",
    "wof:name": "B74 2BP",
    "wof:placetype": "postalcode"
  },
  "geometry": {"coordinates":[-1.885062,52.571235],"type":"Point"}
}
