{
  "type": "Feature",
  "properties": {
    "iso:country": "GB",
    "wof:name": "DT11 8NX",
    "wof:placetype": "postalcode"
  },
  "geometry": {"coordinates":[-2.196324,50.943672],"type":"Point"}
}
