{
  "type": "Feature",
  "properties": {
    "iso:country":"GB",
    "wof:name":"DT11 8NX",
    "wof:placetype":"postalcode"
},
  "geometry": {"coordinates":[-2.19644284860125,50.94364263159985],"type":"Point"}
}