{
  "type": "Feature",
  "properties": {
    "iso:country":"GB",
    "wof:name":"IP1 1DS",
    "wof:placetype":"postalcode"
},
  "geometry": {"coordinates":[1.1533418759557,52.05705265033627],"type":"Point"}
}