{
  "type": "Feature",
  "properties": {
    "iso:country":"GB",
    "wof:name":"PE13 4HJ",
    "wof:placetype":"postalcode"
},
  "geometry": {"coordinates":[-0.00341260207485,52.635927991611],"type":"Point"}
}