{
  "type": "Feature",
  "properties": {
    "iso:country": "GB",
    "wof:name": "B91 1SH",
    "wof:placetype": "postalcode"
  },
  "geometry": {"coordinates":[-1.79789,52.41081],"type":"Point"}
}
