{
  "type": "Feature",
  "properties": {
    "iso:country": "GB",
    "wof:name": "DY10 3RB",
    "wof:placetype": "postalcode"
  },
  "geometry": {"coordinates":[-2.227819,52.413941],"type":"Point"}
}
