{
  "type": "Feature",
  "properties": {
    "iso:country":"GB",
    "wof:name":"DY10 3RB",
    "wof:placetype":"postalcode"
},
  "geometry": {"coordinates":[-2.22782364045208,52.41392641251053],"type":"Point"}
}