{
  "type": "Feature",
  "properties": {
    "iso:country":"GB",
    "wof:name":"LE14 4JF",
    "wof:placetype":"postalcode"
},
  "geometry": {"coordinates":[-0.9147546493411,52.86103979064368],"type":"Point"}
}