{
  "type": "Feature",
  "properties": {
    "iso:country":"GB",
    "wof:name":"WR7 4EA",
    "wof:placetype":"postalcode"
},
  "geometry": {"coordinates":[-1.98003581781125,52.21285389255402],"type":"Point"}
}