{
  "type": "Feature",
  "properties": {
    "iso:country": "GB",
    "wof:name": "WR7 4EA",
    "wof:placetype": "postalcode"
  },
  "geometry": {"coordinates":[-1.980036,52.212854],"type":"Point"}
}
