{
  "type": "Feature",
  "properties": {
    "iso:country":"GB",
    "wof:name":"DN10 6BX",
    "wof:placetype":"postalcode"
},
  "geometry": {"coordinates":[-1.00479752609463,53.44892907772638],"type":"Point"}
}