{
  "type": "Feature",
  "properties": {
    "date:inception_lower":"1980-01-01",
    "date:inception_upper":"1980-01-31",
    "iso:country":"GB",
    "wof:name":"B8 2RT",
    "wof:placetype":"postalcode"
},
  "geometry": {"coordinates":[-1.827157,52.498167],"type":"Point"}
}