{
  "type": "Feature",
  "properties": {
    "iso:country":"GB",
    "wof:name":"B8 2RT",
    "wof:placetype":"postalcode"
},
  "geometry": {"coordinates":[-1.82715665412981,52.49816690367312],"type":"Point"}
}