{
  "type": "Feature",
  "properties": {
    "iso:country": "GB",
    "wof:name": "B8 2RT",
    "wof:placetype": "postalcode"
  },
  "geometry": {"coordinates":[-1.827157,52.498167],"type":"Point"}
}
