{
  "type": "Feature",
  "properties": {
    "iso:country":"GB",
    "wof:name":"DH9 0PH",
    "wof:placetype":"postalcode"
},
  "geometry": {"coordinates":[-1.69276177591493,54.87335025183631],"type":"Point"}
}