{
  "type": "Feature",
  "properties": {
    "iso:country": "GB",
    "wof:name": "DH9 0PH",
    "wof:placetype": "postalcode"
  },
  "geometry": {"coordinates":[-1.692762,54.87335],"type":"Point"}
}
