{
  "type": "Feature",
  "properties": {
    "date:inception_lower":"1980-01-01",
    "date:inception_upper":"1980-01-31",
    "iso:country":"GB",
    "wof:name":"SA61 2NT",
    "wof:placetype":"postalcode"
},
  "geometry": {"coordinates":[-4.963925,51.803643],"type":"Point"}
}