{
  "type": "Feature",
  "properties": {
    "date:inception_lower":"1980-01-01",
    "date:inception_upper":"1980-01-31",
    "iso:country":"GB",
    "wof:name":"ME15 7AX",
    "wof:placetype":"postalcode"
},
  "geometry": {"coordinates":[0.539625,51.259184],"type":"Point"}
}