{
  "type": "Feature",
  "properties": {
    "iso:country": "GB",
    "wof:name": "ME15 7AX",
    "wof:placetype": "postalcode"
  },
  "geometry": {"coordinates":[0.539625,51.259184],"type":"Point"}
}
