{
  "type": "Feature",
  "properties": {
    "iso:country":"GB",
    "wof:name":"KA13 6RG",
    "wof:placetype":"postalcode"
},
  "geometry": {"coordinates":[-4.71661299807594,55.65658581476763],"type":"Point"}
}