{
  "type": "Feature",
  "properties": {
    "date:inception_lower": "1980-01-01",
    "date:inception_upper": "1980-01-01",
    "iso:country": "GB",
    "wof:name": "IP23 8AP",
    "wof:placetype": "postalcode"
  },
  "geometry": {"coordinates":[1.131576,52.345037],"type":"Point"}
}
