{
  "type": "Feature",
  "properties": {
    "date:inception_lower": "2021-12-01",
    "date:inception_upper": "2021-12-01",
    "iso:country": "GB",
    "wof:name": "SE15 4DP",
    "wof:placetype": "postalcode"
  },
  "geometry": {"coordinates":[-0.066365,51.467645],"type":"Point"}
}
