{
  "type": "Feature",
  "properties": {
    "iso:country":"GB",
    "wof:name":"TR8 5AF",
    "wof:placetype":"postalcode"
},
  "geometry": {"coordinates":[-4.98853679333001,50.36587593734636],"type":"Point"}
}