{
  "type": "Feature",
  "properties": {
    "date:inception_lower": "1980-01-01",
    "date:inception_upper": "1980-01-01",
    "iso:country": "GB",
    "wof:name": "TR8 5AF",
    "wof:placetype": "postalcode"
  },
  "geometry": {"coordinates":[-4.988537,50.365876],"type":"Point"}
}
