{
  "type": "Feature",
  "properties": {
    "date:inception_lower": "1980-01-01",
    "date:inception_upper": "1980-01-01",
    "iso:country": "GB",
    "wof:name": "TQ13 7PH",
    "wof:placetype": "postalcode"
  },
  "geometry": {"coordinates":[-3.83681,50.549361],"type":"Point"}
}
