{
  "type": "Feature",
  "properties": {
    "iso:country":"GB",
    "wof:name":"AL1 4RA",
    "wof:placetype":"postalcode"
},
  "geometry": {"coordinates":[-0.32106138584673,51.76651970445431],"type":"Point"}
}