{
  "type": "Feature",
  "properties": {
    "date:inception_lower":"1980-01-01",
    "date:inception_upper":"1980-01-31",
    "iso:country":"GB",
    "wof:name":"AL1 4RA",
    "wof:placetype":"postalcode"
},
  "geometry": {"coordinates":[-0.321061,51.76652],"type":"Point"}
}