{
  "type": "Feature",
  "properties": {
    "iso:country":"GB",
    "wof:name":"DG11 1BD",
    "wof:placetype":"postalcode"
},
  "geometry": {"coordinates":[-3.33408323841092,55.0843531392603],"type":"Point"}
}