{
  "type": "Feature",
  "properties": {
    "iso:country":"GB",
    "wof:name":"W12 8AU",
    "wof:placetype":"postalcode"
},
  "geometry": {"coordinates":[-0.23129262711348,51.50100226761582],"type":"Point"}
}