{
  "type": "Feature",
  "properties": {
    "iso:country":"GB",
    "wof:name":"CM22 6NS",
    "wof:placetype":"postalcode"
},
  "geometry": {"coordinates":[0.27418750487574,51.8693393335631],"type":"Point"}
}