{
  "type": "Feature",
  "properties": {
    "date:inception_lower": "1980-01-01",
    "date:inception_upper": "1980-01-01",
    "iso:country": "GB",
    "wof:name": "CM22 6NS",
    "wof:placetype": "postalcode"
  },
  "geometry": {"coordinates":[0.274188,51.869339],"type":"Point"}
}
