{
  "type": "Feature",
  "properties": {
    "iso:country":"GB",
    "wof:name":"LL22 8SF",
    "wof:placetype":"postalcode"
},
  "geometry": {"coordinates":[-3.60614397689311,53.21763700511587],"type":"Point"}
}