{
  "type": "Feature",
  "properties": {
    "iso:country": "GB",
    "wof:name": "LL22 8SF",
    "wof:placetype": "postalcode"
  },
  "geometry": {"coordinates":[-3.605686,53.217731],"type":"Point"}
}
