{
  "type": "Feature",
  "properties": {
    "iso:country":"GB",
    "wof:name":"ME8 8ED",
    "wof:placetype":"postalcode"
},
  "geometry": {"coordinates":[0.61213150493733,51.36562097483077],"type":"Point"}
}