{
  "type": "Feature",
  "properties": {
    "iso:country": "GB",
    "wof:name": "NE37 2SW",
    "wof:placetype": "postalcode"
  },
  "geometry": {"coordinates":[-1.522198,54.913076],"type":"Point"}
}
