{
  "type": "Feature",
  "properties": {
    "iso:country":"GB",
    "wof:name":"NE37 2SW",
    "wof:placetype":"postalcode"
},
  "geometry": {"coordinates":[-1.52218483483709,54.91306758372261],"type":"Point"}
}