{
  "type": "Feature",
  "properties": {
    "date:inception_lower": "1980-01-01",
    "date:inception_upper": "1980-01-01",
    "iso:country": "GB",
    "wof:name": "NE37 2SW",
    "wof:placetype": "postalcode"
  },
  "geometry": {"coordinates":[-1.522198,54.913076],"type":"Point"}
}
