{
  "type": "Feature",
  "properties": {
    "iso:country": "GB",
    "wof:name": "EX13 5DE",
    "wof:placetype": "postalcode"
  },
  "geometry": {"coordinates":[-2.992436,50.781092],"type":"Point"}
}
