{
  "type": "Feature",
  "properties": {
    "date:inception_lower":"1994-12-01",
    "date:inception_upper":"1994-12-31",
    "iso:country":"GB",
    "wof:name":"EX13 5DE",
    "wof:placetype":"postalcode"
},
  "geometry": {"coordinates":[-2.992436,50.781092],"type":"Point"}
}