{
  "type": "Feature",
  "properties": {
    "iso:country":"GB",
    "wof:name":"EX13 5DE",
    "wof:placetype":"postalcode"
},
  "geometry": {"coordinates":[-2.99243576239285,50.7810923385074],"type":"Point"}
}