{
  "type": "Feature",
  "properties": {
    "iso:country": "GB",
    "wof:name": "NR1 2ES",
    "wof:placetype": "postalcode"
  },
  "geometry": {"coordinates":[1.29951,52.614178],"type":"Point"}
}
