{
  "type": "Feature",
  "properties": {
    "date:inception_lower": "1980-01-01",
    "date:inception_upper": "1980-01-01",
    "iso:country": "GB",
    "wof:name": "WV14 8TD",
    "wof:placetype": "postalcode"
  },
  "geometry": {"coordinates":[-2.077102,52.553679],"type":"Point"}
}
