{
  "type": "Feature",
  "properties": {
    "iso:country":"GB",
    "wof:name":"AB45 2XL",
    "wof:placetype":"postalcode"
},
  "geometry": {"coordinates":[-2.77179456149025,57.62714037499404],"type":"Point"}
}