{
  "type": "Feature",
  "properties": {
    "iso:country": "GB",
    "wof:name": "AB45 2XL",
    "wof:placetype": "postalcode"
  },
  "geometry": {"coordinates":[-2.771795,57.62714],"type":"Point"}
}
