{
  "type": "Feature",
  "properties": {
    "iso:country":"GB",
    "wof:name":"PO3 6JH",
    "wof:placetype":"postalcode"
},
  "geometry": {"coordinates":[-1.05969737777807,50.8089117337519],"type":"Point"}
}