{
  "type": "Feature",
  "properties": {
    "iso:country":"GB",
    "wof:name":"DT3 6AE",
    "wof:placetype":"postalcode"
},
  "geometry": {"coordinates":[-2.44614113674753,50.64559648168991],"type":"Point"}
}