{
  "type": "Feature",
  "properties": {
    "iso:country":"GB",
    "wof:name":"GL2 4PB",
    "wof:placetype":"postalcode"
},
  "geometry": {"coordinates":[-2.29398309073738,51.82614967638681],"type":"Point"}
}