{
  "type": "Feature",
  "properties": {
    "iso:country": "GB",
    "wof:name": "WS13 8UH",
    "wof:placetype": "postalcode"
  },
  "geometry": {"coordinates":[-1.774011,52.717841],"type":"Point"}
}
