{
  "type": "Feature",
  "properties": {
    "iso:country":"GB",
    "wof:name":"EC4V 5AA",
    "wof:placetype":"postalcode"
},
  "geometry": {"coordinates":[-0.1001086801711,51.5130777707092],"type":"Point"}
}