{
  "type": "Feature",
  "properties": {
    "iso:country": "GB",
    "wof:name": "DE11 7HT",
    "wof:placetype": "postalcode"
  },
  "geometry": {"coordinates":[-1.526615,52.772219],"type":"Point"}
}
