{
  "type": "Feature",
  "properties": {
    "iso:country":"GB",
    "wof:name":"DE11 7HT",
    "wof:placetype":"postalcode"
},
  "geometry": {"coordinates":[-1.52661465441854,52.77221911807997],"type":"Point"}
}