{
  "type": "Feature",
  "properties": {
    "iso:country": "GB",
    "wof:name": "LL31 9TQ",
    "wof:placetype": "postalcode"
  },
  "geometry": {"coordinates":[-3.797038,53.287451],"type":"Point"}
}
