{
  "type": "Feature",
  "properties": {
    "date:inception_lower": "1993-08-01",
    "date:inception_upper": "1993-08-01",
    "iso:country": "GB",
    "wof:name": "LL31 9TQ",
    "wof:placetype": "postalcode"
  },
  "geometry": {"coordinates":[-3.797038,53.287451],"type":"Point"}
}
