{
  "type": "Feature",
  "properties": {
    "iso:country":"GB",
    "wof:name":"DL14 8DJ",
    "wof:placetype":"postalcode"
},
  "geometry": {"coordinates":[-1.67865755832742,54.67721858936429],"type":"Point"}
}