{
  "type": "Feature",
  "properties": {
    "iso:country":"GB",
    "wof:name":"IP14 3AU",
    "wof:placetype":"postalcode"
},
  "geometry": {"coordinates":[0.93927163434903,52.17851547889207],"type":"Point"}
}