{
  "type": "Feature",
  "properties": {
    "iso:country": "GB",
    "wof:name": "RM1 4LP",
    "wof:placetype": "postalcode"
  },
  "geometry": {"coordinates":[0.177506,51.584793],"type":"Point"}
}
