{
  "type": "Feature",
  "properties": {
    "date:inception_lower": "1980-01-01",
    "date:inception_upper": "1980-01-01",
    "iso:country": "GB",
    "wof:name": "RM1 4LP",
    "wof:placetype": "postalcode"
  },
  "geometry": {"coordinates":[0.177506,51.584793],"type":"Point"}
}
