{
  "type": "Feature",
  "properties": {
    "iso:country": "GB",
    "wof:name": "BB7 4LR",
    "wof:placetype": "postalcode"
  },
  "geometry": {"coordinates":[-2.277855,53.945042],"type":"Point"}
}
