{
  "type": "Feature",
  "properties": {
    "iso:country":"GB",
    "wof:name":"BB7 4LR",
    "wof:placetype":"postalcode"
},
  "geometry": {"coordinates":[-2.28231414620597,53.94465846705609],"type":"Point"}
}