{
  "type": "Feature",
  "properties": {
    "iso:country": "GB",
    "wof:name": "IP19 0JX",
    "wof:placetype": "postalcode"
  },
  "geometry": {"coordinates":[1.464001,52.381711],"type":"Point"}
}
