{
  "type": "Feature",
  "properties": {
    "iso:country":"GB",
    "wof:name":"IP19 0JX",
    "wof:placetype":"postalcode"
},
  "geometry": {"coordinates":[1.46400070465453,52.38171068586993],"type":"Point"}
}