{
  "type": "Feature",
  "properties": {
    "iso:country":"GB",
    "wof:name":"KT10 8DX",
    "wof:placetype":"postalcode"
},
  "geometry": {"coordinates":[-0.37365867626407,51.38023616427739],"type":"Point"}
}