{
  "type": "Feature",
  "properties": {
    "date:inception_lower": "1996-12-01",
    "date:inception_upper": "1996-12-01",
    "iso:country": "GB",
    "wof:name": "KT10 8DX",
    "wof:placetype": "postalcode"
  },
  "geometry": {"coordinates":[-0.373659,51.380236],"type":"Point"}
}
