{
  "type": "Feature",
  "properties": {
    "iso:country": "GB",
    "wof:name": "M44 6WR",
    "wof:placetype": "postalcode"
  },
  "geometry": {"coordinates":[-2.423057,53.446605],"type":"Point"}
}
