{
  "type": "Feature",
  "properties": {
    "iso:country": "GB",
    "wof:name": "CH47 5BA",
    "wof:placetype": "postalcode"
  },
  "geometry": {"coordinates":[-3.166471,53.40234],"type":"Point"}
}
