{
  "type": "Feature",
  "properties": {
    "iso:country": "GB",
    "wof:name": "ML6 9XT",
    "wof:placetype": "postalcode"
  },
  "geometry": {"coordinates":[-3.991765,55.852412],"type":"Point"}
}
