{
  "type": "Feature",
  "properties": {
    "iso:country":"GB",
    "wof:name":"LE3 6RP",
    "wof:placetype":"postalcode"
},
  "geometry": {"coordinates":[-1.1729398839653,52.64321892849457],"type":"Point"}
}