{
  "type": "Feature",
  "properties": {
    "iso:country":"GB",
    "wof:name":"PE30 2QW",
    "wof:placetype":"postalcode"
},
  "geometry": {"coordinates":[0.41056024572311,52.75634057510602],"type":"Point"}
}