{
  "type": "Feature",
  "properties": {
    "date:inception_lower": "1993-01-01",
    "date:inception_upper": "1993-01-01",
    "iso:country": "GB",
    "wof:name": "PE30 2QW",
    "wof:placetype": "postalcode"
  },
  "geometry": {"coordinates":[0.410694,52.756352],"type":"Point"}
}
