{
  "type": "Feature",
  "properties": {
    "iso:country": "GB",
    "wof:name": "PE30 2QW",
    "wof:placetype": "postalcode"
  },
  "geometry": {"coordinates":[0.410694,52.756352],"type":"Point"}
}
