{
  "type": "Feature",
  "properties": {
    "iso:country":"GB",
    "wof:name":"M27 6PD",
    "wof:placetype":"postalcode"
},
  "geometry": {"coordinates":[-2.34295517656351,53.52849547340489],"type":"Point"}
}