{
  "type": "Feature",
  "properties": {
    "date:inception_lower": "1994-05-01",
    "date:inception_upper": "1994-05-01",
    "iso:country": "GB",
    "wof:name": "M27 6PD",
    "wof:placetype": "postalcode"
  },
  "geometry": {"coordinates":[-2.342955,53.528495],"type":"Point"}
}
