{
  "type": "Feature",
  "properties": {
    "iso:country":"GB",
    "wof:name":"S10 5BU",
    "wof:placetype":"postalcode"
},
  "geometry": {"coordinates":[-1.50559948791712,53.37819045885668],"type":"Point"}
}