{
  "type": "Feature",
  "properties": {
    "iso:country": "GB",
    "wof:name": "S10 5BU",
    "wof:placetype": "postalcode"
  },
  "geometry": {"coordinates":[-1.505599,53.37819],"type":"Point"}
}
