{
  "type": "Feature",
  "properties": {
    "iso:country": "GB",
    "wof:name": "NG2 1LU",
    "wof:placetype": "postalcode"
  },
  "geometry": {"coordinates":[-1.162121,52.935849],"type":"Point"}
}
