{
  "type": "Feature",
  "properties": {
    "iso:country":"GB",
    "wof:name":"NG2 1LU",
    "wof:placetype":"postalcode"
},
  "geometry": {"coordinates":[-1.16212115193541,52.93584895130671],"type":"Point"}
}