{
  "type": "Feature",
  "properties": {
    "iso:country":"GB",
    "wof:name":"LS13 4JW",
    "wof:placetype":"postalcode"
},
  "geometry": {"coordinates":[-1.62038110115303,53.79868892532042],"type":"Point"}
}