{
  "type": "Feature",
  "properties": {
    "date:inception_lower": "2017-07-01",
    "date:inception_upper": "2017-07-01",
    "iso:country": "GB",
    "wof:name": "RH16 4UH",
    "wof:placetype": "postalcode"
  },
  "geometry": {"coordinates":[-0.113567,50.995318],"type":"Point"}
}
