{
  "type": "Feature",
  "properties": {
    "iso:country": "GB",
    "wof:name": "NN17 1SP",
    "wof:placetype": "postalcode"
  },
  "geometry": {"coordinates":[-0.698299,52.489589],"type":"Point"}
}
