{
  "type": "Feature",
  "properties": {
    "date:inception_lower": "1980-01-01",
    "date:inception_upper": "1980-01-01",
    "iso:country": "GB",
    "wof:name": "NN17 1SP",
    "wof:placetype": "postalcode"
  },
  "geometry": {"coordinates":[-0.698311,52.48974],"type":"Point"}
}
