{
  "type": "Feature",
  "properties": {
    "iso:country":"GB",
    "wof:name":"SG8 0PH",
    "wof:placetype":"postalcode"
},
  "geometry": {"coordinates":[-0.11869074833418,52.08193235830341],"type":"Point"}
}