{
  "type": "Feature",
  "properties": {
    "iso:country": "GB",
    "wof:name": "SG8 0PH",
    "wof:placetype": "postalcode"
  },
  "geometry": {"coordinates":[-0.118691,52.081932],"type":"Point"}
}
