{
  "type": "Feature",
  "properties": {
    "iso:country": "GB",
    "wof:name": "IP16 4BH",
    "wof:placetype": "postalcode"
  },
  "geometry": {"coordinates":[1.582057,52.20496],"type":"Point"}
}
