{
  "type": "Feature",
  "properties": {
    "iso:country":"GB",
    "wof:name":"IP16 4BH",
    "wof:placetype":"postalcode"
},
  "geometry": {"coordinates":[1.58205653773138,52.2049595510103],"type":"Point"}
}