{
  "type": "Feature",
  "properties": {
    "iso:country": "GB",
    "wof:name": "NR13 6AQ",
    "wof:placetype": "postalcode"
  },
  "geometry": {"coordinates":[1.446655,52.684438],"type":"Point"}
}
