{
  "type": "Feature",
  "properties": {
    "iso:country":"GB",
    "wof:name":"NR13 6AQ",
    "wof:placetype":"postalcode"
},
  "geometry": {"coordinates":[1.4466547381729,52.6844382206106],"type":"Point"}
}