{
  "type": "Feature",
  "properties": {
    "iso:country":"GB",
    "wof:name":"NE17 7DF",
    "wof:placetype":"postalcode"
},
  "geometry": {"coordinates":[-1.80999796309589,54.91902479495753],"type":"Point"}
}