{
  "type": "Feature",
  "properties": {
    "iso:country": "GB",
    "wof:name": "NE17 7DF",
    "wof:placetype": "postalcode"
  },
  "geometry": {"coordinates":[-1.809998,54.919025],"type":"Point"}
}
