{
  "type": "Feature",
  "properties": {
    "date:inception_lower": "1980-01-01",
    "date:inception_upper": "1980-01-01",
    "iso:country": "GB",
    "wof:name": "NN8 4PG",
    "wof:placetype": "postalcode"
  },
  "geometry": {"coordinates":[-0.69211,52.303689],"type":"Point"}
}
