{
  "type": "Feature",
  "properties": {
    "iso:country":"GB",
    "wof:name":"YO12 7DD",
    "wof:placetype":"postalcode"
},
  "geometry": {"coordinates":[-0.41310413284957,54.28025644129789],"type":"Point"}
}