{
  "type": "Feature",
  "properties": {
    "date:inception_lower": "1980-01-01",
    "date:inception_upper": "1980-01-01",
    "iso:country": "GB",
    "wof:name": "CV36 5AW",
    "wof:placetype": "postalcode"
  },
  "geometry": {"coordinates":[-1.616282,52.039218],"type":"Point"}
}
