{
  "type": "Feature",
  "properties": {
    "iso:country":"GB",
    "wof:name":"CV36 5AW",
    "wof:placetype":"postalcode"
},
  "geometry": {"coordinates":[-1.6162819712094,52.03921847609142],"type":"Point"}
}