{
  "type": "Feature",
  "properties": {
    "iso:country": "GB",
    "wof:name": "NP13 2HF",
    "wof:placetype": "postalcode"
  },
  "geometry": {"coordinates":[-3.141393,51.704789],"type":"Point"}
}
