{
  "type": "Feature",
  "properties": {
    "date:inception_lower": "1983-12-01",
    "date:inception_upper": "1983-12-01",
    "iso:country": "GB",
    "wof:name": "G73 1UB",
    "wof:placetype": "postalcode"
  },
  "geometry": {"coordinates":[-4.215812,55.833454],"type":"Point"}
}
