{
  "type": "Feature",
  "properties": {
    "iso:country":"GB",
    "wof:name":"G73 1UB",
    "wof:placetype":"postalcode"
},
  "geometry": {"coordinates":[-4.21581182668175,55.83345412085466],"type":"Point"}
}