{
  "type": "Feature",
  "properties": {
    "iso:country":"GB",
    "wof:name":"FY7 7LZ",
    "wof:placetype":"postalcode"
},
  "geometry": {"coordinates":[-3.03123381480805,53.91303124351218],"type":"Point"}
}