{
  "type": "Feature",
  "properties": {
    "iso:country": "GB",
    "wof:name": "IP1 5QG",
    "wof:placetype": "postalcode"
  },
  "geometry": {"coordinates":[1.113037,52.073927],"type":"Point"}
}
