{
  "type": "Feature",
  "properties": {
    "iso:country":"GB",
    "wof:name":"IP1 5QG",
    "wof:placetype":"postalcode"
},
  "geometry": {"coordinates":[1.11303674377848,52.0739272658925],"type":"Point"}
}