{
  "type": "Feature",
  "properties": {
    "iso:country":"GB",
    "wof:name":"BD4 6EN",
    "wof:placetype":"postalcode"
},
  "geometry": {"coordinates":[-1.72650891661264,53.76522767878533],"type":"Point"}
}