{
  "type": "Feature",
  "properties": {
    "iso:country": "GB",
    "wof:name": "HU7 3LT",
    "wof:placetype": "postalcode"
  },
  "geometry": {"coordinates":[-0.336669,53.803552],"type":"Point"}
}
