{
  "type": "Feature",
  "properties": {
    "iso:country":"GB",
    "wof:name":"SS8 9TH",
    "wof:placetype":"postalcode"
},
  "geometry": {"coordinates":[0.57621939333112,51.52753630428602],"type":"Point"}
}