{
  "type": "Feature",
  "properties": {
    "iso:country":"GB",
    "wof:name":"ST11 9NJ",
    "wof:placetype":"postalcode"
},
  "geometry": {"coordinates":[-2.05541560030413,52.96331040773583],"type":"Point"}
}