{
  "type": "Feature",
  "properties": {
    "date:inception_lower": "1980-01-01",
    "date:inception_upper": "1980-01-01",
    "iso:country": "GB",
    "wof:name": "ST11 9NJ",
    "wof:placetype": "postalcode"
  },
  "geometry": {"coordinates":[-2.055416,52.96331],"type":"Point"}
}
