{
  "type": "Feature",
  "properties": {
    "date:inception_lower": "1990-07-01",
    "date:inception_upper": "1990-07-01",
    "iso:country": "GB",
    "wof:name": "DN14 6NL",
    "wof:placetype": "postalcode"
  },
  "geometry": {"coordinates":[-0.860903,53.712014],"type":"Point"}
}
