{
  "type": "Feature",
  "properties": {
    "iso:country":"GB",
    "wof:name":"KA25 7HQ",
    "wof:placetype":"postalcode"
},
  "geometry": {"coordinates":[-4.687057105401,55.76507452727905],"type":"Point"}
}