{
  "type": "Feature",
  "properties": {
    "date:inception_lower": "1980-01-01",
    "date:inception_upper": "1980-01-01",
    "iso:country": "GB",
    "wof:name": "BA3 5DG",
    "wof:placetype": "postalcode"
  },
  "geometry": {"coordinates":[-2.472649,51.2422],"type":"Point"}
}
