{
  "type": "Feature",
  "properties": {
    "iso:country": "GB",
    "wof:name": "ME13 7PY",
    "wof:placetype": "postalcode"
  },
  "geometry": {"coordinates":[0.873119,51.315355],"type":"Point"}
}
