{
  "type": "Feature",
  "properties": {
    "date:inception_lower":"1987-04-01",
    "date:inception_upper":"1987-04-30",
    "iso:country":"GB",
    "wof:name":"ME13 7PY",
    "wof:placetype":"postalcode"
},
  "geometry": {"coordinates":[0.873119,51.315355],"type":"Point"}
}