{
  "type": "Feature",
  "properties": {
    "iso:country":"GB",
    "wof:name":"ME13 7PY",
    "wof:placetype":"postalcode"
},
  "geometry": {"coordinates":[0.87311850642265,51.31535541272984],"type":"Point"}
}