{
  "type": "Feature",
  "properties": {
    "date:inception_lower": "1980-01-01",
    "date:inception_upper": "1980-01-01",
    "iso:country": "GB",
    "wof:name": "NN6 9BJ",
    "wof:placetype": "postalcode"
  },
  "geometry": {"coordinates":[-0.908655,52.326003],"type":"Point"}
}
