{
  "type": "Feature",
  "properties": {
    "iso:country": "GB",
    "wof:name": "NR12 7JJ",
    "wof:placetype": "postalcode"
  },
  "geometry": {"coordinates":[1.358664,52.733086],"type":"Point"}
}
