{
  "type": "Feature",
  "properties": {
    "date:inception_lower":"1980-01-01",
    "date:inception_upper":"1980-01-31",
    "iso:country":"GB",
    "wof:name":"NE20 0DX",
    "wof:placetype":"postalcode"
},
  "geometry": {"coordinates":[-1.851578,55.100297],"type":"Point"}
}