{
  "type": "Feature",
  "properties": {
    "iso:country": "GB",
    "wof:name": "NE20 0DX",
    "wof:placetype": "postalcode"
  },
  "geometry": {"coordinates":[-1.851578,55.100297],"type":"Point"}
}
