{
  "type": "Feature",
  "properties": {
    "iso:country":"GB",
    "wof:name":"NE20 0DX",
    "wof:placetype":"postalcode"
},
  "geometry": {"coordinates":[-1.8515783424711,55.10029729332946],"type":"Point"}
}