{
  "type": "Feature",
  "properties": {
    "iso:country": "GB",
    "wof:name": "HU5 2NT",
    "wof:placetype": "postalcode"
  },
  "geometry": {"coordinates":[-0.356255,53.764987],"type":"Point"}
}
