{
  "type": "Feature",
  "properties": {
    "iso:country":"GB",
    "wof:name":"HU5 2NT",
    "wof:placetype":"postalcode"
},
  "geometry": {"coordinates":[-0.35625492670032,53.76498728592705],"type":"Point"}
}