{
  "type": "Feature",
  "properties": {
    "iso:country":"GB",
    "wof:name":"KT18 7RD",
    "wof:placetype":"postalcode"
},
  "geometry": {"coordinates":[-0.26873205042807,51.32683655493665],"type":"Point"}
}