{
  "type": "Feature",
  "properties": {
    "date:inception_lower":"1980-01-01",
    "date:inception_upper":"1980-01-31",
    "iso:country":"GB",
    "wof:name":"SY4 3HZ",
    "wof:placetype":"postalcode"
},
  "geometry": {"coordinates":[-2.778413,52.754135],"type":"Point"}
}