{
  "type": "Feature",
  "properties": {
    "iso:country":"GB",
    "wof:name":"SY4 3HZ",
    "wof:placetype":"postalcode"
},
  "geometry": {"coordinates":[-2.77841513286074,52.75411997011769],"type":"Point"}
}