{
  "type": "Feature",
  "properties": {
    "iso:country": "GB",
    "wof:name": "SY4 3HZ",
    "wof:placetype": "postalcode"
  },
  "geometry": {"coordinates":[-2.778426,52.754072],"type":"Point"}
}
