{
  "type": "Feature",
  "properties": {
    "iso:country": "GB",
    "wof:name": "SE10 0TJ",
    "wof:placetype": "postalcode"
  },
  "geometry": {"coordinates":[0.004525,51.489845],"type":"Point"}
}
