{
  "type": "Feature",
  "properties": {
    "iso:country":"GB",
    "wof:name":"WA11 8LZ",
    "wof:placetype":"postalcode"
},
  "geometry": {"coordinates":[-2.76949628470641,53.48771545051111],"type":"Point"}
}