{
  "type": "Feature",
  "properties": {
    "iso:country":"GB",
    "wof:name":"TN17 4PA",
    "wof:placetype":"postalcode"
},
  "geometry": {"coordinates":[0.62946624639026,51.05366481391699],"type":"Point"}
}