{
  "type": "Feature",
  "properties": {
    "iso:country":"GB",
    "wof:name":"BD12 7AU",
    "wof:placetype":"postalcode"
},
  "geometry": {"coordinates":[-1.74646824305275,53.74831106635975],"type":"Point"}
}