{
  "type": "Feature",
  "properties": {
    "iso:country":"GB",
    "wof:name":"LE2 4JG",
    "wof:placetype":"postalcode"
},
  "geometry": {"coordinates":[-1.06645722578712,52.59588655239308],"type":"Point"}
}