{
  "type": "Feature",
  "properties": {
    "iso:country":"GB",
    "wof:name":"ST15 0QW",
    "wof:placetype":"postalcode"
},
  "geometry": {"coordinates":[-2.22283782193849,52.88985133950598],"type":"Point"}
}