{
  "type": "Feature",
  "properties": {
    "iso:country": "GB",
    "wof:name": "NN5 4FT",
    "wof:placetype": "postalcode"
  },
  "geometry": {"coordinates":[-0.943356,52.236131],"type":"Point"}
}
