{
  "type": "Feature",
  "properties": {
    "date:inception_lower": "1980-01-01",
    "date:inception_upper": "1980-01-01",
    "iso:country": "GB",
    "wof:name": "SO22 4NY",
    "wof:placetype": "postalcode"
  },
  "geometry": {"coordinates":[-1.32717,51.061866],"type":"Point"}
}
