{
  "type": "Feature",
  "properties": {
    "iso:country":"GB",
    "wof:name":"SO22 4NY",
    "wof:placetype":"postalcode"
},
  "geometry": {"coordinates":[-1.32717008529322,51.0618657722605],"type":"Point"}
}