{
  "type": "Feature",
  "properties": {
    "date:inception_lower": "2003-08-01",
    "date:inception_upper": "2003-08-01",
    "iso:country": "GB",
    "wof:name": "ST3 5YQ",
    "wof:placetype": "postalcode"
  },
  "geometry": {"coordinates":[-2.11762,52.991734],"type":"Point"}
}
