{
  "type": "Feature",
  "properties": {
    "iso:country":"GB",
    "wof:name":"NN6 0JN",
    "wof:placetype":"postalcode"
},
  "geometry": {"coordinates":[-0.75159848337131,52.26720417614765],"type":"Point"}
}