{
  "type": "Feature",
  "properties": {
    "iso:country":"GB",
    "wof:name":"SG1 9SA",
    "wof:placetype":"postalcode"
},
  "geometry": {"coordinates":[-0.20323411944448,51.90117715526046],"type":"Point"}
}