{
  "type": "Feature",
  "properties": {
    "date:inception_lower": "2000-12-01",
    "date:inception_upper": "2000-12-01",
    "iso:country": "GB",
    "wof:name": "W1K 2EY",
    "wof:placetype": "postalcode"
  },
  "geometry": {"coordinates":[-0.150007,51.510494],"type":"Point"}
}
