{
  "type": "Feature",
  "properties": {
    "iso:country":"GB",
    "wof:name":"OX7 5SZ",
    "wof:placetype":"postalcode"
},
  "geometry": {"coordinates":[-1.52321080546825,51.94996906526141],"type":"Point"}
}