{
  "type": "Feature",
  "properties": {
    "date:inception_lower": "1993-01-01",
    "date:inception_upper": "1993-01-01",
    "iso:country": "GB",
    "wof:name": "L4 9XU",
    "wof:placetype": "postalcode"
  },
  "geometry": {"coordinates":[-2.93999,53.442415],"type":"Point"}
}
