{
  "type": "Feature",
  "properties": {
    "iso:country": "GB",
    "wof:name": "HR4 8RQ",
    "wof:placetype": "postalcode"
  },
  "geometry": {"coordinates":[-2.871569,52.158101],"type":"Point"}
}
