{
  "type": "Feature",
  "properties": {
    "iso:country":"GB",
    "wof:name":"HR4 8RQ",
    "wof:placetype":"postalcode"
},
  "geometry": {"coordinates":[-2.87156950426834,52.15810077274478],"type":"Point"}
}