{
  "type": "Feature",
  "properties": {
    "date:inception_lower": "2002-05-01",
    "date:inception_upper": "2002-05-01",
    "iso:country": "GB",
    "wof:name": "HR4 8RQ",
    "wof:placetype": "postalcode"
  },
  "geometry": {"coordinates":[-2.871569,52.158101],"type":"Point"}
}
