{
  "type": "Feature",
  "properties": {
    "iso:country":"GB",
    "wof:name":"OL12 7QN",
    "wof:placetype":"postalcode"
},
  "geometry": {"coordinates":[-2.19396812265236,53.62300975284071],"type":"Point"}
}