{
  "type": "Feature",
  "properties": {
    "iso:country":"GB",
    "wof:name":"S62 5HS",
    "wof:placetype":"postalcode"
},
  "geometry": {"coordinates":[-1.32888916238514,53.46077040769751],"type":"Point"}
}