{
  "type": "Feature",
  "properties": {
    "iso:country":"GB",
    "wof:name":"NE49 0JL",
    "wof:placetype":"postalcode"
},
  "geometry": {"coordinates":[-2.53253789853488,54.94388593917937],"type":"Point"}
}