{
  "type": "Feature",
  "properties": {
    "date:inception_lower":"1980-01-01",
    "date:inception_upper":"1980-01-31",
    "iso:country":"GB",
    "wof:name":"NE49 0JL",
    "wof:placetype":"postalcode"
},
  "geometry": {"coordinates":[-2.532538,54.943886],"type":"Point"}
}