{
  "type": "Feature",
  "properties": {
    "iso:country":"GB",
    "wof:name":"BN25 3UE",
    "wof:placetype":"postalcode"
},
  "geometry": {"coordinates":[0.12932563830458,50.77882409933029],"type":"Point"}
}