{
  "type": "Feature",
  "properties": {
    "iso:country":"GB",
    "wof:name":"W1F 7AL",
    "wof:placetype":"postalcode"
},
  "geometry": {"coordinates":[-0.13709188151588,51.51338325550881],"type":"Point"}
}