{
  "type": "Feature",
  "properties": {
    "iso:country": "GB",
    "wof:name": "PL24 2DQ",
    "wof:placetype": "postalcode"
  },
  "geometry": {"coordinates":[-4.720418,50.350082],"type":"Point"}
}
