{
  "type": "Feature",
  "properties": {
    "iso:country":"GB",
    "wof:name":"PL24 2DQ",
    "wof:placetype":"postalcode"
},
  "geometry": {"coordinates":[-4.72041763910824,50.35008201945558],"type":"Point"}
}