{
  "type": "Feature",
  "properties": {
    "date:inception_lower": "2008-02-01",
    "date:inception_upper": "2008-02-01",
    "iso:country": "GB",
    "wof:name": "PL24 2DQ",
    "wof:placetype": "postalcode"
  },
  "geometry": {"coordinates":[-4.720418,50.350082],"type":"Point"}
}
