{
  "type": "Feature",
  "properties": {
    "iso:country":"GB",
    "wof:name":"IV30 9DA",
    "wof:placetype":"postalcode"
},
  "geometry": {"coordinates":[-3.32145465410207,57.64723051754],"type":"Point"}
}