{
  "type": "Feature",
  "properties": {
    "iso:country":"GB",
    "wof:name":"CM8 2HA",
    "wof:placetype":"postalcode"
},
  "geometry": {"coordinates":[0.63155754435321,51.8047248076616],"type":"Point"}
}