{
  "type": "Feature",
  "properties": {
    "iso:country": "GB",
    "wof:name": "B77 5FU",
    "wof:placetype": "postalcode"
  },
  "geometry": {"coordinates":[-1.671621,52.60284],"type":"Point"}
}
