{
  "type": "Feature",
  "properties": {
    "date:inception_lower":"2008-04-01",
    "date:inception_upper":"2008-04-30",
    "iso:country":"GB",
    "wof:name":"B77 5FU",
    "wof:placetype":"postalcode"
},
  "geometry": {"coordinates":[-1.671621,52.60284],"type":"Point"}
}