{
  "type": "Feature",
  "properties": {
    "iso:country":"GB",
    "wof:name":"CM3 3PW",
    "wof:placetype":"postalcode"
},
  "geometry": {"coordinates":[0.46940180280757,51.77707389091494],"type":"Point"}
}