{
  "type": "Feature",
  "properties": {
    "date:inception_lower":"1990-02-01",
    "date:inception_upper":"1990-02-28",
    "iso:country":"GB",
    "wof:name":"LU1 3LG",
    "wof:placetype":"postalcode"
},
  "geometry": {"coordinates":[-0.410197,51.862344],"type":"Point"}
}