{
  "type": "Feature",
  "properties": {
    "iso:country":"GB",
    "wof:name":"LU1 3LG",
    "wof:placetype":"postalcode"
},
  "geometry": {"coordinates":[-0.41019654432238,51.86234366095033],"type":"Point"}
}