{
  "type": "Feature",
  "properties": {
    "date:inception_lower": "2018-08-01",
    "date:inception_upper": "2018-08-01",
    "iso:country": "GB",
    "wof:name": "DL10 4FA",
    "wof:placetype": "postalcode"
  },
  "geometry": {"coordinates":[-1.744666,54.404679],"type":"Point"}
}
