{
  "type": "Feature",
  "properties": {
    "date:inception_lower": "1980-01-01",
    "date:inception_upper": "1980-01-01",
    "iso:country": "GB",
    "wof:name": "SA14 9TE",
    "wof:placetype": "postalcode"
  },
  "geometry": {"coordinates":[-4.091109,51.669093],"type":"Point"}
}
