{
  "type": "Feature",
  "properties": {
    "iso:country":"GB",
    "wof:name":"SA14 9TE",
    "wof:placetype":"postalcode"
},
  "geometry": {"coordinates":[-4.09110895776557,51.66909323656434],"type":"Point"}
}