{
  "type": "Feature",
  "properties": {
    "iso:country":"GB",
    "wof:name":"LA6 1PZ",
    "wof:placetype":"postalcode"
},
  "geometry": {"coordinates":[-2.73089714072019,54.20287173742729],"type":"Point"}
}