{
  "type": "Feature",
  "properties": {
    "date:inception_lower": "1980-01-01",
    "date:inception_upper": "1980-01-01",
    "iso:country": "GB",
    "wof:name": "LA6 1PZ",
    "wof:placetype": "postalcode"
  },
  "geometry": {"coordinates":[-2.730897,54.202872],"type":"Point"}
}
