{
  "type": "Feature",
  "properties": {
    "iso:country": "GB",
    "wof:name": "TS17 0TR",
    "wof:placetype": "postalcode"
  },
  "geometry": {"coordinates":[-1.311758,54.520594],"type":"Point"}
}
