{
  "type": "Feature",
  "properties": {
    "iso:country":"GB",
    "wof:name":"TS17 0TR",
    "wof:placetype":"postalcode"
},
  "geometry": {"coordinates":[-1.31175849694553,54.5205939316885],"type":"Point"}
}