{
  "type": "Feature",
  "properties": {
    "iso:country":"GB",
    "wof:name":"WD25 7EP",
    "wof:placetype":"postalcode"
},
  "geometry": {"coordinates":[-0.39906185576423,51.6975698410534],"type":"Point"}
}