{
  "type": "Feature",
  "properties": {
    "iso:country": "GB",
    "wof:name": "BA2 4NR",
    "wof:placetype": "postalcode"
  },
  "geometry": {"coordinates":[-2.353425,51.375645],"type":"Point"}
}
