{
  "type": "Feature",
  "properties": {
    "date:inception_lower": "2019-01-01",
    "date:inception_upper": "2019-01-01",
    "iso:country": "GB",
    "wof:name": "BS15 3FW",
    "wof:placetype": "postalcode"
  },
  "geometry": {"coordinates":[-2.505961,51.449778],"type":"Point"}
}
