{
  "type": "Feature",
  "properties": {
    "date:inception_lower": "2012-08-01",
    "date:inception_upper": "2012-08-01",
    "iso:country": "GB",
    "wof:name": "BH2 5PA",
    "wof:placetype": "postalcode"
  },
  "geometry": {"coordinates":[-1.884688,50.717563],"type":"Point"}
}
