{
  "type": "Feature",
  "properties": {
    "iso:country":"GB",
    "wof:name":"UB6 0TB",
    "wof:placetype":"postalcode"
},
  "geometry": {"coordinates":[-0.34724218363846,51.55449793434287],"type":"Point"}
}