{
  "type": "Feature",
  "properties": {
    "date:inception_lower": "1988-03-01",
    "date:inception_upper": "1988-03-01",
    "iso:country": "GB",
    "wof:name": "S42 6LU",
    "wof:placetype": "postalcode"
  },
  "geometry": {"coordinates":[-1.42456,53.201674],"type":"Point"}
}
