{
  "type": "Feature",
  "properties": {
    "iso:country":"GB",
    "wof:name":"S42 6LU",
    "wof:placetype":"postalcode"
},
  "geometry": {"coordinates":[-1.42460648836163,53.20164623250572],"type":"Point"}
}