{
  "type": "Feature",
  "properties": {
    "date:inception_lower":"1980-01-01",
    "date:inception_upper":"1980-01-31",
    "iso:country":"GB",
    "wof:name":"CA8 1BW",
    "wof:placetype":"postalcode"
},
  "geometry": {"coordinates":[-2.739222,54.947127],"type":"Point"}
}