{
  "type": "Feature",
  "properties": {
    "date:inception_lower": "1980-01-01",
    "date:inception_upper": "1980-01-01",
    "iso:country": "GB",
    "wof:name": "SE20 7UT",
    "wof:placetype": "postalcode"
  },
  "geometry": {"coordinates":[-0.062549,51.406727],"type":"Point"}
}
