{
  "type": "Feature",
  "properties": {
    "iso:country":"GB",
    "wof:name":"SE20 7UT",
    "wof:placetype":"postalcode"
},
  "geometry": {"coordinates":[-0.06254888831676,51.40672749963417],"type":"Point"}
}