{
  "type": "Feature",
  "properties": {
    "iso:country": "GB",
    "wof:name": "OX26 4UF",
    "wof:placetype": "postalcode"
  },
  "geometry": {"coordinates":[-1.143649,51.905266],"type":"Point"}
}
