{
  "type": "Feature",
  "properties": {
    "date:inception_lower": "2000-10-01",
    "date:inception_upper": "2000-10-01",
    "iso:country": "GB",
    "wof:name": "OX26 4UF",
    "wof:placetype": "postalcode"
  },
  "geometry": {"coordinates":[-1.143649,51.905266],"type":"Point"}
}
