{
  "type": "Feature",
  "properties": {
    "iso:country": "GB",
    "wof:name": "NN1 1DH",
    "wof:placetype": "postalcode"
  },
  "geometry": {"coordinates":[-0.894463,52.234778],"type":"Point"}
}
