{
  "type": "Feature",
  "properties": {
    "iso:country":"GB",
    "wof:name":"NN1 1DH",
    "wof:placetype":"postalcode"
},
  "geometry": {"coordinates":[-0.89446331118866,52.2347779497476],"type":"Point"}
}