{
  "type": "Feature",
  "properties": {
    "date:inception_lower": "1980-01-01",
    "date:inception_upper": "1980-01-01",
    "iso:country": "GB",
    "wof:name": "LL11 6BN",
    "wof:placetype": "postalcode"
  },
  "geometry": {"coordinates":[-3.048513,53.077359],"type":"Point"}
}
