{
  "type": "Feature",
  "properties": {
    "date:inception_lower": "1998-06-01",
    "date:inception_upper": "1998-06-01",
    "iso:country": "GB",
    "wof:name": "HU18 1PP",
    "wof:placetype": "postalcode"
  },
  "geometry": {"coordinates":[-0.164766,53.911377],"type":"Point"}
}
