{
  "type": "Feature",
  "properties": {
    "iso:country":"GB",
    "wof:name":"PR5 0JH",
    "wof:placetype":"postalcode"
},
  "geometry": {"coordinates":[-2.61802214809827,53.74053050123253],"type":"Point"}
}