{
  "type": "Feature",
  "properties": {
    "iso:country": "GB",
    "wof:name": "CB22 6RU",
    "wof:placetype": "postalcode"
  },
  "geometry": {"coordinates":[0.063816,52.115421],"type":"Point"}
}
