{
  "type": "Feature",
  "properties": {
    "iso:country":"GB",
    "wof:name":"CB22 6RU",
    "wof:placetype":"postalcode"
},
  "geometry": {"coordinates":[0.06381636941719,52.11542100379629],"type":"Point"}
}