{
  "type": "Feature",
  "properties": {
    "iso:country":"GB",
    "wof:name":"PO9 2HN",
    "wof:placetype":"postalcode"
},
  "geometry": {"coordinates":[-0.9755612365974,50.86277164930817],"type":"Point"}
}