{
  "type": "Feature",
  "properties": {
    "iso:country":"GB",
    "wof:name":"E18 2AW",
    "wof:placetype":"postalcode"
},
  "geometry": {"coordinates":[0.02558864298035,51.5895789924125],"type":"Point"}
}