{
  "type": "Feature",
  "properties": {
    "iso:country":"GB",
    "wof:name":"M18 8PY",
    "wof:placetype":"postalcode"
},
  "geometry": {"coordinates":[-2.16727309008136,53.4637585357813],"type":"Point"}
}