{
  "type": "Feature",
  "properties": {
    "iso:country": "GB",
    "wof:name": "PA15 3JE",
    "wof:placetype": "postalcode"
  },
  "geometry": {"coordinates":[-4.73038,55.93416],"type":"Point"}
}
