{
  "type": "Feature",
  "properties": {
    "date:inception_lower": "1980-01-01",
    "date:inception_upper": "1980-01-01",
    "iso:country": "GB",
    "wof:name": "PA15 3JE",
    "wof:placetype": "postalcode"
  },
  "geometry": {"coordinates":[-4.730412,55.934159],"type":"Point"}
}
