{
  "type": "Feature",
  "properties": {
    "iso:country": "GB",
    "wof:name": "CH62 1EJ",
    "wof:placetype": "postalcode"
  },
  "geometry": {"coordinates":[-2.995926,53.366661],"type":"Point"}
}
