{
  "type": "Feature",
  "properties": {
    "iso:country":"GB",
    "wof:name":"KA10 7ER",
    "wof:placetype":"postalcode"
},
  "geometry": {"coordinates":[-4.62493001541114,55.53598580898703],"type":"Point"}
}