{
  "type": "Feature",
  "properties": {
    "iso:country": "GB",
    "wof:name": "KA3 2PE",
    "wof:placetype": "postalcode"
  },
  "geometry": {"coordinates":[-4.595535,55.642786],"type":"Point"}
}
