{
  "type": "Feature",
  "properties": {
    "date:inception_lower":"1980-01-01",
    "date:inception_upper":"1980-01-31",
    "iso:country":"GB",
    "wof:name":"KA3 2PE",
    "wof:placetype":"postalcode"
},
  "geometry": {"coordinates":[-4.595535,55.642786],"type":"Point"}
}