{
  "type": "Feature",
  "properties": {
    "iso:country":"GB",
    "wof:name":"KA3 2PE",
    "wof:placetype":"postalcode"
},
  "geometry": {"coordinates":[-4.59553467842868,55.64278594235326],"type":"Point"}
}