{
  "type": "Feature",
  "properties": {
    "iso:country":"GB",
    "wof:name":"SY12 9EG",
    "wof:placetype":"postalcode"
},
  "geometry": {"coordinates":[-2.97186652791209,52.93373691769885],"type":"Point"}
}