{
  "type": "Feature",
  "properties": {
    "date:inception_lower": "1993-01-01",
    "date:inception_upper": "1993-01-01",
    "iso:country": "GB",
    "wof:name": "SY12 9EG",
    "wof:placetype": "postalcode"
  },
  "geometry": {"coordinates":[-2.971866,52.933737],"type":"Point"}
}
