{
  "type": "Feature",
  "properties": {
    "iso:country":"GB",
    "wof:name":"CM3 2NY",
    "wof:placetype":"postalcode"
},
  "geometry": {"coordinates":[0.57438181147709,51.76134908088842],"type":"Point"}
}