{
  "type": "Feature",
  "properties": {
    "iso:country": "GB",
    "wof:name": "CM3 2NY",
    "wof:placetype": "postalcode"
  },
  "geometry": {"coordinates":[0.574382,51.761349],"type":"Point"}
}
