{
  "type": "Feature",
  "properties": {
    "iso:country": "GB",
    "wof:name": "EX5 2BW",
    "wof:placetype": "postalcode"
  },
  "geometry": {"coordinates":[-3.383635,50.725261],"type":"Point"}
}
