{
  "type": "Feature",
  "properties": {
    "iso:country":"GB",
    "wof:name":"S21 1FY",
    "wof:placetype":"postalcode"
},
  "geometry": {"coordinates":[-1.31672057936265,53.32450389959227],"type":"Point"}
}