{
  "type": "Feature",
  "properties": {
    "iso:country":"GB",
    "wof:name":"S70 2DL",
    "wof:placetype":"postalcode"
},
  "geometry": {"coordinates":[-1.48544848322209,53.55455980270609],"type":"Point"}
}