{
  "type": "Feature",
  "properties": {
    "date:inception_lower": "1980-01-01",
    "date:inception_upper": "1980-01-01",
    "iso:country": "GB",
    "wof:name": "RM18 8PP",
    "wof:placetype": "postalcode"
  },
  "geometry": {"coordinates":[0.425582,51.469749],"type":"Point"}
}
