{
  "type": "Feature",
  "properties": {
    "iso:country":"GB",
    "wof:name":"RM18 8PP",
    "wof:placetype":"postalcode"
},
  "geometry": {"coordinates":[0.42555212586757,51.46974817047531],"type":"Point"}
}