{
  "type": "Feature",
  "properties": {
    "date:inception_lower": "1980-01-01",
    "date:inception_upper": "1980-01-01",
    "iso:country": "GB",
    "wof:name": "PL24 2SU",
    "wof:placetype": "postalcode"
  },
  "geometry": {"coordinates":[-4.745023,50.378897],"type":"Point"}
}
