{
  "type": "Feature",
  "properties": {
    "iso:country":"GB",
    "wof:name":"PL24 2SU",
    "wof:placetype":"postalcode"
},
  "geometry": {"coordinates":[-4.74502495949974,50.37891743636758],"type":"Point"}
}