{
  "type": "Feature",
  "properties": {
    "iso:country":"GB",
    "wof:name":"TW12 2TX",
    "wof:placetype":"postalcode"
},
  "geometry": {"coordinates":[-0.3616382999278,51.41825955947358],"type":"Point"}
}