{
  "type": "Feature",
  "properties": {
    "iso:country":"GB",
    "wof:name":"CV5 6GL",
    "wof:placetype":"postalcode"
},
  "geometry": {"coordinates":[-1.53145816958734,52.40279955256138],"type":"Point"}
}