{
  "type": "Feature",
  "properties": {
    "iso:country": "GB",
    "wof:name": "CV5 6GL",
    "wof:placetype": "postalcode"
  },
  "geometry": {"coordinates":[-1.531458,52.4028],"type":"Point"}
}
