{
  "type": "Feature",
  "properties": {
    "iso:country":"GB",
    "wof:name":"L36 0SA",
    "wof:placetype":"postalcode"
},
  "geometry": {"coordinates":[-2.83550223489814,53.403038392144],"type":"Point"}
}