{
  "type": "Feature",
  "properties": {
    "iso:country":"GB",
    "wof:name":"PL14 5HY",
    "wof:placetype":"postalcode"
},
  "geometry": {"coordinates":[-4.46136491617834,50.49356614786862],"type":"Point"}
}