{
  "type": "Feature",
  "properties": {
    "iso:country": "GB",
    "wof:name": "PL14 5HY",
    "wof:placetype": "postalcode"
  },
  "geometry": {"coordinates":[-4.461365,50.493566],"type":"Point"}
}
