{
  "type": "Feature",
  "properties": {
    "iso:country":"GB",
    "wof:name":"RG14 7LW",
    "wof:placetype":"postalcode"
},
  "geometry": {"coordinates":[-1.32325134959795,51.39555491064797],"type":"Point"}
}