{
  "type": "Feature",
  "properties": {
    "iso:country":"GB",
    "wof:name":"CB8 0UX",
    "wof:placetype":"postalcode"
},
  "geometry": {"coordinates":[0.31573459321836,52.20587920365124],"type":"Point"}
}