{
  "type": "Feature",
  "properties": {
    "iso:country": "GB",
    "wof:name": "CB8 0UX",
    "wof:placetype": "postalcode"
  },
  "geometry": {"coordinates":[0.315735,52.205879],"type":"Point"}
}
