{
  "type": "Feature",
  "properties": {
    "iso:country":"GB",
    "wof:name":"NE39 1LD",
    "wof:placetype":"postalcode"
},
  "geometry": {"coordinates":[-1.7502539951176,54.9203636461712],"type":"Point"}
}