{
  "type": "Feature",
  "properties": {
    "date:inception_lower":"1980-01-01",
    "date:inception_upper":"1980-01-31",
    "iso:country":"GB",
    "wof:name":"G66 4LL",
    "wof:placetype":"postalcode"
},
  "geometry": {"coordinates":[-4.146448,55.92364],"type":"Point"}
}