{
  "type": "Feature",
  "properties": {
    "date:inception_lower":"1980-01-01",
    "date:inception_upper":"1980-01-31",
    "iso:country":"GB",
    "wof:name":"LA8 0DQ",
    "wof:placetype":"postalcode"
},
  "geometry": {"coordinates":[-2.648768,54.356785],"type":"Point"}
}