{
  "type": "Feature",
  "properties": {
    "iso:country":"GB",
    "wof:name":"LA8 0DQ",
    "wof:placetype":"postalcode"
},
  "geometry": {"coordinates":[-2.64921129889265,54.35673691535087],"type":"Point"}
}