{
  "type": "Feature",
  "properties": {
    "iso:country": "GB",
    "wof:name": "LA8 0DQ",
    "wof:placetype": "postalcode"
  },
  "geometry": {"coordinates":[-2.648768,54.356785],"type":"Point"}
}
