{
  "type": "Feature",
  "properties": {
    "date:inception_lower": "1980-01-01",
    "date:inception_upper": "1980-01-01",
    "iso:country": "GB",
    "wof:name": "IV51 9YD",
    "wof:placetype": "postalcode"
  },
  "geometry": {"coordinates":[-6.359319,57.583291],"type":"Point"}
}
