{
  "type": "Feature",
  "properties": {
    "iso:country":"GB",
    "wof:name":"IV51 9YD",
    "wof:placetype":"postalcode"
},
  "geometry": {"coordinates":[-6.35962357499617,57.58275842081223],"type":"Point"}
}