{
  "type": "Feature",
  "properties": {
    "iso:country": "GB",
    "wof:name": "BA14 6AN",
    "wof:placetype": "postalcode"
  },
  "geometry": {"coordinates":[-2.18517,51.297139],"type":"Point"}
}
