{
  "type": "Feature",
  "properties": {
    "date:inception_lower":"1990-02-01",
    "date:inception_upper":"1990-02-28",
    "iso:country":"GB",
    "wof:name":"E1 1LJ",
    "wof:placetype":"postalcode"
},
  "geometry": {"coordinates":[-0.066994,51.514686],"type":"Point"}
}