{
  "type": "Feature",
  "properties": {
    "iso:country":"GB",
    "wof:name":"AB25 2XS",
    "wof:placetype":"postalcode"
},
  "geometry": {"coordinates":[-2.11932644321725,57.14941582187106],"type":"Point"}
}