{
  "type": "Feature",
  "properties": {
    "date:inception_lower":"2005-01-01",
    "date:inception_upper":"2005-01-31",
    "iso:country":"GB",
    "wof:name":"RH20 3DN",
    "wof:placetype":"postalcode"
},
  "geometry": {"coordinates":[-0.442886,50.925978],"type":"Point"}
}