{
  "type": "Feature",
  "properties": {
    "iso:country": "GB",
    "wof:name": "RH20 3DN",
    "wof:placetype": "postalcode"
  },
  "geometry": {"coordinates":[-0.442886,50.925978],"type":"Point"}
}
