{
  "type": "Feature",
  "properties": {
    "iso:country":"GB",
    "wof:name":"G75 8DS",
    "wof:placetype":"postalcode"
},
  "geometry": {"coordinates":[-4.19966472676364,55.75363919057848],"type":"Point"}
}