{
  "type": "Feature",
  "properties": {
    "iso:country":"GB",
    "wof:name":"TS6 9HF",
    "wof:placetype":"postalcode"
},
  "geometry": {"coordinates":[-1.14424537349482,54.5575047992423],"type":"Point"}
}