{
  "type": "Feature",
  "properties": {
    "iso:country": "GB",
    "wof:name": "TS6 9HF",
    "wof:placetype": "postalcode"
  },
  "geometry": {"coordinates":[-1.144245,54.557505],"type":"Point"}
}
