{
  "type": "Feature",
  "properties": {
    "iso:country":"GB",
    "wof:name":"S40 4DX",
    "wof:placetype":"postalcode"
},
  "geometry": {"coordinates":[-1.44051498524241,53.24112950248882],"type":"Point"}
}