{
  "type": "Feature",
  "properties": {
    "iso:country":"GB",
    "wof:name":"S70 1HP",
    "wof:placetype":"postalcode"
},
  "geometry": {"coordinates":[-1.47613299575723,53.54983641070441],"type":"Point"}
}