{
  "type": "Feature",
  "properties": {
    "date:inception_lower":"1994-05-01",
    "date:inception_upper":"1994-05-31",
    "iso:country":"GB",
    "wof:name":"WF13 4NH",
    "wof:placetype":"postalcode"
},
  "geometry": {"coordinates":[-1.650242,53.696621],"type":"Point"}
}