{
  "type": "Feature",
  "properties": {
    "iso:country": "GB",
    "wof:name": "WF13 4NH",
    "wof:placetype": "postalcode"
  },
  "geometry": {"coordinates":[-1.650242,53.696621],"type":"Point"}
}
