{
  "type": "Feature",
  "properties": {
    "date:inception_lower": "1999-06-01",
    "date:inception_upper": "1999-06-01",
    "iso:country": "GB",
    "wof:name": "NP11 4HU",
    "wof:placetype": "postalcode"
  },
  "geometry": {"coordinates":[-3.169019,51.658741],"type":"Point"}
}
