{
  "type": "Feature",
  "properties": {
    "iso:country":"GB",
    "wof:name":"NP11 4HU",
    "wof:placetype":"postalcode"
},
  "geometry": {"coordinates":[-3.16901905703866,51.65874081458898],"type":"Point"}
}