{
  "type": "Feature",
  "properties": {
    "iso:country":"GB",
    "wof:name":"SS6 8PX",
    "wof:placetype":"postalcode"
},
  "geometry": {"coordinates":[0.61901309036141,51.58528888980379],"type":"Point"}
}