{
  "type": "Feature",
  "properties": {
    "iso:country":"GB",
    "wof:name":"B27 6DA",
    "wof:placetype":"postalcode"
},
  "geometry": {"coordinates":[-1.81516284442233,52.44620468976014],"type":"Point"}
}