{
  "type": "Feature",
  "properties": {
    "iso:country": "GB",
    "wof:name": "L4 6UA",
    "wof:placetype": "postalcode"
  },
  "geometry": {"coordinates":[-2.958584,53.443777],"type":"Point"}
}
