{
  "type": "Feature",
  "properties": {
    "date:inception_lower": "1980-01-01",
    "date:inception_upper": "1980-01-01",
    "iso:country": "GB",
    "wof:name": "L4 6UA",
    "wof:placetype": "postalcode"
  },
  "geometry": {"coordinates":[-2.958584,53.443777],"type":"Point"}
}
