{
  "type": "Feature",
  "properties": {
    "iso:country":"GB",
    "wof:name":"W3 0RP",
    "wof:placetype":"postalcode"
},
  "geometry": {"coordinates":[-0.2794252253602,51.52215788608469],"type":"Point"}
}