{
  "type": "Feature",
  "properties": {
    "iso:country": "GB",
    "wof:name": "G69 9BN",
    "wof:placetype": "postalcode"
  },
  "geometry": {"coordinates":[-4.114506,55.897505],"type":"Point"}
}
