{
  "type": "Feature",
  "properties": {
    "iso:country":"GB",
    "wof:name":"G69 9BN",
    "wof:placetype":"postalcode"
},
  "geometry": {"coordinates":[-4.11439085816477,55.89752966607412],"type":"Point"}
}