{
  "type": "Feature",
  "properties": {
    "iso:country": "GB",
    "wof:name": "KY5 8HA",
    "wof:placetype": "postalcode"
  },
  "geometry": {"coordinates":[-3.321284,56.158574],"type":"Point"}
}
