{
  "type": "Feature",
  "properties": {
    "date:inception_lower":"1984-03-01",
    "date:inception_upper":"1984-03-31",
    "iso:country":"GB",
    "wof:name":"KY5 8HA",
    "wof:placetype":"postalcode"
},
  "geometry": {"coordinates":[-3.321284,56.158574],"type":"Point"}
}