{
  "type": "Feature",
  "properties": {
    "iso:country":"GB",
    "wof:name":"SE16 4PQ",
    "wof:placetype":"postalcode"
},
  "geometry": {"coordinates":[-0.06210370519231,51.49983934321481],"type":"Point"}
}