{
  "type": "Feature",
  "properties": {
    "iso:country": "GB",
    "wof:name": "SE16 4PQ",
    "wof:placetype": "postalcode"
  },
  "geometry": {"coordinates":[-0.062104,51.499839],"type":"Point"}
}
