{
  "type": "Feature",
  "properties": {
    "iso:country": "GB",
    "wof:name": "SG18 8BW",
    "wof:placetype": "postalcode"
  },
  "geometry": {"coordinates":[-0.26417,52.083023],"type":"Point"}
}
