{
  "type": "Feature",
  "properties": {
    "iso:country": "GB",
    "wof:name": "CO7 8HJ",
    "wof:placetype": "postalcode"
  },
  "geometry": {"coordinates":[1.037792,51.842485],"type":"Point"}
}
