{
  "type": "Feature",
  "properties": {
    "iso:country":"GB",
    "wof:name":"CO7 8HJ",
    "wof:placetype":"postalcode"
},
  "geometry": {"coordinates":[1.03779166234491,51.84248521371172],"type":"Point"}
}