{
  "type": "Feature",
  "properties": {
    "date:inception_lower": "1980-01-01",
    "date:inception_upper": "1980-01-01",
    "iso:country": "GB",
    "wof:name": "CO7 8HJ",
    "wof:placetype": "postalcode"
  },
  "geometry": {"coordinates":[1.037792,51.842485],"type":"Point"}
}
