{
  "type": "Feature",
  "properties": {
    "iso:country": "GB",
    "wof:name": "TN27 0LY",
    "wof:placetype": "postalcode"
  },
  "geometry": {"coordinates":[0.798565,51.215402],"type":"Point"}
}
