{
  "type": "Feature",
  "properties": {
    "iso:country":"GB",
    "wof:name":"DL16 7PE",
    "wof:placetype":"postalcode"
},
  "geometry": {"coordinates":[-1.65508587768744,54.70095054723314],"type":"Point"}
}