{
  "type": "Feature",
  "properties": {
    "iso:country":"GB",
    "wof:name":"IP27 9EG",
    "wof:placetype":"postalcode"
},
  "geometry": {"coordinates":[0.52810900495778,52.41382084281971],"type":"Point"}
}