{
  "type": "Feature",
  "properties": {
    "iso:country":"GB",
    "wof:name":"N17 0BN",
    "wof:placetype":"postalcode"
},
  "geometry": {"coordinates":[-0.06235971112198,51.60141439010601],"type":"Point"}
}