{
  "type": "Feature",
  "properties": {
    "iso:country":"GB",
    "wof:name":"TS24 8JJ",
    "wof:placetype":"postalcode"
},
  "geometry": {"coordinates":[-1.22470564189864,54.69731815563431],"type":"Point"}
}