{
  "type": "Feature",
  "properties": {
    "iso:country":"GB",
    "wof:name":"S43 3DR",
    "wof:placetype":"postalcode"
},
  "geometry": {"coordinates":[-1.36642944510268,53.24948721043926],"type":"Point"}
}