{
  "type": "Feature",
  "properties": {
    "date:inception_lower": "1980-01-01",
    "date:inception_upper": "1980-01-01",
    "iso:country": "GB",
    "wof:name": "S43 3DR",
    "wof:placetype": "postalcode"
  },
  "geometry": {"coordinates":[-1.366429,53.249487],"type":"Point"}
}
