{
  "type": "Feature",
  "properties": {
    "iso:country":"GB",
    "wof:name":"TR26 2AB",
    "wof:placetype":"postalcode"
},
  "geometry": {"coordinates":[-5.47504938848591,50.20687933054411],"type":"Point"}
}