{
  "type": "Feature",
  "properties": {
    "iso:country": "GB",
    "wof:name": "BD23 4BQ",
    "wof:placetype": "postalcode"
  },
  "geometry": {"coordinates":[-2.221202,54.003598],"type":"Point"}
}
