{
  "type": "Feature",
  "properties": {
    "date:inception_lower": "2017-10-01",
    "date:inception_upper": "2017-10-01",
    "iso:country": "GB",
    "wof:name": "BD23 4BQ",
    "wof:placetype": "postalcode"
  },
  "geometry": {"coordinates":[-2.221202,54.003598],"type":"Point"}
}
