{
  "type": "Feature",
  "properties": {
    "iso:country":"GB",
    "wof:name":"L26 7YX",
    "wof:placetype":"postalcode"
},
  "geometry": {"coordinates":[-2.83736917867936,53.36789686399126],"type":"Point"}
}