{
  "type": "Feature",
  "properties": {
    "date:inception_lower": "1980-01-01",
    "date:inception_upper": "1980-01-01",
    "iso:country": "GB",
    "wof:name": "L26 7YX",
    "wof:placetype": "postalcode"
  },
  "geometry": {"coordinates":[-2.837369,53.367897],"type":"Point"}
}
