{
  "type": "Feature",
  "properties": {
    "date:inception_lower": "1980-01-01",
    "date:inception_upper": "1980-01-01",
    "iso:country": "GB",
    "wof:name": "NW8 8JG",
    "wof:placetype": "postalcode"
  },
  "geometry": {"coordinates":[-0.175967,51.525873],"type":"Point"}
}
