{
  "type": "Feature",
  "properties": {
    "iso:country":"GB",
    "wof:name":"NW8 8JG",
    "wof:placetype":"postalcode"
},
  "geometry": {"coordinates":[-0.17596664373576,51.52587329517464],"type":"Point"}
}