{
  "type": "Feature",
  "properties": {
    "iso:country": "GB",
    "wof:name": "DE56 0JA",
    "wof:placetype": "postalcode"
  },
  "geometry": {"coordinates":[-1.462562,53.013007],"type":"Point"}
}
