{
  "type": "Feature",
  "properties": {
    "iso:country": "GB",
    "wof:name": "SG8 5QN",
    "wof:placetype": "postalcode"
  },
  "geometry": {"coordinates":[-0.007036,52.135415],"type":"Point"}
}
