{
  "type": "Feature",
  "properties": {
    "iso:country":"GB",
    "wof:name":"IP33 1SD",
    "wof:placetype":"postalcode"
},
  "geometry": {"coordinates":[0.71090057102407,52.2465058031157],"type":"Point"}
}