{
  "type": "Feature",
  "properties": {
    "iso:country":"GB",
    "wof:name":"L26 7WG",
    "wof:placetype":"postalcode"
},
  "geometry": {"coordinates":[-2.83980671622573,53.37033369856652],"type":"Point"}
}