{
  "type": "Feature",
  "properties": {
    "date:inception_lower": "1995-01-01",
    "date:inception_upper": "1995-01-01",
    "iso:country": "GB",
    "wof:name": "EX3 0DG",
    "wof:placetype": "postalcode"
  },
  "geometry": {"coordinates":[-3.462865,50.685281],"type":"Point"}
}
