{
  "type": "Feature",
  "properties": {
    "iso:country":"GB",
    "wof:name":"EX3 0DG",
    "wof:placetype":"postalcode"
},
  "geometry": {"coordinates":[-3.46286469353811,50.68528091823281],"type":"Point"}
}