{
  "type": "Feature",
  "properties": {
    "iso:country":"GB",
    "wof:name":"WF5 8JU",
    "wof:placetype":"postalcode"
},
  "geometry": {"coordinates":[-1.57941398495301,53.67466010050173],"type":"Point"}
}