{
  "type": "Feature",
  "properties": {
    "iso:country": "GB",
    "wof:name": "LL55 2DY",
    "wof:placetype": "postalcode"
  },
  "geometry": {"coordinates":[-4.25736,53.139725],"type":"Point"}
}
