{
  "type": "Feature",
  "properties": {
    "iso:country":"GB",
    "wof:name":"GU1 3SN",
    "wof:placetype":"postalcode"
},
  "geometry": {"coordinates":[-0.56644174116971,51.23335394600297],"type":"Point"}
}