{
  "type": "Feature",
  "properties": {
    "iso:country": "GB",
    "wof:name": "CW1 4EE",
    "wof:placetype": "postalcode"
  },
  "geometry": {"coordinates":[-2.43562,53.105154],"type":"Point"}
}
