{
  "type": "Feature",
  "properties": {
    "iso:country":"GB",
    "wof:name":"CW1 4EE",
    "wof:placetype":"postalcode"
},
  "geometry": {"coordinates":[-2.43578418030956,53.10520903264862],"type":"Point"}
}