{
  "type": "Feature",
  "properties": {
    "iso:country": "GB",
    "wof:name": "PE32 1SJ",
    "wof:placetype": "postalcode"
  },
  "geometry": {"coordinates":[0.462377,52.703321],"type":"Point"}
}
