{
  "type": "Feature",
  "properties": {
    "date:inception_lower":"1980-01-01",
    "date:inception_upper":"1980-01-31",
    "iso:country":"GB",
    "wof:name":"PE32 1SJ",
    "wof:placetype":"postalcode"
},
  "geometry": {"coordinates":[0.462377,52.703321],"type":"Point"}
}