{
  "type": "Feature",
  "properties": {
    "iso:country":"GB",
    "wof:name":"NG20 8DN",
    "wof:placetype":"postalcode"
},
  "geometry": {"coordinates":[-1.22463563605125,53.20134925498373],"type":"Point"}
}