{
  "type": "Feature",
  "properties": {
    "date:inception_lower": "2001-06-01",
    "date:inception_upper": "2001-06-01",
    "iso:country": "GB",
    "wof:name": "SP1 3RF",
    "wof:placetype": "postalcode"
  },
  "geometry": {"coordinates":[-1.794122,51.071713],"type":"Point"}
}
