{
  "type": "Feature",
  "properties": {
    "iso:country":"GB",
    "wof:name":"SR4 6DW",
    "wof:placetype":"postalcode"
},
  "geometry": {"coordinates":[-1.39357511668761,54.90878278672077],"type":"Point"}
}