{
  "type": "Feature",
  "properties": {
    "iso:country": "GB",
    "wof:name": "SR4 6DW",
    "wof:placetype": "postalcode"
  },
  "geometry": {"coordinates":[-1.393575,54.908783],"type":"Point"}
}
