{
  "type": "Feature",
  "properties": {
    "iso:country":"GB",
    "wof:name":"KY7 6BJ",
    "wof:placetype":"postalcode"
},
  "geometry": {"coordinates":[-3.14313827766042,56.20225714098288],"type":"Point"}
}