{
  "type": "Feature",
  "properties": {
    "date:inception_lower": "1980-01-01",
    "date:inception_upper": "1980-01-01",
    "iso:country": "GB",
    "wof:name": "KY7 6BJ",
    "wof:placetype": "postalcode"
  },
  "geometry": {"coordinates":[-3.143138,56.202257],"type":"Point"}
}
