{
  "type": "Feature",
  "properties": {
    "iso:country": "GB",
    "wof:name": "WN6 7SQ",
    "wof:placetype": "postalcode"
  },
  "geometry": {"coordinates":[-2.660673,53.55783],"type":"Point"}
}
