{
  "type": "Feature",
  "properties": {
    "iso:country":"GB",
    "wof:name":"WN6 7SQ",
    "wof:placetype":"postalcode"
},
  "geometry": {"coordinates":[-2.66067322282213,53.55783024654624],"type":"Point"}
}