{
  "type": "Feature",
  "properties": {
    "date:inception_lower":"1992-08-01",
    "date:inception_upper":"1992-08-31",
    "iso:country":"GB",
    "wof:name":"WN6 7SQ",
    "wof:placetype":"postalcode"
},
  "geometry": {"coordinates":[-2.660673,53.55783],"type":"Point"}
}