{
  "type": "Feature",
  "properties": {
    "date:inception_lower": "1994-05-01",
    "date:inception_upper": "1994-05-01",
    "iso:country": "GB",
    "wof:name": "M33 6WF",
    "wof:placetype": "postalcode"
  },
  "geometry": {"coordinates":[-2.333329,53.426485],"type":"Point"}
}
