{
  "type": "Feature",
  "properties": {
    "iso:country":"GB",
    "wof:name":"SS9 5RB",
    "wof:placetype":"postalcode"
},
  "geometry": {"coordinates":[0.6523797344611,51.57221808445523],"type":"Point"}
}