{
  "type": "Feature",
  "properties": {
    "iso:country": "GB",
    "wof:name": "SS9 5RB",
    "wof:placetype": "postalcode"
  },
  "geometry": {"coordinates":[0.65238,51.572218],"type":"Point"}
}
