{
  "type": "Feature",
  "properties": {
    "date:inception_lower": "1980-01-01",
    "date:inception_upper": "1980-01-01",
    "iso:country": "GB",
    "wof:name": "SS9 5RB",
    "wof:placetype": "postalcode"
  },
  "geometry": {"coordinates":[0.65238,51.572218],"type":"Point"}
}
