{
  "type": "Feature",
  "properties": {
    "date:inception_lower":"1980-01-01",
    "date:inception_upper":"1980-01-31",
    "iso:country":"GB",
    "wof:name":"S5 8AT",
    "wof:placetype":"postalcode"
},
  "geometry": {"coordinates":[-1.483609,53.426573],"type":"Point"}
}