{
  "type": "Feature",
  "properties": {
    "iso:country":"GB",
    "wof:name":"SW8 4XS",
    "wof:placetype":"postalcode"
},
  "geometry": {"coordinates":[-0.13631668088193,51.47516164807406],"type":"Point"}
}