{
  "type": "Feature",
  "properties": {
    "iso:country":"GB",
    "wof:name":"TA23 0PD",
    "wof:placetype":"postalcode"
},
  "geometry": {"coordinates":[-3.36344076997087,51.16245254951139],"type":"Point"}
}