{
  "type": "Feature",
  "properties": {
    "date:inception_lower": "1980-01-01",
    "date:inception_upper": "1980-01-01",
    "iso:country": "GB",
    "wof:name": "M19 2LW",
    "wof:placetype": "postalcode"
  },
  "geometry": {"coordinates":[-2.205855,53.437245],"type":"Point"}
}
