{
  "type": "Feature",
  "properties": {
    "iso:country": "GB",
    "wof:name": "PO38 3EE",
    "wof:placetype": "postalcode"
  },
  "geometry": {"coordinates":[-1.223619,50.617167],"type":"Point"}
}
