{
  "type": "Feature",
  "properties": {
    "iso:country":"GB",
    "wof:name":"BB1 4AR",
    "wof:placetype":"postalcode"
},
  "geometry": {"coordinates":[-2.42612102242644,53.76098783888008],"type":"Point"}
}