{
  "type": "Feature",
  "properties": {
    "iso:country":"GB",
    "wof:name":"NW10 8HD",
    "wof:placetype":"postalcode"
},
  "geometry": {"coordinates":[-0.26127456233994,51.54833673167166],"type":"Point"}
}