{
  "type": "Feature",
  "properties": {
    "iso:country":"GB",
    "wof:name":"SG2 7DL",
    "wof:placetype":"postalcode"
},
  "geometry": {"coordinates":[-0.15797742370974,51.90844429590977],"type":"Point"}
}