{
  "type": "Feature",
  "properties": {
    "iso:country": "GB",
    "wof:name": "KT15 3NP",
    "wof:placetype": "postalcode"
  },
  "geometry": {"coordinates":[-0.494777,51.34968],"type":"Point"}
}
