{
  "type": "Feature",
  "properties": {
    "iso:country": "GB",
    "wof:name": "ST8 7AT",
    "wof:placetype": "postalcode"
  },
  "geometry": {"coordinates":[-2.174834,53.107838],"type":"Point"}
}
