{
  "type": "Feature",
  "properties": {
    "iso:country":"GB",
    "wof:name":"ST8 7AT",
    "wof:placetype":"postalcode"
},
  "geometry": {"coordinates":[-2.17483432664351,53.10783845281505],"type":"Point"}
}