{
  "type": "Feature",
  "properties": {
    "iso:country":"GB",
    "wof:name":"SW6 1RD",
    "wof:placetype":"postalcode"
},
  "geometry": {"coordinates":[-0.20073512677875,51.48485458597059],"type":"Point"}
}