{
  "type": "Feature",
  "properties": {
    "iso:country": "GB",
    "wof:name": "BN22 7FQ",
    "wof:placetype": "postalcode"
  },
  "geometry": {"coordinates":[0.306204,50.783955],"type":"Point"}
}
