{
  "type": "Feature",
  "properties": {
    "date:inception_lower": "2017-02-01",
    "date:inception_upper": "2017-02-01",
    "iso:country": "GB",
    "wof:name": "BN22 7FQ",
    "wof:placetype": "postalcode"
  },
  "geometry": {"coordinates":[0.306204,50.783955],"type":"Point"}
}
