{
  "type": "Feature",
  "properties": {
    "date:inception_lower": "1992-08-01",
    "date:inception_upper": "1992-08-01",
    "iso:country": "GB",
    "wof:name": "DN40 2QU",
    "wof:placetype": "postalcode"
  },
  "geometry": {"coordinates":[-0.202238,53.636282],"type":"Point"}
}
