{
  "type": "Feature",
  "properties": {
    "iso:country":"GB",
    "wof:name":"DN40 2QU",
    "wof:placetype":"postalcode"
},
  "geometry": {"coordinates":[-0.1892185008718,53.63109175980202],"type":"Point"}
}