{
  "type": "Feature",
  "properties": {
    "date:inception_lower": "1980-01-01",
    "date:inception_upper": "1980-01-01",
    "iso:country": "GB",
    "wof:name": "BH20 4SR",
    "wof:placetype": "postalcode"
  },
  "geometry": {"coordinates":[-2.122242,50.69368],"type":"Point"}
}
