{
  "type": "Feature",
  "properties": {
    "iso:country":"GB",
    "wof:name":"WA7 6RA",
    "wof:placetype":"postalcode"
},
  "geometry": {"coordinates":[-2.66090832453069,53.32760225660979],"type":"Point"}
}