{
  "type": "Feature",
  "properties": {
    "iso:country": "GB",
    "wof:name": "WA7 6RA",
    "wof:placetype": "postalcode"
  },
  "geometry": {"coordinates":[-2.660908,53.327602],"type":"Point"}
}
