{
  "type": "Feature",
  "properties": {
    "date:inception_lower":"1984-02-01",
    "date:inception_upper":"1984-02-29",
    "iso:country":"GB",
    "wof:name":"WA7 6RA",
    "wof:placetype":"postalcode"
},
  "geometry": {"coordinates":[-2.660908,53.327602],"type":"Point"}
}