{
  "type": "Feature",
  "properties": {
    "iso:country":"GB",
    "wof:name":"NP16 6LL",
    "wof:placetype":"postalcode"
},
  "geometry": {"coordinates":[-2.71630283191231,51.61939659112008],"type":"Point"}
}