{
  "type": "Feature",
  "properties": {
    "date:inception_lower": "1999-06-01",
    "date:inception_upper": "1999-06-01",
    "iso:country": "GB",
    "wof:name": "NP16 6LL",
    "wof:placetype": "postalcode"
  },
  "geometry": {"coordinates":[-2.71567,51.619275],"type":"Point"}
}
