{
  "type": "Feature",
  "properties": {
    "iso:country": "GB",
    "wof:name": "NP16 6LL",
    "wof:placetype": "postalcode"
  },
  "geometry": {"coordinates":[-2.716303,51.619397],"type":"Point"}
}
