{
  "type": "Feature",
  "properties": {
    "iso:country":"GB",
    "wof:name":"HX5 0DJ",
    "wof:placetype":"postalcode"
},
  "geometry": {"coordinates":[-1.8401031985386,53.68482768359899],"type":"Point"}
}