{
  "type": "Feature",
  "properties": {
    "iso:country":"GB",
    "wof:name":"SS5 5HF",
    "wof:placetype":"postalcode"
},
  "geometry": {"coordinates":[0.66432106493627,51.60586208473776],"type":"Point"}
}