{
  "type": "Feature",
  "properties": {
    "date:inception_lower": "1980-01-01",
    "date:inception_upper": "1980-01-01",
    "iso:country": "GB",
    "wof:name": "SS5 5HF",
    "wof:placetype": "postalcode"
  },
  "geometry": {"coordinates":[0.664662,51.606031],"type":"Point"}
}
