{
  "type": "Feature",
  "properties": {
    "iso:country":"GB",
    "wof:name":"HP16 9QH",
    "wof:placetype":"postalcode"
},
  "geometry": {"coordinates":[-0.68392059019513,51.70988193577232],"type":"Point"}
}