{
  "type": "Feature",
  "properties": {
    "date:inception_lower": "1980-01-01",
    "date:inception_upper": "1980-01-01",
    "iso:country": "GB",
    "wof:name": "HP16 9QH",
    "wof:placetype": "postalcode"
  },
  "geometry": {"coordinates":[-0.683645,51.709597],"type":"Point"}
}
