{
  "type": "Feature",
  "properties": {
    "date:inception_lower": "2017-01-01",
    "date:inception_upper": "2017-01-01",
    "iso:country": "GB",
    "wof:name": "TQ3 1BR",
    "wof:placetype": "postalcode"
  },
  "geometry": {"coordinates":[-3.598705,50.453598],"type":"Point"}
}
