{
  "type": "Feature",
  "properties": {
    "iso:country":"GB",
    "wof:name":"DE23 6RE",
    "wof:placetype":"postalcode"
},
  "geometry": {"coordinates":[-1.48921136641088,52.90689765612119],"type":"Point"}
}