{
  "type": "Feature",
  "properties": {
    "date:inception_lower": "1980-01-01",
    "date:inception_upper": "1980-01-01",
    "iso:country": "GB",
    "wof:name": "LL56 4JZ",
    "wof:placetype": "postalcode"
  },
  "geometry": {"coordinates":[-4.194786,53.191289],"type":"Point"}
}
