{
  "type": "Feature",
  "properties": {
    "iso:country":"GB",
    "wof:name":"LL56 4JZ",
    "wof:placetype":"postalcode"
},
  "geometry": {"coordinates":[-4.19478586686796,53.19128908171672],"type":"Point"}
}