{
  "type": "Feature",
  "properties": {
    "date:inception_lower":"1983-07-01",
    "date:inception_upper":"1983-07-31",
    "iso:country":"GB",
    "wof:name":"RH12 3NU",
    "wof:placetype":"postalcode"
},
  "geometry": {"coordinates":[-0.367486,51.068425],"type":"Point"}
}