{
  "type": "Feature",
  "properties": {
    "iso:country":"GB",
    "wof:name":"RH12 3NU",
    "wof:placetype":"postalcode"
},
  "geometry": {"coordinates":[-0.36752747589601,51.06840190901672],"type":"Point"}
}