{
  "type": "Feature",
  "properties": {
    "iso:country":"GB",
    "wof:name":"FK4 2DH",
    "wof:placetype":"postalcode"
},
  "geometry": {"coordinates":[-3.89317322571042,55.99379154036188],"type":"Point"}
}