{
  "type": "Feature",
  "properties": {
    "iso:country": "GB",
    "wof:name": "FK4 2DH",
    "wof:placetype": "postalcode"
  },
  "geometry": {"coordinates":[-3.893173,55.993792],"type":"Point"}
}
