{
  "type": "Feature",
  "properties": {
    "iso:country": "GB",
    "wof:name": "RG7 1HD",
    "wof:placetype": "postalcode"
  },
  "geometry": {"coordinates":[-0.971737,51.405425],"type":"Point"}
}
