{
  "type": "Feature",
  "properties": {
    "date:inception_lower": "1980-01-01",
    "date:inception_upper": "1980-01-01",
    "iso:country": "GB",
    "wof:name": "RG7 1HD",
    "wof:placetype": "postalcode"
  },
  "geometry": {"coordinates":[-0.971614,51.405489],"type":"Point"}
}
