{
  "type": "Feature",
  "properties": {
    "iso:country":"GB",
    "wof:name":"RG7 1HD",
    "wof:placetype":"postalcode"
},
  "geometry": {"coordinates":[-0.97173733912137,51.40542547419714],"type":"Point"}
}