{
  "type": "Feature",
  "properties": {
    "iso:country": "GB",
    "wof:name": "RG7 1HD",
    "wof:placetype": "postalcode"
  },
  "geometry": {"coordinates":[-0.971426,51.405532],"type":"Point"}
}
