{
  "type": "Feature",
  "properties": {
    "date:inception_lower":"1980-01-01",
    "date:inception_upper":"1980-01-31",
    "iso:country":"GB",
    "wof:name":"B2 4HD",
    "wof:placetype":"postalcode"
},
  "geometry": {"coordinates":[-1.899948,52.478928],"type":"Point"}
}