{
  "type": "Feature",
  "properties": {
    "iso:country": "GB",
    "wof:name": "IP13 6PZ",
    "wof:placetype": "postalcode"
  },
  "geometry": {"coordinates":[1.258088,52.116384],"type":"Point"}
}
