{
  "type": "Feature",
  "properties": {
    "iso:country":"GB",
    "wof:name":"IP13 6PZ",
    "wof:placetype":"postalcode"
},
  "geometry": {"coordinates":[1.25787648059248,52.11648194591775],"type":"Point"}
}