{
  "type": "Feature",
  "properties": {
    "iso:country":"GB",
    "wof:name":"EX17 4HA",
    "wof:placetype":"postalcode"
},
  "geometry": {"coordinates":[-3.59901861618369,50.84537143666617],"type":"Point"}
}