{
  "type": "Feature",
  "properties": {
    "iso:country":"GB",
    "wof:name":"LS9 7SX",
    "wof:placetype":"postalcode"
},
  "geometry": {"coordinates":[-1.52666268111827,53.80129496182846],"type":"Point"}
}