{
  "type": "Feature",
  "properties": {
    "iso:country":"GB",
    "wof:name":"NP44 1UD",
    "wof:placetype":"postalcode"
},
  "geometry": {"coordinates":[-3.01802185932653,51.66870707026913],"type":"Point"}
}