{
  "type": "Feature",
  "properties": {
    "date:inception_lower": "2007-07-01",
    "date:inception_upper": "2007-07-01",
    "iso:country": "GB",
    "wof:name": "CV12 0LW",
    "wof:placetype": "postalcode"
  },
  "geometry": {"coordinates":[-1.507114,52.476995],"type":"Point"}
}
