{
  "type": "Feature",
  "properties": {
    "iso:country": "GB",
    "wof:name": "G66 1BP",
    "wof:placetype": "postalcode"
  },
  "geometry": {"coordinates":[-4.173407,55.93858],"type":"Point"}
}
