{
  "type": "Feature",
  "properties": {
    "date:inception_lower": "1980-01-01",
    "date:inception_upper": "1980-01-01",
    "iso:country": "GB",
    "wof:name": "G66 1BP",
    "wof:placetype": "postalcode"
  },
  "geometry": {"coordinates":[-4.173407,55.93858],"type":"Point"}
}
