{
  "type": "Feature",
  "properties": {
    "iso:country":"GB",
    "wof:name":"G66 1BP",
    "wof:placetype":"postalcode"
},
  "geometry": {"coordinates":[-4.17340696848148,55.93857974999163],"type":"Point"}
}