{
  "type": "Feature",
  "properties": {
    "iso:country":"GB",
    "wof:name":"B24 8BD",
    "wof:placetype":"postalcode"
},
  "geometry": {"coordinates":[-1.84335295053274,52.51671764989883],"type":"Point"}
}