{
  "type": "Feature",
  "properties": {
    "iso:country": "GB",
    "wof:name": "HP18 0ZZ",
    "wof:placetype": "postalcode"
  },
  "geometry": {"coordinates":[-0.849822,51.843886],"type":"Point"}
}
