{
  "type": "Feature",
  "properties": {
    "date:inception_lower": "2005-07-01",
    "date:inception_upper": "2005-07-01",
    "iso:country": "GB",
    "wof:name": "SG19 1AW",
    "wof:placetype": "postalcode"
  },
  "geometry": {"coordinates":[-0.281799,52.124112],"type":"Point"}
}
