{
  "type": "Feature",
  "properties": {
    "iso:country":"GB",
    "wof:name":"DN4 8RG",
    "wof:placetype":"postalcode"
},
  "geometry": {"coordinates":[-1.1576139432229,53.50387454935735],"type":"Point"}
}