{
  "type": "Feature",
  "properties": {
    "iso:country":"GB",
    "wof:name":"SA31 1JB",
    "wof:placetype":"postalcode"
},
  "geometry": {"coordinates":[-4.30155443338001,51.86289746963252],"type":"Point"}
}