{
  "type": "Feature",
  "properties": {
    "date:inception_lower":"1980-01-01",
    "date:inception_upper":"1980-01-31",
    "iso:country":"GB",
    "wof:name":"SA31 1JB",
    "wof:placetype":"postalcode"
},
  "geometry": {"coordinates":[-4.301554,51.862897],"type":"Point"}
}