{
  "type": "Feature",
  "properties": {
    "iso:country": "GB",
    "wof:name": "SA31 1JB",
    "wof:placetype": "postalcode"
  },
  "geometry": {"coordinates":[-4.301554,51.862897],"type":"Point"}
}
