{
  "type": "Feature",
  "properties": {
    "iso:country":"GB",
    "wof:name":"SM2 6PH",
    "wof:placetype":"postalcode"
},
  "geometry": {"coordinates":[-0.19429102987196,51.35654839490162],"type":"Point"}
}