{
  "type": "Feature",
  "properties": {
    "iso:country":"GB",
    "wof:name":"S17 3NA",
    "wof:placetype":"postalcode"
},
  "geometry": {"coordinates":[-1.52025780519449,53.32848868916746],"type":"Point"}
}