{
  "type": "Feature",
  "properties": {
    "iso:country":"GB",
    "wof:name":"NP10 9HF",
    "wof:placetype":"postalcode"
},
  "geometry": {"coordinates":[-3.06288609542225,51.59678125193997],"type":"Point"}
}