{
  "type": "Feature",
  "properties": {
    "date:inception_lower": "1992-08-01",
    "date:inception_upper": "1992-08-01",
    "iso:country": "GB",
    "wof:name": "DE22 1GN",
    "wof:placetype": "postalcode"
  },
  "geometry": {"coordinates":[-1.494148,52.934633],"type":"Point"}
}
