{
  "type": "Feature",
  "properties": {
    "iso:country":"GB",
    "wof:name":"PL22 0NZ",
    "wof:placetype":"postalcode"
},
  "geometry": {"coordinates":[-4.60243787172969,50.3805874238674],"type":"Point"}
}