{
  "type": "Feature",
  "properties": {
    "iso:country": "GB",
    "wof:name": "PL22 0NZ",
    "wof:placetype": "postalcode"
  },
  "geometry": {"coordinates":[-4.602438,50.380587],"type":"Point"}
}
