{
  "type": "Feature",
  "properties": {
    "iso:country":"GB",
    "wof:name":"G74 3RL",
    "wof:placetype":"postalcode"
},
  "geometry": {"coordinates":[-4.15295001474014,55.77928093493313],"type":"Point"}
}