{
  "type": "Feature",
  "properties": {
    "iso:country":"GB",
    "wof:name":"CA7 1DQ",
    "wof:placetype":"postalcode"
},
  "geometry": {"coordinates":[-3.15109997486649,54.76635945385219],"type":"Point"}
}