{
  "type": "Feature",
  "properties": {
    "iso:country": "GB",
    "wof:name": "CA7 1DQ",
    "wof:placetype": "postalcode"
  },
  "geometry": {"coordinates":[-3.1511,54.766359],"type":"Point"}
}
