{
  "type": "Feature",
  "properties": {
    "iso:country":"GB",
    "wof:name":"SG10 6JL",
    "wof:placetype":"postalcode"
},
  "geometry": {"coordinates":[0.09813161702787,51.84631792741957],"type":"Point"}
}