{
  "type": "Feature",
  "properties": {
    "date:inception_lower": "1980-01-01",
    "date:inception_upper": "1980-01-01",
    "iso:country": "GB",
    "wof:name": "SG10 6JL",
    "wof:placetype": "postalcode"
  },
  "geometry": {"coordinates":[0.098132,51.846318],"type":"Point"}
}
