{
  "type": "Feature",
  "properties": {
    "date:inception_lower": "2005-03-01",
    "date:inception_upper": "2005-03-01",
    "iso:country": "GB",
    "wof:name": "W6 6SP",
    "wof:placetype": "postalcode"
  },
  "geometry": {"coordinates":[-0.234138,51.491513],"type":"Point"}
}
