{
  "type": "Feature",
  "properties": {
    "iso:country":"GB",
    "wof:name":"W6 6SP",
    "wof:placetype":"postalcode"
},
  "geometry": {"coordinates":[-0.23413756040935,51.4915131658387],"type":"Point"}
}