{
  "type": "Feature",
  "properties": {
    "iso:country":"GB",
    "wof:name":"BB10 2LG",
    "wof:placetype":"postalcode"
},
  "geometry": {"coordinates":[-2.23577524994047,53.81845263549691],"type":"Point"}
}