{
  "type": "Feature",
  "properties": {
    "date:inception_lower":"2007-08-01",
    "date:inception_upper":"2007-08-31",
    "iso:country":"GB",
    "wof:name":"YO21 1BY",
    "wof:placetype":"postalcode"
},
  "geometry": {"coordinates":[-0.615226,54.482998],"type":"Point"}
}