{
  "type": "Feature",
  "properties": {
    "iso:country":"GB",
    "wof:name":"PE22 0DS",
    "wof:placetype":"postalcode"
},
  "geometry": {"coordinates":[0.07914576195754,52.99416720454508],"type":"Point"}
}