{
  "type": "Feature",
  "properties": {
    "date:inception_lower": "1980-01-01",
    "date:inception_upper": "1980-01-01",
    "iso:country": "GB",
    "wof:name": "PE22 0DS",
    "wof:placetype": "postalcode"
  },
  "geometry": {"coordinates":[0.079146,52.994167],"type":"Point"}
}
