{
  "type": "Feature",
  "properties": {
    "iso:country":"GB",
    "wof:name":"GU14 6EA",
    "wof:placetype":"postalcode"
},
  "geometry": {"coordinates":[-0.74560353136019,51.2796082156423],"type":"Point"}
}