{
  "type": "Feature",
  "properties": {
    "date:inception_lower": "1980-01-01",
    "date:inception_upper": "1980-01-01",
    "iso:country": "GB",
    "wof:name": "GU14 6EA",
    "wof:placetype": "postalcode"
  },
  "geometry": {"coordinates":[-0.745603,51.279608],"type":"Point"}
}
