{
  "type": "Feature",
  "properties": {
    "iso:country": "GB",
    "wof:name": "SK11 9EF",
    "wof:placetype": "postalcode"
  },
  "geometry": {"coordinates":[-2.277195,53.215781],"type":"Point"}
}
