{
  "type": "Feature",
  "properties": {
    "date:inception_lower":"1980-01-01",
    "date:inception_upper":"1980-01-31",
    "iso:country":"GB",
    "wof:name":"SK11 9EF",
    "wof:placetype":"postalcode"
},
  "geometry": {"coordinates":[-2.277195,53.215781],"type":"Point"}
}