{
  "type": "Feature",
  "properties": {
    "iso:country": "GB",
    "wof:name": "OX15 4QP",
    "wof:placetype": "postalcode"
  },
  "geometry": {"coordinates":[-1.377309,52.019893],"type":"Point"}
}
