{
  "type": "Feature",
  "properties": {
    "iso:country":"GB",
    "wof:name":"OX15 4QP",
    "wof:placetype":"postalcode"
},
  "geometry": {"coordinates":[-1.37730928083815,52.01989329114505],"type":"Point"}
}