{
  "type": "Feature",
  "properties": {
    "iso:country": "GB",
    "wof:name": "SW17 0GQ",
    "wof:placetype": "postalcode"
  },
  "geometry": {"coordinates":[-0.173287,51.429962],"type":"Point"}
}
