{
  "type": "Feature",
  "properties": {
    "iso:country":"GB",
    "wof:name":"SW17 0GQ",
    "wof:placetype":"postalcode"
},
  "geometry": {"coordinates":[-0.17328655783422,51.42996235077256],"type":"Point"}
}