{
  "type": "Feature",
  "properties": {
    "date:inception_lower": "2013-05-01",
    "date:inception_upper": "2013-05-01",
    "iso:country": "GB",
    "wof:name": "SW17 0GQ",
    "wof:placetype": "postalcode"
  },
  "geometry": {"coordinates":[-0.173347,51.42999],"type":"Point"}
}
