{
  "type": "Feature",
  "properties": {
    "iso:country": "GB",
    "wof:name": "NN7 3QT",
    "wof:placetype": "postalcode"
  },
  "geometry": {"coordinates":[-1.001437,52.211124],"type":"Point"}
}
