{
  "type": "Feature",
  "properties": {
    "date:inception_lower": "1980-01-01",
    "date:inception_upper": "1980-01-01",
    "iso:country": "GB",
    "wof:name": "NN7 3QT",
    "wof:placetype": "postalcode"
  },
  "geometry": {"coordinates":[-1.001437,52.211124],"type":"Point"}
}
