{
  "type": "Feature",
  "properties": {
    "iso:country": "GB",
    "wof:name": "EX34 9QS",
    "wof:placetype": "postalcode"
  },
  "geometry": {"coordinates":[-4.102087,51.207022],"type":"Point"}
}
