{
  "type": "Feature",
  "properties": {
    "iso:country":"GB",
    "wof:name":"WV8 1UD",
    "wof:placetype":"postalcode"
},
  "geometry": {"coordinates":[-2.15902472935117,52.6196024029444],"type":"Point"}
}