{
  "type": "Feature",
  "properties": {
    "iso:country":"GB",
    "wof:name":"BS48 3HD",
    "wof:placetype":"postalcode"
},
  "geometry": {"coordinates":[-2.74088244099313,51.41223020442951],"type":"Point"}
}