{
  "type": "Feature",
  "properties": {
    "iso:country":"GB",
    "wof:name":"EC1R 0AZ",
    "wof:placetype":"postalcode"
},
  "geometry": {"coordinates":[-0.10653775903499,51.52381991066594],"type":"Point"}
}