{
  "type": "Feature",
  "properties": {
    "iso:country":"GB",
    "wof:name":"LL14 1RE",
    "wof:placetype":"postalcode"
},
  "geometry": {"coordinates":[-3.05599410935445,53.01215455317622],"type":"Point"}
}