{
  "type": "Feature",
  "properties": {
    "iso:country": "GB",
    "wof:name": "BA3 5GU",
    "wof:placetype": "postalcode"
  },
  "geometry": {"coordinates":[-2.458449,51.220347],"type":"Point"}
}
