{
  "type": "Feature",
  "properties": {
    "iso:country":"GB",
    "wof:name":"DH3 4LD",
    "wof:placetype":"postalcode"
},
  "geometry": {"coordinates":[-1.53899763389807,54.83951559654556],"type":"Point"}
}