{
  "type": "Feature",
  "properties": {
    "iso:country":"GB",
    "wof:name":"G41 3LR",
    "wof:placetype":"postalcode"
},
  "geometry": {"coordinates":[-4.28202587168929,55.8275426171645],"type":"Point"}
}