{
  "type": "Feature",
  "properties": {
    "iso:country":"GB",
    "wof:name":"CF14 4NP",
    "wof:placetype":"postalcode"
},
  "geometry": {"coordinates":[-3.19893796327373,51.51867097067313],"type":"Point"}
}