{
  "type": "Feature",
  "properties": {
    "iso:country": "GB",
    "wof:name": "CF14 4NP",
    "wof:placetype": "postalcode"
  },
  "geometry": {"coordinates":[-3.198938,51.518671],"type":"Point"}
}
