{
  "type": "Feature",
  "properties": {
    "iso:country": "GB",
    "wof:name": "BB12 6BP",
    "wof:placetype": "postalcode"
  },
  "geometry": {"coordinates":[-2.279749,53.79575],"type":"Point"}
}
