{
  "type": "Feature",
  "properties": {
    "date:inception_lower": "2019-09-01",
    "date:inception_upper": "2019-09-01",
    "iso:country": "GB",
    "wof:name": "BB12 6BP",
    "wof:placetype": "postalcode"
  },
  "geometry": {"coordinates":[-2.289256,53.7941],"type":"Point"}
}
