{
  "type": "Feature",
  "properties": {
    "date:inception_lower":"1994-05-01",
    "date:inception_upper":"1994-05-31",
    "iso:country":"GB",
    "wof:name":"CF41 7HS",
    "wof:placetype":"postalcode"
},
  "geometry": {"coordinates":[-3.492358,51.653485],"type":"Point"}
}