{
  "type": "Feature",
  "properties": {
    "iso:country": "GB",
    "wof:name": "CF41 7HS",
    "wof:placetype": "postalcode"
  },
  "geometry": {"coordinates":[-3.492358,51.653485],"type":"Point"}
}
