{
  "type": "Feature",
  "properties": {
    "iso:country":"GB",
    "wof:name":"CF41 7HS",
    "wof:placetype":"postalcode"
},
  "geometry": {"coordinates":[-3.49235804017179,51.6534845512455],"type":"Point"}
}