{
  "type": "Feature",
  "properties": {
    "iso:country":"GB",
    "wof:name":"NG32 1EY",
    "wof:placetype":"postalcode"
},
  "geometry": {"coordinates":[-0.81312549076664,52.88231760815457],"type":"Point"}
}