{
  "type": "Feature",
  "properties": {
    "date:inception_lower": "1980-01-01",
    "date:inception_upper": "1980-01-01",
    "iso:country": "GB",
    "wof:name": "NG32 1EY",
    "wof:placetype": "postalcode"
  },
  "geometry": {"coordinates":[-0.813125,52.882318],"type":"Point"}
}
