{
  "type": "Feature",
  "properties": {
    "iso:country":"GB",
    "wof:name":"GL52 5BG",
    "wof:placetype":"postalcode"
},
  "geometry": {"coordinates":[-2.0388693871941,51.91060307409555],"type":"Point"}
}