{
  "type": "Feature",
  "properties": {
    "date:inception_lower":"1985-10-01",
    "date:inception_upper":"1985-10-31",
    "iso:country":"GB",
    "wof:name":"CV22 7SL",
    "wof:placetype":"postalcode"
},
  "geometry": {"coordinates":[-1.29397,52.368887],"type":"Point"}
}