{
  "type": "Feature",
  "properties": {
    "iso:country": "GB",
    "wof:name": "CV22 7SL",
    "wof:placetype": "postalcode"
  },
  "geometry": {"coordinates":[-1.29397,52.368887],"type":"Point"}
}
