{
  "type": "Feature",
  "properties": {
    "iso:country":"GB",
    "wof:name":"CV22 7SL",
    "wof:placetype":"postalcode"
},
  "geometry": {"coordinates":[-1.2939703292546,52.36888677111395],"type":"Point"}
}