{
  "type": "Feature",
  "properties": {
    "iso:country": "GB",
    "wof:name": "CF64 3US",
    "wof:placetype": "postalcode"
  },
  "geometry": {"coordinates":[-3.183122,51.43634],"type":"Point"}
}
