{
  "type": "Feature",
  "properties": {
    "iso:country":"GB",
    "wof:name":"CF64 3US",
    "wof:placetype":"postalcode"
},
  "geometry": {"coordinates":[-3.18299880402811,51.43636788013998],"type":"Point"}
}