{
  "type": "Feature",
  "properties": {
    "iso:country":"GB",
    "wof:name":"WS12 3XE",
    "wof:placetype":"postalcode"
},
  "geometry": {"coordinates":[-1.99276666773821,52.69255272691117],"type":"Point"}
}