{
  "type": "Feature",
  "properties": {
    "iso:country":"GB",
    "wof:name":"M31 4PZ",
    "wof:placetype":"postalcode"
},
  "geometry": {"coordinates":[-2.42979105528006,53.42166482270225],"type":"Point"}
}