{
  "type": "Feature",
  "properties": {
    "iso:country": "GB",
    "wof:name": "M31 4PZ",
    "wof:placetype": "postalcode"
  },
  "geometry": {"coordinates":[-2.429791,53.421665],"type":"Point"}
}
