{
  "type": "Feature",
  "properties": {
    "iso:country":"GB",
    "wof:name":"BS13 0AL",
    "wof:placetype":"postalcode"
},
  "geometry": {"coordinates":[-2.59703581913307,51.41101937528858],"type":"Point"}
}