{
  "type": "Feature",
  "properties": {
    "date:inception_lower": "2021-11-01",
    "date:inception_upper": "2021-11-01",
    "iso:country": "GB",
    "wof:name": "M34 3FL",
    "wof:placetype": "postalcode"
  },
  "geometry": {"coordinates":[-2.107547,53.456563],"type":"Point"}
}
