{
  "type": "Feature",
  "properties": {
    "date:inception_lower": "2003-02-01",
    "date:inception_upper": "2003-02-01",
    "iso:country": "GB",
    "wof:name": "DG8 9SA",
    "wof:placetype": "postalcode"
  },
  "geometry": {"coordinates":[-4.581763,54.757827],"type":"Point"}
}
