{
  "type": "Feature",
  "properties": {
    "iso:country":"GB",
    "wof:name":"DG8 9SA",
    "wof:placetype":"postalcode"
},
  "geometry": {"coordinates":[-4.58176279043138,54.75782734955192],"type":"Point"}
}