{
  "type": "Feature",
  "properties": {
    "iso:country":"GB",
    "wof:name":"B44 9LJ",
    "wof:placetype":"postalcode"
},
  "geometry": {"coordinates":[-1.88871671139005,52.55557819036151],"type":"Point"}
}