{
  "type": "Feature",
  "properties": {
    "date:inception_lower": "2010-07-01",
    "date:inception_upper": "2010-07-01",
    "iso:country": "GB",
    "wof:name": "WR5 3UW",
    "wof:placetype": "postalcode"
  },
  "geometry": {"coordinates":[-2.214495,52.166647],"type":"Point"}
}
