{
  "type": "Feature",
  "properties": {
    "iso:country": "GB",
    "wof:name": "WR5 3UW",
    "wof:placetype": "postalcode"
  },
  "geometry": {"coordinates":[-2.214495,52.166647],"type":"Point"}
}
