{
  "type": "Feature",
  "properties": {
    "iso:country":"GB",
    "wof:name":"G81 6PJ",
    "wof:placetype":"postalcode"
},
  "geometry": {"coordinates":[-4.41305194778952,55.92694462734477],"type":"Point"}
}