{
  "type": "Feature",
  "properties": {
    "date:inception_lower": "1980-01-01",
    "date:inception_upper": "1980-01-01",
    "iso:country": "GB",
    "wof:name": "G81 6PJ",
    "wof:placetype": "postalcode"
  },
  "geometry": {"coordinates":[-4.413052,55.926945],"type":"Point"}
}
