{
  "type": "Feature",
  "properties": {
    "iso:country":"GB",
    "wof:name":"KA5 6AS",
    "wof:placetype":"postalcode"
},
  "geometry": {"coordinates":[-4.3704606908361,55.5161533167645],"type":"Point"}
}