{
  "type": "Feature",
  "properties": {
    "date:inception_lower": "2002-12-01",
    "date:inception_upper": "2002-12-01",
    "iso:country": "GB",
    "wof:name": "GU6 8TB",
    "wof:placetype": "postalcode"
  },
  "geometry": {"coordinates":[-0.532172,51.120036],"type":"Point"}
}
