{
  "type": "Feature",
  "properties": {
    "iso:country":"GB",
    "wof:name":"S75 3ER",
    "wof:placetype":"postalcode"
},
  "geometry": {"coordinates":[-1.51949627728573,53.52707089971373],"type":"Point"}
}