{
  "type": "Feature",
  "properties": {
    "iso:country": "GB",
    "wof:name": "B96 6HA",
    "wof:placetype": "postalcode"
  },
  "geometry": {"coordinates":[-1.956067,52.260258],"type":"Point"}
}
