{
  "type": "Feature",
  "properties": {
    "iso:country":"GB",
    "wof:name":"RH6 8QR",
    "wof:placetype":"postalcode"
},
  "geometry": {"coordinates":[-0.16701021218636,51.18232954757978],"type":"Point"}
}