{
  "type": "Feature",
  "properties": {
    "iso:country":"GB",
    "wof:name":"B63 2UE",
    "wof:placetype":"postalcode"
},
  "geometry": {"coordinates":[-2.08541624839604,52.46553828292423],"type":"Point"}
}