{
  "type": "Feature",
  "properties": {
    "iso:country": "GB",
    "wof:name": "B63 2UE",
    "wof:placetype": "postalcode"
  },
  "geometry": {"coordinates":[-2.085337,52.46558],"type":"Point"}
}
