{
  "type": "Feature",
  "properties": {
    "iso:country": "GB",
    "wof:name": "NE34 7HT",
    "wof:placetype": "postalcode"
  },
  "geometry": {"coordinates":[-1.395436,54.98027],"type":"Point"}
}
