{
  "type": "Feature",
  "properties": {
    "iso:country":"GB",
    "wof:name":"SO51 8HD",
    "wof:placetype":"postalcode"
},
  "geometry": {"coordinates":[-1.50390813919025,50.9892013155076],"type":"Point"}
}