{
  "type": "Feature",
  "properties": {
    "iso:country": "GB",
    "wof:name": "SO51 8HD",
    "wof:placetype": "postalcode"
  },
  "geometry": {"coordinates":[-1.503908,50.989201],"type":"Point"}
}
