{
  "type": "Feature",
  "properties": {
    "iso:country":"GB",
    "wof:name":"G74 4JF",
    "wof:placetype":"postalcode"
},
  "geometry": {"coordinates":[-4.19966557449175,55.77006824409642],"type":"Point"}
}