{
  "type": "Feature",
  "properties": {
    "iso:country":"GB",
    "wof:name":"PR4 5GN",
    "wof:placetype":"postalcode"
},
  "geometry": {"coordinates":[-2.78557751135095,53.71244023506893],"type":"Point"}
}