{
  "type": "Feature",
  "properties": {
    "iso:country":"GB",
    "wof:name":"EX6 6PR",
    "wof:placetype":"postalcode"
},
  "geometry": {"coordinates":[-3.77169959656726,50.69956600492321],"type":"Point"}
}