{
  "type": "Feature",
  "properties": {
    "iso:country":"GB",
    "wof:name":"M19 2LD",
    "wof:placetype":"postalcode"
},
  "geometry": {"coordinates":[-2.20114790368821,53.43823284405515],"type":"Point"}
}