{
  "type": "Feature",
  "properties": {
    "iso:country":"GB",
    "wof:name":"LS23 6RZ",
    "wof:placetype":"postalcode"
},
  "geometry": {"coordinates":[-1.3508258526495,53.87994496549896],"type":"Point"}
}