{
  "type": "Feature",
  "properties": {
    "iso:country": "GB",
    "wof:name": "NE25 0JU",
    "wof:placetype": "postalcode"
  },
  "geometry": {"coordinates":[-1.521993,55.064737],"type":"Point"}
}
