{
  "type": "Feature",
  "properties": {
    "date:inception_lower":"1980-01-01",
    "date:inception_upper":"1980-01-31",
    "iso:country":"GB",
    "wof:name":"NE25 0JU",
    "wof:placetype":"postalcode"
},
  "geometry": {"coordinates":[-1.521993,55.064737],"type":"Point"}
}