{
  "type": "Feature",
  "properties": {
    "iso:country":"GB",
    "wof:name":"B21 9QX",
    "wof:placetype":"postalcode"
},
  "geometry": {"coordinates":[-1.94085927269287,52.50889519857819],"type":"Point"}
}