{
  "type": "Feature",
  "properties": {
    "date:inception_lower": "1995-07-01",
    "date:inception_upper": "1995-07-01",
    "iso:country": "GB",
    "wof:name": "CF83 1QU",
    "wof:placetype": "postalcode"
  },
  "geometry": {"coordinates":[-3.2068,51.578899],"type":"Point"}
}
