{
  "type": "Feature",
  "properties": {
    "iso:country":"GB",
    "wof:name":"CF83 1QU",
    "wof:placetype":"postalcode"
},
  "geometry": {"coordinates":[-3.20680046206438,51.57889859028189],"type":"Point"}
}