{
  "type": "Feature",
  "properties": {
    "iso:country":"GB",
    "wof:name":"SE9 4NA",
    "wof:placetype":"postalcode"
},
  "geometry": {"coordinates":[0.05322470399709,51.4281375515714],"type":"Point"}
}