{
  "type": "Feature",
  "properties": {
    "date:inception_lower": "1980-01-01",
    "date:inception_upper": "1980-01-01",
    "iso:country": "GB",
    "wof:name": "UB3 4BX",
    "wof:placetype": "postalcode"
  },
  "geometry": {"coordinates":[-0.420187,51.503538],"type":"Point"}
}
