{
  "type": "Feature",
  "properties": {
    "iso:country": "GB",
    "wof:name": "UB3 4BX",
    "wof:placetype": "postalcode"
  },
  "geometry": {"coordinates":[-0.420187,51.503538],"type":"Point"}
}
