{
  "type": "Feature",
  "properties": {
    "iso:country":"GB",
    "wof:name":"UB3 4BX",
    "wof:placetype":"postalcode"
},
  "geometry": {"coordinates":[-0.42026538013699,51.50351991377563],"type":"Point"}
}