{
  "type": "Feature",
  "properties": {
    "iso:country": "GB",
    "wof:name": "LS25 2JP",
    "wof:placetype": "postalcode"
  },
  "geometry": {"coordinates":[-1.36781,53.790855],"type":"Point"}
}
