{
  "type": "Feature",
  "properties": {
    "iso:country":"GB",
    "wof:name":"TA12 6NP",
    "wof:placetype":"postalcode"
},
  "geometry": {"coordinates":[-2.75311455052742,50.9775999288099],"type":"Point"}
}