{
  "type": "Feature",
  "properties": {
    "iso:country": "GB",
    "wof:name": "HR8 1RY",
    "wof:placetype": "postalcode"
  },
  "geometry": {"coordinates":[-2.364976,51.997892],"type":"Point"}
}
