{
  "type": "Feature",
  "properties": {
    "iso:country": "GB",
    "wof:name": "LS10 4GU",
    "wof:placetype": "postalcode"
  },
  "geometry": {"coordinates":[-1.522657,53.744861],"type":"Point"}
}
