{
  "type": "Feature",
  "properties": {
    "iso:country":"GB",
    "wof:name":"NR33 8NR",
    "wof:placetype":"postalcode"
},
  "geometry": {"coordinates":[1.69666488939127,52.45987189672122],"type":"Point"}
}