{
  "type": "Feature",
  "properties": {
    "iso:country": "GB",
    "wof:name": "M3 3AZ",
    "wof:placetype": "postalcode"
  },
  "geometry": {"coordinates":[-2.253285,53.480414],"type":"Point"}
}
