{
  "type": "Feature",
  "properties": {
    "date:inception_lower": "1980-01-01",
    "date:inception_upper": "1980-01-01",
    "iso:country": "GB",
    "wof:name": "HA5 4DY",
    "wof:placetype": "postalcode"
  },
  "geometry": {"coordinates":[-0.361084,51.610426],"type":"Point"}
}
