{
  "type": "Feature",
  "properties": {
    "date:inception_lower": "2021-09-01",
    "date:inception_upper": "2021-09-01",
    "iso:country": "GB",
    "wof:name": "OX7 4BY",
    "wof:placetype": "postalcode"
  },
  "geometry": {"coordinates":[-1.437201,51.93159],"type":"Point"}
}
