{
  "type": "Feature",
  "properties": {
    "iso:country":"GB",
    "wof:name":"NE29 8RT",
    "wof:placetype":"postalcode"
},
  "geometry": {"coordinates":[-1.48287168673998,55.01560255352117],"type":"Point"}
}