{
  "type": "Feature",
  "properties": {
    "iso:country":"GB",
    "wof:name":"DT1 1TU",
    "wof:placetype":"postalcode"
},
  "geometry": {"coordinates":[-2.43783983110233,50.71257927924388],"type":"Point"}
}