{
  "type": "Feature",
  "properties": {
    "date:inception_lower":"1980-01-01",
    "date:inception_upper":"1980-01-31",
    "iso:country":"GB",
    "wof:name":"BD19 4NX",
    "wof:placetype":"postalcode"
},
  "geometry": {"coordinates":[-1.692097,53.726621],"type":"Point"}
}