{
  "type": "Feature",
  "properties": {
    "iso:country":"GB",
    "wof:name":"BD19 4NX",
    "wof:placetype":"postalcode"
},
  "geometry": {"coordinates":[-1.69209722360327,53.72662143750838],"type":"Point"}
}