{
  "type": "Feature",
  "properties": {
    "iso:country":"GB",
    "wof:name":"SP11 9NR",
    "wof:placetype":"postalcode"
},
  "geometry": {"coordinates":[-1.60995660080003,51.25530156860088],"type":"Point"}
}