{
  "type": "Feature",
  "properties": {
    "iso:country":"GB",
    "wof:name":"IP5 2YF",
    "wof:placetype":"postalcode"
},
  "geometry": {"coordinates":[1.24325854727022,52.06365832133429],"type":"Point"}
}