{
  "type": "Feature",
  "properties": {
    "iso:country":"GB",
    "wof:name":"NE21 6SL",
    "wof:placetype":"postalcode"
},
  "geometry": {"coordinates":[-1.71563611462256,54.94227712468018],"type":"Point"}
}