{
  "type": "Feature",
  "properties": {
    "iso:country":"GB",
    "wof:name":"LN9 5QJ",
    "wof:placetype":"postalcode"
},
  "geometry": {"coordinates":[-0.10903051080607,53.28432524319678],"type":"Point"}
}