{
  "type": "Feature",
  "properties": {
    "iso:country": "GB",
    "wof:name": "LN9 5QJ",
    "wof:placetype": "postalcode"
  },
  "geometry": {"coordinates":[-0.10903,53.284325],"type":"Point"}
}
