{
  "type": "Feature",
  "properties": {
    "iso:country": "GB",
    "wof:name": "SA62 4HW",
    "wof:placetype": "postalcode"
  },
  "geometry": {"coordinates":[-4.915583,51.750939],"type":"Point"}
}
