{
  "type": "Feature",
  "properties": {
    "iso:country":"GB",
    "wof:name":"SA62 4HW",
    "wof:placetype":"postalcode"
},
  "geometry": {"coordinates":[-4.91554922431659,51.75090864649515],"type":"Point"}
}