{
  "type": "Feature",
  "properties": {
    "iso:country":"GB",
    "wof:name":"NE25 8RY",
    "wof:placetype":"postalcode"
},
  "geometry": {"coordinates":[-1.45240233981799,55.0378181467936],"type":"Point"}
}