{
  "type": "Feature",
  "properties": {
    "date:inception_lower": "1998-12-01",
    "date:inception_upper": "1998-12-01",
    "iso:country": "GB",
    "wof:name": "NE25 8RY",
    "wof:placetype": "postalcode"
  },
  "geometry": {"coordinates":[-1.452402,55.037818],"type":"Point"}
}
