{
  "type": "Feature",
  "properties": {
    "iso:country":"GB",
    "wof:name":"NG24 4UD",
    "wof:placetype":"postalcode"
},
  "geometry": {"coordinates":[-0.81923703527507,53.07287969756666],"type":"Point"}
}