{
  "type": "Feature",
  "properties": {
    "iso:country":"GB",
    "wof:name":"BN17 7ES",
    "wof:placetype":"postalcode"
},
  "geometry": {"coordinates":[-0.55458249385251,50.81791197676305],"type":"Point"}
}