{
  "type": "Feature",
  "properties": {
    "iso:country": "GB",
    "wof:name": "UB6 0LT",
    "wof:placetype": "postalcode"
  },
  "geometry": {"coordinates":[-0.329137,51.554556],"type":"Point"}
}
