{
  "type": "Feature",
  "properties": {
    "date:inception_lower": "1980-01-01",
    "date:inception_upper": "1980-01-01",
    "iso:country": "GB",
    "wof:name": "UB6 0LT",
    "wof:placetype": "postalcode"
  },
  "geometry": {"coordinates":[-0.329137,51.554556],"type":"Point"}
}
