{
  "type": "Feature",
  "properties": {
    "date:inception_lower":"1988-03-01",
    "date:inception_upper":"1988-03-31",
    "iso:country":"GB",
    "wof:name":"N10 2JL",
    "wof:placetype":"postalcode"
},
  "geometry": {"coordinates":[-0.145755,51.602726],"type":"Point"}
}