{
  "type": "Feature",
  "properties": {
    "iso:country":"GB",
    "wof:name":"N10 2JL",
    "wof:placetype":"postalcode"
},
  "geometry": {"coordinates":[-0.14575517815996,51.60272552584123],"type":"Point"}
}