{
  "type": "Feature",
  "properties": {
    "date:inception_lower": "1988-03-01",
    "date:inception_upper": "1988-03-01",
    "iso:country": "GB",
    "wof:name": "N10 2JL",
    "wof:placetype": "postalcode"
  },
  "geometry": {"coordinates":[-0.145715,51.602737],"type":"Point"}
}
