{
  "type": "Feature",
  "properties": {
    "iso:country": "GB",
    "wof:name": "BN12 4EA",
    "wof:placetype": "postalcode"
  },
  "geometry": {"coordinates":[-0.410195,50.81616],"type":"Point"}
}
