{
  "type": "Feature",
  "properties": {
    "iso:country":"GB",
    "wof:name":"TS13 5ND",
    "wof:placetype":"postalcode"
},
  "geometry": {"coordinates":[-0.74588975630395,54.51425336879819],"type":"Point"}
}