{
  "type": "Feature",
  "properties": {
    "date:inception_lower": "1980-01-01",
    "date:inception_upper": "1980-01-01",
    "iso:country": "GB",
    "wof:name": "TS13 5ND",
    "wof:placetype": "postalcode"
  },
  "geometry": {"coordinates":[-0.745709,54.514158],"type":"Point"}
}
