{
  "type": "Feature",
  "properties": {
    "iso:country":"GB",
    "wof:name":"HA0 1DW",
    "wof:placetype":"postalcode"
},
  "geometry": {"coordinates":[-0.30918291942396,51.53483809558093],"type":"Point"}
}