{
  "type": "Feature",
  "properties": {
    "iso:country": "GB",
    "wof:name": "NG18 3RU",
    "wof:placetype": "postalcode"
  },
  "geometry": {"coordinates":[-1.155635,53.133569],"type":"Point"}
}
