{
  "type": "Feature",
  "properties": {
    "iso:country":"GB",
    "wof:name":"SP11 0AA",
    "wof:placetype":"postalcode"
},
  "geometry": {"coordinates":[-1.4528521780468,51.27654140584418],"type":"Point"}
}