{
  "type": "Feature",
  "properties": {
    "iso:country": "GB",
    "wof:name": "OL8 3DG",
    "wof:placetype": "postalcode"
  },
  "geometry": {"coordinates":[-2.11629,53.525372],"type":"Point"}
}
