{
  "type": "Feature",
  "properties": {
    "iso:country":"GB",
    "wof:name":"OL8 3DG",
    "wof:placetype":"postalcode"
},
  "geometry": {"coordinates":[-2.11629037834743,53.52537183218567],"type":"Point"}
}