{
  "type": "Feature",
  "properties": {
    "iso:country": "GB",
    "wof:name": "PR6 9HN",
    "wof:placetype": "postalcode"
  },
  "geometry": {"coordinates":[-2.587906,53.612995],"type":"Point"}
}
