{
  "type": "Feature",
  "properties": {
    "date:inception_lower": "1980-01-01",
    "date:inception_upper": "1980-01-01",
    "iso:country": "GB",
    "wof:name": "PR6 9HN",
    "wof:placetype": "postalcode"
  },
  "geometry": {"coordinates":[-2.588146,53.613],"type":"Point"}
}
