{
  "type": "Feature",
  "properties": {
    "iso:country":"GB",
    "wof:name":"PR6 9HN",
    "wof:placetype":"postalcode"
},
  "geometry": {"coordinates":[-2.58790633887878,53.61299458560381],"type":"Point"}
}