{
  "type": "Feature",
  "properties": {
    "iso:country":"GB",
    "wof:name":"LE4 3NW",
    "wof:placetype":"postalcode"
},
  "geometry": {"coordinates":[-1.13437594424098,52.68613126785974],"type":"Point"}
}