{
  "type": "Feature",
  "properties": {
    "iso:country": "GB",
    "wof:name": "LE4 3NW",
    "wof:placetype": "postalcode"
  },
  "geometry": {"coordinates":[-1.134376,52.686131],"type":"Point"}
}
