{
  "type": "Feature",
  "properties": {
    "iso:country": "GB",
    "wof:name": "HA4 8ST",
    "wof:placetype": "postalcode"
  },
  "geometry": {"coordinates":[-0.403836,51.580693],"type":"Point"}
}
