{
  "type": "Feature",
  "properties": {
    "date:inception_lower": "2012-10-01",
    "date:inception_upper": "2012-10-01",
    "iso:country": "GB",
    "wof:name": "PO15 5UA",
    "wof:placetype": "postalcode"
  },
  "geometry": {"coordinates":[-1.253694,50.869809],"type":"Point"}
}
