{
  "type": "Feature",
  "properties": {
    "iso:country":"GB",
    "wof:name":"SA4 9AE",
    "wof:placetype":"postalcode"
},
  "geometry": {"coordinates":[-4.00491906698375,51.6717748109287],"type":"Point"}
}