{
  "type": "Feature",
  "properties": {
    "date:inception_lower": "2002-06-01",
    "date:inception_upper": "2002-06-01",
    "iso:country": "GB",
    "wof:name": "SA4 9AE",
    "wof:placetype": "postalcode"
  },
  "geometry": {"coordinates":[-4.004953,51.671771],"type":"Point"}
}
