{
  "type": "Feature",
  "properties": {
    "iso:country": "GB",
    "wof:name": "SA4 9AE",
    "wof:placetype": "postalcode"
  },
  "geometry": {"coordinates":[-4.004953,51.671771],"type":"Point"}
}
