{
  "type": "Feature",
  "properties": {
    "date:inception_lower": "1980-01-01",
    "date:inception_upper": "1980-01-01",
    "iso:country": "GB",
    "wof:name": "W4 5NQ",
    "wof:placetype": "postalcode"
  },
  "geometry": {"coordinates":[-0.269419,51.496751],"type":"Point"}
}
