{
  "type": "Feature",
  "properties": {
    "iso:country":"GB",
    "wof:name":"NR20 4AB",
    "wof:placetype":"postalcode"
},
  "geometry": {"coordinates":[0.92011074929904,52.72939907413126],"type":"Point"}
}