{
  "type": "Feature",
  "properties": {
    "iso:country": "GB",
    "wof:name": "M41 7SW",
    "wof:placetype": "postalcode"
  },
  "geometry": {"coordinates":[-2.346711,53.47121],"type":"Point"}
}
