{
  "type": "Feature",
  "properties": {
    "iso:country":"GB",
    "wof:name":"CF35 5NN",
    "wof:placetype":"postalcode"
},
  "geometry": {"coordinates":[-3.50187836251395,51.52288879667154],"type":"Point"}
}