{
  "type": "Feature",
  "properties": {
    "iso:country": "GB",
    "wof:name": "LA1 2TL",
    "wof:placetype": "postalcode"
  },
  "geometry": {"coordinates":[-2.794319,54.066162],"type":"Point"}
}
