{
  "type": "Feature",
  "properties": {
    "iso:country":"GB",
    "wof:name":"CR2 7HU",
    "wof:placetype":"postalcode"
},
  "geometry": {"coordinates":[-0.08164238705126,51.36139441625311],"type":"Point"}
}