{
  "type": "Feature",
  "properties": {
    "iso:country":"GB",
    "wof:name":"IV51 9UA",
    "wof:placetype":"postalcode"
},
  "geometry": {"coordinates":[-6.37776773497624,57.62958886010903],"type":"Point"}
}