{
  "type": "Feature",
  "properties": {
    "iso:country": "GB",
    "wof:name": "IV51 9UA",
    "wof:placetype": "postalcode"
  },
  "geometry": {"coordinates":[-6.377768,57.629589],"type":"Point"}
}
