{
  "type": "Feature",
  "properties": {
    "date:inception_lower":"1980-01-01",
    "date:inception_upper":"1980-01-31",
    "iso:country":"GB",
    "wof:name":"DY12 1RR",
    "wof:placetype":"postalcode"
},
  "geometry": {"coordinates":[-2.315148,52.42544],"type":"Point"}
}