{
  "type": "Feature",
  "properties": {
    "date:inception_lower": "1980-01-01",
    "date:inception_upper": "1980-01-01",
    "iso:country": "GB",
    "wof:name": "HP4 2QJ",
    "wof:placetype": "postalcode"
  },
  "geometry": {"coordinates":[-0.525862,51.767927],"type":"Point"}
}
