{
  "type": "Feature",
  "properties": {
    "iso:country":"GB",
    "wof:name":"WC2H 0HR",
    "wof:placetype":"postalcode"
},
  "geometry": {"coordinates":[-0.12818704415579,51.51052573850625],"type":"Point"}
}