{
  "type": "Feature",
  "properties": {
    "iso:country":"GB",
    "wof:name":"BR1 4HS",
    "wof:placetype":"postalcode"
},
  "geometry": {"coordinates":[0.00919937034827,51.41882863010217],"type":"Point"}
}