{
  "type": "Feature",
  "properties": {
    "iso:country": "GB",
    "wof:name": "BR1 4HS",
    "wof:placetype": "postalcode"
  },
  "geometry": {"coordinates":[0.009199,51.418829],"type":"Point"}
}
