{
  "type": "Feature",
  "properties": {
    "date:inception_lower":"2004-09-01",
    "date:inception_upper":"2004-09-30",
    "iso:country":"GB",
    "wof:name":"PO7 7FY",
    "wof:placetype":"postalcode"
},
  "geometry": {"coordinates":[-1.03284,50.878539],"type":"Point"}
}