{
  "type": "Feature",
  "properties": {
    "iso:country":"GB",
    "wof:name":"IP29 5QF",
    "wof:placetype":"postalcode"
},
  "geometry": {"coordinates":[0.61102780543298,52.1978596703127],"type":"Point"}
}