{
  "type": "Feature",
  "properties": {
    "iso:country": "GB",
    "wof:name": "SK7 1PE",
    "wof:placetype": "postalcode"
  },
  "geometry": {"coordinates":[-2.164807,53.348187],"type":"Point"}
}
