{
  "type": "Feature",
  "properties": {
    "iso:country":"GB",
    "wof:name":"SN11 8JY",
    "wof:placetype":"postalcode"
},
  "geometry": {"coordinates":[-1.98782617504605,51.42660347912925],"type":"Point"}
}