{
  "type": "Feature",
  "properties": {
    "iso:country":"GB",
    "wof:name":"PL25 4ER",
    "wof:placetype":"postalcode"
},
  "geometry": {"coordinates":[-4.78079473765101,50.35218792886503],"type":"Point"}
}