{
  "type": "Feature",
  "properties": {
    "iso:country":"GB",
    "wof:name":"NR23 1NY",
    "wof:placetype":"postalcode"
},
  "geometry": {"coordinates":[0.89045952861443,52.91680160826122],"type":"Point"}
}