{
  "type": "Feature",
  "properties": {
    "iso:country":"GB",
    "wof:name":"NE48 1AG",
    "wof:placetype":"postalcode"
},
  "geometry": {"coordinates":[-2.41171489009848,55.16831718384376],"type":"Point"}
}