{
  "type": "Feature",
  "properties": {
    "iso:country":"GB",
    "wof:name":"SN15 3RX",
    "wof:placetype":"postalcode"
},
  "geometry": {"coordinates":[-2.07582415566903,51.43670389972332],"type":"Point"}
}