{
  "type": "Feature",
  "properties": {
    "iso:country":"GB",
    "wof:name":"PL22 0NS",
    "wof:placetype":"postalcode"
},
  "geometry": {"coordinates":[-4.62732048755918,50.37164433066217],"type":"Point"}
}