{
  "type": "Feature",
  "properties": {
    "iso:country":"GB",
    "wof:name":"LE2 5DF",
    "wof:placetype":"postalcode"
},
  "geometry": {"coordinates":[-1.07614235848663,52.59727502728482],"type":"Point"}
}