{
  "type": "Feature",
  "properties": {
    "date:inception_lower":"1980-01-01",
    "date:inception_upper":"1980-01-31",
    "iso:country":"GB",
    "wof:name":"LE2 5DF",
    "wof:placetype":"postalcode"
},
  "geometry": {"coordinates":[-1.076142,52.597275],"type":"Point"}
}