{
  "type": "Feature",
  "properties": {
    "iso:country": "GB",
    "wof:name": "LE3 0BJ",
    "wof:placetype": "postalcode"
  },
  "geometry": {"coordinates":[-1.146795,52.628443],"type":"Point"}
}
