{
  "type": "Feature",
  "properties": {
    "iso:country":"GB",
    "wof:name":"NG12 3AB",
    "wof:placetype":"postalcode"
},
  "geometry": {"coordinates":[-0.98301160362982,52.92622593503521],"type":"Point"}
}