{
  "type": "Feature",
  "properties": {
    "date:inception_lower": "1980-01-01",
    "date:inception_upper": "1980-01-01",
    "iso:country": "GB",
    "wof:name": "NG12 3AB",
    "wof:placetype": "postalcode"
  },
  "geometry": {"coordinates":[-0.983012,52.926226],"type":"Point"}
}
