{
  "type": "Feature",
  "properties": {
    "date:inception_lower": "1985-10-01",
    "date:inception_upper": "1985-10-01",
    "iso:country": "GB",
    "wof:name": "PL12 6DR",
    "wof:placetype": "postalcode"
  },
  "geometry": {"coordinates":[-4.222395,50.411185],"type":"Point"}
}
