{
  "type": "Feature",
  "properties": {
    "iso:country":"GB",
    "wof:name":"SL6 1EH",
    "wof:placetype":"postalcode"
},
  "geometry": {"coordinates":[-0.72254437822434,51.51972706244727],"type":"Point"}
}