{
  "type": "Feature",
  "properties": {
    "iso:country": "GB",
    "wof:name": "SL6 1EH",
    "wof:placetype": "postalcode"
  },
  "geometry": {"coordinates":[-0.722544,51.519727],"type":"Point"}
}
