{
  "type": "Feature",
  "properties": {
    "iso:country": "GB",
    "wof:name": "EX35 6JJ",
    "wof:placetype": "postalcode"
  },
  "geometry": {"coordinates":[-3.866307,51.227829],"type":"Point"}
}
