{
  "type": "Feature",
  "properties": {
    "date:inception_lower":"1980-01-01",
    "date:inception_upper":"1980-01-31",
    "iso:country":"GB",
    "wof:name":"CV9 1EA",
    "wof:placetype":"postalcode"
},
  "geometry": {"coordinates":[-1.541933,52.574954],"type":"Point"}
}