{
  "type": "Feature",
  "properties": {
    "iso:country":"GB",
    "wof:name":"CV9 1EA",
    "wof:placetype":"postalcode"
},
  "geometry": {"coordinates":[-1.54193271676559,52.57495447221887],"type":"Point"}
}