{
  "type": "Feature",
  "properties": {
    "date:inception_lower":"1980-01-01",
    "date:inception_upper":"1980-01-31",
    "iso:country":"GB",
    "wof:name":"B63 4QW",
    "wof:placetype":"postalcode"
},
  "geometry": {"coordinates":[-2.057089,52.442025],"type":"Point"}
}