{
  "type": "Feature",
  "properties": {
    "date:inception_lower": "2019-12-01",
    "date:inception_upper": "2019-12-01",
    "iso:country": "GB",
    "wof:name": "LE15 7WE",
    "wof:placetype": "postalcode"
  },
  "geometry": {"coordinates":[-0.737662,52.676486],"type":"Point"}
}
