{
  "type": "Feature",
  "properties": {
    "iso:country": "GB",
    "wof:name": "LE15 7WE",
    "wof:placetype": "postalcode"
  },
  "geometry": {"coordinates":[-0.738006,52.677371],"type":"Point"}
}
