{
  "type": "Feature",
  "properties": {
    "date:inception_lower":"1994-05-01",
    "date:inception_upper":"1994-05-31",
    "iso:country":"GB",
    "wof:name":"M34 7HU",
    "wof:placetype":"postalcode"
},
  "geometry": {"coordinates":[-2.106552,53.443658],"type":"Point"}
}