{
  "type": "Feature",
  "properties": {
    "iso:country": "GB",
    "wof:name": "M34 7HU",
    "wof:placetype": "postalcode"
  },
  "geometry": {"coordinates":[-2.106552,53.443658],"type":"Point"}
}
