{
  "type": "Feature",
  "properties": {
    "date:inception_lower":"2014-02-01",
    "date:inception_upper":"2014-02-28",
    "iso:country":"GB",
    "wof:name":"NN17 5FA",
    "wof:placetype":"postalcode"
},
  "geometry": {"coordinates":[-0.636673,52.503963],"type":"Point"}
}