{
  "type": "Feature",
  "properties": {
    "iso:country": "GB",
    "wof:name": "WR6 6LY",
    "wof:placetype": "postalcode"
  },
  "geometry": {"coordinates":[-2.290855,52.264757],"type":"Point"}
}
