{
  "type": "Feature",
  "properties": {
    "date:inception_lower": "1980-01-01",
    "date:inception_upper": "1980-01-01",
    "iso:country": "GB",
    "wof:name": "WR6 6LY",
    "wof:placetype": "postalcode"
  },
  "geometry": {"coordinates":[-2.290855,52.264757],"type":"Point"}
}
