{
  "type": "Feature",
  "properties": {
    "iso:country":"GB",
    "wof:name":"AB56 1LL",
    "wof:placetype":"postalcode"
},
  "geometry": {"coordinates":[-2.95976826427871,57.67220430741045],"type":"Point"}
}