{
  "type": "Feature",
  "properties": {
    "iso:country":"GB",
    "wof:name":"NG6 0JJ",
    "wof:placetype":"postalcode"
},
  "geometry": {"coordinates":[-1.18547407422904,52.97899894082857],"type":"Point"}
}