{
  "type": "Feature",
  "properties": {
    "iso:country":"GB",
    "wof:name":"CT4 6ND",
    "wof:placetype":"postalcode"
},
  "geometry": {"coordinates":[1.10752278925113,51.17361753068595],"type":"Point"}
}