{
  "type": "Feature",
  "properties": {
    "iso:country": "GB",
    "wof:name": "CT4 6ND",
    "wof:placetype": "postalcode"
  },
  "geometry": {"coordinates":[1.107553,51.173621],"type":"Point"}
}
