{
  "type": "Feature",
  "properties": {
    "iso:country": "GB",
    "wof:name": "CT4 6ND",
    "wof:placetype": "postalcode"
  },
  "geometry": {"coordinates":[1.10757,51.173665],"type":"Point"}
}
