{
  "type": "Feature",
  "properties": {
    "iso:country":"GB",
    "wof:name":"W4 2AZ",
    "wof:placetype":"postalcode"
},
  "geometry": {"coordinates":[-0.24556618832537,51.48874417599316],"type":"Point"}
}