{
  "type": "Feature",
  "properties": {
    "iso:country":"GB",
    "wof:name":"SK8 1QJ",
    "wof:placetype":"postalcode"
},
  "geometry": {"coordinates":[-2.22207405602789,53.39536528493842],"type":"Point"}
}