{
  "type": "Feature",
  "properties": {
    "iso:country":"GB",
    "wof:name":"OL13 8PW",
    "wof:placetype":"postalcode"
},
  "geometry": {"coordinates":[-2.20125415438919,53.71473093628434],"type":"Point"}
}