{
  "type": "Feature",
  "properties": {
    "date:inception_lower": "1980-01-01",
    "date:inception_upper": "1980-01-01",
    "iso:country": "GB",
    "wof:name": "LS22 5AQ",
    "wof:placetype": "postalcode"
  },
  "geometry": {"coordinates":[-1.419471,53.904492],"type":"Point"}
}
