{
  "type": "Feature",
  "properties": {
    "iso:country":"GB",
    "wof:name":"LS22 5AQ",
    "wof:placetype":"postalcode"
},
  "geometry": {"coordinates":[-1.41947104970469,53.90449198697583],"type":"Point"}
}