{
  "type": "Feature",
  "properties": {
    "iso:country":"GB",
    "wof:name":"SA15 4PF",
    "wof:placetype":"postalcode"
},
  "geometry": {"coordinates":[-4.1520385076211,51.69747899884059],"type":"Point"}
}