{
  "type": "Feature",
  "properties": {
    "date:inception_lower":"1980-01-01",
    "date:inception_upper":"1980-01-31",
    "iso:country":"GB",
    "wof:name":"SA15 4PF",
    "wof:placetype":"postalcode"
},
  "geometry": {"coordinates":[-4.152017,51.697486],"type":"Point"}
}