{
  "type": "Feature",
  "properties": {
    "iso:country":"GB",
    "wof:name":"LL20 7TN",
    "wof:placetype":"postalcode"
},
  "geometry": {"coordinates":[-3.08819748334852,52.97632819729562],"type":"Point"}
}