{
  "type": "Feature",
  "properties": {
    "iso:country": "GB",
    "wof:name": "LL20 7TN",
    "wof:placetype": "postalcode"
  },
  "geometry": {"coordinates":[-3.088197,52.976328],"type":"Point"}
}
