{
  "type": "Feature",
  "properties": {
    "date:inception_lower":"1980-01-01",
    "date:inception_upper":"1980-01-31",
    "iso:country":"GB",
    "wof:name":"LL20 7TN",
    "wof:placetype":"postalcode"
},
  "geometry": {"coordinates":[-3.088197,52.976328],"type":"Point"}
}