{
  "type": "Feature",
  "properties": {
    "iso:country":"GB",
    "wof:name":"FK9 4QR",
    "wof:placetype":"postalcode"
},
  "geometry": {"coordinates":[-3.9392158702723,56.15099569051584],"type":"Point"}
}