{
  "type": "Feature",
  "properties": {
    "iso:country": "GB",
    "wof:name": "NR18 9JJ",
    "wof:placetype": "postalcode"
  },
  "geometry": {"coordinates":[1.088215,52.546111],"type":"Point"}
}
