{
  "type": "Feature",
  "properties": {
    "iso:country":"GB",
    "wof:name":"BS10 7LR",
    "wof:placetype":"postalcode"
},
  "geometry": {"coordinates":[-2.62484426296764,51.51432319256661],"type":"Point"}
}