{
  "type": "Feature",
  "properties": {
    "iso:country":"GB",
    "wof:name":"MK16 0AX",
    "wof:placetype":"postalcode"
},
  "geometry": {"coordinates":[-0.73563790828463,52.08156871099967],"type":"Point"}
}