{
  "type": "Feature",
  "properties": {
    "iso:country":"GB",
    "wof:name":"BS22 7SJ",
    "wof:placetype":"postalcode"
},
  "geometry": {"coordinates":[-2.90282307032354,51.36798725071736],"type":"Point"}
}