{
  "type": "Feature",
  "properties": {
    "date:inception_lower": "2004-07-01",
    "date:inception_upper": "2004-07-01",
    "iso:country": "GB",
    "wof:name": "BS22 7SJ",
    "wof:placetype": "postalcode"
  },
  "geometry": {"coordinates":[-2.902908,51.368416],"type":"Point"}
}
