{
  "type": "Feature",
  "properties": {
    "iso:country":"GB",
    "wof:name":"LL61 6RZ",
    "wof:placetype":"postalcode"
},
  "geometry": {"coordinates":[-4.27131651983779,53.17750944246691],"type":"Point"}
}