{
  "type": "Feature",
  "properties": {
    "iso:country":"GB",
    "wof:name":"KY2 6GB",
    "wof:placetype":"postalcode"
},
  "geometry": {"coordinates":[-3.2067195128629,56.13474027036551],"type":"Point"}
}