{
  "type": "Feature",
  "properties": {
    "iso:country": "GB",
    "wof:name": "KY2 6GB",
    "wof:placetype": "postalcode"
  },
  "geometry": {"coordinates":[-3.206719,56.13474],"type":"Point"}
}
