{
  "type": "Feature",
  "properties": {
    "iso:country": "GB",
    "wof:name": "BL6 6BQ",
    "wof:placetype": "postalcode"
  },
  "geometry": {"coordinates":[-2.536196,53.598658],"type":"Point"}
}
