{
  "type": "Feature",
  "properties": {
    "iso:country":"GB",
    "wof:name":"BL6 6BQ",
    "wof:placetype":"postalcode"
},
  "geometry": {"coordinates":[-2.53619571659334,53.59865841262658],"type":"Point"}
}