{
  "type": "Feature",
  "properties": {
    "iso:country":"GB",
    "wof:name":"SA14 7EY",
    "wof:placetype":"postalcode"
},
  "geometry": {"coordinates":[-4.12380158503187,51.81748553247144],"type":"Point"}
}