{
  "type": "Feature",
  "properties": {
    "iso:country":"GB",
    "wof:name":"LE4 9AF",
    "wof:placetype":"postalcode"
},
  "geometry": {"coordinates":[-1.0899309554018,52.66854675791775],"type":"Point"}
}