{
  "type": "Feature",
  "properties": {
    "iso:country": "GB",
    "wof:name": "LE4 9AF",
    "wof:placetype": "postalcode"
  },
  "geometry": {"coordinates":[-1.089931,52.668547],"type":"Point"}
}
