{
  "type": "Feature",
  "properties": {
    "iso:country":"GB",
    "wof:name":"SE4 1JN",
    "wof:placetype":"postalcode"
},
  "geometry": {"coordinates":[-0.02401130481236,51.45680313293173],"type":"Point"}
}