{
  "type": "Feature",
  "properties": {
    "iso:country": "GB",
    "wof:name": "BS35 1RN",
    "wof:placetype": "postalcode"
  },
  "geometry": {"coordinates":[-2.558703,51.64874],"type":"Point"}
}
