{
  "type": "Feature",
  "properties": {
    "iso:country":"GB",
    "wof:name":"BS35 1RN",
    "wof:placetype":"postalcode"
},
  "geometry": {"coordinates":[-2.55860217710035,51.64881867079411],"type":"Point"}
}