{
  "type": "Feature",
  "properties": {
    "date:inception_lower": "1980-01-01",
    "date:inception_upper": "1980-01-01",
    "iso:country": "GB",
    "wof:name": "DY10 1LF",
    "wof:placetype": "postalcode"
  },
  "geometry": {"coordinates":[-2.247109,52.379051],"type":"Point"}
}
