{
  "type": "Feature",
  "properties": {
    "iso:country": "GB",
    "wof:name": "ML6 7FG",
    "wof:placetype": "postalcode"
  },
  "geometry": {"coordinates":[-3.938932,55.915894],"type":"Point"}
}
