{
  "type": "Feature",
  "properties": {
    "iso:country":"GB",
    "wof:name":"ML6 7FG",
    "wof:placetype":"postalcode"
},
  "geometry": {"coordinates":[-3.9389319444881,55.91589376677751],"type":"Point"}
}