{
  "type": "Feature",
  "properties": {
    "date:inception_lower": "2009-08-01",
    "date:inception_upper": "2009-08-01",
    "iso:country": "GB",
    "wof:name": "ML6 7FG",
    "wof:placetype": "postalcode"
  },
  "geometry": {"coordinates":[-3.938932,55.915894],"type":"Point"}
}
