{
  "type": "Feature",
  "properties": {
    "iso:country":"GB",
    "wof:name":"ME2 2AG",
    "wof:placetype":"postalcode"
},
  "geometry": {"coordinates":[0.49217905988441,51.39071891459891],"type":"Point"}
}