{
  "type": "Feature",
  "properties": {
    "date:inception_lower": "1980-01-01",
    "date:inception_upper": "1980-01-01",
    "iso:country": "GB",
    "wof:name": "TS11 6AR",
    "wof:placetype": "postalcode"
  },
  "geometry": {"coordinates":[-1.020812,54.59649],"type":"Point"}
}
