{
  "type": "Feature",
  "properties": {
    "iso:country":"GB",
    "wof:name":"TS11 6AR",
    "wof:placetype":"postalcode"
},
  "geometry": {"coordinates":[-1.02081213601489,54.59649030357357],"type":"Point"}
}