{
  "type": "Feature",
  "properties": {
    "iso:country":"GB",
    "wof:name":"ST2 8BQ",
    "wof:placetype":"postalcode"
},
  "geometry": {"coordinates":[-2.14006090811887,53.03021898158428],"type":"Point"}
}