{
  "type": "Feature",
  "properties": {
    "iso:country":"GB",
    "wof:name":"NP16 7DR",
    "wof:placetype":"postalcode"
},
  "geometry": {"coordinates":[-2.66336643916467,51.63929999842284],"type":"Point"}
}