{
  "type": "Feature",
  "properties": {
    "date:inception_lower": "1999-06-01",
    "date:inception_upper": "1999-06-01",
    "iso:country": "GB",
    "wof:name": "NP16 7DR",
    "wof:placetype": "postalcode"
  },
  "geometry": {"coordinates":[-2.663366,51.6393],"type":"Point"}
}
