{
  "type": "Feature",
  "properties": {
    "iso:country":"GB",
    "wof:name":"BS37 6NH",
    "wof:placetype":"postalcode"
},
  "geometry": {"coordinates":[-2.38209224301912,51.53472420162893],"type":"Point"}
}