{
  "type": "Feature",
  "properties": {
    "iso:country":"GB",
    "wof:name":"S66 7RA",
    "wof:placetype":"postalcode"
},
  "geometry": {"coordinates":[-1.21787635465622,53.46208206380475],"type":"Point"}
}