{
  "type": "Feature",
  "properties": {
    "date:inception_lower":"1981-06-01",
    "date:inception_upper":"1981-06-30",
    "iso:country":"GB",
    "wof:name":"S66 7RA",
    "wof:placetype":"postalcode"
},
  "geometry": {"coordinates":[-1.217876,53.462082],"type":"Point"}
}