{
  "type": "Feature",
  "properties": {
    "iso:country":"GB",
    "wof:name":"BD20 6PJ",
    "wof:placetype":"postalcode"
},
  "geometry": {"coordinates":[-1.95679381104342,53.89437298394784],"type":"Point"}
}