{
  "type": "Feature",
  "properties": {
    "iso:country": "GB",
    "wof:name": "LN1 2QS",
    "wof:placetype": "postalcode"
  },
  "geometry": {"coordinates":[-0.665971,53.276448],"type":"Point"}
}
