{
  "type": "Feature",
  "properties": {
    "iso:country":"GB",
    "wof:name":"DL8 2EB",
    "wof:placetype":"postalcode"
},
  "geometry": {"coordinates":[-1.58938135319716,54.28525961069743],"type":"Point"}
}