{
  "type": "Feature",
  "properties": {
    "date:inception_lower": "1980-01-01",
    "date:inception_upper": "1980-01-01",
    "iso:country": "GB",
    "wof:name": "SN10 5XS",
    "wof:placetype": "postalcode"
  },
  "geometry": {"coordinates":[-2.025188,51.288003],"type":"Point"}
}
