{
  "type": "Feature",
  "properties": {
    "iso:country":"GB",
    "wof:name":"SN10 5XS",
    "wof:placetype":"postalcode"
},
  "geometry": {"coordinates":[-2.02518836243769,51.28800349848077],"type":"Point"}
}