{
  "type": "Feature",
  "properties": {
    "iso:country":"GB",
    "wof:name":"DT6 6AR",
    "wof:placetype":"postalcode"
},
  "geometry": {"coordinates":[-2.77827917499222,50.72301524333545],"type":"Point"}
}