{
  "type": "Feature",
  "properties": {
    "iso:country": "GB",
    "wof:name": "DT6 6AR",
    "wof:placetype": "postalcode"
  },
  "geometry": {"coordinates":[-2.778266,50.723013],"type":"Point"}
}
