{
  "type": "Feature",
  "properties": {
    "date:inception_lower":"1982-03-01",
    "date:inception_upper":"1982-03-31",
    "iso:country":"GB",
    "wof:name":"CW9 6PR",
    "wof:placetype":"postalcode"
},
  "geometry": {"coordinates":[-2.464387,53.283684],"type":"Point"}
}