{
  "type": "Feature",
  "properties": {
    "iso:country":"GB",
    "wof:name":"SG4 0AE",
    "wof:placetype":"postalcode"
},
  "geometry": {"coordinates":[-0.26836154577435,51.96220062281147],"type":"Point"}
}