{
  "type": "Feature",
  "properties": {
    "date:inception_lower": "1980-01-01",
    "date:inception_upper": "1980-01-01",
    "iso:country": "GB",
    "wof:name": "CO12 5DD",
    "wof:placetype": "postalcode"
  },
  "geometry": {"coordinates":[1.131291,51.89185],"type":"Point"}
}
