{
  "type": "Feature",
  "properties": {
    "date:inception_lower": "1980-01-01",
    "date:inception_upper": "1980-01-01",
    "iso:country": "GB",
    "wof:name": "DE11 9AZ",
    "wof:placetype": "postalcode"
  },
  "geometry": {"coordinates":[-1.559307,52.772308],"type":"Point"}
}
