{
  "type": "Feature",
  "properties": {
    "iso:country": "GB",
    "wof:name": "NP10 8FQ",
    "wof:placetype": "postalcode"
  },
  "geometry": {"coordinates":[-3.042724,51.556715],"type":"Point"}
}
