{
  "type": "Feature",
  "properties": {
    "date:inception_lower": "2017-11-01",
    "date:inception_upper": "2017-11-01",
    "iso:country": "GB",
    "wof:name": "NN4 6FU",
    "wof:placetype": "postalcode"
  },
  "geometry": {"coordinates":[-0.864549,52.20135],"type":"Point"}
}
