{
  "type": "Feature",
  "properties": {
    "iso:country": "GB",
    "wof:name": "LE10 1TW",
    "wof:placetype": "postalcode"
  },
  "geometry": {"coordinates":[-1.354642,52.552273],"type":"Point"}
}
