{
  "type": "Feature",
  "properties": {
    "iso:country":"GB",
    "wof:name":"LE10 1TW",
    "wof:placetype":"postalcode"
},
  "geometry": {"coordinates":[-1.35464218676367,52.5522726187023],"type":"Point"}
}