{
  "type": "Feature",
  "properties": {
    "date:inception_lower":"1980-01-01",
    "date:inception_upper":"1980-01-31",
    "iso:country":"GB",
    "wof:name":"LE10 1TW",
    "wof:placetype":"postalcode"
},
  "geometry": {"coordinates":[-1.354642,52.552273],"type":"Point"}
}