{
  "type": "Feature",
  "properties": {
    "iso:country":"GB",
    "wof:name":"N16 8RJ",
    "wof:placetype":"postalcode"
},
  "geometry": {"coordinates":[-0.08021465532914,51.55706909471557],"type":"Point"}
}