{
  "type": "Feature",
  "properties": {
    "iso:country":"GB",
    "wof:name":"GL11 6AS",
    "wof:placetype":"postalcode"
},
  "geometry": {"coordinates":[-2.3845782564919,51.6823449274258],"type":"Point"}
}