{
  "type": "Feature",
  "properties": {
    "iso:country":"GB",
    "wof:name":"BB2 7EQ",
    "wof:placetype":"postalcode"
},
  "geometry": {"coordinates":[-2.51464630008955,53.77598299892833],"type":"Point"}
}