{
  "type": "Feature",
  "properties": {
    "iso:country": "GB",
    "wof:name": "NG24 3AD",
    "wof:placetype": "postalcode"
  },
  "geometry": {"coordinates":[-0.785,53.059455],"type":"Point"}
}
