{
  "type": "Feature",
  "properties": {
    "date:inception_lower": "1980-01-01",
    "date:inception_upper": "1980-01-01",
    "iso:country": "GB",
    "wof:name": "WF10 5JU",
    "wof:placetype": "postalcode"
  },
  "geometry": {"coordinates":[-1.363774,53.722201],"type":"Point"}
}
