{
  "type": "Feature",
  "properties": {
    "iso:country":"GB",
    "wof:name":"WF10 5JU",
    "wof:placetype":"postalcode"
},
  "geometry": {"coordinates":[-1.36377417093001,53.72220090022815],"type":"Point"}
}