{
  "type": "Feature",
  "properties": {
    "iso:country":"GB",
    "wof:name":"HX2 8RQ",
    "wof:placetype":"postalcode"
},
  "geometry": {"coordinates":[-1.9063915762747,53.75289249287966],"type":"Point"}
}