{
  "type": "Feature",
  "properties": {
    "iso:country": "GB",
    "wof:name": "PH18 5UP",
    "wof:placetype": "postalcode"
  },
  "geometry": {"coordinates":[-3.94975,56.763525],"type":"Point"}
}
