{
  "type": "Feature",
  "properties": {
    "iso:country":"GB",
    "wof:name":"PH18 5UP",
    "wof:placetype":"postalcode"
},
  "geometry": {"coordinates":[-3.94975046071629,56.76352460257991],"type":"Point"}
}