{
  "type": "Feature",
  "properties": {
    "iso:country":"GB",
    "wof:name":"BN16 2EN",
    "wof:placetype":"postalcode"
},
  "geometry": {"coordinates":[-0.50172488865357,50.80387239057056],"type":"Point"}
}