{
  "type": "Feature",
  "properties": {
    "date:inception_lower":"1985-04-01",
    "date:inception_upper":"1985-04-30",
    "iso:country":"GB",
    "wof:name":"PR9 0PY",
    "wof:placetype":"postalcode"
},
  "geometry": {"coordinates":[-2.998229,53.650346],"type":"Point"}
}