{
  "type": "Feature",
  "properties": {
    "iso:country":"GB",
    "wof:name":"PR9 0PY",
    "wof:placetype":"postalcode"
},
  "geometry": {"coordinates":[-2.99822880660643,53.65034588108669],"type":"Point"}
}