{
  "type": "Feature",
  "properties": {
    "iso:country": "GB",
    "wof:name": "PH11 8LJ",
    "wof:placetype": "postalcode"
  },
  "geometry": {"coordinates":[-3.232986,56.628122],"type":"Point"}
}
