{
  "type": "Feature",
  "properties": {
    "date:inception_lower":"1980-01-01",
    "date:inception_upper":"1980-01-31",
    "iso:country":"GB",
    "wof:name":"PE3 8ND",
    "wof:placetype":"postalcode"
},
  "geometry": {"coordinates":[-0.281606,52.602627],"type":"Point"}
}