{
  "type": "Feature",
  "properties": {
    "iso:country":"GB",
    "wof:name":"GL55 6TQ",
    "wof:placetype":"postalcode"
},
  "geometry": {"coordinates":[-1.74794193993258,52.09664574564833],"type":"Point"}
}