{
  "type": "Feature",
  "properties": {
    "iso:country":"GB",
    "wof:name":"WD23 1NS",
    "wof:placetype":"postalcode"
},
  "geometry": {"coordinates":[-0.33717706534678,51.63229095661048],"type":"Point"}
}