{
  "type": "Feature",
  "properties": {
    "date:inception_lower": "1990-02-01",
    "date:inception_upper": "1990-02-01",
    "iso:country": "GB",
    "wof:name": "YO18 7EY",
    "wof:placetype": "postalcode"
  },
  "geometry": {"coordinates":[-0.778388,54.244145],"type":"Point"}
}
