{
  "type": "Feature",
  "properties": {
    "iso:country": "GB",
    "wof:name": "YO18 7EY",
    "wof:placetype": "postalcode"
  },
  "geometry": {"coordinates":[-0.778388,54.244145],"type":"Point"}
}
