{
  "type": "Feature",
  "properties": {
    "date:inception_lower": "2019-08-01",
    "date:inception_upper": "2019-08-01",
    "iso:country": "GB",
    "wof:name": "WD25 7FF",
    "wof:placetype": "postalcode"
  },
  "geometry": {"coordinates":[-0.398539,51.696957],"type":"Point"}
}
