{
  "type": "Feature",
  "properties": {
    "iso:country":"GB",
    "wof:name":"CM17 9EJ",
    "wof:placetype":"postalcode"
},
  "geometry": {"coordinates":[0.13072265319416,51.75703935722515],"type":"Point"}
}