{
  "type": "Feature",
  "properties": {
    "iso:country": "GB",
    "wof:name": "CM17 9EJ",
    "wof:placetype": "postalcode"
  },
  "geometry": {"coordinates":[0.130723,51.757039],"type":"Point"}
}
