{
  "type": "Feature",
  "properties": {
    "date:inception_lower": "2016-03-01",
    "date:inception_upper": "2016-03-01",
    "iso:country": "GB",
    "wof:name": "YO24 4EL",
    "wof:placetype": "postalcode"
  },
  "geometry": {"coordinates":[-1.094614,53.954497],"type":"Point"}
}
