{
  "type": "Feature",
  "properties": {
    "iso:country":"GB",
    "wof:name":"YO24 4EL",
    "wof:placetype":"postalcode"
},
  "geometry": {"coordinates":[-1.094613640653,53.95449671909896],"type":"Point"}
}