{
  "type": "Feature",
  "properties": {
    "iso:country": "GB",
    "wof:name": "YO24 4EL",
    "wof:placetype": "postalcode"
  },
  "geometry": {"coordinates":[-1.094614,53.954497],"type":"Point"}
}
