{
  "type": "Feature",
  "properties": {
    "iso:country": "GB",
    "wof:name": "SM2 6EU",
    "wof:placetype": "postalcode"
  },
  "geometry": {"coordinates":[-0.209378,51.35419],"type":"Point"}
}
