{
  "type": "Feature",
  "properties": {
    "iso:country":"GB",
    "wof:name":"SM2 6EU",
    "wof:placetype":"postalcode"
},
  "geometry": {"coordinates":[-0.20937760664345,51.35419009300229],"type":"Point"}
}