{
  "type": "Feature",
  "properties": {
    "date:inception_lower": "1980-01-01",
    "date:inception_upper": "1980-01-01",
    "iso:country": "GB",
    "wof:name": "DN6 9NP",
    "wof:placetype": "postalcode"
  },
  "geometry": {"coordinates":[-1.176434,53.621837],"type":"Point"}
}
