{
  "type": "Feature",
  "properties": {
    "iso:country":"GB",
    "wof:name":"BL1 4RE",
    "wof:placetype":"postalcode"
},
  "geometry": {"coordinates":[-2.44860225220362,53.58026033760564],"type":"Point"}
}