{
  "type": "Feature",
  "properties": {
    "date:inception_lower": "1980-01-01",
    "date:inception_upper": "1980-01-01",
    "iso:country": "GB",
    "wof:name": "CV2 4PZ",
    "wof:placetype": "postalcode"
  },
  "geometry": {"coordinates":[-1.486112,52.415539],"type":"Point"}
}
