{
  "type": "Feature",
  "properties": {
    "iso:country":"GB",
    "wof:name":"HX7 6NE",
    "wof:placetype":"postalcode"
},
  "geometry": {"coordinates":[-2.02966321270474,53.7404766759818],"type":"Point"}
}