{
  "type": "Feature",
  "properties": {
    "iso:country": "GB",
    "wof:name": "YO13 0NY",
    "wof:placetype": "postalcode"
  },
  "geometry": {"coordinates":[-0.493233,54.398184],"type":"Point"}
}
