{
  "type": "Feature",
  "properties": {
    "iso:country":"GB",
    "wof:name":"KT24 5RZ",
    "wof:placetype":"postalcode"
},
  "geometry": {"coordinates":[-0.42120984688529,51.26231162027828],"type":"Point"}
}