{
  "type": "Feature",
  "properties": {
    "iso:country":"GB",
    "wof:name":"GL9 1EX",
    "wof:placetype":"postalcode"
},
  "geometry": {"coordinates":[-2.28530726877047,51.53892893763648],"type":"Point"}
}