{
  "type": "Feature",
  "properties": {
    "iso:country":"GB",
    "wof:name":"CM18 7EH",
    "wof:placetype":"postalcode"
},
  "geometry": {"coordinates":[0.11676651204835,51.74893754460579],"type":"Point"}
}