{
  "type": "Feature",
  "properties": {
    "date:inception_lower": "1986-01-01",
    "date:inception_upper": "1986-01-01",
    "iso:country": "GB",
    "wof:name": "SO41 0TZ",
    "wof:placetype": "postalcode"
  },
  "geometry": {"coordinates":[-1.568397,50.723782],"type":"Point"}
}
