{
  "type": "Feature",
  "properties": {
    "iso:country":"GB",
    "wof:name":"SO41 0TZ",
    "wof:placetype":"postalcode"
},
  "geometry": {"coordinates":[-1.56839733102349,50.72378247544658],"type":"Point"}
}