{
  "type": "Feature",
  "properties": {
    "iso:country":"GB",
    "wof:name":"G63 0BG",
    "wof:placetype":"postalcode"
},
  "geometry": {"coordinates":[-4.45231040037801,56.06396933227812],"type":"Point"}
}