{
  "type": "Feature",
  "properties": {
    "iso:country": "GB",
    "wof:name": "G63 0BG",
    "wof:placetype": "postalcode"
  },
  "geometry": {"coordinates":[-4.452341,56.063917],"type":"Point"}
}
