{
  "type": "Feature",
  "properties": {
    "iso:country":"GB",
    "wof:name":"EX8 1DS",
    "wof:placetype":"postalcode"
},
  "geometry": {"coordinates":[-3.42219292483567,50.6168596220405],"type":"Point"}
}