{
  "type": "Feature",
  "properties": {
    "iso:country":"GB",
    "wof:name":"HP11 1TT",
    "wof:placetype":"postalcode"
},
  "geometry": {"coordinates":[-0.77064253043028,51.61490686333627],"type":"Point"}
}