{
  "type": "Feature",
  "properties": {
    "iso:country":"GB",
    "wof:name":"PA67 6DQ",
    "wof:placetype":"postalcode"
},
  "geometry": {"coordinates":[-6.2291856419359,56.31724684631174],"type":"Point"}
}