{
  "type": "Feature",
  "properties": {
    "iso:country": "GB",
    "wof:name": "BA2 3GU",
    "wof:placetype": "postalcode"
  },
  "geometry": {"coordinates":[-2.382863,51.382635],"type":"Point"}
}
