{
  "type": "Feature",
  "properties": {
    "iso:country":"GB",
    "wof:name":"LL40 2RS",
    "wof:placetype":"postalcode"
},
  "geometry": {"coordinates":[-3.82343292130172,52.75350655572747],"type":"Point"}
}