{
  "type": "Feature",
  "properties": {
    "date:inception_lower": "2010-06-01",
    "date:inception_upper": "2010-06-01",
    "iso:country": "GB",
    "wof:name": "AB45 2PZ",
    "wof:placetype": "postalcode"
  },
  "geometry": {"coordinates":[-2.692435,57.682],"type":"Point"}
}
