{
  "type": "Feature",
  "properties": {
    "iso:country": "GB",
    "wof:name": "SY4 3JU",
    "wof:placetype": "postalcode"
  },
  "geometry": {"coordinates":[-2.714205,52.801513],"type":"Point"}
}
