{
  "type": "Feature",
  "properties": {
    "iso:country":"GB",
    "wof:name":"SY4 3JU",
    "wof:placetype":"postalcode"
},
  "geometry": {"coordinates":[-2.71420481180115,52.80151319691815],"type":"Point"}
}