{
  "type": "Feature",
  "properties": {
    "iso:country": "GB",
    "wof:name": "PL25 5BE",
    "wof:placetype": "postalcode"
  },
  "geometry": {"coordinates":[-4.797544,50.340326],"type":"Point"}
}
