{
  "type": "Feature",
  "properties": {
    "date:inception_lower":"2009-04-01",
    "date:inception_upper":"2009-04-30",
    "iso:country":"GB",
    "wof:name":"PL25 5BE",
    "wof:placetype":"postalcode"
},
  "geometry": {"coordinates":[-4.797544,50.340326],"type":"Point"}
}