{
  "type": "Feature",
  "properties": {
    "iso:country":"GB",
    "wof:name":"PL25 5BE",
    "wof:placetype":"postalcode"
},
  "geometry": {"coordinates":[-4.79754444335646,50.34032594924415],"type":"Point"}
}