{
  "type": "Feature",
  "properties": {
    "iso:country": "GB",
    "wof:name": "NP26 3FN",
    "wof:placetype": "postalcode"
  },
  "geometry": {"coordinates":[-2.78243,51.585085],"type":"Point"}
}
