{
  "type": "Feature",
  "properties": {
    "iso:country":"GB",
    "wof:name":"NP26 3FN",
    "wof:placetype":"postalcode"
},
  "geometry": {"coordinates":[-2.78243049938361,51.5850854267231],"type":"Point"}
}