{
  "type": "Feature",
  "properties": {
    "date:inception_lower": "2008-08-01",
    "date:inception_upper": "2008-08-01",
    "iso:country": "GB",
    "wof:name": "NP26 3FN",
    "wof:placetype": "postalcode"
  },
  "geometry": {"coordinates":[-2.78243,51.585085],"type":"Point"}
}
