{
  "type": "Feature",
  "properties": {
    "iso:country":"GB",
    "wof:name":"BD21 4HA",
    "wof:placetype":"postalcode"
},
  "geometry": {"coordinates":[-1.88267643181114,53.87691417362184],"type":"Point"}
}