{
  "type": "Feature",
  "properties": {
    "iso:country":"GB",
    "wof:name":"WD18 7AD",
    "wof:placetype":"postalcode"
},
  "geometry": {"coordinates":[-0.41913748290158,51.65503987850496],"type":"Point"}
}