{
  "type": "Feature",
  "properties": {
    "iso:country": "GB",
    "wof:name": "WD18 7AD",
    "wof:placetype": "postalcode"
  },
  "geometry": {"coordinates":[-0.419137,51.65504],"type":"Point"}
}
