{
  "type": "Feature",
  "properties": {
    "iso:country":"GB",
    "wof:name":"CM20 3QX",
    "wof:placetype":"postalcode"
},
  "geometry": {"coordinates":[0.10017148568559,51.77189634247684],"type":"Point"}
}