{
  "type": "Feature",
  "properties": {
    "iso:country": "GB",
    "wof:name": "OX29 6QG",
    "wof:placetype": "postalcode"
  },
  "geometry": {"coordinates":[-1.440356,51.840335],"type":"Point"}
}
