{
  "type": "Feature",
  "properties": {
    "iso:country":"GB",
    "wof:name":"HU8 8UF",
    "wof:placetype":"postalcode"
},
  "geometry": {"coordinates":[-0.31689410482438,53.7571508820793],"type":"Point"}
}