{
  "type": "Feature",
  "properties": {
    "date:inception_lower":"2014-06-01",
    "date:inception_upper":"2014-06-30",
    "iso:country":"GB",
    "wof:name":"GL50 4GN",
    "wof:placetype":"postalcode"
},
  "geometry": {"coordinates":[-2.082034,51.912864],"type":"Point"}
}