{
  "type": "Feature",
  "properties": {
    "date:inception_lower": "1981-06-01",
    "date:inception_upper": "1981-06-01",
    "iso:country": "GB",
    "wof:name": "GL7 1PX",
    "wof:placetype": "postalcode"
  },
  "geometry": {"coordinates":[-1.965998,51.712057],"type":"Point"}
}
