{
  "type": "Feature",
  "properties": {
    "iso:country":"GB",
    "wof:name":"M18 8LS",
    "wof:placetype":"postalcode"
},
  "geometry": {"coordinates":[-2.17060144132163,53.46365494980977],"type":"Point"}
}