{
  "type": "Feature",
  "properties": {
    "iso:country": "GB",
    "wof:name": "M18 8LS",
    "wof:placetype": "postalcode"
  },
  "geometry": {"coordinates":[-2.170601,53.463655],"type":"Point"}
}
