{
  "type": "Feature",
  "properties": {
    "iso:country": "GB",
    "wof:name": "IP30 9SS",
    "wof:placetype": "postalcode"
  },
  "geometry": {"coordinates":[0.855187,52.222832],"type":"Point"}
}
