{
  "type": "Feature",
  "properties": {
    "date:inception_lower": "2002-09-01",
    "date:inception_upper": "2002-09-01",
    "iso:country": "GB",
    "wof:name": "CV34 6DF",
    "wof:placetype": "postalcode"
  },
  "geometry": {"coordinates":[-1.61052,52.271241],"type":"Point"}
}
