{
  "type": "Feature",
  "properties": {
    "iso:country":"GB",
    "wof:name":"BN9 9EW",
    "wof:placetype":"postalcode"
},
  "geometry": {"coordinates":[0.05027593901782,50.78704897738526],"type":"Point"}
}