{
  "type": "Feature",
  "properties": {
    "iso:country":"GB",
    "wof:name":"BA1 5LJ",
    "wof:placetype":"postalcode"
},
  "geometry": {"coordinates":[-2.36056217336363,51.38438147386979],"type":"Point"}
}