{
  "type": "Feature",
  "properties": {
    "date:inception_lower": "2004-10-01",
    "date:inception_upper": "2004-10-01",
    "iso:country": "GB",
    "wof:name": "B18 5SN",
    "wof:placetype": "postalcode"
  },
  "geometry": {"coordinates":[-1.927934,52.49294],"type":"Point"}
}
