{
  "type": "Feature",
  "properties": {
    "iso:country":"GB",
    "wof:name":"AB56 1DR",
    "wof:placetype":"postalcode"
},
  "geometry": {"coordinates":[-2.98186856390057,57.67109151064054],"type":"Point"}
}