{
  "type": "Feature",
  "properties": {
    "date:inception_lower": "1990-08-01",
    "date:inception_upper": "1990-08-01",
    "iso:country": "GB",
    "wof:name": "AB56 1DR",
    "wof:placetype": "postalcode"
  },
  "geometry": {"coordinates":[-2.981869,57.671092],"type":"Point"}
}
