{
  "type": "Feature",
  "properties": {
    "date:inception_lower":"1997-12-01",
    "date:inception_upper":"1997-12-31",
    "iso:country":"GB",
    "wof:name":"DN8 5TZ",
    "wof:placetype":"postalcode"
},
  "geometry": {"coordinates":[-0.975224,53.614785],"type":"Point"}
}