{
  "type": "Feature",
  "properties": {
    "iso:country":"GB",
    "wof:name":"DN8 5TZ",
    "wof:placetype":"postalcode"
},
  "geometry": {"coordinates":[-0.97521931768975,53.61476472735851],"type":"Point"}
}