{
  "type": "Feature",
  "properties": {
    "iso:country": "GB",
    "wof:name": "DN8 5TZ",
    "wof:placetype": "postalcode"
  },
  "geometry": {"coordinates":[-0.975224,53.614785],"type":"Point"}
}
