{
  "type": "Feature",
  "properties": {
    "iso:country": "GB",
    "wof:name": "ME15 9ZX",
    "wof:placetype": "postalcode"
  },
  "geometry": {"coordinates":[0.555023,51.240375],"type":"Point"}
}
