{
  "type": "Feature",
  "properties": {
    "iso:country": "GB",
    "wof:name": "CF44 6BF",
    "wof:placetype": "postalcode"
  },
  "geometry": {"coordinates":[-3.40208,51.687701],"type":"Point"}
}
