{
  "type": "Feature",
  "properties": {
    "iso:country":"GB",
    "wof:name":"SN16 0PF",
    "wof:placetype":"postalcode"
},
  "geometry": {"coordinates":[-2.17323548139603,51.58898736138389],"type":"Point"}
}