{
  "type": "Feature",
  "properties": {
    "iso:country": "GB",
    "wof:name": "SN16 0PF",
    "wof:placetype": "postalcode"
  },
  "geometry": {"coordinates":[-2.173235,51.588987],"type":"Point"}
}
