{
  "type": "Feature",
  "properties": {
    "iso:country":"GB",
    "wof:name":"N14 5AG",
    "wof:placetype":"postalcode"
},
  "geometry": {"coordinates":[-0.13145890900447,51.63157115233506],"type":"Point"}
}