{
  "type": "Feature",
  "properties": {
    "iso:country":"GB",
    "wof:name":"CV2 4DQ",
    "wof:placetype":"postalcode"
},
  "geometry": {"coordinates":[-1.48143148108997,52.40721176804023],"type":"Point"}
}