{
  "type": "Feature",
  "properties": {
    "iso:country": "GB",
    "wof:name": "BS30 9BG",
    "wof:placetype": "postalcode"
  },
  "geometry": {"coordinates":[-2.496855,51.436814],"type":"Point"}
}
