{
  "type": "Feature",
  "properties": {
    "iso:country":"GB",
    "wof:name":"BS30 9BG",
    "wof:placetype":"postalcode"
},
  "geometry": {"coordinates":[-2.49694092942293,51.43684317872585],"type":"Point"}
}