{
  "type": "Feature",
  "properties": {
    "iso:country":"GB",
    "wof:name":"E5 8RN",
    "wof:placetype":"postalcode"
},
  "geometry": {"coordinates":[-0.06513461952569,51.56262155802754],"type":"Point"}
}