{
  "type": "Feature",
  "properties": {
    "date:inception_lower":"2015-09-01",
    "date:inception_upper":"2015-09-30",
    "iso:country":"GB",
    "wof:name":"NR28 0FQ",
    "wof:placetype":"postalcode"
},
  "geometry": {"coordinates":[1.384391,52.814297],"type":"Point"}
}