{
  "type": "Feature",
  "properties": {
    "iso:country":"GB",
    "wof:name":"NR28 0FQ",
    "wof:placetype":"postalcode"
},
  "geometry": {"coordinates":[1.38272028029307,52.81653803673165],"type":"Point"}
}