{
  "type": "Feature",
  "properties": {
    "iso:country": "GB",
    "wof:name": "NR28 0FQ",
    "wof:placetype": "postalcode"
  },
  "geometry": {"coordinates":[1.384391,52.814297],"type":"Point"}
}
