{
  "type": "Feature",
  "properties": {
    "iso:country":"GB",
    "wof:name":"TS18 3US",
    "wof:placetype":"postalcode"
},
  "geometry": {"coordinates":[-1.31947226818135,54.53982494032319],"type":"Point"}
}