{
  "type": "Feature",
  "properties": {
    "iso:country": "GB",
    "wof:name": "LL14 3QA",
    "wof:placetype": "postalcode"
  },
  "geometry": {"coordinates":[-3.0768,52.978613],"type":"Point"}
}
