{
  "type": "Feature",
  "properties": {
    "date:inception_lower": "1994-12-01",
    "date:inception_upper": "1994-12-01",
    "iso:country": "GB",
    "wof:name": "LL14 3QA",
    "wof:placetype": "postalcode"
  },
  "geometry": {"coordinates":[-3.076338,52.977979],"type":"Point"}
}
