{
  "type": "Feature",
  "properties": {
    "iso:country":"GB",
    "wof:name":"WN8 6AW",
    "wof:placetype":"postalcode"
},
  "geometry": {"coordinates":[-2.75738535426108,53.54808841800902],"type":"Point"}
}