{
  "type": "Feature",
  "properties": {
    "iso:country":"GB",
    "wof:name":"G61 1NL",
    "wof:placetype":"postalcode"
},
  "geometry": {"coordinates":[-4.33776952926187,55.90815705209248],"type":"Point"}
}