{
  "type": "Feature",
  "properties": {
    "iso:country": "GB",
    "wof:name": "KA7 4RE",
    "wof:placetype": "postalcode"
  },
  "geometry": {"coordinates":[-4.62138,55.442605],"type":"Point"}
}
