{
  "type": "Feature",
  "properties": {
    "date:inception_lower": "1980-01-01",
    "date:inception_upper": "1980-01-01",
    "iso:country": "GB",
    "wof:name": "S5 7JG",
    "wof:placetype": "postalcode"
  },
  "geometry": {"coordinates":[-1.457953,53.416815],"type":"Point"}
}
