{
  "type": "Feature",
  "properties": {
    "iso:country": "GB",
    "wof:name": "CO6 2DS",
    "wof:placetype": "postalcode"
  },
  "geometry": {"coordinates":[0.756133,51.924764],"type":"Point"}
}
