{
  "type": "Feature",
  "properties": {
    "date:inception_lower": "1991-01-01",
    "date:inception_upper": "1991-01-01",
    "iso:country": "GB",
    "wof:name": "M11 1WN",
    "wof:placetype": "postalcode"
  },
  "geometry": {"coordinates":[-2.167403,53.470086],"type":"Point"}
}
