{
  "type": "Feature",
  "properties": {
    "iso:country": "GB",
    "wof:name": "HU3 1JY",
    "wof:placetype": "postalcode"
  },
  "geometry": {"coordinates":[-0.35867,53.749361],"type":"Point"}
}
