{
  "type": "Feature",
  "properties": {
    "date:inception_lower": "1980-01-01",
    "date:inception_upper": "1980-01-01",
    "iso:country": "GB",
    "wof:name": "BA2 3JA",
    "wof:placetype": "postalcode"
  },
  "geometry": {"coordinates":[-2.381273,51.378117],"type":"Point"}
}
