{
  "type": "Feature",
  "properties": {
    "iso:country":"GB",
    "wof:name":"BA2 3JA",
    "wof:placetype":"postalcode"
},
  "geometry": {"coordinates":[-2.38127475656426,51.37813857716274],"type":"Point"}
}