{
  "type": "Feature",
  "properties": {
    "iso:country":"GB",
    "wof:name":"OX11 7PG",
    "wof:placetype":"postalcode"
},
  "geometry": {"coordinates":[-1.23227524467112,51.61459720937894],"type":"Point"}
}