{
  "type": "Feature",
  "properties": {
    "date:inception_lower":"1997-12-01",
    "date:inception_upper":"1997-12-31",
    "iso:country":"GB",
    "wof:name":"SL1 4UF",
    "wof:placetype":"postalcode"
},
  "geometry": {"coordinates":[-0.618035,51.52303],"type":"Point"}
}