{
  "type": "Feature",
  "properties": {
    "iso:country":"GB",
    "wof:name":"SL1 4UF",
    "wof:placetype":"postalcode"
},
  "geometry": {"coordinates":[-0.61803484743001,51.52302957368183],"type":"Point"}
}