{
  "type": "Feature",
  "properties": {
    "iso:country": "GB",
    "wof:name": "SL1 4UF",
    "wof:placetype": "postalcode"
  },
  "geometry": {"coordinates":[-0.618035,51.52303],"type":"Point"}
}
