{
  "type": "Feature",
  "properties": {
    "iso:country":"GB",
    "wof:name":"SL1 7DG",
    "wof:placetype":"postalcode"
},
  "geometry": {"coordinates":[-0.66415695887918,51.53645826555841],"type":"Point"}
}