{
  "type": "Feature",
  "properties": {
    "iso:country":"GB",
    "wof:name":"B79 8NN",
    "wof:placetype":"postalcode"
},
  "geometry": {"coordinates":[-1.71604591026507,52.64919782428248],"type":"Point"}
}