{
  "type": "Feature",
  "properties": {
    "iso:country": "GB",
    "wof:name": "DT11 8TU",
    "wof:placetype": "postalcode"
  },
  "geometry": {"coordinates":[-2.137378,50.877777],"type":"Point"}
}
