{
  "type": "Feature",
  "properties": {
    "iso:country":"GB",
    "wof:name":"DT11 8TU",
    "wof:placetype":"postalcode"
},
  "geometry": {"coordinates":[-2.13737850972821,50.87777705785091],"type":"Point"}
}