{
  "type": "Feature",
  "properties": {
    "iso:country":"GB",
    "wof:name":"BS23 1HP",
    "wof:placetype":"postalcode"
},
  "geometry": {"coordinates":[-2.9789364802522,51.35080365564641],"type":"Point"}
}