{
  "type": "Feature",
  "properties": {
    "iso:country":"GB",
    "wof:name":"BH24 3BZ",
    "wof:placetype":"postalcode"
},
  "geometry": {"coordinates":[-1.75635960818942,50.82289422485328],"type":"Point"}
}