{
  "type": "Feature",
  "properties": {
    "date:inception_lower": "2014-08-01",
    "date:inception_upper": "2014-08-01",
    "iso:country": "GB",
    "wof:name": "NE46 1AB",
    "wof:placetype": "postalcode"
  },
  "geometry": {"coordinates":[-2.088816,54.968322],"type":"Point"}
}
