{
  "type": "Feature",
  "properties": {
    "iso:country": "GB",
    "wof:name": "DL7 8TG",
    "wof:placetype": "postalcode"
  },
  "geometry": {"coordinates":[-1.440011,54.334287],"type":"Point"}
}
