{
  "type": "Feature",
  "properties": {
    "date:inception_lower":"2011-05-01",
    "date:inception_upper":"2011-05-31",
    "iso:country":"GB",
    "wof:name":"DL7 8TG",
    "wof:placetype":"postalcode"
},
  "geometry": {"coordinates":[-1.440011,54.334287],"type":"Point"}
}