{
  "type": "Feature",
  "properties": {
    "date:inception_lower":"1980-01-01",
    "date:inception_upper":"1980-01-31",
    "iso:country":"GB",
    "wof:name":"LE2 4HL",
    "wof:placetype":"postalcode"
},
  "geometry": {"coordinates":[-1.069215,52.599531],"type":"Point"}
}