{
  "type": "Feature",
  "properties": {
    "iso:country":"GB",
    "wof:name":"LE2 4HL",
    "wof:placetype":"postalcode"
},
  "geometry": {"coordinates":[-1.06921457868254,52.59953125341794],"type":"Point"}
}