{
  "type": "Feature",
  "properties": {
    "iso:country":"GB",
    "wof:name":"ZE1 0FB",
    "wof:placetype":"postalcode"
},
  "geometry": {"coordinates":[-1.16432278101076,60.16402533934114],"type":"Point"}
}