{
  "type": "Feature",
  "properties": {
    "date:inception_lower":"1994-05-01",
    "date:inception_upper":"1994-05-31",
    "iso:country":"GB",
    "wof:name":"PE22 8NY",
    "wof:placetype":"postalcode"
},
  "geometry": {"coordinates":[0.179874,53.080923],"type":"Point"}
}