{
  "type": "Feature",
  "properties": {
    "iso:country": "GB",
    "wof:name": "PE22 8NY",
    "wof:placetype": "postalcode"
  },
  "geometry": {"coordinates":[0.179874,53.080923],"type":"Point"}
}
