{
  "type": "Feature",
  "properties": {
    "iso:country":"GB",
    "wof:name":"TN8 7NH",
    "wof:placetype":"postalcode"
},
  "geometry": {"coordinates":[0.11042191741524,51.18358859615309],"type":"Point"}
}