{
  "type": "Feature",
  "properties": {
    "iso:country":"GB",
    "wof:name":"BH9 1ED",
    "wof:placetype":"postalcode"
},
  "geometry": {"coordinates":[-1.87627897254543,50.74249123682511],"type":"Point"}
}