{
  "type": "Feature",
  "properties": {
    "iso:country": "GB",
    "wof:name": "BH9 1ED",
    "wof:placetype": "postalcode"
  },
  "geometry": {"coordinates":[-1.876279,50.742491],"type":"Point"}
}
