{
  "type": "Feature",
  "properties": {
    "iso:country":"GB",
    "wof:name":"LE2 8DY",
    "wof:placetype":"postalcode"
},
  "geometry": {"coordinates":[-1.15251816733007,52.60709671945975],"type":"Point"}
}