{
  "type": "Feature",
  "properties": {
    "iso:country": "GB",
    "wof:name": "LE2 8DY",
    "wof:placetype": "postalcode"
  },
  "geometry": {"coordinates":[-1.152518,52.607097],"type":"Point"}
}
