{
  "type": "Feature",
  "properties": {
    "date:inception_lower": "2011-05-01",
    "date:inception_upper": "2011-05-01",
    "iso:country": "GB",
    "wof:name": "LE2 8DY",
    "wof:placetype": "postalcode"
  },
  "geometry": {"coordinates":[-1.15242,52.607177],"type":"Point"}
}
