{
  "type": "Feature",
  "properties": {
    "iso:country":"GB",
    "wof:name":"SK7 2HS",
    "wof:placetype":"postalcode"
},
  "geometry": {"coordinates":[-2.15865921225639,53.36333228553978],"type":"Point"}
}