{
  "type": "Feature",
  "properties": {
    "iso:country": "GB",
    "wof:name": "SK6 5EY",
    "wof:placetype": "postalcode"
  },
  "geometry": {"coordinates":[-2.053987,53.402427],"type":"Point"}
}
