{
  "type": "Feature",
  "properties": {
    "iso:country":"GB",
    "wof:name":"SK6 5EY",
    "wof:placetype":"postalcode"
},
  "geometry": {"coordinates":[-2.05398680238506,53.40242721508192],"type":"Point"}
}