{
  "type": "Feature",
  "properties": {
    "date:inception_lower": "2001-06-01",
    "date:inception_upper": "2001-06-01",
    "iso:country": "GB",
    "wof:name": "SK6 5EY",
    "wof:placetype": "postalcode"
  },
  "geometry": {"coordinates":[-2.053987,53.402427],"type":"Point"}
}
