{
  "type": "Feature",
  "properties": {
    "iso:country":"GB",
    "wof:name":"WR3 8PJ",
    "wof:placetype":"postalcode"
},
  "geometry": {"coordinates":[-2.20771915175909,52.21220478073896],"type":"Point"}
}