{
  "type": "Feature",
  "properties": {
    "iso:country":"GB",
    "wof:name":"SP8 5SB",
    "wof:placetype":"postalcode"
},
  "geometry": {"coordinates":[-2.29165463508198,50.99418705932362],"type":"Point"}
}