{
  "type": "Feature",
  "properties": {
    "iso:country":"GB",
    "wof:name":"UB5 4DN",
    "wof:placetype":"postalcode"
},
  "geometry": {"coordinates":[-0.36928509448632,51.55040915540394],"type":"Point"}
}