{
  "type": "Feature",
  "properties": {
    "iso:country": "GB",
    "wof:name": "UB5 4DN",
    "wof:placetype": "postalcode"
  },
  "geometry": {"coordinates":[-0.369285,51.550409],"type":"Point"}
}
