{
  "type": "Feature",
  "properties": {
    "date:inception_lower":"1980-01-01",
    "date:inception_upper":"1980-01-31",
    "iso:country":"GB",
    "wof:name":"NG34 9BY",
    "wof:placetype":"postalcode"
},
  "geometry": {"coordinates":[-0.386326,53.043452],"type":"Point"}
}