{
  "type": "Feature",
  "properties": {
    "iso:country":"GB",
    "wof:name":"NG34 9BY",
    "wof:placetype":"postalcode"
},
  "geometry": {"coordinates":[-0.38632621094316,53.04345178390952],"type":"Point"}
}