{
  "type": "Feature",
  "properties": {
    "iso:country": "GB",
    "wof:name": "NG34 9BY",
    "wof:placetype": "postalcode"
  },
  "geometry": {"coordinates":[-0.386326,53.043452],"type":"Point"}
}
