{
  "type": "Feature",
  "properties": {
    "iso:country": "GB",
    "wof:name": "TN5 7FH",
    "wof:placetype": "postalcode"
  },
  "geometry": {"coordinates":[0.415131,51.047138],"type":"Point"}
}
