{
  "type": "Feature",
  "properties": {
    "date:inception_lower": "2020-02-01",
    "date:inception_upper": "2020-02-01",
    "iso:country": "GB",
    "wof:name": "TN5 7FH",
    "wof:placetype": "postalcode"
  },
  "geometry": {"coordinates":[0.415131,51.047138],"type":"Point"}
}
