{
  "type": "Feature",
  "properties": {
    "date:inception_lower": "2017-09-01",
    "date:inception_upper": "2017-09-01",
    "iso:country": "GB",
    "wof:name": "ME19 5FT",
    "wof:placetype": "postalcode"
  },
  "geometry": {"coordinates":[0.409734,51.307132],"type":"Point"}
}
