{
  "type": "Feature",
  "properties": {
    "iso:country":"GB",
    "wof:name":"LU7 1TQ",
    "wof:placetype":"postalcode"
},
  "geometry": {"coordinates":[-0.66080344901596,51.91603094901735],"type":"Point"}
}