{
  "type": "Feature",
  "properties": {
    "iso:country":"GB",
    "wof:name":"NE66 3UZ",
    "wof:placetype":"postalcode"
},
  "geometry": {"coordinates":[-1.63394194192804,55.49660517815863],"type":"Point"}
}