{
  "type": "Feature",
  "properties": {
    "iso:country": "GB",
    "wof:name": "E4 8PN",
    "wof:placetype": "postalcode"
  },
  "geometry": {"coordinates":[-0.021163,51.611023],"type":"Point"}
}
