{
  "type": "Feature",
  "properties": {
    "iso:country":"GB",
    "wof:name":"E4 8PN",
    "wof:placetype":"postalcode"
},
  "geometry": {"coordinates":[-0.02116296728839,51.61102347645052],"type":"Point"}
}