{
  "type": "Feature",
  "properties": {
    "date:inception_lower": "1980-01-01",
    "date:inception_upper": "1980-01-01",
    "iso:country": "GB",
    "wof:name": "G81 4QH",
    "wof:placetype": "postalcode"
  },
  "geometry": {"coordinates":[-4.43664,55.921456],"type":"Point"}
}
