{
  "type": "Feature",
  "properties": {
    "iso:country":"GB",
    "wof:name":"SS12 0PP",
    "wof:placetype":"postalcode"
},
  "geometry": {"coordinates":[0.50856722625378,51.60192088818094],"type":"Point"}
}