{
  "type": "Feature",
  "properties": {
    "date:inception_lower":"1980-01-01",
    "date:inception_upper":"1980-01-31",
    "iso:country":"GB",
    "wof:name":"SS12 0PP",
    "wof:placetype":"postalcode"
},
  "geometry": {"coordinates":[0.508567,51.601921],"type":"Point"}
}