{
  "type": "Feature",
  "properties": {
    "iso:country": "GB",
    "wof:name": "WR11 8PZ",
    "wof:placetype": "postalcode"
  },
  "geometry": {"coordinates":[-1.919183,52.138612],"type":"Point"}
}
