{
  "type": "Feature",
  "properties": {
    "iso:country":"GB",
    "wof:name":"LL28 5ET",
    "wof:placetype":"postalcode"
},
  "geometry": {"coordinates":[-3.74696561033125,53.27176165496628],"type":"Point"}
}