{
  "type": "Feature",
  "properties": {
    "iso:country": "GB",
    "wof:name": "LL28 5ET",
    "wof:placetype": "postalcode"
  },
  "geometry": {"coordinates":[-3.746966,53.271762],"type":"Point"}
}
