{
  "type": "Feature",
  "properties": {
    "iso:country":"GB",
    "wof:name":"BB4 8NN",
    "wof:placetype":"postalcode"
},
  "geometry": {"coordinates":[-2.28573504518363,53.72282813506997],"type":"Point"}
}