{
  "type": "Feature",
  "properties": {
    "iso:country": "GB",
    "wof:name": "S6 6GQ",
    "wof:placetype": "postalcode"
  },
  "geometry": {"coordinates":[-1.592041,53.420116],"type":"Point"}
}
