{
  "type": "Feature",
  "properties": {
    "iso:country":"GB",
    "wof:name":"SS17 0DN",
    "wof:placetype":"postalcode"
},
  "geometry": {"coordinates":[0.42398721468154,51.51355083416079],"type":"Point"}
}