{
  "type": "Feature",
  "properties": {
    "iso:country":"GB",
    "wof:name":"M46 9BD",
    "wof:placetype":"postalcode"
},
  "geometry": {"coordinates":[-2.47761473867443,53.51712114945696],"type":"Point"}
}