{
  "type": "Feature",
  "properties": {
    "date:inception_lower":"1980-01-01",
    "date:inception_upper":"1980-01-31",
    "iso:country":"GB",
    "wof:name":"TW17 0EP",
    "wof:placetype":"postalcode"
},
  "geometry": {"coordinates":[-0.456907,51.404877],"type":"Point"}
}