{
  "type": "Feature",
  "properties": {
    "iso:country": "GB",
    "wof:name": "TW17 0EP",
    "wof:placetype": "postalcode"
  },
  "geometry": {"coordinates":[-0.456907,51.404877],"type":"Point"}
}
