{
  "type": "Feature",
  "properties": {
    "iso:country":"GB",
    "wof:name":"EC1A 1HQ",
    "wof:placetype":"postalcode"
},
  "geometry": {"coordinates":[-0.09890559456081,51.51635854288295],"type":"Point"}
}