{
  "type": "Feature",
  "properties": {
    "iso:country": "GB",
    "wof:name": "PE21 8JU",
    "wof:placetype": "postalcode"
  },
  "geometry": {"coordinates":[-0.059342,52.986871],"type":"Point"}
}
