{
  "type": "Feature",
  "properties": {
    "iso:country":"GB",
    "wof:name":"PE21 8JU",
    "wof:placetype":"postalcode"
},
  "geometry": {"coordinates":[-0.05934252819011,52.98687068992845],"type":"Point"}
}