{
  "type": "Feature",
  "properties": {
    "iso:country":"GB",
    "wof:name":"LA14 5NJ",
    "wof:placetype":"postalcode"
},
  "geometry": {"coordinates":[-3.22146824225333,54.12469041500778],"type":"Point"}
}