{
  "type": "Feature",
  "properties": {
    "iso:country":"GB",
    "wof:name":"CV8 2GQ",
    "wof:placetype":"postalcode"
},
  "geometry": {"coordinates":[-1.57127030014491,52.35334273731663],"type":"Point"}
}