{
  "type": "Feature",
  "properties": {
    "iso:country":"GB",
    "wof:name":"LL13 7SP",
    "wof:placetype":"postalcode"
},
  "geometry": {"coordinates":[-2.99673241189876,53.04131567784172],"type":"Point"}
}