{
  "type": "Feature",
  "properties": {
    "date:inception_lower":"1993-08-01",
    "date:inception_upper":"1993-08-31",
    "iso:country":"GB",
    "wof:name":"LL13 7SP",
    "wof:placetype":"postalcode"
},
  "geometry": {"coordinates":[-2.996732,53.041316],"type":"Point"}
}