{
  "type": "Feature",
  "properties": {
    "iso:country": "GB",
    "wof:name": "LL13 7SP",
    "wof:placetype": "postalcode"
  },
  "geometry": {"coordinates":[-2.996732,53.041316],"type":"Point"}
}
