{
  "type": "Feature",
  "properties": {
    "date:inception_lower":"1980-01-01",
    "date:inception_upper":"1980-01-31",
    "iso:country":"GB",
    "wof:name":"TS28 5EH",
    "wof:placetype":"postalcode"
},
  "geometry": {"coordinates":[-1.36939,54.718485],"type":"Point"}
}