{
  "type": "Feature",
  "properties": {
    "iso:country": "GB",
    "wof:name": "TS28 5EH",
    "wof:placetype": "postalcode"
  },
  "geometry": {"coordinates":[-1.36939,54.718485],"type":"Point"}
}
