{
  "type": "Feature",
  "properties": {
    "iso:country": "GB",
    "wof:name": "YO43 3GR",
    "wof:placetype": "postalcode"
  },
  "geometry": {"coordinates":[-0.681941,53.863456],"type":"Point"}
}
