{
  "type": "Feature",
  "properties": {
    "iso:country": "GB",
    "wof:name": "WF13 1DZ",
    "wof:placetype": "postalcode"
  },
  "geometry": {"coordinates":[-1.630343,53.693403],"type":"Point"}
}
