{
  "type": "Feature",
  "properties": {
    "iso:country": "GB",
    "wof:name": "CW2 7LN",
    "wof:placetype": "postalcode"
  },
  "geometry": {"coordinates":[-2.44334,53.090475],"type":"Point"}
}
