{
  "type": "Feature",
  "properties": {
    "iso:country":"GB",
    "wof:name":"BD23 5DB",
    "wof:placetype":"postalcode"
},
  "geometry": {"coordinates":[-1.97600410749721,54.07010538971066],"type":"Point"}
}