{
  "type": "Feature",
  "properties": {
    "date:inception_lower":"1980-01-01",
    "date:inception_upper":"1980-01-31",
    "iso:country":"GB",
    "wof:name":"BD23 5DB",
    "wof:placetype":"postalcode"
},
  "geometry": {"coordinates":[-1.976004,54.070105],"type":"Point"}
}