{
  "type": "Feature",
  "properties": {
    "iso:country": "GB",
    "wof:name": "N7 0DP",
    "wof:placetype": "postalcode"
  },
  "geometry": {"coordinates":[-0.122414,51.558381],"type":"Point"}
}
