{
  "type": "Feature",
  "properties": {
    "iso:country":"GB",
    "wof:name":"N7 0DP",
    "wof:placetype":"postalcode"
},
  "geometry": {"coordinates":[-0.12241426317556,51.55838146615716],"type":"Point"}
}