{
  "type": "Feature",
  "properties": {
    "iso:country":"GB",
    "wof:name":"WR3 8AN",
    "wof:placetype":"postalcode"
},
  "geometry": {"coordinates":[-2.22468652238281,52.20738178337886],"type":"Point"}
}