{
  "type": "Feature",
  "properties": {
    "date:inception_lower":"1980-01-01",
    "date:inception_upper":"1980-01-31",
    "iso:country":"GB",
    "wof:name":"SG7 6JT",
    "wof:placetype":"postalcode"
},
  "geometry": {"coordinates":[-0.188081,51.981206],"type":"Point"}
}