{
  "type": "Feature",
  "properties": {
    "iso:country":"GB",
    "wof:name":"SG7 6JT",
    "wof:placetype":"postalcode"
},
  "geometry": {"coordinates":[-0.18811063968737,51.98112567505447],"type":"Point"}
}