{
  "type": "Feature",
  "properties": {
    "iso:country":"GB",
    "wof:name":"LE10 1SW",
    "wof:placetype":"postalcode"
},
  "geometry": {"coordinates":[-1.36487409199331,52.5566071616115],"type":"Point"}
}