{
  "type": "Feature",
  "properties": {
    "iso:country": "GB",
    "wof:name": "HU18 1AF",
    "wof:placetype": "postalcode"
  },
  "geometry": {"coordinates":[-0.171742,53.91027],"type":"Point"}
}
