{
  "type": "Feature",
  "properties": {
    "iso:country": "GB",
    "wof:name": "CV3 1PP",
    "wof:placetype": "postalcode"
  },
  "geometry": {"coordinates":[-1.484835,52.398992],"type":"Point"}
}
