{
  "type": "Feature",
  "properties": {
    "date:inception_lower": "2011-07-01",
    "date:inception_upper": "2011-07-01",
    "iso:country": "GB",
    "wof:name": "CV3 1PP",
    "wof:placetype": "postalcode"
  },
  "geometry": {"coordinates":[-1.484835,52.398992],"type":"Point"}
}
