{
  "type": "Feature",
  "properties": {
    "iso:country": "GB",
    "wof:name": "TS19 9LD",
    "wof:placetype": "postalcode"
  },
  "geometry": {"coordinates":[-1.343045,54.5888],"type":"Point"}
}
