{
  "type": "Feature",
  "properties": {
    "date:inception_lower":"1980-01-01",
    "date:inception_upper":"1980-01-31",
    "iso:country":"GB",
    "wof:name":"PA23 8SG",
    "wof:placetype":"postalcode"
},
  "geometry": {"coordinates":[-4.988468,56.083218],"type":"Point"}
}