{
  "type": "Feature",
  "properties": {
    "iso:country":"GB",
    "wof:name":"PA23 8SG",
    "wof:placetype":"postalcode"
},
  "geometry": {"coordinates":[-4.98918201962716,56.0770253859368],"type":"Point"}
}