{
  "type": "Feature",
  "properties": {
    "iso:country":"GB",
    "wof:name":"DG5 4HJ",
    "wof:placetype":"postalcode"
},
  "geometry": {"coordinates":[-3.81792604035917,54.93319050545595],"type":"Point"}
}