{
  "type": "Feature",
  "properties": {
    "iso:country":"GB",
    "wof:name":"G21 2QW",
    "wof:placetype":"postalcode"
},
  "geometry": {"coordinates":[-4.23083111047202,55.86955461976758],"type":"Point"}
}