{
  "type": "Feature",
  "properties": {
    "iso:country":"GB",
    "wof:name":"EN5 2PW",
    "wof:placetype":"postalcode"
},
  "geometry": {"coordinates":[-0.20747227840359,51.64270175817818],"type":"Point"}
}