{
  "type": "Feature",
  "properties": {
    "iso:country":"GB",
    "wof:name":"KW1 4RL",
    "wof:placetype":"postalcode"
},
  "geometry": {"coordinates":[-3.10074247522112,58.47376982131117],"type":"Point"}
}