{
  "type": "Feature",
  "properties": {
    "iso:country": "GB",
    "wof:name": "KW1 4RL",
    "wof:placetype": "postalcode"
  },
  "geometry": {"coordinates":[-3.100742,58.47377],"type":"Point"}
}
