{
  "type": "Feature",
  "properties": {
    "iso:country":"GB",
    "wof:name":"SW8 2SA",
    "wof:placetype":"postalcode"
},
  "geometry": {"coordinates":[-0.13384731589253,51.47039228030982],"type":"Point"}
}