{
  "type": "Feature",
  "properties": {
    "iso:country":"GB",
    "wof:name":"BS39 4EN",
    "wof:placetype":"postalcode"
},
  "geometry": {"coordinates":[-2.58006891657619,51.36667643728776],"type":"Point"}
}