{
  "type": "Feature",
  "properties": {
    "iso:country":"GB",
    "wof:name":"SM6 0PZ",
    "wof:placetype":"postalcode"
},
  "geometry": {"coordinates":[-0.14799271755736,51.3535234303837],"type":"Point"}
}