{
  "type": "Feature",
  "properties": {
    "iso:country":"GB",
    "wof:name":"BD9 5BA",
    "wof:placetype":"postalcode"
},
  "geometry": {"coordinates":[-1.78391077943427,53.8098622691619],"type":"Point"}
}