{
  "type": "Feature",
  "properties": {
    "iso:country":"GB",
    "wof:name":"SW18 5AF",
    "wof:placetype":"postalcode"
},
  "geometry": {"coordinates":[-0.19863013174921,51.44213482222391],"type":"Point"}
}