{
  "type": "Feature",
  "properties": {
    "iso:country": "GB",
    "wof:name": "BA2 5QL",
    "wof:placetype": "postalcode"
  },
  "geometry": {"coordinates":[-2.356707,51.359873],"type":"Point"}
}
