{
  "type": "Feature",
  "properties": {
    "iso:country":"GB",
    "wof:name":"BA2 5QL",
    "wof:placetype":"postalcode"
},
  "geometry": {"coordinates":[-2.35670721169016,51.35987291530418],"type":"Point"}
}