{
  "type": "Feature",
  "properties": {
    "iso:country":"GB",
    "wof:name":"TW7 5LF",
    "wof:placetype":"postalcode"
},
  "geometry": {"coordinates":[-0.33800377210543,51.47944370679307],"type":"Point"}
}