{
  "type": "Feature",
  "properties": {
    "iso:country":"GB",
    "wof:name":"RM8 1UH",
    "wof:placetype":"postalcode"
},
  "geometry": {"coordinates":[0.1256575418275,51.56347463715882],"type":"Point"}
}