{
  "type": "Feature",
  "properties": {
    "iso:country":"GB",
    "wof:name":"G15 6QQ",
    "wof:placetype":"postalcode"
},
  "geometry": {"coordinates":[-4.36384072324404,55.90405507789963],"type":"Point"}
}