{
  "type": "Feature",
  "properties": {
    "iso:country":"GB",
    "wof:name":"LA23 1AU",
    "wof:placetype":"postalcode"
},
  "geometry": {"coordinates":[-2.9134321545057,54.38248271064034],"type":"Point"}
}