{
  "type": "Feature",
  "properties": {
    "date:inception_lower":"1980-01-01",
    "date:inception_upper":"1980-01-31",
    "iso:country":"GB",
    "wof:name":"LA23 1AU",
    "wof:placetype":"postalcode"
},
  "geometry": {"coordinates":[-2.913432,54.382483],"type":"Point"}
}