{
  "type": "Feature",
  "properties": {
    "date:inception_lower": "2014-10-01",
    "date:inception_upper": "2014-10-01",
    "iso:country": "GB",
    "wof:name": "TQ4 7FN",
    "wof:placetype": "postalcode"
  },
  "geometry": {"coordinates":[-3.586785,50.41773],"type":"Point"}
}
