{
  "type": "Feature",
  "properties": {
    "iso:country":"GB",
    "wof:name":"B74 4DP",
    "wof:placetype":"postalcode"
},
  "geometry": {"coordinates":[-1.83993087992508,52.59879938094564],"type":"Point"}
}