{
  "type": "Feature",
  "properties": {
    "date:inception_lower":"1980-01-01",
    "date:inception_upper":"1980-01-31",
    "iso:country":"GB",
    "wof:name":"PO17 6EU",
    "wof:placetype":"postalcode"
},
  "geometry": {"coordinates":[-1.075075,50.884016],"type":"Point"}
}