{
  "type": "Feature",
  "properties": {
    "iso:country":"GB",
    "wof:name":"BD10 8RJ",
    "wof:placetype":"postalcode"
},
  "geometry": {"coordinates":[-1.73435074871649,53.83272706688875],"type":"Point"}
}