{
  "type": "Feature",
  "properties": {
    "iso:country":"GB",
    "wof:name":"SY21 7NU",
    "wof:placetype":"postalcode"
},
  "geometry": {"coordinates":[-3.13208965781127,52.66588320745389],"type":"Point"}
}