{
  "type": "Feature",
  "properties": {
    "iso:country": "GB",
    "wof:name": "SY21 7NU",
    "wof:placetype": "postalcode"
  },
  "geometry": {"coordinates":[-3.13209,52.665883],"type":"Point"}
}
