{
  "type": "Feature",
  "properties": {
    "date:inception_lower": "1994-12-01",
    "date:inception_upper": "1994-12-01",
    "iso:country": "GB",
    "wof:name": "SY21 7NU",
    "wof:placetype": "postalcode"
  },
  "geometry": {"coordinates":[-3.13209,52.665883],"type":"Point"}
}
