{
  "type": "Feature",
  "properties": {
    "iso:country":"GB",
    "wof:name":"CO10 8LW",
    "wof:placetype":"postalcode"
},
  "geometry": {"coordinates":[0.61088069266319,52.13066912016331],"type":"Point"}
}