{
  "type": "Feature",
  "properties": {
    "date:inception_lower": "1993-08-01",
    "date:inception_upper": "1993-08-01",
    "iso:country": "GB",
    "wof:name": "CO10 8LW",
    "wof:placetype": "postalcode"
  },
  "geometry": {"coordinates":[0.610881,52.130669],"type":"Point"}
}
