{
  "type": "Feature",
  "properties": {
    "date:inception_lower": "1978-08-01",
    "date:inception_upper": "1978-08-01",
    "iso:country": "GB",
    "wof:name": "G83 0NU",
    "wof:placetype": "postalcode"
  },
  "geometry": {"coordinates":[-4.581264,55.984789],"type":"Point"}
}
