{
  "type": "Feature",
  "properties": {
    "iso:country": "GB",
    "wof:name": "G83 0NU",
    "wof:placetype": "postalcode"
  },
  "geometry": {"coordinates":[-4.581264,55.984789],"type":"Point"}
}
