{
  "type": "Feature",
  "properties": {
    "iso:country": "GB",
    "wof:name": "TW5 0UU",
    "wof:placetype": "postalcode"
  },
  "geometry": {"coordinates":[-0.368843,51.48815],"type":"Point"}
}
