{
  "type": "Feature",
  "properties": {
    "iso:country":"GB",
    "wof:name":"TW5 0UU",
    "wof:placetype":"postalcode"
},
  "geometry": {"coordinates":[-0.36884254692914,51.48814963920221],"type":"Point"}
}