{
  "type": "Feature",
  "properties": {
    "iso:country":"GB",
    "wof:name":"TS23 2EH",
    "wof:placetype":"postalcode"
},
  "geometry": {"coordinates":[-1.29765449280139,54.61235125082231],"type":"Point"}
}