{
  "type": "Feature",
  "properties": {
    "iso:country":"GB",
    "wof:name":"GL14 1DE",
    "wof:placetype":"postalcode"
},
  "geometry": {"coordinates":[-2.452680468506,51.80600916520798],"type":"Point"}
}