{
  "type": "Feature",
  "properties": {
    "date:inception_lower":"2008-04-01",
    "date:inception_upper":"2008-04-30",
    "iso:country":"GB",
    "wof:name":"LL59 5EJ",
    "wof:placetype":"postalcode"
},
  "geometry": {"coordinates":[-4.171525,53.232174],"type":"Point"}
}