{
  "type": "Feature",
  "properties": {
    "iso:country": "GB",
    "wof:name": "LL59 5EJ",
    "wof:placetype": "postalcode"
  },
  "geometry": {"coordinates":[-4.171525,53.232174],"type":"Point"}
}
