{
  "type": "Feature",
  "properties": {
    "iso:country":"GB",
    "wof:name":"GU2 4EL",
    "wof:placetype":"postalcode"
},
  "geometry": {"coordinates":[-0.58030220167914,51.23118484066121],"type":"Point"}
}