{
  "type": "Feature",
  "properties": {
    "iso:country":"GB",
    "wof:name":"SN25 2LQ",
    "wof:placetype":"postalcode"
},
  "geometry": {"coordinates":[-1.82833824826506,51.60165923029621],"type":"Point"}
}