{
  "type": "Feature",
  "properties": {
    "iso:country": "GB",
    "wof:name": "E1 5DQ",
    "wof:placetype": "postalcode"
  },
  "geometry": {"coordinates":[-0.06073,51.523359],"type":"Point"}
}
