{
  "type": "Feature",
  "properties": {
    "iso:country":"GB",
    "wof:name":"E1 5DQ",
    "wof:placetype":"postalcode"
},
  "geometry": {"coordinates":[-0.06073051031261,51.52335927581331],"type":"Point"}
}