{
  "type": "Feature",
  "properties": {
    "date:inception_lower": "1980-01-01",
    "date:inception_upper": "1980-01-01",
    "iso:country": "GB",
    "wof:name": "RM6 5JB",
    "wof:placetype": "postalcode"
  },
  "geometry": {"coordinates":[0.130123,51.584931],"type":"Point"}
}
