{
  "type": "Feature",
  "properties": {
    "iso:country":"GB",
    "wof:name":"RM6 5JB",
    "wof:placetype":"postalcode"
},
  "geometry": {"coordinates":[0.13012338196493,51.58493129520068],"type":"Point"}
}