{
  "type": "Feature",
  "properties": {
    "iso:country":"GB",
    "wof:name":"GU6 7LB",
    "wof:placetype":"postalcode"
},
  "geometry": {"coordinates":[-0.47420083474518,51.13225269156285],"type":"Point"}
}