{
  "type": "Feature",
  "properties": {
    "date:inception_lower":"1980-01-01",
    "date:inception_upper":"1980-01-31",
    "iso:country":"GB",
    "wof:name":"GU6 7LB",
    "wof:placetype":"postalcode"
},
  "geometry": {"coordinates":[-0.474201,51.132253],"type":"Point"}
}