{
  "type": "Feature",
  "properties": {
    "iso:country":"GB",
    "wof:name":"RG45 6RT",
    "wof:placetype":"postalcode"
},
  "geometry": {"coordinates":[-0.7918602645101,51.37454830202318],"type":"Point"}
}