{
  "type": "Feature",
  "properties": {
    "iso:country":"GB",
    "wof:name":"CH41 4DR",
    "wof:placetype":"postalcode"
},
  "geometry": {"coordinates":[-3.03390167402827,53.38952955987588],"type":"Point"}
}