{
  "type": "Feature",
  "properties": {
    "date:inception_lower": "1999-06-01",
    "date:inception_upper": "1999-06-01",
    "iso:country": "GB",
    "wof:name": "CH41 4DR",
    "wof:placetype": "postalcode"
  },
  "geometry": {"coordinates":[-3.033902,53.38953],"type":"Point"}
}
