{
  "type": "Feature",
  "properties": {
    "iso:country": "GB",
    "wof:name": "CH41 4DR",
    "wof:placetype": "postalcode"
  },
  "geometry": {"coordinates":[-3.033902,53.38953],"type":"Point"}
}
