{
  "type": "Feature",
  "properties": {
    "iso:country": "GB",
    "wof:name": "LE16 9BF",
    "wof:placetype": "postalcode"
  },
  "geometry": {"coordinates":[-1.001793,52.43793],"type":"Point"}
}
