{
  "type": "Feature",
  "properties": {
    "date:inception_lower":"2009-06-01",
    "date:inception_upper":"2009-06-30",
    "iso:country":"GB",
    "wof:name":"LE16 9BF",
    "wof:placetype":"postalcode"
},
  "geometry": {"coordinates":[-1.001973,52.437769],"type":"Point"}
}