{
  "type": "Feature",
  "properties": {
    "iso:country":"GB",
    "wof:name":"LE16 9BF",
    "wof:placetype":"postalcode"
},
  "geometry": {"coordinates":[-1.00198642189768,52.43775282574247],"type":"Point"}
}