{
  "type": "Feature",
  "properties": {
    "iso:country":"GB",
    "wof:name":"GU34 5GH",
    "wof:placetype":"postalcode"
},
  "geometry": {"coordinates":[-1.05272635629623,51.10601434233107],"type":"Point"}
}