{
  "type": "Feature",
  "properties": {
    "iso:country": "GB",
    "wof:name": "GU34 5GH",
    "wof:placetype": "postalcode"
  },
  "geometry": {"coordinates":[-1.052726,51.106014],"type":"Point"}
}
