{
  "type": "Feature",
  "properties": {
    "date:inception_lower": "2015-01-01",
    "date:inception_upper": "2015-01-01",
    "iso:country": "GB",
    "wof:name": "GU34 5GH",
    "wof:placetype": "postalcode"
  },
  "geometry": {"coordinates":[-1.052726,51.106014],"type":"Point"}
}
