{
  "type": "Feature",
  "properties": {
    "iso:country": "GB",
    "wof:name": "GU12 4NS",
    "wof:placetype": "postalcode"
  },
  "geometry": {"coordinates":[-0.751137,51.246324],"type":"Point"}
}
