{
  "type": "Feature",
  "properties": {
    "iso:country":"GB",
    "wof:name":"GU12 4NS",
    "wof:placetype":"postalcode"
},
  "geometry": {"coordinates":[-0.75113690812572,51.24632394560275],"type":"Point"}
}