{
  "type": "Feature",
  "properties": {
    "iso:country":"GB",
    "wof:name":"CA28 6UE",
    "wof:placetype":"postalcode"
},
  "geometry": {"coordinates":[-3.56844707833752,54.53871967552625],"type":"Point"}
}