{
  "type": "Feature",
  "properties": {
    "iso:country":"GB",
    "wof:name":"IP30 9DS",
    "wof:placetype":"postalcode"
},
  "geometry": {"coordinates":[0.9089758365229,52.23139182107521],"type":"Point"}
}