{
  "type": "Feature",
  "properties": {
    "iso:country": "GB",
    "wof:name": "HP15 6SQ",
    "wof:placetype": "postalcode"
  },
  "geometry": {"coordinates":[-0.700472,51.661601],"type":"Point"}
}
