{
  "type": "Feature",
  "properties": {
    "iso:country":"GB",
    "wof:name":"WN6 0BY",
    "wof:placetype":"postalcode"
},
  "geometry": {"coordinates":[-2.6460352026866,53.57994996166116],"type":"Point"}
}