{
  "type": "Feature",
  "properties": {
    "date:inception_lower": "1996-06-01",
    "date:inception_upper": "1996-06-01",
    "iso:country": "GB",
    "wof:name": "W7 3PY",
    "wof:placetype": "postalcode"
  },
  "geometry": {"coordinates":[-0.333179,51.508466],"type":"Point"}
}
