{
  "type": "Feature",
  "properties": {
    "iso:country":"GB",
    "wof:name":"BH11 8PD",
    "wof:placetype":"postalcode"
},
  "geometry": {"coordinates":[-1.93071913060626,50.75925345032239],"type":"Point"}
}