{
  "type": "Feature",
  "properties": {
    "date:inception_lower": "2003-07-01",
    "date:inception_upper": "2003-07-01",
    "iso:country": "GB",
    "wof:name": "EX39 5UL",
    "wof:placetype": "postalcode"
  },
  "geometry": {"coordinates":[-4.376008,50.963749],"type":"Point"}
}
