{
  "type": "Feature",
  "properties": {
    "iso:country":"GB",
    "wof:name":"EX39 5UL",
    "wof:placetype":"postalcode"
},
  "geometry": {"coordinates":[-4.37600758501161,50.96374913935637],"type":"Point"}
}