{
  "type": "Feature",
  "properties": {
    "iso:country": "GB",
    "wof:name": "EX39 5UL",
    "wof:placetype": "postalcode"
  },
  "geometry": {"coordinates":[-4.376008,50.963749],"type":"Point"}
}
