{
  "type": "Feature",
  "properties": {
    "iso:country":"GB",
    "wof:name":"OL13 9BN",
    "wof:placetype":"postalcode"
},
  "geometry": {"coordinates":[-2.19847876899371,53.70453407307459],"type":"Point"}
}