{
  "type": "Feature",
  "properties": {
    "iso:country":"GB",
    "wof:name":"HP22 5RY",
    "wof:placetype":"postalcode"
},
  "geometry": {"coordinates":[-0.75665133058618,51.78899057105467],"type":"Point"}
}