{
  "type": "Feature",
  "properties": {
    "iso:country":"GB",
    "wof:name":"LD3 9RT",
    "wof:placetype":"postalcode"
},
  "geometry": {"coordinates":[-3.4744199483653,52.00407114526327],"type":"Point"}
}