{
  "type": "Feature",
  "properties": {
    "iso:country":"GB",
    "wof:name":"NG11 8HZ",
    "wof:placetype":"postalcode"
},
  "geometry": {"coordinates":[-1.17067384020468,52.90639626664803],"type":"Point"}
}