{
  "type": "Feature",
  "properties": {
    "iso:country":"GB",
    "wof:name":"CM8 3NH",
    "wof:placetype":"postalcode"
},
  "geometry": {"coordinates":[0.6744037455027,51.77986239840465],"type":"Point"}
}