{
  "type": "Feature",
  "properties": {
    "iso:country": "GB",
    "wof:name": "CM8 3NH",
    "wof:placetype": "postalcode"
  },
  "geometry": {"coordinates":[0.674404,51.779862],"type":"Point"}
}
