{
  "type": "Feature",
  "properties": {
    "iso:country":"GB",
    "wof:name":"YO60 7JT",
    "wof:placetype":"postalcode"
},
  "geometry": {"coordinates":[-0.88793633043299,54.08563349319856],"type":"Point"}
}