{
  "type": "Feature",
  "properties": {
    "date:inception_lower": "1980-01-01",
    "date:inception_upper": "1980-01-01",
    "iso:country": "GB",
    "wof:name": "KY2 6HA",
    "wof:placetype": "postalcode"
  },
  "geometry": {"coordinates":[-3.189444,56.125042],"type":"Point"}
}
