{
  "type": "Feature",
  "properties": {
    "iso:country":"GB",
    "wof:name":"MK42 7HB",
    "wof:placetype":"postalcode"
},
  "geometry": {"coordinates":[-0.50222921623172,52.11069935264028],"type":"Point"}
}