{
  "type": "Feature",
  "properties": {
    "iso:country":"GB",
    "wof:name":"SY2 5DS",
    "wof:placetype":"postalcode"
},
  "geometry": {"coordinates":[-2.73748520456499,52.7116442240828],"type":"Point"}
}