{
  "type": "Feature",
  "properties": {
    "iso:country": "GB",
    "wof:name": "SY2 5DS",
    "wof:placetype": "postalcode"
  },
  "geometry": {"coordinates":[-2.737485,52.711644],"type":"Point"}
}
