{
  "type": "Feature",
  "properties": {
    "iso:country":"GB",
    "wof:name":"DN17 1QQ",
    "wof:placetype":"postalcode"
},
  "geometry": {"coordinates":[-0.67739258935411,53.57342558266124],"type":"Point"}
}