{
  "type": "Feature",
  "properties": {
    "iso:country": "GB",
    "wof:name": "PE9 4HY",
    "wof:placetype": "postalcode"
  },
  "geometry": {"coordinates":[-0.471172,52.683012],"type":"Point"}
}
