{
  "type": "Feature",
  "properties": {
    "iso:country":"GB",
    "wof:name":"PE9 4HY",
    "wof:placetype":"postalcode"
},
  "geometry": {"coordinates":[-0.47117184449554,52.68301207305596],"type":"Point"}
}