{
  "type": "Feature",
  "properties": {
    "date:inception_lower": "1997-12-01",
    "date:inception_upper": "1997-12-01",
    "iso:country": "GB",
    "wof:name": "BS25 5NU",
    "wof:placetype": "postalcode"
  },
  "geometry": {"coordinates":[-2.793467,51.332197],"type":"Point"}
}
