{
  "type": "Feature",
  "properties": {
    "iso:country":"GB",
    "wof:name":"S70 4NF",
    "wof:placetype":"postalcode"
},
  "geometry": {"coordinates":[-1.47793576334877,53.54561073294146],"type":"Point"}
}