{
  "type": "Feature",
  "properties": {
    "iso:country":"GB",
    "wof:name":"PL19 8EZ",
    "wof:placetype":"postalcode"
},
  "geometry": {"coordinates":[-4.16196214086308,50.54289427757437],"type":"Point"}
}