{
  "type": "Feature",
  "properties": {
    "iso:country":"GB",
    "wof:name":"DT4 0LJ",
    "wof:placetype":"postalcode"
},
  "geometry": {"coordinates":[-2.47286625600899,50.61120121757374],"type":"Point"}
}