{
  "type": "Feature",
  "properties": {
    "date:inception_lower": "1980-01-01",
    "date:inception_upper": "1980-01-01",
    "iso:country": "GB",
    "wof:name": "DT4 0LJ",
    "wof:placetype": "postalcode"
  },
  "geometry": {"coordinates":[-2.472866,50.611201],"type":"Point"}
}
