{
  "type": "Feature",
  "properties": {
    "date:inception_lower": "2006-01-01",
    "date:inception_upper": "2006-01-01",
    "iso:country": "GB",
    "wof:name": "RG27 0SH",
    "wof:placetype": "postalcode"
  },
  "geometry": {"coordinates":[-1.046351,51.301776],"type":"Point"}
}
