{
  "type": "Feature",
  "properties": {
    "iso:country": "GB",
    "wof:name": "B44 8DE",
    "wof:placetype": "postalcode"
  },
  "geometry": {"coordinates":[-1.885323,52.533487],"type":"Point"}
}
