{
  "type": "Feature",
  "properties": {
    "iso:country":"GB",
    "wof:name":"GL1 5DL",
    "wof:placetype":"postalcode"
},
  "geometry": {"coordinates":[-2.24416898843688,51.85271515030698],"type":"Point"}
}