{
  "type": "Feature",
  "properties": {
    "iso:country":"GB",
    "wof:name":"BS24 0HW",
    "wof:placetype":"postalcode"
},
  "geometry": {"coordinates":[-2.94170874746175,51.28529639873004],"type":"Point"}
}