{
  "type": "Feature",
  "properties": {
    "date:inception_lower": "1980-01-01",
    "date:inception_upper": "1980-01-01",
    "iso:country": "GB",
    "wof:name": "BS24 0HW",
    "wof:placetype": "postalcode"
  },
  "geometry": {"coordinates":[-2.941731,51.285328],"type":"Point"}
}
