{
  "type": "Feature",
  "properties": {
    "iso:country":"GB",
    "wof:name":"BS4 1TT",
    "wof:placetype":"postalcode"
},
  "geometry": {"coordinates":[-2.5980225695722,51.42162455034153],"type":"Point"}
}