{
  "type": "Feature",
  "properties": {
    "date:inception_lower": "2002-07-01",
    "date:inception_upper": "2002-07-01",
    "iso:country": "GB",
    "wof:name": "BS4 1TT",
    "wof:placetype": "postalcode"
  },
  "geometry": {"coordinates":[-2.598023,51.421625],"type":"Point"}
}
