{
  "type": "Feature",
  "properties": {
    "iso:country":"GB",
    "wof:name":"SL1 1TA",
    "wof:placetype":"postalcode"
},
  "geometry": {"coordinates":[-0.57733034768843,51.50863231979812],"type":"Point"}
}