{
  "type": "Feature",
  "properties": {
    "iso:country": "GB",
    "wof:name": "MK11 4BX",
    "wof:placetype": "postalcode"
  },
  "geometry": {"coordinates":[-0.839843,52.045662],"type":"Point"}
}
