{
  "type": "Feature",
  "properties": {
    "iso:country":"GB",
    "wof:name":"SW1P 1ET",
    "wof:placetype":"postalcode"
},
  "geometry": {"coordinates":[-0.13976994325953,51.49469434152829],"type":"Point"}
}