{
  "type": "Feature",
  "properties": {
    "iso:country":"GB",
    "wof:name":"CA8 7DP",
    "wof:placetype":"postalcode"
},
  "geometry": {"coordinates":[-2.56927082075098,54.99142797369645],"type":"Point"}
}