{
  "type": "Feature",
  "properties": {
    "date:inception_lower": "2014-08-01",
    "date:inception_upper": "2014-08-01",
    "iso:country": "GB",
    "wof:name": "LU5 6FQ",
    "wof:placetype": "postalcode"
  },
  "geometry": {"coordinates":[-0.492679,51.961681],"type":"Point"}
}
