{
  "type": "Feature",
  "properties": {
    "iso:country": "GB",
    "wof:name": "LU5 6FQ",
    "wof:placetype": "postalcode"
  },
  "geometry": {"coordinates":[-0.492689,51.961698],"type":"Point"}
}
