{
  "type": "Feature",
  "properties": {
    "date:inception_lower": "2017-02-01",
    "date:inception_upper": "2017-02-01",
    "iso:country": "GB",
    "wof:name": "CV37 8QX",
    "wof:placetype": "postalcode"
  },
  "geometry": {"coordinates":[-1.662593,52.13355],"type":"Point"}
}
