{
  "type": "Feature",
  "properties": {
    "iso:country": "GB",
    "wof:name": "CV37 8QX",
    "wof:placetype": "postalcode"
  },
  "geometry": {"coordinates":[-1.662593,52.13355],"type":"Point"}
}
