{
  "type": "Feature",
  "properties": {
    "date:inception_lower":"2000-12-01",
    "date:inception_upper":"2000-12-31",
    "iso:country":"GB",
    "wof:name":"L9 1NR",
    "wof:placetype":"postalcode"
},
  "geometry": {"coordinates":[-2.967543,53.449781],"type":"Point"}
}