{
  "type": "Feature",
  "properties": {
    "iso:country":"GB",
    "wof:name":"EH8 8HN",
    "wof:placetype":"postalcode"
},
  "geometry": {"coordinates":[-3.16264290777229,55.95530412510318],"type":"Point"}
}