{
  "type": "Feature",
  "properties": {
    "iso:country":"GB",
    "wof:name":"TN12 8DX",
    "wof:placetype":"postalcode"
},
  "geometry": {"coordinates":[0.40911913822327,51.12972800385477],"type":"Point"}
}