{
  "type": "Feature",
  "properties": {
    "date:inception_lower": "1980-01-01",
    "date:inception_upper": "1980-01-01",
    "iso:country": "GB",
    "wof:name": "DE7 6DL",
    "wof:placetype": "postalcode"
  },
  "geometry": {"coordinates":[-1.426849,52.968011],"type":"Point"}
}
