{
  "type": "Feature",
  "properties": {
    "iso:country":"GB",
    "wof:name":"WN4 9UR",
    "wof:placetype":"postalcode"
},
  "geometry": {"coordinates":[-2.64966072225056,53.49525848365231],"type":"Point"}
}