{
  "type": "Feature",
  "properties": {
    "iso:country": "GB",
    "wof:name": "BS4 2DR",
    "wof:placetype": "postalcode"
  },
  "geometry": {"coordinates":[-2.574028,51.43721],"type":"Point"}
}
