{
  "type": "Feature",
  "properties": {
    "iso:country":"GB",
    "wof:name":"WD6 5DY",
    "wof:placetype":"postalcode"
},
  "geometry": {"coordinates":[-0.27579671625386,51.66693367715106],"type":"Point"}
}