{
  "type": "Feature",
  "properties": {
    "iso:country": "GB",
    "wof:name": "WD6 5DY",
    "wof:placetype": "postalcode"
  },
  "geometry": {"coordinates":[-0.275797,51.666934],"type":"Point"}
}
