{
  "type": "Feature",
  "properties": {
    "iso:country":"GB",
    "wof:name":"AL3 8AX",
    "wof:placetype":"postalcode"
},
  "geometry": {"coordinates":[-0.46708846719532,51.81344652187263],"type":"Point"}
}