{
  "type": "Feature",
  "properties": {
    "iso:country":"GB",
    "wof:name":"TR11 5FN",
    "wof:placetype":"postalcode"
},
  "geometry": {"coordinates":[-5.073723117026,50.16748360846758],"type":"Point"}
}