{
  "type": "Feature",
  "properties": {
    "date:inception_lower": "2011-03-01",
    "date:inception_upper": "2011-03-01",
    "iso:country": "GB",
    "wof:name": "TR11 5FN",
    "wof:placetype": "postalcode"
  },
  "geometry": {"coordinates":[-5.073723,50.167484],"type":"Point"}
}
