{
  "type": "Feature",
  "properties": {
    "date:inception_lower": "2018-06-01",
    "date:inception_upper": "2018-06-01",
    "iso:country": "GB",
    "wof:name": "NE6 2TY",
    "wof:placetype": "postalcode"
  },
  "geometry": {"coordinates":[-1.576009,54.978856],"type":"Point"}
}
