{
  "type": "Feature",
  "properties": {
    "iso:country": "GB",
    "wof:name": "CH46 3RL",
    "wof:placetype": "postalcode"
  },
  "geometry": {"coordinates":[-3.104661,53.418389],"type":"Point"}
}
