{
  "type": "Feature",
  "properties": {
    "date:inception_lower":"1999-06-01",
    "date:inception_upper":"1999-06-30",
    "iso:country":"GB",
    "wof:name":"CH46 3RL",
    "wof:placetype":"postalcode"
},
  "geometry": {"coordinates":[-3.104661,53.418389],"type":"Point"}
}