{
  "type": "Feature",
  "properties": {
    "iso:country":"GB",
    "wof:name":"CH46 3RL",
    "wof:placetype":"postalcode"
},
  "geometry": {"coordinates":[-3.10466061249867,53.41838867635285],"type":"Point"}
}