{
  "type": "Feature",
  "properties": {
    "iso:country":"GB",
    "wof:name":"WN1 2RL",
    "wof:placetype":"postalcode"
},
  "geometry": {"coordinates":[-2.63873680161119,53.56671321109074],"type":"Point"}
}