{
  "type": "Feature",
  "properties": {
    "date:inception_lower": "2018-06-01",
    "date:inception_upper": "2018-06-01",
    "iso:country": "GB",
    "wof:name": "G41 3DD",
    "wof:placetype": "postalcode"
  },
  "geometry": {"coordinates":[-4.272974,55.826717],"type":"Point"}
}
