{
  "type": "Feature",
  "properties": {
    "iso:country": "GB",
    "wof:name": "G41 3DD",
    "wof:placetype": "postalcode"
  },
  "geometry": {"coordinates":[-4.273174,55.826578],"type":"Point"}
}
