{
  "type": "Feature",
  "properties": {
    "iso:country":"GB",
    "wof:name":"L34 6HT",
    "wof:placetype":"postalcode"
},
  "geometry": {"coordinates":[-2.80019025254168,53.43214330583738],"type":"Point"}
}