{
  "type": "Feature",
  "properties": {
    "iso:country":"GB",
    "wof:name":"WS1 1QR",
    "wof:placetype":"postalcode"
},
  "geometry": {"coordinates":[-1.97969313836106,52.5831104263406],"type":"Point"}
}