{
  "type": "Feature",
  "properties": {
    "date:inception_lower": "1980-01-01",
    "date:inception_upper": "1980-01-01",
    "iso:country": "GB",
    "wof:name": "WS1 1QR",
    "wof:placetype": "postalcode"
  },
  "geometry": {"coordinates":[-1.979693,52.58311],"type":"Point"}
}
