{
  "type": "Feature",
  "properties": {
    "iso:country":"GB",
    "wof:name":"ML2 8LB",
    "wof:placetype":"postalcode"
},
  "geometry": {"coordinates":[-3.90735825577574,55.77533103232642],"type":"Point"}
}