{
  "type": "Feature",
  "properties": {
    "date:inception_lower": "1980-01-01",
    "date:inception_upper": "1980-01-01",
    "iso:country": "GB",
    "wof:name": "B97 5ES",
    "wof:placetype": "postalcode"
  },
  "geometry": {"coordinates":[-1.94606,52.291446],"type":"Point"}
}
