{
  "type": "Feature",
  "properties": {
    "iso:country":"GB",
    "wof:name":"PH3 1LX",
    "wof:placetype":"postalcode"
},
  "geometry": {"coordinates":[-3.72527292096407,56.29134752172022],"type":"Point"}
}