{
  "type": "Feature",
  "properties": {
    "iso:country":"GB",
    "wof:name":"CF31 2AN",
    "wof:placetype":"postalcode"
},
  "geometry": {"coordinates":[-3.55254003076603,51.51679777572445],"type":"Point"}
}