{
  "type": "Feature",
  "properties": {
    "iso:country": "GB",
    "wof:name": "CF31 2AN",
    "wof:placetype": "postalcode"
  },
  "geometry": {"coordinates":[-3.55619,51.517317],"type":"Point"}
}
