{
  "type": "Feature",
  "properties": {
    "iso:country":"GB",
    "wof:name":"DA1 3LF",
    "wof:placetype":"postalcode"
},
  "geometry": {"coordinates":[0.18775129454926,51.44150413969325],"type":"Point"}
}