{
  "type": "Feature",
  "properties": {
    "iso:country":"GB",
    "wof:name":"LL20 8SE",
    "wof:placetype":"postalcode"
},
  "geometry": {"coordinates":[-3.16602210443721,52.97000752281404],"type":"Point"}
}