{
  "type": "Feature",
  "properties": {
    "date:inception_lower":"1990-07-01",
    "date:inception_upper":"1990-07-31",
    "iso:country":"GB",
    "wof:name":"WA5 2SJ",
    "wof:placetype":"postalcode"
},
  "geometry": {"coordinates":[-2.641288,53.382901],"type":"Point"}
}