{
  "type": "Feature",
  "properties": {
    "iso:country":"GB",
    "wof:name":"WA8 7UN",
    "wof:placetype":"postalcode"
},
  "geometry": {"coordinates":[-2.76470734685793,53.37140488658456],"type":"Point"}
}