{
  "type": "Feature",
  "properties": {
    "iso:country":"GB",
    "wof:name":"TW7 6LD",
    "wof:placetype":"postalcode"
},
  "geometry": {"coordinates":[-0.34289840763596,51.46796680650905],"type":"Point"}
}