{
  "type": "Feature",
  "properties": {
    "iso:country": "GB",
    "wof:name": "TQ2 6SS",
    "wof:placetype": "postalcode"
  },
  "geometry": {"coordinates":[-3.553283,50.45697],"type":"Point"}
}
