{
  "type": "Feature",
  "properties": {
    "iso:country": "GB",
    "wof:name": "EH11 3LH",
    "wof:placetype": "postalcode"
  },
  "geometry": {"coordinates":[-3.260828,55.929853],"type":"Point"}
}
