{
  "type": "Feature",
  "properties": {
    "iso:country":"GB",
    "wof:name":"YO8 6NN",
    "wof:placetype":"postalcode"
},
  "geometry": {"coordinates":[-0.99646000860961,53.78091763823679],"type":"Point"}
}