{
  "type": "Feature",
  "properties": {
    "iso:country": "GB",
    "wof:name": "YO8 6NN",
    "wof:placetype": "postalcode"
  },
  "geometry": {"coordinates":[-0.99646,53.780918],"type":"Point"}
}
