{
  "type": "Feature",
  "properties": {
    "iso:country": "GB",
    "wof:name": "DN14 5TG",
    "wof:placetype": "postalcode"
  },
  "geometry": {"coordinates":[-0.870043,53.697325],"type":"Point"}
}
