{
  "type": "Feature",
  "properties": {
    "date:inception_lower": "2021-04-01",
    "date:inception_upper": "2021-04-01",
    "iso:country": "GB",
    "wof:name": "EC2V 7EE",
    "wof:placetype": "postalcode"
  },
  "geometry": {"coordinates":[-0.095338,51.516959],"type":"Point"}
}
