{
  "type": "Feature",
  "properties": {
    "iso:country":"GB",
    "wof:name":"AL5 2RQ",
    "wof:placetype":"postalcode"
},
  "geometry": {"coordinates":[-0.37130649863382,51.81762600958708],"type":"Point"}
}