{
  "type": "Feature",
  "properties": {
    "iso:country":"GB",
    "wof:name":"EN1 4BN",
    "wof:placetype":"postalcode"
},
  "geometry": {"coordinates":[-0.06036510479891,51.66107325509086],"type":"Point"}
}