{
  "type": "Feature",
  "properties": {
    "iso:country":"GB",
    "wof:name":"LE9 6RD",
    "wof:placetype":"postalcode"
},
  "geometry": {"coordinates":[-1.22975096413145,52.53375286073879],"type":"Point"}
}