{
  "type": "Feature",
  "properties": {
    "iso:country":"GB",
    "wof:name":"EH42 1BD",
    "wof:placetype":"postalcode"
},
  "geometry": {"coordinates":[-2.52849104472456,56.00253193369461],"type":"Point"}
}