{
  "type": "Feature",
  "properties": {
    "iso:country": "GB",
    "wof:name": "PO14 9SY",
    "wof:placetype": "postalcode"
  },
  "geometry": {"coordinates":[-1.187451,50.843135],"type":"Point"}
}
