{
  "type": "Feature",
  "properties": {
    "iso:country": "GB",
    "wof:name": "SP7 8BP",
    "wof:placetype": "postalcode"
  },
  "geometry": {"coordinates":[-2.197178,51.007498],"type":"Point"}
}
