{
  "type": "Feature",
  "properties": {
    "iso:country":"GB",
    "wof:name":"SP7 8BP",
    "wof:placetype":"postalcode"
},
  "geometry": {"coordinates":[-2.19749732008557,51.0076389486163],"type":"Point"}
}