{
  "type": "Feature",
  "properties": {
    "iso:country":"GB",
    "wof:name":"SE27 0SE",
    "wof:placetype":"postalcode"
},
  "geometry": {"coordinates":[-0.11271328922026,51.42669154346254],"type":"Point"}
}