{
  "type": "Feature",
  "properties": {
    "date:inception_lower": "1980-01-01",
    "date:inception_upper": "1980-01-01",
    "iso:country": "GB",
    "wof:name": "SP7 0NL",
    "wof:placetype": "postalcode"
  },
  "geometry": {"coordinates":[-2.189113,50.964679],"type":"Point"}
}
