{
  "type": "Feature",
  "properties": {
    "iso:country": "GB",
    "wof:name": "GL10 3DJ",
    "wof:placetype": "postalcode"
  },
  "geometry": {"coordinates":[-2.278471,51.767751],"type":"Point"}
}
