{
  "type": "Feature",
  "properties": {
    "iso:country":"GB",
    "wof:name":"GL10 3DJ",
    "wof:placetype":"postalcode"
},
  "geometry": {"coordinates":[-2.27649402448536,51.76619497286991],"type":"Point"}
}