{
  "type": "Feature",
  "properties": {
    "iso:country": "GB",
    "wof:name": "IP3 0HS",
    "wof:placetype": "postalcode"
  },
  "geometry": {"coordinates":[1.170534,52.035905],"type":"Point"}
}
