{
  "type": "Feature",
  "properties": {
    "date:inception_lower": "1980-01-01",
    "date:inception_upper": "1980-01-01",
    "iso:country": "GB",
    "wof:name": "G41 5DS",
    "wof:placetype": "postalcode"
  },
  "geometry": {"coordinates":[-4.28255,55.845211],"type":"Point"}
}
