{
  "type": "Feature",
  "properties": {
    "iso:country":"GB",
    "wof:name":"N16 5XE",
    "wof:placetype":"postalcode"
},
  "geometry": {"coordinates":[-0.07554690400688,51.56785558309868],"type":"Point"}
}