{
  "type": "Feature",
  "properties": {
    "iso:country":"GB",
    "wof:name":"GU1 1XP",
    "wof:placetype":"postalcode"
},
  "geometry": {"coordinates":[-0.54964746119103,51.25407255014884],"type":"Point"}
}