{
  "type": "Feature",
  "properties": {
    "date:inception_lower": "1985-10-01",
    "date:inception_upper": "1985-10-01",
    "iso:country": "GB",
    "wof:name": "GU1 1XP",
    "wof:placetype": "postalcode"
  },
  "geometry": {"coordinates":[-0.549647,51.254073],"type":"Point"}
}
