{
  "type": "Feature",
  "properties": {
    "iso:country":"GB",
    "wof:name":"NW1 8AF",
    "wof:placetype":"postalcode"
},
  "geometry": {"coordinates":[-0.1466609715833,51.54108781091239],"type":"Point"}
}