{
  "type": "Feature",
  "properties": {
    "iso:country": "GB",
    "wof:name": "NW1 8AF",
    "wof:placetype": "postalcode"
  },
  "geometry": {"coordinates":[-0.146651,51.54133],"type":"Point"}
}
