{
  "type": "Feature",
  "properties": {
    "iso:country": "GB",
    "wof:name": "GL5 4AT",
    "wof:placetype": "postalcode"
  },
  "geometry": {"coordinates":[-2.238362,51.749201],"type":"Point"}
}
