{
  "type": "Feature",
  "properties": {
    "iso:country":"GB",
    "wof:name":"GL5 4AT",
    "wof:placetype":"postalcode"
},
  "geometry": {"coordinates":[-2.23836615204156,51.74919548928349],"type":"Point"}
}