{
  "type": "Feature",
  "properties": {
    "iso:country":"GB",
    "wof:name":"EH10 5HZ",
    "wof:placetype":"postalcode"
},
  "geometry": {"coordinates":[-3.21043076557284,55.92487722820808],"type":"Point"}
}