{
  "type": "Feature",
  "properties": {
    "iso:country":"GB",
    "wof:name":"G82 4EQ",
    "wof:placetype":"postalcode"
},
  "geometry": {"coordinates":[-4.58717471250019,55.94581607260294],"type":"Point"}
}