{
  "type": "Feature",
  "properties": {
    "iso:country": "GB",
    "wof:name": "TS1 5PW",
    "wof:placetype": "postalcode"
  },
  "geometry": {"coordinates":[-1.249611,54.57013],"type":"Point"}
}
