{
  "type": "Feature",
  "properties": {
    "date:inception_lower": "1999-06-01",
    "date:inception_upper": "1999-06-01",
    "iso:country": "GB",
    "wof:name": "TS1 5PW",
    "wof:placetype": "postalcode"
  },
  "geometry": {"coordinates":[-1.249611,54.57013],"type":"Point"}
}
