{
  "type": "Feature",
  "properties": {
    "iso:country":"GB",
    "wof:name":"TS1 5PW",
    "wof:placetype":"postalcode"
},
  "geometry": {"coordinates":[-1.24961060491093,54.57012971588664],"type":"Point"}
}