{
  "type": "Feature",
  "properties": {
    "date:inception_lower":"1995-12-01",
    "date:inception_upper":"1995-12-31",
    "iso:country":"GB",
    "wof:name":"GL4 5YH",
    "wof:placetype":"postalcode"
},
  "geometry": {"coordinates":[-2.190467,51.846413],"type":"Point"}
}