{
  "type": "Feature",
  "properties": {
    "iso:country": "GB",
    "wof:name": "GL4 5YH",
    "wof:placetype": "postalcode"
  },
  "geometry": {"coordinates":[-2.190467,51.846413],"type":"Point"}
}
