{
  "type": "Feature",
  "properties": {
    "iso:country": "GB",
    "wof:name": "BS14 0FQ",
    "wof:placetype": "postalcode"
  },
  "geometry": {"coordinates":[-2.550479,51.405059],"type":"Point"}
}
