{
  "type": "Feature",
  "properties": {
    "iso:country": "GB",
    "wof:name": "RH6 9JP",
    "wof:placetype": "postalcode"
  },
  "geometry": {"coordinates":[-0.097766,51.17376],"type":"Point"}
}
