{
  "type": "Feature",
  "properties": {
    "date:inception_lower": "1980-01-01",
    "date:inception_upper": "1980-01-01",
    "iso:country": "GB",
    "wof:name": "RH6 9JP",
    "wof:placetype": "postalcode"
  },
  "geometry": {"coordinates":[-0.097766,51.17376],"type":"Point"}
}
