{
  "type": "Feature",
  "properties": {
    "iso:country":"GB",
    "wof:name":"RH6 9JP",
    "wof:placetype":"postalcode"
},
  "geometry": {"coordinates":[-0.097766260534,51.17375983190325],"type":"Point"}
}