{
  "type": "Feature",
  "properties": {
    "date:inception_lower": "1980-01-01",
    "date:inception_upper": "1980-01-01",
    "iso:country": "GB",
    "wof:name": "S8 0EG",
    "wof:placetype": "postalcode"
  },
  "geometry": {"coordinates":[-1.49923,53.339306],"type":"Point"}
}
