{
  "type": "Feature",
  "properties": {
    "iso:country":"GB",
    "wof:name":"S8 0EG",
    "wof:placetype":"postalcode"
},
  "geometry": {"coordinates":[-1.49924579068811,53.33929677604482],"type":"Point"}
}