{
  "type": "Feature",
  "properties": {
    "iso:country":"GB",
    "wof:name":"B13 9SD",
    "wof:placetype":"postalcode"
},
  "geometry": {"coordinates":[-1.88179715141588,52.4407520508458],"type":"Point"}
}