{
  "type": "Feature",
  "properties": {
    "date:inception_lower":"2002-11-01",
    "date:inception_upper":"2002-11-30",
    "iso:country":"GB",
    "wof:name":"BS22 7RA",
    "wof:placetype":"postalcode"
},
  "geometry": {"coordinates":[-2.903198,51.365644],"type":"Point"}
}