{
  "type": "Feature",
  "properties": {
    "iso:country":"GB",
    "wof:name":"BS22 7RA",
    "wof:placetype":"postalcode"
},
  "geometry": {"coordinates":[-2.90302106995482,51.3656388346777],"type":"Point"}
}