{
  "type": "Feature",
  "properties": {
    "iso:country":"GB",
    "wof:name":"TQ1 1NN",
    "wof:placetype":"postalcode"
},
  "geometry": {"coordinates":[-3.52611044676089,50.46931806184072],"type":"Point"}
}