{
  "type": "Feature",
  "properties": {
    "iso:country":"GB",
    "wof:name":"TS13 4PS",
    "wof:placetype":"postalcode"
},
  "geometry": {"coordinates":[-0.8907277105763,54.555698290352],"type":"Point"}
}