{
  "type": "Feature",
  "properties": {
    "date:inception_lower":"2016-11-01",
    "date:inception_upper":"2016-11-30",
    "iso:country":"GB",
    "wof:name":"ST18 0QR",
    "wof:placetype":"postalcode"
},
  "geometry": {"coordinates":[-2.004287,52.830874],"type":"Point"}
}