{
  "type": "Feature",
  "properties": {
    "date:inception_lower": "2015-07-01",
    "date:inception_upper": "2015-07-01",
    "iso:country": "GB",
    "wof:name": "SN15 2FF",
    "wof:placetype": "postalcode"
  },
  "geometry": {"coordinates":[-2.13003,51.451303],"type":"Point"}
}
