{
  "type": "Feature",
  "properties": {
    "iso:country": "GB",
    "wof:name": "SN15 2FF",
    "wof:placetype": "postalcode"
  },
  "geometry": {"coordinates":[-2.13003,51.451303],"type":"Point"}
}
