{
  "type": "Feature",
  "properties": {
    "iso:country": "GB",
    "wof:name": "NG31 9AZ",
    "wof:placetype": "postalcode"
  },
  "geometry": {"coordinates":[-0.632687,52.91667],"type":"Point"}
}
