{
  "type": "Feature",
  "properties": {
    "iso:country":"GB",
    "wof:name":"SN15 3TF",
    "wof:placetype":"postalcode"
},
  "geometry": {"coordinates":[-2.09690931164865,51.44787381462799],"type":"Point"}
}