{
  "type": "Feature",
  "properties": {
    "iso:country":"GB",
    "wof:name":"NE15 8LN",
    "wof:placetype":"postalcode"
},
  "geometry": {"coordinates":[-1.73753201574134,54.98138052792635],"type":"Point"}
}