{
  "type": "Feature",
  "properties": {
    "iso:country":"GB",
    "wof:name":"GL6 8GB",
    "wof:placetype":"postalcode"
},
  "geometry": {"coordinates":[-2.15434241713493,51.73384437508899],"type":"Point"}
}