{
  "type": "Feature",
  "properties": {
    "date:inception_lower":"2013-02-01",
    "date:inception_upper":"2013-02-28",
    "iso:country":"GB",
    "wof:name":"GL6 8GB",
    "wof:placetype":"postalcode"
},
  "geometry": {"coordinates":[-2.154342,51.733844],"type":"Point"}
}