{
  "type": "Feature",
  "properties": {
    "date:inception_lower":"1980-01-01",
    "date:inception_upper":"1980-01-31",
    "iso:country":"GB",
    "wof:name":"PR7 1HU",
    "wof:placetype":"postalcode"
},
  "geometry": {"coordinates":[-2.635891,53.653709],"type":"Point"}
}