{
  "type": "Feature",
  "properties": {
    "iso:country":"GB",
    "wof:name":"PR7 1HU",
    "wof:placetype":"postalcode"
},
  "geometry": {"coordinates":[-2.6358907753559,53.65370914839085],"type":"Point"}
}