{
  "type": "Feature",
  "properties": {
    "iso:country": "GB",
    "wof:name": "NP18 1GD",
    "wof:placetype": "postalcode"
  },
  "geometry": {"coordinates":[-2.979697,51.633579],"type":"Point"}
}
