{
  "type": "Feature",
  "properties": {
    "date:inception_lower":"1999-06-01",
    "date:inception_upper":"1999-06-30",
    "iso:country":"GB",
    "wof:name":"NP18 1GD",
    "wof:placetype":"postalcode"
},
  "geometry": {"coordinates":[-2.979697,51.633579],"type":"Point"}
}