{
  "type": "Feature",
  "properties": {
    "iso:country": "GB",
    "wof:name": "BD16 1LU",
    "wof:placetype": "postalcode"
  },
  "geometry": {"coordinates":[-1.828579,53.838273],"type":"Point"}
}
