{
  "type": "Feature",
  "properties": {
    "iso:country":"GB",
    "wof:name":"BD16 1LU",
    "wof:placetype":"postalcode"
},
  "geometry": {"coordinates":[-1.8285788138232,53.83827325961029],"type":"Point"}
}