{
  "type": "Feature",
  "properties": {
    "iso:country":"GB",
    "wof:name":"LS29 8RP",
    "wof:placetype":"postalcode"
},
  "geometry": {"coordinates":[-1.8076166145938,53.91931192062877],"type":"Point"}
}