{
  "type": "Feature",
  "properties": {
    "date:inception_lower": "2000-12-01",
    "date:inception_upper": "2000-12-01",
    "iso:country": "GB",
    "wof:name": "W1U 6NT",
    "wof:placetype": "postalcode"
  },
  "geometry": {"coordinates":[-0.156322,51.521475],"type":"Point"}
}
