{
  "type": "Feature",
  "properties": {
    "iso:country":"GB",
    "wof:name":"W1U 6NT",
    "wof:placetype":"postalcode"
},
  "geometry": {"coordinates":[-0.15632234657093,51.52147460731486],"type":"Point"}
}