{
  "type": "Feature",
  "properties": {
    "iso:country":"GB",
    "wof:name":"MK13 8EN",
    "wof:placetype":"postalcode"
},
  "geometry": {"coordinates":[-0.77353879270371,52.04369399489487],"type":"Point"}
}