{
  "type": "Feature",
  "properties": {
    "iso:country":"GB",
    "wof:name":"KT19 0EH",
    "wof:placetype":"postalcode"
},
  "geometry": {"coordinates":[-0.26386244180007,51.36227627464373],"type":"Point"}
}