{
  "type": "Feature",
  "properties": {
    "iso:country": "GB",
    "wof:name": "MK18 7RF",
    "wof:placetype": "postalcode"
  },
  "geometry": {"coordinates":[-0.97584,51.986493],"type":"Point"}
}
