{
  "type": "Feature",
  "properties": {
    "iso:country":"GB",
    "wof:name":"W3 7TE",
    "wof:placetype":"postalcode"
},
  "geometry": {"coordinates":[-0.25205446284335,51.5058996567052],"type":"Point"}
}