{
  "type": "Feature",
  "properties": {
    "iso:country": "GB",
    "wof:name": "W3 7TE",
    "wof:placetype": "postalcode"
  },
  "geometry": {"coordinates":[-0.252054,51.5059],"type":"Point"}
}
