{
  "type": "Feature",
  "properties": {
    "iso:country":"GB",
    "wof:name":"ME2 1ED",
    "wof:placetype":"postalcode"
},
  "geometry": {"coordinates":[0.44592808099646,51.37629702633232],"type":"Point"}
}