{
  "type": "Feature",
  "properties": {
    "iso:country":"GB",
    "wof:name":"YO23 1DH",
    "wof:placetype":"postalcode"
},
  "geometry": {"coordinates":[-1.09274984073918,53.94768768206823],"type":"Point"}
}