{
  "type": "Feature",
  "properties": {
    "iso:country": "GB",
    "wof:name": "SO19 0JH",
    "wof:placetype": "postalcode"
  },
  "geometry": {"coordinates":[-1.339883,50.898142],"type":"Point"}
}
