{
  "type": "Feature",
  "properties": {
    "date:inception_lower": "2023-10-01",
    "date:inception_upper": "2023-10-01",
    "iso:country": "GB",
    "wof:name": "SW18 1WB",
    "wof:placetype": "postalcode"
  },
  "geometry": {"coordinates":[-0.190352,51.461648],"type":"Point"}
}
