{
  "type": "Feature",
  "properties": {
    "iso:country":"GB",
    "wof:name":"TD1 2DA",
    "wof:placetype":"postalcode"
},
  "geometry": {"coordinates":[-2.77297635080853,55.60982534912634],"type":"Point"}
}