{
  "type": "Feature",
  "properties": {
    "iso:country": "GB",
    "wof:name": "BS15 8JJ",
    "wof:placetype": "postalcode"
  },
  "geometry": {"coordinates":[-2.511921,51.461659],"type":"Point"}
}
