{
  "type": "Feature",
  "properties": {
    "iso:country":"GB",
    "wof:name":"BA3 3EW",
    "wof:placetype":"postalcode"
},
  "geometry": {"coordinates":[-2.46072463294492,51.28317841206374],"type":"Point"}
}