{
  "type": "Feature",
  "properties": {
    "iso:country":"GB",
    "wof:name":"BD7 4RQ",
    "wof:placetype":"postalcode"
},
  "geometry": {"coordinates":[-1.79712018872272,53.77573098648153],"type":"Point"}
}