{
  "type": "Feature",
  "properties": {
    "iso:country":"GB",
    "wof:name":"E15 2SW",
    "wof:placetype":"postalcode"
},
  "geometry": {"coordinates":[-0.00043061712637,51.536851939553],"type":"Point"}
}