{
  "type": "Feature",
  "properties": {
    "iso:country": "GB",
    "wof:name": "CT2 8FG",
    "wof:placetype": "postalcode"
  },
  "geometry": {"coordinates":[1.069998,51.280625],"type":"Point"}
}
