{
  "type": "Feature",
  "properties": {
    "iso:country": "GB",
    "wof:name": "WA9 5BT",
    "wof:placetype": "postalcode"
  },
  "geometry": {"coordinates":[-2.746763,53.428263],"type":"Point"}
}
