{
  "type": "Feature",
  "properties": {
    "iso:country": "GB",
    "wof:name": "BS48 2XJ",
    "wof:placetype": "postalcode"
  },
  "geometry": {"coordinates":[-2.773675,51.434048],"type":"Point"}
}
