{
  "type": "Feature",
  "properties": {
    "iso:country":"GB",
    "wof:name":"DT3 6RA",
    "wof:placetype":"postalcode"
},
  "geometry": {"coordinates":[-2.45785397533296,50.64726865820311],"type":"Point"}
}