{
  "type": "Feature",
  "properties": {
    "iso:country": "GB",
    "wof:name": "NG25 0NQ",
    "wof:placetype": "postalcode"
  },
  "geometry": {"coordinates":[-0.969532,53.075921],"type":"Point"}
}
