{
  "type": "Feature",
  "properties": {
    "date:inception_lower": "1980-01-01",
    "date:inception_upper": "1980-01-01",
    "iso:country": "GB",
    "wof:name": "CM2 0EY",
    "wof:placetype": "postalcode"
  },
  "geometry": {"coordinates":[0.47213,51.728659],"type":"Point"}
}
