{
  "type": "Feature",
  "properties": {
    "iso:country":"GB",
    "wof:name":"CM2 0EY",
    "wof:placetype":"postalcode"
},
  "geometry": {"coordinates":[0.47214739717346,51.72863369500428],"type":"Point"}
}