{
  "type": "Feature",
  "properties": {
    "iso:country":"GB",
    "wof:name":"PA19 1HR",
    "wof:placetype":"postalcode"
},
  "geometry": {"coordinates":[-4.81131217452908,55.94584633959955],"type":"Point"}
}