{
  "type": "Feature",
  "properties": {
    "iso:country": "GB",
    "wof:name": "PA19 1HR",
    "wof:placetype": "postalcode"
  },
  "geometry": {"coordinates":[-4.811312,55.945846],"type":"Point"}
}
