{
  "type": "Feature",
  "properties": {
    "iso:country":"GB",
    "wof:name":"TN5 6DU",
    "wof:placetype":"postalcode"
},
  "geometry": {"coordinates":[0.33829489110699,51.06941562528327],"type":"Point"}
}