{
  "type": "Feature",
  "properties": {
    "iso:country":"GB",
    "wof:name":"SA6 7AT",
    "wof:placetype":"postalcode"
},
  "geometry": {"coordinates":[-3.92848025427563,51.6655466273859],"type":"Point"}
}