{
  "type": "Feature",
  "properties": {
    "date:inception_lower": "2018-06-01",
    "date:inception_upper": "2018-06-01",
    "iso:country": "GB",
    "wof:name": "CB10 1FG",
    "wof:placetype": "postalcode"
  },
  "geometry": {"coordinates":[0.194716,52.059825],"type":"Point"}
}
