{
  "type": "Feature",
  "properties": {
    "iso:country":"GB",
    "wof:name":"BS5 9PY",
    "wof:placetype":"postalcode"
},
  "geometry": {"coordinates":[-2.55885812820366,51.45671450258234],"type":"Point"}
}