{
  "type": "Feature",
  "properties": {
    "iso:country": "GB",
    "wof:name": "LU3 4AB",
    "wof:placetype": "postalcode"
  },
  "geometry": {"coordinates":[-0.436842,51.919501],"type":"Point"}
}
