{
  "type": "Feature",
  "properties": {
    "iso:country":"GB",
    "wof:name":"HD9 7SG",
    "wof:placetype":"postalcode"
},
  "geometry": {"coordinates":[-1.77226893060203,53.58121866111968],"type":"Point"}
}