{
  "type": "Feature",
  "properties": {
    "iso:country": "GB",
    "wof:name": "B90 3QQ",
    "wof:placetype": "postalcode"
  },
  "geometry": {"coordinates":[-1.813452,52.408722],"type":"Point"}
}
