{
  "type": "Feature",
  "properties": {
    "iso:country": "GB",
    "wof:name": "PE14 8AZ",
    "wof:placetype": "postalcode"
  },
  "geometry": {"coordinates":[0.217618,52.614491],"type":"Point"}
}
