{
  "type": "Feature",
  "properties": {
    "iso:country":"GB",
    "wof:name":"BH7 6QL",
    "wof:placetype":"postalcode"
},
  "geometry": {"coordinates":[-1.82083444601547,50.73924495753703],"type":"Point"}
}