{
  "type": "Feature",
  "properties": {
    "iso:country":"GB",
    "wof:name":"DH2 1QQ",
    "wof:placetype":"postalcode"
},
  "geometry": {"coordinates":[-1.614304107864,54.87291996549203],"type":"Point"}
}