{
  "type": "Feature",
  "properties": {
    "iso:country": "GB",
    "wof:name": "WN6 7PU",
    "wof:placetype": "postalcode"
  },
  "geometry": {"coordinates":[-2.649904,53.55842],"type":"Point"}
}
