{
  "type": "Feature",
  "properties": {
    "iso:country": "GB",
    "wof:name": "WN5 8UJ",
    "wof:placetype": "postalcode"
  },
  "geometry": {"coordinates":[-2.718154,53.53436],"type":"Point"}
}
