{
  "type": "Feature",
  "properties": {
    "iso:country":"GB",
    "wof:name":"WN5 8UJ",
    "wof:placetype":"postalcode"
},
  "geometry": {"coordinates":[-2.7181532657847,53.53433534360149],"type":"Point"}
}