{
  "type": "Feature",
  "properties": {
    "iso:country":"GB",
    "wof:name":"RH11 8AU",
    "wof:placetype":"postalcode"
},
  "geometry": {"coordinates":[-0.21055360852247,51.10239995688427],"type":"Point"}
}