{
  "type": "Feature",
  "properties": {
    "iso:country": "GB",
    "wof:name": "RH11 8AU",
    "wof:placetype": "postalcode"
  },
  "geometry": {"coordinates":[-0.210554,51.1024],"type":"Point"}
}
