{
  "type": "Feature",
  "properties": {
    "iso:country":"GB",
    "wof:name":"LL11 4TR",
    "wof:placetype":"postalcode"
},
  "geometry": {"coordinates":[-3.03100442902617,53.07929170162024],"type":"Point"}
}