{
  "type": "Feature",
  "properties": {
    "date:inception_lower":"1980-01-01",
    "date:inception_upper":"1980-01-31",
    "iso:country":"GB",
    "wof:name":"DN32 7SR",
    "wof:placetype":"postalcode"
},
  "geometry": {"coordinates":[-0.074866,53.573571],"type":"Point"}
}