{
  "type": "Feature",
  "properties": {
    "iso:country":"GB",
    "wof:name":"KT6 5RW",
    "wof:placetype":"postalcode"
},
  "geometry": {"coordinates":[-0.3150103825132,51.39093583476899],"type":"Point"}
}