{
  "type": "Feature",
  "properties": {
    "date:inception_lower": "1999-12-01",
    "date:inception_upper": "1999-12-01",
    "iso:country": "GB",
    "wof:name": "KT6 5RW",
    "wof:placetype": "postalcode"
  },
  "geometry": {"coordinates":[-0.31501,51.390936],"type":"Point"}
}
