{
  "type": "Feature",
  "properties": {
    "iso:country":"GB",
    "wof:name":"SW18 4AT",
    "wof:placetype":"postalcode"
},
  "geometry": {"coordinates":[-0.19705509887774,51.45435843851543],"type":"Point"}
}