{
  "type": "Feature",
  "properties": {
    "date:inception_lower": "1980-01-01",
    "date:inception_upper": "1980-01-01",
    "iso:country": "GB",
    "wof:name": "PL11 2NR",
    "wof:placetype": "postalcode"
  },
  "geometry": {"coordinates":[-4.212942,50.372901],"type":"Point"}
}
