{
  "type": "Feature",
  "properties": {
    "iso:country":"GB",
    "wof:name":"TR1 2UD",
    "wof:placetype":"postalcode"
},
  "geometry": {"coordinates":[-5.05563211075836,50.26599725400462],"type":"Point"}
}