{
  "type": "Feature",
  "properties": {
    "iso:country":"GB",
    "wof:name":"UB4 9YE",
    "wof:placetype":"postalcode"
},
  "geometry": {"coordinates":[-0.38672742703269,51.52132666790839],"type":"Point"}
}