{
  "type": "Feature",
  "properties": {
    "iso:country":"GB",
    "wof:name":"M12 6NE",
    "wof:placetype":"postalcode"
},
  "geometry": {"coordinates":[-2.21130149326446,53.47613772492213],"type":"Point"}
}