{
  "type": "Feature",
  "properties": {
    "iso:country":"GB",
    "wof:name":"PO21 1AU",
    "wof:placetype":"postalcode"
},
  "geometry": {"coordinates":[-0.67319059750662,50.7908670360784],"type":"Point"}
}