{
  "type": "Feature",
  "properties": {
    "iso:country":"GB",
    "wof:name":"EH6 5PX",
    "wof:placetype":"postalcode"
},
  "geometry": {"coordinates":[-3.18483206804167,55.96967612474167],"type":"Point"}
}