{
  "type": "Feature",
  "properties": {
    "iso:country": "GB",
    "wof:name": "BD20 8AQ",
    "wof:placetype": "postalcode"
  },
  "geometry": {"coordinates":[-1.991699,53.902047],"type":"Point"}
}
