{
  "type": "Feature",
  "properties": {
    "iso:country":"GB",
    "wof:name":"KY15 5SJ",
    "wof:placetype":"postalcode"
},
  "geometry": {"coordinates":[-3.06503096680444,56.29482525969644],"type":"Point"}
}