{
  "type": "Feature",
  "properties": {
    "iso:country": "GB",
    "wof:name": "BB12 7LS",
    "wof:placetype": "postalcode"
  },
  "geometry": {"coordinates":[-2.318838,53.783495],"type":"Point"}
}
