{
  "type": "Feature",
  "properties": {
    "iso:country":"GB",
    "wof:name":"BB12 7LS",
    "wof:placetype":"postalcode"
},
  "geometry": {"coordinates":[-2.31883783589181,53.78349488721705],"type":"Point"}
}