{
  "type": "Feature",
  "properties": {
    "iso:country": "GB",
    "wof:name": "L19 4TJ",
    "wof:placetype": "postalcode"
  },
  "geometry": {"coordinates":[-2.888753,53.362824],"type":"Point"}
}
