{
  "type": "Feature",
  "properties": {
    "iso:country":"GB",
    "wof:name":"BA13 3HP",
    "wof:placetype":"postalcode"
},
  "geometry": {"coordinates":[-2.17753199757257,51.25785657854527],"type":"Point"}
}