{
  "type": "Feature",
  "properties": {
    "iso:country": "GB",
    "wof:name": "BA13 3HP",
    "wof:placetype": "postalcode"
  },
  "geometry": {"coordinates":[-2.177532,51.257857],"type":"Point"}
}
