{
  "type": "Feature",
  "properties": {
    "date:inception_lower":"1980-01-01",
    "date:inception_upper":"1980-01-31",
    "iso:country":"GB",
    "wof:name":"E1 4TZ",
    "wof:placetype":"postalcode"
},
  "geometry": {"coordinates":[-0.053018,51.521685],"type":"Point"}
}