{
  "type": "Feature",
  "properties": {
    "iso:country":"GB",
    "wof:name":"E1 4TZ",
    "wof:placetype":"postalcode"
},
  "geometry": {"coordinates":[-0.05301762590967,51.52168477492333],"type":"Point"}
}