{
  "type": "Feature",
  "properties": {
    "date:inception_lower": "1980-01-01",
    "date:inception_upper": "1980-01-01",
    "iso:country": "GB",
    "wof:name": "TN22 4HY",
    "wof:placetype": "postalcode"
  },
  "geometry": {"coordinates":[0.180514,50.996378],"type":"Point"}
}
