{
  "type": "Feature",
  "properties": {
    "iso:country":"GB",
    "wof:name":"TN22 4HY",
    "wof:placetype":"postalcode"
},
  "geometry": {"coordinates":[0.17985617293073,50.99632127965066],"type":"Point"}
}