{
  "type": "Feature",
  "properties": {
    "date:inception_lower": "1993-01-01",
    "date:inception_upper": "1993-01-01",
    "iso:country": "GB",
    "wof:name": "TS6 7BE",
    "wof:placetype": "postalcode"
  },
  "geometry": {"coordinates":[-1.151552,54.578739],"type":"Point"}
}
