{
  "type": "Feature",
  "properties": {
    "iso:country": "GB",
    "wof:name": "TS6 7BE",
    "wof:placetype": "postalcode"
  },
  "geometry": {"coordinates":[-1.151552,54.578739],"type":"Point"}
}
