{
  "type": "Feature",
  "properties": {
    "iso:country":"GB",
    "wof:name":"TS6 7BE",
    "wof:placetype":"postalcode"
},
  "geometry": {"coordinates":[-1.15155165738566,54.57873887959707],"type":"Point"}
}