{
  "type": "Feature",
  "properties": {
    "iso:country": "GB",
    "wof:name": "L30 1PG",
    "wof:placetype": "postalcode"
  },
  "geometry": {"coordinates":[-2.958642,53.475768],"type":"Point"}
}
