{
  "type": "Feature",
  "properties": {
    "iso:country":"GB",
    "wof:name":"L30 1PG",
    "wof:placetype":"postalcode"
},
  "geometry": {"coordinates":[-2.95864245259993,53.47576775032239],"type":"Point"}
}