{
  "type": "Feature",
  "properties": {
    "iso:country":"GB",
    "wof:name":"LS29 8RR",
    "wof:placetype":"postalcode"
},
  "geometry": {"coordinates":[-1.8092748628663,53.91961115884717],"type":"Point"}
}