{
  "type": "Feature",
  "properties": {
    "iso:country": "GB",
    "wof:name": "LS29 8RR",
    "wof:placetype": "postalcode"
  },
  "geometry": {"coordinates":[-1.80844,53.919723],"type":"Point"}
}
