{
  "type": "Feature",
  "properties": {
    "iso:country":"GB",
    "wof:name":"BS15 1QG",
    "wof:placetype":"postalcode"
},
  "geometry": {"coordinates":[-2.51430685144733,51.47026201336682],"type":"Point"}
}