{
  "type": "Feature",
  "properties": {
    "iso:country": "GB",
    "wof:name": "CF15 5DE",
    "wof:placetype": "postalcode"
  },
  "geometry": {"coordinates":[-3.261183,51.535913],"type":"Point"}
}
