{
  "type": "Feature",
  "properties": {
    "iso:country":"GB",
    "wof:name":"GL8 8NP",
    "wof:placetype":"postalcode"
},
  "geometry": {"coordinates":[-2.16676446914797,51.68218220114466],"type":"Point"}
}