{
  "type": "Feature",
  "properties": {
    "iso:country": "GB",
    "wof:name": "GL8 8NP",
    "wof:placetype": "postalcode"
  },
  "geometry": {"coordinates":[-2.166764,51.682182],"type":"Point"}
}
