{
  "type": "Feature",
  "properties": {
    "iso:country":"GB",
    "wof:name":"N7 6DE",
    "wof:placetype":"postalcode"
},
  "geometry": {"coordinates":[-0.11222227477813,51.55576297925319],"type":"Point"}
}