{
  "type": "Feature",
  "properties": {
    "date:inception_lower":"1980-01-01",
    "date:inception_upper":"1980-01-31",
    "iso:country":"GB",
    "wof:name":"PO13 9SB",
    "wof:placetype":"postalcode"
},
  "geometry": {"coordinates":[-1.175554,50.806469],"type":"Point"}
}