{
  "type": "Feature",
  "properties": {
    "iso:country":"GB",
    "wof:name":"PO13 9SB",
    "wof:placetype":"postalcode"
},
  "geometry": {"coordinates":[-1.17555433410372,50.8064694071368],"type":"Point"}
}