{
  "type": "Feature",
  "properties": {
    "iso:country": "GB",
    "wof:name": "RG21 7TA",
    "wof:placetype": "postalcode"
  },
  "geometry": {"coordinates":[-1.093986,51.264739],"type":"Point"}
}
