{
  "type": "Feature",
  "properties": {
    "date:inception_lower":"1995-07-01",
    "date:inception_upper":"1995-07-31",
    "iso:country":"GB",
    "wof:name":"RG21 7TA",
    "wof:placetype":"postalcode"
},
  "geometry": {"coordinates":[-1.093986,51.264739],"type":"Point"}
}