{
  "type": "Feature",
  "properties": {
    "iso:country":"GB",
    "wof:name":"DA3 7AT",
    "wof:placetype":"postalcode"
},
  "geometry": {"coordinates":[0.33333944217558,51.38789308980207],"type":"Point"}
}