{
  "type": "Feature",
  "properties": {
    "iso:country": "GB",
    "wof:name": "B61 0DT",
    "wof:placetype": "postalcode"
  },
  "geometry": {"coordinates":[-2.049496,52.343644],"type":"Point"}
}
