{
  "type": "Feature",
  "properties": {
    "iso:country":"GB",
    "wof:name":"B61 0DT",
    "wof:placetype":"postalcode"
},
  "geometry": {"coordinates":[-2.04949635615214,52.34364445038413],"type":"Point"}
}