{
  "type": "Feature",
  "properties": {
    "iso:country":"GB",
    "wof:name":"TN14 7JS",
    "wof:placetype":"postalcode"
},
  "geometry": {"coordinates":[0.125741505253,51.31582576492156],"type":"Point"}
}