{
  "type": "Feature",
  "properties": {
    "date:inception_lower": "1980-01-01",
    "date:inception_upper": "1980-01-01",
    "iso:country": "GB",
    "wof:name": "MK18 1BN",
    "wof:placetype": "postalcode"
  },
  "geometry": {"coordinates":[-0.981557,51.990803],"type":"Point"}
}
