{
  "type": "Feature",
  "properties": {
    "iso:country":"GB",
    "wof:name":"MK18 1BN",
    "wof:placetype":"postalcode"
},
  "geometry": {"coordinates":[-0.98155692027739,51.99080297518402],"type":"Point"}
}