{
  "type": "Feature",
  "properties": {
    "iso:country":"GB",
    "wof:name":"ST15 8XU",
    "wof:placetype":"postalcode"
},
  "geometry": {"coordinates":[-2.07937804040025,52.91094330447311],"type":"Point"}
}