{
  "type": "Feature",
  "properties": {
    "iso:country": "GB",
    "wof:name": "ST15 8XU",
    "wof:placetype": "postalcode"
  },
  "geometry": {"coordinates":[-2.079378,52.910943],"type":"Point"}
}
