{
  "type": "Feature",
  "properties": {
    "date:inception_lower": "1980-01-01",
    "date:inception_upper": "1980-01-01",
    "iso:country": "GB",
    "wof:name": "KY15 4BH",
    "wof:placetype": "postalcode"
  },
  "geometry": {"coordinates":[-3.011306,56.320469],"type":"Point"}
}
