{
  "type": "Feature",
  "properties": {
    "date:inception_lower": "1995-07-01",
    "date:inception_upper": "1995-07-01",
    "iso:country": "GB",
    "wof:name": "RG14 2TH",
    "wof:placetype": "postalcode"
  },
  "geometry": {"coordinates":[-1.294328,51.427566],"type":"Point"}
}
