{
  "type": "Feature",
  "properties": {
    "iso:country":"GB",
    "wof:name":"RG14 2TH",
    "wof:placetype":"postalcode"
},
  "geometry": {"coordinates":[-1.29432800477844,51.42756586463165],"type":"Point"}
}