{
  "type": "Feature",
  "properties": {
    "iso:country": "GB",
    "wof:name": "LS9 7HU",
    "wof:placetype": "postalcode"
  },
  "geometry": {"coordinates":[-1.519143,53.802964],"type":"Point"}
}
