{
  "type": "Feature",
  "properties": {
    "iso:country":"GB",
    "wof:name":"LS9 7HU",
    "wof:placetype":"postalcode"
},
  "geometry": {"coordinates":[-1.51914313239188,53.80296380648039],"type":"Point"}
}