{
  "type": "Feature",
  "properties": {
    "iso:country": "GB",
    "wof:name": "GL7 4BE",
    "wof:placetype": "postalcode"
  },
  "geometry": {"coordinates":[-1.77951,51.705597],"type":"Point"}
}
