{
  "type": "Feature",
  "properties": {
    "date:inception_lower": "2016-03-01",
    "date:inception_upper": "2016-03-01",
    "iso:country": "GB",
    "wof:name": "G66 3TL",
    "wof:placetype": "postalcode"
  },
  "geometry": {"coordinates":[-4.124913,55.928403],"type":"Point"}
}
