{
  "type": "Feature",
  "properties": {
    "iso:country": "GB",
    "wof:name": "G66 3TL",
    "wof:placetype": "postalcode"
  },
  "geometry": {"coordinates":[-4.124723,55.928442],"type":"Point"}
}
