{
  "type": "Feature",
  "properties": {
    "iso:country":"GB",
    "wof:name":"G66 3TL",
    "wof:placetype":"postalcode"
},
  "geometry": {"coordinates":[-4.12647894357645,55.92842578241756],"type":"Point"}
}