{
  "type": "Feature",
  "properties": {
    "iso:country":"GB",
    "wof:name":"BR3 4RJ",
    "wof:placetype":"postalcode"
},
  "geometry": {"coordinates":[-0.04615180102128,51.41056494021719],"type":"Point"}
}