{
  "type": "Feature",
  "properties": {
    "iso:country":"GB",
    "wof:name":"CW2 8NS",
    "wof:placetype":"postalcode"
},
  "geometry": {"coordinates":[-2.4640475574386,53.09021620594597],"type":"Point"}
}