{
  "type": "Feature",
  "properties": {
    "iso:country":"GB",
    "wof:name":"W12 0SJ",
    "wof:placetype":"postalcode"
},
  "geometry": {"coordinates":[-0.23700740517025,51.51532329073482],"type":"Point"}
}