{
  "type": "Feature",
  "properties": {
    "iso:country":"GB",
    "wof:name":"IP14 6PH",
    "wof:placetype":"postalcode"
},
  "geometry": {"coordinates":[1.18019497219929,52.2271334279671],"type":"Point"}
}