{
  "type": "Feature",
  "properties": {
    "iso:country":"GB",
    "wof:name":"CA3 9LD",
    "wof:placetype":"postalcode"
},
  "geometry": {"coordinates":[-2.94177087997325,54.90954605732329],"type":"Point"}
}