{
  "type": "Feature",
  "properties": {
    "iso:country":"GB",
    "wof:name":"RH10 3SE",
    "wof:placetype":"postalcode"
},
  "geometry": {"coordinates":[-0.14488411533338,51.13218654378596],"type":"Point"}
}