{
  "type": "Feature",
  "properties": {
    "iso:country":"GB",
    "wof:name":"YO61 4SA",
    "wof:placetype":"postalcode"
},
  "geometry": {"coordinates":[-1.06692642047915,54.13578762537011],"type":"Point"}
}