{
  "type": "Feature",
  "properties": {
    "iso:country": "GB",
    "wof:name": "YO61 4SA",
    "wof:placetype": "postalcode"
  },
  "geometry": {"coordinates":[-1.066926,54.135788],"type":"Point"}
}
