{
  "type": "Feature",
  "properties": {
    "date:inception_lower": "1980-01-01",
    "date:inception_upper": "1980-01-01",
    "iso:country": "GB",
    "wof:name": "DG9 9BA",
    "wof:placetype": "postalcode"
  },
  "geometry": {"coordinates":[-5.006162,54.86662],"type":"Point"}
}
