{
  "type": "Feature",
  "properties": {
    "iso:country":"GB",
    "wof:name":"DG9 9BA",
    "wof:placetype":"postalcode"
},
  "geometry": {"coordinates":[-5.00562150052076,54.86648046089418],"type":"Point"}
}