{
  "type": "Feature",
  "properties": {
    "iso:country":"GB",
    "wof:name":"HP20 2RX",
    "wof:placetype":"postalcode"
},
  "geometry": {"coordinates":[-0.81524243251911,51.81604831825414],"type":"Point"}
}