{
  "type": "Feature",
  "properties": {
    "iso:country": "GB",
    "wof:name": "HP20 2RX",
    "wof:placetype": "postalcode"
  },
  "geometry": {"coordinates":[-0.815087,51.816117],"type":"Point"}
}
