{
  "type": "Feature",
  "properties": {
    "iso:country": "GB",
    "wof:name": "BH10 7HR",
    "wof:placetype": "postalcode"
  },
  "geometry": {"coordinates":[-1.893147,50.772453],"type":"Point"}
}
