{
  "type": "Feature",
  "properties": {
    "iso:country":"GB",
    "wof:name":"BH10 7HR",
    "wof:placetype":"postalcode"
},
  "geometry": {"coordinates":[-1.89314704289133,50.77245328555406],"type":"Point"}
}