{
  "type": "Feature",
  "properties": {
    "iso:country": "GB",
    "wof:name": "SY12 9PT",
    "wof:placetype": "postalcode"
  },
  "geometry": {"coordinates":[-2.896759,52.912015],"type":"Point"}
}
