{
  "type": "Feature",
  "properties": {
    "date:inception_lower":"2000-06-01",
    "date:inception_upper":"2000-06-30",
    "iso:country":"GB",
    "wof:name":"SY12 9PT",
    "wof:placetype":"postalcode"
},
  "geometry": {"coordinates":[-2.896759,52.912015],"type":"Point"}
}