{
  "type": "Feature",
  "properties": {
    "iso:country":"GB",
    "wof:name":"SY12 9PT",
    "wof:placetype":"postalcode"
},
  "geometry": {"coordinates":[-2.89675885356885,52.91201548394877],"type":"Point"}
}