{
  "type": "Feature",
  "properties": {
    "iso:country":"GB",
    "wof:name":"PL2 1LA",
    "wof:placetype":"postalcode"
},
  "geometry": {"coordinates":[-4.17191545103992,50.38552475652038],"type":"Point"}
}