{
  "type": "Feature",
  "properties": {
    "iso:country": "GB",
    "wof:name": "WA4 4RL",
    "wof:placetype": "postalcode"
  },
  "geometry": {"coordinates":[-2.542101,53.349215],"type":"Point"}
}
