{
  "type": "Feature",
  "properties": {
    "iso:country":"GB",
    "wof:name":"WA4 4RL",
    "wof:placetype":"postalcode"
},
  "geometry": {"coordinates":[-2.54097213312962,53.3501211752253],"type":"Point"}
}