{
  "type": "Feature",
  "properties": {
    "date:inception_lower":"1985-04-01",
    "date:inception_upper":"1985-04-30",
    "iso:country":"GB",
    "wof:name":"WA4 4RL",
    "wof:placetype":"postalcode"
},
  "geometry": {"coordinates":[-2.542101,53.349215],"type":"Point"}
}