{
  "type": "Feature",
  "properties": {
    "date:inception_lower": "2020-04-01",
    "date:inception_upper": "2020-04-01",
    "iso:country": "GB",
    "wof:name": "BD14 6FB",
    "wof:placetype": "postalcode"
  },
  "geometry": {"coordinates":[-1.82899,53.782725],"type":"Point"}
}
