{
  "type": "Feature",
  "properties": {
    "iso:country": "GB",
    "wof:name": "BD14 6FB",
    "wof:placetype": "postalcode"
  },
  "geometry": {"coordinates":[-1.828611,53.782518],"type":"Point"}
}
