{
  "type": "Feature",
  "properties": {
    "iso:country":"GB",
    "wof:name":"CF72 9NS",
    "wof:placetype":"postalcode"
},
  "geometry": {"coordinates":[-3.43894333140393,51.53883848399764],"type":"Point"}
}