{
  "type": "Feature",
  "properties": {
    "iso:country":"GB",
    "wof:name":"DE73 5XP",
    "wof:placetype":"postalcode"
},
  "geometry": {"coordinates":[-1.4478322537588,52.8682647652661],"type":"Point"}
}