{
  "type": "Feature",
  "properties": {
    "iso:country":"GB",
    "wof:name":"IV6 7XP",
    "wof:placetype":"postalcode"
},
  "geometry": {"coordinates":[-4.45610092632947,57.53015662721873],"type":"Point"}
}