{
  "type": "Feature",
  "properties": {
    "iso:country":"GB",
    "wof:name":"SA44 5TL",
    "wof:placetype":"postalcode"
},
  "geometry": {"coordinates":[-4.39322767215996,52.03926563570072],"type":"Point"}
}