{
  "type": "Feature",
  "properties": {
    "iso:country":"GB",
    "wof:name":"MK43 0FD",
    "wof:placetype":"postalcode"
},
  "geometry": {"coordinates":[-0.55628878497965,52.06055506556989],"type":"Point"}
}