{
  "type": "Feature",
  "properties": {
    "iso:country":"GB",
    "wof:name":"AB12 5EX",
    "wof:placetype":"postalcode"
},
  "geometry": {"coordinates":[-2.10654126372199,57.11740283483547],"type":"Point"}
}