{
  "type": "Feature",
  "properties": {
    "date:inception_lower": "1980-01-01",
    "date:inception_upper": "1980-01-01",
    "iso:country": "GB",
    "wof:name": "SE6 3QB",
    "wof:placetype": "postalcode"
  },
  "geometry": {"coordinates":[-0.018849,51.424765],"type":"Point"}
}
