{
  "type": "Feature",
  "properties": {
    "iso:country":"GB",
    "wof:name":"KA25 6AR",
    "wof:placetype":"postalcode"
},
  "geometry": {"coordinates":[-4.69028376052784,55.75058607269369],"type":"Point"}
}