{
  "type": "Feature",
  "properties": {
    "date:inception_lower": "2023-10-01",
    "date:inception_upper": "2023-10-01",
    "iso:country": "GB",
    "wof:name": "PE10 1FD",
    "wof:placetype": "postalcode"
  },
  "geometry": {"coordinates":[-0.3795,52.768124],"type":"Point"}
}
