{
  "type": "Feature",
  "properties": {
    "date:inception_lower": "1980-01-01",
    "date:inception_upper": "1980-01-01",
    "iso:country": "GB",
    "wof:name": "SW12 9RP",
    "wof:placetype": "postalcode"
  },
  "geometry": {"coordinates":[-0.144809,51.44224],"type":"Point"}
}
