{
  "type": "Feature",
  "properties": {
    "iso:country":"GB",
    "wof:name":"SW12 9RP",
    "wof:placetype":"postalcode"
},
  "geometry": {"coordinates":[-0.14480889883744,51.4422396085419],"type":"Point"}
}