{
  "type": "Feature",
  "properties": {
    "date:inception_lower": "1990-02-01",
    "date:inception_upper": "1990-02-01",
    "iso:country": "GB",
    "wof:name": "TA3 7HU",
    "wof:placetype": "postalcode"
  },
  "geometry": {"coordinates":[-3.121556,50.992295],"type":"Point"}
}
