{
  "type": "Feature",
  "properties": {
    "iso:country":"GB",
    "wof:name":"TA3 7HU",
    "wof:placetype":"postalcode"
},
  "geometry": {"coordinates":[-3.12155591673734,50.99229503593416],"type":"Point"}
}