{
  "type": "Feature",
  "properties": {
    "iso:country":"GB",
    "wof:name":"SO50 7EE",
    "wof:placetype":"postalcode"
},
  "geometry": {"coordinates":[-1.29489698622636,50.96463909247512],"type":"Point"}
}