{
  "type": "Feature",
  "properties": {
    "date:inception_lower":"1994-05-01",
    "date:inception_upper":"1994-05-31",
    "iso:country":"GB",
    "wof:name":"LE8 8BP",
    "wof:placetype":"postalcode"
},
  "geometry": {"coordinates":[-1.052763,52.537378],"type":"Point"}
}