{
  "type": "Feature",
  "properties": {
    "iso:country":"GB",
    "wof:name":"LE8 8BP",
    "wof:placetype":"postalcode"
},
  "geometry": {"coordinates":[-1.05276295735944,52.53737786924299],"type":"Point"}
}