{
  "type": "Feature",
  "properties": {
    "iso:country": "GB",
    "wof:name": "SN5 4JA",
    "wof:placetype": "postalcode"
  },
  "geometry": {"coordinates":[-1.880194,51.60434],"type":"Point"}
}
