{
  "type": "Feature",
  "properties": {
    "iso:country":"GB",
    "wof:name":"CM7 1BN",
    "wof:placetype":"postalcode"
},
  "geometry": {"coordinates":[0.55769774702306,51.86580844145895],"type":"Point"}
}