{
  "type": "Feature",
  "properties": {
    "iso:country":"GB",
    "wof:name":"DT6 3JA",
    "wof:placetype":"postalcode"
},
  "geometry": {"coordinates":[-2.73729833789706,50.74671690668144],"type":"Point"}
}