{
  "type": "Feature",
  "properties": {
    "iso:country":"GB",
    "wof:name":"NG17 2EN",
    "wof:placetype":"postalcode"
},
  "geometry": {"coordinates":[-1.27522743956975,53.12546685809956],"type":"Point"}
}