{
  "type": "Feature",
  "properties": {
    "date:inception_lower": "2016-05-01",
    "date:inception_upper": "2016-05-01",
    "iso:country": "GB",
    "wof:name": "AB22 8JP",
    "wof:placetype": "postalcode"
  },
  "geometry": {"coordinates":[-2.107323,57.179882],"type":"Point"}
}
