{
  "type": "Feature",
  "properties": {
    "iso:country": "GB",
    "wof:name": "NW2 1BX",
    "wof:placetype": "postalcode"
  },
  "geometry": {"coordinates":[-0.218845,51.565631],"type":"Point"}
}
