{
  "type": "Feature",
  "properties": {
    "iso:country":"GB",
    "wof:name":"NW2 1BX",
    "wof:placetype":"postalcode"
},
  "geometry": {"coordinates":[-0.21884462498338,51.56563103313047],"type":"Point"}
}