{
  "type": "Feature",
  "properties": {
    "iso:country":"GB",
    "wof:name":"DH9 0UU",
    "wof:placetype":"postalcode"
},
  "geometry": {"coordinates":[-1.6782522052908,54.87354636587541],"type":"Point"}
}