{
  "type": "Feature",
  "properties": {
    "iso:country":"GB",
    "wof:name":"GU16 6TB",
    "wof:placetype":"postalcode"
},
  "geometry": {"coordinates":[-0.69008209264025,51.31255051353133],"type":"Point"}
}