{
  "type": "Feature",
  "properties": {
    "iso:country": "GB",
    "wof:name": "GU16 6TB",
    "wof:placetype": "postalcode"
  },
  "geometry": {"coordinates":[-0.690082,51.312551],"type":"Point"}
}
