{
  "type": "Feature",
  "properties": {
    "iso:country":"GB",
    "wof:name":"DT2 8RF",
    "wof:placetype":"postalcode"
},
  "geometry": {"coordinates":[-2.28628690825885,50.70271762627464],"type":"Point"}
}