{
  "type": "Feature",
  "properties": {
    "iso:country": "GB",
    "wof:name": "DT2 8RF",
    "wof:placetype": "postalcode"
  },
  "geometry": {"coordinates":[-2.286287,50.702718],"type":"Point"}
}
