{
  "type": "Feature",
  "properties": {
    "iso:country":"GB",
    "wof:name":"LE4 8JR",
    "wof:placetype":"postalcode"
},
  "geometry": {"coordinates":[-1.09086676838623,52.67404680564381],"type":"Point"}
}