{
  "type": "Feature",
  "properties": {
    "iso:country":"GB",
    "wof:name":"SS14 2EN",
    "wof:placetype":"postalcode"
},
  "geometry": {"coordinates":[0.46589479034637,51.57530617090116],"type":"Point"}
}