{
  "type": "Feature",
  "properties": {
    "iso:country": "GB",
    "wof:name": "SS14 2EN",
    "wof:placetype": "postalcode"
  },
  "geometry": {"coordinates":[0.465895,51.575306],"type":"Point"}
}
