{
  "type": "Feature",
  "properties": {
    "date:inception_lower": "2020-10-01",
    "date:inception_upper": "2020-10-01",
    "iso:country": "GB",
    "wof:name": "RH13 5XG",
    "wof:placetype": "postalcode"
  },
  "geometry": {"coordinates":[-0.314515,51.072043],"type":"Point"}
}
