{
  "type": "Feature",
  "properties": {
    "iso:country":"GB",
    "wof:name":"NE33 5SE",
    "wof:placetype":"postalcode"
},
  "geometry": {"coordinates":[-1.44571029224209,54.98528103620921],"type":"Point"}
}