{
  "type": "Feature",
  "properties": {
    "iso:country": "GB",
    "wof:name": "CM9 5DR",
    "wof:placetype": "postalcode"
  },
  "geometry": {"coordinates":[0.680573,51.727163],"type":"Point"}
}
