{
  "type": "Feature",
  "properties": {
    "iso:country":"GB",
    "wof:name":"CM9 5DR",
    "wof:placetype":"postalcode"
},
  "geometry": {"coordinates":[0.68054449503547,51.72715624230393],"type":"Point"}
}