{
  "type": "Feature",
  "properties": {
    "iso:country":"GB",
    "wof:name":"WD19 4DS",
    "wof:placetype":"postalcode"
},
  "geometry": {"coordinates":[-0.38005145048307,51.64518247146695],"type":"Point"}
}