{
  "type": "Feature",
  "properties": {
    "date:inception_lower": "1980-01-01",
    "date:inception_upper": "1980-01-01",
    "iso:country": "GB",
    "wof:name": "IV22 2LD",
    "wof:placetype": "postalcode"
  },
  "geometry": {"coordinates":[-5.597508,57.767483],"type":"Point"}
}
