{
  "type": "Feature",
  "properties": {
    "iso:country":"GB",
    "wof:name":"IV22 2LD",
    "wof:placetype":"postalcode"
},
  "geometry": {"coordinates":[-5.59750827532856,57.76748277660948],"type":"Point"}
}