{
  "type": "Feature",
  "properties": {
    "date:inception_lower":"1980-01-01",
    "date:inception_upper":"1980-01-31",
    "iso:country":"GB",
    "wof:name":"LN6 8NP",
    "wof:placetype":"postalcode"
},
  "geometry": {"coordinates":[-0.587414,53.186762],"type":"Point"}
}