{
  "type": "Feature",
  "properties": {
    "iso:country":"GB",
    "wof:name":"W1D 6JD",
    "wof:placetype":"postalcode"
},
  "geometry": {"coordinates":[-0.1313925769175,51.51178185101575],"type":"Point"}
}