{
  "type": "Feature",
  "properties": {
    "date:inception_lower":"1980-01-01",
    "date:inception_upper":"1980-01-31",
    "iso:country":"GB",
    "wof:name":"NN8 3PT",
    "wof:placetype":"postalcode"
},
  "geometry": {"coordinates":[-0.717457,52.294512],"type":"Point"}
}