{
  "type": "Feature",
  "properties": {
    "iso:country":"GB",
    "wof:name":"WF1 3SZ",
    "wof:placetype":"postalcode"
},
  "geometry": {"coordinates":[-1.49757108965428,53.69198880838913],"type":"Point"}
}