{
  "type": "Feature",
  "properties": {
    "iso:country":"GB",
    "wof:name":"CA13 0RG",
    "wof:placetype":"postalcode"
},
  "geometry": {"coordinates":[-3.33191912981961,54.62679419424811],"type":"Point"}
}