{
  "type": "Feature",
  "properties": {
    "iso:country":"GB",
    "wof:name":"BR6 9HA",
    "wof:placetype":"postalcode"
},
  "geometry": {"coordinates":[0.10766468646549,51.36256564760156],"type":"Point"}
}