{
  "type": "Feature",
  "properties": {
    "iso:country": "GB",
    "wof:name": "NP16 6FB",
    "wof:placetype": "postalcode"
  },
  "geometry": {"coordinates":[-2.695081,51.640915],"type":"Point"}
}
