{
  "type": "Feature",
  "properties": {
    "date:inception_lower":"2008-12-01",
    "date:inception_upper":"2008-12-31",
    "iso:country":"GB",
    "wof:name":"NP16 6FB",
    "wof:placetype":"postalcode"
},
  "geometry": {"coordinates":[-2.695081,51.640915],"type":"Point"}
}