{
  "type": "Feature",
  "properties": {
    "date:inception_lower":"1981-09-01",
    "date:inception_upper":"1981-09-30",
    "iso:country":"GB",
    "wof:name":"SS15 6JR",
    "wof:placetype":"postalcode"
},
  "geometry": {"coordinates":[0.410436,51.574067],"type":"Point"}
}