{
  "type": "Feature",
  "properties": {
    "iso:country": "GB",
    "wof:name": "KT9 1JH",
    "wof:placetype": "postalcode"
  },
  "geometry": {"coordinates":[-0.29468,51.366353],"type":"Point"}
}
