{
  "type": "Feature",
  "properties": {
    "date:inception_lower":"1980-01-01",
    "date:inception_upper":"1980-01-31",
    "iso:country":"GB",
    "wof:name":"KT9 1JH",
    "wof:placetype":"postalcode"
},
  "geometry": {"coordinates":[-0.29468,51.366353],"type":"Point"}
}