{
  "type": "Feature",
  "properties": {
    "date:inception_lower": "2004-02-01",
    "date:inception_upper": "2004-02-01",
    "iso:country": "GB",
    "wof:name": "CT21 5BF",
    "wof:placetype": "postalcode"
  },
  "geometry": {"coordinates":[1.082032,51.072867],"type":"Point"}
}
