{
  "type": "Feature",
  "properties": {
    "iso:country":"GB",
    "wof:name":"CT21 5BF",
    "wof:placetype":"postalcode"
},
  "geometry": {"coordinates":[1.08203233061761,51.07286702800428],"type":"Point"}
}