{
  "type": "Feature",
  "properties": {
    "iso:country": "GB",
    "wof:name": "CT21 5BF",
    "wof:placetype": "postalcode"
  },
  "geometry": {"coordinates":[1.082032,51.072867],"type":"Point"}
}
