{
  "type": "Feature",
  "properties": {
    "iso:country": "GB",
    "wof:name": "HA1 1UW",
    "wof:placetype": "postalcode"
  },
  "geometry": {"coordinates":[-0.339682,51.587815],"type":"Point"}
}
