{
  "type": "Feature",
  "properties": {
    "iso:country": "GB",
    "wof:name": "B71 3DN",
    "wof:placetype": "postalcode"
  },
  "geometry": {"coordinates":[-1.986783,52.545235],"type":"Point"}
}
