{
  "type": "Feature",
  "properties": {
    "date:inception_lower":"1994-05-01",
    "date:inception_upper":"1994-05-31",
    "iso:country":"GB",
    "wof:name":"BB5 4PB",
    "wof:placetype":"postalcode"
},
  "geometry": {"coordinates":[-2.411686,53.749111],"type":"Point"}
}