{
  "type": "Feature",
  "properties": {
    "iso:country":"GB",
    "wof:name":"BB5 4PB",
    "wof:placetype":"postalcode"
},
  "geometry": {"coordinates":[-2.41168568516039,53.74911111661935],"type":"Point"}
}