{
  "type": "Feature",
  "properties": {
    "iso:country": "GB",
    "wof:name": "BB5 4PB",
    "wof:placetype": "postalcode"
  },
  "geometry": {"coordinates":[-2.411686,53.749111],"type":"Point"}
}
