{
  "type": "Feature",
  "properties": {
    "iso:country": "GB",
    "wof:name": "DT2 8GD",
    "wof:placetype": "postalcode"
  },
  "geometry": {"coordinates":[-2.346856,50.747831],"type":"Point"}
}
