{
  "type": "Feature",
  "properties": {
    "iso:country":"GB",
    "wof:name":"TW16 7RA",
    "wof:placetype":"postalcode"
},
  "geometry": {"coordinates":[-0.41664203110361,51.42260343409613],"type":"Point"}
}