{
  "type": "Feature",
  "properties": {
    "iso:country":"GB",
    "wof:name":"PL19 0AH",
    "wof:placetype":"postalcode"
},
  "geometry": {"coordinates":[-4.14484063538336,50.55034342538785],"type":"Point"}
}