{
  "type": "Feature",
  "properties": {
    "iso:country": "GB",
    "wof:name": "PL19 0AH",
    "wof:placetype": "postalcode"
  },
  "geometry": {"coordinates":[-4.144841,50.550343],"type":"Point"}
}
