{
  "type": "Feature",
  "properties": {
    "iso:country":"GB",
    "wof:name":"OX11 7QU",
    "wof:placetype":"postalcode"
},
  "geometry": {"coordinates":[-1.22974280397692,51.60891599771366],"type":"Point"}
}