{
  "type": "Feature",
  "properties": {
    "iso:country":"GB",
    "wof:name":"TS15 9JL",
    "wof:placetype":"postalcode"
},
  "geometry": {"coordinates":[-1.31946192016368,54.5004794631104],"type":"Point"}
}