{
  "type": "Feature",
  "properties": {
    "date:inception_lower": "1994-05-01",
    "date:inception_upper": "1994-05-01",
    "iso:country": "GB",
    "wof:name": "LE8 9GP",
    "wof:placetype": "postalcode"
  },
  "geometry": {"coordinates":[-1.025814,52.58656],"type":"Point"}
}
