{
  "type": "Feature",
  "properties": {
    "date:inception_lower": "2024-06-01",
    "date:inception_upper": "2024-06-01",
    "iso:country": "GB",
    "wof:name": "PE12 7FW",
    "wof:placetype": "postalcode"
  },
  "geometry": {"coordinates":[0.007116,52.798015],"type":"Point"}
}
