{
  "type": "Feature",
  "properties": {
    "iso:country": "GB",
    "wof:name": "RH10 1GY",
    "wof:placetype": "postalcode"
  },
  "geometry": {"coordinates":[-0.16336,51.123665],"type":"Point"}
}
