{
  "type": "Feature",
  "properties": {
    "iso:country":"GB",
    "wof:name":"CH49 6PT",
    "wof:placetype":"postalcode"
},
  "geometry": {"coordinates":[-3.10390803156099,53.3829428747116],"type":"Point"}
}