{
  "type": "Feature",
  "properties": {
    "date:inception_lower":"1991-09-01",
    "date:inception_upper":"1991-09-30",
    "iso:country":"GB",
    "wof:name":"RG12 8DD",
    "wof:placetype":"postalcode"
},
  "geometry": {"coordinates":[-0.776363,51.393217],"type":"Point"}
}