{
  "type": "Feature",
  "properties": {
    "iso:country":"GB",
    "wof:name":"RG12 8DD",
    "wof:placetype":"postalcode"
},
  "geometry": {"coordinates":[-0.77636293338171,51.39321695556531],"type":"Point"}
}