{
  "type": "Feature",
  "properties": {
    "iso:country": "GB",
    "wof:name": "RG12 8DD",
    "wof:placetype": "postalcode"
  },
  "geometry": {"coordinates":[-0.776363,51.393217],"type":"Point"}
}
