{
  "type": "Feature",
  "properties": {
    "iso:country":"GB",
    "wof:name":"DL1 1FF",
    "wof:placetype":"postalcode"
},
  "geometry": {"coordinates":[-1.53174674449931,54.52627350702992],"type":"Point"}
}