{
  "type": "Feature",
  "properties": {
    "iso:country": "GB",
    "wof:name": "DL1 1FF",
    "wof:placetype": "postalcode"
  },
  "geometry": {"coordinates":[-1.531747,54.526274],"type":"Point"}
}
