{
  "type": "Feature",
  "properties": {
    "iso:country":"GB",
    "wof:name":"MK12 5GL",
    "wof:placetype":"postalcode"
},
  "geometry": {"coordinates":[-0.818650167632,52.06203806883761],"type":"Point"}
}