{
  "type": "Feature",
  "properties": {
    "iso:country": "GB",
    "wof:name": "MK12 5GL",
    "wof:placetype": "postalcode"
  },
  "geometry": {"coordinates":[-0.81865,52.062038],"type":"Point"}
}
