{
  "type": "Feature",
  "properties": {
    "date:inception_lower": "2007-09-01",
    "date:inception_upper": "2007-09-01",
    "iso:country": "GB",
    "wof:name": "MK12 5GL",
    "wof:placetype": "postalcode"
  },
  "geometry": {"coordinates":[-0.81865,52.062038],"type":"Point"}
}
