{
  "type": "Feature",
  "properties": {
    "iso:country":"GB",
    "wof:name":"NW2 1TP",
    "wof:placetype":"postalcode"
},
  "geometry": {"coordinates":[-0.22065001368388,51.57408424377689],"type":"Point"}
}