{
  "type": "Feature",
  "properties": {
    "iso:country":"GB",
    "wof:name":"IP3 0HN",
    "wof:placetype":"postalcode"
},
  "geometry": {"coordinates":[1.17120143518146,52.03689419924621],"type":"Point"}
}