{
  "type": "Feature",
  "properties": {
    "date:inception_lower": "2020-07-01",
    "date:inception_upper": "2020-07-01",
    "iso:country": "GB",
    "wof:name": "BH23 5FU",
    "wof:placetype": "postalcode"
  },
  "geometry": {"coordinates":[-1.700457,50.74112],"type":"Point"}
}
