{
  "type": "Feature",
  "properties": {
    "date:inception_lower": "2004-11-01",
    "date:inception_upper": "2004-11-01",
    "iso:country": "GB",
    "wof:name": "AB24 5BS",
    "wof:placetype": "postalcode"
  },
  "geometry": {"coordinates":[-2.09242,57.155888],"type":"Point"}
}
