{
  "type": "Feature",
  "properties": {
    "iso:country":"GB",
    "wof:name":"S63 0BH",
    "wof:placetype":"postalcode"
},
  "geometry": {"coordinates":[-1.30123733327909,53.54324413314244],"type":"Point"}
}