{
  "type": "Feature",
  "properties": {
    "iso:country":"GB",
    "wof:name":"W4 1UB",
    "wof:placetype":"postalcode"
},
  "geometry": {"coordinates":[-0.25501116150052,51.49941520515525],"type":"Point"}
}