{
  "type": "Feature",
  "properties": {
    "date:inception_lower": "1980-01-01",
    "date:inception_upper": "1980-01-01",
    "iso:country": "GB",
    "wof:name": "W4 1UB",
    "wof:placetype": "postalcode"
  },
  "geometry": {"coordinates":[-0.255011,51.499415],"type":"Point"}
}
