{
  "type": "Feature",
  "properties": {
    "iso:country":"GB",
    "wof:name":"LS4 2HN",
    "wof:placetype":"postalcode"
},
  "geometry": {"coordinates":[-1.58319731494118,53.8081557627082],"type":"Point"}
}