{
  "type": "Feature",
  "properties": {
    "iso:country": "GB",
    "wof:name": "CR8 5NR",
    "wof:placetype": "postalcode"
  },
  "geometry": {"coordinates":[-0.109165,51.3265],"type":"Point"}
}
