{
  "type": "Feature",
  "properties": {
    "iso:country":"GB",
    "wof:name":"NN4 8TW",
    "wof:placetype":"postalcode"
},
  "geometry": {"coordinates":[-0.92176936595052,52.22587791741546],"type":"Point"}
}