{
  "type": "Feature",
  "properties": {
    "iso:country": "GB",
    "wof:name": "KT20 6QR",
    "wof:placetype": "postalcode"
  },
  "geometry": {"coordinates":[-0.217572,51.281491],"type":"Point"}
}
