{
  "type": "Feature",
  "properties": {
    "iso:country": "GB",
    "wof:name": "S36 1LR",
    "wof:placetype": "postalcode"
  },
  "geometry": {"coordinates":[-1.613139,53.484374],"type":"Point"}
}
