{
  "type": "Feature",
  "properties": {
    "iso:country":"GB",
    "wof:name":"S36 1LR",
    "wof:placetype":"postalcode"
},
  "geometry": {"coordinates":[-1.61313954393969,53.48437359494822],"type":"Point"}
}