{
  "type": "Feature",
  "properties": {
    "date:inception_lower": "2019-04-01",
    "date:inception_upper": "2019-04-01",
    "iso:country": "GB",
    "wof:name": "SN5 4FZ",
    "wof:placetype": "postalcode"
  },
  "geometry": {"coordinates":[-1.839437,51.583487],"type":"Point"}
}
