{
  "type": "Feature",
  "properties": {
    "iso:country": "GB",
    "wof:name": "NE16 5QA",
    "wof:placetype": "postalcode"
  },
  "geometry": {"coordinates":[-1.682615,54.923216],"type":"Point"}
}
