{
  "type": "Feature",
  "properties": {
    "iso:country": "GB",
    "wof:name": "TF6 5HQ",
    "wof:placetype": "postalcode"
  },
  "geometry": {"coordinates":[-2.611844,52.687341],"type":"Point"}
}
