{
  "type": "Feature",
  "properties": {
    "iso:country":"GB",
    "wof:name":"TF6 5HQ",
    "wof:placetype":"postalcode"
},
  "geometry": {"coordinates":[-2.6118442229418,52.68734087861538],"type":"Point"}
}