{
  "type": "Feature",
  "properties": {
    "iso:country": "GB",
    "wof:name": "PE15 0LJ",
    "wof:placetype": "postalcode"
  },
  "geometry": {"coordinates":[0.060577,52.492023],"type":"Point"}
}
