{
  "type": "Feature",
  "properties": {
    "iso:country":"GB",
    "wof:name":"PE15 0LJ",
    "wof:placetype":"postalcode"
},
  "geometry": {"coordinates":[0.06057706414386,52.49202266699661],"type":"Point"}
}