{
  "type": "Feature",
  "properties": {
    "iso:country": "GB",
    "wof:name": "WF13 3QU",
    "wof:placetype": "postalcode"
  },
  "geometry": {"coordinates":[-1.656509,53.687696],"type":"Point"}
}
