{
  "type": "Feature",
  "properties": {
    "iso:country":"GB",
    "wof:name":"E1 4SF",
    "wof:placetype":"postalcode"
},
  "geometry": {"coordinates":[-0.03838783073722,51.51863531795743],"type":"Point"}
}