{
  "type": "Feature",
  "properties": {
    "date:inception_lower": "1980-01-01",
    "date:inception_upper": "1980-01-01",
    "iso:country": "GB",
    "wof:name": "SK4 1LQ",
    "wof:placetype": "postalcode"
  },
  "geometry": {"coordinates":[-2.164437,53.415863],"type":"Point"}
}
