{
  "type": "Feature",
  "properties": {
    "iso:country": "GB",
    "wof:name": "N7 9EQ",
    "wof:placetype": "postalcode"
  },
  "geometry": {"coordinates":[-0.124656,51.549821],"type":"Point"}
}
