{
  "type": "Feature",
  "properties": {
    "date:inception_lower": "1997-12-01",
    "date:inception_upper": "1997-12-01",
    "iso:country": "GB",
    "wof:name": "BS34 5DN",
    "wof:placetype": "postalcode"
  },
  "geometry": {"coordinates":[-2.587414,51.528508],"type":"Point"}
}
