{
  "type": "Feature",
  "properties": {
    "iso:country":"GB",
    "wof:name":"TR18 2AX",
    "wof:placetype":"postalcode"
},
  "geometry": {"coordinates":[-5.53541491227184,50.12502201705189],"type":"Point"}
}