{
  "type": "Feature",
  "properties": {
    "iso:country": "GB",
    "wof:name": "TR18 2AX",
    "wof:placetype": "postalcode"
  },
  "geometry": {"coordinates":[-5.535415,50.125022],"type":"Point"}
}
