{
  "type": "Feature",
  "properties": {
    "iso:country": "GB",
    "wof:name": "E8 3FY",
    "wof:placetype": "postalcode"
  },
  "geometry": {"coordinates":[-0.05719,51.538842],"type":"Point"}
}
