{
  "type": "Feature",
  "properties": {
    "date:inception_lower":"1980-01-01",
    "date:inception_upper":"1980-01-31",
    "iso:country":"GB",
    "wof:name":"RH5 5LH",
    "wof:placetype":"postalcode"
},
  "geometry": {"coordinates":[-0.321889,51.162082],"type":"Point"}
}