{
  "type": "Feature",
  "properties": {
    "iso:country":"GB",
    "wof:name":"RH5 5LH",
    "wof:placetype":"postalcode"
},
  "geometry": {"coordinates":[-0.3199329831055,51.16278217823177],"type":"Point"}
}