{
  "type": "Feature",
  "properties": {
    "iso:country":"GB",
    "wof:name":"PE9 2GJ",
    "wof:placetype":"postalcode"
},
  "geometry": {"coordinates":[-0.47451003477512,52.64918781687651],"type":"Point"}
}