{
  "type": "Feature",
  "properties": {
    "iso:country":"GB",
    "wof:name":"BN20 8LY",
    "wof:placetype":"postalcode"
},
  "geometry": {"coordinates":[0.25717342031607,50.77250701784062],"type":"Point"}
}