{
  "type": "Feature",
  "properties": {
    "iso:country":"GB",
    "wof:name":"SW6 3PT",
    "wof:placetype":"postalcode"
},
  "geometry": {"coordinates":[-0.2056328293867,51.46905789831739],"type":"Point"}
}