{
  "type": "Feature",
  "properties": {
    "iso:country": "GB",
    "wof:name": "SO23 0LR",
    "wof:placetype": "postalcode"
  },
  "geometry": {"coordinates":[-1.299803,51.06639],"type":"Point"}
}
