{
  "type": "Feature",
  "properties": {
    "iso:country":"GB",
    "wof:name":"PE31 6UG",
    "wof:placetype":"postalcode"
},
  "geometry": {"coordinates":[0.65854331406665,52.79814898311433],"type":"Point"}
}