{
  "type": "Feature",
  "properties": {
    "iso:country":"GB",
    "wof:name":"B75 7JY",
    "wof:placetype":"postalcode"
},
  "geometry": {"coordinates":[-1.79527243839135,52.56339173670667],"type":"Point"}
}