{
  "type": "Feature",
  "properties": {
    "iso:country": "GB",
    "wof:name": "G69 7SR",
    "wof:placetype": "postalcode"
  },
  "geometry": {"coordinates":[-4.081355,55.852924],"type":"Point"}
}
