{
  "type": "Feature",
  "properties": {
    "iso:country": "GB",
    "wof:name": "G32 8XU",
    "wof:placetype": "postalcode"
  },
  "geometry": {"coordinates":[-4.144529,55.839023],"type":"Point"}
}
