{
  "type": "Feature",
  "properties": {
    "iso:country":"GB",
    "wof:name":"G32 8XU",
    "wof:placetype":"postalcode"
},
  "geometry": {"coordinates":[-4.14452891649133,55.83902281618568],"type":"Point"}
}