{
  "type": "Feature",
  "properties": {
    "iso:country":"GB",
    "wof:name":"KY6 3HD",
    "wof:placetype":"postalcode"
},
  "geometry": {"coordinates":[-3.21105951679782,56.21285992114615],"type":"Point"}
}