{
  "type": "Feature",
  "properties": {
    "iso:country": "GB",
    "wof:name": "KY6 3HD",
    "wof:placetype": "postalcode"
  },
  "geometry": {"coordinates":[-3.211059,56.21286],"type":"Point"}
}
