{
  "type": "Feature",
  "properties": {
    "iso:country":"GB",
    "wof:name":"CH43 0UA",
    "wof:placetype":"postalcode"
},
  "geometry": {"coordinates":[-3.06291186800563,53.37521590139402],"type":"Point"}
}