{
  "type": "Feature",
  "properties": {
    "iso:country": "GB",
    "wof:name": "S71 4LT",
    "wof:placetype": "postalcode"
  },
  "geometry": {"coordinates":[-1.47079,53.600642],"type":"Point"}
}
