{
  "type": "Feature",
  "properties": {
    "date:inception_lower": "1983-07-01",
    "date:inception_upper": "1983-07-01",
    "iso:country": "GB",
    "wof:name": "S71 4LT",
    "wof:placetype": "postalcode"
  },
  "geometry": {"coordinates":[-1.47079,53.600642],"type":"Point"}
}
