{
  "type": "Feature",
  "properties": {
    "iso:country":"GB",
    "wof:name":"S71 4LT",
    "wof:placetype":"postalcode"
},
  "geometry": {"coordinates":[-1.47079024197578,53.60064232714903],"type":"Point"}
}