{
  "type": "Feature",
  "properties": {
    "date:inception_lower": "1980-01-01",
    "date:inception_upper": "1980-01-01",
    "iso:country": "GB",
    "wof:name": "NR32 5QG",
    "wof:placetype": "postalcode"
  },
  "geometry": {"coordinates":[1.673632,52.525541],"type":"Point"}
}
