{
  "type": "Feature",
  "properties": {
    "iso:country":"GB",
    "wof:name":"NR32 5QG",
    "wof:placetype":"postalcode"
},
  "geometry": {"coordinates":[1.67363202269391,52.52554123515951],"type":"Point"}
}