{
  "type": "Feature",
  "properties": {
    "iso:country":"GB",
    "wof:name":"NR21 9JQ",
    "wof:placetype":"postalcode"
},
  "geometry": {"coordinates":[0.75537462431755,52.90033840958102],"type":"Point"}
}