{
  "type": "Feature",
  "properties": {
    "iso:country": "GB",
    "wof:name": "YO16 4UR",
    "wof:placetype": "postalcode"
  },
  "geometry": {"coordinates":[-0.251806,54.072733],"type":"Point"}
}
