{
  "type": "Feature",
  "properties": {
    "iso:country":"GB",
    "wof:name":"W11 1QN",
    "wof:placetype":"postalcode"
},
  "geometry": {"coordinates":[-0.20998077441123,51.51650561357511],"type":"Point"}
}