{
  "type": "Feature",
  "properties": {
    "date:inception_lower": "1980-01-01",
    "date:inception_upper": "1980-01-01",
    "iso:country": "GB",
    "wof:name": "DN1 2HJ",
    "wof:placetype": "postalcode"
  },
  "geometry": {"coordinates":[-1.128329,53.523397],"type":"Point"}
}
