{
  "type": "Feature",
  "properties": {
    "iso:country":"GB",
    "wof:name":"RH20 1AP",
    "wof:placetype":"postalcode"
},
  "geometry": {"coordinates":[-0.50851296335073,50.96002454835259],"type":"Point"}
}