{
  "type": "Feature",
  "properties": {
    "iso:country":"GB",
    "wof:name":"SN3 2DU",
    "wof:placetype":"postalcode"
},
  "geometry": {"coordinates":[-1.74694432772689,51.5479506015432],"type":"Point"}
}