{
  "type": "Feature",
  "properties": {
    "date:inception_lower": "1980-01-01",
    "date:inception_upper": "1980-01-01",
    "iso:country": "GB",
    "wof:name": "NR27 0HY",
    "wof:placetype": "postalcode"
  },
  "geometry": {"coordinates":[1.304254,52.918353],"type":"Point"}
}
