{
  "type": "Feature",
  "properties": {
    "iso:country":"GB",
    "wof:name":"W9 1BW",
    "wof:placetype":"postalcode"
},
  "geometry": {"coordinates":[-0.17876141629,51.52483762650923],"type":"Point"}
}