{
  "type": "Feature",
  "properties": {
    "date:inception_lower":"2007-07-01",
    "date:inception_upper":"2007-07-31",
    "iso:country":"GB",
    "wof:name":"EH39 5FB",
    "wof:placetype":"postalcode"
},
  "geometry": {"coordinates":[-2.78197,56.048553],"type":"Point"}
}