{
  "type": "Feature",
  "properties": {
    "iso:country":"GB",
    "wof:name":"EH39 5FB",
    "wof:placetype":"postalcode"
},
  "geometry": {"coordinates":[-2.78197034482063,56.04855337456772],"type":"Point"}
}