{
  "type": "Feature",
  "properties": {
    "iso:country":"GB",
    "wof:name":"RG19 3YL",
    "wof:placetype":"postalcode"
},
  "geometry": {"coordinates":[-1.26114501337911,51.39901045977309],"type":"Point"}
}