{
  "type": "Feature",
  "properties": {
    "date:inception_lower": "1995-07-01",
    "date:inception_upper": "1995-07-01",
    "iso:country": "GB",
    "wof:name": "RG19 3YL",
    "wof:placetype": "postalcode"
  },
  "geometry": {"coordinates":[-1.261145,51.39901],"type":"Point"}
}
