{
  "type": "Feature",
  "properties": {
    "date:inception_lower": "1980-01-01",
    "date:inception_upper": "1980-01-01",
    "iso:country": "GB",
    "wof:name": "ME15 8HS",
    "wof:placetype": "postalcode"
  },
  "geometry": {"coordinates":[0.553031,51.249431],"type":"Point"}
}
