{
  "type": "Feature",
  "properties": {
    "date:inception_lower": "1980-01-01",
    "date:inception_upper": "1980-01-01",
    "iso:country": "GB",
    "wof:name": "S9 4BX",
    "wof:placetype": "postalcode"
  },
  "geometry": {"coordinates":[-1.402976,53.381254],"type":"Point"}
}
