{
  "type": "Feature",
  "properties": {
    "iso:country": "GB",
    "wof:name": "S9 4BX",
    "wof:placetype": "postalcode"
  },
  "geometry": {"coordinates":[-1.402976,53.381254],"type":"Point"}
}
