{
  "type": "Feature",
  "properties": {
    "iso:country":"GB",
    "wof:name":"IV30 6YA",
    "wof:placetype":"postalcode"
},
  "geometry": {"coordinates":[-3.31629943998296,57.63812131019473],"type":"Point"}
}