{
  "type": "Feature",
  "properties": {
    "iso:country":"GB",
    "wof:name":"IV9 8RF",
    "wof:placetype":"postalcode"
},
  "geometry": {"coordinates":[-4.20414233657737,57.57308677230381],"type":"Point"}
}