{
  "type": "Feature",
  "properties": {
    "date:inception_lower": "1980-01-01",
    "date:inception_upper": "1980-01-01",
    "iso:country": "GB",
    "wof:name": "IV9 8RF",
    "wof:placetype": "postalcode"
  },
  "geometry": {"coordinates":[-4.204142,57.573087],"type":"Point"}
}
