{
  "type": "Feature",
  "properties": {
    "iso:country":"GB",
    "wof:name":"LL36 9RR",
    "wof:placetype":"postalcode"
},
  "geometry": {"coordinates":[-4.05396244690323,52.60881829817352],"type":"Point"}
}