{
  "type": "Feature",
  "properties": {
    "iso:country": "GB",
    "wof:name": "OX11 0RU",
    "wof:placetype": "postalcode"
  },
  "geometry": {"coordinates":[-1.295127,51.567211],"type":"Point"}
}
