{
  "type": "Feature",
  "properties": {
    "iso:country":"GB",
    "wof:name":"OX11 0RU",
    "wof:placetype":"postalcode"
},
  "geometry": {"coordinates":[-1.2951267041327,51.5672105256528],"type":"Point"}
}