{
  "type": "Feature",
  "properties": {
    "date:inception_lower": "1997-12-01",
    "date:inception_upper": "1997-12-01",
    "iso:country": "GB",
    "wof:name": "BS36 1RG",
    "wof:placetype": "postalcode"
  },
  "geometry": {"coordinates":[-2.501608,51.53056],"type":"Point"}
}
