{
  "type": "Feature",
  "properties": {
    "iso:country":"GB",
    "wof:name":"BS36 1RG",
    "wof:placetype":"postalcode"
},
  "geometry": {"coordinates":[-2.50152218248714,51.53058771001955],"type":"Point"}
}