{
  "type": "Feature",
  "properties": {
    "iso:country":"GB",
    "wof:name":"PE1 3BT",
    "wof:placetype":"postalcode"
},
  "geometry": {"coordinates":[-0.25152464979298,52.59190147912352],"type":"Point"}
}