{
  "type": "Feature",
  "properties": {
    "date:inception_lower": "2019-01-01",
    "date:inception_upper": "2019-01-01",
    "iso:country": "GB",
    "wof:name": "TN39 4GF",
    "wof:placetype": "postalcode"
  },
  "geometry": {"coordinates":[0.424499,50.846178],"type":"Point"}
}
