{
  "type": "Feature",
  "properties": {
    "iso:country": "GB",
    "wof:name": "TN39 4GF",
    "wof:placetype": "postalcode"
  },
  "geometry": {"coordinates":[0.424499,50.846178],"type":"Point"}
}
