{
  "type": "Feature",
  "properties": {
    "iso:country": "GB",
    "wof:name": "WD6 5RB",
    "wof:placetype": "postalcode"
  },
  "geometry": {"coordinates":[-0.26092,51.662704],"type":"Point"}
}
