{
  "type": "Feature",
  "properties": {
    "date:inception_lower": "1990-02-01",
    "date:inception_upper": "1990-02-01",
    "iso:country": "GB",
    "wof:name": "WD6 5RB",
    "wof:placetype": "postalcode"
  },
  "geometry": {"coordinates":[-0.26092,51.662704],"type":"Point"}
}
