{
  "type": "Feature",
  "properties": {
    "date:inception_lower": "2014-09-01",
    "date:inception_upper": "2014-09-01",
    "iso:country": "GB",
    "wof:name": "PE15 0JT",
    "wof:placetype": "postalcode"
  },
  "geometry": {"coordinates":[0.177481,52.496519],"type":"Point"}
}
