{
  "type": "Feature",
  "properties": {
    "iso:country":"GB",
    "wof:name":"PE15 0JT",
    "wof:placetype":"postalcode"
},
  "geometry": {"coordinates":[0.17748120636059,52.49651930766538],"type":"Point"}
}