{
  "type": "Feature",
  "properties": {
    "iso:country": "GB",
    "wof:name": "PE15 0JT",
    "wof:placetype": "postalcode"
  },
  "geometry": {"coordinates":[0.177481,52.496519],"type":"Point"}
}
