{
  "type": "Feature",
  "properties": {
    "iso:country":"GB",
    "wof:name":"PE19 8EE",
    "wof:placetype":"postalcode"
},
  "geometry": {"coordinates":[-0.28917748341535,52.218601768135],"type":"Point"}
}