{
  "type": "Feature",
  "properties": {
    "iso:country": "GB",
    "wof:name": "PE19 8EE",
    "wof:placetype": "postalcode"
  },
  "geometry": {"coordinates":[-0.289177,52.218602],"type":"Point"}
}
