{
  "type": "Feature",
  "properties": {
    "iso:country": "GB",
    "wof:name": "CF31 1JS",
    "wof:placetype": "postalcode"
  },
  "geometry": {"coordinates":[-3.581327,51.511891],"type":"Point"}
}
