{
  "type": "Feature",
  "properties": {
    "iso:country":"GB",
    "wof:name":"SM2 5JQ",
    "wof:placetype":"postalcode"
},
  "geometry": {"coordinates":[-0.19237573498363,51.3563120244007],"type":"Point"}
}