{
  "type": "Feature",
  "properties": {
    "iso:country":"GB",
    "wof:name":"WR3 7TX",
    "wof:placetype":"postalcode"
},
  "geometry": {"coordinates":[-2.2000141565846,52.23022581399469],"type":"Point"}
}