{
  "type": "Feature",
  "properties": {
    "iso:country":"GB",
    "wof:name":"EN6 1SA",
    "wof:placetype":"postalcode"
},
  "geometry": {"coordinates":[-0.18246837214761,51.70520907753153],"type":"Point"}
}