{
  "type": "Feature",
  "properties": {
    "iso:country":"GB",
    "wof:name":"PA4 9LB",
    "wof:placetype":"postalcode"
},
  "geometry": {"coordinates":[-4.43064802192482,55.8865937124005],"type":"Point"}
}