{
  "type": "Feature",
  "properties": {
    "iso:country": "GB",
    "wof:name": "G15 7PX",
    "wof:placetype": "postalcode"
  },
  "geometry": {"coordinates":[-4.357122,55.911976],"type":"Point"}
}
