{
  "type": "Feature",
  "properties": {
    "iso:country":"GB",
    "wof:name":"G15 7PX",
    "wof:placetype":"postalcode"
},
  "geometry": {"coordinates":[-4.35712194407448,55.91197621442656],"type":"Point"}
}