{
  "type": "Feature",
  "properties": {
    "iso:country":"GB",
    "wof:name":"NG9 1NP",
    "wof:placetype":"postalcode"
},
  "geometry": {"coordinates":[-1.19810083658555,52.91717417908929],"type":"Point"}
}