{
  "type": "Feature",
  "properties": {
    "date:inception_lower":"1996-06-01",
    "date:inception_upper":"1996-06-30",
    "iso:country":"GB",
    "wof:name":"LL57 2JQ",
    "wof:placetype":"postalcode"
},
  "geometry": {"coordinates":[-4.140419,53.226488],"type":"Point"}
}