{
  "type": "Feature",
  "properties": {
    "iso:country": "GB",
    "wof:name": "LL57 2JQ",
    "wof:placetype": "postalcode"
  },
  "geometry": {"coordinates":[-4.140419,53.226488],"type":"Point"}
}
