{
  "type": "Feature",
  "properties": {
    "date:inception_lower": "1980-01-01",
    "date:inception_upper": "1980-01-01",
    "iso:country": "GB",
    "wof:name": "SK14 1DF",
    "wof:placetype": "postalcode"
  },
  "geometry": {"coordinates":[-2.082985,53.448782],"type":"Point"}
}
