{
  "type": "Feature",
  "properties": {
    "date:inception_lower":"1980-01-01",
    "date:inception_upper":"1980-01-31",
    "iso:country":"GB",
    "wof:name":"KA9 1LY",
    "wof:placetype":"postalcode"
},
  "geometry": {"coordinates":[-4.607093,55.495675],"type":"Point"}
}