{
  "type": "Feature",
  "properties": {
    "iso:country":"GB",
    "wof:name":"KA9 1LY",
    "wof:placetype":"postalcode"
},
  "geometry": {"coordinates":[-4.60709336107504,55.49567492347589],"type":"Point"}
}