{
  "type": "Feature",
  "properties": {
    "iso:country":"GB",
    "wof:name":"ME14 1TU",
    "wof:placetype":"postalcode"
},
  "geometry": {"coordinates":[0.52553862674455,51.27676558022113],"type":"Point"}
}