{
  "type": "Feature",
  "properties": {
    "iso:country":"GB",
    "wof:name":"HX4 0AQ",
    "wof:placetype":"postalcode"
},
  "geometry": {"coordinates":[-1.91432771733524,53.67583457580259],"type":"Point"}
}