{
  "type": "Feature",
  "properties": {
    "iso:country": "GB",
    "wof:name": "MK40 3PZ",
    "wof:placetype": "postalcode"
  },
  "geometry": {"coordinates":[-0.457494,52.137924],"type":"Point"}
}
