{
  "type": "Feature",
  "properties": {
    "iso:country":"GB",
    "wof:name":"MK40 3PZ",
    "wof:placetype":"postalcode"
},
  "geometry": {"coordinates":[-0.45749391851045,52.13792370507348],"type":"Point"}
}