{
  "type": "Feature",
  "properties": {
    "iso:country": "GB",
    "wof:name": "CT4 7RJ",
    "wof:placetype": "postalcode"
  },
  "geometry": {"coordinates":[0.999425,51.2536],"type":"Point"}
}
