{
  "type": "Feature",
  "properties": {
    "date:inception_lower": "1980-01-01",
    "date:inception_upper": "1980-01-01",
    "iso:country": "GB",
    "wof:name": "CT4 7RJ",
    "wof:placetype": "postalcode"
  },
  "geometry": {"coordinates":[0.999736,51.253529],"type":"Point"}
}
