{
  "type": "Feature",
  "properties": {
    "iso:country":"GB",
    "wof:name":"CT4 7RJ",
    "wof:placetype":"postalcode"
},
  "geometry": {"coordinates":[0.99935213266454,51.2535983120728],"type":"Point"}
}