{
  "type": "Feature",
  "properties": {
    "iso:country":"GB",
    "wof:name":"BS23 3EY",
    "wof:placetype":"postalcode"
},
  "geometry": {"coordinates":[-2.96297290879579,51.34622420710816],"type":"Point"}
}