{
  "type": "Feature",
  "properties": {
    "iso:country":"GB",
    "wof:name":"SO14 0QN",
    "wof:placetype":"postalcode"
},
  "geometry": {"coordinates":[-1.3979180005193,50.91441707468827],"type":"Point"}
}