{
  "type": "Feature",
  "properties": {
    "date:inception_lower":"2000-06-01",
    "date:inception_upper":"2000-06-30",
    "iso:country":"GB",
    "wof:name":"SO14 0QN",
    "wof:placetype":"postalcode"
},
  "geometry": {"coordinates":[-1.397918,50.914417],"type":"Point"}
}