{
  "type": "Feature",
  "properties": {
    "iso:country": "GB",
    "wof:name": "PO33 1YW",
    "wof:placetype": "postalcode"
  },
  "geometry": {"coordinates":[-1.121026,50.692267],"type":"Point"}
}
