{
  "type": "Feature",
  "properties": {
    "iso:country":"GB",
    "wof:name":"PO33 1YW",
    "wof:placetype":"postalcode"
},
  "geometry": {"coordinates":[-1.12127246443669,50.69194522525103],"type":"Point"}
}