{
  "type": "Feature",
  "properties": {
    "date:inception_lower":"2012-12-01",
    "date:inception_upper":"2012-12-31",
    "iso:country":"GB",
    "wof:name":"PH10 7FE",
    "wof:placetype":"postalcode"
},
  "geometry": {"coordinates":[-3.326608,56.596314],"type":"Point"}
}