{
  "type": "Feature",
  "properties": {
    "iso:country":"GB",
    "wof:name":"PH10 7FE",
    "wof:placetype":"postalcode"
},
  "geometry": {"coordinates":[-3.32660794075683,56.59631402662944],"type":"Point"}
}