{
  "type": "Feature",
  "properties": {
    "date:inception_lower": "1999-06-01",
    "date:inception_upper": "1999-06-01",
    "iso:country": "GB",
    "wof:name": "NP10 9EJ",
    "wof:placetype": "postalcode"
  },
  "geometry": {"coordinates":[-3.051067,51.583868],"type":"Point"}
}
