{
  "type": "Feature",
  "properties": {
    "iso:country":"GB",
    "wof:name":"NP10 9EJ",
    "wof:placetype":"postalcode"
},
  "geometry": {"coordinates":[-3.05106696742919,51.58386777089532],"type":"Point"}
}