{
  "type": "Feature",
  "properties": {
    "date:inception_lower":"1980-01-01",
    "date:inception_upper":"1980-01-31",
    "iso:country":"GB",
    "wof:name":"DH1 3HF",
    "wof:placetype":"postalcode"
},
  "geometry": {"coordinates":[-1.570779,54.771757],"type":"Point"}
}