{
  "type": "Feature",
  "properties": {
    "iso:country": "GB",
    "wof:name": "DH1 3HF",
    "wof:placetype": "postalcode"
  },
  "geometry": {"coordinates":[-1.570779,54.771757],"type":"Point"}
}
