{
  "type": "Feature",
  "properties": {
    "iso:country":"GB",
    "wof:name":"MK42 8NN",
    "wof:placetype":"postalcode"
},
  "geometry": {"coordinates":[-0.4842582292184,52.11698838616351],"type":"Point"}
}