{
  "type": "Feature",
  "properties": {
    "iso:country":"GB",
    "wof:name":"CM22 6JG",
    "wof:placetype":"postalcode"
},
  "geometry": {"coordinates":[0.22940426470096,51.93719054211796],"type":"Point"}
}