{
  "type": "Feature",
  "properties": {
    "date:inception_lower": "1980-01-01",
    "date:inception_upper": "1980-01-01",
    "iso:country": "GB",
    "wof:name": "CM22 6JG",
    "wof:placetype": "postalcode"
  },
  "geometry": {"coordinates":[0.229404,51.937191],"type":"Point"}
}
