{
  "type": "Feature",
  "properties": {
    "iso:country":"GB",
    "wof:name":"RG9 2JH",
    "wof:placetype":"postalcode"
},
  "geometry": {"coordinates":[-0.90694463868223,51.54142573563438],"type":"Point"}
}