{
  "type": "Feature",
  "properties": {
    "iso:country": "GB",
    "wof:name": "IV49 9DD",
    "wof:placetype": "postalcode"
  },
  "geometry": {"coordinates":[-5.893873,57.238486],"type":"Point"}
}
