{
  "type": "Feature",
  "properties": {
    "iso:country":"GB",
    "wof:name":"TR7 1HZ",
    "wof:placetype":"postalcode"
},
  "geometry": {"coordinates":[-5.08980808828361,50.41192939360748],"type":"Point"}
}