{
  "type": "Feature",
  "properties": {
    "iso:country":"GB",
    "wof:name":"W6 0DN",
    "wof:placetype":"postalcode"
},
  "geometry": {"coordinates":[-0.23173568936738,51.49588326609791],"type":"Point"}
}