{
  "type": "Feature",
  "properties": {
    "iso:country":"GB",
    "wof:name":"SO19 8NZ",
    "wof:placetype":"postalcode"
},
  "geometry": {"coordinates":[-1.3546386991793,50.90775635042494],"type":"Point"}
}