{
  "type": "Feature",
  "properties": {
    "iso:country": "GB",
    "wof:name": "SO19 8NZ",
    "wof:placetype": "postalcode"
  },
  "geometry": {"coordinates":[-1.354639,50.907756],"type":"Point"}
}
