{
  "type": "Feature",
  "properties": {
    "iso:country":"GB",
    "wof:name":"SP8 5LG",
    "wof:placetype":"postalcode"
},
  "geometry": {"coordinates":[-2.28241137085329,51.00897507495458],"type":"Point"}
}