{
  "type": "Feature",
  "properties": {
    "iso:country":"GB",
    "wof:name":"SY2 6EX",
    "wof:placetype":"postalcode"
},
  "geometry": {"coordinates":[-2.73433598263433,52.68982751303334],"type":"Point"}
}