{
  "type": "Feature",
  "properties": {
    "iso:country": "GB",
    "wof:name": "TQ2 7TL",
    "wof:placetype": "postalcode"
  },
  "geometry": {"coordinates":[-3.557204,50.493549],"type":"Point"}
}
