{
  "type": "Feature",
  "properties": {
    "date:inception_lower": "1980-01-01",
    "date:inception_upper": "1980-01-01",
    "iso:country": "GB",
    "wof:name": "EH12 8EP",
    "wof:placetype": "postalcode"
  },
  "geometry": {"coordinates":[-3.30125,55.944375],"type":"Point"}
}
