{
  "type": "Feature",
  "properties": {
    "iso:country":"GB",
    "wof:name":"SS16 5BA",
    "wof:placetype":"postalcode"
},
  "geometry": {"coordinates":[0.45563055223175,51.56374933726613],"type":"Point"}
}