{
  "type": "Feature",
  "properties": {
    "date:inception_lower": "2023-10-01",
    "date:inception_upper": "2023-10-01",
    "iso:country": "GB",
    "wof:name": "NR10 3TB",
    "wof:placetype": "postalcode"
  },
  "geometry": {"coordinates":[1.238991,52.710966],"type":"Point"}
}
