{
  "type": "Feature",
  "properties": {
    "iso:country":"GB",
    "wof:name":"N10 3NA",
    "wof:placetype":"postalcode"
},
  "geometry": {"coordinates":[-0.14517256600921,51.58760910866443],"type":"Point"}
}