{
  "type": "Feature",
  "properties": {
    "iso:country": "GB",
    "wof:name": "N10 3NA",
    "wof:placetype": "postalcode"
  },
  "geometry": {"coordinates":[-0.145058,51.587673],"type":"Point"}
}
