{
  "type": "Feature",
  "properties": {
    "iso:country": "GB",
    "wof:name": "HX3 7TZ",
    "wof:placetype": "postalcode"
  },
  "geometry": {"coordinates":[-1.808785,53.75319],"type":"Point"}
}
