{
  "type": "Feature",
  "properties": {
    "date:inception_lower":"1981-09-01",
    "date:inception_upper":"1981-09-30",
    "iso:country":"GB",
    "wof:name":"HX3 7TZ",
    "wof:placetype":"postalcode"
},
  "geometry": {"coordinates":[-1.808785,53.75319],"type":"Point"}
}