{
  "type": "Feature",
  "properties": {
    "iso:country": "GB",
    "wof:name": "DN36 4TJ",
    "wof:placetype": "postalcode"
  },
  "geometry": {"coordinates":[-0.022398,53.530138],"type":"Point"}
}
