{
  "type": "Feature",
  "properties": {
    "iso:country":"GB",
    "wof:name":"DN36 4TJ",
    "wof:placetype":"postalcode"
},
  "geometry": {"coordinates":[-0.02239771403389,53.53013843620025],"type":"Point"}
}