{
  "type": "Feature",
  "properties": {
    "iso:country": "GB",
    "wof:name": "DN6 8EA",
    "wof:placetype": "postalcode"
  },
  "geometry": {"coordinates":[-1.178415,53.587532],"type":"Point"}
}
