{
  "type": "Feature",
  "properties": {
    "date:inception_lower":"1980-01-01",
    "date:inception_upper":"1980-01-31",
    "iso:country":"GB",
    "wof:name":"DN6 8EA",
    "wof:placetype":"postalcode"
},
  "geometry": {"coordinates":[-1.178415,53.587532],"type":"Point"}
}