{
  "type": "Feature",
  "properties": {
    "iso:country":"GB",
    "wof:name":"DN6 8EA",
    "wof:placetype":"postalcode"
},
  "geometry": {"coordinates":[-1.17841536419185,53.58753242458238],"type":"Point"}
}