{
  "type": "Feature",
  "properties": {
    "iso:country":"GB",
    "wof:name":"CR4 1HP",
    "wof:placetype":"postalcode"
},
  "geometry": {"coordinates":[-0.13239617941093,51.39482211285389],"type":"Point"}
}