{
  "type": "Feature",
  "properties": {
    "iso:country":"GB",
    "wof:name":"LE12 5AW",
    "wof:placetype":"postalcode"
},
  "geometry": {"coordinates":[-1.13005018082165,52.78540140890296],"type":"Point"}
}