{
  "type": "Feature",
  "properties": {
    "date:inception_lower":"1981-06-01",
    "date:inception_upper":"1981-06-30",
    "iso:country":"GB",
    "wof:name":"LE12 5AW",
    "wof:placetype":"postalcode"
},
  "geometry": {"coordinates":[-1.13005,52.785401],"type":"Point"}
}