{
  "type": "Feature",
  "properties": {
    "iso:country": "GB",
    "wof:name": "LE12 5AW",
    "wof:placetype": "postalcode"
  },
  "geometry": {"coordinates":[-1.13005,52.785401],"type":"Point"}
}
