{
  "type": "Feature",
  "properties": {
    "iso:country":"GB",
    "wof:name":"S63 9HE",
    "wof:placetype":"postalcode"
},
  "geometry": {"coordinates":[-1.30299969760701,53.53241423106467],"type":"Point"}
}