{
  "type": "Feature",
  "properties": {
    "iso:country": "GB",
    "wof:name": "LE2 8QL",
    "wof:placetype": "postalcode"
  },
  "geometry": {"coordinates":[-1.142723,52.602765],"type":"Point"}
}
