{
  "type": "Feature",
  "properties": {
    "iso:country":"GB",
    "wof:name":"LE2 8QL",
    "wof:placetype":"postalcode"
},
  "geometry": {"coordinates":[-1.14291352565152,52.60286524950945],"type":"Point"}
}