{
  "type": "Feature",
  "properties": {
    "date:inception_lower": "1997-12-01",
    "date:inception_upper": "1997-12-01",
    "iso:country": "GB",
    "wof:name": "G33 3GB",
    "wof:placetype": "postalcode"
  },
  "geometry": {"coordinates":[-4.172026,55.864693],"type":"Point"}
}
