{
  "type": "Feature",
  "properties": {
    "iso:country": "GB",
    "wof:name": "NG5 8NR",
    "wof:placetype": "postalcode"
  },
  "geometry": {"coordinates":[-1.140718,53.005169],"type":"Point"}
}
