{
  "type": "Feature",
  "properties": {
    "iso:country":"GB",
    "wof:name":"BS31 2HE",
    "wof:placetype":"postalcode"
},
  "geometry": {"coordinates":[-2.50997398690755,51.41221297586542],"type":"Point"}
}