{
  "type": "Feature",
  "properties": {
    "date:inception_lower":"1983-07-01",
    "date:inception_upper":"1983-07-31",
    "iso:country":"GB",
    "wof:name":"KT6 6SW",
    "wof:placetype":"postalcode"
},
  "geometry": {"coordinates":[-0.30876,51.389704],"type":"Point"}
}