{
  "type": "Feature",
  "properties": {
    "iso:country":"GB",
    "wof:name":"HA1 3GX",
    "wof:placetype":"postalcode"
},
  "geometry": {"coordinates":[-0.31556859218726,51.57432503224353],"type":"Point"}
}