{
  "type": "Feature",
  "properties": {
    "date:inception_lower": "1980-01-01",
    "date:inception_upper": "1980-01-01",
    "iso:country": "GB",
    "wof:name": "SA11 3AF",
    "wof:placetype": "postalcode"
  },
  "geometry": {"coordinates":[-3.799727,51.660856],"type":"Point"}
}
