{
  "type": "Feature",
  "properties": {
    "iso:country":"GB",
    "wof:name":"KY16 0DZ",
    "wof:placetype":"postalcode"
},
  "geometry": {"coordinates":[-2.93303995148943,56.3756829153897],"type":"Point"}
}