{
  "type": "Feature",
  "properties": {
    "iso:country": "GB",
    "wof:name": "KY16 0DZ",
    "wof:placetype": "postalcode"
  },
  "geometry": {"coordinates":[-2.93304,56.375683],"type":"Point"}
}
