{
  "type": "Feature",
  "properties": {
    "date:inception_lower":"1981-06-01",
    "date:inception_upper":"1981-06-30",
    "iso:country":"GB",
    "wof:name":"IG8 8AG",
    "wof:placetype":"postalcode"
},
  "geometry": {"coordinates":[0.066614,51.609214],"type":"Point"}
}