{
  "type": "Feature",
  "properties": {
    "iso:country":"GB",
    "wof:name":"IG8 8AG",
    "wof:placetype":"postalcode"
},
  "geometry": {"coordinates":[0.06661356898392,51.60921404502292],"type":"Point"}
}