{
  "type": "Feature",
  "properties": {
    "iso:country": "GB",
    "wof:name": "IG8 8AG",
    "wof:placetype": "postalcode"
  },
  "geometry": {"coordinates":[0.066614,51.609214],"type":"Point"}
}
