{
  "type": "Feature",
  "properties": {
    "date:inception_lower": "2020-02-01",
    "date:inception_upper": "2020-02-01",
    "iso:country": "GB",
    "wof:name": "SK13 6AD",
    "wof:placetype": "postalcode"
  },
  "geometry": {"coordinates":[-1.97067,53.452896],"type":"Point"}
}
