{
  "type": "Feature",
  "properties": {
    "iso:country": "GB",
    "wof:name": "BA3 4AS",
    "wof:placetype": "postalcode"
  },
  "geometry": {"coordinates":[-2.47455,51.275165],"type":"Point"}
}
