{
  "type": "Feature",
  "properties": {
    "iso:country":"GB",
    "wof:name":"BA3 4AS",
    "wof:placetype":"postalcode"
},
  "geometry": {"coordinates":[-2.4745501939193,51.27516535898231],"type":"Point"}
}