{
  "type": "Feature",
  "properties": {
    "date:inception_lower":"1980-01-01",
    "date:inception_upper":"1980-01-31",
    "iso:country":"GB",
    "wof:name":"EH22 5QE",
    "wof:placetype":"postalcode"
},
  "geometry": {"coordinates":[-3.039051,55.868738],"type":"Point"}
}