{
  "type": "Feature",
  "properties": {
    "iso:country": "GB",
    "wof:name": "EH22 5QE",
    "wof:placetype": "postalcode"
  },
  "geometry": {"coordinates":[-3.039051,55.868738],"type":"Point"}
}
