{
  "type": "Feature",
  "properties": {
    "date:inception_lower": "1981-06-01",
    "date:inception_upper": "1981-06-01",
    "iso:country": "GB",
    "wof:name": "PO7 8DQ",
    "wof:placetype": "postalcode"
  },
  "geometry": {"coordinates":[-1.02094,50.871875],"type":"Point"}
}
