{
  "type": "Feature",
  "properties": {
    "date:inception_lower": "1999-06-01",
    "date:inception_upper": "1999-06-01",
    "iso:country": "GB",
    "wof:name": "CH48 2JX",
    "wof:placetype": "postalcode"
  },
  "geometry": {"coordinates":[-3.168151,53.355499],"type":"Point"}
}
