{
  "type": "Feature",
  "properties": {
    "iso:country": "GB",
    "wof:name": "CH48 2JX",
    "wof:placetype": "postalcode"
  },
  "geometry": {"coordinates":[-3.168151,53.355499],"type":"Point"}
}
