{
  "type": "Feature",
  "properties": {
    "iso:country":"GB",
    "wof:name":"CH48 2JX",
    "wof:placetype":"postalcode"
},
  "geometry": {"coordinates":[-3.16815129408017,53.3554987886759],"type":"Point"}
}