{
  "type": "Feature",
  "properties": {
    "iso:country":"GB",
    "wof:name":"TQ12 6LX",
    "wof:placetype":"postalcode"
},
  "geometry": {"coordinates":[-3.65004744638183,50.52800123242546],"type":"Point"}
}