{
  "type": "Feature",
  "properties": {
    "iso:country":"GB",
    "wof:name":"SL5 9AF",
    "wof:placetype":"postalcode"
},
  "geometry": {"coordinates":[-0.6544623342154,51.40105289114307],"type":"Point"}
}