{
  "type": "Feature",
  "properties": {
    "iso:country": "GB",
    "wof:name": "CF48 1NF",
    "wof:placetype": "postalcode"
  },
  "geometry": {"coordinates":[-3.408082,51.754199],"type":"Point"}
}
