{
  "type": "Feature",
  "properties": {
    "iso:country":"GB",
    "wof:name":"CF48 1NF",
    "wof:placetype":"postalcode"
},
  "geometry": {"coordinates":[-3.40808228791608,51.75419940549713],"type":"Point"}
}