{
  "type": "Feature",
  "properties": {
    "iso:country":"GB",
    "wof:name":"N9 8PQ",
    "wof:placetype":"postalcode"
},
  "geometry": {"coordinates":[-0.04871810586356,51.63431665436561],"type":"Point"}
}