{
  "type": "Feature",
  "properties": {
    "iso:country":"GB",
    "wof:name":"SM3 8BS",
    "wof:placetype":"postalcode"
},
  "geometry": {"coordinates":[-0.21769369898191,51.35824670055826],"type":"Point"}
}