{
  "type": "Feature",
  "properties": {
    "iso:country":"GB",
    "wof:name":"SS7 2NT",
    "wof:placetype":"postalcode"
},
  "geometry": {"coordinates":[0.61306020740991,51.56230841458466],"type":"Point"}
}