{
  "type": "Feature",
  "properties": {
    "date:inception_lower": "1980-01-01",
    "date:inception_upper": "1980-01-01",
    "iso:country": "GB",
    "wof:name": "EN2 0TU",
    "wof:placetype": "postalcode"
  },
  "geometry": {"coordinates":[-0.092441,51.66507],"type":"Point"}
}
