{
  "type": "Feature",
  "properties": {
    "iso:country":"GB",
    "wof:name":"EN2 0TU",
    "wof:placetype":"postalcode"
},
  "geometry": {"coordinates":[-0.09244092358053,51.66506973678065],"type":"Point"}
}