{
  "type": "Feature",
  "properties": {
    "iso:country": "GB",
    "wof:name": "BR8 7NR",
    "wof:placetype": "postalcode"
  },
  "geometry": {"coordinates":[0.193509,51.404633],"type":"Point"}
}
