{
  "type": "Feature",
  "properties": {
    "iso:country":"GB",
    "wof:name":"DE21 4HU",
    "wof:placetype":"postalcode"
},
  "geometry": {"coordinates":[-1.44001219354097,52.93795916139078],"type":"Point"}
}