{
  "type": "Feature",
  "properties": {
    "iso:country":"GB",
    "wof:name":"LL11 5HW",
    "wof:placetype":"postalcode"
},
  "geometry": {"coordinates":[-3.07453725012295,53.10991113461804],"type":"Point"}
}