{
  "type": "Feature",
  "properties": {
    "date:inception_lower": "1980-01-01",
    "date:inception_upper": "1980-01-01",
    "iso:country": "GB",
    "wof:name": "LL11 5HW",
    "wof:placetype": "postalcode"
  },
  "geometry": {"coordinates":[-3.074537,53.109911],"type":"Point"}
}
