{
  "type": "Feature",
  "properties": {
    "iso:country":"GB",
    "wof:name":"YO22 5QJ",
    "wof:placetype":"postalcode"
},
  "geometry": {"coordinates":[-0.71846731281771,54.44573160608458],"type":"Point"}
}