{
  "type": "Feature",
  "properties": {
    "iso:country":"GB",
    "wof:name":"B20 2JJ",
    "wof:placetype":"postalcode"
},
  "geometry": {"coordinates":[-1.93101776024696,52.51793374122814],"type":"Point"}
}