{
  "type": "Feature",
  "properties": {
    "iso:country":"GB",
    "wof:name":"PL27 6LE",
    "wof:placetype":"postalcode"
},
  "geometry": {"coordinates":[-4.91412037419602,50.54517988583812],"type":"Point"}
}