{
  "type": "Feature",
  "properties": {
    "iso:country":"GB",
    "wof:name":"MK18 1TP",
    "wof:placetype":"postalcode"
},
  "geometry": {"coordinates":[-0.98006443574836,52.00457332801181],"type":"Point"}
}