{
  "type": "Feature",
  "properties": {
    "iso:country":"GB",
    "wof:name":"BL8 1EL",
    "wof:placetype":"postalcode"
},
  "geometry": {"coordinates":[-2.30738722712752,53.60591897567147],"type":"Point"}
}