{
  "type": "Feature",
  "properties": {
    "iso:country":"GB",
    "wof:name":"L3 7HP",
    "wof:placetype":"postalcode"
},
  "geometry": {"coordinates":[-2.99868787301162,53.41274222383377],"type":"Point"}
}