{
  "type": "Feature",
  "properties": {
    "date:inception_lower": "1983-01-01",
    "date:inception_upper": "1983-01-01",
    "iso:country": "GB",
    "wof:name": "L3 7HP",
    "wof:placetype": "postalcode"
  },
  "geometry": {"coordinates":[-2.998891,53.41247],"type":"Point"}
}
