{
  "type": "Feature",
  "properties": {
    "iso:country": "GB",
    "wof:name": "CA7 0BE",
    "wof:placetype": "postalcode"
  },
  "geometry": {"coordinates":[-3.176039,54.817508],"type":"Point"}
}
