{
  "type": "Feature",
  "properties": {
    "iso:country":"GB",
    "wof:name":"LA9 7QA",
    "wof:placetype":"postalcode"
},
  "geometry": {"coordinates":[-2.73867327631912,54.30782530152682],"type":"Point"}
}