{
  "type": "Feature",
  "properties": {
    "date:inception_lower": "2000-10-01",
    "date:inception_upper": "2000-10-01",
    "iso:country": "GB",
    "wof:name": "WD18 0WA",
    "wof:placetype": "postalcode"
  },
  "geometry": {"coordinates":[-0.395892,51.652338],"type":"Point"}
}
