{
  "type": "Feature",
  "properties": {
    "iso:country":"GB",
    "wof:name":"BD10 9QR",
    "wof:placetype":"postalcode"
},
  "geometry": {"coordinates":[-1.72091708250374,53.83300219048677],"type":"Point"}
}