{
  "type": "Feature",
  "properties": {
    "iso:country": "GB",
    "wof:name": "BD10 9QR",
    "wof:placetype": "postalcode"
  },
  "geometry": {"coordinates":[-1.720917,53.833002],"type":"Point"}
}
