{
  "type": "Feature",
  "properties": {
    "iso:country":"GB",
    "wof:name":"CR3 5DB",
    "wof:placetype":"postalcode"
},
  "geometry": {"coordinates":[-0.10423093458203,51.27836279460311],"type":"Point"}
}