{
  "type": "Feature",
  "properties": {
    "iso:country":"GB",
    "wof:name":"G77 6FB",
    "wof:placetype":"postalcode"
},
  "geometry": {"coordinates":[-4.34200615817633,55.76921676335452],"type":"Point"}
}