{
  "type": "Feature",
  "properties": {
    "date:inception_lower": "2000-12-01",
    "date:inception_upper": "2000-12-01",
    "iso:country": "GB",
    "wof:name": "G77 6FB",
    "wof:placetype": "postalcode"
  },
  "geometry": {"coordinates":[-4.342006,55.769217],"type":"Point"}
}
