{
  "type": "Feature",
  "properties": {
    "date:inception_lower":"1983-01-01",
    "date:inception_upper":"1983-01-31",
    "iso:country":"GB",
    "wof:name":"CF36 5SN",
    "wof:placetype":"postalcode"
},
  "geometry": {"coordinates":[-3.67869,51.486887],"type":"Point"}
}