{
  "type": "Feature",
  "properties": {
    "iso:country":"GB",
    "wof:name":"CF36 5SN",
    "wof:placetype":"postalcode"
},
  "geometry": {"coordinates":[-3.67869036218484,51.48688678216534],"type":"Point"}
}