{
  "type": "Feature",
  "properties": {
    "iso:country": "GB",
    "wof:name": "BN6 9UL",
    "wof:placetype": "postalcode"
  },
  "geometry": {"coordinates":[-0.180618,50.935124],"type":"Point"}
}
