{
  "type": "Feature",
  "properties": {
    "iso:country":"GB",
    "wof:name":"BN6 9UL",
    "wof:placetype":"postalcode"
},
  "geometry": {"coordinates":[-0.18061805930382,50.93512399419691],"type":"Point"}
}