{
  "type": "Feature",
  "properties": {
    "iso:country":"GB",
    "wof:name":"CT16 2HL",
    "wof:placetype":"postalcode"
},
  "geometry": {"coordinates":[1.2931838306509,51.14795297632055],"type":"Point"}
}