{
  "type": "Feature",
  "properties": {
    "date:inception_lower": "1980-01-01",
    "date:inception_upper": "1980-01-01",
    "iso:country": "GB",
    "wof:name": "CT16 2HL",
    "wof:placetype": "postalcode"
  },
  "geometry": {"coordinates":[1.293271,51.14794],"type":"Point"}
}
