{
  "type": "Feature",
  "properties": {
    "iso:country":"GB",
    "wof:name":"DA10 0JB",
    "wof:placetype":"postalcode"
},
  "geometry": {"coordinates":[0.306996805689,51.4445234545783],"type":"Point"}
}