{
  "type": "Feature",
  "properties": {
    "date:inception_lower":"1980-01-01",
    "date:inception_upper":"1980-01-31",
    "iso:country":"GB",
    "wof:name":"IP9 2BY",
    "wof:placetype":"postalcode"
},
  "geometry": {"coordinates":[1.078381,51.99661],"type":"Point"}
}