{
  "type": "Feature",
  "properties": {
    "iso:country":"GB",
    "wof:name":"IP9 2BY",
    "wof:placetype":"postalcode"
},
  "geometry": {"coordinates":[1.07838065501018,51.99661022812285],"type":"Point"}
}