{
  "type": "Feature",
  "properties": {
    "date:inception_lower": "1980-01-01",
    "date:inception_upper": "1980-01-01",
    "iso:country": "GB",
    "wof:name": "TA18 8AY",
    "wof:placetype": "postalcode"
  },
  "geometry": {"coordinates":[-2.79728,50.883245],"type":"Point"}
}
