{
  "type": "Feature",
  "properties": {
    "iso:country":"GB",
    "wof:name":"NP16 7EB",
    "wof:placetype":"postalcode"
},
  "geometry": {"coordinates":[-2.66165228591432,51.64860675906246],"type":"Point"}
}