{
  "type": "Feature",
  "properties": {
    "iso:country": "GB",
    "wof:name": "NP16 7EB",
    "wof:placetype": "postalcode"
  },
  "geometry": {"coordinates":[-2.661652,51.648607],"type":"Point"}
}
