{
  "type": "Feature",
  "properties": {
    "iso:country":"GB",
    "wof:name":"SE3 7BH",
    "wof:placetype":"postalcode"
},
  "geometry": {"coordinates":[0.02355293204492,51.47383338498559],"type":"Point"}
}