{
  "type": "Feature",
  "properties": {
    "date:inception_lower": "1981-06-01",
    "date:inception_upper": "1981-06-01",
    "iso:country": "GB",
    "wof:name": "SE3 7BH",
    "wof:placetype": "postalcode"
  },
  "geometry": {"coordinates":[0.023553,51.473833],"type":"Point"}
}
