{
  "type": "Feature",
  "properties": {
    "iso:country":"GB",
    "wof:name":"M13 9PY",
    "wof:placetype":"postalcode"
},
  "geometry": {"coordinates":[-2.23222631560093,53.46735307003519],"type":"Point"}
}