{
  "type": "Feature",
  "properties": {
    "iso:country": "GB",
    "wof:name": "M13 9PY",
    "wof:placetype": "postalcode"
  },
  "geometry": {"coordinates":[-2.231954,53.467469],"type":"Point"}
}
