{
  "type": "Feature",
  "properties": {
    "date:inception_lower": "2008-11-01",
    "date:inception_upper": "2008-11-01",
    "iso:country": "GB",
    "wof:name": "M13 9PY",
    "wof:placetype": "postalcode"
  },
  "geometry": {"coordinates":[-2.231954,53.467469],"type":"Point"}
}
