{
  "type": "Feature",
  "properties": {
    "iso:country":"GB",
    "wof:name":"EC1A 7JA",
    "wof:placetype":"postalcode"
},
  "geometry": {"coordinates":[-0.09859035611259,51.5194288845558],"type":"Point"}
}