{
  "type": "Feature",
  "properties": {
    "date:inception_lower":"1980-01-01",
    "date:inception_upper":"1980-01-31",
    "iso:country":"GB",
    "wof:name":"BA11 4JZ",
    "wof:placetype":"postalcode"
},
  "geometry": {"coordinates":[-2.332241,51.225769],"type":"Point"}
}