{
  "type": "Feature",
  "properties": {
    "iso:country":"GB",
    "wof:name":"N14 7HL",
    "wof:placetype":"postalcode"
},
  "geometry": {"coordinates":[-0.12574711587786,51.61975405761377],"type":"Point"}
}