{
  "type": "Feature",
  "properties": {
    "iso:country":"GB",
    "wof:name":"BR7 5AF",
    "wof:placetype":"postalcode"
},
  "geometry": {"coordinates":[0.06734003082794,51.41800623279557],"type":"Point"}
}