{
  "type": "Feature",
  "properties": {
    "iso:country": "GB",
    "wof:name": "LS17 9DH",
    "wof:placetype": "postalcode"
  },
  "geometry": {"coordinates":[-1.443037,53.883545],"type":"Point"}
}
