{
  "type": "Feature",
  "properties": {
    "date:inception_lower":"2001-06-01",
    "date:inception_upper":"2001-06-30",
    "iso:country":"GB",
    "wof:name":"DN7 6TR",
    "wof:placetype":"postalcode"
},
  "geometry": {"coordinates":[-1.009572,53.58211],"type":"Point"}
}