{
  "type": "Feature",
  "properties": {
    "iso:country": "GB",
    "wof:name": "DN7 6TR",
    "wof:placetype": "postalcode"
  },
  "geometry": {"coordinates":[-1.009572,53.58211],"type":"Point"}
}
