{
  "type": "Feature",
  "properties": {
    "iso:country":"GB",
    "wof:name":"DN7 6TR",
    "wof:placetype":"postalcode"
},
  "geometry": {"coordinates":[-1.0095724696984,53.5821104675361],"type":"Point"}
}