{
  "type": "Feature",
  "properties": {
    "date:inception_lower": "2023-04-01",
    "date:inception_upper": "2023-04-01",
    "iso:country": "GB",
    "wof:name": "CF83 1BL",
    "wof:placetype": "postalcode"
  },
  "geometry": {"coordinates":[-3.225979,51.56132],"type":"Point"}
}
