{
  "type": "Feature",
  "properties": {
    "iso:country": "GB",
    "wof:name": "CO10 3EA",
    "wof:placetype": "postalcode"
  },
  "geometry": {"coordinates":[0.754882,52.044786],"type":"Point"}
}
