{
  "type": "Feature",
  "properties": {
    "iso:country": "GB",
    "wof:name": "PR4 3AQ",
    "wof:placetype": "postalcode"
  },
  "geometry": {"coordinates":[-2.884784,53.788689],"type":"Point"}
}
