{
  "type": "Feature",
  "properties": {
    "iso:country":"GB",
    "wof:name":"PR4 3AQ",
    "wof:placetype":"postalcode"
},
  "geometry": {"coordinates":[-2.88478435003613,53.78868873381339],"type":"Point"}
}