{
  "type": "Feature",
  "properties": {
    "iso:country":"GB",
    "wof:name":"G52 2AT",
    "wof:placetype":"postalcode"
},
  "geometry": {"coordinates":[-4.35783712327255,55.84967794883222],"type":"Point"}
}