{
  "type": "Feature",
  "properties": {
    "iso:country": "GB",
    "wof:name": "ST1 3GJ",
    "wof:placetype": "postalcode"
  },
  "geometry": {"coordinates":[-2.165953,53.02063],"type":"Point"}
}
