{
  "type": "Feature",
  "properties": {
    "iso:country":"GB",
    "wof:name":"BB5 6RS",
    "wof:placetype":"postalcode"
},
  "geometry": {"coordinates":[-2.3584884091135,53.75254480751244],"type":"Point"}
}