{
  "type": "Feature",
  "properties": {
    "iso:country":"GB",
    "wof:name":"BB2 3LQ",
    "wof:placetype":"postalcode"
},
  "geometry": {"coordinates":[-2.47937669653691,53.73159315808524],"type":"Point"}
}