{
  "type": "Feature",
  "properties": {
    "iso:country":"GB",
    "wof:name":"RG6 7HT",
    "wof:placetype":"postalcode"
},
  "geometry": {"coordinates":[-0.92587944027856,51.44082013250555],"type":"Point"}
}