{
  "type": "Feature",
  "properties": {
    "date:inception_lower": "1980-01-01",
    "date:inception_upper": "1980-01-01",
    "iso:country": "GB",
    "wof:name": "PO41 0PZ",
    "wof:placetype": "postalcode"
  },
  "geometry": {"coordinates":[-1.495104,50.706024],"type":"Point"}
}
