{
  "type": "Feature",
  "properties": {
    "iso:country": "GB",
    "wof:name": "NE1 3AH",
    "wof:placetype": "postalcode"
  },
  "geometry": {"coordinates":[-1.617533,54.96608],"type":"Point"}
}
