{
  "type": "Feature",
  "properties": {
    "date:inception_lower":"1980-01-01",
    "date:inception_upper":"1980-01-31",
    "iso:country":"GB",
    "wof:name":"EX39 3NP",
    "wof:placetype":"postalcode"
},
  "geometry": {"coordinates":[-4.21739,51.026129],"type":"Point"}
}