{
  "type": "Feature",
  "properties": {
    "iso:country":"GB",
    "wof:name":"EX39 3NP",
    "wof:placetype":"postalcode"
},
  "geometry": {"coordinates":[-4.21739006858727,51.02612896048946],"type":"Point"}
}