{
  "type": "Feature",
  "properties": {
    "iso:country":"GB",
    "wof:name":"NR17 2LA",
    "wof:placetype":"postalcode"
},
  "geometry": {"coordinates":[1.04603977623524,52.53333666467724],"type":"Point"}
}