{
  "type": "Feature",
  "properties": {
    "iso:country":"GB",
    "wof:name":"N1 9DF",
    "wof:placetype":"postalcode"
},
  "geometry": {"coordinates":[-0.11618782739846,51.53275198283495],"type":"Point"}
}