{
  "type": "Feature",
  "properties": {
    "iso:country": "GB",
    "wof:name": "N1 9DF",
    "wof:placetype": "postalcode"
  },
  "geometry": {"coordinates":[-0.116188,51.532752],"type":"Point"}
}
