{
  "type": "Feature",
  "properties": {
    "iso:country":"GB",
    "wof:name":"EN9 1PH",
    "wof:placetype":"postalcode"
},
  "geometry": {"coordinates":[0.00114355438641,51.68632610192683],"type":"Point"}
}