{
  "type": "Feature",
  "properties": {
    "iso:country": "GB",
    "wof:name": "YO43 4RL",
    "wof:placetype": "postalcode"
  },
  "geometry": {"coordinates":[-0.592801,53.855898],"type":"Point"}
}
