{
  "type": "Feature",
  "properties": {
    "iso:country":"GB",
    "wof:name":"YO43 4RL",
    "wof:placetype":"postalcode"
},
  "geometry": {"coordinates":[-0.59280153755802,53.85589823237981],"type":"Point"}
}