{
  "type": "Feature",
  "properties": {
    "date:inception_lower": "1980-01-01",
    "date:inception_upper": "1980-01-01",
    "iso:country": "GB",
    "wof:name": "DN14 6SF",
    "wof:placetype": "postalcode"
  },
  "geometry": {"coordinates":[-0.87761,53.704208],"type":"Point"}
}
