{
  "type": "Feature",
  "properties": {
    "iso:country":"GB",
    "wof:name":"TN9 1LR",
    "wof:placetype":"postalcode"
},
  "geometry": {"coordinates":[0.27962713580585,51.19856188442986],"type":"Point"}
}