{
  "type": "Feature",
  "properties": {
    "iso:country":"GB",
    "wof:name":"DG8 9HG",
    "wof:placetype":"postalcode"
},
  "geometry": {"coordinates":[-4.44406244171748,54.86736555210172],"type":"Point"}
}