{
  "type": "Feature",
  "properties": {
    "iso:country":"GB",
    "wof:name":"EX36 3AE",
    "wof:placetype":"postalcode"
},
  "geometry": {"coordinates":[-3.83546267702198,51.01749371831185],"type":"Point"}
}