{
  "type": "Feature",
  "properties": {
    "date:inception_lower": "2018-03-01",
    "date:inception_upper": "2018-03-01",
    "iso:country": "GB",
    "wof:name": "DN3 3FQ",
    "wof:placetype": "postalcode"
  },
  "geometry": {"coordinates":[-1.035934,53.534365],"type":"Point"}
}
