{
  "type": "Feature",
  "properties": {
    "iso:country":"GB",
    "wof:name":"N18 1LS",
    "wof:placetype":"postalcode"
},
  "geometry": {"coordinates":[-0.07669137743951,51.6200396685233],"type":"Point"}
}