{
  "type": "Feature",
  "properties": {
    "iso:country":"GB",
    "wof:name":"HP17 8DS",
    "wof:placetype":"postalcode"
},
  "geometry": {"coordinates":[-0.92311573726475,51.77357611029304],"type":"Point"}
}