{
  "type": "Feature",
  "properties": {
    "date:inception_lower": "1980-01-01",
    "date:inception_upper": "1980-01-01",
    "iso:country": "GB",
    "wof:name": "ST5 8LB",
    "wof:placetype": "postalcode"
  },
  "geometry": {"coordinates":[-2.228854,53.04129],"type":"Point"}
}
