{
  "type": "Feature",
  "properties": {
    "iso:country":"GB",
    "wof:name":"ST5 8LB",
    "wof:placetype":"postalcode"
},
  "geometry": {"coordinates":[-2.22886865201783,53.04126354828482],"type":"Point"}
}