{
  "type": "Feature",
  "properties": {
    "iso:country":"GB",
    "wof:name":"CB9 7SW",
    "wof:placetype":"postalcode"
},
  "geometry": {"coordinates":[0.39541090507546,52.09471576292119],"type":"Point"}
}