{
  "type": "Feature",
  "properties": {
    "iso:country": "GB",
    "wof:name": "CB9 7SW",
    "wof:placetype": "postalcode"
  },
  "geometry": {"coordinates":[0.395441,52.094728],"type":"Point"}
}
