{
  "type": "Feature",
  "properties": {
    "date:inception_lower": "1984-10-01",
    "date:inception_upper": "1984-10-01",
    "iso:country": "GB",
    "wof:name": "OX1 1SN",
    "wof:placetype": "postalcode"
  },
  "geometry": {"coordinates":[-1.25788,51.746584],"type":"Point"}
}
