{
  "type": "Feature",
  "properties": {
    "iso:country":"GB",
    "wof:name":"OX1 1SN",
    "wof:placetype":"postalcode"
},
  "geometry": {"coordinates":[-1.25788031686124,51.74658410174308],"type":"Point"}
}