{
  "type": "Feature",
  "properties": {
    "iso:country":"GB",
    "wof:name":"WR5 3JH",
    "wof:placetype":"postalcode"
},
  "geometry": {"coordinates":[-2.22395275111372,52.14007172514284],"type":"Point"}
}