{
  "type": "Feature",
  "properties": {
    "iso:country":"GB",
    "wof:name":"HU5 4NN",
    "wof:placetype":"postalcode"
},
  "geometry": {"coordinates":[-0.38694625156254,53.76936837212681],"type":"Point"}
}