{
  "type": "Feature",
  "properties": {
    "date:inception_lower": "2004-05-01",
    "date:inception_upper": "2004-05-01",
    "iso:country": "GB",
    "wof:name": "HR1 2NE",
    "wof:placetype": "postalcode"
  },
  "geometry": {"coordinates":[-2.709078,52.050582],"type":"Point"}
}
