{
  "type": "Feature",
  "properties": {
    "iso:country": "GB",
    "wof:name": "DA1 2EH",
    "wof:placetype": "postalcode"
  },
  "geometry": {"coordinates":[0.21322,51.445334],"type":"Point"}
}
