{
  "type": "Feature",
  "properties": {
    "iso:country":"GB",
    "wof:name":"E3 4PH",
    "wof:placetype":"postalcode"
},
  "geometry": {"coordinates":[-0.03266608392013,51.52531092781867],"type":"Point"}
}