{
  "type": "Feature",
  "properties": {
    "iso:country":"GB",
    "wof:name":"S43 3EB",
    "wof:placetype":"postalcode"
},
  "geometry": {"coordinates":[-1.36974854855733,53.24799465360083],"type":"Point"}
}