{
  "type": "Feature",
  "properties": {
    "date:inception_lower":"1981-06-01",
    "date:inception_upper":"1981-06-30",
    "iso:country":"GB",
    "wof:name":"SE26 4TH",
    "wof:placetype":"postalcode"
},
  "geometry": {"coordinates":[-0.039215,51.429181],"type":"Point"}
}