{
  "type": "Feature",
  "properties": {
    "iso:country":"GB",
    "wof:name":"SE13 7LN",
    "wof:placetype":"postalcode"
},
  "geometry": {"coordinates":[-0.02269096385298,51.45404708167045],"type":"Point"}
}