{
  "type": "Feature",
  "properties": {
    "date:inception_lower":"1995-12-01",
    "date:inception_upper":"1995-12-31",
    "iso:country":"GB",
    "wof:name":"SE13 7LN",
    "wof:placetype":"postalcode"
},
  "geometry": {"coordinates":[-0.022993,51.454115],"type":"Point"}
}