{
  "type": "Feature",
  "properties": {
    "iso:country": "GB",
    "wof:name": "SE13 7LN",
    "wof:placetype": "postalcode"
  },
  "geometry": {"coordinates":[-0.022993,51.454115],"type":"Point"}
}
