{
  "type": "Feature",
  "properties": {
    "date:inception_lower": "1980-01-01",
    "date:inception_upper": "1980-01-01",
    "iso:country": "GB",
    "wof:name": "CR3 7EE",
    "wof:placetype": "postalcode"
  },
  "geometry": {"coordinates":[-0.032723,51.285456],"type":"Point"}
}
