{
  "type": "Feature",
  "properties": {
    "iso:country":"GB",
    "wof:name":"CR3 7EE",
    "wof:placetype":"postalcode"
},
  "geometry": {"coordinates":[-0.03272292999027,51.28545643465643],"type":"Point"}
}