{
  "type": "Feature",
  "properties": {
    "iso:country": "GB",
    "wof:name": "CV23 0GG",
    "wof:placetype": "postalcode"
  },
  "geometry": {"coordinates":[-1.239398,52.399295],"type":"Point"}
}
