{
  "type": "Feature",
  "properties": {
    "date:inception_lower": "1980-01-01",
    "date:inception_upper": "1980-01-01",
    "iso:country": "GB",
    "wof:name": "PL30 5AR",
    "wof:placetype": "postalcode"
  },
  "geometry": {"coordinates":[-4.703109,50.414081],"type":"Point"}
}
