{
  "type": "Feature",
  "properties": {
    "iso:country":"GB",
    "wof:name":"PL30 5AR",
    "wof:placetype":"postalcode"
},
  "geometry": {"coordinates":[-4.7031089233471,50.41408102282854],"type":"Point"}
}