{
  "type": "Feature",
  "properties": {
    "iso:country": "GB",
    "wof:name": "TN38 0UQ",
    "wof:placetype": "postalcode"
  },
  "geometry": {"coordinates":[0.543729,50.858898],"type":"Point"}
}
