{
  "type": "Feature",
  "properties": {
    "iso:country":"GB",
    "wof:name":"TN38 0UQ",
    "wof:placetype":"postalcode"
},
  "geometry": {"coordinates":[0.54372907763908,50.8588975736671],"type":"Point"}
}