{
  "type": "Feature",
  "properties": {
    "iso:country": "GB",
    "wof:name": "SA13 1EZ",
    "wof:placetype": "postalcode"
  },
  "geometry": {"coordinates":[-3.779704,51.592932],"type":"Point"}
}
