{
  "type": "Feature",
  "properties": {
    "date:inception_lower": "1980-01-01",
    "date:inception_upper": "1980-01-01",
    "iso:country": "GB",
    "wof:name": "SA13 1EZ",
    "wof:placetype": "postalcode"
  },
  "geometry": {"coordinates":[-3.779704,51.592932],"type":"Point"}
}
