{
  "type": "Feature",
  "properties": {
    "iso:country":"GB",
    "wof:name":"L19 9DY",
    "wof:placetype":"postalcode"
},
  "geometry": {"coordinates":[-2.91543437665854,53.36602012279275],"type":"Point"}
}