{
  "type": "Feature",
  "properties": {
    "iso:country":"GB",
    "wof:name":"LA13 9LL",
    "wof:placetype":"postalcode"
},
  "geometry": {"coordinates":[-3.20595832402698,54.12332785908228],"type":"Point"}
}