{
  "type": "Feature",
  "properties": {
    "iso:country":"GB",
    "wof:name":"GL15 4AA",
    "wof:placetype":"postalcode"
},
  "geometry": {"coordinates":[-2.47259368343313,51.76022902490166],"type":"Point"}
}