{
  "type": "Feature",
  "properties": {
    "iso:country": "GB",
    "wof:name": "PL31 1PY",
    "wof:placetype": "postalcode"
  },
  "geometry": {"coordinates":[-4.733206,50.462715],"type":"Point"}
}
