{
  "type": "Feature",
  "properties": {
    "date:inception_lower": "2004-04-01",
    "date:inception_upper": "2004-04-01",
    "iso:country": "GB",
    "wof:name": "SP11 6JR",
    "wof:placetype": "postalcode"
  },
  "geometry": {"coordinates":[-1.474761,51.24606],"type":"Point"}
}
