{
  "type": "Feature",
  "properties": {
    "iso:country":"GB",
    "wof:name":"PE21 6DN",
    "wof:placetype":"postalcode"
},
  "geometry": {"coordinates":[-0.01434474854849,52.97008819342454],"type":"Point"}
}