{
  "type": "Feature",
  "properties": {
    "iso:country": "GB",
    "wof:name": "PE21 6DN",
    "wof:placetype": "postalcode"
  },
  "geometry": {"coordinates":[-0.014282,52.969994],"type":"Point"}
}
