{
  "type": "Feature",
  "properties": {
    "iso:country": "GB",
    "wof:name": "CM77 7QB",
    "wof:placetype": "postalcode"
  },
  "geometry": {"coordinates":[0.535135,51.863419],"type":"Point"}
}
