{
  "type": "Feature",
  "properties": {
    "iso:country":"GB",
    "wof:name":"HU7 0WT",
    "wof:placetype":"postalcode"
},
  "geometry": {"coordinates":[-0.34327379028643,53.77716863309359],"type":"Point"}
}