{
  "type": "Feature",
  "properties": {
    "date:inception_lower":"1980-01-01",
    "date:inception_upper":"1980-01-31",
    "iso:country":"GB",
    "wof:name":"YO16 4QL",
    "wof:placetype":"postalcode"
},
  "geometry": {"coordinates":[-0.20967,54.094361],"type":"Point"}
}