{
  "type": "Feature",
  "properties": {
    "iso:country": "GB",
    "wof:name": "YO16 4QL",
    "wof:placetype": "postalcode"
  },
  "geometry": {"coordinates":[-0.20967,54.094361],"type":"Point"}
}
