{
  "type": "Feature",
  "properties": {
    "iso:country":"GB",
    "wof:name":"YO16 4QL",
    "wof:placetype":"postalcode"
},
  "geometry": {"coordinates":[-0.20966975280747,54.09436068653554],"type":"Point"}
}