{
  "type": "Feature",
  "properties": {
    "date:inception_lower": "2024-04-01",
    "date:inception_upper": "2024-04-01",
    "iso:country": "GB",
    "wof:name": "BS21 7GH",
    "wof:placetype": "postalcode"
  },
  "geometry": {"coordinates":[-2.844205,51.453117],"type":"Point"}
}
