{
  "type": "Feature",
  "properties": {
    "iso:country": "GB",
    "wof:name": "NG10 4FJ",
    "wof:placetype": "postalcode"
  },
  "geometry": {"coordinates":[-1.289281,52.90819],"type":"Point"}
}
