{
  "type": "Feature",
  "properties": {
    "date:inception_lower": "1983-03-01",
    "date:inception_upper": "1983-03-01",
    "iso:country": "GB",
    "wof:name": "EX2 9RR",
    "wof:placetype": "postalcode"
  },
  "geometry": {"coordinates":[-3.55437,50.704078],"type":"Point"}
}
