{
  "type": "Feature",
  "properties": {
    "iso:country":"GB",
    "wof:name":"G15 7TY",
    "wof:placetype":"postalcode"
},
  "geometry": {"coordinates":[-4.37420730151584,55.91294208578333],"type":"Point"}
}