{
  "type": "Feature",
  "properties": {
    "iso:country":"GB",
    "wof:name":"HS1 2XN",
    "wof:placetype":"postalcode"
},
  "geometry": {"coordinates":[-6.39151471042399,58.20837868119253],"type":"Point"}
}