{
  "type": "Feature",
  "properties": {
    "date:inception_lower": "2006-07-01",
    "date:inception_upper": "2006-07-01",
    "iso:country": "GB",
    "wof:name": "HS1 2XN",
    "wof:placetype": "postalcode"
  },
  "geometry": {"coordinates":[-6.391515,58.208379],"type":"Point"}
}
