{
  "type": "Feature",
  "properties": {
    "iso:country": "GB",
    "wof:name": "HU3 4UU",
    "wof:placetype": "postalcode"
  },
  "geometry": {"coordinates":[-0.375325,53.730974],"type":"Point"}
}
