{
  "type": "Feature",
  "properties": {
    "iso:country": "GB",
    "wof:name": "BS48 4LZ",
    "wof:placetype": "postalcode"
  },
  "geometry": {"coordinates":[-2.760719,51.426553],"type":"Point"}
}
