{
  "type": "Feature",
  "properties": {
    "iso:country": "GB",
    "wof:name": "WS2 0BX",
    "wof:placetype": "postalcode"
  },
  "geometry": {"coordinates":[-2.019822,52.584612],"type":"Point"}
}
