{
  "type": "Feature",
  "properties": {
    "date:inception_lower": "2022-11-01",
    "date:inception_upper": "2022-11-01",
    "iso:country": "GB",
    "wof:name": "TF2 9XZ",
    "wof:placetype": "postalcode"
  },
  "geometry": {"coordinates":[-2.410973,52.687602],"type":"Point"}
}
