{
  "type": "Feature",
  "properties": {
    "iso:country":"GB",
    "wof:name":"NG2 7PZ",
    "wof:placetype":"postalcode"
},
  "geometry": {"coordinates":[-1.13162927748123,52.93462328495291],"type":"Point"}
}