{
  "type": "Feature",
  "properties": {
    "iso:country":"GB",
    "wof:name":"LS6 1AJ",
    "wof:placetype":"postalcode"
},
  "geometry": {"coordinates":[-1.56665295258813,53.80886114908792],"type":"Point"}
}