{
  "type": "Feature",
  "properties": {
    "iso:country":"GB",
    "wof:name":"DA7 4PP",
    "wof:placetype":"postalcode"
},
  "geometry": {"coordinates":[0.13574411228105,51.46552124113521],"type":"Point"}
}