{
  "type": "Feature",
  "properties": {
    "iso:country":"GB",
    "wof:name":"EH41 3QS",
    "wof:placetype":"postalcode"
},
  "geometry": {"coordinates":[-2.77323561160536,55.95938760223881],"type":"Point"}
}