{
  "type": "Feature",
  "properties": {
    "date:inception_lower": "1995-12-01",
    "date:inception_upper": "1995-12-01",
    "iso:country": "GB",
    "wof:name": "WA7 6QR",
    "wof:placetype": "postalcode"
  },
  "geometry": {"coordinates":[-2.667888,53.335168],"type":"Point"}
}
