{
  "type": "Feature",
  "properties": {
    "iso:country":"GB",
    "wof:name":"WA7 6QR",
    "wof:placetype":"postalcode"
},
  "geometry": {"coordinates":[-2.66788819287086,53.33516793016624],"type":"Point"}
}