{
  "type": "Feature",
  "properties": {
    "iso:country":"GB",
    "wof:name":"SK15 3SD",
    "wof:placetype":"postalcode"
},
  "geometry": {"coordinates":[-2.03059521865709,53.50155150272385],"type":"Point"}
}