{
  "type": "Feature",
  "properties": {
    "iso:country":"GB",
    "wof:name":"SY3 0JH",
    "wof:placetype":"postalcode"
},
  "geometry": {"coordinates":[-2.77612088852589,52.67837783089767],"type":"Point"}
}