{
  "type": "Feature",
  "properties": {
    "iso:country":"GB",
    "wof:name":"CB4 3AN",
    "wof:placetype":"postalcode"
},
  "geometry": {"coordinates":[0.11948445790359,52.21304808257819],"type":"Point"}
}