{
  "type": "Feature",
  "properties": {
    "iso:country": "GB",
    "wof:name": "TN39 4FS",
    "wof:placetype": "postalcode"
  },
  "geometry": {"coordinates":[0.421325,50.846343],"type":"Point"}
}
