{
  "type": "Feature",
  "properties": {
    "iso:country":"GB",
    "wof:name":"DD5 3ET",
    "wof:placetype":"postalcode"
},
  "geometry": {"coordinates":[-2.86865294565054,56.47837594624697],"type":"Point"}
}