{
  "type": "Feature",
  "properties": {
    "iso:country": "GB",
    "wof:name": "BN9 0FB",
    "wof:placetype": "postalcode"
  },
  "geometry": {"coordinates":[0.061014,50.788303],"type":"Point"}
}
