{
  "type": "Feature",
  "properties": {
    "date:inception_lower": "1990-02-01",
    "date:inception_upper": "1990-02-01",
    "iso:country": "GB",
    "wof:name": "L36 4QR",
    "wof:placetype": "postalcode"
  },
  "geometry": {"coordinates":[-2.852934,53.404479],"type":"Point"}
}
