{
  "type": "Feature",
  "properties": {
    "iso:country": "GB",
    "wof:name": "SR2 0DW",
    "wof:placetype": "postalcode"
  },
  "geometry": {"coordinates":[-1.371191,54.875859],"type":"Point"}
}
