{
  "type": "Feature",
  "properties": {
    "date:inception_lower": "1997-12-01",
    "date:inception_upper": "1997-12-01",
    "iso:country": "GB",
    "wof:name": "TF2 6NH",
    "wof:placetype": "postalcode"
  },
  "geometry": {"coordinates":[-2.447783,52.692039],"type":"Point"}
}
