{
  "type": "Feature",
  "properties": {
    "iso:country":"GB",
    "wof:name":"TF2 6NH",
    "wof:placetype":"postalcode"
},
  "geometry": {"coordinates":[-2.44778347846307,52.69203892024488],"type":"Point"}
}