{
  "type": "Feature",
  "properties": {
    "date:inception_lower":"1980-01-01",
    "date:inception_upper":"1980-01-31",
    "iso:country":"GB",
    "wof:name":"TN33 9PH",
    "wof:placetype":"postalcode"
},
  "geometry": {"coordinates":[0.398749,50.919117],"type":"Point"}
}