{
  "type": "Feature",
  "properties": {
    "date:inception_lower": "2006-10-01",
    "date:inception_upper": "2006-10-01",
    "iso:country": "GB",
    "wof:name": "PH22 1TN",
    "wof:placetype": "postalcode"
  },
  "geometry": {"coordinates":[-3.825334,57.204097],"type":"Point"}
}
