{
  "type": "Feature",
  "properties": {
    "iso:country":"GB",
    "wof:name":"NR7 9TN",
    "wof:placetype":"postalcode"
},
  "geometry": {"coordinates":[1.33615949558237,52.64696911374125],"type":"Point"}
}