{
  "type": "Feature",
  "properties": {
    "iso:country":"GB",
    "wof:name":"TA20 1BH",
    "wof:placetype":"postalcode"
},
  "geometry": {"coordinates":[-2.96302654109692,50.87813695778318],"type":"Point"}
}