{
  "type": "Feature",
  "properties": {
    "date:inception_lower":"1980-01-01",
    "date:inception_upper":"1980-01-31",
    "iso:country":"GB",
    "wof:name":"TA20 1BH",
    "wof:placetype":"postalcode"
},
  "geometry": {"coordinates":[-2.963027,50.878137],"type":"Point"}
}