{
  "type": "Feature",
  "properties": {
    "iso:country": "GB",
    "wof:name": "TA20 1BH",
    "wof:placetype": "postalcode"
  },
  "geometry": {"coordinates":[-2.963027,50.878137],"type":"Point"}
}
