{
  "type": "Feature",
  "properties": {
    "iso:country": "GB",
    "wof:name": "TR18 4DY",
    "wof:placetype": "postalcode"
  },
  "geometry": {"coordinates":[-5.536513,50.115812],"type":"Point"}
}
