{
  "type": "Feature",
  "properties": {
    "iso:country":"GB",
    "wof:name":"BN3 2WN",
    "wof:placetype":"postalcode"
},
  "geometry": {"coordinates":[-0.15702562475075,50.82221996528182],"type":"Point"}
}