{
  "type": "Feature",
  "properties": {
    "date:inception_lower":"2003-10-01",
    "date:inception_upper":"2003-10-31",
    "iso:country":"GB",
    "wof:name":"BN3 2WN",
    "wof:placetype":"postalcode"
},
  "geometry": {"coordinates":[-0.157026,50.82222],"type":"Point"}
}