{
  "type": "Feature",
  "properties": {
    "date:inception_lower": "1980-01-01",
    "date:inception_upper": "1980-01-01",
    "iso:country": "GB",
    "wof:name": "DE55 4JX",
    "wof:placetype": "postalcode"
  },
  "geometry": {"coordinates":[-1.36392,53.077703],"type":"Point"}
}
