{
  "type": "Feature",
  "properties": {
    "iso:country": "GB",
    "wof:name": "DE55 4JX",
    "wof:placetype": "postalcode"
  },
  "geometry": {"coordinates":[-1.36392,53.077703],"type":"Point"}
}
