{
  "type": "Feature",
  "properties": {
    "date:inception_lower": "2023-07-01",
    "date:inception_upper": "2023-07-01",
    "iso:country": "GB",
    "wof:name": "CB6 2UN",
    "wof:placetype": "postalcode"
  },
  "geometry": {"coordinates":[0.194489,52.389004],"type":"Point"}
}
