{
  "type": "Feature",
  "properties": {
    "iso:country":"GB",
    "wof:name":"PL9 8SE",
    "wof:placetype":"postalcode"
},
  "geometry": {"coordinates":[-4.08403690166347,50.35861225469418],"type":"Point"}
}