{
  "type": "Feature",
  "properties": {
    "date:inception_lower": "1980-01-01",
    "date:inception_upper": "1980-01-01",
    "iso:country": "GB",
    "wof:name": "NE5 1YG",
    "wof:placetype": "postalcode"
  },
  "geometry": {"coordinates":[-1.7182,55.006544],"type":"Point"}
}
