{
  "type": "Feature",
  "properties": {
    "iso:country":"GB",
    "wof:name":"NP44 2NU",
    "wof:placetype":"postalcode"
},
  "geometry": {"coordinates":[-3.00803799803004,51.66320946549217],"type":"Point"}
}