{
  "type": "Feature",
  "properties": {
    "iso:country": "GB",
    "wof:name": "NP44 2NU",
    "wof:placetype": "postalcode"
  },
  "geometry": {"coordinates":[-3.008038,51.663209],"type":"Point"}
}
