{
  "type": "Feature",
  "properties": {
    "date:inception_lower":"1980-01-01",
    "date:inception_upper":"1980-01-31",
    "iso:country":"GB",
    "wof:name":"NP44 2NU",
    "wof:placetype":"postalcode"
},
  "geometry": {"coordinates":[-3.008038,51.663209],"type":"Point"}
}