{
  "type": "Feature",
  "properties": {
    "iso:country": "GB",
    "wof:name": "WV98 1QT",
    "wof:placetype": "postalcode"
  },
  "geometry": {"coordinates":[-2.238951,52.36463],"type":"Point"}
}
