{
  "type": "Feature",
  "properties": {
    "iso:country":"GB",
    "wof:name":"LL11 3PH",
    "wof:placetype":"postalcode"
},
  "geometry": {"coordinates":[-3.07196499949055,53.05813698465873],"type":"Point"}
}