{
  "type": "Feature",
  "properties": {
    "iso:country": "GB",
    "wof:name": "RG7 4JA",
    "wof:placetype": "postalcode"
  },
  "geometry": {"coordinates":[-1.112168,51.393391],"type":"Point"}
}
