{
  "type": "Feature",
  "properties": {
    "iso:country":"GB",
    "wof:name":"RG7 4JA",
    "wof:placetype":"postalcode"
},
  "geometry": {"coordinates":[-1.11221658154531,51.39339140958553],"type":"Point"}
}