{
  "type": "Feature",
  "properties": {
    "iso:country": "GB",
    "wof:name": "TA5 2DT",
    "wof:placetype": "postalcode"
  },
  "geometry": {"coordinates":[-3.084441,51.108487],"type":"Point"}
}
