{
  "type": "Feature",
  "properties": {
    "iso:country":"GB",
    "wof:name":"TA5 2DT",
    "wof:placetype":"postalcode"
},
  "geometry": {"coordinates":[-3.08444107741336,51.10848687429404],"type":"Point"}
}