{
  "type": "Feature",
  "properties": {
    "date:inception_lower": "1980-01-01",
    "date:inception_upper": "1980-01-01",
    "iso:country": "GB",
    "wof:name": "SY10 8AW",
    "wof:placetype": "postalcode"
  },
  "geometry": {"coordinates":[-3.044661,52.82051],"type":"Point"}
}
