{
  "type": "Feature",
  "properties": {
    "iso:country":"GB",
    "wof:name":"KW15 1JU",
    "wof:placetype":"postalcode"
},
  "geometry": {"coordinates":[-2.9441552489461,58.98067546650921],"type":"Point"}
}