{
  "type": "Feature",
  "properties": {
    "iso:country": "GB",
    "wof:name": "KW15 1JU",
    "wof:placetype": "postalcode"
  },
  "geometry": {"coordinates":[-2.944155,58.980675],"type":"Point"}
}
