{
  "type": "Feature",
  "properties": {
    "date:inception_lower":"1980-01-01",
    "date:inception_upper":"1980-01-31",
    "iso:country":"GB",
    "wof:name":"UB6 9RZ",
    "wof:placetype":"postalcode"
},
  "geometry": {"coordinates":[-0.367151,51.531847],"type":"Point"}
}