{
  "type": "Feature",
  "properties": {
    "iso:country":"GB",
    "wof:name":"DD6 8LH",
    "wof:placetype":"postalcode"
},
  "geometry": {"coordinates":[-2.96695073137644,56.43083993756787],"type":"Point"}
}