{
  "type": "Feature",
  "properties": {
    "iso:country": "GB",
    "wof:name": "DD6 8LH",
    "wof:placetype": "postalcode"
  },
  "geometry": {"coordinates":[-2.966951,56.43084],"type":"Point"}
}
