{
  "type": "Feature",
  "properties": {
    "iso:country":"GB",
    "wof:name":"S5 8HB",
    "wof:placetype":"postalcode"
},
  "geometry": {"coordinates":[-1.48322326286865,53.41861664509261],"type":"Point"}
}