{
  "type": "Feature",
  "properties": {
    "iso:country":"GB",
    "wof:name":"M25 1EL",
    "wof:placetype":"postalcode"
},
  "geometry": {"coordinates":[-2.27635168513791,53.53051970077582],"type":"Point"}
}