{
  "type": "Feature",
  "properties": {
    "iso:country": "GB",
    "wof:name": "GU4 7FS",
    "wof:placetype": "postalcode"
  },
  "geometry": {"coordinates":[-0.542401,51.259378],"type":"Point"}
}
