{
  "type": "Feature",
  "properties": {
    "iso:country":"GB",
    "wof:name":"GU4 7FS",
    "wof:placetype":"postalcode"
},
  "geometry": {"coordinates":[-0.54240059840213,51.2593780229947],"type":"Point"}
}