{
  "type": "Feature",
  "properties": {
    "date:inception_lower": "2015-09-01",
    "date:inception_upper": "2015-09-01",
    "iso:country": "GB",
    "wof:name": "GU4 7FS",
    "wof:placetype": "postalcode"
  },
  "geometry": {"coordinates":[-0.542401,51.259378],"type":"Point"}
}
