{
  "type": "Feature",
  "properties": {
    "date:inception_lower": "1994-06-01",
    "date:inception_upper": "1994-06-01",
    "iso:country": "GB",
    "wof:name": "IV27 4JP",
    "wof:placetype": "postalcode"
  },
  "geometry": {"coordinates":[-5.244688,58.14791],"type":"Point"}
}
