{
  "type": "Feature",
  "properties": {
    "iso:country": "GB",
    "wof:name": "IV27 4JP",
    "wof:placetype": "postalcode"
  },
  "geometry": {"coordinates":[-5.246503,58.147399],"type":"Point"}
}
