{
  "type": "Feature",
  "properties": {
    "iso:country": "GB",
    "wof:name": "MK18 1LS",
    "wof:placetype": "postalcode"
  },
  "geometry": {"coordinates":[-0.992324,52.001631],"type":"Point"}
}
