{
  "type": "Feature",
  "properties": {
    "date:inception_lower": "1985-04-01",
    "date:inception_upper": "1985-04-01",
    "iso:country": "GB",
    "wof:name": "DE5 9TX",
    "wof:placetype": "postalcode"
  },
  "geometry": {"coordinates":[-1.386255,53.039839],"type":"Point"}
}
