{
  "type": "Feature",
  "properties": {
    "iso:country":"GB",
    "wof:name":"SW17 8EX",
    "wof:placetype":"postalcode"
},
  "geometry": {"coordinates":[-0.15037106724719,51.43919808255487],"type":"Point"}
}