{
  "type": "Feature",
  "properties": {
    "iso:country":"GB",
    "wof:name":"SO45 1WE",
    "wof:placetype":"postalcode"
},
  "geometry": {"coordinates":[-1.37215257329111,50.81736867620862],"type":"Point"}
}