{
  "type": "Feature",
  "properties": {
    "iso:country":"GB",
    "wof:name":"FK6 6BL",
    "wof:placetype":"postalcode"
},
  "geometry": {"coordinates":[-3.88227987953965,56.02103464564487],"type":"Point"}
}