{
  "type": "Feature",
  "properties": {
    "iso:country":"GB",
    "wof:name":"EN7 6LG",
    "wof:placetype":"postalcode"
},
  "geometry": {"coordinates":[-0.05096076610565,51.71005188564486],"type":"Point"}
}