{
  "type": "Feature",
  "properties": {
    "iso:country":"GB",
    "wof:name":"EX16 8EU",
    "wof:placetype":"postalcode"
},
  "geometry": {"coordinates":[-3.60231713150726,50.93825208612564],"type":"Point"}
}