{
  "type": "Feature",
  "properties": {
    "iso:country":"GB",
    "wof:name":"CB11 3QT",
    "wof:placetype":"postalcode"
},
  "geometry": {"coordinates":[0.20984651682506,51.98296182175723],"type":"Point"}
}