{
  "type": "Feature",
  "properties": {
    "iso:country":"GB",
    "wof:name":"CR0 0QZ",
    "wof:placetype":"postalcode"
},
  "geometry": {"coordinates":[-0.01592417021353,51.35077628165902],"type":"Point"}
}