{
  "type": "Feature",
  "properties": {
    "iso:country":"GB",
    "wof:name":"WA5 4JY",
    "wof:placetype":"postalcode"
},
  "geometry": {"coordinates":[-2.65348330275872,53.4311307216151],"type":"Point"}
}