{
  "type": "Feature",
  "properties": {
    "date:inception_lower": "1980-01-01",
    "date:inception_upper": "1980-01-01",
    "iso:country": "GB",
    "wof:name": "WS1 1QF",
    "wof:placetype": "postalcode"
  },
  "geometry": {"coordinates":[-1.979515,52.58445],"type":"Point"}
}
