{
  "type": "Feature",
  "properties": {
    "date:inception_lower": "1980-01-01",
    "date:inception_upper": "1980-01-01",
    "iso:country": "GB",
    "wof:name": "B67 7LF",
    "wof:placetype": "postalcode"
  },
  "geometry": {"coordinates":[-1.9834,52.495738],"type":"Point"}
}
