{
  "type": "Feature",
  "properties": {
    "iso:country":"GB",
    "wof:name":"B67 7LF",
    "wof:placetype":"postalcode"
},
  "geometry": {"coordinates":[-1.98340049735177,52.4957384779612],"type":"Point"}
}