{
  "type": "Feature",
  "properties": {
    "iso:country":"GB",
    "wof:name":"MK43 9EN",
    "wof:placetype":"postalcode"
},
  "geometry": {"coordinates":[-0.52889952076789,52.10035350737606],"type":"Point"}
}