{
  "type": "Feature",
  "properties": {
    "iso:country":"GB",
    "wof:name":"AL3 5HX",
    "wof:placetype":"postalcode"
},
  "geometry": {"coordinates":[-0.32918356796535,51.7624182114188],"type":"Point"}
}