{
  "type": "Feature",
  "properties": {
    "iso:country":"GB",
    "wof:name":"DL10 5DH",
    "wof:placetype":"postalcode"
},
  "geometry": {"coordinates":[-1.72043615239119,54.41243415385532],"type":"Point"}
}