{
  "type": "Feature",
  "properties": {
    "iso:country": "GB",
    "wof:name": "LS11 7EH",
    "wof:placetype": "postalcode"
  },
  "geometry": {"coordinates":[-1.554544,53.775013],"type":"Point"}
}
