{
  "type": "Feature",
  "properties": {
    "date:inception_lower": "2018-10-01",
    "date:inception_upper": "2018-10-01",
    "iso:country": "GB",
    "wof:name": "WV5 7BA",
    "wof:placetype": "postalcode"
  },
  "geometry": {"coordinates":[-2.288282,52.516331],"type":"Point"}
}
