{
  "type": "Feature",
  "properties": {
    "iso:country": "GB",
    "wof:name": "KA3 6EZ",
    "wof:placetype": "postalcode"
  },
  "geometry": {"coordinates":[-4.480403,55.63343],"type":"Point"}
}
