{
  "type": "Feature",
  "properties": {
    "date:inception_lower":"1980-01-01",
    "date:inception_upper":"1980-01-31",
    "iso:country":"GB",
    "wof:name":"NR6 5EY",
    "wof:placetype":"postalcode"
},
  "geometry": {"coordinates":[1.253485,52.648317],"type":"Point"}
}