{
  "type": "Feature",
  "properties": {
    "iso:country":"GB",
    "wof:name":"NR6 5EY",
    "wof:placetype":"postalcode"
},
  "geometry": {"coordinates":[1.25348445501295,52.64831675943164],"type":"Point"}
}