{
  "type": "Feature",
  "properties": {
    "iso:country":"GB",
    "wof:name":"SS9 3PP",
    "wof:placetype":"postalcode"
},
  "geometry": {"coordinates":[0.63338965987332,51.54955059430245],"type":"Point"}
}