{
  "type": "Feature",
  "properties": {
    "iso:country": "GB",
    "wof:name": "TS13 4ND",
    "wof:placetype": "postalcode"
  },
  "geometry": {"coordinates":[-0.865528,54.55329],"type":"Point"}
}
