{
  "type": "Feature",
  "properties": {
    "iso:country":"GB",
    "wof:name":"TS13 4ND",
    "wof:placetype":"postalcode"
},
  "geometry": {"coordinates":[-0.8655283215498,54.55328972852809],"type":"Point"}
}