{
  "type": "Feature",
  "properties": {
    "iso:country":"GB",
    "wof:name":"LU5 5AP",
    "wof:placetype":"postalcode"
},
  "geometry": {"coordinates":[-0.52696403886604,51.89511832169278],"type":"Point"}
}