{
  "type": "Feature",
  "properties": {
    "date:inception_lower": "2003-11-01",
    "date:inception_upper": "2003-11-01",
    "iso:country": "GB",
    "wof:name": "LU5 5AP",
    "wof:placetype": "postalcode"
  },
  "geometry": {"coordinates":[-0.526964,51.895118],"type":"Point"}
}
