{
  "type": "Feature",
  "properties": {
    "iso:country":"GB",
    "wof:name":"SS2 6EG",
    "wof:placetype":"postalcode"
},
  "geometry": {"coordinates":[0.70972870404528,51.54372842180033],"type":"Point"}
}