{
  "type": "Feature",
  "properties": {
    "iso:country":"GB",
    "wof:name":"HR6 0HD",
    "wof:placetype":"postalcode"
},
  "geometry": {"coordinates":[-2.70624555252668,52.247026535589],"type":"Point"}
}