{
  "type": "Feature",
  "properties": {
    "iso:country":"GB",
    "wof:name":"EX2 7DA",
    "wof:placetype":"postalcode"
},
  "geometry": {"coordinates":[-3.49689186006698,50.69671095609463],"type":"Point"}
}