{
  "type": "Feature",
  "properties": {
    "date:inception_lower":"1997-06-01",
    "date:inception_upper":"1997-06-30",
    "iso:country":"GB",
    "wof:name":"M17 1EZ",
    "wof:placetype":"postalcode"
},
  "geometry": {"coordinates":[-2.321861,53.474174],"type":"Point"}
}