{
  "type": "Feature",
  "properties": {
    "iso:country": "GB",
    "wof:name": "M17 1EZ",
    "wof:placetype": "postalcode"
  },
  "geometry": {"coordinates":[-2.321861,53.474174],"type":"Point"}
}
