{
  "type": "Feature",
  "properties": {
    "iso:country":"GB",
    "wof:name":"M17 1EZ",
    "wof:placetype":"postalcode"
},
  "geometry": {"coordinates":[-2.32186118685889,53.47417406675189],"type":"Point"}
}