{
  "type": "Feature",
  "properties": {
    "iso:country": "GB",
    "wof:name": "BD14 6NQ",
    "wof:placetype": "postalcode"
  },
  "geometry": {"coordinates":[-1.804601,53.782251],"type":"Point"}
}
