{
  "type": "Feature",
  "properties": {
    "iso:country": "GB",
    "wof:name": "BA22 7LE",
    "wof:placetype": "postalcode"
  },
  "geometry": {"coordinates":[-2.586071,51.045218],"type":"Point"}
}
