{
  "type": "Feature",
  "properties": {
    "iso:country":"GB",
    "wof:name":"BA22 7LE",
    "wof:placetype":"postalcode"
},
  "geometry": {"coordinates":[-2.58607117558773,51.04521784577594],"type":"Point"}
}