{
  "type": "Feature",
  "properties": {
    "iso:country": "GB",
    "wof:name": "WR6 5BH",
    "wof:placetype": "postalcode"
  },
  "geometry": {"coordinates":[-2.476843,52.159504],"type":"Point"}
}
