{
  "type": "Feature",
  "properties": {
    "iso:country":"GB",
    "wof:name":"WR6 5BH",
    "wof:placetype":"postalcode"
},
  "geometry": {"coordinates":[-2.47684256196681,52.15950362007663],"type":"Point"}
}