{
  "type": "Feature",
  "properties": {
    "iso:country": "GB",
    "wof:name": "ST14 5LA",
    "wof:placetype": "postalcode"
  },
  "geometry": {"coordinates":[-1.835547,52.953196],"type":"Point"}
}
