{
  "type": "Feature",
  "properties": {
    "iso:country":"GB",
    "wof:name":"W1K 5ED",
    "wof:placetype":"postalcode"
},
  "geometry": {"coordinates":[-0.149140269307,51.5126747525263],"type":"Point"}
}