{
  "type": "Feature",
  "properties": {
    "iso:country": "GB",
    "wof:name": "HX1 5LE",
    "wof:placetype": "postalcode"
  },
  "geometry": {"coordinates":[-1.872115,53.723596],"type":"Point"}
}
