{
  "type": "Feature",
  "properties": {
    "iso:country":"GB",
    "wof:name":"N10 2JY",
    "wof:placetype":"postalcode"
},
  "geometry": {"coordinates":[-0.13986580567344,51.59418848623653],"type":"Point"}
}