{
  "type": "Feature",
  "properties": {
    "date:inception_lower":"1980-01-01",
    "date:inception_upper":"1980-01-31",
    "iso:country":"GB",
    "wof:name":"TW11 8HB",
    "wof:placetype":"postalcode"
},
  "geometry": {"coordinates":[-0.331711,51.427315],"type":"Point"}
}