{
  "type": "Feature",
  "properties": {
    "iso:country":"GB",
    "wof:name":"BA21 4BX",
    "wof:placetype":"postalcode"
},
  "geometry": {"coordinates":[-2.63290081431815,50.94771220751979],"type":"Point"}
}