{
  "type": "Feature",
  "properties": {
    "iso:country": "GB",
    "wof:name": "BA21 4BX",
    "wof:placetype": "postalcode"
  },
  "geometry": {"coordinates":[-2.632901,50.947712],"type":"Point"}
}
