{
  "type": "Feature",
  "properties": {
    "iso:country":"GB",
    "wof:name":"LN2 1PP",
    "wof:placetype":"postalcode"
},
  "geometry": {"coordinates":[-0.53432802823073,53.2332895000381],"type":"Point"}
}