{
  "type": "Feature",
  "properties": {
    "iso:country":"GB",
    "wof:name":"BL2 3EW",
    "wof:placetype":"postalcode"
},
  "geometry": {"coordinates":[-2.40067076731727,53.60663153689546],"type":"Point"}
}