{
  "type": "Feature",
  "properties": {
    "iso:country":"GB",
    "wof:name":"ST5 3AD",
    "wof:placetype":"postalcode"
},
  "geometry": {"coordinates":[-2.21476074609896,52.99355746876451],"type":"Point"}
}