{
  "type": "Feature",
  "properties": {
    "date:inception_lower": "1983-03-01",
    "date:inception_upper": "1983-03-01",
    "iso:country": "GB",
    "wof:name": "ST5 3AD",
    "wof:placetype": "postalcode"
  },
  "geometry": {"coordinates":[-2.214761,52.993557],"type":"Point"}
}
