{
  "type": "Feature",
  "properties": {
    "date:inception_lower":"1990-02-01",
    "date:inception_upper":"1990-02-28",
    "iso:country":"GB",
    "wof:name":"OX7 4NS",
    "wof:placetype":"postalcode"
},
  "geometry": {"coordinates":[-1.427843,51.933379],"type":"Point"}
}