{
  "type": "Feature",
  "properties": {
    "iso:country":"GB",
    "wof:name":"OX7 4NS",
    "wof:placetype":"postalcode"
},
  "geometry": {"coordinates":[-1.42784267104353,51.93337885561093],"type":"Point"}
}