{
  "type": "Feature",
  "properties": {
    "iso:country": "GB",
    "wof:name": "OX7 4NS",
    "wof:placetype": "postalcode"
  },
  "geometry": {"coordinates":[-1.427843,51.933379],"type":"Point"}
}
