{
  "type": "Feature",
  "properties": {
    "iso:country":"GB",
    "wof:name":"WD3 3RQ",
    "wof:placetype":"postalcode"
},
  "geometry": {"coordinates":[-0.43317760333807,51.65369939251696],"type":"Point"}
}