{
  "type": "Feature",
  "properties": {
    "date:inception_lower": "1980-01-01",
    "date:inception_upper": "1980-01-01",
    "iso:country": "GB",
    "wof:name": "WD3 3RQ",
    "wof:placetype": "postalcode"
  },
  "geometry": {"coordinates":[-0.433109,51.653794],"type":"Point"}
}
