{
  "type": "Feature",
  "properties": {
    "iso:country": "GB",
    "wof:name": "SK10 4QW",
    "wof:placetype": "postalcode"
  },
  "geometry": {"coordinates":[-2.194045,53.303415],"type":"Point"}
}
