{
  "type": "Feature",
  "properties": {
    "iso:country": "GB",
    "wof:name": "S13 7BS",
    "wof:placetype": "postalcode"
  },
  "geometry": {"coordinates":[-1.396404,53.355909],"type":"Point"}
}
