{
  "type": "Feature",
  "properties": {
    "iso:country":"GB",
    "wof:name":"S13 7BS",
    "wof:placetype":"postalcode"
},
  "geometry": {"coordinates":[-1.39640432222835,53.35590881042125],"type":"Point"}
}