{
  "type": "Feature",
  "properties": {
    "iso:country":"GB",
    "wof:name":"B91 2QY",
    "wof:placetype":"postalcode"
},
  "geometry": {"coordinates":[-1.7606862104304,52.41264614811681],"type":"Point"}
}