{
  "type": "Feature",
  "properties": {
    "iso:country":"GB",
    "wof:name":"TQ12 5JN",
    "wof:placetype":"postalcode"
},
  "geometry": {"coordinates":[-3.57524649873768,50.49174097376284],"type":"Point"}
}