{
  "type": "Feature",
  "properties": {
    "date:inception_lower": "1980-01-01",
    "date:inception_upper": "1980-01-01",
    "iso:country": "GB",
    "wof:name": "TQ12 5JN",
    "wof:placetype": "postalcode"
  },
  "geometry": {"coordinates":[-3.575246,50.491741],"type":"Point"}
}
