{
  "type": "Feature",
  "properties": {
    "date:inception_lower": "1993-08-01",
    "date:inception_upper": "1993-08-01",
    "iso:country": "GB",
    "wof:name": "MK46 5JF",
    "wof:placetype": "postalcode"
  },
  "geometry": {"coordinates":[-0.708081,52.155491],"type":"Point"}
}
