{
  "type": "Feature",
  "properties": {
    "iso:country":"GB",
    "wof:name":"RH13 8EL",
    "wof:placetype":"postalcode"
},
  "geometry": {"coordinates":[-0.30244164899383,50.95909971596659],"type":"Point"}
}