{
  "type": "Feature",
  "properties": {
    "date:inception_lower":"2005-03-01",
    "date:inception_upper":"2005-03-31",
    "iso:country":"GB",
    "wof:name":"W5 9SL",
    "wof:placetype":"postalcode"
},
  "geometry": {"coordinates":[-0.307284,51.513328],"type":"Point"}
}