{
  "type": "Feature",
  "properties": {
    "date:inception_lower": "1996-12-01",
    "date:inception_upper": "1996-12-01",
    "iso:country": "GB",
    "wof:name": "RG31 5PJ",
    "wof:placetype": "postalcode"
  },
  "geometry": {"coordinates":[-1.043378,51.460496],"type":"Point"}
}
