{
  "type": "Feature",
  "properties": {
    "iso:country":"GB",
    "wof:name":"EN9 1SQ",
    "wof:placetype":"postalcode"
},
  "geometry": {"coordinates":[0.00744580381263,51.68424021366917],"type":"Point"}
}