{
  "type": "Feature",
  "properties": {
    "iso:country":"GB",
    "wof:name":"M6 6JF",
    "wof:placetype":"postalcode"
},
  "geometry": {"coordinates":[-2.28685117023922,53.50146237468788],"type":"Point"}
}