{
  "type": "Feature",
  "properties": {
    "iso:country": "GB",
    "wof:name": "M6 6JF",
    "wof:placetype": "postalcode"
  },
  "geometry": {"coordinates":[-2.28841,53.502572],"type":"Point"}
}
