{
  "type": "Feature",
  "properties": {
    "date:inception_lower": "2022-04-01",
    "date:inception_upper": "2022-04-01",
    "iso:country": "GB",
    "wof:name": "M6 6JF",
    "wof:placetype": "postalcode"
  },
  "geometry": {"coordinates":[-2.287848,53.501917],"type":"Point"}
}
