{
  "type": "Feature",
  "properties": {
    "iso:country":"GB",
    "wof:name":"EH10 6PF",
    "wof:placetype":"postalcode"
},
  "geometry": {"coordinates":[-3.20563466709624,55.90957697477583],"type":"Point"}
}