{
  "type": "Feature",
  "properties": {
    "iso:country":"GB",
    "wof:name":"BD2 1BN",
    "wof:placetype":"postalcode"
},
  "geometry": {"coordinates":[-1.7583695533194,53.82012277607031],"type":"Point"}
}