{
  "type": "Feature",
  "properties": {
    "date:inception_lower": "1980-01-01",
    "date:inception_upper": "1980-01-01",
    "iso:country": "GB",
    "wof:name": "BD2 1BN",
    "wof:placetype": "postalcode"
  },
  "geometry": {"coordinates":[-1.75837,53.820123],"type":"Point"}
}
