{
  "type": "Feature",
  "properties": {
    "iso:country":"GB",
    "wof:name":"LS15 8RQ",
    "wof:placetype":"postalcode"
},
  "geometry": {"coordinates":[-1.4505528587375,53.81498299750929],"type":"Point"}
}