{
  "type": "Feature",
  "properties": {
    "iso:country": "GB",
    "wof:name": "LS15 8RQ",
    "wof:placetype": "postalcode"
  },
  "geometry": {"coordinates":[-1.450557,53.814999],"type":"Point"}
}
