{
  "type": "Feature",
  "properties": {
    "iso:country": "GB",
    "wof:name": "LS15 8RQ",
    "wof:placetype": "postalcode"
  },
  "geometry": {"coordinates":[-1.45158,53.814627],"type":"Point"}
}
