{
  "type": "Feature",
  "properties": {
    "iso:country":"GB",
    "wof:name":"CV47 8NJ",
    "wof:placetype":"postalcode"
},
  "geometry": {"coordinates":[-1.31941207840008,52.25386925301702],"type":"Point"}
}