{
  "type": "Feature",
  "properties": {
    "date:inception_lower": "2005-02-01",
    "date:inception_upper": "2005-02-01",
    "iso:country": "GB",
    "wof:name": "IV10 8WZ",
    "wof:placetype": "postalcode"
  },
  "geometry": {"coordinates":[-4.131048,57.581485],"type":"Point"}
}
