{
  "type": "Feature",
  "properties": {
    "iso:country": "GB",
    "wof:name": "IV10 8WZ",
    "wof:placetype": "postalcode"
  },
  "geometry": {"coordinates":[-4.131048,57.581485],"type":"Point"}
}
