{
  "type": "Feature",
  "properties": {
    "iso:country": "GB",
    "wof:name": "BA6 8RG",
    "wof:placetype": "postalcode"
  },
  "geometry": {"coordinates":[-2.650291,51.110368],"type":"Point"}
}
