{
  "type": "Feature",
  "properties": {
    "iso:country": "GB",
    "wof:name": "NE5 4LU",
    "wof:placetype": "postalcode"
  },
  "geometry": {"coordinates":[-1.692574,55.006527],"type":"Point"}
}
