{
  "type": "Feature",
  "properties": {
    "iso:country":"GB",
    "wof:name":"NE5 4LU",
    "wof:placetype":"postalcode"
},
  "geometry": {"coordinates":[-1.69257424028253,55.0065265569721],"type":"Point"}
}