{
  "type": "Feature",
  "properties": {
    "date:inception_lower": "1980-01-01",
    "date:inception_upper": "1980-01-01",
    "iso:country": "GB",
    "wof:name": "N1 8AT",
    "wof:placetype": "postalcode"
  },
  "geometry": {"coordinates":[-0.102311,51.534291],"type":"Point"}
}
