{
  "type": "Feature",
  "properties": {
    "iso:country":"GB",
    "wof:name":"N1 8AT",
    "wof:placetype":"postalcode"
},
  "geometry": {"coordinates":[-0.10231113698906,51.53429085032599],"type":"Point"}
}