{
  "type": "Feature",
  "properties": {
    "date:inception_lower": "1980-01-01",
    "date:inception_upper": "1980-01-01",
    "iso:country": "GB",
    "wof:name": "G69 0EL",
    "wof:placetype": "postalcode"
  },
  "geometry": {"coordinates":[-4.083349,55.91313],"type":"Point"}
}
