{
  "type": "Feature",
  "properties": {
    "iso:country":"GB",
    "wof:name":"G69 0EL",
    "wof:placetype":"postalcode"
},
  "geometry": {"coordinates":[-4.08334910293147,55.91313024222077],"type":"Point"}
}