{
  "type": "Feature",
  "properties": {
    "iso:country":"GB",
    "wof:name":"ML3 8TQ",
    "wof:placetype":"postalcode"
},
  "geometry": {"coordinates":[-4.06518047517667,55.7612133585502],"type":"Point"}
}