{
  "type": "Feature",
  "properties": {
    "date:inception_lower": "2023-02-01",
    "date:inception_upper": "2023-02-01",
    "iso:country": "GB",
    "wof:name": "HA5 9SY",
    "wof:placetype": "postalcode"
  },
  "geometry": {"coordinates":[-0.385149,51.595053],"type":"Point"}
}
