{
  "type": "Feature",
  "properties": {
    "date:inception_lower": "1980-01-01",
    "date:inception_upper": "1980-01-01",
    "iso:country": "GB",
    "wof:name": "S9 1SN",
    "wof:placetype": "postalcode"
  },
  "geometry": {"coordinates":[-1.398875,53.414186],"type":"Point"}
}
