{
  "type": "Feature",
  "properties": {
    "date:inception_lower": "1980-01-01",
    "date:inception_upper": "1980-01-01",
    "iso:country": "GB",
    "wof:name": "SP8 4NH",
    "wof:placetype": "postalcode"
  },
  "geometry": {"coordinates":[-2.290407,51.038504],"type":"Point"}
}
