{
  "type": "Feature",
  "properties": {
    "iso:country":"GB",
    "wof:name":"LE8 0JG",
    "wof:placetype":"postalcode"
},
  "geometry": {"coordinates":[-1.00148325695874,52.53740602740775],"type":"Point"}
}