{
  "type": "Feature",
  "properties": {
    "iso:country":"GB",
    "wof:name":"WV7 3BL",
    "wof:placetype":"postalcode"
},
  "geometry": {"coordinates":[-2.25726700685879,52.60968466537012],"type":"Point"}
}