{
  "type": "Feature",
  "properties": {
    "date:inception_lower":"2004-08-01",
    "date:inception_upper":"2004-08-31",
    "iso:country":"GB",
    "wof:name":"WV7 3BL",
    "wof:placetype":"postalcode"
},
  "geometry": {"coordinates":[-2.257267,52.609685],"type":"Point"}
}