{
  "type": "Feature",
  "properties": {
    "date:inception_lower": "1980-01-01",
    "date:inception_upper": "1980-01-01",
    "iso:country": "GB",
    "wof:name": "L12 1NB",
    "wof:placetype": "postalcode"
  },
  "geometry": {"coordinates":[-2.913284,53.425002],"type":"Point"}
}
