{
  "type": "Feature",
  "properties": {
    "iso:country": "GB",
    "wof:name": "L12 1NB",
    "wof:placetype": "postalcode"
  },
  "geometry": {"coordinates":[-2.913284,53.425002],"type":"Point"}
}
