{
  "type": "Feature",
  "properties": {
    "iso:country": "GB",
    "wof:name": "L12 1NB",
    "wof:placetype": "postalcode"
  },
  "geometry": {"coordinates":[-2.912786,53.424916],"type":"Point"}
}
