{
  "type": "Feature",
  "properties": {
    "iso:country": "GB",
    "wof:name": "EX16 9EX",
    "wof:placetype": "postalcode"
  },
  "geometry": {"coordinates":[-3.573108,50.970619],"type":"Point"}
}
