{
  "type": "Feature",
  "properties": {
    "date:inception_lower": "1980-01-01",
    "date:inception_upper": "1980-01-01",
    "iso:country": "GB",
    "wof:name": "EX16 9EX",
    "wof:placetype": "postalcode"
  },
  "geometry": {"coordinates":[-3.573108,50.970619],"type":"Point"}
}
