{
  "type": "Feature",
  "properties": {
    "iso:country":"GB",
    "wof:name":"EX16 9EX",
    "wof:placetype":"postalcode"
},
  "geometry": {"coordinates":[-3.57310784983003,50.9706194827985],"type":"Point"}
}