{
  "type": "Feature",
  "properties": {
    "iso:country":"GB",
    "wof:name":"IV6 7XU",
    "wof:placetype":"postalcode"
},
  "geometry": {"coordinates":[-4.45471170763994,57.5206765219711],"type":"Point"}
}