{
  "type": "Feature",
  "properties": {
    "date:inception_lower": "1980-01-01",
    "date:inception_upper": "1980-01-01",
    "iso:country": "GB",
    "wof:name": "KT10 0EQ",
    "wof:placetype": "postalcode"
  },
  "geometry": {"coordinates":[-0.332638,51.361099],"type":"Point"}
}
