{
  "type": "Feature",
  "properties": {
    "iso:country":"GB",
    "wof:name":"IP9 2QQ",
    "wof:placetype":"postalcode"
},
  "geometry": {"coordinates":[1.14143899488835,51.98993428414251],"type":"Point"}
}