{
  "type": "Feature",
  "properties": {
    "date:inception_lower":"1980-01-01",
    "date:inception_upper":"1980-01-31",
    "iso:country":"GB",
    "wof:name":"WA3 5QZ",
    "wof:placetype":"postalcode"
},
  "geometry": {"coordinates":[-2.521579,53.451049],"type":"Point"}
}