{
  "type": "Feature",
  "properties": {
    "iso:country": "GB",
    "wof:name": "PL15 9GP",
    "wof:placetype": "postalcode"
  },
  "geometry": {"coordinates":[-4.347244,50.627162],"type":"Point"}
}
