{
  "type": "Feature",
  "properties": {
    "iso:country":"GB",
    "wof:name":"DD11 3JS",
    "wof:placetype":"postalcode"
},
  "geometry": {"coordinates":[-2.61103479255933,56.56115461208552],"type":"Point"}
}