{
  "type": "Feature",
  "properties": {
    "date:inception_lower": "2023-04-01",
    "date:inception_upper": "2023-04-01",
    "iso:country": "GB",
    "wof:name": "EH47 9FE",
    "wof:placetype": "postalcode"
  },
  "geometry": {"coordinates":[-3.687341,55.8325],"type":"Point"}
}
