{
  "type": "Feature",
  "properties": {
    "iso:country": "GB",
    "wof:name": "CF5 6AQ",
    "wof:placetype": "postalcode"
  },
  "geometry": {"coordinates":[-3.264533,51.444859],"type":"Point"}
}
