{
  "type": "Feature",
  "properties": {
    "iso:country":"GB",
    "wof:name":"TD1 2NU",
    "wof:placetype":"postalcode"
},
  "geometry": {"coordinates":[-2.76489365158543,55.61376677530362],"type":"Point"}
}