{
  "type": "Feature",
  "properties": {
    "iso:country": "GB",
    "wof:name": "TD1 2NU",
    "wof:placetype": "postalcode"
  },
  "geometry": {"coordinates":[-2.764894,55.613767],"type":"Point"}
}
