{
  "type": "Feature",
  "properties": {
    "iso:country":"GB",
    "wof:name":"GU25 4LR",
    "wof:placetype":"postalcode"
},
  "geometry": {"coordinates":[-0.57091304587976,51.41015323029259],"type":"Point"}
}