{
  "type": "Feature",
  "properties": {
    "iso:country": "GB",
    "wof:name": "G63 9BU",
    "wof:placetype": "postalcode"
  },
  "geometry": {"coordinates":[-4.308771,55.988201],"type":"Point"}
}
