{
  "type": "Feature",
  "properties": {
    "iso:country":"GB",
    "wof:name":"LL59 5ND",
    "wof:placetype":"postalcode"
},
  "geometry": {"coordinates":[-4.1737414469454,53.23156669099259],"type":"Point"}
}