{
  "type": "Feature",
  "properties": {
    "iso:country":"GB",
    "wof:name":"SG6 2SX",
    "wof:placetype":"postalcode"
},
  "geometry": {"coordinates":[-0.2118468878822,51.96648121011091],"type":"Point"}
}