{
  "type": "Feature",
  "properties": {
    "iso:country": "GB",
    "wof:name": "HR7 4NW",
    "wof:placetype": "postalcode"
  },
  "geometry": {"coordinates":[-2.541702,52.237558],"type":"Point"}
}
