{
  "type": "Feature",
  "properties": {
    "iso:country":"GB",
    "wof:name":"HR7 4NW",
    "wof:placetype":"postalcode"
},
  "geometry": {"coordinates":[-2.54214252059378,52.23764547476853],"type":"Point"}
}