{
  "type": "Feature",
  "properties": {
    "iso:country":"GB",
    "wof:name":"PA7 5LB",
    "wof:placetype":"postalcode"
},
  "geometry": {"coordinates":[-4.51293770977082,55.91123060581363],"type":"Point"}
}