{
  "type": "Feature",
  "properties": {
    "iso:country": "GB",
    "wof:name": "PA7 5LB",
    "wof:placetype": "postalcode"
  },
  "geometry": {"coordinates":[-4.512938,55.911231],"type":"Point"}
}
