{
  "type": "Feature",
  "properties": {
    "iso:country":"GB",
    "wof:name":"LS11 8SG",
    "wof:placetype":"postalcode"
},
  "geometry": {"coordinates":[-1.5593446373093,53.78025257099755],"type":"Point"}
}