{
  "type": "Feature",
  "properties": {
    "date:inception_lower":"1980-01-01",
    "date:inception_upper":"1980-01-31",
    "iso:country":"GB",
    "wof:name":"PL14 5QR",
    "wof:placetype":"postalcode"
},
  "geometry": {"coordinates":[-4.420472,50.50207],"type":"Point"}
}