{
  "type": "Feature",
  "properties": {
    "iso:country": "GB",
    "wof:name": "PL14 5QR",
    "wof:placetype": "postalcode"
  },
  "geometry": {"coordinates":[-4.420472,50.50207],"type":"Point"}
}
