{
  "type": "Feature",
  "properties": {
    "iso:country":"GB",
    "wof:name":"PL14 5QR",
    "wof:placetype":"postalcode"
},
  "geometry": {"coordinates":[-4.42047179616466,50.50206954349932],"type":"Point"}
}