{
  "type": "Feature",
  "properties": {
    "iso:country":"GB",
    "wof:name":"BA11 1QS",
    "wof:placetype":"postalcode"
},
  "geometry": {"coordinates":[-2.31446705242556,51.22758956735429],"type":"Point"}
}