{
  "type": "Feature",
  "properties": {
    "date:inception_lower": "1980-01-01",
    "date:inception_upper": "1980-01-01",
    "iso:country": "GB",
    "wof:name": "BA11 1QS",
    "wof:placetype": "postalcode"
  },
  "geometry": {"coordinates":[-2.314467,51.22759],"type":"Point"}
}
