{
  "type": "Feature",
  "properties": {
    "iso:country":"GB",
    "wof:name":"SA14 7DB",
    "wof:placetype":"postalcode"
},
  "geometry": {"coordinates":[-4.13413303129435,51.79907969672293],"type":"Point"}
}