{
  "type": "Feature",
  "properties": {
    "date:inception_lower": "1980-01-01",
    "date:inception_upper": "1980-01-01",
    "iso:country": "GB",
    "wof:name": "SA14 7DB",
    "wof:placetype": "postalcode"
  },
  "geometry": {"coordinates":[-4.134154,51.799087],"type":"Point"}
}
