{
  "type": "Feature",
  "properties": {
    "iso:country":"GB",
    "wof:name":"W4 1HA",
    "wof:placetype":"postalcode"
},
  "geometry": {"coordinates":[-0.25655155673311,51.49831406431758],"type":"Point"}
}