{
  "type": "Feature",
  "properties": {
    "iso:country":"GB",
    "wof:name":"NR15 1RT",
    "wof:placetype":"postalcode"
},
  "geometry": {"coordinates":[1.21992840311093,52.53654556860977],"type":"Point"}
}