{
  "type": "Feature",
  "properties": {
    "iso:country":"GB",
    "wof:name":"NR6 7EH",
    "wof:placetype":"postalcode"
},
  "geometry": {"coordinates":[1.30384236987023,52.66195047911873],"type":"Point"}
}