{
  "type": "Feature",
  "properties": {
    "date:inception_lower":"2004-01-01",
    "date:inception_upper":"2004-01-31",
    "iso:country":"GB",
    "wof:name":"DH6 2BF",
    "wof:placetype":"postalcode"
},
  "geometry": {"coordinates":[-1.414231,54.783684],"type":"Point"}
}