{
  "type": "Feature",
  "properties": {
    "iso:country": "GB",
    "wof:name": "DH6 2BF",
    "wof:placetype": "postalcode"
  },
  "geometry": {"coordinates":[-1.414231,54.783684],"type":"Point"}
}
