{
  "type": "Feature",
  "properties": {
    "iso:country": "GB",
    "wof:name": "S18 2HJ",
    "wof:placetype": "postalcode"
  },
  "geometry": {"coordinates":[-1.469309,53.309352],"type":"Point"}
}
