{
  "type": "Feature",
  "properties": {
    "iso:country":"GB",
    "wof:name":"S18 2HJ",
    "wof:placetype":"postalcode"
},
  "geometry": {"coordinates":[-1.46936986366197,53.30935194755143],"type":"Point"}
}