{
  "type": "Feature",
  "properties": {
    "iso:country": "GB",
    "wof:name": "HA8 9GG",
    "wof:placetype": "postalcode"
  },
  "geometry": {"coordinates":[-0.262926,51.621567],"type":"Point"}
}
