{
  "type": "Feature",
  "properties": {
    "iso:country":"GB",
    "wof:name":"LL58 8AU",
    "wof:placetype":"postalcode"
},
  "geometry": {"coordinates":[-4.09300935780426,53.26256412396036],"type":"Point"}
}