{
  "type": "Feature",
  "properties": {
    "date:inception_lower":"1996-06-01",
    "date:inception_upper":"1996-06-30",
    "iso:country":"GB",
    "wof:name":"DE6 1ET",
    "wof:placetype":"postalcode"
},
  "geometry": {"coordinates":[-1.73444,53.018455],"type":"Point"}
}