{
  "type": "Feature",
  "properties": {
    "iso:country":"GB",
    "wof:name":"DE6 1ET",
    "wof:placetype":"postalcode"
},
  "geometry": {"coordinates":[-1.73443977751332,53.01845485013304],"type":"Point"}
}