{
  "type": "Feature",
  "properties": {
    "iso:country": "GB",
    "wof:name": "DE6 1ET",
    "wof:placetype": "postalcode"
  },
  "geometry": {"coordinates":[-1.73444,53.018455],"type":"Point"}
}
