{
  "type": "Feature",
  "properties": {
    "date:inception_lower": "2023-04-01",
    "date:inception_upper": "2023-04-01",
    "iso:country": "GB",
    "wof:name": "PR6 7YQ",
    "wof:placetype": "postalcode"
  },
  "geometry": {"coordinates":[-2.629004,53.681203],"type":"Point"}
}
