{
  "type": "Feature",
  "properties": {
    "date:inception_lower":"1980-01-01",
    "date:inception_upper":"1980-01-31",
    "iso:country":"GB",
    "wof:name":"HP18 9RF",
    "wof:placetype":"postalcode"
},
  "geometry": {"coordinates":[-1.075714,51.805013],"type":"Point"}
}