{
  "type": "Feature",
  "properties": {
    "iso:country": "GB",
    "wof:name": "HP18 9RF",
    "wof:placetype": "postalcode"
  },
  "geometry": {"coordinates":[-1.075714,51.805013],"type":"Point"}
}
