{
  "type": "Feature",
  "properties": {
    "iso:country": "GB",
    "wof:name": "EX1 3RH",
    "wof:placetype": "postalcode"
  },
  "geometry": {"coordinates":[-3.465556,50.734844],"type":"Point"}
}
