{
  "type": "Feature",
  "properties": {
    "iso:country":"GB",
    "wof:name":"WS8 7DR",
    "wof:placetype":"postalcode"
},
  "geometry": {"coordinates":[-1.94826013554049,52.64362895513041],"type":"Point"}
}