{
  "type": "Feature",
  "properties": {
    "date:inception_lower": "2020-08-01",
    "date:inception_upper": "2020-08-01",
    "iso:country": "GB",
    "wof:name": "CO1 1AZ",
    "wof:placetype": "postalcode"
  },
  "geometry": {"coordinates":[0.901887,51.888965],"type":"Point"}
}
