{
  "type": "Feature",
  "properties": {
    "date:inception_lower": "2000-10-01",
    "date:inception_upper": "2000-10-01",
    "iso:country": "GB",
    "wof:name": "OX25 4SN",
    "wof:placetype": "postalcode"
  },
  "geometry": {"coordinates":[-1.307112,51.923425],"type":"Point"}
}
