{
  "type": "Feature",
  "properties": {
    "iso:country":"GB",
    "wof:name":"CV23 0PP",
    "wof:placetype":"postalcode"
},
  "geometry": {"coordinates":[-1.35523258024191,52.42731359327619],"type":"Point"}
}