{
  "type": "Feature",
  "properties": {
    "iso:country": "GB",
    "wof:name": "CV23 0PP",
    "wof:placetype": "postalcode"
  },
  "geometry": {"coordinates":[-1.348245,52.427733],"type":"Point"}
}
