{
  "type": "Feature",
  "properties": {
    "date:inception_lower": "1980-01-01",
    "date:inception_upper": "1980-01-01",
    "iso:country": "GB",
    "wof:name": "DL8 4BE",
    "wof:placetype": "postalcode"
  },
  "geometry": {"coordinates":[-1.90621,54.256407],"type":"Point"}
}
