{
  "type": "Feature",
  "properties": {
    "iso:country":"GB",
    "wof:name":"DL8 4BE",
    "wof:placetype":"postalcode"
},
  "geometry": {"coordinates":[-1.90620976241254,54.25640732318334],"type":"Point"}
}