{
  "type": "Feature",
  "properties": {
    "iso:country": "GB",
    "wof:name": "DL8 4BE",
    "wof:placetype": "postalcode"
  },
  "geometry": {"coordinates":[-1.90621,54.256407],"type":"Point"}
}
