{
  "type": "Feature",
  "properties": {
    "iso:country":"GB",
    "wof:name":"HA5 3SN",
    "wof:placetype":"postalcode"
},
  "geometry": {"coordinates":[-0.39927946068327,51.60234714073686],"type":"Point"}
}