{
  "type": "Feature",
  "properties": {
    "iso:country":"GB",
    "wof:name":"B29 6HR",
    "wof:placetype":"postalcode"
},
  "geometry": {"coordinates":[-1.94089698109198,52.43648999718597],"type":"Point"}
}