{
  "type": "Feature",
  "properties": {
    "date:inception_lower": "1980-01-01",
    "date:inception_upper": "1980-01-01",
    "iso:country": "GB",
    "wof:name": "LE17 6JX",
    "wof:placetype": "postalcode"
  },
  "geometry": {"coordinates":[-1.05725,52.451044],"type":"Point"}
}
