{
  "type": "Feature",
  "properties": {
    "iso:country":"GB",
    "wof:name":"LE17 6JX",
    "wof:placetype":"postalcode"
},
  "geometry": {"coordinates":[-1.05724983159347,52.45104435317021],"type":"Point"}
}