{
  "type": "Feature",
  "properties": {
    "iso:country":"GB",
    "wof:name":"SA40 9QG",
    "wof:placetype":"postalcode"
},
  "geometry": {"coordinates":[-4.14049323628227,52.0845949835063],"type":"Point"}
}