{
  "type": "Feature",
  "properties": {
    "date:inception_lower": "1980-01-01",
    "date:inception_upper": "1980-01-01",
    "iso:country": "GB",
    "wof:name": "SA40 9QG",
    "wof:placetype": "postalcode"
  },
  "geometry": {"coordinates":[-4.140466,52.084598],"type":"Point"}
}
