{
  "type": "Feature",
  "properties": {
    "iso:country":"GB",
    "wof:name":"SL1 7AY",
    "wof:placetype":"postalcode"
},
  "geometry": {"coordinates":[-0.6656433044345,51.53148463977902],"type":"Point"}
}