{
  "type": "Feature",
  "properties": {
    "date:inception_lower":"2005-02-01",
    "date:inception_upper":"2005-02-28",
    "iso:country":"GB",
    "wof:name":"OX28 9SE",
    "wof:placetype":"postalcode"
},
  "geometry": {"coordinates":[-1.479117,51.793339],"type":"Point"}
}