{
  "type": "Feature",
  "properties": {
    "iso:country":"GB",
    "wof:name":"HR5 3RU",
    "wof:placetype":"postalcode"
},
  "geometry": {"coordinates":[-2.98909357468637,52.22835318155514],"type":"Point"}
}