{
  "type": "Feature",
  "properties": {
    "iso:country": "GB",
    "wof:name": "HR5 3RU",
    "wof:placetype": "postalcode"
  },
  "geometry": {"coordinates":[-2.989094,52.228353],"type":"Point"}
}
