{
  "type": "Feature",
  "properties": {
    "iso:country":"GB",
    "wof:name":"BH24 1JY",
    "wof:placetype":"postalcode"
},
  "geometry": {"coordinates":[-1.7894899734302,50.84613230889619],"type":"Point"}
}