{
  "type": "Feature",
  "properties": {
    "iso:country": "GB",
    "wof:name": "CV34 5GQ",
    "wof:placetype": "postalcode"
  },
  "geometry": {"coordinates":[-1.567231,52.28757],"type":"Point"}
}
