{
  "type": "Feature",
  "properties": {
    "date:inception_lower":"2001-06-01",
    "date:inception_upper":"2001-06-30",
    "iso:country":"GB",
    "wof:name":"CV34 5GQ",
    "wof:placetype":"postalcode"
},
  "geometry": {"coordinates":[-1.567231,52.28757],"type":"Point"}
}