{
  "type": "Feature",
  "properties": {
    "iso:country":"GB",
    "wof:name":"NW9 9PD",
    "wof:placetype":"postalcode"
},
  "geometry": {"coordinates":[-0.26812705871833,51.58322925689126],"type":"Point"}
}