{
  "type": "Feature",
  "properties": {
    "date:inception_lower": "2015-04-01",
    "date:inception_upper": "2015-04-01",
    "iso:country": "GB",
    "wof:name": "G84 8FS",
    "wof:placetype": "postalcode"
  },
  "geometry": {"coordinates":[-4.75565,56.008712],"type":"Point"}
}
