{
  "type": "Feature",
  "properties": {
    "iso:country":"GB",
    "wof:name":"G84 8FS",
    "wof:placetype":"postalcode"
},
  "geometry": {"coordinates":[-4.75564986031996,56.00871249331093],"type":"Point"}
}