{
  "type": "Feature",
  "properties": {
    "iso:country": "GB",
    "wof:name": "G84 8FS",
    "wof:placetype": "postalcode"
  },
  "geometry": {"coordinates":[-4.75565,56.008712],"type":"Point"}
}
