{
  "type": "Feature",
  "properties": {
    "iso:country":"GB",
    "wof:name":"WR11 7SJ",
    "wof:placetype":"postalcode"
},
  "geometry": {"coordinates":[-2.0052321867034,52.04417571441314],"type":"Point"}
}