{
  "type": "Feature",
  "properties": {
    "date:inception_lower":"1980-01-01",
    "date:inception_upper":"1980-01-31",
    "iso:country":"GB",
    "wof:name":"CV12 8DR",
    "wof:placetype":"postalcode"
},
  "geometry": {"coordinates":[-1.470897,52.486611],"type":"Point"}
}