{
  "type": "Feature",
  "properties": {
    "date:inception_lower": "1980-01-01",
    "date:inception_upper": "1980-01-01",
    "iso:country": "GB",
    "wof:name": "SA11 1ES",
    "wof:placetype": "postalcode"
  },
  "geometry": {"coordinates":[-3.804674,51.660177],"type":"Point"}
}
