{
  "type": "Feature",
  "properties": {
    "iso:country":"GB",
    "wof:name":"SA11 1ES",
    "wof:placetype":"postalcode"
},
  "geometry": {"coordinates":[-3.80467412044172,51.66017732999873],"type":"Point"}
}