{
  "type": "Feature",
  "properties": {
    "iso:country": "GB",
    "wof:name": "SA11 1ES",
    "wof:placetype": "postalcode"
  },
  "geometry": {"coordinates":[-3.804674,51.660177],"type":"Point"}
}
