{
  "type": "Feature",
  "properties": {
    "date:inception_lower": "1980-01-01",
    "date:inception_upper": "1980-01-01",
    "iso:country": "GB",
    "wof:name": "TR17 0HE",
    "wof:placetype": "postalcode"
  },
  "geometry": {"coordinates":[-5.472469,50.124045],"type":"Point"}
}
