{
  "type": "Feature",
  "properties": {
    "date:inception_lower": "2018-07-01",
    "date:inception_upper": "2018-07-01",
    "iso:country": "GB",
    "wof:name": "RG45 6QW",
    "wof:placetype": "postalcode"
  },
  "geometry": {"coordinates":[-0.787077,51.378231],"type":"Point"}
}
