{
  "type": "Feature",
  "properties": {
    "date:inception_lower":"1980-01-01",
    "date:inception_upper":"1980-01-31",
    "iso:country":"GB",
    "wof:name":"CO7 7ER",
    "wof:placetype":"postalcode"
},
  "geometry": {"coordinates":[0.983327,51.879343],"type":"Point"}
}