{
  "type": "Feature",
  "properties": {
    "date:inception_lower": "1980-01-01",
    "date:inception_upper": "1980-01-01",
    "iso:country": "GB",
    "wof:name": "BA1 1NP",
    "wof:placetype": "postalcode"
  },
  "geometry": {"coordinates":[-2.359036,51.380295],"type":"Point"}
}
