{
  "type": "Feature",
  "properties": {
    "iso:country": "GB",
    "wof:name": "WN6 8AR",
    "wof:placetype": "postalcode"
  },
  "geometry": {"coordinates":[-2.685154,53.572452],"type":"Point"}
}
