{
  "type": "Feature",
  "properties": {
    "iso:country":"GB",
    "wof:name":"EH4 4UB",
    "wof:placetype":"postalcode"
},
  "geometry": {"coordinates":[-3.25231264522332,55.97050943192313],"type":"Point"}
}