{
  "type": "Feature",
  "properties": {
    "iso:country":"GB",
    "wof:name":"NG32 1LU",
    "wof:placetype":"postalcode"
},
  "geometry": {"coordinates":[-0.75623398541586,52.89803424542187],"type":"Point"}
}