{
  "type": "Feature",
  "properties": {
    "iso:country": "GB",
    "wof:name": "NG32 1LU",
    "wof:placetype": "postalcode"
  },
  "geometry": {"coordinates":[-0.756234,52.898034],"type":"Point"}
}
