{
  "type": "Feature",
  "properties": {
    "iso:country":"GB",
    "wof:name":"EN4 8PA",
    "wof:placetype":"postalcode"
},
  "geometry": {"coordinates":[-0.15066479898328,51.63399744372535],"type":"Point"}
}