{
  "type": "Feature",
  "properties": {
    "date:inception_lower": "1980-01-01",
    "date:inception_upper": "1980-01-01",
    "iso:country": "GB",
    "wof:name": "DN40 2JY",
    "wof:placetype": "postalcode"
  },
  "geometry": {"coordinates":[-0.216792,53.619918],"type":"Point"}
}
