{
  "type": "Feature",
  "properties": {
    "iso:country":"GB",
    "wof:name":"DN40 2JY",
    "wof:placetype":"postalcode"
},
  "geometry": {"coordinates":[-0.2167918637981,53.61991826347372],"type":"Point"}
}