{
  "type": "Feature",
  "properties": {
    "date:inception_lower": "1980-01-01",
    "date:inception_upper": "1980-01-01",
    "iso:country": "GB",
    "wof:name": "G21 3AE",
    "wof:placetype": "postalcode"
  },
  "geometry": {"coordinates":[-4.230437,55.888049],"type":"Point"}
}
