{
  "type": "Feature",
  "properties": {
    "iso:country":"GB",
    "wof:name":"G21 3AE",
    "wof:placetype":"postalcode"
},
  "geometry": {"coordinates":[-4.23043722876319,55.88804879764091],"type":"Point"}
}