{
  "type": "Feature",
  "properties": {
    "date:inception_lower":"1980-01-01",
    "date:inception_upper":"1980-01-31",
    "iso:country":"GB",
    "wof:name":"LS28 8LH",
    "wof:placetype":"postalcode"
},
  "geometry": {"coordinates":[-1.686518,53.796192],"type":"Point"}
}