{
  "type": "Feature",
  "properties": {
    "iso:country": "GB",
    "wof:name": "LS28 8LH",
    "wof:placetype": "postalcode"
  },
  "geometry": {"coordinates":[-1.686518,53.796192],"type":"Point"}
}
