{
  "type": "Feature",
  "properties": {
    "iso:country":"GB",
    "wof:name":"LS28 8LH",
    "wof:placetype":"postalcode"
},
  "geometry": {"coordinates":[-1.68651780759366,53.79619247183034],"type":"Point"}
}