{
  "type": "Feature",
  "properties": {
    "iso:country":"GB",
    "wof:name":"GU35 9NN",
    "wof:placetype":"postalcode"
},
  "geometry": {"coordinates":[-0.90319508260729,51.13291675626583],"type":"Point"}
}