{
  "type": "Feature",
  "properties": {
    "iso:country": "GB",
    "wof:name": "GU35 9NN",
    "wof:placetype": "postalcode"
  },
  "geometry": {"coordinates":[-0.903195,51.132917],"type":"Point"}
}
