{
  "type": "Feature",
  "properties": {
    "date:inception_lower": "2024-07-01",
    "date:inception_upper": "2024-07-01",
    "iso:country": "GB",
    "wof:name": "DD4 8FG",
    "wof:placetype": "postalcode"
  },
  "geometry": {"coordinates":[-2.88486,56.479106],"type":"Point"}
}
