{
  "type": "Feature",
  "properties": {
    "iso:country":"GB",
    "wof:name":"NW7 3EG",
    "wof:placetype":"postalcode"
},
  "geometry": {"coordinates":[-0.26423724292079,51.61295412624342],"type":"Point"}
}