{
  "type": "Feature",
  "properties": {
    "iso:country": "GB",
    "wof:name": "NW7 3EG",
    "wof:placetype": "postalcode"
  },
  "geometry": {"coordinates":[-0.264237,51.612954],"type":"Point"}
}
