{
  "type": "Feature",
  "properties": {
    "iso:country":"GB",
    "wof:name":"RG41 4DX",
    "wof:placetype":"postalcode"
},
  "geometry": {"coordinates":[-0.85388622872856,51.39576308309991],"type":"Point"}
}