{
  "type": "Feature",
  "properties": {
    "date:inception_lower":"1995-07-01",
    "date:inception_upper":"1995-07-31",
    "iso:country":"GB",
    "wof:name":"RG41 4DX",
    "wof:placetype":"postalcode"
},
  "geometry": {"coordinates":[-0.855151,51.395029],"type":"Point"}
}