{
  "type": "Feature",
  "properties": {
    "iso:country":"GB",
    "wof:name":"LL68 9DB",
    "wof:placetype":"postalcode"
},
  "geometry": {"coordinates":[-4.33184948828811,53.41539663228179],"type":"Point"}
}