{
  "type": "Feature",
  "properties": {
    "date:inception_lower": "1993-08-01",
    "date:inception_upper": "1993-08-01",
    "iso:country": "GB",
    "wof:name": "LL68 9DB",
    "wof:placetype": "postalcode"
  },
  "geometry": {"coordinates":[-4.33181,53.41538],"type":"Point"}
}
