{
  "type": "Feature",
  "properties": {
    "date:inception_lower":"1993-08-01",
    "date:inception_upper":"1993-08-31",
    "iso:country":"GB",
    "wof:name":"LL68 9DB",
    "wof:placetype":"postalcode"
},
  "geometry": {"coordinates":[-4.331849,53.415397],"type":"Point"}
}