{
  "type": "Feature",
  "properties": {
    "iso:country": "GB",
    "wof:name": "WF6 1NR",
    "wof:placetype": "postalcode"
  },
  "geometry": {"coordinates":[-1.414677,53.698318],"type":"Point"}
}
