{
  "type": "Feature",
  "properties": {
    "iso:country":"GB",
    "wof:name":"WF6 1NR",
    "wof:placetype":"postalcode"
},
  "geometry": {"coordinates":[-1.41467693138359,53.69831786407136],"type":"Point"}
}