{
  "type": "Feature",
  "properties": {
    "iso:country":"GB",
    "wof:name":"HP3 9DX",
    "wof:placetype":"postalcode"
},
  "geometry": {"coordinates":[-0.47288698044169,51.73756836013392],"type":"Point"}
}