{
  "type": "Feature",
  "properties": {
    "date:inception_lower": "2005-03-01",
    "date:inception_upper": "2005-03-01",
    "iso:country": "GB",
    "wof:name": "YO24 1QU",
    "wof:placetype": "postalcode"
  },
  "geometry": {"coordinates":[-1.10792,53.939757],"type":"Point"}
}
