{
  "type": "Feature",
  "properties": {
    "date:inception_lower": "1980-01-01",
    "date:inception_upper": "1980-01-01",
    "iso:country": "GB",
    "wof:name": "BD12 9LJ",
    "wof:placetype": "postalcode"
  },
  "geometry": {"coordinates":[-1.763911,53.734011],"type":"Point"}
}
