{
  "type": "Feature",
  "properties": {
    "iso:country":"GB",
    "wof:name":"BD12 9LJ",
    "wof:placetype":"postalcode"
},
  "geometry": {"coordinates":[-1.76391098596008,53.73401069076697],"type":"Point"}
}