{
  "type": "Feature",
  "properties": {
    "iso:country":"GB",
    "wof:name":"LN1 2XR",
    "wof:placetype":"postalcode"
},
  "geometry": {"coordinates":[-0.57775282749879,53.34019745806953],"type":"Point"}
}