{
  "type": "Feature",
  "properties": {
    "date:inception_lower":"2003-09-01",
    "date:inception_upper":"2003-09-30",
    "iso:country":"GB",
    "wof:name":"CF15 7NE",
    "wof:placetype":"postalcode"
},
  "geometry": {"coordinates":[-3.238822,51.529084],"type":"Point"}
}