{
  "type": "Feature",
  "properties": {
    "iso:country": "GB",
    "wof:name": "CF15 7NE",
    "wof:placetype": "postalcode"
  },
  "geometry": {"coordinates":[-3.238822,51.529084],"type":"Point"}
}
