{
  "type": "Feature",
  "properties": {
    "iso:country":"GB",
    "wof:name":"CF15 7NE",
    "wof:placetype":"postalcode"
},
  "geometry": {"coordinates":[-3.23876970079203,51.52910122506217],"type":"Point"}
}