{
  "type": "Feature",
  "properties": {
    "date:inception_lower":"2001-12-01",
    "date:inception_upper":"2001-12-31",
    "iso:country":"GB",
    "wof:name":"BS20 7BP",
    "wof:placetype":"postalcode"
},
  "geometry": {"coordinates":[-2.761475,51.490155],"type":"Point"}
}