{
  "type": "Feature",
  "properties": {
    "iso:country":"GB",
    "wof:name":"BS20 7BP",
    "wof:placetype":"postalcode"
},
  "geometry": {"coordinates":[-2.76147455506507,51.49015527227125],"type":"Point"}
}