{
  "type": "Feature",
  "properties": {
    "date:inception_lower": "2005-05-01",
    "date:inception_upper": "2005-05-01",
    "iso:country": "GB",
    "wof:name": "CT5 4QW",
    "wof:placetype": "postalcode"
  },
  "geometry": {"coordinates":[1.023855,51.353634],"type":"Point"}
}
