{
  "type": "Feature",
  "properties": {
    "iso:country": "GB",
    "wof:name": "NN7 4NA",
    "wof:placetype": "postalcode"
  },
  "geometry": {"coordinates":[-1.066993,52.238902],"type":"Point"}
}
