{
  "type": "Feature",
  "properties": {
    "iso:country":"GB",
    "wof:name":"NN7 4NA",
    "wof:placetype":"postalcode"
},
  "geometry": {"coordinates":[-1.06699328352881,52.23890165812251],"type":"Point"}
}