{
  "type": "Feature",
  "properties": {
    "iso:country":"GB",
    "wof:name":"SK3 8UL",
    "wof:placetype":"postalcode"
},
  "geometry": {"coordinates":[-2.16941985531876,53.39394163641386],"type":"Point"}
}