{
  "type": "Feature",
  "properties": {
    "date:inception_lower": "1995-12-01",
    "date:inception_upper": "1995-12-01",
    "iso:country": "GB",
    "wof:name": "SK3 8UL",
    "wof:placetype": "postalcode"
  },
  "geometry": {"coordinates":[-2.16942,53.393942],"type":"Point"}
}
