{
  "type": "Feature",
  "properties": {
    "iso:country": "GB",
    "wof:name": "SK3 8UL",
    "wof:placetype": "postalcode"
  },
  "geometry": {"coordinates":[-2.16942,53.393942],"type":"Point"}
}
