{
  "type": "Feature",
  "properties": {
    "iso:country":"GB",
    "wof:name":"SY14 7BW",
    "wof:placetype":"postalcode"
},
  "geometry": {"coordinates":[-2.84660744806845,53.03579104166079],"type":"Point"}
}