{
  "type": "Feature",
  "properties": {
    "date:inception_lower": "1980-01-01",
    "date:inception_upper": "1980-01-01",
    "iso:country": "GB",
    "wof:name": "SY14 7BW",
    "wof:placetype": "postalcode"
  },
  "geometry": {"coordinates":[-2.846607,53.035791],"type":"Point"}
}
