{
  "type": "Feature",
  "properties": {
    "iso:country":"GB",
    "wof:name":"PO32 6GH",
    "wof:placetype":"postalcode"
},
  "geometry": {"coordinates":[-1.28083756730309,50.74406370813687],"type":"Point"}
}