{
  "type": "Feature",
  "properties": {
    "date:inception_lower": "2009-10-01",
    "date:inception_upper": "2009-10-01",
    "iso:country": "GB",
    "wof:name": "PO32 6GH",
    "wof:placetype": "postalcode"
  },
  "geometry": {"coordinates":[-1.280838,50.744064],"type":"Point"}
}
