{
  "type": "Feature",
  "properties": {
    "iso:country": "GB",
    "wof:name": "PO32 6GH",
    "wof:placetype": "postalcode"
  },
  "geometry": {"coordinates":[-1.280838,50.744064],"type":"Point"}
}
