{
  "type": "Feature",
  "properties": {
    "iso:country": "GB",
    "wof:name": "LE12 7XB",
    "wof:placetype": "postalcode"
  },
  "geometry": {"coordinates":[-1.101502,52.730586],"type":"Point"}
}
