{
  "type": "Feature",
  "properties": {
    "date:inception_lower": "2016-06-01",
    "date:inception_upper": "2016-06-01",
    "iso:country": "GB",
    "wof:name": "LE12 7XB",
    "wof:placetype": "postalcode"
  },
  "geometry": {"coordinates":[-1.101502,52.730586],"type":"Point"}
}
