{
  "type": "Feature",
  "properties": {
    "iso:country": "GB",
    "wof:name": "GL52 7ZU",
    "wof:placetype": "postalcode"
  },
  "geometry": {"coordinates":[-2.074742,51.955638],"type":"Point"}
}
