{
  "type": "Feature",
  "properties": {
    "date:inception_lower":"1980-01-01",
    "date:inception_upper":"1980-01-31",
    "iso:country":"GB",
    "wof:name":"GU7 2BU",
    "wof:placetype":"postalcode"
},
  "geometry": {"coordinates":[-0.620152,51.199954],"type":"Point"}
}