{
  "type": "Feature",
  "properties": {
    "date:inception_lower": "1980-01-01",
    "date:inception_upper": "1980-01-01",
    "iso:country": "GB",
    "wof:name": "SW6 4AY",
    "wof:placetype": "postalcode"
  },
  "geometry": {"coordinates":[-0.196333,51.475956],"type":"Point"}
}
