{
  "type": "Feature",
  "properties": {
    "iso:country": "GB",
    "wof:name": "SW6 4AY",
    "wof:placetype": "postalcode"
  },
  "geometry": {"coordinates":[-0.196333,51.475956],"type":"Point"}
}
