{
  "type": "Feature",
  "properties": {
    "iso:country":"GB",
    "wof:name":"SW6 4AY",
    "wof:placetype":"postalcode"
},
  "geometry": {"coordinates":[-0.19633323156648,51.47595633758615],"type":"Point"}
}