{
  "type": "Feature",
  "properties": {
    "iso:country":"GB",
    "wof:name":"RM15 6RY",
    "wof:placetype":"postalcode"
},
  "geometry": {"coordinates":[0.30128880411014,51.50985378065396],"type":"Point"}
}