{
  "type": "Feature",
  "properties": {
    "iso:country": "GB",
    "wof:name": "M28 0EL",
    "wof:placetype": "postalcode"
  },
  "geometry": {"coordinates":[-2.429185,53.524262],"type":"Point"}
}
