{
  "type": "Feature",
  "properties": {
    "iso:country":"GB",
    "wof:name":"M28 0EL",
    "wof:placetype":"postalcode"
},
  "geometry": {"coordinates":[-2.42918538327963,53.52426196622636],"type":"Point"}
}