{
  "type": "Feature",
  "properties": {
    "iso:country":"GB",
    "wof:name":"SL5 9QW",
    "wof:placetype":"postalcode"
},
  "geometry": {"coordinates":[-0.64703054753759,51.38251537947514],"type":"Point"}
}