{
  "type": "Feature",
  "properties": {
    "date:inception_lower": "1980-01-01",
    "date:inception_upper": "1980-01-01",
    "iso:country": "GB",
    "wof:name": "SL5 9QW",
    "wof:placetype": "postalcode"
  },
  "geometry": {"coordinates":[-0.647031,51.382515],"type":"Point"}
}
