{
  "type": "Feature",
  "properties": {
    "iso:country": "GB",
    "wof:name": "LS10 4DU",
    "wof:placetype": "postalcode"
  },
  "geometry": {"coordinates":[-1.540014,53.742511],"type":"Point"}
}
