{
  "type": "Feature",
  "properties": {
    "date:inception_lower": "1980-01-01",
    "date:inception_upper": "1980-01-01",
    "iso:country": "GB",
    "wof:name": "LS10 4DU",
    "wof:placetype": "postalcode"
  },
  "geometry": {"coordinates":[-1.540014,53.742511],"type":"Point"}
}
