{
  "type": "Feature",
  "properties": {
    "iso:country":"GB",
    "wof:name":"G65 0DE",
    "wof:placetype":"postalcode"
},
  "geometry": {"coordinates":[-4.05581697853737,55.97065999954397],"type":"Point"}
}