{
  "type": "Feature",
  "properties": {
    "date:inception_lower":"1993-08-01",
    "date:inception_upper":"1993-08-31",
    "iso:country":"GB",
    "wof:name":"PL25 3ET",
    "wof:placetype":"postalcode"
},
  "geometry": {"coordinates":[-4.760307,50.345579],"type":"Point"}
}