{
  "type": "Feature",
  "properties": {
    "iso:country":"GB",
    "wof:name":"PL25 3ET",
    "wof:placetype":"postalcode"
},
  "geometry": {"coordinates":[-4.76030690503645,50.34557921769598],"type":"Point"}
}