{
  "type": "Feature",
  "properties": {
    "iso:country":"GB",
    "wof:name":"GU6 8LU",
    "wof:placetype":"postalcode"
},
  "geometry": {"coordinates":[-0.50273415761752,51.14445582367256],"type":"Point"}
}