{
  "type": "Feature",
  "properties": {
    "date:inception_lower": "2016-11-01",
    "date:inception_upper": "2016-11-01",
    "iso:country": "GB",
    "wof:name": "GU9 8EY",
    "wof:placetype": "postalcode"
  },
  "geometry": {"coordinates":[-0.808666,51.201654],"type":"Point"}
}
