{
  "type": "Feature",
  "properties": {
    "iso:country":"GB",
    "wof:name":"KY10 3SX",
    "wof:placetype":"postalcode"
},
  "geometry": {"coordinates":[-2.62708674785537,56.25834912028024],"type":"Point"}
}