{
  "type": "Feature",
  "properties": {
    "iso:country": "GB",
    "wof:name": "KY10 3SX",
    "wof:placetype": "postalcode"
  },
  "geometry": {"coordinates":[-2.627087,56.258349],"type":"Point"}
}
