{
  "type": "Feature",
  "properties": {
    "iso:country":"GB",
    "wof:name":"CV10 9JH",
    "wof:placetype":"postalcode"
},
  "geometry": {"coordinates":[-1.51593914823723,52.52474123735719],"type":"Point"}
}