{
  "type": "Feature",
  "properties": {
    "iso:country": "GB",
    "wof:name": "NG1 5DZ",
    "wof:placetype": "postalcode"
  },
  "geometry": {"coordinates":[-1.160491,52.954628],"type":"Point"}
}
