{
  "type": "Feature",
  "properties": {
    "iso:country":"GB",
    "wof:name":"LN2 4LB",
    "wof:placetype":"postalcode"
},
  "geometry": {"coordinates":[-0.51418037409008,53.23706743180276],"type":"Point"}
}