{
  "type": "Feature",
  "properties": {
    "date:inception_lower": "1980-01-01",
    "date:inception_upper": "1980-01-01",
    "iso:country": "GB",
    "wof:name": "LN2 4LB",
    "wof:placetype": "postalcode"
  },
  "geometry": {"coordinates":[-0.51418,53.237067],"type":"Point"}
}
