{
  "type": "Feature",
  "properties": {
    "iso:country":"GB",
    "wof:name":"CB1 3JY",
    "wof:placetype":"postalcode"
},
  "geometry": {"coordinates":[0.17919064206489,52.1938415210572],"type":"Point"}
}