{
  "type": "Feature",
  "properties": {
    "iso:country": "GB",
    "wof:name": "CV35 8XD",
    "wof:placetype": "postalcode"
  },
  "geometry": {"coordinates":[-1.666863,52.283293],"type":"Point"}
}
