{
  "type": "Feature",
  "properties": {
    "iso:country":"GB",
    "wof:name":"BS7 8QY",
    "wof:placetype":"postalcode"
},
  "geometry": {"coordinates":[-2.59056887902439,51.48151973575408],"type":"Point"}
}