{
  "type": "Feature",
  "properties": {
    "iso:country": "GB",
    "wof:name": "SA71 5TP",
    "wof:placetype": "postalcode"
  },
  "geometry": {"coordinates":[-4.98372,51.675539],"type":"Point"}
}
