{
  "type": "Feature",
  "properties": {
    "iso:country":"GB",
    "wof:name":"SA71 5TP",
    "wof:placetype":"postalcode"
},
  "geometry": {"coordinates":[-4.9830018073713,51.6757159018044],"type":"Point"}
}