{
  "type": "Feature",
  "properties": {
    "iso:country":"GB",
    "wof:name":"EX17 6HL",
    "wof:placetype":"postalcode"
},
  "geometry": {"coordinates":[-3.81042610363048,50.8012360395934],"type":"Point"}
}