{
  "type": "Feature",
  "properties": {
    "iso:country":"GB",
    "wof:name":"SG5 4DL",
    "wof:placetype":"postalcode"
},
  "geometry": {"coordinates":[-0.22314549838144,52.0164575480738],"type":"Point"}
}