{
  "type": "Feature",
  "properties": {
    "iso:country": "GB",
    "wof:name": "ST3 2DT",
    "wof:placetype": "postalcode"
  },
  "geometry": {"coordinates":[-2.157228,52.986447],"type":"Point"}
}
