{
  "type": "Feature",
  "properties": {
    "date:inception_lower":"1980-01-01",
    "date:inception_upper":"1980-01-31",
    "iso:country":"GB",
    "wof:name":"ST3 2DT",
    "wof:placetype":"postalcode"
},
  "geometry": {"coordinates":[-2.157228,52.986447],"type":"Point"}
}