{
  "type": "Feature",
  "properties": {
    "iso:country":"GB",
    "wof:name":"ST3 2DT",
    "wof:placetype":"postalcode"
},
  "geometry": {"coordinates":[-2.15722786631949,52.9864472453587],"type":"Point"}
}