{
  "type": "Feature",
  "properties": {
    "iso:country":"GB",
    "wof:name":"CH4 8EB",
    "wof:placetype":"postalcode"
},
  "geometry": {"coordinates":[-2.92008237630629,53.17631475322182],"type":"Point"}
}