{
  "type": "Feature",
  "properties": {
    "date:inception_lower": "1983-07-01",
    "date:inception_upper": "1983-07-01",
    "iso:country": "GB",
    "wof:name": "CH4 8EB",
    "wof:placetype": "postalcode"
  },
  "geometry": {"coordinates":[-2.920082,53.176315],"type":"Point"}
}
