{
  "type": "Feature",
  "properties": {
    "iso:country":"GB",
    "wof:name":"LL58 8LE",
    "wof:placetype":"postalcode"
},
  "geometry": {"coordinates":[-4.0903876080357,53.27797482644188],"type":"Point"}
}