{
  "type": "Feature",
  "properties": {
    "date:inception_lower":"1985-10-01",
    "date:inception_upper":"1985-10-31",
    "iso:country":"GB",
    "wof:name":"NE7 7YU",
    "wof:placetype":"postalcode"
},
  "geometry": {"coordinates":[-1.570606,55.003695],"type":"Point"}
}