{
  "type": "Feature",
  "properties": {
    "iso:country": "GB",
    "wof:name": "NE7 7YU",
    "wof:placetype": "postalcode"
  },
  "geometry": {"coordinates":[-1.570606,55.003695],"type":"Point"}
}
