{
  "type": "Feature",
  "properties": {
    "date:inception_lower": "1980-01-01",
    "date:inception_upper": "1980-01-01",
    "iso:country": "GB",
    "wof:name": "WA4 2HJ",
    "wof:placetype": "postalcode"
  },
  "geometry": {"coordinates":[-2.536744,53.379496],"type":"Point"}
}
