{
  "type": "Feature",
  "properties": {
    "date:inception_lower": "1980-01-01",
    "date:inception_upper": "1980-01-01",
    "iso:country": "GB",
    "wof:name": "CR0 6BF",
    "wof:placetype": "postalcode"
  },
  "geometry": {"coordinates":[-0.087633,51.380008],"type":"Point"}
}
