{
  "type": "Feature",
  "properties": {
    "iso:country":"GB",
    "wof:name":"CR0 6BF",
    "wof:placetype":"postalcode"
},
  "geometry": {"coordinates":[-0.0876325817411,51.38000846144717],"type":"Point"}
}