{
  "type": "Feature",
  "properties": {
    "date:inception_lower": "2019-10-01",
    "date:inception_upper": "2019-10-01",
    "iso:country": "GB",
    "wof:name": "CW9 9PY",
    "wof:placetype": "postalcode"
  },
  "geometry": {"coordinates":[-2.508697,53.261344],"type":"Point"}
}
