{
  "type": "Feature",
  "properties": {
    "iso:country":"GB",
    "wof:name":"BN3 3YL",
    "wof:placetype":"postalcode"
},
  "geometry": {"coordinates":[-0.17607837150038,50.83171966140171],"type":"Point"}
}