{
  "type": "Feature",
  "properties": {
    "iso:country":"GB",
    "wof:name":"PO33 1FL",
    "wof:placetype":"postalcode"
},
  "geometry": {"coordinates":[-1.15270223684603,50.72573927867182],"type":"Point"}
}