{
  "type": "Feature",
  "properties": {
    "iso:country":"GB",
    "wof:name":"NG5 2EL",
    "wof:placetype":"postalcode"
},
  "geometry": {"coordinates":[-1.14804747940985,52.97743323811262],"type":"Point"}
}