{
  "type": "Feature",
  "properties": {
    "date:inception_lower": "1980-01-01",
    "date:inception_upper": "1980-01-01",
    "iso:country": "GB",
    "wof:name": "PE6 9LU",
    "wof:placetype": "postalcode"
  },
  "geometry": {"coordinates":[-0.343994,52.695796],"type":"Point"}
}
