{
  "type": "Feature",
  "properties": {
    "iso:country":"GB",
    "wof:name":"BS13 9RQ",
    "wof:placetype":"postalcode"
},
  "geometry": {"coordinates":[-2.60367172683662,51.41158781595196],"type":"Point"}
}