{
  "type": "Feature",
  "properties": {
    "date:inception_lower": "1980-01-01",
    "date:inception_upper": "1980-01-01",
    "iso:country": "GB",
    "wof:name": "BS13 9RQ",
    "wof:placetype": "postalcode"
  },
  "geometry": {"coordinates":[-2.603672,51.411588],"type":"Point"}
}
