{
  "type": "Feature",
  "properties": {
    "iso:country": "GB",
    "wof:name": "LA13 9NL",
    "wof:placetype": "postalcode"
  },
  "geometry": {"coordinates":[-3.200964,54.112654],"type":"Point"}
}
