{
  "type": "Feature",
  "properties": {
    "iso:country": "GB",
    "wof:name": "LA13 9NL",
    "wof:placetype": "postalcode"
  },
  "geometry": {"coordinates":[-3.201055,54.112644],"type":"Point"}
}
