{
  "type": "Feature",
  "properties": {
    "date:inception_lower":"1980-01-01",
    "date:inception_upper":"1980-01-31",
    "iso:country":"GB",
    "wof:name":"LA13 9NL",
    "wof:placetype":"postalcode"
},
  "geometry": {"coordinates":[-3.201055,54.112644],"type":"Point"}
}