{
  "type": "Feature",
  "properties": {
    "iso:country":"GB",
    "wof:name":"LA13 9NL",
    "wof:placetype":"postalcode"
},
  "geometry": {"coordinates":[-3.20096711738152,54.11264599598466],"type":"Point"}
}