{
  "type": "Feature",
  "properties": {
    "date:inception_lower": "1980-01-01",
    "date:inception_upper": "1980-01-01",
    "iso:country": "GB",
    "wof:name": "N18 1JW",
    "wof:placetype": "postalcode"
  },
  "geometry": {"coordinates":[-0.087074,51.612584],"type":"Point"}
}
