{
  "type": "Feature",
  "properties": {
    "iso:country":"GB",
    "wof:name":"N18 1JW",
    "wof:placetype":"postalcode"
},
  "geometry": {"coordinates":[-0.08707376221839,51.61258373701105],"type":"Point"}
}