{
  "type": "Feature",
  "properties": {
    "iso:country": "GB",
    "wof:name": "YO17 8HA",
    "wof:placetype": "postalcode"
  },
  "geometry": {"coordinates":[-0.51894,54.123696],"type":"Point"}
}
