{
  "type": "Feature",
  "properties": {
    "iso:country":"GB",
    "wof:name":"TF4 3ER",
    "wof:placetype":"postalcode"
},
  "geometry": {"coordinates":[-2.46737174957422,52.6559413832641],"type":"Point"}
}