{
  "type": "Feature",
  "properties": {
    "iso:country":"GB",
    "wof:name":"PE30 4PH",
    "wof:placetype":"postalcode"
},
  "geometry": {"coordinates":[0.42235459346076,52.75361850980804],"type":"Point"}
}