{
  "type": "Feature",
  "properties": {
    "iso:country":"GB",
    "wof:name":"WN3 5HH",
    "wof:placetype":"postalcode"
},
  "geometry": {"coordinates":[-2.64012722348004,53.53780777718406],"type":"Point"}
}