{
  "type": "Feature",
  "properties": {
    "date:inception_lower": "2002-08-01",
    "date:inception_upper": "2002-08-01",
    "iso:country": "GB",
    "wof:name": "HD8 9UR",
    "wof:placetype": "postalcode"
  },
  "geometry": {"coordinates":[-1.614353,53.593155],"type":"Point"}
}
