{
  "type": "Feature",
  "properties": {
    "iso:country": "GB",
    "wof:name": "DN4 6EF",
    "wof:placetype": "postalcode"
  },
  "geometry": {"coordinates":[-1.080523,53.505356],"type":"Point"}
}
