{
  "type": "Feature",
  "properties": {
    "iso:country":"GB",
    "wof:name":"WS2 9UA",
    "wof:placetype":"postalcode"
},
  "geometry": {"coordinates":[-2.00980050680592,52.58212281656083],"type":"Point"}
}