{
  "type": "Feature",
  "properties": {
    "date:inception_lower": "1980-01-01",
    "date:inception_upper": "1980-01-01",
    "iso:country": "GB",
    "wof:name": "SN10 4HG",
    "wof:placetype": "postalcode"
  },
  "geometry": {"coordinates":[-2.001291,51.28071],"type":"Point"}
}
