{
  "type": "Feature",
  "properties": {
    "iso:country":"GB",
    "wof:name":"SN10 4HG",
    "wof:placetype":"postalcode"
},
  "geometry": {"coordinates":[-2.00129813214471,51.28071390719676],"type":"Point"}
}