{
  "type": "Feature",
  "properties": {
    "iso:country": "GB",
    "wof:name": "EX23 8SX",
    "wof:placetype": "postalcode"
  },
  "geometry": {"coordinates":[-4.549965,50.836691],"type":"Point"}
}
