{
  "type": "Feature",
  "properties": {
    "date:inception_lower": "2007-11-01",
    "date:inception_upper": "2007-11-01",
    "iso:country": "GB",
    "wof:name": "EX23 8SX",
    "wof:placetype": "postalcode"
  },
  "geometry": {"coordinates":[-4.549965,50.836691],"type":"Point"}
}
