{
  "type": "Feature",
  "properties": {
    "date:inception_lower":"2007-11-01",
    "date:inception_upper":"2007-11-30",
    "iso:country":"GB",
    "wof:name":"EX23 8SX",
    "wof:placetype":"postalcode"
},
  "geometry": {"coordinates":[-4.549979,50.836682],"type":"Point"}
}