{
  "type": "Feature",
  "properties": {
    "iso:country": "GB",
    "wof:name": "ST10 4LH",
    "wof:placetype": "postalcode"
  },
  "geometry": {"coordinates":[-1.983943,52.952472],"type":"Point"}
}
