{
  "type": "Feature",
  "properties": {
    "date:inception_lower": "2003-06-01",
    "date:inception_upper": "2003-06-01",
    "iso:country": "GB",
    "wof:name": "ST10 4LH",
    "wof:placetype": "postalcode"
  },
  "geometry": {"coordinates":[-1.983943,52.952472],"type":"Point"}
}
