{
  "type": "Feature",
  "properties": {
    "date:inception_lower":"1992-08-01",
    "date:inception_upper":"1992-08-31",
    "iso:country":"GB",
    "wof:name":"LS27 8TU",
    "wof:placetype":"postalcode"
},
  "geometry": {"coordinates":[-1.580593,53.74497],"type":"Point"}
}