{
  "type": "Feature",
  "properties": {
    "iso:country": "GB",
    "wof:name": "WA9 4BT",
    "wof:placetype": "postalcode"
  },
  "geometry": {"coordinates":[-2.731644,53.415414],"type":"Point"}
}
