{
  "type": "Feature",
  "properties": {
    "date:inception_lower": "1984-10-01",
    "date:inception_upper": "1984-10-01",
    "iso:country": "GB",
    "wof:name": "WA9 4BT",
    "wof:placetype": "postalcode"
  },
  "geometry": {"coordinates":[-2.731644,53.415414],"type":"Point"}
}
