{
  "type": "Feature",
  "properties": {
    "iso:country":"GB",
    "wof:name":"WA9 4BT",
    "wof:placetype":"postalcode"
},
  "geometry": {"coordinates":[-2.73164438812448,53.41541449994148],"type":"Point"}
}