{
  "type": "Feature",
  "properties": {
    "date:inception_lower":"1980-01-01",
    "date:inception_upper":"1980-01-31",
    "iso:country":"GB",
    "wof:name":"SN8 3BW",
    "wof:placetype":"postalcode"
},
  "geometry": {"coordinates":[-1.6791,51.353657],"type":"Point"}
}