{
  "type": "Feature",
  "properties": {
    "iso:country":"GB",
    "wof:name":"SN8 3BW",
    "wof:placetype":"postalcode"
},
  "geometry": {"coordinates":[-1.67898512413621,51.35368347636381],"type":"Point"}
}