{
  "type": "Feature",
  "properties": {
    "iso:country":"GB",
    "wof:name":"BD6 2HW",
    "wof:placetype":"postalcode"
},
  "geometry": {"coordinates":[-1.79678654213155,53.75681962855097],"type":"Point"}
}