{
  "type": "Feature",
  "properties": {
    "date:inception_lower": "2009-05-01",
    "date:inception_upper": "2009-05-01",
    "iso:country": "GB",
    "wof:name": "SE21 8GA",
    "wof:placetype": "postalcode"
  },
  "geometry": {"coordinates":[-0.092589,51.438083],"type":"Point"}
}
