{
  "type": "Feature",
  "properties": {
    "iso:country":"GB",
    "wof:name":"RG42 3RH",
    "wof:placetype":"postalcode"
},
  "geometry": {"coordinates":[-0.71747272138993,51.42106533248184],"type":"Point"}
}