{
  "type": "Feature",
  "properties": {
    "iso:country": "GB",
    "wof:name": "RG42 3RH",
    "wof:placetype": "postalcode"
  },
  "geometry": {"coordinates":[-0.717473,51.421065],"type":"Point"}
}
