{
  "type": "Feature",
  "properties": {
    "iso:country":"GB",
    "wof:name":"PL3 6PJ",
    "wof:placetype":"postalcode"
},
  "geometry": {"coordinates":[-4.1138088504611,50.3935843410409],"type":"Point"}
}