{
  "type": "Feature",
  "properties": {
    "iso:country": "GB",
    "wof:name": "PL3 6PJ",
    "wof:placetype": "postalcode"
  },
  "geometry": {"coordinates":[-4.113809,50.393584],"type":"Point"}
}
