{
  "type": "Feature",
  "properties": {
    "iso:country": "GB",
    "wof:name": "HP22 4SH",
    "wof:placetype": "postalcode"
  },
  "geometry": {"coordinates":[-0.831222,51.875767],"type":"Point"}
}
