{
  "type": "Feature",
  "properties": {
    "iso:country":"GB",
    "wof:name":"HP22 4SH",
    "wof:placetype":"postalcode"
},
  "geometry": {"coordinates":[-0.83122193961988,51.87576703284019],"type":"Point"}
}