{
  "type": "Feature",
  "properties": {
    "date:inception_lower": "2017-11-01",
    "date:inception_upper": "2017-11-01",
    "iso:country": "GB",
    "wof:name": "AB15 9EW",
    "wof:placetype": "postalcode"
  },
  "geometry": {"coordinates":[-2.180901,57.12298],"type":"Point"}
}
