{
  "type": "Feature",
  "properties": {
    "iso:country":"GB",
    "wof:name":"SY5 0YE",
    "wof:placetype":"postalcode"
},
  "geometry": {"coordinates":[-2.89458402215264,52.64367748458156],"type":"Point"}
}