{
  "type": "Feature",
  "properties": {
    "date:inception_lower": "1980-01-01",
    "date:inception_upper": "1980-01-01",
    "iso:country": "GB",
    "wof:name": "G15 6DB",
    "wof:placetype": "postalcode"
  },
  "geometry": {"coordinates":[-4.3561,55.908566],"type":"Point"}
}
