{
  "type": "Feature",
  "properties": {
    "iso:country": "GB",
    "wof:name": "G15 6DB",
    "wof:placetype": "postalcode"
  },
  "geometry": {"coordinates":[-4.3561,55.908566],"type":"Point"}
}
