{
  "type": "Feature",
  "properties": {
    "date:inception_lower":"1980-01-01",
    "date:inception_upper":"1980-01-31",
    "iso:country":"GB",
    "wof:name":"BN17 7DF",
    "wof:placetype":"postalcode"
},
  "geometry": {"coordinates":[-0.54294,50.813118],"type":"Point"}
}