{
  "type": "Feature",
  "properties": {
    "iso:country":"GB",
    "wof:name":"BN17 7DF",
    "wof:placetype":"postalcode"
},
  "geometry": {"coordinates":[-0.54296273955317,50.81312701048872],"type":"Point"}
}