{
  "type": "Feature",
  "properties": {
    "iso:country":"GB",
    "wof:name":"EX8 4QY",
    "wof:placetype":"postalcode"
},
  "geometry": {"coordinates":[-3.40630299920872,50.63860061271837],"type":"Point"}
}