{
  "type": "Feature",
  "properties": {
    "iso:country": "GB",
    "wof:name": "CV36 4NX",
    "wof:placetype": "postalcode"
  },
  "geometry": {"coordinates":[-1.627522,52.090186],"type":"Point"}
}
