{
  "type": "Feature",
  "properties": {
    "iso:country":"GB",
    "wof:name":"PO1 4PE",
    "wof:placetype":"postalcode"
},
  "geometry": {"coordinates":[-1.08284269966847,50.80618227645613],"type":"Point"}
}