{
  "type": "Feature",
  "properties": {
    "iso:country":"GB",
    "wof:name":"TF12 5JT",
    "wof:placetype":"postalcode"
},
  "geometry": {"coordinates":[-2.46178927641021,52.58212088270076],"type":"Point"}
}