{
  "type": "Feature",
  "properties": {
    "iso:country":"GB",
    "wof:name":"HG3 4BW",
    "wof:placetype":"postalcode"
},
  "geometry": {"coordinates":[-1.70239738226167,54.061876145265],"type":"Point"}
}