{
  "type": "Feature",
  "properties": {
    "iso:country": "GB",
    "wof:name": "WS1 3AW",
    "wof:placetype": "postalcode"
  },
  "geometry": {"coordinates":[-1.974516,52.57785],"type":"Point"}
}
