{
  "type": "Feature",
  "properties": {
    "date:inception_lower":"1998-12-01",
    "date:inception_upper":"1998-12-31",
    "iso:country":"GB",
    "wof:name":"IV2 7QL",
    "wof:placetype":"postalcode"
},
  "geometry": {"coordinates":[-4.038462,57.56923],"type":"Point"}
}