{
  "type": "Feature",
  "properties": {
    "date:inception_lower": "1983-07-01",
    "date:inception_upper": "1983-07-01",
    "iso:country": "GB",
    "wof:name": "EC1N 8LB",
    "wof:placetype": "postalcode"
  },
  "geometry": {"coordinates":[-0.108085,51.518559],"type":"Point"}
}
