{
  "type": "Feature",
  "properties": {
    "iso:country":"GB",
    "wof:name":"LA23 2JX",
    "wof:placetype":"postalcode"
},
  "geometry": {"coordinates":[-2.91342244830979,54.37025984960255],"type":"Point"}
}