{
  "type": "Feature",
  "properties": {
    "iso:country":"GB",
    "wof:name":"HA8 5DP",
    "wof:placetype":"postalcode"
},
  "geometry": {"coordinates":[-0.27437713260662,51.5996062829388],"type":"Point"}
}