{
  "type": "Feature",
  "properties": {
    "iso:country":"GB",
    "wof:name":"UB1 1DJ",
    "wof:placetype":"postalcode"
},
  "geometry": {"coordinates":[-0.38874796547984,51.50981739627141],"type":"Point"}
}