{
  "type": "Feature",
  "properties": {
    "iso:country": "GB",
    "wof:name": "AB43 6ST",
    "wof:placetype": "postalcode"
  },
  "geometry": {"coordinates":[-2.093597,57.587155],"type":"Point"}
}
