{
  "type": "Feature",
  "properties": {
    "iso:country":"GB",
    "wof:name":"AB43 6ST",
    "wof:placetype":"postalcode"
},
  "geometry": {"coordinates":[-2.09379828692167,57.58730804652414],"type":"Point"}
}