{
  "type": "Feature",
  "properties": {
    "iso:country": "GB",
    "wof:name": "NP12 1FL",
    "wof:placetype": "postalcode"
  },
  "geometry": {"coordinates":[-3.200703,51.670787],"type":"Point"}
}
