{
  "type": "Feature",
  "properties": {
    "date:inception_lower": "2014-02-01",
    "date:inception_upper": "2014-02-01",
    "iso:country": "GB",
    "wof:name": "NP12 1FL",
    "wof:placetype": "postalcode"
  },
  "geometry": {"coordinates":[-3.200703,51.670787],"type":"Point"}
}
