{
  "type": "Feature",
  "properties": {
    "iso:country":"GB",
    "wof:name":"NP12 1FL",
    "wof:placetype":"postalcode"
},
  "geometry": {"coordinates":[-3.20075308921872,51.67079309151114],"type":"Point"}
}