{
  "type": "Feature",
  "properties": {
    "date:inception_lower": "2003-06-01",
    "date:inception_upper": "2003-06-01",
    "iso:country": "GB",
    "wof:name": "MK19 6EU",
    "wof:placetype": "postalcode"
  },
  "geometry": {"coordinates":[-0.825331,52.037417],"type":"Point"}
}
