{
  "type": "Feature",
  "properties": {
    "iso:country":"GB",
    "wof:name":"MK19 6EU",
    "wof:placetype":"postalcode"
},
  "geometry": {"coordinates":[-0.82318489315173,52.03490339693396],"type":"Point"}
}