{
  "type": "Feature",
  "properties": {
    "iso:country": "GB",
    "wof:name": "AB34 5JZ",
    "wof:placetype": "postalcode"
  },
  "geometry": {"coordinates":[-2.800711,57.076891],"type":"Point"}
}
