{
  "type": "Feature",
  "properties": {
    "iso:country":"GB",
    "wof:name":"AB34 5JZ",
    "wof:placetype":"postalcode"
},
  "geometry": {"coordinates":[-2.8007110893164,57.07689053560795],"type":"Point"}
}