{
  "type": "Feature",
  "properties": {
    "iso:country": "GB",
    "wof:name": "S72 7JZ",
    "wof:placetype": "postalcode"
  },
  "geometry": {"coordinates":[-1.370598,53.57152],"type":"Point"}
}
