{
  "type": "Feature",
  "properties": {
    "iso:country":"GB",
    "wof:name":"S72 7JZ",
    "wof:placetype":"postalcode"
},
  "geometry": {"coordinates":[-1.37059771313878,53.57152037137167],"type":"Point"}
}