{
  "type": "Feature",
  "properties": {
    "iso:country":"GB",
    "wof:name":"M18 7BU",
    "wof:placetype":"postalcode"
},
  "geometry": {"coordinates":[-2.18036015316678,53.45972162185068],"type":"Point"}
}