{
  "type": "Feature",
  "properties": {
    "iso:country": "GB",
    "wof:name": "SW15 1RW",
    "wof:placetype": "postalcode"
  },
  "geometry": {"coordinates":[-0.219825,51.462881],"type":"Point"}
}
