{
  "type": "Feature",
  "properties": {
    "date:inception_lower": "1991-09-01",
    "date:inception_upper": "1991-09-01",
    "iso:country": "GB",
    "wof:name": "NG15 6TY",
    "wof:placetype": "postalcode"
  },
  "geometry": {"coordinates":[-1.237374,53.033369],"type":"Point"}
}
