{
  "type": "Feature",
  "properties": {
    "iso:country":"GB",
    "wof:name":"DT6 3SL",
    "wof:placetype":"postalcode"
},
  "geometry": {"coordinates":[-2.70674712302457,50.76511645314787],"type":"Point"}
}