{
  "type": "Feature",
  "properties": {
    "iso:country":"GB",
    "wof:name":"B11 3SG",
    "wof:placetype":"postalcode"
},
  "geometry": {"coordinates":[-1.86189269891437,52.45503363938943],"type":"Point"}
}