{
  "type": "Feature",
  "properties": {
    "iso:country":"GB",
    "wof:name":"PA20 9HZ",
    "wof:placetype":"postalcode"
},
  "geometry": {"coordinates":[-5.05410179436791,55.82975157779891],"type":"Point"}
}