{
  "type": "Feature",
  "properties": {
    "date:inception_lower":"1980-01-01",
    "date:inception_upper":"1980-01-31",
    "iso:country":"GB",
    "wof:name":"PA20 9HZ",
    "wof:placetype":"postalcode"
},
  "geometry": {"coordinates":[-5.054102,55.829752],"type":"Point"}
}