{
  "type": "Feature",
  "properties": {
    "iso:country":"GB",
    "wof:name":"PL1 4RG",
    "wof:placetype":"postalcode"
},
  "geometry": {"coordinates":[-4.17348673947319,50.3780480274736],"type":"Point"}
}