{
  "type": "Feature",
  "properties": {
    "iso:country":"GB",
    "wof:name":"KA13 6QX",
    "wof:placetype":"postalcode"
},
  "geometry": {"coordinates":[-4.72720820356441,55.65119103416418],"type":"Point"}
}