{
  "type": "Feature",
  "properties": {
    "iso:country": "GB",
    "wof:name": "TA4 4QU",
    "wof:placetype": "postalcode"
  },
  "geometry": {"coordinates":[-3.317471,51.162791],"type":"Point"}
}
