{
  "type": "Feature",
  "properties": {
    "iso:country":"GB",
    "wof:name":"TA4 4QU",
    "wof:placetype":"postalcode"
},
  "geometry": {"coordinates":[-3.31747076851378,51.16279064413602],"type":"Point"}
}