{
  "type": "Feature",
  "properties": {
    "iso:country": "GB",
    "wof:name": "EX6 8HE",
    "wof:placetype": "postalcode"
  },
  "geometry": {"coordinates":[-3.515496,50.618426],"type":"Point"}
}
