{
  "type": "Feature",
  "properties": {
    "date:inception_lower": "1980-01-01",
    "date:inception_upper": "1980-01-01",
    "iso:country": "GB",
    "wof:name": "EX6 8HE",
    "wof:placetype": "postalcode"
  },
  "geometry": {"coordinates":[-3.515496,50.618426],"type":"Point"}
}
