{
  "type": "Feature",
  "properties": {
    "iso:country": "GB",
    "wof:name": "NE47 9US",
    "wof:placetype": "postalcode"
  },
  "geometry": {"coordinates":[-2.244653,54.833123],"type":"Point"}
}
