{
  "type": "Feature",
  "properties": {
    "date:inception_lower": "2013-03-01",
    "date:inception_upper": "2013-03-01",
    "iso:country": "GB",
    "wof:name": "NE47 9US",
    "wof:placetype": "postalcode"
  },
  "geometry": {"coordinates":[-2.244701,54.833221],"type":"Point"}
}
