{
  "type": "Feature",
  "properties": {
    "iso:country":"GB",
    "wof:name":"NE47 9US",
    "wof:placetype":"postalcode"
},
  "geometry": {"coordinates":[-2.24469345660985,54.83321410138186],"type":"Point"}
}