{
  "type": "Feature",
  "properties": {
    "iso:country": "GB",
    "wof:name": "IV36 1QS",
    "wof:placetype": "postalcode"
  },
  "geometry": {"coordinates":[-3.58777,57.611349],"type":"Point"}
}
