{
  "type": "Feature",
  "properties": {
    "iso:country": "GB",
    "wof:name": "BD18 1EX",
    "wof:placetype": "postalcode"
  },
  "geometry": {"coordinates":[-1.755191,53.839054],"type":"Point"}
}
