{
  "type": "Feature",
  "properties": {
    "date:inception_lower":"1980-01-01",
    "date:inception_upper":"1980-01-31",
    "iso:country":"GB",
    "wof:name":"BD18 1EX",
    "wof:placetype":"postalcode"
},
  "geometry": {"coordinates":[-1.755191,53.839054],"type":"Point"}
}