{
  "type": "Feature",
  "properties": {
    "iso:country":"GB",
    "wof:name":"TA21 8TD",
    "wof:placetype":"postalcode"
},
  "geometry": {"coordinates":[-3.2250386663645,50.98225375699628],"type":"Point"}
}