{
  "type": "Feature",
  "properties": {
    "iso:country": "GB",
    "wof:name": "HU9 3AW",
    "wof:placetype": "postalcode"
  },
  "geometry": {"coordinates":[-0.285732,53.755037],"type":"Point"}
}
