{
  "type": "Feature",
  "properties": {
    "iso:country":"GB",
    "wof:name":"HU9 3AW",
    "wof:placetype":"postalcode"
},
  "geometry": {"coordinates":[-0.28573194511919,53.75503725936566],"type":"Point"}
}