{
  "type": "Feature",
  "properties": {
    "iso:country":"GB",
    "wof:name":"ME8 7LR",
    "wof:placetype":"postalcode"
},
  "geometry": {"coordinates":[0.60250954053623,51.3654394848898],"type":"Point"}
}