{
  "type": "Feature",
  "properties": {
    "iso:country": "GB",
    "wof:name": "NE13 7AN",
    "wof:placetype": "postalcode"
  },
  "geometry": {"coordinates":[-1.665942,55.018543],"type":"Point"}
}
