{
  "type": "Feature",
  "properties": {
    "date:inception_lower": "2009-02-01",
    "date:inception_upper": "2009-02-01",
    "iso:country": "GB",
    "wof:name": "CV8 2TL",
    "wof:placetype": "postalcode"
  },
  "geometry": {"coordinates":[-1.529078,52.340873],"type":"Point"}
}
