{
  "type": "Feature",
  "properties": {
    "iso:country":"GB",
    "wof:name":"BH9 2BG",
    "wof:placetype":"postalcode"
},
  "geometry": {"coordinates":[-1.87589769222111,50.75271545580053],"type":"Point"}
}