{
  "type": "Feature",
  "properties": {
    "iso:country": "GB",
    "wof:name": "SL9 8QS",
    "wof:placetype": "postalcode"
  },
  "geometry": {"coordinates":[-0.553919,51.590821],"type":"Point"}
}
