{
  "type": "Feature",
  "properties": {
    "iso:country": "GB",
    "wof:name": "EH14 1DG",
    "wof:placetype": "postalcode"
  },
  "geometry": {"coordinates":[-3.240555,55.920556],"type":"Point"}
}
