{
  "type": "Feature",
  "properties": {
    "iso:country":"GB",
    "wof:name":"WF10 3UZ",
    "wof:placetype":"postalcode"
},
  "geometry": {"coordinates":[-1.32994507022775,53.72052453404132],"type":"Point"}
}