{
  "type": "Feature",
  "properties": {
    "iso:country":"GB",
    "wof:name":"ST5 3AW",
    "wof:placetype":"postalcode"
},
  "geometry": {"coordinates":[-2.21849053145118,52.99754186578628],"type":"Point"}
}