{
  "type": "Feature",
  "properties": {
    "iso:country": "GB",
    "wof:name": "ST5 3AW",
    "wof:placetype": "postalcode"
  },
  "geometry": {"coordinates":[-2.21849,52.997542],"type":"Point"}
}
