{
  "type": "Feature",
  "properties": {
    "iso:country": "GB",
    "wof:name": "SE24 9BE",
    "wof:placetype": "postalcode"
  },
  "geometry": {"coordinates":[-0.106604,51.442951],"type":"Point"}
}
