{
  "type": "Feature",
  "properties": {
    "iso:country":"GB",
    "wof:name":"CM1 7PE",
    "wof:placetype":"postalcode"
},
  "geometry": {"coordinates":[0.48395978478664,51.74755770064929],"type":"Point"}
}