{
  "type": "Feature",
  "properties": {
    "iso:country": "GB",
    "wof:name": "EH24 9BF",
    "wof:placetype": "postalcode"
  },
  "geometry": {"coordinates":[-3.134824,55.85671],"type":"Point"}
}
