{
  "type": "Feature",
  "properties": {
    "date:inception_lower": "2016-05-01",
    "date:inception_upper": "2016-05-01",
    "iso:country": "GB",
    "wof:name": "EH24 9BF",
    "wof:placetype": "postalcode"
  },
  "geometry": {"coordinates":[-3.134824,55.85671],"type":"Point"}
}
