{
  "type": "Feature",
  "properties": {
    "iso:country":"GB",
    "wof:name":"TR15 3PA",
    "wof:placetype":"postalcode"
},
  "geometry": {"coordinates":[-5.26469124479078,50.22930665476171],"type":"Point"}
}