{
  "type": "Feature",
  "properties": {
    "iso:country":"GB",
    "wof:name":"NP12 1ET",
    "wof:placetype":"postalcode"
},
  "geometry": {"coordinates":[-3.20835241170106,51.6721538014384],"type":"Point"}
}