{
  "type": "Feature",
  "properties": {
    "iso:country":"GB",
    "wof:name":"CV21 1EE",
    "wof:placetype":"postalcode"
},
  "geometry": {"coordinates":[-1.23894237244106,52.3899153298246],"type":"Point"}
}