{
  "type": "Feature",
  "properties": {
    "iso:country": "GB",
    "wof:name": "CV21 1EE",
    "wof:placetype": "postalcode"
  },
  "geometry": {"coordinates":[-1.238942,52.389915],"type":"Point"}
}
