{
  "type": "Feature",
  "properties": {
    "date:inception_lower": "1981-06-01",
    "date:inception_upper": "1981-06-01",
    "iso:country": "GB",
    "wof:name": "CV21 1EE",
    "wof:placetype": "postalcode"
  },
  "geometry": {"coordinates":[-1.238942,52.389915],"type":"Point"}
}
