{
  "type": "Feature",
  "properties": {
    "date:inception_lower": "1980-01-01",
    "date:inception_upper": "1980-01-01",
    "iso:country": "GB",
    "wof:name": "SO20 6AP",
    "wof:placetype": "postalcode"
  },
  "geometry": {"coordinates":[-1.439488,51.154079],"type":"Point"}
}
