{
  "type": "Feature",
  "properties": {
    "iso:country": "GB",
    "wof:name": "DE56 4EQ",
    "wof:placetype": "postalcode"
  },
  "geometry": {"coordinates":[-1.486846,52.987522],"type":"Point"}
}
