{
  "type": "Feature",
  "properties": {
    "iso:country":"GB",
    "wof:name":"DE56 4EQ",
    "wof:placetype":"postalcode"
},
  "geometry": {"coordinates":[-1.48684613121214,52.98752187548636],"type":"Point"}
}