{
  "type": "Feature",
  "properties": {
    "iso:country":"GB",
    "wof:name":"EX36 3NP",
    "wof:placetype":"postalcode"
},
  "geometry": {"coordinates":[-3.7040182190184,51.03953974550245],"type":"Point"}
}