{
  "type": "Feature",
  "properties": {
    "iso:country": "GB",
    "wof:name": "HR9 5HY",
    "wof:placetype": "postalcode"
  },
  "geometry": {"coordinates":[-2.586289,51.914326],"type":"Point"}
}
