{
  "type": "Feature",
  "properties": {
    "date:inception_lower": "1980-01-01",
    "date:inception_upper": "1980-01-01",
    "iso:country": "GB",
    "wof:name": "HR9 5HY",
    "wof:placetype": "postalcode"
  },
  "geometry": {"coordinates":[-2.586187,51.914281],"type":"Point"}
}
