{
  "type": "Feature",
  "properties": {
    "iso:country":"GB",
    "wof:name":"PO36 0DL",
    "wof:placetype":"postalcode"
},
  "geometry": {"coordinates":[-1.14468868792722,50.68184043252662],"type":"Point"}
}