{
  "type": "Feature",
  "properties": {
    "iso:country":"GB",
    "wof:name":"FY6 0HP",
    "wof:placetype":"postalcode"
},
  "geometry": {"coordinates":[-2.97067559063947,53.91646632486714],"type":"Point"}
}