{
  "type": "Feature",
  "properties": {
    "iso:country":"GB",
    "wof:name":"TS17 6NL",
    "wof:placetype":"postalcode"
},
  "geometry": {"coordinates":[-1.29943395901409,54.55558172563399],"type":"Point"}
}