{
  "type": "Feature",
  "properties": {
    "iso:country":"GB",
    "wof:name":"SG12 7NN",
    "wof:placetype":"postalcode"
},
  "geometry": {"coordinates":[-0.02330111003707,51.81916094474653],"type":"Point"}
}