{
  "type": "Feature",
  "properties": {
    "iso:country":"GB",
    "wof:name":"LU2 7SW",
    "wof:placetype":"postalcode"
},
  "geometry": {"coordinates":[-0.40212023107656,51.89148428219321],"type":"Point"}
}