{
  "type": "Feature",
  "properties": {
    "iso:country": "GB",
    "wof:name": "LU2 7SW",
    "wof:placetype": "postalcode"
  },
  "geometry": {"coordinates":[-0.40212,51.891484],"type":"Point"}
}
