{
  "type": "Feature",
  "properties": {
    "date:inception_lower": "1980-01-01",
    "date:inception_upper": "1980-01-01",
    "iso:country": "GB",
    "wof:name": "NG33 4AF",
    "wof:placetype": "postalcode"
  },
  "geometry": {"coordinates":[-0.56619,52.895506],"type":"Point"}
}
