{
  "type": "Feature",
  "properties": {
    "iso:country":"GB",
    "wof:name":"PH11 8HT",
    "wof:placetype":"postalcode"
},
  "geometry": {"coordinates":[-3.23739509097201,56.67515687573992],"type":"Point"}
}