{
  "type": "Feature",
  "properties": {
    "iso:country":"GB",
    "wof:name":"BR6 9RL",
    "wof:placetype":"postalcode"
},
  "geometry": {"coordinates":[0.08319859449389,51.37106103583778],"type":"Point"}
}