{
  "type": "Feature",
  "properties": {
    "iso:country":"GB",
    "wof:name":"WF9 1GA",
    "wof:placetype":"postalcode"
},
  "geometry": {"coordinates":[-1.31524758787717,53.62047318068142],"type":"Point"}
}