{
  "type": "Feature",
  "properties": {
    "date:inception_lower": "2007-09-01",
    "date:inception_upper": "2007-09-01",
    "iso:country": "GB",
    "wof:name": "WF9 1GA",
    "wof:placetype": "postalcode"
  },
  "geometry": {"coordinates":[-1.315248,53.620473],"type":"Point"}
}
