{
  "type": "Feature",
  "properties": {
    "iso:country":"GB",
    "wof:name":"PH2 6RJ",
    "wof:placetype":"postalcode"
},
  "geometry": {"coordinates":[-3.39976263775221,56.42379122099015],"type":"Point"}
}