{
  "type": "Feature",
  "properties": {
    "iso:country":"GB",
    "wof:name":"PH1 4HA",
    "wof:placetype":"postalcode"
},
  "geometry": {"coordinates":[-3.44284572959047,56.52573662034452],"type":"Point"}
}