{
  "type": "Feature",
  "properties": {
    "iso:country":"GB",
    "wof:name":"LS25 5EH",
    "wof:placetype":"postalcode"
},
  "geometry": {"coordinates":[-1.22518927221458,53.75981017199881],"type":"Point"}
}