{
  "type": "Feature",
  "properties": {
    "iso:country": "GB",
    "wof:name": "LS25 5EH",
    "wof:placetype": "postalcode"
  },
  "geometry": {"coordinates":[-1.225189,53.75981],"type":"Point"}
}
