{
  "type": "Feature",
  "properties": {
    "date:inception_lower": "1980-01-01",
    "date:inception_upper": "1980-01-01",
    "iso:country": "GB",
    "wof:name": "SL6 0PG",
    "wof:placetype": "postalcode"
  },
  "geometry": {"coordinates":[-0.661136,51.520985],"type":"Point"}
}
