{
  "type": "Feature",
  "properties": {
    "iso:country":"GB",
    "wof:name":"BA14 0AY",
    "wof:placetype":"postalcode"
},
  "geometry": {"coordinates":[-2.21786922476554,51.31478744039556],"type":"Point"}
}