{
  "type": "Feature",
  "properties": {
    "iso:country":"GB",
    "wof:name":"CB6 1TH",
    "wof:placetype":"postalcode"
},
  "geometry": {"coordinates":[0.27754911611651,52.40905972202441],"type":"Point"}
}