{
  "type": "Feature",
  "properties": {
    "date:inception_lower":"1992-08-01",
    "date:inception_upper":"1992-08-31",
    "iso:country":"GB",
    "wof:name":"CB6 1TH",
    "wof:placetype":"postalcode"
},
  "geometry": {"coordinates":[0.277549,52.40906],"type":"Point"}
}