{
  "type": "Feature",
  "properties": {
    "iso:country":"GB",
    "wof:name":"B24 0LW",
    "wof:placetype":"postalcode"
},
  "geometry": {"coordinates":[-1.81243920119623,52.52636388652976],"type":"Point"}
}