{
  "type": "Feature",
  "properties": {
    "date:inception_lower": "2015-11-01",
    "date:inception_upper": "2015-11-01",
    "iso:country": "GB",
    "wof:name": "IP13 0AF",
    "wof:placetype": "postalcode"
  },
  "geometry": {"coordinates":[1.355426,52.152805],"type":"Point"}
}
