{
  "type": "Feature",
  "properties": {
    "date:inception_lower": "1995-12-01",
    "date:inception_upper": "1995-12-01",
    "iso:country": "GB",
    "wof:name": "SA8 3JE",
    "wof:placetype": "postalcode"
  },
  "geometry": {"coordinates":[-3.827161,51.720596],"type":"Point"}
}
