{
  "type": "Feature",
  "properties": {
    "iso:country": "GB",
    "wof:name": "SA8 3JE",
    "wof:placetype": "postalcode"
  },
  "geometry": {"coordinates":[-3.827161,51.720596],"type":"Point"}
}
