{
  "type": "Feature",
  "properties": {
    "date:inception_lower": "2008-12-01",
    "date:inception_upper": "2008-12-01",
    "iso:country": "GB",
    "wof:name": "LN8 3LL",
    "wof:placetype": "postalcode"
  },
  "geometry": {"coordinates":[-0.363541,53.385915],"type":"Point"}
}
