{
  "type": "Feature",
  "properties": {
    "date:inception_lower":"1980-01-01",
    "date:inception_upper":"1980-01-31",
    "iso:country":"GB",
    "wof:name":"DH3 2JJ",
    "wof:placetype":"postalcode"
},
  "geometry": {"coordinates":[-1.561312,54.891046],"type":"Point"}
}