{
  "type": "Feature",
  "properties": {
    "iso:country": "GB",
    "wof:name": "M2 3HQ",
    "wof:placetype": "postalcode"
  },
  "geometry": {"coordinates":[-2.240067,53.479884],"type":"Point"}
}
