{
  "type": "Feature",
  "properties": {
    "date:inception_lower":"1980-01-01",
    "date:inception_upper":"1980-01-31",
    "iso:country":"GB",
    "wof:name":"M2 3HQ",
    "wof:placetype":"postalcode"
},
  "geometry": {"coordinates":[-2.240067,53.479884],"type":"Point"}
}