{
  "type": "Feature",
  "properties": {
    "iso:country":"GB",
    "wof:name":"M2 3HQ",
    "wof:placetype":"postalcode"
},
  "geometry": {"coordinates":[-2.2400698184452,53.47986747787517],"type":"Point"}
}