{
  "type": "Feature",
  "properties": {
    "iso:country": "GB",
    "wof:name": "TS26 0DQ",
    "wof:placetype": "postalcode"
  },
  "geometry": {"coordinates":[-1.243692,54.706793],"type":"Point"}
}
