{
  "type": "Feature",
  "properties": {
    "iso:country":"GB",
    "wof:name":"BS9 4PG",
    "wof:placetype":"postalcode"
},
  "geometry": {"coordinates":[-2.60282695329773,51.49159086906177],"type":"Point"}
}