{
  "type": "Feature",
  "properties": {
    "iso:country":"GB",
    "wof:name":"LE7 7SW",
    "wof:placetype":"postalcode"
},
  "geometry": {"coordinates":[-1.18311384339071,52.66749936280413],"type":"Point"}
}