{
  "type": "Feature",
  "properties": {
    "date:inception_lower":"2011-09-01",
    "date:inception_upper":"2011-09-30",
    "iso:country":"GB",
    "wof:name":"LE7 7SW",
    "wof:placetype":"postalcode"
},
  "geometry": {"coordinates":[-1.183114,52.667499],"type":"Point"}
}