{
  "type": "Feature",
  "properties": {
    "iso:country": "GB",
    "wof:name": "LE7 7SW",
    "wof:placetype": "postalcode"
  },
  "geometry": {"coordinates":[-1.183114,52.667499],"type":"Point"}
}
