{
  "type": "Feature",
  "properties": {
    "iso:country": "GB",
    "wof:name": "BL9 9JD",
    "wof:placetype": "postalcode"
  },
  "geometry": {"coordinates":[-2.289411,53.582783],"type":"Point"}
}
