{
  "type": "Feature",
  "properties": {
    "iso:country":"GB",
    "wof:name":"BL9 9JD",
    "wof:placetype":"postalcode"
},
  "geometry": {"coordinates":[-2.28941086324024,53.58278301942061],"type":"Point"}
}