{
  "type": "Feature",
  "properties": {
    "iso:country": "GB",
    "wof:name": "NN29 7RN",
    "wof:placetype": "postalcode"
  },
  "geometry": {"coordinates":[-0.670691,52.25742],"type":"Point"}
}
