{
  "type": "Feature",
  "properties": {
    "iso:country":"GB",
    "wof:name":"NN29 7RN",
    "wof:placetype":"postalcode"
},
  "geometry": {"coordinates":[-0.67069086893568,52.25742012262325],"type":"Point"}
}