{
  "type": "Feature",
  "properties": {
    "date:inception_lower":"1980-01-01",
    "date:inception_upper":"1980-01-31",
    "iso:country":"GB",
    "wof:name":"L37 6DW",
    "wof:placetype":"postalcode"
},
  "geometry": {"coordinates":[-3.049914,53.548125],"type":"Point"}
}