{
  "type": "Feature",
  "properties": {
    "date:inception_lower":"1995-07-01",
    "date:inception_upper":"1995-07-31",
    "iso:country":"GB",
    "wof:name":"CV36 4SB",
    "wof:placetype":"postalcode"
},
  "geometry": {"coordinates":[-1.632531,52.064957],"type":"Point"}
}