{
  "type": "Feature",
  "properties": {
    "iso:country":"GB",
    "wof:name":"CV36 4SB",
    "wof:placetype":"postalcode"
},
  "geometry": {"coordinates":[-1.63253063866452,52.06495654120247],"type":"Point"}
}