{
  "type": "Feature",
  "properties": {
    "iso:country":"GB",
    "wof:name":"NN13 5LG",
    "wof:placetype":"postalcode"
},
  "geometry": {"coordinates":[-1.2013866678435,52.0378661728374],"type":"Point"}
}