{
  "type": "Feature",
  "properties": {
    "date:inception_lower": "1980-01-01",
    "date:inception_upper": "1980-01-01",
    "iso:country": "GB",
    "wof:name": "PR1 8EQ",
    "wof:placetype": "postalcode"
  },
  "geometry": {"coordinates":[-2.71418,53.750629],"type":"Point"}
}
