{
  "type": "Feature",
  "properties": {
    "date:inception_lower": "2011-01-01",
    "date:inception_upper": "2011-01-01",
    "iso:country": "GB",
    "wof:name": "WR8 0XB",
    "wof:placetype": "postalcode"
  },
  "geometry": {"coordinates":[-2.218103,52.062693],"type":"Point"}
}
