{
  "type": "Feature",
  "properties": {
    "iso:country":"GB",
    "wof:name":"CM9 5ET",
    "wof:placetype":"postalcode"
},
  "geometry": {"coordinates":[0.68041372176319,51.73081953899023],"type":"Point"}
}