{
  "type": "Feature",
  "properties": {
    "date:inception_lower":"1997-12-01",
    "date:inception_upper":"1997-12-31",
    "iso:country":"GB",
    "wof:name":"BS40 5QT",
    "wof:placetype":"postalcode"
},
  "geometry": {"coordinates":[-2.761479,51.359529],"type":"Point"}
}