{
  "type": "Feature",
  "properties": {
    "date:inception_lower":"1998-06-01",
    "date:inception_upper":"1998-06-30",
    "iso:country":"GB",
    "wof:name":"YO24 2SG",
    "wof:placetype":"postalcode"
},
  "geometry": {"coordinates":[-1.126028,53.93962],"type":"Point"}
}