{
  "type": "Feature",
  "properties": {
    "iso:country": "GB",
    "wof:name": "YO11 3BA",
    "wof:placetype": "postalcode"
  },
  "geometry": {"coordinates":[-0.396788,54.264527],"type":"Point"}
}
