{
  "type": "Feature",
  "properties": {
    "iso:country": "GB",
    "wof:name": "PL21 9DU",
    "wof:placetype": "postalcode"
  },
  "geometry": {"coordinates":[-3.924872,50.385074],"type":"Point"}
}
