{
  "type": "Feature",
  "properties": {
    "iso:country":"GB",
    "wof:name":"PL21 9DU",
    "wof:placetype":"postalcode"
},
  "geometry": {"coordinates":[-3.92487230628858,50.38507434704789],"type":"Point"}
}