{
  "type": "Feature",
  "properties": {
    "iso:country": "GB",
    "wof:name": "LA10 5BG",
    "wof:placetype": "postalcode"
  },
  "geometry": {"coordinates":[-2.523641,54.323017],"type":"Point"}
}
