{
  "type": "Feature",
  "properties": {
    "iso:country":"GB",
    "wof:name":"LA10 5BG",
    "wof:placetype":"postalcode"
},
  "geometry": {"coordinates":[-2.52368335561863,54.32299774716421],"type":"Point"}
}