{
  "type": "Feature",
  "properties": {
    "iso:country":"GB",
    "wof:name":"M90 5YP",
    "wof:placetype":"postalcode"
},
  "geometry": {"coordinates":[-2.28552586652381,53.35806231736186],"type":"Point"}
}