{
  "type": "Feature",
  "properties": {
    "date:inception_lower": "1995-12-01",
    "date:inception_upper": "1995-12-01",
    "iso:country": "GB",
    "wof:name": "M90 5YP",
    "wof:placetype": "postalcode"
  },
  "geometry": {"coordinates":[-2.285526,53.358062],"type":"Point"}
}
