{
  "type": "Feature",
  "properties": {
    "iso:country":"GB",
    "wof:name":"WV4 6BH",
    "wof:placetype":"postalcode"
},
  "geometry": {"coordinates":[-2.1094774014141,52.56413770931306],"type":"Point"}
}