{
  "type": "Feature",
  "properties": {
    "date:inception_lower":"1980-01-01",
    "date:inception_upper":"1980-01-31",
    "iso:country":"GB",
    "wof:name":"LA14 5PA",
    "wof:placetype":"postalcode"
},
  "geometry": {"coordinates":[-3.224741,54.124639],"type":"Point"}
}