{
  "type": "Feature",
  "properties": {
    "iso:country":"GB",
    "wof:name":"LA14 5PA",
    "wof:placetype":"postalcode"
},
  "geometry": {"coordinates":[-3.2247413662746,54.12463917107008],"type":"Point"}
}