{
  "type": "Feature",
  "properties": {
    "iso:country":"GB",
    "wof:name":"W5 5ED",
    "wof:placetype":"postalcode"
},
  "geometry": {"coordinates":[-0.30658632543117,51.50961317741726],"type":"Point"}
}