{
  "type": "Feature",
  "properties": {
    "iso:country":"GB",
    "wof:name":"AB10 1YA",
    "wof:placetype":"postalcode"
},
  "geometry": {"coordinates":[-2.12178763761348,57.14397872629837],"type":"Point"}
}