{
  "type": "Feature",
  "properties": {
    "date:inception_lower":"1980-01-01",
    "date:inception_upper":"1980-01-31",
    "iso:country":"GB",
    "wof:name":"CA3 8PX",
    "wof:placetype":"postalcode"
},
  "geometry": {"coordinates":[-2.93572,54.896167],"type":"Point"}
}