{
  "type": "Feature",
  "properties": {
    "iso:country": "GB",
    "wof:name": "CA3 8PX",
    "wof:placetype": "postalcode"
  },
  "geometry": {"coordinates":[-2.93572,54.896167],"type":"Point"}
}
