{
  "type": "Feature",
  "properties": {
    "iso:country":"GB",
    "wof:name":"AB51 0LU",
    "wof:placetype":"postalcode"
},
  "geometry": {"coordinates":[-2.34795409102528,57.27300874658455],"type":"Point"}
}