{
  "type": "Feature",
  "properties": {
    "iso:country":"GB",
    "wof:name":"PE7 2AW",
    "wof:placetype":"postalcode"
},
  "geometry": {"coordinates":[-0.09399760560131,52.55583502289665],"type":"Point"}
}