{
  "type": "Feature",
  "properties": {
    "date:inception_lower": "2004-02-01",
    "date:inception_upper": "2004-02-01",
    "iso:country": "GB",
    "wof:name": "SP9 7RR",
    "wof:placetype": "postalcode"
  },
  "geometry": {"coordinates":[-1.667912,51.232479],"type":"Point"}
}
