{
  "type": "Feature",
  "properties": {
    "iso:country": "GB",
    "wof:name": "SP9 7RR",
    "wof:placetype": "postalcode"
  },
  "geometry": {"coordinates":[-1.667912,51.232479],"type":"Point"}
}
