{
  "type": "Feature",
  "properties": {
    "iso:country": "GB",
    "wof:name": "PO20 8LA",
    "wof:placetype": "postalcode"
  },
  "geometry": {"coordinates":[-0.857328,50.760828],"type":"Point"}
}
