{
  "type": "Feature",
  "properties": {
    "iso:country":"GB",
    "wof:name":"PO20 8LA",
    "wof:placetype":"postalcode"
},
  "geometry": {"coordinates":[-0.85732769975303,50.76082794585341],"type":"Point"}
}