{
  "type": "Feature",
  "properties": {
    "iso:country":"GB",
    "wof:name":"CM2 8PE",
    "wof:placetype":"postalcode"
},
  "geometry": {"coordinates":[0.4779717253685,51.70114502633515],"type":"Point"}
}