{
  "type": "Feature",
  "properties": {
    "date:inception_lower": "1980-01-01",
    "date:inception_upper": "1980-01-01",
    "iso:country": "GB",
    "wof:name": "CM2 8PE",
    "wof:placetype": "postalcode"
  },
  "geometry": {"coordinates":[0.477972,51.701145],"type":"Point"}
}
