{
  "type": "Feature",
  "properties": {
    "iso:country":"GB",
    "wof:name":"WF11 8AZ",
    "wof:placetype":"postalcode"
},
  "geometry": {"coordinates":[-1.23668583674962,53.70881244080869],"type":"Point"}
}