{
  "type": "Feature",
  "properties": {
    "iso:country":"GB",
    "wof:name":"TA10 9NQ",
    "wof:placetype":"postalcode"
},
  "geometry": {"coordinates":[-2.770265731605,51.03359161862625],"type":"Point"}
}