{
  "type": "Feature",
  "properties": {
    "iso:country":"GB",
    "wof:name":"G13 3HU",
    "wof:placetype":"postalcode"
},
  "geometry": {"coordinates":[-4.35854341013142,55.89770357001006],"type":"Point"}
}