{
  "type": "Feature",
  "properties": {
    "iso:country":"GB",
    "wof:name":"OL13 0TT",
    "wof:placetype":"postalcode"
},
  "geometry": {"coordinates":[-2.21703308205202,53.69234991377748],"type":"Point"}
}