{
  "type": "Feature",
  "properties": {
    "iso:country":"GB",
    "wof:name":"BN1 3HQ",
    "wof:placetype":"postalcode"
},
  "geometry": {"coordinates":[-0.14833633965556,50.82796409103222],"type":"Point"}
}