{
  "type": "Feature",
  "properties": {
    "iso:country": "GB",
    "wof:name": "BN1 3HQ",
    "wof:placetype": "postalcode"
  },
  "geometry": {"coordinates":[-0.148378,50.827983],"type":"Point"}
}
