{
  "type": "Feature",
  "properties": {
    "iso:country":"GB",
    "wof:name":"SA33 6LP",
    "wof:placetype":"postalcode"
},
  "geometry": {"coordinates":[-4.31539726410925,51.93864908540601],"type":"Point"}
}