{
  "type": "Feature",
  "properties": {
    "iso:country":"GB",
    "wof:name":"RG25 3HG",
    "wof:placetype":"postalcode"
},
  "geometry": {"coordinates":[-1.26632432757147,51.24396868088803],"type":"Point"}
}