{
  "type": "Feature",
  "properties": {
    "iso:country":"GB",
    "wof:name":"CA11 7DH",
    "wof:placetype":"postalcode"
},
  "geometry": {"coordinates":[-2.75588854415847,54.66263120046611],"type":"Point"}
}