{
  "type": "Feature",
  "properties": {
    "date:inception_lower": "1996-12-01",
    "date:inception_upper": "1996-12-01",
    "iso:country": "GB",
    "wof:name": "CA11 7DH",
    "wof:placetype": "postalcode"
  },
  "geometry": {"coordinates":[-2.755659,54.662586],"type":"Point"}
}
