{
  "type": "Feature",
  "properties": {
    "iso:country":"GB",
    "wof:name":"G32 0LH",
    "wof:placetype":"postalcode"
},
  "geometry": {"coordinates":[-4.15545194341277,55.85717482979168],"type":"Point"}
}