{
  "type": "Feature",
  "properties": {
    "iso:country":"GB",
    "wof:name":"IG8 9HD",
    "wof:placetype":"postalcode"
},
  "geometry": {"coordinates":[0.0212578404168,51.60551658635998],"type":"Point"}
}