{
  "type": "Feature",
  "properties": {
    "iso:country":"GB",
    "wof:name":"BS3 2BG",
    "wof:placetype":"postalcode"
},
  "geometry": {"coordinates":[-2.62118858628067,51.43307633282243],"type":"Point"}
}