{
  "type": "Feature",
  "properties": {
    "iso:country": "GB",
    "wof:name": "NR12 9NS",
    "wof:placetype": "postalcode"
  },
  "geometry": {"coordinates":[1.460833,52.75621],"type":"Point"}
}
