{
  "type": "Feature",
  "properties": {
    "iso:country":"GB",
    "wof:name":"NR6 6NG",
    "wof:placetype":"postalcode"
},
  "geometry": {"coordinates":[1.27956840509129,52.66430712104944],"type":"Point"}
}