{
  "type": "Feature",
  "properties": {
    "date:inception_lower": "1980-01-01",
    "date:inception_upper": "1980-01-01",
    "iso:country": "GB",
    "wof:name": "LE7 7FY",
    "wof:placetype": "postalcode"
  },
  "geometry": {"coordinates":[-1.193473,52.671094],"type":"Point"}
}
