{
  "type": "Feature",
  "properties": {
    "iso:country":"GB",
    "wof:name":"LE7 7FY",
    "wof:placetype":"postalcode"
},
  "geometry": {"coordinates":[-1.19347281128262,52.67109432643836],"type":"Point"}
}