{
  "type": "Feature",
  "properties": {
    "iso:country":"GB",
    "wof:name":"KY5 0XU",
    "wof:placetype":"postalcode"
},
  "geometry": {"coordinates":[-3.23933359154149,56.17367390470291],"type":"Point"}
}