{
  "type": "Feature",
  "properties": {
    "iso:country":"GB",
    "wof:name":"CV9 1ES",
    "wof:placetype":"postalcode"
},
  "geometry": {"coordinates":[-1.54481826612995,52.57559488431282],"type":"Point"}
}