{
  "type": "Feature",
  "properties": {
    "date:inception_lower": "2011-12-01",
    "date:inception_upper": "2011-12-01",
    "iso:country": "GB",
    "wof:name": "LN6 9YP",
    "wof:placetype": "postalcode"
  },
  "geometry": {"coordinates":[-0.658475,53.151229],"type":"Point"}
}
