{
  "type": "Feature",
  "properties": {
    "date:inception_lower": "2000-06-01",
    "date:inception_upper": "2000-06-01",
    "iso:country": "GB",
    "wof:name": "TQ1 1PL",
    "wof:placetype": "postalcode"
  },
  "geometry": {"coordinates":[-3.527735,50.466832],"type":"Point"}
}
