{
  "type": "Feature",
  "properties": {
    "iso:country":"GB",
    "wof:name":"SL4 3HR",
    "wof:placetype":"postalcode"
},
  "geometry": {"coordinates":[-0.61513827921816,51.48164997953693],"type":"Point"}
}