{
  "type": "Feature",
  "properties": {
    "iso:country": "GB",
    "wof:name": "WA3 3HW",
    "wof:placetype": "postalcode"
  },
  "geometry": {"coordinates":[-2.586444,53.476871],"type":"Point"}
}
