{
  "type": "Feature",
  "properties": {
    "iso:country":"GB",
    "wof:name":"WA3 3HW",
    "wof:placetype":"postalcode"
},
  "geometry": {"coordinates":[-2.58644413133135,53.4768713006013],"type":"Point"}
}