{
  "type": "Feature",
  "properties": {
    "date:inception_lower":"1995-07-01",
    "date:inception_upper":"1995-07-31",
    "iso:country":"GB",
    "wof:name":"HS9 5UQ",
    "wof:placetype":"postalcode"
},
  "geometry": {"coordinates":[-7.480294,56.955721],"type":"Point"}
}