{
  "type": "Feature",
  "properties": {
    "iso:country":"GB",
    "wof:name":"HS9 5UQ",
    "wof:placetype":"postalcode"
},
  "geometry": {"coordinates":[-7.48053826262503,56.95560735741088],"type":"Point"}
}