{
  "type": "Feature",
  "properties": {
    "date:inception_lower":"1980-01-01",
    "date:inception_upper":"1980-01-31",
    "iso:country":"GB",
    "wof:name":"HR4 0JG",
    "wof:placetype":"postalcode"
},
  "geometry": {"coordinates":[-2.744137,52.059474],"type":"Point"}
}