{
  "type": "Feature",
  "properties": {
    "iso:country":"GB",
    "wof:name":"HR4 0JG",
    "wof:placetype":"postalcode"
},
  "geometry": {"coordinates":[-2.74413727339578,52.0594735887658],"type":"Point"}
}