{
  "type": "Feature",
  "properties": {
    "iso:country": "GB",
    "wof:name": "TS5 8HR",
    "wof:placetype": "postalcode"
  },
  "geometry": {"coordinates":[-1.253138,54.531965],"type":"Point"}
}
