{
  "type": "Feature",
  "properties": {
    "iso:country":"GB",
    "wof:name":"MK45 3HN",
    "wof:placetype":"postalcode"
},
  "geometry": {"coordinates":[-0.45042167339656,52.08189593163991],"type":"Point"}
}