{
  "type": "Feature",
  "properties": {
    "iso:country": "GB",
    "wof:name": "MK45 3HN",
    "wof:placetype": "postalcode"
  },
  "geometry": {"coordinates":[-0.450422,52.081896],"type":"Point"}
}
