{
  "type": "Feature",
  "properties": {
    "iso:country":"GB",
    "wof:name":"RG31 4TF",
    "wof:placetype":"postalcode"
},
  "geometry": {"coordinates":[-1.0512491355538,51.44882519499053],"type":"Point"}
}