{
  "type": "Feature",
  "properties": {
    "iso:country":"GB",
    "wof:name":"PR4 4BQ",
    "wof:placetype":"postalcode"
},
  "geometry": {"coordinates":[-2.75400016805908,53.73266013305744],"type":"Point"}
}