{
  "type": "Feature",
  "properties": {
    "iso:country":"GB",
    "wof:name":"RM1 2QD",
    "wof:placetype":"postalcode"
},
  "geometry": {"coordinates":[0.19166686613543,51.57395077965625],"type":"Point"}
}