{
  "type": "Feature",
  "properties": {
    "iso:country":"GB",
    "wof:name":"GL6 0DG",
    "wof:placetype":"postalcode"
},
  "geometry": {"coordinates":[-2.2212066494112,51.69404147049821],"type":"Point"}
}