{
  "type": "Feature",
  "properties": {
    "iso:country": "GB",
    "wof:name": "BH14 8JU",
    "wof:placetype": "postalcode"
  },
  "geometry": {"coordinates":[-1.943554,50.70802],"type":"Point"}
}
