{
  "type": "Feature",
  "properties": {
    "iso:country": "GB",
    "wof:name": "RG21 4PF",
    "wof:placetype": "postalcode"
  },
  "geometry": {"coordinates":[-1.069791,51.264081],"type":"Point"}
}
