{
  "type": "Feature",
  "properties": {
    "iso:country":"GB",
    "wof:name":"SG9 0NY",
    "wof:placetype":"postalcode"
},
  "geometry": {"coordinates":[0.03749637886591,51.95285355117736],"type":"Point"}
}