{
  "type": "Feature",
  "properties": {
    "date:inception_lower": "2014-01-01",
    "date:inception_upper": "2014-01-01",
    "iso:country": "GB",
    "wof:name": "EX13 5TQ",
    "wof:placetype": "postalcode"
  },
  "geometry": {"coordinates":[-2.978669,50.789238],"type":"Point"}
}
