{
  "type": "Feature",
  "properties": {
    "iso:country":"GB",
    "wof:name":"EX13 5TQ",
    "wof:placetype":"postalcode"
},
  "geometry": {"coordinates":[-2.97873414778461,50.78927471568649],"type":"Point"}
}