{
  "type": "Feature",
  "properties": {
    "date:inception_lower":"1980-01-01",
    "date:inception_upper":"1980-01-31",
    "iso:country":"GB",
    "wof:name":"EX3 0BU",
    "wof:placetype":"postalcode"
},
  "geometry": {"coordinates":[-3.471899,50.694871],"type":"Point"}
}