{
  "type": "Feature",
  "properties": {
    "iso:country": "GB",
    "wof:name": "EX3 0BU",
    "wof:placetype": "postalcode"
  },
  "geometry": {"coordinates":[-3.471899,50.694871],"type":"Point"}
}
