{
  "type": "Feature",
  "properties": {
    "iso:country": "GB",
    "wof:name": "DL2 2JH",
    "wof:placetype": "postalcode"
  },
  "geometry": {"coordinates":[-1.535851,54.484527],"type":"Point"}
}
