{
  "type": "Feature",
  "properties": {
    "iso:country":"GB",
    "wof:name":"DL2 2JH",
    "wof:placetype":"postalcode"
},
  "geometry": {"coordinates":[-1.53585082664782,54.48452678471903],"type":"Point"}
}