{
  "type": "Feature",
  "properties": {
    "iso:country": "GB",
    "wof:name": "DY9 9UJ",
    "wof:placetype": "postalcode"
  },
  "geometry": {"coordinates":[-2.092154,52.393631],"type":"Point"}
}
