{
  "type": "Feature",
  "properties": {
    "date:inception_lower": "1980-01-01",
    "date:inception_upper": "1980-01-01",
    "iso:country": "GB",
    "wof:name": "DY9 9UJ",
    "wof:placetype": "postalcode"
  },
  "geometry": {"coordinates":[-2.092154,52.393631],"type":"Point"}
}
