{
  "type": "Feature",
  "properties": {
    "iso:country":"GB",
    "wof:name":"DY9 9UJ",
    "wof:placetype":"postalcode"
},
  "geometry": {"coordinates":[-2.0921543520132,52.39363088720444],"type":"Point"}
}