{
  "type": "Feature",
  "properties": {
    "iso:country":"GB",
    "wof:name":"NW10 7AW",
    "wof:placetype":"postalcode"
},
  "geometry": {"coordinates":[-0.26846464349923,51.53408231869711],"type":"Point"}
}