{
  "type": "Feature",
  "properties": {
    "date:inception_lower":"1980-01-01",
    "date:inception_upper":"1980-01-31",
    "iso:country":"GB",
    "wof:name":"NE6 2BP",
    "wof:placetype":"postalcode"
},
  "geometry": {"coordinates":[-1.572277,54.968556],"type":"Point"}
}