{
  "type": "Feature",
  "properties": {
    "iso:country":"GB",
    "wof:name":"NE6 2BP",
    "wof:placetype":"postalcode"
},
  "geometry": {"coordinates":[-1.57227672581698,54.96855593951193],"type":"Point"}
}