{
  "type": "Feature",
  "properties": {
    "date:inception_lower": "1980-01-01",
    "date:inception_upper": "1980-01-01",
    "iso:country": "GB",
    "wof:name": "ST8 7NJ",
    "wof:placetype": "postalcode"
  },
  "geometry": {"coordinates":[-2.146623,53.118286],"type":"Point"}
}
