{
  "type": "Feature",
  "properties": {
    "iso:country":"GB",
    "wof:name":"NP12 1BU",
    "wof:placetype":"postalcode"
},
  "geometry": {"coordinates":[-3.19339442646034,51.67691948619994],"type":"Point"}
}