{
  "type": "Feature",
  "properties": {
    "iso:country":"GB",
    "wof:name":"PE14 0BT",
    "wof:placetype":"postalcode"
},
  "geometry": {"coordinates":[0.16792629823769,52.63546065428984],"type":"Point"}
}