{
  "type": "Feature",
  "properties": {
    "iso:country":"GB",
    "wof:name":"IP23 7PT",
    "wof:placetype":"postalcode"
},
  "geometry": {"coordinates":[1.15613620305157,52.29670755872688],"type":"Point"}
}