{
  "type": "Feature",
  "properties": {
    "date:inception_lower": "1980-01-01",
    "date:inception_upper": "1980-01-01",
    "iso:country": "GB",
    "wof:name": "IP23 7PT",
    "wof:placetype": "postalcode"
  },
  "geometry": {"coordinates":[1.154173,52.298002],"type":"Point"}
}
