{
  "type": "Feature",
  "properties": {
    "iso:country": "GB",
    "wof:name": "DE73 8AA",
    "wof:placetype": "postalcode"
  },
  "geometry": {"coordinates":[-1.42146,52.819362],"type":"Point"}
}
