{
  "type": "Feature",
  "properties": {
    "iso:country":"GB",
    "wof:name":"EH9 1UN",
    "wof:placetype":"postalcode"
},
  "geometry": {"coordinates":[-3.18655189853414,55.93582930292711],"type":"Point"}
}