{
  "type": "Feature",
  "properties": {
    "iso:country":"GB",
    "wof:name":"B70 0NA",
    "wof:placetype":"postalcode"
},
  "geometry": {"coordinates":[-2.02090652421221,52.53699237365203],"type":"Point"}
}