{
  "type": "Feature",
  "properties": {
    "iso:country":"GB",
    "wof:name":"PO20 2AL",
    "wof:placetype":"postalcode"
},
  "geometry": {"coordinates":[-0.71097963109211,50.85198424467841],"type":"Point"}
}