{
  "type": "Feature",
  "properties": {
    "iso:country":"GB",
    "wof:name":"PR4 1JE",
    "wof:placetype":"postalcode"
},
  "geometry": {"coordinates":[-2.86787729928298,53.76894819807424],"type":"Point"}
}