{
  "type": "Feature",
  "properties": {
    "iso:country":"GB",
    "wof:name":"S5 6HU",
    "wof:placetype":"postalcode"
},
  "geometry": {"coordinates":[-1.45372630856054,53.42259324904264],"type":"Point"}
}