{
  "type": "Feature",
  "properties": {
    "date:inception_lower": "1980-01-01",
    "date:inception_upper": "1980-01-01",
    "iso:country": "GB",
    "wof:name": "S5 6HU",
    "wof:placetype": "postalcode"
  },
  "geometry": {"coordinates":[-1.45352,53.422251],"type":"Point"}
}
