{
  "type": "Feature",
  "properties": {
    "iso:country": "GB",
    "wof:name": "S5 6HU",
    "wof:placetype": "postalcode"
  },
  "geometry": {"coordinates":[-1.45352,53.422251],"type":"Point"}
}
