{
  "type": "Feature",
  "properties": {
    "iso:country":"GB",
    "wof:name":"NP24 6DF",
    "wof:placetype":"postalcode"
},
  "geometry": {"coordinates":[-3.23714661946019,51.71676724564716],"type":"Point"}
}