{
  "type": "Feature",
  "properties": {
    "date:inception_lower":"2009-01-01",
    "date:inception_upper":"2009-01-31",
    "iso:country":"GB",
    "wof:name":"CO10 9GU",
    "wof:placetype":"postalcode"
},
  "geometry": {"coordinates":[0.709621,52.062558],"type":"Point"}
}