{
  "type": "Feature",
  "properties": {
    "iso:country": "GB",
    "wof:name": "CO10 9GU",
    "wof:placetype": "postalcode"
  },
  "geometry": {"coordinates":[0.70961,52.062599],"type":"Point"}
}
