{
  "type": "Feature",
  "properties": {
    "iso:country":"GB",
    "wof:name":"CO10 9GU",
    "wof:placetype":"postalcode"
},
  "geometry": {"coordinates":[0.70962052844218,52.06255770263018],"type":"Point"}
}