{
  "type": "Feature",
  "properties": {
    "iso:country": "GB",
    "wof:name": "RG27 0RD",
    "wof:placetype": "postalcode"
  },
  "geometry": {"coordinates":[-0.903017,51.359078],"type":"Point"}
}
