{
  "type": "Feature",
  "properties": {
    "iso:country":"GB",
    "wof:name":"RG27 0RD",
    "wof:placetype":"postalcode"
},
  "geometry": {"coordinates":[-0.90301680509841,51.35907817784095],"type":"Point"}
}