{
  "type": "Feature",
  "properties": {
    "iso:country":"GB",
    "wof:name":"LL15 2SS",
    "wof:placetype":"postalcode"
},
  "geometry": {"coordinates":[-3.297696884724,53.05373989126569],"type":"Point"}
}