{
  "type": "Feature",
  "properties": {
    "iso:country":"GB",
    "wof:name":"CW1 4BY",
    "wof:placetype":"postalcode"
},
  "geometry": {"coordinates":[-2.4378600060524,53.1037002349226],"type":"Point"}
}