{
  "type": "Feature",
  "properties": {
    "iso:country": "GB",
    "wof:name": "CW1 4BY",
    "wof:placetype": "postalcode"
  },
  "geometry": {"coordinates":[-2.43786,53.1037],"type":"Point"}
}
