{
  "type": "Feature",
  "properties": {
    "date:inception_lower": "1980-01-01",
    "date:inception_upper": "1980-01-01",
    "iso:country": "GB",
    "wof:name": "CW1 4BY",
    "wof:placetype": "postalcode"
  },
  "geometry": {"coordinates":[-2.43786,53.1037],"type":"Point"}
}
