{
  "type": "Feature",
  "properties": {
    "date:inception_lower": "1992-08-01",
    "date:inception_upper": "1992-08-01",
    "iso:country": "GB",
    "wof:name": "PE13 2PT",
    "wof:placetype": "postalcode"
  },
  "geometry": {"coordinates":[0.156387,52.659265],"type":"Point"}
}
