{
  "type": "Feature",
  "properties": {
    "iso:country":"GB",
    "wof:name":"PE13 2PT",
    "wof:placetype":"postalcode"
},
  "geometry": {"coordinates":[0.15638732556494,52.65926465692628],"type":"Point"}
}