{
  "type": "Feature",
  "properties": {
    "date:inception_lower": "1996-12-01",
    "date:inception_upper": "1996-12-01",
    "iso:country": "GB",
    "wof:name": "MK45 3WS",
    "wof:placetype": "postalcode"
  },
  "geometry": {"coordinates":[-0.447778,52.073976],"type":"Point"}
}
