{
  "type": "Feature",
  "properties": {
    "iso:country":"GB",
    "wof:name":"SR5 5PN",
    "wof:placetype":"postalcode"
},
  "geometry": {"coordinates":[-1.42094276340442,54.92546023057539],"type":"Point"}
}