{
  "type": "Feature",
  "properties": {
    "date:inception_lower":"1980-01-01",
    "date:inception_upper":"1980-01-31",
    "iso:country":"GB",
    "wof:name":"SR5 5PN",
    "wof:placetype":"postalcode"
},
  "geometry": {"coordinates":[-1.420943,54.92546],"type":"Point"}
}