{
  "type": "Feature",
  "properties": {
    "iso:country":"GB",
    "wof:name":"GU24 8AQ",
    "wof:placetype":"postalcode"
},
  "geometry": {"coordinates":[-0.60214289918995,51.34602849437274],"type":"Point"}
}