{
  "type": "Feature",
  "properties": {
    "date:inception_lower":"1980-01-01",
    "date:inception_upper":"1980-01-31",
    "iso:country":"GB",
    "wof:name":"CT4 5LP",
    "wof:placetype":"postalcode"
},
  "geometry": {"coordinates":[1.120202,51.24647],"type":"Point"}
}