{
  "type": "Feature",
  "properties": {
    "iso:country":"GB",
    "wof:name":"CT4 5LP",
    "wof:placetype":"postalcode"
},
  "geometry": {"coordinates":[1.12020184789547,51.24647026027904],"type":"Point"}
}