{
  "type": "Feature",
  "properties": {
    "iso:country": "GB",
    "wof:name": "CT4 5LP",
    "wof:placetype": "postalcode"
  },
  "geometry": {"coordinates":[1.120202,51.24647],"type":"Point"}
}
