{
  "type": "Feature",
  "properties": {
    "iso:country": "GB",
    "wof:name": "CR0 0EW",
    "wof:placetype": "postalcode"
  },
  "geometry": {"coordinates":[-0.00561,51.340259],"type":"Point"}
}
