{
  "type": "Feature",
  "properties": {
    "date:inception_lower": "1980-01-01",
    "date:inception_upper": "1980-01-01",
    "iso:country": "GB",
    "wof:name": "CR0 0EW",
    "wof:placetype": "postalcode"
  },
  "geometry": {"coordinates":[-0.00561,51.340259],"type":"Point"}
}
