{
  "type": "Feature",
  "properties": {
    "iso:country":"GB",
    "wof:name":"TA20 2RY",
    "wof:placetype":"postalcode"
},
  "geometry": {"coordinates":[-2.95512766246115,50.84496484282437],"type":"Point"}
}