{
  "type": "Feature",
  "properties": {
    "iso:country":"GB",
    "wof:name":"W5 1RG",
    "wof:placetype":"postalcode"
},
  "geometry": {"coordinates":[-0.30680662668147,51.52660284611854],"type":"Point"}
}