{
  "type": "Feature",
  "properties": {
    "iso:country": "GB",
    "wof:name": "W5 1RG",
    "wof:placetype": "postalcode"
  },
  "geometry": {"coordinates":[-0.306807,51.526603],"type":"Point"}
}
