{
  "type": "Feature",
  "properties": {
    "iso:country":"GB",
    "wof:name":"M22 0BU",
    "wof:placetype":"postalcode"
},
  "geometry": {"coordinates":[-2.26347736898478,53.37643190804653],"type":"Point"}
}