{
  "type": "Feature",
  "properties": {
    "iso:country":"GB",
    "wof:name":"NG2 2HS",
    "wof:placetype":"postalcode"
},
  "geometry": {"coordinates":[-1.14590727681428,52.94244873839963],"type":"Point"}
}