{
  "type": "Feature",
  "properties": {
    "iso:country":"GB",
    "wof:name":"M34 3TJ",
    "wof:placetype":"postalcode"
},
  "geometry": {"coordinates":[-2.10707860077556,53.46154469821749],"type":"Point"}
}