{
  "type": "Feature",
  "properties": {
    "iso:country":"GB",
    "wof:name":"LL58 8HG",
    "wof:placetype":"postalcode"
},
  "geometry": {"coordinates":[-4.10096888042636,53.26343100099086],"type":"Point"}
}