{
  "type": "Feature",
  "properties": {
    "iso:country":"GB",
    "wof:name":"LS19 6HF",
    "wof:placetype":"postalcode"
},
  "geometry": {"coordinates":[-1.68265231130786,53.84975953724429],"type":"Point"}
}