{
  "type": "Feature",
  "properties": {
    "iso:country":"GB",
    "wof:name":"ML1 2JX",
    "wof:placetype":"postalcode"
},
  "geometry": {"coordinates":[-3.95668911412868,55.77308154364879],"type":"Point"}
}