{
  "type": "Feature",
  "properties": {
    "date:inception_lower":"2006-05-01",
    "date:inception_upper":"2006-05-31",
    "iso:country":"GB",
    "wof:name":"ML1 2JX",
    "wof:placetype":"postalcode"
},
  "geometry": {"coordinates":[-3.956689,55.773082],"type":"Point"}
}