{
  "type": "Feature",
  "properties": {
    "iso:country": "GB",
    "wof:name": "TN1 1TF",
    "wof:placetype": "postalcode"
  },
  "geometry": {"coordinates":[0.26555,51.127237],"type":"Point"}
}
