{
  "type": "Feature",
  "properties": {
    "iso:country":"GB",
    "wof:name":"TN1 1TF",
    "wof:placetype":"postalcode"
},
  "geometry": {"coordinates":[0.26558262171016,51.1273006127661],"type":"Point"}
}