{
  "type": "Feature",
  "properties": {
    "iso:country":"GB",
    "wof:name":"AL5 2BZ",
    "wof:placetype":"postalcode"
},
  "geometry": {"coordinates":[-0.3582492800625,51.8160147462801],"type":"Point"}
}