{
  "type": "Feature",
  "properties": {
    "iso:country":"GB",
    "wof:name":"TW9 2PL",
    "wof:placetype":"postalcode"
},
  "geometry": {"coordinates":[-0.29740663749533,51.46592124470443],"type":"Point"}
}