{
  "type": "Feature",
  "properties": {
    "iso:country":"GB",
    "wof:name":"RM11 3TH",
    "wof:placetype":"postalcode"
},
  "geometry": {"coordinates":[0.23566169671908,51.56054861652998],"type":"Point"}
}