{
  "type": "Feature",
  "properties": {
    "iso:country":"GB",
    "wof:name":"KT12 4DS",
    "wof:placetype":"postalcode"
},
  "geometry": {"coordinates":[-0.43041967162516,51.34996842411069],"type":"Point"}
}