{
  "type": "Feature",
  "properties": {
    "iso:country":"GB",
    "wof:name":"KT4 8XJ",
    "wof:placetype":"postalcode"
},
  "geometry": {"coordinates":[-0.23260999595466,51.37036991868587],"type":"Point"}
}