{
  "type": "Feature",
  "properties": {
    "iso:country": "GB",
    "wof:name": "TN2 5QL",
    "wof:placetype": "postalcode"
  },
  "geometry": {"coordinates":[0.256965,51.124111],"type":"Point"}
}
