{
  "type": "Feature",
  "properties": {
    "iso:country":"GB",
    "wof:name":"BR1 4AY",
    "wof:placetype":"postalcode"
},
  "geometry": {"coordinates":[0.00455745542394,51.41036495020086],"type":"Point"}
}