{
  "type": "Feature",
  "properties": {
    "iso:country":"GB",
    "wof:name":"ME8 6XD",
    "wof:placetype":"postalcode"
},
  "geometry": {"coordinates":[0.58482942330742,51.37268425216289],"type":"Point"}
}