{
  "type": "Feature",
  "properties": {
    "iso:country":"GB",
    "wof:name":"TN16 1DQ",
    "wof:placetype":"postalcode"
},
  "geometry": {"coordinates":[0.07367720279808,51.27124553158376],"type":"Point"}
}