{
  "type": "Feature",
  "properties": {
    "date:inception_lower": "1994-05-01",
    "date:inception_upper": "1994-05-01",
    "iso:country": "GB",
    "wof:name": "TN16 1DQ",
    "wof:placetype": "postalcode"
  },
  "geometry": {"coordinates":[0.073744,51.27118],"type":"Point"}
}
