{
  "type": "Feature",
  "properties": {
    "iso:country":"GB",
    "wof:name":"WA9 4QD",
    "wof:placetype":"postalcode"
},
  "geometry": {"coordinates":[-2.73666034963226,53.41923083757718],"type":"Point"}
}