{
  "type": "Feature",
  "properties": {
    "iso:country": "GB",
    "wof:name": "WA9 4QD",
    "wof:placetype": "postalcode"
  },
  "geometry": {"coordinates":[-2.73666,53.419231],"type":"Point"}
}
