{
  "type": "Feature",
  "properties": {
    "iso:country":"GB",
    "wof:name":"WF1 5PJ",
    "wof:placetype":"postalcode"
},
  "geometry": {"coordinates":[-1.47951374567808,53.67772831362933],"type":"Point"}
}