{
  "type": "Feature",
  "properties": {
    "date:inception_lower": "1980-01-01",
    "date:inception_upper": "1980-01-01",
    "iso:country": "GB",
    "wof:name": "WF1 5PJ",
    "wof:placetype": "postalcode"
  },
  "geometry": {"coordinates":[-1.479516,53.677745],"type":"Point"}
}
