{
  "type": "Feature",
  "properties": {
    "iso:country":"GB",
    "wof:name":"BL0 0JH",
    "wof:placetype":"postalcode"
},
  "geometry": {"coordinates":[-2.30710719771206,53.67347524993927],"type":"Point"}
}