{
  "type": "Feature",
  "properties": {
    "date:inception_lower": "1980-01-01",
    "date:inception_upper": "1980-01-01",
    "iso:country": "GB",
    "wof:name": "BL0 0JH",
    "wof:placetype": "postalcode"
  },
  "geometry": {"coordinates":[-2.307107,53.673475],"type":"Point"}
}
