{
  "type": "Feature",
  "properties": {
    "iso:country":"GB",
    "wof:name":"OX44 7PF",
    "wof:placetype":"postalcode"
},
  "geometry": {"coordinates":[-1.08433160175926,51.71535633054131],"type":"Point"}
}