{
  "type": "Feature",
  "properties": {
    "date:inception_lower": "1992-08-01",
    "date:inception_upper": "1992-08-01",
    "iso:country": "GB",
    "wof:name": "OX44 7PF",
    "wof:placetype": "postalcode"
  },
  "geometry": {"coordinates":[-1.084332,51.715356],"type":"Point"}
}
