{
  "type": "Feature",
  "properties": {
    "iso:country": "GB",
    "wof:name": "BL9 5JB",
    "wof:placetype": "postalcode"
  },
  "geometry": {"coordinates":[-2.29686,53.617603],"type":"Point"}
}
