{
  "type": "Feature",
  "properties": {
    "date:inception_lower": "1980-01-01",
    "date:inception_upper": "1980-01-01",
    "iso:country": "GB",
    "wof:name": "NE63 0SN",
    "wof:placetype": "postalcode"
  },
  "geometry": {"coordinates":[-1.564045,55.183259],"type":"Point"}
}
