{
  "type": "Feature",
  "properties": {
    "iso:country":"GB",
    "wof:name":"NE63 0SN",
    "wof:placetype":"postalcode"
},
  "geometry": {"coordinates":[-1.56404537139182,55.18325931190303],"type":"Point"}
}