{
  "type": "Feature",
  "properties": {
    "iso:country":"GB",
    "wof:name":"S72 0BL",
    "wof:placetype":"postalcode"
},
  "geometry": {"coordinates":[-1.35204866932776,53.5540736190277],"type":"Point"}
}