{
  "type": "Feature",
  "properties": {
    "iso:country": "GB",
    "wof:name": "S72 0BL",
    "wof:placetype": "postalcode"
  },
  "geometry": {"coordinates":[-1.352021,53.554127],"type":"Point"}
}
