{
  "type": "Feature",
  "properties": {
    "date:inception_lower":"2013-12-01",
    "date:inception_upper":"2013-12-31",
    "iso:country":"GB",
    "wof:name":"PE7 3AG",
    "wof:placetype":"postalcode"
},
  "geometry": {"coordinates":[-0.304776,52.534469],"type":"Point"}
}