{
  "type": "Feature",
  "properties": {
    "iso:country":"GB",
    "wof:name":"PE7 3AG",
    "wof:placetype":"postalcode"
},
  "geometry": {"coordinates":[-0.30479269676609,52.53445119909095],"type":"Point"}
}