{
  "type": "Feature",
  "properties": {
    "iso:country": "GB",
    "wof:name": "PE7 3AG",
    "wof:placetype": "postalcode"
  },
  "geometry": {"coordinates":[-0.312862,52.533919],"type":"Point"}
}
