{
  "type": "Feature",
  "properties": {
    "iso:country":"GB",
    "wof:name":"WA7 4RD",
    "wof:placetype":"postalcode"
},
  "geometry": {"coordinates":[-2.7356971015872,53.3198114827102],"type":"Point"}
}