{
  "type": "Feature",
  "properties": {
    "iso:country":"GB",
    "wof:name":"RH20 3HZ",
    "wof:placetype":"postalcode"
},
  "geometry": {"coordinates":[-0.42369202280089,50.9178034597762],"type":"Point"}
}