{
  "type": "Feature",
  "properties": {
    "iso:country":"GB",
    "wof:name":"EX39 1ED",
    "wof:placetype":"postalcode"
},
  "geometry": {"coordinates":[-4.21195173500334,51.04219569167753],"type":"Point"}
}