{
  "type": "Feature",
  "properties": {
    "iso:country": "GB",
    "wof:name": "EX39 1ED",
    "wof:placetype": "postalcode"
  },
  "geometry": {"coordinates":[-4.211952,51.042196],"type":"Point"}
}
