{
  "type": "Feature",
  "properties": {
    "date:inception_lower": "1980-01-01",
    "date:inception_upper": "1980-01-01",
    "iso:country": "GB",
    "wof:name": "TA5 2NA",
    "wof:placetype": "postalcode"
  },
  "geometry": {"coordinates":[-3.079027,51.148567],"type":"Point"}
}
