{
  "type": "Feature",
  "properties": {
    "date:inception_lower":"1980-01-01",
    "date:inception_upper":"1980-01-31",
    "iso:country":"GB",
    "wof:name":"KA2 9DJ",
    "wof:placetype":"postalcode"
},
  "geometry": {"coordinates":[-4.602842,55.579243],"type":"Point"}
}