{
  "type": "Feature",
  "properties": {
    "iso:country":"GB",
    "wof:name":"SG6 1EG",
    "wof:placetype":"postalcode"
},
  "geometry": {"coordinates":[-0.20899852384119,51.98790130741081],"type":"Point"}
}