{
  "type": "Feature",
  "properties": {
    "iso:country":"GB",
    "wof:name":"CH7 4UF",
    "wof:placetype":"postalcode"
},
  "geometry": {"coordinates":[-3.09435962728737,53.13571896570439],"type":"Point"}
}