{
  "type": "Feature",
  "properties": {
    "date:inception_lower": "1980-01-01",
    "date:inception_upper": "1980-01-01",
    "iso:country": "GB",
    "wof:name": "SE5 0PQ",
    "wof:placetype": "postalcode"
  },
  "geometry": {"coordinates":[-0.099022,51.482136],"type":"Point"}
}
