{
  "type": "Feature",
  "properties": {
    "iso:country":"GB",
    "wof:name":"SE5 0PQ",
    "wof:placetype":"postalcode"
},
  "geometry": {"coordinates":[-0.09897505417517,51.48214292494155],"type":"Point"}
}