{
  "type": "Feature",
  "properties": {
    "iso:country":"GB",
    "wof:name":"SW9 6NZ",
    "wof:placetype":"postalcode"
},
  "geometry": {"coordinates":[-0.10914092648057,51.47906097426122],"type":"Point"}
}