{
  "type": "Feature",
  "properties": {
    "iso:country":"GB",
    "wof:name":"SL4 4EF",
    "wof:placetype":"postalcode"
},
  "geometry": {"coordinates":[-0.63467108641763,51.47377714090221],"type":"Point"}
}