{
  "type": "Feature",
  "properties": {
    "date:inception_lower":"1990-02-01",
    "date:inception_upper":"1990-02-28",
    "iso:country":"GB",
    "wof:name":"SL4 4EF",
    "wof:placetype":"postalcode"
},
  "geometry": {"coordinates":[-0.634671,51.473777],"type":"Point"}
}