{
  "type": "Feature",
  "properties": {
    "iso:country":"GB",
    "wof:name":"SK12 1DE",
    "wof:placetype":"postalcode"
},
  "geometry": {"coordinates":[-2.1086719995362,53.3543368259699],"type":"Point"}
}