{
  "type": "Feature",
  "properties": {
    "date:inception_lower": "1980-01-01",
    "date:inception_upper": "1980-01-01",
    "iso:country": "GB",
    "wof:name": "SK12 1DE",
    "wof:placetype": "postalcode"
  },
  "geometry": {"coordinates":[-2.108716,53.353949],"type":"Point"}
}
