{
  "type": "Feature",
  "properties": {
    "iso:country":"GB",
    "wof:name":"B93 9DH",
    "wof:placetype":"postalcode"
},
  "geometry": {"coordinates":[-1.7388117066734,52.39991487755004],"type":"Point"}
}