{
  "type": "Feature",
  "properties": {
    "iso:country": "GB",
    "wof:name": "HP20 2HG",
    "wof:placetype": "postalcode"
  },
  "geometry": {"coordinates":[-0.802758,51.825651],"type":"Point"}
}
