{
  "type": "Feature",
  "properties": {
    "iso:country":"GB",
    "wof:name":"HP20 2HG",
    "wof:placetype":"postalcode"
},
  "geometry": {"coordinates":[-0.80275818767773,51.82565063279354],"type":"Point"}
}