{
  "type": "Feature",
  "properties": {
    "date:inception_lower":"1980-01-01",
    "date:inception_upper":"1980-01-31",
    "iso:country":"GB",
    "wof:name":"DL4 2JE",
    "wof:placetype":"postalcode"
},
  "geometry": {"coordinates":[-1.645893,54.625049],"type":"Point"}
}