{
  "type": "Feature",
  "properties": {
    "iso:country":"GB",
    "wof:name":"DL4 2JE",
    "wof:placetype":"postalcode"
},
  "geometry": {"coordinates":[-1.64589277196633,54.62504924210859],"type":"Point"}
}