{
  "type": "Feature",
  "properties": {
    "iso:country": "GB",
    "wof:name": "SE18 6FW",
    "wof:placetype": "postalcode"
  },
  "geometry": {"coordinates":[0.072189,51.491519],"type":"Point"}
}
