{
  "type": "Feature",
  "properties": {
    "iso:country":"GB",
    "wof:name":"LL15 1YF",
    "wof:placetype":"postalcode"
},
  "geometry": {"coordinates":[-3.25130618182474,53.11328089386331],"type":"Point"}
}