{
  "type": "Feature",
  "properties": {
    "iso:country":"GB",
    "wof:name":"N7 8QY",
    "wof:placetype":"postalcode"
},
  "geometry": {"coordinates":[-0.11545372686947,51.54808139331826],"type":"Point"}
}