{
  "type": "Feature",
  "properties": {
    "date:inception_lower": "1980-01-01",
    "date:inception_upper": "1980-01-01",
    "iso:country": "GB",
    "wof:name": "GU7 2AB",
    "wof:placetype": "postalcode"
  },
  "geometry": {"coordinates":[-0.616587,51.190214],"type":"Point"}
}
