{
  "type": "Feature",
  "properties": {
    "iso:country": "GB",
    "wof:name": "GU7 2AB",
    "wof:placetype": "postalcode"
  },
  "geometry": {"coordinates":[-0.616587,51.190214],"type":"Point"}
}
