{
  "type": "Feature",
  "properties": {
    "date:inception_lower":"1983-07-01",
    "date:inception_upper":"1983-07-31",
    "iso:country":"GB",
    "wof:name":"TS27 3BX",
    "wof:placetype":"postalcode"
},
  "geometry": {"coordinates":[-1.267992,54.70874],"type":"Point"}
}