{
  "type": "Feature",
  "properties": {
    "iso:country":"GB",
    "wof:name":"AL8 7BU",
    "wof:placetype":"postalcode"
},
  "geometry": {"coordinates":[-0.22010835959988,51.80517483630062],"type":"Point"}
}