{
  "type": "Feature",
  "properties": {
    "iso:country": "GB",
    "wof:name": "AL8 7BU",
    "wof:placetype": "postalcode"
  },
  "geometry": {"coordinates":[-0.220397,51.805357],"type":"Point"}
}
