{
  "type": "Feature",
  "properties": {
    "iso:country": "GB",
    "wof:name": "NE20 0AG",
    "wof:placetype": "postalcode"
  },
  "geometry": {"coordinates":[-1.775343,55.07963],"type":"Point"}
}
