{
  "type": "Feature",
  "properties": {
    "iso:country": "GB",
    "wof:name": "GU1 2XL",
    "wof:placetype": "postalcode"
  },
  "geometry": {"coordinates":[-0.52816,51.242591],"type":"Point"}
}
