{
  "type": "Feature",
  "properties": {
    "date:inception_lower": "1980-01-01",
    "date:inception_upper": "1980-01-01",
    "iso:country": "GB",
    "wof:name": "GU1 2XL",
    "wof:placetype": "postalcode"
  },
  "geometry": {"coordinates":[-0.52816,51.242591],"type":"Point"}
}
