{
  "type": "Feature",
  "properties": {
    "iso:country":"GB",
    "wof:name":"UB7 7LF",
    "wof:placetype":"postalcode"
},
  "geometry": {"coordinates":[-0.47718161752315,51.50516287761954],"type":"Point"}
}