{
  "type": "Feature",
  "properties": {
    "iso:country": "GB",
    "wof:name": "DG8 8BP",
    "wof:placetype": "postalcode"
  },
  "geometry": {"coordinates":[-4.370566,54.787769],"type":"Point"}
}
