{
  "type": "Feature",
  "properties": {
    "iso:country":"GB",
    "wof:name":"DG8 8BP",
    "wof:placetype":"postalcode"
},
  "geometry": {"coordinates":[-4.37056622089748,54.78776932925406],"type":"Point"}
}