{
  "type": "Feature",
  "properties": {
    "iso:country":"GB",
    "wof:name":"CF71 7UD",
    "wof:placetype":"postalcode"
},
  "geometry": {"coordinates":[-3.37670075963917,51.44868488636379],"type":"Point"}
}