{
  "type": "Feature",
  "properties": {
    "iso:country": "GB",
    "wof:name": "CF71 7UD",
    "wof:placetype": "postalcode"
  },
  "geometry": {"coordinates":[-3.376701,51.448685],"type":"Point"}
}
