{
  "type": "Feature",
  "properties": {
    "iso:country": "GB",
    "wof:name": "CB21 4YR",
    "wof:placetype": "postalcode"
  },
  "geometry": {"coordinates":[0.287255,52.099859],"type":"Point"}
}
