{
  "type": "Feature",
  "properties": {
    "iso:country": "GB",
    "wof:name": "YO11 2XZ",
    "wof:placetype": "postalcode"
  },
  "geometry": {"coordinates":[-0.394721,54.2652],"type":"Point"}
}
