{
  "type": "Feature",
  "properties": {
    "iso:country":"GB",
    "wof:name":"YO11 2XZ",
    "wof:placetype":"postalcode"
},
  "geometry": {"coordinates":[-0.39470463699212,54.26518211712661],"type":"Point"}
}