{
  "type": "Feature",
  "properties": {
    "iso:country":"GB",
    "wof:name":"N16 7ES",
    "wof:placetype":"postalcode"
},
  "geometry": {"coordinates":[-0.0687437212808,51.56188967636276],"type":"Point"}
}