{
  "type": "Feature",
  "properties": {
    "date:inception_lower": "1993-08-01",
    "date:inception_upper": "1993-08-01",
    "iso:country": "GB",
    "wof:name": "NP7 0EQ",
    "wof:placetype": "postalcode"
  },
  "geometry": {"coordinates":[-3.082466,51.831478],"type":"Point"}
}
