{
  "type": "Feature",
  "properties": {
    "iso:country":"GB",
    "wof:name":"BD7 4EQ",
    "wof:placetype":"postalcode"
},
  "geometry": {"coordinates":[-1.78562915603283,53.77959383602716],"type":"Point"}
}