{
  "type": "Feature",
  "properties": {
    "date:inception_lower":"1997-12-01",
    "date:inception_upper":"1997-12-31",
    "iso:country":"GB",
    "wof:name":"NG32 3DJ",
    "wof:placetype":"postalcode"
},
  "geometry": {"coordinates":[-0.608215,53.025812],"type":"Point"}
}