{
  "type": "Feature",
  "properties": {
    "iso:country":"GB",
    "wof:name":"NG32 3DJ",
    "wof:placetype":"postalcode"
},
  "geometry": {"coordinates":[-0.60821463371257,53.02581165566274],"type":"Point"}
}