{
  "type": "Feature",
  "properties": {
    "date:inception_lower": "1980-01-01",
    "date:inception_upper": "1980-01-01",
    "iso:country": "GB",
    "wof:name": "IP6 8QJ",
    "wof:placetype": "postalcode"
  },
  "geometry": {"coordinates":[1.042926,52.177953],"type":"Point"}
}
