{
  "type": "Feature",
  "properties": {
    "iso:country":"GB",
    "wof:name":"IP6 8QJ",
    "wof:placetype":"postalcode"
},
  "geometry": {"coordinates":[1.04286719552235,52.17795557944307],"type":"Point"}
}