{
  "type": "Feature",
  "properties": {
    "iso:country": "GB",
    "wof:name": "IP6 8QJ",
    "wof:placetype": "postalcode"
  },
  "geometry": {"coordinates":[1.042867,52.177956],"type":"Point"}
}
