{
  "type": "Feature",
  "properties": {
    "iso:country": "GB",
    "wof:name": "N2 0HG",
    "wof:placetype": "postalcode"
  },
  "geometry": {"coordinates":[-0.177345,51.587349],"type":"Point"}
}
