{
  "type": "Feature",
  "properties": {
    "iso:country":"GB",
    "wof:name":"AB16 5QE",
    "wof:placetype":"postalcode"
},
  "geometry": {"coordinates":[-2.1615449723293,57.15877369964919],"type":"Point"}
}