{
  "type": "Feature",
  "properties": {
    "date:inception_lower":"2001-12-01",
    "date:inception_upper":"2001-12-31",
    "iso:country":"GB",
    "wof:name":"HP6 5FA",
    "wof:placetype":"postalcode"
},
  "geometry": {"coordinates":[-0.607065,51.675969],"type":"Point"}
}