{
  "type": "Feature",
  "properties": {
    "iso:country":"GB",
    "wof:name":"SW13 8DU",
    "wof:placetype":"postalcode"
},
  "geometry": {"coordinates":[-0.23105418365929,51.48557664834499],"type":"Point"}
}