{
  "type": "Feature",
  "properties": {
    "date:inception_lower": "1997-06-01",
    "date:inception_upper": "1997-06-01",
    "iso:country": "GB",
    "wof:name": "SW13 8DU",
    "wof:placetype": "postalcode"
  },
  "geometry": {"coordinates":[-0.231054,51.485577],"type":"Point"}
}
