{
  "type": "Feature",
  "properties": {
    "iso:country": "GB",
    "wof:name": "PR8 6WD",
    "wof:placetype": "postalcode"
  },
  "geometry": {"coordinates":[-2.985822,53.626988],"type":"Point"}
}
