{
  "type": "Feature",
  "properties": {
    "date:inception_lower": "1980-01-01",
    "date:inception_upper": "1980-01-01",
    "iso:country": "GB",
    "wof:name": "G81 1DG",
    "wof:placetype": "postalcode"
  },
  "geometry": {"coordinates":[-4.38793,55.896166],"type":"Point"}
}
