{
  "type": "Feature",
  "properties": {
    "iso:country":"GB",
    "wof:name":"G81 1DG",
    "wof:placetype":"postalcode"
},
  "geometry": {"coordinates":[-4.38793012443394,55.89616620501079],"type":"Point"}
}