{
  "type": "Feature",
  "properties": {
    "iso:country":"GB",
    "wof:name":"BD22 8NS",
    "wof:placetype":"postalcode"
},
  "geometry": {"coordinates":[-1.94774374806513,53.82993544214411],"type":"Point"}
}