{
  "type": "Feature",
  "properties": {
    "iso:country": "GB",
    "wof:name": "BD22 8NS",
    "wof:placetype": "postalcode"
  },
  "geometry": {"coordinates":[-1.947744,53.829935],"type":"Point"}
}
