{
  "type": "Feature",
  "properties": {
    "iso:country":"GB",
    "wof:name":"BB2 6LR",
    "wof:placetype":"postalcode"
},
  "geometry": {"coordinates":[-2.50201592763889,53.74882056926565],"type":"Point"}
}