{
  "type": "Feature",
  "properties": {
    "iso:country":"GB",
    "wof:name":"KT16 8BQ",
    "wof:placetype":"postalcode"
},
  "geometry": {"coordinates":[-0.50345772716067,51.38559867907769],"type":"Point"}
}