{
  "type": "Feature",
  "properties": {
    "date:inception_lower": "2002-06-01",
    "date:inception_upper": "2002-06-01",
    "iso:country": "GB",
    "wof:name": "KT16 8BQ",
    "wof:placetype": "postalcode"
  },
  "geometry": {"coordinates":[-0.503458,51.385599],"type":"Point"}
}
