{
  "type": "Feature",
  "properties": {
    "iso:country": "GB",
    "wof:name": "CM23 3NG",
    "wof:placetype": "postalcode"
  },
  "geometry": {"coordinates":[0.159364,51.857367],"type":"Point"}
}
