{
  "type": "Feature",
  "properties": {
    "iso:country":"GB",
    "wof:name":"TN12 8DT",
    "wof:placetype":"postalcode"
},
  "geometry": {"coordinates":[0.41103098596831,51.12966160694845],"type":"Point"}
}