{
  "type": "Feature",
  "properties": {
    "iso:country": "GB",
    "wof:name": "DN5 7DY",
    "wof:placetype": "postalcode"
  },
  "geometry": {"coordinates":[-1.218064,53.560032],"type":"Point"}
}
