{
  "type": "Feature",
  "properties": {
    "date:inception_lower": "2011-11-01",
    "date:inception_upper": "2011-11-01",
    "iso:country": "GB",
    "wof:name": "DN5 7DY",
    "wof:placetype": "postalcode"
  },
  "geometry": {"coordinates":[-1.218079,53.560178],"type":"Point"}
}
