{
  "type": "Feature",
  "properties": {
    "iso:country":"GB",
    "wof:name":"DN5 7DY",
    "wof:placetype":"postalcode"
},
  "geometry": {"coordinates":[-1.21806416322227,53.56003242388383],"type":"Point"}
}