{
  "type": "Feature",
  "properties": {
    "iso:country":"GB",
    "wof:name":"W1T 2PR",
    "wof:placetype":"postalcode"
},
  "geometry": {"coordinates":[-0.13504047758541,51.51950153060138],"type":"Point"}
}