{
  "type": "Feature",
  "properties": {
    "iso:country": "GB",
    "wof:name": "BA22 7RE",
    "wof:placetype": "postalcode"
  },
  "geometry": {"coordinates":[-2.602422,51.02679],"type":"Point"}
}
