{
  "type": "Feature",
  "properties": {
    "iso:country":"GB",
    "wof:name":"BA22 7RE",
    "wof:placetype":"postalcode"
},
  "geometry": {"coordinates":[-2.60242204375146,51.02679041325037],"type":"Point"}
}