{
  "type": "Feature",
  "properties": {
    "iso:country": "GB",
    "wof:name": "WV6 7SZ",
    "wof:placetype": "postalcode"
  },
  "geometry": {"coordinates":[-2.1986,52.591054],"type":"Point"}
}
