{
  "type": "Feature",
  "properties": {
    "iso:country":"GB",
    "wof:name":"WV6 7SZ",
    "wof:placetype":"postalcode"
},
  "geometry": {"coordinates":[-2.19859959929165,52.59105397033273],"type":"Point"}
}