{
  "type": "Feature",
  "properties": {
    "iso:country":"GB",
    "wof:name":"CM7 2ST",
    "wof:placetype":"postalcode"
},
  "geometry": {"coordinates":[0.54198391044543,51.88209372852402],"type":"Point"}
}