{
  "type": "Feature",
  "properties": {
    "iso:country":"GB",
    "wof:name":"W4 3HH",
    "wof:placetype":"postalcode"
},
  "geometry": {"coordinates":[-0.26284377142147,51.48666335871442],"type":"Point"}
}