{
  "type": "Feature",
  "properties": {
    "iso:country":"GB",
    "wof:name":"CB4 2LY",
    "wof:placetype":"postalcode"
},
  "geometry": {"coordinates":[0.13032631614691,52.23098948069772],"type":"Point"}
}