{
  "type": "Feature",
  "properties": {
    "iso:country":"GB",
    "wof:name":"GU7 2HD",
    "wof:placetype":"postalcode"
},
  "geometry": {"coordinates":[-0.61154380992851,51.19585050501604],"type":"Point"}
}