{
  "type": "Feature",
  "properties": {
    "iso:country":"GB",
    "wof:name":"RG30 2LU",
    "wof:placetype":"postalcode"
},
  "geometry": {"coordinates":[-0.996723233492,51.4521209941767],"type":"Point"}
}