{
  "type": "Feature",
  "properties": {
    "iso:country":"GB",
    "wof:name":"SY13 3NU",
    "wof:placetype":"postalcode"
},
  "geometry": {"coordinates":[-2.6924520209616,52.9371684787715],"type":"Point"}
}