{
  "type": "Feature",
  "properties": {
    "iso:country":"GB",
    "wof:name":"SN2 7UD",
    "wof:placetype":"postalcode"
},
  "geometry": {"coordinates":[-1.76697233550718,51.59660836963762],"type":"Point"}
}