{
  "type": "Feature",
  "properties": {
    "iso:country":"GB",
    "wof:name":"PR1 9BT",
    "wof:placetype":"postalcode"
},
  "geometry": {"coordinates":[-2.71072016351752,53.73342805864537],"type":"Point"}
}