{
  "type": "Feature",
  "properties": {
    "date:inception_lower": "1980-01-01",
    "date:inception_upper": "1980-01-01",
    "iso:country": "GB",
    "wof:name": "RG2 9PW",
    "wof:placetype": "postalcode"
  },
  "geometry": {"coordinates":[-0.903957,51.391081],"type":"Point"}
}
