{
  "type": "Feature",
  "properties": {
    "iso:country": "GB",
    "wof:name": "WF2 0UG",
    "wof:placetype": "postalcode"
  },
  "geometry": {"coordinates":[-1.530069,53.708335],"type":"Point"}
}
