{
  "type": "Feature",
  "properties": {
    "iso:country":"GB",
    "wof:name":"WF2 0UG",
    "wof:placetype":"postalcode"
},
  "geometry": {"coordinates":[-1.53006940989719,53.70833533343281],"type":"Point"}
}