{
  "type": "Feature",
  "properties": {
    "iso:country":"GB",
    "wof:name":"SP10 5BS",
    "wof:placetype":"postalcode"
},
  "geometry": {"coordinates":[-1.47279219882196,51.2202803910799],"type":"Point"}
}