{
  "type": "Feature",
  "properties": {
    "iso:country": "GB",
    "wof:name": "KA1 2QP",
    "wof:placetype": "postalcode"
  },
  "geometry": {"coordinates":[-4.506845,55.612579],"type":"Point"}
}
