{
  "type": "Feature",
  "properties": {
    "iso:country": "GB",
    "wof:name": "CR7 7BT",
    "wof:placetype": "postalcode"
  },
  "geometry": {"coordinates":[-0.099386,51.393212],"type":"Point"}
}
