{
  "type": "Feature",
  "properties": {
    "iso:country":"GB",
    "wof:name":"FY8 1NF",
    "wof:placetype":"postalcode"
},
  "geometry": {"coordinates":[-3.02729423699195,53.74742782042131],"type":"Point"}
}