{
  "type": "Feature",
  "properties": {
    "iso:country":"GB",
    "wof:name":"LA13 9EF",
    "wof:placetype":"postalcode"
},
  "geometry": {"coordinates":[-3.20932490406467,54.12018419336319],"type":"Point"}
}