{
  "type": "Feature",
  "properties": {
    "iso:country":"GB",
    "wof:name":"SA33 4DN",
    "wof:placetype":"postalcode"
},
  "geometry": {"coordinates":[-4.49081555343976,51.83298776813135],"type":"Point"}
}