{
  "type": "Feature",
  "properties": {
    "iso:country": "GB",
    "wof:name": "SW3 2BF",
    "wof:placetype": "postalcode"
  },
  "geometry": {"coordinates":[-0.158772,51.492899],"type":"Point"}
}
