{
  "type": "Feature",
  "properties": {
    "iso:country":"GB",
    "wof:name":"SW3 2BF",
    "wof:placetype":"postalcode"
},
  "geometry": {"coordinates":[-0.15877198654121,51.49289896884169],"type":"Point"}
}