{
  "type": "Feature",
  "properties": {
    "iso:country": "GB",
    "wof:name": "CT15 5HN",
    "wof:placetype": "postalcode"
  },
  "geometry": {"coordinates":[1.325856,51.177053],"type":"Point"}
}
