{
  "type": "Feature",
  "properties": {
    "iso:country":"GB",
    "wof:name":"CT15 5HN",
    "wof:placetype":"postalcode"
},
  "geometry": {"coordinates":[1.32582503099064,51.17704553693142],"type":"Point"}
}