{
  "type": "Feature",
  "properties": {
    "iso:country":"GB",
    "wof:name":"BD1 2PX",
    "wof:placetype":"postalcode"
},
  "geometry": {"coordinates":[-1.76099713993231,53.7961121961772],"type":"Point"}
}