{
  "type": "Feature",
  "properties": {
    "iso:country":"GB",
    "wof:name":"HR8 1JE",
    "wof:placetype":"postalcode"
},
  "geometry": {"coordinates":[-2.41532540629276,52.0460143662772],"type":"Point"}
}