{
  "type": "Feature",
  "properties": {
    "iso:country": "GB",
    "wof:name": "HR8 1JE",
    "wof:placetype": "postalcode"
  },
  "geometry": {"coordinates":[-2.415325,52.046014],"type":"Point"}
}
