{
  "type": "Feature",
  "properties": {
    "date:inception_lower": "1980-01-01",
    "date:inception_upper": "1980-01-01",
    "iso:country": "GB",
    "wof:name": "HR8 1JE",
    "wof:placetype": "postalcode"
  },
  "geometry": {"coordinates":[-2.415325,52.046014],"type":"Point"}
}
