{
  "type": "Feature",
  "properties": {
    "iso:country":"GB",
    "wof:name":"SA6 6QE",
    "wof:placetype":"postalcode"
},
  "geometry": {"coordinates":[-3.91955774459009,51.68092590831687],"type":"Point"}
}