{
  "type": "Feature",
  "properties": {
    "date:inception_lower": "1980-01-01",
    "date:inception_upper": "1980-01-01",
    "iso:country": "GB",
    "wof:name": "SA6 6QE",
    "wof:placetype": "postalcode"
  },
  "geometry": {"coordinates":[-3.919549,51.68095],"type":"Point"}
}
