{
  "type": "Feature",
  "properties": {
    "iso:country":"GB",
    "wof:name":"CO13 9PT",
    "wof:placetype":"postalcode"
},
  "geometry": {"coordinates":[1.24525472688336,51.83335091604229],"type":"Point"}
}