{
  "type": "Feature",
  "properties": {
    "iso:country":"GB",
    "wof:name":"ME3 8UF",
    "wof:placetype":"postalcode"
},
  "geometry": {"coordinates":[0.4981976006536,51.43178090433296],"type":"Point"}
}