{
  "type": "Feature",
  "properties": {
    "date:inception_lower": "1993-01-01",
    "date:inception_upper": "1993-01-01",
    "iso:country": "GB",
    "wof:name": "NN18 8LG",
    "wof:placetype": "postalcode"
  },
  "geometry": {"coordinates":[-0.716721,52.470955],"type":"Point"}
}
