{
  "type": "Feature",
  "properties": {
    "date:inception_lower": "1995-07-01",
    "date:inception_upper": "1995-07-01",
    "iso:country": "GB",
    "wof:name": "DN12 2HT",
    "wof:placetype": "postalcode"
  },
  "geometry": {"coordinates":[-1.213178,53.480739],"type":"Point"}
}
