{
  "type": "Feature",
  "properties": {
    "date:inception_lower":"1980-01-01",
    "date:inception_upper":"1980-01-31",
    "iso:country":"GB",
    "wof:name":"TF9 2NL",
    "wof:placetype":"postalcode"
},
  "geometry": {"coordinates":[-2.43311,52.832745],"type":"Point"}
}