{
  "type": "Feature",
  "properties": {
    "iso:country": "GB",
    "wof:name": "TF9 2NL",
    "wof:placetype": "postalcode"
  },
  "geometry": {"coordinates":[-2.43311,52.832745],"type":"Point"}
}
