{
  "type": "Feature",
  "properties": {
    "iso:country":"GB",
    "wof:name":"TF9 2NL",
    "wof:placetype":"postalcode"
},
  "geometry": {"coordinates":[-2.43311016750299,52.83274466965073],"type":"Point"}
}