{
  "type": "Feature",
  "properties": {
    "iso:country":"GB",
    "wof:name":"BL9 7NW",
    "wof:placetype":"postalcode"
},
  "geometry": {"coordinates":[-2.26790968010835,53.59832896703693],"type":"Point"}
}