{
  "type": "Feature",
  "properties": {
    "date:inception_lower":"1980-01-01",
    "date:inception_upper":"1980-01-31",
    "iso:country":"GB",
    "wof:name":"BL9 7NW",
    "wof:placetype":"postalcode"
},
  "geometry": {"coordinates":[-2.26791,53.598329],"type":"Point"}
}