{
  "type": "Feature",
  "properties": {
    "date:inception_lower":"2017-07-01",
    "date:inception_upper":"2017-07-31",
    "iso:country":"GB",
    "wof:name":"CV4 8JG",
    "wof:placetype":"postalcode"
},
  "geometry": {"coordinates":[-1.571016,52.395288],"type":"Point"}
}