{
  "type": "Feature",
  "properties": {
    "date:inception_lower": "2019-05-01",
    "date:inception_upper": "2019-05-01",
    "iso:country": "GB",
    "wof:name": "YO42 2ST",
    "wof:placetype": "postalcode"
  },
  "geometry": {"coordinates":[-0.774341,53.93768],"type":"Point"}
}
