{
  "type": "Feature",
  "properties": {
    "iso:country":"GB",
    "wof:name":"NG8 3HJ",
    "wof:placetype":"postalcode"
},
  "geometry": {"coordinates":[-1.19889761980748,52.9602302537704],"type":"Point"}
}