{
  "type": "Feature",
  "properties": {
    "iso:country":"GB",
    "wof:name":"NE8 4JJ",
    "wof:placetype":"postalcode"
},
  "geometry": {"coordinates":[-1.60058667853221,54.94744449625386],"type":"Point"}
}