{
  "type": "Feature",
  "properties": {
    "iso:country":"GB",
    "wof:name":"MK40 3QX",
    "wof:placetype":"postalcode"
},
  "geometry": {"coordinates":[-0.45420021355002,52.13682859951882],"type":"Point"}
}