{
  "type": "Feature",
  "properties": {
    "iso:country": "GB",
    "wof:name": "DT6 3JU",
    "wof:placetype": "postalcode"
  },
  "geometry": {"coordinates":[-2.75791,50.733714],"type":"Point"}
}
