{
  "type": "Feature",
  "properties": {
    "date:inception_lower": "1980-01-01",
    "date:inception_upper": "1980-01-01",
    "iso:country": "GB",
    "wof:name": "DT6 3JU",
    "wof:placetype": "postalcode"
  },
  "geometry": {"coordinates":[-2.75791,50.733714],"type":"Point"}
}
