{
  "type": "Feature",
  "properties": {
    "iso:country":"GB",
    "wof:name":"WD7 8DF",
    "wof:placetype":"postalcode"
},
  "geometry": {"coordinates":[-0.32849884446996,51.68046430450414],"type":"Point"}
}