{
  "type": "Feature",
  "properties": {
    "iso:country":"GB",
    "wof:name":"RH18 5AN",
    "wof:placetype":"postalcode"
},
  "geometry": {"coordinates":[0.03357693734781,51.09436112000233],"type":"Point"}
}