{
  "type": "Feature",
  "properties": {
    "date:inception_lower": "2023-03-01",
    "date:inception_upper": "2023-03-01",
    "iso:country": "GB",
    "wof:name": "IV49 9DH",
    "wof:placetype": "postalcode"
  },
  "geometry": {"coordinates":[-5.909511,57.238026],"type":"Point"}
}
