{
  "type": "Feature",
  "properties": {
    "iso:country":"GB",
    "wof:name":"SE27 0AT",
    "wof:placetype":"postalcode"
},
  "geometry": {"coordinates":[-0.1055622956281,51.43473251926641],"type":"Point"}
}