{
  "type": "Feature",
  "properties": {
    "iso:country":"GB",
    "wof:name":"HX3 0SJ",
    "wof:placetype":"postalcode"
},
  "geometry": {"coordinates":[-1.85945887386039,53.70142601050676],"type":"Point"}
}