{
  "type": "Feature",
  "properties": {
    "date:inception_lower": "1990-02-01",
    "date:inception_upper": "1990-02-01",
    "iso:country": "GB",
    "wof:name": "BL1 7LN",
    "wof:placetype": "postalcode"
  },
  "geometry": {"coordinates":[-2.441882,53.613686],"type":"Point"}
}
