{
  "type": "Feature",
  "properties": {
    "date:inception_lower":"1980-01-01",
    "date:inception_upper":"1980-01-31",
    "iso:country":"GB",
    "wof:name":"LS27 0LJ",
    "wof:placetype":"postalcode"
},
  "geometry": {"coordinates":[-1.622153,53.743382],"type":"Point"}
}