{
  "type": "Feature",
  "properties": {
    "iso:country":"GB",
    "wof:name":"PO33 2JP",
    "wof:placetype":"postalcode"
},
  "geometry": {"coordinates":[-1.15994186730211,50.72812079555818],"type":"Point"}
}