{
  "type": "Feature",
  "properties": {
    "date:inception_lower": "1980-01-01",
    "date:inception_upper": "1980-01-01",
    "iso:country": "GB",
    "wof:name": "RG25 3AT",
    "wof:placetype": "postalcode"
  },
  "geometry": {"coordinates":[-1.214721,51.249011],"type":"Point"}
}
