{
  "type": "Feature",
  "properties": {
    "iso:country":"GB",
    "wof:name":"RG25 3AT",
    "wof:placetype":"postalcode"
},
  "geometry": {"coordinates":[-1.21472111062463,51.24901121825552],"type":"Point"}
}