{
  "type": "Feature",
  "properties": {
    "iso:country":"GB",
    "wof:name":"BL8 1BE",
    "wof:placetype":"postalcode"
},
  "geometry": {"coordinates":[-2.30767433143497,53.59968036530265],"type":"Point"}
}