{
  "type": "Feature",
  "properties": {
    "iso:country":"GB",
    "wof:name":"ME7 3DJ",
    "wof:placetype":"postalcode"
},
  "geometry": {"coordinates":[0.55769849629099,51.36930473659561],"type":"Point"}
}