{
  "type": "Feature",
  "properties": {
    "date:inception_lower": "1980-01-01",
    "date:inception_upper": "1980-01-01",
    "iso:country": "GB",
    "wof:name": "PE14 0RY",
    "wof:placetype": "postalcode"
  },
  "geometry": {"coordinates":[0.120118,52.630913],"type":"Point"}
}
