{
  "type": "Feature",
  "properties": {
    "iso:country":"GB",
    "wof:name":"PE14 0RY",
    "wof:placetype":"postalcode"
},
  "geometry": {"coordinates":[0.12011817999528,52.63091321212315],"type":"Point"}
}