{
  "type": "Feature",
  "properties": {
    "iso:country":"GB",
    "wof:name":"WD5 0QX",
    "wof:placetype":"postalcode"
},
  "geometry": {"coordinates":[-0.41024296740416,51.72039935104589],"type":"Point"}
}