{
  "type": "Feature",
  "properties": {
    "iso:country": "GB",
    "wof:name": "DE45 1TU",
    "wof:placetype": "postalcode"
  },
  "geometry": {"coordinates":[-1.700765,53.240277],"type":"Point"}
}
