{
  "type": "Feature",
  "properties": {
    "iso:country":"GB",
    "wof:name":"AB56 1QT",
    "wof:placetype":"postalcode"
},
  "geometry": {"coordinates":[-2.9777213219865,57.67397118408189],"type":"Point"}
}