{
  "type": "Feature",
  "properties": {
    "date:inception_lower": "2018-07-01",
    "date:inception_upper": "2018-07-01",
    "iso:country": "GB",
    "wof:name": "E14 6TS",
    "wof:placetype": "postalcode"
  },
  "geometry": {"coordinates":[-0.014832,51.516433],"type":"Point"}
}
