{
  "type": "Feature",
  "properties": {
    "iso:country": "GB",
    "wof:name": "IV54 8UE",
    "wof:placetype": "postalcode"
  },
  "geometry": {"coordinates":[-5.481316,57.405005],"type":"Point"}
}
