{
  "type": "Feature",
  "properties": {
    "iso:country":"GB",
    "wof:name":"IV54 8UE",
    "wof:placetype":"postalcode"
},
  "geometry": {"coordinates":[-5.48131598030686,57.40500518073603],"type":"Point"}
}