{
  "type": "Feature",
  "properties": {
    "iso:country":"GB",
    "wof:name":"SG18 9NZ",
    "wof:placetype":"postalcode"
},
  "geometry": {"coordinates":[-0.26923155174697,52.05329904960454],"type":"Point"}
}