{
  "type": "Feature",
  "properties": {
    "iso:country":"GB",
    "wof:name":"SM5 1SQ",
    "wof:placetype":"postalcode"
},
  "geometry": {"coordinates":[-0.17957660736969,51.38498026160016],"type":"Point"}
}