{
  "type": "Feature",
  "properties": {
    "date:inception_lower": "2024-07-01",
    "date:inception_upper": "2024-07-01",
    "iso:country": "GB",
    "wof:name": "SN12 6GQ",
    "wof:placetype": "postalcode"
  },
  "geometry": {"coordinates":[-2.141021,51.358503],"type":"Point"}
}
