{
  "type": "Feature",
  "properties": {
    "iso:country":"GB",
    "wof:name":"OL2 5AY",
    "wof:placetype":"postalcode"
},
  "geometry": {"coordinates":[-2.12190013739935,53.5562861552251],"type":"Point"}
}