{
  "type": "Feature",
  "properties": {
    "iso:country":"GB",
    "wof:name":"NR5 8PE",
    "wof:placetype":"postalcode"
},
  "geometry": {"coordinates":[1.25877899033658,52.63322387050125],"type":"Point"}
}