{
  "type": "Feature",
  "properties": {
    "date:inception_lower": "1980-01-01",
    "date:inception_upper": "1980-01-01",
    "iso:country": "GB",
    "wof:name": "NR5 8PE",
    "wof:placetype": "postalcode"
  },
  "geometry": {"coordinates":[1.25882,52.6343],"type":"Point"}
}
