{
  "type": "Feature",
  "properties": {
    "iso:country": "GB",
    "wof:name": "DH9 6PH",
    "wof:placetype": "postalcode"
  },
  "geometry": {"coordinates":[-1.695042,54.859705],"type":"Point"}
}
