{
  "type": "Feature",
  "properties": {
    "iso:country":"GB",
    "wof:name":"DH9 6PH",
    "wof:placetype":"postalcode"
},
  "geometry": {"coordinates":[-1.69535700830746,54.85982327063941],"type":"Point"}
}