{
  "type": "Feature",
  "properties": {
    "iso:country":"GB",
    "wof:name":"RG40 2EJ",
    "wof:placetype":"postalcode"
},
  "geometry": {"coordinates":[-0.82576733286498,51.41104996308729],"type":"Point"}
}