{
  "type": "Feature",
  "properties": {
    "iso:country":"GB",
    "wof:name":"BR8 8AE",
    "wof:placetype":"postalcode"
},
  "geometry": {"coordinates":[0.17791043973583,51.39525641710259],"type":"Point"}
}