{
  "type": "Feature",
  "properties": {
    "iso:country": "GB",
    "wof:name": "NW3 1AY",
    "wof:placetype": "postalcode"
  },
  "geometry": {"coordinates":[-0.176194,51.563456],"type":"Point"}
}
