{
  "type": "Feature",
  "properties": {
    "date:inception_lower":"1993-02-01",
    "date:inception_upper":"1993-02-28",
    "iso:country":"GB",
    "wof:name":"ML4 3NE",
    "wof:placetype":"postalcode"
},
  "geometry": {"coordinates":[-4.047782,55.819687],"type":"Point"}
}