{
  "type": "Feature",
  "properties": {
    "iso:country":"GB",
    "wof:name":"ML4 3NE",
    "wof:placetype":"postalcode"
},
  "geometry": {"coordinates":[-4.0477816256302,55.81968706111653],"type":"Point"}
}