{
  "type": "Feature",
  "properties": {
    "iso:country":"GB",
    "wof:name":"NE61 5AE",
    "wof:placetype":"postalcode"
},
  "geometry": {"coordinates":[-1.60358323915646,55.28499750759983],"type":"Point"}
}