{
  "type": "Feature",
  "properties": {
    "iso:country": "GB",
    "wof:name": "SM7 3JU",
    "wof:placetype": "postalcode"
  },
  "geometry": {"coordinates":[-0.171035,51.318031],"type":"Point"}
}
