{
  "type": "Feature",
  "properties": {
    "iso:country":"GB",
    "wof:name":"SM7 3JU",
    "wof:placetype":"postalcode"
},
  "geometry": {"coordinates":[-0.17103464457378,51.31803150043526],"type":"Point"}
}