{
  "type": "Feature",
  "properties": {
    "iso:country": "GB",
    "wof:name": "OX5 2PX",
    "wof:placetype": "postalcode"
  },
  "geometry": {"coordinates":[-1.27208,51.818378],"type":"Point"}
}
