{
  "type": "Feature",
  "properties": {
    "date:inception_lower": "1990-07-01",
    "date:inception_upper": "1990-07-01",
    "iso:country": "GB",
    "wof:name": "S9 1QQ",
    "wof:placetype": "postalcode"
  },
  "geometry": {"coordinates":[-1.393361,53.418932],"type":"Point"}
}
