{
  "type": "Feature",
  "properties": {
    "iso:country": "GB",
    "wof:name": "S9 1QQ",
    "wof:placetype": "postalcode"
  },
  "geometry": {"coordinates":[-1.393361,53.418932],"type":"Point"}
}
