{
  "type": "Feature",
  "properties": {
    "iso:country":"GB",
    "wof:name":"S9 1QQ",
    "wof:placetype":"postalcode"
},
  "geometry": {"coordinates":[-1.39347987845399,53.41903076518678],"type":"Point"}
}