{
  "type": "Feature",
  "properties": {
    "iso:country":"GB",
    "wof:name":"CB10 2QR",
    "wof:placetype":"postalcode"
},
  "geometry": {"coordinates":[0.42051278999335,51.99765858128663],"type":"Point"}
}