{
  "type": "Feature",
  "properties": {
    "iso:country":"GB",
    "wof:name":"TA4 3PA",
    "wof:placetype":"postalcode"
},
  "geometry": {"coordinates":[-3.18308617977907,51.05401565658111],"type":"Point"}
}