{
  "type": "Feature",
  "properties": {
    "iso:country":"GB",
    "wof:name":"ST3 7PZ",
    "wof:placetype":"postalcode"
},
  "geometry": {"coordinates":[-2.10537727433672,52.96872397504361],"type":"Point"}
}