{
  "type": "Feature",
  "properties": {
    "date:inception_lower": "1980-01-01",
    "date:inception_upper": "1980-01-01",
    "iso:country": "GB",
    "wof:name": "TR15 2EH",
    "wof:placetype": "postalcode"
  },
  "geometry": {"coordinates":[-5.222743,50.234455],"type":"Point"}
}
