{
  "type": "Feature",
  "properties": {
    "iso:country":"GB",
    "wof:name":"TR15 2EH",
    "wof:placetype":"postalcode"
},
  "geometry": {"coordinates":[-5.2227426358654,50.23445515087401],"type":"Point"}
}