{
  "type": "Feature",
  "properties": {
    "date:inception_lower":"1980-01-01",
    "date:inception_upper":"1980-01-31",
    "iso:country":"GB",
    "wof:name":"WA16 9RP",
    "wof:placetype":"postalcode"
},
  "geometry": {"coordinates":[-2.401003,53.276092],"type":"Point"}
}