{
  "type": "Feature",
  "properties": {
    "iso:country":"GB",
    "wof:name":"WA16 9RP",
    "wof:placetype":"postalcode"
},
  "geometry": {"coordinates":[-2.4010050577864,53.27607619122792],"type":"Point"}
}