{
  "type": "Feature",
  "properties": {
    "iso:country": "GB",
    "wof:name": "WA16 9RP",
    "wof:placetype": "postalcode"
  },
  "geometry": {"coordinates":[-2.401003,53.276092],"type":"Point"}
}
