{
  "type": "Feature",
  "properties": {
    "iso:country":"GB",
    "wof:name":"TQ9 6QX",
    "wof:placetype":"postalcode"
},
  "geometry": {"coordinates":[-3.62336614623445,50.40414579589513],"type":"Point"}
}