{
  "type": "Feature",
  "properties": {
    "iso:country": "GB",
    "wof:name": "TQ9 6QX",
    "wof:placetype": "postalcode"
  },
  "geometry": {"coordinates":[-3.623366,50.404146],"type":"Point"}
}
