{
  "type": "Feature",
  "properties": {
    "date:inception_lower": "1980-01-01",
    "date:inception_upper": "1980-01-01",
    "iso:country": "GB",
    "wof:name": "ME14 5HL",
    "wof:placetype": "postalcode"
  },
  "geometry": {"coordinates":[0.534573,51.282758],"type":"Point"}
}
