{
  "type": "Feature",
  "properties": {
    "iso:country":"GB",
    "wof:name":"ME14 5HL",
    "wof:placetype":"postalcode"
},
  "geometry": {"coordinates":[0.53457247976192,51.28275794599919],"type":"Point"}
}