{
  "type": "Feature",
  "properties": {
    "iso:country":"GB",
    "wof:name":"LA12 8NN",
    "wof:placetype":"postalcode"
},
  "geometry": {"coordinates":[-2.95084321298097,54.27499926888538],"type":"Point"}
}