{
  "type": "Feature",
  "properties": {
    "iso:country": "GB",
    "wof:name": "LA12 8NN",
    "wof:placetype": "postalcode"
  },
  "geometry": {"coordinates":[-2.950887,54.274909],"type":"Point"}
}
