{
  "type": "Feature",
  "properties": {
    "iso:country":"GB",
    "wof:name":"CF15 8HA",
    "wof:placetype":"postalcode"
},
  "geometry": {"coordinates":[-3.24216980303687,51.50995745760873],"type":"Point"}
}