{
  "type": "Feature",
  "properties": {
    "date:inception_lower": "2011-10-01",
    "date:inception_upper": "2011-10-01",
    "iso:country": "GB",
    "wof:name": "CF15 8HA",
    "wof:placetype": "postalcode"
  },
  "geometry": {"coordinates":[-3.24217,51.509957],"type":"Point"}
}
