{
  "type": "Feature",
  "properties": {
    "iso:country": "GB",
    "wof:name": "CF15 8HA",
    "wof:placetype": "postalcode"
  },
  "geometry": {"coordinates":[-3.24217,51.509957],"type":"Point"}
}
