{
  "type": "Feature",
  "properties": {
    "iso:country": "GB",
    "wof:name": "ST16 1QH",
    "wof:placetype": "postalcode"
  },
  "geometry": {"coordinates":[-2.130158,52.826659],"type":"Point"}
}
