{
  "type": "Feature",
  "properties": {
    "date:inception_lower": "1980-01-01",
    "date:inception_upper": "1980-01-01",
    "iso:country": "GB",
    "wof:name": "ST16 1QH",
    "wof:placetype": "postalcode"
  },
  "geometry": {"coordinates":[-2.130158,52.826659],"type":"Point"}
}
