{
  "type": "Feature",
  "properties": {
    "iso:country": "GB",
    "wof:name": "SK10 2ZD",
    "wof:placetype": "postalcode"
  },
  "geometry": {"coordinates":[-2.117619,53.281771],"type":"Point"}
}
