{
  "type": "Feature",
  "properties": {
    "iso:country":"GB",
    "wof:name":"TN34 3RB",
    "wof:placetype":"postalcode"
},
  "geometry": {"coordinates":[0.58465855667027,50.85715241167726],"type":"Point"}
}