{
  "type": "Feature",
  "properties": {
    "iso:country": "GB",
    "wof:name": "EH4 2PG",
    "wof:placetype": "postalcode"
  },
  "geometry": {"coordinates":[-3.236633,55.964683],"type":"Point"}
}
