{
  "type": "Feature",
  "properties": {
    "date:inception_lower":"1980-01-01",
    "date:inception_upper":"1980-01-31",
    "iso:country":"GB",
    "wof:name":"EH4 2PG",
    "wof:placetype":"postalcode"
},
  "geometry": {"coordinates":[-3.236633,55.964683],"type":"Point"}
}