{
  "type": "Feature",
  "properties": {
    "iso:country": "GB",
    "wof:name": "SA70 8GR",
    "wof:placetype": "postalcode"
  },
  "geometry": {"coordinates":[-4.763035,51.710923],"type":"Point"}
}
