{
  "type": "Feature",
  "properties": {
    "date:inception_lower":"2008-11-01",
    "date:inception_upper":"2008-11-30",
    "iso:country":"GB",
    "wof:name":"SA70 8GR",
    "wof:placetype":"postalcode"
},
  "geometry": {"coordinates":[-4.763035,51.710923],"type":"Point"}
}