{
  "type": "Feature",
  "properties": {
    "iso:country":"GB",
    "wof:name":"PA24 8AS",
    "wof:placetype":"postalcode"
},
  "geometry": {"coordinates":[-4.89624695463975,56.10166079067443],"type":"Point"}
}