{
  "type": "Feature",
  "properties": {
    "iso:country": "GB",
    "wof:name": "PA24 8AS",
    "wof:placetype": "postalcode"
  },
  "geometry": {"coordinates":[-4.896247,56.101661],"type":"Point"}
}
