{
  "type": "Feature",
  "properties": {
    "date:inception_lower": "2001-06-01",
    "date:inception_upper": "2001-06-01",
    "iso:country": "GB",
    "wof:name": "PA24 8AS",
    "wof:placetype": "postalcode"
  },
  "geometry": {"coordinates":[-4.896247,56.101661],"type":"Point"}
}
