{
  "type": "Feature",
  "properties": {
    "iso:country":"GB",
    "wof:name":"GU51 3FS",
    "wof:placetype":"postalcode"
},
  "geometry": {"coordinates":[-0.83768044002164,51.28473971924445],"type":"Point"}
}