{
  "type": "Feature",
  "properties": {
    "date:inception_lower": "2015-08-01",
    "date:inception_upper": "2015-08-01",
    "iso:country": "GB",
    "wof:name": "GU51 3FS",
    "wof:placetype": "postalcode"
  },
  "geometry": {"coordinates":[-0.837609,51.284639],"type":"Point"}
}
