{
  "type": "Feature",
  "properties": {
    "date:inception_lower": "2021-07-01",
    "date:inception_upper": "2021-07-01",
    "iso:country": "GB",
    "wof:name": "SK9 4FZ",
    "wof:placetype": "postalcode"
  },
  "geometry": {"coordinates":[-2.225123,53.343539],"type":"Point"}
}
