{
  "type": "Feature",
  "properties": {
    "date:inception_lower": "1980-01-01",
    "date:inception_upper": "1980-01-01",
    "iso:country": "GB",
    "wof:name": "HG1 5JA",
    "wof:placetype": "postalcode"
  },
  "geometry": {"coordinates":[-1.537028,54.001933],"type":"Point"}
}
