{
  "type": "Feature",
  "properties": {
    "iso:country":"GB",
    "wof:name":"HG1 5JA",
    "wof:placetype":"postalcode"
},
  "geometry": {"coordinates":[-1.53696232970148,54.00186391801024],"type":"Point"}
}