{
  "type": "Feature",
  "properties": {
    "date:inception_lower":"1999-12-01",
    "date:inception_upper":"1999-12-31",
    "iso:country":"GB",
    "wof:name":"CV37 8BQ",
    "wof:placetype":"postalcode"
},
  "geometry": {"coordinates":[-1.794566,52.134982],"type":"Point"}
}