{
  "type": "Feature",
  "properties": {
    "iso:country":"GB",
    "wof:name":"CV37 8BQ",
    "wof:placetype":"postalcode"
},
  "geometry": {"coordinates":[-1.79456587317775,52.13498181374815],"type":"Point"}
}