{
  "type": "Feature",
  "properties": {
    "iso:country":"GB",
    "wof:name":"NR32 2QP",
    "wof:placetype":"postalcode"
},
  "geometry": {"coordinates":[1.72947176439644,52.48143591757379],"type":"Point"}
}