{
  "type": "Feature",
  "properties": {
    "date:inception_lower": "1980-01-01",
    "date:inception_upper": "1980-01-01",
    "iso:country": "GB",
    "wof:name": "NE25 9XA",
    "wof:placetype": "postalcode"
  },
  "geometry": {"coordinates":[-1.478003,55.050925],"type":"Point"}
}
