{
  "type": "Feature",
  "properties": {
    "iso:country":"GB",
    "wof:name":"NE25 9XA",
    "wof:placetype":"postalcode"
},
  "geometry": {"coordinates":[-1.47800291057647,55.0509246294096],"type":"Point"}
}