{
  "type": "Feature",
  "properties": {
    "iso:country":"GB",
    "wof:name":"NG6 9AH",
    "wof:placetype":"postalcode"
},
  "geometry": {"coordinates":[-1.19181879165611,52.99895380604766],"type":"Point"}
}