{
  "type": "Feature",
  "properties": {
    "iso:country": "GB",
    "wof:name": "NG32 3QR",
    "wof:placetype": "postalcode"
  },
  "geometry": {"coordinates":[-0.531735,52.989004],"type":"Point"}
}
