{
  "type": "Feature",
  "properties": {
    "iso:country":"GB",
    "wof:name":"NR13 4BW",
    "wof:placetype":"postalcode"
},
  "geometry": {"coordinates":[1.48709865071945,52.61939604902022],"type":"Point"}
}