{
  "type": "Feature",
  "properties": {
    "iso:country": "GB",
    "wof:name": "TN21 8AL",
    "wof:placetype": "postalcode"
  },
  "geometry": {"coordinates":[0.252735,50.962962],"type":"Point"}
}
