{
  "type": "Feature",
  "properties": {
    "date:inception_lower": "2000-06-01",
    "date:inception_upper": "2000-06-01",
    "iso:country": "GB",
    "wof:name": "CA8 7HU",
    "wof:placetype": "postalcode"
  },
  "geometry": {"coordinates":[-2.541044,54.990191],"type":"Point"}
}
