{
  "type": "Feature",
  "properties": {
    "iso:country":"GB",
    "wof:name":"CA8 7HU",
    "wof:placetype":"postalcode"
},
  "geometry": {"coordinates":[-2.54104357281209,54.99019092314708],"type":"Point"}
}