{
  "type": "Feature",
  "properties": {
    "iso:country": "GB",
    "wof:name": "CA8 7HU",
    "wof:placetype": "postalcode"
  },
  "geometry": {"coordinates":[-2.541044,54.990191],"type":"Point"}
}
