{
  "type": "Feature",
  "properties": {
    "iso:country":"GB",
    "wof:name":"CV1 3AD",
    "wof:placetype":"postalcode"
},
  "geometry": {"coordinates":[-1.52347760416951,52.41092173884417],"type":"Point"}
}