{
  "type": "Feature",
  "properties": {
    "iso:country":"GB",
    "wof:name":"BH10 7BW",
    "wof:placetype":"postalcode"
},
  "geometry": {"coordinates":[-1.87520309513873,50.76339794447974],"type":"Point"}
}