{
  "type": "Feature",
  "properties": {
    "iso:country":"GB",
    "wof:name":"GL5 2SA",
    "wof:placetype":"postalcode"
},
  "geometry": {"coordinates":[-2.19252840342407,51.72050804621083],"type":"Point"}
}