{
  "type": "Feature",
  "properties": {
    "iso:country": "GB",
    "wof:name": "CA1 3DJ",
    "wof:placetype": "postalcode"
  },
  "geometry": {"coordinates":[-2.910901,54.87616],"type":"Point"}
}
