{
  "type": "Feature",
  "properties": {
    "iso:country":"GB",
    "wof:name":"CA1 3DJ",
    "wof:placetype":"postalcode"
},
  "geometry": {"coordinates":[-2.91091294228491,54.87615311999916],"type":"Point"}
}