{
  "type": "Feature",
  "properties": {
    "iso:country":"GB",
    "wof:name":"DH1 3HW",
    "wof:placetype":"postalcode"
},
  "geometry": {"coordinates":[-1.56790929232945,54.77408311413339],"type":"Point"}
}