{
  "type": "Feature",
  "properties": {
    "iso:country": "GB",
    "wof:name": "DH1 3HW",
    "wof:placetype": "postalcode"
  },
  "geometry": {"coordinates":[-1.567909,54.774083],"type":"Point"}
}
