{
  "type": "Feature",
  "properties": {
    "iso:country":"GB",
    "wof:name":"NG13 0HJ",
    "wof:placetype":"postalcode"
},
  "geometry": {"coordinates":[-0.83910013269686,52.90465330543184],"type":"Point"}
}