{
  "type": "Feature",
  "properties": {
    "iso:country":"GB",
    "wof:name":"NE32 5DN",
    "wof:placetype":"postalcode"
},
  "geometry": {"coordinates":[-1.48485088350343,54.96364320899163],"type":"Point"}
}