{
  "type": "Feature",
  "properties": {
    "date:inception_lower":"2010-01-01",
    "date:inception_upper":"2010-01-31",
    "iso:country":"GB",
    "wof:name":"B5 7BH",
    "wof:placetype":"postalcode"
},
  "geometry": {"coordinates":[-1.900799,52.466684],"type":"Point"}
}