{
  "type": "Feature",
  "properties": {
    "iso:country":"GB",
    "wof:name":"HR6 8QE",
    "wof:placetype":"postalcode"
},
  "geometry": {"coordinates":[-2.74277892654979,52.2156590593695],"type":"Point"}
}