{
  "type": "Feature",
  "properties": {
    "iso:country":"GB",
    "wof:name":"TS19 7BG",
    "wof:placetype":"postalcode"
},
  "geometry": {"coordinates":[-1.35637356835356,54.5639142838392],"type":"Point"}
}