{
  "type": "Feature",
  "properties": {
    "iso:country": "GB",
    "wof:name": "BD21 5EH",
    "wof:placetype": "postalcode"
  },
  "geometry": {"coordinates":[-1.917115,53.852361],"type":"Point"}
}
