{
  "type": "Feature",
  "properties": {
    "iso:country":"GB",
    "wof:name":"BB11 5RX",
    "wof:placetype":"postalcode"
},
  "geometry": {"coordinates":[-2.27300825890249,53.78407546166626],"type":"Point"}
}