{
  "type": "Feature",
  "properties": {
    "date:inception_lower": "2019-10-01",
    "date:inception_upper": "2019-10-01",
    "iso:country": "GB",
    "wof:name": "GL18 1UG",
    "wof:placetype": "postalcode"
  },
  "geometry": {"coordinates":[-2.41548,51.933782],"type":"Point"}
}
