{
  "type": "Feature",
  "properties": {
    "date:inception_lower": "1990-08-01",
    "date:inception_upper": "1990-08-01",
    "iso:country": "GB",
    "wof:name": "AB54 4XD",
    "wof:placetype": "postalcode"
  },
  "geometry": {"coordinates":[-2.951761,57.432231],"type":"Point"}
}
