{
  "type": "Feature",
  "properties": {
    "iso:country":"GB",
    "wof:name":"GL3 3EA",
    "wof:placetype":"postalcode"
},
  "geometry": {"coordinates":[-2.19239149685242,51.85507704774488],"type":"Point"}
}