{
  "type": "Feature",
  "properties": {
    "date:inception_lower":"1980-01-01",
    "date:inception_upper":"1980-01-31",
    "iso:country":"GB",
    "wof:name":"LL53 6EL",
    "wof:placetype":"postalcode"
},
  "geometry": {"coordinates":[-4.530844,52.936049],"type":"Point"}
}