{
  "type": "Feature",
  "properties": {
    "iso:country":"GB",
    "wof:name":"LL53 6EL",
    "wof:placetype":"postalcode"
},
  "geometry": {"coordinates":[-4.53083631373197,52.93603226354548],"type":"Point"}
}