{
  "type": "Feature",
  "properties": {
    "iso:country":"GB",
    "wof:name":"CB23 2TZ",
    "wof:placetype":"postalcode"
},
  "geometry": {"coordinates":[-0.07857538667861,52.17586927378459],"type":"Point"}
}