{
  "type": "Feature",
  "properties": {
    "iso:country": "GB",
    "wof:name": "CB23 2TZ",
    "wof:placetype": "postalcode"
  },
  "geometry": {"coordinates":[-0.078575,52.175869],"type":"Point"}
}
