{
  "type": "Feature",
  "properties": {
    "iso:country":"GB",
    "wof:name":"EX39 4JB",
    "wof:placetype":"postalcode"
},
  "geometry": {"coordinates":[-4.1799582095941,51.0514129624627],"type":"Point"}
}