{
  "type": "Feature",
  "properties": {
    "iso:country":"GB",
    "wof:name":"E16 1UB",
    "wof:placetype":"postalcode"
},
  "geometry": {"coordinates":[0.02618927944399,51.504399135622],"type":"Point"}
}