{
  "type": "Feature",
  "properties": {
    "date:inception_lower": "2002-06-01",
    "date:inception_upper": "2002-06-01",
    "iso:country": "GB",
    "wof:name": "WA5 2JD",
    "wof:placetype": "postalcode"
  },
  "geometry": {"coordinates":[-2.6487,53.386869],"type":"Point"}
}
