{
  "type": "Feature",
  "properties": {
    "iso:country": "GB",
    "wof:name": "L26 7AD",
    "wof:placetype": "postalcode"
  },
  "geometry": {"coordinates":[-2.834968,53.368849],"type":"Point"}
}
