{
  "type": "Feature",
  "properties": {
    "iso:country":"GB",
    "wof:name":"L26 7AD",
    "wof:placetype":"postalcode"
},
  "geometry": {"coordinates":[-2.83496814019977,53.36884853223408],"type":"Point"}
}