{
  "type": "Feature",
  "properties": {
    "date:inception_lower": "1980-01-01",
    "date:inception_upper": "1980-01-01",
    "iso:country": "GB",
    "wof:name": "NR3 1TZ",
    "wof:placetype": "postalcode"
  },
  "geometry": {"coordinates":[1.301755,52.636431],"type":"Point"}
}
