{
  "type": "Feature",
  "properties": {
    "iso:country":"GB",
    "wof:name":"NR3 1TZ",
    "wof:placetype":"postalcode"
},
  "geometry": {"coordinates":[1.30175499229837,52.63643080363727],"type":"Point"}
}