{
  "type": "Feature",
  "properties": {
    "iso:country":"GB",
    "wof:name":"HU8 0LY",
    "wof:placetype":"postalcode"
},
  "geometry": {"coordinates":[-0.29785533923439,53.77144453091744],"type":"Point"}
}