{
  "type": "Feature",
  "properties": {
    "iso:country": "GB",
    "wof:name": "PE10 9HW",
    "wof:placetype": "postalcode"
  },
  "geometry": {"coordinates":[-0.370156,52.76811],"type":"Point"}
}
