{
  "type": "Feature",
  "properties": {
    "iso:country":"GB",
    "wof:name":"HX2 0LZ",
    "wof:placetype":"postalcode"
},
  "geometry": {"coordinates":[-1.8962762802811,53.7281580744262],"type":"Point"}
}