{
  "type": "Feature",
  "properties": {
    "iso:country": "GB",
    "wof:name": "DH6 1HP",
    "wof:placetype": "postalcode"
  },
  "geometry": {"coordinates":[-1.499478,54.77294],"type":"Point"}
}
