{
  "type": "Feature",
  "properties": {
    "date:inception_lower": "1993-01-01",
    "date:inception_upper": "1993-01-01",
    "iso:country": "GB",
    "wof:name": "SS4 3QZ",
    "wof:placetype": "postalcode"
  },
  "geometry": {"coordinates":[0.742891,51.617323],"type":"Point"}
}
