{
  "type": "Feature",
  "properties": {
    "iso:country":"GB",
    "wof:name":"SS4 3QZ",
    "wof:placetype":"postalcode"
},
  "geometry": {"coordinates":[0.742875110317,51.61730855765827],"type":"Point"}
}