{
  "type": "Feature",
  "properties": {
    "date:inception_lower": "1980-01-01",
    "date:inception_upper": "1980-01-01",
    "iso:country": "GB",
    "wof:name": "BB9 5LF",
    "wof:placetype": "postalcode"
  },
  "geometry": {"coordinates":[-2.235854,53.821652],"type":"Point"}
}
