{
  "type": "Feature",
  "properties": {
    "iso:country":"GB",
    "wof:name":"BB9 5LF",
    "wof:placetype":"postalcode"
},
  "geometry": {"coordinates":[-2.23585399269672,53.82165218888976],"type":"Point"}
}