{
  "type": "Feature",
  "properties": {
    "date:inception_lower": "1980-01-01",
    "date:inception_upper": "1980-01-01",
    "iso:country": "GB",
    "wof:name": "OL1 3QU",
    "wof:placetype": "postalcode"
  },
  "geometry": {"coordinates":[-2.1039,53.54745],"type":"Point"}
}
