{
  "type": "Feature",
  "properties": {
    "iso:country":"GB",
    "wof:name":"OL1 3QU",
    "wof:placetype":"postalcode"
},
  "geometry": {"coordinates":[-2.10390014023867,53.54744967796226],"type":"Point"}
}