{
  "type": "Feature",
  "properties": {
    "iso:country": "GB",
    "wof:name": "RH6 9UZ",
    "wof:placetype": "postalcode"
  },
  "geometry": {"coordinates":[-0.148528,51.177569],"type":"Point"}
}
