{
  "type": "Feature",
  "properties": {
    "iso:country":"GB",
    "wof:name":"PR7 4LU",
    "wof:placetype":"postalcode"
},
  "geometry": {"coordinates":[-2.65569754981582,53.61674994020254],"type":"Point"}
}