{
  "type": "Feature",
  "properties": {
    "iso:country":"GB",
    "wof:name":"N7 7BG",
    "wof:placetype":"postalcode"
},
  "geometry": {"coordinates":[-0.10725372156683,51.55243664264169],"type":"Point"}
}