{
  "type": "Feature",
  "properties": {
    "date:inception_lower": "2020-12-01",
    "date:inception_upper": "2020-12-01",
    "iso:country": "GB",
    "wof:name": "DL5 7BF",
    "wof:placetype": "postalcode"
  },
  "geometry": {"coordinates":[-1.59057,54.630609],"type":"Point"}
}
