{
  "type": "Feature",
  "properties": {
    "iso:country": "GB",
    "wof:name": "IP16 4GX",
    "wof:placetype": "postalcode"
  },
  "geometry": {"coordinates":[1.572619,52.208313],"type":"Point"}
}
