{
  "type": "Feature",
  "properties": {
    "date:inception_lower": "2005-09-01",
    "date:inception_upper": "2005-09-01",
    "iso:country": "GB",
    "wof:name": "IP16 4GX",
    "wof:placetype": "postalcode"
  },
  "geometry": {"coordinates":[1.572619,52.208313],"type":"Point"}
}
