{
  "type": "Feature",
  "properties": {
    "iso:country":"GB",
    "wof:name":"SE23 2JQ",
    "wof:placetype":"postalcode"
},
  "geometry": {"coordinates":[-0.04415657876755,51.43642176191353],"type":"Point"}
}