{
  "type": "Feature",
  "properties": {
    "iso:country":"GB",
    "wof:name":"RG10 9UR",
    "wof:placetype":"postalcode"
},
  "geometry": {"coordinates":[-0.8165041108385,51.50802494160133],"type":"Point"}
}