{
  "type": "Feature",
  "properties": {
    "iso:country":"GB",
    "wof:name":"DL15 9DA",
    "wof:placetype":"postalcode"
},
  "geometry": {"coordinates":[-1.73820484624226,54.71396431351155],"type":"Point"}
}