{
  "type": "Feature",
  "properties": {
    "iso:country":"GB",
    "wof:name":"LS1 5HN",
    "wof:placetype":"postalcode"
},
  "geometry": {"coordinates":[-1.54680787965293,53.79732811323959],"type":"Point"}
}