{
  "type": "Feature",
  "properties": {
    "date:inception_lower": "1991-01-01",
    "date:inception_upper": "1991-01-01",
    "iso:country": "GB",
    "wof:name": "NE37 2PA",
    "wof:placetype": "postalcode"
  },
  "geometry": {"coordinates":[-1.501136,54.907087],"type":"Point"}
}
