{
  "type": "Feature",
  "properties": {
    "iso:country":"GB",
    "wof:name":"E1 8JX",
    "wof:placetype":"postalcode"
},
  "geometry": {"coordinates":[-0.06955889875255,51.51060054837075],"type":"Point"}
}