{
  "type": "Feature",
  "properties": {
    "date:inception_lower": "1996-06-01",
    "date:inception_upper": "1996-06-01",
    "iso:country": "GB",
    "wof:name": "AB41 6QG",
    "wof:placetype": "postalcode"
  },
  "geometry": {"coordinates":[-2.15459,57.309348],"type":"Point"}
}
