{
  "type": "Feature",
  "properties": {
    "iso:country":"GB",
    "wof:name":"AB41 6QG",
    "wof:placetype":"postalcode"
},
  "geometry": {"coordinates":[-2.15448723342999,57.30936290805629],"type":"Point"}
}