{
  "type": "Feature",
  "properties": {
    "date:inception_lower":"1980-01-01",
    "date:inception_upper":"1980-01-31",
    "iso:country":"GB",
    "wof:name":"CV7 7HS",
    "wof:placetype":"postalcode"
},
  "geometry": {"coordinates":[-1.648228,52.457558],"type":"Point"}
}