{
  "type": "Feature",
  "properties": {
    "iso:country":"GB",
    "wof:name":"CV7 7HS",
    "wof:placetype":"postalcode"
},
  "geometry": {"coordinates":[-1.64822851284461,52.45755839278597],"type":"Point"}
}