{
  "type": "Feature",
  "properties": {
    "iso:country": "GB",
    "wof:name": "CV7 7HS",
    "wof:placetype": "postalcode"
  },
  "geometry": {"coordinates":[-1.648228,52.457558],"type":"Point"}
}
