{
  "type": "Feature",
  "properties": {
    "iso:country":"GB",
    "wof:name":"OX2 7DT",
    "wof:placetype":"postalcode"
},
  "geometry": {"coordinates":[-1.26225266469472,51.77516777983919],"type":"Point"}
}