{
  "type": "Feature",
  "properties": {
    "iso:country": "GB",
    "wof:name": "OX2 7DT",
    "wof:placetype": "postalcode"
  },
  "geometry": {"coordinates":[-1.262253,51.775168],"type":"Point"}
}
