{
  "type": "Feature",
  "properties": {
    "iso:country":"GB",
    "wof:name":"SW18 4QE",
    "wof:placetype":"postalcode"
},
  "geometry": {"coordinates":[-0.19154502213935,51.44190882824933],"type":"Point"}
}