{
  "type": "Feature",
  "properties": {
    "date:inception_lower":"1980-01-01",
    "date:inception_upper":"1980-01-31",
    "iso:country":"GB",
    "wof:name":"SW18 4QE",
    "wof:placetype":"postalcode"
},
  "geometry": {"coordinates":[-0.191545,51.441909],"type":"Point"}
}