{
  "type": "Feature",
  "properties": {
    "iso:country": "GB",
    "wof:name": "SW18 4QE",
    "wof:placetype": "postalcode"
  },
  "geometry": {"coordinates":[-0.191545,51.441909],"type":"Point"}
}
