{
  "type": "Feature",
  "properties": {
    "iso:country":"GB",
    "wof:name":"LU3 1AB",
    "wof:placetype":"postalcode"
},
  "geometry": {"coordinates":[-0.42500530348024,51.88575939037675],"type":"Point"}
}