{
  "type": "Feature",
  "properties": {
    "iso:country":"GB",
    "wof:name":"CW5 7HH",
    "wof:placetype":"postalcode"
},
  "geometry": {"coordinates":[-2.47897057050303,53.05582752955673],"type":"Point"}
}