{
  "type": "Feature",
  "properties": {
    "iso:country": "GB",
    "wof:name": "CW5 7HH",
    "wof:placetype": "postalcode"
  },
  "geometry": {"coordinates":[-2.482755,53.056755],"type":"Point"}
}
