{
  "type": "Feature",
  "properties": {
    "iso:country":"GB",
    "wof:name":"LE18 1FR",
    "wof:placetype":"postalcode"
},
  "geometry": {"coordinates":[-1.11440591721214,52.59016840501744],"type":"Point"}
}