{
  "type": "Feature",
  "properties": {
    "iso:country": "GB",
    "wof:name": "PR8 4TJ",
    "wof:placetype": "postalcode"
  },
  "geometry": {"coordinates":[-3.015397,53.630067],"type":"Point"}
}
