{
  "type": "Feature",
  "properties": {
    "date:inception_lower": "1981-06-01",
    "date:inception_upper": "1981-06-01",
    "iso:country": "GB",
    "wof:name": "PR8 4TJ",
    "wof:placetype": "postalcode"
  },
  "geometry": {"coordinates":[-3.015397,53.630067],"type":"Point"}
}
