{
  "type": "Feature",
  "properties": {
    "iso:country":"GB",
    "wof:name":"NG2 3AH",
    "wof:placetype":"postalcode"
},
  "geometry": {"coordinates":[-1.13922434180902,52.94626603248736],"type":"Point"}
}