{
  "type": "Feature",
  "properties": {
    "date:inception_lower": "1980-01-01",
    "date:inception_upper": "1980-01-01",
    "iso:country": "GB",
    "wof:name": "KW10 6RJ",
    "wof:placetype": "postalcode"
  },
  "geometry": {"coordinates":[-3.970191,57.97545],"type":"Point"}
}
