{
  "type": "Feature",
  "properties": {
    "iso:country": "GB",
    "wof:name": "KW10 6RJ",
    "wof:placetype": "postalcode"
  },
  "geometry": {"coordinates":[-3.970191,57.97545],"type":"Point"}
}
