{
  "type": "Feature",
  "properties": {
    "iso:country":"GB",
    "wof:name":"NN17 5EN",
    "wof:placetype":"postalcode"
},
  "geometry": {"coordinates":[-0.63716170677843,52.50531757005066],"type":"Point"}
}