{
  "type": "Feature",
  "properties": {
    "date:inception_lower": "2011-11-01",
    "date:inception_upper": "2011-11-01",
    "iso:country": "GB",
    "wof:name": "NN17 5EN",
    "wof:placetype": "postalcode"
  },
  "geometry": {"coordinates":[-0.637162,52.505318],"type":"Point"}
}
