{
  "type": "Feature",
  "properties": {
    "iso:country":"GB",
    "wof:name":"NR19 1SD",
    "wof:placetype":"postalcode"
},
  "geometry": {"coordinates":[0.9961130390342,52.66171891525813],"type":"Point"}
}