{
  "type": "Feature",
  "properties": {
    "iso:country":"GB",
    "wof:name":"BR2 9RR",
    "wof:placetype":"postalcode"
},
  "geometry": {"coordinates":[0.03464406600212,51.39360529489793],"type":"Point"}
}