{
  "type": "Feature",
  "properties": {
    "iso:country":"GB",
    "wof:name":"DA2 7BT",
    "wof:placetype":"postalcode"
},
  "geometry": {"coordinates":[0.20284119764141,51.42584338943229],"type":"Point"}
}