{
  "type": "Feature",
  "properties": {
    "iso:country":"GB",
    "wof:name":"CV37 7EU",
    "wof:placetype":"postalcode"
},
  "geometry": {"coordinates":[-1.68766065526551,52.18557057653572],"type":"Point"}
}