{
  "type": "Feature",
  "properties": {
    "date:inception_lower": "2001-12-01",
    "date:inception_upper": "2001-12-01",
    "iso:country": "GB",
    "wof:name": "W6 9NU",
    "wof:placetype": "postalcode"
  },
  "geometry": {"coordinates":[-0.238318,51.492701],"type":"Point"}
}
