{
  "type": "Feature",
  "properties": {
    "iso:country":"GB",
    "wof:name":"B92 7PS",
    "wof:placetype":"postalcode"
},
  "geometry": {"coordinates":[-1.79916339483361,52.45737120940183],"type":"Point"}
}