{
  "type": "Feature",
  "properties": {
    "iso:country": "GB",
    "wof:name": "B92 7PS",
    "wof:placetype": "postalcode"
  },
  "geometry": {"coordinates":[-1.799163,52.457371],"type":"Point"}
}
