{
  "type": "Feature",
  "properties": {
    "iso:country": "GB",
    "wof:name": "FK7 0BY",
    "wof:placetype": "postalcode"
  },
  "geometry": {"coordinates":[-3.934932,56.100352],"type":"Point"}
}
