{
  "type": "Feature",
  "properties": {
    "iso:country":"GB",
    "wof:name":"YO25 8SQ",
    "wof:placetype":"postalcode"
},
  "geometry": {"coordinates":[-0.3056337061602,53.91049894322387],"type":"Point"}
}