{
  "type": "Feature",
  "properties": {
    "iso:country": "GB",
    "wof:name": "YO25 8SQ",
    "wof:placetype": "postalcode"
  },
  "geometry": {"coordinates":[-0.305634,53.910499],"type":"Point"}
}
