{
  "type": "Feature",
  "properties": {
    "iso:country": "GB",
    "wof:name": "N10 3FA",
    "wof:placetype": "postalcode"
  },
  "geometry": {"coordinates":[-0.150053,51.588013],"type":"Point"}
}
