{
  "type": "Feature",
  "properties": {
    "iso:country":"GB",
    "wof:name":"ST11 9DP",
    "wof:placetype":"postalcode"
},
  "geometry": {"coordinates":[-2.05300145756833,52.97353224970291],"type":"Point"}
}