{
  "type": "Feature",
  "properties": {
    "iso:country": "GB",
    "wof:name": "ST11 9DP",
    "wof:placetype": "postalcode"
  },
  "geometry": {"coordinates":[-2.053001,52.973532],"type":"Point"}
}
