{
  "type": "Feature",
  "properties": {
    "date:inception_lower": "1980-01-01",
    "date:inception_upper": "1980-01-01",
    "iso:country": "GB",
    "wof:name": "B77 1HD",
    "wof:placetype": "postalcode"
  },
  "geometry": {"coordinates":[-1.688644,52.61566],"type":"Point"}
}
