{
  "type": "Feature",
  "properties": {
    "iso:country": "GB",
    "wof:name": "B77 1HD",
    "wof:placetype": "postalcode"
  },
  "geometry": {"coordinates":[-1.688644,52.61566],"type":"Point"}
}
