{
  "type": "Feature",
  "properties": {
    "iso:country": "GB",
    "wof:name": "PO7 3DU",
    "wof:placetype": "postalcode"
  },
  "geometry": {"coordinates":[-1.047815,50.883662],"type":"Point"}
}
