{
  "type": "Feature",
  "properties": {
    "date:inception_lower": "1980-01-01",
    "date:inception_upper": "1980-01-01",
    "iso:country": "GB",
    "wof:name": "NG34 8QR",
    "wof:placetype": "postalcode"
  },
  "geometry": {"coordinates":[-0.478434,53.01548],"type":"Point"}
}
