{
  "type": "Feature",
  "properties": {
    "iso:country":"GB",
    "wof:name":"NW3 4PB",
    "wof:placetype":"postalcode"
},
  "geometry": {"coordinates":[-0.16746177406411,51.54560504793092],"type":"Point"}
}