{
  "type": "Feature",
  "properties": {
    "iso:country": "GB",
    "wof:name": "WD6 5HQ",
    "wof:placetype": "postalcode"
  },
  "geometry": {"coordinates":[-0.275199,51.662114],"type":"Point"}
}
