{
  "type": "Feature",
  "properties": {
    "iso:country":"GB",
    "wof:name":"WD6 5HQ",
    "wof:placetype":"postalcode"
},
  "geometry": {"coordinates":[-0.27519888505054,51.66211410100208],"type":"Point"}
}