{
  "type": "Feature",
  "properties": {
    "iso:country":"GB",
    "wof:name":"DT6 5QH",
    "wof:placetype":"postalcode"
},
  "geometry": {"coordinates":[-2.86094694031083,50.8112828041521],"type":"Point"}
}