{
  "type": "Feature",
  "properties": {
    "iso:country":"GB",
    "wof:name":"SN38 4TD",
    "wof:placetype":"postalcode"
},
  "geometry": {"coordinates":[-1.83675990089628,51.57226954877092],"type":"Point"}
}