{
  "type": "Feature",
  "properties": {
    "date:inception_lower": "1983-07-01",
    "date:inception_upper": "1983-07-01",
    "iso:country": "GB",
    "wof:name": "BD4 8ST",
    "wof:placetype": "postalcode"
  },
  "geometry": {"coordinates":[-1.726892,53.785622],"type":"Point"}
}
