{
  "type": "Feature",
  "properties": {
    "iso:country":"GB",
    "wof:name":"PO14 4RD",
    "wof:placetype":"postalcode"
},
  "geometry": {"coordinates":[-1.26071011155627,50.85481785176047],"type":"Point"}
}