{
  "type": "Feature",
  "properties": {
    "date:inception_lower":"1998-12-01",
    "date:inception_upper":"1998-12-31",
    "iso:country":"GB",
    "wof:name":"SG2 7SH",
    "wof:placetype":"postalcode"
},
  "geometry": {"coordinates":[-0.159788,51.91786],"type":"Point"}
}