{
  "type": "Feature",
  "properties": {
    "iso:country":"GB",
    "wof:name":"SG2 7SH",
    "wof:placetype":"postalcode"
},
  "geometry": {"coordinates":[-0.15978778177209,51.91786019542656],"type":"Point"}
}