{
  "type": "Feature",
  "properties": {
    "iso:country": "GB",
    "wof:name": "SG2 7SH",
    "wof:placetype": "postalcode"
  },
  "geometry": {"coordinates":[-0.159788,51.91786],"type":"Point"}
}
