{
  "type": "Feature",
  "properties": {
    "iso:country":"GB",
    "wof:name":"BN26 6TG",
    "wof:placetype":"postalcode"
},
  "geometry": {"coordinates":[0.17034324493772,50.8491100809964],"type":"Point"}
}