{
  "type": "Feature",
  "properties": {
    "iso:country":"GB",
    "wof:name":"CT12 5JR",
    "wof:placetype":"postalcode"
},
  "geometry": {"coordinates":[1.36624928902372,51.32682775958487],"type":"Point"}
}