{
  "type": "Feature",
  "properties": {
    "iso:country":"GB",
    "wof:name":"BD23 4DY",
    "wof:placetype":"postalcode"
},
  "geometry": {"coordinates":[-2.17542464351131,54.01699755815294],"type":"Point"}
}