{
  "type": "Feature",
  "properties": {
    "date:inception_lower":"1980-01-01",
    "date:inception_upper":"1980-01-31",
    "iso:country":"GB",
    "wof:name":"BD23 4DY",
    "wof:placetype":"postalcode"
},
  "geometry": {"coordinates":[-2.175425,54.016998],"type":"Point"}
}