{
  "type": "Feature",
  "properties": {
    "iso:country": "GB",
    "wof:name": "BD23 4DY",
    "wof:placetype": "postalcode"
  },
  "geometry": {"coordinates":[-2.175425,54.016998],"type":"Point"}
}
