{
  "type": "Feature",
  "properties": {
    "iso:country":"GB",
    "wof:name":"CB22 3AE",
    "wof:placetype":"postalcode"
},
  "geometry": {"coordinates":[0.18213185807097,52.15798985531192],"type":"Point"}
}