{
  "type": "Feature",
  "properties": {
    "iso:country":"GB",
    "wof:name":"CH63 2JA",
    "wof:placetype":"postalcode"
},
  "geometry": {"coordinates":[-3.02098693546073,53.35190486108147],"type":"Point"}
}