{
  "type": "Feature",
  "properties": {
    "iso:country":"GB",
    "wof:name":"CB6 3UL",
    "wof:placetype":"postalcode"
},
  "geometry": {"coordinates":[0.1493498200573,52.3500381171686],"type":"Point"}
}