{
  "type": "Feature",
  "properties": {
    "iso:country": "GB",
    "wof:name": "CB6 3UL",
    "wof:placetype": "postalcode"
  },
  "geometry": {"coordinates":[0.14935,52.350038],"type":"Point"}
}
