{
  "type": "Feature",
  "properties": {
    "iso:country":"GB",
    "wof:name":"UB7 0EG",
    "wof:placetype":"postalcode"
},
  "geometry": {"coordinates":[-0.49183361913946,51.47946371692142],"type":"Point"}
}