{
  "type": "Feature",
  "properties": {
    "iso:country": "GB",
    "wof:name": "UB7 0EG",
    "wof:placetype": "postalcode"
  },
  "geometry": {"coordinates":[-0.491834,51.479464],"type":"Point"}
}
