{
  "type": "Feature",
  "properties": {
    "iso:country":"GB",
    "wof:name":"WR4 0DU",
    "wof:placetype":"postalcode"
},
  "geometry": {"coordinates":[-2.17905471489573,52.21014806408496],"type":"Point"}
}