{
  "type": "Feature",
  "properties": {
    "iso:country": "GB",
    "wof:name": "WR4 0DU",
    "wof:placetype": "postalcode"
  },
  "geometry": {"coordinates":[-2.179055,52.210148],"type":"Point"}
}
