{
  "type": "Feature",
  "properties": {
    "iso:country": "GB",
    "wof:name": "RH12 1PF",
    "wof:placetype": "postalcode"
  },
  "geometry": {"coordinates":[-0.330228,51.06261],"type":"Point"}
}
