{
  "type": "Feature",
  "properties": {
    "date:inception_lower": "1980-01-01",
    "date:inception_upper": "1980-01-01",
    "iso:country": "GB",
    "wof:name": "BB3 3NY",
    "wof:placetype": "postalcode"
  },
  "geometry": {"coordinates":[-2.432833,53.705687],"type":"Point"}
}
