{
  "type": "Feature",
  "properties": {
    "iso:country":"GB",
    "wof:name":"BB3 3NY",
    "wof:placetype":"postalcode"
},
  "geometry": {"coordinates":[-2.43283313124299,53.70568678173856],"type":"Point"}
}