{
  "type": "Feature",
  "properties": {
    "iso:country":"GB",
    "wof:name":"YO23 3XF",
    "wof:placetype":"postalcode"
},
  "geometry": {"coordinates":[-1.13917315556842,53.91746980514908],"type":"Point"}
}