{
  "type": "Feature",
  "properties": {
    "iso:country": "GB",
    "wof:name": "PL3 5LJ",
    "wof:placetype": "postalcode"
  },
  "geometry": {"coordinates":[-4.13074,50.389309],"type":"Point"}
}
