{
  "type": "Feature",
  "properties": {
    "date:inception_lower": "1980-01-01",
    "date:inception_upper": "1980-01-01",
    "iso:country": "GB",
    "wof:name": "IP8 3BL",
    "wof:placetype": "postalcode"
  },
  "geometry": {"coordinates":[1.096494,52.062048],"type":"Point"}
}
