{
  "type": "Feature",
  "properties": {
    "iso:country":"GB",
    "wof:name":"IP8 3BL",
    "wof:placetype":"postalcode"
},
  "geometry": {"coordinates":[1.09661113399933,52.06203880072986],"type":"Point"}
}