{
  "type": "Feature",
  "properties": {
    "iso:country": "GB",
    "wof:name": "BS9 3LP",
    "wof:placetype": "postalcode"
  },
  "geometry": {"coordinates":[-2.621939,51.499907],"type":"Point"}
}
