{
  "type": "Feature",
  "properties": {
    "iso:country":"GB",
    "wof:name":"EH14 7ES",
    "wof:placetype":"postalcode"
},
  "geometry": {"coordinates":[-3.34028250412166,55.87839715732493],"type":"Point"}
}