{
  "type": "Feature",
  "properties": {
    "iso:country":"GB",
    "wof:name":"CT2 7BW",
    "wof:placetype":"postalcode"
},
  "geometry": {"coordinates":[1.08175379903579,51.29705909636002],"type":"Point"}
}