{
  "type": "Feature",
  "properties": {
    "date:inception_lower": "2016-10-01",
    "date:inception_upper": "2016-10-01",
    "iso:country": "GB",
    "wof:name": "W5 2TF",
    "wof:placetype": "postalcode"
  },
  "geometry": {"coordinates":[-0.305886,51.518956],"type":"Point"}
}
