{
  "type": "Feature",
  "properties": {
    "iso:country":"GB",
    "wof:name":"LS13 3HD",
    "wof:placetype":"postalcode"
},
  "geometry": {"coordinates":[-1.64733374845374,53.81084202770818],"type":"Point"}
}