{
  "type": "Feature",
  "properties": {
    "iso:country": "GB",
    "wof:name": "EX8 4QX",
    "wof:placetype": "postalcode"
  },
  "geometry": {"coordinates":[-3.404629,50.637955],"type":"Point"}
}
