{
  "type": "Feature",
  "properties": {
    "iso:country": "GB",
    "wof:name": "AB55 5NG",
    "wof:placetype": "postalcode"
  },
  "geometry": {"coordinates":[-2.948341,57.536254],"type":"Point"}
}
