{
  "type": "Feature",
  "properties": {
    "date:inception_lower": "2001-12-01",
    "date:inception_upper": "2001-12-01",
    "iso:country": "GB",
    "wof:name": "AB55 5NG",
    "wof:placetype": "postalcode"
  },
  "geometry": {"coordinates":[-2.948341,57.536254],"type":"Point"}
}
