{
  "type": "Feature",
  "properties": {
    "iso:country":"GB",
    "wof:name":"AB55 5NG",
    "wof:placetype":"postalcode"
},
  "geometry": {"coordinates":[-2.948341107849,57.53625380854496],"type":"Point"}
}