{
  "type": "Feature",
  "properties": {
    "iso:country":"GB",
    "wof:name":"NG17 7QH",
    "wof:placetype":"postalcode"
},
  "geometry": {"coordinates":[-1.23172299819411,53.09792089473472],"type":"Point"}
}