{
  "type": "Feature",
  "properties": {
    "date:inception_lower": "2005-02-01",
    "date:inception_upper": "2005-02-01",
    "iso:country": "GB",
    "wof:name": "RH12 9SD",
    "wof:placetype": "postalcode"
  },
  "geometry": {"coordinates":[-0.322512,51.064419],"type":"Point"}
}
