{
  "type": "Feature",
  "properties": {
    "iso:country":"GB",
    "wof:name":"BD5 0PD",
    "wof:placetype":"postalcode"
},
  "geometry": {"coordinates":[-1.76672218265102,53.7793608493617],"type":"Point"}
}