{
  "type": "Feature",
  "properties": {
    "date:inception_lower": "2000-06-01",
    "date:inception_upper": "2000-06-01",
    "iso:country": "GB",
    "wof:name": "L31 0EB",
    "wof:placetype": "postalcode"
  },
  "geometry": {"coordinates":[-2.941965,53.515963],"type":"Point"}
}
