{
  "type": "Feature",
  "properties": {
    "iso:country":"GB",
    "wof:name":"L31 0EB",
    "wof:placetype":"postalcode"
},
  "geometry": {"coordinates":[-2.94196488554335,53.51596334097569],"type":"Point"}
}