{
  "type": "Feature",
  "properties": {
    "iso:country":"GB",
    "wof:name":"CH63 2LF",
    "wof:placetype":"postalcode"
},
  "geometry": {"coordinates":[-3.0261464293185,53.35029650394905],"type":"Point"}
}