{
  "type": "Feature",
  "properties": {
    "date:inception_lower":"1980-01-01",
    "date:inception_upper":"1980-01-31",
    "iso:country":"GB",
    "wof:name":"BA13 3EZ",
    "wof:placetype":"postalcode"
},
  "geometry": {"coordinates":[-2.177453,51.259808],"type":"Point"}
}