{
  "type": "Feature",
  "properties": {
    "iso:country":"GB",
    "wof:name":"BA13 3EZ",
    "wof:placetype":"postalcode"
},
  "geometry": {"coordinates":[-2.17745353920044,51.25980792818311],"type":"Point"}
}