{
  "type": "Feature",
  "properties": {
    "iso:country":"GB",
    "wof:name":"OX9 3HW",
    "wof:placetype":"postalcode"
},
  "geometry": {"coordinates":[-0.96498948569714,51.75576255304566],"type":"Point"}
}