{
  "type": "Feature",
  "properties": {
    "iso:country": "GB",
    "wof:name": "OX9 3HW",
    "wof:placetype": "postalcode"
  },
  "geometry": {"coordinates":[-0.964989,51.755763],"type":"Point"}
}
