{
  "type": "Feature",
  "properties": {
    "date:inception_lower": "2007-02-01",
    "date:inception_upper": "2007-02-01",
    "iso:country": "GB",
    "wof:name": "OX9 3HW",
    "wof:placetype": "postalcode"
  },
  "geometry": {"coordinates":[-0.964989,51.755763],"type":"Point"}
}
