{
  "type": "Feature",
  "properties": {
    "date:inception_lower":"1980-01-01",
    "date:inception_upper":"1980-01-31",
    "iso:country":"GB",
    "wof:name":"SE15 2HD",
    "wof:placetype":"postalcode"
},
  "geometry": {"coordinates":[-0.060277,51.475997],"type":"Point"}
}