{
  "type": "Feature",
  "properties": {
    "iso:country": "GB",
    "wof:name": "NE22 7DQ",
    "wof:placetype": "postalcode"
  },
  "geometry": {"coordinates":[-1.591182,55.146337],"type":"Point"}
}
