{
  "type": "Feature",
  "properties": {
    "iso:country": "GB",
    "wof:name": "NE8 4YA",
    "wof:placetype": "postalcode"
  },
  "geometry": {"coordinates":[-1.620373,54.946807],"type":"Point"}
}
