{
  "type": "Feature",
  "properties": {
    "date:inception_lower":"1980-01-01",
    "date:inception_upper":"1980-01-31",
    "iso:country":"GB",
    "wof:name":"NE8 4YA",
    "wof:placetype":"postalcode"
},
  "geometry": {"coordinates":[-1.620373,54.946807],"type":"Point"}
}