{
  "type": "Feature",
  "properties": {
    "iso:country":"GB",
    "wof:name":"NE8 4YA",
    "wof:placetype":"postalcode"
},
  "geometry": {"coordinates":[-1.6203730165755,54.94680690751796],"type":"Point"}
}