{
  "type": "Feature",
  "properties": {
    "iso:country":"GB",
    "wof:name":"CM8 3DZ",
    "wof:placetype":"postalcode"
},
  "geometry": {"coordinates":[0.64642293586904,51.79648595019695],"type":"Point"}
}