{
  "type": "Feature",
  "properties": {
    "date:inception_lower": "2012-06-01",
    "date:inception_upper": "2012-06-01",
    "iso:country": "GB",
    "wof:name": "PO22 9SB",
    "wof:placetype": "postalcode"
  },
  "geometry": {"coordinates":[-0.66253,50.802742],"type":"Point"}
}
