{
  "type": "Feature",
  "properties": {
    "iso:country":"GB",
    "wof:name":"NR5 8EL",
    "wof:placetype":"postalcode"
},
  "geometry": {"coordinates":[1.23641341317101,52.63121137741474],"type":"Point"}
}