{
  "type": "Feature",
  "properties": {
    "date:inception_lower":"2013-04-01",
    "date:inception_upper":"2013-04-30",
    "iso:country":"GB",
    "wof:name":"NR5 8EL",
    "wof:placetype":"postalcode"
},
  "geometry": {"coordinates":[1.236413,52.631211],"type":"Point"}
}