{
  "type": "Feature",
  "properties": {
    "iso:country": "GB",
    "wof:name": "NR5 8EL",
    "wof:placetype": "postalcode"
  },
  "geometry": {"coordinates":[1.236413,52.631211],"type":"Point"}
}
