{
  "type": "Feature",
  "properties": {
    "iso:country":"GB",
    "wof:name":"EX39 2DR",
    "wof:placetype":"postalcode"
},
  "geometry": {"coordinates":[-4.20712949357517,51.01697897424863],"type":"Point"}
}