{
  "type": "Feature",
  "properties": {
    "iso:country":"GB",
    "wof:name":"AL4 0QJ",
    "wof:placetype":"postalcode"
},
  "geometry": {"coordinates":[-0.24610780826436,51.7403193909122],"type":"Point"}
}