{
  "type": "Feature",
  "properties": {
    "iso:country": "GB",
    "wof:name": "AL4 0QJ",
    "wof:placetype": "postalcode"
  },
  "geometry": {"coordinates":[-0.246108,51.740319],"type":"Point"}
}
