{
  "type": "Feature",
  "properties": {
    "iso:country":"GB",
    "wof:name":"RH20 4NR",
    "wof:placetype":"postalcode"
},
  "geometry": {"coordinates":[-0.45385483976046,50.92246047684702],"type":"Point"}
}