{
  "type": "Feature",
  "properties": {
    "iso:country":"GB",
    "wof:name":"EH6 5LA",
    "wof:placetype":"postalcode"
},
  "geometry": {"coordinates":[-3.17231155259712,55.97102687047552],"type":"Point"}
}