{
  "type": "Feature",
  "properties": {
    "iso:country": "GB",
    "wof:name": "NE11 9HL",
    "wof:placetype": "postalcode"
  },
  "geometry": {"coordinates":[-1.657505,54.953315],"type":"Point"}
}
