{
  "type": "Feature",
  "properties": {
    "iso:country":"GB",
    "wof:name":"NE11 9HL",
    "wof:placetype":"postalcode"
},
  "geometry": {"coordinates":[-1.65750474935967,54.95331532178995],"type":"Point"}
}