{
  "type": "Feature",
  "properties": {
    "iso:country": "GB",
    "wof:name": "TN20 6DE",
    "wof:placetype": "postalcode"
  },
  "geometry": {"coordinates":[0.260162,51.019132],"type":"Point"}
}
