{
  "type": "Feature",
  "properties": {
    "iso:country":"GB",
    "wof:name":"IV19 1PS",
    "wof:placetype":"postalcode"
},
  "geometry": {"coordinates":[-4.05809449752089,57.80765369475585],"type":"Point"}
}