{
  "type": "Feature",
  "properties": {
    "iso:country": "GB",
    "wof:name": "SO45 2NE",
    "wof:placetype": "postalcode"
  },
  "geometry": {"coordinates":[-1.383486,50.83206],"type":"Point"}
}
