{
  "type": "Feature",
  "properties": {
    "date:inception_lower":"1980-01-01",
    "date:inception_upper":"1980-01-31",
    "iso:country":"GB",
    "wof:name":"WA4 2JN",
    "wof:placetype":"postalcode"
},
  "geometry": {"coordinates":[-2.529697,53.380904],"type":"Point"}
}