{
  "type": "Feature",
  "properties": {
    "iso:country":"GB",
    "wof:name":"WA4 2JN",
    "wof:placetype":"postalcode"
},
  "geometry": {"coordinates":[-2.52969662876055,53.3809042081422],"type":"Point"}
}