{
  "type": "Feature",
  "properties": {
    "iso:country":"GB",
    "wof:name":"GL12 7HX",
    "wof:placetype":"postalcode"
},
  "geometry": {"coordinates":[-2.34216150590358,51.63713332908253],"type":"Point"}
}