{
  "type": "Feature",
  "properties": {
    "iso:country": "GB",
    "wof:name": "GL12 7HX",
    "wof:placetype": "postalcode"
  },
  "geometry": {"coordinates":[-2.342161,51.637133],"type":"Point"}
}
