{
  "type": "Feature",
  "properties": {
    "iso:country":"GB",
    "wof:name":"W1U 2NT",
    "wof:placetype":"postalcode"
},
  "geometry": {"coordinates":[-0.15097744644976,51.51748773532233],"type":"Point"}
}