{
  "type": "Feature",
  "properties": {
    "iso:country":"GB",
    "wof:name":"TQ6 9RF",
    "wof:placetype":"postalcode"
},
  "geometry": {"coordinates":[-3.57949541921197,50.34973460603847],"type":"Point"}
}