{
  "type": "Feature",
  "properties": {
    "iso:country":"GB",
    "wof:name":"G72 0XG",
    "wof:placetype":"postalcode"
},
  "geometry": {"coordinates":[-4.08503836235484,55.78385818574927],"type":"Point"}
}