{
  "type": "Feature",
  "properties": {
    "iso:country":"GB",
    "wof:name":"SY5 6DS",
    "wof:placetype":"postalcode"
},
  "geometry": {"coordinates":[-2.59995677967744,52.63171875879892],"type":"Point"}
}