{
  "type": "Feature",
  "properties": {
    "iso:country": "GB",
    "wof:name": "SY5 6DS",
    "wof:placetype": "postalcode"
  },
  "geometry": {"coordinates":[-2.599957,52.631719],"type":"Point"}
}
