{
  "type": "Feature",
  "properties": {
    "iso:country": "GB",
    "wof:name": "MK10 7EY",
    "wof:placetype": "postalcode"
  },
  "geometry": {"coordinates":[-0.686588,52.043818],"type":"Point"}
}
