{
  "type": "Feature",
  "properties": {
    "date:inception_lower":"2012-06-01",
    "date:inception_upper":"2012-06-30",
    "iso:country":"GB",
    "wof:name":"MK10 7EY",
    "wof:placetype":"postalcode"
},
  "geometry": {"coordinates":[-0.686588,52.043818],"type":"Point"}
}