{
  "type": "Feature",
  "properties": {
    "iso:country": "GB",
    "wof:name": "BS35 5RW",
    "wof:placetype": "postalcode"
  },
  "geometry": {"coordinates":[-2.617137,51.536879],"type":"Point"}
}
