{
  "type": "Feature",
  "properties": {
    "iso:country":"GB",
    "wof:name":"BS35 5RW",
    "wof:placetype":"postalcode"
},
  "geometry": {"coordinates":[-2.61713680162619,51.53687883051422],"type":"Point"}
}