{
  "type": "Feature",
  "properties": {
    "iso:country":"GB",
    "wof:name":"PE14 7NL",
    "wof:placetype":"postalcode"
},
  "geometry": {"coordinates":[0.21539715888785,52.73250788729028],"type":"Point"}
}