{
  "type": "Feature",
  "properties": {
    "iso:country": "GB",
    "wof:name": "PE14 7NL",
    "wof:placetype": "postalcode"
  },
  "geometry": {"coordinates":[0.215397,52.732508],"type":"Point"}
}
