{
  "type": "Feature",
  "properties": {
    "date:inception_lower":"1999-06-01",
    "date:inception_upper":"1999-06-30",
    "iso:country":"GB",
    "wof:name":"TS9 5LZ",
    "wof:placetype":"postalcode"
},
  "geometry": {"coordinates":[-1.244944,54.488606],"type":"Point"}
}