{
  "type": "Feature",
  "properties": {
    "iso:country": "GB",
    "wof:name": "TS9 5LZ",
    "wof:placetype": "postalcode"
  },
  "geometry": {"coordinates":[-1.244944,54.488606],"type":"Point"}
}
