{
  "type": "Feature",
  "properties": {
    "iso:country": "GB",
    "wof:name": "YO25 8JL",
    "wof:placetype": "postalcode"
  },
  "geometry": {"coordinates":[-0.188023,53.941089],"type":"Point"}
}
