{
  "type": "Feature",
  "properties": {
    "iso:country":"GB",
    "wof:name":"YO25 8JL",
    "wof:placetype":"postalcode"
},
  "geometry": {"coordinates":[-0.188022703489,53.94108858018712],"type":"Point"}
}