{
  "type": "Feature",
  "properties": {
    "iso:country": "GB",
    "wof:name": "AB21 0AU",
    "wof:placetype": "postalcode"
  },
  "geometry": {"coordinates":[-2.165765,57.262943],"type":"Point"}
}
