{
  "type": "Feature",
  "properties": {
    "date:inception_lower": "2008-01-01",
    "date:inception_upper": "2008-01-01",
    "iso:country": "GB",
    "wof:name": "AB21 0AU",
    "wof:placetype": "postalcode"
  },
  "geometry": {"coordinates":[-2.165765,57.262943],"type":"Point"}
}
