{
  "type": "Feature",
  "properties": {
    "date:inception_lower":"2006-03-01",
    "date:inception_upper":"2006-03-31",
    "iso:country":"GB",
    "wof:name":"YO8 6LE",
    "wof:placetype":"postalcode"
},
  "geometry": {"coordinates":[-0.993975,53.783279],"type":"Point"}
}