{
  "type": "Feature",
  "properties": {
    "iso:country": "GB",
    "wof:name": "YO8 6LE",
    "wof:placetype": "postalcode"
  },
  "geometry": {"coordinates":[-0.993975,53.783279],"type":"Point"}
}
