{
  "type": "Feature",
  "properties": {
    "iso:country": "GB",
    "wof:name": "MK41 8JL",
    "wof:placetype": "postalcode"
  },
  "geometry": {"coordinates":[-0.429422,52.155833],"type":"Point"}
}
