{
  "type": "Feature",
  "properties": {
    "iso:country":"GB",
    "wof:name":"MK41 8JL",
    "wof:placetype":"postalcode"
},
  "geometry": {"coordinates":[-0.42942189896131,52.15583251361339],"type":"Point"}
}