{
  "type": "Feature",
  "properties": {
    "iso:country":"GB",
    "wof:name":"G31 2NY",
    "wof:placetype":"postalcode"
},
  "geometry": {"coordinates":[-4.21791418319154,55.86279599045867],"type":"Point"}
}