{
  "type": "Feature",
  "properties": {
    "iso:country":"GB",
    "wof:name":"NE32 4TJ",
    "wof:placetype":"postalcode"
},
  "geometry": {"coordinates":[-1.49426596429257,54.9551546747421],"type":"Point"}
}