{
  "type": "Feature",
  "properties": {
    "iso:country":"GB",
    "wof:name":"SS7 2PG",
    "wof:placetype":"postalcode"
},
  "geometry": {"coordinates":[0.60387086991671,51.55476939615276],"type":"Point"}
}