{
  "type": "Feature",
  "properties": {
    "iso:country":"GB",
    "wof:name":"SK17 6TD",
    "wof:placetype":"postalcode"
},
  "geometry": {"coordinates":[-1.9226656990342,53.2616612052166],"type":"Point"}
}