{
  "type": "Feature",
  "properties": {
    "iso:country":"GB",
    "wof:name":"EN9 3EL",
    "wof:placetype":"postalcode"
},
  "geometry": {"coordinates":[0.02169303317115,51.68645976581965],"type":"Point"}
}