{
  "type": "Feature",
  "properties": {
    "date:inception_lower": "1980-01-01",
    "date:inception_upper": "1980-01-01",
    "iso:country": "GB",
    "wof:name": "HP22 5QL",
    "wof:placetype": "postalcode"
  },
  "geometry": {"coordinates":[-0.727097,51.766139],"type":"Point"}
}
