{
  "type": "Feature",
  "properties": {
    "iso:country": "GB",
    "wof:name": "HP22 5QL",
    "wof:placetype": "postalcode"
  },
  "geometry": {"coordinates":[-0.727122,51.766133],"type":"Point"}
}
