{
  "type": "Feature",
  "properties": {
    "iso:country": "GB",
    "wof:name": "SA16 0DX",
    "wof:placetype": "postalcode"
  },
  "geometry": {"coordinates":[-4.256563,51.689887],"type":"Point"}
}
