{
  "type": "Feature",
  "properties": {
    "date:inception_lower": "1980-01-01",
    "date:inception_upper": "1980-01-01",
    "iso:country": "GB",
    "wof:name": "S43 4EJ",
    "wof:placetype": "postalcode"
  },
  "geometry": {"coordinates":[-1.28026,53.286512],"type":"Point"}
}
