{
  "type": "Feature",
  "properties": {
    "iso:country": "GB",
    "wof:name": "NR33 9DB",
    "wof:placetype": "postalcode"
  },
  "geometry": {"coordinates":[1.726907,52.463724],"type":"Point"}
}
