{
  "type": "Feature",
  "properties": {
    "iso:country":"GB",
    "wof:name":"BH23 3PL",
    "wof:placetype":"postalcode"
},
  "geometry": {"coordinates":[-1.75651048435567,50.7364127553147],"type":"Point"}
}