{
  "type": "Feature",
  "properties": {
    "date:inception_lower": "1980-01-01",
    "date:inception_upper": "1980-01-01",
    "iso:country": "GB",
    "wof:name": "BH23 3PL",
    "wof:placetype": "postalcode"
  },
  "geometry": {"coordinates":[-1.75651,50.736413],"type":"Point"}
}
