{
  "type": "Feature",
  "properties": {
    "iso:country": "GB",
    "wof:name": "W1J 6HE",
    "wof:placetype": "postalcode"
  },
  "geometry": {"coordinates":[-0.145862,51.510708],"type":"Point"}
}
