{
  "type": "Feature",
  "properties": {
    "date:inception_lower": "1980-01-01",
    "date:inception_upper": "1980-01-01",
    "iso:country": "GB",
    "wof:name": "WN5 7NR",
    "wof:placetype": "postalcode"
  },
  "geometry": {"coordinates":[-2.704255,53.495093],"type":"Point"}
}
