{
  "type": "Feature",
  "properties": {
    "date:inception_lower": "1980-01-01",
    "date:inception_upper": "1980-01-01",
    "iso:country": "GB",
    "wof:name": "CO4 3XD",
    "wof:placetype": "postalcode"
  },
  "geometry": {"coordinates":[0.930261,51.88744],"type":"Point"}
}
