{
  "type": "Feature",
  "properties": {
    "iso:country": "GB",
    "wof:name": "CO4 3XD",
    "wof:placetype": "postalcode"
  },
  "geometry": {"coordinates":[0.930261,51.88744],"type":"Point"}
}
