{
  "type": "Feature",
  "properties": {
    "iso:country": "GB",
    "wof:name": "CM3 1FA",
    "wof:placetype": "postalcode"
  },
  "geometry": {"coordinates":[0.513047,51.834594],"type":"Point"}
}
