{
  "type": "Feature",
  "properties": {
    "date:inception_lower": "2004-05-01",
    "date:inception_upper": "2004-05-01",
    "iso:country": "GB",
    "wof:name": "TF3 4EA",
    "wof:placetype": "postalcode"
  },
  "geometry": {"coordinates":[-2.442529,52.671319],"type":"Point"}
}
