{
  "type": "Feature",
  "properties": {
    "iso:country":"GB",
    "wof:name":"TF3 4EA",
    "wof:placetype":"postalcode"
},
  "geometry": {"coordinates":[-2.44252864353328,52.67131937791353],"type":"Point"}
}