{
  "type": "Feature",
  "properties": {
    "iso:country":"GB",
    "wof:name":"HX6 4BU",
    "wof:placetype":"postalcode"
},
  "geometry": {"coordinates":[-1.94836503719849,53.66967915563681],"type":"Point"}
}