{
  "type": "Feature",
  "properties": {
    "date:inception_lower":"1980-01-01",
    "date:inception_upper":"1980-01-31",
    "iso:country":"GB",
    "wof:name":"KW15 1RE",
    "wof:placetype":"postalcode"
},
  "geometry": {"coordinates":[-2.977619,58.98941],"type":"Point"}
}