{
  "type": "Feature",
  "properties": {
    "iso:country":"GB",
    "wof:name":"KW15 1RE",
    "wof:placetype":"postalcode"
},
  "geometry": {"coordinates":[-2.97430653964159,58.98755603574089],"type":"Point"}
}