{
  "type": "Feature",
  "properties": {
    "date:inception_lower": "1980-01-01",
    "date:inception_upper": "1980-01-01",
    "iso:country": "GB",
    "wof:name": "ML9 1JZ",
    "wof:placetype": "postalcode"
  },
  "geometry": {"coordinates":[-3.976073,55.726066],"type":"Point"}
}
