{
  "type": "Feature",
  "properties": {
    "iso:country":"GB",
    "wof:name":"S80 4TR",
    "wof:placetype":"postalcode"
},
  "geometry": {"coordinates":[-1.1984146423057,53.28277835932126],"type":"Point"}
}