{
  "type": "Feature",
  "properties": {
    "iso:country":"GB",
    "wof:name":"CA6 6BZ",
    "wof:placetype":"postalcode"
},
  "geometry": {"coordinates":[-2.89468458745116,54.98209134742824],"type":"Point"}
}