{
  "type": "Feature",
  "properties": {
    "date:inception_lower":"1980-01-01",
    "date:inception_upper":"1980-01-31",
    "iso:country":"GB",
    "wof:name":"SY17 5QU",
    "wof:placetype":"postalcode"
},
  "geometry": {"coordinates":[-3.502045,52.522192],"type":"Point"}
}