{
  "type": "Feature",
  "properties": {
    "date:inception_lower": "2018-09-01",
    "date:inception_upper": "2018-09-01",
    "iso:country": "GB",
    "wof:name": "YO25 9FD",
    "wof:placetype": "postalcode"
  },
  "geometry": {"coordinates":[-0.666901,54.021729],"type":"Point"}
}
