{
  "type": "Feature",
  "properties": {
    "iso:country": "GB",
    "wof:name": "TR12 6BW",
    "wof:placetype": "postalcode"
  },
  "geometry": {"coordinates":[-5.166818,50.072798],"type":"Point"}
}
