{
  "type": "Feature",
  "properties": {
    "iso:country": "GB",
    "wof:name": "LS29 9HU",
    "wof:placetype": "postalcode"
  },
  "geometry": {"coordinates":[-1.821213,53.923635],"type":"Point"}
}
