{
  "type": "Feature",
  "properties": {
    "iso:country":"GB",
    "wof:name":"DH7 8JT",
    "wof:placetype":"postalcode"
},
  "geometry": {"coordinates":[-1.60614699579499,54.76161401316929],"type":"Point"}
}