{
  "type": "Feature",
  "properties": {
    "iso:country":"GB",
    "wof:name":"NE63 9RW",
    "wof:placetype":"postalcode"
},
  "geometry": {"coordinates":[-1.54605144531571,55.17332708989355],"type":"Point"}
}