{
  "type": "Feature",
  "properties": {
    "iso:country":"GB",
    "wof:name":"KT9 1AL",
    "wof:placetype":"postalcode"
},
  "geometry": {"coordinates":[-0.30161317856179,51.36961900140741],"type":"Point"}
}