{
  "type": "Feature",
  "properties": {
    "iso:country": "GB",
    "wof:name": "DG5 4DJ",
    "wof:placetype": "postalcode"
  },
  "geometry": {"coordinates":[-3.819766,54.927617],"type":"Point"}
}
