{
  "type": "Feature",
  "properties": {
    "iso:country":"GB",
    "wof:name":"DG5 4DJ",
    "wof:placetype":"postalcode"
},
  "geometry": {"coordinates":[-3.81976592896804,54.92761749544266],"type":"Point"}
}