{
  "type": "Feature",
  "properties": {
    "iso:country": "GB",
    "wof:name": "IP33 3WD",
    "wof:placetype": "postalcode"
  },
  "geometry": {"coordinates":[0.667545,52.242782],"type":"Point"}
}
