{
  "type": "Feature",
  "properties": {
    "iso:country":"GB",
    "wof:name":"NP15 1HH",
    "wof:placetype":"postalcode"
},
  "geometry": {"coordinates":[-2.82986679093853,51.69000464837746],"type":"Point"}
}