{
  "type": "Feature",
  "properties": {
    "iso:country": "GB",
    "wof:name": "NP15 1HH",
    "wof:placetype": "postalcode"
  },
  "geometry": {"coordinates":[-2.829867,51.690005],"type":"Point"}
}
