{
  "type": "Feature",
  "properties": {
    "iso:country":"GB",
    "wof:name":"HP3 0LT",
    "wof:placetype":"postalcode"
},
  "geometry": {"coordinates":[-0.52993408488728,51.72418764671475],"type":"Point"}
}