{
  "type": "Feature",
  "properties": {
    "iso:country":"GB",
    "wof:name":"YO32 5SX",
    "wof:placetype":"postalcode"
},
  "geometry": {"coordinates":[-1.0243220553763,54.04490565954342],"type":"Point"}
}