{
  "type": "Feature",
  "properties": {
    "iso:country": "GB",
    "wof:name": "YO32 5SX",
    "wof:placetype": "postalcode"
  },
  "geometry": {"coordinates":[-1.024377,54.044941],"type":"Point"}
}
