{
  "type": "Feature",
  "properties": {
    "iso:country": "GB",
    "wof:name": "M29 7ER",
    "wof:placetype": "postalcode"
  },
  "geometry": {"coordinates":[-2.449582,53.503244],"type":"Point"}
}
