{
  "type": "Feature",
  "properties": {
    "iso:country":"GB",
    "wof:name":"M29 7ER",
    "wof:placetype":"postalcode"
},
  "geometry": {"coordinates":[-2.44958236910143,53.50324384496948],"type":"Point"}
}