{
  "type": "Feature",
  "properties": {
    "date:inception_lower": "1991-09-01",
    "date:inception_upper": "1991-09-01",
    "iso:country": "GB",
    "wof:name": "LL30 3LE",
    "wof:placetype": "postalcode"
  },
  "geometry": {"coordinates":[-3.775474,53.312254],"type":"Point"}
}
