{
  "type": "Feature",
  "properties": {
    "iso:country": "GB",
    "wof:name": "LL30 3LE",
    "wof:placetype": "postalcode"
  },
  "geometry": {"coordinates":[-3.775474,53.312254],"type":"Point"}
}
