{
  "type": "Feature",
  "properties": {
    "iso:country": "GB",
    "wof:name": "SE1 7RA",
    "wof:placetype": "postalcode"
  },
  "geometry": {"coordinates":[-0.112473,51.501337],"type":"Point"}
}
