{
  "type": "Feature",
  "properties": {
    "date:inception_lower":"1999-12-01",
    "date:inception_upper":"1999-12-31",
    "iso:country":"GB",
    "wof:name":"SE1 7RA",
    "wof:placetype":"postalcode"
},
  "geometry": {"coordinates":[-0.112473,51.501337],"type":"Point"}
}