{
  "type": "Feature",
  "properties": {
    "iso:country": "GB",
    "wof:name": "SA5 4RN",
    "wof:placetype": "postalcode"
  },
  "geometry": {"coordinates":[-4.00615,51.635487],"type":"Point"}
}
