{
  "type": "Feature",
  "properties": {
    "iso:country":"GB",
    "wof:name":"SA5 4RN",
    "wof:placetype":"postalcode"
},
  "geometry": {"coordinates":[-4.00615024336045,51.63548705890062],"type":"Point"}
}