{
  "type": "Feature",
  "properties": {
    "date:inception_lower": "2017-11-01",
    "date:inception_upper": "2017-11-01",
    "iso:country": "GB",
    "wof:name": "KY11 8QD",
    "wof:placetype": "postalcode"
  },
  "geometry": {"coordinates":[-3.40334,56.072194],"type":"Point"}
}
