{
  "type": "Feature",
  "properties": {
    "iso:country":"GB",
    "wof:name":"SA44 5YN",
    "wof:placetype":"postalcode"
},
  "geometry": {"coordinates":[-4.40452177211619,52.02419782813499],"type":"Point"}
}