{
  "type": "Feature",
  "properties": {
    "iso:country": "GB",
    "wof:name": "EX16 7HY",
    "wof:placetype": "postalcode"
  },
  "geometry": {"coordinates":[-3.338903,50.94595],"type":"Point"}
}
