{
  "type": "Feature",
  "properties": {
    "iso:country":"GB",
    "wof:name":"EX16 7HY",
    "wof:placetype":"postalcode"
},
  "geometry": {"coordinates":[-3.33890318899352,50.94594986948614],"type":"Point"}
}