{
  "type": "Feature",
  "properties": {
    "iso:country":"GB",
    "wof:name":"YO60 7HL",
    "wof:placetype":"postalcode"
},
  "geometry": {"coordinates":[-0.84620143900734,54.10547273751296],"type":"Point"}
}