{
  "type": "Feature",
  "properties": {
    "iso:country": "GB",
    "wof:name": "YO60 7HL",
    "wof:placetype": "postalcode"
  },
  "geometry": {"coordinates":[-0.846201,54.105473],"type":"Point"}
}
