{
  "type": "Feature",
  "properties": {
    "date:inception_lower": "1997-12-01",
    "date:inception_upper": "1997-12-01",
    "iso:country": "GB",
    "wof:name": "SE12 0US",
    "wof:placetype": "postalcode"
  },
  "geometry": {"coordinates":[0.020417,51.439401],"type":"Point"}
}
