{
  "type": "Feature",
  "properties": {
    "iso:country":"GB",
    "wof:name":"SE12 0US",
    "wof:placetype":"postalcode"
},
  "geometry": {"coordinates":[0.02044856358092,51.4394176155527],"type":"Point"}
}