{
  "type": "Feature",
  "properties": {
    "iso:country":"GB",
    "wof:name":"L31 3EP",
    "wof:placetype":"postalcode"
},
  "geometry": {"coordinates":[-2.93407411326106,53.51101854503677],"type":"Point"}
}