{
  "type": "Feature",
  "properties": {
    "date:inception_lower": "1980-01-01",
    "date:inception_upper": "1980-01-01",
    "iso:country": "GB",
    "wof:name": "L32 0UN",
    "wof:placetype": "postalcode"
  },
  "geometry": {"coordinates":[-2.899676,53.482465],"type":"Point"}
}
