{
  "type": "Feature",
  "properties": {
    "iso:country":"GB",
    "wof:name":"L32 0UN",
    "wof:placetype":"postalcode"
},
  "geometry": {"coordinates":[-2.8996759056384,53.48246456126722],"type":"Point"}
}