{
  "type": "Feature",
  "properties": {
    "iso:country": "GB",
    "wof:name": "RM10 8UT",
    "wof:placetype": "postalcode"
  },
  "geometry": {"coordinates":[0.169105,51.542311],"type":"Point"}
}
