{
  "type": "Feature",
  "properties": {
    "iso:country":"GB",
    "wof:name":"RM10 8UT",
    "wof:placetype":"postalcode"
},
  "geometry": {"coordinates":[0.1691045875342,51.54231062174885],"type":"Point"}
}