{
  "type": "Feature",
  "properties": {
    "iso:country":"GB",
    "wof:name":"DA16 1JD",
    "wof:placetype":"postalcode"
},
  "geometry": {"coordinates":[0.12324901106088,51.46339208157221],"type":"Point"}
}