{
  "type": "Feature",
  "properties": {
    "iso:country": "GB",
    "wof:name": "NE33 2ES",
    "wof:placetype": "postalcode"
  },
  "geometry": {"coordinates":[-1.427121,55.00235],"type":"Point"}
}
