{
  "type": "Feature",
  "properties": {
    "iso:country":"GB",
    "wof:name":"RH15 0RU",
    "wof:placetype":"postalcode"
},
  "geometry": {"coordinates":[-0.11419685894373,50.94809969551028],"type":"Point"}
}