{
  "type": "Feature",
  "properties": {
    "iso:country": "GB",
    "wof:name": "RH15 0RU",
    "wof:placetype": "postalcode"
  },
  "geometry": {"coordinates":[-0.114197,50.9481],"type":"Point"}
}
