{
  "type": "Feature",
  "properties": {
    "date:inception_lower": "1980-01-01",
    "date:inception_upper": "1980-01-01",
    "iso:country": "GB",
    "wof:name": "RH15 0RU",
    "wof:placetype": "postalcode"
  },
  "geometry": {"coordinates":[-0.114197,50.9481],"type":"Point"}
}
