{
  "type": "Feature",
  "properties": {
    "iso:country":"GB",
    "wof:name":"EH32 9SD",
    "wof:placetype":"postalcode"
},
  "geometry": {"coordinates":[-2.9713046342326,55.96764449643748],"type":"Point"}
}