{
  "type": "Feature",
  "properties": {
    "iso:country": "GB",
    "wof:name": "AL3 5LB",
    "wof:placetype": "postalcode"
  },
  "geometry": {"coordinates":[-0.341443,51.757041],"type":"Point"}
}
