{
  "type": "Feature",
  "properties": {
    "iso:country":"GB",
    "wof:name":"E2 6AY",
    "wof:placetype":"postalcode"
},
  "geometry": {"coordinates":[-0.06737941356995,51.5277045191604],"type":"Point"}
}