{
  "type": "Feature",
  "properties": {
    "iso:country": "GB",
    "wof:name": "DG2 0AX",
    "wof:placetype": "postalcode"
  },
  "geometry": {"coordinates":[-3.620697,55.073587],"type":"Point"}
}
