{
  "type": "Feature",
  "properties": {
    "date:inception_lower": "1997-12-01",
    "date:inception_upper": "1997-12-01",
    "iso:country": "GB",
    "wof:name": "TN24 9LE",
    "wof:placetype": "postalcode"
  },
  "geometry": {"coordinates":[0.879171,51.173312],"type":"Point"}
}
