{
  "type": "Feature",
  "properties": {
    "iso:country": "GB",
    "wof:name": "TN24 9LE",
    "wof:placetype": "postalcode"
  },
  "geometry": {"coordinates":[0.879171,51.173312],"type":"Point"}
}
