{
  "type": "Feature",
  "properties": {
    "iso:country":"GB",
    "wof:name":"HU9 2JP",
    "wof:placetype":"postalcode"
},
  "geometry": {"coordinates":[-0.30878831484227,53.75351302379065],"type":"Point"}
}