{
  "type": "Feature",
  "properties": {
    "iso:country":"GB",
    "wof:name":"HP2 6NL",
    "wof:placetype":"postalcode"
},
  "geometry": {"coordinates":[-0.46556637315658,51.77495990208655],"type":"Point"}
}