{
  "type": "Feature",
  "properties": {
    "iso:country":"GB",
    "wof:name":"CB22 5LQ",
    "wof:placetype":"postalcode"
},
  "geometry": {"coordinates":[0.13620936249886,52.15309379334462],"type":"Point"}
}