{
  "type": "Feature",
  "properties": {
    "iso:country":"GB",
    "wof:name":"PE23 5EL",
    "wof:placetype":"postalcode"
},
  "geometry": {"coordinates":[0.09032471313757,53.17541242748045],"type":"Point"}
}