{
  "type": "Feature",
  "properties": {
    "iso:country": "GB",
    "wof:name": "NP4 7JF",
    "wof:placetype": "postalcode"
  },
  "geometry": {"coordinates":[-3.070079,51.733454],"type":"Point"}
}
