{
  "type": "Feature",
  "properties": {
    "date:inception_lower":"1980-01-01",
    "date:inception_upper":"1980-01-31",
    "iso:country":"GB",
    "wof:name":"FK15 0HB",
    "wof:placetype":"postalcode"
},
  "geometry": {"coordinates":[-3.95603,56.189121],"type":"Point"}
}