{
  "type": "Feature",
  "properties": {
    "iso:country": "GB",
    "wof:name": "FK15 0HB",
    "wof:placetype": "postalcode"
  },
  "geometry": {"coordinates":[-3.95603,56.189121],"type":"Point"}
}
