{
  "type": "Feature",
  "properties": {
    "iso:country":"GB",
    "wof:name":"FK15 0HB",
    "wof:placetype":"postalcode"
},
  "geometry": {"coordinates":[-3.95603010155798,56.18912057318256],"type":"Point"}
}