{
  "type": "Feature",
  "properties": {
    "date:inception_lower": "1980-01-01",
    "date:inception_upper": "1980-01-01",
    "iso:country": "GB",
    "wof:name": "FK15 0HB",
    "wof:placetype": "postalcode"
  },
  "geometry": {"coordinates":[-3.956777,56.188419],"type":"Point"}
}
