{
  "type": "Feature",
  "properties": {
    "date:inception_lower": "1993-08-01",
    "date:inception_upper": "1993-08-01",
    "iso:country": "GB",
    "wof:name": "NN3 9DH",
    "wof:placetype": "postalcode"
  },
  "geometry": {"coordinates":[-0.832941,52.250028],"type":"Point"}
}
