{
  "type": "Feature",
  "properties": {
    "iso:country":"GB",
    "wof:name":"NN3 9DH",
    "wof:placetype":"postalcode"
},
  "geometry": {"coordinates":[-0.832941230094,52.25002757828592],"type":"Point"}
}