{
  "type": "Feature",
  "properties": {
    "iso:country":"GB",
    "wof:name":"SG1 3AQ",
    "wof:placetype":"postalcode"
},
  "geometry": {"coordinates":[-0.20788191830476,51.91113011006522],"type":"Point"}
}