{
  "type": "Feature",
  "properties": {
    "iso:country": "GB",
    "wof:name": "LE4 4GF",
    "wof:placetype": "postalcode"
  },
  "geometry": {"coordinates":[-1.118054,52.681201],"type":"Point"}
}
