{
  "type": "Feature",
  "properties": {
    "iso:country":"GB",
    "wof:name":"LE4 4GF",
    "wof:placetype":"postalcode"
},
  "geometry": {"coordinates":[-1.11805413388523,52.68120138227057],"type":"Point"}
}