{
  "type": "Feature",
  "properties": {
    "iso:country":"GB",
    "wof:name":"HX1 1HX",
    "wof:placetype":"postalcode"
},
  "geometry": {"coordinates":[-1.86277999894384,53.72354055882537],"type":"Point"}
}