{
  "type": "Feature",
  "properties": {
    "date:inception_lower": "1998-06-01",
    "date:inception_upper": "1998-06-01",
    "iso:country": "GB",
    "wof:name": "NE71 6QQ",
    "wof:placetype": "postalcode"
  },
  "geometry": {"coordinates":[-1.998657,55.546104],"type":"Point"}
}
