{
  "type": "Feature",
  "properties": {
    "iso:country": "GB",
    "wof:name": "NE71 6QQ",
    "wof:placetype": "postalcode"
  },
  "geometry": {"coordinates":[-1.998657,55.546104],"type":"Point"}
}
