{
  "type": "Feature",
  "properties": {
    "date:inception_lower":"1980-01-01",
    "date:inception_upper":"1980-01-31",
    "iso:country":"GB",
    "wof:name":"DA8 1QB",
    "wof:placetype":"postalcode"
},
  "geometry": {"coordinates":[0.160711,51.484147],"type":"Point"}
}