{
  "type": "Feature",
  "properties": {
    "iso:country":"GB",
    "wof:name":"PO5 2LU",
    "wof:placetype":"postalcode"
},
  "geometry": {"coordinates":[-1.08385396274598,50.78349243154737],"type":"Point"}
}