{
  "type": "Feature",
  "properties": {
    "iso:country":"GB",
    "wof:name":"SE3 9RT",
    "wof:placetype":"postalcode"
},
  "geometry": {"coordinates":[0.00941833151932,51.46250282593603],"type":"Point"}
}