{
  "type": "Feature",
  "properties": {
    "iso:country": "GB",
    "wof:name": "TS24 0NG",
    "wof:placetype": "postalcode"
  },
  "geometry": {"coordinates":[-1.183883,54.700402],"type":"Point"}
}
