{
  "type": "Feature",
  "properties": {
    "iso:country":"GB",
    "wof:name":"TS24 0NG",
    "wof:placetype":"postalcode"
},
  "geometry": {"coordinates":[-1.18388286516895,54.70040235916291],"type":"Point"}
}