{
  "type": "Feature",
  "properties": {
    "iso:country":"GB",
    "wof:name":"SE21 7LF",
    "wof:placetype":"postalcode"
},
  "geometry": {"coordinates":[-0.08309714472655,51.44004164983235],"type":"Point"}
}