{
  "type": "Feature",
  "properties": {
    "iso:country":"GB",
    "wof:name":"DN21 2JZ",
    "wof:placetype":"postalcode"
},
  "geometry": {"coordinates":[-0.77751908362146,53.40364527350324],"type":"Point"}
}