{
  "type": "Feature",
  "properties": {
    "iso:country":"GB",
    "wof:name":"CB1 3DT",
    "wof:placetype":"postalcode"
},
  "geometry": {"coordinates":[0.15281982313509,52.20011656366864],"type":"Point"}
}