{
  "type": "Feature",
  "properties": {
    "date:inception_lower": "1980-01-01",
    "date:inception_upper": "1980-01-01",
    "iso:country": "GB",
    "wof:name": "LS9 9BJ",
    "wof:placetype": "postalcode"
  },
  "geometry": {"coordinates":[-1.498502,53.79461],"type":"Point"}
}
