{
  "type": "Feature",
  "properties": {
    "date:inception_lower": "1980-01-01",
    "date:inception_upper": "1980-01-01",
    "iso:country": "GB",
    "wof:name": "CF44 0HY",
    "wof:placetype": "postalcode"
  },
  "geometry": {"coordinates":[-3.420232,51.710614],"type":"Point"}
}
