{
  "type": "Feature",
  "properties": {
    "iso:country":"GB",
    "wof:name":"CF44 0HY",
    "wof:placetype":"postalcode"
},
  "geometry": {"coordinates":[-3.42023226967399,51.71061405140444],"type":"Point"}
}