{
  "type": "Feature",
  "properties": {
    "iso:country": "GB",
    "wof:name": "OX27 8AT",
    "wof:placetype": "postalcode"
  },
  "geometry": {"coordinates":[-1.15744,51.918393],"type":"Point"}
}
