{
  "type": "Feature",
  "properties": {
    "date:inception_lower":"1993-01-01",
    "date:inception_upper":"1993-01-31",
    "iso:country":"GB",
    "wof:name":"LE15 8BS",
    "wof:placetype":"postalcode"
},
  "geometry": {"coordinates":[-0.629308,52.686546],"type":"Point"}
}