{
  "type": "Feature",
  "properties": {
    "iso:country":"GB",
    "wof:name":"PE8 5QB",
    "wof:placetype":"postalcode"
},
  "geometry": {"coordinates":[-0.45569549107656,52.45036654709651],"type":"Point"}
}