{
  "type": "Feature",
  "properties": {
    "iso:country":"GB",
    "wof:name":"WA9 5UX",
    "wof:placetype":"postalcode"
},
  "geometry": {"coordinates":[-2.7540003267308,53.43061919155996],"type":"Point"}
}