{
  "type": "Feature",
  "properties": {
    "date:inception_lower": "1980-01-01",
    "date:inception_upper": "1980-01-01",
    "iso:country": "GB",
    "wof:name": "DN22 0LE",
    "wof:placetype": "postalcode"
  },
  "geometry": {"coordinates":[-0.84519,53.280322],"type":"Point"}
}
