{
  "type": "Feature",
  "properties": {
    "iso:country":"GB",
    "wof:name":"DN22 0LE",
    "wof:placetype":"postalcode"
},
  "geometry": {"coordinates":[-0.84518989067687,53.28032221647441],"type":"Point"}
}