{
  "type": "Feature",
  "properties": {
    "iso:country":"GB",
    "wof:name":"NR11 6SJ",
    "wof:placetype":"postalcode"
},
  "geometry": {"coordinates":[1.07833440652732,52.79601646099973],"type":"Point"}
}