{
  "type": "Feature",
  "properties": {
    "iso:country": "GB",
    "wof:name": "NR11 6SJ",
    "wof:placetype": "postalcode"
  },
  "geometry": {"coordinates":[1.078334,52.796016],"type":"Point"}
}
