{
  "type": "Feature",
  "properties": {
    "iso:country": "GB",
    "wof:name": "AB54 6DE",
    "wof:placetype": "postalcode"
  },
  "geometry": {"coordinates":[-2.613936,57.4716],"type":"Point"}
}
