{
  "type": "Feature",
  "properties": {
    "iso:country": "GB",
    "wof:name": "MK41 7TF",
    "wof:placetype": "postalcode"
  },
  "geometry": {"coordinates":[-0.469654,52.143819],"type":"Point"}
}
