{
  "type": "Feature",
  "properties": {
    "iso:country":"GB",
    "wof:name":"MK41 7TF",
    "wof:placetype":"postalcode"
},
  "geometry": {"coordinates":[-0.46965391786294,52.14381854796414],"type":"Point"}
}