{
  "type": "Feature",
  "properties": {
    "date:inception_lower": "1998-06-01",
    "date:inception_upper": "1998-06-01",
    "iso:country": "GB",
    "wof:name": "EN7 6WY",
    "wof:placetype": "postalcode"
  },
  "geometry": {"coordinates":[-0.092288,51.726161],"type":"Point"}
}
