{
  "type": "Feature",
  "properties": {
    "iso:country":"GB",
    "wof:name":"EN7 6WY",
    "wof:placetype":"postalcode"
},
  "geometry": {"coordinates":[-0.09228840025409,51.72616102867872],"type":"Point"}
}