{
  "type": "Feature",
  "properties": {
    "iso:country":"GB",
    "wof:name":"DY8 3BZ",
    "wof:placetype":"postalcode"
},
  "geometry": {"coordinates":[-2.16358571724562,52.44446417868348],"type":"Point"}
}