{
  "type": "Feature",
  "properties": {
    "iso:country":"GB",
    "wof:name":"B49 5DH",
    "wof:placetype":"postalcode"
},
  "geometry": {"coordinates":[-1.8746050609309,52.21655616901722],"type":"Point"}
}