{
  "type": "Feature",
  "properties": {
    "date:inception_lower":"2008-06-01",
    "date:inception_upper":"2008-06-30",
    "iso:country":"GB",
    "wof:name":"B49 5DH",
    "wof:placetype":"postalcode"
},
  "geometry": {"coordinates":[-1.874605,52.216556],"type":"Point"}
}