{
  "type": "Feature",
  "properties": {
    "iso:country": "GB",
    "wof:name": "B49 5DH",
    "wof:placetype": "postalcode"
  },
  "geometry": {"coordinates":[-1.874605,52.216556],"type":"Point"}
}
