{
  "type": "Feature",
  "properties": {
    "date:inception_lower": "1980-01-01",
    "date:inception_upper": "1980-01-01",
    "iso:country": "GB",
    "wof:name": "BD22 8AX",
    "wof:placetype": "postalcode"
  },
  "geometry": {"coordinates":[-1.953811,53.82557],"type":"Point"}
}
