{
  "type": "Feature",
  "properties": {
    "date:inception_lower": "1980-01-01",
    "date:inception_upper": "1980-01-01",
    "iso:country": "GB",
    "wof:name": "BN13 1NH",
    "wof:placetype": "postalcode"
  },
  "geometry": {"coordinates":[-0.393884,50.828232],"type":"Point"}
}
