{
  "type": "Feature",
  "properties": {
    "iso:country":"GB",
    "wof:name":"BN13 1NH",
    "wof:placetype":"postalcode"
},
  "geometry": {"coordinates":[-0.39388203314106,50.82821213436097],"type":"Point"}
}