{
  "type": "Feature",
  "properties": {
    "iso:country":"GB",
    "wof:name":"PA23 7QJ",
    "wof:placetype":"postalcode"
},
  "geometry": {"coordinates":[-4.93564963192515,55.9380363428606],"type":"Point"}
}