{
  "type": "Feature",
  "properties": {
    "date:inception_lower": "1980-01-01",
    "date:inception_upper": "1980-01-01",
    "iso:country": "GB",
    "wof:name": "PA23 7QJ",
    "wof:placetype": "postalcode"
  },
  "geometry": {"coordinates":[-4.93565,55.938036],"type":"Point"}
}
