{
  "type": "Feature",
  "properties": {
    "iso:country": "GB",
    "wof:name": "PA23 7QJ",
    "wof:placetype": "postalcode"
  },
  "geometry": {"coordinates":[-4.93565,55.938036],"type":"Point"}
}
