{
  "type": "Feature",
  "properties": {
    "iso:country":"GB",
    "wof:name":"E3 4HB",
    "wof:placetype":"postalcode"
},
  "geometry": {"coordinates":[-0.02033186180955,51.52417715981279],"type":"Point"}
}