{
  "type": "Feature",
  "properties": {
    "iso:country":"GB",
    "wof:name":"S35 8RQ",
    "wof:placetype":"postalcode"
},
  "geometry": {"coordinates":[-1.48240081006227,53.44794292767227],"type":"Point"}
}