{
  "type": "Feature",
  "properties": {
    "iso:country":"GB",
    "wof:name":"DL2 3HX",
    "wof:placetype":"postalcode"
},
  "geometry": {"coordinates":[-1.75427001369626,54.57767851237947],"type":"Point"}
}