{
  "type": "Feature",
  "properties": {
    "iso:country": "GB",
    "wof:name": "DL2 3HX",
    "wof:placetype": "postalcode"
  },
  "geometry": {"coordinates":[-1.75427,54.577679],"type":"Point"}
}
