{
  "type": "Feature",
  "properties": {
    "iso:country":"GB",
    "wof:name":"PL32 9XF",
    "wof:placetype":"postalcode"
},
  "geometry": {"coordinates":[-4.65383695331771,50.63350250112163],"type":"Point"}
}