{
  "type": "Feature",
  "properties": {
    "iso:country":"GB",
    "wof:name":"KY14 6EH",
    "wof:placetype":"postalcode"
},
  "geometry": {"coordinates":[-3.25163964103418,56.35117660473211],"type":"Point"}
}