{
  "type": "Feature",
  "properties": {
    "iso:country": "GB",
    "wof:name": "PE30 4NX",
    "wof:placetype": "postalcode"
  },
  "geometry": {"coordinates":[0.423327,52.752178],"type":"Point"}
}
