{
  "type": "Feature",
  "properties": {
    "iso:country":"GB",
    "wof:name":"HG5 0QY",
    "wof:placetype":"postalcode"
},
  "geometry": {"coordinates":[-1.39381516571604,54.05118160451187],"type":"Point"}
}