{
  "type": "Feature",
  "properties": {
    "iso:country":"GB",
    "wof:name":"DG1 2PB",
    "wof:placetype":"postalcode"
},
  "geometry": {"coordinates":[-3.61146272369738,55.06792148417225],"type":"Point"}
}