{
  "type": "Feature",
  "properties": {
    "iso:country":"GB",
    "wof:name":"LN5 0JF",
    "wof:placetype":"postalcode"
},
  "geometry": {"coordinates":[-0.53664763073969,53.09748310796599],"type":"Point"}
}