{
  "type": "Feature",
  "properties": {
    "iso:country": "GB",
    "wof:name": "LN5 0JF",
    "wof:placetype": "postalcode"
  },
  "geometry": {"coordinates":[-0.536648,53.097483],"type":"Point"}
}
