{
  "type": "Feature",
  "properties": {
    "date:inception_lower":"1980-01-01",
    "date:inception_upper":"1980-01-31",
    "iso:country":"GB",
    "wof:name":"BH11 9PU",
    "wof:placetype":"postalcode"
},
  "geometry": {"coordinates":[-1.924104,50.768376],"type":"Point"}
}