{
  "type": "Feature",
  "properties": {
    "iso:country":"GB",
    "wof:name":"BH11 9PU",
    "wof:placetype":"postalcode"
},
  "geometry": {"coordinates":[-1.92416832096996,50.76854774330553],"type":"Point"}
}