{
  "type": "Feature",
  "properties": {
    "iso:country": "GB",
    "wof:name": "KY8 5FQ",
    "wof:placetype": "postalcode"
  },
  "geometry": {"coordinates":[-2.995665,56.205771],"type":"Point"}
}
