{
  "type": "Feature",
  "properties": {
    "iso:country":"GB",
    "wof:name":"SA13 2TG",
    "wof:placetype":"postalcode"
},
  "geometry": {"coordinates":[-3.71913177199873,51.55223259243481],"type":"Point"}
}