{
  "type": "Feature",
  "properties": {
    "iso:country":"GB",
    "wof:name":"AB54 4NX",
    "wof:placetype":"postalcode"
},
  "geometry": {"coordinates":[-2.77280366564703,57.32574061400468],"type":"Point"}
}