{
  "type": "Feature",
  "properties": {
    "date:inception_lower":"1980-01-01",
    "date:inception_upper":"1980-01-31",
    "iso:country":"GB",
    "wof:name":"SA73 1DS",
    "wof:placetype":"postalcode"
},
  "geometry": {"coordinates":[-4.989138,51.714162],"type":"Point"}
}