{
  "type": "Feature",
  "properties": {
    "date:inception_lower": "1980-01-01",
    "date:inception_upper": "1980-01-01",
    "iso:country": "GB",
    "wof:name": "SA73 1DS",
    "wof:placetype": "postalcode"
  },
  "geometry": {"coordinates":[-4.989065,51.714069],"type":"Point"}
}
