{
  "type": "Feature",
  "properties": {
    "iso:country": "GB",
    "wof:name": "IG10 1PX",
    "wof:placetype": "postalcode"
  },
  "geometry": {"coordinates":[0.067093,51.653125],"type":"Point"}
}
