{
  "type": "Feature",
  "properties": {
    "iso:country":"GB",
    "wof:name":"IG10 1PX",
    "wof:placetype":"postalcode"
},
  "geometry": {"coordinates":[0.06709254248517,51.65312546560104],"type":"Point"}
}