{
  "type": "Feature",
  "properties": {
    "iso:country": "GB",
    "wof:name": "CM9 6FQ",
    "wof:placetype": "postalcode"
  },
  "geometry": {"coordinates":[0.691775,51.719487],"type":"Point"}
}
