{
  "type": "Feature",
  "properties": {
    "date:inception_lower": "2016-08-01",
    "date:inception_upper": "2016-08-01",
    "iso:country": "GB",
    "wof:name": "CM9 6FQ",
    "wof:placetype": "postalcode"
  },
  "geometry": {"coordinates":[0.691775,51.719487],"type":"Point"}
}
