{
  "type": "Feature",
  "properties": {
    "date:inception_lower": "2018-12-01",
    "date:inception_upper": "2018-12-01",
    "iso:country": "GB",
    "wof:name": "CT20 3SY",
    "wof:placetype": "postalcode"
  },
  "geometry": {"coordinates":[1.131505,51.083824],"type":"Point"}
}
