{
  "type": "Feature",
  "properties": {
    "date:inception_lower": "2022-11-01",
    "date:inception_upper": "2022-11-01",
    "iso:country": "GB",
    "wof:name": "CH7 4FB",
    "wof:placetype": "postalcode"
  },
  "geometry": {"coordinates":[-3.198792,53.11336],"type":"Point"}
}
