{
  "type": "Feature",
  "properties": {
    "date:inception_lower": "1980-01-01",
    "date:inception_upper": "1980-01-01",
    "iso:country": "GB",
    "wof:name": "PL12 5JS",
    "wof:placetype": "postalcode"
  },
  "geometry": {"coordinates":[-4.339772,50.423499],"type":"Point"}
}
