{
  "type": "Feature",
  "properties": {
    "iso:country":"GB",
    "wof:name":"PL12 5JS",
    "wof:placetype":"postalcode"
},
  "geometry": {"coordinates":[-4.33977197737756,50.4234986722701],"type":"Point"}
}