{
  "type": "Feature",
  "properties": {
    "iso:country": "GB",
    "wof:name": "PA16 7QF",
    "wof:placetype": "postalcode"
  },
  "geometry": {"coordinates":[-4.795751,55.961115],"type":"Point"}
}
