{
  "type": "Feature",
  "properties": {
    "iso:country":"GB",
    "wof:name":"B74 3JB",
    "wof:placetype":"postalcode"
},
  "geometry": {"coordinates":[-1.88523693556462,52.58348828483459],"type":"Point"}
}