{
  "type": "Feature",
  "properties": {
    "iso:country":"GB",
    "wof:name":"PE15 0XW",
    "wof:placetype":"postalcode"
},
  "geometry": {"coordinates":[-0.03188002787336,52.49941438004161],"type":"Point"}
}