{
  "type": "Feature",
  "properties": {
    "date:inception_lower":"1980-01-01",
    "date:inception_upper":"1980-01-31",
    "iso:country":"GB",
    "wof:name":"PE15 0XW",
    "wof:placetype":"postalcode"
},
  "geometry": {"coordinates":[-0.031859,52.499432],"type":"Point"}
}