{
  "type": "Feature",
  "properties": {
    "iso:country":"GB",
    "wof:name":"SS7 2EJ",
    "wof:placetype":"postalcode"
},
  "geometry": {"coordinates":[0.62081852469518,51.55093839926669],"type":"Point"}
}