{
  "type": "Feature",
  "properties": {
    "iso:country":"GB",
    "wof:name":"NE11 0EL",
    "wof:placetype":"postalcode"
},
  "geometry": {"coordinates":[-1.61323758460173,54.93388009111268],"type":"Point"}
}