{
  "type": "Feature",
  "properties": {
    "iso:country":"GB",
    "wof:name":"KA3 6EF",
    "wof:placetype":"postalcode"
},
  "geometry": {"coordinates":[-4.44439738708166,55.65864595743362],"type":"Point"}
}