{
  "type": "Feature",
  "properties": {
    "iso:country":"GB",
    "wof:name":"CH42 2DX",
    "wof:placetype":"postalcode"
},
  "geometry": {"coordinates":[-3.01515462703446,53.3688360111349],"type":"Point"}
}