{
  "type": "Feature",
  "properties": {
    "iso:country":"GB",
    "wof:name":"MK18 7EA",
    "wof:placetype":"postalcode"
},
  "geometry": {"coordinates":[-0.97561139653908,51.99478840813917],"type":"Point"}
}