{
  "type": "Feature",
  "properties": {
    "date:inception_lower": "1983-01-01",
    "date:inception_upper": "1983-01-01",
    "iso:country": "GB",
    "wof:name": "MK18 7EA",
    "wof:placetype": "postalcode"
  },
  "geometry": {"coordinates":[-0.975611,51.994788],"type":"Point"}
}
