{
  "type": "Feature",
  "properties": {
    "date:inception_lower": "1980-01-01",
    "date:inception_upper": "1980-01-01",
    "iso:country": "GB",
    "wof:name": "B21 9HT",
    "wof:placetype": "postalcode"
  },
  "geometry": {"coordinates":[-1.936326,52.505387],"type":"Point"}
}
