{
  "type": "Feature",
  "properties": {
    "iso:country": "GB",
    "wof:name": "B21 9HT",
    "wof:placetype": "postalcode"
  },
  "geometry": {"coordinates":[-1.936326,52.505387],"type":"Point"}
}
