{
  "type": "Feature",
  "properties": {
    "iso:country":"GB",
    "wof:name":"B21 9HT",
    "wof:placetype":"postalcode"
},
  "geometry": {"coordinates":[-1.93632632514482,52.50538678878895],"type":"Point"}
}