{
  "type": "Feature",
  "properties": {
    "date:inception_lower": "1993-08-01",
    "date:inception_upper": "1993-08-01",
    "iso:country": "GB",
    "wof:name": "LE11 3LG",
    "wof:placetype": "postalcode"
  },
  "geometry": {"coordinates":[-1.222413,52.76026],"type":"Point"}
}
