{
  "type": "Feature",
  "properties": {
    "iso:country":"GB",
    "wof:name":"LE11 3LG",
    "wof:placetype":"postalcode"
},
  "geometry": {"coordinates":[-1.22241312256229,52.76025987557706],"type":"Point"}
}