{
  "type": "Feature",
  "properties": {
    "iso:country":"GB",
    "wof:name":"PO1 4PT",
    "wof:placetype":"postalcode"
},
  "geometry": {"coordinates":[-1.08128533653774,50.8059901708825],"type":"Point"}
}