{
  "type": "Feature",
  "properties": {
    "iso:country":"GB",
    "wof:name":"SS11 7BJ",
    "wof:placetype":"postalcode"
},
  "geometry": {"coordinates":[0.52477834724994,51.62287826983756],"type":"Point"}
}