{
  "type": "Feature",
  "properties": {
    "date:inception_lower": "1980-01-01",
    "date:inception_upper": "1980-01-01",
    "iso:country": "GB",
    "wof:name": "SS11 7BJ",
    "wof:placetype": "postalcode"
  },
  "geometry": {"coordinates":[0.524778,51.622878],"type":"Point"}
}
