{
  "type": "Feature",
  "properties": {
    "iso:country":"GB",
    "wof:name":"SP7 9QL",
    "wof:placetype":"postalcode"
},
  "geometry": {"coordinates":[-2.21536628086158,51.03126587018696],"type":"Point"}
}