{
  "type": "Feature",
  "properties": {
    "date:inception_lower":"1997-06-01",
    "date:inception_upper":"1997-06-30",
    "iso:country":"GB",
    "wof:name":"SP7 9QL",
    "wof:placetype":"postalcode"
},
  "geometry": {"coordinates":[-2.215366,51.031266],"type":"Point"}
}