{
  "type": "Feature",
  "properties": {
    "iso:country":"GB",
    "wof:name":"CV3 2EG",
    "wof:placetype":"postalcode"
},
  "geometry": {"coordinates":[-1.44882386960419,52.38974922416497],"type":"Point"}
}