{
  "type": "Feature",
  "properties": {
    "iso:country":"GB",
    "wof:name":"PL1 4GH",
    "wof:placetype":"postalcode"
},
  "geometry": {"coordinates":[-4.17607727925008,50.37164950966505],"type":"Point"}
}