{
  "type": "Feature",
  "properties": {
    "date:inception_lower": "2010-05-01",
    "date:inception_upper": "2010-05-01",
    "iso:country": "GB",
    "wof:name": "PL1 4GH",
    "wof:placetype": "postalcode"
  },
  "geometry": {"coordinates":[-4.175937,50.37163],"type":"Point"}
}
