{
  "type": "Feature",
  "properties": {
    "iso:country":"GB",
    "wof:name":"WD24 7EG",
    "wof:placetype":"postalcode"
},
  "geometry": {"coordinates":[-0.38813937887616,51.67183825527738],"type":"Point"}
}