{
  "type": "Feature",
  "properties": {
    "iso:country": "GB",
    "wof:name": "WD24 7EG",
    "wof:placetype": "postalcode"
  },
  "geometry": {"coordinates":[-0.388139,51.671838],"type":"Point"}
}
