{
  "type": "Feature",
  "properties": {
    "date:inception_lower": "1992-08-01",
    "date:inception_upper": "1992-08-01",
    "iso:country": "GB",
    "wof:name": "DE45 1AE",
    "wof:placetype": "postalcode"
  },
  "geometry": {"coordinates":[-1.672604,53.221525],"type":"Point"}
}
