{
  "type": "Feature",
  "properties": {
    "iso:country":"GB",
    "wof:name":"SL6 8LW",
    "wof:placetype":"postalcode"
},
  "geometry": {"coordinates":[-0.69927856596626,51.53348987017381],"type":"Point"}
}