{
  "type": "Feature",
  "properties": {
    "date:inception_lower": "2007-10-01",
    "date:inception_upper": "2007-10-01",
    "iso:country": "GB",
    "wof:name": "SL6 8LW",
    "wof:placetype": "postalcode"
  },
  "geometry": {"coordinates":[-0.69926,51.533493],"type":"Point"}
}
