{
  "type": "Feature",
  "properties": {
    "iso:country":"GB",
    "wof:name":"CT4 5AJ",
    "wof:placetype":"postalcode"
},
  "geometry": {"coordinates":[1.11705945647025,51.24895564433369],"type":"Point"}
}