{
  "type": "Feature",
  "properties": {
    "iso:country": "GB",
    "wof:name": "RG12 7DT",
    "wof:placetype": "postalcode"
  },
  "geometry": {"coordinates":[-0.75797,51.408418],"type":"Point"}
}
