{
  "type": "Feature",
  "properties": {
    "iso:country":"GB",
    "wof:name":"G33 6BH",
    "wof:placetype":"postalcode"
},
  "geometry": {"coordinates":[-4.14582749559548,55.88431368549745],"type":"Point"}
}