{
  "type": "Feature",
  "properties": {
    "date:inception_lower":"1991-11-01",
    "date:inception_upper":"1991-11-30",
    "iso:country":"GB",
    "wof:name":"G33 6BH",
    "wof:placetype":"postalcode"
},
  "geometry": {"coordinates":[-4.145827,55.884314],"type":"Point"}
}