{
  "type": "Feature",
  "properties": {
    "date:inception_lower": "1980-01-01",
    "date:inception_upper": "1980-01-01",
    "iso:country": "GB",
    "wof:name": "TW16 7DG",
    "wof:placetype": "postalcode"
  },
  "geometry": {"coordinates":[-0.429119,51.41903],"type":"Point"}
}
