{
  "type": "Feature",
  "properties": {
    "date:inception_lower":"1984-02-01",
    "date:inception_upper":"1984-02-29",
    "iso:country":"GB",
    "wof:name":"RM12 6TS",
    "wof:placetype":"postalcode"
},
  "geometry": {"coordinates":[0.211667,51.542082],"type":"Point"}
}