{
  "type": "Feature",
  "properties": {
    "iso:country":"GB",
    "wof:name":"RM12 6TS",
    "wof:placetype":"postalcode"
},
  "geometry": {"coordinates":[0.21166693218239,51.54208237604592],"type":"Point"}
}