{
  "type": "Feature",
  "properties": {
    "iso:country": "GB",
    "wof:name": "ST20 0LR",
    "wof:placetype": "postalcode"
  },
  "geometry": {"coordinates":[-2.299263,52.827557],"type":"Point"}
}
