{
  "type": "Feature",
  "properties": {
    "iso:country":"GB",
    "wof:name":"ST20 0LR",
    "wof:placetype":"postalcode"
},
  "geometry": {"coordinates":[-2.29926328315307,52.82755738274037],"type":"Point"}
}