{
  "type": "Feature",
  "properties": {
    "date:inception_lower":"1980-01-01",
    "date:inception_upper":"1980-01-31",
    "iso:country":"GB",
    "wof:name":"ST20 0LR",
    "wof:placetype":"postalcode"
},
  "geometry": {"coordinates":[-2.299263,52.827557],"type":"Point"}
}