{
  "type": "Feature",
  "properties": {
    "iso:country":"GB",
    "wof:name":"TS1 4LT",
    "wof:placetype":"postalcode"
},
  "geometry": {"coordinates":[-1.24324529639012,54.56889481469856],"type":"Point"}
}