{
  "type": "Feature",
  "properties": {
    "iso:country": "GB",
    "wof:name": "ME20 7LQ",
    "wof:placetype": "postalcode"
  },
  "geometry": {"coordinates":[0.469641,51.297277],"type":"Point"}
}
