{
  "type": "Feature",
  "properties": {
    "iso:country":"GB",
    "wof:name":"HD4 7PB",
    "wof:placetype":"postalcode"
},
  "geometry": {"coordinates":[-1.8016736152854,53.62059462527586],"type":"Point"}
}