{
  "type": "Feature",
  "properties": {
    "date:inception_lower": "1980-01-01",
    "date:inception_upper": "1980-01-01",
    "iso:country": "GB",
    "wof:name": "EH6 4JN",
    "wof:placetype": "postalcode"
  },
  "geometry": {"coordinates":[-3.189638,55.979038],"type":"Point"}
}
