{
  "type": "Feature",
  "properties": {
    "iso:country":"GB",
    "wof:name":"L13 5SL",
    "wof:placetype":"postalcode"
},
  "geometry": {"coordinates":[-2.91155878010429,53.41324151848877],"type":"Point"}
}