{
  "type": "Feature",
  "properties": {
    "iso:country": "GB",
    "wof:name": "EC1N 7TN",
    "wof:placetype": "postalcode"
  },
  "geometry": {"coordinates":[-0.109596,51.520983],"type":"Point"}
}
