{
  "type": "Feature",
  "properties": {
    "date:inception_lower":"1980-01-01",
    "date:inception_upper":"1980-01-31",
    "iso:country":"GB",
    "wof:name":"EC1N 7TN",
    "wof:placetype":"postalcode"
},
  "geometry": {"coordinates":[-0.109596,51.520983],"type":"Point"}
}