{
  "type": "Feature",
  "properties": {
    "iso:country": "GB",
    "wof:name": "OX13 6FE",
    "wof:placetype": "postalcode"
  },
  "geometry": {"coordinates":[-1.307312,51.70237],"type":"Point"}
}
