{
  "type": "Feature",
  "properties": {
    "iso:country":"GB",
    "wof:name":"OX13 6FE",
    "wof:placetype":"postalcode"
},
  "geometry": {"coordinates":[-1.30731165991378,51.70236993058558],"type":"Point"}
}