{
  "type": "Feature",
  "properties": {
    "date:inception_lower": "2008-09-01",
    "date:inception_upper": "2008-09-01",
    "iso:country": "GB",
    "wof:name": "OX13 6FE",
    "wof:placetype": "postalcode"
  },
  "geometry": {"coordinates":[-1.307312,51.70237],"type":"Point"}
}
