{
  "type": "Feature",
  "properties": {
    "iso:country":"GB",
    "wof:name":"E6 3SF",
    "wof:placetype":"postalcode"
},
  "geometry": {"coordinates":[0.04736210917594,51.52154924521064],"type":"Point"}
}