{
  "type": "Feature",
  "properties": {
    "iso:country":"GB",
    "wof:name":"HA8 8DZ",
    "wof:placetype":"postalcode"
},
  "geometry": {"coordinates":[-0.28118766270166,51.61808630070024],"type":"Point"}
}