{
  "type": "Feature",
  "properties": {
    "date:inception_lower": "1992-08-01",
    "date:inception_upper": "1992-08-01",
    "iso:country": "GB",
    "wof:name": "DE22 4EB",
    "wof:placetype": "postalcode"
  },
  "geometry": {"coordinates":[-1.521072,52.930052],"type":"Point"}
}
