{
  "type": "Feature",
  "properties": {
    "iso:country": "GB",
    "wof:name": "HU19 2LY",
    "wof:placetype": "postalcode"
  },
  "geometry": {"coordinates":[0.030791,53.72448],"type":"Point"}
}
