{
  "type": "Feature",
  "properties": {
    "iso:country":"GB",
    "wof:name":"HU19 2LY",
    "wof:placetype":"postalcode"
},
  "geometry": {"coordinates":[0.03079113194929,53.72448006133143],"type":"Point"}
}