{
  "type": "Feature",
  "properties": {
    "date:inception_lower": "1987-04-01",
    "date:inception_upper": "1987-04-01",
    "iso:country": "GB",
    "wof:name": "EX7 0RE",
    "wof:placetype": "postalcode"
  },
  "geometry": {"coordinates":[-3.464577,50.593392],"type":"Point"}
}
