{
  "type": "Feature",
  "properties": {
    "iso:country":"GB",
    "wof:name":"EX7 0RE",
    "wof:placetype":"postalcode"
},
  "geometry": {"coordinates":[-3.46457743599877,50.59339214265817],"type":"Point"}
}