{
  "type": "Feature",
  "properties": {
    "iso:country": "GB",
    "wof:name": "BB5 1NW",
    "wof:placetype": "postalcode"
  },
  "geometry": {"coordinates":[-2.367447,53.752014],"type":"Point"}
}
