{
  "type": "Feature",
  "properties": {
    "date:inception_lower": "1980-01-01",
    "date:inception_upper": "1980-01-01",
    "iso:country": "GB",
    "wof:name": "GL14 2XB",
    "wof:placetype": "postalcode"
  },
  "geometry": {"coordinates":[-2.492207,51.823596],"type":"Point"}
}
