{
  "type": "Feature",
  "properties": {
    "iso:country":"GB",
    "wof:name":"LE9 2DL",
    "wof:placetype":"postalcode"
},
  "geometry": {"coordinates":[-1.23312210050812,52.63469657373356],"type":"Point"}
}