{
  "type": "Feature",
  "properties": {
    "iso:country": "GB",
    "wof:name": "CF15 9ST",
    "wof:placetype": "postalcode"
  },
  "geometry": {"coordinates":[-3.270229,51.543188],"type":"Point"}
}
