{
  "type": "Feature",
  "properties": {
    "date:inception_lower": "2019-11-01",
    "date:inception_upper": "2019-11-01",
    "iso:country": "GB",
    "wof:name": "TQ7 4EW",
    "wof:placetype": "postalcode"
  },
  "geometry": {"coordinates":[-3.872369,50.302116],"type":"Point"}
}
