{
  "type": "Feature",
  "properties": {
    "iso:country":"GB",
    "wof:name":"KY7 5RL",
    "wof:placetype":"postalcode"
},
  "geometry": {"coordinates":[-3.14967001331868,56.20237628183619],"type":"Point"}
}