{
  "type": "Feature",
  "properties": {
    "date:inception_lower": "2024-01-01",
    "date:inception_upper": "2024-01-01",
    "iso:country": "GB",
    "wof:name": "KT15 9FP",
    "wof:placetype": "postalcode"
  },
  "geometry": {"coordinates":[-0.489139,51.371215],"type":"Point"}
}
