{
  "type": "Feature",
  "properties": {
    "iso:country": "GB",
    "wof:name": "L3 4ET",
    "wof:placetype": "postalcode"
  },
  "geometry": {"coordinates":[-2.988392,53.398239],"type":"Point"}
}
