{
  "type": "Feature",
  "properties": {
    "date:inception_lower": "1980-01-01",
    "date:inception_upper": "1980-01-01",
    "iso:country": "GB",
    "wof:name": "RG7 3RB",
    "wof:placetype": "postalcode"
  },
  "geometry": {"coordinates":[-1.055057,51.374439],"type":"Point"}
}
