{
  "type": "Feature",
  "properties": {
    "iso:country":"GB",
    "wof:name":"RG7 3RB",
    "wof:placetype":"postalcode"
},
  "geometry": {"coordinates":[-1.05505718007002,51.37443922335078],"type":"Point"}
}