{
  "type": "Feature",
  "properties": {
    "date:inception_lower": "1980-01-01",
    "date:inception_upper": "1980-01-01",
    "iso:country": "GB",
    "wof:name": "TA4 1BZ",
    "wof:placetype": "postalcode"
  },
  "geometry": {"coordinates":[-3.181131,51.032687],"type":"Point"}
}
