{
  "type": "Feature",
  "properties": {
    "iso:country": "GB",
    "wof:name": "TA4 1BZ",
    "wof:placetype": "postalcode"
  },
  "geometry": {"coordinates":[-3.181131,51.032687],"type":"Point"}
}
