{
  "type": "Feature",
  "properties": {
    "iso:country":"GB",
    "wof:name":"SG13 7RP",
    "wof:placetype":"postalcode"
},
  "geometry": {"coordinates":[-0.04507052483689,51.78820498270762],"type":"Point"}
}