{
  "type": "Feature",
  "properties": {
    "iso:country":"GB",
    "wof:name":"LL60 6EG",
    "wof:placetype":"postalcode"
},
  "geometry": {"coordinates":[-4.25289512362779,53.20920146893825],"type":"Point"}
}