{
  "type": "Feature",
  "properties": {
    "date:inception_lower": "1980-01-01",
    "date:inception_upper": "1980-01-01",
    "iso:country": "GB",
    "wof:name": "BD1 1PR",
    "wof:placetype": "postalcode"
  },
  "geometry": {"coordinates":[-1.752735,53.794163],"type":"Point"}
}
