{
  "type": "Feature",
  "properties": {
    "date:inception_lower":"1980-01-01",
    "date:inception_upper":"1980-01-31",
    "iso:country":"GB",
    "wof:name":"NE61 2HS",
    "wof:placetype":"postalcode"
},
  "geometry": {"coordinates":[-1.674859,55.159262],"type":"Point"}
}