{
  "type": "Feature",
  "properties": {
    "iso:country": "GB",
    "wof:name": "NE61 2HS",
    "wof:placetype": "postalcode"
  },
  "geometry": {"coordinates":[-1.674859,55.159262],"type":"Point"}
}
