{
  "type": "Feature",
  "properties": {
    "date:inception_lower": "1980-01-01",
    "date:inception_upper": "1980-01-01",
    "iso:country": "GB",
    "wof:name": "CH1 4JE",
    "wof:placetype": "postalcode"
  },
  "geometry": {"coordinates":[-2.901848,53.191484],"type":"Point"}
}
