{
  "type": "Feature",
  "properties": {
    "iso:country": "GB",
    "wof:name": "S13 8ER",
    "wof:placetype": "postalcode"
  },
  "geometry": {"coordinates":[-1.40846,53.368473],"type":"Point"}
}
