{
  "type": "Feature",
  "properties": {
    "iso:country":"GB",
    "wof:name":"S13 8ER",
    "wof:placetype":"postalcode"
},
  "geometry": {"coordinates":[-1.40849088458935,53.36843669368913],"type":"Point"}
}