{
  "type": "Feature",
  "properties": {
    "date:inception_lower": "1980-01-01",
    "date:inception_upper": "1980-01-01",
    "iso:country": "GB",
    "wof:name": "S13 8ER",
    "wof:placetype": "postalcode"
  },
  "geometry": {"coordinates":[-1.40846,53.368473],"type":"Point"}
}
