{
  "type": "Feature",
  "properties": {
    "date:inception_lower": "1999-06-01",
    "date:inception_upper": "1999-06-01",
    "iso:country": "GB",
    "wof:name": "CH42 0LJ",
    "wof:placetype": "postalcode"
  },
  "geometry": {"coordinates":[-3.025157,53.376688],"type":"Point"}
}
