{
  "type": "Feature",
  "properties": {
    "iso:country": "GB",
    "wof:name": "EX32 7PR",
    "wof:placetype": "postalcode"
  },
  "geometry": {"coordinates":[-3.907131,51.090834],"type":"Point"}
}
