{
  "type": "Feature",
  "properties": {
    "date:inception_lower":"1980-01-01",
    "date:inception_upper":"1980-01-31",
    "iso:country":"GB",
    "wof:name":"SY25 6SL",
    "wof:placetype":"postalcode"
},
  "geometry": {"coordinates":[-4.042241,52.204856],"type":"Point"}
}