{
  "type": "Feature",
  "properties": {
    "iso:country":"GB",
    "wof:name":"SY25 6SL",
    "wof:placetype":"postalcode"
},
  "geometry": {"coordinates":[-4.04681640829721,52.20376553784485],"type":"Point"}
}