{
  "type": "Feature",
  "properties": {
    "iso:country": "GB",
    "wof:name": "SY25 6SL",
    "wof:placetype": "postalcode"
  },
  "geometry": {"coordinates":[-4.042241,52.204856],"type":"Point"}
}
