{
  "type": "Feature",
  "properties": {
    "date:inception_lower": "1980-01-01",
    "date:inception_upper": "1980-01-01",
    "iso:country": "GB",
    "wof:name": "CT4 5DA",
    "wof:placetype": "postalcode"
  },
  "geometry": {"coordinates":[1.135814,51.255389],"type":"Point"}
}
