{
  "type": "Feature",
  "properties": {
    "iso:country":"GB",
    "wof:name":"CT4 5DA",
    "wof:placetype":"postalcode"
},
  "geometry": {"coordinates":[1.13581396309568,51.2553892707388],"type":"Point"}
}