{
  "type": "Feature",
  "properties": {
    "date:inception_lower":"1983-08-01",
    "date:inception_upper":"1983-08-31",
    "iso:country":"GB",
    "wof:name":"KY16 8TE",
    "wof:placetype":"postalcode"
},
  "geometry": {"coordinates":[-2.66029,56.29955],"type":"Point"}
}