{
  "type": "Feature",
  "properties": {
    "iso:country": "GB",
    "wof:name": "KY16 8TE",
    "wof:placetype": "postalcode"
  },
  "geometry": {"coordinates":[-2.66029,56.29955],"type":"Point"}
}
