{
  "type": "Feature",
  "properties": {
    "date:inception_lower":"2015-10-01",
    "date:inception_upper":"2015-10-31",
    "iso:country":"GB",
    "wof:name":"TS17 6DX",
    "wof:placetype":"postalcode"
},
  "geometry": {"coordinates":[-1.305237,54.558949],"type":"Point"}
}