{
  "type": "Feature",
  "properties": {
    "iso:country":"GB",
    "wof:name":"TS17 6DX",
    "wof:placetype":"postalcode"
},
  "geometry": {"coordinates":[-1.30523690140011,54.55894936114154],"type":"Point"}
}