{
  "type": "Feature",
  "properties": {
    "date:inception_lower": "2021-11-01",
    "date:inception_upper": "2021-11-01",
    "iso:country": "GB",
    "wof:name": "BB3 2FT",
    "wof:placetype": "postalcode"
  },
  "geometry": {"coordinates":[-2.469917,53.695074],"type":"Point"}
}
