{
  "type": "Feature",
  "properties": {
    "date:inception_lower":"1980-01-01",
    "date:inception_upper":"1980-01-31",
    "iso:country":"GB",
    "wof:name":"YO18 8PH",
    "wof:placetype":"postalcode"
},
  "geometry": {"coordinates":[-0.827091,54.269795],"type":"Point"}
}