{
  "type": "Feature",
  "properties": {
    "iso:country":"GB",
    "wof:name":"YO18 8PH",
    "wof:placetype":"postalcode"
},
  "geometry": {"coordinates":[-0.82709087281353,54.2697946724852],"type":"Point"}
}