{
  "type": "Feature",
  "properties": {
    "date:inception_lower": "1993-01-01",
    "date:inception_upper": "1993-01-01",
    "iso:country": "GB",
    "wof:name": "EX17 3DN",
    "wof:placetype": "postalcode"
  },
  "geometry": {"coordinates":[-3.654538,50.787652],"type":"Point"}
}
