{
  "type": "Feature",
  "properties": {
    "date:inception_lower":"1980-01-01",
    "date:inception_upper":"1980-01-31",
    "iso:country":"GB",
    "wof:name":"EX5 5JP",
    "wof:placetype":"postalcode"
},
  "geometry": {"coordinates":[-3.541261,50.792738],"type":"Point"}
}