{
  "type": "Feature",
  "properties": {
    "iso:country":"GB",
    "wof:name":"IP20 0HG",
    "wof:placetype":"postalcode"
},
  "geometry": {"coordinates":[1.34109908365612,52.41344833380954],"type":"Point"}
}