{
  "type": "Feature",
  "properties": {
    "iso:country": "GB",
    "wof:name": "IP20 0HG",
    "wof:placetype": "postalcode"
  },
  "geometry": {"coordinates":[1.341174,52.413464],"type":"Point"}
}
