{
  "type": "Feature",
  "properties": {
    "iso:country": "GB",
    "wof:name": "TW17 8EA",
    "wof:placetype": "postalcode"
  },
  "geometry": {"coordinates":[-0.438985,51.397077],"type":"Point"}
}
