{
  "type": "Feature",
  "properties": {
    "iso:country": "GB",
    "wof:name": "BA14 0SX",
    "wof:placetype": "postalcode"
  },
  "geometry": {"coordinates":[-2.205921,51.296412],"type":"Point"}
}
