{
  "type": "Feature",
  "properties": {
    "iso:country":"GB",
    "wof:name":"BA14 0SX",
    "wof:placetype":"postalcode"
},
  "geometry": {"coordinates":[-2.20592099484296,51.29641190838124],"type":"Point"}
}