{
  "type": "Feature",
  "properties": {
    "date:inception_lower":"1990-02-01",
    "date:inception_upper":"1990-02-28",
    "iso:country":"GB",
    "wof:name":"BA14 0SX",
    "wof:placetype":"postalcode"
},
  "geometry": {"coordinates":[-2.205921,51.296412],"type":"Point"}
}