{
  "type": "Feature",
  "properties": {
    "date:inception_lower":"1998-06-01",
    "date:inception_upper":"1998-06-30",
    "iso:country":"GB",
    "wof:name":"YO30 6EY",
    "wof:placetype":"postalcode"
},
  "geometry": {"coordinates":[-1.085797,53.976496],"type":"Point"}
}