{
  "type": "Feature",
  "properties": {
    "iso:country":"GB",
    "wof:name":"NW6 3HL",
    "wof:placetype":"postalcode"
},
  "geometry": {"coordinates":[-0.18898086829244,51.54230626433027],"type":"Point"}
}