{
  "type": "Feature",
  "properties": {
    "iso:country":"GB",
    "wof:name":"WC2H 9BD",
    "wof:placetype":"postalcode"
},
  "geometry": {"coordinates":[-0.12431895337172,51.51452856371725],"type":"Point"}
}