{
  "type": "Feature",
  "properties": {
    "iso:country": "GB",
    "wof:name": "CO4 6AH",
    "wof:placetype": "postalcode"
  },
  "geometry": {"coordinates":[0.888823,51.916618],"type":"Point"}
}
