{
  "type": "Feature",
  "properties": {
    "date:inception_lower":"2016-02-01",
    "date:inception_upper":"2016-02-29",
    "iso:country":"GB",
    "wof:name":"CO4 6AH",
    "wof:placetype":"postalcode"
},
  "geometry": {"coordinates":[0.888823,51.916618],"type":"Point"}
}