{
  "type": "Feature",
  "properties": {
    "iso:country":"GB",
    "wof:name":"CM12 9AX",
    "wof:placetype":"postalcode"
},
  "geometry": {"coordinates":[0.4180642466041,51.62640252659256],"type":"Point"}
}