{
  "type": "Feature",
  "properties": {
    "iso:country":"GB",
    "wof:name":"E15 1LS",
    "wof:placetype":"postalcode"
},
  "geometry": {"coordinates":[0.00330681298755,51.55037604516404],"type":"Point"}
}