{
  "type": "Feature",
  "properties": {
    "iso:country": "GB",
    "wof:name": "TN23 3PR",
    "wof:placetype": "postalcode"
  },
  "geometry": {"coordinates":[0.853347,51.125835],"type":"Point"}
}
