{
  "type": "Feature",
  "properties": {
    "iso:country":"GB",
    "wof:name":"TN23 3PR",
    "wof:placetype":"postalcode"
},
  "geometry": {"coordinates":[0.85334650263773,51.12583468477906],"type":"Point"}
}