{
  "type": "Feature",
  "properties": {
    "iso:country":"GB",
    "wof:name":"PE6 7QJ",
    "wof:placetype":"postalcode"
},
  "geometry": {"coordinates":[-0.19284529280158,52.57418945963559],"type":"Point"}
}