{
  "type": "Feature",
  "properties": {
    "iso:country": "GB",
    "wof:name": "PE6 7QJ",
    "wof:placetype": "postalcode"
  },
  "geometry": {"coordinates":[-0.192845,52.574189],"type":"Point"}
}
