{
  "type": "Feature",
  "properties": {
    "date:inception_lower": "2002-06-01",
    "date:inception_upper": "2002-06-01",
    "iso:country": "GB",
    "wof:name": "PE6 7QJ",
    "wof:placetype": "postalcode"
  },
  "geometry": {"coordinates":[-0.192845,52.574189],"type":"Point"}
}
