{
  "type": "Feature",
  "properties": {
    "iso:country":"GB",
    "wof:name":"ST14 8BP",
    "wof:placetype":"postalcode"
},
  "geometry": {"coordinates":[-1.86255367585878,52.89453922851669],"type":"Point"}
}