{
  "type": "Feature",
  "properties": {
    "iso:country":"GB",
    "wof:name":"IP28 7RP",
    "wof:placetype":"postalcode"
},
  "geometry": {"coordinates":[0.50114674760528,52.34715920910883],"type":"Point"}
}