{
  "type": "Feature",
  "properties": {
    "iso:country":"GB",
    "wof:name":"AB42 1HH",
    "wof:placetype":"postalcode"
},
  "geometry": {"coordinates":[-1.78866042394912,57.51225307887484],"type":"Point"}
}