{
  "type": "Feature",
  "properties": {
    "iso:country": "GB",
    "wof:name": "SA3 1LX",
    "wof:placetype": "postalcode"
  },
  "geometry": {"coordinates":[-4.171953,51.553264],"type":"Point"}
}
