{
  "type": "Feature",
  "properties": {
    "iso:country":"GB",
    "wof:name":"SA3 1LX",
    "wof:placetype":"postalcode"
},
  "geometry": {"coordinates":[-4.17195266614112,51.55326434238535],"type":"Point"}
}