{
  "type": "Feature",
  "properties": {
    "iso:country":"GB",
    "wof:name":"M27 5NF",
    "wof:placetype":"postalcode"
},
  "geometry": {"coordinates":[-2.33334267629039,53.50505390082326],"type":"Point"}
}