{
  "type": "Feature",
  "properties": {
    "iso:country": "GB",
    "wof:name": "M27 5NF",
    "wof:placetype": "postalcode"
  },
  "geometry": {"coordinates":[-2.333343,53.505054],"type":"Point"}
}
