{
  "type": "Feature",
  "properties": {
    "iso:country":"GB",
    "wof:name":"LE8 9HA",
    "wof:placetype":"postalcode"
},
  "geometry": {"coordinates":[-1.03446875444567,52.57017909631484],"type":"Point"}
}