{
  "type": "Feature",
  "properties": {
    "iso:country": "GB",
    "wof:name": "LE8 9HA",
    "wof:placetype": "postalcode"
  },
  "geometry": {"coordinates":[-1.034459,52.570197],"type":"Point"}
}
