{
  "type": "Feature",
  "properties": {
    "date:inception_lower": "2000-06-01",
    "date:inception_upper": "2000-06-01",
    "iso:country": "GB",
    "wof:name": "LE8 9HA",
    "wof:placetype": "postalcode"
  },
  "geometry": {"coordinates":[-1.034459,52.570197],"type":"Point"}
}
