{
  "type": "Feature",
  "properties": {
    "iso:country": "GB",
    "wof:name": "LE8 9HA",
    "wof:placetype": "postalcode"
  },
  "geometry": {"coordinates":[-1.033688,52.570371],"type":"Point"}
}
