{
  "type": "Feature",
  "properties": {
    "iso:country": "GB",
    "wof:name": "CO5 9SB",
    "wof:placetype": "postalcode"
  },
  "geometry": {"coordinates":[0.711255,51.847234],"type":"Point"}
}
