{
  "type": "Feature",
  "properties": {
    "date:inception_lower":"1980-01-01",
    "date:inception_upper":"1980-01-31",
    "iso:country":"GB",
    "wof:name":"CO5 9SB",
    "wof:placetype":"postalcode"
},
  "geometry": {"coordinates":[0.711255,51.847234],"type":"Point"}
}