{
  "type": "Feature",
  "properties": {
    "iso:country":"GB",
    "wof:name":"CO5 9SB",
    "wof:placetype":"postalcode"
},
  "geometry": {"coordinates":[0.71056202185396,51.84726635693549],"type":"Point"}
}