{
  "type": "Feature",
  "properties": {
    "iso:country":"GB",
    "wof:name":"HS8 5TB",
    "wof:placetype":"postalcode"
},
  "geometry": {"coordinates":[-7.38174466762423,57.15561978867007],"type":"Point"}
}