{
  "type": "Feature",
  "properties": {
    "date:inception_lower": "1980-01-01",
    "date:inception_upper": "1980-01-01",
    "iso:country": "GB",
    "wof:name": "RG14 5LL",
    "wof:placetype": "postalcode"
  },
  "geometry": {"coordinates":[-1.325355,51.399774],"type":"Point"}
}
