{
  "type": "Feature",
  "properties": {
    "iso:country":"GB",
    "wof:name":"BB9 5SH",
    "wof:placetype":"postalcode"
},
  "geometry": {"coordinates":[-2.23190852821935,53.82512923393072],"type":"Point"}
}