{
  "type": "Feature",
  "properties": {
    "iso:country": "GB",
    "wof:name": "BB9 5SH",
    "wof:placetype": "postalcode"
  },
  "geometry": {"coordinates":[-2.231908,53.825129],"type":"Point"}
}
