{
  "type": "Feature",
  "properties": {
    "iso:country":"GB",
    "wof:name":"TQ3 3TX",
    "wof:placetype":"postalcode"
},
  "geometry": {"coordinates":[-3.58858819959456,50.43301945004322],"type":"Point"}
}