{
  "type": "Feature",
  "properties": {
    "iso:country":"GB",
    "wof:name":"ML2 8QT",
    "wof:placetype":"postalcode"
},
  "geometry": {"coordinates":[-3.91283603483577,55.78559872159011],"type":"Point"}
}