{
  "type": "Feature",
  "properties": {
    "iso:country": "GB",
    "wof:name": "ML2 8QT",
    "wof:placetype": "postalcode"
  },
  "geometry": {"coordinates":[-3.912836,55.785599],"type":"Point"}
}
