{
  "type": "Feature",
  "properties": {
    "date:inception_lower": "2020-05-01",
    "date:inception_upper": "2020-05-01",
    "iso:country": "GB",
    "wof:name": "OX44 7BD",
    "wof:placetype": "postalcode"
  },
  "geometry": {"coordinates":[-1.128865,51.67691],"type":"Point"}
}
