{
  "type": "Feature",
  "properties": {
    "date:inception_lower":"1980-01-01",
    "date:inception_upper":"1980-01-31",
    "iso:country":"GB",
    "wof:name":"DH2 3LF",
    "wof:placetype":"postalcode"
},
  "geometry": {"coordinates":[-1.592501,54.824879],"type":"Point"}
}