{
  "type": "Feature",
  "properties": {
    "iso:country":"GB",
    "wof:name":"DH2 3LF",
    "wof:placetype":"postalcode"
},
  "geometry": {"coordinates":[-1.59248888428192,54.8248701035044],"type":"Point"}
}