{
  "type": "Feature",
  "properties": {
    "iso:country": "GB",
    "wof:name": "HP22 5HQ",
    "wof:placetype": "postalcode"
  },
  "geometry": {"coordinates":[-0.731515,51.801733],"type":"Point"}
}
