{
  "type": "Feature",
  "properties": {
    "iso:country":"GB",
    "wof:name":"NW2 7JL",
    "wof:placetype":"postalcode"
},
  "geometry": {"coordinates":[-0.23553523659325,51.56832011241116],"type":"Point"}
}