{
  "type": "Feature",
  "properties": {
    "date:inception_lower": "1992-08-01",
    "date:inception_upper": "1992-08-01",
    "iso:country": "GB",
    "wof:name": "DE24 0RN",
    "wof:placetype": "postalcode"
  },
  "geometry": {"coordinates":[-1.41399,52.892294],"type":"Point"}
}
