{
  "type": "Feature",
  "properties": {
    "iso:country": "GB",
    "wof:name": "GU11 3LQ",
    "wof:placetype": "postalcode"
  },
  "geometry": {"coordinates":[-0.768602,51.247939],"type":"Point"}
}
