{
  "type": "Feature",
  "properties": {
    "date:inception_lower": "1991-09-01",
    "date:inception_upper": "1991-09-01",
    "iso:country": "GB",
    "wof:name": "GU11 3LQ",
    "wof:placetype": "postalcode"
  },
  "geometry": {"coordinates":[-0.768602,51.247939],"type":"Point"}
}
