{
  "type": "Feature",
  "properties": {
    "iso:country":"GB",
    "wof:name":"PO20 3YT",
    "wof:placetype":"postalcode"
},
  "geometry": {"coordinates":[-0.66853614805134,50.84182235302135],"type":"Point"}
}