{
  "type": "Feature",
  "properties": {
    "date:inception_lower": "2002-06-01",
    "date:inception_upper": "2002-06-01",
    "iso:country": "GB",
    "wof:name": "PO20 3YT",
    "wof:placetype": "postalcode"
  },
  "geometry": {"coordinates":[-0.668536,50.841822],"type":"Point"}
}
