{
  "type": "Feature",
  "properties": {
    "iso:country":"GB",
    "wof:name":"B70 6AW",
    "wof:placetype":"postalcode"
},
  "geometry": {"coordinates":[-1.99208745953886,52.51508566392346],"type":"Point"}
}