{
  "type": "Feature",
  "properties": {
    "iso:country":"GB",
    "wof:name":"SL6 6BA",
    "wof:placetype":"postalcode"
},
  "geometry": {"coordinates":[-0.73197234266978,51.5264114250044],"type":"Point"}
}