{
  "type": "Feature",
  "properties": {
    "date:inception_lower":"1980-01-01",
    "date:inception_upper":"1980-01-31",
    "iso:country":"GB",
    "wof:name":"SL6 6BA",
    "wof:placetype":"postalcode"
},
  "geometry": {"coordinates":[-0.731972,51.526411],"type":"Point"}
}