{
  "type": "Feature",
  "properties": {
    "iso:country":"GB",
    "wof:name":"TW12 3RX",
    "wof:placetype":"postalcode"
},
  "geometry": {"coordinates":[-0.37336949314996,51.42364752848907],"type":"Point"}
}