{
  "type": "Feature",
  "properties": {
    "date:inception_lower": "1980-01-01",
    "date:inception_upper": "1980-01-01",
    "iso:country": "GB",
    "wof:name": "TW12 3RX",
    "wof:placetype": "postalcode"
  },
  "geometry": {"coordinates":[-0.373362,51.423648],"type":"Point"}
}
