{
  "type": "Feature",
  "properties": {
    "iso:country":"GB",
    "wof:name":"KA8 9LR",
    "wof:placetype":"postalcode"
},
  "geometry": {"coordinates":[-4.61360558119079,55.47160787337187],"type":"Point"}
}