{
  "type": "Feature",
  "properties": {
    "date:inception_lower": "1980-01-01",
    "date:inception_upper": "1980-01-01",
    "iso:country": "GB",
    "wof:name": "B8 2EA",
    "wof:placetype": "postalcode"
  },
  "geometry": {"coordinates":[-1.82373,52.496813],"type":"Point"}
}
