{
  "type": "Feature",
  "properties": {
    "iso:country":"GB",
    "wof:name":"B25 8NW",
    "wof:placetype":"postalcode"
},
  "geometry": {"coordinates":[-1.83156769501066,52.46551271174506],"type":"Point"}
}