{
  "type": "Feature",
  "properties": {
    "iso:country": "GB",
    "wof:name": "CV31 1HZ",
    "wof:placetype": "postalcode"
  },
  "geometry": {"coordinates":[-1.524178,52.282787],"type":"Point"}
}
