{
  "type": "Feature",
  "properties": {
    "iso:country":"GB",
    "wof:name":"CV31 1HZ",
    "wof:placetype":"postalcode"
},
  "geometry": {"coordinates":[-1.52417827567405,52.28278667044258],"type":"Point"}
}