{
  "type": "Feature",
  "properties": {
    "iso:country":"GB",
    "wof:name":"BB3 2SH",
    "wof:placetype":"postalcode"
},
  "geometry": {"coordinates":[-2.47164740501509,53.68973893427464],"type":"Point"}
}