{
  "type": "Feature",
  "properties": {
    "date:inception_lower": "1981-06-01",
    "date:inception_upper": "1981-06-01",
    "iso:country": "GB",
    "wof:name": "MK6 2NA",
    "wof:placetype": "postalcode"
  },
  "geometry": {"coordinates":[-0.758967,52.032294],"type":"Point"}
}
