{
  "type": "Feature",
  "properties": {
    "iso:country":"GB",
    "wof:name":"MK6 2NA",
    "wof:placetype":"postalcode"
},
  "geometry": {"coordinates":[-0.75896718254673,52.03229352631444],"type":"Point"}
}