{
  "type": "Feature",
  "properties": {
    "iso:country": "GB",
    "wof:name": "HP16 9HB",
    "wof:placetype": "postalcode"
  },
  "geometry": {"coordinates":[-0.741359,51.699978],"type":"Point"}
}
