{
  "type": "Feature",
  "properties": {
    "iso:country":"GB",
    "wof:name":"HP16 9HB",
    "wof:placetype":"postalcode"
},
  "geometry": {"coordinates":[-0.74138063718068,51.69997321414817],"type":"Point"}
}