{
  "type": "Feature",
  "properties": {
    "date:inception_lower":"1992-08-01",
    "date:inception_upper":"1992-08-31",
    "iso:country":"GB",
    "wof:name":"BN7 2FB",
    "wof:placetype":"postalcode"
},
  "geometry": {"coordinates":[0.018493,50.878844],"type":"Point"}
}