{
  "type": "Feature",
  "properties": {
    "date:inception_lower": "2005-01-01",
    "date:inception_upper": "2005-01-01",
    "iso:country": "GB",
    "wof:name": "TW15 2QW",
    "wof:placetype": "postalcode"
  },
  "geometry": {"coordinates":[-0.46695,51.433451],"type":"Point"}
}
