{
  "type": "Feature",
  "properties": {
    "iso:country": "GB",
    "wof:name": "NG2 4RS",
    "wof:placetype": "postalcode"
  },
  "geometry": {"coordinates":[-1.122896,52.943299],"type":"Point"}
}
