{
  "type": "Feature",
  "properties": {
    "iso:country":"GB",
    "wof:name":"IG3 8TD",
    "wof:placetype":"postalcode"
},
  "geometry": {"coordinates":[0.10857032698993,51.56650778029901],"type":"Point"}
}