{
  "type": "Feature",
  "properties": {
    "iso:country": "GB",
    "wof:name": "IG3 8TD",
    "wof:placetype": "postalcode"
  },
  "geometry": {"coordinates":[0.108658,51.566524],"type":"Point"}
}
