{
  "type": "Feature",
  "properties": {
    "iso:country":"GB",
    "wof:name":"RM8 2NH",
    "wof:placetype":"postalcode"
},
  "geometry": {"coordinates":[0.11702637884651,51.5488106233928],"type":"Point"}
}