{
  "type": "Feature",
  "properties": {
    "date:inception_lower": "1986-07-01",
    "date:inception_upper": "1986-07-01",
    "iso:country": "GB",
    "wof:name": "HU12 9LG",
    "wof:placetype": "postalcode"
  },
  "geometry": {"coordinates":[-0.178537,53.719971],"type":"Point"}
}
