{
  "type": "Feature",
  "properties": {
    "iso:country":"GB",
    "wof:name":"HU12 9LG",
    "wof:placetype":"postalcode"
},
  "geometry": {"coordinates":[-0.17853666313915,53.71997059120286],"type":"Point"}
}