{
  "type": "Feature",
  "properties": {
    "date:inception_lower": "1980-01-01",
    "date:inception_upper": "1980-01-01",
    "iso:country": "GB",
    "wof:name": "DN31 1XP",
    "wof:placetype": "postalcode"
  },
  "geometry": {"coordinates":[-0.090086,53.569985],"type":"Point"}
}
