{
  "type": "Feature",
  "properties": {
    "iso:country":"GB",
    "wof:name":"ME17 1SD",
    "wof:placetype":"postalcode"
},
  "geometry": {"coordinates":[0.60585080421959,51.24454260563157],"type":"Point"}
}