{
  "type": "Feature",
  "properties": {
    "date:inception_lower": "2022-07-01",
    "date:inception_upper": "2022-07-01",
    "iso:country": "GB",
    "wof:name": "CO9 1GT",
    "wof:placetype": "postalcode"
  },
  "geometry": {"coordinates":[0.628209,51.941506],"type":"Point"}
}
