{
  "type": "Feature",
  "properties": {
    "iso:country": "GB",
    "wof:name": "LU1 1NP",
    "wof:placetype": "postalcode"
  },
  "geometry": {"coordinates":[-0.432856,51.881863],"type":"Point"}
}
