{
  "type": "Feature",
  "properties": {
    "date:inception_lower": "1980-01-01",
    "date:inception_upper": "1980-01-01",
    "iso:country": "GB",
    "wof:name": "LU1 1NP",
    "wof:placetype": "postalcode"
  },
  "geometry": {"coordinates":[-0.432856,51.881863],"type":"Point"}
}
