{
  "type": "Feature",
  "properties": {
    "iso:country": "GB",
    "wof:name": "LE12 5TR",
    "wof:placetype": "postalcode"
  },
  "geometry": {"coordinates":[-1.119484,52.78954],"type":"Point"}
}
