{
  "type": "Feature",
  "properties": {
    "iso:country":"GB",
    "wof:name":"LE12 5TR",
    "wof:placetype":"postalcode"
},
  "geometry": {"coordinates":[-1.1194836634937,52.7895396946092],"type":"Point"}
}