{
  "type": "Feature",
  "properties": {
    "iso:country":"GB",
    "wof:name":"RM18 7SA",
    "wof:placetype":"postalcode"
},
  "geometry": {"coordinates":[0.36267982353518,51.46492592408485],"type":"Point"}
}