{
  "type": "Feature",
  "properties": {
    "iso:country": "GB",
    "wof:name": "TN26 2AX",
    "wof:placetype": "postalcode"
  },
  "geometry": {"coordinates":[0.784664,51.040669],"type":"Point"}
}
