{
  "type": "Feature",
  "properties": {
    "iso:country":"GB",
    "wof:name":"TN26 2AX",
    "wof:placetype":"postalcode"
},
  "geometry": {"coordinates":[0.78466367593732,51.04066901229329],"type":"Point"}
}