{
  "type": "Feature",
  "properties": {
    "iso:country":"GB",
    "wof:name":"SR4 0EJ",
    "wof:placetype":"postalcode"
},
  "geometry": {"coordinates":[-1.43346837870745,54.90241511296194],"type":"Point"}
}