{
  "type": "Feature",
  "properties": {
    "iso:country": "GB",
    "wof:name": "NG13 8DJ",
    "wof:placetype": "postalcode"
  },
  "geometry": {"coordinates":[-0.940077,52.949494],"type":"Point"}
}
