{
  "type": "Feature",
  "properties": {
    "iso:country":"GB",
    "wof:name":"TN23 1QG",
    "wof:placetype":"postalcode"
},
  "geometry": {"coordinates":[0.87272882574432,51.14863741196231],"type":"Point"}
}