{
  "type": "Feature",
  "properties": {
    "date:inception_lower": "1980-01-01",
    "date:inception_upper": "1980-01-01",
    "iso:country": "GB",
    "wof:name": "TN23 1QG",
    "wof:placetype": "postalcode"
  },
  "geometry": {"coordinates":[0.872729,51.148637],"type":"Point"}
}
