{
  "type": "Feature",
  "properties": {
    "iso:country":"GB",
    "wof:name":"RH1 3ES",
    "wof:placetype":"postalcode"
},
  "geometry": {"coordinates":[-0.1524290054432,51.25925023739084],"type":"Point"}
}