{
  "type": "Feature",
  "properties": {
    "iso:country":"GB",
    "wof:name":"TN13 1DS",
    "wof:placetype":"postalcode"
},
  "geometry": {"coordinates":[0.19211747881059,51.27135349603717],"type":"Point"}
}