{
  "type": "Feature",
  "properties": {
    "iso:country": "GB",
    "wof:name": "TN13 1DS",
    "wof:placetype": "postalcode"
  },
  "geometry": {"coordinates":[0.192118,51.271353],"type":"Point"}
}
