{
  "type": "Feature",
  "properties": {
    "iso:country": "GB",
    "wof:name": "NN11 9ET",
    "wof:placetype": "postalcode"
  },
  "geometry": {"coordinates":[-1.174931,52.259062],"type":"Point"}
}
