{
  "type": "Feature",
  "properties": {
    "iso:country": "GB",
    "wof:name": "CV32 5UB",
    "wof:placetype": "postalcode"
  },
  "geometry": {"coordinates":[-1.532988,52.296712],"type":"Point"}
}
