{
  "type": "Feature",
  "properties": {
    "iso:country":"GB",
    "wof:name":"CV32 5UB",
    "wof:placetype":"postalcode"
},
  "geometry": {"coordinates":[-1.53298845423072,52.29671186934674],"type":"Point"}
}