{
  "type": "Feature",
  "properties": {
    "iso:country":"GB",
    "wof:name":"DT7 3NJ",
    "wof:placetype":"postalcode"
},
  "geometry": {"coordinates":[-2.94603401247543,50.73097412906318],"type":"Point"}
}