{
  "type": "Feature",
  "properties": {
    "iso:country": "GB",
    "wof:name": "DT7 3NJ",
    "wof:placetype": "postalcode"
  },
  "geometry": {"coordinates":[-2.946034,50.730974],"type":"Point"}
}
