{
  "type": "Feature",
  "properties": {
    "iso:country":"GB",
    "wof:name":"IP3 0DP",
    "wof:placetype":"postalcode"
},
  "geometry": {"coordinates":[1.16053245389552,52.04937690507619],"type":"Point"}
}