{
  "type": "Feature",
  "properties": {
    "iso:country": "GB",
    "wof:name": "IP3 0DP",
    "wof:placetype": "postalcode"
  },
  "geometry": {"coordinates":[1.160532,52.049377],"type":"Point"}
}
