{
  "type": "Feature",
  "properties": {
    "iso:country":"GB",
    "wof:name":"TN8 5QJ",
    "wof:placetype":"postalcode"
},
  "geometry": {"coordinates":[0.05604180344752,51.17898133793483],"type":"Point"}
}