{
  "type": "Feature",
  "properties": {
    "iso:country":"GB",
    "wof:name":"BN15 9UQ",
    "wof:placetype":"postalcode"
},
  "geometry": {"coordinates":[-0.34096135420708,50.82898253259064],"type":"Point"}
}