{
  "type": "Feature",
  "properties": {
    "date:inception_lower": "1981-01-01",
    "date:inception_upper": "1981-01-01",
    "iso:country": "GB",
    "wof:name": "ZE2 9XJ",
    "wof:placetype": "postalcode"
  },
  "geometry": {"coordinates":[-1.246438,60.188448],"type":"Point"}
}
