{
  "type": "Feature",
  "properties": {
    "iso:country":"GB",
    "wof:name":"ZE2 9XJ",
    "wof:placetype":"postalcode"
},
  "geometry": {"coordinates":[-1.24641239328678,60.18842884965095],"type":"Point"}
}