{
  "type": "Feature",
  "properties": {
    "iso:country": "GB",
    "wof:name": "ZE2 9XJ",
    "wof:placetype": "postalcode"
  },
  "geometry": {"coordinates":[-1.246412,60.188429],"type":"Point"}
}
