{
  "type": "Feature",
  "properties": {
    "iso:country":"GB",
    "wof:name":"BB3 2NB",
    "wof:placetype":"postalcode"
},
  "geometry": {"coordinates":[-2.45800233453191,53.67985993879545],"type":"Point"}
}