{
  "type": "Feature",
  "properties": {
    "date:inception_lower": "1980-01-01",
    "date:inception_upper": "1980-01-01",
    "iso:country": "GB",
    "wof:name": "BB3 2NB",
    "wof:placetype": "postalcode"
  },
  "geometry": {"coordinates":[-2.458,53.679876],"type":"Point"}
}
