{
  "type": "Feature",
  "properties": {
    "iso:country":"GB",
    "wof:name":"M12 5RP",
    "wof:placetype":"postalcode"
},
  "geometry": {"coordinates":[-2.19091274441629,53.45523792778528],"type":"Point"}
}