{
  "type": "Feature",
  "properties": {
    "iso:country": "GB",
    "wof:name": "M12 5RP",
    "wof:placetype": "postalcode"
  },
  "geometry": {"coordinates":[-2.190913,53.455238],"type":"Point"}
}
