{
  "type": "Feature",
  "properties": {
    "iso:country":"GB",
    "wof:name":"YO1 7FX",
    "wof:placetype":"postalcode"
},
  "geometry": {"coordinates":[-1.07970077677054,53.9611334783563],"type":"Point"}
}