{
  "type": "Feature",
  "properties": {
    "iso:country":"GB",
    "wof:name":"W3 7FE",
    "wof:placetype":"postalcode"
},
  "geometry": {"coordinates":[-0.25074448817009,51.50925227369501],"type":"Point"}
}