{
  "type": "Feature",
  "properties": {
    "iso:country":"GB",
    "wof:name":"EX31 3FP",
    "wof:placetype":"postalcode"
},
  "geometry": {"coordinates":[-4.1281037104118,51.07376451643576],"type":"Point"}
}