{
  "type": "Feature",
  "properties": {
    "iso:country":"GB",
    "wof:name":"TN12 5EA",
    "wof:placetype":"postalcode"
},
  "geometry": {"coordinates":[0.3816135592315,51.209579438709],"type":"Point"}
}