{
  "type": "Feature",
  "properties": {
    "iso:country": "GB",
    "wof:name": "TN12 5EA",
    "wof:placetype": "postalcode"
  },
  "geometry": {"coordinates":[0.381614,51.209579],"type":"Point"}
}
