{
  "type": "Feature",
  "properties": {
    "iso:country":"GB",
    "wof:name":"B4 6NP",
    "wof:placetype":"postalcode"
},
  "geometry": {"coordinates":[-1.89511997352928,52.48647866812468],"type":"Point"}
}