{
  "type": "Feature",
  "properties": {
    "iso:country":"GB",
    "wof:name":"NW10 0AS",
    "wof:placetype":"postalcode"
},
  "geometry": {"coordinates":[-0.25864186303119,51.5610038321171],"type":"Point"}
}