{
  "type": "Feature",
  "properties": {
    "iso:country":"GB",
    "wof:name":"EX16 5BN",
    "wof:placetype":"postalcode"
},
  "geometry": {"coordinates":[-3.50153807254111,50.90083205264168],"type":"Point"}
}