{
  "type": "Feature",
  "properties": {
    "iso:country":"GB",
    "wof:name":"BS26 2DX",
    "wof:placetype":"postalcode"
},
  "geometry": {"coordinates":[-2.81962642317568,51.28299576264684],"type":"Point"}
}