{
  "type": "Feature",
  "properties": {
    "iso:country": "GB",
    "wof:name": "SA18 1ND",
    "wof:placetype": "postalcode"
  },
  "geometry": {"coordinates":[-3.901742,51.801064],"type":"Point"}
}
