{
  "type": "Feature",
  "properties": {
    "date:inception_lower": "1980-01-01",
    "date:inception_upper": "1980-01-01",
    "iso:country": "GB",
    "wof:name": "SA18 1ND",
    "wof:placetype": "postalcode"
  },
  "geometry": {"coordinates":[-3.901742,51.801064],"type":"Point"}
}
