{
  "type": "Feature",
  "properties": {
    "iso:country":"GB",
    "wof:name":"SO40 4UU",
    "wof:placetype":"postalcode"
},
  "geometry": {"coordinates":[-1.44595338973492,50.89537492332714],"type":"Point"}
}