{
  "type": "Feature",
  "properties": {
    "iso:country": "GB",
    "wof:name": "PO17 5GU",
    "wof:placetype": "postalcode"
  },
  "geometry": {"coordinates":[-1.187515,50.904807],"type":"Point"}
}
