{
  "type": "Feature",
  "properties": {
    "date:inception_lower": "2012-08-01",
    "date:inception_upper": "2012-08-01",
    "iso:country": "GB",
    "wof:name": "PO17 5GU",
    "wof:placetype": "postalcode"
  },
  "geometry": {"coordinates":[-1.187515,50.904807],"type":"Point"}
}
