{
  "type": "Feature",
  "properties": {
    "iso:country":"GB",
    "wof:name":"PO17 5GU",
    "wof:placetype":"postalcode"
},
  "geometry": {"coordinates":[-1.18751497660165,50.90480690785481],"type":"Point"}
}