{
  "type": "Feature",
  "properties": {
    "iso:country":"GB",
    "wof:name":"GU16 6JF",
    "wof:placetype":"postalcode"
},
  "geometry": {"coordinates":[-0.73319807689492,51.29275625041973],"type":"Point"}
}