{
  "type": "Feature",
  "properties": {
    "iso:country": "GB",
    "wof:name": "SN7 8JG",
    "wof:placetype": "postalcode"
  },
  "geometry": {"coordinates":[-1.511985,51.650952],"type":"Point"}
}
