{
  "type": "Feature",
  "properties": {
    "iso:country":"GB",
    "wof:name":"DL1 1DN",
    "wof:placetype":"postalcode"
},
  "geometry": {"coordinates":[-1.52296499750727,54.52277922925849],"type":"Point"}
}