{
  "type": "Feature",
  "properties": {
    "iso:country":"GB",
    "wof:name":"SA62 6NF",
    "wof:placetype":"postalcode"
},
  "geometry": {"coordinates":[-5.09795642894255,51.88705815188433],"type":"Point"}
}