{
  "type": "Feature",
  "properties": {
    "iso:country":"GB",
    "wof:name":"TA19 0NE",
    "wof:placetype":"postalcode"
},
  "geometry": {"coordinates":[-2.84386649453401,50.95414744157851],"type":"Point"}
}