{
  "type": "Feature",
  "properties": {
    "iso:country":"GB",
    "wof:name":"NG18 4SX",
    "wof:placetype":"postalcode"
},
  "geometry": {"coordinates":[-1.18864363053142,53.12295785105854],"type":"Point"}
}