{
  "type": "Feature",
  "properties": {
    "iso:country":"GB",
    "wof:name":"GU14 6TQ",
    "wof:placetype":"postalcode"
},
  "geometry": {"coordinates":[-0.77024176488766,51.27294551571849],"type":"Point"}
}