{
  "type": "Feature",
  "properties": {
    "date:inception_lower":"2000-12-01",
    "date:inception_upper":"2000-12-31",
    "iso:country":"GB",
    "wof:name":"GU14 6TQ",
    "wof:placetype":"postalcode"
},
  "geometry": {"coordinates":[-0.770224,51.272944],"type":"Point"}
}