{
  "type": "Feature",
  "properties": {
    "iso:country": "GB",
    "wof:name": "HD2 2TH",
    "wof:placetype": "postalcode"
  },
  "geometry": {"coordinates":[-1.789594,53.660248],"type":"Point"}
}
