{
  "type": "Feature",
  "properties": {
    "date:inception_lower": "1999-06-01",
    "date:inception_upper": "1999-06-01",
    "iso:country": "GB",
    "wof:name": "NP23 6QN",
    "wof:placetype": "postalcode"
  },
  "geometry": {"coordinates":[-3.224633,51.779695],"type":"Point"}
}
