{
  "type": "Feature",
  "properties": {
    "date:inception_lower": "1980-01-01",
    "date:inception_upper": "1980-01-01",
    "iso:country": "GB",
    "wof:name": "HA0 2LR",
    "wof:placetype": "postalcode"
  },
  "geometry": {"coordinates":[-0.317433,51.555873],"type":"Point"}
}
