{
  "type": "Feature",
  "properties": {
    "iso:country":"GB",
    "wof:name":"HD3 4BL",
    "wof:placetype":"postalcode"
},
  "geometry": {"coordinates":[-1.81405253102105,53.64878353593532],"type":"Point"}
}