{
  "type": "Feature",
  "properties": {
    "date:inception_lower": "1980-01-01",
    "date:inception_upper": "1980-01-01",
    "iso:country": "GB",
    "wof:name": "HD3 4BL",
    "wof:placetype": "postalcode"
  },
  "geometry": {"coordinates":[-1.814052,53.648784],"type":"Point"}
}
