{
  "type": "Feature",
  "properties": {
    "date:inception_lower": "2024-06-01",
    "date:inception_upper": "2024-06-01",
    "iso:country": "GB",
    "wof:name": "PO21 3US",
    "wof:placetype": "postalcode"
  },
  "geometry": {"coordinates":[-0.727624,50.786688],"type":"Point"}
}
