{
  "type": "Feature",
  "properties": {
    "iso:country":"GB",
    "wof:name":"WS10 9EG",
    "wof:placetype":"postalcode"
},
  "geometry": {"coordinates":[-2.01926323246342,52.5548914616412],"type":"Point"}
}