{
  "type": "Feature",
  "properties": {
    "iso:country":"GB",
    "wof:name":"W1F 0LN",
    "wof:placetype":"postalcode"
},
  "geometry": {"coordinates":[-0.13612643386649,51.51302620174908],"type":"Point"}
}