{
  "type": "Feature",
  "properties": {
    "iso:country":"GB",
    "wof:name":"SL9 8AY",
    "wof:placetype":"postalcode"
},
  "geometry": {"coordinates":[-0.55046456307508,51.58188530550336],"type":"Point"}
}