{
  "type": "Feature",
  "properties": {
    "date:inception_lower": "2005-10-01",
    "date:inception_upper": "2005-10-01",
    "iso:country": "GB",
    "wof:name": "NG17 9LJ",
    "wof:placetype": "postalcode"
  },
  "geometry": {"coordinates":[-1.270016,53.092588],"type":"Point"}
}
