{
  "type": "Feature",
  "properties": {
    "iso:country":"GB",
    "wof:name":"NG17 9LJ",
    "wof:placetype":"postalcode"
},
  "geometry": {"coordinates":[-1.27001580590282,53.09258848937208],"type":"Point"}
}