{
  "type": "Feature",
  "properties": {
    "date:inception_lower": "1980-01-01",
    "date:inception_upper": "1980-01-01",
    "iso:country": "GB",
    "wof:name": "WR9 0JG",
    "wof:placetype": "postalcode"
  },
  "geometry": {"coordinates":[-2.230068,52.281178],"type":"Point"}
}
