{
  "type": "Feature",
  "properties": {
    "iso:country": "GB",
    "wof:name": "PL20 7LA",
    "wof:placetype": "postalcode"
  },
  "geometry": {"coordinates":[-4.168342,50.455172],"type":"Point"}
}
