{
  "type": "Feature",
  "properties": {
    "iso:country":"GB",
    "wof:name":"PL20 7LA",
    "wof:placetype":"postalcode"
},
  "geometry": {"coordinates":[-4.16834221783561,50.45517169921468],"type":"Point"}
}