{
  "type": "Feature",
  "properties": {
    "iso:country": "GB",
    "wof:name": "YO61 4UD",
    "wof:placetype": "postalcode"
  },
  "geometry": {"coordinates":[-1.142021,54.128131],"type":"Point"}
}
