{
  "type": "Feature",
  "properties": {
    "date:inception_lower":"1999-06-01",
    "date:inception_upper":"1999-06-30",
    "iso:country":"GB",
    "wof:name":"WA4 5RL",
    "wof:placetype":"postalcode"
},
  "geometry": {"coordinates":[-2.573775,53.341833],"type":"Point"}
}