{
  "type": "Feature",
  "properties": {
    "iso:country": "GB",
    "wof:name": "WA4 5RL",
    "wof:placetype": "postalcode"
  },
  "geometry": {"coordinates":[-2.573775,53.341833],"type":"Point"}
}
