{
  "type": "Feature",
  "properties": {
    "iso:country":"GB",
    "wof:name":"DL17 9ES",
    "wof:placetype":"postalcode"
},
  "geometry": {"coordinates":[-1.52122816892965,54.70019947997361],"type":"Point"}
}