{
  "type": "Feature",
  "properties": {
    "date:inception_lower":"1991-01-01",
    "date:inception_upper":"1991-01-31",
    "iso:country":"GB",
    "wof:name":"ST21 6SW",
    "wof:placetype":"postalcode"
},
  "geometry": {"coordinates":[-2.244668,52.857716],"type":"Point"}
}