{
  "type": "Feature",
  "properties": {
    "iso:country": "GB",
    "wof:name": "ST21 6SW",
    "wof:placetype": "postalcode"
  },
  "geometry": {"coordinates":[-2.244668,52.857716],"type":"Point"}
}
