{
  "type": "Feature",
  "properties": {
    "iso:country":"GB",
    "wof:name":"ST21 6SW",
    "wof:placetype":"postalcode"
},
  "geometry": {"coordinates":[-2.24466827610867,52.85771625011353],"type":"Point"}
}