{
  "type": "Feature",
  "properties": {
    "date:inception_lower": "1980-01-01",
    "date:inception_upper": "1980-01-01",
    "iso:country": "GB",
    "wof:name": "SG7 5AF",
    "wof:placetype": "postalcode"
  },
  "geometry": {"coordinates":[-0.190772,51.991022],"type":"Point"}
}
