{
  "type": "Feature",
  "properties": {
    "iso:country":"GB",
    "wof:name":"SL4 1AF",
    "wof:placetype":"postalcode"
},
  "geometry": {"coordinates":[-0.60967075402116,51.4814863789233],"type":"Point"}
}