{
  "type": "Feature",
  "properties": {
    "iso:country": "GB",
    "wof:name": "SL4 1AF",
    "wof:placetype": "postalcode"
  },
  "geometry": {"coordinates":[-0.609671,51.481486],"type":"Point"}
}
