{
  "type": "Feature",
  "properties": {
    "date:inception_lower": "1996-12-01",
    "date:inception_upper": "1996-12-01",
    "iso:country": "GB",
    "wof:name": "L69 3GB",
    "wof:placetype": "postalcode"
  },
  "geometry": {"coordinates":[-2.967397,53.406896],"type":"Point"}
}
