{
  "type": "Feature",
  "properties": {
    "iso:country":"GB",
    "wof:name":"G64 3LW",
    "wof:placetype":"postalcode"
},
  "geometry": {"coordinates":[-4.22116241493179,55.91771295884503],"type":"Point"}
}