{
  "type": "Feature",
  "properties": {
    "iso:country":"GB",
    "wof:name":"GU9 8BT",
    "wof:placetype":"postalcode"
},
  "geometry": {"coordinates":[-0.77954410565102,51.21345087517908],"type":"Point"}
}