{
  "type": "Feature",
  "properties": {
    "iso:country":"GB",
    "wof:name":"TN6 1SN",
    "wof:placetype":"postalcode"
},
  "geometry": {"coordinates":[0.14997826021031,51.0642904233707],"type":"Point"}
}