{
  "type": "Feature",
  "properties": {
    "date:inception_lower": "1980-01-01",
    "date:inception_upper": "1980-01-01",
    "iso:country": "GB",
    "wof:name": "TN6 1SN",
    "wof:placetype": "postalcode"
  },
  "geometry": {"coordinates":[0.149993,51.064314],"type":"Point"}
}
