{
  "type": "Feature",
  "properties": {
    "iso:country":"GB",
    "wof:name":"IP27 0TY",
    "wof:placetype":"postalcode"
},
  "geometry": {"coordinates":[0.63566477897072,52.44384383817007],"type":"Point"}
}