{
  "type": "Feature",
  "properties": {
    "iso:country": "GB",
    "wof:name": "IP27 0TY",
    "wof:placetype": "postalcode"
  },
  "geometry": {"coordinates":[0.635665,52.443844],"type":"Point"}
}
