{
  "type": "Feature",
  "properties": {
    "date:inception_lower":"2009-08-01",
    "date:inception_upper":"2009-08-31",
    "iso:country":"GB",
    "wof:name":"IP27 0TY",
    "wof:placetype":"postalcode"
},
  "geometry": {"coordinates":[0.635665,52.443844],"type":"Point"}
}