{
  "type": "Feature",
  "properties": {
    "iso:country":"GB",
    "wof:name":"BA2 4NF",
    "wof:placetype":"postalcode"
},
  "geometry": {"coordinates":[-2.35074093468494,51.37412481184902],"type":"Point"}
}