{
  "type": "Feature",
  "properties": {
    "iso:country":"GB",
    "wof:name":"TR2 5AQ",
    "wof:placetype":"postalcode"
},
  "geometry": {"coordinates":[-5.01254235614011,50.1598224028281],"type":"Point"}
}