{
  "type": "Feature",
  "properties": {
    "iso:country":"GB",
    "wof:name":"CT13 9AF",
    "wof:placetype":"postalcode"
},
  "geometry": {"coordinates":[1.33833469168906,51.27479927386111],"type":"Point"}
}