{
  "type": "Feature",
  "properties": {
    "iso:country": "GB",
    "wof:name": "NG14 7HA",
    "wof:placetype": "postalcode"
  },
  "geometry": {"coordinates":[-0.969139,53.031123],"type":"Point"}
}
