{
  "type": "Feature",
  "properties": {
    "iso:country":"GB",
    "wof:name":"NG14 7HA",
    "wof:placetype":"postalcode"
},
  "geometry": {"coordinates":[-0.96913861155836,53.03112286824064],"type":"Point"}
}