{
  "type": "Feature",
  "properties": {
    "date:inception_lower": "1980-01-01",
    "date:inception_upper": "1980-01-01",
    "iso:country": "GB",
    "wof:name": "NG14 7HA",
    "wof:placetype": "postalcode"
  },
  "geometry": {"coordinates":[-0.969139,53.031123],"type":"Point"}
}
