{
  "type": "Feature",
  "properties": {
    "iso:country":"GB",
    "wof:name":"BR8 7AY",
    "wof:placetype":"postalcode"
},
  "geometry": {"coordinates":[0.17472298679057,51.39897579884095],"type":"Point"}
}