{
  "type": "Feature",
  "properties": {
    "iso:country": "GB",
    "wof:name": "BR8 7AY",
    "wof:placetype": "postalcode"
  },
  "geometry": {"coordinates":[0.174555,51.399123],"type":"Point"}
}
