{
  "type": "Feature",
  "properties": {
    "date:inception_lower": "1990-07-01",
    "date:inception_upper": "1990-07-01",
    "iso:country": "GB",
    "wof:name": "GL10 2QP",
    "wof:placetype": "postalcode"
  },
  "geometry": {"coordinates":[-2.284721,51.747195],"type":"Point"}
}
