{
  "type": "Feature",
  "properties": {
    "iso:country":"GB",
    "wof:name":"KT8 2LJ",
    "wof:placetype":"postalcode"
},
  "geometry": {"coordinates":[-0.37037938475571,51.39690754264951],"type":"Point"}
}