{
  "type": "Feature",
  "properties": {
    "iso:country":"GB",
    "wof:name":"S44 6PU",
    "wof:placetype":"postalcode"
},
  "geometry": {"coordinates":[-1.2999211753873,53.22713727535441],"type":"Point"}
}