{
  "type": "Feature",
  "properties": {
    "iso:country": "GB",
    "wof:name": "S44 6PU",
    "wof:placetype": "postalcode"
  },
  "geometry": {"coordinates":[-1.29992,53.227138],"type":"Point"}
}
