{
  "type": "Feature",
  "properties": {
    "iso:country":"GB",
    "wof:name":"EX8 1QL",
    "wof:placetype":"postalcode"
},
  "geometry": {"coordinates":[-3.4081781908785,50.62421559998585],"type":"Point"}
}