{
  "type": "Feature",
  "properties": {
    "iso:country": "GB",
    "wof:name": "EX8 1QL",
    "wof:placetype": "postalcode"
  },
  "geometry": {"coordinates":[-3.408178,50.624216],"type":"Point"}
}
