{
  "type": "Feature",
  "properties": {
    "iso:country":"GB",
    "wof:name":"LE4 1EP",
    "wof:placetype":"postalcode"
},
  "geometry": {"coordinates":[-1.16796602987344,52.67557484705515],"type":"Point"}
}