{
  "type": "Feature",
  "properties": {
    "date:inception_lower":"1995-12-01",
    "date:inception_upper":"1995-12-31",
    "iso:country":"GB",
    "wof:name":"NE24 4RT",
    "wof:placetype":"postalcode"
},
  "geometry": {"coordinates":[-1.553333,55.131452],"type":"Point"}
}