{
  "type": "Feature",
  "properties": {
    "date:inception_lower": "1995-12-01",
    "date:inception_upper": "1995-12-01",
    "iso:country": "GB",
    "wof:name": "NG19 9SN",
    "wof:placetype": "postalcode"
  },
  "geometry": {"coordinates":[-1.171924,53.168742],"type":"Point"}
}
