{
  "type": "Feature",
  "properties": {
    "iso:country": "GB",
    "wof:name": "TS22 5LT",
    "wof:placetype": "postalcode"
  },
  "geometry": {"coordinates":[-1.300618,54.621939],"type":"Point"}
}
