{
  "type": "Feature",
  "properties": {
    "iso:country":"GB",
    "wof:name":"TS22 5LT",
    "wof:placetype":"postalcode"
},
  "geometry": {"coordinates":[-1.30061784748128,54.62193949379981],"type":"Point"}
}