{
  "type": "Feature",
  "properties": {
    "date:inception_lower": "2002-12-01",
    "date:inception_upper": "2002-12-01",
    "iso:country": "GB",
    "wof:name": "YO25 5PD",
    "wof:placetype": "postalcode"
  },
  "geometry": {"coordinates":[-0.425434,54.002745],"type":"Point"}
}
