{
  "type": "Feature",
  "properties": {
    "iso:country":"GB",
    "wof:name":"PO30 1SG",
    "wof:placetype":"postalcode"
},
  "geometry": {"coordinates":[-1.29441648992605,50.69964124723081],"type":"Point"}
}