{
  "type": "Feature",
  "properties": {
    "date:inception_lower": "1980-01-01",
    "date:inception_upper": "1980-01-01",
    "iso:country": "GB",
    "wof:name": "FY5 1LP",
    "wof:placetype": "postalcode"
  },
  "geometry": {"coordinates":[-3.046263,53.889999],"type":"Point"}
}
