{
  "type": "Feature",
  "properties": {
    "iso:country":"GB",
    "wof:name":"IP2 0AD",
    "wof:placetype":"postalcode"
},
  "geometry": {"coordinates":[1.13909898386117,52.05222574633402],"type":"Point"}
}