{
  "type": "Feature",
  "properties": {
    "iso:country":"GB",
    "wof:name":"S11 8XJ",
    "wof:placetype":"postalcode"
},
  "geometry": {"coordinates":[-1.49973667159671,53.36666051629927],"type":"Point"}
}