{
  "type": "Feature",
  "properties": {
    "iso:country":"GB",
    "wof:name":"LE65 2QN",
    "wof:placetype":"postalcode"
},
  "geometry": {"coordinates":[-1.47745035690273,52.75095917498609],"type":"Point"}
}