{
  "type": "Feature",
  "properties": {
    "iso:country":"GB",
    "wof:name":"OL12 7LW",
    "wof:placetype":"postalcode"
},
  "geometry": {"coordinates":[-2.18792742169799,53.62795394038103],"type":"Point"}
}