{
  "type": "Feature",
  "properties": {
    "iso:country": "GB",
    "wof:name": "OL12 7LW",
    "wof:placetype": "postalcode"
  },
  "geometry": {"coordinates":[-2.187927,53.627954],"type":"Point"}
}
