{
  "type": "Feature",
  "properties": {
    "date:inception_lower": "1999-06-01",
    "date:inception_upper": "1999-06-01",
    "iso:country": "GB",
    "wof:name": "OL12 7LW",
    "wof:placetype": "postalcode"
  },
  "geometry": {"coordinates":[-2.187927,53.627954],"type":"Point"}
}
