{
  "type": "Feature",
  "properties": {
    "iso:country": "GB",
    "wof:name": "DN32 7FE",
    "wof:placetype": "postalcode"
  },
  "geometry": {"coordinates":[-0.072733,53.569129],"type":"Point"}
}
