{
  "type": "Feature",
  "properties": {
    "date:inception_lower":"1992-08-01",
    "date:inception_upper":"1992-08-31",
    "iso:country":"GB",
    "wof:name":"BH20 5BZ",
    "wof:placetype":"postalcode"
},
  "geometry": {"coordinates":[-2.107494,50.670835],"type":"Point"}
}