{
  "type": "Feature",
  "properties": {
    "iso:country":"GB",
    "wof:name":"ME15 9YE",
    "wof:placetype":"postalcode"
},
  "geometry": {"coordinates":[0.56089086587782,51.23406828343632],"type":"Point"}
}