{
  "type": "Feature",
  "properties": {
    "iso:country":"GB",
    "wof:name":"HR6 9PX",
    "wof:placetype":"postalcode"
},
  "geometry": {"coordinates":[-2.80696476275188,52.26668140212409],"type":"Point"}
}