{
  "type": "Feature",
  "properties": {
    "date:inception_lower":"1980-01-01",
    "date:inception_upper":"1980-01-31",
    "iso:country":"GB",
    "wof:name":"HR6 9PX",
    "wof:placetype":"postalcode"
},
  "geometry": {"coordinates":[-2.806965,52.266681],"type":"Point"}
}