{
  "type": "Feature",
  "properties": {
    "iso:country": "GB",
    "wof:name": "CW1 2LL",
    "wof:placetype": "postalcode"
  },
  "geometry": {"coordinates":[-2.444294,53.097544],"type":"Point"}
}
