{
  "type": "Feature",
  "properties": {
    "iso:country":"GB",
    "wof:name":"CW1 2LL",
    "wof:placetype":"postalcode"
},
  "geometry": {"coordinates":[-2.44409897514762,53.09747463994977],"type":"Point"}
}