{
  "type": "Feature",
  "properties": {
    "date:inception_lower": "2000-10-01",
    "date:inception_upper": "2000-10-01",
    "iso:country": "GB",
    "wof:name": "WD25 9SP",
    "wof:placetype": "postalcode"
  },
  "geometry": {"coordinates":[-0.380629,51.686149],"type":"Point"}
}
