{
  "type": "Feature",
  "properties": {
    "iso:country": "GB",
    "wof:name": "WD25 9SP",
    "wof:placetype": "postalcode"
  },
  "geometry": {"coordinates":[-0.380629,51.686149],"type":"Point"}
}
