{
  "type": "Feature",
  "properties": {
    "iso:country":"GB",
    "wof:name":"SW1X 8JJ",
    "wof:placetype":"postalcode"
},
  "geometry": {"coordinates":[-0.15602837781364,51.49877293350882],"type":"Point"}
}