{
  "type": "Feature",
  "properties": {
    "date:inception_lower":"1995-01-01",
    "date:inception_upper":"1995-01-31",
    "iso:country":"GB",
    "wof:name":"TW6 3RN",
    "wof:placetype":"postalcode"
},
  "geometry": {"coordinates":[-0.470691,51.461026],"type":"Point"}
}