{
  "type": "Feature",
  "properties": {
    "iso:country":"GB",
    "wof:name":"TW6 3RN",
    "wof:placetype":"postalcode"
},
  "geometry": {"coordinates":[-0.47069058338975,51.46102561380637],"type":"Point"}
}