{
  "type": "Feature",
  "properties": {
    "iso:country":"GB",
    "wof:name":"CV6 4GN",
    "wof:placetype":"postalcode"
},
  "geometry": {"coordinates":[-1.51979955902256,52.44908788438982],"type":"Point"}
}