{
  "type": "Feature",
  "properties": {
    "iso:country": "GB",
    "wof:name": "BN6 9BW",
    "wof:placetype": "postalcode"
  },
  "geometry": {"coordinates":[-0.199566,50.933929],"type":"Point"}
}
