{
  "type": "Feature",
  "properties": {
    "iso:country":"GB",
    "wof:name":"BN6 9BW",
    "wof:placetype":"postalcode"
},
  "geometry": {"coordinates":[-0.19959307890857,50.93393423402974],"type":"Point"}
}