{
  "type": "Feature",
  "properties": {
    "iso:country":"GB",
    "wof:name":"SE4 2AG",
    "wof:placetype":"postalcode"
},
  "geometry": {"coordinates":[-0.03604376640272,51.45582728822826],"type":"Point"}
}