{
  "type": "Feature",
  "properties": {
    "iso:country": "GB",
    "wof:name": "HP22 0AF",
    "wof:placetype": "postalcode"
  },
  "geometry": {"coordinates":[-0.729956,51.804232],"type":"Point"}
}
