{
  "type": "Feature",
  "properties": {
    "iso:country": "GB",
    "wof:name": "RG20 8AF",
    "wof:placetype": "postalcode"
  },
  "geometry": {"coordinates":[-1.351793,51.422287],"type":"Point"}
}
