{
  "type": "Feature",
  "properties": {
    "iso:country":"GB",
    "wof:name":"NG8 4NQ",
    "wof:placetype":"postalcode"
},
  "geometry": {"coordinates":[-1.22030614338589,52.96266487347852],"type":"Point"}
}