{
  "type": "Feature",
  "properties": {
    "iso:country":"GB",
    "wof:name":"KA5 6QA",
    "wof:placetype":"postalcode"
},
  "geometry": {"coordinates":[-4.32249931411911,55.50118171269769],"type":"Point"}
}