{
  "type": "Feature",
  "properties": {
    "iso:country":"GB",
    "wof:name":"KY4 0HJ",
    "wof:placetype":"postalcode"
},
  "geometry": {"coordinates":[-3.36912428420226,56.13921992977495],"type":"Point"}
}