{
  "type": "Feature",
  "properties": {
    "date:inception_lower":"1980-01-01",
    "date:inception_upper":"1980-01-31",
    "iso:country":"GB",
    "wof:name":"FY8 1DY",
    "wof:placetype":"postalcode"
},
  "geometry": {"coordinates":[-3.003998,53.740902],"type":"Point"}
}