{
  "type": "Feature",
  "properties": {
    "iso:country":"GB",
    "wof:name":"ML6 6TJ",
    "wof:placetype":"postalcode"
},
  "geometry": {"coordinates":[-3.98562752269569,55.87804290470611],"type":"Point"}
}