{
  "type": "Feature",
  "properties": {
    "iso:country": "GB",
    "wof:name": "ML6 6TJ",
    "wof:placetype": "postalcode"
  },
  "geometry": {"coordinates":[-3.985627,55.878043],"type":"Point"}
}
