{
  "type": "Feature",
  "properties": {
    "date:inception_lower": "1984-11-01",
    "date:inception_upper": "1984-11-01",
    "iso:country": "GB",
    "wof:name": "ML6 6TJ",
    "wof:placetype": "postalcode"
  },
  "geometry": {"coordinates":[-3.985627,55.878043],"type":"Point"}
}
