{
  "type": "Feature",
  "properties": {
    "iso:country":"GB",
    "wof:name":"LE5 6PR",
    "wof:placetype":"postalcode"
},
  "geometry": {"coordinates":[-1.05856486519582,52.63004031161937],"type":"Point"}
}