{
  "type": "Feature",
  "properties": {
    "iso:country": "GB",
    "wof:name": "LE5 6PR",
    "wof:placetype": "postalcode"
  },
  "geometry": {"coordinates":[-1.058565,52.63004],"type":"Point"}
}
