{
  "type": "Feature",
  "properties": {
    "date:inception_lower": "1997-06-01",
    "date:inception_upper": "1997-06-01",
    "iso:country": "GB",
    "wof:name": "FY8 4NY",
    "wof:placetype": "postalcode"
  },
  "geometry": {"coordinates":[-2.933256,53.767729],"type":"Point"}
}
