{
  "type": "Feature",
  "properties": {
    "iso:country":"GB",
    "wof:name":"FY8 4NY",
    "wof:placetype":"postalcode"
},
  "geometry": {"coordinates":[-2.93325614355182,53.76772887945896],"type":"Point"}
}