{
  "type": "Feature",
  "properties": {
    "iso:country":"GB",
    "wof:name":"SL5 9DA",
    "wof:placetype":"postalcode"
},
  "geometry": {"coordinates":[-0.66885078416442,51.40260197701323],"type":"Point"}
}