{
  "type": "Feature",
  "properties": {
    "date:inception_lower": "1990-08-01",
    "date:inception_upper": "1990-08-01",
    "iso:country": "GB",
    "wof:name": "AB53 8DU",
    "wof:placetype": "postalcode"
  },
  "geometry": {"coordinates":[-2.398322,57.52796],"type":"Point"}
}
