{
  "type": "Feature",
  "properties": {
    "iso:country":"GB",
    "wof:name":"SM2 6QX",
    "wof:placetype":"postalcode"
},
  "geometry": {"coordinates":[-0.19742520107867,51.35390785887178],"type":"Point"}
}