{
  "type": "Feature",
  "properties": {
    "iso:country": "GB",
    "wof:name": "NN6 6AQ",
    "wof:placetype": "postalcode"
  },
  "geometry": {"coordinates":[-1.061938,52.390386],"type":"Point"}
}
