{
  "type": "Feature",
  "properties": {
    "date:inception_lower": "2018-12-01",
    "date:inception_upper": "2018-12-01",
    "iso:country": "GB",
    "wof:name": "NN6 6AQ",
    "wof:placetype": "postalcode"
  },
  "geometry": {"coordinates":[-1.061938,52.390386],"type":"Point"}
}
