{
  "type": "Feature",
  "properties": {
    "date:inception_lower": "1992-07-01",
    "date:inception_upper": "1992-07-01",
    "iso:country": "GB",
    "wof:name": "EH1 2ES",
    "wof:placetype": "postalcode"
  },
  "geometry": {"coordinates":[-3.204173,55.947555],"type":"Point"}
}
