{
  "type": "Feature",
  "properties": {
    "iso:country": "GB",
    "wof:name": "N1 3HE",
    "wof:placetype": "postalcode"
  },
  "geometry": {"coordinates":[-0.091241,51.541098],"type":"Point"}
}
