{
  "type": "Feature",
  "properties": {
    "iso:country":"GB",
    "wof:name":"N1 3HE",
    "wof:placetype":"postalcode"
},
  "geometry": {"coordinates":[-0.09124110054103,51.54109844168117],"type":"Point"}
}