{
  "type": "Feature",
  "properties": {
    "date:inception_lower": "1980-01-01",
    "date:inception_upper": "1980-01-01",
    "iso:country": "GB",
    "wof:name": "GL11 4PS",
    "wof:placetype": "postalcode"
  },
  "geometry": {"coordinates":[-2.347279,51.679036],"type":"Point"}
}
