{
  "type": "Feature",
  "properties": {
    "iso:country": "GB",
    "wof:name": "WA14 1AG",
    "wof:placetype": "postalcode"
  },
  "geometry": {"coordinates":[-2.348407,53.389526],"type":"Point"}
}
