{
  "type": "Feature",
  "properties": {
    "iso:country":"GB",
    "wof:name":"WA14 1AG",
    "wof:placetype":"postalcode"
},
  "geometry": {"coordinates":[-2.34840713230803,53.38952623499115],"type":"Point"}
}