{
  "type": "Feature",
  "properties": {
    "date:inception_lower":"2014-11-01",
    "date:inception_upper":"2014-11-30",
    "iso:country":"GB",
    "wof:name":"WA14 1AG",
    "wof:placetype":"postalcode"
},
  "geometry": {"coordinates":[-2.348407,53.389526],"type":"Point"}
}