{
  "type": "Feature",
  "properties": {
    "date:inception_lower": "1996-12-01",
    "date:inception_upper": "1996-12-01",
    "iso:country": "GB",
    "wof:name": "CA11 0RR",
    "wof:placetype": "postalcode"
  },
  "geometry": {"coordinates":[-2.893371,54.644232],"type":"Point"}
}
