{
  "type": "Feature",
  "properties": {
    "iso:country": "GB",
    "wof:name": "CA11 0RR",
    "wof:placetype": "postalcode"
  },
  "geometry": {"coordinates":[-2.893368,54.644224],"type":"Point"}
}
