{
  "type": "Feature",
  "properties": {
    "iso:country":"GB",
    "wof:name":"CA11 0RR",
    "wof:placetype":"postalcode"
},
  "geometry": {"coordinates":[-2.89336781688781,54.64422434987037],"type":"Point"}
}