{
  "type": "Feature",
  "properties": {
    "iso:country":"GB",
    "wof:name":"ME4 6RH",
    "wof:placetype":"postalcode"
},
  "geometry": {"coordinates":[0.52000363223878,51.37859386100598],"type":"Point"}
}