{
  "type": "Feature",
  "properties": {
    "iso:country": "GB",
    "wof:name": "EX35 6JT",
    "wof:placetype": "postalcode"
  },
  "geometry": {"coordinates":[-3.847049,51.214735],"type":"Point"}
}
