{
  "type": "Feature",
  "properties": {
    "iso:country":"GB",
    "wof:name":"DL14 0HD",
    "wof:placetype":"postalcode"
},
  "geometry": {"coordinates":[-1.74608418803948,54.65271003982945],"type":"Point"}
}