{
  "type": "Feature",
  "properties": {
    "iso:country": "GB",
    "wof:name": "YO25 9FD",
    "wof:placetype": "postalcode"
  },
  "geometry": {"coordinates":[-0.666687,54.021735],"type":"Point"}
}
