{
  "type": "Feature",
  "properties": {
    "iso:country":"GB",
    "wof:name":"BN22 8DX",
    "wof:placetype":"postalcode"
},
  "geometry": {"coordinates":[0.29486438388922,50.77463137175961],"type":"Point"}
}