{
  "type": "Feature",
  "properties": {
    "date:inception_lower":"1981-06-01",
    "date:inception_upper":"1981-06-30",
    "iso:country":"GB",
    "wof:name":"BA3 3EU",
    "wof:placetype":"postalcode"
},
  "geometry": {"coordinates":[-2.461162,51.283869],"type":"Point"}
}