{
  "type": "Feature",
  "properties": {
    "iso:country": "GB",
    "wof:name": "BA3 3EU",
    "wof:placetype": "postalcode"
  },
  "geometry": {"coordinates":[-2.461162,51.283869],"type":"Point"}
}
