{
  "type": "Feature",
  "properties": {
    "iso:country": "GB",
    "wof:name": "GU8 4LL",
    "wof:placetype": "postalcode"
  },
  "geometry": {"coordinates":[-0.564726,51.118516],"type":"Point"}
}
