{
  "type": "Feature",
  "properties": {
    "iso:country": "GB",
    "wof:name": "CH46 1PL",
    "wof:placetype": "postalcode"
  },
  "geometry": {"coordinates":[-3.090563,53.41441],"type":"Point"}
}
