{
  "type": "Feature",
  "properties": {
    "date:inception_lower": "1999-06-01",
    "date:inception_upper": "1999-06-01",
    "iso:country": "GB",
    "wof:name": "CH41 6ES",
    "wof:placetype": "postalcode"
  },
  "geometry": {"coordinates":[-3.026043,53.391027],"type":"Point"}
}
