{
  "type": "Feature",
  "properties": {
    "date:inception_lower":"1980-01-01",
    "date:inception_upper":"1980-01-31",
    "iso:country":"GB",
    "wof:name":"CO15 2HD",
    "wof:placetype":"postalcode"
},
  "geometry": {"coordinates":[1.116258,51.774576],"type":"Point"}
}