{
  "type": "Feature",
  "properties": {
    "iso:country": "GB",
    "wof:name": "CO15 2HD",
    "wof:placetype": "postalcode"
  },
  "geometry": {"coordinates":[1.116258,51.774576],"type":"Point"}
}
