{
  "type": "Feature",
  "properties": {
    "date:inception_lower": "1980-01-01",
    "date:inception_upper": "1980-01-01",
    "iso:country": "GB",
    "wof:name": "DL3 0JZ",
    "wof:placetype": "postalcode"
  },
  "geometry": {"coordinates":[-1.57087,54.538814],"type":"Point"}
}
