{
  "type": "Feature",
  "properties": {
    "iso:country":"GB",
    "wof:name":"DL3 0JZ",
    "wof:placetype":"postalcode"
},
  "geometry": {"coordinates":[-1.57086064066092,54.53880251254722],"type":"Point"}
}