{
  "type": "Feature",
  "properties": {
    "iso:country":"GB",
    "wof:name":"SP6 1JF",
    "wof:placetype":"postalcode"
},
  "geometry": {"coordinates":[-1.79348034335768,50.92682845639658],"type":"Point"}
}