{
  "type": "Feature",
  "properties": {
    "iso:country":"GB",
    "wof:name":"IV15 9PJ",
    "wof:placetype":"postalcode"
},
  "geometry": {"coordinates":[-4.43684250337445,57.59649527740969],"type":"Point"}
}