{
  "type": "Feature",
  "properties": {
    "date:inception_lower":"1980-01-01",
    "date:inception_upper":"1980-01-31",
    "iso:country":"GB",
    "wof:name":"BH21 6RF",
    "wof:placetype":"postalcode"
},
  "geometry": {"coordinates":[-1.886043,50.854018],"type":"Point"}
}