{
  "type": "Feature",
  "properties": {
    "iso:country": "GB",
    "wof:name": "BH21 6RF",
    "wof:placetype": "postalcode"
  },
  "geometry": {"coordinates":[-1.886043,50.854018],"type":"Point"}
}
