{
  "type": "Feature",
  "properties": {
    "date:inception_lower": "2018-09-01",
    "date:inception_upper": "2018-09-01",
    "iso:country": "GB",
    "wof:name": "DN36 4BY",
    "wof:placetype": "postalcode"
  },
  "geometry": {"coordinates":[-0.074483,53.525602],"type":"Point"}
}
