{
  "type": "Feature",
  "properties": {
    "iso:country":"GB",
    "wof:name":"PA5 9LY",
    "wof:placetype":"postalcode"
},
  "geometry": {"coordinates":[-4.49676330271589,55.83236627199812],"type":"Point"}
}