{
  "type": "Feature",
  "properties": {
    "iso:country":"GB",
    "wof:name":"WA7 1BE",
    "wof:placetype":"postalcode"
},
  "geometry": {"coordinates":[-2.72893603716223,53.34148920802414],"type":"Point"}
}