{
  "type": "Feature",
  "properties": {
    "date:inception_lower": "1980-01-01",
    "date:inception_upper": "1980-01-01",
    "iso:country": "GB",
    "wof:name": "WA7 1BE",
    "wof:placetype": "postalcode"
  },
  "geometry": {"coordinates":[-2.728936,53.341489],"type":"Point"}
}
