{
  "type": "Feature",
  "properties": {
    "iso:country": "GB",
    "wof:name": "WA7 1BE",
    "wof:placetype": "postalcode"
  },
  "geometry": {"coordinates":[-2.728936,53.341489],"type":"Point"}
}
