{
  "type": "Feature",
  "properties": {
    "iso:country":"GB",
    "wof:name":"CA22 2QS",
    "wof:placetype":"postalcode"
},
  "geometry": {"coordinates":[-3.53142183432735,54.48574303281664],"type":"Point"}
}