{
  "type": "Feature",
  "properties": {
    "iso:country": "GB",
    "wof:name": "CA22 2QS",
    "wof:placetype": "postalcode"
  },
  "geometry": {"coordinates":[-3.531422,54.485743],"type":"Point"}
}
