{
  "type": "Feature",
  "properties": {
    "iso:country":"GB",
    "wof:name":"PA1 1SS",
    "wof:placetype":"postalcode"
},
  "geometry": {"coordinates":[-4.42046114764907,55.84190023906525],"type":"Point"}
}