{
  "type": "Feature",
  "properties": {
    "iso:country":"GB",
    "wof:name":"LN1 1HU",
    "wof:placetype":"postalcode"
},
  "geometry": {"coordinates":[-0.54376675571349,53.23241632379863],"type":"Point"}
}