{
  "type": "Feature",
  "properties": {
    "date:inception_lower": "1999-12-01",
    "date:inception_upper": "1999-12-01",
    "iso:country": "GB",
    "wof:name": "LS24 9UN",
    "wof:placetype": "postalcode"
  },
  "geometry": {"coordinates":[-1.25305,53.820118],"type":"Point"}
}
