{
  "type": "Feature",
  "properties": {
    "iso:country": "GB",
    "wof:name": "LS24 9UN",
    "wof:placetype": "postalcode"
  },
  "geometry": {"coordinates":[-1.253258,53.820092],"type":"Point"}
}
