{
  "type": "Feature",
  "properties": {
    "iso:country":"GB",
    "wof:name":"GU4 8HY",
    "wof:placetype":"postalcode"
},
  "geometry": {"coordinates":[-0.56519373370622,51.2140677364713],"type":"Point"}
}