{
  "type": "Feature",
  "properties": {
    "iso:country":"GB",
    "wof:name":"TN26 3LW",
    "wof:placetype":"postalcode"
},
  "geometry": {"coordinates":[0.71469944312569,51.10577048453649],"type":"Point"}
}