{
  "type": "Feature",
  "properties": {
    "iso:country":"GB",
    "wof:name":"NG19 7LY",
    "wof:placetype":"postalcode"
},
  "geometry": {"coordinates":[-1.23044806605282,53.15764586958277],"type":"Point"}
}