{
  "type": "Feature",
  "properties": {
    "iso:country":"GB",
    "wof:name":"B10 9QX",
    "wof:placetype":"postalcode"
},
  "geometry": {"coordinates":[-1.85807120289322,52.47193929586079],"type":"Point"}
}