{
  "type": "Feature",
  "properties": {
    "date:inception_lower": "1988-03-01",
    "date:inception_upper": "1988-03-01",
    "iso:country": "GB",
    "wof:name": "B10 9QX",
    "wof:placetype": "postalcode"
  },
  "geometry": {"coordinates":[-1.858071,52.471939],"type":"Point"}
}
