{
  "type": "Feature",
  "properties": {
    "iso:country": "GB",
    "wof:name": "TS9 6NG",
    "wof:placetype": "postalcode"
  },
  "geometry": {"coordinates":[-1.138788,54.488399],"type":"Point"}
}
