{
  "type": "Feature",
  "properties": {
    "iso:country":"GB",
    "wof:name":"TS9 6NG",
    "wof:placetype":"postalcode"
},
  "geometry": {"coordinates":[-1.13874325951056,54.4883452461742],"type":"Point"}
}