{
  "type": "Feature",
  "properties": {
    "date:inception_lower": "1980-01-01",
    "date:inception_upper": "1980-01-01",
    "iso:country": "GB",
    "wof:name": "G69 6RL",
    "wof:placetype": "postalcode"
  },
  "geometry": {"coordinates":[-4.117453,55.855085],"type":"Point"}
}
