{
  "type": "Feature",
  "properties": {
    "iso:country":"GB",
    "wof:name":"G69 6RL",
    "wof:placetype":"postalcode"
},
  "geometry": {"coordinates":[-4.11745276788636,55.85508472756676],"type":"Point"}
}