{
  "type": "Feature",
  "properties": {
    "iso:country": "GB",
    "wof:name": "G69 6RL",
    "wof:placetype": "postalcode"
  },
  "geometry": {"coordinates":[-4.117453,55.855085],"type":"Point"}
}
