{
  "type": "Feature",
  "properties": {
    "iso:country":"GB",
    "wof:name":"WS12 4JY",
    "wof:placetype":"postalcode"
},
  "geometry": {"coordinates":[-2.01618473496136,52.72336817236011],"type":"Point"}
}