{
  "type": "Feature",
  "properties": {
    "iso:country": "GB",
    "wof:name": "WS12 4JY",
    "wof:placetype": "postalcode"
  },
  "geometry": {"coordinates":[-2.016185,52.723368],"type":"Point"}
}
