{
  "type": "Feature",
  "properties": {
    "iso:country":"GB",
    "wof:name":"CA13 0PT",
    "wof:placetype":"postalcode"
},
  "geometry": {"coordinates":[-3.383853504648,54.70600285695902],"type":"Point"}
}