{
  "type": "Feature",
  "properties": {
    "iso:country": "GB",
    "wof:name": "HS2 0DB",
    "wof:placetype": "postalcode"
  },
  "geometry": {"coordinates":[-6.40811,58.219083],"type":"Point"}
}
