{
  "type": "Feature",
  "properties": {
    "iso:country":"GB",
    "wof:name":"HS2 0DB",
    "wof:placetype":"postalcode"
},
  "geometry": {"coordinates":[-6.40721714794779,58.21834090484947],"type":"Point"}
}