{
  "type": "Feature",
  "properties": {
    "date:inception_lower":"1995-07-01",
    "date:inception_upper":"1995-07-31",
    "iso:country":"GB",
    "wof:name":"HS2 0DB",
    "wof:placetype":"postalcode"
},
  "geometry": {"coordinates":[-6.40811,58.219083],"type":"Point"}
}