{
  "type": "Feature",
  "properties": {
    "iso:country": "GB",
    "wof:name": "TQ12 1LB",
    "wof:placetype": "postalcode"
  },
  "geometry": {"coordinates":[-3.614637,50.527697],"type":"Point"}
}
