{
  "type": "Feature",
  "properties": {
    "iso:country":"GB",
    "wof:name":"TQ12 1LB",
    "wof:placetype":"postalcode"
},
  "geometry": {"coordinates":[-3.61463706902748,50.52769741048958],"type":"Point"}
}