{
  "type": "Feature",
  "properties": {
    "iso:country":"GB",
    "wof:name":"SY14 8DB",
    "wof:placetype":"postalcode"
},
  "geometry": {"coordinates":[-2.70124628796989,53.08703197169624],"type":"Point"}
}