{
  "type": "Feature",
  "properties": {
    "iso:country": "GB",
    "wof:name": "SY14 8DB",
    "wof:placetype": "postalcode"
  },
  "geometry": {"coordinates":[-2.700903,53.087059],"type":"Point"}
}
