{
  "type": "Feature",
  "properties": {
    "date:inception_lower":"1982-03-01",
    "date:inception_upper":"1982-03-31",
    "iso:country":"GB",
    "wof:name":"SY14 8DB",
    "wof:placetype":"postalcode"
},
  "geometry": {"coordinates":[-2.700903,53.087059],"type":"Point"}
}