{
  "type": "Feature",
  "properties": {
    "date:inception_lower":"1994-05-01",
    "date:inception_upper":"1994-05-31",
    "iso:country":"GB",
    "wof:name":"DY8 4DP",
    "wof:placetype":"postalcode"
},
  "geometry": {"coordinates":[-2.157795,52.46849],"type":"Point"}
}