{
  "type": "Feature",
  "properties": {
    "iso:country": "GB",
    "wof:name": "DY8 4DP",
    "wof:placetype": "postalcode"
  },
  "geometry": {"coordinates":[-2.157795,52.46849],"type":"Point"}
}
