{
  "type": "Feature",
  "properties": {
    "iso:country": "GB",
    "wof:name": "IP13 6UQ",
    "wof:placetype": "postalcode"
  },
  "geometry": {"coordinates":[1.255069,52.10422],"type":"Point"}
}
