{
  "type": "Feature",
  "properties": {
    "iso:country":"GB",
    "wof:name":"RH11 8SZ",
    "wof:placetype":"postalcode"
},
  "geometry": {"coordinates":[-0.19388549592621,51.11226977575458],"type":"Point"}
}