{
  "type": "Feature",
  "properties": {
    "iso:country":"GB",
    "wof:name":"BB1 2DA",
    "wof:placetype":"postalcode"
},
  "geometry": {"coordinates":[-2.44352303751604,53.74694818337409],"type":"Point"}
}