{
  "type": "Feature",
  "properties": {
    "iso:country":"GB",
    "wof:name":"WF5 8NJ",
    "wof:placetype":"postalcode"
},
  "geometry": {"coordinates":[-1.59126436108363,53.67646279138339],"type":"Point"}
}