{
  "type": "Feature",
  "properties": {
    "iso:country":"GB",
    "wof:name":"DY13 8SH",
    "wof:placetype":"postalcode"
},
  "geometry": {"coordinates":[-2.28417584438552,52.34289004522054],"type":"Point"}
}