{
  "type": "Feature",
  "properties": {
    "date:inception_lower": "1991-01-01",
    "date:inception_upper": "1991-01-01",
    "iso:country": "GB",
    "wof:name": "NW9 5LQ",
    "wof:placetype": "postalcode"
  },
  "geometry": {"coordinates":[-0.254018,51.603756],"type":"Point"}
}
