{
  "type": "Feature",
  "properties": {
    "iso:country":"GB",
    "wof:name":"NW9 5LQ",
    "wof:placetype":"postalcode"
},
  "geometry": {"coordinates":[-0.25401758185749,51.60375637107474],"type":"Point"}
}