{
  "type": "Feature",
  "properties": {
    "date:inception_lower": "2019-09-01",
    "date:inception_upper": "2019-09-01",
    "iso:country": "GB",
    "wof:name": "TA5 2FJ",
    "wof:placetype": "postalcode"
  },
  "geometry": {"coordinates":[-3.01145,51.110268],"type":"Point"}
}
