{
  "type": "Feature",
  "properties": {
    "date:inception_lower": "2007-05-01",
    "date:inception_upper": "2007-05-01",
    "iso:country": "GB",
    "wof:name": "HG5 0WF",
    "wof:placetype": "postalcode"
  },
  "geometry": {"coordinates":[-1.455923,54.014656],"type":"Point"}
}
