{
  "type": "Feature",
  "properties": {
    "date:inception_lower":"1994-05-01",
    "date:inception_upper":"1994-05-31",
    "iso:country":"GB",
    "wof:name":"DG16 5JJ",
    "wof:placetype":"postalcode"
},
  "geometry": {"coordinates":[-3.117412,55.005474],"type":"Point"}
}