{
  "type": "Feature",
  "properties": {
    "date:inception_lower": "2018-09-01",
    "date:inception_upper": "2018-09-01",
    "iso:country": "GB",
    "wof:name": "ME18 6AD",
    "wof:placetype": "postalcode"
  },
  "geometry": {"coordinates":[0.412984,51.227372],"type":"Point"}
}
