{
  "type": "Feature",
  "properties": {
    "iso:country":"GB",
    "wof:name":"BA6 9SX",
    "wof:placetype":"postalcode"
},
  "geometry": {"coordinates":[-2.79102337876475,51.15116177922595],"type":"Point"}
}