{
  "type": "Feature",
  "properties": {
    "iso:country": "GB",
    "wof:name": "BA6 9SX",
    "wof:placetype": "postalcode"
  },
  "geometry": {"coordinates":[-2.791023,51.151162],"type":"Point"}
}
