{
  "type": "Feature",
  "properties": {
    "iso:country": "GB",
    "wof:name": "NG5 6BW",
    "wof:placetype": "postalcode"
  },
  "geometry": {"coordinates":[-1.137379,53.000136],"type":"Point"}
}
