{
  "type": "Feature",
  "properties": {
    "iso:country": "GB",
    "wof:name": "BN18 0QX",
    "wof:placetype": "postalcode"
  },
  "geometry": {"coordinates":[-0.630113,50.863267],"type":"Point"}
}
