{
  "type": "Feature",
  "properties": {
    "date:inception_lower":"1980-01-01",
    "date:inception_upper":"1980-01-31",
    "iso:country":"GB",
    "wof:name":"TQ12 4HL",
    "wof:placetype":"postalcode"
},
  "geometry": {"coordinates":[-3.586721,50.531661],"type":"Point"}
}