{
  "type": "Feature",
  "properties": {
    "iso:country": "GB",
    "wof:name": "TQ12 4HL",
    "wof:placetype": "postalcode"
  },
  "geometry": {"coordinates":[-3.586721,50.531661],"type":"Point"}
}
