{
  "type": "Feature",
  "properties": {
    "iso:country": "GB",
    "wof:name": "BH21 2HH",
    "wof:placetype": "postalcode"
  },
  "geometry": {"coordinates":[-1.954447,50.808598],"type":"Point"}
}
