{
  "type": "Feature",
  "properties": {
    "iso:country":"GB",
    "wof:name":"CT4 6JS",
    "wof:placetype":"postalcode"
},
  "geometry": {"coordinates":[1.12720699387215,51.20545589762774],"type":"Point"}
}