{
  "type": "Feature",
  "properties": {
    "date:inception_lower":"1985-10-01",
    "date:inception_upper":"1985-10-31",
    "iso:country":"GB",
    "wof:name":"SK8 4JA",
    "wof:placetype":"postalcode"
},
  "geometry": {"coordinates":[-2.239529,53.391862],"type":"Point"}
}