{
  "type": "Feature",
  "properties": {
    "date:inception_lower": "2004-05-01",
    "date:inception_upper": "2004-05-01",
    "iso:country": "GB",
    "wof:name": "KT13 9SE",
    "wof:placetype": "postalcode"
  },
  "geometry": {"coordinates":[-0.432025,51.376149],"type":"Point"}
}
