{
  "type": "Feature",
  "properties": {
    "date:inception_lower":"1981-06-01",
    "date:inception_upper":"1981-06-30",
    "iso:country":"GB",
    "wof:name":"KT12 3TD",
    "wof:placetype":"postalcode"
},
  "geometry": {"coordinates":[-0.403873,51.384105],"type":"Point"}
}