{
  "type": "Feature",
  "properties": {
    "date:inception_lower": "1989-10-01",
    "date:inception_upper": "1989-10-01",
    "iso:country": "GB",
    "wof:name": "IV31 6TE",
    "wof:placetype": "postalcode"
  },
  "geometry": {"coordinates":[-3.303739,57.71619],"type":"Point"}
}
