{
  "type": "Feature",
  "properties": {
    "iso:country":"GB",
    "wof:name":"IV31 6TE",
    "wof:placetype":"postalcode"
},
  "geometry": {"coordinates":[-3.30373934408145,57.7161900703904],"type":"Point"}
}