{
  "type": "Feature",
  "properties": {
    "date:inception_lower": "1980-01-01",
    "date:inception_upper": "1980-01-01",
    "iso:country": "GB",
    "wof:name": "BS8 4EP",
    "wof:placetype": "postalcode"
  },
  "geometry": {"coordinates":[-2.617205,51.454525],"type":"Point"}
}
