{
  "type": "Feature",
  "properties": {
    "iso:country": "GB",
    "wof:name": "BS8 4EP",
    "wof:placetype": "postalcode"
  },
  "geometry": {"coordinates":[-2.617205,51.454525],"type":"Point"}
}
