{
  "type": "Feature",
  "properties": {
    "iso:country": "GB",
    "wof:name": "CO11 2FR",
    "wof:placetype": "postalcode"
  },
  "geometry": {"coordinates":[1.046503,51.936124],"type":"Point"}
}
