{
  "type": "Feature",
  "properties": {
    "date:inception_lower": "2019-08-01",
    "date:inception_upper": "2019-08-01",
    "iso:country": "GB",
    "wof:name": "CO11 2FR",
    "wof:placetype": "postalcode"
  },
  "geometry": {"coordinates":[1.048167,51.935559],"type":"Point"}
}
