{
  "type": "Feature",
  "properties": {
    "date:inception_lower": "2000-06-01",
    "date:inception_upper": "2000-06-01",
    "iso:country": "GB",
    "wof:name": "OX16 4QX",
    "wof:placetype": "postalcode"
  },
  "geometry": {"coordinates":[-1.322656,52.065607],"type":"Point"}
}
