{
  "type": "Feature",
  "properties": {
    "date:inception_lower":"1980-01-01",
    "date:inception_upper":"1980-01-31",
    "iso:country":"GB",
    "wof:name":"SK9 6BQ",
    "wof:placetype":"postalcode"
},
  "geometry": {"coordinates":[-2.251253,53.319632],"type":"Point"}
}