{
  "type": "Feature",
  "properties": {
    "iso:country":"GB",
    "wof:name":"SR7 8JT",
    "wof:placetype":"postalcode"
},
  "geometry": {"coordinates":[-1.37232536684863,54.83695348327741],"type":"Point"}
}