{
  "type": "Feature",
  "properties": {
    "iso:country":"GB",
    "wof:name":"CB7 5WJ",
    "wof:placetype":"postalcode"
},
  "geometry": {"coordinates":[0.33789513446664,52.33234838310587],"type":"Point"}
}