{
  "type": "Feature",
  "properties": {
    "iso:country":"GB",
    "wof:name":"M40 3ST",
    "wof:placetype":"postalcode"
},
  "geometry": {"coordinates":[-2.15998005897715,53.51497563380582],"type":"Point"}
}