{
  "type": "Feature",
  "properties": {
    "date:inception_lower": "1994-05-01",
    "date:inception_upper": "1994-05-01",
    "iso:country": "GB",
    "wof:name": "M40 3ST",
    "wof:placetype": "postalcode"
  },
  "geometry": {"coordinates":[-2.159949,53.515082],"type":"Point"}
}
