{
  "type": "Feature",
  "properties": {
    "iso:country": "GB",
    "wof:name": "WS1 1RY",
    "wof:placetype": "postalcode"
  },
  "geometry": {"coordinates":[-1.981597,52.583713],"type":"Point"}
}
