{
  "type": "Feature",
  "properties": {
    "iso:country":"GB",
    "wof:name":"CT11 9NP",
    "wof:placetype":"postalcode"
},
  "geometry": {"coordinates":[1.4109698312443,51.33104670229017],"type":"Point"}
}