{
  "type": "Feature",
  "properties": {
    "date:inception_lower": "1992-08-01",
    "date:inception_upper": "1992-08-01",
    "iso:country": "GB",
    "wof:name": "DE6 3LE",
    "wof:placetype": "postalcode"
  },
  "geometry": {"coordinates":[-1.599496,53.048209],"type":"Point"}
}
