{
  "type": "Feature",
  "properties": {
    "iso:country":"GB",
    "wof:name":"DE6 3LE",
    "wof:placetype":"postalcode"
},
  "geometry": {"coordinates":[-1.59949623426686,53.04820902124686],"type":"Point"}
}