{
  "type": "Feature",
  "properties": {
    "iso:country":"GB",
    "wof:name":"B29 5DH",
    "wof:placetype":"postalcode"
},
  "geometry": {"coordinates":[-1.9671103788238,52.43526849990891],"type":"Point"}
}