{
  "type": "Feature",
  "properties": {
    "iso:country": "GB",
    "wof:name": "NE33 3AP",
    "wof:placetype": "postalcode"
  },
  "geometry": {"coordinates":[-1.422185,54.990087],"type":"Point"}
}
