{
  "type": "Feature",
  "properties": {
    "iso:country": "GB",
    "wof:name": "B45 8QD",
    "wof:placetype": "postalcode"
  },
  "geometry": {"coordinates":[-1.990557,52.392746],"type":"Point"}
}
