{
  "type": "Feature",
  "properties": {
    "iso:country":"GB",
    "wof:name":"BS41 9LN",
    "wof:placetype":"postalcode"
},
  "geometry": {"coordinates":[-2.64620477341311,51.43206885663984],"type":"Point"}
}