{
  "type": "Feature",
  "properties": {
    "iso:country": "GB",
    "wof:name": "BS41 9LN",
    "wof:placetype": "postalcode"
  },
  "geometry": {"coordinates":[-2.646205,51.432069],"type":"Point"}
}
