{
  "type": "Feature",
  "properties": {
    "date:inception_lower": "1997-12-01",
    "date:inception_upper": "1997-12-01",
    "iso:country": "GB",
    "wof:name": "BS41 9LN",
    "wof:placetype": "postalcode"
  },
  "geometry": {"coordinates":[-2.646205,51.432069],"type":"Point"}
}
