{
  "type": "Feature",
  "properties": {
    "iso:country":"GB",
    "wof:name":"NN8 1DY",
    "wof:placetype":"postalcode"
},
  "geometry": {"coordinates":[-0.6873347007365,52.3060400498003],"type":"Point"}
}