{
  "type": "Feature",
  "properties": {
    "date:inception_lower": "2022-08-01",
    "date:inception_upper": "2022-08-01",
    "iso:country": "GB",
    "wof:name": "EX20 1YA",
    "wof:placetype": "postalcode"
  },
  "geometry": {"coordinates":[-4.004905,50.738896],"type":"Point"}
}
