{
  "type": "Feature",
  "properties": {
    "iso:country": "GB",
    "wof:name": "NE22 7BZ",
    "wof:placetype": "postalcode"
  },
  "geometry": {"coordinates":[-1.547596,55.143661],"type":"Point"}
}
