{
  "type": "Feature",
  "properties": {
    "iso:country":"GB",
    "wof:name":"ME2 3BY",
    "wof:placetype":"postalcode"
},
  "geometry": {"coordinates":[0.49865603009164,51.40274015772592],"type":"Point"}
}