{
  "type": "Feature",
  "properties": {
    "iso:country":"GB",
    "wof:name":"G41 1HL",
    "wof:placetype":"postalcode"
},
  "geometry": {"coordinates":[-4.277796946099,55.85297486755321],"type":"Point"}
}