{
  "type": "Feature",
  "properties": {
    "iso:country":"GB",
    "wof:name":"TN27 0PD",
    "wof:placetype":"postalcode"
},
  "geometry": {"coordinates":[0.75370024552206,51.17898832067957],"type":"Point"}
}