{
  "type": "Feature",
  "properties": {
    "date:inception_lower":"1980-01-01",
    "date:inception_upper":"1980-01-31",
    "iso:country":"GB",
    "wof:name":"TN27 0PD",
    "wof:placetype":"postalcode"
},
  "geometry": {"coordinates":[0.7537,51.178988],"type":"Point"}
}