{
  "type": "Feature",
  "properties": {
    "iso:country": "GB",
    "wof:name": "TN27 0PD",
    "wof:placetype": "postalcode"
  },
  "geometry": {"coordinates":[0.7537,51.178988],"type":"Point"}
}
