{
  "type": "Feature",
  "properties": {
    "iso:country":"GB",
    "wof:name":"SR4 6RU",
    "wof:placetype":"postalcode"
},
  "geometry": {"coordinates":[-1.41704378312879,54.90913122409491],"type":"Point"}
}