{
  "type": "Feature",
  "properties": {
    "iso:country":"GB",
    "wof:name":"FY4 5BY",
    "wof:placetype":"postalcode"
},
  "geometry": {"coordinates":[-3.02323533227721,53.79129912000084],"type":"Point"}
}