{
  "type": "Feature",
  "properties": {
    "date:inception_lower":"1984-10-01",
    "date:inception_upper":"1984-10-31",
    "iso:country":"GB",
    "wof:name":"FY4 5BY",
    "wof:placetype":"postalcode"
},
  "geometry": {"coordinates":[-3.023235,53.791299],"type":"Point"}
}