{
  "type": "Feature",
  "properties": {
    "iso:country":"GB",
    "wof:name":"DL15 9BW",
    "wof:placetype":"postalcode"
},
  "geometry": {"coordinates":[-1.74112152187308,54.71419523556349],"type":"Point"}
}