{
  "type": "Feature",
  "properties": {
    "iso:country": "GB",
    "wof:name": "DL15 9BW",
    "wof:placetype": "postalcode"
  },
  "geometry": {"coordinates":[-1.741121,54.714195],"type":"Point"}
}
