{
  "type": "Feature",
  "properties": {
    "iso:country": "GB",
    "wof:name": "BD11 1EW",
    "wof:placetype": "postalcode"
  },
  "geometry": {"coordinates":[-1.656297,53.755176],"type":"Point"}
}
