{
  "type": "Feature",
  "properties": {
    "date:inception_lower": "2020-01-01",
    "date:inception_upper": "2020-01-01",
    "iso:country": "GB",
    "wof:name": "BD11 1EW",
    "wof:placetype": "postalcode"
  },
  "geometry": {"coordinates":[-1.656539,53.755159],"type":"Point"}
}
