{
  "type": "Feature",
  "properties": {
    "iso:country": "GB",
    "wof:name": "CB3 9LN",
    "wof:placetype": "postalcode"
  },
  "geometry": {"coordinates":[0.095624,52.199986],"type":"Point"}
}
