{
  "type": "Feature",
  "properties": {
    "iso:country":"GB",
    "wof:name":"SE16 2QD",
    "wof:placetype":"postalcode"
},
  "geometry": {"coordinates":[-0.04755533521782,51.49199924914122],"type":"Point"}
}