{
  "type": "Feature",
  "properties": {
    "iso:country": "GB",
    "wof:name": "PO8 0HS",
    "wof:placetype": "postalcode"
  },
  "geometry": {"coordinates":[-0.997589,50.93217],"type":"Point"}
}
