{
  "type": "Feature",
  "properties": {
    "date:inception_lower": "1980-01-01",
    "date:inception_upper": "1980-01-01",
    "iso:country": "GB",
    "wof:name": "PO8 0HS",
    "wof:placetype": "postalcode"
  },
  "geometry": {"coordinates":[-0.997589,50.93217],"type":"Point"}
}
