{
  "type": "Feature",
  "properties": {
    "iso:country":"GB",
    "wof:name":"PO8 0HS",
    "wof:placetype":"postalcode"
},
  "geometry": {"coordinates":[-0.99758917251769,50.93217050467799],"type":"Point"}
}