{
  "type": "Feature",
  "properties": {
    "iso:country":"GB",
    "wof:name":"PA5 0EX",
    "wof:placetype":"postalcode"
},
  "geometry": {"coordinates":[-4.51805873622638,55.82581105493743],"type":"Point"}
}