{
  "type": "Feature",
  "properties": {
    "iso:country": "GB",
    "wof:name": "CM3 4QQ",
    "wof:placetype": "postalcode"
  },
  "geometry": {"coordinates":[0.581489,51.716227],"type":"Point"}
}
