{
  "type": "Feature",
  "properties": {
    "iso:country":"GB",
    "wof:name":"RM6 4LZ",
    "wof:placetype":"postalcode"
},
  "geometry": {"coordinates":[0.13019986376864,51.57113502350617],"type":"Point"}
}