{
  "type": "Feature",
  "properties": {
    "iso:country": "GB",
    "wof:name": "RM6 4LZ",
    "wof:placetype": "postalcode"
  },
  "geometry": {"coordinates":[0.1302,51.571135],"type":"Point"}
}
