{
  "type": "Feature",
  "properties": {
    "iso:country":"GB",
    "wof:name":"TR19 6BJ",
    "wof:placetype":"postalcode"
},
  "geometry": {"coordinates":[-5.57615892355474,50.06544688108742],"type":"Point"}
}