{
  "type": "Feature",
  "properties": {
    "iso:country": "GB",
    "wof:name": "SS17 7BG",
    "wof:placetype": "postalcode"
  },
  "geometry": {"coordinates":[0.439261,51.524757],"type":"Point"}
}
