{
  "type": "Feature",
  "properties": {
    "iso:country":"GB",
    "wof:name":"WV14 9NA",
    "wof:placetype":"postalcode"
},
  "geometry": {"coordinates":[-2.08974318735952,52.55182928158858],"type":"Point"}
}