{
  "type": "Feature",
  "properties": {
    "iso:country":"GB",
    "wof:name":"E3 4AH",
    "wof:placetype":"postalcode"
},
  "geometry": {"coordinates":[-0.02695060706531,51.51779600550095],"type":"Point"}
}