{
  "type": "Feature",
  "properties": {
    "iso:country": "GB",
    "wof:name": "E2 9FG",
    "wof:placetype": "postalcode"
  },
  "geometry": {"coordinates":[-0.057864,51.531479],"type":"Point"}
}
