{
  "type": "Feature",
  "properties": {
    "date:inception_lower": "2016-11-01",
    "date:inception_upper": "2016-11-01",
    "iso:country": "GB",
    "wof:name": "E2 9FG",
    "wof:placetype": "postalcode"
  },
  "geometry": {"coordinates":[-0.057864,51.531479],"type":"Point"}
}
