{
  "type": "Feature",
  "properties": {
    "iso:country":"GB",
    "wof:name":"ST3 7QS",
    "wof:placetype":"postalcode"
},
  "geometry": {"coordinates":[-2.08947126238065,52.96684930988262],"type":"Point"}
}