{
  "type": "Feature",
  "properties": {
    "iso:country":"GB",
    "wof:name":"EH6 6AF",
    "wof:placetype":"postalcode"
},
  "geometry": {"coordinates":[-3.17105589404942,55.97136228396862],"type":"Point"}
}