{
  "type": "Feature",
  "properties": {
    "iso:country":"GB",
    "wof:name":"CH62 7DQ",
    "wof:placetype":"postalcode"
},
  "geometry": {"coordinates":[-2.98157429294688,53.32875628768198],"type":"Point"}
}