{
  "type": "Feature",
  "properties": {
    "iso:country": "GB",
    "wof:name": "DL10 4EZ",
    "wof:placetype": "postalcode"
  },
  "geometry": {"coordinates":[-1.753543,54.405568],"type":"Point"}
}
