{
  "type": "Feature",
  "properties": {
    "iso:country":"GB",
    "wof:name":"ME18 5LA",
    "wof:placetype":"postalcode"
},
  "geometry": {"coordinates":[0.42782168083654,51.25862498393955],"type":"Point"}
}