{
  "type": "Feature",
  "properties": {
    "iso:country": "GB",
    "wof:name": "ME18 5LA",
    "wof:placetype": "postalcode"
  },
  "geometry": {"coordinates":[0.427822,51.258625],"type":"Point"}
}
