{
  "type": "Feature",
  "properties": {
    "iso:country":"GB",
    "wof:name":"SN13 8JN",
    "wof:placetype":"postalcode"
},
  "geometry": {"coordinates":[-2.24994467887282,51.41632041878141],"type":"Point"}
}