{
  "type": "Feature",
  "properties": {
    "date:inception_lower": "2006-07-01",
    "date:inception_upper": "2006-07-01",
    "iso:country": "GB",
    "wof:name": "SN13 8JN",
    "wof:placetype": "postalcode"
  },
  "geometry": {"coordinates":[-2.249945,51.41632],"type":"Point"}
}
