{
  "type": "Feature",
  "properties": {
    "iso:country":"GB",
    "wof:name":"SE6 3BU",
    "wof:placetype":"postalcode"
},
  "geometry": {"coordinates":[-0.02012928285456,51.43274499746244],"type":"Point"}
}