{
  "type": "Feature",
  "properties": {
    "date:inception_lower": "1980-01-01",
    "date:inception_upper": "1980-01-01",
    "iso:country": "GB",
    "wof:name": "LS12 5PE",
    "wof:placetype": "postalcode"
  },
  "geometry": {"coordinates":[-1.605741,53.783012],"type":"Point"}
}
