{
  "type": "Feature",
  "properties": {
    "iso:country": "GB",
    "wof:name": "PL19 9EZ",
    "wof:placetype": "postalcode"
  },
  "geometry": {"coordinates":[-4.140539,50.536716],"type":"Point"}
}
