{
  "type": "Feature",
  "properties": {
    "iso:country":"GB",
    "wof:name":"PL19 9EZ",
    "wof:placetype":"postalcode"
},
  "geometry": {"coordinates":[-4.14053883236547,50.53671553711202],"type":"Point"}
}