{
  "type": "Feature",
  "properties": {
    "iso:country":"GB",
    "wof:name":"SO22 4QJ",
    "wof:placetype":"postalcode"
},
  "geometry": {"coordinates":[-1.329335472618,51.05124933909457],"type":"Point"}
}