{
  "type": "Feature",
  "properties": {
    "date:inception_lower": "1990-02-01",
    "date:inception_upper": "1990-02-01",
    "iso:country": "GB",
    "wof:name": "EX15 1TF",
    "wof:placetype": "postalcode"
  },
  "geometry": {"coordinates":[-3.402465,50.855175],"type":"Point"}
}
