{
  "type": "Feature",
  "properties": {
    "iso:country": "GB",
    "wof:name": "NG34 0BQ",
    "wof:placetype": "postalcode"
  },
  "geometry": {"coordinates":[-0.381721,52.916978],"type":"Point"}
}
