{
  "type": "Feature",
  "properties": {
    "date:inception_lower": "1994-12-01",
    "date:inception_upper": "1994-12-01",
    "iso:country": "GB",
    "wof:name": "CO13 9AW",
    "wof:placetype": "postalcode"
  },
  "geometry": {"coordinates":[1.250755,51.837156],"type":"Point"}
}
