{
  "type": "Feature",
  "properties": {
    "iso:country":"GB",
    "wof:name":"CO13 9AW",
    "wof:placetype":"postalcode"
},
  "geometry": {"coordinates":[1.25075540035117,51.83715639899332],"type":"Point"}
}