{
  "type": "Feature",
  "properties": {
    "iso:country":"GB",
    "wof:name":"DY14 9SH",
    "wof:placetype":"postalcode"
},
  "geometry": {"coordinates":[-2.37817118976233,52.33528138474634],"type":"Point"}
}