{
  "type": "Feature",
  "properties": {
    "iso:country":"GB",
    "wof:name":"KA23 9DG",
    "wof:placetype":"postalcode"
},
  "geometry": {"coordinates":[-4.85009537102685,55.69229063189005],"type":"Point"}
}