{
  "type": "Feature",
  "properties": {
    "iso:country": "GB",
    "wof:name": "EN8 9XQ",
    "wof:placetype": "postalcode"
  },
  "geometry": {"coordinates":[-0.047642,51.703139],"type":"Point"}
}
