{
  "type": "Feature",
  "properties": {
    "date:inception_lower": "1987-04-01",
    "date:inception_upper": "1987-04-01",
    "iso:country": "GB",
    "wof:name": "EN8 9XQ",
    "wof:placetype": "postalcode"
  },
  "geometry": {"coordinates":[-0.047642,51.703139],"type":"Point"}
}
