{
  "type": "Feature",
  "properties": {
    "iso:country":"GB",
    "wof:name":"CW1 3DN",
    "wof:placetype":"postalcode"
},
  "geometry": {"coordinates":[-2.44956803282136,53.10350375481946],"type":"Point"}
}