{
  "type": "Feature",
  "properties": {
    "date:inception_lower": "1980-01-01",
    "date:inception_upper": "1980-01-01",
    "iso:country": "GB",
    "wof:name": "SM7 2QD",
    "wof:placetype": "postalcode"
  },
  "geometry": {"coordinates":[-0.203248,51.32657],"type":"Point"}
}
