{
  "type": "Feature",
  "properties": {
    "iso:country":"GB",
    "wof:name":"SM7 2QD",
    "wof:placetype":"postalcode"
},
  "geometry": {"coordinates":[-0.20324829648216,51.32656965591872],"type":"Point"}
}