{
  "type": "Feature",
  "properties": {
    "date:inception_lower": "1993-01-01",
    "date:inception_upper": "1993-01-01",
    "iso:country": "GB",
    "wof:name": "IP13 0NZ",
    "wof:placetype": "postalcode"
  },
  "geometry": {"coordinates":[1.394121,52.149017],"type":"Point"}
}
