{
  "type": "Feature",
  "properties": {
    "date:inception_lower": "1980-01-01",
    "date:inception_upper": "1980-01-01",
    "iso:country": "GB",
    "wof:name": "NE15 7AJ",
    "wof:placetype": "postalcode"
  },
  "geometry": {"coordinates":[-1.686792,54.980065],"type":"Point"}
}
