{
  "type": "Feature",
  "properties": {
    "iso:country":"GB",
    "wof:name":"NE15 7AJ",
    "wof:placetype":"postalcode"
},
  "geometry": {"coordinates":[-1.68679206804524,54.98006540814396],"type":"Point"}
}