{
  "type": "Feature",
  "properties": {
    "iso:country": "GB",
    "wof:name": "IG11 9DE",
    "wof:placetype": "postalcode"
  },
  "geometry": {"coordinates":[0.103605,51.549906],"type":"Point"}
}
