{
  "type": "Feature",
  "properties": {
    "date:inception_lower": "1999-06-01",
    "date:inception_upper": "1999-06-01",
    "iso:country": "GB",
    "wof:name": "NP26 4BG",
    "wof:placetype": "postalcode"
  },
  "geometry": {"coordinates":[-2.751969,51.591363],"type":"Point"}
}
