{
  "type": "Feature",
  "properties": {
    "iso:country": "GB",
    "wof:name": "RH13 9JQ",
    "wof:placetype": "postalcode"
  },
  "geometry": {"coordinates":[-0.350328,51.029532],"type":"Point"}
}
