{
  "type": "Feature",
  "properties": {
    "date:inception_lower": "2020-04-01",
    "date:inception_upper": "2020-04-01",
    "iso:country": "GB",
    "wof:name": "RH13 9JQ",
    "wof:placetype": "postalcode"
  },
  "geometry": {"coordinates":[-0.350328,51.029532],"type":"Point"}
}
