{
  "type": "Feature",
  "properties": {
    "date:inception_lower": "1980-01-01",
    "date:inception_upper": "1980-01-01",
    "iso:country": "GB",
    "wof:name": "LL64 5JL",
    "wof:placetype": "postalcode"
  },
  "geometry": {"coordinates":[-4.516561,53.225627],"type":"Point"}
}
