{
  "type": "Feature",
  "properties": {
    "iso:country": "GB",
    "wof:name": "LL64 5JL",
    "wof:placetype": "postalcode"
  },
  "geometry": {"coordinates":[-4.516561,53.225627],"type":"Point"}
}
