{
  "type": "Feature",
  "properties": {
    "iso:country":"GB",
    "wof:name":"LL64 5JL",
    "wof:placetype":"postalcode"
},
  "geometry": {"coordinates":[-4.51656148221336,53.22562661379251],"type":"Point"}
}