{
  "type": "Feature",
  "properties": {
    "iso:country":"GB",
    "wof:name":"BD5 0QW",
    "wof:placetype":"postalcode"
},
  "geometry": {"coordinates":[-1.75446898342194,53.7883513772162],"type":"Point"}
}