{
  "type": "Feature",
  "properties": {
    "iso:country":"GB",
    "wof:name":"N19 3TX",
    "wof:placetype":"postalcode"
},
  "geometry": {"coordinates":[-0.13658193974847,51.56823823280978],"type":"Point"}
}