{
  "type": "Feature",
  "properties": {
    "iso:country": "GB",
    "wof:name": "KY8 3QQ",
    "wof:placetype": "postalcode"
  },
  "geometry": {"coordinates":[-3.026299,56.180155],"type":"Point"}
}
