{
  "type": "Feature",
  "properties": {
    "iso:country":"GB",
    "wof:name":"M46 0BP",
    "wof:placetype":"postalcode"
},
  "geometry": {"coordinates":[-2.49879844567728,53.5204951671165],"type":"Point"}
}