{
  "type": "Feature",
  "properties": {
    "iso:country": "GB",
    "wof:name": "M14 5NE",
    "wof:placetype": "postalcode"
  },
  "geometry": {"coordinates":[-2.225902,53.45088],"type":"Point"}
}
