{
  "type": "Feature",
  "properties": {
    "date:inception_lower":"1980-01-01",
    "date:inception_upper":"1980-01-31",
    "iso:country":"GB",
    "wof:name":"M14 5NE",
    "wof:placetype":"postalcode"
},
  "geometry": {"coordinates":[-2.225902,53.45088],"type":"Point"}
}