{
  "type": "Feature",
  "properties": {
    "iso:country":"GB",
    "wof:name":"M14 5NE",
    "wof:placetype":"postalcode"
},
  "geometry": {"coordinates":[-2.22590244111878,53.45088031958673],"type":"Point"}
}