{
  "type": "Feature",
  "properties": {
    "iso:country": "GB",
    "wof:name": "L74 4BJ",
    "wof:placetype": "postalcode"
  },
  "geometry": {"coordinates":[-2.988646,53.393643],"type":"Point"}
}
