{
  "type": "Feature",
  "properties": {
    "iso:country": "GB",
    "wof:name": "NR17 1DU",
    "wof:placetype": "postalcode"
  },
  "geometry": {"coordinates":[0.922666,52.501386],"type":"Point"}
}
