{
  "type": "Feature",
  "properties": {
    "iso:country":"GB",
    "wof:name":"SS16 4LJ",
    "wof:placetype":"postalcode"
},
  "geometry": {"coordinates":[0.48986168026562,51.56172370540927],"type":"Point"}
}