{
  "type": "Feature",
  "properties": {
    "date:inception_lower": "1980-01-01",
    "date:inception_upper": "1980-01-01",
    "iso:country": "GB",
    "wof:name": "LA14 3SJ",
    "wof:placetype": "postalcode"
  },
  "geometry": {"coordinates":[-3.25286,54.121896],"type":"Point"}
}
