{
  "type": "Feature",
  "properties": {
    "iso:country":"GB",
    "wof:name":"LA14 3SJ",
    "wof:placetype":"postalcode"
},
  "geometry": {"coordinates":[-3.25286025722505,54.12189594330162],"type":"Point"}
}