{
  "type": "Feature",
  "properties": {
    "iso:country":"GB",
    "wof:name":"CA2 5WG",
    "wof:placetype":"postalcode"
},
  "geometry": {"coordinates":[-2.94908156044102,54.89277387039269],"type":"Point"}
}