{
  "type": "Feature",
  "properties": {
    "iso:country":"GB",
    "wof:name":"UB1 2XQ",
    "wof:placetype":"postalcode"
},
  "geometry": {"coordinates":[-0.36693997036197,51.52647519951434],"type":"Point"}
}