{
  "type": "Feature",
  "properties": {
    "iso:country":"GB",
    "wof:name":"RG8 9SE",
    "wof:placetype":"postalcode"
},
  "geometry": {"coordinates":[-1.20061988453482,51.51319496279328],"type":"Point"}
}