{
  "type": "Feature",
  "properties": {
    "date:inception_lower": "1980-01-01",
    "date:inception_upper": "1980-01-01",
    "iso:country": "GB",
    "wof:name": "RG8 9SE",
    "wof:placetype": "postalcode"
  },
  "geometry": {"coordinates":[-1.200459,51.513015],"type":"Point"}
}
