{
  "type": "Feature",
  "properties": {
    "iso:country": "GB",
    "wof:name": "RG8 9SE",
    "wof:placetype": "postalcode"
  },
  "geometry": {"coordinates":[-1.2006,51.513196],"type":"Point"}
}
