{
  "type": "Feature",
  "properties": {
    "iso:country": "GB",
    "wof:name": "NE12 6BF",
    "wof:placetype": "postalcode"
  },
  "geometry": {"coordinates":[-1.549438,55.030028],"type":"Point"}
}
