{
  "type": "Feature",
  "properties": {
    "iso:country":"GB",
    "wof:name":"S75 4QT",
    "wof:placetype":"postalcode"
},
  "geometry": {"coordinates":[-1.56061583461501,53.53453657305441],"type":"Point"}
}