{
  "type": "Feature",
  "properties": {
    "iso:country": "GB",
    "wof:name": "S75 4QT",
    "wof:placetype": "postalcode"
  },
  "geometry": {"coordinates":[-1.560557,53.534527],"type":"Point"}
}
