{
  "type": "Feature",
  "properties": {
    "iso:country":"GB",
    "wof:name":"LU2 7HW",
    "wof:placetype":"postalcode"
},
  "geometry": {"coordinates":[-0.41671037132054,51.89273351591982],"type":"Point"}
}