{
  "type": "Feature",
  "properties": {
    "date:inception_lower": "2005-02-01",
    "date:inception_upper": "2005-02-01",
    "iso:country": "GB",
    "wof:name": "WD6 1ZE",
    "wof:placetype": "postalcode"
  },
  "geometry": {"coordinates":[-0.268484,51.659614],"type":"Point"}
}
