{
  "type": "Feature",
  "properties": {
    "iso:country":"GB",
    "wof:name":"S65 4DW",
    "wof:placetype":"postalcode"
},
  "geometry": {"coordinates":[-1.29250673581492,53.44679894244138],"type":"Point"}
}