{
  "type": "Feature",
  "properties": {
    "date:inception_lower":"1980-01-01",
    "date:inception_upper":"1980-01-31",
    "iso:country":"GB",
    "wof:name":"E9 6DT",
    "wof:placetype":"postalcode"
},
  "geometry": {"coordinates":[-0.048948,51.547759],"type":"Point"}
}