{
  "type": "Feature",
  "properties": {
    "iso:country":"GB",
    "wof:name":"E9 6DT",
    "wof:placetype":"postalcode"
},
  "geometry": {"coordinates":[-0.04894793215506,51.54775859340339],"type":"Point"}
}