{
  "type": "Feature",
  "properties": {
    "iso:country": "GB",
    "wof:name": "B29 5TD",
    "wof:placetype": "postalcode"
  },
  "geometry": {"coordinates":[-1.967222,52.443728],"type":"Point"}
}
