{
  "type": "Feature",
  "properties": {
    "date:inception_lower":"1990-02-01",
    "date:inception_upper":"1990-02-28",
    "iso:country":"GB",
    "wof:name":"YO7 4LU",
    "wof:placetype":"postalcode"
},
  "geometry": {"coordinates":[-1.375169,54.228479],"type":"Point"}
}