{
  "type": "Feature",
  "properties": {
    "iso:country":"GB",
    "wof:name":"YO7 4LU",
    "wof:placetype":"postalcode"
},
  "geometry": {"coordinates":[-1.37516133646921,54.22845661500408],"type":"Point"}
}