{
  "type": "Feature",
  "properties": {
    "iso:country":"GB",
    "wof:name":"SO31 5AZ",
    "wof:placetype":"postalcode"
},
  "geometry": {"coordinates":[-1.34694596967288,50.87507972429152],"type":"Point"}
}