{
  "type": "Feature",
  "properties": {
    "iso:country":"GB",
    "wof:name":"TR3 6PS",
    "wof:placetype":"postalcode"
},
  "geometry": {"coordinates":[-5.09067698349401,50.21010541561667],"type":"Point"}
}