{
  "type": "Feature",
  "properties": {
    "iso:country":"GB",
    "wof:name":"NR28 0EF",
    "wof:placetype":"postalcode"
},
  "geometry": {"coordinates":[1.37443663827886,52.81442672567788],"type":"Point"}
}