{
  "type": "Feature",
  "properties": {
    "iso:country":"GB",
    "wof:name":"KY10 3AW",
    "wof:placetype":"postalcode"
},
  "geometry": {"coordinates":[-2.6818445571316,56.22687406785354],"type":"Point"}
}