{
  "type": "Feature",
  "properties": {
    "iso:country": "GB",
    "wof:name": "KY10 3AW",
    "wof:placetype": "postalcode"
  },
  "geometry": {"coordinates":[-2.681845,56.226874],"type":"Point"}
}
