{
  "type": "Feature",
  "properties": {
    "date:inception_lower":"2013-04-01",
    "date:inception_upper":"2013-04-30",
    "iso:country":"GB",
    "wof:name":"RG12 8EX",
    "wof:placetype":"postalcode"
},
  "geometry": {"coordinates":[-0.784369,51.400269],"type":"Point"}
}