{
  "type": "Feature",
  "properties": {
    "iso:country": "GB",
    "wof:name": "RG12 8EX",
    "wof:placetype": "postalcode"
  },
  "geometry": {"coordinates":[-0.784369,51.400269],"type":"Point"}
}
