{
  "type": "Feature",
  "properties": {
    "iso:country":"GB",
    "wof:name":"PR8 3BX",
    "wof:placetype":"postalcode"
},
  "geometry": {"coordinates":[-3.0134981241337,53.61643832949476],"type":"Point"}
}