{
  "type": "Feature",
  "properties": {
    "date:inception_lower": "2001-12-01",
    "date:inception_upper": "2001-12-01",
    "iso:country": "GB",
    "wof:name": "PR8 3BX",
    "wof:placetype": "postalcode"
  },
  "geometry": {"coordinates":[-3.013498,53.616438],"type":"Point"}
}
