{
  "type": "Feature",
  "properties": {
    "iso:country":"GB",
    "wof:name":"BS22 9SD",
    "wof:placetype":"postalcode"
},
  "geometry": {"coordinates":[-2.95864758672882,51.36325450489341],"type":"Point"}
}