{
  "type": "Feature",
  "properties": {
    "iso:country":"GB",
    "wof:name":"BN16 2NG",
    "wof:placetype":"postalcode"
},
  "geometry": {"coordinates":[-0.52341735633193,50.80274602859267],"type":"Point"}
}