{
  "type": "Feature",
  "properties": {
    "date:inception_lower": "1984-02-01",
    "date:inception_upper": "1984-02-01",
    "iso:country": "GB",
    "wof:name": "BN16 2NG",
    "wof:placetype": "postalcode"
  },
  "geometry": {"coordinates":[-0.523417,50.802746],"type":"Point"}
}
