{
  "type": "Feature",
  "properties": {
    "iso:country": "GB",
    "wof:name": "BH7 7BT",
    "wof:placetype": "postalcode"
  },
  "geometry": {"coordinates":[-1.837639,50.735915],"type":"Point"}
}
