{
  "type": "Feature",
  "properties": {
    "date:inception_lower": "2019-12-01",
    "date:inception_upper": "2019-12-01",
    "iso:country": "GB",
    "wof:name": "S2 1AJ",
    "wof:placetype": "postalcode"
  },
  "geometry": {"coordinates":[-1.424098,53.370104],"type":"Point"}
}
