{
  "type": "Feature",
  "properties": {
    "iso:country": "GB",
    "wof:name": "S2 1AJ",
    "wof:placetype": "postalcode"
  },
  "geometry": {"coordinates":[-1.423974,53.370373],"type":"Point"}
}
