{
  "type": "Feature",
  "properties": {
    "iso:country":"GB",
    "wof:name":"PA11 3LN",
    "wof:placetype":"postalcode"
},
  "geometry": {"coordinates":[-4.57076765521019,55.85532512262871],"type":"Point"}
}