{
  "type": "Feature",
  "properties": {
    "iso:country": "GB",
    "wof:name": "LS29 7RB",
    "wof:placetype": "postalcode"
  },
  "geometry": {"coordinates":[-1.748703,53.904931],"type":"Point"}
}
