{
  "type": "Feature",
  "properties": {
    "date:inception_lower": "1980-01-01",
    "date:inception_upper": "1980-01-01",
    "iso:country": "GB",
    "wof:name": "LS29 7RB",
    "wof:placetype": "postalcode"
  },
  "geometry": {"coordinates":[-1.748703,53.904931],"type":"Point"}
}
