{
  "type": "Feature",
  "properties": {
    "iso:country":"GB",
    "wof:name":"SO16 6TJ",
    "wof:placetype":"postalcode"
},
  "geometry": {"coordinates":[-1.42520915246903,50.9310916631399],"type":"Point"}
}