{
  "type": "Feature",
  "properties": {
    "iso:country": "GB",
    "wof:name": "B37 7BX",
    "wof:placetype": "postalcode"
  },
  "geometry": {"coordinates":[-1.746295,52.46359],"type":"Point"}
}
