{
  "type": "Feature",
  "properties": {
    "iso:country":"GB",
    "wof:name":"B37 7BX",
    "wof:placetype":"postalcode"
},
  "geometry": {"coordinates":[-1.74629517087977,52.46358972956823],"type":"Point"}
}