{
  "type": "Feature",
  "properties": {
    "date:inception_lower": "1980-01-01",
    "date:inception_upper": "1980-01-01",
    "iso:country": "GB",
    "wof:name": "M5 4FQ",
    "wof:placetype": "postalcode"
  },
  "geometry": {"coordinates":[-2.286882,53.481615],"type":"Point"}
}
