{
  "type": "Feature",
  "properties": {
    "iso:country": "GB",
    "wof:name": "TR18 4HQ",
    "wof:placetype": "postalcode"
  },
  "geometry": {"coordinates":[-5.537746,50.114137],"type":"Point"}
}
