{
  "type": "Feature",
  "properties": {
    "iso:country":"GB",
    "wof:name":"TF9 4RL",
    "wof:placetype":"postalcode"
},
  "geometry": {"coordinates":[-2.38925108112166,52.92423802178168],"type":"Point"}
}