{
  "type": "Feature",
  "properties": {
    "iso:country": "GB",
    "wof:name": "LA23 2DD",
    "wof:placetype": "postalcode"
  },
  "geometry": {"coordinates":[-2.908102,54.371882],"type":"Point"}
}
