{
  "type": "Feature",
  "properties": {
    "iso:country":"GB",
    "wof:name":"LA23 2DD",
    "wof:placetype":"postalcode"
},
  "geometry": {"coordinates":[-2.90810158152372,54.37188179579569],"type":"Point"}
}