{
  "type": "Feature",
  "properties": {
    "iso:country":"GB",
    "wof:name":"HU3 6SP",
    "wof:placetype":"postalcode"
},
  "geometry": {"coordinates":[-0.38163085926519,53.74266204785534],"type":"Point"}
}