{
  "type": "Feature",
  "properties": {
    "iso:country":"GB",
    "wof:name":"TN27 0SD",
    "wof:placetype":"postalcode"
},
  "geometry": {"coordinates":[0.75658710110968,51.16453858398901],"type":"Point"}
}