{
  "type": "Feature",
  "properties": {
    "iso:country":"GB",
    "wof:name":"HG1 5EA",
    "wof:placetype":"postalcode"
},
  "geometry": {"coordinates":[-1.5404109605174,53.99625081907994],"type":"Point"}
}