{
  "type": "Feature",
  "properties": {
    "iso:country":"GB",
    "wof:name":"OX4 3RJ",
    "wof:placetype":"postalcode"
},
  "geometry": {"coordinates":[-1.20827982151575,51.72612904923928],"type":"Point"}
}