{
  "type": "Feature",
  "properties": {
    "iso:country":"GB",
    "wof:name":"DN12 3BB",
    "wof:placetype":"postalcode"
},
  "geometry": {"coordinates":[-1.21753464218543,53.48558524752085],"type":"Point"}
}