{
  "type": "Feature",
  "properties": {
    "iso:country": "GB",
    "wof:name": "LS26 8AL",
    "wof:placetype": "postalcode"
  },
  "geometry": {"coordinates":[-1.416229,53.761592],"type":"Point"}
}
