{
  "type": "Feature",
  "properties": {
    "date:inception_lower": "2018-06-01",
    "date:inception_upper": "2018-06-01",
    "iso:country": "GB",
    "wof:name": "LS26 8AL",
    "wof:placetype": "postalcode"
  },
  "geometry": {"coordinates":[-1.396478,53.753127],"type":"Point"}
}
