{
  "type": "Feature",
  "properties": {
    "date:inception_lower":"2018-06-01",
    "date:inception_upper":"2018-06-30",
    "iso:country":"GB",
    "wof:name":"LS26 8AL",
    "wof:placetype":"postalcode"
},
  "geometry": {"coordinates":[-1.416229,53.761592],"type":"Point"}
}