{
  "type": "Feature",
  "properties": {
    "iso:country": "GB",
    "wof:name": "EX23 0NQ",
    "wof:placetype": "postalcode"
  },
  "geometry": {"coordinates":[-4.615694,50.74901],"type":"Point"}
}
