{
  "type": "Feature",
  "properties": {
    "iso:country":"GB",
    "wof:name":"EX23 0NQ",
    "wof:placetype":"postalcode"
},
  "geometry": {"coordinates":[-4.61569410912202,50.7490102887797],"type":"Point"}
}