{
  "type": "Feature",
  "properties": {
    "iso:country": "GB",
    "wof:name": "BD12 0AJ",
    "wof:placetype": "postalcode"
  },
  "geometry": {"coordinates":[-1.772308,53.754391],"type":"Point"}
}
