{
  "type": "Feature",
  "properties": {
    "iso:country":"GB",
    "wof:name":"CT6 8DP",
    "wof:placetype":"postalcode"
},
  "geometry": {"coordinates":[1.09998281144608,51.36908304882409],"type":"Point"}
}