{
  "type": "Feature",
  "properties": {
    "iso:country":"GB",
    "wof:name":"CH6 5RL",
    "wof:placetype":"postalcode"
},
  "geometry": {"coordinates":[-3.17941783306739,53.24925190016113],"type":"Point"}
}