{
  "type": "Feature",
  "properties": {
    "iso:country":"GB",
    "wof:name":"RM12 4NT",
    "wof:placetype":"postalcode"
},
  "geometry": {"coordinates":[0.21324059003275,51.55459779528833],"type":"Point"}
}