{
  "type": "Feature",
  "properties": {
    "iso:country":"GB",
    "wof:name":"ML6 9HP",
    "wof:placetype":"postalcode"
},
  "geometry": {"coordinates":[-3.98379888905649,55.85629722366043],"type":"Point"}
}