{
  "type": "Feature",
  "properties": {
    "iso:country":"GB",
    "wof:name":"ST14 7NU",
    "wof:placetype":"postalcode"
},
  "geometry": {"coordinates":[-1.87917890802238,52.90271058089883],"type":"Point"}
}