{
  "type": "Feature",
  "properties": {
    "iso:country": "GB",
    "wof:name": "CH4 9WZ",
    "wof:placetype": "postalcode"
  },
  "geometry": {"coordinates":[-2.88463,53.197771],"type":"Point"}
}
