{
  "type": "Feature",
  "properties": {
    "date:inception_lower": "1994-12-01",
    "date:inception_upper": "1994-12-01",
    "iso:country": "GB",
    "wof:name": "CH4 9WZ",
    "wof:placetype": "postalcode"
  },
  "geometry": {"coordinates":[-2.88463,53.197771],"type":"Point"}
}
