{
  "type": "Feature",
  "properties": {
    "iso:country":"GB",
    "wof:name":"KW16 3HF",
    "wof:placetype":"postalcode"
},
  "geometry": {"coordinates":[-3.15783937944312,58.99410999899438],"type":"Point"}
}