{
  "type": "Feature",
  "properties": {
    "iso:country":"GB",
    "wof:name":"LE6 0DL",
    "wof:placetype":"postalcode"
},
  "geometry": {"coordinates":[-1.21178233122735,52.66198483796671],"type":"Point"}
}