{
  "type": "Feature",
  "properties": {
    "date:inception_lower":"1980-01-01",
    "date:inception_upper":"1980-01-31",
    "iso:country":"GB",
    "wof:name":"NR31 9PZ",
    "wof:placetype":"postalcode"
},
  "geometry": {"coordinates":[1.651728,52.578389],"type":"Point"}
}