{
  "type": "Feature",
  "properties": {
    "iso:country":"GB",
    "wof:name":"BH6 3JA",
    "wof:placetype":"postalcode"
},
  "geometry": {"coordinates":[-1.79881321280352,50.72238381881265],"type":"Point"}
}