{
  "type": "Feature",
  "properties": {
    "date:inception_lower": "1980-01-01",
    "date:inception_upper": "1980-01-01",
    "iso:country": "GB",
    "wof:name": "PA47 7SR",
    "wof:placetype": "postalcode"
  },
  "geometry": {"coordinates":[-6.504259,55.676885],"type":"Point"}
}
