{
  "type": "Feature",
  "properties": {
    "iso:country":"GB",
    "wof:name":"TF10 7XZ",
    "wof:placetype":"postalcode"
},
  "geometry": {"coordinates":[-2.36548528742142,52.77448649985028],"type":"Point"}
}