{
  "type": "Feature",
  "properties": {
    "date:inception_lower":"2001-06-01",
    "date:inception_upper":"2001-06-30",
    "iso:country":"GB",
    "wof:name":"TF10 7XZ",
    "wof:placetype":"postalcode"
},
  "geometry": {"coordinates":[-2.365485,52.774486],"type":"Point"}
}