{
  "type": "Feature",
  "properties": {
    "date:inception_lower":"1980-01-01",
    "date:inception_upper":"1980-01-31",
    "iso:country":"GB",
    "wof:name":"ML5 4HU",
    "wof:placetype":"postalcode"
},
  "geometry": {"coordinates":[-4.019755,55.849026],"type":"Point"}
}