{
  "type": "Feature",
  "properties": {
    "iso:country":"GB",
    "wof:name":"ML5 4HU",
    "wof:placetype":"postalcode"
},
  "geometry": {"coordinates":[-4.01975508604088,55.8490258236108],"type":"Point"}
}