{
  "type": "Feature",
  "properties": {
    "iso:country": "GB",
    "wof:name": "E8 3FR",
    "wof:placetype": "postalcode"
  },
  "geometry": {"coordinates":[-0.062934,51.540438],"type":"Point"}
}
