{
  "type": "Feature",
  "properties": {
    "date:inception_lower": "1980-01-01",
    "date:inception_upper": "1980-01-01",
    "iso:country": "GB",
    "wof:name": "TS5 8UH",
    "wof:placetype": "postalcode"
  },
  "geometry": {"coordinates":[-1.267996,54.533314],"type":"Point"}
}
