{
  "type": "Feature",
  "properties": {
    "iso:country":"GB",
    "wof:name":"TS5 8UH",
    "wof:placetype":"postalcode"
},
  "geometry": {"coordinates":[-1.26799588086292,54.53331444408399],"type":"Point"}
}