{
  "type": "Feature",
  "properties": {
    "iso:country": "GB",
    "wof:name": "TS5 8UH",
    "wof:placetype": "postalcode"
  },
  "geometry": {"coordinates":[-1.267996,54.533314],"type":"Point"}
}
