{
  "type": "Feature",
  "properties": {
    "iso:country": "GB",
    "wof:name": "S42 5XA",
    "wof:placetype": "postalcode"
  },
  "geometry": {"coordinates":[-1.38577,53.185092],"type":"Point"}
}
