{
  "type": "Feature",
  "properties": {
    "iso:country":"GB",
    "wof:name":"PE22 0EX",
    "wof:placetype":"postalcode"
},
  "geometry": {"coordinates":[0.0684668668234,52.98585720420013],"type":"Point"}
}