{
  "type": "Feature",
  "properties": {
    "iso:country":"GB",
    "wof:name":"LA23 1AY",
    "wof:placetype":"postalcode"
},
  "geometry": {"coordinates":[-2.91234863377863,54.38083721581231],"type":"Point"}
}