{
  "type": "Feature",
  "properties": {
    "iso:country": "GB",
    "wof:name": "LA23 1AY",
    "wof:placetype": "postalcode"
  },
  "geometry": {"coordinates":[-2.912349,54.380837],"type":"Point"}
}
