{
  "type": "Feature",
  "properties": {
    "iso:country":"GB",
    "wof:name":"S71 3DJ",
    "wof:placetype":"postalcode"
},
  "geometry": {"coordinates":[-1.48223151732829,53.58562783893804],"type":"Point"}
}