{
  "type": "Feature",
  "properties": {
    "date:inception_lower": "2020-08-01",
    "date:inception_upper": "2020-08-01",
    "iso:country": "GB",
    "wof:name": "LL12 0QS",
    "wof:placetype": "postalcode"
  },
  "geometry": {"coordinates":[-2.993275,53.100448],"type":"Point"}
}
