{
  "type": "Feature",
  "properties": {
    "iso:country": "GB",
    "wof:name": "S6 1RS",
    "wof:placetype": "postalcode"
  },
  "geometry": {"coordinates":[-1.518085,53.41869],"type":"Point"}
}
