{
  "type": "Feature",
  "properties": {
    "iso:country":"GB",
    "wof:name":"YO21 2NS",
    "wof:placetype":"postalcode"
},
  "geometry": {"coordinates":[-0.89918684838067,54.43842649343276],"type":"Point"}
}