{
  "type": "Feature",
  "properties": {
    "date:inception_lower": "1980-01-01",
    "date:inception_upper": "1980-01-01",
    "iso:country": "GB",
    "wof:name": "YO21 2NS",
    "wof:placetype": "postalcode"
  },
  "geometry": {"coordinates":[-0.899187,54.438426],"type":"Point"}
}
