{
  "type": "Feature",
  "properties": {
    "iso:country":"GB",
    "wof:name":"CV8 1PE",
    "wof:placetype":"postalcode"
},
  "geometry": {"coordinates":[-1.60397342962299,52.37566255032162],"type":"Point"}
}