{
  "type": "Feature",
  "properties": {
    "date:inception_lower": "1980-01-01",
    "date:inception_upper": "1980-01-01",
    "iso:country": "GB",
    "wof:name": "CV8 1PE",
    "wof:placetype": "postalcode"
  },
  "geometry": {"coordinates":[-1.60368,52.376118],"type":"Point"}
}
