{
  "type": "Feature",
  "properties": {
    "iso:country":"GB",
    "wof:name":"HG1 3AJ",
    "wof:placetype":"postalcode"
},
  "geometry": {"coordinates":[-1.54211940991161,54.00876826273068],"type":"Point"}
}