{
  "type": "Feature",
  "properties": {
    "iso:country":"GB",
    "wof:name":"NE2 4BA",
    "wof:placetype":"postalcode"
},
  "geometry": {"coordinates":[-1.62541674881099,54.983639292242],"type":"Point"}
}