{
  "type": "Feature",
  "properties": {
    "date:inception_lower":"1980-01-01",
    "date:inception_upper":"1980-01-31",
    "iso:country":"GB",
    "wof:name":"NE2 4BA",
    "wof:placetype":"postalcode"
},
  "geometry": {"coordinates":[-1.625417,54.983639],"type":"Point"}
}