{
  "type": "Feature",
  "properties": {
    "iso:country": "GB",
    "wof:name": "SY1 3PA",
    "wof:placetype": "postalcode"
  },
  "geometry": {"coordinates":[-2.751809,52.729594],"type":"Point"}
}
