{
  "type": "Feature",
  "properties": {
    "iso:country":"GB",
    "wof:name":"DN33 3EB",
    "wof:placetype":"postalcode"
},
  "geometry": {"coordinates":[-0.0980855397777,53.52868751483888],"type":"Point"}
}