{
  "type": "Feature",
  "properties": {
    "iso:country": "GB",
    "wof:name": "AB22 8YT",
    "wof:placetype": "postalcode"
  },
  "geometry": {"coordinates":[-2.150562,57.17758],"type":"Point"}
}
