{
  "type": "Feature",
  "properties": {
    "date:inception_lower": "1980-01-01",
    "date:inception_upper": "1980-01-01",
    "iso:country": "GB",
    "wof:name": "G51 2DN",
    "wof:placetype": "postalcode"
  },
  "geometry": {"coordinates":[-4.306651,55.858612],"type":"Point"}
}
