{
  "type": "Feature",
  "properties": {
    "iso:country":"GB",
    "wof:name":"BS5 7PN",
    "wof:placetype":"postalcode"
},
  "geometry": {"coordinates":[-2.52828622972367,51.46029109280303],"type":"Point"}
}