{
  "type": "Feature",
  "properties": {
    "iso:country":"GB",
    "wof:name":"SL1 4HB",
    "wof:placetype":"postalcode"
},
  "geometry": {"coordinates":[-0.61629891716865,51.51895371170544],"type":"Point"}
}