{
  "type": "Feature",
  "properties": {
    "date:inception_lower": "1980-01-01",
    "date:inception_upper": "1980-01-01",
    "iso:country": "GB",
    "wof:name": "NG17 3GT",
    "wof:placetype": "postalcode"
  },
  "geometry": {"coordinates":[-1.282851,53.141415],"type":"Point"}
}
