{
  "type": "Feature",
  "properties": {
    "iso:country": "GB",
    "wof:name": "NG17 3GT",
    "wof:placetype": "postalcode"
  },
  "geometry": {"coordinates":[-1.282838,53.141397],"type":"Point"}
}
