{
  "type": "Feature",
  "properties": {
    "date:inception_lower":"1994-05-01",
    "date:inception_upper":"1994-05-31",
    "iso:country":"GB",
    "wof:name":"M25 0FW",
    "wof:placetype":"postalcode"
},
  "geometry": {"coordinates":[-2.258476,53.5183],"type":"Point"}
}