{
  "type": "Feature",
  "properties": {
    "iso:country":"GB",
    "wof:name":"M25 0FW",
    "wof:placetype":"postalcode"
},
  "geometry": {"coordinates":[-2.25852075090605,53.51826349300248],"type":"Point"}
}