{
  "type": "Feature",
  "properties": {
    "iso:country": "GB",
    "wof:name": "M25 0FW",
    "wof:placetype": "postalcode"
  },
  "geometry": {"coordinates":[-2.258476,53.5183],"type":"Point"}
}
