{
  "type": "Feature",
  "properties": {
    "iso:country":"GB",
    "wof:name":"DE73 8BZ",
    "wof:placetype":"postalcode"
},
  "geometry": {"coordinates":[-1.42780212193323,52.83023423848918],"type":"Point"}
}