{
  "type": "Feature",
  "properties": {
    "iso:country": "GB",
    "wof:name": "DE73 8BZ",
    "wof:placetype": "postalcode"
  },
  "geometry": {"coordinates":[-1.427802,52.830234],"type":"Point"}
}
