{
  "type": "Feature",
  "properties": {
    "date:inception_lower": "1980-01-01",
    "date:inception_upper": "1980-01-01",
    "iso:country": "GB",
    "wof:name": "CT14 7NJ",
    "wof:placetype": "postalcode"
  },
  "geometry": {"coordinates":[1.395877,51.202161],"type":"Point"}
}
