{
  "type": "Feature",
  "properties": {
    "date:inception_lower": "1980-01-01",
    "date:inception_upper": "1980-01-01",
    "iso:country": "GB",
    "wof:name": "BS23 2AN",
    "wof:placetype": "postalcode"
  },
  "geometry": {"coordinates":[-2.982954,51.351037],"type":"Point"}
}
