{
  "type": "Feature",
  "properties": {
    "iso:country":"GB",
    "wof:name":"NR10 4LU",
    "wof:placetype":"postalcode"
},
  "geometry": {"coordinates":[1.11807320442973,52.7685384923036],"type":"Point"}
}