{
  "type": "Feature",
  "properties": {
    "iso:country": "GB",
    "wof:name": "NR10 4LU",
    "wof:placetype": "postalcode"
  },
  "geometry": {"coordinates":[1.118073,52.768538],"type":"Point"}
}
