{
  "type": "Feature",
  "properties": {
    "date:inception_lower":"1992-08-01",
    "date:inception_upper":"1992-08-31",
    "iso:country":"GB",
    "wof:name":"LE18 2AN",
    "wof:placetype":"postalcode"
},
  "geometry": {"coordinates":[-1.10574,52.584728],"type":"Point"}
}