{
  "type": "Feature",
  "properties": {
    "date:inception_lower": "2016-02-01",
    "date:inception_upper": "2016-02-01",
    "iso:country": "GB",
    "wof:name": "CT3 3FF",
    "wof:placetype": "postalcode"
  },
  "geometry": {"coordinates":[1.197611,51.230218],"type":"Point"}
}
