{
  "type": "Feature",
  "properties": {
    "iso:country":"GB",
    "wof:name":"N17 9AH",
    "wof:placetype":"postalcode"
},
  "geometry": {"coordinates":[-0.06666458819449,51.59355401460854],"type":"Point"}
}