{
  "type": "Feature",
  "properties": {
    "iso:country": "GB",
    "wof:name": "EH4 8BQ",
    "wof:placetype": "postalcode"
  },
  "geometry": {"coordinates":[-3.304737,55.958563],"type":"Point"}
}
