{
  "type": "Feature",
  "properties": {
    "iso:country":"GB",
    "wof:name":"OL4 2BX",
    "wof:placetype":"postalcode"
},
  "geometry": {"coordinates":[-2.09147318522037,53.54455662145394],"type":"Point"}
}