{
  "type": "Feature",
  "properties": {
    "iso:country": "GB",
    "wof:name": "OL4 2BX",
    "wof:placetype": "postalcode"
  },
  "geometry": {"coordinates":[-2.091471,53.544573],"type":"Point"}
}
