{
  "type": "Feature",
  "properties": {
    "date:inception_lower": "1980-01-01",
    "date:inception_upper": "1980-01-01",
    "iso:country": "GB",
    "wof:name": "OL4 2BX",
    "wof:placetype": "postalcode"
  },
  "geometry": {"coordinates":[-2.091561,53.544564],"type":"Point"}
}
