{
  "type": "Feature",
  "properties": {
    "iso:country": "GB",
    "wof:name": "BN14 7LZ",
    "wof:placetype": "postalcode"
  },
  "geometry": {"coordinates":[-0.394079,50.820059],"type":"Point"}
}
