{
  "type": "Feature",
  "properties": {
    "iso:country":"GB",
    "wof:name":"BN14 0RQ",
    "wof:placetype":"postalcode"
},
  "geometry": {"coordinates":[-0.41720735188123,50.87871269007309],"type":"Point"}
}