{
  "type": "Feature",
  "properties": {
    "iso:country":"GB",
    "wof:name":"NE1 4BF",
    "wof:placetype":"postalcode"
},
  "geometry": {"coordinates":[-1.6187567183716,54.97409318806376],"type":"Point"}
}