{
  "type": "Feature",
  "properties": {
    "date:inception_lower":"1986-04-01",
    "date:inception_upper":"1986-04-30",
    "iso:country":"GB",
    "wof:name":"IP12 1RN",
    "wof:placetype":"postalcode"
},
  "geometry": {"coordinates":[1.326227,52.107916],"type":"Point"}
}