{
  "type": "Feature",
  "properties": {
    "iso:country":"GB",
    "wof:name":"S41 9EB",
    "wof:placetype":"postalcode"
},
  "geometry": {"coordinates":[-1.43592341511141,53.27011505235717],"type":"Point"}
}