{
  "type": "Feature",
  "properties": {
    "date:inception_lower":"1980-01-01",
    "date:inception_upper":"1980-01-31",
    "iso:country":"GB",
    "wof:name":"TW1 1RX",
    "wof:placetype":"postalcode"
},
  "geometry": {"coordinates":[-0.317918,51.457405],"type":"Point"}
}