{
  "type": "Feature",
  "properties": {
    "iso:country":"GB",
    "wof:name":"TW1 1RX",
    "wof:placetype":"postalcode"
},
  "geometry": {"coordinates":[-0.31791851942481,51.4574047613724],"type":"Point"}
}