{
  "type": "Feature",
  "properties": {
    "iso:country":"GB",
    "wof:name":"GU35 0ET",
    "wof:placetype":"postalcode"
},
  "geometry": {"coordinates":[-0.84980877315322,51.11469789620175],"type":"Point"}
}