{
  "type": "Feature",
  "properties": {
    "date:inception_lower":"1980-01-01",
    "date:inception_upper":"1980-01-31",
    "iso:country":"GB",
    "wof:name":"EX22 6SZ",
    "wof:placetype":"postalcode"
},
  "geometry": {"coordinates":[-4.392735,50.801605],"type":"Point"}
}