{
  "type": "Feature",
  "properties": {
    "iso:country": "GB",
    "wof:name": "EX22 6SZ",
    "wof:placetype": "postalcode"
  },
  "geometry": {"coordinates":[-4.392735,50.801605],"type":"Point"}
}
