{
  "type": "Feature",
  "properties": {
    "iso:country":"GB",
    "wof:name":"EX22 6SZ",
    "wof:placetype":"postalcode"
},
  "geometry": {"coordinates":[-4.39273481261225,50.80160515305704],"type":"Point"}
}