{
  "type": "Feature",
  "properties": {
    "iso:country":"GB",
    "wof:name":"RH1 5AT",
    "wof:placetype":"postalcode"
},
  "geometry": {"coordinates":[-0.16698670412004,51.2114122684252],"type":"Point"}
}