{
  "type": "Feature",
  "properties": {
    "date:inception_lower":"1995-01-01",
    "date:inception_upper":"1995-01-31",
    "iso:country":"GB",
    "wof:name":"WV6 7HR",
    "wof:placetype":"postalcode"
},
  "geometry": {"coordinates":[-2.295929,52.594402],"type":"Point"}
}