{
  "type": "Feature",
  "properties": {
    "iso:country":"GB",
    "wof:name":"WV6 7HR",
    "wof:placetype":"postalcode"
},
  "geometry": {"coordinates":[-2.2959288569594,52.59440154068408],"type":"Point"}
}