{
  "type": "Feature",
  "properties": {
    "iso:country": "GB",
    "wof:name": "CB6 3DT",
    "wof:placetype": "postalcode"
  },
  "geometry": {"coordinates":[0.248493,52.394276],"type":"Point"}
}
