{
  "type": "Feature",
  "properties": {
    "iso:country":"GB",
    "wof:name":"WS11 5SW",
    "wof:placetype":"postalcode"
},
  "geometry": {"coordinates":[-2.01478778802377,52.70829280279774],"type":"Point"}
}