{
  "type": "Feature",
  "properties": {
    "iso:country":"GB",
    "wof:name":"CB2 1EL",
    "wof:placetype":"postalcode"
},
  "geometry": {"coordinates":[0.12278640965067,52.19817904499553],"type":"Point"}
}