{
  "type": "Feature",
  "properties": {
    "date:inception_lower":"1994-05-01",
    "date:inception_upper":"1994-05-31",
    "iso:country":"GB",
    "wof:name":"M41 9JS",
    "wof:placetype":"postalcode"
},
  "geometry": {"coordinates":[-2.352599,53.447337],"type":"Point"}
}