{
  "type": "Feature",
  "properties": {
    "iso:country":"GB",
    "wof:name":"M41 9JS",
    "wof:placetype":"postalcode"
},
  "geometry": {"coordinates":[-2.35259931935567,53.44733744295221],"type":"Point"}
}