{
  "type": "Feature",
  "properties": {
    "iso:country": "GB",
    "wof:name": "M41 9JS",
    "wof:placetype": "postalcode"
  },
  "geometry": {"coordinates":[-2.352599,53.447337],"type":"Point"}
}
