{
  "type": "Feature",
  "properties": {
    "date:inception_lower": "1992-08-01",
    "date:inception_upper": "1992-08-01",
    "iso:country": "GB",
    "wof:name": "HP8 4DZ",
    "wof:placetype": "postalcode"
  },
  "geometry": {"coordinates":[-0.574616,51.626916],"type":"Point"}
}
