{
  "type": "Feature",
  "properties": {
    "iso:country":"GB",
    "wof:name":"RM6 6UX",
    "wof:placetype":"postalcode"
},
  "geometry": {"coordinates":[0.13811722490769,51.57625178062762],"type":"Point"}
}