{
  "type": "Feature",
  "properties": {
    "date:inception_lower": "2001-12-01",
    "date:inception_upper": "2001-12-01",
    "iso:country": "GB",
    "wof:name": "FK11 7BD",
    "wof:placetype": "postalcode"
  },
  "geometry": {"coordinates":[-3.850718,56.151706],"type":"Point"}
}
