{
  "type": "Feature",
  "properties": {
    "iso:country":"GB",
    "wof:name":"FK11 7BD",
    "wof:placetype":"postalcode"
},
  "geometry": {"coordinates":[-3.85071840052328,56.15170616743588],"type":"Point"}
}