{
  "type": "Feature",
  "properties": {
    "date:inception_lower": "2021-10-01",
    "date:inception_upper": "2021-10-01",
    "iso:country": "GB",
    "wof:name": "GU12 6GF",
    "wof:placetype": "postalcode"
  },
  "geometry": {"coordinates":[-0.723331,51.24086],"type":"Point"}
}
