{
  "type": "Feature",
  "properties": {
    "iso:country": "GB",
    "wof:name": "SR5 3NH",
    "wof:placetype": "postalcode"
  },
  "geometry": {"coordinates":[-1.45375,54.924857],"type":"Point"}
}
