{
  "type": "Feature",
  "properties": {
    "iso:country":"GB",
    "wof:name":"SR5 3NH",
    "wof:placetype":"postalcode"
},
  "geometry": {"coordinates":[-1.45374962098235,54.92485715632012],"type":"Point"}
}