{
  "type": "Feature",
  "properties": {
    "iso:country": "GB",
    "wof:name": "DE72 3TN",
    "wof:placetype": "postalcode"
  },
  "geometry": {"coordinates":[-1.37054,52.921584],"type":"Point"}
}
