{
  "type": "Feature",
  "properties": {
    "iso:country":"GB",
    "wof:name":"B11 3BH",
    "wof:placetype":"postalcode"
},
  "geometry": {"coordinates":[-1.85263742044683,52.44591561129575],"type":"Point"}
}