{
  "type": "Feature",
  "properties": {
    "iso:country":"GB",
    "wof:name":"OX18 4RP",
    "wof:placetype":"postalcode"
},
  "geometry": {"coordinates":[-1.6354488694813,51.80982372637501],"type":"Point"}
}