{
  "type": "Feature",
  "properties": {
    "iso:country":"GB",
    "wof:name":"NG14 7AZ",
    "wof:placetype":"postalcode"
},
  "geometry": {"coordinates":[-1.01386489421523,53.01255212810528],"type":"Point"}
}