{
  "type": "Feature",
  "properties": {
    "iso:country":"GB",
    "wof:name":"E12 5DN",
    "wof:placetype":"postalcode"
},
  "geometry": {"coordinates":[0.03719562974592,51.56150090225113],"type":"Point"}
}