{
  "type": "Feature",
  "properties": {
    "date:inception_lower":"1980-01-01",
    "date:inception_upper":"1980-01-31",
    "iso:country":"GB",
    "wof:name":"E12 5DN",
    "wof:placetype":"postalcode"
},
  "geometry": {"coordinates":[0.037196,51.561501],"type":"Point"}
}