{
  "type": "Feature",
  "properties": {
    "date:inception_lower":"2003-01-01",
    "date:inception_upper":"2003-01-31",
    "iso:country":"GB",
    "wof:name":"M16 8SA",
    "wof:placetype":"postalcode"
},
  "geometry": {"coordinates":[-2.255175,53.445851],"type":"Point"}
}