{
  "type": "Feature",
  "properties": {
    "iso:country":"GB",
    "wof:name":"HR5 3FE",
    "wof:placetype":"postalcode"
},
  "geometry": {"coordinates":[-3.02392034285921,52.20459932822934],"type":"Point"}
}