{
  "type": "Feature",
  "properties": {
    "iso:country":"GB",
    "wof:name":"MK45 2LS",
    "wof:placetype":"postalcode"
},
  "geometry": {"coordinates":[-0.49857379999377,52.03428047192723],"type":"Point"}
}