{
  "type": "Feature",
  "properties": {
    "iso:country":"GB",
    "wof:name":"SN15 1TG",
    "wof:placetype":"postalcode"
},
  "geometry": {"coordinates":[-2.11556588795023,51.46788101194235],"type":"Point"}
}