{
  "type": "Feature",
  "properties": {
    "date:inception_lower": "1992-01-01",
    "date:inception_upper": "1992-01-01",
    "iso:country": "GB",
    "wof:name": "SN15 1TG",
    "wof:placetype": "postalcode"
  },
  "geometry": {"coordinates":[-2.115566,51.467881],"type":"Point"}
}
