{
  "type": "Feature",
  "properties": {
    "iso:country": "GB",
    "wof:name": "SN15 1TG",
    "wof:placetype": "postalcode"
  },
  "geometry": {"coordinates":[-2.115566,51.467881],"type":"Point"}
}
