{
  "type": "Feature",
  "properties": {
    "date:inception_lower": "1980-01-01",
    "date:inception_upper": "1980-01-01",
    "iso:country": "GB",
    "wof:name": "B93 9EA",
    "wof:placetype": "postalcode"
  },
  "geometry": {"coordinates":[-1.751337,52.381009],"type":"Point"}
}
