{
  "type": "Feature",
  "properties": {
    "iso:country":"GB",
    "wof:name":"B93 9EA",
    "wof:placetype":"postalcode"
},
  "geometry": {"coordinates":[-1.75133721747531,52.38100867263876],"type":"Point"}
}