{
  "type": "Feature",
  "properties": {
    "iso:country":"GB",
    "wof:name":"TN17 4LE",
    "wof:placetype":"postalcode"
},
  "geometry": {"coordinates":[0.55161547853034,51.05744181311808],"type":"Point"}
}