{
  "type": "Feature",
  "properties": {
    "iso:country": "GB",
    "wof:name": "TN17 4LE",
    "wof:placetype": "postalcode"
  },
  "geometry": {"coordinates":[0.551589,51.05745],"type":"Point"}
}
