{
  "type": "Feature",
  "properties": {
    "iso:country":"GB",
    "wof:name":"E1W 1YJ",
    "wof:placetype":"postalcode"
},
  "geometry": {"coordinates":[-0.06810376184161,51.50650294135429],"type":"Point"}
}