{
  "type": "Feature",
  "properties": {
    "iso:country":"GB",
    "wof:name":"S10 1BE",
    "wof:placetype":"postalcode"
},
  "geometry": {"coordinates":[-1.49609796251298,53.38465856125425],"type":"Point"}
}