{
  "type": "Feature",
  "properties": {
    "iso:country":"GB",
    "wof:name":"CF5 2HG",
    "wof:placetype":"postalcode"
},
  "geometry": {"coordinates":[-3.22813695150886,51.49183367146565],"type":"Point"}
}