{
  "type": "Feature",
  "properties": {
    "iso:country":"GB",
    "wof:name":"S41 7NS",
    "wof:placetype":"postalcode"
},
  "geometry": {"coordinates":[-1.42640213593036,53.24320182722608],"type":"Point"}
}