{
  "type": "Feature",
  "properties": {
    "date:inception_lower": "2005-10-01",
    "date:inception_upper": "2005-10-01",
    "iso:country": "GB",
    "wof:name": "S41 7NS",
    "wof:placetype": "postalcode"
  },
  "geometry": {"coordinates":[-1.426402,53.243202],"type":"Point"}
}
