{
  "type": "Feature",
  "properties": {
    "iso:country":"GB",
    "wof:name":"IP1 6QJ",
    "wof:placetype":"postalcode"
},
  "geometry": {"coordinates":[1.13918500713991,52.0838099672829],"type":"Point"}
}