{
  "type": "Feature",
  "properties": {
    "iso:country":"GB",
    "wof:name":"BS24 7FS",
    "wof:placetype":"postalcode"
},
  "geometry": {"coordinates":[-2.89809044127693,51.35076813270946],"type":"Point"}
}