{
  "type": "Feature",
  "properties": {
    "iso:country":"GB",
    "wof:name":"NG19 0PY",
    "wof:placetype":"postalcode"
},
  "geometry": {"coordinates":[-1.17235661234731,53.15323832308138],"type":"Point"}
}