{
  "type": "Feature",
  "properties": {
    "iso:country": "GB",
    "wof:name": "IG4 5JR",
    "wof:placetype": "postalcode"
  },
  "geometry": {"coordinates":[0.045203,51.5795],"type":"Point"}
}
