{
  "type": "Feature",
  "properties": {
    "date:inception_lower":"1980-01-01",
    "date:inception_upper":"1980-01-31",
    "iso:country":"GB",
    "wof:name":"IG4 5JR",
    "wof:placetype":"postalcode"
},
  "geometry": {"coordinates":[0.045203,51.5795],"type":"Point"}
}