{
  "type": "Feature",
  "properties": {
    "iso:country":"GB",
    "wof:name":"IG4 5JR",
    "wof:placetype":"postalcode"
},
  "geometry": {"coordinates":[0.04520274754422,51.57949977673427],"type":"Point"}
}