{
  "type": "Feature",
  "properties": {
    "date:inception_lower":"2005-08-01",
    "date:inception_upper":"2005-08-31",
    "iso:country":"GB",
    "wof:name":"SE16 2PY",
    "wof:placetype":"postalcode"
},
  "geometry": {"coordinates":[-0.046966,51.49029],"type":"Point"}
}