{
  "type": "Feature",
  "properties": {
    "iso:country": "GB",
    "wof:name": "CB10 2NP",
    "wof:placetype": "postalcode"
  },
  "geometry": {"coordinates":[0.263109,52.020934],"type":"Point"}
}
