{
  "type": "Feature",
  "properties": {
    "iso:country":"GB",
    "wof:name":"M22 5DL",
    "wof:placetype":"postalcode"
},
  "geometry": {"coordinates":[-2.24786524177757,53.379979925272],"type":"Point"}
}