{
  "type": "Feature",
  "properties": {
    "iso:country": "GB",
    "wof:name": "EX5 2DY",
    "wof:placetype": "postalcode"
  },
  "geometry": {"coordinates":[-3.414928,50.74441],"type":"Point"}
}
