{
  "type": "Feature",
  "properties": {
    "date:inception_lower": "1980-01-01",
    "date:inception_upper": "1980-01-01",
    "iso:country": "GB",
    "wof:name": "EX5 2DY",
    "wof:placetype": "postalcode"
  },
  "geometry": {"coordinates":[-3.414928,50.74441],"type":"Point"}
}
