{
  "type": "Feature",
  "properties": {
    "iso:country": "GB",
    "wof:name": "TR8 4HP",
    "wof:placetype": "postalcode"
  },
  "geometry": {"coordinates":[-5.012076,50.435901],"type":"Point"}
}
