{
  "type": "Feature",
  "properties": {
    "date:inception_lower":"1984-02-01",
    "date:inception_upper":"1984-02-29",
    "iso:country":"GB",
    "wof:name":"TR8 4HP",
    "wof:placetype":"postalcode"
},
  "geometry": {"coordinates":[-5.012076,50.435901],"type":"Point"}
}