{
  "type": "Feature",
  "properties": {
    "iso:country":"GB",
    "wof:name":"SP11 6GY",
    "wof:placetype":"postalcode"
},
  "geometry": {"coordinates":[-1.44208145552798,51.22120813484555],"type":"Point"}
}