{
  "type": "Feature",
  "properties": {
    "iso:country": "GB",
    "wof:name": "SP11 6GY",
    "wof:placetype": "postalcode"
  },
  "geometry": {"coordinates":[-1.442081,51.221208],"type":"Point"}
}
