{
  "type": "Feature",
  "properties": {
    "date:inception_lower":"1980-01-01",
    "date:inception_upper":"1980-01-31",
    "iso:country":"GB",
    "wof:name":"SR7 9RS",
    "wof:placetype":"postalcode"
},
  "geometry": {"coordinates":[-1.403648,54.817116],"type":"Point"}
}