{
  "type": "Feature",
  "properties": {
    "iso:country":"GB",
    "wof:name":"EX6 7QH",
    "wof:placetype":"postalcode"
},
  "geometry": {"coordinates":[-3.63944827659396,50.64380857487789],"type":"Point"}
}