{
  "type": "Feature",
  "properties": {
    "date:inception_lower": "1980-01-01",
    "date:inception_upper": "1980-01-01",
    "iso:country": "GB",
    "wof:name": "EX6 7QH",
    "wof:placetype": "postalcode"
  },
  "geometry": {"coordinates":[-3.639771,50.643299],"type":"Point"}
}
