{
  "type": "Feature",
  "properties": {
    "date:inception_lower": "1990-02-01",
    "date:inception_upper": "1990-02-01",
    "iso:country": "GB",
    "wof:name": "S40 2UP",
    "wof:placetype": "postalcode"
  },
  "geometry": {"coordinates":[-1.430731,53.21622],"type":"Point"}
}
