{
  "type": "Feature",
  "properties": {
    "date:inception_lower": "1993-01-01",
    "date:inception_upper": "1993-01-01",
    "iso:country": "GB",
    "wof:name": "L33 1UL",
    "wof:placetype": "postalcode"
  },
  "geometry": {"coordinates":[-2.887826,53.4952],"type":"Point"}
}
