{
  "type": "Feature",
  "properties": {
    "iso:country":"GB",
    "wof:name":"L33 1UL",
    "wof:placetype":"postalcode"
},
  "geometry": {"coordinates":[-2.88782609617072,53.49520035775834],"type":"Point"}
}