{
  "type": "Feature",
  "properties": {
    "date:inception_lower":"2005-07-01",
    "date:inception_upper":"2005-07-31",
    "iso:country":"GB",
    "wof:name":"B2 4BB",
    "wof:placetype":"postalcode"
},
  "geometry": {"coordinates":[-1.89589,52.478406],"type":"Point"}
}