{
  "type": "Feature",
  "properties": {
    "iso:country":"GB",
    "wof:name":"GU31 4HW",
    "wof:placetype":"postalcode"
},
  "geometry": {"coordinates":[-0.91870643521368,51.0016272669227],"type":"Point"}
}