{
  "type": "Feature",
  "properties": {
    "iso:country": "GB",
    "wof:name": "GU31 4HW",
    "wof:placetype": "postalcode"
  },
  "geometry": {"coordinates":[-0.918706,51.001627],"type":"Point"}
}
