{
  "type": "Feature",
  "properties": {
    "iso:country":"GB",
    "wof:name":"CW1 4ND",
    "wof:placetype":"postalcode"
},
  "geometry": {"coordinates":[-2.43148896874944,53.11630820757058],"type":"Point"}
}