{
  "type": "Feature",
  "properties": {
    "date:inception_lower":"1980-01-01",
    "date:inception_upper":"1980-01-31",
    "iso:country":"GB",
    "wof:name":"CW1 4ND",
    "wof:placetype":"postalcode"
},
  "geometry": {"coordinates":[-2.432555,53.116815],"type":"Point"}
}