{
  "type": "Feature",
  "properties": {
    "iso:country":"GB",
    "wof:name":"CT6 8UB",
    "wof:placetype":"postalcode"
},
  "geometry": {"coordinates":[1.11785947988565,51.36655754831429],"type":"Point"}
}