{
  "type": "Feature",
  "properties": {
    "iso:country": "GB",
    "wof:name": "CT6 8UB",
    "wof:placetype": "postalcode"
  },
  "geometry": {"coordinates":[1.11786,51.366558],"type":"Point"}
}
