{
  "type": "Feature",
  "properties": {
    "iso:country":"GB",
    "wof:name":"RG7 1BE",
    "wof:placetype":"postalcode"
},
  "geometry": {"coordinates":[-0.97314714114731,51.39382924115251],"type":"Point"}
}