{
  "type": "Feature",
  "properties": {
    "iso:country":"GB",
    "wof:name":"TR19 7NB",
    "wof:placetype":"postalcode"
},
  "geometry": {"coordinates":[-5.68075670551945,50.12353187529845],"type":"Point"}
}