{
  "type": "Feature",
  "properties": {
    "iso:country": "GB",
    "wof:name": "NR31 0LZ",
    "wof:placetype": "postalcode"
  },
  "geometry": {"coordinates":[1.711149,52.598296],"type":"Point"}
}
