{
  "type": "Feature",
  "properties": {
    "iso:country":"GB",
    "wof:name":"NR31 0LZ",
    "wof:placetype":"postalcode"
},
  "geometry": {"coordinates":[1.71110724765064,52.59805573384658],"type":"Point"}
}