{
  "type": "Feature",
  "properties": {
    "iso:country":"GB",
    "wof:name":"NG8 3NR",
    "wof:placetype":"postalcode"
},
  "geometry": {"coordinates":[-1.20089537978192,52.96572726708267],"type":"Point"}
}