{
  "type": "Feature",
  "properties": {
    "iso:country": "GB",
    "wof:name": "GL14 2NL",
    "wof:placetype": "postalcode"
  },
  "geometry": {"coordinates":[-2.498599,51.823086],"type":"Point"}
}
