{
  "type": "Feature",
  "properties": {
    "iso:country":"GB",
    "wof:name":"SA47 0PB",
    "wof:placetype":"postalcode"
},
  "geometry": {"coordinates":[-4.30863454541515,52.1881135360102],"type":"Point"}
}