{
  "type": "Feature",
  "properties": {
    "iso:country": "GB",
    "wof:name": "GL20 5SG",
    "wof:placetype": "postalcode"
  },
  "geometry": {"coordinates":[-2.156591,51.981532],"type":"Point"}
}
