{
  "type": "Feature",
  "properties": {
    "date:inception_lower":"1998-06-01",
    "date:inception_upper":"1998-06-30",
    "iso:country":"GB",
    "wof:name":"GL20 5SG",
    "wof:placetype":"postalcode"
},
  "geometry": {"coordinates":[-2.156591,51.981532],"type":"Point"}
}