{
  "type": "Feature",
  "properties": {
    "iso:country":"GB",
    "wof:name":"GL20 5SG",
    "wof:placetype":"postalcode"
},
  "geometry": {"coordinates":[-2.156591439529,51.98153226656819],"type":"Point"}
}