{
  "type": "Feature",
  "properties": {
    "iso:country":"GB",
    "wof:name":"TS13 4RF",
    "wof:placetype":"postalcode"
},
  "geometry": {"coordinates":[-0.891256512136,54.55444490500039],"type":"Point"}
}