{
  "type": "Feature",
  "properties": {
    "iso:country":"GB",
    "wof:name":"OL8 2NG",
    "wof:placetype":"postalcode"
},
  "geometry": {"coordinates":[-2.10890404064549,53.52140594206487],"type":"Point"}
}