{
  "type": "Feature",
  "properties": {
    "date:inception_lower":"1980-01-01",
    "date:inception_upper":"1980-01-31",
    "iso:country":"GB",
    "wof:name":"OL8 2NG",
    "wof:placetype":"postalcode"
},
  "geometry": {"coordinates":[-2.108904,53.521406],"type":"Point"}
}