{
  "type": "Feature",
  "properties": {
    "iso:country":"GB",
    "wof:name":"CV32 6SJ",
    "wof:placetype":"postalcode"
},
  "geometry": {"coordinates":[-1.55257303666818,52.30018597361428],"type":"Point"}
}