{
  "type": "Feature",
  "properties": {
    "iso:country":"GB",
    "wof:name":"TW8 0PL",
    "wof:placetype":"postalcode"
},
  "geometry": {"coordinates":[-0.30475279024513,51.48601774603372],"type":"Point"}
}