{
  "type": "Feature",
  "properties": {
    "date:inception_lower": "2018-03-01",
    "date:inception_upper": "2018-03-01",
    "iso:country": "GB",
    "wof:name": "NP19 4DX",
    "wof:placetype": "postalcode"
  },
  "geometry": {"coordinates":[-2.933269,51.578203],"type":"Point"}
}
