{
  "type": "Feature",
  "properties": {
    "date:inception_lower":"1980-01-01",
    "date:inception_upper":"1980-01-31",
    "iso:country":"GB",
    "wof:name":"HD2 1TE",
    "wof:placetype":"postalcode"
},
  "geometry": {"coordinates":[-1.75229,53.676167],"type":"Point"}
}