{
  "type": "Feature",
  "properties": {
    "iso:country":"GB",
    "wof:name":"HD2 1TE",
    "wof:placetype":"postalcode"
},
  "geometry": {"coordinates":[-1.75229030488569,53.67616668362449],"type":"Point"}
}