{
  "type": "Feature",
  "properties": {
    "date:inception_lower": "1980-01-01",
    "date:inception_upper": "1980-01-01",
    "iso:country": "GB",
    "wof:name": "WA15 9BX",
    "wof:placetype": "postalcode"
  },
  "geometry": {"coordinates":[-2.338974,53.375594],"type":"Point"}
}
