{
  "type": "Feature",
  "properties": {
    "iso:country":"GB",
    "wof:name":"WA15 9BX",
    "wof:placetype":"postalcode"
},
  "geometry": {"coordinates":[-2.33897397190947,53.37559406869001],"type":"Point"}
}