{
  "type": "Feature",
  "properties": {
    "iso:country":"GB",
    "wof:name":"NG21 9LH",
    "wof:placetype":"postalcode"
},
  "geometry": {"coordinates":[-1.0567447857739,53.18614265169476],"type":"Point"}
}