{
  "type": "Feature",
  "properties": {
    "date:inception_lower":"1980-01-01",
    "date:inception_upper":"1980-01-31",
    "iso:country":"GB",
    "wof:name":"NG21 9LH",
    "wof:placetype":"postalcode"
},
  "geometry": {"coordinates":[-1.056745,53.186143],"type":"Point"}
}