{
  "type": "Feature",
  "properties": {
    "iso:country":"GB",
    "wof:name":"M12 6JR",
    "wof:placetype":"postalcode"
},
  "geometry": {"coordinates":[-2.21617305979874,53.47120332355335],"type":"Point"}
}