{
  "type": "Feature",
  "properties": {
    "date:inception_lower": "1992-01-01",
    "date:inception_upper": "1992-01-01",
    "iso:country": "GB",
    "wof:name": "M12 6JR",
    "wof:placetype": "postalcode"
  },
  "geometry": {"coordinates":[-2.216173,53.471203],"type":"Point"}
}
