{
  "type": "Feature",
  "properties": {
    "iso:country": "GB",
    "wof:name": "NN6 7BN",
    "wof:placetype": "postalcode"
  },
  "geometry": {"coordinates":[-1.077846,52.337712],"type":"Point"}
}
