{
  "type": "Feature",
  "properties": {
    "iso:country":"GB",
    "wof:name":"NN6 7BN",
    "wof:placetype":"postalcode"
},
  "geometry": {"coordinates":[-1.07784634206334,52.3377120706243],"type":"Point"}
}