{
  "type": "Feature",
  "properties": {
    "iso:country": "GB",
    "wof:name": "PA34 4AZ",
    "wof:placetype": "postalcode"
  },
  "geometry": {"coordinates":[-5.471464,56.411973],"type":"Point"}
}
