{
  "type": "Feature",
  "properties": {
    "iso:country": "GB",
    "wof:name": "PR6 0EJ",
    "wof:placetype": "postalcode"
  },
  "geometry": {"coordinates":[-2.617231,53.655488],"type":"Point"}
}
