{
  "type": "Feature",
  "properties": {
    "date:inception_lower": "1990-07-01",
    "date:inception_upper": "1990-07-01",
    "iso:country": "GB",
    "wof:name": "BN18 9NZ",
    "wof:placetype": "postalcode"
  },
  "geometry": {"coordinates":[-0.552777,50.85334],"type":"Point"}
}
