{
  "type": "Feature",
  "properties": {
    "iso:country":"GB",
    "wof:name":"BN18 9NZ",
    "wof:placetype":"postalcode"
},
  "geometry": {"coordinates":[-0.55277740112334,50.85334027975783],"type":"Point"}
}