{
  "type": "Feature",
  "properties": {
    "date:inception_lower":"1999-12-01",
    "date:inception_upper":"1999-12-31",
    "iso:country":"GB",
    "wof:name":"YO21 1YQ",
    "wof:placetype":"postalcode"
},
  "geometry": {"coordinates":[-0.626832,54.485799],"type":"Point"}
}