{
  "type": "Feature",
  "properties": {
    "iso:country": "GB",
    "wof:name": "YO21 1YQ",
    "wof:placetype": "postalcode"
  },
  "geometry": {"coordinates":[-0.626832,54.485799],"type":"Point"}
}
