{
  "type": "Feature",
  "properties": {
    "iso:country": "GB",
    "wof:name": "BS24 8BA",
    "wof:placetype": "postalcode"
  },
  "geometry": {"coordinates":[-2.912898,51.334306],"type":"Point"}
}
