{
  "type": "Feature",
  "properties": {
    "date:inception_lower": "1980-01-01",
    "date:inception_upper": "1980-01-01",
    "iso:country": "GB",
    "wof:name": "BS24 8BA",
    "wof:placetype": "postalcode"
  },
  "geometry": {"coordinates":[-2.912898,51.334306],"type":"Point"}
}
