{
  "type": "Feature",
  "properties": {
    "iso:country":"GB",
    "wof:name":"BS24 8BA",
    "wof:placetype":"postalcode"
},
  "geometry": {"coordinates":[-2.91289835945803,51.33430626537687],"type":"Point"}
}