{
  "type": "Feature",
  "properties": {
    "iso:country":"GB",
    "wof:name":"CM22 7JE",
    "wof:placetype":"postalcode"
},
  "geometry": {"coordinates":[0.24766017946303,51.82734142633229],"type":"Point"}
}