{
  "type": "Feature",
  "properties": {
    "iso:country": "GB",
    "wof:name": "CM22 7JE",
    "wof:placetype": "postalcode"
  },
  "geometry": {"coordinates":[0.247601,51.82735],"type":"Point"}
}
