{
  "type": "Feature",
  "properties": {
    "date:inception_lower": "1997-12-01",
    "date:inception_upper": "1997-12-01",
    "iso:country": "GB",
    "wof:name": "BS48 4RD",
    "wof:placetype": "postalcode"
  },
  "geometry": {"coordinates":[-2.77438,51.425528],"type":"Point"}
}
