{
  "type": "Feature",
  "properties": {
    "iso:country": "GB",
    "wof:name": "WN2 1JF",
    "wof:placetype": "postalcode"
  },
  "geometry": {"coordinates":[-2.595345,53.557257],"type":"Point"}
}
