{
  "type": "Feature",
  "properties": {
    "iso:country":"GB",
    "wof:name":"WN2 1JF",
    "wof:placetype":"postalcode"
},
  "geometry": {"coordinates":[-2.59534505966068,53.55725656200055],"type":"Point"}
}