{
  "type": "Feature",
  "properties": {
    "iso:country":"GB",
    "wof:name":"TA1 4JY",
    "wof:placetype":"postalcode"
},
  "geometry": {"coordinates":[-3.1245634141542,51.0058899004009],"type":"Point"}
}