{
  "type": "Feature",
  "properties": {
    "date:inception_lower":"1996-06-01",
    "date:inception_upper":"1996-06-30",
    "iso:country":"GB",
    "wof:name":"AB24 1TE",
    "wof:placetype":"postalcode"
},
  "geometry": {"coordinates":[-2.09527,57.165076],"type":"Point"}
}