{
  "type": "Feature",
  "properties": {
    "iso:country":"GB",
    "wof:name":"AB24 1TE",
    "wof:placetype":"postalcode"
},
  "geometry": {"coordinates":[-2.09527000594659,57.16507584431318],"type":"Point"}
}