{
  "type": "Feature",
  "properties": {
    "iso:country": "GB",
    "wof:name": "AB24 1TE",
    "wof:placetype": "postalcode"
  },
  "geometry": {"coordinates":[-2.09527,57.165076],"type":"Point"}
}
