{
  "type": "Feature",
  "properties": {
    "iso:country": "GB",
    "wof:name": "ML1 2HN",
    "wof:placetype": "postalcode"
  },
  "geometry": {"coordinates":[-3.974404,55.781309],"type":"Point"}
}
