{
  "type": "Feature",
  "properties": {
    "iso:country": "GB",
    "wof:name": "WS4 1DS",
    "wof:placetype": "postalcode"
  },
  "geometry": {"coordinates":[-1.956381,52.621338],"type":"Point"}
}
