{
  "type": "Feature",
  "properties": {
    "date:inception_lower":"1980-01-01",
    "date:inception_upper":"1980-01-31",
    "iso:country":"GB",
    "wof:name":"NN11 6XU",
    "wof:placetype":"postalcode"
},
  "geometry": {"coordinates":[-1.266078,52.176285],"type":"Point"}
}