{
  "type": "Feature",
  "properties": {
    "date:inception_lower": "1998-12-01",
    "date:inception_upper": "1998-12-01",
    "iso:country": "GB",
    "wof:name": "WA7 1SE",
    "wof:placetype": "postalcode"
  },
  "geometry": {"coordinates":[-2.653915,53.352385],"type":"Point"}
}
