{
  "type": "Feature",
  "properties": {
    "iso:country":"GB",
    "wof:name":"WA7 1SE",
    "wof:placetype":"postalcode"
},
  "geometry": {"coordinates":[-2.65555909977062,53.35181169529576],"type":"Point"}
}