{
  "type": "Feature",
  "properties": {
    "date:inception_lower":"1998-12-01",
    "date:inception_upper":"1998-12-31",
    "iso:country":"GB",
    "wof:name":"WA7 1SE",
    "wof:placetype":"postalcode"
},
  "geometry": {"coordinates":[-2.655559,53.351812],"type":"Point"}
}