{
  "type": "Feature",
  "properties": {
    "iso:country": "GB",
    "wof:name": "NE16 6BP",
    "wof:placetype": "postalcode"
  },
  "geometry": {"coordinates":[-1.733108,54.90851],"type":"Point"}
}
