{
  "type": "Feature",
  "properties": {
    "iso:country":"GB",
    "wof:name":"LE11 5DP",
    "wof:placetype":"postalcode"
},
  "geometry": {"coordinates":[-1.2161030048086,52.77414347290562],"type":"Point"}
}