{
  "type": "Feature",
  "properties": {
    "iso:country":"GB",
    "wof:name":"W1F 9UY",
    "wof:placetype":"postalcode"
},
  "geometry": {"coordinates":[-0.13532392704309,51.51150270369222],"type":"Point"}
}