{
  "type": "Feature",
  "properties": {
    "date:inception_lower": "1983-07-01",
    "date:inception_upper": "1983-07-01",
    "iso:country": "GB",
    "wof:name": "SK16 4UU",
    "wof:placetype": "postalcode"
  },
  "geometry": {"coordinates":[-2.094226,53.466075],"type":"Point"}
}
