{
  "type": "Feature",
  "properties": {
    "iso:country":"GB",
    "wof:name":"SM5 4PT",
    "wof:placetype":"postalcode"
},
  "geometry": {"coordinates":[-0.15874404095637,51.34900771871357],"type":"Point"}
}