{
  "type": "Feature",
  "properties": {
    "iso:country": "GB",
    "wof:name": "EH52 5FD",
    "wof:placetype": "postalcode"
  },
  "geometry": {"coordinates":[-3.461669,55.932373],"type":"Point"}
}
