{
  "type": "Feature",
  "properties": {
    "iso:country":"GB",
    "wof:name":"HD9 5NA",
    "wof:placetype":"postalcode"
},
  "geometry": {"coordinates":[-1.85841932858051,53.59115764683764],"type":"Point"}
}