{
  "type": "Feature",
  "properties": {
    "iso:country": "GB",
    "wof:name": "HP5 1XY",
    "wof:placetype": "postalcode"
  },
  "geometry": {"coordinates":[-0.574667,51.710091],"type":"Point"}
}
