{
  "type": "Feature",
  "properties": {
    "date:inception_lower": "2020-11-01",
    "date:inception_upper": "2020-11-01",
    "iso:country": "GB",
    "wof:name": "TN39 5EU",
    "wof:placetype": "postalcode"
  },
  "geometry": {"coordinates":[0.467637,50.861661],"type":"Point"}
}
