{
  "type": "Feature",
  "properties": {
    "date:inception_lower": "1993-01-01",
    "date:inception_upper": "1993-01-01",
    "iso:country": "GB",
    "wof:name": "NR12 7DD",
    "wof:placetype": "postalcode"
  },
  "geometry": {"coordinates":[1.33967,52.695697],"type":"Point"}
}
