{
  "type": "Feature",
  "properties": {
    "iso:country":"GB",
    "wof:name":"NR12 7DD",
    "wof:placetype":"postalcode"
},
  "geometry": {"coordinates":[1.33966961762575,52.69569696940663],"type":"Point"}
}