{
  "type": "Feature",
  "properties": {
    "iso:country":"GB",
    "wof:name":"NR9 5JG",
    "wof:placetype":"postalcode"
},
  "geometry": {"coordinates":[1.11130346825668,52.71686219683343],"type":"Point"}
}