{
  "type": "Feature",
  "properties": {
    "iso:country":"GB",
    "wof:name":"LE3 0WB",
    "wof:placetype":"postalcode"
},
  "geometry": {"coordinates":[-1.16794591505258,52.63301632710887],"type":"Point"}
}