{
  "type": "Feature",
  "properties": {
    "iso:country": "GB",
    "wof:name": "LE3 0WB",
    "wof:placetype": "postalcode"
  },
  "geometry": {"coordinates":[-1.167946,52.633016],"type":"Point"}
}
