{
  "type": "Feature",
  "properties": {
    "iso:country":"GB",
    "wof:name":"TS5 5BY",
    "wof:placetype":"postalcode"
},
  "geometry": {"coordinates":[-1.25424047689296,54.55883463999962],"type":"Point"}
}