{
  "type": "Feature",
  "properties": {
    "iso:country":"GB",
    "wof:name":"MK18 2JH",
    "wof:placetype":"postalcode"
},
  "geometry": {"coordinates":[-0.9271684714188,51.9667365600969],"type":"Point"}
}