{
  "type": "Feature",
  "properties": {
    "iso:country": "GB",
    "wof:name": "MK18 2JH",
    "wof:placetype": "postalcode"
  },
  "geometry": {"coordinates":[-0.927168,51.966737],"type":"Point"}
}
