{
  "type": "Feature",
  "properties": {
    "date:inception_lower":"1980-01-01",
    "date:inception_upper":"1980-01-31",
    "iso:country":"GB",
    "wof:name":"MK18 2JH",
    "wof:placetype":"postalcode"
},
  "geometry": {"coordinates":[-0.927168,51.966737],"type":"Point"}
}