{
  "type": "Feature",
  "properties": {
    "date:inception_lower": "2005-03-01",
    "date:inception_upper": "2005-03-01",
    "iso:country": "GB",
    "wof:name": "CT11 9PN",
    "wof:placetype": "postalcode"
  },
  "geometry": {"coordinates":[1.411933,51.328941],"type":"Point"}
}
