{
  "type": "Feature",
  "properties": {
    "iso:country": "GB",
    "wof:name": "CT11 9PN",
    "wof:placetype": "postalcode"
  },
  "geometry": {"coordinates":[1.411933,51.328941],"type":"Point"}
}
