{
  "type": "Feature",
  "properties": {
    "iso:country":"GB",
    "wof:name":"CB21 5EX",
    "wof:placetype":"postalcode"
},
  "geometry": {"coordinates":[0.22826074990716,52.18875246037226],"type":"Point"}
}