{
  "type": "Feature",
  "properties": {
    "iso:country":"GB",
    "wof:name":"BN6 9PH",
    "wof:placetype":"postalcode"
},
  "geometry": {"coordinates":[-0.14760885513772,50.91230154954597],"type":"Point"}
}