{
  "type": "Feature",
  "properties": {
    "iso:country":"GB",
    "wof:name":"G71 7JS",
    "wof:placetype":"postalcode"
},
  "geometry": {"coordinates":[-4.07571173376269,55.82018930675972],"type":"Point"}
}