{
  "type": "Feature",
  "properties": {
    "iso:country":"GB",
    "wof:name":"BN21 2EY",
    "wof:placetype":"postalcode"
},
  "geometry": {"coordinates":[0.27597316971636,50.77322084297738],"type":"Point"}
}