{
  "type": "Feature",
  "properties": {
    "date:inception_lower": "2005-07-01",
    "date:inception_upper": "2005-07-01",
    "iso:country": "GB",
    "wof:name": "HP14 4UA",
    "wof:placetype": "postalcode"
  },
  "geometry": {"coordinates":[-0.793055,51.677375],"type":"Point"}
}
