{
  "type": "Feature",
  "properties": {
    "iso:country": "GB",
    "wof:name": "HP14 4UA",
    "wof:placetype": "postalcode"
  },
  "geometry": {"coordinates":[-0.793055,51.677375],"type":"Point"}
}
