{
  "type": "Feature",
  "properties": {
    "iso:country":"GB",
    "wof:name":"TF1 2ER",
    "wof:placetype":"postalcode"
},
  "geometry": {"coordinates":[-2.52708149163619,52.6903372821908],"type":"Point"}
}