{
  "type": "Feature",
  "properties": {
    "iso:country": "GB",
    "wof:name": "TF1 2ER",
    "wof:placetype": "postalcode"
  },
  "geometry": {"coordinates":[-2.527081,52.690337],"type":"Point"}
}
