{
  "type": "Feature",
  "properties": {
    "iso:country": "GB",
    "wof:name": "PO19 6SE",
    "wof:placetype": "postalcode"
  },
  "geometry": {"coordinates":[-0.768027,50.843553],"type":"Point"}
}
