{
  "type": "Feature",
  "properties": {
    "iso:country":"GB",
    "wof:name":"EH39 4QU",
    "wof:placetype":"postalcode"
},
  "geometry": {"coordinates":[-2.72759335809401,56.0518690416349],"type":"Point"}
}