{
  "type": "Feature",
  "properties": {
    "date:inception_lower": "2004-03-01",
    "date:inception_upper": "2004-03-01",
    "iso:country": "GB",
    "wof:name": "KY15 7NY",
    "wof:placetype": "postalcode"
  },
  "geometry": {"coordinates":[-3.182268,56.250714],"type":"Point"}
}
