{
  "type": "Feature",
  "properties": {
    "iso:country":"GB",
    "wof:name":"CW6 0NA",
    "wof:placetype":"postalcode"
},
  "geometry": {"coordinates":[-2.69631268695126,53.1901304191675],"type":"Point"}
}