{
  "type": "Feature",
  "properties": {
    "date:inception_lower": "1980-01-01",
    "date:inception_upper": "1980-01-01",
    "iso:country": "GB",
    "wof:name": "CW6 0NA",
    "wof:placetype": "postalcode"
  },
  "geometry": {"coordinates":[-2.696313,53.19013],"type":"Point"}
}
