{
  "type": "Feature",
  "properties": {
    "iso:country":"GB",
    "wof:name":"TS6 6LL",
    "wof:placetype":"postalcode"
},
  "geometry": {"coordinates":[-1.17590726092315,54.57470116046319],"type":"Point"}
}