{
  "type": "Feature",
  "properties": {
    "date:inception_lower":"1980-01-01",
    "date:inception_upper":"1980-01-31",
    "iso:country":"GB",
    "wof:name":"IP12 4EQ",
    "wof:placetype":"postalcode"
},
  "geometry": {"coordinates":[1.294837,52.088328],"type":"Point"}
}