{
  "type": "Feature",
  "properties": {
    "iso:country":"GB",
    "wof:name":"ST4 4EH",
    "wof:placetype":"postalcode"
},
  "geometry": {"coordinates":[-2.18325197884702,52.99728684680328],"type":"Point"}
}