{
  "type": "Feature",
  "properties": {
    "iso:country": "GB",
    "wof:name": "PE13 4PD",
    "wof:placetype": "postalcode"
  },
  "geometry": {"coordinates":[0.083091,52.685751],"type":"Point"}
}
