{
  "type": "Feature",
  "properties": {
    "iso:country":"GB",
    "wof:name":"CF81 9LG",
    "wof:placetype":"postalcode"
},
  "geometry": {"coordinates":[-3.29700757365477,51.74066874311411],"type":"Point"}
}