{
  "type": "Feature",
  "properties": {
    "iso:country":"GB",
    "wof:name":"CF82 8EZ",
    "wof:placetype":"postalcode"
},
  "geometry": {"coordinates":[-3.2525542624049,51.66142210055224],"type":"Point"}
}