{
  "type": "Feature",
  "properties": {
    "iso:country":"GB",
    "wof:name":"G67 2PQ",
    "wof:placetype":"postalcode"
},
  "geometry": {"coordinates":[-3.98717664657627,55.94024262514493],"type":"Point"}
}