{
  "type": "Feature",
  "properties": {
    "iso:country":"GB",
    "wof:name":"CO3 4SR",
    "wof:placetype":"postalcode"
},
  "geometry": {"coordinates":[0.86075829107638,51.87507688212449],"type":"Point"}
}