{
  "type": "Feature",
  "properties": {
    "date:inception_lower":"1980-01-01",
    "date:inception_upper":"1980-01-31",
    "iso:country":"GB",
    "wof:name":"SE18 2ER",
    "wof:placetype":"postalcode"
},
  "geometry": {"coordinates":[0.08836,51.475242],"type":"Point"}
}