{
  "type": "Feature",
  "properties": {
    "iso:country": "GB",
    "wof:name": "SE18 2ER",
    "wof:placetype": "postalcode"
  },
  "geometry": {"coordinates":[0.08836,51.475242],"type":"Point"}
}
