{
  "type": "Feature",
  "properties": {
    "iso:country": "GB",
    "wof:name": "LU5 4QL",
    "wof:placetype": "postalcode"
  },
  "geometry": {"coordinates":[-0.505315,51.891447],"type":"Point"}
}
