{
  "type": "Feature",
  "properties": {
    "iso:country":"GB",
    "wof:name":"LU5 4QL",
    "wof:placetype":"postalcode"
},
  "geometry": {"coordinates":[-0.50531495710623,51.89144653726613],"type":"Point"}
}