{
  "type": "Feature",
  "properties": {
    "iso:country":"GB",
    "wof:name":"AB42 1EA",
    "wof:placetype":"postalcode"
},
  "geometry": {"coordinates":[-1.7823137112009,57.50452632313458],"type":"Point"}
}