{
  "type": "Feature",
  "properties": {
    "iso:country":"GB",
    "wof:name":"IG8 8LJ",
    "wof:placetype":"postalcode"
},
  "geometry": {"coordinates":[0.04855211778809,51.59331698830226],"type":"Point"}
}