{
  "type": "Feature",
  "properties": {
    "iso:country": "GB",
    "wof:name": "SO41 8PN",
    "wof:placetype": "postalcode"
  },
  "geometry": {"coordinates":[-1.564327,50.795187],"type":"Point"}
}
