{
  "type": "Feature",
  "properties": {
    "iso:country":"GB",
    "wof:name":"TR1 1DR",
    "wof:placetype":"postalcode"
},
  "geometry": {"coordinates":[-5.0517485490462,50.26693598709188],"type":"Point"}
}