{
  "type": "Feature",
  "properties": {
    "iso:country": "GB",
    "wof:name": "TR1 1DR",
    "wof:placetype": "postalcode"
  },
  "geometry": {"coordinates":[-5.051749,50.266936],"type":"Point"}
}
