{
  "type": "Feature",
  "properties": {
    "iso:country":"GB",
    "wof:name":"RG22 6SH",
    "wof:placetype":"postalcode"
},
  "geometry": {"coordinates":[-1.12554697213806,51.25641813567952],"type":"Point"}
}