{
  "type": "Feature",
  "properties": {
    "iso:country":"GB",
    "wof:name":"W1W 8AL",
    "wof:placetype":"postalcode"
},
  "geometry": {"coordinates":[-0.13994634179485,51.5158385499446],"type":"Point"}
}