{
  "type": "Feature",
  "properties": {
    "date:inception_lower": "1993-08-01",
    "date:inception_upper": "1993-08-01",
    "iso:country": "GB",
    "wof:name": "G67 2TS",
    "wof:placetype": "postalcode"
  },
  "geometry": {"coordinates":[-3.987373,55.929234],"type":"Point"}
}
