{
  "type": "Feature",
  "properties": {
    "iso:country": "GB",
    "wof:name": "G67 2TS",
    "wof:placetype": "postalcode"
  },
  "geometry": {"coordinates":[-3.988586,55.92993],"type":"Point"}
}
