{
  "type": "Feature",
  "properties": {
    "date:inception_lower": "1980-01-01",
    "date:inception_upper": "1980-01-01",
    "iso:country": "GB",
    "wof:name": "HG3 3HH",
    "wof:placetype": "postalcode"
  },
  "geometry": {"coordinates":[-1.616677,54.044845],"type":"Point"}
}
