{
  "type": "Feature",
  "properties": {
    "iso:country":"GB",
    "wof:name":"HG3 3HH",
    "wof:placetype":"postalcode"
},
  "geometry": {"coordinates":[-1.6166768193624,54.04484482142632],"type":"Point"}
}