{
  "type": "Feature",
  "properties": {
    "date:inception_lower": "2021-08-01",
    "date:inception_upper": "2021-08-01",
    "iso:country": "GB",
    "wof:name": "CV34 8BA",
    "wof:placetype": "postalcode"
  },
  "geometry": {"coordinates":[-1.55594,52.279104],"type":"Point"}
}
