{
  "type": "Feature",
  "properties": {
    "iso:country":"GB",
    "wof:name":"PL9 9EL",
    "wof:placetype":"postalcode"
},
  "geometry": {"coordinates":[-4.09558350022278,50.35582328929245],"type":"Point"}
}