{
  "type": "Feature",
  "properties": {
    "iso:country":"GB",
    "wof:name":"CW7 2YJ",
    "wof:placetype":"postalcode"
},
  "geometry": {"coordinates":[-2.55192920363608,53.18881059400467],"type":"Point"}
}