{
  "type": "Feature",
  "properties": {
    "iso:country":"GB",
    "wof:name":"N13 4PT",
    "wof:placetype":"postalcode"
},
  "geometry": {"coordinates":[-0.11602660731464,51.62006606204295],"type":"Point"}
}