{
  "type": "Feature",
  "properties": {
    "date:inception_lower": "2003-02-01",
    "date:inception_upper": "2003-02-01",
    "iso:country": "GB",
    "wof:name": "WN8 9TQ",
    "wof:placetype": "postalcode"
  },
  "geometry": {"coordinates":[-2.792289,53.538971],"type":"Point"}
}
