{
  "type": "Feature",
  "properties": {
    "iso:country":"GB",
    "wof:name":"WN8 9TQ",
    "wof:placetype":"postalcode"
},
  "geometry": {"coordinates":[-2.79228992834894,53.53895451044788],"type":"Point"}
}