{
  "type": "Feature",
  "properties": {
    "iso:country": "GB",
    "wof:name": "WN8 9TQ",
    "wof:placetype": "postalcode"
  },
  "geometry": {"coordinates":[-2.791946,53.539171],"type":"Point"}
}
