{
  "type": "Feature",
  "properties": {
    "date:inception_lower":"2003-02-01",
    "date:inception_upper":"2003-02-28",
    "iso:country":"GB",
    "wof:name":"WN8 9TQ",
    "wof:placetype":"postalcode"
},
  "geometry": {"coordinates":[-2.791946,53.539171],"type":"Point"}
}