{
  "type": "Feature",
  "properties": {
    "date:inception_lower": "1995-07-01",
    "date:inception_upper": "1995-07-01",
    "iso:country": "GB",
    "wof:name": "OX1 4TZ",
    "wof:placetype": "postalcode"
  },
  "geometry": {"coordinates":[-1.253559,51.734553],"type":"Point"}
}
