{
  "type": "Feature",
  "properties": {
    "iso:country":"GB",
    "wof:name":"OX1 4TZ",
    "wof:placetype":"postalcode"
},
  "geometry": {"coordinates":[-1.25355928150942,51.73455340365088],"type":"Point"}
}