{
  "type": "Feature",
  "properties": {
    "iso:country": "GB",
    "wof:name": "CT2 0QL",
    "wof:placetype": "postalcode"
  },
  "geometry": {"coordinates":[1.100088,51.311925],"type":"Point"}
}
