{
  "type": "Feature",
  "properties": {
    "iso:country":"GB",
    "wof:name":"DH9 7NE",
    "wof:placetype":"postalcode"
},
  "geometry": {"coordinates":[-1.698828236011,54.86018238989222],"type":"Point"}
}