{
  "type": "Feature",
  "properties": {
    "iso:country":"GB",
    "wof:name":"RG24 7JG",
    "wof:placetype":"postalcode"
},
  "geometry": {"coordinates":[-1.04027177025139,51.26378021031038],"type":"Point"}
}