{
  "type": "Feature",
  "properties": {
    "date:inception_lower": "1993-08-01",
    "date:inception_upper": "1993-08-01",
    "iso:country": "GB",
    "wof:name": "RG24 7JG",
    "wof:placetype": "postalcode"
  },
  "geometry": {"coordinates":[-1.040272,51.26378],"type":"Point"}
}
