{
  "type": "Feature",
  "properties": {
    "iso:country": "GB",
    "wof:name": "M2 6AF",
    "wof:placetype": "postalcode"
  },
  "geometry": {"coordinates":[-2.246211,53.481392],"type":"Point"}
}
