{
  "type": "Feature",
  "properties": {
    "iso:country":"GB",
    "wof:name":"GL3 2RG",
    "wof:placetype":"postalcode"
},
  "geometry": {"coordinates":[-2.17686580280936,51.87979047986199],"type":"Point"}
}