{
  "type": "Feature",
  "properties": {
    "iso:country":"GB",
    "wof:name":"TD1 1PB",
    "wof:placetype":"postalcode"
},
  "geometry": {"coordinates":[-2.81277877502227,55.61851759813934],"type":"Point"}
}