{
  "type": "Feature",
  "properties": {
    "iso:country":"GB",
    "wof:name":"ST2 0NA",
    "wof:placetype":"postalcode"
},
  "geometry": {"coordinates":[-2.12824589993104,53.01828577353417],"type":"Point"}
}