{
  "type": "Feature",
  "properties": {
    "date:inception_lower": "1999-06-01",
    "date:inception_upper": "1999-06-01",
    "iso:country": "GB",
    "wof:name": "TS21 1DP",
    "wof:placetype": "postalcode"
  },
  "geometry": {"coordinates":[-1.407349,54.541402],"type":"Point"}
}
