{
  "type": "Feature",
  "properties": {
    "date:inception_lower": "1990-02-01",
    "date:inception_upper": "1990-02-01",
    "iso:country": "GB",
    "wof:name": "LL11 6YS",
    "wof:placetype": "postalcode"
  },
  "geometry": {"coordinates":[-3.029459,53.054557],"type":"Point"}
}
