{
  "type": "Feature",
  "properties": {
    "iso:country":"GB",
    "wof:name":"LL11 6YS",
    "wof:placetype":"postalcode"
},
  "geometry": {"coordinates":[-3.02945886656678,53.05455708865945],"type":"Point"}
}