{
  "type": "Feature",
  "properties": {
    "date:inception_lower": "1980-01-01",
    "date:inception_upper": "1980-01-01",
    "iso:country": "GB",
    "wof:name": "DL10 7HD",
    "wof:placetype": "postalcode"
  },
  "geometry": {"coordinates":[-1.670738,54.399835],"type":"Point"}
}
