{
  "type": "Feature",
  "properties": {
    "iso:country":"GB",
    "wof:name":"G78 3RB",
    "wof:placetype":"postalcode"
},
  "geometry": {"coordinates":[-4.43780174159138,55.77875887063335],"type":"Point"}
}