{
  "type": "Feature",
  "properties": {
    "iso:country": "GB",
    "wof:name": "G78 3RB",
    "wof:placetype": "postalcode"
  },
  "geometry": {"coordinates":[-4.437802,55.778759],"type":"Point"}
}
