{
  "type": "Feature",
  "properties": {
    "iso:country":"GB",
    "wof:name":"PO16 8RE",
    "wof:placetype":"postalcode"
},
  "geometry": {"coordinates":[-1.16118141349885,50.85302108366142],"type":"Point"}
}