{
  "type": "Feature",
  "properties": {
    "date:inception_lower":"1980-01-01",
    "date:inception_upper":"1980-01-31",
    "iso:country":"GB",
    "wof:name":"TA7 9BW",
    "wof:placetype":"postalcode"
},
  "geometry": {"coordinates":[-2.839722,51.123666],"type":"Point"}
}