{
  "type": "Feature",
  "properties": {
    "iso:country":"GB",
    "wof:name":"TA7 9BW",
    "wof:placetype":"postalcode"
},
  "geometry": {"coordinates":[-2.83972225919697,51.12366566050077],"type":"Point"}
}