{
  "type": "Feature",
  "properties": {
    "iso:country": "GB",
    "wof:name": "TA7 9BW",
    "wof:placetype": "postalcode"
  },
  "geometry": {"coordinates":[-2.839722,51.123666],"type":"Point"}
}
