{
  "type": "Feature",
  "properties": {
    "iso:country":"GB",
    "wof:name":"OX3 8NR",
    "wof:placetype":"postalcode"
},
  "geometry": {"coordinates":[-1.20439421098376,51.75613373422859],"type":"Point"}
}