{
  "type": "Feature",
  "properties": {
    "iso:country":"GB",
    "wof:name":"WN3 4HW",
    "wof:placetype":"postalcode"
},
  "geometry": {"coordinates":[-2.63275204015926,53.54207164167181],"type":"Point"}
}