{
  "type": "Feature",
  "properties": {
    "iso:country": "GB",
    "wof:name": "RH19 2QE",
    "wof:placetype": "postalcode"
  },
  "geometry": {"coordinates":[-0.072088,51.139459],"type":"Point"}
}
