{
  "type": "Feature",
  "properties": {
    "iso:country": "GB",
    "wof:name": "DN15 6HA",
    "wof:placetype": "postalcode"
  },
  "geometry": {"coordinates":[-0.647655,53.592375],"type":"Point"}
}
