{
  "type": "Feature",
  "properties": {
    "date:inception_lower": "1993-08-01",
    "date:inception_upper": "1993-08-01",
    "iso:country": "GB",
    "wof:name": "BH25 6UH",
    "wof:placetype": "postalcode"
  },
  "geometry": {"coordinates":[-1.666477,50.74645],"type":"Point"}
}
