{
  "type": "Feature",
  "properties": {
    "iso:country":"GB",
    "wof:name":"ME8 8AJ",
    "wof:placetype":"postalcode"
},
  "geometry": {"coordinates":[0.61961330417313,51.36077709993952],"type":"Point"}
}