{
  "type": "Feature",
  "properties": {
    "date:inception_lower": "1980-01-01",
    "date:inception_upper": "1980-01-01",
    "iso:country": "GB",
    "wof:name": "ME8 8AJ",
    "wof:placetype": "postalcode"
  },
  "geometry": {"coordinates":[0.619613,51.360777],"type":"Point"}
}
