{
  "type": "Feature",
  "properties": {
    "iso:country":"GB",
    "wof:name":"NN8 4LT",
    "wof:placetype":"postalcode"
},
  "geometry": {"coordinates":[-0.69911073453042,52.30209748387512],"type":"Point"}
}