{
  "type": "Feature",
  "properties": {
    "iso:country": "GB",
    "wof:name": "NN8 4LT",
    "wof:placetype": "postalcode"
  },
  "geometry": {"coordinates":[-0.700827,52.302575],"type":"Point"}
}
