{
  "type": "Feature",
  "properties": {
    "iso:country":"GB",
    "wof:name":"PL20 6BG",
    "wof:placetype":"postalcode"
},
  "geometry": {"coordinates":[-4.07986170144931,50.49355565413795],"type":"Point"}
}