{
  "type": "Feature",
  "properties": {
    "iso:country": "GB",
    "wof:name": "ST3 4PF",
    "wof:placetype": "postalcode"
  },
  "geometry": {"coordinates":[-2.133996,52.978538],"type":"Point"}
}
