{
  "type": "Feature",
  "properties": {
    "iso:country":"GB",
    "wof:name":"LE10 0XN",
    "wof:placetype":"postalcode"
},
  "geometry": {"coordinates":[-1.38858302823414,52.54345371197824],"type":"Point"}
}