{
  "type": "Feature",
  "properties": {
    "date:inception_lower": "1980-01-01",
    "date:inception_upper": "1980-01-01",
    "iso:country": "GB",
    "wof:name": "E8 2BQ",
    "wof:placetype": "postalcode"
  },
  "geometry": {"coordinates":[-0.066354,51.553604],"type":"Point"}
}
