{
  "type": "Feature",
  "properties": {
    "date:inception_lower": "1980-01-01",
    "date:inception_upper": "1980-01-01",
    "iso:country": "GB",
    "wof:name": "BB12 9DZ",
    "wof:placetype": "postalcode"
  },
  "geometry": {"coordinates":[-2.262824,53.832552],"type":"Point"}
}
