{
  "type": "Feature",
  "properties": {
    "date:inception_lower": "1980-01-01",
    "date:inception_upper": "1980-01-01",
    "iso:country": "GB",
    "wof:name": "RG10 8QZ",
    "wof:placetype": "postalcode"
  },
  "geometry": {"coordinates":[-0.822392,51.519803],"type":"Point"}
}
