{
  "type": "Feature",
  "properties": {
    "iso:country":"GB",
    "wof:name":"RG10 8QZ",
    "wof:placetype":"postalcode"
},
  "geometry": {"coordinates":[-0.82124965444758,51.52012182273506],"type":"Point"}
}