{
  "type": "Feature",
  "properties": {
    "iso:country": "GB",
    "wof:name": "N19 4PT",
    "wof:placetype": "postalcode"
  },
  "geometry": {"coordinates":[-0.129008,51.559119],"type":"Point"}
}
