{
  "type": "Feature",
  "properties": {
    "iso:country":"GB",
    "wof:name":"N19 4PT",
    "wof:placetype":"postalcode"
},
  "geometry": {"coordinates":[-0.12909045484528,51.55916254581975],"type":"Point"}
}