{
  "type": "Feature",
  "properties": {
    "iso:country": "GB",
    "wof:name": "N11 2BQ",
    "wof:placetype": "postalcode"
  },
  "geometry": {"coordinates":[-0.126672,51.614916],"type":"Point"}
}
