{
  "type": "Feature",
  "properties": {
    "date:inception_lower": "2016-07-01",
    "date:inception_upper": "2016-07-01",
    "iso:country": "GB",
    "wof:name": "N11 2BQ",
    "wof:placetype": "postalcode"
  },
  "geometry": {"coordinates":[-0.126672,51.614916],"type":"Point"}
}
