{
  "type": "Feature",
  "properties": {
    "iso:country":"GB",
    "wof:name":"LL14 6AE",
    "wof:placetype":"postalcode"
},
  "geometry": {"coordinates":[-3.03644632151443,52.9882255368744],"type":"Point"}
}