{
  "type": "Feature",
  "properties": {
    "iso:country": "GB",
    "wof:name": "TQ13 8HR",
    "wof:placetype": "postalcode"
  },
  "geometry": {"coordinates":[-3.883216,50.680091],"type":"Point"}
}
