{
  "type": "Feature",
  "properties": {
    "iso:country":"GB",
    "wof:name":"TQ13 8HR",
    "wof:placetype":"postalcode"
},
  "geometry": {"coordinates":[-3.88321564291786,50.68009058461552],"type":"Point"}
}