{
  "type": "Feature",
  "properties": {
    "iso:country": "GB",
    "wof:name": "SE10 0LF",
    "wof:placetype": "postalcode"
  },
  "geometry": {"coordinates":[0.008011,51.500981],"type":"Point"}
}
