{
  "type": "Feature",
  "properties": {
    "iso:country":"GB",
    "wof:name":"NW10 3BH",
    "wof:placetype":"postalcode"
},
  "geometry": {"coordinates":[-0.23283354896159,51.53677026831251],"type":"Point"}
}