{
  "type": "Feature",
  "properties": {
    "iso:country": "GB",
    "wof:name": "WA14 5EZ",
    "wof:placetype": "postalcode"
  },
  "geometry": {"coordinates":[-2.355153,53.401542],"type":"Point"}
}
