{
  "type": "Feature",
  "properties": {
    "iso:country": "GB",
    "wof:name": "YO25 9AZ",
    "wof:placetype": "postalcode"
  },
  "geometry": {"coordinates":[-0.456155,53.895702],"type":"Point"}
}
