{
  "type": "Feature",
  "properties": {
    "iso:country":"GB",
    "wof:name":"DD8 4PZ",
    "wof:placetype":"postalcode"
},
  "geometry": {"coordinates":[-3.00181576115067,56.71096588161709],"type":"Point"}
}