{
  "type": "Feature",
  "properties": {
    "iso:country":"GB",
    "wof:name":"ST7 3BS",
    "wof:placetype":"postalcode"
},
  "geometry": {"coordinates":[-2.24964145798862,53.10772290195256],"type":"Point"}
}