{
  "type": "Feature",
  "properties": {
    "date:inception_lower": "1980-01-01",
    "date:inception_upper": "1980-01-01",
    "iso:country": "GB",
    "wof:name": "PR7 6JY",
    "wof:placetype": "postalcode"
  },
  "geometry": {"coordinates":[-2.679395,53.674737],"type":"Point"}
}
