{
  "type": "Feature",
  "properties": {
    "iso:country":"GB",
    "wof:name":"GU30 7TB",
    "wof:placetype":"postalcode"
},
  "geometry": {"coordinates":[-0.80162212110298,51.07814514661669],"type":"Point"}
}