{
  "type": "Feature",
  "properties": {
    "iso:country":"GB",
    "wof:name":"S13 8JA",
    "wof:placetype":"postalcode"
},
  "geometry": {"coordinates":[-1.39617962930775,53.37074810972868],"type":"Point"}
}