{
  "type": "Feature",
  "properties": {
    "date:inception_lower": "1982-03-01",
    "date:inception_upper": "1982-03-01",
    "iso:country": "GB",
    "wof:name": "S13 8JA",
    "wof:placetype": "postalcode"
  },
  "geometry": {"coordinates":[-1.39615,53.370739],"type":"Point"}
}
