{
  "type": "Feature",
  "properties": {
    "date:inception_lower":"1980-01-01",
    "date:inception_upper":"1980-01-31",
    "iso:country":"GB",
    "wof:name":"LS19 7HZ",
    "wof:placetype":"postalcode"
},
  "geometry": {"coordinates":[-1.70264,53.867049],"type":"Point"}
}