{
  "type": "Feature",
  "properties": {
    "iso:country": "GB",
    "wof:name": "NN9 5RY",
    "wof:placetype": "postalcode"
  },
  "geometry": {"coordinates":[-0.6134,52.324714],"type":"Point"}
}
