{
  "type": "Feature",
  "properties": {
    "iso:country":"GB",
    "wof:name":"NN9 5RY",
    "wof:placetype":"postalcode"
},
  "geometry": {"coordinates":[-0.61334398207711,52.32462393539468],"type":"Point"}
}