{
  "type": "Feature",
  "properties": {
    "iso:country": "GB",
    "wof:name": "SW19 3JF",
    "wof:placetype": "postalcode"
  },
  "geometry": {"coordinates":[-0.203778,51.40922],"type":"Point"}
}
