{
  "type": "Feature",
  "properties": {
    "iso:country":"GB",
    "wof:name":"BD8 7HP",
    "wof:placetype":"postalcode"
},
  "geometry": {"coordinates":[-1.76245581628951,53.80395260533749],"type":"Point"}
}