{
  "type": "Feature",
  "properties": {
    "iso:country": "GB",
    "wof:name": "B80 7SH",
    "wof:placetype": "postalcode"
  },
  "geometry": {"coordinates":[-1.89231,52.273276],"type":"Point"}
}
