{
  "type": "Feature",
  "properties": {
    "iso:country":"GB",
    "wof:name":"OX33 1HY",
    "wof:placetype":"postalcode"
},
  "geometry": {"coordinates":[-1.14095299567354,51.74156198871272],"type":"Point"}
}