{
  "type": "Feature",
  "properties": {
    "date:inception_lower":"2011-02-01",
    "date:inception_upper":"2011-02-28",
    "iso:country":"GB",
    "wof:name":"WC2H 8AR",
    "wof:placetype":"postalcode"
},
  "geometry": {"coordinates":[-0.127368,51.516079],"type":"Point"}
}