{
  "type": "Feature",
  "properties": {
    "iso:country": "GB",
    "wof:name": "LL14 2AS",
    "wof:placetype": "postalcode"
  },
  "geometry": {"coordinates":[-3.04063,53.003597],"type":"Point"}
}
