{
  "type": "Feature",
  "properties": {
    "iso:country":"GB",
    "wof:name":"LL14 2AS",
    "wof:placetype":"postalcode"
},
  "geometry": {"coordinates":[-3.04062955576779,53.00359712357024],"type":"Point"}
}