{
  "type": "Feature",
  "properties": {
    "date:inception_lower": "1980-01-01",
    "date:inception_upper": "1980-01-01",
    "iso:country": "GB",
    "wof:name": "LL14 2AS",
    "wof:placetype": "postalcode"
  },
  "geometry": {"coordinates":[-3.04063,53.003597],"type":"Point"}
}
