{
  "type": "Feature",
  "properties": {
    "iso:country":"GB",
    "wof:name":"N17 9PA",
    "wof:placetype":"postalcode"
},
  "geometry": {"coordinates":[-0.05884330638896,51.58668953136449],"type":"Point"}
}