{
  "type": "Feature",
  "properties": {
    "date:inception_lower": "1981-06-01",
    "date:inception_upper": "1981-06-01",
    "iso:country": "GB",
    "wof:name": "N17 9PA",
    "wof:placetype": "postalcode"
  },
  "geometry": {"coordinates":[-0.058843,51.58669],"type":"Point"}
}
