{
  "type": "Feature",
  "properties": {
    "date:inception_lower": "1980-01-01",
    "date:inception_upper": "1980-01-01",
    "iso:country": "GB",
    "wof:name": "RH1 4HE",
    "wof:placetype": "postalcode"
  },
  "geometry": {"coordinates":[-0.132163,51.238749],"type":"Point"}
}
