{
  "type": "Feature",
  "properties": {
    "iso:country":"GB",
    "wof:name":"RH1 4HE",
    "wof:placetype":"postalcode"
},
  "geometry": {"coordinates":[-0.13216258844953,51.23874856116021],"type":"Point"}
}