{
  "type": "Feature",
  "properties": {
    "date:inception_lower":"2015-12-01",
    "date:inception_upper":"2015-12-31",
    "iso:country":"GB",
    "wof:name":"BN17 7AX",
    "wof:placetype":"postalcode"
},
  "geometry": {"coordinates":[-0.559533,50.824654],"type":"Point"}
}