{
  "type": "Feature",
  "properties": {
    "iso:country":"GB",
    "wof:name":"BN17 7AX",
    "wof:placetype":"postalcode"
},
  "geometry": {"coordinates":[-0.55955636928092,50.82466434142007],"type":"Point"}
}