{
  "type": "Feature",
  "properties": {
    "iso:country": "GB",
    "wof:name": "BN17 7AX",
    "wof:placetype": "postalcode"
  },
  "geometry": {"coordinates":[-0.559533,50.824654],"type":"Point"}
}
