{
  "type": "Feature",
  "properties": {
    "iso:country":"GB",
    "wof:name":"HA4 0EL",
    "wof:placetype":"postalcode"
},
  "geometry": {"coordinates":[-0.38666824907601,51.55644042214568],"type":"Point"}
}