{
  "type": "Feature",
  "properties": {
    "iso:country": "GB",
    "wof:name": "HR6 0EW",
    "wof:placetype": "postalcode"
  },
  "geometry": {"coordinates":[-2.699722,52.242061],"type":"Point"}
}
