{
  "type": "Feature",
  "properties": {
    "iso:country":"GB",
    "wof:name":"HR6 0EW",
    "wof:placetype":"postalcode"
},
  "geometry": {"coordinates":[-2.69972247740709,52.24204870223191],"type":"Point"}
}