{
  "type": "Feature",
  "properties": {
    "iso:country":"GB",
    "wof:name":"E3 4AX",
    "wof:placetype":"postalcode"
},
  "geometry": {"coordinates":[-0.02217303352366,51.51728389082661],"type":"Point"}
}