{
  "type": "Feature",
  "properties": {
    "iso:country": "GB",
    "wof:name": "FK8 1SF",
    "wof:placetype": "postalcode"
  },
  "geometry": {"coordinates":[-3.953265,56.12581],"type":"Point"}
}
