{
  "type": "Feature",
  "properties": {
    "iso:country": "GB",
    "wof:name": "CV34 6HN",
    "wof:placetype": "postalcode"
  },
  "geometry": {"coordinates":[-1.59696,52.279755],"type":"Point"}
}
