{
  "type": "Feature",
  "properties": {
    "date:inception_lower": "1993-01-01",
    "date:inception_upper": "1993-01-01",
    "iso:country": "GB",
    "wof:name": "CV34 6HN",
    "wof:placetype": "postalcode"
  },
  "geometry": {"coordinates":[-1.596191,52.278943],"type":"Point"}
}
