{
  "type": "Feature",
  "properties": {
    "iso:country": "GB",
    "wof:name": "YO30 6LY",
    "wof:placetype": "postalcode"
  },
  "geometry": {"coordinates":[-1.098881,53.967211],"type":"Point"}
}
