{
  "type": "Feature",
  "properties": {
    "iso:country":"GB",
    "wof:name":"YO30 6LY",
    "wof:placetype":"postalcode"
},
  "geometry": {"coordinates":[-1.09888081696172,53.96721093180627],"type":"Point"}
}