{
  "type": "Feature",
  "properties": {
    "iso:country":"GB",
    "wof:name":"SL6 3XU",
    "wof:placetype":"postalcode"
},
  "geometry": {"coordinates":[-0.75745762624574,51.50472582765101],"type":"Point"}
}