{
  "type": "Feature",
  "properties": {
    "date:inception_lower": "2021-02-01",
    "date:inception_upper": "2021-02-01",
    "iso:country": "GB",
    "wof:name": "BS24 7NQ",
    "wof:placetype": "postalcode"
  },
  "geometry": {"coordinates":[-2.901763,51.356213],"type":"Point"}
}
