{
  "type": "Feature",
  "properties": {
    "iso:country": "GB",
    "wof:name": "MK44 2HX",
    "wof:placetype": "postalcode"
  },
  "geometry": {"coordinates":[-0.422783,52.250952],"type":"Point"}
}
