{
  "type": "Feature",
  "properties": {
    "iso:country":"GB",
    "wof:name":"G46 6QB",
    "wof:placetype":"postalcode"
},
  "geometry": {"coordinates":[-4.29716326122869,55.79613662272811],"type":"Point"}
}