{
  "type": "Feature",
  "properties": {
    "date:inception_lower": "1980-01-01",
    "date:inception_upper": "1980-01-01",
    "iso:country": "GB",
    "wof:name": "RG7 1JX",
    "wof:placetype": "postalcode"
  },
  "geometry": {"coordinates":[-1.005258,51.399735],"type":"Point"}
}
