{
  "type": "Feature",
  "properties": {
    "iso:country": "GB",
    "wof:name": "BD3 8NN",
    "wof:placetype": "postalcode"
  },
  "geometry": {"coordinates":[-1.712496,53.793498],"type":"Point"}
}
