{
  "type": "Feature",
  "properties": {
    "iso:country":"GB",
    "wof:name":"SW16 1QL",
    "wof:placetype":"postalcode"
},
  "geometry": {"coordinates":[-0.13723183048175,51.42899921609376],"type":"Point"}
}