{
  "type": "Feature",
  "properties": {
    "iso:country":"GB",
    "wof:name":"NE22 7JG",
    "wof:placetype":"postalcode"
},
  "geometry": {"coordinates":[-1.56680956577543,55.14121466528363],"type":"Point"}
}