{
  "type": "Feature",
  "properties": {
    "iso:country": "GB",
    "wof:name": "NE22 7JG",
    "wof:placetype": "postalcode"
  },
  "geometry": {"coordinates":[-1.56681,55.141215],"type":"Point"}
}
