{
  "type": "Feature",
  "properties": {
    "iso:country": "GB",
    "wof:name": "IP13 8AZ",
    "wof:placetype": "postalcode"
  },
  "geometry": {"coordinates":[1.32233,52.276614],"type":"Point"}
}
