{
  "type": "Feature",
  "properties": {
    "iso:country":"GB",
    "wof:name":"IP13 8AZ",
    "wof:placetype":"postalcode"
},
  "geometry": {"coordinates":[1.32220096311535,52.27725465566067],"type":"Point"}
}