{
  "type": "Feature",
  "properties": {
    "iso:country":"GB",
    "wof:name":"EX2 6HP",
    "wof:placetype":"postalcode"
},
  "geometry": {"coordinates":[-3.50249290698982,50.70582104374261],"type":"Point"}
}