{
  "type": "Feature",
  "properties": {
    "iso:country":"GB",
    "wof:name":"B26 3HY",
    "wof:placetype":"postalcode"
},
  "geometry": {"coordinates":[-1.78632758196439,52.45493942600333],"type":"Point"}
}