{
  "type": "Feature",
  "properties": {
    "iso:country":"GB",
    "wof:name":"EX8 1RX",
    "wof:placetype":"postalcode"
},
  "geometry": {"coordinates":[-3.41227701639914,50.62276301050223],"type":"Point"}
}