{
  "type": "Feature",
  "properties": {
    "date:inception_lower": "1980-01-01",
    "date:inception_upper": "1980-01-01",
    "iso:country": "GB",
    "wof:name": "EX8 1RX",
    "wof:placetype": "postalcode"
  },
  "geometry": {"coordinates":[-3.412277,50.622763],"type":"Point"}
}
