{
  "type": "Feature",
  "properties": {
    "iso:country":"GB",
    "wof:name":"NR19 1LX",
    "wof:placetype":"postalcode"
},
  "geometry": {"coordinates":[0.94540961233929,52.66168686026958],"type":"Point"}
}