{
  "type": "Feature",
  "properties": {
    "iso:country":"GB",
    "wof:name":"CM13 3PG",
    "wof:placetype":"postalcode"
},
  "geometry": {"coordinates":[0.34975150080278,51.59596376433625],"type":"Point"}
}