{
  "type": "Feature",
  "properties": {
    "iso:country":"GB",
    "wof:name":"B71 2QA",
    "wof:placetype":"postalcode"
},
  "geometry": {"coordinates":[-2.00905305716375,52.53713773794888],"type":"Point"}
}