{
  "type": "Feature",
  "properties": {
    "date:inception_lower": "1991-01-01",
    "date:inception_upper": "1991-01-01",
    "iso:country": "GB",
    "wof:name": "DY4 9AW",
    "wof:placetype": "postalcode"
  },
  "geometry": {"coordinates":[-2.072943,52.532612],"type":"Point"}
}
