{
  "type": "Feature",
  "properties": {
    "iso:country": "GB",
    "wof:name": "BB10 4NL",
    "wof:placetype": "postalcode"
  },
  "geometry": {"coordinates":[-2.214377,53.786442],"type":"Point"}
}
