{
  "type": "Feature",
  "properties": {
    "iso:country":"GB",
    "wof:name":"BB10 4NL",
    "wof:placetype":"postalcode"
},
  "geometry": {"coordinates":[-2.21437719696266,53.78644173874282],"type":"Point"}
}