{
  "type": "Feature",
  "properties": {
    "date:inception_lower": "1980-01-01",
    "date:inception_upper": "1980-01-01",
    "iso:country": "GB",
    "wof:name": "BB10 4NL",
    "wof:placetype": "postalcode"
  },
  "geometry": {"coordinates":[-2.214377,53.786442],"type":"Point"}
}
