{
  "type": "Feature",
  "properties": {
    "iso:country":"GB",
    "wof:name":"DN10 4QB",
    "wof:placetype":"postalcode"
},
  "geometry": {"coordinates":[-0.82568967479867,53.39686544435],"type":"Point"}
}