{
  "type": "Feature",
  "properties": {
    "iso:country": "GB",
    "wof:name": "DN10 4QB",
    "wof:placetype": "postalcode"
  },
  "geometry": {"coordinates":[-0.82569,53.396865],"type":"Point"}
}
