{
  "type": "Feature",
  "properties": {
    "iso:country":"GB",
    "wof:name":"UB3 2DP",
    "wof:placetype":"postalcode"
},
  "geometry": {"coordinates":[-0.41074827601222,51.51657394981451],"type":"Point"}
}