{
  "type": "Feature",
  "properties": {
    "iso:country": "GB",
    "wof:name": "DD1 2HQ",
    "wof:placetype": "postalcode"
  },
  "geometry": {"coordinates":[-2.965231,56.464087],"type":"Point"}
}
