{
  "type": "Feature",
  "properties": {
    "iso:country":"GB",
    "wof:name":"SS13 2JX",
    "wof:placetype":"postalcode"
},
  "geometry": {"coordinates":[0.53137467760031,51.57577310983559],"type":"Point"}
}