{
  "type": "Feature",
  "properties": {
    "iso:country":"GB",
    "wof:name":"L35 4PX",
    "wof:placetype":"postalcode"
},
  "geometry": {"coordinates":[-2.76721897287093,53.42331702350603],"type":"Point"}
}