{
  "type": "Feature",
  "properties": {
    "date:inception_lower":"1980-01-01",
    "date:inception_upper":"1980-01-31",
    "iso:country":"GB",
    "wof:name":"L35 4PX",
    "wof:placetype":"postalcode"
},
  "geometry": {"coordinates":[-2.767219,53.423317],"type":"Point"}
}