{
  "type": "Feature",
  "properties": {
    "iso:country": "GB",
    "wof:name": "L35 4PX",
    "wof:placetype": "postalcode"
  },
  "geometry": {"coordinates":[-2.767219,53.423317],"type":"Point"}
}
