{
  "type": "Feature",
  "properties": {
    "date:inception_lower": "1980-01-01",
    "date:inception_upper": "1980-01-01",
    "iso:country": "GB",
    "wof:name": "WV14 8BQ",
    "wof:placetype": "postalcode"
  },
  "geometry": {"coordinates":[-2.056219,52.550573],"type":"Point"}
}
