{
  "type": "Feature",
  "properties": {
    "iso:country":"GB",
    "wof:name":"GL7 3EG",
    "wof:placetype":"postalcode"
},
  "geometry": {"coordinates":[-1.69466482313789,51.69906003980807],"type":"Point"}
}