{
  "type": "Feature",
  "properties": {
    "iso:country": "GB",
    "wof:name": "LL61 5RZ",
    "wof:placetype": "postalcode"
  },
  "geometry": {"coordinates":[-4.19889,53.222915],"type":"Point"}
}
