{
  "type": "Feature",
  "properties": {
    "iso:country": "GB",
    "wof:name": "YO62 4JW",
    "wof:placetype": "postalcode"
  },
  "geometry": {"coordinates":[-1.056009,54.189809],"type":"Point"}
}
