{
  "type": "Feature",
  "properties": {
    "date:inception_lower": "1998-06-01",
    "date:inception_upper": "1998-06-01",
    "iso:country": "GB",
    "wof:name": "YO62 4JW",
    "wof:placetype": "postalcode"
  },
  "geometry": {"coordinates":[-1.056009,54.189809],"type":"Point"}
}
