{
  "type": "Feature",
  "properties": {
    "iso:country":"GB",
    "wof:name":"YO62 4JW",
    "wof:placetype":"postalcode"
},
  "geometry": {"coordinates":[-1.05600941473546,54.18980902502719],"type":"Point"}
}