{
  "type": "Feature",
  "properties": {
    "iso:country":"GB",
    "wof:name":"CO2 8HW",
    "wof:placetype":"postalcode"
},
  "geometry": {"coordinates":[0.92650663407943,51.87730812056235],"type":"Point"}
}