{
  "type": "Feature",
  "properties": {
    "iso:country": "GB",
    "wof:name": "CO2 8HW",
    "wof:placetype": "postalcode"
  },
  "geometry": {"coordinates":[0.926507,51.877308],"type":"Point"}
}
