{
  "type": "Feature",
  "properties": {
    "iso:country":"GB",
    "wof:name":"G60 5HG",
    "wof:placetype":"postalcode"
},
  "geometry": {"coordinates":[-4.45408317031273,55.92063301357044],"type":"Point"}
}