{
  "type": "Feature",
  "properties": {
    "date:inception_lower": "1980-01-01",
    "date:inception_upper": "1980-01-01",
    "iso:country": "GB",
    "wof:name": "G60 5HG",
    "wof:placetype": "postalcode"
  },
  "geometry": {"coordinates":[-4.454083,55.920633],"type":"Point"}
}
