{
  "type": "Feature",
  "properties": {
    "date:inception_lower": "1999-12-01",
    "date:inception_upper": "1999-12-01",
    "iso:country": "GB",
    "wof:name": "LE4 8PT",
    "wof:placetype": "postalcode"
  },
  "geometry": {"coordinates":[-1.085095,52.67919],"type":"Point"}
}
