{
  "type": "Feature",
  "properties": {
    "iso:country": "GB",
    "wof:name": "CF24 5FA",
    "wof:placetype": "postalcode"
  },
  "geometry": {"coordinates":[-3.1541,51.476481],"type":"Point"}
}
