{
  "type": "Feature",
  "properties": {
    "iso:country":"GB",
    "wof:name":"CF24 5FA",
    "wof:placetype":"postalcode"
},
  "geometry": {"coordinates":[-3.15410014142939,51.47648131250408],"type":"Point"}
}