{
  "type": "Feature",
  "properties": {
    "date:inception_lower": "1999-12-01",
    "date:inception_upper": "1999-12-01",
    "iso:country": "GB",
    "wof:name": "NE6 1LB",
    "wof:placetype": "postalcode"
  },
  "geometry": {"coordinates":[-1.586911,54.973098],"type":"Point"}
}
