{
  "type": "Feature",
  "properties": {
    "iso:country": "GB",
    "wof:name": "SK6 6LR",
    "wof:placetype": "postalcode"
  },
  "geometry": {"coordinates":[-2.067744,53.399166],"type":"Point"}
}
