{
  "type": "Feature",
  "properties": {
    "iso:country":"GB",
    "wof:name":"SK6 6LR",
    "wof:placetype":"postalcode"
},
  "geometry": {"coordinates":[-2.06774376076717,53.399166315271],"type":"Point"}
}