{
  "type": "Feature",
  "properties": {
    "date:inception_lower": "1980-01-01",
    "date:inception_upper": "1980-01-01",
    "iso:country": "GB",
    "wof:name": "CF46 6AL",
    "wof:placetype": "postalcode"
  },
  "geometry": {"coordinates":[-3.296292,51.668581],"type":"Point"}
}
