{
  "type": "Feature",
  "properties": {
    "iso:country": "GB",
    "wof:name": "PA15 3ES",
    "wof:placetype": "postalcode"
  },
  "geometry": {"coordinates":[-4.741363,55.932774],"type":"Point"}
}
