{
  "type": "Feature",
  "properties": {
    "iso:country":"GB",
    "wof:name":"PA15 3ES",
    "wof:placetype":"postalcode"
},
  "geometry": {"coordinates":[-4.74138264843768,55.93278069502947],"type":"Point"}
}