{
  "type": "Feature",
  "properties": {
    "iso:country":"GB",
    "wof:name":"CO15 3BH",
    "wof:placetype":"postalcode"
},
  "geometry": {"coordinates":[1.14651948962168,51.79357454379223],"type":"Point"}
}