{
  "type": "Feature",
  "properties": {
    "date:inception_lower":"1995-07-01",
    "date:inception_upper":"1995-07-31",
    "iso:country":"GB",
    "wof:name":"HS3 3BL",
    "wof:placetype":"postalcode"
},
  "geometry": {"coordinates":[-6.788135,57.899073],"type":"Point"}
}