{
  "type": "Feature",
  "properties": {
    "iso:country":"GB",
    "wof:name":"HS3 3BL",
    "wof:placetype":"postalcode"
},
  "geometry": {"coordinates":[-6.78813542042513,57.89907263149334],"type":"Point"}
}