{
  "type": "Feature",
  "properties": {
    "date:inception_lower": "2016-06-01",
    "date:inception_upper": "2016-06-01",
    "iso:country": "GB",
    "wof:name": "M13 9JT",
    "wof:placetype": "postalcode"
  },
  "geometry": {"coordinates":[-2.218886,53.465518],"type":"Point"}
}
