{
  "type": "Feature",
  "properties": {
    "iso:country": "GB",
    "wof:name": "IP13 8FE",
    "wof:placetype": "postalcode"
  },
  "geometry": {"coordinates":[1.384051,52.265137],"type":"Point"}
}
