{
  "type": "Feature",
  "properties": {
    "date:inception_lower": "1980-01-01",
    "date:inception_upper": "1980-01-01",
    "iso:country": "GB",
    "wof:name": "PO21 3NL",
    "wof:placetype": "postalcode"
  },
  "geometry": {"coordinates":[-0.72879,50.780515],"type":"Point"}
}
