{
  "type": "Feature",
  "properties": {
    "iso:country":"GB",
    "wof:name":"BL2 4BX",
    "wof:placetype":"postalcode"
},
  "geometry": {"coordinates":[-2.39127990892632,53.60929620149857],"type":"Point"}
}