{
  "type": "Feature",
  "properties": {
    "iso:country":"GB",
    "wof:name":"DY2 0JL",
    "wof:placetype":"postalcode"
},
  "geometry": {"coordinates":[-2.08896431768907,52.48773188550982],"type":"Point"}
}