{
  "type": "Feature",
  "properties": {
    "iso:country":"GB",
    "wof:name":"DH6 2UY",
    "wof:placetype":"postalcode"
},
  "geometry": {"coordinates":[-1.41559310604052,54.80242723631616],"type":"Point"}
}