{
  "type": "Feature",
  "properties": {
    "iso:country":"GB",
    "wof:name":"DE6 3AW",
    "wof:placetype":"postalcode"
},
  "geometry": {"coordinates":[-1.67606657975428,52.97038883438765],"type":"Point"}
}