{
  "type": "Feature",
  "properties": {
    "iso:country": "GB",
    "wof:name": "DE6 3AW",
    "wof:placetype": "postalcode"
  },
  "geometry": {"coordinates":[-1.676067,52.970389],"type":"Point"}
}
