{
  "type": "Feature",
  "properties": {
    "iso:country":"GB",
    "wof:name":"SE11 5NN",
    "wof:placetype":"postalcode"
},
  "geometry": {"coordinates":[-0.1183469414494,51.48982030486682],"type":"Point"}
}