{
  "type": "Feature",
  "properties": {
    "iso:country": "GB",
    "wof:name": "SE11 5NN",
    "wof:placetype": "postalcode"
  },
  "geometry": {"coordinates":[-0.118347,51.48982],"type":"Point"}
}
