{
  "type": "Feature",
  "properties": {
    "iso:country":"GB",
    "wof:name":"SL4 5NL",
    "wof:placetype":"postalcode"
},
  "geometry": {"coordinates":[-0.6370143964274,51.48066534518179],"type":"Point"}
}