{
  "type": "Feature",
  "properties": {
    "date:inception_lower":"1980-01-01",
    "date:inception_upper":"1980-01-31",
    "iso:country":"GB",
    "wof:name":"ME16 0PW",
    "wof:placetype":"postalcode"
},
  "geometry": {"coordinates":[0.495496,51.289417],"type":"Point"}
}