{
  "type": "Feature",
  "properties": {
    "iso:country": "GB",
    "wof:name": "GU15 2SA",
    "wof:placetype": "postalcode"
  },
  "geometry": {"coordinates":[-0.755419,51.321185],"type":"Point"}
}
