{
  "type": "Feature",
  "properties": {
    "iso:country": "GB",
    "wof:name": "S72 0EA",
    "wof:placetype": "postalcode"
  },
  "geometry": {"coordinates":[-1.342884,53.55032],"type":"Point"}
}
