{
  "type": "Feature",
  "properties": {
    "iso:country":"GB",
    "wof:name":"S72 0EA",
    "wof:placetype":"postalcode"
},
  "geometry": {"coordinates":[-1.34288398505498,53.55032037831327],"type":"Point"}
}