{
  "type": "Feature",
  "properties": {
    "date:inception_lower": "1986-02-01",
    "date:inception_upper": "1986-02-01",
    "iso:country": "GB",
    "wof:name": "G31 2PB",
    "wof:placetype": "postalcode"
  },
  "geometry": {"coordinates":[-4.219963,55.863136],"type":"Point"}
}
