{
  "type": "Feature",
  "properties": {
    "iso:country": "GB",
    "wof:name": "WR8 9HF",
    "wof:placetype": "postalcode"
  },
  "geometry": {"coordinates":[-2.131356,52.119722],"type":"Point"}
}
