{
  "type": "Feature",
  "properties": {
    "iso:country": "GB",
    "wof:name": "HG4 4LB",
    "wof:placetype": "postalcode"
  },
  "geometry": {"coordinates":[-1.717197,54.21649],"type":"Point"}
}
