{
  "type": "Feature",
  "properties": {
    "iso:country":"GB",
    "wof:name":"HG4 4LB",
    "wof:placetype":"postalcode"
},
  "geometry": {"coordinates":[-1.71712784070955,54.21663104077673],"type":"Point"}
}