{
  "type": "Feature",
  "properties": {
    "date:inception_lower":"1980-01-01",
    "date:inception_upper":"1980-01-31",
    "iso:country":"GB",
    "wof:name":"HG4 4LB",
    "wof:placetype":"postalcode"
},
  "geometry": {"coordinates":[-1.717134,54.216643],"type":"Point"}
}