{
  "type": "Feature",
  "properties": {
    "date:inception_lower": "1980-01-01",
    "date:inception_upper": "1980-01-01",
    "iso:country": "GB",
    "wof:name": "CW4 8ER",
    "wof:placetype": "postalcode"
  },
  "geometry": {"coordinates":[-2.372367,53.214533],"type":"Point"}
}
