{
  "type": "Feature",
  "properties": {
    "iso:country": "GB",
    "wof:name": "CW4 8ER",
    "wof:placetype": "postalcode"
  },
  "geometry": {"coordinates":[-2.372367,53.214533],"type":"Point"}
}
