{
  "type": "Feature",
  "properties": {
    "iso:country":"GB",
    "wof:name":"CW4 8ER",
    "wof:placetype":"postalcode"
},
  "geometry": {"coordinates":[-2.37236694798962,53.21453260059735],"type":"Point"}
}