{
  "type": "Feature",
  "properties": {
    "iso:country":"GB",
    "wof:name":"HP1 3ES",
    "wof:placetype":"postalcode"
},
  "geometry": {"coordinates":[-0.48718706875076,51.76298431277932],"type":"Point"}
}