{
  "type": "Feature",
  "properties": {
    "iso:country":"GB",
    "wof:name":"N4 1FJ",
    "wof:placetype":"postalcode"
},
  "geometry": {"coordinates":[-0.08754137024831,51.57567731998039],"type":"Point"}
}