{
  "type": "Feature",
  "properties": {
    "date:inception_lower": "2000-06-01",
    "date:inception_upper": "2000-06-01",
    "iso:country": "GB",
    "wof:name": "OL11 4NJ",
    "wof:placetype": "postalcode"
  },
  "geometry": {"coordinates":[-2.169105,53.605907],"type":"Point"}
}
