{
  "type": "Feature",
  "properties": {
    "iso:country": "GB",
    "wof:name": "CA23 3DP",
    "wof:placetype": "postalcode"
  },
  "geometry": {"coordinates":[-3.519881,54.508754],"type":"Point"}
}
