{
  "type": "Feature",
  "properties": {
    "iso:country":"GB",
    "wof:name":"CA23 3DP",
    "wof:placetype":"postalcode"
},
  "geometry": {"coordinates":[-3.51987926346248,54.5087450611226],"type":"Point"}
}