{
  "type": "Feature",
  "properties": {
    "iso:country": "GB",
    "wof:name": "CW7 3FD",
    "wof:placetype": "postalcode"
  },
  "geometry": {"coordinates":[-2.508043,53.202211],"type":"Point"}
}
