{
  "type": "Feature",
  "properties": {
    "iso:country":"GB",
    "wof:name":"CW7 3FD",
    "wof:placetype":"postalcode"
},
  "geometry": {"coordinates":[-2.50804293647438,53.20221069666647],"type":"Point"}
}