{
  "type": "Feature",
  "properties": {
    "iso:country":"GB",
    "wof:name":"DD7 7QJ",
    "wof:placetype":"postalcode"
},
  "geometry": {"coordinates":[-2.72652741546701,56.50030320112155],"type":"Point"}
}