{
  "type": "Feature",
  "properties": {
    "date:inception_lower":"1980-01-01",
    "date:inception_upper":"1980-01-31",
    "iso:country":"GB",
    "wof:name":"DL14 9SZ",
    "wof:placetype":"postalcode"
},
  "geometry": {"coordinates":[-1.689811,54.640159],"type":"Point"}
}