{
  "type": "Feature",
  "properties": {
    "iso:country": "GB",
    "wof:name": "DL14 9SZ",
    "wof:placetype": "postalcode"
  },
  "geometry": {"coordinates":[-1.689811,54.640159],"type":"Point"}
}
