{
  "type": "Feature",
  "properties": {
    "iso:country":"GB",
    "wof:name":"BH23 5AP",
    "wof:placetype":"postalcode"
},
  "geometry": {"coordinates":[-1.71199317588133,50.7514730261156],"type":"Point"}
}