{
  "type": "Feature",
  "properties": {
    "date:inception_lower": "1980-01-01",
    "date:inception_upper": "1980-01-01",
    "iso:country": "GB",
    "wof:name": "NR19 1EE",
    "wof:placetype": "postalcode"
  },
  "geometry": {"coordinates":[0.959542,52.671754],"type":"Point"}
}
