{
  "type": "Feature",
  "properties": {
    "date:inception_lower":"1980-01-01",
    "date:inception_upper":"1980-01-31",
    "iso:country":"GB",
    "wof:name":"CW5 5NN",
    "wof:placetype":"postalcode"
},
  "geometry": {"coordinates":[-2.522211,53.073372],"type":"Point"}
}