{
  "type": "Feature",
  "properties": {
    "iso:country": "GB",
    "wof:name": "HP13 6UL",
    "wof:placetype": "postalcode"
  },
  "geometry": {"coordinates":[-0.731834,51.638709],"type":"Point"}
}
