{
  "type": "Feature",
  "properties": {
    "iso:country":"GB",
    "wof:name":"HP13 6UL",
    "wof:placetype":"postalcode"
},
  "geometry": {"coordinates":[-0.73183442192467,51.63870897019481],"type":"Point"}
}