{
  "type": "Feature",
  "properties": {
    "date:inception_lower": "1980-01-01",
    "date:inception_upper": "1980-01-01",
    "iso:country": "GB",
    "wof:name": "EH32 0EL",
    "wof:placetype": "postalcode"
  },
  "geometry": {"coordinates":[-2.946288,55.97058],"type":"Point"}
}
