{
  "type": "Feature",
  "properties": {
    "iso:country":"GB",
    "wof:name":"KA17 0BN",
    "wof:placetype":"postalcode"
},
  "geometry": {"coordinates":[-4.27754122822484,55.61318866136002],"type":"Point"}
}