{
  "type": "Feature",
  "properties": {
    "iso:country": "GB",
    "wof:name": "NR3 4EQ",
    "wof:placetype": "postalcode"
  },
  "geometry": {"coordinates":[1.311198,52.649496],"type":"Point"}
}
