{
  "type": "Feature",
  "properties": {
    "iso:country":"GB",
    "wof:name":"NR3 4EQ",
    "wof:placetype":"postalcode"
},
  "geometry": {"coordinates":[1.31119839308029,52.64949563209034],"type":"Point"}
}