{
  "type": "Feature",
  "properties": {
    "iso:country":"GB",
    "wof:name":"PR3 1NL",
    "wof:placetype":"postalcode"
},
  "geometry": {"coordinates":[-2.77660034666696,53.91653045845826],"type":"Point"}
}