{
  "type": "Feature",
  "properties": {
    "date:inception_lower": "1980-01-01",
    "date:inception_upper": "1980-01-01",
    "iso:country": "GB",
    "wof:name": "GU14 0AQ",
    "wof:placetype": "postalcode"
  },
  "geometry": {"coordinates":[-0.766064,51.291372],"type":"Point"}
}
