{
  "type": "Feature",
  "properties": {
    "iso:country":"GB",
    "wof:name":"DA11 8LP",
    "wof:placetype":"postalcode"
},
  "geometry": {"coordinates":[0.34301242938382,51.42641604070691],"type":"Point"}
}