{
  "type": "Feature",
  "properties": {
    "date:inception_lower": "1980-01-01",
    "date:inception_upper": "1980-01-01",
    "iso:country": "GB",
    "wof:name": "SW1Y 5JQ",
    "wof:placetype": "postalcode"
  },
  "geometry": {"coordinates":[-0.135988,51.506172],"type":"Point"}
}
