{
  "type": "Feature",
  "properties": {
    "iso:country":"GB",
    "wof:name":"SO51 9DD",
    "wof:placetype":"postalcode"
},
  "geometry": {"coordinates":[-1.40020368047217,51.00217669828152],"type":"Point"}
}