{
  "type": "Feature",
  "properties": {
    "iso:country":"GB",
    "wof:name":"M20 6HF",
    "wof:placetype":"postalcode"
},
  "geometry": {"coordinates":[-2.22331115416553,53.41907481131674],"type":"Point"}
}