{
  "type": "Feature",
  "properties": {
    "date:inception_lower": "1994-05-01",
    "date:inception_upper": "1994-05-01",
    "iso:country": "GB",
    "wof:name": "M20 6HF",
    "wof:placetype": "postalcode"
  },
  "geometry": {"coordinates":[-2.223311,53.419075],"type":"Point"}
}
