{
  "type": "Feature",
  "properties": {
    "iso:country":"GB",
    "wof:name":"DG11 2AA",
    "wof:placetype":"postalcode"
},
  "geometry": {"coordinates":[-3.35592021920828,55.12270153899888],"type":"Point"}
}