{
  "type": "Feature",
  "properties": {
    "iso:country":"GB",
    "wof:name":"TW11 8DY",
    "wof:placetype":"postalcode"
},
  "geometry": {"coordinates":[-0.33031059573025,51.42903102511751],"type":"Point"}
}