{
  "type": "Feature",
  "properties": {
    "iso:country": "GB",
    "wof:name": "WV10 7BX",
    "wof:placetype": "postalcode"
  },
  "geometry": {"coordinates":[-2.12336,52.674509],"type":"Point"}
}
