{
  "type": "Feature",
  "properties": {
    "iso:country":"GB",
    "wof:name":"WV10 7BX",
    "wof:placetype":"postalcode"
},
  "geometry": {"coordinates":[-2.12336001549345,52.67450917374281],"type":"Point"}
}