{
  "type": "Feature",
  "properties": {
    "date:inception_lower": "1995-01-01",
    "date:inception_upper": "1995-01-01",
    "iso:country": "GB",
    "wof:name": "WV10 7BX",
    "wof:placetype": "postalcode"
  },
  "geometry": {"coordinates":[-2.12433,52.673895],"type":"Point"}
}
