{
  "type": "Feature",
  "properties": {
    "iso:country":"GB",
    "wof:name":"NE27 0SF",
    "wof:placetype":"postalcode"
},
  "geometry": {"coordinates":[-1.51754937839267,55.03585606481609],"type":"Point"}
}