{
  "type": "Feature",
  "properties": {
    "date:inception_lower": "1980-01-01",
    "date:inception_upper": "1980-01-01",
    "iso:country": "GB",
    "wof:name": "NE27 0SF",
    "wof:placetype": "postalcode"
  },
  "geometry": {"coordinates":[-1.517549,55.035856],"type":"Point"}
}
