{
  "type": "Feature",
  "properties": {
    "iso:country":"GB",
    "wof:name":"LL61 5JQ",
    "wof:placetype":"postalcode"
},
  "geometry": {"coordinates":[-4.20594335656449,53.22315284559284],"type":"Point"}
}