{
  "type": "Feature",
  "properties": {
    "iso:country": "GB",
    "wof:name": "LL61 5JQ",
    "wof:placetype": "postalcode"
  },
  "geometry": {"coordinates":[-4.205977,53.223124],"type":"Point"}
}
