{
  "type": "Feature",
  "properties": {
    "date:inception_lower": "2003-09-01",
    "date:inception_upper": "2003-09-01",
    "iso:country": "GB",
    "wof:name": "SY7 9QG",
    "wof:placetype": "postalcode"
  },
  "geometry": {"coordinates":[-2.837219,52.444238],"type":"Point"}
}
