{
  "type": "Feature",
  "properties": {
    "iso:country":"GB",
    "wof:name":"SY7 9QG",
    "wof:placetype":"postalcode"
},
  "geometry": {"coordinates":[-2.83721870689731,52.44423770574593],"type":"Point"}
}