{
  "type": "Feature",
  "properties": {
    "iso:country":"GB",
    "wof:name":"TS1 3LS",
    "wof:placetype":"postalcode"
},
  "geometry": {"coordinates":[-1.23102903548542,54.5679191246417],"type":"Point"}
}