{
  "type": "Feature",
  "properties": {
    "date:inception_lower":"1980-01-01",
    "date:inception_upper":"1980-01-31",
    "iso:country":"GB",
    "wof:name":"TS1 3LS",
    "wof:placetype":"postalcode"
},
  "geometry": {"coordinates":[-1.231029,54.567919],"type":"Point"}
}