{
  "type": "Feature",
  "properties": {
    "iso:country": "GB",
    "wof:name": "PE12 6LR",
    "wof:placetype": "postalcode"
  },
  "geometry": {"coordinates":[-0.040465,52.829173],"type":"Point"}
}
