{
  "type": "Feature",
  "properties": {
    "iso:country":"GB",
    "wof:name":"PE12 6LR",
    "wof:placetype":"postalcode"
},
  "geometry": {"coordinates":[-0.04023931933636,52.82914751489867],"type":"Point"}
}