{
  "type": "Feature",
  "properties": {
    "iso:country":"GB",
    "wof:name":"BL5 2JE",
    "wof:placetype":"postalcode"
},
  "geometry": {"coordinates":[-2.51710848954095,53.54523448646111],"type":"Point"}
}