{
  "type": "Feature",
  "properties": {
    "iso:country": "GB",
    "wof:name": "YO8 9TQ",
    "wof:placetype": "postalcode"
  },
  "geometry": {"coordinates":[-1.122301,53.773897],"type":"Point"}
}
