{
  "type": "Feature",
  "properties": {
    "iso:country":"GB",
    "wof:name":"TW15 3QZ",
    "wof:placetype":"postalcode"
},
  "geometry": {"coordinates":[-0.47245525157177,51.42971959001523],"type":"Point"}
}