{
  "type": "Feature",
  "properties": {
    "iso:country":"GB",
    "wof:name":"BS3 3NY",
    "wof:placetype":"postalcode"
},
  "geometry": {"coordinates":[-2.60322708184786,51.4367848250313],"type":"Point"}
}