{
  "type": "Feature",
  "properties": {
    "iso:country":"GB",
    "wof:name":"NR34 9DH",
    "wof:placetype":"postalcode"
},
  "geometry": {"coordinates":[1.56491376388285,52.46142931547312],"type":"Point"}
}