{
  "type": "Feature",
  "properties": {
    "iso:country":"GB",
    "wof:name":"LL53 6BH",
    "wof:placetype":"postalcode"
},
  "geometry": {"coordinates":[-4.55622884719271,52.93457123150774],"type":"Point"}
}