{
  "type": "Feature",
  "properties": {
    "iso:country": "GB",
    "wof:name": "LL53 6BH",
    "wof:placetype": "postalcode"
  },
  "geometry": {"coordinates":[-4.556229,52.934571],"type":"Point"}
}
