{
  "type": "Feature",
  "properties": {
    "date:inception_lower": "1980-01-01",
    "date:inception_upper": "1980-01-01",
    "iso:country": "GB",
    "wof:name": "LL53 6BH",
    "wof:placetype": "postalcode"
  },
  "geometry": {"coordinates":[-4.556229,52.934571],"type":"Point"}
}
