{
  "type": "Feature",
  "properties": {
    "iso:country":"GB",
    "wof:name":"TS9 6DS",
    "wof:placetype":"postalcode"
},
  "geometry": {"coordinates":[-1.14165629835244,54.4929853993923],"type":"Point"}
}