{
  "type": "Feature",
  "properties": {
    "iso:country": "GB",
    "wof:name": "TS9 6DS",
    "wof:placetype": "postalcode"
  },
  "geometry": {"coordinates":[-1.141626,54.492976],"type":"Point"}
}
