{
  "type": "Feature",
  "properties": {
    "iso:country":"GB",
    "wof:name":"ML6 7ES",
    "wof:placetype":"postalcode"
},
  "geometry": {"coordinates":[-3.95933830896586,55.86933370789401],"type":"Point"}
}