{
  "type": "Feature",
  "properties": {
    "date:inception_lower":"1980-01-01",
    "date:inception_upper":"1980-01-31",
    "iso:country":"GB",
    "wof:name":"PL26 7AY",
    "wof:placetype":"postalcode"
},
  "geometry": {"coordinates":[-4.814157,50.32224],"type":"Point"}
}