{
  "type": "Feature",
  "properties": {
    "iso:country": "GB",
    "wof:name": "BB3 0BY",
    "wof:placetype": "postalcode"
  },
  "geometry": {"coordinates":[-2.478302,53.707698],"type":"Point"}
}
