{
  "type": "Feature",
  "properties": {
    "iso:country":"GB",
    "wof:name":"B34 7QD",
    "wof:placetype":"postalcode"
},
  "geometry": {"coordinates":[-1.76946485272128,52.49413110523505],"type":"Point"}
}