{
  "type": "Feature",
  "properties": {
    "iso:country":"GB",
    "wof:name":"IP14 3JF",
    "wof:placetype":"postalcode"
},
  "geometry": {"coordinates":[0.92412738876127,52.20677131079294],"type":"Point"}
}