{
  "type": "Feature",
  "properties": {
    "iso:country": "GB",
    "wof:name": "IP14 3JF",
    "wof:placetype": "postalcode"
  },
  "geometry": {"coordinates":[0.924127,52.206771],"type":"Point"}
}
