{
  "type": "Feature",
  "properties": {
    "date:inception_lower": "2019-03-01",
    "date:inception_upper": "2019-03-01",
    "iso:country": "GB",
    "wof:name": "NE2 2PA",
    "wof:placetype": "postalcode"
  },
  "geometry": {"coordinates":[-1.600667,54.988052],"type":"Point"}
}
