{
  "type": "Feature",
  "properties": {
    "iso:country": "GB",
    "wof:name": "NE2 2PA",
    "wof:placetype": "postalcode"
  },
  "geometry": {"coordinates":[-1.600667,54.988052],"type":"Point"}
}
