{
  "type": "Feature",
  "properties": {
    "iso:country": "GB",
    "wof:name": "LE10 2LY",
    "wof:placetype": "postalcode"
  },
  "geometry": {"coordinates":[-1.371395,52.526588],"type":"Point"}
}
