{
  "type": "Feature",
  "properties": {
    "iso:country":"GB",
    "wof:name":"AB32 6WW",
    "wof:placetype":"postalcode"
},
  "geometry": {"coordinates":[-2.28740139043528,57.15477544864716],"type":"Point"}
}