{
  "type": "Feature",
  "properties": {
    "date:inception_lower": "1995-12-01",
    "date:inception_upper": "1995-12-01",
    "iso:country": "GB",
    "wof:name": "M33 7UL",
    "wof:placetype": "postalcode"
  },
  "geometry": {"coordinates":[-2.323947,53.423626],"type":"Point"}
}
