{
  "type": "Feature",
  "properties": {
    "iso:country":"GB",
    "wof:name":"M11 4JF",
    "wof:placetype":"postalcode"
},
  "geometry": {"coordinates":[-2.17956406198866,53.48873756271511],"type":"Point"}
}