{
  "type": "Feature",
  "properties": {
    "iso:country":"GB",
    "wof:name":"NN8 1PE",
    "wof:placetype":"postalcode"
},
  "geometry": {"coordinates":[-0.68803292966821,52.30375514800988],"type":"Point"}
}