{
  "type": "Feature",
  "properties": {
    "date:inception_lower": "1980-01-01",
    "date:inception_upper": "1980-01-01",
    "iso:country": "GB",
    "wof:name": "TA21 8DA",
    "wof:placetype": "postalcode"
  },
  "geometry": {"coordinates":[-3.228975,50.975414],"type":"Point"}
}
