{
  "type": "Feature",
  "properties": {
    "iso:country":"GB",
    "wof:name":"BB9 6QB",
    "wof:placetype":"postalcode"
},
  "geometry": {"coordinates":[-2.23417945045286,53.8400537621058],"type":"Point"}
}