{
  "type": "Feature",
  "properties": {
    "iso:country": "GB",
    "wof:name": "BB9 6QB",
    "wof:placetype": "postalcode"
  },
  "geometry": {"coordinates":[-2.234179,53.840054],"type":"Point"}
}
