{
  "type": "Feature",
  "properties": {
    "iso:country":"GB",
    "wof:name":"SY10 9LG",
    "wof:placetype":"postalcode"
},
  "geometry": {"coordinates":[-3.24771853605961,52.81233990577641],"type":"Point"}
}