{
  "type": "Feature",
  "properties": {
    "iso:country": "GB",
    "wof:name": "DH1 1GG",
    "wof:placetype": "postalcode"
  },
  "geometry": {"coordinates":[-1.542472,54.788377],"type":"Point"}
}
