{
  "type": "Feature",
  "properties": {
    "iso:country":"GB",
    "wof:name":"NG22 9RG",
    "wof:placetype":"postalcode"
},
  "geometry": {"coordinates":[-1.01729550820468,53.20383830413239],"type":"Point"}
}