{
  "type": "Feature",
  "properties": {
    "iso:country": "GB",
    "wof:name": "WR12 7FD",
    "wof:placetype": "postalcode"
  },
  "geometry": {"coordinates":[-1.859309,52.041891],"type":"Point"}
}
