{
  "type": "Feature",
  "properties": {
    "iso:country":"GB",
    "wof:name":"AB15 6JQ",
    "wof:placetype":"postalcode"
},
  "geometry": {"coordinates":[-2.16647844122338,57.14932609365064],"type":"Point"}
}