{
  "type": "Feature",
  "properties": {
    "iso:country": "GB",
    "wof:name": "LU7 0FW",
    "wof:placetype": "postalcode"
  },
  "geometry": {"coordinates":[-0.678296,51.960251],"type":"Point"}
}
