{
  "type": "Feature",
  "properties": {
    "iso:country":"GB",
    "wof:name":"WF3 3DX",
    "wof:placetype":"postalcode"
},
  "geometry": {"coordinates":[-1.52890254884195,53.7327875439692],"type":"Point"}
}