{
  "type": "Feature",
  "properties": {
    "date:inception_lower": "2003-11-01",
    "date:inception_upper": "2003-11-01",
    "iso:country": "GB",
    "wof:name": "G33 6BJ",
    "wof:placetype": "postalcode"
  },
  "geometry": {"coordinates":[-4.134837,55.889753],"type":"Point"}
}
