{
  "type": "Feature",
  "properties": {
    "iso:country":"GB",
    "wof:name":"G33 6BJ",
    "wof:placetype":"postalcode"
},
  "geometry": {"coordinates":[-4.13483739542957,55.88975333459739],"type":"Point"}
}