{
  "type": "Feature",
  "properties": {
    "iso:country":"GB",
    "wof:name":"UB1 1RW",
    "wof:placetype":"postalcode"
},
  "geometry": {"coordinates":[-0.38011931300354,51.50972552882997],"type":"Point"}
}