{
  "type": "Feature",
  "properties": {
    "iso:country": "GB",
    "wof:name": "UB1 1RW",
    "wof:placetype": "postalcode"
  },
  "geometry": {"coordinates":[-0.380119,51.509726],"type":"Point"}
}
