{
  "type": "Feature",
  "properties": {
    "iso:country":"GB",
    "wof:name":"ML4 2RB",
    "wof:placetype":"postalcode"
},
  "geometry": {"coordinates":[-4.00435626583546,55.81335686314521],"type":"Point"}
}