{
  "type": "Feature",
  "properties": {
    "iso:country": "GB",
    "wof:name": "ML4 2RB",
    "wof:placetype": "postalcode"
  },
  "geometry": {"coordinates":[-4.004356,55.813357],"type":"Point"}
}
