{
  "type": "Feature",
  "properties": {
    "iso:country": "GB",
    "wof:name": "TR10 9AP",
    "wof:placetype": "postalcode"
  },
  "geometry": {"coordinates":[-5.133786,50.180441],"type":"Point"}
}
