{
  "type": "Feature",
  "properties": {
    "date:inception_lower":"1980-01-01",
    "date:inception_upper":"1980-01-31",
    "iso:country":"GB",
    "wof:name":"TR10 9AP",
    "wof:placetype":"postalcode"
},
  "geometry": {"coordinates":[-5.133786,50.180441],"type":"Point"}
}