{
  "type": "Feature",
  "properties": {
    "date:inception_lower":"1986-04-01",
    "date:inception_upper":"1986-04-30",
    "iso:country":"GB",
    "wof:name":"BD17 6NG",
    "wof:placetype":"postalcode"
},
  "geometry": {"coordinates":[-1.765629,53.85365],"type":"Point"}
}