{
  "type": "Feature",
  "properties": {
    "iso:country": "GB",
    "wof:name": "BD17 6NG",
    "wof:placetype": "postalcode"
  },
  "geometry": {"coordinates":[-1.765629,53.85365],"type":"Point"}
}
