{
  "type": "Feature",
  "properties": {
    "iso:country":"GB",
    "wof:name":"G21 4EL",
    "wof:placetype":"postalcode"
},
  "geometry": {"coordinates":[-4.21615916970527,55.87967891062478],"type":"Point"}
}