{
  "type": "Feature",
  "properties": {
    "iso:country":"GB",
    "wof:name":"E13 9PY",
    "wof:placetype":"postalcode"
},
  "geometry": {"coordinates":[0.03674087873905,51.52580786468472],"type":"Point"}
}