{
  "type": "Feature",
  "properties": {
    "date:inception_lower":"1990-02-01",
    "date:inception_upper":"1990-02-28",
    "iso:country":"GB",
    "wof:name":"SW19 1TL",
    "wof:placetype":"postalcode"
},
  "geometry": {"coordinates":[-0.180797,51.423425],"type":"Point"}
}