{
  "type": "Feature",
  "properties": {
    "iso:country": "GB",
    "wof:name": "SW19 1TL",
    "wof:placetype": "postalcode"
  },
  "geometry": {"coordinates":[-0.180797,51.423425],"type":"Point"}
}
