{
  "type": "Feature",
  "properties": {
    "iso:country":"GB",
    "wof:name":"WN6 0NJ",
    "wof:placetype":"postalcode"
},
  "geometry": {"coordinates":[-2.66256845176028,53.58829067823062],"type":"Point"}
}