{
  "type": "Feature",
  "properties": {
    "iso:country":"GB",
    "wof:name":"HX2 9SX",
    "wof:placetype":"postalcode"
},
  "geometry": {"coordinates":[-1.8807636167664,53.75763345039115],"type":"Point"}
}