{
  "type": "Feature",
  "properties": {
    "iso:country": "GB",
    "wof:name": "SE25 4FG",
    "wof:placetype": "postalcode"
  },
  "geometry": {"coordinates":[-0.075152,51.401746],"type":"Point"}
}
