{
  "type": "Feature",
  "properties": {
    "iso:country":"GB",
    "wof:name":"SE25 4FG",
    "wof:placetype":"postalcode"
},
  "geometry": {"coordinates":[-0.07515243499735,51.40174639629886],"type":"Point"}
}