{
  "type": "Feature",
  "properties": {
    "date:inception_lower":"2012-08-01",
    "date:inception_upper":"2012-08-31",
    "iso:country":"GB",
    "wof:name":"SE25 4FG",
    "wof:placetype":"postalcode"
},
  "geometry": {"coordinates":[-0.075152,51.401746],"type":"Point"}
}