{
  "type": "Feature",
  "properties": {
    "date:inception_lower":"2013-12-01",
    "date:inception_upper":"2013-12-31",
    "iso:country":"GB",
    "wof:name":"TF4 2GL",
    "wof:placetype":"postalcode"
},
  "geometry": {"coordinates":[-2.487907,52.673353],"type":"Point"}
}