{
  "type": "Feature",
  "properties": {
    "iso:country":"GB",
    "wof:name":"WD7 8ER",
    "wof:placetype":"postalcode"
},
  "geometry": {"coordinates":[-0.32507731844225,51.69322025997745],"type":"Point"}
}