{
  "type": "Feature",
  "properties": {
    "iso:country":"GB",
    "wof:name":"LS12 3AJ",
    "wof:placetype":"postalcode"
},
  "geometry": {"coordinates":[-1.5995927424434,53.79751584252475],"type":"Point"}
}