{
  "type": "Feature",
  "properties": {
    "iso:country": "GB",
    "wof:name": "DE12 6BQ",
    "wof:placetype": "postalcode"
  },
  "geometry": {"coordinates":[-1.585304,52.744264],"type":"Point"}
}
