{
  "type": "Feature",
  "properties": {
    "iso:country":"GB",
    "wof:name":"CB22 7SF",
    "wof:placetype":"postalcode"
},
  "geometry": {"coordinates":[0.01981283419691,52.13166716298119],"type":"Point"}
}