{
  "type": "Feature",
  "properties": {
    "iso:country":"GB",
    "wof:name":"B77 4HU",
    "wof:placetype":"postalcode"
},
  "geometry": {"coordinates":[-1.64602637878635,52.6146685969937],"type":"Point"}
}