{
  "type": "Feature",
  "properties": {
    "iso:country":"GB",
    "wof:name":"HU6 9JN",
    "wof:placetype":"postalcode"
},
  "geometry": {"coordinates":[-0.37382363962901,53.785011860322],"type":"Point"}
}