{
  "type": "Feature",
  "properties": {
    "iso:country": "GB",
    "wof:name": "HU6 9JN",
    "wof:placetype": "postalcode"
  },
  "geometry": {"coordinates":[-0.373824,53.785012],"type":"Point"}
}
