{
  "type": "Feature",
  "properties": {
    "iso:country":"GB",
    "wof:name":"NG5 2AZ",
    "wof:placetype":"postalcode"
},
  "geometry": {"coordinates":[-1.15319988448877,52.97517772382391],"type":"Point"}
}