{
  "type": "Feature",
  "properties": {
    "iso:country": "GB",
    "wof:name": "NG5 2AZ",
    "wof:placetype": "postalcode"
  },
  "geometry": {"coordinates":[-1.153197,52.975198],"type":"Point"}
}
