{
  "type": "Feature",
  "properties": {
    "date:inception_lower": "1981-06-01",
    "date:inception_upper": "1981-06-01",
    "iso:country": "GB",
    "wof:name": "NG5 2AZ",
    "wof:placetype": "postalcode"
  },
  "geometry": {"coordinates":[-1.153197,52.975198],"type":"Point"}
}
