{
  "type": "Feature",
  "properties": {
    "date:inception_lower": "1980-01-01",
    "date:inception_upper": "1980-01-01",
    "iso:country": "GB",
    "wof:name": "L34 6JN",
    "wof:placetype": "postalcode"
  },
  "geometry": {"coordinates":[-2.793026,53.434582],"type":"Point"}
}
