{
  "type": "Feature",
  "properties": {
    "date:inception_lower":"2010-05-01",
    "date:inception_upper":"2010-05-31",
    "iso:country":"GB",
    "wof:name":"IP2 8FB",
    "wof:placetype":"postalcode"
},
  "geometry": {"coordinates":[1.156173,52.047758],"type":"Point"}
}