{
  "type": "Feature",
  "properties": {
    "iso:country":"GB",
    "wof:name":"IP2 8FB",
    "wof:placetype":"postalcode"
},
  "geometry": {"coordinates":[1.15617332062341,52.04775800662098],"type":"Point"}
}