{
  "type": "Feature",
  "properties": {
    "iso:country": "GB",
    "wof:name": "IP2 8FB",
    "wof:placetype": "postalcode"
  },
  "geometry": {"coordinates":[1.156173,52.047758],"type":"Point"}
}
