{
  "type": "Feature",
  "properties": {
    "date:inception_lower": "2004-01-01",
    "date:inception_upper": "2004-01-01",
    "iso:country": "GB",
    "wof:name": "IP1 1TG",
    "wof:placetype": "postalcode"
  },
  "geometry": {"coordinates":[1.152076,52.055863],"type":"Point"}
}
