{
  "type": "Feature",
  "properties": {
    "iso:country":"GB",
    "wof:name":"HU13 0QJ",
    "wof:placetype":"postalcode"
},
  "geometry": {"coordinates":[-0.43954291089917,53.72540701420012],"type":"Point"}
}