{
  "type": "Feature",
  "properties": {
    "iso:country": "GB",
    "wof:name": "CW1 3DG",
    "wof:placetype": "postalcode"
  },
  "geometry": {"coordinates":[-2.448098,53.101442],"type":"Point"}
}
