{
  "type": "Feature",
  "properties": {
    "iso:country": "GB",
    "wof:name": "S72 7FT",
    "wof:placetype": "postalcode"
  },
  "geometry": {"coordinates":[-1.379275,53.577085],"type":"Point"}
}
