{
  "type": "Feature",
  "properties": {
    "date:inception_lower": "2008-04-01",
    "date:inception_upper": "2008-04-01",
    "iso:country": "GB",
    "wof:name": "S72 7FT",
    "wof:placetype": "postalcode"
  },
  "geometry": {"coordinates":[-1.379275,53.577085],"type":"Point"}
}
