{
  "type": "Feature",
  "properties": {
    "iso:country":"GB",
    "wof:name":"NP4 6JH",
    "wof:placetype":"postalcode"
},
  "geometry": {"coordinates":[-3.0388062046084,51.70368186725053],"type":"Point"}
}