{
  "type": "Feature",
  "properties": {
    "iso:country":"GB",
    "wof:name":"HU15 1ST",
    "wof:placetype":"postalcode"
},
  "geometry": {"coordinates":[-0.56402960707779,53.72894097676473],"type":"Point"}
}