{
  "type": "Feature",
  "properties": {
    "date:inception_lower": "1980-01-01",
    "date:inception_upper": "1980-01-01",
    "iso:country": "GB",
    "wof:name": "DN22 0QD",
    "wof:placetype": "postalcode"
  },
  "geometry": {"coordinates":[-0.938486,53.27709],"type":"Point"}
}
