{
  "type": "Feature",
  "properties": {
    "iso:country": "GB",
    "wof:name": "KY11 4TA",
    "wof:placetype": "postalcode"
  },
  "geometry": {"coordinates":[-3.453268,56.066068],"type":"Point"}
}
