{
  "type": "Feature",
  "properties": {
    "date:inception_lower": "1980-01-01",
    "date:inception_upper": "1980-01-01",
    "iso:country": "GB",
    "wof:name": "KY11 4TA",
    "wof:placetype": "postalcode"
  },
  "geometry": {"coordinates":[-3.453268,56.066068],"type":"Point"}
}
