{
  "type": "Feature",
  "properties": {
    "iso:country":"GB",
    "wof:name":"KY11 4TA",
    "wof:placetype":"postalcode"
},
  "geometry": {"coordinates":[-3.45326806668334,56.06606820424668],"type":"Point"}
}