{
  "type": "Feature",
  "properties": {
    "iso:country":"GB",
    "wof:name":"L40 4AZ",
    "wof:placetype":"postalcode"
},
  "geometry": {"coordinates":[-2.8251396437214,53.61494631631768],"type":"Point"}
}