{
  "type": "Feature",
  "properties": {
    "iso:country":"GB",
    "wof:name":"AB45 2NS",
    "wof:placetype":"postalcode"
},
  "geometry": {"coordinates":[-2.57689354578545,57.67891317275443],"type":"Point"}
}