{
  "type": "Feature",
  "properties": {
    "iso:country":"GB",
    "wof:name":"CA10 2QB",
    "wof:placetype":"postalcode"
},
  "geometry": {"coordinates":[-2.75927393653322,54.58229341289407],"type":"Point"}
}