{
  "type": "Feature",
  "properties": {
    "iso:country": "GB",
    "wof:name": "CA10 2QB",
    "wof:placetype": "postalcode"
  },
  "geometry": {"coordinates":[-2.759274,54.582293],"type":"Point"}
}
