{
  "type": "Feature",
  "properties": {
    "iso:country":"GB",
    "wof:name":"TR2 5ER",
    "wof:placetype":"postalcode"
},
  "geometry": {"coordinates":[-4.989962741683,50.18370531599107],"type":"Point"}
}