{
  "type": "Feature",
  "properties": {
    "iso:country": "GB",
    "wof:name": "TR2 5ER",
    "wof:placetype": "postalcode"
  },
  "geometry": {"coordinates":[-4.989963,50.183705],"type":"Point"}
}
