{
  "type": "Feature",
  "properties": {
    "date:inception_lower": "1980-01-01",
    "date:inception_upper": "1980-01-01",
    "iso:country": "GB",
    "wof:name": "HA8 0HA",
    "wof:placetype": "postalcode"
  },
  "geometry": {"coordinates":[-0.257303,51.604069],"type":"Point"}
}
