{
  "type": "Feature",
  "properties": {
    "iso:country":"GB",
    "wof:name":"HA8 0HA",
    "wof:placetype":"postalcode"
},
  "geometry": {"coordinates":[-0.25666003969332,51.60413735169634],"type":"Point"}
}