{
  "type": "Feature",
  "properties": {
    "iso:country":"GB",
    "wof:name":"BD4 6AB",
    "wof:placetype":"postalcode"
},
  "geometry": {"coordinates":[-1.73158940952568,53.77021851829427],"type":"Point"}
}