{
  "type": "Feature",
  "properties": {
    "iso:country": "GB",
    "wof:name": "SS5 4AR",
    "wof:placetype": "postalcode"
  },
  "geometry": {"coordinates":[0.657998,51.602453],"type":"Point"}
}
