{
  "type": "Feature",
  "properties": {
    "date:inception_lower": "1980-01-01",
    "date:inception_upper": "1980-01-01",
    "iso:country": "GB",
    "wof:name": "CH1 6HU",
    "wof:placetype": "postalcode"
  },
  "geometry": {"coordinates":[-2.989205,53.23675],"type":"Point"}
}
