{
  "type": "Feature",
  "properties": {
    "iso:country":"GB",
    "wof:name":"CH1 6HU",
    "wof:placetype":"postalcode"
},
  "geometry": {"coordinates":[-2.98920618876859,53.23673458468225],"type":"Point"}
}