{
  "type": "Feature",
  "properties": {
    "iso:country":"GB",
    "wof:name":"S11 8YR",
    "wof:placetype":"postalcode"
},
  "geometry": {"coordinates":[-1.49696580232024,53.36459046367412],"type":"Point"}
}