{
  "type": "Feature",
  "properties": {
    "date:inception_lower": "2022-12-01",
    "date:inception_upper": "2022-12-01",
    "iso:country": "GB",
    "wof:name": "SA73 1UJ",
    "wof:placetype": "postalcode"
  },
  "geometry": {"coordinates":[-4.953483,51.710401],"type":"Point"}
}
