{
  "type": "Feature",
  "properties": {
    "iso:country":"GB",
    "wof:name":"PR3 3EJ",
    "wof:placetype":"postalcode"
},
  "geometry": {"coordinates":[-2.60803070586465,53.83075949714222],"type":"Point"}
}