{
  "type": "Feature",
  "properties": {
    "iso:country": "GB",
    "wof:name": "ME19 5LP",
    "wof:placetype": "postalcode"
  },
  "geometry": {"coordinates":[0.394471,51.312707],"type":"Point"}
}
