{
  "type": "Feature",
  "properties": {
    "iso:country":"GB",
    "wof:name":"ME19 5LP",
    "wof:placetype":"postalcode"
},
  "geometry": {"coordinates":[0.39447062616073,51.31270658207352],"type":"Point"}
}