{
  "type": "Feature",
  "properties": {
    "iso:country":"GB",
    "wof:name":"GU9 8QZ",
    "wof:placetype":"postalcode"
},
  "geometry": {"coordinates":[-0.80144833212927,51.20246379223469],"type":"Point"}
}