{
  "type": "Feature",
  "properties": {
    "iso:country": "GB",
    "wof:name": "TN23 4FG",
    "wof:placetype": "postalcode"
  },
  "geometry": {"coordinates":[0.857347,51.145947],"type":"Point"}
}
