{
  "type": "Feature",
  "properties": {
    "iso:country":"GB",
    "wof:name":"IV30 4HZ",
    "wof:placetype":"postalcode"
},
  "geometry": {"coordinates":[-3.30925485168761,57.65507406381276],"type":"Point"}
}