{
  "type": "Feature",
  "properties": {
    "iso:country": "GB",
    "wof:name": "KT16 0LZ",
    "wof:placetype": "postalcode"
  },
  "geometry": {"coordinates":[-0.527617,51.362093],"type":"Point"}
}
