{
  "type": "Feature",
  "properties": {
    "iso:country":"GB",
    "wof:name":"KT16 0LZ",
    "wof:placetype":"postalcode"
},
  "geometry": {"coordinates":[-0.52763707938024,51.36209333143243],"type":"Point"}
}