{
  "type": "Feature",
  "properties": {
    "iso:country": "GB",
    "wof:name": "RG9 4PS",
    "wof:placetype": "postalcode"
  },
  "geometry": {"coordinates":[-0.932858,51.524742],"type":"Point"}
}
