{
  "type": "Feature",
  "properties": {
    "iso:country":"GB",
    "wof:name":"RG9 4PS",
    "wof:placetype":"postalcode"
},
  "geometry": {"coordinates":[-0.93285781698562,51.52474173349218],"type":"Point"}
}