{
  "type": "Feature",
  "properties": {
    "iso:country":"GB",
    "wof:name":"KA9 2PR",
    "wof:placetype":"postalcode"
},
  "geometry": {"coordinates":[-4.59686683236999,55.51710572469481],"type":"Point"}
}