{
  "type": "Feature",
  "properties": {
    "iso:country": "GB",
    "wof:name": "KA9 2PR",
    "wof:placetype": "postalcode"
  },
  "geometry": {"coordinates":[-4.596867,55.517106],"type":"Point"}
}
