{
  "type": "Feature",
  "properties": {
    "iso:country":"GB",
    "wof:name":"SG12 8BB",
    "wof:placetype":"postalcode"
},
  "geometry": {"coordinates":[-0.00567349624773,51.78921576110999],"type":"Point"}
}