{
  "type": "Feature",
  "properties": {
    "iso:country":"GB",
    "wof:name":"S36 8YP",
    "wof:placetype":"postalcode"
},
  "geometry": {"coordinates":[-1.60315253975004,53.51138718440971],"type":"Point"}
}