{
  "type": "Feature",
  "properties": {
    "iso:country":"GB",
    "wof:name":"PA13 4HU",
    "wof:placetype":"postalcode"
},
  "geometry": {"coordinates":[-4.6347640653676,55.89373531323733],"type":"Point"}
}