{
  "type": "Feature",
  "properties": {
    "iso:country": "GB",
    "wof:name": "CF31 1PY",
    "wof:placetype": "postalcode"
  },
  "geometry": {"coordinates":[-3.57197,51.524741],"type":"Point"}
}
