{
  "type": "Feature",
  "properties": {
    "date:inception_lower": "2000-12-01",
    "date:inception_upper": "2000-12-01",
    "iso:country": "GB",
    "wof:name": "CF31 1PY",
    "wof:placetype": "postalcode"
  },
  "geometry": {"coordinates":[-3.57197,51.524741],"type":"Point"}
}
