{
  "type": "Feature",
  "properties": {
    "iso:country":"GB",
    "wof:name":"SY10 8AX",
    "wof:placetype":"postalcode"
},
  "geometry": {"coordinates":[-3.0314482157169,52.82644539791855],"type":"Point"}
}