{
  "type": "Feature",
  "properties": {
    "iso:country": "GB",
    "wof:name": "SY10 8AX",
    "wof:placetype": "postalcode"
  },
  "geometry": {"coordinates":[-3.031448,52.826445],"type":"Point"}
}
