{
  "type": "Feature",
  "properties": {
    "date:inception_lower": "1980-01-01",
    "date:inception_upper": "1980-01-01",
    "iso:country": "GB",
    "wof:name": "CV5 9NU",
    "wof:placetype": "postalcode"
  },
  "geometry": {"coordinates":[-1.559767,52.41758],"type":"Point"}
}
