{
  "type": "Feature",
  "properties": {
    "iso:country": "GB",
    "wof:name": "SP10 3DD",
    "wof:placetype": "postalcode"
  },
  "geometry": {"coordinates":[-1.508437,51.203629],"type":"Point"}
}
