{
  "type": "Feature",
  "properties": {
    "iso:country":"GB",
    "wof:name":"SL6 9ER",
    "wof:placetype":"postalcode"
},
  "geometry": {"coordinates":[-0.7305305721867,51.55907238148384],"type":"Point"}
}