{
  "type": "Feature",
  "properties": {
    "iso:country":"GB",
    "wof:name":"ST6 2HD",
    "wof:placetype":"postalcode"
},
  "geometry": {"coordinates":[-2.18877613594955,53.04081264137277],"type":"Point"}
}