{
  "type": "Feature",
  "properties": {
    "iso:country":"GB",
    "wof:name":"BN17 7HN",
    "wof:placetype":"postalcode"
},
  "geometry": {"coordinates":[-0.54795892834243,50.81496993043623],"type":"Point"}
}