{
  "type": "Feature",
  "properties": {
    "date:inception_lower": "2000-12-01",
    "date:inception_upper": "2000-12-01",
    "iso:country": "GB",
    "wof:name": "WC1N 3AZ",
    "wof:placetype": "postalcode"
  },
  "geometry": {"coordinates":[-0.123415,51.52214],"type":"Point"}
}
