{
  "type": "Feature",
  "properties": {
    "iso:country":"GB",
    "wof:name":"PR6 9LA",
    "wof:placetype":"postalcode"
},
  "geometry": {"coordinates":[-2.60674932608364,53.62205066972046],"type":"Point"}
}