{
  "type": "Feature",
  "properties": {
    "iso:country":"GB",
    "wof:name":"HG3 5PJ",
    "wof:placetype":"postalcode"
},
  "geometry": {"coordinates":[-1.7713779292376,54.09792315643156],"type":"Point"}
}