{
  "type": "Feature",
  "properties": {
    "iso:country":"GB",
    "wof:name":"SR1 3LE",
    "wof:placetype":"postalcode"
},
  "geometry": {"coordinates":[-1.38397754544984,54.90606555649693],"type":"Point"}
}