{
  "type": "Feature",
  "properties": {
    "iso:country":"GB",
    "wof:name":"TF9 2NT",
    "wof:placetype":"postalcode"
},
  "geometry": {"coordinates":[-2.41823854146146,52.86375772663365],"type":"Point"}
}