{
  "type": "Feature",
  "properties": {
    "iso:country":"GB",
    "wof:name":"MK41 0SP",
    "wof:placetype":"postalcode"
},
  "geometry": {"coordinates":[-0.42668906119528,52.1396387260383],"type":"Point"}
}