{
  "type": "Feature",
  "properties": {
    "date:inception_lower": "1990-07-01",
    "date:inception_upper": "1990-07-01",
    "iso:country": "GB",
    "wof:name": "MK41 0SP",
    "wof:placetype": "postalcode"
  },
  "geometry": {"coordinates":[-0.426689,52.139639],"type":"Point"}
}
