{
  "type": "Feature",
  "properties": {
    "date:inception_lower":"1980-01-01",
    "date:inception_upper":"1980-01-31",
    "iso:country":"GB",
    "wof:name":"HP13 7LR",
    "wof:placetype":"postalcode"
},
  "geometry": {"coordinates":[-0.72337,51.636504],"type":"Point"}
}