{
  "type": "Feature",
  "properties": {
    "iso:country": "GB",
    "wof:name": "HP13 7LR",
    "wof:placetype": "postalcode"
  },
  "geometry": {"coordinates":[-0.72337,51.636504],"type":"Point"}
}
