{
  "type": "Feature",
  "properties": {
    "iso:country":"GB",
    "wof:name":"HP13 7LR",
    "wof:placetype":"postalcode"
},
  "geometry": {"coordinates":[-0.72337030727172,51.63650420207225],"type":"Point"}
}