{
  "type": "Feature",
  "properties": {
    "iso:country":"GB",
    "wof:name":"WV11 3AZ",
    "wof:placetype":"postalcode"
},
  "geometry": {"coordinates":[-2.06836335396652,52.61170670860609],"type":"Point"}
}