{
  "type": "Feature",
  "properties": {
    "iso:country":"GB",
    "wof:name":"SE15 3LB",
    "wof:placetype":"postalcode"
},
  "geometry": {"coordinates":[-0.05853801786003,51.46337813596277],"type":"Point"}
}