{
  "type": "Feature",
  "properties": {
    "iso:country": "GB",
    "wof:name": "HR8 2RG",
    "wof:placetype": "postalcode"
  },
  "geometry": {"coordinates":[-2.509354,52.0391],"type":"Point"}
}
