{
  "type": "Feature",
  "properties": {
    "date:inception_lower": "1980-01-01",
    "date:inception_upper": "1980-01-01",
    "iso:country": "GB",
    "wof:name": "HR8 2RG",
    "wof:placetype": "postalcode"
  },
  "geometry": {"coordinates":[-2.509295,52.039191],"type":"Point"}
}
