{
  "type": "Feature",
  "properties": {
    "iso:country":"GB",
    "wof:name":"HR8 2RG",
    "wof:placetype":"postalcode"
},
  "geometry": {"coordinates":[-2.50935362392449,52.03910001416922],"type":"Point"}
}