{
  "type": "Feature",
  "properties": {
    "iso:country":"GB",
    "wof:name":"DT6 5PD",
    "wof:placetype":"postalcode"
},
  "geometry": {"coordinates":[-2.75344623205031,50.79107381521401],"type":"Point"}
}