{
  "type": "Feature",
  "properties": {
    "iso:country":"GB",
    "wof:name":"IG1 4SA",
    "wof:placetype":"postalcode"
},
  "geometry": {"coordinates":[0.07206120561419,51.56580932626606],"type":"Point"}
}