{
  "type": "Feature",
  "properties": {
    "iso:country":"GB",
    "wof:name":"M41 6HU",
    "wof:placetype":"postalcode"
},
  "geometry": {"coordinates":[-2.38822330810818,53.44075516113581],"type":"Point"}
}