{
  "type": "Feature",
  "properties": {
    "iso:country":"GB",
    "wof:name":"W1H 7ET",
    "wof:placetype":"postalcode"
},
  "geometry": {"coordinates":[-0.15966316859349,51.51619453188351],"type":"Point"}
}