{
  "type": "Feature",
  "properties": {
    "iso:country":"GB",
    "wof:name":"SA63 4SP",
    "wof:placetype":"postalcode"
},
  "geometry": {"coordinates":[-4.84208127302257,51.86356461353245],"type":"Point"}
}