{
  "type": "Feature",
  "properties": {
    "iso:country":"GB",
    "wof:name":"WR13 5AD",
    "wof:placetype":"postalcode"
},
  "geometry": {"coordinates":[-2.29940540972687,52.12226474804116],"type":"Point"}
}