{
  "type": "Feature",
  "properties": {
    "date:inception_lower": "2007-07-01",
    "date:inception_upper": "2007-07-01",
    "iso:country": "GB",
    "wof:name": "BB4 6DB",
    "wof:placetype": "postalcode"
  },
  "geometry": {"coordinates":[-2.288719,53.698478],"type":"Point"}
}
