{
  "type": "Feature",
  "properties": {
    "iso:country": "GB",
    "wof:name": "BB4 6DB",
    "wof:placetype": "postalcode"
  },
  "geometry": {"coordinates":[-2.28872,53.698463],"type":"Point"}
}
