{
  "type": "Feature",
  "properties": {
    "iso:country":"GB",
    "wof:name":"BB4 6DB",
    "wof:placetype":"postalcode"
},
  "geometry": {"coordinates":[-2.28872021918243,53.69846316539306],"type":"Point"}
}