{
  "type": "Feature",
  "properties": {
    "iso:country": "GB",
    "wof:name": "WF13 1DF",
    "wof:placetype": "postalcode"
  },
  "geometry": {"coordinates":[-1.629279,53.691633],"type":"Point"}
}
