{
  "type": "Feature",
  "properties": {
    "date:inception_lower": "2016-11-01",
    "date:inception_upper": "2016-11-01",
    "iso:country": "GB",
    "wof:name": "IP15 5PU",
    "wof:placetype": "postalcode"
  },
  "geometry": {"coordinates":[1.592058,52.158532],"type":"Point"}
}
