{
  "type": "Feature",
  "properties": {
    "date:inception_lower": "2020-02-01",
    "date:inception_upper": "2020-02-01",
    "iso:country": "GB",
    "wof:name": "TA13 5FE",
    "wof:placetype": "postalcode"
  },
  "geometry": {"coordinates":[-2.817289,50.949239],"type":"Point"}
}
