{
  "type": "Feature",
  "properties": {
    "iso:country": "GB",
    "wof:name": "TA13 5FE",
    "wof:placetype": "postalcode"
  },
  "geometry": {"coordinates":[-2.810102,50.948498],"type":"Point"}
}
