{
  "type": "Feature",
  "properties": {
    "iso:country": "GB",
    "wof:name": "MK17 0FD",
    "wof:placetype": "postalcode"
  },
  "geometry": {"coordinates":[-0.862835,51.990536],"type":"Point"}
}
