{
  "type": "Feature",
  "properties": {
    "date:inception_lower": "2010-05-01",
    "date:inception_upper": "2010-05-01",
    "iso:country": "GB",
    "wof:name": "MK17 0FD",
    "wof:placetype": "postalcode"
  },
  "geometry": {"coordinates":[-0.862835,51.990536],"type":"Point"}
}
