{
  "type": "Feature",
  "properties": {
    "iso:country":"GB",
    "wof:name":"MK17 0FD",
    "wof:placetype":"postalcode"
},
  "geometry": {"coordinates":[-0.86252460421099,51.99034315888643],"type":"Point"}
}