{
  "type": "Feature",
  "properties": {
    "iso:country":"GB",
    "wof:name":"NR6 7EJ",
    "wof:placetype":"postalcode"
},
  "geometry": {"coordinates":[1.3059163986383,52.66473457504205],"type":"Point"}
}