{
  "type": "Feature",
  "properties": {
    "date:inception_lower": "1980-01-01",
    "date:inception_upper": "1980-01-01",
    "iso:country": "GB",
    "wof:name": "NR6 7EJ",
    "wof:placetype": "postalcode"
  },
  "geometry": {"coordinates":[1.305916,52.664735],"type":"Point"}
}
