{
  "type": "Feature",
  "properties": {
    "iso:country": "GB",
    "wof:name": "NE16 6BF",
    "wof:placetype": "postalcode"
  },
  "geometry": {"coordinates":[-1.72209,54.905026],"type":"Point"}
}
