{
  "type": "Feature",
  "properties": {
    "iso:country":"GB",
    "wof:name":"NE16 6BF",
    "wof:placetype":"postalcode"
},
  "geometry": {"coordinates":[-1.72208986070972,54.90502583273603],"type":"Point"}
}