{
  "type": "Feature",
  "properties": {
    "date:inception_lower": "2008-01-01",
    "date:inception_upper": "2008-01-01",
    "iso:country": "GB",
    "wof:name": "NE16 6BF",
    "wof:placetype": "postalcode"
  },
  "geometry": {"coordinates":[-1.72209,54.905026],"type":"Point"}
}
