{
  "type": "Feature",
  "properties": {
    "iso:country":"GB",
    "wof:name":"WV4 5TJ",
    "wof:placetype":"postalcode"
},
  "geometry": {"coordinates":[-2.14285589800303,52.56233107211965],"type":"Point"}
}