{
  "type": "Feature",
  "properties": {
    "iso:country": "GB",
    "wof:name": "DT4 8JG",
    "wof:placetype": "postalcode"
  },
  "geometry": {"coordinates":[-2.46085,50.606528],"type":"Point"}
}
