{
  "type": "Feature",
  "properties": {
    "date:inception_lower":"2003-09-01",
    "date:inception_upper":"2003-09-30",
    "iso:country":"GB",
    "wof:name":"DT4 8JG",
    "wof:placetype":"postalcode"
},
  "geometry": {"coordinates":[-2.46085,50.606528],"type":"Point"}
}