{
  "type": "Feature",
  "properties": {
    "iso:country":"GB",
    "wof:name":"DT4 8JG",
    "wof:placetype":"postalcode"
},
  "geometry": {"coordinates":[-2.46084986284271,50.60652812330778],"type":"Point"}
}