{
  "type": "Feature",
  "properties": {
    "iso:country":"GB",
    "wof:name":"BN5 9PA",
    "wof:placetype":"postalcode"
},
  "geometry": {"coordinates":[-0.27442452056117,50.93201540895362],"type":"Point"}
}