{
  "type": "Feature",
  "properties": {
    "date:inception_lower": "1980-01-01",
    "date:inception_upper": "1980-01-01",
    "iso:country": "GB",
    "wof:name": "BN5 9PA",
    "wof:placetype": "postalcode"
  },
  "geometry": {"coordinates":[-0.274424,50.932015],"type":"Point"}
}
