{
  "type": "Feature",
  "properties": {
    "iso:country":"GB",
    "wof:name":"SO31 7HH",
    "wof:placetype":"postalcode"
},
  "geometry": {"coordinates":[-1.29323285731269,50.88372356966757],"type":"Point"}
}