{
  "type": "Feature",
  "properties": {
    "iso:country": "GB",
    "wof:name": "M6 8PW",
    "wof:placetype": "postalcode"
  },
  "geometry": {"coordinates":[-2.316138,53.494683],"type":"Point"}
}
