{
  "type": "Feature",
  "properties": {
    "date:inception_lower":"1980-01-01",
    "date:inception_upper":"1980-01-31",
    "iso:country":"GB",
    "wof:name":"M6 8PW",
    "wof:placetype":"postalcode"
},
  "geometry": {"coordinates":[-2.316138,53.494683],"type":"Point"}
}