{
  "type": "Feature",
  "properties": {
    "iso:country":"GB",
    "wof:name":"N19 3JD",
    "wof:placetype":"postalcode"
},
  "geometry": {"coordinates":[-0.12955047344637,51.56412472137141],"type":"Point"}
}