{
  "type": "Feature",
  "properties": {
    "iso:country":"GB",
    "wof:name":"PR26 7JY",
    "wof:placetype":"postalcode"
},
  "geometry": {"coordinates":[-2.74071324857767,53.68909578481936],"type":"Point"}
}