{
  "type": "Feature",
  "properties": {
    "iso:country":"GB",
    "wof:name":"S81 7RH",
    "wof:placetype":"postalcode"
},
  "geometry": {"coordinates":[-1.13105666944232,53.32922929353287],"type":"Point"}
}