{
  "type": "Feature",
  "properties": {
    "iso:country":"GB",
    "wof:name":"S3 8LB",
    "wof:placetype":"postalcode"
},
  "geometry": {"coordinates":[-1.46418911703638,53.38510395915814],"type":"Point"}
}