{
  "type": "Feature",
  "properties": {
    "iso:country":"GB",
    "wof:name":"PE30 3QE",
    "wof:placetype":"postalcode"
},
  "geometry": {"coordinates":[0.42990535228536,52.78649043772913],"type":"Point"}
}