{
  "type": "Feature",
  "properties": {
    "iso:country":"GB",
    "wof:name":"SP3 6WJ",
    "wof:placetype":"postalcode"
},
  "geometry": {"coordinates":[-2.08058976599381,51.06300832394032],"type":"Point"}
}