{
  "type": "Feature",
  "properties": {
    "iso:country":"GB",
    "wof:name":"BB8 7AE",
    "wof:placetype":"postalcode"
},
  "geometry": {"coordinates":[-2.14641787943535,53.86213256325041],"type":"Point"}
}