{
  "type": "Feature",
  "properties": {
    "iso:country":"GB",
    "wof:name":"TR16 6RX",
    "wof:placetype":"postalcode"
},
  "geometry": {"coordinates":[-5.23929184979909,50.21914204119211],"type":"Point"}
}