{
  "type": "Feature",
  "properties": {
    "iso:country":"GB",
    "wof:name":"GL6 8DW",
    "wof:placetype":"postalcode"
},
  "geometry": {"coordinates":[-2.14622370648186,51.72188759500253],"type":"Point"}
}