{
  "type": "Feature",
  "properties": {
    "date:inception_lower": "1980-01-01",
    "date:inception_upper": "1980-01-01",
    "iso:country": "GB",
    "wof:name": "TF7 5DP",
    "wof:placetype": "postalcode"
  },
  "geometry": {"coordinates":[-2.452368,52.630307],"type":"Point"}
}
