{
  "type": "Feature",
  "properties": {
    "iso:country":"GB",
    "wof:name":"TF7 5DP",
    "wof:placetype":"postalcode"
},
  "geometry": {"coordinates":[-2.4523681233261,52.63030683824113],"type":"Point"}
}