{
  "type": "Feature",
  "properties": {
    "date:inception_lower": "2007-08-01",
    "date:inception_upper": "2007-08-01",
    "iso:country": "GB",
    "wof:name": "LE15 7FN",
    "wof:placetype": "postalcode"
  },
  "geometry": {"coordinates":[-0.63228,52.723522],"type":"Point"}
}
