{
  "type": "Feature",
  "properties": {
    "iso:country": "GB",
    "wof:name": "LE15 7FN",
    "wof:placetype": "postalcode"
  },
  "geometry": {"coordinates":[-0.63228,52.723522],"type":"Point"}
}
