{
  "type": "Feature",
  "properties": {
    "date:inception_lower": "1993-01-01",
    "date:inception_upper": "1993-01-01",
    "iso:country": "GB",
    "wof:name": "SA4 4GA",
    "wof:placetype": "postalcode"
  },
  "geometry": {"coordinates":[-4.050228,51.677809],"type":"Point"}
}
