{
  "type": "Feature",
  "properties": {
    "iso:country":"GB",
    "wof:name":"SA4 4GA",
    "wof:placetype":"postalcode"
},
  "geometry": {"coordinates":[-4.05022837103917,51.67780863641435],"type":"Point"}
}