{
  "type": "Feature",
  "properties": {
    "date:inception_lower": "1980-01-01",
    "date:inception_upper": "1980-01-01",
    "iso:country": "GB",
    "wof:name": "SN6 7DR",
    "wof:placetype": "postalcode"
  },
  "geometry": {"coordinates":[-1.715058,51.631182],"type":"Point"}
}
