{
  "type": "Feature",
  "properties": {
    "iso:country": "GB",
    "wof:name": "CV22 7JA",
    "wof:placetype": "postalcode"
  },
  "geometry": {"coordinates":[-1.290464,52.366798],"type":"Point"}
}
