{
  "type": "Feature",
  "properties": {
    "date:inception_lower": "1980-01-01",
    "date:inception_upper": "1980-01-01",
    "iso:country": "GB",
    "wof:name": "TQ7 2RT",
    "wof:placetype": "postalcode"
  },
  "geometry": {"coordinates":[-3.72655,50.248987],"type":"Point"}
}
