{
  "type": "Feature",
  "properties": {
    "iso:country":"GB",
    "wof:name":"SS11 7FQ",
    "wof:placetype":"postalcode"
},
  "geometry": {"coordinates":[0.51665733195233,51.61920358868844],"type":"Point"}
}