{
  "type": "Feature",
  "properties": {
    "iso:country": "GB",
    "wof:name": "SS11 7FQ",
    "wof:placetype": "postalcode"
  },
  "geometry": {"coordinates":[0.516657,51.619204],"type":"Point"}
}
