{
  "type": "Feature",
  "properties": {
    "iso:country": "GB",
    "wof:name": "B91 1HB",
    "wof:placetype": "postalcode"
  },
  "geometry": {"coordinates":[-1.802468,52.417764],"type":"Point"}
}
