{
  "type": "Feature",
  "properties": {
    "iso:country": "GB",
    "wof:name": "SN25 2RE",
    "wof:placetype": "postalcode"
  },
  "geometry": {"coordinates":[-1.827072,51.608888],"type":"Point"}
}
