{
  "type": "Feature",
  "properties": {
    "iso:country": "GB",
    "wof:name": "PE21 6SN",
    "wof:placetype": "postalcode"
  },
  "geometry": {"coordinates":[-0.020191,52.979995],"type":"Point"}
}
