{
  "type": "Feature",
  "properties": {
    "iso:country": "GB",
    "wof:name": "KT21 2NY",
    "wof:placetype": "postalcode"
  },
  "geometry": {"coordinates":[-0.302696,51.308063],"type":"Point"}
}
