{
  "type": "Feature",
  "properties": {
    "iso:country":"GB",
    "wof:name":"KT21 2NY",
    "wof:placetype":"postalcode"
},
  "geometry": {"coordinates":[-0.30269588187136,51.30806253181411],"type":"Point"}
}