{
  "type": "Feature",
  "properties": {
    "date:inception_lower": "2022-07-01",
    "date:inception_upper": "2022-07-01",
    "iso:country": "GB",
    "wof:name": "LL57 4FP",
    "wof:placetype": "postalcode"
  },
  "geometry": {"coordinates":[-4.180825,53.201911],"type":"Point"}
}
