{
  "type": "Feature",
  "properties": {
    "date:inception_lower": "2017-04-01",
    "date:inception_upper": "2017-04-01",
    "iso:country": "GB",
    "wof:name": "SE5 7FS",
    "wof:placetype": "postalcode"
  },
  "geometry": {"coordinates":[-0.084055,51.477729],"type":"Point"}
}
