{
  "type": "Feature",
  "properties": {
    "iso:country":"GB",
    "wof:name":"B45 9HG",
    "wof:placetype":"postalcode"
},
  "geometry": {"coordinates":[-2.030244902492,52.39656687280751],"type":"Point"}
}