{
  "type": "Feature",
  "properties": {
    "iso:country": "GB",
    "wof:name": "EN1 4QB",
    "wof:placetype": "postalcode"
  },
  "geometry": {"coordinates":[-0.050488,51.673913],"type":"Point"}
}
