{
  "type": "Feature",
  "properties": {
    "iso:country":"GB",
    "wof:name":"EN1 4QB",
    "wof:placetype":"postalcode"
},
  "geometry": {"coordinates":[-0.05048784213453,51.67391270272471],"type":"Point"}
}