{
  "type": "Feature",
  "properties": {
    "iso:country": "GB",
    "wof:name": "SN4 0LS",
    "wof:placetype": "postalcode"
  },
  "geometry": {"coordinates":[-1.735146,51.511537],"type":"Point"}
}
