{
  "type": "Feature",
  "properties": {
    "iso:country": "GB",
    "wof:name": "OL11 2UJ",
    "wof:placetype": "postalcode"
  },
  "geometry": {"coordinates":[-2.172408,53.589588],"type":"Point"}
}
