{
  "type": "Feature",
  "properties": {
    "iso:country":"GB",
    "wof:name":"NE40 3LQ",
    "wof:placetype":"postalcode"
},
  "geometry": {"coordinates":[-1.76299054600954,54.96984950608988],"type":"Point"}
}