{
  "type": "Feature",
  "properties": {
    "iso:country":"GB",
    "wof:name":"NN6 0RH",
    "wof:placetype":"postalcode"
},
  "geometry": {"coordinates":[-0.83306493804388,52.28662114548639],"type":"Point"}
}