{
  "type": "Feature",
  "properties": {
    "iso:country": "GB",
    "wof:name": "NN6 0RH",
    "wof:placetype": "postalcode"
  },
  "geometry": {"coordinates":[-0.833065,52.286621],"type":"Point"}
}
