{
  "type": "Feature",
  "properties": {
    "date:inception_lower": "1980-01-01",
    "date:inception_upper": "1980-01-01",
    "iso:country": "GB",
    "wof:name": "GU22 7HR",
    "wof:placetype": "postalcode"
  },
  "geometry": {"coordinates":[-0.549221,51.316762],"type":"Point"}
}
