{
  "type": "Feature",
  "properties": {
    "iso:country":"GB",
    "wof:name":"IP4 5JQ",
    "wof:placetype":"postalcode"
},
  "geometry": {"coordinates":[1.18908754474254,52.05787074901529],"type":"Point"}
}