{
  "type": "Feature",
  "properties": {
    "date:inception_lower": "1990-02-01",
    "date:inception_upper": "1990-02-01",
    "iso:country": "GB",
    "wof:name": "CW6 9XB",
    "wof:placetype": "postalcode"
  },
  "geometry": {"coordinates":[-2.669056,53.154366],"type":"Point"}
}
