{
  "type": "Feature",
  "properties": {
    "date:inception_lower": "1980-01-01",
    "date:inception_upper": "1980-01-01",
    "iso:country": "GB",
    "wof:name": "E1 1PR",
    "wof:placetype": "postalcode"
  },
  "geometry": {"coordinates":[-0.066012,51.513421],"type":"Point"}
}
