{
  "type": "Feature",
  "properties": {
    "iso:country":"GB",
    "wof:name":"E1 1PR",
    "wof:placetype":"postalcode"
},
  "geometry": {"coordinates":[-0.0659364519832,51.51344547589918],"type":"Point"}
}