{
  "type": "Feature",
  "properties": {
    "date:inception_lower": "1990-08-01",
    "date:inception_upper": "1990-08-01",
    "iso:country": "GB",
    "wof:name": "AB45 2YT",
    "wof:placetype": "postalcode"
  },
  "geometry": {"coordinates":[-2.700993,57.646688],"type":"Point"}
}
