{
  "type": "Feature",
  "properties": {
    "iso:country":"GB",
    "wof:name":"AB45 2YT",
    "wof:placetype":"postalcode"
},
  "geometry": {"coordinates":[-2.70768611271058,57.64720539841436],"type":"Point"}
}