{
  "type": "Feature",
  "properties": {
    "iso:country": "GB",
    "wof:name": "BS6 6NL",
    "wof:placetype": "postalcode"
  },
  "geometry": {"coordinates":[-2.602253,51.467567],"type":"Point"}
}
