{
  "type": "Feature",
  "properties": {
    "iso:country":"GB",
    "wof:name":"G82 1RE",
    "wof:placetype":"postalcode"
},
  "geometry": {"coordinates":[-4.55817229735432,55.94321324080339],"type":"Point"}
}