{
  "type": "Feature",
  "properties": {
    "iso:country": "GB",
    "wof:name": "TQ5 9QT",
    "wof:placetype": "postalcode"
  },
  "geometry": {"coordinates":[-3.520449,50.383277],"type":"Point"}
}
