{
  "type": "Feature",
  "properties": {
    "iso:country":"GB",
    "wof:name":"TQ5 9QT",
    "wof:placetype":"postalcode"
},
  "geometry": {"coordinates":[-3.52044895292442,50.38327730448923],"type":"Point"}
}