{
  "type": "Feature",
  "properties": {
    "date:inception_lower":"1993-01-01",
    "date:inception_upper":"1993-01-31",
    "iso:country":"GB",
    "wof:name":"SN10 5QQ",
    "wof:placetype":"postalcode"
},
  "geometry": {"coordinates":[-2.005791,51.320997],"type":"Point"}
}