{
  "type": "Feature",
  "properties": {
    "iso:country": "GB",
    "wof:name": "SN10 5QQ",
    "wof:placetype": "postalcode"
  },
  "geometry": {"coordinates":[-2.005791,51.320997],"type":"Point"}
}
