{
  "type": "Feature",
  "properties": {
    "iso:country":"GB",
    "wof:name":"CB9 7AJ",
    "wof:placetype":"postalcode"
},
  "geometry": {"coordinates":[0.4073067551082,52.04827878480786],"type":"Point"}
}