{
  "type": "Feature",
  "properties": {
    "date:inception_lower": "1992-08-01",
    "date:inception_upper": "1992-08-01",
    "iso:country": "GB",
    "wof:name": "TS8 9QT",
    "wof:placetype": "postalcode"
  },
  "geometry": {"coordinates":[-1.189196,54.522414],"type":"Point"}
}
