{
  "type": "Feature",
  "properties": {
    "iso:country":"GB",
    "wof:name":"TS8 9QT",
    "wof:placetype":"postalcode"
},
  "geometry": {"coordinates":[-1.18919638658015,54.52241395332138],"type":"Point"}
}