{
  "type": "Feature",
  "properties": {
    "iso:country":"GB",
    "wof:name":"EH4 3LN",
    "wof:placetype":"postalcode"
},
  "geometry": {"coordinates":[-3.24629171838903,55.95467507610353],"type":"Point"}
}