{
  "type": "Feature",
  "properties": {
    "date:inception_lower": "1980-01-01",
    "date:inception_upper": "1980-01-01",
    "iso:country": "GB",
    "wof:name": "WV1 2QZ",
    "wof:placetype": "postalcode"
  },
  "geometry": {"coordinates":[-2.107554,52.585832],"type":"Point"}
}
