{
  "type": "Feature",
  "properties": {
    "iso:country":"GB",
    "wof:name":"DH9 8TZ",
    "wof:placetype":"postalcode"
},
  "geometry": {"coordinates":[-1.74254669546303,54.85676915197252],"type":"Point"}
}