{
  "type": "Feature",
  "properties": {
    "date:inception_lower": "1988-03-01",
    "date:inception_upper": "1988-03-01",
    "iso:country": "GB",
    "wof:name": "GL51 0QQ",
    "wof:placetype": "postalcode"
  },
  "geometry": {"coordinates":[-2.119068,51.915107],"type":"Point"}
}
