{
  "type": "Feature",
  "properties": {
    "iso:country":"GB",
    "wof:name":"TN23 3QJ",
    "wof:placetype":"postalcode"
},
  "geometry": {"coordinates":[0.87931044958938,51.11492620791659],"type":"Point"}
}