{
  "type": "Feature",
  "properties": {
    "iso:country":"GB",
    "wof:name":"N21 1RT",
    "wof:placetype":"postalcode"
},
  "geometry": {"coordinates":[-0.09949207985838,51.64135430344783],"type":"Point"}
}