{
  "type": "Feature",
  "properties": {
    "date:inception_lower": "2023-05-01",
    "date:inception_upper": "2023-05-01",
    "iso:country": "GB",
    "wof:name": "CW2 5RL",
    "wof:placetype": "postalcode"
  },
  "geometry": {"coordinates":[-2.417358,53.056409],"type":"Point"}
}
