{
  "type": "Feature",
  "properties": {
    "iso:country":"GB",
    "wof:name":"TS11 7HS",
    "wof:placetype":"postalcode"
},
  "geometry": {"coordinates":[-1.00796318831845,54.58957341348584],"type":"Point"}
}