{
  "type": "Feature",
  "properties": {
    "iso:country":"GB",
    "wof:name":"NE61 1JS",
    "wof:placetype":"postalcode"
},
  "geometry": {"coordinates":[-1.68553853680558,55.17238241962473],"type":"Point"}
}