{
  "type": "Feature",
  "properties": {
    "iso:country": "GB",
    "wof:name": "SE4 2NJ",
    "wof:placetype": "postalcode"
  },
  "geometry": {"coordinates":[-0.040527,51.468447],"type":"Point"}
}
