{
  "type": "Feature",
  "properties": {
    "iso:country": "GB",
    "wof:name": "IP14 5PT",
    "wof:placetype": "postalcode"
  },
  "geometry": {"coordinates":[1.12942,52.264836],"type":"Point"}
}
