{
  "type": "Feature",
  "properties": {
    "iso:country":"GB",
    "wof:name":"IP14 5PT",
    "wof:placetype":"postalcode"
},
  "geometry": {"coordinates":[1.12944991837149,52.26483435195409],"type":"Point"}
}