{
  "type": "Feature",
  "properties": {
    "iso:country":"GB",
    "wof:name":"WD18 6GN",
    "wof:placetype":"postalcode"
},
  "geometry": {"coordinates":[-0.41515478277029,51.64736996009412],"type":"Point"}
}