{
  "type": "Feature",
  "properties": {
    "iso:country":"GB",
    "wof:name":"NP25 4RN",
    "wof:placetype":"postalcode"
},
  "geometry": {"coordinates":[-2.71563584898782,51.77053584227838],"type":"Point"}
}