{
  "type": "Feature",
  "properties": {
    "iso:country":"GB",
    "wof:name":"DE23 8FY",
    "wof:placetype":"postalcode"
},
  "geometry": {"coordinates":[-1.47110903760193,52.90871525363332],"type":"Point"}
}