{
  "type": "Feature",
  "properties": {
    "iso:country": "GB",
    "wof:name": "DE23 8FY",
    "wof:placetype": "postalcode"
  },
  "geometry": {"coordinates":[-1.470972,52.908697],"type":"Point"}
}
