{
  "type": "Feature",
  "properties": {
    "iso:country":"GB",
    "wof:name":"M26 2QP",
    "wof:placetype":"postalcode"
},
  "geometry": {"coordinates":[-2.3042326076203,53.56654025893788],"type":"Point"}
}