{
  "type": "Feature",
  "properties": {
    "date:inception_lower": "2002-07-01",
    "date:inception_upper": "2002-07-01",
    "iso:country": "GB",
    "wof:name": "S66 7SL",
    "wof:placetype": "postalcode"
  },
  "geometry": {"coordinates":[-1.218243,53.462597],"type":"Point"}
}
