{
  "type": "Feature",
  "properties": {
    "iso:country":"GB",
    "wof:name":"S66 7SL",
    "wof:placetype":"postalcode"
},
  "geometry": {"coordinates":[-1.2182434535239,53.46259682153822],"type":"Point"}
}