{
  "type": "Feature",
  "properties": {
    "iso:country":"GB",
    "wof:name":"L31 8BR",
    "wof:placetype":"postalcode"
},
  "geometry": {"coordinates":[-2.95305947713682,53.51169561870276],"type":"Point"}
}