{
  "type": "Feature",
  "properties": {
    "iso:country":"GB",
    "wof:name":"DN5 8EP",
    "wof:placetype":"postalcode"
},
  "geometry": {"coordinates":[-1.16118781256042,53.52599380860605],"type":"Point"}
}