{
  "type": "Feature",
  "properties": {
    "iso:country": "GB",
    "wof:name": "BD23 4RQ",
    "wof:placetype": "postalcode"
  },
  "geometry": {"coordinates":[-2.271081,54.004484],"type":"Point"}
}
