{
  "type": "Feature",
  "properties": {
    "iso:country":"GB",
    "wof:name":"BD23 4RQ",
    "wof:placetype":"postalcode"
},
  "geometry": {"coordinates":[-2.27112396500983,54.00447956767236],"type":"Point"}
}