{
  "type": "Feature",
  "properties": {
    "date:inception_lower":"2017-08-01",
    "date:inception_upper":"2017-08-31",
    "iso:country":"GB",
    "wof:name":"WR5 3BX",
    "wof:placetype":"postalcode"
},
  "geometry": {"coordinates":[-2.222996,52.177414],"type":"Point"}
}