{
  "type": "Feature",
  "properties": {
    "iso:country":"GB",
    "wof:name":"WR5 3BX",
    "wof:placetype":"postalcode"
},
  "geometry": {"coordinates":[-2.22207690609292,52.1770980191712],"type":"Point"}
}