{
  "type": "Feature",
  "properties": {
    "iso:country": "GB",
    "wof:name": "WA10 3SP",
    "wof:placetype": "postalcode"
  },
  "geometry": {"coordinates":[-2.765842,53.437124],"type":"Point"}
}
