{
  "type": "Feature",
  "properties": {
    "iso:country":"GB",
    "wof:name":"SO14 1PB",
    "wof:placetype":"postalcode"
},
  "geometry": {"coordinates":[-1.39704856286084,50.90684092469895],"type":"Point"}
}