{
  "type": "Feature",
  "properties": {
    "date:inception_lower":"1999-06-01",
    "date:inception_upper":"1999-06-30",
    "iso:country":"GB",
    "wof:name":"NP18 2JU",
    "wof:placetype":"postalcode"
},
  "geometry": {"coordinates":[-2.890329,51.612874],"type":"Point"}
}