{
  "type": "Feature",
  "properties": {
    "iso:country":"GB",
    "wof:name":"GU23 7HR",
    "wof:placetype":"postalcode"
},
  "geometry": {"coordinates":[-0.53145130725934,51.28590380983436],"type":"Point"}
}