{
  "type": "Feature",
  "properties": {
    "iso:country":"GB",
    "wof:name":"WF3 3TW",
    "wof:placetype":"postalcode"
},
  "geometry": {"coordinates":[-1.49407189868245,53.74007884542016],"type":"Point"}
}