{
  "type": "Feature",
  "properties": {
    "iso:country": "GB",
    "wof:name": "WC1R 4TF",
    "wof:placetype": "postalcode"
  },
  "geometry": {"coordinates":[-0.115297,51.519411],"type":"Point"}
}
