{
  "type": "Feature",
  "properties": {
    "date:inception_lower": "2001-06-01",
    "date:inception_upper": "2001-06-01",
    "iso:country": "GB",
    "wof:name": "G40 1DF",
    "wof:placetype": "postalcode"
  },
  "geometry": {"coordinates":[-4.229883,55.849665],"type":"Point"}
}
