{
  "type": "Feature",
  "properties": {
    "iso:country":"GB",
    "wof:name":"GU21 2HS",
    "wof:placetype":"postalcode"
},
  "geometry": {"coordinates":[-0.61339564324542,51.32048022263967],"type":"Point"}
}