{
  "type": "Feature",
  "properties": {
    "iso:country":"GB",
    "wof:name":"UB1 3EW",
    "wof:placetype":"postalcode"
},
  "geometry": {"coordinates":[-0.34816104824915,51.5092078888885],"type":"Point"}
}