{
  "type": "Feature",
  "properties": {
    "iso:country": "GB",
    "wof:name": "UB1 3EW",
    "wof:placetype": "postalcode"
  },
  "geometry": {"coordinates":[-0.348139,51.509209],"type":"Point"}
}
