{
  "type": "Feature",
  "properties": {
    "date:inception_lower": "1997-06-01",
    "date:inception_upper": "1997-06-01",
    "iso:country": "GB",
    "wof:name": "MK40 1TS",
    "wof:placetype": "postalcode"
  },
  "geometry": {"coordinates":[-0.469275,52.135677],"type":"Point"}
}
