{
  "type": "Feature",
  "properties": {
    "iso:country": "GB",
    "wof:name": "WS13 8RY",
    "wof:placetype": "postalcode"
  },
  "geometry": {"coordinates":[-1.779446,52.706938],"type":"Point"}
}
