{
  "type": "Feature",
  "properties": {
    "iso:country":"GB",
    "wof:name":"DD3 6EE",
    "wof:placetype":"postalcode"
},
  "geometry": {"coordinates":[-2.99431228569244,56.46896969836482],"type":"Point"}
}