{
  "type": "Feature",
  "properties": {
    "iso:country":"GB",
    "wof:name":"KT16 9PS",
    "wof:placetype":"postalcode"
},
  "geometry": {"coordinates":[-0.51467074272021,51.37661414374822],"type":"Point"}
}