{
  "type": "Feature",
  "properties": {
    "iso:country":"GB",
    "wof:name":"AL9 6NG",
    "wof:placetype":"postalcode"
},
  "geometry": {"coordinates":[-0.17507531719762,51.7256416123338],"type":"Point"}
}