{
  "type": "Feature",
  "properties": {
    "iso:country":"GB",
    "wof:name":"SK9 1ER",
    "wof:placetype":"postalcode"
},
  "geometry": {"coordinates":[-2.23225313293741,53.32603451242034],"type":"Point"}
}