{
  "type": "Feature",
  "properties": {
    "iso:country":"GB",
    "wof:name":"DL2 1DZ",
    "wof:placetype":"postalcode"
},
  "geometry": {"coordinates":[-1.46856839023013,54.50719378209594],"type":"Point"}
}