{
  "type": "Feature",
  "properties": {
    "date:inception_lower":"1980-01-01",
    "date:inception_upper":"1980-01-31",
    "iso:country":"GB",
    "wof:name":"WA13 9TJ",
    "wof:placetype":"postalcode"
},
  "geometry": {"coordinates":[-2.43889,53.39934],"type":"Point"}
}