{
  "type": "Feature",
  "properties": {
    "iso:country":"GB",
    "wof:name":"WA13 9TJ",
    "wof:placetype":"postalcode"
},
  "geometry": {"coordinates":[-2.4388905127833,53.39933994212605],"type":"Point"}
}