{
  "type": "Feature",
  "properties": {
    "iso:country": "GB",
    "wof:name": "WA13 9TJ",
    "wof:placetype": "postalcode"
  },
  "geometry": {"coordinates":[-2.43889,53.39934],"type":"Point"}
}
