{
  "type": "Feature",
  "properties": {
    "iso:country":"GB",
    "wof:name":"PO14 2JU",
    "wof:placetype":"postalcode"
},
  "geometry": {"coordinates":[-1.21940527120791,50.8279217495483],"type":"Point"}
}