{
  "type": "Feature",
  "properties": {
    "date:inception_lower": "1980-01-01",
    "date:inception_upper": "1980-01-01",
    "iso:country": "GB",
    "wof:name": "L39 5AR",
    "wof:placetype": "postalcode"
  },
  "geometry": {"coordinates":[-2.906734,53.555453],"type":"Point"}
}
