{
  "type": "Feature",
  "properties": {
    "iso:country":"GB",
    "wof:name":"L39 5AR",
    "wof:placetype":"postalcode"
},
  "geometry": {"coordinates":[-2.90673386600908,53.55545342881087],"type":"Point"}
}