{
  "type": "Feature",
  "properties": {
    "iso:country":"GB",
    "wof:name":"NE46 2QF",
    "wof:placetype":"postalcode"
},
  "geometry": {"coordinates":[-2.1144241243934,54.95996129105023],"type":"Point"}
}