{
  "type": "Feature",
  "properties": {
    "date:inception_lower":"1991-01-01",
    "date:inception_upper":"1991-01-31",
    "iso:country":"GB",
    "wof:name":"NE46 2QF",
    "wof:placetype":"postalcode"
},
  "geometry": {"coordinates":[-2.114424,54.959961],"type":"Point"}
}