{
  "type": "Feature",
  "properties": {
    "date:inception_lower": "1980-01-01",
    "date:inception_upper": "1980-01-01",
    "iso:country": "GB",
    "wof:name": "HR8 1JA",
    "wof:placetype": "postalcode"
  },
  "geometry": {"coordinates":[-2.418307,52.038937],"type":"Point"}
}
