{
  "type": "Feature",
  "properties": {
    "iso:country":"GB",
    "wof:name":"HR8 1JA",
    "wof:placetype":"postalcode"
},
  "geometry": {"coordinates":[-2.41830675131239,52.03893713488707],"type":"Point"}
}