{
  "type": "Feature",
  "properties": {
    "iso:country":"GB",
    "wof:name":"SG9 0PS",
    "wof:placetype":"postalcode"
},
  "geometry": {"coordinates":[-0.02628762424846,51.9873456112988],"type":"Point"}
}