{
  "type": "Feature",
  "properties": {
    "iso:country":"GB",
    "wof:name":"UB1 1EU",
    "wof:placetype":"postalcode"
},
  "geometry": {"coordinates":[-0.38604497670076,51.51005000324763],"type":"Point"}
}