{
  "type": "Feature",
  "properties": {
    "iso:country":"GB",
    "wof:name":"G78 2PJ",
    "wof:placetype":"postalcode"
},
  "geometry": {"coordinates":[-4.37645376979974,55.79215728272001],"type":"Point"}
}