{
  "type": "Feature",
  "properties": {
    "iso:country": "GB",
    "wof:name": "CA6 5LR",
    "wof:placetype": "postalcode"
  },
  "geometry": {"coordinates":[-3.017576,54.978624],"type":"Point"}
}
