{
  "type": "Feature",
  "properties": {
    "date:inception_lower": "1980-01-01",
    "date:inception_upper": "1980-01-01",
    "iso:country": "GB",
    "wof:name": "CA6 5LR",
    "wof:placetype": "postalcode"
  },
  "geometry": {"coordinates":[-3.017576,54.978624],"type":"Point"}
}
