{
  "type": "Feature",
  "properties": {
    "iso:country":"GB",
    "wof:name":"CA6 5LR",
    "wof:placetype":"postalcode"
},
  "geometry": {"coordinates":[-3.01765239401968,54.97865311352621],"type":"Point"}
}