{
  "type": "Feature",
  "properties": {
    "iso:country":"GB",
    "wof:name":"TN22 3XX",
    "wof:placetype":"postalcode"
},
  "geometry": {"coordinates":[0.05754470389022,51.00332446997537],"type":"Point"}
}