{
  "type": "Feature",
  "properties": {
    "date:inception_lower": "1980-01-01",
    "date:inception_upper": "1980-01-01",
    "iso:country": "GB",
    "wof:name": "TN22 3XX",
    "wof:placetype": "postalcode"
  },
  "geometry": {"coordinates":[0.057571,51.003321],"type":"Point"}
}
