{
  "type": "Feature",
  "properties": {
    "iso:country":"GB",
    "wof:name":"RG7 1BU",
    "wof:placetype":"postalcode"
},
  "geometry": {"coordinates":[-0.96007137395372,51.39302158382726],"type":"Point"}
}