{
  "type": "Feature",
  "properties": {
    "date:inception_lower": "1980-01-01",
    "date:inception_upper": "1980-01-01",
    "iso:country": "GB",
    "wof:name": "SR6 7AR",
    "wof:placetype": "postalcode"
  },
  "geometry": {"coordinates":[-1.36764,54.954356],"type":"Point"}
}
