{
  "type": "Feature",
  "properties": {
    "iso:country":"GB",
    "wof:name":"SR6 7AR",
    "wof:placetype":"postalcode"
},
  "geometry": {"coordinates":[-1.36764025827288,54.95435570379112],"type":"Point"}
}