{
  "type": "Feature",
  "properties": {
    "iso:country":"GB",
    "wof:name":"SL1 2JY",
    "wof:placetype":"postalcode"
},
  "geometry": {"coordinates":[-0.59996602771968,51.50917441726736],"type":"Point"}
}