{
  "type": "Feature",
  "properties": {
    "iso:country":"GB",
    "wof:name":"NE24 5LN",
    "wof:placetype":"postalcode"
},
  "geometry": {"coordinates":[-1.53960330582539,55.12793246045775],"type":"Point"}
}