{
  "type": "Feature",
  "properties": {
    "iso:country":"GB",
    "wof:name":"BN3 6GB",
    "wof:placetype":"postalcode"
},
  "geometry": {"coordinates":[-0.16225802959543,50.83504620063644],"type":"Point"}
}