{
  "type": "Feature",
  "properties": {
    "iso:country":"GB",
    "wof:name":"RG18 9DU",
    "wof:placetype":"postalcode"
},
  "geometry": {"coordinates":[-1.29414612533923,51.4468430002484],"type":"Point"}
}