{
  "type": "Feature",
  "properties": {
    "iso:country": "GB",
    "wof:name": "GU3 2AR",
    "wof:placetype": "postalcode"
  },
  "geometry": {"coordinates":[-0.665112,51.257281],"type":"Point"}
}
