{
  "type": "Feature",
  "properties": {
    "iso:country":"GB",
    "wof:name":"GU3 2AR",
    "wof:placetype":"postalcode"
},
  "geometry": {"coordinates":[-0.66511234284833,51.25728052872763],"type":"Point"}
}