{
  "type": "Feature",
  "properties": {
    "iso:country": "GB",
    "wof:name": "PE24 5QD",
    "wof:placetype": "postalcode"
  },
  "geometry": {"coordinates":[0.301756,53.2291],"type":"Point"}
}
