{
  "type": "Feature",
  "properties": {
    "date:inception_lower": "2002-06-01",
    "date:inception_upper": "2002-06-01",
    "iso:country": "GB",
    "wof:name": "DL11 7GA",
    "wof:placetype": "postalcode"
  },
  "geometry": {"coordinates":[-1.76744,54.455691],"type":"Point"}
}
