{
  "type": "Feature",
  "properties": {
    "iso:country": "GB",
    "wof:name": "DL11 7GA",
    "wof:placetype": "postalcode"
  },
  "geometry": {"coordinates":[-1.766751,54.457433],"type":"Point"}
}
