{
  "type": "Feature",
  "properties": {
    "iso:country":"GB",
    "wof:name":"DH7 9JT",
    "wof:placetype":"postalcode"
},
  "geometry": {"coordinates":[-1.71399246611139,54.76884460746376],"type":"Point"}
}