{
  "type": "Feature",
  "properties": {
    "iso:country":"GB",
    "wof:name":"CO16 8EE",
    "wof:placetype":"postalcode"
},
  "geometry": {"coordinates":[1.14062104377804,51.80511900177064],"type":"Point"}
}