{
  "type": "Feature",
  "properties": {
    "iso:country": "GB",
    "wof:name": "EX10 9QF",
    "wof:placetype": "postalcode"
  },
  "geometry": {"coordinates":[-3.223245,50.695021],"type":"Point"}
}
