{
  "type": "Feature",
  "properties": {
    "iso:country":"GB",
    "wof:name":"NP24 6FL",
    "wof:placetype":"postalcode"
},
  "geometry": {"coordinates":[-3.23447647144622,51.72768416993692],"type":"Point"}
}