{
  "type": "Feature",
  "properties": {
    "iso:country": "GB",
    "wof:name": "NP24 6FL",
    "wof:placetype": "postalcode"
  },
  "geometry": {"coordinates":[-3.234476,51.727684],"type":"Point"}
}
