{
  "type": "Feature",
  "properties": {
    "date:inception_lower":"2009-05-01",
    "date:inception_upper":"2009-05-31",
    "iso:country":"GB",
    "wof:name":"NP24 6FL",
    "wof:placetype":"postalcode"
},
  "geometry": {"coordinates":[-3.234476,51.727684],"type":"Point"}
}