{
  "type": "Feature",
  "properties": {
    "iso:country":"GB",
    "wof:name":"BN2 8RE",
    "wof:placetype":"postalcode"
},
  "geometry": {"coordinates":[-0.02851644388962,50.80438919815755],"type":"Point"}
}