{
  "type": "Feature",
  "properties": {
    "date:inception_lower":"1981-06-01",
    "date:inception_upper":"1981-06-30",
    "iso:country":"GB",
    "wof:name":"NR33 8NN",
    "wof:placetype":"postalcode"
},
  "geometry": {"coordinates":[1.697937,52.46012],"type":"Point"}
}