{
  "type": "Feature",
  "properties": {
    "iso:country":"GB",
    "wof:name":"NR33 8NN",
    "wof:placetype":"postalcode"
},
  "geometry": {"coordinates":[1.69793734385592,52.46011990740389],"type":"Point"}
}