{
  "type": "Feature",
  "properties": {
    "iso:country":"GB",
    "wof:name":"EX16 6DD",
    "wof:placetype":"postalcode"
},
  "geometry": {"coordinates":[-3.47955649048239,50.9068143546795],"type":"Point"}
}