{
  "type": "Feature",
  "properties": {
    "iso:country":"GB",
    "wof:name":"TQ3 1NG",
    "wof:placetype":"postalcode"
},
  "geometry": {"coordinates":[-3.59832324407252,50.45532551357434],"type":"Point"}
}