{
  "type": "Feature",
  "properties": {
    "date:inception_lower": "1980-01-01",
    "date:inception_upper": "1980-01-01",
    "iso:country": "GB",
    "wof:name": "SK14 2PA",
    "wof:placetype": "postalcode"
  },
  "geometry": {"coordinates":[-2.066412,53.451912],"type":"Point"}
}
