{
  "type": "Feature",
  "properties": {
    "iso:country": "GB",
    "wof:name": "NG9 7HA",
    "wof:placetype": "postalcode"
  },
  "geometry": {"coordinates":[-1.274082,52.9288],"type":"Point"}
}
