{
  "type": "Feature",
  "properties": {
    "iso:country":"GB",
    "wof:name":"NG9 7HA",
    "wof:placetype":"postalcode"
},
  "geometry": {"coordinates":[-1.27408239599856,52.92880049257366],"type":"Point"}
}