{
  "type": "Feature",
  "properties": {
    "iso:country": "GB",
    "wof:name": "BN1 8BB",
    "wof:placetype": "postalcode"
  },
  "geometry": {"coordinates":[-0.15131,50.864102],"type":"Point"}
}
