{
  "type": "Feature",
  "properties": {
    "iso:country":"GB",
    "wof:name":"BN1 8BB",
    "wof:placetype":"postalcode"
},
  "geometry": {"coordinates":[-0.15131037494735,50.8641018488227],"type":"Point"}
}