{
  "type": "Feature",
  "properties": {
    "iso:country": "GB",
    "wof:name": "SK8 3LF",
    "wof:placetype": "postalcode"
  },
  "geometry": {"coordinates":[-2.231037,53.364823],"type":"Point"}
}
