{
  "type": "Feature",
  "properties": {
    "iso:country": "GB",
    "wof:name": "NR10 5RP",
    "wof:placetype": "postalcode"
  },
  "geometry": {"coordinates":[1.253589,52.742215],"type":"Point"}
}
