{
  "type": "Feature",
  "properties": {
    "iso:country":"GB",
    "wof:name":"NR10 5RP",
    "wof:placetype":"postalcode"
},
  "geometry": {"coordinates":[1.25358886253106,52.74221475815867],"type":"Point"}
}