{
  "type": "Feature",
  "properties": {
    "iso:country":"GB",
    "wof:name":"CT6 7PN",
    "wof:placetype":"postalcode"
},
  "geometry": {"coordinates":[1.11207340262075,51.36260097687494],"type":"Point"}
}