{
  "type": "Feature",
  "properties": {
    "iso:country": "GB",
    "wof:name": "DN39 6XS",
    "wof:placetype": "postalcode"
  },
  "geometry": {"coordinates":[-0.34562,53.62917],"type":"Point"}
}
