{
  "type": "Feature",
  "properties": {
    "iso:country":"GB",
    "wof:name":"DN39 6XS",
    "wof:placetype":"postalcode"
},
  "geometry": {"coordinates":[-0.34809272364599,53.62842768893302],"type":"Point"}
}