{
  "type": "Feature",
  "properties": {
    "iso:country": "GB",
    "wof:name": "G5 9SS",
    "wof:placetype": "postalcode"
  },
  "geometry": {"coordinates":[-4.258708,55.846442],"type":"Point"}
}
