{
  "type": "Feature",
  "properties": {
    "iso:country":"GB",
    "wof:name":"NG1 7DE",
    "wof:placetype":"postalcode"
},
  "geometry": {"coordinates":[-1.14841945285441,52.9509258955855],"type":"Point"}
}