{
  "type": "Feature",
  "properties": {
    "iso:country":"GB",
    "wof:name":"TS15 9AJ",
    "wof:placetype":"postalcode"
},
  "geometry": {"coordinates":[-1.35324342678312,54.50954403412067],"type":"Point"}
}