{
  "type": "Feature",
  "properties": {
    "iso:country": "GB",
    "wof:name": "WD18 0BQ",
    "wof:placetype": "postalcode"
  },
  "geometry": {"coordinates":[-0.391747,51.648787],"type":"Point"}
}
