{
  "type": "Feature",
  "properties": {
    "iso:country":"GB",
    "wof:name":"BS15 9UD",
    "wof:placetype":"postalcode"
},
  "geometry": {"coordinates":[-2.49358242774062,51.46025356264091],"type":"Point"}
}