{
  "type": "Feature",
  "properties": {
    "iso:country": "GB",
    "wof:name": "BS15 9UD",
    "wof:placetype": "postalcode"
  },
  "geometry": {"coordinates":[-2.493582,51.460254],"type":"Point"}
}
