{
  "type": "Feature",
  "properties": {
    "iso:country":"GB",
    "wof:name":"TA14 6QQ",
    "wof:placetype":"postalcode"
},
  "geometry": {"coordinates":[-2.75050568141971,50.95537840199881],"type":"Point"}
}