{
  "type": "Feature",
  "properties": {
    "iso:country":"GB",
    "wof:name":"SO45 5UF",
    "wof:placetype":"postalcode"
},
  "geometry": {"coordinates":[-1.41984009015635,50.86504227341988],"type":"Point"}
}