{
  "type": "Feature",
  "properties": {
    "iso:country":"GB",
    "wof:name":"CR8 3DD",
    "wof:placetype":"postalcode"
},
  "geometry": {"coordinates":[-0.13889412550705,51.3317336871859],"type":"Point"}
}