{
  "type": "Feature",
  "properties": {
    "iso:country":"GB",
    "wof:name":"LD1 5TG",
    "wof:placetype":"postalcode"
},
  "geometry": {"coordinates":[-3.2630525010346,52.29497717258562],"type":"Point"}
}