{
  "type": "Feature",
  "properties": {
    "iso:country":"GB",
    "wof:name":"PA15 3HP",
    "wof:placetype":"postalcode"
},
  "geometry": {"coordinates":[-4.7329943077381,55.93303911006571],"type":"Point"}
}