{
  "type": "Feature",
  "properties": {
    "iso:country": "GB",
    "wof:name": "E7 9PW",
    "wof:placetype": "postalcode"
  },
  "geometry": {"coordinates":[0.024404,51.53987],"type":"Point"}
}
