{
  "type": "Feature",
  "properties": {
    "iso:country":"GB",
    "wof:name":"DN10 5AU",
    "wof:placetype":"postalcode"
},
  "geometry": {"coordinates":[-0.96018765996989,53.41351933274321],"type":"Point"}
}