{
  "type": "Feature",
  "properties": {
    "date:inception_lower": "1980-01-01",
    "date:inception_upper": "1980-01-01",
    "iso:country": "GB",
    "wof:name": "DN10 5AU",
    "wof:placetype": "postalcode"
  },
  "geometry": {"coordinates":[-0.960188,53.413519],"type":"Point"}
}
