{
  "type": "Feature",
  "properties": {
    "iso:country": "GB",
    "wof:name": "TS16 0QW",
    "wof:placetype": "postalcode"
  },
  "geometry": {"coordinates":[-1.386657,54.506791],"type":"Point"}
}
