{
  "type": "Feature",
  "properties": {
    "iso:country":"GB",
    "wof:name":"SW17 0RU",
    "wof:placetype":"postalcode"
},
  "geometry": {"coordinates":[-0.17070316876265,51.42548871317519],"type":"Point"}
}