{
  "type": "Feature",
  "properties": {
    "date:inception_lower": "1980-01-01",
    "date:inception_upper": "1980-01-01",
    "iso:country": "GB",
    "wof:name": "M18 7LR",
    "wof:placetype": "postalcode"
  },
  "geometry": {"coordinates":[-2.155967,53.457122],"type":"Point"}
}
