{
  "type": "Feature",
  "properties": {
    "iso:country":"GB",
    "wof:name":"M18 7LR",
    "wof:placetype":"postalcode"
},
  "geometry": {"coordinates":[-2.1559670700712,53.45712238073503],"type":"Point"}
}