{
  "type": "Feature",
  "properties": {
    "iso:country":"GB",
    "wof:name":"SW3 4PA",
    "wof:placetype":"postalcode"
},
  "geometry": {"coordinates":[-0.16532463082549,51.48864030005219],"type":"Point"}
}