{
  "type": "Feature",
  "properties": {
    "date:inception_lower": "1980-01-01",
    "date:inception_upper": "1980-01-01",
    "iso:country": "GB",
    "wof:name": "N13 4DR",
    "wof:placetype": "postalcode"
  },
  "geometry": {"coordinates":[-0.101523,51.624655],"type":"Point"}
}
