{
  "type": "Feature",
  "properties": {
    "date:inception_lower": "1980-01-01",
    "date:inception_upper": "1980-01-01",
    "iso:country": "GB",
    "wof:name": "PE33 9LW",
    "wof:placetype": "postalcode"
  },
  "geometry": {"coordinates":[0.541853,52.657717],"type":"Point"}
}
