{
  "type": "Feature",
  "properties": {
    "iso:country":"GB",
    "wof:name":"PE33 9LW",
    "wof:placetype":"postalcode"
},
  "geometry": {"coordinates":[0.54185314495579,52.65771736242507],"type":"Point"}
}