{
  "type": "Feature",
  "properties": {
    "iso:country":"GB",
    "wof:name":"CW12 4YH",
    "wof:placetype":"postalcode"
},
  "geometry": {"coordinates":[-2.24498101928409,53.16811155647311],"type":"Point"}
}