{
  "type": "Feature",
  "properties": {
    "iso:country": "GB",
    "wof:name": "CW12 4YH",
    "wof:placetype": "postalcode"
  },
  "geometry": {"coordinates":[-2.244981,53.168112],"type":"Point"}
}
