{
  "type": "Feature",
  "properties": {
    "date:inception_lower": "2002-08-01",
    "date:inception_upper": "2002-08-01",
    "iso:country": "GB",
    "wof:name": "PL31 1EA",
    "wof:placetype": "postalcode"
  },
  "geometry": {"coordinates":[-4.71724,50.460013],"type":"Point"}
}
