{
  "type": "Feature",
  "properties": {
    "date:inception_lower": "1980-01-01",
    "date:inception_upper": "1980-01-01",
    "iso:country": "GB",
    "wof:name": "CF31 1TT",
    "wof:placetype": "postalcode"
  },
  "geometry": {"coordinates":[-3.569748,51.505041],"type":"Point"}
}
