{
  "type": "Feature",
  "properties": {
    "iso:country":"GB",
    "wof:name":"CF31 1TT",
    "wof:placetype":"postalcode"
},
  "geometry": {"coordinates":[-3.56974802293648,51.50504068418463],"type":"Point"}
}