{
  "type": "Feature",
  "properties": {
    "iso:country":"GB",
    "wof:name":"S61 4QP",
    "wof:placetype":"postalcode"
},
  "geometry": {"coordinates":[-1.36679405819186,53.45704917812961],"type":"Point"}
}