{
  "type": "Feature",
  "properties": {
    "iso:country":"GB",
    "wof:name":"DH8 6TP",
    "wof:placetype":"postalcode"
},
  "geometry": {"coordinates":[-1.81147861578265,54.88590353738093],"type":"Point"}
}