{
  "type": "Feature",
  "properties": {
    "date:inception_lower":"2007-08-01",
    "date:inception_upper":"2007-08-31",
    "iso:country":"GB",
    "wof:name":"DH8 6TP",
    "wof:placetype":"postalcode"
},
  "geometry": {"coordinates":[-1.811479,54.885904],"type":"Point"}
}