{
  "type": "Feature",
  "properties": {
    "iso:country": "GB",
    "wof:name": "CF5 3DN",
    "wof:placetype": "postalcode"
  },
  "geometry": {"coordinates":[-3.230288,51.486119],"type":"Point"}
}
