{
  "type": "Feature",
  "properties": {
    "iso:country":"GB",
    "wof:name":"CF5 3DN",
    "wof:placetype":"postalcode"
},
  "geometry": {"coordinates":[-3.23028778058044,51.48611922170424],"type":"Point"}
}