{
  "type": "Feature",
  "properties": {
    "iso:country":"GB",
    "wof:name":"NN1 5PU",
    "wof:placetype":"postalcode"
},
  "geometry": {"coordinates":[-0.88853225525676,52.23714077418109],"type":"Point"}
}