{
  "type": "Feature",
  "properties": {
    "iso:country": "GB",
    "wof:name": "NN1 5PU",
    "wof:placetype": "postalcode"
  },
  "geometry": {"coordinates":[-0.888532,52.237141],"type":"Point"}
}
