{
  "type": "Feature",
  "properties": {
    "iso:country":"GB",
    "wof:name":"YO16 7EE",
    "wof:placetype":"postalcode"
},
  "geometry": {"coordinates":[-0.20261483362642,54.09731172319944],"type":"Point"}
}