{
  "type": "Feature",
  "properties": {
    "iso:country":"GB",
    "wof:name":"NG5 7AT",
    "wof:placetype":"postalcode"
},
  "geometry": {"coordinates":[-1.13716892192006,53.00468275684779],"type":"Point"}
}