{
  "type": "Feature",
  "properties": {
    "iso:country": "GB",
    "wof:name": "NG5 7AT",
    "wof:placetype": "postalcode"
  },
  "geometry": {"coordinates":[-1.137169,53.004683],"type":"Point"}
}
