{
  "type": "Feature",
  "properties": {
    "iso:country": "GB",
    "wof:name": "GU34 5GE",
    "wof:placetype": "postalcode"
  },
  "geometry": {"coordinates":[-1.042405,51.113358],"type":"Point"}
}
