{
  "type": "Feature",
  "properties": {
    "iso:country":"GB",
    "wof:name":"GU34 5GE",
    "wof:placetype":"postalcode"
},
  "geometry": {"coordinates":[-1.0424046050343,51.11335795313726],"type":"Point"}
}