{
  "type": "Feature",
  "properties": {
    "date:inception_lower": "2014-07-01",
    "date:inception_upper": "2014-07-01",
    "iso:country": "GB",
    "wof:name": "GU34 5GE",
    "wof:placetype": "postalcode"
  },
  "geometry": {"coordinates":[-1.042405,51.113358],"type":"Point"}
}
