{
  "type": "Feature",
  "properties": {
    "iso:country":"GB",
    "wof:name":"SW19 1PX",
    "wof:placetype":"postalcode"
},
  "geometry": {"coordinates":[-0.20050409709743,51.41532082276801],"type":"Point"}
}