{
  "type": "Feature",
  "properties": {
    "date:inception_lower":"1990-07-01",
    "date:inception_upper":"1990-07-31",
    "iso:country":"GB",
    "wof:name":"SW19 1PX",
    "wof:placetype":"postalcode"
},
  "geometry": {"coordinates":[-0.200504,51.415321],"type":"Point"}
}