{
  "type": "Feature",
  "properties": {
    "iso:country": "GB",
    "wof:name": "SW19 1PX",
    "wof:placetype": "postalcode"
  },
  "geometry": {"coordinates":[-0.200504,51.415321],"type":"Point"}
}
