{
  "type": "Feature",
  "properties": {
    "iso:country":"GB",
    "wof:name":"OL9 9AX",
    "wof:placetype":"postalcode"
},
  "geometry": {"coordinates":[-2.1409385533022,53.53918734798906],"type":"Point"}
}