{
  "type": "Feature",
  "properties": {
    "iso:country":"GB",
    "wof:name":"N18 1PX",
    "wof:placetype":"postalcode"
},
  "geometry": {"coordinates":[-0.0769588253634,51.61747221340612],"type":"Point"}
}