{
  "type": "Feature",
  "properties": {
    "date:inception_lower": "1980-01-01",
    "date:inception_upper": "1980-01-01",
    "iso:country": "GB",
    "wof:name": "LL13 9SZ",
    "wof:placetype": "postalcode"
  },
  "geometry": {"coordinates":[-2.973436,53.065861],"type":"Point"}
}
