{
  "type": "Feature",
  "properties": {
    "iso:country":"GB",
    "wof:name":"LL13 9SZ",
    "wof:placetype":"postalcode"
},
  "geometry": {"coordinates":[-2.97343612485369,53.06586104231331],"type":"Point"}
}