{
  "type": "Feature",
  "properties": {
    "date:inception_lower":"2011-10-01",
    "date:inception_upper":"2011-10-31",
    "iso:country":"GB",
    "wof:name":"BA16 0GT",
    "wof:placetype":"postalcode"
},
  "geometry": {"coordinates":[-2.74297,51.125364],"type":"Point"}
}