{
  "type": "Feature",
  "properties": {
    "iso:country": "GB",
    "wof:name": "BA16 0GT",
    "wof:placetype": "postalcode"
  },
  "geometry": {"coordinates":[-2.74297,51.125364],"type":"Point"}
}
