{
  "type": "Feature",
  "properties": {
    "iso:country":"GB",
    "wof:name":"BA16 0GT",
    "wof:placetype":"postalcode"
},
  "geometry": {"coordinates":[-2.74296961089444,51.12536369168903],"type":"Point"}
}