{
  "type": "Feature",
  "properties": {
    "iso:country": "GB",
    "wof:name": "BA16 0GT",
    "wof:placetype": "postalcode"
  },
  "geometry": {"coordinates":[-2.742719,51.125494],"type":"Point"}
}
