{
  "type": "Feature",
  "properties": {
    "iso:country": "GB",
    "wof:name": "SN15 3TJ",
    "wof:placetype": "postalcode"
  },
  "geometry": {"coordinates":[-2.093846,51.448713],"type":"Point"}
}
