{
  "type": "Feature",
  "properties": {
    "iso:country": "GB",
    "wof:name": "SS5 4PN",
    "wof:placetype": "postalcode"
  },
  "geometry": {"coordinates":[0.651741,51.600652],"type":"Point"}
}
