{
  "type": "Feature",
  "properties": {
    "iso:country":"GB",
    "wof:name":"SS5 4PN",
    "wof:placetype":"postalcode"
},
  "geometry": {"coordinates":[0.65174068824526,51.60065205629186],"type":"Point"}
}