{
  "type": "Feature",
  "properties": {
    "iso:country":"GB",
    "wof:name":"CR2 9BS",
    "wof:placetype":"postalcode"
},
  "geometry": {"coordinates":[-0.06625553890053,51.32495428911375],"type":"Point"}
}