{
  "type": "Feature",
  "properties": {
    "date:inception_lower": "1993-08-01",
    "date:inception_upper": "1993-08-01",
    "iso:country": "GB",
    "wof:name": "IG5 0QZ",
    "wof:placetype": "postalcode"
  },
  "geometry": {"coordinates":[0.061152,51.595138],"type":"Point"}
}
