{
  "type": "Feature",
  "properties": {
    "iso:country":"GB",
    "wof:name":"LS13 3JZ",
    "wof:placetype":"postalcode"
},
  "geometry": {"coordinates":[-1.63362474431007,53.81382093270076],"type":"Point"}
}