{
  "type": "Feature",
  "properties": {
    "date:inception_lower": "2018-01-01",
    "date:inception_upper": "2018-01-01",
    "iso:country": "GB",
    "wof:name": "M1 1AL",
    "wof:placetype": "postalcode"
  },
  "geometry": {"coordinates":[-2.230472,53.483183],"type":"Point"}
}
