{
  "type": "Feature",
  "properties": {
    "iso:country": "GB",
    "wof:name": "BA15 2HR",
    "wof:placetype": "postalcode"
  },
  "geometry": {"coordinates":[-2.278823,51.350715],"type":"Point"}
}
