{
  "type": "Feature",
  "properties": {
    "iso:country":"GB",
    "wof:name":"CM2 8QU",
    "wof:placetype":"postalcode"
},
  "geometry": {"coordinates":[0.47855503703215,51.69804808307598],"type":"Point"}
}