{
  "type": "Feature",
  "properties": {
    "iso:country":"GB",
    "wof:name":"PA13 4JS",
    "wof:placetype":"postalcode"
},
  "geometry": {"coordinates":[-4.6465316268345,55.89318615719289],"type":"Point"}
}