{
  "type": "Feature",
  "properties": {
    "iso:country": "GB",
    "wof:name": "DG7 1GD",
    "wof:placetype": "postalcode"
  },
  "geometry": {"coordinates":[-3.924409,54.933798],"type":"Point"}
}
