{
  "type": "Feature",
  "properties": {
    "iso:country":"GB",
    "wof:name":"DG7 1GD",
    "wof:placetype":"postalcode"
},
  "geometry": {"coordinates":[-3.92440929583174,54.93379774435793],"type":"Point"}
}