{
  "type": "Feature",
  "properties": {
    "iso:country":"GB",
    "wof:name":"CM24 8SU",
    "wof:placetype":"postalcode"
},
  "geometry": {"coordinates":[0.2177077675984,51.91477761971672],"type":"Point"}
}