{
  "type": "Feature",
  "properties": {
    "iso:country": "GB",
    "wof:name": "CM24 8SU",
    "wof:placetype": "postalcode"
  },
  "geometry": {"coordinates":[0.212976,51.915604],"type":"Point"}
}
