{
  "type": "Feature",
  "properties": {
    "date:inception_lower": "1980-01-01",
    "date:inception_upper": "1980-01-01",
    "iso:country": "GB",
    "wof:name": "CM24 8SU",
    "wof:placetype": "postalcode"
  },
  "geometry": {"coordinates":[0.217735,51.914786],"type":"Point"}
}
