{
  "type": "Feature",
  "properties": {
    "iso:country":"GB",
    "wof:name":"BS9 1ET",
    "wof:placetype":"postalcode"
},
  "geometry": {"coordinates":[-2.63685262926816,51.47948809823646],"type":"Point"}
}