{
  "type": "Feature",
  "properties": {
    "iso:country":"GB",
    "wof:name":"LU7 9GF",
    "wof:placetype":"postalcode"
},
  "geometry": {"coordinates":[-0.64681547826094,51.82990341715939],"type":"Point"}
}