{
  "type": "Feature",
  "properties": {
    "date:inception_lower": "2000-06-01",
    "date:inception_upper": "2000-06-01",
    "iso:country": "GB",
    "wof:name": "LU7 9GF",
    "wof:placetype": "postalcode"
  },
  "geometry": {"coordinates":[-0.646905,51.829958],"type":"Point"}
}
