{
  "type": "Feature",
  "properties": {
    "iso:country":"GB",
    "wof:name":"SY5 9QU",
    "wof:placetype":"postalcode"
},
  "geometry": {"coordinates":[-2.95023546152017,52.67669595661579],"type":"Point"}
}