{
  "type": "Feature",
  "properties": {
    "date:inception_lower": "1980-01-01",
    "date:inception_upper": "1980-01-01",
    "iso:country": "GB",
    "wof:name": "SY5 9QU",
    "wof:placetype": "postalcode"
  },
  "geometry": {"coordinates":[-2.950235,52.676696],"type":"Point"}
}
