{
  "type": "Feature",
  "properties": {
    "iso:country": "GB",
    "wof:name": "OX11 9FD",
    "wof:placetype": "postalcode"
  },
  "geometry": {"coordinates":[-1.191901,51.588952],"type":"Point"}
}
