{
  "type": "Feature",
  "properties": {
    "iso:country":"GB",
    "wof:name":"OX11 9FD",
    "wof:placetype":"postalcode"
},
  "geometry": {"coordinates":[-1.19187106538308,51.5890060450466],"type":"Point"}
}