{
  "type": "Feature",
  "properties": {
    "iso:country":"GB",
    "wof:name":"YO61 1NG",
    "wof:placetype":"postalcode"
},
  "geometry": {"coordinates":[-1.10163068771849,54.10365045276275],"type":"Point"}
}