{
  "type": "Feature",
  "properties": {
    "iso:country":"GB",
    "wof:name":"DT4 9SX",
    "wof:placetype":"postalcode"
},
  "geometry": {"coordinates":[-2.48812439542467,50.61066163181857],"type":"Point"}
}