{
  "type": "Feature",
  "properties": {
    "iso:country":"GB",
    "wof:name":"DT1 2NX",
    "wof:placetype":"postalcode"
},
  "geometry": {"coordinates":[-2.45256009271348,50.7145014391466],"type":"Point"}
}