{
  "type": "Feature",
  "properties": {
    "date:inception_lower":"2005-07-01",
    "date:inception_upper":"2005-07-31",
    "iso:country":"GB",
    "wof:name":"HP27 0WW",
    "wof:placetype":"postalcode"
},
  "geometry": {"coordinates":[-0.771607,51.778221],"type":"Point"}
}