{
  "type": "Feature",
  "properties": {
    "date:inception_lower": "1980-01-01",
    "date:inception_upper": "1980-01-01",
    "iso:country": "GB",
    "wof:name": "CA3 0HF",
    "wof:placetype": "postalcode"
  },
  "geometry": {"coordinates":[-2.951937,54.916501],"type":"Point"}
}
