{
  "type": "Feature",
  "properties": {
    "iso:country": "GB",
    "wof:name": "DH2 1XD",
    "wof:placetype": "postalcode"
  },
  "geometry": {"coordinates":[-1.622187,54.869853],"type":"Point"}
}
