{
  "type": "Feature",
  "properties": {
    "iso:country":"GB",
    "wof:name":"DH2 1XD",
    "wof:placetype":"postalcode"
},
  "geometry": {"coordinates":[-1.6221866623263,54.86985339462557],"type":"Point"}
}