{
  "type": "Feature",
  "properties": {
    "iso:country":"GB",
    "wof:name":"M8 8FJ",
    "wof:placetype":"postalcode"
},
  "geometry": {"coordinates":[-2.25023724780523,53.49462361128839],"type":"Point"}
}