{
  "type": "Feature",
  "properties": {
    "iso:country":"GB",
    "wof:name":"BS23 1AY",
    "wof:placetype":"postalcode"
},
  "geometry": {"coordinates":[-2.98019641315276,51.345919461022],"type":"Point"}
}