{
  "type": "Feature",
  "properties": {
    "date:inception_lower": "2024-05-01",
    "date:inception_upper": "2024-05-01",
    "iso:country": "GB",
    "wof:name": "BS23 1AY",
    "wof:placetype": "postalcode"
  },
  "geometry": {"coordinates":[-2.980178,51.345431],"type":"Point"}
}
