{
  "type": "Feature",
  "properties": {
    "date:inception_lower": "1980-01-01",
    "date:inception_upper": "1980-01-01",
    "iso:country": "GB",
    "wof:name": "DL7 0JY",
    "wof:placetype": "postalcode"
  },
  "geometry": {"coordinates":[-1.505975,54.447618],"type":"Point"}
}
