{
  "type": "Feature",
  "properties": {
    "iso:country":"GB",
    "wof:name":"DL7 0JY",
    "wof:placetype":"postalcode"
},
  "geometry": {"coordinates":[-1.5056112229097,54.44756901404211],"type":"Point"}
}