{
  "type": "Feature",
  "properties": {
    "date:inception_lower": "1990-07-01",
    "date:inception_upper": "1990-07-01",
    "iso:country": "GB",
    "wof:name": "DE55 3BG",
    "wof:placetype": "postalcode"
  },
  "geometry": {"coordinates":[-1.334612,53.094711],"type":"Point"}
}
