{
  "type": "Feature",
  "properties": {
    "iso:country":"GB",
    "wof:name":"DE55 3BG",
    "wof:placetype":"postalcode"
},
  "geometry": {"coordinates":[-1.33461161707539,53.09471088487158],"type":"Point"}
}