{
  "type": "Feature",
  "properties": {
    "iso:country":"GB",
    "wof:name":"TD10 6XS",
    "wof:placetype":"postalcode"
},
  "geometry": {"coordinates":[-2.51548787720758,55.70108535409357],"type":"Point"}
}