{
  "type": "Feature",
  "properties": {
    "iso:country":"GB",
    "wof:name":"SR8 2NR",
    "wof:placetype":"postalcode"
},
  "geometry": {"coordinates":[-1.34675415037232,54.75530971215948],"type":"Point"}
}