{
  "type": "Feature",
  "properties": {
    "date:inception_lower": "2000-06-01",
    "date:inception_upper": "2000-06-01",
    "iso:country": "GB",
    "wof:name": "M14 6ZG",
    "wof:placetype": "postalcode"
  },
  "geometry": {"coordinates":[-2.217048,53.445097],"type":"Point"}
}
