{
  "type": "Feature",
  "properties": {
    "iso:country":"GB",
    "wof:name":"PR25 5SA",
    "wof:placetype":"postalcode"
},
  "geometry": {"coordinates":[-2.67344821261763,53.70615728843345],"type":"Point"}
}