{
  "type": "Feature",
  "properties": {
    "iso:country": "GB",
    "wof:name": "PR25 5SA",
    "wof:placetype": "postalcode"
  },
  "geometry": {"coordinates":[-2.673448,53.706157],"type":"Point"}
}
