{
  "type": "Feature",
  "properties": {
    "iso:country":"GB",
    "wof:name":"NE26 2TP",
    "wof:placetype":"postalcode"
},
  "geometry": {"coordinates":[-1.44921839011698,55.04179367859548],"type":"Point"}
}