{
  "type": "Feature",
  "properties": {
    "iso:country":"GB",
    "wof:name":"OL2 7BG",
    "wof:placetype":"postalcode"
},
  "geometry": {"coordinates":[-2.10284759564317,53.57388523282085],"type":"Point"}
}