{
  "type": "Feature",
  "properties": {
    "iso:country":"GB",
    "wof:name":"OX25 4TB",
    "wof:placetype":"postalcode"
},
  "geometry": {"coordinates":[-1.19886734070217,51.92013972933818],"type":"Point"}
}