{
  "type": "Feature",
  "properties": {
    "iso:country": "GB",
    "wof:name": "OX25 4TB",
    "wof:placetype": "postalcode"
  },
  "geometry": {"coordinates":[-1.198867,51.92014],"type":"Point"}
}
