{
  "type": "Feature",
  "properties": {
    "date:inception_lower": "2000-10-01",
    "date:inception_upper": "2000-10-01",
    "iso:country": "GB",
    "wof:name": "OX25 4TB",
    "wof:placetype": "postalcode"
  },
  "geometry": {"coordinates":[-1.19867,51.920381],"type":"Point"}
}
