{
  "type": "Feature",
  "properties": {
    "iso:country":"GB",
    "wof:name":"M24 5TT",
    "wof:placetype":"postalcode"
},
  "geometry": {"coordinates":[-2.19908313044139,53.55019619169086],"type":"Point"}
}