{
  "type": "Feature",
  "properties": {
    "date:inception_lower":"1996-06-01",
    "date:inception_upper":"1996-06-30",
    "iso:country":"GB",
    "wof:name":"M24 5TT",
    "wof:placetype":"postalcode"
},
  "geometry": {"coordinates":[-2.199083,53.550196],"type":"Point"}
}