{
  "type": "Feature",
  "properties": {
    "iso:country":"GB",
    "wof:name":"TW11 9AS",
    "wof:placetype":"postalcode"
},
  "geometry": {"coordinates":[-0.33042299515837,51.42555255891101],"type":"Point"}
}