{
  "type": "Feature",
  "properties": {
    "iso:country":"GB",
    "wof:name":"EX35 6NS",
    "wof:placetype":"postalcode"
},
  "geometry": {"coordinates":[-3.83647786612034,51.22074718012336],"type":"Point"}
}