{
  "type": "Feature",
  "properties": {
    "iso:country":"GB",
    "wof:name":"NG15 8HR",
    "wof:placetype":"postalcode"
},
  "geometry": {"coordinates":[-1.18726933047371,53.04285391568877],"type":"Point"}
}