{
  "type": "Feature",
  "properties": {
    "iso:country":"GB",
    "wof:name":"LN9 5ND",
    "wof:placetype":"postalcode"
},
  "geometry": {"coordinates":[-0.17020057870428,53.25073978055713],"type":"Point"}
}