{
  "type": "Feature",
  "properties": {
    "iso:country": "GB",
    "wof:name": "LN9 5ND",
    "wof:placetype": "postalcode"
  },
  "geometry": {"coordinates":[-0.170201,53.25074],"type":"Point"}
}
