{
  "type": "Feature",
  "properties": {
    "iso:country":"GB",
    "wof:name":"SS5 6BN",
    "wof:placetype":"postalcode"
},
  "geometry": {"coordinates":[0.6191077256211,51.61879636139722],"type":"Point"}
}