{
  "type": "Feature",
  "properties": {
    "iso:country":"GB",
    "wof:name":"OX5 1NR",
    "wof:placetype":"postalcode"
},
  "geometry": {"coordinates":[-1.30628063617312,51.84728391005144],"type":"Point"}
}