{
  "type": "Feature",
  "properties": {
    "date:inception_lower": "1992-08-01",
    "date:inception_upper": "1992-08-01",
    "iso:country": "GB",
    "wof:name": "OX5 1NR",
    "wof:placetype": "postalcode"
  },
  "geometry": {"coordinates":[-1.306281,51.847284],"type":"Point"}
}
