{
  "type": "Feature",
  "properties": {
    "date:inception_lower": "2003-04-01",
    "date:inception_upper": "2003-04-01",
    "iso:country": "GB",
    "wof:name": "TN29 9DL",
    "wof:placetype": "postalcode"
  },
  "geometry": {"coordinates":[0.913885,50.952301],"type":"Point"}
}
