{
  "type": "Feature",
  "properties": {
    "date:inception_lower": "1993-01-01",
    "date:inception_upper": "1993-01-01",
    "iso:country": "GB",
    "wof:name": "BA11 4LT",
    "wof:placetype": "postalcode"
  },
  "geometry": {"coordinates":[-2.332426,51.231568],"type":"Point"}
}
