{
  "type": "Feature",
  "properties": {
    "iso:country": "GB",
    "wof:name": "BA11 4LT",
    "wof:placetype": "postalcode"
  },
  "geometry": {"coordinates":[-2.332426,51.231568],"type":"Point"}
}
