{
  "type": "Feature",
  "properties": {
    "iso:country": "GB",
    "wof:name": "TN25 6WE",
    "wof:placetype": "postalcode"
  },
  "geometry": {"coordinates":[0.971213,51.126117],"type":"Point"}
}
