{
  "type": "Feature",
  "properties": {
    "date:inception_lower": "2013-04-01",
    "date:inception_upper": "2013-04-01",
    "iso:country": "GB",
    "wof:name": "TN25 6WE",
    "wof:placetype": "postalcode"
  },
  "geometry": {"coordinates":[0.971213,51.126117],"type":"Point"}
}
