{
  "type": "Feature",
  "properties": {
    "iso:country":"GB",
    "wof:name":"LE5 0TE",
    "wof:placetype":"postalcode"
},
  "geometry": {"coordinates":[-1.08054358074317,52.64796815812044],"type":"Point"}
}