{
  "type": "Feature",
  "properties": {
    "iso:country": "GB",
    "wof:name": "SG6 3LU",
    "wof:placetype": "postalcode"
  },
  "geometry": {"coordinates":[-0.23696,51.967624],"type":"Point"}
}
