{
  "type": "Feature",
  "properties": {
    "iso:country":"GB",
    "wof:name":"N20 9BH",
    "wof:placetype":"postalcode"
},
  "geometry": {"coordinates":[-0.17550831010798,51.63354985381764],"type":"Point"}
}