{
  "type": "Feature",
  "properties": {
    "date:inception_lower": "2003-01-01",
    "date:inception_upper": "2003-01-01",
    "iso:country": "GB",
    "wof:name": "LE67 6PJ",
    "wof:placetype": "postalcode"
  },
  "geometry": {"coordinates":[-1.399013,52.696308],"type":"Point"}
}
