{
  "type": "Feature",
  "properties": {
    "iso:country": "GB",
    "wof:name": "LE67 6PJ",
    "wof:placetype": "postalcode"
  },
  "geometry": {"coordinates":[-1.399013,52.696308],"type":"Point"}
}
