{
  "type": "Feature",
  "properties": {
    "iso:country":"GB",
    "wof:name":"LE67 6PJ",
    "wof:placetype":"postalcode"
},
  "geometry": {"coordinates":[-1.39901311500938,52.69630797451484],"type":"Point"}
}