{
  "type": "Feature",
  "properties": {
    "date:inception_lower":"2004-11-01",
    "date:inception_upper":"2004-11-30",
    "iso:country":"GB",
    "wof:name":"RM6 4UP",
    "wof:placetype":"postalcode"
},
  "geometry": {"coordinates":[0.117754,51.577206],"type":"Point"}
}