{
  "type": "Feature",
  "properties": {
    "iso:country":"GB",
    "wof:name":"SA1 7AL",
    "wof:placetype":"postalcode"
},
  "geometry": {"coordinates":[-3.9195454401905,51.63753788855887],"type":"Point"}
}