{
  "type": "Feature",
  "properties": {
    "date:inception_lower": "1980-01-01",
    "date:inception_upper": "1980-01-01",
    "iso:country": "GB",
    "wof:name": "BB8 0SQ",
    "wof:placetype": "postalcode"
  },
  "geometry": {"coordinates":[-2.170782,53.855526],"type":"Point"}
}
