{
  "type": "Feature",
  "properties": {
    "iso:country":"GB",
    "wof:name":"BB8 0SQ",
    "wof:placetype":"postalcode"
},
  "geometry": {"coordinates":[-2.17076439615072,53.85548526301228],"type":"Point"}
}