{
  "type": "Feature",
  "properties": {
    "iso:country":"GB",
    "wof:name":"GU10 3EB",
    "wof:placetype":"postalcode"
},
  "geometry": {"coordinates":[-0.79891088911797,51.16517338287045],"type":"Point"}
}