{
  "type": "Feature",
  "properties": {
    "iso:country": "GB",
    "wof:name": "TN27 8DZ",
    "wof:placetype": "postalcode"
  },
  "geometry": {"coordinates":[0.634402,51.104099],"type":"Point"}
}
