{
  "type": "Feature",
  "properties": {
    "iso:country":"GB",
    "wof:name":"TN27 8DZ",
    "wof:placetype":"postalcode"
},
  "geometry": {"coordinates":[0.63408587741044,51.10410764076362],"type":"Point"}
}