{
  "type": "Feature",
  "properties": {
    "iso:country": "GB",
    "wof:name": "KA2 0EL",
    "wof:placetype": "postalcode"
  },
  "geometry": {"coordinates":[-4.575715,55.601138],"type":"Point"}
}
