{
  "type": "Feature",
  "properties": {
    "iso:country":"GB",
    "wof:name":"KA2 0EL",
    "wof:placetype":"postalcode"
},
  "geometry": {"coordinates":[-4.57571524304754,55.60113757084162],"type":"Point"}
}