{
  "type": "Feature",
  "properties": {
    "iso:country":"GB",
    "wof:name":"EH44 6PG",
    "wof:placetype":"postalcode"
},
  "geometry": {"coordinates":[-3.0648451999007,55.61619249165756],"type":"Point"}
}