{
  "type": "Feature",
  "properties": {
    "date:inception_lower":"1999-12-01",
    "date:inception_upper":"1999-12-31",
    "iso:country":"GB",
    "wof:name":"NP20 1FB",
    "wof:placetype":"postalcode"
},
  "geometry": {"coordinates":[-2.996907,51.590149],"type":"Point"}
}