{
  "type": "Feature",
  "properties": {
    "iso:country":"GB",
    "wof:name":"PE28 0QW",
    "wof:placetype":"postalcode"
},
  "geometry": {"coordinates":[-0.45008797816814,52.37154188651747],"type":"Point"}
}