{
  "type": "Feature",
  "properties": {
    "iso:country":"GB",
    "wof:name":"LL54 6HS",
    "wof:placetype":"postalcode"
},
  "geometry": {"coordinates":[-4.25600822196699,53.05484949026605],"type":"Point"}
}