{
  "type": "Feature",
  "properties": {
    "date:inception_lower": "1980-01-01",
    "date:inception_upper": "1980-01-01",
    "iso:country": "GB",
    "wof:name": "LL54 6HS",
    "wof:placetype": "postalcode"
  },
  "geometry": {"coordinates":[-4.256008,53.054849],"type":"Point"}
}
