{
  "type": "Feature",
  "properties": {
    "iso:country": "GB",
    "wof:name": "LL54 6HS",
    "wof:placetype": "postalcode"
  },
  "geometry": {"coordinates":[-4.256008,53.054849],"type":"Point"}
}
