{
  "type": "Feature",
  "properties": {
    "iso:country": "GB",
    "wof:name": "LL20 7US",
    "wof:placetype": "postalcode"
  },
  "geometry": {"coordinates":[-3.101785,52.975376],"type":"Point"}
}
