{
  "type": "Feature",
  "properties": {
    "iso:country":"GB",
    "wof:name":"LL20 7US",
    "wof:placetype":"postalcode"
},
  "geometry": {"coordinates":[-3.10178544589973,52.97537595805586],"type":"Point"}
}