{
  "type": "Feature",
  "properties": {
    "date:inception_lower":"2002-07-01",
    "date:inception_upper":"2002-07-31",
    "iso:country":"GB",
    "wof:name":"LL20 7US",
    "wof:placetype":"postalcode"
},
  "geometry": {"coordinates":[-3.101785,52.975376],"type":"Point"}
}