{
  "type": "Feature",
  "properties": {
    "date:inception_lower": "2023-05-01",
    "date:inception_upper": "2023-05-01",
    "iso:country": "GB",
    "wof:name": "BB6 7FY",
    "wof:placetype": "postalcode"
  },
  "geometry": {"coordinates":[-2.407453,53.786593],"type":"Point"}
}
