{
  "type": "Feature",
  "properties": {
    "iso:country":"GB",
    "wof:name":"GU35 0BH",
    "wof:placetype":"postalcode"
},
  "geometry": {"coordinates":[-0.85993598852975,51.11071448770738],"type":"Point"}
}