{
  "type": "Feature",
  "properties": {
    "iso:country":"GB",
    "wof:name":"SS11 8NH",
    "wof:placetype":"postalcode"
},
  "geometry": {"coordinates":[0.54616396387961,51.6151766151547],"type":"Point"}
}