{
  "type": "Feature",
  "properties": {
    "iso:country":"GB",
    "wof:name":"TR9 6TE",
    "wof:placetype":"postalcode"
},
  "geometry": {"coordinates":[-4.94114189181094,50.37949889513686],"type":"Point"}
}