{
  "type": "Feature",
  "properties": {
    "iso:country": "GB",
    "wof:name": "CM22 6BP",
    "wof:placetype": "postalcode"
  },
  "geometry": {"coordinates":[0.248539,51.929695],"type":"Point"}
}
