{
  "type": "Feature",
  "properties": {
    "date:inception_lower":"1980-01-01",
    "date:inception_upper":"1980-01-31",
    "iso:country":"GB",
    "wof:name":"CM22 6BP",
    "wof:placetype":"postalcode"
},
  "geometry": {"coordinates":[0.248539,51.929695],"type":"Point"}
}