{
  "type": "Feature",
  "properties": {
    "iso:country":"GB",
    "wof:name":"GU11 3JN",
    "wof:placetype":"postalcode"
},
  "geometry": {"coordinates":[-0.77237684191881,51.24392284876959],"type":"Point"}
}