{
  "type": "Feature",
  "properties": {
    "iso:country": "GB",
    "wof:name": "DN9 3HH",
    "wof:placetype": "postalcode"
  },
  "geometry": {"coordinates":[-1.018702,53.498968],"type":"Point"}
}
