{
  "type": "Feature",
  "properties": {
    "date:inception_lower":"1981-06-01",
    "date:inception_upper":"1981-06-30",
    "iso:country":"GB",
    "wof:name":"BN2 5GH",
    "wof:placetype":"postalcode"
},
  "geometry": {"coordinates":[-0.107286,50.819841],"type":"Point"}
}