{
  "type": "Feature",
  "properties": {
    "iso:country":"GB",
    "wof:name":"BN2 5GH",
    "wof:placetype":"postalcode"
},
  "geometry": {"coordinates":[-0.10728649033754,50.81984074609967],"type":"Point"}
}