{
  "type": "Feature",
  "properties": {
    "iso:country":"GB",
    "wof:name":"BN10 8QN",
    "wof:placetype":"postalcode"
},
  "geometry": {"coordinates":[0.01708444299146,50.78788858876851],"type":"Point"}
}