{
  "type": "Feature",
  "properties": {
    "iso:country":"GB",
    "wof:name":"BN3 2TN",
    "wof:placetype":"postalcode"
},
  "geometry": {"coordinates":[-0.17602802456386,50.82608899421803],"type":"Point"}
}