{
  "type": "Feature",
  "properties": {
    "iso:country":"GB",
    "wof:name":"DT7 3AB",
    "wof:placetype":"postalcode"
},
  "geometry": {"coordinates":[-2.93880938078783,50.72822675597904],"type":"Point"}
}