{
  "type": "Feature",
  "properties": {
    "iso:country": "GB",
    "wof:name": "SR6 9HP",
    "wof:placetype": "postalcode"
  },
  "geometry": {"coordinates":[-1.378534,54.927345],"type":"Point"}
}
