{
  "type": "Feature",
  "properties": {
    "iso:country":"GB",
    "wof:name":"SR6 9HP",
    "wof:placetype":"postalcode"
},
  "geometry": {"coordinates":[-1.37853435269839,54.92734474384118],"type":"Point"}
}