{
  "type": "Feature",
  "properties": {
    "iso:country":"GB",
    "wof:name":"RM13 9TR",
    "wof:placetype":"postalcode"
},
  "geometry": {"coordinates":[0.1963998147005,51.51673946554043],"type":"Point"}
}