{
  "type": "Feature",
  "properties": {
    "iso:country": "GB",
    "wof:name": "CV3 1DQ",
    "wof:placetype": "postalcode"
  },
  "geometry": {"coordinates":[-1.474423,52.39829],"type":"Point"}
}
