{
  "type": "Feature",
  "properties": {
    "iso:country":"GB",
    "wof:name":"CV3 1DQ",
    "wof:placetype":"postalcode"
},
  "geometry": {"coordinates":[-1.47442265856987,52.39828955490579],"type":"Point"}
}