{
  "type": "Feature",
  "properties": {
    "date:inception_lower":"1995-12-01",
    "date:inception_upper":"1995-12-31",
    "iso:country":"GB",
    "wof:name":"NE39 1PA",
    "wof:placetype":"postalcode"
},
  "geometry": {"coordinates":[-1.741409,54.927489],"type":"Point"}
}