{
  "type": "Feature",
  "properties": {
    "iso:country":"GB",
    "wof:name":"LA9 5DF",
    "wof:placetype":"postalcode"
},
  "geometry": {"coordinates":[-2.74698240902405,54.3219382942353],"type":"Point"}
}