{
  "type": "Feature",
  "properties": {
    "date:inception_lower": "2020-01-01",
    "date:inception_upper": "2020-01-01",
    "iso:country": "GB",
    "wof:name": "NE1 2DS",
    "wof:placetype": "postalcode"
  },
  "geometry": {"coordinates":[-1.607576,54.970093],"type":"Point"}
}
