{
  "type": "Feature",
  "properties": {
    "date:inception_lower":"1980-01-01",
    "date:inception_upper":"1980-01-31",
    "iso:country":"GB",
    "wof:name":"DN38 6AE",
    "wof:placetype":"postalcode"
},
  "geometry": {"coordinates":[-0.364459,53.586475],"type":"Point"}
}