{
  "type": "Feature",
  "properties": {
    "iso:country": "GB",
    "wof:name": "DN38 6AE",
    "wof:placetype": "postalcode"
  },
  "geometry": {"coordinates":[-0.364459,53.586475],"type":"Point"}
}
