{
  "type": "Feature",
  "properties": {
    "iso:country":"GB",
    "wof:name":"DN38 6AE",
    "wof:placetype":"postalcode"
},
  "geometry": {"coordinates":[-0.36445927917842,53.58647453545994],"type":"Point"}
}