{
  "type": "Feature",
  "properties": {
    "date:inception_lower": "1993-01-01",
    "date:inception_upper": "1993-01-01",
    "iso:country": "GB",
    "wof:name": "SP3 5AR",
    "wof:placetype": "postalcode"
  },
  "geometry": {"coordinates":[-2.044944,51.093043],"type":"Point"}
}
