{
  "type": "Feature",
  "properties": {
    "iso:country":"GB",
    "wof:name":"SP3 5AR",
    "wof:placetype":"postalcode"
},
  "geometry": {"coordinates":[-2.04494375881686,51.09304323032302],"type":"Point"}
}