{
  "type": "Feature",
  "properties": {
    "iso:country":"GB",
    "wof:name":"L40 7TF",
    "wof:placetype":"postalcode"
},
  "geometry": {"coordinates":[-2.84605687992674,53.59962758883027],"type":"Point"}
}