{
  "type": "Feature",
  "properties": {
    "iso:country": "GB",
    "wof:name": "L40 7TF",
    "wof:placetype": "postalcode"
  },
  "geometry": {"coordinates":[-2.846057,53.599628],"type":"Point"}
}
