{
  "type": "Feature",
  "properties": {
    "iso:country": "GB",
    "wof:name": "IP12 1BG",
    "wof:placetype": "postalcode"
  },
  "geometry": {"coordinates":[1.320265,52.092362],"type":"Point"}
}
