{
  "type": "Feature",
  "properties": {
    "iso:country":"GB",
    "wof:name":"ST13 6HE",
    "wof:placetype":"postalcode"
},
  "geometry": {"coordinates":[-2.01347863690273,53.10996198300046],"type":"Point"}
}