{
  "type": "Feature",
  "properties": {
    "iso:country":"GB",
    "wof:name":"AL4 9NB",
    "wof:placetype":"postalcode"
},
  "geometry": {"coordinates":[-0.31653571530279,51.7685770777674],"type":"Point"}
}