{
  "type": "Feature",
  "properties": {
    "date:inception_lower": "2023-10-01",
    "date:inception_upper": "2023-10-01",
    "iso:country": "GB",
    "wof:name": "SY12 0FW",
    "wof:placetype": "postalcode"
  },
  "geometry": {"coordinates":[-2.902982,52.903128],"type":"Point"}
}
