{
  "type": "Feature",
  "properties": {
    "iso:country":"GB",
    "wof:name":"SY17 5ER",
    "wof:placetype":"postalcode"
},
  "geometry": {"coordinates":[-3.42629179228167,52.51742905737537],"type":"Point"}
}