{
  "type": "Feature",
  "properties": {
    "iso:country": "GB",
    "wof:name": "IV30 6LL",
    "wof:placetype": "postalcode"
  },
  "geometry": {"coordinates":[-3.298498,57.634104],"type":"Point"}
}
