{
  "type": "Feature",
  "properties": {
    "iso:country":"GB",
    "wof:name":"IV30 6LL",
    "wof:placetype":"postalcode"
},
  "geometry": {"coordinates":[-3.29830957516707,57.63390551120469],"type":"Point"}
}