{
  "type": "Feature",
  "properties": {
    "date:inception_lower": "2015-06-01",
    "date:inception_upper": "2015-06-01",
    "iso:country": "GB",
    "wof:name": "IV30 6LL",
    "wof:placetype": "postalcode"
  },
  "geometry": {"coordinates":[-3.298498,57.634104],"type":"Point"}
}
