{
  "type": "Feature",
  "properties": {
    "iso:country":"GB",
    "wof:name":"PL4 9BH",
    "wof:placetype":"postalcode"
},
  "geometry": {"coordinates":[-4.12829240706881,50.37266009798573],"type":"Point"}
}