{
  "type": "Feature",
  "properties": {
    "iso:country":"GB",
    "wof:name":"TR11 3LR",
    "wof:placetype":"postalcode"
},
  "geometry": {"coordinates":[-5.06987613944834,50.15248141222518],"type":"Point"}
}