{
  "type": "Feature",
  "properties": {
    "iso:country":"GB",
    "wof:name":"ST5 7QZ",
    "wof:placetype":"postalcode"
},
  "geometry": {"coordinates":[-2.25695094962386,53.03341256989877],"type":"Point"}
}