{
  "type": "Feature",
  "properties": {
    "iso:country":"GB",
    "wof:name":"PE4 6LU",
    "wof:placetype":"postalcode"
},
  "geometry": {"coordinates":[-0.28592174768341,52.61803716076758],"type":"Point"}
}