{
  "type": "Feature",
  "properties": {
    "iso:country":"GB",
    "wof:name":"M43 7SN",
    "wof:placetype":"postalcode"
},
  "geometry": {"coordinates":[-2.15801936801394,53.49062863970833],"type":"Point"}
}