{
  "type": "Feature",
  "properties": {
    "iso:country":"GB",
    "wof:name":"SW8 4JT",
    "wof:placetype":"postalcode"
},
  "geometry": {"coordinates":[-0.13953560588982,51.4767415027892],"type":"Point"}
}