{
  "type": "Feature",
  "properties": {
    "iso:country":"GB",
    "wof:name":"NP25 4DY",
    "wof:placetype":"postalcode"
},
  "geometry": {"coordinates":[-2.79404948947771,51.78594666078673],"type":"Point"}
}