{
  "type": "Feature",
  "properties": {
    "iso:country":"GB",
    "wof:name":"IV36 1JU",
    "wof:placetype":"postalcode"
},
  "geometry": {"coordinates":[-3.61965868655559,57.60346082305155],"type":"Point"}
}