{
  "type": "Feature",
  "properties": {
    "iso:country": "GB",
    "wof:name": "IV36 1JU",
    "wof:placetype": "postalcode"
  },
  "geometry": {"coordinates":[-3.619659,57.603461],"type":"Point"}
}
