{
  "type": "Feature",
  "properties": {
    "date:inception_lower":"1998-12-01",
    "date:inception_upper":"1998-12-31",
    "iso:country":"GB",
    "wof:name":"RH10 1UJ",
    "wof:placetype":"postalcode"
},
  "geometry": {"coordinates":[-0.171644,51.11401],"type":"Point"}
}