{
  "type": "Feature",
  "properties": {
    "iso:country":"GB",
    "wof:name":"L22 2AN",
    "wof:placetype":"postalcode"
},
  "geometry": {"coordinates":[-3.03156622094844,53.48254018803206],"type":"Point"}
}