{
  "type": "Feature",
  "properties": {
    "iso:country": "GB",
    "wof:name": "L22 2AN",
    "wof:placetype": "postalcode"
  },
  "geometry": {"coordinates":[-3.031566,53.48254],"type":"Point"}
}
