{
  "type": "Feature",
  "properties": {
    "iso:country": "GB",
    "wof:name": "GL51 7TL",
    "wof:placetype": "postalcode"
  },
  "geometry": {"coordinates":[-2.115025,51.897561],"type":"Point"}
}
