{
  "type": "Feature",
  "properties": {
    "date:inception_lower": "1980-01-01",
    "date:inception_upper": "1980-01-01",
    "iso:country": "GB",
    "wof:name": "CA11 0NZ",
    "wof:placetype": "postalcode"
  },
  "geometry": {"coordinates":[-2.916943,54.508782],"type":"Point"}
}
