{
  "type": "Feature",
  "properties": {
    "iso:country": "GB",
    "wof:name": "CA11 0NZ",
    "wof:placetype": "postalcode"
  },
  "geometry": {"coordinates":[-2.916943,54.508782],"type":"Point"}
}
