{
  "type": "Feature",
  "properties": {
    "iso:country":"GB",
    "wof:name":"BS7 9HT",
    "wof:placetype":"postalcode"
},
  "geometry": {"coordinates":[-2.5839883103847,51.4804287534946],"type":"Point"}
}