{
  "type": "Feature",
  "properties": {
    "date:inception_lower":"1980-01-01",
    "date:inception_upper":"1980-01-31",
    "iso:country":"GB",
    "wof:name":"HR1 3PQ",
    "wof:placetype":"postalcode"
},
  "geometry": {"coordinates":[-2.633365,52.123766],"type":"Point"}
}