{
  "type": "Feature",
  "properties": {
    "iso:country":"GB",
    "wof:name":"HR1 3PQ",
    "wof:placetype":"postalcode"
},
  "geometry": {"coordinates":[-2.63336474980431,52.12376626350461],"type":"Point"}
}