{
  "type": "Feature",
  "properties": {
    "iso:country": "GB",
    "wof:name": "WF3 4NL",
    "wof:placetype": "postalcode"
  },
  "geometry": {"coordinates":[-1.482083,53.701504],"type":"Point"}
}
