{
  "type": "Feature",
  "properties": {
    "date:inception_lower": "1980-01-01",
    "date:inception_upper": "1980-01-01",
    "iso:country": "GB",
    "wof:name": "WF3 4NL",
    "wof:placetype": "postalcode"
  },
  "geometry": {"coordinates":[-1.482083,53.701504],"type":"Point"}
}
