{
  "type": "Feature",
  "properties": {
    "iso:country":"GB",
    "wof:name":"N9 9RB",
    "wof:placetype":"postalcode"
},
  "geometry": {"coordinates":[-0.07178098947442,51.6254624846314],"type":"Point"}
}