{
  "type": "Feature",
  "properties": {
    "date:inception_lower": "1980-01-01",
    "date:inception_upper": "1980-01-01",
    "iso:country": "GB",
    "wof:name": "N9 9RB",
    "wof:placetype": "postalcode"
  },
  "geometry": {"coordinates":[-0.071781,51.625462],"type":"Point"}
}
