{
  "type": "Feature",
  "properties": {
    "date:inception_lower": "2008-09-01",
    "date:inception_upper": "2008-09-01",
    "iso:country": "GB",
    "wof:name": "KY16 9TB",
    "wof:placetype": "postalcode"
  },
  "geometry": {"coordinates":[-2.811999,56.344074],"type":"Point"}
}
