{
  "type": "Feature",
  "properties": {
    "iso:country":"GB",
    "wof:name":"UB1 3HY",
    "wof:placetype":"postalcode"
},
  "geometry": {"coordinates":[-0.36429683983035,51.51374131036473],"type":"Point"}
}