{
  "type": "Feature",
  "properties": {
    "iso:country": "GB",
    "wof:name": "S66 8PT",
    "wof:placetype": "postalcode"
  },
  "geometry": {"coordinates":[-1.246623,53.413934],"type":"Point"}
}
