{
  "type": "Feature",
  "properties": {
    "iso:country":"GB",
    "wof:name":"S66 8PT",
    "wof:placetype":"postalcode"
},
  "geometry": {"coordinates":[-1.24662314944539,53.41393434161609],"type":"Point"}
}