{
  "type": "Feature",
  "properties": {
    "iso:country":"GB",
    "wof:name":"HU14 3RL",
    "wof:placetype":"postalcode"
},
  "geometry": {"coordinates":[-0.4842182043401,53.74249324007035],"type":"Point"}
}