{
  "type": "Feature",
  "properties": {
    "date:inception_lower": "1991-09-01",
    "date:inception_upper": "1991-09-01",
    "iso:country": "GB",
    "wof:name": "HU14 3RL",
    "wof:placetype": "postalcode"
  },
  "geometry": {"coordinates":[-0.484218,53.742493],"type":"Point"}
}
