{
  "type": "Feature",
  "properties": {
    "date:inception_lower": "1998-06-01",
    "date:inception_upper": "1998-06-01",
    "iso:country": "GB",
    "wof:name": "LU6 2JH",
    "wof:placetype": "postalcode"
  },
  "geometry": {"coordinates":[-0.581059,51.864582],"type":"Point"}
}
