{
  "type": "Feature",
  "properties": {
    "iso:country":"GB",
    "wof:name":"S35 9YY",
    "wof:placetype":"postalcode"
},
  "geometry": {"coordinates":[-1.47258710306884,53.44159003301545],"type":"Point"}
}