{
  "type": "Feature",
  "properties": {
    "iso:country":"GB",
    "wof:name":"NE5 5JL",
    "wof:placetype":"postalcode"
},
  "geometry": {"coordinates":[-1.69508169705433,54.99543490839091],"type":"Point"}
}