{
  "type": "Feature",
  "properties": {
    "iso:country": "GB",
    "wof:name": "NE5 5JL",
    "wof:placetype": "postalcode"
  },
  "geometry": {"coordinates":[-1.695082,54.995435],"type":"Point"}
}
