{
  "type": "Feature",
  "properties": {
    "iso:country":"GB",
    "wof:name":"CM4 9DX",
    "wof:placetype":"postalcode"
},
  "geometry": {"coordinates":[0.38889426090338,51.67126355581339],"type":"Point"}
}