{
  "type": "Feature",
  "properties": {
    "iso:country":"GB",
    "wof:name":"M45 8LB",
    "wof:placetype":"postalcode"
},
  "geometry": {"coordinates":[-2.27664920408937,53.55299893295559],"type":"Point"}
}