{
  "type": "Feature",
  "properties": {
    "date:inception_lower":"2012-02-01",
    "date:inception_upper":"2012-02-29",
    "iso:country":"GB",
    "wof:name":"EH22 4FE",
    "wof:placetype":"postalcode"
},
  "geometry": {"coordinates":[-3.055806,55.870204],"type":"Point"}
}