{
  "type": "Feature",
  "properties": {
    "iso:country": "GB",
    "wof:name": "EH22 4FE",
    "wof:placetype": "postalcode"
  },
  "geometry": {"coordinates":[-3.055806,55.870204],"type":"Point"}
}
