{
  "type": "Feature",
  "properties": {
    "iso:country":"GB",
    "wof:name":"DN35 8EU",
    "wof:placetype":"postalcode"
},
  "geometry": {"coordinates":[-0.02532031517174,53.55747110545142],"type":"Point"}
}