{
  "type": "Feature",
  "properties": {
    "iso:country":"GB",
    "wof:name":"KT19 8BG",
    "wof:placetype":"postalcode"
},
  "geometry": {"coordinates":[-0.28467099846371,51.34280812881519],"type":"Point"}
}