{
  "type": "Feature",
  "properties": {
    "date:inception_lower":"2005-01-01",
    "date:inception_upper":"2005-01-31",
    "iso:country":"GB",
    "wof:name":"KT19 8BG",
    "wof:placetype":"postalcode"
},
  "geometry": {"coordinates":[-0.284671,51.342808],"type":"Point"}
}