{
  "type": "Feature",
  "properties": {
    "iso:country":"GB",
    "wof:name":"NR12 8YG",
    "wof:placetype":"postalcode"
},
  "geometry": {"coordinates":[1.45926510077452,52.72410265856131],"type":"Point"}
}