{
  "type": "Feature",
  "properties": {
    "iso:country": "GB",
    "wof:name": "NR12 8YG",
    "wof:placetype": "postalcode"
  },
  "geometry": {"coordinates":[1.459176,52.724034],"type":"Point"}
}
