{
  "type": "Feature",
  "properties": {
    "iso:country":"GB",
    "wof:name":"SY3 9DJ",
    "wof:placetype":"postalcode"
},
  "geometry": {"coordinates":[-2.7707791247956,52.69337182257811],"type":"Point"}
}