{
  "type": "Feature",
  "properties": {
    "iso:country": "GB",
    "wof:name": "WS3 4AR",
    "wof:placetype": "postalcode"
  },
  "geometry": {"coordinates":[-1.975667,52.631124],"type":"Point"}
}
