{
  "type": "Feature",
  "properties": {
    "date:inception_lower": "2014-09-01",
    "date:inception_upper": "2014-09-01",
    "iso:country": "GB",
    "wof:name": "WS3 4AR",
    "wof:placetype": "postalcode"
  },
  "geometry": {"coordinates":[-1.975667,52.631124],"type":"Point"}
}
