{
  "type": "Feature",
  "properties": {
    "iso:country":"GB",
    "wof:name":"WS3 4AR",
    "wof:placetype":"postalcode"
},
  "geometry": {"coordinates":[-1.97566724347754,52.63112400445019],"type":"Point"}
}