{
  "type": "Feature",
  "properties": {
    "iso:country":"GB",
    "wof:name":"CF48 4ER",
    "wof:placetype":"postalcode"
},
  "geometry": {"coordinates":[-3.34853036373535,51.70873463368192],"type":"Point"}
}