{
  "type": "Feature",
  "properties": {
    "date:inception_lower": "1980-01-01",
    "date:inception_upper": "1980-01-01",
    "iso:country": "GB",
    "wof:name": "CF48 4ER",
    "wof:placetype": "postalcode"
  },
  "geometry": {"coordinates":[-3.34853,51.708735],"type":"Point"}
}
