{
  "type": "Feature",
  "properties": {
    "iso:country":"GB",
    "wof:name":"BH24 3JW",
    "wof:placetype":"postalcode"
},
  "geometry": {"coordinates":[-1.75158174080723,50.85380938492562],"type":"Point"}
}