{
  "type": "Feature",
  "properties": {
    "date:inception_lower": "1980-01-01",
    "date:inception_upper": "1980-01-01",
    "iso:country": "GB",
    "wof:name": "BH24 3JW",
    "wof:placetype": "postalcode"
  },
  "geometry": {"coordinates":[-1.751582,50.853809],"type":"Point"}
}
