{
  "type": "Feature",
  "properties": {
    "iso:country":"GB",
    "wof:name":"AB43 6PZ",
    "wof:placetype":"postalcode"
},
  "geometry": {"coordinates":[-2.19682256789567,57.58965953200138],"type":"Point"}
}