{
  "type": "Feature",
  "properties": {
    "iso:country": "GB",
    "wof:name": "GL5 2JF",
    "wof:placetype": "postalcode"
  },
  "geometry": {"coordinates":[-2.208165,51.739983],"type":"Point"}
}
