{
  "type": "Feature",
  "properties": {
    "iso:country":"GB",
    "wof:name":"GL5 2JF",
    "wof:placetype":"postalcode"
},
  "geometry": {"coordinates":[-2.20816533148958,51.73998309709866],"type":"Point"}
}