{
  "type": "Feature",
  "properties": {
    "iso:country":"GB",
    "wof:name":"SW3 4JH",
    "wof:placetype":"postalcode"
},
  "geometry": {"coordinates":[-0.16085277516655,51.48486533247208],"type":"Point"}
}