{
  "type": "Feature",
  "properties": {
    "iso:country": "GB",
    "wof:name": "SP5 1LT",
    "wof:placetype": "postalcode"
  },
  "geometry": {"coordinates":[-1.619807,51.090933],"type":"Point"}
}
