{
  "type": "Feature",
  "properties": {
    "iso:country":"GB",
    "wof:name":"SP5 1LT",
    "wof:placetype":"postalcode"
},
  "geometry": {"coordinates":[-1.61980719372231,51.09093301585929],"type":"Point"}
}