{
  "type": "Feature",
  "properties": {
    "iso:country": "GB",
    "wof:name": "LS14 6QH",
    "wof:placetype": "postalcode"
  },
  "geometry": {"coordinates":[-1.472467,53.818784],"type":"Point"}
}
