{
  "type": "Feature",
  "properties": {
    "iso:country":"GB",
    "wof:name":"LS14 6QH",
    "wof:placetype":"postalcode"
},
  "geometry": {"coordinates":[-1.4724671658544,53.81878439885675],"type":"Point"}
}