{
  "type": "Feature",
  "properties": {
    "iso:country":"GB",
    "wof:name":"OL10 3AQ",
    "wof:placetype":"postalcode"
},
  "geometry": {"coordinates":[-2.22409502713321,53.5906712323857],"type":"Point"}
}