{
  "type": "Feature",
  "properties": {
    "iso:country": "GB",
    "wof:name": "NP13 3LT",
    "wof:placetype": "postalcode"
  },
  "geometry": {"coordinates":[-3.155022,51.770235],"type":"Point"}
}
