{
  "type": "Feature",
  "properties": {
    "date:inception_lower": "1980-01-01",
    "date:inception_upper": "1980-01-01",
    "iso:country": "GB",
    "wof:name": "G61 4BJ",
    "wof:placetype": "postalcode"
  },
  "geometry": {"coordinates":[-4.345658,55.920608],"type":"Point"}
}
