{
  "type": "Feature",
  "properties": {
    "date:inception_lower": "1980-01-01",
    "date:inception_upper": "1980-01-01",
    "iso:country": "GB",
    "wof:name": "NE30 3HW",
    "wof:placetype": "postalcode"
  },
  "geometry": {"coordinates":[-1.452379,55.031492],"type":"Point"}
}
