{
  "type": "Feature",
  "properties": {
    "iso:country":"GB",
    "wof:name":"NE30 3HW",
    "wof:placetype":"postalcode"
},
  "geometry": {"coordinates":[-1.4523790531388,55.03149172695074],"type":"Point"}
}