{
  "type": "Feature",
  "properties": {
    "iso:country":"GB",
    "wof:name":"SA31 1BY",
    "wof:placetype":"postalcode"
},
  "geometry": {"coordinates":[-4.30602225749435,51.85767513792679],"type":"Point"}
}