{
  "type": "Feature",
  "properties": {
    "iso:country": "GB",
    "wof:name": "SL9 9QS",
    "wof:placetype": "postalcode"
  },
  "geometry": {"coordinates":[-0.555852,51.610429],"type":"Point"}
}
