{
  "type": "Feature",
  "properties": {
    "iso:country":"GB",
    "wof:name":"SL9 9QS",
    "wof:placetype":"postalcode"
},
  "geometry": {"coordinates":[-0.55585240179257,51.61042927009402],"type":"Point"}
}