{
  "type": "Feature",
  "properties": {
    "date:inception_lower":"1980-01-01",
    "date:inception_upper":"1980-01-31",
    "iso:country":"GB",
    "wof:name":"SL9 9QS",
    "wof:placetype":"postalcode"
},
  "geometry": {"coordinates":[-0.555852,51.610429],"type":"Point"}
}