{
  "type": "Feature",
  "properties": {
    "date:inception_lower": "2021-10-01",
    "date:inception_upper": "2021-10-01",
    "iso:country": "GB",
    "wof:name": "PR4 0GU",
    "wof:placetype": "postalcode"
  },
  "geometry": {"coordinates":[-2.737864,53.795577],"type":"Point"}
}
