{
  "type": "Feature",
  "properties": {
    "date:inception_lower": "2006-01-01",
    "date:inception_upper": "2006-01-01",
    "iso:country": "GB",
    "wof:name": "PR5 4NW",
    "wof:placetype": "postalcode"
  },
  "geometry": {"coordinates":[-2.687733,53.735854],"type":"Point"}
}
