{
  "type": "Feature",
  "properties": {
    "date:inception_lower": "1980-01-01",
    "date:inception_upper": "1980-01-01",
    "iso:country": "GB",
    "wof:name": "DN21 2LG",
    "wof:placetype": "postalcode"
  },
  "geometry": {"coordinates":[-0.779703,53.40249],"type":"Point"}
}
