{
  "type": "Feature",
  "properties": {
    "iso:country": "GB",
    "wof:name": "DN21 2LG",
    "wof:placetype": "postalcode"
  },
  "geometry": {"coordinates":[-0.779703,53.40249],"type":"Point"}
}
