{
  "type": "Feature",
  "properties": {
    "iso:country":"GB",
    "wof:name":"AL10 0PH",
    "wof:placetype":"postalcode"
},
  "geometry": {"coordinates":[-0.23225310946101,51.76909322891402],"type":"Point"}
}