{
  "type": "Feature",
  "properties": {
    "date:inception_lower":"1980-01-01",
    "date:inception_upper":"1980-01-31",
    "iso:country":"GB",
    "wof:name":"AL10 0PH",
    "wof:placetype":"postalcode"
},
  "geometry": {"coordinates":[-0.232253,51.769093],"type":"Point"}
}