{
  "type": "Feature",
  "properties": {
    "iso:country":"GB",
    "wof:name":"WN5 7AD",
    "wof:placetype":"postalcode"
},
  "geometry": {"coordinates":[-2.71605548586998,53.52714808810309],"type":"Point"}
}