{
  "type": "Feature",
  "properties": {
    "date:inception_lower":"1992-01-01",
    "date:inception_upper":"1992-01-31",
    "iso:country":"GB",
    "wof:name":"DY5 4PT",
    "wof:placetype":"postalcode"
},
  "geometry": {"coordinates":[-2.14141,52.500137],"type":"Point"}
}