{
  "type": "Feature",
  "properties": {
    "iso:country":"GB",
    "wof:name":"SG12 0HB",
    "wof:placetype":"postalcode"
},
  "geometry": {"coordinates":[-0.07635892295231,51.81891689706771],"type":"Point"}
}