{
  "type": "Feature",
  "properties": {
    "date:inception_lower": "1980-01-01",
    "date:inception_upper": "1980-01-01",
    "iso:country": "GB",
    "wof:name": "SG12 0HB",
    "wof:placetype": "postalcode"
  },
  "geometry": {"coordinates":[-0.076359,51.818917],"type":"Point"}
}
