{
  "type": "Feature",
  "properties": {
    "iso:country":"GB",
    "wof:name":"CT21 4NY",
    "wof:placetype":"postalcode"
},
  "geometry": {"coordinates":[1.02879745934343,51.07470030396551],"type":"Point"}
}