{
  "type": "Feature",
  "properties": {
    "iso:country":"GB",
    "wof:name":"BS10 7LG",
    "wof:placetype":"postalcode"
},
  "geometry": {"coordinates":[-2.62237639791402,51.51194456150761],"type":"Point"}
}