{
  "type": "Feature",
  "properties": {
    "iso:country":"GB",
    "wof:name":"TR5 0XP",
    "wof:placetype":"postalcode"
},
  "geometry": {"coordinates":[-5.18982074589814,50.32273273889795],"type":"Point"}
}