{
  "type": "Feature",
  "properties": {
    "iso:country":"GB",
    "wof:name":"S43 3PB",
    "wof:placetype":"postalcode"
},
  "geometry": {"coordinates":[-1.35142534055209,53.2664675626888],"type":"Point"}
}