{
  "type": "Feature",
  "properties": {
    "iso:country": "GB",
    "wof:name": "S43 3PB",
    "wof:placetype": "postalcode"
  },
  "geometry": {"coordinates":[-1.351299,53.266766],"type":"Point"}
}
