{
  "type": "Feature",
  "properties": {
    "iso:country":"GB",
    "wof:name":"WD6 5PD",
    "wof:placetype":"postalcode"
},
  "geometry": {"coordinates":[-0.25468251314339,51.66660381672533],"type":"Point"}
}