{
  "type": "Feature",
  "properties": {
    "iso:country":"GB",
    "wof:name":"LS28 9BJ",
    "wof:placetype":"postalcode"
},
  "geometry": {"coordinates":[-1.65402729147837,53.7965256527679],"type":"Point"}
}