{
  "type": "Feature",
  "properties": {
    "iso:country": "GB",
    "wof:name": "TS22 5LU",
    "wof:placetype": "postalcode"
  },
  "geometry": {"coordinates":[-1.313537,54.617118],"type":"Point"}
}
