{
  "type": "Feature",
  "properties": {
    "iso:country":"GB",
    "wof:name":"BA1 6SL",
    "wof:placetype":"postalcode"
},
  "geometry": {"coordinates":[-2.34448839626101,51.39858274707932],"type":"Point"}
}