{
  "type": "Feature",
  "properties": {
    "iso:country": "GB",
    "wof:name": "ST13 7QJ",
    "wof:placetype": "postalcode"
  },
  "geometry": {"coordinates":[-1.93742,53.07114],"type":"Point"}
}
