{
  "type": "Feature",
  "properties": {
    "date:inception_lower": "1980-01-01",
    "date:inception_upper": "1980-01-01",
    "iso:country": "GB",
    "wof:name": "ST13 7QJ",
    "wof:placetype": "postalcode"
  },
  "geometry": {"coordinates":[-1.93742,53.07114],"type":"Point"}
}
