{
  "type": "Feature",
  "properties": {
    "iso:country":"GB",
    "wof:name":"ST13 7QJ",
    "wof:placetype":"postalcode"
},
  "geometry": {"coordinates":[-1.93957214281121,53.07171723963395],"type":"Point"}
}