{
  "type": "Feature",
  "properties": {
    "iso:country":"GB",
    "wof:name":"YO13 0BH",
    "wof:placetype":"postalcode"
},
  "geometry": {"coordinates":[-0.46997271597213,54.30044190679952],"type":"Point"}
}