{
  "type": "Feature",
  "properties": {
    "iso:country": "GB",
    "wof:name": "EN6 1RG",
    "wof:placetype": "postalcode"
  },
  "geometry": {"coordinates":[-0.176515,51.701727],"type":"Point"}
}
