{
  "type": "Feature",
  "properties": {
    "date:inception_lower": "1980-01-01",
    "date:inception_upper": "1980-01-01",
    "iso:country": "GB",
    "wof:name": "B67 5HL",
    "wof:placetype": "postalcode"
  },
  "geometry": {"coordinates":[-1.975296,52.475483],"type":"Point"}
}
