{
  "type": "Feature",
  "properties": {
    "iso:country": "GB",
    "wof:name": "NR32 5BW",
    "wof:placetype": "postalcode"
  },
  "geometry": {"coordinates":[1.716259,52.511319],"type":"Point"}
}
