{
  "type": "Feature",
  "properties": {
    "date:inception_lower": "1980-01-01",
    "date:inception_upper": "1980-01-01",
    "iso:country": "GB",
    "wof:name": "HP20 1BJ",
    "wof:placetype": "postalcode"
  },
  "geometry": {"coordinates":[-0.806271,51.819554],"type":"Point"}
}
