{
  "type": "Feature",
  "properties": {
    "iso:country": "GB",
    "wof:name": "HP20 1BJ",
    "wof:placetype": "postalcode"
  },
  "geometry": {"coordinates":[-0.806271,51.819554],"type":"Point"}
}
