{
  "type": "Feature",
  "properties": {
    "iso:country":"GB",
    "wof:name":"HG3 1AZ",
    "wof:placetype":"postalcode"
},
  "geometry": {"coordinates":[-1.45900674676292,53.96043730979678],"type":"Point"}
}