{
  "type": "Feature",
  "properties": {
    "iso:country": "GB",
    "wof:name": "HG3 1AZ",
    "wof:placetype": "postalcode"
  },
  "geometry": {"coordinates":[-1.459007,53.960437],"type":"Point"}
}
