{
  "type": "Feature",
  "properties": {
    "iso:country":"GB",
    "wof:name":"CR0 3RF",
    "wof:placetype":"postalcode"
},
  "geometry": {"coordinates":[-0.10959442810873,51.37676778906427],"type":"Point"}
}