{
  "type": "Feature",
  "properties": {
    "date:inception_lower": "1987-04-01",
    "date:inception_upper": "1987-04-01",
    "iso:country": "GB",
    "wof:name": "CR0 3RF",
    "wof:placetype": "postalcode"
  },
  "geometry": {"coordinates":[-0.10858,51.376698],"type":"Point"}
}
