{
  "type": "Feature",
  "properties": {
    "iso:country":"GB",
    "wof:name":"BS16 7FQ",
    "wof:placetype":"postalcode"
},
  "geometry": {"coordinates":[-2.48185172038768,51.50534111174905],"type":"Point"}
}