{
  "type": "Feature",
  "properties": {
    "iso:country": "GB",
    "wof:name": "BS16 7FQ",
    "wof:placetype": "postalcode"
  },
  "geometry": {"coordinates":[-2.481852,51.505341],"type":"Point"}
}
