{
  "type": "Feature",
  "properties": {
    "date:inception_lower": "2000-12-01",
    "date:inception_upper": "2000-12-01",
    "iso:country": "GB",
    "wof:name": "BS16 7FQ",
    "wof:placetype": "postalcode"
  },
  "geometry": {"coordinates":[-2.481852,51.505341],"type":"Point"}
}
