{
  "type": "Feature",
  "properties": {
    "date:inception_lower":"1999-12-01",
    "date:inception_upper":"1999-12-31",
    "iso:country":"GB",
    "wof:name":"TA10 9NS",
    "wof:placetype":"postalcode"
},
  "geometry": {"coordinates":[-2.768138,51.031672],"type":"Point"}
}