{
  "type": "Feature",
  "properties": {
    "iso:country": "GB",
    "wof:name": "TA10 9NS",
    "wof:placetype": "postalcode"
  },
  "geometry": {"coordinates":[-2.768138,51.031672],"type":"Point"}
}
