{
  "type": "Feature",
  "properties": {
    "iso:country":"GB",
    "wof:name":"TA10 9NS",
    "wof:placetype":"postalcode"
},
  "geometry": {"coordinates":[-2.76813757335383,51.03167227488277],"type":"Point"}
}