{
  "type": "Feature",
  "properties": {
    "iso:country":"GB",
    "wof:name":"LS16 9AN",
    "wof:placetype":"postalcode"
},
  "geometry": {"coordinates":[-1.61012054479483,53.8819024630071],"type":"Point"}
}