{
  "type": "Feature",
  "properties": {
    "iso:country": "GB",
    "wof:name": "LS16 9AN",
    "wof:placetype": "postalcode"
  },
  "geometry": {"coordinates":[-1.61012,53.881902],"type":"Point"}
}
