{
  "type": "Feature",
  "properties": {
    "date:inception_lower": "1980-01-01",
    "date:inception_upper": "1980-01-01",
    "iso:country": "GB",
    "wof:name": "LS16 9AN",
    "wof:placetype": "postalcode"
  },
  "geometry": {"coordinates":[-1.61012,53.881902],"type":"Point"}
}
