{
  "type": "Feature",
  "properties": {
    "iso:country":"GB",
    "wof:name":"LS25 1DS",
    "wof:placetype":"postalcode"
},
  "geometry": {"coordinates":[-1.38858765495374,53.7928871522447],"type":"Point"}
}