{
  "type": "Feature",
  "properties": {
    "date:inception_lower": "2006-08-01",
    "date:inception_upper": "2006-08-01",
    "iso:country": "GB",
    "wof:name": "KY8 4GZ",
    "wof:placetype": "postalcode"
  },
  "geometry": {"coordinates":[-2.992131,56.1995],"type":"Point"}
}
