{
  "type": "Feature",
  "properties": {
    "iso:country":"GB",
    "wof:name":"KY8 4GZ",
    "wof:placetype":"postalcode"
},
  "geometry": {"coordinates":[-2.99213083625925,56.19949985525682],"type":"Point"}
}