{
  "type": "Feature",
  "properties": {
    "iso:country": "GB",
    "wof:name": "KY8 4GZ",
    "wof:placetype": "postalcode"
  },
  "geometry": {"coordinates":[-2.992131,56.1995],"type":"Point"}
}
