{
  "type": "Feature",
  "properties": {
    "iso:country":"GB",
    "wof:name":"M23 0GH",
    "wof:placetype":"postalcode"
},
  "geometry": {"coordinates":[-2.29387143373627,53.40266155678808],"type":"Point"}
}