{
  "type": "Feature",
  "properties": {
    "iso:country": "GB",
    "wof:name": "M23 0GH",
    "wof:placetype": "postalcode"
  },
  "geometry": {"coordinates":[-2.293871,53.402662],"type":"Point"}
}
