{
  "type": "Feature",
  "properties": {
    "date:inception_lower":"1997-12-01",
    "date:inception_upper":"1997-12-31",
    "iso:country":"GB",
    "wof:name":"DN9 1GA",
    "wof:placetype":"postalcode"
},
  "geometry": {"coordinates":[-0.821866,53.52431],"type":"Point"}
}