{
  "type": "Feature",
  "properties": {
    "iso:country":"GB",
    "wof:name":"DN9 1GA",
    "wof:placetype":"postalcode"
},
  "geometry": {"coordinates":[-0.82186650433677,53.52431001859815],"type":"Point"}
}