{
  "type": "Feature",
  "properties": {
    "iso:country": "GB",
    "wof:name": "DN9 1GA",
    "wof:placetype": "postalcode"
  },
  "geometry": {"coordinates":[-0.821866,53.52431],"type":"Point"}
}
