{
  "type": "Feature",
  "properties": {
    "iso:country":"GB",
    "wof:name":"GU1 3NR",
    "wof:placetype":"postalcode"
},
  "geometry": {"coordinates":[-0.56072384566873,51.23711457297486],"type":"Point"}
}