{
  "type": "Feature",
  "properties": {
    "date:inception_lower": "1984-02-01",
    "date:inception_upper": "1984-02-01",
    "iso:country": "GB",
    "wof:name": "GU1 3NR",
    "wof:placetype": "postalcode"
  },
  "geometry": {"coordinates":[-0.560724,51.237115],"type":"Point"}
}
