{
  "type": "Feature",
  "properties": {
    "iso:country":"GB",
    "wof:name":"NN4 8EL",
    "wof:placetype":"postalcode"
},
  "geometry": {"coordinates":[-0.89825751264216,52.22939199520744],"type":"Point"}
}