{
  "type": "Feature",
  "properties": {
    "date:inception_lower": "2007-07-01",
    "date:inception_upper": "2007-07-01",
    "iso:country": "GB",
    "wof:name": "NN4 8EL",
    "wof:placetype": "postalcode"
  },
  "geometry": {"coordinates":[-0.898257,52.229392],"type":"Point"}
}
