{
  "type": "Feature",
  "properties": {
    "iso:country":"GB",
    "wof:name":"HX3 0JD",
    "wof:placetype":"postalcode"
},
  "geometry": {"coordinates":[-1.87365748664149,53.70453370211573],"type":"Point"}
}