{
  "type": "Feature",
  "properties": {
    "date:inception_lower":"1980-01-01",
    "date:inception_upper":"1980-01-31",
    "iso:country":"GB",
    "wof:name":"PE15 0JA",
    "wof:placetype":"postalcode"
},
  "geometry": {"coordinates":[0.176711,52.482713],"type":"Point"}
}