{
  "type": "Feature",
  "properties": {
    "iso:country":"GB",
    "wof:name":"B23 6PS",
    "wof:placetype":"postalcode"
},
  "geometry": {"coordinates":[-1.85169108940917,52.52627564920272],"type":"Point"}
}