{
  "type": "Feature",
  "properties": {
    "iso:country":"GB",
    "wof:name":"EX9 6BX",
    "wof:placetype":"postalcode"
},
  "geometry": {"coordinates":[-3.33345544469289,50.62853045265289],"type":"Point"}
}