{
  "type": "Feature",
  "properties": {
    "iso:country": "GB",
    "wof:name": "SA14 6BZ",
    "wof:placetype": "postalcode"
  },
  "geometry": {"coordinates":[-4.113839,51.782262],"type":"Point"}
}
