{
  "type": "Feature",
  "properties": {
    "iso:country":"GB",
    "wof:name":"SA14 6BZ",
    "wof:placetype":"postalcode"
},
  "geometry": {"coordinates":[-4.11383890347823,51.78226189320596],"type":"Point"}
}