{
  "type": "Feature",
  "properties": {
    "iso:country":"GB",
    "wof:name":"CW1 3GU",
    "wof:placetype":"postalcode"
},
  "geometry": {"coordinates":[-2.4577920792874,53.1015487293224],"type":"Point"}
}