{
  "type": "Feature",
  "properties": {
    "date:inception_lower":"2009-03-01",
    "date:inception_upper":"2009-03-31",
    "iso:country":"GB",
    "wof:name":"CW1 3GU",
    "wof:placetype":"postalcode"
},
  "geometry": {"coordinates":[-2.457792,53.101549],"type":"Point"}
}