{
  "type": "Feature",
  "properties": {
    "date:inception_lower": "2022-08-01",
    "date:inception_upper": "2022-08-01",
    "iso:country": "GB",
    "wof:name": "RH10 2AY",
    "wof:placetype": "postalcode"
  },
  "geometry": {"coordinates":[-0.133337,51.139248],"type":"Point"}
}
