{
  "type": "Feature",
  "properties": {
    "date:inception_lower": "1980-01-01",
    "date:inception_upper": "1980-01-01",
    "iso:country": "GB",
    "wof:name": "GL52 6QG",
    "wof:placetype": "postalcode"
  },
  "geometry": {"coordinates":[-2.052188,51.900645],"type":"Point"}
}
