{
  "type": "Feature",
  "properties": {
    "iso:country":"GB",
    "wof:name":"SS9 1HA",
    "wof:placetype":"postalcode"
},
  "geometry": {"coordinates":[0.66862150385301,51.54126251242814],"type":"Point"}
}