{
  "type": "Feature",
  "properties": {
    "iso:country":"GB",
    "wof:name":"NP7 0ET",
    "wof:placetype":"postalcode"
},
  "geometry": {"coordinates":[-3.10703759353234,51.82150297394976],"type":"Point"}
}