{
  "type": "Feature",
  "properties": {
    "iso:country":"GB",
    "wof:name":"SY12 9JQ",
    "wof:placetype":"postalcode"
},
  "geometry": {"coordinates":[-2.93978556591785,52.92670447191831],"type":"Point"}
}