{
  "type": "Feature",
  "properties": {
    "iso:country":"GB",
    "wof:name":"NR20 5BB",
    "wof:placetype":"postalcode"
},
  "geometry": {"coordinates":[0.98143825793858,52.81095625157756],"type":"Point"}
}