{
  "type": "Feature",
  "properties": {
    "date:inception_lower":"2013-12-01",
    "date:inception_upper":"2013-12-31",
    "iso:country":"GB",
    "wof:name":"WA8 5EA",
    "wof:placetype":"postalcode"
},
  "geometry": {"coordinates":[-2.729299,53.390924],"type":"Point"}
}