{
  "type": "Feature",
  "properties": {
    "iso:country": "GB",
    "wof:name": "WA8 5EA",
    "wof:placetype": "postalcode"
  },
  "geometry": {"coordinates":[-2.729299,53.390924],"type":"Point"}
}
