{
  "type": "Feature",
  "properties": {
    "date:inception_lower": "2015-09-01",
    "date:inception_upper": "2015-09-01",
    "iso:country": "GB",
    "wof:name": "RG1 4FG",
    "wof:placetype": "postalcode"
  },
  "geometry": {"coordinates":[-0.966271,51.452117],"type":"Point"}
}
