{
  "type": "Feature",
  "properties": {
    "iso:country":"GB",
    "wof:name":"RG1 4FG",
    "wof:placetype":"postalcode"
},
  "geometry": {"coordinates":[-0.96627072240551,51.45211728074106],"type":"Point"}
}