{
  "type": "Feature",
  "properties": {
    "iso:country": "GB",
    "wof:name": "RG1 4FG",
    "wof:placetype": "postalcode"
  },
  "geometry": {"coordinates":[-0.966271,51.452117],"type":"Point"}
}
