{
  "type": "Feature",
  "properties": {
    "iso:country":"GB",
    "wof:name":"G5 0QA",
    "wof:placetype":"postalcode"
},
  "geometry": {"coordinates":[-4.2420179985328,55.84955195633331],"type":"Point"}
}