{
  "type": "Feature",
  "properties": {
    "iso:country": "GB",
    "wof:name": "LS12 4RR",
    "wof:placetype": "postalcode"
  },
  "geometry": {"coordinates":[-1.589044,53.786335],"type":"Point"}
}
