{
  "type": "Feature",
  "properties": {
    "iso:country":"GB",
    "wof:name":"CV11 5NS",
    "wof:placetype":"postalcode"
},
  "geometry": {"coordinates":[-1.47247560078551,52.51962009991578],"type":"Point"}
}