{
  "type": "Feature",
  "properties": {
    "date:inception_lower": "1980-01-01",
    "date:inception_upper": "1980-01-01",
    "iso:country": "GB",
    "wof:name": "BD20 6JD",
    "wof:placetype": "postalcode"
  },
  "geometry": {"coordinates":[-1.916921,53.873581],"type":"Point"}
}
