{
  "type": "Feature",
  "properties": {
    "iso:country":"GB",
    "wof:name":"BD20 6JD",
    "wof:placetype":"postalcode"
},
  "geometry": {"coordinates":[-1.91692153058199,53.87358123123405],"type":"Point"}
}