{
  "type": "Feature",
  "properties": {
    "iso:country":"GB",
    "wof:name":"KY15 5DW",
    "wof:placetype":"postalcode"
},
  "geometry": {"coordinates":[-3.02101206220128,56.31582513495029],"type":"Point"}
}