{
  "type": "Feature",
  "properties": {
    "iso:country":"GB",
    "wof:name":"NG21 9NP",
    "wof:placetype":"postalcode"
},
  "geometry": {"coordinates":[-1.07568127702096,53.19355431048182],"type":"Point"}
}