{
  "type": "Feature",
  "properties": {
    "date:inception_lower": "1980-01-01",
    "date:inception_upper": "1980-01-01",
    "iso:country": "GB",
    "wof:name": "NG21 9NP",
    "wof:placetype": "postalcode"
  },
  "geometry": {"coordinates":[-1.07541,53.193572],"type":"Point"}
}
