{
  "type": "Feature",
  "properties": {
    "date:inception_lower":"1983-07-01",
    "date:inception_upper":"1983-07-31",
    "iso:country":"GB",
    "wof:name":"BB1 3AR",
    "wof:placetype":"postalcode"
},
  "geometry": {"coordinates":[-2.468742,53.749854],"type":"Point"}
}