{
  "type": "Feature",
  "properties": {
    "iso:country":"GB",
    "wof:name":"BB1 3AR",
    "wof:placetype":"postalcode"
},
  "geometry": {"coordinates":[-2.46874200066763,53.74985419149701],"type":"Point"}
}