{
  "type": "Feature",
  "properties": {
    "iso:country": "GB",
    "wof:name": "KT7 0YA",
    "wof:placetype": "postalcode"
  },
  "geometry": {"coordinates":[-0.325463,51.389674],"type":"Point"}
}
