{
  "type": "Feature",
  "properties": {
    "iso:country":"GB",
    "wof:name":"KT7 0YA",
    "wof:placetype":"postalcode"
},
  "geometry": {"coordinates":[-0.32546267898961,51.38967384608834],"type":"Point"}
}