{
  "type": "Feature",
  "properties": {
    "date:inception_lower": "1980-01-01",
    "date:inception_upper": "1980-01-01",
    "iso:country": "GB",
    "wof:name": "KT7 0YA",
    "wof:placetype": "postalcode"
  },
  "geometry": {"coordinates":[-0.325463,51.389674],"type":"Point"}
}
