{
  "type": "Feature",
  "properties": {
    "iso:country":"GB",
    "wof:name":"DE21 6XQ",
    "wof:placetype":"postalcode"
},
  "geometry": {"coordinates":[-1.45742177098613,52.92479852780153],"type":"Point"}
}