{
  "type": "Feature",
  "properties": {
    "date:inception_lower":"2011-02-01",
    "date:inception_upper":"2011-02-28",
    "iso:country":"GB",
    "wof:name":"DE21 6XQ",
    "wof:placetype":"postalcode"
},
  "geometry": {"coordinates":[-1.457422,52.924799],"type":"Point"}
}