{
  "type": "Feature",
  "properties": {
    "iso:country":"GB",
    "wof:name":"W13 9EG",
    "wof:placetype":"postalcode"
},
  "geometry": {"coordinates":[-0.32425768032165,51.50793362589363],"type":"Point"}
}