{
  "type": "Feature",
  "properties": {
    "date:inception_lower": "1980-01-01",
    "date:inception_upper": "1980-01-01",
    "iso:country": "GB",
    "wof:name": "W13 9EG",
    "wof:placetype": "postalcode"
  },
  "geometry": {"coordinates":[-0.324258,51.507934],"type":"Point"}
}
