{
  "type": "Feature",
  "properties": {
    "date:inception_lower": "1994-05-01",
    "date:inception_upper": "1994-05-01",
    "iso:country": "GB",
    "wof:name": "M25 1FP",
    "wof:placetype": "postalcode"
  },
  "geometry": {"coordinates":[-2.272291,53.530473],"type":"Point"}
}
