{
  "type": "Feature",
  "properties": {
    "date:inception_lower": "1980-01-01",
    "date:inception_upper": "1980-01-01",
    "iso:country": "GB",
    "wof:name": "RM3 0BS",
    "wof:placetype": "postalcode"
  },
  "geometry": {"coordinates":[0.234571,51.59398],"type":"Point"}
}
