{
  "type": "Feature",
  "properties": {
    "iso:country":"GB",
    "wof:name":"RM3 0BS",
    "wof:placetype":"postalcode"
},
  "geometry": {"coordinates":[0.23441068724191,51.59388213666447],"type":"Point"}
}