{
  "type": "Feature",
  "properties": {
    "iso:country": "GB",
    "wof:name": "RM3 0BS",
    "wof:placetype": "postalcode"
  },
  "geometry": {"coordinates":[0.234524,51.593909],"type":"Point"}
}
