{
  "type": "Feature",
  "properties": {
    "iso:country":"GB",
    "wof:name":"NE33 4NA",
    "wof:placetype":"postalcode"
},
  "geometry": {"coordinates":[-1.42846856393811,54.99226454028886],"type":"Point"}
}