{
  "type": "Feature",
  "properties": {
    "iso:country":"GB",
    "wof:name":"BB1 9DP",
    "wof:placetype":"postalcode"
},
  "geometry": {"coordinates":[-2.51381481531653,53.78741042727983],"type":"Point"}
}