{
  "type": "Feature",
  "properties": {
    "date:inception_lower": "1980-01-01",
    "date:inception_upper": "1980-01-01",
    "iso:country": "GB",
    "wof:name": "BB1 9DP",
    "wof:placetype": "postalcode"
  },
  "geometry": {"coordinates":[-2.513736,53.787299],"type":"Point"}
}
