{
  "type": "Feature",
  "properties": {
    "iso:country":"GB",
    "wof:name":"BS6 7NH",
    "wof:placetype":"postalcode"
},
  "geometry": {"coordinates":[-2.61150137936402,51.47893072817857],"type":"Point"}
}