{
  "type": "Feature",
  "properties": {
    "iso:country":"GB",
    "wof:name":"S36 9RA",
    "wof:placetype":"postalcode"
},
  "geometry": {"coordinates":[-1.64954856373095,53.52636298674885],"type":"Point"}
}