{
  "type": "Feature",
  "properties": {
    "iso:country": "GB",
    "wof:name": "S36 9RA",
    "wof:placetype": "postalcode"
  },
  "geometry": {"coordinates":[-1.649488,53.52639],"type":"Point"}
}
