{
  "type": "Feature",
  "properties": {
    "iso:country":"GB",
    "wof:name":"NG19 7AT",
    "wof:placetype":"postalcode"
},
  "geometry": {"coordinates":[-1.20828569821239,53.15269145677404],"type":"Point"}
}