{
  "type": "Feature",
  "properties": {
    "iso:country":"GB",
    "wof:name":"EH4 1QA",
    "wof:placetype":"postalcode"
},
  "geometry": {"coordinates":[-3.21333083223817,55.95570494898732],"type":"Point"}
}