{
  "type": "Feature",
  "properties": {
    "iso:country":"GB",
    "wof:name":"DE6 1QB",
    "wof:placetype":"postalcode"
},
  "geometry": {"coordinates":[-1.71823061320456,53.0879753508064],"type":"Point"}
}