{
  "type": "Feature",
  "properties": {
    "date:inception_lower":"1980-01-01",
    "date:inception_upper":"1980-01-31",
    "iso:country":"GB",
    "wof:name":"DE6 1QB",
    "wof:placetype":"postalcode"
},
  "geometry": {"coordinates":[-1.718231,53.087975],"type":"Point"}
}