{
  "type": "Feature",
  "properties": {
    "iso:country":"GB",
    "wof:name":"SG18 8JL",
    "wof:placetype":"postalcode"
},
  "geometry": {"coordinates":[-0.25355548245618,52.08276703313307],"type":"Point"}
}