{
  "type": "Feature",
  "properties": {
    "iso:country": "GB",
    "wof:name": "LA6 2LF",
    "wof:placetype": "postalcode"
  },
  "geometry": {"coordinates":[-2.563694,54.223318],"type":"Point"}
}
