{
  "type": "Feature",
  "properties": {
    "iso:country":"GB",
    "wof:name":"LA6 2LF",
    "wof:placetype":"postalcode"
},
  "geometry": {"coordinates":[-2.5636939824617,54.22331810766843],"type":"Point"}
}