{
  "type": "Feature",
  "properties": {
    "iso:country": "GB",
    "wof:name": "NR34 8AF",
    "wof:placetype": "postalcode"
  },
  "geometry": {"coordinates":[1.566513,52.353348],"type":"Point"}
}
