{
  "type": "Feature",
  "properties": {
    "date:inception_lower": "1980-01-01",
    "date:inception_upper": "1980-01-01",
    "iso:country": "GB",
    "wof:name": "NR34 8AF",
    "wof:placetype": "postalcode"
  },
  "geometry": {"coordinates":[1.564087,52.352977],"type":"Point"}
}
