{
  "type": "Feature",
  "properties": {
    "iso:country": "GB",
    "wof:name": "LN5 9PG",
    "wof:placetype": "postalcode"
  },
  "geometry": {"coordinates":[-0.55853,53.184519],"type":"Point"}
}
