{
  "type": "Feature",
  "properties": {
    "date:inception_lower":"1993-08-01",
    "date:inception_upper":"1993-08-31",
    "iso:country":"GB",
    "wof:name":"CW8 4XG",
    "wof:placetype":"postalcode"
},
  "geometry": {"coordinates":[-2.522105,53.26411],"type":"Point"}
}