{
  "type": "Feature",
  "properties": {
    "iso:country":"GB",
    "wof:name":"CW8 4XG",
    "wof:placetype":"postalcode"
},
  "geometry": {"coordinates":[-2.52210473225949,53.26411047979673],"type":"Point"}
}