{
  "type": "Feature",
  "properties": {
    "iso:country":"GB",
    "wof:name":"YO16 6GB",
    "wof:placetype":"postalcode"
},
  "geometry": {"coordinates":[-0.18891191448303,54.10222991909148],"type":"Point"}
}