{
  "type": "Feature",
  "properties": {
    "date:inception_lower": "2000-12-01",
    "date:inception_upper": "2000-12-01",
    "iso:country": "GB",
    "wof:name": "YO16 6GB",
    "wof:placetype": "postalcode"
  },
  "geometry": {"coordinates":[-0.188912,54.10223],"type":"Point"}
}
