{
  "type": "Feature",
  "properties": {
    "iso:country":"GB",
    "wof:name":"WV16 6TL",
    "wof:placetype":"postalcode"
},
  "geometry": {"coordinates":[-2.57717210239613,52.49793572381514],"type":"Point"}
}