{
  "type": "Feature",
  "properties": {
    "date:inception_lower": "1992-01-01",
    "date:inception_upper": "1992-01-01",
    "iso:country": "GB",
    "wof:name": "WV16 6TL",
    "wof:placetype": "postalcode"
  },
  "geometry": {"coordinates":[-2.577172,52.497936],"type":"Point"}
}
