{
  "type": "Feature",
  "properties": {
    "iso:country":"GB",
    "wof:name":"SL1 2TF",
    "wof:placetype":"postalcode"
},
  "geometry": {"coordinates":[-0.6181115440234,51.506206392519],"type":"Point"}
}