{
  "type": "Feature",
  "properties": {
    "iso:country": "GB",
    "wof:name": "SL1 2TF",
    "wof:placetype": "postalcode"
  },
  "geometry": {"coordinates":[-0.618112,51.506206],"type":"Point"}
}
