{
  "type": "Feature",
  "properties": {
    "iso:country":"GB",
    "wof:name":"BS34 8RY",
    "wof:placetype":"postalcode"
},
  "geometry": {"coordinates":[-2.53024430772385,51.51494199869534],"type":"Point"}
}