{
  "type": "Feature",
  "properties": {
    "iso:country": "GB",
    "wof:name": "M34 3QF",
    "wof:placetype": "postalcode"
  },
  "geometry": {"coordinates":[-2.127763,53.458181],"type":"Point"}
}
