{
  "type": "Feature",
  "properties": {
    "date:inception_lower":"1980-01-01",
    "date:inception_upper":"1980-01-31",
    "iso:country":"GB",
    "wof:name":"W13 0DG",
    "wof:placetype":"postalcode"
},
  "geometry": {"coordinates":[-0.32658,51.522022],"type":"Point"}
}