{
  "type": "Feature",
  "properties": {
    "iso:country":"GB",
    "wof:name":"W13 0DG",
    "wof:placetype":"postalcode"
},
  "geometry": {"coordinates":[-0.32658025977933,51.52202175268393],"type":"Point"}
}