{
  "type": "Feature",
  "properties": {
    "date:inception_lower":"2002-07-01",
    "date:inception_upper":"2002-07-31",
    "iso:country":"GB",
    "wof:name":"NE1 1UD",
    "wof:placetype":"postalcode"
},
  "geometry": {"coordinates":[-1.614557,54.970539],"type":"Point"}
}