{
  "type": "Feature",
  "properties": {
    "iso:country":"GB",
    "wof:name":"NE1 1UD",
    "wof:placetype":"postalcode"
},
  "geometry": {"coordinates":[-1.61455709290521,54.97053937329365],"type":"Point"}
}