{
  "type": "Feature",
  "properties": {
    "date:inception_lower":"1982-03-01",
    "date:inception_upper":"1982-03-31",
    "iso:country":"GB",
    "wof:name":"CA14 1JQ",
    "wof:placetype":"postalcode"
},
  "geometry": {"coordinates":[-3.528274,54.661459],"type":"Point"}
}