{
  "type": "Feature",
  "properties": {
    "iso:country":"GB",
    "wof:name":"CA14 1JQ",
    "wof:placetype":"postalcode"
},
  "geometry": {"coordinates":[-3.52827424319672,54.66145914429192],"type":"Point"}
}