{
  "type": "Feature",
  "properties": {
    "iso:country":"GB",
    "wof:name":"CT1 2PP",
    "wof:placetype":"postalcode"
},
  "geometry": {"coordinates":[1.07415312234657,51.27671535818233],"type":"Point"}
}