{
  "type": "Feature",
  "properties": {
    "iso:country":"GB",
    "wof:name":"MK4 3BB",
    "wof:placetype":"postalcode"
},
  "geometry": {"coordinates":[-0.77941284905083,51.99397093912272],"type":"Point"}
}