{
  "type": "Feature",
  "properties": {
    "iso:country": "GB",
    "wof:name": "MK4 3BB",
    "wof:placetype": "postalcode"
  },
  "geometry": {"coordinates":[-0.779413,51.993971],"type":"Point"}
}
