{
  "type": "Feature",
  "properties": {
    "date:inception_lower": "1997-06-01",
    "date:inception_upper": "1997-06-01",
    "iso:country": "GB",
    "wof:name": "MK4 3BB",
    "wof:placetype": "postalcode"
  },
  "geometry": {"coordinates":[-0.779413,51.993971],"type":"Point"}
}
