{
  "type": "Feature",
  "properties": {
    "iso:country":"GB",
    "wof:name":"CM3 3BD",
    "wof:placetype":"postalcode"
},
  "geometry": {"coordinates":[0.52885787537017,51.78696082354018],"type":"Point"}
}