{
  "type": "Feature",
  "properties": {
    "iso:country":"GB",
    "wof:name":"SO23 7HN",
    "wof:placetype":"postalcode"
},
  "geometry": {"coordinates":[-1.30980935886512,51.07587345886334],"type":"Point"}
}