{
  "type": "Feature",
  "properties": {
    "iso:country":"GB",
    "wof:name":"BR1 4LP",
    "wof:placetype":"postalcode"
},
  "geometry": {"coordinates":[-0.0085662950521,51.4237181915913],"type":"Point"}
}