{
  "type": "Feature",
  "properties": {
    "iso:country":"GB",
    "wof:name":"SE2 0PN",
    "wof:placetype":"postalcode"
},
  "geometry": {"coordinates":[0.12672808955036,51.48278962573738],"type":"Point"}
}