{
  "type": "Feature",
  "properties": {
    "iso:country":"GB",
    "wof:name":"NW2 3NN",
    "wof:placetype":"postalcode"
},
  "geometry": {"coordinates":[-0.20624240696307,51.55075452576817],"type":"Point"}
}