{
  "type": "Feature",
  "properties": {
    "date:inception_lower": "2016-11-01",
    "date:inception_upper": "2016-11-01",
    "iso:country": "GB",
    "wof:name": "SK17 7BR",
    "wof:placetype": "postalcode"
  },
  "geometry": {"coordinates":[-1.910723,53.265965],"type":"Point"}
}
