{
  "type": "Feature",
  "properties": {
    "iso:country": "GB",
    "wof:name": "WS13 8DY",
    "wof:placetype": "postalcode"
  },
  "geometry": {"coordinates":[-1.859579,52.696803],"type":"Point"}
}
