{
  "type": "Feature",
  "properties": {
    "iso:country":"GB",
    "wof:name":"WS13 8DY",
    "wof:placetype":"postalcode"
},
  "geometry": {"coordinates":[-1.85957870782519,52.69680309053076],"type":"Point"}
}