{
  "type": "Feature",
  "properties": {
    "iso:country": "GB",
    "wof:name": "OX13 6GR",
    "wof:placetype": "postalcode"
  },
  "geometry": {"coordinates":[-1.298713,51.61337],"type":"Point"}
}
