{
  "type": "Feature",
  "properties": {
    "date:inception_lower": "2024-07-01",
    "date:inception_upper": "2024-07-01",
    "iso:country": "GB",
    "wof:name": "OX13 6GR",
    "wof:placetype": "postalcode"
  },
  "geometry": {"coordinates":[-1.298498,51.613297],"type":"Point"}
}
