{
  "type": "Feature",
  "properties": {
    "iso:country":"GB",
    "wof:name":"E17 7EL",
    "wof:placetype":"postalcode"
},
  "geometry": {"coordinates":[-0.03097848173252,51.58445378032578],"type":"Point"}
}