{
  "type": "Feature",
  "properties": {
    "iso:country":"GB",
    "wof:name":"SE23 1JA",
    "wof:placetype":"postalcode"
},
  "geometry": {"coordinates":[-0.03776554886868,51.44252891766927],"type":"Point"}
}