{
  "type": "Feature",
  "properties": {
    "iso:country":"GB",
    "wof:name":"TQ12 2QX",
    "wof:placetype":"postalcode"
},
  "geometry": {"coordinates":[-3.60985888657843,50.53115420141563],"type":"Point"}
}