{
  "type": "Feature",
  "properties": {
    "iso:country":"GB",
    "wof:name":"SE5 7EA",
    "wof:placetype":"postalcode"
},
  "geometry": {"coordinates":[-0.08983995002919,51.47465649294018],"type":"Point"}
}