{
  "type": "Feature",
  "properties": {
    "iso:country":"GB",
    "wof:name":"BL5 2GX",
    "wof:placetype":"postalcode"
},
  "geometry": {"coordinates":[-2.51902566048824,53.5378826133771],"type":"Point"}
}