{
  "type": "Feature",
  "properties": {
    "iso:country": "GB",
    "wof:name": "DT4 7JB",
    "wof:placetype": "postalcode"
  },
  "geometry": {"coordinates":[-2.453688,50.616015],"type":"Point"}
}
