{
  "type": "Feature",
  "properties": {
    "iso:country":"GB",
    "wof:name":"BD20 9EN",
    "wof:placetype":"postalcode"
},
  "geometry": {"coordinates":[-2.00081666187146,53.93195857272497],"type":"Point"}
}