{
  "type": "Feature",
  "properties": {
    "date:inception_lower":"1980-01-01",
    "date:inception_upper":"1980-01-31",
    "iso:country":"GB",
    "wof:name":"BD20 9EN",
    "wof:placetype":"postalcode"
},
  "geometry": {"coordinates":[-2.000817,53.931959],"type":"Point"}
}