{
  "type": "Feature",
  "properties": {
    "iso:country":"GB",
    "wof:name":"M46 9GR",
    "wof:placetype":"postalcode"
},
  "geometry": {"coordinates":[-2.48634347671139,53.52209252101152],"type":"Point"}
}