{
  "type": "Feature",
  "properties": {
    "date:inception_lower":"1990-02-01",
    "date:inception_upper":"1990-02-28",
    "iso:country":"GB",
    "wof:name":"WV12 5HG",
    "wof:placetype":"postalcode"
},
  "geometry": {"coordinates":[-2.045473,52.611907],"type":"Point"}
}