{
  "type": "Feature",
  "properties": {
    "date:inception_lower":"1993-01-01",
    "date:inception_upper":"1993-01-31",
    "iso:country":"GB",
    "wof:name":"LE14 2QU",
    "wof:placetype":"postalcode"
},
  "geometry": {"coordinates":[-0.913717,52.676907],"type":"Point"}
}