{
  "type": "Feature",
  "properties": {
    "iso:country": "GB",
    "wof:name": "HU8 7SJ",
    "wof:placetype": "postalcode"
  },
  "geometry": {"coordinates":[-0.316189,53.754669],"type":"Point"}
}
