{
  "type": "Feature",
  "properties": {
    "iso:country":"GB",
    "wof:name":"HU8 7SJ",
    "wof:placetype":"postalcode"
},
  "geometry": {"coordinates":[-0.31618942662969,53.75466895960164],"type":"Point"}
}