{
  "type": "Feature",
  "properties": {
    "date:inception_lower": "1993-08-01",
    "date:inception_upper": "1993-08-01",
    "iso:country": "GB",
    "wof:name": "CM7 4AE",
    "wof:placetype": "postalcode"
  },
  "geometry": {"coordinates":[0.495977,51.949716],"type":"Point"}
}
