{
  "type": "Feature",
  "properties": {
    "date:inception_lower": "2021-07-01",
    "date:inception_upper": "2021-07-01",
    "iso:country": "GB",
    "wof:name": "HG5 9BF",
    "wof:placetype": "postalcode"
  },
  "geometry": {"coordinates":[-1.502705,54.023457],"type":"Point"}
}
