{
  "type": "Feature",
  "properties": {
    "iso:country":"GB",
    "wof:name":"ST3 4AF",
    "wof:placetype":"postalcode"
},
  "geometry": {"coordinates":[-2.12974663135062,52.96210173232286],"type":"Point"}
}