{
  "type": "Feature",
  "properties": {
    "date:inception_lower": "2005-01-01",
    "date:inception_upper": "2005-01-01",
    "iso:country": "GB",
    "wof:name": "CR2 6NX",
    "wof:placetype": "postalcode"
  },
  "geometry": {"coordinates":[-0.098902,51.357395],"type":"Point"}
}
