{
  "type": "Feature",
  "properties": {
    "iso:country":"GB",
    "wof:name":"L33 1RW",
    "wof:placetype":"postalcode"
},
  "geometry": {"coordinates":[-2.87562661018304,53.49936226568131],"type":"Point"}
}