{
  "type": "Feature",
  "properties": {
    "date:inception_lower":"1980-01-01",
    "date:inception_upper":"1980-01-31",
    "iso:country":"GB",
    "wof:name":"PE23 4EW",
    "wof:placetype":"postalcode"
},
  "geometry": {"coordinates":[0.030529,53.188349],"type":"Point"}
}