{
  "type": "Feature",
  "properties": {
    "iso:country": "GB",
    "wof:name": "PE23 4EW",
    "wof:placetype": "postalcode"
  },
  "geometry": {"coordinates":[0.030529,53.188349],"type":"Point"}
}
