{
  "type": "Feature",
  "properties": {
    "iso:country":"GB",
    "wof:name":"PE23 4EW",
    "wof:placetype":"postalcode"
},
  "geometry": {"coordinates":[0.03056839460688,53.18827770170009],"type":"Point"}
}