{
  "type": "Feature",
  "properties": {
    "date:inception_lower": "1980-01-01",
    "date:inception_upper": "1980-01-01",
    "iso:country": "GB",
    "wof:name": "G32 9DN",
    "wof:placetype": "postalcode"
  },
  "geometry": {"coordinates":[-4.158072,55.845931],"type":"Point"}
}
