{
  "type": "Feature",
  "properties": {
    "iso:country": "GB",
    "wof:name": "BN41 2LZ",
    "wof:placetype": "postalcode"
  },
  "geometry": {"coordinates":[-0.218996,50.841718],"type":"Point"}
}
