{
  "type": "Feature",
  "properties": {
    "iso:country":"GB",
    "wof:name":"BN41 2LZ",
    "wof:placetype":"postalcode"
},
  "geometry": {"coordinates":[-0.21899629897629,50.84171780193394],"type":"Point"}
}