{
  "type": "Feature",
  "properties": {
    "iso:country":"GB",
    "wof:name":"HA3 9UT",
    "wof:placetype":"postalcode"
},
  "geometry": {"coordinates":[-0.29146005702777,51.57724970131602],"type":"Point"}
}