{
  "type": "Feature",
  "properties": {
    "iso:country":"GB",
    "wof:name":"PL6 5RS",
    "wof:placetype":"postalcode"
},
  "geometry": {"coordinates":[-4.11336963083275,50.40015817532623],"type":"Point"}
}