{
  "type": "Feature",
  "properties": {
    "iso:country":"GB",
    "wof:name":"BL0 9NB",
    "wof:placetype":"postalcode"
},
  "geometry": {"coordinates":[-2.3182159951613,53.64513337739438],"type":"Point"}
}