{
  "type": "Feature",
  "properties": {
    "date:inception_lower":"1996-06-01",
    "date:inception_upper":"1996-06-30",
    "iso:country":"GB",
    "wof:name":"BL0 9NB",
    "wof:placetype":"postalcode"
},
  "geometry": {"coordinates":[-2.318216,53.645133],"type":"Point"}
}