{
  "type": "Feature",
  "properties": {
    "iso:country":"GB",
    "wof:name":"N4 2BY",
    "wof:placetype":"postalcode"
},
  "geometry": {"coordinates":[-0.09094326712397,51.57060699878586],"type":"Point"}
}