{
  "type": "Feature",
  "properties": {
    "iso:country":"GB",
    "wof:name":"NE5 4QH",
    "wof:placetype":"postalcode"
},
  "geometry": {"coordinates":[-1.69432715106993,55.01040401497239],"type":"Point"}
}