{
  "type": "Feature",
  "properties": {
    "iso:country":"GB",
    "wof:name":"BL8 1TP",
    "wof:placetype":"postalcode"
},
  "geometry": {"coordinates":[-2.32408131656136,53.60518279891226],"type":"Point"}
}