{
  "type": "Feature",
  "properties": {
    "date:inception_lower": "1980-01-01",
    "date:inception_upper": "1980-01-01",
    "iso:country": "GB",
    "wof:name": "OL12 8SY",
    "wof:placetype": "postalcode"
  },
  "geometry": {"coordinates":[-2.177905,53.650098],"type":"Point"}
}
