{
  "type": "Feature",
  "properties": {
    "iso:country": "GB",
    "wof:name": "OL12 8SY",
    "wof:placetype": "postalcode"
  },
  "geometry": {"coordinates":[-2.177905,53.650098],"type":"Point"}
}
