{
  "type": "Feature",
  "properties": {
    "iso:country":"GB",
    "wof:name":"DY6 7TG",
    "wof:placetype":"postalcode"
},
  "geometry": {"coordinates":[-2.14669970556794,52.50743414691685],"type":"Point"}
}