{
  "type": "Feature",
  "properties": {
    "iso:country": "GB",
    "wof:name": "LN11 1TY",
    "wof:placetype": "postalcode"
  },
  "geometry": {"coordinates":[0.096056,53.360875],"type":"Point"}
}
