{
  "type": "Feature",
  "properties": {
    "iso:country":"GB",
    "wof:name":"ML8 4BY",
    "wof:placetype":"postalcode"
},
  "geometry": {"coordinates":[-3.83347303606959,55.73968199977637],"type":"Point"}
}