{
  "type": "Feature",
  "properties": {
    "iso:country": "GB",
    "wof:name": "B97 5EE",
    "wof:placetype": "postalcode"
  },
  "geometry": {"coordinates":[-1.980695,52.296226],"type":"Point"}
}
