{
  "type": "Feature",
  "properties": {
    "date:inception_lower": "2013-03-01",
    "date:inception_upper": "2013-03-01",
    "iso:country": "GB",
    "wof:name": "NN3 9GJ",
    "wof:placetype": "postalcode"
  },
  "geometry": {"coordinates":[-0.812225,52.255581],"type":"Point"}
}
