{
  "type": "Feature",
  "properties": {
    "iso:country": "GB",
    "wof:name": "NP19 4DW",
    "wof:placetype": "postalcode"
  },
  "geometry": {"coordinates":[-2.934546,51.579263],"type":"Point"}
}
