{
  "type": "Feature",
  "properties": {
    "date:inception_lower": "1994-12-01",
    "date:inception_upper": "1994-12-01",
    "iso:country": "GB",
    "wof:name": "CB5 8SW",
    "wof:placetype": "postalcode"
  },
  "geometry": {"coordinates":[0.164688,52.206774],"type":"Point"}
}
