{
  "type": "Feature",
  "properties": {
    "iso:country":"GB",
    "wof:name":"CB5 8SW",
    "wof:placetype":"postalcode"
},
  "geometry": {"coordinates":[0.16423869617725,52.206831446696],"type":"Point"}
}