{
  "type": "Feature",
  "properties": {
    "iso:country":"GB",
    "wof:name":"BA3 5YA",
    "wof:placetype":"postalcode"
},
  "geometry": {"coordinates":[-2.39801540641977,51.29056600593989],"type":"Point"}
}