{
  "type": "Feature",
  "properties": {
    "iso:country": "GB",
    "wof:name": "SL9 0DR",
    "wof:placetype": "postalcode"
  },
  "geometry": {"coordinates":[-0.547587,51.612368],"type":"Point"}
}
