{
  "type": "Feature",
  "properties": {
    "iso:country":"GB",
    "wof:name":"CO7 9PA",
    "wof:placetype":"postalcode"
},
  "geometry": {"coordinates":[0.95489404658741,51.8625949069401],"type":"Point"}
}