{
  "type": "Feature",
  "properties": {
    "date:inception_lower": "1980-01-01",
    "date:inception_upper": "1980-01-01",
    "iso:country": "GB",
    "wof:name": "CO7 9PA",
    "wof:placetype": "postalcode"
  },
  "geometry": {"coordinates":[0.954894,51.862595],"type":"Point"}
}
