{
  "type": "Feature",
  "properties": {
    "iso:country": "GB",
    "wof:name": "HU3 2SB",
    "wof:placetype": "postalcode"
  },
  "geometry": {"coordinates":[-0.363812,53.743085],"type":"Point"}
}
