{
  "type": "Feature",
  "properties": {
    "iso:country":"GB",
    "wof:name":"HU3 2SB",
    "wof:placetype":"postalcode"
},
  "geometry": {"coordinates":[-0.36381227807714,53.74308530526982],"type":"Point"}
}