{
  "type": "Feature",
  "properties": {
    "iso:country":"GB",
    "wof:name":"SE16 6NS",
    "wof:placetype":"postalcode"
},
  "geometry": {"coordinates":[-0.04108156778961,51.50523636422672],"type":"Point"}
}