{
  "type": "Feature",
  "properties": {
    "date:inception_lower": "1999-12-01",
    "date:inception_upper": "1999-12-01",
    "iso:country": "GB",
    "wof:name": "SE16 6NS",
    "wof:placetype": "postalcode"
  },
  "geometry": {"coordinates":[-0.041082,51.505236],"type":"Point"}
}
