{
  "type": "Feature",
  "properties": {
    "iso:country":"GB",
    "wof:name":"TR11 5SL",
    "wof:placetype":"postalcode"
},
  "geometry": {"coordinates":[-5.07610526180107,50.18951426645559],"type":"Point"}
}