{
  "type": "Feature",
  "properties": {
    "iso:country": "GB",
    "wof:name": "BB1 8NB",
    "wof:placetype": "postalcode"
  },
  "geometry": {"coordinates":[-2.487856,53.77134],"type":"Point"}
}
