{
  "type": "Feature",
  "properties": {
    "iso:country":"GB",
    "wof:name":"BB1 8NB",
    "wof:placetype":"postalcode"
},
  "geometry": {"coordinates":[-2.48785582932543,53.77134035564827],"type":"Point"}
}