{
  "type": "Feature",
  "properties": {
    "date:inception_lower": "1980-01-01",
    "date:inception_upper": "1980-01-01",
    "iso:country": "GB",
    "wof:name": "SG9 9HR",
    "wof:placetype": "postalcode"
  },
  "geometry": {"coordinates":[-0.014398,51.946295],"type":"Point"}
}
