{
  "type": "Feature",
  "properties": {
    "iso:country":"GB",
    "wof:name":"SG9 9HR",
    "wof:placetype":"postalcode"
},
  "geometry": {"coordinates":[-0.01439818698655,51.94629488885548],"type":"Point"}
}