{
  "type": "Feature",
  "properties": {
    "iso:country":"GB",
    "wof:name":"S9 1UJ",
    "wof:placetype":"postalcode"
},
  "geometry": {"coordinates":[-1.3953347831981,53.4123705677607],"type":"Point"}
}