{
  "type": "Feature",
  "properties": {
    "iso:country": "GB",
    "wof:name": "IP4 3PZ",
    "wof:placetype": "postalcode"
  },
  "geometry": {"coordinates":[1.192811,52.07386],"type":"Point"}
}
