{
  "type": "Feature",
  "properties": {
    "iso:country":"GB",
    "wof:name":"IP4 3PZ",
    "wof:placetype":"postalcode"
},
  "geometry": {"coordinates":[1.19281116816517,52.07386010219683],"type":"Point"}
}