{
  "type": "Feature",
  "properties": {
    "iso:country":"GB",
    "wof:name":"LL65 2PR",
    "wof:placetype":"postalcode"
},
  "geometry": {"coordinates":[-4.61603185344424,53.30295855226066],"type":"Point"}
}