{
  "type": "Feature",
  "properties": {
    "iso:country":"GB",
    "wof:name":"B46 2AP",
    "wof:placetype":"postalcode"
},
  "geometry": {"coordinates":[-1.66783438165897,52.51386538203719],"type":"Point"}
}