{
  "type": "Feature",
  "properties": {
    "date:inception_lower":"1991-09-01",
    "date:inception_upper":"1991-09-30",
    "iso:country":"GB",
    "wof:name":"RG27 8SZ",
    "wof:placetype":"postalcode"
},
  "geometry": {"coordinates":[-0.876818,51.268557],"type":"Point"}
}