{
  "type": "Feature",
  "properties": {
    "date:inception_lower": "2020-02-01",
    "date:inception_upper": "2020-02-01",
    "iso:country": "GB",
    "wof:name": "CT12 5GH",
    "wof:placetype": "postalcode"
  },
  "geometry": {"coordinates":[1.368088,51.330975],"type":"Point"}
}
