{
  "type": "Feature",
  "properties": {
    "iso:country": "GB",
    "wof:name": "CT12 5GH",
    "wof:placetype": "postalcode"
  },
  "geometry": {"coordinates":[1.368088,51.330975],"type":"Point"}
}
