{
  "type": "Feature",
  "properties": {
    "date:inception_lower": "1996-06-01",
    "date:inception_upper": "1996-06-01",
    "iso:country": "GB",
    "wof:name": "DH7 7RW",
    "wof:placetype": "postalcode"
  },
  "geometry": {"coordinates":[-1.625229,54.771344],"type":"Point"}
}
