{
  "type": "Feature",
  "properties": {
    "iso:country": "GB",
    "wof:name": "WA11 0GZ",
    "wof:placetype": "postalcode"
  },
  "geometry": {"coordinates":[-2.660972,53.467574],"type":"Point"}
}
