{
  "type": "Feature",
  "properties": {
    "iso:country": "GB",
    "wof:name": "SK1 4EL",
    "wof:placetype": "postalcode"
  },
  "geometry": {"coordinates":[-2.144496,53.405336],"type":"Point"}
}
