{
  "type": "Feature",
  "properties": {
    "iso:country":"GB",
    "wof:name":"NN5 6YQ",
    "wof:placetype":"postalcode"
},
  "geometry": {"coordinates":[-0.95944227966978,52.2564426942608],"type":"Point"}
}