{
  "type": "Feature",
  "properties": {
    "date:inception_lower": "1991-01-01",
    "date:inception_upper": "1991-01-01",
    "iso:country": "GB",
    "wof:name": "NN5 6YQ",
    "wof:placetype": "postalcode"
  },
  "geometry": {"coordinates":[-0.959442,52.256443],"type":"Point"}
}
