{
  "type": "Feature",
  "properties": {
    "iso:country":"GB",
    "wof:name":"DH8 6QD",
    "wof:placetype":"postalcode"
},
  "geometry": {"coordinates":[-1.82707139073637,54.87750649307906],"type":"Point"}
}