{
  "type": "Feature",
  "properties": {
    "iso:country":"GB",
    "wof:name":"TS3 7PZ",
    "wof:placetype":"postalcode"
},
  "geometry": {"coordinates":[-1.21200218510066,54.55842323635507],"type":"Point"}
}