{
  "type": "Feature",
  "properties": {
    "iso:country":"GB",
    "wof:name":"RH11 7SA",
    "wof:placetype":"postalcode"
},
  "geometry": {"coordinates":[-0.1950285870863,51.1291313021614],"type":"Point"}
}