{
  "type": "Feature",
  "properties": {
    "date:inception_lower": "1980-01-01",
    "date:inception_upper": "1980-01-01",
    "iso:country": "GB",
    "wof:name": "NE37 3AH",
    "wof:placetype": "postalcode"
  },
  "geometry": {"coordinates":[-1.511249,54.913123],"type":"Point"}
}
