{
  "type": "Feature",
  "properties": {
    "iso:country":"GB",
    "wof:name":"NE37 3AH",
    "wof:placetype":"postalcode"
},
  "geometry": {"coordinates":[-1.51124947357408,54.913122974463],"type":"Point"}
}