{
  "type": "Feature",
  "properties": {
    "iso:country":"GB",
    "wof:name":"CO2 9ES",
    "wof:placetype":"postalcode"
},
  "geometry": {"coordinates":[0.8721511830684,51.86757730760664],"type":"Point"}
}