{
  "type": "Feature",
  "properties": {
    "iso:country":"GB",
    "wof:name":"G41 5HD",
    "wof:placetype":"postalcode"
},
  "geometry": {"coordinates":[-4.29084454265617,55.8428282578645],"type":"Point"}
}