{
  "type": "Feature",
  "properties": {
    "iso:country":"GB",
    "wof:name":"CV5 8GY",
    "wof:placetype":"postalcode"
},
  "geometry": {"coordinates":[-1.54546273355314,52.41455036290469],"type":"Point"}
}