{
  "type": "Feature",
  "properties": {
    "iso:country": "GB",
    "wof:name": "CV5 8GY",
    "wof:placetype": "postalcode"
  },
  "geometry": {"coordinates":[-1.545463,52.41455],"type":"Point"}
}
