{
  "type": "Feature",
  "properties": {
    "iso:country": "GB",
    "wof:name": "M43 6QF",
    "wof:placetype": "postalcode"
  },
  "geometry": {"coordinates":[-2.164838,53.480624],"type":"Point"}
}
