{
  "type": "Feature",
  "properties": {
    "date:inception_lower":"1994-05-01",
    "date:inception_upper":"1994-05-31",
    "iso:country":"GB",
    "wof:name":"M43 6QF",
    "wof:placetype":"postalcode"
},
  "geometry": {"coordinates":[-2.164838,53.480624],"type":"Point"}
}