{
  "type": "Feature",
  "properties": {
    "date:inception_lower": "2007-03-01",
    "date:inception_upper": "2007-03-01",
    "iso:country": "GB",
    "wof:name": "SN5 4FE",
    "wof:placetype": "postalcode"
  },
  "geometry": {"coordinates":[-1.879116,51.585844],"type":"Point"}
}
