{
  "type": "Feature",
  "properties": {
    "iso:country":"GB",
    "wof:name":"SN5 4FE",
    "wof:placetype":"postalcode"
},
  "geometry": {"coordinates":[-1.87911636483721,51.58584370523317],"type":"Point"}
}