{
  "type": "Feature",
  "properties": {
    "date:inception_lower": "2017-12-01",
    "date:inception_upper": "2017-12-01",
    "iso:country": "GB",
    "wof:name": "SY17 5PW",
    "wof:placetype": "postalcode"
  },
  "geometry": {"coordinates":[-3.520652,52.502998],"type":"Point"}
}
