{
  "type": "Feature",
  "properties": {
    "iso:country":"GB",
    "wof:name":"PO1 3BU",
    "wof:placetype":"postalcode"
},
  "geometry": {"coordinates":[-1.10106038923792,50.79830248603822],"type":"Point"}
}