{
  "type": "Feature",
  "properties": {
    "iso:country": "GB",
    "wof:name": "PO1 3BU",
    "wof:placetype": "postalcode"
  },
  "geometry": {"coordinates":[-1.10106,50.798302],"type":"Point"}
}
