{
  "type": "Feature",
  "properties": {
    "iso:country": "GB",
    "wof:name": "S5 6US",
    "wof:placetype": "postalcode"
  },
  "geometry": {"coordinates":[-1.450757,53.411281],"type":"Point"}
}
