{
  "type": "Feature",
  "properties": {
    "iso:country":"GB",
    "wof:name":"GU14 6HL",
    "wof:placetype":"postalcode"
},
  "geometry": {"coordinates":[-0.74141840736644,51.27692857185551],"type":"Point"}
}