{
  "type": "Feature",
  "properties": {
    "iso:country": "GB",
    "wof:name": "TS6 6HJ",
    "wof:placetype": "postalcode"
  },
  "geometry": {"coordinates":[-1.177144,54.577019],"type":"Point"}
}
