{
  "type": "Feature",
  "properties": {
    "iso:country":"GB",
    "wof:name":"TS6 6HJ",
    "wof:placetype":"postalcode"
},
  "geometry": {"coordinates":[-1.17714454882882,54.57701925879594],"type":"Point"}
}