{
  "type": "Feature",
  "properties": {
    "iso:country":"GB",
    "wof:name":"CH43 7YE",
    "wof:placetype":"postalcode"
},
  "geometry": {"coordinates":[-3.07467892111035,53.39420322815898],"type":"Point"}
}