{
  "type": "Feature",
  "properties": {
    "iso:country": "GB",
    "wof:name": "SY23 3BJ",
    "wof:placetype": "postalcode"
  },
  "geometry": {"coordinates":[-4.040905,52.434052],"type":"Point"}
}
