{
  "type": "Feature",
  "properties": {
    "iso:country":"GB",
    "wof:name":"SY23 3BJ",
    "wof:placetype":"postalcode"
},
  "geometry": {"coordinates":[-4.04089431366221,52.43403622772411],"type":"Point"}
}