{
  "type": "Feature",
  "properties": {
    "date:inception_lower": "1980-01-01",
    "date:inception_upper": "1980-01-01",
    "iso:country": "GB",
    "wof:name": "SY23 3BJ",
    "wof:placetype": "postalcode"
  },
  "geometry": {"coordinates":[-4.040905,52.434052],"type":"Point"}
}
