{
  "type": "Feature",
  "properties": {
    "date:inception_lower": "1980-01-01",
    "date:inception_upper": "1980-01-01",
    "iso:country": "GB",
    "wof:name": "SM4 6RL",
    "wof:placetype": "postalcode"
  },
  "geometry": {"coordinates":[-0.181689,51.389698],"type":"Point"}
}
