{
  "type": "Feature",
  "properties": {
    "iso:country":"GB",
    "wof:name":"SM4 6RL",
    "wof:placetype":"postalcode"
},
  "geometry": {"coordinates":[-0.18168905583598,51.38969822594484],"type":"Point"}
}