{
  "type": "Feature",
  "properties": {
    "iso:country":"GB",
    "wof:name":"IV2 4TT",
    "wof:placetype":"postalcode"
},
  "geometry": {"coordinates":[-4.20779734500105,57.46245881891802],"type":"Point"}
}