{
  "type": "Feature",
  "properties": {
    "iso:country": "GB",
    "wof:name": "RG1 6NF",
    "wof:placetype": "postalcode"
  },
  "geometry": {"coordinates":[-0.985377,51.45107],"type":"Point"}
}
