{
  "type": "Feature",
  "properties": {
    "date:inception_lower": "2002-06-01",
    "date:inception_upper": "2002-06-01",
    "iso:country": "GB",
    "wof:name": "WS13 8FA",
    "wof:placetype": "postalcode"
  },
  "geometry": {"coordinates":[-1.845165,52.676172],"type":"Point"}
}
