{
  "type": "Feature",
  "properties": {
    "iso:country":"GB",
    "wof:name":"BB2 3UW",
    "wof:placetype":"postalcode"
},
  "geometry": {"coordinates":[-2.46791177723515,53.72564339909808],"type":"Point"}
}