{
  "type": "Feature",
  "properties": {
    "iso:country":"GB",
    "wof:name":"DN21 5EP",
    "wof:placetype":"postalcode"
},
  "geometry": {"coordinates":[-0.74796067311834,53.36830815153299],"type":"Point"}
}