{
  "type": "Feature",
  "properties": {
    "iso:country":"GB",
    "wof:name":"BN24 6EG",
    "wof:placetype":"postalcode"
},
  "geometry": {"coordinates":[0.35277628465574,50.81298811785818],"type":"Point"}
}