{
  "type": "Feature",
  "properties": {
    "iso:country":"GB",
    "wof:name":"PL4 6PX",
    "wof:placetype":"postalcode"
},
  "geometry": {"coordinates":[-4.14197335993501,50.38133124215478],"type":"Point"}
}