{
  "type": "Feature",
  "properties": {
    "iso:country": "GB",
    "wof:name": "CV35 9QN",
    "wof:placetype": "postalcode"
  },
  "geometry": {"coordinates":[-1.59711,52.187181],"type":"Point"}
}
