{
  "type": "Feature",
  "properties": {
    "date:inception_lower":"2014-10-01",
    "date:inception_upper":"2014-10-31",
    "iso:country":"GB",
    "wof:name":"CV35 9QN",
    "wof:placetype":"postalcode"
},
  "geometry": {"coordinates":[-1.59711,52.187181],"type":"Point"}
}