{
  "type": "Feature",
  "properties": {
    "iso:country":"GB",
    "wof:name":"CV35 9QN",
    "wof:placetype":"postalcode"
},
  "geometry": {"coordinates":[-1.5967478809312,52.18803719279481],"type":"Point"}
}