{
  "type": "Feature",
  "properties": {
    "date:inception_lower": "1980-01-01",
    "date:inception_upper": "1980-01-01",
    "iso:country": "GB",
    "wof:name": "CF45 3AU",
    "wof:placetype": "postalcode"
  },
  "geometry": {"coordinates":[-3.374876,51.676904],"type":"Point"}
}
