{
  "type": "Feature",
  "properties": {
    "iso:country":"GB",
    "wof:name":"CF45 3AU",
    "wof:placetype":"postalcode"
},
  "geometry": {"coordinates":[-3.37487638761706,51.67690407851799],"type":"Point"}
}