{
  "type": "Feature",
  "properties": {
    "date:inception_lower": "1980-01-01",
    "date:inception_upper": "1980-01-01",
    "iso:country": "GB",
    "wof:name": "TQ7 1JS",
    "wof:placetype": "postalcode"
  },
  "geometry": {"coordinates":[-3.772977,50.279777],"type":"Point"}
}
