{
  "type": "Feature",
  "properties": {
    "iso:country": "GB",
    "wof:name": "TQ7 1JS",
    "wof:placetype": "postalcode"
  },
  "geometry": {"coordinates":[-3.772977,50.279777],"type":"Point"}
}
