{
  "type": "Feature",
  "properties": {
    "date:inception_lower":"2003-08-01",
    "date:inception_upper":"2003-08-31",
    "iso:country":"GB",
    "wof:name":"DT11 7YA",
    "wof:placetype":"postalcode"
},
  "geometry": {"coordinates":[-2.153055,50.868873],"type":"Point"}
}