{
  "type": "Feature",
  "properties": {
    "iso:country": "GB",
    "wof:name": "LN11 0TA",
    "wof:placetype": "postalcode"
  },
  "geometry": {"coordinates":[-0.016915,53.390307],"type":"Point"}
}
