{
  "type": "Feature",
  "properties": {
    "iso:country":"GB",
    "wof:name":"LN11 0TA",
    "wof:placetype":"postalcode"
},
  "geometry": {"coordinates":[-0.01691527350146,53.39030660620767],"type":"Point"}
}