{
  "type": "Feature",
  "properties": {
    "date:inception_lower": "1980-01-01",
    "date:inception_upper": "1980-01-01",
    "iso:country": "GB",
    "wof:name": "LN11 0TA",
    "wof:placetype": "postalcode"
  },
  "geometry": {"coordinates":[-0.016915,53.390307],"type":"Point"}
}
