{
  "type": "Feature",
  "properties": {
    "date:inception_lower": "2004-04-01",
    "date:inception_upper": "2004-04-01",
    "iso:country": "GB",
    "wof:name": "BS24 8BJ",
    "wof:placetype": "postalcode"
  },
  "geometry": {"coordinates":[-2.912969,51.335382],"type":"Point"}
}
