{
  "type": "Feature",
  "properties": {
    "iso:country": "GB",
    "wof:name": "BS24 8BJ",
    "wof:placetype": "postalcode"
  },
  "geometry": {"coordinates":[-2.912815,51.335188],"type":"Point"}
}
