{
  "type": "Feature",
  "properties": {
    "iso:country":"GB",
    "wof:name":"NE5 5QY",
    "wof:placetype":"postalcode"
},
  "geometry": {"coordinates":[-1.70242629845735,55.00201300169588],"type":"Point"}
}