{
  "type": "Feature",
  "properties": {
    "iso:country":"GB",
    "wof:name":"SO40 9BB",
    "wof:placetype":"postalcode"
},
  "geometry": {"coordinates":[-1.49815951748508,50.91047541999627],"type":"Point"}
}