{
  "type": "Feature",
  "properties": {
    "date:inception_lower": "2021-10-01",
    "date:inception_upper": "2021-10-01",
    "iso:country": "GB",
    "wof:name": "B97 6DS",
    "wof:placetype": "postalcode"
  },
  "geometry": {"coordinates":[-1.946883,52.306852],"type":"Point"}
}
