{
  "type": "Feature",
  "properties": {
    "iso:country": "GB",
    "wof:name": "NE25 0FA",
    "wof:placetype": "postalcode"
  },
  "geometry": {"coordinates":[-1.538277,55.076902],"type":"Point"}
}
