{
  "type": "Feature",
  "properties": {
    "date:inception_lower": "1980-01-01",
    "date:inception_upper": "1980-01-01",
    "iso:country": "GB",
    "wof:name": "IP3 0EN",
    "wof:placetype": "postalcode"
  },
  "geometry": {"coordinates":[1.178531,52.035986],"type":"Point"}
}
