{
  "type": "Feature",
  "properties": {
    "iso:country":"GB",
    "wof:name":"NR18 0LE",
    "wof:placetype":"postalcode"
},
  "geometry": {"coordinates":[1.11276550934705,52.57407470583061],"type":"Point"}
}