{
  "type": "Feature",
  "properties": {
    "iso:country": "GB",
    "wof:name": "NR18 0LE",
    "wof:placetype": "postalcode"
  },
  "geometry": {"coordinates":[1.112766,52.574075],"type":"Point"}
}
