{
  "type": "Feature",
  "properties": {
    "date:inception_lower": "1980-01-01",
    "date:inception_upper": "1980-01-01",
    "iso:country": "GB",
    "wof:name": "ME9 0LL",
    "wof:placetype": "postalcode"
  },
  "geometry": {"coordinates":[0.800162,51.284637],"type":"Point"}
}
