{
  "type": "Feature",
  "properties": {
    "iso:country":"GB",
    "wof:name":"ME9 0LL",
    "wof:placetype":"postalcode"
},
  "geometry": {"coordinates":[0.80016169796164,51.2846368809555],"type":"Point"}
}