{
  "type": "Feature",
  "properties": {
    "iso:country":"GB",
    "wof:name":"LL21 0AA",
    "wof:placetype":"postalcode"
},
  "geometry": {"coordinates":[-3.37430777922932,52.98093356777133],"type":"Point"}
}