{
  "type": "Feature",
  "properties": {
    "date:inception_lower": "1980-01-01",
    "date:inception_upper": "1980-01-01",
    "iso:country": "GB",
    "wof:name": "LL21 0AA",
    "wof:placetype": "postalcode"
  },
  "geometry": {"coordinates":[-3.374308,52.980934],"type":"Point"}
}
