{
  "type": "Feature",
  "properties": {
    "iso:country":"GB",
    "wof:name":"HU9 1QH",
    "wof:placetype":"postalcode"
},
  "geometry": {"coordinates":[-0.3178711051904,53.74181106024304],"type":"Point"}
}