{
  "type": "Feature",
  "properties": {
    "iso:country":"GB",
    "wof:name":"PE32 1NY",
    "wof:placetype":"postalcode"
},
  "geometry": {"coordinates":[0.51049324187294,52.72071815647457],"type":"Point"}
}