{
  "type": "Feature",
  "properties": {
    "date:inception_lower":"1995-07-01",
    "date:inception_upper":"1995-07-31",
    "iso:country":"GB",
    "wof:name":"PE32 1NY",
    "wof:placetype":"postalcode"
},
  "geometry": {"coordinates":[0.510271,52.720692],"type":"Point"}
}