{
  "type": "Feature",
  "properties": {
    "iso:country": "GB",
    "wof:name": "PE32 1NY",
    "wof:placetype": "postalcode"
  },
  "geometry": {"coordinates":[0.510511,52.72074],"type":"Point"}
}
