{
  "type": "Feature",
  "properties": {
    "iso:country":"GB",
    "wof:name":"CT5 4SR",
    "wof:placetype":"postalcode"
},
  "geometry": {"coordinates":[1.00390601309233,51.34446946449028],"type":"Point"}
}