{
  "type": "Feature",
  "properties": {
    "iso:country":"GB",
    "wof:name":"LE9 7SG",
    "wof:placetype":"postalcode"
},
  "geometry": {"coordinates":[-1.31252871646038,52.5611785002942],"type":"Point"}
}