{
  "type": "Feature",
  "properties": {
    "iso:country":"GB",
    "wof:name":"M11 2GU",
    "wof:placetype":"postalcode"
},
  "geometry": {"coordinates":[-2.18062761910704,53.47658358066222],"type":"Point"}
}