{
  "type": "Feature",
  "properties": {
    "date:inception_lower": "1980-01-01",
    "date:inception_upper": "1980-01-01",
    "iso:country": "GB",
    "wof:name": "M1 7JP",
    "wof:placetype": "postalcode"
  },
  "geometry": {"coordinates":[-2.231488,53.472846],"type":"Point"}
}
