{
  "type": "Feature",
  "properties": {
    "iso:country":"GB",
    "wof:name":"WN2 5PJ",
    "wof:placetype":"postalcode"
},
  "geometry": {"coordinates":[-2.59680986984852,53.51654037664071],"type":"Point"}
}