{
  "type": "Feature",
  "properties": {
    "date:inception_lower": "1980-01-01",
    "date:inception_upper": "1980-01-01",
    "iso:country": "GB",
    "wof:name": "WN2 5PJ",
    "wof:placetype": "postalcode"
  },
  "geometry": {"coordinates":[-2.596809,53.516556],"type":"Point"}
}
