{
  "type": "Feature",
  "properties": {
    "iso:country":"GB",
    "wof:name":"B98 0SB",
    "wof:placetype":"postalcode"
},
  "geometry": {"coordinates":[-1.88320230488767,52.30950663728071],"type":"Point"}
}