{
  "type": "Feature",
  "properties": {
    "iso:country": "GB",
    "wof:name": "B98 0SB",
    "wof:placetype": "postalcode"
  },
  "geometry": {"coordinates":[-1.883202,52.309507],"type":"Point"}
}
