{
  "type": "Feature",
  "properties": {
    "date:inception_lower": "1981-09-01",
    "date:inception_upper": "1981-09-01",
    "iso:country": "GB",
    "wof:name": "B98 0SB",
    "wof:placetype": "postalcode"
  },
  "geometry": {"coordinates":[-1.883202,52.309507],"type":"Point"}
}
