{
  "type": "Feature",
  "properties": {
    "iso:country":"GB",
    "wof:name":"LE16 8DW",
    "wof:placetype":"postalcode"
},
  "geometry": {"coordinates":[-0.82103109726728,52.52641460204184],"type":"Point"}
}