{
  "type": "Feature",
  "properties": {
    "iso:country":"GB",
    "wof:name":"CA7 4TL",
    "wof:placetype":"postalcode"
},
  "geometry": {"coordinates":[-3.25172794176836,54.84037843335468],"type":"Point"}
}