{
  "type": "Feature",
  "properties": {
    "iso:country":"GB",
    "wof:name":"CH45 2LF",
    "wof:placetype":"postalcode"
},
  "geometry": {"coordinates":[-3.0410831852633,53.43916711749218],"type":"Point"}
}