{
  "type": "Feature",
  "properties": {
    "iso:country":"GB",
    "wof:name":"IP17 3JQ",
    "wof:placetype":"postalcode"
},
  "geometry": {"coordinates":[1.49932461671697,52.27248398630537],"type":"Point"}
}