{
  "type": "Feature",
  "properties": {
    "date:inception_lower": "2011-05-01",
    "date:inception_upper": "2011-05-01",
    "iso:country": "GB",
    "wof:name": "LS10 4FX",
    "wof:placetype": "postalcode"
  },
  "geometry": {"coordinates":[-1.529449,53.743933],"type":"Point"}
}
