{
  "type": "Feature",
  "properties": {
    "iso:country":"GB",
    "wof:name":"LS10 4FX",
    "wof:placetype":"postalcode"
},
  "geometry": {"coordinates":[-1.52944559235492,53.74389002376584],"type":"Point"}
}