{
  "type": "Feature",
  "properties": {
    "iso:country":"GB",
    "wof:name":"ML2 8JZ",
    "wof:placetype":"postalcode"
},
  "geometry": {"coordinates":[-3.91302296312088,55.79006226620753],"type":"Point"}
}