{
  "type": "Feature",
  "properties": {
    "iso:country": "GB",
    "wof:name": "ML2 8JZ",
    "wof:placetype": "postalcode"
  },
  "geometry": {"coordinates":[-3.913045,55.790068],"type":"Point"}
}
