{
  "type": "Feature",
  "properties": {
    "date:inception_lower": "2018-08-01",
    "date:inception_upper": "2018-08-01",
    "iso:country": "GB",
    "wof:name": "BS35 1AQ",
    "wof:placetype": "postalcode"
  },
  "geometry": {"coordinates":[-2.525994,51.618679],"type":"Point"}
}
