{
  "type": "Feature",
  "properties": {
    "iso:country": "GB",
    "wof:name": "S66 7RF",
    "wof:placetype": "postalcode"
  },
  "geometry": {"coordinates":[-1.220429,53.46253],"type":"Point"}
}
