{
  "type": "Feature",
  "properties": {
    "date:inception_lower":"2004-08-01",
    "date:inception_upper":"2004-08-31",
    "iso:country":"GB",
    "wof:name":"S66 7RF",
    "wof:placetype":"postalcode"
},
  "geometry": {"coordinates":[-1.220429,53.46253],"type":"Point"}
}