{
  "type": "Feature",
  "properties": {
    "iso:country":"GB",
    "wof:name":"S66 7RF",
    "wof:placetype":"postalcode"
},
  "geometry": {"coordinates":[-1.2204287028389,53.46253019559551],"type":"Point"}
}