{
  "type": "Feature",
  "properties": {
    "iso:country":"GB",
    "wof:name":"CA15 8JA",
    "wof:placetype":"postalcode"
},
  "geometry": {"coordinates":[-3.4886881855101,54.7070880784746],"type":"Point"}
}