{
  "type": "Feature",
  "properties": {
    "iso:country":"GB",
    "wof:name":"GU2 4EW",
    "wof:placetype":"postalcode"
},
  "geometry": {"coordinates":[-0.58042438469998,51.22767925761562],"type":"Point"}
}