{
  "type": "Feature",
  "properties": {
    "date:inception_lower": "1980-01-01",
    "date:inception_upper": "1980-01-01",
    "iso:country": "GB",
    "wof:name": "SY23 4EA",
    "wof:placetype": "postalcode"
  },
  "geometry": {"coordinates":[-4.029547,52.395601],"type":"Point"}
}
