{
  "type": "Feature",
  "properties": {
    "iso:country":"GB",
    "wof:name":"AB37 9AB",
    "wof:placetype":"postalcode"
},
  "geometry": {"coordinates":[-3.38785472020282,57.41170647699678],"type":"Point"}
}