{
  "type": "Feature",
  "properties": {
    "iso:country": "GB",
    "wof:name": "PL5 2BN",
    "wof:placetype": "postalcode"
  },
  "geometry": {"coordinates":[-4.173266,50.406753],"type":"Point"}
}
