{
  "type": "Feature",
  "properties": {
    "date:inception_lower": "1987-04-01",
    "date:inception_upper": "1987-04-01",
    "iso:country": "GB",
    "wof:name": "PL5 2BN",
    "wof:placetype": "postalcode"
  },
  "geometry": {"coordinates":[-4.173266,50.406753],"type":"Point"}
}
