{
  "type": "Feature",
  "properties": {
    "date:inception_lower": "1980-01-01",
    "date:inception_upper": "1980-01-01",
    "iso:country": "GB",
    "wof:name": "EN8 9LS",
    "wof:placetype": "postalcode"
  },
  "geometry": {"coordinates":[-0.036365,51.702223],"type":"Point"}
}
