{
  "type": "Feature",
  "properties": {
    "iso:country":"GB",
    "wof:name":"BD3 8LE",
    "wof:placetype":"postalcode"
},
  "geometry": {"coordinates":[-1.71376230573987,53.79480447585101],"type":"Point"}
}