{
  "type": "Feature",
  "properties": {
    "iso:country": "GB",
    "wof:name": "EH2 3NR",
    "wof:placetype": "postalcode"
  },
  "geometry": {"coordinates":[-3.202498,55.953978],"type":"Point"}
}
