{
  "type": "Feature",
  "properties": {
    "iso:country":"GB",
    "wof:name":"EH2 3NR",
    "wof:placetype":"postalcode"
},
  "geometry": {"coordinates":[-3.20249821471281,55.95397811159853],"type":"Point"}
}