{
  "type": "Feature",
  "properties": {
    "iso:country":"GB",
    "wof:name":"NG10 2EL",
    "wof:placetype":"postalcode"
},
  "geometry": {"coordinates":[-1.25692798431904,52.89937074563954],"type":"Point"}
}