{
  "type": "Feature",
  "properties": {
    "date:inception_lower": "1987-04-01",
    "date:inception_upper": "1987-04-01",
    "iso:country": "GB",
    "wof:name": "LS27 9NL",
    "wof:placetype": "postalcode"
  },
  "geometry": {"coordinates":[-1.600822,53.75755],"type":"Point"}
}
