{
  "type": "Feature",
  "properties": {
    "iso:country":"GB",
    "wof:name":"LS27 9NL",
    "wof:placetype":"postalcode"
},
  "geometry": {"coordinates":[-1.60082208899311,53.75755007337771],"type":"Point"}
}