{
  "type": "Feature",
  "properties": {
    "iso:country":"GB",
    "wof:name":"S21 1BA",
    "wof:placetype":"postalcode"
},
  "geometry": {"coordinates":[-1.3292089262927,53.32372978434022],"type":"Point"}
}