{
  "type": "Feature",
  "properties": {
    "iso:country":"GB",
    "wof:name":"CV3 2TF",
    "wof:placetype":"postalcode"
},
  "geometry": {"coordinates":[-1.43758760592251,52.39168316052015],"type":"Point"}
}