{
  "type": "Feature",
  "properties": {
    "date:inception_lower": "1993-01-01",
    "date:inception_upper": "1993-01-01",
    "iso:country": "GB",
    "wof:name": "CV3 2TF",
    "wof:placetype": "postalcode"
  },
  "geometry": {"coordinates":[-1.438433,52.392658],"type":"Point"}
}
