{
  "type": "Feature",
  "properties": {
    "iso:country":"GB",
    "wof:name":"CV3 1AS",
    "wof:placetype":"postalcode"
},
  "geometry": {"coordinates":[-1.48538874316673,52.40316549517668],"type":"Point"}
}