{
  "type": "Feature",
  "properties": {
    "date:inception_lower": "1980-01-01",
    "date:inception_upper": "1980-01-01",
    "iso:country": "GB",
    "wof:name": "G82 2HU",
    "wof:placetype": "postalcode"
  },
  "geometry": {"coordinates":[-4.554297,55.948812],"type":"Point"}
}
