{
  "type": "Feature",
  "properties": {
    "iso:country": "GB",
    "wof:name": "G82 2HU",
    "wof:placetype": "postalcode"
  },
  "geometry": {"coordinates":[-4.554297,55.948812],"type":"Point"}
}
