{
  "type": "Feature",
  "properties": {
    "iso:country":"GB",
    "wof:name":"G82 2HU",
    "wof:placetype":"postalcode"
},
  "geometry": {"coordinates":[-4.55429687664654,55.94881237597481],"type":"Point"}
}