{
  "type": "Feature",
  "properties": {
    "iso:country":"GB",
    "wof:name":"PA2 8NX",
    "wof:placetype":"postalcode"
},
  "geometry": {"coordinates":[-4.44105322583424,55.82435320261556],"type":"Point"}
}