{
  "type": "Feature",
  "properties": {
    "date:inception_lower":"1980-01-01",
    "date:inception_upper":"1980-01-31",
    "iso:country":"GB",
    "wof:name":"LA14 2EX",
    "wof:placetype":"postalcode"
},
  "geometry": {"coordinates":[-3.225992,54.109597],"type":"Point"}
}