{
  "type": "Feature",
  "properties": {
    "iso:country": "GB",
    "wof:name": "LA14 2EX",
    "wof:placetype": "postalcode"
  },
  "geometry": {"coordinates":[-3.225992,54.109597],"type":"Point"}
}
