{
  "type": "Feature",
  "properties": {
    "iso:country":"GB",
    "wof:name":"B73 6EP",
    "wof:placetype":"postalcode"
},
  "geometry": {"coordinates":[-1.83140104510656,52.55930429199007],"type":"Point"}
}