{
  "type": "Feature",
  "properties": {
    "iso:country":"GB",
    "wof:name":"KT2 5HP",
    "wof:placetype":"postalcode"
},
  "geometry": {"coordinates":[-0.30412647940528,51.41629049725206],"type":"Point"}
}