{
  "type": "Feature",
  "properties": {
    "iso:country":"GB",
    "wof:name":"EN4 8TE",
    "wof:placetype":"postalcode"
},
  "geometry": {"coordinates":[-0.16467832883515,51.64231041742494],"type":"Point"}
}