{
  "type": "Feature",
  "properties": {
    "iso:country":"GB",
    "wof:name":"B79 7LG",
    "wof:placetype":"postalcode"
},
  "geometry": {"coordinates":[-1.69356173592995,52.63260972499902],"type":"Point"}
}