{
  "type": "Feature",
  "properties": {
    "date:inception_lower": "1981-09-01",
    "date:inception_upper": "1981-09-01",
    "iso:country": "GB",
    "wof:name": "B79 7LG",
    "wof:placetype": "postalcode"
  },
  "geometry": {"coordinates":[-1.693555,52.632627],"type":"Point"}
}
