{
  "type": "Feature",
  "properties": {
    "iso:country":"GB",
    "wof:name":"DE6 2BJ",
    "wof:placetype":"postalcode"
},
  "geometry": {"coordinates":[-1.75633288612187,53.00873943325826],"type":"Point"}
}