{
  "type": "Feature",
  "properties": {
    "date:inception_lower": "1980-01-01",
    "date:inception_upper": "1980-01-01",
    "iso:country": "GB",
    "wof:name": "G43 1RR",
    "wof:placetype": "postalcode"
  },
  "geometry": {"coordinates":[-4.296447,55.82651],"type":"Point"}
}
