{
  "type": "Feature",
  "properties": {
    "iso:country":"GB",
    "wof:name":"LS15 8FY",
    "wof:placetype":"postalcode"
},
  "geometry": {"coordinates":[-1.43875345662718,53.80802556225957],"type":"Point"}
}