{
  "type": "Feature",
  "properties": {
    "date:inception_lower": "2014-03-01",
    "date:inception_upper": "2014-03-01",
    "iso:country": "GB",
    "wof:name": "LS15 8FY",
    "wof:placetype": "postalcode"
  },
  "geometry": {"coordinates":[-1.43894,53.808052],"type":"Point"}
}
