{
  "type": "Feature",
  "properties": {
    "iso:country": "GB",
    "wof:name": "LS15 8FY",
    "wof:placetype": "postalcode"
  },
  "geometry": {"coordinates":[-1.438758,53.808042],"type":"Point"}
}
