{
  "type": "Feature",
  "properties": {
    "date:inception_lower": "2013-07-01",
    "date:inception_upper": "2013-07-01",
    "iso:country": "GB",
    "wof:name": "G75 8WA",
    "wof:placetype": "postalcode"
  },
  "geometry": {"coordinates":[-4.22069,55.73915],"type":"Point"}
}
