{
  "type": "Feature",
  "properties": {
    "date:inception_lower": "1980-01-01",
    "date:inception_upper": "1980-01-01",
    "iso:country": "GB",
    "wof:name": "LA22 9HW",
    "wof:placetype": "postalcode"
  },
  "geometry": {"coordinates":[-3.035527,54.434081],"type":"Point"}
}
