{
  "type": "Feature",
  "properties": {
    "iso:country":"GB",
    "wof:name":"SW4 7DA",
    "wof:placetype":"postalcode"
},
  "geometry": {"coordinates":[-0.13370648215344,51.45902341575709],"type":"Point"}
}