{
  "type": "Feature",
  "properties": {
    "iso:country": "GB",
    "wof:name": "CT8 8TA",
    "wof:placetype": "postalcode"
  },
  "geometry": {"coordinates":[1.340388,51.383444],"type":"Point"}
}
