{
  "type": "Feature",
  "properties": {
    "iso:country":"GB",
    "wof:name":"CT8 8TA",
    "wof:placetype":"postalcode"
},
  "geometry": {"coordinates":[1.34081121595412,51.38310122778999],"type":"Point"}
}