{
  "type": "Feature",
  "properties": {
    "date:inception_lower": "1992-08-01",
    "date:inception_upper": "1992-08-01",
    "iso:country": "GB",
    "wof:name": "LE67 3PF",
    "wof:placetype": "postalcode"
  },
  "geometry": {"coordinates":[-1.374531,52.72378],"type":"Point"}
}
