{
  "type": "Feature",
  "properties": {
    "iso:country":"GB",
    "wof:name":"ME15 0EX",
    "wof:placetype":"postalcode"
},
  "geometry": {"coordinates":[0.49361321964408,51.25626111802985],"type":"Point"}
}