{
  "type": "Feature",
  "properties": {
    "iso:country": "GB",
    "wof:name": "WF5 0HD",
    "wof:placetype": "postalcode"
  },
  "geometry": {"coordinates":[-1.554764,53.673834],"type":"Point"}
}
