{
  "type": "Feature",
  "properties": {
    "iso:country":"GB",
    "wof:name":"WF5 0HD",
    "wof:placetype":"postalcode"
},
  "geometry": {"coordinates":[-1.55476365485778,53.67383401997218],"type":"Point"}
}