{
  "type": "Feature",
  "properties": {
    "date:inception_lower": "2002-06-01",
    "date:inception_upper": "2002-06-01",
    "iso:country": "GB",
    "wof:name": "EH51 9DJ",
    "wof:placetype": "postalcode"
  },
  "geometry": {"coordinates":[-3.582042,56.009904],"type":"Point"}
}
