{
  "type": "Feature",
  "properties": {
    "iso:country":"GB",
    "wof:name":"SR3 1QG",
    "wof:placetype":"postalcode"
},
  "geometry": {"coordinates":[-1.41781527230559,54.88700126351012],"type":"Point"}
}