{
  "type": "Feature",
  "properties": {
    "iso:country": "GB",
    "wof:name": "SR3 1QG",
    "wof:placetype": "postalcode"
  },
  "geometry": {"coordinates":[-1.417815,54.887001],"type":"Point"}
}
