{
  "type": "Feature",
  "properties": {
    "iso:country":"GB",
    "wof:name":"S74 8AQ",
    "wof:placetype":"postalcode"
},
  "geometry": {"coordinates":[-1.41869262522922,53.50106919563877],"type":"Point"}
}