{
  "type": "Feature",
  "properties": {
    "iso:country": "GB",
    "wof:name": "S74 8AQ",
    "wof:placetype": "postalcode"
  },
  "geometry": {"coordinates":[-1.418693,53.501069],"type":"Point"}
}
