{
  "type": "Feature",
  "properties": {
    "iso:country":"GB",
    "wof:name":"FY1 6PS",
    "wof:placetype":"postalcode"
},
  "geometry": {"coordinates":[-3.03510204453604,53.80222601234615],"type":"Point"}
}