{
  "type": "Feature",
  "properties": {
    "iso:country": "GB",
    "wof:name": "FY1 6PS",
    "wof:placetype": "postalcode"
  },
  "geometry": {"coordinates":[-3.035102,53.802226],"type":"Point"}
}
