{
  "type": "Feature",
  "properties": {
    "date:inception_lower": "1980-01-01",
    "date:inception_upper": "1980-01-01",
    "iso:country": "GB",
    "wof:name": "FY1 6PS",
    "wof:placetype": "postalcode"
  },
  "geometry": {"coordinates":[-3.035102,53.802226],"type":"Point"}
}
