{
  "type": "Feature",
  "properties": {
    "iso:country":"GB",
    "wof:name":"SY10 7PX",
    "wof:placetype":"postalcode"
},
  "geometry": {"coordinates":[-3.17077369795277,52.84931752524007],"type":"Point"}
}