{
  "type": "Feature",
  "properties": {
    "iso:country":"GB",
    "wof:name":"W12 7ND",
    "wof:placetype":"postalcode"
},
  "geometry": {"coordinates":[-0.23317949103137,51.51368303070069],"type":"Point"}
}