{
  "type": "Feature",
  "properties": {
    "iso:country":"GB",
    "wof:name":"YO32 3WB",
    "wof:placetype":"postalcode"
},
  "geometry": {"coordinates":[-1.0592072032615,54.01635011337945],"type":"Point"}
}