{
  "type": "Feature",
  "properties": {
    "iso:country": "GB",
    "wof:name": "YO32 3WB",
    "wof:placetype": "postalcode"
  },
  "geometry": {"coordinates":[-1.059207,54.01635],"type":"Point"}
}
