{
  "type": "Feature",
  "properties": {
    "iso:country":"GB",
    "wof:name":"TW8 8NT",
    "wof:placetype":"postalcode"
},
  "geometry": {"coordinates":[-0.31947234536502,51.48132877208004],"type":"Point"}
}