{
  "type": "Feature",
  "properties": {
    "iso:country":"GB",
    "wof:name":"S9 4PN",
    "wof:placetype":"postalcode"
},
  "geometry": {"coordinates":[-1.40779618728376,53.38602419384722],"type":"Point"}
}