{
  "type": "Feature",
  "properties": {
    "iso:country":"GB",
    "wof:name":"GU1 2JG",
    "wof:placetype":"postalcode"
},
  "geometry": {"coordinates":[-0.55360155100532,51.24131619345297],"type":"Point"}
}