{
  "type": "Feature",
  "properties": {
    "iso:country":"GB",
    "wof:name":"L35 2UZ",
    "wof:placetype":"postalcode"
},
  "geometry": {"coordinates":[-2.79607094547006,53.4179056615307],"type":"Point"}
}