{
  "type": "Feature",
  "properties": {
    "iso:country":"GB",
    "wof:name":"SA12 7TB",
    "wof:placetype":"postalcode"
},
  "geometry": {"coordinates":[-3.82254079614007,51.60673885029318],"type":"Point"}
}