{
  "type": "Feature",
  "properties": {
    "iso:country":"GB",
    "wof:name":"BR2 8BN",
    "wof:placetype":"postalcode"
},
  "geometry": {"coordinates":[0.06313891636719,51.38730656270998],"type":"Point"}
}