{
  "type": "Feature",
  "properties": {
    "date:inception_lower": "1980-01-01",
    "date:inception_upper": "1980-01-01",
    "iso:country": "GB",
    "wof:name": "BR6 6JQ",
    "wof:placetype": "postalcode"
  },
  "geometry": {"coordinates":[0.10041,51.360043],"type":"Point"}
}
