{
  "type": "Feature",
  "properties": {
    "date:inception_lower": "2017-08-01",
    "date:inception_upper": "2017-08-01",
    "iso:country": "GB",
    "wof:name": "OX26 1DN",
    "wof:placetype": "postalcode"
  },
  "geometry": {"coordinates":[-1.176376,51.895879],"type":"Point"}
}
