{
  "type": "Feature",
  "properties": {
    "iso:country": "GB",
    "wof:name": "OX26 1DN",
    "wof:placetype": "postalcode"
  },
  "geometry": {"coordinates":[-1.176376,51.895879],"type":"Point"}
}
