{
  "type": "Feature",
  "properties": {
    "date:inception_lower": "1995-07-01",
    "date:inception_upper": "1995-07-01",
    "iso:country": "GB",
    "wof:name": "RG40 3NE",
    "wof:placetype": "postalcode"
  },
  "geometry": {"coordinates":[-0.827658,51.378599],"type":"Point"}
}
