{
  "type": "Feature",
  "properties": {
    "iso:country":"GB",
    "wof:name":"RG40 3NE",
    "wof:placetype":"postalcode"
},
  "geometry": {"coordinates":[-0.82771802184991,51.37861721186594],"type":"Point"}
}