{
  "type": "Feature",
  "properties": {
    "date:inception_lower": "1995-01-01",
    "date:inception_upper": "1995-01-01",
    "iso:country": "GB",
    "wof:name": "LL68 9RT",
    "wof:placetype": "postalcode"
  },
  "geometry": {"coordinates":[-4.360801,53.412912],"type":"Point"}
}
