{
  "type": "Feature",
  "properties": {
    "iso:country":"GB",
    "wof:name":"LE15 7JZ",
    "wof:placetype":"postalcode"
},
  "geometry": {"coordinates":[-0.74911519583353,52.69114338127667],"type":"Point"}
}