{
  "type": "Feature",
  "properties": {
    "iso:country":"GB",
    "wof:name":"SR6 7AS",
    "wof:placetype":"postalcode"
},
  "geometry": {"coordinates":[-1.36675008221001,54.95535755091341],"type":"Point"}
}