{
  "type": "Feature",
  "properties": {
    "iso:country": "GB",
    "wof:name": "CF47 0PG",
    "wof:placetype": "postalcode"
  },
  "geometry": {"coordinates":[-3.367996,51.743227],"type":"Point"}
}
