{
  "type": "Feature",
  "properties": {
    "iso:country":"GB",
    "wof:name":"CF47 0PG",
    "wof:placetype":"postalcode"
},
  "geometry": {"coordinates":[-3.36799592299765,51.74322653033386],"type":"Point"}
}