{
  "type": "Feature",
  "properties": {
    "date:inception_lower": "2001-06-01",
    "date:inception_upper": "2001-06-01",
    "iso:country": "GB",
    "wof:name": "CA7 9HP",
    "wof:placetype": "postalcode"
  },
  "geometry": {"coordinates":[-3.157323,54.824806],"type":"Point"}
}
