{
  "type": "Feature",
  "properties": {
    "date:inception_lower": "1980-01-01",
    "date:inception_upper": "1980-01-01",
    "iso:country": "GB",
    "wof:name": "DH8 9LJ",
    "wof:placetype": "postalcode"
  },
  "geometry": {"coordinates":[-1.875107,54.876397],"type":"Point"}
}
