{
  "type": "Feature",
  "properties": {
    "iso:country":"GB",
    "wof:name":"DH8 9LJ",
    "wof:placetype":"postalcode"
},
  "geometry": {"coordinates":[-1.87510715769019,54.87639704422595],"type":"Point"}
}