{
  "type": "Feature",
  "properties": {
    "iso:country":"GB",
    "wof:name":"BN15 8RQ",
    "wof:placetype":"postalcode"
},
  "geometry": {"coordinates":[-0.32935647717077,50.8195358840166],"type":"Point"}
}