{
  "type": "Feature",
  "properties": {
    "date:inception_lower":"1980-01-01",
    "date:inception_upper":"1980-01-31",
    "iso:country":"GB",
    "wof:name":"BN15 8RQ",
    "wof:placetype":"postalcode"
},
  "geometry": {"coordinates":[-0.329356,50.819536],"type":"Point"}
}