{
  "type": "Feature",
  "properties": {
    "iso:country":"GB",
    "wof:name":"NW3 3AT",
    "wof:placetype":"postalcode"
},
  "geometry": {"coordinates":[-0.15916131754945,51.54114973663125],"type":"Point"}
}