{
  "type": "Feature",
  "properties": {
    "iso:country":"GB",
    "wof:name":"NR21 9PD",
    "wof:placetype":"postalcode"
},
  "geometry": {"coordinates":[0.76606139706481,52.88578335008523],"type":"Point"}
}