{
  "type": "Feature",
  "properties": {
    "date:inception_lower": "1980-01-01",
    "date:inception_upper": "1980-01-01",
    "iso:country": "GB",
    "wof:name": "G11 5RG",
    "wof:placetype": "postalcode"
  },
  "geometry": {"coordinates":[-4.298665,55.871365],"type":"Point"}
}
