{
  "type": "Feature",
  "properties": {
    "iso:country": "GB",
    "wof:name": "G11 5RG",
    "wof:placetype": "postalcode"
  },
  "geometry": {"coordinates":[-4.298665,55.871365],"type":"Point"}
}
