{
  "type": "Feature",
  "properties": {
    "iso:country":"GB",
    "wof:name":"HX3 7DG",
    "wof:placetype":"postalcode"
},
  "geometry": {"coordinates":[-1.83278683579417,53.73539374320528],"type":"Point"}
}