{
  "type": "Feature",
  "properties": {
    "date:inception_lower": "2000-12-01",
    "date:inception_upper": "2000-12-01",
    "iso:country": "GB",
    "wof:name": "BA13 4JJ",
    "wof:placetype": "postalcode"
  },
  "geometry": {"coordinates":[-2.25385,51.228973],"type":"Point"}
}
