{
  "type": "Feature",
  "properties": {
    "date:inception_lower": "2005-01-01",
    "date:inception_upper": "2005-01-01",
    "iso:country": "GB",
    "wof:name": "BN3 3FH",
    "wof:placetype": "postalcode"
  },
  "geometry": {"coordinates":[-0.1616,50.830836],"type":"Point"}
}
