{
  "type": "Feature",
  "properties": {
    "iso:country":"GB",
    "wof:name":"L6 9BD",
    "wof:placetype":"postalcode"
},
  "geometry": {"coordinates":[-2.95524777637982,53.41450895809094],"type":"Point"}
}