{
  "type": "Feature",
  "properties": {
    "iso:country":"GB",
    "wof:name":"SW19 4HT",
    "wof:placetype":"postalcode"
},
  "geometry": {"coordinates":[-0.21838849668152,51.41879540776468],"type":"Point"}
}