{
  "type": "Feature",
  "properties": {
    "iso:country":"GB",
    "wof:name":"RH15 9BD",
    "wof:placetype":"postalcode"
},
  "geometry": {"coordinates":[-0.128925550365,50.95463193875789],"type":"Point"}
}