{
  "type": "Feature",
  "properties": {
    "iso:country": "GB",
    "wof:name": "OL16 2PR",
    "wof:placetype": "postalcode"
  },
  "geometry": {"coordinates":[-2.135045,53.631153],"type":"Point"}
}
