{
  "type": "Feature",
  "properties": {
    "date:inception_lower": "1980-01-01",
    "date:inception_upper": "1980-01-01",
    "iso:country": "GB",
    "wof:name": "EN9 3TE",
    "wof:placetype": "postalcode"
  },
  "geometry": {"coordinates":[0.055238,51.688957],"type":"Point"}
}
