{
  "type": "Feature",
  "properties": {
    "iso:country":"GB",
    "wof:name":"EN9 3TE",
    "wof:placetype":"postalcode"
},
  "geometry": {"coordinates":[0.05521113646682,51.68895345189794],"type":"Point"}
}