{
  "type": "Feature",
  "properties": {
    "iso:country": "GB",
    "wof:name": "G72 6WP",
    "wof:placetype": "postalcode"
  },
  "geometry": {"coordinates":[-4.126749,55.821114],"type":"Point"}
}
