{
  "type": "Feature",
  "properties": {
    "iso:country":"GB",
    "wof:name":"G72 6WP",
    "wof:placetype":"postalcode"
},
  "geometry": {"coordinates":[-4.126749236774,55.8211144992358],"type":"Point"}
}