{
  "type": "Feature",
  "properties": {
    "date:inception_lower":"1990-02-01",
    "date:inception_upper":"1990-02-28",
    "iso:country":"GB",
    "wof:name":"BH25 7DF",
    "wof:placetype":"postalcode"
},
  "geometry": {"coordinates":[-1.652568,50.74231],"type":"Point"}
}