{
  "type": "Feature",
  "properties": {
    "iso:country": "GB",
    "wof:name": "BH25 7DF",
    "wof:placetype": "postalcode"
  },
  "geometry": {"coordinates":[-1.652568,50.74231],"type":"Point"}
}
