{
  "type": "Feature",
  "properties": {
    "iso:country":"GB",
    "wof:name":"BH25 7DF",
    "wof:placetype":"postalcode"
},
  "geometry": {"coordinates":[-1.65256754882441,50.74230961513664],"type":"Point"}
}