{
  "type": "Feature",
  "properties": {
    "iso:country": "GB",
    "wof:name": "SS0 9QD",
    "wof:placetype": "postalcode"
  },
  "geometry": {"coordinates":[0.687159,51.549653],"type":"Point"}
}
