{
  "type": "Feature",
  "properties": {
    "iso:country":"GB",
    "wof:name":"SS0 9QD",
    "wof:placetype":"postalcode"
},
  "geometry": {"coordinates":[0.68715883847494,51.54965294841897],"type":"Point"}
}