{
  "type": "Feature",
  "properties": {
    "iso:country":"GB",
    "wof:name":"TA24 8TP",
    "wof:placetype":"postalcode"
},
  "geometry": {"coordinates":[-3.54877683292146,51.2102428117538],"type":"Point"}
}