{
  "type": "Feature",
  "properties": {
    "iso:country": "GB",
    "wof:name": "TA24 8TP",
    "wof:placetype": "postalcode"
  },
  "geometry": {"coordinates":[-3.548777,51.210243],"type":"Point"}
}
