{
  "type": "Feature",
  "properties": {
    "date:inception_lower": "1996-12-01",
    "date:inception_upper": "1996-12-01",
    "iso:country": "GB",
    "wof:name": "SK23 7NF",
    "wof:placetype": "postalcode"
  },
  "geometry": {"coordinates":[-1.975963,53.336686],"type":"Point"}
}
