{
  "type": "Feature",
  "properties": {
    "iso:country":"GB",
    "wof:name":"W1K 5LS",
    "wof:placetype":"postalcode"
},
  "geometry": {"coordinates":[-0.15017184365209,51.51353632125774],"type":"Point"}
}