{
  "type": "Feature",
  "properties": {
    "iso:country":"GB",
    "wof:name":"B67 5PU",
    "wof:placetype":"postalcode"
},
  "geometry": {"coordinates":[-1.98552690786127,52.47903543162428],"type":"Point"}
}