{
  "type": "Feature",
  "properties": {
    "date:inception_lower":"1980-01-01",
    "date:inception_upper":"1980-01-31",
    "iso:country":"GB",
    "wof:name":"B67 5PU",
    "wof:placetype":"postalcode"
},
  "geometry": {"coordinates":[-1.985527,52.479035],"type":"Point"}
}