{
  "type": "Feature",
  "properties": {
    "iso:country":"GB",
    "wof:name":"BB12 7PT",
    "wof:placetype":"postalcode"
},
  "geometry": {"coordinates":[-2.35649705053762,53.80745865407626],"type":"Point"}
}