{
  "type": "Feature",
  "properties": {
    "iso:country": "GB",
    "wof:name": "AL5 5SA",
    "wof:placetype": "postalcode"
  },
  "geometry": {"coordinates":[-0.33605,51.81528],"type":"Point"}
}
