{
  "type": "Feature",
  "properties": {
    "iso:country":"GB",
    "wof:name":"AL5 5SA",
    "wof:placetype":"postalcode"
},
  "geometry": {"coordinates":[-0.33604990160429,51.81528011196777],"type":"Point"}
}