{
  "type": "Feature",
  "properties": {
    "iso:country":"GB",
    "wof:name":"G83 9AH",
    "wof:placetype":"postalcode"
},
  "geometry": {"coordinates":[-4.57125975623094,55.98454661023678],"type":"Point"}
}