{
  "type": "Feature",
  "properties": {
    "iso:country":"GB",
    "wof:name":"SE2 0HF",
    "wof:placetype":"postalcode"
},
  "geometry": {"coordinates":[0.10480470785881,51.48680936335866],"type":"Point"}
}