{
  "type": "Feature",
  "properties": {
    "iso:country":"GB",
    "wof:name":"NG5 5HZ",
    "wof:placetype":"postalcode"
},
  "geometry": {"coordinates":[-1.16484663030394,52.99135120592268],"type":"Point"}
}