{
  "type": "Feature",
  "properties": {
    "iso:country": "GB",
    "wof:name": "SS8 8NL",
    "wof:placetype": "postalcode"
  },
  "geometry": {"coordinates":[0.614027,51.519289],"type":"Point"}
}
