{
  "type": "Feature",
  "properties": {
    "iso:country": "GB",
    "wof:name": "M43 7WR",
    "wof:placetype": "postalcode"
  },
  "geometry": {"coordinates":[-2.14413,53.488291],"type":"Point"}
}
