{
  "type": "Feature",
  "properties": {
    "iso:country": "GB",
    "wof:name": "B43 5JP",
    "wof:placetype": "postalcode"
  },
  "geometry": {"coordinates":[-1.94338,52.542501],"type":"Point"}
}
