{
  "type": "Feature",
  "properties": {
    "iso:country":"GB",
    "wof:name":"B43 5JP",
    "wof:placetype":"postalcode"
},
  "geometry": {"coordinates":[-1.9433799528295,52.54250063100415],"type":"Point"}
}