{
  "type": "Feature",
  "properties": {
    "iso:country": "GB",
    "wof:name": "WS3 3TZ",
    "wof:placetype": "postalcode"
  },
  "geometry": {"coordinates":[-2.013159,52.629272],"type":"Point"}
}
