{
  "type": "Feature",
  "properties": {
    "iso:country": "GB",
    "wof:name": "LE4 5LE",
    "wof:placetype": "postalcode"
  },
  "geometry": {"coordinates":[-1.123794,52.654535],"type":"Point"}
}
