{
  "type": "Feature",
  "properties": {
    "iso:country": "GB",
    "wof:name": "AB42 0SG",
    "wof:placetype": "postalcode"
  },
  "geometry": {"coordinates":[-1.885929,57.413537],"type":"Point"}
}
