{
  "type": "Feature",
  "properties": {
    "iso:country":"GB",
    "wof:name":"HA6 2TH",
    "wof:placetype":"postalcode"
},
  "geometry": {"coordinates":[-0.43854989249459,51.60882880765019],"type":"Point"}
}