{
  "type": "Feature",
  "properties": {
    "date:inception_lower": "1980-01-01",
    "date:inception_upper": "1980-01-01",
    "iso:country": "GB",
    "wof:name": "HA6 2TH",
    "wof:placetype": "postalcode"
  },
  "geometry": {"coordinates":[-0.43855,51.608829],"type":"Point"}
}
