{
  "type": "Feature",
  "properties": {
    "iso:country": "GB",
    "wof:name": "FK8 1PR",
    "wof:placetype": "postalcode"
  },
  "geometry": {"coordinates":[-3.947295,56.132473],"type":"Point"}
}
