{
  "type": "Feature",
  "properties": {
    "date:inception_lower": "1999-06-01",
    "date:inception_upper": "1999-06-01",
    "iso:country": "GB",
    "wof:name": "CH49 4QU",
    "wof:placetype": "postalcode"
  },
  "geometry": {"coordinates":[-3.092441,53.39308],"type":"Point"}
}
