{
  "type": "Feature",
  "properties": {
    "iso:country": "GB",
    "wof:name": "M23 9QD",
    "wof:placetype": "postalcode"
  },
  "geometry": {"coordinates":[-2.300578,53.406726],"type":"Point"}
}
