{
  "type": "Feature",
  "properties": {
    "date:inception_lower":"1980-01-01",
    "date:inception_upper":"1980-01-31",
    "iso:country":"GB",
    "wof:name":"TA8 1EF",
    "wof:placetype":"postalcode"
},
  "geometry": {"coordinates":[-2.995451,51.238129],"type":"Point"}
}