{
  "type": "Feature",
  "properties": {
    "iso:country": "GB",
    "wof:name": "CH65 8AH",
    "wof:placetype": "postalcode"
  },
  "geometry": {"coordinates":[-2.907456,53.278418],"type":"Point"}
}
