{
  "type": "Feature",
  "properties": {
    "iso:country":"GB",
    "wof:name":"G64 1RX",
    "wof:placetype":"postalcode"
},
  "geometry": {"coordinates":[-4.22646821554969,55.8969282761714],"type":"Point"}
}