{
  "type": "Feature",
  "properties": {
    "iso:country": "GB",
    "wof:name": "G64 1RX",
    "wof:placetype": "postalcode"
  },
  "geometry": {"coordinates":[-4.226771,55.896914],"type":"Point"}
}
