{
  "type": "Feature",
  "properties": {
    "iso:country": "GB",
    "wof:name": "CO13 0JZ",
    "wof:placetype": "postalcode"
  },
  "geometry": {"coordinates":[1.210335,51.844303],"type":"Point"}
}
