{
  "type": "Feature",
  "properties": {
    "iso:country":"GB",
    "wof:name":"CO13 0JZ",
    "wof:placetype":"postalcode"
},
  "geometry": {"coordinates":[1.21033521734707,51.84430270201228],"type":"Point"}
}