{
  "type": "Feature",
  "properties": {
    "date:inception_lower":"2003-11-01",
    "date:inception_upper":"2003-11-30",
    "iso:country":"GB",
    "wof:name":"CO13 0JZ",
    "wof:placetype":"postalcode"
},
  "geometry": {"coordinates":[1.210335,51.844303],"type":"Point"}
}