{
  "type": "Feature",
  "properties": {
    "iso:country":"GB",
    "wof:name":"LS6 2BX",
    "wof:placetype":"postalcode"
},
  "geometry": {"coordinates":[-1.57005026856818,53.81967695153283],"type":"Point"}
}