{
  "type": "Feature",
  "properties": {
    "iso:country":"GB",
    "wof:name":"PR7 1RZ",
    "wof:placetype":"postalcode"
},
  "geometry": {"coordinates":[-2.63451754976868,53.65395013303624],"type":"Point"}
}