{
  "type": "Feature",
  "properties": {
    "date:inception_lower": "1980-01-01",
    "date:inception_upper": "1980-01-01",
    "iso:country": "GB",
    "wof:name": "DH6 2EQ",
    "wof:placetype": "postalcode"
  },
  "geometry": {"coordinates":[-1.424456,54.774198],"type":"Point"}
}
