{
  "type": "Feature",
  "properties": {
    "iso:country":"GB",
    "wof:name":"SA73 2BY",
    "wof:placetype":"postalcode"
},
  "geometry": {"coordinates":[-5.03886171440231,51.71443230372986],"type":"Point"}
}