{
  "type": "Feature",
  "properties": {
    "iso:country":"GB",
    "wof:name":"SG12 9QZ",
    "wof:placetype":"postalcode"
},
  "geometry": {"coordinates":[-0.01793424726549,51.79696764586621],"type":"Point"}
}