{
  "type": "Feature",
  "properties": {
    "iso:country":"GB",
    "wof:name":"PL6 7TQ",
    "wof:placetype":"postalcode"
},
  "geometry": {"coordinates":[-4.09863205881737,50.43190506492624],"type":"Point"}
}