{
  "type": "Feature",
  "properties": {
    "iso:country":"GB",
    "wof:name":"RH2 0JN",
    "wof:placetype":"postalcode"
},
  "geometry": {"coordinates":[-0.20148382915832,51.24247828356852],"type":"Point"}
}