{
  "type": "Feature",
  "properties": {
    "date:inception_lower": "2012-03-01",
    "date:inception_upper": "2012-03-01",
    "iso:country": "GB",
    "wof:name": "RH2 0JN",
    "wof:placetype": "postalcode"
  },
  "geometry": {"coordinates":[-0.201484,51.242478],"type":"Point"}
}
