{
  "type": "Feature",
  "properties": {
    "iso:country":"GB",
    "wof:name":"G15 6SP",
    "wof:placetype":"postalcode"
},
  "geometry": {"coordinates":[-4.36938359788953,55.90260034728608],"type":"Point"}
}