{
  "type": "Feature",
  "properties": {
    "iso:country":"GB",
    "wof:name":"SE28 8EX",
    "wof:placetype":"postalcode"
},
  "geometry": {"coordinates":[0.12254805201407,51.50907953853557],"type":"Point"}
}