{
  "type": "Feature",
  "properties": {
    "iso:country": "GB",
    "wof:name": "LL32 8UA",
    "wof:placetype": "postalcode"
  },
  "geometry": {"coordinates":[-3.820758,53.263492],"type":"Point"}
}
