{
  "type": "Feature",
  "properties": {
    "iso:country":"GB",
    "wof:name":"LL32 8UA",
    "wof:placetype":"postalcode"
},
  "geometry": {"coordinates":[-3.82075816553974,53.26349222546114],"type":"Point"}
}