{
  "type": "Feature",
  "properties": {
    "iso:country":"GB",
    "wof:name":"EX4 4NT",
    "wof:placetype":"postalcode"
},
  "geometry": {"coordinates":[-3.5432993691691,50.72838264991164],"type":"Point"}
}