{
  "type": "Feature",
  "properties": {
    "iso:country": "GB",
    "wof:name": "S4 7QQ",
    "wof:placetype": "postalcode"
  },
  "geometry": {"coordinates":[-1.443225,53.398186],"type":"Point"}
}
