{
  "type": "Feature",
  "properties": {
    "date:inception_lower": "1993-01-01",
    "date:inception_upper": "1993-01-01",
    "iso:country": "GB",
    "wof:name": "S4 7QQ",
    "wof:placetype": "postalcode"
  },
  "geometry": {"coordinates":[-1.443225,53.398186],"type":"Point"}
}
