{
  "type": "Feature",
  "properties": {
    "iso:country":"GB",
    "wof:name":"S4 7QQ",
    "wof:placetype":"postalcode"
},
  "geometry": {"coordinates":[-1.44322552573606,53.3981855059898],"type":"Point"}
}