{
  "type": "Feature",
  "properties": {
    "iso:country":"GB",
    "wof:name":"B31 5QA",
    "wof:placetype":"postalcode"
},
  "geometry": {"coordinates":[-1.98673832642175,52.41523348292595],"type":"Point"}
}