{
  "type": "Feature",
  "properties": {
    "date:inception_lower": "1999-06-01",
    "date:inception_upper": "1999-06-01",
    "iso:country": "GB",
    "wof:name": "NR16 2SZ",
    "wof:placetype": "postalcode"
  },
  "geometry": {"coordinates":[0.931922,52.437415],"type":"Point"}
}
