{
  "type": "Feature",
  "properties": {
    "iso:country": "GB",
    "wof:name": "NR16 2SZ",
    "wof:placetype": "postalcode"
  },
  "geometry": {"coordinates":[0.931922,52.437415],"type":"Point"}
}
