{
  "type": "Feature",
  "properties": {
    "iso:country":"GB",
    "wof:name":"TW12 1DT",
    "wof:placetype":"postalcode"
},
  "geometry": {"coordinates":[-0.36474880404092,51.43225019406913],"type":"Point"}
}