{
  "type": "Feature",
  "properties": {
    "iso:country":"GB",
    "wof:name":"LE10 2DN",
    "wof:placetype":"postalcode"
},
  "geometry": {"coordinates":[-1.34861688781366,52.52589888252999],"type":"Point"}
}