{
  "type": "Feature",
  "properties": {
    "date:inception_lower": "1980-01-01",
    "date:inception_upper": "1980-01-01",
    "iso:country": "GB",
    "wof:name": "LE10 2DN",
    "wof:placetype": "postalcode"
  },
  "geometry": {"coordinates":[-1.348617,52.525899],"type":"Point"}
}
