{
  "type": "Feature",
  "properties": {
    "iso:country":"GB",
    "wof:name":"CF47 8LP",
    "wof:placetype":"postalcode"
},
  "geometry": {"coordinates":[-3.38090131414885,51.74892016081983],"type":"Point"}
}