{
  "type": "Feature",
  "properties": {
    "iso:country": "GB",
    "wof:name": "NW6 4TG",
    "wof:placetype": "postalcode"
  },
  "geometry": {"coordinates":[-0.181444,51.541443],"type":"Point"}
}
