{
  "type": "Feature",
  "properties": {
    "date:inception_lower": "1980-01-01",
    "date:inception_upper": "1980-01-01",
    "iso:country": "GB",
    "wof:name": "NW6 4TG",
    "wof:placetype": "postalcode"
  },
  "geometry": {"coordinates":[-0.181444,51.541443],"type":"Point"}
}
