{
  "type": "Feature",
  "properties": {
    "iso:country":"GB",
    "wof:name":"TW12 1SW",
    "wof:placetype":"postalcode"
},
  "geometry": {"coordinates":[-0.36298825346965,51.42676724304395],"type":"Point"}
}