{
  "type": "Feature",
  "properties": {
    "iso:country": "GB",
    "wof:name": "TW12 1SW",
    "wof:placetype": "postalcode"
  },
  "geometry": {"coordinates":[-0.362995,51.426992],"type":"Point"}
}
