{
  "type": "Feature",
  "properties": {
    "iso:country":"GB",
    "wof:name":"TF2 6HR",
    "wof:placetype":"postalcode"
},
  "geometry": {"coordinates":[-2.46119325825883,52.69953883538555],"type":"Point"}
}