{
  "type": "Feature",
  "properties": {
    "iso:country": "GB",
    "wof:name": "HU11 5QL",
    "wof:placetype": "postalcode"
  },
  "geometry": {"coordinates":[-0.253055,53.898284],"type":"Point"}
}
