{
  "type": "Feature",
  "properties": {
    "date:inception_lower":"1980-01-01",
    "date:inception_upper":"1980-01-31",
    "iso:country":"GB",
    "wof:name":"HU11 5QL",
    "wof:placetype":"postalcode"
},
  "geometry": {"coordinates":[-0.253055,53.898284],"type":"Point"}
}