{
  "type": "Feature",
  "properties": {
    "iso:country":"GB",
    "wof:name":"HU11 5QL",
    "wof:placetype":"postalcode"
},
  "geometry": {"coordinates":[-0.25305512440782,53.89828439452371],"type":"Point"}
}