{
  "type": "Feature",
  "properties": {
    "iso:country":"GB",
    "wof:name":"HG2 8PG",
    "wof:placetype":"postalcode"
},
  "geometry": {"coordinates":[-1.50766341044657,53.98825692570184],"type":"Point"}
}