{
  "type": "Feature",
  "properties": {
    "iso:country":"GB",
    "wof:name":"PO30 5UB",
    "wof:placetype":"postalcode"
},
  "geometry": {"coordinates":[-1.3286039538823,50.72898874426609],"type":"Point"}
}