{
  "type": "Feature",
  "properties": {
    "iso:country":"GB",
    "wof:name":"DN21 3NR",
    "wof:placetype":"postalcode"
},
  "geometry": {"coordinates":[-0.71685984558245,53.43495647908169],"type":"Point"}
}