{
  "type": "Feature",
  "properties": {
    "iso:country": "GB",
    "wof:name": "RG2 7LR",
    "wof:placetype": "postalcode"
  },
  "geometry": {"coordinates":[-0.952022,51.434547],"type":"Point"}
}
