{
  "type": "Feature",
  "properties": {
    "iso:country":"GB",
    "wof:name":"RG2 7LR",
    "wof:placetype":"postalcode"
},
  "geometry": {"coordinates":[-0.9520222418131,51.43454656012847],"type":"Point"}
}