{
  "type": "Feature",
  "properties": {
    "date:inception_lower": "2000-12-01",
    "date:inception_upper": "2000-12-01",
    "iso:country": "GB",
    "wof:name": "RG2 7LR",
    "wof:placetype": "postalcode"
  },
  "geometry": {"coordinates":[-0.952022,51.434547],"type":"Point"}
}
