{
  "type": "Feature",
  "properties": {
    "date:inception_lower": "2022-04-01",
    "date:inception_upper": "2022-04-01",
    "iso:country": "GB",
    "wof:name": "DY8 9JJ",
    "wof:placetype": "postalcode"
  },
  "geometry": {"coordinates":[-2.145216,52.457008],"type":"Point"}
}
