{
  "type": "Feature",
  "properties": {
    "date:inception_lower": "1980-01-01",
    "date:inception_upper": "1980-01-01",
    "iso:country": "GB",
    "wof:name": "MK14 6JR",
    "wof:placetype": "postalcode"
  },
  "geometry": {"coordinates":[-0.74661,52.05821],"type":"Point"}
}
