{
  "type": "Feature",
  "properties": {
    "iso:country":"GB",
    "wof:name":"MK14 6JR",
    "wof:placetype":"postalcode"
},
  "geometry": {"coordinates":[-0.746609658475,52.05821008389046],"type":"Point"}
}