{
  "type": "Feature",
  "properties": {
    "iso:country":"GB",
    "wof:name":"BS8 2BZ",
    "wof:placetype":"postalcode"
},
  "geometry": {"coordinates":[-2.61435601489327,51.46204751434144],"type":"Point"}
}