{
  "type": "Feature",
  "properties": {
    "iso:country":"GB",
    "wof:name":"CB4 3DG",
    "wof:placetype":"postalcode"
},
  "geometry": {"coordinates":[0.11701080907066,52.21366797424268],"type":"Point"}
}