{
  "type": "Feature",
  "properties": {
    "iso:country":"GB",
    "wof:name":"LL61 5NX",
    "wof:placetype":"postalcode"
},
  "geometry": {"coordinates":[-4.19723100681559,53.22152472025202],"type":"Point"}
}