{
  "type": "Feature",
  "properties": {
    "iso:country": "GB",
    "wof:name": "NG22 9PB",
    "wof:placetype": "postalcode"
  },
  "geometry": {"coordinates":[-0.979655,53.230391],"type":"Point"}
}
