{
  "type": "Feature",
  "properties": {
    "iso:country":"GB",
    "wof:name":"NG22 9PB",
    "wof:placetype":"postalcode"
},
  "geometry": {"coordinates":[-0.97965497452809,53.23039084101553],"type":"Point"}
}