{
  "type": "Feature",
  "properties": {
    "iso:country": "GB",
    "wof:name": "BS15 1AT",
    "wof:placetype": "postalcode"
  },
  "geometry": {"coordinates":[-2.516857,51.462788],"type":"Point"}
}
