{
  "type": "Feature",
  "properties": {
    "iso:country":"GB",
    "wof:name":"PL29 3RA",
    "wof:placetype":"postalcode"
},
  "geometry": {"coordinates":[-4.83193974314027,50.59307481530058],"type":"Point"}
}