{
  "type": "Feature",
  "properties": {
    "iso:country":"GB",
    "wof:name":"DA1 1AE",
    "wof:placetype":"postalcode"
},
  "geometry": {"coordinates":[0.2260025369404,51.44273536369965],"type":"Point"}
}