{
  "type": "Feature",
  "properties": {
    "iso:country": "GB",
    "wof:name": "L27 7BR",
    "wof:placetype": "postalcode"
  },
  "geometry": {"coordinates":[-2.846729,53.38971],"type":"Point"}
}
