{
  "type": "Feature",
  "properties": {
    "iso:country": "GB",
    "wof:name": "MK43 9QN",
    "wof:placetype": "postalcode"
  },
  "geometry": {"coordinates":[-0.535199,52.08657],"type":"Point"}
}
