{
  "type": "Feature",
  "properties": {
    "iso:country": "GB",
    "wof:name": "IP11 0GA",
    "wof:placetype": "postalcode"
  },
  "geometry": {"coordinates":[1.309415,51.99392],"type":"Point"}
}
