{
  "type": "Feature",
  "properties": {
    "iso:country":"GB",
    "wof:name":"IP11 0GA",
    "wof:placetype":"postalcode"
},
  "geometry": {"coordinates":[1.30941540550735,51.99391956110766],"type":"Point"}
}