{
  "type": "Feature",
  "properties": {
    "date:inception_lower": "1998-06-01",
    "date:inception_upper": "1998-06-01",
    "iso:country": "GB",
    "wof:name": "LL24 0UJ",
    "wof:placetype": "postalcode"
  },
  "geometry": {"coordinates":[-3.805625,53.039615],"type":"Point"}
}
