{
  "type": "Feature",
  "properties": {
    "date:inception_lower": "1980-01-01",
    "date:inception_upper": "1980-01-01",
    "iso:country": "GB",
    "wof:name": "SE12 9HD",
    "wof:placetype": "postalcode"
  },
  "geometry": {"coordinates":[0.023204,51.43794],"type":"Point"}
}
