{
  "type": "Feature",
  "properties": {
    "iso:country":"GB",
    "wof:name":"SE12 9HD",
    "wof:placetype":"postalcode"
},
  "geometry": {"coordinates":[0.02320353348488,51.43794023732944],"type":"Point"}
}