{
  "type": "Feature",
  "properties": {
    "iso:country": "GB",
    "wof:name": "SE12 9HD",
    "wof:placetype": "postalcode"
  },
  "geometry": {"coordinates":[0.023204,51.43794],"type":"Point"}
}
