{
  "type": "Feature",
  "properties": {
    "iso:country":"GB",
    "wof:name":"HR1 3SA",
    "wof:placetype":"postalcode"
},
  "geometry": {"coordinates":[-2.635124533164,52.08316391939861],"type":"Point"}
}