{
  "type": "Feature",
  "properties": {
    "date:inception_lower": "1980-01-01",
    "date:inception_upper": "1980-01-01",
    "iso:country": "GB",
    "wof:name": "NG2 2JG",
    "wof:placetype": "postalcode"
  },
  "geometry": {"coordinates":[-1.147343,52.943574],"type":"Point"}
}
