{
  "type": "Feature",
  "properties": {
    "iso:country":"GB",
    "wof:name":"NG2 2JG",
    "wof:placetype":"postalcode"
},
  "geometry": {"coordinates":[-1.14734350857838,52.94357374921366],"type":"Point"}
}