{
  "type": "Feature",
  "properties": {
    "date:inception_lower": "2022-03-01",
    "date:inception_upper": "2022-03-01",
    "iso:country": "GB",
    "wof:name": "BR1 3FA",
    "wof:placetype": "postalcode"
  },
  "geometry": {"coordinates":[0.011586,51.408725],"type":"Point"}
}
