{
  "type": "Feature",
  "properties": {
    "iso:country":"GB",
    "wof:name":"NW10 5AH",
    "wof:placetype":"postalcode"
},
  "geometry": {"coordinates":[-0.23103434976364,51.53482777696548],"type":"Point"}
}