{
  "type": "Feature",
  "properties": {
    "iso:country":"GB",
    "wof:name":"N19 4AS",
    "wof:placetype":"postalcode"
},
  "geometry": {"coordinates":[-0.12990822403994,51.56630659585598],"type":"Point"}
}