{
  "type": "Feature",
  "properties": {
    "date:inception_lower": "1987-04-01",
    "date:inception_upper": "1987-04-01",
    "iso:country": "GB",
    "wof:name": "E7 0EG",
    "wof:placetype": "postalcode"
  },
  "geometry": {"coordinates":[0.024775,51.552759],"type":"Point"}
}
