{
  "type": "Feature",
  "properties": {
    "iso:country": "GB",
    "wof:name": "E7 0EG",
    "wof:placetype": "postalcode"
  },
  "geometry": {"coordinates":[0.024775,51.552759],"type":"Point"}
}
