{
  "type": "Feature",
  "properties": {
    "date:inception_lower": "2023-05-01",
    "date:inception_upper": "2023-05-01",
    "iso:country": "GB",
    "wof:name": "NG14 5JW",
    "wof:placetype": "postalcode"
  },
  "geometry": {"coordinates":[-1.058035,52.965582],"type":"Point"}
}
