{
  "type": "Feature",
  "properties": {
    "iso:country": "GB",
    "wof:name": "EH41 3DP",
    "wof:placetype": "postalcode"
  },
  "geometry": {"coordinates":[-2.808554,55.953074],"type":"Point"}
}
