{
  "type": "Feature",
  "properties": {
    "date:inception_lower": "1980-01-01",
    "date:inception_upper": "1980-01-01",
    "iso:country": "GB",
    "wof:name": "WA1 4QL",
    "wof:placetype": "postalcode"
  },
  "geometry": {"coordinates":[-2.534322,53.403328],"type":"Point"}
}
