{
  "type": "Feature",
  "properties": {
    "iso:country":"GB",
    "wof:name":"WA1 4QL",
    "wof:placetype":"postalcode"
},
  "geometry": {"coordinates":[-2.53432212396831,53.40332832367755],"type":"Point"}
}