{
  "type": "Feature",
  "properties": {
    "iso:country": "GB",
    "wof:name": "RM18 8ED",
    "wof:placetype": "postalcode"
  },
  "geometry": {"coordinates":[0.369573,51.45958],"type":"Point"}
}
