{
  "type": "Feature",
  "properties": {
    "date:inception_lower": "2013-03-01",
    "date:inception_upper": "2013-03-01",
    "iso:country": "GB",
    "wof:name": "SY16 2NJ",
    "wof:placetype": "postalcode"
  },
  "geometry": {"coordinates":[-3.315027,52.520049],"type":"Point"}
}
