{
  "type": "Feature",
  "properties": {
    "iso:country":"GB",
    "wof:name":"SY16 2NJ",
    "wof:placetype":"postalcode"
},
  "geometry": {"coordinates":[-3.31502671624894,52.52004865270454],"type":"Point"}
}