{
  "type": "Feature",
  "properties": {
    "iso:country":"GB",
    "wof:name":"SO41 0HZ",
    "wof:placetype":"postalcode"
},
  "geometry": {"coordinates":[-1.62305731082975,50.75506854903296],"type":"Point"}
}