{
  "type": "Feature",
  "properties": {
    "date:inception_lower": "1980-01-01",
    "date:inception_upper": "1980-01-01",
    "iso:country": "GB",
    "wof:name": "MK42 8AH",
    "wof:placetype": "postalcode"
  },
  "geometry": {"coordinates":[-0.48189,52.125017],"type":"Point"}
}
