{
  "type": "Feature",
  "properties": {
    "iso:country":"GB",
    "wof:name":"L36 7XL",
    "wof:placetype":"postalcode"
},
  "geometry": {"coordinates":[-2.83943267617117,53.41702438864589],"type":"Point"}
}