{
  "type": "Feature",
  "properties": {
    "iso:country":"GB",
    "wof:name":"MK40 3PW",
    "wof:placetype":"postalcode"
},
  "geometry": {"coordinates":[-0.45791085705916,52.13558243253274],"type":"Point"}
}