{
  "type": "Feature",
  "properties": {
    "iso:country":"GB",
    "wof:name":"KY10 3TB",
    "wof:placetype":"postalcode"
},
  "geometry": {"coordinates":[-2.62740579867418,56.26009049666774],"type":"Point"}
}