{
  "type": "Feature",
  "properties": {
    "iso:country":"GB",
    "wof:name":"WF3 4JG",
    "wof:placetype":"postalcode"
},
  "geometry": {"coordinates":[-1.485707109109,53.71364500551513],"type":"Point"}
}