{
  "type": "Feature",
  "properties": {
    "date:inception_lower": "1997-06-01",
    "date:inception_upper": "1997-06-01",
    "iso:country": "GB",
    "wof:name": "WF3 4JG",
    "wof:placetype": "postalcode"
  },
  "geometry": {"coordinates":[-1.485707,53.713645],"type":"Point"}
}
