{
  "type": "Feature",
  "properties": {
    "iso:country": "GB",
    "wof:name": "MK17 8JB",
    "wof:placetype": "postalcode"
  },
  "geometry": {"coordinates":[-0.631397,52.0178],"type":"Point"}
}
