{
  "type": "Feature",
  "properties": {
    "date:inception_lower":"1981-06-01",
    "date:inception_upper":"1981-06-30",
    "iso:country":"GB",
    "wof:name":"MK17 8JB",
    "wof:placetype":"postalcode"
},
  "geometry": {"coordinates":[-0.631397,52.0178],"type":"Point"}
}