{
  "type": "Feature",
  "properties": {
    "iso:country":"GB",
    "wof:name":"MK17 8JB",
    "wof:placetype":"postalcode"
},
  "geometry": {"coordinates":[-0.63139527830108,52.0181042942837],"type":"Point"}
}