{
  "type": "Feature",
  "properties": {
    "iso:country":"GB",
    "wof:name":"WS11 0LR",
    "wof:placetype":"postalcode"
},
  "geometry": {"coordinates":[-2.03264189646706,52.67466795727915],"type":"Point"}
}