{
  "type": "Feature",
  "properties": {
    "date:inception_lower":"2010-08-01",
    "date:inception_upper":"2010-08-31",
    "iso:country":"GB",
    "wof:name":"WS11 0LR",
    "wof:placetype":"postalcode"
},
  "geometry": {"coordinates":[-2.033109,52.674891],"type":"Point"}
}