{
  "type": "Feature",
  "properties": {
    "iso:country": "GB",
    "wof:name": "WS11 0LR",
    "wof:placetype": "postalcode"
  },
  "geometry": {"coordinates":[-2.033109,52.674891],"type":"Point"}
}
