{
  "type": "Feature",
  "properties": {
    "iso:country":"GB",
    "wof:name":"HX1 3BA",
    "wof:placetype":"postalcode"
},
  "geometry": {"coordinates":[-1.87771977759594,53.71411022923588],"type":"Point"}
}