{
  "type": "Feature",
  "properties": {
    "iso:country":"GB",
    "wof:name":"HX5 9QH",
    "wof:placetype":"postalcode"
},
  "geometry": {"coordinates":[-1.82139824467784,53.68618546856305],"type":"Point"}
}