{
  "type": "Feature",
  "properties": {
    "iso:country":"GB",
    "wof:name":"RH17 7HP",
    "wof:placetype":"postalcode"
},
  "geometry": {"coordinates":[-0.00251298680338,51.03235419443374],"type":"Point"}
}