{
  "type": "Feature",
  "properties": {
    "iso:country": "GB",
    "wof:name": "SO45 3PA",
    "wof:placetype": "postalcode"
  },
  "geometry": {"coordinates":[-1.395378,50.849082],"type":"Point"}
}
