{
  "type": "Feature",
  "properties": {
    "iso:country": "GB",
    "wof:name": "TS25 3DP",
    "wof:placetype": "postalcode"
  },
  "geometry": {"coordinates":[-1.225323,54.656755],"type":"Point"}
}
