{
  "type": "Feature",
  "properties": {
    "iso:country":"GB",
    "wof:name":"TS25 3DP",
    "wof:placetype":"postalcode"
},
  "geometry": {"coordinates":[-1.22532283969521,54.65675520314058],"type":"Point"}
}