{
  "type": "Feature",
  "properties": {
    "iso:country": "GB",
    "wof:name": "DE11 8GF",
    "wof:placetype": "postalcode"
  },
  "geometry": {"coordinates":[-1.538989,52.769058],"type":"Point"}
}
