{
  "type": "Feature",
  "properties": {
    "date:inception_lower":"1990-07-01",
    "date:inception_upper":"1990-07-31",
    "iso:country":"GB",
    "wof:name":"LE7 9UR",
    "wof:placetype":"postalcode"
},
  "geometry": {"coordinates":[-1.046761,52.641534],"type":"Point"}
}