{
  "type": "Feature",
  "properties": {
    "iso:country":"GB",
    "wof:name":"LS26 0RS",
    "wof:placetype":"postalcode"
},
  "geometry": {"coordinates":[-1.50279985143794,53.758478100109],"type":"Point"}
}