{
  "type": "Feature",
  "properties": {
    "iso:country":"GB",
    "wof:name":"WN2 5PZ",
    "wof:placetype":"postalcode"
},
  "geometry": {"coordinates":[-2.59014985003187,53.51479372357712],"type":"Point"}
}