{
  "type": "Feature",
  "properties": {
    "date:inception_lower": "1980-11-01",
    "date:inception_upper": "1980-11-01",
    "iso:country": "GB",
    "wof:name": "KA21 5RP",
    "wof:placetype": "postalcode"
  },
  "geometry": {"coordinates":[-4.775619,55.641367],"type":"Point"}
}
