{
  "type": "Feature",
  "properties": {
    "iso:country":"GB",
    "wof:name":"KA21 5RP",
    "wof:placetype":"postalcode"
},
  "geometry": {"coordinates":[-4.77561944418628,55.64136746355466],"type":"Point"}
}