{
  "type": "Feature",
  "properties": {
    "date:inception_lower": "2019-08-01",
    "date:inception_upper": "2019-08-01",
    "iso:country": "GB",
    "wof:name": "GU6 9DY",
    "wof:placetype": "postalcode"
  },
  "geometry": {"coordinates":[-0.488362,51.141255],"type":"Point"}
}
