{
  "type": "Feature",
  "properties": {
    "iso:country":"GB",
    "wof:name":"BN44 3DE",
    "wof:placetype":"postalcode"
},
  "geometry": {"coordinates":[-0.37544252798996,50.91022638876136],"type":"Point"}
}