{
  "type": "Feature",
  "properties": {
    "iso:country": "GB",
    "wof:name": "BN44 3DE",
    "wof:placetype": "postalcode"
  },
  "geometry": {"coordinates":[-0.375489,50.910212],"type":"Point"}
}
