{
  "type": "Feature",
  "properties": {
    "date:inception_lower": "1990-07-01",
    "date:inception_upper": "1990-07-01",
    "iso:country": "GB",
    "wof:name": "BN44 3DE",
    "wof:placetype": "postalcode"
  },
  "geometry": {"coordinates":[-0.375489,50.910212],"type":"Point"}
}
