{
  "type": "Feature",
  "properties": {
    "iso:country": "GB",
    "wof:name": "BN11 2AG",
    "wof:placetype": "postalcode"
  },
  "geometry": {"coordinates":[-0.356981,50.820027],"type":"Point"}
}
