{
  "type": "Feature",
  "properties": {
    "iso:country":"GB",
    "wof:name":"BN11 2AG",
    "wof:placetype":"postalcode"
},
  "geometry": {"coordinates":[-0.35698072722367,50.82002709958012],"type":"Point"}
}