{
  "type": "Feature",
  "properties": {
    "date:inception_lower":"1980-01-01",
    "date:inception_upper":"1980-01-31",
    "iso:country":"GB",
    "wof:name":"BR8 7QL",
    "wof:placetype":"postalcode"
},
  "geometry": {"coordinates":[0.155688,51.400856],"type":"Point"}
}