{
  "type": "Feature",
  "properties": {
    "iso:country": "GB",
    "wof:name": "BR8 7QL",
    "wof:placetype": "postalcode"
  },
  "geometry": {"coordinates":[0.155503,51.400905],"type":"Point"}
}
