{
  "type": "Feature",
  "properties": {
    "iso:country":"GB",
    "wof:name":"BR8 7QL",
    "wof:placetype":"postalcode"
},
  "geometry": {"coordinates":[0.15566172291983,51.40085686857989],"type":"Point"}
}