{
  "type": "Feature",
  "properties": {
    "iso:country": "GB",
    "wof:name": "DN34 5SX",
    "wof:placetype": "postalcode"
  },
  "geometry": {"coordinates":[-0.123888,53.55388],"type":"Point"}
}
