{
  "type": "Feature",
  "properties": {
    "iso:country":"GB",
    "wof:name":"TN23 1EP",
    "wof:placetype":"postalcode"
},
  "geometry": {"coordinates":[0.85665265587386,51.15160380440734],"type":"Point"}
}