{
  "type": "Feature",
  "properties": {
    "iso:country": "GB",
    "wof:name": "TN23 1EP",
    "wof:placetype": "postalcode"
  },
  "geometry": {"coordinates":[0.856684,51.151621],"type":"Point"}
}
