{
  "type": "Feature",
  "properties": {
    "date:inception_lower":"1980-01-01",
    "date:inception_upper":"1980-01-31",
    "iso:country":"GB",
    "wof:name":"NG17 8EL",
    "wof:placetype":"postalcode"
},
  "geometry": {"coordinates":[-1.254352,53.101166],"type":"Point"}
}