{
  "type": "Feature",
  "properties": {
    "iso:country":"GB",
    "wof:name":"SP10 3RP",
    "wof:placetype":"postalcode"
},
  "geometry": {"coordinates":[-1.48671681920339,51.21194374842015],"type":"Point"}
}