{
  "type": "Feature",
  "properties": {
    "iso:country":"GB",
    "wof:name":"NG3 5UP",
    "wof:placetype":"postalcode"
},
  "geometry": {"coordinates":[-1.10005871200051,52.99335972484792],"type":"Point"}
}