{
  "type": "Feature",
  "properties": {
    "iso:country":"GB",
    "wof:name":"BD19 3EY",
    "wof:placetype":"postalcode"
},
  "geometry": {"coordinates":[-1.72143748596918,53.72462590378974],"type":"Point"}
}