{
  "type": "Feature",
  "properties": {
    "date:inception_lower":"1980-01-01",
    "date:inception_upper":"1980-01-31",
    "iso:country":"GB",
    "wof:name":"IP28 6AP",
    "wof:placetype":"postalcode"
},
  "geometry": {"coordinates":[0.518864,52.335236],"type":"Point"}
}