{
  "type": "Feature",
  "properties": {
    "iso:country": "GB",
    "wof:name": "IP28 6AP",
    "wof:placetype": "postalcode"
  },
  "geometry": {"coordinates":[0.518864,52.335236],"type":"Point"}
}
