{
  "type": "Feature",
  "properties": {
    "iso:country":"GB",
    "wof:name":"SN1 4EZ",
    "wof:placetype":"postalcode"
},
  "geometry": {"coordinates":[-1.78354818895877,51.54741233040123],"type":"Point"}
}