{
  "type": "Feature",
  "properties": {
    "iso:country":"GB",
    "wof:name":"BS3 5QP",
    "wof:placetype":"postalcode"
},
  "geometry": {"coordinates":[-2.60215974024468,51.43110757530852],"type":"Point"}
}