{
  "type": "Feature",
  "properties": {
    "iso:country":"GB",
    "wof:name":"E1W 3XQ",
    "wof:placetype":"postalcode"
},
  "geometry": {"coordinates":[-0.05575898205698,51.50503997176156],"type":"Point"}
}