{
  "type": "Feature",
  "properties": {
    "date:inception_lower": "1980-01-01",
    "date:inception_upper": "1980-01-01",
    "iso:country": "GB",
    "wof:name": "TF4 3QN",
    "wof:placetype": "postalcode"
  },
  "geometry": {"coordinates":[-2.471608,52.6473],"type":"Point"}
}
