{
  "type": "Feature",
  "properties": {
    "iso:country":"GB",
    "wof:name":"TF4 3QN",
    "wof:placetype":"postalcode"
},
  "geometry": {"coordinates":[-2.47174248893815,52.64723094312923],"type":"Point"}
}