{
  "type": "Feature",
  "properties": {
    "iso:country": "GB",
    "wof:name": "TA24 5DA",
    "wof:placetype": "postalcode"
  },
  "geometry": {"coordinates":[-3.469819,51.203877],"type":"Point"}
}
