{
  "type": "Feature",
  "properties": {
    "iso:country":"GB",
    "wof:name":"DY8 3LE",
    "wof:placetype":"postalcode"
},
  "geometry": {"coordinates":[-2.17302289103843,52.44989868005474],"type":"Point"}
}