{
  "type": "Feature",
  "properties": {
    "date:inception_lower":"1980-01-01",
    "date:inception_upper":"1980-01-31",
    "iso:country":"GB",
    "wof:name":"DY8 3LE",
    "wof:placetype":"postalcode"
},
  "geometry": {"coordinates":[-2.173023,52.449899],"type":"Point"}
}