{
  "type": "Feature",
  "properties": {
    "iso:country": "GB",
    "wof:name": "DY8 3LE",
    "wof:placetype": "postalcode"
  },
  "geometry": {"coordinates":[-2.173032,52.449895],"type":"Point"}
}
