{
  "type": "Feature",
  "properties": {
    "iso:country":"GB",
    "wof:name":"TQ4 6NP",
    "wof:placetype":"postalcode"
},
  "geometry": {"coordinates":[-3.56160010988317,50.41476782740988],"type":"Point"}
}