{
  "type": "Feature",
  "properties": {
    "date:inception_lower": "2013-03-01",
    "date:inception_upper": "2013-03-01",
    "iso:country": "GB",
    "wof:name": "KY6 2LW",
    "wof:placetype": "postalcode"
  },
  "geometry": {"coordinates":[-3.196671,56.19194],"type":"Point"}
}
