{
  "type": "Feature",
  "properties": {
    "iso:country": "GB",
    "wof:name": "KY6 2LW",
    "wof:placetype": "postalcode"
  },
  "geometry": {"coordinates":[-3.196671,56.191948],"type":"Point"}
}
