{
  "type": "Feature",
  "properties": {
    "date:inception_lower": "2022-11-01",
    "date:inception_upper": "2022-11-01",
    "iso:country": "GB",
    "wof:name": "LN6 9XN",
    "wof:placetype": "postalcode"
  },
  "geometry": {"coordinates":[-0.668437,53.154482],"type":"Point"}
}
