{
  "type": "Feature",
  "properties": {
    "iso:country":"GB",
    "wof:name":"CV6 1JA",
    "wof:placetype":"postalcode"
},
  "geometry": {"coordinates":[-1.52640520526258,52.42308815397266],"type":"Point"}
}