{
  "type": "Feature",
  "properties": {
    "iso:country": "GB",
    "wof:name": "BN22 0EZ",
    "wof:placetype": "postalcode"
  },
  "geometry": {"coordinates":[0.260457,50.797069],"type":"Point"}
}
