{
  "type": "Feature",
  "properties": {
    "iso:country":"GB",
    "wof:name":"DN14 7YE",
    "wof:placetype":"postalcode"
},
  "geometry": {"coordinates":[-0.79050364639637,53.70897785848912],"type":"Point"}
}