{
  "type": "Feature",
  "properties": {
    "date:inception_lower":"1980-01-01",
    "date:inception_upper":"1980-01-31",
    "iso:country":"GB",
    "wof:name":"RG21 3DN",
    "wof:placetype":"postalcode"
},
  "geometry": {"coordinates":[-1.08787,51.257983],"type":"Point"}
}