{
  "type": "Feature",
  "properties": {
    "iso:country": "GB",
    "wof:name": "LA11 6HF",
    "wof:placetype": "postalcode"
  },
  "geometry": {"coordinates":[-2.948293,54.20408],"type":"Point"}
}
