{
  "type": "Feature",
  "properties": {
    "iso:country":"GB",
    "wof:name":"HR2 0JE",
    "wof:placetype":"postalcode"
},
  "geometry": {"coordinates":[-2.89711934839641,51.95927383212566],"type":"Point"}
}