{
  "type": "Feature",
  "properties": {
    "iso:country":"GB",
    "wof:name":"TQ12 3SU",
    "wof:placetype":"postalcode"
},
  "geometry": {"coordinates":[-3.58950938966574,50.54240608862052],"type":"Point"}
}