{
  "type": "Feature",
  "properties": {
    "iso:country": "GB",
    "wof:name": "IG7 5QS",
    "wof:placetype": "postalcode"
  },
  "geometry": {"coordinates":[0.071722,51.605941],"type":"Point"}
}
