{
  "type": "Feature",
  "properties": {
    "iso:country":"GB",
    "wof:name":"IG7 5QS",
    "wof:placetype":"postalcode"
},
  "geometry": {"coordinates":[0.07172172335677,51.60594059741157],"type":"Point"}
}