{
  "type": "Feature",
  "properties": {
    "iso:country":"GB",
    "wof:name":"CM8 2TT",
    "wof:placetype":"postalcode"
},
  "geometry": {"coordinates":[0.63980304478304,51.8013472956092],"type":"Point"}
}