{
  "type": "Feature",
  "properties": {
    "iso:country":"GB",
    "wof:name":"DL8 4JS",
    "wof:placetype":"postalcode"
},
  "geometry": {"coordinates":[-1.97344201675744,54.2794211253754],"type":"Point"}
}