{
  "type": "Feature",
  "properties": {
    "date:inception_lower": "1997-06-01",
    "date:inception_upper": "1997-06-01",
    "iso:country": "GB",
    "wof:name": "S35 4LE",
    "wof:placetype": "postalcode"
  },
  "geometry": {"coordinates":[-1.492846,53.476095],"type":"Point"}
}
