{
  "type": "Feature",
  "properties": {
    "iso:country": "GB",
    "wof:name": "S35 4LE",
    "wof:placetype": "postalcode"
  },
  "geometry": {"coordinates":[-1.492846,53.476095],"type":"Point"}
}
