{
  "type": "Feature",
  "properties": {
    "iso:country":"GB",
    "wof:name":"S35 4LE",
    "wof:placetype":"postalcode"
},
  "geometry": {"coordinates":[-1.49284630552073,53.47609494417551],"type":"Point"}
}