{
  "type": "Feature",
  "properties": {
    "iso:country": "GB",
    "wof:name": "WA4 4AS",
    "wof:placetype": "postalcode"
  },
  "geometry": {"coordinates":[-2.633073,53.338933],"type":"Point"}
}
