{
  "type": "Feature",
  "properties": {
    "iso:country":"GB",
    "wof:name":"WA4 4AS",
    "wof:placetype":"postalcode"
},
  "geometry": {"coordinates":[-2.63289409330764,53.33895426497423],"type":"Point"}
}