{
  "type": "Feature",
  "properties": {
    "date:inception_lower": "2014-10-01",
    "date:inception_upper": "2014-10-01",
    "iso:country": "GB",
    "wof:name": "WA4 4AS",
    "wof:placetype": "postalcode"
  },
  "geometry": {"coordinates":[-2.633073,53.338933],"type":"Point"}
}
