{
  "type": "Feature",
  "properties": {
    "date:inception_lower": "2015-09-01",
    "date:inception_upper": "2015-09-01",
    "iso:country": "GB",
    "wof:name": "BB2 1RF",
    "wof:placetype": "postalcode"
  },
  "geometry": {"coordinates":[-2.49083,53.742986],"type":"Point"}
}
