{
  "type": "Feature",
  "properties": {
    "iso:country":"GB",
    "wof:name":"BB2 1RF",
    "wof:placetype":"postalcode"
},
  "geometry": {"coordinates":[-2.49234414204045,53.74389026979581],"type":"Point"}
}