{
  "type": "Feature",
  "properties": {
    "date:inception_lower": "1980-01-01",
    "date:inception_upper": "1980-01-01",
    "iso:country": "GB",
    "wof:name": "TN21 8SB",
    "wof:placetype": "postalcode"
  },
  "geometry": {"coordinates":[0.283115,50.97869],"type":"Point"}
}
