{
  "type": "Feature",
  "properties": {
    "iso:country":"GB",
    "wof:name":"TN21 8SB",
    "wof:placetype":"postalcode"
},
  "geometry": {"coordinates":[0.2831150079796,50.97869026279946],"type":"Point"}
}