{
  "type": "Feature",
  "properties": {
    "iso:country":"GB",
    "wof:name":"SA62 6SH",
    "wof:placetype":"postalcode"
},
  "geometry": {"coordinates":[-5.26775150201165,51.87882694312253],"type":"Point"}
}