{
  "type": "Feature",
  "properties": {
    "iso:country":"GB",
    "wof:name":"SG6 4DB",
    "wof:placetype":"postalcode"
},
  "geometry": {"coordinates":[-0.23831805139391,51.98004417347548],"type":"Point"}
}