{
  "type": "Feature",
  "properties": {
    "iso:country":"GB",
    "wof:name":"SA1 6JN",
    "wof:placetype":"postalcode"
},
  "geometry": {"coordinates":[-3.95735779680082,51.62226467846748],"type":"Point"}
}