{
  "type": "Feature",
  "properties": {
    "iso:country":"GB",
    "wof:name":"GU32 2ED",
    "wof:placetype":"postalcode"
},
  "geometry": {"coordinates":[-0.94300706857146,51.0109770277342],"type":"Point"}
}