{
  "type": "Feature",
  "properties": {
    "date:inception_lower": "1990-07-01",
    "date:inception_upper": "1990-07-01",
    "iso:country": "GB",
    "wof:name": "CV12 9NZ",
    "wof:placetype": "postalcode"
  },
  "geometry": {"coordinates":[-1.466292,52.477735],"type":"Point"}
}
