{
  "type": "Feature",
  "properties": {
    "date:inception_lower": "2014-04-01",
    "date:inception_upper": "2014-04-01",
    "iso:country": "GB",
    "wof:name": "B45 8GX",
    "wof:placetype": "postalcode"
  },
  "geometry": {"coordinates":[-1.986836,52.382303],"type":"Point"}
}
