{
  "type": "Feature",
  "properties": {
    "iso:country":"GB",
    "wof:name":"B45 8GX",
    "wof:placetype":"postalcode"
},
  "geometry": {"coordinates":[-1.98683614788835,52.38230282254862],"type":"Point"}
}