{
  "type": "Feature",
  "properties": {
    "date:inception_lower":"1983-07-01",
    "date:inception_upper":"1983-07-31",
    "iso:country":"GB",
    "wof:name":"BA1 5DB",
    "wof:placetype":"postalcode"
},
  "geometry": {"coordinates":[-2.355674,51.389887],"type":"Point"}
}