{
  "type": "Feature",
  "properties": {
    "iso:country":"GB",
    "wof:name":"BA1 5DB",
    "wof:placetype":"postalcode"
},
  "geometry": {"coordinates":[-2.35569033986406,51.3898812955835],"type":"Point"}
}