{
  "type": "Feature",
  "properties": {
    "iso:country":"GB",
    "wof:name":"SA14 8RF",
    "wof:placetype":"postalcode"
},
  "geometry": {"coordinates":[-4.12447210309085,51.68545429082551],"type":"Point"}
}