{
  "type": "Feature",
  "properties": {
    "date:inception_lower": "1980-01-01",
    "date:inception_upper": "1980-01-01",
    "iso:country": "GB",
    "wof:name": "SA14 8RF",
    "wof:placetype": "postalcode"
  },
  "geometry": {"coordinates":[-4.124472,51.685454],"type":"Point"}
}
