{
  "type": "Feature",
  "properties": {
    "date:inception_lower": "1980-01-01",
    "date:inception_upper": "1980-01-01",
    "iso:country": "GB",
    "wof:name": "SA19 7UY",
    "wof:placetype": "postalcode"
  },
  "geometry": {"coordinates":[-3.967855,51.951844],"type":"Point"}
}
