{
  "type": "Feature",
  "properties": {
    "iso:country": "GB",
    "wof:name": "SA19 7UY",
    "wof:placetype": "postalcode"
  },
  "geometry": {"coordinates":[-3.967855,51.951844],"type":"Point"}
}
