{
  "type": "Feature",
  "properties": {
    "iso:country":"GB",
    "wof:name":"BN3 8ES",
    "wof:placetype":"postalcode"
},
  "geometry": {"coordinates":[-0.19722603921142,50.85302989315911],"type":"Point"}
}