{
  "type": "Feature",
  "properties": {
    "iso:country": "GB",
    "wof:name": "BN11 3SB",
    "wof:placetype": "postalcode"
  },
  "geometry": {"coordinates":[-0.383265,50.80918],"type":"Point"}
}
