{
  "type": "Feature",
  "properties": {
    "iso:country":"GB",
    "wof:name":"BN11 3SB",
    "wof:placetype":"postalcode"
},
  "geometry": {"coordinates":[-0.38326495152111,50.8091797087277],"type":"Point"}
}