{
  "type": "Feature",
  "properties": {
    "iso:country":"GB",
    "wof:name":"CB10 2TE",
    "wof:placetype":"postalcode"
},
  "geometry": {"coordinates":[0.33989978368976,52.00926986661675],"type":"Point"}
}