{
  "type": "Feature",
  "properties": {
    "iso:country":"GB",
    "wof:name":"IP7 7HQ",
    "wof:placetype":"postalcode"
},
  "geometry": {"coordinates":[0.91565623821595,52.09613822764719],"type":"Point"}
}