{
  "type": "Feature",
  "properties": {
    "date:inception_lower": "1999-06-01",
    "date:inception_upper": "1999-06-01",
    "iso:country": "GB",
    "wof:name": "MK18 5HZ",
    "wof:placetype": "postalcode"
  },
  "geometry": {"coordinates":[-0.969078,52.034942],"type":"Point"}
}
