{
  "type": "Feature",
  "properties": {
    "iso:country": "GB",
    "wof:name": "MK18 5HZ",
    "wof:placetype": "postalcode"
  },
  "geometry": {"coordinates":[-0.969078,52.034942],"type":"Point"}
}
