{
  "type": "Feature",
  "properties": {
    "iso:country":"GB",
    "wof:name":"MK18 5HZ",
    "wof:placetype":"postalcode"
},
  "geometry": {"coordinates":[-0.96912576846134,52.03492170527742],"type":"Point"}
}