{
  "type": "Feature",
  "properties": {
    "iso:country":"GB",
    "wof:name":"LE4 7AN",
    "wof:placetype":"postalcode"
},
  "geometry": {"coordinates":[-1.1150925525683,52.6586594918958],"type":"Point"}
}