{
  "type": "Feature",
  "properties": {
    "iso:country":"GB",
    "wof:name":"KT11 2AQ",
    "wof:placetype":"postalcode"
},
  "geometry": {"coordinates":[-0.40811448991041,51.32976711452839],"type":"Point"}
}