{
  "type": "Feature",
  "properties": {
    "iso:country":"GB",
    "wof:name":"G23 5JD",
    "wof:placetype":"postalcode"
},
  "geometry": {"coordinates":[-4.29096699291948,55.90460621086045],"type":"Point"}
}