{
  "type": "Feature",
  "properties": {
    "iso:country": "GB",
    "wof:name": "G23 5JD",
    "wof:placetype": "postalcode"
  },
  "geometry": {"coordinates":[-4.290967,55.904606],"type":"Point"}
}
