{
  "type": "Feature",
  "properties": {
    "iso:country":"GB",
    "wof:name":"HU12 9HU",
    "wof:placetype":"postalcode"
},
  "geometry": {"coordinates":[-0.13622487052816,53.72571136243887],"type":"Point"}
}