{
  "type": "Feature",
  "properties": {
    "iso:country": "GB",
    "wof:name": "DY8 4RT",
    "wof:placetype": "postalcode"
  },
  "geometry": {"coordinates":[-2.170385,52.465631],"type":"Point"}
}
