{
  "type": "Feature",
  "properties": {
    "iso:country":"GB",
    "wof:name":"TA6 6JU",
    "wof:placetype":"postalcode"
},
  "geometry": {"coordinates":[-3.01096675045504,51.11725651593525],"type":"Point"}
}