{
  "type": "Feature",
  "properties": {
    "iso:country": "GB",
    "wof:name": "TA6 6JU",
    "wof:placetype": "postalcode"
  },
  "geometry": {"coordinates":[-3.011018,51.117287],"type":"Point"}
}
