{
  "type": "Feature",
  "properties": {
    "date:inception_lower": "1990-02-01",
    "date:inception_upper": "1990-02-01",
    "iso:country": "GB",
    "wof:name": "NE28 8UE",
    "wof:placetype": "postalcode"
  },
  "geometry": {"coordinates":[-1.557367,55.000512],"type":"Point"}
}
