{
  "type": "Feature",
  "properties": {
    "iso:country":"GB",
    "wof:name":"YO21 3QB",
    "wof:placetype":"postalcode"
},
  "geometry": {"coordinates":[-0.61534893795986,54.48849044538115],"type":"Point"}
}