{
  "type": "Feature",
  "properties": {
    "iso:country":"GB",
    "wof:name":"ST7 2DG",
    "wof:placetype":"postalcode"
},
  "geometry": {"coordinates":[-2.28934542770477,53.09878772118697],"type":"Point"}
}