{
  "type": "Feature",
  "properties": {
    "iso:country": "GB",
    "wof:name": "SW18 5ES",
    "wof:placetype": "postalcode"
  },
  "geometry": {"coordinates":[-0.20213,51.442413],"type":"Point"}
}
