{
  "type": "Feature",
  "properties": {
    "iso:country":"GB",
    "wof:name":"SW18 5ES",
    "wof:placetype":"postalcode"
},
  "geometry": {"coordinates":[-0.20213023529373,51.44241336922574],"type":"Point"}
}