{
  "type": "Feature",
  "properties": {
    "iso:country":"GB",
    "wof:name":"N4 2SX",
    "wof:placetype":"postalcode"
},
  "geometry": {"coordinates":[-0.09692623725504,51.56175666287215],"type":"Point"}
}