{
  "type": "Feature",
  "properties": {
    "date:inception_lower":"1980-01-01",
    "date:inception_upper":"1980-01-31",
    "iso:country":"GB",
    "wof:name":"NR13 5LG",
    "wof:placetype":"postalcode"
},
  "geometry": {"coordinates":[1.436465,52.624241],"type":"Point"}
}