{
  "type": "Feature",
  "properties": {
    "iso:country":"GB",
    "wof:name":"NR13 5LG",
    "wof:placetype":"postalcode"
},
  "geometry": {"coordinates":[1.43646513341999,52.62424098633031],"type":"Point"}
}