{
  "type": "Feature",
  "properties": {
    "iso:country": "GB",
    "wof:name": "NR13 5LG",
    "wof:placetype": "postalcode"
  },
  "geometry": {"coordinates":[1.436465,52.624241],"type":"Point"}
}
