{
  "type": "Feature",
  "properties": {
    "date:inception_lower":"1980-01-01",
    "date:inception_upper":"1980-01-31",
    "iso:country":"GB",
    "wof:name":"LL19 9HB",
    "wof:placetype":"postalcode"
},
  "geometry": {"coordinates":[-3.395883,53.332835],"type":"Point"}
}