{
  "type": "Feature",
  "properties": {
    "iso:country":"GB",
    "wof:name":"LL19 9HB",
    "wof:placetype":"postalcode"
},
  "geometry": {"coordinates":[-3.39588325834477,53.33283461726739],"type":"Point"}
}