{
  "type": "Feature",
  "properties": {
    "iso:country":"GB",
    "wof:name":"MK43 0XB",
    "wof:placetype":"postalcode"
},
  "geometry": {"coordinates":[-0.6049717019718,52.00882105359519],"type":"Point"}
}