{
  "type": "Feature",
  "properties": {
    "iso:country": "GB",
    "wof:name": "HA8 9BY",
    "wof:placetype": "postalcode"
  },
  "geometry": {"coordinates":[-0.256514,51.61096],"type":"Point"}
}
