{
  "type": "Feature",
  "properties": {
    "iso:country":"GB",
    "wof:name":"HA8 9BY",
    "wof:placetype":"postalcode"
},
  "geometry": {"coordinates":[-0.25651420288754,51.61096030021274],"type":"Point"}
}