{
  "type": "Feature",
  "properties": {
    "iso:country":"GB",
    "wof:name":"N21 1NG",
    "wof:placetype":"postalcode"
},
  "geometry": {"coordinates":[-0.11321152241947,51.64021772886684],"type":"Point"}
}