{
  "type": "Feature",
  "properties": {
    "iso:country":"GB",
    "wof:name":"TF10 8AA",
    "wof:placetype":"postalcode"
},
  "geometry": {"coordinates":[-2.38236521609073,52.77911682546134],"type":"Point"}
}