{
  "type": "Feature",
  "properties": {
    "date:inception_lower": "1980-01-01",
    "date:inception_upper": "1980-01-01",
    "iso:country": "GB",
    "wof:name": "TF10 8AA",
    "wof:placetype": "postalcode"
  },
  "geometry": {"coordinates":[-2.382365,52.779117],"type":"Point"}
}
