{
  "type": "Feature",
  "properties": {
    "iso:country": "GB",
    "wof:name": "PO7 7HZ",
    "wof:placetype": "postalcode"
  },
  "geometry": {"coordinates":[-1.048325,50.88872],"type":"Point"}
}
