{
  "type": "Feature",
  "properties": {
    "iso:country":"GB",
    "wof:name":"LL30 3AZ",
    "wof:placetype":"postalcode"
},
  "geometry": {"coordinates":[-3.77096167948883,53.31385806338365],"type":"Point"}
}