{
  "type": "Feature",
  "properties": {
    "iso:country": "GB",
    "wof:name": "LL30 3AZ",
    "wof:placetype": "postalcode"
  },
  "geometry": {"coordinates":[-3.770962,53.313858],"type":"Point"}
}
