{
  "type": "Feature",
  "properties": {
    "iso:country": "GB",
    "wof:name": "EX20 3NN",
    "wof:placetype": "postalcode"
  },
  "geometry": {"coordinates":[-4.122891,50.772771],"type":"Point"}
}
