{
  "type": "Feature",
  "properties": {
    "iso:country":"GB",
    "wof:name":"EX20 3NN",
    "wof:placetype":"postalcode"
},
  "geometry": {"coordinates":[-4.12289056996826,50.77277097680344],"type":"Point"}
}