{
  "type": "Feature",
  "properties": {
    "iso:country": "GB",
    "wof:name": "SS6 9DJ",
    "wof:placetype": "postalcode"
  },
  "geometry": {"coordinates":[0.592636,51.596406],"type":"Point"}
}
