{
  "type": "Feature",
  "properties": {
    "iso:country":"GB",
    "wof:name":"SS6 9DJ",
    "wof:placetype":"postalcode"
},
  "geometry": {"coordinates":[0.59263552253908,51.59640609194694],"type":"Point"}
}