{
  "type": "Feature",
  "properties": {
    "iso:country": "GB",
    "wof:name": "SY21 8EN",
    "wof:placetype": "postalcode"
  },
  "geometry": {"coordinates":[-3.0249,52.70833],"type":"Point"}
}
