{
  "type": "Feature",
  "properties": {
    "iso:country":"GB",
    "wof:name":"SY21 8EN",
    "wof:placetype":"postalcode"
},
  "geometry": {"coordinates":[-3.02490026538681,52.70832985534573],"type":"Point"}
}