{
  "type": "Feature",
  "properties": {
    "iso:country": "GB",
    "wof:name": "YO7 2NW",
    "wof:placetype": "postalcode"
  },
  "geometry": {"coordinates":[-1.349817,54.253047],"type":"Point"}
}
