{
  "type": "Feature",
  "properties": {
    "date:inception_lower": "2015-10-01",
    "date:inception_upper": "2015-10-01",
    "iso:country": "GB",
    "wof:name": "YO7 2NW",
    "wof:placetype": "postalcode"
  },
  "geometry": {"coordinates":[-1.349817,54.253047],"type":"Point"}
}
