{
  "type": "Feature",
  "properties": {
    "iso:country":"GB",
    "wof:name":"YO7 2NW",
    "wof:placetype":"postalcode"
},
  "geometry": {"coordinates":[-1.34740664892002,54.25311501378783],"type":"Point"}
}