{
  "type": "Feature",
  "properties": {
    "date:inception_lower":"1980-01-01",
    "date:inception_upper":"1980-01-31",
    "iso:country":"GB",
    "wof:name":"L12 0HF",
    "wof:placetype":"postalcode"
},
  "geometry": {"coordinates":[-2.902052,53.443184],"type":"Point"}
}