{
  "type": "Feature",
  "properties": {
    "iso:country":"GB",
    "wof:name":"WD19 4PN",
    "wof:placetype":"postalcode"
},
  "geometry": {"coordinates":[-0.38586352704254,51.64594590213974],"type":"Point"}
}