{
  "type": "Feature",
  "properties": {
    "iso:country":"GB",
    "wof:name":"IP28 7AF",
    "wof:placetype":"postalcode"
},
  "geometry": {"coordinates":[0.51164667878953,52.34873485430545],"type":"Point"}
}