{
  "type": "Feature",
  "properties": {
    "iso:country": "GB",
    "wof:name": "WD25 0EJ",
    "wof:placetype": "postalcode"
  },
  "geometry": {"coordinates":[-0.410788,51.685032],"type":"Point"}
}
