{
  "type": "Feature",
  "properties": {
    "iso:country":"GB",
    "wof:name":"SM5 2SU",
    "wof:placetype":"postalcode"
},
  "geometry": {"coordinates":[-0.17090200659,51.37762406264446],"type":"Point"}
}