{
  "type": "Feature",
  "properties": {
    "iso:country":"GB",
    "wof:name":"IG11 8HJ",
    "wof:placetype":"postalcode"
},
  "geometry": {"coordinates":[0.07912779763478,51.53884104215962],"type":"Point"}
}