{
  "type": "Feature",
  "properties": {
    "iso:country":"GB",
    "wof:name":"TF9 4AL",
    "wof:placetype":"postalcode"
},
  "geometry": {"coordinates":[-2.43345011467446,52.94130848702471],"type":"Point"}
}