{
  "type": "Feature",
  "properties": {
    "date:inception_lower":"1980-01-01",
    "date:inception_upper":"1980-01-31",
    "iso:country":"GB",
    "wof:name":"TF9 4AL",
    "wof:placetype":"postalcode"
},
  "geometry": {"coordinates":[-2.43345,52.941308],"type":"Point"}
}