{
  "type": "Feature",
  "properties": {
    "iso:country": "GB",
    "wof:name": "TF9 4AL",
    "wof:placetype": "postalcode"
  },
  "geometry": {"coordinates":[-2.43345,52.941308],"type":"Point"}
}
