{
  "type": "Feature",
  "properties": {
    "date:inception_lower": "2002-06-01",
    "date:inception_upper": "2002-06-01",
    "iso:country": "GB",
    "wof:name": "PO1 2AE",
    "wof:placetype": "postalcode"
  },
  "geometry": {"coordinates":[-1.102777,50.790229],"type":"Point"}
}
