{
  "type": "Feature",
  "properties": {
    "iso:country":"GB",
    "wof:name":"BH12 3HF",
    "wof:placetype":"postalcode"
},
  "geometry": {"coordinates":[-1.94713030826661,50.73966707398765],"type":"Point"}
}