{
  "type": "Feature",
  "properties": {
    "iso:country":"GB",
    "wof:name":"LL55 3AD",
    "wof:placetype":"postalcode"
},
  "geometry": {"coordinates":[-4.17811605658512,53.17311024758455],"type":"Point"}
}