{
  "type": "Feature",
  "properties": {
    "iso:country": "GB",
    "wof:name": "DL3 9SQ",
    "wof:placetype": "postalcode"
  },
  "geometry": {"coordinates":[-1.595963,54.53852],"type":"Point"}
}
