{
  "type": "Feature",
  "properties": {
    "iso:country":"GB",
    "wof:name":"DL3 9SQ",
    "wof:placetype":"postalcode"
},
  "geometry": {"coordinates":[-1.59596329451243,54.53852043797112],"type":"Point"}
}