{
  "type": "Feature",
  "properties": {
    "iso:country":"GB",
    "wof:name":"B11 3AJ",
    "wof:placetype":"postalcode"
},
  "geometry": {"coordinates":[-1.85782868746643,52.44664115487173],"type":"Point"}
}