{
  "type": "Feature",
  "properties": {
    "iso:country":"GB",
    "wof:name":"RH20 1PY",
    "wof:placetype":"postalcode"
},
  "geometry": {"coordinates":[-0.60338936781585,50.9377351373027],"type":"Point"}
}