{
  "type": "Feature",
  "properties": {
    "date:inception_lower": "1980-01-01",
    "date:inception_upper": "1980-01-01",
    "iso:country": "GB",
    "wof:name": "RH20 1PY",
    "wof:placetype": "postalcode"
  },
  "geometry": {"coordinates":[-0.603389,50.937735],"type":"Point"}
}
