{
  "type": "Feature",
  "properties": {
    "iso:country":"GB",
    "wof:name":"WN5 8AE",
    "wof:placetype":"postalcode"
},
  "geometry": {"coordinates":[-2.6788561157293,53.53660537210817],"type":"Point"}
}