{
  "type": "Feature",
  "properties": {
    "iso:country":"GB",
    "wof:name":"AB21 0XP",
    "wof:placetype":"postalcode"
},
  "geometry": {"coordinates":[-2.28354554255945,57.20167553791812],"type":"Point"}
}