{
  "type": "Feature",
  "properties": {
    "iso:country": "GB",
    "wof:name": "AB21 0XP",
    "wof:placetype": "postalcode"
  },
  "geometry": {"coordinates":[-2.283545,57.201676],"type":"Point"}
}
