{
  "type": "Feature",
  "properties": {
    "iso:country":"GB",
    "wof:name":"N7 0RX",
    "wof:placetype":"postalcode"
},
  "geometry": {"coordinates":[-0.11931781861331,51.55650640306023],"type":"Point"}
}