{
  "type": "Feature",
  "properties": {
    "iso:country": "GB",
    "wof:name": "LE12 5PR",
    "wof:placetype": "postalcode"
  },
  "geometry": {"coordinates":[-1.260683,52.793552],"type":"Point"}
}
