{
  "type": "Feature",
  "properties": {
    "iso:country":"GB",
    "wof:name":"RG27 9DB",
    "wof:placetype":"postalcode"
},
  "geometry": {"coordinates":[-0.95690686727843,51.29381136250771],"type":"Point"}
}