{
  "type": "Feature",
  "properties": {
    "iso:country": "GB",
    "wof:name": "RG27 9DB",
    "wof:placetype": "postalcode"
  },
  "geometry": {"coordinates":[-0.956907,51.293811],"type":"Point"}
}
