{
  "type": "Feature",
  "properties": {
    "date:inception_lower": "1980-01-01",
    "date:inception_upper": "1980-01-01",
    "iso:country": "GB",
    "wof:name": "RG27 9DB",
    "wof:placetype": "postalcode"
  },
  "geometry": {"coordinates":[-0.956907,51.293811],"type":"Point"}
}
