{
  "type": "Feature",
  "properties": {
    "iso:country":"GB",
    "wof:name":"BS23 4LL",
    "wof:placetype":"postalcode"
},
  "geometry": {"coordinates":[-2.96801048518833,51.33113007912656],"type":"Point"}
}