{
  "type": "Feature",
  "properties": {
    "date:inception_lower":"1980-01-01",
    "date:inception_upper":"1980-01-31",
    "iso:country":"GB",
    "wof:name":"BS23 4LL",
    "wof:placetype":"postalcode"
},
  "geometry": {"coordinates":[-2.968031,51.331135],"type":"Point"}
}