{
  "type": "Feature",
  "properties": {
    "iso:country":"GB",
    "wof:name":"LA1 2BW",
    "wof:placetype":"postalcode"
},
  "geometry": {"coordinates":[-2.79887200429169,54.05897795518285],"type":"Point"}
}