{
  "type": "Feature",
  "properties": {
    "iso:country":"GB",
    "wof:name":"NG3 2BB",
    "wof:placetype":"postalcode"
},
  "geometry": {"coordinates":[-1.12981197683417,52.95698493431084],"type":"Point"}
}