{
  "type": "Feature",
  "properties": {
    "iso:country": "GB",
    "wof:name": "NG3 2BB",
    "wof:placetype": "postalcode"
  },
  "geometry": {"coordinates":[-1.129719,52.957049],"type":"Point"}
}
