{
  "type": "Feature",
  "properties": {
    "iso:country":"GB",
    "wof:name":"TN3 9SB",
    "wof:placetype":"postalcode"
},
  "geometry": {"coordinates":[0.18299500577904,51.11168545547077],"type":"Point"}
}