{
  "type": "Feature",
  "properties": {
    "iso:country":"GB",
    "wof:name":"BB11 4JF",
    "wof:placetype":"postalcode"
},
  "geometry": {"coordinates":[-2.2542735344667,53.78550084437888],"type":"Point"}
}