{
  "type": "Feature",
  "properties": {
    "iso:country": "GB",
    "wof:name": "BB11 4JF",
    "wof:placetype": "postalcode"
  },
  "geometry": {"coordinates":[-2.254273,53.785501],"type":"Point"}
}
