{
  "type": "Feature",
  "properties": {
    "iso:country":"GB",
    "wof:name":"DG6 4DL",
    "wof:placetype":"postalcode"
},
  "geometry": {"coordinates":[-4.05495564392953,54.83493714569878],"type":"Point"}
}