{
  "type": "Feature",
  "properties": {
    "date:inception_lower":"1980-01-01",
    "date:inception_upper":"1980-01-31",
    "iso:country":"GB",
    "wof:name":"SM5 1QU",
    "wof:placetype":"postalcode"
},
  "geometry": {"coordinates":[-0.180541,51.380598],"type":"Point"}
}