{
  "type": "Feature",
  "properties": {
    "iso:country":"GB",
    "wof:name":"SM5 1QU",
    "wof:placetype":"postalcode"
},
  "geometry": {"coordinates":[-0.18054085312928,51.38059783673209],"type":"Point"}
}