{
  "type": "Feature",
  "properties": {
    "iso:country": "GB",
    "wof:name": "OX27 8BH",
    "wof:placetype": "postalcode"
  },
  "geometry": {"coordinates":[-1.161021,51.921305],"type":"Point"}
}
