{
  "type": "Feature",
  "properties": {
    "date:inception_lower": "1998-06-01",
    "date:inception_upper": "1998-06-01",
    "iso:country": "GB",
    "wof:name": "EH49 7TT",
    "wof:placetype": "postalcode"
  },
  "geometry": {"coordinates":[-3.53055,55.984657],"type":"Point"}
}
