{
  "type": "Feature",
  "properties": {
    "iso:country":"GB",
    "wof:name":"CM9 4AR",
    "wof:placetype":"postalcode"
},
  "geometry": {"coordinates":[0.69492630529592,51.7434829210295],"type":"Point"}
}