{
  "type": "Feature",
  "properties": {
    "iso:country":"GB",
    "wof:name":"WS8 6AB",
    "wof:placetype":"postalcode"
},
  "geometry": {"coordinates":[-1.92978106380783,52.64697264787018],"type":"Point"}
}