{
  "type": "Feature",
  "properties": {
    "iso:country":"GB",
    "wof:name":"SP3 5AY",
    "wof:placetype":"postalcode"
},
  "geometry": {"coordinates":[-2.0412296972441,51.09144401457203],"type":"Point"}
}