{
  "type": "Feature",
  "properties": {
    "date:inception_lower": "2018-10-01",
    "date:inception_upper": "2018-10-01",
    "iso:country": "GB",
    "wof:name": "LE14 4HL",
    "wof:placetype": "postalcode"
  },
  "geometry": {"coordinates":[-0.852338,52.872206],"type":"Point"}
}
