{
  "type": "Feature",
  "properties": {
    "iso:country":"GB",
    "wof:name":"SA37 0HR",
    "wof:placetype":"postalcode"
},
  "geometry": {"coordinates":[-4.62273256002626,52.01402633345895],"type":"Point"}
}