{
  "type": "Feature",
  "properties": {
    "iso:country": "GB",
    "wof:name": "SA37 0HR",
    "wof:placetype": "postalcode"
  },
  "geometry": {"coordinates":[-4.622733,52.014026],"type":"Point"}
}
