{
  "type": "Feature",
  "properties": {
    "iso:country":"GB",
    "wof:name":"KY8 4DY",
    "wof:placetype":"postalcode"
},
  "geometry": {"coordinates":[-3.00324453797323,56.20045242484018],"type":"Point"}
}