{
  "type": "Feature",
  "properties": {
    "iso:country": "GB",
    "wof:name": "B23 6QJ",
    "wof:placetype": "postalcode"
  },
  "geometry": {"coordinates":[-1.832974,52.529595],"type":"Point"}
}
