{
  "type": "Feature",
  "properties": {
    "date:inception_lower": "1984-02-01",
    "date:inception_upper": "1984-02-01",
    "iso:country": "GB",
    "wof:name": "SA62 5QW",
    "wof:placetype": "postalcode"
  },
  "geometry": {"coordinates":[-4.939068,51.869028],"type":"Point"}
}
