{
  "type": "Feature",
  "properties": {
    "iso:country": "GB",
    "wof:name": "EH22 4BW",
    "wof:placetype": "postalcode"
  },
  "geometry": {"coordinates":[-3.057984,55.870949],"type":"Point"}
}
