{
  "type": "Feature",
  "properties": {
    "iso:country":"GB",
    "wof:name":"EH22 4BW",
    "wof:placetype":"postalcode"
},
  "geometry": {"coordinates":[-3.05798391291209,55.87094912397279],"type":"Point"}
}