{
  "type": "Feature",
  "properties": {
    "iso:country":"GB",
    "wof:name":"SP1 2AJ",
    "wof:placetype":"postalcode"
},
  "geometry": {"coordinates":[-1.79323538536073,51.0687887125537],"type":"Point"}
}