{
  "type": "Feature",
  "properties": {
    "iso:country": "GB",
    "wof:name": "SE21 8HG",
    "wof:placetype": "postalcode"
  },
  "geometry": {"coordinates":[-0.093442,51.440481],"type":"Point"}
}
