{
  "type": "Feature",
  "properties": {
    "iso:country": "GB",
    "wof:name": "L3 5PE",
    "wof:placetype": "postalcode"
  },
  "geometry": {"coordinates":[-2.973703,53.408354],"type":"Point"}
}
