{
  "type": "Feature",
  "properties": {
    "date:inception_lower": "2022-04-01",
    "date:inception_upper": "2022-04-01",
    "iso:country": "GB",
    "wof:name": "SA19 0BA",
    "wof:placetype": "postalcode"
  },
  "geometry": {"coordinates":[-3.988484,51.891421],"type":"Point"}
}
