{
  "type": "Feature",
  "properties": {
    "iso:country": "GB",
    "wof:name": "SY15 6DF",
    "wof:placetype": "postalcode"
  },
  "geometry": {"coordinates":[-3.042224,52.568715],"type":"Point"}
}
