{
  "type": "Feature",
  "properties": {
    "iso:country":"GB",
    "wof:name":"L20 3PJ",
    "wof:placetype":"postalcode"
},
  "geometry": {"coordinates":[-2.98710532891513,53.44984583395431],"type":"Point"}
}