{
  "type": "Feature",
  "properties": {
    "iso:country":"GB",
    "wof:name":"KA7 2RH",
    "wof:placetype":"postalcode"
},
  "geometry": {"coordinates":[-4.62813773871518,55.45196153199741],"type":"Point"}
}