{
  "type": "Feature",
  "properties": {
    "iso:country":"GB",
    "wof:name":"HX3 8XN",
    "wof:placetype":"postalcode"
},
  "geometry": {"coordinates":[-1.78622566535645,53.72184671015623],"type":"Point"}
}