{
  "type": "Feature",
  "properties": {
    "iso:country":"GB",
    "wof:name":"NW9 0JY",
    "wof:placetype":"postalcode"
},
  "geometry": {"coordinates":[-0.26410340136927,51.59071432395468],"type":"Point"}
}