{
  "type": "Feature",
  "properties": {
    "iso:country":"GB",
    "wof:name":"S81 0PD",
    "wof:placetype":"postalcode"
},
  "geometry": {"coordinates":[-1.1132174746727,53.32710252944597],"type":"Point"}
}