{
  "type": "Feature",
  "properties": {
    "iso:country": "GB",
    "wof:name": "LL55 2SS",
    "wof:placetype": "postalcode"
  },
  "geometry": {"coordinates":[-4.240303,53.130886],"type":"Point"}
}
