{
  "type": "Feature",
  "properties": {
    "date:inception_lower": "1980-01-01",
    "date:inception_upper": "1980-01-01",
    "iso:country": "GB",
    "wof:name": "EH52 6QF",
    "wof:placetype": "postalcode"
  },
  "geometry": {"coordinates":[-3.456216,55.984057],"type":"Point"}
}
