{
  "type": "Feature",
  "properties": {
    "iso:country":"GB",
    "wof:name":"EH52 6QF",
    "wof:placetype":"postalcode"
},
  "geometry": {"coordinates":[-3.4562165294142,55.98405663952673],"type":"Point"}
}