{
  "type": "Feature",
  "properties": {
    "iso:country": "GB",
    "wof:name": "LL53 7AX",
    "wof:placetype": "postalcode"
  },
  "geometry": {"coordinates":[-4.507875,52.827818],"type":"Point"}
}
