{
  "type": "Feature",
  "properties": {
    "iso:country":"GB",
    "wof:name":"LL53 7AX",
    "wof:placetype":"postalcode"
},
  "geometry": {"coordinates":[-4.50788035460669,52.82778287579156],"type":"Point"}
}