{
  "type": "Feature",
  "properties": {
    "date:inception_lower":"2014-08-01",
    "date:inception_upper":"2014-08-31",
    "iso:country":"GB",
    "wof:name":"LL53 7AX",
    "wof:placetype":"postalcode"
},
  "geometry": {"coordinates":[-4.507875,52.827818],"type":"Point"}
}