{
  "type": "Feature",
  "properties": {
    "iso:country":"GB",
    "wof:name":"SL0 9QL",
    "wof:placetype":"postalcode"
},
  "geometry": {"coordinates":[-0.51686500097406,51.52021160574662],"type":"Point"}
}