{
  "type": "Feature",
  "properties": {
    "iso:country": "GB",
    "wof:name": "SL0 9QL",
    "wof:placetype": "postalcode"
  },
  "geometry": {"coordinates":[-0.516865,51.520212],"type":"Point"}
}
