{
  "type": "Feature",
  "properties": {
    "iso:country":"GB",
    "wof:name":"SA68 0TT",
    "wof:placetype":"postalcode"
},
  "geometry": {"coordinates":[-4.81788242836202,51.70826160686964],"type":"Point"}
}