{
  "type": "Feature",
  "properties": {
    "iso:country": "GB",
    "wof:name": "SA68 0TT",
    "wof:placetype": "postalcode"
  },
  "geometry": {"coordinates":[-4.817882,51.708262],"type":"Point"}
}
