{
  "type": "Feature",
  "properties": {
    "date:inception_lower": "1990-07-01",
    "date:inception_upper": "1990-07-01",
    "iso:country": "GB",
    "wof:name": "BN23 8EZ",
    "wof:placetype": "postalcode"
  },
  "geometry": {"coordinates":[0.306571,50.808155],"type":"Point"}
}
