{
  "type": "Feature",
  "properties": {
    "iso:country":"GB",
    "wof:name":"BN23 8EZ",
    "wof:placetype":"postalcode"
},
  "geometry": {"coordinates":[0.30657104187616,50.80815492346164],"type":"Point"}
}