{
  "type": "Feature",
  "properties": {
    "iso:country": "GB",
    "wof:name": "NR11 7NF",
    "wof:placetype": "postalcode"
  },
  "geometry": {"coordinates":[1.228552,52.853366],"type":"Point"}
}
