{
  "type": "Feature",
  "properties": {
    "date:inception_lower":"1980-01-01",
    "date:inception_upper":"1980-01-31",
    "iso:country":"GB",
    "wof:name":"NR11 7NF",
    "wof:placetype":"postalcode"
},
  "geometry": {"coordinates":[1.228552,52.853366],"type":"Point"}
}