{
  "type": "Feature",
  "properties": {
    "date:inception_lower": "1980-01-01",
    "date:inception_upper": "1980-01-01",
    "iso:country": "GB",
    "wof:name": "NR11 7NF",
    "wof:placetype": "postalcode"
  },
  "geometry": {"coordinates":[1.231373,52.853541],"type":"Point"}
}
