{
  "type": "Feature",
  "properties": {
    "iso:country":"GB",
    "wof:name":"SY8 1JP",
    "wof:placetype":"postalcode"
},
  "geometry": {"coordinates":[-2.70755841140033,52.36532329826299],"type":"Point"}
}