{
  "type": "Feature",
  "properties": {
    "date:inception_lower": "1980-01-01",
    "date:inception_upper": "1980-01-01",
    "iso:country": "GB",
    "wof:name": "OX10 9JJ",
    "wof:placetype": "postalcode"
  },
  "geometry": {"coordinates":[-1.150793,51.548569],"type":"Point"}
}
