{
  "type": "Feature",
  "properties": {
    "iso:country":"GB",
    "wof:name":"OX10 9JJ",
    "wof:placetype":"postalcode"
},
  "geometry": {"coordinates":[-1.15079302675522,51.54856872418911],"type":"Point"}
}