{
  "type": "Feature",
  "properties": {
    "iso:country":"GB",
    "wof:name":"WS6 6JP",
    "wof:placetype":"postalcode"
},
  "geometry": {"coordinates":[-2.01929216879738,52.65308669714273],"type":"Point"}
}