{
  "type": "Feature",
  "properties": {
    "date:inception_lower":"1980-01-01",
    "date:inception_upper":"1980-01-31",
    "iso:country":"GB",
    "wof:name":"WS6 6JP",
    "wof:placetype":"postalcode"
},
  "geometry": {"coordinates":[-2.019292,52.653087],"type":"Point"}
}