{
  "type": "Feature",
  "properties": {
    "iso:country":"GB",
    "wof:name":"AB15 5LW",
    "wof:placetype":"postalcode"
},
  "geometry": {"coordinates":[-2.13322407326312,57.14890774161928],"type":"Point"}
}