{
  "type": "Feature",
  "properties": {
    "iso:country":"GB",
    "wof:name":"BS13 8RJ",
    "wof:placetype":"postalcode"
},
  "geometry": {"coordinates":[-2.62909346598446,51.40533969969179],"type":"Point"}
}