{
  "type": "Feature",
  "properties": {
    "iso:country":"GB",
    "wof:name":"TN3 0SJ",
    "wof:placetype":"postalcode"
},
  "geometry": {"coordinates":[0.1733485778425,51.14024839912875],"type":"Point"}
}