{
  "type": "Feature",
  "properties": {
    "iso:country": "GB",
    "wof:name": "B91 1SQ",
    "wof:placetype": "postalcode"
  },
  "geometry": {"coordinates":[-1.795765,52.410902],"type":"Point"}
}
