{
  "type": "Feature",
  "properties": {
    "iso:country":"GB",
    "wof:name":"B91 1SQ",
    "wof:placetype":"postalcode"
},
  "geometry": {"coordinates":[-1.7957725498219,52.41088689128957],"type":"Point"}
}