{
  "type": "Feature",
  "properties": {
    "iso:country":"GB",
    "wof:name":"SE1 2AA",
    "wof:placetype":"postalcode"
},
  "geometry": {"coordinates":[-0.07869255964226,51.50485139419955],"type":"Point"}
}