{
  "type": "Feature",
  "properties": {
    "iso:country":"GB",
    "wof:name":"SE17 1DE",
    "wof:placetype":"postalcode"
},
  "geometry": {"coordinates":[-0.09402146899036,51.48903177385471],"type":"Point"}
}