{
  "type": "Feature",
  "properties": {
    "date:inception_lower": "2018-01-01",
    "date:inception_upper": "2018-01-01",
    "iso:country": "GB",
    "wof:name": "AB12 3UN",
    "wof:placetype": "postalcode"
  },
  "geometry": {"coordinates":[-2.079785,57.103088],"type":"Point"}
}
