{
  "type": "Feature",
  "properties": {
    "iso:country":"GB",
    "wof:name":"HG1 4RF",
    "wof:placetype":"postalcode"
},
  "geometry": {"coordinates":[-1.51023364024555,54.00187488817787],"type":"Point"}
}