{
  "type": "Feature",
  "properties": {
    "iso:country": "GB",
    "wof:name": "CH2 2QE",
    "wof:placetype": "postalcode"
  },
  "geometry": {"coordinates":[-2.870493,53.208498],"type":"Point"}
}
