{
  "type": "Feature",
  "properties": {
    "iso:country":"GB",
    "wof:name":"CH2 2QE",
    "wof:placetype":"postalcode"
},
  "geometry": {"coordinates":[-2.87058142346734,53.20847258906118],"type":"Point"}
}