{
  "type": "Feature",
  "properties": {
    "iso:country":"GB",
    "wof:name":"DD10 8DY",
    "wof:placetype":"postalcode"
},
  "geometry": {"coordinates":[-2.46097516276569,56.70687325334082],"type":"Point"}
}