{
  "type": "Feature",
  "properties": {
    "iso:country":"GB",
    "wof:name":"HG3 1NJ",
    "wof:placetype":"postalcode"
},
  "geometry": {"coordinates":[-1.53723073386335,53.96525778267365],"type":"Point"}
}