{
  "type": "Feature",
  "properties": {
    "iso:country":"GB",
    "wof:name":"S12 2BS",
    "wof:placetype":"postalcode"
},
  "geometry": {"coordinates":[-1.40514157903261,53.35748973524396],"type":"Point"}
}