{
  "type": "Feature",
  "properties": {
    "date:inception_lower": "1980-01-01",
    "date:inception_upper": "1980-01-01",
    "iso:country": "GB",
    "wof:name": "S5 0LA",
    "wof:placetype": "postalcode"
  },
  "geometry": {"coordinates":[-1.453456,53.428398],"type":"Point"}
}
