{
  "type": "Feature",
  "properties": {
    "iso:country": "GB",
    "wof:name": "DA9 9AE",
    "wof:placetype": "postalcode"
  },
  "geometry": {"coordinates":[0.276931,51.44968],"type":"Point"}
}
