{
  "type": "Feature",
  "properties": {
    "iso:country":"GB",
    "wof:name":"CV10 7DN",
    "wof:placetype":"postalcode"
},
  "geometry": {"coordinates":[-1.48532320341123,52.51991936586003],"type":"Point"}
}