{
  "type": "Feature",
  "properties": {
    "iso:country": "GB",
    "wof:name": "TA1 2ER",
    "wof:placetype": "postalcode"
  },
  "geometry": {"coordinates":[-3.078324,51.018088],"type":"Point"}
}
