{
  "type": "Feature",
  "properties": {
    "date:inception_lower": "1995-07-01",
    "date:inception_upper": "1995-07-01",
    "iso:country": "GB",
    "wof:name": "S75 1RA",
    "wof:placetype": "postalcode"
  },
  "geometry": {"coordinates":[-1.527444,53.570633],"type":"Point"}
}
