{
  "type": "Feature",
  "properties": {
    "iso:country":"GB",
    "wof:name":"S75 1RA",
    "wof:placetype":"postalcode"
},
  "geometry": {"coordinates":[-1.52744397126451,53.57063347780181],"type":"Point"}
}