{
  "type": "Feature",
  "properties": {
    "iso:country": "GB",
    "wof:name": "S75 1RA",
    "wof:placetype": "postalcode"
  },
  "geometry": {"coordinates":[-1.527444,53.570633],"type":"Point"}
}
