{
  "type": "Feature",
  "properties": {
    "iso:country": "GB",
    "wof:name": "RM6 5AJ",
    "wof:placetype": "postalcode"
  },
  "geometry": {"coordinates":[0.128892,51.5799],"type":"Point"}
}
