{
  "type": "Feature",
  "properties": {
    "iso:country":"GB",
    "wof:name":"RM6 5AJ",
    "wof:placetype":"postalcode"
},
  "geometry": {"coordinates":[0.1288921414212,51.57989971646506],"type":"Point"}
}