{
  "type": "Feature",
  "properties": {
    "iso:country":"GB",
    "wof:name":"CO10 2BH",
    "wof:placetype":"postalcode"
},
  "geometry": {"coordinates":[0.72356986352029,52.03739707441876],"type":"Point"}
}