{
  "type": "Feature",
  "properties": {
    "iso:country":"GB",
    "wof:name":"RG6 7AB",
    "wof:placetype":"postalcode"
},
  "geometry": {"coordinates":[-0.91686680419405,51.43923557867318],"type":"Point"}
}