{
  "type": "Feature",
  "properties": {
    "date:inception_lower": "1980-01-01",
    "date:inception_upper": "1980-01-01",
    "iso:country": "GB",
    "wof:name": "NE66 3ED",
    "wof:placetype": "postalcode"
  },
  "geometry": {"coordinates":[-1.627874,55.522375],"type":"Point"}
}
