{
  "type": "Feature",
  "properties": {
    "iso:country": "GB",
    "wof:name": "NE66 3ED",
    "wof:placetype": "postalcode"
  },
  "geometry": {"coordinates":[-1.627874,55.522375],"type":"Point"}
}
