{
  "type": "Feature",
  "properties": {
    "iso:country":"GB",
    "wof:name":"EX5 4HH",
    "wof:placetype":"postalcode"
},
  "geometry": {"coordinates":[-3.48235345841859,50.8161647842295],"type":"Point"}
}