{
  "type": "Feature",
  "properties": {
    "iso:country":"GB",
    "wof:name":"WS7 2AT",
    "wof:placetype":"postalcode"
},
  "geometry": {"coordinates":[-1.92838851386077,52.68526783394589],"type":"Point"}
}