{
  "type": "Feature",
  "properties": {
    "iso:country":"GB",
    "wof:name":"W11 3DB",
    "wof:placetype":"postalcode"
},
  "geometry": {"coordinates":[-0.20087864855858,51.51194207521991],"type":"Point"}
}