{
  "type": "Feature",
  "properties": {
    "iso:country": "GB",
    "wof:name": "SN8 2FQ",
    "wof:placetype": "postalcode"
  },
  "geometry": {"coordinates":[-1.585087,51.450301],"type":"Point"}
}
