{
  "type": "Feature",
  "properties": {
    "iso:country": "GB",
    "wof:name": "WV11 3ER",
    "wof:placetype": "postalcode"
  },
  "geometry": {"coordinates":[-2.069933,52.605008],"type":"Point"}
}
