{
  "type": "Feature",
  "properties": {
    "iso:country": "GB",
    "wof:name": "OX10 0SW",
    "wof:placetype": "postalcode"
  },
  "geometry": {"coordinates":[-1.175867,51.614056],"type":"Point"}
}
