{
  "type": "Feature",
  "properties": {
    "date:inception_lower":"1980-01-01",
    "date:inception_upper":"1980-01-31",
    "iso:country":"GB",
    "wof:name":"DL1 3NF",
    "wof:placetype":"postalcode"
},
  "geometry": {"coordinates":[-1.543452,54.562331],"type":"Point"}
}