{
  "type": "Feature",
  "properties": {
    "iso:country": "GB",
    "wof:name": "DL1 3NF",
    "wof:placetype": "postalcode"
  },
  "geometry": {"coordinates":[-1.544163,54.562324],"type":"Point"}
}
