{
  "type": "Feature",
  "properties": {
    "iso:country":"GB",
    "wof:name":"DL1 3NF",
    "wof:placetype":"postalcode"
},
  "geometry": {"coordinates":[-1.54415419191897,54.56231351687723],"type":"Point"}
}