{
  "type": "Feature",
  "properties": {
    "iso:country":"GB",
    "wof:name":"DT5 2EB",
    "wof:placetype":"postalcode"
},
  "geometry": {"coordinates":[-2.44504698475177,50.53123760171617],"type":"Point"}
}