{
  "type": "Feature",
  "properties": {
    "iso:country":"GB",
    "wof:name":"CR5 1BD",
    "wof:placetype":"postalcode"
},
  "geometry": {"coordinates":[-0.12301965993578,51.3017951221881],"type":"Point"}
}