{
  "type": "Feature",
  "properties": {
    "iso:country": "GB",
    "wof:name": "RH18 5AH",
    "wof:placetype": "postalcode"
  },
  "geometry": {"coordinates":[0.031875,51.096585],"type":"Point"}
}
