{
  "type": "Feature",
  "properties": {
    "iso:country":"GB",
    "wof:name":"RH18 5AH",
    "wof:placetype":"postalcode"
},
  "geometry": {"coordinates":[0.03187494279163,51.09658507759457],"type":"Point"}
}