{
  "type": "Feature",
  "properties": {
    "iso:country": "GB",
    "wof:name": "SL1 6NL",
    "wof:placetype": "postalcode"
  },
  "geometry": {"coordinates":[-0.646004,51.52965],"type":"Point"}
}
