{
  "type": "Feature",
  "properties": {
    "date:inception_lower": "1980-01-01",
    "date:inception_upper": "1980-01-01",
    "iso:country": "GB",
    "wof:name": "SL1 6NL",
    "wof:placetype": "postalcode"
  },
  "geometry": {"coordinates":[-0.646004,51.52965],"type":"Point"}
}
