{
  "type": "Feature",
  "properties": {
    "iso:country":"GB",
    "wof:name":"SL1 6NL",
    "wof:placetype":"postalcode"
},
  "geometry": {"coordinates":[-0.64600412774839,51.52965008526357],"type":"Point"}
}