{
  "type": "Feature",
  "properties": {
    "iso:country":"GB",
    "wof:name":"DN9 2JN",
    "wof:placetype":"postalcode"
},
  "geometry": {"coordinates":[-0.85719792844186,53.50457166440185],"type":"Point"}
}