{
  "type": "Feature",
  "properties": {
    "iso:country":"GB",
    "wof:name":"PO33 4EA",
    "wof:placetype":"postalcode"
},
  "geometry": {"coordinates":[-1.20171046929157,50.70309028257321],"type":"Point"}
}