{
  "type": "Feature",
  "properties": {
    "date:inception_lower": "1981-06-01",
    "date:inception_upper": "1981-06-01",
    "iso:country": "GB",
    "wof:name": "PO33 4EA",
    "wof:placetype": "postalcode"
  },
  "geometry": {"coordinates":[-1.20171,50.70309],"type":"Point"}
}
