{
  "type": "Feature",
  "properties": {
    "date:inception_lower": "1980-01-01",
    "date:inception_upper": "1980-01-01",
    "iso:country": "GB",
    "wof:name": "SS6 9RD",
    "wof:placetype": "postalcode"
  },
  "geometry": {"coordinates":[0.599576,51.608457],"type":"Point"}
}
