{
  "type": "Feature",
  "properties": {
    "iso:country":"GB",
    "wof:name":"RH20 1AD",
    "wof:placetype":"postalcode"
},
  "geometry": {"coordinates":[-0.50930215516293,50.95894647938746],"type":"Point"}
}