{
  "type": "Feature",
  "properties": {
    "date:inception_lower": "1980-01-01",
    "date:inception_upper": "1980-01-01",
    "iso:country": "GB",
    "wof:name": "TN14 7DN",
    "wof:placetype": "postalcode"
  },
  "geometry": {"coordinates":[0.135571,51.333148],"type":"Point"}
}
