{
  "type": "Feature",
  "properties": {
    "iso:country":"GB",
    "wof:name":"CV7 7SD",
    "wof:placetype":"postalcode"
},
  "geometry": {"coordinates":[-1.65017367604779,52.39402224703959],"type":"Point"}
}