{
  "type": "Feature",
  "properties": {
    "iso:country":"GB",
    "wof:name":"ST6 8UA",
    "wof:placetype":"postalcode"
},
  "geometry": {"coordinates":[-2.13752288504768,53.09001730924213],"type":"Point"}
}