{
  "type": "Feature",
  "properties": {
    "iso:country": "GB",
    "wof:name": "DN3 3FP",
    "wof:placetype": "postalcode"
  },
  "geometry": {"coordinates":[-1.04286,53.507335],"type":"Point"}
}
