{
  "type": "Feature",
  "properties": {
    "date:inception_lower":"2015-06-01",
    "date:inception_upper":"2015-06-30",
    "iso:country":"GB",
    "wof:name":"DN3 3FP",
    "wof:placetype":"postalcode"
},
  "geometry": {"coordinates":[-1.04286,53.507335],"type":"Point"}
}