{
  "type": "Feature",
  "properties": {
    "iso:country":"GB",
    "wof:name":"DN3 3FP",
    "wof:placetype":"postalcode"
},
  "geometry": {"coordinates":[-1.04286009111206,53.50733464021035],"type":"Point"}
}