{
  "type": "Feature",
  "properties": {
    "date:inception_lower": "1987-04-01",
    "date:inception_upper": "1987-04-01",
    "iso:country": "GB",
    "wof:name": "PE12 9TU",
    "wof:placetype": "postalcode"
  },
  "geometry": {"coordinates":[0.195613,52.76796],"type":"Point"}
}
