{
  "type": "Feature",
  "properties": {
    "iso:country": "GB",
    "wof:name": "NN3 5LY",
    "wof:placetype": "postalcode"
  },
  "geometry": {"coordinates":[-0.805721,52.26816],"type":"Point"}
}
