{
  "type": "Feature",
  "properties": {
    "date:inception_lower": "1990-02-01",
    "date:inception_upper": "1990-02-01",
    "iso:country": "GB",
    "wof:name": "NN3 5LY",
    "wof:placetype": "postalcode"
  },
  "geometry": {"coordinates":[-0.805721,52.26816],"type":"Point"}
}
