{
  "type": "Feature",
  "properties": {
    "iso:country":"GB",
    "wof:name":"NN3 5LY",
    "wof:placetype":"postalcode"
},
  "geometry": {"coordinates":[-0.80572058765346,52.26815952223832],"type":"Point"}
}