{
  "type": "Feature",
  "properties": {
    "iso:country": "GB",
    "wof:name": "HP22 0AQ",
    "wof:placetype": "postalcode"
  },
  "geometry": {"coordinates":[-0.733764,51.803428],"type":"Point"}
}
