{
  "type": "Feature",
  "properties": {
    "date:inception_lower": "2019-04-01",
    "date:inception_upper": "2019-04-01",
    "iso:country": "GB",
    "wof:name": "HP22 0AQ",
    "wof:placetype": "postalcode"
  },
  "geometry": {"coordinates":[-0.733867,51.803879],"type":"Point"}
}
