{
  "type": "Feature",
  "properties": {
    "iso:country":"GB",
    "wof:name":"G84 7AP",
    "wof:placetype":"postalcode"
},
  "geometry": {"coordinates":[-4.71919282264787,56.00019224813989],"type":"Point"}
}