{
  "type": "Feature",
  "properties": {
    "date:inception_lower":"1995-01-01",
    "date:inception_upper":"1995-01-31",
    "iso:country":"GB",
    "wof:name":"B91 2TQ",
    "wof:placetype":"postalcode"
},
  "geometry": {"coordinates":[-1.739046,52.421219],"type":"Point"}
}