{
  "type": "Feature",
  "properties": {
    "iso:country":"GB",
    "wof:name":"B91 2TQ",
    "wof:placetype":"postalcode"
},
  "geometry": {"coordinates":[-1.73905382375566,52.42117696929169],"type":"Point"}
}