{
  "type": "Feature",
  "properties": {
    "iso:country":"GB",
    "wof:name":"L7 6LQ",
    "wof:placetype":"postalcode"
},
  "geometry": {"coordinates":[-2.95053113393046,53.40203405254569],"type":"Point"}
}