{
  "type": "Feature",
  "properties": {
    "date:inception_lower":"1994-12-01",
    "date:inception_upper":"1994-12-31",
    "iso:country":"GB",
    "wof:name":"L7 6LQ",
    "wof:placetype":"postalcode"
},
  "geometry": {"coordinates":[-2.950531,53.402034],"type":"Point"}
}