{
  "type": "Feature",
  "properties": {
    "iso:country":"GB",
    "wof:name":"AL7 1HE",
    "wof:placetype":"postalcode"
},
  "geometry": {"coordinates":[-0.1977607051282,51.80615624681067],"type":"Point"}
}