{
  "type": "Feature",
  "properties": {
    "date:inception_lower": "2005-09-01",
    "date:inception_upper": "2005-09-01",
    "iso:country": "GB",
    "wof:name": "AL7 1HE",
    "wof:placetype": "postalcode"
  },
  "geometry": {"coordinates":[-0.19649,51.805406],"type":"Point"}
}
