{
  "type": "Feature",
  "properties": {
    "iso:country": "GB",
    "wof:name": "AL7 1HE",
    "wof:placetype": "postalcode"
  },
  "geometry": {"coordinates":[-0.19649,51.805406],"type":"Point"}
}
