{
  "type": "Feature",
  "properties": {
    "iso:country": "GB",
    "wof:name": "CM8 1BA",
    "wof:placetype": "postalcode"
  },
  "geometry": {"coordinates":[0.637006,51.797714],"type":"Point"}
}
