{
  "type": "Feature",
  "properties": {
    "date:inception_lower": "2001-12-01",
    "date:inception_upper": "2001-12-01",
    "iso:country": "GB",
    "wof:name": "TW13 6PG",
    "wof:placetype": "postalcode"
  },
  "geometry": {"coordinates":[-0.385232,51.432741],"type":"Point"}
}
