{
  "type": "Feature",
  "properties": {
    "iso:country":"GB",
    "wof:name":"PR8 5JF",
    "wof:placetype":"postalcode"
},
  "geometry": {"coordinates":[-2.96616503787939,53.62962966316567],"type":"Point"}
}