{
  "type": "Feature",
  "properties": {
    "iso:country": "GB",
    "wof:name": "PR8 5JF",
    "wof:placetype": "postalcode"
  },
  "geometry": {"coordinates":[-2.96595,53.629567],"type":"Point"}
}
