{
  "type": "Feature",
  "properties": {
    "date:inception_lower": "1980-01-01",
    "date:inception_upper": "1980-01-01",
    "iso:country": "GB",
    "wof:name": "PR8 5JF",
    "wof:placetype": "postalcode"
  },
  "geometry": {"coordinates":[-2.966179,53.629646],"type":"Point"}
}
