{
  "type": "Feature",
  "properties": {
    "date:inception_lower": "1997-06-01",
    "date:inception_upper": "1997-06-01",
    "iso:country": "GB",
    "wof:name": "S35 1AF",
    "wof:placetype": "postalcode"
  },
  "geometry": {"coordinates":[-1.470159,53.461327],"type":"Point"}
}
