{
  "type": "Feature",
  "properties": {
    "date:inception_lower":"2004-08-01",
    "date:inception_upper":"2004-08-31",
    "iso:country":"GB",
    "wof:name":"LE10 0AP",
    "wof:placetype":"postalcode"
},
  "geometry": {"coordinates":[-1.375709,52.54353],"type":"Point"}
}