{
  "type": "Feature",
  "properties": {
    "iso:country":"GB",
    "wof:name":"LE10 0AP",
    "wof:placetype":"postalcode"
},
  "geometry": {"coordinates":[-1.37570908173004,52.54353039026078],"type":"Point"}
}