{
  "type": "Feature",
  "properties": {
    "iso:country":"GB",
    "wof:name":"S74 0BU",
    "wof:placetype":"postalcode"
},
  "geometry": {"coordinates":[-1.45795307084106,53.49726267520236],"type":"Point"}
}