{
  "type": "Feature",
  "properties": {
    "iso:country": "GB",
    "wof:name": "LL57 4UN",
    "wof:placetype": "postalcode"
  },
  "geometry": {"coordinates":[-4.117876,53.198652],"type":"Point"}
}
