{
  "type": "Feature",
  "properties": {
    "iso:country":"GB",
    "wof:name":"LL57 4UN",
    "wof:placetype":"postalcode"
},
  "geometry": {"coordinates":[-4.11787579182927,53.19865150977873],"type":"Point"}
}