{
  "type": "Feature",
  "properties": {
    "iso:country":"GB",
    "wof:name":"TN39 3PD",
    "wof:placetype":"postalcode"
},
  "geometry": {"coordinates":[0.46802790685603,50.84190579838262],"type":"Point"}
}