{
  "type": "Feature",
  "properties": {
    "date:inception_lower": "1980-01-01",
    "date:inception_upper": "1980-01-01",
    "iso:country": "GB",
    "wof:name": "OL14 6SF",
    "wof:placetype": "postalcode"
  },
  "geometry": {"coordinates":[-2.103343,53.695924],"type":"Point"}
}
