{
  "type": "Feature",
  "properties": {
    "iso:country": "GB",
    "wof:name": "SG19 2EE",
    "wof:placetype": "postalcode"
  },
  "geometry": {"coordinates":[-0.1594,52.130393],"type":"Point"}
}
