{
  "type": "Feature",
  "properties": {
    "iso:country":"GB",
    "wof:name":"CH48 0QB",
    "wof:placetype":"postalcode"
},
  "geometry": {"coordinates":[-3.18323032539791,53.36829460242811],"type":"Point"}
}