{
  "type": "Feature",
  "properties": {
    "date:inception_lower": "2007-01-01",
    "date:inception_upper": "2007-01-01",
    "iso:country": "GB",
    "wof:name": "S75 5GN",
    "wof:placetype": "postalcode"
  },
  "geometry": {"coordinates":[-1.533967,53.59677],"type":"Point"}
}
