{
  "type": "Feature",
  "properties": {
    "iso:country":"GB",
    "wof:name":"S75 5GN",
    "wof:placetype":"postalcode"
},
  "geometry": {"coordinates":[-1.53396698822038,53.59677025561412],"type":"Point"}
}