{
  "type": "Feature",
  "properties": {
    "iso:country":"GB",
    "wof:name":"TN1 1YJ",
    "wof:placetype":"postalcode"
},
  "geometry": {"coordinates":[0.26009917839954,51.12681317763064],"type":"Point"}
}