{
  "type": "Feature",
  "properties": {
    "iso:country":"GB",
    "wof:name":"EH45 8NQ",
    "wof:placetype":"postalcode"
},
  "geometry": {"coordinates":[-3.15046593884619,55.64468611320984],"type":"Point"}
}