{
  "type": "Feature",
  "properties": {
    "iso:country": "GB",
    "wof:name": "EH45 8NQ",
    "wof:placetype": "postalcode"
  },
  "geometry": {"coordinates":[-3.149563,55.644757],"type":"Point"}
}
