{
  "type": "Feature",
  "properties": {
    "iso:country":"GB",
    "wof:name":"M33 5QY",
    "wof:placetype":"postalcode"
},
  "geometry": {"coordinates":[-2.345154493505,53.43163823505176],"type":"Point"}
}