{
  "type": "Feature",
  "properties": {
    "date:inception_lower":"1994-05-01",
    "date:inception_upper":"1994-05-31",
    "iso:country":"GB",
    "wof:name":"M33 5QY",
    "wof:placetype":"postalcode"
},
  "geometry": {"coordinates":[-2.345154,53.431638],"type":"Point"}
}