{
  "type": "Feature",
  "properties": {
    "iso:country":"GB",
    "wof:name":"SW18 5DJ",
    "wof:placetype":"postalcode"
},
  "geometry": {"coordinates":[-0.19990434028608,51.44120118682387],"type":"Point"}
}