{
  "type": "Feature",
  "properties": {
    "iso:country":"GB",
    "wof:name":"NG2 6QE",
    "wof:placetype":"postalcode"
},
  "geometry": {"coordinates":[-1.1050753906745,52.91783157748133],"type":"Point"}
}