{
  "type": "Feature",
  "properties": {
    "iso:country":"GB",
    "wof:name":"CF31 1DU",
    "wof:placetype":"postalcode"
},
  "geometry": {"coordinates":[-3.57711876690777,51.50526549747006],"type":"Point"}
}