{
  "type": "Feature",
  "properties": {
    "iso:country":"GB",
    "wof:name":"GL5 1UT",
    "wof:placetype":"postalcode"
},
  "geometry": {"coordinates":[-2.21164991860859,51.74805986661246],"type":"Point"}
}