{
  "type": "Feature",
  "properties": {
    "iso:country": "GB",
    "wof:name": "CH49 6NX",
    "wof:placetype": "postalcode"
  },
  "geometry": {"coordinates":[-3.094256,53.385872],"type":"Point"}
}
