{
  "type": "Feature",
  "properties": {
    "iso:country":"GB",
    "wof:name":"CO3 3HX",
    "wof:placetype":"postalcode"
},
  "geometry": {"coordinates":[0.88543822683502,51.88563487506502],"type":"Point"}
}