{
  "type": "Feature",
  "properties": {
    "date:inception_lower":"1980-01-01",
    "date:inception_upper":"1980-01-31",
    "iso:country":"GB",
    "wof:name":"PO5 2DE",
    "wof:placetype":"postalcode"
},
  "geometry": {"coordinates":[-1.082989,50.787101],"type":"Point"}
}