{
  "type": "Feature",
  "properties": {
    "iso:country":"GB",
    "wof:name":"PO5 2DE",
    "wof:placetype":"postalcode"
},
  "geometry": {"coordinates":[-1.08298902644312,50.78710074230911],"type":"Point"}
}