{
  "type": "Feature",
  "properties": {
    "iso:country":"GB",
    "wof:name":"BB3 3AE",
    "wof:placetype":"postalcode"
},
  "geometry": {"coordinates":[-2.46077447030878,53.70080080455062],"type":"Point"}
}