{
  "type": "Feature",
  "properties": {
    "iso:country":"GB",
    "wof:name":"NR14 8JU",
    "wof:placetype":"postalcode"
},
  "geometry": {"coordinates":[1.23624615962036,52.56647149778185],"type":"Point"}
}