{
  "type": "Feature",
  "properties": {
    "iso:country":"GB",
    "wof:name":"E8 2NR",
    "wof:placetype":"postalcode"
},
  "geometry": {"coordinates":[-0.07274877972057,51.54803509649491],"type":"Point"}
}