{
  "type": "Feature",
  "properties": {
    "date:inception_lower": "1980-01-01",
    "date:inception_upper": "1980-01-01",
    "iso:country": "GB",
    "wof:name": "E8 2NR",
    "wof:placetype": "postalcode"
  },
  "geometry": {"coordinates":[-0.072749,51.548035],"type":"Point"}
}
