{
  "type": "Feature",
  "properties": {
    "iso:country":"GB",
    "wof:name":"BR5 1RD",
    "wof:placetype":"postalcode"
},
  "geometry": {"coordinates":[0.09635072809509,51.3903681335396],"type":"Point"}
}