{
  "type": "Feature",
  "properties": {
    "iso:country":"GB",
    "wof:name":"PO33 4LZ",
    "wof:placetype":"postalcode"
},
  "geometry": {"coordinates":[-1.23887806761739,50.7243730280867],"type":"Point"}
}