{
  "type": "Feature",
  "properties": {
    "date:inception_lower": "1980-01-01",
    "date:inception_upper": "1980-01-01",
    "iso:country": "GB",
    "wof:name": "ME17 1EN",
    "wof:placetype": "postalcode"
  },
  "geometry": {"coordinates":[0.65248,51.211188],"type":"Point"}
}
