{
  "type": "Feature",
  "properties": {
    "iso:country":"GB",
    "wof:name":"YO8 9LQ",
    "wof:placetype":"postalcode"
},
  "geometry": {"coordinates":[-1.15498707059874,53.7516240478456],"type":"Point"}
}