{
  "type": "Feature",
  "properties": {
    "iso:country":"GB",
    "wof:name":"CM7 4TH",
    "wof:placetype":"postalcode"
},
  "geometry": {"coordinates":[0.43456425172663,51.94811592208006],"type":"Point"}
}