{
  "type": "Feature",
  "properties": {
    "iso:country":"GB",
    "wof:name":"NN15 6XL",
    "wof:placetype":"postalcode"
},
  "geometry": {"coordinates":[-0.7170914841716,52.37867946402815],"type":"Point"}
}