{
  "type": "Feature",
  "properties": {
    "iso:country": "GB",
    "wof:name": "CM1 2DW",
    "wof:placetype": "postalcode"
  },
  "geometry": {"coordinates":[0.452944,51.748938],"type":"Point"}
}
