{
  "type": "Feature",
  "properties": {
    "iso:country":"GB",
    "wof:name":"CM1 2DW",
    "wof:placetype":"postalcode"
},
  "geometry": {"coordinates":[0.45294355366003,51.74893782281237],"type":"Point"}
}