{
  "type": "Feature",
  "properties": {
    "date:inception_lower": "1980-01-01",
    "date:inception_upper": "1980-01-01",
    "iso:country": "GB",
    "wof:name": "LE2 6JB",
    "wof:placetype": "postalcode"
  },
  "geometry": {"coordinates":[-1.12487,52.600639],"type":"Point"}
}
