{
  "type": "Feature",
  "properties": {
    "iso:country":"GB",
    "wof:name":"HD6 2NA",
    "wof:placetype":"postalcode"
},
  "geometry": {"coordinates":[-1.78992019037231,53.7163884759441],"type":"Point"}
}