{
  "type": "Feature",
  "properties": {
    "date:inception_lower": "1980-01-01",
    "date:inception_upper": "1980-01-01",
    "iso:country": "GB",
    "wof:name": "HD6 2NA",
    "wof:placetype": "postalcode"
  },
  "geometry": {"coordinates":[-1.78992,53.716388],"type":"Point"}
}
