{
  "type": "Feature",
  "properties": {
    "iso:country": "GB",
    "wof:name": "NE13 6HZ",
    "wof:placetype": "postalcode"
  },
  "geometry": {"coordinates":[-1.618335,55.056432],"type":"Point"}
}
