{
  "type": "Feature",
  "properties": {
    "iso:country":"GB",
    "wof:name":"NE13 6HZ",
    "wof:placetype":"postalcode"
},
  "geometry": {"coordinates":[-1.61833532397046,55.05643241413904],"type":"Point"}
}