{
  "type": "Feature",
  "properties": {
    "iso:country":"GB",
    "wof:name":"WF1 4HE",
    "wof:placetype":"postalcode"
},
  "geometry": {"coordinates":[-1.47985639627045,53.68309578225747],"type":"Point"}
}