{
  "type": "Feature",
  "properties": {
    "iso:country": "GB",
    "wof:name": "BA14 7FH",
    "wof:placetype": "postalcode"
  },
  "geometry": {"coordinates":[-2.187871,51.322599],"type":"Point"}
}
