{
  "type": "Feature",
  "properties": {
    "iso:country":"GB",
    "wof:name":"TS17 5NE",
    "wof:placetype":"postalcode"
},
  "geometry": {"coordinates":[-1.31995155496212,54.52493607988649],"type":"Point"}
}