{
  "type": "Feature",
  "properties": {
    "date:inception_lower": "2008-03-01",
    "date:inception_upper": "2008-03-01",
    "iso:country": "GB",
    "wof:name": "SN12 7FD",
    "wof:placetype": "postalcode"
  },
  "geometry": {"coordinates":[-2.135326,51.373529],"type":"Point"}
}
