{
  "type": "Feature",
  "properties": {
    "iso:country":"GB",
    "wof:name":"SN12 7FD",
    "wof:placetype":"postalcode"
},
  "geometry": {"coordinates":[-2.13532571715249,51.37352904030546],"type":"Point"}
}