{
  "type": "Feature",
  "properties": {
    "iso:country": "GB",
    "wof:name": "G71 5LX",
    "wof:placetype": "postalcode"
  },
  "geometry": {"coordinates":[-4.058151,55.832554],"type":"Point"}
}
