{
  "type": "Feature",
  "properties": {
    "date:inception_lower": "1980-01-01",
    "date:inception_upper": "1980-01-01",
    "iso:country": "GB",
    "wof:name": "BH1 1QR",
    "wof:placetype": "postalcode"
  },
  "geometry": {"coordinates":[-1.868232,50.726215],"type":"Point"}
}
