{
  "type": "Feature",
  "properties": {
    "iso:country":"GB",
    "wof:name":"S65 4JF",
    "wof:placetype":"postalcode"
},
  "geometry": {"coordinates":[-1.30204240444974,53.44282808164274],"type":"Point"}
}