{
  "type": "Feature",
  "properties": {
    "iso:country":"GB",
    "wof:name":"G69 6HH",
    "wof:placetype":"postalcode"
},
  "geometry": {"coordinates":[-4.12960107776954,55.85284390230431],"type":"Point"}
}