{
  "type": "Feature",
  "properties": {
    "iso:country":"GB",
    "wof:name":"M28 3RH",
    "wof:placetype":"postalcode"
},
  "geometry": {"coordinates":[-2.40184771867779,53.53161967513719],"type":"Point"}
}