{
  "type": "Feature",
  "properties": {
    "iso:country":"GB",
    "wof:name":"N6 4DE",
    "wof:placetype":"postalcode"
},
  "geometry": {"coordinates":[-0.15692467376928,51.57579840382752],"type":"Point"}
}