{
  "type": "Feature",
  "properties": {
    "iso:country": "GB",
    "wof:name": "BH20 4FL",
    "wof:placetype": "postalcode"
  },
  "geometry": {"coordinates":[-2.122332,50.684813],"type":"Point"}
}
