{
  "type": "Feature",
  "properties": {
    "date:inception_lower": "2015-02-01",
    "date:inception_upper": "2015-02-01",
    "iso:country": "GB",
    "wof:name": "BH20 4FL",
    "wof:placetype": "postalcode"
  },
  "geometry": {"coordinates":[-2.122332,50.684813],"type":"Point"}
}
