{
  "type": "Feature",
  "properties": {
    "date:inception_lower":"1980-01-01",
    "date:inception_upper":"1980-01-31",
    "iso:country":"GB",
    "wof:name":"SY5 7EW",
    "wof:placetype":"postalcode"
},
  "geometry": {"coordinates":[-2.80831,52.623315],"type":"Point"}
}