{
  "type": "Feature",
  "properties": {
    "iso:country": "GB",
    "wof:name": "SY5 7EW",
    "wof:placetype": "postalcode"
  },
  "geometry": {"coordinates":[-2.80831,52.623315],"type":"Point"}
}
