{
  "type": "Feature",
  "properties": {
    "iso:country":"GB",
    "wof:name":"GU17 0BQ",
    "wof:placetype":"postalcode"
},
  "geometry": {"coordinates":[-0.78479357255543,51.33049470841357],"type":"Point"}
}