{
  "type": "Feature",
  "properties": {
    "date:inception_lower":"1981-06-01",
    "date:inception_upper":"1981-06-30",
    "iso:country":"GB",
    "wof:name":"GU17 0BQ",
    "wof:placetype":"postalcode"
},
  "geometry": {"coordinates":[-0.784794,51.330495],"type":"Point"}
}