{
  "type": "Feature",
  "properties": {
    "iso:country": "GB",
    "wof:name": "GU17 0BQ",
    "wof:placetype": "postalcode"
  },
  "geometry": {"coordinates":[-0.784794,51.330495],"type":"Point"}
}
