{
  "type": "Feature",
  "properties": {
    "iso:country":"GB",
    "wof:name":"SS17 0DQ",
    "wof:placetype":"postalcode"
},
  "geometry": {"coordinates":[0.42683512425319,51.51316816856129],"type":"Point"}
}