{
  "type": "Feature",
  "properties": {
    "date:inception_lower": "1980-01-01",
    "date:inception_upper": "1980-01-01",
    "iso:country": "GB",
    "wof:name": "SS17 0DQ",
    "wof:placetype": "postalcode"
  },
  "geometry": {"coordinates":[0.426835,51.513168],"type":"Point"}
}
