{
  "type": "Feature",
  "properties": {
    "iso:country":"GB",
    "wof:name":"M38 9UJ",
    "wof:placetype":"postalcode"
},
  "geometry": {"coordinates":[-2.42540262374695,53.53662559777113],"type":"Point"}
}