{
  "type": "Feature",
  "properties": {
    "iso:country":"GB",
    "wof:name":"GL5 1ET",
    "wof:placetype":"postalcode"
},
  "geometry": {"coordinates":[-2.21415857163746,51.74558276512051],"type":"Point"}
}