{
  "type": "Feature",
  "properties": {
    "iso:country": "GB",
    "wof:name": "OX11 0NJ",
    "wof:placetype": "postalcode"
  },
  "geometry": {"coordinates":[-1.259419,51.586682],"type":"Point"}
}
