{
  "type": "Feature",
  "properties": {
    "iso:country":"GB",
    "wof:name":"OX11 0NJ",
    "wof:placetype":"postalcode"
},
  "geometry": {"coordinates":[-1.25941940089616,51.58668212939943],"type":"Point"}
}