{
  "type": "Feature",
  "properties": {
    "iso:country": "GB",
    "wof:name": "OL6 9DA",
    "wof:placetype": "postalcode"
  },
  "geometry": {"coordinates":[-2.059527,53.50279],"type":"Point"}
}
