{
  "type": "Feature",
  "properties": {
    "iso:country":"GB",
    "wof:name":"GL52 2RR",
    "wof:placetype":"postalcode"
},
  "geometry": {"coordinates":[-2.07079131610217,51.90032958312946],"type":"Point"}
}