{
  "type": "Feature",
  "properties": {
    "iso:country":"GB",
    "wof:name":"M43 6PW",
    "wof:placetype":"postalcode"
},
  "geometry": {"coordinates":[-2.15448474125034,53.4801976926143],"type":"Point"}
}