{
  "type": "Feature",
  "properties": {
    "iso:country":"GB",
    "wof:name":"NG7 2QE",
    "wof:placetype":"postalcode"
},
  "geometry": {"coordinates":[-1.20375751020223,52.93473277138592],"type":"Point"}
}