{
  "type": "Feature",
  "properties": {
    "iso:country":"GB",
    "wof:name":"CO16 8BA",
    "wof:placetype":"postalcode"
},
  "geometry": {"coordinates":[1.12675895899387,51.80062289107523],"type":"Point"}
}