{
  "type": "Feature",
  "properties": {
    "date:inception_lower":"1980-01-01",
    "date:inception_upper":"1980-01-31",
    "iso:country":"GB",
    "wof:name":"EX19 8SF",
    "wof:placetype":"postalcode"
},
  "geometry": {"coordinates":[-4.015714,50.830983],"type":"Point"}
}