{
  "type": "Feature",
  "properties": {
    "iso:country": "GB",
    "wof:name": "EX19 8SF",
    "wof:placetype": "postalcode"
  },
  "geometry": {"coordinates":[-4.015714,50.830983],"type":"Point"}
}
