{
  "type": "Feature",
  "properties": {
    "date:inception_lower": "1980-01-01",
    "date:inception_upper": "1980-01-01",
    "iso:country": "GB",
    "wof:name": "GL5 4TU",
    "wof:placetype": "postalcode"
  },
  "geometry": {"coordinates":[-2.256176,51.740945],"type":"Point"}
}
