{
  "type": "Feature",
  "properties": {
    "iso:country":"GB",
    "wof:name":"DE74 2AH",
    "wof:placetype":"postalcode"
},
  "geometry": {"coordinates":[-1.3234867202358,52.81605759924172],"type":"Point"}
}