{
  "type": "Feature",
  "properties": {
    "iso:country":"GB",
    "wof:name":"SE7 7ST",
    "wof:placetype":"postalcode"
},
  "geometry": {"coordinates":[0.02221669654708,51.48855058484784],"type":"Point"}
}