{
  "type": "Feature",
  "properties": {
    "date:inception_lower": "2021-01-01",
    "date:inception_upper": "2021-01-01",
    "iso:country": "GB",
    "wof:name": "NG23 7BW",
    "wof:placetype": "postalcode"
  },
  "geometry": {"coordinates":[-0.714736,53.23666],"type":"Point"}
}
