{
  "type": "Feature",
  "properties": {
    "iso:country":"GB",
    "wof:name":"RG21 5TF",
    "wof:placetype":"postalcode"
},
  "geometry": {"coordinates":[-1.09307292325356,51.27179934383682],"type":"Point"}
}