{
  "type": "Feature",
  "properties": {
    "date:inception_lower":"1980-01-01",
    "date:inception_upper":"1980-01-31",
    "iso:country":"GB",
    "wof:name":"SA69 9EW",
    "wof:placetype":"postalcode"
},
  "geometry": {"coordinates":[-4.699464,51.710873],"type":"Point"}
}