{
  "type": "Feature",
  "properties": {
    "date:inception_lower": "1980-01-01",
    "date:inception_upper": "1980-01-01",
    "iso:country": "GB",
    "wof:name": "PE19 1AZ",
    "wof:placetype": "postalcode"
  },
  "geometry": {"coordinates":[-0.265578,52.23027],"type":"Point"}
}
