{
  "type": "Feature",
  "properties": {
    "iso:country":"GB",
    "wof:name":"WV4 6JT",
    "wof:placetype":"postalcode"
},
  "geometry": {"coordinates":[-2.10172265931103,52.5599104295466],"type":"Point"}
}