{
  "type": "Feature",
  "properties": {
    "iso:country": "GB",
    "wof:name": "ME17 1UD",
    "wof:placetype": "postalcode"
  },
  "geometry": {"coordinates":[0.635639,51.262538],"type":"Point"}
}
