{
  "type": "Feature",
  "properties": {
    "iso:country":"GB",
    "wof:name":"ME17 1UD",
    "wof:placetype":"postalcode"
},
  "geometry": {"coordinates":[0.63563921190764,51.26253764624106],"type":"Point"}
}