{
  "type": "Feature",
  "properties": {
    "date:inception_lower": "2023-03-01",
    "date:inception_upper": "2023-03-01",
    "iso:country": "GB",
    "wof:name": "LU7 3SF",
    "wof:placetype": "postalcode"
  },
  "geometry": {"coordinates":[-0.641458,51.932327],"type":"Point"}
}
