{
  "type": "Feature",
  "properties": {
    "date:inception_lower": "1994-12-01",
    "date:inception_upper": "1994-12-01",
    "iso:country": "GB",
    "wof:name": "SO16 3HU",
    "wof:placetype": "postalcode"
  },
  "geometry": {"coordinates":[-1.398005,50.938571],"type":"Point"}
}
