{
  "type": "Feature",
  "properties": {
    "iso:country":"GB",
    "wof:name":"SL2 1HA",
    "wof:placetype":"postalcode"
},
  "geometry": {"coordinates":[-0.6169707670828,51.52817845032175],"type":"Point"}
}