{
  "type": "Feature",
  "properties": {
    "iso:country":"GB",
    "wof:name":"TS19 7ET",
    "wof:placetype":"postalcode"
},
  "geometry": {"coordinates":[-1.35296294509792,54.56834466185585],"type":"Point"}
}