{
  "type": "Feature",
  "properties": {
    "iso:country":"GB",
    "wof:name":"G65 0DR",
    "wof:placetype":"postalcode"
},
  "geometry": {"coordinates":[-4.04420155879162,55.97739568627089],"type":"Point"}
}