{
  "type": "Feature",
  "properties": {
    "iso:country": "GB",
    "wof:name": "G65 0DR",
    "wof:placetype": "postalcode"
  },
  "geometry": {"coordinates":[-4.044256,55.977075],"type":"Point"}
}
