{
  "type": "Feature",
  "properties": {
    "date:inception_lower":"2015-09-01",
    "date:inception_upper":"2015-09-30",
    "iso:country":"GB",
    "wof:name":"G65 0DR",
    "wof:placetype":"postalcode"
},
  "geometry": {"coordinates":[-4.044256,55.977075],"type":"Point"}
}