{
  "type": "Feature",
  "properties": {
    "iso:country":"GB",
    "wof:name":"CR0 8NW",
    "wof:placetype":"postalcode"
},
  "geometry": {"coordinates":[-0.02749289437517,51.36998255800643],"type":"Point"}
}