{
  "type": "Feature",
  "properties": {
    "date:inception_lower": "2001-06-01",
    "date:inception_upper": "2001-06-01",
    "iso:country": "GB",
    "wof:name": "RM17 6WD",
    "wof:placetype": "postalcode"
  },
  "geometry": {"coordinates":[0.335816,51.475968],"type":"Point"}
}
