{
  "type": "Feature",
  "properties": {
    "iso:country":"GB",
    "wof:name":"MK13 7DP",
    "wof:placetype":"postalcode"
},
  "geometry": {"coordinates":[-0.78416685485923,52.05557347996589],"type":"Point"}
}