{
  "type": "Feature",
  "properties": {
    "iso:country": "GB",
    "wof:name": "MK13 7DP",
    "wof:placetype": "postalcode"
  },
  "geometry": {"coordinates":[-0.784167,52.055573],"type":"Point"}
}
