{
  "type": "Feature",
  "properties": {
    "date:inception_lower": "2005-03-01",
    "date:inception_upper": "2005-03-01",
    "iso:country": "GB",
    "wof:name": "ML5 1EE",
    "wof:placetype": "postalcode"
  },
  "geometry": {"coordinates":[-4.02921,55.856653],"type":"Point"}
}
