{
  "type": "Feature",
  "properties": {
    "iso:country": "GB",
    "wof:name": "ML5 1EE",
    "wof:placetype": "postalcode"
  },
  "geometry": {"coordinates":[-4.02921,55.856653],"type":"Point"}
}
