{
  "type": "Feature",
  "properties": {
    "iso:country":"GB",
    "wof:name":"ML5 1EE",
    "wof:placetype":"postalcode"
},
  "geometry": {"coordinates":[-4.02921046160295,55.85665291897036],"type":"Point"}
}