{
  "type": "Feature",
  "properties": {
    "iso:country":"GB",
    "wof:name":"CH3 7EH",
    "wof:placetype":"postalcode"
},
  "geometry": {"coordinates":[-2.8498722093751,53.2023477162999],"type":"Point"}
}