{
  "type": "Feature",
  "properties": {
    "iso:country": "GB",
    "wof:name": "WS12 4UD",
    "wof:placetype": "postalcode"
  },
  "geometry": {"coordinates":[-2.042068,52.71101],"type":"Point"}
}
