{
  "type": "Feature",
  "properties": {
    "iso:country":"GB",
    "wof:name":"TQ1 3RG",
    "wof:placetype":"postalcode"
},
  "geometry": {"coordinates":[-3.518627022622,50.47501003227018],"type":"Point"}
}