{
  "type": "Feature",
  "properties": {
    "iso:country":"GB",
    "wof:name":"SK8 1EJ",
    "wof:placetype":"postalcode"
},
  "geometry": {"coordinates":[-2.21060613654277,53.39053225145368],"type":"Point"}
}