{
  "type": "Feature",
  "properties": {
    "iso:country": "GB",
    "wof:name": "SK8 1EJ",
    "wof:placetype": "postalcode"
  },
  "geometry": {"coordinates":[-2.210606,53.390532],"type":"Point"}
}
