{
  "type": "Feature",
  "properties": {
    "iso:country":"GB",
    "wof:name":"NN14 2WS",
    "wof:placetype":"postalcode"
},
  "geometry": {"coordinates":[-0.82662341146791,52.44871192417179],"type":"Point"}
}