{
  "type": "Feature",
  "properties": {
    "date:inception_lower": "2015-06-01",
    "date:inception_upper": "2015-06-01",
    "iso:country": "GB",
    "wof:name": "NN14 2WS",
    "wof:placetype": "postalcode"
  },
  "geometry": {"coordinates":[-0.826623,52.448712],"type":"Point"}
}
