{
  "type": "Feature",
  "properties": {
    "iso:country":"GB",
    "wof:name":"SW9 0UY",
    "wof:placetype":"postalcode"
},
  "geometry": {"coordinates":[-0.11660942896573,51.46836309052359],"type":"Point"}
}