{
  "type": "Feature",
  "properties": {
    "iso:country": "GB",
    "wof:name": "HD7 6JL",
    "wof:placetype": "postalcode"
  },
  "geometry": {"coordinates":[-1.920296,53.601344],"type":"Point"}
}
