{
  "type": "Feature",
  "properties": {
    "iso:country":"GB",
    "wof:name":"CV9 2JT",
    "wof:placetype":"postalcode"
},
  "geometry": {"coordinates":[-1.60574899052189,52.539107534695],"type":"Point"}
}