{
  "type": "Feature",
  "properties": {
    "iso:country":"GB",
    "wof:name":"B13 8LX",
    "wof:placetype":"postalcode"
},
  "geometry": {"coordinates":[-1.89764692872997,52.45088055930898],"type":"Point"}
}