{
  "type": "Feature",
  "properties": {
    "iso:country":"GB",
    "wof:name":"B44 8UQ",
    "wof:placetype":"postalcode"
},
  "geometry": {"coordinates":[-1.9007963394256,52.54251765046814],"type":"Point"}
}