{
  "type": "Feature",
  "properties": {
    "iso:country":"GB",
    "wof:name":"LE65 1WQ",
    "wof:placetype":"postalcode"
},
  "geometry": {"coordinates":[-1.47519514432383,52.72408810649101],"type":"Point"}
}