{
  "type": "Feature",
  "properties": {
    "date:inception_lower":"1992-08-01",
    "date:inception_upper":"1992-08-31",
    "iso:country":"GB",
    "wof:name":"LE65 1WQ",
    "wof:placetype":"postalcode"
},
  "geometry": {"coordinates":[-1.475195,52.724088],"type":"Point"}
}