{
  "type": "Feature",
  "properties": {
    "iso:country": "GB",
    "wof:name": "LE65 1WQ",
    "wof:placetype": "postalcode"
  },
  "geometry": {"coordinates":[-1.475195,52.724088],"type":"Point"}
}
