{
  "type": "Feature",
  "properties": {
    "iso:country":"GB",
    "wof:name":"B21 0AB",
    "wof:placetype":"postalcode"
},
  "geometry": {"coordinates":[-1.95716871564232,52.50974724034759],"type":"Point"}
}