{
  "type": "Feature",
  "properties": {
    "date:inception_lower":"1995-07-01",
    "date:inception_upper":"1995-07-31",
    "iso:country":"GB",
    "wof:name":"B21 0AB",
    "wof:placetype":"postalcode"
},
  "geometry": {"coordinates":[-1.957169,52.509747],"type":"Point"}
}