{
  "type": "Feature",
  "properties": {
    "iso:country":"GB",
    "wof:name":"BD23 5NJ",
    "wof:placetype":"postalcode"
},
  "geometry": {"coordinates":[-2.00299025803716,54.07181532008231],"type":"Point"}
}