{
  "type": "Feature",
  "properties": {
    "iso:country": "GB",
    "wof:name": "L33 8XT",
    "wof:placetype": "postalcode"
  },
  "geometry": {"coordinates":[-2.878293,53.484664],"type":"Point"}
}
