{
  "type": "Feature",
  "properties": {
    "iso:country":"GB",
    "wof:name":"BH25 5DF",
    "wof:placetype":"postalcode"
},
  "geometry": {"coordinates":[-1.64394071107135,50.75671683326031],"type":"Point"}
}