{
  "type": "Feature",
  "properties": {
    "iso:country": "GB",
    "wof:name": "BA2 0HH",
    "wof:placetype": "postalcode"
  },
  "geometry": {"coordinates":[-2.504798,51.332569],"type":"Point"}
}
