{
  "type": "Feature",
  "properties": {
    "iso:country":"GB",
    "wof:name":"BA2 0HH",
    "wof:placetype":"postalcode"
},
  "geometry": {"coordinates":[-2.5047976938653,51.33256859975599],"type":"Point"}
}