{
  "type": "Feature",
  "properties": {
    "date:inception_lower": "1999-06-01",
    "date:inception_upper": "1999-06-01",
    "iso:country": "GB",
    "wof:name": "CA7 0AF",
    "wof:placetype": "postalcode"
  },
  "geometry": {"coordinates":[-3.180746,54.819907],"type":"Point"}
}
