{
  "type": "Feature",
  "properties": {
    "date:inception_lower": "2002-12-01",
    "date:inception_upper": "2002-12-01",
    "iso:country": "GB",
    "wof:name": "DN4 6FJ",
    "wof:placetype": "postalcode"
  },
  "geometry": {"coordinates":[-1.074557,53.51482],"type":"Point"}
}
