{
  "type": "Feature",
  "properties": {
    "iso:country": "GB",
    "wof:name": "DN4 6FJ",
    "wof:placetype": "postalcode"
  },
  "geometry": {"coordinates":[-1.074557,53.51482],"type":"Point"}
}
