{
  "type": "Feature",
  "properties": {
    "iso:country":"GB",
    "wof:name":"DN4 6FJ",
    "wof:placetype":"postalcode"
},
  "geometry": {"coordinates":[-1.07455754263724,53.51482008941809],"type":"Point"}
}