{
  "type": "Feature",
  "properties": {
    "iso:country":"GB",
    "wof:name":"KT20 6LN",
    "wof:placetype":"postalcode"
},
  "geometry": {"coordinates":[-0.20027419624995,51.297675346235],"type":"Point"}
}