{
  "type": "Feature",
  "properties": {
    "date:inception_lower": "2018-02-01",
    "date:inception_upper": "2018-02-01",
    "iso:country": "GB",
    "wof:name": "FY4 5GS",
    "wof:placetype": "postalcode"
  },
  "geometry": {"coordinates":[-3.018118,53.783861],"type":"Point"}
}
