{
  "type": "Feature",
  "properties": {
    "iso:country":"GB",
    "wof:name":"HD7 4DE",
    "wof:placetype":"postalcode"
},
  "geometry": {"coordinates":[-1.8440551083138,53.64373898666206],"type":"Point"}
}