{
  "type": "Feature",
  "properties": {
    "date:inception_lower": "1980-01-01",
    "date:inception_upper": "1980-01-01",
    "iso:country": "GB",
    "wof:name": "HD7 4DE",
    "wof:placetype": "postalcode"
  },
  "geometry": {"coordinates":[-1.844055,53.643739],"type":"Point"}
}
