{
  "type": "Feature",
  "properties": {
    "iso:country": "GB",
    "wof:name": "HD8 8RS",
    "wof:placetype": "postalcode"
  },
  "geometry": {"coordinates":[-1.657588,53.573225],"type":"Point"}
}
