{
  "type": "Feature",
  "properties": {
    "iso:country":"GB",
    "wof:name":"BS1 4QY",
    "wof:placetype":"postalcode"
},
  "geometry": {"coordinates":[-2.59504936490788,51.44958580052309],"type":"Point"}
}