{
  "type": "Feature",
  "properties": {
    "iso:country":"GB",
    "wof:name":"EH14 6AL",
    "wof:placetype":"postalcode"
},
  "geometry": {"coordinates":[-3.30790760791741,55.89534207221217],"type":"Point"}
}