{
  "type": "Feature",
  "properties": {
    "iso:country": "GB",
    "wof:name": "EH14 6AL",
    "wof:placetype": "postalcode"
  },
  "geometry": {"coordinates":[-3.307908,55.895342],"type":"Point"}
}
