{
  "type": "Feature",
  "properties": {
    "iso:country": "GB",
    "wof:name": "RG21 7LZ",
    "wof:placetype": "postalcode"
  },
  "geometry": {"coordinates":[-1.087307,51.262322],"type":"Point"}
}
