{
  "type": "Feature",
  "properties": {
    "iso:country":"GB",
    "wof:name":"CB6 2AG",
    "wof:placetype":"postalcode"
},
  "geometry": {"coordinates":[0.12280338835878,52.40305653273246],"type":"Point"}
}