{
  "type": "Feature",
  "properties": {
    "iso:country": "GB",
    "wof:name": "CB6 2AG",
    "wof:placetype": "postalcode"
  },
  "geometry": {"coordinates":[0.122803,52.403057],"type":"Point"}
}
