{
  "type": "Feature",
  "properties": {
    "date:inception_lower": "1980-01-01",
    "date:inception_upper": "1980-01-01",
    "iso:country": "GB",
    "wof:name": "CB6 2AG",
    "wof:placetype": "postalcode"
  },
  "geometry": {"coordinates":[0.122803,52.403057],"type":"Point"}
}
