{
  "type": "Feature",
  "properties": {
    "iso:country": "GB",
    "wof:name": "RG25 2FD",
    "wof:placetype": "postalcode"
  },
  "geometry": {"coordinates":[-1.038952,51.204017],"type":"Point"}
}
