{
  "type": "Feature",
  "properties": {
    "date:inception_lower": "1984-02-01",
    "date:inception_upper": "1984-02-01",
    "iso:country": "GB",
    "wof:name": "NE38 0EQ",
    "wof:placetype": "postalcode"
  },
  "geometry": {"coordinates":[-1.549139,54.887946],"type":"Point"}
}
