{
  "type": "Feature",
  "properties": {
    "iso:country":"GB",
    "wof:name":"NE38 0EQ",
    "wof:placetype":"postalcode"
},
  "geometry": {"coordinates":[-1.54913917781783,54.88794569070565],"type":"Point"}
}