{
  "type": "Feature",
  "properties": {
    "iso:country":"GB",
    "wof:name":"BS6 7QP",
    "wof:placetype":"postalcode"
},
  "geometry": {"coordinates":[-2.61497630166494,51.47927221429446],"type":"Point"}
}