{
  "type": "Feature",
  "properties": {
    "iso:country":"GB",
    "wof:name":"KY1 4AL",
    "wof:placetype":"postalcode"
},
  "geometry": {"coordinates":[-3.14609950251427,56.1637286064994],"type":"Point"}
}