{
  "type": "Feature",
  "properties": {
    "iso:country": "GB",
    "wof:name": "KY1 4AL",
    "wof:placetype": "postalcode"
  },
  "geometry": {"coordinates":[-3.146099,56.163729],"type":"Point"}
}
