{
  "type": "Feature",
  "properties": {
    "iso:country": "GB",
    "wof:name": "SP6 3QX",
    "wof:placetype": "postalcode"
  },
  "geometry": {"coordinates":[-1.807093,50.972605],"type":"Point"}
}
