{
  "type": "Feature",
  "properties": {
    "iso:country":"GB",
    "wof:name":"SP6 3QX",
    "wof:placetype":"postalcode"
},
  "geometry": {"coordinates":[-1.80709278748396,50.97260465675108],"type":"Point"}
}