{
  "type": "Feature",
  "properties": {
    "iso:country": "GB",
    "wof:name": "OL4 3ER",
    "wof:placetype": "postalcode"
  },
  "geometry": {"coordinates":[-2.083473,53.543502],"type":"Point"}
}
