{
  "type": "Feature",
  "properties": {
    "iso:country":"GB",
    "wof:name":"OL4 3ER",
    "wof:placetype":"postalcode"
},
  "geometry": {"coordinates":[-2.08347290044687,53.54350186596662],"type":"Point"}
}