{
  "type": "Feature",
  "properties": {
    "iso:country":"GB",
    "wof:name":"GL7 2HQ",
    "wof:placetype":"postalcode"
},
  "geometry": {"coordinates":[-1.96272865219858,51.72753857162211],"type":"Point"}
}