{
  "type": "Feature",
  "properties": {
    "iso:country": "GB",
    "wof:name": "BH19 2FA",
    "wof:placetype": "postalcode"
  },
  "geometry": {"coordinates":[-1.953284,50.60718],"type":"Point"}
}
