{
  "type": "Feature",
  "properties": {
    "date:inception_lower":"2014-01-01",
    "date:inception_upper":"2014-01-31",
    "iso:country":"GB",
    "wof:name":"BH19 2FA",
    "wof:placetype":"postalcode"
},
  "geometry": {"coordinates":[-1.953284,50.60718],"type":"Point"}
}