{
  "type": "Feature",
  "properties": {
    "iso:country": "GB",
    "wof:name": "LA6 1BJ",
    "wof:placetype": "postalcode"
  },
  "geometry": {"coordinates":[-2.730617,54.206091],"type":"Point"}
}
