{
  "type": "Feature",
  "properties": {
    "iso:country":"GB",
    "wof:name":"UB8 2HP",
    "wof:placetype":"postalcode"
},
  "geometry": {"coordinates":[-0.47813422759359,51.51765635595481],"type":"Point"}
}