{
  "type": "Feature",
  "properties": {
    "date:inception_lower": "1980-01-01",
    "date:inception_upper": "1980-01-01",
    "iso:country": "GB",
    "wof:name": "B61 8LN",
    "wof:placetype": "postalcode"
  },
  "geometry": {"coordinates":[-2.065831,52.342027],"type":"Point"}
}
