{
  "type": "Feature",
  "properties": {
    "date:inception_lower":"1980-01-01",
    "date:inception_upper":"1980-01-31",
    "iso:country":"GB",
    "wof:name":"N6 6AT",
    "wof:placetype":"postalcode"
},
  "geometry": {"coordinates":[-0.152807,51.561679],"type":"Point"}
}