{
  "type": "Feature",
  "properties": {
    "iso:country":"GB",
    "wof:name":"N6 6AT",
    "wof:placetype":"postalcode"
},
  "geometry": {"coordinates":[-0.15280675098809,51.56167851018856],"type":"Point"}
}