{
  "type": "Feature",
  "properties": {
    "date:inception_lower": "2020-04-01",
    "date:inception_upper": "2020-04-01",
    "iso:country": "GB",
    "wof:name": "OX1 9DY",
    "wof:placetype": "postalcode"
  },
  "geometry": {"coordinates":[-1.267348,51.750236],"type":"Point"}
}
