{
  "type": "Feature",
  "properties": {
    "date:inception_lower": "2010-10-01",
    "date:inception_upper": "2010-10-01",
    "iso:country": "GB",
    "wof:name": "RG1 8FN",
    "wof:placetype": "postalcode"
  },
  "geometry": {"coordinates":[-0.989629,51.461861],"type":"Point"}
}
