{
  "type": "Feature",
  "properties": {
    "iso:country":"GB",
    "wof:name":"TA12 6BN",
    "wof:placetype":"postalcode"
},
  "geometry": {"coordinates":[-2.82070926137299,50.98117304641277],"type":"Point"}
}