{
  "type": "Feature",
  "properties": {
    "iso:country":"GB",
    "wof:name":"M45 8RF",
    "wof:placetype":"postalcode"
},
  "geometry": {"coordinates":[-2.27285460154701,53.55440984094255],"type":"Point"}
}