{
  "type": "Feature",
  "properties": {
    "iso:country": "GB",
    "wof:name": "M45 8RF",
    "wof:placetype": "postalcode"
  },
  "geometry": {"coordinates":[-2.272855,53.55441],"type":"Point"}
}
