{
  "type": "Feature",
  "properties": {
    "iso:country":"GB",
    "wof:name":"SS9 2TB",
    "wof:placetype":"postalcode"
},
  "geometry": {"coordinates":[0.62717591474278,51.54710881365628],"type":"Point"}
}