{
  "type": "Feature",
  "properties": {
    "iso:country": "GB",
    "wof:name": "PL27 6FG",
    "wof:placetype": "postalcode"
  },
  "geometry": {"coordinates":[-4.923119,50.56309],"type":"Point"}
}
