{
  "type": "Feature",
  "properties": {
    "iso:country":"GB",
    "wof:name":"WA16 7AH",
    "wof:placetype":"postalcode"
},
  "geometry": {"coordinates":[-2.3038542487394,53.31131178150545],"type":"Point"}
}