{
  "type": "Feature",
  "properties": {
    "iso:country": "GB",
    "wof:name": "FK7 0EH",
    "wof:placetype": "postalcode"
  },
  "geometry": {"coordinates":[-3.917835,56.094437],"type":"Point"}
}
