{
  "type": "Feature",
  "properties": {
    "iso:country": "GB",
    "wof:name": "GL54 2RB",
    "wof:placetype": "postalcode"
  },
  "geometry": {"coordinates":[-1.695121,51.872695],"type":"Point"}
}
