{
  "type": "Feature",
  "properties": {
    "date:inception_lower": "2016-09-01",
    "date:inception_upper": "2016-09-01",
    "iso:country": "GB",
    "wof:name": "GL54 2RB",
    "wof:placetype": "postalcode"
  },
  "geometry": {"coordinates":[-1.695121,51.872695],"type":"Point"}
}
