{
  "type": "Feature",
  "properties": {
    "iso:country":"GB",
    "wof:name":"CR2 6AH",
    "wof:placetype":"postalcode"
},
  "geometry": {"coordinates":[-0.09819053902727,51.35340888331019],"type":"Point"}
}