{
  "type": "Feature",
  "properties": {
    "date:inception_lower": "2000-12-01",
    "date:inception_upper": "2000-12-01",
    "iso:country": "GB",
    "wof:name": "L15 4QB",
    "wof:placetype": "postalcode"
  },
  "geometry": {"coordinates":[-2.92588,53.402776],"type":"Point"}
}
