{
  "type": "Feature",
  "properties": {
    "iso:country":"GB",
    "wof:name":"B20 3ET",
    "wof:placetype":"postalcode"
},
  "geometry": {"coordinates":[-1.89653159067028,52.51254171987375],"type":"Point"}
}