{
  "type": "Feature",
  "properties": {
    "iso:country":"GB",
    "wof:name":"LU4 9XT",
    "wof:placetype":"postalcode"
},
  "geometry": {"coordinates":[-0.47420502654858,51.90507420041263],"type":"Point"}
}