{
  "type": "Feature",
  "properties": {
    "iso:country":"GB",
    "wof:name":"BS15 4GY",
    "wof:placetype":"postalcode"
},
  "geometry": {"coordinates":[-2.49696624006219,51.47494051107537],"type":"Point"}
}