{
  "type": "Feature",
  "properties": {
    "iso:country":"GB",
    "wof:name":"TN40 2QH",
    "wof:placetype":"postalcode"
},
  "geometry": {"coordinates":[0.49760145031082,50.85064826343408],"type":"Point"}
}