{
  "type": "Feature",
  "properties": {
    "date:inception_lower": "1980-01-01",
    "date:inception_upper": "1980-01-01",
    "iso:country": "GB",
    "wof:name": "AL2 1DN",
    "wof:placetype": "postalcode"
  },
  "geometry": {"coordinates":[-0.30698,51.731282],"type":"Point"}
}
