{
  "type": "Feature",
  "properties": {
    "iso:country":"GB",
    "wof:name":"SN2 5HG",
    "wof:placetype":"postalcode"
},
  "geometry": {"coordinates":[-1.7793394547823,51.59469011171429],"type":"Point"}
}