{
  "type": "Feature",
  "properties": {
    "iso:country":"GB",
    "wof:name":"S10 3RN",
    "wof:placetype":"postalcode"
},
  "geometry": {"coordinates":[-1.54373814039745,53.36534459129326],"type":"Point"}
}