{
  "type": "Feature",
  "properties": {
    "iso:country":"GB",
    "wof:name":"LE5 6PQ",
    "wof:placetype":"postalcode"
},
  "geometry": {"coordinates":[-1.06034140558451,52.62987461026282],"type":"Point"}
}