{
  "type": "Feature",
  "properties": {
    "iso:country":"GB",
    "wof:name":"MK43 9LX",
    "wof:placetype":"postalcode"
},
  "geometry": {"coordinates":[-0.51590163026163,52.06923356567108],"type":"Point"}
}