{
  "type": "Feature",
  "properties": {
    "iso:country":"GB",
    "wof:name":"AB42 2YZ",
    "wof:placetype":"postalcode"
},
  "geometry": {"coordinates":[-1.80435850432493,57.50129274084553],"type":"Point"}
}