{
  "type": "Feature",
  "properties": {
    "iso:country":"GB",
    "wof:name":"SR6 9EY",
    "wof:placetype":"postalcode"
},
  "geometry": {"coordinates":[-1.3785879458945,54.92690468207095],"type":"Point"}
}