{
  "type": "Feature",
  "properties": {
    "iso:country": "GB",
    "wof:name": "SR6 9EY",
    "wof:placetype": "postalcode"
  },
  "geometry": {"coordinates":[-1.378588,54.926905],"type":"Point"}
}
