{
  "type": "Feature",
  "properties": {
    "date:inception_lower":"1980-01-01",
    "date:inception_upper":"1980-01-31",
    "iso:country":"GB",
    "wof:name":"SA32 7PE",
    "wof:placetype":"postalcode"
},
  "geometry": {"coordinates":[-4.158297,51.891234],"type":"Point"}
}