{
  "type": "Feature",
  "properties": {
    "iso:country": "GB",
    "wof:name": "SA32 7PE",
    "wof:placetype": "postalcode"
  },
  "geometry": {"coordinates":[-4.160084,51.889708],"type":"Point"}
}
