{
  "type": "Feature",
  "properties": {
    "iso:country":"GB",
    "wof:name":"SA32 7PE",
    "wof:placetype":"postalcode"
},
  "geometry": {"coordinates":[-4.16006439376639,51.88969938291812],"type":"Point"}
}