{
  "type": "Feature",
  "properties": {
    "date:inception_lower": "1980-01-01",
    "date:inception_upper": "1980-01-01",
    "iso:country": "GB",
    "wof:name": "SA32 7PE",
    "wof:placetype": "postalcode"
  },
  "geometry": {"coordinates":[-4.160084,51.889708],"type":"Point"}
}
