{
  "type": "Feature",
  "properties": {
    "iso:country": "GB",
    "wof:name": "CV12 9NG",
    "wof:placetype": "postalcode"
  },
  "geometry": {"coordinates":[-1.424691,52.476048],"type":"Point"}
}
