{
  "type": "Feature",
  "properties": {
    "iso:country":"GB",
    "wof:name":"CV12 9NG",
    "wof:placetype":"postalcode"
},
  "geometry": {"coordinates":[-1.42469055744239,52.4760475713495],"type":"Point"}
}