{
  "type": "Feature",
  "properties": {
    "iso:country": "GB",
    "wof:name": "NN8 9SX",
    "wof:placetype": "postalcode"
  },
  "geometry": {"coordinates":[-0.690868,52.29912],"type":"Point"}
}
