{
  "type": "Feature",
  "properties": {
    "iso:country":"GB",
    "wof:name":"DN21 2QE",
    "wof:placetype":"postalcode"
},
  "geometry": {"coordinates":[-0.77516403084706,53.40865506166531],"type":"Point"}
}