{
  "type": "Feature",
  "properties": {
    "iso:country":"GB",
    "wof:name":"EH29 9EY",
    "wof:placetype":"postalcode"
},
  "geometry": {"coordinates":[-3.41150777080225,55.96017148968934],"type":"Point"}
}