{
  "type": "Feature",
  "properties": {
    "iso:country":"GB",
    "wof:name":"SE15 5EF",
    "wof:placetype":"postalcode"
},
  "geometry": {"coordinates":[-0.06660892828594,51.47338544839218],"type":"Point"}
}