{
  "type": "Feature",
  "properties": {
    "iso:country":"GB",
    "wof:name":"DY5 2AY",
    "wof:placetype":"postalcode"
},
  "geometry": {"coordinates":[-2.10259925097295,52.4679428951592],"type":"Point"}
}