{
  "type": "Feature",
  "properties": {
    "date:inception_lower":"1980-01-01",
    "date:inception_upper":"1980-01-31",
    "iso:country":"GB",
    "wof:name":"DY5 2AY",
    "wof:placetype":"postalcode"
},
  "geometry": {"coordinates":[-2.102599,52.467943],"type":"Point"}
}