{
  "type": "Feature",
  "properties": {
    "iso:country":"GB",
    "wof:name":"EX15 1ST",
    "wof:placetype":"postalcode"
},
  "geometry": {"coordinates":[-3.39400376542245,50.8582353947323],"type":"Point"}
}