{
  "type": "Feature",
  "properties": {
    "date:inception_lower": "1986-04-01",
    "date:inception_upper": "1986-04-01",
    "iso:country": "GB",
    "wof:name": "EX15 1ST",
    "wof:placetype": "postalcode"
  },
  "geometry": {"coordinates":[-3.394004,50.858235],"type":"Point"}
}
