{
  "type": "Feature",
  "properties": {
    "iso:country": "GB",
    "wof:name": "OL16 4RY",
    "wof:placetype": "postalcode"
  },
  "geometry": {"coordinates":[-2.138183,53.58735],"type":"Point"}
}
