{
  "type": "Feature",
  "properties": {
    "iso:country":"GB",
    "wof:name":"SG8 6JU",
    "wof:placetype":"postalcode"
},
  "geometry": {"coordinates":[0.00824571054193,52.09180594873074],"type":"Point"}
}