{
  "type": "Feature",
  "properties": {
    "date:inception_lower": "1980-01-01",
    "date:inception_upper": "1980-01-01",
    "iso:country": "GB",
    "wof:name": "SG8 6JU",
    "wof:placetype": "postalcode"
  },
  "geometry": {"coordinates":[0.008246,52.091806],"type":"Point"}
}
