{
  "type": "Feature",
  "properties": {
    "iso:country":"GB",
    "wof:name":"NG18 2NS",
    "wof:placetype":"postalcode"
},
  "geometry": {"coordinates":[-1.17591685411233,53.14536149871648],"type":"Point"}
}