{
  "type": "Feature",
  "properties": {
    "date:inception_lower":"2009-09-01",
    "date:inception_upper":"2009-09-30",
    "iso:country":"GB",
    "wof:name":"SA4 8BH",
    "wof:placetype":"postalcode"
},
  "geometry": {"coordinates":[-4.029073,51.70867],"type":"Point"}
}