{
  "type": "Feature",
  "properties": {
    "iso:country":"GB",
    "wof:name":"SA4 8BH",
    "wof:placetype":"postalcode"
},
  "geometry": {"coordinates":[-4.0290727411444,51.70866961504964],"type":"Point"}
}