{
  "type": "Feature",
  "properties": {
    "date:inception_lower": "1980-01-01",
    "date:inception_upper": "1980-01-01",
    "iso:country": "GB",
    "wof:name": "SK15 1QQ",
    "wof:placetype": "postalcode"
  },
  "geometry": {"coordinates":[-2.07291,53.483105],"type":"Point"}
}
