{
  "type": "Feature",
  "properties": {
    "iso:country": "GB",
    "wof:name": "SK15 1QQ",
    "wof:placetype": "postalcode"
  },
  "geometry": {"coordinates":[-2.069686,53.483091],"type":"Point"}
}
