{
  "type": "Feature",
  "properties": {
    "iso:country":"GB",
    "wof:name":"SR8 3QQ",
    "wof:placetype":"postalcode"
},
  "geometry": {"coordinates":[-1.32304889288582,54.78848450163017],"type":"Point"}
}