{
  "type": "Feature",
  "properties": {
    "iso:country":"GB",
    "wof:name":"SK10 5TD",
    "wof:placetype":"postalcode"
},
  "geometry": {"coordinates":[-2.09177410020521,53.27233823037207],"type":"Point"}
}