{
  "type": "Feature",
  "properties": {
    "iso:country":"GB",
    "wof:name":"NG4 1FS",
    "wof:placetype":"postalcode"
},
  "geometry": {"coordinates":[-1.09948408977042,52.96653970017606],"type":"Point"}
}