{
  "type": "Feature",
  "properties": {
    "iso:country":"GB",
    "wof:name":"LE7 2NN",
    "wof:placetype":"postalcode"
},
  "geometry": {"coordinates":[-1.08664270850601,52.69149979146287],"type":"Point"}
}