{
  "type": "Feature",
  "properties": {
    "iso:country":"GB",
    "wof:name":"OL13 9BS",
    "wof:placetype":"postalcode"
},
  "geometry": {"coordinates":[-2.2012100503659,53.70550022735675],"type":"Point"}
}