{
  "type": "Feature",
  "properties": {
    "iso:country":"GB",
    "wof:name":"ME12 1RG",
    "wof:placetype":"postalcode"
},
  "geometry": {"coordinates":[0.76341238183659,51.44059360087996],"type":"Point"}
}