{
  "type": "Feature",
  "properties": {
    "date:inception_lower": "1980-01-01",
    "date:inception_upper": "1980-01-01",
    "iso:country": "GB",
    "wof:name": "OX4 4LG",
    "wof:placetype": "postalcode"
  },
  "geometry": {"coordinates":[-1.22,51.724859],"type":"Point"}
}
