{
  "type": "Feature",
  "properties": {
    "iso:country": "GB",
    "wof:name": "SL3 8SS",
    "wof:placetype": "postalcode"
  },
  "geometry": {"coordinates":[-0.54043,51.497245],"type":"Point"}
}
