{
  "type": "Feature",
  "properties": {
    "iso:country":"GB",
    "wof:name":"SL3 8SS",
    "wof:placetype":"postalcode"
},
  "geometry": {"coordinates":[-0.54043019198534,51.49724458366067],"type":"Point"}
}