{
  "type": "Feature",
  "properties": {
    "iso:country": "GB",
    "wof:name": "G42 0NJ",
    "wof:placetype": "postalcode"
  },
  "geometry": {"coordinates":[-4.239847,55.830668],"type":"Point"}
}
