{
  "type": "Feature",
  "properties": {
    "iso:country":"GB",
    "wof:name":"SG12 0DF",
    "wof:placetype":"postalcode"
},
  "geometry": {"coordinates":[-0.03833853818349,51.81168846420216],"type":"Point"}
}