{
  "type": "Feature",
  "properties": {
    "iso:country": "GB",
    "wof:name": "CO6 1FF",
    "wof:placetype": "postalcode"
  },
  "geometry": {"coordinates":[0.692385,51.876013],"type":"Point"}
}
