{
  "type": "Feature",
  "properties": {
    "iso:country":"GB",
    "wof:name":"CO6 1FF",
    "wof:placetype":"postalcode"
},
  "geometry": {"coordinates":[0.69238538211121,51.87601278075741],"type":"Point"}
}