{
  "type": "Feature",
  "properties": {
    "date:inception_lower": "2005-04-01",
    "date:inception_upper": "2005-04-01",
    "iso:country": "GB",
    "wof:name": "EH95 1AD",
    "wof:placetype": "postalcode"
  },
  "geometry": {"coordinates":[-3.25352,55.97862],"type":"Point"}
}
