{
  "type": "Feature",
  "properties": {
    "iso:country":"GB",
    "wof:name":"N6 5EE",
    "wof:placetype":"postalcode"
},
  "geometry": {"coordinates":[-0.14883853303509,51.57164252409117],"type":"Point"}
}