{
  "type": "Feature",
  "properties": {
    "iso:country":"GB",
    "wof:name":"CO5 0NJ",
    "wof:placetype":"postalcode"
},
  "geometry": {"coordinates":[0.74239334812797,51.8198357985225],"type":"Point"}
}