{
  "type": "Feature",
  "properties": {
    "iso:country":"GB",
    "wof:name":"LS26 8TX",
    "wof:placetype":"postalcode"
},
  "geometry": {"coordinates":[-1.45967298241519,53.75296160060329],"type":"Point"}
}