{
  "type": "Feature",
  "properties": {
    "iso:country": "GB",
    "wof:name": "WV3 8JR",
    "wof:placetype": "postalcode"
  },
  "geometry": {"coordinates":[-2.193142,52.578522],"type":"Point"}
}
