{
  "type": "Feature",
  "properties": {
    "iso:country": "GB",
    "wof:name": "CM12 0JD",
    "wof:placetype": "postalcode"
  },
  "geometry": {"coordinates":[0.409775,51.636034],"type":"Point"}
}
