{
  "type": "Feature",
  "properties": {
    "iso:country":"GB",
    "wof:name":"CM12 0JD",
    "wof:placetype":"postalcode"
},
  "geometry": {"coordinates":[0.40977526710657,51.63603373062401],"type":"Point"}
}