{
  "type": "Feature",
  "properties": {
    "date:inception_lower": "1980-01-01",
    "date:inception_upper": "1980-01-01",
    "iso:country": "GB",
    "wof:name": "CM12 0JD",
    "wof:placetype": "postalcode"
  },
  "geometry": {"coordinates":[0.409775,51.636034],"type":"Point"}
}
