{
  "type": "Feature",
  "properties": {
    "iso:country":"GB",
    "wof:name":"BA11 4PZ",
    "wof:placetype":"postalcode"
},
  "geometry": {"coordinates":[-2.38940194772248,51.20472235518],"type":"Point"}
}