{
  "type": "Feature",
  "properties": {
    "iso:country": "GB",
    "wof:name": "BA11 4PZ",
    "wof:placetype": "postalcode"
  },
  "geometry": {"coordinates":[-2.389402,51.204722],"type":"Point"}
}
