{
  "type": "Feature",
  "properties": {
    "iso:country":"GB",
    "wof:name":"PA34 5NJ",
    "wof:placetype":"postalcode"
},
  "geometry": {"coordinates":[-5.47304506374935,56.41503616422922],"type":"Point"}
}