{
  "type": "Feature",
  "properties": {
    "iso:country": "GB",
    "wof:name": "PA34 5NJ",
    "wof:placetype": "postalcode"
  },
  "geometry": {"coordinates":[-5.473023,56.415022],"type":"Point"}
}
