{
  "type": "Feature",
  "properties": {
    "iso:country": "GB",
    "wof:name": "PO35 5AH",
    "wof:placetype": "postalcode"
  },
  "geometry": {"coordinates":[-1.083329,50.684834],"type":"Point"}
}
