{
  "type": "Feature",
  "properties": {
    "date:inception_lower": "2017-06-01",
    "date:inception_upper": "2017-06-01",
    "iso:country": "GB",
    "wof:name": "PO35 5AH",
    "wof:placetype": "postalcode"
  },
  "geometry": {"coordinates":[-1.083329,50.684834],"type":"Point"}
}
