{
  "type": "Feature",
  "properties": {
    "iso:country": "GB",
    "wof:name": "NR1 4AF",
    "wof:placetype": "postalcode"
  },
  "geometry": {"coordinates":[1.316718,52.62611],"type":"Point"}
}
