{
  "type": "Feature",
  "properties": {
    "iso:country":"GB",
    "wof:name":"HP3 9EX",
    "wof:placetype":"postalcode"
},
  "geometry": {"coordinates":[-0.46427010023084,51.74738306817931],"type":"Point"}
}