{
  "type": "Feature",
  "properties": {
    "date:inception_lower": "1980-01-01",
    "date:inception_upper": "1980-01-01",
    "iso:country": "GB",
    "wof:name": "HP3 9EX",
    "wof:placetype": "postalcode"
  },
  "geometry": {"coordinates":[-0.46427,51.747383],"type":"Point"}
}
