{
  "type": "Feature",
  "properties": {
    "iso:country":"GB",
    "wof:name":"NG23 7RQ",
    "wof:placetype":"postalcode"
},
  "geometry": {"coordinates":[-0.75905458452334,53.14342897877616],"type":"Point"}
}