{
  "type": "Feature",
  "properties": {
    "date:inception_lower": "1983-07-01",
    "date:inception_upper": "1983-07-01",
    "iso:country": "GB",
    "wof:name": "NG23 7RQ",
    "wof:placetype": "postalcode"
  },
  "geometry": {"coordinates":[-0.759055,53.143429],"type":"Point"}
}
