{
  "type": "Feature",
  "properties": {
    "iso:country":"GB",
    "wof:name":"PR8 6SJ",
    "wof:placetype":"postalcode"
},
  "geometry": {"coordinates":[-2.99669656024468,53.64311384880856],"type":"Point"}
}