{
  "type": "Feature",
  "properties": {
    "iso:country":"GB",
    "wof:name":"SL6 9SD",
    "wof:placetype":"postalcode"
},
  "geometry": {"coordinates":[-0.71047182737647,51.56187497112344],"type":"Point"}
}