{
  "type": "Feature",
  "properties": {
    "iso:country":"GB",
    "wof:name":"NP18 2LB",
    "wof:placetype":"postalcode"
},
  "geometry": {"coordinates":[-2.88961077522122,51.60935427450868],"type":"Point"}
}