{
  "type": "Feature",
  "properties": {
    "date:inception_lower": "1999-06-01",
    "date:inception_upper": "1999-06-01",
    "iso:country": "GB",
    "wof:name": "NP18 2LB",
    "wof:placetype": "postalcode"
  },
  "geometry": {"coordinates":[-2.889611,51.609354],"type":"Point"}
}
