{
  "type": "Feature",
  "properties": {
    "iso:country":"GB",
    "wof:name":"L19 3QP",
    "wof:placetype":"postalcode"
},
  "geometry": {"coordinates":[-2.9219731550009,53.36260791503923],"type":"Point"}
}