{
  "type": "Feature",
  "properties": {
    "iso:country": "GB",
    "wof:name": "NN12 8QF",
    "wof:placetype": "postalcode"
  },
  "geometry": {"coordinates":[-1.023075,52.088458],"type":"Point"}
}
