{
  "type": "Feature",
  "properties": {
    "iso:country":"GB",
    "wof:name":"DN10 5EF",
    "wof:placetype":"postalcode"
},
  "geometry": {"coordinates":[-0.97350021584372,53.40112184267689],"type":"Point"}
}