{
  "type": "Feature",
  "properties": {
    "iso:country": "GB",
    "wof:name": "CV22 7XD",
    "wof:placetype": "postalcode"
  },
  "geometry": {"coordinates":[-1.301881,52.354566],"type":"Point"}
}
