{
  "type": "Feature",
  "properties": {
    "date:inception_lower": "2017-11-01",
    "date:inception_upper": "2017-11-01",
    "iso:country": "GB",
    "wof:name": "CV22 7XD",
    "wof:placetype": "postalcode"
  },
  "geometry": {"coordinates":[-1.301881,52.354566],"type":"Point"}
}
