{
  "type": "Feature",
  "properties": {
    "iso:country":"GB",
    "wof:name":"GL5 4BZ",
    "wof:placetype":"postalcode"
},
  "geometry": {"coordinates":[-2.23512320662554,51.75232193812984],"type":"Point"}
}