{
  "type": "Feature",
  "properties": {
    "iso:country": "GB",
    "wof:name": "GL5 4BZ",
    "wof:placetype": "postalcode"
  },
  "geometry": {"coordinates":[-2.235123,51.752322],"type":"Point"}
}
