{
  "type": "Feature",
  "properties": {
    "iso:country":"GB",
    "wof:name":"PL15 8QW",
    "wof:placetype":"postalcode"
},
  "geometry": {"coordinates":[-4.55463939818323,50.64024541461525],"type":"Point"}
}