{
  "type": "Feature",
  "properties": {
    "iso:country":"GB",
    "wof:name":"PA43 7LA",
    "wof:placetype":"postalcode"
},
  "geometry": {"coordinates":[-6.28792648283891,55.75462117072796],"type":"Point"}
}