{
  "type": "Feature",
  "properties": {
    "date:inception_lower": "1980-01-01",
    "date:inception_upper": "1980-01-01",
    "iso:country": "GB",
    "wof:name": "TN22 1JD",
    "wof:placetype": "postalcode"
  },
  "geometry": {"coordinates":[0.10113,50.979639],"type":"Point"}
}
