{
  "type": "Feature",
  "properties": {
    "iso:country":"GB",
    "wof:name":"NR4 7HA",
    "wof:placetype":"postalcode"
},
  "geometry": {"coordinates":[1.26047721078026,52.62505592177127],"type":"Point"}
}