{
  "type": "Feature",
  "properties": {
    "iso:country":"GB",
    "wof:name":"W1K 4QG",
    "wof:placetype":"postalcode"
},
  "geometry": {"coordinates":[-0.14663057691228,51.51201463909091],"type":"Point"}
}