{
  "type": "Feature",
  "properties": {
    "date:inception_lower": "2000-12-01",
    "date:inception_upper": "2000-12-01",
    "iso:country": "GB",
    "wof:name": "W1K 4QG",
    "wof:placetype": "postalcode"
  },
  "geometry": {"coordinates":[-0.146631,51.512015],"type":"Point"}
}
