{
  "type": "Feature",
  "properties": {
    "iso:country": "GB",
    "wof:name": "BN16 4HU",
    "wof:placetype": "postalcode"
  },
  "geometry": {"coordinates":[-0.482708,50.826317],"type":"Point"}
}
