{
  "type": "Feature",
  "properties": {
    "iso:country":"GB",
    "wof:name":"BN16 4HU",
    "wof:placetype":"postalcode"
},
  "geometry": {"coordinates":[-0.48278054887272,50.82615541452716],"type":"Point"}
}