{
  "type": "Feature",
  "properties": {
    "iso:country":"GB",
    "wof:name":"M20 2LE",
    "wof:placetype":"postalcode"
},
  "geometry": {"coordinates":[-2.24426848353418,53.42651221339445],"type":"Point"}
}