{
  "type": "Feature",
  "properties": {
    "iso:country": "GB",
    "wof:name": "M20 2LE",
    "wof:placetype": "postalcode"
  },
  "geometry": {"coordinates":[-2.244268,53.426512],"type":"Point"}
}
