{
  "type": "Feature",
  "properties": {
    "date:inception_lower": "1985-10-01",
    "date:inception_upper": "1985-10-01",
    "iso:country": "GB",
    "wof:name": "M34 5JP",
    "wof:placetype": "postalcode"
  },
  "geometry": {"coordinates":[-2.120856,53.465576],"type":"Point"}
}
