{
  "type": "Feature",
  "properties": {
    "iso:country":"GB",
    "wof:name":"M34 5JP",
    "wof:placetype":"postalcode"
},
  "geometry": {"coordinates":[-2.1208562869706,53.46557633722427],"type":"Point"}
}