{
  "type": "Feature",
  "properties": {
    "iso:country":"GB",
    "wof:name":"AB45 1BU",
    "wof:placetype":"postalcode"
},
  "geometry": {"coordinates":[-2.53106535532827,57.66389764128925],"type":"Point"}
}