{
  "type": "Feature",
  "properties": {
    "iso:country": "GB",
    "wof:name": "LE4 7AE",
    "wof:placetype": "postalcode"
  },
  "geometry": {"coordinates":[-1.113476,52.658153],"type":"Point"}
}
