{
  "type": "Feature",
  "properties": {
    "iso:country":"GB",
    "wof:name":"LE4 7AE",
    "wof:placetype":"postalcode"
},
  "geometry": {"coordinates":[-1.11347650012743,52.65815296918859],"type":"Point"}
}