{
  "type": "Feature",
  "properties": {
    "iso:country":"GB",
    "wof:name":"ML1 9DX",
    "wof:placetype":"postalcode"
},
  "geometry": {"coordinates":[-3.99494855515898,55.79356779335154],"type":"Point"}
}