{
  "type": "Feature",
  "properties": {
    "iso:country": "GB",
    "wof:name": "SM6 7FE",
    "wof:placetype": "postalcode"
  },
  "geometry": {"coordinates":[-0.156776,51.378086],"type":"Point"}
}
