{
  "type": "Feature",
  "properties": {
    "iso:country":"GB",
    "wof:name":"M30 8PD",
    "wof:placetype":"postalcode"
},
  "geometry": {"coordinates":[-2.36170501776873,53.48410916009149],"type":"Point"}
}