{
  "type": "Feature",
  "properties": {
    "date:inception_lower": "1980-01-01",
    "date:inception_upper": "1980-01-01",
    "iso:country": "GB",
    "wof:name": "SN11 0LG",
    "wof:placetype": "postalcode"
  },
  "geometry": {"coordinates":[-1.997578,51.426451],"type":"Point"}
}
