{
  "type": "Feature",
  "properties": {
    "iso:country":"GB",
    "wof:name":"SN11 0LG",
    "wof:placetype":"postalcode"
},
  "geometry": {"coordinates":[-1.99757789931969,51.42645120732591],"type":"Point"}
}