{
  "type": "Feature",
  "properties": {
    "iso:country":"GB",
    "wof:name":"NW1 9HT",
    "wof:placetype":"postalcode"
},
  "geometry": {"coordinates":[-0.1357899111854,51.54244428720903],"type":"Point"}
}