{
  "type": "Feature",
  "properties": {
    "iso:country": "GB",
    "wof:name": "SS5 4RP",
    "wof:placetype": "postalcode"
  },
  "geometry": {"coordinates":[0.640654,51.600755],"type":"Point"}
}
