{
  "type": "Feature",
  "properties": {
    "iso:country":"GB",
    "wof:name":"SS5 4RP",
    "wof:placetype":"postalcode"
},
  "geometry": {"coordinates":[0.64065474112743,51.60074020909286],"type":"Point"}
}