{
  "type": "Feature",
  "properties": {
    "date:inception_lower": "1993-01-01",
    "date:inception_upper": "1993-01-01",
    "iso:country": "GB",
    "wof:name": "LL11 3EE",
    "wof:placetype": "postalcode"
  },
  "geometry": {"coordinates":[-3.083544,53.049231],"type":"Point"}
}
