{
  "type": "Feature",
  "properties": {
    "iso:country":"GB",
    "wof:name":"LL11 3EE",
    "wof:placetype":"postalcode"
},
  "geometry": {"coordinates":[-3.08354414788926,53.04923132063558],"type":"Point"}
}