{
  "type": "Feature",
  "properties": {
    "iso:country":"GB",
    "wof:name":"SP6 1PY",
    "wof:placetype":"postalcode"
},
  "geometry": {"coordinates":[-1.8297060110123,50.93460225871135],"type":"Point"}
}