{
  "type": "Feature",
  "properties": {
    "date:inception_lower": "2008-09-01",
    "date:inception_upper": "2008-09-01",
    "iso:country": "GB",
    "wof:name": "SO15 5UQ",
    "wof:placetype": "postalcode"
  },
  "geometry": {"coordinates":[-1.416858,50.922957],"type":"Point"}
}
