{
  "type": "Feature",
  "properties": {
    "date:inception_lower": "1995-12-01",
    "date:inception_upper": "1995-12-01",
    "iso:country": "GB",
    "wof:name": "KY1 4AP",
    "wof:placetype": "postalcode"
  },
  "geometry": {"coordinates":[-3.145031,56.168393],"type":"Point"}
}
