{
  "type": "Feature",
  "properties": {
    "iso:country": "GB",
    "wof:name": "TA4 4AW",
    "wof:placetype": "postalcode"
  },
  "geometry": {"coordinates":[-3.229644,51.111812],"type":"Point"}
}
