{
  "type": "Feature",
  "properties": {
    "date:inception_lower": "1980-01-01",
    "date:inception_upper": "1980-01-01",
    "iso:country": "GB",
    "wof:name": "TA4 4AW",
    "wof:placetype": "postalcode"
  },
  "geometry": {"coordinates":[-3.229644,51.111812],"type":"Point"}
}
