{
  "type": "Feature",
  "properties": {
    "iso:country":"GB",
    "wof:name":"TA4 4AW",
    "wof:placetype":"postalcode"
},
  "geometry": {"coordinates":[-3.22972003164089,51.11184182433312],"type":"Point"}
}