{
  "type": "Feature",
  "properties": {
    "iso:country":"GB",
    "wof:name":"OX18 2EY",
    "wof:placetype":"postalcode"
},
  "geometry": {"coordinates":[-1.54505405792405,51.73058498477194],"type":"Point"}
}