{
  "type": "Feature",
  "properties": {
    "iso:country": "GB",
    "wof:name": "SA44 4NS",
    "wof:placetype": "postalcode"
  },
  "geometry": {"coordinates":[-4.366567,52.091767],"type":"Point"}
}
