{
  "type": "Feature",
  "properties": {
    "iso:country":"GB",
    "wof:name":"SA44 4NS",
    "wof:placetype":"postalcode"
},
  "geometry": {"coordinates":[-4.36654685437381,52.09175429894007],"type":"Point"}
}