{
  "type": "Feature",
  "properties": {
    "iso:country":"GB",
    "wof:name":"CV37 8BD",
    "wof:placetype":"postalcode"
},
  "geometry": {"coordinates":[-1.80100423358803,52.15573388439923],"type":"Point"}
}