{
  "type": "Feature",
  "properties": {
    "iso:country": "GB",
    "wof:name": "PO20 8AG",
    "wof:placetype": "postalcode"
  },
  "geometry": {"coordinates":[-0.8542,50.761733],"type":"Point"}
}
