{
  "type": "Feature",
  "properties": {
    "date:inception_lower":"2003-07-01",
    "date:inception_upper":"2003-07-31",
    "iso:country":"GB",
    "wof:name":"PO20 8AG",
    "wof:placetype":"postalcode"
},
  "geometry": {"coordinates":[-0.8542,50.761733],"type":"Point"}
}