{
  "type": "Feature",
  "properties": {
    "date:inception_lower": "2000-12-01",
    "date:inception_upper": "2000-12-01",
    "iso:country": "GB",
    "wof:name": "SL6 9EY",
    "wof:placetype": "postalcode"
  },
  "geometry": {"coordinates":[-0.730605,51.558462],"type":"Point"}
}
