{
  "type": "Feature",
  "properties": {
    "iso:country": "GB",
    "wof:name": "SL6 9EY",
    "wof:placetype": "postalcode"
  },
  "geometry": {"coordinates":[-0.730605,51.558462],"type":"Point"}
}
