{
  "type": "Feature",
  "properties": {
    "iso:country":"GB",
    "wof:name":"SL6 9EY",
    "wof:placetype":"postalcode"
},
  "geometry": {"coordinates":[-0.73047598428655,51.55844235999586],"type":"Point"}
}