{
  "type": "Feature",
  "properties": {
    "date:inception_lower": "1991-09-01",
    "date:inception_upper": "1991-09-01",
    "iso:country": "GB",
    "wof:name": "RG12 7EN",
    "wof:placetype": "postalcode"
  },
  "geometry": {"coordinates":[-0.76046,51.4009],"type":"Point"}
}
