{
  "type": "Feature",
  "properties": {
    "iso:country": "GB",
    "wof:name": "G21 2BL",
    "wof:placetype": "postalcode"
  },
  "geometry": {"coordinates":[-4.213612,55.875105],"type":"Point"}
}
