{
  "type": "Feature",
  "properties": {
    "date:inception_lower": "1997-12-01",
    "date:inception_upper": "1997-12-01",
    "iso:country": "GB",
    "wof:name": "G21 2BL",
    "wof:placetype": "postalcode"
  },
  "geometry": {"coordinates":[-4.213612,55.875105],"type":"Point"}
}
