{
  "type": "Feature",
  "properties": {
    "iso:country":"GB",
    "wof:name":"HU12 9NL",
    "wof:placetype":"postalcode"
},
  "geometry": {"coordinates":[-0.14899041637615,53.71426788858551],"type":"Point"}
}