{
  "type": "Feature",
  "properties": {
    "iso:country":"GB",
    "wof:name":"DA15 7NP",
    "wof:placetype":"postalcode"
},
  "geometry": {"coordinates":[0.08144287024188,51.43179449678144],"type":"Point"}
}