{
  "type": "Feature",
  "properties": {
    "iso:country": "GB",
    "wof:name": "DA15 7NP",
    "wof:placetype": "postalcode"
  },
  "geometry": {"coordinates":[0.081443,51.431794],"type":"Point"}
}
