{
  "type": "Feature",
  "properties": {
    "iso:country":"GB",
    "wof:name":"BL6 5DY",
    "wof:placetype":"postalcode"
},
  "geometry": {"coordinates":[-2.58332743042892,53.59553459086359],"type":"Point"}
}