{
  "type": "Feature",
  "properties": {
    "iso:country": "GB",
    "wof:name": "SW6 2FQ",
    "wof:placetype": "postalcode"
  },
  "geometry": {"coordinates":[-0.184844,51.475186],"type":"Point"}
}
