{
  "type": "Feature",
  "properties": {
    "iso:country":"GB",
    "wof:name":"LS2 9DT",
    "wof:placetype":"postalcode"
},
  "geometry": {"coordinates":[-1.55744884411822,53.81044540657724],"type":"Point"}
}