{
  "type": "Feature",
  "properties": {
    "iso:country": "GB",
    "wof:name": "LS2 9DT",
    "wof:placetype": "postalcode"
  },
  "geometry": {"coordinates":[-1.557453,53.810461],"type":"Point"}
}
