{
  "type": "Feature",
  "properties": {
    "date:inception_lower": "2005-03-01",
    "date:inception_upper": "2005-03-01",
    "iso:country": "GB",
    "wof:name": "LS2 9DT",
    "wof:placetype": "postalcode"
  },
  "geometry": {"coordinates":[-1.557162,53.810685],"type":"Point"}
}
