{
  "type": "Feature",
  "properties": {
    "date:inception_lower": "1993-01-01",
    "date:inception_upper": "1993-01-01",
    "iso:country": "GB",
    "wof:name": "N17 6AQ",
    "wof:placetype": "postalcode"
  },
  "geometry": {"coordinates":[-0.082028,51.597286],"type":"Point"}
}
