{
  "type": "Feature",
  "properties": {
    "iso:country":"GB",
    "wof:name":"NN4 8JY",
    "wof:placetype":"postalcode"
},
  "geometry": {"coordinates":[-0.9323065500855,52.22543424343302],"type":"Point"}
}