{
  "type": "Feature",
  "properties": {
    "date:inception_lower":"1998-12-01",
    "date:inception_upper":"1998-12-31",
    "iso:country":"GB",
    "wof:name":"NN4 8JY",
    "wof:placetype":"postalcode"
},
  "geometry": {"coordinates":[-0.932307,52.225434],"type":"Point"}
}