{
  "type": "Feature",
  "properties": {
    "iso:country":"GB",
    "wof:name":"WN8 9UL",
    "wof:placetype":"postalcode"
},
  "geometry": {"coordinates":[-2.78170202458524,53.54412973075951],"type":"Point"}
}