{
  "type": "Feature",
  "properties": {
    "iso:country":"GB",
    "wof:name":"BN12 5RA",
    "wof:placetype":"postalcode"
},
  "geometry": {"coordinates":[-0.45274208605071,50.80534643792263],"type":"Point"}
}