{
  "type": "Feature",
  "properties": {
    "date:inception_lower":"1980-01-01",
    "date:inception_upper":"1980-01-31",
    "iso:country":"GB",
    "wof:name":"PO17 6HE",
    "wof:placetype":"postalcode"
},
  "geometry": {"coordinates":[-1.109275,50.874471],"type":"Point"}
}