{
  "type": "Feature",
  "properties": {
    "iso:country":"GB",
    "wof:name":"PA5 0SX",
    "wof:placetype":"postalcode"
},
  "geometry": {"coordinates":[-4.53128098330039,55.81550871429856],"type":"Point"}
}