{
  "type": "Feature",
  "properties": {
    "date:inception_lower": "2018-01-01",
    "date:inception_upper": "2018-01-01",
    "iso:country": "GB",
    "wof:name": "PE34 4FF",
    "wof:placetype": "postalcode"
  },
  "geometry": {"coordinates":[0.330718,52.757374],"type":"Point"}
}
