{
  "type": "Feature",
  "properties": {
    "iso:country":"GB",
    "wof:name":"OL16 3BS",
    "wof:placetype":"postalcode"
},
  "geometry": {"coordinates":[-2.12652754050995,53.61457934079327],"type":"Point"}
}