{
  "type": "Feature",
  "properties": {
    "date:inception_lower":"1995-01-01",
    "date:inception_upper":"1995-01-31",
    "iso:country":"GB",
    "wof:name":"OL16 3BS",
    "wof:placetype":"postalcode"
},
  "geometry": {"coordinates":[-2.126527,53.614579],"type":"Point"}
}