{
  "type": "Feature",
  "properties": {
    "date:inception_lower": "1994-12-01",
    "date:inception_upper": "1994-12-01",
    "iso:country": "GB",
    "wof:name": "SO19 6BG",
    "wof:placetype": "postalcode"
  },
  "geometry": {"coordinates":[-1.328679,50.910955],"type":"Point"}
}
