{
  "type": "Feature",
  "properties": {
    "iso:country":"GB",
    "wof:name":"SA1 3DH",
    "wof:placetype":"postalcode"
},
  "geometry": {"coordinates":[-3.94542568933184,51.62025993009497],"type":"Point"}
}