{
  "type": "Feature",
  "properties": {
    "iso:country":"GB",
    "wof:name":"EH22 2HJ",
    "wof:placetype":"postalcode"
},
  "geometry": {"coordinates":[-3.04766185674155,55.8935638450749],"type":"Point"}
}