{
  "type": "Feature",
  "properties": {
    "date:inception_lower": "2020-10-01",
    "date:inception_upper": "2020-10-01",
    "iso:country": "GB",
    "wof:name": "DH5 9FN",
    "wof:placetype": "postalcode"
  },
  "geometry": {"coordinates":[-1.461545,54.826895],"type":"Point"}
}
