{
  "type": "Feature",
  "properties": {
    "iso:country":"GB",
    "wof:name":"PE30 4ED",
    "wof:placetype":"postalcode"
},
  "geometry": {"coordinates":[0.42465917700849,52.75562151005016],"type":"Point"}
}