{
  "type": "Feature",
  "properties": {
    "iso:country":"GB",
    "wof:name":"LU5 6HE",
    "wof:placetype":"postalcode"
},
  "geometry": {"coordinates":[-0.51340131833498,51.9608017203107],"type":"Point"}
}