{
  "type": "Feature",
  "properties": {
    "iso:country":"GB",
    "wof:name":"YO12 6SJ",
    "wof:placetype":"postalcode"
},
  "geometry": {"coordinates":[-0.43304569907209,54.29594110651909],"type":"Point"}
}