{
  "type": "Feature",
  "properties": {
    "date:inception_lower": "2003-05-01",
    "date:inception_upper": "2003-05-01",
    "iso:country": "GB",
    "wof:name": "HU17 0FG",
    "wof:placetype": "postalcode"
  },
  "geometry": {"coordinates":[-0.4252,53.841429],"type":"Point"}
}
