{
  "type": "Feature",
  "properties": {
    "date:inception_lower": "2003-09-01",
    "date:inception_upper": "2003-09-01",
    "iso:country": "GB",
    "wof:name": "TN12 6DH",
    "wof:placetype": "postalcode"
  },
  "geometry": {"coordinates":[0.387,51.180276],"type":"Point"}
}
