{
  "type": "Feature",
  "properties": {
    "iso:country":"GB",
    "wof:name":"NG3 4JZ",
    "wof:placetype":"postalcode"
},
  "geometry": {"coordinates":[-1.14466778989827,52.96530913511266],"type":"Point"}
}