{
  "type": "Feature",
  "properties": {
    "iso:country":"GB",
    "wof:name":"EX4 2WD",
    "wof:placetype":"postalcode"
},
  "geometry": {"coordinates":[-3.52224794020735,50.72632122472096],"type":"Point"}
}