{
  "type": "Feature",
  "properties": {
    "date:inception_lower": "1999-06-01",
    "date:inception_upper": "1999-06-01",
    "iso:country": "GB",
    "wof:name": "CH44 0DN",
    "wof:placetype": "postalcode"
  },
  "geometry": {"coordinates":[-3.03145,53.420581],"type":"Point"}
}
