{
  "type": "Feature",
  "properties": {
    "iso:country":"GB",
    "wof:name":"LS12 2BB",
    "wof:placetype":"postalcode"
},
  "geometry": {"coordinates":[-1.58862411549356,53.8013795467146],"type":"Point"}
}