{
  "type": "Feature",
  "properties": {
    "date:inception_lower": "1980-01-01",
    "date:inception_upper": "1980-01-01",
    "iso:country": "GB",
    "wof:name": "LS12 2BB",
    "wof:placetype": "postalcode"
  },
  "geometry": {"coordinates":[-1.588624,53.80138],"type":"Point"}
}
