{
  "type": "Feature",
  "properties": {
    "iso:country": "GB",
    "wof:name": "LE2 5HF",
    "wof:placetype": "postalcode"
  },
  "geometry": {"coordinates":[-1.087086,52.595688],"type":"Point"}
}
