{
  "type": "Feature",
  "properties": {
    "date:inception_lower":"1980-01-01",
    "date:inception_upper":"1980-01-31",
    "iso:country":"GB",
    "wof:name":"LE2 5HF",
    "wof:placetype":"postalcode"
},
  "geometry": {"coordinates":[-1.087086,52.595688],"type":"Point"}
}