{
  "type": "Feature",
  "properties": {
    "iso:country":"GB",
    "wof:name":"NG15 6BD",
    "wof:placetype":"postalcode"
},
  "geometry": {"coordinates":[-1.19915934322776,53.02823693376367],"type":"Point"}
}