{
  "type": "Feature",
  "properties": {
    "iso:country": "GB",
    "wof:name": "NG15 6BD",
    "wof:placetype": "postalcode"
  },
  "geometry": {"coordinates":[-1.199159,53.028237],"type":"Point"}
}
