{
  "type": "Feature",
  "properties": {
    "iso:country":"GB",
    "wof:name":"SG4 8HY",
    "wof:placetype":"postalcode"
},
  "geometry": {"coordinates":[-0.30124837274473,51.8529980133559],"type":"Point"}
}