{
  "type": "Feature",
  "properties": {
    "date:inception_lower": "1994-05-01",
    "date:inception_upper": "1994-05-01",
    "iso:country": "GB",
    "wof:name": "SG4 8HY",
    "wof:placetype": "postalcode"
  },
  "geometry": {"coordinates":[-0.301208,51.85305],"type":"Point"}
}
