{
  "type": "Feature",
  "properties": {
    "iso:country":"GB",
    "wof:name":"E3 5PR",
    "wof:placetype":"postalcode"
},
  "geometry": {"coordinates":[-0.03041086352834,51.53581242239919],"type":"Point"}
}