{
  "type": "Feature",
  "properties": {
    "iso:country": "GB",
    "wof:name": "E3 5PR",
    "wof:placetype": "postalcode"
  },
  "geometry": {"coordinates":[-0.030411,51.535812],"type":"Point"}
}
