{
  "type": "Feature",
  "properties": {
    "date:inception_lower": "1980-01-01",
    "date:inception_upper": "1980-01-01",
    "iso:country": "GB",
    "wof:name": "CM8 2LZ",
    "wof:placetype": "postalcode"
  },
  "geometry": {"coordinates":[0.639602,51.814545],"type":"Point"}
}
