{
  "type": "Feature",
  "properties": {
    "iso:country":"GB",
    "wof:name":"CM8 2LZ",
    "wof:placetype":"postalcode"
},
  "geometry": {"coordinates":[0.63960239696407,51.81454487156697],"type":"Point"}
}