{
  "type": "Feature",
  "properties": {
    "iso:country":"GB",
    "wof:name":"YO42 1XA",
    "wof:placetype":"postalcode"
},
  "geometry": {"coordinates":[-0.69817885234631,53.93968297043308],"type":"Point"}
}