{
  "type": "Feature",
  "properties": {
    "iso:country":"GB",
    "wof:name":"YO30 6JP",
    "wof:placetype":"postalcode"
},
  "geometry": {"coordinates":[-1.09574356870405,53.97411714692553],"type":"Point"}
}