{
  "type": "Feature",
  "properties": {
    "iso:country":"GB",
    "wof:name":"RM3 7NS",
    "wof:placetype":"postalcode"
},
  "geometry": {"coordinates":[0.20805445410165,51.59375153178775],"type":"Point"}
}