{
  "type": "Feature",
  "properties": {
    "iso:country": "GB",
    "wof:name": "EN1 2JN",
    "wof:placetype": "postalcode"
  },
  "geometry": {"coordinates":[-0.074633,51.641363],"type":"Point"}
}
