{
  "type": "Feature",
  "properties": {
    "iso:country":"GB",
    "wof:name":"EN1 2JN",
    "wof:placetype":"postalcode"
},
  "geometry": {"coordinates":[-0.07463299156974,51.64136292912142],"type":"Point"}
}