{
  "type": "Feature",
  "properties": {
    "iso:country":"GB",
    "wof:name":"IV49 9AH",
    "wof:placetype":"postalcode"
},
  "geometry": {"coordinates":[-5.88116681205558,57.23566782911439],"type":"Point"}
}