{
  "type": "Feature",
  "properties": {
    "iso:country":"GB",
    "wof:name":"B96 6TE",
    "wof:placetype":"postalcode"
},
  "geometry": {"coordinates":[-2.0238208161638,52.23111248648065],"type":"Point"}
}