{
  "type": "Feature",
  "properties": {
    "date:inception_lower":"1980-01-01",
    "date:inception_upper":"1980-01-31",
    "iso:country":"GB",
    "wof:name":"BA21 3QF",
    "wof:placetype":"postalcode"
},
  "geometry": {"coordinates":[-2.650432,50.964567],"type":"Point"}
}