{
  "type": "Feature",
  "properties": {
    "iso:country":"GB",
    "wof:name":"BA21 3QF",
    "wof:placetype":"postalcode"
},
  "geometry": {"coordinates":[-2.65043162992164,50.96456656952458],"type":"Point"}
}