{
  "type": "Feature",
  "properties": {
    "iso:country":"GB",
    "wof:name":"GU14 8PY",
    "wof:placetype":"postalcode"
},
  "geometry": {"coordinates":[-0.76937825353724,51.29936464660759],"type":"Point"}
}