{
  "type": "Feature",
  "properties": {
    "iso:country":"GB",
    "wof:name":"GU34 4HT",
    "wof:placetype":"postalcode"
},
  "geometry": {"coordinates":[-0.94062246703963,51.16556215883499],"type":"Point"}
}