{
  "type": "Feature",
  "properties": {
    "iso:country":"GB",
    "wof:name":"LE18 2AA",
    "wof:placetype":"postalcode"
},
  "geometry": {"coordinates":[-1.11077803730281,52.5841628286565],"type":"Point"}
}