{
  "type": "Feature",
  "properties": {
    "iso:country":"GB",
    "wof:name":"BS40 8EA",
    "wof:placetype":"postalcode"
},
  "geometry": {"coordinates":[-2.63065915365194,51.35507628706955],"type":"Point"}
}