{
  "type": "Feature",
  "properties": {
    "date:inception_lower":"2016-01-01",
    "date:inception_upper":"2016-01-31",
    "iso:country":"GB",
    "wof:name":"BS40 8EA",
    "wof:placetype":"postalcode"
},
  "geometry": {"coordinates":[-2.630776,51.355028],"type":"Point"}
}