{
  "type": "Feature",
  "properties": {
    "iso:country": "GB",
    "wof:name": "BS40 8EA",
    "wof:placetype": "postalcode"
  },
  "geometry": {"coordinates":[-2.630776,51.355028],"type":"Point"}
}
