{
  "type": "Feature",
  "properties": {
    "iso:country": "GB",
    "wof:name": "NP22 5LB",
    "wof:placetype": "postalcode"
  },
  "geometry": {"coordinates":[-3.277006,51.750428],"type":"Point"}
}
