{
  "type": "Feature",
  "properties": {
    "iso:country":"GB",
    "wof:name":"NP22 5LB",
    "wof:placetype":"postalcode"
},
  "geometry": {"coordinates":[-3.27700602858549,51.75042793271026],"type":"Point"}
}