{
  "type": "Feature",
  "properties": {
    "iso:country": "GB",
    "wof:name": "PE3 7EQ",
    "wof:placetype": "postalcode"
  },
  "geometry": {"coordinates":[-0.269683,52.585173],"type":"Point"}
}
