{
  "type": "Feature",
  "properties": {
    "date:inception_lower":"1980-01-01",
    "date:inception_upper":"1980-01-31",
    "iso:country":"GB",
    "wof:name":"PE3 7EQ",
    "wof:placetype":"postalcode"
},
  "geometry": {"coordinates":[-0.269683,52.585173],"type":"Point"}
}