{
  "type": "Feature",
  "properties": {
    "iso:country":"GB",
    "wof:name":"PE3 7EQ",
    "wof:placetype":"postalcode"
},
  "geometry": {"coordinates":[-0.26968288597852,52.58517329389094],"type":"Point"}
}