{
  "type": "Feature",
  "properties": {
    "iso:country": "GB",
    "wof:name": "TN6 3LQ",
    "wof:placetype": "postalcode"
  },
  "geometry": {"coordinates":[0.217913,51.044815],"type":"Point"}
}
