{
  "type": "Feature",
  "properties": {
    "iso:country":"GB",
    "wof:name":"SN12 6XT",
    "wof:placetype":"postalcode"
},
  "geometry": {"coordinates":[-2.12077914944157,51.35424882775671],"type":"Point"}
}