{
  "type": "Feature",
  "properties": {
    "iso:country": "GB",
    "wof:name": "SN12 6XT",
    "wof:placetype": "postalcode"
  },
  "geometry": {"coordinates":[-2.120779,51.354249],"type":"Point"}
}
