{
  "type": "Feature",
  "properties": {
    "date:inception_lower":"1986-07-01",
    "date:inception_upper":"1986-07-31",
    "iso:country":"GB",
    "wof:name":"SN12 6XT",
    "wof:placetype":"postalcode"
},
  "geometry": {"coordinates":[-2.120779,51.354249],"type":"Point"}
}