{
  "type": "Feature",
  "properties": {
    "iso:country":"GB",
    "wof:name":"CV36 4EQ",
    "wof:placetype":"postalcode"
},
  "geometry": {"coordinates":[-1.6329121020843,52.06112771565734],"type":"Point"}
}