{
  "type": "Feature",
  "properties": {
    "iso:country": "GB",
    "wof:name": "CV36 4EQ",
    "wof:placetype": "postalcode"
  },
  "geometry": {"coordinates":[-1.632912,52.061128],"type":"Point"}
}
