{
  "type": "Feature",
  "properties": {
    "iso:country":"GB",
    "wof:name":"RG14 6QJ",
    "wof:placetype":"postalcode"
},
  "geometry": {"coordinates":[-1.3421466266633,51.38193202931786],"type":"Point"}
}