{
  "type": "Feature",
  "properties": {
    "iso:country":"GB",
    "wof:name":"SO16 3HZ",
    "wof:placetype":"postalcode"
},
  "geometry": {"coordinates":[-1.40409420048665,50.94094948990431],"type":"Point"}
}