{
  "type": "Feature",
  "properties": {
    "iso:country": "GB",
    "wof:name": "DA10 1AT",
    "wof:placetype": "postalcode"
  },
  "geometry": {"coordinates":[0.316386,51.434401],"type":"Point"}
}
