{
  "type": "Feature",
  "properties": {
    "iso:country":"GB",
    "wof:name":"LE16 7HL",
    "wof:placetype":"postalcode"
},
  "geometry": {"coordinates":[-0.90565462796152,52.4896655002441],"type":"Point"}
}