{
  "type": "Feature",
  "properties": {
    "iso:country":"GB",
    "wof:name":"SY18 6SN",
    "wof:placetype":"postalcode"
},
  "geometry": {"coordinates":[-3.61924388032182,52.412035636603],"type":"Point"}
}