{
  "type": "Feature",
  "properties": {
    "date:inception_lower": "1992-08-01",
    "date:inception_upper": "1992-08-01",
    "iso:country": "GB",
    "wof:name": "DE21 6QB",
    "wof:placetype": "postalcode"
  },
  "geometry": {"coordinates":[-1.439238,52.923033],"type":"Point"}
}
