{
  "type": "Feature",
  "properties": {
    "iso:country":"GB",
    "wof:name":"CV10 8RF",
    "wof:placetype":"postalcode"
},
  "geometry": {"coordinates":[-1.51162019120892,52.52078589557932],"type":"Point"}
}