{
  "type": "Feature",
  "properties": {
    "iso:country":"GB",
    "wof:name":"IG11 9NT",
    "wof:placetype":"postalcode"
},
  "geometry": {"coordinates":[0.10950340318918,51.5374084195622],"type":"Point"}
}