{
  "type": "Feature",
  "properties": {
    "date:inception_lower":"1980-01-01",
    "date:inception_upper":"1980-01-31",
    "iso:country":"GB",
    "wof:name":"IG11 9NT",
    "wof:placetype":"postalcode"
},
  "geometry": {"coordinates":[0.109503,51.537408],"type":"Point"}
}