{
  "type": "Feature",
  "properties": {
    "iso:country":"GB",
    "wof:name":"TN4 0AE",
    "wof:placetype":"postalcode"
},
  "geometry": {"coordinates":[0.26676722908116,51.15878190746862],"type":"Point"}
}