{
  "type": "Feature",
  "properties": {
    "iso:country":"GB",
    "wof:name":"W11 1WJ",
    "wof:placetype":"postalcode"
},
  "geometry": {"coordinates":[-0.21551095895166,51.51329865235451],"type":"Point"}
}