{
  "type": "Feature",
  "properties": {
    "iso:country": "GB",
    "wof:name": "PO32 6GR",
    "wof:placetype": "postalcode"
  },
  "geometry": {"coordinates":[-1.280061,50.746908],"type":"Point"}
}
