{
  "type": "Feature",
  "properties": {
    "date:inception_lower": "2011-03-01",
    "date:inception_upper": "2011-03-01",
    "iso:country": "GB",
    "wof:name": "PO32 6GR",
    "wof:placetype": "postalcode"
  },
  "geometry": {"coordinates":[-1.280033,50.746872],"type":"Point"}
}
