{
  "type": "Feature",
  "properties": {
    "date:inception_lower":"2011-03-01",
    "date:inception_upper":"2011-03-31",
    "iso:country":"GB",
    "wof:name":"PO32 6GR",
    "wof:placetype":"postalcode"
},
  "geometry": {"coordinates":[-1.280061,50.746908],"type":"Point"}
}