{
  "type": "Feature",
  "properties": {
    "iso:country":"GB",
    "wof:name":"PO32 6GR",
    "wof:placetype":"postalcode"
},
  "geometry": {"coordinates":[-1.28018187084716,50.74708123549527],"type":"Point"}
}