{
  "type": "Feature",
  "properties": {
    "iso:country":"GB",
    "wof:name":"NE47 8HQ",
    "wof:placetype":"postalcode"
},
  "geometry": {"coordinates":[-2.33882548085665,54.90300976261265],"type":"Point"}
}