{
  "type": "Feature",
  "properties": {
    "iso:country": "GB",
    "wof:name": "NE47 8HQ",
    "wof:placetype": "postalcode"
  },
  "geometry": {"coordinates":[-2.337794,54.896289],"type":"Point"}
}
