{
  "type": "Feature",
  "properties": {
    "date:inception_lower":"1997-12-01",
    "date:inception_upper":"1997-12-31",
    "iso:country":"GB",
    "wof:name":"AL1 2QY",
    "wof:placetype":"postalcode"
},
  "geometry": {"coordinates":[-0.34834,51.737413],"type":"Point"}
}