{
  "type": "Feature",
  "properties": {
    "iso:country":"GB",
    "wof:name":"AL1 2QY",
    "wof:placetype":"postalcode"
},
  "geometry": {"coordinates":[-0.34834002834532,51.73741258688137],"type":"Point"}
}