{
  "type": "Feature",
  "properties": {
    "date:inception_lower": "1980-01-01",
    "date:inception_upper": "1980-01-01",
    "iso:country": "GB",
    "wof:name": "L10 2LH",
    "wof:placetype": "postalcode"
  },
  "geometry": {"coordinates":[-2.948183,53.485766],"type":"Point"}
}
