{
  "type": "Feature",
  "properties": {
    "iso:country":"GB",
    "wof:name":"L10 2LH",
    "wof:placetype":"postalcode"
},
  "geometry": {"coordinates":[-2.9481828236734,53.48576586187187],"type":"Point"}
}