{
  "type": "Feature",
  "properties": {
    "date:inception_lower": "1992-08-01",
    "date:inception_upper": "1992-08-01",
    "iso:country": "GB",
    "wof:name": "TF2 7BA",
    "wof:placetype": "postalcode"
  },
  "geometry": {"coordinates":[-2.440509,52.707169],"type":"Point"}
}
