{
  "type": "Feature",
  "properties": {
    "iso:country":"GB",
    "wof:name":"TF2 7BA",
    "wof:placetype":"postalcode"
},
  "geometry": {"coordinates":[-2.44050854965408,52.70716887437815],"type":"Point"}
}