{
  "type": "Feature",
  "properties": {
    "date:inception_lower":"1995-07-01",
    "date:inception_upper":"1995-07-31",
    "iso:country":"GB",
    "wof:name":"CM7 9LF",
    "wof:placetype":"postalcode"
},
  "geometry": {"coordinates":[0.569856,51.883125],"type":"Point"}
}