{
  "type": "Feature",
  "properties": {
    "iso:country":"GB",
    "wof:name":"LE2 5WT",
    "wof:placetype":"postalcode"
},
  "geometry": {"coordinates":[-1.0779991465485,52.58688795797026],"type":"Point"}
}