{
  "type": "Feature",
  "properties": {
    "iso:country":"GB",
    "wof:name":"G41 2RJ",
    "wof:placetype":"postalcode"
},
  "geometry": {"coordinates":[-4.27533336916484,55.84281064485263],"type":"Point"}
}