{
  "type": "Feature",
  "properties": {
    "iso:country":"GB",
    "wof:name":"KT18 5LD",
    "wof:placetype":"postalcode"
},
  "geometry": {"coordinates":[-0.25724648639265,51.32123465392204],"type":"Point"}
}