{
  "type": "Feature",
  "properties": {
    "iso:country":"GB",
    "wof:name":"L13 8DG",
    "wof:placetype":"postalcode"
},
  "geometry": {"coordinates":[-2.93231312641813,53.43145449319135],"type":"Point"}
}