{
  "type": "Feature",
  "properties": {
    "date:inception_lower": "1980-01-01",
    "date:inception_upper": "1980-01-01",
    "iso:country": "GB",
    "wof:name": "L13 8DG",
    "wof:placetype": "postalcode"
  },
  "geometry": {"coordinates":[-2.932313,53.431454],"type":"Point"}
}
