{
  "type": "Feature",
  "properties": {
    "date:inception_lower": "1981-06-01",
    "date:inception_upper": "1981-06-01",
    "iso:country": "GB",
    "wof:name": "SN6 7PD",
    "wof:placetype": "postalcode"
  },
  "geometry": {"coordinates":[-1.704135,51.635741],"type":"Point"}
}
