{
  "type": "Feature",
  "properties": {
    "iso:country":"GB",
    "wof:name":"SN6 7PD",
    "wof:placetype":"postalcode"
},
  "geometry": {"coordinates":[-1.70413499685474,51.63574101062975],"type":"Point"}
}