{
  "type": "Feature",
  "properties": {
    "iso:country":"GB",
    "wof:name":"HR6 9PY",
    "wof:placetype":"postalcode"
},
  "geometry": {"coordinates":[-2.80996511619941,52.25683421698137],"type":"Point"}
}