{
  "type": "Feature",
  "properties": {
    "iso:country": "GB",
    "wof:name": "HR6 9PY",
    "wof:placetype": "postalcode"
  },
  "geometry": {"coordinates":[-2.809965,52.256834],"type":"Point"}
}
