{
  "type": "Feature",
  "properties": {
    "date:inception_lower": "2022-02-01",
    "date:inception_upper": "2022-02-01",
    "iso:country": "GB",
    "wof:name": "IP2 8TG",
    "wof:placetype": "postalcode"
  },
  "geometry": {"coordinates":[1.158764,52.045185],"type":"Point"}
}
