{
  "type": "Feature",
  "properties": {
    "date:inception_lower": "1980-01-01",
    "date:inception_upper": "1980-01-01",
    "iso:country": "GB",
    "wof:name": "EX21 5PJ",
    "wof:placetype": "postalcode"
  },
  "geometry": {"coordinates":[-4.15945,50.868936],"type":"Point"}
}
