{
  "type": "Feature",
  "properties": {
    "iso:country": "GB",
    "wof:name": "EX21 5PJ",
    "wof:placetype": "postalcode"
  },
  "geometry": {"coordinates":[-4.15945,50.868936],"type":"Point"}
}
