{
  "type": "Feature",
  "properties": {
    "iso:country":"GB",
    "wof:name":"G15 7PE",
    "wof:placetype":"postalcode"
},
  "geometry": {"coordinates":[-4.35948684838947,55.91297347229716],"type":"Point"}
}