{
  "type": "Feature",
  "properties": {
    "date:inception_lower":"2003-08-01",
    "date:inception_upper":"2003-08-31",
    "iso:country":"GB",
    "wof:name":"G15 7PE",
    "wof:placetype":"postalcode"
},
  "geometry": {"coordinates":[-4.359487,55.912973],"type":"Point"}
}