{
  "type": "Feature",
  "properties": {
    "iso:country": "GB",
    "wof:name": "G83 8NN",
    "wof:placetype": "postalcode"
  },
  "geometry": {"coordinates":[-4.637231,56.10115],"type":"Point"}
}
