{
  "type": "Feature",
  "properties": {
    "iso:country":"GB",
    "wof:name":"G83 8NN",
    "wof:placetype":"postalcode"
},
  "geometry": {"coordinates":[-4.63729813277807,56.10118368064305],"type":"Point"}
}