{
  "type": "Feature",
  "properties": {
    "date:inception_lower": "1980-01-01",
    "date:inception_upper": "1980-01-01",
    "iso:country": "GB",
    "wof:name": "BB6 7SJ",
    "wof:placetype": "postalcode"
  },
  "geometry": {"coordinates":[-2.396835,53.788808],"type":"Point"}
}
