{
  "type": "Feature",
  "properties": {
    "iso:country": "GB",
    "wof:name": "SE24 9HS",
    "wof:placetype": "postalcode"
  },
  "geometry": {"coordinates":[-0.095854,51.452641],"type":"Point"}
}
