{
  "type": "Feature",
  "properties": {
    "date:inception_lower":"2000-12-01",
    "date:inception_upper":"2000-12-31",
    "iso:country":"GB",
    "wof:name":"W1K 5QD",
    "wof:placetype":"postalcode"
},
  "geometry": {"coordinates":[-0.147144,51.513219],"type":"Point"}
}