{
  "type": "Feature",
  "properties": {
    "iso:country":"GB",
    "wof:name":"W1K 5QD",
    "wof:placetype":"postalcode"
},
  "geometry": {"coordinates":[-0.14714377387735,51.51321874994481],"type":"Point"}
}