{
  "type": "Feature",
  "properties": {
    "iso:country": "GB",
    "wof:name": "CF11 9DH",
    "wof:placetype": "postalcode"
  },
  "geometry": {"coordinates":[-3.200479,51.486302],"type":"Point"}
}
