{
  "type": "Feature",
  "properties": {
    "iso:country":"GB",
    "wof:name":"N13 6DH",
    "wof:placetype":"postalcode"
},
  "geometry": {"coordinates":[-0.09828736477416,51.61210949801356],"type":"Point"}
}