{
  "type": "Feature",
  "properties": {
    "iso:country": "GB",
    "wof:name": "HU6 9EQ",
    "wof:placetype": "postalcode"
  },
  "geometry": {"coordinates":[-0.387362,53.787984],"type":"Point"}
}
