{
  "type": "Feature",
  "properties": {
    "iso:country":"GB",
    "wof:name":"W1H 6BQ",
    "wof:placetype":"postalcode"
},
  "geometry": {"coordinates":[-0.15272745585535,51.51591464677938],"type":"Point"}
}