{
  "type": "Feature",
  "properties": {
    "iso:country":"GB",
    "wof:name":"EX23 0AN",
    "wof:placetype":"postalcode"
},
  "geometry": {"coordinates":[-4.55267062700158,50.79214174783743],"type":"Point"}
}