{
  "type": "Feature",
  "properties": {
    "iso:country": "GB",
    "wof:name": "DD10 0DT",
    "wof:placetype": "postalcode"
  },
  "geometry": {"coordinates":[-2.431069,56.803905],"type":"Point"}
}
