{
  "type": "Feature",
  "properties": {
    "iso:country": "GB",
    "wof:name": "BS15 3LS",
    "wof:placetype": "postalcode"
  },
  "geometry": {"coordinates":[-2.515955,51.441545],"type":"Point"}
}
