{
  "type": "Feature",
  "properties": {
    "date:inception_lower":"1987-04-01",
    "date:inception_upper":"1987-04-30",
    "iso:country":"GB",
    "wof:name":"HP12 3BA",
    "wof:placetype":"postalcode"
},
  "geometry": {"coordinates":[-0.771517,51.635489],"type":"Point"}
}