{
  "type": "Feature",
  "properties": {
    "iso:country":"GB",
    "wof:name":"DH8 0JF",
    "wof:placetype":"postalcode"
},
  "geometry": {"coordinates":[-1.85919153463484,54.87306371075501],"type":"Point"}
}