{
  "type": "Feature",
  "properties": {
    "iso:country":"GB",
    "wof:name":"BA1 3QQ",
    "wof:placetype":"postalcode"
},
  "geometry": {"coordinates":[-2.39741535607573,51.39036756159761],"type":"Point"}
}