{
  "type": "Feature",
  "properties": {
    "iso:country":"GB",
    "wof:name":"LL54 7NF",
    "wof:placetype":"postalcode"
},
  "geometry": {"coordinates":[-4.26237255410965,53.09597926494411],"type":"Point"}
}