{
  "type": "Feature",
  "properties": {
    "iso:country":"GB",
    "wof:name":"LL59 5QL",
    "wof:placetype":"postalcode"
},
  "geometry": {"coordinates":[-4.16749582268892,53.23191424493072],"type":"Point"}
}