{
  "type": "Feature",
  "properties": {
    "date:inception_lower": "1984-02-01",
    "date:inception_upper": "1984-02-01",
    "iso:country": "GB",
    "wof:name": "LL59 5QL",
    "wof:placetype": "postalcode"
  },
  "geometry": {"coordinates":[-4.167496,53.231914],"type":"Point"}
}
