{
  "type": "Feature",
  "properties": {
    "iso:country": "GB",
    "wof:name": "S33 0AW",
    "wof:placetype": "postalcode"
  },
  "geometry": {"coordinates":[-1.686319,53.347117],"type":"Point"}
}
