{
  "type": "Feature",
  "properties": {
    "iso:country": "GB",
    "wof:name": "EX10 0ER",
    "wof:placetype": "postalcode"
  },
  "geometry": {"coordinates":[-3.293746,50.700312],"type":"Point"}
}
