{
  "type": "Feature",
  "properties": {
    "iso:country":"GB",
    "wof:name":"TR9 6QH",
    "wof:placetype":"postalcode"
},
  "geometry": {"coordinates":[-4.93187126992758,50.39499831928001],"type":"Point"}
}