{
  "type": "Feature",
  "properties": {
    "date:inception_lower": "1980-01-01",
    "date:inception_upper": "1980-01-01",
    "iso:country": "GB",
    "wof:name": "TR9 6QH",
    "wof:placetype": "postalcode"
  },
  "geometry": {"coordinates":[-4.931871,50.394998],"type":"Point"}
}
