{
  "type": "Feature",
  "properties": {
    "iso:country":"GB",
    "wof:name":"SL4 3ER",
    "wof:placetype":"postalcode"
},
  "geometry": {"coordinates":[-0.60852841579446,51.47453993042144],"type":"Point"}
}