{
  "type": "Feature",
  "properties": {
    "date:inception_lower": "1997-12-01",
    "date:inception_upper": "1997-12-01",
    "iso:country": "GB",
    "wof:name": "SL4 3ER",
    "wof:placetype": "postalcode"
  },
  "geometry": {"coordinates":[-0.608528,51.47454],"type":"Point"}
}
