{
  "type": "Feature",
  "properties": {
    "iso:country":"GB",
    "wof:name":"PH33 6TA",
    "wof:placetype":"postalcode"
},
  "geometry": {"coordinates":[-5.07594703144485,56.83319997649019],"type":"Point"}
}