{
  "type": "Feature",
  "properties": {
    "date:inception_lower": "1999-06-01",
    "date:inception_upper": "1999-06-01",
    "iso:country": "GB",
    "wof:name": "PH33 6TA",
    "wof:placetype": "postalcode"
  },
  "geometry": {"coordinates":[-5.075947,56.8332],"type":"Point"}
}
