{
  "type": "Feature",
  "properties": {
    "iso:country":"GB",
    "wof:name":"S65 3AL",
    "wof:placetype":"postalcode"
},
  "geometry": {"coordinates":[-1.32256600450536,53.42273062018892],"type":"Point"}
}