{
  "type": "Feature",
  "properties": {
    "iso:country": "GB",
    "wof:name": "S65 3AL",
    "wof:placetype": "postalcode"
  },
  "geometry": {"coordinates":[-1.322566,53.422731],"type":"Point"}
}
