{
  "type": "Feature",
  "properties": {
    "iso:country":"GB",
    "wof:name":"KT14 7JN",
    "wof:placetype":"postalcode"
},
  "geometry": {"coordinates":[-0.4826898045558,51.34782447665993],"type":"Point"}
}