{
  "type": "Feature",
  "properties": {
    "iso:country": "GB",
    "wof:name": "CR0 1GU",
    "wof:placetype": "postalcode"
  },
  "geometry": {"coordinates":[-0.099534,51.367531],"type":"Point"}
}
