{
  "type": "Feature",
  "properties": {
    "iso:country":"GB",
    "wof:name":"HR5 3FD",
    "wof:placetype":"postalcode"
},
  "geometry": {"coordinates":[-3.02210068460551,52.20055129420874],"type":"Point"}
}