{
  "type": "Feature",
  "properties": {
    "date:inception_lower": "1999-06-01",
    "date:inception_upper": "1999-06-01",
    "iso:country": "GB",
    "wof:name": "HR5 3FD",
    "wof:placetype": "postalcode"
  },
  "geometry": {"coordinates":[-3.022101,52.200551],"type":"Point"}
}
