{
  "type": "Feature",
  "properties": {
    "iso:country": "GB",
    "wof:name": "SN5 5DY",
    "wof:placetype": "postalcode"
  },
  "geometry": {"coordinates":[-1.828023,51.581788],"type":"Point"}
}
