{
  "type": "Feature",
  "properties": {
    "iso:country":"GB",
    "wof:name":"FY4 3PS",
    "wof:placetype":"postalcode"
},
  "geometry": {"coordinates":[-3.03332118314769,53.78537913129132],"type":"Point"}
}