{
  "type": "Feature",
  "properties": {
    "iso:country":"GB",
    "wof:name":"PE21 6DY",
    "wof:placetype":"postalcode"
},
  "geometry": {"coordinates":[-0.0242853273142,52.97939736296536],"type":"Point"}
}