{
  "type": "Feature",
  "properties": {
    "iso:country": "GB",
    "wof:name": "PE21 6DY",
    "wof:placetype": "postalcode"
  },
  "geometry": {"coordinates":[-0.024267,52.979331],"type":"Point"}
}
