{
  "type": "Feature",
  "properties": {
    "iso:country": "GB",
    "wof:name": "TN24 0XN",
    "wof:placetype": "postalcode"
  },
  "geometry": {"coordinates":[0.886911,51.136208],"type":"Point"}
}
