{
  "type": "Feature",
  "properties": {
    "iso:country":"GB",
    "wof:name":"TN24 0XN",
    "wof:placetype":"postalcode"
},
  "geometry": {"coordinates":[0.8869110539901,51.13620845629528],"type":"Point"}
}