{
  "type": "Feature",
  "properties": {
    "date:inception_lower": "2015-09-01",
    "date:inception_upper": "2015-09-01",
    "iso:country": "GB",
    "wof:name": "TN24 0XN",
    "wof:placetype": "postalcode"
  },
  "geometry": {"coordinates":[0.886911,51.136208],"type":"Point"}
}
