{
  "type": "Feature",
  "properties": {
    "date:inception_lower": "1980-01-01",
    "date:inception_upper": "1980-01-01",
    "iso:country": "GB",
    "wof:name": "LL41 4TP",
    "wof:placetype": "postalcode"
  },
  "geometry": {"coordinates":[-3.881304,52.909221],"type":"Point"}
}
