{
  "type": "Feature",
  "properties": {
    "iso:country":"GB",
    "wof:name":"LL41 4TP",
    "wof:placetype":"postalcode"
},
  "geometry": {"coordinates":[-3.88130374593404,52.90922093489562],"type":"Point"}
}