{
  "type": "Feature",
  "properties": {
    "iso:country": "GB",
    "wof:name": "KT13 8LJ",
    "wof:placetype": "postalcode"
  },
  "geometry": {"coordinates":[-0.458634,51.373184],"type":"Point"}
}
