{
  "type": "Feature",
  "properties": {
    "iso:country":"GB",
    "wof:name":"PR9 9SH",
    "wof:placetype":"postalcode"
},
  "geometry": {"coordinates":[-2.96780010638466,53.66868073402136],"type":"Point"}
}