{
  "type": "Feature",
  "properties": {
    "date:inception_lower":"1996-12-01",
    "date:inception_upper":"1996-12-31",
    "iso:country":"GB",
    "wof:name":"TA6 6RX",
    "wof:placetype":"postalcode"
},
  "geometry": {"coordinates":[-3.010027,51.095143],"type":"Point"}
}