{
  "type": "Feature",
  "properties": {
    "iso:country":"GB",
    "wof:name":"TA6 6RX",
    "wof:placetype":"postalcode"
},
  "geometry": {"coordinates":[-3.01002733830178,51.09514341372464],"type":"Point"}
}