{
  "type": "Feature",
  "properties": {
    "iso:country":"GB",
    "wof:name":"M16 7AP",
    "wof:placetype":"postalcode"
},
  "geometry": {"coordinates":[-2.25350233280768,53.4557685630354],"type":"Point"}
}