{
  "type": "Feature",
  "properties": {
    "date:inception_lower": "1995-12-01",
    "date:inception_upper": "1995-12-01",
    "iso:country": "GB",
    "wof:name": "M16 7AP",
    "wof:placetype": "postalcode"
  },
  "geometry": {"coordinates":[-2.253502,53.455769],"type":"Point"}
}
