{
  "type": "Feature",
  "properties": {
    "iso:country": "GB",
    "wof:name": "M16 7AP",
    "wof:placetype": "postalcode"
  },
  "geometry": {"coordinates":[-2.253502,53.455769],"type":"Point"}
}
