{
  "type": "Feature",
  "properties": {
    "iso:country": "GB",
    "wof:name": "NG9 2PN",
    "wof:placetype": "postalcode"
  },
  "geometry": {"coordinates":[-1.222921,52.932857],"type":"Point"}
}
