{
  "type": "Feature",
  "properties": {
    "iso:country":"GB",
    "wof:name":"NG9 2PN",
    "wof:placetype":"postalcode"
},
  "geometry": {"coordinates":[-1.2230718330119,52.93294581214746],"type":"Point"}
}