{
  "type": "Feature",
  "properties": {
    "iso:country": "GB",
    "wof:name": "LS23 6FH",
    "wof:placetype": "postalcode"
  },
  "geometry": {"coordinates":[-1.349149,53.893282],"type":"Point"}
}
