{
  "type": "Feature",
  "properties": {
    "date:inception_lower":"2007-07-01",
    "date:inception_upper":"2007-07-31",
    "iso:country":"GB",
    "wof:name":"LS23 6FH",
    "wof:placetype":"postalcode"
},
  "geometry": {"coordinates":[-1.348935,53.893326],"type":"Point"}
}