{
  "type": "Feature",
  "properties": {
    "iso:country":"GB",
    "wof:name":"LS23 6FH",
    "wof:placetype":"postalcode"
},
  "geometry": {"coordinates":[-1.34892979628059,53.8933088415822],"type":"Point"}
}