{
  "type": "Feature",
  "properties": {
    "iso:country":"GB",
    "wof:name":"BA20 2JZ",
    "wof:placetype":"postalcode"
},
  "geometry": {"coordinates":[-2.65019794923272,50.92742909595817],"type":"Point"}
}