{
  "type": "Feature",
  "properties": {
    "date:inception_lower": "1980-01-01",
    "date:inception_upper": "1980-01-01",
    "iso:country": "GB",
    "wof:name": "BA20 2JZ",
    "wof:placetype": "postalcode"
  },
  "geometry": {"coordinates":[-2.650198,50.927429],"type":"Point"}
}
