{
  "type": "Feature",
  "properties": {
    "iso:country":"GB",
    "wof:name":"NP7 5JA",
    "wof:placetype":"postalcode"
},
  "geometry": {"coordinates":[-3.00961277200285,51.81581627813051],"type":"Point"}
}