{
  "type": "Feature",
  "properties": {
    "iso:country":"GB",
    "wof:name":"NG23 5NF",
    "wof:placetype":"postalcode"
},
  "geometry": {"coordinates":[-0.89201358282069,53.01952523194583],"type":"Point"}
}