{
  "type": "Feature",
  "properties": {
    "date:inception_lower": "2014-05-01",
    "date:inception_upper": "2014-05-01",
    "iso:country": "GB",
    "wof:name": "DE11 9GU",
    "wof:placetype": "postalcode"
  },
  "geometry": {"coordinates":[-1.585933,52.759855],"type":"Point"}
}
