{
  "type": "Feature",
  "properties": {
    "iso:country": "GB",
    "wof:name": "WN5 7BY",
    "wof:placetype": "postalcode"
  },
  "geometry": {"coordinates":[-2.712044,53.5245],"type":"Point"}
}
