{
  "type": "Feature",
  "properties": {
    "iso:country":"GB",
    "wof:name":"WN5 7BY",
    "wof:placetype":"postalcode"
},
  "geometry": {"coordinates":[-2.71202742693,53.52443063745512],"type":"Point"}
}