{
  "type": "Feature",
  "properties": {
    "iso:country": "GB",
    "wof:name": "NR33 8EG",
    "wof:placetype": "postalcode"
  },
  "geometry": {"coordinates":[1.697735,52.421889],"type":"Point"}
}
