{
  "type": "Feature",
  "properties": {
    "iso:country":"GB",
    "wof:name":"NR33 8EG",
    "wof:placetype":"postalcode"
},
  "geometry": {"coordinates":[1.69773509950366,52.42188921766837],"type":"Point"}
}