{
  "type": "Feature",
  "properties": {
    "iso:country": "GB",
    "wof:name": "EX32 9ED",
    "wof:placetype": "postalcode"
  },
  "geometry": {"coordinates":[-4.046326,51.070027],"type":"Point"}
}
