{
  "type": "Feature",
  "properties": {
    "iso:country":"GB",
    "wof:name":"AB24 1UF",
    "wof:placetype":"postalcode"
},
  "geometry": {"coordinates":[-2.09898354310819,57.16875598719244],"type":"Point"}
}