{
  "type": "Feature",
  "properties": {
    "iso:country":"GB",
    "wof:name":"CR5 2JA",
    "wof:placetype":"postalcode"
},
  "geometry": {"coordinates":[-0.1329600345845,51.32303315491912],"type":"Point"}
}