{
  "type": "Feature",
  "properties": {
    "date:inception_lower":"1990-07-01",
    "date:inception_upper":"1990-07-31",
    "iso:country":"GB",
    "wof:name":"CR5 2JA",
    "wof:placetype":"postalcode"
},
  "geometry": {"coordinates":[-0.13296,51.323033],"type":"Point"}
}