{
  "type": "Feature",
  "properties": {
    "iso:country":"GB",
    "wof:name":"TS27 4EA",
    "wof:placetype":"postalcode"
},
  "geometry": {"coordinates":[-1.2905544152934,54.74809231635761],"type":"Point"}
}