{
  "type": "Feature",
  "properties": {
    "iso:country": "GB",
    "wof:name": "GU11 3PT",
    "wof:placetype": "postalcode"
  },
  "geometry": {"coordinates":[-0.750992,51.238445],"type":"Point"}
}
