{
  "type": "Feature",
  "properties": {
    "iso:country":"GB",
    "wof:name":"GU11 3PT",
    "wof:placetype":"postalcode"
},
  "geometry": {"coordinates":[-0.75099210344828,51.23844512732693],"type":"Point"}
}