{
  "type": "Feature",
  "properties": {
    "date:inception_lower": "1980-01-01",
    "date:inception_upper": "1980-01-01",
    "iso:country": "GB",
    "wof:name": "LL11 2LU",
    "wof:placetype": "postalcode"
  },
  "geometry": {"coordinates":[-2.995502,53.053309],"type":"Point"}
}
