{
  "type": "Feature",
  "properties": {
    "iso:country": "GB",
    "wof:name": "NE46 1NX",
    "wof:placetype": "postalcode"
  },
  "geometry": {"coordinates":[-2.099487,54.969347],"type":"Point"}
}
