{
  "type": "Feature",
  "properties": {
    "date:inception_lower":"1980-01-01",
    "date:inception_upper":"1980-01-31",
    "iso:country":"GB",
    "wof:name":"NE46 1NX",
    "wof:placetype":"postalcode"
},
  "geometry": {"coordinates":[-2.099487,54.969347],"type":"Point"}
}