{
  "type": "Feature",
  "properties": {
    "iso:country":"GB",
    "wof:name":"WC1A 2HH",
    "wof:placetype":"postalcode"
},
  "geometry": {"coordinates":[-0.12604859163731,51.51768560799096],"type":"Point"}
}