{
  "type": "Feature",
  "properties": {
    "iso:country": "GB",
    "wof:name": "WC1A 2HH",
    "wof:placetype": "postalcode"
  },
  "geometry": {"coordinates":[-0.126049,51.517686],"type":"Point"}
}
