{
  "type": "Feature",
  "properties": {
    "date:inception_lower":"1980-01-01",
    "date:inception_upper":"1980-01-31",
    "iso:country":"GB",
    "wof:name":"DT11 9AX",
    "wof:placetype":"postalcode"
},
  "geometry": {"coordinates":[-2.19996,50.778148],"type":"Point"}
}