{
  "type": "Feature",
  "properties": {
    "iso:country":"GB",
    "wof:name":"DT11 9AX",
    "wof:placetype":"postalcode"
},
  "geometry": {"coordinates":[-2.19996021035492,50.77814834412354],"type":"Point"}
}