{
  "type": "Feature",
  "properties": {
    "iso:country": "GB",
    "wof:name": "DT11 9AX",
    "wof:placetype": "postalcode"
  },
  "geometry": {"coordinates":[-2.19996,50.778148],"type":"Point"}
}
