{
  "type": "Feature",
  "properties": {
    "iso:country":"GB",
    "wof:name":"PA9 1DH",
    "wof:placetype":"postalcode"
},
  "geometry": {"coordinates":[-4.56915248851154,55.80083606941952],"type":"Point"}
}