{
  "type": "Feature",
  "properties": {
    "iso:country": "GB",
    "wof:name": "DY5 3JR",
    "wof:placetype": "postalcode"
  },
  "geometry": {"coordinates":[-2.129544,52.467436],"type":"Point"}
}
