{
  "type": "Feature",
  "properties": {
    "iso:country": "GB",
    "wof:name": "CV11 5TJ",
    "wof:placetype": "postalcode"
  },
  "geometry": {"coordinates":[-1.467706,52.520408],"type":"Point"}
}
