{
  "type": "Feature",
  "properties": {
    "iso:country":"GB",
    "wof:name":"WA8 5WA",
    "wof:placetype":"postalcode"
},
  "geometry": {"coordinates":[-2.74681561695238,53.38910030690355],"type":"Point"}
}