{
  "type": "Feature",
  "properties": {
    "iso:country":"GB",
    "wof:name":"DH4 4XE",
    "wof:placetype":"postalcode"
},
  "geometry": {"coordinates":[-1.48762769288069,54.86191983748486],"type":"Point"}
}