{
  "type": "Feature",
  "properties": {
    "iso:country": "GB",
    "wof:name": "CV13 6BH",
    "wof:placetype": "postalcode"
  },
  "geometry": {"coordinates":[-1.480426,52.563283],"type":"Point"}
}
