{
  "type": "Feature",
  "properties": {
    "date:inception_lower": "1980-01-01",
    "date:inception_upper": "1980-01-01",
    "iso:country": "GB",
    "wof:name": "NE66 2TG",
    "wof:placetype": "postalcode"
  },
  "geometry": {"coordinates":[-1.704886,55.481656],"type":"Point"}
}
