{
  "type": "Feature",
  "properties": {
    "iso:country": "GB",
    "wof:name": "GU34 5HX",
    "wof:placetype": "postalcode"
  },
  "geometry": {"coordinates":[-1.053445,51.1079],"type":"Point"}
}
