{
  "type": "Feature",
  "properties": {
    "iso:country":"GB",
    "wof:name":"GU34 5HX",
    "wof:placetype":"postalcode"
},
  "geometry": {"coordinates":[-1.05344489828805,51.10789955668008],"type":"Point"}
}