{
  "type": "Feature",
  "properties": {
    "iso:country": "GB",
    "wof:name": "SA19 9PG",
    "wof:placetype": "postalcode"
  },
  "geometry": {"coordinates":[-3.825444,51.879388],"type":"Point"}
}
