{
  "type": "Feature",
  "properties": {
    "iso:country": "GB",
    "wof:name": "SN8 1SF",
    "wof:placetype": "postalcode"
  },
  "geometry": {"coordinates":[-1.727993,51.451322],"type":"Point"}
}
