{
  "type": "Feature",
  "properties": {
    "date:inception_lower": "1980-01-01",
    "date:inception_upper": "1980-01-01",
    "iso:country": "GB",
    "wof:name": "SN8 1SF",
    "wof:placetype": "postalcode"
  },
  "geometry": {"coordinates":[-1.727993,51.451322],"type":"Point"}
}
