{
  "type": "Feature",
  "properties": {
    "date:inception_lower": "1999-06-01",
    "date:inception_upper": "1999-06-01",
    "iso:country": "GB",
    "wof:name": "WF2 9SA",
    "wof:placetype": "postalcode"
  },
  "geometry": {"coordinates":[-1.507097,53.68045],"type":"Point"}
}
