{
  "type": "Feature",
  "properties": {
    "iso:country":"GB",
    "wof:name":"WF2 9SA",
    "wof:placetype":"postalcode"
},
  "geometry": {"coordinates":[-1.50635300483491,53.68045745768139],"type":"Point"}
}