{
  "type": "Feature",
  "properties": {
    "iso:country":"GB",
    "wof:name":"SN3 2QN",
    "wof:placetype":"postalcode"
},
  "geometry": {"coordinates":[-1.74504605650287,51.55732452975518],"type":"Point"}
}