{
  "type": "Feature",
  "properties": {
    "iso:country":"GB",
    "wof:name":"WA13 0TP",
    "wof:placetype":"postalcode"
},
  "geometry": {"coordinates":[-2.44093811233992,53.36901365236037],"type":"Point"}
}