{
  "type": "Feature",
  "properties": {
    "iso:country":"GB",
    "wof:name":"TW15 3PQ",
    "wof:placetype":"postalcode"
},
  "geometry": {"coordinates":[-0.47434401806655,51.43131783543439],"type":"Point"}
}