{
  "type": "Feature",
  "properties": {
    "iso:country":"GB",
    "wof:name":"HP13 6PX",
    "wof:placetype":"postalcode"
},
  "geometry": {"coordinates":[-0.74775332424824,51.63157849166151],"type":"Point"}
}