{
  "type": "Feature",
  "properties": {
    "iso:country":"GB",
    "wof:name":"SY20 9DB",
    "wof:placetype":"postalcode"
},
  "geometry": {"coordinates":[-3.85154580414892,52.66094158754646],"type":"Point"}
}