{
  "type": "Feature",
  "properties": {
    "iso:country": "GB",
    "wof:name": "SY20 9DB",
    "wof:placetype": "postalcode"
  },
  "geometry": {"coordinates":[-3.851554,52.660957],"type":"Point"}
}
