{
  "type": "Feature",
  "properties": {
    "date:inception_lower":"1980-01-01",
    "date:inception_upper":"1980-01-31",
    "iso:country":"GB",
    "wof:name":"SY20 9DB",
    "wof:placetype":"postalcode"
},
  "geometry": {"coordinates":[-3.851554,52.660957],"type":"Point"}
}