{
  "type": "Feature",
  "properties": {
    "date:inception_lower": "2006-10-01",
    "date:inception_upper": "2006-10-01",
    "iso:country": "GB",
    "wof:name": "CV10 7ST",
    "wof:placetype": "postalcode"
  },
  "geometry": {"coordinates":[-1.481194,52.506389],"type":"Point"}
}
