{
  "type": "Feature",
  "properties": {
    "iso:country":"GB",
    "wof:name":"LS13 4HE",
    "wof:placetype":"postalcode"
},
  "geometry": {"coordinates":[-1.62783037465072,53.80270293189368],"type":"Point"}
}