{
  "type": "Feature",
  "properties": {
    "iso:country":"GB",
    "wof:name":"NG32 1LG",
    "wof:placetype":"postalcode"
},
  "geometry": {"coordinates":[-0.71370539120417,52.88383577032767],"type":"Point"}
}