{
  "type": "Feature",
  "properties": {
    "iso:country":"GB",
    "wof:name":"PE6 7DZ",
    "wof:placetype":"postalcode"
},
  "geometry": {"coordinates":[-0.35012589719967,52.63479941842264],"type":"Point"}
}