{
  "type": "Feature",
  "properties": {
    "iso:country":"GB",
    "wof:name":"M26 2PP",
    "wof:placetype":"postalcode"
},
  "geometry": {"coordinates":[-2.30717434830931,53.56619117795813],"type":"Point"}
}