{
  "type": "Feature",
  "properties": {
    "iso:country":"GB",
    "wof:name":"PO35 5QY",
    "wof:placetype":"postalcode"
},
  "geometry": {"coordinates":[-1.07869197902067,50.68371175524776],"type":"Point"}
}