{
  "type": "Feature",
  "properties": {
    "iso:country": "GB",
    "wof:name": "WF17 0NA",
    "wof:placetype": "postalcode"
  },
  "geometry": {"coordinates":[-1.643557,53.736823],"type":"Point"}
}
