{
  "type": "Feature",
  "properties": {
    "date:inception_lower": "1980-01-01",
    "date:inception_upper": "1980-01-01",
    "iso:country": "GB",
    "wof:name": "WF17 0NA",
    "wof:placetype": "postalcode"
  },
  "geometry": {"coordinates":[-1.643557,53.736823],"type":"Point"}
}
