{
  "type": "Feature",
  "properties": {
    "date:inception_lower": "2017-08-01",
    "date:inception_upper": "2017-08-01",
    "iso:country": "GB",
    "wof:name": "MK3 5NW",
    "wof:placetype": "postalcode"
  },
  "geometry": {"coordinates":[-0.736629,51.976869],"type":"Point"}
}
