{
  "type": "Feature",
  "properties": {
    "date:inception_lower": "2016-02-01",
    "date:inception_upper": "2016-02-01",
    "iso:country": "GB",
    "wof:name": "TA3 7EJ",
    "wof:placetype": "postalcode"
  },
  "geometry": {"coordinates":[-3.121123,50.907471],"type":"Point"}
}
