{
  "type": "Feature",
  "properties": {
    "iso:country": "GB",
    "wof:name": "TA3 7EJ",
    "wof:placetype": "postalcode"
  },
  "geometry": {"coordinates":[-3.121123,50.907471],"type":"Point"}
}
