{
  "type": "Feature",
  "properties": {
    "iso:country":"GB",
    "wof:name":"TA3 7EJ",
    "wof:placetype":"postalcode"
},
  "geometry": {"coordinates":[-3.1211229386644,50.9074713546174],"type":"Point"}
}