{
  "type": "Feature",
  "properties": {
    "iso:country":"GB",
    "wof:name":"LS13 4HU",
    "wof:placetype":"postalcode"
},
  "geometry": {"coordinates":[-1.63029578526796,53.79860303193996],"type":"Point"}
}