{
  "type": "Feature",
  "properties": {
    "date:inception_lower": "1980-01-01",
    "date:inception_upper": "1980-01-01",
    "iso:country": "GB",
    "wof:name": "WV14 9ED",
    "wof:placetype": "postalcode"
  },
  "geometry": {"coordinates":[-2.087116,52.536135],"type":"Point"}
}
