{
  "type": "Feature",
  "properties": {
    "iso:country": "GB",
    "wof:name": "WV14 9ED",
    "wof:placetype": "postalcode"
  },
  "geometry": {"coordinates":[-2.087116,52.536135],"type":"Point"}
}
