{
  "type": "Feature",
  "properties": {
    "iso:country":"GB",
    "wof:name":"WV14 9ED",
    "wof:placetype":"postalcode"
},
  "geometry": {"coordinates":[-2.08711634588924,52.53613494914971],"type":"Point"}
}