{
  "type": "Feature",
  "properties": {
    "date:inception_lower": "1980-01-01",
    "date:inception_upper": "1980-01-01",
    "iso:country": "GB",
    "wof:name": "BB7 2LX",
    "wof:placetype": "postalcode"
  },
  "geometry": {"coordinates":[-2.409044,53.870346],"type":"Point"}
}
