{
  "type": "Feature",
  "properties": {
    "iso:country":"GB",
    "wof:name":"YO10 4ND",
    "wof:placetype":"postalcode"
},
  "geometry": {"coordinates":[-1.06150267525035,53.93939435224502],"type":"Point"}
}