{
  "type": "Feature",
  "properties": {
    "date:inception_lower":"1998-06-01",
    "date:inception_upper":"1998-06-30",
    "iso:country":"GB",
    "wof:name":"YO10 4ND",
    "wof:placetype":"postalcode"
},
  "geometry": {"coordinates":[-1.061503,53.939394],"type":"Point"}
}