{
  "type": "Feature",
  "properties": {
    "iso:country":"GB",
    "wof:name":"PL30 5EN",
    "wof:placetype":"postalcode"
},
  "geometry": {"coordinates":[-4.75209449558494,50.38974229370712],"type":"Point"}
}