{
  "type": "Feature",
  "properties": {
    "date:inception_lower": "1980-01-01",
    "date:inception_upper": "1980-01-01",
    "iso:country": "GB",
    "wof:name": "PL30 5EN",
    "wof:placetype": "postalcode"
  },
  "geometry": {"coordinates":[-4.752135,50.38973],"type":"Point"}
}
