{
  "type": "Feature",
  "properties": {
    "iso:country":"GB",
    "wof:name":"HP18 0PY",
    "wof:placetype":"postalcode"
},
  "geometry": {"coordinates":[-0.86925471148472,51.83280938998864],"type":"Point"}
}