{
  "type": "Feature",
  "properties": {
    "date:inception_lower": "1980-01-01",
    "date:inception_upper": "1980-01-01",
    "iso:country": "GB",
    "wof:name": "HP18 0PY",
    "wof:placetype": "postalcode"
  },
  "geometry": {"coordinates":[-0.86913,51.832851],"type":"Point"}
}
