{
  "type": "Feature",
  "properties": {
    "iso:country": "GB",
    "wof:name": "B44 8PE",
    "wof:placetype": "postalcode"
  },
  "geometry": {"coordinates":[-1.907303,52.551996],"type":"Point"}
}
