{
  "type": "Feature",
  "properties": {
    "iso:country":"GB",
    "wof:name":"B44 8PE",
    "wof:placetype":"postalcode"
},
  "geometry": {"coordinates":[-1.90730850444945,52.55198024440662],"type":"Point"}
}