{
  "type": "Feature",
  "properties": {
    "iso:country":"GB",
    "wof:name":"NE4 9TA",
    "wof:placetype":"postalcode"
},
  "geometry": {"coordinates":[-1.65579085204573,54.98762000105106],"type":"Point"}
}