{
  "type": "Feature",
  "properties": {
    "date:inception_lower": "1980-01-01",
    "date:inception_upper": "1980-01-01",
    "iso:country": "GB",
    "wof:name": "SK9 6LD",
    "wof:placetype": "postalcode"
  },
  "geometry": {"coordinates":[-2.2443,53.319269],"type":"Point"}
}
