{
  "type": "Feature",
  "properties": {
    "date:inception_lower": "2013-02-01",
    "date:inception_upper": "2013-02-01",
    "iso:country": "GB",
    "wof:name": "SG13 9TE",
    "wof:placetype": "postalcode"
  },
  "geometry": {"coordinates":[-0.081971,51.793012],"type":"Point"}
}
