{
  "type": "Feature",
  "properties": {
    "iso:country":"GB",
    "wof:name":"BA1 8DD",
    "wof:placetype":"postalcode"
},
  "geometry": {"coordinates":[-2.3475128887063,51.41073051893368],"type":"Point"}
}