{
  "type": "Feature",
  "properties": {
    "iso:country": "GB",
    "wof:name": "BA1 8DD",
    "wof:placetype": "postalcode"
  },
  "geometry": {"coordinates":[-2.347513,51.410731],"type":"Point"}
}
