{
  "type": "Feature",
  "properties": {
    "iso:country":"GB",
    "wof:name":"EN7 6JY",
    "wof:placetype":"postalcode"
},
  "geometry": {"coordinates":[-0.05389627147512,51.70944411109308],"type":"Point"}
}