{
  "type": "Feature",
  "properties": {
    "iso:country": "GB",
    "wof:name": "KA22 7JY",
    "wof:placetype": "postalcode"
  },
  "geometry": {"coordinates":[-4.809991,55.655782],"type":"Point"}
}
