{
  "type": "Feature",
  "properties": {
    "iso:country":"GB",
    "wof:name":"KA22 7JY",
    "wof:placetype":"postalcode"
},
  "geometry": {"coordinates":[-4.81000777979795,55.65571282793317],"type":"Point"}
}