{
  "type": "Feature",
  "properties": {
    "date:inception_lower": "1999-06-01",
    "date:inception_upper": "1999-06-01",
    "iso:country": "GB",
    "wof:name": "HU9 1ST",
    "wof:placetype": "postalcode"
  },
  "geometry": {"coordinates":[-0.310276,53.745165],"type":"Point"}
}
