{
  "type": "Feature",
  "properties": {
    "iso:country":"GB",
    "wof:name":"HU9 1ST",
    "wof:placetype":"postalcode"
},
  "geometry": {"coordinates":[-0.31027610436607,53.74516506133113],"type":"Point"}
}