{
  "type": "Feature",
  "properties": {
    "date:inception_lower": "1980-01-01",
    "date:inception_upper": "1980-01-01",
    "iso:country": "GB",
    "wof:name": "PE22 0DW",
    "wof:placetype": "postalcode"
  },
  "geometry": {"coordinates":[0.088413,52.987343],"type":"Point"}
}
