{
  "type": "Feature",
  "properties": {
    "iso:country": "GB",
    "wof:name": "S5 0DX",
    "wof:placetype": "postalcode"
  },
  "geometry": {"coordinates":[-1.442671,53.436007],"type":"Point"}
}
