{
  "type": "Feature",
  "properties": {
    "iso:country":"GB",
    "wof:name":"WV4 6PW",
    "wof:placetype":"postalcode"
},
  "geometry": {"coordinates":[-2.11211977859927,52.55326651196979],"type":"Point"}
}