{
  "type": "Feature",
  "properties": {
    "iso:country":"GB",
    "wof:name":"OX2 7PU",
    "wof:placetype":"postalcode"
},
  "geometry": {"coordinates":[-1.2644797697595,51.7834985949784],"type":"Point"}
}