{
  "type": "Feature",
  "properties": {
    "iso:country": "GB",
    "wof:name": "NN6 8PA",
    "wof:placetype": "postalcode"
  },
  "geometry": {"coordinates":[-0.933486,52.34903],"type":"Point"}
}
