{
  "type": "Feature",
  "properties": {
    "iso:country": "GB",
    "wof:name": "NG14 6LJ",
    "wof:placetype": "postalcode"
  },
  "geometry": {"coordinates":[-1.090299,53.04076],"type":"Point"}
}
