{
  "type": "Feature",
  "properties": {
    "date:inception_lower": "2000-12-01",
    "date:inception_upper": "2000-12-01",
    "iso:country": "GB",
    "wof:name": "W1U 4QH",
    "wof:placetype": "postalcode"
  },
  "geometry": {"coordinates":[-0.151732,51.520926],"type":"Point"}
}
