{
  "type": "Feature",
  "properties": {
    "iso:country":"GB",
    "wof:name":"W1U 4QH",
    "wof:placetype":"postalcode"
},
  "geometry": {"coordinates":[-0.15173189264001,51.52092576305063],"type":"Point"}
}