{
  "type": "Feature",
  "properties": {
    "date:inception_lower":"1997-12-01",
    "date:inception_upper":"1997-12-31",
    "iso:country":"GB",
    "wof:name":"LS17 7UY",
    "wof:placetype":"postalcode"
},
  "geometry": {"coordinates":[-1.531984,53.856583],"type":"Point"}
}