{
  "type": "Feature",
  "properties": {
    "iso:country":"GB",
    "wof:name":"LS17 7UY",
    "wof:placetype":"postalcode"
},
  "geometry": {"coordinates":[-1.53198375928465,53.8565830372311],"type":"Point"}
}