{
  "type": "Feature",
  "properties": {
    "iso:country":"GB",
    "wof:name":"CM7 5RJ",
    "wof:placetype":"postalcode"
},
  "geometry": {"coordinates":[0.54401926988884,51.88725665341485],"type":"Point"}
}