{
  "type": "Feature",
  "properties": {
    "date:inception_lower":"1980-01-01",
    "date:inception_upper":"1980-01-31",
    "iso:country":"GB",
    "wof:name":"HU13 9ER",
    "wof:placetype":"postalcode"
},
  "geometry": {"coordinates":[-0.424925,53.729638],"type":"Point"}
}