{
  "type": "Feature",
  "properties": {
    "iso:country": "GB",
    "wof:name": "HU13 9ER",
    "wof:placetype": "postalcode"
  },
  "geometry": {"coordinates":[-0.424925,53.729638],"type":"Point"}
}
