{
  "type": "Feature",
  "properties": {
    "iso:country": "GB",
    "wof:name": "TF1 3DT",
    "wof:placetype": "postalcode"
  },
  "geometry": {"coordinates":[-2.530959,52.703867],"type":"Point"}
}
