{
  "type": "Feature",
  "properties": {
    "date:inception_lower":"1984-02-01",
    "date:inception_upper":"1984-02-29",
    "iso:country":"GB",
    "wof:name":"TF1 3DT",
    "wof:placetype":"postalcode"
},
  "geometry": {"coordinates":[-2.530959,52.703867],"type":"Point"}
}