{
  "type": "Feature",
  "properties": {
    "iso:country":"GB",
    "wof:name":"TF1 3DT",
    "wof:placetype":"postalcode"
},
  "geometry": {"coordinates":[-2.53095924327168,52.7038674902272],"type":"Point"}
}