{
  "type": "Feature",
  "properties": {
    "iso:country": "GB",
    "wof:name": "PH2 6BY",
    "wof:placetype": "postalcode"
  },
  "geometry": {"coordinates":[-3.407562,56.469446],"type":"Point"}
}
