{
  "type": "Feature",
  "properties": {
    "iso:country": "GB",
    "wof:name": "CA1 3JU",
    "wof:placetype": "postalcode"
  },
  "geometry": {"coordinates":[-2.90011,54.878157],"type":"Point"}
}
