{
  "type": "Feature",
  "properties": {
    "iso:country": "GB",
    "wof:name": "PO10 8LP",
    "wof:placetype": "postalcode"
  },
  "geometry": {"coordinates":[-0.909255,50.85022],"type":"Point"}
}
