{
  "type": "Feature",
  "properties": {
    "iso:country":"GB",
    "wof:name":"WD7 7LL",
    "wof:placetype":"postalcode"
},
  "geometry": {"coordinates":[-0.31432632147635,51.66986691552013],"type":"Point"}
}