{
  "type": "Feature",
  "properties": {
    "iso:country":"GB",
    "wof:name":"B63 2DY",
    "wof:placetype":"postalcode"
},
  "geometry": {"coordinates":[-2.07831752446836,52.45500694278029],"type":"Point"}
}