{
  "type": "Feature",
  "properties": {
    "date:inception_lower": "1980-01-01",
    "date:inception_upper": "1980-01-01",
    "iso:country": "GB",
    "wof:name": "B63 2DY",
    "wof:placetype": "postalcode"
  },
  "geometry": {"coordinates":[-2.078312,52.455022],"type":"Point"}
}
