{
  "type": "Feature",
  "properties": {
    "date:inception_lower": "1980-01-01",
    "date:inception_upper": "1980-01-01",
    "iso:country": "GB",
    "wof:name": "BH20 5LN",
    "wof:placetype": "postalcode"
  },
  "geometry": {"coordinates":[-2.067143,50.601159],"type":"Point"}
}
