{
  "type": "Feature",
  "properties": {
    "iso:country":"GB",
    "wof:name":"BH20 5LN",
    "wof:placetype":"postalcode"
},
  "geometry": {"coordinates":[-2.06714946605318,50.60117110956958],"type":"Point"}
}