{
  "type": "Feature",
  "properties": {
    "iso:country":"GB",
    "wof:name":"EC1M 6JH",
    "wof:placetype":"postalcode"
},
  "geometry": {"coordinates":[-0.10056190157729,51.52019821705411],"type":"Point"}
}