{
  "type": "Feature",
  "properties": {
    "iso:country":"GB",
    "wof:name":"N21 2DB",
    "wof:placetype":"postalcode"
},
  "geometry": {"coordinates":[-0.0833988945343,51.64358359493207],"type":"Point"}
}