{
  "type": "Feature",
  "properties": {
    "iso:country":"GB",
    "wof:name":"SG8 9TD",
    "wof:placetype":"postalcode"
},
  "geometry": {"coordinates":[-0.00891660721792,52.04731741881565],"type":"Point"}
}