{
  "type": "Feature",
  "properties": {
    "iso:country": "GB",
    "wof:name": "SG8 9TD",
    "wof:placetype": "postalcode"
  },
  "geometry": {"coordinates":[-0.008916,52.047346],"type":"Point"}
}
