{
  "type": "Feature",
  "properties": {
    "date:inception_lower": "2021-08-01",
    "date:inception_upper": "2021-08-01",
    "iso:country": "GB",
    "wof:name": "WR2 5NL",
    "wof:placetype": "postalcode"
  },
  "geometry": {"coordinates":[-2.243572,52.190841],"type":"Point"}
}
