{
  "type": "Feature",
  "properties": {
    "iso:country":"GB",
    "wof:name":"PR4 1SE",
    "wof:placetype":"postalcode"
},
  "geometry": {"coordinates":[-2.86830126234229,53.75126509723393],"type":"Point"}
}