{
  "type": "Feature",
  "properties": {
    "iso:country":"GB",
    "wof:name":"DG12 6ED",
    "wof:placetype":"postalcode"
},
  "geometry": {"coordinates":[-3.26009101355101,54.98717573975796],"type":"Point"}
}