{
  "type": "Feature",
  "properties": {
    "iso:country":"GB",
    "wof:name":"NE38 7RY",
    "wof:placetype":"postalcode"
},
  "geometry": {"coordinates":[-1.53015328123292,54.89854067021556],"type":"Point"}
}