{
  "type": "Feature",
  "properties": {
    "iso:country":"GB",
    "wof:name":"SA12 7EL",
    "wof:placetype":"postalcode"
},
  "geometry": {"coordinates":[-3.81732382405375,51.60303398833694],"type":"Point"}
}