{
  "type": "Feature",
  "properties": {
    "iso:country":"GB",
    "wof:name":"LE5 4LB",
    "wof:placetype":"postalcode"
},
  "geometry": {"coordinates":[-1.07923463651546,52.63287274826371],"type":"Point"}
}