{
  "type": "Feature",
  "properties": {
    "iso:country":"GB",
    "wof:name":"SY5 7HF",
    "wof:placetype":"postalcode"
},
  "geometry": {"coordinates":[-2.71833790998514,52.60838730869003],"type":"Point"}
}