{
  "type": "Feature",
  "properties": {
    "date:inception_lower": "1980-01-01",
    "date:inception_upper": "1980-01-01",
    "iso:country": "GB",
    "wof:name": "SY5 7HF",
    "wof:placetype": "postalcode"
  },
  "geometry": {"coordinates":[-2.718338,52.608387],"type":"Point"}
}
