{
  "type": "Feature",
  "properties": {
    "iso:country": "GB",
    "wof:name": "SY5 7HF",
    "wof:placetype": "postalcode"
  },
  "geometry": {"coordinates":[-2.718338,52.608387],"type":"Point"}
}
