{
  "type": "Feature",
  "properties": {
    "iso:country":"GB",
    "wof:name":"ST6 4BW",
    "wof:placetype":"postalcode"
},
  "geometry": {"coordinates":[-2.20197999427183,53.04497086617543],"type":"Point"}
}