{
  "type": "Feature",
  "properties": {
    "iso:country":"GB",
    "wof:name":"WA4 2NS",
    "wof:placetype":"postalcode"
},
  "geometry": {"coordinates":[-2.54906219800177,53.37761669386699],"type":"Point"}
}