{
  "type": "Feature",
  "properties": {
    "date:inception_lower": "1992-08-01",
    "date:inception_upper": "1992-08-01",
    "iso:country": "GB",
    "wof:name": "LE18 4XP",
    "wof:placetype": "postalcode"
  },
  "geometry": {"coordinates":[-1.13372,52.58462],"type":"Point"}
}
