{
  "type": "Feature",
  "properties": {
    "iso:country":"GB",
    "wof:name":"LE18 4XP",
    "wof:placetype":"postalcode"
},
  "geometry": {"coordinates":[-1.13371992915672,52.58462050242348],"type":"Point"}
}