{
  "type": "Feature",
  "properties": {
    "date:inception_lower":"2002-06-01",
    "date:inception_upper":"2002-06-30",
    "iso:country":"GB",
    "wof:name":"CB9 7DJ",
    "wof:placetype":"postalcode"
},
  "geometry": {"coordinates":[0.444842,52.043621],"type":"Point"}
}