{
  "type": "Feature",
  "properties": {
    "iso:country":"GB",
    "wof:name":"CB9 7DJ",
    "wof:placetype":"postalcode"
},
  "geometry": {"coordinates":[0.44484209639636,52.04362088642655],"type":"Point"}
}