{
  "type": "Feature",
  "properties": {
    "iso:country":"GB",
    "wof:name":"KW1 5UL",
    "wof:placetype":"postalcode"
},
  "geometry": {"coordinates":[-3.26704679319845,58.48629180733759],"type":"Point"}
}