{
  "type": "Feature",
  "properties": {
    "iso:country":"GB",
    "wof:name":"S36 6BS",
    "wof:placetype":"postalcode"
},
  "geometry": {"coordinates":[-1.63123211332975,53.5233237861656],"type":"Point"}
}