{
  "type": "Feature",
  "properties": {
    "iso:country": "GB",
    "wof:name": "S70 3QY",
    "wof:placetype": "postalcode"
  },
  "geometry": {"coordinates":[-1.460779,53.546649],"type":"Point"}
}
