{
  "type": "Feature",
  "properties": {
    "date:inception_lower":"1998-12-01",
    "date:inception_upper":"1998-12-31",
    "iso:country":"GB",
    "wof:name":"GU23 6LS",
    "wof:placetype":"postalcode"
},
  "geometry": {"coordinates":[-0.515321,51.292058],"type":"Point"}
}