{
  "type": "Feature",
  "properties": {
    "iso:country":"GB",
    "wof:name":"L2 7NX",
    "wof:placetype":"postalcode"
},
  "geometry": {"coordinates":[-2.99128043193013,53.40474987493838],"type":"Point"}
}