{
  "type": "Feature",
  "properties": {
    "iso:country":"GB",
    "wof:name":"TN8 6PE",
    "wof:placetype":"postalcode"
},
  "geometry": {"coordinates":[0.11907212577044,51.21057382030151],"type":"Point"}
}