{
  "type": "Feature",
  "properties": {
    "iso:country":"GB",
    "wof:name":"AL2 1BU",
    "wof:placetype":"postalcode"
},
  "geometry": {"coordinates":[-0.27138386070909,51.7118113999397],"type":"Point"}
}