{
  "type": "Feature",
  "properties": {
    "iso:country": "GB",
    "wof:name": "AL2 1BU",
    "wof:placetype": "postalcode"
  },
  "geometry": {"coordinates":[-0.271243,51.711455],"type":"Point"}
}
