{
  "type": "Feature",
  "properties": {
    "iso:country":"GB",
    "wof:name":"PL9 9RU",
    "wof:placetype":"postalcode"
},
  "geometry": {"coordinates":[-4.1169184042305,50.35283732391837],"type":"Point"}
}