{
  "type": "Feature",
  "properties": {
    "iso:country": "GB",
    "wof:name": "WN8 6PJ",
    "wof:placetype": "postalcode"
  },
  "geometry": {"coordinates":[-2.774766,53.566772],"type":"Point"}
}
