{
  "type": "Feature",
  "properties": {
    "iso:country":"GB",
    "wof:name":"WN8 6PJ",
    "wof:placetype":"postalcode"
},
  "geometry": {"coordinates":[-2.77476629090484,53.56677212622764],"type":"Point"}
}