{
  "type": "Feature",
  "properties": {
    "iso:country":"GB",
    "wof:name":"DA15 7AG",
    "wof:placetype":"postalcode"
},
  "geometry": {"coordinates":[0.10368376432678,51.43427511791047],"type":"Point"}
}