{
  "type": "Feature",
  "properties": {
    "date:inception_lower": "1980-01-01",
    "date:inception_upper": "1980-01-01",
    "iso:country": "GB",
    "wof:name": "DA15 7AG",
    "wof:placetype": "postalcode"
  },
  "geometry": {"coordinates":[0.103684,51.434275],"type":"Point"}
}
