{
  "type": "Feature",
  "properties": {
    "iso:country":"GB",
    "wof:name":"OL10 4BY",
    "wof:placetype":"postalcode"
},
  "geometry": {"coordinates":[-2.2081789335693,53.5951851688328],"type":"Point"}
}