{
  "type": "Feature",
  "properties": {
    "iso:country":"GB",
    "wof:name":"M30 0JQ",
    "wof:placetype":"postalcode"
},
  "geometry": {"coordinates":[-2.34990540509688,53.4804320699807],"type":"Point"}
}