{
  "type": "Feature",
  "properties": {
    "iso:country": "GB",
    "wof:name": "M30 0JQ",
    "wof:placetype": "postalcode"
  },
  "geometry": {"coordinates":[-2.349905,53.480432],"type":"Point"}
}
