{
  "type": "Feature",
  "properties": {
    "date:inception_lower": "1990-08-01",
    "date:inception_upper": "1990-08-01",
    "iso:country": "GB",
    "wof:name": "AB30 1QT",
    "wof:placetype": "postalcode"
  },
  "geometry": {"coordinates":[-2.558562,56.792547],"type":"Point"}
}
