{
  "type": "Feature",
  "properties": {
    "iso:country":"GB",
    "wof:name":"AB30 1QT",
    "wof:placetype":"postalcode"
},
  "geometry": {"coordinates":[-2.55856168003461,56.79254720185056],"type":"Point"}
}