{
  "type": "Feature",
  "properties": {
    "iso:country": "GB",
    "wof:name": "NP11 6FY",
    "wof:placetype": "postalcode"
  },
  "geometry": {"coordinates":[-3.090152,51.620026],"type":"Point"}
}
