{
  "type": "Feature",
  "properties": {
    "iso:country": "GB",
    "wof:name": "TA1 2DP",
    "wof:placetype": "postalcode"
  },
  "geometry": {"coordinates":[-3.073754,51.019258],"type":"Point"}
}
