{
  "type": "Feature",
  "properties": {
    "iso:country": "GB",
    "wof:name": "SL0 9AB",
    "wof:placetype": "postalcode"
  },
  "geometry": {"coordinates":[-0.505337,51.50719],"type":"Point"}
}
