{
  "type": "Feature",
  "properties": {
    "iso:country":"GB",
    "wof:name":"HP18 0ER",
    "wof:placetype":"postalcode"
},
  "geometry": {"coordinates":[-0.90614424088808,51.83408428803114],"type":"Point"}
}