{
  "type": "Feature",
  "properties": {
    "iso:country": "GB",
    "wof:name": "HP18 0ER",
    "wof:placetype": "postalcode"
  },
  "geometry": {"coordinates":[-0.906636,51.834473],"type":"Point"}
}
