{
  "type": "Feature",
  "properties": {
    "iso:country": "GB",
    "wof:name": "DN18 5BH",
    "wof:placetype": "postalcode"
  },
  "geometry": {"coordinates":[-0.444055,53.689806],"type":"Point"}
}
