{
  "type": "Feature",
  "properties": {
    "iso:country":"GB",
    "wof:name":"W5 1LG",
    "wof:placetype":"postalcode"
},
  "geometry": {"coordinates":[-0.30174407971318,51.52783355153119],"type":"Point"}
}