{
  "type": "Feature",
  "properties": {
    "iso:country":"GB",
    "wof:name":"ST6 6RD",
    "wof:placetype":"postalcode"
},
  "geometry": {"coordinates":[-2.18845092798795,53.07221205561233],"type":"Point"}
}