{
  "type": "Feature",
  "properties": {
    "iso:country": "GB",
    "wof:name": "ST6 6RD",
    "wof:placetype": "postalcode"
  },
  "geometry": {"coordinates":[-2.188451,53.072212],"type":"Point"}
}
