{
  "type": "Feature",
  "properties": {
    "iso:country":"GB",
    "wof:name":"WV1 2NE",
    "wof:placetype":"postalcode"
},
  "geometry": {"coordinates":[-2.09642445069198,52.58553585972953],"type":"Point"}
}