{
  "type": "Feature",
  "properties": {
    "iso:country":"GB",
    "wof:name":"IG5 0JP",
    "wof:placetype":"postalcode"
},
  "geometry": {"coordinates":[0.05399932601287,51.59020924261324],"type":"Point"}
}