{
  "type": "Feature",
  "properties": {
    "iso:country":"GB",
    "wof:name":"BH18 8HA",
    "wof:placetype":"postalcode"
},
  "geometry": {"coordinates":[-2.00095428973583,50.74713382620737],"type":"Point"}
}