{
  "type": "Feature",
  "properties": {
    "date:inception_lower": "2022-02-01",
    "date:inception_upper": "2022-02-01",
    "iso:country": "GB",
    "wof:name": "SY2 5WW",
    "wof:placetype": "postalcode"
  },
  "geometry": {"coordinates":[-2.717374,52.699502],"type":"Point"}
}
