{
  "type": "Feature",
  "properties": {
    "iso:country": "GB",
    "wof:name": "SS3 0PU",
    "wof:placetype": "postalcode"
  },
  "geometry": {"coordinates":[0.767514,51.552821],"type":"Point"}
}
