{
  "type": "Feature",
  "properties": {
    "iso:country":"GB",
    "wof:name":"CV6 4HU",
    "wof:placetype":"postalcode"
},
  "geometry": {"coordinates":[-1.51834528532524,52.44751769928551],"type":"Point"}
}