{
  "type": "Feature",
  "properties": {
    "iso:country": "GB",
    "wof:name": "WR10 3JH",
    "wof:placetype": "postalcode"
  },
  "geometry": {"coordinates":[-2.024712,52.070507],"type":"Point"}
}
