{
  "type": "Feature",
  "properties": {
    "date:inception_lower": "1985-04-01",
    "date:inception_upper": "1985-04-01",
    "iso:country": "GB",
    "wof:name": "WR10 3JH",
    "wof:placetype": "postalcode"
  },
  "geometry": {"coordinates":[-2.024712,52.070507],"type":"Point"}
}
