{
  "type": "Feature",
  "properties": {
    "iso:country":"GB",
    "wof:name":"TD8 6RG",
    "wof:placetype":"postalcode"
},
  "geometry": {"coordinates":[-2.47359534257792,55.44962664120692],"type":"Point"}
}