{
  "type": "Feature",
  "properties": {
    "iso:country": "GB",
    "wof:name": "M44 6QD",
    "wof:placetype": "postalcode"
  },
  "geometry": {"coordinates":[-2.41213,53.455001],"type":"Point"}
}
