{
  "type": "Feature",
  "properties": {
    "iso:country":"GB",
    "wof:name":"M44 6QD",
    "wof:placetype":"postalcode"
},
  "geometry": {"coordinates":[-2.41213176095582,53.45498479570959],"type":"Point"}
}