{
  "type": "Feature",
  "properties": {
    "date:inception_lower":"2006-09-01",
    "date:inception_upper":"2006-09-30",
    "iso:country":"GB",
    "wof:name":"BD5 0RG",
    "wof:placetype":"postalcode"
},
  "geometry": {"coordinates":[-1.757404,53.787324],"type":"Point"}
}