{
  "type": "Feature",
  "properties": {
    "iso:country":"GB",
    "wof:name":"BS3 3BE",
    "wof:placetype":"postalcode"
},
  "geometry": {"coordinates":[-2.60468734831627,51.43951076676955],"type":"Point"}
}