{
  "type": "Feature",
  "properties": {
    "iso:country": "GB",
    "wof:name": "BH20 4HA",
    "wof:placetype": "postalcode"
  },
  "geometry": {"coordinates":[-2.109656,50.687461],"type":"Point"}
}
