{
  "type": "Feature",
  "properties": {
    "date:inception_lower":"1980-01-01",
    "date:inception_upper":"1980-01-31",
    "iso:country":"GB",
    "wof:name":"DN35 8TW",
    "wof:placetype":"postalcode"
},
  "geometry": {"coordinates":[-0.030221,53.552077],"type":"Point"}
}