{
  "type": "Feature",
  "properties": {
    "iso:country":"GB",
    "wof:name":"DN35 8TW",
    "wof:placetype":"postalcode"
},
  "geometry": {"coordinates":[-0.03022114631931,53.55207709273468],"type":"Point"}
}