{
  "type": "Feature",
  "properties": {
    "iso:country":"GB",
    "wof:name":"CW10 0FY",
    "wof:placetype":"postalcode"
},
  "geometry": {"coordinates":[-2.43823976136633,53.17331885308731],"type":"Point"}
}