{
  "type": "Feature",
  "properties": {
    "date:inception_lower": "2015-11-01",
    "date:inception_upper": "2015-11-01",
    "iso:country": "GB",
    "wof:name": "CW10 0FY",
    "wof:placetype": "postalcode"
  },
  "geometry": {"coordinates":[-2.438162,53.173173],"type":"Point"}
}
