{
  "type": "Feature",
  "properties": {
    "iso:country":"GB",
    "wof:name":"SA17 4RP",
    "wof:placetype":"postalcode"
},
  "geometry": {"coordinates":[-4.26930808379801,51.74997407772455],"type":"Point"}
}