{
  "type": "Feature",
  "properties": {
    "iso:country":"GB",
    "wof:name":"GL13 9JH",
    "wof:placetype":"postalcode"
},
  "geometry": {"coordinates":[-2.43497441538684,51.66611064159773],"type":"Point"}
}