{
  "type": "Feature",
  "properties": {
    "iso:country":"GB",
    "wof:name":"PH1 3FF",
    "wof:placetype":"postalcode"
},
  "geometry": {"coordinates":[-3.46261233901765,56.45226788732745],"type":"Point"}
}