{
  "type": "Feature",
  "properties": {
    "date:inception_lower": "2003-07-01",
    "date:inception_upper": "2003-07-01",
    "iso:country": "GB",
    "wof:name": "PH1 3FF",
    "wof:placetype": "postalcode"
  },
  "geometry": {"coordinates":[-3.462612,56.452268],"type":"Point"}
}
