{
  "type": "Feature",
  "properties": {
    "iso:country":"GB",
    "wof:name":"RG41 5AJ",
    "wof:placetype":"postalcode"
},
  "geometry": {"coordinates":[-0.86832465011542,51.42286136162652],"type":"Point"}
}