{
  "type": "Feature",
  "properties": {
    "iso:country":"GB",
    "wof:name":"CF39 8AL",
    "wof:placetype":"postalcode"
},
  "geometry": {"coordinates":[-3.42986298798669,51.57299328265659],"type":"Point"}
}