{
  "type": "Feature",
  "properties": {
    "iso:country": "GB",
    "wof:name": "BD4 6QJ",
    "wof:placetype": "postalcode"
  },
  "geometry": {"coordinates":[-1.718616,53.766492],"type":"Point"}
}
