{
  "type": "Feature",
  "properties": {
    "iso:country":"GB",
    "wof:name":"BD4 6QJ",
    "wof:placetype":"postalcode"
},
  "geometry": {"coordinates":[-1.71861216807469,53.76647673515808],"type":"Point"}
}