{
  "type": "Feature",
  "properties": {
    "iso:country":"GB",
    "wof:name":"B92 8RJ",
    "wof:placetype":"postalcode"
},
  "geometry": {"coordinates":[-1.7936349203163,52.43739486598495],"type":"Point"}
}