{
  "type": "Feature",
  "properties": {
    "iso:country": "GB",
    "wof:name": "WR4 0UT",
    "wof:placetype": "postalcode"
  },
  "geometry": {"coordinates":[-2.176729,52.203022],"type":"Point"}
}
