{
  "type": "Feature",
  "properties": {
    "date:inception_lower": "1992-08-01",
    "date:inception_upper": "1992-08-01",
    "iso:country": "GB",
    "wof:name": "WR4 0UT",
    "wof:placetype": "postalcode"
  },
  "geometry": {"coordinates":[-2.17725,52.202881],"type":"Point"}
}
