{
  "type": "Feature",
  "properties": {
    "iso:country":"GB",
    "wof:name":"LS29 0FA",
    "wof:placetype":"postalcode"
},
  "geometry": {"coordinates":[-1.90841493071207,53.94551333437715],"type":"Point"}
}