{
  "type": "Feature",
  "properties": {
    "date:inception_lower": "2015-07-01",
    "date:inception_upper": "2015-07-01",
    "iso:country": "GB",
    "wof:name": "LS29 0FA",
    "wof:placetype": "postalcode"
  },
  "geometry": {"coordinates":[-1.908415,53.945513],"type":"Point"}
}
