{
  "type": "Feature",
  "properties": {
    "iso:country": "GB",
    "wof:name": "LS29 0FA",
    "wof:placetype": "postalcode"
  },
  "geometry": {"coordinates":[-1.908415,53.945513],"type":"Point"}
}
