{
  "type": "Feature",
  "properties": {
    "iso:country": "GB",
    "wof:name": "SO40 7QA",
    "wof:placetype": "postalcode"
  },
  "geometry": {"coordinates":[-1.503938,50.910104],"type":"Point"}
}
