{
  "type": "Feature",
  "properties": {
    "iso:country":"GB",
    "wof:name":"SO40 7QA",
    "wof:placetype":"postalcode"
},
  "geometry": {"coordinates":[-1.50393820984724,50.91010443347226],"type":"Point"}
}