{
  "type": "Feature",
  "properties": {
    "date:inception_lower":"1980-01-01",
    "date:inception_upper":"1980-01-31",
    "iso:country":"GB",
    "wof:name":"GL15 5JE",
    "wof:placetype":"postalcode"
},
  "geometry": {"coordinates":[-2.536896,51.727315],"type":"Point"}
}