{
  "type": "Feature",
  "properties": {
    "date:inception_lower":"1982-03-01",
    "date:inception_upper":"1982-03-31",
    "iso:country":"GB",
    "wof:name":"EX10 0NU",
    "wof:placetype":"postalcode"
},
  "geometry": {"coordinates":[-3.190803,50.697642],"type":"Point"}
}