{
  "type": "Feature",
  "properties": {
    "date:inception_lower": "2022-06-01",
    "date:inception_upper": "2022-06-01",
    "iso:country": "GB",
    "wof:name": "BA14 6GY",
    "wof:placetype": "postalcode"
  },
  "geometry": {"coordinates":[-2.153244,51.341592],"type":"Point"}
}
