{
  "type": "Feature",
  "properties": {
    "iso:country":"GB",
    "wof:name":"OX10 6HG",
    "wof:placetype":"postalcode"
},
  "geometry": {"coordinates":[-1.07636003277678,51.62198945332991],"type":"Point"}
}