{
  "type": "Feature",
  "properties": {
    "iso:country": "GB",
    "wof:name": "OX10 6HG",
    "wof:placetype": "postalcode"
  },
  "geometry": {"coordinates":[-1.07636,51.621989],"type":"Point"}
}
