{
  "type": "Feature",
  "properties": {
    "date:inception_lower": "2012-06-01",
    "date:inception_upper": "2012-06-01",
    "iso:country": "GB",
    "wof:name": "B31 2AW",
    "wof:placetype": "postalcode"
  },
  "geometry": {"coordinates":[-1.955163,52.423919],"type":"Point"}
}
