{
  "type": "Feature",
  "properties": {
    "date:inception_lower": "1980-01-01",
    "date:inception_upper": "1980-01-01",
    "iso:country": "GB",
    "wof:name": "CA28 6EA",
    "wof:placetype": "postalcode"
  },
  "geometry": {"coordinates":[-3.577824,54.560194],"type":"Point"}
}
