{
  "type": "Feature",
  "properties": {
    "iso:country":"GB",
    "wof:name":"DN15 6LT",
    "wof:placetype":"postalcode"
},
  "geometry": {"coordinates":[-0.64921863262826,53.5912056934143],"type":"Point"}
}