{
  "type": "Feature",
  "properties": {
    "iso:country": "GB",
    "wof:name": "G42 0LE",
    "wof:placetype": "postalcode"
  },
  "geometry": {"coordinates":[-4.237566,55.830193],"type":"Point"}
}
