{
  "type": "Feature",
  "properties": {
    "iso:country":"GB",
    "wof:name":"G42 0LE",
    "wof:placetype":"postalcode"
},
  "geometry": {"coordinates":[-4.23756630214555,55.83019318693489],"type":"Point"}
}