{
  "type": "Feature",
  "properties": {
    "date:inception_lower": "1980-01-01",
    "date:inception_upper": "1980-01-01",
    "iso:country": "GB",
    "wof:name": "CF31 1PR",
    "wof:placetype": "postalcode"
  },
  "geometry": {"coordinates":[-3.57478,51.520963],"type":"Point"}
}
