{
  "type": "Feature",
  "properties": {
    "date:inception_lower": "1980-01-01",
    "date:inception_upper": "1980-01-01",
    "iso:country": "GB",
    "wof:name": "G46 7UG",
    "wof:placetype": "postalcode"
  },
  "geometry": {"coordinates":[-4.317401,55.798408],"type":"Point"}
}
