{
  "type": "Feature",
  "properties": {
    "iso:country":"GB",
    "wof:name":"G46 7UG",
    "wof:placetype":"postalcode"
},
  "geometry": {"coordinates":[-4.31740069196677,55.79840804865285],"type":"Point"}
}