{
  "type": "Feature",
  "properties": {
    "iso:country": "GB",
    "wof:name": "KY15 4EW",
    "wof:placetype": "postalcode"
  },
  "geometry": {"coordinates":[-3.025112,56.322835],"type":"Point"}
}
