{
  "type": "Feature",
  "properties": {
    "iso:country": "GB",
    "wof:name": "M19 2HR",
    "wof:placetype": "postalcode"
  },
  "geometry": {"coordinates":[-2.199921,53.43988],"type":"Point"}
}
