{
  "type": "Feature",
  "properties": {
    "iso:country":"GB",
    "wof:name":"CT10 2TF",
    "wof:placetype":"postalcode"
},
  "geometry": {"coordinates":[1.41934249255535,51.36384176192222],"type":"Point"}
}