{
  "type": "Feature",
  "properties": {
    "iso:country": "GB",
    "wof:name": "OX2 0QT",
    "wof:placetype": "postalcode"
  },
  "geometry": {"coordinates":[-1.281794,51.751201],"type":"Point"}
}
