{
  "type": "Feature",
  "properties": {
    "iso:country":"GB",
    "wof:name":"OX2 0QT",
    "wof:placetype":"postalcode"
},
  "geometry": {"coordinates":[-1.28179382667558,51.75120125376375],"type":"Point"}
}