{
  "type": "Feature",
  "properties": {
    "iso:country": "GB",
    "wof:name": "AB53 8BX",
    "wof:placetype": "postalcode"
  },
  "geometry": {"coordinates":[-2.460173,57.496194],"type":"Point"}
}
