{
  "type": "Feature",
  "properties": {
    "iso:country":"GB",
    "wof:name":"DL6 2QB",
    "wof:placetype":"postalcode"
},
  "geometry": {"coordinates":[-1.43081235871421,54.35558863786481],"type":"Point"}
}