{
  "type": "Feature",
  "properties": {
    "iso:country": "GB",
    "wof:name": "G64 3BX",
    "wof:placetype": "postalcode"
  },
  "geometry": {"coordinates":[-4.228427,55.911273],"type":"Point"}
}
