{
  "type": "Feature",
  "properties": {
    "iso:country":"GB",
    "wof:name":"G64 3BX",
    "wof:placetype":"postalcode"
},
  "geometry": {"coordinates":[-4.22842664544627,55.91127257875615],"type":"Point"}
}