{
  "type": "Feature",
  "properties": {
    "date:inception_lower": "2023-05-01",
    "date:inception_upper": "2023-05-01",
    "iso:country": "GB",
    "wof:name": "PE29 2QE",
    "wof:placetype": "postalcode"
  },
  "geometry": {"coordinates":[-0.15344,52.314802],"type":"Point"}
}
