{
  "type": "Feature",
  "properties": {
    "iso:country":"GB",
    "wof:name":"TR12 6QH",
    "wof:placetype":"postalcode"
},
  "geometry": {"coordinates":[-5.07749625186093,50.06291407361872],"type":"Point"}
}