{
  "type": "Feature",
  "properties": {
    "date:inception_lower": "1990-02-01",
    "date:inception_upper": "1990-02-01",
    "iso:country": "GB",
    "wof:name": "OL15 8RU",
    "wof:placetype": "postalcode"
  },
  "geometry": {"coordinates":[-2.108332,53.645526],"type":"Point"}
}
