{
  "type": "Feature",
  "properties": {
    "iso:country": "GB",
    "wof:name": "OL15 8RU",
    "wof:placetype": "postalcode"
  },
  "geometry": {"coordinates":[-2.108332,53.645526],"type":"Point"}
}
