{
  "type": "Feature",
  "properties": {
    "iso:country":"GB",
    "wof:name":"BN1 3LR",
    "wof:placetype":"postalcode"
},
  "geometry": {"coordinates":[-0.14249497346092,50.82809607109562],"type":"Point"}
}