{
  "type": "Feature",
  "properties": {
    "iso:country": "GB",
    "wof:name": "TS15 9LA",
    "wof:placetype": "postalcode"
  },
  "geometry": {"coordinates":[-1.280505,54.495113],"type":"Point"}
}
