{
  "type": "Feature",
  "properties": {
    "iso:country":"GB",
    "wof:name":"TS15 9LA",
    "wof:placetype":"postalcode"
},
  "geometry": {"coordinates":[-1.28050494061604,54.49511337134231],"type":"Point"}
}