{
  "type": "Feature",
  "properties": {
    "iso:country": "GB",
    "wof:name": "CV7 7FR",
    "wof:placetype": "postalcode"
  },
  "geometry": {"coordinates":[-1.658601,52.385569],"type":"Point"}
}
