{
  "type": "Feature",
  "properties": {
    "iso:country":"GB",
    "wof:name":"CV7 7FR",
    "wof:placetype":"postalcode"
},
  "geometry": {"coordinates":[-1.65860060923353,52.38556916558883],"type":"Point"}
}