{
  "type": "Feature",
  "properties": {
    "iso:country":"GB",
    "wof:name":"M20 2SP",
    "wof:placetype":"postalcode"
},
  "geometry": {"coordinates":[-2.22889415325871,53.4080172934561],"type":"Point"}
}