{
  "type": "Feature",
  "properties": {
    "date:inception_lower": "1999-06-01",
    "date:inception_upper": "1999-06-01",
    "iso:country": "GB",
    "wof:name": "TN6 2JN",
    "wof:placetype": "postalcode"
  },
  "geometry": {"coordinates":[0.166556,51.050087],"type":"Point"}
}
