{
  "type": "Feature",
  "properties": {
    "iso:country":"GB",
    "wof:name":"TN6 2JN",
    "wof:placetype":"postalcode"
},
  "geometry": {"coordinates":[0.1665280161322,51.05008981528538],"type":"Point"}
}