{
  "type": "Feature",
  "properties": {
    "iso:country":"GB",
    "wof:name":"EH7 5SY",
    "wof:placetype":"postalcode"
},
  "geometry": {"coordinates":[-3.16588574618501,55.9566212970243],"type":"Point"}
}