{
  "type": "Feature",
  "properties": {
    "iso:country":"GB",
    "wof:name":"B21 8EP",
    "wof:placetype":"postalcode"
},
  "geometry": {"coordinates":[-1.93999662169238,52.5148640667318],"type":"Point"}
}