{
  "type": "Feature",
  "properties": {
    "date:inception_lower": "2004-01-01",
    "date:inception_upper": "2004-01-01",
    "iso:country": "GB",
    "wof:name": "G15 7EJ",
    "wof:placetype": "postalcode"
  },
  "geometry": {"coordinates":[-4.365173,55.913299],"type":"Point"}
}
