{
  "type": "Feature",
  "properties": {
    "date:inception_lower": "1980-01-01",
    "date:inception_upper": "1980-01-01",
    "iso:country": "GB",
    "wof:name": "HP15 7QB",
    "wof:placetype": "postalcode"
  },
  "geometry": {"coordinates":[-0.718213,51.650304],"type":"Point"}
}
