{
  "type": "Feature",
  "properties": {
    "iso:country":"GB",
    "wof:name":"HP15 7QB",
    "wof:placetype":"postalcode"
},
  "geometry": {"coordinates":[-0.71821270930214,51.65030432006996],"type":"Point"}
}