{
  "type": "Feature",
  "properties": {
    "iso:country":"GB",
    "wof:name":"RM12 4AU",
    "wof:placetype":"postalcode"
},
  "geometry": {"coordinates":[0.19274575076092,51.54958695274597],"type":"Point"}
}