{
  "type": "Feature",
  "properties": {
    "date:inception_lower":"2010-11-01",
    "date:inception_upper":"2010-11-30",
    "iso:country":"GB",
    "wof:name":"L22 0QH",
    "wof:placetype":"postalcode"
},
  "geometry": {"coordinates":[-3.021595,53.47466],"type":"Point"}
}