{
  "type": "Feature",
  "properties": {
    "iso:country": "GB",
    "wof:name": "L22 0QH",
    "wof:placetype": "postalcode"
  },
  "geometry": {"coordinates":[-3.021595,53.47466],"type":"Point"}
}
