{
  "type": "Feature",
  "properties": {
    "iso:country":"GB",
    "wof:name":"L22 0QH",
    "wof:placetype":"postalcode"
},
  "geometry": {"coordinates":[-3.02158012831681,53.47459894446639],"type":"Point"}
}