{
  "type": "Feature",
  "properties": {
    "iso:country": "GB",
    "wof:name": "CB8 0XA",
    "wof:placetype": "postalcode"
  },
  "geometry": {"coordinates":[0.319237,52.224538],"type":"Point"}
}
