{
  "type": "Feature",
  "properties": {
    "iso:country":"GB",
    "wof:name":"CB8 0XA",
    "wof:placetype":"postalcode"
},
  "geometry": {"coordinates":[0.32215249613134,52.22313496431658],"type":"Point"}
}