{
  "type": "Feature",
  "properties": {
    "iso:country":"GB",
    "wof:name":"LL12 7HD",
    "wof:placetype":"postalcode"
},
  "geometry": {"coordinates":[-2.98900413973599,53.05620381863811],"type":"Point"}
}