{
  "type": "Feature",
  "properties": {
    "iso:country":"GB",
    "wof:name":"L12 0BJ",
    "wof:placetype":"postalcode"
},
  "geometry": {"coordinates":[-2.87313919505845,53.4524052821337],"type":"Point"}
}