{
  "type": "Feature",
  "properties": {
    "iso:country": "GB",
    "wof:name": "DY3 2NS",
    "wof:placetype": "postalcode"
  },
  "geometry": {"coordinates":[-2.126359,52.516552],"type":"Point"}
}
