{
  "type": "Feature",
  "properties": {
    "iso:country": "GB",
    "wof:name": "RH12 1FF",
    "wof:placetype": "postalcode"
  },
  "geometry": {"coordinates":[-0.354402,51.057845],"type":"Point"}
}
