{
  "type": "Feature",
  "properties": {
    "date:inception_lower": "2018-09-01",
    "date:inception_upper": "2018-09-01",
    "iso:country": "GB",
    "wof:name": "RH12 1FF",
    "wof:placetype": "postalcode"
  },
  "geometry": {"coordinates":[-0.352921,51.058148],"type":"Point"}
}
