{
  "type": "Feature",
  "properties": {
    "iso:country":"GB",
    "wof:name":"LN6 5UR",
    "wof:placetype":"postalcode"
},
  "geometry": {"coordinates":[-0.61377911666047,53.23611873557871],"type":"Point"}
}