{
  "type": "Feature",
  "properties": {
    "iso:country":"GB",
    "wof:name":"HP21 9HD",
    "wof:placetype":"postalcode"
},
  "geometry": {"coordinates":[-0.80508201854494,51.80307877852327],"type":"Point"}
}