{
  "type": "Feature",
  "properties": {
    "date:inception_lower":"2010-12-01",
    "date:inception_upper":"2010-12-31",
    "iso:country":"GB",
    "wof:name":"HP21 9HD",
    "wof:placetype":"postalcode"
},
  "geometry": {"coordinates":[-0.805082,51.803079],"type":"Point"}
}