{
  "type": "Feature",
  "properties": {
    "iso:country": "GB",
    "wof:name": "HP21 9HD",
    "wof:placetype": "postalcode"
  },
  "geometry": {"coordinates":[-0.805082,51.803079],"type":"Point"}
}
