{
  "type": "Feature",
  "properties": {
    "iso:country": "GB",
    "wof:name": "TA8 1LQ",
    "wof:placetype": "postalcode"
  },
  "geometry": {"coordinates":[-2.994392,51.234864],"type":"Point"}
}
