{
  "type": "Feature",
  "properties": {
    "iso:country": "GB",
    "wof:name": "TD11 3TS",
    "wof:placetype": "postalcode"
  },
  "geometry": {"coordinates":[-2.370837,55.821523],"type":"Point"}
}
