{
  "type": "Feature",
  "properties": {
    "iso:country":"GB",
    "wof:name":"TD11 3TS",
    "wof:placetype":"postalcode"
},
  "geometry": {"coordinates":[-2.37083713763756,55.82152271857373],"type":"Point"}
}