{
  "type": "Feature",
  "properties": {
    "iso:country":"GB",
    "wof:name":"CV9 1BJ",
    "wof:placetype":"postalcode"
},
  "geometry": {"coordinates":[-1.55204829910911,52.57999151935493],"type":"Point"}
}