{
  "type": "Feature",
  "properties": {
    "date:inception_lower": "2022-11-01",
    "date:inception_upper": "2022-11-01",
    "iso:country": "GB",
    "wof:name": "CV13 0BJ",
    "wof:placetype": "postalcode"
  },
  "geometry": {"coordinates":[-1.363596,52.64836],"type":"Point"}
}
