{
  "type": "Feature",
  "properties": {
    "iso:country":"GB",
    "wof:name":"NE61 5NW",
    "wof:placetype":"postalcode"
},
  "geometry": {"coordinates":[-1.6150935035412,55.23599858261382],"type":"Point"}
}