{
  "type": "Feature",
  "properties": {
    "iso:country": "GB",
    "wof:name": "NE61 5NW",
    "wof:placetype": "postalcode"
  },
  "geometry": {"coordinates":[-1.615093,55.235999],"type":"Point"}
}
