{
  "type": "Feature",
  "properties": {
    "iso:country":"GB",
    "wof:name":"DA15 9LT",
    "wof:placetype":"postalcode"
},
  "geometry": {"coordinates":[0.10469482246003,51.44938302588646],"type":"Point"}
}