{
  "type": "Feature",
  "properties": {
    "iso:country": "GB",
    "wof:name": "NR13 5AJ",
    "wof:placetype": "postalcode"
  },
  "geometry": {"coordinates":[1.369773,52.650082],"type":"Point"}
}
