{
  "type": "Feature",
  "properties": {
    "iso:country":"GB",
    "wof:name":"NR13 5AJ",
    "wof:placetype":"postalcode"
},
  "geometry": {"coordinates":[1.36977282951943,52.65008224495328],"type":"Point"}
}