{
  "type": "Feature",
  "properties": {
    "iso:country":"GB",
    "wof:name":"BB8 0DD",
    "wof:placetype":"postalcode"
},
  "geometry": {"coordinates":[-2.17781301726677,53.85421670758698],"type":"Point"}
}