{
  "type": "Feature",
  "properties": {
    "date:inception_lower": "2019-07-01",
    "date:inception_upper": "2019-07-01",
    "iso:country": "GB",
    "wof:name": "S60 9ZS",
    "wof:placetype": "postalcode"
  },
  "geometry": {"coordinates":[-1.357404,53.434708],"type":"Point"}
}
