{
  "type": "Feature",
  "properties": {
    "iso:country":"GB",
    "wof:name":"SA5 9JS",
    "wof:placetype":"postalcode"
},
  "geometry": {"coordinates":[-3.94561946924099,51.64166773563253],"type":"Point"}
}