{
  "type": "Feature",
  "properties": {
    "date:inception_lower": "1997-12-01",
    "date:inception_upper": "1997-12-01",
    "iso:country": "GB",
    "wof:name": "BS34 8SS",
    "wof:placetype": "postalcode"
  },
  "geometry": {"coordinates":[-2.553104,51.508147],"type":"Point"}
}
