{
  "type": "Feature",
  "properties": {
    "iso:country":"GB",
    "wof:name":"BS34 8SS",
    "wof:placetype":"postalcode"
},
  "geometry": {"coordinates":[-2.5531043033162,51.50814668702871],"type":"Point"}
}