{
  "type": "Feature",
  "properties": {
    "iso:country": "GB",
    "wof:name": "NE61 5BQ",
    "wof:placetype": "postalcode"
  },
  "geometry": {"coordinates":[-1.560594,55.219941],"type":"Point"}
}
