{
  "type": "Feature",
  "properties": {
    "date:inception_lower": "2018-01-01",
    "date:inception_upper": "2018-01-01",
    "iso:country": "GB",
    "wof:name": "NE61 5BQ",
    "wof:placetype": "postalcode"
  },
  "geometry": {"coordinates":[-1.560254,55.219472],"type":"Point"}
}
