{
  "type": "Feature",
  "properties": {
    "iso:country": "GB",
    "wof:name": "LL28 5EQ",
    "wof:placetype": "postalcode"
  },
  "geometry": {"coordinates":[-3.791738,53.266189],"type":"Point"}
}
