{
  "type": "Feature",
  "properties": {
    "iso:country":"GB",
    "wof:name":"LL28 5EQ",
    "wof:placetype":"postalcode"
},
  "geometry": {"coordinates":[-3.79173771261552,53.26618851850051],"type":"Point"}
}