{
  "type": "Feature",
  "properties": {
    "iso:country":"GB",
    "wof:name":"S61 2BW",
    "wof:placetype":"postalcode"
},
  "geometry": {"coordinates":[-1.40700355766195,53.44090511239972],"type":"Point"}
}