{
  "type": "Feature",
  "properties": {
    "iso:country": "GB",
    "wof:name": "M19 1GF",
    "wof:placetype": "postalcode"
  },
  "geometry": {"coordinates":[-2.202688,53.432846],"type":"Point"}
}
