{
  "type": "Feature",
  "properties": {
    "iso:country":"GB",
    "wof:name":"M19 1GF",
    "wof:placetype":"postalcode"
},
  "geometry": {"coordinates":[-2.20268777858916,53.43284611486302],"type":"Point"}
}