{
  "type": "Feature",
  "properties": {
    "iso:country":"GB",
    "wof:name":"NG8 5RA",
    "wof:placetype":"postalcode"
},
  "geometry": {"coordinates":[-1.20782265513973,52.97447540070972],"type":"Point"}
}