{
  "type": "Feature",
  "properties": {
    "date:inception_lower": "1980-01-01",
    "date:inception_upper": "1980-01-01",
    "iso:country": "GB",
    "wof:name": "NG8 5RA",
    "wof:placetype": "postalcode"
  },
  "geometry": {"coordinates":[-1.207444,52.974699],"type":"Point"}
}
