{
  "type": "Feature",
  "properties": {
    "iso:country":"GB",
    "wof:name":"MK45 5NA",
    "wof:placetype":"postalcode"
},
  "geometry": {"coordinates":[-0.50466976536198,51.9830709368309],"type":"Point"}
}