{
  "type": "Feature",
  "properties": {
    "date:inception_lower": "2000-12-01",
    "date:inception_upper": "2000-12-01",
    "iso:country": "GB",
    "wof:name": "MK45 5NA",
    "wof:placetype": "postalcode"
  },
  "geometry": {"coordinates":[-0.50467,51.983071],"type":"Point"}
}
