{
  "type": "Feature",
  "properties": {
    "iso:country":"GB",
    "wof:name":"RM15 5EL",
    "wof:placetype":"postalcode"
},
  "geometry": {"coordinates":[0.28133146953757,51.51193444567587],"type":"Point"}
}