{
  "type": "Feature",
  "properties": {
    "iso:country":"GB",
    "wof:name":"ME17 4NJ",
    "wof:placetype":"postalcode"
},
  "geometry": {"coordinates":[0.53797230477156,51.23672624446534],"type":"Point"}
}