{
  "type": "Feature",
  "properties": {
    "iso:country":"GB",
    "wof:name":"KT24 5HX",
    "wof:placetype":"postalcode"
},
  "geometry": {"coordinates":[-0.42005588350285,51.29178261649985],"type":"Point"}
}