{
  "type": "Feature",
  "properties": {
    "iso:country":"GB",
    "wof:name":"CM15 9NA",
    "wof:placetype":"postalcode"
},
  "geometry": {"coordinates":[0.28937777701541,51.63779620813694],"type":"Point"}
}