{
  "type": "Feature",
  "properties": {
    "iso:country":"GB",
    "wof:name":"EX4 1RN",
    "wof:placetype":"postalcode"
},
  "geometry": {"coordinates":[-3.55839275859267,50.71780353237452],"type":"Point"}
}