{
  "type": "Feature",
  "properties": {
    "iso:country": "GB",
    "wof:name": "BS24 9PD",
    "wof:placetype": "postalcode"
  },
  "geometry": {"coordinates":[-2.952829,51.321651],"type":"Point"}
}
