{
  "type": "Feature",
  "properties": {
    "date:inception_lower": "1986-07-01",
    "date:inception_upper": "1986-07-01",
    "iso:country": "GB",
    "wof:name": "BS24 9PD",
    "wof:placetype": "postalcode"
  },
  "geometry": {"coordinates":[-2.952829,51.321651],"type":"Point"}
}
