{
  "type": "Feature",
  "properties": {
    "iso:country":"GB",
    "wof:name":"BN42 4FR",
    "wof:placetype":"postalcode"
},
  "geometry": {"coordinates":[-0.23737152461266,50.83505396370522],"type":"Point"}
}