{
  "type": "Feature",
  "properties": {
    "iso:country":"GB",
    "wof:name":"N10 2DG",
    "wof:placetype":"postalcode"
},
  "geometry": {"coordinates":[-0.14071578222341,51.59812263718361],"type":"Point"}
}