{
  "type": "Feature",
  "properties": {
    "date:inception_lower": "1990-02-01",
    "date:inception_upper": "1990-02-01",
    "iso:country": "GB",
    "wof:name": "DN15 8EQ",
    "wof:placetype": "postalcode"
  },
  "geometry": {"coordinates":[-0.676718,53.600835],"type":"Point"}
}
