{
  "type": "Feature",
  "properties": {
    "iso:country":"GB",
    "wof:name":"CF81 9FE",
    "wof:placetype":"postalcode"
},
  "geometry": {"coordinates":[-3.2198151505566,51.6918708705298],"type":"Point"}
}