{
  "type": "Feature",
  "properties": {
    "iso:country":"GB",
    "wof:name":"RM14 1DE",
    "wof:placetype":"postalcode"
},
  "geometry": {"coordinates":[0.25283735092644,51.55980636091041],"type":"Point"}
}