{
  "type": "Feature",
  "properties": {
    "iso:country":"GB",
    "wof:name":"OX3 9TY",
    "wof:placetype":"postalcode"
},
  "geometry": {"coordinates":[-1.18140286077157,51.78653720833216],"type":"Point"}
}