{
  "type": "Feature",
  "properties": {
    "iso:country":"GB",
    "wof:name":"NN11 3BP",
    "wof:placetype":"postalcode"
},
  "geometry": {"coordinates":[-1.14628723929008,52.21939862620557],"type":"Point"}
}