{
  "type": "Feature",
  "properties": {
    "date:inception_lower":"1993-08-01",
    "date:inception_upper":"1993-08-31",
    "iso:country":"GB",
    "wof:name":"NN11 3BP",
    "wof:placetype":"postalcode"
},
  "geometry": {"coordinates":[-1.146272,52.219413],"type":"Point"}
}