{
  "type": "Feature",
  "properties": {
    "iso:country": "GB",
    "wof:name": "NN11 3BP",
    "wof:placetype": "postalcode"
  },
  "geometry": {"coordinates":[-1.146272,52.219413],"type":"Point"}
}
