{
  "type": "Feature",
  "properties": {
    "iso:country":"GB",
    "wof:name":"LE7 7PB",
    "wof:placetype":"postalcode"
},
  "geometry": {"coordinates":[-1.13924424301059,52.71015174031098],"type":"Point"}
}