{
  "type": "Feature",
  "properties": {
    "date:inception_lower":"1980-01-01",
    "date:inception_upper":"1980-01-31",
    "iso:country":"GB",
    "wof:name":"LE7 7PB",
    "wof:placetype":"postalcode"
},
  "geometry": {"coordinates":[-1.139244,52.710152],"type":"Point"}
}