{
  "type": "Feature",
  "properties": {
    "iso:country":"GB",
    "wof:name":"BS3 1RZ",
    "wof:placetype":"postalcode"
},
  "geometry": {"coordinates":[-2.61806914686901,51.44389182923086],"type":"Point"}
}