{
  "type": "Feature",
  "properties": {
    "iso:country":"GB",
    "wof:name":"N21 2DS",
    "wof:placetype":"postalcode"
},
  "geometry": {"coordinates":[-0.08264945814503,51.6377083146286],"type":"Point"}
}