{
  "type": "Feature",
  "properties": {
    "date:inception_lower": "1980-01-01",
    "date:inception_upper": "1980-01-01",
    "iso:country": "GB",
    "wof:name": "N21 2DS",
    "wof:placetype": "postalcode"
  },
  "geometry": {"coordinates":[-0.082649,51.637708],"type":"Point"}
}
