{
  "type": "Feature",
  "properties": {
    "iso:country":"GB",
    "wof:name":"PL15 9EW",
    "wof:placetype":"postalcode"
},
  "geometry": {"coordinates":[-4.35647196563596,50.63728261704258],"type":"Point"}
}