{
  "type": "Feature",
  "properties": {
    "iso:country":"GB",
    "wof:name":"SY16 2BU",
    "wof:placetype":"postalcode"
},
  "geometry": {"coordinates":[-3.31545945052684,52.51776025239672],"type":"Point"}
}