{
  "type": "Feature",
  "properties": {
    "date:inception_lower": "1980-01-01",
    "date:inception_upper": "1980-01-01",
    "iso:country": "GB",
    "wof:name": "SY16 2BU",
    "wof:placetype": "postalcode"
  },
  "geometry": {"coordinates":[-3.315459,52.51776],"type":"Point"}
}
