{
  "type": "Feature",
  "properties": {
    "iso:country":"GB",
    "wof:name":"SW3 5SD",
    "wof:placetype":"postalcode"
},
  "geometry": {"coordinates":[-0.16634146864439,51.48627318853357],"type":"Point"}
}