{
  "type": "Feature",
  "properties": {
    "iso:country":"GB",
    "wof:name":"N14 4RU",
    "wof:placetype":"postalcode"
},
  "geometry": {"coordinates":[-0.12852313903388,51.64111023666259],"type":"Point"}
}