{
  "type": "Feature",
  "properties": {
    "iso:country": "GB",
    "wof:name": "N14 4RU",
    "wof:placetype": "postalcode"
  },
  "geometry": {"coordinates":[-0.128523,51.64111],"type":"Point"}
}
