{
  "type": "Feature",
  "properties": {
    "date:inception_lower": "1980-01-01",
    "date:inception_upper": "1980-01-01",
    "iso:country": "GB",
    "wof:name": "SY16 3LN",
    "wof:placetype": "postalcode"
  },
  "geometry": {"coordinates":[-3.335765,52.544369],"type":"Point"}
}
