{
  "type": "Feature",
  "properties": {
    "iso:country": "GB",
    "wof:name": "HP4 9DR",
    "wof:placetype": "postalcode"
  },
  "geometry": {"coordinates":[-0.569452,51.762241],"type":"Point"}
}
