{
  "type": "Feature",
  "properties": {
    "date:inception_lower": "1980-01-01",
    "date:inception_upper": "1980-01-01",
    "iso:country": "GB",
    "wof:name": "TQ7 2NZ",
    "wof:placetype": "postalcode"
  },
  "geometry": {"coordinates":[-3.717715,50.270354],"type":"Point"}
}
