{
  "type": "Feature",
  "properties": {
    "iso:country": "GB",
    "wof:name": "TQ7 2NZ",
    "wof:placetype": "postalcode"
  },
  "geometry": {"coordinates":[-3.717715,50.270354],"type":"Point"}
}
