{
  "type": "Feature",
  "properties": {
    "iso:country":"GB",
    "wof:name":"DA15 7LF",
    "wof:placetype":"postalcode"
},
  "geometry": {"coordinates":[0.09427411432719,51.43269901646207],"type":"Point"}
}