{
  "type": "Feature",
  "properties": {
    "iso:country": "GB",
    "wof:name": "DA15 7LF",
    "wof:placetype": "postalcode"
  },
  "geometry": {"coordinates":[0.094274,51.432699],"type":"Point"}
}
