{
  "type": "Feature",
  "properties": {
    "iso:country": "GB",
    "wof:name": "CH63 0LQ",
    "wof:placetype": "postalcode"
  },
  "geometry": {"coordinates":[-2.987466,53.319916],"type":"Point"}
}
