{
  "type": "Feature",
  "properties": {
    "iso:country": "GB",
    "wof:name": "IP7 5PF",
    "wof:placetype": "postalcode"
  },
  "geometry": {"coordinates":[0.943355,52.03777],"type":"Point"}
}
