{
  "type": "Feature",
  "properties": {
    "date:inception_lower": "1980-01-01",
    "date:inception_upper": "1980-01-01",
    "iso:country": "GB",
    "wof:name": "IP7 5PF",
    "wof:placetype": "postalcode"
  },
  "geometry": {"coordinates":[0.943791,52.03731],"type":"Point"}
}
