{
  "type": "Feature",
  "properties": {
    "iso:country":"GB",
    "wof:name":"IP7 5PF",
    "wof:placetype":"postalcode"
},
  "geometry": {"coordinates":[0.94332383240965,52.03775702071828],"type":"Point"}
}