{
  "type": "Feature",
  "properties": {
    "date:inception_lower": "1980-01-01",
    "date:inception_upper": "1980-01-01",
    "iso:country": "GB",
    "wof:name": "HG4 5EB",
    "wof:placetype": "postalcode"
  },
  "geometry": {"coordinates":[-1.505707,54.155298],"type":"Point"}
}
