{
  "type": "Feature",
  "properties": {
    "date:inception_lower": "1980-01-01",
    "date:inception_upper": "1980-01-01",
    "iso:country": "GB",
    "wof:name": "DH6 1JQ",
    "wof:placetype": "postalcode"
  },
  "geometry": {"coordinates":[-1.5084,54.780426],"type":"Point"}
}
