{
  "type": "Feature",
  "properties": {
    "iso:country": "GB",
    "wof:name": "LN4 2FU",
    "wof:placetype": "postalcode"
  },
  "geometry": {"coordinates":[-0.531962,53.198178],"type":"Point"}
}
