{
  "type": "Feature",
  "properties": {
    "date:inception_lower": "1980-01-01",
    "date:inception_upper": "1980-01-01",
    "iso:country": "GB",
    "wof:name": "M14 6RB",
    "wof:placetype": "postalcode"
  },
  "geometry": {"coordinates":[-2.216053,53.435994],"type":"Point"}
}
