{
  "type": "Feature",
  "properties": {
    "iso:country": "GB",
    "wof:name": "SA62 3PE",
    "wof:placetype": "postalcode"
  },
  "geometry": {"coordinates":[-4.992459,51.762663],"type":"Point"}
}
