{
  "type": "Feature",
  "properties": {
    "iso:country":"GB",
    "wof:name":"SO24 0AE",
    "wof:placetype":"postalcode"
},
  "geometry": {"coordinates":[-1.1355115064244,51.08474128923734],"type":"Point"}
}