{
  "type": "Feature",
  "properties": {
    "iso:country":"GB",
    "wof:name":"WA7 6QU",
    "wof:placetype":"postalcode"
},
  "geometry": {"coordinates":[-2.66786406044384,53.33554559613649],"type":"Point"}
}