{
  "type": "Feature",
  "properties": {
    "iso:country": "GB",
    "wof:name": "WA7 6QU",
    "wof:placetype": "postalcode"
  },
  "geometry": {"coordinates":[-2.667864,53.335546],"type":"Point"}
}
