{
  "type": "Feature",
  "properties": {
    "iso:country":"GB",
    "wof:name":"S10 1TD",
    "wof:placetype":"postalcode"
},
  "geometry": {"coordinates":[-1.51328824986443,53.38414557455562],"type":"Point"}
}