{
  "type": "Feature",
  "properties": {
    "date:inception_lower":"1980-01-01",
    "date:inception_upper":"1980-01-31",
    "iso:country":"GB",
    "wof:name":"TS12 3LH",
    "wof:placetype":"postalcode"
},
  "geometry": {"coordinates":[-0.945154,54.506714],"type":"Point"}
}