{
  "type": "Feature",
  "properties": {
    "iso:country":"GB",
    "wof:name":"TS12 3LH",
    "wof:placetype":"postalcode"
},
  "geometry": {"coordinates":[-0.94964524106496,54.50615549973857],"type":"Point"}
}