{
  "type": "Feature",
  "properties": {
    "iso:country": "GB",
    "wof:name": "TA5 2GP",
    "wof:placetype": "postalcode"
  },
  "geometry": {"coordinates":[-3.016936,51.113869],"type":"Point"}
}
