{
  "type": "Feature",
  "properties": {
    "date:inception_lower":"2013-09-01",
    "date:inception_upper":"2013-09-30",
    "iso:country":"GB",
    "wof:name":"TA5 2GP",
    "wof:placetype":"postalcode"
},
  "geometry": {"coordinates":[-3.016936,51.113869],"type":"Point"}
}