{
  "type": "Feature",
  "properties": {
    "iso:country": "GB",
    "wof:name": "NR6 7BT",
    "wof:placetype": "postalcode"
  },
  "geometry": {"coordinates":[1.306938,52.656826],"type":"Point"}
}
