{
  "type": "Feature",
  "properties": {
    "iso:country":"GB",
    "wof:name":"WF6 1EP",
    "wof:placetype":"postalcode"
},
  "geometry": {"coordinates":[-1.42094628868933,53.6972966934546],"type":"Point"}
}