{
  "type": "Feature",
  "properties": {
    "iso:country": "GB",
    "wof:name": "SK15 1AJ",
    "wof:placetype": "postalcode"
  },
  "geometry": {"coordinates":[-2.056293,53.485794],"type":"Point"}
}
