{
  "type": "Feature",
  "properties": {
    "iso:country": "GB",
    "wof:name": "GL2 5NA",
    "wof:placetype": "postalcode"
  },
  "geometry": {"coordinates":[-2.266675,51.853626],"type":"Point"}
}
