{
  "type": "Feature",
  "properties": {
    "date:inception_lower": "2018-11-01",
    "date:inception_upper": "2018-11-01",
    "iso:country": "GB",
    "wof:name": "GL2 5NA",
    "wof:placetype": "postalcode"
  },
  "geometry": {"coordinates":[-2.266895,51.853905],"type":"Point"}
}
