{
  "type": "Feature",
  "properties": {
    "iso:country":"GB",
    "wof:name":"G40 3RX",
    "wof:placetype":"postalcode"
},
  "geometry": {"coordinates":[-4.21645079436942,55.84917054336899],"type":"Point"}
}