{
  "type": "Feature",
  "properties": {
    "iso:country": "GB",
    "wof:name": "NP23 5AZ",
    "wof:placetype": "postalcode"
  },
  "geometry": {"coordinates":[-3.20599,51.782918],"type":"Point"}
}
