{
  "type": "Feature",
  "properties": {
    "iso:country":"GB",
    "wof:name":"AB51 4QX",
    "wof:placetype":"postalcode"
},
  "geometry": {"coordinates":[-2.38504806693176,57.28872841003043],"type":"Point"}
}