{
  "type": "Feature",
  "properties": {
    "iso:country":"GB",
    "wof:name":"TS10 3JW",
    "wof:placetype":"postalcode"
},
  "geometry": {"coordinates":[-1.06318404911215,54.61567156703583],"type":"Point"}
}