{
  "type": "Feature",
  "properties": {
    "iso:country": "GB",
    "wof:name": "TS10 3JW",
    "wof:placetype": "postalcode"
  },
  "geometry": {"coordinates":[-1.063184,54.615672],"type":"Point"}
}
