{
  "type": "Feature",
  "properties": {
    "iso:country":"GB",
    "wof:name":"B91 1UE",
    "wof:placetype":"postalcode"
},
  "geometry": {"coordinates":[-1.80620189996702,52.40609472902404],"type":"Point"}
}