{
  "type": "Feature",
  "properties": {
    "date:inception_lower": "2020-04-01",
    "date:inception_upper": "2020-04-01",
    "iso:country": "GB",
    "wof:name": "RH16 2GQ",
    "wof:placetype": "postalcode"
  },
  "geometry": {"coordinates":[-0.091625,51.017436],"type":"Point"}
}
