{
  "type": "Feature",
  "properties": {
    "iso:country":"GB",
    "wof:name":"HU17 0NU",
    "wof:placetype":"postalcode"
},
  "geometry": {"coordinates":[-0.41866800417307,53.83852072125662],"type":"Point"}
}