{
  "type": "Feature",
  "properties": {
    "iso:country":"GB",
    "wof:name":"CT16 3EN",
    "wof:placetype":"postalcode"
},
  "geometry": {"coordinates":[1.2860042427284,51.15840956178388],"type":"Point"}
}