{
  "type": "Feature",
  "properties": {
    "iso:country":"GB",
    "wof:name":"BD6 2JJ",
    "wof:placetype":"postalcode"
},
  "geometry": {"coordinates":[-1.79303933650763,53.7631947273313],"type":"Point"}
}