{
  "type": "Feature",
  "properties": {
    "date:inception_lower":"2015-08-01",
    "date:inception_upper":"2015-08-31",
    "iso:country":"GB",
    "wof:name":"SE1 0HT",
    "wof:placetype":"postalcode"
},
  "geometry": {"coordinates":[-0.09759,51.50435],"type":"Point"}
}