{
  "type": "Feature",
  "properties": {
    "iso:country":"GB",
    "wof:name":"SE1 0HT",
    "wof:placetype":"postalcode"
},
  "geometry": {"coordinates":[-0.09758986009523,51.50435012640591],"type":"Point"}
}