{
  "type": "Feature",
  "properties": {
    "iso:country": "GB",
    "wof:name": "TQ1 1QS",
    "wof:placetype": "postalcode"
  },
  "geometry": {"coordinates":[-3.515014,50.466486],"type":"Point"}
}
