{
  "type": "Feature",
  "properties": {
    "iso:country":"GB",
    "wof:name":"TQ1 1QS",
    "wof:placetype":"postalcode"
},
  "geometry": {"coordinates":[-3.51501439445947,50.46648617717234],"type":"Point"}
}