{
  "type": "Feature",
  "properties": {
    "iso:country": "GB",
    "wof:name": "PE19 8HT",
    "wof:placetype": "postalcode"
  },
  "geometry": {"coordinates":[-0.287044,52.219263],"type":"Point"}
}
