{
  "type": "Feature",
  "properties": {
    "iso:country":"GB",
    "wof:name":"RH12 3DE",
    "wof:placetype":"postalcode"
},
  "geometry": {"coordinates":[-0.44290851335645,51.09970013104302],"type":"Point"}
}