{
  "type": "Feature",
  "properties": {
    "date:inception_lower":"1990-07-01",
    "date:inception_upper":"1990-07-31",
    "iso:country":"GB",
    "wof:name":"NG18 4TW",
    "wof:placetype":"postalcode"
},
  "geometry": {"coordinates":[-1.187373,53.127713],"type":"Point"}
}