{
  "type": "Feature",
  "properties": {
    "iso:country":"GB",
    "wof:name":"NG18 4TW",
    "wof:placetype":"postalcode"
},
  "geometry": {"coordinates":[-1.1873734401035,53.1277134808645],"type":"Point"}
}