{
  "type": "Feature",
  "properties": {
    "date:inception_lower":"1980-01-01",
    "date:inception_upper":"1980-01-31",
    "iso:country":"GB",
    "wof:name":"CH2 4HU",
    "wof:placetype":"postalcode"
},
  "geometry": {"coordinates":[-2.838283,53.265884],"type":"Point"}
}