{
  "type": "Feature",
  "properties": {
    "iso:country":"GB",
    "wof:name":"CH2 4HU",
    "wof:placetype":"postalcode"
},
  "geometry": {"coordinates":[-2.83806077228351,53.26602914299869],"type":"Point"}
}