{
  "type": "Feature",
  "properties": {
    "iso:country": "GB",
    "wof:name": "CH2 4HU",
    "wof:placetype": "postalcode"
  },
  "geometry": {"coordinates":[-2.838283,53.265884],"type":"Point"}
}
