{
  "type": "Feature",
  "properties": {
    "iso:country": "GB",
    "wof:name": "BN2 4FN",
    "wof:placetype": "postalcode"
  },
  "geometry": {"coordinates":[-0.113385,50.838677],"type":"Point"}
}
