{
  "type": "Feature",
  "properties": {
    "iso:country":"GB",
    "wof:name":"BN2 4FN",
    "wof:placetype":"postalcode"
},
  "geometry": {"coordinates":[-0.11341278829923,50.83868239752834],"type":"Point"}
}