{
  "type": "Feature",
  "properties": {
    "iso:country":"GB",
    "wof:name":"SE1 4JF",
    "wof:placetype":"postalcode"
},
  "geometry": {"coordinates":[-0.0915086263786,51.49815435305808],"type":"Point"}
}