{
  "type": "Feature",
  "properties": {
    "date:inception_lower": "2008-05-01",
    "date:inception_upper": "2008-05-01",
    "iso:country": "GB",
    "wof:name": "CF24 1AD",
    "wof:placetype": "postalcode"
  },
  "geometry": {"coordinates":[-3.155349,51.488537],"type":"Point"}
}
