{
  "type": "Feature",
  "properties": {
    "iso:country":"GB",
    "wof:name":"CF24 1AD",
    "wof:placetype":"postalcode"
},
  "geometry": {"coordinates":[-3.15546923844981,51.48848999637967],"type":"Point"}
}