{
  "type": "Feature",
  "properties": {
    "iso:country":"GB",
    "wof:name":"LL12 7UE",
    "wof:placetype":"postalcode"
},
  "geometry": {"coordinates":[-2.97158011061462,53.06362885990637],"type":"Point"}
}