{
  "type": "Feature",
  "properties": {
    "iso:country":"GB",
    "wof:name":"DY13 0LT",
    "wof:placetype":"postalcode"
},
  "geometry": {"coordinates":[-2.29496991317531,52.33046607315229],"type":"Point"}
}