{
  "type": "Feature",
  "properties": {
    "date:inception_lower":"1995-12-01",
    "date:inception_upper":"1995-12-31",
    "iso:country":"GB",
    "wof:name":"CF83 1SH",
    "wof:placetype":"postalcode"
},
  "geometry": {"coordinates":[-3.243875,51.569358],"type":"Point"}
}