{
  "type": "Feature",
  "properties": {
    "iso:country":"GB",
    "wof:name":"CF83 1SH",
    "wof:placetype":"postalcode"
},
  "geometry": {"coordinates":[-3.24387508395077,51.56935772754012],"type":"Point"}
}