{
  "type": "Feature",
  "properties": {
    "iso:country":"GB",
    "wof:name":"L23 8TN",
    "wof:placetype":"postalcode"
},
  "geometry": {"coordinates":[-3.04138576061203,53.48968204505835],"type":"Point"}
}