{
  "type": "Feature",
  "properties": {
    "iso:country": "GB",
    "wof:name": "L23 8TN",
    "wof:placetype": "postalcode"
  },
  "geometry": {"coordinates":[-3.041386,53.489682],"type":"Point"}
}
