{
  "type": "Feature",
  "properties": {
    "iso:country": "GB",
    "wof:name": "PO33 2UB",
    "wof:placetype": "postalcode"
  },
  "geometry": {"coordinates":[-1.168412,50.722064],"type":"Point"}
}
