{
  "type": "Feature",
  "properties": {
    "iso:country":"GB",
    "wof:name":"PO33 2UB",
    "wof:placetype":"postalcode"
},
  "geometry": {"coordinates":[-1.16846504593044,50.72206673331342],"type":"Point"}
}