{
  "type": "Feature",
  "properties": {
    "iso:country":"GB",
    "wof:name":"BS10 6EH",
    "wof:placetype":"postalcode"
},
  "geometry": {"coordinates":[-2.59692556766912,51.50733833669229],"type":"Point"}
}