{
  "type": "Feature",
  "properties": {
    "date:inception_lower": "2024-01-01",
    "date:inception_upper": "2024-01-01",
    "iso:country": "GB",
    "wof:name": "DT11 9QQ",
    "wof:placetype": "postalcode"
  },
  "geometry": {"coordinates":[-2.14665,50.839926],"type":"Point"}
}
