{
  "type": "Feature",
  "properties": {
    "iso:country": "GB",
    "wof:name": "LL11 3SU",
    "wof:placetype": "postalcode"
  },
  "geometry": {"coordinates":[-3.071388,53.052308],"type":"Point"}
}
