{
  "type": "Feature",
  "properties": {
    "iso:country":"GB",
    "wof:name":"LL11 3SU",
    "wof:placetype":"postalcode"
},
  "geometry": {"coordinates":[-3.07138764103561,53.05230799097098],"type":"Point"}
}