{
  "type": "Feature",
  "properties": {
    "date:inception_lower": "1980-01-01",
    "date:inception_upper": "1980-01-01",
    "iso:country": "GB",
    "wof:name": "LL11 3SU",
    "wof:placetype": "postalcode"
  },
  "geometry": {"coordinates":[-3.071388,53.052308],"type":"Point"}
}
