{
  "type": "Feature",
  "properties": {
    "iso:country":"GB",
    "wof:name":"UB10 9BJ",
    "wof:placetype":"postalcode"
},
  "geometry": {"coordinates":[-0.44273823992404,51.54886220755591],"type":"Point"}
}