{
  "type": "Feature",
  "properties": {
    "iso:country":"GB",
    "wof:name":"CO12 3JQ",
    "wof:placetype":"postalcode"
},
  "geometry": {"coordinates":[1.28350780442024,51.94094038486946],"type":"Point"}
}