{
  "type": "Feature",
  "properties": {
    "iso:country":"GB",
    "wof:name":"M22 8HN",
    "wof:placetype":"postalcode"
},
  "geometry": {"coordinates":[-2.26759974929804,53.38900678566717],"type":"Point"}
}