{
  "type": "Feature",
  "properties": {
    "iso:country":"GB",
    "wof:name":"LE2 7SZ",
    "wof:placetype":"postalcode"
},
  "geometry": {"coordinates":[-1.13439008481439,52.6157848863519],"type":"Point"}
}