{
  "type": "Feature",
  "properties": {
    "iso:country": "GB",
    "wof:name": "PR2 6QN",
    "wof:placetype": "postalcode"
  },
  "geometry": {"coordinates":[-2.662531,53.775056],"type":"Point"}
}
