{
  "type": "Feature",
  "properties": {
    "iso:country":"GB",
    "wof:name":"EN7 6EB",
    "wof:placetype":"postalcode"
},
  "geometry": {"coordinates":[-0.05916779736054,51.70768789252233],"type":"Point"}
}