{
  "type": "Feature",
  "properties": {
    "date:inception_lower": "1980-01-01",
    "date:inception_upper": "1980-01-01",
    "iso:country": "GB",
    "wof:name": "NN11 6XZ",
    "wof:placetype": "postalcode"
  },
  "geometry": {"coordinates":[-1.296407,52.165277],"type":"Point"}
}
