{
  "type": "Feature",
  "properties": {
    "iso:country": "GB",
    "wof:name": "LE11 1DH",
    "wof:placetype": "postalcode"
  },
  "geometry": {"coordinates":[-1.198523,52.770898],"type":"Point"}
}
