{
  "type": "Feature",
  "properties": {
    "date:inception_lower": "1986-04-01",
    "date:inception_upper": "1986-04-01",
    "iso:country": "GB",
    "wof:name": "LE11 1DH",
    "wof:placetype": "postalcode"
  },
  "geometry": {"coordinates":[-1.198523,52.770898],"type":"Point"}
}
