{
  "type": "Feature",
  "properties": {
    "iso:country":"GB",
    "wof:name":"WV4 6DJ",
    "wof:placetype":"postalcode"
},
  "geometry": {"coordinates":[-2.10361002033736,52.55959414447761],"type":"Point"}
}