{
  "type": "Feature",
  "properties": {
    "iso:country":"GB",
    "wof:name":"NW10 5HP",
    "wof:placetype":"postalcode"
},
  "geometry": {"coordinates":[-0.22310802902831,51.53472597353411],"type":"Point"}
}