{
  "type": "Feature",
  "properties": {
    "iso:country":"GB",
    "wof:name":"DD9 7QS",
    "wof:placetype":"postalcode"
},
  "geometry": {"coordinates":[-2.66316760658518,56.74055770447973],"type":"Point"}
}