{
  "type": "Feature",
  "properties": {
    "iso:country": "GB",
    "wof:name": "DD9 7QS",
    "wof:placetype": "postalcode"
  },
  "geometry": {"coordinates":[-2.662906,56.740189],"type":"Point"}
}
