{
  "type": "Feature",
  "properties": {
    "iso:country": "GB",
    "wof:name": "BH5 1LY",
    "wof:placetype": "postalcode"
  },
  "geometry": {"coordinates":[-1.831912,50.724729],"type":"Point"}
}
