{
  "type": "Feature",
  "properties": {
    "iso:country":"GB",
    "wof:name":"BH5 1LY",
    "wof:placetype":"postalcode"
},
  "geometry": {"coordinates":[-1.83191174438929,50.72472928600462],"type":"Point"}
}