{
  "type": "Feature",
  "properties": {
    "iso:country":"GB",
    "wof:name":"CT14 9LL",
    "wof:placetype":"postalcode"
},
  "geometry": {"coordinates":[1.36673644604611,51.21586712106597],"type":"Point"}
}