{
  "type": "Feature",
  "properties": {
    "iso:country":"GB",
    "wof:name":"B12 0TS",
    "wof:placetype":"postalcode"
},
  "geometry": {"coordinates":[-1.88515154220891,52.46899294090924],"type":"Point"}
}