{
  "type": "Feature",
  "properties": {
    "iso:country": "GB",
    "wof:name": "NP19 0HG",
    "wof:placetype": "postalcode"
  },
  "geometry": {"coordinates":[-2.969303,51.582919],"type":"Point"}
}
