{
  "type": "Feature",
  "properties": {
    "iso:country":"GB",
    "wof:name":"CR0 4DH",
    "wof:placetype":"postalcode"
},
  "geometry": {"coordinates":[-0.1088947116047,51.36341127008576],"type":"Point"}
}