{
  "type": "Feature",
  "properties": {
    "iso:country":"GB",
    "wof:name":"B45 9XL",
    "wof:placetype":"postalcode"
},
  "geometry": {"coordinates":[-2.02390210028328,52.38065586622009],"type":"Point"}
}