{
  "type": "Feature",
  "properties": {
    "iso:country":"GB",
    "wof:name":"BA4 5SR",
    "wof:placetype":"postalcode"
},
  "geometry": {"coordinates":[-2.55119034396775,51.18415444084626],"type":"Point"}
}