{
  "type": "Feature",
  "properties": {
    "date:inception_lower": "1980-01-01",
    "date:inception_upper": "1980-01-01",
    "iso:country": "GB",
    "wof:name": "B6 5LX",
    "wof:placetype": "postalcode"
  },
  "geometry": {"coordinates":[-1.88578,52.503044],"type":"Point"}
}
