{
  "type": "Feature",
  "properties": {
    "iso:country":"GB",
    "wof:name":"B6 5LX",
    "wof:placetype":"postalcode"
},
  "geometry": {"coordinates":[-1.88577042412311,52.50293960224047],"type":"Point"}
}