{
  "type": "Feature",
  "properties": {
    "iso:country":"GB",
    "wof:name":"L40 4AF",
    "wof:placetype":"postalcode"
},
  "geometry": {"coordinates":[-2.83033484832389,53.60083435080421],"type":"Point"}
}