{
  "type": "Feature",
  "properties": {
    "iso:country": "GB",
    "wof:name": "ST3 7RJ",
    "wof:placetype": "postalcode"
  },
  "geometry": {"coordinates":[-2.102493,52.970407],"type":"Point"}
}
