{
  "type": "Feature",
  "properties": {
    "date:inception_lower": "1991-09-01",
    "date:inception_upper": "1991-09-01",
    "iso:country": "GB",
    "wof:name": "GL51 0TB",
    "wof:placetype": "postalcode"
  },
  "geometry": {"coordinates":[-2.133335,51.896886],"type":"Point"}
}
