{
  "type": "Feature",
  "properties": {
    "date:inception_lower":"1994-05-01",
    "date:inception_upper":"1994-05-31",
    "iso:country":"GB",
    "wof:name":"BS27 3DJ",
    "wof:placetype":"postalcode"
},
  "geometry": {"coordinates":[-2.78527,51.278389],"type":"Point"}
}