{
  "type": "Feature",
  "properties": {
    "iso:country": "GB",
    "wof:name": "BS27 3DJ",
    "wof:placetype": "postalcode"
  },
  "geometry": {"coordinates":[-2.78527,51.278389],"type":"Point"}
}
