{
  "type": "Feature",
  "properties": {
    "iso:country":"GB",
    "wof:name":"SW12 0AA",
    "wof:placetype":"postalcode"
},
  "geometry": {"coordinates":[-0.14243481391392,51.44826302245436],"type":"Point"}
}