{
  "type": "Feature",
  "properties": {
    "iso:country": "GB",
    "wof:name": "DT3 6DD",
    "wof:placetype": "postalcode"
  },
  "geometry": {"coordinates":[-2.420018,50.64715],"type":"Point"}
}
