{
  "type": "Feature",
  "properties": {
    "date:inception_lower":"1980-01-01",
    "date:inception_upper":"1980-01-31",
    "iso:country":"GB",
    "wof:name":"DT3 6DD",
    "wof:placetype":"postalcode"
},
  "geometry": {"coordinates":[-2.420018,50.64715],"type":"Point"}
}