{
  "type": "Feature",
  "properties": {
    "iso:country":"GB",
    "wof:name":"DT3 6DD",
    "wof:placetype":"postalcode"
},
  "geometry": {"coordinates":[-2.42001803849448,50.64715046050645],"type":"Point"}
}