{
  "type": "Feature",
  "properties": {
    "iso:country":"GB",
    "wof:name":"KT18 5RB",
    "wof:placetype":"postalcode"
},
  "geometry": {"coordinates":[-0.23400277504173,51.30837763882501],"type":"Point"}
}