{
  "type": "Feature",
  "properties": {
    "date:inception_lower": "1980-01-01",
    "date:inception_upper": "1980-01-01",
    "iso:country": "GB",
    "wof:name": "CH3 5RP",
    "wof:placetype": "postalcode"
  },
  "geometry": {"coordinates":[-2.859306,53.185255],"type":"Point"}
}
