{
  "type": "Feature",
  "properties": {
    "iso:country": "GB",
    "wof:name": "PE6 7UT",
    "wof:placetype": "postalcode"
  },
  "geometry": {"coordinates":[-0.167959,52.614653],"type":"Point"}
}
