{
  "type": "Feature",
  "properties": {
    "iso:country":"GB",
    "wof:name":"PE6 7UT",
    "wof:placetype":"postalcode"
},
  "geometry": {"coordinates":[-0.16795913324898,52.61465304100625],"type":"Point"}
}