{
  "type": "Feature",
  "properties": {
    "iso:country":"GB",
    "wof:name":"SP7 0DS",
    "wof:placetype":"postalcode"
},
  "geometry": {"coordinates":[-2.15956642964374,50.98178131856029],"type":"Point"}
}