{
  "type": "Feature",
  "properties": {
    "iso:country":"GB",
    "wof:name":"ME9 8TE",
    "wof:placetype":"postalcode"
},
  "geometry": {"coordinates":[0.72746804585225,51.37955811406416],"type":"Point"}
}