{
  "type": "Feature",
  "properties": {
    "iso:country":"GB",
    "wof:name":"SA2 0UT",
    "wof:placetype":"postalcode"
},
  "geometry": {"coordinates":[-3.97424004993178,51.62512026967553],"type":"Point"}
}