{
  "type": "Feature",
  "properties": {
    "iso:country": "GB",
    "wof:name": "NR10 4NZ",
    "wof:placetype": "postalcode"
  },
  "geometry": {"coordinates":[1.14115,52.758045],"type":"Point"}
}
