{
  "type": "Feature",
  "properties": {
    "iso:country":"GB",
    "wof:name":"BN2 4DR",
    "wof:placetype":"postalcode"
},
  "geometry": {"coordinates":[-0.11549661419109,50.83984025681868],"type":"Point"}
}