{
  "type": "Feature",
  "properties": {
    "iso:country":"GB",
    "wof:name":"SK16 4UG",
    "wof:placetype":"postalcode"
},
  "geometry": {"coordinates":[-2.09665524966786,53.46780957694831],"type":"Point"}
}