{
  "type": "Feature",
  "properties": {
    "iso:country": "GB",
    "wof:name": "SK16 4UG",
    "wof:placetype": "postalcode"
  },
  "geometry": {"coordinates":[-2.096655,53.46781],"type":"Point"}
}
