{
  "type": "Feature",
  "properties": {
    "date:inception_lower": "1992-08-01",
    "date:inception_upper": "1992-08-01",
    "iso:country": "GB",
    "wof:name": "SK16 4UG",
    "wof:placetype": "postalcode"
  },
  "geometry": {"coordinates":[-2.096655,53.46781],"type":"Point"}
}
