{
  "type": "Feature",
  "properties": {
    "iso:country":"GB",
    "wof:name":"ST7 1SU",
    "wof:placetype":"postalcode"
},
  "geometry": {"coordinates":[-2.26030510721807,53.07281352530672],"type":"Point"}
}