{
  "type": "Feature",
  "properties": {
    "date:inception_lower":"1980-01-01",
    "date:inception_upper":"1980-01-31",
    "iso:country":"GB",
    "wof:name":"DH4 5AD",
    "wof:placetype":"postalcode"
},
  "geometry": {"coordinates":[-1.472344,54.844025],"type":"Point"}
}