{
  "type": "Feature",
  "properties": {
    "iso:country":"GB",
    "wof:name":"TR11 4SZ",
    "wof:placetype":"postalcode"
},
  "geometry": {"coordinates":[-5.09300666347699,50.14837670673248],"type":"Point"}
}