{
  "type": "Feature",
  "properties": {
    "iso:country": "GB",
    "wof:name": "TR11 4SZ",
    "wof:placetype": "postalcode"
  },
  "geometry": {"coordinates":[-5.093007,50.148377],"type":"Point"}
}
