{
  "type": "Feature",
  "properties": {
    "date:inception_lower":"1980-01-01",
    "date:inception_upper":"1980-01-31",
    "iso:country":"GB",
    "wof:name":"SR6 9RT",
    "wof:placetype":"postalcode"
},
  "geometry": {"coordinates":[-1.38225,54.923131],"type":"Point"}
}