{
  "type": "Feature",
  "properties": {
    "iso:country":"GB",
    "wof:name":"BL3 1DL",
    "wof:placetype":"postalcode"
},
  "geometry": {"coordinates":[-2.38129308933569,53.564413758438],"type":"Point"}
}