{
  "type": "Feature",
  "properties": {
    "iso:country": "GB",
    "wof:name": "G33 1SA",
    "wof:placetype": "postalcode"
  },
  "geometry": {"coordinates":[-4.192761,55.897974],"type":"Point"}
}
