{
  "type": "Feature",
  "properties": {
    "date:inception_lower": "1997-12-01",
    "date:inception_upper": "1997-12-01",
    "iso:country": "GB",
    "wof:name": "G33 1SA",
    "wof:placetype": "postalcode"
  },
  "geometry": {"coordinates":[-4.192761,55.897974],"type":"Point"}
}
