{
  "type": "Feature",
  "properties": {
    "iso:country": "GB",
    "wof:name": "SA12 9YH",
    "wof:placetype": "postalcode"
  },
  "geometry": {"coordinates":[-3.74554,51.626698],"type":"Point"}
}
