{
  "type": "Feature",
  "properties": {
    "iso:country": "GB",
    "wof:name": "SA12 9YH",
    "wof:placetype": "postalcode"
  },
  "geometry": {"coordinates":[-3.745711,51.626624],"type":"Point"}
}
