{
  "type": "Feature",
  "properties": {
    "iso:country":"GB",
    "wof:name":"SA12 9YH",
    "wof:placetype":"postalcode"
},
  "geometry": {"coordinates":[-3.74569505913285,51.6266200220957],"type":"Point"}
}