{
  "type": "Feature",
  "properties": {
    "date:inception_lower":"1980-01-01",
    "date:inception_upper":"1980-01-31",
    "iso:country":"GB",
    "wof:name":"MK43 9EY",
    "wof:placetype":"postalcode"
},
  "geometry": {"coordinates":[-0.533095,52.095281],"type":"Point"}
}