{
  "type": "Feature",
  "properties": {
    "date:inception_lower":"1980-01-01",
    "date:inception_upper":"1980-01-31",
    "iso:country":"GB",
    "wof:name":"DE4 3EF",
    "wof:placetype":"postalcode"
},
  "geometry": {"coordinates":[-1.576449,53.151665],"type":"Point"}
}