{
  "type": "Feature",
  "properties": {
    "iso:country":"GB",
    "wof:name":"CV7 9AQ",
    "wof:placetype":"postalcode"
},
  "geometry": {"coordinates":[-1.50988428814693,52.46085121157427],"type":"Point"}
}