{
  "type": "Feature",
  "properties": {
    "iso:country": "GB",
    "wof:name": "CV7 9AQ",
    "wof:placetype": "postalcode"
  },
  "geometry": {"coordinates":[-1.509884,52.460851],"type":"Point"}
}
