{
  "type": "Feature",
  "properties": {
    "date:inception_lower": "2021-12-01",
    "date:inception_upper": "2021-12-01",
    "iso:country": "GB",
    "wof:name": "TD1 2FF",
    "wof:placetype": "postalcode"
  },
  "geometry": {"coordinates":[-2.798247,55.613482],"type":"Point"}
}
