{
  "type": "Feature",
  "properties": {
    "iso:country":"GB",
    "wof:name":"PE10 0LQ",
    "wof:placetype":"postalcode"
},
  "geometry": {"coordinates":[-0.36960270426929,52.74522186040255],"type":"Point"}
}