{
  "type": "Feature",
  "properties": {
    "date:inception_lower": "1995-01-01",
    "date:inception_upper": "1995-01-01",
    "iso:country": "GB",
    "wof:name": "PE10 0LQ",
    "wof:placetype": "postalcode"
  },
  "geometry": {"coordinates":[-0.369603,52.745222],"type":"Point"}
}
