{
  "type": "Feature",
  "properties": {
    "iso:country":"GB",
    "wof:name":"NG21 0HS",
    "wof:placetype":"postalcode"
},
  "geometry": {"coordinates":[-1.0975997278436,53.11768230939076],"type":"Point"}
}