{
  "type": "Feature",
  "properties": {
    "iso:country": "GB",
    "wof:name": "B79 8UQ",
    "wof:placetype": "postalcode"
  },
  "geometry": {"coordinates":[-1.685323,52.649344],"type":"Point"}
}
