{
  "type": "Feature",
  "properties": {
    "iso:country":"GB",
    "wof:name":"WF6 2SY",
    "wof:placetype":"postalcode"
},
  "geometry": {"coordinates":[-1.42356475611062,53.70962319537448],"type":"Point"}
}