{
  "type": "Feature",
  "properties": {
    "iso:country": "GB",
    "wof:name": "WF6 2SY",
    "wof:placetype": "postalcode"
  },
  "geometry": {"coordinates":[-1.423565,53.709623],"type":"Point"}
}
