{
  "type": "Feature",
  "properties": {
    "iso:country": "GB",
    "wof:name": "SY11 3QG",
    "wof:placetype": "postalcode"
  },
  "geometry": {"coordinates":[-3.0037,52.92323],"type":"Point"}
}
