{
  "type": "Feature",
  "properties": {
    "date:inception_lower": "2020-02-01",
    "date:inception_upper": "2020-02-01",
    "iso:country": "GB",
    "wof:name": "SY11 3QG",
    "wof:placetype": "postalcode"
  },
  "geometry": {"coordinates":[-3.040554,52.901328],"type":"Point"}
}
