{
  "type": "Feature",
  "properties": {
    "iso:country":"GB",
    "wof:name":"SO30 0BQ",
    "wof:placetype":"postalcode"
},
  "geometry": {"coordinates":[-1.30404418138631,50.91089198971776],"type":"Point"}
}