{
  "type": "Feature",
  "properties": {
    "date:inception_lower": "1994-12-01",
    "date:inception_upper": "1994-12-01",
    "iso:country": "GB",
    "wof:name": "SO30 0BQ",
    "wof:placetype": "postalcode"
  },
  "geometry": {"coordinates":[-1.304019,50.91091],"type":"Point"}
}
