{
  "type": "Feature",
  "properties": {
    "iso:country":"GB",
    "wof:name":"CA24 3HA",
    "wof:placetype":"postalcode"
},
  "geometry": {"coordinates":[-3.54522978398578,54.52152808634889],"type":"Point"}
}