{
  "type": "Feature",
  "properties": {
    "date:inception_lower": "1980-01-01",
    "date:inception_upper": "1980-01-01",
    "iso:country": "GB",
    "wof:name": "RG7 4QN",
    "wof:placetype": "postalcode"
  },
  "geometry": {"coordinates":[-1.102108,51.380402],"type":"Point"}
}
