{
  "type": "Feature",
  "properties": {
    "iso:country":"GB",
    "wof:name":"RG7 4QN",
    "wof:placetype":"postalcode"
},
  "geometry": {"coordinates":[-1.10210781183913,51.38040207479735],"type":"Point"}
}