{
  "type": "Feature",
  "properties": {
    "date:inception_lower": "2016-07-01",
    "date:inception_upper": "2016-07-01",
    "iso:country": "GB",
    "wof:name": "EH10 6TX",
    "wof:placetype": "postalcode"
  },
  "geometry": {"coordinates":[-3.203319,55.903521],"type":"Point"}
}
