{
  "type": "Feature",
  "properties": {
    "iso:country":"GB",
    "wof:name":"DN5 8XD",
    "wof:placetype":"postalcode"
},
  "geometry": {"coordinates":[-1.17923299141031,53.5414086497935],"type":"Point"}
}