{
  "type": "Feature",
  "properties": {
    "iso:country":"GB",
    "wof:name":"NR12 7AS",
    "wof:placetype":"postalcode"
},
  "geometry": {"coordinates":[1.37238508253894,52.72908106015414],"type":"Point"}
}