{
  "type": "Feature",
  "properties": {
    "iso:country":"GB",
    "wof:name":"CW1 5EY",
    "wof:placetype":"postalcode"
},
  "geometry": {"coordinates":[-2.42643312448905,53.09760219960255],"type":"Point"}
}