{
  "type": "Feature",
  "properties": {
    "iso:country":"GB",
    "wof:name":"CT19 4HL",
    "wof:placetype":"postalcode"
},
  "geometry": {"coordinates":[1.13834591045807,51.08788221317357],"type":"Point"}
}