{
  "type": "Feature",
  "properties": {
    "date:inception_lower": "1980-01-01",
    "date:inception_upper": "1980-01-01",
    "iso:country": "GB",
    "wof:name": "DD10 0NA",
    "wof:placetype": "postalcode"
  },
  "geometry": {"coordinates":[-2.291163,56.827362],"type":"Point"}
}
