{
  "type": "Feature",
  "properties": {
    "iso:country":"GB",
    "wof:name":"HP13 7HL",
    "wof:placetype":"postalcode"
},
  "geometry": {"coordinates":[-0.71281806784733,51.62744219773705],"type":"Point"}
}