{
  "type": "Feature",
  "properties": {
    "iso:country":"GB",
    "wof:name":"NP4 9AB",
    "wof:placetype":"postalcode"
},
  "geometry": {"coordinates":[-3.08559920375938,51.77466895521216],"type":"Point"}
}