{
  "type": "Feature",
  "properties": {
    "iso:country": "GB",
    "wof:name": "NP4 9AB",
    "wof:placetype": "postalcode"
  },
  "geometry": {"coordinates":[-3.085599,51.774669],"type":"Point"}
}
