{
  "type": "Feature",
  "properties": {
    "date:inception_lower": "1980-01-01",
    "date:inception_upper": "1980-01-01",
    "iso:country": "GB",
    "wof:name": "SW8 2RR",
    "wof:placetype": "postalcode"
  },
  "geometry": {"coordinates":[-0.133033,51.471998],"type":"Point"}
}
