{
  "type": "Feature",
  "properties": {
    "iso:country":"GB",
    "wof:name":"SW8 2RR",
    "wof:placetype":"postalcode"
},
  "geometry": {"coordinates":[-0.13303304226938,51.47199798034877],"type":"Point"}
}