{
  "type": "Feature",
  "properties": {
    "iso:country":"GB",
    "wof:name":"AL4 8JZ",
    "wof:placetype":"postalcode"
},
  "geometry": {"coordinates":[-0.29492685820966,51.81509567148318],"type":"Point"}
}