{
  "type": "Feature",
  "properties": {
    "date:inception_lower":"2015-04-01",
    "date:inception_upper":"2015-04-30",
    "iso:country":"GB",
    "wof:name":"AL4 8JZ",
    "wof:placetype":"postalcode"
},
  "geometry": {"coordinates":[-0.294927,51.815096],"type":"Point"}
}