{
  "type": "Feature",
  "properties": {
    "iso:country":"GB",
    "wof:name":"LL18 1LF",
    "wof:placetype":"postalcode"
},
  "geometry": {"coordinates":[-3.49610087951205,53.3171285806414],"type":"Point"}
}