{
  "type": "Feature",
  "properties": {
    "date:inception_lower":"1980-01-01",
    "date:inception_upper":"1980-01-31",
    "iso:country":"GB",
    "wof:name":"LS13 3EB",
    "wof:placetype":"postalcode"
},
  "geometry": {"coordinates":[-1.640527,53.807613],"type":"Point"}
}