{
  "type": "Feature",
  "properties": {
    "iso:country":"GB",
    "wof:name":"LS13 3EB",
    "wof:placetype":"postalcode"
},
  "geometry": {"coordinates":[-1.64052742407529,53.80761312531335],"type":"Point"}
}