{
  "type": "Feature",
  "properties": {
    "date:inception_lower": "1980-01-01",
    "date:inception_upper": "1980-01-01",
    "iso:country": "GB",
    "wof:name": "L35 1RU",
    "wof:placetype": "postalcode"
  },
  "geometry": {"coordinates":[-2.82683,53.39793],"type":"Point"}
}
