{
  "type": "Feature",
  "properties": {
    "iso:country":"GB",
    "wof:name":"L35 1RU",
    "wof:placetype":"postalcode"
},
  "geometry": {"coordinates":[-2.82682963877878,53.3979302026068],"type":"Point"}
}