{
  "type": "Feature",
  "properties": {
    "iso:country":"GB",
    "wof:name":"DL10 7JH",
    "wof:placetype":"postalcode"
},
  "geometry": {"coordinates":[-1.65974433958637,54.40124242299913],"type":"Point"}
}