{
  "type": "Feature",
  "properties": {
    "iso:country": "GB",
    "wof:name": "DL10 7JH",
    "wof:placetype": "postalcode"
  },
  "geometry": {"coordinates":[-1.659744,54.401242],"type":"Point"}
}
