{
  "type": "Feature",
  "properties": {
    "iso:country":"GB",
    "wof:name":"LA14 3XP",
    "wof:placetype":"postalcode"
},
  "geometry": {"coordinates":[-3.25956898493507,54.11405115694901],"type":"Point"}
}