{
  "type": "Feature",
  "properties": {
    "iso:country": "GB",
    "wof:name": "LA14 3XP",
    "wof:placetype": "postalcode"
  },
  "geometry": {"coordinates":[-3.259569,54.114051],"type":"Point"}
}
