{
  "type": "Feature",
  "properties": {
    "date:inception_lower":"1980-01-01",
    "date:inception_upper":"1980-01-31",
    "iso:country":"GB",
    "wof:name":"LA14 3XP",
    "wof:placetype":"postalcode"
},
  "geometry": {"coordinates":[-3.259569,54.114051],"type":"Point"}
}