{
  "type": "Feature",
  "properties": {
    "iso:country":"GB",
    "wof:name":"PL20 6EH",
    "wof:placetype":"postalcode"
},
  "geometry": {"coordinates":[-4.09193082313248,50.49578568997399],"type":"Point"}
}