{
  "type": "Feature",
  "properties": {
    "iso:country": "GB",
    "wof:name": "CH5 3LW",
    "wof:placetype": "postalcode"
  },
  "geometry": {"coordinates":[-3.030704,53.184722],"type":"Point"}
}
