{
  "type": "Feature",
  "properties": {
    "iso:country": "GB",
    "wof:name": "BN22 0NN",
    "wof:placetype": "postalcode"
  },
  "geometry": {"coordinates":[0.258182,50.801097],"type":"Point"}
}
