{
  "type": "Feature",
  "properties": {
    "iso:country":"GB",
    "wof:name":"BN22 0NN",
    "wof:placetype":"postalcode"
},
  "geometry": {"coordinates":[0.2581820220944,50.80109728605407],"type":"Point"}
}