{
  "type": "Feature",
  "properties": {
    "iso:country":"GB",
    "wof:name":"TF8 7PS",
    "wof:placetype":"postalcode"
},
  "geometry": {"coordinates":[-2.47921587742272,52.62780994238737],"type":"Point"}
}