{
  "type": "Feature",
  "properties": {
    "date:inception_lower": "1980-01-01",
    "date:inception_upper": "1980-01-01",
    "iso:country": "GB",
    "wof:name": "EH12 0AP",
    "wof:placetype": "postalcode"
  },
  "geometry": {"coordinates":[-3.34743,55.953676],"type":"Point"}
}
