{
  "type": "Feature",
  "properties": {
    "iso:country":"GB",
    "wof:name":"WS11 1RZ",
    "wof:placetype":"postalcode"
},
  "geometry": {"coordinates":[-2.08680716894137,52.6852573282442],"type":"Point"}
}