{
  "type": "Feature",
  "properties": {
    "iso:country":"GB",
    "wof:name":"S44 5NB",
    "wof:placetype":"postalcode"
},
  "geometry": {"coordinates":[-1.28553377984428,53.1897473999119],"type":"Point"}
}