{
  "type": "Feature",
  "properties": {
    "date:inception_lower": "1980-01-01",
    "date:inception_upper": "1980-01-01",
    "iso:country": "GB",
    "wof:name": "S44 5NB",
    "wof:placetype": "postalcode"
  },
  "geometry": {"coordinates":[-1.285534,53.189747],"type":"Point"}
}
