{
  "type": "Feature",
  "properties": {
    "iso:country":"GB",
    "wof:name":"DH9 0ED",
    "wof:placetype":"postalcode"
},
  "geometry": {"coordinates":[-1.69237472603363,54.8750656726858],"type":"Point"}
}