{
  "type": "Feature",
  "properties": {
    "date:inception_lower": "2010-02-01",
    "date:inception_upper": "2010-02-01",
    "iso:country": "GB",
    "wof:name": "CT21 6PB",
    "wof:placetype": "postalcode"
  },
  "geometry": {"coordinates":[1.050325,51.06358],"type":"Point"}
}
