{
  "type": "Feature",
  "properties": {
    "iso:country":"GB",
    "wof:name":"CT21 6PB",
    "wof:placetype":"postalcode"
},
  "geometry": {"coordinates":[1.05032509011031,51.06358020821999],"type":"Point"}
}