{
  "type": "Feature",
  "properties": {
    "iso:country":"GB",
    "wof:name":"M30 0BJ",
    "wof:placetype":"postalcode"
},
  "geometry": {"coordinates":[-2.33543546893989,53.48369146413476],"type":"Point"}
}