{
  "type": "Feature",
  "properties": {
    "iso:country":"GB",
    "wof:name":"GL15 4QY",
    "wof:placetype":"postalcode"
},
  "geometry": {"coordinates":[-2.53920557754432,51.75710099609921],"type":"Point"}
}