{
  "type": "Feature",
  "properties": {
    "iso:country": "GB",
    "wof:name": "GL15 4QY",
    "wof:placetype": "postalcode"
  },
  "geometry": {"coordinates":[-2.539206,51.757101],"type":"Point"}
}
