{
  "type": "Feature",
  "properties": {
    "date:inception_lower": "2016-09-01",
    "date:inception_upper": "2016-09-01",
    "iso:country": "GB",
    "wof:name": "NG24 2PL",
    "wof:placetype": "postalcode"
  },
  "geometry": {"coordinates":[-0.77606,53.07891],"type":"Point"}
}
