{
  "type": "Feature",
  "properties": {
    "iso:country": "GB",
    "wof:name": "NG24 2PL",
    "wof:placetype": "postalcode"
  },
  "geometry": {"coordinates":[-0.77606,53.07891],"type":"Point"}
}
