{
  "type": "Feature",
  "properties": {
    "iso:country":"GB",
    "wof:name":"SS4 2DN",
    "wof:placetype":"postalcode"
},
  "geometry": {"coordinates":[0.77944617946632,51.60345203676192],"type":"Point"}
}