{
  "type": "Feature",
  "properties": {
    "date:inception_lower": "1995-12-01",
    "date:inception_upper": "1995-12-01",
    "iso:country": "GB",
    "wof:name": "CR0 3GR",
    "wof:placetype": "postalcode"
  },
  "geometry": {"coordinates":[-0.130348,51.386894],"type":"Point"}
}
