{
  "type": "Feature",
  "properties": {
    "iso:country": "GB",
    "wof:name": "WF4 2PP",
    "wof:placetype": "postalcode"
  },
  "geometry": {"coordinates":[-1.423625,53.620864],"type":"Point"}
}
