{
  "type": "Feature",
  "properties": {
    "iso:country":"GB",
    "wof:name":"WF4 2PP",
    "wof:placetype":"postalcode"
},
  "geometry": {"coordinates":[-1.42362520521233,53.62086411849479],"type":"Point"}
}