{
  "type": "Feature",
  "properties": {
    "date:inception_lower": "1997-12-01",
    "date:inception_upper": "1997-12-01",
    "iso:country": "GB",
    "wof:name": "WF4 2PP",
    "wof:placetype": "postalcode"
  },
  "geometry": {"coordinates":[-1.423625,53.620864],"type":"Point"}
}
