{
  "type": "Feature",
  "properties": {
    "iso:country":"GB",
    "wof:name":"HG1 3DB",
    "wof:placetype":"postalcode"
},
  "geometry": {"coordinates":[-1.54442154457076,54.01313604884626],"type":"Point"}
}