{
  "type": "Feature",
  "properties": {
    "iso:country": "GB",
    "wof:name": "HG1 3DB",
    "wof:placetype": "postalcode"
  },
  "geometry": {"coordinates":[-1.544421,54.013136],"type":"Point"}
}
