{
  "type": "Feature",
  "properties": {
    "date:inception_lower": "2004-04-01",
    "date:inception_upper": "2004-04-01",
    "iso:country": "GB",
    "wof:name": "NE29 9AE",
    "wof:placetype": "postalcode"
  },
  "geometry": {"coordinates":[-1.468171,55.015611],"type":"Point"}
}
