{
  "type": "Feature",
  "properties": {
    "date:inception_lower":"1991-01-01",
    "date:inception_upper":"1991-01-31",
    "iso:country":"GB",
    "wof:name":"PE37 7TT",
    "wof:placetype":"postalcode"
},
  "geometry": {"coordinates":[0.695574,52.639958],"type":"Point"}
}