{
  "type": "Feature",
  "properties": {
    "date:inception_lower": "1980-01-01",
    "date:inception_upper": "1980-01-01",
    "iso:country": "GB",
    "wof:name": "L31 6BT",
    "wof:placetype": "postalcode"
  },
  "geometry": {"coordinates":[-2.933338,53.514584],"type":"Point"}
}
