{
  "type": "Feature",
  "properties": {
    "date:inception_lower": "2017-05-01",
    "date:inception_upper": "2017-05-01",
    "iso:country": "GB",
    "wof:name": "HU15 1XX",
    "wof:placetype": "postalcode"
  },
  "geometry": {"coordinates":[-0.575901,53.720959],"type":"Point"}
}
