{
  "type": "Feature",
  "properties": {
    "date:inception_lower": "1995-07-01",
    "date:inception_upper": "1995-07-01",
    "iso:country": "GB",
    "wof:name": "SN12 6GB",
    "wof:placetype": "postalcode"
  },
  "geometry": {"coordinates":[-2.125564,51.371031],"type":"Point"}
}
