{
  "type": "Feature",
  "properties": {
    "date:inception_lower": "1995-07-01",
    "date:inception_upper": "1995-07-01",
    "iso:country": "GB",
    "wof:name": "RG40 5YD",
    "wof:placetype": "postalcode"
  },
  "geometry": {"coordinates":[-0.819607,51.417426],"type":"Point"}
}
