{
  "type": "Feature",
  "properties": {
    "iso:country": "GB",
    "wof:name": "TF12 5SR",
    "wof:placetype": "postalcode"
  },
  "geometry": {"coordinates":[-2.482256,52.612722],"type":"Point"}
}
