{
  "type": "Feature",
  "properties": {
    "date:inception_lower": "2020-09-01",
    "date:inception_upper": "2020-09-01",
    "iso:country": "GB",
    "wof:name": "CM6 4BF",
    "wof:placetype": "postalcode"
  },
  "geometry": {"coordinates":[0.364235,51.862644],"type":"Point"}
}
