{
  "type": "Feature",
  "properties": {
    "iso:country":"GB",
    "wof:name":"TA23 0EG",
    "wof:placetype":"postalcode"
},
  "geometry": {"coordinates":[-3.32490800380021,51.17827261067765],"type":"Point"}
}