{
  "type": "Feature",
  "properties": {
    "iso:country":"GB",
    "wof:name":"CT20 2BN",
    "wof:placetype":"postalcode"
},
  "geometry": {"coordinates":[1.17309905223788,51.07751655117427],"type":"Point"}
}