{
  "type": "Feature",
  "properties": {
    "iso:country": "GB",
    "wof:name": "CT20 2BN",
    "wof:placetype": "postalcode"
  },
  "geometry": {"coordinates":[1.173099,51.077517],"type":"Point"}
}
