{
  "type": "Feature",
  "properties": {
    "iso:country":"GB",
    "wof:name":"M15 4HH",
    "wof:placetype":"postalcode"
},
  "geometry": {"coordinates":[-2.26005556699405,53.47092703291568],"type":"Point"}
}