{
  "type": "Feature",
  "properties": {
    "iso:country": "GB",
    "wof:name": "M15 4HH",
    "wof:placetype": "postalcode"
  },
  "geometry": {"coordinates":[-2.260056,53.470927],"type":"Point"}
}
