{
  "type": "Feature",
  "properties": {
    "iso:country":"GB",
    "wof:name":"WV2 3LQ",
    "wof:placetype":"postalcode"
},
  "geometry": {"coordinates":[-2.12446422147853,52.57921678452298],"type":"Point"}
}