{
  "type": "Feature",
  "properties": {
    "date:inception_lower":"1991-09-01",
    "date:inception_upper":"1991-09-30",
    "iso:country":"GB",
    "wof:name":"PE22 7QH",
    "wof:placetype":"postalcode"
},
  "geometry": {"coordinates":[-0.088392,53.132537],"type":"Point"}
}