{
  "type": "Feature",
  "properties": {
    "date:inception_lower": "1980-01-01",
    "date:inception_upper": "1980-01-01",
    "iso:country": "GB",
    "wof:name": "TW13 5LL",
    "wof:placetype": "postalcode"
  },
  "geometry": {"coordinates":[-0.384129,51.442779],"type":"Point"}
}
