{
  "type": "Feature",
  "properties": {
    "iso:country":"GB",
    "wof:name":"ST5 5HN",
    "wof:placetype":"postalcode"
},
  "geometry": {"coordinates":[-2.27899113634016,52.97573319609203],"type":"Point"}
}