{
  "type": "Feature",
  "properties": {
    "iso:country":"GB",
    "wof:name":"M40 5GH",
    "wof:placetype":"postalcode"
},
  "geometry": {"coordinates":[-2.18822767573723,53.5188084358224],"type":"Point"}
}