{
  "type": "Feature",
  "properties": {
    "date:inception_lower": "2005-10-01",
    "date:inception_upper": "2005-10-01",
    "iso:country": "GB",
    "wof:name": "S60 3HH",
    "wof:placetype": "postalcode"
  },
  "geometry": {"coordinates":[-1.334421,53.414267],"type":"Point"}
}
