{
  "type": "Feature",
  "properties": {
    "iso:country": "GB",
    "wof:name": "S60 3HH",
    "wof:placetype": "postalcode"
  },
  "geometry": {"coordinates":[-1.334421,53.414267],"type":"Point"}
}
