{
  "type": "Feature",
  "properties": {
    "iso:country": "GB",
    "wof:name": "IG6 2FN",
    "wof:placetype": "postalcode"
  },
  "geometry": {"coordinates":[0.087861,51.604578],"type":"Point"}
}
