{
  "type": "Feature",
  "properties": {
    "iso:country":"GB",
    "wof:name":"WD3 8HT",
    "wof:placetype":"postalcode"
},
  "geometry": {"coordinates":[-0.49200168161115,51.64011829619233],"type":"Point"}
}