{
  "type": "Feature",
  "properties": {
    "iso:country":"GB",
    "wof:name":"E20 2AQ",
    "wof:placetype":"postalcode"
},
  "geometry": {"coordinates":[-0.01015864622861,51.53994895711609],"type":"Point"}
}