{
  "type": "Feature",
  "properties": {
    "date:inception_lower": "2002-07-01",
    "date:inception_upper": "2002-07-01",
    "iso:country": "GB",
    "wof:name": "WF1 5EP",
    "wof:placetype": "postalcode"
  },
  "geometry": {"coordinates":[-1.47836,53.67189],"type":"Point"}
}
