{
  "type": "Feature",
  "properties": {
    "iso:country": "GB",
    "wof:name": "TW3 4HS",
    "wof:placetype": "postalcode"
  },
  "geometry": {"coordinates":[-0.36542,51.472087],"type":"Point"}
}
