{
  "type": "Feature",
  "properties": {
    "iso:country":"GB",
    "wof:name":"CV3 1BS",
    "wof:placetype":"postalcode"
},
  "geometry": {"coordinates":[-1.48071895979744,52.40028621270724],"type":"Point"}
}