{
  "type": "Feature",
  "properties": {
    "iso:country":"GB",
    "wof:name":"NE48 3EQ",
    "wof:placetype":"postalcode"
},
  "geometry": {"coordinates":[-2.28137401611305,55.07033595689644],"type":"Point"}
}