{
  "type": "Feature",
  "properties": {
    "iso:country": "GB",
    "wof:name": "NE48 3EQ",
    "wof:placetype": "postalcode"
  },
  "geometry": {"coordinates":[-2.281374,55.070336],"type":"Point"}
}
