{
  "type": "Feature",
  "properties": {
    "iso:country":"GB",
    "wof:name":"TD15 2SJ",
    "wof:placetype":"postalcode"
},
  "geometry": {"coordinates":[-1.80012675470869,55.6711689926856],"type":"Point"}
}