{
  "type": "Feature",
  "properties": {
    "iso:country":"GB",
    "wof:name":"SA7 9WA",
    "wof:placetype":"postalcode"
},
  "geometry": {"coordinates":[-3.89540460008102,51.65227303413382],"type":"Point"}
}