{
  "type": "Feature",
  "properties": {
    "date:inception_lower":"1997-06-01",
    "date:inception_upper":"1997-06-30",
    "iso:country":"GB",
    "wof:name":"SA7 9WA",
    "wof:placetype":"postalcode"
},
  "geometry": {"coordinates":[-3.895405,51.652273],"type":"Point"}
}