{
  "type": "Feature",
  "properties": {
    "iso:country": "GB",
    "wof:name": "NG16 5AG",
    "wof:placetype": "postalcode"
  },
  "geometry": {"coordinates":[-1.315439,53.034338],"type":"Point"}
}
