{
  "type": "Feature",
  "properties": {
    "iso:country":"GB",
    "wof:name":"CR3 5WN",
    "wof:placetype":"postalcode"
},
  "geometry": {"coordinates":[-0.09999734899614,51.28401362592571],"type":"Point"}
}