{
  "type": "Feature",
  "properties": {
    "iso:country": "GB",
    "wof:name": "CR3 5WN",
    "wof:placetype": "postalcode"
  },
  "geometry": {"coordinates":[-0.099997,51.284014],"type":"Point"}
}
