{
  "type": "Feature",
  "properties": {
    "date:inception_lower": "2014-12-01",
    "date:inception_upper": "2014-12-01",
    "iso:country": "GB",
    "wof:name": "CR3 5WN",
    "wof:placetype": "postalcode"
  },
  "geometry": {"coordinates":[-0.099997,51.284014],"type":"Point"}
}
