{
  "type": "Feature",
  "properties": {
    "iso:country":"GB",
    "wof:name":"SY23 5BN",
    "wof:placetype":"postalcode"
},
  "geometry": {"coordinates":[-4.14482778578588,52.3045673346823],"type":"Point"}
}