{
  "type": "Feature",
  "properties": {
    "iso:country": "GB",
    "wof:name": "SY23 5BN",
    "wof:placetype": "postalcode"
  },
  "geometry": {"coordinates":[-4.144828,52.304567],"type":"Point"}
}
