{
  "type": "Feature",
  "properties": {
    "date:inception_lower":"1980-01-01",
    "date:inception_upper":"1980-01-31",
    "iso:country":"GB",
    "wof:name":"PR2 3QU",
    "wof:placetype":"postalcode"
},
  "geometry": {"coordinates":[-2.721051,53.78166],"type":"Point"}
}