{
  "type": "Feature",
  "properties": {
    "iso:country":"GB",
    "wof:name":"PR2 3QU",
    "wof:placetype":"postalcode"
},
  "geometry": {"coordinates":[-2.72105074421037,53.78166008502747],"type":"Point"}
}