{
  "type": "Feature",
  "properties": {
    "iso:country":"GB",
    "wof:name":"PE15 9UL",
    "wof:placetype":"postalcode"
},
  "geometry": {"coordinates":[0.08047290925668,52.54930948922931],"type":"Point"}
}