{
  "type": "Feature",
  "properties": {
    "iso:country": "GB",
    "wof:name": "PE15 9UL",
    "wof:placetype": "postalcode"
  },
  "geometry": {"coordinates":[0.080473,52.549309],"type":"Point"}
}
