{
  "type": "Feature",
  "properties": {
    "iso:country":"GB",
    "wof:name":"CF48 2UY",
    "wof:placetype":"postalcode"
},
  "geometry": {"coordinates":[-3.37157283306549,51.77475456427725],"type":"Point"}
}