{
  "type": "Feature",
  "properties": {
    "date:inception_lower":"1980-01-01",
    "date:inception_upper":"1980-01-31",
    "iso:country":"GB",
    "wof:name":"CF48 2UY",
    "wof:placetype":"postalcode"
},
  "geometry": {"coordinates":[-3.371573,51.774755],"type":"Point"}
}