{
  "type": "Feature",
  "properties": {
    "iso:country": "GB",
    "wof:name": "WV14 9EW",
    "wof:placetype": "postalcode"
  },
  "geometry": {"coordinates":[-2.087545,52.539422],"type":"Point"}
}
