{
  "type": "Feature",
  "properties": {
    "iso:country":"GB",
    "wof:name":"TQ6 0LL",
    "wof:placetype":"postalcode"
},
  "geometry": {"coordinates":[-3.64329679037927,50.32082507646295],"type":"Point"}
}