{
  "type": "Feature",
  "properties": {
    "date:inception_lower": "2019-11-01",
    "date:inception_upper": "2019-11-01",
    "iso:country": "GB",
    "wof:name": "NP18 2EJ",
    "wof:placetype": "postalcode"
  },
  "geometry": {"coordinates":[-2.920566,51.591593],"type":"Point"}
}
