{
  "type": "Feature",
  "properties": {
    "iso:country": "GB",
    "wof:name": "NP18 2EJ",
    "wof:placetype": "postalcode"
  },
  "geometry": {"coordinates":[-2.8901,51.597178],"type":"Point"}
}
