{
  "type": "Feature",
  "properties": {
    "iso:country": "GB",
    "wof:name": "PO19 7PE",
    "wof:placetype": "postalcode"
  },
  "geometry": {"coordinates":[-0.771264,50.832778],"type":"Point"}
}
