{
  "type": "Feature",
  "properties": {
    "iso:country": "GB",
    "wof:name": "OX28 4DY",
    "wof:placetype": "postalcode"
  },
  "geometry": {"coordinates":[-1.495988,51.784844],"type":"Point"}
}
