{
  "type": "Feature",
  "properties": {
    "iso:country":"GB",
    "wof:name":"CT14 7BW",
    "wof:placetype":"postalcode"
},
  "geometry": {"coordinates":[1.40363373675935,51.22171610590621],"type":"Point"}
}