{
  "type": "Feature",
  "properties": {
    "iso:country":"GB",
    "wof:name":"BH16 5NF",
    "wof:placetype":"postalcode"
},
  "geometry": {"coordinates":[-2.039457117797,50.73818838680676],"type":"Point"}
}