{
  "type": "Feature",
  "properties": {
    "iso:country":"GB",
    "wof:name":"SM2 5DA",
    "wof:placetype":"postalcode"
},
  "geometry": {"coordinates":[-0.18930260167988,51.35848575161082],"type":"Point"}
}