{
  "type": "Feature",
  "properties": {
    "iso:country":"GB",
    "wof:name":"HU15 2HQ",
    "wof:placetype":"postalcode"
},
  "geometry": {"coordinates":[-0.61322716728701,53.76366891213261],"type":"Point"}
}