{
  "type": "Feature",
  "properties": {
    "iso:country": "GB",
    "wof:name": "HU15 2HQ",
    "wof:placetype": "postalcode"
  },
  "geometry": {"coordinates":[-0.613227,53.763669],"type":"Point"}
}
