{
  "type": "Feature",
  "properties": {
    "date:inception_lower": "2004-10-01",
    "date:inception_upper": "2004-10-01",
    "iso:country": "GB",
    "wof:name": "OX1 1AD",
    "wof:placetype": "postalcode"
  },
  "geometry": {"coordinates":[-1.273059,51.758377],"type":"Point"}
}
