{
  "type": "Feature",
  "properties": {
    "iso:country":"GB",
    "wof:name":"TW2 7HE",
    "wof:placetype":"postalcode"
},
  "geometry": {"coordinates":[-0.36010711899082,51.45741793278206],"type":"Point"}
}