{
  "type": "Feature",
  "properties": {
    "iso:country":"GB",
    "wof:name":"EH8 7AA",
    "wof:placetype":"postalcode"
},
  "geometry": {"coordinates":[-3.15004997355732,55.9551617361846],"type":"Point"}
}