{
  "type": "Feature",
  "properties": {
    "iso:country":"GB",
    "wof:name":"WR2 4HF",
    "wof:placetype":"postalcode"
},
  "geometry": {"coordinates":[-2.24013975398078,52.18566644356095],"type":"Point"}
}