{
  "type": "Feature",
  "properties": {
    "date:inception_lower": "1980-01-01",
    "date:inception_upper": "1980-01-01",
    "iso:country": "GB",
    "wof:name": "WR2 4HF",
    "wof:placetype": "postalcode"
  },
  "geometry": {"coordinates":[-2.24014,52.185666],"type":"Point"}
}
