{
  "type": "Feature",
  "properties": {
    "iso:country":"GB",
    "wof:name":"TN21 8DJ",
    "wof:placetype":"postalcode"
},
  "geometry": {"coordinates":[0.25313566377527,50.96770664021049],"type":"Point"}
}