{
  "type": "Feature",
  "properties": {
    "date:inception_lower": "2005-03-01",
    "date:inception_upper": "2005-03-01",
    "iso:country": "GB",
    "wof:name": "DD3 6NT",
    "wof:placetype": "postalcode"
  },
  "geometry": {"coordinates":[-2.976035,56.467048],"type":"Point"}
}
