{
  "type": "Feature",
  "properties": {
    "iso:country":"GB",
    "wof:name":"WF12 0SG",
    "wof:placetype":"postalcode"
},
  "geometry": {"coordinates":[-1.6214120816929,53.66547036927755],"type":"Point"}
}