{
  "type": "Feature",
  "properties": {
    "date:inception_lower": "1998-12-01",
    "date:inception_upper": "1998-12-01",
    "iso:country": "GB",
    "wof:name": "OL12 7NR",
    "wof:placetype": "postalcode"
  },
  "geometry": {"coordinates":[-2.189711,53.627744],"type":"Point"}
}
