{
  "type": "Feature",
  "properties": {
    "iso:country":"GB",
    "wof:name":"OL12 7NR",
    "wof:placetype":"postalcode"
},
  "geometry": {"coordinates":[-2.18971072386643,53.62774439441507],"type":"Point"}
}