{
  "type": "Feature",
  "properties": {
    "iso:country":"GB",
    "wof:name":"EX15 3BP",
    "wof:placetype":"postalcode"
},
  "geometry": {"coordinates":[-3.34106059541747,50.90120361981644],"type":"Point"}
}