{
  "type": "Feature",
  "properties": {
    "iso:country":"GB",
    "wof:name":"PO22 0JB",
    "wof:placetype":"postalcode"
},
  "geometry": {"coordinates":[-0.63604684152639,50.83180666674496],"type":"Point"}
}