{
  "type": "Feature",
  "properties": {
    "iso:country":"GB",
    "wof:name":"LU6 3BT",
    "wof:placetype":"postalcode"
},
  "geometry": {"coordinates":[-0.52420904699333,51.87895292130213],"type":"Point"}
}