{
  "type": "Feature",
  "properties": {
    "iso:country":"GB",
    "wof:name":"EX33 1AT",
    "wof:placetype":"postalcode"
},
  "geometry": {"coordinates":[-4.16750060273377,51.11093867554899],"type":"Point"}
}