{
  "type": "Feature",
  "properties": {
    "iso:country": "GB",
    "wof:name": "SK11 7AB",
    "wof:placetype": "postalcode"
  },
  "geometry": {"coordinates":[-2.121119,53.256312],"type":"Point"}
}
