{
  "type": "Feature",
  "properties": {
    "iso:country":"GB",
    "wof:name":"M26 3XN",
    "wof:placetype":"postalcode"
},
  "geometry": {"coordinates":[-2.34992178940217,53.56106716532774],"type":"Point"}
}