{
  "type": "Feature",
  "properties": {
    "iso:country":"GB",
    "wof:name":"WV14 6JX",
    "wof:placetype":"postalcode"
},
  "geometry": {"coordinates":[-2.07041483723989,52.57420011139957],"type":"Point"}
}