{
  "type": "Feature",
  "properties": {
    "iso:country": "GB",
    "wof:name": "WV14 6JX",
    "wof:placetype": "postalcode"
  },
  "geometry": {"coordinates":[-2.070415,52.5742],"type":"Point"}
}
