{
  "type": "Feature",
  "properties": {
    "iso:country":"GB",
    "wof:name":"AL3 6AD",
    "wof:placetype":"postalcode"
},
  "geometry": {"coordinates":[-0.36078015033712,51.75023843024785],"type":"Point"}
}