{
  "type": "Feature",
  "properties": {
    "iso:country": "GB",
    "wof:name": "MK17 0QR",
    "wof:placetype": "postalcode"
  },
  "geometry": {"coordinates":[-0.877677,51.970879],"type":"Point"}
}
