{
  "type": "Feature",
  "properties": {
    "iso:country":"GB",
    "wof:name":"MK17 0QR",
    "wof:placetype":"postalcode"
},
  "geometry": {"coordinates":[-0.87767666783159,51.97087881886471],"type":"Point"}
}