{
  "type": "Feature",
  "properties": {
    "iso:country": "GB",
    "wof:name": "BL2 6UB",
    "wof:placetype": "postalcode"
  },
  "geometry": {"coordinates":[-2.380839,53.576055],"type":"Point"}
}
