{
  "type": "Feature",
  "properties": {
    "iso:country":"GB",
    "wof:name":"BL2 6UB",
    "wof:placetype":"postalcode"
},
  "geometry": {"coordinates":[-2.38083910990537,53.57605512863955],"type":"Point"}
}