{
  "type": "Feature",
  "properties": {
    "date:inception_lower":"1980-01-01",
    "date:inception_upper":"1980-01-31",
    "iso:country":"GB",
    "wof:name":"SA62 5EW",
    "wof:placetype":"postalcode"
},
  "geometry": {"coordinates":[-5.053403,51.941611],"type":"Point"}
}