{
  "type": "Feature",
  "properties": {
    "iso:country": "GB",
    "wof:name": "SA62 5EW",
    "wof:placetype": "postalcode"
  },
  "geometry": {"coordinates":[-5.053403,51.941611],"type":"Point"}
}
