{
  "type": "Feature",
  "properties": {
    "iso:country": "GB",
    "wof:name": "BH23 7NB",
    "wof:placetype": "postalcode"
  },
  "geometry": {"coordinates":[-1.773402,50.754108],"type":"Point"}
}
