{
  "type": "Feature",
  "properties": {
    "iso:country":"GB",
    "wof:name":"BH23 7NB",
    "wof:placetype":"postalcode"
},
  "geometry": {"coordinates":[-1.77340163381961,50.75410831880625],"type":"Point"}
}