{
  "type": "Feature",
  "properties": {
    "iso:country":"GB",
    "wof:name":"SN12 7JN",
    "wof:placetype":"postalcode"
},
  "geometry": {"coordinates":[-2.12238099749059,51.37869552479488],"type":"Point"}
}