{
  "type": "Feature",
  "properties": {
    "iso:country":"GB",
    "wof:name":"PO6 2AZ",
    "wof:placetype":"postalcode"
},
  "geometry": {"coordinates":[-1.06018143854948,50.83642446944231],"type":"Point"}
}