{
  "type": "Feature",
  "properties": {
    "iso:country":"GB",
    "wof:name":"S65 3QZ",
    "wof:placetype":"postalcode"
},
  "geometry": {"coordinates":[-1.31506737443358,53.44175288944941],"type":"Point"}
}