{
  "type": "Feature",
  "properties": {
    "iso:country": "GB",
    "wof:name": "TA6 3JN",
    "wof:placetype": "postalcode"
  },
  "geometry": {"coordinates":[-3.003754,51.133856],"type":"Point"}
}
