{
  "type": "Feature",
  "properties": {
    "iso:country":"GB",
    "wof:name":"TA6 3JN",
    "wof:placetype":"postalcode"
},
  "geometry": {"coordinates":[-3.00375432068344,51.13385556879516],"type":"Point"}
}