{
  "type": "Feature",
  "properties": {
    "date:inception_lower": "2001-06-01",
    "date:inception_upper": "2001-06-01",
    "iso:country": "GB",
    "wof:name": "PR26 8LR",
    "wof:placetype": "postalcode"
  },
  "geometry": {"coordinates":[-2.738028,53.663729],"type":"Point"}
}
