{
  "type": "Feature",
  "properties": {
    "iso:country":"GB",
    "wof:name":"S10 2BR",
    "wof:placetype":"postalcode"
},
  "geometry": {"coordinates":[-1.49026141400717,53.37232827918406],"type":"Point"}
}