{
  "type": "Feature",
  "properties": {
    "iso:country":"GB",
    "wof:name":"HD5 8XJ",
    "wof:placetype":"postalcode"
},
  "geometry": {"coordinates":[-1.74965339994,53.6306359801703],"type":"Point"}
}