{
  "type": "Feature",
  "properties": {
    "iso:country":"GB",
    "wof:name":"HP4 1TD",
    "wof:placetype":"postalcode"
},
  "geometry": {"coordinates":[-0.58425221335187,51.77160253128844],"type":"Point"}
}