{
  "type": "Feature",
  "properties": {
    "date:inception_lower":"1994-05-01",
    "date:inception_upper":"1994-05-31",
    "iso:country":"GB",
    "wof:name":"HP4 1TD",
    "wof:placetype":"postalcode"
},
  "geometry": {"coordinates":[-0.584252,51.771603],"type":"Point"}
}