{
  "type": "Feature",
  "properties": {
    "iso:country":"GB",
    "wof:name":"CR0 2TR",
    "wof:placetype":"postalcode"
},
  "geometry": {"coordinates":[-0.1015435827422,51.38554940554901],"type":"Point"}
}