{
  "type": "Feature",
  "properties": {
    "iso:country": "GB",
    "wof:name": "B6 4TN",
    "wof:placetype": "postalcode"
  },
  "geometry": {"coordinates":[-1.888735,52.495804],"type":"Point"}
}
