{
  "type": "Feature",
  "properties": {
    "iso:country":"GB",
    "wof:name":"PO21 4BP",
    "wof:placetype":"postalcode"
},
  "geometry": {"coordinates":[-0.7170092109373,50.7828497589413],"type":"Point"}
}