{
  "type": "Feature",
  "properties": {
    "iso:country": "GB",
    "wof:name": "SR1 1EE",
    "wof:placetype": "postalcode"
  },
  "geometry": {"coordinates":[-1.377092,54.905554],"type":"Point"}
}
