{
  "type": "Feature",
  "properties": {
    "iso:country":"GB",
    "wof:name":"W1B 5AB",
    "wof:placetype":"postalcode"
},
  "geometry": {"coordinates":[-0.13639892343712,51.51023385997561],"type":"Point"}
}