{
  "type": "Feature",
  "properties": {
    "date:inception_lower":"2000-10-01",
    "date:inception_upper":"2000-10-31",
    "iso:country":"GB",
    "wof:name":"W1B 5AB",
    "wof:placetype":"postalcode"
},
  "geometry": {"coordinates":[-0.136399,51.510234],"type":"Point"}
}