{
  "type": "Feature",
  "properties": {
    "iso:country": "GB",
    "wof:name": "BS20 7LP",
    "wof:placetype": "postalcode"
  },
  "geometry": {"coordinates":[-2.75368,51.479551],"type":"Point"}
}
