{
  "type": "Feature",
  "properties": {
    "iso:country": "GB",
    "wof:name": "WA7 4JB",
    "wof:placetype": "postalcode"
  },
  "geometry": {"coordinates":[-2.751883,53.331933],"type":"Point"}
}
