{
  "type": "Feature",
  "properties": {
    "date:inception_lower": "1980-01-01",
    "date:inception_upper": "1980-01-01",
    "iso:country": "GB",
    "wof:name": "WA7 4JB",
    "wof:placetype": "postalcode"
  },
  "geometry": {"coordinates":[-2.75197,53.331726],"type":"Point"}
}
