{
  "type": "Feature",
  "properties": {
    "iso:country":"GB",
    "wof:name":"L20 4HH",
    "wof:placetype":"postalcode"
},
  "geometry": {"coordinates":[-3.00361514894721,53.4545802142305],"type":"Point"}
}