{
  "type": "Feature",
  "properties": {
    "iso:country": "GB",
    "wof:name": "L20 4HH",
    "wof:placetype": "postalcode"
  },
  "geometry": {"coordinates":[-3.003615,53.45458],"type":"Point"}
}
