{
  "type": "Feature",
  "properties": {
    "date:inception_lower": "1980-01-01",
    "date:inception_upper": "1980-01-01",
    "iso:country": "GB",
    "wof:name": "L20 4HH",
    "wof:placetype": "postalcode"
  },
  "geometry": {"coordinates":[-3.003615,53.45458],"type":"Point"}
}
