{
  "type": "Feature",
  "properties": {
    "iso:country":"GB",
    "wof:name":"SM1 4LS",
    "wof:placetype":"postalcode"
},
  "geometry": {"coordinates":[-0.17988737913035,51.36410414546243],"type":"Point"}
}