{
  "type": "Feature",
  "properties": {
    "date:inception_lower":"1980-01-01",
    "date:inception_upper":"1980-01-31",
    "iso:country":"GB",
    "wof:name":"SM1 4LS",
    "wof:placetype":"postalcode"
},
  "geometry": {"coordinates":[-0.180027,51.363837],"type":"Point"}
}