{
  "type": "Feature",
  "properties": {
    "iso:country":"GB",
    "wof:name":"NG23 5AL",
    "wof:placetype":"postalcode"
},
  "geometry": {"coordinates":[-0.73737505889231,53.0337523032364],"type":"Point"}
}