{
  "type": "Feature",
  "properties": {
    "date:inception_lower":"2005-01-01",
    "date:inception_upper":"2005-01-31",
    "iso:country":"GB",
    "wof:name":"EX4 2QL",
    "wof:placetype":"postalcode"
},
  "geometry": {"coordinates":[-3.558451,50.731518],"type":"Point"}
}