{
  "type": "Feature",
  "properties": {
    "iso:country":"GB",
    "wof:name":"SK17 8TA",
    "wof:placetype":"postalcode"
},
  "geometry": {"coordinates":[-1.8232591869171,53.27257575055339],"type":"Point"}
}