{
  "type": "Feature",
  "properties": {
    "iso:country":"GB",
    "wof:name":"NG20 0EF",
    "wof:placetype":"postalcode"
},
  "geometry": {"coordinates":[-1.16296294022228,53.19566449179477],"type":"Point"}
}