{
  "type": "Feature",
  "properties": {
    "iso:country":"GB",
    "wof:name":"DY1 3AB",
    "wof:placetype":"postalcode"
},
  "geometry": {"coordinates":[-2.09892681759978,52.52368364141],"type":"Point"}
}