{
  "type": "Feature",
  "properties": {
    "iso:country": "GB",
    "wof:name": "DY1 3AB",
    "wof:placetype": "postalcode"
  },
  "geometry": {"coordinates":[-2.098927,52.523684],"type":"Point"}
}
