{
  "type": "Feature",
  "properties": {
    "iso:country": "GB",
    "wof:name": "LA2 7BP",
    "wof:placetype": "postalcode"
  },
  "geometry": {"coordinates":[-2.520648,54.120236],"type":"Point"}
}
