{
  "type": "Feature",
  "properties": {
    "date:inception_lower":"1980-01-01",
    "date:inception_upper":"1980-01-31",
    "iso:country":"GB",
    "wof:name":"LL68 9RP",
    "wof:placetype":"postalcode"
},
  "geometry": {"coordinates":[-4.372669,53.410924],"type":"Point"}
}