{
  "type": "Feature",
  "properties": {
    "iso:country": "GB",
    "wof:name": "LL68 9RP",
    "wof:placetype": "postalcode"
  },
  "geometry": {"coordinates":[-4.372669,53.410924],"type":"Point"}
}
