{
  "type": "Feature",
  "properties": {
    "iso:country":"GB",
    "wof:name":"LL68 9RP",
    "wof:placetype":"postalcode"
},
  "geometry": {"coordinates":[-4.37266869778695,53.41092391954714],"type":"Point"}
}