{
  "type": "Feature",
  "properties": {
    "iso:country":"GB",
    "wof:name":"PE16 6FF",
    "wof:placetype":"postalcode"
},
  "geometry": {"coordinates":[0.04660056560094,52.45305361043454],"type":"Point"}
}