{
  "type": "Feature",
  "properties": {
    "iso:country":"GB",
    "wof:name":"G42 8AE",
    "wof:placetype":"postalcode"
},
  "geometry": {"coordinates":[-4.25607772248998,55.834681212183],"type":"Point"}
}