{
  "type": "Feature",
  "properties": {
    "date:inception_lower": "1980-01-01",
    "date:inception_upper": "1980-01-01",
    "iso:country": "GB",
    "wof:name": "YO8 8DH",
    "wof:placetype": "postalcode"
  },
  "geometry": {"coordinates":[-1.055834,53.777319],"type":"Point"}
}
