{
  "type": "Feature",
  "properties": {
    "iso:country":"GB",
    "wof:name":"YO8 8DH",
    "wof:placetype":"postalcode"
},
  "geometry": {"coordinates":[-1.05583447130606,53.7773190465971],"type":"Point"}
}