{
  "type": "Feature",
  "properties": {
    "iso:country": "GB",
    "wof:name": "MK11 4BP",
    "wof:placetype": "postalcode"
  },
  "geometry": {"coordinates":[-0.838389,52.043238],"type":"Point"}
}
