{
  "type": "Feature",
  "properties": {
    "iso:country":"GB",
    "wof:name":"HA8 7RE",
    "wof:placetype":"postalcode"
},
  "geometry": {"coordinates":[-0.2913921007731,51.61253420668347],"type":"Point"}
}