{
  "type": "Feature",
  "properties": {
    "iso:country":"GB",
    "wof:name":"NE10 0EF",
    "wof:placetype":"postalcode"
},
  "geometry": {"coordinates":[-1.58091609997232,54.96091170628676],"type":"Point"}
}