{
  "type": "Feature",
  "properties": {
    "iso:country":"GB",
    "wof:name":"G66 3EL",
    "wof:placetype":"postalcode"
},
  "geometry": {"coordinates":[-4.14770896769906,55.93340465763333],"type":"Point"}
}