{
  "type": "Feature",
  "properties": {
    "iso:country":"GB",
    "wof:name":"RG17 7SF",
    "wof:placetype":"postalcode"
},
  "geometry": {"coordinates":[-1.54121002191409,51.48041225015328],"type":"Point"}
}