{
  "type": "Feature",
  "properties": {
    "date:inception_lower": "1995-07-01",
    "date:inception_upper": "1995-07-01",
    "iso:country": "GB",
    "wof:name": "RG17 7SF",
    "wof:placetype": "postalcode"
  },
  "geometry": {"coordinates":[-1.54121,51.480412],"type":"Point"}
}
