{
  "type": "Feature",
  "properties": {
    "iso:country":"GB",
    "wof:name":"LA13 0PH",
    "wof:placetype":"postalcode"
},
  "geometry": {"coordinates":[-3.19421574699974,54.13906622005413],"type":"Point"}
}