{
  "type": "Feature",
  "properties": {
    "iso:country":"GB",
    "wof:name":"EX4 1NQ",
    "wof:placetype":"postalcode"
},
  "geometry": {"coordinates":[-3.55430820179215,50.7155198098692],"type":"Point"}
}