{
  "type": "Feature",
  "properties": {
    "date:inception_lower":"1987-04-01",
    "date:inception_upper":"1987-04-30",
    "iso:country":"GB",
    "wof:name":"TR11 5EL",
    "wof:placetype":"postalcode"
},
  "geometry": {"coordinates":[-5.104363,50.146596],"type":"Point"}
}