{
  "type": "Feature",
  "properties": {
    "iso:country":"GB",
    "wof:name":"TR11 5EL",
    "wof:placetype":"postalcode"
},
  "geometry": {"coordinates":[-5.10434384339707,50.14660758604512],"type":"Point"}
}