{
  "type": "Feature",
  "properties": {
    "date:inception_lower": "2006-09-01",
    "date:inception_upper": "2006-09-01",
    "iso:country": "GB",
    "wof:name": "CB25 9BJ",
    "wof:placetype": "postalcode"
  },
  "geometry": {"coordinates":[0.266487,52.220899],"type":"Point"}
}
