{
  "type": "Feature",
  "properties": {
    "iso:country":"GB",
    "wof:name":"CB25 9BJ",
    "wof:placetype":"postalcode"
},
  "geometry": {"coordinates":[0.26648720790449,52.22089932747595],"type":"Point"}
}