{
  "type": "Feature",
  "properties": {
    "iso:country": "GB",
    "wof:name": "BH31 6HE",
    "wof:placetype": "postalcode"
  },
  "geometry": {"coordinates":[-1.87145,50.870621],"type":"Point"}
}
