{
  "type": "Feature",
  "properties": {
    "iso:country":"GB",
    "wof:name":"BH31 6HE",
    "wof:placetype":"postalcode"
},
  "geometry": {"coordinates":[-1.87145006665441,50.87062074772366],"type":"Point"}
}