{
  "type": "Feature",
  "properties": {
    "iso:country":"GB",
    "wof:name":"TW15 3AH",
    "wof:placetype":"postalcode"
},
  "geometry": {"coordinates":[-0.47016085555028,51.44285435748756],"type":"Point"}
}