{
  "type": "Feature",
  "properties": {
    "date:inception_lower":"1980-01-01",
    "date:inception_upper":"1980-01-31",
    "iso:country":"GB",
    "wof:name":"TA11 7NL",
    "wof:placetype":"postalcode"
},
  "geometry": {"coordinates":[-2.726591,51.053223],"type":"Point"}
}