{
  "type": "Feature",
  "properties": {
    "iso:country": "GB",
    "wof:name": "SG12 7RP",
    "wof:placetype": "postalcode"
  },
  "geometry": {"coordinates":[0.021529,51.822607],"type":"Point"}
}
