{
  "type": "Feature",
  "properties": {
    "iso:country":"GB",
    "wof:name":"SG12 7RP",
    "wof:placetype":"postalcode"
},
  "geometry": {"coordinates":[0.02152879590868,51.8226071398913],"type":"Point"}
}