{
  "type": "Feature",
  "properties": {
    "date:inception_lower": "1980-01-01",
    "date:inception_upper": "1980-01-01",
    "iso:country": "GB",
    "wof:name": "SG12 7RP",
    "wof:placetype": "postalcode"
  },
  "geometry": {"coordinates":[0.021529,51.822607],"type":"Point"}
}
