{
  "type": "Feature",
  "properties": {
    "iso:country":"GB",
    "wof:name":"SW2 3LF",
    "wof:placetype":"postalcode"
},
  "geometry": {"coordinates":[-0.10649423651258,51.43933382997783],"type":"Point"}
}