{
  "type": "Feature",
  "properties": {
    "date:inception_lower": "2019-05-01",
    "date:inception_upper": "2019-05-01",
    "iso:country": "GB",
    "wof:name": "BS39 6YW",
    "wof:placetype": "postalcode"
  },
  "geometry": {"coordinates":[-2.521964,51.312123],"type":"Point"}
}
