{
  "type": "Feature",
  "properties": {
    "iso:country": "GB",
    "wof:name": "FK8 1ZR",
    "wof:placetype": "postalcode"
  },
  "geometry": {"coordinates":[-3.961787,56.136605],"type":"Point"}
}
