{
  "type": "Feature",
  "properties": {
    "iso:country":"GB",
    "wof:name":"PA5 9QS",
    "wof:placetype":"postalcode"
},
  "geometry": {"coordinates":[-4.4963318230786,55.82837534051428],"type":"Point"}
}