{
  "type": "Feature",
  "properties": {
    "iso:country":"GB",
    "wof:name":"BH24 1TN",
    "wof:placetype":"postalcode"
},
  "geometry": {"coordinates":[-1.77159150232337,50.85228552251586],"type":"Point"}
}