{
  "type": "Feature",
  "properties": {
    "iso:country":"GB",
    "wof:name":"PO9 4JE",
    "wof:placetype":"postalcode"
},
  "geometry": {"coordinates":[-1.00011866294289,50.87522365480654],"type":"Point"}
}