{
  "type": "Feature",
  "properties": {
    "iso:country": "GB",
    "wof:name": "OX14 4GB",
    "wof:placetype": "postalcode"
  },
  "geometry": {"coordinates":[-1.26255,51.644502],"type":"Point"}
}
