{
  "type": "Feature",
  "properties": {
    "iso:country":"GB",
    "wof:name":"IP1 1TF",
    "wof:placetype":"postalcode"
},
  "geometry": {"coordinates":[1.15344390605366,52.05539503572086],"type":"Point"}
}