{
  "type": "Feature",
  "properties": {
    "iso:country":"GB",
    "wof:name":"PE11 1LS",
    "wof:placetype":"postalcode"
},
  "geometry": {"coordinates":[-0.1703609721385,52.78677473516957],"type":"Point"}
}