{
  "type": "Feature",
  "properties": {
    "date:inception_lower": "1980-01-01",
    "date:inception_upper": "1980-01-01",
    "iso:country": "GB",
    "wof:name": "SO24 9NL",
    "wof:placetype": "postalcode"
  },
  "geometry": {"coordinates":[-1.162161,51.081896],"type":"Point"}
}
