{
  "type": "Feature",
  "properties": {
    "date:inception_lower": "1994-05-01",
    "date:inception_upper": "1994-05-01",
    "iso:country": "GB",
    "wof:name": "M21 9NF",
    "wof:placetype": "postalcode"
  },
  "geometry": {"coordinates":[-2.280972,53.449101],"type":"Point"}
}
