{
  "type": "Feature",
  "properties": {
    "iso:country":"GB",
    "wof:name":"M21 9NF",
    "wof:placetype":"postalcode"
},
  "geometry": {"coordinates":[-2.28097197839682,53.44910051068266],"type":"Point"}
}