{
  "type": "Feature",
  "properties": {
    "iso:country": "GB",
    "wof:name": "BS16 9PW",
    "wof:placetype": "postalcode"
  },
  "geometry": {"coordinates":[-2.436665,51.488486],"type":"Point"}
}
