{
  "type": "Feature",
  "properties": {
    "iso:country":"GB",
    "wof:name":"RG4 7ND",
    "wof:placetype":"postalcode"
},
  "geometry": {"coordinates":[-0.98488248874802,51.48051420778372],"type":"Point"}
}