{
  "type": "Feature",
  "properties": {
    "date:inception_lower":"1980-01-01",
    "date:inception_upper":"1980-01-31",
    "iso:country":"GB",
    "wof:name":"TR11 4SN",
    "wof:placetype":"postalcode"
},
  "geometry": {"coordinates":[-5.095322,50.153659],"type":"Point"}
}