{
  "type": "Feature",
  "properties": {
    "iso:country":"GB",
    "wof:name":"TR11 4SN",
    "wof:placetype":"postalcode"
},
  "geometry": {"coordinates":[-5.09532191170191,50.15365852700224],"type":"Point"}
}