{
  "type": "Feature",
  "properties": {
    "date:inception_lower": "1980-01-01",
    "date:inception_upper": "1980-01-01",
    "iso:country": "GB",
    "wof:name": "HA9 8TF",
    "wof:placetype": "postalcode"
  },
  "geometry": {"coordinates":[-0.299465,51.572513],"type":"Point"}
}
