{
  "type": "Feature",
  "properties": {
    "iso:country":"GB",
    "wof:name":"DD4 7DF",
    "wof:placetype":"postalcode"
},
  "geometry": {"coordinates":[-2.95888415821404,56.47754110070487],"type":"Point"}
}