{
  "type": "Feature",
  "properties": {
    "iso:country": "GB",
    "wof:name": "DD4 7DF",
    "wof:placetype": "postalcode"
  },
  "geometry": {"coordinates":[-2.958888,56.477532],"type":"Point"}
}
