{
  "type": "Feature",
  "properties": {
    "date:inception_lower": "1980-01-01",
    "date:inception_upper": "1980-01-01",
    "iso:country": "GB",
    "wof:name": "DD4 7DF",
    "wof:placetype": "postalcode"
  },
  "geometry": {"coordinates":[-2.958724,56.477461],"type":"Point"}
}
