{
  "type": "Feature",
  "properties": {
    "iso:country": "GB",
    "wof:name": "EN11 8TH",
    "wof:placetype": "postalcode"
  },
  "geometry": {"coordinates":[-0.014874,51.760368],"type":"Point"}
}
