{
  "type": "Feature",
  "properties": {
    "iso:country":"GB",
    "wof:name":"DE56 0RT",
    "wof:placetype":"postalcode"
},
  "geometry": {"coordinates":[-1.47582496372492,52.99596869376855],"type":"Point"}
}