{
  "type": "Feature",
  "properties": {
    "date:inception_lower": "1992-08-01",
    "date:inception_upper": "1992-08-01",
    "iso:country": "GB",
    "wof:name": "DE56 0RT",
    "wof:placetype": "postalcode"
  },
  "geometry": {"coordinates":[-1.475825,52.995969],"type":"Point"}
}
