{
  "type": "Feature",
  "properties": {
    "date:inception_lower": "2024-07-01",
    "date:inception_upper": "2024-07-01",
    "iso:country": "GB",
    "wof:name": "DA2 6GT",
    "wof:placetype": "postalcode"
  },
  "geometry": {"coordinates":[0.249285,51.445942],"type":"Point"}
}
