{
  "type": "Feature",
  "properties": {
    "iso:country":"GB",
    "wof:name":"LD5 4TL",
    "wof:placetype":"postalcode"
},
  "geometry": {"coordinates":[-3.65602022762368,52.11883466515827],"type":"Point"}
}