{
  "type": "Feature",
  "properties": {
    "iso:country": "GB",
    "wof:name": "LD5 4TL",
    "wof:placetype": "postalcode"
  },
  "geometry": {"coordinates":[-3.65602,52.118835],"type":"Point"}
}
