{
  "type": "Feature",
  "properties": {
    "iso:country":"GB",
    "wof:name":"CF48 4JB",
    "wof:placetype":"postalcode"
},
  "geometry": {"coordinates":[-3.34666757451204,51.71521205424985],"type":"Point"}
}