{
  "type": "Feature",
  "properties": {
    "iso:country":"GB",
    "wof:name":"NR9 4RH",
    "wof:placetype":"postalcode"
},
  "geometry": {"coordinates":[0.9946344312783,52.61760094580604],"type":"Point"}
}