{
  "type": "Feature",
  "properties": {
    "iso:country": "GB",
    "wof:name": "NR9 4RH",
    "wof:placetype": "postalcode"
  },
  "geometry": {"coordinates":[0.994634,52.617601],"type":"Point"}
}
