{
  "type": "Feature",
  "properties": {
    "iso:country":"GB",
    "wof:name":"PR8 2AZ",
    "wof:placetype":"postalcode"
},
  "geometry": {"coordinates":[-3.02200394838603,53.63686905998862],"type":"Point"}
}