{
  "type": "Feature",
  "properties": {
    "iso:country": "GB",
    "wof:name": "ME7 4AG",
    "wof:placetype": "postalcode"
  },
  "geometry": {"coordinates":[0.555157,51.373974],"type":"Point"}
}
