{
  "type": "Feature",
  "properties": {
    "iso:country":"GB",
    "wof:name":"ME7 4AG",
    "wof:placetype":"postalcode"
},
  "geometry": {"coordinates":[0.55515671363622,51.37397395331563],"type":"Point"}
}