{
  "type": "Feature",
  "properties": {
    "date:inception_lower":"1980-01-01",
    "date:inception_upper":"1980-01-31",
    "iso:country":"GB",
    "wof:name":"L23 9XW",
    "wof:placetype":"postalcode"
},
  "geometry": {"coordinates":[-3.009898,53.494024],"type":"Point"}
}