{
  "type": "Feature",
  "properties": {
    "iso:country":"GB",
    "wof:name":"PO16 7RH",
    "wof:placetype":"postalcode"
},
  "geometry": {"coordinates":[-1.19511271673287,50.86253136305659],"type":"Point"}
}