{
  "type": "Feature",
  "properties": {
    "iso:country":"GB",
    "wof:name":"W8 7QR",
    "wof:placetype":"postalcode"
},
  "geometry": {"coordinates":[-0.19848058319588,51.50258908893147],"type":"Point"}
}