{
  "type": "Feature",
  "properties": {
    "date:inception_lower": "1980-01-01",
    "date:inception_upper": "1980-01-01",
    "iso:country": "GB",
    "wof:name": "WN2 4XA",
    "wof:placetype": "postalcode"
  },
  "geometry": {"coordinates":[-2.555194,53.532129],"type":"Point"}
}
