{
  "type": "Feature",
  "properties": {
    "iso:country":"GB",
    "wof:name":"WN2 4XA",
    "wof:placetype":"postalcode"
},
  "geometry": {"coordinates":[-2.55519357326327,53.53212925978632],"type":"Point"}
}