{
  "type": "Feature",
  "properties": {
    "date:inception_lower":"1980-01-01",
    "date:inception_upper":"1980-01-31",
    "iso:country":"GB",
    "wof:name":"PH1 3PL",
    "wof:placetype":"postalcode"
},
  "geometry": {"coordinates":[-3.575596,56.417504],"type":"Point"}
}