{
  "type": "Feature",
  "properties": {
    "iso:country": "GB",
    "wof:name": "PH1 3PL",
    "wof:placetype": "postalcode"
  },
  "geometry": {"coordinates":[-3.575596,56.417504],"type":"Point"}
}
