{
  "type": "Feature",
  "properties": {
    "date:inception_lower":"1980-01-01",
    "date:inception_upper":"1980-01-31",
    "iso:country":"GB",
    "wof:name":"LN12 1PB",
    "wof:placetype":"postalcode"
},
  "geometry": {"coordinates":[0.209451,53.362344],"type":"Point"}
}