{
  "type": "Feature",
  "properties": {
    "iso:country": "GB",
    "wof:name": "LN12 1PB",
    "wof:placetype": "postalcode"
  },
  "geometry": {"coordinates":[0.209451,53.362344],"type":"Point"}
}
