{
  "type": "Feature",
  "properties": {
    "iso:country":"GB",
    "wof:name":"LN12 1PB",
    "wof:placetype":"postalcode"
},
  "geometry": {"coordinates":[0.20945091096257,53.36234438096683],"type":"Point"}
}