{
  "type": "Feature",
  "properties": {
    "iso:country":"GB",
    "wof:name":"EC1N 2JT",
    "wof:placetype":"postalcode"
},
  "geometry": {"coordinates":[-0.11015884321652,51.5174846181996],"type":"Point"}
}