{
  "type": "Feature",
  "properties": {
    "iso:country":"GB",
    "wof:name":"NN16 9PW",
    "wof:placetype":"postalcode"
},
  "geometry": {"coordinates":[-0.71542956335287,52.41063221320229],"type":"Point"}
}