{
  "type": "Feature",
  "properties": {
    "date:inception_lower":"1983-07-01",
    "date:inception_upper":"1983-07-31",
    "iso:country":"GB",
    "wof:name":"PE5 7BY",
    "wof:placetype":"postalcode"
},
  "geometry": {"coordinates":[-0.347225,52.57373],"type":"Point"}
}