{
  "type": "Feature",
  "properties": {
    "iso:country":"GB",
    "wof:name":"PE5 7BY",
    "wof:placetype":"postalcode"
},
  "geometry": {"coordinates":[-0.34722480035367,52.57372980013882],"type":"Point"}
}