{
  "type": "Feature",
  "properties": {
    "date:inception_lower": "2023-01-01",
    "date:inception_upper": "2023-01-01",
    "iso:country": "GB",
    "wof:name": "CV6 6NJ",
    "wof:placetype": "postalcode"
  },
  "geometry": {"coordinates":[-1.502299,52.441103],"type":"Point"}
}
