{
  "type": "Feature",
  "properties": {
    "iso:country":"GB",
    "wof:name":"TW7 5AF",
    "wof:placetype":"postalcode"
},
  "geometry": {"coordinates":[-0.32860784088736,51.47646857987707],"type":"Point"}
}