{
  "type": "Feature",
  "properties": {
    "iso:country": "GB",
    "wof:name": "TW7 5AF",
    "wof:placetype": "postalcode"
  },
  "geometry": {"coordinates":[-0.328608,51.476469],"type":"Point"}
}
