{
  "type": "Feature",
  "properties": {
    "iso:country": "GB",
    "wof:name": "LS29 7RH",
    "wof:placetype": "postalcode"
  },
  "geometry": {"coordinates":[-1.744993,53.906792],"type":"Point"}
}
