{
  "type": "Feature",
  "properties": {
    "iso:country":"GB",
    "wof:name":"LS29 7RH",
    "wof:placetype":"postalcode"
},
  "geometry": {"coordinates":[-1.7449930115967,53.90679223845456],"type":"Point"}
}