{
  "type": "Feature",
  "properties": {
    "iso:country": "GB",
    "wof:name": "GU26 6PD",
    "wof:placetype": "postalcode"
  },
  "geometry": {"coordinates":[-0.75519,51.122056],"type":"Point"}
}
