{
  "type": "Feature",
  "properties": {
    "iso:country":"GB",
    "wof:name":"EH13 9DN",
    "wof:placetype":"postalcode"
},
  "geometry": {"coordinates":[-3.2347565740293,55.90877619953204],"type":"Point"}
}