{
  "type": "Feature",
  "properties": {
    "iso:country":"GB",
    "wof:name":"KW12 6UP",
    "wof:placetype":"postalcode"
},
  "geometry": {"coordinates":[-3.49592540971842,58.4207427933075],"type":"Point"}
}