{
  "type": "Feature",
  "properties": {
    "iso:country":"GB",
    "wof:name":"BN21 4UP",
    "wof:placetype":"postalcode"
},
  "geometry": {"coordinates":[0.27996114690258,50.76655931220184],"type":"Point"}
}