{
  "type": "Feature",
  "properties": {
    "date:inception_lower":"1980-01-01",
    "date:inception_upper":"1980-01-31",
    "iso:country":"GB",
    "wof:name":"N15 5AX",
    "wof:placetype":"postalcode"
},
  "geometry": {"coordinates":[-0.08779,51.58283],"type":"Point"}
}