{
  "type": "Feature",
  "properties": {
    "iso:country":"GB",
    "wof:name":"N15 5AX",
    "wof:placetype":"postalcode"
},
  "geometry": {"coordinates":[-0.08778954184287,51.58283038373377],"type":"Point"}
}