{
  "type": "Feature",
  "properties": {
    "iso:country":"GB",
    "wof:name":"S5 9NT",
    "wof:placetype":"postalcode"
},
  "geometry": {"coordinates":[-1.48152816967288,53.43180460372326],"type":"Point"}
}