{
  "type": "Feature",
  "properties": {
    "date:inception_lower":"1980-01-01",
    "date:inception_upper":"1980-01-31",
    "iso:country":"GB",
    "wof:name":"PE13 4EL",
    "wof:placetype":"postalcode"
},
  "geometry": {"coordinates":[0.068991,52.630963],"type":"Point"}
}