{
  "type": "Feature",
  "properties": {
    "iso:country": "GB",
    "wof:name": "PE13 4EL",
    "wof:placetype": "postalcode"
  },
  "geometry": {"coordinates":[0.068991,52.630963],"type":"Point"}
}
