{
  "type": "Feature",
  "properties": {
    "iso:country":"GB",
    "wof:name":"PE13 4EL",
    "wof:placetype":"postalcode"
},
  "geometry": {"coordinates":[0.06899109417049,52.63096312662799],"type":"Point"}
}