{
  "type": "Feature",
  "properties": {
    "iso:country": "GB",
    "wof:name": "TF10 9LW",
    "wof:placetype": "postalcode"
  },
  "geometry": {"coordinates":[-2.376303,52.756941],"type":"Point"}
}
