{
  "type": "Feature",
  "properties": {
    "date:inception_lower": "1980-01-01",
    "date:inception_upper": "1980-01-01",
    "iso:country": "GB",
    "wof:name": "NR30 5ST",
    "wof:placetype": "postalcode"
  },
  "geometry": {"coordinates":[1.692167,52.64328],"type":"Point"}
}
