{
  "type": "Feature",
  "properties": {
    "iso:country":"GB",
    "wof:name":"SK14 1DG",
    "wof:placetype":"postalcode"
},
  "geometry": {"coordinates":[-2.08193387514417,53.45007736928735],"type":"Point"}
}