{
  "type": "Feature",
  "properties": {
    "iso:country": "GB",
    "wof:name": "SK14 1DG",
    "wof:placetype": "postalcode"
  },
  "geometry": {"coordinates":[-2.081934,53.450077],"type":"Point"}
}
