{
  "type": "Feature",
  "properties": {
    "date:inception_lower":"1983-03-01",
    "date:inception_upper":"1983-03-31",
    "iso:country":"GB",
    "wof:name":"PE14 7TB",
    "wof:placetype":"postalcode"
},
  "geometry": {"coordinates":[0.275994,52.703801],"type":"Point"}
}