{
  "type": "Feature",
  "properties": {
    "iso:country":"GB",
    "wof:name":"PE14 7TB",
    "wof:placetype":"postalcode"
},
  "geometry": {"coordinates":[0.27599399555416,52.70380117971539],"type":"Point"}
}