{
  "type": "Feature",
  "properties": {
    "iso:country":"GB",
    "wof:name":"CV8 3PA",
    "wof:placetype":"postalcode"
},
  "geometry": {"coordinates":[-1.40434963410873,52.37407039457695],"type":"Point"}
}