{
  "type": "Feature",
  "properties": {
    "date:inception_lower": "1999-12-01",
    "date:inception_upper": "1999-12-01",
    "iso:country": "GB",
    "wof:name": "CV8 3PA",
    "wof:placetype": "postalcode"
  },
  "geometry": {"coordinates":[-1.40435,52.37407],"type":"Point"}
}
