{
  "type": "Feature",
  "properties": {
    "iso:country":"GB",
    "wof:name":"LE9 8DY",
    "wof:placetype":"postalcode"
},
  "geometry": {"coordinates":[-1.35486894844989,52.5609491929942],"type":"Point"}
}