{
  "type": "Feature",
  "properties": {
    "iso:country":"GB",
    "wof:name":"CA26 3SJ",
    "wof:placetype":"postalcode"
},
  "geometry": {"coordinates":[-3.49666876690477,54.54139096188577],"type":"Point"}
}