{
  "type": "Feature",
  "properties": {
    "date:inception_lower": "1980-01-01",
    "date:inception_upper": "1980-01-01",
    "iso:country": "GB",
    "wof:name": "CA26 3SJ",
    "wof:placetype": "postalcode"
  },
  "geometry": {"coordinates":[-3.496669,54.541391],"type":"Point"}
}
