{
  "type": "Feature",
  "properties": {
    "iso:country":"GB",
    "wof:name":"LS7 3PU",
    "wof:placetype":"postalcode"
},
  "geometry": {"coordinates":[-1.5397518110908,53.83446670188852],"type":"Point"}
}