{
  "type": "Feature",
  "properties": {
    "iso:country": "GB",
    "wof:name": "CV35 7TT",
    "wof:placetype": "postalcode"
  },
  "geometry": {"coordinates":[-1.634346,52.301483],"type":"Point"}
}
