{
  "type": "Feature",
  "properties": {
    "iso:country": "GB",
    "wof:name": "ME13 0NH",
    "wof:placetype": "postalcode"
  },
  "geometry": {"coordinates":[0.88034,51.272062],"type":"Point"}
}
