{
  "type": "Feature",
  "properties": {
    "iso:country":"GB",
    "wof:name":"ME13 0NH",
    "wof:placetype":"postalcode"
},
  "geometry": {"coordinates":[0.88032359340402,51.27205986351089],"type":"Point"}
}