{
  "type": "Feature",
  "properties": {
    "date:inception_lower": "1980-01-01",
    "date:inception_upper": "1980-01-01",
    "iso:country": "GB",
    "wof:name": "EN9 2SQ",
    "wof:placetype": "postalcode"
  },
  "geometry": {"coordinates":[0.041217,51.726549],"type":"Point"}
}
