{
  "type": "Feature",
  "properties": {
    "iso:country":"GB",
    "wof:name":"EN9 2SQ",
    "wof:placetype":"postalcode"
},
  "geometry": {"coordinates":[0.04108745224348,51.72683320347079],"type":"Point"}
}