{
  "type": "Feature",
  "properties": {
    "date:inception_lower": "2010-04-01",
    "date:inception_upper": "2010-04-01",
    "iso:country": "GB",
    "wof:name": "PL2 1EN",
    "wof:placetype": "postalcode"
  },
  "geometry": {"coordinates":[-4.168953,50.386273],"type":"Point"}
}
