{
  "type": "Feature",
  "properties": {
    "iso:country":"GB",
    "wof:name":"PL2 1EN",
    "wof:placetype":"postalcode"
},
  "geometry": {"coordinates":[-4.16895316634869,50.38627262736541],"type":"Point"}
}