{
  "type": "Feature",
  "properties": {
    "date:inception_lower":"1980-01-01",
    "date:inception_upper":"1980-01-31",
    "iso:country":"GB",
    "wof:name":"N3 1HJ",
    "wof:placetype":"postalcode"
},
  "geometry": {"coordinates":[-0.197065,51.602275],"type":"Point"}
}