{
  "type": "Feature",
  "properties": {
    "iso:country":"GB",
    "wof:name":"N3 1HJ",
    "wof:placetype":"postalcode"
},
  "geometry": {"coordinates":[-0.19706500942071,51.60227493756639],"type":"Point"}
}