{
  "type": "Feature",
  "properties": {
    "iso:country": "GB",
    "wof:name": "N3 1HJ",
    "wof:placetype": "postalcode"
  },
  "geometry": {"coordinates":[-0.197065,51.602275],"type":"Point"}
}
