{
  "type": "Feature",
  "properties": {
    "iso:country":"GB",
    "wof:name":"WA9 1EP",
    "wof:placetype":"postalcode"
},
  "geometry": {"coordinates":[-2.71750588911578,53.45586859281168],"type":"Point"}
}