{
  "type": "Feature",
  "properties": {
    "iso:country": "GB",
    "wof:name": "WA9 1EP",
    "wof:placetype": "postalcode"
  },
  "geometry": {"coordinates":[-2.717506,53.455869],"type":"Point"}
}
