{
  "type": "Feature",
  "properties": {
    "date:inception_lower": "2008-06-01",
    "date:inception_upper": "2008-06-01",
    "iso:country": "GB",
    "wof:name": "CV3 1JW",
    "wof:placetype": "postalcode"
  },
  "geometry": {"coordinates":[-1.480981,52.396727],"type":"Point"}
}
