{
  "type": "Feature",
  "properties": {
    "iso:country": "GB",
    "wof:name": "TQ7 4NQ",
    "wof:placetype": "postalcode"
  },
  "geometry": {"coordinates":[-3.856388,50.318975],"type":"Point"}
}
