{
  "type": "Feature",
  "properties": {
    "iso:country":"GB",
    "wof:name":"TQ7 4NQ",
    "wof:placetype":"postalcode"
},
  "geometry": {"coordinates":[-3.85638761768133,50.31897492559084],"type":"Point"}
}