{
  "type": "Feature",
  "properties": {
    "iso:country": "GB",
    "wof:name": "BN2 9NJ",
    "wof:placetype": "postalcode"
  },
  "geometry": {"coordinates":[-0.13234,50.827089],"type":"Point"}
}
