{
  "type": "Feature",
  "properties": {
    "iso:country":"GB",
    "wof:name":"BN2 9NJ",
    "wof:placetype":"postalcode"
},
  "geometry": {"coordinates":[-0.13233966972871,50.82708855661787],"type":"Point"}
}