{
  "type": "Feature",
  "properties": {
    "date:inception_lower":"2001-12-01",
    "date:inception_upper":"2001-12-31",
    "iso:country":"GB",
    "wof:name":"BN2 9NJ",
    "wof:placetype":"postalcode"
},
  "geometry": {"coordinates":[-0.13234,50.827089],"type":"Point"}
}