{
  "type": "Feature",
  "properties": {
    "date:inception_lower": "2008-01-01",
    "date:inception_upper": "2008-01-01",
    "iso:country": "GB",
    "wof:name": "NP7 9FD",
    "wof:placetype": "postalcode"
  },
  "geometry": {"coordinates":[-3.029871,51.81163],"type":"Point"}
}
