{
  "type": "Feature",
  "properties": {
    "date:inception_lower": "1985-04-01",
    "date:inception_upper": "1985-04-01",
    "iso:country": "GB",
    "wof:name": "TA1 2NH",
    "wof:placetype": "postalcode"
  },
  "geometry": {"coordinates":[-3.073198,51.01649],"type":"Point"}
}
