{
  "type": "Feature",
  "properties": {
    "iso:country":"GB",
    "wof:name":"TA1 2NH",
    "wof:placetype":"postalcode"
},
  "geometry": {"coordinates":[-3.07319756448305,51.01648976203731],"type":"Point"}
}