{
  "type": "Feature",
  "properties": {
    "iso:country":"GB",
    "wof:name":"CF24 2EP",
    "wof:placetype":"postalcode"
},
  "geometry": {"coordinates":[-3.14939922302628,51.480223167106],"type":"Point"}
}