{
  "type": "Feature",
  "properties": {
    "date:inception_lower":"2004-11-01",
    "date:inception_upper":"2004-11-30",
    "iso:country":"GB",
    "wof:name":"CF24 2EP",
    "wof:placetype":"postalcode"
},
  "geometry": {"coordinates":[-3.149408,51.480224],"type":"Point"}
}