{
  "type": "Feature",
  "properties": {
    "date:inception_lower": "2011-10-01",
    "date:inception_upper": "2011-10-01",
    "iso:country": "GB",
    "wof:name": "KA18 1LS",
    "wof:placetype": "postalcode"
  },
  "geometry": {"coordinates":[-4.258257,55.448009],"type":"Point"}
}
