{
  "type": "Feature",
  "properties": {
    "date:inception_lower": "1993-01-01",
    "date:inception_upper": "1993-01-01",
    "iso:country": "GB",
    "wof:name": "NG13 8LY",
    "wof:placetype": "postalcode"
  },
  "geometry": {"coordinates":[-0.963663,52.982064],"type":"Point"}
}
