{
  "type": "Feature",
  "properties": {
    "iso:country":"GB",
    "wof:name":"NG13 8LY",
    "wof:placetype":"postalcode"
},
  "geometry": {"coordinates":[-0.9636634127485,52.98206422941081],"type":"Point"}
}