{
  "type": "Feature",
  "properties": {
    "iso:country": "GB",
    "wof:name": "OX13 6DJ",
    "wof:placetype": "postalcode"
  },
  "geometry": {"coordinates":[-1.352244,51.623936],"type":"Point"}
}
