{
  "type": "Feature",
  "properties": {
    "iso:country":"GB",
    "wof:name":"OX13 6DJ",
    "wof:placetype":"postalcode"
},
  "geometry": {"coordinates":[-1.35333248787627,51.62280698181043],"type":"Point"}
}