{
  "type": "Feature",
  "properties": {
    "iso:country":"GB",
    "wof:name":"CA22 2LU",
    "wof:placetype":"postalcode"
},
  "geometry": {"coordinates":[-3.53489186426637,54.48029723897743],"type":"Point"}
}