{
  "type": "Feature",
  "properties": {
    "iso:country": "GB",
    "wof:name": "CR3 6EU",
    "wof:placetype": "postalcode"
  },
  "geometry": {"coordinates":[-0.084676,51.276929],"type":"Point"}
}
