{
  "type": "Feature",
  "properties": {
    "date:inception_lower": "1995-01-01",
    "date:inception_upper": "1995-01-01",
    "iso:country": "GB",
    "wof:name": "AL7 3BN",
    "wof:placetype": "postalcode"
  },
  "geometry": {"coordinates":[-0.205962,51.794673],"type":"Point"}
}
