{
  "type": "Feature",
  "properties": {
    "iso:country":"GB",
    "wof:name":"AL7 3BN",
    "wof:placetype":"postalcode"
},
  "geometry": {"coordinates":[-0.20596238106815,51.79467295927462],"type":"Point"}
}