{
  "type": "Feature",
  "properties": {
    "iso:country":"GB",
    "wof:name":"SG5 4NJ",
    "wof:placetype":"postalcode"
},
  "geometry": {"coordinates":[-0.22793466390426,52.01290603191548],"type":"Point"}
}