{
  "type": "Feature",
  "properties": {
    "date:inception_lower": "1990-07-01",
    "date:inception_upper": "1990-07-01",
    "iso:country": "GB",
    "wof:name": "SG5 4NJ",
    "wof:placetype": "postalcode"
  },
  "geometry": {"coordinates":[-0.227935,52.012906],"type":"Point"}
}
