{
  "type": "Feature",
  "properties": {
    "iso:country":"GB",
    "wof:name":"LN6 5UG",
    "wof:placetype":"postalcode"
},
  "geometry": {"coordinates":[-0.62110273236714,53.23622165279064],"type":"Point"}
}