{
  "type": "Feature",
  "properties": {
    "date:inception_lower": "1992-01-01",
    "date:inception_upper": "1992-01-01",
    "iso:country": "GB",
    "wof:name": "LN6 5UG",
    "wof:placetype": "postalcode"
  },
  "geometry": {"coordinates":[-0.621103,53.236222],"type":"Point"}
}
