{
  "type": "Feature",
  "properties": {
    "date:inception_lower": "2018-09-01",
    "date:inception_upper": "2018-09-01",
    "iso:country": "GB",
    "wof:name": "DL6 2BZ",
    "wof:placetype": "postalcode"
  },
  "geometry": {"coordinates":[-1.430725,54.352598],"type":"Point"}
}
