{
  "type": "Feature",
  "properties": {
    "iso:country":"GB",
    "wof:name":"HA5 2NW",
    "wof:placetype":"postalcode"
},
  "geometry": {"coordinates":[-0.41508183479416,51.59431580944052],"type":"Point"}
}