{
  "type": "Feature",
  "properties": {
    "iso:country":"GB",
    "wof:name":"RG31 4XQ",
    "wof:placetype":"postalcode"
},
  "geometry": {"coordinates":[-1.04929427685133,51.44247912080782],"type":"Point"}
}