{
  "type": "Feature",
  "properties": {
    "iso:country":"GB",
    "wof:name":"S10 2QD",
    "wof:placetype":"postalcode"
},
  "geometry": {"coordinates":[-1.49959397342211,53.37627782580788],"type":"Point"}
}