{
  "type": "Feature",
  "properties": {
    "date:inception_lower": "1980-01-01",
    "date:inception_upper": "1980-01-01",
    "iso:country": "GB",
    "wof:name": "LL67 0NH",
    "wof:placetype": "postalcode"
  },
  "geometry": {"coordinates":[-4.449704,53.412892],"type":"Point"}
}
