{
  "type": "Feature",
  "properties": {
    "iso:country":"GB",
    "wof:name":"LL67 0NH",
    "wof:placetype":"postalcode"
},
  "geometry": {"coordinates":[-4.4497044489795,53.41289195391417],"type":"Point"}
}