{
  "type": "Feature",
  "properties": {
    "iso:country": "GB",
    "wof:name": "WR1 2AG",
    "wof:placetype": "postalcode"
  },
  "geometry": {"coordinates":[-2.218155,52.19149],"type":"Point"}
}
