{
  "type": "Feature",
  "properties": {
    "date:inception_lower":"1980-01-01",
    "date:inception_upper":"1980-01-31",
    "iso:country":"GB",
    "wof:name":"PL23 1PX",
    "wof:placetype":"postalcode"
},
  "geometry": {"coordinates":[-4.635423,50.328519],"type":"Point"}
}