{
  "type": "Feature",
  "properties": {
    "iso:country":"GB",
    "wof:name":"PL23 1PX",
    "wof:placetype":"postalcode"
},
  "geometry": {"coordinates":[-4.63542256970054,50.328518727785],"type":"Point"}
}