{
  "type": "Feature",
  "properties": {
    "iso:country":"GB",
    "wof:name":"SW19 5AP",
    "wof:placetype":"postalcode"
},
  "geometry": {"coordinates":[-0.21870588543108,51.42505904425764],"type":"Point"}
}