{
  "type": "Feature",
  "properties": {
    "iso:country":"GB",
    "wof:name":"NN4 8NL",
    "wof:placetype":"postalcode"
},
  "geometry": {"coordinates":[-0.90243484883016,52.22208545724023],"type":"Point"}
}