{
  "type": "Feature",
  "properties": {
    "iso:country": "GB",
    "wof:name": "BD13 2BT",
    "wof:placetype": "postalcode"
  },
  "geometry": {"coordinates":[-1.862029,53.763078],"type":"Point"}
}
