{
  "type": "Feature",
  "properties": {
    "iso:country": "GB",
    "wof:name": "NN13 5SN",
    "wof:placetype": "postalcode"
  },
  "geometry": {"coordinates":[-1.1526,51.976441],"type":"Point"}
}
