{
  "type": "Feature",
  "properties": {
    "iso:country":"GB",
    "wof:name":"NN13 5SN",
    "wof:placetype":"postalcode"
},
  "geometry": {"coordinates":[-1.15260044886498,51.9764412168992],"type":"Point"}
}