{
  "type": "Feature",
  "properties": {
    "iso:country": "GB",
    "wof:name": "WD19 4QH",
    "wof:placetype": "postalcode"
  },
  "geometry": {"coordinates":[-0.388546,51.644877],"type":"Point"}
}
