{
  "type": "Feature",
  "properties": {
    "iso:country":"GB",
    "wof:name":"WD19 4QH",
    "wof:placetype":"postalcode"
},
  "geometry": {"coordinates":[-0.38854645640431,51.644876727113],"type":"Point"}
}