{
  "type": "Feature",
  "properties": {
    "iso:country":"GB",
    "wof:name":"GU51 5SU",
    "wof:placetype":"postalcode"
},
  "geometry": {"coordinates":[-0.8660787319403,51.26117982343631],"type":"Point"}
}