{
  "type": "Feature",
  "properties": {
    "iso:country":"GB",
    "wof:name":"KA1 1SY",
    "wof:placetype":"postalcode"
},
  "geometry": {"coordinates":[-4.50290572561273,55.60060579645794],"type":"Point"}
}