{
  "type": "Feature",
  "properties": {
    "date:inception_lower": "2009-06-01",
    "date:inception_upper": "2009-06-01",
    "iso:country": "GB",
    "wof:name": "LE3 9GZ",
    "wof:placetype": "postalcode"
  },
  "geometry": {"coordinates":[-1.18234,52.648436],"type":"Point"}
}
