{
  "type": "Feature",
  "properties": {
    "date:inception_lower": "2022-09-01",
    "date:inception_upper": "2022-09-01",
    "iso:country": "GB",
    "wof:name": "E3 3ZD",
    "wof:placetype": "postalcode"
  },
  "geometry": {"coordinates":[-0.010781,51.525052],"type":"Point"}
}
