{
  "type": "Feature",
  "properties": {
    "iso:country":"GB",
    "wof:name":"CV37 6HB",
    "wof:placetype":"postalcode"
},
  "geometry": {"coordinates":[-1.70888633197474,52.18969747263751],"type":"Point"}
}