{
  "type": "Feature",
  "properties": {
    "iso:country":"GB",
    "wof:name":"RG22 6RN",
    "wof:placetype":"postalcode"
},
  "geometry": {"coordinates":[-1.12141275423873,51.25453482328276],"type":"Point"}
}