{
  "type": "Feature",
  "properties": {
    "iso:country": "GB",
    "wof:name": "RG22 6RN",
    "wof:placetype": "postalcode"
  },
  "geometry": {"coordinates":[-1.121395,51.254534],"type":"Point"}
}
