{
  "type": "Feature",
  "properties": {
    "iso:country":"GB",
    "wof:name":"PE28 3EL",
    "wof:placetype":"postalcode"
},
  "geometry": {"coordinates":[-0.00576474132805,52.38362622936121],"type":"Point"}
}