{
  "type": "Feature",
  "properties": {
    "iso:country":"GB",
    "wof:name":"HP19 7WA",
    "wof:placetype":"postalcode"
},
  "geometry": {"coordinates":[-0.83617728908503,51.81602354783067],"type":"Point"}
}