{
  "type": "Feature",
  "properties": {
    "date:inception_lower": "2005-10-01",
    "date:inception_upper": "2005-10-01",
    "iso:country": "GB",
    "wof:name": "HP19 7WA",
    "wof:placetype": "postalcode"
  },
  "geometry": {"coordinates":[-0.83614,51.81603],"type":"Point"}
}
