{
  "type": "Feature",
  "properties": {
    "iso:country":"GB",
    "wof:name":"B44 0AU",
    "wof:placetype":"postalcode"
},
  "geometry": {"coordinates":[-1.86632297787182,52.54235796257706],"type":"Point"}
}