{
  "type": "Feature",
  "properties": {
    "iso:country":"GB",
    "wof:name":"DT4 0NF",
    "wof:placetype":"postalcode"
},
  "geometry": {"coordinates":[-2.47285503774347,50.61290092091276],"type":"Point"}
}