{
  "type": "Feature",
  "properties": {
    "date:inception_lower": "1980-01-01",
    "date:inception_upper": "1980-01-01",
    "iso:country": "GB",
    "wof:name": "DT4 0NF",
    "wof:placetype": "postalcode"
  },
  "geometry": {"coordinates":[-2.472855,50.612901],"type":"Point"}
}
