{
  "type": "Feature",
  "properties": {
    "date:inception_lower":"2002-06-01",
    "date:inception_upper":"2002-06-30",
    "iso:country":"GB",
    "wof:name":"GL11 5GF",
    "wof:placetype":"postalcode"
},
  "geometry": {"coordinates":[-2.341094,51.677804],"type":"Point"}
}