{
  "type": "Feature",
  "properties": {
    "iso:country":"GB",
    "wof:name":"IG11 9PH",
    "wof:placetype":"postalcode"
},
  "geometry": {"coordinates":[0.09882394012476,51.53941653236086],"type":"Point"}
}