{
  "type": "Feature",
  "properties": {
    "iso:country":"GB",
    "wof:name":"PE8 5DF",
    "wof:placetype":"postalcode"
},
  "geometry": {"coordinates":[-0.49334402349712,52.55016370565078],"type":"Point"}
}