{
  "type": "Feature",
  "properties": {
    "iso:country": "GB",
    "wof:name": "WR2 6AN",
    "wof:placetype": "postalcode"
  },
  "geometry": {"coordinates":[-2.24625,52.196221],"type":"Point"}
}
