{
  "type": "Feature",
  "properties": {
    "iso:country":"GB",
    "wof:name":"SA43 2EF",
    "wof:placetype":"postalcode"
},
  "geometry": {"coordinates":[-4.54027726615329,52.12975447415118],"type":"Point"}
}