{
  "type": "Feature",
  "properties": {
    "iso:country": "GB",
    "wof:name": "SA43 2EF",
    "wof:placetype": "postalcode"
  },
  "geometry": {"coordinates":[-4.540277,52.129754],"type":"Point"}
}
