{
  "type": "Feature",
  "properties": {
    "iso:country":"GB",
    "wof:name":"TS25 2LF",
    "wof:placetype":"postalcode"
},
  "geometry": {"coordinates":[-1.24590347412389,54.65279596509819],"type":"Point"}
}