{
  "type": "Feature",
  "properties": {
    "iso:country": "GB",
    "wof:name": "TS25 2LF",
    "wof:placetype": "postalcode"
  },
  "geometry": {"coordinates":[-1.245903,54.652796],"type":"Point"}
}
