{
  "type": "Feature",
  "properties": {
    "iso:country": "GB",
    "wof:name": "PE14 7BB",
    "wof:placetype": "postalcode"
  },
  "geometry": {"coordinates":[0.207139,52.673975],"type":"Point"}
}
