{
  "type": "Feature",
  "properties": {
    "date:inception_lower": "1980-01-01",
    "date:inception_upper": "1980-01-01",
    "iso:country": "GB",
    "wof:name": "TS21 1BH",
    "wof:placetype": "postalcode"
  },
  "geometry": {"coordinates":[-1.40491,54.569548],"type":"Point"}
}
