{
  "type": "Feature",
  "properties": {
    "iso:country":"GB",
    "wof:name":"TS21 1BH",
    "wof:placetype":"postalcode"
},
  "geometry": {"coordinates":[-1.38904799954316,54.56933198003176],"type":"Point"}
}