{
  "type": "Feature",
  "properties": {
    "date:inception_lower": "1980-01-01",
    "date:inception_upper": "1980-01-01",
    "iso:country": "GB",
    "wof:name": "S61 3JJ",
    "wof:placetype": "postalcode"
  },
  "geometry": {"coordinates":[-1.3923,53.442773],"type":"Point"}
}
