{
  "type": "Feature",
  "properties": {
    "iso:country": "GB",
    "wof:name": "EH4 5JR",
    "wof:placetype": "postalcode"
  },
  "geometry": {"coordinates":[-3.258573,55.974822],"type":"Point"}
}
