{
  "type": "Feature",
  "properties": {
    "iso:country": "GB",
    "wof:name": "TQ11 0AD",
    "wof:placetype": "postalcode"
  },
  "geometry": {"coordinates":[-3.779407,50.481243],"type":"Point"}
}
