{
  "type": "Feature",
  "properties": {
    "iso:country":"GB",
    "wof:name":"HS2 9BL",
    "wof:placetype":"postalcode"
},
  "geometry": {"coordinates":[-6.69187742881933,58.31452614222177],"type":"Point"}
}