{
  "type": "Feature",
  "properties": {
    "iso:country":"GB",
    "wof:name":"CF14 2FT",
    "wof:placetype":"postalcode"
},
  "geometry": {"coordinates":[-3.23187391752221,51.50755732217871],"type":"Point"}
}