{
  "type": "Feature",
  "properties": {
    "iso:country": "GB",
    "wof:name": "CM8 3XX",
    "wof:placetype": "postalcode"
  },
  "geometry": {"coordinates":[0.679144,51.780825],"type":"Point"}
}
