{
  "type": "Feature",
  "properties": {
    "iso:country":"GB",
    "wof:name":"M28 0HJ",
    "wof:placetype":"postalcode"
},
  "geometry": {"coordinates":[-2.41392999842438,53.52368659280005],"type":"Point"}
}