{
  "type": "Feature",
  "properties": {
    "date:inception_lower": "1995-12-01",
    "date:inception_upper": "1995-12-01",
    "iso:country": "GB",
    "wof:name": "M28 0HJ",
    "wof:placetype": "postalcode"
  },
  "geometry": {"coordinates":[-2.41393,53.523687],"type":"Point"}
}
