{
  "type": "Feature",
  "properties": {
    "iso:country":"GB",
    "wof:name":"CM14 4RA",
    "wof:placetype":"postalcode"
},
  "geometry": {"coordinates":[0.28097926309311,51.61529760436682],"type":"Point"}
}