{
  "type": "Feature",
  "properties": {
    "date:inception_lower":"1980-01-01",
    "date:inception_upper":"1980-01-31",
    "iso:country":"GB",
    "wof:name":"CM14 4RA",
    "wof:placetype":"postalcode"
},
  "geometry": {"coordinates":[0.280956,51.615166],"type":"Point"}
}