{
  "type": "Feature",
  "properties": {
    "iso:country": "GB",
    "wof:name": "CM14 4RA",
    "wof:placetype": "postalcode"
  },
  "geometry": {"coordinates":[0.280956,51.615166],"type":"Point"}
}
