{
  "type": "Feature",
  "properties": {
    "date:inception_lower": "1998-12-01",
    "date:inception_upper": "1998-12-01",
    "iso:country": "GB",
    "wof:name": "KY11 9YP",
    "wof:placetype": "postalcode"
  },
  "geometry": {"coordinates":[-3.366355,56.031173],"type":"Point"}
}
