{
  "type": "Feature",
  "properties": {
    "iso:country": "GB",
    "wof:name": "KY11 9YP",
    "wof:placetype": "postalcode"
  },
  "geometry": {"coordinates":[-3.366355,56.031173],"type":"Point"}
}
