{
  "type": "Feature",
  "properties": {
    "iso:country":"GB",
    "wof:name":"PO36 9AB",
    "wof:placetype":"postalcode"
},
  "geometry": {"coordinates":[-1.15717658261265,50.65871160336563],"type":"Point"}
}