{
  "type": "Feature",
  "properties": {
    "iso:country":"GB",
    "wof:name":"EH4 7JE",
    "wof:placetype":"postalcode"
},
  "geometry": {"coordinates":[-3.28890824245963,55.95267312457064],"type":"Point"}
}