{
  "type": "Feature",
  "properties": {
    "date:inception_lower": "1980-01-01",
    "date:inception_upper": "1980-01-01",
    "iso:country": "GB",
    "wof:name": "EH4 7JE",
    "wof:placetype": "postalcode"
  },
  "geometry": {"coordinates":[-3.288908,55.952673],"type":"Point"}
}
