{
  "type": "Feature",
  "properties": {
    "iso:country":"GB",
    "wof:name":"BN15 9TB",
    "wof:placetype":"postalcode"
},
  "geometry": {"coordinates":[-0.3359945067977,50.82969421771408],"type":"Point"}
}