{
  "type": "Feature",
  "properties": {
    "iso:country": "GB",
    "wof:name": "WV6 0TP",
    "wof:placetype": "postalcode"
  },
  "geometry": {"coordinates":[-2.149826,52.599037],"type":"Point"}
}
