{
  "type": "Feature",
  "properties": {
    "iso:country":"GB",
    "wof:name":"WV6 0TP",
    "wof:placetype":"postalcode"
},
  "geometry": {"coordinates":[-2.14982597990556,52.59903683421413],"type":"Point"}
}