{
  "type": "Feature",
  "properties": {
    "iso:country":"GB",
    "wof:name":"TA9 4NN",
    "wof:placetype":"postalcode"
},
  "geometry": {"coordinates":[-2.8882569122016,51.2275714736662],"type":"Point"}
}