{
  "type": "Feature",
  "properties": {
    "iso:country": "GB",
    "wof:name": "TF9 2TZ",
    "wof:placetype": "postalcode"
  },
  "geometry": {"coordinates":[-2.456982,52.834579],"type":"Point"}
}
