{
  "type": "Feature",
  "properties": {
    "date:inception_lower": "1990-02-01",
    "date:inception_upper": "1990-02-01",
    "iso:country": "GB",
    "wof:name": "TF9 2TZ",
    "wof:placetype": "postalcode"
  },
  "geometry": {"coordinates":[-2.456982,52.834579],"type":"Point"}
}
