{
  "type": "Feature",
  "properties": {
    "iso:country":"GB",
    "wof:name":"BA1 2TF",
    "wof:placetype":"postalcode"
},
  "geometry": {"coordinates":[-2.36805539359012,51.39056242063882],"type":"Point"}
}