{
  "type": "Feature",
  "properties": {
    "iso:country": "GB",
    "wof:name": "BA1 2TF",
    "wof:placetype": "postalcode"
  },
  "geometry": {"coordinates":[-2.368055,51.390562],"type":"Point"}
}
