{
  "type": "Feature",
  "properties": {
    "iso:country": "GB",
    "wof:name": "TF4 2GF",
    "wof:placetype": "postalcode"
  },
  "geometry": {"coordinates":[-2.485956,52.673618],"type":"Point"}
}
