{
  "type": "Feature",
  "properties": {
    "iso:country":"GB",
    "wof:name":"TF4 2GF",
    "wof:placetype":"postalcode"
},
  "geometry": {"coordinates":[-2.48592425076254,52.67321696436061],"type":"Point"}
}