{
  "type": "Feature",
  "properties": {
    "iso:country": "GB",
    "wof:name": "RG8 9SR",
    "wof:placetype": "postalcode"
  },
  "geometry": {"coordinates":[-1.171465,51.501844],"type":"Point"}
}
