{
  "type": "Feature",
  "properties": {
    "iso:country":"GB",
    "wof:name":"RG8 9SR",
    "wof:placetype":"postalcode"
},
  "geometry": {"coordinates":[-1.17152954012441,51.50180755543605],"type":"Point"}
}