{
  "type": "Feature",
  "properties": {
    "iso:country":"GB",
    "wof:name":"ML1 3RE",
    "wof:placetype":"postalcode"
},
  "geometry": {"coordinates":[-4.01542390960588,55.79713411243964],"type":"Point"}
}