{
  "type": "Feature",
  "properties": {
    "iso:country":"GB",
    "wof:name":"WA4 4JH",
    "wof:placetype":"postalcode"
},
  "geometry": {"coordinates":[-2.6214843166643,53.31239835941646],"type":"Point"}
}