{
  "type": "Feature",
  "properties": {
    "date:inception_lower": "1999-06-01",
    "date:inception_upper": "1999-06-01",
    "iso:country": "GB",
    "wof:name": "NP11 3EJ",
    "wof:placetype": "postalcode"
  },
  "geometry": {"coordinates":[-3.161483,51.69616],"type":"Point"}
}
