{
  "type": "Feature",
  "properties": {
    "iso:country": "GB",
    "wof:name": "DH9 0QH",
    "wof:placetype": "postalcode"
  },
  "geometry": {"coordinates":[-1.665587,54.873018],"type":"Point"}
}
