{
  "type": "Feature",
  "properties": {
    "iso:country":"GB",
    "wof:name":"DH9 0QH",
    "wof:placetype":"postalcode"
},
  "geometry": {"coordinates":[-1.66558732316305,54.87301793726912],"type":"Point"}
}