{
  "type": "Feature",
  "properties": {
    "iso:country": "GB",
    "wof:name": "S4 7BP",
    "wof:placetype": "postalcode"
  },
  "geometry": {"coordinates":[-1.467834,53.403834],"type":"Point"}
}
