{
  "type": "Feature",
  "properties": {
    "date:inception_lower": "1980-01-01",
    "date:inception_upper": "1980-01-01",
    "iso:country": "GB",
    "wof:name": "WF10 2EP",
    "wof:placetype": "postalcode"
  },
  "geometry": {"coordinates":[-1.383138,53.750641],"type":"Point"}
}
