{
  "type": "Feature",
  "properties": {
    "iso:country":"GB",
    "wof:name":"WF10 2EP",
    "wof:placetype":"postalcode"
},
  "geometry": {"coordinates":[-1.38303015562748,53.75055147407564],"type":"Point"}
}