{
  "type": "Feature",
  "properties": {
    "iso:country":"GB",
    "wof:name":"HR2 0JL",
    "wof:placetype":"postalcode"
},
  "geometry": {"coordinates":[-2.88360434454662,51.95212929696188],"type":"Point"}
}