{
  "type": "Feature",
  "properties": {
    "iso:country": "GB",
    "wof:name": "HR2 0JL",
    "wof:placetype": "postalcode"
  },
  "geometry": {"coordinates":[-2.883604,51.952129],"type":"Point"}
}
