{
  "type": "Feature",
  "properties": {
    "iso:country": "GB",
    "wof:name": "SL1 2XF",
    "wof:placetype": "postalcode"
  },
  "geometry": {"coordinates":[-0.614958,51.511376],"type":"Point"}
}
