{
  "type": "Feature",
  "properties": {
    "iso:country":"GB",
    "wof:name":"SL1 2XF",
    "wof:placetype":"postalcode"
},
  "geometry": {"coordinates":[-0.61495773675033,51.51137558834294],"type":"Point"}
}