{
  "type": "Feature",
  "properties": {
    "date:inception_lower": "2008-03-01",
    "date:inception_upper": "2008-03-01",
    "iso:country": "GB",
    "wof:name": "NG17 9GU",
    "wof:placetype": "postalcode"
  },
  "geometry": {"coordinates":[-1.272728,53.089226],"type":"Point"}
}
