{
  "type": "Feature",
  "properties": {
    "iso:country": "GB",
    "wof:name": "CM7 5RQ",
    "wof:placetype": "postalcode"
  },
  "geometry": {"coordinates":[0.547329,51.892581],"type":"Point"}
}
