{
  "type": "Feature",
  "properties": {
    "iso:country":"GB",
    "wof:name":"CM7 5RQ",
    "wof:placetype":"postalcode"
},
  "geometry": {"coordinates":[0.54732875836548,51.89258080915434],"type":"Point"}
}