{
  "type": "Feature",
  "properties": {
    "iso:country":"GB",
    "wof:name":"SS9 5SZ",
    "wof:placetype":"postalcode"
},
  "geometry": {"coordinates":[0.66732777102322,51.56968468929899],"type":"Point"}
}