{
  "type": "Feature",
  "properties": {
    "iso:country":"GB",
    "wof:name":"RG7 1WR",
    "wof:placetype":"postalcode"
},
  "geometry": {"coordinates":[-0.9750220721579,51.40512153879467],"type":"Point"}
}