{
  "type": "Feature",
  "properties": {
    "iso:country": "GB",
    "wof:name": "HD8 0BE",
    "wof:placetype": "postalcode"
  },
  "geometry": {"coordinates":[-1.724545,53.64098],"type":"Point"}
}
