{
  "type": "Feature",
  "properties": {
    "iso:country":"GB",
    "wof:name":"TS14 6TA",
    "wof:placetype":"postalcode"
},
  "geometry": {"coordinates":[-1.05841616115542,54.53975582491574],"type":"Point"}
}