{
  "type": "Feature",
  "properties": {
    "date:inception_lower": "1981-06-01",
    "date:inception_upper": "1981-06-01",
    "iso:country": "GB",
    "wof:name": "MK41 0PY",
    "wof:placetype": "postalcode"
  },
  "geometry": {"coordinates":[-0.422156,52.151117],"type":"Point"}
}
