{
  "type": "Feature",
  "properties": {
    "iso:country":"GB",
    "wof:name":"MK41 0PY",
    "wof:placetype":"postalcode"
},
  "geometry": {"coordinates":[-0.42219219037134,52.15110550843239],"type":"Point"}
}