{
  "type": "Feature",
  "properties": {
    "iso:country":"GB",
    "wof:name":"KT3 5NG",
    "wof:placetype":"postalcode"
},
  "geometry": {"coordinates":[-0.26285232276642,51.38707178904908],"type":"Point"}
}