{
  "type": "Feature",
  "properties": {
    "iso:country": "GB",
    "wof:name": "SO40 4PB",
    "wof:placetype": "postalcode"
  },
  "geometry": {"coordinates":[-1.445895,50.893693],"type":"Point"}
}
