{
  "type": "Feature",
  "properties": {
    "iso:country": "GB",
    "wof:name": "TQ2 7AD",
    "wof:placetype": "postalcode"
  },
  "geometry": {"coordinates":[-3.554651,50.484499],"type":"Point"}
}
