{
  "type": "Feature",
  "properties": {
    "iso:country":"GB",
    "wof:name":"TQ2 7AD",
    "wof:placetype":"postalcode"
},
  "geometry": {"coordinates":[-3.55465080282731,50.48449925946889],"type":"Point"}
}