{
  "type": "Feature",
  "properties": {
    "iso:country":"GB",
    "wof:name":"BA5 3RF",
    "wof:placetype":"postalcode"
},
  "geometry": {"coordinates":[-2.59160469249239,51.1983082798144],"type":"Point"}
}