{
  "type": "Feature",
  "properties": {
    "date:inception_lower":"1980-01-01",
    "date:inception_upper":"1980-01-31",
    "iso:country":"GB",
    "wof:name":"S3 7RF",
    "wof:placetype":"postalcode"
},
  "geometry": {"coordinates":[-1.484855,53.380656],"type":"Point"}
}