{
  "type": "Feature",
  "properties": {
    "iso:country":"GB",
    "wof:name":"S3 7RF",
    "wof:placetype":"postalcode"
},
  "geometry": {"coordinates":[-1.48485533526272,53.38065558399391],"type":"Point"}
}