{
  "type": "Feature",
  "properties": {
    "iso:country":"GB",
    "wof:name":"TS19 8NE",
    "wof:placetype":"postalcode"
},
  "geometry": {"coordinates":[-1.35834294525679,54.58525082473819],"type":"Point"}
}