{
  "type": "Feature",
  "properties": {
    "iso:country": "GB",
    "wof:name": "FK20 8QP",
    "wof:placetype": "postalcode"
  },
  "geometry": {"coordinates":[-4.617718,56.392332],"type":"Point"}
}
