{
  "type": "Feature",
  "properties": {
    "iso:country":"GB",
    "wof:name":"TR26 2FD",
    "wof:placetype":"postalcode"
},
  "geometry": {"coordinates":[-5.47924622695175,50.20868781063638],"type":"Point"}
}