{
  "type": "Feature",
  "properties": {
    "iso:country":"GB",
    "wof:name":"EN9 3NB",
    "wof:placetype":"postalcode"
},
  "geometry": {"coordinates":[0.02570723564713,51.6823979401677],"type":"Point"}
}