{
  "type": "Feature",
  "properties": {
    "date:inception_lower":"1992-01-01",
    "date:inception_upper":"1992-01-31",
    "iso:country":"GB",
    "wof:name":"EN9 3NB",
    "wof:placetype":"postalcode"
},
  "geometry": {"coordinates":[0.025707,51.682398],"type":"Point"}
}