{
  "type": "Feature",
  "properties": {
    "iso:country":"GB",
    "wof:name":"DG2 0DF",
    "wof:placetype":"postalcode"
},
  "geometry": {"coordinates":[-3.62095262482542,55.08262449916077],"type":"Point"}
}