{
  "type": "Feature",
  "properties": {
    "date:inception_lower": "1992-08-01",
    "date:inception_upper": "1992-08-01",
    "iso:country": "GB",
    "wof:name": "BA1 3HZ",
    "wof:placetype": "postalcode"
  },
  "geometry": {"coordinates":[-2.40359,51.386507],"type":"Point"}
}
