{
  "type": "Feature",
  "properties": {
    "date:inception_lower": "1980-01-01",
    "date:inception_upper": "1980-01-01",
    "iso:country": "GB",
    "wof:name": "HU8 9DB",
    "wof:placetype": "postalcode"
  },
  "geometry": {"coordinates":[-0.282928,53.770593],"type":"Point"}
}
