{
  "type": "Feature",
  "properties": {
    "iso:country":"GB",
    "wof:name":"HU8 9DB",
    "wof:placetype":"postalcode"
},
  "geometry": {"coordinates":[-0.28292828637537,53.77059342559738],"type":"Point"}
}