{
  "type": "Feature",
  "properties": {
    "date:inception_lower": "1980-01-01",
    "date:inception_upper": "1980-01-01",
    "iso:country": "GB",
    "wof:name": "ML3 6UH",
    "wof:placetype": "postalcode"
  },
  "geometry": {"coordinates":[-4.048109,55.769111],"type":"Point"}
}
