{
  "type": "Feature",
  "properties": {
    "iso:country": "GB",
    "wof:name": "KY12 7JE",
    "wof:placetype": "postalcode"
  },
  "geometry": {"coordinates":[-3.456541,56.071614],"type":"Point"}
}
