{
  "type": "Feature",
  "properties": {
    "iso:country":"GB",
    "wof:name":"KY12 7JE",
    "wof:placetype":"postalcode"
},
  "geometry": {"coordinates":[-3.45654542178045,56.07161864961279],"type":"Point"}
}