{
  "type": "Feature",
  "properties": {
    "iso:country":"GB",
    "wof:name":"S66 2DH",
    "wof:placetype":"postalcode"
},
  "geometry": {"coordinates":[-1.29174824657117,53.42268674923604],"type":"Point"}
}