{
  "type": "Feature",
  "properties": {
    "iso:country": "GB",
    "wof:name": "SO24 9SB",
    "wof:placetype": "postalcode"
  },
  "geometry": {"coordinates":[-1.099829,51.173891],"type":"Point"}
}
