{
  "type": "Feature",
  "properties": {
    "date:inception_lower": "1980-01-01",
    "date:inception_upper": "1980-01-01",
    "iso:country": "GB",
    "wof:name": "PO12 2SP",
    "wof:placetype": "postalcode"
  },
  "geometry": {"coordinates":[-1.165509,50.791173],"type":"Point"}
}
