{
  "type": "Feature",
  "properties": {
    "date:inception_lower":"1980-01-01",
    "date:inception_upper":"1980-01-31",
    "iso:country":"GB",
    "wof:name":"SR1 1QB",
    "wof:placetype":"postalcode"
},
  "geometry": {"coordinates":[-1.381404,54.904066],"type":"Point"}
}