{
  "type": "Feature",
  "properties": {
    "iso:country":"GB",
    "wof:name":"PL35 0HP",
    "wof:placetype":"postalcode"
},
  "geometry": {"coordinates":[-4.63338164768145,50.68322150614617],"type":"Point"}
}