{
  "type": "Feature",
  "properties": {
    "iso:country": "GB",
    "wof:name": "PL35 0HP",
    "wof:placetype": "postalcode"
  },
  "geometry": {"coordinates":[-4.633382,50.683222],"type":"Point"}
}
