{
  "type": "Feature",
  "properties": {
    "iso:country":"GB",
    "wof:name":"SK2 6JH",
    "wof:placetype":"postalcode"
},
  "geometry": {"coordinates":[-2.15432455631681,53.39462728795139],"type":"Point"}
}