{
  "type": "Feature",
  "properties": {
    "iso:country": "GB",
    "wof:name": "SK2 6JH",
    "wof:placetype": "postalcode"
  },
  "geometry": {"coordinates":[-2.154325,53.394627],"type":"Point"}
}
