{
  "type": "Feature",
  "properties": {
    "iso:country":"GB",
    "wof:name":"CM23 5PP",
    "wof:placetype":"postalcode"
},
  "geometry": {"coordinates":[0.17519762319226,51.88364815313438],"type":"Point"}
}