{
  "type": "Feature",
  "properties": {
    "iso:country":"GB",
    "wof:name":"GL4 4NR",
    "wof:placetype":"postalcode"
},
  "geometry": {"coordinates":[-2.21839523125394,51.85201962891903],"type":"Point"}
}