{
  "type": "Feature",
  "properties": {
    "iso:country":"GB",
    "wof:name":"NG33 4PT",
    "wof:placetype":"postalcode"
},
  "geometry": {"coordinates":[-0.49673296832684,52.75241234245469],"type":"Point"}
}