{
  "type": "Feature",
  "properties": {
    "iso:country": "GB",
    "wof:name": "NG33 4PT",
    "wof:placetype": "postalcode"
  },
  "geometry": {"coordinates":[-0.496733,52.752412],"type":"Point"}
}
