{
  "type": "Feature",
  "properties": {
    "iso:country": "GB",
    "wof:name": "SS8 9XQ",
    "wof:placetype": "postalcode"
  },
  "geometry": {"coordinates":[0.584477,51.528731],"type":"Point"}
}
