{
  "type": "Feature",
  "properties": {
    "iso:country":"GB",
    "wof:name":"SS8 9XQ",
    "wof:placetype":"postalcode"
},
  "geometry": {"coordinates":[0.58447655091673,51.52873060407838],"type":"Point"}
}