{
  "type": "Feature",
  "properties": {
    "iso:country":"GB",
    "wof:name":"S17 4PN",
    "wof:placetype":"postalcode"
},
  "geometry": {"coordinates":[-1.51110104508316,53.31909423733821],"type":"Point"}
}