{
  "type": "Feature",
  "properties": {
    "iso:country": "GB",
    "wof:name": "SS9 2NL",
    "wof:placetype": "postalcode"
  },
  "geometry": {"coordinates":[0.637581,51.54371],"type":"Point"}
}
