{
  "type": "Feature",
  "properties": {
    "iso:country":"GB",
    "wof:name":"SS9 2NL",
    "wof:placetype":"postalcode"
},
  "geometry": {"coordinates":[0.63758123654007,51.54370952433047],"type":"Point"}
}