{
  "type": "Feature",
  "properties": {
    "iso:country":"GB",
    "wof:name":"G83 8NX",
    "wof:placetype":"postalcode"
},
  "geometry": {"coordinates":[-4.64452406509093,56.09680461890093],"type":"Point"}
}