{
  "type": "Feature",
  "properties": {
    "date:inception_lower":"1980-01-01",
    "date:inception_upper":"1980-01-31",
    "iso:country":"GB",
    "wof:name":"G83 8NX",
    "wof:placetype":"postalcode"
},
  "geometry": {"coordinates":[-4.644524,56.096805],"type":"Point"}
}