{
  "type": "Feature",
  "properties": {
    "iso:country":"GB",
    "wof:name":"EN1 3QD",
    "wof:placetype":"postalcode"
},
  "geometry": {"coordinates":[-0.05272147222895,51.65926517049382],"type":"Point"}
}