{
  "type": "Feature",
  "properties": {
    "iso:country": "GB",
    "wof:name": "EN1 3QD",
    "wof:placetype": "postalcode"
  },
  "geometry": {"coordinates":[-0.052721,51.659265],"type":"Point"}
}
