{
  "type": "Feature",
  "properties": {
    "iso:country":"GB",
    "wof:name":"W10 5BE",
    "wof:placetype":"postalcode"
},
  "geometry": {"coordinates":[-0.21084690441307,51.52640149349407],"type":"Point"}
}