{
  "type": "Feature",
  "properties": {
    "iso:country": "GB",
    "wof:name": "W10 5BE",
    "wof:placetype": "postalcode"
  },
  "geometry": {"coordinates":[-0.210847,51.526401],"type":"Point"}
}
