{
  "type": "Feature",
  "properties": {
    "date:inception_lower":"1997-06-01",
    "date:inception_upper":"1997-06-30",
    "iso:country":"GB",
    "wof:name":"BS16 7BQ",
    "wof:placetype":"postalcode"
},
  "geometry": {"coordinates":[-2.487132,51.503313],"type":"Point"}
}