{
  "type": "Feature",
  "properties": {
    "iso:country":"GB",
    "wof:name":"BS16 7BQ",
    "wof:placetype":"postalcode"
},
  "geometry": {"coordinates":[-2.48711781631314,51.5033142385543],"type":"Point"}
}