{
  "type": "Feature",
  "properties": {
    "iso:country": "GB",
    "wof:name": "GL20 8HR",
    "wof:placetype": "postalcode"
  },
  "geometry": {"coordinates":[-2.097488,52.019941],"type":"Point"}
}
