{
  "type": "Feature",
  "properties": {
    "date:inception_lower": "1992-08-01",
    "date:inception_upper": "1992-08-01",
    "iso:country": "GB",
    "wof:name": "DE24 9HQ",
    "wof:placetype": "postalcode"
  },
  "geometry": {"coordinates":[-1.48813,52.884752],"type":"Point"}
}
