{
  "type": "Feature",
  "properties": {
    "iso:country":"GB",
    "wof:name":"DE24 9HQ",
    "wof:placetype":"postalcode"
},
  "geometry": {"coordinates":[-1.48828307302899,52.88471676405519],"type":"Point"}
}