{
  "type": "Feature",
  "properties": {
    "iso:country": "GB",
    "wof:name": "RG17 0DT",
    "wof:placetype": "postalcode"
  },
  "geometry": {"coordinates":[-1.514299,51.413658],"type":"Point"}
}
