{
  "type": "Feature",
  "properties": {
    "date:inception_lower": "1986-07-01",
    "date:inception_upper": "1986-07-01",
    "iso:country": "GB",
    "wof:name": "RG17 0DT",
    "wof:placetype": "postalcode"
  },
  "geometry": {"coordinates":[-1.514299,51.413658],"type":"Point"}
}
