{
  "type": "Feature",
  "properties": {
    "iso:country": "GB",
    "wof:name": "KT17 4AS",
    "wof:placetype": "postalcode"
  },
  "geometry": {"coordinates":[-0.255446,51.338815],"type":"Point"}
}
