{
  "type": "Feature",
  "properties": {
    "iso:country":"GB",
    "wof:name":"GL12 7LQ",
    "wof:placetype":"postalcode"
},
  "geometry": {"coordinates":[-2.34778179380039,51.63327752386726],"type":"Point"}
}