{
  "type": "Feature",
  "properties": {
    "iso:country": "GB",
    "wof:name": "GL12 7LQ",
    "wof:placetype": "postalcode"
  },
  "geometry": {"coordinates":[-2.347782,51.633278],"type":"Point"}
}
