{
  "type": "Feature",
  "properties": {
    "iso:country": "GB",
    "wof:name": "DE4 3RW",
    "wof:placetype": "postalcode"
  },
  "geometry": {"coordinates":[-1.549832,53.144601],"type":"Point"}
}
