{
  "type": "Feature",
  "properties": {
    "iso:country":"GB",
    "wof:name":"DE4 3RW",
    "wof:placetype":"postalcode"
},
  "geometry": {"coordinates":[-1.54983216974196,53.14460142919375],"type":"Point"}
}