{
  "type": "Feature",
  "properties": {
    "date:inception_lower": "2021-11-01",
    "date:inception_upper": "2021-11-01",
    "iso:country": "GB",
    "wof:name": "BN6 9QQ",
    "wof:placetype": "postalcode"
  },
  "geometry": {"coordinates":[-0.1494,50.934242],"type":"Point"}
}
