{
  "type": "Feature",
  "properties": {
    "iso:country":"GB",
    "wof:name":"TN27 0BS",
    "wof:placetype":"postalcode"
},
  "geometry": {"coordinates":[0.74414773305763,51.20341615708621],"type":"Point"}
}