{
  "type": "Feature",
  "properties": {
    "date:inception_lower": "1980-01-01",
    "date:inception_upper": "1980-01-01",
    "iso:country": "GB",
    "wof:name": "DL8 1JP",
    "wof:placetype": "postalcode"
  },
  "geometry": {"coordinates":[-1.668157,54.311178],"type":"Point"}
}
