{
  "type": "Feature",
  "properties": {
    "iso:country":"GB",
    "wof:name":"DL8 1JP",
    "wof:placetype":"postalcode"
},
  "geometry": {"coordinates":[-1.66815681813586,54.3111784842799],"type":"Point"}
}