{
  "type": "Feature",
  "properties": {
    "iso:country": "GB",
    "wof:name": "YO51 9HS",
    "wof:placetype": "postalcode"
  },
  "geometry": {"coordinates":[-1.397397,54.088065],"type":"Point"}
}
