{
  "type": "Feature",
  "properties": {
    "iso:country":"GB",
    "wof:name":"NE4 8TT",
    "wof:placetype":"postalcode"
},
  "geometry": {"coordinates":[-1.65643491442577,54.97257885657955],"type":"Point"}
}