{
  "type": "Feature",
  "properties": {
    "iso:country":"GB",
    "wof:name":"G14 0XT",
    "wof:placetype":"postalcode"
},
  "geometry": {"coordinates":[-4.36107862067849,55.88624960961203],"type":"Point"}
}