{
  "type": "Feature",
  "properties": {
    "iso:country":"GB",
    "wof:name":"DE5 3RW",
    "wof:placetype":"postalcode"
},
  "geometry": {"coordinates":[-1.41495374815187,53.04507192740073],"type":"Point"}
}