{
  "type": "Feature",
  "properties": {
    "date:inception_lower": "1980-01-01",
    "date:inception_upper": "1980-01-01",
    "iso:country": "GB",
    "wof:name": "DE5 3RW",
    "wof:placetype": "postalcode"
  },
  "geometry": {"coordinates":[-1.414954,53.045072],"type":"Point"}
}
