{
  "type": "Feature",
  "properties": {
    "iso:country":"GB",
    "wof:name":"YO11 3AB",
    "wof:placetype":"postalcode"
},
  "geometry": {"coordinates":[-0.38915035631987,54.26153066174031],"type":"Point"}
}