{
  "type": "Feature",
  "properties": {
    "iso:country":"GB",
    "wof:name":"SA8 4NG",
    "wof:placetype":"postalcode"
},
  "geometry": {"coordinates":[-3.85870693615802,51.73046303406841],"type":"Point"}
}