{
  "type": "Feature",
  "properties": {
    "date:inception_lower": "1981-06-01",
    "date:inception_upper": "1981-06-01",
    "iso:country": "GB",
    "wof:name": "SA8 4NG",
    "wof:placetype": "postalcode"
  },
  "geometry": {"coordinates":[-3.858707,51.730463],"type":"Point"}
}
