{
  "type": "Feature",
  "properties": {
    "iso:country":"GB",
    "wof:name":"BA3 4TQ",
    "wof:placetype":"postalcode"
},
  "geometry": {"coordinates":[-2.54179775760682,51.24088386410391],"type":"Point"}
}