{
  "type": "Feature",
  "properties": {
    "iso:country":"GB",
    "wof:name":"DE74 2LE",
    "wof:placetype":"postalcode"
},
  "geometry": {"coordinates":[-1.33638154324168,52.84230804073852],"type":"Point"}
}