{
  "type": "Feature",
  "properties": {
    "iso:country":"GB",
    "wof:name":"LN5 0RR",
    "wof:placetype":"postalcode"
},
  "geometry": {"coordinates":[-0.69396882326446,53.07255083352746],"type":"Point"}
}