{
  "type": "Feature",
  "properties": {
    "iso:country":"GB",
    "wof:name":"TS12 1ED",
    "wof:placetype":"postalcode"
},
  "geometry": {"coordinates":[-0.97523893273654,54.58500495192455],"type":"Point"}
}