{
  "type": "Feature",
  "properties": {
    "iso:country": "GB",
    "wof:name": "TS12 1ED",
    "wof:placetype": "postalcode"
  },
  "geometry": {"coordinates":[-0.975239,54.585005],"type":"Point"}
}
