{
  "type": "Feature",
  "properties": {
    "iso:country":"GB",
    "wof:name":"LL53 8EY",
    "wof:placetype":"postalcode"
},
  "geometry": {"coordinates":[-4.61372859991527,52.8475640497078],"type":"Point"}
}