{
  "type": "Feature",
  "properties": {
    "iso:country":"GB",
    "wof:name":"GL6 8GZ",
    "wof:placetype":"postalcode"
},
  "geometry": {"coordinates":[-2.16199169036772,51.73081304934929],"type":"Point"}
}