{
  "type": "Feature",
  "properties": {
    "date:inception_lower": "2002-06-01",
    "date:inception_upper": "2002-06-01",
    "iso:country": "GB",
    "wof:name": "GL6 8GZ",
    "wof:placetype": "postalcode"
  },
  "geometry": {"coordinates":[-2.161992,51.730813],"type":"Point"}
}
