{
  "type": "Feature",
  "properties": {
    "iso:country":"GB",
    "wof:name":"BN25 4EJ",
    "wof:placetype":"postalcode"
},
  "geometry": {"coordinates":[0.12708276587078,50.76909774122458],"type":"Point"}
}