{
  "type": "Feature",
  "properties": {
    "iso:country":"GB",
    "wof:name":"LL75 8LJ",
    "wof:placetype":"postalcode"
},
  "geometry": {"coordinates":[-4.21815862208045,53.28669696263852],"type":"Point"}
}