{
  "type": "Feature",
  "properties": {
    "iso:country": "GB",
    "wof:name": "LL75 8LJ",
    "wof:placetype": "postalcode"
  },
  "geometry": {"coordinates":[-4.218159,53.286697],"type":"Point"}
}
