{
  "type": "Feature",
  "properties": {
    "date:inception_lower": "1994-05-01",
    "date:inception_upper": "1994-05-01",
    "iso:country": "GB",
    "wof:name": "M26 3TP",
    "wof:placetype": "postalcode"
  },
  "geometry": {"coordinates":[-2.340955,53.568652],"type":"Point"}
}
