{
  "type": "Feature",
  "properties": {
    "iso:country":"GB",
    "wof:name":"M26 3TP",
    "wof:placetype":"postalcode"
},
  "geometry": {"coordinates":[-2.34095488448627,53.56865228529669],"type":"Point"}
}