{
  "type": "Feature",
  "properties": {
    "iso:country":"GB",
    "wof:name":"BR5 1RP",
    "wof:placetype":"postalcode"
},
  "geometry": {"coordinates":[0.06843401890218,51.38456927481935],"type":"Point"}
}