{
  "type": "Feature",
  "properties": {
    "iso:country": "GB",
    "wof:name": "EX19 8NB",
    "wof:placetype": "postalcode"
  },
  "geometry": {"coordinates":[-4.050025,50.909828],"type":"Point"}
}
