{
  "type": "Feature",
  "properties": {
    "iso:country":"GB",
    "wof:name":"EX19 8NB",
    "wof:placetype":"postalcode"
},
  "geometry": {"coordinates":[-4.05047444410463,50.91086949035808],"type":"Point"}
}