{
  "type": "Feature",
  "properties": {
    "iso:country":"GB",
    "wof:name":"S17 3EW",
    "wof:placetype":"postalcode"
},
  "geometry": {"coordinates":[-1.54783522288584,53.33034912361001],"type":"Point"}
}