{
  "type": "Feature",
  "properties": {
    "iso:country": "GB",
    "wof:name": "S17 3EW",
    "wof:placetype": "postalcode"
  },
  "geometry": {"coordinates":[-1.547835,53.330349],"type":"Point"}
}
