{
  "type": "Feature",
  "properties": {
    "iso:country":"GB",
    "wof:name":"LS14 5AF",
    "wof:placetype":"postalcode"
},
  "geometry": {"coordinates":[-1.45348129325933,53.81753998738047],"type":"Point"}
}