{
  "type": "Feature",
  "properties": {
    "iso:country": "GB",
    "wof:name": "AL5 3LZ",
    "wof:placetype": "postalcode"
  },
  "geometry": {"coordinates":[-0.378579,51.830063],"type":"Point"}
}
