{
  "type": "Feature",
  "properties": {
    "iso:country":"GB",
    "wof:name":"AL5 3LZ",
    "wof:placetype":"postalcode"
},
  "geometry": {"coordinates":[-0.37857858673487,51.83006326306095],"type":"Point"}
}