{
  "type": "Feature",
  "properties": {
    "iso:country": "GB",
    "wof:name": "SG6 2BB",
    "wof:placetype": "postalcode"
  },
  "geometry": {"coordinates":[-0.205733,51.966919],"type":"Point"}
}
