{
  "type": "Feature",
  "properties": {
    "iso:country":"GB",
    "wof:name":"SG6 2BB",
    "wof:placetype":"postalcode"
},
  "geometry": {"coordinates":[-0.2057737043691,51.96691933743665],"type":"Point"}
}