{
  "type": "Feature",
  "properties": {
    "date:inception_lower": "1999-12-01",
    "date:inception_upper": "1999-12-01",
    "iso:country": "GB",
    "wof:name": "GL3 2EQ",
    "wof:placetype": "postalcode"
  },
  "geometry": {"coordinates":[-2.166407,51.8762],"type":"Point"}
}
