{
  "type": "Feature",
  "properties": {
    "iso:country":"GB",
    "wof:name":"SL5 0QU",
    "wof:placetype":"postalcode"
},
  "geometry": {"coordinates":[-0.63614899206454,51.39616528880151],"type":"Point"}
}