{
  "type": "Feature",
  "properties": {
    "iso:country": "GB",
    "wof:name": "SL5 0QU",
    "wof:placetype": "postalcode"
  },
  "geometry": {"coordinates":[-0.636149,51.396165],"type":"Point"}
}
