{
  "type": "Feature",
  "properties": {
    "iso:country":"GB",
    "wof:name":"WA3 2DP",
    "wof:placetype":"postalcode"
},
  "geometry": {"coordinates":[-2.58347821653875,53.47594202384676],"type":"Point"}
}