{
  "type": "Feature",
  "properties": {
    "iso:country":"GB",
    "wof:name":"LL34 6LU",
    "wof:placetype":"postalcode"
},
  "geometry": {"coordinates":[-3.93017907364055,53.26835119745381],"type":"Point"}
}