{
  "type": "Feature",
  "properties": {
    "date:inception_lower": "1980-01-01",
    "date:inception_upper": "1980-01-01",
    "iso:country": "GB",
    "wof:name": "W6 7HQ",
    "wof:placetype": "postalcode"
  },
  "geometry": {"coordinates":[-0.227984,51.50124],"type":"Point"}
}
