{
  "type": "Feature",
  "properties": {
    "iso:country":"GB",
    "wof:name":"G66 8AB",
    "wof:placetype":"postalcode"
},
  "geometry": {"coordinates":[-4.14515683288717,55.96397832167347],"type":"Point"}
}