{
  "type": "Feature",
  "properties": {
    "iso:country": "GB",
    "wof:name": "G66 8AB",
    "wof:placetype": "postalcode"
  },
  "geometry": {"coordinates":[-4.145157,55.963978],"type":"Point"}
}
