{
  "type": "Feature",
  "properties": {
    "iso:country":"GB",
    "wof:name":"GU10 4TY",
    "wof:placetype":"postalcode"
},
  "geometry": {"coordinates":[-0.81496575545336,51.18831261140074],"type":"Point"}
}