{
  "type": "Feature",
  "properties": {
    "date:inception_lower": "1981-06-01",
    "date:inception_upper": "1981-06-01",
    "iso:country": "GB",
    "wof:name": "GU10 4TY",
    "wof:placetype": "postalcode"
  },
  "geometry": {"coordinates":[-0.814966,51.188313],"type":"Point"}
}
