{
  "type": "Feature",
  "properties": {
    "iso:country": "GB",
    "wof:name": "GU10 4TY",
    "wof:placetype": "postalcode"
  },
  "geometry": {"coordinates":[-0.814966,51.188313],"type":"Point"}
}
