{
  "type": "Feature",
  "properties": {
    "iso:country": "GB",
    "wof:name": "IP17 2JZ",
    "wof:placetype": "postalcode"
  },
  "geometry": {"coordinates":[1.477275,52.280745],"type":"Point"}
}
