{
  "type": "Feature",
  "properties": {
    "iso:country":"GB",
    "wof:name":"IP17 2JZ",
    "wof:placetype":"postalcode"
},
  "geometry": {"coordinates":[1.47727495766714,52.28074537137933],"type":"Point"}
}