{
  "type": "Feature",
  "properties": {
    "iso:country":"GB",
    "wof:name":"HP19 9JW",
    "wof:placetype":"postalcode"
},
  "geometry": {"coordinates":[-0.83000927921021,51.82731850443579],"type":"Point"}
}