{
  "type": "Feature",
  "properties": {
    "iso:country": "GB",
    "wof:name": "IP13 7GZ",
    "wof:placetype": "postalcode"
  },
  "geometry": {"coordinates":[1.315729,52.195483],"type":"Point"}
}
