{
  "type": "Feature",
  "properties": {
    "date:inception_lower": "2018-09-01",
    "date:inception_upper": "2018-09-01",
    "iso:country": "GB",
    "wof:name": "LA4 5QY",
    "wof:placetype": "postalcode"
  },
  "geometry": {"coordinates":[-2.858412,54.074119],"type":"Point"}
}
