{
  "type": "Feature",
  "properties": {
    "iso:country":"GB",
    "wof:name":"BA2 1HA",
    "wof:placetype":"postalcode"
},
  "geometry": {"coordinates":[-2.39303502288978,51.37563597043416],"type":"Point"}
}