{
  "type": "Feature",
  "properties": {
    "iso:country": "GB",
    "wof:name": "BA2 1HA",
    "wof:placetype": "postalcode"
  },
  "geometry": {"coordinates":[-2.393035,51.375636],"type":"Point"}
}
