{
  "type": "Feature",
  "properties": {
    "date:inception_lower":"1997-12-01",
    "date:inception_upper":"1997-12-31",
    "iso:country":"GB",
    "wof:name":"BA2 1HA",
    "wof:placetype":"postalcode"
},
  "geometry": {"coordinates":[-2.393035,51.375636],"type":"Point"}
}