{
  "type": "Feature",
  "properties": {
    "date:inception_lower":"1994-05-01",
    "date:inception_upper":"1994-05-31",
    "iso:country":"GB",
    "wof:name":"M33 4NU",
    "wof:placetype":"postalcode"
},
  "geometry": {"coordinates":[-2.352567,53.412507],"type":"Point"}
}