{
  "type": "Feature",
  "properties": {
    "iso:country": "GB",
    "wof:name": "GU35 0XU",
    "wof:placetype": "postalcode"
  },
  "geometry": {"coordinates":[-0.853983,51.106502],"type":"Point"}
}
