{
  "type": "Feature",
  "properties": {
    "date:inception_lower": "1992-01-01",
    "date:inception_upper": "1992-01-01",
    "iso:country": "GB",
    "wof:name": "GU35 0XU",
    "wof:placetype": "postalcode"
  },
  "geometry": {"coordinates":[-0.853983,51.106502],"type":"Point"}
}
