{
  "type": "Feature",
  "properties": {
    "iso:country":"GB",
    "wof:name":"GU35 0XU",
    "wof:placetype":"postalcode"
},
  "geometry": {"coordinates":[-0.85398315820295,51.10650179589162],"type":"Point"}
}