{
  "type": "Feature",
  "properties": {
    "date:inception_lower": "2021-08-01",
    "date:inception_upper": "2021-08-01",
    "iso:country": "GB",
    "wof:name": "CV2 1WE",
    "wof:placetype": "postalcode"
  },
  "geometry": {"coordinates":[-1.469565,52.442373],"type":"Point"}
}
