{
  "type": "Feature",
  "properties": {
    "iso:country":"GB",
    "wof:name":"WN7 5ND",
    "wof:placetype":"postalcode"
},
  "geometry": {"coordinates":[-2.52752385758092,53.51144624512498],"type":"Point"}
}