{
  "type": "Feature",
  "properties": {
    "date:inception_lower":"1980-01-01",
    "date:inception_upper":"1980-01-31",
    "iso:country":"GB",
    "wof:name":"EH22 4HX",
    "wof:placetype":"postalcode"
},
  "geometry": {"coordinates":[-3.053166,55.886005],"type":"Point"}
}