{
  "type": "Feature",
  "properties": {
    "iso:country":"GB",
    "wof:name":"EH22 4HX",
    "wof:placetype":"postalcode"
},
  "geometry": {"coordinates":[-3.05316567734001,55.8860050856085],"type":"Point"}
}