{
  "type": "Feature",
  "properties": {
    "iso:country":"GB",
    "wof:name":"WS15 4BS",
    "wof:placetype":"postalcode"
},
  "geometry": {"coordinates":[-1.87982959223165,52.74223175505921],"type":"Point"}
}