{
  "type": "Feature",
  "properties": {
    "date:inception_lower": "1980-01-01",
    "date:inception_upper": "1980-01-01",
    "iso:country": "GB",
    "wof:name": "WS15 4BS",
    "wof:placetype": "postalcode"
  },
  "geometry": {"coordinates":[-1.87983,52.742232],"type":"Point"}
}
