{
  "type": "Feature",
  "properties": {
    "date:inception_lower": "2024-04-01",
    "date:inception_upper": "2024-04-01",
    "iso:country": "GB",
    "wof:name": "LS15 0FH",
    "wof:placetype": "postalcode"
  },
  "geometry": {"coordinates":[-1.479152,53.794463],"type":"Point"}
}
