{
  "type": "Feature",
  "properties": {
    "iso:country":"GB",
    "wof:name":"YO23 1LX",
    "wof:placetype":"postalcode"
},
  "geometry": {"coordinates":[-1.08541650445595,53.94232013225224],"type":"Point"}
}