{
  "type": "Feature",
  "properties": {
    "iso:country":"GB",
    "wof:name":"B78 1ND",
    "wof:placetype":"postalcode"
},
  "geometry": {"coordinates":[-1.60764041470197,52.6114193142586],"type":"Point"}
}