{
  "type": "Feature",
  "properties": {
    "iso:country": "GB",
    "wof:name": "EX16 5PR",
    "wof:placetype": "postalcode"
  },
  "geometry": {"coordinates":[-3.497563,50.891306],"type":"Point"}
}
