{
  "type": "Feature",
  "properties": {
    "iso:country": "GB",
    "wof:name": "WR9 0HU",
    "wof:placetype": "postalcode"
  },
  "geometry": {"coordinates":[-2.262564,52.283249],"type":"Point"}
}
