{
  "type": "Feature",
  "properties": {
    "iso:country":"GB",
    "wof:name":"SE6 4QU",
    "wof:placetype":"postalcode"
},
  "geometry": {"coordinates":[-0.02263632000211,51.44931598413529],"type":"Point"}
}