{
  "type": "Feature",
  "properties": {
    "date:inception_lower":"1980-01-01",
    "date:inception_upper":"1980-01-31",
    "iso:country":"GB",
    "wof:name":"SN7 7RA",
    "wof:placetype":"postalcode"
},
  "geometry": {"coordinates":[-1.56229,51.602363],"type":"Point"}
}