{
  "type": "Feature",
  "properties": {
    "iso:country": "GB",
    "wof:name": "SN7 7RA",
    "wof:placetype": "postalcode"
  },
  "geometry": {"coordinates":[-1.56229,51.602363],"type":"Point"}
}
