{
  "type": "Feature",
  "properties": {
    "iso:country":"GB",
    "wof:name":"SN7 7RA",
    "wof:placetype":"postalcode"
},
  "geometry": {"coordinates":[-1.56229048138352,51.60236300691763],"type":"Point"}
}