{
  "type": "Feature",
  "properties": {
    "date:inception_lower": "1980-01-01",
    "date:inception_upper": "1980-01-01",
    "iso:country": "GB",
    "wof:name": "LE8 0HQ",
    "wof:placetype": "postalcode"
  },
  "geometry": {"coordinates":[-0.997281,52.536777],"type":"Point"}
}
