{
  "type": "Feature",
  "properties": {
    "iso:country":"GB",
    "wof:name":"LE8 0HQ",
    "wof:placetype":"postalcode"
},
  "geometry": {"coordinates":[-0.99728083222177,52.53677715709986],"type":"Point"}
}