{
  "type": "Feature",
  "properties": {
    "iso:country": "GB",
    "wof:name": "SL6 9AZ",
    "wof:placetype": "postalcode"
  },
  "geometry": {"coordinates":[-0.748535,51.562039],"type":"Point"}
}
