{
  "type": "Feature",
  "properties": {
    "iso:country":"GB",
    "wof:name":"SL6 9AZ",
    "wof:placetype":"postalcode"
},
  "geometry": {"coordinates":[-0.74855337841155,51.56203543448306],"type":"Point"}
}