{
  "type": "Feature",
  "properties": {
    "iso:country": "GB",
    "wof:name": "DH1 2RB",
    "wof:placetype": "postalcode"
  },
  "geometry": {"coordinates":[-1.533827,54.778756],"type":"Point"}
}
