{
  "type": "Feature",
  "properties": {
    "iso:country": "GB",
    "wof:name": "BB12 8XA",
    "wof:placetype": "postalcode"
  },
  "geometry": {"coordinates":[-2.275507,53.801839],"type":"Point"}
}
