{
  "type": "Feature",
  "properties": {
    "date:inception_lower": "1990-02-01",
    "date:inception_upper": "1990-02-01",
    "iso:country": "GB",
    "wof:name": "BB12 8XA",
    "wof:placetype": "postalcode"
  },
  "geometry": {"coordinates":[-2.275507,53.801839],"type":"Point"}
}
