{
  "type": "Feature",
  "properties": {
    "date:inception_lower": "1997-12-01",
    "date:inception_upper": "1997-12-01",
    "iso:country": "GB",
    "wof:name": "PO2 9NS",
    "wof:placetype": "postalcode"
  },
  "geometry": {"coordinates":[-1.08055,50.830454],"type":"Point"}
}
