{
  "type": "Feature",
  "properties": {
    "iso:country":"GB",
    "wof:name":"LS9 0LD",
    "wof:placetype":"postalcode"
},
  "geometry": {"coordinates":[-1.49445367443707,53.79165422178469],"type":"Point"}
}