{
  "type": "Feature",
  "properties": {
    "iso:country":"GB",
    "wof:name":"WN5 0DP",
    "wof:placetype":"postalcode"
},
  "geometry": {"coordinates":[-2.68443627235266,53.53925213599042],"type":"Point"}
}