{
  "type": "Feature",
  "properties": {
    "iso:country": "GB",
    "wof:name": "M43 6HQ",
    "wof:placetype": "postalcode"
  },
  "geometry": {"coordinates":[-2.161926,53.479541],"type":"Point"}
}
