{
  "type": "Feature",
  "properties": {
    "iso:country":"GB",
    "wof:name":"M43 6HQ",
    "wof:placetype":"postalcode"
},
  "geometry": {"coordinates":[-2.16192588394364,53.47954065822559],"type":"Point"}
}