{
  "type": "Feature",
  "properties": {
    "iso:country":"GB",
    "wof:name":"PO14 9EH",
    "wof:placetype":"postalcode"
},
  "geometry": {"coordinates":[-1.18746401394364,50.84314419032714],"type":"Point"}
}