{
  "type": "Feature",
  "properties": {
    "iso:country":"GB",
    "wof:name":"CO15 5NX",
    "wof:placetype":"postalcode"
},
  "geometry": {"coordinates":[1.19091458587363,51.80440242752803],"type":"Point"}
}