{
  "type": "Feature",
  "properties": {
    "iso:country":"GB",
    "wof:name":"NG11 6LP",
    "wof:placetype":"postalcode"
},
  "geometry": {"coordinates":[-1.14072077436219,52.90677676983532],"type":"Point"}
}