{
  "type": "Feature",
  "properties": {
    "iso:country": "GB",
    "wof:name": "NG11 6LP",
    "wof:placetype": "postalcode"
  },
  "geometry": {"coordinates":[-1.140721,52.906777],"type":"Point"}
}
