{
  "type": "Feature",
  "properties": {
    "date:inception_lower": "1980-01-01",
    "date:inception_upper": "1980-01-01",
    "iso:country": "GB",
    "wof:name": "WC1X 0HT",
    "wof:placetype": "postalcode"
  },
  "geometry": {"coordinates":[-0.112031,51.52729],"type":"Point"}
}
