{
  "type": "Feature",
  "properties": {
    "iso:country":"GB",
    "wof:name":"WC1X 0HT",
    "wof:placetype":"postalcode"
},
  "geometry": {"coordinates":[-0.11203067603955,51.52728963968942],"type":"Point"}
}