{
  "type": "Feature",
  "properties": {
    "iso:country": "GB",
    "wof:name": "DL17 8PL",
    "wof:placetype": "postalcode"
  },
  "geometry": {"coordinates":[-1.561921,54.687961],"type":"Point"}
}
