{
  "type": "Feature",
  "properties": {
    "iso:country":"GB",
    "wof:name":"UB4 8NL",
    "wof:placetype":"postalcode"
},
  "geometry": {"coordinates":[-0.41798549273788,51.53356811148797],"type":"Point"}
}