{
  "type": "Feature",
  "properties": {
    "iso:country":"GB",
    "wof:name":"RM3 9XH",
    "wof:placetype":"postalcode"
},
  "geometry": {"coordinates":[0.243764139794,51.60408144517924],"type":"Point"}
}