{
  "type": "Feature",
  "properties": {
    "iso:country": "GB",
    "wof:name": "PO21 5QF",
    "wof:placetype": "postalcode"
  },
  "geometry": {"coordinates":[-0.703764,50.790932],"type":"Point"}
}
