{
  "type": "Feature",
  "properties": {
    "iso:country":"GB",
    "wof:name":"KT13 9RH",
    "wof:placetype":"postalcode"
},
  "geometry": {"coordinates":[-0.42979981468316,51.37566044270738],"type":"Point"}
}