{
  "type": "Feature",
  "properties": {
    "iso:country": "GB",
    "wof:name": "KT13 9RH",
    "wof:placetype": "postalcode"
  },
  "geometry": {"coordinates":[-0.4298,51.37566],"type":"Point"}
}
