{
  "type": "Feature",
  "properties": {
    "iso:country":"GB",
    "wof:name":"L26 1UG",
    "wof:placetype":"postalcode"
},
  "geometry": {"coordinates":[-2.83721874639779,53.3556280841546],"type":"Point"}
}