{
  "type": "Feature",
  "properties": {
    "iso:country":"GB",
    "wof:name":"WC1N 3NA",
    "wof:placetype":"postalcode"
},
  "geometry": {"coordinates":[-0.11853916415388,51.52223250992539],"type":"Point"}
}