{
  "type": "Feature",
  "properties": {
    "iso:country": "GB",
    "wof:name": "AL1 5BD",
    "wof:placetype": "postalcode"
  },
  "geometry": {"coordinates":[-0.326201,51.749955],"type":"Point"}
}
