{
  "type": "Feature",
  "properties": {
    "date:inception_lower": "1980-01-01",
    "date:inception_upper": "1980-01-01",
    "iso:country": "GB",
    "wof:name": "IP22 2TD",
    "wof:placetype": "postalcode"
  },
  "geometry": {"coordinates":[0.877888,52.401035],"type":"Point"}
}
