{
  "type": "Feature",
  "properties": {
    "iso:country":"GB",
    "wof:name":"IP22 2TD",
    "wof:placetype":"postalcode"
},
  "geometry": {"coordinates":[0.87788759435182,52.40103526657994],"type":"Point"}
}