{
  "type": "Feature",
  "properties": {
    "iso:country":"GB",
    "wof:name":"B38 9PD",
    "wof:placetype":"postalcode"
},
  "geometry": {"coordinates":[-1.921274022475,52.40355703724966],"type":"Point"}
}