{
  "type": "Feature",
  "properties": {
    "iso:country":"GB",
    "wof:name":"SW17 7RU",
    "wof:placetype":"postalcode"
},
  "geometry": {"coordinates":[-0.16329023209661,51.44103787578804],"type":"Point"}
}