{
  "type": "Feature",
  "properties": {
    "iso:country":"GB",
    "wof:name":"KA7 1BW",
    "wof:placetype":"postalcode"
},
  "geometry": {"coordinates":[-4.63329769237946,55.46364393015595],"type":"Point"}
}