{
  "type": "Feature",
  "properties": {
    "date:inception_lower": "1980-01-01",
    "date:inception_upper": "1980-01-01",
    "iso:country": "GB",
    "wof:name": "DN36 4EX",
    "wof:placetype": "postalcode"
  },
  "geometry": {"coordinates":[0.008304,53.53262],"type":"Point"}
}
