{
  "type": "Feature",
  "properties": {
    "iso:country":"GB",
    "wof:name":"DA7 4HN",
    "wof:placetype":"postalcode"
},
  "geometry": {"coordinates":[0.14764628002091,51.45806448350252],"type":"Point"}
}