{
  "type": "Feature",
  "properties": {
    "date:inception_lower":"1992-08-01",
    "date:inception_upper":"1992-08-31",
    "iso:country":"GB",
    "wof:name":"DE56 2FB",
    "wof:placetype":"postalcode"
},
  "geometry": {"coordinates":[-1.466924,53.067834],"type":"Point"}
}