{
  "type": "Feature",
  "properties": {
    "iso:country":"GB",
    "wof:name":"E18 2DH",
    "wof:placetype":"postalcode"
},
  "geometry": {"coordinates":[0.01990669343232,51.59101682519844],"type":"Point"}
}