{
  "type": "Feature",
  "properties": {
    "iso:country": "GB",
    "wof:name": "KA22 7HA",
    "wof:placetype": "postalcode"
  },
  "geometry": {"coordinates":[-4.80694,55.65661],"type":"Point"}
}
