{
  "type": "Feature",
  "properties": {
    "date:inception_lower": "2001-12-01",
    "date:inception_upper": "2001-12-01",
    "iso:country": "GB",
    "wof:name": "LS27 0QU",
    "wof:placetype": "postalcode"
  },
  "geometry": {"coordinates":[-1.594688,53.73461],"type":"Point"}
}
