{
  "type": "Feature",
  "properties": {
    "iso:country":"GB",
    "wof:name":"DL3 9TG",
    "wof:placetype":"postalcode"
},
  "geometry": {"coordinates":[-1.57828854556815,54.52890704856642],"type":"Point"}
}