{
  "type": "Feature",
  "properties": {
    "iso:country": "GB",
    "wof:name": "PE3 9YG",
    "wof:placetype": "postalcode"
  },
  "geometry": {"coordinates":[-0.290487,52.583138],"type":"Point"}
}
