{
  "type": "Feature",
  "properties": {
    "iso:country":"GB",
    "wof:name":"PE3 9YG",
    "wof:placetype":"postalcode"
},
  "geometry": {"coordinates":[-0.29048660713863,52.58313783105663],"type":"Point"}
}