{
  "type": "Feature",
  "properties": {
    "date:inception_lower":"1992-01-01",
    "date:inception_upper":"1992-01-31",
    "iso:country":"GB",
    "wof:name":"PE3 9YG",
    "wof:placetype":"postalcode"
},
  "geometry": {"coordinates":[-0.290487,52.583138],"type":"Point"}
}