{
  "type": "Feature",
  "properties": {
    "date:inception_lower": "1980-01-01",
    "date:inception_upper": "1980-01-01",
    "iso:country": "GB",
    "wof:name": "SY10 9BA",
    "wof:placetype": "postalcode"
  },
  "geometry": {"coordinates":[-3.111249,52.849077],"type":"Point"}
}
