{
  "type": "Feature",
  "properties": {
    "iso:country": "GB",
    "wof:name": "GU32 3HE",
    "wof:placetype": "postalcode"
  },
  "geometry": {"coordinates":[-0.93699,51.006687],"type":"Point"}
}
