{
  "type": "Feature",
  "properties": {
    "iso:country":"GB",
    "wof:name":"LL41 4LL",
    "wof:placetype":"postalcode"
},
  "geometry": {"coordinates":[-3.93154443361833,52.96110861489995],"type":"Point"}
}