{
  "type": "Feature",
  "properties": {
    "iso:country":"GB",
    "wof:name":"BN18 0NF",
    "wof:placetype":"postalcode"
},
  "geometry": {"coordinates":[-0.62085285397917,50.86840943683346],"type":"Point"}
}