{
  "type": "Feature",
  "properties": {
    "iso:country":"GB",
    "wof:name":"PL25 3AL",
    "wof:placetype":"postalcode"
},
  "geometry": {"coordinates":[-4.76296090503668,50.33633204701542],"type":"Point"}
}