{
  "type": "Feature",
  "properties": {
    "iso:country": "GB",
    "wof:name": "PL25 3AL",
    "wof:placetype": "postalcode"
  },
  "geometry": {"coordinates":[-4.762961,50.336332],"type":"Point"}
}
