{
  "type": "Feature",
  "properties": {
    "iso:country":"GB",
    "wof:name":"B68 8PG",
    "wof:placetype":"postalcode"
},
  "geometry": {"coordinates":[-2.00753940735177,52.48159816533784],"type":"Point"}
}