{
  "type": "Feature",
  "properties": {
    "date:inception_lower": "1980-01-01",
    "date:inception_upper": "1980-01-01",
    "iso:country": "GB",
    "wof:name": "GL7 3QN",
    "wof:placetype": "postalcode"
  },
  "geometry": {"coordinates":[-1.675102,51.7112],"type":"Point"}
}
