{
  "type": "Feature",
  "properties": {
    "iso:country": "GB",
    "wof:name": "GL7 3QN",
    "wof:placetype": "postalcode"
  },
  "geometry": {"coordinates":[-1.675102,51.7112],"type":"Point"}
}
