{
  "type": "Feature",
  "properties": {
    "date:inception_lower": "1994-12-01",
    "date:inception_upper": "1994-12-01",
    "iso:country": "GB",
    "wof:name": "DN18 6JX",
    "wof:placetype": "postalcode"
  },
  "geometry": {"coordinates":[-0.426645,53.67907],"type":"Point"}
}
