{
  "type": "Feature",
  "properties": {
    "iso:country": "GB",
    "wof:name": "PE7 8GJ",
    "wof:placetype": "postalcode"
  },
  "geometry": {"coordinates":[-0.26181,52.536049],"type":"Point"}
}
