{
  "type": "Feature",
  "properties": {
    "date:inception_lower": "1980-01-01",
    "date:inception_upper": "1980-01-01",
    "iso:country": "GB",
    "wof:name": "L11 3EE",
    "wof:placetype": "postalcode"
  },
  "geometry": {"coordinates":[-2.922711,53.45232],"type":"Point"}
}
