{
  "type": "Feature",
  "properties": {
    "iso:country":"GB",
    "wof:name":"LL77 7UG",
    "wof:placetype":"postalcode"
},
  "geometry": {"coordinates":[-4.31180056960778,53.28765075082353],"type":"Point"}
}