{
  "type": "Feature",
  "properties": {
    "iso:country": "GB",
    "wof:name": "LL77 7UG",
    "wof:placetype": "postalcode"
  },
  "geometry": {"coordinates":[-4.311801,53.287651],"type":"Point"}
}
