{
  "type": "Feature",
  "properties": {
    "iso:country":"GB",
    "wof:name":"NW4 2DF",
    "wof:placetype":"postalcode"
},
  "geometry": {"coordinates":[-0.22089282401167,51.58634446150928],"type":"Point"}
}