{
  "type": "Feature",
  "properties": {
    "iso:country": "GB",
    "wof:name": "PO15 5BJ",
    "wof:placetype": "postalcode"
  },
  "geometry": {"coordinates":[-1.217984,50.855196],"type":"Point"}
}
