{
  "type": "Feature",
  "properties": {
    "iso:country":"GB",
    "wof:name":"DA7 5AT",
    "wof:placetype":"postalcode"
},
  "geometry": {"coordinates":[0.15159420771879,51.46120256392629],"type":"Point"}
}