{
  "type": "Feature",
  "properties": {
    "iso:country":"GB",
    "wof:name":"PH3 1LW",
    "wof:placetype":"postalcode"
},
  "geometry": {"coordinates":[-3.73261090442945,56.28996904963812],"type":"Point"}
}