{
  "type": "Feature",
  "properties": {
    "iso:country": "GB",
    "wof:name": "PH3 1LW",
    "wof:placetype": "postalcode"
  },
  "geometry": {"coordinates":[-3.732611,56.289969],"type":"Point"}
}
