{
  "type": "Feature",
  "properties": {
    "date:inception_lower":"1980-01-01",
    "date:inception_upper":"1980-01-31",
    "iso:country":"GB",
    "wof:name":"SA19 6YA",
    "wof:placetype":"postalcode"
},
  "geometry": {"coordinates":[-3.958397,51.892088],"type":"Point"}
}