{
  "type": "Feature",
  "properties": {
    "iso:country": "GB",
    "wof:name": "OL12 8PY",
    "wof:placetype": "postalcode"
  },
  "geometry": {"coordinates":[-2.17301,53.655453],"type":"Point"}
}
