{
  "type": "Feature",
  "properties": {
    "iso:country":"GB",
    "wof:name":"UB6 8GA",
    "wof:placetype":"postalcode"
},
  "geometry": {"coordinates":[-0.35393875633117,51.53841504632765],"type":"Point"}
}