{
  "type": "Feature",
  "properties": {
    "date:inception_lower": "2005-02-01",
    "date:inception_upper": "2005-02-01",
    "iso:country": "GB",
    "wof:name": "TN37 7RA",
    "wof:placetype": "postalcode"
  },
  "geometry": {"coordinates":[0.556883,50.885296],"type":"Point"}
}
