{
  "type": "Feature",
  "properties": {
    "iso:country":"GB",
    "wof:name":"SS1 3JQ",
    "wof:placetype":"postalcode"
},
  "geometry": {"coordinates":[0.76306721944158,51.53348997885988],"type":"Point"}
}