{
  "type": "Feature",
  "properties": {
    "iso:country":"GB",
    "wof:name":"CR5 3NA",
    "wof:placetype":"postalcode"
},
  "geometry": {"coordinates":[-0.16995971820361,51.31078453692165],"type":"Point"}
}