{
  "type": "Feature",
  "properties": {
    "iso:country":"GB",
    "wof:name":"E5 8RX",
    "wof:placetype":"postalcode"
},
  "geometry": {"coordinates":[-0.06146015441631,51.56454825578251],"type":"Point"}
}