{
  "type": "Feature",
  "properties": {
    "iso:country": "GB",
    "wof:name": "IP8 3SE",
    "wof:placetype": "postalcode"
  },
  "geometry": {"coordinates":[1.10219,52.038946],"type":"Point"}
}
