{
  "type": "Feature",
  "properties": {
    "iso:country": "GB",
    "wof:name": "IP8 3SE",
    "wof:placetype": "postalcode"
  },
  "geometry": {"coordinates":[1.102116,52.038942],"type":"Point"}
}
