{
  "type": "Feature",
  "properties": {
    "iso:country": "GB",
    "wof:name": "HR6 9NP",
    "wof:placetype": "postalcode"
  },
  "geometry": {"coordinates":[-2.911741,52.249603],"type":"Point"}
}
