{
  "type": "Feature",
  "properties": {
    "iso:country":"GB",
    "wof:name":"HR6 9NP",
    "wof:placetype":"postalcode"
},
  "geometry": {"coordinates":[-2.90861128601848,52.2484470509308],"type":"Point"}
}