{
  "type": "Feature",
  "properties": {
    "iso:country":"GB",
    "wof:name":"PO22 0BD",
    "wof:placetype":"postalcode"
},
  "geometry": {"coordinates":[-0.62710179432611,50.82692647891837],"type":"Point"}
}