{
  "type": "Feature",
  "properties": {
    "iso:country":"GB",
    "wof:name":"S60 4JJ",
    "wof:placetype":"postalcode"
},
  "geometry": {"coordinates":[-1.33073975020703,53.40338802689141],"type":"Point"}
}