{
  "type": "Feature",
  "properties": {
    "iso:country": "GB",
    "wof:name": "S60 4JJ",
    "wof:placetype": "postalcode"
  },
  "geometry": {"coordinates":[-1.33074,53.403388],"type":"Point"}
}
