{
  "type": "Feature",
  "properties": {
    "date:inception_lower":"1987-04-01",
    "date:inception_upper":"1987-04-30",
    "iso:country":"GB",
    "wof:name":"S60 4JJ",
    "wof:placetype":"postalcode"
},
  "geometry": {"coordinates":[-1.33074,53.403388],"type":"Point"}
}