{
  "type": "Feature",
  "properties": {
    "date:inception_lower": "2008-09-01",
    "date:inception_upper": "2008-09-01",
    "iso:country": "GB",
    "wof:name": "CR8 2EZ",
    "wof:placetype": "postalcode"
  },
  "geometry": {"coordinates":[-0.114747,51.338074],"type":"Point"}
}
