{
  "type": "Feature",
  "properties": {
    "iso:country": "GB",
    "wof:name": "GU35 9FN",
    "wof:placetype": "postalcode"
  },
  "geometry": {"coordinates":[-0.870143,51.11089],"type":"Point"}
}
