{
  "type": "Feature",
  "properties": {
    "date:inception_lower":"1980-01-01",
    "date:inception_upper":"1980-01-31",
    "iso:country":"GB",
    "wof:name":"OL4 4BW",
    "wof:placetype":"postalcode"
},
  "geometry": {"coordinates":[-2.057187,53.545045],"type":"Point"}
}