{
  "type": "Feature",
  "properties": {
    "iso:country":"GB",
    "wof:name":"TN8 6BL",
    "wof:placetype":"postalcode"
},
  "geometry": {"coordinates":[0.06817875277789,51.20719483529751],"type":"Point"}
}