{
  "type": "Feature",
  "properties": {
    "iso:country":"GB",
    "wof:name":"DD3 8LY",
    "wof:placetype":"postalcode"
},
  "geometry": {"coordinates":[-2.98813341257735,56.48541575187926],"type":"Point"}
}