{
  "type": "Feature",
  "properties": {
    "iso:country": "GB",
    "wof:name": "BN12 6LY",
    "wof:placetype": "postalcode"
  },
  "geometry": {"coordinates":[-0.431992,50.821473],"type":"Point"}
}
