{
  "type": "Feature",
  "properties": {
    "iso:country":"GB",
    "wof:name":"BN12 6LY",
    "wof:placetype":"postalcode"
},
  "geometry": {"coordinates":[-0.43199205437233,50.82147299333102],"type":"Point"}
}