{
  "type": "Feature",
  "properties": {
    "iso:country":"GB",
    "wof:name":"RG1 6AB",
    "wof:placetype":"postalcode"
},
  "geometry": {"coordinates":[-0.97638852558425,51.45145071450764],"type":"Point"}
}