{
  "type": "Feature",
  "properties": {
    "iso:country": "GB",
    "wof:name": "L6 6DE",
    "wof:placetype": "postalcode"
  },
  "geometry": {"coordinates":[-2.948195,53.413307],"type":"Point"}
}
