{
  "type": "Feature",
  "properties": {
    "date:inception_lower": "1980-01-01",
    "date:inception_upper": "1980-01-01",
    "iso:country": "GB",
    "wof:name": "L6 6DE",
    "wof:placetype": "postalcode"
  },
  "geometry": {"coordinates":[-2.948195,53.413307],"type":"Point"}
}
