{
  "type": "Feature",
  "properties": {
    "iso:country":"GB",
    "wof:name":"L6 6DE",
    "wof:placetype":"postalcode"
},
  "geometry": {"coordinates":[-2.9481947930002,53.41330673670161],"type":"Point"}
}