{
  "type": "Feature",
  "properties": {
    "date:inception_lower": "1980-01-01",
    "date:inception_upper": "1980-01-01",
    "iso:country": "GB",
    "wof:name": "TQ1 3DT",
    "wof:placetype": "postalcode"
  },
  "geometry": {"coordinates":[-3.532239,50.469264],"type":"Point"}
}
