{
  "type": "Feature",
  "properties": {
    "iso:country":"GB",
    "wof:name":"UB3 5LX",
    "wof:placetype":"postalcode"
},
  "geometry": {"coordinates":[-0.43946394883188,51.48518999566015],"type":"Point"}
}