{
  "type": "Feature",
  "properties": {
    "iso:country": "GB",
    "wof:name": "SN14 0FN",
    "wof:placetype": "postalcode"
  },
  "geometry": {"coordinates":[-2.124213,51.46253],"type":"Point"}
}
