{
  "type": "Feature",
  "properties": {
    "iso:country":"GB",
    "wof:name":"KA3 6AW",
    "wof:placetype":"postalcode"
},
  "geometry": {"coordinates":[-4.45160135277009,55.65231831638776],"type":"Point"}
}