{
  "type": "Feature",
  "properties": {
    "date:inception_lower": "2020-11-01",
    "date:inception_upper": "2020-11-01",
    "iso:country": "GB",
    "wof:name": "IP19 8LN",
    "wof:placetype": "postalcode"
  },
  "geometry": {"coordinates":[1.515285,52.343466],"type":"Point"}
}
