{
  "type": "Feature",
  "properties": {
    "iso:country":"GB",
    "wof:name":"S25 4AW",
    "wof:placetype":"postalcode"
},
  "geometry": {"coordinates":[-1.22138807069585,53.35730478886062],"type":"Point"}
}