{
  "type": "Feature",
  "properties": {
    "iso:country": "GB",
    "wof:name": "DE5 8JY",
    "wof:placetype": "postalcode"
  },
  "geometry": {"coordinates":[-1.411939,53.030944],"type":"Point"}
}
