{
  "type": "Feature",
  "properties": {
    "iso:country":"GB",
    "wof:name":"DE5 8JY",
    "wof:placetype":"postalcode"
},
  "geometry": {"coordinates":[-1.41193895318294,53.0309439681794],"type":"Point"}
}