{
  "type": "Feature",
  "properties": {
    "date:inception_lower": "1980-01-01",
    "date:inception_upper": "1980-01-01",
    "iso:country": "GB",
    "wof:name": "NG11 0LG",
    "wof:placetype": "postalcode"
  },
  "geometry": {"coordinates":[-1.224837,52.86158],"type":"Point"}
}
