{
  "type": "Feature",
  "properties": {
    "iso:country": "GB",
    "wof:name": "RM12 4QX",
    "wof:placetype": "postalcode"
  },
  "geometry": {"coordinates":[0.20044,51.554535],"type":"Point"}
}
