{
  "type": "Feature",
  "properties": {
    "iso:country":"GB",
    "wof:name":"SW16 2XW",
    "wof:placetype":"postalcode"
},
  "geometry": {"coordinates":[-0.12049138824301,51.4302966862191],"type":"Point"}
}