{
  "type": "Feature",
  "properties": {
    "iso:country":"GB",
    "wof:name":"DE23 2TD",
    "wof:placetype":"postalcode"
},
  "geometry": {"coordinates":[-1.50947173031445,52.89289659118361],"type":"Point"}
}