{
  "type": "Feature",
  "properties": {
    "iso:country": "GB",
    "wof:name": "MK19 7PB",
    "wof:placetype": "postalcode"
  },
  "geometry": {"coordinates":[-0.826426,52.115414],"type":"Point"}
}
