{
  "type": "Feature",
  "properties": {
    "iso:country":"GB",
    "wof:name":"DD2 3AD",
    "wof:placetype":"postalcode"
},
  "geometry": {"coordinates":[-3.00528891764747,56.47035475042227],"type":"Point"}
}