{
  "type": "Feature",
  "properties": {
    "date:inception_lower": "1997-06-01",
    "date:inception_upper": "1997-06-01",
    "iso:country": "GB",
    "wof:name": "LE3 8TA",
    "wof:placetype": "postalcode"
  },
  "geometry": {"coordinates":[-1.188602,52.656228],"type":"Point"}
}
