{
  "type": "Feature",
  "properties": {
    "iso:country": "GB",
    "wof:name": "IG8 7HD",
    "wof:placetype": "postalcode"
  },
  "geometry": {"coordinates":[0.041573,51.605749],"type":"Point"}
}
