{
  "type": "Feature",
  "properties": {
    "iso:country":"GB",
    "wof:name":"IG8 7HD",
    "wof:placetype":"postalcode"
},
  "geometry": {"coordinates":[0.04157316345149,51.60574948654588],"type":"Point"}
}