{
  "type": "Feature",
  "properties": {
    "iso:country":"GB",
    "wof:name":"KA22 8BD",
    "wof:placetype":"postalcode"
},
  "geometry": {"coordinates":[-4.80344074965573,55.6443660739237],"type":"Point"}
}