{
  "type": "Feature",
  "properties": {
    "date:inception_lower":"2017-06-01",
    "date:inception_upper":"2017-06-30",
    "iso:country":"GB",
    "wof:name":"L3 7DH",
    "wof:placetype":"postalcode"
},
  "geometry": {"coordinates":[-2.995701,53.419535],"type":"Point"}
}