{
  "type": "Feature",
  "properties": {
    "iso:country":"GB",
    "wof:name":"NE6 4PJ",
    "wof:placetype":"postalcode"
},
  "geometry": {"coordinates":[-1.55471071303851,54.98914340055182],"type":"Point"}
}