{
  "type": "Feature",
  "properties": {
    "date:inception_lower": "1980-01-01",
    "date:inception_upper": "1980-01-01",
    "iso:country": "GB",
    "wof:name": "NE6 4PJ",
    "wof:placetype": "postalcode"
  },
  "geometry": {"coordinates":[-1.554711,54.989143],"type":"Point"}
}
