{
  "type": "Feature",
  "properties": {
    "date:inception_lower": "1984-10-01",
    "date:inception_upper": "1984-10-01",
    "iso:country": "GB",
    "wof:name": "BS10 6JB",
    "wof:placetype": "postalcode"
  },
  "geometry": {"coordinates":[-2.600057,51.510964],"type":"Point"}
}
