{
  "type": "Feature",
  "properties": {
    "iso:country":"GB",
    "wof:name":"BS10 6JB",
    "wof:placetype":"postalcode"
},
  "geometry": {"coordinates":[-2.60005666532614,51.51096393641753],"type":"Point"}
}