{
  "type": "Feature",
  "properties": {
    "iso:country": "GB",
    "wof:name": "SA73 1EY",
    "wof:placetype": "postalcode"
  },
  "geometry": {"coordinates":[-5.020355,51.715814],"type":"Point"}
}
