{
  "type": "Feature",
  "properties": {
    "iso:country":"GB",
    "wof:name":"SA73 1EY",
    "wof:placetype":"postalcode"
},
  "geometry": {"coordinates":[-5.020367433927,51.71588096322698],"type":"Point"}
}