{
  "type": "Feature",
  "properties": {
    "date:inception_lower":"2015-07-01",
    "date:inception_upper":"2015-07-31",
    "iso:country":"GB",
    "wof:name":"SA73 1EY",
    "wof:placetype":"postalcode"
},
  "geometry": {"coordinates":[-5.020355,51.715814],"type":"Point"}
}