{
  "type": "Feature",
  "properties": {
    "iso:country": "GB",
    "wof:name": "NP23 5PN",
    "wof:placetype": "postalcode"
  },
  "geometry": {"coordinates":[-3.217088,51.796678],"type":"Point"}
}
