{
  "type": "Feature",
  "properties": {
    "date:inception_lower": "1992-01-01",
    "date:inception_upper": "1992-01-01",
    "iso:country": "GB",
    "wof:name": "PE9 4LG",
    "wof:placetype": "postalcode"
  },
  "geometry": {"coordinates":[-0.454697,52.700033],"type":"Point"}
}
