{
  "type": "Feature",
  "properties": {
    "iso:country":"GB",
    "wof:name":"PE9 4LG",
    "wof:placetype":"postalcode"
},
  "geometry": {"coordinates":[-0.45469735507929,52.70003323855344],"type":"Point"}
}