{
  "type": "Feature",
  "properties": {
    "date:inception_lower": "2024-09-01",
    "date:inception_upper": "2024-09-01",
    "iso:country": "GB",
    "wof:name": "NR20 5FJ",
    "wof:placetype": "postalcode"
  },
  "geometry": {"coordinates":[1.055457,52.802093],"type":"Point"}
}
