{
  "type": "Feature",
  "properties": {
    "date:inception_lower": "1980-01-01",
    "date:inception_upper": "1980-01-01",
    "iso:country": "GB",
    "wof:name": "OL16 3LY",
    "wof:placetype": "postalcode"
  },
  "geometry": {"coordinates":[-2.11487,53.613252],"type":"Point"}
}
