{
  "type": "Feature",
  "properties": {
    "iso:country": "GB",
    "wof:name": "DY1 1DW",
    "wof:placetype": "postalcode"
  },
  "geometry": {"coordinates":[-2.089447,52.510671],"type":"Point"}
}
