{
  "type": "Feature",
  "properties": {
    "iso:country":"GB",
    "wof:name":"PE7 3BU",
    "wof:placetype":"postalcode"
},
  "geometry": {"coordinates":[-0.23026843503508,52.53794575847154],"type":"Point"}
}