{
  "type": "Feature",
  "properties": {
    "iso:country": "GB",
    "wof:name": "PE7 3BU",
    "wof:placetype": "postalcode"
  },
  "geometry": {"coordinates":[-0.230268,52.537946],"type":"Point"}
}
