{
  "type": "Feature",
  "properties": {
    "date:inception_lower": "2019-06-01",
    "date:inception_upper": "2019-06-01",
    "iso:country": "GB",
    "wof:name": "TS22 5FX",
    "wof:placetype": "postalcode"
  },
  "geometry": {"coordinates":[-1.323844,54.633415],"type":"Point"}
}
