{
  "type": "Feature",
  "properties": {
    "iso:country": "GB",
    "wof:name": "TS22 5FX",
    "wof:placetype": "postalcode"
  },
  "geometry": {"coordinates":[-1.323844,54.633415],"type":"Point"}
}
