{
  "type": "Feature",
  "properties": {
    "iso:country":"GB",
    "wof:name":"HR9 5NW",
    "wof:placetype":"postalcode"
},
  "geometry": {"coordinates":[-2.57811385867931,51.91066307113879],"type":"Point"}
}