{
  "type": "Feature",
  "properties": {
    "iso:country":"GB",
    "wof:name":"BS5 7FB",
    "wof:placetype":"postalcode"
},
  "geometry": {"coordinates":[-2.54286355576105,51.46726490897287],"type":"Point"}
}