{
  "type": "Feature",
  "properties": {
    "iso:country":"GB",
    "wof:name":"KA5 6AN",
    "wof:placetype":"postalcode"
},
  "geometry": {"coordinates":[-4.37574691549529,55.51633846684615],"type":"Point"}
}