{
  "type": "Feature",
  "properties": {
    "iso:country":"GB",
    "wof:name":"RG27 9SQ",
    "wof:placetype":"postalcode"
},
  "geometry": {"coordinates":[-0.95397438349801,51.28274289149807],"type":"Point"}
}