{
  "type": "Feature",
  "properties": {
    "date:inception_lower": "1987-10-01",
    "date:inception_upper": "1987-10-01",
    "iso:country": "GB",
    "wof:name": "RG27 9SQ",
    "wof:placetype": "postalcode"
  },
  "geometry": {"coordinates":[-0.953974,51.282743],"type":"Point"}
}
