{
  "type": "Feature",
  "properties": {
    "iso:country":"GB",
    "wof:name":"PO15 7AJ",
    "wof:placetype":"postalcode"
},
  "geometry": {"coordinates":[-1.24975886542668,50.88036790383725],"type":"Point"}
}