{
  "type": "Feature",
  "properties": {
    "date:inception_lower": "1990-07-01",
    "date:inception_upper": "1990-07-01",
    "iso:country": "GB",
    "wof:name": "PO15 7AJ",
    "wof:placetype": "postalcode"
  },
  "geometry": {"coordinates":[-1.249759,50.880368],"type":"Point"}
}
