{
  "type": "Feature",
  "properties": {
    "iso:country":"GB",
    "wof:name":"DN21 1AU",
    "wof:placetype":"postalcode"
},
  "geometry": {"coordinates":[-0.76350519475032,53.38011117668398],"type":"Point"}
}