{
  "type": "Feature",
  "properties": {
    "iso:country": "GB",
    "wof:name": "DN21 1AU",
    "wof:placetype": "postalcode"
  },
  "geometry": {"coordinates":[-0.763505,53.380111],"type":"Point"}
}
