{
  "type": "Feature",
  "properties": {
    "iso:country":"GB",
    "wof:name":"SO21 1EY",
    "wof:placetype":"postalcode"
},
  "geometry": {"coordinates":[-1.2639515456273,51.09172594258936],"type":"Point"}
}