{
  "type": "Feature",
  "properties": {
    "date:inception_lower": "2004-05-01",
    "date:inception_upper": "2004-05-01",
    "iso:country": "GB",
    "wof:name": "SO21 1EY",
    "wof:placetype": "postalcode"
  },
  "geometry": {"coordinates":[-1.263952,51.091726],"type":"Point"}
}
