{
  "type": "Feature",
  "properties": {
    "iso:country":"GB",
    "wof:name":"RG1 5PN",
    "wof:placetype":"postalcode"
},
  "geometry": {"coordinates":[-0.95479227300702,51.4468092432967],"type":"Point"}
}