{
  "type": "Feature",
  "properties": {
    "iso:country": "GB",
    "wof:name": "RG1 5PN",
    "wof:placetype": "postalcode"
  },
  "geometry": {"coordinates":[-0.954792,51.446809],"type":"Point"}
}
