{
  "type": "Feature",
  "properties": {
    "iso:country":"GB",
    "wof:name":"WS14 9DP",
    "wof:placetype":"postalcode"
},
  "geometry": {"coordinates":[-1.82630466958772,52.67704477890683],"type":"Point"}
}