{
  "type": "Feature",
  "properties": {
    "iso:country": "GB",
    "wof:name": "NR13 4WE",
    "wof:placetype": "postalcode"
  },
  "geometry": {"coordinates":[1.447765,52.633652],"type":"Point"}
}
