{
  "type": "Feature",
  "properties": {
    "date:inception_lower":"1998-06-01",
    "date:inception_upper":"1998-06-30",
    "iso:country":"GB",
    "wof:name":"M2 1HL",
    "wof:placetype":"postalcode"
},
  "geometry": {"coordinates":[-2.244389,53.48162],"type":"Point"}
}