{
  "type": "Feature",
  "properties": {
    "iso:country":"GB",
    "wof:name":"M2 1HL",
    "wof:placetype":"postalcode"
},
  "geometry": {"coordinates":[-2.24438935633184,53.48162045159237],"type":"Point"}
}