{
  "type": "Feature",
  "properties": {
    "iso:country":"GB",
    "wof:name":"CH7 6GF",
    "wof:placetype":"postalcode"
},
  "geometry": {"coordinates":[-3.09223814475687,53.20231369273141],"type":"Point"}
}