{
  "type": "Feature",
  "properties": {
    "date:inception_lower": "1992-08-01",
    "date:inception_upper": "1992-08-01",
    "iso:country": "GB",
    "wof:name": "CH7 6GF",
    "wof:placetype": "postalcode"
  },
  "geometry": {"coordinates":[-3.092228,53.202545],"type":"Point"}
}
