{
  "type": "Feature",
  "properties": {
    "iso:country":"GB",
    "wof:name":"TN3 0JR",
    "wof:placetype":"postalcode"
},
  "geometry": {"coordinates":[0.21257304050998,51.14105958794288],"type":"Point"}
}