{
  "type": "Feature",
  "properties": {
    "iso:country": "GB",
    "wof:name": "TN3 0JR",
    "wof:placetype": "postalcode"
  },
  "geometry": {"coordinates":[0.212573,51.14106],"type":"Point"}
}
