{
  "type": "Feature",
  "properties": {
    "iso:country":"GB",
    "wof:name":"NW2 3QA",
    "wof:placetype":"postalcode"
},
  "geometry": {"coordinates":[-0.20782113690475,51.55022112387959],"type":"Point"}
}