{
  "type": "Feature",
  "properties": {
    "date:inception_lower":"2009-03-01",
    "date:inception_upper":"2009-03-31",
    "iso:country":"GB",
    "wof:name":"NR29 3BF",
    "wof:placetype":"postalcode"
},
  "geometry": {"coordinates":[1.613844,52.66893],"type":"Point"}
}