{
  "type": "Feature",
  "properties": {
    "iso:country": "GB",
    "wof:name": "NR29 3BF",
    "wof:placetype": "postalcode"
  },
  "geometry": {"coordinates":[1.613844,52.66893],"type":"Point"}
}
