{
  "type": "Feature",
  "properties": {
    "iso:country":"GB",
    "wof:name":"NR29 3BF",
    "wof:placetype":"postalcode"
},
  "geometry": {"coordinates":[1.6138439159062,52.66892997803541],"type":"Point"}
}