{
  "type": "Feature",
  "properties": {
    "iso:country":"GB",
    "wof:name":"G83 9AT",
    "wof:placetype":"postalcode"
},
  "geometry": {"coordinates":[-4.56969462304962,55.98584658255887],"type":"Point"}
}