{
  "type": "Feature",
  "properties": {
    "iso:country":"GB",
    "wof:name":"S81 9RW",
    "wof:placetype":"postalcode"
},
  "geometry": {"coordinates":[-1.11731884677311,53.38008673539824],"type":"Point"}
}