{
  "type": "Feature",
  "properties": {
    "iso:country":"GB",
    "wof:name":"SL2 5PR",
    "wof:placetype":"postalcode"
},
  "geometry": {"coordinates":[-0.57509845402109,51.51458495684372],"type":"Point"}
}