{
  "type": "Feature",
  "properties": {
    "iso:country": "GB",
    "wof:name": "SL2 5PR",
    "wof:placetype": "postalcode"
  },
  "geometry": {"coordinates":[-0.575098,51.514585],"type":"Point"}
}
