{
  "type": "Feature",
  "properties": {
    "iso:country":"GB",
    "wof:name":"RM6 6RD",
    "wof:placetype":"postalcode"
},
  "geometry": {"coordinates":[0.14062422403351,51.57616110612073],"type":"Point"}
}