{
  "type": "Feature",
  "properties": {
    "date:inception_lower": "2023-10-01",
    "date:inception_upper": "2023-10-01",
    "iso:country": "GB",
    "wof:name": "DY6 7DB",
    "wof:placetype": "postalcode"
  },
  "geometry": {"coordinates":[-2.147384,52.511197],"type":"Point"}
}
