{
  "type": "Feature",
  "properties": {
    "date:inception_lower": "1980-01-01",
    "date:inception_upper": "1980-01-01",
    "iso:country": "GB",
    "wof:name": "PA16 0JP",
    "wof:placetype": "postalcode"
  },
  "geometry": {"coordinates":[-4.820519,55.940344],"type":"Point"}
}
