{
  "type": "Feature",
  "properties": {
    "iso:country": "GB",
    "wof:name": "PA16 0JP",
    "wof:placetype": "postalcode"
  },
  "geometry": {"coordinates":[-4.820554,55.940332],"type":"Point"}
}
