{
  "type": "Feature",
  "properties": {
    "iso:country":"GB",
    "wof:name":"LS25 5AL",
    "wof:placetype":"postalcode"
},
  "geometry": {"coordinates":[-1.26021551368216,53.77521247976418],"type":"Point"}
}