{
  "type": "Feature",
  "properties": {
    "iso:country":"GB",
    "wof:name":"WV8 1LR",
    "wof:placetype":"postalcode"
},
  "geometry": {"coordinates":[-2.17678611776626,52.62127625486911],"type":"Point"}
}