{
  "type": "Feature",
  "properties": {
    "iso:country": "GB",
    "wof:name": "WV8 1LR",
    "wof:placetype": "postalcode"
  },
  "geometry": {"coordinates":[-2.176786,52.621276],"type":"Point"}
}
