{
  "type": "Feature",
  "properties": {
    "iso:country":"GB",
    "wof:name":"SN3 1SE",
    "wof:placetype":"postalcode"
},
  "geometry": {"coordinates":[-1.77189507418401,51.55046534339169],"type":"Point"}
}