{
  "type": "Feature",
  "properties": {
    "date:inception_lower": "2015-12-01",
    "date:inception_upper": "2015-12-01",
    "iso:country": "GB",
    "wof:name": "BA14 0FN",
    "wof:placetype": "postalcode"
  },
  "geometry": {"coordinates":[-2.207378,51.308563],"type":"Point"}
}
