{
  "type": "Feature",
  "properties": {
    "iso:country":"GB",
    "wof:name":"NE3 3SP",
    "wof:placetype":"postalcode"
},
  "geometry": {"coordinates":[-1.6471684670498,55.01033942518627],"type":"Point"}
}