{
  "type": "Feature",
  "properties": {
    "iso:country":"GB",
    "wof:name":"BH24 2EJ",
    "wof:placetype":"postalcode"
},
  "geometry": {"coordinates":[-1.84203226094736,50.84126027508951],"type":"Point"}
}