{
  "type": "Feature",
  "properties": {
    "iso:country":"GB",
    "wof:name":"BD14 6PY",
    "wof:placetype":"postalcode"
},
  "geometry": {"coordinates":[-1.84161699808524,53.78185582975245],"type":"Point"}
}