{
  "type": "Feature",
  "properties": {
    "iso:country": "GB",
    "wof:name": "KT13 0RL",
    "wof:placetype": "postalcode"
  },
  "geometry": {"coordinates":[-0.463921,51.344837],"type":"Point"}
}
