{
  "type": "Feature",
  "properties": {
    "iso:country":"GB",
    "wof:name":"KT13 0RL",
    "wof:placetype":"postalcode"
},
  "geometry": {"coordinates":[-0.46392129560027,51.34483719908091],"type":"Point"}
}