{
  "type": "Feature",
  "properties": {
    "date:inception_lower":"1996-06-01",
    "date:inception_upper":"1996-06-30",
    "iso:country":"GB",
    "wof:name":"KT13 0RL",
    "wof:placetype":"postalcode"
},
  "geometry": {"coordinates":[-0.463921,51.344837],"type":"Point"}
}