{
  "type": "Feature",
  "properties": {
    "iso:country":"GB",
    "wof:name":"WF1 4TE",
    "wof:placetype":"postalcode"
},
  "geometry": {"coordinates":[-1.47852679527092,53.6926804474403],"type":"Point"}
}