{
  "type": "Feature",
  "properties": {
    "date:inception_lower":"1980-01-01",
    "date:inception_upper":"1980-01-31",
    "iso:country":"GB",
    "wof:name":"WF1 4TE",
    "wof:placetype":"postalcode"
},
  "geometry": {"coordinates":[-1.478527,53.69268],"type":"Point"}
}