{
  "type": "Feature",
  "properties": {
    "iso:country":"GB",
    "wof:name":"WF17 5RY",
    "wof:placetype":"postalcode"
},
  "geometry": {"coordinates":[-1.63381631057058,53.71504273024497],"type":"Point"}
}