{
  "type": "Feature",
  "properties": {
    "iso:country":"GB",
    "wof:name":"HP4 1HB",
    "wof:placetype":"postalcode"
},
  "geometry": {"coordinates":[-0.56098787592869,51.76483704755712],"type":"Point"}
}