{
  "type": "Feature",
  "properties": {
    "date:inception_lower":"1980-01-01",
    "date:inception_upper":"1980-01-31",
    "iso:country":"GB",
    "wof:name":"LU5 4QJ",
    "wof:placetype":"postalcode"
},
  "geometry": {"coordinates":[-0.502458,51.889972],"type":"Point"}
}