{
  "type": "Feature",
  "properties": {
    "iso:country":"GB",
    "wof:name":"LU5 4QJ",
    "wof:placetype":"postalcode"
},
  "geometry": {"coordinates":[-0.50245755409569,51.88997155599439],"type":"Point"}
}