{
  "type": "Feature",
  "properties": {
    "iso:country":"GB",
    "wof:name":"EX2 6DH",
    "wof:placetype":"postalcode"
},
  "geometry": {"coordinates":[-3.50189945847524,50.71251071297676],"type":"Point"}
}