{
  "type": "Feature",
  "properties": {
    "iso:country": "GB",
    "wof:name": "EX2 6DH",
    "wof:placetype": "postalcode"
  },
  "geometry": {"coordinates":[-3.501899,50.712511],"type":"Point"}
}
