{
  "type": "Feature",
  "properties": {
    "date:inception_lower": "1996-12-01",
    "date:inception_upper": "1996-12-01",
    "iso:country": "GB",
    "wof:name": "SK23 0JH",
    "wof:placetype": "postalcode"
  },
  "geometry": {"coordinates":[-1.912657,53.325582],"type":"Point"}
}
