{
  "type": "Feature",
  "properties": {
    "iso:country": "GB",
    "wof:name": "S40 3NJ",
    "wof:placetype": "postalcode"
  },
  "geometry": {"coordinates":[-1.457361,53.221854],"type":"Point"}
}
