{
  "type": "Feature",
  "properties": {
    "iso:country": "GB",
    "wof:name": "NW1 1LL",
    "wof:placetype": "postalcode"
  },
  "geometry": {"coordinates":[-0.130885,51.528401],"type":"Point"}
}
