{
  "type": "Feature",
  "properties": {
    "iso:country":"GB",
    "wof:name":"NW1 1LL",
    "wof:placetype":"postalcode"
},
  "geometry": {"coordinates":[-0.13088520730275,51.5284009141482],"type":"Point"}
}