{
  "type": "Feature",
  "properties": {
    "date:inception_lower": "1980-01-01",
    "date:inception_upper": "1980-01-01",
    "iso:country": "GB",
    "wof:name": "SE25 4EQ",
    "wof:placetype": "postalcode"
  },
  "geometry": {"coordinates":[-0.075251,51.405282],"type":"Point"}
}
