{
  "type": "Feature",
  "properties": {
    "iso:country":"GB",
    "wof:name":"SE25 4EQ",
    "wof:placetype":"postalcode"
},
  "geometry": {"coordinates":[-0.07531910759649,51.40531025629745],"type":"Point"}
}