{
  "type": "Feature",
  "properties": {
    "iso:country":"GB",
    "wof:name":"TN12 9ER",
    "wof:placetype":"postalcode"
},
  "geometry": {"coordinates":[0.50309074686538,51.17344220454284],"type":"Point"}
}