{
  "type": "Feature",
  "properties": {
    "date:inception_lower": "1980-01-01",
    "date:inception_upper": "1980-01-01",
    "iso:country": "GB",
    "wof:name": "PE22 0TG",
    "wof:placetype": "postalcode"
  },
  "geometry": {"coordinates":[-0.001718,53.013165],"type":"Point"}
}
