{
  "type": "Feature",
  "properties": {
    "iso:country": "GB",
    "wof:name": "PE22 0TG",
    "wof:placetype": "postalcode"
  },
  "geometry": {"coordinates":[-0.001718,53.013165],"type":"Point"}
}
