{
  "type": "Feature",
  "properties": {
    "iso:country":"GB",
    "wof:name":"B70 9BF",
    "wof:placetype":"postalcode"
},
  "geometry": {"coordinates":[-2.0295786810506,52.5199366951359],"type":"Point"}
}