{
  "type": "Feature",
  "properties": {
    "iso:country":"GB",
    "wof:name":"NP4 0BG",
    "wof:placetype":"postalcode"
},
  "geometry": {"coordinates":[-2.98166198192356,51.73923093870085],"type":"Point"}
}