{
  "type": "Feature",
  "properties": {
    "iso:country": "GB",
    "wof:name": "NP4 0BG",
    "wof:placetype": "postalcode"
  },
  "geometry": {"coordinates":[-2.981662,51.739231],"type":"Point"}
}
