{
  "type": "Feature",
  "properties": {
    "iso:country":"GB",
    "wof:name":"SL4 4RA",
    "wof:placetype":"postalcode"
},
  "geometry": {"coordinates":[-0.64662572950738,51.45808066351288],"type":"Point"}
}