{
  "type": "Feature",
  "properties": {
    "iso:country":"GB",
    "wof:name":"RG30 3BZ",
    "wof:placetype":"postalcode"
},
  "geometry": {"coordinates":[-1.00876770931218,51.4442026924634],"type":"Point"}
}