{
  "type": "Feature",
  "properties": {
    "date:inception_lower": "1980-01-01",
    "date:inception_upper": "1980-01-01",
    "iso:country": "GB",
    "wof:name": "ST10 4JE",
    "wof:placetype": "postalcode"
  },
  "geometry": {"coordinates":[-1.990745,52.953129],"type":"Point"}
}
