{
  "type": "Feature",
  "properties": {
    "iso:country": "GB",
    "wof:name": "ST10 4JE",
    "wof:placetype": "postalcode"
  },
  "geometry": {"coordinates":[-1.990745,52.953129],"type":"Point"}
}
