{
  "type": "Feature",
  "properties": {
    "iso:country":"GB",
    "wof:name":"DY2 8LS",
    "wof:placetype":"postalcode"
},
  "geometry": {"coordinates":[-2.07538425677236,52.50369848292566],"type":"Point"}
}