{
  "type": "Feature",
  "properties": {
    "iso:country": "GB",
    "wof:name": "DY2 8LS",
    "wof:placetype": "postalcode"
  },
  "geometry": {"coordinates":[-2.075384,52.503698],"type":"Point"}
}
