{
  "type": "Feature",
  "properties": {
    "iso:country":"GB",
    "wof:name":"SK6 3DR",
    "wof:placetype":"postalcode"
},
  "geometry": {"coordinates":[-2.09998662991206,53.41122421500913],"type":"Point"}
}