{
  "type": "Feature",
  "properties": {
    "date:inception_lower": "1980-01-01",
    "date:inception_upper": "1980-01-01",
    "iso:country": "GB",
    "wof:name": "WS5 4PA",
    "wof:placetype": "postalcode"
  },
  "geometry": {"coordinates":[-1.978345,52.563629],"type":"Point"}
}
