{
  "type": "Feature",
  "properties": {
    "iso:country":"GB",
    "wof:name":"WS5 4PA",
    "wof:placetype":"postalcode"
},
  "geometry": {"coordinates":[-1.97834482713333,52.56362926091763],"type":"Point"}
}