{
  "type": "Feature",
  "properties": {
    "iso:country":"GB",
    "wof:name":"NN14 2LT",
    "wof:placetype":"postalcode"
},
  "geometry": {"coordinates":[-0.84785469751485,52.44200694197347],"type":"Point"}
}