{
  "type": "Feature",
  "properties": {
    "date:inception_lower": "1980-01-01",
    "date:inception_upper": "1980-01-01",
    "iso:country": "GB",
    "wof:name": "NN14 2LT",
    "wof:placetype": "postalcode"
  },
  "geometry": {"coordinates":[-0.847855,52.442007],"type":"Point"}
}
