{
  "type": "Feature",
  "properties": {
    "iso:country": "GB",
    "wof:name": "NN14 2LT",
    "wof:placetype": "postalcode"
  },
  "geometry": {"coordinates":[-0.847855,52.442007],"type":"Point"}
}
