{
  "type": "Feature",
  "properties": {
    "iso:country":"GB",
    "wof:name":"TQ13 7PB",
    "wof:placetype":"postalcode"
},
  "geometry": {"coordinates":[-3.82445932880142,50.53803422460047],"type":"Point"}
}