{
  "type": "Feature",
  "properties": {
    "date:inception_lower": "1980-01-01",
    "date:inception_upper": "1980-01-01",
    "iso:country": "GB",
    "wof:name": "TQ13 7PB",
    "wof:placetype": "postalcode"
  },
  "geometry": {"coordinates":[-3.824459,50.538034],"type":"Point"}
}
