{
  "type": "Feature",
  "properties": {
    "iso:country":"GB",
    "wof:name":"G43 2AF",
    "wof:placetype":"postalcode"
},
  "geometry": {"coordinates":[-4.29961862994318,55.81153145103582],"type":"Point"}
}