{
  "type": "Feature",
  "properties": {
    "iso:country": "GB",
    "wof:name": "BN1 3RA",
    "wof:placetype": "postalcode"
  },
  "geometry": {"coordinates":[-0.144724,50.827376],"type":"Point"}
}
