{
  "type": "Feature",
  "properties": {
    "date:inception_lower": "1980-01-01",
    "date:inception_upper": "1980-01-01",
    "iso:country": "GB",
    "wof:name": "IG1 4NH",
    "wof:placetype": "postalcode"
  },
  "geometry": {"coordinates":[0.069643,51.561213],"type":"Point"}
}
