{
  "type": "Feature",
  "properties": {
    "date:inception_lower": "2007-07-01",
    "date:inception_upper": "2007-07-01",
    "iso:country": "GB",
    "wof:name": "TA1 1NR",
    "wof:placetype": "postalcode"
  },
  "geometry": {"coordinates":[-3.105955,51.019943],"type":"Point"}
}
