{
  "type": "Feature",
  "properties": {
    "iso:country":"GB",
    "wof:name":"TA1 1NR",
    "wof:placetype":"postalcode"
},
  "geometry": {"coordinates":[-3.10595531340925,51.01994310076332],"type":"Point"}
}