{
  "type": "Feature",
  "properties": {
    "iso:country":"GB",
    "wof:name":"HU17 9QE",
    "wof:placetype":"postalcode"
},
  "geometry": {"coordinates":[-0.42203527493113,53.85042143774936],"type":"Point"}
}