{
  "type": "Feature",
  "properties": {
    "iso:country": "GB",
    "wof:name": "SG12 0LN",
    "wof:placetype": "postalcode"
  },
  "geometry": {"coordinates":[-0.066307,51.873379],"type":"Point"}
}
