{
  "type": "Feature",
  "properties": {
    "iso:country":"GB",
    "wof:name":"SG12 0LN",
    "wof:placetype":"postalcode"
},
  "geometry": {"coordinates":[-0.06630705191561,51.87337926462198],"type":"Point"}
}