{
  "type": "Feature",
  "properties": {
    "iso:country":"GB",
    "wof:name":"CB4 2SW",
    "wof:placetype":"postalcode"
},
  "geometry": {"coordinates":[0.12725880866552,52.23176416913758],"type":"Point"}
}