{
  "type": "Feature",
  "properties": {
    "iso:country":"GB",
    "wof:name":"CR3 5BY",
    "wof:placetype":"postalcode"
},
  "geometry": {"coordinates":[-0.10377122585314,51.28848131564171],"type":"Point"}
}