{
  "type": "Feature",
  "properties": {
    "iso:country":"GB",
    "wof:name":"PO2 8RA",
    "wof:placetype":"postalcode"
},
  "geometry": {"coordinates":[-1.09051534714495,50.82253719189379],"type":"Point"}
}