{
  "type": "Feature",
  "properties": {
    "iso:country":"GB",
    "wof:name":"RM12 4XQ",
    "wof:placetype":"postalcode"
},
  "geometry": {"coordinates":[0.21370187158402,51.56201722021779],"type":"Point"}
}