{
  "type": "Feature",
  "properties": {
    "iso:country": "GB",
    "wof:name": "CT15 4EN",
    "wof:placetype": "postalcode"
  },
  "geometry": {"coordinates":[1.260543,51.206653],"type":"Point"}
}
