{
  "type": "Feature",
  "properties": {
    "iso:country":"GB",
    "wof:name":"CT15 4EN",
    "wof:placetype":"postalcode"
},
  "geometry": {"coordinates":[1.26054281824463,51.2066526583072],"type":"Point"}
}