{
  "type": "Feature",
  "properties": {
    "iso:country": "GB",
    "wof:name": "ME20 6QP",
    "wof:placetype": "postalcode"
  },
  "geometry": {"coordinates":[0.453196,51.294763],"type":"Point"}
}
