{
  "type": "Feature",
  "properties": {
    "iso:country":"GB",
    "wof:name":"DE23 4AA",
    "wof:placetype":"postalcode"
},
  "geometry": {"coordinates":[-1.54071087384609,52.89754308231716],"type":"Point"}
}