{
  "type": "Feature",
  "properties": {
    "iso:country": "GB",
    "wof:name": "CM2 9HB",
    "wof:placetype": "postalcode"
  },
  "geometry": {"coordinates":[0.468559,51.7162],"type":"Point"}
}
