{
  "type": "Feature",
  "properties": {
    "iso:country":"GB",
    "wof:name":"MK45 1PZ",
    "wof:placetype":"postalcode"
},
  "geometry": {"coordinates":[-0.5071794342954,52.00481709606764],"type":"Point"}
}