{
  "type": "Feature",
  "properties": {
    "date:inception_lower": "1995-07-01",
    "date:inception_upper": "1995-07-01",
    "iso:country": "GB",
    "wof:name": "RG29 1JW",
    "wof:placetype": "postalcode"
  },
  "geometry": {"coordinates":[-0.927386,51.278636],"type":"Point"}
}
