{
  "type": "Feature",
  "properties": {
    "iso:country": "GB",
    "wof:name": "RG29 1JW",
    "wof:placetype": "postalcode"
  },
  "geometry": {"coordinates":[-0.927386,51.278636],"type":"Point"}
}
