{
  "type": "Feature",
  "properties": {
    "iso:country":"GB",
    "wof:name":"TN3 9NG",
    "wof:placetype":"postalcode"
},
  "geometry": {"coordinates":[0.19307261022816,51.109680148933],"type":"Point"}
}