{
  "type": "Feature",
  "properties": {
    "iso:country":"GB",
    "wof:name":"HU16 4AJ",
    "wof:placetype":"postalcode"
},
  "geometry": {"coordinates":[-0.41578071879806,53.77970372089495],"type":"Point"}
}