{
  "type": "Feature",
  "properties": {
    "iso:country": "GB",
    "wof:name": "HU16 4AJ",
    "wof:placetype": "postalcode"
  },
  "geometry": {"coordinates":[-0.415781,53.779704],"type":"Point"}
}
