{
  "type": "Feature",
  "properties": {
    "date:inception_lower": "1980-01-01",
    "date:inception_upper": "1980-01-01",
    "iso:country": "GB",
    "wof:name": "HU16 4AJ",
    "wof:placetype": "postalcode"
  },
  "geometry": {"coordinates":[-0.415781,53.779704],"type":"Point"}
}
