{
  "type": "Feature",
  "properties": {
    "iso:country":"GB",
    "wof:name":"G62 6DU",
    "wof:placetype":"postalcode"
},
  "geometry": {"coordinates":[-4.32682088548302,55.93825708584875],"type":"Point"}
}