{
  "type": "Feature",
  "properties": {
    "iso:country":"GB",
    "wof:name":"GL51 6DE",
    "wof:placetype":"postalcode"
},
  "geometry": {"coordinates":[-2.12061382406873,51.89509224426794],"type":"Point"}
}