{
  "type": "Feature",
  "properties": {
    "date:inception_lower": "1980-01-01",
    "date:inception_upper": "1980-01-01",
    "iso:country": "GB",
    "wof:name": "HG2 7ES",
    "wof:placetype": "postalcode"
  },
  "geometry": {"coordinates":[-1.490097,53.998052],"type":"Point"}
}
