{
  "type": "Feature",
  "properties": {
    "iso:country":"GB",
    "wof:name":"HG2 7ES",
    "wof:placetype":"postalcode"
},
  "geometry": {"coordinates":[-1.49009658216824,53.99805229279161],"type":"Point"}
}