{
  "type": "Feature",
  "properties": {
    "iso:country":"GB",
    "wof:name":"SL2 1TY",
    "wof:placetype":"postalcode"
},
  "geometry": {"coordinates":[-0.63652793400445,51.52883897101131],"type":"Point"}
}