{
  "type": "Feature",
  "properties": {
    "iso:country": "GB",
    "wof:name": "SL2 1TY",
    "wof:placetype": "postalcode"
  },
  "geometry": {"coordinates":[-0.63651,51.528842],"type":"Point"}
}
