{
  "type": "Feature",
  "properties": {
    "date:inception_lower": "1983-03-01",
    "date:inception_upper": "1983-03-01",
    "iso:country": "GB",
    "wof:name": "SL2 1TY",
    "wof:placetype": "postalcode"
  },
  "geometry": {"coordinates":[-0.63651,51.528842],"type":"Point"}
}
