{
  "type": "Feature",
  "properties": {
    "iso:country":"GB",
    "wof:name":"ST7 2JP",
    "wof:placetype":"postalcode"
},
  "geometry": {"coordinates":[-2.32899749869201,53.09107091245902],"type":"Point"}
}