{
  "type": "Feature",
  "properties": {
    "iso:country":"GB",
    "wof:name":"W1B 5PB",
    "wof:placetype":"postalcode"
},
  "geometry": {"coordinates":[-0.13858124650577,51.51220190557355],"type":"Point"}
}