{
  "type": "Feature",
  "properties": {
    "iso:country": "GB",
    "wof:name": "W1B 5PB",
    "wof:placetype": "postalcode"
  },
  "geometry": {"coordinates":[-0.138581,51.512202],"type":"Point"}
}
