{
  "type": "Feature",
  "properties": {
    "date:inception_lower": "2023-07-01",
    "date:inception_upper": "2023-07-01",
    "iso:country": "GB",
    "wof:name": "GU12 6TT",
    "wof:placetype": "postalcode"
  },
  "geometry": {"coordinates":[-0.707109,51.25025],"type":"Point"}
}
