{
  "type": "Feature",
  "properties": {
    "date:inception_lower": "2000-06-01",
    "date:inception_upper": "2000-06-01",
    "iso:country": "GB",
    "wof:name": "PE29 1EP",
    "wof:placetype": "postalcode"
  },
  "geometry": {"coordinates":[-0.17092,52.349991],"type":"Point"}
}
