{
  "type": "Feature",
  "properties": {
    "iso:country":"GB",
    "wof:name":"PE29 1EP",
    "wof:placetype":"postalcode"
},
  "geometry": {"coordinates":[-0.17092040172973,52.34999084425878],"type":"Point"}
}