{
  "type": "Feature",
  "properties": {
    "iso:country": "GB",
    "wof:name": "SY22 6AQ",
    "wof:placetype": "postalcode"
  },
  "geometry": {"coordinates":[-3.156588,52.774265],"type":"Point"}
}
