{
  "type": "Feature",
  "properties": {
    "iso:country":"GB",
    "wof:name":"SY22 6AQ",
    "wof:placetype":"postalcode"
},
  "geometry": {"coordinates":[-3.15658783239047,52.77426471674771],"type":"Point"}
}