{
  "type": "Feature",
  "properties": {
    "iso:country":"GB",
    "wof:name":"SK8 6QL",
    "wof:placetype":"postalcode"
},
  "geometry": {"coordinates":[-2.20690339815994,53.35568088613623],"type":"Point"}
}