{
  "type": "Feature",
  "properties": {
    "date:inception_lower": "2006-09-01",
    "date:inception_upper": "2006-09-01",
    "iso:country": "GB",
    "wof:name": "SK8 6QL",
    "wof:placetype": "postalcode"
  },
  "geometry": {"coordinates":[-2.205911,53.355816],"type":"Point"}
}
