{
  "type": "Feature",
  "properties": {
    "iso:country": "GB",
    "wof:name": "SK8 6QL",
    "wof:placetype": "postalcode"
  },
  "geometry": {"coordinates":[-2.206962,53.355465],"type":"Point"}
}
