{
  "type": "Feature",
  "properties": {
    "iso:country":"GB",
    "wof:name":"GU2 9XH",
    "wof:placetype":"postalcode"
},
  "geometry": {"coordinates":[-0.59481898101791,51.2591466568166],"type":"Point"}
}