{
  "type": "Feature",
  "properties": {
    "iso:country":"GB",
    "wof:name":"BL1 3TU",
    "wof:placetype":"postalcode"
},
  "geometry": {"coordinates":[-2.43833111048355,53.59041931688609],"type":"Point"}
}