{
  "type": "Feature",
  "properties": {
    "date:inception_lower":"1994-05-01",
    "date:inception_upper":"1994-05-31",
    "iso:country":"GB",
    "wof:name":"M22 0EN",
    "wof:placetype":"postalcode"
},
  "geometry": {"coordinates":[-2.257867,53.370916],"type":"Point"}
}