{
  "type": "Feature",
  "properties": {
    "iso:country": "GB",
    "wof:name": "M22 0EN",
    "wof:placetype": "postalcode"
  },
  "geometry": {"coordinates":[-2.257867,53.370916],"type":"Point"}
}
