{
  "type": "Feature",
  "properties": {
    "iso:country":"GB",
    "wof:name":"M22 0EN",
    "wof:placetype":"postalcode"
},
  "geometry": {"coordinates":[-2.25786733524069,53.37091616665284],"type":"Point"}
}