{
  "type": "Feature",
  "properties": {
    "iso:country":"GB",
    "wof:name":"CF48 4HA",
    "wof:placetype":"postalcode"
},
  "geometry": {"coordinates":[-3.34910367596041,51.71000487404853],"type":"Point"}
}