{
  "type": "Feature",
  "properties": {
    "iso:country":"GB",
    "wof:name":"DN20 0AH",
    "wof:placetype":"postalcode"
},
  "geometry": {"coordinates":[-0.55755664854352,53.56270103627934],"type":"Point"}
}