{
  "type": "Feature",
  "properties": {
    "iso:country":"GB",
    "wof:name":"RM1 2SH",
    "wof:placetype":"postalcode"
},
  "geometry": {"coordinates":[0.19165149348572,51.572431276483],"type":"Point"}
}