{
  "type": "Feature",
  "properties": {
    "date:inception_lower": "1980-01-01",
    "date:inception_upper": "1980-01-01",
    "iso:country": "GB",
    "wof:name": "TQ3 3AR",
    "wof:placetype": "postalcode"
  },
  "geometry": {"coordinates":[-3.571121,50.437924],"type":"Point"}
}
