{
  "type": "Feature",
  "properties": {
    "iso:country":"GB",
    "wof:name":"TQ3 3AR",
    "wof:placetype":"postalcode"
},
  "geometry": {"coordinates":[-3.5711213492719,50.43792444478195],"type":"Point"}
}