{
  "type": "Feature",
  "properties": {
    "iso:country":"GB",
    "wof:name":"EN3 6AE",
    "wof:placetype":"postalcode"
},
  "geometry": {"coordinates":[-0.03337619609004,51.67128037934262],"type":"Point"}
}