{
  "type": "Feature",
  "properties": {
    "iso:country":"GB",
    "wof:name":"EX8 4NQ",
    "wof:placetype":"postalcode"
},
  "geometry": {"coordinates":[-3.3947711611735,50.63122983722755],"type":"Point"}
}