{
  "type": "Feature",
  "properties": {
    "iso:country":"GB",
    "wof:name":"NR12 8QY",
    "wof:placetype":"postalcode"
},
  "geometry": {"coordinates":[1.40851528077365,52.73739163367625],"type":"Point"}
}