{
  "type": "Feature",
  "properties": {
    "iso:country": "GB",
    "wof:name": "NE48 1QZ",
    "wof:placetype": "postalcode"
  },
  "geometry": {"coordinates":[-2.537171,55.197177],"type":"Point"}
}
