{
  "type": "Feature",
  "properties": {
    "iso:country": "GB",
    "wof:name": "LS20 8NN",
    "wof:placetype": "postalcode"
  },
  "geometry": {"coordinates":[-1.724671,53.865313],"type":"Point"}
}
