{
  "type": "Feature",
  "properties": {
    "iso:country":"GB",
    "wof:name":"LS20 8NN",
    "wof:placetype":"postalcode"
},
  "geometry": {"coordinates":[-1.72467109502666,53.86531340129891],"type":"Point"}
}