{
  "type": "Feature",
  "properties": {
    "iso:country":"GB",
    "wof:name":"LL48 6LN",
    "wof:placetype":"postalcode"
},
  "geometry": {"coordinates":[-4.06552766982392,52.92940978264102],"type":"Point"}
}