{
  "type": "Feature",
  "properties": {
    "iso:country": "GB",
    "wof:name": "LL48 6LN",
    "wof:placetype": "postalcode"
  },
  "geometry": {"coordinates":[-4.065528,52.92941],"type":"Point"}
}
