{
  "type": "Feature",
  "properties": {
    "date:inception_lower": "1980-01-01",
    "date:inception_upper": "1980-01-01",
    "iso:country": "GB",
    "wof:name": "IV6 7TL",
    "wof:placetype": "postalcode"
  },
  "geometry": {"coordinates":[-4.465571,57.514804],"type":"Point"}
}
