{
  "type": "Feature",
  "properties": {
    "iso:country":"GB",
    "wof:name":"IV6 7TL",
    "wof:placetype":"postalcode"
},
  "geometry": {"coordinates":[-4.46491512568185,57.51496913942653],"type":"Point"}
}