{
  "type": "Feature",
  "properties": {
    "date:inception_lower": "1993-08-01",
    "date:inception_upper": "1993-08-01",
    "iso:country": "GB",
    "wof:name": "WD7 9JE",
    "wof:placetype": "postalcode"
  },
  "geometry": {"coordinates":[-0.290106,51.696673],"type":"Point"}
}
