{
  "type": "Feature",
  "properties": {
    "iso:country":"GB",
    "wof:name":"WD7 9JE",
    "wof:placetype":"postalcode"
},
  "geometry": {"coordinates":[-0.2901061601327,51.69667295365162],"type":"Point"}
}