{
  "type": "Feature",
  "properties": {
    "iso:country":"GB",
    "wof:name":"LE1 5GW",
    "wof:placetype":"postalcode"
},
  "geometry": {"coordinates":[-1.13405046872296,52.63524576429371],"type":"Point"}
}