{
  "type": "Feature",
  "properties": {
    "date:inception_lower": "1980-01-01",
    "date:inception_upper": "1980-01-01",
    "iso:country": "GB",
    "wof:name": "BA22 9DY",
    "wof:placetype": "postalcode"
  },
  "geometry": {"coordinates":[-2.718879,50.916271],"type":"Point"}
}
