{
  "type": "Feature",
  "properties": {
    "date:inception_lower":"1980-01-01",
    "date:inception_upper":"1980-01-31",
    "iso:country":"GB",
    "wof:name":"M24 2QL",
    "wof:placetype":"postalcode"
},
  "geometry": {"coordinates":[-2.184889,53.56256],"type":"Point"}
}