{
  "type": "Feature",
  "properties": {
    "iso:country":"GB",
    "wof:name":"M24 2QL",
    "wof:placetype":"postalcode"
},
  "geometry": {"coordinates":[-2.18488933124187,53.56255998824572],"type":"Point"}
}