{
  "type": "Feature",
  "properties": {
    "iso:country":"GB",
    "wof:name":"PR6 0AW",
    "wof:placetype":"postalcode"
},
  "geometry": {"coordinates":[-2.61713124858742,53.65694427119415],"type":"Point"}
}