{
  "type": "Feature",
  "properties": {
    "iso:country":"GB",
    "wof:name":"BH6 5NF",
    "wof:placetype":"postalcode"
},
  "geometry": {"coordinates":[-1.79559615855558,50.73245901521351],"type":"Point"}
}