{
  "type": "Feature",
  "properties": {
    "iso:country":"GB",
    "wof:name":"EX14 1JB",
    "wof:placetype":"postalcode"
},
  "geometry": {"coordinates":[-3.19508572142737,50.79531589855755],"type":"Point"}
}