{
  "type": "Feature",
  "properties": {
    "iso:country": "GB",
    "wof:name": "TS12 2WQ",
    "wof:placetype": "postalcode"
  },
  "geometry": {"coordinates":[-0.978532,54.566555],"type":"Point"}
}
