{
  "type": "Feature",
  "properties": {
    "iso:country":"GB",
    "wof:name":"TS12 2WQ",
    "wof:placetype":"postalcode"
},
  "geometry": {"coordinates":[-0.97853204587585,54.56655498812467],"type":"Point"}
}