{
  "type": "Feature",
  "properties": {
    "iso:country": "GB",
    "wof:name": "PO9 5SS",
    "wof:placetype": "postalcode"
  },
  "geometry": {"coordinates":[-0.970845,50.869187],"type":"Point"}
}
