{
  "type": "Feature",
  "properties": {
    "iso:country":"GB",
    "wof:name":"SL4 6NW",
    "wof:placetype":"postalcode"
},
  "geometry": {"coordinates":[-0.64148192234031,51.50042773810419],"type":"Point"}
}