{
  "type": "Feature",
  "properties": {
    "iso:country": "GB",
    "wof:name": "SL4 6NW",
    "wof:placetype": "postalcode"
  },
  "geometry": {"coordinates":[-0.641482,51.500428],"type":"Point"}
}
