{
  "type": "Feature",
  "properties": {
    "iso:country": "GB",
    "wof:name": "HD2 2NQ",
    "wof:placetype": "postalcode"
  },
  "geometry": {"coordinates":[-1.79146,53.668484],"type":"Point"}
}
