{
  "type": "Feature",
  "properties": {
    "iso:country": "GB",
    "wof:name": "CR7 6DW",
    "wof:placetype": "postalcode"
  },
  "geometry": {"coordinates":[-0.118284,51.394722],"type":"Point"}
}
