{
  "type": "Feature",
  "properties": {
    "iso:country":"GB",
    "wof:name":"SN4 9DE",
    "wof:placetype":"postalcode"
},
  "geometry": {"coordinates":[-1.79240288139062,51.5220005639358],"type":"Point"}
}