{
  "type": "Feature",
  "properties": {
    "iso:country": "GB",
    "wof:name": "SN4 9DE",
    "wof:placetype": "postalcode"
  },
  "geometry": {"coordinates":[-1.792403,51.522001],"type":"Point"}
}
