{
  "type": "Feature",
  "properties": {
    "iso:country": "GB",
    "wof:name": "ME14 5NX",
    "wof:placetype": "postalcode"
  },
  "geometry": {"coordinates":[0.537149,51.27539],"type":"Point"}
}
