{
  "type": "Feature",
  "properties": {
    "iso:country":"GB",
    "wof:name":"ME14 5NX",
    "wof:placetype":"postalcode"
},
  "geometry": {"coordinates":[0.53714932603862,51.2753902187135],"type":"Point"}
}