{
  "type": "Feature",
  "properties": {
    "iso:country": "GB",
    "wof:name": "PE11 4XJ",
    "wof:placetype": "postalcode"
  },
  "geometry": {"coordinates":[-0.20529,52.903655],"type":"Point"}
}
