{
  "type": "Feature",
  "properties": {
    "iso:country":"GB",
    "wof:name":"PE11 4XJ",
    "wof:placetype":"postalcode"
},
  "geometry": {"coordinates":[-0.20529002732589,52.90365545136474],"type":"Point"}
}