{
  "type": "Feature",
  "properties": {
    "iso:country":"GB",
    "wof:name":"E14 3EW",
    "wof:placetype":"postalcode"
},
  "geometry": {"coordinates":[-0.00436204631726,51.4898152936825],"type":"Point"}
}