{
  "type": "Feature",
  "properties": {
    "iso:country": "GB",
    "wof:name": "DL13 2NR",
    "wof:placetype": "postalcode"
  },
  "geometry": {"coordinates":[-2.012801,54.75118],"type":"Point"}
}
