{
  "type": "Feature",
  "properties": {
    "iso:country":"GB",
    "wof:name":"DL13 2NR",
    "wof:placetype":"postalcode"
},
  "geometry": {"coordinates":[-2.01280122184677,54.75118042977168],"type":"Point"}
}