{
  "type": "Feature",
  "properties": {
    "iso:country": "GB",
    "wof:name": "RH14 0EG",
    "wof:placetype": "postalcode"
  },
  "geometry": {"coordinates":[-0.493484,51.030183],"type":"Point"}
}
