{
  "type": "Feature",
  "properties": {
    "iso:country":"GB",
    "wof:name":"NE11 9HH",
    "wof:placetype":"postalcode"
},
  "geometry": {"coordinates":[-1.64518797258263,54.95654205355723],"type":"Point"}
}