{
  "type": "Feature",
  "properties": {
    "iso:country":"GB",
    "wof:name":"ST17 4EH",
    "wof:placetype":"postalcode"
},
  "geometry": {"coordinates":[-2.10874811654808,52.78733373599],"type":"Point"}
}