{
  "type": "Feature",
  "properties": {
    "iso:country":"GB",
    "wof:name":"B24 0GD",
    "wof:placetype":"postalcode"
},
  "geometry": {"coordinates":[-1.81550299930315,52.51980606492994],"type":"Point"}
}