{
  "type": "Feature",
  "properties": {
    "date:inception_lower": "1998-12-01",
    "date:inception_upper": "1998-12-01",
    "iso:country": "GB",
    "wof:name": "B24 0GD",
    "wof:placetype": "postalcode"
  },
  "geometry": {"coordinates":[-1.815503,52.519806],"type":"Point"}
}
