{
  "type": "Feature",
  "properties": {
    "iso:country": "GB",
    "wof:name": "CH5 3PS",
    "wof:placetype": "postalcode"
  },
  "geometry": {"coordinates":[-2.98691,53.183151],"type":"Point"}
}
