{
  "type": "Feature",
  "properties": {
    "iso:country":"GB",
    "wof:name":"CH5 3PS",
    "wof:placetype":"postalcode"
},
  "geometry": {"coordinates":[-2.9869099453317,53.18315089730488],"type":"Point"}
}