{
  "type": "Feature",
  "properties": {
    "date:inception_lower": "1980-01-01",
    "date:inception_upper": "1980-01-01",
    "iso:country": "GB",
    "wof:name": "SW1W 9SX",
    "wof:placetype": "postalcode"
  },
  "geometry": {"coordinates":[-0.149605,51.491604],"type":"Point"}
}
