{
  "type": "Feature",
  "properties": {
    "iso:country":"GB",
    "wof:name":"SW1W 9SX",
    "wof:placetype":"postalcode"
},
  "geometry": {"coordinates":[-0.14960486078547,51.4916036359966],"type":"Point"}
}