{
  "type": "Feature",
  "properties": {
    "iso:country":"GB",
    "wof:name":"NP22 4LF",
    "wof:placetype":"postalcode"
},
  "geometry": {"coordinates":[-3.23578501246618,51.76556088820196],"type":"Point"}
}