{
  "type": "Feature",
  "properties": {
    "iso:country": "GB",
    "wof:name": "DE24 3BR",
    "wof:placetype": "postalcode"
  },
  "geometry": {"coordinates":[-1.508354,52.877053],"type":"Point"}
}
