{
  "type": "Feature",
  "properties": {
    "iso:country":"GB",
    "wof:name":"E8 4QL",
    "wof:placetype":"postalcode"
},
  "geometry": {"coordinates":[-0.0614085762222,51.53556441891775],"type":"Point"}
}