{
  "type": "Feature",
  "properties": {
    "date:inception_lower": "2023-02-01",
    "date:inception_upper": "2023-02-01",
    "iso:country": "GB",
    "wof:name": "SL5 8QP",
    "wof:placetype": "postalcode"
  },
  "geometry": {"coordinates":[-0.677105,51.430338],"type":"Point"}
}
