{
  "type": "Feature",
  "properties": {
    "date:inception_lower": "2020-10-01",
    "date:inception_upper": "2020-10-01",
    "iso:country": "GB",
    "wof:name": "SP11 6QN",
    "wof:placetype": "postalcode"
  },
  "geometry": {"coordinates":[-1.444925,51.221784],"type":"Point"}
}
