{
  "type": "Feature",
  "properties": {
    "iso:country": "GB",
    "wof:name": "DN21 2RE",
    "wof:placetype": "postalcode"
  },
  "geometry": {"coordinates":[-0.775439,53.406402],"type":"Point"}
}
