{
  "type": "Feature",
  "properties": {
    "iso:country":"GB",
    "wof:name":"SS14 1DF",
    "wof:placetype":"postalcode"
},
  "geometry": {"coordinates":[0.45658764620854,51.56945798731194],"type":"Point"}
}