{
  "type": "Feature",
  "properties": {
    "date:inception_lower":"1980-01-01",
    "date:inception_upper":"1980-01-31",
    "iso:country":"GB",
    "wof:name":"CA14 5AS",
    "wof:placetype":"postalcode"
},
  "geometry": {"coordinates":[-3.555869,54.628554],"type":"Point"}
}