{
  "type": "Feature",
  "properties": {
    "iso:country":"GB",
    "wof:name":"NE24 4QW",
    "wof:placetype":"postalcode"
},
  "geometry": {"coordinates":[-1.53061762517631,55.11720477331254],"type":"Point"}
}