{
  "type": "Feature",
  "properties": {
    "iso:country":"GB",
    "wof:name":"M34 6ED",
    "wof:placetype":"postalcode"
},
  "geometry": {"coordinates":[-2.10434961868585,53.45425746651565],"type":"Point"}
}