{
  "type": "Feature",
  "properties": {
    "iso:country":"GB",
    "wof:name":"EX39 5AQ",
    "wof:placetype":"postalcode"
},
  "geometry": {"coordinates":[-4.22176688229538,51.01029796148727],"type":"Point"}
}