{
  "type": "Feature",
  "properties": {
    "iso:country": "GB",
    "wof:name": "CW8 1TH",
    "wof:placetype": "postalcode"
  },
  "geometry": {"coordinates":[-2.528412,53.250534],"type":"Point"}
}
