{
  "type": "Feature",
  "properties": {
    "date:inception_lower":"1980-01-01",
    "date:inception_upper":"1980-01-31",
    "iso:country":"GB",
    "wof:name":"KT2 7SL",
    "wof:placetype":"postalcode"
},
  "geometry": {"coordinates":[-0.285851,51.418507],"type":"Point"}
}