{
  "type": "Feature",
  "properties": {
    "iso:country":"GB",
    "wof:name":"KT2 7SL",
    "wof:placetype":"postalcode"
},
  "geometry": {"coordinates":[-0.28585132153232,51.41850656667088],"type":"Point"}
}