{
  "type": "Feature",
  "properties": {
    "iso:country": "GB",
    "wof:name": "KT2 7SL",
    "wof:placetype": "postalcode"
  },
  "geometry": {"coordinates":[-0.285851,51.418507],"type":"Point"}
}
