{
  "type": "Feature",
  "properties": {
    "date:inception_lower":"1986-07-01",
    "date:inception_upper":"1986-07-31",
    "iso:country":"GB",
    "wof:name":"PO9 2XH",
    "wof:placetype":"postalcode"
},
  "geometry": {"coordinates":[-0.967263,50.849263],"type":"Point"}
}