{
  "type": "Feature",
  "properties": {
    "iso:country":"GB",
    "wof:name":"PO9 2XH",
    "wof:placetype":"postalcode"
},
  "geometry": {"coordinates":[-0.96726290439009,50.8492633566944],"type":"Point"}
}