{
  "type": "Feature",
  "properties": {
    "iso:country":"GB",
    "wof:name":"WD6 2EH",
    "wof:placetype":"postalcode"
},
  "geometry": {"coordinates":[-0.27591341604155,51.65243104978828],"type":"Point"}
}