{
  "type": "Feature",
  "properties": {
    "date:inception_lower":"1990-02-01",
    "date:inception_upper":"1990-02-28",
    "iso:country":"GB",
    "wof:name":"WD6 2EH",
    "wof:placetype":"postalcode"
},
  "geometry": {"coordinates":[-0.275913,51.652431],"type":"Point"}
}