{
  "type": "Feature",
  "properties": {
    "date:inception_lower": "2008-09-01",
    "date:inception_upper": "2008-09-01",
    "iso:country": "GB",
    "wof:name": "W5 2AY",
    "wof:placetype": "postalcode"
  },
  "geometry": {"coordinates":[-0.295478,51.523849],"type":"Point"}
}
