{
  "type": "Feature",
  "properties": {
    "iso:country": "GB",
    "wof:name": "SS2 5NN",
    "wof:placetype": "postalcode"
  },
  "geometry": {"coordinates":[0.708591,51.561238],"type":"Point"}
}
