{
  "type": "Feature",
  "properties": {
    "iso:country":"GB",
    "wof:name":"SS2 5NN",
    "wof:placetype":"postalcode"
},
  "geometry": {"coordinates":[0.70859109750485,51.56123837064762],"type":"Point"}
}