{
  "type": "Feature",
  "properties": {
    "iso:country":"GB",
    "wof:name":"LN2 4LJ",
    "wof:placetype":"postalcode"
},
  "geometry": {"coordinates":[-0.51704130117905,53.24229907599568],"type":"Point"}
}