{
  "type": "Feature",
  "properties": {
    "date:inception_lower": "1980-01-01",
    "date:inception_upper": "1980-01-01",
    "iso:country": "GB",
    "wof:name": "LN2 4LJ",
    "wof:placetype": "postalcode"
  },
  "geometry": {"coordinates":[-0.517041,53.242299],"type":"Point"}
}
