{
  "type": "Feature",
  "properties": {
    "date:inception_lower":"1991-01-01",
    "date:inception_upper":"1991-01-31",
    "iso:country":"GB",
    "wof:name":"SG3 6LT",
    "wof:placetype":"postalcode"
},
  "geometry": {"coordinates":[-0.178087,51.850507],"type":"Point"}
}