{
  "type": "Feature",
  "properties": {
    "iso:country":"GB",
    "wof:name":"SG3 6LT",
    "wof:placetype":"postalcode"
},
  "geometry": {"coordinates":[-0.17808690928807,51.85050745049021],"type":"Point"}
}