{
  "type": "Feature",
  "properties": {
    "iso:country": "GB",
    "wof:name": "SG3 6LT",
    "wof:placetype": "postalcode"
  },
  "geometry": {"coordinates":[-0.178087,51.850507],"type":"Point"}
}
