{
  "type": "Feature",
  "properties": {
    "iso:country": "GB",
    "wof:name": "TN16 3JE",
    "wof:placetype": "postalcode"
  },
  "geometry": {"coordinates":[0.047489,51.306186],"type":"Point"}
}
