{
  "type": "Feature",
  "properties": {
    "date:inception_lower": "1999-12-01",
    "date:inception_upper": "1999-12-01",
    "iso:country": "GB",
    "wof:name": "TN16 3JE",
    "wof:placetype": "postalcode"
  },
  "geometry": {"coordinates":[0.047489,51.306186],"type":"Point"}
}
