{
  "type": "Feature",
  "properties": {
    "iso:country":"GB",
    "wof:name":"NP23 6WB",
    "wof:placetype":"postalcode"
},
  "geometry": {"coordinates":[-3.22396445160134,51.78071842034024],"type":"Point"}
}