{
  "type": "Feature",
  "properties": {
    "iso:country": "GB",
    "wof:name": "WA12 9NH",
    "wof:placetype": "postalcode"
  },
  "geometry": {"coordinates":[-2.647377,53.452242],"type":"Point"}
}
