{
  "type": "Feature",
  "properties": {
    "iso:country":"GB",
    "wof:name":"NG2 4PQ",
    "wof:placetype":"postalcode"
},
  "geometry": {"coordinates":[-1.13716524793052,52.95177067102247],"type":"Point"}
}