{
  "type": "Feature",
  "properties": {
    "iso:country":"GB",
    "wof:name":"KA4 8NE",
    "wof:placetype":"postalcode"
},
  "geometry": {"coordinates":[-4.36293907622272,55.58407790663771],"type":"Point"}
}