{
  "type": "Feature",
  "properties": {
    "iso:country":"GB",
    "wof:name":"PH33 6EA",
    "wof:placetype":"postalcode"
},
  "geometry": {"coordinates":[-5.11513338139096,56.81599365750492],"type":"Point"}
}