{
  "type": "Feature",
  "properties": {
    "iso:country":"GB",
    "wof:name":"G81 2YD",
    "wof:placetype":"postalcode"
},
  "geometry": {"coordinates":[-4.40274208395015,55.91556107819528],"type":"Point"}
}