{
  "type": "Feature",
  "properties": {
    "date:inception_lower": "1992-10-01",
    "date:inception_upper": "1992-10-01",
    "iso:country": "GB",
    "wof:name": "G81 2YD",
    "wof:placetype": "postalcode"
  },
  "geometry": {"coordinates":[-4.402742,55.915546],"type":"Point"}
}
