{
  "type": "Feature",
  "properties": {
    "iso:country":"GB",
    "wof:name":"DN36 5RY",
    "wof:placetype":"postalcode"
},
  "geometry": {"coordinates":[-0.05662963791302,53.46395864913418],"type":"Point"}
}