{
  "type": "Feature",
  "properties": {
    "date:inception_lower": "1992-01-01",
    "date:inception_upper": "1992-01-01",
    "iso:country": "GB",
    "wof:name": "DN36 5RY",
    "wof:placetype": "postalcode"
  },
  "geometry": {"coordinates":[-0.056604,53.463965],"type":"Point"}
}
