{
  "type": "Feature",
  "properties": {
    "iso:country":"GB",
    "wof:name":"RG26 4BX",
    "wof:placetype":"postalcode"
},
  "geometry": {"coordinates":[-1.15211201898541,51.35393368152673],"type":"Point"}
}