{
  "type": "Feature",
  "properties": {
    "iso:country":"GB",
    "wof:name":"B62 9SN",
    "wof:placetype":"postalcode"
},
  "geometry": {"coordinates":[-2.01707283126558,52.46089324853985],"type":"Point"}
}