{
  "type": "Feature",
  "properties": {
    "date:inception_lower": "2023-04-01",
    "date:inception_upper": "2023-04-01",
    "iso:country": "GB",
    "wof:name": "B63 4DG",
    "wof:placetype": "postalcode"
  },
  "geometry": {"coordinates":[-2.059691,52.440658],"type":"Point"}
}
