{
  "type": "Feature",
  "properties": {
    "iso:country": "GB",
    "wof:name": "PA38 4DQ",
    "wof:placetype": "postalcode"
  },
  "geometry": {"coordinates":[-5.401467,56.547244],"type":"Point"}
}
