{
  "type": "Feature",
  "properties": {
    "iso:country":"GB",
    "wof:name":"LS26 8GH",
    "wof:placetype":"postalcode"
},
  "geometry": {"coordinates":[-1.44853587192377,53.7533782899314],"type":"Point"}
}