{
  "type": "Feature",
  "properties": {
    "date:inception_lower":"2009-08-01",
    "date:inception_upper":"2009-08-31",
    "iso:country":"GB",
    "wof:name":"LS26 8GH",
    "wof:placetype":"postalcode"
},
  "geometry": {"coordinates":[-1.448536,53.753378],"type":"Point"}
}