{
  "type": "Feature",
  "properties": {
    "date:inception_lower": "1998-12-01",
    "date:inception_upper": "1998-12-01",
    "iso:country": "GB",
    "wof:name": "B43 5PE",
    "wof:placetype": "postalcode"
  },
  "geometry": {"coordinates":[-1.936327,52.535287],"type":"Point"}
}
