{
  "type": "Feature",
  "properties": {
    "iso:country":"GB",
    "wof:name":"TN26 1EG",
    "wof:placetype":"postalcode"
},
  "geometry": {"coordinates":[0.82007455641457,51.16972508847132],"type":"Point"}
}