{
  "type": "Feature",
  "properties": {
    "iso:country": "GB",
    "wof:name": "TN26 1EG",
    "wof:placetype": "postalcode"
  },
  "geometry": {"coordinates":[0.820075,51.169725],"type":"Point"}
}
