{
  "type": "Feature",
  "properties": {
    "iso:country":"GB",
    "wof:name":"NE63 9BS",
    "wof:placetype":"postalcode"
},
  "geometry": {"coordinates":[-1.56124531287098,55.18226081981717],"type":"Point"}
}