{
  "type": "Feature",
  "properties": {
    "iso:country":"GB",
    "wof:name":"WA4 2NN",
    "wof:placetype":"postalcode"
},
  "geometry": {"coordinates":[-2.54551279408669,53.37864869716916],"type":"Point"}
}