{
  "type": "Feature",
  "properties": {
    "iso:country":"GB",
    "wof:name":"W9 1JJ",
    "wof:placetype":"postalcode"
},
  "geometry": {"coordinates":[-0.18881819422825,51.52896799295446],"type":"Point"}
}