{
  "type": "Feature",
  "properties": {
    "iso:country": "GB",
    "wof:name": "TQ13 7AE",
    "wof:placetype": "postalcode"
  },
  "geometry": {"coordinates":[-3.756257,50.516473],"type":"Point"}
}
