{
  "type": "Feature",
  "properties": {
    "iso:country":"GB",
    "wof:name":"TQ13 7AE",
    "wof:placetype":"postalcode"
},
  "geometry": {"coordinates":[-3.75625748867256,50.51647292689393],"type":"Point"}
}