{
  "type": "Feature",
  "properties": {
    "date:inception_lower": "2021-06-01",
    "date:inception_upper": "2021-06-01",
    "iso:country": "GB",
    "wof:name": "AB30 1JE",
    "wof:placetype": "postalcode"
  },
  "geometry": {"coordinates":[-2.47957,56.831422],"type":"Point"}
}
