{
  "type": "Feature",
  "properties": {
    "iso:country":"GB",
    "wof:name":"G60 5AR",
    "wof:placetype":"postalcode"
},
  "geometry": {"coordinates":[-4.4446321466776,55.92331068669295],"type":"Point"}
}