{
  "type": "Feature",
  "properties": {
    "iso:country":"GB",
    "wof:name":"PL17 7JW",
    "wof:placetype":"postalcode"
},
  "geometry": {"coordinates":[-4.33043236062308,50.50534705540434],"type":"Point"}
}