{
  "type": "Feature",
  "properties": {
    "date:inception_lower":"1980-01-01",
    "date:inception_upper":"1980-01-31",
    "iso:country":"GB",
    "wof:name":"PL17 7JW",
    "wof:placetype":"postalcode"
},
  "geometry": {"coordinates":[-4.330432,50.505347],"type":"Point"}
}