{
  "type": "Feature",
  "properties": {
    "iso:country":"GB",
    "wof:name":"TN18 5JR",
    "wof:placetype":"postalcode"
},
  "geometry": {"coordinates":[0.56691564664917,51.02495288334527],"type":"Point"}
}