{
  "type": "Feature",
  "properties": {
    "date:inception_lower": "2020-05-01",
    "date:inception_upper": "2020-05-01",
    "iso:country": "GB",
    "wof:name": "DL12 2BN",
    "wof:placetype": "postalcode"
  },
  "geometry": {"coordinates":[-1.922067,54.554303],"type":"Point"}
}
