{
  "type": "Feature",
  "properties": {
    "iso:country":"GB",
    "wof:name":"CV35 8DS",
    "wof:placetype":"postalcode"
},
  "geometry": {"coordinates":[-1.60642358017853,52.24028618624434],"type":"Point"}
}