{
  "type": "Feature",
  "properties": {
    "date:inception_lower":"2002-11-01",
    "date:inception_upper":"2002-11-30",
    "iso:country":"GB",
    "wof:name":"BH22 8NQ",
    "wof:placetype":"postalcode"
},
  "geometry": {"coordinates":[-1.879979,50.792143],"type":"Point"}
}