{
  "type": "Feature",
  "properties": {
    "iso:country":"GB",
    "wof:name":"TW8 0GE",
    "wof:placetype":"postalcode"
},
  "geometry": {"coordinates":[-0.30195212060949,51.49006875279767],"type":"Point"}
}