{
  "type": "Feature",
  "properties": {
    "iso:country":"GB",
    "wof:name":"NW1 8XE",
    "wof:placetype":"postalcode"
},
  "geometry": {"coordinates":[-0.15819257063011,51.54085576589767],"type":"Point"}
}