{
  "type": "Feature",
  "properties": {
    "iso:country": "GB",
    "wof:name": "AB21 0YA",
    "wof:placetype": "postalcode"
  },
  "geometry": {"coordinates":[-2.26747,57.23767],"type":"Point"}
}
