{
  "type": "Feature",
  "properties": {
    "date:inception_lower": "2021-02-01",
    "date:inception_upper": "2021-02-01",
    "iso:country": "GB",
    "wof:name": "CM24 8YT",
    "wof:placetype": "postalcode"
  },
  "geometry": {"coordinates":[0.202445,51.907816],"type":"Point"}
}
