{
  "type": "Feature",
  "properties": {
    "iso:country": "GB",
    "wof:name": "NE6 2AR",
    "wof:placetype": "postalcode"
  },
  "geometry": {"coordinates":[-1.580087,54.971286],"type":"Point"}
}
