{
  "type": "Feature",
  "properties": {
    "iso:country":"GB",
    "wof:name":"NE6 2AR",
    "wof:placetype":"postalcode"
},
  "geometry": {"coordinates":[-1.57992288863165,54.97079319748127],"type":"Point"}
}