{
  "type": "Feature",
  "properties": {
    "iso:country":"GB",
    "wof:name":"YO30 4YE",
    "wof:placetype":"postalcode"
},
  "geometry": {"coordinates":[-1.09832105071682,53.98325935474092],"type":"Point"}
}