{
  "type": "Feature",
  "properties": {
    "iso:country": "GB",
    "wof:name": "L12 0PR",
    "wof:placetype": "postalcode"
  },
  "geometry": {"coordinates":[-2.878463,53.455009],"type":"Point"}
}
