{
  "type": "Feature",
  "properties": {
    "iso:country": "GB",
    "wof:name": "HR3 5RN",
    "wof:placetype": "postalcode"
  },
  "geometry": {"coordinates":[-3.083959,52.035969],"type":"Point"}
}
