{
  "type": "Feature",
  "properties": {
    "date:inception_lower":"1980-01-01",
    "date:inception_upper":"1980-01-31",
    "iso:country":"GB",
    "wof:name":"HR3 5RN",
    "wof:placetype":"postalcode"
},
  "geometry": {"coordinates":[-3.083959,52.035969],"type":"Point"}
}