{
  "type": "Feature",
  "properties": {
    "iso:country": "GB",
    "wof:name": "CA15 8EY",
    "wof:placetype": "postalcode"
  },
  "geometry": {"coordinates":[-3.494638,54.704274],"type":"Point"}
}
