{
  "type": "Feature",
  "properties": {
    "iso:country":"GB",
    "wof:name":"CA15 8EY",
    "wof:placetype":"postalcode"
},
  "geometry": {"coordinates":[-3.49463789347433,54.70427361956513],"type":"Point"}
}