{
  "type": "Feature",
  "properties": {
    "iso:country":"GB",
    "wof:name":"PE33 9RR",
    "wof:placetype":"postalcode"
},
  "geometry": {"coordinates":[0.44420645094392,52.57702005070343],"type":"Point"}
}