{
  "type": "Feature",
  "properties": {
    "date:inception_lower": "2003-10-01",
    "date:inception_upper": "2003-10-01",
    "iso:country": "GB",
    "wof:name": "E3 2DH",
    "wof:placetype": "postalcode"
  },
  "geometry": {"coordinates":[-0.02502,51.53511],"type":"Point"}
}
