{
  "type": "Feature",
  "properties": {
    "iso:country": "GB",
    "wof:name": "NP12 3NX",
    "wof:placetype": "postalcode"
  },
  "geometry": {"coordinates":[-3.217909,51.665069],"type":"Point"}
}
