{
  "type": "Feature",
  "properties": {
    "iso:country":"GB",
    "wof:name":"NP12 3NX",
    "wof:placetype":"postalcode"
},
  "geometry": {"coordinates":[-3.21790934744704,51.66506853890905],"type":"Point"}
}