{
  "type": "Feature",
  "properties": {
    "iso:country":"GB",
    "wof:name":"NG5 6AZ",
    "wof:placetype":"postalcode"
},
  "geometry": {"coordinates":[-1.13927749348101,52.99756940597761],"type":"Point"}
}