{
  "type": "Feature",
  "properties": {
    "date:inception_lower":"1980-01-01",
    "date:inception_upper":"1980-01-31",
    "iso:country":"GB",
    "wof:name":"TR18 3DJ",
    "wof:placetype":"postalcode"
},
  "geometry": {"coordinates":[-5.528082,50.13131],"type":"Point"}
}