{
  "type": "Feature",
  "properties": {
    "iso:country":"GB",
    "wof:name":"NW1 5DA",
    "wof:placetype":"postalcode"
},
  "geometry": {"coordinates":[-0.16804921611072,51.5209209613656],"type":"Point"}
}