{
  "type": "Feature",
  "properties": {
    "iso:country": "GB",
    "wof:name": "W4 2BY",
    "wof:placetype": "postalcode"
  },
  "geometry": {"coordinates":[-0.255961,51.489619],"type":"Point"}
}
