{
  "type": "Feature",
  "properties": {
    "iso:country":"GB",
    "wof:name":"W4 2BY",
    "wof:placetype":"postalcode"
},
  "geometry": {"coordinates":[-0.25596139515271,51.48961862598923],"type":"Point"}
}