{
  "type": "Feature",
  "properties": {
    "date:inception_lower": "1980-01-01",
    "date:inception_upper": "1980-01-01",
    "iso:country": "GB",
    "wof:name": "W4 2BY",
    "wof:placetype": "postalcode"
  },
  "geometry": {"coordinates":[-0.255961,51.489619],"type":"Point"}
}
