{
  "type": "Feature",
  "properties": {
    "iso:country": "GB",
    "wof:name": "WV8 2BA",
    "wof:placetype": "postalcode"
  },
  "geometry": {"coordinates":[-2.210718,52.622548],"type":"Point"}
}
