{
  "type": "Feature",
  "properties": {
    "iso:country":"GB",
    "wof:name":"WV8 2BA",
    "wof:placetype":"postalcode"
},
  "geometry": {"coordinates":[-2.21072225109357,52.62253318485559],"type":"Point"}
}