{
  "type": "Feature",
  "properties": {
    "date:inception_lower":"1994-12-01",
    "date:inception_upper":"1994-12-31",
    "iso:country":"GB",
    "wof:name":"SO18 6NQ",
    "wof:placetype":"postalcode"
},
  "geometry": {"coordinates":[-1.351123,50.918213],"type":"Point"}
}