{
  "type": "Feature",
  "properties": {
    "iso:country":"GB",
    "wof:name":"KA22 7HZ",
    "wof:placetype":"postalcode"
},
  "geometry": {"coordinates":[-4.80443033761292,55.65642479705747],"type":"Point"}
}