{
  "type": "Feature",
  "properties": {
    "date:inception_lower": "2019-12-01",
    "date:inception_upper": "2019-12-01",
    "iso:country": "GB",
    "wof:name": "MK43 9SX",
    "wof:placetype": "postalcode"
  },
  "geometry": {"coordinates":[-0.504276,52.071544],"type":"Point"}
}
