{
  "type": "Feature",
  "properties": {
    "date:inception_lower": "2020-08-01",
    "date:inception_upper": "2020-08-01",
    "iso:country": "GB",
    "wof:name": "RH20 2GX",
    "wof:placetype": "postalcode"
  },
  "geometry": {"coordinates":[-0.473181,50.947232],"type":"Point"}
}
