{
  "type": "Feature",
  "properties": {
    "iso:country": "GB",
    "wof:name": "OX14 5GU",
    "wof:placetype": "postalcode"
  },
  "geometry": {"coordinates":[-1.286026,51.66905],"type":"Point"}
}
