{
  "type": "Feature",
  "properties": {
    "date:inception_lower": "2000-12-01",
    "date:inception_upper": "2000-12-01",
    "iso:country": "GB",
    "wof:name": "OX25 4SD",
    "wof:placetype": "postalcode"
  },
  "geometry": {"coordinates":[-1.317306,51.930308],"type":"Point"}
}
