{
  "type": "Feature",
  "properties": {
    "iso:country": "GB",
    "wof:name": "OX25 4SD",
    "wof:placetype": "postalcode"
  },
  "geometry": {"coordinates":[-1.317306,51.930308],"type":"Point"}
}
