{
  "type": "Feature",
  "properties": {
    "iso:country":"GB",
    "wof:name":"KT22 8SN",
    "wof:placetype":"postalcode"
},
  "geometry": {"coordinates":[-0.32446371421664,51.29379899691173],"type":"Point"}
}