{
  "type": "Feature",
  "properties": {
    "date:inception_lower": "1991-01-01",
    "date:inception_upper": "1991-01-01",
    "iso:country": "GB",
    "wof:name": "KT22 8SN",
    "wof:placetype": "postalcode"
  },
  "geometry": {"coordinates":[-0.324464,51.293799],"type":"Point"}
}
