{
  "type": "Feature",
  "properties": {
    "iso:country":"GB",
    "wof:name":"LA1 3QX",
    "wof:placetype":"postalcode"
},
  "geometry": {"coordinates":[-2.78954731131292,54.04740928619864],"type":"Point"}
}