{
  "type": "Feature",
  "properties": {
    "date:inception_lower": "1990-02-01",
    "date:inception_upper": "1990-02-01",
    "iso:country": "GB",
    "wof:name": "AL7 2NN",
    "wof:placetype": "postalcode"
  },
  "geometry": {"coordinates":[-0.166319,51.8011],"type":"Point"}
}
