{
  "type": "Feature",
  "properties": {
    "iso:country": "GB",
    "wof:name": "SR8 2HH",
    "wof:placetype": "postalcode"
  },
  "geometry": {"coordinates":[-1.353724,54.76552],"type":"Point"}
}
