{
  "type": "Feature",
  "properties": {
    "iso:country":"GB",
    "wof:name":"BL6 4AZ",
    "wof:placetype":"postalcode"
},
  "geometry": {"coordinates":[-2.52118672889467,53.58357933980398],"type":"Point"}
}