{
  "type": "Feature",
  "properties": {
    "iso:country":"GB",
    "wof:name":"LE4 4AE",
    "wof:placetype":"postalcode"
},
  "geometry": {"coordinates":[-1.1250873098439,52.67345022583695],"type":"Point"}
}