{
  "type": "Feature",
  "properties": {
    "iso:country": "GB",
    "wof:name": "CR0 6TU",
    "wof:placetype": "postalcode"
  },
  "geometry": {"coordinates":[-0.084357,51.378273],"type":"Point"}
}
