{
  "type": "Feature",
  "properties": {
    "iso:country":"GB",
    "wof:name":"CR0 6TU",
    "wof:placetype":"postalcode"
},
  "geometry": {"coordinates":[-0.08435676683331,51.37827329966558],"type":"Point"}
}