{
  "type": "Feature",
  "properties": {
    "date:inception_lower":"1980-01-01",
    "date:inception_upper":"1980-01-31",
    "iso:country":"GB",
    "wof:name":"HX2 6JG",
    "wof:placetype":"postalcode"
},
  "geometry": {"coordinates":[-1.966073,53.727272],"type":"Point"}
}