{
  "type": "Feature",
  "properties": {
    "iso:country":"GB",
    "wof:name":"DH4 5PW",
    "wof:placetype":"postalcode"
},
  "geometry": {"coordinates":[-1.48836622051641,54.85280166482761],"type":"Point"}
}