{
  "type": "Feature",
  "properties": {
    "date:inception_lower": "1980-01-01",
    "date:inception_upper": "1980-01-01",
    "iso:country": "GB",
    "wof:name": "DH4 5PW",
    "wof:placetype": "postalcode"
  },
  "geometry": {"coordinates":[-1.488366,54.852802],"type":"Point"}
}
