{
  "type": "Feature",
  "properties": {
    "iso:country":"GB",
    "wof:name":"SL0 9DD",
    "wof:placetype":"postalcode"
},
  "geometry": {"coordinates":[-0.50663569448486,51.50244826657433],"type":"Point"}
}