{
  "type": "Feature",
  "properties": {
    "iso:country": "GB",
    "wof:name": "SL0 9DD",
    "wof:placetype": "postalcode"
  },
  "geometry": {"coordinates":[-0.506689,51.501974],"type":"Point"}
}
