{
  "type": "Feature",
  "properties": {
    "date:inception_lower": "1980-01-01",
    "date:inception_upper": "1980-01-01",
    "iso:country": "GB",
    "wof:name": "SL0 9DD",
    "wof:placetype": "postalcode"
  },
  "geometry": {"coordinates":[-0.506689,51.501974],"type":"Point"}
}
