{
  "type": "Feature",
  "properties": {
    "iso:country": "GB",
    "wof:name": "SW16 4LU",
    "wof:placetype": "postalcode"
  },
  "geometry": {"coordinates":[-0.124396,51.40098],"type":"Point"}
}
