{
  "type": "Feature",
  "properties": {
    "iso:country":"GB",
    "wof:name":"SW16 4LU",
    "wof:placetype":"postalcode"
},
  "geometry": {"coordinates":[-0.12439628821192,51.4009802193154],"type":"Point"}
}