{
  "type": "Feature",
  "properties": {
    "iso:country":"GB",
    "wof:name":"ME14 5JH",
    "wof:placetype":"postalcode"
},
  "geometry": {"coordinates":[0.55423840919192,51.27301286285471],"type":"Point"}
}