{
  "type": "Feature",
  "properties": {
    "iso:country":"GB",
    "wof:name":"BA11 4AH",
    "wof:placetype":"postalcode"
},
  "geometry": {"coordinates":[-2.32466252648406,51.22540364735168],"type":"Point"}
}