{
  "type": "Feature",
  "properties": {
    "date:inception_lower": "2015-10-01",
    "date:inception_upper": "2015-10-01",
    "iso:country": "GB",
    "wof:name": "IV30 8UJ",
    "wof:placetype": "postalcode"
  },
  "geometry": {"coordinates":[-3.306489,57.629419],"type":"Point"}
}
