{
  "type": "Feature",
  "properties": {
    "iso:country":"GB",
    "wof:name":"WF2 8UJ",
    "wof:placetype":"postalcode"
},
  "geometry": {"coordinates":[-1.53817585252897,53.66805472564475],"type":"Point"}
}