{
  "type": "Feature",
  "properties": {
    "iso:country": "GB",
    "wof:name": "DD2 3PU",
    "wof:placetype": "postalcode"
  },
  "geometry": {"coordinates":[-3.000377,56.478615],"type":"Point"}
}
