{
  "type": "Feature",
  "properties": {
    "date:inception_lower": "2013-03-01",
    "date:inception_upper": "2013-03-01",
    "iso:country": "GB",
    "wof:name": "DD2 3PU",
    "wof:placetype": "postalcode"
  },
  "geometry": {"coordinates":[-3.000377,56.478615],"type":"Point"}
}
