{
  "type": "Feature",
  "properties": {
    "iso:country":"GB",
    "wof:name":"SO21 2QB",
    "wof:placetype":"postalcode"
},
  "geometry": {"coordinates":[-1.40118733930753,51.11282238914817],"type":"Point"}
}