{
  "type": "Feature",
  "properties": {
    "iso:country": "GB",
    "wof:name": "HA4 7XS",
    "wof:placetype": "postalcode"
  },
  "geometry": {"coordinates":[-0.424152,51.582955],"type":"Point"}
}
