{
  "type": "Feature",
  "properties": {
    "date:inception_lower": "2021-04-01",
    "date:inception_upper": "2021-04-01",
    "iso:country": "GB",
    "wof:name": "OX29 0AT",
    "wof:placetype": "postalcode"
  },
  "geometry": {"coordinates":[-1.530535,51.788886],"type":"Point"}
}
