{
  "type": "Feature",
  "properties": {
    "iso:country":"GB",
    "wof:name":"DY14 0UB",
    "wof:placetype":"postalcode"
},
  "geometry": {"coordinates":[-2.51320850745559,52.41528802905199],"type":"Point"}
}