{
  "type": "Feature",
  "properties": {
    "iso:country": "GB",
    "wof:name": "DY14 0UB",
    "wof:placetype": "postalcode"
  },
  "geometry": {"coordinates":[-2.513206,52.415302],"type":"Point"}
}
