{
  "type": "Feature",
  "properties": {
    "iso:country": "GB",
    "wof:name": "PH1 1BU",
    "wof:placetype": "postalcode"
  },
  "geometry": {"coordinates":[-3.459183,56.389897],"type":"Point"}
}
