{
  "type": "Feature",
  "properties": {
    "iso:country":"GB",
    "wof:name":"PH1 1BU",
    "wof:placetype":"postalcode"
},
  "geometry": {"coordinates":[-3.45918324082664,56.38989711499695],"type":"Point"}
}