{
  "type": "Feature",
  "properties": {
    "iso:country":"GB",
    "wof:name":"SO50 4HH",
    "wof:placetype":"postalcode"
},
  "geometry": {"coordinates":[-1.35042795230012,50.97525728521764],"type":"Point"}
}