{
  "type": "Feature",
  "properties": {
    "iso:country": "GB",
    "wof:name": "SO50 4HH",
    "wof:placetype": "postalcode"
  },
  "geometry": {"coordinates":[-1.350532,50.97516],"type":"Point"}
}
