{
  "type": "Feature",
  "properties": {
    "iso:country":"GB",
    "wof:name":"M34 5BU",
    "wof:placetype":"postalcode"
},
  "geometry": {"coordinates":[-2.11173692971569,53.4689109625028],"type":"Point"}
}