{
  "type": "Feature",
  "properties": {
    "iso:country":"GB",
    "wof:name":"M29 7TD",
    "wof:placetype":"postalcode"
},
  "geometry": {"coordinates":[-2.46503367780524,53.50994404164219],"type":"Point"}
}