{
  "type": "Feature",
  "properties": {
    "iso:country":"GB",
    "wof:name":"TS24 0DW",
    "wof:placetype":"postalcode"
},
  "geometry": {"coordinates":[-1.19552752892438,54.703203207745],"type":"Point"}
}