{
  "type": "Feature",
  "properties": {
    "iso:country":"GB",
    "wof:name":"TW18 1LZ",
    "wof:placetype":"postalcode"
},
  "geometry": {"coordinates":[-0.48257894654768,51.42244143670077],"type":"Point"}
}