{
  "type": "Feature",
  "properties": {
    "iso:country": "GB",
    "wof:name": "EX14 3NA",
    "wof:placetype": "postalcode"
  },
  "geometry": {"coordinates":[-3.298617,50.807375],"type":"Point"}
}
