{
  "type": "Feature",
  "properties": {
    "date:inception_lower": "1998-12-01",
    "date:inception_upper": "1998-12-01",
    "iso:country": "GB",
    "wof:name": "IV36 1FD",
    "wof:placetype": "postalcode"
  },
  "geometry": {"coordinates":[-3.587223,57.613782],"type":"Point"}
}
