{
  "type": "Feature",
  "properties": {
    "iso:country":"GB",
    "wof:name":"EH22 3AU",
    "wof:placetype":"postalcode"
},
  "geometry": {"coordinates":[-3.07712794783385,55.88474643156323],"type":"Point"}
}