{
  "type": "Feature",
  "properties": {
    "date:inception_lower": "1980-01-01",
    "date:inception_upper": "1980-01-01",
    "iso:country": "GB",
    "wof:name": "EH22 3AU",
    "wof:placetype": "postalcode"
  },
  "geometry": {"coordinates":[-3.077128,55.884746],"type":"Point"}
}
