{
  "type": "Feature",
  "properties": {
    "iso:country": "GB",
    "wof:name": "B79 8QJ",
    "wof:placetype": "postalcode"
  },
  "geometry": {"coordinates":[-1.701545,52.648406],"type":"Point"}
}
