{
  "type": "Feature",
  "properties": {
    "iso:country":"GB",
    "wof:name":"B79 8QJ",
    "wof:placetype":"postalcode"
},
  "geometry": {"coordinates":[-1.7015802220964,52.64848808254813],"type":"Point"}
}