{
  "type": "Feature",
  "properties": {
    "iso:country": "GB",
    "wof:name": "BN3 4PN",
    "wof:placetype": "postalcode"
  },
  "geometry": {"coordinates":[-0.203045,50.830636],"type":"Point"}
}
