{
  "type": "Feature",
  "properties": {
    "iso:country": "GB",
    "wof:name": "SG8 5JQ",
    "wof:placetype": "postalcode"
  },
  "geometry": {"coordinates":[-0.038177,52.082139],"type":"Point"}
}
