{
  "type": "Feature",
  "properties": {
    "iso:country": "GB",
    "wof:name": "CO6 1DL",
    "wof:placetype": "postalcode"
  },
  "geometry": {"coordinates":[0.792167,51.861097],"type":"Point"}
}
