{
  "type": "Feature",
  "properties": {
    "date:inception_lower": "1980-01-01",
    "date:inception_upper": "1980-01-01",
    "iso:country": "GB",
    "wof:name": "CO6 1DL",
    "wof:placetype": "postalcode"
  },
  "geometry": {"coordinates":[0.792052,51.861118],"type":"Point"}
}
