{
  "type": "Feature",
  "properties": {
    "iso:country":"GB",
    "wof:name":"CO6 1DL",
    "wof:placetype":"postalcode"
},
  "geometry": {"coordinates":[0.79202346628604,51.86110745016099],"type":"Point"}
}