{
  "type": "Feature",
  "properties": {
    "iso:country":"GB",
    "wof:name":"HX5 0QA",
    "wof:placetype":"postalcode"
},
  "geometry": {"coordinates":[-1.84322970732559,53.68281846667789],"type":"Point"}
}