{
  "type": "Feature",
  "properties": {
    "iso:country":"GB",
    "wof:name":"BR8 8TD",
    "wof:placetype":"postalcode"
},
  "geometry": {"coordinates":[0.15862015613527,51.38246559545424],"type":"Point"}
}