{
  "type": "Feature",
  "properties": {
    "date:inception_lower":"1980-01-01",
    "date:inception_upper":"1980-01-31",
    "iso:country":"GB",
    "wof:name":"BR8 8TD",
    "wof:placetype":"postalcode"
},
  "geometry": {"coordinates":[0.15862,51.382466],"type":"Point"}
}