{
  "type": "Feature",
  "properties": {
    "iso:country": "GB",
    "wof:name": "BR8 8TD",
    "wof:placetype": "postalcode"
  },
  "geometry": {"coordinates":[0.15862,51.382466],"type":"Point"}
}
