{
  "type": "Feature",
  "properties": {
    "date:inception_lower": "1994-12-01",
    "date:inception_upper": "1994-12-01",
    "iso:country": "GB",
    "wof:name": "SO18 4RG",
    "wof:placetype": "postalcode"
  },
  "geometry": {"coordinates":[-1.364279,50.917359],"type":"Point"}
}
