{
  "type": "Feature",
  "properties": {
    "iso:country":"GB",
    "wof:name":"SO18 4RG",
    "wof:placetype":"postalcode"
},
  "geometry": {"coordinates":[-1.36427898875032,50.91735923606154],"type":"Point"}
}