{
  "type": "Feature",
  "properties": {
    "date:inception_lower": "1980-01-01",
    "date:inception_upper": "1980-01-01",
    "iso:country": "GB",
    "wof:name": "NE6 5NA",
    "wof:placetype": "postalcode"
  },
  "geometry": {"coordinates":[-1.573851,54.986579],"type":"Point"}
}
