{
  "type": "Feature",
  "properties": {
    "date:inception_lower": "2019-04-01",
    "date:inception_upper": "2019-04-01",
    "iso:country": "GB",
    "wof:name": "SY10 8PU",
    "wof:placetype": "postalcode"
  },
  "geometry": {"coordinates":[-2.991896,52.79464],"type":"Point"}
}
