{
  "type": "Feature",
  "properties": {
    "iso:country": "GB",
    "wof:name": "KT20 6BT",
    "wof:placetype": "postalcode"
  },
  "geometry": {"coordinates":[-0.217662,51.30501],"type":"Point"}
}
