{
  "type": "Feature",
  "properties": {
    "date:inception_lower": "1980-01-01",
    "date:inception_upper": "1980-01-01",
    "iso:country": "GB",
    "wof:name": "KT20 6BT",
    "wof:placetype": "postalcode"
  },
  "geometry": {"coordinates":[-0.217662,51.30501],"type":"Point"}
}
