{
  "type": "Feature",
  "properties": {
    "iso:country": "GB",
    "wof:name": "EX14 1DN",
    "wof:placetype": "postalcode"
  },
  "geometry": {"coordinates":[-3.188667,50.798457],"type":"Point"}
}
