{
  "type": "Feature",
  "properties": {
    "iso:country": "GB",
    "wof:name": "SN14 0NP",
    "wof:placetype": "postalcode"
  },
  "geometry": {"coordinates":[-2.142512,51.453096],"type":"Point"}
}
