{
  "type": "Feature",
  "properties": {
    "iso:country":"GB",
    "wof:name":"GU29 0NU",
    "wof:placetype":"postalcode"
},
  "geometry": {"coordinates":[-0.77524871700363,50.99398879845894],"type":"Point"}
}