{
  "type": "Feature",
  "properties": {
    "iso:country": "GB",
    "wof:name": "GU29 0NU",
    "wof:placetype": "postalcode"
  },
  "geometry": {"coordinates":[-0.775249,50.993989],"type":"Point"}
}
