{
  "type": "Feature",
  "properties": {
    "iso:country":"GB",
    "wof:name":"SW7 4LS",
    "wof:placetype":"postalcode"
},
  "geometry": {"coordinates":[-0.18578211463403,51.49290628053043],"type":"Point"}
}