{
  "type": "Feature",
  "properties": {
    "iso:country":"GB",
    "wof:name":"HR8 2EN",
    "wof:placetype":"postalcode"
},
  "geometry": {"coordinates":[-2.43356940909575,52.02975636800089],"type":"Point"}
}