{
  "type": "Feature",
  "properties": {
    "date:inception_lower": "1980-01-01",
    "date:inception_upper": "1980-01-01",
    "iso:country": "GB",
    "wof:name": "HR8 2EN",
    "wof:placetype": "postalcode"
  },
  "geometry": {"coordinates":[-2.433568,52.029748],"type":"Point"}
}
