{
  "type": "Feature",
  "properties": {
    "date:inception_lower":"2011-07-01",
    "date:inception_upper":"2011-07-31",
    "iso:country":"GB",
    "wof:name":"G75 9LY",
    "wof:placetype":"postalcode"
},
  "geometry": {"coordinates":[-4.184677,55.748955],"type":"Point"}
}