{
  "type": "Feature",
  "properties": {
    "iso:country":"GB",
    "wof:name":"G75 9LY",
    "wof:placetype":"postalcode"
},
  "geometry": {"coordinates":[-4.18467742278477,55.74895459302443],"type":"Point"}
}