{
  "type": "Feature",
  "properties": {
    "date:inception_lower":"1980-01-01",
    "date:inception_upper":"1980-01-31",
    "iso:country":"GB",
    "wof:name":"WD3 3DQ",
    "wof:placetype":"postalcode"
},
  "geometry": {"coordinates":[-0.43307,51.650119],"type":"Point"}
}