{
  "type": "Feature",
  "properties": {
    "iso:country": "GB",
    "wof:name": "WD3 3DQ",
    "wof:placetype": "postalcode"
  },
  "geometry": {"coordinates":[-0.43307,51.650119],"type":"Point"}
}
