{
  "type": "Feature",
  "properties": {
    "date:inception_lower": "1980-01-01",
    "date:inception_upper": "1980-01-01",
    "iso:country": "GB",
    "wof:name": "OX11 9ER",
    "wof:placetype": "postalcode"
  },
  "geometry": {"coordinates":[-1.199934,51.574558],"type":"Point"}
}
