{
  "type": "Feature",
  "properties": {
    "iso:country":"GB",
    "wof:name":"M22 5TS",
    "wof:placetype":"postalcode"
},
  "geometry": {"coordinates":[-2.26289512292436,53.37951628871868],"type":"Point"}
}