{
  "type": "Feature",
  "properties": {
    "iso:country":"GB",
    "wof:name":"SO51 0PH",
    "wof:placetype":"postalcode"
},
  "geometry": {"coordinates":[-1.47980579421297,51.02576714523703],"type":"Point"}
}