{
  "type": "Feature",
  "properties": {
    "date:inception_lower": "1986-01-01",
    "date:inception_upper": "1986-01-01",
    "iso:country": "GB",
    "wof:name": "SO51 0PH",
    "wof:placetype": "postalcode"
  },
  "geometry": {"coordinates":[-1.479806,51.025767],"type":"Point"}
}
