{
  "type": "Feature",
  "properties": {
    "iso:country": "GB",
    "wof:name": "WV14 7BP",
    "wof:placetype": "postalcode"
  },
  "geometry": {"coordinates":[-2.063136,52.571301],"type":"Point"}
}
