{
  "type": "Feature",
  "properties": {
    "iso:country":"GB",
    "wof:name":"WV14 7BP",
    "wof:placetype":"postalcode"
},
  "geometry": {"coordinates":[-2.06313612679009,52.57130052087588],"type":"Point"}
}