{
  "type": "Feature",
  "properties": {
    "iso:country":"GB",
    "wof:name":"NW10 4HE",
    "wof:placetype":"postalcode"
},
  "geometry": {"coordinates":[-0.24421475929276,51.5392791669953],"type":"Point"}
}