{
  "type": "Feature",
  "properties": {
    "date:inception_lower": "1980-01-01",
    "date:inception_upper": "1980-01-01",
    "iso:country": "GB",
    "wof:name": "CT13 0BU",
    "wof:placetype": "postalcode"
  },
  "geometry": {"coordinates":[1.339302,51.266982],"type":"Point"}
}
