{
  "type": "Feature",
  "properties": {
    "iso:country":"GB",
    "wof:name":"WN1 1AN",
    "wof:placetype":"postalcode"
},
  "geometry": {"coordinates":[-2.63278508621882,53.54732074990419],"type":"Point"}
}