{
  "type": "Feature",
  "properties": {
    "iso:country": "GB",
    "wof:name": "WN1 1AN",
    "wof:placetype": "postalcode"
  },
  "geometry": {"coordinates":[-2.632785,53.547321],"type":"Point"}
}
