{
  "type": "Feature",
  "properties": {
    "iso:country":"GB",
    "wof:name":"RH2 9JS",
    "wof:placetype":"postalcode"
},
  "geometry": {"coordinates":[-0.22611149129298,51.24174803032247],"type":"Point"}
}