{
  "type": "Feature",
  "properties": {
    "date:inception_lower": "1980-01-01",
    "date:inception_upper": "1980-01-01",
    "iso:country": "GB",
    "wof:name": "ME6 5AB",
    "wof:placetype": "postalcode"
  },
  "geometry": {"coordinates":[0.44168,51.328055],"type":"Point"}
}
