{
  "type": "Feature",
  "properties": {
    "iso:country":"GB",
    "wof:name":"WS2 9TT",
    "wof:placetype":"postalcode"
},
  "geometry": {"coordinates":[-2.00160944068601,52.57711590772752],"type":"Point"}
}