{
  "type": "Feature",
  "properties": {
    "date:inception_lower": "1996-12-01",
    "date:inception_upper": "1996-12-01",
    "iso:country": "GB",
    "wof:name": "WS2 9TT",
    "wof:placetype": "postalcode"
  },
  "geometry": {"coordinates":[-2.001604,52.577132],"type":"Point"}
}
