{
  "type": "Feature",
  "properties": {
    "iso:country":"GB",
    "wof:name":"SW19 8AG",
    "wof:placetype":"postalcode"
},
  "geometry": {"coordinates":[-0.1967409671295,51.4352984182871],"type":"Point"}
}