{
  "type": "Feature",
  "properties": {
    "date:inception_lower":"2014-05-01",
    "date:inception_upper":"2014-05-31",
    "iso:country":"GB",
    "wof:name":"DY13 8DZ",
    "wof:placetype":"postalcode"
},
  "geometry": {"coordinates":[-2.31154,52.355947],"type":"Point"}
}