{
  "type": "Feature",
  "properties": {
    "iso:country":"GB",
    "wof:name":"DY13 8DZ",
    "wof:placetype":"postalcode"
},
  "geometry": {"coordinates":[-2.3115404656463,52.35594668501934],"type":"Point"}
}