{
  "type": "Feature",
  "properties": {
    "iso:country": "GB",
    "wof:name": "TN12 9PB",
    "wof:placetype": "postalcode"
  },
  "geometry": {"coordinates":[0.451365,51.174393],"type":"Point"}
}
