{
  "type": "Feature",
  "properties": {
    "iso:country":"GB",
    "wof:name":"TN12 9PB",
    "wof:placetype":"postalcode"
},
  "geometry": {"coordinates":[0.45133557593686,51.17439470806823],"type":"Point"}
}