{
  "type": "Feature",
  "properties": {
    "iso:country": "GB",
    "wof:name": "DE7 6LA",
    "wof:placetype": "postalcode"
  },
  "geometry": {"coordinates":[-1.361065,52.968098],"type":"Point"}
}
