{
  "type": "Feature",
  "properties": {
    "iso:country":"GB",
    "wof:name":"DE7 6LA",
    "wof:placetype":"postalcode"
},
  "geometry": {"coordinates":[-1.36106522314652,52.96809806284882],"type":"Point"}
}