{
  "type": "Feature",
  "properties": {
    "iso:country":"GB",
    "wof:name":"DN7 5HU",
    "wof:placetype":"postalcode"
},
  "geometry": {"coordinates":[-1.01672845160619,53.60180070360068],"type":"Point"}
}