{
  "type": "Feature",
  "properties": {
    "date:inception_lower": "1985-10-01",
    "date:inception_upper": "1985-10-01",
    "iso:country": "GB",
    "wof:name": "DN7 5HU",
    "wof:placetype": "postalcode"
  },
  "geometry": {"coordinates":[-1.016728,53.601801],"type":"Point"}
}
