{
  "type": "Feature",
  "properties": {
    "date:inception_lower": "2014-08-01",
    "date:inception_upper": "2014-08-01",
    "iso:country": "GB",
    "wof:name": "NG15 8GJ",
    "wof:placetype": "postalcode"
  },
  "geometry": {"coordinates":[-1.190669,53.042913],"type":"Point"}
}
