{
  "type": "Feature",
  "properties": {
    "iso:country":"GB",
    "wof:name":"NG15 8GJ",
    "wof:placetype":"postalcode"
},
  "geometry": {"coordinates":[-1.19066897346313,53.04291304250408],"type":"Point"}
}