{
  "type": "Feature",
  "properties": {
    "iso:country":"GB",
    "wof:name":"CF47 0ER",
    "wof:placetype":"postalcode"
},
  "geometry": {"coordinates":[-3.37432293172535,51.74647961769247],"type":"Point"}
}