{
  "type": "Feature",
  "properties": {
    "iso:country": "GB",
    "wof:name": "LU4 9EP",
    "wof:placetype": "postalcode"
  },
  "geometry": {"coordinates":[-0.477497,51.9066],"type":"Point"}
}
