{
  "type": "Feature",
  "properties": {
    "iso:country":"GB",
    "wof:name":"LU4 9EP",
    "wof:placetype":"postalcode"
},
  "geometry": {"coordinates":[-0.47749683983989,51.90660044251356],"type":"Point"}
}