{
  "type": "Feature",
  "properties": {
    "iso:country":"GB",
    "wof:name":"LD1 6DE",
    "wof:placetype":"postalcode"
},
  "geometry": {"coordinates":[-3.37803510600986,52.24883538965804],"type":"Point"}
}