{
  "type": "Feature",
  "properties": {
    "iso:country": "GB",
    "wof:name": "LD1 6DE",
    "wof:placetype": "postalcode"
  },
  "geometry": {"coordinates":[-3.378035,52.248835],"type":"Point"}
}
