{
  "type": "Feature",
  "properties": {
    "iso:country":"GB",
    "wof:name":"HU10 6DQ",
    "wof:placetype":"postalcode"
},
  "geometry": {"coordinates":[-0.44890181527995,53.76268914727557],"type":"Point"}
}