{
  "type": "Feature",
  "properties": {
    "iso:country":"GB",
    "wof:name":"BH7 6JD",
    "wof:placetype":"postalcode"
},
  "geometry": {"coordinates":[-1.83619248152467,50.73221726602767],"type":"Point"}
}