{
  "type": "Feature",
  "properties": {
    "iso:country":"GB",
    "wof:name":"M19 3DZ",
    "wof:placetype":"postalcode"
},
  "geometry": {"coordinates":[-2.19316522660504,53.44719858883419],"type":"Point"}
}