{
  "type": "Feature",
  "properties": {
    "iso:country":"GB",
    "wof:name":"PO16 8QQ",
    "wof:placetype":"postalcode"
},
  "geometry": {"coordinates":[-1.14578773350063,50.85036453561053],"type":"Point"}
}