{
  "type": "Feature",
  "properties": {
    "date:inception_lower":"1980-01-01",
    "date:inception_upper":"1980-01-31",
    "iso:country":"GB",
    "wof:name":"SA5 9AH",
    "wof:placetype":"postalcode"
},
  "geometry": {"coordinates":[-3.953661,51.65424],"type":"Point"}
}