{
  "type": "Feature",
  "properties": {
    "iso:country": "GB",
    "wof:name": "SA5 9AH",
    "wof:placetype": "postalcode"
  },
  "geometry": {"coordinates":[-3.953661,51.65424],"type":"Point"}
}
