{
  "type": "Feature",
  "properties": {
    "iso:country":"GB",
    "wof:name":"SA5 9AH",
    "wof:placetype":"postalcode"
},
  "geometry": {"coordinates":[-3.95366115563338,51.6542404716775],"type":"Point"}
}