{
  "type": "Feature",
  "properties": {
    "iso:country":"GB",
    "wof:name":"RH1 1DP",
    "wof:placetype":"postalcode"
},
  "geometry": {"coordinates":[-0.17789832214986,51.24110626753099],"type":"Point"}
}