{
  "type": "Feature",
  "properties": {
    "iso:country": "GB",
    "wof:name": "M34 2JH",
    "wof:placetype": "postalcode"
  },
  "geometry": {"coordinates":[-2.139725,53.450365],"type":"Point"}
}
