{
  "type": "Feature",
  "properties": {
    "iso:country":"GB",
    "wof:name":"CF35 5HP",
    "wof:placetype":"postalcode"
},
  "geometry": {"coordinates":[-3.53481133362981,51.50518846093136],"type":"Point"}
}