{
  "type": "Feature",
  "properties": {
    "iso:country": "GB",
    "wof:name": "CF35 5HP",
    "wof:placetype": "postalcode"
  },
  "geometry": {"coordinates":[-3.534811,51.505189],"type":"Point"}
}
