{
  "type": "Feature",
  "properties": {
    "date:inception_lower":"1980-01-01",
    "date:inception_upper":"1980-01-31",
    "iso:country":"GB",
    "wof:name":"TS9 6PH",
    "wof:placetype":"postalcode"
},
  "geometry": {"coordinates":[-1.145202,54.486585],"type":"Point"}
}