{
  "type": "Feature",
  "properties": {
    "iso:country":"GB",
    "wof:name":"LU3 3DW",
    "wof:placetype":"postalcode"
},
  "geometry": {"coordinates":[-0.46284559514192,51.91590513264958],"type":"Point"}
}