{
  "type": "Feature",
  "properties": {
    "iso:country": "GB",
    "wof:name": "TQ11 0HS",
    "wof:placetype": "postalcode"
  },
  "geometry": {"coordinates":[-3.819586,50.499419],"type":"Point"}
}
