{
  "type": "Feature",
  "properties": {
    "iso:country":"GB",
    "wof:name":"TQ11 0HS",
    "wof:placetype":"postalcode"
},
  "geometry": {"coordinates":[-3.8195864149987,50.49941896788567],"type":"Point"}
}