{
  "type": "Feature",
  "properties": {
    "iso:country": "GB",
    "wof:name": "BL2 5DJ",
    "wof:placetype": "postalcode"
  },
  "geometry": {"coordinates":[-2.392915,53.590056],"type":"Point"}
}
