{
  "type": "Feature",
  "properties": {
    "date:inception_lower": "1980-01-01",
    "date:inception_upper": "1980-01-01",
    "iso:country": "GB",
    "wof:name": "BN11 2SG",
    "wof:placetype": "postalcode"
  },
  "geometry": {"coordinates":[-0.3482,50.818599],"type":"Point"}
}
