{
  "type": "Feature",
  "properties": {
    "date:inception_lower": "1982-03-01",
    "date:inception_upper": "1982-03-01",
    "iso:country": "GB",
    "wof:name": "BB10 4UA",
    "wof:placetype": "postalcode"
  },
  "geometry": {"coordinates":[-2.209704,53.768591],"type":"Point"}
}
