{
  "type": "Feature",
  "properties": {
    "iso:country":"GB",
    "wof:name":"E15 4LT",
    "wof:placetype":"postalcode"
},
  "geometry": {"coordinates":[0.00648637713362,51.54265098844325],"type":"Point"}
}