{
  "type": "Feature",
  "properties": {
    "iso:country": "GB",
    "wof:name": "TA22 9BE",
    "wof:placetype": "postalcode"
  },
  "geometry": {"coordinates":[-3.522361,51.006787],"type":"Point"}
}
