{
  "type": "Feature",
  "properties": {
    "iso:country":"GB",
    "wof:name":"TA22 9BE",
    "wof:placetype":"postalcode"
},
  "geometry": {"coordinates":[-3.52236152334793,51.00678713842193],"type":"Point"}
}