{
  "type": "Feature",
  "properties": {
    "iso:country":"GB",
    "wof:name":"NR16 1AS",
    "wof:placetype":"postalcode"
},
  "geometry": {"coordinates":[1.17891520268423,52.54006532760452],"type":"Point"}
}