{
  "type": "Feature",
  "properties": {
    "iso:country":"GB",
    "wof:name":"UB4 8RN",
    "wof:placetype":"postalcode"
},
  "geometry": {"coordinates":[-0.4211517268642,51.52456462327842],"type":"Point"}
}