{
  "type": "Feature",
  "properties": {
    "iso:country":"GB",
    "wof:name":"M26 2PE",
    "wof:placetype":"postalcode"
},
  "geometry": {"coordinates":[-2.30759179624661,53.56753835575795],"type":"Point"}
}