{
  "type": "Feature",
  "properties": {
    "iso:country":"GB",
    "wof:name":"BL0 0NF",
    "wof:placetype":"postalcode"
},
  "geometry": {"coordinates":[-2.31436556513806,53.65825736483497],"type":"Point"}
}