{
  "type": "Feature",
  "properties": {
    "date:inception_lower": "2004-06-01",
    "date:inception_upper": "2004-06-01",
    "iso:country": "GB",
    "wof:name": "NN18 8PH",
    "wof:placetype": "postalcode"
  },
  "geometry": {"coordinates":[-0.698562,52.471701],"type":"Point"}
}
