{
  "type": "Feature",
  "properties": {
    "iso:country": "GB",
    "wof:name": "NG9 6AQ",
    "wof:placetype": "postalcode"
  },
  "geometry": {"coordinates":[-1.227819,52.90697],"type":"Point"}
}
