{
  "type": "Feature",
  "properties": {
    "iso:country":"GB",
    "wof:name":"NG9 6AQ",
    "wof:placetype":"postalcode"
},
  "geometry": {"coordinates":[-1.22781871047095,52.90697009508734],"type":"Point"}
}