{
  "type": "Feature",
  "properties": {
    "iso:country":"GB",
    "wof:name":"NP22 4AN",
    "wof:placetype":"postalcode"
},
  "geometry": {"coordinates":[-3.25430671628559,51.78653074677118],"type":"Point"}
}