{
  "type": "Feature",
  "properties": {
    "date:inception_lower":"1999-06-01",
    "date:inception_upper":"1999-06-30",
    "iso:country":"GB",
    "wof:name":"NP22 4AN",
    "wof:placetype":"postalcode"
},
  "geometry": {"coordinates":[-3.254307,51.786531],"type":"Point"}
}