{
  "type": "Feature",
  "properties": {
    "iso:country":"GB",
    "wof:name":"SL6 4BL",
    "wof:placetype":"postalcode"
},
  "geometry": {"coordinates":[-0.73832223553427,51.50893663080443],"type":"Point"}
}