{
  "type": "Feature",
  "properties": {
    "date:inception_lower": "2019-06-01",
    "date:inception_upper": "2019-06-01",
    "iso:country": "GB",
    "wof:name": "DG1 3TW",
    "wof:placetype": "postalcode"
  },
  "geometry": {"coordinates":[-3.58566,55.079248],"type":"Point"}
}
