{
  "type": "Feature",
  "properties": {
    "iso:country": "GB",
    "wof:name": "DG1 3TW",
    "wof:placetype": "postalcode"
  },
  "geometry": {"coordinates":[-3.58566,55.079248],"type":"Point"}
}
