{
  "type": "Feature",
  "properties": {
    "iso:country":"GB",
    "wof:name":"SO18 3DB",
    "wof:placetype":"postalcode"
},
  "geometry": {"coordinates":[-1.34504997068832,50.92517537766954],"type":"Point"}
}