{
  "type": "Feature",
  "properties": {
    "date:inception_lower": "1990-07-01",
    "date:inception_upper": "1990-07-01",
    "iso:country": "GB",
    "wof:name": "SG12 7AB",
    "wof:placetype": "postalcode"
  },
  "geometry": {"coordinates":[-0.026422,51.809502],"type":"Point"}
}
