{
  "type": "Feature",
  "properties": {
    "iso:country": "GB",
    "wof:name": "SG12 7AB",
    "wof:placetype": "postalcode"
  },
  "geometry": {"coordinates":[-0.026422,51.809502],"type":"Point"}
}
