{
  "type": "Feature",
  "properties": {
    "iso:country":"GB",
    "wof:name":"DE13 9RW",
    "wof:placetype":"postalcode"
},
  "geometry": {"coordinates":[-1.73257492629745,52.80360577533768],"type":"Point"}
}