{
  "type": "Feature",
  "properties": {
    "date:inception_lower": "1980-01-01",
    "date:inception_upper": "1980-01-01",
    "iso:country": "GB",
    "wof:name": "DE13 9RW",
    "wof:placetype": "postalcode"
  },
  "geometry": {"coordinates":[-1.732575,52.803606],"type":"Point"}
}
