{
  "type": "Feature",
  "properties": {
    "iso:country":"GB",
    "wof:name":"WR1 3EB",
    "wof:placetype":"postalcode"
},
  "geometry": {"coordinates":[-2.22938210799332,52.20134018277891],"type":"Point"}
}