{
  "type": "Feature",
  "properties": {
    "iso:country":"GB",
    "wof:name":"LE12 9AX",
    "wof:placetype":"postalcode"
},
  "geometry": {"coordinates":[-1.29195817081228,52.77850377830182],"type":"Point"}
}