{
  "type": "Feature",
  "properties": {
    "iso:country":"GB",
    "wof:name":"BL2 6AU",
    "wof:placetype":"postalcode"
},
  "geometry": {"coordinates":[-2.40689825985836,53.58000505228528],"type":"Point"}
}