{
  "type": "Feature",
  "properties": {
    "iso:country":"GB",
    "wof:name":"IP28 7PX",
    "wof:placetype":"postalcode"
},
  "geometry": {"coordinates":[0.5171315284507,52.35377969802202],"type":"Point"}
}