{
  "type": "Feature",
  "properties": {
    "iso:country":"GB",
    "wof:name":"UB6 9AT",
    "wof:placetype":"postalcode"
},
  "geometry": {"coordinates":[-0.35442055408788,51.51865683057052],"type":"Point"}
}