{
  "type": "Feature",
  "properties": {
    "date:inception_lower": "1980-01-01",
    "date:inception_upper": "1980-01-01",
    "iso:country": "GB",
    "wof:name": "SG4 7UJ",
    "wof:placetype": "postalcode"
  },
  "geometry": {"coordinates":[-0.288041,51.907162],"type":"Point"}
}
