{
  "type": "Feature",
  "properties": {
    "iso:country":"GB",
    "wof:name":"SG4 7UJ",
    "wof:placetype":"postalcode"
},
  "geometry": {"coordinates":[-0.28804063984601,51.90716214418675],"type":"Point"}
}