{
  "type": "Feature",
  "properties": {
    "iso:country":"GB",
    "wof:name":"WS12 0PJ",
    "wof:placetype":"postalcode"
},
  "geometry": {"coordinates":[-1.95973213633169,52.72073760609207],"type":"Point"}
}