{
  "type": "Feature",
  "properties": {
    "iso:country":"GB",
    "wof:name":"DH4 5LJ",
    "wof:placetype":"postalcode"
},
  "geometry": {"coordinates":[-1.48586102237773,54.85015804673894],"type":"Point"}
}