{
  "type": "Feature",
  "properties": {
    "iso:country": "GB",
    "wof:name": "DH4 5LJ",
    "wof:placetype": "postalcode"
  },
  "geometry": {"coordinates":[-1.485861,54.850158],"type":"Point"}
}
