{
  "type": "Feature",
  "properties": {
    "date:inception_lower": "1990-02-01",
    "date:inception_upper": "1990-02-01",
    "iso:country": "GB",
    "wof:name": "HR4 9XD",
    "wof:placetype": "postalcode"
  },
  "geometry": {"coordinates":[-2.735587,52.063717],"type":"Point"}
}
