{
  "type": "Feature",
  "properties": {
    "date:inception_lower":"1993-08-01",
    "date:inception_upper":"1993-08-31",
    "iso:country":"GB",
    "wof:name":"NN6 6LD",
    "wof:placetype":"postalcode"
},
  "geometry": {"coordinates":[-1.107139,52.383797],"type":"Point"}
}