{
  "type": "Feature",
  "properties": {
    "iso:country": "GB",
    "wof:name": "B7 4PG",
    "wof:placetype": "postalcode"
  },
  "geometry": {"coordinates":[-1.874429,52.491987],"type":"Point"}
}
