{
  "type": "Feature",
  "properties": {
    "date:inception_lower": "1980-01-01",
    "date:inception_upper": "1980-01-01",
    "iso:country": "GB",
    "wof:name": "B7 4PG",
    "wof:placetype": "postalcode"
  },
  "geometry": {"coordinates":[-1.874429,52.491987],"type":"Point"}
}
