{
  "type": "Feature",
  "properties": {
    "iso:country":"GB",
    "wof:name":"SE16 3SN",
    "wof:placetype":"postalcode"
},
  "geometry": {"coordinates":[-0.06944595187696,51.4952033516978],"type":"Point"}
}