{
  "type": "Feature",
  "properties": {
    "date:inception_lower": "2000-12-01",
    "date:inception_upper": "2000-12-01",
    "iso:country": "GB",
    "wof:name": "BN3 5EW",
    "wof:placetype": "postalcode"
  },
  "geometry": {"coordinates":[-0.184605,50.836322],"type":"Point"}
}
