{
  "type": "Feature",
  "properties": {
    "iso:country":"GB",
    "wof:name":"BN3 5EW",
    "wof:placetype":"postalcode"
},
  "geometry": {"coordinates":[-0.18460495674878,50.83632236561444],"type":"Point"}
}