{
  "type": "Feature",
  "properties": {
    "iso:country":"GB",
    "wof:name":"NR31 9FE",
    "wof:placetype":"postalcode"
},
  "geometry": {"coordinates":[1.65771844438417,52.57745696270817],"type":"Point"}
}