{
  "type": "Feature",
  "properties": {
    "iso:country":"GB",
    "wof:name":"NP15 1DX",
    "wof:placetype":"postalcode"
},
  "geometry": {"coordinates":[-2.8090453380963,51.71817599117803],"type":"Point"}
}