{
  "type": "Feature",
  "properties": {
    "iso:country": "GB",
    "wof:name": "NP15 1DX",
    "wof:placetype": "postalcode"
  },
  "geometry": {"coordinates":[-2.809123,51.717297],"type":"Point"}
}
