{
  "type": "Feature",
  "properties": {
    "date:inception_lower": "2002-07-01",
    "date:inception_upper": "2002-07-01",
    "iso:country": "GB",
    "wof:name": "WF6 1WT",
    "wof:placetype": "postalcode"
  },
  "geometry": {"coordinates":[-1.403529,53.696178],"type":"Point"}
}
