{
  "type": "Feature",
  "properties": {
    "iso:country":"GB",
    "wof:name":"M16 9JQ",
    "wof:placetype":"postalcode"
},
  "geometry": {"coordinates":[-2.26576856362153,53.46183608235486],"type":"Point"}
}