{
  "type": "Feature",
  "properties": {
    "iso:country":"GB",
    "wof:name":"DT9 6DN",
    "wof:placetype":"postalcode"
},
  "geometry": {"coordinates":[-2.52600939538794,50.94380953634993],"type":"Point"}
}