{
  "type": "Feature",
  "properties": {
    "iso:country": "GB",
    "wof:name": "CM17 9DB",
    "wof:placetype": "postalcode"
  },
  "geometry": {"coordinates":[0.137664,51.756446],"type":"Point"}
}
