{
  "type": "Feature",
  "properties": {
    "iso:country":"GB",
    "wof:name":"CM17 9DB",
    "wof:placetype":"postalcode"
},
  "geometry": {"coordinates":[0.1376643690601,51.75644567390169],"type":"Point"}
}