{
  "type": "Feature",
  "properties": {
    "iso:country":"GB",
    "wof:name":"SA33 5QJ",
    "wof:placetype":"postalcode"
},
  "geometry": {"coordinates":[-4.48137689062374,51.86273813928721],"type":"Point"}
}