{
  "type": "Feature",
  "properties": {
    "date:inception_lower": "1980-01-01",
    "date:inception_upper": "1980-01-01",
    "iso:country": "GB",
    "wof:name": "G20 9QU",
    "wof:placetype": "postalcode"
  },
  "geometry": {"coordinates":[-4.276699,55.88801],"type":"Point"}
}
