{
  "type": "Feature",
  "properties": {
    "iso:country":"GB",
    "wof:name":"G20 9QU",
    "wof:placetype":"postalcode"
},
  "geometry": {"coordinates":[-4.27697376267388,55.88778070196053],"type":"Point"}
}