{
  "type": "Feature",
  "properties": {
    "iso:country":"GB",
    "wof:name":"CF31 1NB",
    "wof:placetype":"postalcode"
},
  "geometry": {"coordinates":[-3.57925425523859,51.5145167216043],"type":"Point"}
}