{
  "type": "Feature",
  "properties": {
    "iso:country": "GB",
    "wof:name": "TW11 8NA",
    "wof:placetype": "postalcode"
  },
  "geometry": {"coordinates":[-0.338037,51.432162],"type":"Point"}
}
