{
  "type": "Feature",
  "properties": {
    "date:inception_lower":"1992-08-01",
    "date:inception_upper":"1992-08-31",
    "iso:country":"GB",
    "wof:name":"MK43 0EJ",
    "wof:placetype":"postalcode"
},
  "geometry": {"coordinates":[-0.603101,52.072133],"type":"Point"}
}