{
  "type": "Feature",
  "properties": {
    "iso:country":"GB",
    "wof:name":"MK43 0EJ",
    "wof:placetype":"postalcode"
},
  "geometry": {"coordinates":[-0.60310153244532,52.07213346277819],"type":"Point"}
}