{
  "type": "Feature",
  "properties": {
    "iso:country": "GB",
    "wof:name": "CO7 9SH",
    "wof:placetype": "postalcode"
  },
  "geometry": {"coordinates":[0.953537,51.868709],"type":"Point"}
}
