{
  "type": "Feature",
  "properties": {
    "date:inception_lower": "1984-02-01",
    "date:inception_upper": "1984-02-01",
    "iso:country": "GB",
    "wof:name": "CO7 9SH",
    "wof:placetype": "postalcode"
  },
  "geometry": {"coordinates":[0.953537,51.868709],"type":"Point"}
}
