{
  "type": "Feature",
  "properties": {
    "iso:country":"GB",
    "wof:name":"BD3 9HA",
    "wof:placetype":"postalcode"
},
  "geometry": {"coordinates":[-1.73954657298189,53.79604960157317],"type":"Point"}
}