{
  "type": "Feature",
  "properties": {
    "iso:country": "GB",
    "wof:name": "SR3 2TN",
    "wof:placetype": "postalcode"
  },
  "geometry": {"coordinates":[-1.418704,54.867487],"type":"Point"}
}
