{
  "type": "Feature",
  "properties": {
    "date:inception_lower": "2023-06-01",
    "date:inception_upper": "2023-06-01",
    "iso:country": "GB",
    "wof:name": "RH13 9JX",
    "wof:placetype": "postalcode"
  },
  "geometry": {"coordinates":[-0.357585,51.023546],"type":"Point"}
}
