{
  "type": "Feature",
  "properties": {
    "iso:country": "GB",
    "wof:name": "W2 4QS",
    "wof:placetype": "postalcode"
  },
  "geometry": {"coordinates":[-0.187579,51.511162],"type":"Point"}
}
