{
  "type": "Feature",
  "properties": {
    "date:inception_lower": "1980-01-01",
    "date:inception_upper": "1980-01-01",
    "iso:country": "GB",
    "wof:name": "W2 4QS",
    "wof:placetype": "postalcode"
  },
  "geometry": {"coordinates":[-0.187579,51.511162],"type":"Point"}
}
