{
  "type": "Feature",
  "properties": {
    "iso:country":"GB",
    "wof:name":"W2 4QS",
    "wof:placetype":"postalcode"
},
  "geometry": {"coordinates":[-0.18757895368894,51.5111617987917],"type":"Point"}
}