{
  "type": "Feature",
  "properties": {
    "iso:country": "GB",
    "wof:name": "NE9 5AQ",
    "wof:placetype": "postalcode"
  },
  "geometry": {"coordinates":[-1.600403,54.937315],"type":"Point"}
}
