{
  "type": "Feature",
  "properties": {
    "iso:country":"GB",
    "wof:name":"NE9 5AQ",
    "wof:placetype":"postalcode"
},
  "geometry": {"coordinates":[-1.60108762711994,54.93783977070928],"type":"Point"}
}