{
  "type": "Feature",
  "properties": {
    "iso:country":"GB",
    "wof:name":"NG9 7GL",
    "wof:placetype":"postalcode"
},
  "geometry": {"coordinates":[-1.27533746011646,52.92312680360868],"type":"Point"}
}