{
  "type": "Feature",
  "properties": {
    "iso:country": "GB",
    "wof:name": "NG9 7GL",
    "wof:placetype": "postalcode"
  },
  "geometry": {"coordinates":[-1.275337,52.923127],"type":"Point"}
}
