{
  "type": "Feature",
  "properties": {
    "date:inception_lower": "1980-01-01",
    "date:inception_upper": "1980-01-01",
    "iso:country": "GB",
    "wof:name": "NG9 7GL",
    "wof:placetype": "postalcode"
  },
  "geometry": {"coordinates":[-1.275337,52.923127],"type":"Point"}
}
