{
  "type": "Feature",
  "properties": {
    "date:inception_lower": "1980-01-01",
    "date:inception_upper": "1980-01-01",
    "iso:country": "GB",
    "wof:name": "LL54 7PN",
    "wof:placetype": "postalcode"
  },
  "geometry": {"coordinates":[-4.235475,53.108437],"type":"Point"}
}
