{
  "type": "Feature",
  "properties": {
    "iso:country":"GB",
    "wof:name":"LL54 7PN",
    "wof:placetype":"postalcode"
},
  "geometry": {"coordinates":[-4.23547537154948,53.10843667410007],"type":"Point"}
}