{
  "type": "Feature",
  "properties": {
    "date:inception_lower": "1980-01-01",
    "date:inception_upper": "1980-01-01",
    "iso:country": "GB",
    "wof:name": "SE19 3HS",
    "wof:placetype": "postalcode"
  },
  "geometry": {"coordinates":[-0.104347,51.417177],"type":"Point"}
}
