{
  "type": "Feature",
  "properties": {
    "iso:country":"GB",
    "wof:name":"SE19 3HS",
    "wof:placetype":"postalcode"
},
  "geometry": {"coordinates":[-0.10434666080139,51.41717716159562],"type":"Point"}
}