{
  "type": "Feature",
  "properties": {
    "iso:country":"GB",
    "wof:name":"BS11 9EL",
    "wof:placetype":"postalcode"
},
  "geometry": {"coordinates":[-2.69764362143755,51.49988577323369],"type":"Point"}
}