{
  "type": "Feature",
  "properties": {
    "date:inception_lower": "2002-10-01",
    "date:inception_upper": "2002-10-01",
    "iso:country": "GB",
    "wof:name": "CF14 0UP",
    "wof:placetype": "postalcode"
  },
  "geometry": {"coordinates":[-3.184817,51.54213],"type":"Point"}
}
