{
  "type": "Feature",
  "properties": {
    "iso:country":"GB",
    "wof:name":"UB6 8AD",
    "wof:placetype":"postalcode"
},
  "geometry": {"coordinates":[-0.32400915166431,51.53512277541181],"type":"Point"}
}