{
  "type": "Feature",
  "properties": {
    "iso:country":"GB",
    "wof:name":"KA12 0UB",
    "wof:placetype":"postalcode"
},
  "geometry": {"coordinates":[-4.66435893735126,55.62322442948722],"type":"Point"}
}