{
  "type": "Feature",
  "properties": {
    "date:inception_lower": "1993-08-01",
    "date:inception_upper": "1993-08-01",
    "iso:country": "GB",
    "wof:name": "LE16 7PY",
    "wof:placetype": "postalcode"
  },
  "geometry": {"coordinates":[-0.906027,52.48306],"type":"Point"}
}
