{
  "type": "Feature",
  "properties": {
    "iso:country":"GB",
    "wof:name":"LE16 7PY",
    "wof:placetype":"postalcode"
},
  "geometry": {"coordinates":[-0.90612660437977,52.48310689400797],"type":"Point"}
}