{
  "type": "Feature",
  "properties": {
    "date:inception_lower":"1993-08-01",
    "date:inception_upper":"1993-08-31",
    "iso:country":"GB",
    "wof:name":"LE16 7PY",
    "wof:placetype":"postalcode"
},
  "geometry": {"coordinates":[-0.906127,52.483107],"type":"Point"}
}