{
  "type": "Feature",
  "properties": {
    "iso:country":"GB",
    "wof:name":"PL14 4QD",
    "wof:placetype":"postalcode"
},
  "geometry": {"coordinates":[-4.5351826537515,50.4019253431609],"type":"Point"}
}