{
  "type": "Feature",
  "properties": {
    "date:inception_lower":"1980-01-01",
    "date:inception_upper":"1980-01-31",
    "iso:country":"GB",
    "wof:name":"PL14 4QD",
    "wof:placetype":"postalcode"
},
  "geometry": {"coordinates":[-4.535183,50.401925],"type":"Point"}
}