{
  "type": "Feature",
  "properties": {
    "iso:country":"GB",
    "wof:name":"CF31 4EJ",
    "wof:placetype":"postalcode"
},
  "geometry": {"coordinates":[-3.6035722718172,51.50973554076697],"type":"Point"}
}