{
  "type": "Feature",
  "properties": {
    "date:inception_lower":"1980-01-01",
    "date:inception_upper":"1980-01-31",
    "iso:country":"GB",
    "wof:name":"S9 4AA",
    "wof:placetype":"postalcode"
},
  "geometry": {"coordinates":[-1.399545,53.381525],"type":"Point"}
}