{
  "type": "Feature",
  "properties": {
    "date:inception_lower": "1980-01-01",
    "date:inception_upper": "1980-01-01",
    "iso:country": "GB",
    "wof:name": "CH5 1AH",
    "wof:placetype": "postalcode"
  },
  "geometry": {"coordinates":[-3.036865,53.209964],"type":"Point"}
}
