{
  "type": "Feature",
  "properties": {
    "iso:country":"GB",
    "wof:name":"CH5 1AH",
    "wof:placetype":"postalcode"
},
  "geometry": {"coordinates":[-3.03686477996401,53.20996399259774],"type":"Point"}
}