{
  "type": "Feature",
  "properties": {
    "date:inception_lower": "1995-01-01",
    "date:inception_upper": "1995-01-01",
    "iso:country": "GB",
    "wof:name": "RH7 6EQ",
    "wof:placetype": "postalcode"
  },
  "geometry": {"coordinates":[-0.017121,51.176809],"type":"Point"}
}
