{
  "type": "Feature",
  "properties": {
    "iso:country":"GB",
    "wof:name":"RH7 6EQ",
    "wof:placetype":"postalcode"
},
  "geometry": {"coordinates":[-0.01712119722187,51.17680913345021],"type":"Point"}
}