{
  "type": "Feature",
  "properties": {
    "iso:country":"GB",
    "wof:name":"MK6 2JJ",
    "wof:placetype":"postalcode"
},
  "geometry": {"coordinates":[-0.74699889005596,52.03334471618577],"type":"Point"}
}