{
  "type": "Feature",
  "properties": {
    "date:inception_lower": "2018-08-01",
    "date:inception_upper": "2018-08-01",
    "iso:country": "GB",
    "wof:name": "B75 7SJ",
    "wof:placetype": "postalcode"
  },
  "geometry": {"coordinates":[-1.80106,52.567202],"type":"Point"}
}
