{
  "type": "Feature",
  "properties": {
    "iso:country":"GB",
    "wof:name":"N8 7PR",
    "wof:placetype":"postalcode"
},
  "geometry": {"coordinates":[-0.11960537724485,51.58765186494769],"type":"Point"}
}