{
  "type": "Feature",
  "properties": {
    "iso:country":"GB",
    "wof:name":"LA18 5JR",
    "wof:placetype":"postalcode"
},
  "geometry": {"coordinates":[-3.26927960510037,54.24497725727337],"type":"Point"}
}