{
  "type": "Feature",
  "properties": {
    "iso:country": "GB",
    "wof:name": "LA18 5JR",
    "wof:placetype": "postalcode"
  },
  "geometry": {"coordinates":[-3.26928,54.244986],"type":"Point"}
}
