{
  "type": "Feature",
  "properties": {
    "iso:country": "GB",
    "wof:name": "NR12 8LJ",
    "wof:placetype": "postalcode"
  },
  "geometry": {"coordinates":[1.465199,52.705537],"type":"Point"}
}
