{
  "type": "Feature",
  "properties": {
    "iso:country":"GB",
    "wof:name":"NR12 8LJ",
    "wof:placetype":"postalcode"
},
  "geometry": {"coordinates":[1.46519867802604,52.70553655793577],"type":"Point"}
}