{
  "type": "Feature",
  "properties": {
    "date:inception_lower": "1980-01-01",
    "date:inception_upper": "1980-01-01",
    "iso:country": "GB",
    "wof:name": "WF1 4QX",
    "wof:placetype": "postalcode"
  },
  "geometry": {"coordinates":[-1.480361,53.687628],"type":"Point"}
}
