{
  "type": "Feature",
  "properties": {
    "iso:country":"GB",
    "wof:name":"DL12 9SH",
    "wof:placetype":"postalcode"
},
  "geometry": {"coordinates":[-1.91019899640839,54.51185004646111],"type":"Point"}
}