{
  "type": "Feature",
  "properties": {
    "date:inception_lower": "2006-04-01",
    "date:inception_upper": "2006-04-01",
    "iso:country": "GB",
    "wof:name": "KY1 2SH",
    "wof:placetype": "postalcode"
  },
  "geometry": {"coordinates":[-3.152143,56.115485],"type":"Point"}
}
