{
  "type": "Feature",
  "properties": {
    "iso:country":"GB",
    "wof:name":"KY1 2SH",
    "wof:placetype":"postalcode"
},
  "geometry": {"coordinates":[-3.15214305643431,56.11548499110405],"type":"Point"}
}