{
  "type": "Feature",
  "properties": {
    "iso:country": "GB",
    "wof:name": "KY1 2SH",
    "wof:placetype": "postalcode"
  },
  "geometry": {"coordinates":[-3.152143,56.115485],"type":"Point"}
}
