{
  "type": "Feature",
  "properties": {
    "iso:country": "GB",
    "wof:name": "M28 7XP",
    "wof:placetype": "postalcode"
  },
  "geometry": {"coordinates":[-2.406167,53.510042],"type":"Point"}
}
