{
  "type": "Feature",
  "properties": {
    "iso:country":"GB",
    "wof:name":"M28 7XP",
    "wof:placetype":"postalcode"
},
  "geometry": {"coordinates":[-2.4061670810169,53.51004180513863],"type":"Point"}
}