{
  "type": "Feature",
  "properties": {
    "iso:country":"GB",
    "wof:name":"SG5 3LB",
    "wof:placetype":"postalcode"
},
  "geometry": {"coordinates":[-0.35955277603243,51.97171578197437],"type":"Point"}
}