{
  "type": "Feature",
  "properties": {
    "iso:country": "GB",
    "wof:name": "SG5 3LB",
    "wof:placetype": "postalcode"
  },
  "geometry": {"coordinates":[-0.359553,51.971716],"type":"Point"}
}
