{
  "type": "Feature",
  "properties": {
    "iso:country": "GB",
    "wof:name": "CT4 5RA",
    "wof:placetype": "postalcode"
  },
  "geometry": {"coordinates":[1.046173,51.221181],"type":"Point"}
}
