{
  "type": "Feature",
  "properties": {
    "iso:country": "GB",
    "wof:name": "CF23 7AS",
    "wof:placetype": "postalcode"
  },
  "geometry": {"coordinates":[-3.151663,51.523758],"type":"Point"}
}
