{
  "type": "Feature",
  "properties": {
    "date:inception_lower":"1999-06-01",
    "date:inception_upper":"1999-06-30",
    "iso:country":"GB",
    "wof:name":"CF23 7AS",
    "wof:placetype":"postalcode"
},
  "geometry": {"coordinates":[-3.151663,51.523758],"type":"Point"}
}