{
  "type": "Feature",
  "properties": {
    "iso:country":"GB",
    "wof:name":"PO6 3LR",
    "wof:placetype":"postalcode"
},
  "geometry": {"coordinates":[-1.05434470820785,50.85399407280597],"type":"Point"}
}