{
  "type": "Feature",
  "properties": {
    "iso:country":"GB",
    "wof:name":"S10 5BJ",
    "wof:placetype":"postalcode"
},
  "geometry": {"coordinates":[-1.50200668944693,53.3794878822258],"type":"Point"}
}