{
  "type": "Feature",
  "properties": {
    "iso:country": "GB",
    "wof:name": "S10 5BJ",
    "wof:placetype": "postalcode"
  },
  "geometry": {"coordinates":[-1.502007,53.379488],"type":"Point"}
}
