{
  "type": "Feature",
  "properties": {
    "date:inception_lower": "1980-01-01",
    "date:inception_upper": "1980-01-01",
    "iso:country": "GB",
    "wof:name": "S10 5BJ",
    "wof:placetype": "postalcode"
  },
  "geometry": {"coordinates":[-1.502051,53.379497],"type":"Point"}
}
