{
  "type": "Feature",
  "properties": {
    "date:inception_lower":"2010-07-01",
    "date:inception_upper":"2010-07-31",
    "iso:country":"GB",
    "wof:name":"GL3 4FG",
    "wof:placetype":"postalcode"
},
  "geometry": {"coordinates":[-2.18131,51.843424],"type":"Point"}
}