{
  "type": "Feature",
  "properties": {
    "iso:country":"GB",
    "wof:name":"GL3 4FG",
    "wof:placetype":"postalcode"
},
  "geometry": {"coordinates":[-2.18130995010028,51.84342443704059],"type":"Point"}
}