{
  "type": "Feature",
  "properties": {
    "iso:country": "GB",
    "wof:name": "GL3 4FG",
    "wof:placetype": "postalcode"
  },
  "geometry": {"coordinates":[-2.18131,51.843424],"type":"Point"}
}
