{
  "type": "Feature",
  "properties": {
    "iso:country": "GB",
    "wof:name": "PL14 3ET",
    "wof:placetype": "postalcode"
  },
  "geometry": {"coordinates":[-4.4557,50.459371],"type":"Point"}
}
