{
  "type": "Feature",
  "properties": {
    "iso:country": "GB",
    "wof:name": "LN5 0HS",
    "wof:placetype": "postalcode"
  },
  "geometry": {"coordinates":[-0.530518,53.09721],"type":"Point"}
}
