{
  "type": "Feature",
  "properties": {
    "iso:country":"GB",
    "wof:name":"LN5 0HS",
    "wof:placetype":"postalcode"
},
  "geometry": {"coordinates":[-0.53051849159645,53.09720982428183],"type":"Point"}
}