{
  "type": "Feature",
  "properties": {
    "iso:country":"GB",
    "wof:name":"PA5 0LH",
    "wof:placetype":"postalcode"
},
  "geometry": {"coordinates":[-4.5319618296146,55.82500418241386],"type":"Point"}
}