{
  "type": "Feature",
  "properties": {
    "iso:country":"GB",
    "wof:name":"BH17 8BJ",
    "wof:placetype":"postalcode"
},
  "geometry": {"coordinates":[-1.95671544907372,50.74953592277109],"type":"Point"}
}