{
  "type": "Feature",
  "properties": {
    "iso:country":"GB",
    "wof:name":"ME16 9NH",
    "wof:placetype":"postalcode"
},
  "geometry": {"coordinates":[0.4653838033722,51.26387434243156],"type":"Point"}
}