{
  "type": "Feature",
  "properties": {
    "iso:country":"GB",
    "wof:name":"CF72 9RN",
    "wof:placetype":"postalcode"
},
  "geometry": {"coordinates":[-3.44031016802513,51.52641267367535],"type":"Point"}
}