{
  "type": "Feature",
  "properties": {
    "iso:country": "GB",
    "wof:name": "CF72 9RN",
    "wof:placetype": "postalcode"
  },
  "geometry": {"coordinates":[-3.440632,51.526608],"type":"Point"}
}
