{
  "type": "Feature",
  "properties": {
    "date:inception_lower":"1980-01-01",
    "date:inception_upper":"1980-01-31",
    "iso:country":"GB",
    "wof:name":"SY10 7AQ",
    "wof:placetype":"postalcode"
},
  "geometry": {"coordinates":[-3.031807,52.883518],"type":"Point"}
}