{
  "type": "Feature",
  "properties": {
    "iso:country":"GB",
    "wof:name":"SY10 7AQ",
    "wof:placetype":"postalcode"
},
  "geometry": {"coordinates":[-3.03180687258592,52.88351838663802],"type":"Point"}
}