{
  "type": "Feature",
  "properties": {
    "iso:country": "GB",
    "wof:name": "KT13 9LJ",
    "wof:placetype": "postalcode"
  },
  "geometry": {"coordinates":[-0.43531,51.376723],"type":"Point"}
}
