{
  "type": "Feature",
  "properties": {
    "date:inception_lower":"1998-06-01",
    "date:inception_upper":"1998-06-30",
    "iso:country":"GB",
    "wof:name":"YO10 4JP",
    "wof:placetype":"postalcode"
},
  "geometry": {"coordinates":[-1.071471,53.941207],"type":"Point"}
}