{
  "type": "Feature",
  "properties": {
    "iso:country":"GB",
    "wof:name":"YO10 4JP",
    "wof:placetype":"postalcode"
},
  "geometry": {"coordinates":[-1.07147097665113,53.9412065056735],"type":"Point"}
}