{
  "type": "Feature",
  "properties": {
    "iso:country": "GB",
    "wof:name": "YO10 4JP",
    "wof:placetype": "postalcode"
  },
  "geometry": {"coordinates":[-1.071471,53.941207],"type":"Point"}
}
