{
  "type": "Feature",
  "properties": {
    "iso:country": "GB",
    "wof:name": "WR9 7TR",
    "wof:placetype": "postalcode"
  },
  "geometry": {"coordinates":[-2.148975,52.250166],"type":"Point"}
}
