{
  "type": "Feature",
  "properties": {
    "iso:country":"GB",
    "wof:name":"YO25 6AQ",
    "wof:placetype":"postalcode"
},
  "geometry": {"coordinates":[-0.4394163031618,54.00503102094301],"type":"Point"}
}