{
  "type": "Feature",
  "properties": {
    "date:inception_lower":"1998-06-01",
    "date:inception_upper":"1998-06-30",
    "iso:country":"GB",
    "wof:name":"YO25 6AQ",
    "wof:placetype":"postalcode"
},
  "geometry": {"coordinates":[-0.439416,54.005031],"type":"Point"}
}