{
  "type": "Feature",
  "properties": {
    "date:inception_lower": "1980-01-01",
    "date:inception_upper": "1980-01-01",
    "iso:country": "GB",
    "wof:name": "SS0 7RF",
    "wof:placetype": "postalcode"
  },
  "geometry": {"coordinates":[0.696547,51.53619],"type":"Point"}
}
