{
  "type": "Feature",
  "properties": {
    "iso:country":"GB",
    "wof:name":"SS0 7RF",
    "wof:placetype":"postalcode"
},
  "geometry": {"coordinates":[0.69654684398707,51.53618981606917],"type":"Point"}
}