{
  "type": "Feature",
  "properties": {
    "iso:country":"GB",
    "wof:name":"HA4 0NQ",
    "wof:placetype":"postalcode"
},
  "geometry": {"coordinates":[-0.38985799089663,51.56251798315075],"type":"Point"}
}