{
  "type": "Feature",
  "properties": {
    "iso:country": "GB",
    "wof:name": "DN11 0SL",
    "wof:placetype": "postalcode"
  },
  "geometry": {"coordinates":[-1.077868,53.475529],"type":"Point"}
}
