{
  "type": "Feature",
  "properties": {
    "iso:country":"GB",
    "wof:name":"DN11 0SL",
    "wof:placetype":"postalcode"
},
  "geometry": {"coordinates":[-1.07786836353067,53.47552886554135],"type":"Point"}
}