{
  "type": "Feature",
  "properties": {
    "iso:country":"GB",
    "wof:name":"ST5 8AN",
    "wof:placetype":"postalcode"
},
  "geometry": {"coordinates":[-2.22780503825046,53.03189892027621],"type":"Point"}
}