{
  "type": "Feature",
  "properties": {
    "iso:country":"GB",
    "wof:name":"NG13 8DD",
    "wof:placetype":"postalcode"
},
  "geometry": {"coordinates":[-0.94294611130122,52.95147893420301],"type":"Point"}
}