{
  "type": "Feature",
  "properties": {
    "date:inception_lower": "2019-08-01",
    "date:inception_upper": "2019-08-01",
    "iso:country": "GB",
    "wof:name": "CB6 2FU",
    "wof:placetype": "postalcode"
  },
  "geometry": {"coordinates":[0.259977,52.410592],"type":"Point"}
}
