{
  "type": "Feature",
  "properties": {
    "iso:country":"GB",
    "wof:name":"NW6 7HU",
    "wof:placetype":"postalcode"
},
  "geometry": {"coordinates":[-0.19674598278422,51.54068134854388],"type":"Point"}
}