{
  "type": "Feature",
  "properties": {
    "iso:country": "GB",
    "wof:name": "NW6 7HU",
    "wof:placetype": "postalcode"
  },
  "geometry": {"coordinates":[-0.196774,51.540691],"type":"Point"}
}
