{
  "type": "Feature",
  "properties": {
    "date:inception_lower": "2002-05-01",
    "date:inception_upper": "2002-05-01",
    "iso:country": "GB",
    "wof:name": "M50 3AH",
    "wof:placetype": "postalcode"
  },
  "geometry": {"coordinates":[-2.293062,53.470896],"type":"Point"}
}
