{
  "type": "Feature",
  "properties": {
    "iso:country":"GB",
    "wof:name":"M50 3AH",
    "wof:placetype":"postalcode"
},
  "geometry": {"coordinates":[-2.29306246847638,53.47089551764584],"type":"Point"}
}