{
  "type": "Feature",
  "properties": {
    "date:inception_lower": "1980-01-01",
    "date:inception_upper": "1980-01-01",
    "iso:country": "GB",
    "wof:name": "ML1 2LB",
    "wof:placetype": "postalcode"
  },
  "geometry": {"coordinates":[-3.96064,55.773342],"type":"Point"}
}
