{
  "type": "Feature",
  "properties": {
    "iso:country":"GB",
    "wof:name":"WV6 7DY",
    "wof:placetype":"postalcode"
},
  "geometry": {"coordinates":[-2.30925565719653,52.58549450846139],"type":"Point"}
}