{
  "type": "Feature",
  "properties": {
    "iso:country":"GB",
    "wof:name":"AL1 4DQ",
    "wof:placetype":"postalcode"
},
  "geometry": {"coordinates":[-0.3275872387893,51.75895159107129],"type":"Point"}
}