{
  "type": "Feature",
  "properties": {
    "iso:country":"GB",
    "wof:name":"DH3 1DA",
    "wof:placetype":"postalcode"
},
  "geometry": {"coordinates":[-1.57097043193427,54.9005247708828],"type":"Point"}
}