{
  "type": "Feature",
  "properties": {
    "iso:country": "GB",
    "wof:name": "DH3 1DA",
    "wof:placetype": "postalcode"
  },
  "geometry": {"coordinates":[-1.57097,54.900525],"type":"Point"}
}
