{
  "type": "Feature",
  "properties": {
    "iso:country":"GB",
    "wof:name":"DL16 7QE",
    "wof:placetype":"postalcode"
},
  "geometry": {"coordinates":[-1.65028557495557,54.69978651164753],"type":"Point"}
}