{
  "type": "Feature",
  "properties": {
    "iso:country":"GB",
    "wof:name":"KY8 6JE",
    "wof:placetype":"postalcode"
},
  "geometry": {"coordinates":[-2.89810413231469,56.22096448390375],"type":"Point"}
}