{
  "type": "Feature",
  "properties": {
    "iso:country": "GB",
    "wof:name": "ST19 9QP",
    "wof:placetype": "postalcode"
  },
  "geometry": {"coordinates":[-2.24545,52.698897],"type":"Point"}
}
