{
  "type": "Feature",
  "properties": {
    "iso:country":"GB",
    "wof:name":"TW7 4NA",
    "wof:placetype":"postalcode"
},
  "geometry": {"coordinates":[-0.34470043816124,51.48301845813288],"type":"Point"}
}