{
  "type": "Feature",
  "properties": {
    "iso:country":"GB",
    "wof:name":"WN3 6BF",
    "wof:placetype":"postalcode"
},
  "geometry": {"coordinates":[-2.67103335582062,53.52758010736372],"type":"Point"}
}