{
  "type": "Feature",
  "properties": {
    "iso:country":"GB",
    "wof:name":"N1 5LB",
    "wof:placetype":"postalcode"
},
  "geometry": {"coordinates":[-0.08224187981788,51.53459394616954],"type":"Point"}
}