{
  "type": "Feature",
  "properties": {
    "iso:country":"GB",
    "wof:name":"BR1 4NH",
    "wof:placetype":"postalcode"
},
  "geometry": {"coordinates":[-0.00010342537945,51.42185645757645],"type":"Point"}
}