{
  "type": "Feature",
  "properties": {
    "iso:country": "GB",
    "wof:name": "G71 8NR",
    "wof:placetype": "postalcode"
  },
  "geometry": {"coordinates":[-4.073539,55.805757],"type":"Point"}
}
