{
  "type": "Feature",
  "properties": {
    "date:inception_lower":"2004-11-01",
    "date:inception_upper":"2004-11-30",
    "iso:country":"GB",
    "wof:name":"G71 8NR",
    "wof:placetype":"postalcode"
},
  "geometry": {"coordinates":[-4.073539,55.805757],"type":"Point"}
}