{
  "type": "Feature",
  "properties": {
    "iso:country":"GB",
    "wof:name":"CF5 3AN",
    "wof:placetype":"postalcode"
},
  "geometry": {"coordinates":[-3.23428184893362,51.48895466614728],"type":"Point"}
}