{
  "type": "Feature",
  "properties": {
    "iso:country":"GB",
    "wof:name":"TQ3 3DQ",
    "wof:placetype":"postalcode"
},
  "geometry": {"coordinates":[-3.57614383195363,50.4373528490696],"type":"Point"}
}