{
  "type": "Feature",
  "properties": {
    "iso:country": "GB",
    "wof:name": "TQ3 3DQ",
    "wof:placetype": "postalcode"
  },
  "geometry": {"coordinates":[-3.576144,50.437353],"type":"Point"}
}
