{
  "type": "Feature",
  "properties": {
    "iso:country":"GB",
    "wof:name":"LS8 2EB",
    "wof:placetype":"postalcode"
},
  "geometry": {"coordinates":[-1.50377355150843,53.84700543076739],"type":"Point"}
}