{
  "type": "Feature",
  "properties": {
    "date:inception_lower": "1980-01-01",
    "date:inception_upper": "1980-01-01",
    "iso:country": "GB",
    "wof:name": "LS8 2EB",
    "wof:placetype": "postalcode"
  },
  "geometry": {"coordinates":[-1.503774,53.847005],"type":"Point"}
}
