{
  "type": "Feature",
  "properties": {
    "date:inception_lower": "1995-12-01",
    "date:inception_upper": "1995-12-01",
    "iso:country": "GB",
    "wof:name": "KT2 6ST",
    "wof:placetype": "postalcode"
  },
  "geometry": {"coordinates":[-0.298497,51.411991],"type":"Point"}
}
