{
  "type": "Feature",
  "properties": {
    "iso:country":"GB",
    "wof:name":"KT2 6ST",
    "wof:placetype":"postalcode"
},
  "geometry": {"coordinates":[-0.29852021370716,51.41196479684999],"type":"Point"}
}