{
  "type": "Feature",
  "properties": {
    "date:inception_lower":"2015-04-01",
    "date:inception_upper":"2015-04-30",
    "iso:country":"GB",
    "wof:name":"PO39 0FG",
    "wof:placetype":"postalcode"
},
  "geometry": {"coordinates":[-1.538747,50.684658],"type":"Point"}
}