{
  "type": "Feature",
  "properties": {
    "iso:country": "GB",
    "wof:name": "PO39 0FG",
    "wof:placetype": "postalcode"
  },
  "geometry": {"coordinates":[-1.538747,50.684658],"type":"Point"}
}
