{
  "type": "Feature",
  "properties": {
    "iso:country":"GB",
    "wof:name":"BA2 4DH",
    "wof:placetype":"postalcode"
},
  "geometry": {"coordinates":[-2.35561005356951,51.38323669002448],"type":"Point"}
}