{
  "type": "Feature",
  "properties": {
    "iso:country": "GB",
    "wof:name": "YO61 2QP",
    "wof:placetype": "postalcode"
  },
  "geometry": {"coordinates":[-1.328706,54.12192],"type":"Point"}
}
