{
  "type": "Feature",
  "properties": {
    "iso:country":"GB",
    "wof:name":"HP10 8LR",
    "wof:placetype":"postalcode"
},
  "geometry": {"coordinates":[-0.69616425648062,51.63637614344309],"type":"Point"}
}