{
  "type": "Feature",
  "properties": {
    "iso:country":"GB",
    "wof:name":"HG2 8EB",
    "wof:placetype":"postalcode"
},
  "geometry": {"coordinates":[-1.52932670724322,53.97547317766858],"type":"Point"}
}