{
  "type": "Feature",
  "properties": {
    "iso:country":"GB",
    "wof:name":"TW5 0SD",
    "wof:placetype":"postalcode"
},
  "geometry": {"coordinates":[-0.36903539632964,51.48516687814844],"type":"Point"}
}