{
  "type": "Feature",
  "properties": {
    "iso:country":"GB",
    "wof:name":"HD1 4DU",
    "wof:placetype":"postalcode"
},
  "geometry": {"coordinates":[-1.79504770992912,53.64957946945085],"type":"Point"}
}