{
  "type": "Feature",
  "properties": {
    "date:inception_lower": "1997-12-01",
    "date:inception_upper": "1997-12-01",
    "iso:country": "GB",
    "wof:name": "M2 5BG",
    "wof:placetype": "postalcode"
  },
  "geometry": {"coordinates":[-2.247097,53.478199],"type":"Point"}
}
