{
  "type": "Feature",
  "properties": {
    "iso:country":"GB",
    "wof:name":"M2 5BG",
    "wof:placetype":"postalcode"
},
  "geometry": {"coordinates":[-2.24709688114385,53.47819926379211],"type":"Point"}
}