{
  "type": "Feature",
  "properties": {
    "iso:country":"GB",
    "wof:name":"LE15 7SN",
    "wof:placetype":"postalcode"
},
  "geometry": {"coordinates":[-0.59699035129352,52.71534187758575],"type":"Point"}
}