{
  "type": "Feature",
  "properties": {
    "date:inception_lower": "2006-09-01",
    "date:inception_upper": "2006-09-01",
    "iso:country": "GB",
    "wof:name": "LE15 7SN",
    "wof:placetype": "postalcode"
  },
  "geometry": {"coordinates":[-0.59699,52.715342],"type":"Point"}
}
