{
  "type": "Feature",
  "properties": {
    "date:inception_lower": "2007-07-01",
    "date:inception_upper": "2007-07-01",
    "iso:country": "GB",
    "wof:name": "BH21 1GJ",
    "wof:placetype": "postalcode"
  },
  "geometry": {"coordinates":[-1.978566,50.796133],"type":"Point"}
}
