{
  "type": "Feature",
  "properties": {
    "iso:country":"GB",
    "wof:name":"BH21 1GJ",
    "wof:placetype":"postalcode"
},
  "geometry": {"coordinates":[-1.97856582523508,50.79613254114837],"type":"Point"}
}