{
  "type": "Feature",
  "properties": {
    "iso:country": "GB",
    "wof:name": "BN14 8EL",
    "wof:placetype": "postalcode"
  },
  "geometry": {"coordinates":[-0.36681,50.823151],"type":"Point"}
}
