{
  "type": "Feature",
  "properties": {
    "iso:country": "GB",
    "wof:name": "TA6 3UY",
    "wof:placetype": "postalcode"
  },
  "geometry": {"coordinates":[-3.011938,51.135565],"type":"Point"}
}
