{
  "type": "Feature",
  "properties": {
    "iso:country":"GB",
    "wof:name":"TA6 3UY",
    "wof:placetype":"postalcode"
},
  "geometry": {"coordinates":[-3.01193837521548,51.13556550111968],"type":"Point"}
}