{
  "type": "Feature",
  "properties": {
    "iso:country": "GB",
    "wof:name": "LD2 3DX",
    "wof:placetype": "postalcode"
  },
  "geometry": {"coordinates":[-3.399476,52.147632],"type":"Point"}
}
