{
  "type": "Feature",
  "properties": {
    "iso:country":"GB",
    "wof:name":"LD2 3DX",
    "wof:placetype":"postalcode"
},
  "geometry": {"coordinates":[-3.39947587940377,52.14763152677558],"type":"Point"}
}