{
  "type": "Feature",
  "properties": {
    "date:inception_lower": "1980-01-01",
    "date:inception_upper": "1980-01-01",
    "iso:country": "GB",
    "wof:name": "KT19 8AX",
    "wof:placetype": "postalcode"
  },
  "geometry": {"coordinates":[-0.2671,51.334446],"type":"Point"}
}
