{
  "type": "Feature",
  "properties": {
    "iso:country":"GB",
    "wof:name":"KT19 8AX",
    "wof:placetype":"postalcode"
},
  "geometry": {"coordinates":[-0.26712464943134,51.33444751993623],"type":"Point"}
}