{
  "type": "Feature",
  "properties": {
    "iso:country":"GB",
    "wof:name":"NP4 0NN",
    "wof:placetype":"postalcode"
},
  "geometry": {"coordinates":[-3.00105559388962,51.69341771842379],"type":"Point"}
}