{
  "type": "Feature",
  "properties": {
    "iso:country":"GB",
    "wof:name":"HU5 2NY",
    "wof:placetype":"postalcode"
},
  "geometry": {"coordinates":[-0.35532279321216,53.76438121914779],"type":"Point"}
}