{
  "type": "Feature",
  "properties": {
    "iso:country":"GB",
    "wof:name":"NE30 3DG",
    "wof:placetype":"postalcode"
},
  "geometry": {"coordinates":[-1.43950100039725,55.03166677808087],"type":"Point"}
}