{
  "type": "Feature",
  "properties": {
    "iso:country":"GB",
    "wof:name":"CT11 0HU",
    "wof:placetype":"postalcode"
},
  "geometry": {"coordinates":[1.40165146768394,51.32911414509674],"type":"Point"}
}