{
  "type": "Feature",
  "properties": {
    "iso:country":"GB",
    "wof:name":"GU35 8AA",
    "wof:placetype":"postalcode"
},
  "geometry": {"coordinates":[-0.8178756048157,51.12655526805464],"type":"Point"}
}