{
  "type": "Feature",
  "properties": {
    "iso:country": "GB",
    "wof:name": "CB24 9JS",
    "wof:placetype": "postalcode"
  },
  "geometry": {"coordinates":[0.101201,52.250242],"type":"Point"}
}
