{
  "type": "Feature",
  "properties": {
    "iso:country":"GB",
    "wof:name":"SY23 4QU",
    "wof:placetype":"postalcode"
},
  "geometry": {"coordinates":[-3.87574924535451,52.37757350933295],"type":"Point"}
}