{
  "type": "Feature",
  "properties": {
    "iso:country": "GB",
    "wof:name": "SY23 4QU",
    "wof:placetype": "postalcode"
  },
  "geometry": {"coordinates":[-3.879366,52.37914],"type":"Point"}
}
