{
  "type": "Feature",
  "properties": {
    "date:inception_lower": "2018-12-01",
    "date:inception_upper": "2018-12-01",
    "iso:country": "GB",
    "wof:name": "MK19 6FT",
    "wof:placetype": "postalcode"
  },
  "geometry": {"coordinates":[-0.886832,52.050072],"type":"Point"}
}
