{
  "type": "Feature",
  "properties": {
    "iso:country": "GB",
    "wof:name": "MK19 6FT",
    "wof:placetype": "postalcode"
  },
  "geometry": {"coordinates":[-0.886682,52.050251],"type":"Point"}
}
