{
  "type": "Feature",
  "properties": {
    "iso:country":"GB",
    "wof:name":"PR6 9NS",
    "wof:placetype":"postalcode"
},
  "geometry": {"coordinates":[-2.59419381620286,53.61940818506309],"type":"Point"}
}