{
  "type": "Feature",
  "properties": {
    "iso:country": "GB",
    "wof:name": "L38 6JG",
    "wof:placetype": "postalcode"
  },
  "geometry": {"coordinates":[-3.026053,53.523199],"type":"Point"}
}
