{
  "type": "Feature",
  "properties": {
    "iso:country":"GB",
    "wof:name":"L38 6JG",
    "wof:placetype":"postalcode"
},
  "geometry": {"coordinates":[-3.02605285310705,53.52319915971729],"type":"Point"}
}