{
  "type": "Feature",
  "properties": {
    "iso:country": "GB",
    "wof:name": "WF4 5AT",
    "wof:placetype": "postalcode"
  },
  "geometry": {"coordinates":[-1.554288,53.658687],"type":"Point"}
}
