{
  "type": "Feature",
  "properties": {
    "iso:country":"GB",
    "wof:name":"DH8 5JJ",
    "wof:placetype":"postalcode"
},
  "geometry": {"coordinates":[-1.83252124819878,54.85984692786064],"type":"Point"}
}