{
  "type": "Feature",
  "properties": {
    "iso:country": "GB",
    "wof:name": "BD19 3HJ",
    "wof:placetype": "postalcode"
  },
  "geometry": {"coordinates":[-1.712875,53.725062],"type":"Point"}
}
