{
  "type": "Feature",
  "properties": {
    "iso:country":"GB",
    "wof:name":"CV2 4JT",
    "wof:placetype":"postalcode"
},
  "geometry": {"coordinates":[-1.47592493327544,52.41415487407154],"type":"Point"}
}