{
  "type": "Feature",
  "properties": {
    "date:inception_lower": "1990-07-01",
    "date:inception_upper": "1990-07-01",
    "iso:country": "GB",
    "wof:name": "BN10 7AD",
    "wof:placetype": "postalcode"
  },
  "geometry": {"coordinates":[-0.018389,50.794522],"type":"Point"}
}
