{
  "type": "Feature",
  "properties": {
    "iso:country":"GB",
    "wof:name":"BN10 7AD",
    "wof:placetype":"postalcode"
},
  "geometry": {"coordinates":[-0.01838856914117,50.79452244786626],"type":"Point"}
}