{
  "type": "Feature",
  "properties": {
    "iso:country": "GB",
    "wof:name": "BN10 7AD",
    "wof:placetype": "postalcode"
  },
  "geometry": {"coordinates":[-0.018389,50.794522],"type":"Point"}
}
