{
  "type": "Feature",
  "properties": {
    "iso:country": "GB",
    "wof:name": "BS5 8LR",
    "wof:placetype": "postalcode"
  },
  "geometry": {"coordinates":[-2.53093,51.45742],"type":"Point"}
}
