{
  "type": "Feature",
  "properties": {
    "iso:country": "GB",
    "wof:name": "TA2 8SA",
    "wof:placetype": "postalcode"
  },
  "geometry": {"coordinates":[-3.090395,51.034891],"type":"Point"}
}
