{
  "type": "Feature",
  "properties": {
    "iso:country":"GB",
    "wof:name":"TA2 8SA",
    "wof:placetype":"postalcode"
},
  "geometry": {"coordinates":[-3.09039480137873,51.03489109325279],"type":"Point"}
}