{
  "type": "Feature",
  "properties": {
    "date:inception_lower":"1986-07-01",
    "date:inception_upper":"1986-07-31",
    "iso:country":"GB",
    "wof:name":"TA2 8SA",
    "wof:placetype":"postalcode"
},
  "geometry": {"coordinates":[-3.090395,51.034891],"type":"Point"}
}