{
  "type": "Feature",
  "properties": {
    "iso:country":"GB",
    "wof:name":"SA71 5HR",
    "wof:placetype":"postalcode"
},
  "geometry": {"coordinates":[-4.99365092352039,51.64132132745392],"type":"Point"}
}