{
  "type": "Feature",
  "properties": {
    "iso:country": "GB",
    "wof:name": "SA71 5HR",
    "wof:placetype": "postalcode"
  },
  "geometry": {"coordinates":[-4.993645,51.641333],"type":"Point"}
}
