{
  "type": "Feature",
  "properties": {
    "iso:country":"GB",
    "wof:name":"PO19 3HH",
    "wof:placetype":"postalcode"
},
  "geometry": {"coordinates":[-0.79138994006256,50.83648653203528],"type":"Point"}
}