{
  "type": "Feature",
  "properties": {
    "iso:country": "GB",
    "wof:name": "GL52 6BA",
    "wof:placetype": "postalcode"
  },
  "geometry": {"coordinates":[-2.063843,51.899381],"type":"Point"}
}
