{
  "type": "Feature",
  "properties": {
    "iso:country":"GB",
    "wof:name":"S81 0UD",
    "wof:placetype":"postalcode"
},
  "geometry": {"coordinates":[-1.08927699747056,53.30557335140447],"type":"Point"}
}