{
  "type": "Feature",
  "properties": {
    "iso:country":"GB",
    "wof:name":"RM16 6QX",
    "wof:placetype":"postalcode"
},
  "geometry": {"coordinates":[0.31657685828026,51.49388674918993],"type":"Point"}
}