{
  "type": "Feature",
  "properties": {
    "date:inception_lower": "1985-04-01",
    "date:inception_upper": "1985-04-01",
    "iso:country": "GB",
    "wof:name": "MK42 7AY",
    "wof:placetype": "postalcode"
  },
  "geometry": {"coordinates":[-0.499015,52.106184],"type":"Point"}
}
