{
  "type": "Feature",
  "properties": {
    "date:inception_lower": "2018-01-01",
    "date:inception_upper": "2018-01-01",
    "iso:country": "GB",
    "wof:name": "SO31 4BS",
    "wof:placetype": "postalcode"
  },
  "geometry": {"coordinates":[-1.313483,50.868997],"type":"Point"}
}
