{
  "type": "Feature",
  "properties": {
    "iso:country":"GB",
    "wof:name":"TN4 0TE",
    "wof:placetype":"postalcode"
},
  "geometry": {"coordinates":[0.2625305910675,51.16076158156356],"type":"Point"}
}