{
  "type": "Feature",
  "properties": {
    "date:inception_lower":"1992-01-01",
    "date:inception_upper":"1992-01-31",
    "iso:country":"GB",
    "wof:name":"TQ14 8FD",
    "wof:placetype":"postalcode"
},
  "geometry": {"coordinates":[-3.491639,50.557785],"type":"Point"}
}