{
  "type": "Feature",
  "properties": {
    "iso:country":"GB",
    "wof:name":"RG20 0NF",
    "wof:placetype":"postalcode"
},
  "geometry": {"coordinates":[-1.37269492882759,51.36621100409297],"type":"Point"}
}