{
  "type": "Feature",
  "properties": {
    "iso:country":"GB",
    "wof:name":"HP23 5FE",
    "wof:placetype":"postalcode"
},
  "geometry": {"coordinates":[-0.65645559094109,51.80391143728333],"type":"Point"}
}