{
  "type": "Feature",
  "properties": {
    "iso:country":"GB",
    "wof:name":"LA1 4PU",
    "wof:placetype":"postalcode"
},
  "geometry": {"coordinates":[-2.79500168545228,54.02751016741929],"type":"Point"}
}