{
  "type": "Feature",
  "properties": {
    "date:inception_lower": "2021-05-01",
    "date:inception_upper": "2021-05-01",
    "iso:country": "GB",
    "wof:name": "SE15 2FA",
    "wof:placetype": "postalcode"
  },
  "geometry": {"coordinates":[-0.0625,51.474605],"type":"Point"}
}
