{
  "type": "Feature",
  "properties": {
    "iso:country":"GB",
    "wof:name":"M40 0EH",
    "wof:placetype":"postalcode"
},
  "geometry": {"coordinates":[-2.17256694764504,53.52108818368514],"type":"Point"}
}