{
  "type": "Feature",
  "properties": {
    "date:inception_lower":"1980-01-01",
    "date:inception_upper":"1980-01-31",
    "iso:country":"GB",
    "wof:name":"SG18 8RS",
    "wof:placetype":"postalcode"
},
  "geometry": {"coordinates":[-0.19523,52.083615],"type":"Point"}
}