{
  "type": "Feature",
  "properties": {
    "iso:country":"GB",
    "wof:name":"SG18 8RS",
    "wof:placetype":"postalcode"
},
  "geometry": {"coordinates":[-0.19522990956298,52.08361477218575],"type":"Point"}
}