{
  "type": "Feature",
  "properties": {
    "iso:country": "GB",
    "wof:name": "NR35 2SE",
    "wof:placetype": "postalcode"
  },
  "geometry": {"coordinates":[1.380032,52.434772],"type":"Point"}
}
