{
  "type": "Feature",
  "properties": {
    "iso:country": "GB",
    "wof:name": "WF9 5NG",
    "wof:placetype": "postalcode"
  },
  "geometry": {"coordinates":[-1.363748,53.622448],"type":"Point"}
}
