{
  "type": "Feature",
  "properties": {
    "iso:country":"GB",
    "wof:name":"WF9 5NG",
    "wof:placetype":"postalcode"
},
  "geometry": {"coordinates":[-1.36374765198885,53.62244850253897],"type":"Point"}
}