{
  "type": "Feature",
  "properties": {
    "date:inception_lower": "2002-05-01",
    "date:inception_upper": "2002-05-01",
    "iso:country": "GB",
    "wof:name": "WF9 5NG",
    "wof:placetype": "postalcode"
  },
  "geometry": {"coordinates":[-1.363748,53.622448],"type":"Point"}
}
