{
  "type": "Feature",
  "properties": {
    "iso:country":"GB",
    "wof:name":"BD17 5QG",
    "wof:placetype":"postalcode"
},
  "geometry": {"coordinates":[-1.76770567655153,53.84313231320722],"type":"Point"}
}