{
  "type": "Feature",
  "properties": {
    "iso:country":"GB",
    "wof:name":"NE65 7TJ",
    "wof:placetype":"postalcode"
},
  "geometry": {"coordinates":[-1.91367257225057,55.3095296787552],"type":"Point"}
}