{
  "type": "Feature",
  "properties": {
    "iso:country":"GB",
    "wof:name":"SW9 9NF",
    "wof:placetype":"postalcode"
},
  "geometry": {"coordinates":[-0.12641137651159,51.4652738132619],"type":"Point"}
}