{
  "type": "Feature",
  "properties": {
    "iso:country":"GB",
    "wof:name":"KT12 3DZ",
    "wof:placetype":"postalcode"
},
  "geometry": {"coordinates":[-0.39944033976471,51.37852290993359],"type":"Point"}
}