{
  "type": "Feature",
  "properties": {
    "iso:country":"GB",
    "wof:name":"G44 5AG",
    "wof:placetype":"postalcode"
},
  "geometry": {"coordinates":[-4.2532010510898,55.81725327858697],"type":"Point"}
}