{
  "type": "Feature",
  "properties": {
    "iso:country":"GB",
    "wof:name":"NE30 4DD",
    "wof:placetype":"postalcode"
},
  "geometry": {"coordinates":[-1.41912505869088,55.01479390982998],"type":"Point"}
}