{
  "type": "Feature",
  "properties": {
    "iso:country": "GB",
    "wof:name": "NE66 2AA",
    "wof:placetype": "postalcode"
  },
  "geometry": {"coordinates":[-1.709458,55.406377],"type":"Point"}
}
