{
  "type": "Feature",
  "properties": {
    "date:inception_lower":"1980-01-01",
    "date:inception_upper":"1980-01-31",
    "iso:country":"GB",
    "wof:name":"NE66 2AA",
    "wof:placetype":"postalcode"
},
  "geometry": {"coordinates":[-1.709458,55.406377],"type":"Point"}
}