{
  "type": "Feature",
  "properties": {
    "iso:country":"GB",
    "wof:name":"NE66 2AA",
    "wof:placetype":"postalcode"
},
  "geometry": {"coordinates":[-1.7094577317979,55.40637711340212],"type":"Point"}
}