{
  "type": "Feature",
  "properties": {
    "date:inception_lower": "1990-07-01",
    "date:inception_upper": "1990-07-01",
    "iso:country": "GB",
    "wof:name": "WA4 5RG",
    "wof:placetype": "postalcode"
  },
  "geometry": {"coordinates":[-2.563976,53.351588],"type":"Point"}
}
