{
  "type": "Feature",
  "properties": {
    "iso:country":"GB",
    "wof:name":"WA4 5RG",
    "wof:placetype":"postalcode"
},
  "geometry": {"coordinates":[-2.56397575563258,53.35158767064846],"type":"Point"}
}