{
  "type": "Feature",
  "properties": {
    "iso:country":"GB",
    "wof:name":"NR19 2RH",
    "wof:placetype":"postalcode"
},
  "geometry": {"coordinates":[0.87536290788759,52.70963038312085],"type":"Point"}
}