{
  "type": "Feature",
  "properties": {
    "date:inception_lower":"1980-01-01",
    "date:inception_upper":"1980-01-31",
    "iso:country":"GB",
    "wof:name":"NR19 2RH",
    "wof:placetype":"postalcode"
},
  "geometry": {"coordinates":[0.875363,52.70963],"type":"Point"}
}