{
  "type": "Feature",
  "properties": {
    "iso:country":"GB",
    "wof:name":"E11 3AQ",
    "wof:placetype":"postalcode"
},
  "geometry": {"coordinates":[0.01219884664203,51.56850587567738],"type":"Point"}
}