{
  "type": "Feature",
  "properties": {
    "iso:country":"GB",
    "wof:name":"MK17 8BG",
    "wof:placetype":"postalcode"
},
  "geometry": {"coordinates":[-0.63976533508571,52.04435679691429],"type":"Point"}
}