{
  "type": "Feature",
  "properties": {
    "date:inception_lower": "1980-01-01",
    "date:inception_upper": "1980-01-01",
    "iso:country": "GB",
    "wof:name": "WA11 7SQ",
    "wof:placetype": "postalcode"
  },
  "geometry": {"coordinates":[-2.744968,53.492435],"type":"Point"}
}
