{
  "type": "Feature",
  "properties": {
    "iso:country":"GB",
    "wof:name":"SK22 2LH",
    "wof:placetype":"postalcode"
},
  "geometry": {"coordinates":[-1.92670640544947,53.38002667303025],"type":"Point"}
}