{
  "type": "Feature",
  "properties": {
    "iso:country":"GB",
    "wof:name":"SS9 5HZ",
    "wof:placetype":"postalcode"
},
  "geometry": {"coordinates":[0.64279676865825,51.57172389773476],"type":"Point"}
}