{
  "type": "Feature",
  "properties": {
    "iso:country": "GB",
    "wof:name": "SS9 5HZ",
    "wof:placetype": "postalcode"
  },
  "geometry": {"coordinates":[0.643376,51.571527],"type":"Point"}
}
