{
  "type": "Feature",
  "properties": {
    "iso:country":"GB",
    "wof:name":"ST5 6HX",
    "wof:placetype":"postalcode"
},
  "geometry": {"coordinates":[-2.25227280255583,53.02392106694739],"type":"Point"}
}