{
  "type": "Feature",
  "properties": {
    "iso:country":"GB",
    "wof:name":"EN6 1NA",
    "wof:placetype":"postalcode"
},
  "geometry": {"coordinates":[-0.18107799320638,51.70775932543908],"type":"Point"}
}