{
  "type": "Feature",
  "properties": {
    "iso:country":"GB",
    "wof:name":"KW1 5AT",
    "wof:placetype":"postalcode"
},
  "geometry": {"coordinates":[-3.08637564285781,58.43825223551784],"type":"Point"}
}