{
  "type": "Feature",
  "properties": {
    "iso:country":"GB",
    "wof:name":"EH54 6AB",
    "wof:placetype":"postalcode"
},
  "geometry": {"coordinates":[-3.53314510594889,55.90033607557354],"type":"Point"}
}