{
  "type": "Feature",
  "properties": {
    "iso:country":"GB",
    "wof:name":"HR6 0DP",
    "wof:placetype":"postalcode"
},
  "geometry": {"coordinates":[-2.73186191352121,52.27362611443348],"type":"Point"}
}