{
  "type": "Feature",
  "properties": {
    "date:inception_lower": "1980-01-01",
    "date:inception_upper": "1980-01-01",
    "iso:country": "GB",
    "wof:name": "HR6 0DP",
    "wof:placetype": "postalcode"
  },
  "geometry": {"coordinates":[-2.731862,52.273626],"type":"Point"}
}
