{
  "type": "Feature",
  "properties": {
    "iso:country":"GB",
    "wof:name":"WA15 6HY",
    "wof:placetype":"postalcode"
},
  "geometry": {"coordinates":[-2.33158238269855,53.40314697573189],"type":"Point"}
}