{
  "type": "Feature",
  "properties": {
    "iso:country":"GB",
    "wof:name":"TS25 2AR",
    "wof:placetype":"postalcode"
},
  "geometry": {"coordinates":[-1.19947521484793,54.65400795792435],"type":"Point"}
}