{
  "type": "Feature",
  "properties": {
    "date:inception_lower": "2005-06-01",
    "date:inception_upper": "2005-06-01",
    "iso:country": "GB",
    "wof:name": "L26 6BL",
    "wof:placetype": "postalcode"
  },
  "geometry": {"coordinates":[-2.81989,53.370194],"type":"Point"}
}
