{
  "type": "Feature",
  "properties": {
    "iso:country": "GB",
    "wof:name": "L26 6BL",
    "wof:placetype": "postalcode"
  },
  "geometry": {"coordinates":[-2.81989,53.370194],"type":"Point"}
}
