{
  "type": "Feature",
  "properties": {
    "iso:country":"GB",
    "wof:name":"L26 6BL",
    "wof:placetype":"postalcode"
},
  "geometry": {"coordinates":[-2.81988960088278,53.37019355063994],"type":"Point"}
}