{
  "type": "Feature",
  "properties": {
    "iso:country":"GB",
    "wof:name":"PA1 2RH",
    "wof:placetype":"postalcode"
},
  "geometry": {"coordinates":[-4.44317632918101,55.83936582661259],"type":"Point"}
}