{
  "type": "Feature",
  "properties": {
    "date:inception_lower": "1980-01-01",
    "date:inception_upper": "1980-01-01",
    "iso:country": "GB",
    "wof:name": "PA1 2RH",
    "wof:placetype": "postalcode"
  },
  "geometry": {"coordinates":[-4.443176,55.839366],"type":"Point"}
}
