{
  "type": "Feature",
  "properties": {
    "date:inception_lower": "2016-06-01",
    "date:inception_upper": "2016-06-01",
    "iso:country": "GB",
    "wof:name": "NE1 5AS",
    "wof:placetype": "postalcode"
  },
  "geometry": {"coordinates":[-1.617626,54.971122],"type":"Point"}
}
