{
  "type": "Feature",
  "properties": {
    "iso:country": "GB",
    "wof:name": "NE1 5AS",
    "wof:placetype": "postalcode"
  },
  "geometry": {"coordinates":[-1.617626,54.971122],"type":"Point"}
}
