{
  "type": "Feature",
  "properties": {
    "iso:country":"GB",
    "wof:name":"LN8 5RY",
    "wof:placetype":"postalcode"
},
  "geometry": {"coordinates":[-0.25121154142898,53.31777098092444],"type":"Point"}
}