{
  "type": "Feature",
  "properties": {
    "iso:country": "GB",
    "wof:name": "LN8 5RY",
    "wof:placetype": "postalcode"
  },
  "geometry": {"coordinates":[-0.251211,53.317771],"type":"Point"}
}
