{
  "type": "Feature",
  "properties": {
    "iso:country": "GB",
    "wof:name": "BS15 3TR",
    "wof:placetype": "postalcode"
  },
  "geometry": {"coordinates":[-2.518695,51.435715],"type":"Point"}
}
