{
  "type": "Feature",
  "properties": {
    "iso:country": "GB",
    "wof:name": "SO19 7RL",
    "wof:placetype": "postalcode"
  },
  "geometry": {"coordinates":[-1.358638,50.910629],"type":"Point"}
}
