{
  "type": "Feature",
  "properties": {
    "iso:country":"GB",
    "wof:name":"SO19 7RL",
    "wof:placetype":"postalcode"
},
  "geometry": {"coordinates":[-1.35863850664035,50.91062900167782],"type":"Point"}
}