{
  "type": "Feature",
  "properties": {
    "date:inception_lower": "1990-08-01",
    "date:inception_upper": "1990-08-01",
    "iso:country": "GB",
    "wof:name": "AB30 1BU",
    "wof:placetype": "postalcode"
  },
  "geometry": {"coordinates":[-2.474465,56.829953],"type":"Point"}
}
