{
  "type": "Feature",
  "properties": {
    "iso:country": "GB",
    "wof:name": "W10 5YR",
    "wof:placetype": "postalcode"
  },
  "geometry": {"coordinates":[-0.20714,51.519475],"type":"Point"}
}
