{
  "type": "Feature",
  "properties": {
    "iso:country": "GB",
    "wof:name": "LE12 8PA",
    "wof:placetype": "postalcode"
  },
  "geometry": {"coordinates":[-1.143249,52.751309],"type":"Point"}
}
