{
  "type": "Feature",
  "properties": {
    "iso:country":"GB",
    "wof:name":"LE12 8PA",
    "wof:placetype":"postalcode"
},
  "geometry": {"coordinates":[-1.14324865276052,52.7513092587385],"type":"Point"}
}