{
  "type": "Feature",
  "properties": {
    "iso:country":"GB",
    "wof:name":"TA20 3AB",
    "wof:placetype":"postalcode"
},
  "geometry": {"coordinates":[-2.95552239116243,50.88998803762465],"type":"Point"}
}