{
  "type": "Feature",
  "properties": {
    "date:inception_lower": "1980-01-01",
    "date:inception_upper": "1980-01-01",
    "iso:country": "GB",
    "wof:name": "TA20 3AB",
    "wof:placetype": "postalcode"
  },
  "geometry": {"coordinates":[-2.95715,50.89002],"type":"Point"}
}
