{
  "type": "Feature",
  "properties": {
    "iso:country": "GB",
    "wof:name": "CO15 5NP",
    "wof:placetype": "postalcode"
  },
  "geometry": {"coordinates":[1.190199,51.802083],"type":"Point"}
}
