{
  "type": "Feature",
  "properties": {
    "iso:country":"GB",
    "wof:name":"NE43 7AE",
    "wof:placetype":"postalcode"
},
  "geometry": {"coordinates":[-1.92826356730657,54.94786295948627],"type":"Point"}
}