{
  "type": "Feature",
  "properties": {
    "date:inception_lower": "1980-01-01",
    "date:inception_upper": "1980-01-01",
    "iso:country": "GB",
    "wof:name": "NE43 7AE",
    "wof:placetype": "postalcode"
  },
  "geometry": {"coordinates":[-1.928264,54.947863],"type":"Point"}
}
