{
  "type": "Feature",
  "properties": {
    "iso:country":"GB",
    "wof:name":"LS28 9NH",
    "wof:placetype":"postalcode"
},
  "geometry": {"coordinates":[-1.65515445257893,53.80162509392422],"type":"Point"}
}