{
  "type": "Feature",
  "properties": {
    "iso:country":"GB",
    "wof:name":"TA9 3NL",
    "wof:placetype":"postalcode"
},
  "geometry": {"coordinates":[-2.97904715580278,51.19619260169069],"type":"Point"}
}