{
  "type": "Feature",
  "properties": {
    "iso:country": "GB",
    "wof:name": "TA9 3NL",
    "wof:placetype": "postalcode"
  },
  "geometry": {"coordinates":[-2.979047,51.196193],"type":"Point"}
}
