{
  "type": "Feature",
  "properties": {
    "iso:country":"GB",
    "wof:name":"B35 6BU",
    "wof:placetype":"postalcode"
},
  "geometry": {"coordinates":[-1.79355880657889,52.51984179304056],"type":"Point"}
}