{
  "type": "Feature",
  "properties": {
    "date:inception_lower": "1980-01-01",
    "date:inception_upper": "1980-01-01",
    "iso:country": "GB",
    "wof:name": "CV34 5SQ",
    "wof:placetype": "postalcode"
  },
  "geometry": {"coordinates":[-1.574146,52.292738],"type":"Point"}
}
