{
  "type": "Feature",
  "properties": {
    "date:inception_lower": "1998-06-01",
    "date:inception_upper": "1998-06-01",
    "iso:country": "GB",
    "wof:name": "YO24 4EA",
    "wof:placetype": "postalcode"
  },
  "geometry": {"coordinates":[-1.1074,53.949146],"type":"Point"}
}
