{
  "type": "Feature",
  "properties": {
    "iso:country":"GB",
    "wof:name":"YO24 4EA",
    "wof:placetype":"postalcode"
},
  "geometry": {"coordinates":[-1.1073922021451,53.94911858762057],"type":"Point"}
}