{
  "type": "Feature",
  "properties": {
    "iso:country":"GB",
    "wof:name":"LE5 0FH",
    "wof:placetype":"postalcode"
},
  "geometry": {"coordinates":[-1.10518102430171,52.64301443644188],"type":"Point"}
}