{
  "type": "Feature",
  "properties": {
    "iso:country":"GB",
    "wof:name":"PO9 3BG",
    "wof:placetype":"postalcode"
},
  "geometry": {"coordinates":[-1.00381243402294,50.85462592853267],"type":"Point"}
}