{
  "type": "Feature",
  "properties": {
    "date:inception_lower":"1994-12-01",
    "date:inception_upper":"1994-12-31",
    "iso:country":"GB",
    "wof:name":"PO9 3BG",
    "wof:placetype":"postalcode"
},
  "geometry": {"coordinates":[-1.003812,50.854626],"type":"Point"}
}