{
  "type": "Feature",
  "properties": {
    "iso:country":"GB",
    "wof:name":"NE17 7TF",
    "wof:placetype":"postalcode"
},
  "geometry": {"coordinates":[-1.81709253663618,54.90608640460688],"type":"Point"}
}