{
  "type": "Feature",
  "properties": {
    "iso:country":"GB",
    "wof:name":"TS14 8JB",
    "wof:placetype":"postalcode"
},
  "geometry": {"coordinates":[-1.08196300905104,54.52775008766522],"type":"Point"}
}