{
  "type": "Feature",
  "properties": {
    "iso:country":"GB",
    "wof:name":"LN4 2HR",
    "wof:placetype":"postalcode"
},
  "geometry": {"coordinates":[-0.49487059300938,53.14846498869071],"type":"Point"}
}