{
  "type": "Feature",
  "properties": {
    "date:inception_lower": "1992-01-01",
    "date:inception_upper": "1992-01-01",
    "iso:country": "GB",
    "wof:name": "LN4 2HR",
    "wof:placetype": "postalcode"
  },
  "geometry": {"coordinates":[-0.494871,53.148465],"type":"Point"}
}
