{
  "type": "Feature",
  "properties": {
    "iso:country": "GB",
    "wof:name": "DE7 5JP",
    "wof:placetype": "postalcode"
  },
  "geometry": {"coordinates":[-1.303358,52.975199],"type":"Point"}
}
