{
  "type": "Feature",
  "properties": {
    "iso:country":"GB",
    "wof:name":"WA8 8ER",
    "wof:placetype":"postalcode"
},
  "geometry": {"coordinates":[-2.76330119187876,53.36757565796933],"type":"Point"}
}