{
  "type": "Feature",
  "properties": {
    "date:inception_lower": "1980-01-01",
    "date:inception_upper": "1980-01-01",
    "iso:country": "GB",
    "wof:name": "SW20 0UQ",
    "wof:placetype": "postalcode"
  },
  "geometry": {"coordinates":[-0.237784,51.406607],"type":"Point"}
}
