{
  "type": "Feature",
  "properties": {
    "date:inception_lower": "1980-01-01",
    "date:inception_upper": "1980-01-01",
    "iso:country": "GB",
    "wof:name": "ME19 6NA",
    "wof:placetype": "postalcode"
  },
  "geometry": {"coordinates":[0.408772,51.293688],"type":"Point"}
}
