{
  "type": "Feature",
  "properties": {
    "iso:country":"GB",
    "wof:name":"ME19 6NA",
    "wof:placetype":"postalcode"
},
  "geometry": {"coordinates":[0.40890426850089,51.29402776238101],"type":"Point"}
}