{
  "type": "Feature",
  "properties": {
    "iso:country": "GB",
    "wof:name": "DN6 8QJ",
    "wof:placetype": "postalcode"
  },
  "geometry": {"coordinates":[-1.181604,53.587446],"type":"Point"}
}
