{
  "type": "Feature",
  "properties": {
    "iso:country":"GB",
    "wof:name":"ME2 4LB",
    "wof:placetype":"postalcode"
},
  "geometry": {"coordinates":[0.51219848013188,51.41109329253758],"type":"Point"}
}