{
  "type": "Feature",
  "properties": {
    "iso:country":"GB",
    "wof:name":"LA11 7RW",
    "wof:placetype":"postalcode"
},
  "geometry": {"coordinates":[-2.94079978943923,54.18531803299656],"type":"Point"}
}