{
  "type": "Feature",
  "properties": {
    "iso:country":"GB",
    "wof:name":"CB22 4PS",
    "wof:placetype":"postalcode"
},
  "geometry": {"coordinates":[0.15905872827509,52.09659410825866],"type":"Point"}
}