{
  "type": "Feature",
  "properties": {
    "iso:country":"GB",
    "wof:name":"SE1 2TU",
    "wof:placetype":"postalcode"
},
  "geometry": {"coordinates":[-0.08176025363738,51.50385847083613],"type":"Point"}
}