{
  "type": "Feature",
  "properties": {
    "iso:country":"GB",
    "wof:name":"BS30 5TF",
    "wof:placetype":"postalcode"
},
  "geometry": {"coordinates":[-2.40600570224073,51.46452800188843],"type":"Point"}
}