{
  "type": "Feature",
  "properties": {
    "iso:country":"GB",
    "wof:name":"PL12 6NY",
    "wof:placetype":"postalcode"
},
  "geometry": {"coordinates":[-4.20591427702139,50.4430243897574],"type":"Point"}
}