{
  "type": "Feature",
  "properties": {
    "iso:country": "GB",
    "wof:name": "PL12 6NY",
    "wof:placetype": "postalcode"
  },
  "geometry": {"coordinates":[-4.205914,50.443024],"type":"Point"}
}
