{
  "type": "Feature",
  "properties": {
    "iso:country":"GB",
    "wof:name":"SY20 8UA",
    "wof:placetype":"postalcode"
},
  "geometry": {"coordinates":[-3.86283278098259,52.5612072666973],"type":"Point"}
}