{
  "type": "Feature",
  "properties": {
    "iso:country":"GB",
    "wof:name":"PO36 9FE",
    "wof:placetype":"postalcode"
},
  "geometry": {"coordinates":[-1.16250465119996,50.65663665743885],"type":"Point"}
}