{
  "type": "Feature",
  "properties": {
    "date:inception_lower":"2003-03-01",
    "date:inception_upper":"2003-03-31",
    "iso:country":"GB",
    "wof:name":"PO36 9FE",
    "wof:placetype":"postalcode"
},
  "geometry": {"coordinates":[-1.162505,50.656637],"type":"Point"}
}