{
  "type": "Feature",
  "properties": {
    "iso:country":"GB",
    "wof:name":"NG4 1BB",
    "wof:placetype":"postalcode"
},
  "geometry": {"coordinates":[-1.0893637906829,52.96561760842595],"type":"Point"}
}