{
  "type": "Feature",
  "properties": {
    "date:inception_lower": "1982-03-01",
    "date:inception_upper": "1982-03-01",
    "iso:country": "GB",
    "wof:name": "NG4 1BB",
    "wof:placetype": "postalcode"
  },
  "geometry": {"coordinates":[-1.089423,52.965485],"type":"Point"}
}
