{
  "type": "Feature",
  "properties": {
    "date:inception_lower":"1980-01-01",
    "date:inception_upper":"1980-01-31",
    "iso:country":"GB",
    "wof:name":"PL19 0JD",
    "wof:placetype":"postalcode"
},
  "geometry": {"coordinates":[-4.140598,50.552976],"type":"Point"}
}