{
  "type": "Feature",
  "properties": {
    "date:inception_lower": "2007-01-01",
    "date:inception_upper": "2007-01-01",
    "iso:country": "GB",
    "wof:name": "YO25 8UL",
    "wof:placetype": "postalcode"
  },
  "geometry": {"coordinates":[-0.23037,53.974413],"type":"Point"}
}
