{
  "type": "Feature",
  "properties": {
    "iso:country":"GB",
    "wof:name":"YO25 8UL",
    "wof:placetype":"postalcode"
},
  "geometry": {"coordinates":[-0.23036955002767,53.97441307372002],"type":"Point"}
}