{
  "type": "Feature",
  "properties": {
    "iso:country": "GB",
    "wof:name": "YO25 8UL",
    "wof:placetype": "postalcode"
  },
  "geometry": {"coordinates":[-0.23037,53.974413],"type":"Point"}
}
