{
  "type": "Feature",
  "properties": {
    "iso:country":"GB",
    "wof:name":"SE6 4LU",
    "wof:placetype":"postalcode"
},
  "geometry": {"coordinates":[-0.03086248300406,51.43373516147665],"type":"Point"}
}