{
  "type": "Feature",
  "properties": {
    "iso:country":"GB",
    "wof:name":"LL75 8RJ",
    "wof:placetype":"postalcode"
},
  "geometry": {"coordinates":[-4.20769018372943,53.30712918688941],"type":"Point"}
}