{
  "type": "Feature",
  "properties": {
    "iso:country":"GB",
    "wof:name":"NG3 2BP",
    "wof:placetype":"postalcode"
},
  "geometry": {"coordinates":[-1.12713984339676,52.95514047527301],"type":"Point"}
}