{
  "type": "Feature",
  "properties": {
    "iso:country":"GB",
    "wof:name":"TR13 0EJ",
    "wof:placetype":"postalcode"
},
  "geometry": {"coordinates":[-5.20516316028056,50.15093700424811],"type":"Point"}
}