{
  "type": "Feature",
  "properties": {
    "iso:country": "GB",
    "wof:name": "HA9 9QZ",
    "wof:placetype": "postalcode"
  },
  "geometry": {"coordinates":[-0.284477,51.570682],"type":"Point"}
}
