{
  "type": "Feature",
  "properties": {
    "iso:country":"GB",
    "wof:name":"BR6 0DX",
    "wof:placetype":"postalcode"
},
  "geometry": {"coordinates":[0.10013911346129,51.38112745536477],"type":"Point"}
}