{
  "type": "Feature",
  "properties": {
    "iso:country": "GB",
    "wof:name": "NP44 3HF",
    "wof:placetype": "postalcode"
  },
  "geometry": {"coordinates":[-3.004657,51.631264],"type":"Point"}
}
