{
  "type": "Feature",
  "properties": {
    "iso:country":"GB",
    "wof:name":"NP44 3HF",
    "wof:placetype":"postalcode"
},
  "geometry": {"coordinates":[-3.0046566096908,51.63126448268945],"type":"Point"}
}