{
  "type": "Feature",
  "properties": {
    "iso:country":"GB",
    "wof:name":"TA12 6DS",
    "wof:placetype":"postalcode"
},
  "geometry": {"coordinates":[-2.76921654420885,50.97021109084167],"type":"Point"}
}