{
  "type": "Feature",
  "properties": {
    "iso:country":"GB",
    "wof:name":"DN14 5JN",
    "wof:placetype":"postalcode"
},
  "geometry": {"coordinates":[-0.86058533712783,53.70580863163411],"type":"Point"}
}