{
  "type": "Feature",
  "properties": {
    "iso:country": "GB",
    "wof:name": "DN14 5JN",
    "wof:placetype": "postalcode"
  },
  "geometry": {"coordinates":[-0.860585,53.705809],"type":"Point"}
}
