{
  "type": "Feature",
  "properties": {
    "iso:country": "GB",
    "wof:name": "LS18 4SE",
    "wof:placetype": "postalcode"
  },
  "geometry": {"coordinates":[-1.635409,53.839727],"type":"Point"}
}
