{
  "type": "Feature",
  "properties": {
    "date:inception_lower": "1980-01-01",
    "date:inception_upper": "1980-01-01",
    "iso:country": "GB",
    "wof:name": "N5 2TJ",
    "wof:placetype": "postalcode"
  },
  "geometry": {"coordinates":[-0.093967,51.557644],"type":"Point"}
}
