{
  "type": "Feature",
  "properties": {
    "iso:country":"GB",
    "wof:name":"N5 2TJ",
    "wof:placetype":"postalcode"
},
  "geometry": {"coordinates":[-0.09396744237895,51.55764402698163],"type":"Point"}
}