{
  "type": "Feature",
  "properties": {
    "iso:country":"GB",
    "wof:name":"HU6 9NU",
    "wof:placetype":"postalcode"
},
  "geometry": {"coordinates":[-0.36522030993186,53.78219814720341],"type":"Point"}
}