{
  "type": "Feature",
  "properties": {
    "date:inception_lower": "1980-01-01",
    "date:inception_upper": "1980-01-01",
    "iso:country": "GB",
    "wof:name": "HU6 9NU",
    "wof:placetype": "postalcode"
  },
  "geometry": {"coordinates":[-0.36522,53.782198],"type":"Point"}
}
