{
  "type": "Feature",
  "properties": {
    "iso:country":"GB",
    "wof:name":"PO10 7SU",
    "wof:placetype":"postalcode"
},
  "geometry": {"coordinates":[-0.92983638225976,50.86024813301474],"type":"Point"}
}