{
  "type": "Feature",
  "properties": {
    "iso:country": "GB",
    "wof:name": "TQ3 3UG",
    "wof:placetype": "postalcode"
  },
  "geometry": {"coordinates":[-3.586763,50.432748],"type":"Point"}
}
