{
  "type": "Feature",
  "properties": {
    "iso:country":"GB",
    "wof:name":"TQ3 3UG",
    "wof:placetype":"postalcode"
},
  "geometry": {"coordinates":[-3.58676267450843,50.43274757338211],"type":"Point"}
}