{
  "type": "Feature",
  "properties": {
    "iso:country":"GB",
    "wof:name":"BR5 3QJ",
    "wof:placetype":"postalcode"
},
  "geometry": {"coordinates":[0.11556460134504,51.4067946523794],"type":"Point"}
}