{
  "type": "Feature",
  "properties": {
    "iso:country": "GB",
    "wof:name": "ME19 5GX",
    "wof:placetype": "postalcode"
  },
  "geometry": {"coordinates":[0.407323,51.310401],"type":"Point"}
}
