{
  "type": "Feature",
  "properties": {
    "date:inception_lower": "2018-12-01",
    "date:inception_upper": "2018-12-01",
    "iso:country": "GB",
    "wof:name": "ME19 5GX",
    "wof:placetype": "postalcode"
  },
  "geometry": {"coordinates":[0.407323,51.310401],"type":"Point"}
}
