{
  "type": "Feature",
  "properties": {
    "iso:country":"GB",
    "wof:name":"BS16 6HN",
    "wof:placetype":"postalcode"
},
  "geometry": {"coordinates":[-2.50404242864641,51.48989924010284],"type":"Point"}
}