{
  "type": "Feature",
  "properties": {
    "date:inception_lower": "2019-05-01",
    "date:inception_upper": "2019-05-01",
    "iso:country": "GB",
    "wof:name": "OX29 7BB",
    "wof:placetype": "postalcode"
  },
  "geometry": {"coordinates":[-1.522317,51.783126],"type":"Point"}
}
