{
  "type": "Feature",
  "properties": {
    "iso:country": "GB",
    "wof:name": "OX29 7BB",
    "wof:placetype": "postalcode"
  },
  "geometry": {"coordinates":[-1.523408,51.782771],"type":"Point"}
}
