{
  "type": "Feature",
  "properties": {
    "date:inception_lower": "1980-01-01",
    "date:inception_upper": "1980-01-01",
    "iso:country": "GB",
    "wof:name": "DT11 8TT",
    "wof:placetype": "postalcode"
  },
  "geometry": {"coordinates":[-2.088056,50.869372],"type":"Point"}
}
