{
  "type": "Feature",
  "properties": {
    "iso:country":"GB",
    "wof:name":"ML6 6PW",
    "wof:placetype":"postalcode"
},
  "geometry": {"coordinates":[-3.97613237822312,55.87491555885278],"type":"Point"}
}