{
  "type": "Feature",
  "properties": {
    "iso:country":"GB",
    "wof:name":"GU31 4NY",
    "wof:placetype":"postalcode"
},
  "geometry": {"coordinates":[-0.92070491195991,51.00640280665039],"type":"Point"}
}