{
  "type": "Feature",
  "properties": {
    "iso:country":"GB",
    "wof:name":"HP22 5JD",
    "wof:placetype":"postalcode"
},
  "geometry": {"coordinates":[-0.72049801265777,51.80258457423468],"type":"Point"}
}