{
  "type": "Feature",
  "properties": {
    "iso:country":"GB",
    "wof:name":"DG7 1QG",
    "wof:placetype":"postalcode"
},
  "geometry": {"coordinates":[-3.8747253073139,54.89154030785649],"type":"Point"}
}