{
  "type": "Feature",
  "properties": {
    "iso:country":"GB",
    "wof:name":"DD4 7NX",
    "wof:placetype":"postalcode"
},
  "geometry": {"coordinates":[-2.9203765941158,56.46890202520803],"type":"Point"}
}