{
  "type": "Feature",
  "properties": {
    "date:inception_lower": "2009-02-01",
    "date:inception_upper": "2009-02-01",
    "iso:country": "GB",
    "wof:name": "CO5 8GL",
    "wof:placetype": "postalcode"
  },
  "geometry": {"coordinates":[0.904303,51.776491],"type":"Point"}
}
