{
  "type": "Feature",
  "properties": {
    "iso:country": "GB",
    "wof:name": "WD3 8ND",
    "wof:placetype": "postalcode"
  },
  "geometry": {"coordinates":[-0.496676,51.64168],"type":"Point"}
}
