{
  "type": "Feature",
  "properties": {
    "iso:country": "GB",
    "wof:name": "RM20 3AA",
    "wof:placetype": "postalcode"
  },
  "geometry": {"coordinates":[0.280215,51.473124],"type":"Point"}
}
