{
  "type": "Feature",
  "properties": {
    "iso:country":"GB",
    "wof:name":"NR8 6SY",
    "wof:placetype":"postalcode"
},
  "geometry": {"coordinates":[1.19597630740644,52.6790756345541],"type":"Point"}
}