{
  "type": "Feature",
  "properties": {
    "date:inception_lower": "1980-01-01",
    "date:inception_upper": "1980-01-01",
    "iso:country": "GB",
    "wof:name": "SY12 9DS",
    "wof:placetype": "postalcode"
  },
  "geometry": {"coordinates":[-2.912882,52.93769],"type":"Point"}
}
