{
  "type": "Feature",
  "properties": {
    "iso:country": "GB",
    "wof:name": "EX39 6DS",
    "wof:placetype": "postalcode"
  },
  "geometry": {"coordinates":[-4.497284,50.995386],"type":"Point"}
}
