{
  "type": "Feature",
  "properties": {
    "date:inception_lower": "1997-12-01",
    "date:inception_upper": "1997-12-01",
    "iso:country": "GB",
    "wof:name": "SK13 6NE",
    "wof:placetype": "postalcode"
  },
  "geometry": {"coordinates":[-1.968741,53.438363],"type":"Point"}
}
