{
  "type": "Feature",
  "properties": {
    "iso:country":"GB",
    "wof:name":"SK13 6NE",
    "wof:placetype":"postalcode"
},
  "geometry": {"coordinates":[-1.96874059636636,53.4383626545901],"type":"Point"}
}