{
  "type": "Feature",
  "properties": {
    "iso:country":"GB",
    "wof:name":"LU1 2RD",
    "wof:placetype":"postalcode"
},
  "geometry": {"coordinates":[-0.42009021525719,51.87965108919621],"type":"Point"}
}