{
  "type": "Feature",
  "properties": {
    "iso:country": "GB",
    "wof:name": "TD12 4LQ",
    "wof:placetype": "postalcode"
  },
  "geometry": {"coordinates":[-2.26379,55.647828],"type":"Point"}
}
