{
  "type": "Feature",
  "properties": {
    "iso:country":"GB",
    "wof:name":"TS9 6AN",
    "wof:placetype":"postalcode"
},
  "geometry": {"coordinates":[-1.13790210102044,54.49017265077143],"type":"Point"}
}