{
  "type": "Feature",
  "properties": {
    "date:inception_lower":"1980-01-01",
    "date:inception_upper":"1980-01-31",
    "iso:country":"GB",
    "wof:name":"TS9 6AN",
    "wof:placetype":"postalcode"
},
  "geometry": {"coordinates":[-1.137855,54.490199],"type":"Point"}
}