{
  "type": "Feature",
  "properties": {
    "iso:country":"GB",
    "wof:name":"EX32 9DX",
    "wof:placetype":"postalcode"
},
  "geometry": {"coordinates":[-4.04859610482177,51.0693849057166],"type":"Point"}
}