{
  "type": "Feature",
  "properties": {
    "iso:country":"GB",
    "wof:name":"HG3 4DB",
    "wof:placetype":"postalcode"
},
  "geometry": {"coordinates":[-1.70906940706429,54.0690735347837],"type":"Point"}
}