{
  "type": "Feature",
  "properties": {
    "date:inception_lower": "1980-01-01",
    "date:inception_upper": "1980-01-01",
    "iso:country": "GB",
    "wof:name": "HG3 4DB",
    "wof:placetype": "postalcode"
  },
  "geometry": {"coordinates":[-1.709069,54.069074],"type":"Point"}
}
