{
  "type": "Feature",
  "properties": {
    "iso:country":"GB",
    "wof:name":"W1H 1EN",
    "wof:placetype":"postalcode"
},
  "geometry": {"coordinates":[-0.16015489717779,51.52008699639809],"type":"Point"}
}