{
  "type": "Feature",
  "properties": {
    "iso:country":"GB",
    "wof:name":"LL53 6LA",
    "wof:placetype":"postalcode"
},
  "geometry": {"coordinates":[-4.51873468461137,52.93650535150311],"type":"Point"}
}