{
  "type": "Feature",
  "properties": {
    "date:inception_lower":"1980-01-01",
    "date:inception_upper":"1980-01-31",
    "iso:country":"GB",
    "wof:name":"LL53 6LA",
    "wof:placetype":"postalcode"
},
  "geometry": {"coordinates":[-4.518668,52.936524],"type":"Point"}
}