{
  "type": "Feature",
  "properties": {
    "iso:country":"GB",
    "wof:name":"B77 2BG",
    "wof:placetype":"postalcode"
},
  "geometry": {"coordinates":[-1.67429611050555,52.62644533431279],"type":"Point"}
}