{
  "type": "Feature",
  "properties": {
    "iso:country":"GB",
    "wof:name":"RG8 0LU",
    "wof:placetype":"postalcode"
},
  "geometry": {"coordinates":[-1.11641081759738,51.54040229132275],"type":"Point"}
}