{
  "type": "Feature",
  "properties": {
    "iso:country":"GB",
    "wof:name":"SA3 4BN",
    "wof:placetype":"postalcode"
},
  "geometry": {"coordinates":[-4.00381300519929,51.57524090042413],"type":"Point"}
}