{
  "type": "Feature",
  "properties": {
    "iso:country": "GB",
    "wof:name": "SA3 4BN",
    "wof:placetype": "postalcode"
  },
  "geometry": {"coordinates":[-4.003813,51.575241],"type":"Point"}
}
