{
  "type": "Feature",
  "properties": {
    "iso:country":"GB",
    "wof:name":"WV4 5ED",
    "wof:placetype":"postalcode"
},
  "geometry": {"coordinates":[-2.12069682102894,52.56157366629792],"type":"Point"}
}