{
  "type": "Feature",
  "properties": {
    "date:inception_lower": "1980-01-01",
    "date:inception_upper": "1980-01-01",
    "iso:country": "GB",
    "wof:name": "WV4 5ED",
    "wof:placetype": "postalcode"
  },
  "geometry": {"coordinates":[-2.120697,52.561574],"type":"Point"}
}
