{
  "type": "Feature",
  "properties": {
    "date:inception_lower": "1980-01-01",
    "date:inception_upper": "1980-01-01",
    "iso:country": "GB",
    "wof:name": "SM1 4JZ",
    "wof:placetype": "postalcode"
  },
  "geometry": {"coordinates":[-0.175292,51.36334],"type":"Point"}
}
