{
  "type": "Feature",
  "properties": {
    "iso:country":"GB",
    "wof:name":"SM1 4JZ",
    "wof:placetype":"postalcode"
},
  "geometry": {"coordinates":[-0.17529218842617,51.36334022509354],"type":"Point"}
}