{
  "type": "Feature",
  "properties": {
    "iso:country": "GB",
    "wof:name": "SA31 1DS",
    "wof:placetype": "postalcode"
  },
  "geometry": {"coordinates":[-4.306597,51.861531],"type":"Point"}
}
