{
  "type": "Feature",
  "properties": {
    "iso:country":"GB",
    "wof:name":"NW2 4RT",
    "wof:placetype":"postalcode"
},
  "geometry": {"coordinates":[-0.21955707226451,51.55034584844176],"type":"Point"}
}