{
  "type": "Feature",
  "properties": {
    "iso:country": "GB",
    "wof:name": "PL24 2HR",
    "wof:placetype": "postalcode"
  },
  "geometry": {"coordinates":[-4.722485,50.348873],"type":"Point"}
}
