{
  "type": "Feature",
  "properties": {
    "date:inception_lower": "2005-10-01",
    "date:inception_upper": "2005-10-01",
    "iso:country": "GB",
    "wof:name": "TA1 3TE",
    "wof:placetype": "postalcode"
  },
  "geometry": {"coordinates":[-3.096021,51.011593],"type":"Point"}
}
