{
  "type": "Feature",
  "properties": {
    "iso:country":"GB",
    "wof:name":"TA1 3TE",
    "wof:placetype":"postalcode"
},
  "geometry": {"coordinates":[-3.09602055877122,51.01159272756767],"type":"Point"}
}