{
  "type": "Feature",
  "properties": {
    "iso:country":"GB",
    "wof:name":"AB25 3AH",
    "wof:placetype":"postalcode"
},
  "geometry": {"coordinates":[-2.12107650463676,57.15895409532862],"type":"Point"}
}