{
  "type": "Feature",
  "properties": {
    "iso:country": "GB",
    "wof:name": "DN37 7BB",
    "wof:placetype": "postalcode"
  },
  "geometry": {"coordinates":[-0.170545,53.54493],"type":"Point"}
}
