{
  "type": "Feature",
  "properties": {
    "iso:country":"GB",
    "wof:name":"DN37 7BB",
    "wof:placetype":"postalcode"
},
  "geometry": {"coordinates":[-0.17054536521796,53.54492993701287],"type":"Point"}
}