{
  "type": "Feature",
  "properties": {
    "date:inception_lower": "1980-01-01",
    "date:inception_upper": "1980-01-01",
    "iso:country": "GB",
    "wof:name": "SE25 4JS",
    "wof:placetype": "postalcode"
  },
  "geometry": {"coordinates":[-0.064909,51.396803],"type":"Point"}
}
