{
  "type": "Feature",
  "properties": {
    "iso:country":"GB",
    "wof:name":"SE25 4JS",
    "wof:placetype":"postalcode"
},
  "geometry": {"coordinates":[-0.06490897881221,51.39680253229466],"type":"Point"}
}