{
  "type": "Feature",
  "properties": {
    "iso:country":"GB",
    "wof:name":"RG45 6JU",
    "wof:placetype":"postalcode"
},
  "geometry": {"coordinates":[-0.80306777549599,51.37781952913265],"type":"Point"}
}