{
  "type": "Feature",
  "properties": {
    "date:inception_lower": "1999-12-01",
    "date:inception_upper": "1999-12-01",
    "iso:country": "GB",
    "wof:name": "CV47 2SW",
    "wof:placetype": "postalcode"
  },
  "geometry": {"coordinates":[-1.425817,52.210201],"type":"Point"}
}
