{
  "type": "Feature",
  "properties": {
    "iso:country":"GB",
    "wof:name":"DE4 2AD",
    "wof:placetype":"postalcode"
},
  "geometry": {"coordinates":[-1.58371658630337,53.11761369800514],"type":"Point"}
}