{
  "type": "Feature",
  "properties": {
    "iso:country":"GB",
    "wof:name":"CH8 8NX",
    "wof:placetype":"postalcode"
},
  "geometry": {"coordinates":[-3.25460180324415,53.28015372843891],"type":"Point"}
}