{
  "type": "Feature",
  "properties": {
    "date:inception_lower":"1980-01-01",
    "date:inception_upper":"1980-01-31",
    "iso:country":"GB",
    "wof:name":"CH8 8NX",
    "wof:placetype":"postalcode"
},
  "geometry": {"coordinates":[-3.254602,53.280154],"type":"Point"}
}