{
  "type": "Feature",
  "properties": {
    "iso:country": "GB",
    "wof:name": "CH8 8NX",
    "wof:placetype": "postalcode"
  },
  "geometry": {"coordinates":[-3.254602,53.280154],"type":"Point"}
}
