{
  "type": "Feature",
  "properties": {
    "date:inception_lower":"2010-07-01",
    "date:inception_upper":"2010-07-31",
    "iso:country":"GB",
    "wof:name":"DE11 9TW",
    "wof:placetype":"postalcode"
},
  "geometry": {"coordinates":[-1.580497,52.762686],"type":"Point"}
}