{
  "type": "Feature",
  "properties": {
    "iso:country": "GB",
    "wof:name": "NE42 5EX",
    "wof:placetype": "postalcode"
  },
  "geometry": {"coordinates":[-1.838553,54.964509],"type":"Point"}
}
