{
  "type": "Feature",
  "properties": {
    "iso:country":"GB",
    "wof:name":"NE42 5EX",
    "wof:placetype":"postalcode"
},
  "geometry": {"coordinates":[-1.83855287556777,54.96450949610372],"type":"Point"}
}