{
  "type": "Feature",
  "properties": {
    "date:inception_lower":"2007-02-01",
    "date:inception_upper":"2007-02-28",
    "iso:country":"GB",
    "wof:name":"NE42 5EX",
    "wof:placetype":"postalcode"
},
  "geometry": {"coordinates":[-1.838553,54.964509],"type":"Point"}
}