{
  "type": "Feature",
  "properties": {
    "iso:country":"GB",
    "wof:name":"CA28 7UZ",
    "wof:placetype":"postalcode"
},
  "geometry": {"coordinates":[-3.58746272850021,54.55034463691791],"type":"Point"}
}