{
  "type": "Feature",
  "properties": {
    "iso:country":"GB",
    "wof:name":"G46 7LG",
    "wof:placetype":"postalcode"
},
  "geometry": {"coordinates":[-4.31035437291829,55.7933907791482],"type":"Point"}
}