{
  "type": "Feature",
  "properties": {
    "iso:country":"GB",
    "wof:name":"EC2M 3WA",
    "wof:placetype":"postalcode"
},
  "geometry": {"coordinates":[-0.07989334854314,51.51947500779767],"type":"Point"}
}