{
  "type": "Feature",
  "properties": {
    "date:inception_lower": "1980-01-01",
    "date:inception_upper": "1980-01-01",
    "iso:country": "GB",
    "wof:name": "BL4 9HS",
    "wof:placetype": "postalcode"
  },
  "geometry": {"coordinates":[-2.402627,53.54536],"type":"Point"}
}
