{
  "type": "Feature",
  "properties": {
    "iso:country":"GB",
    "wof:name":"CF72 8QQ",
    "wof:placetype":"postalcode"
},
  "geometry": {"coordinates":[-3.37460359785931,51.54408816578473],"type":"Point"}
}