{
  "type": "Feature",
  "properties": {
    "iso:country": "GB",
    "wof:name": "CF72 8QQ",
    "wof:placetype": "postalcode"
  },
  "geometry": {"coordinates":[-3.374604,51.544088],"type":"Point"}
}
