{
  "type": "Feature",
  "properties": {
    "iso:country":"GB",
    "wof:name":"BB8 0RB",
    "wof:placetype":"postalcode"
},
  "geometry": {"coordinates":[-2.16070592540995,53.86091886428277],"type":"Point"}
}