{
  "type": "Feature",
  "properties": {
    "iso:country":"GB",
    "wof:name":"SE10 0JP",
    "wof:placetype":"postalcode"
},
  "geometry": {"coordinates":[0.0105929512456,51.48889435673745],"type":"Point"}
}