{
  "type": "Feature",
  "properties": {
    "iso:country": "GB",
    "wof:name": "SA72 6FB",
    "wof:placetype": "postalcode"
  },
  "geometry": {"coordinates":[-4.936319,51.699846],"type":"Point"}
}
