{
  "type": "Feature",
  "properties": {
    "date:inception_lower": "1999-06-01",
    "date:inception_upper": "1999-06-01",
    "iso:country": "GB",
    "wof:name": "SA72 6FB",
    "wof:placetype": "postalcode"
  },
  "geometry": {"coordinates":[-4.936319,51.699846],"type":"Point"}
}
