{
  "type": "Feature",
  "properties": {
    "iso:country":"GB",
    "wof:name":"DA1 4FG",
    "wof:placetype":"postalcode"
},
  "geometry": {"coordinates":[0.1787888351454,51.46060133041204],"type":"Point"}
}