{
  "type": "Feature",
  "properties": {
    "iso:country":"GB",
    "wof:name":"LS27 8GG",
    "wof:placetype":"postalcode"
},
  "geometry": {"coordinates":[-1.5877868910996,53.74271158045548],"type":"Point"}
}