{
  "type": "Feature",
  "properties": {
    "date:inception_lower": "2021-06-01",
    "date:inception_upper": "2021-06-01",
    "iso:country": "GB",
    "wof:name": "SK8 7GY",
    "wof:placetype": "postalcode"
  },
  "geometry": {"coordinates":[-2.190116,53.371528],"type":"Point"}
}
