{
  "type": "Feature",
  "properties": {
    "iso:country":"GB",
    "wof:name":"HD3 3FX",
    "wof:placetype":"postalcode"
},
  "geometry": {"coordinates":[-1.82217523548291,53.65985132420489],"type":"Point"}
}