{
  "type": "Feature",
  "properties": {
    "iso:country": "GB",
    "wof:name": "HD3 3FX",
    "wof:placetype": "postalcode"
  },
  "geometry": {"coordinates":[-1.8221,53.659866],"type":"Point"}
}
