{
  "type": "Feature",
  "properties": {
    "date:inception_lower": "2007-01-01",
    "date:inception_upper": "2007-01-01",
    "iso:country": "GB",
    "wof:name": "HD3 3FX",
    "wof:placetype": "postalcode"
  },
  "geometry": {"coordinates":[-1.822176,53.659866],"type":"Point"}
}
