{
  "type": "Feature",
  "properties": {
    "date:inception_lower": "2022-10-01",
    "date:inception_upper": "2022-10-01",
    "iso:country": "GB",
    "wof:name": "CW7 1GU",
    "wof:placetype": "postalcode"
  },
  "geometry": {"coordinates":[-2.540368,53.18709],"type":"Point"}
}
