{
  "type": "Feature",
  "properties": {
    "iso:country": "GB",
    "wof:name": "HU8 9UJ",
    "wof:placetype": "postalcode"
  },
  "geometry": {"coordinates":[-0.302189,53.785134],"type":"Point"}
}
