{
  "type": "Feature",
  "properties": {
    "iso:country":"GB",
    "wof:name":"HU8 9UJ",
    "wof:placetype":"postalcode"
},
  "geometry": {"coordinates":[-0.30218895396244,53.7851335681399],"type":"Point"}
}