{
  "type": "Feature",
  "properties": {
    "date:inception_lower": "1993-01-01",
    "date:inception_upper": "1993-01-01",
    "iso:country": "GB",
    "wof:name": "L3 4BL",
    "wof:placetype": "postalcode"
  },
  "geometry": {"coordinates":[-2.979358,53.38473],"type":"Point"}
}
