{
  "type": "Feature",
  "properties": {
    "date:inception_lower": "2000-12-01",
    "date:inception_upper": "2000-12-01",
    "iso:country": "GB",
    "wof:name": "CF5 1NR",
    "wof:placetype": "postalcode"
  },
  "geometry": {"coordinates":[-3.201708,51.48068],"type":"Point"}
}
