{
  "type": "Feature",
  "properties": {
    "iso:country":"GB",
    "wof:name":"CF5 1NR",
    "wof:placetype":"postalcode"
},
  "geometry": {"coordinates":[-3.20167193446244,51.48071512266401],"type":"Point"}
}