{
  "type": "Feature",
  "properties": {
    "iso:country":"GB",
    "wof:name":"SP2 8LU",
    "wof:placetype":"postalcode"
},
  "geometry": {"coordinates":[-1.81854588105971,51.06348934854314],"type":"Point"}
}