{
  "type": "Feature",
  "properties": {
    "iso:country":"GB",
    "wof:name":"KY7 6DR",
    "wof:placetype":"postalcode"
},
  "geometry": {"coordinates":[-3.13339500915111,56.204736859573],"type":"Point"}
}