{
  "type": "Feature",
  "properties": {
    "iso:country": "GB",
    "wof:name": "M33 4JS",
    "wof:placetype": "postalcode"
  },
  "geometry": {"coordinates":[-2.34236,53.41162],"type":"Point"}
}
