{
  "type": "Feature",
  "properties": {
    "date:inception_lower":"1980-01-01",
    "date:inception_upper":"1980-01-31",
    "iso:country":"GB",
    "wof:name":"GL17 0HF",
    "wof:placetype":"postalcode"
},
  "geometry": {"coordinates":[-2.491062,51.850476],"type":"Point"}
}