{
  "type": "Feature",
  "properties": {
    "date:inception_lower": "1980-01-01",
    "date:inception_upper": "1980-01-01",
    "iso:country": "GB",
    "wof:name": "EX34 9AZ",
    "wof:placetype": "postalcode"
  },
  "geometry": {"coordinates":[-4.121518,51.209261],"type":"Point"}
}
