{
  "type": "Feature",
  "properties": {
    "iso:country": "GB",
    "wof:name": "DN14 9DS",
    "wof:placetype": "postalcode"
  },
  "geometry": {"coordinates":[-1.025052,53.690505],"type":"Point"}
}
