{
  "type": "Feature",
  "properties": {
    "iso:country":"GB",
    "wof:name":"SE3 9PP",
    "wof:placetype":"postalcode"
},
  "geometry": {"coordinates":[0.02891098078288,51.46477499365152],"type":"Point"}
}