{
  "type": "Feature",
  "properties": {
    "date:inception_lower": "1980-01-01",
    "date:inception_upper": "1980-01-01",
    "iso:country": "GB",
    "wof:name": "SE3 9PP",
    "wof:placetype": "postalcode"
  },
  "geometry": {"coordinates":[0.028937,51.464775],"type":"Point"}
}
