{
  "type": "Feature",
  "properties": {
    "iso:country":"GB",
    "wof:name":"ME8 7EY",
    "wof:placetype":"postalcode"
},
  "geometry": {"coordinates":[0.59748599561114,51.36628850343546],"type":"Point"}
}