{
  "type": "Feature",
  "properties": {
    "iso:country":"GB",
    "wof:name":"CH2 4NL",
    "wof:placetype":"postalcode"
},
  "geometry": {"coordinates":[-2.82527850142732,53.28117492374787],"type":"Point"}
}