{
  "type": "Feature",
  "properties": {
    "date:inception_lower": "1980-01-01",
    "date:inception_upper": "1980-01-01",
    "iso:country": "GB",
    "wof:name": "CH2 4NL",
    "wof:placetype": "postalcode"
  },
  "geometry": {"coordinates":[-2.825218,53.281164],"type":"Point"}
}
