{
  "type": "Feature",
  "properties": {
    "date:inception_lower":"2009-05-01",
    "date:inception_upper":"2009-05-31",
    "iso:country":"GB",
    "wof:name":"DN14 0WN",
    "wof:placetype":"postalcode"
},
  "geometry": {"coordinates":[-1.102378,53.703936],"type":"Point"}
}