{
  "type": "Feature",
  "properties": {
    "iso:country":"GB",
    "wof:name":"DN14 0WN",
    "wof:placetype":"postalcode"
},
  "geometry": {"coordinates":[-1.10237763115324,53.70393582928858],"type":"Point"}
}