{
  "type": "Feature",
  "properties": {
    "iso:country": "GB",
    "wof:name": "DN14 0WN",
    "wof:placetype": "postalcode"
  },
  "geometry": {"coordinates":[-1.102378,53.703936],"type":"Point"}
}
