{
  "type": "Feature",
  "properties": {
    "iso:country": "GB",
    "wof:name": "CM9 5NA",
    "wof:placetype": "postalcode"
  },
  "geometry": {"coordinates":[0.689078,51.721844],"type":"Point"}
}
