{
  "type": "Feature",
  "properties": {
    "iso:country": "GB",
    "wof:name": "WF13 3SR",
    "wof:placetype": "postalcode"
  },
  "geometry": {"coordinates":[-1.659653,53.692226],"type":"Point"}
}
