{
  "type": "Feature",
  "properties": {
    "iso:country":"GB",
    "wof:name":"DN4 6AX",
    "wof:placetype":"postalcode"
},
  "geometry": {"coordinates":[-1.07910440320241,53.50821252096986],"type":"Point"}
}