{
  "type": "Feature",
  "properties": {
    "iso:country":"GB",
    "wof:name":"NN12 7GH",
    "wof:placetype":"postalcode"
},
  "geometry": {"coordinates":[-0.8810682147547,52.07603470116478],"type":"Point"}
}