{
  "type": "Feature",
  "properties": {
    "iso:country": "GB",
    "wof:name": "NN12 7GH",
    "wof:placetype": "postalcode"
  },
  "geometry": {"coordinates":[-0.881068,52.076035],"type":"Point"}
}
