{
  "type": "Feature",
  "properties": {
    "iso:country":"GB",
    "wof:name":"PE13 1EN",
    "wof:placetype":"postalcode"
},
  "geometry": {"coordinates":[0.15995476280306,52.66383921711753],"type":"Point"}
}