{
  "type": "Feature",
  "properties": {
    "iso:country": "GB",
    "wof:name": "PE13 1EN",
    "wof:placetype": "postalcode"
  },
  "geometry": {"coordinates":[0.159955,52.663839],"type":"Point"}
}
