{
  "type": "Feature",
  "properties": {
    "iso:country":"GB",
    "wof:name":"DL3 8UL",
    "wof:placetype":"postalcode"
},
  "geometry": {"coordinates":[-1.60254161216091,54.52478323624163],"type":"Point"}
}