{
  "type": "Feature",
  "properties": {
    "date:inception_lower":"1995-12-01",
    "date:inception_upper":"1995-12-31",
    "iso:country":"GB",
    "wof:name":"DL3 8UL",
    "wof:placetype":"postalcode"
},
  "geometry": {"coordinates":[-1.602542,54.524783],"type":"Point"}
}