{
  "type": "Feature",
  "properties": {
    "iso:country":"GB",
    "wof:name":"N16 7UU",
    "wof:placetype":"postalcode"
},
  "geometry": {"coordinates":[-0.07237810621588,51.55578057019115],"type":"Point"}
}