{
  "type": "Feature",
  "properties": {
    "iso:country":"GB",
    "wof:name":"S18 8YX",
    "wof:placetype":"postalcode"
},
  "geometry": {"coordinates":[-1.5058102922332,53.30147240448265],"type":"Point"}
}