{
  "type": "Feature",
  "properties": {
    "date:inception_lower": "2017-09-01",
    "date:inception_upper": "2017-09-01",
    "iso:country": "GB",
    "wof:name": "SE17 1FH",
    "wof:placetype": "postalcode"
  },
  "geometry": {"coordinates":[-0.096321,51.491993],"type":"Point"}
}
