{
  "type": "Feature",
  "properties": {
    "date:inception_lower": "1999-12-01",
    "date:inception_upper": "1999-12-01",
    "iso:country": "GB",
    "wof:name": "MK45 3XA",
    "wof:placetype": "postalcode"
  },
  "geometry": {"coordinates":[-0.445141,52.073833],"type":"Point"}
}
