{
  "type": "Feature",
  "properties": {
    "iso:country": "GB",
    "wof:name": "MK45 3XA",
    "wof:placetype": "postalcode"
  },
  "geometry": {"coordinates":[-0.445141,52.073833],"type":"Point"}
}
