{
  "type": "Feature",
  "properties": {
    "iso:country":"GB",
    "wof:name":"IP22 2LL",
    "wof:placetype":"postalcode"
},
  "geometry": {"coordinates":[0.99971983617974,52.39418233812518],"type":"Point"}
}