{
  "type": "Feature",
  "properties": {
    "date:inception_lower":"1980-01-01",
    "date:inception_upper":"1980-01-31",
    "iso:country":"GB",
    "wof:name":"IP22 2LL",
    "wof:placetype":"postalcode"
},
  "geometry": {"coordinates":[0.99972,52.394182],"type":"Point"}
}