{
  "type": "Feature",
  "properties": {
    "date:inception_lower":"1980-01-01",
    "date:inception_upper":"1980-01-31",
    "iso:country":"GB",
    "wof:name":"ME7 1SX",
    "wof:placetype":"postalcode"
},
  "geometry": {"coordinates":[0.561238,51.39101],"type":"Point"}
}