{
  "type": "Feature",
  "properties": {
    "iso:country":"GB",
    "wof:name":"ME7 1SX",
    "wof:placetype":"postalcode"
},
  "geometry": {"coordinates":[0.56123793065,51.39100994859423],"type":"Point"}
}