{
  "type": "Feature",
  "properties": {
    "iso:country":"GB",
    "wof:name":"BS22 9AE",
    "wof:placetype":"postalcode"
},
  "geometry": {"coordinates":[-2.9442508253981,51.35954987583914],"type":"Point"}
}