{
  "type": "Feature",
  "properties": {
    "iso:country": "GB",
    "wof:name": "BS22 9AE",
    "wof:placetype": "postalcode"
  },
  "geometry": {"coordinates":[-2.944285,51.359556],"type":"Point"}
}
