{
  "type": "Feature",
  "properties": {
    "iso:country":"GB",
    "wof:name":"BR1 9RG",
    "wof:placetype":"postalcode"
},
  "geometry": {"coordinates":[0.01757778519496,51.40822602252302],"type":"Point"}
}