{
  "type": "Feature",
  "properties": {
    "date:inception_lower": "1986-07-01",
    "date:inception_upper": "1986-07-01",
    "iso:country": "GB",
    "wof:name": "HU10 7AZ",
    "wof:placetype": "postalcode"
  },
  "geometry": {"coordinates":[-0.435027,53.739254],"type":"Point"}
}
