{
  "type": "Feature",
  "properties": {
    "iso:country":"GB",
    "wof:name":"HU10 7AZ",
    "wof:placetype":"postalcode"
},
  "geometry": {"coordinates":[-0.43502714481231,53.73925419509793],"type":"Point"}
}