{
  "type": "Feature",
  "properties": {
    "date:inception_lower":"1980-01-01",
    "date:inception_upper":"1980-01-31",
    "iso:country":"GB",
    "wof:name":"DE5 8RH",
    "wof:placetype":"postalcode"
},
  "geometry": {"coordinates":[-1.435357,53.015327],"type":"Point"}
}