{
  "type": "Feature",
  "properties": {
    "date:inception_lower": "2023-10-01",
    "date:inception_upper": "2023-10-01",
    "iso:country": "GB",
    "wof:name": "EX36 4FW",
    "wof:placetype": "postalcode"
  },
  "geometry": {"coordinates":[-3.842034,51.011927],"type":"Point"}
}
