{
  "type": "Feature",
  "properties": {
    "iso:country": "GB",
    "wof:name": "YO26 8DL",
    "wof:placetype": "postalcode"
  },
  "geometry": {"coordinates":[-1.29012,53.993677],"type":"Point"}
}
