{
  "type": "Feature",
  "properties": {
    "iso:country":"GB",
    "wof:name":"WN5 8JZ",
    "wof:placetype":"postalcode"
},
  "geometry": {"coordinates":[-2.68303548481234,53.53378612877223],"type":"Point"}
}