{
  "type": "Feature",
  "properties": {
    "iso:country":"GB",
    "wof:name":"SE27 0NY",
    "wof:placetype":"postalcode"
},
  "geometry": {"coordinates":[-0.10804857454355,51.43340579417084],"type":"Point"}
}