{
  "type": "Feature",
  "properties": {
    "iso:country": "GB",
    "wof:name": "SE27 0NY",
    "wof:placetype": "postalcode"
  },
  "geometry": {"coordinates":[-0.108049,51.433406],"type":"Point"}
}
