{
  "type": "Feature",
  "properties": {
    "iso:country":"GB",
    "wof:name":"S35 2ZY",
    "wof:placetype":"postalcode"
},
  "geometry": {"coordinates":[-1.47933888490621,53.46562814055425],"type":"Point"}
}