{
  "type": "Feature",
  "properties": {
    "date:inception_lower":"1980-01-01",
    "date:inception_upper":"1980-01-31",
    "iso:country":"GB",
    "wof:name":"TA20 3QU",
    "wof:placetype":"postalcode"
},
  "geometry": {"coordinates":[-3.100384,50.933936],"type":"Point"}
}