{
  "type": "Feature",
  "properties": {
    "iso:country":"GB",
    "wof:name":"TA20 3QU",
    "wof:placetype":"postalcode"
},
  "geometry": {"coordinates":[-3.10038418679588,50.93393638967833],"type":"Point"}
}