{
  "type": "Feature",
  "properties": {
    "iso:country": "GB",
    "wof:name": "TA20 3QU",
    "wof:placetype": "postalcode"
  },
  "geometry": {"coordinates":[-3.100384,50.933936],"type":"Point"}
}
