{
  "type": "Feature",
  "properties": {
    "date:inception_lower": "1980-01-01",
    "date:inception_upper": "1980-01-01",
    "iso:country": "GB",
    "wof:name": "RG9 1AS",
    "wof:placetype": "postalcode"
  },
  "geometry": {"coordinates":[-0.897626,51.529622],"type":"Point"}
}
