{
  "type": "Feature",
  "properties": {
    "iso:country":"GB",
    "wof:name":"RG9 1AS",
    "wof:placetype":"postalcode"
},
  "geometry": {"coordinates":[-0.89762615852545,51.52962227787394],"type":"Point"}
}