{
  "type": "Feature",
  "properties": {
    "iso:country":"GB",
    "wof:name":"S26 5QS",
    "wof:placetype":"postalcode"
},
  "geometry": {"coordinates":[-1.27864752804585,53.34312951458978],"type":"Point"}
}