{
  "type": "Feature",
  "properties": {
    "iso:country":"GB",
    "wof:name":"LN6 7JL",
    "wof:placetype":"postalcode"
},
  "geometry": {"coordinates":[-0.5802235401829,53.20328030573845],"type":"Point"}
}