{
  "type": "Feature",
  "properties": {
    "iso:country":"GB",
    "wof:name":"S12 2TR",
    "wof:placetype":"postalcode"
},
  "geometry": {"coordinates":[-1.42899680654757,53.35445113820977],"type":"Point"}
}