{
  "type": "Feature",
  "properties": {
    "iso:country":"GB",
    "wof:name":"CO4 5GN",
    "wof:placetype":"postalcode"
},
  "geometry": {"coordinates":[0.91968966077879,51.92053009450773],"type":"Point"}
}