{
  "type": "Feature",
  "properties": {
    "date:inception_lower":"1997-06-01",
    "date:inception_upper":"1997-06-30",
    "iso:country":"GB",
    "wof:name":"CO4 5GN",
    "wof:placetype":"postalcode"
},
  "geometry": {"coordinates":[0.91969,51.92053],"type":"Point"}
}