{
  "type": "Feature",
  "properties": {
    "date:inception_lower": "1990-02-01",
    "date:inception_upper": "1990-02-01",
    "iso:country": "GB",
    "wof:name": "BA13 3QD",
    "wof:placetype": "postalcode"
  },
  "geometry": {"coordinates":[-2.194624,51.256921],"type":"Point"}
}
