{
  "type": "Feature",
  "properties": {
    "iso:country":"GB",
    "wof:name":"BA13 3QD",
    "wof:placetype":"postalcode"
},
  "geometry": {"coordinates":[-2.19462416344062,51.25692119621114],"type":"Point"}
}