{
  "type": "Feature",
  "properties": {
    "iso:country":"GB",
    "wof:name":"EN1 4LN",
    "wof:placetype":"postalcode"
},
  "geometry": {"coordinates":[-0.05433552558267,51.66647685553828],"type":"Point"}
}