{
  "type": "Feature",
  "properties": {
    "iso:country":"GB",
    "wof:name":"CO15 1JP",
    "wof:placetype":"postalcode"
},
  "geometry": {"coordinates":[1.14997740467253,51.78783351798666],"type":"Point"}
}