{
  "type": "Feature",
  "properties": {
    "date:inception_lower": "1980-01-01",
    "date:inception_upper": "1980-01-01",
    "iso:country": "GB",
    "wof:name": "IV7 8BU",
    "wof:placetype": "postalcode"
  },
  "geometry": {"coordinates":[-4.432812,57.567486],"type":"Point"}
}
