{
  "type": "Feature",
  "properties": {
    "iso:country":"GB",
    "wof:name":"IV7 8BU",
    "wof:placetype":"postalcode"
},
  "geometry": {"coordinates":[-4.43281251219655,57.56748584051211],"type":"Point"}
}