{
  "type": "Feature",
  "properties": {
    "iso:country": "GB",
    "wof:name": "CM7 9NA",
    "wof:placetype": "postalcode"
  },
  "geometry": {"coordinates":[0.564176,51.883932],"type":"Point"}
}
