{
  "type": "Feature",
  "properties": {
    "iso:country":"GB",
    "wof:name":"CM7 9NA",
    "wof:placetype":"postalcode"
},
  "geometry": {"coordinates":[0.5641762712746,51.88393218162763],"type":"Point"}
}