{
  "type": "Feature",
  "properties": {
    "iso:country": "GB",
    "wof:name": "HD3 3BY",
    "wof:placetype": "postalcode"
  },
  "geometry": {"coordinates":[-1.817407,53.66394],"type":"Point"}
}
