{
  "type": "Feature",
  "properties": {
    "date:inception_lower": "1981-06-01",
    "date:inception_upper": "1981-06-01",
    "iso:country": "GB",
    "wof:name": "HD3 3BY",
    "wof:placetype": "postalcode"
  },
  "geometry": {"coordinates":[-1.817407,53.66394],"type":"Point"}
}
