{
  "type": "Feature",
  "properties": {
    "iso:country": "GB",
    "wof:name": "OX15 0TE",
    "wof:placetype": "postalcode"
  },
  "geometry": {"coordinates":[-1.318085,51.98157],"type":"Point"}
}
