{
  "type": "Feature",
  "properties": {
    "iso:country":"GB",
    "wof:name":"OX15 0TE",
    "wof:placetype":"postalcode"
},
  "geometry": {"coordinates":[-1.31808493042923,51.98157020227059],"type":"Point"}
}