{
  "type": "Feature",
  "properties": {
    "iso:country":"GB",
    "wof:name":"BD11 2ES",
    "wof:placetype":"postalcode"
},
  "geometry": {"coordinates":[-1.68663367716953,53.74800792194819],"type":"Point"}
}