{
  "type": "Feature",
  "properties": {
    "iso:country":"GB",
    "wof:name":"NN4 8ST",
    "wof:placetype":"postalcode"
},
  "geometry": {"coordinates":[-0.91792172502783,52.22636417572586],"type":"Point"}
}