{
  "type": "Feature",
  "properties": {
    "iso:country":"GB",
    "wof:name":"SN15 1BJ",
    "wof:placetype":"postalcode"
},
  "geometry": {"coordinates":[-2.11558573149685,51.46434732491173],"type":"Point"}
}