{
  "type": "Feature",
  "properties": {
    "iso:country": "GB",
    "wof:name": "SN15 1BJ",
    "wof:placetype": "postalcode"
  },
  "geometry": {"coordinates":[-2.115586,51.464347],"type":"Point"}
}
