{
  "type": "Feature",
  "properties": {
    "date:inception_lower": "2002-07-01",
    "date:inception_upper": "2002-07-01",
    "iso:country": "GB",
    "wof:name": "DH7 7TL",
    "wof:placetype": "postalcode"
  },
  "geometry": {"coordinates":[-1.637079,54.786981],"type":"Point"}
}
