{
  "type": "Feature",
  "properties": {
    "iso:country":"GB",
    "wof:name":"PE19 6SB",
    "wof:placetype":"postalcode"
},
  "geometry": {"coordinates":[-0.15645831194043,52.24792942427474],"type":"Point"}
}