{
  "type": "Feature",
  "properties": {
    "iso:country":"GB",
    "wof:name":"AL7 4AA",
    "wof:placetype":"postalcode"
},
  "geometry": {"coordinates":[-0.17192117333287,51.78585786912127],"type":"Point"}
}