{
  "type": "Feature",
  "properties": {
    "iso:country": "GB",
    "wof:name": "WA12 9NQ",
    "wof:placetype": "postalcode"
  },
  "geometry": {"coordinates":[-2.660372,53.45225],"type":"Point"}
}
