{
  "type": "Feature",
  "properties": {
    "iso:country": "GB",
    "wof:name": "PO2 0AS",
    "wof:placetype": "postalcode"
  },
  "geometry": {"coordinates":[-1.065886,50.813862],"type":"Point"}
}
