{
  "type": "Feature",
  "properties": {
    "date:inception_lower": "1980-01-01",
    "date:inception_upper": "1980-01-01",
    "iso:country": "GB",
    "wof:name": "LA2 9JZ",
    "wof:placetype": "postalcode"
  },
  "geometry": {"coordinates":[-2.672927,54.090136],"type":"Point"}
}
