{
  "type": "Feature",
  "properties": {
    "iso:country":"GB",
    "wof:name":"LA2 9JZ",
    "wof:placetype":"postalcode"
},
  "geometry": {"coordinates":[-2.6729267294259,54.09013627873338],"type":"Point"}
}