{
  "type": "Feature",
  "properties": {
    "iso:country":"GB",
    "wof:name":"RG4 8HN",
    "wof:placetype":"postalcode"
},
  "geometry": {"coordinates":[-0.97262370935187,51.46914971423462],"type":"Point"}
}