{
  "type": "Feature",
  "properties": {
    "iso:country": "GB",
    "wof:name": "RG4 8HN",
    "wof:placetype": "postalcode"
  },
  "geometry": {"coordinates":[-0.972696,51.46915],"type":"Point"}
}
