{
  "type": "Feature",
  "properties": {
    "iso:country":"GB",
    "wof:name":"NE34 6LY",
    "wof:placetype":"postalcode"
},
  "geometry": {"coordinates":[-1.41775712025381,54.98182557257714],"type":"Point"}
}