{
  "type": "Feature",
  "properties": {
    "iso:country": "GB",
    "wof:name": "NE34 6LY",
    "wof:placetype": "postalcode"
  },
  "geometry": {"coordinates":[-1.417757,54.981826],"type":"Point"}
}
