{
  "type": "Feature",
  "properties": {
    "iso:country":"GB",
    "wof:name":"B77 4RA",
    "wof:placetype":"postalcode"
},
  "geometry": {"coordinates":[-1.64792253188002,52.63054121229084],"type":"Point"}
}