{
  "type": "Feature",
  "properties": {
    "iso:country": "GB",
    "wof:name": "B77 4RA",
    "wof:placetype": "postalcode"
  },
  "geometry": {"coordinates":[-1.647922,52.630541],"type":"Point"}
}
