{
  "type": "Feature",
  "properties": {
    "iso:country":"GB",
    "wof:name":"PE22 9NY",
    "wof:placetype":"postalcode"
},
  "geometry": {"coordinates":[0.09324369275683,53.03269709867851],"type":"Point"}
}