{
  "type": "Feature",
  "properties": {
    "iso:country": "GB",
    "wof:name": "PE22 9NY",
    "wof:placetype": "postalcode"
  },
  "geometry": {"coordinates":[0.093244,53.032697],"type":"Point"}
}
