{
  "type": "Feature",
  "properties": {
    "date:inception_lower": "1980-01-01",
    "date:inception_upper": "1980-01-01",
    "iso:country": "GB",
    "wof:name": "PE22 9NY",
    "wof:placetype": "postalcode"
  },
  "geometry": {"coordinates":[0.093244,53.032697],"type":"Point"}
}
