{
  "type": "Feature",
  "properties": {
    "date:inception_lower": "2023-06-01",
    "date:inception_upper": "2023-06-01",
    "iso:country": "GB",
    "wof:name": "TF10 8FF",
    "wof:placetype": "postalcode"
  },
  "geometry": {"coordinates":[-2.41878,52.773579],"type":"Point"}
}
