{
  "type": "Feature",
  "properties": {
    "date:inception_lower":"1980-01-01",
    "date:inception_upper":"1980-01-31",
    "iso:country":"GB",
    "wof:name":"BS9 1LQ",
    "wof:placetype":"postalcode"
},
  "geometry": {"coordinates":[-2.633626,51.478355],"type":"Point"}
}