{
  "type": "Feature",
  "properties": {
    "date:inception_lower": "1999-06-01",
    "date:inception_upper": "1999-06-01",
    "iso:country": "GB",
    "wof:name": "NP11 7GB",
    "wof:placetype": "postalcode"
  },
  "geometry": {"coordinates":[-3.125383,51.630565],"type":"Point"}
}
