{
  "type": "Feature",
  "properties": {
    "date:inception_lower": "1980-01-01",
    "date:inception_upper": "1980-01-01",
    "iso:country": "GB",
    "wof:name": "S10 3LS",
    "wof:placetype": "postalcode"
  },
  "geometry": {"coordinates":[-1.535425,53.372458],"type":"Point"}
}
