{
  "type": "Feature",
  "properties": {
    "iso:country":"GB",
    "wof:name":"LE7 2JW",
    "wof:placetype":"postalcode"
},
  "geometry": {"coordinates":[-1.06512959419231,52.69289638745666],"type":"Point"}
}