{
  "type": "Feature",
  "properties": {
    "iso:country":"GB",
    "wof:name":"NE65 0TP",
    "wof:placetype":"postalcode"
},
  "geometry": {"coordinates":[-1.61456837046344,55.3407084244194],"type":"Point"}
}