{
  "type": "Feature",
  "properties": {
    "date:inception_lower":"1980-01-01",
    "date:inception_upper":"1980-01-31",
    "iso:country":"GB",
    "wof:name":"N15 6UU",
    "wof:placetype":"postalcode"
},
  "geometry": {"coordinates":[-0.069138,51.580261],"type":"Point"}
}