{
  "type": "Feature",
  "properties": {
    "iso:country":"GB",
    "wof:name":"N15 6UU",
    "wof:placetype":"postalcode"
},
  "geometry": {"coordinates":[-0.06922105068688,51.58025124637221],"type":"Point"}
}