{
  "type": "Feature",
  "properties": {
    "iso:country": "GB",
    "wof:name": "N15 6UU",
    "wof:placetype": "postalcode"
  },
  "geometry": {"coordinates":[-0.069138,51.580261],"type":"Point"}
}
