{
  "type": "Feature",
  "properties": {
    "iso:country":"GB",
    "wof:name":"YO24 3HR",
    "wof:placetype":"postalcode"
},
  "geometry": {"coordinates":[-1.13820612753887,53.94816609317028],"type":"Point"}
}