{
  "type": "Feature",
  "properties": {
    "iso:country":"GB",
    "wof:name":"SS14 2NL",
    "wof:placetype":"postalcode"
},
  "geometry": {"coordinates":[0.47618904042113,51.5777603309601],"type":"Point"}
}