{
  "type": "Feature",
  "properties": {
    "iso:country":"GB",
    "wof:name":"LE11 3EP",
    "wof:placetype":"postalcode"
},
  "geometry": {"coordinates":[-1.20794264948948,52.77128449534776],"type":"Point"}
}