{
  "type": "Feature",
  "properties": {
    "date:inception_lower": "1990-07-01",
    "date:inception_upper": "1990-07-01",
    "iso:country": "GB",
    "wof:name": "M5 4UF",
    "wof:placetype": "postalcode"
  },
  "geometry": {"coordinates":[-2.293388,53.480989],"type":"Point"}
}
