{
  "type": "Feature",
  "properties": {
    "date:inception_lower": "1981-09-01",
    "date:inception_upper": "1981-09-01",
    "iso:country": "GB",
    "wof:name": "TW13 6YQ",
    "wof:placetype": "postalcode"
  },
  "geometry": {"coordinates":[-0.389282,51.435791],"type":"Point"}
}
