{
  "type": "Feature",
  "properties": {
    "iso:country":"GB",
    "wof:name":"PO38 2BQ",
    "wof:placetype":"postalcode"
},
  "geometry": {"coordinates":[-1.28462061106384,50.58484978919881],"type":"Point"}
}