{
  "type": "Feature",
  "properties": {
    "date:inception_lower": "1980-01-01",
    "date:inception_upper": "1980-01-01",
    "iso:country": "GB",
    "wof:name": "PO38 2BQ",
    "wof:placetype": "postalcode"
  },
  "geometry": {"coordinates":[-1.284621,50.58485],"type":"Point"}
}
