{
  "type": "Feature",
  "properties": {
    "iso:country": "GB",
    "wof:name": "NP25 5TN",
    "wof:placetype": "postalcode"
  },
  "geometry": {"coordinates":[-2.723932,51.804472],"type":"Point"}
}
