{
  "type": "Feature",
  "properties": {
    "iso:country":"GB",
    "wof:name":"NP25 5TN",
    "wof:placetype":"postalcode"
},
  "geometry": {"coordinates":[-2.72393253182048,51.80447171797771],"type":"Point"}
}