{
  "type": "Feature",
  "properties": {
    "iso:country":"GB",
    "wof:name":"SP5 3PQ",
    "wof:placetype":"postalcode"
},
  "geometry": {"coordinates":[-1.7444611154561,50.99221364886326],"type":"Point"}
}