{
  "type": "Feature",
  "properties": {
    "iso:country":"GB",
    "wof:name":"TR14 8BU",
    "wof:placetype":"postalcode"
},
  "geometry": {"coordinates":[-5.29171244708229,50.21746025919155],"type":"Point"}
}