{
  "type": "Feature",
  "properties": {
    "iso:country":"GB",
    "wof:name":"LL19 8YL",
    "wof:placetype":"postalcode"
},
  "geometry": {"coordinates":[-3.42669454789894,53.32640218974824],"type":"Point"}
}