{
  "type": "Feature",
  "properties": {
    "date:inception_lower": "2002-09-01",
    "date:inception_upper": "2002-09-01",
    "iso:country": "GB",
    "wof:name": "LL19 8YL",
    "wof:placetype": "postalcode"
  },
  "geometry": {"coordinates":[-3.426695,53.326402],"type":"Point"}
}
