{
  "type": "Feature",
  "properties": {
    "iso:country": "GB",
    "wof:name": "DN17 1EL",
    "wof:placetype": "postalcode"
  },
  "geometry": {"coordinates":[-0.659226,53.572432],"type":"Point"}
}
