{
  "type": "Feature",
  "properties": {
    "iso:country": "GB",
    "wof:name": "TN34 2JX",
    "wof:placetype": "postalcode"
  },
  "geometry": {"coordinates":[0.576753,50.872267],"type":"Point"}
}
