{
  "type": "Feature",
  "properties": {
    "date:inception_lower": "2016-06-01",
    "date:inception_upper": "2016-06-01",
    "iso:country": "GB",
    "wof:name": "KY13 0QT",
    "wof:placetype": "postalcode"
  },
  "geometry": {"coordinates":[-3.587911,56.178675],"type":"Point"}
}
