{
  "type": "Feature",
  "properties": {
    "iso:country": "GB",
    "wof:name": "KY13 0QT",
    "wof:placetype": "postalcode"
  },
  "geometry": {"coordinates":[-3.589034,56.178561],"type":"Point"}
}
