{
  "type": "Feature",
  "properties": {
    "iso:country": "GB",
    "wof:name": "BR7 5QJ",
    "wof:placetype": "postalcode"
  },
  "geometry": {"coordinates":[0.076655,51.406466],"type":"Point"}
}
