{
  "type": "Feature",
  "properties": {
    "iso:country": "GB",
    "wof:name": "BH23 2TD",
    "wof:placetype": "postalcode"
  },
  "geometry": {"coordinates":[-1.804486,50.761664],"type":"Point"}
}
