{
  "type": "Feature",
  "properties": {
    "iso:country":"GB",
    "wof:name":"SA3 4PD",
    "wof:placetype":"postalcode"
},
  "geometry": {"coordinates":[-4.0011721675041,51.56933288143658],"type":"Point"}
}