{
  "type": "Feature",
  "properties": {
    "iso:country":"GB",
    "wof:name":"HU8 9EU",
    "wof:placetype":"postalcode"
},
  "geometry": {"coordinates":[-0.27131225675869,53.77484918146098],"type":"Point"}
}