{
  "type": "Feature",
  "properties": {
    "iso:country":"GB",
    "wof:name":"NN11 3ED",
    "wof:placetype":"postalcode"
},
  "geometry": {"coordinates":[-1.12803842830219,52.21241440064252],"type":"Point"}
}