{
  "type": "Feature",
  "properties": {
    "date:inception_lower":"2014-08-01",
    "date:inception_upper":"2014-08-31",
    "iso:country":"GB",
    "wof:name":"NN11 3ED",
    "wof:placetype":"postalcode"
},
  "geometry": {"coordinates":[-1.128038,52.212414],"type":"Point"}
}