{
  "type": "Feature",
  "properties": {
    "iso:country":"GB",
    "wof:name":"DT5 2EJ",
    "wof:placetype":"postalcode"
},
  "geometry": {"coordinates":[-2.44078862403841,50.53000377985835],"type":"Point"}
}