{
  "type": "Feature",
  "properties": {
    "iso:country": "GB",
    "wof:name": "DT5 2EJ",
    "wof:placetype": "postalcode"
  },
  "geometry": {"coordinates":[-2.440789,50.530004],"type":"Point"}
}
