{
  "type": "Feature",
  "properties": {
    "date:inception_lower": "2023-10-01",
    "date:inception_upper": "2023-10-01",
    "iso:country": "GB",
    "wof:name": "SP2 9GT",
    "wof:placetype": "postalcode"
  },
  "geometry": {"coordinates":[-1.83746,51.091782],"type":"Point"}
}
