{
  "type": "Feature",
  "properties": {
    "date:inception_lower": "2023-10-01",
    "date:inception_upper": "2023-10-01",
    "iso:country": "GB",
    "wof:name": "SP2 9GT",
    "wof:placetype": "postalcode"
  },
  "geometry": {"coordinates":[-1.837245,51.091899],"type":"Point"}
}
