{
  "type": "Feature",
  "properties": {
    "iso:country": "GB",
    "wof:name": "SN11 0QY",
    "wof:placetype": "postalcode"
  },
  "geometry": {"coordinates":[-2.005951,51.439363],"type":"Point"}
}
