{
  "type": "Feature",
  "properties": {
    "date:inception_lower": "1995-07-01",
    "date:inception_upper": "1995-07-01",
    "iso:country": "GB",
    "wof:name": "SN11 0QY",
    "wof:placetype": "postalcode"
  },
  "geometry": {"coordinates":[-2.005951,51.439363],"type":"Point"}
}
