{
  "type": "Feature",
  "properties": {
    "iso:country":"GB",
    "wof:name":"N15 6JX",
    "wof:placetype":"postalcode"
},
  "geometry": {"coordinates":[-0.0713924657271,51.57703166896557],"type":"Point"}
}