{
  "type": "Feature",
  "properties": {
    "date:inception_lower":"1981-06-01",
    "date:inception_upper":"1981-06-30",
    "iso:country":"GB",
    "wof:name":"BS8 3PS",
    "wof:placetype":"postalcode"
},
  "geometry": {"coordinates":[-2.632349,51.451674],"type":"Point"}
}