{
  "type": "Feature",
  "properties": {
    "iso:country": "GB",
    "wof:name": "TN15 7SS",
    "wof:placetype": "postalcode"
  },
  "geometry": {"coordinates":[0.338525,51.298144],"type":"Point"}
}
