{
  "type": "Feature",
  "properties": {
    "iso:country":"GB",
    "wof:name":"TN15 7SS",
    "wof:placetype":"postalcode"
},
  "geometry": {"coordinates":[0.33852529139657,51.29814400660528],"type":"Point"}
}