{
  "type": "Feature",
  "properties": {
    "date:inception_lower": "1980-01-01",
    "date:inception_upper": "1980-01-01",
    "iso:country": "GB",
    "wof:name": "TN15 7SS",
    "wof:placetype": "postalcode"
  },
  "geometry": {"coordinates":[0.338525,51.298144],"type":"Point"}
}
