{
  "type": "Feature",
  "properties": {
    "iso:country":"GB",
    "wof:name":"AB53 8AJ",
    "wof:placetype":"postalcode"
},
  "geometry": {"coordinates":[-2.47896588644148,57.51455592422836],"type":"Point"}
}