{
  "type": "Feature",
  "properties": {
    "iso:country":"GB",
    "wof:name":"BA1 3RF",
    "wof:placetype":"postalcode"
},
  "geometry": {"coordinates":[-2.39487941414703,51.38961184662178],"type":"Point"}
}