{
  "type": "Feature",
  "properties": {
    "iso:country":"GB",
    "wof:name":"BL0 0PS",
    "wof:placetype":"postalcode"
},
  "geometry": {"coordinates":[-2.31624322468515,53.65439647476193],"type":"Point"}
}