{
  "type": "Feature",
  "properties": {
    "iso:country":"GB",
    "wof:name":"HA1 4JH",
    "wof:placetype":"postalcode"
},
  "geometry": {"coordinates":[-0.34958045439804,51.58274837687721],"type":"Point"}
}