{
  "type": "Feature",
  "properties": {
    "iso:country":"GB",
    "wof:name":"B44 8AB",
    "wof:placetype":"postalcode"
},
  "geometry": {"coordinates":[-1.89249258842091,52.53136297476153],"type":"Point"}
}