{
  "type": "Feature",
  "properties": {
    "date:inception_lower":"1980-01-01",
    "date:inception_upper":"1980-01-31",
    "iso:country":"GB",
    "wof:name":"DT9 6JB",
    "wof:placetype":"postalcode"
},
  "geometry": {"coordinates":[-2.550541,50.857593],"type":"Point"}
}