{
  "type": "Feature",
  "properties": {
    "iso:country":"GB",
    "wof:name":"DT9 6JB",
    "wof:placetype":"postalcode"
},
  "geometry": {"coordinates":[-2.55054077533825,50.85759346223063],"type":"Point"}
}