{
  "type": "Feature",
  "properties": {
    "iso:country":"GB",
    "wof:name":"CO4 5ZJ",
    "wof:placetype":"postalcode"
},
  "geometry": {"coordinates":[0.9165458460104,51.92296441003764],"type":"Point"}
}