{
  "type": "Feature",
  "properties": {
    "iso:country":"GB",
    "wof:name":"M14 7NT",
    "wof:placetype":"postalcode"
},
  "geometry": {"coordinates":[-2.23544169014282,53.4495495602403],"type":"Point"}
}