{
  "type": "Feature",
  "properties": {
    "iso:country": "GB",
    "wof:name": "RH9 8DN",
    "wof:placetype": "postalcode"
  },
  "geometry": {"coordinates":[-0.069669,51.245316],"type":"Point"}
}
