{
  "type": "Feature",
  "properties": {
    "date:inception_lower": "1981-06-01",
    "date:inception_upper": "1981-06-01",
    "iso:country": "GB",
    "wof:name": "RH9 8DN",
    "wof:placetype": "postalcode"
  },
  "geometry": {"coordinates":[-0.069669,51.245316],"type":"Point"}
}
