{
  "type": "Feature",
  "properties": {
    "iso:country": "GB",
    "wof:name": "PA14 5PF",
    "wof:placetype": "postalcode"
  },
  "geometry": {"coordinates":[-4.679053,55.931942],"type":"Point"}
}
