{
  "type": "Feature",
  "properties": {
    "iso:country":"GB",
    "wof:name":"PA14 5PF",
    "wof:placetype":"postalcode"
},
  "geometry": {"coordinates":[-4.67905273535445,55.93194169755642],"type":"Point"}
}