{
  "type": "Feature",
  "properties": {
    "iso:country":"GB",
    "wof:name":"HA4 7DR",
    "wof:placetype":"postalcode"
},
  "geometry": {"coordinates":[-0.43144201637745,51.57285561845424],"type":"Point"}
}