{
  "type": "Feature",
  "properties": {
    "iso:country":"GB",
    "wof:name":"SS0 7LP",
    "wof:placetype":"postalcode"
},
  "geometry": {"coordinates":[0.69428428397601,51.53938960217602],"type":"Point"}
}