{
  "type": "Feature",
  "properties": {
    "iso:country": "GB",
    "wof:name": "CH7 6PJ",
    "wof:placetype": "postalcode"
  },
  "geometry": {"coordinates":[-3.177895,53.213471],"type":"Point"}
}
