{
  "type": "Feature",
  "properties": {
    "iso:country":"GB",
    "wof:name":"CH7 6PJ",
    "wof:placetype":"postalcode"
},
  "geometry": {"coordinates":[-3.17789548686304,53.21347136464156],"type":"Point"}
}