{
  "type": "Feature",
  "properties": {
    "iso:country": "GB",
    "wof:name": "LE19 4DA",
    "wof:placetype": "postalcode"
  },
  "geometry": {"coordinates":[-1.232944,52.605532],"type":"Point"}
}
