{
  "type": "Feature",
  "properties": {
    "iso:country":"GB",
    "wof:name":"BH11 8DG",
    "wof:placetype":"postalcode"
},
  "geometry": {"coordinates":[-1.90273670467656,50.75730911619045],"type":"Point"}
}