{
  "type": "Feature",
  "properties": {
    "iso:country": "GB",
    "wof:name": "NN14 2JU",
    "wof:placetype": "postalcode"
  },
  "geometry": {"coordinates":[-0.814141,52.448327],"type":"Point"}
}
