{
  "type": "Feature",
  "properties": {
    "date:inception_lower": "2008-01-01",
    "date:inception_upper": "2008-01-01",
    "iso:country": "GB",
    "wof:name": "NN14 2JU",
    "wof:placetype": "postalcode"
  },
  "geometry": {"coordinates":[-0.814141,52.448327],"type":"Point"}
}
