{
  "type": "Feature",
  "properties": {
    "date:inception_lower": "2003-09-01",
    "date:inception_upper": "2003-09-01",
    "iso:country": "GB",
    "wof:name": "M50 1BX",
    "wof:placetype": "postalcode"
  },
  "geometry": {"coordinates":[-2.311472,53.481356],"type":"Point"}
}
