{
  "type": "Feature",
  "properties": {
    "date:inception_lower": "1991-09-01",
    "date:inception_upper": "1991-09-01",
    "iso:country": "GB",
    "wof:name": "CH5 4GU",
    "wof:placetype": "postalcode"
  },
  "geometry": {"coordinates":[-3.076938,53.202327],"type":"Point"}
}
