{
  "type": "Feature",
  "properties": {
    "iso:country":"GB",
    "wof:name":"CH5 4GU",
    "wof:placetype":"postalcode"
},
  "geometry": {"coordinates":[-3.07693790128892,53.20232714692298],"type":"Point"}
}