{
  "type": "Feature",
  "properties": {
    "iso:country":"GB",
    "wof:name":"SL3 8PX",
    "wof:placetype":"postalcode"
},
  "geometry": {"coordinates":[-0.53291859279629,51.48710665557244],"type":"Point"}
}