{
  "type": "Feature",
  "properties": {
    "iso:country": "GB",
    "wof:name": "SL3 8PX",
    "wof:placetype": "postalcode"
  },
  "geometry": {"coordinates":[-0.532919,51.487107],"type":"Point"}
}
