{
  "type": "Feature",
  "properties": {
    "iso:country":"GB",
    "wof:name":"SL2 5QE",
    "wof:placetype":"postalcode"
},
  "geometry": {"coordinates":[-0.57471771888342,51.5147781571563],"type":"Point"}
}