{
  "type": "Feature",
  "properties": {
    "iso:country":"GB",
    "wof:name":"HU8 7TG",
    "wof:placetype":"postalcode"
},
  "geometry": {"coordinates":[-0.31967261974703,53.75784607498869],"type":"Point"}
}