{
  "type": "Feature",
  "properties": {
    "iso:country":"GB",
    "wof:name":"NP16 6LG",
    "wof:placetype":"postalcode"
},
  "geometry": {"coordinates":[-2.70308404108987,51.62017785478694],"type":"Point"}
}