{
  "type": "Feature",
  "properties": {
    "iso:country":"GB",
    "wof:name":"MK41 7XW",
    "wof:placetype":"postalcode"
},
  "geometry": {"coordinates":[-0.45363726066323,52.16615972386043],"type":"Point"}
}