{
  "type": "Feature",
  "properties": {
    "iso:country":"GB",
    "wof:name":"OX26 2YA",
    "wof:placetype":"postalcode"
},
  "geometry": {"coordinates":[-1.17051582585063,51.90894736369562],"type":"Point"}
}