{
  "type": "Feature",
  "properties": {
    "iso:country":"GB",
    "wof:name":"RG17 7EW",
    "wof:placetype":"postalcode"
},
  "geometry": {"coordinates":[-1.44998702494464,51.47428348092969],"type":"Point"}
}