{
  "type": "Feature",
  "properties": {
    "iso:country":"GB",
    "wof:name":"CB4 3RG",
    "wof:placetype":"postalcode"
},
  "geometry": {"coordinates":[0.11565641037687,52.22521086773477],"type":"Point"}
}