{
  "type": "Feature",
  "properties": {
    "date:inception_lower":"1980-01-01",
    "date:inception_upper":"1980-01-31",
    "iso:country":"GB",
    "wof:name":"CB4 3RG",
    "wof:placetype":"postalcode"
},
  "geometry": {"coordinates":[0.115656,52.225211],"type":"Point"}
}