{
  "type": "Feature",
  "properties": {
    "iso:country": "GB",
    "wof:name": "HP9 2QJ",
    "wof:placetype": "postalcode"
  },
  "geometry": {"coordinates":[-0.606362,51.613848],"type":"Point"}
}
