{
  "type": "Feature",
  "properties": {
    "iso:country":"GB",
    "wof:name":"SN7 8DP",
    "wof:placetype":"postalcode"
},
  "geometry": {"coordinates":[-1.67711638937087,51.66202329340529],"type":"Point"}
}