{
  "type": "Feature",
  "properties": {
    "iso:country": "GB",
    "wof:name": "SN7 8DP",
    "wof:placetype": "postalcode"
  },
  "geometry": {"coordinates":[-1.677116,51.662023],"type":"Point"}
}
