{
  "type": "Feature",
  "properties": {
    "iso:country":"GB",
    "wof:name":"SE5 7SH",
    "wof:placetype":"postalcode"
},
  "geometry": {"coordinates":[-0.08673888200524,51.47718681283459],"type":"Point"}
}