{
  "type": "Feature",
  "properties": {
    "date:inception_lower": "2021-05-01",
    "date:inception_upper": "2021-05-01",
    "iso:country": "GB",
    "wof:name": "TN27 9FX",
    "wof:placetype": "postalcode"
  },
  "geometry": {"coordinates":[0.620141,51.172443],"type":"Point"}
}
