{
  "type": "Feature",
  "properties": {
    "iso:country":"GB",
    "wof:name":"DE74 2GR",
    "wof:placetype":"postalcode"
},
  "geometry": {"coordinates":[-1.37504695912409,52.8419694142538],"type":"Point"}
}