{
  "type": "Feature",
  "properties": {
    "iso:country":"GB",
    "wof:name":"YO1 0ZZ",
    "wof:placetype":"postalcode"
},
  "geometry": {"coordinates":[-1.08585576779368,53.95985920872319],"type":"Point"}
}