{
  "type": "Feature",
  "properties": {
    "date:inception_lower": "2016-03-01",
    "date:inception_upper": "2016-03-01",
    "iso:country": "GB",
    "wof:name": "YO1 0ZZ",
    "wof:placetype": "postalcode"
  },
  "geometry": {"coordinates":[-1.085856,53.959859],"type":"Point"}
}
