{
  "type": "Feature",
  "properties": {
    "iso:country": "GB",
    "wof:name": "CM14 5QJ",
    "wof:placetype": "postalcode"
  },
  "geometry": {"coordinates":[0.268904,51.621395],"type":"Point"}
}
