{
  "type": "Feature",
  "properties": {
    "iso:country":"GB",
    "wof:name":"BR5 2RH",
    "wof:placetype":"postalcode"
},
  "geometry": {"coordinates":[0.1020226246838,51.40748801719552],"type":"Point"}
}