{
  "type": "Feature",
  "properties": {
    "date:inception_lower": "1996-06-01",
    "date:inception_upper": "1996-06-01",
    "iso:country": "GB",
    "wof:name": "BR5 2RH",
    "wof:placetype": "postalcode"
  },
  "geometry": {"coordinates":[0.102023,51.407488],"type":"Point"}
}
