{
  "type": "Feature",
  "properties": {
    "iso:country":"GB",
    "wof:name":"BL4 0BE",
    "wof:placetype":"postalcode"
},
  "geometry": {"coordinates":[-2.41317215838117,53.54809277474031],"type":"Point"}
}