{
  "type": "Feature",
  "properties": {
    "iso:country": "GB",
    "wof:name": "IP9 2BW",
    "wof:placetype": "postalcode"
  },
  "geometry": {"coordinates":[1.075252,51.99072],"type":"Point"}
}
