{
  "type": "Feature",
  "properties": {
    "iso:country":"GB",
    "wof:name":"IP9 2BW",
    "wof:placetype":"postalcode"
},
  "geometry": {"coordinates":[1.07525215372418,51.99072011253792],"type":"Point"}
}