{
  "type": "Feature",
  "properties": {
    "iso:country":"GB",
    "wof:name":"PO19 7US",
    "wof:placetype":"postalcode"
},
  "geometry": {"coordinates":[-0.77095627379146,50.83369216797838],"type":"Point"}
}