{
  "type": "Feature",
  "properties": {
    "iso:country": "GB",
    "wof:name": "PO19 7US",
    "wof:placetype": "postalcode"
  },
  "geometry": {"coordinates":[-0.770895,50.833655],"type":"Point"}
}
