{
  "type": "Feature",
  "properties": {
    "iso:country":"GB",
    "wof:name":"TF2 8AJ",
    "wof:placetype":"postalcode"
},
  "geometry": {"coordinates":[-2.43364761961285,52.72274630439863],"type":"Point"}
}