{
  "type": "Feature",
  "properties": {
    "iso:country": "GB",
    "wof:name": "E2 6QU",
    "wof:placetype": "postalcode"
  },
  "geometry": {"coordinates":[-0.059061,51.531101],"type":"Point"}
}
