{
  "type": "Feature",
  "properties": {
    "iso:country":"GB",
    "wof:name":"E2 6QU",
    "wof:placetype":"postalcode"
},
  "geometry": {"coordinates":[-0.05906065304112,51.53110124700869],"type":"Point"}
}