{
  "type": "Feature",
  "properties": {
    "iso:country": "GB",
    "wof:name": "LL24 0DH",
    "wof:placetype": "postalcode"
  },
  "geometry": {"coordinates":[-3.850128,53.105612],"type":"Point"}
}
