{
  "type": "Feature",
  "properties": {
    "date:inception_lower": "1980-01-01",
    "date:inception_upper": "1980-01-01",
    "iso:country": "GB",
    "wof:name": "PE11 2AB",
    "wof:placetype": "postalcode"
  },
  "geometry": {"coordinates":[-0.146704,52.788712],"type":"Point"}
}
