{
  "type": "Feature",
  "properties": {
    "date:inception_lower": "1980-01-01",
    "date:inception_upper": "1980-01-01",
    "iso:country": "GB",
    "wof:name": "PR7 1EP",
    "wof:placetype": "postalcode"
  },
  "geometry": {"coordinates":[-2.631659,53.655222],"type":"Point"}
}
