{
  "type": "Feature",
  "properties": {
    "iso:country":"GB",
    "wof:name":"PR7 1EP",
    "wof:placetype":"postalcode"
},
  "geometry": {"coordinates":[-2.63158001555109,53.65481057341615],"type":"Point"}
}