{
  "type": "Feature",
  "properties": {
    "date:inception_lower": "1981-06-01",
    "date:inception_upper": "1981-06-01",
    "iso:country": "GB",
    "wof:name": "LL18 4JN",
    "wof:placetype": "postalcode"
  },
  "geometry": {"coordinates":[-3.467066,53.321454],"type":"Point"}
}
