{
  "type": "Feature",
  "properties": {
    "iso:country":"GB",
    "wof:name":"LL18 4JN",
    "wof:placetype":"postalcode"
},
  "geometry": {"coordinates":[-3.4670658530814,53.3214536581964],"type":"Point"}
}