{
  "type": "Feature",
  "properties": {
    "date:inception_lower": "1980-01-01",
    "date:inception_upper": "1980-01-01",
    "iso:country": "GB",
    "wof:name": "GU10 5RU",
    "wof:placetype": "postalcode"
  },
  "geometry": {"coordinates":[-0.86201,51.248262],"type":"Point"}
}
