{
  "type": "Feature",
  "properties": {
    "iso:country":"GB",
    "wof:name":"PA23 8NW",
    "wof:placetype":"postalcode"
},
  "geometry": {"coordinates":[-4.92480166650042,55.96110893992911],"type":"Point"}
}