{
  "type": "Feature",
  "properties": {
    "iso:country": "GB",
    "wof:name": "S61 3AL",
    "wof:placetype": "postalcode"
  },
  "geometry": {"coordinates":[-1.399439,53.446872],"type":"Point"}
}
