{
  "type": "Feature",
  "properties": {
    "iso:country": "GB",
    "wof:name": "CV37 9NQ",
    "wof:placetype": "postalcode"
  },
  "geometry": {"coordinates":[-1.725646,52.200873],"type":"Point"}
}
