{
  "type": "Feature",
  "properties": {
    "iso:country":"GB",
    "wof:name":"CV37 9NQ",
    "wof:placetype":"postalcode"
},
  "geometry": {"coordinates":[-1.72561218287521,52.20061592173095],"type":"Point"}
}