{
  "type": "Feature",
  "properties": {
    "date:inception_lower": "1987-04-01",
    "date:inception_upper": "1987-04-01",
    "iso:country": "GB",
    "wof:name": "BL2 6RS",
    "wof:placetype": "postalcode"
  },
  "geometry": {"coordinates":[-2.359797,53.572004],"type":"Point"}
}
