{
  "type": "Feature",
  "properties": {
    "iso:country":"GB",
    "wof:name":"BL2 6RS",
    "wof:placetype":"postalcode"
},
  "geometry": {"coordinates":[-2.35979745743382,53.57200364237183],"type":"Point"}
}