{
  "type": "Feature",
  "properties": {
    "iso:country":"GB",
    "wof:name":"RH11 7BJ",
    "wof:placetype":"postalcode"
},
  "geometry": {"coordinates":[-0.19858231618342,51.1149322193201],"type":"Point"}
}