{
  "type": "Feature",
  "properties": {
    "iso:country":"GB",
    "wof:name":"SA11 1NP",
    "wof:placetype":"postalcode"
},
  "geometry": {"coordinates":[-3.80812035436138,51.65921608684814],"type":"Point"}
}