{
  "type": "Feature",
  "properties": {
    "date:inception_lower": "2011-05-01",
    "date:inception_upper": "2011-05-01",
    "iso:country": "GB",
    "wof:name": "CF83 2DD",
    "wof:placetype": "postalcode"
  },
  "geometry": {"coordinates":[-3.244897,51.573474],"type":"Point"}
}
