{
  "type": "Feature",
  "properties": {
    "iso:country":"GB",
    "wof:name":"KT19 9NF",
    "wof:placetype":"postalcode"
},
  "geometry": {"coordinates":[-0.28014693686792,51.36470166361126],"type":"Point"}
}