{
  "type": "Feature",
  "properties": {
    "iso:country": "GB",
    "wof:name": "IP12 1HS",
    "wof:placetype": "postalcode"
  },
  "geometry": {"coordinates":[1.318473,52.094588],"type":"Point"}
}
