{
  "type": "Feature",
  "properties": {
    "date:inception_lower":"2010-10-01",
    "date:inception_upper":"2010-10-31",
    "iso:country":"GB",
    "wof:name":"BA1 6FA",
    "wof:placetype":"postalcode"
},
  "geometry": {"coordinates":[-2.345643,51.397249],"type":"Point"}
}