{
  "type": "Feature",
  "properties": {
    "date:inception_lower": "1980-01-01",
    "date:inception_upper": "1980-01-01",
    "iso:country": "GB",
    "wof:name": "SR6 9NJ",
    "wof:placetype": "postalcode"
  },
  "geometry": {"coordinates":[-1.370488,54.928966],"type":"Point"}
}
