{
  "type": "Feature",
  "properties": {
    "iso:country":"GB",
    "wof:name":"SR6 9NJ",
    "wof:placetype":"postalcode"
},
  "geometry": {"coordinates":[-1.37048841232646,54.92896585245351],"type":"Point"}
}