{
  "type": "Feature",
  "properties": {
    "iso:country":"GB",
    "wof:name":"SO22 4AA",
    "wof:placetype":"postalcode"
},
  "geometry": {"coordinates":[-1.32540501348398,51.0556689171847],"type":"Point"}
}