{
  "type": "Feature",
  "properties": {
    "date:inception_lower":"1980-01-01",
    "date:inception_upper":"1980-01-31",
    "iso:country":"GB",
    "wof:name":"SO22 4AA",
    "wof:placetype":"postalcode"
},
  "geometry": {"coordinates":[-1.325405,51.055669],"type":"Point"}
}