{
  "type": "Feature",
  "properties": {
    "date:inception_lower": "2022-03-01",
    "date:inception_upper": "2022-03-01",
    "iso:country": "GB",
    "wof:name": "MK13 0FB",
    "wof:placetype": "postalcode"
  },
  "geometry": {"coordinates":[-0.7926,52.064429],"type":"Point"}
}
