{
  "type": "Feature",
  "properties": {
    "iso:country":"GB",
    "wof:name":"PR1 3SE",
    "wof:placetype":"postalcode"
},
  "geometry": {"coordinates":[-2.6954253024728,53.7564018645532],"type":"Point"}
}