{
  "type": "Feature",
  "properties": {
    "iso:country":"GB",
    "wof:name":"BR8 8HY",
    "wof:placetype":"postalcode"
},
  "geometry": {"coordinates":[0.17582268592713,51.39609559058542],"type":"Point"}
}