{
  "type": "Feature",
  "properties": {
    "date:inception_lower": "2003-03-01",
    "date:inception_upper": "2003-03-01",
    "iso:country": "GB",
    "wof:name": "WS11 0EF",
    "wof:placetype": "postalcode"
  },
  "geometry": {"coordinates":[-2.027134,52.689026],"type":"Point"}
}
