{
  "type": "Feature",
  "properties": {
    "iso:country":"GB",
    "wof:name":"BH23 3NS",
    "wof:placetype":"postalcode"
},
  "geometry": {"coordinates":[-1.74780607215551,50.72916416990078],"type":"Point"}
}