{
  "type": "Feature",
  "properties": {
    "date:inception_lower": "2002-10-01",
    "date:inception_upper": "2002-10-01",
    "iso:country": "GB",
    "wof:name": "SN15 1GE",
    "wof:placetype": "postalcode"
  },
  "geometry": {"coordinates":[-2.108854,51.46857],"type":"Point"}
}
