{
  "type": "Feature",
  "properties": {
    "iso:country": "GB",
    "wof:name": "SN15 1GE",
    "wof:placetype": "postalcode"
  },
  "geometry": {"coordinates":[-2.110249,51.468101],"type":"Point"}
}
