{
  "type": "Feature",
  "properties": {
    "iso:country":"GB",
    "wof:name":"DL9 4NA",
    "wof:placetype":"postalcode"
},
  "geometry": {"coordinates":[-1.69337557016907,54.37992513156067],"type":"Point"}
}