{
  "type": "Feature",
  "properties": {
    "iso:country":"GB",
    "wof:name":"RG12 1AD",
    "wof:placetype":"postalcode"
},
  "geometry": {"coordinates":[-0.74742249456287,51.41715390138383],"type":"Point"}
}