{
  "type": "Feature",
  "properties": {
    "iso:country":"GB",
    "wof:name":"NR6 6XQ",
    "wof:placetype":"postalcode"
},
  "geometry": {"coordinates":[1.2780161457016,52.66234454000022],"type":"Point"}
}