{
  "type": "Feature",
  "properties": {
    "date:inception_lower":"1993-08-01",
    "date:inception_upper":"1993-08-31",
    "iso:country":"GB",
    "wof:name":"GU21 3NL",
    "wof:placetype":"postalcode"
},
  "geometry": {"coordinates":[-0.590331,51.3173],"type":"Point"}
}