{
  "type": "Feature",
  "properties": {
    "iso:country":"GB",
    "wof:name":"BN3 5DQ",
    "wof:placetype":"postalcode"
},
  "geometry": {"coordinates":[-0.18043464494063,50.83290286376387],"type":"Point"}
}