{
  "type": "Feature",
  "properties": {
    "iso:country":"GB",
    "wof:name":"M28 3LH",
    "wof:placetype":"postalcode"
},
  "geometry": {"coordinates":[-2.39525837327304,53.52551154547691],"type":"Point"}
}