{
  "type": "Feature",
  "properties": {
    "iso:country":"GB",
    "wof:name":"BS4 5QW",
    "wof:placetype":"postalcode"
},
  "geometry": {"coordinates":[-2.53530978002913,51.43440828037501],"type":"Point"}
}