{
  "type": "Feature",
  "properties": {
    "iso:country": "GB",
    "wof:name": "BS4 5QW",
    "wof:placetype": "postalcode"
  },
  "geometry": {"coordinates":[-2.53531,51.434408],"type":"Point"}
}
