{
  "type": "Feature",
  "properties": {
    "iso:country":"GB",
    "wof:name":"W1G 8QT",
    "wof:placetype":"postalcode"
},
  "geometry": {"coordinates":[-0.14750204184474,51.51895262818541],"type":"Point"}
}