{
  "type": "Feature",
  "properties": {
    "iso:country": "GB",
    "wof:name": "DY13 9JU",
    "wof:placetype": "postalcode"
  },
  "geometry": {"coordinates":[-2.257138,52.350459],"type":"Point"}
}
