{
  "type": "Feature",
  "properties": {
    "iso:country":"GB",
    "wof:name":"DY13 9JU",
    "wof:placetype":"postalcode"
},
  "geometry": {"coordinates":[-2.25713786866554,52.35045884085969],"type":"Point"}
}