{
  "type": "Feature",
  "properties": {
    "iso:country": "GB",
    "wof:name": "PE6 7YF",
    "wof:placetype": "postalcode"
  },
  "geometry": {"coordinates":[-0.199705,52.608109],"type":"Point"}
}
