{
  "type": "Feature",
  "properties": {
    "iso:country":"GB",
    "wof:name":"PO7 5XT",
    "wof:placetype":"postalcode"
},
  "geometry": {"coordinates":[-1.04118754229913,50.86724991059052],"type":"Point"}
}