{
  "type": "Feature",
  "properties": {
    "iso:country":"GB",
    "wof:name":"LS9 6PH",
    "wof:placetype":"postalcode"
},
  "geometry": {"coordinates":[-1.48901911554068,53.8066682265405],"type":"Point"}
}