{
  "type": "Feature",
  "properties": {
    "iso:country": "GB",
    "wof:name": "CA7 0JJ",
    "wof:placetype": "postalcode"
  },
  "geometry": {"coordinates":[-3.136438,54.890294],"type":"Point"}
}
