{
  "type": "Feature",
  "properties": {
    "iso:country": "GB",
    "wof:name": "RG41 3GH",
    "wof:placetype": "postalcode"
  },
  "geometry": {"coordinates":[-0.857072,51.411548],"type":"Point"}
}
