{
  "type": "Feature",
  "properties": {
    "iso:country":"GB",
    "wof:name":"WF2 6JS",
    "wof:placetype":"postalcode"
},
  "geometry": {"coordinates":[-1.46573355269533,53.6481142191214],"type":"Point"}
}