{
  "type": "Feature",
  "properties": {
    "iso:country":"GB",
    "wof:name":"BS5 9TA",
    "wof:placetype":"postalcode"
},
  "geometry": {"coordinates":[-2.55427400320357,51.45611584993195],"type":"Point"}
}