{
  "type": "Feature",
  "properties": {
    "date:inception_lower":"2003-05-01",
    "date:inception_upper":"2003-05-31",
    "iso:country":"GB",
    "wof:name":"BS5 9TA",
    "wof:placetype":"postalcode"
},
  "geometry": {"coordinates":[-2.554274,51.456116],"type":"Point"}
}