{
  "type": "Feature",
  "properties": {
    "iso:country":"GB",
    "wof:name":"BN9 9QD",
    "wof:placetype":"postalcode"
},
  "geometry": {"coordinates":[0.05130626749603,50.79243608179398],"type":"Point"}
}