{
  "type": "Feature",
  "properties": {
    "iso:country": "GB",
    "wof:name": "BN9 9QD",
    "wof:placetype": "postalcode"
  },
  "geometry": {"coordinates":[0.051306,50.792436],"type":"Point"}
}
