{
  "type": "Feature",
  "properties": {
    "iso:country":"GB",
    "wof:name":"BA2 8JW",
    "wof:placetype":"postalcode"
},
  "geometry": {"coordinates":[-2.43180728970147,51.31558733687005],"type":"Point"}
}