{
  "type": "Feature",
  "properties": {
    "iso:country":"GB",
    "wof:name":"N13 6BQ",
    "wof:placetype":"postalcode"
},
  "geometry": {"coordinates":[-0.09624008076032,51.61478303045379],"type":"Point"}
}