{
  "type": "Feature",
  "properties": {
    "iso:country": "GB",
    "wof:name": "ME4 6QP",
    "wof:placetype": "postalcode"
  },
  "geometry": {"coordinates":[0.518347,51.372235],"type":"Point"}
}
