{
  "type": "Feature",
  "properties": {
    "date:inception_lower": "1980-01-01",
    "date:inception_upper": "1980-01-01",
    "iso:country": "GB",
    "wof:name": "ME4 6QP",
    "wof:placetype": "postalcode"
  },
  "geometry": {"coordinates":[0.518347,51.372235],"type":"Point"}
}
