{
  "type": "Feature",
  "properties": {
    "iso:country":"GB",
    "wof:name":"ME4 6QP",
    "wof:placetype":"postalcode"
},
  "geometry": {"coordinates":[0.5186496409481,51.37225553938288],"type":"Point"}
}