{
  "type": "Feature",
  "properties": {
    "iso:country": "GB",
    "wof:name": "SK4 2JD",
    "wof:placetype": "postalcode"
  },
  "geometry": {"coordinates":[-2.1795,53.412992],"type":"Point"}
}
