{
  "type": "Feature",
  "properties": {
    "date:inception_lower": "1980-01-01",
    "date:inception_upper": "1980-01-01",
    "iso:country": "GB",
    "wof:name": "SK4 2JD",
    "wof:placetype": "postalcode"
  },
  "geometry": {"coordinates":[-2.1795,53.412992],"type":"Point"}
}
