{
  "type": "Feature",
  "properties": {
    "iso:country":"GB",
    "wof:name":"SK4 2JD",
    "wof:placetype":"postalcode"
},
  "geometry": {"coordinates":[-2.179500161383,53.41299163137267],"type":"Point"}
}