{
  "type": "Feature",
  "properties": {
    "iso:country":"GB",
    "wof:name":"TR1 2PD",
    "wof:placetype":"postalcode"
},
  "geometry": {"coordinates":[-5.05450359725535,50.25955003273265],"type":"Point"}
}