{
  "type": "Feature",
  "properties": {
    "date:inception_lower": "2012-04-01",
    "date:inception_upper": "2012-04-01",
    "iso:country": "GB",
    "wof:name": "MK45 2GB",
    "wof:placetype": "postalcode"
  },
  "geometry": {"coordinates":[-0.503302,52.021033],"type":"Point"}
}
