{
  "type": "Feature",
  "properties": {
    "iso:country":"GB",
    "wof:name":"MK45 2GB",
    "wof:placetype":"postalcode"
},
  "geometry": {"coordinates":[-0.50330217760899,52.02103336589903],"type":"Point"}
}