{
  "type": "Feature",
  "properties": {
    "iso:country":"GB",
    "wof:name":"W1G 7AT",
    "wof:placetype":"postalcode"
},
  "geometry": {"coordinates":[-0.14770463590098,51.52213017605168],"type":"Point"}
}