{
  "type": "Feature",
  "properties": {
    "iso:country":"GB",
    "wof:name":"TR9 6BQ",
    "wof:placetype":"postalcode"
},
  "geometry": {"coordinates":[-4.93793371712177,50.43270671567066],"type":"Point"}
}