{
  "type": "Feature",
  "properties": {
    "iso:country": "GB",
    "wof:name": "DE7 5TE",
    "wof:placetype": "postalcode"
  },
  "geometry": {"coordinates":[-1.295678,52.977671],"type":"Point"}
}
