{
  "type": "Feature",
  "properties": {
    "iso:country": "GB",
    "wof:name": "S36 1BZ",
    "wof:placetype": "postalcode"
  },
  "geometry": {"coordinates":[-1.594704,53.477023],"type":"Point"}
}
