{
  "type": "Feature",
  "properties": {
    "iso:country":"GB",
    "wof:name":"S36 1BZ",
    "wof:placetype":"postalcode"
},
  "geometry": {"coordinates":[-1.59470398981426,53.47702286875624],"type":"Point"}
}