{
  "type": "Feature",
  "properties": {
    "iso:country":"GB",
    "wof:name":"M12 5DQ",
    "wof:placetype":"postalcode"
},
  "geometry": {"coordinates":[-2.2011782043356,53.46691507518116],"type":"Point"}
}