{
  "type": "Feature",
  "properties": {
    "date:inception_lower": "2021-11-01",
    "date:inception_upper": "2021-11-01",
    "iso:country": "GB",
    "wof:name": "PE19 5WJ",
    "wof:placetype": "postalcode"
  },
  "geometry": {"coordinates":[-0.255608,52.289057],"type":"Point"}
}
