{
  "type": "Feature",
  "properties": {
    "date:inception_lower": "1994-05-01",
    "date:inception_upper": "1994-05-01",
    "iso:country": "GB",
    "wof:name": "M21 0UT",
    "wof:placetype": "postalcode"
  },
  "geometry": {"coordinates":[-2.25981,53.443054],"type":"Point"}
}
