{
  "type": "Feature",
  "properties": {
    "iso:country":"GB",
    "wof:name":"E10 7LA",
    "wof:placetype":"postalcode"
},
  "geometry": {"coordinates":[-0.02430773542555,51.57085282851772],"type":"Point"}
}