{
  "type": "Feature",
  "properties": {
    "iso:country": "GB",
    "wof:name": "WR10 3AU",
    "wof:placetype": "postalcode"
  },
  "geometry": {"coordinates":[-2.111553,52.070467],"type":"Point"}
}
