{
  "type": "Feature",
  "properties": {
    "iso:country":"GB",
    "wof:name":"WR10 3AU",
    "wof:placetype":"postalcode"
},
  "geometry": {"coordinates":[-2.11163375220632,52.07071694054455],"type":"Point"}
}