{
  "type": "Feature",
  "properties": {
    "iso:country":"GB",
    "wof:name":"BS22 8HN",
    "wof:placetype":"postalcode"
},
  "geometry": {"coordinates":[-2.94386577420392,51.35618998988792],"type":"Point"}
}