{
  "type": "Feature",
  "properties": {
    "iso:country":"GB",
    "wof:name":"UB4 9PS",
    "wof:placetype":"postalcode"
},
  "geometry": {"coordinates":[-0.38845062241842,51.52763591890675],"type":"Point"}
}