{
  "type": "Feature",
  "properties": {
    "iso:country":"GB",
    "wof:name":"HG3 3QT",
    "wof:placetype":"postalcode"
},
  "geometry": {"coordinates":[-1.48790969608418,54.09047245597506],"type":"Point"}
}