{
  "type": "Feature",
  "properties": {
    "date:inception_lower": "1980-01-01",
    "date:inception_upper": "1980-01-01",
    "iso:country": "GB",
    "wof:name": "HG3 3QT",
    "wof:placetype": "postalcode"
  },
  "geometry": {"coordinates":[-1.497092,54.090265],"type":"Point"}
}
