{
  "type": "Feature",
  "properties": {
    "iso:country":"GB",
    "wof:name":"LA13 0QH",
    "wof:placetype":"postalcode"
},
  "geometry": {"coordinates":[-3.17471291276517,54.07410356164162],"type":"Point"}
}