{
  "type": "Feature",
  "properties": {
    "date:inception_lower": "1980-01-01",
    "date:inception_upper": "1980-01-01",
    "iso:country": "GB",
    "wof:name": "DN36 5UU",
    "wof:placetype": "postalcode"
  },
  "geometry": {"coordinates":[0.060124,53.494124],"type":"Point"}
}
