{
  "type": "Feature",
  "properties": {
    "iso:country":"GB",
    "wof:name":"DN36 5UU",
    "wof:placetype":"postalcode"
},
  "geometry": {"coordinates":[0.06012402775114,53.49412402016311],"type":"Point"}
}