{
  "type": "Feature",
  "properties": {
    "iso:country":"GB",
    "wof:name":"CW7 1BS",
    "wof:placetype":"postalcode"
},
  "geometry": {"coordinates":[-2.53240346379604,53.18799159966662],"type":"Point"}
}