{
  "type": "Feature",
  "properties": {
    "iso:country": "GB",
    "wof:name": "DY10 3AY",
    "wof:placetype": "postalcode"
  },
  "geometry": {"coordinates":[-2.22715,52.385789],"type":"Point"}
}
