{
  "type": "Feature",
  "properties": {
    "date:inception_lower": "1980-01-01",
    "date:inception_upper": "1980-01-01",
    "iso:country": "GB",
    "wof:name": "DY10 3AY",
    "wof:placetype": "postalcode"
  },
  "geometry": {"coordinates":[-2.22715,52.385789],"type":"Point"}
}
