{
  "type": "Feature",
  "properties": {
    "iso:country": "GB",
    "wof:name": "LN4 2FX",
    "wof:placetype": "postalcode"
  },
  "geometry": {"coordinates":[-0.410781,53.166822],"type":"Point"}
}
