{
  "type": "Feature",
  "properties": {
    "iso:country":"GB",
    "wof:name":"BB4 7NB",
    "wof:placetype":"postalcode"
},
  "geometry": {"coordinates":[-2.28361770724851,53.70096507870893],"type":"Point"}
}