{
  "type": "Feature",
  "properties": {
    "iso:country":"GB",
    "wof:name":"LL18 4TB",
    "wof:placetype":"postalcode"
},
  "geometry": {"coordinates":[-3.46613820658502,53.30797178563449],"type":"Point"}
}