{
  "type": "Feature",
  "properties": {
    "iso:country":"GB",
    "wof:name":"KA5 6EW",
    "wof:placetype":"postalcode"
},
  "geometry": {"coordinates":[-4.37820688799148,55.5166771947727],"type":"Point"}
}