{
  "type": "Feature",
  "properties": {
    "date:inception_lower": "2007-02-01",
    "date:inception_upper": "2007-02-01",
    "iso:country": "GB",
    "wof:name": "ST12 9JR",
    "wof:placetype": "postalcode"
  },
  "geometry": {"coordinates":[-2.202605,52.936488],"type":"Point"}
}
