{
  "type": "Feature",
  "properties": {
    "date:inception_lower":"1980-01-01",
    "date:inception_upper":"1980-01-31",
    "iso:country":"GB",
    "wof:name":"BN18 9RR",
    "wof:placetype":"postalcode"
},
  "geometry": {"coordinates":[-0.523841,50.870343],"type":"Point"}
}