{
  "type": "Feature",
  "properties": {
    "iso:country": "GB",
    "wof:name": "BN18 9RR",
    "wof:placetype": "postalcode"
  },
  "geometry": {"coordinates":[-0.523841,50.870343],"type":"Point"}
}
