{
  "type": "Feature",
  "properties": {
    "date:inception_lower": "1999-06-01",
    "date:inception_upper": "1999-06-01",
    "iso:country": "GB",
    "wof:name": "CH63 9NB",
    "wof:placetype": "postalcode"
  },
  "geometry": {"coordinates":[-2.997347,53.33356],"type":"Point"}
}
