{
  "type": "Feature",
  "properties": {
    "iso:country":"GB",
    "wof:name":"CH63 9NB",
    "wof:placetype":"postalcode"
},
  "geometry": {"coordinates":[-2.99734736144855,53.33356043574506],"type":"Point"}
}