{
  "type": "Feature",
  "properties": {
    "iso:country": "GB",
    "wof:name": "SP11 0NJ",
    "wof:placetype": "postalcode"
  },
  "geometry": {"coordinates":[-1.423922,51.26501],"type":"Point"}
}
