{
  "type": "Feature",
  "properties": {
    "iso:country":"GB",
    "wof:name":"SP11 0NJ",
    "wof:placetype":"postalcode"
},
  "geometry": {"coordinates":[-1.42392229372859,51.2650099495346],"type":"Point"}
}