{
  "type": "Feature",
  "properties": {
    "date:inception_lower": "1980-01-01",
    "date:inception_upper": "1980-01-01",
    "iso:country": "GB",
    "wof:name": "WF13 3DR",
    "wof:placetype": "postalcode"
  },
  "geometry": {"coordinates":[-1.668933,53.68294],"type":"Point"}
}
