{
  "type": "Feature",
  "properties": {
    "iso:country":"GB",
    "wof:name":"GU24 8BU",
    "wof:placetype":"postalcode"
},
  "geometry": {"coordinates":[-0.60474999358775,51.34765120691442],"type":"Point"}
}