{
  "type": "Feature",
  "properties": {
    "iso:country":"GB",
    "wof:name":"S63 6FP",
    "wof:placetype":"postalcode"
},
  "geometry": {"coordinates":[-1.35967888399301,53.50955859419922],"type":"Point"}
}