{
  "type": "Feature",
  "properties": {
    "iso:country":"GB",
    "wof:name":"L3 1EN",
    "wof:placetype":"postalcode"
},
  "geometry": {"coordinates":[-2.99381048202079,53.40358724371688],"type":"Point"}
}