{
  "type": "Feature",
  "properties": {
    "iso:country":"GB",
    "wof:name":"LL33 0RN",
    "wof:placetype":"postalcode"
},
  "geometry": {"coordinates":[-3.96947172591374,53.25896085506319],"type":"Point"}
}