{
  "type": "Feature",
  "properties": {
    "iso:country": "GB",
    "wof:name": "MK6 3NP",
    "wof:placetype": "postalcode"
  },
  "geometry": {"coordinates":[-0.733374,52.041929],"type":"Point"}
}
