{
  "type": "Feature",
  "properties": {
    "date:inception_lower": "1980-01-01",
    "date:inception_upper": "1980-01-01",
    "iso:country": "GB",
    "wof:name": "NG16 6PP",
    "wof:placetype": "postalcode"
  },
  "geometry": {"coordinates":[-1.32247,53.086193],"type":"Point"}
}
