{
  "type": "Feature",
  "properties": {
    "iso:country":"GB",
    "wof:name":"KT10 0PA",
    "wof:placetype":"postalcode"
},
  "geometry": {"coordinates":[-0.34786772520591,51.36139579764291],"type":"Point"}
}