{
  "type": "Feature",
  "properties": {
    "iso:country":"GB",
    "wof:name":"N21 3PJ",
    "wof:placetype":"postalcode"
},
  "geometry": {"coordinates":[-0.10167162484498,51.63173174484132],"type":"Point"}
}