{
  "type": "Feature",
  "properties": {
    "iso:country":"GB",
    "wof:name":"SY11 4JP",
    "wof:placetype":"postalcode"
},
  "geometry": {"coordinates":[-2.9626052957986,52.82676308833415],"type":"Point"}
}