{
  "type": "Feature",
  "properties": {
    "date:inception_lower": "1980-01-01",
    "date:inception_upper": "1980-01-01",
    "iso:country": "GB",
    "wof:name": "SY11 4JP",
    "wof:placetype": "postalcode"
  },
  "geometry": {"coordinates":[-2.962605,52.826763],"type":"Point"}
}
