{
  "type": "Feature",
  "properties": {
    "date:inception_lower": "1980-01-01",
    "date:inception_upper": "1980-01-01",
    "iso:country": "GB",
    "wof:name": "GU5 9AD",
    "wof:placetype": "postalcode"
  },
  "geometry": {"coordinates":[-0.49714,51.220722],"type":"Point"}
}
