{
  "type": "Feature",
  "properties": {
    "iso:country": "GB",
    "wof:name": "GU5 9AD",
    "wof:placetype": "postalcode"
  },
  "geometry": {"coordinates":[-0.49714,51.220722],"type":"Point"}
}
