{
  "type": "Feature",
  "properties": {
    "iso:country":"GB",
    "wof:name":"NG5 3FE",
    "wof:placetype":"postalcode"
},
  "geometry": {"coordinates":[-1.14309735457401,52.98901206138815],"type":"Point"}
}