{
  "type": "Feature",
  "properties": {
    "date:inception_lower":"1998-06-01",
    "date:inception_upper":"1998-06-30",
    "iso:country":"GB",
    "wof:name":"PO32 6UA",
    "wof:placetype":"postalcode"
},
  "geometry": {"coordinates":[-1.287195,50.761601],"type":"Point"}
}