{
  "type": "Feature",
  "properties": {
    "iso:country":"GB",
    "wof:name":"PO32 6UA",
    "wof:placetype":"postalcode"
},
  "geometry": {"coordinates":[-1.28717602219875,50.76160251807707],"type":"Point"}
}