{
  "type": "Feature",
  "properties": {
    "iso:country": "GB",
    "wof:name": "LA23 3BL",
    "wof:placetype": "postalcode"
  },
  "geometry": {"coordinates":[-2.91676,54.365893],"type":"Point"}
}
