{
  "type": "Feature",
  "properties": {
    "date:inception_lower": "2019-07-01",
    "date:inception_upper": "2019-07-01",
    "iso:country": "GB",
    "wof:name": "HP17 8FR",
    "wof:placetype": "postalcode"
  },
  "geometry": {"coordinates":[-0.92158,51.770205],"type":"Point"}
}
