{
  "type": "Feature",
  "properties": {
    "iso:country": "GB",
    "wof:name": "CV47 1FW",
    "wof:placetype": "postalcode"
  },
  "geometry": {"coordinates":[-1.379714,52.252475],"type":"Point"}
}
