{
  "type": "Feature",
  "properties": {
    "iso:country":"GB",
    "wof:name":"SG14 1EA",
    "wof:placetype":"postalcode"
},
  "geometry": {"coordinates":[-0.0789051115482,51.79657700002285],"type":"Point"}
}