{
  "type": "Feature",
  "properties": {
    "date:inception_lower": "1980-01-01",
    "date:inception_upper": "1980-01-01",
    "iso:country": "GB",
    "wof:name": "SG14 1EA",
    "wof:placetype": "postalcode"
  },
  "geometry": {"coordinates":[-0.078905,51.796577],"type":"Point"}
}
