{
  "type": "Feature",
  "properties": {
    "date:inception_lower": "1980-01-01",
    "date:inception_upper": "1980-01-01",
    "iso:country": "GB",
    "wof:name": "LA8 9HR",
    "wof:placetype": "postalcode"
  },
  "geometry": {"coordinates":[-2.829038,54.350225],"type":"Point"}
}
