{
  "type": "Feature",
  "properties": {
    "iso:country":"GB",
    "wof:name":"LA8 9HR",
    "wof:placetype":"postalcode"
},
  "geometry": {"coordinates":[-2.82966638322545,54.35018466900795],"type":"Point"}
}