{
  "type": "Feature",
  "properties": {
    "iso:country": "GB",
    "wof:name": "LA8 9HR",
    "wof:placetype": "postalcode"
  },
  "geometry": {"coordinates":[-2.829666,54.350185],"type":"Point"}
}
