{
  "type": "Feature",
  "properties": {
    "iso:country":"GB",
    "wof:name":"WN4 8DU",
    "wof:placetype":"postalcode"
},
  "geometry": {"coordinates":[-2.63788372923081,53.50199145681769],"type":"Point"}
}