{
  "type": "Feature",
  "properties": {
    "iso:country": "GB",
    "wof:name": "WN4 8DU",
    "wof:placetype": "postalcode"
  },
  "geometry": {"coordinates":[-2.637884,53.501991],"type":"Point"}
}
