{
  "type": "Feature",
  "properties": {
    "date:inception_lower": "1990-08-01",
    "date:inception_upper": "1990-08-01",
    "iso:country": "GB",
    "wof:name": "AB54 4XX",
    "wof:placetype": "postalcode"
  },
  "geometry": {"coordinates":[-2.962543,57.440091],"type":"Point"}
}
