{
  "type": "Feature",
  "properties": {
    "iso:country": "GB",
    "wof:name": "GL54 1HP",
    "wof:placetype": "postalcode"
  },
  "geometry": {"coordinates":[-1.715411,51.923735],"type":"Point"}
}
