{
  "type": "Feature",
  "properties": {
    "iso:country":"GB",
    "wof:name":"GL54 1HP",
    "wof:placetype":"postalcode"
},
  "geometry": {"coordinates":[-1.71525911207572,51.92413869285996],"type":"Point"}
}