{
  "type": "Feature",
  "properties": {
    "iso:country": "GB",
    "wof:name": "EX1 3AT",
    "wof:placetype": "postalcode"
  },
  "geometry": {"coordinates":[-3.496995,50.723959],"type":"Point"}
}
