{
  "type": "Feature",
  "properties": {
    "iso:country":"GB",
    "wof:name":"EX1 3AT",
    "wof:placetype":"postalcode"
},
  "geometry": {"coordinates":[-3.49699511843073,50.723959302873],"type":"Point"}
}