{
  "type": "Feature",
  "properties": {
    "iso:country":"GB",
    "wof:name":"B32 4AN",
    "wof:placetype":"postalcode"
},
  "geometry": {"coordinates":[-2.01370852589529,52.4335191191897],"type":"Point"}
}