{
  "type": "Feature",
  "properties": {
    "iso:country": "GB",
    "wof:name": "KA8 9BJ",
    "wof:placetype": "postalcode"
  },
  "geometry": {"coordinates":[-4.618684,55.4778],"type":"Point"}
}
