{
  "type": "Feature",
  "properties": {
    "date:inception_lower":"1993-01-01",
    "date:inception_upper":"1993-01-31",
    "iso:country":"GB",
    "wof:name":"NG21 9RG",
    "wof:placetype":"postalcode"
},
  "geometry": {"coordinates":[-1.063854,53.196419],"type":"Point"}
}