{
  "type": "Feature",
  "properties": {
    "date:inception_lower": "1991-09-01",
    "date:inception_upper": "1991-09-01",
    "iso:country": "GB",
    "wof:name": "PO38 3DL",
    "wof:placetype": "postalcode"
  },
  "geometry": {"coordinates":[-1.225299,50.619004],"type":"Point"}
}
