{
  "type": "Feature",
  "properties": {
    "iso:country":"GB",
    "wof:name":"PO38 3DL",
    "wof:placetype":"postalcode"
},
  "geometry": {"coordinates":[-1.22529891227349,50.61900366442144],"type":"Point"}
}