{
  "type": "Feature",
  "properties": {
    "date:inception_lower":"2014-11-01",
    "date:inception_upper":"2014-11-30",
    "iso:country":"GB",
    "wof:name":"NG14 6RS",
    "wof:placetype":"postalcode"
},
  "geometry": {"coordinates":[-1.099841,53.042503],"type":"Point"}
}