{
  "type": "Feature",
  "properties": {
    "iso:country":"GB",
    "wof:name":"SO21 3QQ",
    "wof:placetype":"postalcode"
},
  "geometry": {"coordinates":[-1.34696261760488,51.17743750102944],"type":"Point"}
}