{
  "type": "Feature",
  "properties": {
    "iso:country":"GB",
    "wof:name":"HD2 2RE",
    "wof:placetype":"postalcode"
},
  "geometry": {"coordinates":[-1.78296464866882,53.66343596578577],"type":"Point"}
}