{
  "type": "Feature",
  "properties": {
    "iso:country": "GB",
    "wof:name": "WS2 8BG",
    "wof:placetype": "postalcode"
  },
  "geometry": {"coordinates":[-1.98983,52.595185],"type":"Point"}
}
