{
  "type": "Feature",
  "properties": {
    "date:inception_lower":"2007-04-01",
    "date:inception_upper":"2007-04-30",
    "iso:country":"GB",
    "wof:name":"WS2 8BG",
    "wof:placetype":"postalcode"
},
  "geometry": {"coordinates":[-1.98983,52.595185],"type":"Point"}
}