{
  "type": "Feature",
  "properties": {
    "iso:country": "GB",
    "wof:name": "SL1 3DW",
    "wof:placetype": "postalcode"
  },
  "geometry": {"coordinates":[-0.608643,51.518557],"type":"Point"}
}
