{
  "type": "Feature",
  "properties": {
    "iso:country":"GB",
    "wof:name":"SL1 3DW",
    "wof:placetype":"postalcode"
},
  "geometry": {"coordinates":[-0.60864323188103,51.51855743823624],"type":"Point"}
}