{
  "type": "Feature",
  "properties": {
    "date:inception_lower": "2013-07-01",
    "date:inception_upper": "2013-07-01",
    "iso:country": "GB",
    "wof:name": "CW9 7FE",
    "wof:placetype": "postalcode"
  },
  "geometry": {"coordinates":[-2.458287,53.27025],"type":"Point"}
}
