{
  "type": "Feature",
  "properties": {
    "date:inception_lower": "1991-01-01",
    "date:inception_upper": "1991-01-01",
    "iso:country": "GB",
    "wof:name": "WA10 4EY",
    "wof:placetype": "postalcode"
  },
  "geometry": {"coordinates":[-2.765232,53.455959],"type":"Point"}
}
