{
  "type": "Feature",
  "properties": {
    "iso:country":"GB",
    "wof:name":"BL1 3PW",
    "wof:placetype":"postalcode"
},
  "geometry": {"coordinates":[-2.44189988722783,53.59219486353793],"type":"Point"}
}