{
  "type": "Feature",
  "properties": {
    "iso:country": "GB",
    "wof:name": "EH33 1BT",
    "wof:placetype": "postalcode"
  },
  "geometry": {"coordinates":[-2.954611,55.948151],"type":"Point"}
}
