{
  "type": "Feature",
  "properties": {
    "iso:country":"GB",
    "wof:name":"EH33 1BT",
    "wof:placetype":"postalcode"
},
  "geometry": {"coordinates":[-2.95461146061694,55.94815125719354],"type":"Point"}
}