{
  "type": "Feature",
  "properties": {
    "iso:country":"GB",
    "wof:name":"CV21 2TQ",
    "wof:placetype":"postalcode"
},
  "geometry": {"coordinates":[-1.25902169175433,52.37722269175427],"type":"Point"}
}