{
  "type": "Feature",
  "properties": {
    "iso:country": "GB",
    "wof:name": "CV10 8LA",
    "wof:placetype": "postalcode"
  },
  "geometry": {"coordinates":[-1.512446,52.516762],"type":"Point"}
}
