{
  "type": "Feature",
  "properties": {
    "iso:country":"GB",
    "wof:name":"CV10 8LA",
    "wof:placetype":"postalcode"
},
  "geometry": {"coordinates":[-1.51244582226847,52.51676178544141],"type":"Point"}
}