{
  "type": "Feature",
  "properties": {
    "date:inception_lower": "1984-02-01",
    "date:inception_upper": "1984-02-01",
    "iso:country": "GB",
    "wof:name": "DY5 3NS",
    "wof:placetype": "postalcode"
  },
  "geometry": {"coordinates":[-2.136474,52.466431],"type":"Point"}
}
