{
  "type": "Feature",
  "properties": {
    "iso:country":"GB",
    "wof:name":"TS26 0LZ",
    "wof:placetype":"postalcode"
},
  "geometry": {"coordinates":[-1.23696233718225,54.68827423095244],"type":"Point"}
}