{
  "type": "Feature",
  "properties": {
    "iso:country":"GB",
    "wof:name":"BH22 0DU",
    "wof:placetype":"postalcode"
},
  "geometry": {"coordinates":[-1.87020291415691,50.81295055209272],"type":"Point"}
}