{
  "type": "Feature",
  "properties": {
    "date:inception_lower": "2004-11-01",
    "date:inception_upper": "2004-11-01",
    "iso:country": "GB",
    "wof:name": "BH22 0DU",
    "wof:placetype": "postalcode"
  },
  "geometry": {"coordinates":[-1.870203,50.812951],"type":"Point"}
}
