{
  "type": "Feature",
  "properties": {
    "date:inception_lower": "1980-01-01",
    "date:inception_upper": "1980-01-01",
    "iso:country": "GB",
    "wof:name": "N17 9EX",
    "wof:placetype": "postalcode"
  },
  "geometry": {"coordinates":[-0.064084,51.59016],"type":"Point"}
}
