{
  "type": "Feature",
  "properties": {
    "iso:country":"GB",
    "wof:name":"SR4 0RS",
    "wof:placetype":"postalcode"
},
  "geometry": {"coordinates":[-1.442329763237,54.90892631819877],"type":"Point"}
}