{
  "type": "Feature",
  "properties": {
    "iso:country":"GB",
    "wof:name":"W4 5AD",
    "wof:placetype":"postalcode"
},
  "geometry": {"coordinates":[-0.2655278734678,51.49981400232667],"type":"Point"}
}