{
  "type": "Feature",
  "properties": {
    "iso:country": "GB",
    "wof:name": "W4 5AD",
    "wof:placetype": "postalcode"
  },
  "geometry": {"coordinates":[-0.265528,51.499814],"type":"Point"}
}
