{
  "type": "Feature",
  "properties": {
    "iso:country": "GB",
    "wof:name": "LS12 6LJ",
    "wof:placetype": "postalcode"
  },
  "geometry": {"coordinates":[-1.603417,53.778375],"type":"Point"}
}
