{
  "type": "Feature",
  "properties": {
    "iso:country":"GB",
    "wof:name":"LS12 6LJ",
    "wof:placetype":"postalcode"
},
  "geometry": {"coordinates":[-1.60341679360872,53.77837503788767],"type":"Point"}
}