{
  "type": "Feature",
  "properties": {
    "iso:country":"GB",
    "wof:name":"W11 4HB",
    "wof:placetype":"postalcode"
},
  "geometry": {"coordinates":[-0.21405482264094,51.512943769939],"type":"Point"}
}