{
  "type": "Feature",
  "properties": {
    "iso:country": "GB",
    "wof:name": "W11 4HB",
    "wof:placetype": "postalcode"
  },
  "geometry": {"coordinates":[-0.214055,51.512944],"type":"Point"}
}
