{
  "type": "Feature",
  "properties": {
    "iso:country": "GB",
    "wof:name": "KY12 9JH",
    "wof:placetype": "postalcode"
  },
  "geometry": {"coordinates":[-3.541803,56.084209],"type":"Point"}
}
