{
  "type": "Feature",
  "properties": {
    "iso:country":"GB",
    "wof:name":"KY12 9JH",
    "wof:placetype":"postalcode"
},
  "geometry": {"coordinates":[-3.54144166173239,56.08428177485545],"type":"Point"}
}