{
  "type": "Feature",
  "properties": {
    "iso:country": "GB",
    "wof:name": "BH24 2FU",
    "wof:placetype": "postalcode"
  },
  "geometry": {"coordinates":[-1.815461,50.817453],"type":"Point"}
}
