{
  "type": "Feature",
  "properties": {
    "date:inception_lower": "2020-02-01",
    "date:inception_upper": "2020-02-01",
    "iso:country": "GB",
    "wof:name": "BH24 2FU",
    "wof:placetype": "postalcode"
  },
  "geometry": {"coordinates":[-1.81604,50.818291],"type":"Point"}
}
