{
  "type": "Feature",
  "properties": {
    "iso:country": "GB",
    "wof:name": "NE4 7RR",
    "wof:placetype": "postalcode"
  },
  "geometry": {"coordinates":[-1.647438,54.967054],"type":"Point"}
}
