{
  "type": "Feature",
  "properties": {
    "iso:country":"GB",
    "wof:name":"NE4 7RR",
    "wof:placetype":"postalcode"
},
  "geometry": {"coordinates":[-1.64743833071133,54.96705354196521],"type":"Point"}
}