{
  "type": "Feature",
  "properties": {
    "iso:country":"GB",
    "wof:name":"TR1 3RL",
    "wof:placetype":"postalcode"
},
  "geometry": {"coordinates":[-5.05857451741499,50.26833063724102],"type":"Point"}
}