{
  "type": "Feature",
  "properties": {
    "iso:country": "GB",
    "wof:name": "HG3 1SP",
    "wof:placetype": "postalcode"
  },
  "geometry": {"coordinates":[-1.703026,53.997167],"type":"Point"}
}
