{
  "type": "Feature",
  "properties": {
    "iso:country":"GB",
    "wof:name":"IV7 8JF",
    "wof:placetype":"postalcode"
},
  "geometry": {"coordinates":[-4.34295560407142,57.59910739752801],"type":"Point"}
}