{
  "type": "Feature",
  "properties": {
    "date:inception_lower": "1997-06-01",
    "date:inception_upper": "1997-06-01",
    "iso:country": "GB",
    "wof:name": "IV7 8JF",
    "wof:placetype": "postalcode"
  },
  "geometry": {"coordinates":[-4.342956,57.599107],"type":"Point"}
}
