{
  "type": "Feature",
  "properties": {
    "iso:country": "GB",
    "wof:name": "CO10 0YQ",
    "wof:placetype": "postalcode"
  },
  "geometry": {"coordinates":[0.755385,52.027151],"type":"Point"}
}
