{
  "type": "Feature",
  "properties": {
    "iso:country":"GB",
    "wof:name":"B7 4HW",
    "wof:placetype":"postalcode"
},
  "geometry": {"coordinates":[-1.8765540652868,52.48507634354428],"type":"Point"}
}