{
  "type": "Feature",
  "properties": {
    "iso:country":"GB",
    "wof:name":"CR5 3PQ",
    "wof:placetype":"postalcode"
},
  "geometry": {"coordinates":[-0.16850121616578,51.30345061955395],"type":"Point"}
}