{
  "type": "Feature",
  "properties": {
    "iso:country": "GB",
    "wof:name": "BL7 0EZ",
    "wof:placetype": "postalcode"
  },
  "geometry": {"coordinates":[-2.40531,53.638075],"type":"Point"}
}
