{
  "type": "Feature",
  "properties": {
    "iso:country":"GB",
    "wof:name":"BL7 0EZ",
    "wof:placetype":"postalcode"
},
  "geometry": {"coordinates":[-2.40530956481792,53.63807491085512],"type":"Point"}
}