{
  "type": "Feature",
  "properties": {
    "date:inception_lower": "1980-01-01",
    "date:inception_upper": "1980-01-01",
    "iso:country": "GB",
    "wof:name": "LL18 6DH",
    "wof:placetype": "postalcode"
  },
  "geometry": {"coordinates":[-3.370611,53.307121],"type":"Point"}
}
