{
  "type": "Feature",
  "properties": {
    "iso:country":"GB",
    "wof:name":"LL18 6DH",
    "wof:placetype":"postalcode"
},
  "geometry": {"coordinates":[-3.37061057401818,53.30712131377947],"type":"Point"}
}