{
  "type": "Feature",
  "properties": {
    "iso:country":"GB",
    "wof:name":"WS2 7ES",
    "wof:placetype":"postalcode"
},
  "geometry": {"coordinates":[-2.00299837214239,52.60149618999131],"type":"Point"}
}