{
  "type": "Feature",
  "properties": {
    "iso:country":"GB",
    "wof:name":"B38 8RY",
    "wof:placetype":"postalcode"
},
  "geometry": {"coordinates":[-1.93141014408199,52.40740209074262],"type":"Point"}
}