{
  "type": "Feature",
  "properties": {
    "iso:country": "GB",
    "wof:name": "DE15 0UA",
    "wof:placetype": "postalcode"
  },
  "geometry": {"coordinates":[-1.555148,52.799909],"type":"Point"}
}
