{
  "type": "Feature",
  "properties": {
    "date:inception_lower":"2001-12-01",
    "date:inception_upper":"2001-12-31",
    "iso:country":"GB",
    "wof:name":"DE15 0UA",
    "wof:placetype":"postalcode"
},
  "geometry": {"coordinates":[-1.555148,52.799909],"type":"Point"}
}