{
  "type": "Feature",
  "properties": {
    "iso:country":"GB",
    "wof:name":"CT19 5TR",
    "wof:placetype":"postalcode"
},
  "geometry": {"coordinates":[1.16173063401253,51.08983315350022],"type":"Point"}
}