{
  "type": "Feature",
  "properties": {
    "iso:country": "GB",
    "wof:name": "GL19 4AN",
    "wof:placetype": "postalcode"
  },
  "geometry": {"coordinates":[-2.170842,51.936288],"type":"Point"}
}
