{
  "type": "Feature",
  "properties": {
    "iso:country":"GB",
    "wof:name":"GL19 4AN",
    "wof:placetype":"postalcode"
},
  "geometry": {"coordinates":[-2.17115374239948,51.9363153890807],"type":"Point"}
}