{
  "type": "Feature",
  "properties": {
    "iso:country":"GB",
    "wof:name":"DD3 8AW",
    "wof:placetype":"postalcode"
},
  "geometry": {"coordinates":[-2.97995984900745,56.47575033286792],"type":"Point"}
}