{
  "type": "Feature",
  "properties": {
    "iso:country": "GB",
    "wof:name": "DD3 8AW",
    "wof:placetype": "postalcode"
  },
  "geometry": {"coordinates":[-2.97996,56.47575],"type":"Point"}
}
