{
  "type": "Feature",
  "properties": {
    "iso:country":"GB",
    "wof:name":"B20 2LJ",
    "wof:placetype":"postalcode"
},
  "geometry": {"coordinates":[-1.92256787740268,52.52119186716764],"type":"Point"}
}