{
  "type": "Feature",
  "properties": {
    "iso:country":"GB",
    "wof:name":"TF5 0BH",
    "wof:placetype":"postalcode"
},
  "geometry": {"coordinates":[-2.54273621770028,52.71074521255126],"type":"Point"}
}