{
  "type": "Feature",
  "properties": {
    "iso:country": "GB",
    "wof:name": "TF5 0BH",
    "wof:placetype": "postalcode"
  },
  "geometry": {"coordinates":[-2.542736,52.710745],"type":"Point"}
}
