{
  "type": "Feature",
  "properties": {
    "iso:country":"GB",
    "wof:name":"BH24 3PY",
    "wof:placetype":"postalcode"
},
  "geometry": {"coordinates":[-1.80471874607489,50.89327918469129],"type":"Point"}
}