{
  "type": "Feature",
  "properties": {
    "date:inception_lower":"1980-01-01",
    "date:inception_upper":"1980-01-31",
    "iso:country":"GB",
    "wof:name":"NR12 7DR",
    "wof:placetype":"postalcode"
},
  "geometry": {"coordinates":[1.364923,52.728951],"type":"Point"}
}