{
  "type": "Feature",
  "properties": {
    "iso:country": "GB",
    "wof:name": "DE24 3LN",
    "wof:placetype": "postalcode"
  },
  "geometry": {"coordinates":[-1.501861,52.8761],"type":"Point"}
}
