{
  "type": "Feature",
  "properties": {
    "date:inception_lower": "1993-01-01",
    "date:inception_upper": "1993-01-01",
    "iso:country": "GB",
    "wof:name": "DE24 3LN",
    "wof:placetype": "postalcode"
  },
  "geometry": {"coordinates":[-1.501861,52.8761],"type":"Point"}
}
