{
  "type": "Feature",
  "properties": {
    "date:inception_lower": "1980-01-01",
    "date:inception_upper": "1980-01-01",
    "iso:country": "GB",
    "wof:name": "B30 2NW",
    "wof:placetype": "postalcode"
  },
  "geometry": {"coordinates":[-1.921399,52.424243],"type":"Point"}
}
