{
  "type": "Feature",
  "properties": {
    "iso:country":"GB",
    "wof:name":"TQ9 7BJ",
    "wof:placetype":"postalcode"
},
  "geometry": {"coordinates":[-3.67842415798887,50.34696329122533],"type":"Point"}
}