{
  "type": "Feature",
  "properties": {
    "date:inception_lower": "1980-01-01",
    "date:inception_upper": "1980-01-01",
    "iso:country": "GB",
    "wof:name": "TQ9 7BJ",
    "wof:placetype": "postalcode"
  },
  "geometry": {"coordinates":[-3.678317,50.346958],"type":"Point"}
}
