{
  "type": "Feature",
  "properties": {
    "iso:country":"GB",
    "wof:name":"IP3 0HQ",
    "wof:placetype":"postalcode"
},
  "geometry": {"coordinates":[1.17526438421772,52.03681166767244],"type":"Point"}
}