{
  "type": "Feature",
  "properties": {
    "iso:country": "GB",
    "wof:name": "KY10 3HA",
    "wof:placetype": "postalcode"
  },
  "geometry": {"coordinates":[-2.703896,56.223588],"type":"Point"}
}
