{
  "type": "Feature",
  "properties": {
    "iso:country":"GB",
    "wof:name":"B23 6JJ",
    "wof:placetype":"postalcode"
},
  "geometry": {"coordinates":[-1.85687668842101,52.52711808142193],"type":"Point"}
}