{
  "type": "Feature",
  "properties": {
    "iso:country": "GB",
    "wof:name": "TF10 9ER",
    "wof:placetype": "postalcode"
  },
  "geometry": {"coordinates":[-2.39605,52.744983],"type":"Point"}
}
