{
  "type": "Feature",
  "properties": {
    "iso:country":"GB",
    "wof:name":"TF10 9ER",
    "wof:placetype":"postalcode"
},
  "geometry": {"coordinates":[-2.39604996825108,52.74498340343296],"type":"Point"}
}