{
  "type": "Feature",
  "properties": {
    "iso:country":"GB",
    "wof:name":"SN14 8FA",
    "wof:placetype":"postalcode"
},
  "geometry": {"coordinates":[-2.21900770601909,51.47217502948453],"type":"Point"}
}