{
  "type": "Feature",
  "properties": {
    "date:inception_lower": "2020-06-01",
    "date:inception_upper": "2020-06-01",
    "iso:country": "GB",
    "wof:name": "SN14 8FA",
    "wof:placetype": "postalcode"
  },
  "geometry": {"coordinates":[-2.219004,51.472174],"type":"Point"}
}
