{
  "type": "Feature",
  "properties": {
    "date:inception_lower": "1980-01-01",
    "date:inception_upper": "1980-01-01",
    "iso:country": "GB",
    "wof:name": "HU17 7QB",
    "wof:placetype": "postalcode"
  },
  "geometry": {"coordinates":[-0.53139,53.87182],"type":"Point"}
}
