{
  "type": "Feature",
  "properties": {
    "iso:country": "GB",
    "wof:name": "HU17 7QB",
    "wof:placetype": "postalcode"
  },
  "geometry": {"coordinates":[-0.53136,53.872673],"type":"Point"}
}
