{
  "type": "Feature",
  "properties": {
    "iso:country": "GB",
    "wof:name": "S1 1LL",
    "wof:placetype": "postalcode"
  },
  "geometry": {"coordinates":[-1.469607,53.380957],"type":"Point"}
}
