{
  "type": "Feature",
  "properties": {
    "iso:country":"GB",
    "wof:name":"S1 1LL",
    "wof:placetype":"postalcode"
},
  "geometry": {"coordinates":[-1.46963863202031,53.38091258206283],"type":"Point"}
}