{
  "type": "Feature",
  "properties": {
    "date:inception_lower":"2015-07-01",
    "date:inception_upper":"2015-07-31",
    "iso:country":"GB",
    "wof:name":"PE7 0ND",
    "wof:placetype":"postalcode"
},
  "geometry": {"coordinates":[-0.246032,52.553466],"type":"Point"}
}