{
  "type": "Feature",
  "properties": {
    "iso:country":"GB",
    "wof:name":"PE7 0ND",
    "wof:placetype":"postalcode"
},
  "geometry": {"coordinates":[-0.2474613649146,52.553126550803],"type":"Point"}
}