{
  "type": "Feature",
  "properties": {
    "iso:country":"GB",
    "wof:name":"ST4 8TT",
    "wof:placetype":"postalcode"
},
  "geometry": {"coordinates":[-2.1798383412684,52.95748783974194],"type":"Point"}
}