{
  "type": "Feature",
  "properties": {
    "date:inception_lower": "1980-01-01",
    "date:inception_upper": "1980-01-01",
    "iso:country": "GB",
    "wof:name": "ST4 8TT",
    "wof:placetype": "postalcode"
  },
  "geometry": {"coordinates":[-2.179838,52.957488],"type":"Point"}
}
