{
  "type": "Feature",
  "properties": {
    "date:inception_lower": "1980-01-01",
    "date:inception_upper": "1980-01-01",
    "iso:country": "GB",
    "wof:name": "BB12 0BP",
    "wof:placetype": "postalcode"
  },
  "geometry": {"coordinates":[-2.250209,53.796169],"type":"Point"}
}
