{
  "type": "Feature",
  "properties": {
    "iso:country":"GB",
    "wof:name":"WF4 1TE",
    "wof:placetype":"postalcode"
},
  "geometry": {"coordinates":[-1.41963764705331,53.65256469346971],"type":"Point"}
}