{
  "type": "Feature",
  "properties": {
    "iso:country": "GB",
    "wof:name": "CO7 6HA",
    "wof:placetype": "postalcode"
  },
  "geometry": {"coordinates":[0.991537,51.958697],"type":"Point"}
}
