{
  "type": "Feature",
  "properties": {
    "iso:country":"GB",
    "wof:name":"CO7 6HA",
    "wof:placetype":"postalcode"
},
  "geometry": {"coordinates":[0.99147350528733,51.95863148154105],"type":"Point"}
}