{
  "type": "Feature",
  "properties": {
    "date:inception_lower": "1980-01-01",
    "date:inception_upper": "1980-01-01",
    "iso:country": "GB",
    "wof:name": "ST7 3NA",
    "wof:placetype": "postalcode"
  },
  "geometry": {"coordinates":[-2.216088,53.110008],"type":"Point"}
}
