{
  "type": "Feature",
  "properties": {
    "iso:country": "GB",
    "wof:name": "CV34 6XE",
    "wof:placetype": "postalcode"
  },
  "geometry": {"coordinates":[-1.547542,52.268913],"type":"Point"}
}
