{
  "type": "Feature",
  "properties": {
    "iso:country":"GB",
    "wof:name":"PE24 5HT",
    "wof:placetype":"postalcode"
},
  "geometry": {"coordinates":[0.2275945567431,53.18242716778826],"type":"Point"}
}