{
  "type": "Feature",
  "properties": {
    "iso:country": "GB",
    "wof:name": "PE24 5HT",
    "wof:placetype": "postalcode"
  },
  "geometry": {"coordinates":[0.227597,53.182454],"type":"Point"}
}
