{
  "type": "Feature",
  "properties": {
    "iso:country":"GB",
    "wof:name":"DN34 5DR",
    "wof:placetype":"postalcode"
},
  "geometry": {"coordinates":[-0.10314210411927,53.55226715545913],"type":"Point"}
}