{
  "type": "Feature",
  "properties": {
    "date:inception_lower": "1986-07-01",
    "date:inception_upper": "1986-07-01",
    "iso:country": "GB",
    "wof:name": "PL14 5RZ",
    "wof:placetype": "postalcode"
  },
  "geometry": {"coordinates":[-4.472095,50.488167],"type":"Point"}
}
