{
  "type": "Feature",
  "properties": {
    "iso:country":"GB",
    "wof:name":"PL14 5RZ",
    "wof:placetype":"postalcode"
},
  "geometry": {"coordinates":[-4.47209531339414,50.48816670924536],"type":"Point"}
}