{
  "type": "Feature",
  "properties": {
    "date:inception_lower": "1980-01-01",
    "date:inception_upper": "1980-01-01",
    "iso:country": "GB",
    "wof:name": "DH9 0RG",
    "wof:placetype": "postalcode"
  },
  "geometry": {"coordinates":[-1.658469,54.881805],"type":"Point"}
}
