{
  "type": "Feature",
  "properties": {
    "iso:country": "GB",
    "wof:name": "SY1 1XB",
    "wof:placetype": "postalcode"
  },
  "geometry": {"coordinates":[-2.750301,52.706409],"type":"Point"}
}
