{
  "type": "Feature",
  "properties": {
    "iso:country":"GB",
    "wof:name":"NN11 3QU",
    "wof:placetype":"postalcode"
},
  "geometry": {"coordinates":[-1.22517229063328,52.18151691697022],"type":"Point"}
}