{
  "type": "Feature",
  "properties": {
    "iso:country": "GB",
    "wof:name": "S12 4WA",
    "wof:placetype": "postalcode"
  },
  "geometry": {"coordinates":[-1.408351,53.352472],"type":"Point"}
}
