{
  "type": "Feature",
  "properties": {
    "iso:country":"GB",
    "wof:name":"S12 4WA",
    "wof:placetype":"postalcode"
},
  "geometry": {"coordinates":[-1.40835126891022,53.35247197480593],"type":"Point"}
}