{
  "type": "Feature",
  "properties": {
    "iso:country": "GB",
    "wof:name": "W1U 1LP",
    "wof:placetype": "postalcode"
  },
  "geometry": {"coordinates":[-0.151464,51.514735],"type":"Point"}
}
