{
  "type": "Feature",
  "properties": {
    "iso:country":"GB",
    "wof:name":"W1U 1LP",
    "wof:placetype":"postalcode"
},
  "geometry": {"coordinates":[-0.1514636561612,51.51473470452287],"type":"Point"}
}