{
  "type": "Feature",
  "properties": {
    "date:inception_lower":"2003-09-01",
    "date:inception_upper":"2003-09-30",
    "iso:country":"GB",
    "wof:name":"BN2 3RY",
    "wof:placetype":"postalcode"
},
  "geometry": {"coordinates":[-0.132905,50.835686],"type":"Point"}
}