{
  "type": "Feature",
  "properties": {
    "iso:country": "GB",
    "wof:name": "IV15 9PY",
    "wof:placetype": "postalcode"
  },
  "geometry": {"coordinates":[-4.437953,57.596582],"type":"Point"}
}
