{
  "type": "Feature",
  "properties": {
    "iso:country":"GB",
    "wof:name":"IV15 9PY",
    "wof:placetype":"postalcode"
},
  "geometry": {"coordinates":[-4.4379528653513,57.59658167948734],"type":"Point"}
}