{
  "type": "Feature",
  "properties": {
    "iso:country": "GB",
    "wof:name": "SL1 5DJ",
    "wof:placetype": "postalcode"
  },
  "geometry": {"coordinates":[-0.635358,51.513008],"type":"Point"}
}
