{
  "type": "Feature",
  "properties": {
    "iso:country":"GB",
    "wof:name":"SL1 5DJ",
    "wof:placetype":"postalcode"
},
  "geometry": {"coordinates":[-0.63535769663711,51.51300843023228],"type":"Point"}
}