{
  "type": "Feature",
  "properties": {
    "iso:country":"GB",
    "wof:name":"B93 8PA",
    "wof:placetype":"postalcode"
},
  "geometry": {"coordinates":[-1.74966975581525,52.37971057785906],"type":"Point"}
}