{
  "type": "Feature",
  "properties": {
    "date:inception_lower":"1980-01-01",
    "date:inception_upper":"1980-01-31",
    "iso:country":"GB",
    "wof:name":"B93 8PA",
    "wof:placetype":"postalcode"
},
  "geometry": {"coordinates":[-1.74967,52.379711],"type":"Point"}
}