{
  "type": "Feature",
  "properties": {
    "iso:country":"GB",
    "wof:name":"WF14 0LB",
    "wof:placetype":"postalcode"
},
  "geometry": {"coordinates":[-1.69480068932804,53.69021743981553],"type":"Point"}
}