{
  "type": "Feature",
  "properties": {
    "iso:country":"GB",
    "wof:name":"E4 7PP",
    "wof:placetype":"postalcode"
},
  "geometry": {"coordinates":[-0.01047247193845,51.63452903640454],"type":"Point"}
}