{
  "type": "Feature",
  "properties": {
    "date:inception_lower": "1980-01-01",
    "date:inception_upper": "1980-01-01",
    "iso:country": "GB",
    "wof:name": "E4 7PP",
    "wof:placetype": "postalcode"
  },
  "geometry": {"coordinates":[-0.010472,51.634529],"type":"Point"}
}
