{
  "type": "Feature",
  "properties": {
    "iso:country":"GB",
    "wof:name":"RH11 0PW",
    "wof:placetype":"postalcode"
},
  "geometry": {"coordinates":[-0.17934462510393,51.14526438164597],"type":"Point"}
}