{
  "type": "Feature",
  "properties": {
    "iso:country":"GB",
    "wof:name":"G81 3HS",
    "wof:placetype":"postalcode"
},
  "geometry": {"coordinates":[-4.4070616255547,55.91527895899514],"type":"Point"}
}