{
  "type": "Feature",
  "properties": {
    "iso:country": "GB",
    "wof:name": "LA14 5NS",
    "wof:placetype": "postalcode"
  },
  "geometry": {"coordinates":[-3.222595,54.12449],"type":"Point"}
}
