{
  "type": "Feature",
  "properties": {
    "iso:country":"GB",
    "wof:name":"LS26 0HN",
    "wof:placetype":"postalcode"
},
  "geometry": {"coordinates":[-1.47291609190667,53.75268797318321],"type":"Point"}
}