{
  "type": "Feature",
  "properties": {
    "iso:country": "GB",
    "wof:name": "LS26 0HN",
    "wof:placetype": "postalcode"
  },
  "geometry": {"coordinates":[-1.472916,53.752688],"type":"Point"}
}
