{
  "type": "Feature",
  "properties": {
    "date:inception_lower": "2011-11-01",
    "date:inception_upper": "2011-11-01",
    "iso:country": "GB",
    "wof:name": "SE5 0SG",
    "wof:placetype": "postalcode"
  },
  "geometry": {"coordinates":[-0.09531,51.480573],"type":"Point"}
}
