{
  "type": "Feature",
  "properties": {
    "iso:country":"GB",
    "wof:name":"SE5 0SG",
    "wof:placetype":"postalcode"
},
  "geometry": {"coordinates":[-0.09531028229648,51.48057269506405],"type":"Point"}
}