{
  "type": "Feature",
  "properties": {
    "iso:country":"GB",
    "wof:name":"BB11 5BY",
    "wof:placetype":"postalcode"
},
  "geometry": {"coordinates":[-2.27109655601792,53.77945996588643],"type":"Point"}
}