{
  "type": "Feature",
  "properties": {
    "iso:country":"GB",
    "wof:name":"LL19 7NQ",
    "wof:placetype":"postalcode"
},
  "geometry": {"coordinates":[-3.41129751015526,53.33939531596144],"type":"Point"}
}