{
  "type": "Feature",
  "properties": {
    "iso:country":"GB",
    "wof:name":"BS6 5ND",
    "wof:placetype":"postalcode"
},
  "geometry": {"coordinates":[-2.58407979565281,51.46617659694895],"type":"Point"}
}