{
  "type": "Feature",
  "properties": {
    "date:inception_lower": "1980-01-01",
    "date:inception_upper": "1980-01-01",
    "iso:country": "GB",
    "wof:name": "BS6 5ND",
    "wof:placetype": "postalcode"
  },
  "geometry": {"coordinates":[-2.58408,51.466177],"type":"Point"}
}
