{
  "type": "Feature",
  "properties": {
    "iso:country":"GB",
    "wof:name":"EN4 0BG",
    "wof:placetype":"postalcode"
},
  "geometry": {"coordinates":[-0.14471063659758,51.64605213825535],"type":"Point"}
}