{
  "type": "Feature",
  "properties": {
    "iso:country":"GB",
    "wof:name":"CM4 9DP",
    "wof:placetype":"postalcode"
},
  "geometry": {"coordinates":[0.44770699900385,51.67778623020475],"type":"Point"}
}