{
  "type": "Feature",
  "properties": {
    "iso:country": "GB",
    "wof:name": "CM4 9DP",
    "wof:placetype": "postalcode"
  },
  "geometry": {"coordinates":[0.444525,51.677309],"type":"Point"}
}
