{
  "type": "Feature",
  "properties": {
    "date:inception_lower":"1994-12-01",
    "date:inception_upper":"1994-12-31",
    "iso:country":"GB",
    "wof:name":"CM4 9DP",
    "wof:placetype":"postalcode"
},
  "geometry": {"coordinates":[0.444525,51.677309],"type":"Point"}
}