{
  "type": "Feature",
  "properties": {
    "date:inception_lower": "1980-01-01",
    "date:inception_upper": "1980-01-01",
    "iso:country": "GB",
    "wof:name": "IP8 4QZ",
    "wof:placetype": "postalcode"
  },
  "geometry": {"coordinates":[1.036835,52.12055],"type":"Point"}
}
