{
  "type": "Feature",
  "properties": {
    "date:inception_lower":"1980-01-01",
    "date:inception_upper":"1980-01-31",
    "iso:country":"GB",
    "wof:name":"IP8 4QZ",
    "wof:placetype":"postalcode"
},
  "geometry": {"coordinates":[1.036852,52.120586],"type":"Point"}
}