{
  "type": "Feature",
  "properties": {
    "iso:country": "GB",
    "wof:name": "IP8 4QZ",
    "wof:placetype": "postalcode"
  },
  "geometry": {"coordinates":[1.036852,52.120586],"type":"Point"}
}
