{
  "type": "Feature",
  "properties": {
    "iso:country":"GB",
    "wof:name":"IP8 4QZ",
    "wof:placetype":"postalcode"
},
  "geometry": {"coordinates":[1.03682142127642,52.12057055128044],"type":"Point"}
}