{
  "type": "Feature",
  "properties": {
    "iso:country":"GB",
    "wof:name":"SY3 9DL",
    "wof:placetype":"postalcode"
},
  "geometry": {"coordinates":[-2.77014264741827,52.69335798073735],"type":"Point"}
}