{
  "type": "Feature",
  "properties": {
    "iso:country": "GB",
    "wof:name": "TA21 9QP",
    "wof:placetype": "postalcode"
  },
  "geometry": {"coordinates":[-3.270533,50.963701],"type":"Point"}
}
