{
  "type": "Feature",
  "properties": {
    "iso:country":"GB",
    "wof:name":"TA21 9QP",
    "wof:placetype":"postalcode"
},
  "geometry": {"coordinates":[-3.27053262666639,50.9637012592223],"type":"Point"}
}