{
  "type": "Feature",
  "properties": {
    "iso:country":"GB",
    "wof:name":"IP1 3NG",
    "wof:placetype":"postalcode"
},
  "geometry": {"coordinates":[1.15008791847454,52.06347146159956],"type":"Point"}
}