{
  "type": "Feature",
  "properties": {
    "iso:country":"GB",
    "wof:name":"YO14 9QL",
    "wof:placetype":"postalcode"
},
  "geometry": {"coordinates":[-0.28734130227583,54.17664133986204],"type":"Point"}
}