{
  "type": "Feature",
  "properties": {
    "date:inception_lower": "1980-01-01",
    "date:inception_upper": "1980-01-01",
    "iso:country": "GB",
    "wof:name": "YO14 9QL",
    "wof:placetype": "postalcode"
  },
  "geometry": {"coordinates":[-0.287341,54.176641],"type":"Point"}
}
