{
  "type": "Feature",
  "properties": {
    "iso:country":"GB",
    "wof:name":"WR4 9AQ",
    "wof:placetype":"postalcode"
},
  "geometry": {"coordinates":[-2.1943051382633,52.19697995126325],"type":"Point"}
}