{
  "type": "Feature",
  "properties": {
    "iso:country": "GB",
    "wof:name": "BS24 0BE",
    "wof:placetype": "postalcode"
  },
  "geometry": {"coordinates":[-2.946037,51.303336],"type":"Point"}
}
