{
  "type": "Feature",
  "properties": {
    "iso:country":"GB",
    "wof:name":"EX39 5DJ",
    "wof:placetype":"postalcode"
},
  "geometry": {"coordinates":[-4.31504852019566,50.98431067190332],"type":"Point"}
}