{
  "type": "Feature",
  "properties": {
    "date:inception_lower":"1980-01-01",
    "date:inception_upper":"1980-01-31",
    "iso:country":"GB",
    "wof:name":"EX39 5DJ",
    "wof:placetype":"postalcode"
},
  "geometry": {"coordinates":[-4.315048,50.984311],"type":"Point"}
}