{
  "type": "Feature",
  "properties": {
    "iso:country":"GB",
    "wof:name":"IP2 9HR",
    "wof:placetype":"postalcode"
},
  "geometry": {"coordinates":[1.13032440006086,52.04670326350885],"type":"Point"}
}