{
  "type": "Feature",
  "properties": {
    "iso:country":"GB",
    "wof:name":"S25 3QY",
    "wof:placetype":"postalcode"
},
  "geometry": {"coordinates":[-1.21853686610153,53.3751829570006],"type":"Point"}
}