{
  "type": "Feature",
  "properties": {
    "iso:country":"GB",
    "wof:name":"W3 6QD",
    "wof:placetype":"postalcode"
},
  "geometry": {"coordinates":[-0.26259875474338,51.51280959991882],"type":"Point"}
}