{
  "type": "Feature",
  "properties": {
    "iso:country": "GB",
    "wof:name": "PE19 8EQ",
    "wof:placetype": "postalcode"
  },
  "geometry": {"coordinates":[-0.28978,52.215868],"type":"Point"}
}
