{
  "type": "Feature",
  "properties": {
    "iso:country":"GB",
    "wof:name":"BN6 9TL",
    "wof:placetype":"postalcode"
},
  "geometry": {"coordinates":[-0.17932455089865,50.94237038735503],"type":"Point"}
}