{
  "type": "Feature",
  "properties": {
    "iso:country":"GB",
    "wof:name":"RM11 2RD",
    "wof:placetype":"postalcode"
},
  "geometry": {"coordinates":[0.22019203160567,51.57854939698331],"type":"Point"}
}