{
  "type": "Feature",
  "properties": {
    "date:inception_lower": "1980-01-01",
    "date:inception_upper": "1980-01-01",
    "iso:country": "GB",
    "wof:name": "RM11 2RD",
    "wof:placetype": "postalcode"
  },
  "geometry": {"coordinates":[0.220192,51.578549],"type":"Point"}
}
