{
  "type": "Feature",
  "properties": {
    "iso:country":"GB",
    "wof:name":"PL19 9DD",
    "wof:placetype":"postalcode"
},
  "geometry": {"coordinates":[-4.13754892387625,50.53956767192137],"type":"Point"}
}