{
  "type": "Feature",
  "properties": {
    "iso:country":"GB",
    "wof:name":"BL9 9PG",
    "wof:placetype":"postalcode"
},
  "geometry": {"coordinates":[-2.29629771910219,53.57402949878384],"type":"Point"}
}