{
  "type": "Feature",
  "properties": {
    "iso:country": "GB",
    "wof:name": "PO20 0SZ",
    "wof:placetype": "postalcode"
  },
  "geometry": {"coordinates":[-0.775867,50.733274],"type":"Point"}
}
