{
  "type": "Feature",
  "properties": {
    "iso:country":"GB",
    "wof:name":"PO20 0SZ",
    "wof:placetype":"postalcode"
},
  "geometry": {"coordinates":[-0.77586717341929,50.73327418932988],"type":"Point"}
}