{
  "type": "Feature",
  "properties": {
    "date:inception_lower": "1980-01-01",
    "date:inception_upper": "1980-01-01",
    "iso:country": "GB",
    "wof:name": "B77 4ER",
    "wof:placetype": "postalcode"
  },
  "geometry": {"coordinates":[-1.650193,52.631177],"type":"Point"}
}
