{
  "type": "Feature",
  "properties": {
    "iso:country":"GB",
    "wof:name":"B77 4ER",
    "wof:placetype":"postalcode"
},
  "geometry": {"coordinates":[-1.65019275999926,52.63117721541651],"type":"Point"}
}