{
  "type": "Feature",
  "properties": {
    "iso:country":"GB",
    "wof:name":"S41 9RX",
    "wof:placetype":"postalcode"
},
  "geometry": {"coordinates":[-1.44402130352545,53.26888563369202],"type":"Point"}
}