{
  "type": "Feature",
  "properties": {
    "iso:country": "GB",
    "wof:name": "S41 9RX",
    "wof:placetype": "postalcode"
  },
  "geometry": {"coordinates":[-1.444021,53.268886],"type":"Point"}
}
