{
  "type": "Feature",
  "properties": {
    "iso:country": "GB",
    "wof:name": "OL13 0TA",
    "wof:placetype": "postalcode"
  },
  "geometry": {"coordinates":[-2.230686,53.694056],"type":"Point"}
}
