{
  "type": "Feature",
  "properties": {
    "iso:country":"GB",
    "wof:name":"YO7 2BZ",
    "wof:placetype":"postalcode"
},
  "geometry": {"coordinates":[-1.28747425441004,54.20294897393491],"type":"Point"}
}