{
  "type": "Feature",
  "properties": {
    "date:inception_lower":"2013-02-01",
    "date:inception_upper":"2013-02-28",
    "iso:country":"GB",
    "wof:name":"YO7 2BZ",
    "wof:placetype":"postalcode"
},
  "geometry": {"coordinates":[-1.287474,54.202949],"type":"Point"}
}