{
  "type": "Feature",
  "properties": {
    "iso:country": "GB",
    "wof:name": "YO7 2BZ",
    "wof:placetype": "postalcode"
  },
  "geometry": {"coordinates":[-1.287474,54.202949],"type":"Point"}
}
