{
  "type": "Feature",
  "properties": {
    "iso:country":"GB",
    "wof:name":"PE19 2JE",
    "wof:placetype":"postalcode"
},
  "geometry": {"coordinates":[-0.261560659825,52.21991553145104],"type":"Point"}
}