{
  "type": "Feature",
  "properties": {
    "iso:country":"GB",
    "wof:name":"S44 5RX",
    "wof:placetype":"postalcode"
},
  "geometry": {"coordinates":[-1.33235859862864,53.19585277249472],"type":"Point"}
}