{
  "type": "Feature",
  "properties": {
    "iso:country":"GB",
    "wof:name":"WV6 9DS",
    "wof:placetype":"postalcode"
},
  "geometry": {"coordinates":[-2.16521397123526,52.61574630373535],"type":"Point"}
}