{
  "type": "Feature",
  "properties": {
    "iso:country":"GB",
    "wof:name":"M22 8BG",
    "wof:placetype":"postalcode"
},
  "geometry": {"coordinates":[-2.26330527488161,53.39481398744292],"type":"Point"}
}