{
  "type": "Feature",
  "properties": {
    "iso:country":"GB",
    "wof:name":"M34 5AJ",
    "wof:placetype":"postalcode"
},
  "geometry": {"coordinates":[-2.11161916695936,53.46422808463475],"type":"Point"}
}