{
  "type": "Feature",
  "properties": {
    "iso:country": "GB",
    "wof:name": "WF17 9HY",
    "wof:placetype": "postalcode"
  },
  "geometry": {"coordinates":[-1.676158,53.734325],"type":"Point"}
}
