{
  "type": "Feature",
  "properties": {
    "iso:country":"GB",
    "wof:name":"WF17 9HY",
    "wof:placetype":"postalcode"
},
  "geometry": {"coordinates":[-1.67659279643861,53.7344901603299],"type":"Point"}
}