{
  "type": "Feature",
  "properties": {
    "iso:country": "GB",
    "wof:name": "WN7 2LY",
    "wof:placetype": "postalcode"
  },
  "geometry": {"coordinates":[-2.492007,53.494212],"type":"Point"}
}
