{
  "type": "Feature",
  "properties": {
    "iso:country":"GB",
    "wof:name":"PO20 8HA",
    "wof:placetype":"postalcode"
},
  "geometry": {"coordinates":[-0.87983106085298,50.76846539597491],"type":"Point"}
}