{
  "type": "Feature",
  "properties": {
    "iso:country": "GB",
    "wof:name": "PO20 8HA",
    "wof:placetype": "postalcode"
  },
  "geometry": {"coordinates":[-0.879831,50.768465],"type":"Point"}
}
