{
  "type": "Feature",
  "properties": {
    "date:inception_lower": "2022-06-01",
    "date:inception_upper": "2022-06-01",
    "iso:country": "GB",
    "wof:name": "GL16 7SJ",
    "wof:placetype": "postalcode"
  },
  "geometry": {"coordinates":[-2.61652,51.806286],"type":"Point"}
}
