{
  "type": "Feature",
  "properties": {
    "iso:country": "GB",
    "wof:name": "BS8 1UH",
    "wof:placetype": "postalcode"
  },
  "geometry": {"coordinates":[-2.601777,51.457788],"type":"Point"}
}
