{
  "type": "Feature",
  "properties": {
    "iso:country":"GB",
    "wof:name":"BS8 1UH",
    "wof:placetype":"postalcode"
},
  "geometry": {"coordinates":[-2.60177685454149,51.45778779681665],"type":"Point"}
}