{
  "type": "Feature",
  "properties": {
    "date:inception_lower": "1980-01-01",
    "date:inception_upper": "1980-01-01",
    "iso:country": "GB",
    "wof:name": "B74 4PS",
    "wof:placetype": "postalcode"
  },
  "geometry": {"coordinates":[-1.860585,52.589593],"type":"Point"}
}
