{
  "type": "Feature",
  "properties": {
    "iso:country":"GB",
    "wof:name":"B74 4PS",
    "wof:placetype":"postalcode"
},
  "geometry": {"coordinates":[-1.86058523063324,52.5895929312],"type":"Point"}
}