{
  "type": "Feature",
  "properties": {
    "iso:country": "GB",
    "wof:name": "SY14 7BH",
    "wof:placetype": "postalcode"
  },
  "geometry": {"coordinates":[-2.834864,53.033132],"type":"Point"}
}
