{
  "type": "Feature",
  "properties": {
    "iso:country":"GB",
    "wof:name":"SY14 7BH",
    "wof:placetype":"postalcode"
},
  "geometry": {"coordinates":[-2.83486415601402,53.03313230633373],"type":"Point"}
}