{
  "type": "Feature",
  "properties": {
    "date:inception_lower":"1980-01-01",
    "date:inception_upper":"1980-01-31",
    "iso:country":"GB",
    "wof:name":"SY14 7BH",
    "wof:placetype":"postalcode"
},
  "geometry": {"coordinates":[-2.834864,53.033132],"type":"Point"}
}