{
  "type": "Feature",
  "properties": {
    "date:inception_lower": "2023-02-01",
    "date:inception_upper": "2023-02-01",
    "iso:country": "GB",
    "wof:name": "TS22 5XB",
    "wof:placetype": "postalcode"
  },
  "geometry": {"coordinates":[-1.359901,54.634815],"type":"Point"}
}
