{
  "type": "Feature",
  "properties": {
    "date:inception_lower": "1980-01-01",
    "date:inception_upper": "1980-01-01",
    "iso:country": "GB",
    "wof:name": "CH2 1PT",
    "wof:placetype": "postalcode"
  },
  "geometry": {"coordinates":[-2.871206,53.209007],"type":"Point"}
}
