{
  "type": "Feature",
  "properties": {
    "iso:country":"GB",
    "wof:name":"SW18 5TU",
    "wof:placetype":"postalcode"
},
  "geometry": {"coordinates":[-0.20377062818126,51.44791496736966],"type":"Point"}
}