{
  "type": "Feature",
  "properties": {
    "iso:country":"GB",
    "wof:name":"S72 8AN",
    "wof:placetype":"postalcode"
},
  "geometry": {"coordinates":[-1.40989811002838,53.58504144513471],"type":"Point"}
}