{
  "type": "Feature",
  "properties": {
    "iso:country":"GB",
    "wof:name":"PE34 4BU",
    "wof:placetype":"postalcode"
},
  "geometry": {"coordinates":[0.36675918510281,52.75840981411822],"type":"Point"}
}