{
  "type": "Feature",
  "properties": {
    "iso:country": "GB",
    "wof:name": "PE34 4BU",
    "wof:placetype": "postalcode"
  },
  "geometry": {"coordinates":[0.366759,52.75841],"type":"Point"}
}
