{
  "type": "Feature",
  "properties": {
    "date:inception_lower": "1980-01-01",
    "date:inception_upper": "1980-01-01",
    "iso:country": "GB",
    "wof:name": "PE34 4BU",
    "wof:placetype": "postalcode"
  },
  "geometry": {"coordinates":[0.366759,52.75841],"type":"Point"}
}
