{
  "type": "Feature",
  "properties": {
    "iso:country":"GB",
    "wof:name":"DE65 6HF",
    "wof:placetype":"postalcode"
},
  "geometry": {"coordinates":[-1.61081356256443,52.85294510766385],"type":"Point"}
}