{
  "type": "Feature",
  "properties": {
    "date:inception_lower": "1994-05-01",
    "date:inception_upper": "1994-05-01",
    "iso:country": "GB",
    "wof:name": "M40 5AJ",
    "wof:placetype": "postalcode"
  },
  "geometry": {"coordinates":[-2.206973,53.497257],"type":"Point"}
}
