{
  "type": "Feature",
  "properties": {
    "iso:country":"GB",
    "wof:name":"M40 5AJ",
    "wof:placetype":"postalcode"
},
  "geometry": {"coordinates":[-2.20688453963065,53.49729526784274],"type":"Point"}
}