{
  "type": "Feature",
  "properties": {
    "iso:country":"GB",
    "wof:name":"SG1 5AZ",
    "wof:placetype":"postalcode"
},
  "geometry": {"coordinates":[-0.18510802925504,51.91596044150521],"type":"Point"}
}