{
  "type": "Feature",
  "properties": {
    "iso:country":"GB",
    "wof:name":"M7 1TD",
    "wof:placetype":"postalcode"
},
  "geometry": {"coordinates":[-2.25824326932958,53.49249428177544],"type":"Point"}
}