{
  "type": "Feature",
  "properties": {
    "iso:country":"GB",
    "wof:name":"N3 1TU",
    "wof:placetype":"postalcode"
},
  "geometry": {"coordinates":[-0.19880649489486,51.59913637773293],"type":"Point"}
}