{
  "type": "Feature",
  "properties": {
    "iso:country":"GB",
    "wof:name":"EX2 7DL",
    "wof:placetype":"postalcode"
},
  "geometry": {"coordinates":[-3.48452241549352,50.69600582978387],"type":"Point"}
}