{
  "type": "Feature",
  "properties": {
    "date:inception_lower": "1980-01-01",
    "date:inception_upper": "1980-01-01",
    "iso:country": "GB",
    "wof:name": "TN29 0PJ",
    "wof:placetype": "postalcode"
  },
  "geometry": {"coordinates":[0.990879,51.024938],"type":"Point"}
}
