{
  "type": "Feature",
  "properties": {
    "iso:country":"GB",
    "wof:name":"PO7 5RF",
    "wof:placetype":"postalcode"
},
  "geometry": {"coordinates":[-1.03015658512162,50.86056713944686],"type":"Point"}
}