{
  "type": "Feature",
  "properties": {
    "date:inception_lower":"2010-07-01",
    "date:inception_upper":"2010-07-31",
    "iso:country":"GB",
    "wof:name":"GL7 1GB",
    "wof:placetype":"postalcode"
},
  "geometry": {"coordinates":[-1.947765,51.721752],"type":"Point"}
}