{
  "type": "Feature",
  "properties": {
    "date:inception_lower": "1980-01-01",
    "date:inception_upper": "1980-01-01",
    "iso:country": "GB",
    "wof:name": "CM22 7EH",
    "wof:placetype": "postalcode"
  },
  "geometry": {"coordinates":[0.20556,51.815207],"type":"Point"}
}
