{
  "type": "Feature",
  "properties": {
    "iso:country":"GB",
    "wof:name":"ST2 0DN",
    "wof:placetype":"postalcode"
},
  "geometry": {"coordinates":[-2.132300454452,53.01340021696326],"type":"Point"}
}