{
  "type": "Feature",
  "properties": {
    "date:inception_lower": "1980-01-01",
    "date:inception_upper": "1980-01-01",
    "iso:country": "GB",
    "wof:name": "ST2 0DN",
    "wof:placetype": "postalcode"
  },
  "geometry": {"coordinates":[-2.1323,53.0134],"type":"Point"}
}
