{
  "type": "Feature",
  "properties": {
    "iso:country":"GB",
    "wof:name":"NR5 8XE",
    "wof:placetype":"postalcode"
},
  "geometry": {"coordinates":[1.24381470932868,52.64054190813244],"type":"Point"}
}