{
  "type": "Feature",
  "properties": {
    "iso:country": "GB",
    "wof:name": "NR5 8XE",
    "wof:placetype": "postalcode"
  },
  "geometry": {"coordinates":[1.243815,52.640542],"type":"Point"}
}
