{
  "type": "Feature",
  "properties": {
    "iso:country":"GB",
    "wof:name":"UB3 1JQ",
    "wof:placetype":"postalcode"
},
  "geometry": {"coordinates":[-0.42762144393684,51.51543451793833],"type":"Point"}
}