{
  "type": "Feature",
  "properties": {
    "iso:country":"GB",
    "wof:name":"BD5 8DF",
    "wof:placetype":"postalcode"
},
  "geometry": {"coordinates":[-1.75738162780793,53.77545951395754],"type":"Point"}
}