{
  "type": "Feature",
  "properties": {
    "iso:country":"GB",
    "wof:name":"LA6 2BT",
    "wof:placetype":"postalcode"
},
  "geometry": {"coordinates":[-2.59630946636314,54.2004407067834],"type":"Point"}
}