{
  "type": "Feature",
  "properties": {
    "iso:country": "GB",
    "wof:name": "NR33 9PD",
    "wof:placetype": "postalcode"
  },
  "geometry": {"coordinates":[1.713262,52.467753],"type":"Point"}
}
