{
  "type": "Feature",
  "properties": {
    "date:inception_lower":"1980-01-01",
    "date:inception_upper":"1980-01-31",
    "iso:country":"GB",
    "wof:name":"NR33 9PD",
    "wof:placetype":"postalcode"
},
  "geometry": {"coordinates":[1.713262,52.467753],"type":"Point"}
}