{
  "type": "Feature",
  "properties": {
    "iso:country": "GB",
    "wof:name": "SY11 3HP",
    "wof:placetype": "postalcode"
  },
  "geometry": {"coordinates":[-2.990902,52.913829],"type":"Point"}
}
