{
  "type": "Feature",
  "properties": {
    "iso:country":"GB",
    "wof:name":"SY11 3HP",
    "wof:placetype":"postalcode"
},
  "geometry": {"coordinates":[-2.99090220660581,52.91382940940835],"type":"Point"}
}