{
  "type": "Feature",
  "properties": {
    "date:inception_lower": "1980-01-01",
    "date:inception_upper": "1980-01-01",
    "iso:country": "GB",
    "wof:name": "SY11 3HP",
    "wof:placetype": "postalcode"
  },
  "geometry": {"coordinates":[-2.990902,52.913829],"type":"Point"}
}
