{
  "type": "Feature",
  "properties": {
    "iso:country": "GB",
    "wof:name": "CA9 3BW",
    "wof:placetype": "postalcode"
  },
  "geometry": {"coordinates":[-2.555672,54.772399],"type":"Point"}
}
