{
  "type": "Feature",
  "properties": {
    "iso:country":"GB",
    "wof:name":"W1D 6BL",
    "wof:placetype":"postalcode"
},
  "geometry": {"coordinates":[-0.13203342866573,51.51056008417557],"type":"Point"}
}