{
  "type": "Feature",
  "properties": {
    "iso:country":"GB",
    "wof:name":"YO32 9UW",
    "wof:placetype":"postalcode"
},
  "geometry": {"coordinates":[-0.99958303139844,53.99646363362775],"type":"Point"}
}