{
  "type": "Feature",
  "properties": {
    "iso:country":"GB",
    "wof:name":"B20 3WJ",
    "wof:placetype":"postalcode"
},
  "geometry": {"coordinates":[-1.90298249807173,52.51391363565409],"type":"Point"}
}