{
  "type": "Feature",
  "properties": {
    "date:inception_lower":"2016-02-01",
    "date:inception_upper":"2016-02-29",
    "iso:country":"GB",
    "wof:name":"B20 3WJ",
    "wof:placetype":"postalcode"
},
  "geometry": {"coordinates":[-1.902978,52.513929],"type":"Point"}
}