{
  "type": "Feature",
  "properties": {
    "iso:country":"GB",
    "wof:name":"CR4 2LW",
    "wof:placetype":"postalcode"
},
  "geometry": {"coordinates":[-0.15754983449075,51.40596653103051],"type":"Point"}
}