{
  "type": "Feature",
  "properties": {
    "iso:country":"GB",
    "wof:name":"M29 8WB",
    "wof:placetype":"postalcode"
},
  "geometry": {"coordinates":[-2.45280817041688,53.51450320918505],"type":"Point"}
}