{
  "type": "Feature",
  "properties": {
    "iso:country":"GB",
    "wof:name":"WR11 8JR",
    "wof:placetype":"postalcode"
},
  "geometry": {"coordinates":[-1.89119299206685,52.11861275065554],"type":"Point"}
}