{
  "type": "Feature",
  "properties": {
    "iso:country":"GB",
    "wof:name":"PO36 9HF",
    "wof:placetype":"postalcode"
},
  "geometry": {"coordinates":[-1.16695437432031,50.64980691114081],"type":"Point"}
}