{
  "type": "Feature",
  "properties": {
    "iso:country":"GB",
    "wof:name":"DD11 5DD",
    "wof:placetype":"postalcode"
},
  "geometry": {"coordinates":[-2.56492553753546,56.56448121958091],"type":"Point"}
}