{
  "type": "Feature",
  "properties": {
    "date:inception_lower":"1980-01-01",
    "date:inception_upper":"1980-01-31",
    "iso:country":"GB",
    "wof:name":"DD11 5DD",
    "wof:placetype":"postalcode"
},
  "geometry": {"coordinates":[-2.564925,56.564481],"type":"Point"}
}