{
  "type": "Feature",
  "properties": {
    "iso:country": "GB",
    "wof:name": "WA15 8EY",
    "wof:placetype": "postalcode"
  },
  "geometry": {"coordinates":[-2.343074,53.390205],"type":"Point"}
}
