{
  "type": "Feature",
  "properties": {
    "iso:country": "GB",
    "wof:name": "ME1 3XG",
    "wof:placetype": "postalcode"
  },
  "geometry": {"coordinates":[0.457738,51.34915],"type":"Point"}
}
