{
  "type": "Feature",
  "properties": {
    "iso:country":"GB",
    "wof:name":"ME1 3XG",
    "wof:placetype":"postalcode"
},
  "geometry": {"coordinates":[0.4577376579772,51.34915027080601],"type":"Point"}
}