{
  "type": "Feature",
  "properties": {
    "date:inception_lower": "1995-12-01",
    "date:inception_upper": "1995-12-01",
    "iso:country": "GB",
    "wof:name": "CW11 3HW",
    "wof:placetype": "postalcode"
  },
  "geometry": {"coordinates":[-2.391243,53.143073],"type":"Point"}
}
