{
  "type": "Feature",
  "properties": {
    "iso:country": "GB",
    "wof:name": "CW11 3HW",
    "wof:placetype": "postalcode"
  },
  "geometry": {"coordinates":[-2.391243,53.143073],"type":"Point"}
}
