{
  "type": "Feature",
  "properties": {
    "iso:country": "GB",
    "wof:name": "RG40 4UQ",
    "wof:placetype": "postalcode"
  },
  "geometry": {"coordinates":[-0.854817,51.384406],"type":"Point"}
}
