{
  "type": "Feature",
  "properties": {
    "iso:country":"GB",
    "wof:name":"HA0 1BN",
    "wof:placetype":"postalcode"
},
  "geometry": {"coordinates":[-0.30562170787438,51.53871634835728],"type":"Point"}
}