{
  "type": "Feature",
  "properties": {
    "date:inception_lower":"1998-06-01",
    "date:inception_upper":"1998-06-30",
    "iso:country":"GB",
    "wof:name":"YO19 5UT",
    "wof:placetype":"postalcode"
},
  "geometry": {"coordinates":[-1.00738,53.961744],"type":"Point"}
}