{
  "type": "Feature",
  "properties": {
    "iso:country":"GB",
    "wof:name":"YO19 5UT",
    "wof:placetype":"postalcode"
},
  "geometry": {"coordinates":[-1.00737991714131,53.96174432738803],"type":"Point"}
}