{
  "type": "Feature",
  "properties": {
    "iso:country":"GB",
    "wof:name":"CA14 4TZ",
    "wof:placetype":"postalcode"
},
  "geometry": {"coordinates":[-3.4140128461615,54.57887574158799],"type":"Point"}
}