{
  "type": "Feature",
  "properties": {
    "iso:country":"GB",
    "wof:name":"M11 2BP",
    "wof:placetype":"postalcode"
},
  "geometry": {"coordinates":[-2.1928694045717,53.47491953722542],"type":"Point"}
}