{
  "type": "Feature",
  "properties": {
    "date:inception_lower":"1994-05-01",
    "date:inception_upper":"1994-05-31",
    "iso:country":"GB",
    "wof:name":"M11 2BP",
    "wof:placetype":"postalcode"
},
  "geometry": {"coordinates":[-2.192869,53.47492],"type":"Point"}
}