{
  "type": "Feature",
  "properties": {
    "date:inception_lower": "1980-01-01",
    "date:inception_upper": "1980-01-01",
    "iso:country": "GB",
    "wof:name": "SK15 1UR",
    "wof:placetype": "postalcode"
  },
  "geometry": {"coordinates":[-2.071379,53.476942],"type":"Point"}
}
