{
  "type": "Feature",
  "properties": {
    "iso:country": "GB",
    "wof:name": "SK15 1UR",
    "wof:placetype": "postalcode"
  },
  "geometry": {"coordinates":[-2.071379,53.476942],"type":"Point"}
}
