{
  "type": "Feature",
  "properties": {
    "iso:country":"GB",
    "wof:name":"WV10 7LD",
    "wof:placetype":"postalcode"
},
  "geometry": {"coordinates":[-2.08181106596337,52.65579275726784],"type":"Point"}
}