{
  "type": "Feature",
  "properties": {
    "iso:country":"GB",
    "wof:name":"B93 8DB",
    "wof:placetype":"postalcode"
},
  "geometry": {"coordinates":[-1.75366504659035,52.37453165386657],"type":"Point"}
}