{
  "type": "Feature",
  "properties": {
    "date:inception_lower": "1980-01-01",
    "date:inception_upper": "1980-01-01",
    "iso:country": "GB",
    "wof:name": "CT4 5JN",
    "wof:placetype": "postalcode"
  },
  "geometry": {"coordinates":[1.142041,51.229619],"type":"Point"}
}
