{
  "type": "Feature",
  "properties": {
    "iso:country":"GB",
    "wof:name":"CT4 5JN",
    "wof:placetype":"postalcode"
},
  "geometry": {"coordinates":[1.14210963989989,51.22958518651468],"type":"Point"}
}