{
  "type": "Feature",
  "properties": {
    "date:inception_lower":"1995-07-01",
    "date:inception_upper":"1995-07-31",
    "iso:country":"GB",
    "wof:name":"M8 0JL",
    "wof:placetype":"postalcode"
},
  "geometry": {"coordinates":[-2.225528,53.50234],"type":"Point"}
}