{
  "type": "Feature",
  "properties": {
    "iso:country":"GB",
    "wof:name":"M8 0JL",
    "wof:placetype":"postalcode"
},
  "geometry": {"coordinates":[-2.22552796456877,53.50233996774407],"type":"Point"}
}