{
  "type": "Feature",
  "properties": {
    "iso:country": "GB",
    "wof:name": "CT14 9DL",
    "wof:placetype": "postalcode"
  },
  "geometry": {"coordinates":[1.39001,51.210211],"type":"Point"}
}
