{
  "type": "Feature",
  "properties": {
    "iso:country": "GB",
    "wof:name": "LS13 2LL",
    "wof:placetype": "postalcode"
  },
  "geometry": {"coordinates":[-1.630904,53.814019],"type":"Point"}
}
