{
  "type": "Feature",
  "properties": {
    "date:inception_lower": "1980-01-01",
    "date:inception_upper": "1980-01-01",
    "iso:country": "GB",
    "wof:name": "SW11 3EG",
    "wof:placetype": "postalcode"
  },
  "geometry": {"coordinates":[-0.16741,51.472558],"type":"Point"}
}
