{
  "type": "Feature",
  "properties": {
    "iso:country":"GB",
    "wof:name":"BN43 5DB",
    "wof:placetype":"postalcode"
},
  "geometry": {"coordinates":[-0.27803889877508,50.83253154830328],"type":"Point"}
}