{
  "type": "Feature",
  "properties": {
    "iso:country":"GB",
    "wof:name":"PL3 5BE",
    "wof:placetype":"postalcode"
},
  "geometry": {"coordinates":[-4.12991586299986,50.38723719829463],"type":"Point"}
}