{
  "type": "Feature",
  "properties": {
    "iso:country": "GB",
    "wof:name": "HR2 8BN",
    "wof:placetype": "postalcode"
  },
  "geometry": {"coordinates":[-2.735114,52.029492],"type":"Point"}
}
