{
  "type": "Feature",
  "properties": {
    "iso:country":"GB",
    "wof:name":"HR2 8BN",
    "wof:placetype":"postalcode"
},
  "geometry": {"coordinates":[-2.73506893960226,52.02951021997888],"type":"Point"}
}