{
  "type": "Feature",
  "properties": {
    "date:inception_lower": "1998-06-01",
    "date:inception_upper": "1998-06-01",
    "iso:country": "GB",
    "wof:name": "HR2 8BN",
    "wof:placetype": "postalcode"
  },
  "geometry": {"coordinates":[-2.735114,52.029492],"type":"Point"}
}
