{
  "type": "Feature",
  "properties": {
    "iso:country":"GB",
    "wof:name":"N16 9BB",
    "wof:placetype":"postalcode"
},
  "geometry": {"coordinates":[-0.08891566725406,51.55632987746267],"type":"Point"}
}