{
  "type": "Feature",
  "properties": {
    "iso:country":"GB",
    "wof:name":"IV2 3BN",
    "wof:placetype":"postalcode"
},
  "geometry": {"coordinates":[-4.20210997162803,57.4760093749992],"type":"Point"}
}