{
  "type": "Feature",
  "properties": {
    "iso:country":"GB",
    "wof:name":"IP19 8RA",
    "wof:placetype":"postalcode"
},
  "geometry": {"coordinates":[1.54650574666691,52.37954905095012],"type":"Point"}
}