{
  "type": "Feature",
  "properties": {
    "iso:country":"GB",
    "wof:name":"W1T 6AZ",
    "wof:placetype":"postalcode"
},
  "geometry": {"coordinates":[-0.14194516498264,51.52338795790251],"type":"Point"}
}