{
  "type": "Feature",
  "properties": {
    "iso:country": "GB",
    "wof:name": "W1T 6AZ",
    "wof:placetype": "postalcode"
  },
  "geometry": {"coordinates":[-0.141945,51.523388],"type":"Point"}
}
