{
  "type": "Feature",
  "properties": {
    "iso:country": "GB",
    "wof:name": "CT3 1DB",
    "wof:placetype": "postalcode"
  },
  "geometry": {"coordinates":[1.218298,51.278415],"type":"Point"}
}
