{
  "type": "Feature",
  "properties": {
    "date:inception_lower": "1980-01-01",
    "date:inception_upper": "1980-01-01",
    "iso:country": "GB",
    "wof:name": "NN2 7QT",
    "wof:placetype": "postalcode"
  },
  "geometry": {"coordinates":[-0.88573,52.264833],"type":"Point"}
}
