{
  "type": "Feature",
  "properties": {
    "iso:country": "GB",
    "wof:name": "PE19 5DJ",
    "wof:placetype": "postalcode"
  },
  "geometry": {"coordinates":[-0.312989,52.275149],"type":"Point"}
}
