{
  "type": "Feature",
  "properties": {
    "date:inception_lower": "1980-01-01",
    "date:inception_upper": "1980-01-01",
    "iso:country": "GB",
    "wof:name": "GL7 5LR",
    "wof:placetype": "postalcode"
  },
  "geometry": {"coordinates":[-1.857868,51.70713],"type":"Point"}
}
