{
  "type": "Feature",
  "properties": {
    "iso:country":"GB",
    "wof:name":"GL7 5LR",
    "wof:placetype":"postalcode"
},
  "geometry": {"coordinates":[-1.85786778024024,51.70712981397779],"type":"Point"}
}