{
  "type": "Feature",
  "properties": {
    "date:inception_lower":"1980-01-01",
    "date:inception_upper":"1980-01-31",
    "iso:country":"GB",
    "wof:name":"PO22 0HG",
    "wof:placetype":"postalcode"
},
  "geometry": {"coordinates":[-0.642753,50.835095],"type":"Point"}
}