{
  "type": "Feature",
  "properties": {
    "iso:country":"GB",
    "wof:name":"PO22 0HG",
    "wof:placetype":"postalcode"
},
  "geometry": {"coordinates":[-0.64275341244412,50.83509536309926],"type":"Point"}
}