{
  "type": "Feature",
  "properties": {
    "iso:country":"GB",
    "wof:name":"S10 3FP",
    "wof:placetype":"postalcode"
},
  "geometry": {"coordinates":[-1.51943113729945,53.37400424872286],"type":"Point"}
}