{
  "type": "Feature",
  "properties": {
    "iso:country": "GB",
    "wof:name": "OX1 5PB",
    "wof:placetype": "postalcode"
  },
  "geometry": {"coordinates":[-1.248112,51.723334],"type":"Point"}
}
