{
  "type": "Feature",
  "properties": {
    "iso:country":"GB",
    "wof:name":"OX1 5PB",
    "wof:placetype":"postalcode"
},
  "geometry": {"coordinates":[-1.2481123281642,51.72333352883019],"type":"Point"}
}