{
  "type": "Feature",
  "properties": {
    "date:inception_lower": "1983-07-01",
    "date:inception_upper": "1983-07-01",
    "iso:country": "GB",
    "wof:name": "EX4 2LU",
    "wof:placetype": "postalcode"
  },
  "geometry": {"coordinates":[-3.551168,50.732397],"type":"Point"}
}
