{
  "type": "Feature",
  "properties": {
    "iso:country":"GB",
    "wof:name":"DG1 2LZ",
    "wof:placetype":"postalcode"
},
  "geometry": {"coordinates":[-3.60309535985972,55.06428427349589],"type":"Point"}
}