{
  "type": "Feature",
  "properties": {
    "iso:country":"GB",
    "wof:name":"BB5 6EF",
    "wof:placetype":"postalcode"
},
  "geometry": {"coordinates":[-2.35917580257682,53.75667726217219],"type":"Point"}
}