{
  "type": "Feature",
  "properties": {
    "iso:country": "GB",
    "wof:name": "KT23 3JD",
    "wof:placetype": "postalcode"
  },
  "geometry": {"coordinates":[-0.381803,51.286548],"type":"Point"}
}
