{
  "type": "Feature",
  "properties": {
    "iso:country":"GB",
    "wof:name":"CO4 3TA",
    "wof:placetype":"postalcode"
},
  "geometry": {"coordinates":[0.94173880527978,51.88804421579466],"type":"Point"}
}