{
  "type": "Feature",
  "properties": {
    "iso:country":"GB",
    "wof:name":"IP24 2DN",
    "wof:placetype":"postalcode"
},
  "geometry": {"coordinates":[0.75493548761484,52.41312083386163],"type":"Point"}
}