{
  "type": "Feature",
  "properties": {
    "date:inception_lower": "1980-01-01",
    "date:inception_upper": "1980-01-01",
    "iso:country": "GB",
    "wof:name": "BB9 0XD",
    "wof:placetype": "postalcode"
  },
  "geometry": {"coordinates":[-2.209612,53.829071],"type":"Point"}
}
