{
  "type": "Feature",
  "properties": {
    "iso:country":"GB",
    "wof:name":"SM1 2TA",
    "wof:placetype":"postalcode"
},
  "geometry": {"coordinates":[-0.20486061520848,51.36356324091678],"type":"Point"}
}