{
  "type": "Feature",
  "properties": {
    "iso:country":"GB",
    "wof:name":"DA6 8GA",
    "wof:placetype":"postalcode"
},
  "geometry": {"coordinates":[0.12582635311707,51.45720321773299],"type":"Point"}
}