{
  "type": "Feature",
  "properties": {
    "iso:country":"GB",
    "wof:name":"HD4 5HH",
    "wof:placetype":"postalcode"
},
  "geometry": {"coordinates":[-1.805173634601,53.63206035823386],"type":"Point"}
}