{
  "type": "Feature",
  "properties": {
    "date:inception_lower":"1995-12-01",
    "date:inception_upper":"1995-12-31",
    "iso:country":"GB",
    "wof:name":"HD4 5HH",
    "wof:placetype":"postalcode"
},
  "geometry": {"coordinates":[-1.805174,53.63206],"type":"Point"}
}