{
  "type": "Feature",
  "properties": {
    "iso:country": "GB",
    "wof:name": "HD4 5HH",
    "wof:placetype": "postalcode"
  },
  "geometry": {"coordinates":[-1.805174,53.63206],"type":"Point"}
}
