{
  "type": "Feature",
  "properties": {
    "iso:country":"GB",
    "wof:name":"RG12 0GD",
    "wof:placetype":"postalcode"
},
  "geometry": {"coordinates":[-0.73268179640122,51.39271681046699],"type":"Point"}
}