{
  "type": "Feature",
  "properties": {
    "iso:country":"GB",
    "wof:name":"L17 6BE",
    "wof:placetype":"postalcode"
},
  "geometry": {"coordinates":[-2.9235078890823,53.36895123027957],"type":"Point"}
}