{
  "type": "Feature",
  "properties": {
    "iso:country": "GB",
    "wof:name": "CM1 1HR",
    "wof:placetype": "postalcode"
  },
  "geometry": {"coordinates":[0.468434,51.734429],"type":"Point"}
}
