{
  "type": "Feature",
  "properties": {
    "iso:country": "GB",
    "wof:name": "TA6 4RQ",
    "wof:placetype": "postalcode"
  },
  "geometry": {"coordinates":[-2.983361,51.133966],"type":"Point"}
}
