{
  "type": "Feature",
  "properties": {
    "iso:country": "GB",
    "wof:name": "EX14 9HN",
    "wof:placetype": "postalcode"
  },
  "geometry": {"coordinates":[-3.130405,50.820296],"type":"Point"}
}
