{
  "type": "Feature",
  "properties": {
    "iso:country":"GB",
    "wof:name":"CO10 0JB",
    "wof:placetype":"postalcode"
},
  "geometry": {"coordinates":[0.743534983058,52.02528750149769],"type":"Point"}
}