{
  "type": "Feature",
  "properties": {
    "iso:country": "GB",
    "wof:name": "RH20 3ND",
    "wof:placetype": "postalcode"
  },
  "geometry": {"coordinates":[-0.446973,50.921038],"type":"Point"}
}
