{
  "type": "Feature",
  "properties": {
    "date:inception_lower": "2005-11-01",
    "date:inception_upper": "2005-11-01",
    "iso:country": "GB",
    "wof:name": "OL7 0PS",
    "wof:placetype": "postalcode"
  },
  "geometry": {"coordinates":[-2.101736,53.482259],"type":"Point"}
}
