{
  "type": "Feature",
  "properties": {
    "iso:country":"GB",
    "wof:name":"OL7 0PS",
    "wof:placetype":"postalcode"
},
  "geometry": {"coordinates":[-2.10173623665271,53.48225877146662],"type":"Point"}
}