{
  "type": "Feature",
  "properties": {
    "iso:country":"GB",
    "wof:name":"CF64 4JS",
    "wof:placetype":"postalcode"
},
  "geometry": {"coordinates":[-3.21488555176925,51.43386560537697],"type":"Point"}
}