{
  "type": "Feature",
  "properties": {
    "iso:country":"GB",
    "wof:name":"PL17 7EN",
    "wof:placetype":"postalcode"
},
  "geometry": {"coordinates":[-4.31205554680926,50.49755576750992],"type":"Point"}
}