{
  "type": "Feature",
  "properties": {
    "date:inception_lower":"1986-01-01",
    "date:inception_upper":"1986-01-31",
    "iso:country":"GB",
    "wof:name":"SO41 5RA",
    "wof:placetype":"postalcode"
},
  "geometry": {"coordinates":[-1.518695,50.782903],"type":"Point"}
}