{
  "type": "Feature",
  "properties": {
    "iso:country": "GB",
    "wof:name": "SO41 5RA",
    "wof:placetype": "postalcode"
  },
  "geometry": {"coordinates":[-1.518695,50.782903],"type":"Point"}
}
