{
  "type": "Feature",
  "properties": {
    "iso:country":"GB",
    "wof:name":"M41 0TL",
    "wof:placetype":"postalcode"
},
  "geometry": {"coordinates":[-2.35011132784558,53.45787032909846],"type":"Point"}
}