{
  "type": "Feature",
  "properties": {
    "iso:country":"GB",
    "wof:name":"LS9 6DW",
    "wof:placetype":"postalcode"
},
  "geometry": {"coordinates":[-1.50886932236065,53.80768586227544],"type":"Point"}
}