{
  "type": "Feature",
  "properties": {
    "date:inception_lower": "2022-03-01",
    "date:inception_upper": "2022-03-01",
    "iso:country": "GB",
    "wof:name": "DY5 1JL",
    "wof:placetype": "postalcode"
  },
  "geometry": {"coordinates":[-2.111931,52.493256],"type":"Point"}
}
