{
  "type": "Feature",
  "properties": {
    "iso:country":"GB",
    "wof:name":"OX5 1RX",
    "wof:placetype":"postalcode"
},
  "geometry": {"coordinates":[-1.32469590366737,51.82056159399291],"type":"Point"}
}