{
  "type": "Feature",
  "properties": {
    "iso:country":"GB",
    "wof:name":"WR3 7HD",
    "wof:placetype":"postalcode"
},
  "geometry": {"coordinates":[-2.22649707951162,52.21808586660051],"type":"Point"}
}