{
  "type": "Feature",
  "properties": {
    "iso:country": "GB",
    "wof:name": "GU14 7PX",
    "wof:placetype": "postalcode"
  },
  "geometry": {"coordinates":[-0.762799,51.295977],"type":"Point"}
}
