{
  "type": "Feature",
  "properties": {
    "iso:country": "GB",
    "wof:name": "CO15 3DG",
    "wof:placetype": "postalcode"
  },
  "geometry": {"coordinates":[1.146255,51.795812],"type":"Point"}
}
