{
  "type": "Feature",
  "properties": {
    "iso:country":"GB",
    "wof:name":"YO7 4ET",
    "wof:placetype":"postalcode"
},
  "geometry": {"coordinates":[-1.42632476105834,54.2579020562419],"type":"Point"}
}