{
  "type": "Feature",
  "properties": {
    "iso:country":"GB",
    "wof:name":"TN28 8LQ",
    "wof:placetype":"postalcode"
},
  "geometry": {"coordinates":[0.95042802319678,50.98582384887846],"type":"Point"}
}