{
  "type": "Feature",
  "properties": {
    "date:inception_lower":"1980-01-01",
    "date:inception_upper":"1980-01-31",
    "iso:country":"GB",
    "wof:name":"TS3 7BG",
    "wof:placetype":"postalcode"
},
  "geometry": {"coordinates":[-1.212885,54.563183],"type":"Point"}
}