{
  "type": "Feature",
  "properties": {
    "iso:country": "GB",
    "wof:name": "TS3 7BG",
    "wof:placetype": "postalcode"
  },
  "geometry": {"coordinates":[-1.212885,54.563183],"type":"Point"}
}
