{
  "type": "Feature",
  "properties": {
    "iso:country":"GB",
    "wof:name":"TS3 7BG",
    "wof:placetype":"postalcode"
},
  "geometry": {"coordinates":[-1.21288473378024,54.56318314732667],"type":"Point"}
}