{
  "type": "Feature",
  "properties": {
    "iso:country": "GB",
    "wof:name": "LN6 9SG",
    "wof:placetype": "postalcode"
  },
  "geometry": {"coordinates":[-0.600706,53.183952],"type":"Point"}
}
