{
  "type": "Feature",
  "properties": {
    "iso:country":"GB",
    "wof:name":"LN6 9SG",
    "wof:placetype":"postalcode"
},
  "geometry": {"coordinates":[-0.60070596884669,53.18395216723758],"type":"Point"}
}