{
  "type": "Feature",
  "properties": {
    "iso:country":"GB",
    "wof:name":"B61 8PP",
    "wof:placetype":"postalcode"
},
  "geometry": {"coordinates":[-2.07034820248105,52.33945339996914],"type":"Point"}
}