{
  "type": "Feature",
  "properties": {
    "iso:country":"GB",
    "wof:name":"HD6 2JQ",
    "wof:placetype":"postalcode"
},
  "geometry": {"coordinates":[-1.79349528013678,53.71037265560421],"type":"Point"}
}