{
  "type": "Feature",
  "properties": {
    "iso:country":"GB",
    "wof:name":"SE4 1ER",
    "wof:placetype":"postalcode"
},
  "geometry": {"coordinates":[-0.03474351435787,51.45493320459985],"type":"Point"}
}