{
  "type": "Feature",
  "properties": {
    "date:inception_lower": "1980-01-01",
    "date:inception_upper": "1980-01-01",
    "iso:country": "GB",
    "wof:name": "TN17 4BN",
    "wof:placetype": "postalcode"
  },
  "geometry": {"coordinates":[0.618907,51.083967],"type":"Point"}
}
