{
  "type": "Feature",
  "properties": {
    "iso:country":"GB",
    "wof:name":"BH12 2AW",
    "wof:placetype":"postalcode"
},
  "geometry": {"coordinates":[-1.92455443671981,50.73112068139729],"type":"Point"}
}