{
  "type": "Feature",
  "properties": {
    "date:inception_lower": "2003-10-01",
    "date:inception_upper": "2003-10-01",
    "iso:country": "GB",
    "wof:name": "EN7 6HP",
    "wof:placetype": "postalcode"
  },
  "geometry": {"coordinates":[-0.051486,51.712983],"type":"Point"}
}
