{
  "type": "Feature",
  "properties": {
    "iso:country":"GB",
    "wof:name":"ST4 7QA",
    "wof:placetype":"postalcode"
},
  "geometry": {"coordinates":[-2.18895268876905,53.00277928943959],"type":"Point"}
}