{
  "type": "Feature",
  "properties": {
    "iso:country":"GB",
    "wof:name":"BD9 6EH",
    "wof:placetype":"postalcode"
},
  "geometry": {"coordinates":[-1.8085791618545,53.81184551577651],"type":"Point"}
}