{
  "type": "Feature",
  "properties": {
    "iso:country":"GB",
    "wof:name":"KA19 7QW",
    "wof:placetype":"postalcode"
},
  "geometry": {"coordinates":[-4.60099750663261,55.31108387841183],"type":"Point"}
}