{
  "type": "Feature",
  "properties": {
    "iso:country": "GB",
    "wof:name": "KA19 7QW",
    "wof:placetype": "postalcode"
  },
  "geometry": {"coordinates":[-4.600997,55.311084],"type":"Point"}
}
