{
  "type": "Feature",
  "properties": {
    "iso:country": "GB",
    "wof:name": "SO31 1EY",
    "wof:placetype": "postalcode"
  },
  "geometry": {"coordinates":[-1.26524,50.872291],"type":"Point"}
}
