{
  "type": "Feature",
  "properties": {
    "iso:country":"GB",
    "wof:name":"TQ12 4LH",
    "wof:placetype":"postalcode"
},
  "geometry": {"coordinates":[-3.58861219661476,50.52116640252829],"type":"Point"}
}