{
  "type": "Feature",
  "properties": {
    "iso:country": "GB",
    "wof:name": "TQ12 4LH",
    "wof:placetype": "postalcode"
  },
  "geometry": {"coordinates":[-3.588612,50.521166],"type":"Point"}
}
