{
  "type": "Feature",
  "properties": {
    "iso:country":"GB",
    "wof:name":"PR7 5AH",
    "wof:placetype":"postalcode"
},
  "geometry": {"coordinates":[-2.66552114565138,53.62332015171636],"type":"Point"}
}