{
  "type": "Feature",
  "properties": {
    "date:inception_lower": "1991-09-01",
    "date:inception_upper": "1991-09-01",
    "iso:country": "GB",
    "wof:name": "SY11 2HH",
    "wof:placetype": "postalcode"
  },
  "geometry": {"coordinates":[-3.051644,52.856402],"type":"Point"}
}
