{
  "type": "Feature",
  "properties": {
    "iso:country":"GB",
    "wof:name":"SY11 2HH",
    "wof:placetype":"postalcode"
},
  "geometry": {"coordinates":[-3.05164410961351,52.85640200008341],"type":"Point"}
}