{
  "type": "Feature",
  "properties": {
    "date:inception_lower": "1995-07-01",
    "date:inception_upper": "1995-07-01",
    "iso:country": "GB",
    "wof:name": "ST6 2PT",
    "wof:placetype": "postalcode"
  },
  "geometry": {"coordinates":[-2.190425,53.039219],"type":"Point"}
}
