{
  "type": "Feature",
  "properties": {
    "iso:country": "GB",
    "wof:name": "ST6 2PT",
    "wof:placetype": "postalcode"
  },
  "geometry": {"coordinates":[-2.190425,53.039219],"type":"Point"}
}
