{
  "type": "Feature",
  "properties": {
    "iso:country":"GB",
    "wof:name":"SS5 4QA",
    "wof:placetype":"postalcode"
},
  "geometry": {"coordinates":[0.65293991604828,51.59694660129766],"type":"Point"}
}