{
  "type": "Feature",
  "properties": {
    "iso:country":"GB",
    "wof:name":"SP2 8EG",
    "wof:placetype":"postalcode"
},
  "geometry": {"coordinates":[-1.79572546795319,51.05750793506645],"type":"Point"}
}