{
  "type": "Feature",
  "properties": {
    "iso:country": "GB",
    "wof:name": "SP2 8EG",
    "wof:placetype": "postalcode"
  },
  "geometry": {"coordinates":[-1.795725,51.057508],"type":"Point"}
}
