{
  "type": "Feature",
  "properties": {
    "iso:country": "GB",
    "wof:name": "TD15 2BX",
    "wof:placetype": "postalcode"
  },
  "geometry": {"coordinates":[-2.01366,55.753499],"type":"Point"}
}
