{
  "type": "Feature",
  "properties": {
    "iso:country":"GB",
    "wof:name":"TD15 2BX",
    "wof:placetype":"postalcode"
},
  "geometry": {"coordinates":[-2.01365988619112,55.75349922469123],"type":"Point"}
}