{
  "type": "Feature",
  "properties": {
    "iso:country":"GB",
    "wof:name":"TN8 6QP",
    "wof:placetype":"postalcode"
},
  "geometry": {"coordinates":[0.02886816298239,51.21409740689887],"type":"Point"}
}