{
  "type": "Feature",
  "properties": {
    "iso:country":"GB",
    "wof:name":"CV3 1FJ",
    "wof:placetype":"postalcode"
},
  "geometry": {"coordinates":[-1.46975199964076,52.39681229947256],"type":"Point"}
}