{
  "type": "Feature",
  "properties": {
    "iso:country":"GB",
    "wof:name":"SR2 7NL",
    "wof:placetype":"postalcode"
},
  "geometry": {"coordinates":[-1.38785782923367,54.89495989901986],"type":"Point"}
}