{
  "type": "Feature",
  "properties": {
    "iso:country": "GB",
    "wof:name": "SR2 7NL",
    "wof:placetype": "postalcode"
  },
  "geometry": {"coordinates":[-1.387858,54.89496],"type":"Point"}
}
