{
  "type": "Feature",
  "properties": {
    "iso:country":"GB",
    "wof:name":"DE3 0PB",
    "wof:placetype":"postalcode"
},
  "geometry": {"coordinates":[-1.54533653049505,52.91435303571504],"type":"Point"}
}