{
  "type": "Feature",
  "properties": {
    "iso:country":"GB",
    "wof:name":"WN5 0TS",
    "wof:placetype":"postalcode"
},
  "geometry": {"coordinates":[-2.65505057145134,53.53979429035601],"type":"Point"}
}