{
  "type": "Feature",
  "properties": {
    "date:inception_lower":"1980-01-01",
    "date:inception_upper":"1980-01-31",
    "iso:country":"GB",
    "wof:name":"RG7 1EA",
    "wof:placetype":"postalcode"
},
  "geometry": {"coordinates":[-0.970343,51.397078],"type":"Point"}
}