{
  "type": "Feature",
  "properties": {
    "iso:country":"GB",
    "wof:name":"BA15 1RL",
    "wof:placetype":"postalcode"
},
  "geometry": {"coordinates":[-2.25316948648461,51.3519511740851],"type":"Point"}
}