{
  "type": "Feature",
  "properties": {
    "iso:country":"GB",
    "wof:name":"W1D 5BH",
    "wof:placetype":"postalcode"
},
  "geometry": {"coordinates":[-0.13157882663212,51.51251321218032],"type":"Point"}
}