{
  "type": "Feature",
  "properties": {
    "iso:country":"GB",
    "wof:name":"SO41 0PJ",
    "wof:placetype":"postalcode"
},
  "geometry": {"coordinates":[-1.59109933965975,50.72301893071312],"type":"Point"}
}