{
  "type": "Feature",
  "properties": {
    "iso:country":"GB",
    "wof:name":"LL53 5TB",
    "wof:placetype":"postalcode"
},
  "geometry": {"coordinates":[-4.43497920225345,52.88725234993096],"type":"Point"}
}