{
  "type": "Feature",
  "properties": {
    "date:inception_lower": "1998-12-01",
    "date:inception_upper": "1998-12-01",
    "iso:country": "GB",
    "wof:name": "BS16 7EE",
    "wof:placetype": "postalcode"
  },
  "geometry": {"coordinates":[-2.480715,51.484971],"type":"Point"}
}
