{
  "type": "Feature",
  "properties": {
    "iso:country":"GB",
    "wof:name":"BS16 7EE",
    "wof:placetype":"postalcode"
},
  "geometry": {"coordinates":[-2.480715179478,51.48497094290553],"type":"Point"}
}