{
  "type": "Feature",
  "properties": {
    "date:inception_lower":"1980-01-01",
    "date:inception_upper":"1980-01-31",
    "iso:country":"GB",
    "wof:name":"PO22 6RA",
    "wof:placetype":"postalcode"
},
  "geometry": {"coordinates":[-0.629422,50.797151],"type":"Point"}
}