{
  "type": "Feature",
  "properties": {
    "iso:country":"GB",
    "wof:name":"PO22 6RA",
    "wof:placetype":"postalcode"
},
  "geometry": {"coordinates":[-0.6294216979982,50.79715080237452],"type":"Point"}
}