{
  "type": "Feature",
  "properties": {
    "iso:country":"GB",
    "wof:name":"PE3 8LL",
    "wof:placetype":"postalcode"
},
  "geometry": {"coordinates":[-0.29178135785853,52.5972901039562],"type":"Point"}
}