{
  "type": "Feature",
  "properties": {
    "iso:country": "GB",
    "wof:name": "PE3 8LL",
    "wof:placetype": "postalcode"
  },
  "geometry": {"coordinates":[-0.291781,52.59729],"type":"Point"}
}
