{
  "type": "Feature",
  "properties": {
    "iso:country": "GB",
    "wof:name": "IP3 8AY",
    "wof:placetype": "postalcode"
  },
  "geometry": {"coordinates":[1.170987,52.051785],"type":"Point"}
}
