{
  "type": "Feature",
  "properties": {
    "iso:country":"GB",
    "wof:name":"LE17 5TB",
    "wof:placetype":"postalcode"
},
  "geometry": {"coordinates":[-1.22284508235464,52.48147508821341],"type":"Point"}
}