{
  "type": "Feature",
  "properties": {
    "date:inception_lower":"1999-12-01",
    "date:inception_upper":"1999-12-31",
    "iso:country":"GB",
    "wof:name":"LE17 5TB",
    "wof:placetype":"postalcode"
},
  "geometry": {"coordinates":[-1.222845,52.481475],"type":"Point"}
}