{
  "type": "Feature",
  "properties": {
    "iso:country":"GB",
    "wof:name":"BA3 4NR",
    "wof:placetype":"postalcode"
},
  "geometry": {"coordinates":[-2.58536796501491,51.26852203665327],"type":"Point"}
}