{
  "type": "Feature",
  "properties": {
    "iso:country": "GB",
    "wof:name": "DL5 4LN",
    "wof:placetype": "postalcode"
  },
  "geometry": {"coordinates":[-1.576474,54.622068],"type":"Point"}
}
