{
  "type": "Feature",
  "properties": {
    "date:inception_lower": "1980-01-01",
    "date:inception_upper": "1980-01-01",
    "iso:country": "GB",
    "wof:name": "OX14 2PF",
    "wof:placetype": "postalcode"
  },
  "geometry": {"coordinates":[-1.266754,51.6887],"type":"Point"}
}
