{
  "type": "Feature",
  "properties": {
    "date:inception_lower": "2021-10-01",
    "date:inception_upper": "2021-10-01",
    "iso:country": "GB",
    "wof:name": "IP13 9YS",
    "wof:placetype": "postalcode"
  },
  "geometry": {"coordinates":[1.341861,52.221872],"type":"Point"}
}
