{
  "type": "Feature",
  "properties": {
    "iso:country":"GB",
    "wof:name":"PE30 5NY",
    "wof:placetype":"postalcode"
},
  "geometry": {"coordinates":[0.41152804216408,52.74703250432142],"type":"Point"}
}