{
  "type": "Feature",
  "properties": {
    "iso:country": "GB",
    "wof:name": "PE30 5NY",
    "wof:placetype": "postalcode"
  },
  "geometry": {"coordinates":[0.411528,52.747032],"type":"Point"}
}
