{
  "type": "Feature",
  "properties": {
    "iso:country": "GB",
    "wof:name": "BS21 6XW",
    "wof:placetype": "postalcode"
  },
  "geometry": {"coordinates":[-2.872346,51.401515],"type":"Point"}
}
