{
  "type": "Feature",
  "properties": {
    "iso:country":"GB",
    "wof:name":"GL2 4RG",
    "wof:placetype":"postalcode"
},
  "geometry": {"coordinates":[-2.28413975104463,51.81605002905786],"type":"Point"}
}