{
  "type": "Feature",
  "properties": {
    "iso:country": "GB",
    "wof:name": "GL2 4RG",
    "wof:placetype": "postalcode"
  },
  "geometry": {"coordinates":[-2.28414,51.81605],"type":"Point"}
}
