{
  "type": "Feature",
  "properties": {
    "iso:country":"GB",
    "wof:name":"DE21 4JF",
    "wof:placetype":"postalcode"
},
  "geometry": {"coordinates":[-1.4429002111787,52.93784687712154],"type":"Point"}
}