{
  "type": "Feature",
  "properties": {
    "iso:country": "GB",
    "wof:name": "BS25 1BQ",
    "wof:placetype": "postalcode"
  },
  "geometry": {"coordinates":[-2.843512,51.313408],"type":"Point"}
}
