{
  "type": "Feature",
  "properties": {
    "iso:country":"GB",
    "wof:name":"BS25 1BQ",
    "wof:placetype":"postalcode"
},
  "geometry": {"coordinates":[-2.84351253065479,51.31340781561711],"type":"Point"}
}