{
  "type": "Feature",
  "properties": {
    "iso:country":"GB",
    "wof:name":"EX19 8NW",
    "wof:placetype":"postalcode"
},
  "geometry": {"coordinates":[-4.06678630865874,50.92360441334889],"type":"Point"}
}