{
  "type": "Feature",
  "properties": {
    "iso:country":"GB",
    "wof:name":"NG34 9PL",
    "wof:placetype":"postalcode"
},
  "geometry": {"coordinates":[-0.32915602192483,53.01047769353956],"type":"Point"}
}