{
  "type": "Feature",
  "properties": {
    "date:inception_lower": "1980-01-01",
    "date:inception_upper": "1980-01-01",
    "iso:country": "GB",
    "wof:name": "NG34 9PL",
    "wof:placetype": "postalcode"
  },
  "geometry": {"coordinates":[-0.32894,53.010921],"type":"Point"}
}
