{
  "type": "Feature",
  "properties": {
    "iso:country": "GB",
    "wof:name": "LS18 5BW",
    "wof:placetype": "postalcode"
  },
  "geometry": {"coordinates":[-1.637863,53.840178],"type":"Point"}
}
