{
  "type": "Feature",
  "properties": {
    "iso:country": "GB",
    "wof:name": "TR20 9BT",
    "wof:placetype": "postalcode"
  },
  "geometry": {"coordinates":[-5.435925,50.135309],"type":"Point"}
}
