{
  "type": "Feature",
  "properties": {
    "date:inception_lower":"1990-02-01",
    "date:inception_upper":"1990-02-28",
    "iso:country":"GB",
    "wof:name":"BL8 1PQ",
    "wof:placetype":"postalcode"
},
  "geometry": {"coordinates":[-2.323593,53.596672],"type":"Point"}
}