{
  "type": "Feature",
  "properties": {
    "iso:country":"GB",
    "wof:name":"BL8 1PQ",
    "wof:placetype":"postalcode"
},
  "geometry": {"coordinates":[-2.32359306067367,53.59667220574507],"type":"Point"}
}