{
  "type": "Feature",
  "properties": {
    "iso:country": "GB",
    "wof:name": "BL8 1PQ",
    "wof:placetype": "postalcode"
  },
  "geometry": {"coordinates":[-2.323593,53.596672],"type":"Point"}
}
