{
  "type": "Feature",
  "properties": {
    "iso:country":"GB",
    "wof:name":"DE4 4DX",
    "wof:placetype":"postalcode"
},
  "geometry": {"coordinates":[-1.57155121846259,53.0788366022405],"type":"Point"}
}