{
  "type": "Feature",
  "properties": {
    "iso:country":"GB",
    "wof:name":"SR7 9LD",
    "wof:placetype":"postalcode"
},
  "geometry": {"coordinates":[-1.38160076870486,54.82193055713668],"type":"Point"}
}