{
  "type": "Feature",
  "properties": {
    "iso:country": "GB",
    "wof:name": "SR7 9LD",
    "wof:placetype": "postalcode"
  },
  "geometry": {"coordinates":[-1.381601,54.821931],"type":"Point"}
}
