{
  "type": "Feature",
  "properties": {
    "date:inception_lower": "2023-10-01",
    "date:inception_upper": "2023-10-01",
    "iso:country": "GB",
    "wof:name": "TQ6 0FZ",
    "wof:placetype": "postalcode"
  },
  "geometry": {"coordinates":[-3.608637,50.345973],"type":"Point"}
}
