{
  "type": "Feature",
  "properties": {
    "iso:country":"GB",
    "wof:name":"TF4 3DF",
    "wof:placetype":"postalcode"
},
  "geometry": {"coordinates":[-2.4689937689944,52.66107711713264],"type":"Point"}
}