{
  "type": "Feature",
  "properties": {
    "iso:country":"GB",
    "wof:name":"NW10 8UT",
    "wof:placetype":"postalcode"
},
  "geometry": {"coordinates":[-0.25398312592219,51.53686213386977],"type":"Point"}
}