{
  "type": "Feature",
  "properties": {
    "iso:country": "GB",
    "wof:name": "NW10 8UT",
    "wof:placetype": "postalcode"
  },
  "geometry": {"coordinates":[-0.253983,51.536862],"type":"Point"}
}
