{
  "type": "Feature",
  "properties": {
    "iso:country": "GB",
    "wof:name": "PE12 0LU",
    "wof:placetype": "postalcode"
  },
  "geometry": {"coordinates":[0.027773,52.677198],"type":"Point"}
}
