{
  "type": "Feature",
  "properties": {
    "iso:country":"GB",
    "wof:name":"PE12 0LU",
    "wof:placetype":"postalcode"
},
  "geometry": {"coordinates":[0.02777338264269,52.6771982131122],"type":"Point"}
}