{
  "type": "Feature",
  "properties": {
    "iso:country":"GB",
    "wof:name":"W1J 7UH",
    "wof:placetype":"postalcode"
},
  "geometry": {"coordinates":[-0.14654040494275,51.50677957625522],"type":"Point"}
}