{
  "type": "Feature",
  "properties": {
    "iso:country":"GB",
    "wof:name":"HU15 1ZB",
    "wof:placetype":"postalcode"
},
  "geometry": {"coordinates":[-0.60005871198309,53.76869341982442],"type":"Point"}
}