{
  "type": "Feature",
  "properties": {
    "iso:country":"GB",
    "wof:name":"RH20 1LQ",
    "wof:placetype":"postalcode"
},
  "geometry": {"coordinates":[-0.54333034089232,50.93901586533497],"type":"Point"}
}