{
  "type": "Feature",
  "properties": {
    "date:inception_lower": "1980-01-01",
    "date:inception_upper": "1980-01-01",
    "iso:country": "GB",
    "wof:name": "RH20 1LQ",
    "wof:placetype": "postalcode"
  },
  "geometry": {"coordinates":[-0.543308,50.939009],"type":"Point"}
}
