{
  "type": "Feature",
  "properties": {
    "date:inception_lower": "2016-04-01",
    "date:inception_upper": "2016-04-01",
    "iso:country": "GB",
    "wof:name": "PE33 0FA",
    "wof:placetype": "postalcode"
  },
  "geometry": {"coordinates":[0.391854,52.671014],"type":"Point"}
}
