{
  "type": "Feature",
  "properties": {
    "iso:country":"GB",
    "wof:name":"PE33 0FA",
    "wof:placetype":"postalcode"
},
  "geometry": {"coordinates":[0.39096707806858,52.67106456010513],"type":"Point"}
}