{
  "type": "Feature",
  "properties": {
    "iso:country": "GB",
    "wof:name": "TR8 5BH",
    "wof:placetype": "postalcode"
  },
  "geometry": {"coordinates":[-4.958119,50.364963],"type":"Point"}
}
