{
  "type": "Feature",
  "properties": {
    "iso:country":"GB",
    "wof:name":"TR8 5BH",
    "wof:placetype":"postalcode"
},
  "geometry": {"coordinates":[-4.95815892972583,50.36518700207743],"type":"Point"}
}