{
  "type": "Feature",
  "properties": {
    "iso:country":"GB",
    "wof:name":"SS14 3PS",
    "wof:placetype":"postalcode"
},
  "geometry": {"coordinates":[0.49027563582762,51.57959355956084],"type":"Point"}
}