{
  "type": "Feature",
  "properties": {
    "iso:country": "GB",
    "wof:name": "RM13 7UJ",
    "wof:placetype": "postalcode"
  },
  "geometry": {"coordinates":[0.186977,51.53277],"type":"Point"}
}
