{
  "type": "Feature",
  "properties": {
    "iso:country":"GB",
    "wof:name":"ST2 9PN",
    "wof:placetype":"postalcode"
},
  "geometry": {"coordinates":[-2.15255891816373,53.01412201149686],"type":"Point"}
}