{
  "type": "Feature",
  "properties": {
    "iso:country":"GB",
    "wof:name":"RG4 9QL",
    "wof:placetype":"postalcode"
},
  "geometry": {"coordinates":[-0.93692973933627,51.48728288393355],"type":"Point"}
}