{
  "type": "Feature",
  "properties": {
    "iso:country":"GB",
    "wof:name":"CF15 7TL",
    "wof:placetype":"postalcode"
},
  "geometry": {"coordinates":[-3.26643098843456,51.56221966292934],"type":"Point"}
}