{
  "type": "Feature",
  "properties": {
    "iso:country": "GB",
    "wof:name": "CF15 7TL",
    "wof:placetype": "postalcode"
  },
  "geometry": {"coordinates":[-3.266431,51.56222],"type":"Point"}
}
