{
  "type": "Feature",
  "properties": {
    "iso:country":"GB",
    "wof:name":"E10 6AW",
    "wof:placetype":"postalcode"
},
  "geometry": {"coordinates":[-0.00963645743719,51.5770255820763],"type":"Point"}
}