{
  "type": "Feature",
  "properties": {
    "date:inception_lower": "1980-01-01",
    "date:inception_upper": "1980-01-01",
    "iso:country": "GB",
    "wof:name": "EX3 0QJ",
    "wof:placetype": "postalcode"
  },
  "geometry": {"coordinates":[-3.446106,50.686288],"type":"Point"}
}
