{
  "type": "Feature",
  "properties": {
    "date:inception_lower":"1980-01-01",
    "date:inception_upper":"1980-01-31",
    "iso:country":"GB",
    "wof:name":"EX3 0QJ",
    "wof:placetype":"postalcode"
},
  "geometry": {"coordinates":[-3.449824,50.684724],"type":"Point"}
}