{
  "type": "Feature",
  "properties": {
    "iso:country": "GB",
    "wof:name": "EX3 0QJ",
    "wof:placetype": "postalcode"
  },
  "geometry": {"coordinates":[-3.449824,50.684724],"type":"Point"}
}
