{
  "type": "Feature",
  "properties": {
    "iso:country": "GB",
    "wof:name": "GL16 9BG",
    "wof:placetype": "postalcode"
  },
  "geometry": {"coordinates":[-2.617246,51.792718],"type":"Point"}
}
