{
  "type": "Feature",
  "properties": {
    "iso:country": "GB",
    "wof:name": "CO15 1XN",
    "wof:placetype": "postalcode"
  },
  "geometry": {"coordinates":[1.138345,51.780716],"type":"Point"}
}
