{
  "type": "Feature",
  "properties": {
    "date:inception_lower":"1997-06-01",
    "date:inception_upper":"1997-06-30",
    "iso:country":"GB",
    "wof:name":"CO15 1XN",
    "wof:placetype":"postalcode"
},
  "geometry": {"coordinates":[1.138345,51.780716],"type":"Point"}
}