{
  "type": "Feature",
  "properties": {
    "iso:country":"GB",
    "wof:name":"SY16 2JE",
    "wof:placetype":"postalcode"
},
  "geometry": {"coordinates":[-3.30881699622067,52.51542446265895],"type":"Point"}
}