{
  "type": "Feature",
  "properties": {
    "iso:country":"GB",
    "wof:name":"M21 0GY",
    "wof:placetype":"postalcode"
},
  "geometry": {"coordinates":[-2.26967861700747,53.44664573064049],"type":"Point"}
}