{
  "type": "Feature",
  "properties": {
    "date:inception_lower": "2017-09-01",
    "date:inception_upper": "2017-09-01",
    "iso:country": "GB",
    "wof:name": "WA7 5GH",
    "wof:placetype": "postalcode"
  },
  "geometry": {"coordinates":[-2.731469,53.337642],"type":"Point"}
}
