{
  "type": "Feature",
  "properties": {
    "iso:country":"GB",
    "wof:name":"SK11 8EW",
    "wof:placetype":"postalcode"
},
  "geometry": {"coordinates":[-2.13487685255206,53.25564997263054],"type":"Point"}
}