{
  "type": "Feature",
  "properties": {
    "date:inception_lower": "1980-01-01",
    "date:inception_upper": "1980-01-01",
    "iso:country": "GB",
    "wof:name": "SK11 8EW",
    "wof:placetype": "postalcode"
  },
  "geometry": {"coordinates":[-2.134874,53.255667],"type":"Point"}
}
