{
  "type": "Feature",
  "properties": {
    "iso:country":"GB",
    "wof:name":"WD7 7FD",
    "wof:placetype":"postalcode"
},
  "geometry": {"coordinates":[-0.31740256038608,51.69338933716207],"type":"Point"}
}