{
  "type": "Feature",
  "properties": {
    "iso:country":"GB",
    "wof:name":"W1U 7HQ",
    "wof:placetype":"postalcode"
},
  "geometry": {"coordinates":[-0.15463344157097,51.51796795858836],"type":"Point"}
}