{
  "type": "Feature",
  "properties": {
    "iso:country":"GB",
    "wof:name":"WV5 0EW",
    "wof:placetype":"postalcode"
},
  "geometry": {"coordinates":[-2.19765979132644,52.52987063403542],"type":"Point"}
}