{
  "type": "Feature",
  "properties": {
    "date:inception_lower": "1993-08-01",
    "date:inception_upper": "1993-08-01",
    "iso:country": "GB",
    "wof:name": "LL29 8SD",
    "wof:placetype": "postalcode"
  },
  "geometry": {"coordinates":[-3.669551,53.283632],"type":"Point"}
}
