{
  "type": "Feature",
  "properties": {
    "iso:country":"GB",
    "wof:name":"UB10 9HR",
    "wof:placetype":"postalcode"
},
  "geometry": {"coordinates":[-0.44750654952577,51.54097634278353],"type":"Point"}
}