{
  "type": "Feature",
  "properties": {
    "date:inception_lower": "1980-01-01",
    "date:inception_upper": "1980-01-01",
    "iso:country": "GB",
    "wof:name": "SA3 3DQ",
    "wof:placetype": "postalcode"
  },
  "geometry": {"coordinates":[-4.045434,51.583254],"type":"Point"}
}
