{
  "type": "Feature",
  "properties": {
    "iso:country": "GB",
    "wof:name": "SA3 3DQ",
    "wof:placetype": "postalcode"
  },
  "geometry": {"coordinates":[-4.045434,51.583254],"type":"Point"}
}
