{
  "type": "Feature",
  "properties": {
    "iso:country":"GB",
    "wof:name":"SA3 3DQ",
    "wof:placetype":"postalcode"
},
  "geometry": {"coordinates":[-4.04543391374852,51.58325442074126],"type":"Point"}
}