{
  "type": "Feature",
  "properties": {
    "iso:country": "GB",
    "wof:name": "BD22 6PA",
    "wof:placetype": "postalcode"
  },
  "geometry": {"coordinates":[-1.934309,53.871336],"type":"Point"}
}
