{
  "type": "Feature",
  "properties": {
    "iso:country":"GB",
    "wof:name":"HD7 5TQ",
    "wof:placetype":"postalcode"
},
  "geometry": {"coordinates":[-1.8424834351059,53.63114445403277],"type":"Point"}
}