{
  "type": "Feature",
  "properties": {
    "date:inception_lower": "2005-07-01",
    "date:inception_upper": "2005-07-01",
    "iso:country": "GB",
    "wof:name": "RH10 7PB",
    "wof:placetype": "postalcode"
  },
  "geometry": {"coordinates":[-0.149044,51.120022],"type":"Point"}
}
