{
  "type": "Feature",
  "properties": {
    "iso:country":"GB",
    "wof:name":"RH10 7PB",
    "wof:placetype":"postalcode"
},
  "geometry": {"coordinates":[-0.14904376563789,51.12002193588489],"type":"Point"}
}