{
  "type": "Feature",
  "properties": {
    "date:inception_lower":"1980-01-01",
    "date:inception_upper":"1980-01-31",
    "iso:country":"GB",
    "wof:name":"LE4 2TL",
    "wof:placetype":"postalcode"
},
  "geometry": {"coordinates":[-1.135056,52.662915],"type":"Point"}
}