{
  "type": "Feature",
  "properties": {
    "iso:country":"GB",
    "wof:name":"LE4 2TL",
    "wof:placetype":"postalcode"
},
  "geometry": {"coordinates":[-1.13505636471917,52.66291524252634],"type":"Point"}
}