{
  "type": "Feature",
  "properties": {
    "iso:country":"GB",
    "wof:name":"NE25 8SS",
    "wof:placetype":"postalcode"
},
  "geometry": {"coordinates":[-1.4673872064631,55.03938530053019],"type":"Point"}
}