{
  "type": "Feature",
  "properties": {
    "iso:country": "GB",
    "wof:name": "NE25 8SS",
    "wof:placetype": "postalcode"
  },
  "geometry": {"coordinates":[-1.467387,55.039385],"type":"Point"}
}
