{
  "type": "Feature",
  "properties": {
    "iso:country":"GB",
    "wof:name":"B33 0LP",
    "wof:placetype":"postalcode"
},
  "geometry": {"coordinates":[-1.76203426346126,52.47635223203331],"type":"Point"}
}