{
  "type": "Feature",
  "properties": {
    "iso:country":"GB",
    "wof:name":"E17 8JQ",
    "wof:placetype":"postalcode"
},
  "geometry": {"coordinates":[-0.02444220476322,51.5717453564937],"type":"Point"}
}