{
  "type": "Feature",
  "properties": {
    "iso:country": "GB",
    "wof:name": "PL4 8HZ",
    "wof:placetype": "postalcode"
  },
  "geometry": {"coordinates":[-4.136287,50.377191],"type":"Point"}
}
