{
  "type": "Feature",
  "properties": {
    "iso:country":"GB",
    "wof:name":"PL4 8HZ",
    "wof:placetype":"postalcode"
},
  "geometry": {"coordinates":[-4.13628731175651,50.37719052591554],"type":"Point"}
}