{
  "type": "Feature",
  "properties": {
    "iso:country": "GB",
    "wof:name": "M25 9RT",
    "wof:placetype": "postalcode"
  },
  "geometry": {"coordinates":[-2.282525,53.521957],"type":"Point"}
}
