{
  "type": "Feature",
  "properties": {
    "iso:country":"GB",
    "wof:name":"M25 9RT",
    "wof:placetype":"postalcode"
},
  "geometry": {"coordinates":[-2.28252516907388,53.52195729473455],"type":"Point"}
}