{
  "type": "Feature",
  "properties": {
    "date:inception_lower": "1996-06-01",
    "date:inception_upper": "1996-06-01",
    "iso:country": "GB",
    "wof:name": "AB56 4PY",
    "wof:placetype": "postalcode"
  },
  "geometry": {"coordinates":[-2.898558,57.697958],"type":"Point"}
}
