{
  "type": "Feature",
  "properties": {
    "iso:country":"GB",
    "wof:name":"PR7 1HR",
    "wof:placetype":"postalcode"
},
  "geometry": {"coordinates":[-2.63607205221404,53.65369020847771],"type":"Point"}
}