{
  "type": "Feature",
  "properties": {
    "iso:country":"GB",
    "wof:name":"BS10 5DX",
    "wof:placetype":"postalcode"
},
  "geometry": {"coordinates":[-2.60101607982392,51.49517881729505],"type":"Point"}
}