{
  "type": "Feature",
  "properties": {
    "iso:country":"GB",
    "wof:name":"BH6 4AD",
    "wof:placetype":"postalcode"
},
  "geometry": {"coordinates":[-1.79256868617882,50.72173441118861],"type":"Point"}
}