{
  "type": "Feature",
  "properties": {
    "iso:country":"GB",
    "wof:name":"MK42 7LS",
    "wof:placetype":"postalcode"
},
  "geometry": {"coordinates":[-0.48867895609643,52.11410498025635],"type":"Point"}
}