{
  "type": "Feature",
  "properties": {
    "iso:country": "GB",
    "wof:name": "IP4 5PJ",
    "wof:placetype": "postalcode"
  },
  "geometry": {"coordinates":[1.202888,52.06131],"type":"Point"}
}
