{
  "type": "Feature",
  "properties": {
    "iso:country":"GB",
    "wof:name":"IP4 5PJ",
    "wof:placetype":"postalcode"
},
  "geometry": {"coordinates":[1.20288824424914,52.06130962562933],"type":"Point"}
}