{
  "type": "Feature",
  "properties": {
    "iso:country": "GB",
    "wof:name": "CF5 6EN",
    "wof:placetype": "postalcode"
  },
  "geometry": {"coordinates":[-3.270385,51.478381],"type":"Point"}
}
