{
  "type": "Feature",
  "properties": {
    "iso:country":"GB",
    "wof:name":"NN1 5QL",
    "wof:placetype":"postalcode"
},
  "geometry": {"coordinates":[-0.88774824070465,52.23804145656892],"type":"Point"}
}