{
  "type": "Feature",
  "properties": {
    "iso:country":"GB",
    "wof:name":"SK15 1JE",
    "wof:placetype":"postalcode"
},
  "geometry": {"coordinates":[-2.06346396629343,53.49402418859228],"type":"Point"}
}