{
  "type": "Feature",
  "properties": {
    "iso:country":"GB",
    "wof:name":"NR27 9QJ",
    "wof:placetype":"postalcode"
},
  "geometry": {"coordinates":[1.2465240581994,52.93605243866146],"type":"Point"}
}