{
  "type": "Feature",
  "properties": {
    "date:inception_lower": "2000-12-01",
    "date:inception_upper": "2000-12-01",
    "iso:country": "GB",
    "wof:name": "LL13 8HL",
    "wof:placetype": "postalcode"
  },
  "geometry": {"coordinates":[-2.98598,53.049891],"type":"Point"}
}
