{
  "type": "Feature",
  "properties": {
    "iso:country": "GB",
    "wof:name": "LL13 8HL",
    "wof:placetype": "postalcode"
  },
  "geometry": {"coordinates":[-2.98598,53.049891],"type":"Point"}
}
