{
  "type": "Feature",
  "properties": {
    "date:inception_lower": "2008-03-01",
    "date:inception_upper": "2008-03-01",
    "iso:country": "GB",
    "wof:name": "NG22 9FD",
    "wof:placetype": "postalcode"
  },
  "geometry": {"coordinates":[-1.004586,53.199247],"type":"Point"}
}
