{
  "type": "Feature",
  "properties": {
    "iso:country": "GB",
    "wof:name": "SE15 5AN",
    "wof:placetype": "postalcode"
  },
  "geometry": {"coordinates":[-0.080448,51.470277],"type":"Point"}
}
