{
  "type": "Feature",
  "properties": {
    "iso:country":"GB",
    "wof:name":"SE15 5AN",
    "wof:placetype":"postalcode"
},
  "geometry": {"coordinates":[-0.08044783710705,51.47027656734807],"type":"Point"}
}