{
  "type": "Feature",
  "properties": {
    "iso:country":"GB",
    "wof:name":"NG5 6AT",
    "wof:placetype":"postalcode"
},
  "geometry": {"coordinates":[-1.14114543326867,52.99729524610434],"type":"Point"}
}