{
  "type": "Feature",
  "properties": {
    "date:inception_lower": "1980-01-01",
    "date:inception_upper": "1980-01-01",
    "iso:country": "GB",
    "wof:name": "NG5 6AT",
    "wof:placetype": "postalcode"
  },
  "geometry": {"coordinates":[-1.141618,52.997372],"type":"Point"}
}
