{
  "type": "Feature",
  "properties": {
    "iso:country":"GB",
    "wof:name":"TD2 6TG",
    "wof:placetype":"postalcode"
},
  "geometry": {"coordinates":[-2.75076206799553,55.72074498740855],"type":"Point"}
}