{
  "type": "Feature",
  "properties": {
    "iso:country":"GB",
    "wof:name":"OX39 4DF",
    "wof:placetype":"postalcode"
},
  "geometry": {"coordinates":[-0.91001447915684,51.69406062005302],"type":"Point"}
}