{
  "type": "Feature",
  "properties": {
    "date:inception_lower": "2012-03-01",
    "date:inception_upper": "2012-03-01",
    "iso:country": "GB",
    "wof:name": "OX39 4DF",
    "wof:placetype": "postalcode"
  },
  "geometry": {"coordinates":[-0.910225,51.693995],"type":"Point"}
}
