{
  "type": "Feature",
  "properties": {
    "iso:country": "GB",
    "wof:name": "M1 6JB",
    "wof:placetype": "postalcode"
  },
  "geometry": {"coordinates":[-2.238347,53.476338],"type":"Point"}
}
