{
  "type": "Feature",
  "properties": {
    "iso:country": "GB",
    "wof:name": "NG17 7QR",
    "wof:placetype": "postalcode"
  },
  "geometry": {"coordinates":[-1.222693,53.084342],"type":"Point"}
}
