{
  "type": "Feature",
  "properties": {
    "iso:country":"GB",
    "wof:name":"NG17 7QR",
    "wof:placetype":"postalcode"
},
  "geometry": {"coordinates":[-1.22269327232045,53.08434245054586],"type":"Point"}
}