{
  "type": "Feature",
  "properties": {
    "iso:country":"GB",
    "wof:name":"LU7 3QX",
    "wof:placetype":"postalcode"
},
  "geometry": {"coordinates":[-0.64930266707063,51.91456881663525],"type":"Point"}
}