{
  "type": "Feature",
  "properties": {
    "iso:country":"GB",
    "wof:name":"DE11 7DW",
    "wof:placetype":"postalcode"
},
  "geometry": {"coordinates":[-1.5268628051205,52.76299677761875],"type":"Point"}
}