{
  "type": "Feature",
  "properties": {
    "iso:country": "GB",
    "wof:name": "TF4 2BN",
    "wof:placetype": "postalcode"
  },
  "geometry": {"coordinates":[-2.465153,52.676671],"type":"Point"}
}
