{
  "type": "Feature",
  "properties": {
    "iso:country":"GB",
    "wof:name":"TF4 2BN",
    "wof:placetype":"postalcode"
},
  "geometry": {"coordinates":[-2.46515269238204,52.67667149519247],"type":"Point"}
}