{
  "type": "Feature",
  "properties": {
    "iso:country":"GB",
    "wof:name":"TQ12 1PX",
    "wof:placetype":"postalcode"
},
  "geometry": {"coordinates":[-3.62403780407306,50.5352112263805],"type":"Point"}
}