{
  "type": "Feature",
  "properties": {
    "date:inception_lower": "1980-01-01",
    "date:inception_upper": "1980-01-01",
    "iso:country": "GB",
    "wof:name": "TQ12 1PX",
    "wof:placetype": "postalcode"
  },
  "geometry": {"coordinates":[-3.624038,50.535211],"type":"Point"}
}
