{
  "type": "Feature",
  "properties": {
    "iso:country":"GB",
    "wof:name":"G12 9NB",
    "wof:placetype":"postalcode"
},
  "geometry": {"coordinates":[-4.29642068335679,55.87913283041662],"type":"Point"}
}