{
  "type": "Feature",
  "properties": {
    "iso:country":"GB",
    "wof:name":"ST16 3EE",
    "wof:placetype":"postalcode"
},
  "geometry": {"coordinates":[-2.10901255008432,52.82776809254981],"type":"Point"}
}