{
  "type": "Feature",
  "properties": {
    "iso:country":"GB",
    "wof:name":"SY25 6PU",
    "wof:placetype":"postalcode"
},
  "geometry": {"coordinates":[-3.98883846147912,52.19995580716937],"type":"Point"}
}