{
  "type": "Feature",
  "properties": {
    "iso:country":"GB",
    "wof:name":"DD4 6EH",
    "wof:placetype":"postalcode"
},
  "geometry": {"coordinates":[-2.95784637464119,56.46727985633625],"type":"Point"}
}