{
  "type": "Feature",
  "properties": {
    "date:inception_lower":"1980-01-01",
    "date:inception_upper":"1980-01-31",
    "iso:country":"GB",
    "wof:name":"DD4 6EH",
    "wof:placetype":"postalcode"
},
  "geometry": {"coordinates":[-2.957846,56.46728],"type":"Point"}
}