{
  "type": "Feature",
  "properties": {
    "iso:country": "GB",
    "wof:name": "ME12 1XT",
    "wof:placetype": "postalcode"
  },
  "geometry": {"coordinates":[0.765467,51.434348],"type":"Point"}
}
