{
  "type": "Feature",
  "properties": {
    "iso:country": "GB",
    "wof:name": "LE15 6JQ",
    "wof:placetype": "postalcode"
  },
  "geometry": {"coordinates":[-0.725711,52.665101],"type":"Point"}
}
