{
  "type": "Feature",
  "properties": {
    "iso:country":"GB",
    "wof:name":"GL4 6BG",
    "wof:placetype":"postalcode"
},
  "geometry": {"coordinates":[-2.22809163444355,51.85165955182588],"type":"Point"}
}