{
  "type": "Feature",
  "properties": {
    "date:inception_lower": "1980-01-01",
    "date:inception_upper": "1980-01-01",
    "iso:country": "GB",
    "wof:name": "G20 0SH",
    "wof:placetype": "postalcode"
  },
  "geometry": {"coordinates":[-4.28228,55.896176],"type":"Point"}
}
