{
  "type": "Feature",
  "properties": {
    "iso:country":"GB",
    "wof:name":"RG22 4NP",
    "wof:placetype":"postalcode"
},
  "geometry": {"coordinates":[-1.10389431315575,51.24238863788688],"type":"Point"}
}