{
  "type": "Feature",
  "properties": {
    "date:inception_lower": "1983-07-01",
    "date:inception_upper": "1983-07-01",
    "iso:country": "GB",
    "wof:name": "RG22 4NP",
    "wof:placetype": "postalcode"
  },
  "geometry": {"coordinates":[-1.103894,51.242389],"type":"Point"}
}
