{
  "type": "Feature",
  "properties": {
    "iso:country": "GB",
    "wof:name": "RG22 4NP",
    "wof:placetype": "postalcode"
  },
  "geometry": {"coordinates":[-1.103894,51.242389],"type":"Point"}
}
