{
  "type": "Feature",
  "properties": {
    "iso:country":"GB",
    "wof:name":"SK4 4AU",
    "wof:placetype":"postalcode"
},
  "geometry": {"coordinates":[-2.19038234996786,53.42422841202026],"type":"Point"}
}