{
  "type": "Feature",
  "properties": {
    "date:inception_lower":"1980-01-01",
    "date:inception_upper":"1980-01-31",
    "iso:country":"GB",
    "wof:name":"N18 2SF",
    "wof:placetype":"postalcode"
},
  "geometry": {"coordinates":[-0.063161,51.609053],"type":"Point"}
}