{
  "type": "Feature",
  "properties": {
    "iso:country":"GB",
    "wof:name":"N18 2SF",
    "wof:placetype":"postalcode"
},
  "geometry": {"coordinates":[-0.06316097374456,51.60905323090982],"type":"Point"}
}