{
  "type": "Feature",
  "properties": {
    "iso:country":"GB",
    "wof:name":"DN14 8HD",
    "wof:placetype":"postalcode"
},
  "geometry": {"coordinates":[-0.79059388432723,53.69790469716452],"type":"Point"}
}