{
  "type": "Feature",
  "properties": {
    "iso:country":"GB",
    "wof:name":"TQ7 4AZ",
    "wof:placetype":"postalcode"
},
  "geometry": {"coordinates":[-3.89410431339172,50.2853755422522],"type":"Point"}
}