{
  "type": "Feature",
  "properties": {
    "date:inception_lower": "2023-06-01",
    "date:inception_upper": "2023-06-01",
    "iso:country": "GB",
    "wof:name": "LN4 3FZ",
    "wof:placetype": "postalcode"
  },
  "geometry": {"coordinates":[-0.404269,53.126173],"type":"Point"}
}
