{
  "type": "Feature",
  "properties": {
    "iso:country": "GB",
    "wof:name": "SY8 1EL",
    "wof:placetype": "postalcode"
  },
  "geometry": {"coordinates":[-2.729952,52.380318],"type":"Point"}
}
