{
  "type": "Feature",
  "properties": {
    "iso:country":"GB",
    "wof:name":"SY8 1EL",
    "wof:placetype":"postalcode"
},
  "geometry": {"coordinates":[-2.72995251160905,52.38031774107539],"type":"Point"}
}