{
  "type": "Feature",
  "properties": {
    "iso:country":"GB",
    "wof:name":"LE12 6LT",
    "wof:placetype":"postalcode"
},
  "geometry": {"coordinates":[-1.17261207875159,52.82957550749509],"type":"Point"}
}