{
  "type": "Feature",
  "properties": {
    "iso:country":"GB",
    "wof:name":"S71 4BF",
    "wof:placetype":"postalcode"
},
  "geometry": {"coordinates":[-1.46686557695702,53.59910588126357],"type":"Point"}
}