{
  "type": "Feature",
  "properties": {
    "date:inception_lower": "2012-02-01",
    "date:inception_upper": "2012-02-01",
    "iso:country": "GB",
    "wof:name": "S71 4BF",
    "wof:placetype": "postalcode"
  },
  "geometry": {"coordinates":[-1.466866,53.599106],"type":"Point"}
}
