{
  "type": "Feature",
  "properties": {
    "date:inception_lower": "1980-01-01",
    "date:inception_upper": "1980-01-01",
    "iso:country": "GB",
    "wof:name": "IP4 4HF",
    "wof:placetype": "postalcode"
  },
  "geometry": {"coordinates":[1.177994,52.06417],"type":"Point"}
}
