{
  "type": "Feature",
  "properties": {
    "iso:country": "GB",
    "wof:name": "PH16 5DX",
    "wof:placetype": "postalcode"
  },
  "geometry": {"coordinates":[-3.726353,56.700265],"type":"Point"}
}
