{
  "type": "Feature",
  "properties": {
    "iso:country": "GB",
    "wof:name": "PO40 9RH",
    "wof:placetype": "postalcode"
  },
  "geometry": {"coordinates":[-1.517605,50.676299],"type":"Point"}
}
