{
  "type": "Feature",
  "properties": {
    "date:inception_lower":"1987-04-01",
    "date:inception_upper":"1987-04-30",
    "iso:country":"GB",
    "wof:name":"PO40 9RH",
    "wof:placetype":"postalcode"
},
  "geometry": {"coordinates":[-1.517605,50.676299],"type":"Point"}
}