{
  "type": "Feature",
  "properties": {
    "iso:country":"GB",
    "wof:name":"PO40 9RH",
    "wof:placetype":"postalcode"
},
  "geometry": {"coordinates":[-1.51761464980086,50.67627262239993],"type":"Point"}
}