{
  "type": "Feature",
  "properties": {
    "date:inception_lower": "1980-01-01",
    "date:inception_upper": "1980-01-01",
    "iso:country": "GB",
    "wof:name": "NE43 7NT",
    "wof:placetype": "postalcode"
  },
  "geometry": {"coordinates":[-1.906604,54.94773],"type":"Point"}
}
