{
  "type": "Feature",
  "properties": {
    "iso:country":"GB",
    "wof:name":"NE43 7NT",
    "wof:placetype":"postalcode"
},
  "geometry": {"coordinates":[-1.90664141011875,54.94766860258705],"type":"Point"}
}