{
  "type": "Feature",
  "properties": {
    "date:inception_lower": "2018-05-01",
    "date:inception_upper": "2018-05-01",
    "iso:country": "GB",
    "wof:name": "CV34 7BQ",
    "wof:placetype": "postalcode"
  },
  "geometry": {"coordinates":[-1.552056,52.264525],"type":"Point"}
}
