{
  "type": "Feature",
  "properties": {
    "iso:country":"GB",
    "wof:name":"WD25 7NA",
    "wof:placetype":"postalcode"
},
  "geometry": {"coordinates":[-0.41573305972519,51.6946216782327],"type":"Point"}
}