{
  "type": "Feature",
  "properties": {
    "iso:country": "GB",
    "wof:name": "WD25 7NA",
    "wof:placetype": "postalcode"
  },
  "geometry": {"coordinates":[-0.415419,51.695109],"type":"Point"}
}
