{
  "type": "Feature",
  "properties": {
    "date:inception_lower": "1980-01-01",
    "date:inception_upper": "1980-01-01",
    "iso:country": "GB",
    "wof:name": "FY1 1RN",
    "wof:placetype": "postalcode"
  },
  "geometry": {"coordinates":[-3.053693,53.821996],"type":"Point"}
}
