{
  "type": "Feature",
  "properties": {
    "iso:country":"GB",
    "wof:name":"FY1 1RN",
    "wof:placetype":"postalcode"
},
  "geometry": {"coordinates":[-3.0538855668207,53.82223233194419],"type":"Point"}
}