{
  "type": "Feature",
  "properties": {
    "iso:country": "GB",
    "wof:name": "LU7 9RX",
    "wof:placetype": "postalcode"
  },
  "geometry": {"coordinates":[-0.586738,51.931745],"type":"Point"}
}
