{
  "type": "Feature",
  "properties": {
    "iso:country":"GB",
    "wof:name":"LU7 9RX",
    "wof:placetype":"postalcode"
},
  "geometry": {"coordinates":[-0.58673808884213,51.93174527522976],"type":"Point"}
}