{
  "type": "Feature",
  "properties": {
    "date:inception_lower":"2011-08-01",
    "date:inception_upper":"2011-08-31",
    "iso:country":"GB",
    "wof:name":"LU7 9RX",
    "wof:placetype":"postalcode"
},
  "geometry": {"coordinates":[-0.586738,51.931745],"type":"Point"}
}