{
  "type": "Feature",
  "properties": {
    "iso:country": "GB",
    "wof:name": "BN1 2RD",
    "wof:placetype": "postalcode"
  },
  "geometry": {"coordinates":[-0.144203,50.823339],"type":"Point"}
}
