{
  "type": "Feature",
  "properties": {
    "date:inception_lower": "1980-01-01",
    "date:inception_upper": "1980-01-01",
    "iso:country": "GB",
    "wof:name": "TQ2 6HT",
    "wof:placetype": "postalcode"
  },
  "geometry": {"coordinates":[-3.547592,50.462122],"type":"Point"}
}
