{
  "type": "Feature",
  "properties": {
    "iso:country":"GB",
    "wof:name":"N16 9NX",
    "wof:placetype":"postalcode"
},
  "geometry": {"coordinates":[-0.08735621720605,51.55533327491367],"type":"Point"}
}