{
  "type": "Feature",
  "properties": {
    "date:inception_lower": "1980-01-01",
    "date:inception_upper": "1980-01-01",
    "iso:country": "GB",
    "wof:name": "TN27 9EE",
    "wof:placetype": "postalcode"
  },
  "geometry": {"coordinates":[0.715138,51.185808],"type":"Point"}
}
