{
  "type": "Feature",
  "properties": {
    "date:inception_lower": "2021-07-01",
    "date:inception_upper": "2021-07-01",
    "iso:country": "GB",
    "wof:name": "GU6 8WQ",
    "wof:placetype": "postalcode"
  },
  "geometry": {"coordinates":[-0.504444,51.139942],"type":"Point"}
}
