{
  "type": "Feature",
  "properties": {
    "iso:country":"GB",
    "wof:name":"S42 7LN",
    "wof:placetype":"postalcode"
},
  "geometry": {"coordinates":[-1.4864704219527,53.21365933595278],"type":"Point"}
}