{
  "type": "Feature",
  "properties": {
    "date:inception_lower": "1980-01-01",
    "date:inception_upper": "1980-01-01",
    "iso:country": "GB",
    "wof:name": "S42 7LN",
    "wof:placetype": "postalcode"
  },
  "geometry": {"coordinates":[-1.486469,53.213642],"type":"Point"}
}
