{
  "type": "Feature",
  "properties": {
    "iso:country":"GB",
    "wof:name":"CB6 1JH",
    "wof:placetype":"postalcode"
},
  "geometry": {"coordinates":[0.30113055527207,52.45954196669064],"type":"Point"}
}