{
  "type": "Feature",
  "properties": {
    "iso:country": "GB",
    "wof:name": "KY10 3SQ",
    "wof:placetype": "postalcode"
  },
  "geometry": {"coordinates":[-2.626677,56.259941],"type":"Point"}
}
