{
  "type": "Feature",
  "properties": {
    "iso:country":"GB",
    "wof:name":"M18 8QN",
    "wof:placetype":"postalcode"
},
  "geometry": {"coordinates":[-2.16377499393002,53.4667205952051],"type":"Point"}
}