{
  "type": "Feature",
  "properties": {
    "iso:country":"GB",
    "wof:name":"GL20 5NU",
    "wof:placetype":"postalcode"
},
  "geometry": {"coordinates":[-2.1559406579948,51.99536085817905],"type":"Point"}
}