{
  "type": "Feature",
  "properties": {
    "iso:country": "GB",
    "wof:name": "IP33 3HJ",
    "wof:placetype": "postalcode"
  },
  "geometry": {"coordinates":[0.682942,52.249816],"type":"Point"}
}
