{
  "type": "Feature",
  "properties": {
    "iso:country":"GB",
    "wof:name":"IP33 3HJ",
    "wof:placetype":"postalcode"
},
  "geometry": {"coordinates":[0.68294162848827,52.249815748408],"type":"Point"}
}