{
  "type": "Feature",
  "properties": {
    "iso:country":"GB",
    "wof:name":"NE65 9JH",
    "wof:placetype":"postalcode"
},
  "geometry": {"coordinates":[-1.74411424896183,55.32432566106124],"type":"Point"}
}