{
  "type": "Feature",
  "properties": {
    "iso:country":"GB",
    "wof:name":"HA3 6NS",
    "wof:placetype":"postalcode"
},
  "geometry": {"coordinates":[-0.358393799455,51.6049297419902],"type":"Point"}
}