{
  "type": "Feature",
  "properties": {
    "iso:country":"GB",
    "wof:name":"GL5 5DF",
    "wof:placetype":"postalcode"
},
  "geometry": {"coordinates":[-2.2134344931556,51.72104732121762],"type":"Point"}
}