{
  "type": "Feature",
  "properties": {
    "date:inception_lower":"1980-01-01",
    "date:inception_upper":"1980-01-31",
    "iso:country":"GB",
    "wof:name":"GL5 5DF",
    "wof:placetype":"postalcode"
},
  "geometry": {"coordinates":[-2.213434,51.721047],"type":"Point"}
}