{
  "type": "Feature",
  "properties": {
    "iso:country": "GB",
    "wof:name": "EX38 8ET",
    "wof:placetype": "postalcode"
  },
  "geometry": {"coordinates":[-4.139112,50.951162],"type":"Point"}
}
