{
  "type": "Feature",
  "properties": {
    "date:inception_lower":"1992-08-01",
    "date:inception_upper":"1992-08-31",
    "iso:country":"GB",
    "wof:name":"EX38 8ET",
    "wof:placetype":"postalcode"
},
  "geometry": {"coordinates":[-4.139112,50.951162],"type":"Point"}
}