{
  "type": "Feature",
  "properties": {
    "iso:country":"GB",
    "wof:name":"EX38 8ET",
    "wof:placetype":"postalcode"
},
  "geometry": {"coordinates":[-4.13911247604909,50.95116168140804],"type":"Point"}
}