{
  "type": "Feature",
  "properties": {
    "iso:country":"GB",
    "wof:name":"AB24 3HT",
    "wof:placetype":"postalcode"
},
  "geometry": {"coordinates":[-2.09978066875942,57.157769156],"type":"Point"}
}