{
  "type": "Feature",
  "properties": {
    "iso:country":"GB",
    "wof:name":"PO7 8BE",
    "wof:placetype":"postalcode"
},
  "geometry": {"coordinates":[-1.02608056804362,50.86457093383888],"type":"Point"}
}