{
  "type": "Feature",
  "properties": {
    "iso:country":"GB",
    "wof:name":"EN1 4RF",
    "wof:placetype":"postalcode"
},
  "geometry": {"coordinates":[-0.04944279201405,51.67904799002506],"type":"Point"}
}