{
  "type": "Feature",
  "properties": {
    "iso:country":"GB",
    "wof:name":"CH63 7NY",
    "wof:placetype":"postalcode"
},
  "geometry": {"coordinates":[-3.00487499013468,53.35481026884238],"type":"Point"}
}