{
  "type": "Feature",
  "properties": {
    "date:inception_lower": "1999-06-01",
    "date:inception_upper": "1999-06-01",
    "iso:country": "GB",
    "wof:name": "CH63 7NY",
    "wof:placetype": "postalcode"
  },
  "geometry": {"coordinates":[-3.004875,53.35481],"type":"Point"}
}
