{
  "type": "Feature",
  "properties": {
    "iso:country":"GB",
    "wof:name":"FY4 5DZ",
    "wof:placetype":"postalcode"
},
  "geometry": {"coordinates":[-3.00845761836496,53.77453514389909],"type":"Point"}
}