{
  "type": "Feature",
  "properties": {
    "iso:country": "GB",
    "wof:name": "FY4 5DZ",
    "wof:placetype": "postalcode"
  },
  "geometry": {"coordinates":[-3.007818,53.774591],"type":"Point"}
}
