{
  "type": "Feature",
  "properties": {
    "iso:country": "GB",
    "wof:name": "CM9 4LG",
    "wof:placetype": "postalcode"
  },
  "geometry": {"coordinates":[0.680078,51.732977],"type":"Point"}
}
