{
  "type": "Feature",
  "properties": {
    "iso:country":"GB",
    "wof:name":"PO9 5NL",
    "wof:placetype":"postalcode"
},
  "geometry": {"coordinates":[-0.96912463986092,50.87436057972016],"type":"Point"}
}