{
  "type": "Feature",
  "properties": {
    "date:inception_lower":"1980-01-01",
    "date:inception_upper":"1980-01-31",
    "iso:country":"GB",
    "wof:name":"PO9 5NL",
    "wof:placetype":"postalcode"
},
  "geometry": {"coordinates":[-0.969125,50.874361],"type":"Point"}
}