{
  "type": "Feature",
  "properties": {
    "iso:country":"GB",
    "wof:name":"RH10 7EW",
    "wof:placetype":"postalcode"
},
  "geometry": {"coordinates":[-0.15015182280467,51.11553395690132],"type":"Point"}
}