{
  "type": "Feature",
  "properties": {
    "iso:country":"GB",
    "wof:name":"RM19 1GR",
    "wof:placetype":"postalcode"
},
  "geometry": {"coordinates":[0.23616810910566,51.48731821893617],"type":"Point"}
}