{
  "type": "Feature",
  "properties": {
    "iso:country": "GB",
    "wof:name": "RM19 1GR",
    "wof:placetype": "postalcode"
  },
  "geometry": {"coordinates":[0.236168,51.487318],"type":"Point"}
}
