{
  "type": "Feature",
  "properties": {
    "date:inception_lower": "1995-07-01",
    "date:inception_upper": "1995-07-01",
    "iso:country": "GB",
    "wof:name": "RM19 1GR",
    "wof:placetype": "postalcode"
  },
  "geometry": {"coordinates":[0.236168,51.487318],"type":"Point"}
}
