{
  "type": "Feature",
  "properties": {
    "iso:country":"GB",
    "wof:name":"W3 8SW",
    "wof:placetype":"postalcode"
},
  "geometry": {"coordinates":[-0.27528895340634,51.50229596866996],"type":"Point"}
}