{
  "type": "Feature",
  "properties": {
    "date:inception_lower": "1980-01-01",
    "date:inception_upper": "1980-01-01",
    "iso:country": "GB",
    "wof:name": "BA13 3BD",
    "wof:placetype": "postalcode"
  },
  "geometry": {"coordinates":[-2.183781,51.261758],"type":"Point"}
}
