{
  "type": "Feature",
  "properties": {
    "iso:country":"GB",
    "wof:name":"BD24 9DF",
    "wof:placetype":"postalcode"
},
  "geometry": {"coordinates":[-2.28237772969429,54.07115081926049],"type":"Point"}
}