{
  "type": "Feature",
  "properties": {
    "iso:country":"GB",
    "wof:name":"W1U 3DU",
    "wof:placetype":"postalcode"
},
  "geometry": {"coordinates":[-0.15224501331509,51.5175077105425],"type":"Point"}
}