{
  "type": "Feature",
  "properties": {
    "iso:country":"GB",
    "wof:name":"RG10 0EN",
    "wof:placetype":"postalcode"
},
  "geometry": {"coordinates":[-0.8601710133488,51.4603867024822],"type":"Point"}
}