{
  "type": "Feature",
  "properties": {
    "date:inception_lower": "1980-01-01",
    "date:inception_upper": "1980-01-01",
    "iso:country": "GB",
    "wof:name": "RG10 0EN",
    "wof:placetype": "postalcode"
  },
  "geometry": {"coordinates":[-0.860153,51.460388],"type":"Point"}
}
