{
  "type": "Feature",
  "properties": {
    "iso:country":"GB",
    "wof:name":"RG1 5DZ",
    "wof:placetype":"postalcode"
},
  "geometry": {"coordinates":[-0.96273899870303,51.44856128393872],"type":"Point"}
}