{
  "type": "Feature",
  "properties": {
    "iso:country": "GB",
    "wof:name": "RG26 3SQ",
    "wof:placetype": "postalcode"
  },
  "geometry": {"coordinates":[-1.128734,51.350552],"type":"Point"}
}
