{
  "type": "Feature",
  "properties": {
    "iso:country": "GB",
    "wof:name": "RG26 3SQ",
    "wof:placetype": "postalcode"
  },
  "geometry": {"coordinates":[-1.128792,51.350544],"type":"Point"}
}
