{
  "type": "Feature",
  "properties": {
    "iso:country":"GB",
    "wof:name":"RG26 3SQ",
    "wof:placetype":"postalcode"
},
  "geometry": {"coordinates":[-1.128753916623,51.35055223790433],"type":"Point"}
}