{
  "type": "Feature",
  "properties": {
    "date:inception_lower": "1995-07-01",
    "date:inception_upper": "1995-07-01",
    "iso:country": "GB",
    "wof:name": "RG26 3SQ",
    "wof:placetype": "postalcode"
  },
  "geometry": {"coordinates":[-1.128792,51.350544],"type":"Point"}
}
