{
  "type": "Feature",
  "properties": {
    "iso:country":"GB",
    "wof:name":"S71 4BU",
    "wof:placetype":"postalcode"
},
  "geometry": {"coordinates":[-1.43878488604832,53.60178192012935],"type":"Point"}
}