{
  "type": "Feature",
  "properties": {
    "date:inception_lower":"2009-10-01",
    "date:inception_upper":"2009-10-31",
    "iso:country":"GB",
    "wof:name":"S71 4BU",
    "wof:placetype":"postalcode"
},
  "geometry": {"coordinates":[-1.438655,53.601609],"type":"Point"}
}