{
  "type": "Feature",
  "properties": {
    "iso:country":"GB",
    "wof:name":"TR18 3JD",
    "wof:placetype":"postalcode"
},
  "geometry": {"coordinates":[-5.55007816135749,50.12838866668152],"type":"Point"}
}