{
  "type": "Feature",
  "properties": {
    "iso:country": "GB",
    "wof:name": "EH19 3QB",
    "wof:placetype": "postalcode"
  },
  "geometry": {"coordinates":[-3.097065,55.878002],"type":"Point"}
}
