{
  "type": "Feature",
  "properties": {
    "iso:country":"GB",
    "wof:name":"EH19 3QB",
    "wof:placetype":"postalcode"
},
  "geometry": {"coordinates":[-3.09706524474606,55.87800197275133],"type":"Point"}
}