{
  "type": "Feature",
  "properties": {
    "iso:country":"GB",
    "wof:name":"KA10 6AR",
    "wof:placetype":"postalcode"
},
  "geometry": {"coordinates":[-4.67089046647667,55.54268632025758],"type":"Point"}
}