{
  "type": "Feature",
  "properties": {
    "iso:country": "GB",
    "wof:name": "KA10 6AR",
    "wof:placetype": "postalcode"
  },
  "geometry": {"coordinates":[-4.67089,55.542686],"type":"Point"}
}
