{
  "type": "Feature",
  "properties": {
    "iso:country": "GB",
    "wof:name": "RH5 4LP",
    "wof:placetype": "postalcode"
  },
  "geometry": {"coordinates":[-0.340123,51.17813],"type":"Point"}
}
