{
  "type": "Feature",
  "properties": {
    "iso:country": "GB",
    "wof:name": "NW9 9QL",
    "wof:placetype": "postalcode"
  },
  "geometry": {"coordinates":[-0.282298,51.586387],"type":"Point"}
}
