{
  "type": "Feature",
  "properties": {
    "iso:country":"GB",
    "wof:name":"NW9 9QL",
    "wof:placetype":"postalcode"
},
  "geometry": {"coordinates":[-0.28229758294011,51.58638696692771],"type":"Point"}
}