{
  "type": "Feature",
  "properties": {
    "date:inception_lower":"1981-06-01",
    "date:inception_upper":"1981-06-30",
    "iso:country":"GB",
    "wof:name":"SS2 5NJ",
    "wof:placetype":"postalcode"
},
  "geometry": {"coordinates":[0.716394,51.553683],"type":"Point"}
}