{
  "type": "Feature",
  "properties": {
    "iso:country":"GB",
    "wof:name":"LL19 8YB",
    "wof:placetype":"postalcode"
},
  "geometry": {"coordinates":[-3.42517328955287,53.32535961960136],"type":"Point"}
}