{
  "type": "Feature",
  "properties": {
    "iso:country": "GB",
    "wof:name": "LL19 8YB",
    "wof:placetype": "postalcode"
  },
  "geometry": {"coordinates":[-3.425173,53.32536],"type":"Point"}
}
