{
  "type": "Feature",
  "properties": {
    "iso:country":"GB",
    "wof:name":"RM3 0QS",
    "wof:placetype":"postalcode"
},
  "geometry": {"coordinates":[0.23524220916504,51.59317384900164],"type":"Point"}
}