{
  "type": "Feature",
  "properties": {
    "iso:country": "GB",
    "wof:name": "HU16 5LY",
    "wof:placetype": "postalcode"
  },
  "geometry": {"coordinates":[-0.438179,53.775461],"type":"Point"}
}
