{
  "type": "Feature",
  "properties": {
    "date:inception_lower": "1990-07-01",
    "date:inception_upper": "1990-07-01",
    "iso:country": "GB",
    "wof:name": "CT1 1TB",
    "wof:placetype": "postalcode"
  },
  "geometry": {"coordinates":[1.094464,51.276761],"type":"Point"}
}
