{
  "type": "Feature",
  "properties": {
    "iso:country":"GB",
    "wof:name":"CT1 1TB",
    "wof:placetype":"postalcode"
},
  "geometry": {"coordinates":[1.09450402327947,51.27673647938207],"type":"Point"}
}