{
  "type": "Feature",
  "properties": {
    "iso:country": "GB",
    "wof:name": "CT1 1TB",
    "wof:placetype": "postalcode"
  },
  "geometry": {"coordinates":[1.094464,51.276761],"type":"Point"}
}
