{
  "type": "Feature",
  "properties": {
    "date:inception_lower":"1980-01-01",
    "date:inception_upper":"1980-01-31",
    "iso:country":"GB",
    "wof:name":"EX2 5JS",
    "wof:placetype":"postalcode"
},
  "geometry": {"coordinates":[-3.491868,50.719537],"type":"Point"}
}