{
  "type": "Feature",
  "properties": {
    "iso:country": "GB",
    "wof:name": "EX2 5JS",
    "wof:placetype": "postalcode"
  },
  "geometry": {"coordinates":[-3.491868,50.719537],"type":"Point"}
}
