{
  "type": "Feature",
  "properties": {
    "iso:country":"GB",
    "wof:name":"EX2 5JS",
    "wof:placetype":"postalcode"
},
  "geometry": {"coordinates":[-3.4918675809392,50.71953740361045],"type":"Point"}
}