{
  "type": "Feature",
  "properties": {
    "iso:country":"GB",
    "wof:name":"SE1 2XU",
    "wof:placetype":"postalcode"
},
  "geometry": {"coordinates":[-0.07440371413542,51.49994303507764],"type":"Point"}
}