{
  "type": "Feature",
  "properties": {
    "date:inception_lower": "2007-02-01",
    "date:inception_upper": "2007-02-01",
    "iso:country": "GB",
    "wof:name": "LA9 5LT",
    "wof:placetype": "postalcode"
  },
  "geometry": {"coordinates":[-2.749179,54.322608],"type":"Point"}
}
