{
  "type": "Feature",
  "properties": {
    "iso:country":"GB",
    "wof:name":"LA9 5LT",
    "wof:placetype":"postalcode"
},
  "geometry": {"coordinates":[-2.74914684259101,54.32259892582116],"type":"Point"}
}