{
  "type": "Feature",
  "properties": {
    "date:inception_lower":"2000-06-01",
    "date:inception_upper":"2000-06-30",
    "iso:country":"GB",
    "wof:name":"SA61 1XU",
    "wof:placetype":"postalcode"
},
  "geometry": {"coordinates":[-4.979872,51.792042],"type":"Point"}
}