{
  "type": "Feature",
  "properties": {
    "iso:country":"GB",
    "wof:name":"SA61 1XU",
    "wof:placetype":"postalcode"
},
  "geometry": {"coordinates":[-4.97987221143249,51.79204199145492],"type":"Point"}
}