{
  "type": "Feature",
  "properties": {
    "date:inception_lower": "1980-01-01",
    "date:inception_upper": "1980-01-01",
    "iso:country": "GB",
    "wof:name": "DN14 0EN",
    "wof:placetype": "postalcode"
  },
  "geometry": {"coordinates":[-1.11174,53.670056],"type":"Point"}
}
