{
  "type": "Feature",
  "properties": {
    "iso:country":"GB",
    "wof:name":"DN14 0EN",
    "wof:placetype":"postalcode"
},
  "geometry": {"coordinates":[-1.11174052651163,53.67005624337941],"type":"Point"}
}