{
  "type": "Feature",
  "properties": {
    "iso:country":"GB",
    "wof:name":"DE45 1NQ",
    "wof:placetype":"postalcode"
},
  "geometry": {"coordinates":[-1.68675647997703,53.24217411577702],"type":"Point"}
}