{
  "type": "Feature",
  "properties": {
    "date:inception_lower": "1992-08-01",
    "date:inception_upper": "1992-08-01",
    "iso:country": "GB",
    "wof:name": "DE45 1NQ",
    "wof:placetype": "postalcode"
  },
  "geometry": {"coordinates":[-1.686756,53.242174],"type":"Point"}
}
