{
  "type": "Feature",
  "properties": {
    "iso:country":"GB",
    "wof:name":"DN20 9EG",
    "wof:placetype":"postalcode"
},
  "geometry": {"coordinates":[-0.52376755968959,53.51188624286835],"type":"Point"}
}