{
  "type": "Feature",
  "properties": {
    "iso:country":"GB",
    "wof:name":"OL16 2PT",
    "wof:placetype":"postalcode"
},
  "geometry": {"coordinates":[-2.13459428953196,53.63193577698392],"type":"Point"}
}