{
  "type": "Feature",
  "properties": {
    "date:inception_lower": "2020-11-01",
    "date:inception_upper": "2020-11-01",
    "iso:country": "GB",
    "wof:name": "PE6 0FU",
    "wof:placetype": "postalcode"
  },
  "geometry": {"coordinates":[-0.09365,52.617923],"type":"Point"}
}
