{
  "type": "Feature",
  "properties": {
    "date:inception_lower": "2018-04-01",
    "date:inception_upper": "2018-04-01",
    "iso:country": "GB",
    "wof:name": "ST10 2BY",
    "wof:placetype": "postalcode"
  },
  "geometry": {"coordinates":[-2.019848,52.998882],"type":"Point"}
}
