{
  "type": "Feature",
  "properties": {
    "iso:country": "GB",
    "wof:name": "ST10 2BY",
    "wof:placetype": "postalcode"
  },
  "geometry": {"coordinates":[-2.019834,52.998873],"type":"Point"}
}
