{
  "type": "Feature",
  "properties": {
    "iso:country":"GB",
    "wof:name":"RM14 2LD",
    "wof:placetype":"postalcode"
},
  "geometry": {"coordinates":[0.24226834396717,51.55231089911067],"type":"Point"}
}