{
  "type": "Feature",
  "properties": {
    "iso:country":"GB",
    "wof:name":"W1G 8AJ",
    "wof:placetype":"postalcode"
},
  "geometry": {"coordinates":[-0.14868120494508,51.51866550082173],"type":"Point"}
}