{
  "type": "Feature",
  "properties": {
    "date:inception_lower":"2000-12-01",
    "date:inception_upper":"2000-12-31",
    "iso:country":"GB",
    "wof:name":"W1G 8AJ",
    "wof:placetype":"postalcode"
},
  "geometry": {"coordinates":[-0.148681,51.518665],"type":"Point"}
}