{
  "type": "Feature",
  "properties": {
    "date:inception_lower": "1980-01-01",
    "date:inception_upper": "1980-01-01",
    "iso:country": "GB",
    "wof:name": "DD7 6HH",
    "wof:placetype": "postalcode"
  },
  "geometry": {"coordinates":[-2.712846,56.504425],"type":"Point"}
}
