{
  "type": "Feature",
  "properties": {
    "iso:country":"GB",
    "wof:name":"DD7 6HH",
    "wof:placetype":"postalcode"
},
  "geometry": {"coordinates":[-2.71284576657743,56.50442538863942],"type":"Point"}
}