{
  "type": "Feature",
  "properties": {
    "iso:country":"GB",
    "wof:name":"CF63 1LY",
    "wof:placetype":"postalcode"
},
  "geometry": {"coordinates":[-3.25111581224554,51.41776631531981],"type":"Point"}
}