{
  "type": "Feature",
  "properties": {
    "iso:country":"GB",
    "wof:name":"BA16 0TX",
    "wof:placetype":"postalcode"
},
  "geometry": {"coordinates":[-2.74401453314127,51.11035803237167],"type":"Point"}
}