{
  "type": "Feature",
  "properties": {
    "date:inception_lower": "1993-08-01",
    "date:inception_upper": "1993-08-01",
    "iso:country": "GB",
    "wof:name": "BA16 0TX",
    "wof:placetype": "postalcode"
  },
  "geometry": {"coordinates":[-2.744014,51.110358],"type":"Point"}
}
