{
  "type": "Feature",
  "properties": {
    "iso:country":"GB",
    "wof:name":"LE1 6TE",
    "wof:placetype":"postalcode"
},
  "geometry": {"coordinates":[-1.13054597305023,52.63014974954982],"type":"Point"}
}