{
  "type": "Feature",
  "properties": {
    "date:inception_lower": "1980-01-01",
    "date:inception_upper": "1980-01-01",
    "iso:country": "GB",
    "wof:name": "LE1 6TE",
    "wof:placetype": "postalcode"
  },
  "geometry": {"coordinates":[-1.130302,52.63013],"type":"Point"}
}
