{
  "type": "Feature",
  "properties": {
    "iso:country":"GB",
    "wof:name":"N4 1EF",
    "wof:placetype":"postalcode"
},
  "geometry": {"coordinates":[-0.10452043940983,51.57481076588135],"type":"Point"}
}