{
  "type": "Feature",
  "properties": {
    "iso:country": "GB",
    "wof:name": "LS14 2AG",
    "wof:placetype": "postalcode"
  },
  "geometry": {"coordinates":[-1.45627,53.823907],"type":"Point"}
}
