{
  "type": "Feature",
  "properties": {
    "iso:country":"GB",
    "wof:name":"LS14 2AG",
    "wof:placetype":"postalcode"
},
  "geometry": {"coordinates":[-1.45626963933717,53.82390719871579],"type":"Point"}
}