{
  "type": "Feature",
  "properties": {
    "iso:country":"GB",
    "wof:name":"TA21 9HZ",
    "wof:placetype":"postalcode"
},
  "geometry": {"coordinates":[-3.20098124482465,50.98572301582546],"type":"Point"}
}