{
  "type": "Feature",
  "properties": {
    "iso:country":"GB",
    "wof:name":"CF10 5AE",
    "wof:placetype":"postalcode"
},
  "geometry": {"coordinates":[-3.16644845527761,51.46607234008165],"type":"Point"}
}