{
  "type": "Feature",
  "properties": {
    "date:inception_lower": "1980-01-01",
    "date:inception_upper": "1980-01-01",
    "iso:country": "GB",
    "wof:name": "CV36 4PJ",
    "wof:placetype": "postalcode"
  },
  "geometry": {"coordinates":[-1.692591,52.068617],"type":"Point"}
}
