{
  "type": "Feature",
  "properties": {
    "iso:country":"GB",
    "wof:name":"CV36 4PJ",
    "wof:placetype":"postalcode"
},
  "geometry": {"coordinates":[-1.69259054471068,52.06861671381937],"type":"Point"}
}