{
  "type": "Feature",
  "properties": {
    "iso:country":"GB",
    "wof:name":"BS41 9HA",
    "wof:placetype":"postalcode"
},
  "geometry": {"coordinates":[-2.6612931193197,51.43096861824231],"type":"Point"}
}