{
  "type": "Feature",
  "properties": {
    "date:inception_lower": "2017-11-01",
    "date:inception_upper": "2017-11-01",
    "iso:country": "GB",
    "wof:name": "DA5 1BL",
    "wof:placetype": "postalcode"
  },
  "geometry": {"coordinates":[0.14874,51.44094],"type":"Point"}
}
