{
  "type": "Feature",
  "properties": {
    "iso:country":"GB",
    "wof:name":"B29 5JS",
    "wof:placetype":"postalcode"
},
  "geometry": {"coordinates":[-1.96494208908845,52.44293636964287],"type":"Point"}
}