{
  "type": "Feature",
  "properties": {
    "iso:country": "GB",
    "wof:name": "ME17 1NQ",
    "wof:placetype": "postalcode"
  },
  "geometry": {"coordinates":[0.672081,51.223766],"type":"Point"}
}
