{
  "type": "Feature",
  "properties": {
    "iso:country":"GB",
    "wof:name":"PL21 9LD",
    "wof:placetype":"postalcode"
},
  "geometry": {"coordinates":[-3.95783414428721,50.36976452573519],"type":"Point"}
}