{
  "type": "Feature",
  "properties": {
    "iso:country": "GB",
    "wof:name": "BS14 0PU",
    "wof:placetype": "postalcode"
  },
  "geometry": {"coordinates":[-2.558103,51.40543],"type":"Point"}
}
