{
  "type": "Feature",
  "properties": {
    "date:inception_lower":"1997-12-01",
    "date:inception_upper":"1997-12-31",
    "iso:country":"GB",
    "wof:name":"CF71 7HY",
    "wof:placetype":"postalcode"
},
  "geometry": {"coordinates":[-3.443174,51.452885],"type":"Point"}
}