{
  "type": "Feature",
  "properties": {
    "date:inception_lower": "1980-01-01",
    "date:inception_upper": "1980-01-01",
    "iso:country": "GB",
    "wof:name": "CM1 4LD",
    "wof:placetype": "postalcode"
  },
  "geometry": {"coordinates":[0.383564,51.756445],"type":"Point"}
}
