{
  "type": "Feature",
  "properties": {
    "iso:country":"GB",
    "wof:name":"B42 1SG",
    "wof:placetype":"postalcode"
},
  "geometry": {"coordinates":[-1.90136162241111,52.52050189938306],"type":"Point"}
}