{
  "type": "Feature",
  "properties": {
    "iso:country": "GB",
    "wof:name": "B42 1SG",
    "wof:placetype": "postalcode"
  },
  "geometry": {"coordinates":[-1.901357,52.520517],"type":"Point"}
}
