{
  "type": "Feature",
  "properties": {
    "date:inception_lower": "2017-02-01",
    "date:inception_upper": "2017-02-01",
    "iso:country": "GB",
    "wof:name": "G21 2FF",
    "wof:placetype": "postalcode"
  },
  "geometry": {"coordinates":[-4.223725,55.867953],"type":"Point"}
}
