{
  "type": "Feature",
  "properties": {
    "iso:country":"GB",
    "wof:name":"M44 5HD",
    "wof:placetype":"postalcode"
},
  "geometry": {"coordinates":[-2.44524374521825,53.42731594432923],"type":"Point"}
}