{
  "type": "Feature",
  "properties": {
    "iso:country":"GB",
    "wof:name":"ST3 7BT",
    "wof:placetype":"postalcode"
},
  "geometry": {"coordinates":[-2.10816043779669,52.96824504080791],"type":"Point"}
}