{
  "type": "Feature",
  "properties": {
    "iso:country":"GB",
    "wof:name":"HG4 4HU",
    "wof:placetype":"postalcode"
},
  "geometry": {"coordinates":[-1.66131095567372,54.2200821663866],"type":"Point"}
}