{
  "type": "Feature",
  "properties": {
    "iso:country":"GB",
    "wof:name":"DH8 5YP",
    "wof:placetype":"postalcode"
},
  "geometry": {"coordinates":[-1.84706674524534,54.84862411843253],"type":"Point"}
}