{
  "type": "Feature",
  "properties": {
    "iso:country": "GB",
    "wof:name": "DH8 5YP",
    "wof:placetype": "postalcode"
  },
  "geometry": {"coordinates":[-1.847123,54.848641],"type":"Point"}
}
