{
  "type": "Feature",
  "properties": {
    "date:inception_lower": "2015-09-01",
    "date:inception_upper": "2015-09-01",
    "iso:country": "GB",
    "wof:name": "DH8 5YP",
    "wof:placetype": "postalcode"
  },
  "geometry": {"coordinates":[-1.84675,54.848407],"type":"Point"}
}
