{
  "type": "Feature",
  "properties": {
    "iso:country":"GB",
    "wof:name":"E1 4JH",
    "wof:placetype":"postalcode"
},
  "geometry": {"coordinates":[-0.05188060704493,51.52434568945876],"type":"Point"}
}