{
  "type": "Feature",
  "properties": {
    "iso:country":"GB",
    "wof:name":"IV36 2GR",
    "wof:placetype":"postalcode"
},
  "geometry": {"coordinates":[-3.61091685830751,57.60030244996275],"type":"Point"}
}