{
  "type": "Feature",
  "properties": {
    "date:inception_lower": "1980-01-01",
    "date:inception_upper": "1980-01-01",
    "iso:country": "GB",
    "wof:name": "SK10 5SG",
    "wof:placetype": "postalcode"
  },
  "geometry": {"coordinates":[-2.079303,53.331528],"type":"Point"}
}
