{
  "type": "Feature",
  "properties": {
    "iso:country": "GB",
    "wof:name": "SG1 5RH",
    "wof:placetype": "postalcode"
  },
  "geometry": {"coordinates":[-0.176156,51.919419],"type":"Point"}
}
