{
  "type": "Feature",
  "properties": {
    "iso:country":"GB",
    "wof:name":"SG1 5RH",
    "wof:placetype":"postalcode"
},
  "geometry": {"coordinates":[-0.17615625420311,51.91941881870776],"type":"Point"}
}