{
  "type": "Feature",
  "properties": {
    "date:inception_lower": "1996-12-01",
    "date:inception_upper": "1996-12-01",
    "iso:country": "GB",
    "wof:name": "SG2 8XZ",
    "wof:placetype": "postalcode"
  },
  "geometry": {"coordinates":[-0.182776,51.885478],"type":"Point"}
}
