{
  "type": "Feature",
  "properties": {
    "iso:country":"GB",
    "wof:name":"SG2 8XZ",
    "wof:placetype":"postalcode"
},
  "geometry": {"coordinates":[-0.18277610418867,51.88547781215875],"type":"Point"}
}