{
  "type": "Feature",
  "properties": {
    "iso:country": "GB",
    "wof:name": "SG2 8XZ",
    "wof:placetype": "postalcode"
  },
  "geometry": {"coordinates":[-0.182776,51.885478],"type":"Point"}
}
