{
  "type": "Feature",
  "properties": {
    "iso:country": "GB",
    "wof:name": "E8 4PY",
    "wof:placetype": "postalcode"
  },
  "geometry": {"coordinates":[-0.066074,51.536064],"type":"Point"}
}
