{
  "type": "Feature",
  "properties": {
    "iso:country": "GB",
    "wof:name": "PA23 7LG",
    "wof:placetype": "postalcode"
  },
  "geometry": {"coordinates":[-4.936002,55.942693],"type":"Point"}
}
