{
  "type": "Feature",
  "properties": {
    "iso:country":"GB",
    "wof:name":"PA23 7LG",
    "wof:placetype":"postalcode"
},
  "geometry": {"coordinates":[-4.93600220669363,55.94269331031391],"type":"Point"}
}