{
  "type": "Feature",
  "properties": {
    "date:inception_lower":"1980-01-01",
    "date:inception_upper":"1980-01-31",
    "iso:country":"GB",
    "wof:name":"CH2 2AL",
    "wof:placetype":"postalcode"
},
  "geometry": {"coordinates":[-2.892635,53.203365],"type":"Point"}
}