{
  "type": "Feature",
  "properties": {
    "iso:country":"GB",
    "wof:name":"CH2 2AL",
    "wof:placetype":"postalcode"
},
  "geometry": {"coordinates":[-2.89263544560894,53.2033653423326],"type":"Point"}
}