{
  "type": "Feature",
  "properties": {
    "date:inception_lower":"1999-06-01",
    "date:inception_upper":"1999-06-30",
    "iso:country":"GB",
    "wof:name":"NP26 4EA",
    "wof:placetype":"postalcode"
},
  "geometry": {"coordinates":[-2.762429,51.594739],"type":"Point"}
}