{
  "type": "Feature",
  "properties": {
    "iso:country": "GB",
    "wof:name": "DN33 3RE",
    "wof:placetype": "postalcode"
  },
  "geometry": {"coordinates":[-0.098806,53.543262],"type":"Point"}
}
