{
  "type": "Feature",
  "properties": {
    "iso:country": "GB",
    "wof:name": "TN13 2HR",
    "wof:placetype": "postalcode"
  },
  "geometry": {"coordinates":[0.168082,51.27851],"type":"Point"}
}
