{
  "type": "Feature",
  "properties": {
    "iso:country":"GB",
    "wof:name":"DH9 8ST",
    "wof:placetype":"postalcode"
},
  "geometry": {"coordinates":[-1.73952701640312,54.86368224290599],"type":"Point"}
}