{
  "type": "Feature",
  "properties": {
    "iso:country": "GB",
    "wof:name": "DH9 8ST",
    "wof:placetype": "postalcode"
  },
  "geometry": {"coordinates":[-1.739527,54.863682],"type":"Point"}
}
