{
  "type": "Feature",
  "properties": {
    "iso:country":"GB",
    "wof:name":"PO22 0BT",
    "wof:placetype":"postalcode"
},
  "geometry": {"coordinates":[-0.64638970697022,50.825739908266],"type":"Point"}
}