{
  "type": "Feature",
  "properties": {
    "date:inception_lower": "1980-01-01",
    "date:inception_upper": "1980-01-01",
    "iso:country": "GB",
    "wof:name": "IP24 1NJ",
    "wof:placetype": "postalcode"
  },
  "geometry": {"coordinates":[0.877905,52.496755],"type":"Point"}
}
