{
  "type": "Feature",
  "properties": {
    "iso:country": "GB",
    "wof:name": "CA4 0RY",
    "wof:placetype": "postalcode"
  },
  "geometry": {"coordinates":[-2.882324,54.82736],"type":"Point"}
}
