{
  "type": "Feature",
  "properties": {
    "iso:country":"GB",
    "wof:name":"CA4 0RY",
    "wof:placetype":"postalcode"
},
  "geometry": {"coordinates":[-2.8823241275207,54.82735954088169],"type":"Point"}
}