{
  "type": "Feature",
  "properties": {
    "date:inception_lower": "1980-01-01",
    "date:inception_upper": "1980-01-01",
    "iso:country": "GB",
    "wof:name": "CA14 2EE",
    "wof:placetype": "postalcode"
  },
  "geometry": {"coordinates":[-3.550687,54.645023],"type":"Point"}
}
