{
  "type": "Feature",
  "properties": {
    "iso:country": "GB",
    "wof:name": "CA14 2EE",
    "wof:placetype": "postalcode"
  },
  "geometry": {"coordinates":[-3.550687,54.645023],"type":"Point"}
}
