{
  "type": "Feature",
  "properties": {
    "iso:country":"GB",
    "wof:name":"CV10 9RL",
    "wof:placetype":"postalcode"
},
  "geometry": {"coordinates":[-1.52767555627323,52.52574156299242],"type":"Point"}
}