{
  "type": "Feature",
  "properties": {
    "date:inception_lower": "1980-01-01",
    "date:inception_upper": "1980-01-01",
    "iso:country": "GB",
    "wof:name": "EX23 9PE",
    "wof:placetype": "postalcode"
  },
  "geometry": {"coordinates":[-4.518293,50.906945],"type":"Point"}
}
