{
  "type": "Feature",
  "properties": {
    "iso:country":"GB",
    "wof:name":"EX23 9PE",
    "wof:placetype":"postalcode"
},
  "geometry": {"coordinates":[-4.51829311022067,50.90694525284543],"type":"Point"}
}