{
  "type": "Feature",
  "properties": {
    "iso:country":"GB",
    "wof:name":"PL17 8BY",
    "wof:placetype":"postalcode"
},
  "geometry": {"coordinates":[-4.23344631264721,50.49197687713112],"type":"Point"}
}