{
  "type": "Feature",
  "properties": {
    "date:inception_lower": "1996-06-01",
    "date:inception_upper": "1996-06-01",
    "iso:country": "GB",
    "wof:name": "AB54 8ES",
    "wof:placetype": "postalcode"
  },
  "geometry": {"coordinates":[-2.789129,57.444988],"type":"Point"}
}
