{
  "type": "Feature",
  "properties": {
    "iso:country":"GB",
    "wof:name":"AB54 8ES",
    "wof:placetype":"postalcode"
},
  "geometry": {"coordinates":[-2.78912937467306,57.4449876971455],"type":"Point"}
}