{
  "type": "Feature",
  "properties": {
    "iso:country":"GB",
    "wof:name":"LS22 7UG",
    "wof:placetype":"postalcode"
},
  "geometry": {"coordinates":[-1.39413508016311,53.94192739269081],"type":"Point"}
}