{
  "type": "Feature",
  "properties": {
    "date:inception_lower": "1993-01-01",
    "date:inception_upper": "1993-01-01",
    "iso:country": "GB",
    "wof:name": "LS22 7UG",
    "wof:placetype": "postalcode"
  },
  "geometry": {"coordinates":[-1.394135,53.941927],"type":"Point"}
}
