{
  "type": "Feature",
  "properties": {
    "iso:country": "GB",
    "wof:name": "LS22 7UG",
    "wof:placetype": "postalcode"
  },
  "geometry": {"coordinates":[-1.394135,53.941927],"type":"Point"}
}
