{
  "type": "Feature",
  "properties": {
    "iso:country":"GB",
    "wof:name":"WC2H 7BL",
    "wof:placetype":"postalcode"
},
  "geometry": {"coordinates":[-0.13111808218985,51.51109404594033],"type":"Point"}
}