{
  "type": "Feature",
  "properties": {
    "date:inception_lower": "2017-01-01",
    "date:inception_upper": "2017-01-01",
    "iso:country": "GB",
    "wof:name": "PH10 6GT",
    "wof:placetype": "postalcode"
  },
  "geometry": {"coordinates":[-3.336431,56.587142],"type":"Point"}
}
