{
  "type": "Feature",
  "properties": {
    "iso:country":"GB",
    "wof:name":"TN8 6DU",
    "wof:placetype":"postalcode"
},
  "geometry": {"coordinates":[0.06660456191812,51.20465060673008],"type":"Point"}
}