{
  "type": "Feature",
  "properties": {
    "date:inception_lower": "1980-01-01",
    "date:inception_upper": "1980-01-01",
    "iso:country": "GB",
    "wof:name": "TN8 6DU",
    "wof:placetype": "postalcode"
  },
  "geometry": {"coordinates":[0.066605,51.204651],"type":"Point"}
}
