{
  "type": "Feature",
  "properties": {
    "iso:country":"GB",
    "wof:name":"CF81 8QL",
    "wof:placetype":"postalcode"
},
  "geometry": {"coordinates":[-3.23879725456549,51.68340884635148],"type":"Point"}
}