{
  "type": "Feature",
  "properties": {
    "iso:country": "GB",
    "wof:name": "CF81 8QL",
    "wof:placetype": "postalcode"
  },
  "geometry": {"coordinates":[-3.238797,51.683409],"type":"Point"}
}
