{
  "type": "Feature",
  "properties": {
    "iso:country": "GB",
    "wof:name": "DD9 6DN",
    "wof:placetype": "postalcode"
  },
  "geometry": {"coordinates":[-2.657292,56.730787],"type":"Point"}
}
