{
  "type": "Feature",
  "properties": {
    "date:inception_lower": "2005-02-01",
    "date:inception_upper": "2005-02-01",
    "iso:country": "GB",
    "wof:name": "MK8 0PW",
    "wof:placetype": "postalcode"
  },
  "geometry": {"coordinates":[-0.812541,52.023414],"type":"Point"}
}
