{
  "type": "Feature",
  "properties": {
    "iso:country": "GB",
    "wof:name": "MK8 0PW",
    "wof:placetype": "postalcode"
  },
  "geometry": {"coordinates":[-0.812541,52.023414],"type":"Point"}
}
