{
  "type": "Feature",
  "properties": {
    "iso:country":"GB",
    "wof:name":"NN7 4QW",
    "wof:placetype":"postalcode"
},
  "geometry": {"coordinates":[-1.08582392935,52.22832314253462],"type":"Point"}
}