{
  "type": "Feature",
  "properties": {
    "iso:country": "GB",
    "wof:name": "NN7 4QW",
    "wof:placetype": "postalcode"
  },
  "geometry": {"coordinates":[-1.085824,52.228323],"type":"Point"}
}
