{
  "type": "Feature",
  "properties": {
    "date:inception_lower": "1986-07-01",
    "date:inception_upper": "1986-07-01",
    "iso:country": "GB",
    "wof:name": "NE6 4LL",
    "wof:placetype": "postalcode"
  },
  "geometry": {"coordinates":[-1.540383,54.979277],"type":"Point"}
}
