{
  "type": "Feature",
  "properties": {
    "iso:country":"GB",
    "wof:name":"NE6 4LL",
    "wof:placetype":"postalcode"
},
  "geometry": {"coordinates":[-1.54038295253323,54.97927713146964],"type":"Point"}
}