{
  "type": "Feature",
  "properties": {
    "iso:country":"GB",
    "wof:name":"SY5 6JU",
    "wof:placetype":"postalcode"
},
  "geometry": {"coordinates":[-2.68006727902073,52.663100991116],"type":"Point"}
}