{
  "type": "Feature",
  "properties": {
    "iso:country": "GB",
    "wof:name": "GU9 7AY",
    "wof:placetype": "postalcode"
  },
  "geometry": {"coordinates":[-0.814553,51.214449],"type":"Point"}
}
