{
  "type": "Feature",
  "properties": {
    "date:inception_lower":"1980-01-01",
    "date:inception_upper":"1980-01-31",
    "iso:country":"GB",
    "wof:name":"EX7 9LP",
    "wof:placetype":"postalcode"
},
  "geometry": {"coordinates":[-3.471453,50.58326],"type":"Point"}
}