{
  "type": "Feature",
  "properties": {
    "iso:country":"GB",
    "wof:name":"EX7 9LP",
    "wof:placetype":"postalcode"
},
  "geometry": {"coordinates":[-3.47145290539631,50.58325978533807],"type":"Point"}
}