{
  "type": "Feature",
  "properties": {
    "iso:country": "GB",
    "wof:name": "L20 6DG",
    "wof:placetype": "postalcode"
  },
  "geometry": {"coordinates":[-2.986923,53.462135],"type":"Point"}
}
