{
  "type": "Feature",
  "properties": {
    "date:inception_lower":"2013-08-01",
    "date:inception_upper":"2013-08-31",
    "iso:country":"GB",
    "wof:name":"L20 6DG",
    "wof:placetype":"postalcode"
},
  "geometry": {"coordinates":[-2.986923,53.462135],"type":"Point"}
}