{
  "type": "Feature",
  "properties": {
    "iso:country":"GB",
    "wof:name":"L20 6DG",
    "wof:placetype":"postalcode"
},
  "geometry": {"coordinates":[-2.98692352669636,53.46213510682798],"type":"Point"}
}