{
  "type": "Feature",
  "properties": {
    "iso:country": "GB",
    "wof:name": "S8 9FH",
    "wof:placetype": "postalcode"
  },
  "geometry": {"coordinates":[-1.477658,53.35453],"type":"Point"}
}
