{
  "type": "Feature",
  "properties": {
    "iso:country":"GB",
    "wof:name":"RG21 7RA",
    "wof:placetype":"postalcode"
},
  "geometry": {"coordinates":[-1.1032287875405,51.26556512723814],"type":"Point"}
}