{
  "type": "Feature",
  "properties": {
    "date:inception_lower":"1985-10-01",
    "date:inception_upper":"1985-10-31",
    "iso:country":"GB",
    "wof:name":"DN37 0XY",
    "wof:placetype":"postalcode"
},
  "geometry": {"coordinates":[-0.115469,53.516737],"type":"Point"}
}