{
  "type": "Feature",
  "properties": {
    "iso:country":"GB",
    "wof:name":"DN37 0XY",
    "wof:placetype":"postalcode"
},
  "geometry": {"coordinates":[-0.1154690977687,53.51673667983164],"type":"Point"}
}