{
  "type": "Feature",
  "properties": {
    "iso:country":"GB",
    "wof:name":"EN9 1RX",
    "wof:placetype":"postalcode"
},
  "geometry": {"coordinates":[-0.00343969799156,51.68606239095769],"type":"Point"}
}