{
  "type": "Feature",
  "properties": {
    "date:inception_lower": "2013-07-01",
    "date:inception_upper": "2013-07-01",
    "iso:country": "GB",
    "wof:name": "EN9 1RX",
    "wof:placetype": "postalcode"
  },
  "geometry": {"coordinates":[-0.003386,51.686029],"type":"Point"}
}
