{
  "type": "Feature",
  "properties": {
    "date:inception_lower": "1998-06-01",
    "date:inception_upper": "1998-06-01",
    "iso:country": "GB",
    "wof:name": "NN12 6HY",
    "wof:placetype": "postalcode"
  },
  "geometry": {"coordinates":[-0.984981,52.126524],"type":"Point"}
}
