{
  "type": "Feature",
  "properties": {
    "iso:country":"GB",
    "wof:name":"WD6 2ET",
    "wof:placetype":"postalcode"
},
  "geometry": {"coordinates":[-0.26275855799534,51.64902696846147],"type":"Point"}
}