{
  "type": "Feature",
  "properties": {
    "date:inception_lower":"1980-01-01",
    "date:inception_upper":"1980-01-31",
    "iso:country":"GB",
    "wof:name":"RH2 7QT",
    "wof:placetype":"postalcode"
},
  "geometry": {"coordinates":[-0.189997,51.212823],"type":"Point"}
}