{
  "type": "Feature",
  "properties": {
    "iso:country":"GB",
    "wof:name":"RH2 7QT",
    "wof:placetype":"postalcode"
},
  "geometry": {"coordinates":[-0.18999685389164,51.2128226420484],"type":"Point"}
}