{
  "type": "Feature",
  "properties": {
    "iso:country":"GB",
    "wof:name":"DN16 1RR",
    "wof:placetype":"postalcode"
},
  "geometry": {"coordinates":[-0.62660613702308,53.56727115391651],"type":"Point"}
}