{
  "type": "Feature",
  "properties": {
    "date:inception_lower": "1994-05-01",
    "date:inception_upper": "1994-05-01",
    "iso:country": "GB",
    "wof:name": "SA2 9GY",
    "wof:placetype": "postalcode"
  },
  "geometry": {"coordinates":[-3.996254,51.627976],"type":"Point"}
}
