{
  "type": "Feature",
  "properties": {
    "iso:country": "GB",
    "wof:name": "SA2 9GY",
    "wof:placetype": "postalcode"
  },
  "geometry": {"coordinates":[-3.996254,51.627976],"type":"Point"}
}
