{
  "type": "Feature",
  "properties": {
    "iso:country": "GB",
    "wof:name": "HD8 9LZ",
    "wof:placetype": "postalcode"
  },
  "geometry": {"coordinates":[-1.611675,53.593542],"type":"Point"}
}
