{
  "type": "Feature",
  "properties": {
    "iso:country":"GB",
    "wof:name":"TN5 6JL",
    "wof:placetype":"postalcode"
},
  "geometry": {"coordinates":[0.30505547333668,51.0591937153672],"type":"Point"}
}