{
  "type": "Feature",
  "properties": {
    "iso:country":"GB",
    "wof:name":"MK18 1UL",
    "wof:placetype":"postalcode"
},
  "geometry": {"coordinates":[-0.98137770206393,51.98778942334714],"type":"Point"}
}