{
  "type": "Feature",
  "properties": {
    "iso:country": "GB",
    "wof:name": "L31 1LJ",
    "wof:placetype": "postalcode"
  },
  "geometry": {"coordinates":[-2.911461,53.490951],"type":"Point"}
}
