{
  "type": "Feature",
  "properties": {
    "iso:country":"GB",
    "wof:name":"L31 1LJ",
    "wof:placetype":"postalcode"
},
  "geometry": {"coordinates":[-2.91146134196677,53.49095050732038],"type":"Point"}
}