{
  "type": "Feature",
  "properties": {
    "date:inception_lower": "2000-06-01",
    "date:inception_upper": "2000-06-01",
    "iso:country": "GB",
    "wof:name": "L31 1LJ",
    "wof:placetype": "postalcode"
  },
  "geometry": {"coordinates":[-2.911461,53.490951],"type":"Point"}
}
