{
  "type": "Feature",
  "properties": {
    "iso:country":"GB",
    "wof:name":"DA8 1JZ",
    "wof:placetype":"postalcode"
},
  "geometry": {"coordinates":[0.15711116907049,51.47134412678183],"type":"Point"}
}