{
  "type": "Feature",
  "properties": {
    "date:inception_lower":"1980-01-01",
    "date:inception_upper":"1980-01-31",
    "iso:country":"GB",
    "wof:name":"LS28 5BS",
    "wof:placetype":"postalcode"
},
  "geometry": {"coordinates":[-1.67115,53.806443],"type":"Point"}
}