{
  "type": "Feature",
  "properties": {
    "iso:country":"GB",
    "wof:name":"SP6 2LE",
    "wof:placetype":"postalcode"
},
  "geometry": {"coordinates":[-1.75700539817949,50.93100273234679],"type":"Point"}
}