{
  "type": "Feature",
  "properties": {
    "iso:country":"GB",
    "wof:name":"LE11 5UA",
    "wof:placetype":"postalcode"
},
  "geometry": {"coordinates":[-1.22521970736654,52.78081078340276],"type":"Point"}
}