{
  "type": "Feature",
  "properties": {
    "iso:country": "GB",
    "wof:name": "LE11 5UA",
    "wof:placetype": "postalcode"
  },
  "geometry": {"coordinates":[-1.22522,52.780811],"type":"Point"}
}
