{
  "type": "Feature",
  "properties": {
    "date:inception_lower":"1996-06-01",
    "date:inception_upper":"1996-06-30",
    "iso:country":"GB",
    "wof:name":"LE11 5UA",
    "wof:placetype":"postalcode"
},
  "geometry": {"coordinates":[-1.22522,52.780811],"type":"Point"}
}