{
  "type": "Feature",
  "properties": {
    "iso:country":"GB",
    "wof:name":"WF1 2NB",
    "wof:placetype":"postalcode"
},
  "geometry": {"coordinates":[-1.50681165614696,53.70600384530943],"type":"Point"}
}