{
  "type": "Feature",
  "properties": {
    "iso:country":"GB",
    "wof:name":"PO33 1AF",
    "wof:placetype":"postalcode"
},
  "geometry": {"coordinates":[-1.14582667263616,50.71973585146188],"type":"Point"}
}