{
  "type": "Feature",
  "properties": {
    "iso:country": "GB",
    "wof:name": "PO33 1AF",
    "wof:placetype": "postalcode"
  },
  "geometry": {"coordinates":[-1.145829,50.719761],"type":"Point"}
}
