{
  "type": "Feature",
  "properties": {
    "iso:country":"GB",
    "wof:name":"MK44 1PL",
    "wof:placetype":"postalcode"
},
  "geometry": {"coordinates":[-0.54390675852759,52.22314327349351],"type":"Point"}
}