{
  "type": "Feature",
  "properties": {
    "iso:country": "GB",
    "wof:name": "MK44 1PL",
    "wof:placetype": "postalcode"
  },
  "geometry": {"coordinates":[-0.543907,52.223143],"type":"Point"}
}
