{
  "type": "Feature",
  "properties": {
    "iso:country": "GB",
    "wof:name": "TF1 6PH",
    "wof:placetype": "postalcode"
  },
  "geometry": {"coordinates":[-2.486531,52.706779],"type":"Point"}
}
