{
  "type": "Feature",
  "properties": {
    "iso:country":"GB",
    "wof:name":"SO24 9JY",
    "wof:placetype":"postalcode"
},
  "geometry": {"coordinates":[-1.16436326926966,51.08566140412461],"type":"Point"}
}