{
  "type": "Feature",
  "properties": {
    "date:inception_lower": "1980-01-01",
    "date:inception_upper": "1980-01-01",
    "iso:country": "GB",
    "wof:name": "SO24 9JY",
    "wof:placetype": "postalcode"
  },
  "geometry": {"coordinates":[-1.164363,51.085661],"type":"Point"}
}
