{
  "type": "Feature",
  "properties": {
    "iso:country": "GB",
    "wof:name": "HX1 2QX",
    "wof:placetype": "postalcode"
  },
  "geometry": {"coordinates":[-1.861905,53.71758],"type":"Point"}
}
