{
  "type": "Feature",
  "properties": {
    "date:inception_lower": "1980-01-01",
    "date:inception_upper": "1980-01-01",
    "iso:country": "GB",
    "wof:name": "BD17 5EE",
    "wof:placetype": "postalcode"
  },
  "geometry": {"coordinates":[-1.792341,53.856162],"type":"Point"}
}
