{
  "type": "Feature",
  "properties": {
    "iso:country": "GB",
    "wof:name": "NW10 5DJ",
    "wof:placetype": "postalcode"
  },
  "geometry": {"coordinates":[-0.2214,51.529718],"type":"Point"}
}
