{
  "type": "Feature",
  "properties": {
    "iso:country":"GB",
    "wof:name":"NW10 5DJ",
    "wof:placetype":"postalcode"
},
  "geometry": {"coordinates":[-0.22139995116374,51.52971830586475],"type":"Point"}
}