{
  "type": "Feature",
  "properties": {
    "iso:country": "GB",
    "wof:name": "YO8 3AQ",
    "wof:placetype": "postalcode"
  },
  "geometry": {"coordinates":[-1.069852,53.788484],"type":"Point"}
}
