{
  "type": "Feature",
  "properties": {
    "date:inception_lower":"2011-12-01",
    "date:inception_upper":"2011-12-31",
    "iso:country":"GB",
    "wof:name":"YO8 3AQ",
    "wof:placetype":"postalcode"
},
  "geometry": {"coordinates":[-1.069852,53.788484],"type":"Point"}
}