{
  "type": "Feature",
  "properties": {
    "iso:country":"GB",
    "wof:name":"YO8 3AQ",
    "wof:placetype":"postalcode"
},
  "geometry": {"coordinates":[-1.06985206314165,53.78848423356859],"type":"Point"}
}