{
  "type": "Feature",
  "properties": {
    "date:inception_lower":"1980-01-01",
    "date:inception_upper":"1980-01-31",
    "iso:country":"GB",
    "wof:name":"BN9 9UG",
    "wof:placetype":"postalcode"
},
  "geometry": {"coordinates":[0.032989,50.788539],"type":"Point"}
}