{
  "type": "Feature",
  "properties": {
    "iso:country":"GB",
    "wof:name":"BN9 9UG",
    "wof:placetype":"postalcode"
},
  "geometry": {"coordinates":[0.03298897316013,50.78853877640275],"type":"Point"}
}