{
  "type": "Feature",
  "properties": {
    "iso:country":"GB",
    "wof:name":"SW13 0JX",
    "wof:placetype":"postalcode"
},
  "geometry": {"coordinates":[-0.25168778708422,51.46728073832721],"type":"Point"}
}