{
  "type": "Feature",
  "properties": {
    "date:inception_lower": "2021-04-01",
    "date:inception_upper": "2021-04-01",
    "iso:country": "GB",
    "wof:name": "OL5 9FQ",
    "wof:placetype": "postalcode"
  },
  "geometry": {"coordinates":[-2.036081,53.52029],"type":"Point"}
}
