{
  "type": "Feature",
  "properties": {
    "iso:country":"GB",
    "wof:name":"BL0 9NG",
    "wof:placetype":"postalcode"
},
  "geometry": {"coordinates":[-2.32353846809391,53.64287204397522],"type":"Point"}
}