{
  "type": "Feature",
  "properties": {
    "date:inception_lower": "1980-01-01",
    "date:inception_upper": "1980-01-01",
    "iso:country": "GB",
    "wof:name": "BL0 9NG",
    "wof:placetype": "postalcode"
  },
  "geometry": {"coordinates":[-2.323552,53.642897],"type":"Point"}
}
