{
  "type": "Feature",
  "properties": {
    "iso:country": "GB",
    "wof:name": "S65 1AB",
    "wof:placetype": "postalcode"
  },
  "geometry": {"coordinates":[-1.353316,53.435162],"type":"Point"}
}
