{
  "type": "Feature",
  "properties": {
    "iso:country":"GB",
    "wof:name":"S65 1AB",
    "wof:placetype":"postalcode"
},
  "geometry": {"coordinates":[-1.35331624703725,53.43516156092556],"type":"Point"}
}