{
  "type": "Feature",
  "properties": {
    "date:inception_lower":"2011-02-01",
    "date:inception_upper":"2011-02-28",
    "iso:country":"GB",
    "wof:name":"NP4 6TW",
    "wof:placetype":"postalcode"
},
  "geometry": {"coordinates":[-3.059445,51.716823],"type":"Point"}
}