{
  "type": "Feature",
  "properties": {
    "iso:country":"GB",
    "wof:name":"NP4 6TW",
    "wof:placetype":"postalcode"
},
  "geometry": {"coordinates":[-3.05944545596748,51.71682291177541],"type":"Point"}
}