{
  "type": "Feature",
  "properties": {
    "iso:country":"GB",
    "wof:name":"DH8 5FE",
    "wof:placetype":"postalcode"
},
  "geometry": {"coordinates":[-1.84557761084632,54.85523621700253],"type":"Point"}
}