{
  "type": "Feature",
  "properties": {
    "date:inception_lower": "1994-05-01",
    "date:inception_upper": "1994-05-01",
    "iso:country": "GB",
    "wof:name": "M9 0QZ",
    "wof:placetype": "postalcode"
  },
  "geometry": {"coordinates":[-2.241228,53.535243],"type":"Point"}
}
