{
  "type": "Feature",
  "properties": {
    "iso:country":"GB",
    "wof:name":"M9 0QZ",
    "wof:placetype":"postalcode"
},
  "geometry": {"coordinates":[-2.24122817741239,53.53524278174812],"type":"Point"}
}