{
  "type": "Feature",
  "properties": {
    "iso:country": "GB",
    "wof:name": "G52 2HW",
    "wof:placetype": "postalcode"
  },
  "geometry": {"coordinates":[-4.342956,55.850088],"type":"Point"}
}
