{
  "type": "Feature",
  "properties": {
    "iso:country":"GB",
    "wof:name":"RG17 8XZ",
    "wof:placetype":"postalcode"
},
  "geometry": {"coordinates":[-1.53185652385532,51.50931907111337],"type":"Point"}
}