{
  "type": "Feature",
  "properties": {
    "iso:country":"GB",
    "wof:name":"TA7 0EP",
    "wof:placetype":"postalcode"
},
  "geometry": {"coordinates":[-2.92739398450398,51.10907396899758],"type":"Point"}
}