{
  "type": "Feature",
  "properties": {
    "iso:country":"GB",
    "wof:name":"NW9 0QA",
    "wof:placetype":"postalcode"
},
  "geometry": {"coordinates":[-0.26161704012438,51.58588464595191],"type":"Point"}
}