{
  "type": "Feature",
  "properties": {
    "iso:country":"GB",
    "wof:name":"WF10 1NA",
    "wof:placetype":"postalcode"
},
  "geometry": {"coordinates":[-1.36479780351672,53.72668246759304],"type":"Point"}
}