{
  "type": "Feature",
  "properties": {
    "iso:country": "GB",
    "wof:name": "WF10 1NA",
    "wof:placetype": "postalcode"
  },
  "geometry": {"coordinates":[-1.364798,53.726682],"type":"Point"}
}
