{
  "type": "Feature",
  "properties": {
    "iso:country": "GB",
    "wof:name": "B45 8ET",
    "wof:placetype": "postalcode"
  },
  "geometry": {"coordinates":[-2.017068,52.373932],"type":"Point"}
}
