{
  "type": "Feature",
  "properties": {
    "iso:country":"GB",
    "wof:name":"B45 8ET",
    "wof:placetype":"postalcode"
},
  "geometry": {"coordinates":[-2.01706813811577,52.3739324597036],"type":"Point"}
}