{
  "type": "Feature",
  "properties": {
    "iso:country":"GB",
    "wof:name":"B63 4NF",
    "wof:placetype":"postalcode"
},
  "geometry": {"coordinates":[-2.06625763671993,52.44014486477985],"type":"Point"}
}