{
  "type": "Feature",
  "properties": {
    "iso:country":"GB",
    "wof:name":"CT20 2UA",
    "wof:placetype":"postalcode"
},
  "geometry": {"coordinates":[1.16460578957028,51.07839461889566],"type":"Point"}
}