{
  "type": "Feature",
  "properties": {
    "iso:country":"GB",
    "wof:name":"HG3 3RW",
    "wof:placetype":"postalcode"
},
  "geometry": {"coordinates":[-1.502691065612,54.06894611958673],"type":"Point"}
}