{
  "type": "Feature",
  "properties": {
    "date:inception_lower": "1980-01-01",
    "date:inception_upper": "1980-01-01",
    "iso:country": "GB",
    "wof:name": "HG3 3RW",
    "wof:placetype": "postalcode"
  },
  "geometry": {"coordinates":[-1.502691,54.068946],"type":"Point"}
}
