{
  "type": "Feature",
  "properties": {
    "iso:country": "GB",
    "wof:name": "NE6 5TX",
    "wof:placetype": "postalcode"
  },
  "geometry": {"coordinates":[-1.575259,54.990861],"type":"Point"}
}
