{
  "type": "Feature",
  "properties": {
    "iso:country":"GB",
    "wof:name":"NE6 5TX",
    "wof:placetype":"postalcode"
},
  "geometry": {"coordinates":[-1.57525923667545,54.99086131708197],"type":"Point"}
}