{
  "type": "Feature",
  "properties": {
    "date:inception_lower": "1980-01-01",
    "date:inception_upper": "1980-01-01",
    "iso:country": "GB",
    "wof:name": "NE6 5TX",
    "wof:placetype": "postalcode"
  },
  "geometry": {"coordinates":[-1.575259,54.990861],"type":"Point"}
}
