{
  "type": "Feature",
  "properties": {
    "iso:country": "GB",
    "wof:name": "RG14 6RR",
    "wof:placetype": "postalcode"
  },
  "geometry": {"coordinates":[-1.352297,51.375389],"type":"Point"}
}
