{
  "type": "Feature",
  "properties": {
    "date:inception_lower": "1994-12-01",
    "date:inception_upper": "1994-12-01",
    "iso:country": "GB",
    "wof:name": "TN23 6JL",
    "wof:placetype": "postalcode"
  },
  "geometry": {"coordinates":[0.86377,51.132586],"type":"Point"}
}
