{
  "type": "Feature",
  "properties": {
    "iso:country": "GB",
    "wof:name": "TN23 6JL",
    "wof:placetype": "postalcode"
  },
  "geometry": {"coordinates":[0.86377,51.132586],"type":"Point"}
}
