{
  "type": "Feature",
  "properties": {
    "iso:country":"GB",
    "wof:name":"PE26 2QX",
    "wof:placetype":"postalcode"
},
  "geometry": {"coordinates":[-0.1510012432181,52.42616968922415],"type":"Point"}
}