{
  "type": "Feature",
  "properties": {
    "iso:country": "GB",
    "wof:name": "PE26 2QX",
    "wof:placetype": "postalcode"
  },
  "geometry": {"coordinates":[-0.151001,52.42617],"type":"Point"}
}
