{
  "type": "Feature",
  "properties": {
    "iso:country":"GB",
    "wof:name":"BS13 8PZ",
    "wof:placetype":"postalcode"
},
  "geometry": {"coordinates":[-2.62255698234419,51.40887239717909],"type":"Point"}
}