{
  "type": "Feature",
  "properties": {
    "iso:country":"GB",
    "wof:name":"FY5 1AJ",
    "wof:placetype":"postalcode"
},
  "geometry": {"coordinates":[-3.04164344573785,53.87740178467617],"type":"Point"}
}