{
  "type": "Feature",
  "properties": {
    "iso:country":"GB",
    "wof:name":"BS3 2NR",
    "wof:placetype":"postalcode"
},
  "geometry": {"coordinates":[-2.61233581370721,51.43371637854661],"type":"Point"}
}