{
  "type": "Feature",
  "properties": {
    "iso:country":"GB",
    "wof:name":"PE23 5RS",
    "wof:placetype":"postalcode"
},
  "geometry": {"coordinates":[0.15201423494882,53.19380544145443],"type":"Point"}
}