{
  "type": "Feature",
  "properties": {
    "iso:country": "GB",
    "wof:name": "PE23 5RS",
    "wof:placetype": "postalcode"
  },
  "geometry": {"coordinates":[0.151121,53.193569],"type":"Point"}
}
