{
  "type": "Feature",
  "properties": {
    "iso:country": "GB",
    "wof:name": "PE23 5RS",
    "wof:placetype": "postalcode"
  },
  "geometry": {"coordinates":[0.152017,53.193832],"type":"Point"}
}
