{
  "type": "Feature",
  "properties": {
    "date:inception_lower": "1992-08-01",
    "date:inception_upper": "1992-08-01",
    "iso:country": "GB",
    "wof:name": "L17 7HP",
    "wof:placetype": "postalcode"
  },
  "geometry": {"coordinates":[-2.957507,53.375767],"type":"Point"}
}
