{
  "type": "Feature",
  "properties": {
    "iso:country":"GB",
    "wof:name":"RG30 2NX",
    "wof:placetype":"postalcode"
},
  "geometry": {"coordinates":[-1.0074882487048,51.45277908034384],"type":"Point"}
}