{
  "type": "Feature",
  "properties": {
    "date:inception_lower":"1980-01-01",
    "date:inception_upper":"1980-01-31",
    "iso:country":"GB",
    "wof:name":"SA61 2JN",
    "wof:placetype":"postalcode"
},
  "geometry": {"coordinates":[-4.970791,51.803919],"type":"Point"}
}