{
  "type": "Feature",
  "properties": {
    "iso:country":"GB",
    "wof:name":"SA61 2JN",
    "wof:placetype":"postalcode"
},
  "geometry": {"coordinates":[-4.97079093540785,51.80391903148205],"type":"Point"}
}