{
  "type": "Feature",
  "properties": {
    "iso:country": "GB",
    "wof:name": "SA61 2JN",
    "wof:placetype": "postalcode"
  },
  "geometry": {"coordinates":[-4.970791,51.803919],"type":"Point"}
}
