{
  "type": "Feature",
  "properties": {
    "iso:country":"GB",
    "wof:name":"W1H 4LD",
    "wof:placetype":"postalcode"
},
  "geometry": {"coordinates":[-0.16640726534077,51.51801771593097],"type":"Point"}
}