{
  "type": "Feature",
  "properties": {
    "iso:country": "GB",
    "wof:name": "W1H 4LD",
    "wof:placetype": "postalcode"
  },
  "geometry": {"coordinates":[-0.166407,51.518018],"type":"Point"}
}
