{
  "type": "Feature",
  "properties": {
    "date:inception_lower":"2000-12-01",
    "date:inception_upper":"2000-12-31",
    "iso:country":"GB",
    "wof:name":"W1H 4LD",
    "wof:placetype":"postalcode"
},
  "geometry": {"coordinates":[-0.166407,51.518018],"type":"Point"}
}