{
  "type": "Feature",
  "properties": {
    "iso:country": "GB",
    "wof:name": "LD2 3UR",
    "wof:placetype": "postalcode"
  },
  "geometry": {"coordinates":[-3.326959,52.119258],"type":"Point"}
}
