{
  "type": "Feature",
  "properties": {
    "iso:country":"GB",
    "wof:name":"LD2 3UR",
    "wof:placetype":"postalcode"
},
  "geometry": {"coordinates":[-3.32695916386283,52.11925790964498],"type":"Point"}
}