{
  "type": "Feature",
  "properties": {
    "date:inception_lower": "1999-06-01",
    "date:inception_upper": "1999-06-01",
    "iso:country": "GB",
    "wof:name": "CH44 5XT",
    "wof:placetype": "postalcode"
  },
  "geometry": {"coordinates":[-3.045472,53.419325],"type":"Point"}
}
