{
  "type": "Feature",
  "properties": {
    "date:inception_lower": "2010-05-01",
    "date:inception_upper": "2010-05-01",
    "iso:country": "GB",
    "wof:name": "DL15 0GH",
    "wof:placetype": "postalcode"
  },
  "geometry": {"coordinates":[-1.679951,54.711398],"type":"Point"}
}
