{
  "type": "Feature",
  "properties": {
    "iso:country":"GB",
    "wof:name":"DL15 0GH",
    "wof:placetype":"postalcode"
},
  "geometry": {"coordinates":[-1.68019127790883,54.71098551095958],"type":"Point"}
}