{
  "type": "Feature",
  "properties": {
    "iso:country":"GB",
    "wof:name":"TQ3 3FW",
    "wof:placetype":"postalcode"
},
  "geometry": {"coordinates":[-3.58754456160281,50.44307073257426],"type":"Point"}
}