{
  "type": "Feature",
  "properties": {
    "iso:country":"GB",
    "wof:name":"CT9 3NQ",
    "wof:placetype":"postalcode"
},
  "geometry": {"coordinates":[1.41207589932823,51.38417603474116],"type":"Point"}
}