{
  "type": "Feature",
  "properties": {
    "iso:country":"GB",
    "wof:name":"PL26 8SD",
    "wof:placetype":"postalcode"
},
  "geometry": {"coordinates":[-4.79256145699529,50.38162589923624],"type":"Point"}
}