{
  "type": "Feature",
  "properties": {
    "iso:country": "GB",
    "wof:name": "CW5 5SJ",
    "wof:placetype": "postalcode"
  },
  "geometry": {"coordinates":[-2.515274,53.06613],"type":"Point"}
}
