{
  "type": "Feature",
  "properties": {
    "iso:country":"GB",
    "wof:name":"G1 1PP",
    "wof:placetype":"postalcode"
},
  "geometry": {"coordinates":[-4.24031370412944,55.86018817949623],"type":"Point"}
}