{
  "type": "Feature",
  "properties": {
    "iso:country": "GB",
    "wof:name": "SW18 3JZ",
    "wof:placetype": "postalcode"
  },
  "geometry": {"coordinates":[-0.172561,51.44201],"type":"Point"}
}
