{
  "type": "Feature",
  "properties": {
    "iso:country":"GB",
    "wof:name":"NW3 4BY",
    "wof:placetype":"postalcode"
},
  "geometry": {"coordinates":[-0.16579587830594,51.54937382065165],"type":"Point"}
}