{
  "type": "Feature",
  "properties": {
    "date:inception_lower": "2011-12-01",
    "date:inception_upper": "2011-12-01",
    "iso:country": "GB",
    "wof:name": "NP22 5DY",
    "wof:placetype": "postalcode"
  },
  "geometry": {"coordinates":[-3.287922,51.75899],"type":"Point"}
}
