{
  "type": "Feature",
  "properties": {
    "iso:country": "GB",
    "wof:name": "NP22 5DY",
    "wof:placetype": "postalcode"
  },
  "geometry": {"coordinates":[-3.287922,51.75899],"type":"Point"}
}
