{
  "type": "Feature",
  "properties": {
    "iso:country":"GB",
    "wof:name":"NP22 5DY",
    "wof:placetype":"postalcode"
},
  "geometry": {"coordinates":[-3.28791160663407,51.75898579875017],"type":"Point"}
}