{
  "type": "Feature",
  "properties": {
    "date:inception_lower":"1980-01-01",
    "date:inception_upper":"1980-01-31",
    "iso:country":"GB",
    "wof:name":"E13 9AE",
    "wof:placetype":"postalcode"
},
  "geometry": {"coordinates":[0.024679,51.53143],"type":"Point"}
}