{
  "type": "Feature",
  "properties": {
    "iso:country":"GB",
    "wof:name":"E13 9AE",
    "wof:placetype":"postalcode"
},
  "geometry": {"coordinates":[0.02467876649952,51.53143029612444],"type":"Point"}
}