{
  "type": "Feature",
  "properties": {
    "iso:country":"GB",
    "wof:name":"EN2 9EJ",
    "wof:placetype":"postalcode"
},
  "geometry": {"coordinates":[-0.06897062803373,51.66849891260109],"type":"Point"}
}