{
  "type": "Feature",
  "properties": {
    "iso:country":"GB",
    "wof:name":"E18 1JR",
    "wof:placetype":"postalcode"
},
  "geometry": {"coordinates":[0.033955634511,51.59299534805724],"type":"Point"}
}