{
  "type": "Feature",
  "properties": {
    "date:inception_lower":"1980-01-01",
    "date:inception_upper":"1980-01-31",
    "iso:country":"GB",
    "wof:name":"E18 1JR",
    "wof:placetype":"postalcode"
},
  "geometry": {"coordinates":[0.033956,51.592995],"type":"Point"}
}