{
  "type": "Feature",
  "properties": {
    "iso:country":"GB",
    "wof:name":"PL5 3PJ",
    "wof:placetype":"postalcode"
},
  "geometry": {"coordinates":[-4.15844313966291,50.40916100579899],"type":"Point"}
}