{
  "type": "Feature",
  "properties": {
    "iso:country": "GB",
    "wof:name": "SS7 5SR",
    "wof:placetype": "postalcode"
  },
  "geometry": {"coordinates":[0.553379,51.56588],"type":"Point"}
}
