{
  "type": "Feature",
  "properties": {
    "iso:country":"GB",
    "wof:name":"PO19 6PT",
    "wof:placetype":"postalcode"
},
  "geometry": {"coordinates":[-0.77509092600472,50.85584915844207],"type":"Point"}
}