{
  "type": "Feature",
  "properties": {
    "date:inception_lower": "1980-01-01",
    "date:inception_upper": "1980-01-01",
    "iso:country": "GB",
    "wof:name": "TN12 9SH",
    "wof:placetype": "postalcode"
  },
  "geometry": {"coordinates":[0.480662,51.189524],"type":"Point"}
}
