{
  "type": "Feature",
  "properties": {
    "iso:country":"GB",
    "wof:name":"TN12 9SH",
    "wof:placetype":"postalcode"
},
  "geometry": {"coordinates":[0.48066231241213,51.18952431976481],"type":"Point"}
}