{
  "type": "Feature",
  "properties": {
    "iso:country": "GB",
    "wof:name": "YO32 5AX",
    "wof:placetype": "postalcode"
  },
  "geometry": {"coordinates":[-1.041635,54.033226],"type":"Point"}
}
