{
  "type": "Feature",
  "properties": {
    "iso:country":"GB",
    "wof:name":"YO32 5AX",
    "wof:placetype":"postalcode"
},
  "geometry": {"coordinates":[-1.04163458990334,54.03322563916751],"type":"Point"}
}