{
  "type": "Feature",
  "properties": {
    "date:inception_lower": "1980-01-01",
    "date:inception_upper": "1980-01-01",
    "iso:country": "GB",
    "wof:name": "RM15 4EA",
    "wof:placetype": "postalcode"
  },
  "geometry": {"coordinates":[0.243526,51.49841],"type":"Point"}
}
