{
  "type": "Feature",
  "properties": {
    "date:inception_lower": "2016-08-01",
    "date:inception_upper": "2016-08-01",
    "iso:country": "GB",
    "wof:name": "BS34 5GL",
    "wof:placetype": "postalcode"
  },
  "geometry": {"coordinates":[-2.579615,51.524877],"type":"Point"}
}
