{
  "type": "Feature",
  "properties": {
    "iso:country": "GB",
    "wof:name": "BS34 5GL",
    "wof:placetype": "postalcode"
  },
  "geometry": {"coordinates":[-2.579615,51.524877],"type":"Point"}
}
