{
  "type": "Feature",
  "properties": {
    "iso:country":"GB",
    "wof:name":"IP9 1DT",
    "wof:placetype":"postalcode"
},
  "geometry": {"coordinates":[1.20495018396447,51.99025435686269],"type":"Point"}
}