{
  "type": "Feature",
  "properties": {
    "date:inception_lower": "1990-02-01",
    "date:inception_upper": "1990-02-01",
    "iso:country": "GB",
    "wof:name": "NR28 9UU",
    "wof:placetype": "postalcode"
  },
  "geometry": {"coordinates":[1.396284,52.821],"type":"Point"}
}
