{
  "type": "Feature",
  "properties": {
    "iso:country":"GB",
    "wof:name":"NR28 9UU",
    "wof:placetype":"postalcode"
},
  "geometry": {"coordinates":[1.39626376925422,52.82098049934694],"type":"Point"}
}