{
  "type": "Feature",
  "properties": {
    "iso:country":"GB",
    "wof:name":"EX36 4QD",
    "wof:placetype":"postalcode"
},
  "geometry": {"coordinates":[-3.73374142702587,50.99664615097281],"type":"Point"}
}