{
  "type": "Feature",
  "properties": {
    "iso:country": "GB",
    "wof:name": "HR4 9SH",
    "wof:placetype": "postalcode"
  },
  "geometry": {"coordinates":[-2.720112,52.070223],"type":"Point"}
}
