{
  "type": "Feature",
  "properties": {
    "iso:country":"GB",
    "wof:name":"CB4 1NF",
    "wof:placetype":"postalcode"
},
  "geometry": {"coordinates":[0.14077593265573,52.21777109108187],"type":"Point"}
}