{
  "type": "Feature",
  "properties": {
    "iso:country":"GB",
    "wof:name":"CF35 6SP",
    "wof:placetype":"postalcode"
},
  "geometry": {"coordinates":[-3.50002172019892,51.53042996826521],"type":"Point"}
}