{
  "type": "Feature",
  "properties": {
    "date:inception_lower": "1980-01-01",
    "date:inception_upper": "1980-01-01",
    "iso:country": "GB",
    "wof:name": "CF35 6SP",
    "wof:placetype": "postalcode"
  },
  "geometry": {"coordinates":[-3.500022,51.53043],"type":"Point"}
}
