{
  "type": "Feature",
  "properties": {
    "iso:country":"GB",
    "wof:name":"SO17 1TS",
    "wof:placetype":"postalcode"
},
  "geometry": {"coordinates":[-1.39680674002236,50.93766582584045],"type":"Point"}
}