{
  "type": "Feature",
  "properties": {
    "iso:country":"GB",
    "wof:name":"N1 8LD",
    "wof:placetype":"postalcode"
},
  "geometry": {"coordinates":[-0.10019168647576,51.53324938165511],"type":"Point"}
}