{
  "type": "Feature",
  "properties": {
    "iso:country": "GB",
    "wof:name": "ST6 5JW",
    "wof:placetype": "postalcode"
  },
  "geometry": {"coordinates":[-2.212233,53.064271],"type":"Point"}
}
