{
  "type": "Feature",
  "properties": {
    "iso:country":"GB",
    "wof:name":"KT1 3RS",
    "wof:placetype":"postalcode"
},
  "geometry": {"coordinates":[-0.27641741088813,51.4100771335044],"type":"Point"}
}