{
  "type": "Feature",
  "properties": {
    "iso:country":"GB",
    "wof:name":"CF32 7BT",
    "wof:placetype":"postalcode"
},
  "geometry": {"coordinates":[-3.54425280106586,51.60450832650904],"type":"Point"}
}