{
  "type": "Feature",
  "properties": {
    "date:inception_lower": "1980-01-01",
    "date:inception_upper": "1980-01-01",
    "iso:country": "GB",
    "wof:name": "CF32 7BT",
    "wof:placetype": "postalcode"
  },
  "geometry": {"coordinates":[-3.544284,51.604596],"type":"Point"}
}
