{
  "type": "Feature",
  "properties": {
    "iso:country": "GB",
    "wof:name": "CF32 7BT",
    "wof:placetype": "postalcode"
  },
  "geometry": {"coordinates":[-3.544253,51.604508],"type":"Point"}
}
