{
  "type": "Feature",
  "properties": {
    "iso:country":"GB",
    "wof:name":"DN10 6RX",
    "wof:placetype":"postalcode"
},
  "geometry": {"coordinates":[-1.02457255350565,53.43033235331767],"type":"Point"}
}