{
  "type": "Feature",
  "properties": {
    "date:inception_lower": "1990-07-01",
    "date:inception_upper": "1990-07-01",
    "iso:country": "GB",
    "wof:name": "DN10 6RX",
    "wof:placetype": "postalcode"
  },
  "geometry": {"coordinates":[-1.024573,53.430332],"type":"Point"}
}
