{
  "type": "Feature",
  "properties": {
    "iso:country": "GB",
    "wof:name": "DN10 6RX",
    "wof:placetype": "postalcode"
  },
  "geometry": {"coordinates":[-1.024573,53.430332],"type":"Point"}
}
