{
  "type": "Feature",
  "properties": {
    "date:inception_lower":"2005-05-01",
    "date:inception_upper":"2005-05-31",
    "iso:country":"GB",
    "wof:name":"BB3 3RT",
    "wof:placetype":"postalcode"
},
  "geometry": {"coordinates":[-2.444217,53.712099],"type":"Point"}
}