{
  "type": "Feature",
  "properties": {
    "iso:country":"GB",
    "wof:name":"LE7 9BX",
    "wof:placetype":"postalcode"
},
  "geometry": {"coordinates":[-0.97239032886829,52.60194045827417],"type":"Point"}
}