{
  "type": "Feature",
  "properties": {
    "iso:country": "GB",
    "wof:name": "LE7 9BX",
    "wof:placetype": "postalcode"
  },
  "geometry": {"coordinates":[-0.97285,52.601495],"type":"Point"}
}
