{
  "type": "Feature",
  "properties": {
    "date:inception_lower": "2022-02-01",
    "date:inception_upper": "2022-02-01",
    "iso:country": "GB",
    "wof:name": "E8 3NT",
    "wof:placetype": "postalcode"
  },
  "geometry": {"coordinates":[-0.06923,51.545353],"type":"Point"}
}
