{
  "type": "Feature",
  "properties": {
    "iso:country": "GB",
    "wof:name": "L3 9PP",
    "wof:placetype": "postalcode"
  },
  "geometry": {"coordinates":[-2.994875,53.409249],"type":"Point"}
}
