{
  "type": "Feature",
  "properties": {
    "iso:country": "GB",
    "wof:name": "SO53 1JP",
    "wof:placetype": "postalcode"
  },
  "geometry": {"coordinates":[-1.390833,50.996175],"type":"Point"}
}
