{
  "type": "Feature",
  "properties": {
    "iso:country":"GB",
    "wof:name":"SO53 1JP",
    "wof:placetype":"postalcode"
},
  "geometry": {"coordinates":[-1.39083342538165,50.99617530987362],"type":"Point"}
}