{
  "type": "Feature",
  "properties": {
    "iso:country": "GB",
    "wof:name": "EN1 4QR",
    "wof:placetype": "postalcode"
  },
  "geometry": {"coordinates":[-0.049253,51.676116],"type":"Point"}
}
