{
  "type": "Feature",
  "properties": {
    "iso:country":"GB",
    "wof:name":"PE2 7AB",
    "wof:placetype":"postalcode"
},
  "geometry": {"coordinates":[-0.27065092283676,52.557576428887],"type":"Point"}
}