{
  "type": "Feature",
  "properties": {
    "iso:country":"GB",
    "wof:name":"E13 9EW",
    "wof:placetype":"postalcode"
},
  "geometry": {"coordinates":[0.03443028312754,51.53089286757051],"type":"Point"}
}