{
  "type": "Feature",
  "properties": {
    "iso:country":"GB",
    "wof:name":"SY15 6NE",
    "wof:placetype":"postalcode"
},
  "geometry": {"coordinates":[-3.2382369826265,52.54458494364383],"type":"Point"}
}