{
  "type": "Feature",
  "properties": {
    "iso:country":"GB",
    "wof:name":"PR9 0JH",
    "wof:placetype":"postalcode"
},
  "geometry": {"coordinates":[-2.99915685923421,53.65760090901595],"type":"Point"}
}