{
  "type": "Feature",
  "properties": {
    "iso:country":"GB",
    "wof:name":"W14 0HY",
    "wof:placetype":"postalcode"
},
  "geometry": {"coordinates":[-0.21917455318041,51.49732982382044],"type":"Point"}
}