{
  "type": "Feature",
  "properties": {
    "iso:country":"GB",
    "wof:name":"BB7 4SL",
    "wof:placetype":"postalcode"
},
  "geometry": {"coordinates":[-2.39053090885112,53.89433786809673],"type":"Point"}
}