{
  "type": "Feature",
  "properties": {
    "date:inception_lower":"1980-01-01",
    "date:inception_upper":"1980-01-31",
    "iso:country":"GB",
    "wof:name":"SS7 3UG",
    "wof:placetype":"postalcode"
},
  "geometry": {"coordinates":[0.590304,51.568884],"type":"Point"}
}