{
  "type": "Feature",
  "properties": {
    "iso:country":"GB",
    "wof:name":"SS7 3UG",
    "wof:placetype":"postalcode"
},
  "geometry": {"coordinates":[0.59030400527329,51.56888375208039],"type":"Point"}
}