{
  "type": "Feature",
  "properties": {
    "date:inception_lower": "2023-09-01",
    "date:inception_upper": "2023-09-01",
    "iso:country": "GB",
    "wof:name": "RM4 1FG",
    "wof:placetype": "postalcode"
  },
  "geometry": {"coordinates":[0.16855,51.634968],"type":"Point"}
}
