{
  "type": "Feature",
  "properties": {
    "iso:country": "GB",
    "wof:name": "CO15 6BB",
    "wof:placetype": "postalcode"
  },
  "geometry": {"coordinates":[1.16433,51.794382],"type":"Point"}
}
