{
  "type": "Feature",
  "properties": {
    "iso:country":"GB",
    "wof:name":"M33 6QX",
    "wof:placetype":"postalcode"
},
  "geometry": {"coordinates":[-2.33389984369964,53.42056937582984],"type":"Point"}
}