{
  "type": "Feature",
  "properties": {
    "date:inception_lower": "1983-07-01",
    "date:inception_upper": "1983-07-01",
    "iso:country": "GB",
    "wof:name": "DT9 3PN",
    "wof:placetype": "postalcode"
  },
  "geometry": {"coordinates":[-2.522396,50.949062],"type":"Point"}
}
