{
  "type": "Feature",
  "properties": {
    "iso:country": "GB",
    "wof:name": "EX39 1NP",
    "wof:placetype": "postalcode"
  },
  "geometry": {"coordinates":[-4.204657,51.048107],"type":"Point"}
}
