{
  "type": "Feature",
  "properties": {
    "iso:country":"GB",
    "wof:name":"EX39 1NP",
    "wof:placetype":"postalcode"
},
  "geometry": {"coordinates":[-4.20465729853518,51.04810746219815],"type":"Point"}
}