{
  "type": "Feature",
  "properties": {
    "iso:country": "GB",
    "wof:name": "CW5 6PB",
    "wof:placetype": "postalcode"
  },
  "geometry": {"coordinates":[-2.491092,53.089218],"type":"Point"}
}
