{
  "type": "Feature",
  "properties": {
    "iso:country":"GB",
    "wof:name":"CW5 6PB",
    "wof:placetype":"postalcode"
},
  "geometry": {"coordinates":[-2.49109237519414,53.08921771112131],"type":"Point"}
}