{
  "type": "Feature",
  "properties": {
    "iso:country":"GB",
    "wof:name":"OX33 1QF",
    "wof:placetype":"postalcode"
},
  "geometry": {"coordinates":[-1.13695105256533,51.75548720287312],"type":"Point"}
}