{
  "type": "Feature",
  "properties": {
    "date:inception_lower": "1980-01-01",
    "date:inception_upper": "1980-01-01",
    "iso:country": "GB",
    "wof:name": "HX4 9HY",
    "wof:placetype": "postalcode"
  },
  "geometry": {"coordinates":[-1.8798,53.66448],"type":"Point"}
}
