{
  "type": "Feature",
  "properties": {
    "iso:country":"GB",
    "wof:name":"NR21 9EE",
    "wof:placetype":"postalcode"
},
  "geometry": {"coordinates":[0.84486953375568,52.83180087033428],"type":"Point"}
}