{
  "type": "Feature",
  "properties": {
    "date:inception_lower": "1980-01-01",
    "date:inception_upper": "1980-01-01",
    "iso:country": "GB",
    "wof:name": "NR21 9EE",
    "wof:placetype": "postalcode"
  },
  "geometry": {"coordinates":[0.845209,52.83198],"type":"Point"}
}
