{
  "type": "Feature",
  "properties": {
    "iso:country":"GB",
    "wof:name":"EH24 9EA",
    "wof:placetype":"postalcode"
},
  "geometry": {"coordinates":[-3.12405905367945,55.83638903127945],"type":"Point"}
}