{
  "type": "Feature",
  "properties": {
    "iso:country": "GB",
    "wof:name": "SO53 1JA",
    "wof:placetype": "postalcode"
  },
  "geometry": {"coordinates":[-1.388856,50.996203],"type":"Point"}
}
