{
  "type": "Feature",
  "properties": {
    "iso:country":"GB",
    "wof:name":"SO53 1JA",
    "wof:placetype":"postalcode"
},
  "geometry": {"coordinates":[-1.38885213553281,50.99621892123402],"type":"Point"}
}