{
  "type": "Feature",
  "properties": {
    "date:inception_lower": "2004-07-01",
    "date:inception_upper": "2004-07-01",
    "iso:country": "GB",
    "wof:name": "SO53 1JA",
    "wof:placetype": "postalcode"
  },
  "geometry": {"coordinates":[-1.388856,50.996203],"type":"Point"}
}
