{
  "type": "Feature",
  "properties": {
    "iso:country":"GB",
    "wof:name":"SK9 3QJ",
    "wof:placetype":"postalcode"
},
  "geometry": {"coordinates":[-2.21113358756214,53.35130498752351],"type":"Point"}
}