{
  "type": "Feature",
  "properties": {
    "date:inception_lower": "1980-01-01",
    "date:inception_upper": "1980-01-01",
    "iso:country": "GB",
    "wof:name": "SK9 3QJ",
    "wof:placetype": "postalcode"
  },
  "geometry": {"coordinates":[-2.211134,53.351305],"type":"Point"}
}
