{
  "type": "Feature",
  "properties": {
    "iso:country": "GB",
    "wof:name": "SK9 3QJ",
    "wof:placetype": "postalcode"
  },
  "geometry": {"coordinates":[-2.211134,53.351305],"type":"Point"}
}
