{
  "type": "Feature",
  "properties": {
    "date:inception_lower": "1999-06-01",
    "date:inception_upper": "1999-06-01",
    "iso:country": "GB",
    "wof:name": "BL9 8RQ",
    "wof:placetype": "postalcode"
  },
  "geometry": {"coordinates":[-2.278616,53.579256],"type":"Point"}
}
