{
  "type": "Feature",
  "properties": {
    "iso:country":"GB",
    "wof:name":"HU15 1NS",
    "wof:placetype":"postalcode"
},
  "geometry": {"coordinates":[-0.54729391320074,53.73072582426067],"type":"Point"}
}