{
  "type": "Feature",
  "properties": {
    "iso:country": "GB",
    "wof:name": "HU15 1NS",
    "wof:placetype": "postalcode"
  },
  "geometry": {"coordinates":[-0.547294,53.730726],"type":"Point"}
}
