{
  "type": "Feature",
  "properties": {
    "date:inception_lower":"1980-01-01",
    "date:inception_upper":"1980-01-31",
    "iso:country":"GB",
    "wof:name":"HU15 1NS",
    "wof:placetype":"postalcode"
},
  "geometry": {"coordinates":[-0.547294,53.730726],"type":"Point"}
}