{
  "type": "Feature",
  "properties": {
    "iso:country": "GB",
    "wof:name": "NR32 1QG",
    "wof:placetype": "postalcode"
  },
  "geometry": {"coordinates":[1.750846,52.477835],"type":"Point"}
}
