{
  "type": "Feature",
  "properties": {
    "iso:country": "GB",
    "wof:name": "OX14 2QS",
    "wof:placetype": "postalcode"
  },
  "geometry": {"coordinates":[-1.267072,51.68694],"type":"Point"}
}
