{
  "type": "Feature",
  "properties": {
    "date:inception_lower": "1980-01-01",
    "date:inception_upper": "1980-01-01",
    "iso:country": "GB",
    "wof:name": "TR2 4QH",
    "wof:placetype": "postalcode"
  },
  "geometry": {"coordinates":[-4.936726,50.343548],"type":"Point"}
}
