{
  "type": "Feature",
  "properties": {
    "iso:country":"GB",
    "wof:name":"TR2 4QH",
    "wof:placetype":"postalcode"
},
  "geometry": {"coordinates":[-4.93675416605296,50.34354721212597],"type":"Point"}
}