{
  "type": "Feature",
  "properties": {
    "iso:country":"GB",
    "wof:name":"LE3 8GB",
    "wof:placetype":"postalcode"
},
  "geometry": {"coordinates":[-1.20733945571179,52.65747824110816],"type":"Point"}
}