{
  "type": "Feature",
  "properties": {
    "date:inception_lower": "1980-01-01",
    "date:inception_upper": "1980-01-01",
    "iso:country": "GB",
    "wof:name": "AL3 8LY",
    "wof:placetype": "postalcode"
  },
  "geometry": {"coordinates":[-0.460348,51.837115],"type":"Point"}
}
