{
  "type": "Feature",
  "properties": {
    "iso:country":"GB",
    "wof:name":"AL3 8LY",
    "wof:placetype":"postalcode"
},
  "geometry": {"coordinates":[-0.46034834451806,51.8371146107668],"type":"Point"}
}