{
  "type": "Feature",
  "properties": {
    "date:inception_lower":"1980-01-01",
    "date:inception_upper":"1980-01-31",
    "iso:country":"GB",
    "wof:name":"DH4 5HE",
    "wof:placetype":"postalcode"
},
  "geometry": {"coordinates":[-1.481281,54.849024],"type":"Point"}
}