{
  "type": "Feature",
  "properties": {
    "iso:country":"GB",
    "wof:name":"DH4 5HE",
    "wof:placetype":"postalcode"
},
  "geometry": {"coordinates":[-1.4812810986893,54.84902425427414],"type":"Point"}
}