{
  "type": "Feature",
  "properties": {
    "iso:country": "GB",
    "wof:name": "WS11 8JA",
    "wof:placetype": "postalcode"
  },
  "geometry": {"coordinates":[-2.019382,52.670786],"type":"Point"}
}
