{
  "type": "Feature",
  "properties": {
    "iso:country":"GB",
    "wof:name":"SL0 0EN",
    "wof:placetype":"postalcode"
},
  "geometry": {"coordinates":[-0.51617949004197,51.52932992215217],"type":"Point"}
}