{
  "type": "Feature",
  "properties": {
    "iso:country": "GB",
    "wof:name": "L4 1XG",
    "wof:placetype": "postalcode"
  },
  "geometry": {"coordinates":[-2.980943,53.437914],"type":"Point"}
}
