{
  "type": "Feature",
  "properties": {
    "iso:country":"GB",
    "wof:name":"L4 1XG",
    "wof:placetype":"postalcode"
},
  "geometry": {"coordinates":[-2.98094267574882,53.43791444139873],"type":"Point"}
}