{
  "type": "Feature",
  "properties": {
    "iso:country": "GB",
    "wof:name": "BN13 1DF",
    "wof:placetype": "postalcode"
  },
  "geometry": {"coordinates":[-0.402872,50.823587],"type":"Point"}
}
