{
  "type": "Feature",
  "properties": {
    "iso:country":"GB",
    "wof:name":"BN13 1DF",
    "wof:placetype":"postalcode"
},
  "geometry": {"coordinates":[-0.40287195174449,50.82358712052383],"type":"Point"}
}