{
  "type": "Feature",
  "properties": {
    "date:inception_lower": "1980-01-01",
    "date:inception_upper": "1980-01-01",
    "iso:country": "GB",
    "wof:name": "TS6 9JN",
    "wof:placetype": "postalcode"
  },
  "geometry": {"coordinates":[-1.138602,54.560431],"type":"Point"}
}
