{
  "type": "Feature",
  "properties": {
    "date:inception_lower": "2002-07-01",
    "date:inception_upper": "2002-07-01",
    "iso:country": "GB",
    "wof:name": "ST1 5GA",
    "wof:placetype": "postalcode"
  },
  "geometry": {"coordinates":[-2.196797,53.020484],"type":"Point"}
}
