{
  "type": "Feature",
  "properties": {
    "date:inception_lower": "1999-06-01",
    "date:inception_upper": "1999-06-01",
    "iso:country": "GB",
    "wof:name": "CF3 4AQ",
    "wof:placetype": "postalcode"
  },
  "geometry": {"coordinates":[-3.134318,51.508506],"type":"Point"}
}
