{
  "type": "Feature",
  "properties": {
    "iso:country":"GB",
    "wof:name":"CF3 0HP",
    "wof:placetype":"postalcode"
},
  "geometry": {"coordinates":[-3.09468772318376,51.5245459802109],"type":"Point"}
}