{
  "type": "Feature",
  "properties": {
    "iso:country": "GB",
    "wof:name": "CF3 0HP",
    "wof:placetype": "postalcode"
  },
  "geometry": {"coordinates":[-3.094688,51.524546],"type":"Point"}
}
