{
  "type": "Feature",
  "properties": {
    "iso:country": "GB",
    "wof:name": "GL15 5RS",
    "wof:placetype": "postalcode"
  },
  "geometry": {"coordinates":[-2.529893,51.725148],"type":"Point"}
}
