{
  "type": "Feature",
  "properties": {
    "iso:country":"GB",
    "wof:name":"GL15 5RS",
    "wof:placetype":"postalcode"
},
  "geometry": {"coordinates":[-2.52989246096845,51.72515274487441],"type":"Point"}
}