{
  "type": "Feature",
  "properties": {
    "iso:country": "GB",
    "wof:name": "SK10 4RX",
    "wof:placetype": "postalcode"
  },
  "geometry": {"coordinates":[-2.208618,53.264307],"type":"Point"}
}
