{
  "type": "Feature",
  "properties": {
    "iso:country":"GB",
    "wof:name":"SK10 4RX",
    "wof:placetype":"postalcode"
},
  "geometry": {"coordinates":[-2.21193923624479,53.26543437878171],"type":"Point"}
}