{
  "type": "Feature",
  "properties": {
    "iso:country": "GB",
    "wof:name": "HA8 6PW",
    "wof:placetype": "postalcode"
  },
  "geometry": {"coordinates":[-0.285252,51.610037],"type":"Point"}
}
