{
  "type": "Feature",
  "properties": {
    "iso:country":"GB",
    "wof:name":"HA8 6PW",
    "wof:placetype":"postalcode"
},
  "geometry": {"coordinates":[-0.2851934857402,51.60991701322647],"type":"Point"}
}