{
  "type": "Feature",
  "properties": {
    "iso:country":"GB",
    "wof:name":"RM11 3EB",
    "wof:placetype":"postalcode"
},
  "geometry": {"coordinates":[0.23665391622116,51.57900113776343],"type":"Point"}
}