{
  "type": "Feature",
  "properties": {
    "iso:country":"GB",
    "wof:name":"NG9 1GZ",
    "wof:placetype":"postalcode"
},
  "geometry": {"coordinates":[-1.2192326955135,52.91892400027769],"type":"Point"}
}