{
  "type": "Feature",
  "properties": {
    "iso:country":"GB",
    "wof:name":"TD7 4PT",
    "wof:placetype":"postalcode"
},
  "geometry": {"coordinates":[-2.82278998314764,55.56507629948322],"type":"Point"}
}