{
  "type": "Feature",
  "properties": {
    "iso:country":"GB",
    "wof:name":"AB15 9RS",
    "wof:placetype":"postalcode"
},
  "geometry": {"coordinates":[-2.18531806188147,57.11931423513904],"type":"Point"}
}