{
  "type": "Feature",
  "properties": {
    "iso:country": "GB",
    "wof:name": "NE9 7QJ",
    "wof:placetype": "postalcode"
  },
  "geometry": {"coordinates":[-1.555698,54.922352],"type":"Point"}
}
