{
  "type": "Feature",
  "properties": {
    "iso:country":"GB",
    "wof:name":"NE9 7QJ",
    "wof:placetype":"postalcode"
},
  "geometry": {"coordinates":[-1.55569779529481,54.92235175221088],"type":"Point"}
}