{
  "type": "Feature",
  "properties": {
    "iso:country":"GB",
    "wof:name":"DY9 8TF",
    "wof:placetype":"postalcode"
},
  "geometry": {"coordinates":[-2.1086015371642,52.45458738782797],"type":"Point"}
}