{
  "type": "Feature",
  "properties": {
    "date:inception_lower": "1980-01-01",
    "date:inception_upper": "1980-01-01",
    "iso:country": "GB",
    "wof:name": "DY9 8TF",
    "wof:placetype": "postalcode"
  },
  "geometry": {"coordinates":[-2.108595,52.454611],"type":"Point"}
}
