{
  "type": "Feature",
  "properties": {
    "iso:country":"GB",
    "wof:name":"BH24 4AT",
    "wof:placetype":"postalcode"
},
  "geometry": {"coordinates":[-1.68421137230984,50.82499655114994],"type":"Point"}
}