{
  "type": "Feature",
  "properties": {
    "iso:country":"GB",
    "wof:name":"L26 6BR",
    "wof:placetype":"postalcode"
},
  "geometry": {"coordinates":[-2.82167604419563,53.37164644834258],"type":"Point"}
}