{
  "type": "Feature",
  "properties": {
    "date:inception_lower": "2006-03-01",
    "date:inception_upper": "2006-03-01",
    "iso:country": "GB",
    "wof:name": "L26 6BR",
    "wof:placetype": "postalcode"
  },
  "geometry": {"coordinates":[-2.821676,53.371646],"type":"Point"}
}
