{
  "type": "Feature",
  "properties": {
    "iso:country": "GB",
    "wof:name": "RH8 0NR",
    "wof:placetype": "postalcode"
  },
  "geometry": {"coordinates":[-0.009291,51.262875],"type":"Point"}
}
