{
  "type": "Feature",
  "properties": {
    "iso:country":"GB",
    "wof:name":"CM4 9JP",
    "wof:placetype":"postalcode"
},
  "geometry": {"coordinates":[0.42338075822713,51.68979292017224],"type":"Point"}
}