{
  "type": "Feature",
  "properties": {
    "iso:country":"GB",
    "wof:name":"PO15 7EZ",
    "wof:placetype":"postalcode"
},
  "geometry": {"coordinates":[-1.2598885367768,50.88429035924128],"type":"Point"}
}