{
  "type": "Feature",
  "properties": {
    "date:inception_lower": "2024-01-01",
    "date:inception_upper": "2024-01-01",
    "iso:country": "GB",
    "wof:name": "IP22 1FP",
    "wof:placetype": "postalcode"
  },
  "geometry": {"coordinates":[1.011843,52.343612],"type":"Point"}
}
