{
  "type": "Feature",
  "properties": {
    "iso:country":"GB",
    "wof:name":"BB9 7XG",
    "wof:placetype":"postalcode"
},
  "geometry": {"coordinates":[-2.21279365378267,53.83934764405163],"type":"Point"}
}