{
  "type": "Feature",
  "properties": {
    "iso:country": "GB",
    "wof:name": "BB9 7XG",
    "wof:placetype": "postalcode"
  },
  "geometry": {"coordinates":[-2.212794,53.839348],"type":"Point"}
}
