{
  "type": "Feature",
  "properties": {
    "date:inception_lower":"1995-07-01",
    "date:inception_upper":"1995-07-31",
    "iso:country":"GB",
    "wof:name":"L23 1TG",
    "wof:placetype":"postalcode"
},
  "geometry": {"coordinates":[-2.997007,53.497196],"type":"Point"}
}