{
  "type": "Feature",
  "properties": {
    "iso:country": "GB",
    "wof:name": "L23 1TG",
    "wof:placetype": "postalcode"
  },
  "geometry": {"coordinates":[-2.997007,53.497196],"type":"Point"}
}
