{
  "type": "Feature",
  "properties": {
    "iso:country":"GB",
    "wof:name":"L23 1TG",
    "wof:placetype":"postalcode"
},
  "geometry": {"coordinates":[-2.99700837768381,53.4971797150944],"type":"Point"}
}