{
  "type": "Feature",
  "properties": {
    "iso:country":"GB",
    "wof:name":"TN40 2UP",
    "wof:placetype":"postalcode"
},
  "geometry": {"coordinates":[0.48633884478334,50.84912600522036],"type":"Point"}
}