{
  "type": "Feature",
  "properties": {
    "iso:country": "GB",
    "wof:name": "YO61 2QY",
    "wof:placetype": "postalcode"
  },
  "geometry": {"coordinates":[-1.331778,54.09312],"type":"Point"}
}
