{
  "type": "Feature",
  "properties": {
    "iso:country": "GB",
    "wof:name": "DT3 4BJ",
    "wof:placetype": "postalcode"
  },
  "geometry": {"coordinates":[-2.479003,50.642353],"type":"Point"}
}
