{
  "type": "Feature",
  "properties": {
    "iso:country":"GB",
    "wof:name":"DT3 4BJ",
    "wof:placetype":"postalcode"
},
  "geometry": {"coordinates":[-2.47883515321712,50.64227419454224],"type":"Point"}
}