{
  "type": "Feature",
  "properties": {
    "iso:country":"GB",
    "wof:name":"GL4 3QR",
    "wof:placetype":"postalcode"
},
  "geometry": {"coordinates":[-2.20890074707706,51.85525564634992],"type":"Point"}
}