{
  "type": "Feature",
  "properties": {
    "iso:country":"GB",
    "wof:name":"DT11 0BA",
    "wof:placetype":"postalcode"
},
  "geometry": {"coordinates":[-2.2749247875585,50.81783266988514],"type":"Point"}
}