{
  "type": "Feature",
  "properties": {
    "date:inception_lower":"2003-11-01",
    "date:inception_upper":"2003-11-30",
    "iso:country":"GB",
    "wof:name":"DT11 0BA",
    "wof:placetype":"postalcode"
},
  "geometry": {"coordinates":[-2.274925,50.817833],"type":"Point"}
}