{
  "type": "Feature",
  "properties": {
    "iso:country":"GB",
    "wof:name":"LL28 5UB",
    "wof:placetype":"postalcode"
},
  "geometry": {"coordinates":[-3.79185556076621,53.21808103538627],"type":"Point"}
}