{
  "type": "Feature",
  "properties": {
    "date:inception_lower":"2012-10-01",
    "date:inception_upper":"2012-10-31",
    "iso:country":"GB",
    "wof:name":"HX2 6NG",
    "wof:placetype":"postalcode"
},
  "geometry": {"coordinates":[-1.940324,53.726175],"type":"Point"}
}