{
  "type": "Feature",
  "properties": {
    "iso:country":"GB",
    "wof:name":"HX2 6NG",
    "wof:placetype":"postalcode"
},
  "geometry": {"coordinates":[-1.94032419837196,53.72617468054031],"type":"Point"}
}