{
  "type": "Feature",
  "properties": {
    "date:inception_lower": "1980-01-01",
    "date:inception_upper": "1980-01-01",
    "iso:country": "GB",
    "wof:name": "CV4 9NP",
    "wof:placetype": "postalcode"
  },
  "geometry": {"coordinates":[-1.582079,52.404437],"type":"Point"}
}
