{
  "type": "Feature",
  "properties": {
    "iso:country":"GB",
    "wof:name":"NG15 7NW",
    "wof:placetype":"postalcode"
},
  "geometry": {"coordinates":[-1.20653393278447,53.03344623012685],"type":"Point"}
}