{
  "type": "Feature",
  "properties": {
    "iso:country": "GB",
    "wof:name": "EX2 5PW",
    "wof:placetype": "postalcode"
  },
  "geometry": {"coordinates":[-3.501252,50.720604],"type":"Point"}
}
