{
  "type": "Feature",
  "properties": {
    "iso:country":"GB",
    "wof:name":"EX2 5PW",
    "wof:placetype":"postalcode"
},
  "geometry": {"coordinates":[-3.50125155854557,50.72060402449577],"type":"Point"}
}