{
  "type": "Feature",
  "properties": {
    "date:inception_lower":"2006-09-01",
    "date:inception_upper":"2006-09-30",
    "iso:country":"GB",
    "wof:name":"EX2 5PW",
    "wof:placetype":"postalcode"
},
  "geometry": {"coordinates":[-3.501252,50.720604],"type":"Point"}
}