{
  "type": "Feature",
  "properties": {
    "date:inception_lower": "2024-08-01",
    "date:inception_upper": "2024-08-01",
    "iso:country": "GB",
    "wof:name": "DE74 2ZB",
    "wof:placetype": "postalcode"
  },
  "geometry": {"coordinates":[-1.357351,52.836428],"type":"Point"}
}
