{
  "type": "Feature",
  "properties": {
    "iso:country":"GB",
    "wof:name":"DL13 3RE",
    "wof:placetype":"postalcode"
},
  "geometry": {"coordinates":[-1.81295962637759,54.67328527063367],"type":"Point"}
}