{
  "type": "Feature",
  "properties": {
    "iso:country": "GB",
    "wof:name": "BH11 0GE",
    "wof:placetype": "postalcode"
  },
  "geometry": {"coordinates":[-1.924228,50.758152],"type":"Point"}
}
