{
  "type": "Feature",
  "properties": {
    "iso:country": "GB",
    "wof:name": "WA2 8UH",
    "wof:placetype": "postalcode"
  },
  "geometry": {"coordinates":[-2.600292,53.421469],"type":"Point"}
}
