{
  "type": "Feature",
  "properties": {
    "iso:country":"GB",
    "wof:name":"PO5 3AY",
    "wof:placetype":"postalcode"
},
  "geometry": {"coordinates":[-1.09363911044529,50.7887666876342],"type":"Point"}
}