{
  "type": "Feature",
  "properties": {
    "iso:country":"GB",
    "wof:name":"LA3 2RB",
    "wof:placetype":"postalcode"
},
  "geometry": {"coordinates":[-2.89538024210247,54.04129291273617],"type":"Point"}
}