{
  "type": "Feature",
  "properties": {
    "iso:country":"GB",
    "wof:name":"NR14 8DD",
    "wof:placetype":"postalcode"
},
  "geometry": {"coordinates":[1.26869658289295,52.58008602664241],"type":"Point"}
}