{
  "type": "Feature",
  "properties": {
    "iso:country": "GB",
    "wof:name": "S74 0HZ",
    "wof:placetype": "postalcode"
  },
  "geometry": {"coordinates":[-1.42855,53.505737],"type":"Point"}
}
