{
  "type": "Feature",
  "properties": {
    "iso:country": "GB",
    "wof:name": "CM3 1SH",
    "wof:placetype": "postalcode"
  },
  "geometry": {"coordinates":[0.509345,51.832749],"type":"Point"}
}
