{
  "type": "Feature",
  "properties": {
    "iso:country": "GB",
    "wof:name": "DN21 3SH",
    "wof:placetype": "postalcode"
  },
  "geometry": {"coordinates":[-0.669085,53.495983],"type":"Point"}
}
