{
  "type": "Feature",
  "properties": {
    "iso:country":"GB",
    "wof:name":"CT4 6JL",
    "wof:placetype":"postalcode"
},
  "geometry": {"coordinates":[1.11692181773251,51.21132528887198],"type":"Point"}
}