{
  "type": "Feature",
  "properties": {
    "iso:country":"GB",
    "wof:name":"BL6 7RR",
    "wof:placetype":"postalcode"
},
  "geometry": {"coordinates":[-2.56008157084208,53.60294426806056],"type":"Point"}
}