{
  "type": "Feature",
  "properties": {
    "iso:country":"GB",
    "wof:name":"NG3 7BH",
    "wof:placetype":"postalcode"
},
  "geometry": {"coordinates":[-1.11175219065081,52.9614899763348],"type":"Point"}
}