{
  "type": "Feature",
  "properties": {
    "date:inception_lower": "1980-01-01",
    "date:inception_upper": "1980-01-01",
    "iso:country": "GB",
    "wof:name": "NG3 7BH",
    "wof:placetype": "postalcode"
  },
  "geometry": {"coordinates":[-1.111752,52.96149],"type":"Point"}
}
