{
  "type": "Feature",
  "properties": {
    "iso:country": "GB",
    "wof:name": "SW1X 0LN",
    "wof:placetype": "postalcode"
  },
  "geometry": {"coordinates":[-0.161451,51.498993],"type":"Point"}
}
