{
  "type": "Feature",
  "properties": {
    "iso:country": "GB",
    "wof:name": "EN6 3JR",
    "wof:placetype": "postalcode"
  },
  "geometry": {"coordinates":[-0.202928,51.706423],"type":"Point"}
}
