{
  "type": "Feature",
  "properties": {
    "iso:country":"GB",
    "wof:name":"EN6 3JR",
    "wof:placetype":"postalcode"
},
  "geometry": {"coordinates":[-0.20292836560626,51.70642305259592],"type":"Point"}
}