{
  "type": "Feature",
  "properties": {
    "date:inception_lower": "2005-06-01",
    "date:inception_upper": "2005-06-01",
    "iso:country": "GB",
    "wof:name": "EN6 3JR",
    "wof:placetype": "postalcode"
  },
  "geometry": {"coordinates":[-0.202852,51.7063],"type":"Point"}
}
