{
  "type": "Feature",
  "properties": {
    "date:inception_lower": "2020-01-01",
    "date:inception_upper": "2020-01-01",
    "iso:country": "GB",
    "wof:name": "KT15 2GS",
    "wof:placetype": "postalcode"
  },
  "geometry": {"coordinates":[-0.48484,51.374334],"type":"Point"}
}
