{
  "type": "Feature",
  "properties": {
    "iso:country": "GB",
    "wof:name": "B67 5DZ",
    "wof:placetype": "postalcode"
  },
  "geometry": {"coordinates":[-1.97599,52.471195],"type":"Point"}
}
