{
  "type": "Feature",
  "properties": {
    "iso:country":"GB",
    "wof:name":"HX3 7AT",
    "wof:placetype":"postalcode"
},
  "geometry": {"coordinates":[-1.83719356526135,53.73265844167681],"type":"Point"}
}