{
  "type": "Feature",
  "properties": {
    "date:inception_lower":"2011-11-01",
    "date:inception_upper":"2011-11-30",
    "iso:country":"GB",
    "wof:name":"TS18 3BY",
    "wof:placetype":"postalcode"
},
  "geometry": {"coordinates":[-1.319585,54.554394],"type":"Point"}
}