{
  "type": "Feature",
  "properties": {
    "iso:country":"GB",
    "wof:name":"TS18 3BY",
    "wof:placetype":"postalcode"
},
  "geometry": {"coordinates":[-1.31958546354035,54.55439356253477],"type":"Point"}
}