{
  "type": "Feature",
  "properties": {
    "date:inception_lower": "1991-09-01",
    "date:inception_upper": "1991-09-01",
    "iso:country": "GB",
    "wof:name": "RG12 7HF",
    "wof:placetype": "postalcode"
  },
  "geometry": {"coordinates":[-0.757889,51.390703],"type":"Point"}
}
