{
  "type": "Feature",
  "properties": {
    "iso:country":"GB",
    "wof:name":"RG12 7HF",
    "wof:placetype":"postalcode"
},
  "geometry": {"coordinates":[-0.75788942268047,51.39070267428746],"type":"Point"}
}