{
  "type": "Feature",
  "properties": {
    "iso:country":"GB",
    "wof:name":"PE38 0BN",
    "wof:placetype":"postalcode"
},
  "geometry": {"coordinates":[0.29202821108383,52.58373306492266],"type":"Point"}
}