{
  "type": "Feature",
  "properties": {
    "iso:country":"GB",
    "wof:name":"G72 0BJ",
    "wof:placetype":"postalcode"
},
  "geometry": {"coordinates":[-4.09415450329217,55.7926544182882],"type":"Point"}
}