{
  "type": "Feature",
  "properties": {
    "iso:country": "GB",
    "wof:name": "G72 0BJ",
    "wof:placetype": "postalcode"
  },
  "geometry": {"coordinates":[-4.093988,55.792752],"type":"Point"}
}
