{
  "type": "Feature",
  "properties": {
    "iso:country":"GB",
    "wof:name":"CH5 2TB",
    "wof:placetype":"postalcode"
},
  "geometry": {"coordinates":[-3.02058073176844,53.20838766013871],"type":"Point"}
}