{
  "type": "Feature",
  "properties": {
    "date:inception_lower": "1980-01-01",
    "date:inception_upper": "1980-01-01",
    "iso:country": "GB",
    "wof:name": "NR14 7AS",
    "wof:placetype": "postalcode"
  },
  "geometry": {"coordinates":[1.450919,52.578607],"type":"Point"}
}
