{
  "type": "Feature",
  "properties": {
    "iso:country":"GB",
    "wof:name":"LL69 9UG",
    "wof:placetype":"postalcode"
},
  "geometry": {"coordinates":[-4.32603447158031,53.36896521801461],"type":"Point"}
}