{
  "type": "Feature",
  "properties": {
    "iso:country": "GB",
    "wof:name": "LL69 9UG",
    "wof:placetype": "postalcode"
  },
  "geometry": {"coordinates":[-4.326034,53.368965],"type":"Point"}
}
