{
  "type": "Feature",
  "properties": {
    "date:inception_lower": "2016-04-01",
    "date:inception_upper": "2016-04-01",
    "iso:country": "GB",
    "wof:name": "SE8 4EQ",
    "wof:placetype": "postalcode"
  },
  "geometry": {"coordinates":[-0.029544,51.472113],"type":"Point"}
}
