{
  "type": "Feature",
  "properties": {
    "iso:country": "GB",
    "wof:name": "SE8 4EQ",
    "wof:placetype": "postalcode"
  },
  "geometry": {"coordinates":[-0.029547,51.472041],"type":"Point"}
}
