{
  "type": "Feature",
  "properties": {
    "iso:country":"GB",
    "wof:name":"SE8 4EQ",
    "wof:placetype":"postalcode"
},
  "geometry": {"coordinates":[-0.02685264177339,51.47402705999006],"type":"Point"}
}