{
  "type": "Feature",
  "properties": {
    "iso:country": "GB",
    "wof:name": "WF9 5JY",
    "wof:placetype": "postalcode"
  },
  "geometry": {"coordinates":[-1.374746,53.627091],"type":"Point"}
}
