{
  "type": "Feature",
  "properties": {
    "iso:country":"GB",
    "wof:name":"WF9 5JY",
    "wof:placetype":"postalcode"
},
  "geometry": {"coordinates":[-1.37474616951375,53.62709050693988],"type":"Point"}
}