{
  "type": "Feature",
  "properties": {
    "iso:country":"GB",
    "wof:name":"TF4 2EG",
    "wof:placetype":"postalcode"
},
  "geometry": {"coordinates":[-2.46663950669594,52.66491605147335],"type":"Point"}
}