{
  "type": "Feature",
  "properties": {
    "iso:country":"GB",
    "wof:name":"WF17 8DN",
    "wof:placetype":"postalcode"
},
  "geometry": {"coordinates":[-1.6596957186757,53.72070059196261],"type":"Point"}
}