{
  "type": "Feature",
  "properties": {
    "date:inception_lower": "2019-07-01",
    "date:inception_upper": "2019-07-01",
    "iso:country": "GB",
    "wof:name": "PE30 9FT",
    "wof:placetype": "postalcode"
  },
  "geometry": {"coordinates":[0.400617,52.757455],"type":"Point"}
}
