{
  "type": "Feature",
  "properties": {
    "date:inception_lower": "1992-08-01",
    "date:inception_upper": "1992-08-01",
    "iso:country": "GB",
    "wof:name": "DE75 7JG",
    "wof:placetype": "postalcode"
  },
  "geometry": {"coordinates":[-1.34223,53.002174],"type":"Point"}
}
