{
  "type": "Feature",
  "properties": {
    "iso:country": "GB",
    "wof:name": "DE75 7JG",
    "wof:placetype": "postalcode"
  },
  "geometry": {"coordinates":[-1.340933,53.004199],"type":"Point"}
}
