{
  "type": "Feature",
  "properties": {
    "date:inception_lower":"2002-07-01",
    "date:inception_upper":"2002-07-31",
    "iso:country":"GB",
    "wof:name":"NG23 6JD",
    "wof:placetype":"postalcode"
},
  "geometry": {"coordinates":[-0.80761,53.145228],"type":"Point"}
}