{
  "type": "Feature",
  "properties": {
    "date:inception_lower": "2019-07-01",
    "date:inception_upper": "2019-07-01",
    "iso:country": "GB",
    "wof:name": "CF3 6AU",
    "wof:placetype": "postalcode"
  },
  "geometry": {"coordinates":[-3.122563,51.534048],"type":"Point"}
}
