{
  "type": "Feature",
  "properties": {
    "iso:country": "GB",
    "wof:name": "CF3 6AU",
    "wof:placetype": "postalcode"
  },
  "geometry": {"coordinates":[-3.122563,51.534048],"type":"Point"}
}
