{
  "type": "Feature",
  "properties": {
    "iso:country": "GB",
    "wof:name": "DN37 9AG",
    "wof:placetype": "postalcode"
  },
  "geometry": {"coordinates":[-0.121122,53.569623],"type":"Point"}
}
