{
  "type": "Feature",
  "properties": {
    "iso:country": "GB",
    "wof:name": "SE19 3JT",
    "wof:placetype": "postalcode"
  },
  "geometry": {"coordinates":[-0.092617,51.420134],"type":"Point"}
}
