{
  "type": "Feature",
  "properties": {
    "iso:country":"GB",
    "wof:name":"M20 6AP",
    "wof:placetype":"postalcode"
},
  "geometry": {"coordinates":[-2.2317421286816,53.42274403606304],"type":"Point"}
}