{
  "type": "Feature",
  "properties": {
    "date:inception_lower": "1993-08-01",
    "date:inception_upper": "1993-08-01",
    "iso:country": "GB",
    "wof:name": "ME14 4JQ",
    "wof:placetype": "postalcode"
  },
  "geometry": {"coordinates":[0.573324,51.27022],"type":"Point"}
}
