{
  "type": "Feature",
  "properties": {
    "iso:country":"GB",
    "wof:name":"ML11 0JG",
    "wof:placetype":"postalcode"
},
  "geometry": {"coordinates":[-3.94787153674247,55.66626752240978],"type":"Point"}
}