{
  "type": "Feature",
  "properties": {
    "iso:country": "GB",
    "wof:name": "ML11 0JG",
    "wof:placetype": "postalcode"
  },
  "geometry": {"coordinates":[-3.947871,55.666268],"type":"Point"}
}
