{
  "type": "Feature",
  "properties": {
    "iso:country":"GB",
    "wof:name":"DH9 8AS",
    "wof:placetype":"postalcode"
},
  "geometry": {"coordinates":[-1.70172052489403,54.87568206032525],"type":"Point"}
}