{
  "type": "Feature",
  "properties": {
    "iso:country": "GB",
    "wof:name": "CT5 1FL",
    "wof:placetype": "postalcode"
  },
  "geometry": {"coordinates":[1.038378,51.357548],"type":"Point"}
}
