{
  "type": "Feature",
  "properties": {
    "iso:country":"GB",
    "wof:name":"CT5 1FL",
    "wof:placetype":"postalcode"
},
  "geometry": {"coordinates":[1.03837804706,51.35754816064614],"type":"Point"}
}