{
  "type": "Feature",
  "properties": {
    "date:inception_lower": "2011-08-01",
    "date:inception_upper": "2011-08-01",
    "iso:country": "GB",
    "wof:name": "BA12 8FP",
    "wof:placetype": "postalcode"
  },
  "geometry": {"coordinates":[-2.206769,51.204379],"type":"Point"}
}
