{
  "type": "Feature",
  "properties": {
    "iso:country":"GB",
    "wof:name":"BA12 8FP",
    "wof:placetype":"postalcode"
},
  "geometry": {"coordinates":[-2.20676944003111,51.20437870355173],"type":"Point"}
}