{
  "type": "Feature",
  "properties": {
    "iso:country":"GB",
    "wof:name":"SY21 7NS",
    "wof:placetype":"postalcode"
},
  "geometry": {"coordinates":[-3.14810427697866,52.6529091415253],"type":"Point"}
}