{
  "type": "Feature",
  "properties": {
    "iso:country": "GB",
    "wof:name": "SY21 7NS",
    "wof:placetype": "postalcode"
  },
  "geometry": {"coordinates":[-3.148104,52.652909],"type":"Point"}
}
