{
  "type": "Feature",
  "properties": {
    "iso:country":"GB",
    "wof:name":"OX16 9TE",
    "wof:placetype":"postalcode"
},
  "geometry": {"coordinates":[-1.3254393304663,52.04544738294731],"type":"Point"}
}