{
  "type": "Feature",
  "properties": {
    "date:inception_lower": "1980-01-01",
    "date:inception_upper": "1980-01-01",
    "iso:country": "GB",
    "wof:name": "OX16 9TE",
    "wof:placetype": "postalcode"
  },
  "geometry": {"coordinates":[-1.325439,52.045447],"type":"Point"}
}
