{
  "type": "Feature",
  "properties": {
    "iso:country":"GB",
    "wof:name":"NR16 2QZ",
    "wof:placetype":"postalcode"
},
  "geometry": {"coordinates":[0.91480357184886,52.46473600918974],"type":"Point"}
}