{
  "type": "Feature",
  "properties": {
    "iso:country": "GB",
    "wof:name": "RH1 1SR",
    "wof:placetype": "postalcode"
  },
  "geometry": {"coordinates":[-0.167116,51.242044],"type":"Point"}
}
