{
  "type": "Feature",
  "properties": {
    "date:inception_lower": "2005-07-01",
    "date:inception_upper": "2005-07-01",
    "iso:country": "GB",
    "wof:name": "RH1 1SR",
    "wof:placetype": "postalcode"
  },
  "geometry": {"coordinates":[-0.170989,51.240197],"type":"Point"}
}
