{
  "type": "Feature",
  "properties": {
    "iso:country":"GB",
    "wof:name":"RH1 1SR",
    "wof:placetype":"postalcode"
},
  "geometry": {"coordinates":[-0.16711601665736,51.24204402301901],"type":"Point"}
}