{
  "type": "Feature",
  "properties": {
    "iso:country":"GB",
    "wof:name":"CW11 4JW",
    "wof:placetype":"postalcode"
},
  "geometry": {"coordinates":[-2.35190673638528,53.1427192479053],"type":"Point"}
}