{
  "type": "Feature",
  "properties": {
    "date:inception_lower": "1995-12-01",
    "date:inception_upper": "1995-12-01",
    "iso:country": "GB",
    "wof:name": "CW11 4JW",
    "wof:placetype": "postalcode"
  },
  "geometry": {"coordinates":[-2.351907,53.142719],"type":"Point"}
}
