{
  "type": "Feature",
  "properties": {
    "iso:country":"GB",
    "wof:name":"HA0 1HR",
    "wof:placetype":"postalcode"
},
  "geometry": {"coordinates":[-0.29702813519447,51.53831316224689],"type":"Point"}
}