{
  "type": "Feature",
  "properties": {
    "iso:country": "GB",
    "wof:name": "HS5 3TL",
    "wof:placetype": "postalcode"
  },
  "geometry": {"coordinates":[-7.009311,57.769917],"type":"Point"}
}
