{
  "type": "Feature",
  "properties": {
    "iso:country":"GB",
    "wof:name":"HS5 3TL",
    "wof:placetype":"postalcode"
},
  "geometry": {"coordinates":[-7.00931145740006,57.76991738037057],"type":"Point"}
}