{
  "type": "Feature",
  "properties": {
    "iso:country":"GB",
    "wof:name":"DA7 5PE",
    "wof:placetype":"postalcode"
},
  "geometry": {"coordinates":[0.14382331052957,51.47447459888575],"type":"Point"}
}