{
  "type": "Feature",
  "properties": {
    "iso:country":"GB",
    "wof:name":"RH10 3TH",
    "wof:placetype":"postalcode"
},
  "geometry": {"coordinates":[-0.15413776845866,51.12880771844052],"type":"Point"}
}