{
  "type": "Feature",
  "properties": {
    "date:inception_lower": "1980-01-01",
    "date:inception_upper": "1980-01-01",
    "iso:country": "GB",
    "wof:name": "SA5 5PR",
    "wof:placetype": "postalcode"
  },
  "geometry": {"coordinates":[-3.978299,51.657641],"type":"Point"}
}
