{
  "type": "Feature",
  "properties": {
    "iso:country":"GB",
    "wof:name":"WV8 1XH",
    "wof:placetype":"postalcode"
},
  "geometry": {"coordinates":[-2.15282944342253,52.61780362995876],"type":"Point"}
}