{
  "type": "Feature",
  "properties": {
    "date:inception_lower": "1981-06-01",
    "date:inception_upper": "1981-06-01",
    "iso:country": "GB",
    "wof:name": "WV8 1XH",
    "wof:placetype": "postalcode"
  },
  "geometry": {"coordinates":[-2.152829,52.617804],"type":"Point"}
}
