{
  "type": "Feature",
  "properties": {
    "iso:country": "GB",
    "wof:name": "WV8 1XH",
    "wof:placetype": "postalcode"
  },
  "geometry": {"coordinates":[-2.152829,52.617804],"type":"Point"}
}
