{
  "type": "Feature",
  "properties": {
    "date:inception_lower":"2001-12-01",
    "date:inception_upper":"2001-12-31",
    "iso:country":"GB",
    "wof:name":"BS1 6JW",
    "wof:placetype":"postalcode"
},
  "geometry": {"coordinates":[-2.605212,51.447628],"type":"Point"}
}