{
  "type": "Feature",
  "properties": {
    "date:inception_lower":"1980-01-01",
    "date:inception_upper":"1980-01-31",
    "iso:country":"GB",
    "wof:name":"IV26 2XG",
    "wof:placetype":"postalcode"
},
  "geometry": {"coordinates":[-5.15947,57.90059],"type":"Point"}
}