{
  "type": "Feature",
  "properties": {
    "date:inception_lower": "2023-05-01",
    "date:inception_upper": "2023-05-01",
    "iso:country": "GB",
    "wof:name": "OX12 2FN",
    "wof:placetype": "postalcode"
  },
  "geometry": {"coordinates":[-1.427392,51.588279],"type":"Point"}
}
