{
  "type": "Feature",
  "properties": {
    "iso:country": "GB",
    "wof:name": "CM16 6SU",
    "wof:placetype": "postalcode"
  },
  "geometry": {"coordinates":[0.120204,51.704767],"type":"Point"}
}
