{
  "type": "Feature",
  "properties": {
    "iso:country": "GB",
    "wof:name": "CB21 4LP",
    "wof:placetype": "postalcode"
  },
  "geometry": {"coordinates":[0.284606,52.096871],"type":"Point"}
}
