{
  "type": "Feature",
  "properties": {
    "iso:country":"GB",
    "wof:name":"CB21 4LP",
    "wof:placetype":"postalcode"
},
  "geometry": {"coordinates":[0.28460558846029,52.09687098240685],"type":"Point"}
}