{
  "type": "Feature",
  "properties": {
    "iso:country":"GB",
    "wof:name":"SO16 7AP",
    "wof:placetype":"postalcode"
},
  "geometry": {"coordinates":[-1.41767187679204,50.93414773556216],"type":"Point"}
}