{
  "type": "Feature",
  "properties": {
    "iso:country":"GB",
    "wof:name":"NP12 3TT",
    "wof:placetype":"postalcode"
},
  "geometry": {"coordinates":[-3.22236330182313,51.65541913467463],"type":"Point"}
}