{
  "type": "Feature",
  "properties": {
    "iso:country":"GB",
    "wof:name":"B62 8AZ",
    "wof:placetype":"postalcode"
},
  "geometry": {"coordinates":[-2.04616801461059,52.4592222584319],"type":"Point"}
}