{
  "type": "Feature",
  "properties": {
    "date:inception_lower": "2010-11-01",
    "date:inception_upper": "2010-11-01",
    "iso:country": "GB",
    "wof:name": "NE25 0FL",
    "wof:placetype": "postalcode"
  },
  "geometry": {"coordinates":[-1.529896,55.07583],"type":"Point"}
}
