{
  "type": "Feature",
  "properties": {
    "date:inception_lower":"2003-02-01",
    "date:inception_upper":"2003-02-28",
    "iso:country":"GB",
    "wof:name":"PR7 5FH",
    "wof:placetype":"postalcode"
},
  "geometry": {"coordinates":[-2.670359,53.618502],"type":"Point"}
}