{
  "type": "Feature",
  "properties": {
    "iso:country": "GB",
    "wof:name": "PR7 5FH",
    "wof:placetype": "postalcode"
  },
  "geometry": {"coordinates":[-2.670359,53.618502],"type":"Point"}
}
