{
  "type": "Feature",
  "properties": {
    "iso:country":"GB",
    "wof:name":"PR7 5FH",
    "wof:placetype":"postalcode"
},
  "geometry": {"coordinates":[-2.67035855652936,53.61850232765632],"type":"Point"}
}