{
  "type": "Feature",
  "properties": {
    "iso:country":"GB",
    "wof:name":"DT1 1TR",
    "wof:placetype":"postalcode"
},
  "geometry": {"coordinates":[-2.43985702753081,50.7147299379972],"type":"Point"}
}