{
  "type": "Feature",
  "properties": {
    "iso:country":"GB",
    "wof:name":"SO17 1PH",
    "wof:placetype":"postalcode"
},
  "geometry": {"coordinates":[-1.40173820700464,50.93044327607049],"type":"Point"}
}