{
  "type": "Feature",
  "properties": {
    "iso:country":"GB",
    "wof:name":"E1 3AB",
    "wof:placetype":"postalcode"
},
  "geometry": {"coordinates":[-0.05516952477247,51.51922053365554],"type":"Point"}
}