{
  "type": "Feature",
  "properties": {
    "iso:country":"GB",
    "wof:name":"N16 9NH",
    "wof:placetype":"postalcode"
},
  "geometry": {"coordinates":[-0.08783136724421,51.55329072721512],"type":"Point"}
}