{
  "type": "Feature",
  "properties": {
    "iso:country":"GB",
    "wof:name":"WA14 4UL",
    "wof:placetype":"postalcode"
},
  "geometry": {"coordinates":[-2.36682633003013,53.39301254433229],"type":"Point"}
}