{
  "type": "Feature",
  "properties": {
    "iso:country": "GB",
    "wof:name": "WA14 4UL",
    "wof:placetype": "postalcode"
  },
  "geometry": {"coordinates":[-2.366826,53.393013],"type":"Point"}
}
