{
  "type": "Feature",
  "properties": {
    "iso:country":"GB",
    "wof:name":"EX1 2DR",
    "wof:placetype":"postalcode"
},
  "geometry": {"coordinates":[-3.51274339498032,50.72684067101989],"type":"Point"}
}