{
  "type": "Feature",
  "properties": {
    "date:inception_lower":"1980-01-01",
    "date:inception_upper":"1980-01-31",
    "iso:country":"GB",
    "wof:name":"RM18 8QX",
    "wof:placetype":"postalcode"
},
  "geometry": {"coordinates":[0.399062,51.473405],"type":"Point"}
}