{
  "type": "Feature",
  "properties": {
    "iso:country": "GB",
    "wof:name": "RM18 8QX",
    "wof:placetype": "postalcode"
  },
  "geometry": {"coordinates":[0.399062,51.473405],"type":"Point"}
}
