{
  "type": "Feature",
  "properties": {
    "date:inception_lower": "1980-01-01",
    "date:inception_upper": "1980-01-01",
    "iso:country": "GB",
    "wof:name": "NR33 7LN",
    "wof:placetype": "postalcode"
  },
  "geometry": {"coordinates":[1.731241,52.460233],"type":"Point"}
}
