{
  "type": "Feature",
  "properties": {
    "iso:country": "GB",
    "wof:name": "ST13 6JQ",
    "wof:placetype": "postalcode"
  },
  "geometry": {"coordinates":[-2.022004,53.106437],"type":"Point"}
}
