{
  "type": "Feature",
  "properties": {
    "iso:country":"GB",
    "wof:name":"ST13 6JQ",
    "wof:placetype":"postalcode"
},
  "geometry": {"coordinates":[-2.02199170029145,53.10646397500553],"type":"Point"}
}