{
  "type": "Feature",
  "properties": {
    "date:inception_lower": "1980-01-01",
    "date:inception_upper": "1980-01-01",
    "iso:country": "GB",
    "wof:name": "NR25 7JA",
    "wof:placetype": "postalcode"
  },
  "geometry": {"coordinates":[1.068875,52.909743],"type":"Point"}
}
