{
  "type": "Feature",
  "properties": {
    "date:inception_lower": "1999-06-01",
    "date:inception_upper": "1999-06-01",
    "iso:country": "GB",
    "wof:name": "CH41 5LS",
    "wof:placetype": "postalcode"
  },
  "geometry": {"coordinates":[-3.014398,53.392051],"type":"Point"}
}
