{
  "type": "Feature",
  "properties": {
    "iso:country":"GB",
    "wof:name":"CH41 5LS",
    "wof:placetype":"postalcode"
},
  "geometry": {"coordinates":[-3.01450109761128,53.39192530056958],"type":"Point"}
}