{
  "type": "Feature",
  "properties": {
    "iso:country":"GB",
    "wof:name":"SP11 6EL",
    "wof:placetype":"postalcode"
},
  "geometry": {"coordinates":[-1.405576577521,51.25499118184278],"type":"Point"}
}