{
  "type": "Feature",
  "properties": {
    "date:inception_lower": "1980-01-01",
    "date:inception_upper": "1980-01-01",
    "iso:country": "GB",
    "wof:name": "SP11 6EL",
    "wof:placetype": "postalcode"
  },
  "geometry": {"coordinates":[-1.405562,51.254988],"type":"Point"}
}
