{
  "type": "Feature",
  "properties": {
    "date:inception_lower":"1980-01-01",
    "date:inception_upper":"1980-01-31",
    "iso:country":"GB",
    "wof:name":"DT7 3LS",
    "wof:placetype":"postalcode"
},
  "geometry": {"coordinates":[-2.946763,50.729862],"type":"Point"}
}