{
  "type": "Feature",
  "properties": {
    "iso:country":"GB",
    "wof:name":"NE34 7QH",
    "wof:placetype":"postalcode"
},
  "geometry": {"coordinates":[-1.3979237907507,54.97273372350178],"type":"Point"}
}