{
  "type": "Feature",
  "properties": {
    "iso:country": "GB",
    "wof:name": "SO41 6FT",
    "wof:placetype": "postalcode"
  },
  "geometry": {"coordinates":[-1.635697,50.776718],"type":"Point"}
}
