{
  "type": "Feature",
  "properties": {
    "iso:country": "GB",
    "wof:name": "DT3 6JY",
    "wof:placetype": "postalcode"
  },
  "geometry": {"coordinates":[-2.442592,50.63516],"type":"Point"}
}
