{
  "type": "Feature",
  "properties": {
    "iso:country":"GB",
    "wof:name":"DT3 6JY",
    "wof:placetype":"postalcode"
},
  "geometry": {"coordinates":[-2.44259206191431,50.63516033438991],"type":"Point"}
}