{
  "type": "Feature",
  "properties": {
    "iso:country": "GB",
    "wof:name": "ME15 6XF",
    "wof:placetype": "postalcode"
  },
  "geometry": {"coordinates":[0.51507,51.251548],"type":"Point"}
}
