{
  "type": "Feature",
  "properties": {
    "iso:country":"GB",
    "wof:name":"ME15 6XF",
    "wof:placetype":"postalcode"
},
  "geometry": {"coordinates":[0.5150701285525,51.25154784815109],"type":"Point"}
}