{
  "type": "Feature",
  "properties": {
    "iso:country":"GB",
    "wof:name":"IV21 2DJ",
    "wof:placetype":"postalcode"
},
  "geometry": {"coordinates":[-5.75901829328289,57.73241905421091],"type":"Point"}
}