{
  "type": "Feature",
  "properties": {
    "iso:country":"GB",
    "wof:name":"HP15 6LQ",
    "wof:placetype":"postalcode"
},
  "geometry": {"coordinates":[-0.73512541614367,51.65494757477517],"type":"Point"}
}