{
  "type": "Feature",
  "properties": {
    "iso:country":"GB",
    "wof:name":"SA6 5DE",
    "wof:placetype":"postalcode"
},
  "geometry": {"coordinates":[-3.9022782526111,51.69591855636914],"type":"Point"}
}