{
  "type": "Feature",
  "properties": {
    "iso:country": "GB",
    "wof:name": "DY3 1PX",
    "wof:placetype": "postalcode"
  },
  "geometry": {"coordinates":[-2.117133,52.547202],"type":"Point"}
}
