{
  "type": "Feature",
  "properties": {
    "date:inception_lower": "2004-10-01",
    "date:inception_upper": "2004-10-01",
    "iso:country": "GB",
    "wof:name": "PO6 4FH",
    "wof:placetype": "postalcode"
  },
  "geometry": {"coordinates":[-1.08703,50.84983],"type":"Point"}
}
