{
  "type": "Feature",
  "properties": {
    "iso:country":"GB",
    "wof:name":"G78 3EW",
    "wof:placetype":"postalcode"
},
  "geometry": {"coordinates":[-4.43237541383051,55.78432211962686],"type":"Point"}
}