{
  "type": "Feature",
  "properties": {
    "iso:country":"GB",
    "wof:name":"DD9 7DQ",
    "wof:placetype":"postalcode"
},
  "geometry": {"coordinates":[-2.64674610993838,56.72770728212876],"type":"Point"}
}