{
  "type": "Feature",
  "properties": {
    "iso:country":"GB",
    "wof:name":"CM21 0DF",
    "wof:placetype":"postalcode"
},
  "geometry": {"coordinates":[0.14638296739879,51.81743573305901],"type":"Point"}
}