{
  "type": "Feature",
  "properties": {
    "iso:country":"GB",
    "wof:name":"B92 0AH",
    "wof:placetype":"postalcode"
},
  "geometry": {"coordinates":[-1.7018016746338,52.42418156577564],"type":"Point"}
}