{
  "type": "Feature",
  "properties": {
    "iso:country": "GB",
    "wof:name": "CM3 6XT",
    "wof:placetype": "postalcode"
  },
  "geometry": {"coordinates":[0.728388,51.667432],"type":"Point"}
}
