{
  "type": "Feature",
  "properties": {
    "date:inception_lower": "1980-01-01",
    "date:inception_upper": "1980-01-01",
    "iso:country": "GB",
    "wof:name": "SY15 6JH",
    "wof:placetype": "postalcode"
  },
  "geometry": {"coordinates":[-3.251218,52.542659],"type":"Point"}
}
