{
  "type": "Feature",
  "properties": {
    "iso:country":"GB",
    "wof:name":"TW3 1QE",
    "wof:placetype":"postalcode"
},
  "geometry": {"coordinates":[-0.35858176755332,51.47225193415616],"type":"Point"}
}