{
  "type": "Feature",
  "properties": {
    "iso:country":"GB",
    "wof:name":"SE6 4HB",
    "wof:placetype":"postalcode"
},
  "geometry": {"coordinates":[-0.03855161542376,51.43157094289753],"type":"Point"}
}