{
  "type": "Feature",
  "properties": {
    "date:inception_lower": "2019-09-01",
    "date:inception_upper": "2019-09-01",
    "iso:country": "GB",
    "wof:name": "PO20 3AY",
    "wof:placetype": "postalcode"
  },
  "geometry": {"coordinates":[-0.664012,50.843821],"type":"Point"}
}
