{
  "type": "Feature",
  "properties": {
    "date:inception_lower": "1980-01-01",
    "date:inception_upper": "1980-01-01",
    "iso:country": "GB",
    "wof:name": "L4 3QS",
    "wof:placetype": "postalcode"
  },
  "geometry": {"coordinates":[-2.973015,53.437512],"type":"Point"}
}
