{
  "type": "Feature",
  "properties": {
    "iso:country":"GB",
    "wof:name":"EH6 5QR",
    "wof:placetype":"postalcode"
},
  "geometry": {"coordinates":[-3.18557698815775,55.97255328591523],"type":"Point"}
}