{
  "type": "Feature",
  "properties": {
    "date:inception_lower":"1992-08-01",
    "date:inception_upper":"1992-08-31",
    "iso:country":"GB",
    "wof:name":"TF2 9TR",
    "wof:placetype":"postalcode"
},
  "geometry": {"coordinates":[-2.439449,52.700466],"type":"Point"}
}