{
  "type": "Feature",
  "properties": {
    "iso:country": "GB",
    "wof:name": "TF2 9TR",
    "wof:placetype": "postalcode"
  },
  "geometry": {"coordinates":[-2.439449,52.700466],"type":"Point"}
}
