{
  "type": "Feature",
  "properties": {
    "date:inception_lower": "1996-12-01",
    "date:inception_upper": "1996-12-01",
    "iso:country": "GB",
    "wof:name": "AB43 6TF",
    "wof:placetype": "postalcode"
  },
  "geometry": {"coordinates":[-2.091056,57.585427],"type":"Point"}
}
