{
  "type": "Feature",
  "properties": {
    "iso:country": "GB",
    "wof:name": "G32 6FY",
    "wof:placetype": "postalcode"
  },
  "geometry": {"coordinates":[-4.190459,55.857082],"type":"Point"}
}
