{
  "type": "Feature",
  "properties": {
    "date:inception_lower": "2017-01-01",
    "date:inception_upper": "2017-01-01",
    "iso:country": "GB",
    "wof:name": "G32 6FY",
    "wof:placetype": "postalcode"
  },
  "geometry": {"coordinates":[-4.190459,55.857082],"type":"Point"}
}
