{
  "type": "Feature",
  "properties": {
    "iso:country": "GB",
    "wof:name": "GL54 2GR",
    "wof:placetype": "postalcode"
  },
  "geometry": {"coordinates":[-1.700546,51.8712],"type":"Point"}
}
