{
  "type": "Feature",
  "properties": {
    "iso:country":"GB",
    "wof:name":"GL54 2GR",
    "wof:placetype":"postalcode"
},
  "geometry": {"coordinates":[-1.7005458698145,51.87119987905758],"type":"Point"}
}