{
  "type": "Feature",
  "properties": {
    "date:inception_lower": "1980-01-01",
    "date:inception_upper": "1980-01-01",
    "iso:country": "GB",
    "wof:name": "SL1 1JP",
    "wof:placetype": "postalcode"
  },
  "geometry": {"coordinates":[-0.592335,51.508508],"type":"Point"}
}
