{
  "type": "Feature",
  "properties": {
    "iso:country":"GB",
    "wof:name":"HD9 6EH",
    "wof:placetype":"postalcode"
},
  "geometry": {"coordinates":[-1.79776390599208,53.5971916588502],"type":"Point"}
}