{
  "type": "Feature",
  "properties": {
    "iso:country": "GB",
    "wof:name": "HD9 6EH",
    "wof:placetype": "postalcode"
  },
  "geometry": {"coordinates":[-1.797764,53.597192],"type":"Point"}
}
