{
  "type": "Feature",
  "properties": {
    "iso:country": "GB",
    "wof:name": "AB54 7LT",
    "wof:placetype": "postalcode"
  },
  "geometry": {"coordinates":[-2.757319,57.522121],"type":"Point"}
}
