{
  "type": "Feature",
  "properties": {
    "iso:country":"GB",
    "wof:name":"AB54 7LT",
    "wof:placetype":"postalcode"
},
  "geometry": {"coordinates":[-2.75731927485199,57.52212102528058],"type":"Point"}
}