{
  "type": "Feature",
  "properties": {
    "iso:country":"GB",
    "wof:name":"BH23 3DD",
    "wof:placetype":"postalcode"
},
  "geometry": {"coordinates":[-1.74772472407912,50.74432562301964],"type":"Point"}
}