{
  "type": "Feature",
  "properties": {
    "iso:country":"GB",
    "wof:name":"HP15 7LQ",
    "wof:placetype":"postalcode"
},
  "geometry": {"coordinates":[-0.71337939416208,51.65151930946429],"type":"Point"}
}