{
  "type": "Feature",
  "properties": {
    "date:inception_lower": "1980-01-01",
    "date:inception_upper": "1980-01-01",
    "iso:country": "GB",
    "wof:name": "WN2 1DQ",
    "wof:placetype": "postalcode"
  },
  "geometry": {"coordinates":[-2.607157,53.557745],"type":"Point"}
}
