{
  "type": "Feature",
  "properties": {
    "iso:country":"GB",
    "wof:name":"WN2 1DQ",
    "wof:placetype":"postalcode"
},
  "geometry": {"coordinates":[-2.60715690537305,53.55774545842446],"type":"Point"}
}