{
  "type": "Feature",
  "properties": {
    "iso:country": "GB",
    "wof:name": "NN3 6RL",
    "wof:placetype": "postalcode"
  },
  "geometry": {"coordinates":[-0.860095,52.2725],"type":"Point"}
}
