{
  "type": "Feature",
  "properties": {
    "date:inception_lower": "2006-08-01",
    "date:inception_upper": "2006-08-01",
    "iso:country": "GB",
    "wof:name": "NN3 6RL",
    "wof:placetype": "postalcode"
  },
  "geometry": {"coordinates":[-0.860095,52.2725],"type":"Point"}
}
