{
  "type": "Feature",
  "properties": {
    "iso:country": "GB",
    "wof:name": "LS22 6LT",
    "wof:placetype": "postalcode"
  },
  "geometry": {"coordinates":[-1.385493,53.92771],"type":"Point"}
}
