{
  "type": "Feature",
  "properties": {
    "iso:country":"GB",
    "wof:name":"LS22 6LT",
    "wof:placetype":"postalcode"
},
  "geometry": {"coordinates":[-1.38549282551557,53.92770958346075],"type":"Point"}
}