{
  "type": "Feature",
  "properties": {
    "iso:country":"GB",
    "wof:name":"BA1 7EN",
    "wof:placetype":"postalcode"
},
  "geometry": {"coordinates":[-2.32011389679012,51.40743674720599],"type":"Point"}
}