{
  "type": "Feature",
  "properties": {
    "date:inception_lower":"1980-01-01",
    "date:inception_upper":"1980-01-31",
    "iso:country":"GB",
    "wof:name":"BA1 7EN",
    "wof:placetype":"postalcode"
},
  "geometry": {"coordinates":[-2.320114,51.407437],"type":"Point"}
}