{
  "type": "Feature",
  "properties": {
    "iso:country": "GB",
    "wof:name": "KA10 6BB",
    "wof:placetype": "postalcode"
  },
  "geometry": {"coordinates":[-4.674915,55.541727],"type":"Point"}
}
