{
  "type": "Feature",
  "properties": {
    "iso:country":"GB",
    "wof:name":"KA10 6BB",
    "wof:placetype":"postalcode"
},
  "geometry": {"coordinates":[-4.67491533384665,55.54172654193928],"type":"Point"}
}