{
  "type": "Feature",
  "properties": {
    "date:inception_lower": "2022-04-01",
    "date:inception_upper": "2022-04-01",
    "iso:country": "GB",
    "wof:name": "PH3 1YZ",
    "wof:placetype": "postalcode"
  },
  "geometry": {"coordinates":[-3.707039,56.296346],"type":"Point"}
}
