{
  "type": "Feature",
  "properties": {
    "iso:country":"GB",
    "wof:name":"HU3 6QP",
    "wof:placetype":"postalcode"
},
  "geometry": {"coordinates":[-0.37850477657697,53.7439052376977],"type":"Point"}
}