{
  "type": "Feature",
  "properties": {
    "date:inception_lower": "1999-12-01",
    "date:inception_upper": "1999-12-01",
    "iso:country": "GB",
    "wof:name": "DL10 5QW",
    "wof:placetype": "postalcode"
  },
  "geometry": {"coordinates":[-1.693329,54.472062],"type":"Point"}
}
