{
  "type": "Feature",
  "properties": {
    "iso:country":"GB",
    "wof:name":"CW10 0JY",
    "wof:placetype":"postalcode"
},
  "geometry": {"coordinates":[-2.39145081105526,53.18234499811869],"type":"Point"}
}