{
  "type": "Feature",
  "properties": {
    "date:inception_lower": "1980-01-01",
    "date:inception_upper": "1980-01-01",
    "iso:country": "GB",
    "wof:name": "CW10 0JY",
    "wof:placetype": "postalcode"
  },
  "geometry": {"coordinates":[-2.391451,53.182345],"type":"Point"}
}
