{
  "type": "Feature",
  "properties": {
    "iso:country":"GB",
    "wof:name":"DH3 4HA",
    "wof:placetype":"postalcode"
},
  "geometry": {"coordinates":[-1.54102134207079,54.84779082351459],"type":"Point"}
}