{
  "type": "Feature",
  "properties": {
    "iso:country": "GB",
    "wof:name": "DH3 4HA",
    "wof:placetype": "postalcode"
  },
  "geometry": {"coordinates":[-1.541021,54.847791],"type":"Point"}
}
