{
  "type": "Feature",
  "properties": {
    "iso:country":"GB",
    "wof:name":"NE3 1SH",
    "wof:placetype":"postalcode"
},
  "geometry": {"coordinates":[-1.60316861949924,55.00866734870198],"type":"Point"}
}