{
  "type": "Feature",
  "properties": {
    "iso:country": "GB",
    "wof:name": "NE3 1SH",
    "wof:placetype": "postalcode"
  },
  "geometry": {"coordinates":[-1.603169,55.008667],"type":"Point"}
}
