{
  "type": "Feature",
  "properties": {
    "iso:country":"GB",
    "wof:name":"SP3 4LT",
    "wof:placetype":"postalcode"
},
  "geometry": {"coordinates":[-1.90458375021762,51.13186796918311],"type":"Point"}
}