{
  "type": "Feature",
  "properties": {
    "date:inception_lower":"1995-07-01",
    "date:inception_upper":"1995-07-31",
    "iso:country":"GB",
    "wof:name":"RG40 4NX",
    "wof:placetype":"postalcode"
},
  "geometry": {"coordinates":[-0.861779,51.360214],"type":"Point"}
}