{
  "type": "Feature",
  "properties": {
    "iso:country":"GB",
    "wof:name":"RM3 8JD",
    "wof:placetype":"postalcode"
},
  "geometry": {"coordinates":[0.21649088267955,51.60422202381773],"type":"Point"}
}