{
  "type": "Feature",
  "properties": {
    "iso:country":"GB",
    "wof:name":"SE5 8HR",
    "wof:placetype":"postalcode"
},
  "geometry": {"coordinates":[-0.08828025426715,51.46029682038215],"type":"Point"}
}