{
  "type": "Feature",
  "properties": {
    "iso:country":"GB",
    "wof:name":"BS8 3BL",
    "wof:placetype":"postalcode"
},
  "geometry": {"coordinates":[-2.61863271928749,51.45790684760659],"type":"Point"}
}