{
  "type": "Feature",
  "properties": {
    "date:inception_lower": "2003-06-01",
    "date:inception_upper": "2003-06-01",
    "iso:country": "GB",
    "wof:name": "LS15 9JH",
    "wof:placetype": "postalcode"
  },
  "geometry": {"coordinates":[-1.431924,53.79195],"type":"Point"}
}
