{
  "type": "Feature",
  "properties": {
    "iso:country":"GB",
    "wof:name":"LS15 9JH",
    "wof:placetype":"postalcode"
},
  "geometry": {"coordinates":[-1.43192454024496,53.79194969691486],"type":"Point"}
}