{
  "type": "Feature",
  "properties": {
    "iso:country": "GB",
    "wof:name": "GL51 9TP",
    "wof:placetype": "postalcode"
  },
  "geometry": {"coordinates":[-2.097262,51.922617],"type":"Point"}
}
