{
  "type": "Feature",
  "properties": {
    "iso:country":"GB",
    "wof:name":"GL51 9TP",
    "wof:placetype":"postalcode"
},
  "geometry": {"coordinates":[-2.09726211509915,51.92261688203774],"type":"Point"}
}