{
  "type": "Feature",
  "properties": {
    "date:inception_lower":"2003-10-01",
    "date:inception_upper":"2003-10-31",
    "iso:country":"GB",
    "wof:name":"GL51 9TP",
    "wof:placetype":"postalcode"
},
  "geometry": {"coordinates":[-2.097262,51.922617],"type":"Point"}
}