{
  "type": "Feature",
  "properties": {
    "iso:country": "GB",
    "wof:name": "BH21 7EY",
    "wof:placetype": "postalcode"
  },
  "geometry": {"coordinates":[-1.974586,50.86104],"type":"Point"}
}
