{
  "type": "Feature",
  "properties": {
    "iso:country":"GB",
    "wof:name":"BH21 7EY",
    "wof:placetype":"postalcode"
},
  "geometry": {"coordinates":[-1.9745865242761,50.86103963727172],"type":"Point"}
}