{
  "type": "Feature",
  "properties": {
    "date:inception_lower":"1990-02-01",
    "date:inception_upper":"1990-02-28",
    "iso:country":"GB",
    "wof:name":"TR2 4TY",
    "wof:placetype":"postalcode"
},
  "geometry": {"coordinates":[-4.930578,50.31973],"type":"Point"}
}