{
  "type": "Feature",
  "properties": {
    "iso:country":"GB",
    "wof:name":"TR2 4TY",
    "wof:placetype":"postalcode"
},
  "geometry": {"coordinates":[-4.93057841607035,50.3197302843848],"type":"Point"}
}