{
  "type": "Feature",
  "properties": {
    "iso:country":"GB",
    "wof:name":"S71 5NT",
    "wof:placetype":"postalcode"
},
  "geometry": {"coordinates":[-1.43501527078625,53.55923102536949],"type":"Point"}
}