{
  "type": "Feature",
  "properties": {
    "date:inception_lower": "2014-02-01",
    "date:inception_upper": "2014-02-01",
    "iso:country": "GB",
    "wof:name": "L20 7SD",
    "wof:placetype": "postalcode"
  },
  "geometry": {"coordinates":[-2.994223,53.445778],"type":"Point"}
}
