{
  "type": "Feature",
  "properties": {
    "date:inception_lower": "1980-01-01",
    "date:inception_upper": "1980-01-01",
    "iso:country": "GB",
    "wof:name": "CV4 7AE",
    "wof:placetype": "postalcode"
  },
  "geometry": {"coordinates":[-1.547992,52.371353],"type":"Point"}
}
