{
  "type": "Feature",
  "properties": {
    "iso:country":"GB",
    "wof:name":"DY3 3UR",
    "wof:placetype":"postalcode"
},
  "geometry": {"coordinates":[-2.1201619476261,52.53323817308261],"type":"Point"}
}