{
  "type": "Feature",
  "properties": {
    "iso:country":"GB",
    "wof:name":"MK18 1UZ",
    "wof:placetype":"postalcode"
},
  "geometry": {"coordinates":[-0.97700473945828,52.00586848340819],"type":"Point"}
}