{
  "type": "Feature",
  "properties": {
    "iso:country": "GB",
    "wof:name": "MK18 1UZ",
    "wof:placetype": "postalcode"
  },
  "geometry": {"coordinates":[-0.977005,52.005868],"type":"Point"}
}
