{
  "type": "Feature",
  "properties": {
    "iso:country":"GB",
    "wof:name":"FY2 0PL",
    "wof:placetype":"postalcode"
},
  "geometry": {"coordinates":[-3.02548410032842,53.86103847580262],"type":"Point"}
}