{
  "type": "Feature",
  "properties": {
    "date:inception_lower":"1992-08-01",
    "date:inception_upper":"1992-08-31",
    "iso:country":"GB",
    "wof:name":"FY2 0PL",
    "wof:placetype":"postalcode"
},
  "geometry": {"coordinates":[-3.025484,53.861038],"type":"Point"}
}