{
  "type": "Feature",
  "properties": {
    "iso:country": "GB",
    "wof:name": "FY2 0PL",
    "wof:placetype": "postalcode"
  },
  "geometry": {"coordinates":[-3.025484,53.861038],"type":"Point"}
}
