{
  "type": "Feature",
  "properties": {
    "iso:country":"GB",
    "wof:name":"ME10 4TR",
    "wof:placetype":"postalcode"
},
  "geometry": {"coordinates":[0.74062966279748,51.33692534616235],"type":"Point"}
}