{
  "type": "Feature",
  "properties": {
    "iso:country":"GB",
    "wof:name":"B32 3DE",
    "wof:placetype":"postalcode"
},
  "geometry": {"coordinates":[-2.00010314150693,52.44236612585726],"type":"Point"}
}