{
  "type": "Feature",
  "properties": {
    "date:inception_lower":"1980-01-01",
    "date:inception_upper":"1980-01-31",
    "iso:country":"GB",
    "wof:name":"B32 3DE",
    "wof:placetype":"postalcode"
},
  "geometry": {"coordinates":[-2.000103,52.442366],"type":"Point"}
}