{
  "type": "Feature",
  "properties": {
    "date:inception_lower": "1983-03-01",
    "date:inception_upper": "1983-03-01",
    "iso:country": "GB",
    "wof:name": "ME2 2EG",
    "wof:placetype": "postalcode"
  },
  "geometry": {"coordinates":[0.489877,51.392009],"type":"Point"}
}
