{
  "type": "Feature",
  "properties": {
    "iso:country":"GB",
    "wof:name":"NP12 2DD",
    "wof:placetype":"postalcode"
},
  "geometry": {"coordinates":[-3.19302302711913,51.65233107611571],"type":"Point"}
}