{
  "type": "Feature",
  "properties": {
    "iso:country":"GB",
    "wof:name":"KY12 0QG",
    "wof:placetype":"postalcode"
},
  "geometry": {"coordinates":[-3.46119545410727,56.0747805493084],"type":"Point"}
}