{
  "type": "Feature",
  "properties": {
    "date:inception_lower": "2021-06-01",
    "date:inception_upper": "2021-06-01",
    "iso:country": "GB",
    "wof:name": "GL2 8LG",
    "wof:placetype": "postalcode"
  },
  "geometry": {"coordinates":[-2.318811,51.85329],"type":"Point"}
}
