{
  "type": "Feature",
  "properties": {
    "iso:country":"GB",
    "wof:name":"CV10 9BD",
    "wof:placetype":"postalcode"
},
  "geometry": {"coordinates":[-1.49728100515998,52.52976081988357],"type":"Point"}
}