{
  "type": "Feature",
  "properties": {
    "iso:country":"GB",
    "wof:name":"M16 8HE",
    "wof:placetype":"postalcode"
},
  "geometry": {"coordinates":[-2.26150552512125,53.44949529862048],"type":"Point"}
}