{
  "type": "Feature",
  "properties": {
    "iso:country":"GB",
    "wof:name":"MK41 0NY",
    "wof:placetype":"postalcode"
},
  "geometry": {"coordinates":[-0.4265626796398,52.15400514091488],"type":"Point"}
}