{
  "type": "Feature",
  "properties": {
    "iso:country":"GB",
    "wof:name":"BN2 1LG",
    "wof:placetype":"postalcode"
},
  "geometry": {"coordinates":[-0.12905127410206,50.82019183393992],"type":"Point"}
}