{
  "type": "Feature",
  "properties": {
    "iso:country":"GB",
    "wof:name":"OX2 0JN",
    "wof:placetype":"postalcode"
},
  "geometry": {"coordinates":[-1.29377959765663,51.75269446736048],"type":"Point"}
}