{
  "type": "Feature",
  "properties": {
    "date:inception_lower": "1983-03-01",
    "date:inception_upper": "1983-03-01",
    "iso:country": "GB",
    "wof:name": "OX2 0JN",
    "wof:placetype": "postalcode"
  },
  "geometry": {"coordinates":[-1.29378,51.752694],"type":"Point"}
}
