{
  "type": "Feature",
  "properties": {
    "iso:country":"GB",
    "wof:name":"SN4 8LE",
    "wof:placetype":"postalcode"
},
  "geometry": {"coordinates":[-1.8947327057183,51.54847262359379],"type":"Point"}
}