{
  "type": "Feature",
  "properties": {
    "iso:country": "GB",
    "wof:name": "SN4 8LE",
    "wof:placetype": "postalcode"
  },
  "geometry": {"coordinates":[-1.894733,51.548473],"type":"Point"}
}
