{
  "type": "Feature",
  "properties": {
    "iso:country":"GB",
    "wof:name":"BN27 1BJ",
    "wof:placetype":"postalcode"
},
  "geometry": {"coordinates":[0.2598373177808,50.86302424166766],"type":"Point"}
}