{
  "type": "Feature",
  "properties": {
    "iso:country":"GB",
    "wof:name":"NR5 0LP",
    "wof:placetype":"postalcode"
},
  "geometry": {"coordinates":[1.23015531522925,52.64998082508299],"type":"Point"}
}