{
  "type": "Feature",
  "properties": {
    "iso:country": "GB",
    "wof:name": "N7 0LT",
    "wof:placetype": "postalcode"
  },
  "geometry": {"coordinates":[-0.12592,51.555569],"type":"Point"}
}
