{
  "type": "Feature",
  "properties": {
    "iso:country":"GB",
    "wof:name":"BD22 0BS",
    "wof:placetype":"postalcode"
},
  "geometry": {"coordinates":[-2.04204213839651,53.88369568241632],"type":"Point"}
}