{
  "type": "Feature",
  "properties": {
    "iso:country": "GB",
    "wof:name": "BD22 0BS",
    "wof:placetype": "postalcode"
  },
  "geometry": {"coordinates":[-2.042042,53.883696],"type":"Point"}
}
