{
  "type": "Feature",
  "properties": {
    "date:inception_lower": "2008-12-01",
    "date:inception_upper": "2008-12-01",
    "iso:country": "GB",
    "wof:name": "EX17 5BN",
    "wof:placetype": "postalcode"
  },
  "geometry": {"coordinates":[-3.748962,50.811104],"type":"Point"}
}
