{
  "type": "Feature",
  "properties": {
    "iso:country": "GB",
    "wof:name": "KT11 2SP",
    "wof:placetype": "postalcode"
  },
  "geometry": {"coordinates":[-0.372197,51.327835],"type":"Point"}
}
