{
  "type": "Feature",
  "properties": {
    "iso:country":"GB",
    "wof:name":"CF24 0LG",
    "wof:placetype":"postalcode"
},
  "geometry": {"coordinates":[-3.15886544630519,51.48553411143058],"type":"Point"}
}