{
  "type": "Feature",
  "properties": {
    "iso:country": "GB",
    "wof:name": "NP7 5DF",
    "wof:placetype": "postalcode"
  },
  "geometry": {"coordinates":[-3.026491,51.820926],"type":"Point"}
}
