{
  "type": "Feature",
  "properties": {
    "date:inception_lower": "1980-01-01",
    "date:inception_upper": "1980-01-01",
    "iso:country": "GB",
    "wof:name": "NP7 5DF",
    "wof:placetype": "postalcode"
  },
  "geometry": {"coordinates":[-3.026491,51.820926],"type":"Point"}
}
