{
  "type": "Feature",
  "properties": {
    "iso:country": "GB",
    "wof:name": "WF2 6HZ",
    "wof:placetype": "postalcode"
  },
  "geometry": {"coordinates":[-1.483076,53.65015],"type":"Point"}
}
