{
  "type": "Feature",
  "properties": {
    "date:inception_lower": "1983-10-01",
    "date:inception_upper": "1983-10-01",
    "iso:country": "GB",
    "wof:name": "KA10 6QR",
    "wof:placetype": "postalcode"
  },
  "geometry": {"coordinates":[-4.665284,55.544947],"type":"Point"}
}
