{
  "type": "Feature",
  "properties": {
    "iso:country": "GB",
    "wof:name": "CM8 1BD",
    "wof:placetype": "postalcode"
  },
  "geometry": {"coordinates":[0.6309,51.790197],"type":"Point"}
}
