{
  "type": "Feature",
  "properties": {
    "iso:country":"GB",
    "wof:name":"IP20 0NJ",
    "wof:placetype":"postalcode"
},
  "geometry": {"coordinates":[1.33745479364718,52.39791984115991],"type":"Point"}
}