{
  "type": "Feature",
  "properties": {
    "date:inception_lower": "1980-01-01",
    "date:inception_upper": "1980-01-01",
    "iso:country": "GB",
    "wof:name": "ST3 1EW",
    "wof:placetype": "postalcode"
  },
  "geometry": {"coordinates":[-2.137463,52.991677],"type":"Point"}
}
