{
  "type": "Feature",
  "properties": {
    "iso:country": "GB",
    "wof:name": "HG4 5BF",
    "wof:placetype": "postalcode"
  },
  "geometry": {"coordinates":[-1.4952,54.164965],"type":"Point"}
}
