{
  "type": "Feature",
  "properties": {
    "iso:country":"GB",
    "wof:name":"HG4 5BF",
    "wof:placetype":"postalcode"
},
  "geometry": {"coordinates":[-1.49520012518793,54.16496523961825],"type":"Point"}
}