{
  "type": "Feature",
  "properties": {
    "date:inception_lower": "2013-12-01",
    "date:inception_upper": "2013-12-01",
    "iso:country": "GB",
    "wof:name": "HG4 5BF",
    "wof:placetype": "postalcode"
  },
  "geometry": {"coordinates":[-1.498436,54.166439],"type":"Point"}
}
