{
  "type": "Feature",
  "properties": {
    "iso:country":"GB",
    "wof:name":"LE3 6HQ",
    "wof:placetype":"postalcode"
},
  "geometry": {"coordinates":[-1.17193624347849,52.63453660860888],"type":"Point"}
}