{
  "type": "Feature",
  "properties": {
    "iso:country":"GB",
    "wof:name":"BS40 5BW",
    "wof:placetype":"postalcode"
},
  "geometry": {"coordinates":[-2.76585323982307,51.34133990662232],"type":"Point"}
}