{
  "type": "Feature",
  "properties": {
    "date:inception_lower": "1993-08-01",
    "date:inception_upper": "1993-08-01",
    "iso:country": "GB",
    "wof:name": "SA8 3HL",
    "wof:placetype": "postalcode"
  },
  "geometry": {"coordinates":[-3.82929,51.722796],"type":"Point"}
}
