{
  "type": "Feature",
  "properties": {
    "iso:country":"GB",
    "wof:name":"B90 2JF",
    "wof:placetype":"postalcode"
},
  "geometry": {"coordinates":[-1.84563484298043,52.40776192375329],"type":"Point"}
}