{
  "type": "Feature",
  "properties": {
    "date:inception_lower": "2022-02-01",
    "date:inception_upper": "2022-02-01",
    "iso:country": "GB",
    "wof:name": "PR4 2FH",
    "wof:placetype": "postalcode"
  },
  "geometry": {"coordinates":[-2.913105,53.779601],"type":"Point"}
}
