{
  "type": "Feature",
  "properties": {
    "iso:country":"GB",
    "wof:name":"EX1 1DB",
    "wof:placetype":"postalcode"
},
  "geometry": {"coordinates":[-3.5311626692068,50.72075451694636],"type":"Point"}
}