{
  "type": "Feature",
  "properties": {
    "iso:country":"GB",
    "wof:name":"SN14 0HZ",
    "wof:placetype":"postalcode"
},
  "geometry": {"coordinates":[-2.13635841291338,51.46461269182971],"type":"Point"}
}