{
  "type": "Feature",
  "properties": {
    "date:inception_lower": "1980-01-01",
    "date:inception_upper": "1980-01-01",
    "iso:country": "GB",
    "wof:name": "SN14 0HZ",
    "wof:placetype": "postalcode"
  },
  "geometry": {"coordinates":[-2.136358,51.464613],"type":"Point"}
}
