{
  "type": "Feature",
  "properties": {
    "iso:country":"GB",
    "wof:name":"N18 2QS",
    "wof:placetype":"postalcode"
},
  "geometry": {"coordinates":[-0.05962718242343,51.61639566548413],"type":"Point"}
}