{
  "type": "Feature",
  "properties": {
    "iso:country": "GB",
    "wof:name": "N18 2QS",
    "wof:placetype": "postalcode"
  },
  "geometry": {"coordinates":[-0.059627,51.616396],"type":"Point"}
}
