{
  "type": "Feature",
  "properties": {
    "iso:country":"GB",
    "wof:name":"SG9 9SQ",
    "wof:placetype":"postalcode"
},
  "geometry": {"coordinates":[-0.02408009206454,51.94186286496488],"type":"Point"}
}