{
  "type": "Feature",
  "properties": {
    "iso:country": "GB",
    "wof:name": "SG9 9SQ",
    "wof:placetype": "postalcode"
  },
  "geometry": {"coordinates":[-0.02408,51.941863],"type":"Point"}
}
