{
  "type": "Feature",
  "properties": {
    "iso:country": "GB",
    "wof:name": "HP16 9HA",
    "wof:placetype": "postalcode"
  },
  "geometry": {"coordinates":[-0.741257,51.699977],"type":"Point"}
}
