{
  "type": "Feature",
  "properties": {
    "iso:country":"GB",
    "wof:name":"TQ7 2RN",
    "wof:placetype":"postalcode"
},
  "geometry": {"coordinates":[-3.72167876374428,50.24834929418293],"type":"Point"}
}