{
  "type": "Feature",
  "properties": {
    "iso:country":"GB",
    "wof:name":"CH64 0UD",
    "wof:placetype":"postalcode"
},
  "geometry": {"coordinates":[-3.05914734263618,53.27919177970588],"type":"Point"}
}