{
  "type": "Feature",
  "properties": {
    "iso:country":"GB",
    "wof:name":"CO2 0JR",
    "wof:placetype":"postalcode"
},
  "geometry": {"coordinates":[0.85810936716213,51.84477005386626],"type":"Point"}
}