{
  "type": "Feature",
  "properties": {
    "iso:country":"GB",
    "wof:name":"NW8 0NX",
    "wof:placetype":"postalcode"
},
  "geometry": {"coordinates":[-0.17617342733014,51.53548943085288],"type":"Point"}
}