{
  "type": "Feature",
  "properties": {
    "date:inception_lower": "1993-08-01",
    "date:inception_upper": "1993-08-01",
    "iso:country": "GB",
    "wof:name": "NW8 0NX",
    "wof:placetype": "postalcode"
  },
  "geometry": {"coordinates":[-0.176173,51.535489],"type":"Point"}
}
