{
  "type": "Feature",
  "properties": {
    "iso:country":"GB",
    "wof:name":"TW9 3LA",
    "wof:placetype":"postalcode"
},
  "geometry": {"coordinates":[-0.28926635154794,51.47647673927347],"type":"Point"}
}