{
  "type": "Feature",
  "properties": {
    "iso:country": "GB",
    "wof:name": "TW9 3LA",
    "wof:placetype": "postalcode"
  },
  "geometry": {"coordinates":[-0.289266,51.476477],"type":"Point"}
}
