{
  "type": "Feature",
  "properties": {
    "iso:country":"GB",
    "wof:name":"CF38 1DR",
    "wof:placetype":"postalcode"
},
  "geometry": {"coordinates":[-3.32119157405172,51.56659725515551],"type":"Point"}
}