{
  "type": "Feature",
  "properties": {
    "iso:country":"GB",
    "wof:name":"WR13 6EX",
    "wof:placetype":"postalcode"
},
  "geometry": {"coordinates":[-2.35360606000794,52.08510035584182],"type":"Point"}
}