{
  "type": "Feature",
  "properties": {
    "iso:country":"GB",
    "wof:name":"LU1 1HP",
    "wof:placetype":"postalcode"
},
  "geometry": {"coordinates":[-0.4246573973897,51.88407328977769],"type":"Point"}
}