{
  "type": "Feature",
  "properties": {
    "iso:country":"GB",
    "wof:name":"BR5 3LZ",
    "wof:placetype":"postalcode"
},
  "geometry": {"coordinates":[0.12150765275885,51.39788307585043],"type":"Point"}
}