{
  "type": "Feature",
  "properties": {
    "iso:country":"GB",
    "wof:name":"M9 6DP",
    "wof:placetype":"postalcode"
},
  "geometry": {"coordinates":[-2.19928513098895,53.52896534507282],"type":"Point"}
}