{
  "type": "Feature",
  "properties": {
    "date:inception_lower": "2000-12-01",
    "date:inception_upper": "2000-12-01",
    "iso:country": "GB",
    "wof:name": "M9 6DP",
    "wof:placetype": "postalcode"
  },
  "geometry": {"coordinates":[-2.199285,53.528965],"type":"Point"}
}
