{
  "type": "Feature",
  "properties": {
    "date:inception_lower": "2012-04-01",
    "date:inception_upper": "2012-04-01",
    "iso:country": "GB",
    "wof:name": "IP3 8JP",
    "wof:placetype": "postalcode"
  },
  "geometry": {"coordinates":[1.18964,52.05129],"type":"Point"}
}
