{
  "type": "Feature",
  "properties": {
    "iso:country": "GB",
    "wof:name": "IP3 8JP",
    "wof:placetype": "postalcode"
  },
  "geometry": {"coordinates":[1.18964,52.05129],"type":"Point"}
}
