{
  "type": "Feature",
  "properties": {
    "iso:country":"GB",
    "wof:name":"NE27 0AX",
    "wof:placetype":"postalcode"
},
  "geometry": {"coordinates":[-1.53680359757421,55.0418437285119],"type":"Point"}
}