{
  "type": "Feature",
  "properties": {
    "iso:country":"GB",
    "wof:name":"CH63 7QN",
    "wof:placetype":"postalcode"
},
  "geometry": {"coordinates":[-3.0079729896037,53.35429872961275],"type":"Point"}
}