{
  "type": "Feature",
  "properties": {
    "date:inception_lower":"1998-12-01",
    "date:inception_upper":"1998-12-31",
    "iso:country":"GB",
    "wof:name":"NN4 9QN",
    "wof:placetype":"postalcode"
},
  "geometry": {"coordinates":[-0.939997,52.219084],"type":"Point"}
}