{
  "type": "Feature",
  "properties": {
    "iso:country":"GB",
    "wof:name":"PE33 9QN",
    "wof:placetype":"postalcode"
},
  "geometry": {"coordinates":[0.49388745284191,52.56763011583109],"type":"Point"}
}