{
  "type": "Feature",
  "properties": {
    "date:inception_lower":"1980-01-01",
    "date:inception_upper":"1980-01-31",
    "iso:country":"GB",
    "wof:name":"HD8 8UT",
    "wof:placetype":"postalcode"
},
  "geometry": {"coordinates":[-1.658398,53.562952],"type":"Point"}
}