{
  "type": "Feature",
  "properties": {
    "date:inception_lower": "2003-10-01",
    "date:inception_upper": "2003-10-01",
    "iso:country": "GB",
    "wof:name": "BB2 3UB",
    "wof:placetype": "postalcode"
  },
  "geometry": {"coordinates":[-2.466413,53.726033],"type":"Point"}
}
