{
  "type": "Feature",
  "properties": {
    "iso:country":"GB",
    "wof:name":"BB2 3UB",
    "wof:placetype":"postalcode"
},
  "geometry": {"coordinates":[-2.4664154925107,53.7260177497353],"type":"Point"}
}