{
  "type": "Feature",
  "properties": {
    "iso:country":"GB",
    "wof:name":"WF2 0BT",
    "wof:placetype":"postalcode"
},
  "geometry": {"coordinates":[-1.53296488887273,53.6917364703565],"type":"Point"}
}