{
  "type": "Feature",
  "properties": {
    "iso:country":"GB",
    "wof:name":"NP7 8AT",
    "wof:placetype":"postalcode"
},
  "geometry": {"coordinates":[-2.99626556341806,51.85260552478539],"type":"Point"}
}