{
  "type": "Feature",
  "properties": {
    "iso:country": "GB",
    "wof:name": "LE17 5HG",
    "wof:placetype": "postalcode"
  },
  "geometry": {"coordinates":[-1.223273,52.504843],"type":"Point"}
}
