{
  "type": "Feature",
  "properties": {
    "iso:country":"GB",
    "wof:name":"DN4 9DB",
    "wof:placetype":"postalcode"
},
  "geometry": {"coordinates":[-1.16124273091619,53.49418328709879],"type":"Point"}
}