{
  "type": "Feature",
  "properties": {
    "iso:country":"GB",
    "wof:name":"NR14 6HW",
    "wof:placetype":"postalcode"
},
  "geometry": {"coordinates":[1.4794995899531,52.54354729860145],"type":"Point"}
}