{
  "type": "Feature",
  "properties": {
    "iso:country": "GB",
    "wof:name": "NR14 6HW",
    "wof:placetype": "postalcode"
  },
  "geometry": {"coordinates":[1.4795,52.543547],"type":"Point"}
}
