{
  "type": "Feature",
  "properties": {
    "iso:country": "GB",
    "wof:name": "AL4 9UD",
    "wof:placetype": "postalcode"
  },
  "geometry": {"coordinates":[-0.301187,51.762808],"type":"Point"}
}
