{
  "type": "Feature",
  "properties": {
    "iso:country": "GB",
    "wof:name": "NR6 7JR",
    "wof:placetype": "postalcode"
  },
  "geometry": {"coordinates":[1.311105,52.668205],"type":"Point"}
}
