{
  "type": "Feature",
  "properties": {
    "date:inception_lower": "1985-10-01",
    "date:inception_upper": "1985-10-01",
    "iso:country": "GB",
    "wof:name": "CV22 7SJ",
    "wof:placetype": "postalcode"
  },
  "geometry": {"coordinates":[-1.294122,52.369508],"type":"Point"}
}
