{
  "type": "Feature",
  "properties": {
    "iso:country":"GB",
    "wof:name":"PL4 6RB",
    "wof:placetype":"postalcode"
},
  "geometry": {"coordinates":[-4.13688305278555,50.38262116679147],"type":"Point"}
}