{
  "type": "Feature",
  "properties": {
    "iso:country":"GB",
    "wof:name":"WF10 5DB",
    "wof:placetype":"postalcode"
},
  "geometry": {"coordinates":[-1.35630307632265,53.72218798089453],"type":"Point"}
}