{
  "type": "Feature",
  "properties": {
    "iso:country":"GB",
    "wof:name":"CO15 2AJ",
    "wof:placetype":"postalcode"
},
  "geometry": {"coordinates":[1.13912901801406,51.79262999247898],"type":"Point"}
}