{
  "type": "Feature",
  "properties": {
    "date:inception_lower": "1980-01-01",
    "date:inception_upper": "1980-01-01",
    "iso:country": "GB",
    "wof:name": "TN33 0HS",
    "wof:placetype": "postalcode"
  },
  "geometry": {"coordinates":[0.471925,50.917173],"type":"Point"}
}
