{
  "type": "Feature",
  "properties": {
    "iso:country": "GB",
    "wof:name": "TN33 0HS",
    "wof:placetype": "postalcode"
  },
  "geometry": {"coordinates":[0.47168,50.917124],"type":"Point"}
}
