{
  "type": "Feature",
  "properties": {
    "iso:country":"GB",
    "wof:name":"TN33 0HS",
    "wof:placetype":"postalcode"
},
  "geometry": {"coordinates":[0.47134722516863,50.91703538128176],"type":"Point"}
}