{
  "type": "Feature",
  "properties": {
    "iso:country":"GB",
    "wof:name":"E13 0AJ",
    "wof:placetype":"postalcode"
},
  "geometry": {"coordinates":[0.02182971698176,51.52993269887132],"type":"Point"}
}