{
  "type": "Feature",
  "properties": {
    "iso:country":"GB",
    "wof:name":"ME10 1QR",
    "wof:placetype":"postalcode"
},
  "geometry": {"coordinates":[0.71093480827709,51.34444312730104],"type":"Point"}
}