{
  "type": "Feature",
  "properties": {
    "iso:country": "GB",
    "wof:name": "SK6 3FL",
    "wof:placetype": "postalcode"
  },
  "geometry": {"coordinates":[-2.098727,53.413812],"type":"Point"}
}
