{
  "type": "Feature",
  "properties": {
    "date:inception_lower": "2020-01-01",
    "date:inception_upper": "2020-01-01",
    "iso:country": "GB",
    "wof:name": "SK6 3FL",
    "wof:placetype": "postalcode"
  },
  "geometry": {"coordinates":[-2.098727,53.413812],"type":"Point"}
}
