{
  "type": "Feature",
  "properties": {
    "iso:country":"GB",
    "wof:name":"BN23 5SU",
    "wof:placetype":"postalcode"
},
  "geometry": {"coordinates":[0.32582540556209,50.78770683443211],"type":"Point"}
}