{
  "type": "Feature",
  "properties": {
    "iso:country": "GB",
    "wof:name": "MK8 8HF",
    "wof:placetype": "postalcode"
  },
  "geometry": {"coordinates":[-0.800983,52.037593],"type":"Point"}
}
