{
  "type": "Feature",
  "properties": {
    "iso:country":"GB",
    "wof:name":"MK8 8HF",
    "wof:placetype":"postalcode"
},
  "geometry": {"coordinates":[-0.8009832548557,52.03759271849777],"type":"Point"}
}