{
  "type": "Feature",
  "properties": {
    "iso:country":"GB",
    "wof:name":"NE34 7QQ",
    "wof:placetype":"postalcode"
},
  "geometry": {"coordinates":[-1.39928607911413,54.97147337912263],"type":"Point"}
}