{
  "type": "Feature",
  "properties": {
    "iso:country":"GB",
    "wof:name":"BL9 7TY",
    "wof:placetype":"postalcode"
},
  "geometry": {"coordinates":[-2.24660811704184,53.60415426866835],"type":"Point"}
}