{
  "type": "Feature",
  "properties": {
    "date:inception_lower":"1985-10-01",
    "date:inception_upper":"1985-10-31",
    "iso:country":"GB",
    "wof:name":"BL9 7TY",
    "wof:placetype":"postalcode"
},
  "geometry": {"coordinates":[-2.246606,53.60417],"type":"Point"}
}