{
  "type": "Feature",
  "properties": {
    "date:inception_lower": "1985-10-01",
    "date:inception_upper": "1985-10-01",
    "iso:country": "GB",
    "wof:name": "BL9 7TY",
    "wof:placetype": "postalcode"
  },
  "geometry": {"coordinates":[-2.247179,53.604106],"type":"Point"}
}
