{
  "type": "Feature",
  "properties": {
    "iso:country": "GB",
    "wof:name": "IP32 6FL",
    "wof:placetype": "postalcode"
  },
  "geometry": {"coordinates":[0.697816,52.26944],"type":"Point"}
}
