{
  "type": "Feature",
  "properties": {
    "date:inception_lower":"1983-07-01",
    "date:inception_upper":"1983-07-31",
    "iso:country":"GB",
    "wof:name":"SL2 5XP",
    "wof:placetype":"postalcode"
},
  "geometry": {"coordinates":[-0.571013,51.512494],"type":"Point"}
}