{
  "type": "Feature",
  "properties": {
    "iso:country":"GB",
    "wof:name":"SL2 5XP",
    "wof:placetype":"postalcode"
},
  "geometry": {"coordinates":[-0.57101329026767,51.51249406619515],"type":"Point"}
}