{
  "type": "Feature",
  "properties": {
    "iso:country":"GB",
    "wof:name":"RH1 4QD",
    "wof:placetype":"postalcode"
},
  "geometry": {"coordinates":[-0.1133755848856,51.24203537848417],"type":"Point"}
}