{
  "type": "Feature",
  "properties": {
    "iso:country":"GB",
    "wof:name":"PL3 4EY",
    "wof:placetype":"postalcode"
},
  "geometry": {"coordinates":[-4.15667810412589,50.37989910835803],"type":"Point"}
}