{
  "type": "Feature",
  "properties": {
    "iso:country": "GB",
    "wof:name": "NR26 8EP",
    "wof:placetype": "postalcode"
  },
  "geometry": {"coordinates":[1.217994,52.942117],"type":"Point"}
}
