{
  "type": "Feature",
  "properties": {
    "iso:country":"GB",
    "wof:name":"DN2 5SG",
    "wof:placetype":"postalcode"
},
  "geometry": {"coordinates":[-1.09964490989934,53.53793275979515],"type":"Point"}
}