{
  "type": "Feature",
  "properties": {
    "date:inception_lower": "1980-01-01",
    "date:inception_upper": "1980-01-01",
    "iso:country": "GB",
    "wof:name": "DN2 5SG",
    "wof:placetype": "postalcode"
  },
  "geometry": {"coordinates":[-1.099645,53.537933],"type":"Point"}
}
