{
  "type": "Feature",
  "properties": {
    "date:inception_lower": "1980-01-01",
    "date:inception_upper": "1980-01-01",
    "iso:country": "GB",
    "wof:name": "GU33 7EE",
    "wof:placetype": "postalcode"
  },
  "geometry": {"coordinates":[-0.888589,51.042306],"type":"Point"}
}
