{
  "type": "Feature",
  "properties": {
    "iso:country":"GB",
    "wof:name":"GU33 7EE",
    "wof:placetype":"postalcode"
},
  "geometry": {"coordinates":[-0.88858944031109,51.04230579142991],"type":"Point"}
}