{
  "type": "Feature",
  "properties": {
    "date:inception_lower": "1980-01-01",
    "date:inception_upper": "1980-01-01",
    "iso:country": "GB",
    "wof:name": "BH18 9EF",
    "wof:placetype": "postalcode"
  },
  "geometry": {"coordinates":[-2.004755,50.766855],"type":"Point"}
}
