{
  "type": "Feature",
  "properties": {
    "date:inception_lower":"1990-02-01",
    "date:inception_upper":"1990-02-28",
    "iso:country":"GB",
    "wof:name":"EN5 1EQ",
    "wof:placetype":"postalcode"
},
  "geometry": {"coordinates":[-0.188079,51.64735],"type":"Point"}
}