{
  "type": "Feature",
  "properties": {
    "iso:country":"GB",
    "wof:name":"EN5 1EQ",
    "wof:placetype":"postalcode"
},
  "geometry": {"coordinates":[-0.18807898623295,51.64734984053176],"type":"Point"}
}