{
  "type": "Feature",
  "properties": {
    "iso:country":"GB",
    "wof:name":"NE26 4HU",
    "wof:placetype":"postalcode"
},
  "geometry": {"coordinates":[-1.48438245077009,55.08555757001405],"type":"Point"}
}