{
  "type": "Feature",
  "properties": {
    "iso:country": "GB",
    "wof:name": "NE26 4HU",
    "wof:placetype": "postalcode"
  },
  "geometry": {"coordinates":[-1.484382,55.085558],"type":"Point"}
}
