{
  "type": "Feature",
  "properties": {
    "date:inception_lower": "1981-06-01",
    "date:inception_upper": "1981-06-01",
    "iso:country": "GB",
    "wof:name": "CM4 9SD",
    "wof:placetype": "postalcode"
  },
  "geometry": {"coordinates":[0.460938,51.653408],"type":"Point"}
}
