{
  "type": "Feature",
  "properties": {
    "iso:country":"GB",
    "wof:name":"CM4 9SD",
    "wof:placetype":"postalcode"
},
  "geometry": {"coordinates":[0.46093755948279,51.65340811838688],"type":"Point"}
}