{
  "type": "Feature",
  "properties": {
    "iso:country":"GB",
    "wof:name":"EX8 5QQ",
    "wof:placetype":"postalcode"
},
  "geometry": {"coordinates":[-3.3858398474093,50.64390009588423],"type":"Point"}
}