{
  "type": "Feature",
  "properties": {
    "iso:country":"GB",
    "wof:name":"WA8 5BA",
    "wof:placetype":"postalcode"
},
  "geometry": {"coordinates":[-2.73389443027429,53.3905557426755],"type":"Point"}
}