{
  "type": "Feature",
  "properties": {
    "iso:country":"GB",
    "wof:name":"ML5 2SE",
    "wof:placetype":"postalcode"
},
  "geometry": {"coordinates":[-4.05609206924197,55.89426650575298],"type":"Point"}
}