{
  "type": "Feature",
  "properties": {
    "iso:country": "GB",
    "wof:name": "M35 0RX",
    "wof:placetype": "postalcode"
  },
  "geometry": {"coordinates":[-2.155179,53.505176],"type":"Point"}
}
