{
  "type": "Feature",
  "properties": {
    "iso:country":"GB",
    "wof:name":"LE15 9SW",
    "wof:placetype":"postalcode"
},
  "geometry": {"coordinates":[-0.72567499356362,52.59056205486826],"type":"Point"}
}