{
  "type": "Feature",
  "properties": {
    "iso:country": "GB",
    "wof:name": "LE15 9SW",
    "wof:placetype": "postalcode"
  },
  "geometry": {"coordinates":[-0.725675,52.590562],"type":"Point"}
}
