{
  "type": "Feature",
  "properties": {
    "iso:country":"GB",
    "wof:name":"BS4 1BG",
    "wof:placetype":"postalcode"
},
  "geometry": {"coordinates":[-2.57621692446678,51.43052767777454],"type":"Point"}
}