{
  "type": "Feature",
  "properties": {
    "iso:country": "GB",
    "wof:name": "BS4 1BG",
    "wof:placetype": "postalcode"
  },
  "geometry": {"coordinates":[-2.576218,51.430526],"type":"Point"}
}
