{
  "type": "Feature",
  "properties": {
    "date:inception_lower": "1980-01-01",
    "date:inception_upper": "1980-01-01",
    "iso:country": "GB",
    "wof:name": "LD3 0RB",
    "wof:placetype": "postalcode"
  },
  "geometry": {"coordinates":[-3.28335,51.996488],"type":"Point"}
}
