{
  "type": "Feature",
  "properties": {
    "iso:country":"GB",
    "wof:name":"BH18 8HX",
    "wof:placetype":"postalcode"
},
  "geometry": {"coordinates":[-2.0014647014567,50.75127042767954],"type":"Point"}
}