{
  "type": "Feature",
  "properties": {
    "iso:country": "GB",
    "wof:name": "BH18 8HX",
    "wof:placetype": "postalcode"
  },
  "geometry": {"coordinates":[-2.001465,50.75127],"type":"Point"}
}
