{
  "type": "Feature",
  "properties": {
    "date:inception_lower":"2001-06-01",
    "date:inception_upper":"2001-06-30",
    "iso:country":"GB",
    "wof:name":"SE25 4UE",
    "wof:placetype":"postalcode"
},
  "geometry": {"coordinates":[-0.073889,51.399316],"type":"Point"}
}