{
  "type": "Feature",
  "properties": {
    "date:inception_lower":"2014-11-01",
    "date:inception_upper":"2014-11-30",
    "iso:country":"GB",
    "wof:name":"CT12 5FL",
    "wof:placetype":"postalcode"
},
  "geometry": {"coordinates":[1.327723,51.347152],"type":"Point"}
}