{
  "type": "Feature",
  "properties": {
    "iso:country":"GB",
    "wof:name":"SN14 7BN",
    "wof:placetype":"postalcode"
},
  "geometry": {"coordinates":[-2.19409319198293,51.48746856207199],"type":"Point"}
}