{
  "type": "Feature",
  "properties": {
    "iso:country": "GB",
    "wof:name": "SO23 7PP",
    "wof:placetype": "postalcode"
  },
  "geometry": {"coordinates":[-1.296977,51.098542],"type":"Point"}
}
