{
  "type": "Feature",
  "properties": {
    "iso:country":"GB",
    "wof:name":"SO23 7PP",
    "wof:placetype":"postalcode"
},
  "geometry": {"coordinates":[-1.29703228034423,51.09859269164676],"type":"Point"}
}