{
  "type": "Feature",
  "properties": {
    "iso:country":"GB",
    "wof:name":"CV47 1BQ",
    "wof:placetype":"postalcode"
},
  "geometry": {"coordinates":[-1.38014114869987,52.26384131496243],"type":"Point"}
}