{
  "type": "Feature",
  "properties": {
    "date:inception_lower": "2005-11-01",
    "date:inception_upper": "2005-11-01",
    "iso:country": "GB",
    "wof:name": "NG23 7JX",
    "wof:placetype": "postalcode"
  },
  "geometry": {"coordinates":[-0.732162,53.167148],"type":"Point"}
}
