{
  "type": "Feature",
  "properties": {
    "iso:country":"GB",
    "wof:name":"NP22 3TD",
    "wof:placetype":"postalcode"
},
  "geometry": {"coordinates":[-3.25233027522562,51.76751673488808],"type":"Point"}
}