{
  "type": "Feature",
  "properties": {
    "date:inception_lower": "1980-01-01",
    "date:inception_upper": "1980-01-01",
    "iso:country": "GB",
    "wof:name": "FK10 2QG",
    "wof:placetype": "postalcode"
  },
  "geometry": {"coordinates":[-3.844831,56.1357],"type":"Point"}
}
