{
  "type": "Feature",
  "properties": {
    "iso:country":"GB",
    "wof:name":"FK10 2QG",
    "wof:placetype":"postalcode"
},
  "geometry": {"coordinates":[-3.84483153275315,56.13569987619913],"type":"Point"}
}