{
  "type": "Feature",
  "properties": {
    "iso:country":"GB",
    "wof:name":"NW4 4TD",
    "wof:placetype":"postalcode"
},
  "geometry": {"coordinates":[-0.23490765604346,51.59532355960592],"type":"Point"}
}