{
  "type": "Feature",
  "properties": {
    "iso:country":"GB",
    "wof:name":"BS37 5EU",
    "wof:placetype":"postalcode"
},
  "geometry": {"coordinates":[-2.42069448305522,51.54490525695608],"type":"Point"}
}