{
  "type": "Feature",
  "properties": {
    "iso:country":"GB",
    "wof:name":"B42 2TA",
    "wof:placetype":"postalcode"
},
  "geometry": {"coordinates":[-1.89406048164762,52.51686368533686],"type":"Point"}
}