{
  "type": "Feature",
  "properties": {
    "iso:country":"GB",
    "wof:name":"IV2 3AL",
    "wof:placetype":"postalcode"
},
  "geometry": {"coordinates":[-4.22161037769161,57.47631417934713],"type":"Point"}
}