{
  "type": "Feature",
  "properties": {
    "iso:country":"GB",
    "wof:name":"SS7 4DN",
    "wof:placetype":"postalcode"
},
  "geometry": {"coordinates":[0.54888365885048,51.57089729544195],"type":"Point"}
}