{
  "type": "Feature",
  "properties": {
    "iso:country":"GB",
    "wof:name":"L14 2DT",
    "wof:placetype":"postalcode"
},
  "geometry": {"coordinates":[-2.88164940729722,53.42051338925339],"type":"Point"}
}