{
  "type": "Feature",
  "properties": {
    "iso:country":"GB",
    "wof:name":"SG8 7LH",
    "wof:placetype":"postalcode"
},
  "geometry": {"coordinates":[-0.00937771602075,52.05006775119116],"type":"Point"}
}