{
  "type": "Feature",
  "properties": {
    "date:inception_lower": "1980-01-01",
    "date:inception_upper": "1980-01-01",
    "iso:country": "GB",
    "wof:name": "TS23 2DJ",
    "wof:placetype": "postalcode"
  },
  "geometry": {"coordinates":[-1.289961,54.612234],"type":"Point"}
}
