{
  "type": "Feature",
  "properties": {
    "iso:country":"GB",
    "wof:name":"IP2 9DQ",
    "wof:placetype":"postalcode"
},
  "geometry": {"coordinates":[1.13902374053294,52.04054466943753],"type":"Point"}
}