{
  "type": "Feature",
  "properties": {
    "iso:country":"GB",
    "wof:name":"ML2 0PL",
    "wof:placetype":"postalcode"
},
  "geometry": {"coordinates":[-3.91842478006433,55.76367354557977],"type":"Point"}
}