{
  "type": "Feature",
  "properties": {
    "iso:country":"GB",
    "wof:name":"NW7 3NL",
    "wof:placetype":"postalcode"
},
  "geometry": {"coordinates":[-0.24773711945608,51.6142286827784],"type":"Point"}
}