{
  "type": "Feature",
  "properties": {
    "iso:country":"GB",
    "wof:name":"KT13 0PX",
    "wof:placetype":"postalcode"
},
  "geometry": {"coordinates":[-0.44366605704136,51.35995587596426],"type":"Point"}
}