{
  "type": "Feature",
  "properties": {
    "iso:country":"GB",
    "wof:name":"S10 3AL",
    "wof:placetype":"postalcode"
},
  "geometry": {"coordinates":[-1.50674540647295,53.37138176887308],"type":"Point"}
}