{
  "type": "Feature",
  "properties": {
    "date:inception_lower": "2008-10-01",
    "date:inception_upper": "2008-10-01",
    "iso:country": "GB",
    "wof:name": "S10 3AL",
    "wof:placetype": "postalcode"
  },
  "geometry": {"coordinates":[-1.506745,53.371382],"type":"Point"}
}
