{
  "type": "Feature",
  "properties": {
    "date:inception_lower": "2015-04-01",
    "date:inception_upper": "2015-04-01",
    "iso:country": "GB",
    "wof:name": "SP7 8GT",
    "wof:placetype": "postalcode"
  },
  "geometry": {"coordinates":[-2.181702,51.008216],"type":"Point"}
}
