{
  "type": "Feature",
  "properties": {
    "iso:country": "GB",
    "wof:name": "L2 4SW",
    "wof:placetype": "postalcode"
  },
  "geometry": {"coordinates":[-2.990801,53.406776],"type":"Point"}
}
