{
  "type": "Feature",
  "properties": {
    "iso:country":"GB",
    "wof:name":"L2 4SW",
    "wof:placetype":"postalcode"
},
  "geometry": {"coordinates":[-2.99080105852577,53.40677636518495],"type":"Point"}
}