{
  "type": "Feature",
  "properties": {
    "iso:country": "GB",
    "wof:name": "TN37 7JU",
    "wof:placetype": "postalcode"
  },
  "geometry": {"coordinates":[0.555352,50.880706],"type":"Point"}
}
