{
  "type": "Feature",
  "properties": {
    "iso:country": "GB",
    "wof:name": "TQ14 8PJ",
    "wof:placetype": "postalcode"
  },
  "geometry": {"coordinates":[-3.494261,50.55008],"type":"Point"}
}
