{
  "type": "Feature",
  "properties": {
    "iso:country":"GB",
    "wof:name":"LS18 4RL",
    "wof:placetype":"postalcode"
},
  "geometry": {"coordinates":[-1.6317280499195,53.83268987193914],"type":"Point"}
}