{
  "type": "Feature",
  "properties": {
    "iso:country":"GB",
    "wof:name":"BR5 4JE",
    "wof:placetype":"postalcode"
},
  "geometry": {"coordinates":[0.11311784837597,51.38241388180799],"type":"Point"}
}