{
  "type": "Feature",
  "properties": {
    "iso:country":"GB",
    "wof:name":"SY7 9AS",
    "wof:placetype":"postalcode"
},
  "geometry": {"coordinates":[-2.7848665941861,52.4116835169433],"type":"Point"}
}