{
  "type": "Feature",
  "properties": {
    "date:inception_lower": "1980-01-01",
    "date:inception_upper": "1980-01-01",
    "iso:country": "GB",
    "wof:name": "SY7 9AS",
    "wof:placetype": "postalcode"
  },
  "geometry": {"coordinates":[-2.784881,52.411724],"type":"Point"}
}
