{
  "type": "Feature",
  "properties": {
    "iso:country":"GB",
    "wof:name":"BS13 8BF",
    "wof:placetype":"postalcode"
},
  "geometry": {"coordinates":[-2.62968499589276,51.4075844539091],"type":"Point"}
}