{
  "type": "Feature",
  "properties": {
    "iso:country":"GB",
    "wof:name":"BR2 8EF",
    "wof:placetype":"postalcode"
},
  "geometry": {"coordinates":[0.05184760081274,51.38871889980799],"type":"Point"}
}