{
  "type": "Feature",
  "properties": {
    "iso:country": "GB",
    "wof:name": "BR2 8EF",
    "wof:placetype": "postalcode"
  },
  "geometry": {"coordinates":[0.051848,51.388719],"type":"Point"}
}
