{
  "type": "Feature",
  "properties": {
    "iso:country": "GB",
    "wof:name": "BB12 6DY",
    "wof:placetype": "postalcode"
  },
  "geometry": {"coordinates":[-2.272413,53.792867],"type":"Point"}
}
