{
  "type": "Feature",
  "properties": {
    "iso:country":"GB",
    "wof:name":"CT1 3LE",
    "wof:placetype":"postalcode"
},
  "geometry": {"coordinates":[1.08484683475885,51.26851857823564],"type":"Point"}
}