{
  "type": "Feature",
  "properties": {
    "iso:country":"GB",
    "wof:name":"DD9 7LZ",
    "wof:placetype":"postalcode"
},
  "geometry": {"coordinates":[-2.64385857724267,56.72513488927738],"type":"Point"}
}