{
  "type": "Feature",
  "properties": {
    "iso:country": "GB",
    "wof:name": "DD9 7LZ",
    "wof:placetype": "postalcode"
  },
  "geometry": {"coordinates":[-2.643585,56.725009],"type":"Point"}
}
