{
  "type": "Feature",
  "properties": {
    "iso:country": "GB",
    "wof:name": "DE15 9DS",
    "wof:placetype": "postalcode"
  },
  "geometry": {"coordinates":[-1.605613,52.797562],"type":"Point"}
}
