{
  "type": "Feature",
  "properties": {
    "date:inception_lower": "1988-03-01",
    "date:inception_upper": "1988-03-01",
    "iso:country": "GB",
    "wof:name": "DE15 9DS",
    "wof:placetype": "postalcode"
  },
  "geometry": {"coordinates":[-1.605613,52.797562],"type":"Point"}
}
