{
  "type": "Feature",
  "properties": {
    "iso:country":"GB",
    "wof:name":"DE15 9DS",
    "wof:placetype":"postalcode"
},
  "geometry": {"coordinates":[-1.60561259292441,52.79756170407965],"type":"Point"}
}