{
  "type": "Feature",
  "properties": {
    "iso:country": "GB",
    "wof:name": "B27 7AH",
    "wof:placetype": "postalcode"
  },
  "geometry": {"coordinates":[-1.816437,52.435496],"type":"Point"}
}
