{
  "type": "Feature",
  "properties": {
    "iso:country":"GB",
    "wof:name":"B27 7AH",
    "wof:placetype":"postalcode"
},
  "geometry": {"coordinates":[-1.8164580860663,52.4354456385547],"type":"Point"}
}