{
  "type": "Feature",
  "properties": {
    "date:inception_lower": "1980-01-01",
    "date:inception_upper": "1980-01-01",
    "iso:country": "GB",
    "wof:name": "LL19 9PL",
    "wof:placetype": "postalcode"
  },
  "geometry": {"coordinates":[-3.398104,53.324511],"type":"Point"}
}
