{
  "type": "Feature",
  "properties": {
    "iso:country":"GB",
    "wof:name":"CH3 8HL",
    "wof:placetype":"postalcode"
},
  "geometry": {"coordinates":[-2.75320561788921,53.17248917165741],"type":"Point"}
}