{
  "type": "Feature",
  "properties": {
    "iso:country":"GB",
    "wof:name":"TF6 6NR",
    "wof:placetype":"postalcode"
},
  "geometry": {"coordinates":[-2.55094308526712,52.77466882838726],"type":"Point"}
}