{
  "type": "Feature",
  "properties": {
    "date:inception_lower": "1980-01-01",
    "date:inception_upper": "1980-01-01",
    "iso:country": "GB",
    "wof:name": "ML12 6RY",
    "wof:placetype": "postalcode"
  },
  "geometry": {"coordinates":[-3.694358,55.492237],"type":"Point"}
}
