{
  "type": "Feature",
  "properties": {
    "iso:country":"GB",
    "wof:name":"SN1 2AZ",
    "wof:placetype":"postalcode"
},
  "geometry": {"coordinates":[-1.78042807892001,51.56647728052896],"type":"Point"}
}