{
  "type": "Feature",
  "properties": {
    "iso:country":"GB",
    "wof:name":"SA14 7EN",
    "wof:placetype":"postalcode"
},
  "geometry": {"coordinates":[-4.11633293128881,51.81106476470104],"type":"Point"}
}