{
  "type": "Feature",
  "properties": {
    "date:inception_lower": "1980-01-01",
    "date:inception_upper": "1980-01-01",
    "iso:country": "GB",
    "wof:name": "PE22 8DQ",
    "wof:placetype": "postalcode"
  },
  "geometry": {"coordinates":[0.010345,53.089563],"type":"Point"}
}
