{
  "type": "Feature",
  "properties": {
    "iso:country": "GB",
    "wof:name": "LS22 6PP",
    "wof:placetype": "postalcode"
  },
  "geometry": {"coordinates":[-1.387671,53.93288],"type":"Point"}
}
