{
  "type": "Feature",
  "properties": {
    "iso:country":"GB",
    "wof:name":"LS22 6PP",
    "wof:placetype":"postalcode"
},
  "geometry": {"coordinates":[-1.38767108327108,53.93287976545606],"type":"Point"}
}