{
  "type": "Feature",
  "properties": {
    "iso:country":"GB",
    "wof:name":"DA6 8LU",
    "wof:placetype":"postalcode"
},
  "geometry": {"coordinates":[0.13374932320618,51.45177142554878],"type":"Point"}
}