{
  "type": "Feature",
  "properties": {
    "date:inception_lower": "1980-01-01",
    "date:inception_upper": "1980-01-01",
    "iso:country": "GB",
    "wof:name": "DA6 8LU",
    "wof:placetype": "postalcode"
  },
  "geometry": {"coordinates":[0.133749,51.451771],"type":"Point"}
}
