{
  "type": "Feature",
  "properties": {
    "iso:country": "GB",
    "wof:name": "S65 2AF",
    "wof:placetype": "postalcode"
  },
  "geometry": {"coordinates":[-1.348531,53.429149],"type":"Point"}
}
