{
  "type": "Feature",
  "properties": {
    "iso:country":"GB",
    "wof:name":"OL4 5AW",
    "wof:placetype":"postalcode"
},
  "geometry": {"coordinates":[-2.07427113171382,53.53689253125941],"type":"Point"}
}