{
  "type": "Feature",
  "properties": {
    "iso:country": "GB",
    "wof:name": "OL4 5AW",
    "wof:placetype": "postalcode"
  },
  "geometry": {"coordinates":[-2.074271,53.536893],"type":"Point"}
}
