{
  "type": "Feature",
  "properties": {
    "iso:country":"GB",
    "wof:name":"IV2 5EY",
    "wof:placetype":"postalcode"
},
  "geometry": {"coordinates":[-4.05584655107815,57.48249561725378],"type":"Point"}
}