{
  "type": "Feature",
  "properties": {
    "date:inception_lower": "1998-12-01",
    "date:inception_upper": "1998-12-01",
    "iso:country": "GB",
    "wof:name": "IV2 5EY",
    "wof:placetype": "postalcode"
  },
  "geometry": {"coordinates":[-4.055846,57.482496],"type":"Point"}
}
