{
  "type": "Feature",
  "properties": {
    "iso:country": "GB",
    "wof:name": "EX33 2HU",
    "wof:placetype": "postalcode"
  },
  "geometry": {"coordinates":[-4.160538,51.10104],"type":"Point"}
}
