{
  "type": "Feature",
  "properties": {
    "iso:country":"GB",
    "wof:name":"EX33 2HU",
    "wof:placetype":"postalcode"
},
  "geometry": {"coordinates":[-4.1605382228509,51.10103993052399],"type":"Point"}
}