{
  "type": "Feature",
  "properties": {
    "iso:country":"GB",
    "wof:name":"BB2 3HF",
    "wof:placetype":"postalcode"
},
  "geometry": {"coordinates":[-2.47098862450484,53.73514978772568],"type":"Point"}
}