{
  "type": "Feature",
  "properties": {
    "iso:country":"GB",
    "wof:name":"WN3 6EW",
    "wof:placetype":"postalcode"
},
  "geometry": {"coordinates":[-2.67219236765361,53.5236096453843],"type":"Point"}
}