{
  "type": "Feature",
  "properties": {
    "date:inception_lower": "1980-01-01",
    "date:inception_upper": "1980-01-01",
    "iso:country": "GB",
    "wof:name": "DA10 0AT",
    "wof:placetype": "postalcode"
  },
  "geometry": {"coordinates":[0.311233,51.445186],"type":"Point"}
}
