{
  "type": "Feature",
  "properties": {
    "iso:country":"GB",
    "wof:name":"CM20 2GF",
    "wof:placetype":"postalcode"
},
  "geometry": {"coordinates":[0.11114699525096,51.78251763580915],"type":"Point"}
}