{
  "type": "Feature",
  "properties": {
    "iso:country":"GB",
    "wof:name":"W5 1RR",
    "wof:placetype":"postalcode"
},
  "geometry": {"coordinates":[-0.31560770531303,51.52484116343797],"type":"Point"}
}