{
  "type": "Feature",
  "properties": {
    "iso:country":"GB",
    "wof:name":"M40 2RH",
    "wof:placetype":"postalcode"
},
  "geometry": {"coordinates":[-2.1796175550149,53.49425637896866],"type":"Point"}
}