{
  "type": "Feature",
  "properties": {
    "iso:country":"GB",
    "wof:name":"NE10 9TA",
    "wof:placetype":"postalcode"
},
  "geometry": {"coordinates":[-1.58012846846844,54.945075120045],"type":"Point"}
}