{
  "type": "Feature",
  "properties": {
    "iso:country": "GB",
    "wof:name": "NE10 9TA",
    "wof:placetype": "postalcode"
  },
  "geometry": {"coordinates":[-1.580128,54.945075],"type":"Point"}
}
