{
  "type": "Feature",
  "properties": {
    "iso:country": "GB",
    "wof:name": "BL1 5PD",
    "wof:placetype": "postalcode"
  },
  "geometry": {"coordinates":[-2.480992,53.58622],"type":"Point"}
}
