{
  "type": "Feature",
  "properties": {
    "iso:country": "GB",
    "wof:name": "CH60 2SZ",
    "wof:placetype": "postalcode"
  },
  "geometry": {"coordinates":[-3.079294,53.328757],"type":"Point"}
}
