{
  "type": "Feature",
  "properties": {
    "iso:country": "GB",
    "wof:name": "WN6 7DY",
    "wof:placetype": "postalcode"
  },
  "geometry": {"coordinates":[-2.64252,53.550316],"type":"Point"}
}
