{
  "type": "Feature",
  "properties": {
    "iso:country": "GB",
    "wof:name": "TS7 0GZ",
    "wof:placetype": "postalcode"
  },
  "geometry": {"coordinates":[-1.166057,54.534222],"type":"Point"}
}
