{
  "type": "Feature",
  "properties": {
    "iso:country":"GB",
    "wof:name":"L21 7PT",
    "wof:placetype":"postalcode"
},
  "geometry": {"coordinates":[-2.99436884920138,53.47328245333328],"type":"Point"}
}