{
  "type": "Feature",
  "properties": {
    "iso:country":"GB",
    "wof:name":"WF16 9JT",
    "wof:placetype":"postalcode"
},
  "geometry": {"coordinates":[-1.66581664122657,53.71129825062658],"type":"Point"}
}