{
  "type": "Feature",
  "properties": {
    "iso:country": "GB",
    "wof:name": "B25 8UL",
    "wof:placetype": "postalcode"
  },
  "geometry": {"coordinates":[-1.816181,52.463296],"type":"Point"}
}
