{
  "type": "Feature",
  "properties": {
    "date:inception_lower":"2014-01-01",
    "date:inception_upper":"2014-01-31",
    "iso:country":"GB",
    "wof:name":"TF3 5GP",
    "wof:placetype":"postalcode"
},
  "geometry": {"coordinates":[-2.480536,52.679673],"type":"Point"}
}