{
  "type": "Feature",
  "properties": {
    "date:inception_lower":"1992-08-01",
    "date:inception_upper":"1992-08-31",
    "iso:country":"GB",
    "wof:name":"OX44 9JD",
    "wof:placetype":"postalcode"
},
  "geometry": {"coordinates":[-1.139039,51.718782],"type":"Point"}
}