{
  "type": "Feature",
  "properties": {
    "iso:country":"GB",
    "wof:name":"NG32 1DT",
    "wof:placetype":"postalcode"
},
  "geometry": {"coordinates":[-0.69397202934657,52.91588537604301],"type":"Point"}
}