{
  "type": "Feature",
  "properties": {
    "iso:country":"GB",
    "wof:name":"WF10 3HG",
    "wof:placetype":"postalcode"
},
  "geometry": {"coordinates":[-1.32569188765244,53.71830754917475],"type":"Point"}
}