{
  "type": "Feature",
  "properties": {
    "date:inception_lower": "1980-01-01",
    "date:inception_upper": "1980-01-01",
    "iso:country": "GB",
    "wof:name": "WF10 3HG",
    "wof:placetype": "postalcode"
  },
  "geometry": {"coordinates":[-1.325692,53.718308],"type":"Point"}
}
