{
  "type": "Feature",
  "properties": {
    "iso:country": "GB",
    "wof:name": "DG12 5JH",
    "wof:placetype": "postalcode"
  },
  "geometry": {"coordinates":[-3.252256,54.992047],"type":"Point"}
}
