{
  "type": "Feature",
  "properties": {
    "date:inception_lower":"1980-01-01",
    "date:inception_upper":"1980-01-31",
    "iso:country":"GB",
    "wof:name":"CT9 1PU",
    "wof:placetype":"postalcode"
},
  "geometry": {"coordinates":[1.382585,51.388756],"type":"Point"}
}