{
  "type": "Feature",
  "properties": {
    "iso:country":"GB",
    "wof:name":"CT9 1PU",
    "wof:placetype":"postalcode"
},
  "geometry": {"coordinates":[1.38258506784816,51.38875587766731],"type":"Point"}
}