{
  "type": "Feature",
  "properties": {
    "iso:country":"GB",
    "wof:name":"HX7 7DR",
    "wof:placetype":"postalcode"
},
  "geometry": {"coordinates":[-2.01259312553298,53.74456029208341],"type":"Point"}
}