{
  "type": "Feature",
  "properties": {
    "iso:country":"GB",
    "wof:name":"KY11 9YL",
    "wof:placetype":"postalcode"
},
  "geometry": {"coordinates":[-3.36696984905123,56.02994395732451],"type":"Point"}
}