{
  "type": "Feature",
  "properties": {
    "iso:country":"GB",
    "wof:name":"HU3 6LJ",
    "wof:placetype":"postalcode"
},
  "geometry": {"coordinates":[-0.37849606488754,53.75082673507971],"type":"Point"}
}