{
  "type": "Feature",
  "properties": {
    "iso:country":"GB",
    "wof:name":"EH52 5DW",
    "wof:placetype":"postalcode"
},
  "geometry": {"coordinates":[-3.50666628410712,55.92982241367965],"type":"Point"}
}