{
  "type": "Feature",
  "properties": {
    "iso:country":"GB",
    "wof:name":"NR1 3JJ",
    "wof:placetype":"postalcode"
},
  "geometry": {"coordinates":[1.2965769152016,52.61830003287605],"type":"Point"}
}