{
  "type": "Feature",
  "properties": {
    "date:inception_lower": "1980-01-01",
    "date:inception_upper": "1980-01-01",
    "iso:country": "GB",
    "wof:name": "ML2 0QZ",
    "wof:placetype": "postalcode"
  },
  "geometry": {"coordinates":[-3.919206,55.754917],"type":"Point"}
}
