{
  "type": "Feature",
  "properties": {
    "iso:country":"GB",
    "wof:name":"ML2 0QZ",
    "wof:placetype":"postalcode"
},
  "geometry": {"coordinates":[-3.91920590672564,55.75491711307964],"type":"Point"}
}