{
  "type": "Feature",
  "properties": {
    "iso:country": "GB",
    "wof:name": "CH65 0AL",
    "wof:placetype": "postalcode"
  },
  "geometry": {"coordinates":[-2.900833,53.278668],"type":"Point"}
}
