{
  "type": "Feature",
  "properties": {
    "iso:country":"GB",
    "wof:name":"E1 3AE",
    "wof:placetype":"postalcode"
},
  "geometry": {"coordinates":[-0.05376774930313,51.51930519301231],"type":"Point"}
}