{
  "type": "Feature",
  "properties": {
    "iso:country":"GB",
    "wof:name":"TS12 2QN",
    "wof:placetype":"postalcode"
},
  "geometry": {"coordinates":[-0.93668509244618,54.57166785553913],"type":"Point"}
}