{
  "type": "Feature",
  "properties": {
    "iso:country":"GB",
    "wof:name":"BL9 8DZ",
    "wof:placetype":"postalcode"
},
  "geometry": {"coordinates":[-2.28841153106096,53.5624718110245],"type":"Point"}
}