{
  "type": "Feature",
  "properties": {
    "iso:country": "GB",
    "wof:name": "BL9 8DZ",
    "wof:placetype": "postalcode"
  },
  "geometry": {"coordinates":[-2.288411,53.562472],"type":"Point"}
}
