{
  "type": "Feature",
  "properties": {
    "date:inception_lower":"2006-09-01",
    "date:inception_upper":"2006-09-30",
    "iso:country":"GB",
    "wof:name":"CV3 1LB",
    "wof:placetype":"postalcode"
},
  "geometry": {"coordinates":[-1.465355,52.400721],"type":"Point"}
}