{
  "type": "Feature",
  "properties": {
    "iso:country":"GB",
    "wof:name":"CV3 1LB",
    "wof:placetype":"postalcode"
},
  "geometry": {"coordinates":[-1.46535459951496,52.40072121352665],"type":"Point"}
}