{
  "type": "Feature",
  "properties": {
    "iso:country":"GB",
    "wof:name":"SE1 6LW",
    "wof:placetype":"postalcode"
},
  "geometry": {"coordinates":[-0.10092587399371,51.4958522593205],"type":"Point"}
}