{
  "type": "Feature",
  "properties": {
    "iso:country":"GB",
    "wof:name":"LS18 5JW",
    "wof:placetype":"postalcode"
},
  "geometry": {"coordinates":[-1.65261311458827,53.8390796292973],"type":"Point"}
}