{
  "type": "Feature",
  "properties": {
    "iso:country":"GB",
    "wof:name":"TS12 3AU",
    "wof:placetype":"postalcode"
},
  "geometry": {"coordinates":[-0.98197914557537,54.54303735362253],"type":"Point"}
}