{
  "type": "Feature",
  "properties": {
    "iso:country":"GB",
    "wof:name":"HU4 7AP",
    "wof:placetype":"postalcode"
},
  "geometry": {"coordinates":[-0.41102756918619,53.72793575727652],"type":"Point"}
}