{
  "type": "Feature",
  "properties": {
    "date:inception_lower": "1980-01-01",
    "date:inception_upper": "1980-01-01",
    "iso:country": "GB",
    "wof:name": "HR2 7NB",
    "wof:placetype": "postalcode"
  },
  "geometry": {"coordinates":[-2.727394,52.042469],"type":"Point"}
}
