{
  "type": "Feature",
  "properties": {
    "iso:country":"GB",
    "wof:name":"HR2 7NB",
    "wof:placetype":"postalcode"
},
  "geometry": {"coordinates":[-2.7273936984669,52.04246867989031],"type":"Point"}
}