{
  "type": "Feature",
  "properties": {
    "iso:country":"GB",
    "wof:name":"EH16 6ET",
    "wof:placetype":"postalcode"
},
  "geometry": {"coordinates":[-3.15943218984292,55.90629172330082],"type":"Point"}
}