{
  "type": "Feature",
  "properties": {
    "iso:country":"GB",
    "wof:name":"DY8 3UG",
    "wof:placetype":"postalcode"
},
  "geometry": {"coordinates":[-2.15787712977537,52.45261690242736],"type":"Point"}
}