{
  "type": "Feature",
  "properties": {
    "iso:country":"GB",
    "wof:name":"PO13 0YL",
    "wof:placetype":"postalcode"
},
  "geometry": {"coordinates":[-1.17048756027405,50.82972461645701],"type":"Point"}
}