{
  "type": "Feature",
  "properties": {
    "iso:country":"GB",
    "wof:name":"EH53 0QS",
    "wof:placetype":"postalcode"
},
  "geometry": {"coordinates":[-3.46218744578343,55.88655225796479],"type":"Point"}
}