{
  "type": "Feature",
  "properties": {
    "iso:country": "GB",
    "wof:name": "EH53 0QS",
    "wof:placetype": "postalcode"
  },
  "geometry": {"coordinates":[-3.462187,55.886552],"type":"Point"}
}
