{
  "type": "Feature",
  "properties": {
    "date:inception_lower": "2017-06-01",
    "date:inception_upper": "2017-06-01",
    "iso:country": "GB",
    "wof:name": "NN14 1TJ",
    "wof:placetype": "postalcode"
  },
  "geometry": {"coordinates":[-0.762364,52.439325],"type":"Point"}
}
