{
  "type": "Feature",
  "properties": {
    "date:inception_lower": "1980-01-01",
    "date:inception_upper": "1980-01-01",
    "iso:country": "GB",
    "wof:name": "TN32 5QJ",
    "wof:placetype": "postalcode"
  },
  "geometry": {"coordinates":[0.542297,50.974045],"type":"Point"}
}
