{
  "type": "Feature",
  "properties": {
    "iso:country":"GB",
    "wof:name":"CV5 6UD",
    "wof:placetype":"postalcode"
},
  "geometry": {"coordinates":[-1.55272500425282,52.40153335123049],"type":"Point"}
}