{
  "type": "Feature",
  "properties": {
    "iso:country":"GB",
    "wof:name":"HU3 1RN",
    "wof:placetype":"postalcode"
},
  "geometry": {"coordinates":[-0.3486680068429,53.75070714600893],"type":"Point"}
}