{
  "type": "Feature",
  "properties": {
    "iso:country": "GB",
    "wof:name": "HU3 1RN",
    "wof:placetype": "postalcode"
  },
  "geometry": {"coordinates":[-0.348668,53.750707],"type":"Point"}
}
