{
  "type": "Feature",
  "properties": {
    "date:inception_lower":"2010-03-01",
    "date:inception_upper":"2010-03-31",
    "iso:country":"GB",
    "wof:name":"HU3 1RN",
    "wof:placetype":"postalcode"
},
  "geometry": {"coordinates":[-0.348668,53.750707],"type":"Point"}
}