{
  "type": "Feature",
  "properties": {
    "iso:country":"GB",
    "wof:name":"CM8 2QN",
    "wof:placetype":"postalcode"
},
  "geometry": {"coordinates":[0.63359706244135,51.81482347363389],"type":"Point"}
}