{
  "type": "Feature",
  "properties": {
    "iso:country":"GB",
    "wof:name":"AL9 7AQ",
    "wof:placetype":"postalcode"
},
  "geometry": {"coordinates":[-0.18435582574856,51.72132527233641],"type":"Point"}
}