{
  "type": "Feature",
  "properties": {
    "date:inception_lower": "2019-02-01",
    "date:inception_upper": "2019-02-01",
    "iso:country": "GB",
    "wof:name": "SK14 2DR",
    "wof:placetype": "postalcode"
  },
  "geometry": {"coordinates":[-2.089603,53.452623],"type":"Point"}
}
