{
  "type": "Feature",
  "properties": {
    "iso:country":"GB",
    "wof:name":"LS9 0NY",
    "wof:placetype":"postalcode"
},
  "geometry": {"coordinates":[-1.51958984826465,53.78645453854207],"type":"Point"}
}