{
  "type": "Feature",
  "properties": {
    "iso:country": "GB",
    "wof:name": "LS9 0NY",
    "wof:placetype": "postalcode"
  },
  "geometry": {"coordinates":[-1.519594,53.786471],"type":"Point"}
}
