{
  "type": "Feature",
  "properties": {
    "iso:country": "GB",
    "wof:name": "EX2 8JN",
    "wof:placetype": "postalcode"
  },
  "geometry": {"coordinates":[-3.534382,50.711755],"type":"Point"}
}
