{
  "type": "Feature",
  "properties": {
    "date:inception_lower":"1999-06-01",
    "date:inception_upper":"1999-06-30",
    "iso:country":"GB",
    "wof:name":"NP20 2HZ",
    "wof:placetype":"postalcode"
},
  "geometry": {"coordinates":[-2.982023,51.577095],"type":"Point"}
}