{
  "type": "Feature",
  "properties": {
    "iso:country":"GB",
    "wof:name":"NP20 2HZ",
    "wof:placetype":"postalcode"
},
  "geometry": {"coordinates":[-2.98181315935493,51.57701361022092],"type":"Point"}
}