{
  "type": "Feature",
  "properties": {
    "iso:country":"GB",
    "wof:name":"E17 4LN",
    "wof:placetype":"postalcode"
},
  "geometry": {"coordinates":[-0.01373918101141,51.59944159916726],"type":"Point"}
}