{
  "type": "Feature",
  "properties": {
    "iso:country": "GB",
    "wof:name": "SP5 3AW",
    "wof:placetype": "postalcode"
  },
  "geometry": {"coordinates":[-1.741156,51.045863],"type":"Point"}
}
