{
  "type": "Feature",
  "properties": {
    "iso:country":"GB",
    "wof:name":"SP5 3AW",
    "wof:placetype":"postalcode"
},
  "geometry": {"coordinates":[-1.74115647036585,51.04586299691909],"type":"Point"}
}