{
  "type": "Feature",
  "properties": {
    "date:inception_lower": "2004-01-01",
    "date:inception_upper": "2004-01-01",
    "iso:country": "GB",
    "wof:name": "SK23 9HF",
    "wof:placetype": "postalcode"
  },
  "geometry": {"coordinates":[-1.919899,53.32245],"type":"Point"}
}
