{
  "type": "Feature",
  "properties": {
    "date:inception_lower": "2000-12-01",
    "date:inception_upper": "2000-12-01",
    "iso:country": "GB",
    "wof:name": "S74 9AQ",
    "wof:placetype": "postalcode"
  },
  "geometry": {"coordinates":[-1.440988,53.500025],"type":"Point"}
}
