{
  "type": "Feature",
  "properties": {
    "iso:country": "GB",
    "wof:name": "S74 9AQ",
    "wof:placetype": "postalcode"
  },
  "geometry": {"coordinates":[-1.440988,53.500025],"type":"Point"}
}
