{
  "type": "Feature",
  "properties": {
    "iso:country": "GB",
    "wof:name": "G66 5ND",
    "wof:placetype": "postalcode"
  },
  "geometry": {"coordinates":[-4.139641,55.923264],"type":"Point"}
}
