{
  "type": "Feature",
  "properties": {
    "iso:country":"GB",
    "wof:name":"RG1 8AS",
    "wof:placetype":"postalcode"
},
  "geometry": {"coordinates":[-0.97550916530706,51.46244905983237],"type":"Point"}
}