{
  "type": "Feature",
  "properties": {
    "iso:country":"GB",
    "wof:name":"WA4 1RS",
    "wof:placetype":"postalcode"
},
  "geometry": {"coordinates":[-2.55965934598441,53.38560336716048],"type":"Point"}
}