{
  "type": "Feature",
  "properties": {
    "date:inception_lower": "2005-02-01",
    "date:inception_upper": "2005-02-01",
    "iso:country": "GB",
    "wof:name": "MK10 1SE",
    "wof:placetype": "postalcode"
  },
  "geometry": {"coordinates":[-0.760872,52.043552],"type":"Point"}
}
