{
  "type": "Feature",
  "properties": {
    "iso:country":"GB",
    "wof:name":"B43 6BW",
    "wof:placetype":"postalcode"
},
  "geometry": {"coordinates":[-1.93584118896461,52.54530163907456],"type":"Point"}
}