{
  "type": "Feature",
  "properties": {
    "date:inception_lower": "1990-02-01",
    "date:inception_upper": "1990-02-01",
    "iso:country": "GB",
    "wof:name": "AL7 2PP",
    "wof:placetype": "postalcode"
  },
  "geometry": {"coordinates":[-0.16506,51.802359],"type":"Point"}
}
