{
  "type": "Feature",
  "properties": {
    "iso:country":"GB",
    "wof:name":"EX14 3EP",
    "wof:placetype":"postalcode"
},
  "geometry": {"coordinates":[-3.23987109882575,50.79763617663431],"type":"Point"}
}