{
  "type": "Feature",
  "properties": {
    "date:inception_lower": "1999-12-01",
    "date:inception_upper": "1999-12-01",
    "iso:country": "GB",
    "wof:name": "EX14 3EP",
    "wof:placetype": "postalcode"
  },
  "geometry": {"coordinates":[-3.239577,50.797846],"type":"Point"}
}
