{
  "type": "Feature",
  "properties": {
    "iso:country":"GB",
    "wof:name":"GL6 6BJ",
    "wof:placetype":"postalcode"
},
  "geometry": {"coordinates":[-2.23232650809382,51.76907788571427],"type":"Point"}
}