{
  "type": "Feature",
  "properties": {
    "iso:country": "GB",
    "wof:name": "GL6 6BJ",
    "wof:placetype": "postalcode"
  },
  "geometry": {"coordinates":[-2.232326,51.769078],"type":"Point"}
}
