{
  "type": "Feature",
  "properties": {
    "iso:country":"GB",
    "wof:name":"B13 0BG",
    "wof:placetype":"postalcode"
},
  "geometry": {"coordinates":[-1.85653184629552,52.43367597442885],"type":"Point"}
}