{
  "type": "Feature",
  "properties": {
    "iso:country":"GB",
    "wof:name":"NR17 2LJ",
    "wof:placetype":"postalcode"
},
  "geometry": {"coordinates":[1.04705163850264,52.51941612874035],"type":"Point"}
}