{
  "type": "Feature",
  "properties": {
    "date:inception_lower": "1980-01-01",
    "date:inception_upper": "1980-01-01",
    "iso:country": "GB",
    "wof:name": "NR17 2LJ",
    "wof:placetype": "postalcode"
  },
  "geometry": {"coordinates":[1.047052,52.519416],"type":"Point"}
}
