{
  "type": "Feature",
  "properties": {
    "iso:country":"GB",
    "wof:name":"LL53 5RG",
    "wof:placetype":"postalcode"
},
  "geometry": {"coordinates":[-4.41859334204917,52.88904397486419],"type":"Point"}
}