{
  "type": "Feature",
  "properties": {
    "iso:country": "GB",
    "wof:name": "LA8 8HB",
    "wof:placetype": "postalcode"
  },
  "geometry": {"coordinates":[-2.798378,54.32267],"type":"Point"}
}
