{
  "type": "Feature",
  "properties": {
    "iso:country": "GB",
    "wof:name": "HP13 6XR",
    "wof:placetype": "postalcode"
  },
  "geometry": {"coordinates":[-0.734923,51.633671],"type":"Point"}
}
