{
  "type": "Feature",
  "properties": {
    "iso:country":"GB",
    "wof:name":"HP13 6XR",
    "wof:placetype":"postalcode"
},
  "geometry": {"coordinates":[-0.73492256613291,51.63367092703098],"type":"Point"}
}