{
  "type": "Feature",
  "properties": {
    "iso:country":"GB",
    "wof:name":"RM16 4TX",
    "wof:placetype":"postalcode"
},
  "geometry": {"coordinates":[0.37699796109486,51.49136430822275],"type":"Point"}
}