{
  "type": "Feature",
  "properties": {
    "date:inception_lower": "1980-01-01",
    "date:inception_upper": "1980-01-01",
    "iso:country": "GB",
    "wof:name": "NR12 0UE",
    "wof:placetype": "postalcode"
  },
  "geometry": {"coordinates":[1.599287,52.785698],"type":"Point"}
}
