{
  "type": "Feature",
  "properties": {
    "iso:country": "GB",
    "wof:name": "DN17 3AQ",
    "wof:placetype": "postalcode"
  },
  "geometry": {"coordinates":[-0.736827,53.543409],"type":"Point"}
}
