{
  "type": "Feature",
  "properties": {
    "iso:country":"GB",
    "wof:name":"DN17 3AQ",
    "wof:placetype":"postalcode"
},
  "geometry": {"coordinates":[-0.73682429356733,53.543388507671],"type":"Point"}
}