{
  "type": "Feature",
  "properties": {
    "date:inception_lower": "1980-01-01",
    "date:inception_upper": "1980-01-01",
    "iso:country": "GB",
    "wof:name": "GL20 7JE",
    "wof:placetype": "postalcode"
  },
  "geometry": {"coordinates":[-2.078597,52.033873],"type":"Point"}
}
