{
  "type": "Feature",
  "properties": {
    "iso:country":"GB",
    "wof:name":"GL20 7JE",
    "wof:placetype":"postalcode"
},
  "geometry": {"coordinates":[-2.07859748861199,52.03387315854965],"type":"Point"}
}