{
  "type": "Feature",
  "properties": {
    "date:inception_lower": "2021-11-01",
    "date:inception_upper": "2021-11-01",
    "iso:country": "GB",
    "wof:name": "TN14 7EL",
    "wof:placetype": "postalcode"
  },
  "geometry": {"coordinates":[0.129555,51.325982],"type":"Point"}
}
