{
  "type": "Feature",
  "properties": {
    "iso:country": "GB",
    "wof:name": "KA8 0JP",
    "wof:placetype": "postalcode"
  },
  "geometry": {"coordinates":[-4.607365,55.468956],"type":"Point"}
}
