{
  "type": "Feature",
  "properties": {
    "date:inception_lower": "1980-01-01",
    "date:inception_upper": "1980-01-01",
    "iso:country": "GB",
    "wof:name": "KA8 0JP",
    "wof:placetype": "postalcode"
  },
  "geometry": {"coordinates":[-4.607245,55.468823],"type":"Point"}
}
