{
  "type": "Feature",
  "properties": {
    "iso:country":"GB",
    "wof:name":"EH9 3AQ",
    "wof:placetype":"postalcode"
},
  "geometry": {"coordinates":[-3.17453680831011,55.92865723603522],"type":"Point"}
}