{
  "type": "Feature",
  "properties": {
    "iso:country":"GB",
    "wof:name":"EX31 3DS",
    "wof:placetype":"postalcode"
},
  "geometry": {"coordinates":[-4.13679714291988,51.06972967711842],"type":"Point"}
}