{
  "type": "Feature",
  "properties": {
    "date:inception_lower":"1980-01-01",
    "date:inception_upper":"1980-01-31",
    "iso:country":"GB",
    "wof:name":"LA16 7DP",
    "wof:placetype":"postalcode"
},
  "geometry": {"coordinates":[-3.195539,54.188164],"type":"Point"}
}