{
  "type": "Feature",
  "properties": {
    "iso:country":"GB",
    "wof:name":"EX23 8EE",
    "wof:placetype":"postalcode"
},
  "geometry": {"coordinates":[-4.52863509452959,50.82477521796385],"type":"Point"}
}