{
  "type": "Feature",
  "properties": {
    "date:inception_lower": "2014-12-01",
    "date:inception_upper": "2014-12-01",
    "iso:country": "GB",
    "wof:name": "EX23 8EE",
    "wof:placetype": "postalcode"
  },
  "geometry": {"coordinates":[-4.528635,50.824775],"type":"Point"}
}
