{
  "type": "Feature",
  "properties": {
    "iso:country": "GB",
    "wof:name": "DE13 0PQ",
    "wof:placetype": "postalcode"
  },
  "geometry": {"coordinates":[-1.653381,52.827727],"type":"Point"}
}
