{
  "type": "Feature",
  "properties": {
    "iso:country":"GB",
    "wof:name":"NW9 5LY",
    "wof:placetype":"postalcode"
},
  "geometry": {"coordinates":[-0.24338736739511,51.59744705897266],"type":"Point"}
}