{
  "type": "Feature",
  "properties": {
    "iso:country": "GB",
    "wof:name": "LL65 2AN",
    "wof:placetype": "postalcode"
  },
  "geometry": {"coordinates":[-4.635408,53.305607],"type":"Point"}
}
