{
  "type": "Feature",
  "properties": {
    "iso:country":"GB",
    "wof:name":"LL65 2AN",
    "wof:placetype":"postalcode"
},
  "geometry": {"coordinates":[-4.63540800375684,53.30560678902464],"type":"Point"}
}