{
  "type": "Feature",
  "properties": {
    "iso:country":"GB",
    "wof:name":"GL54 3AW",
    "wof:placetype":"postalcode"
},
  "geometry": {"coordinates":[-1.8331239784941,51.82831480415074],"type":"Point"}
}