{
  "type": "Feature",
  "properties": {
    "iso:country": "GB",
    "wof:name": "UB10 0QB",
    "wof:placetype": "postalcode"
  },
  "geometry": {"coordinates":[-0.443517,51.532813],"type":"Point"}
}
