{
  "type": "Feature",
  "properties": {
    "date:inception_lower": "1980-01-01",
    "date:inception_upper": "1980-01-01",
    "iso:country": "GB",
    "wof:name": "UB10 0QB",
    "wof:placetype": "postalcode"
  },
  "geometry": {"coordinates":[-0.443517,51.532813],"type":"Point"}
}
