{
  "type": "Feature",
  "properties": {
    "iso:country":"GB",
    "wof:name":"UB10 0QB",
    "wof:placetype":"postalcode"
},
  "geometry": {"coordinates":[-0.44351664202134,51.53281255841705],"type":"Point"}
}