{
  "type": "Feature",
  "properties": {
    "iso:country": "GB",
    "wof:name": "TS16 0EE",
    "wof:placetype": "postalcode"
  },
  "geometry": {"coordinates":[-1.354767,54.519708],"type":"Point"}
}
