{
  "type": "Feature",
  "properties": {
    "iso:country":"GB",
    "wof:name":"TS16 0EE",
    "wof:placetype":"postalcode"
},
  "geometry": {"coordinates":[-1.354766796193,54.51970755019697],"type":"Point"}
}