{
  "type": "Feature",
  "properties": {
    "iso:country":"GB",
    "wof:name":"BB1 5NJ",
    "wof:placetype":"postalcode"
},
  "geometry": {"coordinates":[-2.46822607938369,53.75936563010867],"type":"Point"}
}