{
  "type": "Feature",
  "properties": {
    "iso:country": "GB",
    "wof:name": "G66 7JH",
    "wof:placetype": "postalcode"
  },
  "geometry": {"coordinates":[-4.20462,55.972185],"type":"Point"}
}
