{
  "type": "Feature",
  "properties": {
    "date:inception_lower":"1998-12-01",
    "date:inception_upper":"1998-12-31",
    "iso:country":"GB",
    "wof:name":"G66 7JH",
    "wof:placetype":"postalcode"
},
  "geometry": {"coordinates":[-4.20462,55.972185],"type":"Point"}
}