{
  "type": "Feature",
  "properties": {
    "iso:country":"GB",
    "wof:name":"M25 0DU",
    "wof:placetype":"postalcode"
},
  "geometry": {"coordinates":[-2.2602801805711,53.52480322719209],"type":"Point"}
}