{
  "type": "Feature",
  "properties": {
    "iso:country":"GB",
    "wof:name":"LE8 0PT",
    "wof:placetype":"postalcode"
},
  "geometry": {"coordinates":[-0.99424347503407,52.54452793860639],"type":"Point"}
}