{
  "type": "Feature",
  "properties": {
    "date:inception_lower": "1987-04-01",
    "date:inception_upper": "1987-04-01",
    "iso:country": "GB",
    "wof:name": "LE8 0PT",
    "wof:placetype": "postalcode"
  },
  "geometry": {"coordinates":[-0.994243,52.544528],"type":"Point"}
}
