{
  "type": "Feature",
  "properties": {
    "date:inception_lower": "1994-05-01",
    "date:inception_upper": "1994-05-01",
    "iso:country": "GB",
    "wof:name": "CV3 2XE",
    "wof:placetype": "postalcode"
  },
  "geometry": {"coordinates":[-1.4345,52.403302],"type":"Point"}
}
