{
  "type": "Feature",
  "properties": {
    "iso:country":"GB",
    "wof:name":"CV3 2XE",
    "wof:placetype":"postalcode"
},
  "geometry": {"coordinates":[-1.4345001957649,52.40330175139604],"type":"Point"}
}