{
  "type": "Feature",
  "properties": {
    "iso:country": "GB",
    "wof:name": "S40 1PZ",
    "wof:placetype": "postalcode"
  },
  "geometry": {"coordinates":[-1.427656,53.235604],"type":"Point"}
}
