{
  "type": "Feature",
  "properties": {
    "date:inception_lower":"2015-02-01",
    "date:inception_upper":"2015-02-28",
    "iso:country":"GB",
    "wof:name":"S40 1PZ",
    "wof:placetype":"postalcode"
},
  "geometry": {"coordinates":[-1.427656,53.235604],"type":"Point"}
}