{
  "type": "Feature",
  "properties": {
    "iso:country":"GB",
    "wof:name":"S40 1PZ",
    "wof:placetype":"postalcode"
},
  "geometry": {"coordinates":[-1.42765766518364,53.23557625970457],"type":"Point"}
}