{
  "type": "Feature",
  "properties": {
    "date:inception_lower": "1998-12-01",
    "date:inception_upper": "1998-12-01",
    "iso:country": "GB",
    "wof:name": "IV30 8JS",
    "wof:placetype": "postalcode"
  },
  "geometry": {"coordinates":[-3.218376,57.636111],"type":"Point"}
}
