{
  "type": "Feature",
  "properties": {
    "iso:country":"GB",
    "wof:name":"N18 2JF",
    "wof:placetype":"postalcode"
},
  "geometry": {"coordinates":[-0.06190493838138,51.61378951194724],"type":"Point"}
}