{
  "type": "Feature",
  "properties": {
    "iso:country": "GB",
    "wof:name": "GU22 8QT",
    "wof:placetype": "postalcode"
  },
  "geometry": {"coordinates":[-0.513214,51.327533],"type":"Point"}
}
