{
  "type": "Feature",
  "properties": {
    "iso:country": "GB",
    "wof:name": "HP14 4SF",
    "wof:placetype": "postalcode"
  },
  "geometry": {"coordinates":[-0.778756,51.666694],"type":"Point"}
}
