{
  "type": "Feature",
  "properties": {
    "iso:country":"GB",
    "wof:name":"SA67 8TA",
    "wof:placetype":"postalcode"
},
  "geometry": {"coordinates":[-4.72858812189568,51.79778724362048],"type":"Point"}
}