{
  "type": "Feature",
  "properties": {
    "iso:country":"GB",
    "wof:name":"SA70 8QG",
    "wof:placetype":"postalcode"
},
  "geometry": {"coordinates":[-4.81192656759402,51.65565646461674],"type":"Point"}
}