{
  "type": "Feature",
  "properties": {
    "iso:country":"GB",
    "wof:name":"L37 1QA",
    "wof:placetype":"postalcode"
},
  "geometry": {"coordinates":[-3.08176571824805,53.5660879172646],"type":"Point"}
}