{
  "type": "Feature",
  "properties": {
    "iso:country": "GB",
    "wof:name": "L37 1QA",
    "wof:placetype": "postalcode"
  },
  "geometry": {"coordinates":[-3.082307,53.566099],"type":"Point"}
}
