{
  "type": "Feature",
  "properties": {
    "iso:country":"GB",
    "wof:name":"NP15 2BB",
    "wof:placetype":"postalcode"
},
  "geometry": {"coordinates":[-2.91164323519765,51.78404140868985],"type":"Point"}
}