{
  "type": "Feature",
  "properties": {
    "iso:country": "GB",
    "wof:name": "NP15 2BB",
    "wof:placetype": "postalcode"
  },
  "geometry": {"coordinates":[-2.911738,51.784197],"type":"Point"}
}
