{
  "type": "Feature",
  "properties": {
    "date:inception_lower":"1980-01-01",
    "date:inception_upper":"1980-01-31",
    "iso:country":"GB",
    "wof:name":"EH28 8LA",
    "wof:placetype":"postalcode"
},
  "geometry": {"coordinates":[-3.421707,55.93821],"type":"Point"}
}