{
  "type": "Feature",
  "properties": {
    "date:inception_lower": "1996-06-01",
    "date:inception_upper": "1996-06-01",
    "iso:country": "GB",
    "wof:name": "AB16 7AQ",
    "wof:placetype": "postalcode"
  },
  "geometry": {"coordinates":[-2.146112,57.164829],"type":"Point"}
}
