{
  "type": "Feature",
  "properties": {
    "iso:country": "GB",
    "wof:name": "KY5 0EW",
    "wof:placetype": "postalcode"
  },
  "geometry": {"coordinates":[-3.255095,56.138895],"type":"Point"}
}
