{
  "type": "Feature",
  "properties": {
    "date:inception_lower": "1980-01-01",
    "date:inception_upper": "1980-01-01",
    "iso:country": "GB",
    "wof:name": "N8 0LT",
    "wof:placetype": "postalcode"
  },
  "geometry": {"coordinates":[-0.109214,51.588285],"type":"Point"}
}
