{
  "type": "Feature",
  "properties": {
    "iso:country":"GB",
    "wof:name":"N8 0LT",
    "wof:placetype":"postalcode"
},
  "geometry": {"coordinates":[-0.10921429529668,51.58828523991664],"type":"Point"}
}