{
  "type": "Feature",
  "properties": {
    "iso:country":"GB",
    "wof:name":"BN2 8PG",
    "wof:placetype":"postalcode"
},
  "geometry": {"coordinates":[-0.03050619138215,50.80432388249227],"type":"Point"}
}