{
  "type": "Feature",
  "properties": {
    "iso:country":"GB",
    "wof:name":"DN7 5BJ",
    "wof:placetype":"postalcode"
},
  "geometry": {"coordinates":[-1.02073214007396,53.59988299125773],"type":"Point"}
}