{
  "type": "Feature",
  "properties": {
    "date:inception_lower": "1980-01-01",
    "date:inception_upper": "1980-01-01",
    "iso:country": "GB",
    "wof:name": "SK10 1QA",
    "wof:placetype": "postalcode"
  },
  "geometry": {"coordinates":[-2.109358,53.264377],"type":"Point"}
}
