{
  "type": "Feature",
  "properties": {
    "iso:country": "GB",
    "wof:name": "SK10 1QA",
    "wof:placetype": "postalcode"
  },
  "geometry": {"coordinates":[-2.109358,53.264377],"type":"Point"}
}
