{
  "type": "Feature",
  "properties": {
    "iso:country":"GB",
    "wof:name":"SK10 1QA",
    "wof:placetype":"postalcode"
},
  "geometry": {"coordinates":[-2.10935776828421,53.26437729846502],"type":"Point"}
}