{
  "type": "Feature",
  "properties": {
    "iso:country": "GB",
    "wof:name": "PE11 3LQ",
    "wof:placetype": "postalcode"
  },
  "geometry": {"coordinates":[-0.174447,52.787398],"type":"Point"}
}
