{
  "type": "Feature",
  "properties": {
    "iso:country":"GB",
    "wof:name":"TN4 9QH",
    "wof:placetype":"postalcode"
},
  "geometry": {"coordinates":[0.26309102743738,51.1418194358112],"type":"Point"}
}