{
  "type": "Feature",
  "properties": {
    "iso:country":"GB",
    "wof:name":"M22 1AJ",
    "wof:placetype":"postalcode"
},
  "geometry": {"coordinates":[-2.26786430199145,53.37607157970863],"type":"Point"}
}