{
  "type": "Feature",
  "properties": {
    "iso:country": "GB",
    "wof:name": "BS30 8BL",
    "wof:placetype": "postalcode"
  },
  "geometry": {"coordinates":[-2.477504,51.450564],"type":"Point"}
}
