{
  "type": "Feature",
  "properties": {
    "date:inception_lower": "1997-12-01",
    "date:inception_upper": "1997-12-01",
    "iso:country": "GB",
    "wof:name": "BS30 8BL",
    "wof:placetype": "postalcode"
  },
  "geometry": {"coordinates":[-2.477504,51.450564],"type":"Point"}
}
