{
  "type": "Feature",
  "properties": {
    "iso:country":"GB",
    "wof:name":"BS30 8BL",
    "wof:placetype":"postalcode"
},
  "geometry": {"coordinates":[-2.47750420250672,51.45056428673519],"type":"Point"}
}