{
  "type": "Feature",
  "properties": {
    "iso:country": "GB",
    "wof:name": "RG12 7PT",
    "wof:placetype": "postalcode"
  },
  "geometry": {"coordinates":[-0.748433,51.397535],"type":"Point"}
}
