{
  "type": "Feature",
  "properties": {
    "iso:country":"GB",
    "wof:name":"TN12 8JB",
    "wof:placetype":"postalcode"
},
  "geometry": {"coordinates":[0.42709437790659,51.13942916542845],"type":"Point"}
}