{
  "type": "Feature",
  "properties": {
    "iso:country":"GB",
    "wof:name":"BS16 4BP",
    "wof:placetype":"postalcode"
},
  "geometry": {"coordinates":[-2.52400935827102,51.47394155622283],"type":"Point"}
}