{
  "type": "Feature",
  "properties": {
    "iso:country": "GB",
    "wof:name": "G69 9FR",
    "wof:placetype": "postalcode"
  },
  "geometry": {"coordinates":[-4.114007,55.893919],"type":"Point"}
}
