{
  "type": "Feature",
  "properties": {
    "iso:country": "GB",
    "wof:name": "B20 1JE",
    "wof:placetype": "postalcode"
  },
  "geometry": {"coordinates":[-1.937698,52.525228],"type":"Point"}
}
