{
  "type": "Feature",
  "properties": {
    "iso:country": "GB",
    "wof:name": "DN21 1GD",
    "wof:placetype": "postalcode"
  },
  "geometry": {"coordinates":[-0.748984,53.395029],"type":"Point"}
}
