{
  "type": "Feature",
  "properties": {
    "iso:country":"GB",
    "wof:name":"DN21 1GD",
    "wof:placetype":"postalcode"
},
  "geometry": {"coordinates":[-0.75021032190138,53.39568585649657],"type":"Point"}
}