{
  "type": "Feature",
  "properties": {
    "date:inception_lower":"2000-06-01",
    "date:inception_upper":"2000-06-30",
    "iso:country":"GB",
    "wof:name":"DN21 1GD",
    "wof:placetype":"postalcode"
},
  "geometry": {"coordinates":[-0.748984,53.395029],"type":"Point"}
}