{
  "type": "Feature",
  "properties": {
    "date:inception_lower":"1980-01-01",
    "date:inception_upper":"1980-01-31",
    "iso:country":"GB",
    "wof:name":"KA12 0RF",
    "wof:placetype":"postalcode"
},
  "geometry": {"coordinates":[-4.661629,55.622789],"type":"Point"}
}