{
  "type": "Feature",
  "properties": {
    "iso:country":"GB",
    "wof:name":"KA12 0RF",
    "wof:placetype":"postalcode"
},
  "geometry": {"coordinates":[-4.66162889632384,55.62278935529815],"type":"Point"}
}