{
  "type": "Feature",
  "properties": {
    "iso:country":"GB",
    "wof:name":"ME10 2DR",
    "wof:placetype":"postalcode"
},
  "geometry": {"coordinates":[0.73108731826362,51.34910130051772],"type":"Point"}
}