{
  "type": "Feature",
  "properties": {
    "iso:country": "GB",
    "wof:name": "DN12 3EB",
    "wof:placetype": "postalcode"
  },
  "geometry": {"coordinates":[-1.224938,53.486282],"type":"Point"}
}
