{
  "type": "Feature",
  "properties": {
    "iso:country":"GB",
    "wof:name":"BD21 5LH",
    "wof:placetype":"postalcode"
},
  "geometry": {"coordinates":[-1.91039260242724,53.8612811654987],"type":"Point"}
}