{
  "type": "Feature",
  "properties": {
    "date:inception_lower": "1980-01-01",
    "date:inception_upper": "1980-01-01",
    "iso:country": "GB",
    "wof:name": "BD21 5LH",
    "wof:placetype": "postalcode"
  },
  "geometry": {"coordinates":[-1.910274,53.861124],"type":"Point"}
}
