{
  "type": "Feature",
  "properties": {
    "iso:country": "GB",
    "wof:name": "NR33 8SN",
    "wof:placetype": "postalcode"
  },
  "geometry": {"coordinates":[1.705418,52.458374],"type":"Point"}
}
