{
  "type": "Feature",
  "properties": {
    "date:inception_lower": "1981-06-01",
    "date:inception_upper": "1981-06-01",
    "iso:country": "GB",
    "wof:name": "NR33 8SN",
    "wof:placetype": "postalcode"
  },
  "geometry": {"coordinates":[1.705418,52.458374],"type":"Point"}
}
