{
  "type": "Feature",
  "properties": {
    "iso:country":"GB",
    "wof:name":"HX7 5EF",
    "wof:placetype":"postalcode"
},
  "geometry": {"coordinates":[-1.9877768278423,53.72788755517352],"type":"Point"}
}