{
  "type": "Feature",
  "properties": {
    "iso:country": "GB",
    "wof:name": "HX7 5EF",
    "wof:placetype": "postalcode"
  },
  "geometry": {"coordinates":[-1.987778,53.727903],"type":"Point"}
}
