{
  "type": "Feature",
  "properties": {
    "iso:country":"GB",
    "wof:name":"PL4 7EG",
    "wof:placetype":"postalcode"
},
  "geometry": {"coordinates":[-4.12592396702933,50.38228242231665],"type":"Point"}
}