{
  "type": "Feature",
  "properties": {
    "iso:country":"GB",
    "wof:name":"NW9 0RG",
    "wof:placetype":"postalcode"
},
  "geometry": {"coordinates":[-0.27324490178205,51.59253072086829],"type":"Point"}
}