{
  "type": "Feature",
  "properties": {
    "date:inception_lower": "1994-05-01",
    "date:inception_upper": "1994-05-01",
    "iso:country": "GB",
    "wof:name": "M31 4FZ",
    "wof:placetype": "postalcode"
  },
  "geometry": {"coordinates":[-2.429533,53.413945],"type":"Point"}
}
