{
  "type": "Feature",
  "properties": {
    "iso:country":"GB",
    "wof:name":"M31 4FZ",
    "wof:placetype":"postalcode"
},
  "geometry": {"coordinates":[-2.42953263329746,53.41394454296908],"type":"Point"}
}