{
  "type": "Feature",
  "properties": {
    "date:inception_lower": "1991-01-01",
    "date:inception_upper": "1991-01-01",
    "iso:country": "GB",
    "wof:name": "RM7 0AZ",
    "wof:placetype": "postalcode"
  },
  "geometry": {"coordinates":[0.184256,51.570225],"type":"Point"}
}
