{
  "type": "Feature",
  "properties": {
    "iso:country": "GB",
    "wof:name": "RM7 0AZ",
    "wof:placetype": "postalcode"
  },
  "geometry": {"coordinates":[0.184256,51.570225],"type":"Point"}
}
