{
  "type": "Feature",
  "properties": {
    "iso:country":"GB",
    "wof:name":"DL5 6PB",
    "wof:placetype":"postalcode"
},
  "geometry": {"coordinates":[-1.56178198954171,54.60142652142446],"type":"Point"}
}