{
  "type": "Feature",
  "properties": {
    "date:inception_lower":"2014-11-01",
    "date:inception_upper":"2014-11-30",
    "iso:country":"GB",
    "wof:name":"DL5 6PB",
    "wof:placetype":"postalcode"
},
  "geometry": {"coordinates":[-1.561782,54.601427],"type":"Point"}
}