{
  "type": "Feature",
  "properties": {
    "iso:country":"GB",
    "wof:name":"N17 6PE",
    "wof:placetype":"postalcode"
},
  "geometry": {"coordinates":[-0.08527604367865,51.58905715284193],"type":"Point"}
}