{
  "type": "Feature",
  "properties": {
    "iso:country":"GB",
    "wof:name":"EX2 8AD",
    "wof:placetype":"postalcode"
},
  "geometry": {"coordinates":[-3.53520056697765,50.69518733432366],"type":"Point"}
}