{
  "type": "Feature",
  "properties": {
    "iso:country":"GB",
    "wof:name":"NN8 2UJ",
    "wof:placetype":"postalcode"
},
  "geometry": {"coordinates":[-0.72052963682376,52.28965439377262],"type":"Point"}
}