{
  "type": "Feature",
  "properties": {
    "iso:country": "GB",
    "wof:name": "NN8 2UJ",
    "wof:placetype": "postalcode"
  },
  "geometry": {"coordinates":[-0.72053,52.289654],"type":"Point"}
}
