{
  "type": "Feature",
  "properties": {
    "date:inception_lower": "1980-01-01",
    "date:inception_upper": "1980-01-01",
    "iso:country": "GB",
    "wof:name": "NN8 2UJ",
    "wof:placetype": "postalcode"
  },
  "geometry": {"coordinates":[-0.72053,52.289654],"type":"Point"}
}
