{
  "type": "Feature",
  "properties": {
    "iso:country": "GB",
    "wof:name": "M38 0LN",
    "wof:placetype": "postalcode"
  },
  "geometry": {"coordinates":[-2.42609,53.523922],"type":"Point"}
}
