{
  "type": "Feature",
  "properties": {
    "iso:country":"GB",
    "wof:name":"TR3 6JD",
    "wof:placetype":"postalcode"
},
  "geometry": {"coordinates":[-5.09190465879514,50.22344950534018],"type":"Point"}
}