{
  "type": "Feature",
  "properties": {
    "iso:country":"GB",
    "wof:name":"NN7 2HN",
    "wof:placetype":"postalcode"
},
  "geometry": {"coordinates":[-0.84576007851287,52.14829636227763],"type":"Point"}
}