{
  "type": "Feature",
  "properties": {
    "iso:country": "GB",
    "wof:name": "CF83 8FB",
    "wof:placetype": "postalcode"
  },
  "geometry": {"coordinates":[-3.19293,51.592636],"type":"Point"}
}
