{
  "type": "Feature",
  "properties": {
    "iso:country":"GB",
    "wof:name":"CF83 8FB",
    "wof:placetype":"postalcode"
},
  "geometry": {"coordinates":[-3.19293052698556,51.59263598807387],"type":"Point"}
}