{
  "type": "Feature",
  "properties": {
    "iso:country": "GB",
    "wof:name": "GU21 5HS",
    "wof:placetype": "postalcode"
  },
  "geometry": {"coordinates":[-0.548193,51.323259],"type":"Point"}
}
