{
  "type": "Feature",
  "properties": {
    "iso:country":"GB",
    "wof:name":"GU21 5HS",
    "wof:placetype":"postalcode"
},
  "geometry": {"coordinates":[-0.54805366712334,51.32329439601614],"type":"Point"}
}