{
  "type": "Feature",
  "properties": {
    "iso:country":"GB",
    "wof:name":"SW16 3DB",
    "wof:placetype":"postalcode"
},
  "geometry": {"coordinates":[-0.121132083541,51.41888629148738],"type":"Point"}
}