{
  "type": "Feature",
  "properties": {
    "iso:country":"GB",
    "wof:name":"LL17 0BE",
    "wof:placetype":"postalcode"
},
  "geometry": {"coordinates":[-3.43074163163986,53.23820235419777],"type":"Point"}
}