{
  "type": "Feature",
  "properties": {
    "iso:country":"GB",
    "wof:name":"RH1 4QL",
    "wof:placetype":"postalcode"
},
  "geometry": {"coordinates":[-0.12097260286526,51.25178899178845],"type":"Point"}
}