{
  "type": "Feature",
  "properties": {
    "iso:country": "GB",
    "wof:name": "BD4 8TG",
    "wof:placetype": "postalcode"
  },
  "geometry": {"coordinates":[-1.722381,53.78625],"type":"Point"}
}
