{
  "type": "Feature",
  "properties": {
    "iso:country":"GB",
    "wof:name":"BD4 8TG",
    "wof:placetype":"postalcode"
},
  "geometry": {"coordinates":[-1.72238064316121,53.78625016678339],"type":"Point"}
}