{
  "type": "Feature",
  "properties": {
    "date:inception_lower": "1980-01-01",
    "date:inception_upper": "1980-01-01",
    "iso:country": "GB",
    "wof:name": "SY10 9PN",
    "wof:placetype": "postalcode"
  },
  "geometry": {"coordinates":[-3.061113,52.850714],"type":"Point"}
}
