{
  "type": "Feature",
  "properties": {
    "iso:country":"GB",
    "wof:name":"SY10 9PN",
    "wof:placetype":"postalcode"
},
  "geometry": {"coordinates":[-3.06123004098899,52.85058119379698],"type":"Point"}
}