{
  "type": "Feature",
  "properties": {
    "date:inception_lower": "1980-01-01",
    "date:inception_upper": "1980-01-01",
    "iso:country": "GB",
    "wof:name": "KW16 3NP",
    "wof:placetype": "postalcode"
  },
  "geometry": {"coordinates":[-3.10441,58.825871],"type":"Point"}
}
