{
  "type": "Feature",
  "properties": {
    "iso:country": "GB",
    "wof:name": "KW16 3NP",
    "wof:placetype": "postalcode"
  },
  "geometry": {"coordinates":[-3.103317,58.826357],"type":"Point"}
}
