{
  "type": "Feature",
  "properties": {
    "iso:country":"GB",
    "wof:name":"KW16 3NP",
    "wof:placetype":"postalcode"
},
  "geometry": {"coordinates":[-3.10416282248358,58.82591032321331],"type":"Point"}
}