{
  "type": "Feature",
  "properties": {
    "iso:country": "GB",
    "wof:name": "SK13 0JA",
    "wof:placetype": "postalcode"
  },
  "geometry": {"coordinates":[-1.987584,53.449251],"type":"Point"}
}
