{
  "type": "Feature",
  "properties": {
    "iso:country":"GB",
    "wof:name":"SK13 0JA",
    "wof:placetype":"postalcode"
},
  "geometry": {"coordinates":[-1.9875842135319,53.44925111969567],"type":"Point"}
}