{
  "type": "Feature",
  "properties": {
    "date:inception_lower": "1980-01-01",
    "date:inception_upper": "1980-01-01",
    "iso:country": "GB",
    "wof:name": "SE3 7BD",
    "wof:placetype": "postalcode"
  },
  "geometry": {"coordinates":[0.018096,51.473523],"type":"Point"}
}
