{
  "type": "Feature",
  "properties": {
    "iso:country":"GB",
    "wof:name":"GU17 0ER",
    "wof:placetype":"postalcode"
},
  "geometry": {"coordinates":[-0.79628292984468,51.33902098862863],"type":"Point"}
}