{
  "type": "Feature",
  "properties": {
    "iso:country": "GB",
    "wof:name": "GU17 0ER",
    "wof:placetype": "postalcode"
  },
  "geometry": {"coordinates":[-0.796283,51.339021],"type":"Point"}
}
