{
  "type": "Feature",
  "properties": {
    "iso:country": "GB",
    "wof:name": "B70 0RF",
    "wof:placetype": "postalcode"
  },
  "geometry": {"coordinates":[-2.01473,52.539717],"type":"Point"}
}
