{
  "type": "Feature",
  "properties": {
    "iso:country":"GB",
    "wof:name":"B70 0RF",
    "wof:placetype":"postalcode"
},
  "geometry": {"coordinates":[-2.01473006987876,52.53971724729362],"type":"Point"}
}