{
  "type": "Feature",
  "properties": {
    "date:inception_lower": "1980-01-01",
    "date:inception_upper": "1980-01-01",
    "iso:country": "GB",
    "wof:name": "TN29 0DW",
    "wof:placetype": "postalcode"
  },
  "geometry": {"coordinates":[0.928887,51.042584],"type":"Point"}
}
