{
  "type": "Feature",
  "properties": {
    "iso:country":"GB",
    "wof:name":"TN29 0DW",
    "wof:placetype":"postalcode"
},
  "geometry": {"coordinates":[0.92885210379413,51.0425837840683],"type":"Point"}
}