{
  "type": "Feature",
  "properties": {
    "iso:country": "GB",
    "wof:name": "TN29 0DW",
    "wof:placetype": "postalcode"
  },
  "geometry": {"coordinates":[0.928887,51.042584],"type":"Point"}
}
