{
  "type": "Feature",
  "properties": {
    "date:inception_lower": "1987-04-01",
    "date:inception_upper": "1987-04-01",
    "iso:country": "GB",
    "wof:name": "NR9 3LY",
    "wof:placetype": "postalcode"
  },
  "geometry": {"coordinates":[1.171562,52.597596],"type":"Point"}
}
