{
  "type": "Feature",
  "properties": {
    "date:inception_lower": "2023-06-01",
    "date:inception_upper": "2023-06-01",
    "iso:country": "GB",
    "wof:name": "WA1 1AU",
    "wof:placetype": "postalcode"
  },
  "geometry": {"coordinates":[-2.603218,53.375232],"type":"Point"}
}
