{
  "type": "Feature",
  "properties": {
    "iso:country": "GB",
    "wof:name": "LA1 1NQ",
    "wof:placetype": "postalcode"
  },
  "geometry": {"coordinates":[-2.797835,54.048712],"type":"Point"}
}
