{
  "type": "Feature",
  "properties": {
    "iso:country":"GB",
    "wof:name":"NN13 5GW",
    "wof:placetype":"postalcode"
},
  "geometry": {"coordinates":[-1.09786204778006,52.0161614305806],"type":"Point"}
}