{
  "type": "Feature",
  "properties": {
    "iso:country": "GB",
    "wof:name": "NN13 5GW",
    "wof:placetype": "postalcode"
  },
  "geometry": {"coordinates":[-1.097862,52.016161],"type":"Point"}
}
