{
  "type": "Feature",
  "properties": {
    "date:inception_lower": "2008-01-01",
    "date:inception_upper": "2008-01-01",
    "iso:country": "GB",
    "wof:name": "NN13 5GW",
    "wof:placetype": "postalcode"
  },
  "geometry": {"coordinates":[-1.097862,52.016161],"type":"Point"}
}
