{
  "type": "Feature",
  "properties": {
    "iso:country":"GB",
    "wof:name":"LL13 9SY",
    "wof:placetype":"postalcode"
},
  "geometry": {"coordinates":[-2.90982718060418,53.08335445876472],"type":"Point"}
}