{
  "type": "Feature",
  "properties": {
    "iso:country":"GB",
    "wof:name":"SA1 4NG",
    "wof:placetype":"postalcode"
},
  "geometry": {"coordinates":[-3.96105109974155,51.61578238811935],"type":"Point"}
}