{
  "type": "Feature",
  "properties": {
    "iso:country":"GB",
    "wof:name":"CF82 7JS",
    "wof:placetype":"postalcode"
},
  "geometry": {"coordinates":[-3.23227817434979,51.64894936179166],"type":"Point"}
}