{
  "type": "Feature",
  "properties": {
    "date:inception_lower":"1995-07-01",
    "date:inception_upper":"1995-07-31",
    "iso:country":"GB",
    "wof:name":"CF82 7JS",
    "wof:placetype":"postalcode"
},
  "geometry": {"coordinates":[-3.232278,51.648949],"type":"Point"}
}