{
  "type": "Feature",
  "properties": {
    "iso:country":"GB",
    "wof:name":"TR12 6NU",
    "wof:placetype":"postalcode"
},
  "geometry": {"coordinates":[-5.08783823897057,50.03899765991638],"type":"Point"}
}