{
  "type": "Feature",
  "properties": {
    "iso:country": "GB",
    "wof:name": "TR12 6NU",
    "wof:placetype": "postalcode"
  },
  "geometry": {"coordinates":[-5.087838,50.038998],"type":"Point"}
}
