{
  "type": "Feature",
  "properties": {
    "iso:country":"GB",
    "wof:name":"PL6 7FB",
    "wof:placetype":"postalcode"
},
  "geometry": {"coordinates":[-4.11248252333639,50.4317802247605],"type":"Point"}
}