{
  "type": "Feature",
  "properties": {
    "date:inception_lower":"2016-04-01",
    "date:inception_upper":"2016-04-30",
    "iso:country":"GB",
    "wof:name":"PL6 7FB",
    "wof:placetype":"postalcode"
},
  "geometry": {"coordinates":[-4.098132,50.422515],"type":"Point"}
}