{
  "type": "Feature",
  "properties": {
    "iso:country":"GB",
    "wof:name":"SM6 9PF",
    "wof:placetype":"postalcode"
},
  "geometry": {"coordinates":[-0.14438847717041,51.34426682755903],"type":"Point"}
}