{
  "type": "Feature",
  "properties": {
    "iso:country": "GB",
    "wof:name": "NR21 0HA",
    "wof:placetype": "postalcode"
  },
  "geometry": {"coordinates":[0.87195,52.845265],"type":"Point"}
}
