{
  "type": "Feature",
  "properties": {
    "date:inception_lower": "1980-01-01",
    "date:inception_upper": "1980-01-01",
    "iso:country": "GB",
    "wof:name": "NR21 0HA",
    "wof:placetype": "postalcode"
  },
  "geometry": {"coordinates":[0.87194,52.845337],"type":"Point"}
}
