{
  "type": "Feature",
  "properties": {
    "iso:country":"GB",
    "wof:name":"NR21 0HA",
    "wof:placetype":"postalcode"
},
  "geometry": {"coordinates":[0.87192190004001,52.84529418913535],"type":"Point"}
}