{
  "type": "Feature",
  "properties": {
    "date:inception_lower": "1993-06-01",
    "date:inception_upper": "1993-06-01",
    "iso:country": "GB",
    "wof:name": "AB51 3UA",
    "wof:placetype": "postalcode"
  },
  "geometry": {"coordinates":[-2.369524,57.277011],"type":"Point"}
}
