{
  "type": "Feature",
  "properties": {
    "iso:country": "GB",
    "wof:name": "AB51 3UA",
    "wof:placetype": "postalcode"
  },
  "geometry": {"coordinates":[-2.368872,57.277],"type":"Point"}
}
