{
  "type": "Feature",
  "properties": {
    "iso:country":"GB",
    "wof:name":"AB51 3UA",
    "wof:placetype":"postalcode"
},
  "geometry": {"coordinates":[-2.36867206828492,57.27693806755752],"type":"Point"}
}