{
  "type": "Feature",
  "properties": {
    "iso:country":"GB",
    "wof:name":"NP7 8HG",
    "wof:placetype":"postalcode"
},
  "geometry": {"coordinates":[-2.91437623640655,51.91619073893614],"type":"Point"}
}