{
  "type": "Feature",
  "properties": {
    "iso:country": "GB",
    "wof:name": "NP7 8HG",
    "wof:placetype": "postalcode"
  },
  "geometry": {"coordinates":[-2.914376,51.916191],"type":"Point"}
}
