{
  "type": "Feature",
  "properties": {
    "iso:country":"GB",
    "wof:name":"S71 2RF",
    "wof:placetype":"postalcode"
},
  "geometry": {"coordinates":[-1.44645611685584,53.57096945079658],"type":"Point"}
}