{
  "type": "Feature",
  "properties": {
    "date:inception_lower": "1980-01-01",
    "date:inception_upper": "1980-01-01",
    "iso:country": "GB",
    "wof:name": "S71 2RF",
    "wof:placetype": "postalcode"
  },
  "geometry": {"coordinates":[-1.446456,53.570969],"type":"Point"}
}
