{
  "type": "Feature",
  "properties": {
    "iso:country": "GB",
    "wof:name": "S71 2RF",
    "wof:placetype": "postalcode"
  },
  "geometry": {"coordinates":[-1.446456,53.570969],"type":"Point"}
}
