{
  "type": "Feature",
  "properties": {
    "iso:country":"GB",
    "wof:name":"E14 6NJ",
    "wof:placetype":"postalcode"
},
  "geometry": {"coordinates":[-0.01563159664603,51.51822553787166],"type":"Point"}
}