{
  "type": "Feature",
  "properties": {
    "date:inception_lower": "1980-01-01",
    "date:inception_upper": "1980-01-01",
    "iso:country": "GB",
    "wof:name": "G76 7XX",
    "wof:placetype": "postalcode"
  },
  "geometry": {"coordinates":[-4.28811,55.782968],"type":"Point"}
}
