{
  "type": "Feature",
  "properties": {
    "iso:country":"GB",
    "wof:name":"G76 7XX",
    "wof:placetype":"postalcode"
},
  "geometry": {"coordinates":[-4.28811047865528,55.78296787116606],"type":"Point"}
}