{
  "type": "Feature",
  "properties": {
    "date:inception_lower": "1990-02-01",
    "date:inception_upper": "1990-02-01",
    "iso:country": "GB",
    "wof:name": "WF3 1TW",
    "wof:placetype": "postalcode"
  },
  "geometry": {"coordinates":[-1.570086,53.728475],"type":"Point"}
}
