{
  "type": "Feature",
  "properties": {
    "iso:country":"GB",
    "wof:name":"WF3 1TW",
    "wof:placetype":"postalcode"
},
  "geometry": {"coordinates":[-1.57008645879585,53.72847516474596],"type":"Point"}
}