{
  "type": "Feature",
  "properties": {
    "iso:country":"GB",
    "wof:name":"BB18 6PN",
    "wof:placetype":"postalcode"
},
  "geometry": {"coordinates":[-2.14161727348066,53.9172786412041],"type":"Point"}
}