{
  "type": "Feature",
  "properties": {
    "iso:country":"GB",
    "wof:name":"PE36 5ND",
    "wof:placetype":"postalcode"
},
  "geometry": {"coordinates":[0.53892983970729,52.90000290314358],"type":"Point"}
}