{
  "type": "Feature",
  "properties": {
    "date:inception_lower":"1980-01-01",
    "date:inception_upper":"1980-01-31",
    "iso:country":"GB",
    "wof:name":"PE36 5ND",
    "wof:placetype":"postalcode"
},
  "geometry": {"coordinates":[0.53893,52.900003],"type":"Point"}
}