{
  "type": "Feature",
  "properties": {
    "date:inception_lower": "1980-01-01",
    "date:inception_upper": "1980-01-01",
    "iso:country": "GB",
    "wof:name": "SG11 1HE",
    "wof:placetype": "postalcode"
  },
  "geometry": {"coordinates":[-0.020444,51.887292],"type":"Point"}
}
