{
  "type": "Feature",
  "properties": {
    "iso:country":"GB",
    "wof:name":"WD24 4AU",
    "wof:placetype":"postalcode"
},
  "geometry": {"coordinates":[-0.39646760764803,51.67107103241909],"type":"Point"}
}