{
  "type": "Feature",
  "properties": {
    "date:inception_lower": "1980-01-01",
    "date:inception_upper": "1980-01-01",
    "iso:country": "GB",
    "wof:name": "SY2 5HF",
    "wof:placetype": "postalcode"
  },
  "geometry": {"coordinates":[-2.736355,52.708834],"type":"Point"}
}
