{
  "type": "Feature",
  "properties": {
    "iso:country":"GB",
    "wof:name":"SY2 5HF",
    "wof:placetype":"postalcode"
},
  "geometry": {"coordinates":[-2.73634211043311,52.70881055304549],"type":"Point"}
}