{
  "type": "Feature",
  "properties": {
    "iso:country":"GB",
    "wof:name":"KY15 5EQ",
    "wof:placetype":"postalcode"
},
  "geometry": {"coordinates":[-3.01410699209633,56.31757998611851],"type":"Point"}
}