{
  "type": "Feature",
  "properties": {
    "iso:country": "GB",
    "wof:name": "SY20 8SG",
    "wof:placetype": "postalcode"
  },
  "geometry": {"coordinates":[-3.745713,52.564692],"type":"Point"}
}
