{
  "type": "Feature",
  "properties": {
    "iso:country":"GB",
    "wof:name":"E18 1QG",
    "wof:placetype":"postalcode"
},
  "geometry": {"coordinates":[0.0301895831023,51.58559669392348],"type":"Point"}
}