{
  "type": "Feature",
  "properties": {
    "date:inception_lower": "2015-10-01",
    "date:inception_upper": "2015-10-01",
    "iso:country": "GB",
    "wof:name": "NN5 6WQ",
    "wof:placetype": "postalcode"
  },
  "geometry": {"coordinates":[-0.954498,52.264203],"type":"Point"}
}
