{
  "type": "Feature",
  "properties": {
    "iso:country": "GB",
    "wof:name": "NN5 6WQ",
    "wof:placetype": "postalcode"
  },
  "geometry": {"coordinates":[-0.954498,52.264203],"type":"Point"}
}
