{
  "type": "Feature",
  "properties": {
    "iso:country":"GB",
    "wof:name":"NN5 6WQ",
    "wof:placetype":"postalcode"
},
  "geometry": {"coordinates":[-0.95449839772965,52.26420292642948],"type":"Point"}
}