{
  "type": "Feature",
  "properties": {
    "date:inception_lower": "1992-08-01",
    "date:inception_upper": "1992-08-01",
    "iso:country": "GB",
    "wof:name": "TS10 2NP",
    "wof:placetype": "postalcode"
  },
  "geometry": {"coordinates":[-1.05703,54.597874],"type":"Point"}
}
