{
  "type": "Feature",
  "properties": {
    "iso:country":"GB",
    "wof:name":"TS10 2NP",
    "wof:placetype":"postalcode"
},
  "geometry": {"coordinates":[-1.05702964936733,54.59787420509188],"type":"Point"}
}