{
  "type": "Feature",
  "properties": {
    "iso:country": "GB",
    "wof:name": "SA31 3RA",
    "wof:placetype": "postalcode"
  },
  "geometry": {"coordinates":[-4.331068,51.847721],"type":"Point"}
}
