{
  "type": "Feature",
  "properties": {
    "iso:country":"GB",
    "wof:name":"SA31 3RA",
    "wof:placetype":"postalcode"
},
  "geometry": {"coordinates":[-4.33106788565052,51.84772094686674],"type":"Point"}
}