{
  "type": "Feature",
  "properties": {
    "iso:country":"GB",
    "wof:name":"CB25 9NB",
    "wof:placetype":"postalcode"
},
  "geometry": {"coordinates":[0.19529182798006,52.26519110698959],"type":"Point"}
}