{
  "type": "Feature",
  "properties": {
    "date:inception_lower": "2006-09-01",
    "date:inception_upper": "2006-09-01",
    "iso:country": "GB",
    "wof:name": "CB25 9NB",
    "wof:placetype": "postalcode"
  },
  "geometry": {"coordinates":[0.195292,52.265191],"type":"Point"}
}
