{
  "type": "Feature",
  "properties": {
    "iso:country":"GB",
    "wof:name":"N2 9QG",
    "wof:placetype":"postalcode"
},
  "geometry": {"coordinates":[-0.16167699178623,51.58821050183028],"type":"Point"}
}