{
  "type": "Feature",
  "properties": {
    "iso:country": "GB",
    "wof:name": "WV15 5LX",
    "wof:placetype": "postalcode"
  },
  "geometry": {"coordinates":[-2.381294,52.574946],"type":"Point"}
}
