{
  "type": "Feature",
  "properties": {
    "iso:country": "GB",
    "wof:name": "DY14 0BE",
    "wof:placetype": "postalcode"
  },
  "geometry": {"coordinates":[-2.543108,52.352821],"type":"Point"}
}
