{
  "type": "Feature",
  "properties": {
    "date:inception_lower": "1981-06-01",
    "date:inception_upper": "1981-06-01",
    "iso:country": "GB",
    "wof:name": "DY14 0BE",
    "wof:placetype": "postalcode"
  },
  "geometry": {"coordinates":[-2.543108,52.352821],"type":"Point"}
}
