{
  "type": "Feature",
  "properties": {
    "iso:country":"GB",
    "wof:name":"DY14 0BE",
    "wof:placetype":"postalcode"
},
  "geometry": {"coordinates":[-2.54311070315065,52.35280730633094],"type":"Point"}
}