{
  "type": "Feature",
  "properties": {
    "iso:country": "GB",
    "wof:name": "HU5 4ES",
    "wof:placetype": "postalcode"
  },
  "geometry": {"coordinates":[-0.376843,53.760665],"type":"Point"}
}
