{
  "type": "Feature",
  "properties": {
    "date:inception_lower": "2010-06-01",
    "date:inception_upper": "2010-06-01",
    "iso:country": "GB",
    "wof:name": "B1 2NR",
    "wof:placetype": "postalcode"
  },
  "geometry": {"coordinates":[-1.90855,52.479621],"type":"Point"}
}
