{
  "type": "Feature",
  "properties": {
    "iso:country":"GB",
    "wof:name":"HA3 6DH",
    "wof:placetype":"postalcode"
},
  "geometry": {"coordinates":[-0.33657850978538,51.61231093589989],"type":"Point"}
}