{
  "type": "Feature",
  "properties": {
    "iso:country":"GB",
    "wof:name":"TS25 4LE",
    "wof:placetype":"postalcode"
},
  "geometry": {"coordinates":[-1.2374075964915,54.67279261539143],"type":"Point"}
}