{
  "type": "Feature",
  "properties": {
    "iso:country":"GB",
    "wof:name":"CF32 8NA",
    "wof:placetype":"postalcode"
},
  "geometry": {"coordinates":[-3.58478900273312,51.61534288263159],"type":"Point"}
}