{
  "type": "Feature",
  "properties": {
    "date:inception_lower":"1980-01-01",
    "date:inception_upper":"1980-01-31",
    "iso:country":"GB",
    "wof:name":"DL8 2LN",
    "wof:placetype":"postalcode"
},
  "geometry": {"coordinates":[-1.534899,54.246312],"type":"Point"}
}