{
  "type": "Feature",
  "properties": {
    "date:inception_lower": "1980-01-01",
    "date:inception_upper": "1980-01-01",
    "iso:country": "GB",
    "wof:name": "DL8 2LN",
    "wof:placetype": "postalcode"
  },
  "geometry": {"coordinates":[-1.53677,54.246382],"type":"Point"}
}
