{
  "type": "Feature",
  "properties": {
    "iso:country":"GB",
    "wof:name":"DL8 2LN",
    "wof:placetype":"postalcode"
},
  "geometry": {"coordinates":[-1.53486195521669,54.24611962293876],"type":"Point"}
}