{
  "type": "Feature",
  "properties": {
    "iso:country": "GB",
    "wof:name": "DL8 2LN",
    "wof:placetype": "postalcode"
  },
  "geometry": {"coordinates":[-1.534899,54.246312],"type":"Point"}
}
