{
  "type": "Feature",
  "properties": {
    "iso:country":"GB",
    "wof:name":"TN24 0EL",
    "wof:placetype":"postalcode"
},
  "geometry": {"coordinates":[0.89543774851117,51.13858792992513],"type":"Point"}
}