{
  "type": "Feature",
  "properties": {
    "date:inception_lower":"1980-01-01",
    "date:inception_upper":"1980-01-31",
    "iso:country":"GB",
    "wof:name":"TN24 0EL",
    "wof:placetype":"postalcode"
},
  "geometry": {"coordinates":[0.895438,51.138588],"type":"Point"}
}