{
  "type": "Feature",
  "properties": {
    "iso:country": "GB",
    "wof:name": "HU5 2BP",
    "wof:placetype": "postalcode"
  },
  "geometry": {"coordinates":[-0.367638,53.762536],"type":"Point"}
}
