{
  "type": "Feature",
  "properties": {
    "iso:country":"GB",
    "wof:name":"CH4 0DU",
    "wof:placetype":"postalcode"
},
  "geometry": {"coordinates":[-2.9647952017368,53.17126851912782],"type":"Point"}
}