{
  "type": "Feature",
  "properties": {
    "iso:country": "GB",
    "wof:name": "CA22 2JR",
    "wof:placetype": "postalcode"
  },
  "geometry": {"coordinates":[-3.530772,54.479496],"type":"Point"}
}
