{
  "type": "Feature",
  "properties": {
    "iso:country": "GB",
    "wof:name": "LE11 2WE",
    "wof:placetype": "postalcode"
  },
  "geometry": {"coordinates":[-1.201598,52.77502],"type":"Point"}
}
