{
  "type": "Feature",
  "properties": {
    "iso:country":"GB",
    "wof:name":"HP10 8NU",
    "wof:placetype":"postalcode"
},
  "geometry": {"coordinates":[-0.68309758912608,51.63201318918373],"type":"Point"}
}