{
  "type": "Feature",
  "properties": {
    "date:inception_lower":"2015-06-01",
    "date:inception_upper":"2015-06-30",
    "iso:country":"GB",
    "wof:name":"MK18 1HW",
    "wof:placetype":"postalcode"
},
  "geometry": {"coordinates":[-0.978703,52.0111],"type":"Point"}
}