{
  "type": "Feature",
  "properties": {
    "iso:country":"GB",
    "wof:name":"MK18 1HW",
    "wof:placetype":"postalcode"
},
  "geometry": {"coordinates":[-0.97918608360357,52.0111651340901],"type":"Point"}
}