{
  "type": "Feature",
  "properties": {
    "date:inception_lower":"1980-01-01",
    "date:inception_upper":"1980-01-31",
    "iso:country":"GB",
    "wof:name":"DD5 2NZ",
    "wof:placetype":"postalcode"
},
  "geometry": {"coordinates":[-2.85394,56.475333],"type":"Point"}
}