{
  "type": "Feature",
  "properties": {
    "date:inception_lower":"1980-01-01",
    "date:inception_upper":"1980-01-31",
    "iso:country":"GB",
    "wof:name":"SN15 5LD",
    "wof:placetype":"postalcode"
},
  "geometry": {"coordinates":[-2.103723,51.501988],"type":"Point"}
}