{
  "type": "Feature",
  "properties": {
    "iso:country": "GB",
    "wof:name": "SN15 5LD",
    "wof:placetype": "postalcode"
  },
  "geometry": {"coordinates":[-2.103723,51.501988],"type":"Point"}
}
