{
  "type": "Feature",
  "properties": {
    "iso:country":"GB",
    "wof:name":"SN15 5LD",
    "wof:placetype":"postalcode"
},
  "geometry": {"coordinates":[-2.10372351131866,51.50198784244785],"type":"Point"}
}