{
  "type": "Feature",
  "properties": {
    "iso:country":"GB",
    "wof:name":"CA7 4QN",
    "wof:placetype":"postalcode"
},
  "geometry": {"coordinates":[-3.38105220041122,54.87729753408798],"type":"Point"}
}