{
  "type": "Feature",
  "properties": {
    "iso:country": "GB",
    "wof:name": "CA7 4QN",
    "wof:placetype": "postalcode"
  },
  "geometry": {"coordinates":[-3.381052,54.877298],"type":"Point"}
}
