{
  "type": "Feature",
  "properties": {
    "date:inception_lower": "1980-01-01",
    "date:inception_upper": "1980-01-01",
    "iso:country": "GB",
    "wof:name": "PO12 4EU",
    "wof:placetype": "postalcode"
  },
  "geometry": {"coordinates":[-1.148172,50.813017],"type":"Point"}
}
