{
  "type": "Feature",
  "properties": {
    "iso:country": "GB",
    "wof:name": "PO12 4EU",
    "wof:placetype": "postalcode"
  },
  "geometry": {"coordinates":[-1.148172,50.813017],"type":"Point"}
}
