{
  "type": "Feature",
  "properties": {
    "iso:country":"GB",
    "wof:name":"CO6 4HZ",
    "wof:placetype":"postalcode"
},
  "geometry": {"coordinates":[0.8681071852944,51.97286408252777],"type":"Point"}
}