{
  "type": "Feature",
  "properties": {
    "iso:country":"GB",
    "wof:name":"LE18 3SU",
    "wof:placetype":"postalcode"
},
  "geometry": {"coordinates":[-1.10007015570337,52.57442660344098],"type":"Point"}
}