{
  "type": "Feature",
  "properties": {
    "iso:country":"GB",
    "wof:name":"CO9 1SE",
    "wof:placetype":"postalcode"
},
  "geometry": {"coordinates":[0.58087473170048,51.93871204447811],"type":"Point"}
}