{
  "type": "Feature",
  "properties": {
    "date:inception_lower":"1992-08-01",
    "date:inception_upper":"1992-08-31",
    "iso:country":"GB",
    "wof:name":"HP27 0AN",
    "wof:placetype":"postalcode"
},
  "geometry": {"coordinates":[-0.832591,51.724554],"type":"Point"}
}