{
  "type": "Feature",
  "properties": {
    "iso:country":"GB",
    "wof:name":"HP27 0AN",
    "wof:placetype":"postalcode"
},
  "geometry": {"coordinates":[-0.83259115353509,51.72455362832525],"type":"Point"}
}