{
  "type": "Feature",
  "properties": {
    "iso:country":"GB",
    "wof:name":"TN1 2AB",
    "wof:placetype":"postalcode"
},
  "geometry": {"coordinates":[0.26380092076852,51.13499760601154],"type":"Point"}
}