{
  "type": "Feature",
  "properties": {
    "iso:country": "GB",
    "wof:name": "TN1 2AB",
    "wof:placetype": "postalcode"
  },
  "geometry": {"coordinates":[0.263801,51.134998],"type":"Point"}
}
