{
  "type": "Feature",
  "properties": {
    "date:inception_lower": "1980-01-01",
    "date:inception_upper": "1980-01-01",
    "iso:country": "GB",
    "wof:name": "TN1 2AB",
    "wof:placetype": "postalcode"
  },
  "geometry": {"coordinates":[0.263801,51.134998],"type":"Point"}
}
