{
  "type": "Feature",
  "properties": {
    "iso:country":"GB",
    "wof:name":"SA5 8JY",
    "wof:placetype":"postalcode"
},
  "geometry": {"coordinates":[-3.9648022816292,51.6354041775646],"type":"Point"}
}