{
  "type": "Feature",
  "properties": {
    "iso:country":"GB",
    "wof:name":"BA3 5NH",
    "wof:placetype":"postalcode"
},
  "geometry": {"coordinates":[-2.45027976952887,51.24292640871921],"type":"Point"}
}