{
  "type": "Feature",
  "properties": {
    "iso:country":"GB",
    "wof:name":"YO32 4TP",
    "wof:placetype":"postalcode"
},
  "geometry": {"coordinates":[-1.07653226797515,53.98657231451032],"type":"Point"}
}