{
  "type": "Feature",
  "properties": {
    "iso:country": "GB",
    "wof:name": "YO32 4TP",
    "wof:placetype": "postalcode"
  },
  "geometry": {"coordinates":[-1.076532,53.986572],"type":"Point"}
}
