{
  "type": "Feature",
  "properties": {
    "date:inception_lower":"2011-05-01",
    "date:inception_upper":"2011-05-31",
    "iso:country":"GB",
    "wof:name":"YO32 4TP",
    "wof:placetype":"postalcode"
},
  "geometry": {"coordinates":[-1.076532,53.986572],"type":"Point"}
}