{
  "type": "Feature",
  "properties": {
    "iso:country":"GB",
    "wof:name":"BD4 9DB",
    "wof:placetype":"postalcode"
},
  "geometry": {"coordinates":[-1.71370198279629,53.77466220446866],"type":"Point"}
}