{
  "type": "Feature",
  "properties": {
    "iso:country": "GB",
    "wof:name": "BD4 9DB",
    "wof:placetype": "postalcode"
  },
  "geometry": {"coordinates":[-1.713702,53.774662],"type":"Point"}
}
