{
  "type": "Feature",
  "properties": {
    "iso:country":"GB",
    "wof:name":"CV9 3SS",
    "wof:placetype":"postalcode"
},
  "geometry": {"coordinates":[-1.56636021765116,52.65807633063037],"type":"Point"}
}