{
  "type": "Feature",
  "properties": {
    "iso:country": "GB",
    "wof:name": "CV9 3SS",
    "wof:placetype": "postalcode"
  },
  "geometry": {"coordinates":[-1.56636,52.658076],"type":"Point"}
}
