{
  "type": "Feature",
  "properties": {
    "date:inception_lower": "1980-01-01",
    "date:inception_upper": "1980-01-01",
    "iso:country": "GB",
    "wof:name": "GU28 0AP",
    "wof:placetype": "postalcode"
  },
  "geometry": {"coordinates":[-0.610038,50.985633],"type":"Point"}
}
