{
  "type": "Feature",
  "properties": {
    "iso:country":"GB",
    "wof:name":"GU28 0AP",
    "wof:placetype":"postalcode"
},
  "geometry": {"coordinates":[-0.61004653583385,50.98558452596902],"type":"Point"}
}