{
  "type": "Feature",
  "properties": {
    "iso:country": "GB",
    "wof:name": "GU28 0AP",
    "wof:placetype": "postalcode"
  },
  "geometry": {"coordinates":[-0.610038,50.985633],"type":"Point"}
}
