{
  "type": "Feature",
  "properties": {
    "iso:country":"GB",
    "wof:name":"LU2 9LF",
    "wof:placetype":"postalcode"
},
  "geometry": {"coordinates":[-0.38358126444678,51.87637676561497],"type":"Point"}
}