{
  "type": "Feature",
  "properties": {
    "date:inception_lower": "2001-06-01",
    "date:inception_upper": "2001-06-01",
    "iso:country": "GB",
    "wof:name": "LU2 9LF",
    "wof:placetype": "postalcode"
  },
  "geometry": {"coordinates":[-0.384755,51.875772],"type":"Point"}
}
