{
  "type": "Feature",
  "properties": {
    "iso:country": "GB",
    "wof:name": "NP10 9PT",
    "wof:placetype": "postalcode"
  },
  "geometry": {"coordinates":[-3.058419,51.584424],"type":"Point"}
}
