{
  "type": "Feature",
  "properties": {
    "iso:country": "GB",
    "wof:name": "SW6 2DN",
    "wof:placetype": "postalcode"
  },
  "geometry": {"coordinates":[-0.183511,51.474661],"type":"Point"}
}
