{
  "type": "Feature",
  "properties": {
    "iso:country":"GB",
    "wof:name":"SW6 2DN",
    "wof:placetype":"postalcode"
},
  "geometry": {"coordinates":[-0.18351091341831,51.47466131228054],"type":"Point"}
}