{
  "type": "Feature",
  "properties": {
    "date:inception_lower":"1980-01-01",
    "date:inception_upper":"1980-01-31",
    "iso:country":"GB",
    "wof:name":"TW9 4HH",
    "wof:placetype":"postalcode"
},
  "geometry": {"coordinates":[-0.284235,51.474722],"type":"Point"}
}