{
  "type": "Feature",
  "properties": {
    "iso:country": "GB",
    "wof:name": "BN20 7NT",
    "wof:placetype": "postalcode"
  },
  "geometry": {"coordinates":[0.270075,50.756571],"type":"Point"}
}
