{
  "type": "Feature",
  "properties": {
    "date:inception_lower":"1980-01-01",
    "date:inception_upper":"1980-01-31",
    "iso:country":"GB",
    "wof:name":"B18 6BL",
    "wof:placetype":"postalcode"
},
  "geometry": {"coordinates":[-1.91225,52.489375],"type":"Point"}
}