{
  "type": "Feature",
  "properties": {
    "iso:country": "GB",
    "wof:name": "B18 6BL",
    "wof:placetype": "postalcode"
  },
  "geometry": {"coordinates":[-1.91225,52.489375],"type":"Point"}
}
