{
  "type": "Feature",
  "properties": {
    "iso:country":"GB",
    "wof:name":"B18 6BL",
    "wof:placetype":"postalcode"
},
  "geometry": {"coordinates":[-1.91219657986685,52.48943224724632],"type":"Point"}
}