{
  "type": "Feature",
  "properties": {
    "iso:country": "GB",
    "wof:name": "G61 3JQ",
    "wof:placetype": "postalcode"
  },
  "geometry": {"coordinates":[-4.338773,55.930391],"type":"Point"}
}
