{
  "type": "Feature",
  "properties": {
    "iso:country":"GB",
    "wof:name":"E16 1LN",
    "wof:placetype":"postalcode"
},
  "geometry": {"coordinates":[0.01683421758698,51.51248296690412],"type":"Point"}
}