{
  "type": "Feature",
  "properties": {
    "date:inception_lower": "2007-11-01",
    "date:inception_upper": "2007-11-01",
    "iso:country": "GB",
    "wof:name": "OX44 7AG",
    "wof:placetype": "postalcode"
  },
  "geometry": {"coordinates":[-1.128477,51.683871],"type":"Point"}
}
