{
  "type": "Feature",
  "properties": {
    "iso:country":"GB",
    "wof:name":"OX44 7AG",
    "wof:placetype":"postalcode"
},
  "geometry": {"coordinates":[-1.1284769537576,51.68387140778817],"type":"Point"}
}