{
  "type": "Feature",
  "properties": {
    "iso:country": "GB",
    "wof:name": "DY9 0QH",
    "wof:placetype": "postalcode"
  },
  "geometry": {"coordinates":[-2.129907,52.423622],"type":"Point"}
}
