{
  "type": "Feature",
  "properties": {
    "iso:country":"GB",
    "wof:name":"DY9 0QH",
    "wof:placetype":"postalcode"
},
  "geometry": {"coordinates":[-2.12990677905983,52.42362219029416],"type":"Point"}
}