{
  "type": "Feature",
  "properties": {
    "iso:country": "GB",
    "wof:name": "BL3 2EJ",
    "wof:placetype": "postalcode"
  },
  "geometry": {"coordinates":[-2.426659,53.558076],"type":"Point"}
}
