{
  "type": "Feature",
  "properties": {
    "iso:country":"GB",
    "wof:name":"SN7 7EB",
    "wof:placetype":"postalcode"
},
  "geometry": {"coordinates":[-1.58987469026243,51.65294880798702],"type":"Point"}
}