{
  "type": "Feature",
  "properties": {
    "date:inception_lower": "1999-06-01",
    "date:inception_upper": "1999-06-01",
    "iso:country": "GB",
    "wof:name": "CH65 5DE",
    "wof:placetype": "postalcode"
  },
  "geometry": {"coordinates":[-2.884353,53.273711],"type":"Point"}
}
