{
  "type": "Feature",
  "properties": {
    "iso:country":"GB",
    "wof:name":"CH65 5DE",
    "wof:placetype":"postalcode"
},
  "geometry": {"coordinates":[-2.88536948592166,53.27426270430761],"type":"Point"}
}