{
  "type": "Feature",
  "properties": {
    "iso:country":"GB",
    "wof:name":"DY5 1AS",
    "wof:placetype":"postalcode"
},
  "geometry": {"coordinates":[-2.09811279388552,52.47596576741765],"type":"Point"}
}