{
  "type": "Feature",
  "properties": {
    "iso:country": "GB",
    "wof:name": "DE7 8YL",
    "wof:placetype": "postalcode"
  },
  "geometry": {"coordinates":[-1.313899,52.979099],"type":"Point"}
}
