{
  "type": "Feature",
  "properties": {
    "iso:country":"GB",
    "wof:name":"DE7 8YL",
    "wof:placetype":"postalcode"
},
  "geometry": {"coordinates":[-1.31389923441286,52.97909899733165],"type":"Point"}
}