{
  "type": "Feature",
  "properties": {
    "date:inception_lower": "1980-01-01",
    "date:inception_upper": "1980-01-01",
    "iso:country": "GB",
    "wof:name": "NG5 5DB",
    "wof:placetype": "postalcode"
  },
  "geometry": {"coordinates":[-1.176328,53.013545],"type":"Point"}
}
