{
  "type": "Feature",
  "properties": {
    "iso:country":"GB",
    "wof:name":"NG5 5DB",
    "wof:placetype":"postalcode"
},
  "geometry": {"coordinates":[-1.17632780923375,53.01354523160578],"type":"Point"}
}