{
  "type": "Feature",
  "properties": {
    "iso:country": "GB",
    "wof:name": "CH43 3BW",
    "wof:placetype": "postalcode"
  },
  "geometry": {"coordinates":[-3.047937,53.365308],"type":"Point"}
}
