{
  "type": "Feature",
  "properties": {
    "iso:country":"GB",
    "wof:name":"CH43 3BW",
    "wof:placetype":"postalcode"
},
  "geometry": {"coordinates":[-3.04793746620523,53.36530758155278],"type":"Point"}
}