{
  "type": "Feature",
  "properties": {
    "iso:country": "GB",
    "wof:name": "AB33 8LP",
    "wof:placetype": "postalcode"
  },
  "geometry": {"coordinates":[-2.781422,57.153443],"type":"Point"}
}
