{
  "type": "Feature",
  "properties": {
    "date:inception_lower": "2002-12-01",
    "date:inception_upper": "2002-12-01",
    "iso:country": "GB",
    "wof:name": "AB33 8LP",
    "wof:placetype": "postalcode"
  },
  "geometry": {"coordinates":[-2.781422,57.153443],"type":"Point"}
}
