{
  "type": "Feature",
  "properties": {
    "date:inception_lower": "2019-07-01",
    "date:inception_upper": "2019-07-01",
    "iso:country": "GB",
    "wof:name": "PR6 0FH",
    "wof:placetype": "postalcode"
  },
  "geometry": {"coordinates":[-2.620913,53.65606],"type":"Point"}
}
