{
  "type": "Feature",
  "properties": {
    "iso:country":"GB",
    "wof:name":"BL8 1BT",
    "wof:placetype":"postalcode"
},
  "geometry": {"coordinates":[-2.3017629678986,53.60560073491692],"type":"Point"}
}