{
  "type": "Feature",
  "properties": {
    "date:inception_lower": "1980-01-01",
    "date:inception_upper": "1980-01-01",
    "iso:country": "GB",
    "wof:name": "ML3 9LG",
    "wof:placetype": "postalcode"
  },
  "geometry": {"coordinates":[-4.077455,55.77562],"type":"Point"}
}
