{
  "type": "Feature",
  "properties": {
    "iso:country":"GB",
    "wof:name":"ML3 9LG",
    "wof:placetype":"postalcode"
},
  "geometry": {"coordinates":[-4.07745488898063,55.77561956576096],"type":"Point"}
}