{
  "type": "Feature",
  "properties": {
    "iso:country": "GB",
    "wof:name": "W3 6JZ",
    "wof:placetype": "postalcode"
  },
  "geometry": {"coordinates":[-0.265345,51.514255],"type":"Point"}
}
