{
  "type": "Feature",
  "properties": {
    "iso:country":"GB",
    "wof:name":"CT9 3TL",
    "wof:placetype":"postalcode"
},
  "geometry": {"coordinates":[1.41380059087607,51.37992500615344],"type":"Point"}
}