{
  "type": "Feature",
  "properties": {
    "date:inception_lower": "2023-05-01",
    "date:inception_upper": "2023-05-01",
    "iso:country": "GB",
    "wof:name": "PR2 7FL",
    "wof:placetype": "postalcode"
  },
  "geometry": {"coordinates":[-2.735506,53.785768],"type":"Point"}
}
