{
  "type": "Feature",
  "properties": {
    "iso:country":"GB",
    "wof:name":"UB5 5PW",
    "wof:placetype":"postalcode"
},
  "geometry": {"coordinates":[-0.38627597702096,51.5377672300287],"type":"Point"}
}