{
  "type": "Feature",
  "properties": {
    "iso:country":"GB",
    "wof:name":"NP23 5AQ",
    "wof:placetype":"postalcode"
},
  "geometry": {"coordinates":[-3.23310960900281,51.79553074661195],"type":"Point"}
}