{
  "type": "Feature",
  "properties": {
    "iso:country":"GB",
    "wof:name":"SA67 8DH",
    "wof:placetype":"postalcode"
},
  "geometry": {"coordinates":[-4.7959351486029,51.82006363620172],"type":"Point"}
}