{
  "type": "Feature",
  "properties": {
    "iso:country":"GB",
    "wof:name":"N5 2NU",
    "wof:placetype":"postalcode"
},
  "geometry": {"coordinates":[-0.09407398801351,51.54922877289654],"type":"Point"}
}