{
  "type": "Feature",
  "properties": {
    "iso:country":"GB",
    "wof:name":"HG4 4ER",
    "wof:placetype":"postalcode"
},
  "geometry": {"coordinates":[-1.65939596191037,54.223563871973],"type":"Point"}
}