{
  "type": "Feature",
  "properties": {
    "date:inception_lower":"1980-01-01",
    "date:inception_upper":"1980-01-31",
    "iso:country":"GB",
    "wof:name":"HR6 9JH",
    "wof:placetype":"postalcode"
},
  "geometry": {"coordinates":[-2.92835,52.184155],"type":"Point"}
}