{
  "type": "Feature",
  "properties": {
    "iso:country":"GB",
    "wof:name":"HR6 9JH",
    "wof:placetype":"postalcode"
},
  "geometry": {"coordinates":[-2.92871379385736,52.18417820834422],"type":"Point"}
}