{
  "type": "Feature",
  "properties": {
    "iso:country":"GB",
    "wof:name":"WA7 2WZ",
    "wof:placetype":"postalcode"
},
  "geometry": {"coordinates":[-2.70184555880523,53.32348520047506],"type":"Point"}
}