{
  "type": "Feature",
  "properties": {
    "date:inception_lower":"1997-06-01",
    "date:inception_upper":"1997-06-30",
    "iso:country":"GB",
    "wof:name":"WA7 2WZ",
    "wof:placetype":"postalcode"
},
  "geometry": {"coordinates":[-2.701846,53.323485],"type":"Point"}
}