{
  "type": "Feature",
  "properties": {
    "iso:country":"GB",
    "wof:name":"SL4 2LB",
    "wof:placetype":"postalcode"
},
  "geometry": {"coordinates":[-0.60632845076244,51.47821854978098],"type":"Point"}
}