{
  "type": "Feature",
  "properties": {
    "date:inception_lower":"1980-01-01",
    "date:inception_upper":"1980-01-31",
    "iso:country":"GB",
    "wof:name":"SP10 4AN",
    "wof:placetype":"postalcode"
},
  "geometry": {"coordinates":[-1.498366,51.221553],"type":"Point"}
}