{
  "type": "Feature",
  "properties": {
    "iso:country":"GB",
    "wof:name":"SP10 4AN",
    "wof:placetype":"postalcode"
},
  "geometry": {"coordinates":[-1.49836607074041,51.22155270527003],"type":"Point"}
}