{
  "type": "Feature",
  "properties": {
    "iso:country": "GB",
    "wof:name": "SP10 4AN",
    "wof:placetype": "postalcode"
  },
  "geometry": {"coordinates":[-1.498366,51.221553],"type":"Point"}
}
