{
  "type": "Feature",
  "properties": {
    "iso:country": "GB",
    "wof:name": "HG5 8NR",
    "wof:placetype": "postalcode"
  },
  "geometry": {"coordinates":[-1.41531,54.000145],"type":"Point"}
}
