{
  "type": "Feature",
  "properties": {
    "iso:country":"GB",
    "wof:name":"HG5 8NR",
    "wof:placetype":"postalcode"
},
  "geometry": {"coordinates":[-1.41535015720566,54.00012086854161],"type":"Point"}
}