{
  "type": "Feature",
  "properties": {
    "iso:country":"GB",
    "wof:name":"W2 6PA",
    "wof:placetype":"postalcode"
},
  "geometry": {"coordinates":[-0.18669039619706,51.52047323634093],"type":"Point"}
}