{
  "type": "Feature",
  "properties": {
    "iso:country":"GB",
    "wof:name":"CV37 7TE",
    "wof:placetype":"postalcode"
},
  "geometry": {"coordinates":[-1.60889810832666,52.13690416154161],"type":"Point"}
}