{
  "type": "Feature",
  "properties": {
    "iso:country": "GB",
    "wof:name": "YO14 9AD",
    "wof:placetype": "postalcode"
  },
  "geometry": {"coordinates":[-0.289928,54.20937],"type":"Point"}
}
