{
  "type": "Feature",
  "properties": {
    "iso:country":"GB",
    "wof:name":"LS26 8GL",
    "wof:placetype":"postalcode"
},
  "geometry": {"coordinates":[-1.45763431165281,53.75699706154634],"type":"Point"}
}