{
  "type": "Feature",
  "properties": {
    "date:inception_lower": "2010-07-01",
    "date:inception_upper": "2010-07-01",
    "iso:country": "GB",
    "wof:name": "LS26 8GL",
    "wof:placetype": "postalcode"
  },
  "geometry": {"coordinates":[-1.457634,53.756997],"type":"Point"}
}
