{
  "type": "Feature",
  "properties": {
    "date:inception_lower":"1992-08-01",
    "date:inception_upper":"1992-08-31",
    "iso:country":"GB",
    "wof:name":"LA7 7RF",
    "wof:placetype":"postalcode"
},
  "geometry": {"coordinates":[-2.774438,54.228412],"type":"Point"}
}