{
  "type": "Feature",
  "properties": {
    "iso:country":"GB",
    "wof:name":"LA7 7RF",
    "wof:placetype":"postalcode"
},
  "geometry": {"coordinates":[-2.77443763449028,54.22841199221602],"type":"Point"}
}