{
  "type": "Feature",
  "properties": {
    "iso:country":"GB",
    "wof:name":"TW7 6PN",
    "wof:placetype":"postalcode"
},
  "geometry": {"coordinates":[-0.33018714834662,51.47068201735889],"type":"Point"}
}