{
  "type": "Feature",
  "properties": {
    "iso:country":"GB",
    "wof:name":"S80 1PH",
    "wof:placetype":"postalcode"
},
  "geometry": {"coordinates":[-1.12156364127832,53.30891661676015],"type":"Point"}
}