{
  "type": "Feature",
  "properties": {
    "iso:country":"GB",
    "wof:name":"LS17 7AD",
    "wof:placetype":"postalcode"
},
  "geometry": {"coordinates":[-1.53257617994395,53.8538979449652],"type":"Point"}
}