{
  "type": "Feature",
  "properties": {
    "iso:country":"GB",
    "wof:name":"WN7 1RE",
    "wof:placetype":"postalcode"
},
  "geometry": {"coordinates":[-2.52069131607779,53.50024957028695],"type":"Point"}
}