{
  "type": "Feature",
  "properties": {
    "iso:country": "GB",
    "wof:name": "BB2 3WN",
    "wof:placetype": "postalcode"
  },
  "geometry": {"coordinates":[-2.466128,53.727475],"type":"Point"}
}
