{
  "type": "Feature",
  "properties": {
    "iso:country":"GB",
    "wof:name":"BL1 5LY",
    "wof:placetype":"postalcode"
},
  "geometry": {"coordinates":[-2.46435355303815,53.58696844673658],"type":"Point"}
}