{
  "type": "Feature",
  "properties": {
    "iso:country": "GB",
    "wof:name": "BL1 5LY",
    "wof:placetype": "postalcode"
  },
  "geometry": {"coordinates":[-2.464354,53.586968],"type":"Point"}
}
