{
  "type": "Feature",
  "properties": {
    "iso:country":"GB",
    "wof:name":"TN39 5BZ",
    "wof:placetype":"postalcode"
},
  "geometry": {"coordinates":[0.4691681202285,50.85838594564282],"type":"Point"}
}