{
  "type": "Feature",
  "properties": {
    "iso:country":"GB",
    "wof:name":"SG1 5DT",
    "wof:placetype":"postalcode"
},
  "geometry": {"coordinates":[-0.19122003242518,51.9114956452508],"type":"Point"}
}