{
  "type": "Feature",
  "properties": {
    "iso:country":"GB",
    "wof:name":"PE1 2BY",
    "wof:placetype":"postalcode"
},
  "geometry": {"coordinates":[-0.25100832716859,52.58447637416941],"type":"Point"}
}