{
  "type": "Feature",
  "properties": {
    "date:inception_lower": "1980-01-01",
    "date:inception_upper": "1980-01-01",
    "iso:country": "GB",
    "wof:name": "TN21 9JP",
    "wof:placetype": "postalcode"
  },
  "geometry": {"coordinates":[0.355512,50.948189],"type":"Point"}
}
