{
  "type": "Feature",
  "properties": {
    "iso:country":"GB",
    "wof:name":"LU5 5GJ",
    "wof:placetype":"postalcode"
},
  "geometry": {"coordinates":[-0.52806815127648,51.90002354260278],"type":"Point"}
}