{
  "type": "Feature",
  "properties": {
    "iso:country": "GB",
    "wof:name": "LU5 5GJ",
    "wof:placetype": "postalcode"
  },
  "geometry": {"coordinates":[-0.528068,51.900024],"type":"Point"}
}
