{
  "type": "Feature",
  "properties": {
    "iso:country": "GB",
    "wof:name": "GU28 9DB",
    "wof:placetype": "postalcode"
  },
  "geometry": {"coordinates":[-0.677864,50.997073],"type":"Point"}
}
