{
  "type": "Feature",
  "properties": {
    "date:inception_lower": "1980-01-01",
    "date:inception_upper": "1980-01-01",
    "iso:country": "GB",
    "wof:name": "GU28 9DB",
    "wof:placetype": "postalcode"
  },
  "geometry": {"coordinates":[-0.677864,50.997073],"type":"Point"}
}
