{
  "type": "Feature",
  "properties": {
    "date:inception_lower": "1983-03-01",
    "date:inception_upper": "1983-03-01",
    "iso:country": "GB",
    "wof:name": "GL11 5JL",
    "wof:placetype": "postalcode"
  },
  "geometry": {"coordinates":[-2.369246,51.705385],"type":"Point"}
}
