{
  "type": "Feature",
  "properties": {
    "iso:country":"GB",
    "wof:name":"GL11 5JL",
    "wof:placetype":"postalcode"
},
  "geometry": {"coordinates":[-2.36924593482815,51.7053846731263],"type":"Point"}
}