{
  "type": "Feature",
  "properties": {
    "iso:country":"GB",
    "wof:name":"TW18 1DW",
    "wof:placetype":"postalcode"
},
  "geometry": {"coordinates":[-0.48831547141672,51.42861231643008],"type":"Point"}
}