{
  "type": "Feature",
  "properties": {
    "iso:country":"GB",
    "wof:name":"BN3 5QP",
    "wof:placetype":"postalcode"
},
  "geometry": {"coordinates":[-0.18596719592265,50.83232350268526],"type":"Point"}
}