{
  "type": "Feature",
  "properties": {
    "date:inception_lower": "1980-01-01",
    "date:inception_upper": "1980-01-01",
    "iso:country": "GB",
    "wof:name": "BS5 8HH",
    "wof:placetype": "postalcode"
  },
  "geometry": {"coordinates":[-2.53858,51.46046],"type":"Point"}
}
