{
  "type": "Feature",
  "properties": {
    "iso:country":"GB",
    "wof:name":"BS5 8HH",
    "wof:placetype":"postalcode"
},
  "geometry": {"coordinates":[-2.53857977814064,51.46046004096794],"type":"Point"}
}