{
  "type": "Feature",
  "properties": {
    "iso:country":"GB",
    "wof:name":"OX13 5HF",
    "wof:placetype":"postalcode"
},
  "geometry": {"coordinates":[-1.44340318254028,51.68262003451441],"type":"Point"}
}