{
  "type": "Feature",
  "properties": {
    "iso:country":"GB",
    "wof:name":"LU3 1UH",
    "wof:placetype":"postalcode"
},
  "geometry": {"coordinates":[-0.42536025068823,51.90179627598418],"type":"Point"}
}