{
  "type": "Feature",
  "properties": {
    "iso:country":"GB",
    "wof:name":"BN22 0UR",
    "wof:placetype":"postalcode"
},
  "geometry": {"coordinates":[0.27354550826942,50.80650995005833],"type":"Point"}
}