{
  "type": "Feature",
  "properties": {
    "iso:country":"GB",
    "wof:name":"SK8 1DU",
    "wof:placetype":"postalcode"
},
  "geometry": {"coordinates":[-2.21554768381237,53.39242900291377],"type":"Point"}
}