{
  "type": "Feature",
  "properties": {
    "iso:country": "GB",
    "wof:name": "WD17 2AU",
    "wof:placetype": "postalcode"
  },
  "geometry": {"coordinates":[-0.396137,51.656037],"type":"Point"}
}
