{
  "type": "Feature",
  "properties": {
    "iso:country": "GB",
    "wof:name": "TS17 8HS",
    "wof:placetype": "postalcode"
  },
  "geometry": {"coordinates":[-1.295405,54.544396],"type":"Point"}
}
