{
  "type": "Feature",
  "properties": {
    "iso:country": "GB",
    "wof:name": "WA16 8EY",
    "wof:placetype": "postalcode"
  },
  "geometry": {"coordinates":[-2.360853,53.309085],"type":"Point"}
}
