{
  "type": "Feature",
  "properties": {
    "iso:country":"GB",
    "wof:name":"S40 2NG",
    "wof:placetype":"postalcode"
},
  "geometry": {"coordinates":[-1.43823350270957,53.21967117683965],"type":"Point"}
}