{
  "type": "Feature",
  "properties": {
    "iso:country":"GB",
    "wof:name":"SE1 9PU",
    "wof:placetype":"postalcode"
},
  "geometry": {"coordinates":[-0.1116401484411,51.50641167983636],"type":"Point"}
}