{
  "type": "Feature",
  "properties": {
    "date:inception_lower": "2001-06-01",
    "date:inception_upper": "2001-06-01",
    "iso:country": "GB",
    "wof:name": "BN17 7DJ",
    "wof:placetype": "postalcode"
  },
  "geometry": {"coordinates":[-0.555575,50.818878],"type":"Point"}
}
