{
  "type": "Feature",
  "properties": {
    "iso:country":"GB",
    "wof:name":"KT8 9BX",
    "wof:placetype":"postalcode"
},
  "geometry": {"coordinates":[-0.33977936247491,51.4071070992584],"type":"Point"}
}