{
  "type": "Feature",
  "properties": {
    "iso:country":"GB",
    "wof:name":"LL20 7RN",
    "wof:placetype":"postalcode"
},
  "geometry": {"coordinates":[-3.08668269087399,52.96344190508592],"type":"Point"}
}