{
  "type": "Feature",
  "properties": {
    "date:inception_lower": "1980-01-01",
    "date:inception_upper": "1980-01-01",
    "iso:country": "GB",
    "wof:name": "LL20 7RN",
    "wof:placetype": "postalcode"
  },
  "geometry": {"coordinates":[-3.086683,52.963442],"type":"Point"}
}
