{
  "type": "Feature",
  "properties": {
    "iso:country":"GB",
    "wof:name":"WD18 7EA",
    "wof:placetype":"postalcode"
},
  "geometry": {"coordinates":[-0.4085140335067,51.65621822271572],"type":"Point"}
}