{
  "type": "Feature",
  "properties": {
    "iso:country":"GB",
    "wof:name":"KT10 0EL",
    "wof:placetype":"postalcode"
},
  "geometry": {"coordinates":[-0.33701537549915,51.36041494304841],"type":"Point"}
}