{
  "type": "Feature",
  "properties": {
    "iso:country":"GB",
    "wof:name":"ST17 0SP",
    "wof:placetype":"postalcode"
},
  "geometry": {"coordinates":[-2.06506698734499,52.75835666818252],"type":"Point"}
}