{
  "type": "Feature",
  "properties": {
    "iso:country":"GB",
    "wof:name":"W1H 5AZ",
    "wof:placetype":"postalcode"
},
  "geometry": {"coordinates":[-0.16128537253193,51.51456535700623],"type":"Point"}
}