{
  "type": "Feature",
  "properties": {
    "iso:country":"GB",
    "wof:name":"PE9 3LX",
    "wof:placetype":"postalcode"
},
  "geometry": {"coordinates":[-0.50724708683861,52.62720934726616],"type":"Point"}
}