{
  "type": "Feature",
  "properties": {
    "iso:country": "GB",
    "wof:name": "PE9 3LX",
    "wof:placetype": "postalcode"
  },
  "geometry": {"coordinates":[-0.507247,52.627209],"type":"Point"}
}
