{
  "type": "Feature",
  "properties": {
    "iso:country":"GB",
    "wof:name":"TN10 3BY",
    "wof:placetype":"postalcode"
},
  "geometry": {"coordinates":[0.27523685015869,51.20445712786384],"type":"Point"}
}