{
  "type": "Feature",
  "properties": {
    "date:inception_lower": "1980-01-01",
    "date:inception_upper": "1980-01-01",
    "iso:country": "GB",
    "wof:name": "RH19 3UQ",
    "wof:placetype": "postalcode"
  },
  "geometry": {"coordinates":[0.007356,51.118787],"type":"Point"}
}
