{
  "type": "Feature",
  "properties": {
    "iso:country": "GB",
    "wof:name": "RH19 3UQ",
    "wof:placetype": "postalcode"
  },
  "geometry": {"coordinates":[0.007356,51.118787],"type":"Point"}
}
