{
  "type": "Feature",
  "properties": {
    "iso:country":"GB",
    "wof:name":"AL9 5PE",
    "wof:placetype":"postalcode"
},
  "geometry": {"coordinates":[-0.19617517323858,51.77392237755058],"type":"Point"}
}