{
  "type": "Feature",
  "properties": {
    "iso:country": "GB",
    "wof:name": "AL9 5PE",
    "wof:placetype": "postalcode"
  },
  "geometry": {"coordinates":[-0.196175,51.773922],"type":"Point"}
}
