{
  "type": "Feature",
  "properties": {
    "date:inception_lower": "1997-06-01",
    "date:inception_upper": "1997-06-01",
    "iso:country": "GB",
    "wof:name": "OX9 2HJ",
    "wof:placetype": "postalcode"
  },
  "geometry": {"coordinates":[-1.000792,51.740244],"type":"Point"}
}
