{
  "type": "Feature",
  "properties": {
    "iso:country": "GB",
    "wof:name": "OX9 2HJ",
    "wof:placetype": "postalcode"
  },
  "geometry": {"coordinates":[-1.001286,51.740131],"type":"Point"}
}
