{
  "type": "Feature",
  "properties": {
    "iso:country": "GB",
    "wof:name": "NG17 5GJ",
    "wof:placetype": "postalcode"
  },
  "geometry": {"coordinates":[-1.240383,53.123335],"type":"Point"}
}
