{
  "type": "Feature",
  "properties": {
    "date:inception_lower":"1985-04-01",
    "date:inception_upper":"1985-04-30",
    "iso:country":"GB",
    "wof:name":"TS6 6XS",
    "wof:placetype":"postalcode"
},
  "geometry": {"coordinates":[-1.17251,54.572863],"type":"Point"}
}