{
  "type": "Feature",
  "properties": {
    "date:inception_lower":"1998-12-01",
    "date:inception_upper":"1998-12-31",
    "iso:country":"GB",
    "wof:name":"BN3 7HZ",
    "wof:placetype":"postalcode"
},
  "geometry": {"coordinates":[-0.19071,50.842991],"type":"Point"}
}