{
  "type": "Feature",
  "properties": {
    "iso:country":"GB",
    "wof:name":"BN3 7HZ",
    "wof:placetype":"postalcode"
},
  "geometry": {"coordinates":[-0.19070967162533,50.84299135744714],"type":"Point"}
}