{
  "type": "Feature",
  "properties": {
    "date:inception_lower": "1980-01-01",
    "date:inception_upper": "1980-01-01",
    "iso:country": "GB",
    "wof:name": "SA12 7PA",
    "wof:placetype": "postalcode"
  },
  "geometry": {"coordinates":[-3.812045,51.61334],"type":"Point"}
}
