{
  "type": "Feature",
  "properties": {
    "iso:country":"GB",
    "wof:name":"DG7 3QH",
    "wof:placetype":"postalcode"
},
  "geometry": {"coordinates":[-4.07672628426456,55.09073979282413],"type":"Point"}
}