{
  "type": "Feature",
  "properties": {
    "iso:country": "GB",
    "wof:name": "LN13 9AA",
    "wof:placetype": "postalcode"
  },
  "geometry": {"coordinates":[0.179389,53.260342],"type":"Point"}
}
