{
  "type": "Feature",
  "properties": {
    "iso:country":"GB",
    "wof:name":"LN13 9AA",
    "wof:placetype":"postalcode"
},
  "geometry": {"coordinates":[0.17938881888724,53.26034206495998],"type":"Point"}
}