{
  "type": "Feature",
  "properties": {
    "iso:country":"GB",
    "wof:name":"BA5 2BJ",
    "wof:placetype":"postalcode"
},
  "geometry": {"coordinates":[-2.65729624342922,51.20931452046879],"type":"Point"}
}