{
  "type": "Feature",
  "properties": {
    "date:inception_lower": "1980-01-01",
    "date:inception_upper": "1980-01-01",
    "iso:country": "GB",
    "wof:name": "TF6 6DF",
    "wof:placetype": "postalcode"
  },
  "geometry": {"coordinates":[-2.484577,52.729201],"type":"Point"}
}
