{
  "type": "Feature",
  "properties": {
    "iso:country": "GB",
    "wof:name": "TF6 6DF",
    "wof:placetype": "postalcode"
  },
  "geometry": {"coordinates":[-2.484577,52.729201],"type":"Point"}
}
