{
  "type": "Feature",
  "properties": {
    "iso:country":"GB",
    "wof:name":"TF6 6DF",
    "wof:placetype":"postalcode"
},
  "geometry": {"coordinates":[-2.48457728425024,52.72920137463371],"type":"Point"}
}