{
  "type": "Feature",
  "properties": {
    "iso:country":"GB",
    "wof:name":"EX7 0PQ",
    "wof:placetype":"postalcode"
},
  "geometry": {"coordinates":[-3.44504260929426,50.59862753875245],"type":"Point"}
}