{
  "type": "Feature",
  "properties": {
    "date:inception_lower": "1980-01-01",
    "date:inception_upper": "1980-01-01",
    "iso:country": "GB",
    "wof:name": "EX7 0PQ",
    "wof:placetype": "postalcode"
  },
  "geometry": {"coordinates":[-3.444977,50.598355],"type":"Point"}
}
