{
  "type": "Feature",
  "properties": {
    "date:inception_lower": "2020-01-01",
    "date:inception_upper": "2020-01-01",
    "iso:country": "GB",
    "wof:name": "TR11 5JJ",
    "wof:placetype": "postalcode"
  },
  "geometry": {"coordinates":[-5.079393,50.139255],"type":"Point"}
}
