{
  "type": "Feature",
  "properties": {
    "iso:country": "GB",
    "wof:name": "TR11 5JJ",
    "wof:placetype": "postalcode"
  },
  "geometry": {"coordinates":[-5.079056,50.139462],"type":"Point"}
}
