{
  "type": "Feature",
  "properties": {
    "iso:country":"GB",
    "wof:name":"BS40 8RG",
    "wof:placetype":"postalcode"
},
  "geometry": {"coordinates":[-2.61058281337628,51.36696192778958],"type":"Point"}
}