{
  "type": "Feature",
  "properties": {
    "date:inception_lower": "1997-12-01",
    "date:inception_upper": "1997-12-01",
    "iso:country": "GB",
    "wof:name": "BS40 8RG",
    "wof:placetype": "postalcode"
  },
  "geometry": {"coordinates":[-2.610599,51.366959],"type":"Point"}
}
