{
  "type": "Feature",
  "properties": {
    "date:inception_lower": "1980-01-01",
    "date:inception_upper": "1980-01-01",
    "iso:country": "GB",
    "wof:name": "IP7 6RB",
    "wof:placetype": "postalcode"
  },
  "geometry": {"coordinates":[0.952239,52.078517],"type":"Point"}
}
