{
  "type": "Feature",
  "properties": {
    "iso:country":"GB",
    "wof:name":"GL1 4US",
    "wof:placetype":"postalcode"
},
  "geometry": {"coordinates":[-2.24107869802367,51.85583239444041],"type":"Point"}
}