{
  "type": "Feature",
  "properties": {
    "iso:country": "GB",
    "wof:name": "BA10 0LQ",
    "wof:placetype": "postalcode"
  },
  "geometry": {"coordinates":[-2.399493,51.113743],"type":"Point"}
}
