{
  "type": "Feature",
  "properties": {
    "iso:country":"GB",
    "wof:name":"NG9 6BH",
    "wof:placetype":"postalcode"
},
  "geometry": {"coordinates":[-1.23211158183517,52.90804968497986],"type":"Point"}
}