{
  "type": "Feature",
  "properties": {
    "iso:country":"GB",
    "wof:name":"IV27 4PZ",
    "wof:placetype":"postalcode"
},
  "geometry": {"coordinates":[-4.74217573811076,58.56438522024754],"type":"Point"}
}