{
  "type": "Feature",
  "properties": {
    "date:inception_lower":"1980-01-01",
    "date:inception_upper":"1980-01-31",
    "iso:country":"GB",
    "wof:name":"IV27 4PZ",
    "wof:placetype":"postalcode"
},
  "geometry": {"coordinates":[-4.742174,58.564367],"type":"Point"}
}