{
  "type": "Feature",
  "properties": {
    "iso:country": "GB",
    "wof:name": "IV27 4PZ",
    "wof:placetype": "postalcode"
  },
  "geometry": {"coordinates":[-4.742174,58.564367],"type":"Point"}
}
