{
  "type": "Feature",
  "properties": {
    "iso:country":"GB",
    "wof:name":"LE12 8SF",
    "wof:placetype":"postalcode"
},
  "geometry": {"coordinates":[-1.2174267744821,52.7250950394112],"type":"Point"}
}