{
  "type": "Feature",
  "properties": {
    "iso:country": "GB",
    "wof:name": "PE12 9DY",
    "wof:placetype": "postalcode"
  },
  "geometry": {"coordinates":[0.120992,52.78721],"type":"Point"}
}
