{
  "type": "Feature",
  "properties": {
    "iso:country":"GB",
    "wof:name":"PE12 9DY",
    "wof:placetype":"postalcode"
},
  "geometry": {"coordinates":[0.12099175274832,52.78721030406046],"type":"Point"}
}