{
  "type": "Feature",
  "properties": {
    "date:inception_lower": "1990-07-01",
    "date:inception_upper": "1990-07-01",
    "iso:country": "GB",
    "wof:name": "E4 6UY",
    "wof:placetype": "postalcode"
  },
  "geometry": {"coordinates":[0.005508,51.62236],"type":"Point"}
}
