{
  "type": "Feature",
  "properties": {
    "iso:country":"GB",
    "wof:name":"E4 6UY",
    "wof:placetype":"postalcode"
},
  "geometry": {"coordinates":[0.00550794096593,51.622360022002],"type":"Point"}
}