{
  "type": "Feature",
  "properties": {
    "iso:country":"GB",
    "wof:name":"CM7 2LL",
    "wof:placetype":"postalcode"
},
  "geometry": {"coordinates":[0.54522672737001,51.8721043314338],"type":"Point"}
}