{
  "type": "Feature",
  "properties": {
    "iso:country": "GB",
    "wof:name": "GU26 6FG",
    "wof:placetype": "postalcode"
  },
  "geometry": {"coordinates":[-0.761889,51.111462],"type":"Point"}
}
