{
  "type": "Feature",
  "properties": {
    "date:inception_lower":"2011-03-01",
    "date:inception_upper":"2011-03-31",
    "iso:country":"GB",
    "wof:name":"GU26 6FG",
    "wof:placetype":"postalcode"
},
  "geometry": {"coordinates":[-0.761889,51.111462],"type":"Point"}
}