{
  "type": "Feature",
  "properties": {
    "iso:country":"GB",
    "wof:name":"NN11 3RL",
    "wof:placetype":"postalcode"
},
  "geometry": {"coordinates":[-1.20587600033002,52.17112135174911],"type":"Point"}
}