{
  "type": "Feature",
  "properties": {
    "iso:country": "GB",
    "wof:name": "NG21 9GG",
    "wof:placetype": "postalcode"
  },
  "geometry": {"coordinates":[-1.123696,53.168622],"type":"Point"}
}
