{
  "type": "Feature",
  "properties": {
    "iso:country":"GB",
    "wof:name":"WD7 7JS",
    "wof:placetype":"postalcode"
},
  "geometry": {"coordinates":[-0.31542068623804,51.67740000393144],"type":"Point"}
}