{
  "type": "Feature",
  "properties": {
    "iso:country": "GB",
    "wof:name": "RH5 4LG",
    "wof:placetype": "postalcode"
  },
  "geometry": {"coordinates":[-0.338776,51.185272],"type":"Point"}
}
