{
  "type": "Feature",
  "properties": {
    "date:inception_lower": "1980-01-01",
    "date:inception_upper": "1980-01-01",
    "iso:country": "GB",
    "wof:name": "RH5 4LG",
    "wof:placetype": "postalcode"
  },
  "geometry": {"coordinates":[-0.338776,51.185272],"type":"Point"}
}
