{
  "type": "Feature",
  "properties": {
    "iso:country":"GB",
    "wof:name":"LS14 1BF",
    "wof:placetype":"postalcode"
},
  "geometry": {"coordinates":[-1.47916556117717,53.82492551516098],"type":"Point"}
}