{
  "type": "Feature",
  "properties": {
    "iso:country":"GB",
    "wof:name":"WV2 2EE",
    "wof:placetype":"postalcode"
},
  "geometry": {"coordinates":[-2.10758580779923,52.57481935958077],"type":"Point"}
}