{
  "type": "Feature",
  "properties": {
    "date:inception_lower": "2002-06-01",
    "date:inception_upper": "2002-06-01",
    "iso:country": "GB",
    "wof:name": "WV2 2EE",
    "wof:placetype": "postalcode"
  },
  "geometry": {"coordinates":[-2.108051,52.574547],"type":"Point"}
}
