{
  "type": "Feature",
  "properties": {
    "iso:country":"GB",
    "wof:name":"TN6 2BX",
    "wof:placetype":"postalcode"
},
  "geometry": {"coordinates":[0.18022082362409,51.05697596847691],"type":"Point"}
}