{
  "type": "Feature",
  "properties": {
    "iso:country":"GB",
    "wof:name":"CH8 7LP",
    "wof:placetype":"postalcode"
},
  "geometry": {"coordinates":[-3.22350535060949,53.27422933289533],"type":"Point"}
}