{
  "type": "Feature",
  "properties": {
    "date:inception_lower": "1980-01-01",
    "date:inception_upper": "1980-01-01",
    "iso:country": "GB",
    "wof:name": "DY8 2TA",
    "wof:placetype": "postalcode"
  },
  "geometry": {"coordinates":[-2.159503,52.443999],"type":"Point"}
}
