{
  "type": "Feature",
  "properties": {
    "iso:country":"GB",
    "wof:name":"LE11 3RN",
    "wof:placetype":"postalcode"
},
  "geometry": {"coordinates":[-1.2354727909371,52.75916707447863],"type":"Point"}
}