{
  "type": "Feature",
  "properties": {
    "iso:country":"GB",
    "wof:name":"PL3 4AP",
    "wof:placetype":"postalcode"
},
  "geometry": {"coordinates":[-4.15832085440756,50.38045325678746],"type":"Point"}
}