{
  "type": "Feature",
  "properties": {
    "iso:country": "GB",
    "wof:name": "AL6 9HN",
    "wof:placetype": "postalcode"
  },
  "geometry": {"coordinates":[-0.224468,51.828224],"type":"Point"}
}
