{
  "type": "Feature",
  "properties": {
    "iso:country":"GB",
    "wof:name":"AL6 9HN",
    "wof:placetype":"postalcode"
},
  "geometry": {"coordinates":[-0.22446781050024,51.82822427264263],"type":"Point"}
}