{
  "type": "Feature",
  "properties": {
    "iso:country":"GB",
    "wof:name":"CF33 4PD",
    "wof:placetype":"postalcode"
},
  "geometry": {"coordinates":[-3.70603883929527,51.52574359214329],"type":"Point"}
}