{
  "type": "Feature",
  "properties": {
    "date:inception_lower": "2006-08-01",
    "date:inception_upper": "2006-08-01",
    "iso:country": "GB",
    "wof:name": "CF33 4PD",
    "wof:placetype": "postalcode"
  },
  "geometry": {"coordinates":[-3.706039,51.525744],"type":"Point"}
}
