{
  "type": "Feature",
  "properties": {
    "iso:country": "GB",
    "wof:name": "CF33 4PD",
    "wof:placetype": "postalcode"
  },
  "geometry": {"coordinates":[-3.706039,51.525744],"type":"Point"}
}
