{
  "type": "Feature",
  "properties": {
    "iso:country": "GB",
    "wof:name": "DT1 3DU",
    "wof:placetype": "postalcode"
  },
  "geometry": {"coordinates":[-2.466481,50.715894],"type":"Point"}
}
