{
  "type": "Feature",
  "properties": {
    "iso:country":"GB",
    "wof:name":"NE9 5PP",
    "wof:placetype":"postalcode"
},
  "geometry": {"coordinates":[-1.58548397671153,54.94498564849354],"type":"Point"}
}