{
  "type": "Feature",
  "properties": {
    "iso:country":"GB",
    "wof:name":"SN14 0HF",
    "wof:placetype":"postalcode"
},
  "geometry": {"coordinates":[-2.12916875945612,51.46230103436617],"type":"Point"}
}