{
  "type": "Feature",
  "properties": {
    "iso:country":"GB",
    "wof:name":"TA6 5AY",
    "wof:placetype":"postalcode"
},
  "geometry": {"coordinates":[-3.00073871024584,51.12923238828436],"type":"Point"}
}