{
  "type": "Feature",
  "properties": {
    "date:inception_lower": "2020-11-01",
    "date:inception_upper": "2020-11-01",
    "iso:country": "GB",
    "wof:name": "BA14 9HA",
    "wof:placetype": "postalcode"
  },
  "geometry": {"coordinates":[-2.229559,51.314528],"type":"Point"}
}
