{
  "type": "Feature",
  "properties": {
    "iso:country":"GB",
    "wof:name":"BN1 5NQ",
    "wof:placetype":"postalcode"
},
  "geometry": {"coordinates":[-0.15350094202647,50.84030399618667],"type":"Point"}
}