{
  "type": "Feature",
  "properties": {
    "iso:country": "GB",
    "wof:name": "BN1 5NQ",
    "wof:placetype": "postalcode"
  },
  "geometry": {"coordinates":[-0.153501,50.840304],"type":"Point"}
}
