{
  "type": "Feature",
  "properties": {
    "iso:country":"GB",
    "wof:name":"LE13 1JR",
    "wof:placetype":"postalcode"
},
  "geometry": {"coordinates":[-0.88742507106127,52.77499633618636],"type":"Point"}
}