{
  "type": "Feature",
  "properties": {
    "iso:country": "GB",
    "wof:name": "LE13 1JR",
    "wof:placetype": "postalcode"
  },
  "geometry": {"coordinates":[-0.887425,52.774996],"type":"Point"}
}
