{
  "type": "Feature",
  "properties": {
    "iso:country": "GB",
    "wof:name": "SL9 0FE",
    "wof:placetype": "postalcode"
  },
  "geometry": {"coordinates":[-0.547346,51.621531],"type":"Point"}
}
