{
  "type": "Feature",
  "properties": {
    "iso:country": "GB",
    "wof:name": "BB18 6SE",
    "wof:placetype": "postalcode"
  },
  "geometry": {"coordinates":[-2.148958,53.90519],"type":"Point"}
}
