{
  "type": "Feature",
  "properties": {
    "iso:country":"GB",
    "wof:name":"BB18 6SE",
    "wof:placetype":"postalcode"
},
  "geometry": {"coordinates":[-2.14895831595691,53.90519014962859],"type":"Point"}
}