{
  "type": "Feature",
  "properties": {
    "date:inception_lower":"1997-12-01",
    "date:inception_upper":"1997-12-31",
    "iso:country":"GB",
    "wof:name":"BB18 6SE",
    "wof:placetype":"postalcode"
},
  "geometry": {"coordinates":[-2.148958,53.90519],"type":"Point"}
}