{
  "type": "Feature",
  "properties": {
    "iso:country": "GB",
    "wof:name": "ST17 4QS",
    "wof:placetype": "postalcode"
  },
  "geometry": {"coordinates":[-2.086921,52.786696],"type":"Point"}
}
