{
  "type": "Feature",
  "properties": {
    "date:inception_lower": "1980-01-01",
    "date:inception_upper": "1980-01-01",
    "iso:country": "GB",
    "wof:name": "ST17 4QS",
    "wof:placetype": "postalcode"
  },
  "geometry": {"coordinates":[-2.086921,52.786696],"type":"Point"}
}
