{
  "type": "Feature",
  "properties": {
    "date:inception_lower": "1998-12-01",
    "date:inception_upper": "1998-12-01",
    "iso:country": "GB",
    "wof:name": "SA32 8SN",
    "wof:placetype": "postalcode"
  },
  "geometry": {"coordinates":[-4.123259,51.886341],"type":"Point"}
}
