{
  "type": "Feature",
  "properties": {
    "iso:country": "GB",
    "wof:name": "SA32 8SN",
    "wof:placetype": "postalcode"
  },
  "geometry": {"coordinates":[-4.123259,51.886341],"type":"Point"}
}
