{
  "type": "Feature",
  "properties": {
    "iso:country":"GB",
    "wof:name":"AL2 2QE",
    "wof:placetype":"postalcode"
},
  "geometry": {"coordinates":[-0.34910080236102,51.72249659894457],"type":"Point"}
}