{
  "type": "Feature",
  "properties": {
    "date:inception_lower":"1996-06-01",
    "date:inception_upper":"1996-06-30",
    "iso:country":"GB",
    "wof:name":"RG7 1RZ",
    "wof:placetype":"postalcode"
},
  "geometry": {"coordinates":[-0.956559,51.376202],"type":"Point"}
}