{
  "type": "Feature",
  "properties": {
    "iso:country":"GB",
    "wof:name":"RG7 1RZ",
    "wof:placetype":"postalcode"
},
  "geometry": {"coordinates":[-0.95655877240404,51.37620236004359],"type":"Point"}
}