{
  "type": "Feature",
  "properties": {
    "iso:country":"GB",
    "wof:name":"DD4 9SF",
    "wof:placetype":"postalcode"
},
  "geometry": {"coordinates":[-2.95248559992643,56.48847951706033],"type":"Point"}
}