{
  "type": "Feature",
  "properties": {
    "date:inception_lower": "1980-01-01",
    "date:inception_upper": "1980-01-01",
    "iso:country": "GB",
    "wof:name": "NG22 9NS",
    "wof:placetype": "postalcode"
  },
  "geometry": {"coordinates":[-0.978144,53.229039],"type":"Point"}
}
