{
  "type": "Feature",
  "properties": {
    "iso:country":"GB",
    "wof:name":"NG22 9NS",
    "wof:placetype":"postalcode"
},
  "geometry": {"coordinates":[-0.97814413212045,53.22903850726283],"type":"Point"}
}