{
  "type": "Feature",
  "properties": {
    "iso:country":"GB",
    "wof:name":"GL13 9PD",
    "wof:placetype":"postalcode"
},
  "geometry": {"coordinates":[-2.47099713669677,51.71402082871277],"type":"Point"}
}