{
  "type": "Feature",
  "properties": {
    "iso:country":"GB",
    "wof:name":"HD1 4LA",
    "wof:placetype":"postalcode"
},
  "geometry": {"coordinates":[-1.80149995863947,53.65119921235646],"type":"Point"}
}