{
  "type": "Feature",
  "properties": {
    "iso:country": "GB",
    "wof:name": "HD1 4LA",
    "wof:placetype": "postalcode"
  },
  "geometry": {"coordinates":[-1.8015,53.651199],"type":"Point"}
}
