{
  "type": "Feature",
  "properties": {
    "iso:country":"GB",
    "wof:name":"TW8 8ER",
    "wof:placetype":"postalcode"
},
  "geometry": {"coordinates":[-0.31203175956877,51.4847019506971],"type":"Point"}
}