{
  "type": "Feature",
  "properties": {
    "date:inception_lower": "2005-04-01",
    "date:inception_upper": "2005-04-01",
    "iso:country": "GB",
    "wof:name": "TW8 8ER",
    "wof:placetype": "postalcode"
  },
  "geometry": {"coordinates":[-0.312032,51.484702],"type":"Point"}
}
