{
  "type": "Feature",
  "properties": {
    "iso:country":"GB",
    "wof:name":"M40 5WS",
    "wof:placetype":"postalcode"
},
  "geometry": {"coordinates":[-2.19361239198703,53.50570372430528],"type":"Point"}
}