{
  "type": "Feature",
  "properties": {
    "iso:country": "GB",
    "wof:name": "CA7 8ND",
    "wof:placetype": "postalcode"
  },
  "geometry": {"coordinates":[-3.153,54.790535],"type":"Point"}
}
