{
  "type": "Feature",
  "properties": {
    "iso:country": "GB",
    "wof:name": "NE31 1DP",
    "wof:placetype": "postalcode"
  },
  "geometry": {"coordinates":[-1.525721,54.97985],"type":"Point"}
}
