{
  "type": "Feature",
  "properties": {
    "iso:country": "GB",
    "wof:name": "PL9 8GN",
    "wof:placetype": "postalcode"
  },
  "geometry": {"coordinates":[-4.0588,50.36412],"type":"Point"}
}
