{
  "type": "Feature",
  "properties": {
    "iso:country":"GB",
    "wof:name":"NE10 0HJ",
    "wof:placetype":"postalcode"
},
  "geometry": {"coordinates":[-1.56314706970457,54.95196175520907],"type":"Point"}
}