{
  "type": "Feature",
  "properties": {
    "iso:country": "GB",
    "wof:name": "NE10 0HJ",
    "wof:placetype": "postalcode"
  },
  "geometry": {"coordinates":[-1.563147,54.951962],"type":"Point"}
}
