{
  "type": "Feature",
  "properties": {
    "iso:country": "GB",
    "wof:name": "KT1 3QN",
    "wof:placetype": "postalcode"
  },
  "geometry": {"coordinates":[-0.283933,51.408659],"type":"Point"}
}
