{
  "type": "Feature",
  "properties": {
    "iso:country":"GB",
    "wof:name":"KT1 3QN",
    "wof:placetype":"postalcode"
},
  "geometry": {"coordinates":[-0.2839333771247,51.4086587029857],"type":"Point"}
}