{
  "type": "Feature",
  "properties": {
    "iso:country":"GB",
    "wof:name":"CM0 7BD",
    "wof:placetype":"postalcode"
},
  "geometry": {"coordinates":[0.8175573776726,51.66563406655104],"type":"Point"}
}