{
  "type": "Feature",
  "properties": {
    "iso:country":"GB",
    "wof:name":"DY14 0JA",
    "wof:placetype":"postalcode"
},
  "geometry": {"coordinates":[-2.54133410906241,52.40803334548028],"type":"Point"}
}