{
  "type": "Feature",
  "properties": {
    "iso:country": "GB",
    "wof:name": "BB6 8AE",
    "wof:placetype": "postalcode"
  },
  "geometry": {"coordinates":[-2.460623,53.803406],"type":"Point"}
}
