{
  "type": "Feature",
  "properties": {
    "iso:country":"GB",
    "wof:name":"BB6 8AE",
    "wof:placetype":"postalcode"
},
  "geometry": {"coordinates":[-2.46082404822799,53.80366056079144],"type":"Point"}
}