{
  "type": "Feature",
  "properties": {
    "iso:country":"GB",
    "wof:name":"SW20 8HW",
    "wof:placetype":"postalcode"
},
  "geometry": {"coordinates":[-0.22415399601408,51.41846925083438],"type":"Point"}
}