{
  "type": "Feature",
  "properties": {
    "iso:country":"GB",
    "wof:name":"BH21 3BH",
    "wof:placetype":"postalcode"
},
  "geometry": {"coordinates":[-1.97521405070107,50.77521516821192],"type":"Point"}
}