{
  "type": "Feature",
  "properties": {
    "iso:country": "GB",
    "wof:name": "EH4 2QX",
    "wof:placetype": "postalcode"
  },
  "geometry": {"coordinates":[-3.242606,55.965109],"type":"Point"}
}
