{
  "type": "Feature",
  "properties": {
    "iso:country":"GB",
    "wof:name":"LE5 0FB",
    "wof:placetype":"postalcode"
},
  "geometry": {"coordinates":[-1.10329957056792,52.64323395731801],"type":"Point"}
}