{
  "type": "Feature",
  "properties": {
    "date:inception_lower":"1997-12-01",
    "date:inception_upper":"1997-12-31",
    "iso:country":"GB",
    "wof:name":"BS22 7XT",
    "wof:placetype":"postalcode"
},
  "geometry": {"coordinates":[-2.898633,51.363838],"type":"Point"}
}