{
  "type": "Feature",
  "properties": {
    "iso:country":"GB",
    "wof:name":"TD8 6LB",
    "wof:placetype":"postalcode"
},
  "geometry": {"coordinates":[-2.54817282917626,55.47377403469605],"type":"Point"}
}