{
  "type": "Feature",
  "properties": {
    "iso:country":"GB",
    "wof:name":"SA47 0PH",
    "wof:placetype":"postalcode"
},
  "geometry": {"coordinates":[-4.33108000902017,52.17893148849762],"type":"Point"}
}