{
  "type": "Feature",
  "properties": {
    "iso:country":"GB",
    "wof:name":"NE16 5JN",
    "wof:placetype":"postalcode"
},
  "geometry": {"coordinates":[-1.68111897762519,54.93681776841051],"type":"Point"}
}