{
  "type": "Feature",
  "properties": {
    "iso:country":"GB",
    "wof:name":"DN14 6SR",
    "wof:placetype":"postalcode"
},
  "geometry": {"coordinates":[-0.88429818173848,53.7068047912984],"type":"Point"}
}