{
  "type": "Feature",
  "properties": {
    "iso:country":"GB",
    "wof:name":"DN1 1JS",
    "wof:placetype":"postalcode"
},
  "geometry": {"coordinates":[-1.13041007019122,53.52401221784727],"type":"Point"}
}