{
  "type": "Feature",
  "properties": {
    "iso:country":"GB",
    "wof:name":"B44 8SR",
    "wof:placetype":"postalcode"
},
  "geometry": {"coordinates":[-1.89249094896095,52.54413758362544],"type":"Point"}
}