{
  "type": "Feature",
  "properties": {
    "date:inception_lower": "1980-01-01",
    "date:inception_upper": "1980-01-01",
    "iso:country": "GB",
    "wof:name": "SE22 0ES",
    "wof:placetype": "postalcode"
  },
  "geometry": {"coordinates":[-0.068576,51.448625],"type":"Point"}
}
