{
  "type": "Feature",
  "properties": {
    "iso:country":"GB",
    "wof:name":"NG16 3HY",
    "wof:placetype":"postalcode"
},
  "geometry": {"coordinates":[-1.30629530160517,53.00937597976534],"type":"Point"}
}