{
  "type": "Feature",
  "properties": {
    "date:inception_lower":"2005-04-01",
    "date:inception_upper":"2005-04-30",
    "iso:country":"GB",
    "wof:name":"NG16 3HY",
    "wof:placetype":"postalcode"
},
  "geometry": {"coordinates":[-1.306295,53.009376],"type":"Point"}
}