{
  "type": "Feature",
  "properties": {
    "iso:country":"GB",
    "wof:name":"EC2V 7EH",
    "wof:placetype":"postalcode"
},
  "geometry": {"coordinates":[-0.09380426807626,51.51564626745309],"type":"Point"}
}