{
  "type": "Feature",
  "properties": {
    "iso:country":"GB",
    "wof:name":"OL3 7NP",
    "wof:placetype":"postalcode"
},
  "geometry": {"coordinates":[-1.98873637289479,53.53550408072398],"type":"Point"}
}