{
  "type": "Feature",
  "properties": {
    "iso:country": "GB",
    "wof:name": "OL3 7NP",
    "wof:placetype": "postalcode"
  },
  "geometry": {"coordinates":[-1.988736,53.535504],"type":"Point"}
}
