{
  "type": "Feature",
  "properties": {
    "date:inception_lower":"1980-01-01",
    "date:inception_upper":"1980-01-31",
    "iso:country":"GB",
    "wof:name":"OL3 7NP",
    "wof:placetype":"postalcode"
},
  "geometry": {"coordinates":[-1.988736,53.535504],"type":"Point"}
}