{
  "type": "Feature",
  "properties": {
    "date:inception_lower": "1980-01-01",
    "date:inception_upper": "1980-01-01",
    "iso:country": "GB",
    "wof:name": "GU31 5EU",
    "wof:placetype": "postalcode"
  },
  "geometry": {"coordinates":[-0.801134,51.000327],"type":"Point"}
}
