{
  "type": "Feature",
  "properties": {
    "iso:country":"GB",
    "wof:name":"GU31 5EU",
    "wof:placetype":"postalcode"
},
  "geometry": {"coordinates":[-0.80113365639521,51.00032729354437],"type":"Point"}
}