{
  "type": "Feature",
  "properties": {
    "iso:country": "GB",
    "wof:name": "GU31 5EU",
    "wof:placetype": "postalcode"
  },
  "geometry": {"coordinates":[-0.801134,51.000327],"type":"Point"}
}
