{
  "type": "Feature",
  "properties": {
    "date:inception_lower": "2005-07-01",
    "date:inception_upper": "2005-07-01",
    "iso:country": "GB",
    "wof:name": "IP32 7GR",
    "wof:placetype": "postalcode"
  },
  "geometry": {"coordinates":[0.754509,52.249938],"type":"Point"}
}
