{
  "type": "Feature",
  "properties": {
    "date:inception_lower": "2017-08-01",
    "date:inception_upper": "2017-08-01",
    "iso:country": "GB",
    "wof:name": "EX34 9JP",
    "wof:placetype": "postalcode"
  },
  "geometry": {"coordinates":[-4.12225,51.206298],"type":"Point"}
}
