{
  "type": "Feature",
  "properties": {
    "iso:country":"GB",
    "wof:name":"EX34 9JP",
    "wof:placetype":"postalcode"
},
  "geometry": {"coordinates":[-4.12222634977608,51.20629817647212],"type":"Point"}
}