{
  "type": "Feature",
  "properties": {
    "iso:country": "GB",
    "wof:name": "WR4 9BJ",
    "wof:placetype": "postalcode"
  },
  "geometry": {"coordinates":[-2.189252,52.200201],"type":"Point"}
}
