{
  "type": "Feature",
  "properties": {
    "iso:country":"GB",
    "wof:name":"TN25 6ST",
    "wof:placetype":"postalcode"
},
  "geometry": {"coordinates":[0.96639004399413,51.11442103719725],"type":"Point"}
}