{
  "type": "Feature",
  "properties": {
    "iso:country":"GB",
    "wof:name":"NE70 7NG",
    "wof:placetype":"postalcode"
},
  "geometry": {"coordinates":[-1.8286021961125,55.59809918216722],"type":"Point"}
}