{
  "type": "Feature",
  "properties": {
    "date:inception_lower":"2007-05-01",
    "date:inception_upper":"2007-05-31",
    "iso:country":"GB",
    "wof:name":"CB7 4GQ",
    "wof:placetype":"postalcode"
},
  "geometry": {"coordinates":[0.280883,52.407269],"type":"Point"}
}