{
  "type": "Feature",
  "properties": {
    "iso:country": "GB",
    "wof:name": "EH5 1BT",
    "wof:placetype": "postalcode"
  },
  "geometry": {"coordinates":[-3.252791,55.97639],"type":"Point"}
}
