{
  "type": "Feature",
  "properties": {
    "iso:country":"GB",
    "wof:name":"NN3 5DB",
    "wof:placetype":"postalcode"
},
  "geometry": {"coordinates":[-0.82555228040453,52.27854493093348],"type":"Point"}
}