{
  "type": "Feature",
  "properties": {
    "date:inception_lower": "1994-12-01",
    "date:inception_upper": "1994-12-01",
    "iso:country": "GB",
    "wof:name": "SO19 6LX",
    "wof:placetype": "postalcode"
  },
  "geometry": {"coordinates":[-1.335849,50.903847],"type":"Point"}
}
