{
  "type": "Feature",
  "properties": {
    "iso:country":"GB",
    "wof:name":"LE7 1NZ",
    "wof:placetype":"postalcode"
},
  "geometry": {"coordinates":[-1.0837667799252,52.6938869079742],"type":"Point"}
}