{
  "type": "Feature",
  "properties": {
    "iso:country":"GB",
    "wof:name":"HG3 2TZ",
    "wof:placetype":"postalcode"
},
  "geometry": {"coordinates":[-1.55771600383546,54.00422490584271],"type":"Point"}
}