{
  "type": "Feature",
  "properties": {
    "iso:country":"GB",
    "wof:name":"CV6 1DD",
    "wof:placetype":"postalcode"
},
  "geometry": {"coordinates":[-1.53558701394902,52.41834180433812],"type":"Point"}
}