{
  "type": "Feature",
  "properties": {
    "iso:country": "GB",
    "wof:name": "CV6 1DD",
    "wof:placetype": "postalcode"
  },
  "geometry": {"coordinates":[-1.535587,52.418342],"type":"Point"}
}
