{
  "type": "Feature",
  "properties": {
    "iso:country":"GB",
    "wof:name":"PL8 1DH",
    "wof:placetype":"postalcode"
},
  "geometry": {"coordinates":[-4.04118213720729,50.31564229001093],"type":"Point"}
}