{
  "type": "Feature",
  "properties": {
    "date:inception_lower": "1985-10-01",
    "date:inception_upper": "1985-10-01",
    "iso:country": "GB",
    "wof:name": "HP1 3DL",
    "wof:placetype": "postalcode"
  },
  "geometry": {"coordinates":[-0.481904,51.770783],"type":"Point"}
}
