{
  "type": "Feature",
  "properties": {
    "iso:country":"GB",
    "wof:name":"HP1 3DL",
    "wof:placetype":"postalcode"
},
  "geometry": {"coordinates":[-0.47870107717072,51.76626470298989],"type":"Point"}
}