{
  "type": "Feature",
  "properties": {
    "iso:country":"GB",
    "wof:name":"SA62 3TA",
    "wof:placetype":"postalcode"
},
  "geometry": {"coordinates":[-5.13284728087555,51.72136954985271],"type":"Point"}
}