{
  "type": "Feature",
  "properties": {
    "date:inception_lower": "1980-01-01",
    "date:inception_upper": "1980-01-01",
    "iso:country": "GB",
    "wof:name": "SA62 3TA",
    "wof:placetype": "postalcode"
  },
  "geometry": {"coordinates":[-5.132847,51.72137],"type":"Point"}
}
