{
  "type": "Feature",
  "properties": {
    "iso:country":"GB",
    "wof:name":"SO50 6DJ",
    "wof:placetype":"postalcode"
},
  "geometry": {"coordinates":[-1.33733177759923,50.97571430794955],"type":"Point"}
}