{
  "type": "Feature",
  "properties": {
    "iso:country": "GB",
    "wof:name": "PE33 9XW",
    "wof:placetype": "postalcode"
  },
  "geometry": {"coordinates":[0.507232,52.573643],"type":"Point"}
}
