{
  "type": "Feature",
  "properties": {
    "iso:country":"GB",
    "wof:name":"IP6 8AE",
    "wof:placetype":"postalcode"
},
  "geometry": {"coordinates":[1.05069892622851,52.15559296101733],"type":"Point"}
}