{
  "type": "Feature",
  "properties": {
    "date:inception_lower": "1980-01-01",
    "date:inception_upper": "1980-01-01",
    "iso:country": "GB",
    "wof:name": "L11 0DE",
    "wof:placetype": "postalcode"
  },
  "geometry": {"coordinates":[-2.897454,53.460018],"type":"Point"}
}
