{
  "type": "Feature",
  "properties": {
    "iso:country":"GB",
    "wof:name":"PO7 8JS",
    "wof:placetype":"postalcode"
},
  "geometry": {"coordinates":[-1.01468670688634,50.88198411750215],"type":"Point"}
}