{
  "type": "Feature",
  "properties": {
    "iso:country":"GB",
    "wof:name":"HD8 9AS",
    "wof:placetype":"postalcode"
},
  "geometry": {"coordinates":[-1.65956533351462,53.5921507598431],"type":"Point"}
}