{
  "type": "Feature",
  "properties": {
    "iso:country": "GB",
    "wof:name": "ME13 9LL",
    "wof:placetype": "postalcode"
  },
  "geometry": {"coordinates":[0.989569,51.290766],"type":"Point"}
}
