{
  "type": "Feature",
  "properties": {
    "date:inception_lower": "1980-01-01",
    "date:inception_upper": "1980-01-01",
    "iso:country": "GB",
    "wof:name": "ME13 9LL",
    "wof:placetype": "postalcode"
  },
  "geometry": {"coordinates":[0.989655,51.290989],"type":"Point"}
}
