{
  "type": "Feature",
  "properties": {
    "iso:country":"GB",
    "wof:name":"ME13 9LL",
    "wof:placetype":"postalcode"
},
  "geometry": {"coordinates":[0.98962473364019,51.29098549764083],"type":"Point"}
}