{
  "type": "Feature",
  "properties": {
    "date:inception_lower":"1980-01-01",
    "date:inception_upper":"1980-01-31",
    "iso:country":"GB",
    "wof:name":"SM1 3HN",
    "wof:placetype":"postalcode"
},
  "geometry": {"coordinates":[-0.197488,51.374997],"type":"Point"}
}