{
  "type": "Feature",
  "properties": {
    "iso:country":"GB",
    "wof:name":"SM1 3HN",
    "wof:placetype":"postalcode"
},
  "geometry": {"coordinates":[-0.19748782681375,51.37499658561921],"type":"Point"}
}