{
  "type": "Feature",
  "properties": {
    "iso:country":"GB",
    "wof:name":"BA1 1HL",
    "wof:placetype":"postalcode"
},
  "geometry": {"coordinates":[-2.36388049238084,51.38242900601851],"type":"Point"}
}