{
  "type": "Feature",
  "properties": {
    "iso:country":"GB",
    "wof:name":"NR30 3JD",
    "wof:placetype":"postalcode"
},
  "geometry": {"coordinates":[1.73506673984151,52.60030588908813],"type":"Point"}
}