{
  "type": "Feature",
  "properties": {
    "iso:country":"GB",
    "wof:name":"TR26 2RT",
    "wof:placetype":"postalcode"
},
  "geometry": {"coordinates":[-5.46990610694496,50.19531086302329],"type":"Point"}
}