{
  "type": "Feature",
  "properties": {
    "iso:country": "GB",
    "wof:name": "AB51 0RY",
    "wof:placetype": "postalcode"
  },
  "geometry": {"coordinates":[-2.34477,57.237544],"type":"Point"}
}
