{
  "type": "Feature",
  "properties": {
    "date:inception_lower":"2006-08-01",
    "date:inception_upper":"2006-08-31",
    "iso:country":"GB",
    "wof:name":"AB51 0RY",
    "wof:placetype":"postalcode"
},
  "geometry": {"coordinates":[-2.34477,57.237544],"type":"Point"}
}