{
  "type": "Feature",
  "properties": {
    "iso:country": "GB",
    "wof:name": "SE23 1BB",
    "wof:placetype": "postalcode"
  },
  "geometry": {"coordinates":[-0.044264,51.444427],"type":"Point"}
}
