{
  "type": "Feature",
  "properties": {
    "date:inception_lower": "1980-01-01",
    "date:inception_upper": "1980-01-01",
    "iso:country": "GB",
    "wof:name": "SE23 1BB",
    "wof:placetype": "postalcode"
  },
  "geometry": {"coordinates":[-0.044264,51.444427],"type":"Point"}
}
