{
  "type": "Feature",
  "properties": {
    "iso:country":"GB",
    "wof:name":"SE23 1BB",
    "wof:placetype":"postalcode"
},
  "geometry": {"coordinates":[-0.04436187595324,51.4447524450219],"type":"Point"}
}