{
  "type": "Feature",
  "properties": {
    "iso:country":"GB",
    "wof:name":"KY6 3NZ",
    "wof:placetype":"postalcode"
},
  "geometry": {"coordinates":[-3.198509281878,56.21111328666269],"type":"Point"}
}