{
  "type": "Feature",
  "properties": {
    "iso:country": "GB",
    "wof:name": "KY6 3NZ",
    "wof:placetype": "postalcode"
  },
  "geometry": {"coordinates":[-3.198509,56.211113],"type":"Point"}
}
