{
  "type": "Feature",
  "properties": {
    "date:inception_lower":"2006-09-01",
    "date:inception_upper":"2006-09-30",
    "iso:country":"GB",
    "wof:name":"KY6 3NZ",
    "wof:placetype":"postalcode"
},
  "geometry": {"coordinates":[-3.198509,56.211113],"type":"Point"}
}