{
  "type": "Feature",
  "properties": {
    "iso:country": "GB",
    "wof:name": "HA8 5SL",
    "wof:placetype": "postalcode"
  },
  "geometry": {"coordinates":[-0.276073,51.601708],"type":"Point"}
}
