{
  "type": "Feature",
  "properties": {
    "date:inception_lower": "2004-05-01",
    "date:inception_upper": "2004-05-01",
    "iso:country": "GB",
    "wof:name": "MK8 0PR",
    "wof:placetype": "postalcode"
  },
  "geometry": {"coordinates":[-0.814052,52.023582],"type":"Point"}
}
