{
  "type": "Feature",
  "properties": {
    "iso:country":"GB",
    "wof:name":"MK8 0PR",
    "wof:placetype":"postalcode"
},
  "geometry": {"coordinates":[-0.8140523095615,52.02358194198541],"type":"Point"}
}