{
  "type": "Feature",
  "properties": {
    "iso:country": "GB",
    "wof:name": "MK8 0PR",
    "wof:placetype": "postalcode"
  },
  "geometry": {"coordinates":[-0.814052,52.023582],"type":"Point"}
}
