{
  "type": "Feature",
  "properties": {
    "iso:country":"GB",
    "wof:name":"TQ14 0BH",
    "wof:placetype":"postalcode"
},
  "geometry": {"coordinates":[-3.50191503994519,50.53820007532817],"type":"Point"}
}