{
  "type": "Feature",
  "properties": {
    "date:inception_lower":"2016-04-01",
    "date:inception_upper":"2016-04-30",
    "iso:country":"GB",
    "wof:name":"B73 9YW",
    "wof:placetype":"postalcode"
},
  "geometry": {"coordinates":[-1.829167,52.568642],"type":"Point"}
}