{
  "type": "Feature",
  "properties": {
    "iso:country":"GB",
    "wof:name":"HU17 7NS",
    "wof:placetype":"postalcode"
},
  "geometry": {"coordinates":[-0.42414134867045,53.88459788145245],"type":"Point"}
}