{
  "type": "Feature",
  "properties": {
    "iso:country": "GB",
    "wof:name": "HU17 7NS",
    "wof:placetype": "postalcode"
  },
  "geometry": {"coordinates":[-0.424141,53.884598],"type":"Point"}
}
