{
  "type": "Feature",
  "properties": {
    "iso:country": "GB",
    "wof:name": "PO18 0HP",
    "wof:placetype": "postalcode"
  },
  "geometry": {"coordinates":[-0.750153,50.911799],"type":"Point"}
}
