{
  "type": "Feature",
  "properties": {
    "iso:country":"GB",
    "wof:name":"PO18 0HP",
    "wof:placetype":"postalcode"
},
  "geometry": {"coordinates":[-0.75015267427343,50.91179909954221],"type":"Point"}
}