{
  "type": "Feature",
  "properties": {
    "iso:country":"GB",
    "wof:name":"TQ7 1HJ",
    "wof:placetype":"postalcode"
},
  "geometry": {"coordinates":[-3.78033378266056,50.27946644696681],"type":"Point"}
}