{
  "type": "Feature",
  "properties": {
    "iso:country": "GB",
    "wof:name": "TQ7 1HJ",
    "wof:placetype": "postalcode"
  },
  "geometry": {"coordinates":[-3.780334,50.279466],"type":"Point"}
}
