{
  "type": "Feature",
  "properties": {
    "date:inception_lower":"1980-01-01",
    "date:inception_upper":"1980-01-31",
    "iso:country":"GB",
    "wof:name":"GL1 3BY",
    "wof:placetype":"postalcode"
},
  "geometry": {"coordinates":[-2.23884,51.869108],"type":"Point"}
}