{
  "type": "Feature",
  "properties": {
    "iso:country":"GB",
    "wof:name":"CT5 4DG",
    "wof:placetype":"postalcode"
},
  "geometry": {"coordinates":[1.0095173975294,51.34857069658648],"type":"Point"}
}