{
  "type": "Feature",
  "properties": {
    "iso:country":"GB",
    "wof:name":"BA6 9FG",
    "wof:placetype":"postalcode"
},
  "geometry": {"coordinates":[-2.72097235491083,51.15068850270751],"type":"Point"}
}