{
  "type": "Feature",
  "properties": {
    "iso:country": "GB",
    "wof:name": "BN10 8FW",
    "wof:placetype": "postalcode"
  },
  "geometry": {"coordinates":[0.009445,50.799995],"type":"Point"}
}
