{
  "type": "Feature",
  "properties": {
    "date:inception_lower": "2019-11-01",
    "date:inception_upper": "2019-11-01",
    "iso:country": "GB",
    "wof:name": "BN10 8FW",
    "wof:placetype": "postalcode"
  },
  "geometry": {"coordinates":[0.009688,50.800036],"type":"Point"}
}
