{
  "type": "Feature",
  "properties": {
    "iso:country":"GB",
    "wof:name":"YO42 4LG",
    "wof:placetype":"postalcode"
},
  "geometry": {"coordinates":[-0.74539454527055,53.84959959753448],"type":"Point"}
}