{
  "type": "Feature",
  "properties": {
    "date:inception_lower": "1998-06-01",
    "date:inception_upper": "1998-06-01",
    "iso:country": "GB",
    "wof:name": "YO42 4LG",
    "wof:placetype": "postalcode"
  },
  "geometry": {"coordinates":[-0.745145,53.849536],"type":"Point"}
}
