{
  "type": "Feature",
  "properties": {
    "iso:country": "GB",
    "wof:name": "YO42 4LG",
    "wof:placetype": "postalcode"
  },
  "geometry": {"coordinates":[-0.743621,53.850671],"type":"Point"}
}
