{
  "type": "Feature",
  "properties": {
    "iso:country": "GB",
    "wof:name": "WR14 1TT",
    "wof:placetype": "postalcode"
  },
  "geometry": {"coordinates":[-2.32049,52.133573],"type":"Point"}
}
