{
  "type": "Feature",
  "properties": {
    "iso:country":"GB",
    "wof:name":"PE19 6GU",
    "wof:placetype":"postalcode"
},
  "geometry": {"coordinates":[-0.24489760749149,52.22964934438565],"type":"Point"}
}