{
  "type": "Feature",
  "properties": {
    "date:inception_lower": "2011-05-01",
    "date:inception_upper": "2011-05-01",
    "iso:country": "GB",
    "wof:name": "PE19 6GU",
    "wof:placetype": "postalcode"
  },
  "geometry": {"coordinates":[-0.244898,52.229649],"type":"Point"}
}
