{
  "type": "Feature",
  "properties": {
    "iso:country":"GB",
    "wof:name":"HS1 2HL",
    "wof:placetype":"postalcode"
},
  "geometry": {"coordinates":[-6.38295594614453,58.21730677829716],"type":"Point"}
}