{
  "type": "Feature",
  "properties": {
    "date:inception_lower":"1980-01-01",
    "date:inception_upper":"1980-01-31",
    "iso:country":"GB",
    "wof:name":"LL65 1PG",
    "wof:placetype":"postalcode"
},
  "geometry": {"coordinates":[-4.647477,53.310707],"type":"Point"}
}