{
  "type": "Feature",
  "properties": {
    "iso:country":"GB",
    "wof:name":"LE4 6RT",
    "wof:placetype":"postalcode"
},
  "geometry": {"coordinates":[-1.10750785701769,52.65431441319976],"type":"Point"}
}