{
  "type": "Feature",
  "properties": {
    "iso:country": "GB",
    "wof:name": "OX1 5JJ",
    "wof:placetype": "postalcode"
  },
  "geometry": {"coordinates":[-1.301186,51.713015],"type":"Point"}
}
