{
  "type": "Feature",
  "properties": {
    "iso:country":"GB",
    "wof:name":"OX1 5JJ",
    "wof:placetype":"postalcode"
},
  "geometry": {"coordinates":[-1.3011858326711,51.71301533092299],"type":"Point"}
}