{
  "type": "Feature",
  "properties": {
    "iso:country":"GB",
    "wof:name":"TS5 5BP",
    "wof:placetype":"postalcode"
},
  "geometry": {"coordinates":[-1.25639799147011,54.55838957350888],"type":"Point"}
}