{
  "type": "Feature",
  "properties": {
    "iso:country": "GB",
    "wof:name": "BH12 1HX",
    "wof:placetype": "postalcode"
  },
  "geometry": {"coordinates":[-1.904126,50.72937],"type":"Point"}
}
