{
  "type": "Feature",
  "properties": {
    "iso:country": "GB",
    "wof:name": "TS18 3QS",
    "wof:placetype": "postalcode"
  },
  "geometry": {"coordinates":[-1.328604,54.550187],"type":"Point"}
}
