{
  "type": "Feature",
  "properties": {
    "date:inception_lower": "2012-04-01",
    "date:inception_upper": "2012-04-01",
    "iso:country": "GB",
    "wof:name": "TS18 3QS",
    "wof:placetype": "postalcode"
  },
  "geometry": {"coordinates":[-1.327576,54.550622],"type":"Point"}
}
