{
  "type": "Feature",
  "properties": {
    "date:inception_lower":"2012-04-01",
    "date:inception_upper":"2012-04-30",
    "iso:country":"GB",
    "wof:name":"TS18 3QS",
    "wof:placetype":"postalcode"
},
  "geometry": {"coordinates":[-1.328604,54.550187],"type":"Point"}
}