{
  "type": "Feature",
  "properties": {
    "iso:country":"GB",
    "wof:name":"LS6 3BN",
    "wof:placetype":"postalcode"
},
  "geometry": {"coordinates":[-1.57732877410794,53.81488523357829],"type":"Point"}
}