{
  "type": "Feature",
  "properties": {
    "iso:country":"GB",
    "wof:name":"SA4 8TJ",
    "wof:placetype":"postalcode"
},
  "geometry": {"coordinates":[-4.04533468282885,51.71652569880926],"type":"Point"}
}