{
  "type": "Feature",
  "properties": {
    "date:inception_lower": "1980-01-01",
    "date:inception_upper": "1980-01-01",
    "iso:country": "GB",
    "wof:name": "SA39 9ET",
    "wof:placetype": "postalcode"
  },
  "geometry": {"coordinates":[-4.263426,52.000692],"type":"Point"}
}
