{
  "type": "Feature",
  "properties": {
    "iso:country":"GB",
    "wof:name":"SA39 9ET",
    "wof:placetype":"postalcode"
},
  "geometry": {"coordinates":[-4.26342569007438,52.0006919369067],"type":"Point"}
}