{
  "type": "Feature",
  "properties": {
    "iso:country":"GB",
    "wof:name":"WA8 7EQ",
    "wof:placetype":"postalcode"
},
  "geometry": {"coordinates":[-2.73923342767456,53.36978562744952],"type":"Point"}
}