{
  "type": "Feature",
  "properties": {
    "date:inception_lower":"1980-01-01",
    "date:inception_upper":"1980-01-31",
    "iso:country":"GB",
    "wof:name":"WA8 7EQ",
    "wof:placetype":"postalcode"
},
  "geometry": {"coordinates":[-2.739233,53.369786],"type":"Point"}
}