{
  "type": "Feature",
  "properties": {
    "iso:country": "GB",
    "wof:name": "G71 7DU",
    "wof:placetype": "postalcode"
  },
  "geometry": {"coordinates":[-4.089725,55.824616],"type":"Point"}
}
