{
  "type": "Feature",
  "properties": {
    "iso:country":"GB",
    "wof:name":"G71 7DU",
    "wof:placetype":"postalcode"
},
  "geometry": {"coordinates":[-4.08972546402689,55.82461624538407],"type":"Point"}
}