{
  "type": "Feature",
  "properties": {
    "iso:country": "GB",
    "wof:name": "TN27 0DF",
    "wof:placetype": "postalcode"
  },
  "geometry": {"coordinates":[0.807415,51.194467],"type":"Point"}
}
