{
  "type": "Feature",
  "properties": {
    "iso:country":"GB",
    "wof:name":"TN27 0DF",
    "wof:placetype":"postalcode"
},
  "geometry": {"coordinates":[0.80741447190401,51.19446719586806],"type":"Point"}
}