{
  "type": "Feature",
  "properties": {
    "iso:country":"GB",
    "wof:name":"BA16 0SE",
    "wof:placetype":"postalcode"
},
  "geometry": {"coordinates":[-2.7363757109072,51.12046869283174],"type":"Point"}
}