{
  "type": "Feature",
  "properties": {
    "iso:country":"GB",
    "wof:name":"WV10 7JL",
    "wof:placetype":"postalcode"
},
  "geometry": {"coordinates":[-2.07988660297708,52.6543377441885],"type":"Point"}
}