{
  "type": "Feature",
  "properties": {
    "date:inception_lower": "1987-04-01",
    "date:inception_upper": "1987-04-01",
    "iso:country": "GB",
    "wof:name": "WV10 7JL",
    "wof:placetype": "postalcode"
  },
  "geometry": {"coordinates":[-2.079887,52.654338],"type":"Point"}
}
