{
  "type": "Feature",
  "properties": {
    "iso:country": "GB",
    "wof:name": "WV10 7JL",
    "wof:placetype": "postalcode"
  },
  "geometry": {"coordinates":[-2.079887,52.654338],"type":"Point"}
}
