{
  "type": "Feature",
  "properties": {
    "iso:country":"GB",
    "wof:name":"FK6 6JQ",
    "wof:placetype":"postalcode"
},
  "geometry": {"coordinates":[-3.91345726711944,56.02527270028902],"type":"Point"}
}