{
  "type": "Feature",
  "properties": {
    "iso:country":"GB",
    "wof:name":"CV1 5EX",
    "wof:placetype":"postalcode"
},
  "geometry": {"coordinates":[-1.50828541597178,52.40880082456558],"type":"Point"}
}