{
  "type": "Feature",
  "properties": {
    "iso:country":"GB",
    "wof:name":"B90 4PT",
    "wof:placetype":"postalcode"
},
  "geometry": {"coordinates":[-1.81294959710051,52.39898543148361],"type":"Point"}
}