{
  "type": "Feature",
  "properties": {
    "date:inception_lower": "2022-03-01",
    "date:inception_upper": "2022-03-01",
    "iso:country": "GB",
    "wof:name": "CA14 1DY",
    "wof:placetype": "postalcode"
  },
  "geometry": {"coordinates":[-3.514052,54.648397],"type":"Point"}
}
