{
  "type": "Feature",
  "properties": {
    "iso:country": "GB",
    "wof:name": "BH20 5JN",
    "wof:placetype": "postalcode"
  },
  "geometry": {"coordinates":[-2.003655,50.669662],"type":"Point"}
}
