{
  "type": "Feature",
  "properties": {
    "iso:country":"GB",
    "wof:name":"SK9 7QB",
    "wof:placetype":"postalcode"
},
  "geometry": {"coordinates":[-2.23742079632787,53.30494581232544],"type":"Point"}
}