{
  "type": "Feature",
  "properties": {
    "iso:country":"GB",
    "wof:name":"BN20 7LE",
    "wof:placetype":"postalcode"
},
  "geometry": {"coordinates":[0.27302315171913,50.75713414157462],"type":"Point"}
}