{
  "type": "Feature",
  "properties": {
    "iso:country": "GB",
    "wof:name": "BN20 7LE",
    "wof:placetype": "postalcode"
  },
  "geometry": {"coordinates":[0.273023,50.757134],"type":"Point"}
}
