{
  "type": "Feature",
  "properties": {
    "iso:country":"GB",
    "wof:name":"WF2 0NH",
    "wof:placetype":"postalcode"
},
  "geometry": {"coordinates":[-1.52748153546373,53.69997513455478],"type":"Point"}
}