{
  "type": "Feature",
  "properties": {
    "date:inception_lower": "1980-01-01",
    "date:inception_upper": "1980-01-01",
    "iso:country": "GB",
    "wof:name": "PL1 5EH",
    "wof:placetype": "postalcode"
  },
  "geometry": {"coordinates":[-4.152559,50.374354],"type":"Point"}
}
