{
  "type": "Feature",
  "properties": {
    "iso:country":"GB",
    "wof:name":"PL1 5EH",
    "wof:placetype":"postalcode"
},
  "geometry": {"coordinates":[-4.15255886397545,50.37435396229804],"type":"Point"}
}