{
  "type": "Feature",
  "properties": {
    "iso:country":"GB",
    "wof:name":"WS10 0BN",
    "wof:placetype":"postalcode"
},
  "geometry": {"coordinates":[-2.01095787603542,52.54868954493172],"type":"Point"}
}