{
  "type": "Feature",
  "properties": {
    "date:inception_lower": "1980-01-01",
    "date:inception_upper": "1980-01-01",
    "iso:country": "GB",
    "wof:name": "EX36 4HR",
    "wof:placetype": "postalcode"
  },
  "geometry": {"coordinates":[-3.876531,51.013055],"type":"Point"}
}
