{
  "type": "Feature",
  "properties": {
    "iso:country":"GB",
    "wof:name":"EX36 4HR",
    "wof:placetype":"postalcode"
},
  "geometry": {"coordinates":[-3.87653091800536,51.01305497406715],"type":"Point"}
}