{
  "type": "Feature",
  "properties": {
    "iso:country":"GB",
    "wof:name":"G53 7ER",
    "wof:placetype":"postalcode"
},
  "geometry": {"coordinates":[-4.35644900769864,55.82912267544004],"type":"Point"}
}