{
  "type": "Feature",
  "properties": {
    "iso:country":"GB",
    "wof:name":"BS41 8LU",
    "wof:placetype":"postalcode"
},
  "geometry": {"coordinates":[-2.64935929754865,51.39685781228325],"type":"Point"}
}