{
  "type": "Feature",
  "properties": {
    "date:inception_lower": "1984-02-01",
    "date:inception_upper": "1984-02-01",
    "iso:country": "GB",
    "wof:name": "SL4 1YA",
    "wof:placetype": "postalcode"
  },
  "geometry": {"coordinates":[-0.606314,51.479621],"type":"Point"}
}
