{
  "type": "Feature",
  "properties": {
    "iso:country": "GB",
    "wof:name": "SL4 1YA",
    "wof:placetype": "postalcode"
  },
  "geometry": {"coordinates":[-0.606314,51.479621],"type":"Point"}
}
