{
  "type": "Feature",
  "properties": {
    "iso:country": "GB",
    "wof:name": "RG21 3DP",
    "wof:placetype": "postalcode"
  },
  "geometry": {"coordinates":[-1.087232,51.259803],"type":"Point"}
}
