{
  "type": "Feature",
  "properties": {
    "iso:country":"GB",
    "wof:name":"RG21 3DP",
    "wof:placetype":"postalcode"
},
  "geometry": {"coordinates":[-1.08723245030837,51.25980350483335],"type":"Point"}
}