{
  "type": "Feature",
  "properties": {
    "iso:country":"GB",
    "wof:name":"B31 5QP",
    "wof:placetype":"postalcode"
},
  "geometry": {"coordinates":[-1.99441338644555,52.41236624861882],"type":"Point"}
}