{
  "type": "Feature",
  "properties": {
    "date:inception_lower":"1980-01-01",
    "date:inception_upper":"1980-01-31",
    "iso:country":"GB",
    "wof:name":"B31 5QP",
    "wof:placetype":"postalcode"
},
  "geometry": {"coordinates":[-1.994413,52.412366],"type":"Point"}
}