{
  "type": "Feature",
  "properties": {
    "date:inception_lower": "1995-01-01",
    "date:inception_upper": "1995-01-01",
    "iso:country": "GB",
    "wof:name": "SS3 8BT",
    "wof:placetype": "postalcode"
  },
  "geometry": {"coordinates":[0.787721,51.543303],"type":"Point"}
}
