{
  "type": "Feature",
  "properties": {
    "iso:country":"GB",
    "wof:name":"NN14 4NU",
    "wof:placetype":"postalcode"
},
  "geometry": {"coordinates":[-0.5289146499768,52.3979484762805],"type":"Point"}
}