{
  "type": "Feature",
  "properties": {
    "iso:country":"GB",
    "wof:name":"HU9 1TA",
    "wof:placetype":"postalcode"
},
  "geometry": {"coordinates":[-0.29071047558235,53.74561573674496],"type":"Point"}
}