{
  "type": "Feature",
  "properties": {
    "date:inception_lower": "1980-01-01",
    "date:inception_upper": "1980-01-01",
    "iso:country": "GB",
    "wof:name": "BD3 9DS",
    "wof:placetype": "postalcode"
  },
  "geometry": {"coordinates":[-1.734262,53.796362],"type":"Point"}
}
