{
  "type": "Feature",
  "properties": {
    "iso:country":"GB",
    "wof:name":"BD3 9DS",
    "wof:placetype":"postalcode"
},
  "geometry": {"coordinates":[-1.73426157140213,53.79636158684548],"type":"Point"}
}