{
  "type": "Feature",
  "properties": {
    "iso:country": "GB",
    "wof:name": "BD3 9DS",
    "wof:placetype": "postalcode"
  },
  "geometry": {"coordinates":[-1.734262,53.796362],"type":"Point"}
}
