{
  "type": "Feature",
  "properties": {
    "date:inception_lower":"1980-01-01",
    "date:inception_upper":"1980-01-31",
    "iso:country":"GB",
    "wof:name":"BN14 7RU",
    "wof:placetype":"postalcode"
},
  "geometry": {"coordinates":[-0.380996,50.825129],"type":"Point"}
}