{
  "type": "Feature",
  "properties": {
    "iso:country":"GB",
    "wof:name":"BN14 7RU",
    "wof:placetype":"postalcode"
},
  "geometry": {"coordinates":[-0.38099609928467,50.82512923370635],"type":"Point"}
}