{
  "type": "Feature",
  "properties": {
    "iso:country":"GB",
    "wof:name":"OX1 2LA",
    "wof:placetype":"postalcode"
},
  "geometry": {"coordinates":[-1.26027634933686,51.75685821649469],"type":"Point"}
}