{
  "type": "Feature",
  "properties": {
    "iso:country":"GB",
    "wof:name":"HU19 2LS",
    "wof:placetype":"postalcode"
},
  "geometry": {"coordinates":[0.03212046126121,53.72375631900611],"type":"Point"}
}