{
  "type": "Feature",
  "properties": {
    "date:inception_lower": "1980-01-01",
    "date:inception_upper": "1980-01-01",
    "iso:country": "GB",
    "wof:name": "HU19 2LS",
    "wof:placetype": "postalcode"
  },
  "geometry": {"coordinates":[0.032121,53.723756],"type":"Point"}
}
