{
  "type": "Feature",
  "properties": {
    "iso:country":"GB",
    "wof:name":"SG12 9EY",
    "wof:placetype":"postalcode"
},
  "geometry": {"coordinates":[-0.0349132255213,51.79905113147802],"type":"Point"}
}