{
  "type": "Feature",
  "properties": {
    "date:inception_lower": "2002-08-01",
    "date:inception_upper": "2002-08-01",
    "iso:country": "GB",
    "wof:name": "SG12 9EY",
    "wof:placetype": "postalcode"
  },
  "geometry": {"coordinates":[-0.034913,51.799051],"type":"Point"}
}
