{
  "type": "Feature",
  "properties": {
    "date:inception_lower": "2020-06-01",
    "date:inception_upper": "2020-06-01",
    "iso:country": "GB",
    "wof:name": "EX20 2FH",
    "wof:placetype": "postalcode"
  },
  "geometry": {"coordinates":[-3.898056,50.795005],"type":"Point"}
}
