{
  "type": "Feature",
  "properties": {
    "date:inception_lower": "1980-01-01",
    "date:inception_upper": "1980-01-01",
    "iso:country": "GB",
    "wof:name": "S75 4HT",
    "wof:placetype": "postalcode"
  },
  "geometry": {"coordinates":[-1.569,53.569163],"type":"Point"}
}
