{
  "type": "Feature",
  "properties": {
    "iso:country":"GB",
    "wof:name":"S75 4HT",
    "wof:placetype":"postalcode"
},
  "geometry": {"coordinates":[-1.56900001170687,53.56916342291516],"type":"Point"}
}