{
  "type": "Feature",
  "properties": {
    "iso:country":"GB",
    "wof:name":"KA7 1NW",
    "wof:placetype":"postalcode"
},
  "geometry": {"coordinates":[-4.6334796950792,55.4621029171759],"type":"Point"}
}