{
  "type": "Feature",
  "properties": {
    "iso:country":"GB",
    "wof:name":"GL56 9NZ",
    "wof:placetype":"postalcode"
},
  "geometry": {"coordinates":[-1.65462003019202,52.0189730843083],"type":"Point"}
}