{
  "type": "Feature",
  "properties": {
    "iso:country": "GB",
    "wof:name": "GL56 9NZ",
    "wof:placetype": "postalcode"
  },
  "geometry": {"coordinates":[-1.65462,52.018973],"type":"Point"}
}
