{
  "type": "Feature",
  "properties": {
    "date:inception_lower": "1983-07-01",
    "date:inception_upper": "1983-07-01",
    "iso:country": "GB",
    "wof:name": "TN38 0YL",
    "wof:placetype": "postalcode"
  },
  "geometry": {"coordinates":[0.549017,50.853688],"type":"Point"}
}
