{
  "type": "Feature",
  "properties": {
    "iso:country": "GB",
    "wof:name": "TN38 0YL",
    "wof:placetype": "postalcode"
  },
  "geometry": {"coordinates":[0.54901,50.853571],"type":"Point"}
}
