{
  "type": "Feature",
  "properties": {
    "iso:country": "GB",
    "wof:name": "NE28 0AB",
    "wof:placetype": "postalcode"
  },
  "geometry": {"coordinates":[-1.495571,54.997889],"type":"Point"}
}
