{
  "type": "Feature",
  "properties": {
    "date:inception_lower": "1995-07-01",
    "date:inception_upper": "1995-07-01",
    "iso:country": "GB",
    "wof:name": "TQ5 9TD",
    "wof:placetype": "postalcode"
  },
  "geometry": {"coordinates":[-3.503966,50.396686],"type":"Point"}
}
