{
  "type": "Feature",
  "properties": {
    "iso:country": "GB",
    "wof:name": "CR0 6BY",
    "wof:placetype": "postalcode"
  },
  "geometry": {"coordinates":[-0.081272,51.388466],"type":"Point"}
}
