{
  "type": "Feature",
  "properties": {
    "iso:country": "GB",
    "wof:name": "LS21 2EQ",
    "wof:placetype": "postalcode"
  },
  "geometry": {"coordinates":[-1.711324,53.915542],"type":"Point"}
}
