{
  "type": "Feature",
  "properties": {
    "iso:country":"GB",
    "wof:name":"LS21 2EQ",
    "wof:placetype":"postalcode"
},
  "geometry": {"coordinates":[-1.71132420352937,53.91554213027493],"type":"Point"}
}