{
  "type": "Feature",
  "properties": {
    "iso:country":"GB",
    "wof:name":"CM0 7QX",
    "wof:placetype":"postalcode"
},
  "geometry": {"coordinates":[0.88868643840513,51.73379588813257],"type":"Point"}
}