{
  "type": "Feature",
  "properties": {
    "date:inception_lower": "1991-09-01",
    "date:inception_upper": "1991-09-01",
    "iso:country": "GB",
    "wof:name": "HU5 5GA",
    "wof:placetype": "postalcode"
  },
  "geometry": {"coordinates":[-0.394364,53.756299],"type":"Point"}
}
