{
  "type": "Feature",
  "properties": {
    "iso:country":"GB",
    "wof:name":"HU5 5GA",
    "wof:placetype":"postalcode"
},
  "geometry": {"coordinates":[-0.39436394362548,53.75629896350522],"type":"Point"}
}