{
  "type": "Feature",
  "properties": {
    "iso:country":"GB",
    "wof:name":"DN8 4NG",
    "wof:placetype":"postalcode"
},
  "geometry": {"coordinates":[-0.9482276850155,53.63577982069015],"type":"Point"}
}