{
  "type": "Feature",
  "properties": {
    "iso:country": "GB",
    "wof:name": "DN8 4NG",
    "wof:placetype": "postalcode"
  },
  "geometry": {"coordinates":[-0.948228,53.63578],"type":"Point"}
}
