{
  "type": "Feature",
  "properties": {
    "iso:country":"GB",
    "wof:name":"SA11 1AX",
    "wof:placetype":"postalcode"
},
  "geometry": {"coordinates":[-3.80119365260366,51.65663388437385],"type":"Point"}
}