{
  "type": "Feature",
  "properties": {
    "iso:country": "GB",
    "wof:name": "BH11 8RU",
    "wof:placetype": "postalcode"
  },
  "geometry": {"coordinates":[-1.909259,50.749446],"type":"Point"}
}
