{
  "type": "Feature",
  "properties": {
    "iso:country":"GB",
    "wof:name":"BH11 8RU",
    "wof:placetype":"postalcode"
},
  "geometry": {"coordinates":[-1.90925908138341,50.74944581422611],"type":"Point"}
}