{
  "type": "Feature",
  "properties": {
    "date:inception_lower":"1986-07-01",
    "date:inception_upper":"1986-07-31",
    "iso:country":"GB",
    "wof:name":"SN5 7XP",
    "wof:placetype":"postalcode"
},
  "geometry": {"coordinates":[-1.814766,51.558939],"type":"Point"}
}