{
  "type": "Feature",
  "properties": {
    "iso:country":"GB",
    "wof:name":"M33 3BZ",
    "wof:placetype":"postalcode"
},
  "geometry": {"coordinates":[-2.31698192468543,53.42191885166099],"type":"Point"}
}