{
  "type": "Feature",
  "properties": {
    "iso:country": "GB",
    "wof:name": "TS24 0JS",
    "wof:placetype": "postalcode"
  },
  "geometry": {"coordinates":[-1.184734,54.697381],"type":"Point"}
}
