{
  "type": "Feature",
  "properties": {
    "iso:country":"GB",
    "wof:name":"TS24 0JS",
    "wof:placetype":"postalcode"
},
  "geometry": {"coordinates":[-1.18470435804955,54.69735233841871],"type":"Point"}
}