{
  "type": "Feature",
  "properties": {
    "iso:country":"GB",
    "wof:name":"G46 6AH",
    "wof:placetype":"postalcode"
},
  "geometry": {"coordinates":[-4.29445651660031,55.81087295420719],"type":"Point"}
}