{
  "type": "Feature",
  "properties": {
    "date:inception_lower": "2017-11-01",
    "date:inception_upper": "2017-11-01",
    "iso:country": "GB",
    "wof:name": "PL6 6FJ",
    "wof:placetype": "postalcode"
  },
  "geometry": {"coordinates":[-4.132226,50.429285],"type":"Point"}
}
