{
  "type": "Feature",
  "properties": {
    "iso:country":"GB",
    "wof:name":"TR26 2FF",
    "wof:placetype":"postalcode"
},
  "geometry": {"coordinates":[-5.47908738070624,50.20939429730195],"type":"Point"}
}