{
  "type": "Feature",
  "properties": {
    "iso:country": "GB",
    "wof:name": "TR26 2FF",
    "wof:placetype": "postalcode"
  },
  "geometry": {"coordinates":[-5.479087,50.209394],"type":"Point"}
}
