{
  "type": "Feature",
  "properties": {
    "date:inception_lower":"2008-03-01",
    "date:inception_upper":"2008-03-31",
    "iso:country":"GB",
    "wof:name":"TR26 2FF",
    "wof:placetype":"postalcode"
},
  "geometry": {"coordinates":[-5.479087,50.209394],"type":"Point"}
}