{
  "type": "Feature",
  "properties": {
    "date:inception_lower": "2008-03-01",
    "date:inception_upper": "2008-03-01",
    "iso:country": "GB",
    "wof:name": "TR26 2FF",
    "wof:placetype": "postalcode"
  },
  "geometry": {"coordinates":[-5.47918,50.209376],"type":"Point"}
}
