{
  "type": "Feature",
  "properties": {
    "iso:country":"GB",
    "wof:name":"SS0 9XU",
    "wof:placetype":"postalcode"
},
  "geometry": {"coordinates":[0.67438135073153,51.54971119583826],"type":"Point"}
}