{
  "type": "Feature",
  "properties": {
    "iso:country":"GB",
    "wof:name":"LS14 6PT",
    "wof:placetype":"postalcode"
},
  "geometry": {"coordinates":[-1.46247804586927,53.8230992759383],"type":"Point"}
}