{
  "type": "Feature",
  "properties": {
    "date:inception_lower": "1995-07-01",
    "date:inception_upper": "1995-07-01",
    "iso:country": "GB",
    "wof:name": "CV1 3HG",
    "wof:placetype": "postalcode"
  },
  "geometry": {"coordinates":[-1.52824,52.408208],"type":"Point"}
}
