{
  "type": "Feature",
  "properties": {
    "iso:country":"GB",
    "wof:name":"SO51 0AG",
    "wof:placetype":"postalcode"
},
  "geometry": {"coordinates":[-1.50001602258808,51.02525283379519],"type":"Point"}
}