{
  "type": "Feature",
  "properties": {
    "iso:country": "GB",
    "wof:name": "SO51 0AG",
    "wof:placetype": "postalcode"
  },
  "geometry": {"coordinates":[-1.500016,51.025253],"type":"Point"}
}
