{
  "type": "Feature",
  "properties": {
    "date:inception_lower": "1991-09-01",
    "date:inception_upper": "1991-09-01",
    "iso:country": "GB",
    "wof:name": "NN8 5FE",
    "wof:placetype": "postalcode"
  },
  "geometry": {"coordinates":[-0.718983,52.316322],"type":"Point"}
}
