{
  "type": "Feature",
  "properties": {
    "iso:country":"GB",
    "wof:name":"NN8 5FE",
    "wof:placetype":"postalcode"
},
  "geometry": {"coordinates":[-0.71898323776829,52.31632230627438],"type":"Point"}
}