{
  "type": "Feature",
  "properties": {
    "iso:country":"GB",
    "wof:name":"GU1 1JF",
    "wof:placetype":"postalcode"
},
  "geometry": {"coordinates":[-0.57870049031422,51.25434795457442],"type":"Point"}
}