{
  "type": "Feature",
  "properties": {
    "iso:country": "GB",
    "wof:name": "PL27 7JZ",
    "wof:placetype": "postalcode"
  },
  "geometry": {"coordinates":[-4.830817,50.506993],"type":"Point"}
}
