{
  "type": "Feature",
  "properties": {
    "iso:country":"GB",
    "wof:name":"PL27 7JZ",
    "wof:placetype":"postalcode"
},
  "geometry": {"coordinates":[-4.83081726402262,50.50699256529014],"type":"Point"}
}