{
  "type": "Feature",
  "properties": {
    "iso:country":"GB",
    "wof:name":"NR3 3UA",
    "wof:placetype":"postalcode"
},
  "geometry": {"coordinates":[1.28099331333257,52.65253102642535],"type":"Point"}
}