{
  "type": "Feature",
  "properties": {
    "iso:country":"GB",
    "wof:name":"KT20 6UY",
    "wof:placetype":"postalcode"
},
  "geometry": {"coordinates":[-0.2034399684611,51.26691477590364],"type":"Point"}
}