{
  "type": "Feature",
  "properties": {
    "iso:country": "GB",
    "wof:name": "KT20 6UY",
    "wof:placetype": "postalcode"
  },
  "geometry": {"coordinates":[-0.20344,51.266915],"type":"Point"}
}
