{
  "type": "Feature",
  "properties": {
    "iso:country":"GB",
    "wof:name":"EX17 4QG",
    "wof:placetype":"postalcode"
},
  "geometry": {"coordinates":[-3.72735286553188,50.88210489445125],"type":"Point"}
}