{
  "type": "Feature",
  "properties": {
    "iso:country": "GB",
    "wof:name": "NG24 2GW",
    "wof:placetype": "postalcode"
  },
  "geometry": {"coordinates":[-0.773289,53.076607],"type":"Point"}
}
