{
  "type": "Feature",
  "properties": {
    "iso:country":"GB",
    "wof:name":"SK10 5JW",
    "wof:placetype":"postalcode"
},
  "geometry": {"coordinates":[-2.10568792095421,53.29600301330433],"type":"Point"}
}