{
  "type": "Feature",
  "properties": {
    "iso:country": "GB",
    "wof:name": "EX2 7EX",
    "wof:placetype": "postalcode"
  },
  "geometry": {"coordinates":[-3.477171,50.711244],"type":"Point"}
}
