{
  "type": "Feature",
  "properties": {
    "iso:country":"GB",
    "wof:name":"LA15 8JX",
    "wof:placetype":"postalcode"
},
  "geometry": {"coordinates":[-3.19363831776331,54.1668809191705],"type":"Point"}
}