{
  "type": "Feature",
  "properties": {
    "iso:country": "GB",
    "wof:name": "LA15 8JX",
    "wof:placetype": "postalcode"
  },
  "geometry": {"coordinates":[-3.193638,54.166881],"type":"Point"}
}
