{
  "type": "Feature",
  "properties": {
    "iso:country": "GB",
    "wof:name": "EH8 7QN",
    "wof:placetype": "postalcode"
  },
  "geometry": {"coordinates":[-3.135164,55.948902],"type":"Point"}
}
