{
  "type": "Feature",
  "properties": {
    "iso:country": "GB",
    "wof:name": "LA22 0HE",
    "wof:placetype": "postalcode"
  },
  "geometry": {"coordinates":[-2.957467,54.417353],"type":"Point"}
}
