{
  "type": "Feature",
  "properties": {
    "iso:country": "GB",
    "wof:name": "BS34 8RW",
    "wof:placetype": "postalcode"
  },
  "geometry": {"coordinates":[-2.531682,51.515816],"type":"Point"}
}
