{
  "type": "Feature",
  "properties": {
    "date:inception_lower":"2002-09-01",
    "date:inception_upper":"2002-09-30",
    "iso:country":"GB",
    "wof:name":"BS34 8RW",
    "wof:placetype":"postalcode"
},
  "geometry": {"coordinates":[-2.531682,51.515816],"type":"Point"}
}