{
  "type": "Feature",
  "properties": {
    "iso:country": "GB",
    "wof:name": "PE28 4TZ",
    "wof:placetype": "postalcode"
  },
  "geometry": {"coordinates":[-0.230845,52.325971],"type":"Point"}
}
