{
  "type": "Feature",
  "properties": {
    "iso:country":"GB",
    "wof:name":"PE28 4TZ",
    "wof:placetype":"postalcode"
},
  "geometry": {"coordinates":[-0.23084505833051,52.32597057192317],"type":"Point"}
}