{
  "type": "Feature",
  "properties": {
    "iso:country":"GB",
    "wof:name":"RG24 9JS",
    "wof:placetype":"postalcode"
},
  "geometry": {"coordinates":[-1.12628225716125,51.28037843795046],"type":"Point"}
}