{
  "type": "Feature",
  "properties": {
    "date:inception_lower":"1991-09-01",
    "date:inception_upper":"1991-09-30",
    "iso:country":"GB",
    "wof:name":"RG24 9JS",
    "wof:placetype":"postalcode"
},
  "geometry": {"coordinates":[-1.126282,51.280378],"type":"Point"}
}