{
  "type": "Feature",
  "properties": {
    "date:inception_lower": "1992-01-01",
    "date:inception_upper": "1992-01-01",
    "iso:country": "GB",
    "wof:name": "L34 9GT",
    "wof:placetype": "postalcode"
  },
  "geometry": {"coordinates":[-2.869214,53.462223],"type":"Point"}
}
