{
  "type": "Feature",
  "properties": {
    "iso:country":"GB",
    "wof:name":"L34 9GT",
    "wof:placetype":"postalcode"
},
  "geometry": {"coordinates":[-2.86921362950916,53.46222268633716],"type":"Point"}
}