{
  "type": "Feature",
  "properties": {
    "iso:country": "GB",
    "wof:name": "OL11 2HX",
    "wof:placetype": "postalcode"
  },
  "geometry": {"coordinates":[-2.15516,53.598825],"type":"Point"}
}
