{
  "type": "Feature",
  "properties": {
    "date:inception_lower": "1980-01-01",
    "date:inception_upper": "1980-01-01",
    "iso:country": "GB",
    "wof:name": "OL11 2HX",
    "wof:placetype": "postalcode"
  },
  "geometry": {"coordinates":[-2.15516,53.598825],"type":"Point"}
}
