{
  "type": "Feature",
  "properties": {
    "iso:country":"GB",
    "wof:name":"OL11 2HX",
    "wof:placetype":"postalcode"
},
  "geometry": {"coordinates":[-2.15515969633637,53.59882512999823],"type":"Point"}
}