{
  "type": "Feature",
  "properties": {
    "date:inception_lower": "2007-07-01",
    "date:inception_upper": "2007-07-01",
    "iso:country": "GB",
    "wof:name": "B98 7FS",
    "wof:placetype": "postalcode"
  },
  "geometry": {"coordinates":[-1.932099,52.303225],"type":"Point"}
}
