{
  "type": "Feature",
  "properties": {
    "iso:country":"GB",
    "wof:name":"B98 7FS",
    "wof:placetype":"postalcode"
},
  "geometry": {"coordinates":[-1.93209856388061,52.30322462526805],"type":"Point"}
}