{
  "type": "Feature",
  "properties": {
    "iso:country": "GB",
    "wof:name": "TN10 4PW",
    "wof:placetype": "postalcode"
  },
  "geometry": {"coordinates":[0.280912,51.21066],"type":"Point"}
}
