{
  "type": "Feature",
  "properties": {
    "iso:country":"GB",
    "wof:name":"TN10 4PW",
    "wof:placetype":"postalcode"
},
  "geometry": {"coordinates":[0.28091192055082,51.21066000375779],"type":"Point"}
}