{
  "type": "Feature",
  "properties": {
    "iso:country":"GB",
    "wof:name":"WD5 0NA",
    "wof:placetype":"postalcode"
},
  "geometry": {"coordinates":[-0.4115922662005,51.70048247190712],"type":"Point"}
}