{
  "type": "Feature",
  "properties": {
    "iso:country": "GB",
    "wof:name": "WD5 0NA",
    "wof:placetype": "postalcode"
  },
  "geometry": {"coordinates":[-0.411592,51.700482],"type":"Point"}
}
