{
  "type": "Feature",
  "properties": {
    "date:inception_lower": "1980-01-01",
    "date:inception_upper": "1980-01-01",
    "iso:country": "GB",
    "wof:name": "WD5 0NA",
    "wof:placetype": "postalcode"
  },
  "geometry": {"coordinates":[-0.411592,51.700482],"type":"Point"}
}
