{
  "type": "Feature",
  "properties": {
    "iso:country": "GB",
    "wof:name": "BN16 2AT",
    "wof:placetype": "postalcode"
  },
  "geometry": {"coordinates":[-0.495956,50.808502],"type":"Point"}
}
