{
  "type": "Feature",
  "properties": {
    "iso:country":"GB",
    "wof:name":"GU2 9PX",
    "wof:placetype":"postalcode"
},
  "geometry": {"coordinates":[-0.58733674480568,51.2559092612078],"type":"Point"}
}