{
  "type": "Feature",
  "properties": {
    "iso:country":"GB",
    "wof:name":"PE11 3YP",
    "wof:placetype":"postalcode"
},
  "geometry": {"coordinates":[-0.16043796769579,52.8226740219342],"type":"Point"}
}