{
  "type": "Feature",
  "properties": {
    "date:inception_lower":"1995-12-01",
    "date:inception_upper":"1995-12-31",
    "iso:country":"GB",
    "wof:name":"M33 7FY",
    "wof:placetype":"postalcode"
},
  "geometry": {"coordinates":[-2.310269,53.429999],"type":"Point"}
}