{
  "type": "Feature",
  "properties": {
    "date:inception_lower":"1980-01-01",
    "date:inception_upper":"1980-01-31",
    "iso:country":"GB",
    "wof:name":"RH17 6TN",
    "wof:placetype":"postalcode"
},
  "geometry": {"coordinates":[-0.090152,51.068506],"type":"Point"}
}