{
  "type": "Feature",
  "properties": {
    "iso:country": "GB",
    "wof:name": "NG11 8AX",
    "wof:placetype": "postalcode"
  },
  "geometry": {"coordinates":[-1.18111,52.910406],"type":"Point"}
}
