{
  "type": "Feature",
  "properties": {
    "iso:country":"GB",
    "wof:name":"NG11 8AX",
    "wof:placetype":"postalcode"
},
  "geometry": {"coordinates":[-1.18111039718615,52.91040606554989],"type":"Point"}
}