{
  "type": "Feature",
  "properties": {
    "iso:country":"GB",
    "wof:name":"YO23 3FR",
    "wof:placetype":"postalcode"
},
  "geometry": {"coordinates":[-1.16149094730288,53.92065664214881],"type":"Point"}
}