{
  "type": "Feature",
  "properties": {
    "iso:country":"GB",
    "wof:name":"DY3 2QQ",
    "wof:placetype":"postalcode"
},
  "geometry": {"coordinates":[-2.12635672962267,52.51384050127265],"type":"Point"}
}