{
  "type": "Feature",
  "properties": {
    "date:inception_lower":"1980-01-01",
    "date:inception_upper":"1980-01-31",
    "iso:country":"GB",
    "wof:name":"DY3 2QQ",
    "wof:placetype":"postalcode"
},
  "geometry": {"coordinates":[-2.126357,52.51384],"type":"Point"}
}