{
  "type": "Feature",
  "properties": {
    "date:inception_lower":"2013-08-01",
    "date:inception_upper":"2013-08-31",
    "iso:country":"GB",
    "wof:name":"PE26 1NP",
    "wof:placetype":"postalcode"
},
  "geometry": {"coordinates":[-0.109993,52.445806],"type":"Point"}
}