{
  "type": "Feature",
  "properties": {
    "iso:country": "GB",
    "wof:name": "PE26 1NP",
    "wof:placetype": "postalcode"
  },
  "geometry": {"coordinates":[-0.109993,52.445806],"type":"Point"}
}
