{
  "type": "Feature",
  "properties": {
    "date:inception_lower": "2021-04-01",
    "date:inception_upper": "2021-04-01",
    "iso:country": "GB",
    "wof:name": "CT5 1SH",
    "wof:placetype": "postalcode"
  },
  "geometry": {"coordinates":[1.033852,51.345348],"type":"Point"}
}
