{
  "type": "Feature",
  "properties": {
    "iso:country":"GB",
    "wof:name":"HP2 5TA",
    "wof:placetype":"postalcode"
},
  "geometry": {"coordinates":[-0.45923262439747,51.76643375790456],"type":"Point"}
}