{
  "type": "Feature",
  "properties": {
    "date:inception_lower":"1980-01-01",
    "date:inception_upper":"1980-01-31",
    "iso:country":"GB",
    "wof:name":"HP2 5TA",
    "wof:placetype":"postalcode"
},
  "geometry": {"coordinates":[-0.459233,51.766434],"type":"Point"}
}