{
  "type": "Feature",
  "properties": {
    "iso:country":"GB",
    "wof:name":"GL5 3DE",
    "wof:placetype":"postalcode"
},
  "geometry": {"coordinates":[-2.21776544096473,51.7456480587126],"type":"Point"}
}