{
  "type": "Feature",
  "properties": {
    "iso:country":"GB",
    "wof:name":"LA8 8JA",
    "wof:placetype":"postalcode"
},
  "geometry": {"coordinates":[-2.87353938075371,54.3259952826934],"type":"Point"}
}