{
  "type": "Feature",
  "properties": {
    "iso:country":"GB",
    "wof:name":"BD22 0HY",
    "wof:placetype":"postalcode"
},
  "geometry": {"coordinates":[-1.99143849024445,53.83633681945484],"type":"Point"}
}