{
  "type": "Feature",
  "properties": {
    "iso:country":"GB",
    "wof:name":"NE28 9PZ",
    "wof:placetype":"postalcode"
},
  "geometry": {"coordinates":[-1.5195059171474,55.01355100145099],"type":"Point"}
}