{
  "type": "Feature",
  "properties": {
    "date:inception_lower": "1980-01-01",
    "date:inception_upper": "1980-01-01",
    "iso:country": "GB",
    "wof:name": "BN20 9PS",
    "wof:placetype": "postalcode"
  },
  "geometry": {"coordinates":[0.244844,50.807956],"type":"Point"}
}
