{
  "type": "Feature",
  "properties": {
    "iso:country":"GB",
    "wof:name":"S36 2EJ",
    "wof:placetype":"postalcode"
},
  "geometry": {"coordinates":[-1.58457200552265,53.48081720470295],"type":"Point"}
}