{
  "type": "Feature",
  "properties": {
    "iso:country": "GB",
    "wof:name": "SA5 8PW",
    "wof:placetype": "postalcode"
  },
  "geometry": {"coordinates":[-3.954114,51.641572],"type":"Point"}
}
