{
  "type": "Feature",
  "properties": {
    "iso:country":"GB",
    "wof:name":"DE24 8BD",
    "wof:placetype":"postalcode"
},
  "geometry": {"coordinates":[-1.46167078399038,52.90001607452327],"type":"Point"}
}