{
  "type": "Feature",
  "properties": {
    "iso:country":"GB",
    "wof:name":"PL4 8RN",
    "wof:placetype":"postalcode"
},
  "geometry": {"coordinates":[-4.12497373610423,50.37738887923922],"type":"Point"}
}