{
  "type": "Feature",
  "properties": {
    "date:inception_lower": "1980-01-01",
    "date:inception_upper": "1980-01-01",
    "iso:country": "GB",
    "wof:name": "PL4 8RN",
    "wof:placetype": "postalcode"
  },
  "geometry": {"coordinates":[-4.124974,50.377389],"type":"Point"}
}
