{
  "type": "Feature",
  "properties": {
    "iso:country":"GB",
    "wof:name":"CH66 4RS",
    "wof:placetype":"postalcode"
},
  "geometry": {"coordinates":[-2.9305994729294,53.27434069330783],"type":"Point"}
}