{
  "type": "Feature",
  "properties": {
    "date:inception_lower": "1980-01-01",
    "date:inception_upper": "1980-01-01",
    "iso:country": "GB",
    "wof:name": "S75 6JB",
    "wof:placetype": "postalcode"
  },
  "geometry": {"coordinates":[-1.498815,53.590957],"type":"Point"}
}
