{
  "type": "Feature",
  "properties": {
    "iso:country":"GB",
    "wof:name":"S75 6JB",
    "wof:placetype":"postalcode"
},
  "geometry": {"coordinates":[-1.49881503802846,53.59095661375662],"type":"Point"}
}