{
  "type": "Feature",
  "properties": {
    "iso:country":"GB",
    "wof:name":"LU3 1PZ",
    "wof:placetype":"postalcode"
},
  "geometry": {"coordinates":[-0.42788870246738,51.9009848637578],"type":"Point"}
}