{
  "type": "Feature",
  "properties": {
    "date:inception_lower": "1980-01-01",
    "date:inception_upper": "1980-01-01",
    "iso:country": "GB",
    "wof:name": "ML6 8SS",
    "wof:placetype": "postalcode"
  },
  "geometry": {"coordinates":[-3.949979,55.845874],"type":"Point"}
}
