{
  "type": "Feature",
  "properties": {
    "iso:country":"GB",
    "wof:name":"ML6 8SS",
    "wof:placetype":"postalcode"
},
  "geometry": {"coordinates":[-3.94997916009234,55.8458740404602],"type":"Point"}
}