{
  "type": "Feature",
  "properties": {
    "iso:country":"GB",
    "wof:name":"GU14 0RE",
    "wof:placetype":"postalcode"
},
  "geometry": {"coordinates":[-0.78223262586502,51.28843857455684],"type":"Point"}
}