{
  "type": "Feature",
  "properties": {
    "date:inception_lower": "1994-12-01",
    "date:inception_upper": "1994-12-01",
    "iso:country": "GB",
    "wof:name": "GU14 0RE",
    "wof:placetype": "postalcode"
  },
  "geometry": {"coordinates":[-0.782233,51.288439],"type":"Point"}
}
