{
  "type": "Feature",
  "properties": {
    "iso:country":"GB",
    "wof:name":"NG19 9ES",
    "wof:placetype":"postalcode"
},
  "geometry": {"coordinates":[-1.17653350654544,53.17174901518256],"type":"Point"}
}