{
  "type": "Feature",
  "properties": {
    "iso:country":"GB",
    "wof:name":"BA10 0NP",
    "wof:placetype":"postalcode"
},
  "geometry": {"coordinates":[-2.46670460797971,51.10062603459931],"type":"Point"}
}