{
  "type": "Feature",
  "properties": {
    "date:inception_lower":"1980-01-01",
    "date:inception_upper":"1980-01-31",
    "iso:country":"GB",
    "wof:name":"L22 9QJ",
    "wof:placetype":"postalcode"
},
  "geometry": {"coordinates":[-3.028549,53.479897],"type":"Point"}
}