{
  "type": "Feature",
  "properties": {
    "iso:country":"GB",
    "wof:name":"TS4 3AA",
    "wof:placetype":"postalcode"
},
  "geometry": {"coordinates":[-1.22193410122857,54.55656425240166],"type":"Point"}
}