{
  "type": "Feature",
  "properties": {
    "iso:country":"GB",
    "wof:name":"DL13 4PJ",
    "wof:placetype":"postalcode"
},
  "geometry": {"coordinates":[-1.86123398052457,54.74538661667689],"type":"Point"}
}