{
  "type": "Feature",
  "properties": {
    "date:inception_lower":"1980-01-01",
    "date:inception_upper":"1980-01-31",
    "iso:country":"GB",
    "wof:name":"DL13 4PJ",
    "wof:placetype":"postalcode"
},
  "geometry": {"coordinates":[-1.861234,54.745387],"type":"Point"}
}