{
  "type": "Feature",
  "properties": {
    "iso:country": "GB",
    "wof:name": "HA1 2HP",
    "wof:placetype": "postalcode"
  },
  "geometry": {"coordinates":[-0.32799,51.587184],"type":"Point"}
}
