{
  "type": "Feature",
  "properties": {
    "iso:country":"GB",
    "wof:name":"WS12 4RE",
    "wof:placetype":"postalcode"
},
  "geometry": {"coordinates":[-2.00019428305209,52.71866775682894],"type":"Point"}
}