{
  "type": "Feature",
  "properties": {
    "iso:country":"GB",
    "wof:name":"S6 6HX",
    "wof:placetype":"postalcode"
},
  "geometry": {"coordinates":[-1.59809309024033,53.41806942666444],"type":"Point"}
}