{
  "type": "Feature",
  "properties": {
    "iso:country": "GB",
    "wof:name": "L18 5EN",
    "wof:placetype": "postalcode"
  },
  "geometry": {"coordinates":[-2.916529,53.383405],"type":"Point"}
}
