{
  "type": "Feature",
  "properties": {
    "date:inception_lower": "2002-06-01",
    "date:inception_upper": "2002-06-01",
    "iso:country": "GB",
    "wof:name": "EH47 8FD",
    "wof:placetype": "postalcode"
  },
  "geometry": {"coordinates":[-3.680216,55.843507],"type":"Point"}
}
