{
  "type": "Feature",
  "properties": {
    "iso:country":"GB",
    "wof:name":"EH47 8FD",
    "wof:placetype":"postalcode"
},
  "geometry": {"coordinates":[-3.68015147579302,55.84297201236715],"type":"Point"}
}