{
  "type": "Feature",
  "properties": {
    "iso:country": "GB",
    "wof:name": "EH47 8FD",
    "wof:placetype": "postalcode"
  },
  "geometry": {"coordinates":[-3.680738,55.843401],"type":"Point"}
}
