{
  "type": "Feature",
  "properties": {
    "iso:country":"GB",
    "wof:name":"BS8 4TG",
    "wof:placetype":"postalcode"
},
  "geometry": {"coordinates":[-2.60945427097664,51.45175069775929],"type":"Point"}
}