{
  "type": "Feature",
  "properties": {
    "date:inception_lower":"1999-06-01",
    "date:inception_upper":"1999-06-30",
    "iso:country":"GB",
    "wof:name":"WV13 2AN",
    "wof:placetype":"postalcode"
},
  "geometry": {"coordinates":[-2.053264,52.58239],"type":"Point"}
}