{
  "type": "Feature",
  "properties": {
    "iso:country":"GB",
    "wof:name":"WV13 2AN",
    "wof:placetype":"postalcode"
},
  "geometry": {"coordinates":[-2.05326400718972,52.5823898314509],"type":"Point"}
}