{
  "type": "Feature",
  "properties": {
    "iso:country": "GB",
    "wof:name": "NN12 6JA",
    "wof:placetype": "postalcode"
  },
  "geometry": {"coordinates":[-0.995049,52.12706],"type":"Point"}
}
