{
  "type": "Feature",
  "properties": {
    "date:inception_lower":"2000-12-01",
    "date:inception_upper":"2000-12-31",
    "iso:country":"GB",
    "wof:name":"W1J 8DU",
    "wof:placetype":"postalcode"
},
  "geometry": {"coordinates":[-0.143135,51.508299],"type":"Point"}
}