{
  "type": "Feature",
  "properties": {
    "iso:country":"GB",
    "wof:name":"W1J 8DU",
    "wof:placetype":"postalcode"
},
  "geometry": {"coordinates":[-0.14313549892943,51.50829940731119],"type":"Point"}
}