{
  "type": "Feature",
  "properties": {
    "iso:country":"GB",
    "wof:name":"EH22 2QD",
    "wof:placetype":"postalcode"
},
  "geometry": {"coordinates":[-3.03285004639231,55.88737228929276],"type":"Point"}
}