{
  "type": "Feature",
  "properties": {
    "iso:country": "GB",
    "wof:name": "PL21 0NX",
    "wof:placetype": "postalcode"
  },
  "geometry": {"coordinates":[-3.859997,50.387299],"type":"Point"}
}
