{
  "type": "Feature",
  "properties": {
    "date:inception_lower": "2002-12-01",
    "date:inception_upper": "2002-12-01",
    "iso:country": "GB",
    "wof:name": "SP11 6HX",
    "wof:placetype": "postalcode"
  },
  "geometry": {"coordinates":[-1.476887,51.238004],"type":"Point"}
}
