{
  "type": "Feature",
  "properties": {
    "iso:country":"GB",
    "wof:name":"SP11 6HX",
    "wof:placetype":"postalcode"
},
  "geometry": {"coordinates":[-1.47688703843452,51.2380039304191],"type":"Point"}
}