{
  "type": "Feature",
  "properties": {
    "iso:country":"GB",
    "wof:name":"WV3 8NF",
    "wof:placetype":"postalcode"
},
  "geometry": {"coordinates":[-2.18849824448913,52.57623730990449],"type":"Point"}
}