{
  "type": "Feature",
  "properties": {
    "iso:country":"GB",
    "wof:name":"NE43 7RY",
    "wof:placetype":"postalcode"
},
  "geometry": {"coordinates":[-1.9219908561133,54.92996749092113],"type":"Point"}
}