{
  "type": "Feature",
  "properties": {
    "iso:country": "GB",
    "wof:name": "NE43 7RY",
    "wof:placetype": "postalcode"
  },
  "geometry": {"coordinates":[-1.921991,54.929967],"type":"Point"}
}
