{
  "type": "Feature",
  "properties": {
    "iso:country":"GB",
    "wof:name":"WF4 6ET",
    "wof:placetype":"postalcode"
},
  "geometry": {"coordinates":[-1.56771840407341,53.66374273147667],"type":"Point"}
}