{
  "type": "Feature",
  "properties": {
    "date:inception_lower":"1980-01-01",
    "date:inception_upper":"1980-01-31",
    "iso:country":"GB",
    "wof:name":"WF4 6ET",
    "wof:placetype":"postalcode"
},
  "geometry": {"coordinates":[-1.567718,53.663743],"type":"Point"}
}