{
  "type": "Feature",
  "properties": {
    "iso:country":"GB",
    "wof:name":"CB11 3QS",
    "wof:placetype":"postalcode"
},
  "geometry": {"coordinates":[0.21118659214754,51.98148889636026],"type":"Point"}
}