{
  "type": "Feature",
  "properties": {
    "iso:country":"GB",
    "wof:name":"SK3 9NN",
    "wof:placetype":"postalcode"
},
  "geometry": {"coordinates":[-2.17672700219143,53.40091515033928],"type":"Point"}
}