{
  "type": "Feature",
  "properties": {
    "date:inception_lower": "1980-01-01",
    "date:inception_upper": "1980-01-01",
    "iso:country": "GB",
    "wof:name": "SK3 9NN",
    "wof:placetype": "postalcode"
  },
  "geometry": {"coordinates":[-2.176727,53.400915],"type":"Point"}
}
