{
  "type": "Feature",
  "properties": {
    "iso:country":"GB",
    "wof:name":"HR1 1EN",
    "wof:placetype":"postalcode"
},
  "geometry": {"coordinates":[-2.71064207192706,52.06274624447175],"type":"Point"}
}