{
  "type": "Feature",
  "properties": {
    "iso:country": "GB",
    "wof:name": "BD9 5QB",
    "wof:placetype": "postalcode"
  },
  "geometry": {"coordinates":[-1.787858,53.813141],"type":"Point"}
}
