{
  "type": "Feature",
  "properties": {
    "iso:country":"GB",
    "wof:name":"BD9 5QB",
    "wof:placetype":"postalcode"
},
  "geometry": {"coordinates":[-1.78785781770678,53.81314092109067],"type":"Point"}
}