{
  "type": "Feature",
  "properties": {
    "iso:country":"GB",
    "wof:name":"ME15 8AY",
    "wof:placetype":"postalcode"
},
  "geometry": {"coordinates":[0.55278040971268,51.25110889367487],"type":"Point"}
}