{
  "type": "Feature",
  "properties": {
    "date:inception_lower":"1980-01-01",
    "date:inception_upper":"1980-01-31",
    "iso:country":"GB",
    "wof:name":"ME15 8AY",
    "wof:placetype":"postalcode"
},
  "geometry": {"coordinates":[0.55278,51.251109],"type":"Point"}
}