{
  "type": "Feature",
  "properties": {
    "iso:country": "GB",
    "wof:name": "BD20 8PS",
    "wof:placetype": "postalcode"
  },
  "geometry": {"coordinates":[-1.999416,53.900034],"type":"Point"}
}
