{
  "type": "Feature",
  "properties": {
    "date:inception_lower": "1980-01-01",
    "date:inception_upper": "1980-01-01",
    "iso:country": "GB",
    "wof:name": "BD20 8PS",
    "wof:placetype": "postalcode"
  },
  "geometry": {"coordinates":[-1.999416,53.900034],"type":"Point"}
}
