{
  "type": "Feature",
  "properties": {
    "iso:country": "GB",
    "wof:name": "LL65 3HU",
    "wof:placetype": "postalcode"
  },
  "geometry": {"coordinates":[-4.542939,53.276802],"type":"Point"}
}
