{
  "type": "Feature",
  "properties": {
    "iso:country":"GB",
    "wof:name":"SO40 7GS",
    "wof:placetype":"postalcode"
},
  "geometry": {"coordinates":[-1.55180574276469,50.91246505673231],"type":"Point"}
}