{
  "type": "Feature",
  "properties": {
    "iso:country":"GB",
    "wof:name":"LE3 1BU",
    "wof:placetype":"postalcode"
},
  "geometry": {"coordinates":[-1.16313167849192,52.61893108330703],"type":"Point"}
}