{
  "type": "Feature",
  "properties": {
    "date:inception_lower": "1980-01-01",
    "date:inception_upper": "1980-01-01",
    "iso:country": "GB",
    "wof:name": "DH3 1EJ",
    "wof:placetype": "postalcode"
  },
  "geometry": {"coordinates":[-1.581773,54.899349],"type":"Point"}
}
