{
  "type": "Feature",
  "properties": {
    "iso:country":"GB",
    "wof:name":"DH3 1EJ",
    "wof:placetype":"postalcode"
},
  "geometry": {"coordinates":[-1.58177352344257,54.8993492462534],"type":"Point"}
}