{
  "type": "Feature",
  "properties": {
    "iso:country":"GB",
    "wof:name":"LA21 8AU",
    "wof:placetype":"postalcode"
},
  "geometry": {"coordinates":[-3.09306108340092,54.34607276087948],"type":"Point"}
}