{
  "type": "Feature",
  "properties": {
    "date:inception_lower": "1980-01-01",
    "date:inception_upper": "1980-01-01",
    "iso:country": "GB",
    "wof:name": "LA21 8AU",
    "wof:placetype": "postalcode"
  },
  "geometry": {"coordinates":[-3.093105,54.345918],"type":"Point"}
}
