{
  "type": "Feature",
  "properties": {
    "iso:country": "GB",
    "wof:name": "CM6 1ZB",
    "wof:placetype": "postalcode"
  },
  "geometry": {"coordinates":[0.288597,51.872747],"type":"Point"}
}
