{
  "type": "Feature",
  "properties": {
    "iso:country":"GB",
    "wof:name":"CM6 1ZB",
    "wof:placetype":"postalcode"
},
  "geometry": {"coordinates":[0.28859657414205,51.87274680478462],"type":"Point"}
}