{
  "type": "Feature",
  "properties": {
    "iso:country":"GB",
    "wof:name":"DN5 8DY",
    "wof:placetype":"postalcode"
},
  "geometry": {"coordinates":[-1.15672289035235,53.52826350609097],"type":"Point"}
}