{
  "type": "Feature",
  "properties": {
    "iso:country": "GB",
    "wof:name": "DN5 8DY",
    "wof:placetype": "postalcode"
  },
  "geometry": {"coordinates":[-1.156723,53.528264],"type":"Point"}
}
