{
  "type": "Feature",
  "properties": {
    "date:inception_lower":"1980-01-01",
    "date:inception_upper":"1980-01-31",
    "iso:country":"GB",
    "wof:name":"DN5 8DY",
    "wof:placetype":"postalcode"
},
  "geometry": {"coordinates":[-1.156723,53.528264],"type":"Point"}
}