{
  "type": "Feature",
  "properties": {
    "iso:country":"GB",
    "wof:name":"BR6 9XS",
    "wof:placetype":"postalcode"
},
  "geometry": {"coordinates":[0.09869300377281,51.36239399858403],"type":"Point"}
}