{
  "type": "Feature",
  "properties": {
    "iso:country": "GB",
    "wof:name": "G4 9DL",
    "wof:placetype": "postalcode"
  },
  "geometry": {"coordinates":[-4.274853,55.872038],"type":"Point"}
}
