{
  "type": "Feature",
  "properties": {
    "date:inception_lower": "1980-01-01",
    "date:inception_upper": "1980-01-01",
    "iso:country": "GB",
    "wof:name": "CB9 8LU",
    "wof:placetype": "postalcode"
  },
  "geometry": {"coordinates":[0.427017,52.076372],"type":"Point"}
}
