{
  "type": "Feature",
  "properties": {
    "iso:country":"GB",
    "wof:name":"LL53 5PW",
    "wof:placetype":"postalcode"
},
  "geometry": {"coordinates":[-4.42678399598516,52.88238492397728],"type":"Point"}
}