{
  "type": "Feature",
  "properties": {
    "iso:country":"GB",
    "wof:name":"GU10 3EG",
    "wof:placetype":"postalcode"
},
  "geometry": {"coordinates":[-0.80687052141604,51.16377108004671],"type":"Point"}
}