{
  "type": "Feature",
  "properties": {
    "date:inception_lower": "1980-01-01",
    "date:inception_upper": "1980-01-01",
    "iso:country": "GB",
    "wof:name": "BR3 4PT",
    "wof:placetype": "postalcode"
  },
  "geometry": {"coordinates":[-0.040965,51.408788],"type":"Point"}
}
