{
  "type": "Feature",
  "properties": {
    "iso:country":"GB",
    "wof:name":"BR3 4PT",
    "wof:placetype":"postalcode"
},
  "geometry": {"coordinates":[-0.04096473212758,51.40878770088138],"type":"Point"}
}