{
  "type": "Feature",
  "properties": {
    "iso:country":"GB",
    "wof:name":"TA8 2HJ",
    "wof:placetype":"postalcode"
},
  "geometry": {"coordinates":[-2.99915799186667,51.24724204746181],"type":"Point"}
}