{
  "type": "Feature",
  "properties": {
    "iso:country":"GB",
    "wof:name":"HU17 8SU",
    "wof:placetype":"postalcode"
},
  "geometry": {"coordinates":[-0.49437183986899,53.82236186468727],"type":"Point"}
}