{
  "type": "Feature",
  "properties": {
    "iso:country":"GB",
    "wof:name":"HG5 9JZ",
    "wof:placetype":"postalcode"
},
  "geometry": {"coordinates":[-1.44044359681906,54.05827407283427],"type":"Point"}
}