{
  "type": "Feature",
  "properties": {
    "iso:country": "GB",
    "wof:name": "HG5 9JZ",
    "wof:placetype": "postalcode"
  },
  "geometry": {"coordinates":[-1.440444,54.058274],"type":"Point"}
}
