{
  "type": "Feature",
  "properties": {
    "iso:country": "GB",
    "wof:name": "OL5 0RS",
    "wof:placetype": "postalcode"
  },
  "geometry": {"coordinates":[-2.037057,53.529539],"type":"Point"}
}
