{
  "type": "Feature",
  "properties": {
    "date:inception_lower":"1980-01-01",
    "date:inception_upper":"1980-01-31",
    "iso:country":"GB",
    "wof:name":"OL5 0RS",
    "wof:placetype":"postalcode"
},
  "geometry": {"coordinates":[-2.037057,53.529539],"type":"Point"}
}