{
  "type": "Feature",
  "properties": {
    "iso:country":"GB",
    "wof:name":"OL5 0RS",
    "wof:placetype":"postalcode"
},
  "geometry": {"coordinates":[-2.03705711310523,53.52953948292898],"type":"Point"}
}