{
  "type": "Feature",
  "properties": {
    "iso:country":"GB",
    "wof:name":"NG1 1GD",
    "wof:placetype":"postalcode"
},
  "geometry": {"coordinates":[-1.13898133178961,52.95101073898505],"type":"Point"}
}