{
  "type": "Feature",
  "properties": {
    "iso:country": "GB",
    "wof:name": "NG1 1GD",
    "wof:placetype": "postalcode"
  },
  "geometry": {"coordinates":[-1.138951,52.951055],"type":"Point"}
}
