{
  "type": "Feature",
  "properties": {
    "iso:country":"GB",
    "wof:name":"DD2 3WB",
    "wof:placetype":"postalcode"
},
  "geometry": {"coordinates":[-3.01204560510526,56.48331842630429],"type":"Point"}
}