{
  "type": "Feature",
  "properties": {
    "iso:country":"GB",
    "wof:name":"HX6 2PQ",
    "wof:placetype":"postalcode"
},
  "geometry": {"coordinates":[-1.90631552850843,53.71196980764341],"type":"Point"}
}