{
  "type": "Feature",
  "properties": {
    "iso:country":"GB",
    "wof:name":"TW7 7JN",
    "wof:placetype":"postalcode"
},
  "geometry": {"coordinates":[-0.32849243203883,51.4591386447802],"type":"Point"}
}