{
  "type": "Feature",
  "properties": {
    "iso:country":"GB",
    "wof:name":"SW1X 9HH",
    "wof:placetype":"postalcode"
},
  "geometry": {"coordinates":[-0.1582726852011,51.50171277911152],"type":"Point"}
}