{
  "type": "Feature",
  "properties": {
    "date:inception_lower": "1980-01-01",
    "date:inception_upper": "1980-01-01",
    "iso:country": "GB",
    "wof:name": "SW1X 9HH",
    "wof:placetype": "postalcode"
  },
  "geometry": {"coordinates":[-0.158273,51.501713],"type":"Point"}
}
