{
  "type": "Feature",
  "properties": {
    "iso:country":"GB",
    "wof:name":"SY21 0HB",
    "wof:placetype":"postalcode"
},
  "geometry": {"coordinates":[-3.39895279306754,52.65412331242808],"type":"Point"}
}