{
  "type": "Feature",
  "properties": {
    "iso:country":"GB",
    "wof:name":"IG6 2BP",
    "wof:placetype":"postalcode"
},
  "geometry": {"coordinates":[0.07329139778208,51.59062537184553],"type":"Point"}
}