{
  "type": "Feature",
  "properties": {
    "iso:country":"GB",
    "wof:name":"ME2 3AA",
    "wof:placetype":"postalcode"
},
  "geometry": {"coordinates":[0.49490605696289,51.39856615664938],"type":"Point"}
}