{
  "type": "Feature",
  "properties": {
    "iso:country": "GB",
    "wof:name": "YO12 5ST",
    "wof:placetype": "postalcode"
  },
  "geometry": {"coordinates":[-0.447397,54.292702],"type":"Point"}
}
