{
  "type": "Feature",
  "properties": {
    "iso:country":"GB",
    "wof:name":"HD3 3GD",
    "wof:placetype":"postalcode"
},
  "geometry": {"coordinates":[-1.82888952615017,53.67215690297941],"type":"Point"}
}