{
  "type": "Feature",
  "properties": {
    "date:inception_lower": "2009-09-01",
    "date:inception_upper": "2009-09-01",
    "iso:country": "GB",
    "wof:name": "HD3 3GD",
    "wof:placetype": "postalcode"
  },
  "geometry": {"coordinates":[-1.828906,53.672172],"type":"Point"}
}
