{
  "type": "Feature",
  "properties": {
    "date:inception_lower":"2016-09-01",
    "date:inception_upper":"2016-09-30",
    "iso:country":"GB",
    "wof:name":"ST15 0TL",
    "wof:placetype":"postalcode"
},
  "geometry": {"coordinates":[-2.140158,52.886092],"type":"Point"}
}