{
  "type": "Feature",
  "properties": {
    "iso:country":"GB",
    "wof:name":"PL8 1DW",
    "wof:placetype":"postalcode"
},
  "geometry": {"coordinates":[-4.04201797932972,50.31580749275676],"type":"Point"}
}