{
  "type": "Feature",
  "properties": {
    "iso:country": "GB",
    "wof:name": "PL8 1DW",
    "wof:placetype": "postalcode"
  },
  "geometry": {"coordinates":[-4.042018,50.315807],"type":"Point"}
}
