{
  "type": "Feature",
  "properties": {
    "iso:country":"GB",
    "wof:name":"RM8 3QS",
    "wof:placetype":"postalcode"
},
  "geometry": {"coordinates":[0.12881329751506,51.55751815808499],"type":"Point"}
}