{
  "type": "Feature",
  "properties": {
    "date:inception_lower": "1980-01-01",
    "date:inception_upper": "1980-01-01",
    "iso:country": "GB",
    "wof:name": "RM8 3QS",
    "wof:placetype": "postalcode"
  },
  "geometry": {"coordinates":[0.128813,51.557518],"type":"Point"}
}
