{
  "type": "Feature",
  "properties": {
    "iso:country": "GB",
    "wof:name": "GU14 9UP",
    "wof:placetype": "postalcode"
  },
  "geometry": {"coordinates":[-0.78782,51.299008],"type":"Point"}
}
