{
  "type": "Feature",
  "properties": {
    "iso:country":"GB",
    "wof:name":"GU14 9UP",
    "wof:placetype":"postalcode"
},
  "geometry": {"coordinates":[-0.78781963861649,51.29900844184682],"type":"Point"}
}