{
  "type": "Feature",
  "properties": {
    "date:inception_lower":"1980-01-01",
    "date:inception_upper":"1980-01-31",
    "iso:country":"GB",
    "wof:name":"CO15 3AE",
    "wof:placetype":"postalcode"
},
  "geometry": {"coordinates":[1.149811,51.793765],"type":"Point"}
}