{
  "type": "Feature",
  "properties": {
    "iso:country":"GB",
    "wof:name":"CO15 3AE",
    "wof:placetype":"postalcode"
},
  "geometry": {"coordinates":[1.14981082960966,51.79376516423658],"type":"Point"}
}