{
  "type": "Feature",
  "properties": {
    "iso:country": "GB",
    "wof:name": "LL57 3SY",
    "wof:placetype": "postalcode"
  },
  "geometry": {"coordinates":[-4.050142,53.178871],"type":"Point"}
}
