{
  "type": "Feature",
  "properties": {
    "date:inception_lower":"1980-01-01",
    "date:inception_upper":"1980-01-31",
    "iso:country":"GB",
    "wof:name":"NN17 2PG",
    "wof:placetype":"postalcode"
},
  "geometry": {"coordinates":[-0.718121,52.495748],"type":"Point"}
}