{
  "type": "Feature",
  "properties": {
    "iso:country": "GB",
    "wof:name": "NN17 2PG",
    "wof:placetype": "postalcode"
  },
  "geometry": {"coordinates":[-0.718121,52.495748],"type":"Point"}
}
