{
  "type": "Feature",
  "properties": {
    "iso:country": "GB",
    "wof:name": "IP31 3HT",
    "wof:placetype": "postalcode"
  },
  "geometry": {"coordinates":[0.944808,52.270406],"type":"Point"}
}
