{
  "type": "Feature",
  "properties": {
    "iso:country":"GB",
    "wof:name":"SP2 9EW",
    "wof:placetype":"postalcode"
},
  "geometry": {"coordinates":[-1.82711048220071,51.08968738323315],"type":"Point"}
}