{
  "type": "Feature",
  "properties": {
    "date:inception_lower":"1980-01-01",
    "date:inception_upper":"1980-01-31",
    "iso:country":"GB",
    "wof:name":"SP2 9EW",
    "wof:placetype":"postalcode"
},
  "geometry": {"coordinates":[-1.82711,51.089687],"type":"Point"}
}