{
  "type": "Feature",
  "properties": {
    "iso:country":"GB",
    "wof:name":"S66 9PG",
    "wof:placetype":"postalcode"
},
  "geometry": {"coordinates":[-1.26309149911097,53.39338087468585],"type":"Point"}
}