{
  "type": "Feature",
  "properties": {
    "iso:country": "GB",
    "wof:name": "S66 9PG",
    "wof:placetype": "postalcode"
  },
  "geometry": {"coordinates":[-1.263091,53.393381],"type":"Point"}
}
