{
  "type": "Feature",
  "properties": {
    "iso:country": "GB",
    "wof:name": "WS9 9EA",
    "wof:placetype": "postalcode"
  },
  "geometry": {"coordinates":[-1.89529,52.632096],"type":"Point"}
}
