{
  "type": "Feature",
  "properties": {
    "iso:country":"GB",
    "wof:name":"WS9 9EA",
    "wof:placetype":"postalcode"
},
  "geometry": {"coordinates":[-1.89529014419698,52.63209625426209],"type":"Point"}
}