{
  "type": "Feature",
  "properties": {
    "iso:country":"GB",
    "wof:name":"N14 5AX",
    "wof:placetype":"postalcode"
},
  "geometry": {"coordinates":[-0.14141156321298,51.62846491208934],"type":"Point"}
}