{
  "type": "Feature",
  "properties": {
    "iso:country":"GB",
    "wof:name":"NP20 7ST",
    "wof:placetype":"postalcode"
},
  "geometry": {"coordinates":[-3.03264277636645,51.61026898348966],"type":"Point"}
}