{
  "type": "Feature",
  "properties": {
    "date:inception_lower": "1993-08-01",
    "date:inception_upper": "1993-08-01",
    "iso:country": "GB",
    "wof:name": "L32 2DG",
    "wof:placetype": "postalcode"
  },
  "geometry": {"coordinates":[-2.902512,53.488996],"type":"Point"}
}
