{
  "type": "Feature",
  "properties": {
    "date:inception_lower": "1980-01-01",
    "date:inception_upper": "1980-01-01",
    "iso:country": "GB",
    "wof:name": "DL12 0DL",
    "wof:placetype": "postalcode"
  },
  "geometry": {"coordinates":[-1.959994,54.607838],"type":"Point"}
}
