{
  "type": "Feature",
  "properties": {
    "iso:country":"GB",
    "wof:name":"DL12 0DL",
    "wof:placetype":"postalcode"
},
  "geometry": {"coordinates":[-1.95999401606758,54.60783783299816],"type":"Point"}
}