{
  "type": "Feature",
  "properties": {
    "iso:country": "GB",
    "wof:name": "TA22 9AT",
    "wof:placetype": "postalcode"
  },
  "geometry": {"coordinates":[-3.533095,51.018855],"type":"Point"}
}
