{
  "type": "Feature",
  "properties": {
    "iso:country": "GB",
    "wof:name": "NE1 6AP",
    "wof:placetype": "postalcode"
  },
  "geometry": {"coordinates":[-1.611225,54.973977],"type":"Point"}
}
