{
  "type": "Feature",
  "properties": {
    "iso:country": "GB",
    "wof:name": "CV12 9NX",
    "wof:placetype": "postalcode"
  },
  "geometry": {"coordinates":[-1.431171,52.487298],"type":"Point"}
}
