{
  "type": "Feature",
  "properties": {
    "iso:country":"GB",
    "wof:name":"OL15 8QU",
    "wof:placetype":"postalcode"
},
  "geometry": {"coordinates":[-2.10775591058112,53.63325730395724],"type":"Point"}
}