{
  "type": "Feature",
  "properties": {
    "iso:country":"GB",
    "wof:name":"NE37 2TH",
    "wof:placetype":"postalcode"
},
  "geometry": {"coordinates":[-1.52656734045412,54.91312965653546],"type":"Point"}
}