{
  "type": "Feature",
  "properties": {
    "iso:country":"GB",
    "wof:name":"RG9 6EU",
    "wof:placetype":"postalcode"
},
  "geometry": {"coordinates":[-0.97846268885928,51.60020125453704],"type":"Point"}
}