{
  "type": "Feature",
  "properties": {
    "date:inception_lower": "1980-01-01",
    "date:inception_upper": "1980-01-01",
    "iso:country": "GB",
    "wof:name": "RG9 6EU",
    "wof:placetype": "postalcode"
  },
  "geometry": {"coordinates":[-0.978458,51.600133],"type":"Point"}
}
