{
  "type": "Feature",
  "properties": {
    "iso:country": "GB",
    "wof:name": "FY8 3AX",
    "wof:placetype": "postalcode"
  },
  "geometry": {"coordinates":[-3.024628,53.766866],"type":"Point"}
}
