{
  "type": "Feature",
  "properties": {
    "iso:country":"GB",
    "wof:name":"PL5 3QL",
    "wof:placetype":"postalcode"
},
  "geometry": {"coordinates":[-4.1630280394825,50.41341108361276],"type":"Point"}
}