{
  "type": "Feature",
  "properties": {
    "iso:country": "GB",
    "wof:name": "OL14 8AB",
    "wof:placetype": "postalcode"
  },
  "geometry": {"coordinates":[-2.075759,53.718516],"type":"Point"}
}
