{
  "type": "Feature",
  "properties": {
    "date:inception_lower":"1980-01-01",
    "date:inception_upper":"1980-01-31",
    "iso:country":"GB",
    "wof:name":"OL14 8AB",
    "wof:placetype":"postalcode"
},
  "geometry": {"coordinates":[-2.075759,53.718516],"type":"Point"}
}