{
  "type": "Feature",
  "properties": {
    "iso:country":"GB",
    "wof:name":"CV35 9LN",
    "wof:placetype":"postalcode"
},
  "geometry": {"coordinates":[-1.60798410539141,52.18611511263702],"type":"Point"}
}