{
  "type": "Feature",
  "properties": {
    "date:inception_lower": "1980-01-01",
    "date:inception_upper": "1980-01-01",
    "iso:country": "GB",
    "wof:name": "N1 3AA",
    "wof:placetype": "postalcode"
  },
  "geometry": {"coordinates":[-0.094451,51.540557],"type":"Point"}
}
