{
  "type": "Feature",
  "properties": {
    "iso:country":"GB",
    "wof:name":"TW5 0BA",
    "wof:placetype":"postalcode"
},
  "geometry": {"coordinates":[-0.37561824760294,51.47784858864291],"type":"Point"}
}