{
  "type": "Feature",
  "properties": {
    "date:inception_lower":"1980-01-01",
    "date:inception_upper":"1980-01-31",
    "iso:country":"GB",
    "wof:name":"SM7 2RA",
    "wof:placetype":"postalcode"
},
  "geometry": {"coordinates":[-0.200969,51.326499],"type":"Point"}
}