{
  "type": "Feature",
  "properties": {
    "date:inception_lower": "2018-01-01",
    "date:inception_upper": "2018-01-01",
    "iso:country": "GB",
    "wof:name": "E3 2TF",
    "wof:placetype": "postalcode"
  },
  "geometry": {"coordinates":[-0.023775,51.53957],"type":"Point"}
}
