{
  "type": "Feature",
  "properties": {
    "iso:country": "GB",
    "wof:name": "E3 2TF",
    "wof:placetype": "postalcode"
  },
  "geometry": {"coordinates":[-0.023775,51.53957],"type":"Point"}
}
