{
  "type": "Feature",
  "properties": {
    "iso:country": "GB",
    "wof:name": "NG15 7TQ",
    "wof:placetype": "postalcode"
  },
  "geometry": {"coordinates":[-1.197661,53.039095],"type":"Point"}
}
