{
  "type": "Feature",
  "properties": {
    "iso:country":"GB",
    "wof:name":"DN21 4UD",
    "wof:placetype":"postalcode"
},
  "geometry": {"coordinates":[-0.56023408392662,53.43706381697461],"type":"Point"}
}