{
  "type": "Feature",
  "properties": {
    "iso:country":"GB",
    "wof:name":"G72 0GW",
    "wof:placetype":"postalcode"
},
  "geometry": {"coordinates":[-4.09681841982141,55.77128235391409],"type":"Point"}
}