{
  "type": "Feature",
  "properties": {
    "date:inception_lower": "2003-09-01",
    "date:inception_upper": "2003-09-01",
    "iso:country": "GB",
    "wof:name": "G72 0GW",
    "wof:placetype": "postalcode"
  },
  "geometry": {"coordinates":[-4.096818,55.771282],"type":"Point"}
}
