{
  "type": "Feature",
  "properties": {
    "iso:country": "GB",
    "wof:name": "SL6 6QR",
    "wof:placetype": "postalcode"
  },
  "geometry": {"coordinates":[-0.799839,51.529697],"type":"Point"}
}
