{
  "type": "Feature",
  "properties": {
    "iso:country":"GB",
    "wof:name":"SL6 6QR",
    "wof:placetype":"postalcode"
},
  "geometry": {"coordinates":[-0.79983940938666,51.5296969151007],"type":"Point"}
}