{
  "type": "Feature",
  "properties": {
    "date:inception_lower": "1980-01-01",
    "date:inception_upper": "1980-01-01",
    "iso:country": "GB",
    "wof:name": "SL6 6QR",
    "wof:placetype": "postalcode"
  },
  "geometry": {"coordinates":[-0.799839,51.529697],"type":"Point"}
}
