{
  "type": "Feature",
  "properties": {
    "iso:country": "GB",
    "wof:name": "SY9 5HA",
    "wof:placetype": "postalcode"
  },
  "geometry": {"coordinates":[-2.992558,52.501293],"type":"Point"}
}
