{
  "type": "Feature",
  "properties": {
    "iso:country":"GB",
    "wof:name":"SY9 5HA",
    "wof:placetype":"postalcode"
},
  "geometry": {"coordinates":[-2.99255815637137,52.5012929282654],"type":"Point"}
}