{
  "type": "Feature",
  "properties": {
    "date:inception_lower": "1980-01-01",
    "date:inception_upper": "1980-01-01",
    "iso:country": "GB",
    "wof:name": "SY9 5HA",
    "wof:placetype": "postalcode"
  },
  "geometry": {"coordinates":[-2.992558,52.501293],"type":"Point"}
}
