{
  "type": "Feature",
  "properties": {
    "iso:country":"GB",
    "wof:name":"DY11 5SN",
    "wof:placetype":"postalcode"
},
  "geometry": {"coordinates":[-2.2661011441932,52.42987567788447],"type":"Point"}
}