{
  "type": "Feature",
  "properties": {
    "iso:country":"GB",
    "wof:name":"ST8 7EJ",
    "wof:placetype":"postalcode"
},
  "geometry": {"coordinates":[-2.15865826310205,53.12442786752134],"type":"Point"}
}