{
  "type": "Feature",
  "properties": {
    "date:inception_lower":"1992-08-01",
    "date:inception_upper":"1992-08-31",
    "iso:country":"GB",
    "wof:name":"DE24 9DW",
    "wof:placetype":"postalcode"
},
  "geometry": {"coordinates":[-1.453739,52.880581],"type":"Point"}
}