{
  "type": "Feature",
  "properties": {
    "iso:country":"GB",
    "wof:name":"CB4 1QB",
    "wof:placetype":"postalcode"
},
  "geometry": {"coordinates":[0.13654932420966,52.21938531928608],"type":"Point"}
}