{
  "type": "Feature",
  "properties": {
    "iso:country":"GB",
    "wof:name":"CB4 3HA",
    "wof:placetype":"postalcode"
},
  "geometry": {"coordinates":[0.11333043628031,52.22063072572688],"type":"Point"}
}