{
  "type": "Feature",
  "properties": {
    "iso:country": "GB",
    "wof:name": "CB4 3HA",
    "wof:placetype": "postalcode"
  },
  "geometry": {"coordinates":[0.11333,52.220631],"type":"Point"}
}
