{
  "type": "Feature",
  "properties": {
    "iso:country":"GB",
    "wof:name":"PE15 8YD",
    "wof:placetype":"postalcode"
},
  "geometry": {"coordinates":[0.0993981883903,52.55860511164109],"type":"Point"}
}