{
  "type": "Feature",
  "properties": {
    "iso:country":"GB",
    "wof:name":"SE9 6JG",
    "wof:placetype":"postalcode"
},
  "geometry": {"coordinates":[0.03716970197,51.45819293383273],"type":"Point"}
}