{
  "type": "Feature",
  "properties": {
    "iso:country":"GB",
    "wof:name":"PR7 2QE",
    "wof:placetype":"postalcode"
},
  "geometry": {"coordinates":[-2.64522972535454,53.64899421606304],"type":"Point"}
}