{
  "type": "Feature",
  "properties": {
    "iso:country":"GB",
    "wof:name":"LS8 4DA",
    "wof:placetype":"postalcode"
},
  "geometry": {"coordinates":[-1.5119316557185,53.82382287527546],"type":"Point"}
}