{
  "type": "Feature",
  "properties": {
    "date:inception_lower": "1980-01-01",
    "date:inception_upper": "1980-01-01",
    "iso:country": "GB",
    "wof:name": "L10 4YE",
    "wof:placetype": "postalcode"
  },
  "geometry": {"coordinates":[-2.90841,53.468763],"type":"Point"}
}
