{
  "type": "Feature",
  "properties": {
    "iso:country": "GB",
    "wof:name": "L10 4YE",
    "wof:placetype": "postalcode"
  },
  "geometry": {"coordinates":[-2.90841,53.468763],"type":"Point"}
}
