{
  "type": "Feature",
  "properties": {
    "iso:country":"GB",
    "wof:name":"L10 4YE",
    "wof:placetype":"postalcode"
},
  "geometry": {"coordinates":[-2.90840972247382,53.46876250884721],"type":"Point"}
}