{
  "type": "Feature",
  "properties": {
    "iso:country":"GB",
    "wof:name":"DG9 0NU",
    "wof:placetype":"postalcode"
},
  "geometry": {"coordinates":[-5.10145570863071,54.97514048089257],"type":"Point"}
}