{
  "type": "Feature",
  "properties": {
    "iso:country": "GB",
    "wof:name": "DG9 0NU",
    "wof:placetype": "postalcode"
  },
  "geometry": {"coordinates":[-5.10143,54.97515],"type":"Point"}
}
