{
  "type": "Feature",
  "properties": {
    "iso:country":"GB",
    "wof:name":"CB6 3QT",
    "wof:placetype":"postalcode"
},
  "geometry": {"coordinates":[0.24434088017537,52.39384237865564],"type":"Point"}
}