{
  "type": "Feature",
  "properties": {
    "date:inception_lower": "1996-06-01",
    "date:inception_upper": "1996-06-01",
    "iso:country": "GB",
    "wof:name": "CB6 3QT",
    "wof:placetype": "postalcode"
  },
  "geometry": {"coordinates":[0.244341,52.393842],"type":"Point"}
}
