{
  "type": "Feature",
  "properties": {
    "iso:country":"GB",
    "wof:name":"G14 0LP",
    "wof:placetype":"postalcode"
},
  "geometry": {"coordinates":[-4.37256244576994,55.8862803765473],"type":"Point"}
}