{
  "type": "Feature",
  "properties": {
    "iso:country":"GB",
    "wof:name":"UB1 1LG",
    "wof:placetype":"postalcode"
},
  "geometry": {"coordinates":[-0.37925457041453,51.51054087100807],"type":"Point"}
}