{
  "type": "Feature",
  "properties": {
    "iso:country": "GB",
    "wof:name": "BN3 7GT",
    "wof:placetype": "postalcode"
  },
  "geometry": {"coordinates":[-0.202579,50.837581],"type":"Point"}
}
