{
  "type": "Feature",
  "properties": {
    "iso:country":"GB",
    "wof:name":"BN3 7GT",
    "wof:placetype":"postalcode"
},
  "geometry": {"coordinates":[-0.20257930565957,50.83758092453766],"type":"Point"}
}