{
  "type": "Feature",
  "properties": {
    "iso:country":"GB",
    "wof:name":"GU1 1HB",
    "wof:placetype":"postalcode"
},
  "geometry": {"coordinates":[-0.57110176230322,51.24707048405551],"type":"Point"}
}