{
  "type": "Feature",
  "properties": {
    "iso:country":"GB",
    "wof:name":"GL2 8DS",
    "wof:placetype":"postalcode"
},
  "geometry": {"coordinates":[-2.31813000963337,51.88818725565287],"type":"Point"}
}