{
  "type": "Feature",
  "properties": {
    "iso:country":"GB",
    "wof:name":"WS10 9DH",
    "wof:placetype":"postalcode"
},
  "geometry": {"coordinates":[-2.01864416602432,52.5558175159223],"type":"Point"}
}