{
  "type": "Feature",
  "properties": {
    "iso:country":"GB",
    "wof:name":"SK23 6DH",
    "wof:placetype":"postalcode"
},
  "geometry": {"coordinates":[-1.93494907760696,53.33727255955917],"type":"Point"}
}