{
  "type": "Feature",
  "properties": {
    "date:inception_lower": "1996-12-01",
    "date:inception_upper": "1996-12-01",
    "iso:country": "GB",
    "wof:name": "SK23 6DH",
    "wof:placetype": "postalcode"
  },
  "geometry": {"coordinates":[-1.934949,53.337273],"type":"Point"}
}
