{
  "type": "Feature",
  "properties": {
    "iso:country":"GB",
    "wof:name":"BB1 5NN",
    "wof:placetype":"postalcode"
},
  "geometry": {"coordinates":[-2.46860656419851,53.75948098792865],"type":"Point"}
}