{
  "type": "Feature",
  "properties": {
    "iso:country": "GB",
    "wof:name": "BB1 5NN",
    "wof:placetype": "postalcode"
  },
  "geometry": {"coordinates":[-2.468665,53.75946],"type":"Point"}
}
