{
  "type": "Feature",
  "properties": {
    "iso:country":"GB",
    "wof:name":"BA9 9PS",
    "wof:placetype":"postalcode"
},
  "geometry": {"coordinates":[-2.35825068336983,51.04913310759515],"type":"Point"}
}