{
  "type": "Feature",
  "properties": {
    "iso:country":"GB",
    "wof:name":"CH5 3US",
    "wof:placetype":"postalcode"
},
  "geometry": {"coordinates":[-2.98919215905838,53.17567986081571],"type":"Point"}
}