{
  "type": "Feature",
  "properties": {
    "iso:country": "GB",
    "wof:name": "CH5 3US",
    "wof:placetype": "postalcode"
  },
  "geometry": {"coordinates":[-2.989192,53.17568],"type":"Point"}
}
