{
  "type": "Feature",
  "properties": {
    "date:inception_lower":"2007-05-01",
    "date:inception_upper":"2007-05-31",
    "iso:country":"GB",
    "wof:name":"CH5 3US",
    "wof:placetype":"postalcode"
},
  "geometry": {"coordinates":[-2.989192,53.17568],"type":"Point"}
}