{
  "type": "Feature",
  "properties": {
    "iso:country": "GB",
    "wof:name": "PR26 7SA",
    "wof:placetype": "postalcode"
  },
  "geometry": {"coordinates":[-2.726863,53.689423],"type":"Point"}
}
