{
  "type": "Feature",
  "properties": {
    "iso:country":"GB",
    "wof:name":"PR26 7SA",
    "wof:placetype":"postalcode"
},
  "geometry": {"coordinates":[-2.72686309454623,53.6894233458446],"type":"Point"}
}