{
  "type": "Feature",
  "properties": {
    "iso:country":"GB",
    "wof:name":"PL5 1DZ",
    "wof:placetype":"postalcode"
},
  "geometry": {"coordinates":[-4.19420464046978,50.39966816698757],"type":"Point"}
}