{
  "type": "Feature",
  "properties": {
    "iso:country":"GB",
    "wof:name":"PL25 4LN",
    "wof:placetype":"postalcode"
},
  "geometry": {"coordinates":[-4.77859261004272,50.34120348567224],"type":"Point"}
}