{
  "type": "Feature",
  "properties": {
    "iso:country":"GB",
    "wof:name":"SW4 8AE",
    "wof:placetype":"postalcode"
},
  "geometry": {"coordinates":[-0.13434408708166,51.45433043861176],"type":"Point"}
}