{
  "type": "Feature",
  "properties": {
    "iso:country": "GB",
    "wof:name": "CW2 5WG",
    "wof:placetype": "postalcode"
  },
  "geometry": {"coordinates":[-2.441122,53.067784],"type":"Point"}
}
