{
  "type": "Feature",
  "properties": {
    "date:inception_lower": "2019-11-01",
    "date:inception_upper": "2019-11-01",
    "iso:country": "GB",
    "wof:name": "CW2 5WG",
    "wof:placetype": "postalcode"
  },
  "geometry": {"coordinates":[-2.441122,53.067784],"type":"Point"}
}
