{
  "type": "Feature",
  "properties": {
    "date:inception_lower": "2019-03-01",
    "date:inception_upper": "2019-03-01",
    "iso:country": "GB",
    "wof:name": "M20 2NP",
    "wof:placetype": "postalcode"
  },
  "geometry": {"coordinates":[-2.250237,53.425635],"type":"Point"}
}
