{
  "type": "Feature",
  "properties": {
    "iso:country":"GB",
    "wof:name":"GU6 8SU",
    "wof:placetype":"postalcode"
},
  "geometry": {"coordinates":[-0.49659871486957,51.14320807492933],"type":"Point"}
}