{
  "type": "Feature",
  "properties": {
    "iso:country": "GB",
    "wof:name": "GU6 8SU",
    "wof:placetype": "postalcode"
  },
  "geometry": {"coordinates":[-0.496599,51.143208],"type":"Point"}
}
