{
  "type": "Feature",
  "properties": {
    "iso:country":"GB",
    "wof:name":"OX5 1RA",
    "wof:placetype":"postalcode"
},
  "geometry": {"coordinates":[-1.31542836725509,51.8327898942697],"type":"Point"}
}