{
  "type": "Feature",
  "properties": {
    "iso:country":"GB",
    "wof:name":"GU26 6NT",
    "wof:placetype":"postalcode"
},
  "geometry": {"coordinates":[-0.75325785519056,51.12271896960685],"type":"Point"}
}