{
  "type": "Feature",
  "properties": {
    "iso:country":"GB",
    "wof:name":"PL8 2JB",
    "wof:placetype":"postalcode"
},
  "geometry": {"coordinates":[-3.97244160543119,50.32863881624453],"type":"Point"}
}