{
  "type": "Feature",
  "properties": {
    "date:inception_lower": "1980-01-01",
    "date:inception_upper": "1980-01-01",
    "iso:country": "GB",
    "wof:name": "PL8 2JB",
    "wof:placetype": "postalcode"
  },
  "geometry": {"coordinates":[-3.971018,50.3306],"type":"Point"}
}
