{
  "type": "Feature",
  "properties": {
    "iso:country": "GB",
    "wof:name": "SE25 4TN",
    "wof:placetype": "postalcode"
  },
  "geometry": {"coordinates":[-0.070708,51.400423],"type":"Point"}
}
