{
  "type": "Feature",
  "properties": {
    "iso:country": "GB",
    "wof:name": "EH29 9FJ",
    "wof:placetype": "postalcode"
  },
  "geometry": {"coordinates":[-3.40481,55.960122],"type":"Point"}
}
