{
  "type": "Feature",
  "properties": {
    "date:inception_lower":"2011-05-01",
    "date:inception_upper":"2011-05-31",
    "iso:country":"GB",
    "wof:name":"EH29 9FJ",
    "wof:placetype":"postalcode"
},
  "geometry": {"coordinates":[-3.40481,55.960122],"type":"Point"}
}