{
  "type": "Feature",
  "properties": {
    "iso:country":"GB",
    "wof:name":"GL3 2QR",
    "wof:placetype":"postalcode"
},
  "geometry": {"coordinates":[-2.18189252242501,51.87986372405025],"type":"Point"}
}