{
  "type": "Feature",
  "properties": {
    "iso:country":"GB",
    "wof:name":"AB10 6RZ",
    "wof:placetype":"postalcode"
},
  "geometry": {"coordinates":[-2.12443985576064,57.13660105277739],"type":"Point"}
}