{
  "type": "Feature",
  "properties": {
    "iso:country":"GB",
    "wof:name":"NR25 6HE",
    "wof:placetype":"postalcode"
},
  "geometry": {"coordinates":[1.09092976792319,52.90946731878349],"type":"Point"}
}