{
  "type": "Feature",
  "properties": {
    "iso:country":"GB",
    "wof:name":"CT1 1BN",
    "wof:placetype":"postalcode"
},
  "geometry": {"coordinates":[1.08690637453936,51.28469058094065],"type":"Point"}
}