{
  "type": "Feature",
  "properties": {
    "iso:country":"GB",
    "wof:name":"M9 5TQ",
    "wof:placetype":"postalcode"
},
  "geometry": {"coordinates":[-2.22527606411054,53.50600771837074],"type":"Point"}
}