{
  "type": "Feature",
  "properties": {
    "iso:country": "GB",
    "wof:name": "SE12 0JE",
    "wof:placetype": "postalcode"
  },
  "geometry": {"coordinates":[0.01234,51.44971],"type":"Point"}
}
