{
  "type": "Feature",
  "properties": {
    "iso:country":"GB",
    "wof:name":"SE12 0JE",
    "wof:placetype":"postalcode"
},
  "geometry": {"coordinates":[0.01233950818218,51.44970996901519],"type":"Point"}
}