{
  "type": "Feature",
  "properties": {
    "iso:country": "GB",
    "wof:name": "DH1 1RZ",
    "wof:placetype": "postalcode"
  },
  "geometry": {"coordinates":[-1.567235,54.779023],"type":"Point"}
}
