{
  "type": "Feature",
  "properties": {
    "date:inception_lower":"1982-03-01",
    "date:inception_upper":"1982-03-31",
    "iso:country":"GB",
    "wof:name":"DH1 1RZ",
    "wof:placetype":"postalcode"
},
  "geometry": {"coordinates":[-1.567235,54.779023],"type":"Point"}
}