{
  "type": "Feature",
  "properties": {
    "iso:country": "GB",
    "wof:name": "MK2 2JB",
    "wof:placetype": "postalcode"
  },
  "geometry": {"coordinates":[-0.715424,51.995161],"type":"Point"}
}
