{
  "type": "Feature",
  "properties": {
    "date:inception_lower": "1980-01-01",
    "date:inception_upper": "1980-01-01",
    "iso:country": "GB",
    "wof:name": "MK2 2JB",
    "wof:placetype": "postalcode"
  },
  "geometry": {"coordinates":[-0.715424,51.995161],"type":"Point"}
}
