{
  "type": "Feature",
  "properties": {
    "iso:country":"GB",
    "wof:name":"MK2 2JB",
    "wof:placetype":"postalcode"
},
  "geometry": {"coordinates":[-0.71542397778613,51.99516071096321],"type":"Point"}
}