{
  "type": "Feature",
  "properties": {
    "iso:country":"GB",
    "wof:name":"BA5 2UY",
    "wof:placetype":"postalcode"
},
  "geometry": {"coordinates":[-2.63847903320072,51.21297059435069],"type":"Point"}
}