{
  "type": "Feature",
  "properties": {
    "iso:country":"GB",
    "wof:name":"OL14 7QT",
    "wof:placetype":"postalcode"
},
  "geometry": {"coordinates":[-2.1028100570492,53.6949653930989],"type":"Point"}
}