{
  "type": "Feature",
  "properties": {
    "date:inception_lower": "1987-10-01",
    "date:inception_upper": "1987-10-01",
    "iso:country": "GB",
    "wof:name": "OL14 7QT",
    "wof:placetype": "postalcode"
  },
  "geometry": {"coordinates":[-2.103052,53.694756],"type":"Point"}
}
