{
  "type": "Feature",
  "properties": {
    "iso:country": "GB",
    "wof:name": "BA14 9TR",
    "wof:placetype": "postalcode"
  },
  "geometry": {"coordinates":[-2.22355,51.317573],"type":"Point"}
}
