{
  "type": "Feature",
  "properties": {
    "iso:country":"GB",
    "wof:name":"DE4 2LW",
    "wof:placetype":"postalcode"
},
  "geometry": {"coordinates":[-1.64696640279307,53.17550024580066],"type":"Point"}
}