{
  "type": "Feature",
  "properties": {
    "iso:country":"GB",
    "wof:name":"M7 1RU",
    "wof:placetype":"postalcode"
},
  "geometry": {"coordinates":[-2.25817402808491,53.493501137076],"type":"Point"}
}