{
  "type": "Feature",
  "properties": {
    "iso:country": "GB",
    "wof:name": "NG23 7DN",
    "wof:placetype": "postalcode"
  },
  "geometry": {"coordinates":[-0.692846,53.245465],"type":"Point"}
}
