{
  "type": "Feature",
  "properties": {
    "iso:country":"GB",
    "wof:name":"NG23 7DN",
    "wof:placetype":"postalcode"
},
  "geometry": {"coordinates":[-0.69284722151746,53.24544405735909],"type":"Point"}
}