{
  "type": "Feature",
  "properties": {
    "date:inception_lower": "1980-01-01",
    "date:inception_upper": "1980-01-01",
    "iso:country": "GB",
    "wof:name": "BL9 9DN",
    "wof:placetype": "postalcode"
  },
  "geometry": {"coordinates":[-2.28722,53.584981],"type":"Point"}
}
