{
  "type": "Feature",
  "properties": {
    "iso:country": "GB",
    "wof:name": "S6 4LA",
    "wof:placetype": "postalcode"
  },
  "geometry": {"coordinates":[-1.503106,53.401272],"type":"Point"}
}
