{
  "type": "Feature",
  "properties": {
    "date:inception_lower":"1994-05-01",
    "date:inception_upper":"1994-05-31",
    "iso:country":"GB",
    "wof:name":"LS25 1QH",
    "wof:placetype":"postalcode"
},
  "geometry": {"coordinates":[-1.385824,53.797384],"type":"Point"}
}