{
  "type": "Feature",
  "properties": {
    "iso:country":"GB",
    "wof:name":"LS25 1QH",
    "wof:placetype":"postalcode"
},
  "geometry": {"coordinates":[-1.38561288330939,53.79700648837924],"type":"Point"}
}