{
  "type": "Feature",
  "properties": {
    "date:inception_lower": "2013-12-01",
    "date:inception_upper": "2013-12-01",
    "iso:country": "GB",
    "wof:name": "EH6 7JR",
    "wof:placetype": "postalcode"
  },
  "geometry": {"coordinates":[-3.1606,55.973675],"type":"Point"}
}
