{
  "type": "Feature",
  "properties": {
    "iso:country": "GB",
    "wof:name": "EH6 7JR",
    "wof:placetype": "postalcode"
  },
  "geometry": {"coordinates":[-3.160537,55.973694],"type":"Point"}
}
