{
  "type": "Feature",
  "properties": {
    "iso:country": "GB",
    "wof:name": "EH6 7JR",
    "wof:placetype": "postalcode"
  },
  "geometry": {"coordinates":[-3.1606,55.973675],"type":"Point"}
}
