{
  "type": "Feature",
  "properties": {
    "iso:country":"GB",
    "wof:name":"NN18 0AW",
    "wof:placetype":"postalcode"
},
  "geometry": {"coordinates":[-0.72145640061347,52.48740514851529],"type":"Point"}
}