{
  "type": "Feature",
  "properties": {
    "iso:country": "GB",
    "wof:name": "UB10 9BD",
    "wof:placetype": "postalcode"
  },
  "geometry": {"coordinates":[-0.448378,51.543344],"type":"Point"}
}
