{
  "type": "Feature",
  "properties": {
    "iso:country":"GB",
    "wof:name":"UB10 9BD",
    "wof:placetype":"postalcode"
},
  "geometry": {"coordinates":[-0.44837777153151,51.54334380851019],"type":"Point"}
}