{
  "type": "Feature",
  "properties": {
    "iso:country": "GB",
    "wof:name": "TA18 8EL",
    "wof:placetype": "postalcode"
  },
  "geometry": {"coordinates":[-2.791053,50.880661],"type":"Point"}
}
