{
  "type": "Feature",
  "properties": {
    "iso:country":"GB",
    "wof:name":"TA18 8EL",
    "wof:placetype":"postalcode"
},
  "geometry": {"coordinates":[-2.79105258583204,50.88066148958919],"type":"Point"}
}