{
  "type": "Feature",
  "properties": {
    "date:inception_lower": "1980-01-01",
    "date:inception_upper": "1980-01-01",
    "iso:country": "GB",
    "wof:name": "DD2 4TQ",
    "wof:placetype": "postalcode"
  },
  "geometry": {"coordinates":[-3.039559,56.468006],"type":"Point"}
}
