{
  "type": "Feature",
  "properties": {
    "iso:country":"GB",
    "wof:name":"DD2 4TQ",
    "wof:placetype":"postalcode"
},
  "geometry": {"coordinates":[-3.03842104018689,56.46687451785643],"type":"Point"}
}