{
  "type": "Feature",
  "properties": {
    "iso:country": "GB",
    "wof:name": "DD2 4TQ",
    "wof:placetype": "postalcode"
  },
  "geometry": {"coordinates":[-3.038421,56.466875],"type":"Point"}
}
