{
  "type": "Feature",
  "properties": {
    "date:inception_lower": "1980-01-01",
    "date:inception_upper": "1980-01-01",
    "iso:country": "GB",
    "wof:name": "DT10 2JE",
    "wof:placetype": "postalcode"
  },
  "geometry": {"coordinates":[-2.381617,50.932961],"type":"Point"}
}
