{
  "type": "Feature",
  "properties": {
    "iso:country":"GB",
    "wof:name":"DT10 2JE",
    "wof:placetype":"postalcode"
},
  "geometry": {"coordinates":[-2.38273997680725,50.93250631882583],"type":"Point"}
}