{
  "type": "Feature",
  "properties": {
    "iso:country": "GB",
    "wof:name": "DT10 2JE",
    "wof:placetype": "postalcode"
  },
  "geometry": {"coordinates":[-2.382738,50.932499],"type":"Point"}
}
