{
  "type": "Feature",
  "properties": {
    "date:inception_lower":"1994-05-01",
    "date:inception_upper":"1994-05-31",
    "iso:country":"GB",
    "wof:name":"AB51 5NU",
    "wof:placetype":"postalcode"
},
  "geometry": {"coordinates":[-2.400597,57.260132],"type":"Point"}
}