{
  "type": "Feature",
  "properties": {
    "iso:country":"GB",
    "wof:name":"LD1 5UR",
    "wof:placetype":"postalcode"
},
  "geometry": {"coordinates":[-3.18952786304108,52.32882659562225],"type":"Point"}
}