{
  "type": "Feature",
  "properties": {
    "date:inception_lower": "1993-08-01",
    "date:inception_upper": "1993-08-01",
    "iso:country": "GB",
    "wof:name": "LD1 5UR",
    "wof:placetype": "postalcode"
  },
  "geometry": {"coordinates":[-3.189528,52.328827],"type":"Point"}
}
