{
  "type": "Feature",
  "properties": {
    "iso:country": "GB",
    "wof:name": "LD1 5UR",
    "wof:placetype": "postalcode"
  },
  "geometry": {"coordinates":[-3.189528,52.328827],"type":"Point"}
}
