{
  "type": "Feature",
  "properties": {
    "iso:country":"GB",
    "wof:name":"NW10 8EQ",
    "wof:placetype":"postalcode"
},
  "geometry": {"coordinates":[-0.26080833749573,51.53976013105239],"type":"Point"}
}