{
  "type": "Feature",
  "properties": {
    "iso:country":"GB",
    "wof:name":"LS13 2RJ",
    "wof:placetype":"postalcode"
},
  "geometry": {"coordinates":[-1.61821482632852,53.81154388796629],"type":"Point"}
}