{
  "type": "Feature",
  "properties": {
    "iso:country":"GB",
    "wof:name":"CF37 2NE",
    "wof:placetype":"postalcode"
},
  "geometry": {"coordinates":[-3.37717496113478,51.60867404875211],"type":"Point"}
}