{
  "type": "Feature",
  "properties": {
    "date:inception_lower": "1980-01-01",
    "date:inception_upper": "1980-01-01",
    "iso:country": "GB",
    "wof:name": "B65 0JN",
    "wof:placetype": "postalcode"
  },
  "geometry": {"coordinates":[-2.038118,52.476081],"type":"Point"}
}
