{
  "type": "Feature",
  "properties": {
    "iso:country": "GB",
    "wof:name": "CV31 2EX",
    "wof:placetype": "postalcode"
  },
  "geometry": {"coordinates":[-1.525725,52.272436],"type":"Point"}
}
