{
  "type": "Feature",
  "properties": {
    "iso:country": "GB",
    "wof:name": "PL27 6SR",
    "wof:placetype": "postalcode"
  },
  "geometry": {"coordinates":[-4.914547,50.573135],"type":"Point"}
}
