{
  "type": "Feature",
  "properties": {
    "iso:country":"GB",
    "wof:name":"PL27 6SR",
    "wof:placetype":"postalcode"
},
  "geometry": {"coordinates":[-4.91454677536168,50.57313515902402],"type":"Point"}
}