{
  "type": "Feature",
  "properties": {
    "iso:country":"GB",
    "wof:name":"M8 5UY",
    "wof:placetype":"postalcode"
},
  "geometry": {"coordinates":[-2.22542714315965,53.51174204031681],"type":"Point"}
}