{
  "type": "Feature",
  "properties": {
    "iso:country": "GB",
    "wof:name": "WF10 5QD",
    "wof:placetype": "postalcode"
  },
  "geometry": {"coordinates":[-1.390105,53.715408],"type":"Point"}
}
