{
  "type": "Feature",
  "properties": {
    "date:inception_lower":"2002-10-01",
    "date:inception_upper":"2002-10-31",
    "iso:country":"GB",
    "wof:name":"PE33 9SE",
    "wof:placetype":"postalcode"
},
  "geometry": {"coordinates":[0.512783,52.570324],"type":"Point"}
}