{
  "type": "Feature",
  "properties": {
    "iso:country":"GB",
    "wof:name":"PE33 9SE",
    "wof:placetype":"postalcode"
},
  "geometry": {"coordinates":[0.51278299690795,52.57032371821204],"type":"Point"}
}