{
  "type": "Feature",
  "properties": {
    "iso:country":"GB",
    "wof:name":"M16 8FR",
    "wof:placetype":"postalcode"
},
  "geometry": {"coordinates":[-2.25321948990788,53.45379169354177],"type":"Point"}
}