{
  "type": "Feature",
  "properties": {
    "date:inception_lower":"1992-01-01",
    "date:inception_upper":"1992-01-31",
    "iso:country":"GB",
    "wof:name":"M16 8FR",
    "wof:placetype":"postalcode"
},
  "geometry": {"coordinates":[-2.253219,53.453792],"type":"Point"}
}