{
  "type": "Feature",
  "properties": {
    "iso:country":"GB",
    "wof:name":"E1 4HR",
    "wof:placetype":"postalcode"
},
  "geometry": {"coordinates":[-0.05277363129928,51.52301162884694],"type":"Point"}
}