{
  "type": "Feature",
  "properties": {
    "iso:country":"GB",
    "wof:name":"CR7 8JG",
    "wof:placetype":"postalcode"
},
  "geometry": {"coordinates":[-0.10059991437159,51.40382529530438],"type":"Point"}
}