{
  "type": "Feature",
  "properties": {
    "iso:country":"GB",
    "wof:name":"WD18 0RD",
    "wof:placetype":"postalcode"
},
  "geometry": {"coordinates":[-0.40143271676663,51.65285794166205],"type":"Point"}
}