{
  "type": "Feature",
  "properties": {
    "iso:country":"GB",
    "wof:name":"BA15 1AE",
    "wof:placetype":"postalcode"
},
  "geometry": {"coordinates":[-2.24553631627589,51.3477413317496],"type":"Point"}
}