{
  "type": "Feature",
  "properties": {
    "iso:country":"GB",
    "wof:name":"EH32 9ED",
    "wof:placetype":"postalcode"
},
  "geometry": {"coordinates":[-2.97801705097372,55.95874096458927],"type":"Point"}
}