{
  "type": "Feature",
  "properties": {
    "iso:country": "GB",
    "wof:name": "ME13 0SB",
    "wof:placetype": "postalcode"
  },
  "geometry": {"coordinates":[0.835653,51.290081],"type":"Point"}
}
