{
  "type": "Feature",
  "properties": {
    "iso:country":"GB",
    "wof:name":"M11 2DT",
    "wof:placetype":"postalcode"
},
  "geometry": {"coordinates":[-2.20015768781858,53.47411655239745],"type":"Point"}
}