{
  "type": "Feature",
  "properties": {
    "date:inception_lower": "2022-07-01",
    "date:inception_upper": "2022-07-01",
    "iso:country": "GB",
    "wof:name": "IP25 7FQ",
    "wof:placetype": "postalcode"
  },
  "geometry": {"coordinates":[0.788948,52.610058],"type":"Point"}
}
