{
  "type": "Feature",
  "properties": {
    "iso:country":"GB",
    "wof:name":"WV15 5JG",
    "wof:placetype":"postalcode"
},
  "geometry": {"coordinates":[-2.37842053140221,52.52917865618744],"type":"Point"}
}