{
  "type": "Feature",
  "properties": {
    "date:inception_lower":"1980-01-01",
    "date:inception_upper":"1980-01-31",
    "iso:country":"GB",
    "wof:name":"WV15 5JG",
    "wof:placetype":"postalcode"
},
  "geometry": {"coordinates":[-2.37842,52.529179],"type":"Point"}
}