{
  "type": "Feature",
  "properties": {
    "iso:country":"GB",
    "wof:name":"SA61 2LJ",
    "wof:placetype":"postalcode"
},
  "geometry": {"coordinates":[-4.96783075209846,51.80368805811215],"type":"Point"}
}