{
  "type": "Feature",
  "properties": {
    "iso:country": "GB",
    "wof:name": "SA61 2LJ",
    "wof:placetype": "postalcode"
  },
  "geometry": {"coordinates":[-4.96777,51.803605],"type":"Point"}
}
