{
  "type": "Feature",
  "properties": {
    "date:inception_lower": "1992-01-01",
    "date:inception_upper": "1992-01-01",
    "iso:country": "GB",
    "wof:name": "SA61 2LJ",
    "wof:placetype": "postalcode"
  },
  "geometry": {"coordinates":[-4.967863,51.803701],"type":"Point"}
}
