{
  "type": "Feature",
  "properties": {
    "iso:country":"GB",
    "wof:name":"WS9 9HW",
    "wof:placetype":"postalcode"
},
  "geometry": {"coordinates":[-1.8743594999017,52.63010720407623],"type":"Point"}
}