{
  "type": "Feature",
  "properties": {
    "date:inception_lower": "2007-09-01",
    "date:inception_upper": "2007-09-01",
    "iso:country": "GB",
    "wof:name": "WS9 9HW",
    "wof:placetype": "postalcode"
  },
  "geometry": {"coordinates":[-1.874353,52.630123],"type":"Point"}
}
