{
  "type": "Feature",
  "properties": {
    "iso:country":"GB",
    "wof:name":"LE3 2EU",
    "wof:placetype":"postalcode"
},
  "geometry": {"coordinates":[-1.15691670510163,52.61489546845696],"type":"Point"}
}