{
  "type": "Feature",
  "properties": {
    "iso:country": "GB",
    "wof:name": "LE3 2EU",
    "wof:placetype": "postalcode"
  },
  "geometry": {"coordinates":[-1.156917,52.614895],"type":"Point"}
}
