{
  "type": "Feature",
  "properties": {
    "date:inception_lower": "2019-07-01",
    "date:inception_upper": "2019-07-01",
    "iso:country": "GB",
    "wof:name": "CB9 8AY",
    "wof:placetype": "postalcode"
  },
  "geometry": {"coordinates":[0.432238,52.082473],"type":"Point"}
}
