{
  "type": "Feature",
  "properties": {
    "date:inception_lower": "1999-12-01",
    "date:inception_upper": "1999-12-01",
    "iso:country": "GB",
    "wof:name": "RG41 2QE",
    "wof:placetype": "postalcode"
  },
  "geometry": {"coordinates":[-0.850891,51.40228],"type":"Point"}
}
