{
  "type": "Feature",
  "properties": {
    "iso:country":"GB",
    "wof:name":"PL27 6NP",
    "wof:placetype":"postalcode"
},
  "geometry": {"coordinates":[-4.90618150798992,50.54715950317608],"type":"Point"}
}