{
  "type": "Feature",
  "properties": {
    "iso:country": "GB",
    "wof:name": "PL27 6NP",
    "wof:placetype": "postalcode"
  },
  "geometry": {"coordinates":[-4.906181,50.54716],"type":"Point"}
}
