{
  "type": "Feature",
  "properties": {
    "date:inception_lower": "1980-01-01",
    "date:inception_upper": "1980-01-01",
    "iso:country": "GB",
    "wof:name": "PL27 6NP",
    "wof:placetype": "postalcode"
  },
  "geometry": {"coordinates":[-4.906181,50.54716],"type":"Point"}
}
