{
  "type": "Feature",
  "properties": {
    "date:inception_lower": "2023-04-01",
    "date:inception_upper": "2023-04-01",
    "iso:country": "GB",
    "wof:name": "TF6 5FL",
    "wof:placetype": "postalcode"
  },
  "geometry": {"coordinates":[-2.584235,52.708262],"type":"Point"}
}
