{
  "type": "Feature",
  "properties": {
    "iso:country": "GB",
    "wof:name": "DN14 0XJ",
    "wof:placetype": "postalcode"
  },
  "geometry": {"coordinates":[-1.149044,53.702929],"type":"Point"}
}
