{
  "type": "Feature",
  "properties": {
    "iso:country":"GB",
    "wof:name":"DN14 0XJ",
    "wof:placetype":"postalcode"
},
  "geometry": {"coordinates":[-1.14899671418289,53.70281983747135],"type":"Point"}
}