{
  "type": "Feature",
  "properties": {
    "date:inception_lower": "2000-06-01",
    "date:inception_upper": "2000-06-01",
    "iso:country": "GB",
    "wof:name": "DN14 0XJ",
    "wof:placetype": "postalcode"
  },
  "geometry": {"coordinates":[-1.149044,53.702929],"type":"Point"}
}
