{
  "type": "Feature",
  "properties": {
    "iso:country":"GB",
    "wof:name":"NG15 6HS",
    "wof:placetype":"postalcode"
},
  "geometry": {"coordinates":[-1.22367868453552,53.02621502357424],"type":"Point"}
}