{
  "type": "Feature",
  "properties": {
    "iso:country":"GB",
    "wof:name":"HD3 3DY",
    "wof:placetype":"postalcode"
},
  "geometry": {"coordinates":[-1.81744766924976,53.65430750135365],"type":"Point"}
}