{
  "type": "Feature",
  "properties": {
    "iso:country": "GB",
    "wof:name": "HD3 3DY",
    "wof:placetype": "postalcode"
  },
  "geometry": {"coordinates":[-1.817448,53.654307],"type":"Point"}
}
