{
  "type": "Feature",
  "properties": {
    "iso:country": "GB",
    "wof:name": "KY12 8BT",
    "wof:placetype": "postalcode"
  },
  "geometry": {"coordinates":[-3.600938,56.059541],"type":"Point"}
}
