{
  "type": "Feature",
  "properties": {
    "iso:country":"GB",
    "wof:name":"SY7 9JX",
    "wof:placetype":"postalcode"
},
  "geometry": {"coordinates":[-2.73391633596054,52.47043822266484],"type":"Point"}
}