{
  "type": "Feature",
  "properties": {
    "iso:country": "GB",
    "wof:name": "SY7 9JX",
    "wof:placetype": "postalcode"
  },
  "geometry": {"coordinates":[-2.73445,52.469856],"type":"Point"}
}
