{
  "type": "Feature",
  "properties": {
    "iso:country":"GB",
    "wof:name":"LA1 5AB",
    "wof:placetype":"postalcode"
},
  "geometry": {"coordinates":[-2.79907477343245,54.02815724992449],"type":"Point"}
}