{
  "type": "Feature",
  "properties": {
    "iso:country":"GB",
    "wof:name":"CT9 2BN",
    "wof:placetype":"postalcode"
},
  "geometry": {"coordinates":[1.38968289902268,51.38889238877723],"type":"Point"}
}