{
  "type": "Feature",
  "properties": {
    "date:inception_lower": "2008-02-01",
    "date:inception_upper": "2008-02-01",
    "iso:country": "GB",
    "wof:name": "CF48 1AU",
    "wof:placetype": "postalcode"
  },
  "geometry": {"coordinates":[-3.386468,51.745743],"type":"Point"}
}
