{
  "type": "Feature",
  "properties": {
    "iso:country": "GB",
    "wof:name": "CF48 1AU",
    "wof:placetype": "postalcode"
  },
  "geometry": {"coordinates":[-3.386468,51.745743],"type":"Point"}
}
