{
  "type": "Feature",
  "properties": {
    "iso:country":"GB",
    "wof:name":"CA7 2EX",
    "wof:placetype":"postalcode"
},
  "geometry": {"coordinates":[-3.32212866766916,54.73937905751027],"type":"Point"}
}