{
  "type": "Feature",
  "properties": {
    "iso:country":"GB",
    "wof:name":"KY5 0YF",
    "wof:placetype":"postalcode"
},
  "geometry": {"coordinates":[-3.2360630614575,56.17515327649774],"type":"Point"}
}