{
  "type": "Feature",
  "properties": {
    "date:inception_lower": "1994-05-01",
    "date:inception_upper": "1994-05-01",
    "iso:country": "GB",
    "wof:name": "FY5 2BY",
    "wof:placetype": "postalcode"
  },
  "geometry": {"coordinates":[-3.023794,53.883991],"type":"Point"}
}
