{
  "type": "Feature",
  "properties": {
    "date:inception_lower":"1980-01-01",
    "date:inception_upper":"1980-01-31",
    "iso:country":"GB",
    "wof:name":"DL12 9QL",
    "wof:placetype":"postalcode"
},
  "geometry": {"coordinates":[-1.973448,54.582661],"type":"Point"}
}