{
  "type": "Feature",
  "properties": {
    "iso:country":"GB",
    "wof:name":"DL12 9QL",
    "wof:placetype":"postalcode"
},
  "geometry": {"coordinates":[-1.97344826042156,54.58266060600881],"type":"Point"}
}