{
  "type": "Feature",
  "properties": {
    "iso:country":"GB",
    "wof:name":"BD19 6EJ",
    "wof:placetype":"postalcode"
},
  "geometry": {"coordinates":[-1.74947180807335,53.73026034380415],"type":"Point"}
}