{
  "type": "Feature",
  "properties": {
    "iso:country": "GB",
    "wof:name": "BD19 6EJ",
    "wof:placetype": "postalcode"
  },
  "geometry": {"coordinates":[-1.749472,53.73026],"type":"Point"}
}
