{
  "type": "Feature",
  "properties": {
    "iso:country":"GB",
    "wof:name":"SA1 5AP",
    "wof:placetype":"postalcode"
},
  "geometry": {"coordinates":[-3.94107611298192,51.62632092666605],"type":"Point"}
}