{
  "type": "Feature",
  "properties": {
    "date:inception_lower":"1998-06-01",
    "date:inception_upper":"1998-06-30",
    "iso:country":"GB",
    "wof:name":"KA26 9GD",
    "wof:placetype":"postalcode"
},
  "geometry": {"coordinates":[-4.739096,55.276888],"type":"Point"}
}