{
  "type": "Feature",
  "properties": {
    "iso:country":"GB",
    "wof:name":"KA26 9GD",
    "wof:placetype":"postalcode"
},
  "geometry": {"coordinates":[-4.7390957241025,55.27688817849273],"type":"Point"}
}