{
  "type": "Feature",
  "properties": {
    "iso:country":"GB",
    "wof:name":"GL20 7BT",
    "wof:placetype":"postalcode"
},
  "geometry": {"coordinates":[-2.13779479678994,51.96273817469727],"type":"Point"}
}