{
  "type": "Feature",
  "properties": {
    "iso:country": "GB",
    "wof:name": "GL20 7BT",
    "wof:placetype": "postalcode"
  },
  "geometry": {"coordinates":[-2.137795,51.962738],"type":"Point"}
}
