{
  "type": "Feature",
  "properties": {
    "date:inception_lower":"1980-01-01",
    "date:inception_upper":"1980-01-31",
    "iso:country":"GB",
    "wof:name":"GL20 7BT",
    "wof:placetype":"postalcode"
},
  "geometry": {"coordinates":[-2.137795,51.962738],"type":"Point"}
}