{
  "type": "Feature",
  "properties": {
    "iso:country": "GB",
    "wof:name": "N6 5AG",
    "wof:placetype": "postalcode"
  },
  "geometry": {"coordinates":[-0.141694,51.576637],"type":"Point"}
}
