{
  "type": "Feature",
  "properties": {
    "iso:country":"GB",
    "wof:name":"BD2 3DJ",
    "wof:placetype":"postalcode"
},
  "geometry": {"coordinates":[-1.73187209720057,53.81159988040388],"type":"Point"}
}