{
  "type": "Feature",
  "properties": {
    "date:inception_lower": "1980-01-01",
    "date:inception_upper": "1980-01-01",
    "iso:country": "GB",
    "wof:name": "SE8 4JG",
    "wof:placetype": "postalcode"
  },
  "geometry": {"coordinates":[-0.020411,51.469152],"type":"Point"}
}
