{
  "type": "Feature",
  "properties": {
    "iso:country":"GB",
    "wof:name":"HA9 9BY",
    "wof:placetype":"postalcode"
},
  "geometry": {"coordinates":[-0.26408545594705,51.56239736570744],"type":"Point"}
}