{
  "type": "Feature",
  "properties": {
    "iso:country": "GB",
    "wof:name": "B36 9TA",
    "wof:placetype": "postalcode"
  },
  "geometry": {"coordinates":[-1.773191,52.511282],"type":"Point"}
}
