{
  "type": "Feature",
  "properties": {
    "iso:country":"GB",
    "wof:name":"B36 9TA",
    "wof:placetype":"postalcode"
},
  "geometry": {"coordinates":[-1.77319147594329,52.51128211633204],"type":"Point"}
}