{
  "type": "Feature",
  "properties": {
    "date:inception_lower":"1983-01-01",
    "date:inception_upper":"1983-01-31",
    "iso:country":"GB",
    "wof:name":"B36 9TA",
    "wof:placetype":"postalcode"
},
  "geometry": {"coordinates":[-1.773191,52.511282],"type":"Point"}
}