{
  "type": "Feature",
  "properties": {
    "iso:country": "GB",
    "wof:name": "CO1 1DH",
    "wof:placetype": "postalcode"
  },
  "geometry": {"coordinates":[0.900648,51.889587],"type":"Point"}
}
