{
  "type": "Feature",
  "properties": {
    "iso:country":"GB",
    "wof:name":"HP27 9HR",
    "wof:placetype":"postalcode"
},
  "geometry": {"coordinates":[-0.83315773150541,51.72954057089778],"type":"Point"}
}