{
  "type": "Feature",
  "properties": {
    "iso:country":"GB",
    "wof:name":"PE36 5AX",
    "wof:placetype":"postalcode"
},
  "geometry": {"coordinates":[0.48538280774935,52.93168026200136],"type":"Point"}
}