{
  "type": "Feature",
  "properties": {
    "iso:country": "GB",
    "wof:name": "PE36 5AX",
    "wof:placetype": "postalcode"
  },
  "geometry": {"coordinates":[0.485383,52.93168],"type":"Point"}
}
