{
  "type": "Feature",
  "properties": {
    "date:inception_lower": "1980-01-01",
    "date:inception_upper": "1980-01-01",
    "iso:country": "GB",
    "wof:name": "OX3 9LG",
    "wof:placetype": "postalcode"
  },
  "geometry": {"coordinates":[-1.201316,51.767999],"type":"Point"}
}
