{
  "type": "Feature",
  "properties": {
    "date:inception_lower": "1987-04-01",
    "date:inception_upper": "1987-04-01",
    "iso:country": "GB",
    "wof:name": "SG14 2TH",
    "wof:placetype": "postalcode"
  },
  "geometry": {"coordinates":[-0.100111,51.795456],"type":"Point"}
}
