{
  "type": "Feature",
  "properties": {
    "iso:country":"GB",
    "wof:name":"NW7 2PL",
    "wof:placetype":"postalcode"
},
  "geometry": {"coordinates":[-0.22399365200741,51.610841473185],"type":"Point"}
}