{
  "type": "Feature",
  "properties": {
    "iso:country": "GB",
    "wof:name": "NW7 2PL",
    "wof:placetype": "postalcode"
  },
  "geometry": {"coordinates":[-0.22407,51.610735],"type":"Point"}
}
