{
  "type": "Feature",
  "properties": {
    "iso:country":"GB",
    "wof:name":"PL15 9NN",
    "wof:placetype":"postalcode"
},
  "geometry": {"coordinates":[-4.3322059557152,50.59707201342516],"type":"Point"}
}