{
  "type": "Feature",
  "properties": {
    "date:inception_lower": "2002-11-01",
    "date:inception_upper": "2002-11-01",
    "iso:country": "GB",
    "wof:name": "NG14 6BP",
    "wof:placetype": "postalcode"
  },
  "geometry": {"coordinates":[-1.08148,53.043092],"type":"Point"}
}
