{
  "type": "Feature",
  "properties": {
    "iso:country":"GB",
    "wof:name":"OL11 3HB",
    "wof:placetype":"postalcode"
},
  "geometry": {"coordinates":[-2.17726905927027,53.59954039930813],"type":"Point"}
}