{
  "type": "Feature",
  "properties": {
    "iso:country": "GB",
    "wof:name": "OL11 3HB",
    "wof:placetype": "postalcode"
  },
  "geometry": {"coordinates":[-2.177269,53.59954],"type":"Point"}
}
