{
  "type": "Feature",
  "properties": {
    "iso:country": "GB",
    "wof:name": "TA14 6AB",
    "wof:placetype": "postalcode"
  },
  "geometry": {"coordinates":[-2.730047,50.954332],"type":"Point"}
}
