{
  "type": "Feature",
  "properties": {
    "iso:country": "GB",
    "wof:name": "CR0 3RP",
    "wof:placetype": "postalcode"
  },
  "geometry": {"coordinates":[-0.112237,51.378987],"type":"Point"}
}
