{
  "type": "Feature",
  "properties": {
    "iso:country":"GB",
    "wof:name":"OL8 2RP",
    "wof:placetype":"postalcode"
},
  "geometry": {"coordinates":[-2.10078322179133,53.51875252034316],"type":"Point"}
}