{
  "type": "Feature",
  "properties": {
    "iso:country": "GB",
    "wof:name": "NP44 3XQ",
    "wof:placetype": "postalcode"
  },
  "geometry": {"coordinates":[-3.040283,51.651967],"type":"Point"}
}
