{
  "type": "Feature",
  "properties": {
    "iso:country": "GB",
    "wof:name": "GL53 8AH",
    "wof:placetype": "postalcode"
  },
  "geometry": {"coordinates":[-2.053231,51.885657],"type":"Point"}
}
