{
  "type": "Feature",
  "properties": {
    "date:inception_lower": "1980-01-01",
    "date:inception_upper": "1980-01-01",
    "iso:country": "GB",
    "wof:name": "GL53 8AH",
    "wof:placetype": "postalcode"
  },
  "geometry": {"coordinates":[-2.053231,51.885657],"type":"Point"}
}
