{
  "type": "Feature",
  "properties": {
    "iso:country":"GB",
    "wof:name":"NE37 1BJ",
    "wof:placetype":"postalcode"
},
  "geometry": {"coordinates":[-1.53233899891055,54.90773319720612],"type":"Point"}
}