{
  "type": "Feature",
  "properties": {
    "date:inception_lower":"1984-10-01",
    "date:inception_upper":"1984-10-31",
    "iso:country":"GB",
    "wof:name":"NE37 1BJ",
    "wof:placetype":"postalcode"
},
  "geometry": {"coordinates":[-1.532339,54.907733],"type":"Point"}
}