{
  "type": "Feature",
  "properties": {
    "iso:country":"GB",
    "wof:name":"SO16 7AL",
    "wof:placetype":"postalcode"
},
  "geometry": {"coordinates":[-1.41536404201872,50.93434303580464],"type":"Point"}
}