{
  "type": "Feature",
  "properties": {
    "date:inception_lower": "1980-01-01",
    "date:inception_upper": "1980-01-01",
    "iso:country": "GB",
    "wof:name": "CV2 3HS",
    "wof:placetype": "postalcode"
  },
  "geometry": {"coordinates":[-1.475104,52.422584],"type":"Point"}
}
