{
  "type": "Feature",
  "properties": {
    "iso:country": "GB",
    "wof:name": "CF44 8HE",
    "wof:placetype": "postalcode"
  },
  "geometry": {"coordinates":[-3.464485,51.715277],"type":"Point"}
}
