{
  "type": "Feature",
  "properties": {
    "iso:country":"GB",
    "wof:name":"CF44 8HE",
    "wof:placetype":"postalcode"
},
  "geometry": {"coordinates":[-3.46448525939241,51.71527690001485],"type":"Point"}
}