{
  "type": "Feature",
  "properties": {
    "iso:country":"GB",
    "wof:name":"HA2 9NE",
    "wof:placetype":"postalcode"
},
  "geometry": {"coordinates":[-0.37340984172635,51.57104053658698],"type":"Point"}
}