{
  "type": "Feature",
  "properties": {
    "iso:country": "GB",
    "wof:name": "CH8 8PN",
    "wof:placetype": "postalcode"
  },
  "geometry": {"coordinates":[-3.2653,53.274198],"type":"Point"}
}
