{
  "type": "Feature",
  "properties": {
    "iso:country":"GB",
    "wof:name":"CH8 8PN",
    "wof:placetype":"postalcode"
},
  "geometry": {"coordinates":[-3.26529987167518,53.27419757949828],"type":"Point"}
}