{
  "type": "Feature",
  "properties": {
    "iso:country":"GB",
    "wof:name":"B94 6JY",
    "wof:placetype":"postalcode"
},
  "geometry": {"coordinates":[-1.73207141244938,52.33820039323951],"type":"Point"}
}