{
  "type": "Feature",
  "properties": {
    "iso:country":"GB",
    "wof:name":"HA4 7JW",
    "wof:placetype":"postalcode"
},
  "geometry": {"coordinates":[-0.43515306446937,51.57530605188124],"type":"Point"}
}