{
  "type": "Feature",
  "properties": {
    "iso:country":"GB",
    "wof:name":"TS1 3AD",
    "wof:placetype":"postalcode"
},
  "geometry": {"coordinates":[-1.23677026453336,54.57272758492277],"type":"Point"}
}