{
  "type": "Feature",
  "properties": {
    "iso:country":"GB",
    "wof:name":"N21 2RX",
    "wof:placetype":"postalcode"
},
  "geometry": {"coordinates":[-0.09451299236947,51.63394480482884],"type":"Point"}
}