{
  "type": "Feature",
  "properties": {
    "date:inception_lower":"1999-06-01",
    "date:inception_upper":"1999-06-30",
    "iso:country":"GB",
    "wof:name":"NP19 7BN",
    "wof:placetype":"postalcode"
},
  "geometry": {"coordinates":[-2.975805,51.602375],"type":"Point"}
}