{
  "type": "Feature",
  "properties": {
    "iso:country":"GB",
    "wof:name":"NP19 7BN",
    "wof:placetype":"postalcode"
},
  "geometry": {"coordinates":[-2.9758048942158,51.60237514764305],"type":"Point"}
}