{
  "type": "Feature",
  "properties": {
    "iso:country": "GB",
    "wof:name": "NP19 7BN",
    "wof:placetype": "postalcode"
  },
  "geometry": {"coordinates":[-2.975805,51.602375],"type":"Point"}
}
