{
  "type": "Feature",
  "properties": {
    "iso:country":"GB",
    "wof:name":"LN8 6DF",
    "wof:placetype":"postalcode"
},
  "geometry": {"coordinates":[-0.17809947339398,53.42658733375024],"type":"Point"}
}