{
  "type": "Feature",
  "properties": {
    "date:inception_lower": "1980-01-01",
    "date:inception_upper": "1980-01-01",
    "iso:country": "GB",
    "wof:name": "S10 4PR",
    "wof:placetype": "postalcode"
  },
  "geometry": {"coordinates":[-1.559203,53.360773],"type":"Point"}
}
