{
  "type": "Feature",
  "properties": {
    "iso:country":"GB",
    "wof:name":"S10 4PR",
    "wof:placetype":"postalcode"
},
  "geometry": {"coordinates":[-1.55945847186026,53.36083735532346],"type":"Point"}
}