{
  "type": "Feature",
  "properties": {
    "date:inception_lower": "1996-12-01",
    "date:inception_upper": "1996-12-01",
    "iso:country": "GB",
    "wof:name": "B2 4AE",
    "wof:placetype": "postalcode"
  },
  "geometry": {"coordinates":[-1.895696,52.479566],"type":"Point"}
}
