{
  "type": "Feature",
  "properties": {
    "date:inception_lower":"1980-01-01",
    "date:inception_upper":"1980-01-31",
    "iso:country":"GB",
    "wof:name":"CB8 0QH",
    "wof:placetype":"postalcode"
},
  "geometry": {"coordinates":[0.392544,52.244497],"type":"Point"}
}