{
  "type": "Feature",
  "properties": {
    "date:inception_lower": "1981-06-01",
    "date:inception_upper": "1981-06-01",
    "iso:country": "GB",
    "wof:name": "SK1 3JA",
    "wof:placetype": "postalcode"
  },
  "geometry": {"coordinates":[-2.151056,53.40167],"type":"Point"}
}
