{
  "type": "Feature",
  "properties": {
    "iso:country": "GB",
    "wof:name": "SK1 3JA",
    "wof:placetype": "postalcode"
  },
  "geometry": {"coordinates":[-2.151056,53.40167],"type":"Point"}
}
