{
  "type": "Feature",
  "properties": {
    "iso:country":"GB",
    "wof:name":"SP8 5AF",
    "wof:placetype":"postalcode"
},
  "geometry": {"coordinates":[-2.29891408761563,51.07717576044886],"type":"Point"}
}