{
  "type": "Feature",
  "properties": {
    "iso:country":"GB",
    "wof:name":"W3 0EL",
    "wof:placetype":"postalcode"
},
  "geometry": {"coordinates":[-0.28466870505115,51.51841293450213],"type":"Point"}
}