{
  "type": "Feature",
  "properties": {
    "date:inception_lower":"2007-07-01",
    "date:inception_upper":"2007-07-31",
    "iso:country":"GB",
    "wof:name":"YO43 4TH",
    "wof:placetype":"postalcode"
},
  "geometry": {"coordinates":[-0.574445,53.824724],"type":"Point"}
}