{
  "type": "Feature",
  "properties": {
    "iso:country": "GB",
    "wof:name": "TR18 3FE",
    "wof:placetype": "postalcode"
  },
  "geometry": {"coordinates":[-5.553195,50.128149],"type":"Point"}
}
