{
  "type": "Feature",
  "properties": {
    "date:inception_lower":"2008-06-01",
    "date:inception_upper":"2008-06-30",
    "iso:country":"GB",
    "wof:name":"TR18 3FE",
    "wof:placetype":"postalcode"
},
  "geometry": {"coordinates":[-5.553195,50.128149],"type":"Point"}
}