{
  "type": "Feature",
  "properties": {
    "iso:country":"GB",
    "wof:name":"TR18 3FE",
    "wof:placetype":"postalcode"
},
  "geometry": {"coordinates":[-5.55319530981299,50.12814925909039],"type":"Point"}
}