{
  "type": "Feature",
  "properties": {
    "iso:country": "GB",
    "wof:name": "SE15 6NP",
    "wof:placetype": "postalcode"
  },
  "geometry": {"coordinates":[-0.073819,51.485788],"type":"Point"}
}
