{
  "type": "Feature",
  "properties": {
    "date:inception_lower": "2019-09-01",
    "date:inception_upper": "2019-09-01",
    "iso:country": "GB",
    "wof:name": "EH20 9FH",
    "wof:placetype": "postalcode"
  },
  "geometry": {"coordinates":[-3.154432,55.88494],"type":"Point"}
}
