{
  "type": "Feature",
  "properties": {
    "iso:country": "GB",
    "wof:name": "EH20 9FH",
    "wof:placetype": "postalcode"
  },
  "geometry": {"coordinates":[-3.155574,55.885163],"type":"Point"}
}
