{
  "type": "Feature",
  "properties": {
    "iso:country":"GB",
    "wof:name":"SE12 0UF",
    "wof:placetype":"postalcode"
},
  "geometry": {"coordinates":[0.00584697675602,51.44868815941606],"type":"Point"}
}