{
  "type": "Feature",
  "properties": {
    "date:inception_lower": "1996-12-01",
    "date:inception_upper": "1996-12-01",
    "iso:country": "GB",
    "wof:name": "SE12 0UF",
    "wof:placetype": "postalcode"
  },
  "geometry": {"coordinates":[0.005895,51.448535],"type":"Point"}
}
