{
  "type": "Feature",
  "properties": {
    "iso:country": "GB",
    "wof:name": "E1W 3WD",
    "wof:placetype": "postalcode"
  },
  "geometry": {"coordinates":[-0.043766,51.510182],"type":"Point"}
}
