{
  "type": "Feature",
  "properties": {
    "iso:country": "GB",
    "wof:name": "S13 7UB",
    "wof:placetype": "postalcode"
  },
  "geometry": {"coordinates":[-1.365676,53.359192],"type":"Point"}
}
