{
  "type": "Feature",
  "properties": {
    "date:inception_lower": "2022-11-01",
    "date:inception_upper": "2022-11-01",
    "iso:country": "GB",
    "wof:name": "EC2Y 5EB",
    "wof:placetype": "postalcode"
  },
  "geometry": {"coordinates":[-0.09603,51.517285],"type":"Point"}
}
