{
  "type": "Feature",
  "properties": {
    "iso:country":"GB",
    "wof:name":"BH21 5NS",
    "wof:placetype":"postalcode"
},
  "geometry": {"coordinates":[-1.94479954150342,50.91469613136668],"type":"Point"}
}