{
  "type": "Feature",
  "properties": {
    "date:inception_lower": "1980-01-01",
    "date:inception_upper": "1980-01-01",
    "iso:country": "GB",
    "wof:name": "BH21 5NS",
    "wof:placetype": "postalcode"
  },
  "geometry": {"coordinates":[-1.944992,50.91441],"type":"Point"}
}
