{
  "type": "Feature",
  "properties": {
    "iso:country":"GB",
    "wof:name":"TW4 5HG",
    "wof:placetype":"postalcode"
},
  "geometry": {"coordinates":[-0.37857176490223,51.46318703328511],"type":"Point"}
}