{
  "type": "Feature",
  "properties": {
    "iso:country": "GB",
    "wof:name": "BD23 6NW",
    "wof:placetype": "postalcode"
  },
  "geometry": {"coordinates":[-1.998073,53.976511],"type":"Point"}
}
