{
  "type": "Feature",
  "properties": {
    "date:inception_lower": "1980-01-01",
    "date:inception_upper": "1980-01-01",
    "iso:country": "GB",
    "wof:name": "BD23 6NW",
    "wof:placetype": "postalcode"
  },
  "geometry": {"coordinates":[-1.998047,53.976534],"type":"Point"}
}
