{
  "type": "Feature",
  "properties": {
    "iso:country":"GB",
    "wof:name":"BD23 6NW",
    "wof:placetype":"postalcode"
},
  "geometry": {"coordinates":[-1.99807342447847,53.97651069151234],"type":"Point"}
}