{
  "type": "Feature",
  "properties": {
    "date:inception_lower":"2005-04-01",
    "date:inception_upper":"2005-04-30",
    "iso:country":"GB",
    "wof:name":"IP33 2EA",
    "wof:placetype":"postalcode"
},
  "geometry": {"coordinates":[0.694882,52.234571],"type":"Point"}
}