{
  "type": "Feature",
  "properties": {
    "iso:country": "GB",
    "wof:name": "IP33 2EA",
    "wof:placetype": "postalcode"
  },
  "geometry": {"coordinates":[0.694882,52.234571],"type":"Point"}
}
