{
  "type": "Feature",
  "properties": {
    "iso:country":"GB",
    "wof:name":"LN5 8TN",
    "wof:placetype":"postalcode"
},
  "geometry": {"coordinates":[-0.55675777582298,53.19405369842946],"type":"Point"}
}