{
  "type": "Feature",
  "properties": {
    "date:inception_lower": "1981-06-01",
    "date:inception_upper": "1981-06-01",
    "iso:country": "GB",
    "wof:name": "LN5 8TN",
    "wof:placetype": "postalcode"
  },
  "geometry": {"coordinates":[-0.556758,53.194054],"type":"Point"}
}
