{
  "type": "Feature",
  "properties": {
    "iso:country": "GB",
    "wof:name": "BN15 9QT",
    "wof:placetype": "postalcode"
  },
  "geometry": {"coordinates":[-0.331369,50.832014],"type":"Point"}
}
