{
  "type": "Feature",
  "properties": {
    "iso:country":"GB",
    "wof:name":"BN15 9QT",
    "wof:placetype":"postalcode"
},
  "geometry": {"coordinates":[-0.33136370269512,50.83212821193312],"type":"Point"}
}