{
  "type": "Feature",
  "properties": {
    "iso:country": "GB",
    "wof:name": "NP4 6SX",
    "wof:placetype": "postalcode"
  },
  "geometry": {"coordinates":[-3.055187,51.71209],"type":"Point"}
}
