{
  "type": "Feature",
  "properties": {
    "iso:country": "GB",
    "wof:name": "ME8 8SZ",
    "wof:placetype": "postalcode"
  },
  "geometry": {"coordinates":[0.603905,51.342681],"type":"Point"}
}
