{
  "type": "Feature",
  "properties": {
    "iso:country":"GB",
    "wof:name":"ME8 8SZ",
    "wof:placetype":"postalcode"
},
  "geometry": {"coordinates":[0.60390502269415,51.34268131609454],"type":"Point"}
}