{
  "type": "Feature",
  "properties": {
    "iso:country": "GB",
    "wof:name": "ML1 4TX",
    "wof:placetype": "postalcode"
  },
  "geometry": {"coordinates":[-3.96845,55.825126],"type":"Point"}
}
