{
  "type": "Feature",
  "properties": {
    "iso:country":"GB",
    "wof:name":"CM8 2LR",
    "wof:placetype":"postalcode"
},
  "geometry": {"coordinates":[0.64073827614801,51.81560753722346],"type":"Point"}
}