{
  "type": "Feature",
  "properties": {
    "iso:country":"GB",
    "wof:name":"M40 9BY",
    "wof:placetype":"postalcode"
},
  "geometry": {"coordinates":[-2.19565305776277,53.50684192574301],"type":"Point"}
}