{
  "type": "Feature",
  "properties": {
    "iso:country":"GB",
    "wof:name":"HR2 6AY",
    "wof:placetype":"postalcode"
},
  "geometry": {"coordinates":[-2.71349948226075,52.04434282732877],"type":"Point"}
}