{
  "type": "Feature",
  "properties": {
    "iso:country": "GB",
    "wof:name": "HR2 6AY",
    "wof:placetype": "postalcode"
  },
  "geometry": {"coordinates":[-2.713499,52.044343],"type":"Point"}
}
