{
  "type": "Feature",
  "properties": {
    "iso:country":"GB",
    "wof:name":"EH3 7AU",
    "wof:placetype":"postalcode"
},
  "geometry": {"coordinates":[-3.21117879618556,55.94936439243517],"type":"Point"}
}