{
  "type": "Feature",
  "properties": {
    "iso:country":"GB",
    "wof:name":"TN6 2RS",
    "wof:placetype":"postalcode"
},
  "geometry": {"coordinates":[0.16612803130145,51.05772371606539],"type":"Point"}
}