{
  "type": "Feature",
  "properties": {
    "iso:country":"GB",
    "wof:name":"BR3 3LN",
    "wof:placetype":"postalcode"
},
  "geometry": {"coordinates":[-0.02351185069315,51.3996996764529],"type":"Point"}
}