{
  "type": "Feature",
  "properties": {
    "iso:country": "GB",
    "wof:name": "BR3 3LN",
    "wof:placetype": "postalcode"
  },
  "geometry": {"coordinates":[-0.023512,51.3997],"type":"Point"}
}
