{
  "type": "Feature",
  "properties": {
    "date:inception_lower": "1980-01-01",
    "date:inception_upper": "1980-01-01",
    "iso:country": "GB",
    "wof:name": "DD11 4TS",
    "wof:placetype": "postalcode"
  },
  "geometry": {"coordinates":[-2.663666,56.63804],"type":"Point"}
}
