{
  "type": "Feature",
  "properties": {
    "iso:country": "GB",
    "wof:name": "YO11 2RT",
    "wof:placetype": "postalcode"
  },
  "geometry": {"coordinates":[-0.40327,54.270859],"type":"Point"}
}
