{
  "type": "Feature",
  "properties": {
    "iso:country":"GB",
    "wof:name":"YO11 2RT",
    "wof:placetype":"postalcode"
},
  "geometry": {"coordinates":[-0.4032535117254,54.27084145145437],"type":"Point"}
}