{
  "type": "Feature",
  "properties": {
    "iso:country":"GB",
    "wof:name":"PO36 9JB",
    "wof:placetype":"postalcode"
},
  "geometry": {"coordinates":[-1.17485490680684,50.64855912285294],"type":"Point"}
}