{
  "type": "Feature",
  "properties": {
    "iso:country":"GB",
    "wof:name":"G12 9NZ",
    "wof:placetype":"postalcode"
},
  "geometry": {"coordinates":[-4.30080293252976,55.87996769130172],"type":"Point"}
}