{
  "type": "Feature",
  "properties": {
    "date:inception_lower":"2013-08-01",
    "date:inception_upper":"2013-08-31",
    "iso:country":"GB",
    "wof:name":"KY11 8YY",
    "wof:placetype":"postalcode"
},
  "geometry": {"coordinates":[-3.40646,56.07485],"type":"Point"}
}