{
  "type": "Feature",
  "properties": {
    "date:inception_lower":"1980-01-01",
    "date:inception_upper":"1980-01-31",
    "iso:country":"GB",
    "wof:name":"PE13 2RD",
    "wof:placetype":"postalcode"
},
  "geometry": {"coordinates":[0.15992,52.652933],"type":"Point"}
}