{
  "type": "Feature",
  "properties": {
    "iso:country":"GB",
    "wof:name":"PE13 2RD",
    "wof:placetype":"postalcode"
},
  "geometry": {"coordinates":[0.15991978425558,52.65293332485729],"type":"Point"}
}