{
  "type": "Feature",
  "properties": {
    "iso:country": "GB",
    "wof:name": "NG12 3GS",
    "wof:placetype": "postalcode"
  },
  "geometry": {"coordinates":[-0.979474,52.912181],"type":"Point"}
}
