{
  "type": "Feature",
  "properties": {
    "iso:country": "GB",
    "wof:name": "CO11 2DD",
    "wof:placetype": "postalcode"
  },
  "geometry": {"coordinates":[1.08795,51.940674],"type":"Point"}
}
