{
  "type": "Feature",
  "properties": {
    "iso:country":"GB",
    "wof:name":"B42 2DL",
    "wof:placetype":"postalcode"
},
  "geometry": {"coordinates":[-1.91148478143928,52.53600844494171],"type":"Point"}
}