{
  "type": "Feature",
  "properties": {
    "date:inception_lower": "2021-03-01",
    "date:inception_upper": "2021-03-01",
    "iso:country": "GB",
    "wof:name": "GU15 3FE",
    "wof:placetype": "postalcode"
  },
  "geometry": {"coordinates":[-0.744827,51.336898],"type":"Point"}
}
