{
  "type": "Feature",
  "properties": {
    "iso:country":"GB",
    "wof:name":"SY13 2PG",
    "wof:placetype":"postalcode"
},
  "geometry": {"coordinates":[-2.74001963176682,52.92054780376849],"type":"Point"}
}