{
  "type": "Feature",
  "properties": {
    "iso:country":"GB",
    "wof:name":"MK16 9AL",
    "wof:placetype":"postalcode"
},
  "geometry": {"coordinates":[-0.71625769730123,52.08563903693349],"type":"Point"}
}