{
  "type": "Feature",
  "properties": {
    "iso:country": "GB",
    "wof:name": "MK16 9AL",
    "wof:placetype": "postalcode"
  },
  "geometry": {"coordinates":[-0.716362,52.085577],"type":"Point"}
}
