{
  "type": "Feature",
  "properties": {
    "iso:country":"GB",
    "wof:name":"SM5 3LF",
    "wof:placetype":"postalcode"
},
  "geometry": {"coordinates":[-0.17006469873516,51.35681992168265],"type":"Point"}
}