{
  "type": "Feature",
  "properties": {
    "date:inception_lower": "1985-10-01",
    "date:inception_upper": "1985-10-01",
    "iso:country": "GB",
    "wof:name": "SE1 0LB",
    "wof:placetype": "postalcode"
  },
  "geometry": {"coordinates":[-0.096897,51.503691],"type":"Point"}
}
