{
  "type": "Feature",
  "properties": {
    "iso:country":"GB",
    "wof:name":"SE1 0LB",
    "wof:placetype":"postalcode"
},
  "geometry": {"coordinates":[-0.09689683935115,51.50369141754633],"type":"Point"}
}