{
  "type": "Feature",
  "properties": {
    "iso:country":"GB",
    "wof:name":"SM5 4AL",
    "wof:placetype":"postalcode"
},
  "geometry": {"coordinates":[-0.1667677902675,51.34118401536008],"type":"Point"}
}