{
  "type": "Feature",
  "properties": {
    "iso:country":"GB",
    "wof:name":"CV7 8NN",
    "wof:placetype":"postalcode"
},
  "geometry": {"coordinates":[-1.5295563732528,52.46276501116678],"type":"Point"}
}