{
  "type": "Feature",
  "properties": {
    "iso:country":"GB",
    "wof:name":"PL17 8QH",
    "wof:placetype":"postalcode"
},
  "geometry": {"coordinates":[-4.34723634310873,50.56090049201],"type":"Point"}
}