{
  "type": "Feature",
  "properties": {
    "iso:country": "GB",
    "wof:name": "PL17 8QH",
    "wof:placetype": "postalcode"
  },
  "geometry": {"coordinates":[-4.347236,50.5609],"type":"Point"}
}
