{
  "type": "Feature",
  "properties": {
    "iso:country":"GB",
    "wof:name":"E10 5LS",
    "wof:placetype":"postalcode"
},
  "geometry": {"coordinates":[-0.01346858741702,51.56228873245376],"type":"Point"}
}