{
  "type": "Feature",
  "properties": {
    "iso:country":"GB",
    "wof:name":"NG6 9DG",
    "wof:placetype":"postalcode"
},
  "geometry": {"coordinates":[-1.18456167600368,52.99186556060376],"type":"Point"}
}