{
  "type": "Feature",
  "properties": {
    "iso:country":"GB",
    "wof:name":"TW15 2JU",
    "wof:placetype":"postalcode"
},
  "geometry": {"coordinates":[-0.46020198920832,51.43605171093015],"type":"Point"}
}