{
  "type": "Feature",
  "properties": {
    "date:inception_lower": "1980-01-01",
    "date:inception_upper": "1980-01-01",
    "iso:country": "GB",
    "wof:name": "HU17 9PJ",
    "wof:placetype": "postalcode"
  },
  "geometry": {"coordinates":[-0.419632,53.851657],"type":"Point"}
}
