{
  "type": "Feature",
  "properties": {
    "iso:country":"GB",
    "wof:name":"HU17 9PJ",
    "wof:placetype":"postalcode"
},
  "geometry": {"coordinates":[-0.41963233311603,53.85165725091753],"type":"Point"}
}