{
  "type": "Feature",
  "properties": {
    "date:inception_lower": "1999-06-01",
    "date:inception_upper": "1999-06-01",
    "iso:country": "GB",
    "wof:name": "CW1 4TX",
    "wof:placetype": "postalcode"
  },
  "geometry": {"coordinates":[-2.458079,53.120083],"type":"Point"}
}
