{
  "type": "Feature",
  "properties": {
    "iso:country":"GB",
    "wof:name":"CW1 4TX",
    "wof:placetype":"postalcode"
},
  "geometry": {"coordinates":[-2.45807872613794,53.12008310054988],"type":"Point"}
}