{
  "type": "Feature",
  "properties": {
    "iso:country":"GB",
    "wof:name":"DY5 3XB",
    "wof:placetype":"postalcode"
},
  "geometry": {"coordinates":[-2.12840134678517,52.48232857044973],"type":"Point"}
}