{
  "type": "Feature",
  "properties": {
    "iso:country": "GB",
    "wof:name": "DY5 3XB",
    "wof:placetype": "postalcode"
  },
  "geometry": {"coordinates":[-2.128454,52.482352],"type":"Point"}
}
