{
  "type": "Feature",
  "properties": {
    "date:inception_lower": "1980-01-01",
    "date:inception_upper": "1980-01-01",
    "iso:country": "GB",
    "wof:name": "PE10 0AB",
    "wof:placetype": "postalcode"
  },
  "geometry": {"coordinates":[-0.383427,52.785185],"type":"Point"}
}
