{
  "type": "Feature",
  "properties": {
    "iso:country":"GB",
    "wof:name":"RM11 2PZ",
    "wof:placetype":"postalcode"
},
  "geometry": {"coordinates":[0.23433172363463,51.57668025095683],"type":"Point"}
}