{
  "type": "Feature",
  "properties": {
    "date:inception_lower":"1980-01-01",
    "date:inception_upper":"1980-01-31",
    "iso:country":"GB",
    "wof:name":"RM11 2PZ",
    "wof:placetype":"postalcode"
},
  "geometry": {"coordinates":[0.234374,51.576709],"type":"Point"}
}