{
  "type": "Feature",
  "properties": {
    "iso:country": "GB",
    "wof:name": "RG10 9QU",
    "wof:placetype": "postalcode"
  },
  "geometry": {"coordinates":[-0.888994,51.475581],"type":"Point"}
}
