{
  "type": "Feature",
  "properties": {
    "iso:country": "GB",
    "wof:name": "ME17 4HQ",
    "wof:placetype": "postalcode"
  },
  "geometry": {"coordinates":[0.500849,51.23588],"type":"Point"}
}
