{
  "type": "Feature",
  "properties": {
    "date:inception_lower": "2022-02-01",
    "date:inception_upper": "2022-02-01",
    "iso:country": "GB",
    "wof:name": "NG15 6XL",
    "wof:placetype": "postalcode"
  },
  "geometry": {"coordinates":[-1.221683,53.017681],"type":"Point"}
}
