{
  "type": "Feature",
  "properties": {
    "iso:country":"GB",
    "wof:name":"KY2 5SW",
    "wof:placetype":"postalcode"
},
  "geometry": {"coordinates":[-3.17007563033867,56.11867685096632],"type":"Point"}
}