{
  "type": "Feature",
  "properties": {
    "date:inception_lower": "1980-01-01",
    "date:inception_upper": "1980-01-01",
    "iso:country": "GB",
    "wof:name": "PL28 8SE",
    "wof:placetype": "postalcode"
  },
  "geometry": {"coordinates":[-4.998747,50.53801],"type":"Point"}
}
