{
  "type": "Feature",
  "properties": {
    "iso:country": "GB",
    "wof:name": "PL28 8SE",
    "wof:placetype": "postalcode"
  },
  "geometry": {"coordinates":[-4.998747,50.53801],"type":"Point"}
}
