{
  "type": "Feature",
  "properties": {
    "iso:country":"GB",
    "wof:name":"PL28 8SE",
    "wof:placetype":"postalcode"
},
  "geometry": {"coordinates":[-4.99874747190554,50.53800998061016],"type":"Point"}
}