{
  "type": "Feature",
  "properties": {
    "iso:country":"GB",
    "wof:name":"LA2 0QR",
    "wof:placetype":"postalcode"
},
  "geometry": {"coordinates":[-2.70442975783817,54.0084995924136],"type":"Point"}
}