{
  "type": "Feature",
  "properties": {
    "iso:country": "GB",
    "wof:name": "LA2 0QR",
    "wof:placetype": "postalcode"
  },
  "geometry": {"coordinates":[-2.70443,54.0085],"type":"Point"}
}
