{
  "type": "Feature",
  "properties": {
    "iso:country": "GB",
    "wof:name": "IV18 0JE",
    "wof:placetype": "postalcode"
  },
  "geometry": {"coordinates":[-4.152932,57.694729],"type":"Point"}
}
