{
  "type": "Feature",
  "properties": {
    "iso:country":"GB",
    "wof:name":"IV18 0JE",
    "wof:placetype":"postalcode"
},
  "geometry": {"coordinates":[-4.15293251593455,57.69472892415053],"type":"Point"}
}