{
  "type": "Feature",
  "properties": {
    "iso:country":"GB",
    "wof:name":"BH12 2BU",
    "wof:placetype":"postalcode"
},
  "geometry": {"coordinates":[-1.93401968469969,50.73088359790133],"type":"Point"}
}