{
  "type": "Feature",
  "properties": {
    "iso:country":"GB",
    "wof:name":"SS3 8TW",
    "wof:placetype":"postalcode"
},
  "geometry": {"coordinates":[0.78287686762628,51.54500122534557],"type":"Point"}
}