{
  "type": "Feature",
  "properties": {
    "iso:country": "GB",
    "wof:name": "SS3 8TW",
    "wof:placetype": "postalcode"
  },
  "geometry": {"coordinates":[0.782877,51.545001],"type":"Point"}
}
