{
  "type": "Feature",
  "properties": {
    "iso:country":"GB",
    "wof:name":"SA33 5PL",
    "wof:placetype":"postalcode"
},
  "geometry": {"coordinates":[-4.48696403821048,51.89449089502636],"type":"Point"}
}