{
  "type": "Feature",
  "properties": {
    "date:inception_lower": "1980-01-01",
    "date:inception_upper": "1980-01-01",
    "iso:country": "GB",
    "wof:name": "TN32 5EJ",
    "wof:placetype": "postalcode"
  },
  "geometry": {"coordinates":[0.456159,50.984676],"type":"Point"}
}
