{
  "type": "Feature",
  "properties": {
    "iso:country":"GB",
    "wof:name":"M22 4GT",
    "wof:placetype":"postalcode"
},
  "geometry": {"coordinates":[-2.25369218442627,53.38911807340608],"type":"Point"}
}