{
  "type": "Feature",
  "properties": {
    "iso:country":"GB",
    "wof:name":"LE8 6NY",
    "wof:placetype":"postalcode"
},
  "geometry": {"coordinates":[-1.1821072145035,52.5708410965826],"type":"Point"}
}