{
  "type": "Feature",
  "properties": {
    "iso:country":"GB",
    "wof:name":"PO11 9NF",
    "wof:placetype":"postalcode"
},
  "geometry": {"coordinates":[-0.95991757807892,50.78347861903032],"type":"Point"}
}