{
  "type": "Feature",
  "properties": {
    "date:inception_lower": "1980-01-01",
    "date:inception_upper": "1980-01-01",
    "iso:country": "GB",
    "wof:name": "PA27 8BZ",
    "wof:placetype": "postalcode"
  },
  "geometry": {"coordinates":[-5.110732,56.152516],"type":"Point"}
}
