{
  "type": "Feature",
  "properties": {
    "iso:country":"GB",
    "wof:name":"PA27 8BZ",
    "wof:placetype":"postalcode"
},
  "geometry": {"coordinates":[-5.1107318908705,56.15251613879372],"type":"Point"}
}