{
  "type": "Feature",
  "properties": {
    "date:inception_lower":"2010-07-01",
    "date:inception_upper":"2010-07-31",
    "iso:country":"GB",
    "wof:name":"GL2 2EW",
    "wof:placetype":"postalcode"
},
  "geometry": {"coordinates":[-2.261617,51.817592],"type":"Point"}
}