{
  "type": "Feature",
  "properties": {
    "iso:country": "GB",
    "wof:name": "GL2 2EW",
    "wof:placetype": "postalcode"
  },
  "geometry": {"coordinates":[-2.261617,51.817592],"type":"Point"}
}
