{
  "type": "Feature",
  "properties": {
    "iso:country":"GB",
    "wof:name":"LS28 7SP",
    "wof:placetype":"postalcode"
},
  "geometry": {"coordinates":[-1.67588909097188,53.79446550979144],"type":"Point"}
}