{
  "type": "Feature",
  "properties": {
    "iso:country": "GB",
    "wof:name": "BH23 8BU",
    "wof:placetype": "postalcode"
  },
  "geometry": {"coordinates":[-1.735892,50.784281],"type":"Point"}
}
