{
  "type": "Feature",
  "properties": {
    "iso:country":"GB",
    "wof:name":"BH23 8BU",
    "wof:placetype":"postalcode"
},
  "geometry": {"coordinates":[-1.7358923939804,50.78428064867594],"type":"Point"}
}