{
  "type": "Feature",
  "properties": {
    "iso:country":"GB",
    "wof:name":"BA16 9SE",
    "wof:placetype":"postalcode"
},
  "geometry": {"coordinates":[-2.76176073691942,51.14275056575612],"type":"Point"}
}