{
  "type": "Feature",
  "properties": {
    "iso:country":"GB",
    "wof:name":"NE45 5QA",
    "wof:placetype":"postalcode"
},
  "geometry": {"coordinates":[-1.99870321527872,55.01138034190009],"type":"Point"}
}