{
  "type": "Feature",
  "properties": {
    "iso:country": "GB",
    "wof:name": "CT6 6HD",
    "wof:placetype": "postalcode"
  },
  "geometry": {"coordinates":[1.139464,51.36437],"type":"Point"}
}
