{
  "type": "Feature",
  "properties": {
    "iso:country":"GB",
    "wof:name":"CT6 6HD",
    "wof:placetype":"postalcode"
},
  "geometry": {"coordinates":[1.13946437924866,51.36437010611682],"type":"Point"}
}