{
  "type": "Feature",
  "properties": {
    "date:inception_lower": "1980-01-01",
    "date:inception_upper": "1980-01-01",
    "iso:country": "GB",
    "wof:name": "CT6 6HD",
    "wof:placetype": "postalcode"
  },
  "geometry": {"coordinates":[1.139464,51.36437],"type":"Point"}
}
