{
  "type": "Feature",
  "properties": {
    "iso:country": "GB",
    "wof:name": "LN6 7BB",
    "wof:placetype": "postalcode"
  },
  "geometry": {"coordinates":[-0.554415,53.21787],"type":"Point"}
}
