{
  "type": "Feature",
  "properties": {
    "iso:country":"GB",
    "wof:name":"LN6 7BB",
    "wof:placetype":"postalcode"
},
  "geometry": {"coordinates":[-0.55430067714024,53.21814316130482],"type":"Point"}
}