{
  "type": "Feature",
  "properties": {
    "iso:country":"GB",
    "wof:name":"BR6 7QA",
    "wof:placetype":"postalcode"
},
  "geometry": {"coordinates":[0.15080134147982,51.36405674057772],"type":"Point"}
}