{
  "type": "Feature",
  "properties": {
    "iso:country":"GB",
    "wof:name":"SP4 0LB",
    "wof:placetype":"postalcode"
},
  "geometry": {"coordinates":[-1.72787849345391,51.12822769396981],"type":"Point"}
}