{
  "type": "Feature",
  "properties": {
    "iso:country":"GB",
    "wof:name":"WR5 2SB",
    "wof:placetype":"postalcode"
},
  "geometry": {"coordinates":[-2.19363979793571,52.16174754683668],"type":"Point"}
}