{
  "type": "Feature",
  "properties": {
    "iso:country": "GB",
    "wof:name": "WR5 2SB",
    "wof:placetype": "postalcode"
  },
  "geometry": {"coordinates":[-2.19364,52.161748],"type":"Point"}
}
