{
  "type": "Feature",
  "properties": {
    "date:inception_lower": "1980-01-01",
    "date:inception_upper": "1980-01-01",
    "iso:country": "GB",
    "wof:name": "SG17 5LA",
    "wof:placetype": "postalcode"
  },
  "geometry": {"coordinates":[-0.33163,52.035964],"type":"Point"}
}
