{
  "type": "Feature",
  "properties": {
    "date:inception_lower": "1983-01-01",
    "date:inception_upper": "1983-01-01",
    "iso:country": "GB",
    "wof:name": "LE16 9PT",
    "wof:placetype": "postalcode"
  },
  "geometry": {"coordinates":[-0.927805,52.469694],"type":"Point"}
}
