{
  "type": "Feature",
  "properties": {
    "iso:country":"GB",
    "wof:name":"LE16 9PT",
    "wof:placetype":"postalcode"
},
  "geometry": {"coordinates":[-0.92780505663355,52.46969388448845],"type":"Point"}
}