{
  "type": "Feature",
  "properties": {
    "iso:country": "GB",
    "wof:name": "DN11 8RY",
    "wof:placetype": "postalcode"
  },
  "geometry": {"coordinates":[-1.065429,53.410065],"type":"Point"}
}
