{
  "type": "Feature",
  "properties": {
    "iso:country": "GB",
    "wof:name": "GU6 8SS",
    "wof:placetype": "postalcode"
  },
  "geometry": {"coordinates":[-0.490522,51.141934],"type":"Point"}
}
