{
  "type": "Feature",
  "properties": {
    "date:inception_lower":"1985-10-01",
    "date:inception_upper":"1985-10-31",
    "iso:country":"GB",
    "wof:name":"GU6 8SS",
    "wof:placetype":"postalcode"
},
  "geometry": {"coordinates":[-0.490522,51.141934],"type":"Point"}
}