{
  "type": "Feature",
  "properties": {
    "iso:country":"GB",
    "wof:name":"GU6 8SS",
    "wof:placetype":"postalcode"
},
  "geometry": {"coordinates":[-0.49052164651457,51.14193377779926],"type":"Point"}
}