{
  "type": "Feature",
  "properties": {
    "iso:country":"GB",
    "wof:name":"TW2 6SN",
    "wof:placetype":"postalcode"
},
  "geometry": {"coordinates":[-0.33946348788172,51.44677715062539],"type":"Point"}
}