{
  "type": "Feature",
  "properties": {
    "date:inception_lower": "2019-09-01",
    "date:inception_upper": "2019-09-01",
    "iso:country": "GB",
    "wof:name": "W4 5QW",
    "wof:placetype": "postalcode"
  },
  "geometry": {"coordinates":[-0.273116,51.497418],"type":"Point"}
}
