{
  "type": "Feature",
  "properties": {
    "date:inception_lower":"2008-10-01",
    "date:inception_upper":"2008-10-31",
    "iso:country":"GB",
    "wof:name":"RH16 3SW",
    "wof:placetype":"postalcode"
},
  "geometry": {"coordinates":[-0.095924,51.00295],"type":"Point"}
}