{
  "type": "Feature",
  "properties": {
    "iso:country": "GB",
    "wof:name": "RH16 3SW",
    "wof:placetype": "postalcode"
  },
  "geometry": {"coordinates":[-0.095924,51.00295],"type":"Point"}
}
