{
  "type": "Feature",
  "properties": {
    "iso:country":"GB",
    "wof:name":"RH16 3SW",
    "wof:placetype":"postalcode"
},
  "geometry": {"coordinates":[-0.09592437358104,51.00295007605526],"type":"Point"}
}