{
  "type": "Feature",
  "properties": {
    "date:inception_lower": "1980-01-01",
    "date:inception_upper": "1980-01-01",
    "iso:country": "GB",
    "wof:name": "B66 2RP",
    "wof:placetype": "postalcode"
  },
  "geometry": {"coordinates":[-1.971956,52.495071],"type":"Point"}
}
