{
  "type": "Feature",
  "properties": {
    "iso:country":"GB",
    "wof:name":"IV2 4BD",
    "wof:placetype":"postalcode"
},
  "geometry": {"coordinates":[-4.22033271378648,57.45416073477164],"type":"Point"}
}