{
  "type": "Feature",
  "properties": {
    "date:inception_lower":"1992-05-01",
    "date:inception_upper":"1992-05-31",
    "iso:country":"GB",
    "wof:name":"IV2 4BD",
    "wof:placetype":"postalcode"
},
  "geometry": {"coordinates":[-4.220333,57.454161],"type":"Point"}
}