{
  "type": "Feature",
  "properties": {
    "iso:country":"GB",
    "wof:name":"DY5 3NH",
    "wof:placetype":"postalcode"
},
  "geometry": {"coordinates":[-2.14168499474745,52.47831284535695],"type":"Point"}
}