{
  "type": "Feature",
  "properties": {
    "date:inception_lower":"1980-01-01",
    "date:inception_upper":"1980-01-31",
    "iso:country":"GB",
    "wof:name":"BD19 4QX",
    "wof:placetype":"postalcode"
},
  "geometry": {"coordinates":[-1.679842,53.727857],"type":"Point"}
}