{
  "type": "Feature",
  "properties": {
    "date:inception_lower": "2002-12-01",
    "date:inception_upper": "2002-12-01",
    "iso:country": "GB",
    "wof:name": "L20 5GA",
    "wof:placetype": "postalcode"
  },
  "geometry": {"coordinates":[-2.989117,53.458638],"type":"Point"}
}
