{
  "type": "Feature",
  "properties": {
    "date:inception_lower": "2019-07-01",
    "date:inception_upper": "2019-07-01",
    "iso:country": "GB",
    "wof:name": "M32 0EY",
    "wof:placetype": "postalcode"
  },
  "geometry": {"coordinates":[-2.300294,53.449583],"type":"Point"}
}
