{
  "type": "Feature",
  "properties": {
    "iso:country":"GB",
    "wof:name":"B12 0JB",
    "wof:placetype":"postalcode"
},
  "geometry": {"coordinates":[-1.87921463181784,52.47066816768471],"type":"Point"}
}