{
  "type": "Feature",
  "properties": {
    "iso:country": "GB",
    "wof:name": "B12 0JB",
    "wof:placetype": "postalcode"
  },
  "geometry": {"coordinates":[-1.879215,52.470668],"type":"Point"}
}
