{
  "type": "Feature",
  "properties": {
    "date:inception_lower": "2018-07-01",
    "date:inception_upper": "2018-07-01",
    "iso:country": "GB",
    "wof:name": "PL22 0GD",
    "wof:placetype": "postalcode"
  },
  "geometry": {"coordinates":[-4.672579,50.403424],"type":"Point"}
}
