{
  "type": "Feature",
  "properties": {
    "date:inception_lower": "2002-06-01",
    "date:inception_upper": "2002-06-01",
    "iso:country": "GB",
    "wof:name": "SN11 9FD",
    "wof:placetype": "postalcode"
  },
  "geometry": {"coordinates":[-2.01188,51.447203],"type":"Point"}
}
