{
  "type": "Feature",
  "properties": {
    "iso:country":"GB",
    "wof:name":"CA1 1LH",
    "wof:placetype":"postalcode"
},
  "geometry": {"coordinates":[-2.91524989830456,54.89421975002155],"type":"Point"}
}