{
  "type": "Feature",
  "properties": {
    "iso:country":"GB",
    "wof:name":"SS9 1NG",
    "wof:placetype":"postalcode"
},
  "geometry": {"coordinates":[0.66398894475505,51.54516313944001],"type":"Point"}
}