{
  "type": "Feature",
  "properties": {
    "date:inception_lower":"2011-12-01",
    "date:inception_upper":"2011-12-31",
    "iso:country":"GB",
    "wof:name":"CF31 4AT",
    "wof:placetype":"postalcode"
},
  "geometry": {"coordinates":[-3.600831,51.517866],"type":"Point"}
}