{
  "type": "Feature",
  "properties": {
    "iso:country":"GB",
    "wof:name":"CF31 4AT",
    "wof:placetype":"postalcode"
},
  "geometry": {"coordinates":[-3.60083114388884,51.51786600265208],"type":"Point"}
}