{
  "type": "Feature",
  "properties": {
    "iso:country":"GB",
    "wof:name":"LA10 5AS",
    "wof:placetype":"postalcode"
},
  "geometry": {"coordinates":[-2.52538820235943,54.325273102295],"type":"Point"}
}