{
  "type": "Feature",
  "properties": {
    "iso:country": "GB",
    "wof:name": "LA10 5AS",
    "wof:placetype": "postalcode"
  },
  "geometry": {"coordinates":[-2.525388,54.325273],"type":"Point"}
}
