{
  "type": "Feature",
  "properties": {
    "iso:country": "GB",
    "wof:name": "NN11 4QL",
    "wof:placetype": "postalcode"
  },
  "geometry": {"coordinates":[-1.182009,52.25422],"type":"Point"}
}
