{
  "type": "Feature",
  "properties": {
    "iso:country":"GB",
    "wof:name":"IP26 5LU",
    "wof:placetype":"postalcode"
},
  "geometry": {"coordinates":[0.60742596913215,52.52701988355632],"type":"Point"}
}