{
  "type": "Feature",
  "properties": {
    "iso:country": "GB",
    "wof:name": "ML5 5SF",
    "wof:placetype": "postalcode"
  },
  "geometry": {"coordinates":[-4.06531,55.851334],"type":"Point"}
}
