{
  "type": "Feature",
  "properties": {
    "iso:country":"GB",
    "wof:name":"ML5 5SF",
    "wof:placetype":"postalcode"
},
  "geometry": {"coordinates":[-4.06531038700191,55.85133392098781],"type":"Point"}
}