{
  "type": "Feature",
  "properties": {
    "iso:country":"GB",
    "wof:name":"TS18 4HZ",
    "wof:placetype":"postalcode"
},
  "geometry": {"coordinates":[-1.34102541578811,54.56336438534572],"type":"Point"}
}