{
  "type": "Feature",
  "properties": {
    "iso:country": "GB",
    "wof:name": "GL50 4DE",
    "wof:placetype": "postalcode"
  },
  "geometry": {"coordinates":[-2.077331,51.904316],"type":"Point"}
}
