{
  "type": "Feature",
  "properties": {
    "iso:country":"GB",
    "wof:name":"GL50 4DE",
    "wof:placetype":"postalcode"
},
  "geometry": {"coordinates":[-2.07735250331861,51.90405664025108],"type":"Point"}
}