{
  "type": "Feature",
  "properties": {
    "date:inception_lower": "2019-07-01",
    "date:inception_upper": "2019-07-01",
    "iso:country": "GB",
    "wof:name": "S42 6GD",
    "wof:placetype": "postalcode"
  },
  "geometry": {"coordinates":[-1.416516,53.206444],"type":"Point"}
}
