{
  "type": "Feature",
  "properties": {
    "date:inception_lower": "1980-01-01",
    "date:inception_upper": "1980-01-01",
    "iso:country": "GB",
    "wof:name": "BD20 8EU",
    "wof:placetype": "postalcode"
  },
  "geometry": {"coordinates":[-2.069755,53.908309],"type":"Point"}
}
