{
  "type": "Feature",
  "properties": {
    "iso:country":"GB",
    "wof:name":"BD20 8EU",
    "wof:placetype":"postalcode"
},
  "geometry": {"coordinates":[-2.06975538035677,53.90830931514679],"type":"Point"}
}