{
  "type": "Feature",
  "properties": {
    "iso:country":"GB",
    "wof:name":"LN2 3PN",
    "wof:placetype":"postalcode"
},
  "geometry": {"coordinates":[-0.50527794253866,53.32997155875047],"type":"Point"}
}