{
  "type": "Feature",
  "properties": {
    "iso:country": "GB",
    "wof:name": "LN2 3PN",
    "wof:placetype": "postalcode"
  },
  "geometry": {"coordinates":[-0.505278,53.329972],"type":"Point"}
}
