{
  "type": "Feature",
  "properties": {
    "iso:country": "GB",
    "wof:name": "WR3 7SP",
    "wof:placetype": "postalcode"
  },
  "geometry": {"coordinates":[-2.215814,52.221594],"type":"Point"}
}
