{
  "type": "Feature",
  "properties": {
    "iso:country":"GB",
    "wof:name":"SK17 7TL",
    "wof:placetype":"postalcode"
},
  "geometry": {"coordinates":[-1.90227571335448,53.25593841088599],"type":"Point"}
}