{
  "type": "Feature",
  "properties": {
    "iso:country":"GB",
    "wof:name":"N11 3EX",
    "wof:placetype":"postalcode"
},
  "geometry": {"coordinates":[-0.15026331401289,51.61544891128568],"type":"Point"}
}