{
  "type": "Feature",
  "properties": {
    "iso:country": "GB",
    "wof:name": "B38 8LF",
    "wof:placetype": "postalcode"
  },
  "geometry": {"coordinates":[-1.951692,52.397748],"type":"Point"}
}
