{
  "type": "Feature",
  "properties": {
    "date:inception_lower": "2011-12-01",
    "date:inception_upper": "2011-12-01",
    "iso:country": "GB",
    "wof:name": "B38 8LF",
    "wof:placetype": "postalcode"
  },
  "geometry": {"coordinates":[-1.951692,52.397748],"type":"Point"}
}
