{
  "type": "Feature",
  "properties": {
    "iso:country":"GB",
    "wof:name":"NG9 6AP",
    "wof:placetype":"postalcode"
},
  "geometry": {"coordinates":[-1.22886770452324,52.90650945092387],"type":"Point"}
}