{
  "type": "Feature",
  "properties": {
    "date:inception_lower":"1980-01-01",
    "date:inception_upper":"1980-01-31",
    "iso:country":"GB",
    "wof:name":"NG9 6AP",
    "wof:placetype":"postalcode"
},
  "geometry": {"coordinates":[-1.228868,52.906509],"type":"Point"}
}