{
  "type": "Feature",
  "properties": {
    "date:inception_lower": "1980-01-01",
    "date:inception_upper": "1980-01-01",
    "iso:country": "GB",
    "wof:name": "UB7 8NF",
    "wof:placetype": "postalcode"
  },
  "geometry": {"coordinates":[-0.450292,51.507778],"type":"Point"}
}
