{
  "type": "Feature",
  "properties": {
    "iso:country":"GB",
    "wof:name":"UB7 8NF",
    "wof:placetype":"postalcode"
},
  "geometry": {"coordinates":[-0.45029226381016,51.50777812587715],"type":"Point"}
}