{
  "type": "Feature",
  "properties": {
    "iso:country":"GB",
    "wof:name":"SE17 1DL",
    "wof:placetype":"postalcode"
},
  "geometry": {"coordinates":[-0.09374107122164,51.48884736407426],"type":"Point"}
}