{
  "type": "Feature",
  "properties": {
    "date:inception_lower": "1980-01-01",
    "date:inception_upper": "1980-01-01",
    "iso:country": "GB",
    "wof:name": "RM14 3AP",
    "wof:placetype": "postalcode"
  },
  "geometry": {"coordinates":[0.24842,51.54983],"type":"Point"}
}
