{
  "type": "Feature",
  "properties": {
    "iso:country":"GB",
    "wof:name":"RM14 3AP",
    "wof:placetype":"postalcode"
},
  "geometry": {"coordinates":[0.24828049118266,51.55019938824807],"type":"Point"}
}