{
  "type": "Feature",
  "properties": {
    "iso:country": "GB",
    "wof:name": "HR6 8PJ",
    "wof:placetype": "postalcode"
  },
  "geometry": {"coordinates":[-2.744172,52.221971],"type":"Point"}
}
