{
  "type": "Feature",
  "properties": {
    "iso:country": "GB",
    "wof:name": "TS10 4GW",
    "wof:placetype": "postalcode"
  },
  "geometry": {"coordinates":[-1.076693,54.601719],"type":"Point"}
}
