{
  "type": "Feature",
  "properties": {
    "iso:country":"GB",
    "wof:name":"TS10 4GW",
    "wof:placetype":"postalcode"
},
  "geometry": {"coordinates":[-1.07669322255452,54.60171945038444],"type":"Point"}
}