{
  "type": "Feature",
  "properties": {
    "date:inception_lower": "2009-02-01",
    "date:inception_upper": "2009-02-01",
    "iso:country": "GB",
    "wof:name": "TS10 4GW",
    "wof:placetype": "postalcode"
  },
  "geometry": {"coordinates":[-1.076693,54.601719],"type":"Point"}
}
