{
  "type": "Feature",
  "properties": {
    "iso:country":"GB",
    "wof:name":"BA1 6JR",
    "wof:placetype":"postalcode"
},
  "geometry": {"coordinates":[-2.35964957364356,51.3981055698322],"type":"Point"}
}