{
  "type": "Feature",
  "properties": {
    "iso:country": "GB",
    "wof:name": "BA1 6JR",
    "wof:placetype": "postalcode"
  },
  "geometry": {"coordinates":[-2.359576,51.398112],"type":"Point"}
}
