{
  "type": "Feature",
  "properties": {
    "iso:country": "GB",
    "wof:name": "PL11 3DF",
    "wof:placetype": "postalcode"
  },
  "geometry": {"coordinates":[-4.2987,50.367616],"type":"Point"}
}
