{
  "type": "Feature",
  "properties": {
    "date:inception_lower":"1985-10-01",
    "date:inception_upper":"1985-10-31",
    "iso:country":"GB",
    "wof:name":"PL11 3DF",
    "wof:placetype":"postalcode"
},
  "geometry": {"coordinates":[-4.2987,50.367616],"type":"Point"}
}