{
  "type": "Feature",
  "properties": {
    "iso:country":"GB",
    "wof:name":"PL11 3DF",
    "wof:placetype":"postalcode"
},
  "geometry": {"coordinates":[-4.29870051435534,50.36761634955779],"type":"Point"}
}