{
  "type": "Feature",
  "properties": {
    "iso:country":"GB",
    "wof:name":"WD6 4BX",
    "wof:placetype":"postalcode"
},
  "geometry": {"coordinates":[-0.28930822580488,51.66947820543441],"type":"Point"}
}