{
  "type": "Feature",
  "properties": {
    "iso:country": "GB",
    "wof:name": "WD6 4BX",
    "wof:placetype": "postalcode"
  },
  "geometry": {"coordinates":[-0.289308,51.669478],"type":"Point"}
}
