{
  "type": "Feature",
  "properties": {
    "date:inception_lower":"1987-04-01",
    "date:inception_upper":"1987-04-30",
    "iso:country":"GB",
    "wof:name":"NG34 8TZ",
    "wof:placetype":"postalcode"
},
  "geometry": {"coordinates":[-0.409085,53.010351],"type":"Point"}
}