{
  "type": "Feature",
  "properties": {
    "iso:country":"GB",
    "wof:name":"NG34 8TZ",
    "wof:placetype":"postalcode"
},
  "geometry": {"coordinates":[-0.40908480145823,53.01035118903456],"type":"Point"}
}