{
  "type": "Feature",
  "properties": {
    "iso:country": "GB",
    "wof:name": "NG34 8TZ",
    "wof:placetype": "postalcode"
  },
  "geometry": {"coordinates":[-0.409085,53.010351],"type":"Point"}
}
