{
  "type": "Feature",
  "properties": {
    "iso:country":"GB",
    "wof:name":"SL8 5LP",
    "wof:placetype":"postalcode"
},
  "geometry": {"coordinates":[-0.71038698155204,51.58221364455467],"type":"Point"}
}