{
  "type": "Feature",
  "properties": {
    "iso:country": "GB",
    "wof:name": "SL8 5LP",
    "wof:placetype": "postalcode"
  },
  "geometry": {"coordinates":[-0.710387,51.582214],"type":"Point"}
}
