{
  "type": "Feature",
  "properties": {
    "iso:country":"GB",
    "wof:name":"S64 0QD",
    "wof:placetype":"postalcode"
},
  "geometry": {"coordinates":[-1.27386633821445,53.500673001422],"type":"Point"}
}