{
  "type": "Feature",
  "properties": {
    "iso:country":"GB",
    "wof:name":"E3 3JD",
    "wof:placetype":"postalcode"
},
  "geometry": {"coordinates":[-0.01970757582693,51.52726907962921],"type":"Point"}
}