{
  "type": "Feature",
  "properties": {
    "iso:country":"GB",
    "wof:name":"CH5 3HB",
    "wof:placetype":"postalcode"
},
  "geometry": {"coordinates":[-3.02779800138433,53.1877491715741],"type":"Point"}
}