{
  "type": "Feature",
  "properties": {
    "date:inception_lower":"1987-04-01",
    "date:inception_upper":"1987-04-30",
    "iso:country":"GB",
    "wof:name":"CH5 3HB",
    "wof:placetype":"postalcode"
},
  "geometry": {"coordinates":[-3.027798,53.187749],"type":"Point"}
}