{
  "type": "Feature",
  "properties": {
    "iso:country": "GB",
    "wof:name": "HA4 0QH",
    "wof:placetype": "postalcode"
  },
  "geometry": {"coordinates":[-0.380174,51.556935],"type":"Point"}
}
