{
  "type": "Feature",
  "properties": {
    "iso:country":"GB",
    "wof:name":"HA4 0QH",
    "wof:placetype":"postalcode"
},
  "geometry": {"coordinates":[-0.38017371532725,51.55693544199903],"type":"Point"}
}