{
  "type": "Feature",
  "properties": {
    "date:inception_lower":"1980-01-01",
    "date:inception_upper":"1980-01-31",
    "iso:country":"GB",
    "wof:name":"ST7 1PT",
    "wof:placetype":"postalcode"
},
  "geometry": {"coordinates":[-2.260972,53.07443],"type":"Point"}
}