{
  "type": "Feature",
  "properties": {
    "iso:country":"GB",
    "wof:name":"ST7 1PT",
    "wof:placetype":"postalcode"
},
  "geometry": {"coordinates":[-2.26097161483386,53.07443009819742],"type":"Point"}
}