{
  "type": "Feature",
  "properties": {
    "iso:country":"GB",
    "wof:name":"CF72 9DX",
    "wof:placetype":"postalcode"
},
  "geometry": {"coordinates":[-3.39829434511702,51.52846777017977],"type":"Point"}
}