{
  "type": "Feature",
  "properties": {
    "date:inception_lower": "2018-01-01",
    "date:inception_upper": "2018-01-01",
    "iso:country": "GB",
    "wof:name": "EH24 9EX",
    "wof:placetype": "postalcode"
  },
  "geometry": {"coordinates":[-3.140851,55.852494],"type":"Point"}
}
