{
  "type": "Feature",
  "properties": {
    "iso:country":"GB",
    "wof:name":"PE33 9HX",
    "wof:placetype":"postalcode"
},
  "geometry": {"coordinates":[0.51169320663515,52.65886426483941],"type":"Point"}
}