{
  "type": "Feature",
  "properties": {
    "date:inception_lower":"1985-10-01",
    "date:inception_upper":"1985-10-31",
    "iso:country":"GB",
    "wof:name":"RG23 7EN",
    "wof:placetype":"postalcode"
},
  "geometry": {"coordinates":[-1.180612,51.250333],"type":"Point"}
}