{
  "type": "Feature",
  "properties": {
    "iso:country": "GB",
    "wof:name": "RG23 7EN",
    "wof:placetype": "postalcode"
  },
  "geometry": {"coordinates":[-1.180612,51.250333],"type":"Point"}
}
