{
  "type": "Feature",
  "properties": {
    "date:inception_lower": "2001-12-01",
    "date:inception_upper": "2001-12-01",
    "iso:country": "GB",
    "wof:name": "NN4 6RS",
    "wof:placetype": "postalcode"
  },
  "geometry": {"coordinates":[-0.888078,52.20726],"type":"Point"}
}
