{
  "type": "Feature",
  "properties": {
    "iso:country":"GB",
    "wof:name":"AL5 2HU",
    "wof:placetype":"postalcode"
},
  "geometry": {"coordinates":[-0.3562139314934,51.81373835196035],"type":"Point"}
}