{
  "type": "Feature",
  "properties": {
    "iso:country":"GB",
    "wof:name":"CR0 8BZ",
    "wof:placetype":"postalcode"
},
  "geometry": {"coordinates":[-0.03194769934016,51.37632548243988],"type":"Point"}
}