{
  "type": "Feature",
  "properties": {
    "iso:country":"GB",
    "wof:name":"PR4 2WS",
    "wof:placetype":"postalcode"
},
  "geometry": {"coordinates":[-2.91440937063788,53.77592770672088],"type":"Point"}
}