{
  "type": "Feature",
  "properties": {
    "iso:country":"GB",
    "wof:name":"FY4 5HP",
    "wof:placetype":"postalcode"
},
  "geometry": {"coordinates":[-3.01191782547123,53.78779982843442],"type":"Point"}
}