{
  "type": "Feature",
  "properties": {
    "date:inception_lower":"1980-01-01",
    "date:inception_upper":"1980-01-31",
    "iso:country":"GB",
    "wof:name":"TA12 6AN",
    "wof:placetype":"postalcode"
},
  "geometry": {"coordinates":[-2.765766,50.986411],"type":"Point"}
}