{
  "type": "Feature",
  "properties": {
    "date:inception_lower": "1981-06-01",
    "date:inception_upper": "1981-06-01",
    "iso:country": "GB",
    "wof:name": "MK14 5ET",
    "wof:placetype": "postalcode"
  },
  "geometry": {"coordinates":[-0.752429,52.069735],"type":"Point"}
}
