{
  "type": "Feature",
  "properties": {
    "iso:country":"GB",
    "wof:name":"TS24 8LE",
    "wof:placetype":"postalcode"
},
  "geometry": {"coordinates":[-1.21930638559981,54.69406620611313],"type":"Point"}
}