{
  "type": "Feature",
  "properties": {
    "iso:country":"GB",
    "wof:name":"WA2 0PQ",
    "wof:placetype":"postalcode"
},
  "geometry": {"coordinates":[-2.54384179355478,53.41147399934537],"type":"Point"}
}