{
  "type": "Feature",
  "properties": {
    "iso:country":"GB",
    "wof:name":"NR29 4LF",
    "wof:placetype":"postalcode"
},
  "geometry": {"coordinates":[1.68130941181751,52.6931692701536],"type":"Point"}
}