{
  "type": "Feature",
  "properties": {
    "iso:country":"GB",
    "wof:name":"SS4 2HA",
    "wof:placetype":"postalcode"
},
  "geometry": {"coordinates":[0.79149481937535,51.62186392669754],"type":"Point"}
}