{
  "type": "Feature",
  "properties": {
    "iso:country":"GB",
    "wof:name":"DE24 9FF",
    "wof:placetype":"postalcode"
},
  "geometry": {"coordinates":[-1.44445625076292,52.88252430377175],"type":"Point"}
}