{
  "type": "Feature",
  "properties": {
    "date:inception_lower": "1992-08-01",
    "date:inception_upper": "1992-08-01",
    "iso:country": "GB",
    "wof:name": "DE24 9FF",
    "wof:placetype": "postalcode"
  },
  "geometry": {"coordinates":[-1.444481,52.882534],"type":"Point"}
}
