{
  "type": "Feature",
  "properties": {
    "iso:country": "GB",
    "wof:name": "GU34 5NQ",
    "wof:placetype": "postalcode"
  },
  "geometry": {"coordinates":[-1.081426,51.130996],"type":"Point"}
}
