{
  "type": "Feature",
  "properties": {
    "iso:country":"GB",
    "wof:name":"SG2 7PL",
    "wof:placetype":"postalcode"
},
  "geometry": {"coordinates":[-0.12595444518292,51.91950236614108],"type":"Point"}
}