{
  "type": "Feature",
  "properties": {
    "iso:country":"GB",
    "wof:name":"NG9 6AT",
    "wof:placetype":"postalcode"
},
  "geometry": {"coordinates":[-1.2319104880616,52.90512678959939],"type":"Point"}
}