{
  "type": "Feature",
  "properties": {
    "iso:country": "GB",
    "wof:name": "GL15 6NE",
    "wof:placetype": "postalcode"
  },
  "geometry": {"coordinates":[-2.570141,51.750499],"type":"Point"}
}
