{
  "type": "Feature",
  "properties": {
    "date:inception_lower": "2020-01-01",
    "date:inception_upper": "2020-01-01",
    "iso:country": "GB",
    "wof:name": "LN11 7BZ",
    "wof:placetype": "postalcode"
  },
  "geometry": {"coordinates":[0.017961,53.370337],"type":"Point"}
}
