{
  "type": "Feature",
  "properties": {
    "iso:country":"GB",
    "wof:name":"WA6 8JX",
    "wof:placetype":"postalcode"
},
  "geometry": {"coordinates":[-2.64540580650032,53.24750625681364],"type":"Point"}
}