{
  "type": "Feature",
  "properties": {
    "iso:country": "GB",
    "wof:name": "OX10 6JJ",
    "wof:placetype": "postalcode"
  },
  "geometry": {"coordinates":[-1.104906,51.638462],"type":"Point"}
}
