{
  "type": "Feature",
  "properties": {
    "date:inception_lower":"2015-08-01",
    "date:inception_upper":"2015-08-31",
    "iso:country":"GB",
    "wof:name":"ME12 4EA",
    "wof:placetype":"postalcode"
},
  "geometry": {"coordinates":[0.921183,51.399274],"type":"Point"}
}