{
  "type": "Feature",
  "properties": {
    "iso:country":"GB",
    "wof:name":"ME12 4EA",
    "wof:placetype":"postalcode"
},
  "geometry": {"coordinates":[0.92135489289442,51.39928292404297],"type":"Point"}
}