{
  "type": "Feature",
  "properties": {
    "iso:country":"GB",
    "wof:name":"NE4 9UP",
    "wof:placetype":"postalcode"
},
  "geometry": {"coordinates":[-1.65223733829758,54.98651358252405],"type":"Point"}
}