{
  "type": "Feature",
  "properties": {
    "iso:country": "GB",
    "wof:name": "L34 2QE",
    "wof:placetype": "postalcode"
  },
  "geometry": {"coordinates":[-2.791359,53.433964],"type":"Point"}
}
