{
  "type": "Feature",
  "properties": {
    "iso:country":"GB",
    "wof:name":"L34 2QE",
    "wof:placetype":"postalcode"
},
  "geometry": {"coordinates":[-2.79135874169403,53.43396395759649],"type":"Point"}
}