{
  "type": "Feature",
  "properties": {
    "iso:country":"GB",
    "wof:name":"RH16 2QN",
    "wof:placetype":"postalcode"
},
  "geometry": {"coordinates":[-0.05413713620616,51.01410564886874],"type":"Point"}
}