{
  "type": "Feature",
  "properties": {
    "iso:country": "GB",
    "wof:name": "RH16 2QN",
    "wof:placetype": "postalcode"
  },
  "geometry": {"coordinates":[-0.054137,51.014106],"type":"Point"}
}
