{
  "type": "Feature",
  "properties": {
    "iso:country":"GB",
    "wof:name":"CF45 3LT",
    "wof:placetype":"postalcode"
},
  "geometry": {"coordinates":[-3.38199813111254,51.67899649228292],"type":"Point"}
}