{
  "type": "Feature",
  "properties": {
    "iso:country": "GB",
    "wof:name": "CF45 3LT",
    "wof:placetype": "postalcode"
  },
  "geometry": {"coordinates":[-3.381998,51.678996],"type":"Point"}
}
