{
  "type": "Feature",
  "properties": {
    "date:inception_lower": "1999-12-01",
    "date:inception_upper": "1999-12-01",
    "iso:country": "GB",
    "wof:name": "CV47 9PG",
    "wof:placetype": "postalcode"
  },
  "geometry": {"coordinates":[-1.396433,52.283435],"type":"Point"}
}
