{
  "type": "Feature",
  "properties": {
    "iso:country":"GB",
    "wof:name":"CV47 9PG",
    "wof:placetype":"postalcode"
},
  "geometry": {"coordinates":[-1.39643262902052,52.28343484482261],"type":"Point"}
}