{
  "type": "Feature",
  "properties": {
    "iso:country": "GB",
    "wof:name": "LS14 3DG",
    "wof:placetype": "postalcode"
  },
  "geometry": {"coordinates":[-1.434773,53.849918],"type":"Point"}
}
