{
  "type": "Feature",
  "properties": {
    "iso:country":"GB",
    "wof:name":"LS14 3DG",
    "wof:placetype":"postalcode"
},
  "geometry": {"coordinates":[-1.43477327675733,53.84991811327381],"type":"Point"}
}