{
  "type": "Feature",
  "properties": {
    "date:inception_lower": "1992-08-01",
    "date:inception_upper": "1992-08-01",
    "iso:country": "GB",
    "wof:name": "DE56 2AJ",
    "wof:placetype": "postalcode"
  },
  "geometry": {"coordinates":[-1.448291,53.050751],"type":"Point"}
}
