{
  "type": "Feature",
  "properties": {
    "iso:country":"GB",
    "wof:name":"ML2 8RS",
    "wof:placetype":"postalcode"
},
  "geometry": {"coordinates":[-3.90946305294709,55.7886977071616],"type":"Point"}
}