{
  "type": "Feature",
  "properties": {
    "iso:country":"GB",
    "wof:name":"BS15 1LT",
    "wof:placetype":"postalcode"
},
  "geometry": {"coordinates":[-2.52084016269717,51.47000837354651],"type":"Point"}
}