{
  "type": "Feature",
  "properties": {
    "date:inception_lower":"2015-05-01",
    "date:inception_upper":"2015-05-31",
    "iso:country":"GB",
    "wof:name":"BH21 8AB",
    "wof:placetype":"postalcode"
},
  "geometry": {"coordinates":[-1.918604,50.878504],"type":"Point"}
}