{
  "type": "Feature",
  "properties": {
    "date:inception_lower": "1980-01-01",
    "date:inception_upper": "1980-01-01",
    "iso:country": "GB",
    "wof:name": "TR1 1BT",
    "wof:placetype": "postalcode"
  },
  "geometry": {"coordinates":[-5.049441,50.269704],"type":"Point"}
}
