{
  "type": "Feature",
  "properties": {
    "iso:country":"GB",
    "wof:name":"CO3 9XS",
    "wof:placetype":"postalcode"
},
  "geometry": {"coordinates":[0.85073662357963,51.87514040586565],"type":"Point"}
}