{
  "type": "Feature",
  "properties": {
    "iso:country":"GB",
    "wof:name":"KY13 0QW",
    "wof:placetype":"postalcode"
},
  "geometry": {"coordinates":[-3.48061620809263,56.18938529981796],"type":"Point"}
}