{
  "type": "Feature",
  "properties": {
    "date:inception_lower": "1998-12-01",
    "date:inception_upper": "1998-12-01",
    "iso:country": "GB",
    "wof:name": "KY13 0QW",
    "wof:placetype": "postalcode"
  },
  "geometry": {"coordinates":[-3.480616,56.189385],"type":"Point"}
}
