{
  "type": "Feature",
  "properties": {
    "iso:country":"GB",
    "wof:name":"AL9 5BD",
    "wof:placetype":"postalcode"
},
  "geometry": {"coordinates":[-0.21256366455716,51.76451524207366],"type":"Point"}
}