{
  "type": "Feature",
  "properties": {
    "iso:country": "GB",
    "wof:name": "S60 5SE",
    "wof:placetype": "postalcode"
  },
  "geometry": {"coordinates":[-1.367408,53.395417],"type":"Point"}
}
