{
  "type": "Feature",
  "properties": {
    "date:inception_lower": "1981-06-01",
    "date:inception_upper": "1981-06-01",
    "iso:country": "GB",
    "wof:name": "DL1 1RJ",
    "wof:placetype": "postalcode"
  },
  "geometry": {"coordinates":[-1.54794,54.530397],"type":"Point"}
}
