{
  "type": "Feature",
  "properties": {
    "date:inception_lower": "1986-07-01",
    "date:inception_upper": "1986-07-01",
    "iso:country": "GB",
    "wof:name": "PE12 6ND",
    "wof:placetype": "postalcode"
  },
  "geometry": {"coordinates":[-0.115386,52.783139],"type":"Point"}
}
