{
  "type": "Feature",
  "properties": {
    "iso:country":"GB",
    "wof:name":"CO12 4DR",
    "wof:placetype":"postalcode"
},
  "geometry": {"coordinates":[1.2677116695497,51.932646834385],"type":"Point"}
}