{
  "type": "Feature",
  "properties": {
    "iso:country":"GB",
    "wof:name":"TN30 6TB",
    "wof:placetype":"postalcode"
},
  "geometry": {"coordinates":[0.67676165908188,51.09675207100447],"type":"Point"}
}