{
  "type": "Feature",
  "properties": {
    "iso:country":"GB",
    "wof:name":"AL8 7EP",
    "wof:placetype":"postalcode"
},
  "geometry": {"coordinates":[-0.21156215542205,51.81770590773234],"type":"Point"}
}