{
  "type": "Feature",
  "properties": {
    "iso:country":"GB",
    "wof:name":"NG8 3LQ",
    "wof:placetype":"postalcode"
},
  "geometry": {"coordinates":[-1.19650798433237,52.96064562414513],"type":"Point"}
}