{
  "type": "Feature",
  "properties": {
    "iso:country": "GB",
    "wof:name": "NG8 3LQ",
    "wof:placetype": "postalcode"
  },
  "geometry": {"coordinates":[-1.196508,52.960646],"type":"Point"}
}
