{
  "type": "Feature",
  "properties": {
    "iso:country":"GB",
    "wof:name":"HX3 9EF",
    "wof:placetype":"postalcode"
},
  "geometry": {"coordinates":[-1.85035091117106,53.69844892294842],"type":"Point"}
}