{
  "type": "Feature",
  "properties": {
    "iso:country":"GB",
    "wof:name":"N12 8PH",
    "wof:placetype":"postalcode"
},
  "geometry": {"coordinates":[-0.18364674302,51.60923495003879],"type":"Point"}
}