{
  "type": "Feature",
  "properties": {
    "date:inception_lower":"1980-01-01",
    "date:inception_upper":"1980-01-31",
    "iso:country":"GB",
    "wof:name":"RG26 5PT",
    "wof:placetype":"postalcode"
},
  "geometry": {"coordinates":[-1.144938,51.313481],"type":"Point"}
}