{
  "type": "Feature",
  "properties": {
    "iso:country":"GB",
    "wof:name":"RG26 5PT",
    "wof:placetype":"postalcode"
},
  "geometry": {"coordinates":[-1.14493756769904,51.31348077182503],"type":"Point"}
}