{
  "type": "Feature",
  "properties": {
    "date:inception_lower": "1996-06-01",
    "date:inception_upper": "1996-06-01",
    "iso:country": "GB",
    "wof:name": "AB42 2XA",
    "wof:placetype": "postalcode"
  },
  "geometry": {"coordinates":[-1.794277,57.502565],"type":"Point"}
}
