{
  "type": "Feature",
  "properties": {
    "iso:country":"GB",
    "wof:name":"BD19 6JW",
    "wof:placetype":"postalcode"
},
  "geometry": {"coordinates":[-1.73338812068318,53.72093198895576],"type":"Point"}
}