{
  "type": "Feature",
  "properties": {
    "date:inception_lower": "2005-09-01",
    "date:inception_upper": "2005-09-01",
    "iso:country": "GB",
    "wof:name": "WF9 4SZ",
    "wof:placetype": "postalcode"
  },
  "geometry": {"coordinates":[-1.354745,53.608028],"type":"Point"}
}
