{
  "type": "Feature",
  "properties": {
    "iso:country":"GB",
    "wof:name":"WF9 4SZ",
    "wof:placetype":"postalcode"
},
  "geometry": {"coordinates":[-1.3547449013229,53.6080278790005],"type":"Point"}
}