{
  "type": "Feature",
  "properties": {
    "date:inception_lower":"2009-11-01",
    "date:inception_upper":"2009-11-30",
    "iso:country":"GB",
    "wof:name":"LL24 0PN",
    "wof:placetype":"postalcode"
},
  "geometry": {"coordinates":[-3.776456,53.065533],"type":"Point"}
}