{
  "type": "Feature",
  "properties": {
    "iso:country":"GB",
    "wof:name":"GU21 3AS",
    "wof:placetype":"postalcode"
},
  "geometry": {"coordinates":[-0.58365349986384,51.32071784667342],"type":"Point"}
}