{
  "type": "Feature",
  "properties": {
    "iso:country":"GB",
    "wof:name":"RG22 6JJ",
    "wof:placetype":"postalcode"
},
  "geometry": {"coordinates":[-1.117968475863,51.25030963038429],"type":"Point"}
}