{
  "type": "Feature",
  "properties": {
    "iso:country":"GB",
    "wof:name":"DH7 6AN",
    "wof:placetype":"postalcode"
},
  "geometry": {"coordinates":[-1.63612205457241,54.82425376558049],"type":"Point"}
}