{
  "type": "Feature",
  "properties": {
    "iso:country": "GB",
    "wof:name": "G73 3QE",
    "wof:placetype": "postalcode"
  },
  "geometry": {"coordinates":[-4.204374,55.818435],"type":"Point"}
}
