{
  "type": "Feature",
  "properties": {
    "iso:country":"GB",
    "wof:name":"HA4 6EN",
    "wof:placetype":"postalcode"
},
  "geometry": {"coordinates":[-0.42114976438072,51.56753814243345],"type":"Point"}
}