{
  "type": "Feature",
  "properties": {
    "iso:country":"GB",
    "wof:name":"GU9 9NN",
    "wof:placetype":"postalcode"
},
  "geometry": {"coordinates":[-0.77361146175513,51.22281283390299],"type":"Point"}
}