{
  "type": "Feature",
  "properties": {
    "iso:country":"GB",
    "wof:name":"HX4 0AN",
    "wof:placetype":"postalcode"
},
  "geometry": {"coordinates":[-1.91977945532304,53.67471482149727],"type":"Point"}
}