{
  "type": "Feature",
  "properties": {
    "iso:country":"GB",
    "wof:name":"SG19 2QZ",
    "wof:placetype":"postalcode"
},
  "geometry": {"coordinates":[-0.21170121200081,52.13049627322643],"type":"Point"}
}