{
  "type": "Feature",
  "properties": {
    "date:inception_lower":"1980-01-01",
    "date:inception_upper":"1980-01-31",
    "iso:country":"GB",
    "wof:name":"TD8 6LD",
    "wof:placetype":"postalcode"
},
  "geometry": {"coordinates":[-2.549095,55.47412],"type":"Point"}
}