{
  "type": "Feature",
  "properties": {
    "iso:country": "GB",
    "wof:name": "TD8 6LD",
    "wof:placetype": "postalcode"
  },
  "geometry": {"coordinates":[-2.549095,55.47412],"type":"Point"}
}
