{
  "type": "Feature",
  "properties": {
    "iso:country": "GB",
    "wof:name": "PE9 4EG",
    "wof:placetype": "postalcode"
  },
  "geometry": {"coordinates":[-0.50343,52.719125],"type":"Point"}
}
