{
  "type": "Feature",
  "properties": {
    "date:inception_lower": "1980-01-01",
    "date:inception_upper": "1980-01-01",
    "iso:country": "GB",
    "wof:name": "PE9 4EG",
    "wof:placetype": "postalcode"
  },
  "geometry": {"coordinates":[-0.50343,52.719125],"type":"Point"}
}
