{
  "type": "Feature",
  "properties": {
    "iso:country":"GB",
    "wof:name":"PE9 4EG",
    "wof:placetype":"postalcode"
},
  "geometry": {"coordinates":[-0.5034298900956,52.71912472363906],"type":"Point"}
}