{
  "type": "Feature",
  "properties": {
    "iso:country":"GB",
    "wof:name":"KT5 8SX",
    "wof:placetype":"postalcode"
},
  "geometry": {"coordinates":[-0.29322229949003,51.3885702161158],"type":"Point"}
}