{
  "type": "Feature",
  "properties": {
    "date:inception_lower": "1980-01-01",
    "date:inception_upper": "1980-01-01",
    "iso:country": "GB",
    "wof:name": "DG2 8DL",
    "wof:placetype": "postalcode"
  },
  "geometry": {"coordinates":[-3.594601,54.94197],"type":"Point"}
}
