{
  "type": "Feature",
  "properties": {
    "iso:country":"GB",
    "wof:name":"DG2 8DL",
    "wof:placetype":"postalcode"
},
  "geometry": {"coordinates":[-3.59460153632379,54.94197030924465],"type":"Point"}
}