{
  "type": "Feature",
  "properties": {
    "iso:country":"GB",
    "wof:name":"DT3 4HL",
    "wof:placetype":"postalcode"
},
  "geometry": {"coordinates":[-2.5343134731561,50.65702399296117],"type":"Point"}
}