{
  "type": "Feature",
  "properties": {
    "date:inception_lower":"1992-01-01",
    "date:inception_upper":"1992-01-31",
    "iso:country":"GB",
    "wof:name":"DT3 4HL",
    "wof:placetype":"postalcode"
},
  "geometry": {"coordinates":[-2.534298,50.657023],"type":"Point"}
}