{
  "type": "Feature",
  "properties": {
    "iso:country": "GB",
    "wof:name": "DT3 4HL",
    "wof:placetype": "postalcode"
  },
  "geometry": {"coordinates":[-2.534298,50.657023],"type":"Point"}
}
