{
  "type": "Feature",
  "properties": {
    "iso:country":"GB",
    "wof:name":"CV1 2HS",
    "wof:placetype":"postalcode"
},
  "geometry": {"coordinates":[-1.49611651161597,52.40594468831037],"type":"Point"}
}