{
  "type": "Feature",
  "properties": {
    "iso:country": "GB",
    "wof:name": "CV1 2HS",
    "wof:placetype": "postalcode"
  },
  "geometry": {"coordinates":[-1.496063,52.405997],"type":"Point"}
}
