{
  "type": "Feature",
  "properties": {
    "date:inception_lower": "1980-01-01",
    "date:inception_upper": "1980-01-01",
    "iso:country": "GB",
    "wof:name": "CV1 2HS",
    "wof:placetype": "postalcode"
  },
  "geometry": {"coordinates":[-1.496034,52.405997],"type":"Point"}
}
