{
  "type": "Feature",
  "properties": {
    "iso:country":"GB",
    "wof:name":"LA13 0LX",
    "wof:placetype":"postalcode"
},
  "geometry": {"coordinates":[-3.18142848780233,54.13510285859562],"type":"Point"}
}