{
  "type": "Feature",
  "properties": {
    "date:inception_lower": "1980-01-01",
    "date:inception_upper": "1980-01-01",
    "iso:country": "GB",
    "wof:name": "LA13 0LX",
    "wof:placetype": "postalcode"
  },
  "geometry": {"coordinates":[-3.181428,54.135103],"type":"Point"}
}
