{
  "type": "Feature",
  "properties": {
    "iso:country": "GB",
    "wof:name": "LA13 0LX",
    "wof:placetype": "postalcode"
  },
  "geometry": {"coordinates":[-3.181428,54.135103],"type":"Point"}
}
