{
  "type": "Feature",
  "properties": {
    "iso:country":"GB",
    "wof:name":"PA15 2WA",
    "wof:placetype":"postalcode"
},
  "geometry": {"coordinates":[-4.70628125914723,55.93871672463936],"type":"Point"}
}