{
  "type": "Feature",
  "properties": {
    "date:inception_lower":"2007-10-01",
    "date:inception_upper":"2007-10-31",
    "iso:country":"GB",
    "wof:name":"PA15 2WA",
    "wof:placetype":"postalcode"
},
  "geometry": {"coordinates":[-4.706545,55.938866],"type":"Point"}
}