{
  "type": "Feature",
  "properties": {
    "date:inception_lower":"2007-05-01",
    "date:inception_upper":"2007-05-31",
    "iso:country":"GB",
    "wof:name":"CV37 7PY",
    "wof:placetype":"postalcode"
},
  "geometry": {"coordinates":[-1.700131,52.188687],"type":"Point"}
}