{
  "type": "Feature",
  "properties": {
    "iso:country":"GB",
    "wof:name":"CV37 7PY",
    "wof:placetype":"postalcode"
},
  "geometry": {"coordinates":[-1.700130920189,52.18868661925333],"type":"Point"}
}