{
  "type": "Feature",
  "properties": {
    "iso:country": "GB",
    "wof:name": "CV37 7PY",
    "wof:placetype": "postalcode"
  },
  "geometry": {"coordinates":[-1.700131,52.188687],"type":"Point"}
}
