{
  "type": "Feature",
  "properties": {
    "date:inception_lower": "1980-01-01",
    "date:inception_upper": "1980-01-01",
    "iso:country": "GB",
    "wof:name": "GL3 3TZ",
    "wof:placetype": "postalcode"
  },
  "geometry": {"coordinates":[-2.169285,51.849538],"type":"Point"}
}
