{
  "type": "Feature",
  "properties": {
    "iso:country": "GB",
    "wof:name": "ST5 4BN",
    "wof:placetype": "postalcode"
  },
  "geometry": {"coordinates":[-2.219263,52.982376],"type":"Point"}
}
