{
  "type": "Feature",
  "properties": {
    "iso:country":"GB",
    "wof:name":"DE24 3LE",
    "wof:placetype":"postalcode"
},
  "geometry": {"coordinates":[-1.49869204789316,52.87643690746539],"type":"Point"}
}