{
  "type": "Feature",
  "properties": {
    "iso:country": "GB",
    "wof:name": "DE24 3LE",
    "wof:placetype": "postalcode"
  },
  "geometry": {"coordinates":[-1.498692,52.876437],"type":"Point"}
}
