{
  "type": "Feature",
  "properties": {
    "iso:country":"GB",
    "wof:name":"SW1V 4AS",
    "wof:placetype":"postalcode"
},
  "geometry": {"coordinates":[-0.14665314033821,51.4883736668661],"type":"Point"}
}