{
  "type": "Feature",
  "properties": {
    "date:inception_lower": "1999-06-01",
    "date:inception_upper": "1999-06-01",
    "iso:country": "GB",
    "wof:name": "NP23 6EZ",
    "wof:placetype": "postalcode"
  },
  "geometry": {"coordinates":[-3.208089,51.783612],"type":"Point"}
}
