{
  "type": "Feature",
  "properties": {
    "iso:country":"GB",
    "wof:name":"OX3 9TD",
    "wof:placetype":"postalcode"
},
  "geometry": {"coordinates":[-1.18229584079569,51.80610831738137],"type":"Point"}
}