{
  "type": "Feature",
  "properties": {
    "iso:country":"GB",
    "wof:name":"TR4 9RR",
    "wof:placetype":"postalcode"
},
  "geometry": {"coordinates":[-5.08063426079075,50.28588288003685],"type":"Point"}
}