{
  "type": "Feature",
  "properties": {
    "date:inception_lower":"2014-07-01",
    "date:inception_upper":"2014-07-31",
    "iso:country":"GB",
    "wof:name":"TR4 9RR",
    "wof:placetype":"postalcode"
},
  "geometry": {"coordinates":[-5.080634,50.285883],"type":"Point"}
}