{
  "type": "Feature",
  "properties": {
    "iso:country": "GB",
    "wof:name": "TS17 0ED",
    "wof:placetype": "postalcode"
  },
  "geometry": {"coordinates":[-1.297007,54.534844],"type":"Point"}
}
