{
  "type": "Feature",
  "properties": {
    "iso:country":"GB",
    "wof:name":"TS17 0ED",
    "wof:placetype":"postalcode"
},
  "geometry": {"coordinates":[-1.2970072534222,54.5348435117133],"type":"Point"}
}