{
  "type": "Feature",
  "properties": {
    "iso:country": "GB",
    "wof:name": "NG34 8GP",
    "wof:placetype": "postalcode"
  },
  "geometry": {"coordinates":[-0.452355,52.985637],"type":"Point"}
}
