{
  "type": "Feature",
  "properties": {
    "iso:country":"GB",
    "wof:name":"NG34 8GP",
    "wof:placetype":"postalcode"
},
  "geometry": {"coordinates":[-0.45250497377824,52.98616547944239],"type":"Point"}
}