{
  "type": "Feature",
  "properties": {
    "date:inception_lower": "2018-06-01",
    "date:inception_upper": "2018-06-01",
    "iso:country": "GB",
    "wof:name": "MK16 9FN",
    "wof:placetype": "postalcode"
  },
  "geometry": {"coordinates":[-0.708272,52.082505],"type":"Point"}
}
