{
  "type": "Feature",
  "properties": {
    "iso:country":"GB",
    "wof:name":"M45 8RZ",
    "wof:placetype":"postalcode"
},
  "geometry": {"coordinates":[-2.27367758817144,53.55329340303849],"type":"Point"}
}