{
  "type": "Feature",
  "properties": {
    "iso:country": "GB",
    "wof:name": "ML8 5FF",
    "wof:placetype": "postalcode"
  },
  "geometry": {"coordinates":[-3.870145,55.755581],"type":"Point"}
}
