{
  "type": "Feature",
  "properties": {
    "iso:country":"GB",
    "wof:name":"ML8 5FF",
    "wof:placetype":"postalcode"
},
  "geometry": {"coordinates":[-3.8694367800176,55.75555875018387],"type":"Point"}
}