{
  "type": "Feature",
  "properties": {
    "iso:country": "GB",
    "wof:name": "IP29 5EQ",
    "wof:placetype": "postalcode"
  },
  "geometry": {"coordinates":[0.573394,52.233911],"type":"Point"}
}
