{
  "type": "Feature",
  "properties": {
    "iso:country":"GB",
    "wof:name":"IP29 5EQ",
    "wof:placetype":"postalcode"
},
  "geometry": {"coordinates":[0.57339377400891,52.23391091466821],"type":"Point"}
}