{
  "type": "Feature",
  "properties": {
    "iso:country":"GB",
    "wof:name":"LE2 9UJ",
    "wof:placetype":"postalcode"
},
  "geometry": {"coordinates":[-1.1499778010648,52.57888574717145],"type":"Point"}
}