{
  "type": "Feature",
  "properties": {
    "iso:country": "GB",
    "wof:name": "LE2 9UJ",
    "wof:placetype": "postalcode"
  },
  "geometry": {"coordinates":[-1.149978,52.578886],"type":"Point"}
}
