{
  "type": "Feature",
  "properties": {
    "date:inception_lower":"1986-04-01",
    "date:inception_upper":"1986-04-30",
    "iso:country":"GB",
    "wof:name":"LE2 9UJ",
    "wof:placetype":"postalcode"
},
  "geometry": {"coordinates":[-1.149978,52.578886],"type":"Point"}
}