{
  "type": "Feature",
  "properties": {
    "iso:country": "GB",
    "wof:name": "MK18 7RD",
    "wof:placetype": "postalcode"
  },
  "geometry": {"coordinates":[-0.974458,51.986606],"type":"Point"}
}
