{
  "type": "Feature",
  "properties": {
    "date:inception_lower": "2012-11-01",
    "date:inception_upper": "2012-11-01",
    "iso:country": "GB",
    "wof:name": "MK18 7RD",
    "wof:placetype": "postalcode"
  },
  "geometry": {"coordinates":[-0.974458,51.986606],"type":"Point"}
}
