{
  "type": "Feature",
  "properties": {
    "iso:country":"GB",
    "wof:name":"HP19 8SW",
    "wof:placetype":"postalcode"
},
  "geometry": {"coordinates":[-0.84704468973539,51.82563448052783],"type":"Point"}
}