{
  "type": "Feature",
  "properties": {
    "iso:country":"GB",
    "wof:name":"HX3 9DQ",
    "wof:placetype":"postalcode"
},
  "geometry": {"coordinates":[-1.84781410271396,53.70471943359055],"type":"Point"}
}