{
  "type": "Feature",
  "properties": {
    "iso:country":"GB",
    "wof:name":"WA7 4HP",
    "wof:placetype":"postalcode"
},
  "geometry": {"coordinates":[-2.75829133380551,53.32496442928332],"type":"Point"}
}