{
  "type": "Feature",
  "properties": {
    "date:inception_lower": "1995-12-01",
    "date:inception_upper": "1995-12-01",
    "iso:country": "GB",
    "wof:name": "CA2 5SL",
    "wof:placetype": "postalcode"
  },
  "geometry": {"coordinates":[-2.941736,54.883195],"type":"Point"}
}
