{
  "type": "Feature",
  "properties": {
    "iso:country":"GB",
    "wof:name":"BN16 3QY",
    "wof:placetype":"postalcode"
},
  "geometry": {"coordinates":[-0.51085442717598,50.81579727258308],"type":"Point"}
}