{
  "type": "Feature",
  "properties": {
    "iso:country": "GB",
    "wof:name": "BN16 3QY",
    "wof:placetype": "postalcode"
  },
  "geometry": {"coordinates":[-0.510854,50.815797],"type":"Point"}
}
