{
  "type": "Feature",
  "properties": {
    "date:inception_lower": "2023-04-01",
    "date:inception_upper": "2023-04-01",
    "iso:country": "GB",
    "wof:name": "BB11 2HJ",
    "wof:placetype": "postalcode"
  },
  "geometry": {"coordinates":[-2.246127,53.786026],"type":"Point"}
}
