{
  "type": "Feature",
  "properties": {
    "iso:country":"GB",
    "wof:name":"SY4 5JX",
    "wof:placetype":"postalcode"
},
  "geometry": {"coordinates":[-2.72468570944798,52.85643913330199],"type":"Point"}
}