{
  "type": "Feature",
  "properties": {
    "date:inception_lower": "1992-08-01",
    "date:inception_upper": "1992-08-01",
    "iso:country": "GB",
    "wof:name": "SY4 5JX",
    "wof:placetype": "postalcode"
  },
  "geometry": {"coordinates":[-2.724686,52.856439],"type":"Point"}
}
