{
  "type": "Feature",
  "properties": {
    "iso:country":"GB",
    "wof:name":"UB7 0DR",
    "wof:placetype":"postalcode"
},
  "geometry": {"coordinates":[-0.4567131979432,51.48192927122474],"type":"Point"}
}