{
  "type": "Feature",
  "properties": {
    "iso:country":"GB",
    "wof:name":"WN2 1ZA",
    "wof:placetype":"postalcode"
},
  "geometry": {"coordinates":[-2.58566520736013,53.5722970977745],"type":"Point"}
}