{
  "type": "Feature",
  "properties": {
    "iso:country":"GB",
    "wof:name":"E1 8EB",
    "wof:placetype":"postalcode"
},
  "geometry": {"coordinates":[-0.07021270872898,51.51422632921618],"type":"Point"}
}