{
  "type": "Feature",
  "properties": {
    "iso:country":"GB",
    "wof:name":"OL6 8JE",
    "wof:placetype":"postalcode"
},
  "geometry": {"coordinates":[-2.08902729036617,53.49379210471755],"type":"Point"}
}