{
  "type": "Feature",
  "properties": {
    "iso:country":"GB",
    "wof:name":"TA1 3DT",
    "wof:placetype":"postalcode"
},
  "geometry": {"coordinates":[-3.09536682913636,51.01228229424131],"type":"Point"}
}