{
  "type": "Feature",
  "properties": {
    "iso:country":"GB",
    "wof:name":"EX7 9QL",
    "wof:placetype":"postalcode"
},
  "geometry": {"coordinates":[-3.4783061485652,50.58017815636202],"type":"Point"}
}