{
  "type": "Feature",
  "properties": {
    "iso:country": "GB",
    "wof:name": "DL12 8EN",
    "wof:placetype": "postalcode"
  },
  "geometry": {"coordinates":[-1.92161,54.545963],"type":"Point"}
}
