{
  "type": "Feature",
  "properties": {
    "iso:country":"GB",
    "wof:name":"BR6 6LG",
    "wof:placetype":"postalcode"
},
  "geometry": {"coordinates":[0.09580135449829,51.35726580543182],"type":"Point"}
}