{
  "type": "Feature",
  "properties": {
    "iso:country": "GB",
    "wof:name": "N17 6UJ",
    "wof:placetype": "postalcode"
  },
  "geometry": {"coordinates":[-0.074592,51.593522],"type":"Point"}
}
