{
  "type": "Feature",
  "properties": {
    "date:inception_lower": "1980-01-01",
    "date:inception_upper": "1980-01-01",
    "iso:country": "GB",
    "wof:name": "N17 6UJ",
    "wof:placetype": "postalcode"
  },
  "geometry": {"coordinates":[-0.074592,51.593522],"type":"Point"}
}
