{
  "type": "Feature",
  "properties": {
    "iso:country":"GB",
    "wof:name":"N17 6UJ",
    "wof:placetype":"postalcode"
},
  "geometry": {"coordinates":[-0.07459215863028,51.59352247488346],"type":"Point"}
}