{
  "type": "Feature",
  "properties": {
    "date:inception_lower":"1980-01-01",
    "date:inception_upper":"1980-01-31",
    "iso:country":"GB",
    "wof:name":"EX34 9AU",
    "wof:placetype":"postalcode"
},
  "geometry": {"coordinates":[-4.122241,51.208789],"type":"Point"}
}