{
  "type": "Feature",
  "properties": {
    "date:inception_lower":"1983-07-01",
    "date:inception_upper":"1983-07-31",
    "iso:country":"GB",
    "wof:name":"ME8 0DZ",
    "wof:placetype":"postalcode"
},
  "geometry": {"coordinates":[0.591081,51.35768],"type":"Point"}
}