{
  "type": "Feature",
  "properties": {
    "iso:country":"GB",
    "wof:name":"ME8 0DZ",
    "wof:placetype":"postalcode"
},
  "geometry": {"coordinates":[0.5910805467406,51.35767953910194],"type":"Point"}
}