{
  "type": "Feature",
  "properties": {
    "date:inception_lower": "2022-04-01",
    "date:inception_upper": "2022-04-01",
    "iso:country": "GB",
    "wof:name": "NE25 0GG",
    "wof:placetype": "postalcode"
  },
  "geometry": {"coordinates":[-1.513073,55.084855],"type":"Point"}
}
