{
  "type": "Feature",
  "properties": {
    "iso:country": "GB",
    "wof:name": "MK14 6AX",
    "wof:placetype": "postalcode"
  },
  "geometry": {"coordinates":[-0.764079,52.066614],"type":"Point"}
}
