{
  "type": "Feature",
  "properties": {
    "iso:country":"GB",
    "wof:name":"SN5 6EH",
    "wof:placetype":"postalcode"
},
  "geometry": {"coordinates":[-1.84590490082694,51.55605246427946],"type":"Point"}
}