{
  "type": "Feature",
  "properties": {
    "date:inception_lower":"1985-04-01",
    "date:inception_upper":"1985-04-30",
    "iso:country":"GB",
    "wof:name":"SN5 6EH",
    "wof:placetype":"postalcode"
},
  "geometry": {"coordinates":[-1.845905,51.556052],"type":"Point"}
}