{
  "type": "Feature",
  "properties": {
    "date:inception_lower": "1996-12-01",
    "date:inception_upper": "1996-12-01",
    "iso:country": "GB",
    "wof:name": "LA12 8LU",
    "wof:placetype": "postalcode"
  },
  "geometry": {"coordinates":[-3.018773,54.322474],"type":"Point"}
}
