{
  "type": "Feature",
  "properties": {
    "iso:country":"GB",
    "wof:name":"LA12 8LU",
    "wof:placetype":"postalcode"
},
  "geometry": {"coordinates":[-3.01877313530432,54.32247435513118],"type":"Point"}
}