{
  "type": "Feature",
  "properties": {
    "iso:country":"GB",
    "wof:name":"G44 4HG",
    "wof:placetype":"postalcode"
},
  "geometry": {"coordinates":[-4.26260709259924,55.81787142489983],"type":"Point"}
}