{
  "type": "Feature",
  "properties": {
    "iso:country":"GB",
    "wof:name":"W1U 3JU",
    "wof:placetype":"postalcode"
},
  "geometry": {"coordinates":[-0.15156198124395,51.51729012131222],"type":"Point"}
}