{
  "type": "Feature",
  "properties": {
    "iso:country":"GB",
    "wof:name":"ST5 5LW",
    "wof:placetype":"postalcode"
},
  "geometry": {"coordinates":[-2.3062741344973,52.95688743660204],"type":"Point"}
}