{
  "type": "Feature",
  "properties": {
    "iso:country":"GB",
    "wof:name":"HS1 2XJ",
    "wof:placetype":"postalcode"
},
  "geometry": {"coordinates":[-6.38996855910251,58.2084139586177],"type":"Point"}
}