{
  "type": "Feature",
  "properties": {
    "iso:country":"GB",
    "wof:name":"W3 0PW",
    "wof:placetype":"postalcode"
},
  "geometry": {"coordinates":[-0.26740826231733,51.52279032157093],"type":"Point"}
}