{
  "type": "Feature",
  "properties": {
    "iso:country": "GB",
    "wof:name": "PE11 2AL",
    "wof:placetype": "postalcode"
  },
  "geometry": {"coordinates":[-0.136032,52.797497],"type":"Point"}
}
