{
  "type": "Feature",
  "properties": {
    "date:inception_lower":"2009-08-01",
    "date:inception_upper":"2009-08-31",
    "iso:country":"GB",
    "wof:name":"PE11 2AL",
    "wof:placetype":"postalcode"
},
  "geometry": {"coordinates":[-0.136032,52.797497],"type":"Point"}
}