{
  "type": "Feature",
  "properties": {
    "iso:country": "GB",
    "wof:name": "L36 0SR",
    "wof:placetype": "postalcode"
  },
  "geometry": {"coordinates":[-2.828385,53.402126],"type":"Point"}
}
