{
  "type": "Feature",
  "properties": {
    "iso:country": "GB",
    "wof:name": "CT1 3UB",
    "wof:placetype": "postalcode"
  },
  "geometry": {"coordinates":[1.059735,51.268432],"type":"Point"}
}
