{
  "type": "Feature",
  "properties": {
    "iso:country":"GB",
    "wof:name":"CF15 9TN",
    "wof:placetype":"postalcode"
},
  "geometry": {"coordinates":[-3.29911831021273,51.53071425826204],"type":"Point"}
}