{
  "type": "Feature",
  "properties": {
    "date:inception_lower": "1980-01-01",
    "date:inception_upper": "1980-01-01",
    "iso:country": "GB",
    "wof:name": "SL2 1ET",
    "wof:placetype": "postalcode"
  },
  "geometry": {"coordinates":[-0.620597,51.526018],"type":"Point"}
}
