{
  "type": "Feature",
  "properties": {
    "iso:country":"GB",
    "wof:name":"SL2 1ET",
    "wof:placetype":"postalcode"
},
  "geometry": {"coordinates":[-0.62059679690322,51.52601809529581],"type":"Point"}
}