{
  "type": "Feature",
  "properties": {
    "iso:country":"GB",
    "wof:name":"LA4 4BW",
    "wof:placetype":"postalcode"
},
  "geometry": {"coordinates":[-2.86777484380955,54.07154184343385],"type":"Point"}
}