{
  "type": "Feature",
  "properties": {
    "iso:country":"GB",
    "wof:name":"W1G 0QD",
    "wof:placetype":"postalcode"
},
  "geometry": {"coordinates":[-0.14354184842318,51.51709151629507],"type":"Point"}
}