{
  "type": "Feature",
  "properties": {
    "iso:country":"GB",
    "wof:name":"L30 3TD",
    "wof:placetype":"postalcode"
},
  "geometry": {"coordinates":[-2.97705153933386,53.48875126800048],"type":"Point"}
}