{
  "type": "Feature",
  "properties": {
    "iso:country":"GB",
    "wof:name":"NW4 2EU",
    "wof:placetype":"postalcode"
},
  "geometry": {"coordinates":[-0.21612967649742,51.5830169397229],"type":"Point"}
}