{
  "type": "Feature",
  "properties": {
    "iso:country":"GB",
    "wof:name":"RG12 9QE",
    "wof:placetype":"postalcode"
},
  "geometry": {"coordinates":[-0.73524968455952,51.40592697043144],"type":"Point"}
}