{
  "type": "Feature",
  "properties": {
    "iso:country": "GB",
    "wof:name": "DE23 6FZ",
    "wof:placetype": "postalcode"
  },
  "geometry": {"coordinates":[-1.508172,52.905],"type":"Point"}
}
