{
  "type": "Feature",
  "properties": {
    "iso:country":"GB",
    "wof:name":"DE23 6FZ",
    "wof:placetype":"postalcode"
},
  "geometry": {"coordinates":[-1.50809843129003,52.90523337230118],"type":"Point"}
}