{
  "type": "Feature",
  "properties": {
    "iso:country":"GB",
    "wof:name":"SP4 8HT",
    "wof:placetype":"postalcode"
},
  "geometry": {"coordinates":[-1.76802795091023,51.20650850265999],"type":"Point"}
}