{
  "type": "Feature",
  "properties": {
    "date:inception_lower": "1980-01-01",
    "date:inception_upper": "1980-01-01",
    "iso:country": "GB",
    "wof:name": "SP4 8HT",
    "wof:placetype": "postalcode"
  },
  "geometry": {"coordinates":[-1.768028,51.206508],"type":"Point"}
}
