{
  "type": "Feature",
  "properties": {
    "iso:country": "GB",
    "wof:name": "MK45 3DX",
    "wof:placetype": "postalcode"
  },
  "geometry": {"coordinates":[-0.441787,52.079651],"type":"Point"}
}
