{
  "type": "Feature",
  "properties": {
    "iso:country":"GB",
    "wof:name":"MK45 3DX",
    "wof:placetype":"postalcode"
},
  "geometry": {"coordinates":[-0.44178720031294,52.07965115106273],"type":"Point"}
}