{
  "type": "Feature",
  "properties": {
    "date:inception_lower": "1980-01-01",
    "date:inception_upper": "1980-01-01",
    "iso:country": "GB",
    "wof:name": "DT2 7RB",
    "wof:placetype": "postalcode"
  },
  "geometry": {"coordinates":[-2.417395,50.801133],"type":"Point"}
}
