{
  "type": "Feature",
  "properties": {
    "iso:country":"GB",
    "wof:name":"DT2 7RB",
    "wof:placetype":"postalcode"
},
  "geometry": {"coordinates":[-2.41739636082567,50.80116007910714],"type":"Point"}
}