{
  "type": "Feature",
  "properties": {
    "iso:country":"GB",
    "wof:name":"M41 6ER",
    "wof:placetype":"postalcode"
},
  "geometry": {"coordinates":[-2.40579708541961,53.44764487387692],"type":"Point"}
}