{
  "type": "Feature",
  "properties": {
    "iso:country":"GB",
    "wof:name":"PE3 7BQ",
    "wof:placetype":"postalcode"
},
  "geometry": {"coordinates":[-0.27329287471196,52.58608911088757],"type":"Point"}
}