{
  "type": "Feature",
  "properties": {
    "iso:country": "GB",
    "wof:name": "TN15 6GD",
    "wof:placetype": "postalcode"
  },
  "geometry": {"coordinates":[0.230486,51.307825],"type":"Point"}
}
