{
  "type": "Feature",
  "properties": {
    "iso:country":"GB",
    "wof:name":"BB3 1JH",
    "wof:placetype":"postalcode"
},
  "geometry": {"coordinates":[-2.48416543590656,53.70115791516361],"type":"Point"}
}