{
  "type": "Feature",
  "properties": {
    "iso:country": "GB",
    "wof:name": "BB3 1JH",
    "wof:placetype": "postalcode"
  },
  "geometry": {"coordinates":[-2.484165,53.701158],"type":"Point"}
}
