{
  "type": "Feature",
  "properties": {
    "date:inception_lower": "2009-09-01",
    "date:inception_upper": "2009-09-01",
    "iso:country": "GB",
    "wof:name": "BD21 5EG",
    "wof:placetype": "postalcode"
  },
  "geometry": {"coordinates":[-1.917129,53.853125],"type":"Point"}
}
