{
  "type": "Feature",
  "properties": {
    "iso:country":"GB",
    "wof:name":"BD21 5EG",
    "wof:placetype":"postalcode"
},
  "geometry": {"coordinates":[-1.9171291378392,53.85312500660756],"type":"Point"}
}