{
  "type": "Feature",
  "properties": {
    "iso:country": "GB",
    "wof:name": "TD15 2QG",
    "wof:placetype": "postalcode"
  },
  "geometry": {"coordinates":[-2.085042,55.632],"type":"Point"}
}
