{
  "type": "Feature",
  "properties": {
    "date:inception_lower": "1981-06-01",
    "date:inception_upper": "1981-06-01",
    "iso:country": "GB",
    "wof:name": "TD15 2QG",
    "wof:placetype": "postalcode"
  },
  "geometry": {"coordinates":[-2.085042,55.632],"type":"Point"}
}
