{
  "type": "Feature",
  "properties": {
    "date:inception_lower":"1994-05-01",
    "date:inception_upper":"1994-05-31",
    "iso:country":"GB",
    "wof:name":"M9 7EH",
    "wof:placetype":"postalcode"
},
  "geometry": {"coordinates":[-2.196209,53.522732],"type":"Point"}
}