{
  "type": "Feature",
  "properties": {
    "iso:country":"GB",
    "wof:name":"M9 7EH",
    "wof:placetype":"postalcode"
},
  "geometry": {"coordinates":[-2.19620903004471,53.52273250181311],"type":"Point"}
}