{
  "type": "Feature",
  "properties": {
    "iso:country": "GB",
    "wof:name": "CA21 2YF",
    "wof:placetype": "postalcode"
  },
  "geometry": {"coordinates":[-3.51655,54.448873],"type":"Point"}
}
