{
  "type": "Feature",
  "properties": {
    "iso:country":"GB",
    "wof:name":"CA21 2YF",
    "wof:placetype":"postalcode"
},
  "geometry": {"coordinates":[-3.51654970259279,54.44887318275284],"type":"Point"}
}