{
  "type": "Feature",
  "properties": {
    "iso:country":"GB",
    "wof:name":"W5 5DA",
    "wof:placetype":"postalcode"
},
  "geometry": {"coordinates":[-0.30517975971663,51.51101365006691],"type":"Point"}
}