{
  "type": "Feature",
  "properties": {
    "iso:country":"GB",
    "wof:name":"SP10 4BX",
    "wof:placetype":"postalcode"
},
  "geometry": {"coordinates":[-1.48287287626844,51.22281612078875],"type":"Point"}
}