{
  "type": "Feature",
  "properties": {
    "iso:country": "GB",
    "wof:name": "NR29 3LE",
    "wof:placetype": "postalcode"
  },
  "geometry": {"coordinates":[1.688231,52.67993],"type":"Point"}
}
