{
  "type": "Feature",
  "properties": {
    "date:inception_lower": "1980-01-01",
    "date:inception_upper": "1980-01-01",
    "iso:country": "GB",
    "wof:name": "NR29 3LE",
    "wof:placetype": "postalcode"
  },
  "geometry": {"coordinates":[1.688231,52.67993],"type":"Point"}
}
