{
  "type": "Feature",
  "properties": {
    "iso:country":"GB",
    "wof:name":"SO51 8LZ",
    "wof:placetype":"postalcode"
},
  "geometry": {"coordinates":[-1.49900724523859,50.98652767667978],"type":"Point"}
}