{
  "type": "Feature",
  "properties": {
    "iso:country":"GB",
    "wof:name":"DN7 6DZ",
    "wof:placetype":"postalcode"
},
  "geometry": {"coordinates":[-0.97175407152832,53.57071739145867],"type":"Point"}
}