{
  "type": "Feature",
  "properties": {
    "iso:country":"GB",
    "wof:name":"BL2 1LJ",
    "wof:placetype":"postalcode"
},
  "geometry": {"coordinates":[-2.41233705574348,53.57240024524313],"type":"Point"}
}