{
  "type": "Feature",
  "properties": {
    "iso:country": "GB",
    "wof:name": "TS25 4HS",
    "wof:placetype": "postalcode"
  },
  "geometry": {"coordinates":[-1.238341,54.669321],"type":"Point"}
}
