{
  "type": "Feature",
  "properties": {
    "date:inception_lower":"1993-08-01",
    "date:inception_upper":"1993-08-31",
    "iso:country":"GB",
    "wof:name":"BN1 9RP",
    "wof:placetype":"postalcode"
},
  "geometry": {"coordinates":[-0.088139,50.869766],"type":"Point"}
}