{
  "type": "Feature",
  "properties": {
    "iso:country": "GB",
    "wof:name": "BN1 9RP",
    "wof:placetype": "postalcode"
  },
  "geometry": {"coordinates":[-0.088139,50.869766],"type":"Point"}
}
