{
  "type": "Feature",
  "properties": {
    "iso:country":"GB",
    "wof:name":"HU19 2EX",
    "wof:placetype":"postalcode"
},
  "geometry": {"coordinates":[0.02502938626958,53.72696886336898],"type":"Point"}
}