{
  "type": "Feature",
  "properties": {
    "iso:country":"GB",
    "wof:name":"ME16 9BY",
    "wof:placetype":"postalcode"
},
  "geometry": {"coordinates":[0.48619934130806,51.26442324193337],"type":"Point"}
}