{
  "type": "Feature",
  "properties": {
    "date:inception_lower": "2018-06-01",
    "date:inception_upper": "2018-06-01",
    "iso:country": "GB",
    "wof:name": "SG19 2FA",
    "wof:placetype": "postalcode"
  },
  "geometry": {"coordinates":[-0.216085,52.125153],"type":"Point"}
}
