{
  "type": "Feature",
  "properties": {
    "iso:country":"GB",
    "wof:name":"M27 5ZG",
    "wof:placetype":"postalcode"
},
  "geometry": {"coordinates":[-2.342376267313,53.50723051929123],"type":"Point"}
}