{
  "type": "Feature",
  "properties": {
    "iso:country":"GB",
    "wof:name":"CH44 2EW",
    "wof:placetype":"postalcode"
},
  "geometry": {"coordinates":[-3.06051335097213,53.41720691122998],"type":"Point"}
}