{
  "type": "Feature",
  "properties": {
    "date:inception_lower": "1994-12-01",
    "date:inception_upper": "1994-12-01",
    "iso:country": "GB",
    "wof:name": "WN2 3DZ",
    "wof:placetype": "postalcode"
  },
  "geometry": {"coordinates":[-2.582078,53.531004],"type":"Point"}
}
