{
  "type": "Feature",
  "properties": {
    "iso:country":"GB",
    "wof:name":"WN2 3DZ",
    "wof:placetype":"postalcode"
},
  "geometry": {"coordinates":[-2.58207779390965,53.53100363643331],"type":"Point"}
}