{
  "type": "Feature",
  "properties": {
    "date:inception_lower":"2004-08-01",
    "date:inception_upper":"2004-08-31",
    "iso:country":"GB",
    "wof:name":"BH21 3JS",
    "wof:placetype":"postalcode"
},
  "geometry": {"coordinates":[-2.019815,50.768373],"type":"Point"}
}