{
  "type": "Feature",
  "properties": {
    "iso:country":"GB",
    "wof:name":"BH21 3JS",
    "wof:placetype":"postalcode"
},
  "geometry": {"coordinates":[-2.01981461923014,50.76837265517446],"type":"Point"}
}