{
  "type": "Feature",
  "properties": {
    "iso:country":"GB",
    "wof:name":"PH16 5GZ",
    "wof:placetype":"postalcode"
},
  "geometry": {"coordinates":[-3.77978281374716,56.74461901022018],"type":"Point"}
}