{
  "type": "Feature",
  "properties": {
    "iso:country": "GB",
    "wof:name": "PH16 5GZ",
    "wof:placetype": "postalcode"
  },
  "geometry": {"coordinates":[-3.77978,56.744607],"type":"Point"}
}
