{
  "type": "Feature",
  "properties": {
    "iso:country":"GB",
    "wof:name":"TA5 1NG",
    "wof:placetype":"postalcode"
},
  "geometry": {"coordinates":[-3.15690009695484,51.15165724880303],"type":"Point"}
}