{
  "type": "Feature",
  "properties": {
    "iso:country":"GB",
    "wof:name":"DN21 1TH",
    "wof:placetype":"postalcode"
},
  "geometry": {"coordinates":[-0.75679428012422,53.39992555653575],"type":"Point"}
}