{
  "type": "Feature",
  "properties": {
    "iso:country":"GB",
    "wof:name":"MK4 4EP",
    "wof:placetype":"postalcode"
},
  "geometry": {"coordinates":[-0.80773649674905,52.00403440090757],"type":"Point"}
}