{
  "type": "Feature",
  "properties": {
    "date:inception_lower": "2005-11-01",
    "date:inception_upper": "2005-11-01",
    "iso:country": "GB",
    "wof:name": "MK4 4EP",
    "wof:placetype": "postalcode"
  },
  "geometry": {"coordinates":[-0.807736,52.004034],"type":"Point"}
}
