{
  "type": "Feature",
  "properties": {
    "iso:country":"GB",
    "wof:name":"CO9 3DN",
    "wof:placetype":"postalcode"
},
  "geometry": {"coordinates":[0.59550193287639,51.99194340614508],"type":"Point"}
}