{
  "type": "Feature",
  "properties": {
    "date:inception_lower":"1980-01-01",
    "date:inception_upper":"1980-01-31",
    "iso:country":"GB",
    "wof:name":"WA4 4DA",
    "wof:placetype":"postalcode"
},
  "geometry": {"coordinates":[-2.600981,53.335935],"type":"Point"}
}