{
  "type": "Feature",
  "properties": {
    "iso:country":"GB",
    "wof:name":"WA4 4DA",
    "wof:placetype":"postalcode"
},
  "geometry": {"coordinates":[-2.59896500993164,53.33557888946886],"type":"Point"}
}