{
  "type": "Feature",
  "properties": {
    "date:inception_lower":"1980-01-01",
    "date:inception_upper":"1980-01-31",
    "iso:country":"GB",
    "wof:name":"DA7 5DP",
    "wof:placetype":"postalcode"
},
  "geometry": {"coordinates":[0.148357,51.469823],"type":"Point"}
}