{
  "type": "Feature",
  "properties": {
    "iso:country":"GB",
    "wof:name":"DA7 5DP",
    "wof:placetype":"postalcode"
},
  "geometry": {"coordinates":[0.14835687581174,51.46982320591774],"type":"Point"}
}