{
  "type": "Feature",
  "properties": {
    "iso:country":"GB",
    "wof:name":"TS24 9PS",
    "wof:placetype":"postalcode"
},
  "geometry": {"coordinates":[-1.23626526295929,54.7130106798933],"type":"Point"}
}