{
  "type": "Feature",
  "properties": {
    "date:inception_lower": "1987-04-01",
    "date:inception_upper": "1987-04-01",
    "iso:country": "GB",
    "wof:name": "IP12 1DW",
    "wof:placetype": "postalcode"
  },
  "geometry": {"coordinates":[1.316274,52.092898],"type":"Point"}
}
