{
  "type": "Feature",
  "properties": {
    "iso:country":"GB",
    "wof:name":"B67 5BE",
    "wof:placetype":"postalcode"
},
  "geometry": {"coordinates":[-1.97158678007241,52.4738816871786],"type":"Point"}
}