{
  "type": "Feature",
  "properties": {
    "iso:country":"GB",
    "wof:name":"W1K 2LA",
    "wof:placetype":"postalcode"
},
  "geometry": {"coordinates":[-0.15090355833629,51.51005877049558],"type":"Point"}
}