{
  "type": "Feature",
  "properties": {
    "date:inception_lower": "1987-04-01",
    "date:inception_upper": "1987-04-01",
    "iso:country": "GB",
    "wof:name": "BN11 4BZ",
    "wof:placetype": "postalcode"
  },
  "geometry": {"coordinates":[-0.378408,50.811729],"type":"Point"}
}
