{
  "type": "Feature",
  "properties": {
    "iso:country": "GB",
    "wof:name": "LA15 8SJ",
    "wof:placetype": "postalcode"
  },
  "geometry": {"coordinates":[-3.178765,54.159387],"type":"Point"}
}
