{
  "type": "Feature",
  "properties": {
    "date:inception_lower": "1980-01-01",
    "date:inception_upper": "1980-01-01",
    "iso:country": "GB",
    "wof:name": "NR16 1NZ",
    "wof:placetype": "postalcode"
  },
  "geometry": {"coordinates":[1.131853,52.444399],"type":"Point"}
}
