{
  "type": "Feature",
  "properties": {
    "date:inception_lower": "2019-07-01",
    "date:inception_upper": "2019-07-01",
    "iso:country": "GB",
    "wof:name": "EX17 3FP",
    "wof:placetype": "postalcode"
  },
  "geometry": {"coordinates":[-3.645048,50.785286],"type":"Point"}
}
