{
  "type": "Feature",
  "properties": {
    "iso:country":"GB",
    "wof:name":"TS5 5JP",
    "wof:placetype":"postalcode"
},
  "geometry": {"coordinates":[-1.25745648393222,54.55289598892081],"type":"Point"}
}