{
  "type": "Feature",
  "properties": {
    "iso:country":"GB",
    "wof:name":"CO15 5LW",
    "wof:placetype":"postalcode"
},
  "geometry": {"coordinates":[1.18675441518346,51.80198795396937],"type":"Point"}
}