{
  "type": "Feature",
  "properties": {
    "iso:country": "GB",
    "wof:name": "CO15 5LW",
    "wof:placetype": "postalcode"
  },
  "geometry": {"coordinates":[1.186754,51.801988],"type":"Point"}
}
