{
  "type": "Feature",
  "properties": {
    "iso:country":"GB",
    "wof:name":"NW1 4QP",
    "wof:placetype":"postalcode"
},
  "geometry": {"coordinates":[-0.15671742091276,51.52382785241922],"type":"Point"}
}