{
  "type": "Feature",
  "properties": {
    "date:inception_lower": "1980-01-01",
    "date:inception_upper": "1980-01-01",
    "iso:country": "GB",
    "wof:name": "PO6 3RE",
    "wof:placetype": "postalcode"
  },
  "geometry": {"coordinates":[-1.07837,50.850274],"type":"Point"}
}
