{
  "type": "Feature",
  "properties": {
    "iso:country":"GB",
    "wof:name":"WD19 4LT",
    "wof:placetype":"postalcode"
},
  "geometry": {"coordinates":[-0.39369535028922,51.6337341760323],"type":"Point"}
}