{
  "type": "Feature",
  "properties": {
    "date:inception_lower":"2001-06-01",
    "date:inception_upper":"2001-06-30",
    "iso:country":"GB",
    "wof:name":"BD23 6XJ",
    "wof:placetype":"postalcode"
},
  "geometry": {"coordinates":[-2.001752,53.96964],"type":"Point"}
}