{
  "type": "Feature",
  "properties": {
    "iso:country":"GB",
    "wof:name":"BD23 6XJ",
    "wof:placetype":"postalcode"
},
  "geometry": {"coordinates":[-2.00174752422678,53.96962611482878],"type":"Point"}
}