{
  "type": "Feature",
  "properties": {
    "iso:country": "GB",
    "wof:name": "BD23 6XJ",
    "wof:placetype": "postalcode"
  },
  "geometry": {"coordinates":[-2.001752,53.96964],"type":"Point"}
}
