{
  "type": "Feature",
  "properties": {
    "iso:country": "GB",
    "wof:name": "IP9 2FP",
    "wof:placetype": "postalcode"
  },
  "geometry": {"coordinates":[1.114208,51.988199],"type":"Point"}
}
