{
  "type": "Feature",
  "properties": {
    "iso:country":"GB",
    "wof:name":"IP24 1FG",
    "wof:placetype":"postalcode"
},
  "geometry": {"coordinates":[0.75460762532129,52.42602401968267],"type":"Point"}
}