{
  "type": "Feature",
  "properties": {
    "date:inception_lower":"2008-04-01",
    "date:inception_upper":"2008-04-30",
    "iso:country":"GB",
    "wof:name":"IP24 1FG",
    "wof:placetype":"postalcode"
},
  "geometry": {"coordinates":[0.754608,52.426024],"type":"Point"}
}