{
  "type": "Feature",
  "properties": {
    "iso:country":"GB",
    "wof:name":"SP5 1RT",
    "wof:placetype":"postalcode"
},
  "geometry": {"coordinates":[-1.66294321874036,51.09487788882549],"type":"Point"}
}