{
  "type": "Feature",
  "properties": {
    "date:inception_lower":"1990-02-01",
    "date:inception_upper":"1990-02-28",
    "iso:country":"GB",
    "wof:name":"SP5 1RT",
    "wof:placetype":"postalcode"
},
  "geometry": {"coordinates":[-1.662943,51.094878],"type":"Point"}
}