{
  "type": "Feature",
  "properties": {
    "iso:country": "GB",
    "wof:name": "SM7 1BU",
    "wof:placetype": "postalcode"
  },
  "geometry": {"coordinates":[-0.213374,51.31346],"type":"Point"}
}
