{
  "type": "Feature",
  "properties": {
    "iso:country":"GB",
    "wof:name":"SM7 1BU",
    "wof:placetype":"postalcode"
},
  "geometry": {"coordinates":[-0.21337442021518,51.31346034598922],"type":"Point"}
}