{
  "type": "Feature",
  "properties": {
    "iso:country":"GB",
    "wof:name":"DL11 7JP",
    "wof:placetype":"postalcode"
},
  "geometry": {"coordinates":[-1.77479801783615,54.44853167389905],"type":"Point"}
}