{
  "type": "Feature",
  "properties": {
    "date:inception_lower": "2007-07-01",
    "date:inception_upper": "2007-07-01",
    "iso:country": "GB",
    "wof:name": "TR5 0RQ",
    "wof:placetype": "postalcode"
  },
  "geometry": {"coordinates":[-5.204267,50.311063],"type":"Point"}
}
