{
  "type": "Feature",
  "properties": {
    "iso:country":"GB",
    "wof:name":"TR5 0RQ",
    "wof:placetype":"postalcode"
},
  "geometry": {"coordinates":[-5.20426698014235,50.311063251043],"type":"Point"}
}