{
  "type": "Feature",
  "properties": {
    "iso:country": "GB",
    "wof:name": "PE12 9NL",
    "wof:placetype": "postalcode"
  },
  "geometry": {"coordinates":[0.14212,52.849274],"type":"Point"}
}
