{
  "type": "Feature",
  "properties": {
    "date:inception_lower": "1980-01-01",
    "date:inception_upper": "1980-01-01",
    "iso:country": "GB",
    "wof:name": "PE12 9NL",
    "wof:placetype": "postalcode"
  },
  "geometry": {"coordinates":[0.142517,52.849262],"type":"Point"}
}
