{
  "type": "Feature",
  "properties": {
    "iso:country": "GB",
    "wof:name": "G32 8PP",
    "wof:placetype": "postalcode"
  },
  "geometry": {"coordinates":[-4.179204,55.841622],"type":"Point"}
}
