{
  "type": "Feature",
  "properties": {
    "iso:country":"GB",
    "wof:name":"G32 8PP",
    "wof:placetype":"postalcode"
},
  "geometry": {"coordinates":[-4.17920436615512,55.84162171493097],"type":"Point"}
}