{
  "type": "Feature",
  "properties": {
    "iso:country": "GB",
    "wof:name": "SP2 0JS",
    "wof:placetype": "postalcode"
  },
  "geometry": {"coordinates":[-1.864521,51.079585],"type":"Point"}
}
