{
  "type": "Feature",
  "properties": {
    "iso:country":"GB",
    "wof:name":"SP2 0JS",
    "wof:placetype":"postalcode"
},
  "geometry": {"coordinates":[-1.86452059121193,51.07958453818338],"type":"Point"}
}