{
  "type": "Feature",
  "properties": {
    "iso:country":"GB",
    "wof:name":"IG6 1EG",
    "wof:placetype":"postalcode"
},
  "geometry": {"coordinates":[0.08028904211977,51.58294768509806],"type":"Point"}
}