{
  "type": "Feature",
  "properties": {
    "date:inception_lower":"1980-01-01",
    "date:inception_upper":"1980-01-31",
    "iso:country":"GB",
    "wof:name":"IG6 1EG",
    "wof:placetype":"postalcode"
},
  "geometry": {"coordinates":[0.080289,51.582948],"type":"Point"}
}