{
  "type": "Feature",
  "properties": {
    "iso:country": "GB",
    "wof:name": "LL14 5LS",
    "wof:placetype": "postalcode"
  },
  "geometry": {"coordinates":[-3.058422,52.932278],"type":"Point"}
}
