{
  "type": "Feature",
  "properties": {
    "date:inception_lower":"1980-01-01",
    "date:inception_upper":"1980-01-31",
    "iso:country":"GB",
    "wof:name":"LL14 5LS",
    "wof:placetype":"postalcode"
},
  "geometry": {"coordinates":[-3.058422,52.932278],"type":"Point"}
}