{
  "type": "Feature",
  "properties": {
    "iso:country":"GB",
    "wof:name":"UB5 4JZ",
    "wof:placetype":"postalcode"
},
  "geometry": {"coordinates":[-0.35414444134678,51.55349790107479],"type":"Point"}
}