{
  "type": "Feature",
  "properties": {
    "iso:country":"GB",
    "wof:name":"CW1 4TE",
    "wof:placetype":"postalcode"
},
  "geometry": {"coordinates":[-2.45847216501785,53.1219513099438],"type":"Point"}
}