{
  "type": "Feature",
  "properties": {
    "iso:country": "GB",
    "wof:name": "CW1 4TE",
    "wof:placetype": "postalcode"
  },
  "geometry": {"coordinates":[-2.458472,53.121951],"type":"Point"}
}
