{
  "type": "Feature",
  "properties": {
    "iso:country":"GB",
    "wof:name":"B36 0LR",
    "wof:placetype":"postalcode"
},
  "geometry": {"coordinates":[-1.73779361626987,52.49483837184307],"type":"Point"}
}