{
  "type": "Feature",
  "properties": {
    "date:inception_lower":"1995-01-01",
    "date:inception_upper":"1995-01-31",
    "iso:country":"GB",
    "wof:name":"B36 0LR",
    "wof:placetype":"postalcode"
},
  "geometry": {"coordinates":[-1.737794,52.494838],"type":"Point"}
}