{
  "type": "Feature",
  "properties": {
    "iso:country":"GB",
    "wof:name":"LN8 3AA",
    "wof:placetype":"postalcode"
},
  "geometry": {"coordinates":[-0.33608320215557,53.38670448087565],"type":"Point"}
}