{
  "type": "Feature",
  "properties": {
    "iso:country":"GB",
    "wof:name":"B74 4HH",
    "wof:placetype":"postalcode"
},
  "geometry": {"coordinates":[-1.86008252181168,52.59450076675037],"type":"Point"}
}