{
  "type": "Feature",
  "properties": {
    "iso:country":"GB",
    "wof:name":"CR9 1SN",
    "wof:placetype":"postalcode"
},
  "geometry": {"coordinates":[-0.10057164355111,51.37708947541832],"type":"Point"}
}