{
  "type": "Feature",
  "properties": {
    "date:inception_lower":"1980-01-01",
    "date:inception_upper":"1980-01-31",
    "iso:country":"GB",
    "wof:name":"CO10 7QT",
    "wof:placetype":"postalcode"
},
  "geometry": {"coordinates":[0.669595,52.087915],"type":"Point"}
}