{
  "type": "Feature",
  "properties": {
    "iso:country":"GB",
    "wof:name":"BS2 8LD",
    "wof:placetype":"postalcode"
},
  "geometry": {"coordinates":[-2.59175372149758,51.4629191035062],"type":"Point"}
}