{
  "type": "Feature",
  "properties": {
    "date:inception_lower": "1980-01-01",
    "date:inception_upper": "1980-01-01",
    "iso:country": "GB",
    "wof:name": "BS2 8LD",
    "wof:placetype": "postalcode"
  },
  "geometry": {"coordinates":[-2.591754,51.462919],"type":"Point"}
}
