{
  "type": "Feature",
  "properties": {
    "date:inception_lower": "1984-02-01",
    "date:inception_upper": "1984-02-01",
    "iso:country": "GB",
    "wof:name": "KT6 6QJ",
    "wof:placetype": "postalcode"
  },
  "geometry": {"coordinates":[-0.30223,51.384403],"type":"Point"}
}
