{
  "type": "Feature",
  "properties": {
    "iso:country":"GB",
    "wof:name":"KT6 6QJ",
    "wof:placetype":"postalcode"
},
  "geometry": {"coordinates":[-0.3022300231037,51.38440265443896],"type":"Point"}
}