{
  "type": "Feature",
  "properties": {
    "date:inception_lower":"1980-01-01",
    "date:inception_upper":"1980-01-31",
    "iso:country":"GB",
    "wof:name":"DT10 1HE",
    "wof:placetype":"postalcode"
},
  "geometry": {"coordinates":[-2.292376,50.934991],"type":"Point"}
}