{
  "type": "Feature",
  "properties": {
    "iso:country": "GB",
    "wof:name": "DT10 1HE",
    "wof:placetype": "postalcode"
  },
  "geometry": {"coordinates":[-2.292376,50.934991],"type":"Point"}
}
