{
  "type": "Feature",
  "properties": {
    "iso:country": "GB",
    "wof:name": "PE38 0DY",
    "wof:placetype": "postalcode"
  },
  "geometry": {"coordinates":[0.378414,52.587443],"type":"Point"}
}
