{
  "type": "Feature",
  "properties": {
    "date:inception_lower": "1980-01-01",
    "date:inception_upper": "1980-01-01",
    "iso:country": "GB",
    "wof:name": "PE38 0DY",
    "wof:placetype": "postalcode"
  },
  "geometry": {"coordinates":[0.378552,52.587818],"type":"Point"}
}
