{
  "type": "Feature",
  "properties": {
    "iso:country":"GB",
    "wof:name":"PE38 0DY",
    "wof:placetype":"postalcode"
},
  "geometry": {"coordinates":[0.37853251918662,52.58779934500425],"type":"Point"}
}