{
  "type": "Feature",
  "properties": {
    "iso:country":"GB",
    "wof:name":"CT21 4QZ",
    "wof:placetype":"postalcode"
},
  "geometry": {"coordinates":[1.08275020583317,51.07915347656105],"type":"Point"}
}