{
  "type": "Feature",
  "properties": {
    "date:inception_lower":"1998-06-01",
    "date:inception_upper":"1998-06-30",
    "iso:country":"GB",
    "wof:name":"SE20 8QB",
    "wof:placetype":"postalcode"
},
  "geometry": {"coordinates":[-0.063652,51.413634],"type":"Point"}
}