{
  "type": "Feature",
  "properties": {
    "iso:country":"GB",
    "wof:name":"SE20 8QB",
    "wof:placetype":"postalcode"
},
  "geometry": {"coordinates":[-0.06365183345963,51.41363416698185],"type":"Point"}
}