{
  "type": "Feature",
  "properties": {
    "iso:country":"GB",
    "wof:name":"E8 4LR",
    "wof:placetype":"postalcode"
},
  "geometry": {"coordinates":[-0.0665810390302,51.54008311649048],"type":"Point"}
}