{
  "type": "Feature",
  "properties": {
    "iso:country":"GB",
    "wof:name":"AB14 0XU",
    "wof:placetype":"postalcode"
},
  "geometry": {"coordinates":[-2.27782093534582,57.10279400093533],"type":"Point"}
}