{
  "type": "Feature",
  "properties": {
    "iso:country":"GB",
    "wof:name":"ME5 9PN",
    "wof:placetype":"postalcode"
},
  "geometry": {"coordinates":[0.52513629699069,51.33606949134178],"type":"Point"}
}