{
  "type": "Feature",
  "properties": {
    "iso:country": "GB",
    "wof:name": "GL18 1BW",
    "wof:placetype": "postalcode"
  },
  "geometry": {"coordinates":[-2.413485,51.930301],"type":"Point"}
}
