{
  "type": "Feature",
  "properties": {
    "date:inception_lower": "1980-01-01",
    "date:inception_upper": "1980-01-01",
    "iso:country": "GB",
    "wof:name": "SE25 5EJ",
    "wof:placetype": "postalcode"
  },
  "geometry": {"coordinates":[-0.092519,51.392435],"type":"Point"}
}
