{
  "type": "Feature",
  "properties": {
    "iso:country": "GB",
    "wof:name": "SE25 5EJ",
    "wof:placetype": "postalcode"
  },
  "geometry": {"coordinates":[-0.092519,51.392435],"type":"Point"}
}
