{
  "type": "Feature",
  "properties": {
    "iso:country":"GB",
    "wof:name":"SE25 5EJ",
    "wof:placetype":"postalcode"
},
  "geometry": {"coordinates":[-0.09251910531117,51.39243514886056],"type":"Point"}
}