{
  "type": "Feature",
  "properties": {
    "iso:country": "GB",
    "wof:name": "OL16 1AY",
    "wof:placetype": "postalcode"
  },
  "geometry": {"coordinates":[-2.156186,53.619495],"type":"Point"}
}
