{
  "type": "Feature",
  "properties": {
    "iso:country": "GB",
    "wof:name": "OL16 1AY",
    "wof:placetype": "postalcode"
  },
  "geometry": {"coordinates":[-2.156156,53.619504],"type":"Point"}
}
