{
  "type": "Feature",
  "properties": {
    "date:inception_lower": "2020-01-01",
    "date:inception_upper": "2020-01-01",
    "iso:country": "GB",
    "wof:name": "OL16 1AY",
    "wof:placetype": "postalcode"
  },
  "geometry": {"coordinates":[-2.156186,53.619495],"type":"Point"}
}
