{
  "type": "Feature",
  "properties": {
    "date:inception_lower": "1980-01-01",
    "date:inception_upper": "1980-01-01",
    "iso:country": "GB",
    "wof:name": "SE25 6DH",
    "wof:placetype": "postalcode"
  },
  "geometry": {"coordinates":[-0.085176,51.406497],"type":"Point"}
}
