{
  "type": "Feature",
  "properties": {
    "iso:country":"GB",
    "wof:name":"CR0 4BT",
    "wof:placetype":"postalcode"
},
  "geometry": {"coordinates":[-0.10643444146141,51.36838048836545],"type":"Point"}
}