{
  "type": "Feature",
  "properties": {
    "iso:country": "GB",
    "wof:name": "LE14 2EW",
    "wof:placetype": "postalcode"
  },
  "geometry": {"coordinates":[-0.899787,52.719493],"type":"Point"}
}
