{
  "type": "Feature",
  "properties": {
    "iso:country":"GB",
    "wof:name":"LE14 2EW",
    "wof:placetype":"postalcode"
},
  "geometry": {"coordinates":[-0.89946130457991,52.71975720098888],"type":"Point"}
}