{
  "type": "Feature",
  "properties": {
    "iso:country":"GB",
    "wof:name":"PR9 9PS",
    "wof:placetype":"postalcode"
},
  "geometry": {"coordinates":[-2.97684112104302,53.66169511528962],"type":"Point"}
}