{
  "type": "Feature",
  "properties": {
    "iso:country": "GB",
    "wof:name": "SR8 4LH",
    "wof:placetype": "postalcode"
  },
  "geometry": {"coordinates":[-1.314913,54.764661],"type":"Point"}
}
