{
  "type": "Feature",
  "properties": {
    "iso:country":"GB",
    "wof:name":"B95 5HH",
    "wof:placetype":"postalcode"
},
  "geometry": {"coordinates":[-1.72244581875581,52.31198069099285],"type":"Point"}
}