{
  "type": "Feature",
  "properties": {
    "iso:country":"GB",
    "wof:name":"WF13 2QE",
    "wof:placetype":"postalcode"
},
  "geometry": {"coordinates":[-1.64151871416968,53.68945875996423],"type":"Point"}
}