{
  "type": "Feature",
  "properties": {
    "date:inception_lower":"1980-01-01",
    "date:inception_upper":"1980-01-31",
    "iso:country":"GB",
    "wof:name":"WF13 2QE",
    "wof:placetype":"postalcode"
},
  "geometry": {"coordinates":[-1.641519,53.689459],"type":"Point"}
}