{
  "type": "Feature",
  "properties": {
    "date:inception_lower": "1993-01-01",
    "date:inception_upper": "1993-01-01",
    "iso:country": "GB",
    "wof:name": "NR19 2UJ",
    "wof:placetype": "postalcode"
  },
  "geometry": {"coordinates":[0.930334,52.676863],"type":"Point"}
}
