{
  "type": "Feature",
  "properties": {
    "iso:country":"GB",
    "wof:name":"YO26 4WX",
    "wof:placetype":"postalcode"
},
  "geometry": {"coordinates":[-1.10044200260821,53.96054450937628],"type":"Point"}
}