{
  "type": "Feature",
  "properties": {
    "iso:country": "GB",
    "wof:name": "YO25 6NY",
    "wof:placetype": "postalcode"
  },
  "geometry": {"coordinates":[-0.436819,54.003892],"type":"Point"}
}
