{
  "type": "Feature",
  "properties": {
    "iso:country":"GB",
    "wof:name":"YO25 6NY",
    "wof:placetype":"postalcode"
},
  "geometry": {"coordinates":[-0.43681923130484,54.00389166924927],"type":"Point"}
}