{
  "type": "Feature",
  "properties": {
    "iso:country":"GB",
    "wof:name":"SW13 0AT",
    "wof:placetype":"postalcode"
},
  "geometry": {"coordinates":[-0.25310945966276,51.46888459844884],"type":"Point"}
}