{
  "type": "Feature",
  "properties": {
    "iso:country": "GB",
    "wof:name": "AL1 3NN",
    "wof:placetype": "postalcode"
  },
  "geometry": {"coordinates":[-0.332944,51.753711],"type":"Point"}
}
