{
  "type": "Feature",
  "properties": {
    "iso:country":"GB",
    "wof:name":"W3 6YP",
    "wof:placetype":"postalcode"
},
  "geometry": {"coordinates":[-0.25824932635824,51.51877897608239],"type":"Point"}
}