{
  "type": "Feature",
  "properties": {
    "iso:country":"GB",
    "wof:name":"RG6 7BB",
    "wof:placetype":"postalcode"
},
  "geometry": {"coordinates":[-0.93471669304868,51.44316670890803],"type":"Point"}
}