{
  "type": "Feature",
  "properties": {
    "iso:country":"GB",
    "wof:name":"LU6 1TW",
    "wof:placetype":"postalcode"
},
  "geometry": {"coordinates":[-0.54427280262027,51.88703449440908],"type":"Point"}
}