{
  "type": "Feature",
  "properties": {
    "iso:country":"GB",
    "wof:name":"SW6 5SH",
    "wof:placetype":"postalcode"
},
  "geometry": {"coordinates":[-0.20962185448199,51.47271587286483],"type":"Point"}
}