{
  "type": "Feature",
  "properties": {
    "iso:country": "GB",
    "wof:name": "SP4 7GG",
    "wof:placetype": "postalcode"
  },
  "geometry": {"coordinates":[-1.764172,51.160277],"type":"Point"}
}
