{
  "type": "Feature",
  "properties": {
    "iso:country":"GB",
    "wof:name":"SP4 7GG",
    "wof:placetype":"postalcode"
},
  "geometry": {"coordinates":[-1.76391180748445,51.16038946267382],"type":"Point"}
}