{
  "type": "Feature",
  "properties": {
    "date:inception_lower":"2015-05-01",
    "date:inception_upper":"2015-05-31",
    "iso:country":"GB",
    "wof:name":"GL50 4EE",
    "wof:placetype":"postalcode"
},
  "geometry": {"coordinates":[-2.08096,51.909762],"type":"Point"}
}