{
  "type": "Feature",
  "properties": {
    "iso:country":"GB",
    "wof:name":"GL50 4EE",
    "wof:placetype":"postalcode"
},
  "geometry": {"coordinates":[-2.0809675543597,51.90979934692905],"type":"Point"}
}