{
  "type": "Feature",
  "properties": {
    "iso:country":"GB",
    "wof:name":"S41 0BW",
    "wof:placetype":"postalcode"
},
  "geometry": {"coordinates":[-1.40148903336489,53.23303876199012],"type":"Point"}
}