{
  "type": "Feature",
  "properties": {
    "date:inception_lower": "1983-07-01",
    "date:inception_upper": "1983-07-01",
    "iso:country": "GB",
    "wof:name": "ME1 3SL",
    "wof:placetype": "postalcode"
  },
  "geometry": {"coordinates":[0.478542,51.332011],"type":"Point"}
}
