{
  "type": "Feature",
  "properties": {
    "date:inception_lower": "1980-01-01",
    "date:inception_upper": "1980-01-01",
    "iso:country": "GB",
    "wof:name": "GL3 2PR",
    "wof:placetype": "postalcode"
  },
  "geometry": {"coordinates":[-2.160207,51.880947],"type":"Point"}
}
