{
  "type": "Feature",
  "properties": {
    "iso:country":"GB",
    "wof:name":"GL3 2PR",
    "wof:placetype":"postalcode"
},
  "geometry": {"coordinates":[-2.16020718379786,51.88094722769146],"type":"Point"}
}