{
  "type": "Feature",
  "properties": {
    "iso:country":"GB",
    "wof:name":"SE8 4AR",
    "wof:placetype":"postalcode"
},
  "geometry": {"coordinates":[-0.02709756547396,51.47636028892803],"type":"Point"}
}