{
  "type": "Feature",
  "properties": {
    "date:inception_lower": "1980-01-01",
    "date:inception_upper": "1980-01-01",
    "iso:country": "GB",
    "wof:name": "SS8 9YG",
    "wof:placetype": "postalcode"
  },
  "geometry": {"coordinates":[0.587631,51.52867],"type":"Point"}
}
