{
  "type": "Feature",
  "properties": {
    "iso:country":"GB",
    "wof:name":"SE4 1QD",
    "wof:placetype":"postalcode"
},
  "geometry": {"coordinates":[-0.02382765403705,51.46605354089624],"type":"Point"}
}