{
  "type": "Feature",
  "properties": {
    "iso:country": "GB",
    "wof:name": "GL50 2LY",
    "wof:placetype": "postalcode"
  },
  "geometry": {"coordinates":[-2.09438,51.88644],"type":"Point"}
}
