{
  "type": "Feature",
  "properties": {
    "iso:country":"GB",
    "wof:name":"PH1 4HT",
    "wof:placetype":"postalcode"
},
  "geometry": {"coordinates":[-3.53913093391443,56.53163437826848],"type":"Point"}
}