{
  "type": "Feature",
  "properties": {
    "iso:country":"GB",
    "wof:name":"IV30 4GJ",
    "wof:placetype":"postalcode"
},
  "geometry": {"coordinates":[-3.30541339248591,57.66056662019154],"type":"Point"}
}