{
  "type": "Feature",
  "properties": {
    "iso:country":"GB",
    "wof:name":"AB25 2UD",
    "wof:placetype":"postalcode"
},
  "geometry": {"coordinates":[-2.11116160280395,57.14929757532692],"type":"Point"}
}