{
  "type": "Feature",
  "properties": {
    "date:inception_lower": "2009-01-01",
    "date:inception_upper": "2009-01-01",
    "iso:country": "GB",
    "wof:name": "HR2 6GH",
    "wof:placetype": "postalcode"
  },
  "geometry": {"coordinates":[-2.716809,52.037022],"type":"Point"}
}
