{
  "type": "Feature",
  "properties": {
    "iso:country":"GB",
    "wof:name":"HR2 6GH",
    "wof:placetype":"postalcode"
},
  "geometry": {"coordinates":[-2.71680881071519,52.03702220477523],"type":"Point"}
}