{
  "type": "Feature",
  "properties": {
    "iso:country":"GB",
    "wof:name":"NG24 3FT",
    "wof:placetype":"postalcode"
},
  "geometry": {"coordinates":[-0.76474533365859,53.04506099068419],"type":"Point"}
}