{
  "type": "Feature",
  "properties": {
    "date:inception_lower": "2004-10-01",
    "date:inception_upper": "2004-10-01",
    "iso:country": "GB",
    "wof:name": "NG24 3FT",
    "wof:placetype": "postalcode"
  },
  "geometry": {"coordinates":[-0.764745,53.045061],"type":"Point"}
}
