{
  "type": "Feature",
  "properties": {
    "iso:country": "GB",
    "wof:name": "NG24 3FT",
    "wof:placetype": "postalcode"
  },
  "geometry": {"coordinates":[-0.764745,53.045061],"type":"Point"}
}
