{
  "type": "Feature",
  "properties": {
    "iso:country": "GB",
    "wof:name": "NR21 0PQ",
    "wof:placetype": "postalcode"
  },
  "geometry": {"coordinates":[0.926,52.888998],"type":"Point"}
}
