{
  "type": "Feature",
  "properties": {
    "iso:country":"GB",
    "wof:name":"UB8 1BB",
    "wof:placetype":"postalcode"
},
  "geometry": {"coordinates":[-0.47482883233237,51.5523140467913],"type":"Point"}
}