{
  "type": "Feature",
  "properties": {
    "date:inception_lower":"1980-01-01",
    "date:inception_upper":"1980-01-31",
    "iso:country":"GB",
    "wof:name":"UB8 1BB",
    "wof:placetype":"postalcode"
},
  "geometry": {"coordinates":[-0.474829,51.552314],"type":"Point"}
}