{
  "type": "Feature",
  "properties": {
    "iso:country":"GB",
    "wof:name":"YO7 3TY",
    "wof:placetype":"postalcode"
},
  "geometry": {"coordinates":[-1.32830378436766,54.22720706738532],"type":"Point"}
}