{
  "type": "Feature",
  "properties": {
    "date:inception_lower":"1995-12-01",
    "date:inception_upper":"1995-12-31",
    "iso:country":"GB",
    "wof:name":"YO7 3TY",
    "wof:placetype":"postalcode"
},
  "geometry": {"coordinates":[-1.328297,54.227211],"type":"Point"}
}