{
  "type": "Feature",
  "properties": {
    "date:inception_lower":"1998-06-01",
    "date:inception_upper":"1998-06-30",
    "iso:country":"GB",
    "wof:name":"NG16 1RS",
    "wof:placetype":"postalcode"
},
  "geometry": {"coordinates":[-1.231026,52.985262],"type":"Point"}
}