{
  "type": "Feature",
  "properties": {
    "iso:country": "GB",
    "wof:name": "NG16 1RS",
    "wof:placetype": "postalcode"
  },
  "geometry": {"coordinates":[-1.231026,52.985262],"type":"Point"}
}
