{
  "type": "Feature",
  "properties": {
    "iso:country":"GB",
    "wof:name":"SA31 2LG",
    "wof:placetype":"postalcode"
},
  "geometry": {"coordinates":[-4.28336801890823,51.84738009621568],"type":"Point"}
}