{
  "type": "Feature",
  "properties": {
    "iso:country":"GB",
    "wof:name":"DE15 9HN",
    "wof:placetype":"postalcode"
},
  "geometry": {"coordinates":[-1.61138875026436,52.79180047652591],"type":"Point"}
}