{
  "type": "Feature",
  "properties": {
    "iso:country": "GB",
    "wof:name": "SK10 4DX",
    "wof:placetype": "postalcode"
  },
  "geometry": {"coordinates":[-2.136683,53.304924],"type":"Point"}
}
