{
  "type": "Feature",
  "properties": {
    "iso:country":"GB",
    "wof:name":"TA8 1BS",
    "wof:placetype":"postalcode"
},
  "geometry": {"coordinates":[-2.99813928282631,51.235264195458],"type":"Point"}
}