{
  "type": "Feature",
  "properties": {
    "iso:country": "GB",
    "wof:name": "TA8 1BS",
    "wof:placetype": "postalcode"
  },
  "geometry": {"coordinates":[-2.998139,51.235264],"type":"Point"}
}
