{
  "type": "Feature",
  "properties": {
    "iso:country":"GB",
    "wof:name":"GL50 3EB",
    "wof:placetype":"postalcode"
},
  "geometry": {"coordinates":[-2.08043860488315,51.89855216592291],"type":"Point"}
}