{
  "type": "Feature",
  "properties": {
    "iso:country":"GB",
    "wof:name":"S26 7WA",
    "wof:placetype":"postalcode"
},
  "geometry": {"coordinates":[-1.25926267753018,53.32543756402069],"type":"Point"}
}