{
  "type": "Feature",
  "properties": {
    "iso:country": "GB",
    "wof:name": "S26 7WA",
    "wof:placetype": "postalcode"
  },
  "geometry": {"coordinates":[-1.259263,53.325438],"type":"Point"}
}
