{
  "type": "Feature",
  "properties": {
    "iso:country":"GB",
    "wof:name":"B37 7BT",
    "wof:placetype":"postalcode"
},
  "geometry": {"coordinates":[-1.74602098704517,52.46519835260877],"type":"Point"}
}