{
  "type": "Feature",
  "properties": {
    "date:inception_lower": "1980-01-01",
    "date:inception_upper": "1980-01-01",
    "iso:country": "GB",
    "wof:name": "B37 7BT",
    "wof:placetype": "postalcode"
  },
  "geometry": {"coordinates":[-1.746014,52.465204],"type":"Point"}
}
