{
  "type": "Feature",
  "properties": {
    "iso:country":"GB",
    "wof:name":"AL2 2FN",
    "wof:placetype":"postalcode"
},
  "geometry": {"coordinates":[-0.35206660822153,51.72096463329589],"type":"Point"}
}