{
  "type": "Feature",
  "properties": {
    "iso:country": "GB",
    "wof:name": "AL2 2FN",
    "wof:placetype": "postalcode"
  },
  "geometry": {"coordinates":[-0.352067,51.720965],"type":"Point"}
}
