{
  "type": "Feature",
  "properties": {
    "iso:country":"GB",
    "wof:name":"L12 7HW",
    "wof:placetype":"postalcode"
},
  "geometry": {"coordinates":[-2.92113579705084,53.43242214520281],"type":"Point"}
}