{
  "type": "Feature",
  "properties": {
    "date:inception_lower":"1993-01-01",
    "date:inception_upper":"1993-01-31",
    "iso:country":"GB",
    "wof:name":"GL17 9UR",
    "wof:placetype":"postalcode"
},
  "geometry": {"coordinates":[-2.553957,51.855512],"type":"Point"}
}