{
  "type": "Feature",
  "properties": {
    "iso:country":"GB",
    "wof:name":"M18 7BY",
    "wof:placetype":"postalcode"
},
  "geometry": {"coordinates":[-2.1801337082062,53.45959612522044],"type":"Point"}
}