{
  "type": "Feature",
  "properties": {
    "iso:country":"GB",
    "wof:name":"S36 6AE",
    "wof:placetype":"postalcode"
},
  "geometry": {"coordinates":[-1.63919384064585,53.52892986567025],"type":"Point"}
}