{
  "type": "Feature",
  "properties": {
    "date:inception_lower": "1980-01-01",
    "date:inception_upper": "1980-01-01",
    "iso:country": "GB",
    "wof:name": "ML4 1LW",
    "wof:placetype": "postalcode"
  },
  "geometry": {"coordinates":[-4.018766,55.827491],"type":"Point"}
}
