{
  "type": "Feature",
  "properties": {
    "iso:country": "GB",
    "wof:name": "ML4 1LW",
    "wof:placetype": "postalcode"
  },
  "geometry": {"coordinates":[-4.018766,55.827491],"type":"Point"}
}
