{
  "type": "Feature",
  "properties": {
    "iso:country": "GB",
    "wof:name": "LL12 8BA",
    "wof:placetype": "postalcode"
  },
  "geometry": {"coordinates":[-2.9888,53.068126],"type":"Point"}
}
