{
  "type": "Feature",
  "properties": {
    "iso:country": "GB",
    "wof:name": "DN39 6RQ",
    "wof:placetype": "postalcode"
  },
  "geometry": {"coordinates":[-0.364405,53.619564],"type":"Point"}
}
