{
  "type": "Feature",
  "properties": {
    "iso:country": "GB",
    "wof:name": "SK16 5JL",
    "wof:placetype": "postalcode"
  },
  "geometry": {"coordinates":[-2.069553,53.475424],"type":"Point"}
}
