{
  "type": "Feature",
  "properties": {
    "date:inception_lower": "1980-01-01",
    "date:inception_upper": "1980-01-01",
    "iso:country": "GB",
    "wof:name": "SK16 5JL",
    "wof:placetype": "postalcode"
  },
  "geometry": {"coordinates":[-2.069553,53.475424],"type":"Point"}
}
