{
  "type": "Feature",
  "properties": {
    "date:inception_lower": "1980-01-01",
    "date:inception_upper": "1980-01-01",
    "iso:country": "GB",
    "wof:name": "SL7 1UW",
    "wof:placetype": "postalcode"
  },
  "geometry": {"coordinates":[-0.758969,51.57531],"type":"Point"}
}
