{
  "type": "Feature",
  "properties": {
    "iso:country": "GB",
    "wof:name": "ME10 1LQ",
    "wof:placetype": "postalcode"
  },
  "geometry": {"coordinates":[0.719739,51.335479],"type":"Point"}
}
