{
  "type": "Feature",
  "properties": {
    "iso:country":"GB",
    "wof:name":"ME10 1LQ",
    "wof:placetype":"postalcode"
},
  "geometry": {"coordinates":[0.7197384753618,51.33547885784302],"type":"Point"}
}