{
  "type": "Feature",
  "properties": {
    "iso:country":"GB",
    "wof:name":"YO25 5JB",
    "wof:placetype":"postalcode"
},
  "geometry": {"coordinates":[-0.42758590647113,54.01244532000698],"type":"Point"}
}