{
  "type": "Feature",
  "properties": {
    "date:inception_lower": "1980-01-01",
    "date:inception_upper": "1980-01-01",
    "iso:country": "GB",
    "wof:name": "LE13 1QH",
    "wof:placetype": "postalcode"
  },
  "geometry": {"coordinates":[-0.876865,52.769422],"type":"Point"}
}
