{
  "type": "Feature",
  "properties": {
    "iso:country":"GB",
    "wof:name":"W7 3BW",
    "wof:placetype":"postalcode"
},
  "geometry": {"coordinates":[-0.34297124303583,51.5152224669395],"type":"Point"}
}