{
  "type": "Feature",
  "properties": {
    "iso:country":"GB",
    "wof:name":"SA70 8HU",
    "wof:placetype":"postalcode"
},
  "geometry": {"coordinates":[-4.70809179993867,51.67863979240636],"type":"Point"}
}