{
  "type": "Feature",
  "properties": {
    "date:inception_lower":"1980-01-01",
    "date:inception_upper":"1980-01-31",
    "iso:country":"GB",
    "wof:name":"SA70 8HU",
    "wof:placetype":"postalcode"
},
  "geometry": {"coordinates":[-4.708092,51.67864],"type":"Point"}
}