{
  "type": "Feature",
  "properties": {
    "date:inception_lower": "1980-01-01",
    "date:inception_upper": "1980-01-01",
    "iso:country": "GB",
    "wof:name": "NG14 6HU",
    "wof:placetype": "postalcode"
  },
  "geometry": {"coordinates":[-1.080605,53.040891],"type":"Point"}
}
