{
  "type": "Feature",
  "properties": {
    "iso:country": "GB",
    "wof:name": "SA61 1QL",
    "wof:placetype": "postalcode"
  },
  "geometry": {"coordinates":[-4.971903,51.798549],"type":"Point"}
}
