{
  "type": "Feature",
  "properties": {
    "iso:country":"GB",
    "wof:name":"SA61 1QL",
    "wof:placetype":"postalcode"
},
  "geometry": {"coordinates":[-4.97190271907454,51.79854857055429],"type":"Point"}
}