{
  "type": "Feature",
  "properties": {
    "date:inception_lower": "1996-12-01",
    "date:inception_upper": "1996-12-01",
    "iso:country": "GB",
    "wof:name": "CF62 4LF",
    "wof:placetype": "postalcode"
  },
  "geometry": {"coordinates":[-3.416248,51.405456],"type":"Point"}
}
