{
  "type": "Feature",
  "properties": {
    "iso:country":"GB",
    "wof:name":"CF62 4LF",
    "wof:placetype":"postalcode"
},
  "geometry": {"coordinates":[-3.41624797131282,51.40545584861702],"type":"Point"}
}