{
  "type": "Feature",
  "properties": {
    "date:inception_lower": "2005-03-01",
    "date:inception_upper": "2005-03-01",
    "iso:country": "GB",
    "wof:name": "DH9 0PN",
    "wof:placetype": "postalcode"
  },
  "geometry": {"coordinates":[-1.690968,54.873615],"type":"Point"}
}
