{
  "type": "Feature",
  "properties": {
    "iso:country":"GB",
    "wof:name":"DH9 0PN",
    "wof:placetype":"postalcode"
},
  "geometry": {"coordinates":[-1.69096767619539,54.87361529650744],"type":"Point"}
}