{
  "type": "Feature",
  "properties": {
    "iso:country":"GB",
    "wof:name":"CB9 9LG",
    "wof:placetype":"postalcode"
},
  "geometry": {"coordinates":[0.43271300577222,52.08423066916756],"type":"Point"}
}