{
  "type": "Feature",
  "properties": {
    "iso:country":"GB",
    "wof:name":"DD3 0HD",
    "wof:placetype":"postalcode"
},
  "geometry": {"coordinates":[-2.98193075508992,56.49171815734964],"type":"Point"}
}