{
  "type": "Feature",
  "properties": {
    "date:inception_lower": "1980-01-01",
    "date:inception_upper": "1980-01-01",
    "iso:country": "GB",
    "wof:name": "DD3 0HD",
    "wof:placetype": "postalcode"
  },
  "geometry": {"coordinates":[-2.981931,56.491718],"type":"Point"}
}
