{
  "type": "Feature",
  "properties": {
    "iso:country": "GB",
    "wof:name": "CF5 5TT",
    "wof:placetype": "postalcode"
  },
  "geometry": {"coordinates":[-3.268521,51.463259],"type":"Point"}
}
