{
  "type": "Feature",
  "properties": {
    "date:inception_lower":"2018-07-01",
    "date:inception_upper":"2018-07-31",
    "iso:country":"GB",
    "wof:name":"CF5 5TT",
    "wof:placetype":"postalcode"
},
  "geometry": {"coordinates":[-3.268521,51.463259],"type":"Point"}
}