{
  "type": "Feature",
  "properties": {
    "iso:country": "GB",
    "wof:name": "L14 9QB",
    "wof:placetype": "postalcode"
  },
  "geometry": {"coordinates":[-2.873865,53.423959],"type":"Point"}
}
