{
  "type": "Feature",
  "properties": {
    "date:inception_lower": "1980-01-01",
    "date:inception_upper": "1980-01-01",
    "iso:country": "GB",
    "wof:name": "L14 9QB",
    "wof:placetype": "postalcode"
  },
  "geometry": {"coordinates":[-2.873865,53.423959],"type":"Point"}
}
