{
  "type": "Feature",
  "properties": {
    "date:inception_lower": "1987-10-01",
    "date:inception_upper": "1987-10-01",
    "iso:country": "GB",
    "wof:name": "HG1 2HJ",
    "wof:placetype": "postalcode"
  },
  "geometry": {"coordinates":[-1.546042,53.999379],"type":"Point"}
}
