{
  "type": "Feature",
  "properties": {
    "iso:country":"GB",
    "wof:name":"CH5 4DG",
    "wof:placetype":"postalcode"
},
  "geometry": {"coordinates":[-3.0758937448193,53.22279620231059],"type":"Point"}
}