{
  "type": "Feature",
  "properties": {
    "iso:country": "GB",
    "wof:name": "CH5 4DG",
    "wof:placetype": "postalcode"
  },
  "geometry": {"coordinates":[-3.075894,53.222796],"type":"Point"}
}
