{
  "type": "Feature",
  "properties": {
    "iso:country":"GB",
    "wof:name":"WF10 3JA",
    "wof:placetype":"postalcode"
},
  "geometry": {"coordinates":[-1.31989997495715,53.71757374299111],"type":"Point"}
}