{
  "type": "Feature",
  "properties": {
    "date:inception_lower": "1980-01-01",
    "date:inception_upper": "1980-01-01",
    "iso:country": "GB",
    "wof:name": "WF10 3JA",
    "wof:placetype": "postalcode"
  },
  "geometry": {"coordinates":[-1.3199,53.717574],"type":"Point"}
}
