{
  "type": "Feature",
  "properties": {
    "date:inception_lower": "1980-01-01",
    "date:inception_upper": "1980-01-01",
    "iso:country": "GB",
    "wof:name": "GU14 7EB",
    "wof:placetype": "postalcode"
  },
  "geometry": {"coordinates":[-0.740102,51.287822],"type":"Point"}
}
