{
  "type": "Feature",
  "properties": {
    "iso:country": "GB",
    "wof:name": "TS25 2NA",
    "wof:placetype": "postalcode"
  },
  "geometry": {"coordinates":[-1.238905,54.653229],"type":"Point"}
}
