{
  "type": "Feature",
  "properties": {
    "date:inception_lower":"1980-01-01",
    "date:inception_upper":"1980-01-31",
    "iso:country":"GB",
    "wof:name":"TS25 2NA",
    "wof:placetype":"postalcode"
},
  "geometry": {"coordinates":[-1.238905,54.653229],"type":"Point"}
}