{
  "type": "Feature",
  "properties": {
    "iso:country":"GB",
    "wof:name":"TN2 5JY",
    "wof:placetype":"postalcode"
},
  "geometry": {"coordinates":[0.26128743749235,51.12129515550619],"type":"Point"}
}