{
  "type": "Feature",
  "properties": {
    "iso:country": "GB",
    "wof:name": "TN2 5JY",
    "wof:placetype": "postalcode"
  },
  "geometry": {"coordinates":[0.261287,51.121295],"type":"Point"}
}
