{
  "type": "Feature",
  "properties": {
    "date:inception_lower": "2005-01-01",
    "date:inception_upper": "2005-01-01",
    "iso:country": "GB",
    "wof:name": "TN2 5JY",
    "wof:placetype": "postalcode"
  },
  "geometry": {"coordinates":[0.261287,51.121295],"type":"Point"}
}
