{
  "type": "Feature",
  "properties": {
    "date:inception_lower": "2013-12-01",
    "date:inception_upper": "2013-12-01",
    "iso:country": "GB",
    "wof:name": "OL14 6BG",
    "wof:placetype": "postalcode"
  },
  "geometry": {"coordinates":[-2.098872,53.6946],"type":"Point"}
}
