{
  "type": "Feature",
  "properties": {
    "iso:country":"GB",
    "wof:name":"OL14 6BG",
    "wof:placetype":"postalcode"
},
  "geometry": {"coordinates":[-2.09887157927218,53.6946002042889],"type":"Point"}
}