{
  "type": "Feature",
  "properties": {
    "iso:country":"GB",
    "wof:name":"EH48 1TF",
    "wof:placetype":"postalcode"
},
  "geometry": {"coordinates":[-3.60507040815754,55.90299579124451],"type":"Point"}
}