{
  "type": "Feature",
  "properties": {
    "date:inception_lower": "2009-10-01",
    "date:inception_upper": "2009-10-01",
    "iso:country": "GB",
    "wof:name": "EH48 1TF",
    "wof:placetype": "postalcode"
  },
  "geometry": {"coordinates":[-3.60507,55.902996],"type":"Point"}
}
