{
  "type": "Feature",
  "properties": {
    "date:inception_lower": "1980-01-01",
    "date:inception_upper": "1980-01-01",
    "iso:country": "GB",
    "wof:name": "CM13 1LZ",
    "wof:placetype": "postalcode"
  },
  "geometry": {"coordinates":[0.35091,51.632959],"type":"Point"}
}
