{
  "type": "Feature",
  "properties": {
    "iso:country":"GB",
    "wof:name":"CM23 4FX",
    "wof:placetype":"postalcode"
},
  "geometry": {"coordinates":[0.13786130823595,51.85839858804263],"type":"Point"}
}