{
  "type": "Feature",
  "properties": {
    "iso:country":"GB",
    "wof:name":"M22 1TL",
    "wof:placetype":"postalcode"
},
  "geometry": {"coordinates":[-2.27061149892479,53.37314407520592],"type":"Point"}
}