{
  "type": "Feature",
  "properties": {
    "date:inception_lower": "1980-01-01",
    "date:inception_upper": "1980-01-01",
    "iso:country": "GB",
    "wof:name": "TA19 9PZ",
    "wof:placetype": "postalcode"
  },
  "geometry": {"coordinates":[-2.945034,50.940036],"type":"Point"}
}
