{
  "type": "Feature",
  "properties": {
    "date:inception_lower": "2001-06-01",
    "date:inception_upper": "2001-06-01",
    "iso:country": "GB",
    "wof:name": "SK17 9EE",
    "wof:placetype": "postalcode"
  },
  "geometry": {"coordinates":[-1.910424,53.25082],"type":"Point"}
}
