{
  "type": "Feature",
  "properties": {
    "iso:country": "GB",
    "wof:name": "SK17 9EE",
    "wof:placetype": "postalcode"
  },
  "geometry": {"coordinates":[-1.910319,53.250847],"type":"Point"}
}
