{
  "type": "Feature",
  "properties": {
    "iso:country":"GB",
    "wof:name":"YO31 9ES",
    "wof:placetype":"postalcode"
},
  "geometry": {"coordinates":[-1.06395748421572,53.98421007260653],"type":"Point"}
}