{
  "type": "Feature",
  "properties": {
    "iso:country":"GB",
    "wof:name":"B15 3QF",
    "wof:placetype":"postalcode"
},
  "geometry": {"coordinates":[-1.94865671385679,52.46792264751294],"type":"Point"}
}