{
  "type": "Feature",
  "properties": {
    "date:inception_lower":"2001-06-01",
    "date:inception_upper":"2001-06-30",
    "iso:country":"GB",
    "wof:name":"PE32 1PF",
    "wof:placetype":"postalcode"
},
  "geometry": {"coordinates":[0.560558,52.743391],"type":"Point"}
}