{
  "type": "Feature",
  "properties": {
    "iso:country":"GB",
    "wof:name":"PE32 1PF",
    "wof:placetype":"postalcode"
},
  "geometry": {"coordinates":[0.56054186987402,52.74336829582592],"type":"Point"}
}