{
  "type": "Feature",
  "properties": {
    "date:inception_lower": "1980-01-01",
    "date:inception_upper": "1980-01-01",
    "iso:country": "GB",
    "wof:name": "UB1 3JX",
    "wof:placetype": "postalcode"
  },
  "geometry": {"coordinates":[-0.360677,51.518619],"type":"Point"}
}
