{
  "type": "Feature",
  "properties": {
    "iso:country":"GB",
    "wof:name":"DN41 8HD",
    "wof:placetype":"postalcode"
},
  "geometry": {"coordinates":[-0.23995671929633,53.57045029493367],"type":"Point"}
}