{
  "type": "Feature",
  "properties": {
    "date:inception_lower": "1997-06-01",
    "date:inception_upper": "1997-06-01",
    "iso:country": "GB",
    "wof:name": "DN41 8HD",
    "wof:placetype": "postalcode"
  },
  "geometry": {"coordinates":[-0.239957,53.57045],"type":"Point"}
}
