{
  "type": "Feature",
  "properties": {
    "iso:country": "GB",
    "wof:name": "CV35 0TS",
    "wof:placetype": "postalcode"
  },
  "geometry": {"coordinates":[-1.510962,52.091469],"type":"Point"}
}
