{
  "type": "Feature",
  "properties": {
    "iso:country":"GB",
    "wof:name":"BB3 1JX",
    "wof:placetype":"postalcode"
},
  "geometry": {"coordinates":[-2.48639570919809,53.6975356195266],"type":"Point"}
}