{
  "type": "Feature",
  "properties": {
    "date:inception_lower":"1980-01-01",
    "date:inception_upper":"1980-01-31",
    "iso:country":"GB",
    "wof:name":"BB3 1JX",
    "wof:placetype":"postalcode"
},
  "geometry": {"coordinates":[-2.486348,53.697525],"type":"Point"}
}