{
  "type": "Feature",
  "properties": {
    "iso:country": "GB",
    "wof:name": "LS19 6ET",
    "wof:placetype": "postalcode"
  },
  "geometry": {"coordinates":[-1.678709,53.850648],"type":"Point"}
}
