{
  "type": "Feature",
  "properties": {
    "date:inception_lower": "1995-07-01",
    "date:inception_upper": "1995-07-01",
    "iso:country": "GB",
    "wof:name": "CF83 4AY",
    "wof:placetype": "postalcode"
  },
  "geometry": {"coordinates":[-3.265038,51.595199],"type":"Point"}
}
