{
  "type": "Feature",
  "properties": {
    "iso:country": "GB",
    "wof:name": "WD18 7PL",
    "wof:placetype": "postalcode"
  },
  "geometry": {"coordinates":[-0.419768,51.650396],"type":"Point"}
}
