{
  "type": "Feature",
  "properties": {
    "iso:country":"GB",
    "wof:name":"NG18 4AF",
    "wof:placetype":"postalcode"
},
  "geometry": {"coordinates":[-1.19778675542587,53.13351020044649],"type":"Point"}
}