{
  "type": "Feature",
  "properties": {
    "date:inception_lower": "2002-06-01",
    "date:inception_upper": "2002-06-01",
    "iso:country": "GB",
    "wof:name": "NG31 7DE",
    "wof:placetype": "postalcode"
  },
  "geometry": {"coordinates":[-0.674031,52.910423],"type":"Point"}
}
