{
  "type": "Feature",
  "properties": {
    "date:inception_lower": "1987-04-01",
    "date:inception_upper": "1987-04-01",
    "iso:country": "GB",
    "wof:name": "PA15 3EF",
    "wof:placetype": "postalcode"
  },
  "geometry": {"coordinates":[-4.73868,55.931738],"type":"Point"}
}
