{
  "type": "Feature",
  "properties": {
    "iso:country":"GB",
    "wof:name":"W6 7DT",
    "wof:placetype":"postalcode"
},
  "geometry": {"coordinates":[-0.22020946958137,51.4944319831411],"type":"Point"}
}