{
  "type": "Feature",
  "properties": {
    "iso:country": "GB",
    "wof:name": "L33 0YD",
    "wof:placetype": "postalcode"
  },
  "geometry": {"coordinates":[-2.880431,53.483866],"type":"Point"}
}
