{
  "type": "Feature",
  "properties": {
    "iso:country":"GB",
    "wof:name":"B75 6RD",
    "wof:placetype":"postalcode"
},
  "geometry": {"coordinates":[-1.81775537286138,52.58457249496274],"type":"Point"}
}