{
  "type": "Feature",
  "properties": {
    "date:inception_lower": "2021-11-01",
    "date:inception_upper": "2021-11-01",
    "iso:country": "GB",
    "wof:name": "NN15 4AP",
    "wof:placetype": "postalcode"
  },
  "geometry": {"coordinates":[-0.680447,52.393557],"type":"Point"}
}
