{
  "type": "Feature",
  "properties": {
    "date:inception_lower": "2015-11-01",
    "date:inception_upper": "2015-11-01",
    "iso:country": "GB",
    "wof:name": "CM14 4SH",
    "wof:placetype": "postalcode"
  },
  "geometry": {"coordinates":[0.301371,51.616905],"type":"Point"}
}
