{
  "type": "Feature",
  "properties": {
    "iso:country": "GB",
    "wof:name": "KA22 8PU",
    "wof:placetype": "postalcode"
  },
  "geometry": {"coordinates":[-4.808277,55.647761],"type":"Point"}
}
