{
  "type": "Feature",
  "properties": {
    "iso:country":"GB",
    "wof:name":"KA22 8PU",
    "wof:placetype":"postalcode"
},
  "geometry": {"coordinates":[-4.80827747098386,55.64776114485527],"type":"Point"}
}