{
  "type": "Feature",
  "properties": {
    "date:inception_lower": "1996-06-01",
    "date:inception_upper": "1996-06-01",
    "iso:country": "GB",
    "wof:name": "KA22 8PU",
    "wof:placetype": "postalcode"
  },
  "geometry": {"coordinates":[-4.808277,55.647761],"type":"Point"}
}
