{
  "type": "Feature",
  "properties": {
    "iso:country":"GB",
    "wof:name":"SK14 2JU",
    "wof:placetype":"postalcode"
},
  "geometry": {"coordinates":[-2.06997315886473,53.45610727965573],"type":"Point"}
}