{
  "type": "Feature",
  "properties": {
    "iso:country": "GB",
    "wof:name": "CM3 4HT",
    "wof:placetype": "postalcode"
  },
  "geometry": {"coordinates":[0.581667,51.691393],"type":"Point"}
}
