{
  "type": "Feature",
  "properties": {
    "iso:country":"GB",
    "wof:name":"CM3 4HT",
    "wof:placetype":"postalcode"
},
  "geometry": {"coordinates":[0.58166693366291,51.6913927409324],"type":"Point"}
}