{
  "type": "Feature",
  "properties": {
    "iso:country":"GB",
    "wof:name":"CV23 0LJ",
    "wof:placetype":"postalcode"
},
  "geometry": {"coordinates":[-1.35704753617323,52.41476417254907],"type":"Point"}
}