{
  "type": "Feature",
  "properties": {
    "iso:country":"GB",
    "wof:name":"B30 3DJ",
    "wof:placetype":"postalcode"
},
  "geometry": {"coordinates":[-1.92892607803966,52.41644463329586],"type":"Point"}
}