{
  "type": "Feature",
  "properties": {
    "date:inception_lower": "2000-06-01",
    "date:inception_upper": "2000-06-01",
    "iso:country": "GB",
    "wof:name": "SN2 7JN",
    "wof:placetype": "postalcode"
  },
  "geometry": {"coordinates":[-1.764105,51.584267],"type":"Point"}
}
