{
  "type": "Feature",
  "properties": {
    "iso:country":"GB",
    "wof:name":"E7 0NH",
    "wof:placetype":"postalcode"
},
  "geometry": {"coordinates":[0.02913856804397,51.55066049740785],"type":"Point"}
}