{
  "type": "Feature",
  "properties": {
    "date:inception_lower": "1980-01-01",
    "date:inception_upper": "1980-01-01",
    "iso:country": "GB",
    "wof:name": "E7 0NH",
    "wof:placetype": "postalcode"
  },
  "geometry": {"coordinates":[0.029139,51.55066],"type":"Point"}
}
