{
  "type": "Feature",
  "properties": {
    "date:inception_lower": "1980-01-01",
    "date:inception_upper": "1980-01-01",
    "iso:country": "GB",
    "wof:name": "BB10 4TP",
    "wof:placetype": "postalcode"
  },
  "geometry": {"coordinates":[-2.20581,53.766455],"type":"Point"}
}
