{
  "type": "Feature",
  "properties": {
    "date:inception_lower": "2004-07-01",
    "date:inception_upper": "2004-07-01",
    "iso:country": "GB",
    "wof:name": "WV13 2LD",
    "wof:placetype": "postalcode"
  },
  "geometry": {"coordinates":[-2.052446,52.577104],"type":"Point"}
}
