{
  "type": "Feature",
  "properties": {
    "iso:country":"GB",
    "wof:name":"LL19 7SW",
    "wof:placetype":"postalcode"
},
  "geometry": {"coordinates":[-3.40937908266266,53.3372425549092],"type":"Point"}
}