{
  "type": "Feature",
  "properties": {
    "date:inception_lower":"1980-01-01",
    "date:inception_upper":"1980-01-31",
    "iso:country":"GB",
    "wof:name":"LL19 7SW",
    "wof:placetype":"postalcode"
},
  "geometry": {"coordinates":[-3.409379,53.337243],"type":"Point"}
}