{
  "type": "Feature",
  "properties": {
    "iso:country":"GB",
    "wof:name":"TA6 3RH",
    "wof:placetype":"postalcode"
},
  "geometry": {"coordinates":[-3.00951201293772,51.12654918538014],"type":"Point"}
}