{
  "type": "Feature",
  "properties": {
    "date:inception_lower": "1980-01-01",
    "date:inception_upper": "1980-01-01",
    "iso:country": "GB",
    "wof:name": "TA6 3RH",
    "wof:placetype": "postalcode"
  },
  "geometry": {"coordinates":[-3.009577,51.12658],"type":"Point"}
}
