{
  "type": "Feature",
  "properties": {
    "iso:country":"GB",
    "wof:name":"SW9 9NL",
    "wof:placetype":"postalcode"
},
  "geometry": {"coordinates":[-0.12814992528488,51.46430340609324],"type":"Point"}
}