{
  "type": "Feature",
  "properties": {
    "iso:country": "GB",
    "wof:name": "SW9 9NL",
    "wof:placetype": "postalcode"
  },
  "geometry": {"coordinates":[-0.12815,51.464303],"type":"Point"}
}
