{
  "type": "Feature",
  "properties": {
    "date:inception_lower": "1996-12-01",
    "date:inception_upper": "1996-12-01",
    "iso:country": "GB",
    "wof:name": "HD1 6NA",
    "wof:placetype": "postalcode"
  },
  "geometry": {"coordinates":[-1.774245,53.652901],"type":"Point"}
}
