{
  "type": "Feature",
  "properties": {
    "iso:country":"GB",
    "wof:name":"HA2 7HA",
    "wof:placetype":"postalcode"
},
  "geometry": {"coordinates":[-0.36987821283195,51.57658466646069],"type":"Point"}
}