{
  "type": "Feature",
  "properties": {
    "iso:country":"GB",
    "wof:name":"E14 6PF",
    "wof:placetype":"postalcode"
},
  "geometry": {"coordinates":[-0.01648841664435,51.51807816362595],"type":"Point"}
}