{
  "type": "Feature",
  "properties": {
    "date:inception_lower": "1980-01-01",
    "date:inception_upper": "1980-01-01",
    "iso:country": "GB",
    "wof:name": "N17 0BL",
    "wof:placetype": "postalcode"
  },
  "geometry": {"coordinates":[-0.063305,51.600926],"type":"Point"}
}
