{
  "type": "Feature",
  "properties": {
    "iso:country":"GB",
    "wof:name":"HR3 6LW",
    "wof:placetype":"postalcode"
},
  "geometry": {"coordinates":[-3.01739915499451,52.16382869905996],"type":"Point"}
}