{
  "type": "Feature",
  "properties": {
    "iso:country": "GB",
    "wof:name": "CV35 8XQ",
    "wof:placetype": "postalcode"
  },
  "geometry": {"coordinates":[-1.675155,52.287919],"type":"Point"}
}
