{
  "type": "Feature",
  "properties": {
    "iso:country":"GB",
    "wof:name":"IP13 0RA",
    "wof:placetype":"postalcode"
},
  "geometry": {"coordinates":[1.36330000401104,52.1534808204212],"type":"Point"}
}