{
  "type": "Feature",
  "properties": {
    "date:inception_lower":"1980-01-01",
    "date:inception_upper":"1980-01-31",
    "iso:country":"GB",
    "wof:name":"B27 7LH",
    "wof:placetype":"postalcode"
},
  "geometry": {"coordinates":[-1.820947,52.431047],"type":"Point"}
}