{
  "type": "Feature",
  "properties": {
    "iso:country":"GB",
    "wof:name":"B27 7LH",
    "wof:placetype":"postalcode"
},
  "geometry": {"coordinates":[-1.82094750138202,52.43104739072768],"type":"Point"}
}