{
  "type": "Feature",
  "properties": {
    "iso:country":"GB",
    "wof:name":"BD16 1JG",
    "wof:placetype":"postalcode"
},
  "geometry": {"coordinates":[-1.86596099228657,53.83854545802879],"type":"Point"}
}