{
  "type": "Feature",
  "properties": {
    "iso:country":"GB",
    "wof:name":"TQ12 3BU",
    "wof:placetype":"postalcode"
},
  "geometry": {"coordinates":[-3.59156983669066,50.54743234248657],"type":"Point"}
}