{
  "type": "Feature",
  "properties": {
    "iso:country":"GB",
    "wof:name":"WV1 2LS",
    "wof:placetype":"postalcode"
},
  "geometry": {"coordinates":[-2.09635371768159,52.58692933625733],"type":"Point"}
}