{
  "type": "Feature",
  "properties": {
    "iso:country": "GB",
    "wof:name": "WR12 7DT",
    "wof:placetype": "postalcode"
  },
  "geometry": {"coordinates":[-1.859248,52.03627],"type":"Point"}
}
