{
  "type": "Feature",
  "properties": {
    "iso:country": "GB",
    "wof:name": "NG16 5LQ",
    "wof:placetype": "postalcode"
  },
  "geometry": {"coordinates":[-1.338063,53.062316],"type":"Point"}
}
