{
  "type": "Feature",
  "properties": {
    "date:inception_lower":"1980-01-01",
    "date:inception_upper":"1980-01-31",
    "iso:country":"GB",
    "wof:name":"NG16 5LQ",
    "wof:placetype":"postalcode"
},
  "geometry": {"coordinates":[-1.338063,53.062316],"type":"Point"}
}