{
  "type": "Feature",
  "properties": {
    "iso:country":"GB",
    "wof:name":"RG23 8JL",
    "wof:placetype":"postalcode"
},
  "geometry": {"coordinates":[-1.12636142366352,51.27015508270082],"type":"Point"}
}