{
  "type": "Feature",
  "properties": {
    "date:inception_lower": "1980-01-01",
    "date:inception_upper": "1980-01-01",
    "iso:country": "GB",
    "wof:name": "RG23 8JL",
    "wof:placetype": "postalcode"
  },
  "geometry": {"coordinates":[-1.126361,51.270155],"type":"Point"}
}
