{
  "type": "Feature",
  "properties": {
    "iso:country": "GB",
    "wof:name": "BH24 1TX",
    "wof:placetype": "postalcode"
  },
  "geometry": {"coordinates":[-1.768918,50.854465],"type":"Point"}
}
