{
  "type": "Feature",
  "properties": {
    "iso:country":"GB",
    "wof:name":"TF1 5RQ",
    "wof:placetype":"postalcode"
},
  "geometry": {"coordinates":[-2.47811570834297,52.70436216190907],"type":"Point"}
}