{
  "type": "Feature",
  "properties": {
    "date:inception_lower": "1980-01-01",
    "date:inception_upper": "1980-01-01",
    "iso:country": "GB",
    "wof:name": "EH51 0BY",
    "wof:placetype": "postalcode"
  },
  "geometry": {"coordinates":[-3.606846,56.015101],"type":"Point"}
}
