{
  "type": "Feature",
  "properties": {
    "iso:country":"GB",
    "wof:name":"HX5 0SN",
    "wof:placetype":"postalcode"
},
  "geometry": {"coordinates":[-1.845009194245,53.68887878092409],"type":"Point"}
}