{
  "type": "Feature",
  "properties": {
    "iso:country":"GB",
    "wof:name":"BD23 1XP",
    "wof:placetype":"postalcode"
},
  "geometry": {"coordinates":[-2.02588670551866,53.95771457665517],"type":"Point"}
}