{
  "type": "Feature",
  "properties": {
    "date:inception_lower": "2008-12-01",
    "date:inception_upper": "2008-12-01",
    "iso:country": "GB",
    "wof:name": "WD17 1BJ",
    "wof:placetype": "postalcode"
  },
  "geometry": {"coordinates":[-0.398015,51.657304],"type":"Point"}
}
