{
  "type": "Feature",
  "properties": {
    "date:inception_lower":"1991-01-01",
    "date:inception_upper":"1991-01-31",
    "iso:country":"GB",
    "wof:name":"B1 2EA",
    "wof:placetype":"postalcode"
},
  "geometry": {"coordinates":[-1.910789,52.478868],"type":"Point"}
}