{
  "type": "Feature",
  "properties": {
    "iso:country":"GB",
    "wof:name":"RG22 5RL",
    "wof:placetype":"postalcode"
},
  "geometry": {"coordinates":[-1.13805796910323,51.24258217954241],"type":"Point"}
}