{
  "type": "Feature",
  "properties": {
    "iso:country":"GB",
    "wof:name":"B33 0DD",
    "wof:placetype":"postalcode"
},
  "geometry": {"coordinates":[-1.76174820394368,52.48025330843031],"type":"Point"}
}