{
  "type": "Feature",
  "properties": {
    "iso:country":"GB",
    "wof:name":"DT7 3AG",
    "wof:placetype":"postalcode"
},
  "geometry": {"coordinates":[-2.93697583303282,50.72793575054696],"type":"Point"}
}