{
  "type": "Feature",
  "properties": {
    "date:inception_lower": "1980-01-01",
    "date:inception_upper": "1980-01-01",
    "iso:country": "GB",
    "wof:name": "DT7 3AG",
    "wof:placetype": "postalcode"
  },
  "geometry": {"coordinates":[-2.936976,50.727936],"type":"Point"}
}
