{
  "type": "Feature",
  "properties": {
    "iso:country": "GB",
    "wof:name": "LE5 6FH",
    "wof:placetype": "postalcode"
  },
  "geometry": {"coordinates":[-1.074365,52.620258],"type":"Point"}
}
