{
  "type": "Feature",
  "properties": {
    "iso:country":"GB",
    "wof:name":"LE5 6FH",
    "wof:placetype":"postalcode"
},
  "geometry": {"coordinates":[-1.07433056558371,52.62019454754275],"type":"Point"}
}