{
  "type": "Feature",
  "properties": {
    "date:inception_lower": "1980-01-01",
    "date:inception_upper": "1980-01-01",
    "iso:country": "GB",
    "wof:name": "EC4R 2RP",
    "wof:placetype": "postalcode"
  },
  "geometry": {"coordinates":[-0.092049,51.511492],"type":"Point"}
}
