{
  "type": "Feature",
  "properties": {
    "iso:country":"GB",
    "wof:name":"LS16 6ET",
    "wof:placetype":"postalcode"
},
  "geometry": {"coordinates":[-1.60432044711999,53.84042220169814],"type":"Point"}
}