{
  "type": "Feature",
  "properties": {
    "date:inception_lower": "1980-10-01",
    "date:inception_upper": "1980-10-01",
    "iso:country": "GB",
    "wof:name": "G66 3EZ",
    "wof:placetype": "postalcode"
  },
  "geometry": {"coordinates":[-4.126204,55.932964],"type":"Point"}
}
