{
  "type": "Feature",
  "properties": {
    "iso:country":"GB",
    "wof:name":"G66 3EZ",
    "wof:placetype":"postalcode"
},
  "geometry": {"coordinates":[-4.12655491878787,55.93302585647226],"type":"Point"}
}