{
  "type": "Feature",
  "properties": {
    "iso:country": "GB",
    "wof:name": "SE15 5PD",
    "wof:placetype": "postalcode"
  },
  "geometry": {"coordinates":[-0.077211,51.471923],"type":"Point"}
}
