{
  "type": "Feature",
  "properties": {
    "iso:country":"GB",
    "wof:name":"NE61 9ST",
    "wof:placetype":"postalcode"
},
  "geometry": {"coordinates":[-1.68864371884972,55.15668293008198],"type":"Point"}
}