{
  "type": "Feature",
  "properties": {
    "iso:country": "GB",
    "wof:name": "M45 8PF",
    "wof:placetype": "postalcode"
  },
  "geometry": {"coordinates":[-2.288001,53.557628],"type":"Point"}
}
