{
  "type": "Feature",
  "properties": {
    "iso:country":"GB",
    "wof:name":"M45 8PF",
    "wof:placetype":"postalcode"
},
  "geometry": {"coordinates":[-2.28800116705906,53.55762808108227],"type":"Point"}
}