{
  "type": "Feature",
  "properties": {
    "iso:country": "GB",
    "wof:name": "BS24 7HS",
    "wof:placetype": "postalcode"
  },
  "geometry": {"coordinates":[-2.926291,51.346859],"type":"Point"}
}
