{
  "type": "Feature",
  "properties": {
    "iso:country": "GB",
    "wof:name": "BS24 7HS",
    "wof:placetype": "postalcode"
  },
  "geometry": {"coordinates":[-2.9263,51.346844],"type":"Point"}
}
