{
  "type": "Feature",
  "properties": {
    "iso:country":"GB",
    "wof:name":"BS24 7HS",
    "wof:placetype":"postalcode"
},
  "geometry": {"coordinates":[-2.92629990765269,51.34684372699434],"type":"Point"}
}