{
  "type": "Feature",
  "properties": {
    "date:inception_lower": "2003-04-01",
    "date:inception_upper": "2003-04-01",
    "iso:country": "GB",
    "wof:name": "BS24 7HS",
    "wof:placetype": "postalcode"
  },
  "geometry": {"coordinates":[-2.926291,51.346859],"type":"Point"}
}
