{
  "type": "Feature",
  "properties": {
    "iso:country":"GB",
    "wof:name":"EX19 8QH",
    "wof:placetype":"postalcode"
},
  "geometry": {"coordinates":[-4.03231951926489,50.89152718831293],"type":"Point"}
}