{
  "type": "Feature",
  "properties": {
    "date:inception_lower": "1980-01-01",
    "date:inception_upper": "1980-01-01",
    "iso:country": "GB",
    "wof:name": "EX19 8QH",
    "wof:placetype": "postalcode"
  },
  "geometry": {"coordinates":[-4.032441,50.891501],"type":"Point"}
}
