{
  "type": "Feature",
  "properties": {
    "iso:country":"GB",
    "wof:name":"BR4 9HR",
    "wof:placetype":"postalcode"
},
  "geometry": {"coordinates":[0.00035617492947,51.36944737189838],"type":"Point"}
}