{
  "type": "Feature",
  "properties": {
    "iso:country": "GB",
    "wof:name": "HR9 7JD",
    "wof:placetype": "postalcode"
  },
  "geometry": {"coordinates":[-2.580172,51.936133],"type":"Point"}
}
