{
  "type": "Feature",
  "properties": {
    "iso:country":"GB",
    "wof:name":"HR9 7JD",
    "wof:placetype":"postalcode"
},
  "geometry": {"coordinates":[-2.58017222777313,51.93613321022121],"type":"Point"}
}