{
  "type": "Feature",
  "properties": {
    "iso:country":"GB",
    "wof:name":"DL17 9EB",
    "wof:placetype":"postalcode"
},
  "geometry": {"coordinates":[-1.48229342560522,54.68456437034105],"type":"Point"}
}