{
  "type": "Feature",
  "properties": {
    "date:inception_lower":"1980-01-01",
    "date:inception_upper":"1980-01-31",
    "iso:country":"GB",
    "wof:name":"DL17 9EB",
    "wof:placetype":"postalcode"
},
  "geometry": {"coordinates":[-1.484849,54.684504],"type":"Point"}
}