{
  "type": "Feature",
  "properties": {
    "iso:country":"GB",
    "wof:name":"YO30 7DH",
    "wof:placetype":"postalcode"
},
  "geometry": {"coordinates":[-1.09106244959555,53.96432981169691],"type":"Point"}
}