{
  "type": "Feature",
  "properties": {
    "iso:country": "GB",
    "wof:name": "HP22 4SJ",
    "wof:placetype": "postalcode"
  },
  "geometry": {"coordinates":[-0.832949,51.876655],"type":"Point"}
}
