{
  "type": "Feature",
  "properties": {
    "date:inception_lower": "1996-06-01",
    "date:inception_upper": "1996-06-01",
    "iso:country": "GB",
    "wof:name": "HP22 4SJ",
    "wof:placetype": "postalcode"
  },
  "geometry": {"coordinates":[-0.832949,51.876655],"type":"Point"}
}
