{
  "type": "Feature",
  "properties": {
    "iso:country":"GB",
    "wof:name":"HP22 4SJ",
    "wof:placetype":"postalcode"
},
  "geometry": {"coordinates":[-0.83299834855207,51.87672875128089],"type":"Point"}
}