{
  "type": "Feature",
  "properties": {
    "date:inception_lower":"1981-06-01",
    "date:inception_upper":"1981-06-30",
    "iso:country":"GB",
    "wof:name":"NE6 2FG",
    "wof:placetype":"postalcode"
},
  "geometry": {"coordinates":[-1.576136,54.971463],"type":"Point"}
}