{
  "type": "Feature",
  "properties": {
    "iso:country": "GB",
    "wof:name": "NE6 2FG",
    "wof:placetype": "postalcode"
  },
  "geometry": {"coordinates":[-1.576136,54.971463],"type":"Point"}
}
