{
  "type": "Feature",
  "properties": {
    "iso:country":"GB",
    "wof:name":"YO16 6QU",
    "wof:placetype":"postalcode"
},
  "geometry": {"coordinates":[-0.18434455815264,54.09299239983286],"type":"Point"}
}