{
  "type": "Feature",
  "properties": {
    "iso:country": "GB",
    "wof:name": "YO16 6QU",
    "wof:placetype": "postalcode"
  },
  "geometry": {"coordinates":[-0.184345,54.092992],"type":"Point"}
}
