{
  "type": "Feature",
  "properties": {
    "iso:country":"GB",
    "wof:name":"DE65 6LQ",
    "wof:placetype":"postalcode"
},
  "geometry": {"coordinates":[-1.60009306487557,52.88675468309041],"type":"Point"}
}