{
  "type": "Feature",
  "properties": {
    "iso:country": "GB",
    "wof:name": "DE65 6LQ",
    "wof:placetype": "postalcode"
  },
  "geometry": {"coordinates":[-1.600093,52.886755],"type":"Point"}
}
