{
  "type": "Feature",
  "properties": {
    "iso:country":"GB",
    "wof:name":"L23 6TJ",
    "wof:placetype":"postalcode"
},
  "geometry": {"coordinates":[-3.05348962108061,53.49275799742114],"type":"Point"}
}