{
  "type": "Feature",
  "properties": {
    "iso:country":"GB",
    "wof:name":"LL53 6UR",
    "wof:placetype":"postalcode"
},
  "geometry": {"coordinates":[-4.38422444300936,52.92560604789472],"type":"Point"}
}