{
  "type": "Feature",
  "properties": {
    "iso:country":"GB",
    "wof:name":"TN29 0HA",
    "wof:placetype":"postalcode"
},
  "geometry": {"coordinates":[0.9699557656122,51.00575573161115],"type":"Point"}
}