{
  "type": "Feature",
  "properties": {
    "date:inception_lower":"1980-01-01",
    "date:inception_upper":"1980-01-31",
    "iso:country":"GB",
    "wof:name":"TR19 6UF",
    "wof:placetype":"postalcode"
},
  "geometry": {"coordinates":[-5.549994,50.090209],"type":"Point"}
}