{
  "type": "Feature",
  "properties": {
    "iso:country":"GB",
    "wof:name":"DN32 7QX",
    "wof:placetype":"postalcode"
},
  "geometry": {"coordinates":[-0.05848547440446,53.57044707366137],"type":"Point"}
}