{
  "type": "Feature",
  "properties": {
    "iso:country":"GB",
    "wof:name":"CF24 4JU",
    "wof:placetype":"postalcode"
},
  "geometry": {"coordinates":[-3.18189129423909,51.49375665030929],"type":"Point"}
}