{
  "type": "Feature",
  "properties": {
    "date:inception_lower": "1999-06-01",
    "date:inception_upper": "1999-06-01",
    "iso:country": "GB",
    "wof:name": "CF24 4JU",
    "wof:placetype": "postalcode"
  },
  "geometry": {"coordinates":[-3.181891,51.493757],"type":"Point"}
}
