{
  "type": "Feature",
  "properties": {
    "date:inception_lower": "2016-10-01",
    "date:inception_upper": "2016-10-01",
    "iso:country": "GB",
    "wof:name": "CH1 9DB",
    "wof:placetype": "postalcode"
  },
  "geometry": {"coordinates":[-2.884632,53.197786],"type":"Point"}
}
