{
  "type": "Feature",
  "properties": {
    "iso:country":"GB",
    "wof:name":"LS28 8ES",
    "wof:placetype":"postalcode"
},
  "geometry": {"coordinates":[-1.6979894115824,53.80328644319886],"type":"Point"}
}