{
  "type": "Feature",
  "properties": {
    "date:inception_lower": "2022-06-01",
    "date:inception_upper": "2022-06-01",
    "iso:country": "GB",
    "wof:name": "NN17 1US",
    "wof:placetype": "postalcode"
  },
  "geometry": {"coordinates":[-0.681316,52.488671],"type":"Point"}
}
