{
  "type": "Feature",
  "properties": {
    "iso:country":"GB",
    "wof:name":"NG5 7AN",
    "wof:placetype":"postalcode"
},
  "geometry": {"coordinates":[-1.13219330563789,53.00459262517054],"type":"Point"}
}