{
  "type": "Feature",
  "properties": {
    "iso:country": "GB",
    "wof:name": "SW13 9LT",
    "wof:placetype": "postalcode"
  },
  "geometry": {"coordinates":[-0.247812,51.473733],"type":"Point"}
}
