{
  "type": "Feature",
  "properties": {
    "iso:country":"GB",
    "wof:name":"SW13 9LT",
    "wof:placetype":"postalcode"
},
  "geometry": {"coordinates":[-0.24781246299209,51.47373342123038],"type":"Point"}
}