{
  "type": "Feature",
  "properties": {
    "date:inception_lower": "1990-02-01",
    "date:inception_upper": "1990-02-01",
    "iso:country": "GB",
    "wof:name": "WF13 3SS",
    "wof:placetype": "postalcode"
  },
  "geometry": {"coordinates":[-1.657414,53.690009],"type":"Point"}
}
