{
  "type": "Feature",
  "properties": {
    "iso:country": "GB",
    "wof:name": "WF13 3SS",
    "wof:placetype": "postalcode"
  },
  "geometry": {"coordinates":[-1.657414,53.690009],"type":"Point"}
}
