{
  "type": "Feature",
  "properties": {
    "iso:country":"GB",
    "wof:name":"WF13 3SS",
    "wof:placetype":"postalcode"
},
  "geometry": {"coordinates":[-1.65741418668606,53.69000857675207],"type":"Point"}
}