{
  "type": "Feature",
  "properties": {
    "iso:country":"GB",
    "wof:name":"CO5 9SX",
    "wof:placetype":"postalcode"
},
  "geometry": {"coordinates":[0.73142914668546,51.82354456148099],"type":"Point"}
}