{
  "type": "Feature",
  "properties": {
    "iso:country":"GB",
    "wof:name":"WS13 6RD",
    "wof:placetype":"postalcode"
},
  "geometry": {"coordinates":[-1.83913865364732,52.67409627062891],"type":"Point"}
}