{
  "type": "Feature",
  "properties": {
    "iso:country":"GB",
    "wof:name":"B98 8AR",
    "wof:placetype":"postalcode"
},
  "geometry": {"coordinates":[-1.94016028954871,52.30638453612246],"type":"Point"}
}