{
  "type": "Feature",
  "properties": {
    "iso:country": "GB",
    "wof:name": "TA6 6YN",
    "wof:placetype": "postalcode"
  },
  "geometry": {"coordinates":[-2.994772,51.109626],"type":"Point"}
}
