{
  "type": "Feature",
  "properties": {
    "date:inception_lower": "1980-01-01",
    "date:inception_upper": "1980-01-01",
    "iso:country": "GB",
    "wof:name": "LA11 7NS",
    "wof:placetype": "postalcode"
  },
  "geometry": {"coordinates":[-2.974394,54.182238],"type":"Point"}
}
