{
  "type": "Feature",
  "properties": {
    "date:inception_lower": "2016-03-01",
    "date:inception_upper": "2016-03-01",
    "iso:country": "GB",
    "wof:name": "SM4 9ZZ",
    "wof:placetype": "postalcode"
  },
  "geometry": {"coordinates":[-0.199812,51.395958],"type":"Point"}
}
