{
  "type": "Feature",
  "properties": {
    "iso:country":"GB",
    "wof:name":"SM4 9ZZ",
    "wof:placetype":"postalcode"
},
  "geometry": {"coordinates":[-0.19981213996595,51.39595814341677],"type":"Point"}
}