{
  "type": "Feature",
  "properties": {
    "iso:country":"GB",
    "wof:name":"CT17 0BL",
    "wof:placetype":"postalcode"
},
  "geometry": {"coordinates":[1.30436215276371,51.12926921205312],"type":"Point"}
}