{
  "type": "Feature",
  "properties": {
    "date:inception_lower": "1980-01-01",
    "date:inception_upper": "1980-01-01",
    "iso:country": "GB",
    "wof:name": "CT4 7AA",
    "wof:placetype": "postalcode"
  },
  "geometry": {"coordinates":[1.085648,51.254354],"type":"Point"}
}
