{
  "type": "Feature",
  "properties": {
    "iso:country": "GB",
    "wof:name": "CT4 7AA",
    "wof:placetype": "postalcode"
  },
  "geometry": {"coordinates":[1.085648,51.254354],"type":"Point"}
}
