{
  "type": "Feature",
  "properties": {
    "iso:country":"GB",
    "wof:name":"DE4 4BY",
    "wof:placetype":"postalcode"
},
  "geometry": {"coordinates":[-1.62754941406036,53.07832374827355],"type":"Point"}
}