{
  "type": "Feature",
  "properties": {
    "iso:country": "GB",
    "wof:name": "DE4 4BY",
    "wof:placetype": "postalcode"
  },
  "geometry": {"coordinates":[-1.627549,53.078324],"type":"Point"}
}
