{
  "type": "Feature",
  "properties": {
    "iso:country": "GB",
    "wof:name": "S8 9DL",
    "wof:placetype": "postalcode"
  },
  "geometry": {"coordinates":[-1.477426,53.352668],"type":"Point"}
}
