{
  "type": "Feature",
  "properties": {
    "iso:country":"GB",
    "wof:name":"SA17 4RJ",
    "wof:placetype":"postalcode"
},
  "geometry": {"coordinates":[-4.28078418134207,51.74914031181775],"type":"Point"}
}