{
  "type": "Feature",
  "properties": {
    "date:inception_lower": "2012-12-01",
    "date:inception_upper": "2012-12-01",
    "iso:country": "GB",
    "wof:name": "SA17 4RJ",
    "wof:placetype": "postalcode"
  },
  "geometry": {"coordinates":[-4.280784,51.74914],"type":"Point"}
}
