{
  "type": "Feature",
  "properties": {
    "iso:country": "GB",
    "wof:name": "SA17 4RJ",
    "wof:placetype": "postalcode"
  },
  "geometry": {"coordinates":[-4.280784,51.74914],"type":"Point"}
}
