{
  "type": "Feature",
  "properties": {
    "date:inception_lower": "2007-02-01",
    "date:inception_upper": "2007-02-01",
    "iso:country": "GB",
    "wof:name": "FK5 4GS",
    "wof:placetype": "postalcode"
  },
  "geometry": {"coordinates":[-3.831654,56.022669],"type":"Point"}
}
