{
  "type": "Feature",
  "properties": {
    "iso:country":"GB",
    "wof:name":"FK5 4GS",
    "wof:placetype":"postalcode"
},
  "geometry": {"coordinates":[-3.83165408822544,56.02266872595794],"type":"Point"}
}