{
  "type": "Feature",
  "properties": {
    "iso:country":"GB",
    "wof:name":"SL9 9TY",
    "wof:placetype":"postalcode"
},
  "geometry": {"coordinates":[-0.5481214204804,51.60785213999903],"type":"Point"}
}