{
  "type": "Feature",
  "properties": {
    "iso:country": "GB",
    "wof:name": "SL9 9TY",
    "wof:placetype": "postalcode"
  },
  "geometry": {"coordinates":[-0.548121,51.607852],"type":"Point"}
}
