{
  "type": "Feature",
  "properties": {
    "iso:country": "GB",
    "wof:name": "TN13 2UG",
    "wof:placetype": "postalcode"
  },
  "geometry": {"coordinates":[0.167882,51.291923],"type":"Point"}
}
