{
  "type": "Feature",
  "properties": {
    "iso:country":"GB",
    "wof:name":"TN13 2UG",
    "wof:placetype":"postalcode"
},
  "geometry": {"coordinates":[0.16788177644754,51.29192268012077],"type":"Point"}
}