{
  "type": "Feature",
  "properties": {
    "iso:country":"GB",
    "wof:name":"CR4 3ET",
    "wof:placetype":"postalcode"
},
  "geometry": {"coordinates":[-0.17478717195866,51.41071459342017],"type":"Point"}
}