{
  "type": "Feature",
  "properties": {
    "iso:country":"GB",
    "wof:name":"CR0 6PR",
    "wof:placetype":"postalcode"
},
  "geometry": {"coordinates":[-0.08442505711657,51.38042368484797],"type":"Point"}
}