{
  "type": "Feature",
  "properties": {
    "iso:country": "GB",
    "wof:name": "PL9 8RZ",
    "wof:placetype": "postalcode"
  },
  "geometry": {"coordinates":[-4.084136,50.35799],"type":"Point"}
}
