{
  "type": "Feature",
  "properties": {
    "iso:country":"GB",
    "wof:name":"PL9 8RZ",
    "wof:placetype":"postalcode"
},
  "geometry": {"coordinates":[-4.08413617124329,50.35798986573943],"type":"Point"}
}