{
  "type": "Feature",
  "properties": {
    "iso:country": "GB",
    "wof:name": "KA1 5HL",
    "wof:placetype": "postalcode"
  },
  "geometry": {"coordinates":[-4.509419,55.584518],"type":"Point"}
}
