{
  "type": "Feature",
  "properties": {
    "date:inception_lower":"1996-06-01",
    "date:inception_upper":"1996-06-30",
    "iso:country":"GB",
    "wof:name":"KA1 5HL",
    "wof:placetype":"postalcode"
},
  "geometry": {"coordinates":[-4.509419,55.584518],"type":"Point"}
}