{
  "type": "Feature",
  "properties": {
    "iso:country":"GB",
    "wof:name":"PO20 3UQ",
    "wof:placetype":"postalcode"
},
  "geometry": {"coordinates":[-0.66817234717845,50.84262756932932],"type":"Point"}
}