{
  "type": "Feature",
  "properties": {
    "iso:country":"GB",
    "wof:name":"DY8 1QU",
    "wof:placetype":"postalcode"
},
  "geometry": {"coordinates":[-2.14119412491412,52.44920384656722],"type":"Point"}
}