{
  "type": "Feature",
  "properties": {
    "iso:country": "GB",
    "wof:name": "WS3 4NW",
    "wof:placetype": "postalcode"
  },
  "geometry": {"coordinates":[-1.971464,52.618861],"type":"Point"}
}
