{
  "type": "Feature",
  "properties": {
    "iso:country":"GB",
    "wof:name":"KT17 3BW",
    "wof:placetype":"postalcode"
},
  "geometry": {"coordinates":[-0.24642738314895,51.33849190998926],"type":"Point"}
}