{
  "type": "Feature",
  "properties": {
    "iso:country":"GB",
    "wof:name":"NG15 7JR",
    "wof:placetype":"postalcode"
},
  "geometry": {"coordinates":[-1.20383103028436,53.0352709928726],"type":"Point"}
}