{
  "type": "Feature",
  "properties": {
    "iso:country": "GB",
    "wof:name": "NR27 9LQ",
    "wof:placetype": "postalcode"
  },
  "geometry": {"coordinates":[1.297747,52.914972],"type":"Point"}
}
