{
  "type": "Feature",
  "properties": {
    "iso:country": "GB",
    "wof:name": "M33 7GG",
    "wof:placetype": "postalcode"
  },
  "geometry": {"coordinates":[-2.322914,53.424346],"type":"Point"}
}
