{
  "type": "Feature",
  "properties": {
    "iso:country":"GB",
    "wof:name":"CF14 1LR",
    "wof:placetype":"postalcode"
},
  "geometry": {"coordinates":[-3.21821824209708,51.5066389361083],"type":"Point"}
}