{
  "type": "Feature",
  "properties": {
    "iso:country":"GB",
    "wof:name":"LE7 7FG",
    "wof:placetype":"postalcode"
},
  "geometry": {"coordinates":[-1.1928860562625,52.67484811093792],"type":"Point"}
}