{
  "type": "Feature",
  "properties": {
    "date:inception_lower": "1996-06-01",
    "date:inception_upper": "1996-06-01",
    "iso:country": "GB",
    "wof:name": "AB11 9AR",
    "wof:placetype": "postalcode"
  },
  "geometry": {"coordinates":[-2.09237,57.135982],"type":"Point"}
}
