{
  "type": "Feature",
  "properties": {
    "iso:country":"GB",
    "wof:name":"AB11 9AR",
    "wof:placetype":"postalcode"
},
  "geometry": {"coordinates":[-2.09236991321942,57.13598205235783],"type":"Point"}
}