{
  "type": "Feature",
  "properties": {
    "iso:country":"GB",
    "wof:name":"SA4 4YN",
    "wof:placetype":"postalcode"
},
  "geometry": {"coordinates":[-4.05133960922083,51.67615258785217],"type":"Point"}
}