{
  "type": "Feature",
  "properties": {
    "iso:country": "GB",
    "wof:name": "SA4 4YN",
    "wof:placetype": "postalcode"
  },
  "geometry": {"coordinates":[-4.05134,51.676153],"type":"Point"}
}
