{
  "type": "Feature",
  "properties": {
    "iso:country": "GB",
    "wof:name": "IV30 5TZ",
    "wof:placetype": "postalcode"
  },
  "geometry": {"coordinates":[-3.495768,57.702846],"type":"Point"}
}
