{
  "type": "Feature",
  "properties": {
    "iso:country":"GB",
    "wof:name":"WA2 9LZ",
    "wof:placetype":"postalcode"
},
  "geometry": {"coordinates":[-2.57887943937433,53.4137002137612],"type":"Point"}
}