{
  "type": "Feature",
  "properties": {
    "iso:country": "GB",
    "wof:name": "IV16 9YU",
    "wof:placetype": "postalcode"
  },
  "geometry": {"coordinates":[-4.342499,57.662482],"type":"Point"}
}
