{
  "type": "Feature",
  "properties": {
    "iso:country":"GB",
    "wof:name":"IV16 9YU",
    "wof:placetype":"postalcode"
},
  "geometry": {"coordinates":[-4.34249889925091,57.66248174602278],"type":"Point"}
}