{
  "type": "Feature",
  "properties": {
    "date:inception_lower":"2015-09-01",
    "date:inception_upper":"2015-09-30",
    "iso:country":"GB",
    "wof:name":"SG9 9FU",
    "wof:placetype":"postalcode"
},
  "geometry": {"coordinates":[-0.01214,51.947048],"type":"Point"}
}