{
  "type": "Feature",
  "properties": {
    "iso:country": "GB",
    "wof:name": "SG9 9FU",
    "wof:placetype": "postalcode"
  },
  "geometry": {"coordinates":[-0.01214,51.947048],"type":"Point"}
}
