{
  "type": "Feature",
  "properties": {
    "iso:country":"GB",
    "wof:name":"SG9 9FU",
    "wof:placetype":"postalcode"
},
  "geometry": {"coordinates":[-0.01179782877064,51.94718617201927],"type":"Point"}
}