{
  "type": "Feature",
  "properties": {
    "iso:country": "GB",
    "wof:name": "GU46 7AS",
    "wof:placetype": "postalcode"
  },
  "geometry": {"coordinates":[-0.825549,51.34715],"type":"Point"}
}
