{
  "type": "Feature",
  "properties": {
    "iso:country":"GB",
    "wof:name":"G61 4DR",
    "wof:placetype":"postalcode"
},
  "geometry": {"coordinates":[-4.35899400691769,55.92435226841487],"type":"Point"}
}