{
  "type": "Feature",
  "properties": {
    "iso:country":"GB",
    "wof:name":"HX3 6DG",
    "wof:placetype":"postalcode"
},
  "geometry": {"coordinates":[-1.86151692981805,53.72974986536307],"type":"Point"}
}