{
  "type": "Feature",
  "properties": {
    "date:inception_lower": "1990-02-01",
    "date:inception_upper": "1990-02-01",
    "iso:country": "GB",
    "wof:name": "SE1 8TL",
    "wof:placetype": "postalcode"
  },
  "geometry": {"coordinates":[-0.115437,51.506581],"type":"Point"}
}
