{
  "type": "Feature",
  "properties": {
    "iso:country": "GB",
    "wof:name": "SE1 8TL",
    "wof:placetype": "postalcode"
  },
  "geometry": {"coordinates":[-0.115437,51.506581],"type":"Point"}
}
