{
  "type": "Feature",
  "properties": {
    "iso:country":"GB",
    "wof:name":"BD18 2EY",
    "wof:placetype":"postalcode"
},
  "geometry": {"coordinates":[-1.77155003000134,53.8292982902604],"type":"Point"}
}