{
  "type": "Feature",
  "properties": {
    "iso:country":"GB",
    "wof:name":"BN14 0TY",
    "wof:placetype":"postalcode"
},
  "geometry": {"coordinates":[-0.40452470504449,50.86589566709709],"type":"Point"}
}