{
  "type": "Feature",
  "properties": {
    "date:inception_lower": "2019-06-01",
    "date:inception_upper": "2019-06-01",
    "iso:country": "GB",
    "wof:name": "MK5 6FU",
    "wof:placetype": "postalcode"
  },
  "geometry": {"coordinates":[-0.810726,52.016374],"type":"Point"}
}
