{
  "type": "Feature",
  "properties": {
    "iso:country": "GB",
    "wof:name": "MK5 6FU",
    "wof:placetype": "postalcode"
  },
  "geometry": {"coordinates":[-0.811006,52.01626],"type":"Point"}
}
