{
  "type": "Feature",
  "properties": {
    "date:inception_lower": "1980-01-01",
    "date:inception_upper": "1980-01-01",
    "iso:country": "GB",
    "wof:name": "ME2 2XP",
    "wof:placetype": "postalcode"
  },
  "geometry": {"coordinates":[0.458508,51.393832],"type":"Point"}
}
