{
  "type": "Feature",
  "properties": {
    "iso:country":"GB",
    "wof:name":"ME2 2XP",
    "wof:placetype":"postalcode"
},
  "geometry": {"coordinates":[0.45850776526087,51.3938317147991],"type":"Point"}
}