{
  "type": "Feature",
  "properties": {
    "iso:country":"GB",
    "wof:name":"BB10 1NE",
    "wof:placetype":"postalcode"
},
  "geometry": {"coordinates":[-2.23719864013496,53.80155246116527],"type":"Point"}
}