{
  "type": "Feature",
  "properties": {
    "iso:country": "GB",
    "wof:name": "SY5 9PW",
    "wof:placetype": "postalcode"
  },
  "geometry": {"coordinates":[-2.888473,52.685713],"type":"Point"}
}
