{
  "type": "Feature",
  "properties": {
    "iso:country":"GB",
    "wof:name":"SY5 9PW",
    "wof:placetype":"postalcode"
},
  "geometry": {"coordinates":[-2.88847493774781,52.68569758835611],"type":"Point"}
}