{
  "type": "Feature",
  "properties": {
    "iso:country":"GB",
    "wof:name":"YO30 4XS",
    "wof:placetype":"postalcode"
},
  "geometry": {"coordinates":[-1.10376662480175,53.98390227432137],"type":"Point"}
}