{
  "type": "Feature",
  "properties": {
    "iso:country": "GB",
    "wof:name": "BS24 7LR",
    "wof:placetype": "postalcode"
  },
  "geometry": {"coordinates":[-2.902737,51.337772],"type":"Point"}
}
