{
  "type": "Feature",
  "properties": {
    "date:inception_lower":"1980-10-01",
    "date:inception_upper":"1980-10-31",
    "iso:country":"GB",
    "wof:name":"EH52 5HU",
    "wof:placetype":"postalcode"
},
  "geometry": {"coordinates":[-3.466972,55.932827],"type":"Point"}
}