{
  "type": "Feature",
  "properties": {
    "iso:country":"GB",
    "wof:name":"WA12 9PS",
    "wof:placetype":"postalcode"
},
  "geometry": {"coordinates":[-2.64297359672449,53.45278752239387],"type":"Point"}
}