{
  "type": "Feature",
  "properties": {
    "date:inception_lower": "1980-01-01",
    "date:inception_upper": "1980-01-01",
    "iso:country": "GB",
    "wof:name": "WA12 9PS",
    "wof:placetype": "postalcode"
  },
  "geometry": {"coordinates":[-2.642974,53.452788],"type":"Point"}
}
