{
  "type": "Feature",
  "properties": {
    "iso:country":"GB",
    "wof:name":"WN7 3DH",
    "wof:placetype":"postalcode"
},
  "geometry": {"coordinates":[-2.4976619588017,53.48916600439533],"type":"Point"}
}