{
  "type": "Feature",
  "properties": {
    "iso:country":"GB",
    "wof:name":"TQ2 7AY",
    "wof:placetype":"postalcode"
},
  "geometry": {"coordinates":[-3.54648977374054,50.48020111736468],"type":"Point"}
}