{
  "type": "Feature",
  "properties": {
    "date:inception_lower":"1983-07-01",
    "date:inception_upper":"1983-07-31",
    "iso:country":"GB",
    "wof:name":"TQ1 1TU",
    "wof:placetype":"postalcode"
},
  "geometry": {"coordinates":[-3.512843,50.467324],"type":"Point"}
}