{
  "type": "Feature",
  "properties": {
    "iso:country":"GB",
    "wof:name":"SK11 7DL",
    "wof:placetype":"postalcode"
},
  "geometry": {"coordinates":[-2.10818168359151,53.25580308379966],"type":"Point"}
}