{
  "type": "Feature",
  "properties": {
    "date:inception_lower":"1987-04-01",
    "date:inception_upper":"1987-04-30",
    "iso:country":"GB",
    "wof:name":"TA19 9HT",
    "wof:placetype":"postalcode"
},
  "geometry": {"coordinates":[-2.92286,50.952318],"type":"Point"}
}