{
  "type": "Feature",
  "properties": {
    "iso:country":"GB",
    "wof:name":"WN2 1RW",
    "wof:placetype":"postalcode"
},
  "geometry": {"coordinates":[-2.59395868386801,53.57466509193284],"type":"Point"}
}