{
  "type": "Feature",
  "properties": {
    "iso:country":"GB",
    "wof:name":"IV18 0PH",
    "wof:placetype":"postalcode"
},
  "geometry": {"coordinates":[-4.07018722925203,57.74902972098],"type":"Point"}
}