{
  "type": "Feature",
  "properties": {
    "date:inception_lower": "2005-11-01",
    "date:inception_upper": "2005-11-01",
    "iso:country": "GB",
    "wof:name": "IV18 0PH",
    "wof:placetype": "postalcode"
  },
  "geometry": {"coordinates":[-4.070187,57.74903],"type":"Point"}
}
