{
  "type": "Feature",
  "properties": {
    "iso:country":"GB",
    "wof:name":"WA11 0YF",
    "wof:placetype":"postalcode"
},
  "geometry": {"coordinates":[-2.67209951404455,53.47105388269787],"type":"Point"}
}