{
  "type": "Feature",
  "properties": {
    "iso:country": "GB",
    "wof:name": "S44 6GF",
    "wof:placetype": "postalcode"
  },
  "geometry": {"coordinates":[-1.304316,53.223037],"type":"Point"}
}
