{
  "type": "Feature",
  "properties": {
    "iso:country": "GB",
    "wof:name": "LS25 5AQ",
    "wof:placetype": "postalcode"
  },
  "geometry": {"coordinates":[-1.255631,53.777872],"type":"Point"}
}
