{
  "type": "Feature",
  "properties": {
    "iso:country":"GB",
    "wof:name":"LS25 5AQ",
    "wof:placetype":"postalcode"
},
  "geometry": {"coordinates":[-1.25563147118136,53.77787159436642],"type":"Point"}
}