{
  "type": "Feature",
  "properties": {
    "date:inception_lower":"2007-08-01",
    "date:inception_upper":"2007-08-31",
    "iso:country":"GB",
    "wof:name":"LD8 2SQ",
    "wof:placetype":"postalcode"
},
  "geometry": {"coordinates":[-3.079911,52.255374],"type":"Point"}
}