{
  "type": "Feature",
  "properties": {
    "iso:country":"GB",
    "wof:name":"LD8 2SQ",
    "wof:placetype":"postalcode"
},
  "geometry": {"coordinates":[-3.07991067211204,52.25537426521852],"type":"Point"}
}