{
  "type": "Feature",
  "properties": {
    "iso:country": "GB",
    "wof:name": "LD8 2SQ",
    "wof:placetype": "postalcode"
  },
  "geometry": {"coordinates":[-3.079911,52.255374],"type":"Point"}
}
