{
  "type": "Feature",
  "properties": {
    "iso:country":"GB",
    "wof:name":"ST4 3PF",
    "wof:placetype":"postalcode"
},
  "geometry": {"coordinates":[-2.1494971313693,52.99510483139267],"type":"Point"}
}