{
  "type": "Feature",
  "properties": {
    "iso:country":"GB",
    "wof:name":"MK17 0BW",
    "wof:placetype":"postalcode"
},
  "geometry": {"coordinates":[-0.76873515719532,51.97278440295501],"type":"Point"}
}