{
  "type": "Feature",
  "properties": {
    "date:inception_lower": "1980-01-01",
    "date:inception_upper": "1980-01-01",
    "iso:country": "GB",
    "wof:name": "MK17 0BW",
    "wof:placetype": "postalcode"
  },
  "geometry": {"coordinates":[-0.768735,51.972784],"type":"Point"}
}
