{
  "type": "Feature",
  "properties": {
    "iso:country":"GB",
    "wof:name":"SE9 2DA",
    "wof:placetype":"postalcode"
},
  "geometry": {"coordinates":[0.07244665745218,51.44059606963016],"type":"Point"}
}