{
  "type": "Feature",
  "properties": {
    "date:inception_lower": "1980-01-01",
    "date:inception_upper": "1980-01-01",
    "iso:country": "GB",
    "wof:name": "DH8 8BD",
    "wof:placetype": "postalcode"
  },
  "geometry": {"coordinates":[-1.853251,54.84377],"type":"Point"}
}
