{
  "type": "Feature",
  "properties": {
    "iso:country":"GB",
    "wof:name":"DH8 8BD",
    "wof:placetype":"postalcode"
},
  "geometry": {"coordinates":[-1.85325150016295,54.84377009751822],"type":"Point"}
}