{
  "type": "Feature",
  "properties": {
    "iso:country":"GB",
    "wof:name":"BN26 6PP",
    "wof:placetype":"postalcode"
},
  "geometry": {"coordinates":[0.24487590853014,50.82639322510753],"type":"Point"}
}