{
  "type": "Feature",
  "properties": {
    "date:inception_lower": "2006-07-01",
    "date:inception_upper": "2006-07-01",
    "iso:country": "GB",
    "wof:name": "IV4 7GD",
    "wof:placetype": "postalcode"
  },
  "geometry": {"coordinates":[-4.471311,57.48165],"type":"Point"}
}
