{
  "type": "Feature",
  "properties": {
    "iso:country":"GB",
    "wof:name":"IV4 7GD",
    "wof:placetype":"postalcode"
},
  "geometry": {"coordinates":[-4.47131107529922,57.48164956782521],"type":"Point"}
}