{
  "type": "Feature",
  "properties": {
    "iso:country":"GB",
    "wof:name":"IP11 9QX",
    "wof:placetype":"postalcode"
},
  "geometry": {"coordinates":[1.32683728716306,51.97677970334355],"type":"Point"}
}