{
  "type": "Feature",
  "properties": {
    "date:inception_lower":"1980-01-01",
    "date:inception_upper":"1980-01-31",
    "iso:country":"GB",
    "wof:name":"IP11 9QX",
    "wof:placetype":"postalcode"
},
  "geometry": {"coordinates":[1.326837,51.97678],"type":"Point"}
}