{
  "type": "Feature",
  "properties": {
    "date:inception_lower": "1980-01-01",
    "date:inception_upper": "1980-01-01",
    "iso:country": "GB",
    "wof:name": "NE6 4DS",
    "wof:placetype": "postalcode"
  },
  "geometry": {"coordinates":[-1.544856,54.977234],"type":"Point"}
}
