{
  "type": "Feature",
  "properties": {
    "iso:country":"GB",
    "wof:name":"WS15 2XF",
    "wof:placetype":"postalcode"
},
  "geometry": {"coordinates":[-1.95314044425813,52.76563803406633],"type":"Point"}
}