{
  "type": "Feature",
  "properties": {
    "iso:country":"GB",
    "wof:name":"UB2 4HR",
    "wof:placetype":"postalcode"
},
  "geometry": {"coordinates":[-0.36531070510562,51.49870237604699],"type":"Point"}
}