{
  "type": "Feature",
  "properties": {
    "iso:country":"GB",
    "wof:name":"S70 4AT",
    "wof:placetype":"postalcode"
},
  "geometry": {"coordinates":[-1.45976690100147,53.53720676947393],"type":"Point"}
}