{
  "type": "Feature",
  "properties": {
    "iso:country": "GB",
    "wof:name": "S70 4AT",
    "wof:placetype": "postalcode"
  },
  "geometry": {"coordinates":[-1.459767,53.537207],"type":"Point"}
}
