{
  "type": "Feature",
  "properties": {
    "iso:country":"GB",
    "wof:name":"EN9 3AT",
    "wof:placetype":"postalcode"
},
  "geometry": {"coordinates":[0.01293761189178,51.68574687451013],"type":"Point"}
}