{
  "type": "Feature",
  "properties": {
    "date:inception_lower":"1980-01-01",
    "date:inception_upper":"1980-01-31",
    "iso:country":"GB",
    "wof:name":"EX13 7AU",
    "wof:placetype":"postalcode"
},
  "geometry": {"coordinates":[-2.948054,50.814528],"type":"Point"}
}