{
  "type": "Feature",
  "properties": {
    "iso:country": "GB",
    "wof:name": "EX13 7AU",
    "wof:placetype": "postalcode"
  },
  "geometry": {"coordinates":[-2.948054,50.814528],"type":"Point"}
}
