{
  "type": "Feature",
  "properties": {
    "date:inception_lower": "1980-01-01",
    "date:inception_upper": "1980-01-01",
    "iso:country": "GB",
    "wof:name": "EX13 7AU",
    "wof:placetype": "postalcode"
  },
  "geometry": {"coordinates":[-2.947681,50.814333],"type":"Point"}
}
