{
  "type": "Feature",
  "properties": {
    "date:inception_lower": "2008-10-01",
    "date:inception_upper": "2008-10-01",
    "iso:country": "GB",
    "wof:name": "SE1 6DT",
    "wof:placetype": "postalcode"
  },
  "geometry": {"coordinates":[-0.099246,51.49605],"type":"Point"}
}
