{
  "type": "Feature",
  "properties": {
    "iso:country":"GB",
    "wof:name":"S8 9FX",
    "wof:placetype":"postalcode"
},
  "geometry": {"coordinates":[-1.47151274130021,53.35580642054547],"type":"Point"}
}