{
  "type": "Feature",
  "properties": {
    "iso:country": "GB",
    "wof:name": "S8 9FX",
    "wof:placetype": "postalcode"
  },
  "geometry": {"coordinates":[-1.471513,53.355806],"type":"Point"}
}
