{
  "type": "Feature",
  "properties": {
    "iso:country":"GB",
    "wof:name":"LS19 7JQ",
    "wof:placetype":"postalcode"
},
  "geometry": {"coordinates":[-1.6982613552561,53.85849107300491],"type":"Point"}
}