{
  "type": "Feature",
  "properties": {
    "iso:country":"GB",
    "wof:name":"BA21 5TE",
    "wof:placetype":"postalcode"
},
  "geometry": {"coordinates":[-2.60887514221032,50.97515890348682],"type":"Point"}
}