{
  "type": "Feature",
  "properties": {
    "iso:country":"GB",
    "wof:name":"LS18 5PP",
    "wof:placetype":"postalcode"
},
  "geometry": {"coordinates":[-1.6355707174322,53.84862823647576],"type":"Point"}
}