{
  "type": "Feature",
  "properties": {
    "iso:country":"GB",
    "wof:name":"WV4 6LS",
    "wof:placetype":"postalcode"
},
  "geometry": {"coordinates":[-2.10517552251158,52.55424380348366],"type":"Point"}
}