{
  "type": "Feature",
  "properties": {
    "iso:country":"GB",
    "wof:name":"PE32 2LN",
    "wof:placetype":"postalcode"
},
  "geometry": {"coordinates":[0.76442574757556,52.69495109262601],"type":"Point"}
}