{
  "type": "Feature",
  "properties": {
    "iso:country":"GB",
    "wof:name":"E14 7AS",
    "wof:placetype":"postalcode"
},
  "geometry": {"coordinates":[-0.02618096415949,51.51726148281834],"type":"Point"}
}