{
  "type": "Feature",
  "properties": {
    "date:inception_lower": "2016-07-01",
    "date:inception_upper": "2016-07-01",
    "iso:country": "GB",
    "wof:name": "CM1 4FQ",
    "wof:placetype": "postalcode"
  },
  "geometry": {"coordinates":[0.469672,51.750222],"type":"Point"}
}
