{
  "type": "Feature",
  "properties": {
    "iso:country":"GB",
    "wof:name":"NN4 5DU",
    "wof:placetype":"postalcode"
},
  "geometry": {"coordinates":[-0.88562904215065,52.19048718357421],"type":"Point"}
}