{
  "type": "Feature",
  "properties": {
    "date:inception_lower": "1999-06-01",
    "date:inception_upper": "1999-06-01",
    "iso:country": "GB",
    "wof:name": "LL13 7LT",
    "wof:placetype": "postalcode"
  },
  "geometry": {"coordinates":[-2.997931,53.045414],"type":"Point"}
}
