{
  "type": "Feature",
  "properties": {
    "iso:country":"GB",
    "wof:name":"NE16 5JS",
    "wof:placetype":"postalcode"
},
  "geometry": {"coordinates":[-1.67954086671976,54.9350702807338],"type":"Point"}
}