{
  "type": "Feature",
  "properties": {
    "date:inception_lower":"2004-01-01",
    "date:inception_upper":"2004-01-31",
    "iso:country":"GB",
    "wof:name":"NE16 5JS",
    "wof:placetype":"postalcode"
},
  "geometry": {"coordinates":[-1.679541,54.93507],"type":"Point"}
}