{
  "type": "Feature",
  "properties": {
    "iso:country":"GB",
    "wof:name":"SA10 8LW",
    "wof:placetype":"postalcode"
},
  "geometry": {"coordinates":[-3.78070013580184,51.6866747300033],"type":"Point"}
}