{
  "type": "Feature",
  "properties": {
    "iso:country": "GB",
    "wof:name": "SL6 7UD",
    "wof:placetype": "postalcode"
  },
  "geometry": {"coordinates":[-0.727778,51.540888],"type":"Point"}
}
