{
  "type": "Feature",
  "properties": {
    "iso:country":"GB",
    "wof:name":"SL6 7UD",
    "wof:placetype":"postalcode"
},
  "geometry": {"coordinates":[-0.72777766272869,51.54088795267664],"type":"Point"}
}