{
  "type": "Feature",
  "properties": {
    "date:inception_lower":"1985-04-01",
    "date:inception_upper":"1985-04-30",
    "iso:country":"GB",
    "wof:name":"SL6 7UD",
    "wof:placetype":"postalcode"
},
  "geometry": {"coordinates":[-0.727778,51.540888],"type":"Point"}
}