{
  "type": "Feature",
  "properties": {
    "iso:country":"GB",
    "wof:name":"DN15 7JH",
    "wof:placetype":"postalcode"
},
  "geometry": {"coordinates":[-0.65855537810463,53.59789965300682],"type":"Point"}
}