{
  "type": "Feature",
  "properties": {
    "iso:country":"GB",
    "wof:name":"E8 4BF",
    "wof:placetype":"postalcode"
},
  "geometry": {"coordinates":[-0.06350616159195,51.54050001146194],"type":"Point"}
}