{
  "type": "Feature",
  "properties": {
    "date:inception_lower": "2010-05-01",
    "date:inception_upper": "2010-05-01",
    "iso:country": "GB",
    "wof:name": "E8 4BF",
    "wof:placetype": "postalcode"
  },
  "geometry": {"coordinates":[-0.063506,51.5405],"type":"Point"}
}
