{
  "type": "Feature",
  "properties": {
    "date:inception_lower": "1988-03-01",
    "date:inception_upper": "1988-03-01",
    "iso:country": "GB",
    "wof:name": "SO21 2DL",
    "wof:placetype": "postalcode"
  },
  "geometry": {"coordinates":[-1.338285,51.01186],"type":"Point"}
}
