{
  "type": "Feature",
  "properties": {
    "iso:country":"GB",
    "wof:name":"SO21 2DL",
    "wof:placetype":"postalcode"
},
  "geometry": {"coordinates":[-1.33828522652261,51.01186004705501],"type":"Point"}
}