{
  "type": "Feature",
  "properties": {
    "iso:country": "GB",
    "wof:name": "SO21 2DL",
    "wof:placetype": "postalcode"
  },
  "geometry": {"coordinates":[-1.338285,51.01186],"type":"Point"}
}
