{
  "type": "Feature",
  "properties": {
    "iso:country":"GB",
    "wof:name":"EX5 4BE",
    "wof:placetype":"postalcode"
},
  "geometry": {"coordinates":[-3.50844105302528,50.7719705693515],"type":"Point"}
}