{
  "type": "Feature",
  "properties": {
    "iso:country":"GB",
    "wof:name":"WF9 5HE",
    "wof:placetype":"postalcode"
},
  "geometry": {"coordinates":[-1.37466667223338,53.62326104446199],"type":"Point"}
}