{
  "type": "Feature",
  "properties": {
    "iso:country": "GB",
    "wof:name": "CO5 8JD",
    "wof:placetype": "postalcode"
  },
  "geometry": {"coordinates":[0.913093,51.777002],"type":"Point"}
}
