{
  "type": "Feature",
  "properties": {
    "iso:country":"GB",
    "wof:name":"CO5 8JD",
    "wof:placetype":"postalcode"
},
  "geometry": {"coordinates":[0.91309274496276,51.77700172759202],"type":"Point"}
}