{
  "type": "Feature",
  "properties": {
    "iso:country": "GB",
    "wof:name": "LL30 1JB",
    "wof:placetype": "postalcode"
  },
  "geometry": {"coordinates":[-3.825794,53.31233],"type":"Point"}
}
