{
  "type": "Feature",
  "properties": {
    "iso:country":"GB",
    "wof:name":"LL30 1JB",
    "wof:placetype":"postalcode"
},
  "geometry": {"coordinates":[-3.82579374719502,53.31232992681459],"type":"Point"}
}