{
  "type": "Feature",
  "properties": {
    "iso:country":"GB",
    "wof:name":"BL6 4GL",
    "wof:placetype":"postalcode"
},
  "geometry": {"coordinates":[-2.52387978326527,53.580268832706],"type":"Point"}
}