{
  "type": "Feature",
  "properties": {
    "date:inception_lower": "2012-05-01",
    "date:inception_upper": "2012-05-01",
    "iso:country": "GB",
    "wof:name": "BL6 4GL",
    "wof:placetype": "postalcode"
  },
  "geometry": {"coordinates":[-2.52388,53.580269],"type":"Point"}
}
