{
  "type": "Feature",
  "properties": {
    "iso:country": "GB",
    "wof:name": "BL6 4GL",
    "wof:placetype": "postalcode"
  },
  "geometry": {"coordinates":[-2.52388,53.580269],"type":"Point"}
}
