{
  "type": "Feature",
  "properties": {
    "iso:country":"GB",
    "wof:name":"BA13 4AP",
    "wof:placetype":"postalcode"
},
  "geometry": {"coordinates":[-2.26121325824918,51.23116455066832],"type":"Point"}
}