{
  "type": "Feature",
  "properties": {
    "iso:country":"GB",
    "wof:name":"LA2 8NP",
    "wof:placetype":"postalcode"
},
  "geometry": {"coordinates":[-2.58875538698364,54.12625865370885],"type":"Point"}
}