{
  "type": "Feature",
  "properties": {
    "date:inception_lower": "1980-01-01",
    "date:inception_upper": "1980-01-01",
    "iso:country": "GB",
    "wof:name": "LA2 8NP",
    "wof:placetype": "postalcode"
  },
  "geometry": {"coordinates":[-2.588755,54.126259],"type":"Point"}
}
