{
  "type": "Feature",
  "properties": {
    "iso:country": "GB",
    "wof:name": "LA2 8NP",
    "wof:placetype": "postalcode"
  },
  "geometry": {"coordinates":[-2.588755,54.126259],"type":"Point"}
}
