{
  "type": "Feature",
  "properties": {
    "date:inception_lower": "1995-07-01",
    "date:inception_upper": "1995-07-01",
    "iso:country": "GB",
    "wof:name": "LL43 2BF",
    "wof:placetype": "postalcode"
  },
  "geometry": {"coordinates":[-4.105482,52.771194],"type":"Point"}
}
