{
  "type": "Feature",
  "properties": {
    "iso:country": "GB",
    "wof:name": "LL43 2BF",
    "wof:placetype": "postalcode"
  },
  "geometry": {"coordinates":[-4.105482,52.771194],"type":"Point"}
}
