{
  "type": "Feature",
  "properties": {
    "iso:country":"GB",
    "wof:name":"BN3 8LU",
    "wof:placetype":"postalcode"
},
  "geometry": {"coordinates":[-0.2011247160263,50.84512193708461],"type":"Point"}
}