{
  "type": "Feature",
  "properties": {
    "iso:country":"GB",
    "wof:name":"YO12 4DU",
    "wof:placetype":"postalcode"
},
  "geometry": {"coordinates":[-0.41648362507531,54.274242735659],"type":"Point"}
}