{
  "type": "Feature",
  "properties": {
    "iso:country":"GB",
    "wof:name":"BR6 0NH",
    "wof:placetype":"postalcode"
},
  "geometry": {"coordinates":[0.09681032173125,51.37401068716129],"type":"Point"}
}