{
  "type": "Feature",
  "properties": {
    "iso:country":"GB",
    "wof:name":"PL7 2QP",
    "wof:placetype":"postalcode"
},
  "geometry": {"coordinates":[-4.02582855915367,50.38464528536247],"type":"Point"}
}