{
  "type": "Feature",
  "properties": {
    "iso:country":"GB",
    "wof:name":"SN12 6HZ",
    "wof:placetype":"postalcode"
},
  "geometry": {"coordinates":[-2.14311684833283,51.36577793711766],"type":"Point"}
}