{
  "type": "Feature",
  "properties": {
    "date:inception_lower":"2012-09-01",
    "date:inception_upper":"2012-09-30",
    "iso:country":"GB",
    "wof:name":"NR31 8GA",
    "wof:placetype":"postalcode"
},
  "geometry": {"coordinates":[1.720196,52.587227],"type":"Point"}
}