{
  "type": "Feature",
  "properties": {
    "iso:country": "GB",
    "wof:name": "BL6 5ET",
    "wof:placetype": "postalcode"
  },
  "geometry": {"coordinates":[-2.590113,53.594575],"type":"Point"}
}
