{
  "type": "Feature",
  "properties": {
    "iso:country":"GB",
    "wof:name":"BL6 5ET",
    "wof:placetype":"postalcode"
},
  "geometry": {"coordinates":[-2.59011326161736,53.59457549876522],"type":"Point"}
}