{
  "type": "Feature",
  "properties": {
    "iso:country":"GB",
    "wof:name":"L9 6BZ",
    "wof:placetype":"postalcode"
},
  "geometry": {"coordinates":[-2.92460244466464,53.45482248438731],"type":"Point"}
}