{
  "type": "Feature",
  "properties": {
    "date:inception_lower": "1980-01-01",
    "date:inception_upper": "1980-01-01",
    "iso:country": "GB",
    "wof:name": "L9 6BZ",
    "wof:placetype": "postalcode"
  },
  "geometry": {"coordinates":[-2.924602,53.454822],"type":"Point"}
}
