{
  "type": "Feature",
  "properties": {
    "iso:country":"GB",
    "wof:name":"DE3 9BT",
    "wof:placetype":"postalcode"
},
  "geometry": {"coordinates":[-1.53525947892998,52.90827320620469],"type":"Point"}
}