{
  "type": "Feature",
  "properties": {
    "date:inception_lower": "1993-08-01",
    "date:inception_upper": "1993-08-01",
    "iso:country": "GB",
    "wof:name": "LE8 0PA",
    "wof:placetype": "postalcode"
  },
  "geometry": {"coordinates":[-1.000478,52.542702],"type":"Point"}
}
