{
  "type": "Feature",
  "properties": {
    "iso:country":"GB",
    "wof:name":"LE8 0PA",
    "wof:placetype":"postalcode"
},
  "geometry": {"coordinates":[-1.00047838005098,52.54270177865262],"type":"Point"}
}