{
  "type": "Feature",
  "properties": {
    "iso:country":"GB",
    "wof:name":"SK4 4BJ",
    "wof:placetype":"postalcode"
},
  "geometry": {"coordinates":[-2.19179311503754,53.42339021818923],"type":"Point"}
}