{
  "type": "Feature",
  "properties": {
    "iso:country":"GB",
    "wof:name":"BN1 5DN",
    "wof:placetype":"postalcode"
},
  "geometry": {"coordinates":[-0.14595030723634,50.83406872107754],"type":"Point"}
}