{
  "type": "Feature",
  "properties": {
    "iso:country":"GB",
    "wof:name":"PO21 1RH",
    "wof:placetype":"postalcode"
},
  "geometry": {"coordinates":[-0.67076800067285,50.78423856039662],"type":"Point"}
}