{
  "type": "Feature",
  "properties": {
    "date:inception_lower": "2020-11-01",
    "date:inception_upper": "2020-11-01",
    "iso:country": "GB",
    "wof:name": "LU6 9LB",
    "wof:placetype": "postalcode"
  },
  "geometry": {"coordinates":[-0.523968,51.887761],"type":"Point"}
}
