{
  "type": "Feature",
  "properties": {
    "date:inception_lower": "1993-08-01",
    "date:inception_upper": "1993-08-01",
    "iso:country": "GB",
    "wof:name": "OX7 5JR",
    "wof:placetype": "postalcode"
  },
  "geometry": {"coordinates":[-1.558657,51.937889],"type":"Point"}
}
