{
  "type": "Feature",
  "properties": {
    "iso:country":"GB",
    "wof:name":"WV16 6BX",
    "wof:placetype":"postalcode"
},
  "geometry": {"coordinates":[-2.38585225511309,52.45378254720123],"type":"Point"}
}