{
  "type": "Feature",
  "properties": {
    "iso:country": "GB",
    "wof:name": "LS28 8BB",
    "wof:placetype": "postalcode"
  },
  "geometry": {"coordinates":[-1.662488,53.792155],"type":"Point"}
}
