{
  "type": "Feature",
  "properties": {
    "iso:country": "GB",
    "wof:name": "CM7 4QY",
    "wof:placetype": "postalcode"
  },
  "geometry": {"coordinates":[0.519883,51.916932],"type":"Point"}
}
