{
  "type": "Feature",
  "properties": {
    "iso:country":"GB",
    "wof:name":"CM7 4QY",
    "wof:placetype":"postalcode"
},
  "geometry": {"coordinates":[0.52289739222016,51.91309862564189],"type":"Point"}
}