{
  "type": "Feature",
  "properties": {
    "iso:country":"GB",
    "wof:name":"NG5 7JS",
    "wof:placetype":"postalcode"
},
  "geometry": {"coordinates":[-1.11552392512471,53.00135949547026],"type":"Point"}
}