{
  "type": "Feature",
  "properties": {
    "iso:country":"GB",
    "wof:name":"ML6 7PR",
    "wof:placetype":"postalcode"
},
  "geometry": {"coordinates":[-3.89041730208598,55.8916384163652],"type":"Point"}
}