{
  "type": "Feature",
  "properties": {
    "date:inception_lower": "1980-01-01",
    "date:inception_upper": "1980-01-01",
    "iso:country": "GB",
    "wof:name": "LE4 7SL",
    "wof:placetype": "postalcode"
  },
  "geometry": {"coordinates":[-1.112703,52.663119],"type":"Point"}
}
