{
  "type": "Feature",
  "properties": {
    "iso:country": "GB",
    "wof:name": "PE9 2LH",
    "wof:placetype": "postalcode"
  },
  "geometry": {"coordinates":[-0.458588,52.649656],"type":"Point"}
}
