{
  "type": "Feature",
  "properties": {
    "iso:country":"GB",
    "wof:name":"IP13 9LA",
    "wof:placetype":"postalcode"
},
  "geometry": {"coordinates":[1.34545695562334,52.21848624051257],"type":"Point"}
}