{
  "type": "Feature",
  "properties": {
    "iso:country":"GB",
    "wof:name":"NE29 8LT",
    "wof:placetype":"postalcode"
},
  "geometry": {"coordinates":[-1.4742759316256,55.01638349206496],"type":"Point"}
}