{
  "type": "Feature",
  "properties": {
    "iso:country":"GB",
    "wof:name":"KT23 4RA",
    "wof:placetype":"postalcode"
},
  "geometry": {"coordinates":[-0.37102693848536,51.27821543312086],"type":"Point"}
}