{
  "type": "Feature",
  "properties": {
    "iso:country":"GB",
    "wof:name":"B70 9HE",
    "wof:placetype":"postalcode"
},
  "geometry": {"coordinates":[-2.00425996338074,52.52203501640594],"type":"Point"}
}