{
  "type": "Feature",
  "properties": {
    "iso:country":"GB",
    "wof:name":"BS30 6UN",
    "wof:placetype":"postalcode"
},
  "geometry": {"coordinates":[-2.4776522668839,51.43166328941733],"type":"Point"}
}