{
  "type": "Feature",
  "properties": {
    "iso:country":"GB",
    "wof:name":"DL5 4NR",
    "wof:placetype":"postalcode"
},
  "geometry": {"coordinates":[-1.57298384601062,54.62263946018068],"type":"Point"}
}