{
  "type": "Feature",
  "properties": {
    "iso:country":"GB",
    "wof:name":"SK9 6AP",
    "wof:placetype":"postalcode"
},
  "geometry": {"coordinates":[-2.24951844675277,53.32080415180376],"type":"Point"}
}