{
  "type": "Feature",
  "properties": {
    "date:inception_lower":"1983-07-01",
    "date:inception_upper":"1983-07-31",
    "iso:country":"GB",
    "wof:name":"NR8 6RL",
    "wof:placetype":"postalcode"
},
  "geometry": {"coordinates":[1.221124,52.675157],"type":"Point"}
}