{
  "type": "Feature",
  "properties": {
    "iso:country":"GB",
    "wof:name":"NR8 6RL",
    "wof:placetype":"postalcode"
},
  "geometry": {"coordinates":[1.22112395153075,52.67515667963775],"type":"Point"}
}