{
  "type": "Feature",
  "properties": {
    "date:inception_lower": "2022-02-01",
    "date:inception_upper": "2022-02-01",
    "iso:country": "GB",
    "wof:name": "EH42 1ZX",
    "wof:placetype": "postalcode"
  },
  "geometry": {"coordinates":[-2.498994,55.991463],"type":"Point"}
}
