{
  "type": "Feature",
  "properties": {
    "iso:country": "GB",
    "wof:name": "NW10 5EB",
    "wof:placetype": "postalcode"
  },
  "geometry": {"coordinates":[-0.219825,51.529425],"type":"Point"}
}
