{
  "type": "Feature",
  "properties": {
    "iso:country":"GB",
    "wof:name":"CW2 7QP",
    "wof:placetype":"postalcode"
},
  "geometry": {"coordinates":[-2.44959549663958,53.09611461937134],"type":"Point"}
}