{
  "type": "Feature",
  "properties": {
    "date:inception_lower": "1980-01-01",
    "date:inception_upper": "1980-01-01",
    "iso:country": "GB",
    "wof:name": "CW2 7QP",
    "wof:placetype": "postalcode"
  },
  "geometry": {"coordinates":[-2.449595,53.096115],"type":"Point"}
}
