{
  "type": "Feature",
  "properties": {
    "iso:country": "GB",
    "wof:name": "AB52 6QJ",
    "wof:placetype": "postalcode"
  },
  "geometry": {"coordinates":[-2.618157,57.309523],"type":"Point"}
}
