{
  "type": "Feature",
  "properties": {
    "iso:country":"GB",
    "wof:name":"S21 1GQ",
    "wof:placetype":"postalcode"
},
  "geometry": {"coordinates":[-1.32149900320838,53.31856255807887],"type":"Point"}
}