{
  "type": "Feature",
  "properties": {
    "iso:country":"GB",
    "wof:name":"TS12 2AH",
    "wof:placetype":"postalcode"
},
  "geometry": {"coordinates":[-0.96260112174476,54.55985877271644],"type":"Point"}
}