{
  "type": "Feature",
  "properties": {
    "date:inception_lower": "1991-01-01",
    "date:inception_upper": "1991-01-01",
    "iso:country": "GB",
    "wof:name": "MK7 8EN",
    "wof:placetype": "postalcode"
  },
  "geometry": {"coordinates":[-0.681295,52.017055],"type":"Point"}
}
