{
  "type": "Feature",
  "properties": {
    "iso:country":"GB",
    "wof:name":"MK7 8EN",
    "wof:placetype":"postalcode"
},
  "geometry": {"coordinates":[-0.68129474962187,52.01705493873389],"type":"Point"}
}