{
  "type": "Feature",
  "properties": {
    "iso:country": "GB",
    "wof:name": "CV34 6SW",
    "wof:placetype": "postalcode"
  },
  "geometry": {"coordinates":[-1.535878,52.270288],"type":"Point"}
}
