{
  "type": "Feature",
  "properties": {
    "date:inception_lower": "2003-02-01",
    "date:inception_upper": "2003-02-01",
    "iso:country": "GB",
    "wof:name": "CV34 6SW",
    "wof:placetype": "postalcode"
  },
  "geometry": {"coordinates":[-1.535892,52.27036],"type":"Point"}
}
