{
  "type": "Feature",
  "properties": {
    "date:inception_lower":"2003-02-01",
    "date:inception_upper":"2003-02-28",
    "iso:country":"GB",
    "wof:name":"CV34 6SW",
    "wof:placetype":"postalcode"
},
  "geometry": {"coordinates":[-1.535878,52.270288],"type":"Point"}
}