{
  "type": "Feature",
  "properties": {
    "date:inception_lower":"1980-01-01",
    "date:inception_upper":"1980-01-31",
    "iso:country":"GB",
    "wof:name":"WA6 7HX",
    "wof:placetype":"postalcode"
},
  "geometry": {"coordinates":[-2.708975,53.298939],"type":"Point"}
}