{
  "type": "Feature",
  "properties": {
    "iso:country":"GB",
    "wof:name":"CV2 4QL",
    "wof:placetype":"postalcode"
},
  "geometry": {"coordinates":[-1.49048373030145,52.41640307980837],"type":"Point"}
}