{
  "type": "Feature",
  "properties": {
    "date:inception_lower": "1980-01-01",
    "date:inception_upper": "1980-01-01",
    "iso:country": "GB",
    "wof:name": "RM7 0PS",
    "wof:placetype": "postalcode"
  },
  "geometry": {"coordinates":[0.183587,51.565864],"type":"Point"}
}
