{
  "type": "Feature",
  "properties": {
    "iso:country": "GB",
    "wof:name": "WR8 9DL",
    "wof:placetype": "postalcode"
  },
  "geometry": {"coordinates":[-2.205441,52.11183],"type":"Point"}
}
