{
  "type": "Feature",
  "properties": {
    "date:inception_lower":"1985-10-01",
    "date:inception_upper":"1985-10-31",
    "iso:country":"GB",
    "wof:name":"SY16 3AH",
    "wof:placetype":"postalcode"
},
  "geometry": {"coordinates":[-3.298842,52.516487],"type":"Point"}
}