{
  "type": "Feature",
  "properties": {
    "iso:country": "GB",
    "wof:name": "SY16 3AH",
    "wof:placetype": "postalcode"
  },
  "geometry": {"coordinates":[-3.298842,52.516487],"type":"Point"}
}
