{
  "type": "Feature",
  "properties": {
    "date:inception_lower": "2021-05-01",
    "date:inception_upper": "2021-05-01",
    "iso:country": "GB",
    "wof:name": "PL7 5FL",
    "wof:placetype": "postalcode"
  },
  "geometry": {"coordinates":[-4.015228,50.382476],"type":"Point"}
}
