{
  "type": "Feature",
  "properties": {
    "iso:country":"GB",
    "wof:name":"G63 9LT",
    "wof:placetype":"postalcode"
},
  "geometry": {"coordinates":[-4.37941779291487,56.03965662684553],"type":"Point"}
}