{
  "type": "Feature",
  "properties": {
    "date:inception_lower": "1980-04-01",
    "date:inception_upper": "1980-04-01",
    "iso:country": "GB",
    "wof:name": "G63 9LT",
    "wof:placetype": "postalcode"
  },
  "geometry": {"coordinates":[-4.379418,56.039657],"type":"Point"}
}
