{
  "type": "Feature",
  "properties": {
    "date:inception_lower":"1997-12-01",
    "date:inception_upper":"1997-12-31",
    "iso:country":"GB",
    "wof:name":"BS37 4JX",
    "wof:placetype":"postalcode"
},
  "geometry": {"coordinates":[-2.430265,51.530691],"type":"Point"}
}