{
  "type": "Feature",
  "properties": {
    "date:inception_lower": "2023-02-01",
    "date:inception_upper": "2023-02-01",
    "iso:country": "GB",
    "wof:name": "NP19 4EL",
    "wof:placetype": "postalcode"
  },
  "geometry": {"coordinates":[-2.936588,51.580298],"type":"Point"}
}
