{
  "type": "Feature",
  "properties": {
    "date:inception_lower": "1980-01-01",
    "date:inception_upper": "1980-01-01",
    "iso:country": "GB",
    "wof:name": "LE3 2AB",
    "wof:placetype": "postalcode"
  },
  "geometry": {"coordinates":[-1.150791,52.621181],"type":"Point"}
}
