{
  "type": "Feature",
  "properties": {
    "iso:country":"GB",
    "wof:name":"LE3 2AB",
    "wof:placetype":"postalcode"
},
  "geometry": {"coordinates":[-1.1506024292783,52.62139509916724],"type":"Point"}
}