{
  "type": "Feature",
  "properties": {
    "iso:country":"GB",
    "wof:name":"MK1 1DH",
    "wof:placetype":"postalcode"
},
  "geometry": {"coordinates":[-0.73672583840248,52.00163098487772],"type":"Point"}
}