{
  "type": "Feature",
  "properties": {
    "iso:country": "GB",
    "wof:name": "MK1 1DH",
    "wof:placetype": "postalcode"
  },
  "geometry": {"coordinates":[-0.736726,52.001631],"type":"Point"}
}
