{
  "type": "Feature",
  "properties": {
    "iso:country": "GB",
    "wof:name": "TN16 3QF",
    "wof:placetype": "postalcode"
  },
  "geometry": {"coordinates":[0.02774,51.308616],"type":"Point"}
}
