{
  "type": "Feature",
  "properties": {
    "iso:country":"GB",
    "wof:name":"TN16 3QF",
    "wof:placetype":"postalcode"
},
  "geometry": {"coordinates":[0.0277400709719,51.30861592013198],"type":"Point"}
}