{
  "type": "Feature",
  "properties": {
    "date:inception_lower": "1980-01-01",
    "date:inception_upper": "1980-01-01",
    "iso:country": "GB",
    "wof:name": "TN16 3QF",
    "wof:placetype": "postalcode"
  },
  "geometry": {"coordinates":[0.02774,51.308616],"type":"Point"}
}
