{
  "type": "Feature",
  "properties": {
    "iso:country":"GB",
    "wof:name":"E5 9LW",
    "wof:placetype":"postalcode"
},
  "geometry": {"coordinates":[-0.05613354497227,51.56494572752503],"type":"Point"}
}