{
  "type": "Feature",
  "properties": {
    "iso:country":"GB",
    "wof:name":"IP7 7SB",
    "wof:placetype":"postalcode"
},
  "geometry": {"coordinates":[0.90484890349947,52.10711630452904],"type":"Point"}
}