{
  "type": "Feature",
  "properties": {
    "date:inception_lower": "1980-01-01",
    "date:inception_upper": "1980-01-01",
    "iso:country": "GB",
    "wof:name": "SM2 7HU",
    "wof:placetype": "postalcode"
  },
  "geometry": {"coordinates":[-0.220525,51.345979],"type":"Point"}
}
