{
  "type": "Feature",
  "properties": {
    "iso:country":"GB",
    "wof:name":"SM2 7HU",
    "wof:placetype":"postalcode"
},
  "geometry": {"coordinates":[-0.22052462022042,51.34597881051753],"type":"Point"}
}