{
  "type": "Feature",
  "properties": {
    "date:inception_lower": "1980-01-01",
    "date:inception_upper": "1980-01-01",
    "iso:country": "GB",
    "wof:name": "WV2 4BS",
    "wof:placetype": "postalcode"
  },
  "geometry": {"coordinates":[-2.131268,52.579533],"type":"Point"}
}
