{
  "type": "Feature",
  "properties": {
    "date:inception_lower": "1998-06-01",
    "date:inception_upper": "1998-06-01",
    "iso:country": "GB",
    "wof:name": "YO25 3HG",
    "wof:placetype": "postalcode"
  },
  "geometry": {"coordinates":[-0.611497,54.035896],"type":"Point"}
}
