{
  "type": "Feature",
  "properties": {
    "date:inception_lower":"2005-10-01",
    "date:inception_upper":"2005-10-31",
    "iso:country":"GB",
    "wof:name":"PO18 9BE",
    "wof:placetype":"postalcode"
},
  "geometry": {"coordinates":[-0.826296,50.87259],"type":"Point"}
}