{
  "type": "Feature",
  "properties": {
    "date:inception_lower": "2005-10-01",
    "date:inception_upper": "2005-10-01",
    "iso:country": "GB",
    "wof:name": "PO18 9BE",
    "wof:placetype": "postalcode"
  },
  "geometry": {"coordinates":[-0.826438,50.8726],"type":"Point"}
}
