{
  "type": "Feature",
  "properties": {
    "iso:country":"GB",
    "wof:name":"PO18 9BE",
    "wof:placetype":"postalcode"
},
  "geometry": {"coordinates":[-0.82631449459976,50.8725985224271],"type":"Point"}
}