{
  "type": "Feature",
  "properties": {
    "iso:country":"GB",
    "wof:name":"ST5 8AS",
    "wof:placetype":"postalcode"
},
  "geometry": {"coordinates":[-2.22367064949588,53.03401922126971],"type":"Point"}
}