{
  "type": "Feature",
  "properties": {
    "iso:country": "GB",
    "wof:name": "WA9 5NW",
    "wof:placetype": "postalcode"
  },
  "geometry": {"coordinates":[-2.755016,53.4285],"type":"Point"}
}
