{
  "type": "Feature",
  "properties": {
    "iso:country":"GB",
    "wof:name":"WA9 5NW",
    "wof:placetype":"postalcode"
},
  "geometry": {"coordinates":[-2.75501633089249,53.42850041812483],"type":"Point"}
}