{
  "type": "Feature",
  "properties": {
    "iso:country":"GB",
    "wof:name":"NR30 5DY",
    "wof:placetype":"postalcode"
},
  "geometry": {"coordinates":[1.73154369072716,52.64517498923005],"type":"Point"}
}