{
  "type": "Feature",
  "properties": {
    "iso:country": "GB",
    "wof:name": "DG2 9AP",
    "wof:placetype": "postalcode"
  },
  "geometry": {"coordinates":[-3.626254,55.072053],"type":"Point"}
}
