{
  "type": "Feature",
  "properties": {
    "iso:country":"GB",
    "wof:name":"DG2 9AP",
    "wof:placetype":"postalcode"
},
  "geometry": {"coordinates":[-3.62619216116579,55.07198558298952],"type":"Point"}
}