{
  "type": "Feature",
  "properties": {
    "date:inception_lower":"2013-01-01",
    "date:inception_upper":"2013-01-31",
    "iso:country":"GB",
    "wof:name":"DG2 9AP",
    "wof:placetype":"postalcode"
},
  "geometry": {"coordinates":[-3.626254,55.072053],"type":"Point"}
}