{
  "type": "Feature",
  "properties": {
    "iso:country":"GB",
    "wof:name":"NE28 7LF",
    "wof:placetype":"postalcode"
},
  "geometry": {"coordinates":[-1.51887160704224,54.99337434947582],"type":"Point"}
}