{
  "type": "Feature",
  "properties": {
    "date:inception_lower": "1980-01-01",
    "date:inception_upper": "1980-01-01",
    "iso:country": "GB",
    "wof:name": "SS13 2NJ",
    "wof:placetype": "postalcode"
  },
  "geometry": {"coordinates":[0.514529,51.566854],"type":"Point"}
}
