{
  "type": "Feature",
  "properties": {
    "iso:country":"GB",
    "wof:name":"SS13 2NJ",
    "wof:placetype":"postalcode"
},
  "geometry": {"coordinates":[0.51452941276101,51.56685429307259],"type":"Point"}
}