{
  "type": "Feature",
  "properties": {
    "iso:country": "GB",
    "wof:name": "CW3 9AA",
    "wof:placetype": "postalcode"
  },
  "geometry": {"coordinates":[-2.368478,53.033452],"type":"Point"}
}
