{
  "type": "Feature",
  "properties": {
    "date:inception_lower": "1980-01-01",
    "date:inception_upper": "1980-01-01",
    "iso:country": "GB",
    "wof:name": "LL57 1AN",
    "wof:placetype": "postalcode"
  },
  "geometry": {"coordinates":[-4.122657,53.231166],"type":"Point"}
}
