{
  "type": "Feature",
  "properties": {
    "iso:country":"GB",
    "wof:name":"LL57 1AN",
    "wof:placetype":"postalcode"
},
  "geometry": {"coordinates":[-4.12265738196345,53.23116622367323],"type":"Point"}
}