{
  "type": "Feature",
  "properties": {
    "iso:country":"GB",
    "wof:name":"B92 7LZ",
    "wof:placetype":"postalcode"
},
  "geometry": {"coordinates":[-1.80031977564242,52.44897649253424],"type":"Point"}
}