{
  "type": "Feature",
  "properties": {
    "iso:country":"GB",
    "wof:name":"B30 2NN",
    "wof:placetype":"postalcode"
},
  "geometry": {"coordinates":[-1.92087122166201,52.42337086547744],"type":"Point"}
}