{
  "type": "Feature",
  "properties": {
    "iso:country":"GB",
    "wof:name":"NP19 4NL",
    "wof:placetype":"postalcode"
},
  "geometry": {"coordinates":[-2.95481105427803,51.57968217534887],"type":"Point"}
}