{
  "type": "Feature",
  "properties": {
    "iso:country": "GB",
    "wof:name": "NP19 4NL",
    "wof:placetype": "postalcode"
  },
  "geometry": {"coordinates":[-2.954811,51.579682],"type":"Point"}
}
