{
  "type": "Feature",
  "properties": {
    "iso:country":"GB",
    "wof:name":"N7 9BA",
    "wof:placetype":"postalcode"
},
  "geometry": {"coordinates":[-0.11839237574418,51.54712140231417],"type":"Point"}
}