{
  "type": "Feature",
  "properties": {
    "iso:country":"GB",
    "wof:name":"WA9 5SN",
    "wof:placetype":"postalcode"
},
  "geometry": {"coordinates":[-2.74618906286369,53.43578284716018],"type":"Point"}
}