{
  "type": "Feature",
  "properties": {
    "iso:country": "GB",
    "wof:name": "HU17 5NY",
    "wof:placetype": "postalcode"
  },
  "geometry": {"coordinates":[-0.316235,53.887277],"type":"Point"}
}
