{
  "type": "Feature",
  "properties": {
    "iso:country":"GB",
    "wof:name":"HU17 5NY",
    "wof:placetype":"postalcode"
},
  "geometry": {"coordinates":[-0.31623532057016,53.88727671489445],"type":"Point"}
}