{
  "type": "Feature",
  "properties": {
    "date:inception_lower":"1984-10-01",
    "date:inception_upper":"1984-10-31",
    "iso:country":"GB",
    "wof:name":"HU17 5NY",
    "wof:placetype":"postalcode"
},
  "geometry": {"coordinates":[-0.316235,53.887277],"type":"Point"}
}