{
  "type": "Feature",
  "properties": {
    "iso:country":"GB",
    "wof:name":"PO7 7UN",
    "wof:placetype":"postalcode"
},
  "geometry": {"coordinates":[-1.04149234359649,50.88634387888396],"type":"Point"}
}