{
  "type": "Feature",
  "properties": {
    "date:inception_lower": "1995-07-01",
    "date:inception_upper": "1995-07-01",
    "iso:country": "GB",
    "wof:name": "PO7 7UN",
    "wof:placetype": "postalcode"
  },
  "geometry": {"coordinates":[-1.041492,50.886344],"type":"Point"}
}
