{
  "type": "Feature",
  "properties": {
    "iso:country":"GB",
    "wof:name":"SL4 2AD",
    "wof:placetype":"postalcode"
},
  "geometry": {"coordinates":[-0.60596718644856,51.47731504696701],"type":"Point"}
}