{
  "type": "Feature",
  "properties": {
    "date:inception_lower": "1999-12-01",
    "date:inception_upper": "1999-12-01",
    "iso:country": "GB",
    "wof:name": "FY7 6FZ",
    "wof:placetype": "postalcode"
  },
  "geometry": {"coordinates":[-3.012967,53.919416],"type":"Point"}
}
