{
  "type": "Feature",
  "properties": {
    "iso:country":"GB",
    "wof:name":"FY7 6FZ",
    "wof:placetype":"postalcode"
},
  "geometry": {"coordinates":[-3.01296708165482,53.91941559680519],"type":"Point"}
}