{
  "type": "Feature",
  "properties": {
    "iso:country": "GB",
    "wof:name": "FY7 6FZ",
    "wof:placetype": "postalcode"
  },
  "geometry": {"coordinates":[-3.012967,53.919416],"type":"Point"}
}
