{
  "type": "Feature",
  "properties": {
    "iso:country":"GB",
    "wof:name":"SY12 9EJ",
    "wof:placetype":"postalcode"
},
  "geometry": {"coordinates":[-2.97735250628663,52.95203970160219],"type":"Point"}
}