{
  "type": "Feature",
  "properties": {
    "date:inception_lower":"1993-01-01",
    "date:inception_upper":"1993-01-31",
    "iso:country":"GB",
    "wof:name":"SY12 9EJ",
    "wof:placetype":"postalcode"
},
  "geometry": {"coordinates":[-2.977352,52.95204],"type":"Point"}
}