{
  "type": "Feature",
  "properties": {
    "date:inception_lower": "1980-01-01",
    "date:inception_upper": "1980-01-01",
    "iso:country": "GB",
    "wof:name": "SG9 9LJ",
    "wof:placetype": "postalcode"
  },
  "geometry": {"coordinates":[-0.009585,51.925838],"type":"Point"}
}
