{
  "type": "Feature",
  "properties": {
    "iso:country":"GB",
    "wof:name":"SG9 9LJ",
    "wof:placetype":"postalcode"
},
  "geometry": {"coordinates":[-0.00958538379063,51.92583753397845],"type":"Point"}
}