{
  "type": "Feature",
  "properties": {
    "iso:country":"GB",
    "wof:name":"NP44 1DY",
    "wof:placetype":"postalcode"
},
  "geometry": {"coordinates":[-3.02527239606188,51.66128890573325],"type":"Point"}
}