{
  "type": "Feature",
  "properties": {
    "date:inception_lower": "1999-06-01",
    "date:inception_upper": "1999-06-01",
    "iso:country": "GB",
    "wof:name": "NP20 5DL",
    "wof:placetype": "postalcode"
  },
  "geometry": {"coordinates":[-3.018938,51.588712],"type":"Point"}
}
