{
  "type": "Feature",
  "properties": {
    "date:inception_lower": "1980-01-01",
    "date:inception_upper": "1980-01-01",
    "iso:country": "GB",
    "wof:name": "GU4 7TE",
    "wof:placetype": "postalcode"
  },
  "geometry": {"coordinates":[-0.503978,51.262445],"type":"Point"}
}
