{
  "type": "Feature",
  "properties": {
    "date:inception_lower": "1980-01-01",
    "date:inception_upper": "1980-01-01",
    "iso:country": "GB",
    "wof:name": "HP21 8RS",
    "wof:placetype": "postalcode"
  },
  "geometry": {"coordinates":[-0.807662,51.804229],"type":"Point"}
}
