{
  "type": "Feature",
  "properties": {
    "iso:country":"GB",
    "wof:name":"CH5 3NG",
    "wof:placetype":"postalcode"
},
  "geometry": {"coordinates":[-3.04489018018481,53.16993645216832],"type":"Point"}
}