{
  "type": "Feature",
  "properties": {
    "iso:country":"GB",
    "wof:name":"M20 4TE",
    "wof:placetype":"postalcode"
},
  "geometry": {"coordinates":[-2.21540428281103,53.42652287345765],"type":"Point"}
}