{
  "type": "Feature",
  "properties": {
    "date:inception_lower": "1994-05-01",
    "date:inception_upper": "1994-05-01",
    "iso:country": "GB",
    "wof:name": "M20 4TE",
    "wof:placetype": "postalcode"
  },
  "geometry": {"coordinates":[-2.215404,53.426523],"type":"Point"}
}
