{
  "type": "Feature",
  "properties": {
    "date:inception_lower": "1980-01-01",
    "date:inception_upper": "1980-01-01",
    "iso:country": "GB",
    "wof:name": "HA3 7TG",
    "wof:placetype": "postalcode"
  },
  "geometry": {"coordinates":[-0.33051,51.596623],"type":"Point"}
}
