{
  "type": "Feature",
  "properties": {
    "iso:country":"GB",
    "wof:name":"HA3 7TG",
    "wof:placetype":"postalcode"
},
  "geometry": {"coordinates":[-0.33051018477027,51.59662337660178],"type":"Point"}
}