{
  "type": "Feature",
  "properties": {
    "date:inception_lower":"1980-01-01",
    "date:inception_upper":"1980-01-31",
    "iso:country":"GB",
    "wof:name":"BL8 2RU",
    "wof:placetype":"postalcode"
},
  "geometry": {"coordinates":[-2.320733,53.592177],"type":"Point"}
}