{
  "type": "Feature",
  "properties": {
    "iso:country":"GB",
    "wof:name":"BH9 2LT",
    "wof:placetype":"postalcode"
},
  "geometry": {"coordinates":[-1.88965655218766,50.74301721171236],"type":"Point"}
}