{
  "type": "Feature",
  "properties": {
    "date:inception_lower":"1987-04-01",
    "date:inception_upper":"1987-04-30",
    "iso:country":"GB",
    "wof:name":"EX13 5HU",
    "wof:placetype":"postalcode"
},
  "geometry": {"coordinates":[-2.983942,50.790363],"type":"Point"}
}