{
  "type": "Feature",
  "properties": {
    "iso:country": "GB",
    "wof:name": "EX13 5HU",
    "wof:placetype": "postalcode"
  },
  "geometry": {"coordinates":[-2.983942,50.790363],"type":"Point"}
}
