{
  "type": "Feature",
  "properties": {
    "iso:country":"GB",
    "wof:name":"EX13 5HU",
    "wof:placetype":"postalcode"
},
  "geometry": {"coordinates":[-2.98393547452393,50.79037303503982],"type":"Point"}
}