{
  "type": "Feature",
  "properties": {
    "iso:country":"GB",
    "wof:name":"W1W 8QE",
    "wof:placetype":"postalcode"
},
  "geometry": {"coordinates":[-0.14150599689238,51.51682547091747],"type":"Point"}
}