{
  "type": "Feature",
  "properties": {
    "iso:country":"GB",
    "wof:name":"DH3 3FB",
    "wof:placetype":"postalcode"
},
  "geometry": {"coordinates":[-1.57607626715597,54.85085675155004],"type":"Point"}
}