{
  "type": "Feature",
  "properties": {
    "date:inception_lower":"1992-08-01",
    "date:inception_upper":"1992-08-31",
    "iso:country":"GB",
    "wof:name":"DE75 7PP",
    "wof:placetype":"postalcode"
},
  "geometry": {"coordinates":[-1.359377,53.017845],"type":"Point"}
}