{
  "type": "Feature",
  "properties": {
    "iso:country":"GB",
    "wof:name":"DE75 7PP",
    "wof:placetype":"postalcode"
},
  "geometry": {"coordinates":[-1.35937684138226,53.01784491663562],"type":"Point"}
}