{
  "type": "Feature",
  "properties": {
    "date:inception_lower":"1980-01-01",
    "date:inception_upper":"1980-01-31",
    "iso:country":"GB",
    "wof:name":"HU18 1NQ",
    "wof:placetype":"postalcode"
},
  "geometry": {"coordinates":[-0.164372,53.917468],"type":"Point"}
}