{
  "type": "Feature",
  "properties": {
    "date:inception_lower": "1999-06-01",
    "date:inception_upper": "1999-06-01",
    "iso:country": "GB",
    "wof:name": "CH41 7BE",
    "wof:placetype": "postalcode"
  },
  "geometry": {"coordinates":[-3.060643,53.404882],"type":"Point"}
}
