{
  "type": "Feature",
  "properties": {
    "iso:country": "GB",
    "wof:name": "WS6 7HJ",
    "wof:placetype": "postalcode"
  },
  "geometry": {"coordinates":[-2.035922,52.660722],"type":"Point"}
}
