{
  "type": "Feature",
  "properties": {
    "iso:country":"GB",
    "wof:name":"WS6 7HJ",
    "wof:placetype":"postalcode"
},
  "geometry": {"coordinates":[-2.03622424635238,52.66087675289214],"type":"Point"}
}