{
  "type": "Feature",
  "properties": {
    "iso:country":"GB",
    "wof:name":"HU8 8TU",
    "wof:placetype":"postalcode"
},
  "geometry": {"coordinates":[-0.31915590448648,53.75862987782915],"type":"Point"}
}