{
  "type": "Feature",
  "properties": {
    "iso:country": "GB",
    "wof:name": "WC2A 2AT",
    "wof:placetype": "postalcode"
  },
  "geometry": {"coordinates":[-0.115658,51.513888],"type":"Point"}
}
