{
  "type": "Feature",
  "properties": {
    "iso:country": "GB",
    "wof:name": "TS27 4NE",
    "wof:placetype": "postalcode"
  },
  "geometry": {"coordinates":[-1.294154,54.751043],"type":"Point"}
}
