{
  "type": "Feature",
  "properties": {
    "iso:country":"GB",
    "wof:name":"MK6 2NF",
    "wof:placetype":"postalcode"
},
  "geometry": {"coordinates":[-0.75603516381584,52.03078806125795],"type":"Point"}
}