{
  "type": "Feature",
  "properties": {
    "date:inception_lower": "1981-06-01",
    "date:inception_upper": "1981-06-01",
    "iso:country": "GB",
    "wof:name": "MK6 2NF",
    "wof:placetype": "postalcode"
  },
  "geometry": {"coordinates":[-0.756035,52.030788],"type":"Point"}
}
