{
  "type": "Feature",
  "properties": {
    "date:inception_lower": "1980-01-01",
    "date:inception_upper": "1980-01-01",
    "iso:country": "GB",
    "wof:name": "SA12 6RB",
    "wof:placetype": "postalcode"
  },
  "geometry": {"coordinates":[-3.808058,51.594437],"type":"Point"}
}
