{
  "type": "Feature",
  "properties": {
    "iso:country": "GB",
    "wof:name": "WF15 6EW",
    "wof:placetype": "postalcode"
  },
  "geometry": {"coordinates":[-1.691207,53.713988],"type":"Point"}
}
