{
  "type": "Feature",
  "properties": {
    "iso:country":"GB",
    "wof:name":"WF15 6EW",
    "wof:placetype":"postalcode"
},
  "geometry": {"coordinates":[-1.69100710385141,53.71405325460535],"type":"Point"}
}