{
  "type": "Feature",
  "properties": {
    "date:inception_lower":"2002-06-01",
    "date:inception_upper":"2002-06-30",
    "iso:country":"GB",
    "wof:name":"CO3 0RW",
    "wof:placetype":"postalcode"
},
  "geometry": {"coordinates":[0.834713,51.880501],"type":"Point"}
}