{
  "type": "Feature",
  "properties": {
    "iso:country": "GB",
    "wof:name": "CO3 0RW",
    "wof:placetype": "postalcode"
  },
  "geometry": {"coordinates":[0.834713,51.880501],"type":"Point"}
}
