{
  "type": "Feature",
  "properties": {
    "iso:country":"GB",
    "wof:name":"KY14 6HR",
    "wof:placetype":"postalcode"
},
  "geometry": {"coordinates":[-3.22148099120919,56.34676046299933],"type":"Point"}
}