{
  "type": "Feature",
  "properties": {
    "iso:country":"GB",
    "wof:name":"DL8 3NA",
    "wof:placetype":"postalcode"
},
  "geometry": {"coordinates":[-2.21316500629381,54.29655354764463],"type":"Point"}
}