{
  "type": "Feature",
  "properties": {
    "iso:country": "GB",
    "wof:name": "HX6 2JA",
    "wof:placetype": "postalcode"
  },
  "geometry": {"coordinates":[-1.910993,53.713996],"type":"Point"}
}
