{
  "type": "Feature",
  "properties": {
    "iso:country":"GB",
    "wof:name":"SA17 4HB",
    "wof:placetype":"postalcode"
},
  "geometry": {"coordinates":[-4.24717001551769,51.73100240162096],"type":"Point"}
}