{
  "type": "Feature",
  "properties": {
    "date:inception_lower": "1980-01-01",
    "date:inception_upper": "1980-01-01",
    "iso:country": "GB",
    "wof:name": "SA17 4HB",
    "wof:placetype": "postalcode"
  },
  "geometry": {"coordinates":[-4.24717,51.731002],"type":"Point"}
}
