{
  "type": "Feature",
  "properties": {
    "iso:country":"GB",
    "wof:name":"BN26 6JJ",
    "wof:placetype":"postalcode"
},
  "geometry": {"coordinates":[0.26184838485114,50.82058804742319],"type":"Point"}
}