{
  "type": "Feature",
  "properties": {
    "iso:country":"GB",
    "wof:name":"SO45 2FD",
    "wof:placetype":"postalcode"
},
  "geometry": {"coordinates":[-1.39066968170414,50.82669322835871],"type":"Point"}
}