{
  "type": "Feature",
  "properties": {
    "date:inception_lower": "1994-12-01",
    "date:inception_upper": "1994-12-01",
    "iso:country": "GB",
    "wof:name": "SO45 2FD",
    "wof:placetype": "postalcode"
  },
  "geometry": {"coordinates":[-1.39067,50.826693],"type":"Point"}
}
