{
  "type": "Feature",
  "properties": {
    "iso:country":"GB",
    "wof:name":"PE21 7RN",
    "wof:placetype":"postalcode"
},
  "geometry": {"coordinates":[-0.0206152678816,52.96420499404161],"type":"Point"}
}