{
  "type": "Feature",
  "properties": {
    "iso:country":"GB",
    "wof:name":"UB5 5HE",
    "wof:placetype":"postalcode"
},
  "geometry": {"coordinates":[-0.37185884829727,51.54497763345945],"type":"Point"}
}