{
  "type": "Feature",
  "properties": {
    "iso:country": "GB",
    "wof:name": "NN1 3DZ",
    "wof:placetype": "postalcode"
  },
  "geometry": {"coordinates":[-0.894051,52.244295],"type":"Point"}
}
