{
  "type": "Feature",
  "properties": {
    "iso:country": "GB",
    "wof:name": "PE9 2YF",
    "wof:placetype": "postalcode"
  },
  "geometry": {"coordinates":[-0.483854,52.652553],"type":"Point"}
}
