{
  "type": "Feature",
  "properties": {
    "iso:country":"GB",
    "wof:name":"PE9 2YF",
    "wof:placetype":"postalcode"
},
  "geometry": {"coordinates":[-0.48385425277158,52.65255331826307],"type":"Point"}
}