{
  "type": "Feature",
  "properties": {
    "iso:country": "GB",
    "wof:name": "SA4 8JF",
    "wof:placetype": "postalcode"
  },
  "geometry": {"coordinates":[-4.030281,51.710438],"type":"Point"}
}
