{
  "type": "Feature",
  "properties": {
    "date:inception_lower": "1980-01-01",
    "date:inception_upper": "1980-01-01",
    "iso:country": "GB",
    "wof:name": "IG11 7XD",
    "wof:placetype": "postalcode"
  },
  "geometry": {"coordinates":[0.08508,51.535606],"type":"Point"}
}
