{
  "type": "Feature",
  "properties": {
    "iso:country":"GB",
    "wof:name":"KT3 4EW",
    "wof:placetype":"postalcode"
},
  "geometry": {"coordinates":[-0.25013675618331,51.40467884212299],"type":"Point"}
}