{
  "type": "Feature",
  "properties": {
    "date:inception_lower": "1994-12-01",
    "date:inception_upper": "1994-12-01",
    "iso:country": "GB",
    "wof:name": "KT3 4EW",
    "wof:placetype": "postalcode"
  },
  "geometry": {"coordinates":[-0.24997,51.404658],"type":"Point"}
}
