{
  "type": "Feature",
  "properties": {
    "iso:country":"GB",
    "wof:name":"ST2 0RN",
    "wof:placetype":"postalcode"
},
  "geometry": {"coordinates":[-2.12452521813758,53.01002870767062],"type":"Point"}
}