{
  "type": "Feature",
  "properties": {
    "iso:country": "GB",
    "wof:name": "PO13 9JW",
    "wof:placetype": "postalcode"
  },
  "geometry": {"coordinates":[-1.202296,50.804569],"type":"Point"}
}
