{
  "type": "Feature",
  "properties": {
    "iso:country":"GB",
    "wof:name":"KA25 6JQ",
    "wof:placetype":"postalcode"
},
  "geometry": {"coordinates":[-4.68712284464073,55.74610701575063],"type":"Point"}
}