{
  "type": "Feature",
  "properties": {
    "date:inception_lower": "1980-01-01",
    "date:inception_upper": "1980-01-01",
    "iso:country": "GB",
    "wof:name": "SS4 1PN",
    "wof:placetype": "postalcode"
  },
  "geometry": {"coordinates":[0.681287,51.575146],"type":"Point"}
}
