{
  "type": "Feature",
  "properties": {
    "iso:country": "GB",
    "wof:name": "W1J 7TS",
    "wof:placetype": "postalcode"
  },
  "geometry": {"coordinates":[-0.148689,51.506492],"type":"Point"}
}
