{
  "type": "Feature",
  "properties": {
    "iso:country":"GB",
    "wof:name":"AB11 9QP",
    "wof:placetype":"postalcode"
},
  "geometry": {"coordinates":[-2.08049402723375,57.13732872997087],"type":"Point"}
}