{
  "type": "Feature",
  "properties": {
    "iso:country": "GB",
    "wof:name": "AB41 7RA",
    "wof:placetype": "postalcode"
  },
  "geometry": {"coordinates":[-2.19708,57.328005],"type":"Point"}
}
