{
  "type": "Feature",
  "properties": {
    "iso:country":"GB",
    "wof:name":"AB41 7RA",
    "wof:placetype":"postalcode"
},
  "geometry": {"coordinates":[-2.19708054750336,57.32800546097835],"type":"Point"}
}