{
  "type": "Feature",
  "properties": {
    "date:inception_lower": "2000-12-01",
    "date:inception_upper": "2000-12-01",
    "iso:country": "GB",
    "wof:name": "SY5 9EY",
    "wof:placetype": "postalcode"
  },
  "geometry": {"coordinates":[-2.997997,52.634598],"type":"Point"}
}
