{
  "type": "Feature",
  "properties": {
    "iso:country":"GB",
    "wof:name":"SY5 9EY",
    "wof:placetype":"postalcode"
},
  "geometry": {"coordinates":[-2.99799662161513,52.63459849071033],"type":"Point"}
}