{
  "type": "Feature",
  "properties": {
    "iso:country": "GB",
    "wof:name": "SW15 3QH",
    "wof:placetype": "postalcode"
  },
  "geometry": {"coordinates":[-0.258962,51.426689],"type":"Point"}
}
