{
  "type": "Feature",
  "properties": {
    "iso:country":"GB",
    "wof:name":"SW15 3QH",
    "wof:placetype":"postalcode"
},
  "geometry": {"coordinates":[-0.25896252165699,51.42668907501998],"type":"Point"}
}