{
  "type": "Feature",
  "properties": {
    "date:inception_lower": "1980-01-01",
    "date:inception_upper": "1980-01-01",
    "iso:country": "GB",
    "wof:name": "S61 3AF",
    "wof:placetype": "postalcode"
  },
  "geometry": {"coordinates":[-1.397975,53.448042],"type":"Point"}
}
