{
  "type": "Feature",
  "properties": {
    "iso:country": "GB",
    "wof:name": "S61 3AF",
    "wof:placetype": "postalcode"
  },
  "geometry": {"coordinates":[-1.397975,53.448042],"type":"Point"}
}
