{
  "type": "Feature",
  "properties": {
    "iso:country": "GB",
    "wof:name": "SN5 4AT",
    "wof:placetype": "postalcode"
  },
  "geometry": {"coordinates":[-1.87197,51.586376],"type":"Point"}
}
