{
  "type": "Feature",
  "properties": {
    "date:inception_lower": "2000-06-01",
    "date:inception_upper": "2000-06-01",
    "iso:country": "GB",
    "wof:name": "SN5 4AT",
    "wof:placetype": "postalcode"
  },
  "geometry": {"coordinates":[-1.87197,51.586376],"type":"Point"}
}
