{
  "type": "Feature",
  "properties": {
    "iso:country":"GB",
    "wof:name":"SN5 4AT",
    "wof:placetype":"postalcode"
},
  "geometry": {"coordinates":[-1.87197039273565,51.5863756249361],"type":"Point"}
}