{
  "type": "Feature",
  "properties": {
    "iso:country":"GB",
    "wof:name":"KT6 6JP",
    "wof:placetype":"postalcode"
},
  "geometry": {"coordinates":[-0.30912130108304,51.38809930152975],"type":"Point"}
}