{
  "type": "Feature",
  "properties": {
    "date:inception_lower": "2004-03-01",
    "date:inception_upper": "2004-03-01",
    "iso:country": "GB",
    "wof:name": "KT6 6JP",
    "wof:placetype": "postalcode"
  },
  "geometry": {"coordinates":[-0.3091,51.388062],"type":"Point"}
}
