{
  "type": "Feature",
  "properties": {
    "date:inception_lower": "1980-01-01",
    "date:inception_upper": "1980-01-01",
    "iso:country": "GB",
    "wof:name": "GL53 7DF",
    "wof:placetype": "postalcode"
  },
  "geometry": {"coordinates":[-2.06861,51.885728],"type":"Point"}
}
