{
  "type": "Feature",
  "properties": {
    "iso:country": "GB",
    "wof:name": "GL53 7DF",
    "wof:placetype": "postalcode"
  },
  "geometry": {"coordinates":[-2.068663,51.886413],"type":"Point"}
}
