{
  "type": "Feature",
  "properties": {
    "iso:country": "GB",
    "wof:name": "FK9 4DA",
    "wof:placetype": "postalcode"
  },
  "geometry": {"coordinates":[-3.948759,56.150594],"type":"Point"}
}
