{
  "type": "Feature",
  "properties": {
    "iso:country": "GB",
    "wof:name": "SO14 0AH",
    "wof:placetype": "postalcode"
  },
  "geometry": {"coordinates":[-1.399841,50.912386],"type":"Point"}
}
