{
  "type": "Feature",
  "properties": {
    "iso:country":"GB",
    "wof:name":"SO14 0AH",
    "wof:placetype":"postalcode"
},
  "geometry": {"coordinates":[-1.39982236631864,50.91234062126556],"type":"Point"}
}