{
  "type": "Feature",
  "properties": {
    "iso:country":"GB",
    "wof:name":"DG2 7AL",
    "wof:placetype":"postalcode"
},
  "geometry": {"coordinates":[-3.62418886321953,55.06699741780599],"type":"Point"}
}