{
  "type": "Feature",
  "properties": {
    "date:inception_lower":"1980-01-01",
    "date:inception_upper":"1980-01-31",
    "iso:country":"GB",
    "wof:name":"LE9 6NB",
    "wof:placetype":"postalcode"
},
  "geometry": {"coordinates":[-1.211256,52.522169],"type":"Point"}
}