{
  "type": "Feature",
  "properties": {
    "iso:country":"GB",
    "wof:name":"LE9 6NB",
    "wof:placetype":"postalcode"
},
  "geometry": {"coordinates":[-1.21096758001925,52.52231963398386],"type":"Point"}
}