{
  "type": "Feature",
  "properties": {
    "iso:country": "GB",
    "wof:name": "S41 7AF",
    "wof:placetype": "postalcode"
  },
  "geometry": {"coordinates":[-1.44441,53.246955],"type":"Point"}
}
