{
  "type": "Feature",
  "properties": {
    "iso:country": "GB",
    "wof:name": "RG12 2GQ",
    "wof:placetype": "postalcode"
  },
  "geometry": {"coordinates":[-0.73904,51.418063],"type":"Point"}
}
