{
  "type": "Feature",
  "properties": {
    "iso:country": "GB",
    "wof:name": "TA4 4AT",
    "wof:placetype": "postalcode"
  },
  "geometry": {"coordinates":[-3.310018,51.165839],"type":"Point"}
}
