{
  "type": "Feature",
  "properties": {
    "iso:country": "GB",
    "wof:name": "TA4 4AT",
    "wof:placetype": "postalcode"
  },
  "geometry": {"coordinates":[-3.310297,51.16601],"type":"Point"}
}
