{
  "type": "Feature",
  "properties": {
    "iso:country":"GB",
    "wof:name":"TA4 4AT",
    "wof:placetype":"postalcode"
},
  "geometry": {"coordinates":[-3.31029675131719,51.16600962314887],"type":"Point"}
}