{
  "type": "Feature",
  "properties": {
    "date:inception_lower": "2008-01-01",
    "date:inception_upper": "2008-01-01",
    "iso:country": "GB",
    "wof:name": "AB51 5QX",
    "wof:placetype": "postalcode"
  },
  "geometry": {"coordinates":[-2.41059,57.2911],"type":"Point"}
}
