{
  "type": "Feature",
  "properties": {
    "iso:country":"GB",
    "wof:name":"S73 8LP",
    "wof:placetype":"postalcode"
},
  "geometry": {"coordinates":[-1.41056595890565,53.52830958237045],"type":"Point"}
}