{
  "type": "Feature",
  "properties": {
    "iso:country":"GB",
    "wof:name":"NN6 6DU",
    "wof:placetype":"postalcode"
},
  "geometry": {"coordinates":[-0.99030996678619,52.39316018267157],"type":"Point"}
}