{
  "type": "Feature",
  "properties": {
    "date:inception_lower":"2010-07-01",
    "date:inception_upper":"2010-07-31",
    "iso:country":"GB",
    "wof:name":"NN6 6DU",
    "wof:placetype":"postalcode"
},
  "geometry": {"coordinates":[-0.99031,52.39316],"type":"Point"}
}