{
  "type": "Feature",
  "properties": {
    "iso:country": "GB",
    "wof:name": "NN6 6DU",
    "wof:placetype": "postalcode"
  },
  "geometry": {"coordinates":[-0.99031,52.39316],"type":"Point"}
}
