{
  "type": "Feature",
  "properties": {
    "date:inception_lower": "1997-06-01",
    "date:inception_upper": "1997-06-01",
    "iso:country": "GB",
    "wof:name": "LL22 7LQ",
    "wof:placetype": "postalcode"
  },
  "geometry": {"coordinates":[-3.582127,53.287197],"type":"Point"}
}
