{
  "type": "Feature",
  "properties": {
    "iso:country":"GB",
    "wof:name":"LL22 7LQ",
    "wof:placetype":"postalcode"
},
  "geometry": {"coordinates":[-3.58212364383946,53.28717950932364],"type":"Point"}
}