{
  "type": "Feature",
  "properties": {
    "iso:country": "GB",
    "wof:name": "LL22 7LQ",
    "wof:placetype": "postalcode"
  },
  "geometry": {"coordinates":[-3.582051,53.28718],"type":"Point"}
}
