{
  "type": "Feature",
  "properties": {
    "iso:country": "GB",
    "wof:name": "MK43 8TS",
    "wof:placetype": "postalcode"
  },
  "geometry": {"coordinates":[-0.559844,52.142602],"type":"Point"}
}
