{
  "type": "Feature",
  "properties": {
    "date:inception_lower":"1996-06-01",
    "date:inception_upper":"1996-06-30",
    "iso:country":"GB",
    "wof:name":"AB43 8XS",
    "wof:placetype":"postalcode"
},
  "geometry": {"coordinates":[-1.959111,57.635368],"type":"Point"}
}