{
  "type": "Feature",
  "properties": {
    "iso:country":"GB",
    "wof:name":"OX18 3JG",
    "wof:placetype":"postalcode"
},
  "geometry": {"coordinates":[-1.59552094653293,51.75911845638131],"type":"Point"}
}