{
  "type": "Feature",
  "properties": {
    "iso:country": "GB",
    "wof:name": "RH20 1PA",
    "wof:placetype": "postalcode"
  },
  "geometry": {"coordinates":[-0.562381,50.911086],"type":"Point"}
}
