{
  "type": "Feature",
  "properties": {
    "iso:country":"GB",
    "wof:name":"M30 9GH",
    "wof:placetype":"postalcode"
},
  "geometry": {"coordinates":[-2.35066239035826,53.48816892947582],"type":"Point"}
}