{
  "type": "Feature",
  "properties": {
    "iso:country": "GB",
    "wof:name": "M30 9GH",
    "wof:placetype": "postalcode"
  },
  "geometry": {"coordinates":[-2.350662,53.488169],"type":"Point"}
}
