{
  "type": "Feature",
  "properties": {
    "date:inception_lower": "1980-01-01",
    "date:inception_upper": "1980-01-01",
    "iso:country": "GB",
    "wof:name": "LE15 9HX",
    "wof:placetype": "postalcode"
  },
  "geometry": {"coordinates":[-0.66197,52.568966],"type":"Point"}
}
