{
  "type": "Feature",
  "properties": {
    "iso:country": "GB",
    "wof:name": "LE15 9HX",
    "wof:placetype": "postalcode"
  },
  "geometry": {"coordinates":[-0.66197,52.568966],"type":"Point"}
}
