{
  "type": "Feature",
  "properties": {
    "date:inception_lower":"1980-01-01",
    "date:inception_upper":"1980-01-31",
    "iso:country":"GB",
    "wof:name":"LS29 7NR",
    "wof:placetype":"postalcode"
},
  "geometry": {"coordinates":[-1.750892,53.910481],"type":"Point"}
}