{
  "type": "Feature",
  "properties": {
    "iso:country": "GB",
    "wof:name": "LE11 2JA",
    "wof:placetype": "postalcode"
  },
  "geometry": {"coordinates":[-1.207039,52.756553],"type":"Point"}
}
