{
  "type": "Feature",
  "properties": {
    "iso:country":"GB",
    "wof:name":"SE8 3NA",
    "wof:placetype":"postalcode"
},
  "geometry": {"coordinates":[-0.03155095910652,51.48430373588652],"type":"Point"}
}