{
  "type": "Feature",
  "properties": {
    "date:inception_lower":"1998-06-01",
    "date:inception_upper":"1998-06-30",
    "iso:country":"GB",
    "wof:name":"SE8 3NA",
    "wof:placetype":"postalcode"
},
  "geometry": {"coordinates":[-0.031551,51.484304],"type":"Point"}
}