{
  "type": "Feature",
  "properties": {
    "iso:country": "GB",
    "wof:name": "SE8 3NA",
    "wof:placetype": "postalcode"
  },
  "geometry": {"coordinates":[-0.031551,51.484304],"type":"Point"}
}
