{
  "type": "Feature",
  "properties": {
    "iso:country":"GB",
    "wof:name":"LL48 6EL",
    "wof:placetype":"postalcode"
},
  "geometry": {"coordinates":[-4.08962167237652,52.92334202259055],"type":"Point"}
}