{
  "type": "Feature",
  "properties": {
    "date:inception_lower": "1980-01-01",
    "date:inception_upper": "1980-01-01",
    "iso:country": "GB",
    "wof:name": "LL48 6EL",
    "wof:placetype": "postalcode"
  },
  "geometry": {"coordinates":[-4.089622,52.923342],"type":"Point"}
}
