{
  "type": "Feature",
  "properties": {
    "iso:country":"GB",
    "wof:name":"DT3 5NH",
    "wof:placetype":"postalcode"
},
  "geometry": {"coordinates":[-2.46888672410645,50.6586816358887],"type":"Point"}
}