{
  "type": "Feature",
  "properties": {
    "iso:country": "GB",
    "wof:name": "DT3 5NH",
    "wof:placetype": "postalcode"
  },
  "geometry": {"coordinates":[-2.469208,50.658517],"type":"Point"}
}
