{
  "type": "Feature",
  "properties": {
    "date:inception_lower": "1997-12-01",
    "date:inception_upper": "1997-12-01",
    "iso:country": "GB",
    "wof:name": "DT3 5NH",
    "wof:placetype": "postalcode"
  },
  "geometry": {"coordinates":[-2.469208,50.658517],"type":"Point"}
}
