{
  "type": "Feature",
  "properties": {
    "iso:country":"GB",
    "wof:name":"CH43 0RA",
    "wof:placetype":"postalcode"
},
  "geometry": {"coordinates":[-3.04723585163101,53.36672502032368],"type":"Point"}
}