{
  "type": "Feature",
  "properties": {
    "date:inception_lower": "1995-12-01",
    "date:inception_upper": "1995-12-01",
    "iso:country": "GB",
    "wof:name": "DD2 1XF",
    "wof:placetype": "postalcode"
  },
  "geometry": {"coordinates":[-3.054977,56.463258],"type":"Point"}
}
