{
  "type": "Feature",
  "properties": {
    "date:inception_lower":"1995-12-01",
    "date:inception_upper":"1995-12-31",
    "iso:country":"GB",
    "wof:name":"DD2 1XF",
    "wof:placetype":"postalcode"
},
  "geometry": {"coordinates":[-3.055865,56.463709],"type":"Point"}
}