{
  "type": "Feature",
  "properties": {
    "iso:country": "GB",
    "wof:name": "DD2 1XF",
    "wof:placetype": "postalcode"
  },
  "geometry": {"coordinates":[-3.054977,56.463258],"type":"Point"}
}
