{
  "type": "Feature",
  "properties": {
    "date:inception_lower":"1980-01-01",
    "date:inception_upper":"1980-01-31",
    "iso:country":"GB",
    "wof:name":"SP5 1HT",
    "wof:placetype":"postalcode"
},
  "geometry": {"coordinates":[-1.644487,51.041653],"type":"Point"}
}