{
  "type": "Feature",
  "properties": {
    "iso:country":"GB",
    "wof:name":"SP5 1HT",
    "wof:placetype":"postalcode"
},
  "geometry": {"coordinates":[-1.64448705611776,51.04165258459101],"type":"Point"}
}