{
  "type": "Feature",
  "properties": {
    "iso:country":"GB",
    "wof:name":"TW5 0LN",
    "wof:placetype":"postalcode"
},
  "geometry": {"coordinates":[-0.37799657807279,51.48549798461063],"type":"Point"}
}