{
  "type": "Feature",
  "properties": {
    "iso:country":"GB",
    "wof:name":"OX4 4EF",
    "wof:placetype":"postalcode"
},
  "geometry": {"coordinates":[-1.23681825939579,51.73031891682885],"type":"Point"}
}