{
  "type": "Feature",
  "properties": {
    "date:inception_lower": "1999-06-01",
    "date:inception_upper": "1999-06-01",
    "iso:country": "GB",
    "wof:name": "GL55 6JT",
    "wof:placetype": "postalcode"
  },
  "geometry": {"coordinates":[-1.765306,52.053356],"type":"Point"}
}
