{
  "type": "Feature",
  "properties": {
    "iso:country":"GB",
    "wof:name":"EH1 3NX",
    "wof:placetype":"postalcode"
},
  "geometry": {"coordinates":[-3.1854566787731,55.95971424304697],"type":"Point"}
}