{
  "type": "Feature",
  "properties": {
    "iso:country":"GB",
    "wof:name":"CA3 9SX",
    "wof:placetype":"postalcode"
},
  "geometry": {"coordinates":[-2.94195133532498,54.91326515103873],"type":"Point"}
}