{
  "type": "Feature",
  "properties": {
    "date:inception_lower": "2003-03-01",
    "date:inception_upper": "2003-03-01",
    "iso:country": "GB",
    "wof:name": "NN5 6GD",
    "wof:placetype": "postalcode"
  },
  "geometry": {"coordinates":[-0.963952,52.247743],"type":"Point"}
}
