{
  "type": "Feature",
  "properties": {
    "iso:country":"GB",
    "wof:name":"AB31 5TN",
    "wof:placetype":"postalcode"
},
  "geometry": {"coordinates":[-2.49604872464059,57.05160730297182],"type":"Point"}
}