{
  "type": "Feature",
  "properties": {
    "date:inception_lower":"1980-01-01",
    "date:inception_upper":"1980-01-31",
    "iso:country":"GB",
    "wof:name":"BD2 1HX",
    "wof:placetype":"postalcode"
},
  "geometry": {"coordinates":[-1.739765,53.822151],"type":"Point"}
}