{
  "type": "Feature",
  "properties": {
    "iso:country":"GB",
    "wof:name":"BD2 1HX",
    "wof:placetype":"postalcode"
},
  "geometry": {"coordinates":[-1.73976465870222,53.82215112823781],"type":"Point"}
}