{
  "type": "Feature",
  "properties": {
    "iso:country": "GB",
    "wof:name": "NE66 1SP",
    "wof:placetype": "postalcode"
  },
  "geometry": {"coordinates":[-1.7072,55.412716],"type":"Point"}
}
