{
  "type": "Feature",
  "properties": {
    "iso:country":"GB",
    "wof:name":"NE66 1SP",
    "wof:placetype":"postalcode"
},
  "geometry": {"coordinates":[-1.7071999851602,55.41271556025784],"type":"Point"}
}