{
  "type": "Feature",
  "properties": {
    "iso:country":"GB",
    "wof:name":"WS9 0RW",
    "wof:placetype":"postalcode"
},
  "geometry": {"coordinates":[-1.91481150397729,52.59978470375084],"type":"Point"}
}