{
  "type": "Feature",
  "properties": {
    "iso:country":"GB",
    "wof:name":"SW19 1BJ",
    "wof:placetype":"postalcode"
},
  "geometry": {"coordinates":[-0.18474249641773,51.41749676090998],"type":"Point"}
}