{
  "type": "Feature",
  "properties": {
    "iso:country":"GB",
    "wof:name":"PO30 4AD",
    "wof:placetype":"postalcode"
},
  "geometry": {"coordinates":[-1.37414874602263,50.64010504843534],"type":"Point"}
}