{
  "type": "Feature",
  "properties": {
    "date:inception_lower": "1980-01-01",
    "date:inception_upper": "1980-01-01",
    "iso:country": "GB",
    "wof:name": "PO30 4AD",
    "wof:placetype": "postalcode"
  },
  "geometry": {"coordinates":[-1.374149,50.640105],"type":"Point"}
}
