{
  "type": "Feature",
  "properties": {
    "date:inception_lower": "2021-11-01",
    "date:inception_upper": "2021-11-01",
    "iso:country": "GB",
    "wof:name": "CH8 7FJ",
    "wof:placetype": "postalcode"
  },
  "geometry": {"coordinates":[-3.220609,53.27255],"type":"Point"}
}
