{
  "type": "Feature",
  "properties": {
    "iso:country":"GB",
    "wof:name":"SW7 5HF",
    "wof:placetype":"postalcode"
},
  "geometry": {"coordinates":[-0.17908259188672,51.49799111101225],"type":"Point"}
}