{
  "type": "Feature",
  "properties": {
    "iso:country":"GB",
    "wof:name":"L21 8PG",
    "wof:placetype":"postalcode"
},
  "geometry": {"coordinates":[-2.99567655326098,53.46478609000609],"type":"Point"}
}