{
  "type": "Feature",
  "properties": {
    "iso:country":"GB",
    "wof:name":"PO9 2EA",
    "wof:placetype":"postalcode"
},
  "geometry": {"coordinates":[-0.98099689465779,50.8630710196266],"type":"Point"}
}