{
  "type": "Feature",
  "properties": {
    "iso:country":"GB",
    "wof:name":"CF39 8AQ",
    "wof:placetype":"postalcode"
},
  "geometry": {"coordinates":[-3.43208237197402,51.57427904355987],"type":"Point"}
}