{
  "type": "Feature",
  "properties": {
    "iso:country": "GB",
    "wof:name": "CF39 8AQ",
    "wof:placetype": "postalcode"
  },
  "geometry": {"coordinates":[-3.432082,51.574279],"type":"Point"}
}
