{
  "type": "Feature",
  "properties": {
    "iso:country":"GB",
    "wof:name":"DA17 6AR",
    "wof:placetype":"postalcode"
},
  "geometry": {"coordinates":[0.16850198180719,51.49807678953271],"type":"Point"}
}