{
  "type": "Feature",
  "properties": {
    "date:inception_lower":"1980-01-01",
    "date:inception_upper":"1980-01-31",
    "iso:country":"GB",
    "wof:name":"LL49 9NA",
    "wof:placetype":"postalcode"
},
  "geometry": {"coordinates":[-4.12647,52.924531],"type":"Point"}
}