{
  "type": "Feature",
  "properties": {
    "iso:country":"GB",
    "wof:name":"LL49 9NA",
    "wof:placetype":"postalcode"
},
  "geometry": {"coordinates":[-4.12647029003681,52.92453108567164],"type":"Point"}
}