{
  "type": "Feature",
  "properties": {
    "iso:country":"GB",
    "wof:name":"CM2 8JE",
    "wof:placetype":"postalcode"
},
  "geometry": {"coordinates":[0.50187155538817,51.70936162317259],"type":"Point"}
}