{
  "type": "Feature",
  "properties": {
    "iso:country":"GB",
    "wof:name":"LL65 4AY",
    "wof:placetype":"postalcode"
},
  "geometry": {"coordinates":[-4.49789385222636,53.34364199659968],"type":"Point"}
}