{
  "type": "Feature",
  "properties": {
    "iso:country": "GB",
    "wof:name": "LL65 4AY",
    "wof:placetype": "postalcode"
  },
  "geometry": {"coordinates":[-4.497894,53.343642],"type":"Point"}
}
