{
  "type": "Feature",
  "properties": {
    "iso:country":"GB",
    "wof:name":"SS16 6SF",
    "wof:placetype":"postalcode"
},
  "geometry": {"coordinates":[0.40792904355834,51.56132081167451],"type":"Point"}
}