{
  "type": "Feature",
  "properties": {
    "iso:country":"GB",
    "wof:name":"BR3 6YE",
    "wof:placetype":"postalcode"
},
  "geometry": {"coordinates":[-0.00915658039137,51.40384514513141],"type":"Point"}
}