{
  "type": "Feature",
  "properties": {
    "iso:country": "GB",
    "wof:name": "BR3 6YE",
    "wof:placetype": "postalcode"
  },
  "geometry": {"coordinates":[-0.009157,51.403845],"type":"Point"}
}
