{
  "type": "Feature",
  "properties": {
    "iso:country":"GB",
    "wof:name":"TD15 2AZ",
    "wof:placetype":"postalcode"
},
  "geometry": {"coordinates":[-2.00304962498472,55.76021178920833],"type":"Point"}
}