{
  "type": "Feature",
  "properties": {
    "date:inception_lower": "2023-04-01",
    "date:inception_upper": "2023-04-01",
    "iso:country": "GB",
    "wof:name": "EX8 5DQ",
    "wof:placetype": "postalcode"
  },
  "geometry": {"coordinates":[-3.406904,50.651173],"type":"Point"}
}
