{
  "type": "Feature",
  "properties": {
    "date:inception_lower": "1991-01-01",
    "date:inception_upper": "1991-01-01",
    "iso:country": "GB",
    "wof:name": "NE49 9PB",
    "wof:placetype": "postalcode"
  },
  "geometry": {"coordinates":[-2.467707,54.973421],"type":"Point"}
}
