{
  "type": "Feature",
  "properties": {
    "iso:country":"GB",
    "wof:name":"NE49 9PB",
    "wof:placetype":"postalcode"
},
  "geometry": {"coordinates":[-2.4677065563291,54.97342118643429],"type":"Point"}
}