{
  "type": "Feature",
  "properties": {
    "iso:country": "GB",
    "wof:name": "CO5 8JN",
    "wof:placetype": "postalcode"
  },
  "geometry": {"coordinates":[0.906918,51.78086],"type":"Point"}
}
