{
  "type": "Feature",
  "properties": {
    "iso:country":"GB",
    "wof:name":"CO5 8JN",
    "wof:placetype":"postalcode"
},
  "geometry": {"coordinates":[0.906917993056,51.78086009768339],"type":"Point"}
}