{
  "type": "Feature",
  "properties": {
    "iso:country":"GB",
    "wof:name":"M15 6JT",
    "wof:placetype":"postalcode"
},
  "geometry": {"coordinates":[-2.23997573663056,53.46054244904807],"type":"Point"}
}