{
  "type": "Feature",
  "properties": {
    "date:inception_lower":"1980-01-01",
    "date:inception_upper":"1980-01-31",
    "iso:country":"GB",
    "wof:name":"M15 6JT",
    "wof:placetype":"postalcode"
},
  "geometry": {"coordinates":[-2.239976,53.460542],"type":"Point"}
}