{
  "type": "Feature",
  "properties": {
    "iso:country":"GB",
    "wof:name":"S8 0RU",
    "wof:placetype":"postalcode"
},
  "geometry": {"coordinates":[-1.48180860001827,53.35298413694895],"type":"Point"}
}