{
  "type": "Feature",
  "properties": {
    "iso:country":"GB",
    "wof:name":"HX7 7NG",
    "wof:placetype":"postalcode"
},
  "geometry": {"coordinates":[-2.02041973974969,53.75017671686977],"type":"Point"}
}