{
  "type": "Feature",
  "properties": {
    "date:inception_lower":"1980-01-01",
    "date:inception_upper":"1980-01-31",
    "iso:country":"GB",
    "wof:name":"HX7 7NG",
    "wof:placetype":"postalcode"
},
  "geometry": {"coordinates":[-2.02042,53.750177],"type":"Point"}
}