{
  "type": "Feature",
  "properties": {
    "date:inception_lower": "2016-11-01",
    "date:inception_upper": "2016-11-01",
    "iso:country": "GB",
    "wof:name": "DE73 6WS",
    "wof:placetype": "postalcode"
  },
  "geometry": {"coordinates":[-1.434401,52.861172],"type":"Point"}
}
