{
  "type": "Feature",
  "properties": {
    "iso:country": "GB",
    "wof:name": "BA1 7SZ",
    "wof:placetype": "postalcode"
  },
  "geometry": {"coordinates":[-2.299394,51.400433],"type":"Point"}
}
