{
  "type": "Feature",
  "properties": {
    "iso:country":"GB",
    "wof:name":"BA1 7SZ",
    "wof:placetype":"postalcode"
},
  "geometry": {"coordinates":[-2.29939385769626,51.40043311416781],"type":"Point"}
}