{
  "type": "Feature",
  "properties": {
    "iso:country": "GB",
    "wof:name": "NP13 3BG",
    "wof:placetype": "postalcode"
  },
  "geometry": {"coordinates":[-3.162933,51.764263],"type":"Point"}
}
