{
  "type": "Feature",
  "properties": {
    "iso:country":"GB",
    "wof:name":"SM6 9LZ",
    "wof:placetype":"postalcode"
},
  "geometry": {"coordinates":[-0.14442570587488,51.34974399118349],"type":"Point"}
}