{
  "type": "Feature",
  "properties": {
    "date:inception_lower": "1991-01-01",
    "date:inception_upper": "1991-01-01",
    "iso:country": "GB",
    "wof:name": "SM6 9LZ",
    "wof:placetype": "postalcode"
  },
  "geometry": {"coordinates":[-0.144426,51.349744],"type":"Point"}
}
