{
  "type": "Feature",
  "properties": {
    "iso:country": "GB",
    "wof:name": "YO51 9UU",
    "wof:placetype": "postalcode"
  },
  "geometry": {"coordinates":[-1.399797,54.087603],"type":"Point"}
}
