{
  "type": "Feature",
  "properties": {
    "iso:country":"GB",
    "wof:name":"BH20 4SQ",
    "wof:placetype":"postalcode"
},
  "geometry": {"coordinates":[-2.11702966655304,50.69828960718152],"type":"Point"}
}