{
  "type": "Feature",
  "properties": {
    "iso:country": "GB",
    "wof:name": "BH20 4SQ",
    "wof:placetype": "postalcode"
  },
  "geometry": {"coordinates":[-2.11703,50.69829],"type":"Point"}
}
