{
  "type": "Feature",
  "properties": {
    "iso:country":"GB",
    "wof:name":"BN1 1YW",
    "wof:placetype":"postalcode"
},
  "geometry": {"coordinates":[-0.13688900038078,50.82552448614987],"type":"Point"}
}