{
  "type": "Feature",
  "properties": {
    "date:inception_lower": "1996-06-01",
    "date:inception_upper": "1996-06-01",
    "iso:country": "GB",
    "wof:name": "AB38 9LH",
    "wof:placetype": "postalcode"
  },
  "geometry": {"coordinates":[-3.221781,57.4681],"type":"Point"}
}
