{
  "type": "Feature",
  "properties": {
    "iso:country":"GB",
    "wof:name":"AB38 9LH",
    "wof:placetype":"postalcode"
},
  "geometry": {"coordinates":[-3.2217814910184,57.46810000564359],"type":"Point"}
}