{
  "type": "Feature",
  "properties": {
    "iso:country":"GB",
    "wof:name":"TW4 5EG",
    "wof:placetype":"postalcode"
},
  "geometry": {"coordinates":[-0.38133362310425,51.46080625850577],"type":"Point"}
}