{
  "type": "Feature",
  "properties": {
    "iso:country": "GB",
    "wof:name": "PE25 3DL",
    "wof:placetype": "postalcode"
  },
  "geometry": {"coordinates":[0.340657,53.133281],"type":"Point"}
}
