{
  "type": "Feature",
  "properties": {
    "iso:country": "GB",
    "wof:name": "EX6 7BG",
    "wof:placetype": "postalcode"
  },
  "geometry": {"coordinates":[-3.641792,50.694796],"type":"Point"}
}
