{
  "type": "Feature",
  "properties": {
    "iso:country": "GB",
    "wof:name": "BB8 9DN",
    "wof:placetype": "postalcode"
  },
  "geometry": {"coordinates":[-2.181564,53.863375],"type":"Point"}
}
