{
  "type": "Feature",
  "properties": {
    "date:inception_lower": "2017-10-01",
    "date:inception_upper": "2017-10-01",
    "iso:country": "GB",
    "wof:name": "BB8 9DN",
    "wof:placetype": "postalcode"
  },
  "geometry": {"coordinates":[-2.181564,53.863366],"type":"Point"}
}
