{
  "type": "Feature",
  "properties": {
    "iso:country":"GB",
    "wof:name":"HX2 9JA",
    "wof:placetype":"postalcode"
},
  "geometry": {"coordinates":[-1.88935153571248,53.76217162654768],"type":"Point"}
}