{
  "type": "Feature",
  "properties": {
    "iso:country": "GB",
    "wof:name": "HX2 9JA",
    "wof:placetype": "postalcode"
  },
  "geometry": {"coordinates":[-1.889351,53.762172],"type":"Point"}
}
