{
  "type": "Feature",
  "properties": {
    "iso:country":"GB",
    "wof:name":"PR7 2RA",
    "wof:placetype":"postalcode"
},
  "geometry": {"coordinates":[-2.65426696990477,53.64055901362399],"type":"Point"}
}