{
  "type": "Feature",
  "properties": {
    "date:inception_lower": "2023-01-01",
    "date:inception_upper": "2023-01-01",
    "iso:country": "GB",
    "wof:name": "SY21 8FH",
    "wof:placetype": "postalcode"
  },
  "geometry": {"coordinates":[-3.072178,52.695835],"type":"Point"}
}
