{
  "type": "Feature",
  "properties": {
    "iso:country":"GB",
    "wof:name":"WF12 7QL",
    "wof:placetype":"postalcode"
},
  "geometry": {"coordinates":[-1.60307176813567,53.70388946811212],"type":"Point"}
}