{
  "type": "Feature",
  "properties": {
    "iso:country":"GB",
    "wof:name":"IV3 8GY",
    "wof:placetype":"postalcode"
},
  "geometry": {"coordinates":[-4.32465134852836,57.4236600451625],"type":"Point"}
}