{
  "type": "Feature",
  "properties": {
    "iso:country": "GB",
    "wof:name": "BD19 4PE",
    "wof:placetype": "postalcode"
  },
  "geometry": {"coordinates":[-1.690315,53.732001],"type":"Point"}
}
