{
  "type": "Feature",
  "properties": {
    "iso:country":"GB",
    "wof:name":"CR2 9NE",
    "wof:placetype":"postalcode"
},
  "geometry": {"coordinates":[-0.08688911057166,51.33544607924265],"type":"Point"}
}