{
  "type": "Feature",
  "properties": {
    "date:inception_lower":"1980-01-01",
    "date:inception_upper":"1980-01-31",
    "iso:country":"GB",
    "wof:name":"CR2 9NE",
    "wof:placetype":"postalcode"
},
  "geometry": {"coordinates":[-0.086889,51.335446],"type":"Point"}
}