{
  "type": "Feature",
  "properties": {
    "iso:country": "GB",
    "wof:name": "KY4 8EB",
    "wof:placetype": "postalcode"
  },
  "geometry": {"coordinates":[-3.3634,56.099343],"type":"Point"}
}
