{
  "type": "Feature",
  "properties": {
    "iso:country":"GB",
    "wof:name":"CB1 3XB",
    "wof:placetype":"postalcode"
},
  "geometry": {"coordinates":[0.14934243602918,52.19871428222198],"type":"Point"}
}