{
  "type": "Feature",
  "properties": {
    "iso:country": "GB",
    "wof:name": "CB1 3XB",
    "wof:placetype": "postalcode"
  },
  "geometry": {"coordinates":[0.149342,52.198714],"type":"Point"}
}
