{
  "type": "Feature",
  "properties": {
    "date:inception_lower": "1991-09-01",
    "date:inception_upper": "1991-09-01",
    "iso:country": "GB",
    "wof:name": "CB1 3XB",
    "wof:placetype": "postalcode"
  },
  "geometry": {"coordinates":[0.149342,52.198714],"type":"Point"}
}
