{
  "type": "Feature",
  "properties": {
    "iso:country": "GB",
    "wof:name": "TW13 5JL",
    "wof:placetype": "postalcode"
  },
  "geometry": {"coordinates":[-0.382281,51.443788],"type":"Point"}
}
