{
  "type": "Feature",
  "properties": {
    "iso:country":"GB",
    "wof:name":"TW13 5JL",
    "wof:placetype":"postalcode"
},
  "geometry": {"coordinates":[-0.38228074859458,51.44378784860636],"type":"Point"}
}