{
  "type": "Feature",
  "properties": {
    "date:inception_lower":"1980-01-01",
    "date:inception_upper":"1980-01-31",
    "iso:country":"GB",
    "wof:name":"TW13 5JL",
    "wof:placetype":"postalcode"
},
  "geometry": {"coordinates":[-0.382281,51.443788],"type":"Point"}
}