{
  "type": "Feature",
  "properties": {
    "date:inception_lower": "2000-10-01",
    "date:inception_upper": "2000-10-01",
    "iso:country": "GB",
    "wof:name": "WD3 8ED",
    "wof:placetype": "postalcode"
  },
  "geometry": {"coordinates":[-0.494439,51.634161],"type":"Point"}
}
