{
  "type": "Feature",
  "properties": {
    "iso:country":"GB",
    "wof:name":"SP8 5PA",
    "wof:placetype":"postalcode"
},
  "geometry": {"coordinates":[-2.33586481440143,51.03496496943506],"type":"Point"}
}