{
  "type": "Feature",
  "properties": {
    "iso:country": "GB",
    "wof:name": "SP8 5PA",
    "wof:placetype": "postalcode"
  },
  "geometry": {"coordinates":[-2.335865,51.034965],"type":"Point"}
}
