{
  "type": "Feature",
  "properties": {
    "iso:country":"GB",
    "wof:name":"S8 7UW",
    "wof:placetype":"postalcode"
},
  "geometry": {"coordinates":[-1.48368547324395,53.33192264061229],"type":"Point"}
}