{
  "type": "Feature",
  "properties": {
    "date:inception_lower": "2023-11-01",
    "date:inception_upper": "2023-11-01",
    "iso:country": "GB",
    "wof:name": "NE15 9GW",
    "wof:placetype": "postalcode"
  },
  "geometry": {"coordinates":[-1.734813,55.000172],"type":"Point"}
}
