{
  "type": "Feature",
  "properties": {
    "date:inception_lower": "1980-01-01",
    "date:inception_upper": "1980-01-01",
    "iso:country": "GB",
    "wof:name": "CT19 4JJ",
    "wof:placetype": "postalcode"
  },
  "geometry": {"coordinates":[1.140371,51.087166],"type":"Point"}
}
