{
  "type": "Feature",
  "properties": {
    "iso:country":"GB",
    "wof:name":"DE3 0PL",
    "wof:placetype":"postalcode"
},
  "geometry": {"coordinates":[-1.54995648139078,52.91626737135633],"type":"Point"}
}