{
  "type": "Feature",
  "properties": {
    "date:inception_lower": "2002-06-01",
    "date:inception_upper": "2002-06-01",
    "iso:country": "GB",
    "wof:name": "DE3 0PL",
    "wof:placetype": "postalcode"
  },
  "geometry": {"coordinates":[-1.549956,52.916267],"type":"Point"}
}
