{
  "type": "Feature",
  "properties": {
    "date:inception_lower": "1994-12-01",
    "date:inception_upper": "1994-12-01",
    "iso:country": "GB",
    "wof:name": "SO30 3RG",
    "wof:placetype": "postalcode"
  },
  "geometry": {"coordinates":[-1.33655,50.933832],"type":"Point"}
}
