{
  "type": "Feature",
  "properties": {
    "iso:country": "GB",
    "wof:name": "S81 0PQ",
    "wof:placetype": "postalcode"
  },
  "geometry": {"coordinates":[-1.114367,53.324513],"type":"Point"}
}
