{
  "type": "Feature",
  "properties": {
    "iso:country":"GB",
    "wof:name":"WA16 7HN",
    "wof:placetype":"postalcode"
},
  "geometry": {"coordinates":[-2.32758468520694,53.31350510058479],"type":"Point"}
}