{
  "type": "Feature",
  "properties": {
    "iso:country":"GB",
    "wof:name":"HU10 7JS",
    "wof:placetype":"postalcode"
},
  "geometry": {"coordinates":[-0.45211404999843,53.74464478701606],"type":"Point"}
}