{
  "type": "Feature",
  "properties": {
    "iso:country":"GB",
    "wof:name":"HD9 1EY",
    "wof:placetype":"postalcode"
},
  "geometry": {"coordinates":[-1.77754549218633,53.56581361782865],"type":"Point"}
}