{
  "type": "Feature",
  "properties": {
    "iso:country":"GB",
    "wof:name":"LN5 9RF",
    "wof:placetype":"postalcode"
},
  "geometry": {"coordinates":[-0.54167686013577,53.16558845219949],"type":"Point"}
}