{
  "type": "Feature",
  "properties": {
    "date:inception_lower": "1980-01-01",
    "date:inception_upper": "1980-01-01",
    "iso:country": "GB",
    "wof:name": "LN5 9RF",
    "wof:placetype": "postalcode"
  },
  "geometry": {"coordinates":[-0.541677,53.165588],"type":"Point"}
}
