{
  "type": "Feature",
  "properties": {
    "iso:country":"GB",
    "wof:name":"BN3 6QG",
    "wof:placetype":"postalcode"
},
  "geometry": {"coordinates":[-0.16997221964364,50.85240780733059],"type":"Point"}
}