{
  "type": "Feature",
  "properties": {
    "iso:country": "GB",
    "wof:name": "BN3 6QG",
    "wof:placetype": "postalcode"
  },
  "geometry": {"coordinates":[-0.169972,50.852408],"type":"Point"}
}
