{
  "type": "Feature",
  "properties": {
    "iso:country":"GB",
    "wof:name":"SY8 4LJ",
    "wof:placetype":"postalcode"
},
  "geometry": {"coordinates":[-2.66578942273937,52.31247819683944],"type":"Point"}
}