{
  "type": "Feature",
  "properties": {
    "date:inception_lower": "1980-01-01",
    "date:inception_upper": "1980-01-01",
    "iso:country": "GB",
    "wof:name": "SY8 4LJ",
    "wof:placetype": "postalcode"
  },
  "geometry": {"coordinates":[-2.665789,52.312478],"type":"Point"}
}
