{
  "type": "Feature",
  "properties": {
    "iso:country":"GB",
    "wof:name":"S43 3TT",
    "wof:placetype":"postalcode"
},
  "geometry": {"coordinates":[-1.34442788159952,53.26912598967038],"type":"Point"}
}