{
  "type": "Feature",
  "properties": {
    "date:inception_lower": "1983-07-01",
    "date:inception_upper": "1983-07-01",
    "iso:country": "GB",
    "wof:name": "IP20 9EZ",
    "wof:placetype": "postalcode"
  },
  "geometry": {"coordinates":[1.299541,52.407448],"type":"Point"}
}
