{
  "type": "Feature",
  "properties": {
    "iso:country": "GB",
    "wof:name": "M11 1PG",
    "wof:placetype": "postalcode"
  },
  "geometry": {"coordinates":[-2.15752,53.474062],"type":"Point"}
}
