{
  "type": "Feature",
  "properties": {
    "iso:country": "GB",
    "wof:name": "RG9 5LY",
    "wof:placetype": "postalcode"
  },
  "geometry": {"coordinates":[-0.991957,51.532602],"type":"Point"}
}
