{
  "type": "Feature",
  "properties": {
    "iso:country":"GB",
    "wof:name":"RG9 5LY",
    "wof:placetype":"postalcode"
},
  "geometry": {"coordinates":[-0.991956677094,51.53260156881531],"type":"Point"}
}