{
  "type": "Feature",
  "properties": {
    "iso:country": "GB",
    "wof:name": "PA5 0PP",
    "wof:placetype": "postalcode"
  },
  "geometry": {"coordinates":[-4.535766,55.82089],"type":"Point"}
}
