{
  "type": "Feature",
  "properties": {
    "iso:country":"GB",
    "wof:name":"SW18 5RR",
    "wof:placetype":"postalcode"
},
  "geometry": {"coordinates":[-0.2019308741981,51.44858818075448],"type":"Point"}
}