{
  "type": "Feature",
  "properties": {
    "iso:country":"GB",
    "wof:name":"WA6 9AP",
    "wof:placetype":"postalcode"
},
  "geometry": {"coordinates":[-2.76429441191752,53.26685754316123],"type":"Point"}
}