{
  "type": "Feature",
  "properties": {
    "iso:country":"GB",
    "wof:name":"SP3 4SF",
    "wof:placetype":"postalcode"
},
  "geometry": {"coordinates":[-1.95684048582697,51.23150270671209],"type":"Point"}
}