{
  "type": "Feature",
  "properties": {
    "iso:country": "GB",
    "wof:name": "SP3 4SF",
    "wof:placetype": "postalcode"
  },
  "geometry": {"coordinates":[-1.95684,51.231503],"type":"Point"}
}
