{
  "type": "Feature",
  "properties": {
    "iso:country":"GB",
    "wof:name":"E9 6FR",
    "wof:placetype":"postalcode"
},
  "geometry": {"coordinates":[-0.04691593142501,51.54738306467437],"type":"Point"}
}