{
  "type": "Feature",
  "properties": {
    "iso:country": "GB",
    "wof:name": "S70 2BB",
    "wof:placetype": "postalcode"
  },
  "geometry": {"coordinates":[-1.485194,53.55704],"type":"Point"}
}
