{
  "type": "Feature",
  "properties": {
    "date:inception_lower": "1994-05-01",
    "date:inception_upper": "1994-05-01",
    "iso:country": "GB",
    "wof:name": "M27 0HP",
    "wof:placetype": "postalcode"
  },
  "geometry": {"coordinates":[-2.354059,53.506918],"type":"Point"}
}
