{
  "type": "Feature",
  "properties": {
    "iso:country":"GB",
    "wof:name":"YO26 6PA",
    "wof:placetype":"postalcode"
},
  "geometry": {"coordinates":[-1.13696311714924,53.97590319140314],"type":"Point"}
}