{
  "type": "Feature",
  "properties": {
    "date:inception_lower": "1980-01-01",
    "date:inception_upper": "1980-01-01",
    "iso:country": "GB",
    "wof:name": "TS25 2ET",
    "wof:placetype": "postalcode"
  },
  "geometry": {"coordinates":[-1.237343,54.640619],"type":"Point"}
}
