{
  "type": "Feature",
  "properties": {
    "iso:country":"GB",
    "wof:name":"TS25 2ET",
    "wof:placetype":"postalcode"
},
  "geometry": {"coordinates":[-1.23734339653389,54.64061900808812],"type":"Point"}
}