{
  "type": "Feature",
  "properties": {
    "iso:country": "GB",
    "wof:name": "RH14 9HN",
    "wof:placetype": "postalcode"
  },
  "geometry": {"coordinates":[-0.446275,51.028292],"type":"Point"}
}
