{
  "type": "Feature",
  "properties": {
    "iso:country":"GB",
    "wof:name":"RH14 9HN",
    "wof:placetype":"postalcode"
},
  "geometry": {"coordinates":[-0.44628770718607,51.02825209338349],"type":"Point"}
}