{
  "type": "Feature",
  "properties": {
    "iso:country":"GB",
    "wof:name":"SW9 7PR",
    "wof:placetype":"postalcode"
},
  "geometry": {"coordinates":[-0.11165384030935,51.46389498883444],"type":"Point"}
}