{
  "type": "Feature",
  "properties": {
    "date:inception_lower": "2016-05-01",
    "date:inception_upper": "2016-05-01",
    "iso:country": "GB",
    "wof:name": "PO20 2EB",
    "wof:placetype": "postalcode"
  },
  "geometry": {"coordinates":[-0.711133,50.849801],"type":"Point"}
}
