{
  "type": "Feature",
  "properties": {
    "iso:country":"GB",
    "wof:name":"NG6 8PU",
    "wof:placetype":"postalcode"
},
  "geometry": {"coordinates":[-1.19981473049628,52.98796886287602],"type":"Point"}
}