{
  "type": "Feature",
  "properties": {
    "iso:country": "GB",
    "wof:name": "NG6 8PU",
    "wof:placetype": "postalcode"
  },
  "geometry": {"coordinates":[-1.199815,52.987969],"type":"Point"}
}
