{
  "type": "Feature",
  "properties": {
    "date:inception_lower":"1994-10-01",
    "date:inception_upper":"1994-10-31",
    "iso:country":"GB",
    "wof:name":"G64 1JE",
    "wof:placetype":"postalcode"
},
  "geometry": {"coordinates":[-4.205814,55.900509],"type":"Point"}
}