{
  "type": "Feature",
  "properties": {
    "iso:country": "GB",
    "wof:name": "LE17 4RZ",
    "wof:placetype": "postalcode"
  },
  "geometry": {"coordinates":[-1.210578,52.467522],"type":"Point"}
}
