{
  "type": "Feature",
  "properties": {
    "date:inception_lower": "2023-08-01",
    "date:inception_upper": "2023-08-01",
    "iso:country": "GB",
    "wof:name": "DN14 7EH",
    "wof:placetype": "postalcode"
  },
  "geometry": {"coordinates":[-0.87027,53.750504],"type":"Point"}
}
