{
  "type": "Feature",
  "properties": {
    "iso:country":"GB",
    "wof:name":"PL14 5EH",
    "wof:placetype":"postalcode"
},
  "geometry": {"coordinates":[-4.46184420582635,50.49003911619469],"type":"Point"}
}