{
  "type": "Feature",
  "properties": {
    "iso:country":"GB",
    "wof:name":"CV21 1BT",
    "wof:placetype":"postalcode"
},
  "geometry": {"coordinates":[-1.24863179228484,52.38611146661309],"type":"Point"}
}