{
  "type": "Feature",
  "properties": {
    "date:inception_lower": "1980-01-01",
    "date:inception_upper": "1980-01-01",
    "iso:country": "GB",
    "wof:name": "CV21 1BT",
    "wof:placetype": "postalcode"
  },
  "geometry": {"coordinates":[-1.248632,52.386111],"type":"Point"}
}
