{
  "type": "Feature",
  "properties": {
    "date:inception_lower": "1980-01-01",
    "date:inception_upper": "1980-01-01",
    "iso:country": "GB",
    "wof:name": "BH25 7AP",
    "wof:placetype": "postalcode"
  },
  "geometry": {"coordinates":[-1.651638,50.739546],"type":"Point"}
}
