{
  "type": "Feature",
  "properties": {
    "iso:country":"GB",
    "wof:name":"EX17 4RP",
    "wof:placetype":"postalcode"
},
  "geometry": {"coordinates":[-3.69673726348259,50.85722014562766],"type":"Point"}
}