{
  "type": "Feature",
  "properties": {
    "iso:country":"GB",
    "wof:name":"SY23 2DT",
    "wof:placetype":"postalcode"
},
  "geometry": {"coordinates":[-4.08400786815771,52.41584929671713],"type":"Point"}
}