{
  "type": "Feature",
  "properties": {
    "date:inception_lower": "1980-01-01",
    "date:inception_upper": "1980-01-01",
    "iso:country": "GB",
    "wof:name": "NP4 7SF",
    "wof:placetype": "postalcode"
  },
  "geometry": {"coordinates":[-3.065398,51.740336],"type":"Point"}
}
