{
  "type": "Feature",
  "properties": {
    "iso:country": "GB",
    "wof:name": "GU11 2PY",
    "wof:placetype": "postalcode"
  },
  "geometry": {"coordinates":[-0.742038,51.264742],"type":"Point"}
}
