{
  "type": "Feature",
  "properties": {
    "date:inception_lower": "1994-05-01",
    "date:inception_upper": "1994-05-01",
    "iso:country": "GB",
    "wof:name": "GU11 2PY",
    "wof:placetype": "postalcode"
  },
  "geometry": {"coordinates":[-0.742038,51.264742],"type":"Point"}
}
