{
  "type": "Feature",
  "properties": {
    "iso:country":"GB",
    "wof:name":"E2 6HG",
    "wof:placetype":"postalcode"
},
  "geometry": {"coordinates":[-0.0615109543021,51.5263667067963],"type":"Point"}
}