{
  "type": "Feature",
  "properties": {
    "iso:country": "GB",
    "wof:name": "BL3 6SX",
    "wof:placetype": "postalcode"
  },
  "geometry": {"coordinates":[-2.444017,53.56522],"type":"Point"}
}
