{
  "type": "Feature",
  "properties": {
    "iso:country":"GB",
    "wof:name":"FY5 3DD",
    "wof:placetype":"postalcode"
},
  "geometry": {"coordinates":[-3.01900932597395,53.85989820070071],"type":"Point"}
}