{
  "type": "Feature",
  "properties": {
    "date:inception_lower": "1980-01-01",
    "date:inception_upper": "1980-01-01",
    "iso:country": "GB",
    "wof:name": "FY5 3DD",
    "wof:placetype": "postalcode"
  },
  "geometry": {"coordinates":[-3.019009,53.859898],"type":"Point"}
}
