{
  "type": "Feature",
  "properties": {
    "iso:country":"GB",
    "wof:name":"SW1W 9AQ",
    "wof:placetype":"postalcode"
},
  "geometry": {"coordinates":[-0.1520682453492,51.49658836618156],"type":"Point"}
}