{
  "type": "Feature",
  "properties": {
    "iso:country": "GB",
    "wof:name": "SW1W 9AQ",
    "wof:placetype": "postalcode"
  },
  "geometry": {"coordinates":[-0.152068,51.496588],"type":"Point"}
}
