{
  "type": "Feature",
  "properties": {
    "iso:country":"GB",
    "wof:name":"GL54 1JZ",
    "wof:placetype":"postalcode"
},
  "geometry": {"coordinates":[-1.73650005945645,51.91989947734042],"type":"Point"}
}