{
  "type": "Feature",
  "properties": {
    "iso:country":"GB",
    "wof:name":"S70 3HJ",
    "wof:placetype":"postalcode"
},
  "geometry": {"coordinates":[-1.44908009501528,53.54450161406168],"type":"Point"}
}