{
  "type": "Feature",
  "properties": {
    "date:inception_lower": "1980-01-01",
    "date:inception_upper": "1980-01-01",
    "iso:country": "GB",
    "wof:name": "ST7 8BS",
    "wof:placetype": "postalcode"
  },
  "geometry": {"coordinates":[-2.28296,53.029307],"type":"Point"}
}
