{
  "type": "Feature",
  "properties": {
    "date:inception_lower": "1980-01-01",
    "date:inception_upper": "1980-01-01",
    "iso:country": "GB",
    "wof:name": "NR1 1TR",
    "wof:placetype": "postalcode"
  },
  "geometry": {"coordinates":[1.32165,52.625468],"type":"Point"}
}
