{
  "type": "Feature",
  "properties": {
    "iso:country": "GB",
    "wof:name": "NR1 1TR",
    "wof:placetype": "postalcode"
  },
  "geometry": {"coordinates":[1.32165,52.625468],"type":"Point"}
}
