{
  "type": "Feature",
  "properties": {
    "date:inception_lower":"1980-01-01",
    "date:inception_upper":"1980-01-31",
    "iso:country":"GB",
    "wof:name":"GU23 7DA",
    "wof:placetype":"postalcode"
},
  "geometry": {"coordinates":[-0.514687,51.282365],"type":"Point"}
}