{
  "type": "Feature",
  "properties": {
    "iso:country":"GB",
    "wof:name":"GU23 7DA",
    "wof:placetype":"postalcode"
},
  "geometry": {"coordinates":[-0.51468715170352,51.28236515236144],"type":"Point"}
}