{
  "type": "Feature",
  "properties": {
    "date:inception_lower":"1993-08-01",
    "date:inception_upper":"1993-08-31",
    "iso:country":"GB",
    "wof:name":"RH10 4RH",
    "wof:placetype":"postalcode"
},
  "geometry": {"coordinates":[-0.068674,51.108524],"type":"Point"}
}