{
  "type": "Feature",
  "properties": {
    "iso:country": "GB",
    "wof:name": "RH10 4RH",
    "wof:placetype": "postalcode"
  },
  "geometry": {"coordinates":[-0.068674,51.108524],"type":"Point"}
}
