{
  "type": "Feature",
  "properties": {
    "date:inception_lower":"1980-01-01",
    "date:inception_upper":"1980-01-31",
    "iso:country":"GB",
    "wof:name":"KA15 1HS",
    "wof:placetype":"postalcode"
},
  "geometry": {"coordinates":[-4.599833,55.729164],"type":"Point"}
}