{
  "type": "Feature",
  "properties": {
    "iso:country":"GB",
    "wof:name":"KA15 1HS",
    "wof:placetype":"postalcode"
},
  "geometry": {"coordinates":[-4.59983293181463,55.72916435114844],"type":"Point"}
}