{
  "type": "Feature",
  "properties": {
    "iso:country": "GB",
    "wof:name": "SW15 3PZ",
    "wof:placetype": "postalcode"
  },
  "geometry": {"coordinates":[-0.259281,51.434212],"type":"Point"}
}
