{
  "type": "Feature",
  "properties": {
    "iso:country":"GB",
    "wof:name":"SW15 3PZ",
    "wof:placetype":"postalcode"
},
  "geometry": {"coordinates":[-0.2592808016704,51.43421152470629],"type":"Point"}
}