{
  "type": "Feature",
  "properties": {
    "iso:country": "GB",
    "wof:name": "BN9 0NT",
    "wof:placetype": "postalcode"
  },
  "geometry": {"coordinates":[0.069335,50.801313],"type":"Point"}
}
