{
  "type": "Feature",
  "properties": {
    "iso:country":"GB",
    "wof:name":"BN9 0NT",
    "wof:placetype":"postalcode"
},
  "geometry": {"coordinates":[0.06930763448957,50.80131865212789],"type":"Point"}
}