{
  "type": "Feature",
  "properties": {
    "iso:country": "GB",
    "wof:name": "BN10 8HE",
    "wof:placetype": "postalcode"
  },
  "geometry": {"coordinates":[0.00613,50.792817],"type":"Point"}
}
