{
  "type": "Feature",
  "properties": {
    "date:inception_lower": "1980-01-01",
    "date:inception_upper": "1980-01-01",
    "iso:country": "GB",
    "wof:name": "HX7 7EZ",
    "wof:placetype": "postalcode"
  },
  "geometry": {"coordinates":[-2.030508,53.754036],"type":"Point"}
}
