{
  "type": "Feature",
  "properties": {
    "iso:country":"GB",
    "wof:name":"HX7 7EZ",
    "wof:placetype":"postalcode"
},
  "geometry": {"coordinates":[-2.03085584040335,53.75410222869625],"type":"Point"}
}