{
  "type": "Feature",
  "properties": {
    "iso:country": "GB",
    "wof:name": "WR2 4NB",
    "wof:placetype": "postalcode"
  },
  "geometry": {"coordinates":[-2.233149,52.182992],"type":"Point"}
}
