{
  "type": "Feature",
  "properties": {
    "iso:country":"GB",
    "wof:name":"HP9 2PW",
    "wof:placetype":"postalcode"
},
  "geometry": {"coordinates":[-0.6465241797151,51.61221991439601],"type":"Point"}
}