{
  "type": "Feature",
  "properties": {
    "date:inception_lower": "1983-03-01",
    "date:inception_upper": "1983-03-01",
    "iso:country": "GB",
    "wof:name": "HP9 2PW",
    "wof:placetype": "postalcode"
  },
  "geometry": {"coordinates":[-0.646524,51.61222],"type":"Point"}
}
