{
  "type": "Feature",
  "properties": {
    "iso:country":"GB",
    "wof:name":"BN13 1PQ",
    "wof:placetype":"postalcode"
},
  "geometry": {"coordinates":[-0.4080500650262,50.82287547678204],"type":"Point"}
}