{
  "type": "Feature",
  "properties": {
    "date:inception_lower": "1990-07-01",
    "date:inception_upper": "1990-07-01",
    "iso:country": "GB",
    "wof:name": "DL1 1GB",
    "wof:placetype": "postalcode"
  },
  "geometry": {"coordinates":[-1.549816,54.526434],"type":"Point"}
}
