{
  "type": "Feature",
  "properties": {
    "iso:country": "GB",
    "wof:name": "DL1 1GB",
    "wof:placetype": "postalcode"
  },
  "geometry": {"coordinates":[-1.549816,54.526434],"type":"Point"}
}
