{
  "type": "Feature",
  "properties": {
    "iso:country": "GB",
    "wof:name": "PO19 5TY",
    "wof:placetype": "postalcode"
  },
  "geometry": {"coordinates":[-0.781867,50.847143],"type":"Point"}
}
