{
  "type": "Feature",
  "properties": {
    "date:inception_lower": "2021-11-01",
    "date:inception_upper": "2021-11-01",
    "iso:country": "GB",
    "wof:name": "BA6 9RG",
    "wof:placetype": "postalcode"
  },
  "geometry": {"coordinates":[-2.720667,51.153751],"type":"Point"}
}
