{
  "type": "Feature",
  "properties": {
    "iso:country":"GB",
    "wof:name":"M17 1PQ",
    "wof:placetype":"postalcode"
},
  "geometry": {"coordinates":[-2.31527385393087,53.46354926607092],"type":"Point"}
}