{
  "type": "Feature",
  "properties": {
    "iso:country":"GB",
    "wof:name":"KA1 3NG",
    "wof:placetype":"postalcode"
},
  "geometry": {"coordinates":[-4.48258570279043,55.59710018965731],"type":"Point"}
}