{
  "type": "Feature",
  "properties": {
    "date:inception_lower": "1980-01-01",
    "date:inception_upper": "1980-01-01",
    "iso:country": "GB",
    "wof:name": "GL52 2DG",
    "wof:placetype": "postalcode"
  },
  "geometry": {"coordinates":[-2.06349,51.907149],"type":"Point"}
}
