{
  "type": "Feature",
  "properties": {
    "iso:country":"GB",
    "wof:name":"S40 1JW",
    "wof:placetype":"postalcode"
},
  "geometry": {"coordinates":[-1.4299358417825,53.23663887618981],"type":"Point"}
}