{
  "type": "Feature",
  "properties": {
    "iso:country": "GB",
    "wof:name": "S40 1JW",
    "wof:placetype": "postalcode"
  },
  "geometry": {"coordinates":[-1.42998,53.236622],"type":"Point"}
}
