{
  "type": "Feature",
  "properties": {
    "iso:country":"GB",
    "wof:name":"BD5 7NS",
    "wof:placetype":"postalcode"
},
  "geometry": {"coordinates":[-1.76387907344498,53.77761161731775],"type":"Point"}
}