{
  "type": "Feature",
  "properties": {
    "iso:country": "GB",
    "wof:name": "LS25 6NR",
    "wof:placetype": "postalcode"
  },
  "geometry": {"coordinates":[-1.249435,53.797984],"type":"Point"}
}
