{
  "type": "Feature",
  "properties": {
    "date:inception_lower":"2002-09-01",
    "date:inception_upper":"2002-09-30",
    "iso:country":"GB",
    "wof:name":"LS25 6NR",
    "wof:placetype":"postalcode"
},
  "geometry": {"coordinates":[-1.249435,53.797984],"type":"Point"}
}