{
  "type": "Feature",
  "properties": {
    "iso:country":"GB",
    "wof:name":"TR16 4PX",
    "wof:placetype":"postalcode"
},
  "geometry": {"coordinates":[-5.28824821343741,50.25166272875393],"type":"Point"}
}