{
  "type": "Feature",
  "properties": {
    "iso:country": "GB",
    "wof:name": "LL53 6DY",
    "wof:placetype": "postalcode"
  },
  "geometry": {"coordinates":[-4.522137,52.93449],"type":"Point"}
}
