{
  "type": "Feature",
  "properties": {
    "iso:country":"GB",
    "wof:name":"LL53 6DY",
    "wof:placetype":"postalcode"
},
  "geometry": {"coordinates":[-4.52191360218547,52.93461258216259],"type":"Point"}
}