{
  "type": "Feature",
  "properties": {
    "iso:country":"GB",
    "wof:name":"TN35 5NL",
    "wof:placetype":"postalcode"
},
  "geometry": {"coordinates":[0.60103598028355,50.86315636253772],"type":"Point"}
}