{
  "type": "Feature",
  "properties": {
    "iso:country":"GB",
    "wof:name":"NG2 5GU",
    "wof:placetype":"postalcode"
},
  "geometry": {"coordinates":[-1.12478497149044,52.93537315791926],"type":"Point"}
}