{
  "type": "Feature",
  "properties": {
    "date:inception_lower": "1980-01-01",
    "date:inception_upper": "1980-01-01",
    "iso:country": "GB",
    "wof:name": "WF15 7PL",
    "wof:placetype": "postalcode"
  },
  "geometry": {"coordinates":[-1.69572,53.699583],"type":"Point"}
}
