{
  "type": "Feature",
  "properties": {
    "iso:country":"GB",
    "wof:name":"WF15 7PL",
    "wof:placetype":"postalcode"
},
  "geometry": {"coordinates":[-1.6957176268885,53.69956744473657],"type":"Point"}
}