{
  "type": "Feature",
  "properties": {
    "iso:country": "GB",
    "wof:name": "B63 3JW",
    "wof:placetype": "postalcode"
  },
  "geometry": {"coordinates":[-2.047449,52.451784],"type":"Point"}
}
