{
  "type": "Feature",
  "properties": {
    "date:inception_lower":"2016-01-01",
    "date:inception_upper":"2016-01-31",
    "iso:country":"GB",
    "wof:name":"B63 3JW",
    "wof:placetype":"postalcode"
},
  "geometry": {"coordinates":[-2.047449,52.451784],"type":"Point"}
}