{
  "type": "Feature",
  "properties": {
    "date:inception_lower": "2011-03-01",
    "date:inception_upper": "2011-03-01",
    "iso:country": "GB",
    "wof:name": "SL3 8BZ",
    "wof:placetype": "postalcode"
  },
  "geometry": {"coordinates":[-0.544596,51.498987],"type":"Point"}
}
