{
  "type": "Feature",
  "properties": {
    "iso:country":"GB",
    "wof:name":"PE2 7AJ",
    "wof:placetype":"postalcode"
},
  "geometry": {"coordinates":[-0.26946849036747,52.55688483239611],"type":"Point"}
}