{
  "type": "Feature",
  "properties": {
    "iso:country":"GB",
    "wof:name":"KT23 4QP",
    "wof:placetype":"postalcode"
},
  "geometry": {"coordinates":[-0.36651121364853,51.27576947792997],"type":"Point"}
}