{
  "type": "Feature",
  "properties": {
    "date:inception_lower": "1980-01-01",
    "date:inception_upper": "1980-01-01",
    "iso:country": "GB",
    "wof:name": "NE38 9AZ",
    "wof:placetype": "postalcode"
  },
  "geometry": {"coordinates":[-1.532198,54.88355],"type":"Point"}
}
