{
  "type": "Feature",
  "properties": {
    "iso:country":"GB",
    "wof:name":"NE38 9AZ",
    "wof:placetype":"postalcode"
},
  "geometry": {"coordinates":[-1.53219809053097,54.88355022435485],"type":"Point"}
}