{
  "type": "Feature",
  "properties": {
    "date:inception_lower": "1980-01-01",
    "date:inception_upper": "1980-01-01",
    "iso:country": "GB",
    "wof:name": "LL18 5DT",
    "wof:placetype": "postalcode"
  },
  "geometry": {"coordinates":[-3.523499,53.307837],"type":"Point"}
}
