{
  "type": "Feature",
  "properties": {
    "iso:country":"GB",
    "wof:name":"LL18 5DT",
    "wof:placetype":"postalcode"
},
  "geometry": {"coordinates":[-3.5235109543451,53.30780097131463],"type":"Point"}
}