{
  "type": "Feature",
  "properties": {
    "date:inception_lower": "2021-03-01",
    "date:inception_upper": "2021-03-01",
    "iso:country": "GB",
    "wof:name": "ST21 6FE",
    "wof:placetype": "postalcode"
  },
  "geometry": {"coordinates":[-2.248649,52.8582],"type":"Point"}
}
