{
  "type": "Feature",
  "properties": {
    "date:inception_lower": "2006-11-01",
    "date:inception_upper": "2006-11-01",
    "iso:country": "GB",
    "wof:name": "M7 2AG",
    "wof:placetype": "postalcode"
  },
  "geometry": {"coordinates":[-2.257104,53.506033],"type":"Point"}
}
