{
  "type": "Feature",
  "properties": {
    "iso:country":"GB",
    "wof:name":"SN7 8LR",
    "wof:placetype":"postalcode"
},
  "geometry": {"coordinates":[-1.50769521430574,51.63734803195311],"type":"Point"}
}