{
  "type": "Feature",
  "properties": {
    "date:inception_lower": "1980-01-01",
    "date:inception_upper": "1980-01-01",
    "iso:country": "GB",
    "wof:name": "ST5 1NG",
    "wof:placetype": "postalcode"
  },
  "geometry": {"coordinates":[-2.21967,53.006817],"type":"Point"}
}
