{
  "type": "Feature",
  "properties": {
    "iso:country":"GB",
    "wof:name":"YO10 3AE",
    "wof:placetype":"postalcode"
},
  "geometry": {"coordinates":[-1.05466021723501,53.95433286965275],"type":"Point"}
}