{
  "type": "Feature",
  "properties": {
    "iso:country":"GB",
    "wof:name":"KA3 3AZ",
    "wof:placetype":"postalcode"
},
  "geometry": {"coordinates":[-4.52508506063663,55.67715423436932],"type":"Point"}
}