{
  "type": "Feature",
  "properties": {
    "iso:country": "GB",
    "wof:name": "G68 9DH",
    "wof:placetype": "postalcode"
  },
  "geometry": {"coordinates":[-4.010505,55.949174],"type":"Point"}
}
