{
  "type": "Feature",
  "properties": {
    "date:inception_lower": "1987-09-01",
    "date:inception_upper": "1987-09-01",
    "iso:country": "GB",
    "wof:name": "G68 9DH",
    "wof:placetype": "postalcode"
  },
  "geometry": {"coordinates":[-4.010505,55.949174],"type":"Point"}
}
