{
  "type": "Feature",
  "properties": {
    "iso:country":"GB",
    "wof:name":"CW7 3EG",
    "wof:placetype":"postalcode"
},
  "geometry": {"coordinates":[-2.50682575682784,53.19675059467723],"type":"Point"}
}