{
  "type": "Feature",
  "properties": {
    "date:inception_lower": "1997-06-01",
    "date:inception_upper": "1997-06-01",
    "iso:country": "GB",
    "wof:name": "CH8 7UU",
    "wof:placetype": "postalcode"
  },
  "geometry": {"coordinates":[-3.220962,53.270768],"type":"Point"}
}
