{
  "type": "Feature",
  "properties": {
    "iso:country":"GB",
    "wof:name":"CH8 7UU",
    "wof:placetype":"postalcode"
},
  "geometry": {"coordinates":[-3.22096224134229,53.27076754619004],"type":"Point"}
}