{
  "type": "Feature",
  "properties": {
    "iso:country":"GB",
    "wof:name":"DN14 0XD",
    "wof:placetype":"postalcode"
},
  "geometry": {"coordinates":[-1.09752427023638,53.69216946507574],"type":"Point"}
}