{
  "type": "Feature",
  "properties": {
    "iso:country": "GB",
    "wof:name": "DN14 0XD",
    "wof:placetype": "postalcode"
  },
  "geometry": {"coordinates":[-1.097524,53.692169],"type":"Point"}
}
