{
  "type": "Feature",
  "properties": {
    "date:inception_lower": "1995-01-01",
    "date:inception_upper": "1995-01-01",
    "iso:country": "GB",
    "wof:name": "DN14 0XD",
    "wof:placetype": "postalcode"
  },
  "geometry": {"coordinates":[-1.097524,53.692169],"type":"Point"}
}
