{
  "type": "Feature",
  "properties": {
    "iso:country":"GB",
    "wof:name":"S60 4JH",
    "wof:placetype":"postalcode"
},
  "geometry": {"coordinates":[-1.32831787854466,53.40626880440217],"type":"Point"}
}