{
  "type": "Feature",
  "properties": {
    "iso:country": "GB",
    "wof:name": "LA5 0AT",
    "wof:placetype": "postalcode"
  },
  "geometry": {"coordinates":[-2.840966,54.198226],"type":"Point"}
}
