{
  "type": "Feature",
  "properties": {
    "iso:country":"GB",
    "wof:name":"LA5 0AT",
    "wof:placetype":"postalcode"
},
  "geometry": {"coordinates":[-2.84096610171598,54.19822589976978],"type":"Point"}
}