{
  "type": "Feature",
  "properties": {
    "date:inception_lower":"1986-01-01",
    "date:inception_upper":"1986-01-31",
    "iso:country":"GB",
    "wof:name":"SO51 0JH",
    "wof:placetype":"postalcode"
},
  "geometry": {"coordinates":[-1.560391,51.030837],"type":"Point"}
}