{
  "type": "Feature",
  "properties": {
    "iso:country": "GB",
    "wof:name": "SO51 0JH",
    "wof:placetype": "postalcode"
  },
  "geometry": {"coordinates":[-1.560391,51.030837],"type":"Point"}
}
