{
  "type": "Feature",
  "properties": {
    "iso:country":"GB",
    "wof:name":"SY11 4QE",
    "wof:placetype":"postalcode"
},
  "geometry": {"coordinates":[-2.97820630127974,52.8209270000192],"type":"Point"}
}