{
  "type": "Feature",
  "properties": {
    "iso:country": "GB",
    "wof:name": "SY11 4QE",
    "wof:placetype": "postalcode"
  },
  "geometry": {"coordinates":[-2.97841,52.820841],"type":"Point"}
}
