{
  "type": "Feature",
  "properties": {
    "date:inception_lower":"2003-03-01",
    "date:inception_upper":"2003-03-31",
    "iso:country":"GB",
    "wof:name":"SY11 4QE",
    "wof:placetype":"postalcode"
},
  "geometry": {"coordinates":[-2.97841,52.820841],"type":"Point"}
}