{
  "type": "Feature",
  "properties": {
    "iso:country":"GB",
    "wof:name":"BB2 1LQ",
    "wof:placetype":"postalcode"
},
  "geometry": {"coordinates":[-2.48686779215882,53.74758879745572],"type":"Point"}
}