{
  "type": "Feature",
  "properties": {
    "iso:country":"GB",
    "wof:name":"NP7 8EP",
    "wof:placetype":"postalcode"
},
  "geometry": {"coordinates":[-2.86805356438122,51.91542669114337],"type":"Point"}
}