{
  "type": "Feature",
  "properties": {
    "iso:country": "GB",
    "wof:name": "NP7 8EP",
    "wof:placetype": "postalcode"
  },
  "geometry": {"coordinates":[-2.868054,51.915427],"type":"Point"}
}
