{
  "type": "Feature",
  "properties": {
    "iso:country": "GB",
    "wof:name": "NE6 4PN",
    "wof:placetype": "postalcode"
  },
  "geometry": {"coordinates":[-1.553163,54.987763],"type":"Point"}
}
