{
  "type": "Feature",
  "properties": {
    "iso:country":"GB",
    "wof:name":"NE6 4PN",
    "wof:placetype":"postalcode"
},
  "geometry": {"coordinates":[-1.55316322413381,54.98776283144647],"type":"Point"}
}