{
  "type": "Feature",
  "properties": {
    "iso:country":"GB",
    "wof:name":"SY5 6PJ",
    "wof:placetype":"postalcode"
},
  "geometry": {"coordinates":[-2.64495658505844,52.67452562018712],"type":"Point"}
}