{
  "type": "Feature",
  "properties": {
    "iso:country": "GB",
    "wof:name": "SY5 6PJ",
    "wof:placetype": "postalcode"
  },
  "geometry": {"coordinates":[-2.644957,52.674526],"type":"Point"}
}
