{
  "type": "Feature",
  "properties": {
    "iso:country": "GB",
    "wof:name": "BN17 7PD",
    "wof:placetype": "postalcode"
  },
  "geometry": {"coordinates":[-0.554476,50.824277],"type":"Point"}
}
