{
  "type": "Feature",
  "properties": {
    "iso:country":"GB",
    "wof:name":"BN17 7PD",
    "wof:placetype":"postalcode"
},
  "geometry": {"coordinates":[-0.55524503911652,50.82404447561301],"type":"Point"}
}