{
  "type": "Feature",
  "properties": {
    "date:inception_lower": "1980-01-01",
    "date:inception_upper": "1980-01-01",
    "iso:country": "GB",
    "wof:name": "BN17 7PD",
    "wof:placetype": "postalcode"
  },
  "geometry": {"coordinates":[-0.554476,50.824277],"type":"Point"}
}
