{
  "type": "Feature",
  "properties": {
    "iso:country":"GB",
    "wof:name":"WA8 0QB",
    "wof:placetype":"postalcode"
},
  "geometry": {"coordinates":[-2.71354754130848,53.37244986306986],"type":"Point"}
}