{
  "type": "Feature",
  "properties": {
    "iso:country": "GB",
    "wof:name": "WA8 0QB",
    "wof:placetype": "postalcode"
  },
  "geometry": {"coordinates":[-2.713547,53.37245],"type":"Point"}
}
