{
  "type": "Feature",
  "properties": {
    "date:inception_lower": "2013-09-01",
    "date:inception_upper": "2013-09-01",
    "iso:country": "GB",
    "wof:name": "WA8 0QB",
    "wof:placetype": "postalcode"
  },
  "geometry": {"coordinates":[-2.713547,53.37245],"type":"Point"}
}
