{
  "type": "Feature",
  "properties": {
    "iso:country":"GB",
    "wof:name":"DG7 3SU",
    "wof:placetype":"postalcode"
},
  "geometry": {"coordinates":[-4.19286219923448,55.1553152730705],"type":"Point"}
}