{
  "type": "Feature",
  "properties": {
    "iso:country":"GB",
    "wof:name":"CF43 4DG",
    "wof:placetype":"postalcode"
},
  "geometry": {"coordinates":[-3.48753902425799,51.67671784999558],"type":"Point"}
}