{
  "type": "Feature",
  "properties": {
    "iso:country":"GB",
    "wof:name":"IP20 9DJ",
    "wof:placetype":"postalcode"
},
  "geometry": {"coordinates":[1.29222959506652,52.40109589055668],"type":"Point"}
}