{
  "type": "Feature",
  "properties": {
    "date:inception_lower": "1980-01-01",
    "date:inception_upper": "1980-01-01",
    "iso:country": "GB",
    "wof:name": "BS4 5HF",
    "wof:placetype": "postalcode"
  },
  "geometry": {"coordinates":[-2.54526,51.4268],"type":"Point"}
}
