{
  "type": "Feature",
  "properties": {
    "iso:country":"GB",
    "wof:name":"BS4 5HF",
    "wof:placetype":"postalcode"
},
  "geometry": {"coordinates":[-2.5452603572384,51.42680041258119],"type":"Point"}
}