{
  "type": "Feature",
  "properties": {
    "iso:country":"GB",
    "wof:name":"RG24 9TF",
    "wof:placetype":"postalcode"
},
  "geometry": {"coordinates":[-1.1112589262114,51.27727105054307],"type":"Point"}
}