{
  "type": "Feature",
  "properties": {
    "date:inception_lower":"2010-09-01",
    "date:inception_upper":"2010-09-30",
    "iso:country":"GB",
    "wof:name":"RG24 9TF",
    "wof:placetype":"postalcode"
},
  "geometry": {"coordinates":[-1.111259,51.277271],"type":"Point"}
}