{
  "type": "Feature",
  "properties": {
    "iso:country":"GB",
    "wof:name":"LN4 4LD",
    "wof:placetype":"postalcode"
},
  "geometry": {"coordinates":[-0.18743719845421,53.10595593543862],"type":"Point"}
}