{
  "type": "Feature",
  "properties": {
    "iso:country": "GB",
    "wof:name": "LN4 4LD",
    "wof:placetype": "postalcode"
  },
  "geometry": {"coordinates":[-0.187437,53.105956],"type":"Point"}
}
