{
  "type": "Feature",
  "properties": {
    "iso:country":"GB",
    "wof:name":"RH4 1SN",
    "wof:placetype":"postalcode"
},
  "geometry": {"coordinates":[-0.32499738215493,51.23457199481105],"type":"Point"}
}