{
  "type": "Feature",
  "properties": {
    "iso:country":"GB",
    "wof:name":"RH10 4QW",
    "wof:placetype":"postalcode"
},
  "geometry": {"coordinates":[-0.06752711855129,51.1096559420338],"type":"Point"}
}