{
  "type": "Feature",
  "properties": {
    "date:inception_lower":"1980-01-01",
    "date:inception_upper":"1980-01-31",
    "iso:country":"GB",
    "wof:name":"TW1 4LR",
    "wof:placetype":"postalcode"
},
  "geometry": {"coordinates":[-0.333868,51.448289],"type":"Point"}
}