{
  "type": "Feature",
  "properties": {
    "iso:country":"GB",
    "wof:name":"TW1 4LR",
    "wof:placetype":"postalcode"
},
  "geometry": {"coordinates":[-0.33386800715575,51.44828941483517],"type":"Point"}
}