{
  "type": "Feature",
  "properties": {
    "iso:country": "GB",
    "wof:name": "SG14 3JR",
    "wof:placetype": "postalcode"
  },
  "geometry": {"coordinates":[-0.072577,51.804861],"type":"Point"}
}
