{
  "type": "Feature",
  "properties": {
    "iso:country": "GB",
    "wof:name": "YO42 2BJ",
    "wof:placetype": "postalcode"
  },
  "geometry": {"coordinates":[-0.777237,53.93264],"type":"Point"}
}
