{
  "type": "Feature",
  "properties": {
    "iso:country":"GB",
    "wof:name":"EX16 8BE",
    "wof:placetype":"postalcode"
},
  "geometry": {"coordinates":[-3.53888108439745,50.91972562121345],"type":"Point"}
}