{
  "type": "Feature",
  "properties": {
    "iso:country": "GB",
    "wof:name": "EX16 8BE",
    "wof:placetype": "postalcode"
  },
  "geometry": {"coordinates":[-3.538881,50.919726],"type":"Point"}
}
