{
  "type": "Feature",
  "properties": {
    "iso:country":"GB",
    "wof:name":"TQ12 5DE",
    "wof:placetype":"postalcode"
},
  "geometry": {"coordinates":[-3.5798828435188,50.49928676227003],"type":"Point"}
}