{
  "type": "Feature",
  "properties": {
    "iso:country":"GB",
    "wof:name":"GU11 3JZ",
    "wof:placetype":"postalcode"
},
  "geometry": {"coordinates":[-0.77345801509723,51.24852025405256],"type":"Point"}
}