{
  "type": "Feature",
  "properties": {
    "iso:country": "GB",
    "wof:name": "DN41 8DS",
    "wof:placetype": "postalcode"
  },
  "geometry": {"coordinates":[-0.172477,53.609851],"type":"Point"}
}
