{
  "type": "Feature",
  "properties": {
    "iso:country":"GB",
    "wof:name":"M24 4EG",
    "wof:placetype":"postalcode"
},
  "geometry": {"coordinates":[-2.21120897012687,53.55446280740908],"type":"Point"}
}