{
  "type": "Feature",
  "properties": {
    "iso:country":"GB",
    "wof:name":"KW17 2NH",
    "wof:placetype":"postalcode"
},
  "geometry": {"coordinates":[-3.07459021214419,59.11779607876284],"type":"Point"}
}