{
  "type": "Feature",
  "properties": {
    "iso:country": "GB",
    "wof:name": "NG19 7RG",
    "wof:placetype": "postalcode"
  },
  "geometry": {"coordinates":[-1.228572,53.164717],"type":"Point"}
}
