{
  "type": "Feature",
  "properties": {
    "date:inception_lower": "1998-06-01",
    "date:inception_upper": "1998-06-01",
    "iso:country": "GB",
    "wof:name": "YO30 1BN",
    "wof:placetype": "postalcode"
  },
  "geometry": {"coordinates":[-1.153792,54.01787],"type":"Point"}
}
