{
  "type": "Feature",
  "properties": {
    "iso:country":"GB",
    "wof:name":"YO30 1BN",
    "wof:placetype":"postalcode"
},
  "geometry": {"coordinates":[-1.15378441238912,54.01784375106708],"type":"Point"}
}