{
  "type": "Feature",
  "properties": {
    "date:inception_lower": "1980-01-01",
    "date:inception_upper": "1980-01-01",
    "iso:country": "GB",
    "wof:name": "EN3 6BP",
    "wof:placetype": "postalcode"
  },
  "geometry": {"coordinates":[-0.035459,51.672334],"type":"Point"}
}
