{
  "type": "Feature",
  "properties": {
    "iso:country": "GB",
    "wof:name": "EN3 6BP",
    "wof:placetype": "postalcode"
  },
  "geometry": {"coordinates":[-0.035095,51.672334],"type":"Point"}
}
