{
  "type": "Feature",
  "properties": {
    "iso:country":"GB",
    "wof:name":"EN3 6BP",
    "wof:placetype":"postalcode"
},
  "geometry": {"coordinates":[-0.03509499534685,51.6723342855413],"type":"Point"}
}