{
  "type": "Feature",
  "properties": {
    "iso:country":"GB",
    "wof:name":"IP6 0SD",
    "wof:placetype":"postalcode"
},
  "geometry": {"coordinates":[1.16514609786493,52.1294247219469],"type":"Point"}
}