{
  "type": "Feature",
  "properties": {
    "iso:country": "GB",
    "wof:name": "LE9 2BW",
    "wof:placetype": "postalcode"
  },
  "geometry": {"coordinates":[-1.243069,52.634581],"type":"Point"}
}
