{
  "type": "Feature",
  "properties": {
    "iso:country":"GB",
    "wof:name":"LE9 2BW",
    "wof:placetype":"postalcode"
},
  "geometry": {"coordinates":[-1.24306856262956,52.63458071295621],"type":"Point"}
}