{
  "type": "Feature",
  "properties": {
    "date:inception_lower":"1994-05-01",
    "date:inception_upper":"1994-05-31",
    "iso:country":"GB",
    "wof:name":"LE9 2BW",
    "wof:placetype":"postalcode"
},
  "geometry": {"coordinates":[-1.243069,52.634581],"type":"Point"}
}