{
  "type": "Feature",
  "properties": {
    "iso:country":"GB",
    "wof:name":"YO17 9SW",
    "wof:placetype":"postalcode"
},
  "geometry": {"coordinates":[-0.80261605481421,54.05803009468548],"type":"Point"}
}