{
  "type": "Feature",
  "properties": {
    "date:inception_lower":"2007-02-01",
    "date:inception_upper":"2007-02-28",
    "iso:country":"GB",
    "wof:name":"NN16 6UQ",
    "wof:placetype":"postalcode"
},
  "geometry": {"coordinates":[-0.537024,52.392277],"type":"Point"}
}