{
  "type": "Feature",
  "properties": {
    "date:inception_lower": "1980-01-01",
    "date:inception_upper": "1980-01-01",
    "iso:country": "GB",
    "wof:name": "TS26 0DW",
    "wof:placetype": "postalcode"
  },
  "geometry": {"coordinates":[-1.234859,54.682168],"type":"Point"}
}
