{
  "type": "Feature",
  "properties": {
    "iso:country":"GB",
    "wof:name":"TS26 0DW",
    "wof:placetype":"postalcode"
},
  "geometry": {"coordinates":[-1.23485885422003,54.68216786328807],"type":"Point"}
}