{
  "type": "Feature",
  "properties": {
    "iso:country":"GB",
    "wof:name":"NE23 8EE",
    "wof:placetype":"postalcode"
},
  "geometry": {"coordinates":[-1.60391326315525,55.08543851910477],"type":"Point"}
}