{
  "type": "Feature",
  "properties": {
    "iso:country": "GB",
    "wof:name": "NE23 8EE",
    "wof:placetype": "postalcode"
  },
  "geometry": {"coordinates":[-1.603913,55.085439],"type":"Point"}
}
