{
  "type": "Feature",
  "properties": {
    "date:inception_lower": "2013-09-01",
    "date:inception_upper": "2013-09-01",
    "iso:country": "GB",
    "wof:name": "CH1 1AD",
    "wof:placetype": "postalcode"
  },
  "geometry": {"coordinates":[-2.893235,53.188295],"type":"Point"}
}
