{
  "type": "Feature",
  "properties": {
    "date:inception_lower": "2022-03-01",
    "date:inception_upper": "2022-03-01",
    "iso:country": "GB",
    "wof:name": "GU6 8EW",
    "wof:placetype": "postalcode"
  },
  "geometry": {"coordinates":[-0.515236,51.097561],"type":"Point"}
}
