{
  "type": "Feature",
  "properties": {
    "iso:country":"GB",
    "wof:name":"NR31 8LG",
    "wof:placetype":"postalcode"
},
  "geometry": {"coordinates":[1.71437045523349,52.57919927766113],"type":"Point"}
}