{
  "type": "Feature",
  "properties": {
    "date:inception_lower":"1980-01-01",
    "date:inception_upper":"1980-01-31",
    "iso:country":"GB",
    "wof:name":"SE3 7AJ",
    "wof:placetype":"postalcode"
},
  "geometry": {"coordinates":[0.013742,51.476017],"type":"Point"}
}