{
  "type": "Feature",
  "properties": {
    "iso:country":"GB",
    "wof:name":"SE3 7AJ",
    "wof:placetype":"postalcode"
},
  "geometry": {"coordinates":[0.01374195207344,51.47601668243493],"type":"Point"}
}