{
  "type": "Feature",
  "properties": {
    "iso:country":"GB",
    "wof:name":"B60 3LE",
    "wof:placetype":"postalcode"
},
  "geometry": {"coordinates":[-2.06109395659161,52.32342906524056],"type":"Point"}
}