{
  "type": "Feature",
  "properties": {
    "date:inception_lower": "1980-01-01",
    "date:inception_upper": "1980-01-01",
    "iso:country": "GB",
    "wof:name": "B60 3LE",
    "wof:placetype": "postalcode"
  },
  "geometry": {"coordinates":[-2.061073,52.323236],"type":"Point"}
}
