{
  "type": "Feature",
  "properties": {
    "date:inception_lower": "1980-02-01",
    "date:inception_upper": "1980-02-01",
    "iso:country": "GB",
    "wof:name": "ML8 4EX",
    "wof:placetype": "postalcode"
  },
  "geometry": {"coordinates":[-3.82992,55.73898],"type":"Point"}
}
