{
  "type": "Feature",
  "properties": {
    "iso:country":"GB",
    "wof:name":"ML8 4EX",
    "wof:placetype":"postalcode"
},
  "geometry": {"coordinates":[-3.82991975405657,55.73898010538455],"type":"Point"}
}