{
  "type": "Feature",
  "properties": {
    "iso:country":"GB",
    "wof:name":"BD16 2SF",
    "wof:placetype":"postalcode"
},
  "geometry": {"coordinates":[-1.84133143974995,53.85764170023781],"type":"Point"}
}