{
  "type": "Feature",
  "properties": {
    "iso:country":"GB",
    "wof:name":"NN9 6DU",
    "wof:placetype":"postalcode"
},
  "geometry": {"coordinates":[-0.54038188404909,52.34037823871052],"type":"Point"}
}