{
  "type": "Feature",
  "properties": {
    "iso:country":"GB",
    "wof:name":"GL53 8PR",
    "wof:placetype":"postalcode"
},
  "geometry": {"coordinates":[-2.0457563635872,51.87859313372488],"type":"Point"}
}