{
  "type": "Feature",
  "properties": {
    "iso:country": "GB",
    "wof:name": "PE28 4AD",
    "wof:placetype": "postalcode"
  },
  "geometry": {"coordinates":[-0.205052,52.358831],"type":"Point"}
}
