{
  "type": "Feature",
  "properties": {
    "date:inception_lower":"2000-06-01",
    "date:inception_upper":"2000-06-30",
    "iso:country":"GB",
    "wof:name":"PE28 4AD",
    "wof:placetype":"postalcode"
},
  "geometry": {"coordinates":[-0.205052,52.358831],"type":"Point"}
}