{
  "type": "Feature",
  "properties": {
    "iso:country":"GB",
    "wof:name":"PE28 4AD",
    "wof:placetype":"postalcode"
},
  "geometry": {"coordinates":[-0.20505195041382,52.35883122193199],"type":"Point"}
}