{
  "type": "Feature",
  "properties": {
    "iso:country": "GB",
    "wof:name": "CO15 4LD",
    "wof:placetype": "postalcode"
  },
  "geometry": {"coordinates":[1.16206,51.804643],"type":"Point"}
}
