{
  "type": "Feature",
  "properties": {
    "iso:country":"GB",
    "wof:name":"CO15 4LD",
    "wof:placetype":"postalcode"
},
  "geometry": {"coordinates":[1.16206007876066,51.80464290000363],"type":"Point"}
}