{
  "type": "Feature",
  "properties": {
    "iso:country": "GB",
    "wof:name": "WV14 0JY",
    "wof:placetype": "postalcode"
  },
  "geometry": {"coordinates":[-2.075963,52.557251],"type":"Point"}
}
