{
  "type": "Feature",
  "properties": {
    "iso:country":"GB",
    "wof:name":"WV14 0JY",
    "wof:placetype":"postalcode"
},
  "geometry": {"coordinates":[-2.0759630782908,52.55725084272386],"type":"Point"}
}