{
  "type": "Feature",
  "properties": {
    "iso:country": "GB",
    "wof:name": "NR33 9EP",
    "wof:placetype": "postalcode"
  },
  "geometry": {"coordinates":[1.708502,52.461768],"type":"Point"}
}
