{
  "type": "Feature",
  "properties": {
    "date:inception_lower":"1980-01-01",
    "date:inception_upper":"1980-01-31",
    "iso:country":"GB",
    "wof:name":"SR2 9AS",
    "wof:placetype":"postalcode"
},
  "geometry": {"coordinates":[-1.390186,54.890514],"type":"Point"}
}