{
  "type": "Feature",
  "properties": {
    "iso:country":"GB",
    "wof:name":"SR2 9AS",
    "wof:placetype":"postalcode"
},
  "geometry": {"coordinates":[-1.39018577540913,54.89051430268844],"type":"Point"}
}