{
  "type": "Feature",
  "properties": {
    "date:inception_lower": "1994-05-01",
    "date:inception_upper": "1994-05-01",
    "iso:country": "GB",
    "wof:name": "L3 5TX",
    "wof:placetype": "postalcode"
  },
  "geometry": {"coordinates":[-2.965193,53.405881],"type":"Point"}
}
