{
  "type": "Feature",
  "properties": {
    "iso:country":"GB",
    "wof:name":"NW3 2SS",
    "wof:placetype":"postalcode"
},
  "geometry": {"coordinates":[-0.16313417419508,51.55780304275961],"type":"Point"}
}