{
  "type": "Feature",
  "properties": {
    "iso:country": "GB",
    "wof:name": "NW3 2SS",
    "wof:placetype": "postalcode"
  },
  "geometry": {"coordinates":[-0.163134,51.557803],"type":"Point"}
}
