{
  "type": "Feature",
  "properties": {
    "iso:country": "GB",
    "wof:name": "NG9 8GD",
    "wof:placetype": "postalcode"
  },
  "geometry": {"coordinates":[-1.2753,52.933366],"type":"Point"}
}
