{
  "type": "Feature",
  "properties": {
    "iso:country": "GB",
    "wof:name": "CV9 1NG",
    "wof:placetype": "postalcode"
  },
  "geometry": {"coordinates":[-1.527554,52.57007],"type":"Point"}
}
