{
  "type": "Feature",
  "properties": {
    "iso:country":"GB",
    "wof:name":"CV9 1NG",
    "wof:placetype":"postalcode"
},
  "geometry": {"coordinates":[-1.52755380212246,52.57007043772346],"type":"Point"}
}