{
  "type": "Feature",
  "properties": {
    "date:inception_lower": "1980-01-01",
    "date:inception_upper": "1980-01-01",
    "iso:country": "GB",
    "wof:name": "CV9 1NG",
    "wof:placetype": "postalcode"
  },
  "geometry": {"coordinates":[-1.527554,52.57007],"type":"Point"}
}
