{
  "type": "Feature",
  "properties": {
    "iso:country":"GB",
    "wof:name":"EH48 4DD",
    "wof:placetype":"postalcode"
},
  "geometry": {"coordinates":[-3.63521739690094,55.90439628502059],"type":"Point"}
}