{
  "type": "Feature",
  "properties": {
    "date:inception_lower": "1980-01-01",
    "date:inception_upper": "1980-01-01",
    "iso:country": "GB",
    "wof:name": "IP31 1EN",
    "wof:placetype": "postalcode"
  },
  "geometry": {"coordinates":[0.777558,52.324012],"type":"Point"}
}
