{
  "type": "Feature",
  "properties": {
    "iso:country":"GB",
    "wof:name":"IP31 1EN",
    "wof:placetype":"postalcode"
},
  "geometry": {"coordinates":[0.77755827744345,52.32401201788644],"type":"Point"}
}