{
  "type": "Feature",
  "properties": {
    "iso:country":"GB",
    "wof:name":"W1J 8EU",
    "wof:placetype":"postalcode"
},
  "geometry": {"coordinates":[-0.14319687911353,51.50678963716837],"type":"Point"}
}