{
  "type": "Feature",
  "properties": {
    "iso:country": "GB",
    "wof:name": "BD23 6BJ",
    "wof:placetype": "postalcode"
  },
  "geometry": {"coordinates":[-1.981716,54.051921],"type":"Point"}
}
