{
  "type": "Feature",
  "properties": {
    "iso:country":"GB",
    "wof:name":"BD23 6BJ",
    "wof:placetype":"postalcode"
},
  "geometry": {"coordinates":[-1.98177297460433,54.05161898035707],"type":"Point"}
}