{
  "type": "Feature",
  "properties": {
    "iso:country": "GB",
    "wof:name": "WN7 5DP",
    "wof:placetype": "postalcode"
  },
  "geometry": {"coordinates":[-2.535832,53.50545],"type":"Point"}
}
