{
  "type": "Feature",
  "properties": {
    "date:inception_lower": "1980-01-01",
    "date:inception_upper": "1980-01-01",
    "iso:country": "GB",
    "wof:name": "WN7 5DP",
    "wof:placetype": "postalcode"
  },
  "geometry": {"coordinates":[-2.535832,53.50545],"type":"Point"}
}
