{
  "type": "Feature",
  "properties": {
    "iso:country":"GB",
    "wof:name":"ST15 0QA",
    "wof:placetype":"postalcode"
},
  "geometry": {"coordinates":[-2.17649226109705,52.91811086736659],"type":"Point"}
}