{
  "type": "Feature",
  "properties": {
    "iso:country": "GB",
    "wof:name": "ST15 0QA",
    "wof:placetype": "postalcode"
  },
  "geometry": {"coordinates":[-2.176492,52.918111],"type":"Point"}
}
