{
  "type": "Feature",
  "properties": {
    "iso:country": "GB",
    "wof:name": "SE13 6QW",
    "wof:placetype": "postalcode"
  },
  "geometry": {"coordinates":[-0.015686,51.452948],"type":"Point"}
}
