{
  "type": "Feature",
  "properties": {
    "iso:country":"GB",
    "wof:name":"CM3 3BN",
    "wof:placetype":"postalcode"
},
  "geometry": {"coordinates":[0.53893417319474,51.75904479318852],"type":"Point"}
}