{
  "type": "Feature",
  "properties": {
    "date:inception_lower": "1980-01-01",
    "date:inception_upper": "1980-01-01",
    "iso:country": "GB",
    "wof:name": "CM3 3BN",
    "wof:placetype": "postalcode"
  },
  "geometry": {"coordinates":[0.538934,51.759045],"type":"Point"}
}
