{
  "type": "Feature",
  "properties": {
    "iso:country": "GB",
    "wof:name": "HD3 4HE",
    "wof:placetype": "postalcode"
  },
  "geometry": {"coordinates":[-1.821028,53.644857],"type":"Point"}
}
