{
  "type": "Feature",
  "properties": {
    "date:inception_lower":"1980-01-01",
    "date:inception_upper":"1980-01-31",
    "iso:country":"GB",
    "wof:name":"BS10 5NB",
    "wof:placetype":"postalcode"
},
  "geometry": {"coordinates":[-2.591016,51.494806],"type":"Point"}
}