{
  "type": "Feature",
  "properties": {
    "iso:country":"GB",
    "wof:name":"BS10 5NB",
    "wof:placetype":"postalcode"
},
  "geometry": {"coordinates":[-2.59296212573427,51.49726990811052],"type":"Point"}
}