{
  "type": "Feature",
  "properties": {
    "date:inception_lower": "1980-01-01",
    "date:inception_upper": "1980-01-01",
    "iso:country": "GB",
    "wof:name": "SG7 5JG",
    "wof:placetype": "postalcode"
  },
  "geometry": {"coordinates":[-0.160277,52.06546],"type":"Point"}
}
