{
  "type": "Feature",
  "properties": {
    "iso:country":"GB",
    "wof:name":"SG7 5JG",
    "wof:placetype":"postalcode"
},
  "geometry": {"coordinates":[-0.16027682542384,52.06545961884099],"type":"Point"}
}