{
  "type": "Feature",
  "properties": {
    "iso:country":"GB",
    "wof:name":"CO2 7DX",
    "wof:placetype":"postalcode"
},
  "geometry": {"coordinates":[0.90323693346786,51.88781392944106],"type":"Point"}
}