{
  "type": "Feature",
  "properties": {
    "iso:country": "GB",
    "wof:name": "RG2 0DA",
    "wof:placetype": "postalcode"
  },
  "geometry": {"coordinates":[-0.971886,51.419644],"type":"Point"}
}
