{
  "type": "Feature",
  "properties": {
    "date:inception_lower": "2019-03-01",
    "date:inception_upper": "2019-03-01",
    "iso:country": "GB",
    "wof:name": "EX1 3FA",
    "wof:placetype": "postalcode"
  },
  "geometry": {"coordinates":[-3.466208,50.733028],"type":"Point"}
}
