{
  "type": "Feature",
  "properties": {
    "date:inception_lower": "2018-03-01",
    "date:inception_upper": "2018-03-01",
    "iso:country": "GB",
    "wof:name": "EH3 9RF",
    "wof:placetype": "postalcode"
  },
  "geometry": {"coordinates":[-3.207617,55.94191],"type":"Point"}
}
