{
  "type": "Feature",
  "properties": {
    "date:inception_lower":"1990-02-01",
    "date:inception_upper":"1990-02-28",
    "iso:country":"GB",
    "wof:name":"RG25 3TN",
    "wof:placetype":"postalcode"
},
  "geometry": {"coordinates":[-1.26235,51.244339],"type":"Point"}
}