{
  "type": "Feature",
  "properties": {
    "iso:country": "GB",
    "wof:name": "RG25 3TN",
    "wof:placetype": "postalcode"
  },
  "geometry": {"coordinates":[-1.26235,51.244339],"type":"Point"}
}
