{
  "type": "Feature",
  "properties": {
    "iso:country":"GB",
    "wof:name":"PE19 5XE",
    "wof:placetype":"postalcode"
},
  "geometry": {"coordinates":[-0.25549383360266,52.2928806522041],"type":"Point"}
}