{
  "type": "Feature",
  "properties": {
    "iso:country": "GB",
    "wof:name": "NE11 0XT",
    "wof:placetype": "postalcode"
  },
  "geometry": {"coordinates":[-1.621385,54.903909],"type":"Point"}
}
