{
  "type": "Feature",
  "properties": {
    "date:inception_lower": "1980-01-01",
    "date:inception_upper": "1980-01-01",
    "iso:country": "GB",
    "wof:name": "BS7 9TX",
    "wof:placetype": "postalcode"
  },
  "geometry": {"coordinates":[-2.572657,51.482885],"type":"Point"}
}
