{
  "type": "Feature",
  "properties": {
    "iso:country":"GB",
    "wof:name":"BS16 3TU",
    "wof:placetype":"postalcode"
},
  "geometry": {"coordinates":[-2.52829058649157,51.48060308560848],"type":"Point"}
}