{
  "type": "Feature",
  "properties": {
    "iso:country": "GB",
    "wof:name": "BS16 3TU",
    "wof:placetype": "postalcode"
  },
  "geometry": {"coordinates":[-2.528291,51.480603],"type":"Point"}
}
