{
  "type": "Feature",
  "properties": {
    "iso:country": "GB",
    "wof:name": "RG10 0DN",
    "wof:placetype": "postalcode"
  },
  "geometry": {"coordinates":[-0.85436,51.458469],"type":"Point"}
}
