{
  "type": "Feature",
  "properties": {
    "iso:country":"GB",
    "wof:name":"RG10 0DN",
    "wof:placetype":"postalcode"
},
  "geometry": {"coordinates":[-0.85436053893729,51.45846875571419],"type":"Point"}
}