{
  "type": "Feature",
  "properties": {
    "iso:country": "GB",
    "wof:name": "FK9 5GQ",
    "wof:placetype": "postalcode"
  },
  "geometry": {"coordinates":[-3.950552,56.136106],"type":"Point"}
}
