{
  "type": "Feature",
  "properties": {
    "iso:country":"GB",
    "wof:name":"S11 8TB",
    "wof:placetype":"postalcode"
},
  "geometry": {"coordinates":[-1.5072723680982,53.36608959990365],"type":"Point"}
}