{
  "type": "Feature",
  "properties": {
    "iso:country": "GB",
    "wof:name": "W12 8QP",
    "wof:placetype": "postalcode"
  },
  "geometry": {"coordinates":[-0.225736,51.502357],"type":"Point"}
}
