{
  "type": "Feature",
  "properties": {
    "iso:country":"GB",
    "wof:name":"W12 8QP",
    "wof:placetype":"postalcode"
},
  "geometry": {"coordinates":[-0.22566135456159,51.50242793560388],"type":"Point"}
}