{
  "type": "Feature",
  "properties": {
    "iso:country":"GB",
    "wof:name":"W7 3QE",
    "wof:placetype":"postalcode"
},
  "geometry": {"coordinates":[-0.33189119205735,51.50961608916682],"type":"Point"}
}