{
  "type": "Feature",
  "properties": {
    "iso:country":"GB",
    "wof:name":"EX8 5LW",
    "wof:placetype":"postalcode"
},
  "geometry": {"coordinates":[-3.41739931550008,50.64782817595284],"type":"Point"}
}