{
  "type": "Feature",
  "properties": {
    "iso:country": "GB",
    "wof:name": "KA1 5SG",
    "wof:placetype": "postalcode"
  },
  "geometry": {"coordinates":[-4.545624,55.561102],"type":"Point"}
}
