{
  "type": "Feature",
  "properties": {
    "iso:country":"GB",
    "wof:name":"KA1 5SG",
    "wof:placetype":"postalcode"
},
  "geometry": {"coordinates":[-4.54562414147718,55.56110235172508],"type":"Point"}
}