{
  "type": "Feature",
  "properties": {
    "iso:country": "GB",
    "wof:name": "IV18 0BF",
    "wof:placetype": "postalcode"
  },
  "geometry": {"coordinates":[-4.16099,57.689419],"type":"Point"}
}
