{
  "type": "Feature",
  "properties": {
    "date:inception_lower": "1980-01-01",
    "date:inception_upper": "1980-01-01",
    "iso:country": "GB",
    "wof:name": "S80 4SY",
    "wof:placetype": "postalcode"
  },
  "geometry": {"coordinates":[-1.20784,53.28565],"type":"Point"}
}
