{
  "type": "Feature",
  "properties": {
    "date:inception_lower":"1998-12-01",
    "date:inception_upper":"1998-12-31",
    "iso:country":"GB",
    "wof:name":"CB1 9JL",
    "wof:placetype":"postalcode"
},
  "geometry": {"coordinates":[0.174682,52.183633],"type":"Point"}
}