{
  "type": "Feature",
  "properties": {
    "date:inception_lower": "2003-11-01",
    "date:inception_upper": "2003-11-01",
    "iso:country": "GB",
    "wof:name": "EX14 1DH",
    "wof:placetype": "postalcode"
  },
  "geometry": {"coordinates":[-3.192645,50.798102],"type":"Point"}
}
