{
  "type": "Feature",
  "properties": {
    "iso:country":"GB",
    "wof:name":"SE10 9JN",
    "wof:placetype":"postalcode"
},
  "geometry": {"coordinates":[-0.00810402331888,51.47964522377974],"type":"Point"}
}