{
  "type": "Feature",
  "properties": {
    "iso:country":"GB",
    "wof:name":"LE6 0YH",
    "wof:placetype":"postalcode"
},
  "geometry": {"coordinates":[-1.22285578713881,52.65369733279923],"type":"Point"}
}