{
  "type": "Feature",
  "properties": {
    "iso:country":"GB",
    "wof:name":"WN3 6SF",
    "wof:placetype":"postalcode"
},
  "geometry": {"coordinates":[-2.65698495459204,53.52244479785103],"type":"Point"}
}