{
  "type": "Feature",
  "properties": {
    "iso:country":"GB",
    "wof:name":"G81 1DR",
    "wof:placetype":"postalcode"
},
  "geometry": {"coordinates":[-4.3920748274972,55.89957295311152],"type":"Point"}
}