{
  "type": "Feature",
  "properties": {
    "iso:country": "GB",
    "wof:name": "G81 1DR",
    "wof:placetype": "postalcode"
  },
  "geometry": {"coordinates":[-4.392075,55.899573],"type":"Point"}
}
