{
  "type": "Feature",
  "properties": {
    "iso:country":"GB",
    "wof:name":"SA1 4LX",
    "wof:placetype":"postalcode"
},
  "geometry": {"coordinates":[-3.9646355054537,51.61382501807586],"type":"Point"}
}