{
  "type": "Feature",
  "properties": {
    "iso:country": "GB",
    "wof:name": "CM24 8AX",
    "wof:placetype": "postalcode"
  },
  "geometry": {"coordinates":[0.19734,51.901455],"type":"Point"}
}
