{
  "type": "Feature",
  "properties": {
    "iso:country":"GB",
    "wof:name":"CM24 8AX",
    "wof:placetype":"postalcode"
},
  "geometry": {"coordinates":[0.19733960577369,51.9014553090094],"type":"Point"}
}