{
  "type": "Feature",
  "properties": {
    "iso:country":"GB",
    "wof:name":"NG10 4DU",
    "wof:placetype":"postalcode"
},
  "geometry": {"coordinates":[-1.29450182603359,52.90717789589412],"type":"Point"}
}