{
  "type": "Feature",
  "properties": {
    "date:inception_lower": "1980-01-01",
    "date:inception_upper": "1980-01-01",
    "iso:country": "GB",
    "wof:name": "NG10 4DU",
    "wof:placetype": "postalcode"
  },
  "geometry": {"coordinates":[-1.294502,52.907178],"type":"Point"}
}
