{
  "type": "Feature",
  "properties": {
    "iso:country":"GB",
    "wof:name":"GU31 4EA",
    "wof:placetype":"postalcode"
},
  "geometry": {"coordinates":[-0.93236527623275,51.00386610586456],"type":"Point"}
}