{
  "type": "Feature",
  "properties": {
    "date:inception_lower": "1980-01-01",
    "date:inception_upper": "1980-01-01",
    "iso:country": "GB",
    "wof:name": "GU31 4EA",
    "wof:placetype": "postalcode"
  },
  "geometry": {"coordinates":[-0.932365,51.003866],"type":"Point"}
}
