{
  "type": "Feature",
  "properties": {
    "iso:country":"GB",
    "wof:name":"GL56 9PH",
    "wof:placetype":"postalcode"
},
  "geometry": {"coordinates":[-1.65959444542788,52.00675119117405],"type":"Point"}
}