{
  "type": "Feature",
  "properties": {
    "iso:country": "GB",
    "wof:name": "GL56 9PH",
    "wof:placetype": "postalcode"
  },
  "geometry": {"coordinates":[-1.659594,52.006751],"type":"Point"}
}
