{
  "type": "Feature",
  "properties": {
    "date:inception_lower":"1980-01-01",
    "date:inception_upper":"1980-01-31",
    "iso:country":"GB",
    "wof:name":"GL56 9PH",
    "wof:placetype":"postalcode"
},
  "geometry": {"coordinates":[-1.659594,52.006751],"type":"Point"}
}