{
  "type": "Feature",
  "properties": {
    "iso:country":"GB",
    "wof:name":"DL3 6QZ",
    "wof:placetype":"postalcode"
},
  "geometry": {"coordinates":[-1.56013399819663,54.53596907368893],"type":"Point"}
}