{
  "type": "Feature",
  "properties": {
    "iso:country": "GB",
    "wof:name": "BA2 2HW",
    "wof:placetype": "postalcode"
  },
  "geometry": {"coordinates":[-2.378682,51.370432],"type":"Point"}
}
