{
  "type": "Feature",
  "properties": {
    "iso:country":"GB",
    "wof:name":"AL3 8JX",
    "wof:placetype":"postalcode"
},
  "geometry": {"coordinates":[-0.45897904793889,51.83428227344359],"type":"Point"}
}