{
  "type": "Feature",
  "properties": {
    "iso:country": "GB",
    "wof:name": "ME15 6QG",
    "wof:placetype": "postalcode"
  },
  "geometry": {"coordinates":[0.521456,51.264802],"type":"Point"}
}
