{
  "type": "Feature",
  "properties": {
    "date:inception_lower": "1980-01-01",
    "date:inception_upper": "1980-01-01",
    "iso:country": "GB",
    "wof:name": "LL58 8UG",
    "wof:placetype": "postalcode"
  },
  "geometry": {"coordinates":[-4.136159,53.294947],"type":"Point"}
}
