{
  "type": "Feature",
  "properties": {
    "iso:country":"GB",
    "wof:name":"LL58 8UG",
    "wof:placetype":"postalcode"
},
  "geometry": {"coordinates":[-4.13615873647569,53.29494652717727],"type":"Point"}
}