{
  "type": "Feature",
  "properties": {
    "date:inception_lower": "2013-02-01",
    "date:inception_upper": "2013-02-01",
    "iso:country": "GB",
    "wof:name": "LA12 0AP",
    "wof:placetype": "postalcode"
  },
  "geometry": {"coordinates":[-3.147897,54.172853],"type":"Point"}
}
