{
  "type": "Feature",
  "properties": {
    "iso:country":"GB",
    "wof:name":"LA12 0AP",
    "wof:placetype":"postalcode"
},
  "geometry": {"coordinates":[-3.14789711843805,54.1728533097826],"type":"Point"}
}