{
  "type": "Feature",
  "properties": {
    "iso:country":"GB",
    "wof:name":"SP10 1LD",
    "wof:placetype":"postalcode"
},
  "geometry": {"coordinates":[-1.46447460104557,51.21396624064839],"type":"Point"}
}