{
  "type": "Feature",
  "properties": {
    "iso:country":"GB",
    "wof:name":"CF44 6YF",
    "wof:placetype":"postalcode"
},
  "geometry": {"coordinates":[-3.43224199435713,51.70316688772451],"type":"Point"}
}