{
  "type": "Feature",
  "properties": {
    "date:inception_lower": "1998-06-01",
    "date:inception_upper": "1998-06-01",
    "iso:country": "GB",
    "wof:name": "S4 7UL",
    "wof:placetype": "postalcode"
  },
  "geometry": {"coordinates":[-1.454719,53.389654],"type":"Point"}
}
