{
  "type": "Feature",
  "properties": {
    "iso:country": "GB",
    "wof:name": "S4 7UL",
    "wof:placetype": "postalcode"
  },
  "geometry": {"coordinates":[-1.45475,53.389636],"type":"Point"}
}
