{
  "type": "Feature",
  "properties": {
    "iso:country": "GB",
    "wof:name": "NE11 9RY",
    "wof:placetype": "postalcode"
  },
  "geometry": {"coordinates":[-1.641023,54.943805],"type":"Point"}
}
