{
  "type": "Feature",
  "properties": {
    "iso:country":"GB",
    "wof:name":"B17 8PU",
    "wof:placetype":"postalcode"
},
  "geometry": {"coordinates":[-1.96215590132022,52.46688486841522],"type":"Point"}
}