{
  "type": "Feature",
  "properties": {
    "date:inception_lower": "1980-01-01",
    "date:inception_upper": "1980-01-01",
    "iso:country": "GB",
    "wof:name": "B17 8PU",
    "wof:placetype": "postalcode"
  },
  "geometry": {"coordinates":[-1.962156,52.466885],"type":"Point"}
}
