{
  "type": "Feature",
  "properties": {
    "iso:country": "GB",
    "wof:name": "PE12 0QY",
    "wof:placetype": "postalcode"
  },
  "geometry": {"coordinates":[-0.02217,52.659431],"type":"Point"}
}
