{
  "type": "Feature",
  "properties": {
    "date:inception_lower": "1980-01-01",
    "date:inception_upper": "1980-01-01",
    "iso:country": "GB",
    "wof:name": "PE12 0QY",
    "wof:placetype": "postalcode"
  },
  "geometry": {"coordinates":[-0.02217,52.659431],"type":"Point"}
}
