{
  "type": "Feature",
  "properties": {
    "iso:country":"GB",
    "wof:name":"PE12 0QY",
    "wof:placetype":"postalcode"
},
  "geometry": {"coordinates":[-0.02217053660187,52.65943073338715],"type":"Point"}
}