{
  "type": "Feature",
  "properties": {
    "date:inception_lower": "1980-01-01",
    "date:inception_upper": "1980-01-01",
    "iso:country": "GB",
    "wof:name": "GL51 6TE",
    "wof:placetype": "postalcode"
  },
  "geometry": {"coordinates":[-2.141822,51.892299],"type":"Point"}
}
