{
  "type": "Feature",
  "properties": {
    "date:inception_lower": "1980-01-01",
    "date:inception_upper": "1980-01-01",
    "iso:country": "GB",
    "wof:name": "CV23 8EB",
    "wof:placetype": "postalcode"
  },
  "geometry": {"coordinates":[-1.351106,52.305545],"type":"Point"}
}
