{
  "type": "Feature",
  "properties": {
    "date:inception_lower": "1990-02-01",
    "date:inception_upper": "1990-02-01",
    "iso:country": "GB",
    "wof:name": "SL4 4NY",
    "wof:placetype": "postalcode"
  },
  "geometry": {"coordinates":[-0.642885,51.476957],"type":"Point"}
}
