{
  "type": "Feature",
  "properties": {
    "iso:country": "GB",
    "wof:name": "SL4 4NY",
    "wof:placetype": "postalcode"
  },
  "geometry": {"coordinates":[-0.642885,51.476957],"type":"Point"}
}
