{
  "type": "Feature",
  "properties": {
    "iso:country":"GB",
    "wof:name":"SL4 4NY",
    "wof:placetype":"postalcode"
},
  "geometry": {"coordinates":[-0.64288484749232,51.47695675604449],"type":"Point"}
}