{
  "type": "Feature",
  "properties": {
    "iso:country":"GB",
    "wof:name":"B32 4BB",
    "wof:placetype":"postalcode"
},
  "geometry": {"coordinates":[-2.0207725054247,52.41071032551486],"type":"Point"}
}