{
  "type": "Feature",
  "properties": {
    "iso:country":"GB",
    "wof:name":"DN14 7HU",
    "wof:placetype":"postalcode"
},
  "geometry": {"coordinates":[-0.96042121004457,53.7506162091645],"type":"Point"}
}