{
  "type": "Feature",
  "properties": {
    "iso:country":"GB",
    "wof:name":"SE16 4LL",
    "wof:placetype":"postalcode"
},
  "geometry": {"coordinates":[-0.05158077404245,51.50131063126405],"type":"Point"}
}