{
  "type": "Feature",
  "properties": {
    "date:inception_lower": "1985-04-01",
    "date:inception_upper": "1985-04-01",
    "iso:country": "GB",
    "wof:name": "SE16 4LL",
    "wof:placetype": "postalcode"
  },
  "geometry": {"coordinates":[-0.051581,51.501311],"type":"Point"}
}
