{
  "type": "Feature",
  "properties": {
    "date:inception_lower":"2015-12-01",
    "date:inception_upper":"2015-12-31",
    "iso:country":"GB",
    "wof:name":"BB9 8DQ",
    "wof:placetype":"postalcode"
},
  "geometry": {"coordinates":[-2.184085,53.838421],"type":"Point"}
}