{
  "type": "Feature",
  "properties": {
    "date:inception_lower": "1996-06-01",
    "date:inception_upper": "1996-06-01",
    "iso:country": "GB",
    "wof:name": "G12 9YH",
    "wof:placetype": "postalcode"
  },
  "geometry": {"coordinates":[-4.3134,55.880199],"type":"Point"}
}
