{
  "type": "Feature",
  "properties": {
    "iso:country":"GB",
    "wof:name":"SO45 5WT",
    "wof:placetype":"postalcode"
},
  "geometry": {"coordinates":[-1.42678661610676,50.85941127789591],"type":"Point"}
}