{
  "type": "Feature",
  "properties": {
    "date:inception_lower":"1994-12-01",
    "date:inception_upper":"1994-12-31",
    "iso:country":"GB",
    "wof:name":"SO45 5WT",
    "wof:placetype":"postalcode"
},
  "geometry": {"coordinates":[-1.426787,50.859411],"type":"Point"}
}