{
  "type": "Feature",
  "properties": {
    "iso:country": "GB",
    "wof:name": "TA10 0LA",
    "wof:placetype": "postalcode"
  },
  "geometry": {"coordinates":[-2.846517,51.019297],"type":"Point"}
}
