{
  "type": "Feature",
  "properties": {
    "iso:country": "GB",
    "wof:name": "IG10 2QL",
    "wof:placetype": "postalcode"
  },
  "geometry": {"coordinates":[0.072575,51.657642],"type":"Point"}
}
