{
  "type": "Feature",
  "properties": {
    "date:inception_lower": "1980-01-01",
    "date:inception_upper": "1980-01-01",
    "iso:country": "GB",
    "wof:name": "IG10 2QL",
    "wof:placetype": "postalcode"
  },
  "geometry": {"coordinates":[0.072575,51.657642],"type":"Point"}
}
