{
  "type": "Feature",
  "properties": {
    "iso:country":"GB",
    "wof:name":"LE3 9LF",
    "wof:placetype":"postalcode"
},
  "geometry": {"coordinates":[-1.1819386629295,52.65123747600278],"type":"Point"}
}