{
  "type": "Feature",
  "properties": {
    "iso:country": "GB",
    "wof:name": "LE3 9LF",
    "wof:placetype": "postalcode"
  },
  "geometry": {"coordinates":[-1.181939,52.651237],"type":"Point"}
}
