{
  "type": "Feature",
  "properties": {
    "iso:country": "GB",
    "wof:name": "BA5 1LF",
    "wof:placetype": "postalcode"
  },
  "geometry": {"coordinates":[-2.693352,51.208063],"type":"Point"}
}
