{
  "type": "Feature",
  "properties": {
    "iso:country":"GB",
    "wof:name":"BA5 1LF",
    "wof:placetype":"postalcode"
},
  "geometry": {"coordinates":[-2.69335247473712,51.20806328421374],"type":"Point"}
}