{
  "type": "Feature",
  "properties": {
    "iso:country": "GB",
    "wof:name": "G66 1PU",
    "wof:placetype": "postalcode"
  },
  "geometry": {"coordinates":[-4.156637,55.942159],"type":"Point"}
}
