{
  "type": "Feature",
  "properties": {
    "iso:country":"GB",
    "wof:name":"G66 1PU",
    "wof:placetype":"postalcode"
},
  "geometry": {"coordinates":[-4.15628874941975,55.94172959095155],"type":"Point"}
}