{
  "type": "Feature",
  "properties": {
    "iso:country": "GB",
    "wof:name": "LU4 0PL",
    "wof:placetype": "postalcode"
  },
  "geometry": {"coordinates":[-0.49189,51.89961],"type":"Point"}
}
