{
  "type": "Feature",
  "properties": {
    "iso:country":"GB",
    "wof:name":"E14 6DW",
    "wof:placetype":"postalcode"
},
  "geometry": {"coordinates":[-0.0175925785087,51.51256635241116],"type":"Point"}
}