{
  "type": "Feature",
  "properties": {
    "iso:country":"GB",
    "wof:name":"LA14 2AD",
    "wof:placetype":"postalcode"
},
  "geometry": {"coordinates":[-3.21645988217324,54.11095339238787],"type":"Point"}
}