{
  "type": "Feature",
  "properties": {
    "iso:country": "GB",
    "wof:name": "PE14 7SA",
    "wof:placetype": "postalcode"
  },
  "geometry": {"coordinates":[0.281032,52.721211],"type":"Point"}
}
