{
  "type": "Feature",
  "properties": {
    "iso:country": "GB",
    "wof:name": "HP27 9SL",
    "wof:placetype": "postalcode"
  },
  "geometry": {"coordinates":[-0.861023,51.737933],"type":"Point"}
}
