{
  "type": "Feature",
  "properties": {
    "iso:country":"GB",
    "wof:name":"DE73 5SX",
    "wof:placetype":"postalcode"
},
  "geometry": {"coordinates":[-1.44110839145956,52.87013909694064],"type":"Point"}
}