{
  "type": "Feature",
  "properties": {
    "date:inception_lower":"2004-09-01",
    "date:inception_upper":"2004-09-30",
    "iso:country":"GB",
    "wof:name":"DE73 5SX",
    "wof:placetype":"postalcode"
},
  "geometry": {"coordinates":[-1.441108,52.870139],"type":"Point"}
}