{
  "type": "Feature",
  "properties": {
    "iso:country":"GB",
    "wof:name":"RH12 4TY",
    "wof:placetype":"postalcode"
},
  "geometry": {"coordinates":[-0.28702449954589,51.07892272220091],"type":"Point"}
}