{
  "type": "Feature",
  "properties": {
    "date:inception_lower": "2020-04-01",
    "date:inception_upper": "2020-04-01",
    "iso:country": "GB",
    "wof:name": "TQ13 8FN",
    "wof:placetype": "postalcode"
  },
  "geometry": {"coordinates":[-3.837487,50.674706],"type":"Point"}
}
