{
  "type": "Feature",
  "properties": {
    "iso:country":"GB",
    "wof:name":"LE3 6HJ",
    "wof:placetype":"postalcode"
},
  "geometry": {"coordinates":[-1.16552031538506,52.63935518167483],"type":"Point"}
}