{
  "type": "Feature",
  "properties": {
    "iso:country":"GB",
    "wof:name":"TS10 2LD",
    "wof:placetype":"postalcode"
},
  "geometry": {"coordinates":[-1.05187449677686,54.60523936239116],"type":"Point"}
}