{
  "type": "Feature",
  "properties": {
    "iso:country": "GB",
    "wof:name": "TS10 2LD",
    "wof:placetype": "postalcode"
  },
  "geometry": {"coordinates":[-1.051874,54.605239],"type":"Point"}
}
