{
  "type": "Feature",
  "properties": {
    "date:inception_lower": "1980-01-01",
    "date:inception_upper": "1980-01-01",
    "iso:country": "GB",
    "wof:name": "CA14 5JH",
    "wof:placetype": "postalcode"
  },
  "geometry": {"coordinates":[-3.564793,54.620511],"type":"Point"}
}
