{
  "type": "Feature",
  "properties": {
    "date:inception_lower": "1980-01-01",
    "date:inception_upper": "1980-01-01",
    "iso:country": "GB",
    "wof:name": "HR1 3PX",
    "wof:placetype": "postalcode"
  },
  "geometry": {"coordinates":[-2.641881,52.083163],"type":"Point"}
}
