{
  "type": "Feature",
  "properties": {
    "iso:country":"GB",
    "wof:name":"HR1 3PX",
    "wof:placetype":"postalcode"
},
  "geometry": {"coordinates":[-2.64188125734514,52.08316326938323],"type":"Point"}
}