{
  "type": "Feature",
  "properties": {
    "iso:country":"GB",
    "wof:name":"EH19 2LL",
    "wof:placetype":"postalcode"
},
  "geometry": {"coordinates":[-3.12000663239427,55.87203563539536],"type":"Point"}
}