{
  "type": "Feature",
  "properties": {
    "iso:country":"GB",
    "wof:name":"BA3 4GW",
    "wof:placetype":"postalcode"
},
  "geometry": {"coordinates":[-2.58070021158079,51.28824655827748],"type":"Point"}
}