{
  "type": "Feature",
  "properties": {
    "date:inception_lower": "2001-06-01",
    "date:inception_upper": "2001-06-01",
    "iso:country": "GB",
    "wof:name": "BA3 4GW",
    "wof:placetype": "postalcode"
  },
  "geometry": {"coordinates":[-2.580755,51.287882],"type":"Point"}
}
