{
  "type": "Feature",
  "properties": {
    "iso:country":"GB",
    "wof:name":"ML6 9QJ",
    "wof:placetype":"postalcode"
},
  "geometry": {"coordinates":[-3.96129753499439,55.85461801698024],"type":"Point"}
}