{
  "type": "Feature",
  "properties": {
    "iso:country":"GB",
    "wof:name":"SW1P 1PA",
    "wof:placetype":"postalcode"
},
  "geometry": {"coordinates":[-0.13717432752552,51.49546246747071],"type":"Point"}
}