{
  "type": "Feature",
  "properties": {
    "date:inception_lower": "1980-01-01",
    "date:inception_upper": "1980-01-01",
    "iso:country": "GB",
    "wof:name": "SW1P 1PA",
    "wof:placetype": "postalcode"
  },
  "geometry": {"coordinates":[-0.137158,51.495599],"type":"Point"}
}
