{
  "type": "Feature",
  "properties": {
    "date:inception_lower": "1980-01-01",
    "date:inception_upper": "1980-01-01",
    "iso:country": "GB",
    "wof:name": "B46 1JZ",
    "wof:placetype": "postalcode"
  },
  "geometry": {"coordinates":[-1.70842,52.516451],"type":"Point"}
}
