{
  "type": "Feature",
  "properties": {
    "date:inception_lower":"1980-01-01",
    "date:inception_upper":"1980-01-31",
    "iso:country":"GB",
    "wof:name":"B46 1JZ",
    "wof:placetype":"postalcode"
},
  "geometry": {"coordinates":[-1.707554,52.516081],"type":"Point"}
}