{
  "type": "Feature",
  "properties": {
    "iso:country":"GB",
    "wof:name":"B46 1JZ",
    "wof:placetype":"postalcode"
},
  "geometry": {"coordinates":[-1.70842834513531,52.51643550094667],"type":"Point"}
}