{
  "type": "Feature",
  "properties": {
    "iso:country": "GB",
    "wof:name": "OL12 9PG",
    "wof:placetype": "postalcode"
  },
  "geometry": {"coordinates":[-2.136062,53.650827],"type":"Point"}
}
