{
  "type": "Feature",
  "properties": {
    "iso:country":"GB",
    "wof:name":"OL12 9PG",
    "wof:placetype":"postalcode"
},
  "geometry": {"coordinates":[-2.13606154780212,53.65082730959266],"type":"Point"}
}