{
  "type": "Feature",
  "properties": {
    "iso:country": "GB",
    "wof:name": "PO20 8PA",
    "wof:placetype": "postalcode"
  },
  "geometry": {"coordinates":[-0.861605,50.764367],"type":"Point"}
}
