{
  "type": "Feature",
  "properties": {
    "iso:country":"GB",
    "wof:name":"LN5 9GY",
    "wof:placetype":"postalcode"
},
  "geometry": {"coordinates":[-0.64354114027443,53.12449567375655],"type":"Point"}
}