{
  "type": "Feature",
  "properties": {
    "date:inception_lower": "2007-01-01",
    "date:inception_upper": "2007-01-01",
    "iso:country": "GB",
    "wof:name": "LN5 9GY",
    "wof:placetype": "postalcode"
  },
  "geometry": {"coordinates":[-0.643541,53.124496],"type":"Point"}
}
