{
  "type": "Feature",
  "properties": {
    "iso:country": "GB",
    "wof:name": "NG17 5JX",
    "wof:placetype": "postalcode"
  },
  "geometry": {"coordinates":[-1.236492,53.118735],"type":"Point"}
}
