{
  "type": "Feature",
  "properties": {
    "date:inception_lower": "1980-01-01",
    "date:inception_upper": "1980-01-01",
    "iso:country": "GB",
    "wof:name": "SW6 7PF",
    "wof:placetype": "postalcode"
  },
  "geometry": {"coordinates":[-0.218798,51.48371],"type":"Point"}
}
