{
  "type": "Feature",
  "properties": {
    "iso:country":"GB",
    "wof:name":"SW6 7PF",
    "wof:placetype":"postalcode"
},
  "geometry": {"coordinates":[-0.21879783910496,51.48370953283393],"type":"Point"}
}