{
  "type": "Feature",
  "properties": {
    "iso:country": "GB",
    "wof:name": "TF8 7LZ",
    "wof:placetype": "postalcode"
  },
  "geometry": {"coordinates":[-2.468859,52.625038],"type":"Point"}
}
