{
  "type": "Feature",
  "properties": {
    "date:inception_lower":"2011-01-01",
    "date:inception_upper":"2011-01-31",
    "iso:country":"GB",
    "wof:name":"TN15 0AZ",
    "wof:placetype":"postalcode"
},
  "geometry": {"coordinates":[0.221181,51.288936],"type":"Point"}
}