{
  "type": "Feature",
  "properties": {
    "iso:country": "GB",
    "wof:name": "NN6 6DT",
    "wof:placetype": "postalcode"
  },
  "geometry": {"coordinates":[-0.990025,52.394066],"type":"Point"}
}
