{
  "type": "Feature",
  "properties": {
    "iso:country":"GB",
    "wof:name":"NN6 6DT",
    "wof:placetype":"postalcode"
},
  "geometry": {"coordinates":[-0.99002477447437,52.39406578190081],"type":"Point"}
}