{
  "type": "Feature",
  "properties": {
    "date:inception_lower": "2006-07-01",
    "date:inception_upper": "2006-07-01",
    "iso:country": "GB",
    "wof:name": "NN6 6DT",
    "wof:placetype": "postalcode"
  },
  "geometry": {"coordinates":[-0.990025,52.394066],"type":"Point"}
}
