{
  "type": "Feature",
  "properties": {
    "iso:country":"GB",
    "wof:name":"DN6 0BA",
    "wof:placetype":"postalcode"
},
  "geometry": {"coordinates":[-1.16068159821412,53.61109417828598],"type":"Point"}
}