{
  "type": "Feature",
  "properties": {
    "iso:country":"GB",
    "wof:name":"SY2 5YD",
    "wof:placetype":"postalcode"
},
  "geometry": {"coordinates":[-2.71714881353267,52.71356696840151],"type":"Point"}
}