{
  "type": "Feature",
  "properties": {
    "iso:country": "GB",
    "wof:name": "SY2 5YD",
    "wof:placetype": "postalcode"
  },
  "geometry": {"coordinates":[-2.717149,52.713567],"type":"Point"}
}
