{
  "type": "Feature",
  "properties": {
    "date:inception_lower":"1980-01-01",
    "date:inception_upper":"1980-01-31",
    "iso:country":"GB",
    "wof:name":"EH22 4HF",
    "wof:placetype":"postalcode"
},
  "geometry": {"coordinates":[-3.05204,55.879842],"type":"Point"}
}