{
  "type": "Feature",
  "properties": {
    "iso:country": "GB",
    "wof:name": "CH2 2EW",
    "wof:placetype": "postalcode"
  },
  "geometry": {"coordinates":[-2.881377,53.204087],"type":"Point"}
}
