{
  "type": "Feature",
  "properties": {
    "date:inception_lower": "1980-01-01",
    "date:inception_upper": "1980-01-01",
    "iso:country": "GB",
    "wof:name": "CH2 2EW",
    "wof:placetype": "postalcode"
  },
  "geometry": {"coordinates":[-2.881377,53.204087],"type":"Point"}
}
