{
  "type": "Feature",
  "properties": {
    "iso:country": "GB",
    "wof:name": "DN5 8UA",
    "wof:placetype": "postalcode"
  },
  "geometry": {"coordinates":[-1.17465,53.533404],"type":"Point"}
}
