{
  "type": "Feature",
  "properties": {
    "iso:country":"GB",
    "wof:name":"HU18 1EY",
    "wof:placetype":"postalcode"
},
  "geometry": {"coordinates":[-0.17288157332271,53.91729862047617],"type":"Point"}
}