{
  "type": "Feature",
  "properties": {
    "iso:country":"GB",
    "wof:name":"BN15 9FP",
    "wof:placetype":"postalcode"
},
  "geometry": {"coordinates":[-0.31119554116922,50.8314243538691],"type":"Point"}
}