{
  "type": "Feature",
  "properties": {
    "date:inception_lower":"2014-06-01",
    "date:inception_upper":"2014-06-30",
    "iso:country":"GB",
    "wof:name":"BN15 9FP",
    "wof:placetype":"postalcode"
},
  "geometry": {"coordinates":[-0.311196,50.831424],"type":"Point"}
}