{
  "type": "Feature",
  "properties": {
    "iso:country": "GB",
    "wof:name": "BN15 9FP",
    "wof:placetype": "postalcode"
  },
  "geometry": {"coordinates":[-0.311196,50.831424],"type":"Point"}
}
