{
  "type": "Feature",
  "properties": {
    "iso:country": "GB",
    "wof:name": "CM16 6NN",
    "wof:placetype": "postalcode"
  },
  "geometry": {"coordinates":[0.116544,51.724347],"type":"Point"}
}
