{
  "type": "Feature",
  "properties": {
    "iso:country": "GB",
    "wof:name": "AB25 3UJ",
    "wof:placetype": "postalcode"
  },
  "geometry": {"coordinates":[-2.110467,57.154607],"type":"Point"}
}
