{
  "type": "Feature",
  "properties": {
    "date:inception_lower": "1980-01-01",
    "date:inception_upper": "1980-01-01",
    "iso:country": "GB",
    "wof:name": "WA10 6RJ",
    "wof:placetype": "postalcode"
  },
  "geometry": {"coordinates":[-2.754869,53.459225],"type":"Point"}
}
