{
  "type": "Feature",
  "properties": {
    "date:inception_lower":"1980-01-01",
    "date:inception_upper":"1980-01-31",
    "iso:country":"GB",
    "wof:name":"SN4 8QR",
    "wof:placetype":"postalcode"
},
  "geometry": {"coordinates":[-1.863191,51.534737],"type":"Point"}
}