{
  "type": "Feature",
  "properties": {
    "iso:country":"GB",
    "wof:name":"SN4 8QR",
    "wof:placetype":"postalcode"
},
  "geometry": {"coordinates":[-1.86319080889918,51.53473725899467],"type":"Point"}
}