{
  "type": "Feature",
  "properties": {
    "iso:country": "GB",
    "wof:name": "WF9 2RN",
    "wof:placetype": "postalcode"
  },
  "geometry": {"coordinates":[-1.289902,53.594762],"type":"Point"}
}
