{
  "type": "Feature",
  "properties": {
    "iso:country":"GB",
    "wof:name":"WF9 2RN",
    "wof:placetype":"postalcode"
},
  "geometry": {"coordinates":[-1.29006799533364,53.59478137414057],"type":"Point"}
}