{
  "type": "Feature",
  "properties": {
    "iso:country":"GB",
    "wof:name":"OX2 7ST",
    "wof:placetype":"postalcode"
},
  "geometry": {"coordinates":[-1.26287314899971,51.78512493498648],"type":"Point"}
}