{
  "type": "Feature",
  "properties": {
    "iso:country":"GB",
    "wof:name":"SN1 3AD",
    "wof:placetype":"postalcode"
},
  "geometry": {"coordinates":[-1.77081759057983,51.56112703956146],"type":"Point"}
}