{
  "type": "Feature",
  "properties": {
    "iso:country": "GB",
    "wof:name": "SN1 3AD",
    "wof:placetype": "postalcode"
  },
  "geometry": {"coordinates":[-1.77086,51.561199],"type":"Point"}
}
