{
  "type": "Feature",
  "properties": {
    "iso:country":"GB",
    "wof:name":"OL16 2QB",
    "wof:placetype":"postalcode"
},
  "geometry": {"coordinates":[-2.13628523267732,53.63108896809064],"type":"Point"}
}