{
  "type": "Feature",
  "properties": {
    "date:inception_lower":"1993-01-01",
    "date:inception_upper":"1993-01-31",
    "iso:country":"GB",
    "wof:name":"M1 3AB",
    "wof:placetype":"postalcode"
},
  "geometry": {"coordinates":[-2.236943,53.475757],"type":"Point"}
}