{
  "type": "Feature",
  "properties": {
    "iso:country":"GB",
    "wof:name":"ML6 6LU",
    "wof:placetype":"postalcode"
},
  "geometry": {"coordinates":[-3.96982919613801,55.87513345391302],"type":"Point"}
}