{
  "type": "Feature",
  "properties": {
    "date:inception_lower": "2002-06-01",
    "date:inception_upper": "2002-06-01",
    "iso:country": "GB",
    "wof:name": "HP11 1FN",
    "wof:placetype": "postalcode"
  },
  "geometry": {"coordinates":[-0.755165,51.625609],"type":"Point"}
}
