{
  "type": "Feature",
  "properties": {
    "iso:country":"GB",
    "wof:name":"HP11 1FN",
    "wof:placetype":"postalcode"
},
  "geometry": {"coordinates":[-0.75502702605441,51.62555043057257],"type":"Point"}
}