{
  "type": "Feature",
  "properties": {
    "date:inception_lower": "1980-01-01",
    "date:inception_upper": "1980-01-01",
    "iso:country": "GB",
    "wof:name": "LD3 7BY",
    "wof:placetype": "postalcode"
  },
  "geometry": {"coordinates":[-3.382401,51.947184],"type":"Point"}
}
