{
  "type": "Feature",
  "properties": {
    "iso:country":"GB",
    "wof:name":"M24 1JZ",
    "wof:placetype":"postalcode"
},
  "geometry": {"coordinates":[-2.19651580189596,53.54010652305843],"type":"Point"}
}