{
  "type": "Feature",
  "properties": {
    "date:inception_lower": "1980-01-01",
    "date:inception_upper": "1980-01-01",
    "iso:country": "GB",
    "wof:name": "UB1 3DX",
    "wof:placetype": "postalcode"
  },
  "geometry": {"coordinates":[-0.360283,51.509944],"type":"Point"}
}
