{
  "type": "Feature",
  "properties": {
    "iso:country":"GB",
    "wof:name":"UB1 3DX",
    "wof:placetype":"postalcode"
},
  "geometry": {"coordinates":[-0.36028256437428,51.50994447929089],"type":"Point"}
}