{
  "type": "Feature",
  "properties": {
    "date:inception_lower": "2022-02-01",
    "date:inception_upper": "2022-02-01",
    "iso:country": "GB",
    "wof:name": "SG19 2GA",
    "wof:placetype": "postalcode"
  },
  "geometry": {"coordinates":[-0.222139,52.13197],"type":"Point"}
}
