{
  "type": "Feature",
  "properties": {
    "date:inception_lower": "2022-02-01",
    "date:inception_upper": "2022-02-01",
    "iso:country": "GB",
    "wof:name": "SG19 2GA",
    "wof:placetype": "postalcode"
  },
  "geometry": {"coordinates":[-0.223118,52.131976],"type":"Point"}
}
