{
  "type": "Feature",
  "properties": {
    "iso:country":"GB",
    "wof:name":"ME7 4NT",
    "wof:placetype":"postalcode"
},
  "geometry": {"coordinates":[0.55057666763678,51.38644899790565],"type":"Point"}
}