{
  "type": "Feature",
  "properties": {
    "iso:country":"GB",
    "wof:name":"YO8 6QU",
    "wof:placetype":"postalcode"
},
  "geometry": {"coordinates":[-0.9789047921829,53.76637899513181],"type":"Point"}
}