{
  "type": "Feature",
  "properties": {
    "iso:country": "GB",
    "wof:name": "RH12 1NY",
    "wof:placetype": "postalcode"
  },
  "geometry": {"coordinates":[-0.326976,51.062573],"type":"Point"}
}
