{
  "type": "Feature",
  "properties": {
    "iso:country":"GB",
    "wof:name":"TR2 4DL",
    "wof:placetype":"postalcode"
},
  "geometry": {"coordinates":[-4.92787862679856,50.32060795335082],"type":"Point"}
}