{
  "type": "Feature",
  "properties": {
    "iso:country": "GB",
    "wof:name": "DL13 2DA",
    "wof:placetype": "postalcode"
  },
  "geometry": {"coordinates":[-2.099986,54.780984],"type":"Point"}
}
