{
  "type": "Feature",
  "properties": {
    "iso:country": "GB",
    "wof:name": "KY16 8AQ",
    "wof:placetype": "postalcode"
  },
  "geometry": {"coordinates":[-2.798863,56.33557],"type":"Point"}
}
