{
  "type": "Feature",
  "properties": {
    "date:inception_lower": "1980-01-01",
    "date:inception_upper": "1980-01-01",
    "iso:country": "GB",
    "wof:name": "KY16 8AQ",
    "wof:placetype": "postalcode"
  },
  "geometry": {"coordinates":[-2.798863,56.33557],"type":"Point"}
}
