{
  "type": "Feature",
  "properties": {
    "iso:country":"GB",
    "wof:name":"DN14 7EP",
    "wof:placetype":"postalcode"
},
  "geometry": {"coordinates":[-0.87470088597394,53.74115031519832],"type":"Point"}
}