{
  "type": "Feature",
  "properties": {
    "iso:country":"GB",
    "wof:name":"EH8 9QX",
    "wof:placetype":"postalcode"
},
  "geometry": {"coordinates":[-3.17953625355878,55.94201579442614],"type":"Point"}
}