{
  "type": "Feature",
  "properties": {
    "date:inception_lower":"1980-01-01",
    "date:inception_upper":"1980-01-31",
    "iso:country":"GB",
    "wof:name":"EH8 9QX",
    "wof:placetype":"postalcode"
},
  "geometry": {"coordinates":[-3.179536,55.942016],"type":"Point"}
}