{
  "type": "Feature",
  "properties": {
    "date:inception_lower": "1998-06-01",
    "date:inception_upper": "1998-06-01",
    "iso:country": "GB",
    "wof:name": "TR9 6QX",
    "wof:placetype": "postalcode"
  },
  "geometry": {"coordinates":[-4.933532,50.39179],"type":"Point"}
}
