{
  "type": "Feature",
  "properties": {
    "iso:country":"GB",
    "wof:name":"TR9 6QX",
    "wof:placetype":"postalcode"
},
  "geometry": {"coordinates":[-4.93303260807642,50.39192857913896],"type":"Point"}
}