{
  "type": "Feature",
  "properties": {
    "date:inception_lower":"1998-06-01",
    "date:inception_upper":"1998-06-30",
    "iso:country":"GB",
    "wof:name":"TR9 6QX",
    "wof:placetype":"postalcode"
},
  "geometry": {"coordinates":[-4.933076,50.391918],"type":"Point"}
}