{
  "type": "Feature",
  "properties": {
    "iso:country":"GB",
    "wof:name":"PO19 1HR",
    "wof:placetype":"postalcode"
},
  "geometry": {"coordinates":[-0.77729468438213,50.83622280335641],"type":"Point"}
}