{
  "type": "Feature",
  "properties": {
    "iso:country":"GB",
    "wof:name":"ME1 3JG",
    "wof:placetype":"postalcode"
},
  "geometry": {"coordinates":[0.49340275992922,51.37092510812702],"type":"Point"}
}