{
  "type": "Feature",
  "properties": {
    "date:inception_lower": "1980-01-01",
    "date:inception_upper": "1980-01-01",
    "iso:country": "GB",
    "wof:name": "KT24 6AR",
    "wof:placetype": "postalcode"
  },
  "geometry": {"coordinates":[-0.449434,51.261976],"type":"Point"}
}
