{
  "type": "Feature",
  "properties": {
    "date:inception_lower":"1992-01-01",
    "date:inception_upper":"1992-01-31",
    "iso:country":"GB",
    "wof:name":"ML6 6DJ",
    "wof:placetype":"postalcode"
},
  "geometry": {"coordinates":[-3.975255,55.868333],"type":"Point"}
}