{
  "type": "Feature",
  "properties": {
    "iso:country": "GB",
    "wof:name": "WF9 3HS",
    "wof:placetype": "postalcode"
  },
  "geometry": {"coordinates":[-1.331571,53.591065],"type":"Point"}
}
