{
  "type": "Feature",
  "properties": {
    "iso:country": "GB",
    "wof:name": "YO51 9PA",
    "wof:placetype": "postalcode"
  },
  "geometry": {"coordinates":[-1.400747,54.088962],"type":"Point"}
}
