{
  "type": "Feature",
  "properties": {
    "date:inception_lower": "2017-12-01",
    "date:inception_upper": "2017-12-01",
    "iso:country": "GB",
    "wof:name": "YO51 9PA",
    "wof:placetype": "postalcode"
  },
  "geometry": {"coordinates":[-1.400704,54.088782],"type":"Point"}
}
