{
  "type": "Feature",
  "properties": {
    "iso:country":"GB",
    "wof:name":"NG20 9QA",
    "wof:placetype":"postalcode"
},
  "geometry": {"coordinates":[-1.13576487345762,53.21948935235572],"type":"Point"}
}