{
  "type": "Feature",
  "properties": {
    "iso:country":"GB",
    "wof:name":"LS10 3NG",
    "wof:placetype":"postalcode"
},
  "geometry": {"coordinates":[-1.53081516252534,53.75161618567202],"type":"Point"}
}