{
  "type": "Feature",
  "properties": {
    "date:inception_lower": "1980-01-01",
    "date:inception_upper": "1980-01-01",
    "iso:country": "GB",
    "wof:name": "KY10 3RU",
    "wof:placetype": "postalcode"
  },
  "geometry": {"coordinates":[-2.629218,56.259929],"type":"Point"}
}
