{
  "type": "Feature",
  "properties": {
    "iso:country":"GB",
    "wof:name":"TA6 4DS",
    "wof:placetype":"postalcode"
},
  "geometry": {"coordinates":[-2.99686550511288,51.13717871802245],"type":"Point"}
}