{
  "type": "Feature",
  "properties": {
    "date:inception_lower": "1980-01-01",
    "date:inception_upper": "1980-01-01",
    "iso:country": "GB",
    "wof:name": "SG5 3AR",
    "wof:placetype": "postalcode"
  },
  "geometry": {"coordinates":[-0.339343,51.930421],"type":"Point"}
}
