{
  "type": "Feature",
  "properties": {
    "iso:country":"GB",
    "wof:name":"NP19 0BZ",
    "wof:placetype":"postalcode"
},
  "geometry": {"coordinates":[-2.9816832176451,51.58772373622752],"type":"Point"}
}