{
  "type": "Feature",
  "properties": {
    "date:inception_lower": "1990-07-01",
    "date:inception_upper": "1990-07-01",
    "iso:country": "GB",
    "wof:name": "CV6 6NT",
    "wof:placetype": "postalcode"
  },
  "geometry": {"coordinates":[-1.503052,52.442149],"type":"Point"}
}
