{
  "type": "Feature",
  "properties": {
    "iso:country": "GB",
    "wof:name": "CV6 6NT",
    "wof:placetype": "postalcode"
  },
  "geometry": {"coordinates":[-1.503104,52.442133],"type":"Point"}
}
