{
  "type": "Feature",
  "properties": {
    "date:inception_lower":"1990-07-01",
    "date:inception_upper":"1990-07-31",
    "iso:country":"GB",
    "wof:name":"CV6 6NT",
    "wof:placetype":"postalcode"
},
  "geometry": {"coordinates":[-1.503104,52.442133],"type":"Point"}
}