{
  "type": "Feature",
  "properties": {
    "iso:country":"GB",
    "wof:name":"CV6 6NT",
    "wof:placetype":"postalcode"
},
  "geometry": {"coordinates":[-1.50310391033349,52.44213254669199],"type":"Point"}
}