{
  "type": "Feature",
  "properties": {
    "iso:country":"GB",
    "wof:name":"CF40 1RQ",
    "wof:placetype":"postalcode"
},
  "geometry": {"coordinates":[-3.44375880162009,51.60484353189047],"type":"Point"}
}