{
  "type": "Feature",
  "properties": {
    "date:inception_lower": "1980-01-01",
    "date:inception_upper": "1980-01-01",
    "iso:country": "GB",
    "wof:name": "CF40 1RQ",
    "wof:placetype": "postalcode"
  },
  "geometry": {"coordinates":[-3.443759,51.604844],"type":"Point"}
}
