{
  "type": "Feature",
  "properties": {
    "iso:country":"GB",
    "wof:name":"LS13 1RH",
    "wof:placetype":"postalcode"
},
  "geometry": {"coordinates":[-1.65718590455174,53.82063151054354],"type":"Point"}
}