{
  "type": "Feature",
  "properties": {
    "iso:country":"GB",
    "wof:name":"CF39 9DX",
    "wof:placetype":"postalcode"
},
  "geometry": {"coordinates":[-3.4167257211251,51.59878871886666],"type":"Point"}
}