{
  "type": "Feature",
  "properties": {
    "iso:country":"GB",
    "wof:name":"BB3 2HY",
    "wof:placetype":"postalcode"
},
  "geometry": {"coordinates":[-2.4382735648713,53.67965516259394],"type":"Point"}
}