{
  "type": "Feature",
  "properties": {
    "date:inception_lower": "1980-01-01",
    "date:inception_upper": "1980-01-01",
    "iso:country": "GB",
    "wof:name": "BB3 2HY",
    "wof:placetype": "postalcode"
  },
  "geometry": {"coordinates":[-2.438274,53.679655],"type":"Point"}
}
