{
  "type": "Feature",
  "properties": {
    "iso:country":"GB",
    "wof:name":"LN8 6DN",
    "wof:placetype":"postalcode"
},
  "geometry": {"coordinates":[-0.17727800690832,53.42679055498409],"type":"Point"}
}