{
  "type": "Feature",
  "properties": {
    "iso:country":"GB",
    "wof:name":"LL28 5BX",
    "wof:placetype":"postalcode"
},
  "geometry": {"coordinates":[-3.7974896609754,53.2638993581695],"type":"Point"}
}