{
  "type": "Feature",
  "properties": {
    "iso:country":"GB",
    "wof:name":"NE6 4AP",
    "wof:placetype":"postalcode"
},
  "geometry": {"coordinates":[-1.5588732123753,54.98152022933333],"type":"Point"}
}