{
  "type": "Feature",
  "properties": {
    "date:inception_lower": "1980-01-01",
    "date:inception_upper": "1980-01-01",
    "iso:country": "GB",
    "wof:name": "NE6 4AP",
    "wof:placetype": "postalcode"
  },
  "geometry": {"coordinates":[-1.558873,54.98152],"type":"Point"}
}
