{
  "type": "Feature",
  "properties": {
    "date:inception_lower": "1980-01-01",
    "date:inception_upper": "1980-01-01",
    "iso:country": "GB",
    "wof:name": "G83 8PS",
    "wof:placetype": "postalcode"
  },
  "geometry": {"coordinates":[-4.577784,56.001631],"type":"Point"}
}
