{
  "type": "Feature",
  "properties": {
    "iso:country":"GB",
    "wof:name":"G83 8PS",
    "wof:placetype":"postalcode"
},
  "geometry": {"coordinates":[-4.57778440152441,56.00163145778098],"type":"Point"}
}