{
  "type": "Feature",
  "properties": {
    "date:inception_lower":"1997-06-01",
    "date:inception_upper":"1997-06-30",
    "iso:country":"GB",
    "wof:name":"WN6 8AJ",
    "wof:placetype":"postalcode"
},
  "geometry": {"coordinates":[-2.684134,53.571954],"type":"Point"}
}