{
  "type": "Feature",
  "properties": {
    "date:inception_lower": "1980-01-01",
    "date:inception_upper": "1980-01-01",
    "iso:country": "GB",
    "wof:name": "LD3 0LY",
    "wof:placetype": "postalcode"
  },
  "geometry": {"coordinates":[-3.259069,52.007182],"type":"Point"}
}
