{
  "type": "Feature",
  "properties": {
    "iso:country": "GB",
    "wof:name": "LD3 0LY",
    "wof:placetype": "postalcode"
  },
  "geometry": {"coordinates":[-3.259069,52.007182],"type":"Point"}
}
