{
  "type": "Feature",
  "properties": {
    "iso:country":"GB",
    "wof:name":"PO16 9DW",
    "wof:placetype":"postalcode"
},
  "geometry": {"coordinates":[-1.14388962495814,50.843857918895],"type":"Point"}
}