{
  "type": "Feature",
  "properties": {
    "iso:country":"GB",
    "wof:name":"CV36 4AW",
    "wof:placetype":"postalcode"
},
  "geometry": {"coordinates":[-1.6229597644175,52.06168071261355],"type":"Point"}
}