{
  "type": "Feature",
  "properties": {
    "date:inception_lower": "2004-10-01",
    "date:inception_upper": "2004-10-01",
    "iso:country": "GB",
    "wof:name": "HU12 9GE",
    "wof:placetype": "postalcode"
  },
  "geometry": {"coordinates":[-0.180226,53.72085],"type":"Point"}
}
