{
  "type": "Feature",
  "properties": {
    "iso:country":"GB",
    "wof:name":"HU12 9GE",
    "wof:placetype":"postalcode"
},
  "geometry": {"coordinates":[-0.18022646143365,53.72085026534441],"type":"Point"}
}