{
  "type": "Feature",
  "properties": {
    "iso:country":"GB",
    "wof:name":"WR2 4LH",
    "wof:placetype":"postalcode"
},
  "geometry": {"coordinates":[-2.23667847207375,52.18390233034849],"type":"Point"}
}