{
  "type": "Feature",
  "properties": {
    "date:inception_lower": "2011-05-01",
    "date:inception_upper": "2011-05-01",
    "iso:country": "GB",
    "wof:name": "SG5 4HG",
    "wof:placetype": "postalcode"
  },
  "geometry": {"coordinates":[-0.231148,52.010859],"type":"Point"}
}
