{
  "type": "Feature",
  "properties": {
    "iso:country": "GB",
    "wof:name": "HU9 4TR",
    "wof:placetype": "postalcode"
  },
  "geometry": {"coordinates":[-0.274701,53.768066],"type":"Point"}
}
