{
  "type": "Feature",
  "properties": {
    "date:inception_lower": "1998-06-01",
    "date:inception_upper": "1998-06-01",
    "iso:country": "GB",
    "wof:name": "YO24 2HX",
    "wof:placetype": "postalcode"
  },
  "geometry": {"coordinates":[-1.115468,53.940487],"type":"Point"}
}
