{
  "type": "Feature",
  "properties": {
    "iso:country":"GB",
    "wof:name":"YO24 2HX",
    "wof:placetype":"postalcode"
},
  "geometry": {"coordinates":[-1.11546765021883,53.94048684654567],"type":"Point"}
}