{
  "type": "Feature",
  "properties": {
    "iso:country":"GB",
    "wof:name":"SE7 7LH",
    "wof:placetype":"postalcode"
},
  "geometry": {"coordinates":[0.02350250498231,51.48310578036771],"type":"Point"}
}