{
  "type": "Feature",
  "properties": {
    "iso:country":"GB",
    "wof:name":"TA18 7TH",
    "wof:placetype":"postalcode"
},
  "geometry": {"coordinates":[-2.76266031719716,50.88901576976283],"type":"Point"}
}