{
  "type": "Feature",
  "properties": {
    "date:inception_lower": "2002-06-01",
    "date:inception_upper": "2002-06-01",
    "iso:country": "GB",
    "wof:name": "TA18 7TH",
    "wof:placetype": "postalcode"
  },
  "geometry": {"coordinates":[-2.762647,50.888972],"type":"Point"}
}
