{
  "type": "Feature",
  "properties": {
    "date:inception_lower": "1980-01-01",
    "date:inception_upper": "1980-01-01",
    "iso:country": "GB",
    "wof:name": "BB3 2LB",
    "wof:placetype": "postalcode"
  },
  "geometry": {"coordinates":[-2.461302,53.681195],"type":"Point"}
}
