{
  "type": "Feature",
  "properties": {
    "iso:country":"GB",
    "wof:name":"BB3 2LB",
    "wof:placetype":"postalcode"
},
  "geometry": {"coordinates":[-2.46130218837337,53.68119550080628],"type":"Point"}
}