{
  "type": "Feature",
  "properties": {
    "date:inception_lower":"1998-06-01",
    "date:inception_upper":"1998-06-30",
    "iso:country":"GB",
    "wof:name":"WS13 8SG",
    "wof:placetype":"postalcode"
},
  "geometry": {"coordinates":[-1.766706,52.711975],"type":"Point"}
}