{
  "type": "Feature",
  "properties": {
    "iso:country": "GB",
    "wof:name": "SN9 6EH",
    "wof:placetype": "postalcode"
  },
  "geometry": {"coordinates":[-1.821736,51.300537],"type":"Point"}
}
