{
  "type": "Feature",
  "properties": {
    "date:inception_lower": "1980-01-01",
    "date:inception_upper": "1980-01-01",
    "iso:country": "GB",
    "wof:name": "SN9 6EH",
    "wof:placetype": "postalcode"
  },
  "geometry": {"coordinates":[-1.819181,51.300901],"type":"Point"}
}
