{
  "type": "Feature",
  "properties": {
    "iso:country": "GB",
    "wof:name": "HP20 1DP",
    "wof:placetype": "postalcode"
  },
  "geometry": {"coordinates":[-0.80383,51.8197],"type":"Point"}
}
