{
  "type": "Feature",
  "properties": {
    "iso:country":"GB",
    "wof:name":"SR5 1EB",
    "wof:placetype":"postalcode"
},
  "geometry": {"coordinates":[-1.39153398226096,54.92002362795274],"type":"Point"}
}