{
  "type": "Feature",
  "properties": {
    "date:inception_lower": "2020-05-01",
    "date:inception_upper": "2020-05-01",
    "iso:country": "GB",
    "wof:name": "SR5 1EB",
    "wof:placetype": "postalcode"
  },
  "geometry": {"coordinates":[-1.391302,54.919788],"type":"Point"}
}
