{
  "type": "Feature",
  "properties": {
    "iso:country": "GB",
    "wof:name": "PE19 7BE",
    "wof:placetype": "postalcode"
  },
  "geometry": {"coordinates":[-0.284832,52.223484],"type":"Point"}
}
