{
  "type": "Feature",
  "properties": {
    "iso:country":"GB",
    "wof:name":"PE19 7BE",
    "wof:placetype":"postalcode"
},
  "geometry": {"coordinates":[-0.28483187321382,52.22348393605103],"type":"Point"}
}