{
  "type": "Feature",
  "properties": {
    "iso:country":"GB",
    "wof:name":"SP10 3DA",
    "wof:placetype":"postalcode"
},
  "geometry": {"coordinates":[-1.50610979114298,51.20977915958565],"type":"Point"}
}