{
  "type": "Feature",
  "properties": {
    "iso:country":"GB",
    "wof:name":"IV36 2SN",
    "wof:placetype":"postalcode"
},
  "geometry": {"coordinates":[-3.63349834052154,57.61127833435425],"type":"Point"}
}