{
  "type": "Feature",
  "properties": {
    "iso:country":"GB",
    "wof:name":"HX2 6XF",
    "wof:placetype":"postalcode"
},
  "geometry": {"coordinates":[-1.9493843604688,53.72874042766706],"type":"Point"}
}