{
  "type": "Feature",
  "properties": {
    "date:inception_lower": "1980-01-01",
    "date:inception_upper": "1980-01-01",
    "iso:country": "GB",
    "wof:name": "HX2 6XF",
    "wof:placetype": "postalcode"
  },
  "geometry": {"coordinates":[-1.94931,53.728692],"type":"Point"}
}
