{
  "type": "Feature",
  "properties": {
    "iso:country":"GB",
    "wof:name":"CO2 8PY",
    "wof:placetype":"postalcode"
},
  "geometry": {"coordinates":[0.90687546364408,51.87145457118417],"type":"Point"}
}