{
  "type": "Feature",
  "properties": {
    "iso:country": "GB",
    "wof:name": "CO2 8PY",
    "wof:placetype": "postalcode"
  },
  "geometry": {"coordinates":[0.906876,51.871455],"type":"Point"}
}
