{
  "type": "Feature",
  "properties": {
    "iso:country": "GB",
    "wof:name": "EX22 6LG",
    "wof:placetype": "postalcode"
  },
  "geometry": {"coordinates":[-4.414922,50.782692],"type":"Point"}
}
