{
  "type": "Feature",
  "properties": {
    "date:inception_lower": "1994-05-01",
    "date:inception_upper": "1994-05-01",
    "iso:country": "GB",
    "wof:name": "OL16 2QH",
    "wof:placetype": "postalcode"
  },
  "geometry": {"coordinates":[-2.130413,53.634232],"type":"Point"}
}
