{
  "type": "Feature",
  "properties": {
    "iso:country":"GB",
    "wof:name":"TD7 4JW",
    "wof:placetype":"postalcode"
},
  "geometry": {"coordinates":[-2.83138822377731,55.5570120391261],"type":"Point"}
}