{
  "type": "Feature",
  "properties": {
    "iso:country": "GB",
    "wof:name": "ST6 4JZ",
    "wof:placetype": "postalcode"
  },
  "geometry": {"coordinates":[-2.212133,53.053078],"type":"Point"}
}
