{
  "type": "Feature",
  "properties": {
    "iso:country": "GB",
    "wof:name": "OL8 1QN",
    "wof:placetype": "postalcode"
  },
  "geometry": {"coordinates":[-2.112559,53.529133],"type":"Point"}
}
