{
  "type": "Feature",
  "properties": {
    "iso:country":"GB",
    "wof:name":"CO2 8LX",
    "wof:placetype":"postalcode"
},
  "geometry": {"coordinates":[0.90701839369583,51.86353663322967],"type":"Point"}
}