{
  "type": "Feature",
  "properties": {
    "iso:country":"GB",
    "wof:name":"CR2 0RX",
    "wof:placetype":"postalcode"
},
  "geometry": {"coordinates":[-0.0996237038543,51.34098613279223],"type":"Point"}
}