{
  "type": "Feature",
  "properties": {
    "date:inception_lower": "1992-01-01",
    "date:inception_upper": "1992-01-01",
    "iso:country": "GB",
    "wof:name": "BA12 9BX",
    "wof:placetype": "postalcode"
  },
  "geometry": {"coordinates":[-2.179046,51.205099],"type":"Point"}
}
