{
  "type": "Feature",
  "properties": {
    "date:inception_lower": "1990-02-01",
    "date:inception_upper": "1990-02-01",
    "iso:country": "GB",
    "wof:name": "DH1 3QY",
    "wof:placetype": "postalcode"
  },
  "geometry": {"coordinates":[-1.588259,54.764754],"type":"Point"}
}
