{
  "type": "Feature",
  "properties": {
    "date:inception_lower": "1995-01-01",
    "date:inception_upper": "1995-01-01",
    "iso:country": "GB",
    "wof:name": "YO11 3NU",
    "wof:placetype": "postalcode"
  },
  "geometry": {"coordinates":[-0.339099,54.234417],"type":"Point"}
}
