{
  "type": "Feature",
  "properties": {
    "iso:country": "GB",
    "wof:name": "YO11 3NU",
    "wof:placetype": "postalcode"
  },
  "geometry": {"coordinates":[-0.337052,54.233759],"type":"Point"}
}
