{
  "type": "Feature",
  "properties": {
    "iso:country": "GB",
    "wof:name": "YO11 3NU",
    "wof:placetype": "postalcode"
  },
  "geometry": {"coordinates":[-0.339099,54.234417],"type":"Point"}
}
