{
  "type": "Feature",
  "properties": {
    "date:inception_lower":"1995-01-01",
    "date:inception_upper":"1995-01-31",
    "iso:country":"GB",
    "wof:name":"YO11 3NU",
    "wof:placetype":"postalcode"
},
  "geometry": {"coordinates":[-0.337052,54.233759],"type":"Point"}
}