{
  "type": "Feature",
  "properties": {
    "iso:country":"GB",
    "wof:name":"YO11 3NU",
    "wof:placetype":"postalcode"
},
  "geometry": {"coordinates":[-0.33705243809071,54.23375900758317],"type":"Point"}
}