{
  "type": "Feature",
  "properties": {
    "date:inception_lower":"1980-01-01",
    "date:inception_upper":"1980-01-31",
    "iso:country":"GB",
    "wof:name":"TQ2 5TN",
    "wof:placetype":"postalcode"
},
  "geometry": {"coordinates":[-3.531158,50.462857],"type":"Point"}
}