{
  "type": "Feature",
  "properties": {
    "iso:country":"GB",
    "wof:name":"PR9 9EG",
    "wof:placetype":"postalcode"
},
  "geometry": {"coordinates":[-2.98298419561588,53.65319558307648],"type":"Point"}
}