{
  "type": "Feature",
  "properties": {
    "iso:country":"GB",
    "wof:name":"CA22 2EU",
    "wof:placetype":"postalcode"
},
  "geometry": {"coordinates":[-3.53771572345015,54.48315546699987],"type":"Point"}
}