{
  "type": "Feature",
  "properties": {
    "date:inception_lower":"1980-01-01",
    "date:inception_upper":"1980-01-31",
    "iso:country":"GB",
    "wof:name":"CA22 2EU",
    "wof:placetype":"postalcode"
},
  "geometry": {"coordinates":[-3.537716,54.483155],"type":"Point"}
}