{
  "type": "Feature",
  "properties": {
    "iso:country": "GB",
    "wof:name": "CA22 2EU",
    "wof:placetype": "postalcode"
  },
  "geometry": {"coordinates":[-3.537716,54.483155],"type":"Point"}
}
