{
  "type": "Feature",
  "properties": {
    "iso:country":"GB",
    "wof:name":"AL1 4QW",
    "wof:placetype":"postalcode"
},
  "geometry": {"coordinates":[-0.31347341884966,51.75352558556419],"type":"Point"}
}