{
  "type": "Feature",
  "properties": {
    "date:inception_lower":"1980-01-01",
    "date:inception_upper":"1980-01-31",
    "iso:country":"GB",
    "wof:name":"CM0 7LG",
    "wof:placetype":"postalcode"
},
  "geometry": {"coordinates":[0.801233,51.692871],"type":"Point"}
}