{
  "type": "Feature",
  "properties": {
    "iso:country":"GB",
    "wof:name":"CM0 7LG",
    "wof:placetype":"postalcode"
},
  "geometry": {"coordinates":[0.80123260328508,51.69287088397353],"type":"Point"}
}