{
  "type": "Feature",
  "properties": {
    "iso:country":"GB",
    "wof:name":"PE14 0RS",
    "wof:placetype":"postalcode"
},
  "geometry": {"coordinates":[0.1293342162003,52.64024276021696],"type":"Point"}
}