{
  "type": "Feature",
  "properties": {
    "iso:country":"GB",
    "wof:name":"CH8 9RD",
    "wof:placetype":"postalcode"
},
  "geometry": {"coordinates":[-3.3219041327301,53.34921994152898],"type":"Point"}
}