{
  "type": "Feature",
  "properties": {
    "date:inception_lower": "1980-01-01",
    "date:inception_upper": "1980-01-01",
    "iso:country": "GB",
    "wof:name": "NE33 4HN",
    "wof:placetype": "postalcode"
  },
  "geometry": {"coordinates":[-1.429486,54.98996],"type":"Point"}
}
