{
  "type": "Feature",
  "properties": {
    "iso:country":"GB",
    "wof:name":"SN1 4GP",
    "wof:placetype":"postalcode"
},
  "geometry": {"coordinates":[-1.7955673990691,51.54920516418029],"type":"Point"}
}