{
  "type": "Feature",
  "properties": {
    "iso:country":"GB",
    "wof:name":"S66 1XA",
    "wof:placetype":"postalcode"
},
  "geometry": {"coordinates":[-1.25992144431913,53.42095677428598],"type":"Point"}
}