{
  "type": "Feature",
  "properties": {
    "date:inception_lower": "2008-07-01",
    "date:inception_upper": "2008-07-01",
    "iso:country": "GB",
    "wof:name": "S66 1XA",
    "wof:placetype": "postalcode"
  },
  "geometry": {"coordinates":[-1.259921,53.420957],"type":"Point"}
}
