{
  "type": "Feature",
  "properties": {
    "iso:country": "GB",
    "wof:name": "CO12 4HR",
    "wof:placetype": "postalcode"
  },
  "geometry": {"coordinates":[1.253938,51.931113],"type":"Point"}
}
