{
  "type": "Feature",
  "properties": {
    "iso:country":"GB",
    "wof:name":"CO12 4HR",
    "wof:placetype":"postalcode"
},
  "geometry": {"coordinates":[1.2539382376588,51.93111292642371],"type":"Point"}
}