{
  "type": "Feature",
  "properties": {
    "iso:country":"GB",
    "wof:name":"PL6 8RP",
    "wof:placetype":"postalcode"
},
  "geometry": {"coordinates":[-4.09131064740962,50.41275326416345],"type":"Point"}
}