{
  "type": "Feature",
  "properties": {
    "iso:country":"GB",
    "wof:name":"SN13 9RX",
    "wof:placetype":"postalcode"
},
  "geometry": {"coordinates":[-2.19595020296714,51.42348164128728],"type":"Point"}
}