{
  "type": "Feature",
  "properties": {
    "iso:country":"GB",
    "wof:name":"SN16 0JW",
    "wof:placetype":"postalcode"
},
  "geometry": {"coordinates":[-2.14838073563903,51.56278469664735],"type":"Point"}
}