{
  "type": "Feature",
  "properties": {
    "iso:country": "GB",
    "wof:name": "SN16 0JW",
    "wof:placetype": "postalcode"
  },
  "geometry": {"coordinates":[-2.148376,51.562785],"type":"Point"}
}
