{
  "type": "Feature",
  "properties": {
    "date:inception_lower": "1980-01-01",
    "date:inception_upper": "1980-01-01",
    "iso:country": "GB",
    "wof:name": "SN16 0JW",
    "wof:placetype": "postalcode"
  },
  "geometry": {"coordinates":[-2.148376,51.562785],"type":"Point"}
}
