{
  "type": "Feature",
  "properties": {
    "iso:country": "GB",
    "wof:name": "MK4 4ER",
    "wof:placetype": "postalcode"
  },
  "geometry": {"coordinates":[-0.807165,52.00526],"type":"Point"}
}
