{
  "type": "Feature",
  "properties": {
    "iso:country":"GB",
    "wof:name":"OX3 8RQ",
    "wof:placetype":"postalcode"
},
  "geometry": {"coordinates":[-1.19873197324848,51.75025994586649],"type":"Point"}
}