{
  "type": "Feature",
  "properties": {
    "iso:country": "GB",
    "wof:name": "ST15 0GH",
    "wof:placetype": "postalcode"
  },
  "geometry": {"coordinates":[-2.204719,52.88956],"type":"Point"}
}
