{
  "type": "Feature",
  "properties": {
    "iso:country":"GB",
    "wof:name":"ST15 0GH",
    "wof:placetype":"postalcode"
},
  "geometry": {"coordinates":[-2.20471891906101,52.88956037117899],"type":"Point"}
}