{
  "type": "Feature",
  "properties": {
    "date:inception_lower":"2009-06-01",
    "date:inception_upper":"2009-06-30",
    "iso:country":"GB",
    "wof:name":"ST15 0GH",
    "wof:placetype":"postalcode"
},
  "geometry": {"coordinates":[-2.204719,52.88956],"type":"Point"}
}