{
  "type": "Feature",
  "properties": {
    "iso:country":"GB",
    "wof:name":"WN5 9UW",
    "wof:placetype":"postalcode"
},
  "geometry": {"coordinates":[-2.67938458373047,53.54133932595101],"type":"Point"}
}