{
  "type": "Feature",
  "properties": {
    "iso:country": "GB",
    "wof:name": "TS10 5EU",
    "wof:placetype": "postalcode"
  },
  "geometry": {"coordinates":[-1.092447,54.608196],"type":"Point"}
}
