{
  "type": "Feature",
  "properties": {
    "iso:country":"GB",
    "wof:name":"TS10 5EU",
    "wof:placetype":"postalcode"
},
  "geometry": {"coordinates":[-1.09238664500942,54.60812906997027],"type":"Point"}
}