{
  "type": "Feature",
  "properties": {
    "date:inception_lower": "1995-01-01",
    "date:inception_upper": "1995-01-01",
    "iso:country": "GB",
    "wof:name": "TS10 5EU",
    "wof:placetype": "postalcode"
  },
  "geometry": {"coordinates":[-1.092447,54.608196],"type":"Point"}
}
