{
  "type": "Feature",
  "properties": {
    "date:inception_lower":"2006-02-01",
    "date:inception_upper":"2006-02-28",
    "iso:country":"GB",
    "wof:name":"NN6 9GZ",
    "wof:placetype":"postalcode"
},
  "geometry": {"coordinates":[-0.895702,52.335287],"type":"Point"}
}