{
  "type": "Feature",
  "properties": {
    "iso:country":"GB",
    "wof:name":"NN6 9GZ",
    "wof:placetype":"postalcode"
},
  "geometry": {"coordinates":[-0.89570176627289,52.33528730142342],"type":"Point"}
}