{
  "type": "Feature",
  "properties": {
    "iso:country": "GB",
    "wof:name": "WN2 5JW",
    "wof:placetype": "postalcode"
  },
  "geometry": {"coordinates":[-2.605817,53.509403],"type":"Point"}
}
