{
  "type": "Feature",
  "properties": {
    "iso:country":"GB",
    "wof:name":"FK4 1QX",
    "wof:placetype":"postalcode"
},
  "geometry": {"coordinates":[-3.91874017148045,55.99590344623986],"type":"Point"}
}