{
  "type": "Feature",
  "properties": {
    "iso:country":"GB",
    "wof:name":"MK19 7HG",
    "wof:placetype":"postalcode"
},
  "geometry": {"coordinates":[-0.83958635505668,52.09059473676186],"type":"Point"}
}