{
  "type": "Feature",
  "properties": {
    "iso:country": "GB",
    "wof:name": "RG10 9BG",
    "wof:placetype": "postalcode"
  },
  "geometry": {"coordinates":[-0.860134,51.48497],"type":"Point"}
}
