{
  "type": "Feature",
  "properties": {
    "iso:country": "GB",
    "wof:name": "OL10 1JG",
    "wof:placetype": "postalcode"
  },
  "geometry": {"coordinates":[-2.228673,53.593548],"type":"Point"}
}
