{
  "type": "Feature",
  "properties": {
    "iso:country":"GB",
    "wof:name":"OL10 1JG",
    "wof:placetype":"postalcode"
},
  "geometry": {"coordinates":[-2.22867301105069,53.59354780144187],"type":"Point"}
}