{
  "type": "Feature",
  "properties": {
    "iso:country": "GB",
    "wof:name": "RG20 6AA",
    "wof:placetype": "postalcode"
  },
  "geometry": {"coordinates":[-1.253315,51.516744],"type":"Point"}
}
