{
  "type": "Feature",
  "properties": {
    "date:inception_lower": "2021-04-01",
    "date:inception_upper": "2021-04-01",
    "iso:country": "GB",
    "wof:name": "BN41 2AN",
    "wof:placetype": "postalcode"
  },
  "geometry": {"coordinates":[-0.230049,50.856332],"type":"Point"}
}
