{
  "type": "Feature",
  "properties": {
    "iso:country":"GB",
    "wof:name":"GU4 8JX",
    "wof:placetype":"postalcode"
},
  "geometry": {"coordinates":[-0.56303389882414,51.2130790377941],"type":"Point"}
}