{
  "type": "Feature",
  "properties": {
    "iso:country":"GB",
    "wof:name":"W1D 4SN",
    "wof:placetype":"postalcode"
},
  "geometry": {"coordinates":[-0.1320196160815,51.51371623795171],"type":"Point"}
}