{
  "type": "Feature",
  "properties": {
    "date:inception_lower": "2018-01-01",
    "date:inception_upper": "2018-01-01",
    "iso:country": "GB",
    "wof:name": "WA3 6BJ",
    "wof:placetype": "postalcode"
  },
  "geometry": {"coordinates":[-2.521952,53.418797],"type":"Point"}
}
