{
  "type": "Feature",
  "properties": {
    "iso:country":"GB",
    "wof:name":"S2 5FF",
    "wof:placetype":"postalcode"
},
  "geometry": {"coordinates":[-1.44210128387941,53.37604109585589],"type":"Point"}
}