{
  "type": "Feature",
  "properties": {
    "iso:country":"GB",
    "wof:name":"CH48 9XZ",
    "wof:placetype":"postalcode"
},
  "geometry": {"coordinates":[-3.15962401060295,53.37179837990222],"type":"Point"}
}