{
  "type": "Feature",
  "properties": {
    "iso:country": "GB",
    "wof:name": "NN4 6HL",
    "wof:placetype": "postalcode"
  },
  "geometry": {"coordinates":[-0.883375,52.202801],"type":"Point"}
}
