{
  "type": "Feature",
  "properties": {
    "date:inception_lower": "1985-04-01",
    "date:inception_upper": "1985-04-01",
    "iso:country": "GB",
    "wof:name": "CT20 3TA",
    "wof:placetype": "postalcode"
  },
  "geometry": {"coordinates":[1.132383,51.074046],"type":"Point"}
}
