{
  "type": "Feature",
  "properties": {
    "iso:country":"GB",
    "wof:name":"CT20 3TA",
    "wof:placetype":"postalcode"
},
  "geometry": {"coordinates":[1.13238324267048,51.07404613424888],"type":"Point"}
}