{
  "type": "Feature",
  "properties": {
    "iso:country": "GB",
    "wof:name": "AB42 4TQ",
    "wof:placetype": "postalcode"
  },
  "geometry": {"coordinates":[-1.940877,57.515847],"type":"Point"}
}
