{
  "type": "Feature",
  "properties": {
    "iso:country":"GB",
    "wof:name":"IP1 2LS",
    "wof:placetype":"postalcode"
},
  "geometry": {"coordinates":[1.13964733220661,52.06066538801668],"type":"Point"}
}