{
  "type": "Feature",
  "properties": {
    "date:inception_lower": "1980-01-01",
    "date:inception_upper": "1980-01-01",
    "iso:country": "GB",
    "wof:name": "WS9 8JS",
    "wof:placetype": "postalcode"
  },
  "geometry": {"coordinates":[-1.920333,52.616509],"type":"Point"}
}
