{
  "type": "Feature",
  "properties": {
    "iso:country":"GB",
    "wof:name":"G61 3SL",
    "wof:placetype":"postalcode"
},
  "geometry": {"coordinates":[-4.33329249783383,55.91992584560633],"type":"Point"}
}