{
  "type": "Feature",
  "properties": {
    "iso:country": "GB",
    "wof:name": "G61 3SL",
    "wof:placetype": "postalcode"
  },
  "geometry": {"coordinates":[-4.333292,55.919926],"type":"Point"}
}
