{
  "type": "Feature",
  "properties": {
    "iso:country":"GB",
    "wof:name":"LS26 0LE",
    "wof:placetype":"postalcode"
},
  "geometry": {"coordinates":[-1.47440891684699,53.74972843888838],"type":"Point"}
}