{
  "type": "Feature",
  "properties": {
    "iso:country":"GB",
    "wof:name":"NR17 1JS",
    "wof:placetype":"postalcode"
},
  "geometry": {"coordinates":[0.94735374066622,52.55053142241736],"type":"Point"}
}