{
  "type": "Feature",
  "properties": {
    "date:inception_lower": "1980-01-01",
    "date:inception_upper": "1980-01-01",
    "iso:country": "GB",
    "wof:name": "NR17 1JS",
    "wof:placetype": "postalcode"
  },
  "geometry": {"coordinates":[0.947354,52.550531],"type":"Point"}
}
