{
  "type": "Feature",
  "properties": {
    "iso:country": "GB",
    "wof:name": "NR17 1JS",
    "wof:placetype": "postalcode"
  },
  "geometry": {"coordinates":[0.947354,52.550531],"type":"Point"}
}
