{
  "type": "Feature",
  "properties": {
    "iso:country":"GB",
    "wof:name":"PO18 9DN",
    "wof:placetype":"postalcode"
},
  "geometry": {"coordinates":[-0.87179227991951,50.87916197744276],"type":"Point"}
}