{
  "type": "Feature",
  "properties": {
    "iso:country": "GB",
    "wof:name": "PO18 9DN",
    "wof:placetype": "postalcode"
  },
  "geometry": {"coordinates":[-0.870127,50.877491],"type":"Point"}
}
