{
  "type": "Feature",
  "properties": {
    "date:inception_lower":"1980-01-01",
    "date:inception_upper":"1980-01-31",
    "iso:country":"GB",
    "wof:name":"PO18 9DN",
    "wof:placetype":"postalcode"
},
  "geometry": {"coordinates":[-0.870127,50.877491],"type":"Point"}
}