{
  "type": "Feature",
  "properties": {
    "iso:country":"GB",
    "wof:name":"NG8 5LG",
    "wof:placetype":"postalcode"
},
  "geometry": {"coordinates":[-1.19598176693581,52.97938507462828],"type":"Point"}
}