{
  "type": "Feature",
  "properties": {
    "iso:country": "GB",
    "wof:name": "CV10 8LJ",
    "wof:placetype": "postalcode"
  },
  "geometry": {"coordinates":[-1.508157,52.522039],"type":"Point"}
}
