{
  "type": "Feature",
  "properties": {
    "date:inception_lower":"1980-01-01",
    "date:inception_upper":"1980-01-31",
    "iso:country":"GB",
    "wof:name":"CV10 8LJ",
    "wof:placetype":"postalcode"
},
  "geometry": {"coordinates":[-1.508157,52.522039],"type":"Point"}
}