{
  "type": "Feature",
  "properties": {
    "date:inception_lower": "1980-01-01",
    "date:inception_upper": "1980-01-01",
    "iso:country": "GB",
    "wof:name": "ST6 6JG",
    "wof:placetype": "postalcode"
  },
  "geometry": {"coordinates":[-2.2026,53.072234],"type":"Point"}
}
