{
  "type": "Feature",
  "properties": {
    "iso:country":"GB",
    "wof:name":"HU8 9PR",
    "wof:placetype":"postalcode"
},
  "geometry": {"coordinates":[-0.2686736621374,53.77517067416537],"type":"Point"}
}