{
  "type": "Feature",
  "properties": {
    "date:inception_lower":"1980-01-01",
    "date:inception_upper":"1980-01-31",
    "iso:country":"GB",
    "wof:name":"ME17 4LW",
    "wof:placetype":"postalcode"
},
  "geometry": {"coordinates":[0.527452,51.232466],"type":"Point"}
}