{
  "type": "Feature",
  "properties": {
    "date:inception_lower": "2006-10-01",
    "date:inception_upper": "2006-10-01",
    "iso:country": "GB",
    "wof:name": "SO16 3UH",
    "wof:placetype": "postalcode"
  },
  "geometry": {"coordinates":[-1.401059,50.943425],"type":"Point"}
}
