{
  "type": "Feature",
  "properties": {
    "date:inception_lower": "1980-01-01",
    "date:inception_upper": "1980-01-01",
    "iso:country": "GB",
    "wof:name": "GU12 6LT",
    "wof:placetype": "postalcode"
  },
  "geometry": {"coordinates":[-0.72778,51.2442],"type":"Point"}
}
