{
  "type": "Feature",
  "properties": {
    "iso:country":"GB",
    "wof:name":"GU12 6LT",
    "wof:placetype":"postalcode"
},
  "geometry": {"coordinates":[-0.72759804306607,51.24472161975766],"type":"Point"}
}