{
  "type": "Feature",
  "properties": {
    "iso:country":"GB",
    "wof:name":"SO32 1FP",
    "wof:placetype":"postalcode"
},
  "geometry": {"coordinates":[-1.23005372417183,50.96079468258505],"type":"Point"}
}