{
  "type": "Feature",
  "properties": {
    "date:inception_lower": "1980-01-01",
    "date:inception_upper": "1980-01-01",
    "iso:country": "GB",
    "wof:name": "PL14 4HZ",
    "wof:placetype": "postalcode"
  },
  "geometry": {"coordinates":[-4.470722,50.452782],"type":"Point"}
}
