{
  "type": "Feature",
  "properties": {
    "iso:country":"GB",
    "wof:name":"PL14 4HZ",
    "wof:placetype":"postalcode"
},
  "geometry": {"coordinates":[-4.47075730715602,50.4527922282572],"type":"Point"}
}