{
  "type": "Feature",
  "properties": {
    "iso:country":"GB",
    "wof:name":"KT20 7HP",
    "wof:placetype":"postalcode"
},
  "geometry": {"coordinates":[-0.22876121440736,51.25705789585366],"type":"Point"}
}