{
  "type": "Feature",
  "properties": {
    "iso:country":"GB",
    "wof:name":"GL53 9AL",
    "wof:placetype":"postalcode"
},
  "geometry": {"coordinates":[-2.07285599197125,51.87400305412347],"type":"Point"}
}