{
  "type": "Feature",
  "properties": {
    "iso:country":"GB",
    "wof:name":"TR11 2BB",
    "wof:placetype":"postalcode"
},
  "geometry": {"coordinates":[-5.07844207227892,50.15679737242902],"type":"Point"}
}