{
  "type": "Feature",
  "properties": {
    "iso:country": "GB",
    "wof:name": "CH43 9TG",
    "wof:placetype": "postalcode"
  },
  "geometry": {"coordinates":[-3.060681,53.384665],"type":"Point"}
}
