{
  "type": "Feature",
  "properties": {
    "iso:country":"GB",
    "wof:name":"BR1 5PP",
    "wof:placetype":"postalcode"
},
  "geometry": {"coordinates":[0.00303900411774,51.42694667063041],"type":"Point"}
}