{
  "type": "Feature",
  "properties": {
    "date:inception_lower":"1980-01-01",
    "date:inception_upper":"1980-01-31",
    "iso:country":"GB",
    "wof:name":"BR1 5PP",
    "wof:placetype":"postalcode"
},
  "geometry": {"coordinates":[0.003039,51.426947],"type":"Point"}
}