{
  "type": "Feature",
  "properties": {
    "iso:country": "GB",
    "wof:name": "CH41 8HN",
    "wof:placetype": "postalcode"
  },
  "geometry": {"coordinates":[-3.049696,53.400772],"type":"Point"}
}
