{
  "type": "Feature",
  "properties": {
    "iso:country":"GB",
    "wof:name":"CH41 8HN",
    "wof:placetype":"postalcode"
},
  "geometry": {"coordinates":[-3.04956915186051,53.40049423113641],"type":"Point"}
}