{
  "type": "Feature",
  "properties": {
    "iso:country":"GB",
    "wof:name":"AL5 1JD",
    "wof:placetype":"postalcode"
},
  "geometry": {"coordinates":[-0.32131142632552,51.81094336611734],"type":"Point"}
}