{
  "type": "Feature",
  "properties": {
    "date:inception_lower":"2006-09-01",
    "date:inception_upper":"2006-09-30",
    "iso:country":"GB",
    "wof:name":"CB23 5FW",
    "wof:placetype":"postalcode"
},
  "geometry": {"coordinates":[-0.084101,52.217456],"type":"Point"}
}