{
  "type": "Feature",
  "properties": {
    "date:inception_lower": "2023-11-01",
    "date:inception_upper": "2023-11-01",
    "iso:country": "GB",
    "wof:name": "G21 3HF",
    "wof:placetype": "postalcode"
  },
  "geometry": {"coordinates":[-4.198981,55.879784],"type":"Point"}
}
