{
  "type": "Feature",
  "properties": {
    "iso:country":"GB",
    "wof:name":"LD3 8RH",
    "wof:placetype":"postalcode"
},
  "geometry": {"coordinates":[-3.67362234889583,51.97098066654246],"type":"Point"}
}