{
  "type": "Feature",
  "properties": {
    "iso:country":"GB",
    "wof:name":"BD18 1EL",
    "wof:placetype":"postalcode"
},
  "geometry": {"coordinates":[-1.75322682635395,53.83969702250425],"type":"Point"}
}