{
  "type": "Feature",
  "properties": {
    "iso:country":"GB",
    "wof:name":"LE5 1QF",
    "wof:placetype":"postalcode"
},
  "geometry": {"coordinates":[-1.05910982318277,52.6583632186037],"type":"Point"}
}