{
  "type": "Feature",
  "properties": {
    "date:inception_lower": "2002-11-01",
    "date:inception_upper": "2002-11-01",
    "iso:country": "GB",
    "wof:name": "LE5 1QF",
    "wof:placetype": "postalcode"
  },
  "geometry": {"coordinates":[-1.05911,52.658363],"type":"Point"}
}
