{
  "type": "Feature",
  "properties": {
    "iso:country":"GB",
    "wof:name":"DH6 1LF",
    "wof:placetype":"postalcode"
},
  "geometry": {"coordinates":[-1.47073747823811,54.76565531189924],"type":"Point"}
}