{
  "type": "Feature",
  "properties": {
    "iso:country": "GB",
    "wof:name": "DH6 1LF",
    "wof:placetype": "postalcode"
  },
  "geometry": {"coordinates":[-1.470737,54.765655],"type":"Point"}
}
