{
  "type": "Feature",
  "properties": {
    "iso:country":"GB",
    "wof:name":"DL13 3EY",
    "wof:placetype":"postalcode"
},
  "geometry": {"coordinates":[-1.88002753692716,54.73573709759189],"type":"Point"}
}