{
  "type": "Feature",
  "properties": {
    "date:inception_lower": "1980-01-01",
    "date:inception_upper": "1980-01-01",
    "iso:country": "GB",
    "wof:name": "DL13 3EY",
    "wof:placetype": "postalcode"
  },
  "geometry": {"coordinates":[-1.880084,54.73579],"type":"Point"}
}
