{
  "type": "Feature",
  "properties": {
    "iso:country": "GB",
    "wof:name": "DL13 3EY",
    "wof:placetype": "postalcode"
  },
  "geometry": {"coordinates":[-1.880027,54.735737],"type":"Point"}
}
