{
  "type": "Feature",
  "properties": {
    "iso:country":"GB",
    "wof:name":"RM7 0QA",
    "wof:placetype":"postalcode"
},
  "geometry": {"coordinates":[0.17829363473028,51.56590843759487],"type":"Point"}
}