{
  "type": "Feature",
  "properties": {
    "iso:country":"GB",
    "wof:name":"WN2 5XD",
    "wof:placetype":"postalcode"
},
  "geometry": {"coordinates":[-2.59067917974026,53.50514641585819],"type":"Point"}
}