{
  "type": "Feature",
  "properties": {
    "date:inception_lower": "2016-01-01",
    "date:inception_upper": "2016-01-01",
    "iso:country": "GB",
    "wof:name": "G69 9FE",
    "wof:placetype": "postalcode"
  },
  "geometry": {"coordinates":[-4.106077,55.906654],"type":"Point"}
}
