{
  "type": "Feature",
  "properties": {
    "iso:country":"GB",
    "wof:name":"G69 9FE",
    "wof:placetype":"postalcode"
},
  "geometry": {"coordinates":[-4.10650396740474,55.90665197578273],"type":"Point"}
}