{
  "type": "Feature",
  "properties": {
    "date:inception_lower":"1980-01-01",
    "date:inception_upper":"1980-01-31",
    "iso:country":"GB",
    "wof:name":"PL13 2LH",
    "wof:placetype":"postalcode"
},
  "geometry": {"coordinates":[-4.53224,50.368115],"type":"Point"}
}