{
  "type": "Feature",
  "properties": {
    "iso:country":"GB",
    "wof:name":"PL13 2LH",
    "wof:placetype":"postalcode"
},
  "geometry": {"coordinates":[-4.53224034873787,50.36811494619357],"type":"Point"}
}