{
  "type": "Feature",
  "properties": {
    "iso:country": "GB",
    "wof:name": "G41 1QD",
    "wof:placetype": "postalcode"
  },
  "geometry": {"coordinates":[-4.265255,55.84146],"type":"Point"}
}
