{
  "type": "Feature",
  "properties": {
    "date:inception_lower": "1980-01-01",
    "date:inception_upper": "1980-01-01",
    "iso:country": "GB",
    "wof:name": "LL46 2RN",
    "wof:placetype": "postalcode"
  },
  "geometry": {"coordinates":[-4.115712,52.843811],"type":"Point"}
}
