{
  "type": "Feature",
  "properties": {
    "iso:country":"GB",
    "wof:name":"NN3 5JT",
    "wof:placetype":"postalcode"
},
  "geometry": {"coordinates":[-0.80608756483371,52.26649994023686],"type":"Point"}
}