{
  "type": "Feature",
  "properties": {
    "date:inception_lower":"1986-07-01",
    "date:inception_upper":"1986-07-31",
    "iso:country":"GB",
    "wof:name":"NN3 5JT",
    "wof:placetype":"postalcode"
},
  "geometry": {"coordinates":[-0.806088,52.2665],"type":"Point"}
}