{
  "type": "Feature",
  "properties": {
    "date:inception_lower": "2007-01-01",
    "date:inception_upper": "2007-01-01",
    "iso:country": "GB",
    "wof:name": "PE13 1DR",
    "wof:placetype": "postalcode"
  },
  "geometry": {"coordinates":[0.159665,52.66577],"type":"Point"}
}
