{
  "type": "Feature",
  "properties": {
    "iso:country":"GB",
    "wof:name":"PE13 1DR",
    "wof:placetype":"postalcode"
},
  "geometry": {"coordinates":[0.15962284460895,52.66580538392756],"type":"Point"}
}