{
  "type": "Feature",
  "properties": {
    "iso:country":"GB",
    "wof:name":"DH8 0UE",
    "wof:placetype":"postalcode"
},
  "geometry": {"coordinates":[-1.84837921385731,54.87243964807818],"type":"Point"}
}