{
  "type": "Feature",
  "properties": {
    "date:inception_lower": "1990-02-01",
    "date:inception_upper": "1990-02-01",
    "iso:country": "GB",
    "wof:name": "DH8 0UE",
    "wof:placetype": "postalcode"
  },
  "geometry": {"coordinates":[-1.848379,54.87244],"type":"Point"}
}
