{
  "type": "Feature",
  "properties": {
    "iso:country": "GB",
    "wof:name": "DH8 0UE",
    "wof:placetype": "postalcode"
  },
  "geometry": {"coordinates":[-1.848379,54.87244],"type":"Point"}
}
