{
  "type": "Feature",
  "properties": {
    "iso:country": "GB",
    "wof:name": "NE6 3DB",
    "wof:placetype": "postalcode"
  },
  "geometry": {"coordinates":[-1.544056,54.972264],"type":"Point"}
}
