{
  "type": "Feature",
  "properties": {
    "date:inception_lower":"1993-01-01",
    "date:inception_upper":"1993-01-31",
    "iso:country":"GB",
    "wof:name":"NE6 3DB",
    "wof:placetype":"postalcode"
},
  "geometry": {"coordinates":[-1.544056,54.972264],"type":"Point"}
}