{
  "type": "Feature",
  "properties": {
    "date:inception_lower": "1980-01-01",
    "date:inception_upper": "1980-01-01",
    "iso:country": "GB",
    "wof:name": "SY7 9PS",
    "wof:placetype": "postalcode"
  },
  "geometry": {"coordinates":[-2.835286,52.444737],"type":"Point"}
}
