{
  "type": "Feature",
  "properties": {
    "iso:country":"GB",
    "wof:name":"SY7 9PS",
    "wof:placetype":"postalcode"
},
  "geometry": {"coordinates":[-2.83528609126373,52.44473684907729],"type":"Point"}
}