{
  "type": "Feature",
  "properties": {
    "iso:country": "GB",
    "wof:name": "SY7 9PS",
    "wof:placetype": "postalcode"
  },
  "geometry": {"coordinates":[-2.835286,52.444737],"type":"Point"}
}
