{
  "type": "Feature",
  "properties": {
    "iso:country": "GB",
    "wof:name": "DE21 2DQ",
    "wof:placetype": "postalcode"
  },
  "geometry": {"coordinates":[-1.436026,52.942453],"type":"Point"}
}
