{
  "type": "Feature",
  "properties": {
    "date:inception_lower":"1980-01-01",
    "date:inception_upper":"1980-01-31",
    "iso:country":"GB",
    "wof:name":"OX14 4HA",
    "wof:placetype":"postalcode"
},
  "geometry": {"coordinates":[-1.295811,51.644122],"type":"Point"}
}