{
  "type": "Feature",
  "properties": {
    "iso:country": "GB",
    "wof:name": "EH7 6GX",
    "wof:placetype": "postalcode"
  },
  "geometry": {"coordinates":[-3.147627,55.966285],"type":"Point"}
}
