{
  "type": "Feature",
  "properties": {
    "iso:country": "GB",
    "wof:name": "ST16 3AZ",
    "wof:placetype": "postalcode"
  },
  "geometry": {"coordinates":[-2.12058,52.815124],"type":"Point"}
}
