{
  "type": "Feature",
  "properties": {
    "date:inception_lower":"1980-01-01",
    "date:inception_upper":"1980-01-31",
    "iso:country":"GB",
    "wof:name":"LE4 3DG",
    "wof:placetype":"postalcode"
},
  "geometry": {"coordinates":[-1.128396,52.67886],"type":"Point"}
}