{
  "type": "Feature",
  "properties": {
    "iso:country":"GB",
    "wof:name":"LE4 3DG",
    "wof:placetype":"postalcode"
},
  "geometry": {"coordinates":[-1.12839605642415,52.67885956544387],"type":"Point"}
}