{
  "type": "Feature",
  "properties": {
    "iso:country":"GB",
    "wof:name":"B25 8AP",
    "wof:placetype":"postalcode"
},
  "geometry": {"coordinates":[-1.8234497017456,52.46374784468172],"type":"Point"}
}