{
  "type": "Feature",
  "properties": {
    "date:inception_lower":"1991-01-01",
    "date:inception_upper":"1991-01-31",
    "iso:country":"GB",
    "wof:name":"RH5 4RU",
    "wof:placetype":"postalcode"
},
  "geometry": {"coordinates":[-0.299942,51.1335],"type":"Point"}
}