{
  "type": "Feature",
  "properties": {
    "iso:country": "GB",
    "wof:name": "RH5 4RU",
    "wof:placetype": "postalcode"
  },
  "geometry": {"coordinates":[-0.299942,51.1335],"type":"Point"}
}
