{
  "type": "Feature",
  "properties": {
    "iso:country":"GB",
    "wof:name":"RH5 4RU",
    "wof:placetype":"postalcode"
},
  "geometry": {"coordinates":[-0.29994209997305,51.13350039838781],"type":"Point"}
}