{
  "type": "Feature",
  "properties": {
    "iso:country":"GB",
    "wof:name":"PO9 5HX",
    "wof:placetype":"postalcode"
},
  "geometry": {"coordinates":[-0.97852464183536,50.87021662142114],"type":"Point"}
}