{
  "type": "Feature",
  "properties": {
    "iso:country": "GB",
    "wof:name": "SO41 5PB",
    "wof:placetype": "postalcode"
  },
  "geometry": {"coordinates":[-1.545113,50.78756],"type":"Point"}
}
