{
  "type": "Feature",
  "properties": {
    "iso:country":"GB",
    "wof:name":"SO41 5PB",
    "wof:placetype":"postalcode"
},
  "geometry": {"coordinates":[-1.54511286153512,50.78755997279071],"type":"Point"}
}