{
  "type": "Feature",
  "properties": {
    "date:inception_lower":"2008-02-01",
    "date:inception_upper":"2008-02-29",
    "iso:country":"GB",
    "wof:name":"SO41 5PB",
    "wof:placetype":"postalcode"
},
  "geometry": {"coordinates":[-1.545113,50.78756],"type":"Point"}
}