{
  "type": "Feature",
  "properties": {
    "date:inception_lower": "2001-06-01",
    "date:inception_upper": "2001-06-01",
    "iso:country": "GB",
    "wof:name": "CH7 6NL",
    "wof:placetype": "postalcode"
  },
  "geometry": {"coordinates":[-3.105592,53.174944],"type":"Point"}
}
