{
  "type": "Feature",
  "properties": {
    "iso:country":"GB",
    "wof:name":"CH7 6NL",
    "wof:placetype":"postalcode"
},
  "geometry": {"coordinates":[-3.10559167978272,53.17494379112715],"type":"Point"}
}