{
  "type": "Feature",
  "properties": {
    "iso:country":"GB",
    "wof:name":"SE1 4TL",
    "wof:placetype":"postalcode"
},
  "geometry": {"coordinates":[-0.08390770940466,51.49560240737205],"type":"Point"}
}