{
  "type": "Feature",
  "properties": {
    "iso:country": "GB",
    "wof:name": "SE1 4TL",
    "wof:placetype": "postalcode"
  },
  "geometry": {"coordinates":[-0.083908,51.495602],"type":"Point"}
}
