{
  "type": "Feature",
  "properties": {
    "date:inception_lower": "1992-08-01",
    "date:inception_upper": "1992-08-01",
    "iso:country": "GB",
    "wof:name": "PR6 0JU",
    "wof:placetype": "postalcode"
  },
  "geometry": {"coordinates":[-2.617001,53.662527],"type":"Point"}
}
