{
  "type": "Feature",
  "properties": {
    "iso:country": "GB",
    "wof:name": "S75 2SU",
    "wof:placetype": "postalcode"
  },
  "geometry": {"coordinates":[-1.495142,53.559365],"type":"Point"}
}
