{
  "type": "Feature",
  "properties": {
    "iso:country":"GB",
    "wof:name":"S75 2SU",
    "wof:placetype":"postalcode"
},
  "geometry": {"coordinates":[-1.49514247438408,53.5593649544624],"type":"Point"}
}