{
  "type": "Feature",
  "properties": {
    "iso:country": "GB",
    "wof:name": "L5 9TZ",
    "wof:placetype": "postalcode"
  },
  "geometry": {"coordinates":[-2.996031,53.424629],"type":"Point"}
}
