{
  "type": "Feature",
  "properties": {
    "date:inception_lower": "1980-01-01",
    "date:inception_upper": "1980-01-01",
    "iso:country": "GB",
    "wof:name": "SY12 9LL",
    "wof:placetype": "postalcode"
  },
  "geometry": {"coordinates":[-2.958149,52.926351],"type":"Point"}
}
