{
  "type": "Feature",
  "properties": {
    "iso:country": "GB",
    "wof:name": "SY12 9LL",
    "wof:placetype": "postalcode"
  },
  "geometry": {"coordinates":[-2.958149,52.926351],"type":"Point"}
}
