{
  "type": "Feature",
  "properties": {
    "date:inception_lower": "1980-01-01",
    "date:inception_upper": "1980-01-01",
    "iso:country": "GB",
    "wof:name": "WS4 1PY",
    "wof:placetype": "postalcode"
  },
  "geometry": {"coordinates":[-1.948318,52.619042],"type":"Point"}
}
