{
  "type": "Feature",
  "properties": {
    "iso:country":"GB",
    "wof:name":"WS4 1PY",
    "wof:placetype":"postalcode"
},
  "geometry": {"coordinates":[-1.94831852166428,52.61904207596655],"type":"Point"}
}