{
  "type": "Feature",
  "properties": {
    "date:inception_lower": "1980-01-01",
    "date:inception_upper": "1980-01-01",
    "iso:country": "GB",
    "wof:name": "EN7 5ET",
    "wof:placetype": "postalcode"
  },
  "geometry": {"coordinates":[-0.085946,51.710136],"type":"Point"}
}
