{
  "type": "Feature",
  "properties": {
    "iso:country": "GB",
    "wof:name": "IP28 8YZ",
    "wof:placetype": "postalcode"
  },
  "geometry": {"coordinates":[0.502005,52.299481],"type":"Point"}
}
