{
  "type": "Feature",
  "properties": {
    "date:inception_lower": "2021-08-01",
    "date:inception_upper": "2021-08-01",
    "iso:country": "GB",
    "wof:name": "NG23 5GU",
    "wof:placetype": "postalcode"
  },
  "geometry": {"coordinates":[-0.758006,53.000127],"type":"Point"}
}
