{
  "type": "Feature",
  "properties": {
    "date:inception_lower": "2018-03-01",
    "date:inception_upper": "2018-03-01",
    "iso:country": "GB",
    "wof:name": "NE61 3FJ",
    "wof:placetype": "postalcode"
  },
  "geometry": {"coordinates":[-1.709864,55.17978],"type":"Point"}
}
