{
  "type": "Feature",
  "properties": {
    "date:inception_lower": "2021-08-01",
    "date:inception_upper": "2021-08-01",
    "iso:country": "GB",
    "wof:name": "YO11 3XF",
    "wof:placetype": "postalcode"
  },
  "geometry": {"coordinates":[-0.393981,54.248283],"type":"Point"}
}
