{
  "type": "Feature",
  "properties": {
    "iso:country":"GB",
    "wof:name":"B45 8NP",
    "wof:placetype":"postalcode"
},
  "geometry": {"coordinates":[-1.98826682305387,52.36071768247982],"type":"Point"}
}