{
  "type": "Feature",
  "properties": {
    "iso:country": "GB",
    "wof:name": "BN17 6DJ",
    "wof:placetype": "postalcode"
  },
  "geometry": {"coordinates":[-0.529499,50.817122],"type":"Point"}
}
