{
  "type": "Feature",
  "properties": {
    "iso:country":"GB",
    "wof:name":"BN17 6DJ",
    "wof:placetype":"postalcode"
},
  "geometry": {"coordinates":[-0.52962363295325,50.8170695234861],"type":"Point"}
}