{
  "type": "Feature",
  "properties": {
    "date:inception_lower": "1982-03-01",
    "date:inception_upper": "1982-03-01",
    "iso:country": "GB",
    "wof:name": "NG23 6HZ",
    "wof:placetype": "postalcode"
  },
  "geometry": {"coordinates":[-0.809723,53.119108],"type":"Point"}
}
