{
  "type": "Feature",
  "properties": {
    "iso:country":"GB",
    "wof:name":"LE4 4AW",
    "wof:placetype":"postalcode"
},
  "geometry": {"coordinates":[-1.12313632580632,52.67043317220275],"type":"Point"}
}