{
  "type": "Feature",
  "properties": {
    "date:inception_lower": "2019-03-01",
    "date:inception_upper": "2019-03-01",
    "iso:country": "GB",
    "wof:name": "DE22 3XU",
    "wof:placetype": "postalcode"
  },
  "geometry": {"coordinates":[-1.510859,52.915915],"type":"Point"}
}
