{
  "type": "Feature",
  "properties": {
    "iso:country":"GB",
    "wof:name":"RM3 0FE",
    "wof:placetype":"postalcode"
},
  "geometry": {"coordinates":[0.22569914231707,51.59318437751936],"type":"Point"}
}