{
  "type": "Feature",
  "properties": {
    "date:inception_lower": "1996-06-01",
    "date:inception_upper": "1996-06-01",
    "iso:country": "GB",
    "wof:name": "DH6 3EQ",
    "wof:placetype": "postalcode"
  },
  "geometry": {"coordinates":[-1.43392,54.753267],"type":"Point"}
}
