{
  "type": "Feature",
  "properties": {
    "iso:country":"GB",
    "wof:name":"DH6 3EQ",
    "wof:placetype":"postalcode"
},
  "geometry": {"coordinates":[-1.43392030556381,54.75326732220369],"type":"Point"}
}