{
  "type": "Feature",
  "properties": {
    "date:inception_lower": "2010-10-01",
    "date:inception_upper": "2010-10-01",
    "iso:country": "GB",
    "wof:name": "AB33 8DZ",
    "wof:placetype": "postalcode"
  },
  "geometry": {"coordinates":[-2.651183,57.258386],"type":"Point"}
}
