{
  "type": "Feature",
  "properties": {
    "date:inception_lower": "1980-01-01",
    "date:inception_upper": "1980-01-01",
    "iso:country": "GB",
    "wof:name": "CT6 5PB",
    "wof:placetype": "postalcode"
  },
  "geometry": {"coordinates":[1.127899,51.369434],"type":"Point"}
}
