{
  "type": "Feature",
  "properties": {
    "iso:country":"GB",
    "wof:name":"CT6 5PB",
    "wof:placetype":"postalcode"
},
  "geometry": {"coordinates":[1.12797706342497,51.36953470598522],"type":"Point"}
}