{
  "type": "Feature",
  "properties": {
    "iso:country": "GB",
    "wof:name": "DA11 7EL",
    "wof:placetype": "postalcode"
  },
  "geometry": {"coordinates":[0.35204,51.427099],"type":"Point"}
}
