{
  "type": "Feature",
  "properties": {
    "iso:country": "GB",
    "wof:name": "CM77 7UY",
    "wof:placetype": "postalcode"
  },
  "geometry": {"coordinates":[0.531057,51.862959],"type":"Point"}
}
