{
  "type": "Feature",
  "properties": {
    "iso:country":"GB",
    "wof:name":"CM77 7UY",
    "wof:placetype":"postalcode"
},
  "geometry": {"coordinates":[0.53105662017463,51.86295853696704],"type":"Point"}
}