{
  "type": "Feature",
  "properties": {
    "iso:country":"GB",
    "wof:name":"LE12 8JZ",
    "wof:placetype":"postalcode"
},
  "geometry": {"coordinates":[-1.15167277628699,52.75238563486809],"type":"Point"}
}