{
  "type": "Feature",
  "properties": {
    "iso:country":"GB",
    "wof:name":"NE10 8BU",
    "wof:placetype":"postalcode"
},
  "geometry": {"coordinates":[-1.53526469743714,54.93944832002583],"type":"Point"}
}