{
  "type": "Feature",
  "properties": {
    "iso:country": "GB",
    "wof:name": "NE10 8BU",
    "wof:placetype": "postalcode"
  },
  "geometry": {"coordinates":[-1.535265,54.939448],"type":"Point"}
}
