{
  "type": "Feature",
  "properties": {
    "iso:country": "GB",
    "wof:name": "BD7 2RJ",
    "wof:placetype": "postalcode"
  },
  "geometry": {"coordinates":[-1.7987,53.784794],"type":"Point"}
}
