{
  "type": "Feature",
  "properties": {
    "date:inception_lower":"1980-01-01",
    "date:inception_upper":"1980-01-31",
    "iso:country":"GB",
    "wof:name":"BD7 2RJ",
    "wof:placetype":"postalcode"
},
  "geometry": {"coordinates":[-1.7987,53.784794],"type":"Point"}
}