{
  "type": "Feature",
  "properties": {
    "iso:country":"GB",
    "wof:name":"HR7 4DH",
    "wof:placetype":"postalcode"
},
  "geometry": {"coordinates":[-2.50252848346424,52.1868899267621],"type":"Point"}
}