{
  "type": "Feature",
  "properties": {
    "iso:country":"GB",
    "wof:name":"SE21 8NY",
    "wof:placetype":"postalcode"
},
  "geometry": {"coordinates":[-0.08185938364498,51.43283624987877],"type":"Point"}
}