{
  "type": "Feature",
  "properties": {
    "iso:country":"GB",
    "wof:name":"LE11 2LQ",
    "wof:placetype":"postalcode"
},
  "geometry": {"coordinates":[-1.20089402765796,52.75875946389976],"type":"Point"}
}