{
  "type": "Feature",
  "properties": {
    "date:inception_lower": "1993-08-01",
    "date:inception_upper": "1993-08-01",
    "iso:country": "GB",
    "wof:name": "LE11 2LQ",
    "wof:placetype": "postalcode"
  },
  "geometry": {"coordinates":[-1.200894,52.758759],"type":"Point"}
}
