{
  "type": "Feature",
  "properties": {
    "iso:country": "GB",
    "wof:name": "ME15 9DR",
    "wof:placetype": "postalcode"
  },
  "geometry": {"coordinates":[0.543226,51.245471],"type":"Point"}
}
