{
  "type": "Feature",
  "properties": {
    "date:inception_lower": "1980-01-01",
    "date:inception_upper": "1980-01-01",
    "iso:country": "GB",
    "wof:name": "ME15 9DR",
    "wof:placetype": "postalcode"
  },
  "geometry": {"coordinates":[0.543226,51.245471],"type":"Point"}
}
