{
  "type": "Feature",
  "properties": {
    "date:inception_lower": "1980-01-01",
    "date:inception_upper": "1980-01-01",
    "iso:country": "GB",
    "wof:name": "CH7 2BJ",
    "wof:placetype": "postalcode"
  },
  "geometry": {"coordinates":[-3.083538,53.161285],"type":"Point"}
}
