{
  "type": "Feature",
  "properties": {
    "iso:country":"GB",
    "wof:name":"CH7 2BJ",
    "wof:placetype":"postalcode"
},
  "geometry": {"coordinates":[-3.08353802764137,53.16128489533264],"type":"Point"}
}