{
  "type": "Feature",
  "properties": {
    "iso:country": "GB",
    "wof:name": "CW2 5TX",
    "wof:placetype": "postalcode"
  },
  "geometry": {"coordinates":[-2.453512,53.055351],"type":"Point"}
}
