{
  "type": "Feature",
  "properties": {
    "date:inception_lower": "2018-12-01",
    "date:inception_upper": "2018-12-01",
    "iso:country": "GB",
    "wof:name": "CW2 5TX",
    "wof:placetype": "postalcode"
  },
  "geometry": {"coordinates":[-2.453138,53.055226],"type":"Point"}
}
