{
  "type": "Feature",
  "properties": {
    "date:inception_lower":"1980-01-01",
    "date:inception_upper":"1980-01-31",
    "iso:country":"GB",
    "wof:name":"OL4 4DN",
    "wof:placetype":"postalcode"
},
  "geometry": {"coordinates":[-2.040987,53.53743],"type":"Point"}
}