{
  "type": "Feature",
  "properties": {
    "iso:country": "GB",
    "wof:name": "OL4 4DN",
    "wof:placetype": "postalcode"
  },
  "geometry": {"coordinates":[-2.040987,53.53743],"type":"Point"}
}
