{
  "type": "Feature",
  "properties": {
    "iso:country":"GB",
    "wof:name":"IP7 7EE",
    "wof:placetype":"postalcode"
},
  "geometry": {"coordinates":[0.89643401158744,52.10528198053995],"type":"Point"}
}