{
  "type": "Feature",
  "properties": {
    "iso:country":"GB",
    "wof:name":"PH7 4HJ",
    "wof:placetype":"postalcode"
},
  "geometry": {"coordinates":[-3.83974673376896,56.35204396422215],"type":"Point"}
}