{
  "type": "Feature",
  "properties": {
    "date:inception_lower": "2006-08-01",
    "date:inception_upper": "2006-08-01",
    "iso:country": "GB",
    "wof:name": "WF7 6GB",
    "wof:placetype": "postalcode"
  },
  "geometry": {"coordinates":[-1.401517,53.67678],"type":"Point"}
}
