{
  "type": "Feature",
  "properties": {
    "iso:country":"GB",
    "wof:name":"WF7 6GB",
    "wof:placetype":"postalcode"
},
  "geometry": {"coordinates":[-1.40151738134035,53.67677990207796],"type":"Point"}
}