{
  "type": "Feature",
  "properties": {
    "iso:country":"GB",
    "wof:name":"CT19 6EH",
    "wof:placetype":"postalcode"
},
  "geometry": {"coordinates":[1.1857427418486,51.08882993635304],"type":"Point"}
}