{
  "type": "Feature",
  "properties": {
    "date:inception_lower": "1980-01-01",
    "date:inception_upper": "1980-01-01",
    "iso:country": "GB",
    "wof:name": "SA62 3UP",
    "wof:placetype": "postalcode"
  },
  "geometry": {"coordinates":[-5.109279,51.771653],"type":"Point"}
}
