{
  "type": "Feature",
  "properties": {
    "iso:country": "GB",
    "wof:name": "SA62 3UP",
    "wof:placetype": "postalcode"
  },
  "geometry": {"coordinates":[-5.109279,51.771653],"type":"Point"}
}
