{
  "type": "Feature",
  "properties": {
    "iso:country":"GB",
    "wof:name":"SA62 3UP",
    "wof:placetype":"postalcode"
},
  "geometry": {"coordinates":[-5.10927881331097,51.77165298346369],"type":"Point"}
}