{
  "type": "Feature",
  "properties": {
    "iso:country":"GB",
    "wof:name":"NE5 2EY",
    "wof:placetype":"postalcode"
},
  "geometry": {"coordinates":[-1.69814037914924,54.9919199361077],"type":"Point"}
}