{
  "type": "Feature",
  "properties": {
    "iso:country":"GB",
    "wof:name":"NN6 9RJ",
    "wof:placetype":"postalcode"
},
  "geometry": {"coordinates":[-0.84660693356813,52.35226012314376],"type":"Point"}
}