{
  "type": "Feature",
  "properties": {
    "date:inception_lower":"1980-01-01",
    "date:inception_upper":"1980-01-31",
    "iso:country":"GB",
    "wof:name":"NN6 9RJ",
    "wof:placetype":"postalcode"
},
  "geometry": {"coordinates":[-0.846607,52.35226],"type":"Point"}
}