{
  "type": "Feature",
  "properties": {
    "iso:country": "GB",
    "wof:name": "NN6 9RJ",
    "wof:placetype": "postalcode"
  },
  "geometry": {"coordinates":[-0.846607,52.35226],"type":"Point"}
}
