{
  "type": "Feature",
  "properties": {
    "iso:country":"GB",
    "wof:name":"L20 4EA",
    "wof:placetype":"postalcode"
},
  "geometry": {"coordinates":[-2.99953153179651,53.45127059646908],"type":"Point"}
}