{
  "type": "Feature",
  "properties": {
    "iso:country": "GB",
    "wof:name": "SO23 8AU",
    "wof:placetype": "postalcode"
  },
  "geometry": {"coordinates":[-1.313185,51.064806],"type":"Point"}
}
