{
  "type": "Feature",
  "properties": {
    "date:inception_lower": "1997-12-01",
    "date:inception_upper": "1997-12-01",
    "iso:country": "GB",
    "wof:name": "SO23 8AU",
    "wof:placetype": "postalcode"
  },
  "geometry": {"coordinates":[-1.313185,51.064806],"type":"Point"}
}
