{
  "type": "Feature",
  "properties": {
    "iso:country":"GB",
    "wof:name":"CF31 1RR",
    "wof:placetype":"postalcode"
},
  "geometry": {"coordinates":[-3.58159564508097,51.52136420354157],"type":"Point"}
}