{
  "type": "Feature",
  "properties": {
    "date:inception_lower": "2007-07-01",
    "date:inception_upper": "2007-07-01",
    "iso:country": "GB",
    "wof:name": "TS17 8GG",
    "wof:placetype": "postalcode"
  },
  "geometry": {"coordinates":[-1.291978,54.550434],"type":"Point"}
}
