{
  "type": "Feature",
  "properties": {
    "iso:country": "GB",
    "wof:name": "SA73 3RA",
    "wof:placetype": "postalcode"
  },
  "geometry": {"coordinates":[-5.054191,51.71416],"type":"Point"}
}
