{
  "type": "Feature",
  "properties": {
    "iso:country":"GB",
    "wof:name":"SA73 3RA",
    "wof:placetype":"postalcode"
},
  "geometry": {"coordinates":[-5.05419104407513,51.71416038478187],"type":"Point"}
}