{
  "type": "Feature",
  "properties": {
    "iso:country":"GB",
    "wof:name":"BH1 4DP",
    "wof:placetype":"postalcode"
},
  "geometry": {"coordinates":[-1.84810111812106,50.72585756097695],"type":"Point"}
}