{
  "type": "Feature",
  "properties": {
    "iso:country": "GB",
    "wof:name": "WN1 3EY",
    "wof:placetype": "postalcode"
  },
  "geometry": {"coordinates":[-2.623844,53.543835],"type":"Point"}
}
