{
  "type": "Feature",
  "properties": {
    "iso:country":"GB",
    "wof:name":"KT14 6BN",
    "wof:placetype":"postalcode"
},
  "geometry": {"coordinates":[-0.50829613339782,51.33622044769021],"type":"Point"}
}