{
  "type": "Feature",
  "properties": {
    "iso:country":"GB",
    "wof:name":"AB42 3FB",
    "wof:placetype":"postalcode"
},
  "geometry": {"coordinates":[-1.78621681123848,57.47339050767858],"type":"Point"}
}