{
  "type": "Feature",
  "properties": {
    "iso:country":"GB",
    "wof:name":"SP3 4SP",
    "wof:placetype":"postalcode"
},
  "geometry": {"coordinates":[-1.89205690793173,51.16587388024402],"type":"Point"}
}