{
  "type": "Feature",
  "properties": {
    "date:inception_lower": "1996-06-01",
    "date:inception_upper": "1996-06-01",
    "iso:country": "GB",
    "wof:name": "AB16 6FE",
    "wof:placetype": "postalcode"
  },
  "geometry": {"coordinates":[-2.176713,57.153651],"type":"Point"}
}
