{
  "type": "Feature",
  "properties": {
    "iso:country":"GB",
    "wof:name":"LL13 9NH",
    "wof:placetype":"postalcode"
},
  "geometry": {"coordinates":[-2.96821484593202,53.05264424557759],"type":"Point"}
}