{
  "type": "Feature",
  "properties": {
    "date:inception_lower":"1980-01-01",
    "date:inception_upper":"1980-01-31",
    "iso:country":"GB",
    "wof:name":"LL13 9NH",
    "wof:placetype":"postalcode"
},
  "geometry": {"coordinates":[-2.968248,53.052804],"type":"Point"}
}