{
  "type": "Feature",
  "properties": {
    "iso:country":"GB",
    "wof:name":"TA7 8QZ",
    "wof:placetype":"postalcode"
},
  "geometry": {"coordinates":[-2.94561427348447,51.13461901717047],"type":"Point"}
}