{
  "type": "Feature",
  "properties": {
    "date:inception_lower":"1995-12-01",
    "date:inception_upper":"1995-12-31",
    "iso:country":"GB",
    "wof:name":"DE75 7NN",
    "wof:placetype":"postalcode"
},
  "geometry": {"coordinates":[-1.368975,53.024072],"type":"Point"}
}