{
  "type": "Feature",
  "properties": {
    "iso:country":"GB",
    "wof:name":"DE75 7NN",
    "wof:placetype":"postalcode"
},
  "geometry": {"coordinates":[-1.36897543645573,53.02407184561605],"type":"Point"}
}