{
  "type": "Feature",
  "properties": {
    "iso:country":"GB",
    "wof:name":"PO33 1BE",
    "wof:placetype":"postalcode"
},
  "geometry": {"coordinates":[-1.15594029284708,50.71978250551317],"type":"Point"}
}