{
  "type": "Feature",
  "properties": {
    "iso:country":"GB",
    "wof:name":"PL3 6BU",
    "wof:placetype":"postalcode"
},
  "geometry": {"coordinates":[-4.11038926406103,50.38406750713479],"type":"Point"}
}