{
  "type": "Feature",
  "properties": {
    "iso:country":"GB",
    "wof:name":"NR29 5HY",
    "wof:placetype":"postalcode"
},
  "geometry": {"coordinates":[1.57319317930798,52.71356129201286],"type":"Point"}
}