{
  "type": "Feature",
  "properties": {
    "iso:country": "GB",
    "wof:name": "NR29 5HY",
    "wof:placetype": "postalcode"
  },
  "geometry": {"coordinates":[1.57316,52.713446],"type":"Point"}
}
