{
  "type": "Feature",
  "properties": {
    "iso:country":"GB",
    "wof:name":"DL14 7TE",
    "wof:placetype":"postalcode"
},
  "geometry": {"coordinates":[-1.6755577715528,54.65752048254016],"type":"Point"}
}