{
  "type": "Feature",
  "properties": {
    "date:inception_lower":"1980-01-01",
    "date:inception_upper":"1980-01-31",
    "iso:country":"GB",
    "wof:name":"DL14 7TE",
    "wof:placetype":"postalcode"
},
  "geometry": {"coordinates":[-1.67549,54.657548],"type":"Point"}
}