{
  "type": "Feature",
  "properties": {
    "iso:country": "GB",
    "wof:name": "DL14 7TE",
    "wof:placetype": "postalcode"
  },
  "geometry": {"coordinates":[-1.67549,54.657548],"type":"Point"}
}
