{
  "type": "Feature",
  "properties": {
    "iso:country":"GB",
    "wof:name":"HA7 2AF",
    "wof:placetype":"postalcode"
},
  "geometry": {"coordinates":[-0.32301296498982,51.6010395735946],"type":"Point"}
}