{
  "type": "Feature",
  "properties": {
    "date:inception_lower": "1997-12-01",
    "date:inception_upper": "1997-12-01",
    "iso:country": "GB",
    "wof:name": "PE2 8QS",
    "wof:placetype": "postalcode"
  },
  "geometry": {"coordinates":[-0.226538,52.553669],"type":"Point"}
}
