{
  "type": "Feature",
  "properties": {
    "iso:country":"GB",
    "wof:name":"PE2 8QS",
    "wof:placetype":"postalcode"
},
  "geometry": {"coordinates":[-0.22653820434891,52.55366908669446],"type":"Point"}
}