{
  "type": "Feature",
  "properties": {
    "date:inception_lower": "1980-01-01",
    "date:inception_upper": "1980-01-01",
    "iso:country": "GB",
    "wof:name": "PE31 7JY",
    "wof:placetype": "postalcode"
  },
  "geometry": {"coordinates":[0.497299,52.921106],"type":"Point"}
}
