{
  "type": "Feature",
  "properties": {
    "iso:country":"GB",
    "wof:name":"PE31 7JY",
    "wof:placetype":"postalcode"
},
  "geometry": {"coordinates":[0.49729534137524,52.92096416550252],"type":"Point"}
}