{
  "type": "Feature",
  "properties": {
    "iso:country":"GB",
    "wof:name":"PE37 8LS",
    "wof:placetype":"postalcode"
},
  "geometry": {"coordinates":[0.75181117381401,52.62875482474085],"type":"Point"}
}