{
  "type": "Feature",
  "properties": {
    "date:inception_lower": "2001-12-01",
    "date:inception_upper": "2001-12-01",
    "iso:country": "GB",
    "wof:name": "PE37 8LS",
    "wof:placetype": "postalcode"
  },
  "geometry": {"coordinates":[0.751811,52.628755],"type":"Point"}
}
