{
  "type": "Feature",
  "properties": {
    "iso:country":"GB",
    "wof:name":"LN4 3SA",
    "wof:placetype":"postalcode"
},
  "geometry": {"coordinates":[-0.33091630377199,53.11313369721807],"type":"Point"}
}