{
  "type": "Feature",
  "properties": {
    "iso:country": "GB",
    "wof:name": "SL1 2JZ",
    "wof:placetype": "postalcode"
  },
  "geometry": {"coordinates":[-0.599266,51.506621],"type":"Point"}
}
