{
  "type": "Feature",
  "properties": {
    "iso:country":"GB",
    "wof:name":"SL1 2JZ",
    "wof:placetype":"postalcode"
},
  "geometry": {"coordinates":[-0.59926617598947,51.50662131138557],"type":"Point"}
}