{
  "type": "Feature",
  "properties": {
    "date:inception_lower":"1985-04-01",
    "date:inception_upper":"1985-04-30",
    "iso:country":"GB",
    "wof:name":"SL1 2JZ",
    "wof:placetype":"postalcode"
},
  "geometry": {"coordinates":[-0.599266,51.506621],"type":"Point"}
}