{
  "type": "Feature",
  "properties": {
    "iso:country": "GB",
    "wof:name": "PL6 7AY",
    "wof:placetype": "postalcode"
  },
  "geometry": {"coordinates":[-4.110503,50.440136],"type":"Point"}
}
