{
  "type": "Feature",
  "properties": {
    "iso:country":"GB",
    "wof:name":"PL6 7AY",
    "wof:placetype":"postalcode"
},
  "geometry": {"coordinates":[-4.11050263024864,50.44013586116305],"type":"Point"}
}