{
  "type": "Feature",
  "properties": {
    "iso:country":"GB",
    "wof:name":"KY16 8XB",
    "wof:placetype":"postalcode"
},
  "geometry": {"coordinates":[-2.81122979453037,56.32991932848177],"type":"Point"}
}