{
  "type": "Feature",
  "properties": {
    "date:inception_lower": "1981-06-01",
    "date:inception_upper": "1981-06-01",
    "iso:country": "GB",
    "wof:name": "SK7 3DF",
    "wof:placetype": "postalcode"
  },
  "geometry": {"coordinates":[-2.146283,53.37852],"type":"Point"}
}
