{
  "type": "Feature",
  "properties": {
    "iso:country": "GB",
    "wof:name": "SK7 3DF",
    "wof:placetype": "postalcode"
  },
  "geometry": {"coordinates":[-2.146268,53.378565],"type":"Point"}
}
