{
  "type": "Feature",
  "properties": {
    "iso:country":"GB",
    "wof:name":"SK7 3DF",
    "wof:placetype":"postalcode"
},
  "geometry": {"coordinates":[-2.14628406363392,53.37850291531615],"type":"Point"}
}