{
  "type": "Feature",
  "properties": {
    "iso:country": "GB",
    "wof:name": "WR5 3SZ",
    "wof:placetype": "postalcode"
  },
  "geometry": {"coordinates":[-2.205885,52.170079],"type":"Point"}
}
