{
  "type": "Feature",
  "properties": {
    "iso:country": "GB",
    "wof:name": "LN6 9HD",
    "wof:placetype": "postalcode"
  },
  "geometry": {"coordinates":[-0.729106,53.204233],"type":"Point"}
}
