{
  "type": "Feature",
  "properties": {
    "iso:country":"GB",
    "wof:name":"HA4 7EB",
    "wof:placetype":"postalcode"
},
  "geometry": {"coordinates":[-0.42418302817441,51.57245264352434],"type":"Point"}
}