{
  "type": "Feature",
  "properties": {
    "date:inception_lower":"1983-01-01",
    "date:inception_upper":"1983-01-31",
    "iso:country":"GB",
    "wof:name":"HA4 7EB",
    "wof:placetype":"postalcode"
},
  "geometry": {"coordinates":[-0.424183,51.572453],"type":"Point"}
}