{
  "type": "Feature",
  "properties": {
    "iso:country":"GB",
    "wof:name":"BS16 4QN",
    "wof:placetype":"postalcode"
},
  "geometry": {"coordinates":[-2.50541307138155,51.47839312511114],"type":"Point"}
}