{
  "type": "Feature",
  "properties": {
    "iso:country":"GB",
    "wof:name":"SP8 5JL",
    "wof:placetype":"postalcode"
},
  "geometry": {"coordinates":[-2.28164173202987,51.02544171276722],"type":"Point"}
}