{
  "type": "Feature",
  "properties": {
    "iso:country":"GB",
    "wof:name":"W14 0BT",
    "wof:placetype":"postalcode"
},
  "geometry": {"coordinates":[-0.21978363343755,51.50166443310641],"type":"Point"}
}