{
  "type": "Feature",
  "properties": {
    "iso:country":"GB",
    "wof:name":"UB2 5GR",
    "wof:placetype":"postalcode"
},
  "geometry": {"coordinates":[-0.38634304778339,51.50242867305057],"type":"Point"}
}