{
  "type": "Feature",
  "properties": {
    "iso:country":"GB",
    "wof:name":"NP4 9DF",
    "wof:placetype":"postalcode"
},
  "geometry": {"coordinates":[-3.09558954576917,51.77004456985989],"type":"Point"}
}