{
  "type": "Feature",
  "properties": {
    "iso:country":"GB",
    "wof:name":"E14 3DP",
    "wof:placetype":"postalcode"
},
  "geometry": {"coordinates":[-0.00637779952404,51.49049705687018],"type":"Point"}
}