{
  "type": "Feature",
  "properties": {
    "date:inception_lower": "1994-12-01",
    "date:inception_upper": "1994-12-01",
    "iso:country": "GB",
    "wof:name": "SO16 3HS",
    "wof:placetype": "postalcode"
  },
  "geometry": {"coordinates":[-1.396348,50.938985],"type":"Point"}
}
