{
  "type": "Feature",
  "properties": {
    "date:inception_lower": "1980-01-01",
    "date:inception_upper": "1980-01-01",
    "iso:country": "GB",
    "wof:name": "NR19 2RW",
    "wof:placetype": "postalcode"
  },
  "geometry": {"coordinates":[0.870944,52.708182],"type":"Point"}
}
