{
  "type": "Feature",
  "properties": {
    "iso:country": "GB",
    "wof:name": "NR19 2RW",
    "wof:placetype": "postalcode"
  },
  "geometry": {"coordinates":[0.870944,52.708182],"type":"Point"}
}
