{
  "type": "Feature",
  "properties": {
    "iso:country": "GB",
    "wof:name": "DN12 3AJ",
    "wof:placetype": "postalcode"
  },
  "geometry": {"coordinates":[-1.220798,53.482667],"type":"Point"}
}
