{
  "type": "Feature",
  "properties": {
    "date:inception_lower": "2003-01-01",
    "date:inception_upper": "2003-01-01",
    "iso:country": "GB",
    "wof:name": "NR27 9EN",
    "wof:placetype": "postalcode"
  },
  "geometry": {"coordinates":[1.285445,52.925017],"type":"Point"}
}
