{
  "type": "Feature",
  "properties": {
    "iso:country":"GB",
    "wof:name":"SP8 4HS",
    "wof:placetype":"postalcode"
},
  "geometry": {"coordinates":[-2.27941905712301,51.04467238760427],"type":"Point"}
}