{
  "type": "Feature",
  "properties": {
    "iso:country":"GB",
    "wof:name":"LN11 9UG",
    "wof:placetype":"postalcode"
},
  "geometry": {"coordinates":[-0.1142951902776,53.29013531744659],"type":"Point"}
}