{
  "type": "Feature",
  "properties": {
    "date:inception_lower": "1980-01-01",
    "date:inception_upper": "1980-01-01",
    "iso:country": "GB",
    "wof:name": "LN11 9UG",
    "wof:placetype": "postalcode"
  },
  "geometry": {"coordinates":[-0.114295,53.29016],"type":"Point"}
}
