{
  "type": "Feature",
  "properties": {
    "date:inception_lower": "1980-01-01",
    "date:inception_upper": "1980-01-01",
    "iso:country": "GB",
    "wof:name": "NR30 2JG",
    "wof:placetype": "postalcode"
  },
  "geometry": {"coordinates":[1.734025,52.605772],"type":"Point"}
}
