{
  "type": "Feature",
  "properties": {
    "iso:country":"GB",
    "wof:name":"WV13 2DL",
    "wof:placetype":"postalcode"
},
  "geometry": {"coordinates":[-2.05825051850064,52.58102102256688],"type":"Point"}
}