{
  "type": "Feature",
  "properties": {
    "iso:country": "GB",
    "wof:name": "CO3 8DF",
    "wof:placetype": "postalcode"
  },
  "geometry": {"coordinates":[0.828841,51.882579],"type":"Point"}
}
