{
  "type": "Feature",
  "properties": {
    "iso:country": "GB",
    "wof:name": "HD9 2SJ",
    "wof:placetype": "postalcode"
  },
  "geometry": {"coordinates":[-1.781138,53.563061],"type":"Point"}
}
