{
  "type": "Feature",
  "properties": {
    "iso:country":"GB",
    "wof:name":"W6 7AS",
    "wof:placetype":"postalcode"
},
  "geometry": {"coordinates":[-0.22372839035603,51.49433246287772],"type":"Point"}
}