{
  "type": "Feature",
  "properties": {
    "date:inception_lower": "2016-05-01",
    "date:inception_upper": "2016-05-01",
    "iso:country": "GB",
    "wof:name": "CH2 3JN",
    "wof:placetype": "postalcode"
  },
  "geometry": {"coordinates":[-2.872723,53.200394],"type":"Point"}
}
