{
  "type": "Feature",
  "properties": {
    "iso:country": "GB",
    "wof:name": "BB9 0SB",
    "wof:placetype": "postalcode"
  },
  "geometry": {"coordinates":[-2.208747,53.829243],"type":"Point"}
}
