{
  "type": "Feature",
  "properties": {
    "iso:country":"GB",
    "wof:name":"BB9 0SB",
    "wof:placetype":"postalcode"
},
  "geometry": {"coordinates":[-2.20874659147481,53.82924335369174],"type":"Point"}
}