{
  "type": "Feature",
  "properties": {
    "date:inception_lower": "1992-08-01",
    "date:inception_upper": "1992-08-01",
    "iso:country": "GB",
    "wof:name": "DE23 6PR",
    "wof:placetype": "postalcode"
  },
  "geometry": {"coordinates":[-1.490912,52.906411],"type":"Point"}
}
