{
  "type": "Feature",
  "properties": {
    "iso:country":"GB",
    "wof:name":"BS5 9NJ",
    "wof:placetype":"postalcode"
},
  "geometry": {"coordinates":[-2.55940699725663,51.45687373332132],"type":"Point"}
}