{
  "type": "Feature",
  "properties": {
    "date:inception_lower":"1980-01-01",
    "date:inception_upper":"1980-01-31",
    "iso:country":"GB",
    "wof:name":"PE36 6AZ",
    "wof:placetype":"postalcode"
},
  "geometry": {"coordinates":[0.491726,52.943407],"type":"Point"}
}