{
  "type": "Feature",
  "properties": {
    "iso:country":"GB",
    "wof:name":"PE36 6AZ",
    "wof:placetype":"postalcode"
},
  "geometry": {"coordinates":[0.4917262322001,52.94340725144983],"type":"Point"}
}