{
  "type": "Feature",
  "properties": {
    "iso:country": "GB",
    "wof:name": "TN17 4BA",
    "wof:placetype": "postalcode"
  },
  "geometry": {"coordinates":[0.546377,51.051179],"type":"Point"}
}
