{
  "type": "Feature",
  "properties": {
    "date:inception_lower": "1980-01-01",
    "date:inception_upper": "1980-01-01",
    "iso:country": "GB",
    "wof:name": "G44 5BB",
    "wof:placetype": "postalcode"
  },
  "geometry": {"coordinates":[-4.247924,55.814878],"type":"Point"}
}
