{
  "type": "Feature",
  "properties": {
    "date:inception_lower": "1980-01-01",
    "date:inception_upper": "1980-01-01",
    "iso:country": "GB",
    "wof:name": "RH18 5LL",
    "wof:placetype": "postalcode"
  },
  "geometry": {"coordinates":[0.034257,51.088063],"type":"Point"}
}
