{
  "type": "Feature",
  "properties": {
    "iso:country": "GB",
    "wof:name": "SO18 5BU",
    "wof:placetype": "postalcode"
  },
  "geometry": {"coordinates":[-1.348418,50.917317],"type":"Point"}
}
