{
  "type": "Feature",
  "properties": {
    "iso:country":"GB",
    "wof:name":"NP19 8DN",
    "wof:placetype":"postalcode"
},
  "geometry": {"coordinates":[-2.9840726829422,51.59209163529035],"type":"Point"}
}