{
  "type": "Feature",
  "properties": {
    "iso:country":"GB",
    "wof:name":"NP19 9LZ",
    "wof:placetype":"postalcode"
},
  "geometry": {"coordinates":[-2.93294339769346,51.59078288456351],"type":"Point"}
}