{
  "type": "Feature",
  "properties": {
    "iso:country": "GB",
    "wof:name": "NP19 9LZ",
    "wof:placetype": "postalcode"
  },
  "geometry": {"coordinates":[-2.932943,51.590783],"type":"Point"}
}
