{
  "type": "Feature",
  "properties": {
    "iso:country": "GB",
    "wof:name": "NG23 7RN",
    "wof:placetype": "postalcode"
  },
  "geometry": {"coordinates":[-0.769803,53.126712],"type":"Point"}
}
