{
  "type": "Feature",
  "properties": {
    "iso:country": "GB",
    "wof:name": "EN5 2NZ",
    "wof:placetype": "postalcode"
  },
  "geometry": {"coordinates":[-0.206281,51.642863],"type":"Point"}
}
