{
  "type": "Feature",
  "properties": {
    "iso:country": "GB",
    "wof:name": "PR8 3DY",
    "wof:placetype": "postalcode"
  },
  "geometry": {"coordinates":[-3.018392,53.60997],"type":"Point"}
}
