{
  "type": "Feature",
  "properties": {
    "date:inception_lower": "2003-03-01",
    "date:inception_upper": "2003-03-01",
    "iso:country": "GB",
    "wof:name": "SA10 9DF",
    "wof:placetype": "postalcode"
  },
  "geometry": {"coordinates":[-3.710841,51.76607],"type":"Point"}
}
