{
  "type": "Feature",
  "properties": {
    "iso:country":"GB",
    "wof:name":"SA10 9DF",
    "wof:placetype":"postalcode"
},
  "geometry": {"coordinates":[-3.71084062870076,51.76606998001242],"type":"Point"}
}