{
  "type": "Feature",
  "properties": {
    "iso:country":"GB",
    "wof:name":"NE49 0DY",
    "wof:placetype":"postalcode"
},
  "geometry": {"coordinates":[-2.45300462668085,54.97189527497147],"type":"Point"}
}