{
  "type": "Feature",
  "properties": {
    "date:inception_lower": "1999-06-01",
    "date:inception_upper": "1999-06-01",
    "iso:country": "GB",
    "wof:name": "CH63 9HU",
    "wof:placetype": "postalcode"
  },
  "geometry": {"coordinates":[-3.010416,53.339446],"type":"Point"}
}
