{
  "type": "Feature",
  "properties": {
    "iso:country":"GB",
    "wof:name":"CH63 9HU",
    "wof:placetype":"postalcode"
},
  "geometry": {"coordinates":[-3.01041616845628,53.33944615153123],"type":"Point"}
}