{
  "type": "Feature",
  "properties": {
    "iso:country": "GB",
    "wof:name": "DY1 3BZ",
    "wof:placetype": "postalcode"
  },
  "geometry": {"coordinates":[-2.106632,52.522517],"type":"Point"}
}
