{
  "type": "Feature",
  "properties": {
    "iso:country":"GB",
    "wof:name":"DY1 3BZ",
    "wof:placetype":"postalcode"
},
  "geometry": {"coordinates":[-2.1066323297393,52.52251723676081],"type":"Point"}
}