{
  "type": "Feature",
  "properties": {
    "iso:country":"GB",
    "wof:name":"RG45 6PE",
    "wof:placetype":"postalcode"
},
  "geometry": {"coordinates":[-0.79956913546417,51.37149827277798],"type":"Point"}
}