{
  "type": "Feature",
  "properties": {
    "iso:country": "GB",
    "wof:name": "RG45 6PE",
    "wof:placetype": "postalcode"
  },
  "geometry": {"coordinates":[-0.799569,51.371498],"type":"Point"}
}
