{
  "type": "Feature",
  "properties": {
    "date:inception_lower":"1995-07-01",
    "date:inception_upper":"1995-07-31",
    "iso:country":"GB",
    "wof:name":"RG45 6PE",
    "wof:placetype":"postalcode"
},
  "geometry": {"coordinates":[-0.799569,51.371498],"type":"Point"}
}