{
  "type": "Feature",
  "properties": {
    "date:inception_lower": "1991-09-01",
    "date:inception_upper": "1991-09-01",
    "iso:country": "GB",
    "wof:name": "GU20 6QH",
    "wof:placetype": "postalcode"
  },
  "geometry": {"coordinates":[-0.658409,51.364914],"type":"Point"}
}
