{
  "type": "Feature",
  "properties": {
    "iso:country":"GB",
    "wof:name":"AB11 6XA",
    "wof:placetype":"postalcode"
},
  "geometry": {"coordinates":[-2.10895460666164,57.14067581763274],"type":"Point"}
}