{
  "type": "Feature",
  "properties": {
    "iso:country":"GB",
    "wof:name":"OX29 6QA",
    "wof:placetype":"postalcode"
},
  "geometry": {"coordinates":[-1.42702786907632,51.8316509380809],"type":"Point"}
}