{
  "type": "Feature",
  "properties": {
    "iso:country":"GB",
    "wof:name":"S10 3TH",
    "wof:placetype":"postalcode"
},
  "geometry": {"coordinates":[-1.53742079830775,53.36448434271542],"type":"Point"}
}