{
  "type": "Feature",
  "properties": {
    "iso:country": "GB",
    "wof:name": "PH19 1AA",
    "wof:placetype": "postalcode"
  },
  "geometry": {"coordinates":[-4.239359,56.94009],"type":"Point"}
}
