{
  "type": "Feature",
  "properties": {
    "date:inception_lower":"1980-01-01",
    "date:inception_upper":"1980-01-31",
    "iso:country":"GB",
    "wof:name":"PH19 1AA",
    "wof:placetype":"postalcode"
},
  "geometry": {"coordinates":[-4.239359,56.94009],"type":"Point"}
}