{
  "type": "Feature",
  "properties": {
    "iso:country":"GB",
    "wof:name":"PH19 1AA",
    "wof:placetype":"postalcode"
},
  "geometry": {"coordinates":[-4.23935953002349,56.94008956377996],"type":"Point"}
}