{
  "type": "Feature",
  "properties": {
    "iso:country":"GB",
    "wof:name":"EH33 2NF",
    "wof:placetype":"postalcode"
},
  "geometry": {"coordinates":[-2.9482090258903,55.93188353624484],"type":"Point"}
}