{
  "type": "Feature",
  "properties": {
    "iso:country": "GB",
    "wof:name": "EH33 2NF",
    "wof:placetype": "postalcode"
  },
  "geometry": {"coordinates":[-2.948209,55.931884],"type":"Point"}
}
