{
  "type": "Feature",
  "properties": {
    "iso:country":"GB",
    "wof:name":"NE25 9SF",
    "wof:placetype":"postalcode"
},
  "geometry": {"coordinates":[-1.478074154023,55.03821842581817],"type":"Point"}
}