{
  "type": "Feature",
  "properties": {
    "date:inception_lower": "1980-01-01",
    "date:inception_upper": "1980-01-01",
    "iso:country": "GB",
    "wof:name": "PE20 3BZ",
    "wof:placetype": "postalcode"
  },
  "geometry": {"coordinates":[-0.183372,52.92463],"type":"Point"}
}
