{
  "type": "Feature",
  "properties": {
    "iso:country":"GB",
    "wof:name":"PE20 3BZ",
    "wof:placetype":"postalcode"
},
  "geometry": {"coordinates":[-0.18337238387893,52.92462981325122],"type":"Point"}
}