{
  "type": "Feature",
  "properties": {
    "iso:country":"GB",
    "wof:name":"PL3 4FA",
    "wof:placetype":"postalcode"
},
  "geometry": {"coordinates":[-4.13701997827021,50.38691795253663],"type":"Point"}
}