{
  "type": "Feature",
  "properties": {
    "date:inception_lower": "2011-10-01",
    "date:inception_upper": "2011-10-01",
    "iso:country": "GB",
    "wof:name": "PL3 4FA",
    "wof:placetype": "postalcode"
  },
  "geometry": {"coordinates":[-4.13713,50.386831],"type":"Point"}
}
