{
  "type": "Feature",
  "properties": {
    "iso:country":"GB",
    "wof:name":"HU8 9EX",
    "wof:placetype":"postalcode"
},
  "geometry": {"coordinates":[-0.27981167019019,53.77704794386678],"type":"Point"}
}