{
  "type": "Feature",
  "properties": {
    "iso:country": "GB",
    "wof:name": "HU8 9EX",
    "wof:placetype": "postalcode"
  },
  "geometry": {"coordinates":[-0.279839,53.776934],"type":"Point"}
}
