{
  "type": "Feature",
  "properties": {
    "date:inception_lower":"1993-01-01",
    "date:inception_upper":"1993-01-31",
    "iso:country":"GB",
    "wof:name":"CF64 3NE",
    "wof:placetype":"postalcode"
},
  "geometry": {"coordinates":[-3.188876,51.433881],"type":"Point"}
}