{
  "type": "Feature",
  "properties": {
    "iso:country": "GB",
    "wof:name": "CF64 3NE",
    "wof:placetype": "postalcode"
  },
  "geometry": {"coordinates":[-3.188876,51.433881],"type":"Point"}
}
