{
  "type": "Feature",
  "properties": {
    "iso:country":"GB",
    "wof:name":"CF64 3NE",
    "wof:placetype":"postalcode"
},
  "geometry": {"coordinates":[-3.18887596875968,51.43388056960417],"type":"Point"}
}