{
  "type": "Feature",
  "properties": {
    "iso:country":"GB",
    "wof:name":"PL6 7AH",
    "wof:placetype":"postalcode"
},
  "geometry": {"coordinates":[-4.08512900102325,50.4415379221752],"type":"Point"}
}