{
  "type": "Feature",
  "properties": {
    "iso:country": "GB",
    "wof:name": "SY16 3JZ",
    "wof:placetype": "postalcode"
  },
  "geometry": {"coordinates":[-3.314815,52.529743],"type":"Point"}
}
