{
  "type": "Feature",
  "properties": {
    "iso:country":"GB",
    "wof:name":"DY2 0HA",
    "wof:placetype":"postalcode"
},
  "geometry": {"coordinates":[-2.09323976799648,52.48300885900561],"type":"Point"}
}