{
  "type": "Feature",
  "properties": {
    "iso:country": "GB",
    "wof:name": "LE5 0PJ",
    "wof:placetype": "postalcode"
  },
  "geometry": {"coordinates":[-1.094225,52.643947],"type":"Point"}
}
