{
  "type": "Feature",
  "properties": {
    "iso:country":"GB",
    "wof:name":"LE5 0PJ",
    "wof:placetype":"postalcode"
},
  "geometry": {"coordinates":[-1.09422510992558,52.64394708799065],"type":"Point"}
}