{
  "type": "Feature",
  "properties": {
    "date:inception_lower": "1980-01-01",
    "date:inception_upper": "1980-01-01",
    "iso:country": "GB",
    "wof:name": "LN11 8JD",
    "wof:placetype": "postalcode"
  },
  "geometry": {"coordinates":[0.076059,53.331637],"type":"Point"}
}
