{
  "type": "Feature",
  "properties": {
    "iso:country": "GB",
    "wof:name": "LN11 8JD",
    "wof:placetype": "postalcode"
  },
  "geometry": {"coordinates":[0.076059,53.331637],"type":"Point"}
}
