{
  "type": "Feature",
  "properties": {
    "iso:country":"GB",
    "wof:name":"TS10 5LR",
    "wof:placetype":"postalcode"
},
  "geometry": {"coordinates":[-1.09959421750872,54.60564850891838],"type":"Point"}
}