{
  "type": "Feature",
  "properties": {
    "iso:country": "GB",
    "wof:name": "ME2 2FY",
    "wof:placetype": "postalcode"
  },
  "geometry": {"coordinates":[0.472509,51.38395],"type":"Point"}
}
