{
  "type": "Feature",
  "properties": {
    "iso:country":"GB",
    "wof:name":"ME2 2FY",
    "wof:placetype":"postalcode"
},
  "geometry": {"coordinates":[0.47250872245876,51.38394997574273],"type":"Point"}
}