{
  "type": "Feature",
  "properties": {
    "date:inception_lower":"2011-01-01",
    "date:inception_upper":"2011-01-31",
    "iso:country":"GB",
    "wof:name":"ME2 2FY",
    "wof:placetype":"postalcode"
},
  "geometry": {"coordinates":[0.472509,51.38395],"type":"Point"}
}