{
  "type": "Feature",
  "properties": {
    "iso:country":"GB",
    "wof:name":"BR5 1NH",
    "wof:placetype":"postalcode"
},
  "geometry": {"coordinates":[0.07271072763764,51.39461073633476],"type":"Point"}
}