{
  "type": "Feature",
  "properties": {
    "iso:country":"GB",
    "wof:name":"BN14 7LP",
    "wof:placetype":"postalcode"
},
  "geometry": {"coordinates":[-0.39003944165361,50.82020916851284],"type":"Point"}
}