{
  "type": "Feature",
  "properties": {
    "iso:country": "GB",
    "wof:name": "WA4 2AZ",
    "wof:placetype": "postalcode"
  },
  "geometry": {"coordinates":[-2.579192,53.369196],"type":"Point"}
}
