{
  "type": "Feature",
  "properties": {
    "iso:country":"GB",
    "wof:name":"WA4 2AZ",
    "wof:placetype":"postalcode"
},
  "geometry": {"coordinates":[-2.57919242591841,53.36919563098029],"type":"Point"}
}