{
  "type": "Feature",
  "properties": {
    "iso:country":"GB",
    "wof:name":"BL1 2RY",
    "wof:placetype":"postalcode"
},
  "geometry": {"coordinates":[-2.42433843784336,53.58407008509311],"type":"Point"}
}