{
  "type": "Feature",
  "properties": {
    "iso:country": "GB",
    "wof:name": "BL1 2RY",
    "wof:placetype": "postalcode"
  },
  "geometry": {"coordinates":[-2.424338,53.58407],"type":"Point"}
}
