{
  "type": "Feature",
  "properties": {
    "iso:country":"GB",
    "wof:name":"SY7 0HX",
    "wof:placetype":"postalcode"
},
  "geometry": {"coordinates":[-2.97859381909727,52.42902822503525],"type":"Point"}
}