{
  "type": "Feature",
  "properties": {
    "iso:country": "GB",
    "wof:name": "L13 5SD",
    "wof:placetype": "postalcode"
  },
  "geometry": {"coordinates":[-2.911693,53.412503],"type":"Point"}
}
