{
  "type": "Feature",
  "properties": {
    "iso:country":"GB",
    "wof:name":"L13 5SD",
    "wof:placetype":"postalcode"
},
  "geometry": {"coordinates":[-2.9116934396736,53.41250340322693],"type":"Point"}
}