{
  "type": "Feature",
  "properties": {
    "date:inception_lower": "2016-11-01",
    "date:inception_upper": "2016-11-01",
    "iso:country": "GB",
    "wof:name": "CF72 9ZJ",
    "wof:placetype": "postalcode"
  },
  "geometry": {"coordinates":[-3.397388,51.536618],"type":"Point"}
}
