{
  "type": "Feature",
  "properties": {
    "iso:country":"GB",
    "wof:name":"CR2 8LA",
    "wof:placetype":"postalcode"
},
  "geometry": {"coordinates":[-0.06247767501359,51.34239191921341],"type":"Point"}
}