{
  "type": "Feature",
  "properties": {
    "iso:country": "GB",
    "wof:name": "CH66 2PD",
    "wof:placetype": "postalcode"
  },
  "geometry": {"coordinates":[-2.912301,53.258014],"type":"Point"}
}
