{
  "type": "Feature",
  "properties": {
    "date:inception_lower": "1980-01-01",
    "date:inception_upper": "1980-01-01",
    "iso:country": "GB",
    "wof:name": "SL5 8PD",
    "wof:placetype": "postalcode"
  },
  "geometry": {"coordinates":[-0.687476,51.421309],"type":"Point"}
}
