{
  "type": "Feature",
  "properties": {
    "iso:country":"GB",
    "wof:name":"SL5 8PD",
    "wof:placetype":"postalcode"
},
  "geometry": {"coordinates":[-0.68703765496214,51.42115103986848],"type":"Point"}
}