{
  "type": "Feature",
  "properties": {
    "iso:country": "GB",
    "wof:name": "SL5 8PD",
    "wof:placetype": "postalcode"
  },
  "geometry": {"coordinates":[-0.687038,51.421151],"type":"Point"}
}
