{
  "type": "Feature",
  "properties": {
    "date:inception_lower": "2005-01-01",
    "date:inception_upper": "2005-01-01",
    "iso:country": "GB",
    "wof:name": "RH16 4TR",
    "wof:placetype": "postalcode"
  },
  "geometry": {"coordinates":[-0.114957,50.986698],"type":"Point"}
}
