{
  "type": "Feature",
  "properties": {
    "date:inception_lower":"2005-01-01",
    "date:inception_upper":"2005-01-31",
    "iso:country":"GB",
    "wof:name":"RH16 4TR",
    "wof:placetype":"postalcode"
},
  "geometry": {"coordinates":[-0.114956,50.986675],"type":"Point"}
}