{
  "type": "Feature",
  "properties": {
    "iso:country":"GB",
    "wof:name":"N16 0QL",
    "wof:placetype":"postalcode"
},
  "geometry": {"coordinates":[-0.08406945636102,51.56523435430687],"type":"Point"}
}