{
  "type": "Feature",
  "properties": {
    "iso:country": "GB",
    "wof:name": "DE13 8RL",
    "wof:placetype": "postalcode"
  },
  "geometry": {"coordinates":[-1.769751,52.800034],"type":"Point"}
}
