{
  "type": "Feature",
  "properties": {
    "date:inception_lower":"1980-01-01",
    "date:inception_upper":"1980-01-31",
    "iso:country":"GB",
    "wof:name":"DE13 8RL",
    "wof:placetype":"postalcode"
},
  "geometry": {"coordinates":[-1.769751,52.800034],"type":"Point"}
}