{
  "type": "Feature",
  "properties": {
    "iso:country":"GB",
    "wof:name":"DE13 8RL",
    "wof:placetype":"postalcode"
},
  "geometry": {"coordinates":[-1.76975094671486,52.80003390478574],"type":"Point"}
}