{
  "type": "Feature",
  "properties": {
    "iso:country":"GB",
    "wof:name":"PA1 1LP",
    "wof:placetype":"postalcode"
},
  "geometry": {"coordinates":[-4.41315023643967,55.84429987551422],"type":"Point"}
}