{
  "type": "Feature",
  "properties": {
    "date:inception_lower": "2014-11-01",
    "date:inception_upper": "2014-11-01",
    "iso:country": "GB",
    "wof:name": "BS14 9QX",
    "wof:placetype": "postalcode"
  },
  "geometry": {"coordinates":[-2.560551,51.41278],"type":"Point"}
}
