{
  "type": "Feature",
  "properties": {
    "iso:country": "GB",
    "wof:name": "BS14 9QX",
    "wof:placetype": "postalcode"
  },
  "geometry": {"coordinates":[-2.560594,51.412755],"type":"Point"}
}
