{
  "type": "Feature",
  "properties": {
    "iso:country": "GB",
    "wof:name": "DN35 9LT",
    "wof:placetype": "postalcode"
  },
  "geometry": {"coordinates":[-0.050793,53.552504],"type":"Point"}
}
