{
  "type": "Feature",
  "properties": {
    "iso:country":"GB",
    "wof:name":"GL2 5LW",
    "wof:placetype":"postalcode"
},
  "geometry": {"coordinates":[-2.27220892295632,51.85108013532591],"type":"Point"}
}