{
  "type": "Feature",
  "properties": {
    "iso:country":"GB",
    "wof:name":"IG6 1LB",
    "wof:placetype":"postalcode"
},
  "geometry": {"coordinates":[0.07220015109875,51.58568069587554],"type":"Point"}
}