{
  "type": "Feature",
  "properties": {
    "iso:country": "GB",
    "wof:name": "PR25 4NX",
    "wof:placetype": "postalcode"
  },
  "geometry": {"coordinates":[-2.685401,53.699672],"type":"Point"}
}
