{
  "type": "Feature",
  "properties": {
    "iso:country":"GB",
    "wof:name":"PR25 4NX",
    "wof:placetype":"postalcode"
},
  "geometry": {"coordinates":[-2.68540140233778,53.69967183601815],"type":"Point"}
}