{
  "type": "Feature",
  "properties": {
    "date:inception_lower": "1980-01-01",
    "date:inception_upper": "1980-01-01",
    "iso:country": "GB",
    "wof:name": "NP7 5PY",
    "wof:placetype": "postalcode"
  },
  "geometry": {"coordinates":[-3.012778,51.825644],"type":"Point"}
}
