{
  "type": "Feature",
  "properties": {
    "date:inception_lower": "2014-10-01",
    "date:inception_upper": "2014-10-01",
    "iso:country": "GB",
    "wof:name": "NG7 4FW",
    "wof:placetype": "postalcode"
  },
  "geometry": {"coordinates":[-1.160011,52.959557],"type":"Point"}
}
