{
  "type": "Feature",
  "properties": {
    "iso:country": "GB",
    "wof:name": "SN7 8FL",
    "wof:placetype": "postalcode"
  },
  "geometry": {"coordinates":[-1.503876,51.645634],"type":"Point"}
}
