{
  "type": "Feature",
  "properties": {
    "iso:country":"GB",
    "wof:name":"B62 9BN",
    "wof:placetype":"postalcode"
},
  "geometry": {"coordinates":[-2.01592497415897,52.46123503069852],"type":"Point"}
}