{
  "type": "Feature",
  "properties": {
    "iso:country": "GB",
    "wof:name": "E12 5AD",
    "wof:placetype": "postalcode"
  },
  "geometry": {"coordinates":[0.045407,51.55002],"type":"Point"}
}
