{
  "type": "Feature",
  "properties": {
    "iso:country": "GB",
    "wof:name": "AB52 6NE",
    "wof:placetype": "postalcode"
  },
  "geometry": {"coordinates":[-2.678142,57.373244],"type":"Point"}
}
