{
  "type": "Feature",
  "properties": {
    "date:inception_lower": "1984-10-01",
    "date:inception_upper": "1984-10-01",
    "iso:country": "GB",
    "wof:name": "NR33 8DQ",
    "wof:placetype": "postalcode"
  },
  "geometry": {"coordinates":[1.703245,52.456167],"type":"Point"}
}
