{
  "type": "Feature",
  "properties": {
    "iso:country": "GB",
    "wof:name": "BB2 4GX",
    "wof:placetype": "postalcode"
  },
  "geometry": {"coordinates":[-2.495793,53.732884],"type":"Point"}
}
