{
  "type": "Feature",
  "properties": {
    "date:inception_lower":"2007-09-01",
    "date:inception_upper":"2007-09-30",
    "iso:country":"GB",
    "wof:name":"BB2 4GX",
    "wof:placetype":"postalcode"
},
  "geometry": {"coordinates":[-2.495793,53.732884],"type":"Point"}
}