{
  "type": "Feature",
  "properties": {
    "iso:country":"GB",
    "wof:name":"DN12 2AE",
    "wof:placetype":"postalcode"
},
  "geometry": {"coordinates":[-1.21511468912784,53.48115594534901],"type":"Point"}
}