{
  "type": "Feature",
  "properties": {
    "date:inception_lower": "1980-01-01",
    "date:inception_upper": "1980-01-01",
    "iso:country": "GB",
    "wof:name": "DN12 2AE",
    "wof:placetype": "postalcode"
  },
  "geometry": {"coordinates":[-1.215115,53.481156],"type":"Point"}
}
