{
  "type": "Feature",
  "properties": {
    "iso:country": "GB",
    "wof:name": "RM11 1FQ",
    "wof:placetype": "postalcode"
  },
  "geometry": {"coordinates":[0.203178,51.564016],"type":"Point"}
}
