{
  "type": "Feature",
  "properties": {
    "date:inception_lower": "1980-01-01",
    "date:inception_upper": "1980-01-01",
    "iso:country": "GB",
    "wof:name": "NR12 9RR",
    "wof:placetype": "postalcode"
  },
  "geometry": {"coordinates":[1.527355,52.762992],"type":"Point"}
}
