{
  "type": "Feature",
  "properties": {
    "iso:country": "GB",
    "wof:name": "NR12 9RR",
    "wof:placetype": "postalcode"
  },
  "geometry": {"coordinates":[1.52733,52.762929],"type":"Point"}
}
