{
  "type": "Feature",
  "properties": {
    "iso:country":"GB",
    "wof:name":"NR12 9RR",
    "wof:placetype":"postalcode"
},
  "geometry": {"coordinates":[1.52732988664895,52.76292863235267],"type":"Point"}
}