{
  "type": "Feature",
  "properties": {
    "iso:country":"GB",
    "wof:name":"WA5 4BE",
    "wof:placetype":"postalcode"
},
  "geometry": {"coordinates":[-2.64670199079174,53.43553613789243],"type":"Point"}
}