{
  "type": "Feature",
  "properties": {
    "date:inception_lower": "1980-01-01",
    "date:inception_upper": "1980-01-01",
    "iso:country": "GB",
    "wof:name": "WA5 4BE",
    "wof:placetype": "postalcode"
  },
  "geometry": {"coordinates":[-2.646449,53.439742],"type":"Point"}
}
