{
  "type": "Feature",
  "properties": {
    "iso:country": "GB",
    "wof:name": "UB10 0YF",
    "wof:placetype": "postalcode"
  },
  "geometry": {"coordinates":[-0.469435,51.544378],"type":"Point"}
}
