{
  "type": "Feature",
  "properties": {
    "iso:country": "GB",
    "wof:name": "GL3 4QJ",
    "wof:placetype": "postalcode"
  },
  "geometry": {"coordinates":[-2.155808,51.848127],"type":"Point"}
}
