{
  "type": "Feature",
  "properties": {
    "iso:country":"GB",
    "wof:name":"OX28 5YA",
    "wof:placetype":"postalcode"
},
  "geometry": {"coordinates":[-1.49667273967638,51.78583624492885],"type":"Point"}
}