{
  "type": "Feature",
  "properties": {
    "date:inception_lower": "2023-06-01",
    "date:inception_upper": "2023-06-01",
    "iso:country": "GB",
    "wof:name": "EX39 1ZL",
    "wof:placetype": "postalcode"
  },
  "geometry": {"coordinates":[-4.210977,51.045457],"type":"Point"}
}
