{
  "type": "Feature",
  "properties": {
    "iso:country":"GB",
    "wof:name":"SW1X 0HT",
    "wof:placetype":"postalcode"
},
  "geometry": {"coordinates":[-0.15996293178596,51.49623589783316],"type":"Point"}
}