{
  "type": "Feature",
  "properties": {
    "iso:country":"GB",
    "wof:name":"PR3 8AH",
    "wof:placetype":"postalcode"
},
  "geometry": {"coordinates":[-2.59798572399901,53.83382999196757],"type":"Point"}
}