{
  "type": "Feature",
  "properties": {
    "iso:country":"GB",
    "wof:name":"SK14 4BL",
    "wof:placetype":"postalcode"
},
  "geometry": {"coordinates":[-2.0770492981565,53.46337458185621],"type":"Point"}
}