{
  "type": "Feature",
  "properties": {
    "iso:country":"GB",
    "wof:name":"ME4 6JE",
    "wof:placetype":"postalcode"
},
  "geometry": {"coordinates":[0.51872907525571,51.36349408614436],"type":"Point"}
}