{
  "type": "Feature",
  "properties": {
    "iso:country": "GB",
    "wof:name": "CW11 2LG",
    "wof:placetype": "postalcode"
  },
  "geometry": {"coordinates":[-2.34209,53.145247],"type":"Point"}
}
