{
  "type": "Feature",
  "properties": {
    "iso:country":"GB",
    "wof:name":"BA21 4NB",
    "wof:placetype":"postalcode"
},
  "geometry": {"coordinates":[-2.62770012221051,50.95579749739466],"type":"Point"}
}