{
  "type": "Feature",
  "properties": {
    "iso:country":"GB",
    "wof:name":"EX7 9NE",
    "wof:placetype":"postalcode"
},
  "geometry": {"coordinates":[-3.47452058299287,50.58333789381675],"type":"Point"}
}