{
  "type": "Feature",
  "properties": {
    "iso:country":"GB",
    "wof:name":"GU30 7BZ",
    "wof:placetype":"postalcode"
},
  "geometry": {"coordinates":[-0.78939794117595,51.07776742250916],"type":"Point"}
}