{
  "type": "Feature",
  "properties": {
    "iso:country": "GB",
    "wof:name": "GU30 7BZ",
    "wof:placetype": "postalcode"
  },
  "geometry": {"coordinates":[-0.789398,51.077767],"type":"Point"}
}
