{
  "type": "Feature",
  "properties": {
    "date:inception_lower": "2004-01-01",
    "date:inception_upper": "2004-01-01",
    "iso:country": "GB",
    "wof:name": "FK19 8YF",
    "wof:placetype": "postalcode"
  },
  "geometry": {"coordinates":[-4.28792,56.385225],"type":"Point"}
}
