{
  "type": "Feature",
  "properties": {
    "iso:country":"GB",
    "wof:name":"DT6 3RJ",
    "wof:placetype":"postalcode"
},
  "geometry": {"coordinates":[-2.75882051797799,50.73219032295558],"type":"Point"}
}