{
  "type": "Feature",
  "properties": {
    "date:inception_lower": "1980-01-01",
    "date:inception_upper": "1980-01-01",
    "iso:country": "GB",
    "wof:name": "DT6 3RJ",
    "wof:placetype": "postalcode"
  },
  "geometry": {"coordinates":[-2.758764,50.73218],"type":"Point"}
}
