{
  "type": "Feature",
  "properties": {
    "iso:country":"GB",
    "wof:name":"TN1 1QQ",
    "wof:placetype":"postalcode"
},
  "geometry": {"coordinates":[0.26394850648051,51.13041704777789],"type":"Point"}
}