{
  "type": "Feature",
  "properties": {
    "iso:country":"GB",
    "wof:name":"ST14 8UR",
    "wof:placetype":"postalcode"
},
  "geometry": {"coordinates":[-1.87014608411236,52.89062840390251],"type":"Point"}
}