{
  "type": "Feature",
  "properties": {
    "iso:country":"GB",
    "wof:name":"BL1 5PL",
    "wof:placetype":"postalcode"
},
  "geometry": {"coordinates":[-2.4728509472952,53.589011461083],"type":"Point"}
}