{
  "type": "Feature",
  "properties": {
    "date:inception_lower": "2022-03-01",
    "date:inception_upper": "2022-03-01",
    "iso:country": "GB",
    "wof:name": "IP32 6FU",
    "wof:placetype": "postalcode"
  },
  "geometry": {"coordinates":[0.69318,52.267198],"type":"Point"}
}
