{
  "type": "Feature",
  "properties": {
    "iso:country":"GB",
    "wof:name":"B69 4LA",
    "wof:placetype":"postalcode"
},
  "geometry": {"coordinates":[-2.01135774252139,52.49926308776045],"type":"Point"}
}