{
  "type": "Feature",
  "properties": {
    "date:inception_lower":"2000-12-01",
    "date:inception_upper":"2000-12-31",
    "iso:country":"GB",
    "wof:name":"B69 4LA",
    "wof:placetype":"postalcode"
},
  "geometry": {"coordinates":[-2.010674,52.497382],"type":"Point"}
}