{
  "type": "Feature",
  "properties": {
    "iso:country":"GB",
    "wof:name":"WF2 7LR",
    "wof:placetype":"postalcode"
},
  "geometry": {"coordinates":[-1.48533826302475,53.66064881737009],"type":"Point"}
}