{
  "type": "Feature",
  "properties": {
    "iso:country":"GB",
    "wof:name":"TW13 6QY",
    "wof:placetype":"postalcode"
},
  "geometry": {"coordinates":[-0.3912680756424,51.43413684138701],"type":"Point"}
}