{
  "type": "Feature",
  "properties": {
    "date:inception_lower": "1998-06-01",
    "date:inception_upper": "1998-06-01",
    "iso:country": "GB",
    "wof:name": "TW13 6QY",
    "wof:placetype": "postalcode"
  },
  "geometry": {"coordinates":[-0.391161,51.434127],"type":"Point"}
}
