{
  "type": "Feature",
  "properties": {
    "date:inception_lower": "1992-08-01",
    "date:inception_upper": "1992-08-01",
    "iso:country": "GB",
    "wof:name": "N13 4EZ",
    "wof:placetype": "postalcode"
  },
  "geometry": {"coordinates":[-0.112148,51.615705],"type":"Point"}
}
