{
  "type": "Feature",
  "properties": {
    "iso:country":"GB",
    "wof:name":"G13 1DX",
    "wof:placetype":"postalcode"
},
  "geometry": {"coordinates":[-4.32439320560524,55.89318543418857],"type":"Point"}
}