{
  "type": "Feature",
  "properties": {
    "date:inception_lower": "2015-11-01",
    "date:inception_upper": "2015-11-01",
    "iso:country": "GB",
    "wof:name": "G13 1DX",
    "wof:placetype": "postalcode"
  },
  "geometry": {"coordinates":[-4.324393,55.893185],"type":"Point"}
}
