{
  "type": "Feature",
  "properties": {
    "date:inception_lower": "2023-11-01",
    "date:inception_upper": "2023-11-01",
    "iso:country": "GB",
    "wof:name": "SK7 1LW",
    "wof:placetype": "postalcode"
  },
  "geometry": {"coordinates":[-2.156378,53.335622],"type":"Point"}
}
