{
  "type": "Feature",
  "properties": {
    "iso:country": "GB",
    "wof:name": "OL11 3PW",
    "wof:placetype": "postalcode"
  },
  "geometry": {"coordinates":[-2.166426,53.60512],"type":"Point"}
}
