{
  "type": "Feature",
  "properties": {
    "iso:country":"GB",
    "wof:name":"OL11 3PW",
    "wof:placetype":"postalcode"
},
  "geometry": {"coordinates":[-2.16642653608468,53.60511972696588],"type":"Point"}
}