{
  "type": "Feature",
  "properties": {
    "date:inception_lower": "1980-01-01",
    "date:inception_upper": "1980-01-01",
    "iso:country": "GB",
    "wof:name": "OL11 3PW",
    "wof:placetype": "postalcode"
  },
  "geometry": {"coordinates":[-2.166426,53.60512],"type":"Point"}
}
