{
  "type": "Feature",
  "properties": {
    "iso:country":"GB",
    "wof:name":"UB5 6PN",
    "wof:placetype":"postalcode"
},
  "geometry": {"coordinates":[-0.40940738462108,51.53479196399529],"type":"Point"}
}