{
  "type": "Feature",
  "properties": {
    "iso:country":"GB",
    "wof:name":"WS12 0QA",
    "wof:placetype":"postalcode"
},
  "geometry": {"coordinates":[-1.952927176105,52.70190189256277],"type":"Point"}
}