{
  "type": "Feature",
  "properties": {
    "iso:country":"GB",
    "wof:name":"DE7 8WQ",
    "wof:placetype":"postalcode"
},
  "geometry": {"coordinates":[-1.30520137216998,52.99396186180394],"type":"Point"}
}