{
  "type": "Feature",
  "properties": {
    "iso:country": "GB",
    "wof:name": "DE7 8WQ",
    "wof:placetype": "postalcode"
  },
  "geometry": {"coordinates":[-1.305201,52.993962],"type":"Point"}
}
