{
  "type": "Feature",
  "properties": {
    "iso:country": "GB",
    "wof:name": "KW1 5XR",
    "wof:placetype": "postalcode"
  },
  "geometry": {"coordinates":[-3.425563,58.463892],"type":"Point"}
}
