{
  "type": "Feature",
  "properties": {
    "date:inception_lower": "2017-01-01",
    "date:inception_upper": "2017-01-01",
    "iso:country": "GB",
    "wof:name": "PE2 9QU",
    "wof:placetype": "postalcode"
  },
  "geometry": {"coordinates":[-0.254739,52.561929],"type":"Point"}
}
