{
  "type": "Feature",
  "properties": {
    "iso:country":"GB",
    "wof:name":"NP4 0AF",
    "wof:placetype":"postalcode"
},
  "geometry": {"coordinates":[-2.98596366671367,51.72993376494151],"type":"Point"}
}