{
  "type": "Feature",
  "properties": {
    "date:inception_lower":"2004-09-01",
    "date:inception_upper":"2004-09-30",
    "iso:country":"GB",
    "wof:name":"NP4 0AF",
    "wof:placetype":"postalcode"
},
  "geometry": {"coordinates":[-2.986027,51.729909],"type":"Point"}
}