{
  "type": "Feature",
  "properties": {
    "iso:country": "GB",
    "wof:name": "NP4 0AF",
    "wof:placetype": "postalcode"
  },
  "geometry": {"coordinates":[-2.986027,51.729909],"type":"Point"}
}
