{
  "type": "Feature",
  "properties": {
    "iso:country":"GB",
    "wof:name":"KA11 4EE",
    "wof:placetype":"postalcode"
},
  "geometry": {"coordinates":[-4.60594731471457,55.61220162209261],"type":"Point"}
}