{
  "type": "Feature",
  "properties": {
    "date:inception_lower":"1980-01-01",
    "date:inception_upper":"1980-01-31",
    "iso:country":"GB",
    "wof:name":"KA11 4EE",
    "wof:placetype":"postalcode"
},
  "geometry": {"coordinates":[-4.605947,55.612202],"type":"Point"}
}