{
  "type": "Feature",
  "properties": {
    "date:inception_lower": "2023-04-01",
    "date:inception_upper": "2023-04-01",
    "iso:country": "GB",
    "wof:name": "TF3 4TN",
    "wof:placetype": "postalcode"
  },
  "geometry": {"coordinates":[-2.461061,52.681566],"type":"Point"}
}
