{
  "type": "Feature",
  "properties": {
    "iso:country": "GB",
    "wof:name": "WA4 6HU",
    "wof:placetype": "postalcode"
  },
  "geometry": {"coordinates":[-2.584918,53.370246],"type":"Point"}
}
