{
  "type": "Feature",
  "properties": {
    "date:inception_lower": "1980-01-01",
    "date:inception_upper": "1980-01-01",
    "iso:country": "GB",
    "wof:name": "WA4 6HU",
    "wof:placetype": "postalcode"
  },
  "geometry": {"coordinates":[-2.584918,53.370246],"type":"Point"}
}
