{
  "type": "Feature",
  "properties": {
    "iso:country": "GB",
    "wof:name": "HU9 4AG",
    "wof:placetype": "postalcode"
  },
  "geometry": {"coordinates":[-0.273338,53.770968],"type":"Point"}
}
