{
  "type": "Feature",
  "properties": {
    "iso:country":"GB",
    "wof:name":"BB5 6SQ",
    "wof:placetype":"postalcode"
},
  "geometry": {"coordinates":[-2.3559504823763,53.75371183774573],"type":"Point"}
}