{
  "type": "Feature",
  "properties": {
    "iso:country":"GB",
    "wof:name":"LE17 6QU",
    "wof:placetype":"postalcode"
},
  "geometry": {"coordinates":[-1.02257594250077,52.46857279631028],"type":"Point"}
}