{
  "type": "Feature",
  "properties": {
    "iso:country":"GB",
    "wof:name":"B8 1PP",
    "wof:placetype":"postalcode"
},
  "geometry": {"coordinates":[-1.85330773807294,52.49222384070519],"type":"Point"}
}