{
  "type": "Feature",
  "properties": {
    "date:inception_lower":"1980-01-01",
    "date:inception_upper":"1980-01-31",
    "iso:country":"GB",
    "wof:name":"BR4 0BS",
    "wof:placetype":"postalcode"
},
  "geometry": {"coordinates":[0.001079,51.384705],"type":"Point"}
}