{
  "type": "Feature",
  "properties": {
    "iso:country":"GB",
    "wof:name":"BR4 0BS",
    "wof:placetype":"postalcode"
},
  "geometry": {"coordinates":[0.00107893795304,51.38470490364138],"type":"Point"}
}