{
  "type": "Feature",
  "properties": {
    "iso:country":"GB",
    "wof:name":"WA7 2LT",
    "wof:placetype":"postalcode"
},
  "geometry": {"coordinates":[-2.6902270462196,53.33195758300175],"type":"Point"}
}