{
  "type": "Feature",
  "properties": {
    "date:inception_lower": "1980-01-01",
    "date:inception_upper": "1980-01-01",
    "iso:country": "GB",
    "wof:name": "WA7 2LT",
    "wof:placetype": "postalcode"
  },
  "geometry": {"coordinates":[-2.690227,53.331958],"type":"Point"}
}
