{
  "type": "Feature",
  "properties": {
    "iso:country":"GB",
    "wof:name":"CM21 9HS",
    "wof:placetype":"postalcode"
},
  "geometry": {"coordinates":[0.14431094824907,51.80741097758112],"type":"Point"}
}