{
  "type": "Feature",
  "properties": {
    "iso:country": "GB",
    "wof:name": "CM21 9HS",
    "wof:placetype": "postalcode"
  },
  "geometry": {"coordinates":[0.144311,51.807411],"type":"Point"}
}
