{
  "type": "Feature",
  "properties": {
    "date:inception_lower": "1980-01-01",
    "date:inception_upper": "1980-01-01",
    "iso:country": "GB",
    "wof:name": "CM21 9HS",
    "wof:placetype": "postalcode"
  },
  "geometry": {"coordinates":[0.144311,51.807411],"type":"Point"}
}
