{
  "type": "Feature",
  "properties": {
    "date:inception_lower": "2011-05-01",
    "date:inception_upper": "2011-05-01",
    "iso:country": "GB",
    "wof:name": "FK16 6DT",
    "wof:placetype": "postalcode"
  },
  "geometry": {"coordinates":[-4.052224,56.193303],"type":"Point"}
}
