{
  "type": "Feature",
  "properties": {
    "iso:country": "GB",
    "wof:name": "FK16 6DT",
    "wof:placetype": "postalcode"
  },
  "geometry": {"coordinates":[-4.052224,56.193303],"type":"Point"}
}
