{
  "type": "Feature",
  "properties": {
    "iso:country":"GB",
    "wof:name":"FK16 6DT",
    "wof:placetype":"postalcode"
},
  "geometry": {"coordinates":[-4.05222397705744,56.19330323439274],"type":"Point"}
}