{
  "type": "Feature",
  "properties": {
    "date:inception_lower": "2005-09-01",
    "date:inception_upper": "2005-09-01",
    "iso:country": "GB",
    "wof:name": "DE7 8BL",
    "wof:placetype": "postalcode"
  },
  "geometry": {"coordinates":[-1.309708,52.99628],"type":"Point"}
}
