{
  "type": "Feature",
  "properties": {
    "iso:country":"GB",
    "wof:name":"BN23 6JH",
    "wof:placetype":"postalcode"
},
  "geometry": {"coordinates":[0.323192714028,50.79470271460547],"type":"Point"}
}