{
  "type": "Feature",
  "properties": {
    "date:inception_lower":"2009-03-01",
    "date:inception_upper":"2009-03-31",
    "iso:country":"GB",
    "wof:name":"EC2P 2SA",
    "wof:placetype":"postalcode"
},
  "geometry": {"coordinates":[-0.091457,51.51595],"type":"Point"}
}