{
  "type": "Feature",
  "properties": {
    "iso:country":"GB",
    "wof:name":"EC2P 2SA",
    "wof:placetype":"postalcode"
},
  "geometry": {"coordinates":[-0.0914566927864,51.5159498078809],"type":"Point"}
}