{
  "type": "Feature",
  "properties": {
    "iso:country": "GB",
    "wof:name": "EC2P 2SA",
    "wof:placetype": "postalcode"
  },
  "geometry": {"coordinates":[-0.091457,51.51595],"type":"Point"}
}
