{
  "type": "Feature",
  "properties": {
    "date:inception_lower": "2020-10-01",
    "date:inception_upper": "2020-10-01",
    "iso:country": "GB",
    "wof:name": "CH6 5GF",
    "wof:placetype": "postalcode"
  },
  "geometry": {"coordinates":[-3.122969,53.239943],"type":"Point"}
}
