{
  "type": "Feature",
  "properties": {
    "iso:country":"GB",
    "wof:name":"BS5 6UF",
    "wof:placetype":"postalcode"
},
  "geometry": {"coordinates":[-2.56672173914039,51.47688089660574],"type":"Point"}
}