{
  "type": "Feature",
  "properties": {
    "iso:country": "GB",
    "wof:name": "HX6 1BE",
    "wof:placetype": "postalcode"
  },
  "geometry": {"coordinates":[-1.925385,53.706599],"type":"Point"}
}
