{
  "type": "Feature",
  "properties": {
    "iso:country":"GB",
    "wof:name":"NE47 6HF",
    "wof:placetype":"postalcode"
},
  "geometry": {"coordinates":[-2.24958669360818,54.97506227009807],"type":"Point"}
}