{
  "type": "Feature",
  "properties": {
    "date:inception_lower": "1980-01-01",
    "date:inception_upper": "1980-01-01",
    "iso:country": "GB",
    "wof:name": "NE47 6HF",
    "wof:placetype": "postalcode"
  },
  "geometry": {"coordinates":[-2.249587,54.975062],"type":"Point"}
}
