{
  "type": "Feature",
  "properties": {
    "date:inception_lower":"1994-05-01",
    "date:inception_upper":"1994-05-31",
    "iso:country":"GB",
    "wof:name":"LA9 5QF",
    "wof:placetype":"postalcode"
},
  "geometry": {"coordinates":[-2.755482,54.340256],"type":"Point"}
}