{
  "type": "Feature",
  "properties": {
    "iso:country":"GB",
    "wof:name":"LA9 5QF",
    "wof:placetype":"postalcode"
},
  "geometry": {"coordinates":[-2.75548204880808,54.34025560572831],"type":"Point"}
}