{
  "type": "Feature",
  "properties": {
    "iso:country":"GB",
    "wof:name":"LL57 2HX",
    "wof:placetype":"postalcode"
},
  "geometry": {"coordinates":[-4.15875851722513,53.22026820058913],"type":"Point"}
}