{
  "type": "Feature",
  "properties": {
    "iso:country": "GB",
    "wof:name": "LL57 2HX",
    "wof:placetype": "postalcode"
  },
  "geometry": {"coordinates":[-4.158758,53.220268],"type":"Point"}
}
