{
  "type": "Feature",
  "properties": {
    "date:inception_lower":"1980-01-01",
    "date:inception_upper":"1980-01-31",
    "iso:country":"GB",
    "wof:name":"LL57 2HX",
    "wof:placetype":"postalcode"
},
  "geometry": {"coordinates":[-4.158758,53.220268],"type":"Point"}
}