{
  "type": "Feature",
  "properties": {
    "date:inception_lower":"2000-12-01",
    "date:inception_upper":"2000-12-31",
    "iso:country":"GB",
    "wof:name":"RM8 2JX",
    "wof:placetype":"postalcode"
},
  "geometry": {"coordinates":[0.123162,51.559761],"type":"Point"}
}