{
  "type": "Feature",
  "properties": {
    "iso:country": "GB",
    "wof:name": "BH23 2AL",
    "wof:placetype": "postalcode"
  },
  "geometry": {"coordinates":[-1.791454,50.739799],"type":"Point"}
}
