{
  "type": "Feature",
  "properties": {
    "iso:country":"GB",
    "wof:name":"SL6 9AA",
    "wof:placetype":"postalcode"
},
  "geometry": {"coordinates":[-0.73124603378259,51.56291065387622],"type":"Point"}
}