{
  "type": "Feature",
  "properties": {
    "iso:country":"GB",
    "wof:name":"SA11 2LH",
    "wof:placetype":"postalcode"
},
  "geometry": {"coordinates":[-3.82534761911803,51.63889670970067],"type":"Point"}
}