{
  "type": "Feature",
  "properties": {
    "iso:country":"GB",
    "wof:name":"SY17 5NP",
    "wof:placetype":"postalcode"
},
  "geometry": {"coordinates":[-3.48758297643656,52.54872600261827],"type":"Point"}
}