{
  "type": "Feature",
  "properties": {
    "date:inception_lower": "2000-06-01",
    "date:inception_upper": "2000-06-01",
    "iso:country": "GB",
    "wof:name": "TF1 5BX",
    "wof:placetype": "postalcode"
  },
  "geometry": {"coordinates":[-2.487629,52.69884],"type":"Point"}
}
