{
  "type": "Feature",
  "properties": {
    "iso:country": "GB",
    "wof:name": "NP7 9FJ",
    "wof:placetype": "postalcode"
  },
  "geometry": {"coordinates":[-3.028776,51.812346],"type":"Point"}
}
