{
  "type": "Feature",
  "properties": {
    "iso:country":"GB",
    "wof:name":"NP7 9FJ",
    "wof:placetype":"postalcode"
},
  "geometry": {"coordinates":[-3.02879934593038,51.81235013356082],"type":"Point"}
}