{
  "type": "Feature",
  "properties": {
    "date:inception_lower": "2008-06-01",
    "date:inception_upper": "2008-06-01",
    "iso:country": "GB",
    "wof:name": "NP7 9FJ",
    "wof:placetype": "postalcode"
  },
  "geometry": {"coordinates":[-3.028776,51.812346],"type":"Point"}
}
