{
  "type": "Feature",
  "properties": {
    "iso:country": "GB",
    "wof:name": "NP19 0QA",
    "wof:placetype": "postalcode"
  },
  "geometry": {"coordinates":[-2.991137,51.588725],"type":"Point"}
}
