{
  "type": "Feature",
  "properties": {
    "date:inception_lower": "1980-01-01",
    "date:inception_upper": "1980-01-01",
    "iso:country": "GB",
    "wof:name": "E9 6RU",
    "wof:placetype": "postalcode"
  },
  "geometry": {"coordinates":[-0.050209,51.545956],"type":"Point"}
}
