{
  "type": "Feature",
  "properties": {
    "iso:country":"GB",
    "wof:name":"G14 0XF",
    "wof:placetype":"postalcode"
},
  "geometry": {"coordinates":[-4.36214438203504,55.88247230562474],"type":"Point"}
}