{
  "type": "Feature",
  "properties": {
    "iso:country":"GB",
    "wof:name":"GU9 9PA",
    "wof:placetype":"postalcode"
},
  "geometry": {"coordinates":[-0.77282997145686,51.22419845476362],"type":"Point"}
}