{
  "type": "Feature",
  "properties": {
    "iso:country": "GB",
    "wof:name": "SY13 3HD",
    "wof:placetype": "postalcode"
  },
  "geometry": {"coordinates":[-2.749913,52.951729],"type":"Point"}
}
