{
  "type": "Feature",
  "properties": {
    "iso:country":"GB",
    "wof:name":"SY13 3HD",
    "wof:placetype":"postalcode"
},
  "geometry": {"coordinates":[-2.74935015151808,52.95182660168404],"type":"Point"}
}