{
  "type": "Feature",
  "properties": {
    "iso:country":"GB",
    "wof:name":"WN7 4AD",
    "wof:placetype":"postalcode"
},
  "geometry": {"coordinates":[-2.52267381633635,53.49719380702946],"type":"Point"}
}