{
  "type": "Feature",
  "properties": {
    "iso:country": "GB",
    "wof:name": "WN7 4AD",
    "wof:placetype": "postalcode"
  },
  "geometry": {"coordinates":[-2.522673,53.49721],"type":"Point"}
}
