{
  "type": "Feature",
  "properties": {
    "iso:country":"GB",
    "wof:name":"PR2 3NL",
    "wof:placetype":"postalcode"
},
  "geometry": {"coordinates":[-2.71611172838652,53.79819199093596],"type":"Point"}
}