{
  "type": "Feature",
  "properties": {
    "iso:country":"GB",
    "wof:name":"CM22 6BA",
    "wof:placetype":"postalcode"
},
  "geometry": {"coordinates":[0.25543154902344,51.93429363367998],"type":"Point"}
}