{
  "type": "Feature",
  "properties": {
    "date:inception_lower": "1980-01-01",
    "date:inception_upper": "1980-01-01",
    "iso:country": "GB",
    "wof:name": "B65 8NA",
    "wof:placetype": "postalcode"
  },
  "geometry": {"coordinates":[-2.062967,52.494734],"type":"Point"}
}
