{
  "type": "Feature",
  "properties": {
    "date:inception_lower":"2008-03-01",
    "date:inception_upper":"2008-03-31",
    "iso:country":"GB",
    "wof:name":"LS10 4GF",
    "wof:placetype":"postalcode"
},
  "geometry": {"coordinates":[-1.525922,53.744406],"type":"Point"}
}