{
  "type": "Feature",
  "properties": {
    "iso:country":"GB",
    "wof:name":"LS10 4GF",
    "wof:placetype":"postalcode"
},
  "geometry": {"coordinates":[-1.52592210032116,53.74440644647733],"type":"Point"}
}