{
  "type": "Feature",
  "properties": {
    "iso:country":"GB",
    "wof:name":"NG2 7BE",
    "wof:placetype":"postalcode"
},
  "geometry": {"coordinates":[-1.12962440927473,52.91885891607511],"type":"Point"}
}