{
  "type": "Feature",
  "properties": {
    "iso:country": "GB",
    "wof:name": "RH12 4JB",
    "wof:placetype": "postalcode"
  },
  "geometry": {"coordinates":[-0.30574,51.07621],"type":"Point"}
}
