{
  "type": "Feature",
  "properties": {
    "iso:country":"GB",
    "wof:name":"CW8 3HP",
    "wof:placetype":"postalcode"
},
  "geometry": {"coordinates":[-2.58658019954335,53.26147347884037],"type":"Point"}
}