{
  "type": "Feature",
  "properties": {
    "iso:country":"GB",
    "wof:name":"RG23 8QH",
    "wof:placetype":"postalcode"
},
  "geometry": {"coordinates":[-1.12769364921317,51.26641533000044],"type":"Point"}
}