{
  "type": "Feature",
  "properties": {
    "iso:country": "GB",
    "wof:name": "RG23 8QH",
    "wof:placetype": "postalcode"
  },
  "geometry": {"coordinates":[-1.127694,51.266415],"type":"Point"}
}
