{
  "type": "Feature",
  "properties": {
    "iso:country":"GB",
    "wof:name":"KA7 2JQ",
    "wof:placetype":"postalcode"
},
  "geometry": {"coordinates":[-4.6245408624509,55.45067246698225],"type":"Point"}
}