{
  "type": "Feature",
  "properties": {
    "date:inception_lower":"2005-11-01",
    "date:inception_upper":"2005-11-30",
    "iso:country":"GB",
    "wof:name":"BS7 8QN",
    "wof:placetype":"postalcode"
},
  "geometry": {"coordinates":[-2.589579,51.481812],"type":"Point"}
}