{
  "type": "Feature",
  "properties": {
    "iso:country":"GB",
    "wof:name":"TF1 1WB",
    "wof:placetype":"postalcode"
},
  "geometry": {"coordinates":[-2.5199168787147,52.69996996394746],"type":"Point"}
}