{
  "type": "Feature",
  "properties": {
    "iso:country":"GB",
    "wof:name":"RG8 0HA",
    "wof:placetype":"postalcode"
},
  "geometry": {"coordinates":[-1.12733170934248,51.52804855580664],"type":"Point"}
}