{
  "type": "Feature",
  "properties": {
    "iso:country": "GB",
    "wof:name": "RG8 0HA",
    "wof:placetype": "postalcode"
  },
  "geometry": {"coordinates":[-1.127332,51.528049],"type":"Point"}
}
