{
  "type": "Feature",
  "properties": {
    "iso:country":"GB",
    "wof:name":"AL2 1UA",
    "wof:placetype":"postalcode"
},
  "geometry": {"coordinates":[-0.30813855713978,51.72220168793208],"type":"Point"}
}