{
  "type": "Feature",
  "properties": {
    "iso:country": "GB",
    "wof:name": "AL2 1UA",
    "wof:placetype": "postalcode"
  },
  "geometry": {"coordinates":[-0.308139,51.722202],"type":"Point"}
}
