{
  "type": "Feature",
  "properties": {
    "date:inception_lower":"2003-01-01",
    "date:inception_upper":"2003-01-31",
    "iso:country":"GB",
    "wof:name":"AL2 1UA",
    "wof:placetype":"postalcode"
},
  "geometry": {"coordinates":[-0.308139,51.722202],"type":"Point"}
}