{
  "type": "Feature",
  "properties": {
    "iso:country":"GB",
    "wof:name":"HP15 7DD",
    "wof:placetype":"postalcode"
},
  "geometry": {"coordinates":[-0.70678048920041,51.65990807196003],"type":"Point"}
}