{
  "type": "Feature",
  "properties": {
    "iso:country": "GB",
    "wof:name": "TQ13 0DP",
    "wof:placetype": "postalcode"
  },
  "geometry": {"coordinates":[-3.587369,50.618141],"type":"Point"}
}
