{
  "type": "Feature",
  "properties": {
    "iso:country":"GB",
    "wof:name":"SN4 9PF",
    "wof:placetype":"postalcode"
},
  "geometry": {"coordinates":[-1.84003174269827,51.48675659297037],"type":"Point"}
}