{
  "type": "Feature",
  "properties": {
    "iso:country": "GB",
    "wof:name": "SN4 9PF",
    "wof:placetype": "postalcode"
  },
  "geometry": {"coordinates":[-1.840032,51.486757],"type":"Point"}
}
