{
  "type": "Feature",
  "properties": {
    "iso:country":"GB",
    "wof:name":"TS5 6BS",
    "wof:placetype":"postalcode"
},
  "geometry": {"coordinates":[-1.24296435265193,54.56318627654228],"type":"Point"}
}