{
  "type": "Feature",
  "properties": {
    "iso:country":"GB",
    "wof:name":"IV2 4EL",
    "wof:placetype":"postalcode"
},
  "geometry": {"coordinates":[-4.22312770937032,57.45736417849797],"type":"Point"}
}