{
  "type": "Feature",
  "properties": {
    "iso:country":"GB",
    "wof:name":"GU3 1NG",
    "wof:placetype":"postalcode"
},
  "geometry": {"coordinates":[-0.58045908365253,51.20885839582808],"type":"Point"}
}