{
  "type": "Feature",
  "properties": {
    "iso:country": "GB",
    "wof:name": "GU3 1NG",
    "wof:placetype": "postalcode"
  },
  "geometry": {"coordinates":[-0.580459,51.208858],"type":"Point"}
}
