{
  "type": "Feature",
  "properties": {
    "iso:country": "GB",
    "wof:name": "BN18 0FS",
    "wof:placetype": "postalcode"
  },
  "geometry": {"coordinates":[-0.601568,50.8187],"type":"Point"}
}
