{
  "type": "Feature",
  "properties": {
    "iso:country":"GB",
    "wof:name":"BN18 0FS",
    "wof:placetype":"postalcode"
},
  "geometry": {"coordinates":[-0.60367022725332,50.81895039754147],"type":"Point"}
}