{
  "type": "Feature",
  "properties": {
    "iso:country": "GB",
    "wof:name": "G61 3SR",
    "wof:placetype": "postalcode"
  },
  "geometry": {"coordinates":[-4.332201,55.92225],"type":"Point"}
}
