{
  "type": "Feature",
  "properties": {
    "iso:country":"GB",
    "wof:name":"G61 3SR",
    "wof:placetype":"postalcode"
},
  "geometry": {"coordinates":[-4.33236807650916,55.92238797956438],"type":"Point"}
}