{
  "type": "Feature",
  "properties": {
    "date:inception_lower": "1980-01-01",
    "date:inception_upper": "1980-01-01",
    "iso:country": "GB",
    "wof:name": "DG1 1BU",
    "wof:placetype": "postalcode"
  },
  "geometry": {"coordinates":[-3.611194,55.070662],"type":"Point"}
}
