{
  "type": "Feature",
  "properties": {
    "iso:country":"GB",
    "wof:name":"DG1 1BU",
    "wof:placetype":"postalcode"
},
  "geometry": {"coordinates":[-3.6112139104256,55.07069285783258],"type":"Point"}
}