{
  "type": "Feature",
  "properties": {
    "iso:country":"GB",
    "wof:name":"ML9 2SF",
    "wof:placetype":"postalcode"
},
  "geometry": {"coordinates":[-3.9540235103045,55.73191877326477],"type":"Point"}
}