{
  "type": "Feature",
  "properties": {
    "iso:country":"GB",
    "wof:name":"BS37 9XB",
    "wof:placetype":"postalcode"
},
  "geometry": {"coordinates":[-2.45500003546608,51.55495549401104],"type":"Point"}
}