{
  "type": "Feature",
  "properties": {
    "iso:country":"GB",
    "wof:name":"PO15 6QY",
    "wof:placetype":"postalcode"
},
  "geometry": {"coordinates":[-1.23184343750254,50.8668434630375],"type":"Point"}
}