{
  "type": "Feature",
  "properties": {
    "iso:country": "GB",
    "wof:name": "PO15 6QY",
    "wof:placetype": "postalcode"
  },
  "geometry": {"coordinates":[-1.231758,50.866951],"type":"Point"}
}
