{
  "type": "Feature",
  "properties": {
    "iso:country":"GB",
    "wof:name":"TN12 0RX",
    "wof:placetype":"postalcode"
},
  "geometry": {"coordinates":[0.54790598949852,51.17068450165029],"type":"Point"}
}