{
  "type": "Feature",
  "properties": {
    "iso:country":"GB",
    "wof:name":"DD7 7LY",
    "wof:placetype":"postalcode"
},
  "geometry": {"coordinates":[-2.73063920883798,56.49871582056367],"type":"Point"}
}