{
  "type": "Feature",
  "properties": {
    "iso:country":"GB",
    "wof:name":"PL6 5UF",
    "wof:placetype":"postalcode"
},
  "geometry": {"coordinates":[-4.12724388495532,50.41616689064175],"type":"Point"}
}