{
  "type": "Feature",
  "properties": {
    "date:inception_lower": "2006-09-01",
    "date:inception_upper": "2006-09-01",
    "iso:country": "GB",
    "wof:name": "CB25 0BH",
    "wof:placetype": "postalcode"
  },
  "geometry": {"coordinates":[0.324047,52.303746],"type":"Point"}
}
