{
  "type": "Feature",
  "properties": {
    "iso:country":"GB",
    "wof:name":"CB25 0BH",
    "wof:placetype":"postalcode"
},
  "geometry": {"coordinates":[0.3298515025911,52.30330106333442],"type":"Point"}
}