{
  "type": "Feature",
  "properties": {
    "iso:country": "GB",
    "wof:name": "CB25 0BH",
    "wof:placetype": "postalcode"
  },
  "geometry": {"coordinates":[0.324047,52.303746],"type":"Point"}
}
