{
  "type": "Feature",
  "properties": {
    "iso:country":"GB",
    "wof:name":"NG1 2GH",
    "wof:placetype":"postalcode"
},
  "geometry": {"coordinates":[-1.14747857817818,52.95184507206746],"type":"Point"}
}