{
  "type": "Feature",
  "properties": {
    "iso:country":"GB",
    "wof:name":"CM7 4SJ",
    "wof:placetype":"postalcode"
},
  "geometry": {"coordinates":[0.43908608167863,51.94402052948482],"type":"Point"}
}