{
  "type": "Feature",
  "properties": {
    "iso:country": "GB",
    "wof:name": "PL31 2SN",
    "wof:placetype": "postalcode"
  },
  "geometry": {"coordinates":[-4.743719,50.470788],"type":"Point"}
}
