{
  "type": "Feature",
  "properties": {
    "iso:country":"GB",
    "wof:name":"EH8 7LA",
    "wof:placetype":"postalcode"
},
  "geometry": {"coordinates":[-3.14176912283234,55.94970373925269],"type":"Point"}
}