{
  "type": "Feature",
  "properties": {
    "iso:country":"GB",
    "wof:name":"TS11 7AT",
    "wof:placetype":"postalcode"
},
  "geometry": {"coordinates":[-1.01334845036915,54.59214282274514],"type":"Point"}
}