{
  "type": "Feature",
  "properties": {
    "iso:country": "GB",
    "wof:name": "TA6 4RY",
    "wof:placetype": "postalcode"
  },
  "geometry": {"coordinates":[-3.00298,51.180815],"type":"Point"}
}
