{
  "type": "Feature",
  "properties": {
    "iso:country":"GB",
    "wof:name":"TA6 4RY",
    "wof:placetype":"postalcode"
},
  "geometry": {"coordinates":[-3.00298588571016,51.1808198810011],"type":"Point"}
}