{
  "type": "Feature",
  "properties": {
    "date:inception_lower": "1980-01-01",
    "date:inception_upper": "1980-01-01",
    "iso:country": "GB",
    "wof:name": "B31 2UA",
    "wof:placetype": "postalcode"
  },
  "geometry": {"coordinates":[-1.991137,52.400904],"type":"Point"}
}
