{
  "type": "Feature",
  "properties": {
    "date:inception_lower": "1980-01-01",
    "date:inception_upper": "1980-01-01",
    "iso:country": "GB",
    "wof:name": "SY5 0XX",
    "wof:placetype": "postalcode"
  },
  "geometry": {"coordinates":[-2.891273,52.64657],"type":"Point"}
}
