{
  "type": "Feature",
  "properties": {
    "date:inception_lower": "1980-01-01",
    "date:inception_upper": "1980-01-01",
    "iso:country": "GB",
    "wof:name": "S75 4JA",
    "wof:placetype": "postalcode"
  },
  "geometry": {"coordinates":[-1.568453,53.573916],"type":"Point"}
}
