{
  "type": "Feature",
  "properties": {
    "iso:country":"GB",
    "wof:name":"S75 4JA",
    "wof:placetype":"postalcode"
},
  "geometry": {"coordinates":[-1.56845335873164,53.57391630215773],"type":"Point"}
}