{
  "type": "Feature",
  "properties": {
    "iso:country": "GB",
    "wof:name": "EH47 9HB",
    "wof:placetype": "postalcode"
  },
  "geometry": {"coordinates":[-3.698589,55.827388],"type":"Point"}
}
