{
  "type": "Feature",
  "properties": {
    "iso:country":"GB",
    "wof:name":"EH47 9HB",
    "wof:placetype":"postalcode"
},
  "geometry": {"coordinates":[-3.69858942505186,55.82738802139929],"type":"Point"}
}