{
  "type": "Feature",
  "properties": {
    "date:inception_lower":"1980-01-01",
    "date:inception_upper":"1980-01-31",
    "iso:country":"GB",
    "wof:name":"WS2 7HN",
    "wof:placetype":"postalcode"
},
  "geometry": {"coordinates":[-2.006748,52.599123],"type":"Point"}
}