{
  "type": "Feature",
  "properties": {
    "iso:country":"GB",
    "wof:name":"WS2 7HN",
    "wof:placetype":"postalcode"
},
  "geometry": {"coordinates":[-2.00674825317668,52.59912272705067],"type":"Point"}
}