{
  "type": "Feature",
  "properties": {
    "date:inception_lower": "2022-02-01",
    "date:inception_upper": "2022-02-01",
    "iso:country": "GB",
    "wof:name": "YO16 6AQ",
    "wof:placetype": "postalcode"
  },
  "geometry": {"coordinates":[-0.205215,54.101874],"type":"Point"}
}
