{
  "type": "Feature",
  "properties": {
    "iso:country":"GB",
    "wof:name":"EX16 8QH",
    "wof:placetype":"postalcode"
},
  "geometry": {"coordinates":[-3.67425222450038,50.94065992151678],"type":"Point"}
}