{
  "type": "Feature",
  "properties": {
    "iso:country": "GB",
    "wof:name": "EX16 8QH",
    "wof:placetype": "postalcode"
  },
  "geometry": {"coordinates":[-3.674252,50.94066],"type":"Point"}
}
