{
  "type": "Feature",
  "properties": {
    "iso:country": "GB",
    "wof:name": "PR3 0EN",
    "wof:placetype": "postalcode"
  },
  "geometry": {"coordinates":[-2.760099,53.874964],"type":"Point"}
}
