{
  "type": "Feature",
  "properties": {
    "iso:country":"GB",
    "wof:name":"SP4 7RX",
    "wof:placetype":"postalcode"
},
  "geometry": {"coordinates":[-1.76230720376953,51.17489929494646],"type":"Point"}
}