{
  "type": "Feature",
  "properties": {
    "iso:country":"GB",
    "wof:name":"WF13 1DL",
    "wof:placetype":"postalcode"
},
  "geometry": {"coordinates":[-1.62884063564302,53.69158632602235],"type":"Point"}
}