{
  "type": "Feature",
  "properties": {
    "date:inception_lower":"1980-01-01",
    "date:inception_upper":"1980-01-31",
    "iso:country":"GB",
    "wof:name":"PR2 2QB",
    "wof:placetype":"postalcode"
},
  "geometry": {"coordinates":[-2.716977,53.763465],"type":"Point"}
}