{
  "type": "Feature",
  "properties": {
    "iso:country":"GB",
    "wof:name":"SL1 7AG",
    "wof:placetype":"postalcode"
},
  "geometry": {"coordinates":[-0.66475059788092,51.53341674816821],"type":"Point"}
}