{
  "type": "Feature",
  "properties": {
    "iso:country":"GB",
    "wof:name":"CH1 4RJ",
    "wof:placetype":"postalcode"
},
  "geometry": {"coordinates":[-2.92334277006612,53.19505899020994],"type":"Point"}
}