{
  "type": "Feature",
  "properties": {
    "date:inception_lower": "1993-08-01",
    "date:inception_upper": "1993-08-01",
    "iso:country": "GB",
    "wof:name": "CH1 4RJ",
    "wof:placetype": "postalcode"
  },
  "geometry": {"coordinates":[-2.923373,53.195056],"type":"Point"}
}
