{
  "type": "Feature",
  "properties": {
    "iso:country": "GB",
    "wof:name": "CH1 4RJ",
    "wof:placetype": "postalcode"
  },
  "geometry": {"coordinates":[-2.923373,53.195056],"type":"Point"}
}
