{
  "type": "Feature",
  "properties": {
    "iso:country":"GB",
    "wof:name":"KA23 9LZ",
    "wof:placetype":"postalcode"
},
  "geometry": {"coordinates":[-4.86416304826147,55.68858307698107],"type":"Point"}
}