{
  "type": "Feature",
  "properties": {
    "date:inception_lower": "1980-01-01",
    "date:inception_upper": "1980-01-01",
    "iso:country": "GB",
    "wof:name": "CM23 5BD",
    "wof:placetype": "postalcode"
  },
  "geometry": {"coordinates":[0.181386,51.874604],"type":"Point"}
}
