{
  "type": "Feature",
  "properties": {
    "iso:country":"GB",
    "wof:name":"CM23 5BD",
    "wof:placetype":"postalcode"
},
  "geometry": {"coordinates":[0.18138585277908,51.87460408756576],"type":"Point"}
}