{
  "type": "Feature",
  "properties": {
    "iso:country":"GB",
    "wof:name":"HP22 4NF",
    "wof:placetype":"postalcode"
},
  "geometry": {"coordinates":[-0.77732256190561,51.87114627961635],"type":"Point"}
}