{
  "type": "Feature",
  "properties": {
    "iso:country": "GB",
    "wof:name": "HP22 4NF",
    "wof:placetype": "postalcode"
  },
  "geometry": {"coordinates":[-0.777227,51.871144],"type":"Point"}
}
