{
  "type": "Feature",
  "properties": {
    "iso:country": "GB",
    "wof:name": "TS14 6AR",
    "wof:placetype": "postalcode"
  },
  "geometry": {"coordinates":[-1.056619,54.535257],"type":"Point"}
}
