{
  "type": "Feature",
  "properties": {
    "iso:country": "GB",
    "wof:name": "BB2 4HD",
    "wof:placetype": "postalcode"
  },
  "geometry": {"coordinates":[-2.500716,53.732816],"type":"Point"}
}
