{
  "type": "Feature",
  "properties": {
    "date:inception_lower": "1980-01-01",
    "date:inception_upper": "1980-01-01",
    "iso:country": "GB",
    "wof:name": "BB2 4HD",
    "wof:placetype": "postalcode"
  },
  "geometry": {"coordinates":[-2.500716,53.732816],"type":"Point"}
}
