{
  "type": "Feature",
  "properties": {
    "iso:country":"GB",
    "wof:name":"BB2 4HD",
    "wof:placetype":"postalcode"
},
  "geometry": {"coordinates":[-2.50068826730006,53.7328182403438],"type":"Point"}
}