{
  "type": "Feature",
  "properties": {
    "iso:country":"GB",
    "wof:name":"TN4 0AA",
    "wof:placetype":"postalcode"
},
  "geometry": {"coordinates":[0.26369623259444,51.15564871069491],"type":"Point"}
}