{
  "type": "Feature",
  "properties": {
    "iso:country": "GB",
    "wof:name": "HG4 5HL",
    "wof:placetype": "postalcode"
  },
  "geometry": {"coordinates":[-1.481904,54.184735],"type":"Point"}
}
