{
  "type": "Feature",
  "properties": {
    "date:inception_lower":"1980-01-01",
    "date:inception_upper":"1980-01-31",
    "iso:country":"GB",
    "wof:name":"HG4 5HL",
    "wof:placetype":"postalcode"
},
  "geometry": {"coordinates":[-1.481904,54.184735],"type":"Point"}
}