{
  "type": "Feature",
  "properties": {
    "iso:country":"GB",
    "wof:name":"HG4 5HL",
    "wof:placetype":"postalcode"
},
  "geometry": {"coordinates":[-1.48190400689885,54.18473523590359],"type":"Point"}
}