{
  "type": "Feature",
  "properties": {
    "date:inception_lower": "1980-01-01",
    "date:inception_upper": "1980-01-01",
    "iso:country": "GB",
    "wof:name": "TA24 7DX",
    "wof:placetype": "postalcode"
  },
  "geometry": {"coordinates":[-3.538134,51.138269],"type":"Point"}
}
