{
  "type": "Feature",
  "properties": {
    "iso:country":"GB",
    "wof:name":"TA24 7DX",
    "wof:placetype":"postalcode"
},
  "geometry": {"coordinates":[-3.53811699411432,51.13821738163333],"type":"Point"}
}