{
  "type": "Feature",
  "properties": {
    "iso:country": "GB",
    "wof:name": "CF14 9EL",
    "wof:placetype": "postalcode"
  },
  "geometry": {"coordinates":[-3.194386,51.540783],"type":"Point"}
}
