{
  "type": "Feature",
  "properties": {
    "iso:country":"GB",
    "wof:name":"ML10 6JT",
    "wof:placetype":"postalcode"
},
  "geometry": {"coordinates":[-4.06491649445581,55.68322672104019],"type":"Point"}
}