{
  "type": "Feature",
  "properties": {
    "iso:country":"GB",
    "wof:name":"BL8 2PE",
    "wof:placetype":"postalcode"
},
  "geometry": {"coordinates":[-2.31926857922926,53.59024820448164],"type":"Point"}
}