{
  "type": "Feature",
  "properties": {
    "iso:country":"GB",
    "wof:name":"HP5 2YD",
    "wof:placetype":"postalcode"
},
  "geometry": {"coordinates":[-0.65174724083784,51.72443442792126],"type":"Point"}
}