{
  "type": "Feature",
  "properties": {
    "iso:country": "GB",
    "wof:name": "HP5 2YD",
    "wof:placetype": "postalcode"
  },
  "geometry": {"coordinates":[-0.651747,51.724434],"type":"Point"}
}
