{
  "type": "Feature",
  "properties": {
    "iso:country":"GB",
    "wof:name":"B45 9PX",
    "wof:placetype":"postalcode"
},
  "geometry": {"coordinates":[-2.0018662099707,52.39430528824235],"type":"Point"}
}