{
  "type": "Feature",
  "properties": {
    "iso:country":"GB",
    "wof:name":"PR5 0DU",
    "wof:placetype":"postalcode"
},
  "geometry": {"coordinates":[-2.61546144546297,53.73441373008483],"type":"Point"}
}