{
  "type": "Feature",
  "properties": {
    "iso:country": "GB",
    "wof:name": "PR5 0DU",
    "wof:placetype": "postalcode"
  },
  "geometry": {"coordinates":[-2.615461,53.734414],"type":"Point"}
}
