{
  "type": "Feature",
  "properties": {
    "iso:country": "GB",
    "wof:name": "NR14 6FX",
    "wof:placetype": "postalcode"
  },
  "geometry": {"coordinates":[1.472017,52.535365],"type":"Point"}
}
