{
  "type": "Feature",
  "properties": {
    "iso:country": "GB",
    "wof:name": "NE21 4JQ",
    "wof:placetype": "postalcode"
  },
  "geometry": {"coordinates":[-1.719078,54.96582],"type":"Point"}
}
