{
  "type": "Feature",
  "properties": {
    "iso:country": "GB",
    "wof:name": "HD5 0RU",
    "wof:placetype": "postalcode"
  },
  "geometry": {"coordinates":[-1.739662,53.683987],"type":"Point"}
}
