{
  "type": "Feature",
  "properties": {
    "iso:country":"GB",
    "wof:name":"WA9 4SN",
    "wof:placetype":"postalcode"
},
  "geometry": {"coordinates":[-2.69489526669513,53.41584978934138],"type":"Point"}
}