{
  "type": "Feature",
  "properties": {
    "iso:country":"GB",
    "wof:name":"SK10 3EW",
    "wof:placetype":"postalcode"
},
  "geometry": {"coordinates":[-2.15778792409775,53.26994991050578],"type":"Point"}
}