{
  "type": "Feature",
  "properties": {
    "iso:country": "GB",
    "wof:name": "DN22 9LD",
    "wof:placetype": "postalcode"
  },
  "geometry": {"coordinates":[-0.907687,53.350972],"type":"Point"}
}
