{
  "type": "Feature",
  "properties": {
    "date:inception_lower":"1980-01-01",
    "date:inception_upper":"1980-01-31",
    "iso:country":"GB",
    "wof:name":"EX4 1JH",
    "wof:placetype":"postalcode"
},
  "geometry": {"coordinates":[-3.547735,50.716785],"type":"Point"}
}