{
  "type": "Feature",
  "properties": {
    "iso:country":"GB",
    "wof:name":"L24 9PS",
    "wof:placetype":"postalcode"
},
  "geometry": {"coordinates":[-2.84220024056562,53.35300422035898],"type":"Point"}
}