{
  "type": "Feature",
  "properties": {
    "iso:country":"GB",
    "wof:name":"NW9 6FL",
    "wof:placetype":"postalcode"
},
  "geometry": {"coordinates":[-0.25566046450425,51.59140744575136],"type":"Point"}
}