{
  "type": "Feature",
  "properties": {
    "iso:country":"GB",
    "wof:name":"SW4 7TT",
    "wof:placetype":"postalcode"
},
  "geometry": {"coordinates":[-0.13102239858267,51.46341400339001],"type":"Point"}
}