{
  "type": "Feature",
  "properties": {
    "iso:country":"GB",
    "wof:name":"TR20 9QL",
    "wof:placetype":"postalcode"
},
  "geometry": {"coordinates":[-5.40010050045704,50.11406185367935],"type":"Point"}
}