{
  "type": "Feature",
  "properties": {
    "iso:country":"GB",
    "wof:name":"RG40 3QL",
    "wof:placetype":"postalcode"
},
  "geometry": {"coordinates":[-0.83620542781502,51.37256022312146],"type":"Point"}
}