{
  "type": "Feature",
  "properties": {
    "date:inception_lower": "1990-02-01",
    "date:inception_upper": "1990-02-01",
    "iso:country": "GB",
    "wof:name": "PO30 4PX",
    "wof:placetype": "postalcode"
  },
  "geometry": {"coordinates":[-1.420561,50.70111],"type":"Point"}
}
