{
  "type": "Feature",
  "properties": {
    "iso:country":"GB",
    "wof:name":"PO30 4PX",
    "wof:placetype":"postalcode"
},
  "geometry": {"coordinates":[-1.42056152865127,50.70110957399887],"type":"Point"}
}