{
  "type": "Feature",
  "properties": {
    "iso:country": "GB",
    "wof:name": "PO30 4PX",
    "wof:placetype": "postalcode"
  },
  "geometry": {"coordinates":[-1.420561,50.70111],"type":"Point"}
}
