{
  "type": "Feature",
  "properties": {
    "date:inception_lower": "1980-01-01",
    "date:inception_upper": "1980-01-01",
    "iso:country": "GB",
    "wof:name": "HP9 2HD",
    "wof:placetype": "postalcode"
  },
  "geometry": {"coordinates":[-0.634591,51.608962],"type":"Point"}
}
