{
  "type": "Feature",
  "properties": {
    "date:inception_lower":"2014-08-01",
    "date:inception_upper":"2014-08-31",
    "iso:country":"GB",
    "wof:name":"ST10 4FG",
    "wof:placetype":"postalcode"
},
  "geometry": {"coordinates":[-1.888602,52.97325],"type":"Point"}
}