{
  "type": "Feature",
  "properties": {
    "iso:country":"GB",
    "wof:name":"ST10 4FG",
    "wof:placetype":"postalcode"
},
  "geometry": {"coordinates":[-1.88860241853531,52.97324953023868],"type":"Point"}
}