{
  "type": "Feature",
  "properties": {
    "iso:country": "GB",
    "wof:name": "HP18 0GP",
    "wof:placetype": "postalcode"
  },
  "geometry": {"coordinates":[-0.855814,51.840331],"type":"Point"}
}
