{
  "type": "Feature",
  "properties": {
    "iso:country":"GB",
    "wof:name":"LN8 3LQ",
    "wof:placetype":"postalcode"
},
  "geometry": {"coordinates":[-0.36270329524483,53.38657810089534],"type":"Point"}
}