{
  "type": "Feature",
  "properties": {
    "iso:country":"GB",
    "wof:name":"CF5 3SN",
    "wof:placetype":"postalcode"
},
  "geometry": {"coordinates":[-3.25644429046788,51.4945550439907],"type":"Point"}
}