{
  "type": "Feature",
  "properties": {
    "iso:country":"GB",
    "wof:name":"BS7 9TP",
    "wof:placetype":"postalcode"
},
  "geometry": {"coordinates":[-2.56148077588611,51.49096895714279],"type":"Point"}
}