{
  "type": "Feature",
  "properties": {
    "iso:country": "GB",
    "wof:name": "TD8 6PZ",
    "wof:placetype": "postalcode"
  },
  "geometry": {"coordinates":[-2.543797,55.474234],"type":"Point"}
}
