{
  "type": "Feature",
  "properties": {
    "iso:country": "GB",
    "wof:name": "DH5 8AZ",
    "wof:placetype": "postalcode"
  },
  "geometry": {"coordinates":[-1.465408,54.845756],"type":"Point"}
}
