{
  "type": "Feature",
  "properties": {
    "iso:country":"GB",
    "wof:name":"DH5 8AZ",
    "wof:placetype":"postalcode"
},
  "geometry": {"coordinates":[-1.4654076362841,54.84575625028528],"type":"Point"}
}