{
  "type": "Feature",
  "properties": {
    "iso:country":"GB",
    "wof:name":"PE15 0AA",
    "wof:placetype":"postalcode"
},
  "geometry": {"coordinates":[0.05524098128498,52.57560940422755],"type":"Point"}
}