{
  "type": "Feature",
  "properties": {
    "iso:country": "GB",
    "wof:name": "YO60 7PE",
    "wof:placetype": "postalcode"
  },
  "geometry": {"coordinates":[-0.908011,54.061486],"type":"Point"}
}
