{
  "type": "Feature",
  "properties": {
    "iso:country":"GB",
    "wof:name":"YO60 7PE",
    "wof:placetype":"postalcode"
},
  "geometry": {"coordinates":[-0.90781740302957,54.06147593901054],"type":"Point"}
}