{
  "type": "Feature",
  "properties": {
    "iso:country":"GB",
    "wof:name":"G76 7UJ",
    "wof:placetype":"postalcode"
},
  "geometry": {"coordinates":[-4.29213787990113,55.78826741521807],"type":"Point"}
}