{
  "type": "Feature",
  "properties": {
    "date:inception_lower": "2014-02-01",
    "date:inception_upper": "2014-02-01",
    "iso:country": "GB",
    "wof:name": "TA6 7EP",
    "wof:placetype": "postalcode"
  },
  "geometry": {"coordinates":[-3.014838,51.125064],"type":"Point"}
}
