{
  "type": "Feature",
  "properties": {
    "iso:country": "GB",
    "wof:name": "CM23 5QJ",
    "wof:placetype": "postalcode"
  },
  "geometry": {"coordinates":[0.191152,51.883684],"type":"Point"}
}
