{
  "type": "Feature",
  "properties": {
    "iso:country":"GB",
    "wof:name":"CM23 5QJ",
    "wof:placetype":"postalcode"
},
  "geometry": {"coordinates":[0.19112492940892,51.88367629389581],"type":"Point"}
}