{
  "type": "Feature",
  "properties": {
    "iso:country": "GB",
    "wof:name": "CF3 0AL",
    "wof:placetype": "postalcode"
  },
  "geometry": {"coordinates":[-3.110139,51.522117],"type":"Point"}
}
