{
  "type": "Feature",
  "properties": {
    "iso:country": "GB",
    "wof:name": "CM3 4XG",
    "wof:placetype": "postalcode"
  },
  "geometry": {"coordinates":[0.581518,51.690047],"type":"Point"}
}
