{
  "type": "Feature",
  "properties": {
    "iso:country":"GB",
    "wof:name":"CM3 4XG",
    "wof:placetype":"postalcode"
},
  "geometry": {"coordinates":[0.58151798747716,51.69004702415106],"type":"Point"}
}