{
  "type": "Feature",
  "properties": {
    "iso:country":"GB",
    "wof:name":"L31 4JP",
    "wof:placetype":"postalcode"
},
  "geometry": {"coordinates":[-2.94902773254066,53.52966921613236],"type":"Point"}
}