{
  "type": "Feature",
  "properties": {
    "iso:country": "GB",
    "wof:name": "L31 4JP",
    "wof:placetype": "postalcode"
  },
  "geometry": {"coordinates":[-2.949028,53.529669],"type":"Point"}
}
