{
  "type": "Feature",
  "properties": {
    "date:inception_lower": "1990-07-01",
    "date:inception_upper": "1990-07-01",
    "iso:country": "GB",
    "wof:name": "BN43 6TL",
    "wof:placetype": "postalcode"
  },
  "geometry": {"coordinates":[-0.244558,50.844497],"type":"Point"}
}
