{
  "type": "Feature",
  "properties": {
    "iso:country":"GB",
    "wof:name":"DD5 4DB",
    "wof:placetype":"postalcode"
},
  "geometry": {"coordinates":[-2.81987666540718,56.48112444012589],"type":"Point"}
}