{
  "type": "Feature",
  "properties": {
    "date:inception_lower": "2011-12-01",
    "date:inception_upper": "2011-12-01",
    "iso:country": "GB",
    "wof:name": "B34 7AQ",
    "wof:placetype": "postalcode"
  },
  "geometry": {"coordinates":[-1.777267,52.494937],"type":"Point"}
}
