{
  "type": "Feature",
  "properties": {
    "iso:country":"GB",
    "wof:name":"B34 7AQ",
    "wof:placetype":"postalcode"
},
  "geometry": {"coordinates":[-1.77726707421235,52.49493714682252],"type":"Point"}
}