{
  "type": "Feature",
  "properties": {
    "iso:country":"GB",
    "wof:name":"DD8 2QJ",
    "wof:placetype":"postalcode"
},
  "geometry": {"coordinates":[-2.76714900089463,56.61978202162462],"type":"Point"}
}