{
  "type": "Feature",
  "properties": {
    "iso:country": "GB",
    "wof:name": "CV23 0XW",
    "wof:placetype": "postalcode"
  },
  "geometry": {"coordinates":[-1.251501,52.402473],"type":"Point"}
}
