{
  "type": "Feature",
  "properties": {
    "date:inception_lower": "1990-02-01",
    "date:inception_upper": "1990-02-01",
    "iso:country": "GB",
    "wof:name": "OL15 8RY",
    "wof:placetype": "postalcode"
  },
  "geometry": {"coordinates":[-2.107907,53.645104],"type":"Point"}
}
