{
  "type": "Feature",
  "properties": {
    "iso:country": "GB",
    "wof:name": "OL15 8RY",
    "wof:placetype": "postalcode"
  },
  "geometry": {"coordinates":[-2.107907,53.645104],"type":"Point"}
}
