{
  "type": "Feature",
  "properties": {
    "iso:country":"GB",
    "wof:name":"OL15 8RY",
    "wof:placetype":"postalcode"
},
  "geometry": {"coordinates":[-2.10790719366546,53.64510361444069],"type":"Point"}
}