{
  "type": "Feature",
  "properties": {
    "iso:country":"GB",
    "wof:name":"YO14 0QA",
    "wof:placetype":"postalcode"
},
  "geometry": {"coordinates":[-0.31497399278843,54.18326021229777],"type":"Point"}
}