{
  "type": "Feature",
  "properties": {
    "date:inception_lower": "1980-01-01",
    "date:inception_upper": "1980-01-01",
    "iso:country": "GB",
    "wof:name": "UB7 8BJ",
    "wof:placetype": "postalcode"
  },
  "geometry": {"coordinates":[-0.463714,51.516596],"type":"Point"}
}
