{
  "type": "Feature",
  "properties": {
    "iso:country":"GB",
    "wof:name":"UB7 8BJ",
    "wof:placetype":"postalcode"
},
  "geometry": {"coordinates":[-0.46371378238664,51.51659615234302],"type":"Point"}
}