{
  "type": "Feature",
  "properties": {
    "iso:country":"GB",
    "wof:name":"ME5 9TJ",
    "wof:placetype":"postalcode"
},
  "geometry": {"coordinates":[0.51459327850289,51.3525118631106],"type":"Point"}
}