{
  "type": "Feature",
  "properties": {
    "iso:country": "GB",
    "wof:name": "SY5 0BW",
    "wof:placetype": "postalcode"
  },
  "geometry": {"coordinates":[-2.917009,52.641894],"type":"Point"}
}
