{
  "type": "Feature",
  "properties": {
    "date:inception_lower": "1980-01-01",
    "date:inception_upper": "1980-01-01",
    "iso:country": "GB",
    "wof:name": "SY5 0BW",
    "wof:placetype": "postalcode"
  },
  "geometry": {"coordinates":[-2.917256,52.641694],"type":"Point"}
}
