{
  "type": "Feature",
  "properties": {
    "iso:country":"GB",
    "wof:name":"SE26 6NT",
    "wof:placetype":"postalcode"
},
  "geometry": {"coordinates":[-0.06920057168073,51.42597380012824],"type":"Point"}
}