{
  "type": "Feature",
  "properties": {
    "date:inception_lower": "2024-10-01",
    "date:inception_upper": "2024-10-01",
    "iso:country": "GB",
    "wof:name": "GL10 3WS",
    "wof:placetype": "postalcode"
  },
  "geometry": {"coordinates":[-2.29788,51.759602],"type":"Point"}
}
