{
  "type": "Feature",
  "properties": {
    "iso:country":"GB",
    "wof:name":"BN2 4HD",
    "wof:placetype":"postalcode"
},
  "geometry": {"coordinates":[-0.11507904191089,50.84844025282394],"type":"Point"}
}