{
  "type": "Feature",
  "properties": {
    "date:inception_lower": "2000-10-01",
    "date:inception_upper": "2000-10-01",
    "iso:country": "GB",
    "wof:name": "W1F 8BG",
    "wof:placetype": "postalcode"
  },
  "geometry": {"coordinates":[-0.134864,51.515704],"type":"Point"}
}
