{
  "type": "Feature",
  "properties": {
    "iso:country":"GB",
    "wof:name":"NR6 7HU",
    "wof:placetype":"postalcode"
},
  "geometry": {"coordinates":[1.30485818351414,52.66913501882273],"type":"Point"}
}