{
  "type": "Feature",
  "properties": {
    "date:inception_lower": "2009-09-01",
    "date:inception_upper": "2009-09-01",
    "iso:country": "GB",
    "wof:name": "NR6 7HU",
    "wof:placetype": "postalcode"
  },
  "geometry": {"coordinates":[1.304858,52.669135],"type":"Point"}
}
