{
  "type": "Feature",
  "properties": {
    "iso:country":"GB",
    "wof:name":"EN1 3BX",
    "wof:placetype":"postalcode"
},
  "geometry": {"coordinates":[-0.07665202375194,51.65341885645057],"type":"Point"}
}