{
  "type": "Feature",
  "properties": {
    "date:inception_lower": "1980-01-01",
    "date:inception_upper": "1980-01-01",
    "iso:country": "GB",
    "wof:name": "PL6 5EH",
    "wof:placetype": "postalcode"
  },
  "geometry": {"coordinates":[-4.127849,50.411146],"type":"Point"}
}
