{
  "type": "Feature",
  "properties": {
    "iso:country": "GB",
    "wof:name": "TA1 3GG",
    "wof:placetype": "postalcode"
  },
  "geometry": {"coordinates":[-3.089009,50.996698],"type":"Point"}
}
