{
  "type": "Feature",
  "properties": {
    "iso:country":"GB",
    "wof:name":"PA14 6YS",
    "wof:placetype":"postalcode"
},
  "geometry": {"coordinates":[-4.59876847050972,55.91972182460687],"type":"Point"}
}