{
  "type": "Feature",
  "properties": {
    "iso:country": "GB",
    "wof:name": "PA14 6YS",
    "wof:placetype": "postalcode"
  },
  "geometry": {"coordinates":[-4.597953,55.91975],"type":"Point"}
}
