{
  "type": "Feature",
  "properties": {
    "date:inception_lower":"2009-02-01",
    "date:inception_upper":"2009-02-28",
    "iso:country":"GB",
    "wof:name":"CB23 6DQ",
    "wof:placetype":"postalcode"
},
  "geometry": {"coordinates":[-0.055039,52.220541],"type":"Point"}
}