{
  "type": "Feature",
  "properties": {
    "iso:country":"GB",
    "wof:name":"WV3 7BQ",
    "wof:placetype":"postalcode"
},
  "geometry": {"coordinates":[-2.14648604083827,52.57154120713427],"type":"Point"}
}