{
  "type": "Feature",
  "properties": {
    "iso:country":"GB",
    "wof:name":"L11 6LB",
    "wof:placetype":"postalcode"
},
  "geometry": {"coordinates":[-2.89403376867869,53.45780577793143],"type":"Point"}
}