{
  "type": "Feature",
  "properties": {
    "date:inception_lower": "1980-01-01",
    "date:inception_upper": "1980-01-01",
    "iso:country": "GB",
    "wof:name": "L11 6LB",
    "wof:placetype": "postalcode"
  },
  "geometry": {"coordinates":[-2.894034,53.457806],"type":"Point"}
}
