{
  "type": "Feature",
  "properties": {
    "iso:country": "GB",
    "wof:name": "L11 6LB",
    "wof:placetype": "postalcode"
  },
  "geometry": {"coordinates":[-2.894034,53.457806],"type":"Point"}
}
