{
  "type": "Feature",
  "properties": {
    "iso:country": "GB",
    "wof:name": "IP11 7HA",
    "wof:placetype": "postalcode"
  },
  "geometry": {"coordinates":[1.353099,51.962578],"type":"Point"}
}
