{
  "type": "Feature",
  "properties": {
    "date:inception_lower": "1980-01-01",
    "date:inception_upper": "1980-01-01",
    "iso:country": "GB",
    "wof:name": "IP11 7HA",
    "wof:placetype": "postalcode"
  },
  "geometry": {"coordinates":[1.353099,51.962578],"type":"Point"}
}
