{
  "type": "Feature",
  "properties": {
    "iso:country": "GB",
    "wof:name": "LE9 1UT",
    "wof:placetype": "postalcode"
  },
  "geometry": {"coordinates":[-1.191353,52.551864],"type":"Point"}
}
