{
  "type": "Feature",
  "properties": {
    "date:inception_lower": "2014-09-01",
    "date:inception_upper": "2014-09-01",
    "iso:country": "GB",
    "wof:name": "ML5 4QG",
    "wof:placetype": "postalcode"
  },
  "geometry": {"coordinates":[-4.006518,55.851521],"type":"Point"}
}
