{
  "type": "Feature",
  "properties": {
    "iso:country":"GB",
    "wof:name":"YO26 6GB",
    "wof:placetype":"postalcode"
},
  "geometry": {"coordinates":[-1.13359584866692,53.9735870268364],"type":"Point"}
}