{
  "type": "Feature",
  "properties": {
    "date:inception_lower": "1998-06-01",
    "date:inception_upper": "1998-06-01",
    "iso:country": "GB",
    "wof:name": "YO26 6GB",
    "wof:placetype": "postalcode"
  },
  "geometry": {"coordinates":[-1.133596,53.973587],"type":"Point"}
}
