{
  "type": "Feature",
  "properties": {
    "iso:country": "GB",
    "wof:name": "YO26 6GB",
    "wof:placetype": "postalcode"
  },
  "geometry": {"coordinates":[-1.133596,53.973587],"type":"Point"}
}
