{
  "type": "Feature",
  "properties": {
    "iso:country":"GB",
    "wof:name":"EX4 3LQ",
    "wof:placetype":"postalcode"
},
  "geometry": {"coordinates":[-3.52868949705821,50.72529262373921],"type":"Point"}
}