{
  "type": "Feature",
  "properties": {
    "iso:country":"GB",
    "wof:name":"W1D 3JP",
    "wof:placetype":"postalcode"
},
  "geometry": {"coordinates":[-0.13229450677616,51.51439505425855],"type":"Point"}
}