{
  "type": "Feature",
  "properties": {
    "iso:country":"GB",
    "wof:name":"SK8 1LW",
    "wof:placetype":"postalcode"
},
  "geometry": {"coordinates":[-2.22279550289222,53.38666298420884],"type":"Point"}
}