{
  "type": "Feature",
  "properties": {
    "iso:country":"GB",
    "wof:name":"CH7 5UE",
    "wof:placetype":"postalcode"
},
  "geometry": {"coordinates":[-3.30244202331911,53.23310238597461],"type":"Point"}
}