{
  "type": "Feature",
  "properties": {
    "iso:country":"GB",
    "wof:name":"WF10 4NL",
    "wof:placetype":"postalcode"
},
  "geometry": {"coordinates":[-1.3479431935436,53.71790933572421],"type":"Point"}
}