{
  "type": "Feature",
  "properties": {
    "iso:country":"GB",
    "wof:name":"WD23 3BW",
    "wof:placetype":"postalcode"
},
  "geometry": {"coordinates":[-0.36094084973254,51.64446767761642],"type":"Point"}
}