{
  "type": "Feature",
  "properties": {
    "iso:country":"GB",
    "wof:name":"PE6 7UY",
    "wof:placetype":"postalcode"
},
  "geometry": {"coordinates":[-0.19247559052982,52.60864614888802],"type":"Point"}
}