{
  "type": "Feature",
  "properties": {
    "iso:country":"GB",
    "wof:name":"SY4 5NA",
    "wof:placetype":"postalcode"
},
  "geometry": {"coordinates":[-2.75353703096747,52.86642670533287],"type":"Point"}
}