{
  "type": "Feature",
  "properties": {
    "iso:country": "GB",
    "wof:name": "SY4 5NA",
    "wof:placetype": "postalcode"
  },
  "geometry": {"coordinates":[-2.753431,52.866496],"type":"Point"}
}
