{
  "type": "Feature",
  "properties": {
    "iso:country": "GB",
    "wof:name": "NE6 4PZ",
    "wof:placetype": "postalcode"
  },
  "geometry": {"coordinates":[-1.56291,54.989667],"type":"Point"}
}
