{
  "type": "Feature",
  "properties": {
    "date:inception_lower":"1995-07-01",
    "date:inception_upper":"1995-07-31",
    "iso:country":"GB",
    "wof:name":"NE6 4PZ",
    "wof:placetype":"postalcode"
},
  "geometry": {"coordinates":[-1.56291,54.989667],"type":"Point"}
}