{
  "type": "Feature",
  "properties": {
    "iso:country":"GB",
    "wof:name":"NE6 4PZ",
    "wof:placetype":"postalcode"
},
  "geometry": {"coordinates":[-1.56290980686941,54.98966736125099],"type":"Point"}
}