{
  "type": "Feature",
  "properties": {
    "date:inception_lower": "1995-01-01",
    "date:inception_upper": "1995-01-01",
    "iso:country": "GB",
    "wof:name": "BA16 0AF",
    "wof:placetype": "postalcode"
  },
  "geometry": {"coordinates":[-2.731498,51.131865],"type":"Point"}
}
