{
  "type": "Feature",
  "properties": {
    "iso:country": "GB",
    "wof:name": "BA16 0AF",
    "wof:placetype": "postalcode"
  },
  "geometry": {"coordinates":[-2.731498,51.131865],"type":"Point"}
}
