{
  "type": "Feature",
  "properties": {
    "iso:country": "GB",
    "wof:name": "NE8 1YA",
    "wof:placetype": "postalcode"
  },
  "geometry": {"coordinates":[-1.612912,54.953155],"type":"Point"}
}
