{
  "type": "Feature",
  "properties": {
    "iso:country": "GB",
    "wof:name": "DE3 0FQ",
    "wof:placetype": "postalcode"
  },
  "geometry": {"coordinates":[-1.548031,52.92222],"type":"Point"}
}
