{
  "type": "Feature",
  "properties": {
    "iso:country":"GB",
    "wof:name":"M20 2EB",
    "wof:placetype":"postalcode"
},
  "geometry": {"coordinates":[-2.24870282875589,53.43078159726748],"type":"Point"}
}