{
  "type": "Feature",
  "properties": {
    "date:inception_lower": "2003-09-01",
    "date:inception_upper": "2003-09-01",
    "iso:country": "GB",
    "wof:name": "M20 2EB",
    "wof:placetype": "postalcode"
  },
  "geometry": {"coordinates":[-2.248703,53.430782],"type":"Point"}
}
