{
  "type": "Feature",
  "properties": {
    "iso:country":"GB",
    "wof:name":"DL2 2FB",
    "wof:placetype":"postalcode"
},
  "geometry": {"coordinates":[-1.59184996831539,54.54648701582527],"type":"Point"}
}