{
  "type": "Feature",
  "properties": {
    "date:inception_lower": "2008-02-01",
    "date:inception_upper": "2008-02-01",
    "iso:country": "GB",
    "wof:name": "DL2 2FB",
    "wof:placetype": "postalcode"
  },
  "geometry": {"coordinates":[-1.59185,54.546487],"type":"Point"}
}
