{
  "type": "Feature",
  "properties": {
    "iso:country": "GB",
    "wof:name": "DL2 2FB",
    "wof:placetype": "postalcode"
  },
  "geometry": {"coordinates":[-1.59185,54.546487],"type":"Point"}
}
