{
  "type": "Feature",
  "properties": {
    "iso:country":"GB",
    "wof:name":"SR4 7TE",
    "wof:placetype":"postalcode"
},
  "geometry": {"coordinates":[-1.41204316363656,54.90121703753282],"type":"Point"}
}