{
  "type": "Feature",
  "properties": {
    "iso:country":"GB",
    "wof:name":"BA11 2QP",
    "wof:placetype":"postalcode"
},
  "geometry": {"coordinates":[-2.35176267851809,51.25810974013584],"type":"Point"}
}