{
  "type": "Feature",
  "properties": {
    "iso:country": "GB",
    "wof:name": "LE16 9UY",
    "wof:placetype": "postalcode"
  },
  "geometry": {"coordinates":[-0.966565,52.478642],"type":"Point"}
}
