{
  "type": "Feature",
  "properties": {
    "date:inception_lower": "2022-06-01",
    "date:inception_upper": "2022-06-01",
    "iso:country": "GB",
    "wof:name": "MK17 7AU",
    "wof:placetype": "postalcode"
  },
  "geometry": {"coordinates":[-0.645777,52.036264],"type":"Point"}
}
