{
  "type": "Feature",
  "properties": {
    "date:inception_lower":"2016-04-01",
    "date:inception_upper":"2016-04-30",
    "iso:country":"GB",
    "wof:name":"IV17 0UZ",
    "wof:placetype":"postalcode"
},
  "geometry": {"coordinates":[-4.245578,57.695304],"type":"Point"}
}