{
  "type": "Feature",
  "properties": {
    "iso:country":"GB",
    "wof:name":"DE22 4JN",
    "wof:placetype":"postalcode"
},
  "geometry": {"coordinates":[-1.5242083696591,52.92623520519317],"type":"Point"}
}