{
  "type": "Feature",
  "properties": {
    "iso:country":"GB",
    "wof:name":"SE19 2NU",
    "wof:placetype":"postalcode"
},
  "geometry": {"coordinates":[-0.08529444422137,51.41398977204648],"type":"Point"}
}