{
  "type": "Feature",
  "properties": {
    "iso:country":"GB",
    "wof:name":"NR18 0NT",
    "wof:placetype":"postalcode"
},
  "geometry": {"coordinates":[1.12048361621282,52.57321488713003],"type":"Point"}
}