{
  "type": "Feature",
  "properties": {
    "iso:country": "GB",
    "wof:name": "LE17 4GB",
    "wof:placetype": "postalcode"
  },
  "geometry": {"coordinates":[-1.201549,52.468639],"type":"Point"}
}
