{
  "type": "Feature",
  "properties": {
    "iso:country":"GB",
    "wof:name":"LE17 4GB",
    "wof:placetype":"postalcode"
},
  "geometry": {"coordinates":[-1.2015495023476,52.46863918584386],"type":"Point"}
}