{
  "type": "Feature",
  "properties": {
    "iso:country":"GB",
    "wof:name":"BN15 9RE",
    "wof:placetype":"postalcode"
},
  "geometry": {"coordinates":[-0.32880929967544,50.83645338666922],"type":"Point"}
}