{
  "type": "Feature",
  "properties": {
    "date:inception_lower": "1980-01-01",
    "date:inception_upper": "1980-01-01",
    "iso:country": "GB",
    "wof:name": "BN15 9RE",
    "wof:placetype": "postalcode"
  },
  "geometry": {"coordinates":[-0.328809,50.836453],"type":"Point"}
}
