{
  "type": "Feature",
  "properties": {
    "date:inception_lower": "2019-04-01",
    "date:inception_upper": "2019-04-01",
    "iso:country": "GB",
    "wof:name": "G3 6QG",
    "wof:placetype": "postalcode"
  },
  "geometry": {"coordinates":[-4.268649,55.868139],"type":"Point"}
}
