{
  "type": "Feature",
  "properties": {
    "date:inception_lower":"1994-05-01",
    "date:inception_upper":"1994-05-31",
    "iso:country":"GB",
    "wof:name":"BN2 6PR",
    "wof:placetype":"postalcode"
},
  "geometry": {"coordinates":[-0.073908,50.837093],"type":"Point"}
}