{
  "type": "Feature",
  "properties": {
    "iso:country":"GB",
    "wof:name":"PO21 3HG",
    "wof:placetype":"postalcode"
},
  "geometry": {"coordinates":[-0.71721675182538,50.78459668748538],"type":"Point"}
}