{
  "type": "Feature",
  "properties": {
    "date:inception_lower": "1996-06-01",
    "date:inception_upper": "1996-06-01",
    "iso:country": "GB",
    "wof:name": "AB54 7LN",
    "wof:placetype": "postalcode"
  },
  "geometry": {"coordinates":[-2.755342,57.554067],"type":"Point"}
}
