{
  "type": "Feature",
  "properties": {
    "iso:country":"GB",
    "wof:name":"AB54 7LN",
    "wof:placetype":"postalcode"
},
  "geometry": {"coordinates":[-2.75534202011859,57.55406665168977],"type":"Point"}
}