{
  "type": "Feature",
  "properties": {
    "iso:country":"GB",
    "wof:name":"TF1 3HR",
    "wof:placetype":"postalcode"
},
  "geometry": {"coordinates":[-2.5293597947346,52.70866616298298],"type":"Point"}
}