{
  "type": "Feature",
  "properties": {
    "date:inception_lower": "2007-09-01",
    "date:inception_upper": "2007-09-01",
    "iso:country": "GB",
    "wof:name": "LA9 4SN",
    "wof:placetype": "postalcode"
  },
  "geometry": {"coordinates":[-2.748427,54.333676],"type":"Point"}
}
