{
  "type": "Feature",
  "properties": {
    "iso:country": "GB",
    "wof:name": "IP24 2LU",
    "wof:placetype": "postalcode"
  },
  "geometry": {"coordinates":[0.756397,52.418869],"type":"Point"}
}
