{
  "type": "Feature",
  "properties": {
    "date:inception_lower": "2011-06-01",
    "date:inception_upper": "2011-06-01",
    "iso:country": "GB",
    "wof:name": "CA11 0FE",
    "wof:placetype": "postalcode"
  },
  "geometry": {"coordinates":[-2.892263,54.643863],"type":"Point"}
}
