{
  "type": "Feature",
  "properties": {
    "iso:country": "GB",
    "wof:name": "CA11 0FE",
    "wof:placetype": "postalcode"
  },
  "geometry": {"coordinates":[-2.892433,54.643861],"type":"Point"}
}
