{
  "type": "Feature",
  "properties": {
    "iso:country":"GB",
    "wof:name":"L24 4BJ",
    "wof:placetype":"postalcode"
},
  "geometry": {"coordinates":[-2.79528160014558,53.33687652734499],"type":"Point"}
}