{
  "type": "Feature",
  "properties": {
    "iso:country": "GB",
    "wof:name": "L24 4BJ",
    "wof:placetype": "postalcode"
  },
  "geometry": {"coordinates":[-2.795282,53.336877],"type":"Point"}
}
