{
  "type": "Feature",
  "properties": {
    "iso:country":"GB",
    "wof:name":"SP5 1RP",
    "wof:placetype":"postalcode"
},
  "geometry": {"coordinates":[-1.66463312129186,51.0981558758624],"type":"Point"}
}