{
  "type": "Feature",
  "properties": {
    "iso:country": "GB",
    "wof:name": "NN3 9ST",
    "wof:placetype": "postalcode"
  },
  "geometry": {"coordinates":[-0.833415,52.25094],"type":"Point"}
}
