{
  "type": "Feature",
  "properties": {
    "iso:country":"GB",
    "wof:name":"NN3 9ST",
    "wof:placetype":"postalcode"
},
  "geometry": {"coordinates":[-0.83341534309716,52.25094033167731],"type":"Point"}
}