{
  "type": "Feature",
  "properties": {
    "iso:country":"GB",
    "wof:name":"TR14 9AU",
    "wof:placetype":"postalcode"
},
  "geometry": {"coordinates":[-5.27297462645045,50.21122510597155],"type":"Point"}
}