{
  "type": "Feature",
  "properties": {
    "iso:country":"GB",
    "wof:name":"TW15 1PN",
    "wof:placetype":"postalcode"
},
  "geometry": {"coordinates":[-0.43960195607714,51.42922393222715],"type":"Point"}
}