{
  "type": "Feature",
  "properties": {
    "iso:country":"GB",
    "wof:name":"SK9 1HB",
    "wof:placetype":"postalcode"
},
  "geometry": {"coordinates":[-2.23165463585117,53.32641320216209],"type":"Point"}
}