{
  "type": "Feature",
  "properties": {
    "iso:country":"GB",
    "wof:name":"TN4 9DJ",
    "wof:placetype":"postalcode"
},
  "geometry": {"coordinates":[0.27347490413834,51.15325558760415],"type":"Point"}
}