{
  "type": "Feature",
  "properties": {
    "iso:country": "GB",
    "wof:name": "ML9 3RJ",
    "wof:placetype": "postalcode"
  },
  "geometry": {"coordinates":[-3.992716,55.695151],"type":"Point"}
}
