{
  "type": "Feature",
  "properties": {
    "iso:country":"GB",
    "wof:name":"ML9 3RJ",
    "wof:placetype":"postalcode"
},
  "geometry": {"coordinates":[-3.99271575359558,55.69515096547889],"type":"Point"}
}