{
  "type": "Feature",
  "properties": {
    "date:inception_lower":"1987-04-01",
    "date:inception_upper":"1987-04-30",
    "iso:country":"GB",
    "wof:name":"BH24 1SB",
    "wof:placetype":"postalcode"
},
  "geometry": {"coordinates":[-1.779301,50.857759],"type":"Point"}
}