{
  "type": "Feature",
  "properties": {
    "iso:country":"GB",
    "wof:name":"SW17 7NS",
    "wof:placetype":"postalcode"
},
  "geometry": {"coordinates":[-0.16547586594496,51.43245720599503],"type":"Point"}
}