{
  "type": "Feature",
  "properties": {
    "iso:country":"GB",
    "wof:name":"DH2 1EB",
    "wof:placetype":"postalcode"
},
  "geometry": {"coordinates":[-1.60777482848631,54.87130847786504],"type":"Point"}
}