{
  "type": "Feature",
  "properties": {
    "iso:country": "GB",
    "wof:name": "NG19 8FF",
    "wof:placetype": "postalcode"
  },
  "geometry": {"coordinates":[-1.193099,53.178605],"type":"Point"}
}
