{
  "type": "Feature",
  "properties": {
    "iso:country": "GB",
    "wof:name": "PL30 4BL",
    "wof:placetype": "postalcode"
  },
  "geometry": {"coordinates":[-4.647146,50.487634],"type":"Point"}
}
