{
  "type": "Feature",
  "properties": {
    "date:inception_lower": "2022-08-01",
    "date:inception_upper": "2022-08-01",
    "iso:country": "GB",
    "wof:name": "CB6 2FW",
    "wof:placetype": "postalcode"
  },
  "geometry": {"coordinates":[0.262311,52.409954],"type":"Point"}
}
