{
  "type": "Feature",
  "properties": {
    "iso:country":"GB",
    "wof:name":"NE63 9QQ",
    "wof:placetype":"postalcode"
},
  "geometry": {"coordinates":[-1.54936596178927,55.17316864221203],"type":"Point"}
}