{
  "type": "Feature",
  "properties": {
    "iso:country":"GB",
    "wof:name":"PA31 8UY",
    "wof:placetype":"postalcode"
},
  "geometry": {"coordinates":[-5.42553107047424,56.04022381618459],"type":"Point"}
}