{
  "type": "Feature",
  "properties": {
    "date:inception_lower": "2011-07-01",
    "date:inception_upper": "2011-07-01",
    "iso:country": "GB",
    "wof:name": "PA31 8UY",
    "wof:placetype": "postalcode"
  },
  "geometry": {"coordinates":[-5.425084,56.040558],"type":"Point"}
}
