{
  "type": "Feature",
  "properties": {
    "iso:country":"GB",
    "wof:name":"WC1A 2JA",
    "wof:placetype":"postalcode"
},
  "geometry": {"coordinates":[-0.12447523852961,51.51809210115631],"type":"Point"}
}