{
  "type": "Feature",
  "properties": {
    "iso:country": "GB",
    "wof:name": "WC1A 2JA",
    "wof:placetype": "postalcode"
  },
  "geometry": {"coordinates":[-0.124475,51.518092],"type":"Point"}
}
