{
  "type": "Feature",
  "properties": {
    "iso:country":"GB",
    "wof:name":"CA5 7AP",
    "wof:placetype":"postalcode"
},
  "geometry": {"coordinates":[-2.93491353040489,54.82497074679346],"type":"Point"}
}