{
  "type": "Feature",
  "properties": {
    "date:inception_lower": "1980-01-01",
    "date:inception_upper": "1980-01-01",
    "iso:country": "GB",
    "wof:name": "CA5 7AP",
    "wof:placetype": "postalcode"
  },
  "geometry": {"coordinates":[-2.934869,54.824879],"type":"Point"}
}
