{
  "type": "Feature",
  "properties": {
    "date:inception_lower": "1992-05-01",
    "date:inception_upper": "1992-05-01",
    "iso:country": "GB",
    "wof:name": "KY1 2EL",
    "wof:placetype": "postalcode"
  },
  "geometry": {"coordinates":[-3.148412,56.126302],"type":"Point"}
}
