{
  "type": "Feature",
  "properties": {
    "date:inception_lower": "1980-01-01",
    "date:inception_upper": "1980-01-01",
    "iso:country": "GB",
    "wof:name": "PR1 6XX",
    "wof:placetype": "postalcode"
  },
  "geometry": {"coordinates":[-2.682692,53.770892],"type":"Point"}
}
