{
  "type": "Feature",
  "properties": {
    "iso:country": "GB",
    "wof:name": "RG4 8AL",
    "wof:placetype": "postalcode"
  },
  "geometry": {"coordinates":[-0.976109,51.465862],"type":"Point"}
}
