{
  "type": "Feature",
  "properties": {
    "date:inception_lower": "1980-01-01",
    "date:inception_upper": "1980-01-01",
    "iso:country": "GB",
    "wof:name": "S43 1AJ",
    "wof:placetype": "postalcode"
  },
  "geometry": {"coordinates":[-1.402764,53.255383],"type":"Point"}
}
