{
  "type": "Feature",
  "properties": {
    "iso:country":"GB",
    "wof:name":"GL18 1NY",
    "wof:placetype":"postalcode"
},
  "geometry": {"coordinates":[-2.45899647270872,51.92505206935488],"type":"Point"}
}