{
  "type": "Feature",
  "properties": {
    "iso:country": "GB",
    "wof:name": "HA5 5JR",
    "wof:placetype": "postalcode"
  },
  "geometry": {"coordinates":[-0.380584,51.586795],"type":"Point"}
}
