{
  "type": "Feature",
  "properties": {
    "iso:country":"GB",
    "wof:name":"HA5 5JR",
    "wof:placetype":"postalcode"
},
  "geometry": {"coordinates":[-0.38058438214728,51.58679510187452],"type":"Point"}
}