{
  "type": "Feature",
  "properties": {
    "iso:country": "GB",
    "wof:name": "RH17 7AJ",
    "wof:placetype": "postalcode"
  },
  "geometry": {"coordinates":[-0.024429,51.035497],"type":"Point"}
}
