{
  "type": "Feature",
  "properties": {
    "date:inception_lower":"2011-06-01",
    "date:inception_upper":"2011-06-30",
    "iso:country":"GB",
    "wof:name":"GU1 2ST",
    "wof:placetype":"postalcode"
},
  "geometry": {"coordinates":[-0.543049,51.240223],"type":"Point"}
}