{
  "type": "Feature",
  "properties": {
    "iso:country":"GB",
    "wof:name":"GU1 2ST",
    "wof:placetype":"postalcode"
},
  "geometry": {"coordinates":[-0.54304902441487,51.24022312712326],"type":"Point"}
}