{
  "type": "Feature",
  "properties": {
    "date:inception_lower": "1980-01-01",
    "date:inception_upper": "1980-01-01",
    "iso:country": "GB",
    "wof:name": "WA6 9EA",
    "wof:placetype": "postalcode"
  },
  "geometry": {"coordinates":[-2.744432,53.248097],"type":"Point"}
}
