{
  "type": "Feature",
  "properties": {
    "iso:country":"GB",
    "wof:name":"MK44 3QG",
    "wof:placetype":"postalcode"
},
  "geometry": {"coordinates":[-0.37349392901135,52.13853943888594],"type":"Point"}
}