{
  "type": "Feature",
  "properties": {
    "iso:country":"GB",
    "wof:name":"EX31 4TL",
    "wof:placetype":"postalcode"
},
  "geometry": {"coordinates":[-3.93176646322777,51.12424570326546],"type":"Point"}
}