{
  "type": "Feature",
  "properties": {
    "iso:country":"GB",
    "wof:name":"DD4 9LG",
    "wof:placetype":"postalcode"
},
  "geometry": {"coordinates":[-2.9377284111118,56.48932856695951],"type":"Point"}
}