{
  "type": "Feature",
  "properties": {
    "iso:country":"GB",
    "wof:name":"ME6 5RQ",
    "wof:placetype":"postalcode"
},
  "geometry": {"coordinates":[0.4335843567196,51.33077739539676],"type":"Point"}
}