{
  "type": "Feature",
  "properties": {
    "date:inception_lower": "1981-06-01",
    "date:inception_upper": "1981-06-01",
    "iso:country": "GB",
    "wof:name": "ME6 5RQ",
    "wof:placetype": "postalcode"
  },
  "geometry": {"coordinates":[0.433584,51.330777],"type":"Point"}
}
