{
  "type": "Feature",
  "properties": {
    "iso:country":"GB",
    "wof:name":"SR4 6NW",
    "wof:placetype":"postalcode"
},
  "geometry": {"coordinates":[-1.41491847383645,54.90726082050116],"type":"Point"}
}