{
  "type": "Feature",
  "properties": {
    "iso:country":"GB",
    "wof:name":"DE21 5EE",
    "wof:placetype":"postalcode"
},
  "geometry": {"coordinates":[-1.46133849299049,52.97356558402848],"type":"Point"}
}