{
  "type": "Feature",
  "properties": {
    "iso:country": "GB",
    "wof:name": "DE21 5EE",
    "wof:placetype": "postalcode"
  },
  "geometry": {"coordinates":[-1.461338,52.973566],"type":"Point"}
}
