{
  "type": "Feature",
  "properties": {
    "iso:country":"GB",
    "wof:name":"TS4 2XW",
    "wof:placetype":"postalcode"
},
  "geometry": {"coordinates":[-1.22682428792728,54.55635293821422],"type":"Point"}
}