{
  "type": "Feature",
  "properties": {
    "iso:country": "GB",
    "wof:name": "CA6 5UY",
    "wof:placetype": "postalcode"
  },
  "geometry": {"coordinates":[-2.971358,55.008999],"type":"Point"}
}
