{
  "type": "Feature",
  "properties": {
    "iso:country":"GB",
    "wof:name":"CA6 5UY",
    "wof:placetype":"postalcode"
},
  "geometry": {"coordinates":[-2.97102817526178,55.00906759869063],"type":"Point"}
}