{
  "type": "Feature",
  "properties": {
    "iso:country": "GB",
    "wof:name": "DN36 5LL",
    "wof:placetype": "postalcode"
  },
  "geometry": {"coordinates":[-0.029642,53.502138],"type":"Point"}
}
