{
  "type": "Feature",
  "properties": {
    "iso:country":"GB",
    "wof:name":"DN36 5LL",
    "wof:placetype":"postalcode"
},
  "geometry": {"coordinates":[-0.02964231921535,53.50213754257555],"type":"Point"}
}