{
  "type": "Feature",
  "properties": {
    "iso:country":"GB",
    "wof:name":"WF10 9BY",
    "wof:placetype":"postalcode"
},
  "geometry": {"coordinates":[-1.3903328703681,53.71643364667131],"type":"Point"}
}