{
  "type": "Feature",
  "properties": {
    "date:inception_lower": "1999-06-01",
    "date:inception_upper": "1999-06-01",
    "iso:country": "GB",
    "wof:name": "BH14 0DE",
    "wof:placetype": "postalcode"
  },
  "geometry": {"coordinates":[-1.945345,50.727023],"type":"Point"}
}
