{
  "type": "Feature",
  "properties": {
    "date:inception_lower": "2011-03-01",
    "date:inception_upper": "2011-03-01",
    "iso:country": "GB",
    "wof:name": "M24 4JS",
    "wof:placetype": "postalcode"
  },
  "geometry": {"coordinates":[-2.233203,53.543744],"type":"Point"}
}
