{
  "type": "Feature",
  "properties": {
    "iso:country":"GB",
    "wof:name":"PE7 3WE",
    "wof:placetype":"postalcode"
},
  "geometry": {"coordinates":[-0.24728385322615,52.52241080305978],"type":"Point"}
}