{
  "type": "Feature",
  "properties": {
    "iso:country":"GB",
    "wof:name":"LS12 2SP",
    "wof:placetype":"postalcode"
},
  "geometry": {"coordinates":[-1.60760109063423,53.80809421953255],"type":"Point"}
}