{
  "type": "Feature",
  "properties": {
    "iso:country":"GB",
    "wof:name":"ST9 0AB",
    "wof:placetype":"postalcode"
},
  "geometry": {"coordinates":[-2.03897576740704,53.04136087022309],"type":"Point"}
}