{
  "type": "Feature",
  "properties": {
    "date:inception_lower": "1980-01-01",
    "date:inception_upper": "1980-01-01",
    "iso:country": "GB",
    "wof:name": "ST9 0AB",
    "wof:placetype": "postalcode"
  },
  "geometry": {"coordinates":[-2.032294,53.043996],"type":"Point"}
}
