{
  "type": "Feature",
  "properties": {
    "iso:country":"GB",
    "wof:name":"CV12 0AA",
    "wof:placetype":"postalcode"
},
  "geometry": {"coordinates":[-1.48955838431643,52.47999504214109],"type":"Point"}
}