{
  "type": "Feature",
  "properties": {
    "date:inception_lower": "1980-01-01",
    "date:inception_upper": "1980-01-01",
    "iso:country": "GB",
    "wof:name": "CV12 0AA",
    "wof:placetype": "postalcode"
  },
  "geometry": {"coordinates":[-1.489558,52.479995],"type":"Point"}
}
