{
  "type": "Feature",
  "properties": {
    "iso:country": "GB",
    "wof:name": "WA4 5LY",
    "wof:placetype": "postalcode"
  },
  "geometry": {"coordinates":[-2.566996,53.359582],"type":"Point"}
}
