{
  "type": "Feature",
  "properties": {
    "iso:country":"GB",
    "wof:name":"G83 9DX",
    "wof:placetype":"postalcode"
},
  "geometry": {"coordinates":[-4.56347849172451,55.98083489584761],"type":"Point"}
}