{
  "type": "Feature",
  "properties": {
    "iso:country": "GB",
    "wof:name": "WF9 4JX",
    "wof:placetype": "postalcode"
  },
  "geometry": {"coordinates":[-1.35431,53.612887],"type":"Point"}
}
