{
  "type": "Feature",
  "properties": {
    "iso:country":"GB",
    "wof:name":"WF9 4JX",
    "wof:placetype":"postalcode"
},
  "geometry": {"coordinates":[-1.35455070636058,53.61283562972415],"type":"Point"}
}