{
  "type": "Feature",
  "properties": {
    "iso:country":"GB",
    "wof:name":"TF2 8HG",
    "wof:placetype":"postalcode"
},
  "geometry": {"coordinates":[-2.43672416577391,52.71651416222573],"type":"Point"}
}