{
  "type": "Feature",
  "properties": {
    "iso:country":"GB",
    "wof:name":"WA1 3UD",
    "wof:placetype":"postalcode"
},
  "geometry": {"coordinates":[-2.54903328611315,53.39756274016027],"type":"Point"}
}