{
  "type": "Feature",
  "properties": {
    "iso:country": "GB",
    "wof:name": "WA1 3UD",
    "wof:placetype": "postalcode"
  },
  "geometry": {"coordinates":[-2.549033,53.397563],"type":"Point"}
}
