{
  "type": "Feature",
  "properties": {
    "iso:country":"GB",
    "wof:name":"SA8 4DF",
    "wof:placetype":"postalcode"
},
  "geometry": {"coordinates":[-3.87675590552414,51.70228210165908],"type":"Point"}
}