{
  "type": "Feature",
  "properties": {
    "date:inception_lower": "1997-06-01",
    "date:inception_upper": "1997-06-01",
    "iso:country": "GB",
    "wof:name": "SA8 4DF",
    "wof:placetype": "postalcode"
  },
  "geometry": {"coordinates":[-3.876756,51.702282],"type":"Point"}
}
