{
  "type": "Feature",
  "properties": {
    "iso:country":"GB",
    "wof:name":"TA24 6NB",
    "wof:placetype":"postalcode"
},
  "geometry": {"coordinates":[-3.41723632584526,51.17247813720038],"type":"Point"}
}