{
  "type": "Feature",
  "properties": {
    "iso:country":"GB",
    "wof:name":"BA3 4UB",
    "wof:placetype":"postalcode"
},
  "geometry": {"coordinates":[-2.54443535823035,51.25073578248336],"type":"Point"}
}