{
  "type": "Feature",
  "properties": {
    "iso:country":"GB",
    "wof:name":"OL6 9PQ",
    "wof:placetype":"postalcode"
},
  "geometry": {"coordinates":[-2.08477317260832,53.49201549979886],"type":"Point"}
}