{
  "type": "Feature",
  "properties": {
    "iso:country": "GB",
    "wof:name": "HU17 7JF",
    "wof:placetype": "postalcode"
  },
  "geometry": {"coordinates":[-0.439016,53.854113],"type":"Point"}
}
