{
  "type": "Feature",
  "properties": {
    "date:inception_lower": "2021-07-01",
    "date:inception_upper": "2021-07-01",
    "iso:country": "GB",
    "wof:name": "BA2 7PT",
    "wof:placetype": "postalcode"
  },
  "geometry": {"coordinates":[-2.322256,51.301414],"type":"Point"}
}
