{
  "type": "Feature",
  "properties": {
    "iso:country":"GB",
    "wof:name":"KT20 6HA",
    "wof:placetype":"postalcode"
},
  "geometry": {"coordinates":[-0.21229055354256,51.29556628286019],"type":"Point"}
}