{
  "type": "Feature",
  "properties": {
    "date:inception_lower": "1980-01-01",
    "date:inception_upper": "1980-01-01",
    "iso:country": "GB",
    "wof:name": "B38 9TU",
    "wof:placetype": "postalcode"
  },
  "geometry": {"coordinates":[-1.935824,52.394486],"type":"Point"}
}
