{
  "type": "Feature",
  "properties": {
    "date:inception_lower":"2007-08-01",
    "date:inception_upper":"2007-08-31",
    "iso:country":"GB",
    "wof:name":"S97 3ZX",
    "wof:placetype":"postalcode"
},
  "geometry": {"coordinates":[-1.332929,53.508603],"type":"Point"}
}