{
  "type": "Feature",
  "properties": {
    "iso:country":"GB",
    "wof:name":"S97 3ZX",
    "wof:placetype":"postalcode"
},
  "geometry": {"coordinates":[-1.33292901523949,53.508603414183],"type":"Point"}
}