{
  "type": "Feature",
  "properties": {
    "iso:country":"GB",
    "wof:name":"BA1 5PN",
    "wof:placetype":"postalcode"
},
  "geometry": {"coordinates":[-2.36316918317505,51.39240298444417],"type":"Point"}
}