{
  "type": "Feature",
  "properties": {
    "date:inception_lower": "1980-01-01",
    "date:inception_upper": "1980-01-01",
    "iso:country": "GB",
    "wof:name": "BA1 5PN",
    "wof:placetype": "postalcode"
  },
  "geometry": {"coordinates":[-2.363008,51.392247],"type":"Point"}
}
