{
  "type": "Feature",
  "properties": {
    "iso:country":"GB",
    "wof:name":"HX3 8NG",
    "wof:placetype":"postalcode"
},
  "geometry": {"coordinates":[-1.81015200400046,53.72575182735594],"type":"Point"}
}