{
  "type": "Feature",
  "properties": {
    "iso:country":"GB",
    "wof:name":"SK10 3DP",
    "wof:placetype":"postalcode"
},
  "geometry": {"coordinates":[-2.14411804157022,53.26690207595561],"type":"Point"}
}