{
  "type": "Feature",
  "properties": {
    "iso:country":"GB",
    "wof:name":"G75 0QZ",
    "wof:placetype":"postalcode"
},
  "geometry": {"coordinates":[-4.14542562289031,55.74828041426871],"type":"Point"}
}