{
  "type": "Feature",
  "properties": {
    "iso:country": "GB",
    "wof:name": "G75 0QZ",
    "wof:placetype": "postalcode"
  },
  "geometry": {"coordinates":[-4.145426,55.74828],"type":"Point"}
}
