{
  "type": "Feature",
  "properties": {
    "date:inception_lower":"1993-01-01",
    "date:inception_upper":"1993-01-31",
    "iso:country":"GB",
    "wof:name":"SN8 1UR",
    "wof:placetype":"postalcode"
},
  "geometry": {"coordinates":[-1.746437,51.41849],"type":"Point"}
}