{
  "type": "Feature",
  "properties": {
    "iso:country":"GB",
    "wof:name":"SN8 1UR",
    "wof:placetype":"postalcode"
},
  "geometry": {"coordinates":[-1.74643674389608,51.41848975643759],"type":"Point"}
}