{
  "type": "Feature",
  "properties": {
    "date:inception_lower":"2008-01-01",
    "date:inception_upper":"2008-01-31",
    "iso:country":"GB",
    "wof:name":"NR24 2SB",
    "wof:placetype":"postalcode"
},
  "geometry": {"coordinates":[1.063714,52.84823],"type":"Point"}
}