{
  "type": "Feature",
  "properties": {
    "iso:country":"GB",
    "wof:name":"NR24 2SB",
    "wof:placetype":"postalcode"
},
  "geometry": {"coordinates":[1.0637144120545,52.8482301798987],"type":"Point"}
}