{
  "type": "Feature",
  "properties": {
    "iso:country": "GB",
    "wof:name": "NR24 2SB",
    "wof:placetype": "postalcode"
  },
  "geometry": {"coordinates":[1.063714,52.84823],"type":"Point"}
}
