{
  "type": "Feature",
  "properties": {
    "date:inception_lower": "1980-01-01",
    "date:inception_upper": "1980-01-01",
    "iso:country": "GB",
    "wof:name": "S6 5HP",
    "wof:placetype": "postalcode"
  },
  "geometry": {"coordinates":[-1.517099,53.39688],"type":"Point"}
}
