{
  "type": "Feature",
  "properties": {
    "iso:country":"GB",
    "wof:name":"ME10 1BF",
    "wof:placetype":"postalcode"
},
  "geometry": {"coordinates":[0.72839457389689,51.34318311474071],"type":"Point"}
}