{
  "type": "Feature",
  "properties": {
    "iso:country": "GB",
    "wof:name": "CA27 0EF",
    "wof:placetype": "postalcode"
  },
  "geometry": {"coordinates":[-3.594566,54.495793],"type":"Point"}
}
