{
  "type": "Feature",
  "properties": {
    "date:inception_lower": "1980-01-01",
    "date:inception_upper": "1980-01-01",
    "iso:country": "GB",
    "wof:name": "CA27 0EF",
    "wof:placetype": "postalcode"
  },
  "geometry": {"coordinates":[-3.594566,54.495793],"type":"Point"}
}
