{
  "type": "Feature",
  "properties": {
    "iso:country":"GB",
    "wof:name":"SG3 6AW",
    "wof:placetype":"postalcode"
},
  "geometry": {"coordinates":[-0.18412450821354,51.86824307283515],"type":"Point"}
}