{
  "type": "Feature",
  "properties": {
    "iso:country":"GB",
    "wof:name":"NG11 0LH",
    "wof:placetype":"postalcode"
},
  "geometry": {"coordinates":[-1.19930353750244,52.86483603282944],"type":"Point"}
}