{
  "type": "Feature",
  "properties": {
    "iso:country":"GB",
    "wof:name":"BN24 5HX",
    "wof:placetype":"postalcode"
},
  "geometry": {"coordinates":[0.31750007142301,50.81846124401233],"type":"Point"}
}