{
  "type": "Feature",
  "properties": {
    "iso:country":"GB",
    "wof:name":"GL56 9BA",
    "wof:placetype":"postalcode"
},
  "geometry": {"coordinates":[-1.76311069118193,52.01347789574473],"type":"Point"}
}