{
  "type": "Feature",
  "properties": {
    "iso:country":"GB",
    "wof:name":"BS4 3TB",
    "wof:placetype":"postalcode"
},
  "geometry": {"coordinates":[-2.57760863747384,51.4427854540851],"type":"Point"}
}