{
  "type": "Feature",
  "properties": {
    "date:inception_lower": "1981-06-01",
    "date:inception_upper": "1981-06-01",
    "iso:country": "GB",
    "wof:name": "SK2 6TB",
    "wof:placetype": "postalcode"
  },
  "geometry": {"coordinates":[-2.136095,53.393929],"type":"Point"}
}
