{
  "type": "Feature",
  "properties": {
    "iso:country": "GB",
    "wof:name": "SK2 6TB",
    "wof:placetype": "postalcode"
  },
  "geometry": {"coordinates":[-2.13614,53.393929],"type":"Point"}
}
