{
  "type": "Feature",
  "properties": {
    "iso:country": "GB",
    "wof:name": "NN11 3TT",
    "wof:placetype": "postalcode"
  },
  "geometry": {"coordinates":[-1.220784,52.166492],"type":"Point"}
}
