{
  "type": "Feature",
  "properties": {
    "iso:country":"GB",
    "wof:name":"BA1 3EB",
    "wof:placetype":"postalcode"
},
  "geometry": {"coordinates":[-2.3900870723443,51.38545576601454],"type":"Point"}
}