{
  "type": "Feature",
  "properties": {
    "iso:country":"GB",
    "wof:name":"MK19 6AT",
    "wof:placetype":"postalcode"
},
  "geometry": {"coordinates":[-0.86452760231518,52.06141000282231],"type":"Point"}
}