{
  "type": "Feature",
  "properties": {
    "iso:country": "GB",
    "wof:name": "NE20 9SJ",
    "wof:placetype": "postalcode"
  },
  "geometry": {"coordinates":[-1.71733,55.045557],"type":"Point"}
}
