{
  "type": "Feature",
  "properties": {
    "iso:country":"GB",
    "wof:name":"NE20 9SJ",
    "wof:placetype":"postalcode"
},
  "geometry": {"coordinates":[-1.71734664816434,55.04560444249545],"type":"Point"}
}