{
  "type": "Feature",
  "properties": {
    "iso:country":"GB",
    "wof:name":"CO4 5HQ",
    "wof:placetype":"postalcode"
},
  "geometry": {"coordinates":[0.89686745913417,51.90628195558687],"type":"Point"}
}