{
  "type": "Feature",
  "properties": {
    "iso:country":"GB",
    "wof:name":"LL12 8PW",
    "wof:placetype":"postalcode"
},
  "geometry": {"coordinates":[-2.98240327716809,53.07954113778149],"type":"Point"}
}