{
  "type": "Feature",
  "properties": {
    "iso:country": "GB",
    "wof:name": "LL12 8PW",
    "wof:placetype": "postalcode"
  },
  "geometry": {"coordinates":[-2.982404,53.079557],"type":"Point"}
}
