{
  "type": "Feature",
  "properties": {
    "iso:country":"GB",
    "wof:name":"N17 6PF",
    "wof:placetype":"postalcode"
},
  "geometry": {"coordinates":[-0.09522920971549,51.58958780818917],"type":"Point"}
}