{
  "type": "Feature",
  "properties": {
    "date:inception_lower": "1980-01-01",
    "date:inception_upper": "1980-01-01",
    "iso:country": "GB",
    "wof:name": "WA14 2RY",
    "wof:placetype": "postalcode"
  },
  "geometry": {"coordinates":[-2.352812,53.375031],"type":"Point"}
}
