{
  "type": "Feature",
  "properties": {
    "iso:country":"GB",
    "wof:name":"WA14 2RY",
    "wof:placetype":"postalcode"
},
  "geometry": {"coordinates":[-2.35281294336125,53.37501462313599],"type":"Point"}
}