{
  "type": "Feature",
  "properties": {
    "iso:country":"GB",
    "wof:name":"NN11 4NL",
    "wof:placetype":"postalcode"
},
  "geometry": {"coordinates":[-1.18543412854925,52.25276046344448],"type":"Point"}
}