{
  "type": "Feature",
  "properties": {
    "iso:country": "GB",
    "wof:name": "N13 6HS",
    "wof:placetype": "postalcode"
  },
  "geometry": {"coordinates":[-0.09822,51.614153],"type":"Point"}
}
