{
  "type": "Feature",
  "properties": {
    "date:inception_lower":"2006-11-01",
    "date:inception_upper":"2006-11-30",
    "iso:country":"GB",
    "wof:name":"PL31 2RZ",
    "wof:placetype":"postalcode"
},
  "geometry": {"coordinates":[-4.734089,50.470934],"type":"Point"}
}