{
  "type": "Feature",
  "properties": {
    "date:inception_lower":"2001-06-01",
    "date:inception_upper":"2001-06-30",
    "iso:country":"GB",
    "wof:name":"W1F 7BX",
    "wof:placetype":"postalcode"
},
  "geometry": {"coordinates":[-0.139167,51.51303],"type":"Point"}
}