{
  "type": "Feature",
  "properties": {
    "iso:country": "GB",
    "wof:name": "BA11 1PA",
    "wof:placetype": "postalcode"
  },
  "geometry": {"coordinates":[-2.317458,51.22313],"type":"Point"}
}
