{
  "type": "Feature",
  "properties": {
    "date:inception_lower": "1980-01-01",
    "date:inception_upper": "1980-01-01",
    "iso:country": "GB",
    "wof:name": "BA11 1PA",
    "wof:placetype": "postalcode"
  },
  "geometry": {"coordinates":[-2.317458,51.22313],"type":"Point"}
}
