{
  "type": "Feature",
  "properties": {
    "date:inception_lower": "1980-01-01",
    "date:inception_upper": "1980-01-01",
    "iso:country": "GB",
    "wof:name": "CA7 8LZ",
    "wof:placetype": "postalcode"
  },
  "geometry": {"coordinates":[-3.133274,54.792435],"type":"Point"}
}
