{
  "type": "Feature",
  "properties": {
    "iso:country":"GB",
    "wof:name":"KA7 2NJ",
    "wof:placetype":"postalcode"
},
  "geometry": {"coordinates":[-4.61917761615115,55.448261580359],"type":"Point"}
}