{
  "type": "Feature",
  "properties": {
    "iso:country": "GB",
    "wof:name": "KA7 2NJ",
    "wof:placetype": "postalcode"
  },
  "geometry": {"coordinates":[-4.619178,55.448262],"type":"Point"}
}
