{
  "type": "Feature",
  "properties": {
    "iso:country":"GB",
    "wof:name":"TA24 7QQ",
    "wof:placetype":"postalcode"
},
  "geometry": {"coordinates":[-3.64049795639485,51.14035080752075],"type":"Point"}
}