{
  "type": "Feature",
  "properties": {
    "iso:country":"GB",
    "wof:name":"SK11 8JZ",
    "wof:placetype":"postalcode"
},
  "geometry": {"coordinates":[-2.14059403940836,53.25301863025719],"type":"Point"}
}