{
  "type": "Feature",
  "properties": {
    "date:inception_lower":"1983-07-01",
    "date:inception_upper":"1983-07-31",
    "iso:country":"GB",
    "wof:name":"CB6 1HD",
    "wof:placetype":"postalcode"
},
  "geometry": {"coordinates":[0.301428,52.455652],"type":"Point"}
}