{
  "type": "Feature",
  "properties": {
    "date:inception_lower": "2019-08-01",
    "date:inception_upper": "2019-08-01",
    "iso:country": "GB",
    "wof:name": "GL52 9EA",
    "wof:placetype": "postalcode"
  },
  "geometry": {"coordinates":[-2.063565,51.965292],"type":"Point"}
}
