{
  "type": "Feature",
  "properties": {
    "date:inception_lower":"1992-01-01",
    "date:inception_upper":"1992-01-31",
    "iso:country":"GB",
    "wof:name":"HU1 3RN",
    "wof:placetype":"postalcode"
},
  "geometry": {"coordinates":[-0.326561,53.744072],"type":"Point"}
}