{
  "type": "Feature",
  "properties": {
    "iso:country":"GB",
    "wof:name":"SS2 5DX",
    "wof:placetype":"postalcode"
},
  "geometry": {"coordinates":[0.71232616313517,51.5490825612214],"type":"Point"}
}