{
  "type": "Feature",
  "properties": {
    "iso:country":"GB",
    "wof:name":"BS37 8UY",
    "wof:placetype":"postalcode"
},
  "geometry": {"coordinates":[-2.42130053038514,51.52621881959984],"type":"Point"}
}