{
  "type": "Feature",
  "properties": {
    "iso:country": "GB",
    "wof:name": "BS37 8UY",
    "wof:placetype": "postalcode"
  },
  "geometry": {"coordinates":[-2.4213,51.526219],"type":"Point"}
}
