{
  "type": "Feature",
  "properties": {
    "iso:country":"GB",
    "wof:name":"LL12 0NA",
    "wof:placetype":"postalcode"
},
  "geometry": {"coordinates":[-2.99117583072363,53.09100178691767],"type":"Point"}
}