{
  "type": "Feature",
  "properties": {
    "date:inception_lower": "1980-01-01",
    "date:inception_upper": "1980-01-01",
    "iso:country": "GB",
    "wof:name": "LL12 0NA",
    "wof:placetype": "postalcode"
  },
  "geometry": {"coordinates":[-2.991176,53.091002],"type":"Point"}
}
