{
  "type": "Feature",
  "properties": {
    "iso:country": "GB",
    "wof:name": "DE7 8LH",
    "wof:placetype": "postalcode"
  },
  "geometry": {"coordinates":[-1.312194,52.983341],"type":"Point"}
}
