{
  "type": "Feature",
  "properties": {
    "iso:country":"GB",
    "wof:name":"DE7 8LH",
    "wof:placetype":"postalcode"
},
  "geometry": {"coordinates":[-1.31219360854161,52.98334111797577],"type":"Point"}
}