{
  "type": "Feature",
  "properties": {
    "date:inception_lower":"1991-09-01",
    "date:inception_upper":"1991-09-30",
    "iso:country":"GB",
    "wof:name":"CB8 8DE",
    "wof:placetype":"postalcode"
},
  "geometry": {"coordinates":[0.40778,52.234824],"type":"Point"}
}