{
  "type": "Feature",
  "properties": {
    "iso:country":"GB",
    "wof:name":"CH45 2LJ",
    "wof:placetype":"postalcode"
},
  "geometry": {"coordinates":[-3.03920601704975,53.43812277402864],"type":"Point"}
}