{
  "type": "Feature",
  "properties": {
    "iso:country":"GB",
    "wof:name":"L30 7PD",
    "wof:placetype":"postalcode"
},
  "geometry": {"coordinates":[-2.96640675230854,53.49652325334446],"type":"Point"}
}