{
  "type": "Feature",
  "properties": {
    "iso:country": "GB",
    "wof:name": "DG11 1DF",
    "wof:placetype": "postalcode"
  },
  "geometry": {"coordinates":[-3.395835,55.090015],"type":"Point"}
}
