{
  "type": "Feature",
  "properties": {
    "iso:country":"GB",
    "wof:name":"TW19 7LZ",
    "wof:placetype":"postalcode"
},
  "geometry": {"coordinates":[-0.45886080076262,51.45324529496633],"type":"Point"}
}