{
  "type": "Feature",
  "properties": {
    "iso:country": "GB",
    "wof:name": "TW19 7LZ",
    "wof:placetype": "postalcode"
  },
  "geometry": {"coordinates":[-0.458861,51.453245],"type":"Point"}
}
