{
  "type": "Feature",
  "properties": {
    "iso:country":"GB",
    "wof:name":"KY15 5SL",
    "wof:placetype":"postalcode"
},
  "geometry": {"coordinates":[-3.03269173252039,56.30651889530893],"type":"Point"}
}