{
  "type": "Feature",
  "properties": {
    "date:inception_lower":"1996-12-01",
    "date:inception_upper":"1996-12-31",
    "iso:country":"GB",
    "wof:name":"LN8 6NJ",
    "wof:placetype":"postalcode"
},
  "geometry": {"coordinates":[-0.205432,53.333291],"type":"Point"}
}