{
  "type": "Feature",
  "properties": {
    "iso:country":"GB",
    "wof:name":"LN8 6NJ",
    "wof:placetype":"postalcode"
},
  "geometry": {"coordinates":[-0.20543163877448,53.3332909189517],"type":"Point"}
}