{
  "type": "Feature",
  "properties": {
    "iso:country": "GB",
    "wof:name": "ME12 4AD",
    "wof:placetype": "postalcode"
  },
  "geometry": {"coordinates":[0.901299,51.396822],"type":"Point"}
}
