{
  "type": "Feature",
  "properties": {
    "iso:country":"GB",
    "wof:name":"SE15 4EN",
    "wof:placetype":"postalcode"
},
  "geometry": {"coordinates":[-0.07479096663873,51.46441952873497],"type":"Point"}
}