{
  "type": "Feature",
  "properties": {
    "date:inception_lower": "1984-02-01",
    "date:inception_upper": "1984-02-01",
    "iso:country": "GB",
    "wof:name": "ST15 0HQ",
    "wof:placetype": "postalcode"
  },
  "geometry": {"coordinates":[-2.148489,52.897337],"type":"Point"}
}
