{
  "type": "Feature",
  "properties": {
    "iso:country":"GB",
    "wof:name":"ST15 0HQ",
    "wof:placetype":"postalcode"
},
  "geometry": {"coordinates":[-2.14877283349081,52.89717680103465],"type":"Point"}
}