{
  "type": "Feature",
  "properties": {
    "date:inception_lower": "2022-02-01",
    "date:inception_upper": "2022-02-01",
    "iso:country": "GB",
    "wof:name": "GL18 1FD",
    "wof:placetype": "postalcode"
  },
  "geometry": {"coordinates":[-2.405805,51.925382],"type":"Point"}
}
