{
  "type": "Feature",
  "properties": {
    "iso:country": "GB",
    "wof:name": "TS3 6ND",
    "wof:placetype": "postalcode"
  },
  "geometry": {"coordinates":[-1.213599,54.570202],"type":"Point"}
}
