{
  "type": "Feature",
  "properties": {
    "iso:country":"GB",
    "wof:name":"TS3 6ND",
    "wof:placetype":"postalcode"
},
  "geometry": {"coordinates":[-1.21356977715747,54.57017954584634],"type":"Point"}
}