{
  "type": "Feature",
  "properties": {
    "iso:country":"GB",
    "wof:name":"BH20 7JW",
    "wof:placetype":"postalcode"
},
  "geometry": {"coordinates":[-2.22019204750553,50.74634093910387],"type":"Point"}
}