{
  "type": "Feature",
  "properties": {
    "iso:country":"GB",
    "wof:name":"PE36 5BX",
    "wof:placetype":"postalcode"
},
  "geometry": {"coordinates":[0.48789958616746,52.9361233608514],"type":"Point"}
}