{
  "type": "Feature",
  "properties": {
    "date:inception_lower": "1980-01-01",
    "date:inception_upper": "1980-01-01",
    "iso:country": "GB",
    "wof:name": "PE36 5BX",
    "wof:placetype": "postalcode"
  },
  "geometry": {"coordinates":[0.4871,52.93603],"type":"Point"}
}
