{
  "type": "Feature",
  "properties": {
    "iso:country": "GB",
    "wof:name": "CR2 7BH",
    "wof:placetype": "postalcode"
  },
  "geometry": {"coordinates":[-0.086558,51.35339],"type":"Point"}
}
