{
  "type": "Feature",
  "properties": {
    "iso:country": "GB",
    "wof:name": "PO13 9GE",
    "wof:placetype": "postalcode"
  },
  "geometry": {"coordinates":[-1.204831,50.808416],"type":"Point"}
}
