{
  "type": "Feature",
  "properties": {
    "iso:country":"GB",
    "wof:name":"HA1 2PR",
    "wof:placetype":"postalcode"
},
  "geometry": {"coordinates":[-0.32547354876881,51.58399852562833],"type":"Point"}
}