{
  "type": "Feature",
  "properties": {
    "iso:country":"GB",
    "wof:name":"DL1 3HF",
    "wof:placetype":"postalcode"
},
  "geometry": {"coordinates":[-1.5143664505183,54.54824999910024],"type":"Point"}
}