{
  "type": "Feature",
  "properties": {
    "date:inception_lower": "1980-01-01",
    "date:inception_upper": "1980-01-01",
    "iso:country": "GB",
    "wof:name": "DL1 3HF",
    "wof:placetype": "postalcode"
  },
  "geometry": {"coordinates":[-1.514366,54.54825],"type":"Point"}
}
