{
  "type": "Feature",
  "properties": {
    "iso:country":"GB",
    "wof:name":"B43 6PT",
    "wof:placetype":"postalcode"
},
  "geometry": {"coordinates":[-1.94900710037583,52.547222852235],"type":"Point"}
}