{
  "type": "Feature",
  "properties": {
    "date:inception_lower": "1980-01-01",
    "date:inception_upper": "1980-01-01",
    "iso:country": "GB",
    "wof:name": "L14 9PW",
    "wof:placetype": "postalcode"
  },
  "geometry": {"coordinates":[-2.871273,53.420138],"type":"Point"}
}
