{
  "type": "Feature",
  "properties": {
    "iso:country": "GB",
    "wof:name": "SK12 1YJ",
    "wof:placetype": "postalcode"
  },
  "geometry": {"coordinates":[-2.124656,53.338357],"type":"Point"}
}
