{
  "type": "Feature",
  "properties": {
    "date:inception_lower": "2006-02-01",
    "date:inception_upper": "2006-02-01",
    "iso:country": "GB",
    "wof:name": "WN5 9DT",
    "wof:placetype": "postalcode"
  },
  "geometry": {"coordinates":[-2.658327,53.536981],"type":"Point"}
}
