{
  "type": "Feature",
  "properties": {
    "iso:country":"GB",
    "wof:name":"WF7 5JW",
    "wof:placetype":"postalcode"
},
  "geometry": {"coordinates":[-1.36851336931929,53.6728803607349],"type":"Point"}
}