{
  "type": "Feature",
  "properties": {
    "iso:country":"GB",
    "wof:name":"ML7 5JQ",
    "wof:placetype":"postalcode"
},
  "geometry": {"coordinates":[-3.78182498028312,55.80979173698525],"type":"Point"}
}