{
  "type": "Feature",
  "properties": {
    "date:inception_lower": "1980-01-01",
    "date:inception_upper": "1980-01-01",
    "iso:country": "GB",
    "wof:name": "RG22 4BG",
    "wof:placetype": "postalcode"
  },
  "geometry": {"coordinates":[-1.109458,51.24878],"type":"Point"}
}
