{
  "type": "Feature",
  "properties": {
    "date:inception_lower": "1980-01-01",
    "date:inception_upper": "1980-01-01",
    "iso:country": "GB",
    "wof:name": "TN2 4RS",
    "wof:placetype": "postalcode"
  },
  "geometry": {"coordinates":[0.298405,51.14471],"type":"Point"}
}
