{
  "type": "Feature",
  "properties": {
    "iso:country":"GB",
    "wof:name":"TN2 4RS",
    "wof:placetype":"postalcode"
},
  "geometry": {"coordinates":[0.29840473166117,51.1447099983907],"type":"Point"}
}