{
  "type": "Feature",
  "properties": {
    "iso:country":"GB",
    "wof:name":"BL3 2SA",
    "wof:placetype":"postalcode"
},
  "geometry": {"coordinates":[-2.41326756859002,53.56561980162637],"type":"Point"}
}