{
  "type": "Feature",
  "properties": {
    "date:inception_lower": "1988-03-01",
    "date:inception_upper": "1988-03-01",
    "iso:country": "GB",
    "wof:name": "ME14 1JL",
    "wof:placetype": "postalcode"
  },
  "geometry": {"coordinates":[0.52143,51.273976],"type":"Point"}
}
