{
  "type": "Feature",
  "properties": {
    "date:inception_lower":"1980-01-01",
    "date:inception_upper":"1980-01-31",
    "iso:country":"GB",
    "wof:name":"BN11 5HD",
    "wof:placetype":"postalcode"
},
  "geometry": {"coordinates":[-0.395384,50.813394],"type":"Point"}
}