{
  "type": "Feature",
  "properties": {
    "iso:country":"GB",
    "wof:name":"BN11 5HD",
    "wof:placetype":"postalcode"
},
  "geometry": {"coordinates":[-0.39538396993837,50.81339398132616],"type":"Point"}
}