{
  "type": "Feature",
  "properties": {
    "date:inception_lower": "1999-06-01",
    "date:inception_upper": "1999-06-01",
    "iso:country": "GB",
    "wof:name": "KT18 6YT",
    "wof:placetype": "postalcode"
  },
  "geometry": {"coordinates":[-0.26244,51.335322],"type":"Point"}
}
