{
  "type": "Feature",
  "properties": {
    "iso:country": "GB",
    "wof:name": "DT9 6ES",
    "wof:placetype": "postalcode"
  },
  "geometry": {"coordinates":[-2.501836,50.907676],"type":"Point"}
}
