{
  "type": "Feature",
  "properties": {
    "iso:country":"GB",
    "wof:name":"DT9 6ES",
    "wof:placetype":"postalcode"
},
  "geometry": {"coordinates":[-2.50183577397784,50.90767650347954],"type":"Point"}
}