{
  "type": "Feature",
  "properties": {
    "date:inception_lower": "2006-11-01",
    "date:inception_upper": "2006-11-01",
    "iso:country": "GB",
    "wof:name": "E14 7BT",
    "wof:placetype": "postalcode"
  },
  "geometry": {"coordinates":[-0.025702,51.518],"type":"Point"}
}
