{
  "type": "Feature",
  "properties": {
    "iso:country":"GB",
    "wof:name":"E14 7BT",
    "wof:placetype":"postalcode"
},
  "geometry": {"coordinates":[-0.02570221598121,51.51799981374636],"type":"Point"}
}