{
  "type": "Feature",
  "properties": {
    "date:inception_lower": "1980-01-01",
    "date:inception_upper": "1980-01-01",
    "iso:country": "GB",
    "wof:name": "B66 1BB",
    "wof:placetype": "postalcode"
  },
  "geometry": {"coordinates":[-1.967855,52.503664],"type":"Point"}
}
