{
  "type": "Feature",
  "properties": {
    "iso:country":"GB",
    "wof:name":"B66 1BB",
    "wof:placetype":"postalcode"
},
  "geometry": {"coordinates":[-1.96785529492353,52.50366442750347],"type":"Point"}
}