{
  "type": "Feature",
  "properties": {
    "iso:country":"GB",
    "wof:name":"GU51 3QX",
    "wof:placetype":"postalcode"
},
  "geometry": {"coordinates":[-0.84076393219533,51.27788225777714],"type":"Point"}
}