{
  "type": "Feature",
  "properties": {
    "iso:country":"GB",
    "wof:name":"KA1 4PS",
    "wof:placetype":"postalcode"
},
  "geometry": {"coordinates":[-4.49543349655265,55.58519033854962],"type":"Point"}
}