{
  "type": "Feature",
  "properties": {
    "iso:country": "GB",
    "wof:name": "BS40 5TN",
    "wof:placetype": "postalcode"
  },
  "geometry": {"coordinates":[-2.709567,51.374245],"type":"Point"}
}
