{
  "type": "Feature",
  "properties": {
    "iso:country":"GB",
    "wof:name":"BS40 5TN",
    "wof:placetype":"postalcode"
},
  "geometry": {"coordinates":[-2.70956683858835,51.37424493619823],"type":"Point"}
}