{
  "type": "Feature",
  "properties": {
    "date:inception_lower":"1997-12-01",
    "date:inception_upper":"1997-12-31",
    "iso:country":"GB",
    "wof:name":"BS40 5TN",
    "wof:placetype":"postalcode"
},
  "geometry": {"coordinates":[-2.709567,51.374245],"type":"Point"}
}