{
  "type": "Feature",
  "properties": {
    "date:inception_lower": "2019-09-01",
    "date:inception_upper": "2019-09-01",
    "iso:country": "GB",
    "wof:name": "WA7 1WE",
    "wof:placetype": "postalcode"
  },
  "geometry": {"coordinates":[-2.65161,53.343076],"type":"Point"}
}
