{
  "type": "Feature",
  "properties": {
    "date:inception_lower":"1980-01-01",
    "date:inception_upper":"1980-01-31",
    "iso:country":"GB",
    "wof:name":"CA12 4AZ",
    "wof:placetype":"postalcode"
},
  "geometry": {"coordinates":[-3.121177,54.599145],"type":"Point"}
}