{
  "type": "Feature",
  "properties": {
    "iso:country":"GB",
    "wof:name":"HA2 0UD",
    "wof:placetype":"postalcode"
},
  "geometry": {"coordinates":[-0.36233452345885,51.56603072433721],"type":"Point"}
}