{
  "type": "Feature",
  "properties": {
    "iso:country":"GB",
    "wof:name":"BS8 2EW",
    "wof:placetype":"postalcode"
},
  "geometry": {"coordinates":[-2.61402463420093,51.46095227094963],"type":"Point"}
}