{
  "type": "Feature",
  "properties": {
    "iso:country":"GB",
    "wof:name":"HP1 1HU",
    "wof:placetype":"postalcode"
},
  "geometry": {"coordinates":[-0.47670030479971,51.75423473712138],"type":"Point"}
}