{
  "type": "Feature",
  "properties": {
    "iso:country": "GB",
    "wof:name": "HP1 1HU",
    "wof:placetype": "postalcode"
  },
  "geometry": {"coordinates":[-0.4767,51.754235],"type":"Point"}
}
