{
  "type": "Feature",
  "properties": {
    "date:inception_lower":"1991-09-01",
    "date:inception_upper":"1991-09-30",
    "iso:country":"GB",
    "wof:name":"NE23 6QU",
    "wof:placetype":"postalcode"
},
  "geometry": {"coordinates":[-1.568742,55.078209],"type":"Point"}
}