{
  "type": "Feature",
  "properties": {
    "iso:country":"GB",
    "wof:name":"NE23 6QU",
    "wof:placetype":"postalcode"
},
  "geometry": {"coordinates":[-1.56872766156412,55.07820209138375],"type":"Point"}
}