{
  "type": "Feature",
  "properties": {
    "iso:country": "GB",
    "wof:name": "NE45 5PY",
    "wof:placetype": "postalcode"
  },
  "geometry": {"coordinates":[-1.967449,55.007099],"type":"Point"}
}
