{
  "type": "Feature",
  "properties": {
    "iso:country":"GB",
    "wof:name":"PO38 3LA",
    "wof:placetype":"postalcode"
},
  "geometry": {"coordinates":[-1.27899721001036,50.64137194984454],"type":"Point"}
}