{
  "type": "Feature",
  "properties": {
    "iso:country":"GB",
    "wof:name":"EX15 1JH",
    "wof:placetype":"postalcode"
},
  "geometry": {"coordinates":[-3.39307761362544,50.85624101870947],"type":"Point"}
}