{
  "type": "Feature",
  "properties": {
    "date:inception_lower": "1980-01-01",
    "date:inception_upper": "1980-01-01",
    "iso:country": "GB",
    "wof:name": "EX15 1JH",
    "wof:placetype": "postalcode"
  },
  "geometry": {"coordinates":[-3.393078,50.856241],"type":"Point"}
}
