{
  "type": "Feature",
  "properties": {
    "iso:country":"GB",
    "wof:name":"WS9 9HJ",
    "wof:placetype":"postalcode"
},
  "geometry": {"coordinates":[-1.89582664997433,52.62391606672559],"type":"Point"}
}