{
  "type": "Feature",
  "properties": {
    "iso:country": "GB",
    "wof:name": "WS9 9HJ",
    "wof:placetype": "postalcode"
  },
  "geometry": {"coordinates":[-1.895827,52.623916],"type":"Point"}
}
