{
  "type": "Feature",
  "properties": {
    "iso:country": "GB",
    "wof:name": "WR12 7PJ",
    "wof:placetype": "postalcode"
  },
  "geometry": {"coordinates":[-1.847715,52.05412],"type":"Point"}
}
