{
  "type": "Feature",
  "properties": {
    "iso:country":"GB",
    "wof:name":"PR25 1LB",
    "wof:placetype":"postalcode"
},
  "geometry": {"coordinates":[-2.70198576496051,53.69140539252621],"type":"Point"}
}