{
  "type": "Feature",
  "properties": {
    "iso:country":"GB",
    "wof:name":"N4 3BS",
    "wof:placetype":"postalcode"
},
  "geometry": {"coordinates":[-0.1168820061261,51.56832839658885],"type":"Point"}
}