{
  "type": "Feature",
  "properties": {
    "date:inception_lower": "1984-10-01",
    "date:inception_upper": "1984-10-01",
    "iso:country": "GB",
    "wof:name": "BA21 3RN",
    "wof:placetype": "postalcode"
  },
  "geometry": {"coordinates":[-2.664257,50.946504],"type":"Point"}
}
