{
  "type": "Feature",
  "properties": {
    "date:inception_lower": "1980-01-01",
    "date:inception_upper": "1980-01-01",
    "iso:country": "GB",
    "wof:name": "RM18 8BH",
    "wof:placetype": "postalcode"
  },
  "geometry": {"coordinates":[0.375633,51.462883],"type":"Point"}
}
