{
  "type": "Feature",
  "properties": {
    "iso:country": "GB",
    "wof:name": "RM18 8BH",
    "wof:placetype": "postalcode"
  },
  "geometry": {"coordinates":[0.375633,51.462883],"type":"Point"}
}
