{
  "type": "Feature",
  "properties": {
    "iso:country":"GB",
    "wof:name":"CF43 4TP",
    "wof:placetype":"postalcode"
},
  "geometry": {"coordinates":[-3.47808366557655,51.66883447156687],"type":"Point"}
}