{
  "type": "Feature",
  "properties": {
    "iso:country":"GB",
    "wof:name":"N1 8DU",
    "wof:placetype":"postalcode"
},
  "geometry": {"coordinates":[-0.10231927017317,51.53582870295009],"type":"Point"}
}