{
  "type": "Feature",
  "properties": {
    "iso:country": "GB",
    "wof:name": "N1 8DU",
    "wof:placetype": "postalcode"
  },
  "geometry": {"coordinates":[-0.102319,51.535829],"type":"Point"}
}
