{
  "type": "Feature",
  "properties": {
    "iso:country": "GB",
    "wof:name": "NP23 4HB",
    "wof:placetype": "postalcode"
  },
  "geometry": {"coordinates":[-3.179578,51.797977],"type":"Point"}
}
