{
  "type": "Feature",
  "properties": {
    "iso:country":"GB",
    "wof:name":"NP23 4HB",
    "wof:placetype":"postalcode"
},
  "geometry": {"coordinates":[-3.1795782067682,51.79797731455455],"type":"Point"}
}