{
  "type": "Feature",
  "properties": {
    "iso:country": "GB",
    "wof:name": "SY22 6PY",
    "wof:placetype": "postalcode"
  },
  "geometry": {"coordinates":[-3.103942,52.733017],"type":"Point"}
}
