{
  "type": "Feature",
  "properties": {
    "iso:country":"GB",
    "wof:name":"SY22 6PY",
    "wof:placetype":"postalcode"
},
  "geometry": {"coordinates":[-3.10394205201563,52.73301690579077],"type":"Point"}
}