{
  "type": "Feature",
  "properties": {
    "date:inception_lower": "1981-10-01",
    "date:inception_upper": "1981-10-01",
    "iso:country": "GB",
    "wof:name": "DG13 0PW",
    "wof:placetype": "postalcode"
  },
  "geometry": {"coordinates":[-3.01026,55.151966],"type":"Point"}
}
