{
  "type": "Feature",
  "properties": {
    "iso:country":"GB",
    "wof:name":"DG13 0PW",
    "wof:placetype":"postalcode"
},
  "geometry": {"coordinates":[-3.01026000136141,55.15196620765905],"type":"Point"}
}