{
  "type": "Feature",
  "properties": {
    "date:inception_lower": "1980-01-01",
    "date:inception_upper": "1980-01-01",
    "iso:country": "GB",
    "wof:name": "OL6 6HP",
    "wof:placetype": "postalcode"
  },
  "geometry": {"coordinates":[-2.090997,53.491731],"type":"Point"}
}
