{
  "type": "Feature",
  "properties": {
    "iso:country": "GB",
    "wof:name": "NG2 7ZJ",
    "wof:placetype": "postalcode"
  },
  "geometry": {"coordinates":[-1.148426,52.926917],"type":"Point"}
}
