{
  "type": "Feature",
  "properties": {
    "iso:country":"GB",
    "wof:name":"CA10 1XS",
    "wof:placetype":"postalcode"
},
  "geometry": {"coordinates":[-2.56347467799795,54.63733892296285],"type":"Point"}
}