{
  "type": "Feature",
  "properties": {
    "date:inception_lower":"1980-01-01",
    "date:inception_upper":"1980-01-31",
    "iso:country":"GB",
    "wof:name":"CA10 1XS",
    "wof:placetype":"postalcode"
},
  "geometry": {"coordinates":[-2.563475,54.637339],"type":"Point"}
}