{
  "type": "Feature",
  "properties": {
    "date:inception_lower":"1980-01-01",
    "date:inception_upper":"1980-01-31",
    "iso:country":"GB",
    "wof:name":"SY10 0HY",
    "wof:placetype":"postalcode"
},
  "geometry": {"coordinates":[-3.366791,52.797746],"type":"Point"}
}