{
  "type": "Feature",
  "properties": {
    "date:inception_lower": "1980-01-01",
    "date:inception_upper": "1980-01-01",
    "iso:country": "GB",
    "wof:name": "CH7 6ES",
    "wof:placetype": "postalcode"
  },
  "geometry": {"coordinates":[-3.108809,53.192965],"type":"Point"}
}
