{
  "type": "Feature",
  "properties": {
    "iso:country":"GB",
    "wof:name":"CH7 6ES",
    "wof:placetype":"postalcode"
},
  "geometry": {"coordinates":[-3.10880948236596,53.19296450542139],"type":"Point"}
}