{
  "type": "Feature",
  "properties": {
    "iso:country":"GB",
    "wof:name":"NG8 3BG",
    "wof:placetype":"postalcode"
},
  "geometry": {"coordinates":[-1.21099919026175,52.96850056125448],"type":"Point"}
}