{
  "type": "Feature",
  "properties": {
    "date:inception_lower":"2012-02-01",
    "date:inception_upper":"2012-02-29",
    "iso:country":"GB",
    "wof:name":"NG8 3BG",
    "wof:placetype":"postalcode"
},
  "geometry": {"coordinates":[-1.210999,52.968501],"type":"Point"}
}