{
  "type": "Feature",
  "properties": {
    "iso:country": "GB",
    "wof:name": "NG8 3BG",
    "wof:placetype": "postalcode"
  },
  "geometry": {"coordinates":[-1.210999,52.968501],"type":"Point"}
}
