{
  "type": "Feature",
  "properties": {
    "date:inception_lower": "1980-01-01",
    "date:inception_upper": "1980-01-01",
    "iso:country": "GB",
    "wof:name": "PR3 0JH",
    "wof:placetype": "postalcode"
  },
  "geometry": {"coordinates":[-2.81728,53.896945],"type":"Point"}
}
