{
  "type": "Feature",
  "properties": {
    "iso:country":"GB",
    "wof:name":"CH43 9AJ",
    "wof:placetype":"postalcode"
},
  "geometry": {"coordinates":[-3.0730668686392,53.3827297528529],"type":"Point"}
}