{
  "type": "Feature",
  "properties": {
    "iso:country":"GB",
    "wof:name":"GU32 3AL",
    "wof:placetype":"postalcode"
},
  "geometry": {"coordinates":[-0.95125107208085,51.00254435812326],"type":"Point"}
}