{
  "type": "Feature",
  "properties": {
    "date:inception_lower": "1980-01-01",
    "date:inception_upper": "1980-01-01",
    "iso:country": "GB",
    "wof:name": "OX11 9BH",
    "wof:placetype": "postalcode"
  },
  "geometry": {"coordinates":[-1.199344,51.618792],"type":"Point"}
}
