{
  "type": "Feature",
  "properties": {
    "iso:country":"GB",
    "wof:name":"E12 6UE",
    "wof:placetype":"postalcode"
},
  "geometry": {"coordinates":[0.04325056379846,51.54594619775689],"type":"Point"}
}