{
  "type": "Feature",
  "properties": {
    "date:inception_lower":"1980-01-01",
    "date:inception_upper":"1980-01-31",
    "iso:country":"GB",
    "wof:name":"E12 6UE",
    "wof:placetype":"postalcode"
},
  "geometry": {"coordinates":[0.043251,51.545946],"type":"Point"}
}