{
  "type": "Feature",
  "properties": {
    "iso:country": "GB",
    "wof:name": "NE15 7DE",
    "wof:placetype": "postalcode"
  },
  "geometry": {"coordinates":[-1.680487,54.979087],"type":"Point"}
}
