{
  "type": "Feature",
  "properties": {
    "iso:country": "GB",
    "wof:name": "PL28 8AY",
    "wof:placetype": "postalcode"
  },
  "geometry": {"coordinates":[-4.94079,50.540929],"type":"Point"}
}
