{
  "type": "Feature",
  "properties": {
    "iso:country":"GB",
    "wof:name":"PL28 8AY",
    "wof:placetype":"postalcode"
},
  "geometry": {"coordinates":[-4.94079053804,50.54092871111938],"type":"Point"}
}