{
  "type": "Feature",
  "properties": {
    "iso:country": "GB",
    "wof:name": "MK19 7AU",
    "wof:placetype": "postalcode"
  },
  "geometry": {"coordinates":[-0.806957,52.074975],"type":"Point"}
}
