{
  "type": "Feature",
  "properties": {
    "date:inception_lower": "1980-01-01",
    "date:inception_upper": "1980-01-01",
    "iso:country": "GB",
    "wof:name": "NE5 3TA",
    "wof:placetype": "postalcode"
  },
  "geometry": {"coordinates":[-1.67499,54.996174],"type":"Point"}
}
