{
  "type": "Feature",
  "properties": {
    "iso:country":"GB",
    "wof:name":"NE5 3TA",
    "wof:placetype":"postalcode"
},
  "geometry": {"coordinates":[-1.67499050259929,54.99617372755375],"type":"Point"}
}