{
  "type": "Feature",
  "properties": {
    "iso:country": "GB",
    "wof:name": "TN19 7EE",
    "wof:placetype": "postalcode"
  },
  "geometry": {"coordinates":[0.389334,50.998867],"type":"Point"}
}
