{
  "type": "Feature",
  "properties": {
    "iso:country":"GB",
    "wof:name":"TN19 7EE",
    "wof:placetype":"postalcode"
},
  "geometry": {"coordinates":[0.38927624848253,50.99884412702906],"type":"Point"}
}