{
  "type": "Feature",
  "properties": {
    "date:inception_lower": "1980-01-01",
    "date:inception_upper": "1980-01-01",
    "iso:country": "GB",
    "wof:name": "SA10 7EE",
    "wof:placetype": "postalcode"
  },
  "geometry": {"coordinates":[-3.820805,51.664379],"type":"Point"}
}
