{
  "type": "Feature",
  "properties": {
    "date:inception_lower":"2003-06-01",
    "date:inception_upper":"2003-06-30",
    "iso:country":"GB",
    "wof:name":"KY13 0RT",
    "wof:placetype":"postalcode"
},
  "geometry": {"coordinates":[-3.469413,56.234806],"type":"Point"}
}