{
  "type": "Feature",
  "properties": {
    "iso:country":"GB",
    "wof:name":"DE24 0GD",
    "wof:placetype":"postalcode"
},
  "geometry": {"coordinates":[-1.43493156749958,52.89047101968058],"type":"Point"}
}