{
  "type": "Feature",
  "properties": {
    "date:inception_lower":"1981-09-01",
    "date:inception_upper":"1981-09-30",
    "iso:country":"GB",
    "wof:name":"B97 5XJ",
    "wof:placetype":"postalcode"
},
  "geometry": {"coordinates":[-1.959941,52.295038],"type":"Point"}
}