{
  "type": "Feature",
  "properties": {
    "iso:country": "GB",
    "wof:name": "B97 5XJ",
    "wof:placetype": "postalcode"
  },
  "geometry": {"coordinates":[-1.959941,52.295038],"type":"Point"}
}
