{
  "type": "Feature",
  "properties": {
    "date:inception_lower":"1995-12-01",
    "date:inception_upper":"1995-12-31",
    "iso:country":"GB",
    "wof:name":"BN27 3XN",
    "wof:placetype":"postalcode"
},
  "geometry": {"coordinates":[0.245326,50.865364],"type":"Point"}
}