{
  "type": "Feature",
  "properties": {
    "iso:country":"GB",
    "wof:name":"BN27 3XN",
    "wof:placetype":"postalcode"
},
  "geometry": {"coordinates":[0.24532641645202,50.86536398599577],"type":"Point"}
}