{
  "type": "Feature",
  "properties": {
    "date:inception_lower": "1996-06-01",
    "date:inception_upper": "1996-06-01",
    "iso:country": "GB",
    "wof:name": "AB24 2XN",
    "wof:placetype": "postalcode"
  },
  "geometry": {"coordinates":[-2.120876,57.173453],"type":"Point"}
}
