{
  "type": "Feature",
  "properties": {
    "iso:country":"GB",
    "wof:name":"EH9 3DR",
    "wof:placetype":"postalcode"
},
  "geometry": {"coordinates":[-3.17956399130943,55.92870803195997],"type":"Point"}
}