{
  "type": "Feature",
  "properties": {
    "date:inception_lower": "1991-09-01",
    "date:inception_upper": "1991-09-01",
    "iso:country": "GB",
    "wof:name": "AL1 2JF",
    "wof:placetype": "postalcode"
  },
  "geometry": {"coordinates":[-0.340928,51.740087],"type":"Point"}
}
