{
  "type": "Feature",
  "properties": {
    "iso:country":"GB",
    "wof:name":"AL1 2JF",
    "wof:placetype":"postalcode"
},
  "geometry": {"coordinates":[-0.34092821406837,51.7400867028757],"type":"Point"}
}