{
  "type": "Feature",
  "properties": {
    "date:inception_lower": "1980-01-01",
    "date:inception_upper": "1980-01-01",
    "iso:country": "GB",
    "wof:name": "IP31 1RR",
    "wof:placetype": "postalcode"
  },
  "geometry": {"coordinates":[0.811599,52.339367],"type":"Point"}
}
