{
  "type": "Feature",
  "properties": {
    "iso:country":"GB",
    "wof:name":"TQ14 9RH",
    "wof:placetype":"postalcode"
},
  "geometry": {"coordinates":[-3.54403721021369,50.55065366395864],"type":"Point"}
}