{
  "type": "Feature",
  "properties": {
    "iso:country":"GB",
    "wof:name":"CF5 1EL",
    "wof:placetype":"postalcode"
},
  "geometry": {"coordinates":[-3.21459286483013,51.48463733974341],"type":"Point"}
}