{
  "type": "Feature",
  "properties": {
    "iso:country":"GB",
    "wof:name":"PE1 3PY",
    "wof:placetype":"postalcode"
},
  "geometry": {"coordinates":[-0.2457245518312,52.59111441173537],"type":"Point"}
}