{
  "type": "Feature",
  "properties": {
    "iso:country": "GB",
    "wof:name": "G46 7QN",
    "wof:placetype": "postalcode"
  },
  "geometry": {"coordinates":[-4.299393,55.806889],"type":"Point"}
}
