{
  "type": "Feature",
  "properties": {
    "iso:country":"GB",
    "wof:name":"WF11 8EL",
    "wof:placetype":"postalcode"
},
  "geometry": {"coordinates":[-1.25500832064662,53.70675256096313],"type":"Point"}
}