{
  "type": "Feature",
  "properties": {
    "iso:country":"GB",
    "wof:name":"CV9 2DH",
    "wof:placetype":"postalcode"
},
  "geometry": {"coordinates":[-1.59595332492859,52.58149783344472],"type":"Point"}
}