{
  "type": "Feature",
  "properties": {
    "iso:country":"GB",
    "wof:name":"TN5 6SB",
    "wof:placetype":"postalcode"
},
  "geometry": {"coordinates":[0.31197715081023,51.07466097301512],"type":"Point"}
}