{
  "type": "Feature",
  "properties": {
    "iso:country":"GB",
    "wof:name":"DE22 4FX",
    "wof:placetype":"postalcode"
},
  "geometry": {"coordinates":[-1.51782170328636,52.92134622795098],"type":"Point"}
}