{
  "type": "Feature",
  "properties": {
    "date:inception_lower": "2018-01-01",
    "date:inception_upper": "2018-01-01",
    "iso:country": "GB",
    "wof:name": "PO9 1SE",
    "wof:placetype": "postalcode"
  },
  "geometry": {"coordinates":[-0.984833,50.847322],"type":"Point"}
}
