{
  "type": "Feature",
  "properties": {
    "iso:country": "GB",
    "wof:name": "G1 2NB",
    "wof:placetype": "postalcode"
  },
  "geometry": {"coordinates":[-4.253696,55.86055],"type":"Point"}
}
