{
  "type": "Feature",
  "properties": {
    "iso:country":"GB",
    "wof:name":"CV6 4FZ",
    "wof:placetype":"postalcode"
},
  "geometry": {"coordinates":[-1.51194341092442,52.4436616903869],"type":"Point"}
}