{
  "type": "Feature",
  "properties": {
    "date:inception_lower":"1980-01-01",
    "date:inception_upper":"1980-01-31",
    "iso:country":"GB",
    "wof:name":"CV6 4FZ",
    "wof:placetype":"postalcode"
},
  "geometry": {"coordinates":[-1.511943,52.443662],"type":"Point"}
}