{
  "type": "Feature",
  "properties": {
    "iso:country": "GB",
    "wof:name": "CV6 4FZ",
    "wof:placetype": "postalcode"
  },
  "geometry": {"coordinates":[-1.511943,52.443662],"type":"Point"}
}
