{
  "type": "Feature",
  "properties": {
    "iso:country": "GB",
    "wof:name": "LL11 3BZ",
    "wof:placetype": "postalcode"
  },
  "geometry": {"coordinates":[-3.018476,53.044988],"type":"Point"}
}
