{
  "type": "Feature",
  "properties": {
    "date:inception_lower":"2007-11-01",
    "date:inception_upper":"2007-11-30",
    "iso:country":"GB",
    "wof:name":"LL11 3BZ",
    "wof:placetype":"postalcode"
},
  "geometry": {"coordinates":[-3.018476,53.044988],"type":"Point"}
}