{
  "type": "Feature",
  "properties": {
    "iso:country":"GB",
    "wof:name":"LL11 3BZ",
    "wof:placetype":"postalcode"
},
  "geometry": {"coordinates":[-3.01847595464213,53.04498794715746],"type":"Point"}
}