{
  "type": "Feature",
  "properties": {
    "iso:country": "GB",
    "wof:name": "LS1 2QS",
    "wof:placetype": "postalcode"
  },
  "geometry": {"coordinates":[-1.550251,53.799469],"type":"Point"}
}
