{
  "type": "Feature",
  "properties": {
    "date:inception_lower":"2007-09-01",
    "date:inception_upper":"2007-09-30",
    "iso:country":"GB",
    "wof:name":"NE37 1WQ",
    "wof:placetype":"postalcode"
},
  "geometry": {"coordinates":[-1.532476,54.906682],"type":"Point"}
}