{
  "type": "Feature",
  "properties": {
    "iso:country":"GB",
    "wof:name":"DA2 7PF",
    "wof:placetype":"postalcode"
},
  "geometry": {"coordinates":[0.16936290807053,51.42180954121674],"type":"Point"}
}