{
  "type": "Feature",
  "properties": {
    "iso:country":"GB",
    "wof:name":"HA6 2EE",
    "wof:placetype":"postalcode"
},
  "geometry": {"coordinates":[-0.42991890523127,51.620816999707],"type":"Point"}
}