{
  "type": "Feature",
  "properties": {
    "iso:country":"GB",
    "wof:name":"CR0 6LA",
    "wof:placetype":"postalcode"
},
  "geometry": {"coordinates":[-0.07470457899391,51.38091182871214],"type":"Point"}
}