{
  "type": "Feature",
  "properties": {
    "iso:country":"GB",
    "wof:name":"KA18 3QP",
    "wof:placetype":"postalcode"
},
  "geometry": {"coordinates":[-4.06546205040869,55.52266712761963],"type":"Point"}
}