{
  "type": "Feature",
  "properties": {
    "iso:country":"GB",
    "wof:name":"DE21 6NA",
    "wof:placetype":"postalcode"
},
  "geometry": {"coordinates":[-1.43909811688347,52.92464157185574],"type":"Point"}
}