{
  "type": "Feature",
  "properties": {
    "date:inception_lower":"1980-01-01",
    "date:inception_upper":"1980-01-31",
    "iso:country":"GB",
    "wof:name":"NE61 6YA",
    "wof:placetype":"postalcode"
},
  "geometry": {"coordinates":[-1.654476,55.180592],"type":"Point"}
}