{
  "type": "Feature",
  "properties": {
    "iso:country":"GB",
    "wof:name":"HP2 4QF",
    "wof:placetype":"postalcode"
},
  "geometry": {"coordinates":[-0.4385504500068,51.75305075196508],"type":"Point"}
}