{
  "type": "Feature",
  "properties": {
    "iso:country": "GB",
    "wof:name": "NR30 3AA",
    "wof:placetype": "postalcode"
  },
  "geometry": {"coordinates":[1.735153,52.602534],"type":"Point"}
}
