{
  "type": "Feature",
  "properties": {
    "iso:country":"GB",
    "wof:name":"DN15 6DF",
    "wof:placetype":"postalcode"
},
  "geometry": {"coordinates":[-0.65455296767445,53.59688391066924],"type":"Point"}
}