{
  "type": "Feature",
  "properties": {
    "date:inception_lower": "1980-01-01",
    "date:inception_upper": "1980-01-01",
    "iso:country": "GB",
    "wof:name": "HU11 4LW",
    "wof:placetype": "postalcode"
  },
  "geometry": {"coordinates":[-0.184141,53.808304],"type":"Point"}
}
