{
  "type": "Feature",
  "properties": {
    "iso:country":"GB",
    "wof:name":"HU11 4LW",
    "wof:placetype":"postalcode"
},
  "geometry": {"coordinates":[-0.18414070582448,53.80830423072994],"type":"Point"}
}