{
  "type": "Feature",
  "properties": {
    "iso:country":"GB",
    "wof:name":"NP12 2HD",
    "wof:placetype":"postalcode"
},
  "geometry": {"coordinates":[-3.20828688146929,51.64958537199574],"type":"Point"}
}