{
  "type": "Feature",
  "properties": {
    "iso:country": "GB",
    "wof:name": "EH10 5EU",
    "wof:placetype": "postalcode"
  },
  "geometry": {"coordinates":[-3.215421,55.929887],"type":"Point"}
}
