{
  "type": "Feature",
  "properties": {
    "iso:country":"GB",
    "wof:name":"WF1 3LS",
    "wof:placetype":"postalcode"
},
  "geometry": {"coordinates":[-1.49775987038253,53.68757638306069],"type":"Point"}
}