{
  "type": "Feature",
  "properties": {
    "date:inception_lower": "2001-12-01",
    "date:inception_upper": "2001-12-01",
    "iso:country": "GB",
    "wof:name": "AB56 1LW",
    "wof:placetype": "postalcode"
  },
  "geometry": {"coordinates":[-2.955286,57.670073],"type":"Point"}
}
