{
  "type": "Feature",
  "properties": {
    "iso:country":"GB",
    "wof:name":"S63 6QU",
    "wof:placetype":"postalcode"
},
  "geometry": {"coordinates":[-1.35797263548887,53.50372486022137],"type":"Point"}
}