{
  "type": "Feature",
  "properties": {
    "iso:country":"GB",
    "wof:name":"SG14 3YJ",
    "wof:placetype":"postalcode"
},
  "geometry": {"coordinates":[-0.08831267775661,51.80011140952792],"type":"Point"}
}