{
  "type": "Feature",
  "properties": {
    "date:inception_lower":"1999-12-01",
    "date:inception_upper":"1999-12-31",
    "iso:country":"GB",
    "wof:name":"SG14 3YJ",
    "wof:placetype":"postalcode"
},
  "geometry": {"coordinates":[-0.088313,51.800111],"type":"Point"}
}