{
  "type": "Feature",
  "properties": {
    "date:inception_lower": "2005-01-01",
    "date:inception_upper": "2005-01-01",
    "iso:country": "GB",
    "wof:name": "HR9 5HF",
    "wof:placetype": "postalcode"
  },
  "geometry": {"coordinates":[-2.585073,51.914773],"type":"Point"}
}
