{
  "type": "Feature",
  "properties": {
    "date:inception_lower": "1985-10-01",
    "date:inception_upper": "1985-10-01",
    "iso:country": "GB",
    "wof:name": "CM8 1XP",
    "wof:placetype": "postalcode"
  },
  "geometry": {"coordinates":[0.636284,51.800455],"type":"Point"}
}
