{
  "type": "Feature",
  "properties": {
    "iso:country":"GB",
    "wof:name":"CM8 1XP",
    "wof:placetype":"postalcode"
},
  "geometry": {"coordinates":[0.63628413427193,51.80045501425955],"type":"Point"}
}