{
  "type": "Feature",
  "properties": {
    "iso:country": "GB",
    "wof:name": "YO51 9LF",
    "wof:placetype": "postalcode"
  },
  "geometry": {"coordinates":[-1.396025,54.096778],"type":"Point"}
}
