{
  "type": "Feature",
  "properties": {
    "iso:country":"GB",
    "wof:name":"YO51 9LF",
    "wof:placetype":"postalcode"
},
  "geometry": {"coordinates":[-1.39602551802356,54.09677830440699],"type":"Point"}
}