{
  "type": "Feature",
  "properties": {
    "iso:country":"GB",
    "wof:name":"EX20 2PJ",
    "wof:placetype":"postalcode"
},
  "geometry": {"coordinates":[-3.90427404784654,50.71737786392197],"type":"Point"}
}