{
  "type": "Feature",
  "properties": {
    "iso:country":"GB",
    "wof:name":"WR5 1JG",
    "wof:placetype":"postalcode"
},
  "geometry": {"coordinates":[-2.18313785023227,52.1923857570649],"type":"Point"}
}