{
  "type": "Feature",
  "properties": {
    "iso:country":"GB",
    "wof:name":"DN14 6YB",
    "wof:placetype":"postalcode"
},
  "geometry": {"coordinates":[-0.86109755157915,53.71489200465863],"type":"Point"}
}