{
  "type": "Feature",
  "properties": {
    "date:inception_lower":"1991-01-01",
    "date:inception_upper":"1991-01-31",
    "iso:country":"GB",
    "wof:name":"DN14 6YB",
    "wof:placetype":"postalcode"
},
  "geometry": {"coordinates":[-0.861098,53.714892],"type":"Point"}
}