{
  "type": "Feature",
  "properties": {
    "iso:country":"GB",
    "wof:name":"BA5 1RR",
    "wof:placetype":"postalcode"
},
  "geometry": {"coordinates":[-2.70503463039736,51.18375980419524],"type":"Point"}
}