{
  "type": "Feature",
  "properties": {
    "date:inception_lower":"2000-06-01",
    "date:inception_upper":"2000-06-30",
    "iso:country":"GB",
    "wof:name":"CF10 4DF",
    "wof:placetype":"postalcode"
},
  "geometry": {"coordinates":[-3.141141,51.46901],"type":"Point"}
}