{
  "type": "Feature",
  "properties": {
    "iso:country":"GB",
    "wof:name":"NN6 0BN",
    "wof:placetype":"postalcode"
},
  "geometry": {"coordinates":[-0.79066385562196,52.30124512696388],"type":"Point"}
}