{
  "type": "Feature",
  "properties": {
    "iso:country":"GB",
    "wof:name":"BD1 3LS",
    "wof:placetype":"postalcode"
},
  "geometry": {"coordinates":[-1.75348488112955,53.79570153545199],"type":"Point"}
}