{
  "type": "Feature",
  "properties": {
    "iso:country": "GB",
    "wof:name": "E4 6PL",
    "wof:placetype": "postalcode"
  },
  "geometry": {"coordinates":[-0.001694,51.623517],"type":"Point"}
}
