{
  "type": "Feature",
  "properties": {
    "iso:country":"GB",
    "wof:name":"E4 6PL",
    "wof:placetype":"postalcode"
},
  "geometry": {"coordinates":[-0.00169355996424,51.62351697638909],"type":"Point"}
}