{
  "type": "Feature",
  "properties": {
    "iso:country":"GB",
    "wof:name":"NE24 2LS",
    "wof:placetype":"postalcode"
},
  "geometry": {"coordinates":[-1.50938643053321,55.12512779310642],"type":"Point"}
}