{
  "type": "Feature",
  "properties": {
    "date:inception_lower": "1980-01-01",
    "date:inception_upper": "1980-01-01",
    "iso:country": "GB",
    "wof:name": "NE24 2LS",
    "wof:placetype": "postalcode"
  },
  "geometry": {"coordinates":[-1.509386,55.125128],"type":"Point"}
}
