{
  "type": "Feature",
  "properties": {
    "iso:country":"GB",
    "wof:name":"KA6 5HB",
    "wof:placetype":"postalcode"
},
  "geometry": {"coordinates":[-4.5751585168893,55.48163662386365],"type":"Point"}
}