{
  "type": "Feature",
  "properties": {
    "date:inception_lower":"2012-11-01",
    "date:inception_upper":"2012-11-30",
    "iso:country":"GB",
    "wof:name":"KA6 5HB",
    "wof:placetype":"postalcode"
},
  "geometry": {"coordinates":[-4.575158,55.481637],"type":"Point"}
}