{
  "type": "Feature",
  "properties": {
    "iso:country": "GB",
    "wof:name": "LE3 2FU",
    "wof:placetype": "postalcode"
  },
  "geometry": {"coordinates":[-1.163375,52.614699],"type":"Point"}
}
