{
  "type": "Feature",
  "properties": {
    "date:inception_lower": "2000-10-01",
    "date:inception_upper": "2000-10-01",
    "iso:country": "GB",
    "wof:name": "W1J 8AL",
    "wof:placetype": "postalcode"
  },
  "geometry": {"coordinates":[-0.143121,51.507589],"type":"Point"}
}
