{
  "type": "Feature",
  "properties": {
    "iso:country":"GB",
    "wof:name":"PL3 6EL",
    "wof:placetype":"postalcode"
},
  "geometry": {"coordinates":[-4.08991871626151,50.38816093153995],"type":"Point"}
}