{
  "type": "Feature",
  "properties": {
    "iso:country":"GB",
    "wof:name":"BD7 2EE",
    "wof:placetype":"postalcode"
},
  "geometry": {"coordinates":[-1.78361745226792,53.79012415613609],"type":"Point"}
}