{
  "type": "Feature",
  "properties": {
    "date:inception_lower": "1980-01-01",
    "date:inception_upper": "1980-01-01",
    "iso:country": "GB",
    "wof:name": "CM15 0RB",
    "wof:placetype": "postalcode"
  },
  "geometry": {"coordinates":[0.304689,51.66161],"type":"Point"}
}
