{
  "type": "Feature",
  "properties": {
    "iso:country":"GB",
    "wof:name":"W3 6HZ",
    "wof:placetype":"postalcode"
},
  "geometry": {"coordinates":[-0.26610293702712,51.51465093354454],"type":"Point"}
}