{
  "type": "Feature",
  "properties": {
    "iso:country":"GB",
    "wof:name":"CM16 4AY",
    "wof:placetype":"postalcode"
},
  "geometry": {"coordinates":[0.10402785968251,51.6952111737328],"type":"Point"}
}