{
  "type": "Feature",
  "properties": {
    "iso:country":"GB",
    "wof:name":"HD9 2RN",
    "wof:placetype":"postalcode"
},
  "geometry": {"coordinates":[-1.79285304069314,53.55392254193106],"type":"Point"}
}