{
  "type": "Feature",
  "properties": {
    "iso:country": "GB",
    "wof:name": "BA22 7FT",
    "wof:placetype": "postalcode"
  },
  "geometry": {"coordinates":[-2.520556,51.061834],"type":"Point"}
}
