{
  "type": "Feature",
  "properties": {
    "date:inception_lower": "2020-04-01",
    "date:inception_upper": "2020-04-01",
    "iso:country": "GB",
    "wof:name": "BA22 7FT",
    "wof:placetype": "postalcode"
  },
  "geometry": {"coordinates":[-2.520556,51.061834],"type":"Point"}
}
