{
  "type": "Feature",
  "properties": {
    "iso:country":"GB",
    "wof:name":"FK10 3QF",
    "wof:placetype":"postalcode"
},
  "geometry": {"coordinates":[-3.68026066305737,56.10751398818132],"type":"Point"}
}