{
  "type": "Feature",
  "properties": {
    "date:inception_lower":"2002-12-01",
    "date:inception_upper":"2002-12-31",
    "iso:country":"GB",
    "wof:name":"FK10 3QF",
    "wof:placetype":"postalcode"
},
  "geometry": {"coordinates":[-3.680261,56.107514],"type":"Point"}
}