{
  "type": "Feature",
  "properties": {
    "iso:country": "GB",
    "wof:name": "FK10 3QF",
    "wof:placetype": "postalcode"
  },
  "geometry": {"coordinates":[-3.680261,56.107514],"type":"Point"}
}
