{
  "type": "Feature",
  "properties": {
    "date:inception_lower": "1980-01-01",
    "date:inception_upper": "1980-01-01",
    "iso:country": "GB",
    "wof:name": "PH11 8DP",
    "wof:placetype": "postalcode"
  },
  "geometry": {"coordinates":[-3.236952,56.625288],"type":"Point"}
}
