{
  "type": "Feature",
  "properties": {
    "iso:country":"GB",
    "wof:name":"WS10 0GA",
    "wof:placetype":"postalcode"
},
  "geometry": {"coordinates":[-1.98562075311416,52.55382243907306],"type":"Point"}
}