{
  "type": "Feature",
  "properties": {
    "date:inception_lower":"2005-07-01",
    "date:inception_upper":"2005-07-31",
    "iso:country":"GB",
    "wof:name":"WS10 0GA",
    "wof:placetype":"postalcode"
},
  "geometry": {"coordinates":[-1.985621,52.553822],"type":"Point"}
}