{
  "type": "Feature",
  "properties": {
    "iso:country":"GB",
    "wof:name":"MK5 8PL",
    "wof:placetype":"postalcode"
},
  "geometry": {"coordinates":[-0.76696688216127,52.02181289588888],"type":"Point"}
}