{
  "type": "Feature",
  "properties": {
    "iso:country": "GB",
    "wof:name": "MK5 8PL",
    "wof:placetype": "postalcode"
  },
  "geometry": {"coordinates":[-0.766967,52.021813],"type":"Point"}
}
