{
  "type": "Feature",
  "properties": {
    "date:inception_lower": "1980-01-01",
    "date:inception_upper": "1980-01-01",
    "iso:country": "GB",
    "wof:name": "PL21 0LN",
    "wof:placetype": "postalcode"
  },
  "geometry": {"coordinates":[-3.896169,50.373629],"type":"Point"}
}
