{
  "type": "Feature",
  "properties": {
    "iso:country": "GB",
    "wof:name": "PL21 0LN",
    "wof:placetype": "postalcode"
  },
  "geometry": {"coordinates":[-3.896169,50.373629],"type":"Point"}
}
