{
  "type": "Feature",
  "properties": {
    "iso:country": "GB",
    "wof:name": "WF17 9JZ",
    "wof:placetype": "postalcode"
  },
  "geometry": {"coordinates":[-1.673833,53.734644],"type":"Point"}
}
