{
  "type": "Feature",
  "properties": {
    "iso:country":"GB",
    "wof:name":"BA14 9BH",
    "wof:placetype":"postalcode"
},
  "geometry": {"coordinates":[-2.22918481618328,51.32815454305283],"type":"Point"}
}