{
  "type": "Feature",
  "properties": {
    "date:inception_lower":"2002-06-01",
    "date:inception_upper":"2002-06-30",
    "iso:country":"GB",
    "wof:name":"BA14 9BH",
    "wof:placetype":"postalcode"
},
  "geometry": {"coordinates":[-2.229124,51.328079],"type":"Point"}
}