{
  "type": "Feature",
  "properties": {
    "date:inception_lower": "1990-08-01",
    "date:inception_upper": "1990-08-01",
    "iso:country": "GB",
    "wof:name": "AB54 4SR",
    "wof:placetype": "postalcode"
  },
  "geometry": {"coordinates":[-2.826412,57.50974],"type":"Point"}
}
