{
  "type": "Feature",
  "properties": {
    "iso:country":"GB",
    "wof:name":"AB54 4SR",
    "wof:placetype":"postalcode"
},
  "geometry": {"coordinates":[-2.82641179360644,57.50974022734349],"type":"Point"}
}