{
  "type": "Feature",
  "properties": {
    "iso:country":"GB",
    "wof:name":"TN2 4TW",
    "wof:placetype":"postalcode"
},
  "geometry": {"coordinates":[0.27526487577897,51.12888430183611],"type":"Point"}
}