{
  "type": "Feature",
  "properties": {
    "iso:country":"GB",
    "wof:name":"DY12 3AR",
    "wof:placetype":"postalcode"
},
  "geometry": {"coordinates":[-2.41354299995389,52.41569680757126],"type":"Point"}
}