{
  "type": "Feature",
  "properties": {
    "iso:country": "GB",
    "wof:name": "NE27 0DY",
    "wof:placetype": "postalcode"
  },
  "geometry": {"coordinates":[-1.516166,55.025975],"type":"Point"}
}
