{
  "type": "Feature",
  "properties": {
    "iso:country":"GB",
    "wof:name":"MK8 8ES",
    "wof:placetype":"postalcode"
},
  "geometry": {"coordinates":[-0.79648007087465,52.03915622521054],"type":"Point"}
}