{
  "type": "Feature",
  "properties": {
    "date:inception_lower": "1983-03-01",
    "date:inception_upper": "1983-03-01",
    "iso:country": "GB",
    "wof:name": "MK8 8ES",
    "wof:placetype": "postalcode"
  },
  "geometry": {"coordinates":[-0.79648,52.039156],"type":"Point"}
}
