{
  "type": "Feature",
  "properties": {
    "iso:country":"GB",
    "wof:name":"CV6 1PS",
    "wof:placetype":"postalcode"
},
  "geometry": {"coordinates":[-1.54805469469865,52.42132086583243],"type":"Point"}
}