{
  "type": "Feature",
  "properties": {
    "iso:country": "GB",
    "wof:name": "CV6 1PS",
    "wof:placetype": "postalcode"
  },
  "geometry": {"coordinates":[-1.548055,52.421321],"type":"Point"}
}
