{
  "type": "Feature",
  "properties": {
    "iso:country":"GB",
    "wof:name":"DE24 0UG",
    "wof:placetype":"postalcode"
},
  "geometry": {"coordinates":[-1.41399888176022,52.88537150242543],"type":"Point"}
}