{
  "type": "Feature",
  "properties": {
    "iso:country": "GB",
    "wof:name": "DE24 0UG",
    "wof:placetype": "postalcode"
  },
  "geometry": {"coordinates":[-1.413999,52.885371],"type":"Point"}
}
