{
  "type": "Feature",
  "properties": {
    "iso:country":"GB",
    "wof:name":"SA44 4SA",
    "wof:placetype":"postalcode"
},
  "geometry": {"coordinates":[-4.32282075700593,51.99809618445928],"type":"Point"}
}