{
  "type": "Feature",
  "properties": {
    "iso:country":"GB",
    "wof:name":"LE14 3QU",
    "wof:placetype":"postalcode"
},
  "geometry": {"coordinates":[-0.92334824106134,52.76340703897426],"type":"Point"}
}