{
  "type": "Feature",
  "properties": {
    "iso:country":"GB",
    "wof:name":"WF14 8JP",
    "wof:placetype":"postalcode"
},
  "geometry": {"coordinates":[-1.7036590879892,53.66651088990854],"type":"Point"}
}