{
  "type": "Feature",
  "properties": {
    "iso:country": "GB",
    "wof:name": "CH41 8HG",
    "wof:placetype": "postalcode"
  },
  "geometry": {"coordinates":[-3.051409,53.400738],"type":"Point"}
}
