{
  "type": "Feature",
  "properties": {
    "date:inception_lower": "2014-09-01",
    "date:inception_upper": "2014-09-01",
    "iso:country": "GB",
    "wof:name": "CH41 8HG",
    "wof:placetype": "postalcode"
  },
  "geometry": {"coordinates":[-3.051409,53.400738],"type":"Point"}
}
