{
  "type": "Feature",
  "properties": {
    "iso:country":"GB",
    "wof:name":"LU7 2TB",
    "wof:placetype":"postalcode"
},
  "geometry": {"coordinates":[-0.67155270387704,51.91884117564489],"type":"Point"}
}