{
  "type": "Feature",
  "properties": {
    "iso:country":"GB",
    "wof:name":"NE66 2BW",
    "wof:placetype":"postalcode"
},
  "geometry": {"coordinates":[-1.82002441821073,55.38092668935859],"type":"Point"}
}