{
  "type": "Feature",
  "properties": {
    "iso:country": "GB",
    "wof:name": "NE66 2BW",
    "wof:placetype": "postalcode"
  },
  "geometry": {"coordinates":[-1.820024,55.380927],"type":"Point"}
}
