{
  "type": "Feature",
  "properties": {
    "iso:country": "GB",
    "wof:name": "FK9 4NU",
    "wof:placetype": "postalcode"
  },
  "geometry": {"coordinates":[-3.950328,56.154865],"type":"Point"}
}
