{
  "type": "Feature",
  "properties": {
    "iso:country":"GB",
    "wof:name":"FK9 4NU",
    "wof:placetype":"postalcode"
},
  "geometry": {"coordinates":[-3.9503275723484,56.15486465335002],"type":"Point"}
}