{
  "type": "Feature",
  "properties": {
    "iso:country":"GB",
    "wof:name":"CV1 4JR",
    "wof:placetype":"postalcode"
},
  "geometry": {"coordinates":[-1.50599743894474,52.42280692234772],"type":"Point"}
}