{
  "type": "Feature",
  "properties": {
    "date:inception_lower": "2009-10-01",
    "date:inception_upper": "2009-10-01",
    "iso:country": "GB",
    "wof:name": "CH7 4TA",
    "wof:placetype": "postalcode"
  },
  "geometry": {"coordinates":[-3.086289,53.129876],"type":"Point"}
}
