{
  "type": "Feature",
  "properties": {
    "iso:country": "GB",
    "wof:name": "SA33 4BT",
    "wof:placetype": "postalcode"
  },
  "geometry": {"coordinates":[-4.489164,51.823393],"type":"Point"}
}
