{
  "type": "Feature",
  "properties": {
    "iso:country":"GB",
    "wof:name":"SA33 4BT",
    "wof:placetype":"postalcode"
},
  "geometry": {"coordinates":[-4.48950121726763,51.82363595753742],"type":"Point"}
}