{
  "type": "Feature",
  "properties": {
    "date:inception_lower":"2004-11-01",
    "date:inception_upper":"2004-11-30",
    "iso:country":"GB",
    "wof:name":"SA33 4BT",
    "wof:placetype":"postalcode"
},
  "geometry": {"coordinates":[-4.489526,51.823646],"type":"Point"}
}