{
  "type": "Feature",
  "properties": {
    "date:inception_lower": "1999-12-01",
    "date:inception_upper": "1999-12-01",
    "iso:country": "GB",
    "wof:name": "NR1 2DZ",
    "wof:placetype": "postalcode"
  },
  "geometry": {"coordinates":[1.30338,52.620143],"type":"Point"}
}
