{
  "type": "Feature",
  "properties": {
    "iso:country":"GB",
    "wof:name":"NR1 2DZ",
    "wof:placetype":"postalcode"
},
  "geometry": {"coordinates":[1.30338015564032,52.62014290752055],"type":"Point"}
}