{
  "type": "Feature",
  "properties": {
    "iso:country":"GB",
    "wof:name":"IV27 4QA",
    "wof:placetype":"postalcode"
},
  "geometry": {"coordinates":[-4.72456699539571,58.563520024347],"type":"Point"}
}