{
  "type": "Feature",
  "properties": {
    "iso:country": "GB",
    "wof:name": "IV27 4QA",
    "wof:placetype": "postalcode"
  },
  "geometry": {"coordinates":[-4.724567,58.56352],"type":"Point"}
}
