{
  "type": "Feature",
  "properties": {
    "iso:country":"GB",
    "wof:name":"NP22 3NT",
    "wof:placetype":"postalcode"
},
  "geometry": {"coordinates":[-3.2507917728599,51.76795572264093],"type":"Point"}
}