{
  "type": "Feature",
  "properties": {
    "date:inception_lower":"1999-06-01",
    "date:inception_upper":"1999-06-30",
    "iso:country":"GB",
    "wof:name":"NP22 3NT",
    "wof:placetype":"postalcode"
},
  "geometry": {"coordinates":[-3.250792,51.767956],"type":"Point"}
}