{
  "type": "Feature",
  "properties": {
    "iso:country": "GB",
    "wof:name": "WF9 2TB",
    "wof:placetype": "postalcode"
  },
  "geometry": {"coordinates":[-1.287333,53.596572],"type":"Point"}
}
