{
  "type": "Feature",
  "properties": {
    "iso:country":"GB",
    "wof:name":"CV6 6QR",
    "wof:placetype":"postalcode"
},
  "geometry": {"coordinates":[-1.46853595571628,52.458892722774],"type":"Point"}
}