{
  "type": "Feature",
  "properties": {
    "iso:country": "GB",
    "wof:name": "CV6 6QR",
    "wof:placetype": "postalcode"
  },
  "geometry": {"coordinates":[-1.468536,52.458893],"type":"Point"}
}
