{
  "type": "Feature",
  "properties": {
    "iso:country":"GB",
    "wof:name":"WF13 3LJ",
    "wof:placetype":"postalcode"
},
  "geometry": {"coordinates":[-1.66702013075121,53.67781172818285],"type":"Point"}
}