{
  "type": "Feature",
  "properties": {
    "iso:country": "GB",
    "wof:name": "WF13 3LJ",
    "wof:placetype": "postalcode"
  },
  "geometry": {"coordinates":[-1.666753,53.677583],"type":"Point"}
}
