{
  "type": "Feature",
  "properties": {
    "iso:country": "GB",
    "wof:name": "SK6 8HW",
    "wof:placetype": "postalcode"
  },
  "geometry": {"coordinates":[-2.068198,53.363472],"type":"Point"}
}
