{
  "type": "Feature",
  "properties": {
    "iso:country":"GB",
    "wof:name":"SK6 8HW",
    "wof:placetype":"postalcode"
},
  "geometry": {"coordinates":[-2.06819782736305,53.36347237672729],"type":"Point"}
}