{
  "type": "Feature",
  "properties": {
    "iso:country":"GB",
    "wof:name":"LA6 1EA",
    "wof:placetype":"postalcode"
},
  "geometry": {"coordinates":[-2.74554599816161,54.11050571070155],"type":"Point"}
}