{
  "type": "Feature",
  "properties": {
    "date:inception_lower":"1980-01-01",
    "date:inception_upper":"1980-01-31",
    "iso:country":"GB",
    "wof:name":"LA6 1EA",
    "wof:placetype":"postalcode"
},
  "geometry": {"coordinates":[-2.745546,54.110506],"type":"Point"}
}