{
  "type": "Feature",
  "properties": {
    "iso:country": "GB",
    "wof:name": "LA6 1EA",
    "wof:placetype": "postalcode"
  },
  "geometry": {"coordinates":[-2.745546,54.110506],"type":"Point"}
}
