{
  "type": "Feature",
  "properties": {
    "iso:country":"GB",
    "wof:name":"RG14 5PD",
    "wof:placetype":"postalcode"
},
  "geometry": {"coordinates":[-1.33069592524525,51.39857391798074],"type":"Point"}
}