{
  "type": "Feature",
  "properties": {
    "iso:country": "GB",
    "wof:name": "TN17 2DY",
    "wof:placetype": "postalcode"
  },
  "geometry": {"coordinates":[0.558382,51.112048],"type":"Point"}
}
