{
  "type": "Feature",
  "properties": {
    "date:inception_lower":"2017-10-01",
    "date:inception_upper":"2017-10-31",
    "iso:country":"GB",
    "wof:name":"W6 7BA",
    "wof:placetype":"postalcode"
},
  "geometry": {"coordinates":[-0.225929,51.494565],"type":"Point"}
}