{
  "type": "Feature",
  "properties": {
    "date:inception_lower": "1980-01-01",
    "date:inception_upper": "1980-01-01",
    "iso:country": "GB",
    "wof:name": "TR26 1LA",
    "wof:placetype": "postalcode"
  },
  "geometry": {"coordinates":[-5.482828,50.214743],"type":"Point"}
}
