{
  "type": "Feature",
  "properties": {
    "date:inception_lower": "2006-03-01",
    "date:inception_upper": "2006-03-01",
    "iso:country": "GB",
    "wof:name": "G75 0RR",
    "wof:placetype": "postalcode"
  },
  "geometry": {"coordinates":[-4.156698,55.741765],"type":"Point"}
}
