{
  "type": "Feature",
  "properties": {
    "iso:country":"GB",
    "wof:name":"G75 0RR",
    "wof:placetype":"postalcode"
},
  "geometry": {"coordinates":[-4.15669794782778,55.74176486659481],"type":"Point"}
}