{
  "type": "Feature",
  "properties": {
    "iso:country": "GB",
    "wof:name": "PL25 5BW",
    "wof:placetype": "postalcode"
  },
  "geometry": {"coordinates":[-4.793966,50.336112],"type":"Point"}
}
