{
  "type": "Feature",
  "properties": {
    "iso:country":"GB",
    "wof:name":"PL25 5BW",
    "wof:placetype":"postalcode"
},
  "geometry": {"coordinates":[-4.79396590025194,50.33611233068331],"type":"Point"}
}