{
  "type": "Feature",
  "properties": {
    "date:inception_lower": "1997-06-01",
    "date:inception_upper": "1997-06-01",
    "iso:country": "GB",
    "wof:name": "S26 4NE",
    "wof:placetype": "postalcode"
  },
  "geometry": {"coordinates":[-1.316558,53.361026],"type":"Point"}
}
