{
  "type": "Feature",
  "properties": {
    "date:inception_lower": "1992-08-01",
    "date:inception_upper": "1992-08-01",
    "iso:country": "GB",
    "wof:name": "DE21 7PB",
    "wof:placetype": "postalcode"
  },
  "geometry": {"coordinates":[-1.398254,52.916981],"type":"Point"}
}
