{
  "type": "Feature",
  "properties": {
    "iso:country":"GB",
    "wof:name":"IV7 8JB",
    "wof:placetype":"postalcode"
},
  "geometry": {"coordinates":[-4.36019430515873,57.57999753862498],"type":"Point"}
}