{
  "type": "Feature",
  "properties": {
    "iso:country":"GB",
    "wof:name":"HP11 2LQ",
    "wof:placetype":"postalcode"
},
  "geometry": {"coordinates":[-0.7603583501429,51.63348360010357],"type":"Point"}
}