{
  "type": "Feature",
  "properties": {
    "date:inception_lower": "1980-01-01",
    "date:inception_upper": "1980-01-01",
    "iso:country": "GB",
    "wof:name": "NG5 3HU",
    "wof:placetype": "postalcode"
  },
  "geometry": {"coordinates":[-1.14974,52.990437],"type":"Point"}
}
