{
  "type": "Feature",
  "properties": {
    "iso:country":"GB",
    "wof:name":"NG5 3HU",
    "wof:placetype":"postalcode"
},
  "geometry": {"coordinates":[-1.14974365036397,52.99041716822827],"type":"Point"}
}