{
  "type": "Feature",
  "properties": {
    "date:inception_lower": "1980-01-01",
    "date:inception_upper": "1980-01-01",
    "iso:country": "GB",
    "wof:name": "ST17 9NZ",
    "wof:placetype": "postalcode"
  },
  "geometry": {"coordinates":[-2.117619,52.783487],"type":"Point"}
}
