{
  "type": "Feature",
  "properties": {
    "iso:country": "GB",
    "wof:name": "KT24 6TJ",
    "wof:placetype": "postalcode"
  },
  "geometry": {"coordinates":[-0.430854,51.258152],"type":"Point"}
}
