{
  "type": "Feature",
  "properties": {
    "iso:country":"GB",
    "wof:name":"BS1 3DF",
    "wof:placetype":"postalcode"
},
  "geometry": {"coordinates":[-2.5876799454114,51.45731083934158],"type":"Point"}
}