{
  "type": "Feature",
  "properties": {
    "iso:country":"GB",
    "wof:name":"RG30 2PG",
    "wof:placetype":"postalcode"
},
  "geometry": {"coordinates":[-1.01361870930905,51.45881036859521],"type":"Point"}
}