{
  "type": "Feature",
  "properties": {
    "iso:country": "GB",
    "wof:name": "LE7 9QT",
    "wof:placetype": "postalcode"
  },
  "geometry": {"coordinates":[-1.042001,52.634825],"type":"Point"}
}
