{
  "type": "Feature",
  "properties": {
    "iso:country":"GB",
    "wof:name":"LE7 9QT",
    "wof:placetype":"postalcode"
},
  "geometry": {"coordinates":[-1.0420011031813,52.63482513031033],"type":"Point"}
}