{
  "type": "Feature",
  "properties": {
    "iso:country":"GB",
    "wof:name":"NP11 7GF",
    "wof:placetype":"postalcode"
},
  "geometry": {"coordinates":[-3.12566527274904,51.62560765925546],"type":"Point"}
}