{
  "type": "Feature",
  "properties": {
    "iso:country": "GB",
    "wof:name": "WA7 1EN",
    "wof:placetype": "postalcode"
  },
  "geometry": {"coordinates":[-2.741008,53.343006],"type":"Point"}
}
