{
  "type": "Feature",
  "properties": {
    "iso:country":"GB",
    "wof:name":"WA7 1EN",
    "wof:placetype":"postalcode"
},
  "geometry": {"coordinates":[-2.74100798763481,53.34300585915017],"type":"Point"}
}