{
  "type": "Feature",
  "properties": {
    "iso:country":"GB",
    "wof:name":"RM10 9NH",
    "wof:placetype":"postalcode"
},
  "geometry": {"coordinates":[0.15048333329324,51.53124158004741],"type":"Point"}
}