{
  "type": "Feature",
  "properties": {
    "date:inception_lower": "2021-03-01",
    "date:inception_upper": "2021-03-01",
    "iso:country": "GB",
    "wof:name": "B96 6LN",
    "wof:placetype": "postalcode"
  },
  "geometry": {"coordinates":[-1.942411,52.238855],"type":"Point"}
}
