{
  "type": "Feature",
  "properties": {
    "iso:country":"GB",
    "wof:name":"NR34 8BD",
    "wof:placetype":"postalcode"
},
  "geometry": {"coordinates":[1.60655884557067,52.36618063512404],"type":"Point"}
}