{
  "type": "Feature",
  "properties": {
    "date:inception_lower": "1980-01-01",
    "date:inception_upper": "1980-01-01",
    "iso:country": "GB",
    "wof:name": "NR34 8BD",
    "wof:placetype": "postalcode"
  },
  "geometry": {"coordinates":[1.606559,52.366181],"type":"Point"}
}
