{
  "type": "Feature",
  "properties": {
    "iso:country": "GB",
    "wof:name": "BA16 0AJ",
    "wof:placetype": "postalcode"
  },
  "geometry": {"coordinates":[-2.731379,51.132496],"type":"Point"}
}
