{
  "type": "Feature",
  "properties": {
    "iso:country":"GB",
    "wof:name":"BA16 0AJ",
    "wof:placetype":"postalcode"
},
  "geometry": {"coordinates":[-2.73137914287549,51.13249564999974],"type":"Point"}
}