{
  "type": "Feature",
  "properties": {
    "iso:country":"GB",
    "wof:name":"SS7 3QY",
    "wof:placetype":"postalcode"
},
  "geometry": {"coordinates":[0.58802928427665,51.56999518817652],"type":"Point"}
}