{
  "type": "Feature",
  "properties": {
    "iso:country":"GB",
    "wof:name":"HD6 2AJ",
    "wof:placetype":"postalcode"
},
  "geometry": {"coordinates":[-1.78899638617085,53.7041630312104],"type":"Point"}
}