{
  "type": "Feature",
  "properties": {
    "iso:country": "GB",
    "wof:name": "SL3 6SB",
    "wof:placetype": "postalcode"
  },
  "geometry": {"coordinates":[-0.557231,51.521335],"type":"Point"}
}
