{
  "type": "Feature",
  "properties": {
    "iso:country":"GB",
    "wof:name":"SL3 6SB",
    "wof:placetype":"postalcode"
},
  "geometry": {"coordinates":[-0.55723077044676,51.52133542866002],"type":"Point"}
}