{
  "type": "Feature",
  "properties": {
    "date:inception_lower": "1990-02-01",
    "date:inception_upper": "1990-02-01",
    "iso:country": "GB",
    "wof:name": "SL3 6SB",
    "wof:placetype": "postalcode"
  },
  "geometry": {"coordinates":[-0.557231,51.521335],"type":"Point"}
}
