{
  "type": "Feature",
  "properties": {
    "iso:country":"GB",
    "wof:name":"HP21 7AG",
    "wof:placetype":"postalcode"
},
  "geometry": {"coordinates":[-0.7826597351139,51.80954746679107],"type":"Point"}
}