{
  "type": "Feature",
  "properties": {
    "iso:country":"GB",
    "wof:name":"CR7 8DW",
    "wof:placetype":"postalcode"
},
  "geometry": {"coordinates":[-0.10273627022192,51.41056845522505],"type":"Point"}
}