{
  "type": "Feature",
  "properties": {
    "iso:country":"GB",
    "wof:name":"ST21 6AF",
    "wof:placetype":"postalcode"
},
  "geometry": {"coordinates":[-2.25563356673996,52.85600311847687],"type":"Point"}
}