{
  "type": "Feature",
  "properties": {
    "iso:country": "GB",
    "wof:name": "EH7 4NN",
    "wof:placetype": "postalcode"
  },
  "geometry": {"coordinates":[-3.188816,55.965805],"type":"Point"}
}
