{
  "type": "Feature",
  "properties": {
    "date:inception_lower": "2018-02-01",
    "date:inception_upper": "2018-02-01",
    "iso:country": "GB",
    "wof:name": "EH7 4NN",
    "wof:placetype": "postalcode"
  },
  "geometry": {"coordinates":[-3.188816,55.965805],"type":"Point"}
}
