{
  "type": "Feature",
  "properties": {
    "iso:country": "GB",
    "wof:name": "WS12 4LZ",
    "wof:placetype": "postalcode"
  },
  "geometry": {"coordinates":[-2.037947,52.703146],"type":"Point"}
}
