{
  "type": "Feature",
  "properties": {
    "iso:country":"GB",
    "wof:name":"SY23 5EE",
    "wof:placetype":"postalcode"
},
  "geometry": {"coordinates":[-4.11957727168422,52.29215614843822],"type":"Point"}
}