{
  "type": "Feature",
  "properties": {
    "date:inception_lower": "1980-01-01",
    "date:inception_upper": "1980-01-01",
    "iso:country": "GB",
    "wof:name": "PO21 3PB",
    "wof:placetype": "postalcode"
  },
  "geometry": {"coordinates":[-0.730668,50.782927],"type":"Point"}
}
