{
  "type": "Feature",
  "properties": {
    "iso:country": "GB",
    "wof:name": "PO21 3PB",
    "wof:placetype": "postalcode"
  },
  "geometry": {"coordinates":[-0.730668,50.782927],"type":"Point"}
}
