{
  "type": "Feature",
  "properties": {
    "iso:country": "GB",
    "wof:name": "EH46 7BD",
    "wof:placetype": "postalcode"
  },
  "geometry": {"coordinates":[-3.265078,55.761498],"type":"Point"}
}
