{
  "type": "Feature",
  "properties": {
    "iso:country":"GB",
    "wof:name":"EH46 7BD",
    "wof:placetype":"postalcode"
},
  "geometry": {"coordinates":[-3.26507845010219,55.76149782831164],"type":"Point"}
}