{
  "type": "Feature",
  "properties": {
    "iso:country":"GB",
    "wof:name":"S70 3LX",
    "wof:placetype":"postalcode"
},
  "geometry": {"coordinates":[-1.45989913727199,53.53985896331739],"type":"Point"}
}