{
  "type": "Feature",
  "properties": {
    "iso:country":"GB",
    "wof:name":"ML6 8GU",
    "wof:placetype":"postalcode"
},
  "geometry": {"coordinates":[-3.9434917879434,55.84231009669466],"type":"Point"}
}