{
  "type": "Feature",
  "properties": {
    "date:inception_lower": "2005-05-01",
    "date:inception_upper": "2005-05-01",
    "iso:country": "GB",
    "wof:name": "ML6 8GU",
    "wof:placetype": "postalcode"
  },
  "geometry": {"coordinates":[-3.943492,55.84231],"type":"Point"}
}
