{
  "type": "Feature",
  "properties": {
    "iso:country":"GB",
    "wof:name":"BS30 6NS",
    "wof:placetype":"postalcode"
},
  "geometry": {"coordinates":[-2.44877429879389,51.43674083606903],"type":"Point"}
}