{
  "type": "Feature",
  "properties": {
    "date:inception_lower": "1997-12-01",
    "date:inception_upper": "1997-12-01",
    "iso:country": "GB",
    "wof:name": "BS30 6NS",
    "wof:placetype": "postalcode"
  },
  "geometry": {"coordinates":[-2.448774,51.436741],"type":"Point"}
}
