{
  "type": "Feature",
  "properties": {
    "iso:country": "GB",
    "wof:name": "BS30 6NS",
    "wof:placetype": "postalcode"
  },
  "geometry": {"coordinates":[-2.448774,51.436741],"type":"Point"}
}
