{
  "type": "Feature",
  "properties": {
    "iso:country":"GB",
    "wof:name":"ST2 0DD",
    "wof:placetype":"postalcode"
},
  "geometry": {"coordinates":[-2.12846276395746,53.01101331803788],"type":"Point"}
}