{
  "type": "Feature",
  "properties": {
    "iso:country":"GB",
    "wof:name":"CT4 8DB",
    "wof:placetype":"postalcode"
},
  "geometry": {"coordinates":[0.95788734301259,51.2433481577706],"type":"Point"}
}