{
  "type": "Feature",
  "properties": {
    "iso:country": "GB",
    "wof:name": "CT4 8DB",
    "wof:placetype": "postalcode"
  },
  "geometry": {"coordinates":[0.957887,51.243348],"type":"Point"}
}
