{
  "type": "Feature",
  "properties": {
    "iso:country":"GB",
    "wof:name":"OL11 1NW",
    "wof:placetype":"postalcode"
},
  "geometry": {"coordinates":[-2.15807515844279,53.60668603557782],"type":"Point"}
}