{
  "type": "Feature",
  "properties": {
    "iso:country": "GB",
    "wof:name": "RG40 1LB",
    "wof:placetype": "postalcode"
  },
  "geometry": {"coordinates":[-0.808287,51.406891],"type":"Point"}
}
