{
  "type": "Feature",
  "properties": {
    "iso:country":"GB",
    "wof:name":"DN31 2LG",
    "wof:placetype":"postalcode"
},
  "geometry": {"coordinates":[-0.0940201761926,53.56477971948249],"type":"Point"}
}