{
  "type": "Feature",
  "properties": {
    "iso:country":"GB",
    "wof:name":"DD3 8BH",
    "wof:placetype":"postalcode"
},
  "geometry": {"coordinates":[-2.98117646658347,56.47760051335934],"type":"Point"}
}