{
  "type": "Feature",
  "properties": {
    "iso:country":"GB",
    "wof:name":"PA4 8TP",
    "wof:placetype":"postalcode"
},
  "geometry": {"coordinates":[-4.38703043874467,55.87735435342839],"type":"Point"}
}