{
  "type": "Feature",
  "properties": {
    "iso:country":"GB",
    "wof:name":"L16 2NL",
    "wof:placetype":"postalcode"
},
  "geometry": {"coordinates":[-2.87230369730194,53.40354818378959],"type":"Point"}
}