{
  "type": "Feature",
  "properties": {
    "iso:country":"GB",
    "wof:name":"CH65 6QP",
    "wof:placetype":"postalcode"
},
  "geometry": {"coordinates":[-2.90642158803379,53.27343930291469],"type":"Point"}
}