{
  "type": "Feature",
  "properties": {
    "iso:country":"GB",
    "wof:name":"EH21 6SF",
    "wof:placetype":"postalcode"
},
  "geometry": {"coordinates":[-3.07075907964489,55.93849868893887],"type":"Point"}
}