{
  "type": "Feature",
  "properties": {
    "iso:country": "GB",
    "wof:name": "FK1 5RZ",
    "wof:placetype": "postalcode"
  },
  "geometry": {"coordinates":[-3.792413,55.999086],"type":"Point"}
}
