{
  "type": "Feature",
  "properties": {
    "iso:country": "GB",
    "wof:name": "PE12 0PL",
    "wof:placetype": "postalcode"
  },
  "geometry": {"coordinates":[-0.022721,52.687195],"type":"Point"}
}
