{
  "type": "Feature",
  "properties": {
    "date:inception_lower": "1980-01-01",
    "date:inception_upper": "1980-01-01",
    "iso:country": "GB",
    "wof:name": "DH7 9PL",
    "wof:placetype": "postalcode"
  },
  "geometry": {"coordinates":[-1.6963,54.771525],"type":"Point"}
}
