{
  "type": "Feature",
  "properties": {
    "iso:country":"GB",
    "wof:name":"DH7 9PL",
    "wof:placetype":"postalcode"
},
  "geometry": {"coordinates":[-1.6962999523514,54.77152456715555],"type":"Point"}
}