{
  "type": "Feature",
  "properties": {
    "iso:country": "GB",
    "wof:name": "DT6 3BN",
    "wof:placetype": "postalcode"
  },
  "geometry": {"coordinates":[-2.747099,50.738191],"type":"Point"}
}
