{
  "type": "Feature",
  "properties": {
    "iso:country":"GB",
    "wof:name":"DT6 3BN",
    "wof:placetype":"postalcode"
},
  "geometry": {"coordinates":[-2.74714152339808,50.738219000777],"type":"Point"}
}