{
  "type": "Feature",
  "properties": {
    "date:inception_lower":"1986-07-01",
    "date:inception_upper":"1986-07-31",
    "iso:country":"GB",
    "wof:name":"BS24 9ES",
    "wof:placetype":"postalcode"
},
  "geometry": {"coordinates":[-2.952423,51.326987],"type":"Point"}
}