{
  "type": "Feature",
  "properties": {
    "iso:country":"GB",
    "wof:name":"BS24 9ES",
    "wof:placetype":"postalcode"
},
  "geometry": {"coordinates":[-2.95242271385385,51.32698670174941],"type":"Point"}
}