{
  "type": "Feature",
  "properties": {
    "iso:country": "GB",
    "wof:name": "BS24 9ES",
    "wof:placetype": "postalcode"
  },
  "geometry": {"coordinates":[-2.952423,51.326987],"type":"Point"}
}
