{
  "type": "Feature",
  "properties": {
    "iso:country":"GB",
    "wof:name":"WA8 6BF",
    "wof:placetype":"postalcode"
},
  "geometry": {"coordinates":[-2.7284823356217,53.36596857848157],"type":"Point"}
}