{
  "type": "Feature",
  "properties": {
    "date:inception_lower":"1994-05-01",
    "date:inception_upper":"1994-05-31",
    "iso:country":"GB",
    "wof:name":"M33 5ER",
    "wof:placetype":"postalcode"
},
  "geometry": {"coordinates":[-2.354926,53.42841],"type":"Point"}
}