{
  "type": "Feature",
  "properties": {
    "iso:country":"GB",
    "wof:name":"M33 5ER",
    "wof:placetype":"postalcode"
},
  "geometry": {"coordinates":[-2.35492577770048,53.42840965248099],"type":"Point"}
}