{
  "type": "Feature",
  "properties": {
    "iso:country":"GB",
    "wof:name":"DD1 3BA",
    "wof:placetype":"postalcode"
},
  "geometry": {"coordinates":[-2.96891903328408,56.46040163687424],"type":"Point"}
}