{
  "type": "Feature",
  "properties": {
    "iso:country":"GB",
    "wof:name":"S63 5NB",
    "wof:placetype":"postalcode"
},
  "geometry": {"coordinates":[-1.31428331923288,53.49886219388084],"type":"Point"}
}