{
  "type": "Feature",
  "properties": {
    "date:inception_lower":"2003-02-01",
    "date:inception_upper":"2003-02-28",
    "iso:country":"GB",
    "wof:name":"S63 5NB",
    "wof:placetype":"postalcode"
},
  "geometry": {"coordinates":[-1.313477,53.499425],"type":"Point"}
}