{
  "type": "Feature",
  "properties": {
    "iso:country": "GB",
    "wof:name": "S62 5RS",
    "wof:placetype": "postalcode"
  },
  "geometry": {"coordinates":[-1.333754,53.463674],"type":"Point"}
}
