{
  "type": "Feature",
  "properties": {
    "iso:country":"GB",
    "wof:name":"HS3 3DH",
    "wof:placetype":"postalcode"
},
  "geometry": {"coordinates":[-6.79826349945607,57.89938223608939],"type":"Point"}
}