{
  "type": "Feature",
  "properties": {
    "iso:country": "GB",
    "wof:name": "HS3 3DH",
    "wof:placetype": "postalcode"
  },
  "geometry": {"coordinates":[-6.798428,57.899227],"type":"Point"}
}
