{
  "type": "Feature",
  "properties": {
    "iso:country":"GB",
    "wof:name":"HX2 0JP",
    "wof:placetype":"postalcode"
},
  "geometry": {"coordinates":[-1.89685738164602,53.73225713080735],"type":"Point"}
}