{
  "type": "Feature",
  "properties": {
    "iso:country": "GB",
    "wof:name": "HX2 0JP",
    "wof:placetype": "postalcode"
  },
  "geometry": {"coordinates":[-1.896857,53.732257],"type":"Point"}
}
