{
  "type": "Feature",
  "properties": {
    "iso:country": "GB",
    "wof:name": "CH5 4ZE",
    "wof:placetype": "postalcode"
  },
  "geometry": {"coordinates":[-3.076655,53.206564],"type":"Point"}
}
