{
  "type": "Feature",
  "properties": {
    "iso:country":"GB",
    "wof:name":"LE2 0DP",
    "wof:placetype":"postalcode"
},
  "geometry": {"coordinates":[-1.11517539131021,52.63111478927249],"type":"Point"}
}