{
  "type": "Feature",
  "properties": {
    "iso:country": "GB",
    "wof:name": "NG6 8WS",
    "wof:placetype": "postalcode"
  },
  "geometry": {"coordinates":[-1.153609,53.028928],"type":"Point"}
}
