{
  "type": "Feature",
  "properties": {
    "date:inception_lower": "1992-08-01",
    "date:inception_upper": "1992-08-01",
    "iso:country": "GB",
    "wof:name": "NG6 8WS",
    "wof:placetype": "postalcode"
  },
  "geometry": {"coordinates":[-1.153609,53.028928],"type":"Point"}
}
