{
  "type": "Feature",
  "properties": {
    "iso:country": "GB",
    "wof:name": "LE15 6EL",
    "wof:placetype": "postalcode"
  },
  "geometry": {"coordinates":[-0.720225,52.673205],"type":"Point"}
}
