{
  "type": "Feature",
  "properties": {
    "iso:country":"GB",
    "wof:name":"LE15 6EL",
    "wof:placetype":"postalcode"
},
  "geometry": {"coordinates":[-0.7202251925949,52.67320519404512],"type":"Point"}
}