{
  "type": "Feature",
  "properties": {
    "iso:country":"GB",
    "wof:name":"PE19 2DD",
    "wof:placetype":"postalcode"
},
  "geometry": {"coordinates":[-0.26179113668566,52.22413588423058],"type":"Point"}
}