{
  "type": "Feature",
  "properties": {
    "iso:country":"GB",
    "wof:name":"HA5 4AA",
    "wof:placetype":"postalcode"
},
  "geometry": {"coordinates":[-0.37035736271787,51.61482591137624],"type":"Point"}
}