{
  "type": "Feature",
  "properties": {
    "date:inception_lower": "2007-08-01",
    "date:inception_upper": "2007-08-01",
    "iso:country": "GB",
    "wof:name": "WR14 1GS",
    "wof:placetype": "postalcode"
  },
  "geometry": {"coordinates":[-2.301864,52.127924],"type":"Point"}
}
