{
  "type": "Feature",
  "properties": {
    "iso:country":"GB",
    "wof:name":"WC2N 4DN",
    "wof:placetype":"postalcode"
},
  "geometry": {"coordinates":[-0.12517851219805,51.50938958923243],"type":"Point"}
}