{
  "type": "Feature",
  "properties": {
    "date:inception_lower": "2018-10-01",
    "date:inception_upper": "2018-10-01",
    "iso:country": "GB",
    "wof:name": "WR4 0AE",
    "wof:placetype": "postalcode"
  },
  "geometry": {"coordinates":[-2.158786,52.203519],"type":"Point"}
}
