{
  "type": "Feature",
  "properties": {
    "iso:country":"GB",
    "wof:name":"CF40 1DW",
    "wof:placetype":"postalcode"
},
  "geometry": {"coordinates":[-3.45342728265757,51.62046009936709],"type":"Point"}
}