{
  "type": "Feature",
  "properties": {
    "iso:country":"GB",
    "wof:name":"SW11 5UT",
    "wof:placetype":"postalcode"
},
  "geometry": {"coordinates":[-0.15547733525535,51.4660224581291],"type":"Point"}
}