{
  "type": "Feature",
  "properties": {
    "date:inception_lower": "1980-01-01",
    "date:inception_upper": "1980-01-01",
    "iso:country": "GB",
    "wof:name": "SA12 8NW",
    "wof:placetype": "postalcode"
  },
  "geometry": {"coordinates":[-3.802968,51.617194],"type":"Point"}
}
