{
  "type": "Feature",
  "properties": {
    "iso:country":"GB",
    "wof:name":"RH6 9DE",
    "wof:placetype":"postalcode"
},
  "geometry": {"coordinates":[-0.15050832425684,51.16706055412757],"type":"Point"}
}