{
  "type": "Feature",
  "properties": {
    "iso:country": "GB",
    "wof:name": "UB2 5QX",
    "wof:placetype": "postalcode"
  },
  "geometry": {"coordinates":[-0.372791,51.492143],"type":"Point"}
}
