{
  "type": "Feature",
  "properties": {
    "date:inception_lower": "2007-03-01",
    "date:inception_upper": "2007-03-01",
    "iso:country": "GB",
    "wof:name": "RH11 7GQ",
    "wof:placetype": "postalcode"
  },
  "geometry": {"coordinates":[-0.209882,51.129387],"type":"Point"}
}
