{
  "type": "Feature",
  "properties": {
    "iso:country":"GB",
    "wof:name":"SS7 1JW",
    "wof:placetype":"postalcode"
},
  "geometry": {"coordinates":[0.56531571199819,51.55054673686709],"type":"Point"}
}