{
  "type": "Feature",
  "properties": {
    "date:inception_lower": "1990-02-01",
    "date:inception_upper": "1990-02-01",
    "iso:country": "GB",
    "wof:name": "GL18 1PW",
    "wof:placetype": "postalcode"
  },
  "geometry": {"coordinates":[-2.411608,51.92868],"type":"Point"}
}
