{
  "type": "Feature",
  "properties": {
    "iso:country":"GB",
    "wof:name":"GL18 1PW",
    "wof:placetype":"postalcode"
},
  "geometry": {"coordinates":[-2.41160845703875,51.9286798972018],"type":"Point"}
}