{
  "type": "Feature",
  "properties": {
    "iso:country":"GB",
    "wof:name":"B45 9BL",
    "wof:placetype":"postalcode"
},
  "geometry": {"coordinates":[-2.01279954426387,52.39374720010508],"type":"Point"}
}