{
  "type": "Feature",
  "properties": {
    "iso:country":"GB",
    "wof:name":"DA9 9GQ",
    "wof:placetype":"postalcode"
},
  "geometry": {"coordinates":[0.28961318601857,51.45202289511226],"type":"Point"}
}