{
  "type": "Feature",
  "properties": {
    "iso:country":"GB",
    "wof:name":"LN5 8PE",
    "wof:placetype":"postalcode"
},
  "geometry": {"coordinates":[-0.55226722006988,53.20382493064494],"type":"Point"}
}