{
  "type": "Feature",
  "properties": {
    "iso:country": "GB",
    "wof:name": "LN5 8PE",
    "wof:placetype": "postalcode"
  },
  "geometry": {"coordinates":[-0.552207,53.203828],"type":"Point"}
}
