{
  "type": "Feature",
  "properties": {
    "iso:country":"GB",
    "wof:name":"PL26 7JJ",
    "wof:placetype":"postalcode"
},
  "geometry": {"coordinates":[-4.84605647582497,50.30775404832733],"type":"Point"}
}