{
  "type": "Feature",
  "properties": {
    "date:inception_lower": "1980-01-01",
    "date:inception_upper": "1980-01-01",
    "iso:country": "GB",
    "wof:name": "ST8 7PT",
    "wof:placetype": "postalcode"
  },
  "geometry": {"coordinates":[-2.180149,53.096396],"type":"Point"}
}
