{
  "type": "Feature",
  "properties": {
    "iso:country":"GB",
    "wof:name":"RM6 5RA",
    "wof:placetype":"postalcode"
},
  "geometry": {"coordinates":[0.14050967233648,51.57833045299483],"type":"Point"}
}