{
  "type": "Feature",
  "properties": {
    "iso:country":"GB",
    "wof:name":"RG30 2PX",
    "wof:placetype":"postalcode"
},
  "geometry": {"coordinates":[-1.0055268366296,51.45296927651559],"type":"Point"}
}