{
  "type": "Feature",
  "properties": {
    "iso:country": "GB",
    "wof:name": "BD23 3AL",
    "wof:placetype": "postalcode"
  },
  "geometry": {"coordinates":[-2.099958,53.954116],"type":"Point"}
}
