{
  "type": "Feature",
  "properties": {
    "iso:country": "GB",
    "wof:name": "FK1 5DT",
    "wof:placetype": "postalcode"
  },
  "geometry": {"coordinates":[-3.816611,55.997891],"type":"Point"}
}
