{
  "type": "Feature",
  "properties": {
    "date:inception_lower": "2020-05-01",
    "date:inception_upper": "2020-05-01",
    "iso:country": "GB",
    "wof:name": "BA11 6AW",
    "wof:placetype": "postalcode"
  },
  "geometry": {"coordinates":[-2.276844,51.280175],"type":"Point"}
}
