{
  "type": "Feature",
  "properties": {
    "iso:country":"GB",
    "wof:name":"PR25 5PH",
    "wof:placetype":"postalcode"
},
  "geometry": {"coordinates":[-2.66880418703355,53.7056260400518],"type":"Point"}
}