{
  "type": "Feature",
  "properties": {
    "iso:country": "GB",
    "wof:name": "PR25 5PH",
    "wof:placetype": "postalcode"
  },
  "geometry": {"coordinates":[-2.668804,53.705626],"type":"Point"}
}
