{
  "type": "Feature",
  "properties": {
    "iso:country": "GB",
    "wof:name": "AL2 3NP",
    "wof:placetype": "postalcode"
  },
  "geometry": {"coordinates":[-0.364517,51.733826],"type":"Point"}
}
