{
  "type": "Feature",
  "properties": {
    "iso:country":"GB",
    "wof:name":"AL2 3NP",
    "wof:placetype":"postalcode"
},
  "geometry": {"coordinates":[-0.36451655907234,51.73382623799431],"type":"Point"}
}