{
  "type": "Feature",
  "properties": {
    "date:inception_lower":"1980-01-01",
    "date:inception_upper":"1980-01-31",
    "iso:country":"GB",
    "wof:name":"AL2 3NP",
    "wof:placetype":"postalcode"
},
  "geometry": {"coordinates":[-0.364517,51.733826],"type":"Point"}
}