{
  "type": "Feature",
  "properties": {
    "date:inception_lower": "1980-01-01",
    "date:inception_upper": "1980-01-01",
    "iso:country": "GB",
    "wof:name": "W13 9QP",
    "wof:placetype": "postalcode"
  },
  "geometry": {"coordinates":[-0.318989,51.505053],"type":"Point"}
}
