{
  "type": "Feature",
  "properties": {
    "iso:country":"GB",
    "wof:name":"W13 9QP",
    "wof:placetype":"postalcode"
},
  "geometry": {"coordinates":[-0.31898876253915,51.50505262707632],"type":"Point"}
}