{
  "type": "Feature",
  "properties": {
    "iso:country":"GB",
    "wof:name":"CT15 5AS",
    "wof:placetype":"postalcode"
},
  "geometry": {"coordinates":[1.28852921561775,51.17640077458823],"type":"Point"}
}