{
  "type": "Feature",
  "properties": {
    "date:inception_lower": "1995-12-01",
    "date:inception_upper": "1995-12-01",
    "iso:country": "GB",
    "wof:name": "HP17 8HT",
    "wof:placetype": "postalcode"
  },
  "geometry": {"coordinates":[-0.927706,51.77223],"type":"Point"}
}
