{
  "type": "Feature",
  "properties": {
    "date:inception_lower": "1980-01-01",
    "date:inception_upper": "1980-01-01",
    "iso:country": "GB",
    "wof:name": "G52 2BX",
    "wof:placetype": "postalcode"
  },
  "geometry": {"coordinates":[-4.343142,55.849734],"type":"Point"}
}
