{
  "type": "Feature",
  "properties": {
    "iso:country": "GB",
    "wof:name": "SA69 9JE",
    "wof:placetype": "postalcode"
  },
  "geometry": {"coordinates":[-4.700877,51.712452],"type":"Point"}
}
