{
  "type": "Feature",
  "properties": {
    "iso:country": "GB",
    "wof:name": "G43 1EX",
    "wof:placetype": "postalcode"
  },
  "geometry": {"coordinates":[-4.306744,55.814894],"type":"Point"}
}
