{
  "type": "Feature",
  "properties": {
    "iso:country":"GB",
    "wof:name":"G43 1EX",
    "wof:placetype":"postalcode"
},
  "geometry": {"coordinates":[-4.30674454592817,55.81489412514551],"type":"Point"}
}