{
  "type": "Feature",
  "properties": {
    "iso:country":"GB",
    "wof:name":"NR30 2JY",
    "wof:placetype":"postalcode"
},
  "geometry": {"coordinates":[1.73264020609015,52.60407933563792],"type":"Point"}
}