{
  "type": "Feature",
  "properties": {
    "iso:country":"GB",
    "wof:name":"G66 7EH",
    "wof:placetype":"postalcode"
},
  "geometry": {"coordinates":[-4.19646339321451,55.97361621375004],"type":"Point"}
}