{
  "type": "Feature",
  "properties": {
    "iso:country":"GB",
    "wof:name":"BL3 6QU",
    "wof:placetype":"postalcode"
},
  "geometry": {"coordinates":[-2.42851593537658,53.56550319948624],"type":"Point"}
}