{
  "type": "Feature",
  "properties": {
    "iso:country":"GB",
    "wof:name":"WV4 5NS",
    "wof:placetype":"postalcode"
},
  "geometry": {"coordinates":[-2.15255689563026,52.5564755501338],"type":"Point"}
}