{
  "type": "Feature",
  "properties": {
    "iso:country":"GB",
    "wof:name":"NE19 2AW",
    "wof:placetype":"postalcode"
},
  "geometry": {"coordinates":[-1.98192160228442,55.12498971086443],"type":"Point"}
}