{
  "type": "Feature",
  "properties": {
    "date:inception_lower":"1980-01-01",
    "date:inception_upper":"1980-01-31",
    "iso:country":"GB",
    "wof:name":"NE19 2AW",
    "wof:placetype":"postalcode"
},
  "geometry": {"coordinates":[-1.981922,55.12499],"type":"Point"}
}