{
  "type": "Feature",
  "properties": {
    "date:inception_lower": "2001-12-01",
    "date:inception_upper": "2001-12-01",
    "iso:country": "GB",
    "wof:name": "CF63 1FG",
    "wof:placetype": "postalcode"
  },
  "geometry": {"coordinates":[-3.247935,51.421379],"type":"Point"}
}
