{
  "type": "Feature",
  "properties": {
    "iso:country": "GB",
    "wof:name": "TN34 3FH",
    "wof:placetype": "postalcode"
  },
  "geometry": {"coordinates":[0.590601,50.866932],"type":"Point"}
}
