{
  "type": "Feature",
  "properties": {
    "iso:country":"GB",
    "wof:name":"TN34 3FH",
    "wof:placetype":"postalcode"
},
  "geometry": {"coordinates":[0.5906005852861,50.86693233233488],"type":"Point"}
}