{
  "type": "Feature",
  "properties": {
    "date:inception_lower":"2012-08-01",
    "date:inception_upper":"2012-08-31",
    "iso:country":"GB",
    "wof:name":"TN34 3FH",
    "wof:placetype":"postalcode"
},
  "geometry": {"coordinates":[0.590601,50.866932],"type":"Point"}
}