{
  "type": "Feature",
  "properties": {
    "iso:country":"GB",
    "wof:name":"MK3 7SB",
    "wof:placetype":"postalcode"
},
  "geometry": {"coordinates":[-0.76956734003216,51.99501938754415],"type":"Point"}
}