{
  "type": "Feature",
  "properties": {
    "iso:country":"GB",
    "wof:name":"LE12 7LL",
    "wof:placetype":"postalcode"
},
  "geometry": {"coordinates":[-1.08588398310939,52.75402762214161],"type":"Point"}
}