{
  "type": "Feature",
  "properties": {
    "iso:country": "GB",
    "wof:name": "BN3 3YF",
    "wof:placetype": "postalcode"
  },
  "geometry": {"coordinates":[-0.173028,50.830907],"type":"Point"}
}
