{
  "type": "Feature",
  "properties": {
    "date:inception_lower": "1998-12-01",
    "date:inception_upper": "1998-12-01",
    "iso:country": "GB",
    "wof:name": "B45 8GH",
    "wof:placetype": "postalcode"
  },
  "geometry": {"coordinates":[-2.007716,52.368248],"type":"Point"}
}
