{
  "type": "Feature",
  "properties": {
    "iso:country":"GB",
    "wof:name":"B45 8GH",
    "wof:placetype":"postalcode"
},
  "geometry": {"coordinates":[-2.0076515837083,52.36815281529758],"type":"Point"}
}