{
  "type": "Feature",
  "properties": {
    "iso:country": "GB",
    "wof:name": "TW12 3PE",
    "wof:placetype": "postalcode"
  },
  "geometry": {"coordinates":[-0.383275,51.422966],"type":"Point"}
}
