{
  "type": "Feature",
  "properties": {
    "date:inception_lower": "1980-01-01",
    "date:inception_upper": "1980-01-01",
    "iso:country": "GB",
    "wof:name": "NE10 9EH",
    "wof:placetype": "postalcode"
  },
  "geometry": {"coordinates":[-1.566854,54.947033],"type":"Point"}
}
