{
  "type": "Feature",
  "properties": {
    "iso:country":"GB",
    "wof:name":"NE10 9EH",
    "wof:placetype":"postalcode"
},
  "geometry": {"coordinates":[-1.56685365481797,54.94703253285675],"type":"Point"}
}