{
  "type": "Feature",
  "properties": {
    "date:inception_lower": "1980-01-01",
    "date:inception_upper": "1980-01-01",
    "iso:country": "GB",
    "wof:name": "SW1X 7DW",
    "wof:placetype": "postalcode"
  },
  "geometry": {"coordinates":[-0.152692,51.500393],"type":"Point"}
}
