{
  "type": "Feature",
  "properties": {
    "iso:country":"GB",
    "wof:name":"B31 5JE",
    "wof:placetype":"postalcode"
},
  "geometry": {"coordinates":[-1.99748628437069,52.40704422829459],"type":"Point"}
}