{
  "type": "Feature",
  "properties": {
    "date:inception_lower":"1980-01-01",
    "date:inception_upper":"1980-01-31",
    "iso:country":"GB",
    "wof:name":"NG22 9QX",
    "wof:placetype":"postalcode"
},
  "geometry": {"coordinates":[-1.014964,53.201698],"type":"Point"}
}