{
  "type": "Feature",
  "properties": {
    "iso:country":"GB",
    "wof:name":"NG22 9QX",
    "wof:placetype":"postalcode"
},
  "geometry": {"coordinates":[-1.01496409698186,53.20169760073426],"type":"Point"}
}