{
  "type": "Feature",
  "properties": {
    "date:inception_lower": "1980-01-01",
    "date:inception_upper": "1980-01-01",
    "iso:country": "GB",
    "wof:name": "EH22 1AB",
    "wof:placetype": "postalcode"
  },
  "geometry": {"coordinates":[-3.069547,55.892199],"type":"Point"}
}
