{
  "type": "Feature",
  "properties": {
    "iso:country": "GB",
    "wof:name": "PO21 3QP",
    "wof:placetype": "postalcode"
  },
  "geometry": {"coordinates":[-0.703217,50.784523],"type":"Point"}
}
