{
  "type": "Feature",
  "properties": {
    "iso:country":"GB",
    "wof:name":"PO5 2RH",
    "wof:placetype":"postalcode"
},
  "geometry": {"coordinates":[-1.08237734335927,50.78356176310206],"type":"Point"}
}