{
  "type": "Feature",
  "properties": {
    "iso:country":"GB",
    "wof:name":"HR2 0LG",
    "wof:placetype":"postalcode"
},
  "geometry": {"coordinates":[-2.98997819124016,51.95833170382593],"type":"Point"}
}