{
  "type": "Feature",
  "properties": {
    "iso:country":"GB",
    "wof:name":"SN9 5NS",
    "wof:placetype":"postalcode"
},
  "geometry": {"coordinates":[-1.79789635307361,51.34851768329673],"type":"Point"}
}