{
  "type": "Feature",
  "properties": {
    "iso:country":"GB",
    "wof:name":"AB54 8BJ",
    "wof:placetype":"postalcode"
},
  "geometry": {"coordinates":[-2.78461642353653,57.44353368965076],"type":"Point"}
}