{
  "type": "Feature",
  "properties": {
    "iso:country": "GB",
    "wof:name": "AB54 8BJ",
    "wof:placetype": "postalcode"
  },
  "geometry": {"coordinates":[-2.784616,57.443534],"type":"Point"}
}
