{
  "type": "Feature",
  "properties": {
    "iso:country":"GB",
    "wof:name":"TF10 9HL",
    "wof:placetype":"postalcode"
},
  "geometry": {"coordinates":[-2.40183257570059,52.72786567538062],"type":"Point"}
}