{
  "type": "Feature",
  "properties": {
    "date:inception_lower":"1980-01-01",
    "date:inception_upper":"1980-01-31",
    "iso:country":"GB",
    "wof:name":"TF10 9HL",
    "wof:placetype":"postalcode"
},
  "geometry": {"coordinates":[-2.401831,52.72788],"type":"Point"}
}