{
  "type": "Feature",
  "properties": {
    "iso:country": "GB",
    "wof:name": "TF10 9HL",
    "wof:placetype": "postalcode"
  },
  "geometry": {"coordinates":[-2.401831,52.72788],"type":"Point"}
}
