{
  "type": "Feature",
  "properties": {
    "iso:country":"GB",
    "wof:name":"CO2 0NZ",
    "wof:placetype":"postalcode"
},
  "geometry": {"coordinates":[0.78567982352595,51.84847825455288],"type":"Point"}
}