{
  "type": "Feature",
  "properties": {
    "iso:country": "GB",
    "wof:name": "GU10 1DW",
    "wof:placetype": "postalcode"
  },
  "geometry": {"coordinates":[-0.735416,51.230769],"type":"Point"}
}
