{
  "type": "Feature",
  "properties": {
    "iso:country":"GB",
    "wof:name":"W4 3TS",
    "wof:placetype":"postalcode"
},
  "geometry": {"coordinates":[-0.27388398780892,51.48036983752605],"type":"Point"}
}