{
  "type": "Feature",
  "properties": {
    "iso:country":"GB",
    "wof:name":"WD25 9ND",
    "wof:placetype":"postalcode"
},
  "geometry": {"coordinates":[-0.38348102983225,51.69787801995304],"type":"Point"}
}