{
  "type": "Feature",
  "properties": {
    "iso:country":"GB",
    "wof:name":"NP10 9HR",
    "wof:placetype":"postalcode"
},
  "geometry": {"coordinates":[-3.04690269302048,51.58542459164862],"type":"Point"}
}