{
  "type": "Feature",
  "properties": {
    "iso:country": "GB",
    "wof:name": "NP10 9HR",
    "wof:placetype": "postalcode"
  },
  "geometry": {"coordinates":[-3.046903,51.585425],"type":"Point"}
}
