{
  "type": "Feature",
  "properties": {
    "iso:country":"GB",
    "wof:name":"SA70 8AP",
    "wof:placetype":"postalcode"
},
  "geometry": {"coordinates":[-4.70249828308837,51.67508137942318],"type":"Point"}
}