{
  "type": "Feature",
  "properties": {
    "date:inception_lower": "1980-01-01",
    "date:inception_upper": "1980-01-01",
    "iso:country": "GB",
    "wof:name": "N2 9LU",
    "wof:placetype": "postalcode"
  },
  "geometry": {"coordinates":[-0.154219,51.588426],"type":"Point"}
}
