{
  "type": "Feature",
  "properties": {
    "iso:country":"GB",
    "wof:name":"N2 9LU",
    "wof:placetype":"postalcode"
},
  "geometry": {"coordinates":[-0.15421941416833,51.58842616974099],"type":"Point"}
}