{
  "type": "Feature",
  "properties": {
    "iso:country": "GB",
    "wof:name": "N2 9LU",
    "wof:placetype": "postalcode"
  },
  "geometry": {"coordinates":[-0.154219,51.588426],"type":"Point"}
}
