{
  "type": "Feature",
  "properties": {
    "iso:country":"GB",
    "wof:name":"WN2 5DH",
    "wof:placetype":"postalcode"
},
  "geometry": {"coordinates":[-2.6019661814564,53.51856389867346],"type":"Point"}
}