{
  "type": "Feature",
  "properties": {
    "date:inception_lower": "1980-01-01",
    "date:inception_upper": "1980-01-01",
    "iso:country": "GB",
    "wof:name": "WN2 5DH",
    "wof:placetype": "postalcode"
  },
  "geometry": {"coordinates":[-2.601966,53.518564],"type":"Point"}
}
