{
  "type": "Feature",
  "properties": {
    "date:inception_lower": "2018-01-01",
    "date:inception_upper": "2018-01-01",
    "iso:country": "GB",
    "wof:name": "LE11 2WE",
    "wof:placetype": "postalcode"
  },
  "geometry": {"coordinates":[-1.195553,52.756316],"type":"Point"}
}
