{
  "type": "Feature",
  "properties": {
    "iso:country":"GB",
    "wof:name":"EH22 5PX",
    "wof:placetype":"postalcode"
},
  "geometry": {"coordinates":[-3.04221447239353,55.86692343641966],"type":"Point"}
}