{
  "type": "Feature",
  "properties": {
    "iso:country": "GB",
    "wof:name": "EH22 5PX",
    "wof:placetype": "postalcode"
  },
  "geometry": {"coordinates":[-3.042214,55.866923],"type":"Point"}
}
