{
  "type": "Feature",
  "properties": {
    "iso:country":"GB",
    "wof:name":"LN5 9DS",
    "wof:placetype":"postalcode"
},
  "geometry": {"coordinates":[-0.55995585730067,53.18125513356626],"type":"Point"}
}