{
  "type": "Feature",
  "properties": {
    "iso:country":"GB",
    "wof:name":"M24 4EP",
    "wof:placetype":"postalcode"
},
  "geometry": {"coordinates":[-2.21561496841149,53.55414933295816],"type":"Point"}
}