{
  "type": "Feature",
  "properties": {
    "date:inception_lower": "1980-01-01",
    "date:inception_upper": "1980-01-01",
    "iso:country": "GB",
    "wof:name": "M24 4EP",
    "wof:placetype": "postalcode"
  },
  "geometry": {"coordinates":[-2.215615,53.554149],"type":"Point"}
}
