{
  "type": "Feature",
  "properties": {
    "iso:country": "GB",
    "wof:name": "DY11 7XQ",
    "wof:placetype": "postalcode"
  },
  "geometry": {"coordinates":[-2.229337,52.331538],"type":"Point"}
}
