{
  "type": "Feature",
  "properties": {
    "date:inception_lower": "1980-01-01",
    "date:inception_upper": "1980-01-01",
    "iso:country": "GB",
    "wof:name": "DY11 7XQ",
    "wof:placetype": "postalcode"
  },
  "geometry": {"coordinates":[-2.229337,52.331538],"type":"Point"}
}
