{
  "type": "Feature",
  "properties": {
    "iso:country": "GB",
    "wof:name": "NE46 2NW",
    "wof:placetype": "postalcode"
  },
  "geometry": {"coordinates":[-2.165303,54.969282],"type":"Point"}
}
