{
  "type": "Feature",
  "properties": {
    "iso:country": "GB",
    "wof:name": "N4 3AS",
    "wof:placetype": "postalcode"
  },
  "geometry": {"coordinates":[-0.111913,51.570551],"type":"Point"}
}
