{
  "type": "Feature",
  "properties": {
    "date:inception_lower": "2023-06-01",
    "date:inception_upper": "2023-06-01",
    "iso:country": "GB",
    "wof:name": "CM23 4RU",
    "wof:placetype": "postalcode"
  },
  "geometry": {"coordinates":[0.159405,51.852528],"type":"Point"}
}
