{
  "type": "Feature",
  "properties": {
    "date:inception_lower": "1980-01-01",
    "date:inception_upper": "1980-01-01",
    "iso:country": "GB",
    "wof:name": "CV6 6FU",
    "wof:placetype": "postalcode"
  },
  "geometry": {"coordinates":[-1.498248,52.440952],"type":"Point"}
}
