{
  "type": "Feature",
  "properties": {
    "iso:country":"GB",
    "wof:name":"CV6 6FU",
    "wof:placetype":"postalcode"
},
  "geometry": {"coordinates":[-1.49824776680326,52.44095233212899],"type":"Point"}
}