{
  "type": "Feature",
  "properties": {
    "iso:country": "GB",
    "wof:name": "CV6 6FU",
    "wof:placetype": "postalcode"
  },
  "geometry": {"coordinates":[-1.498248,52.440952],"type":"Point"}
}
