{
  "type": "Feature",
  "properties": {
    "date:inception_lower": "1994-12-01",
    "date:inception_upper": "1994-12-01",
    "iso:country": "GB",
    "wof:name": "SO32 1FR",
    "wof:placetype": "postalcode"
  },
  "geometry": {"coordinates":[-1.220814,50.969213],"type":"Point"}
}
