{
  "type": "Feature",
  "properties": {
    "iso:country":"GB",
    "wof:name":"SO32 1FR",
    "wof:placetype":"postalcode"
},
  "geometry": {"coordinates":[-1.22081420284822,50.96921332249315],"type":"Point"}
}