{
  "type": "Feature",
  "properties": {
    "iso:country": "GB",
    "wof:name": "BB2 5FN",
    "wof:placetype": "postalcode"
  },
  "geometry": {"coordinates":[-2.517697,53.725688],"type":"Point"}
}
