{
  "type": "Feature",
  "properties": {
    "iso:country":"GB",
    "wof:name":"MK40 2PR",
    "wof:placetype":"postalcode"
},
  "geometry": {"coordinates":[-0.4629392855331,52.13934349158982],"type":"Point"}
}