{
  "type": "Feature",
  "properties": {
    "iso:country": "GB",
    "wof:name": "G67 2DL",
    "wof:placetype": "postalcode"
  },
  "geometry": {"coordinates":[-3.975124,55.953539],"type":"Point"}
}
