{
  "type": "Feature",
  "properties": {
    "iso:country": "GB",
    "wof:name": "KT13 0RH",
    "wof:placetype": "postalcode"
  },
  "geometry": {"coordinates":[-0.458177,51.354689],"type":"Point"}
}
