{
  "type": "Feature",
  "properties": {
    "date:inception_lower":"1997-12-01",
    "date:inception_upper":"1997-12-31",
    "iso:country":"GB",
    "wof:name":"BS35 3SF",
    "wof:placetype":"postalcode"
},
  "geometry": {"coordinates":[-2.54162,51.577336],"type":"Point"}
}