{
  "type": "Feature",
  "properties": {
    "iso:country": "GB",
    "wof:name": "DL4 2GX",
    "wof:placetype": "postalcode"
  },
  "geometry": {"coordinates":[-1.630145,54.629173],"type":"Point"}
}
