{
  "type": "Feature",
  "properties": {
    "iso:country": "GB",
    "wof:name": "CH65 3DQ",
    "wof:placetype": "postalcode"
  },
  "geometry": {"coordinates":[-2.914345,53.289137],"type":"Point"}
}
