{
  "type": "Feature",
  "properties": {
    "iso:country": "GB",
    "wof:name": "CO7 0RX",
    "wof:placetype": "postalcode"
  },
  "geometry": {"coordinates":[1.020304,51.817033],"type":"Point"}
}
