{
  "type": "Feature",
  "properties": {
    "iso:country":"GB",
    "wof:name":"CO7 0RX",
    "wof:placetype":"postalcode"
},
  "geometry": {"coordinates":[1.02030411286326,51.81703344300298],"type":"Point"}
}