{
  "type": "Feature",
  "properties": {
    "iso:country": "GB",
    "wof:name": "TN10 3LU",
    "wof:placetype": "postalcode"
  },
  "geometry": {"coordinates":[0.27432,51.21926],"type":"Point"}
}
