{
  "type": "Feature",
  "properties": {
    "iso:country":"GB",
    "wof:name":"TN10 3LU",
    "wof:placetype":"postalcode"
},
  "geometry": {"coordinates":[0.27431986946328,51.2192601554399],"type":"Point"}
}