{
  "type": "Feature",
  "properties": {
    "date:inception_lower": "1980-01-01",
    "date:inception_upper": "1980-01-01",
    "iso:country": "GB",
    "wof:name": "TN10 3LU",
    "wof:placetype": "postalcode"
  },
  "geometry": {"coordinates":[0.27432,51.21926],"type":"Point"}
}
