{
  "type": "Feature",
  "properties": {
    "date:inception_lower": "1980-01-01",
    "date:inception_upper": "1980-01-01",
    "iso:country": "GB",
    "wof:name": "KY5 9LQ",
    "wof:placetype": "postalcode"
  },
  "geometry": {"coordinates":[-3.307282,56.12368],"type":"Point"}
}
