{
  "type": "Feature",
  "properties": {
    "iso:country":"GB",
    "wof:name":"CO12 4NZ",
    "wof:placetype":"postalcode"
},
  "geometry": {"coordinates":[1.25063870745151,51.93900219151324],"type":"Point"}
}