{
  "type": "Feature",
  "properties": {
    "iso:country":"GB",
    "wof:name":"OX33 1LT",
    "wof:placetype":"postalcode"
},
  "geometry": {"coordinates":[-1.13492805373605,51.74686764806214],"type":"Point"}
}