{
  "type": "Feature",
  "properties": {
    "date:inception_lower": "1992-08-01",
    "date:inception_upper": "1992-08-01",
    "iso:country": "GB",
    "wof:name": "OX33 1LT",
    "wof:placetype": "postalcode"
  },
  "geometry": {"coordinates":[-1.13491,51.746783],"type":"Point"}
}
