{
  "type": "Feature",
  "properties": {
    "iso:country": "GB",
    "wof:name": "LA3 2BE",
    "wof:placetype": "postalcode"
  },
  "geometry": {"coordinates":[-2.889896,54.051229],"type":"Point"}
}
