{
  "type": "Feature",
  "properties": {
    "iso:country":"GB",
    "wof:name":"LA3 2BE",
    "wof:placetype":"postalcode"
},
  "geometry": {"coordinates":[-2.88989654273253,54.05122932566182],"type":"Point"}
}