{
  "type": "Feature",
  "properties": {
    "iso:country":"GB",
    "wof:name":"SY13 2LP",
    "wof:placetype":"postalcode"
},
  "geometry": {"coordinates":[-2.79435989871152,52.90877112243776],"type":"Point"}
}