{
  "type": "Feature",
  "properties": {
    "date:inception_lower":"1980-01-01",
    "date:inception_upper":"1980-01-31",
    "iso:country":"GB",
    "wof:name":"SY13 2LP",
    "wof:placetype":"postalcode"
},
  "geometry": {"coordinates":[-2.79436,52.908771],"type":"Point"}
}