{
  "type": "Feature",
  "properties": {
    "iso:country": "GB",
    "wof:name": "SY13 2LP",
    "wof:placetype": "postalcode"
  },
  "geometry": {"coordinates":[-2.79436,52.908771],"type":"Point"}
}
