{
  "type": "Feature",
  "properties": {
    "iso:country":"GB",
    "wof:name":"NG16 3FX",
    "wof:placetype":"postalcode"
},
  "geometry": {"coordinates":[-1.30086201005124,53.02095838297991],"type":"Point"}
}