{
  "type": "Feature",
  "properties": {
    "date:inception_lower": "1980-01-01",
    "date:inception_upper": "1980-01-01",
    "iso:country": "GB",
    "wof:name": "NG16 3FX",
    "wof:placetype": "postalcode"
  },
  "geometry": {"coordinates":[-1.300862,53.020958],"type":"Point"}
}
