{
  "type": "Feature",
  "properties": {
    "iso:country": "GB",
    "wof:name": "ME12 1YL",
    "wof:placetype": "postalcode"
  },
  "geometry": {"coordinates":[0.763261,51.432611],"type":"Point"}
}
