{
  "type": "Feature",
  "properties": {
    "iso:country": "GB",
    "wof:name": "BH20 7HZ",
    "wof:placetype": "postalcode"
  },
  "geometry": {"coordinates":[-2.219906,50.754929],"type":"Point"}
}
