{
  "type": "Feature",
  "properties": {
    "iso:country": "GB",
    "wof:name": "HX4 8EN",
    "wof:placetype": "postalcode"
  },
  "geometry": {"coordinates":[-1.867967,53.688331],"type":"Point"}
}
