{
  "type": "Feature",
  "properties": {
    "iso:country":"GB",
    "wof:name":"NG9 4FF",
    "wof:placetype":"postalcode"
},
  "geometry": {"coordinates":[-1.23936188363877,52.92536515205929],"type":"Point"}
}