{
  "type": "Feature",
  "properties": {
    "date:inception_lower": "2022-06-01",
    "date:inception_upper": "2022-06-01",
    "iso:country": "GB",
    "wof:name": "OL7 0FZ",
    "wof:placetype": "postalcode"
  },
  "geometry": {"coordinates":[-2.097958,53.484112],"type":"Point"}
}
