{
  "type": "Feature",
  "properties": {
    "iso:country": "GB",
    "wof:name": "MK12 5JN",
    "wof:placetype": "postalcode"
  },
  "geometry": {"coordinates":[-0.809141,52.062509],"type":"Point"}
}
