{
  "type": "Feature",
  "properties": {
    "iso:country":"GB",
    "wof:name":"DH2 3HB",
    "wof:placetype":"postalcode"
},
  "geometry": {"coordinates":[-1.58654529453078,54.84600418867925],"type":"Point"}
}