{
  "type": "Feature",
  "properties": {
    "date:inception_lower":"1980-01-01",
    "date:inception_upper":"1980-01-31",
    "iso:country":"GB",
    "wof:name":"DH2 3HB",
    "wof:placetype":"postalcode"
},
  "geometry": {"coordinates":[-1.586545,54.846004],"type":"Point"}
}