{
  "type": "Feature",
  "properties": {
    "iso:country": "GB",
    "wof:name": "DH2 3HB",
    "wof:placetype": "postalcode"
  },
  "geometry": {"coordinates":[-1.586545,54.846004],"type":"Point"}
}
