{
  "type": "Feature",
  "properties": {
    "iso:country":"GB",
    "wof:name":"TN38 9JU",
    "wof:placetype":"postalcode"
},
  "geometry": {"coordinates":[0.54850702144715,50.87589135036616],"type":"Point"}
}