{
  "type": "Feature",
  "properties": {
    "iso:country": "GB",
    "wof:name": "B79 8TR",
    "wof:placetype": "postalcode"
  },
  "geometry": {"coordinates":[-1.68532,52.644625],"type":"Point"}
}
