{
  "type": "Feature",
  "properties": {
    "date:inception_lower":"1980-01-01",
    "date:inception_upper":"1980-01-31",
    "iso:country":"GB",
    "wof:name":"M6 5LR",
    "wof:placetype":"postalcode"
},
  "geometry": {"coordinates":[-2.293582,53.487298],"type":"Point"}
}