{
  "type": "Feature",
  "properties": {
    "iso:country":"GB",
    "wof:name":"TQ1 1JX",
    "wof:placetype":"postalcode"
},
  "geometry": {"coordinates":[-3.51603057735262,50.47138347654107],"type":"Point"}
}