{
  "type": "Feature",
  "properties": {
    "iso:country":"GB",
    "wof:name":"BS16 5DU",
    "wof:placetype":"postalcode"
},
  "geometry": {"coordinates":[-2.5143467641525,51.48404593035752],"type":"Point"}
}