{
  "type": "Feature",
  "properties": {
    "iso:country": "GB",
    "wof:name": "DA10 0GA",
    "wof:placetype": "postalcode"
  },
  "geometry": {"coordinates":[0.30868,51.44708],"type":"Point"}
}
