{
  "type": "Feature",
  "properties": {
    "iso:country":"GB",
    "wof:name":"DA10 0GA",
    "wof:placetype":"postalcode"
},
  "geometry": {"coordinates":[0.30868004979489,51.44708034152828],"type":"Point"}
}