{
  "type": "Feature",
  "properties": {
    "date:inception_lower": "2018-01-01",
    "date:inception_upper": "2018-01-01",
    "iso:country": "GB",
    "wof:name": "NE27 0XQ",
    "wof:placetype": "postalcode"
  },
  "geometry": {"coordinates":[-1.540367,55.039403],"type":"Point"}
}
