{
  "type": "Feature",
  "properties": {
    "iso:country": "GB",
    "wof:name": "NE27 0XQ",
    "wof:placetype": "postalcode"
  },
  "geometry": {"coordinates":[-1.540243,55.039304],"type":"Point"}
}
