{
  "type": "Feature",
  "properties": {
    "date:inception_lower": "1980-01-01",
    "date:inception_upper": "1980-01-01",
    "iso:country": "GB",
    "wof:name": "UB1 1PQ",
    "wof:placetype": "postalcode"
  },
  "geometry": {"coordinates":[-0.387658,51.514559],"type":"Point"}
}
