{
  "type": "Feature",
  "properties": {
    "iso:country":"GB",
    "wof:name":"PA34 4EH",
    "wof:placetype":"postalcode"
},
  "geometry": {"coordinates":[-5.46128963605465,56.40882903139538],"type":"Point"}
}