{
  "type": "Feature",
  "properties": {
    "date:inception_lower": "1980-01-01",
    "date:inception_upper": "1980-01-01",
    "iso:country": "GB",
    "wof:name": "BA14 7JP",
    "wof:placetype": "postalcode"
  },
  "geometry": {"coordinates":[-2.190614,51.327591],"type":"Point"}
}
