{
  "type": "Feature",
  "properties": {
    "iso:country":"GB",
    "wof:name":"BA14 7JP",
    "wof:placetype":"postalcode"
},
  "geometry": {"coordinates":[-2.19071755757037,51.32738734507371],"type":"Point"}
}