{
  "type": "Feature",
  "properties": {
    "iso:country":"GB",
    "wof:name":"MK9 1AH",
    "wof:placetype":"postalcode"
},
  "geometry": {"coordinates":[-0.77251401231184,52.03905289379269],"type":"Point"}
}