{
  "type": "Feature",
  "properties": {
    "date:inception_lower": "1996-06-01",
    "date:inception_upper": "1996-06-01",
    "iso:country": "GB",
    "wof:name": "MK9 1AH",
    "wof:placetype": "postalcode"
  },
  "geometry": {"coordinates":[-0.772514,52.039053],"type":"Point"}
}
