{
  "type": "Feature",
  "properties": {
    "iso:country":"GB",
    "wof:name":"N16 7RT",
    "wof:placetype":"postalcode"
},
  "geometry": {"coordinates":[-0.06683744176197,51.56057235246482],"type":"Point"}
}