{
  "type": "Feature",
  "properties": {
    "iso:country": "GB",
    "wof:name": "CH63 0LY",
    "wof:placetype": "postalcode"
  },
  "geometry": {"coordinates":[-3.011791,53.320117],"type":"Point"}
}
