{
  "type": "Feature",
  "properties": {
    "iso:country":"GB",
    "wof:name":"AL10 9DE",
    "wof:placetype":"postalcode"
},
  "geometry": {"coordinates":[-0.23643195965602,51.74888790534439],"type":"Point"}
}