{
  "type": "Feature",
  "properties": {
    "iso:country": "GB",
    "wof:name": "AL10 9DE",
    "wof:placetype": "postalcode"
  },
  "geometry": {"coordinates":[-0.236432,51.748888],"type":"Point"}
}
