{
  "type": "Feature",
  "properties": {
    "date:inception_lower": "1980-01-01",
    "date:inception_upper": "1980-01-01",
    "iso:country": "GB",
    "wof:name": "GL18 1HF",
    "wof:placetype": "postalcode"
  },
  "geometry": {"coordinates":[-2.351619,51.917672],"type":"Point"}
}
