{
  "type": "Feature",
  "properties": {
    "iso:country":"GB",
    "wof:name":"GL18 1HF",
    "wof:placetype":"postalcode"
},
  "geometry": {"coordinates":[-2.35161944529247,51.91767189028831],"type":"Point"}
}