{
  "type": "Feature",
  "properties": {
    "date:inception_lower": "2022-10-01",
    "date:inception_upper": "2022-10-01",
    "iso:country": "GB",
    "wof:name": "SN11 8NB",
    "wof:placetype": "postalcode"
  },
  "geometry": {"coordinates":[-1.992835,51.448047],"type":"Point"}
}
