{
  "type": "Feature",
  "properties": {
    "iso:country":"GB",
    "wof:name":"SN14 6DQ",
    "wof:placetype":"postalcode"
},
  "geometry": {"coordinates":[-2.13615814737502,51.51812123915104],"type":"Point"}
}