{
  "type": "Feature",
  "properties": {
    "iso:country": "GB",
    "wof:name": "N11 3NE",
    "wof:placetype": "postalcode"
  },
  "geometry": {"coordinates":[-0.151554,51.609274],"type":"Point"}
}
