{
  "type": "Feature",
  "properties": {
    "iso:country":"GB",
    "wof:name":"N11 3NE",
    "wof:placetype":"postalcode"
},
  "geometry": {"coordinates":[-0.15155419858874,51.60927351137424],"type":"Point"}
}