{
  "type": "Feature",
  "properties": {
    "iso:country": "GB",
    "wof:name": "GL20 5RY",
    "wof:placetype": "postalcode"
  },
  "geometry": {"coordinates":[-2.159714,51.991508],"type":"Point"}
}
