{
  "type": "Feature",
  "properties": {
    "iso:country":"GB",
    "wof:name":"GL20 5RY",
    "wof:placetype":"postalcode"
},
  "geometry": {"coordinates":[-2.15971372323997,51.99150776947535],"type":"Point"}
}