{
  "type": "Feature",
  "properties": {
    "date:inception_lower": "1980-01-01",
    "date:inception_upper": "1980-01-01",
    "iso:country": "GB",
    "wof:name": "CT16 2DA",
    "wof:placetype": "postalcode"
  },
  "geometry": {"coordinates":[1.294927,51.143712],"type":"Point"}
}
