{
  "type": "Feature",
  "properties": {
    "iso:country":"GB",
    "wof:name":"LS25 3DA",
    "wof:placetype":"postalcode"
},
  "geometry": {"coordinates":[-1.34289797254366,53.82768127698744],"type":"Point"}
}