{
  "type": "Feature",
  "properties": {
    "iso:country": "GB",
    "wof:name": "SA13 2DF",
    "wof:placetype": "postalcode"
  },
  "geometry": {"coordinates":[-3.754146,51.569654],"type":"Point"}
}
