{
  "type": "Feature",
  "properties": {
    "iso:country":"GB",
    "wof:name":"NR11 7AL",
    "wof:placetype":"postalcode"
},
  "geometry": {"coordinates":[1.22734657006044,52.85357701231186],"type":"Point"}
}