{
  "type": "Feature",
  "properties": {
    "date:inception_lower": "1980-01-01",
    "date:inception_upper": "1980-01-01",
    "iso:country": "GB",
    "wof:name": "NG9 5DL",
    "wof:placetype": "postalcode"
  },
  "geometry": {"coordinates":[-1.234564,52.91657],"type":"Point"}
}
