{
  "type": "Feature",
  "properties": {
    "iso:country":"GB",
    "wof:name":"NG9 5DL",
    "wof:placetype":"postalcode"
},
  "geometry": {"coordinates":[-1.23456354926543,52.91656958449803],"type":"Point"}
}