{
  "type": "Feature",
  "properties": {
    "iso:country": "GB",
    "wof:name": "NG9 5DL",
    "wof:placetype": "postalcode"
  },
  "geometry": {"coordinates":[-1.234564,52.91657],"type":"Point"}
}
