{
  "type": "Feature",
  "properties": {
    "date:inception_lower":"1980-01-01",
    "date:inception_upper":"1980-01-31",
    "iso:country":"GB",
    "wof:name":"CO12 3AP",
    "wof:placetype":"postalcode"
},
  "geometry": {"coordinates":[1.282042,51.937806],"type":"Point"}
}