{
  "type": "Feature",
  "properties": {
    "iso:country":"GB",
    "wof:name":"SA20 0RS",
    "wof:placetype":"postalcode"
},
  "geometry": {"coordinates":[-3.71742992373025,51.99348531159817],"type":"Point"}
}