{
  "type": "Feature",
  "properties": {
    "iso:country": "GB",
    "wof:name": "SA20 0RS",
    "wof:placetype": "postalcode"
  },
  "geometry": {"coordinates":[-3.71743,51.993485],"type":"Point"}
}
