{
  "type": "Feature",
  "properties": {
    "iso:country":"GB",
    "wof:name":"NP25 5AP",
    "wof:placetype":"postalcode"
},
  "geometry": {"coordinates":[-2.71875711962927,51.80643657598633],"type":"Point"}
}