{
  "type": "Feature",
  "properties": {
    "date:inception_lower": "1998-06-01",
    "date:inception_upper": "1998-06-01",
    "iso:country": "GB",
    "wof:name": "YO61 2QA",
    "wof:placetype": "postalcode"
  },
  "geometry": {"coordinates":[-1.328229,54.126417],"type":"Point"}
}
