{
  "type": "Feature",
  "properties": {
    "iso:country":"GB",
    "wof:name":"YO61 2QA",
    "wof:placetype":"postalcode"
},
  "geometry": {"coordinates":[-1.32825141778669,54.12640209520531],"type":"Point"}
}