{
  "type": "Feature",
  "properties": {
    "iso:country": "GB",
    "wof:name": "RH3 7HA",
    "wof:placetype": "postalcode"
  },
  "geometry": {"coordinates":[-0.285639,51.244461],"type":"Point"}
}
