{
  "type": "Feature",
  "properties": {
    "iso:country":"GB",
    "wof:name":"NE8 3HE",
    "wof:placetype":"postalcode"
},
  "geometry": {"coordinates":[-1.59385512339505,54.95701958264262],"type":"Point"}
}