{
  "type": "Feature",
  "properties": {
    "iso:country":"GB",
    "wof:name":"SN10 5PU",
    "wof:placetype":"postalcode"
},
  "geometry": {"coordinates":[-2.02619549037853,51.31877310413201],"type":"Point"}
}