{
  "type": "Feature",
  "properties": {
    "date:inception_lower":"1980-01-01",
    "date:inception_upper":"1980-01-31",
    "iso:country":"GB",
    "wof:name":"SN10 5PU",
    "wof:placetype":"postalcode"
},
  "geometry": {"coordinates":[-2.026195,51.318773],"type":"Point"}
}