{
  "type": "Feature",
  "properties": {
    "iso:country": "GB",
    "wof:name": "DE6 3GJ",
    "wof:placetype": "postalcode"
  },
  "geometry": {"coordinates":[-1.623792,52.972707],"type":"Point"}
}
