{
  "type": "Feature",
  "properties": {
    "iso:country":"GB",
    "wof:name":"LS12 4RA",
    "wof:placetype":"postalcode"
},
  "geometry": {"coordinates":[-1.6067776656818,53.79221868941332],"type":"Point"}
}