{
  "type": "Feature",
  "properties": {
    "iso:country": "GB",
    "wof:name": "LS12 4RA",
    "wof:placetype": "postalcode"
  },
  "geometry": {"coordinates":[-1.606689,53.792252],"type":"Point"}
}
