{
  "type": "Feature",
  "properties": {
    "iso:country":"GB",
    "wof:name":"NR1 3RP",
    "wof:placetype":"postalcode"
},
  "geometry": {"coordinates":[1.29209651602594,52.62101491531674],"type":"Point"}
}