{
  "type": "Feature",
  "properties": {
    "iso:country":"GB",
    "wof:name":"LE10 1SU",
    "wof:placetype":"postalcode"
},
  "geometry": {"coordinates":[-1.36594018901881,52.55427547716783],"type":"Point"}
}