{
  "type": "Feature",
  "properties": {
    "iso:country":"GB",
    "wof:name":"LE15 6AR",
    "wof:placetype":"postalcode"
},
  "geometry": {"coordinates":[-0.7284078174147,52.66950835727732],"type":"Point"}
}