{
  "type": "Feature",
  "properties": {
    "date:inception_lower":"1980-01-01",
    "date:inception_upper":"1980-01-31",
    "iso:country":"GB",
    "wof:name":"LE15 6AR",
    "wof:placetype":"postalcode"
},
  "geometry": {"coordinates":[-0.728408,52.669508],"type":"Point"}
}