{
  "type": "Feature",
  "properties": {
    "iso:country":"GB",
    "wof:name":"M21 7RW",
    "wof:placetype":"postalcode"
},
  "geometry": {"coordinates":[-2.25976972736505,53.43401186837623],"type":"Point"}
}