{
  "type": "Feature",
  "properties": {
    "iso:country":"GB",
    "wof:name":"WF1 2FF",
    "wof:placetype":"postalcode"
},
  "geometry": {"coordinates":[-1.51490005853956,53.70477850331848],"type":"Point"}
}