{
  "type": "Feature",
  "properties": {
    "date:inception_lower": "2014-05-01",
    "date:inception_upper": "2014-05-01",
    "iso:country": "GB",
    "wof:name": "WF1 2FF",
    "wof:placetype": "postalcode"
  },
  "geometry": {"coordinates":[-1.514903,53.704786],"type":"Point"}
}
