{
  "type": "Feature",
  "properties": {
    "iso:country": "GB",
    "wof:name": "WF1 2FF",
    "wof:placetype": "postalcode"
  },
  "geometry": {"coordinates":[-1.514903,53.704795],"type":"Point"}
}
