{
  "type": "Feature",
  "properties": {
    "iso:country":"GB",
    "wof:name":"DA16 1PY",
    "wof:placetype":"postalcode"
},
  "geometry": {"coordinates":[0.11711236083009,51.46331421963225],"type":"Point"}
}