{
  "type": "Feature",
  "properties": {
    "iso:country":"GB",
    "wof:name":"EN6 2LP",
    "wof:placetype":"postalcode"
},
  "geometry": {"coordinates":[-0.19165330344377,51.692276174849],"type":"Point"}
}