{
  "type": "Feature",
  "properties": {
    "iso:country":"GB",
    "wof:name":"SR4 6EF",
    "wof:placetype":"postalcode"
},
  "geometry": {"coordinates":[-1.40088938477321,54.90778560587147],"type":"Point"}
}