{
  "type": "Feature",
  "properties": {
    "date:inception_lower":"1980-01-01",
    "date:inception_upper":"1980-01-31",
    "iso:country":"GB",
    "wof:name":"SR4 6EF",
    "wof:placetype":"postalcode"
},
  "geometry": {"coordinates":[-1.400889,54.907786],"type":"Point"}
}