{
  "type": "Feature",
  "properties": {
    "date:inception_lower": "2018-06-01",
    "date:inception_upper": "2018-06-01",
    "iso:country": "GB",
    "wof:name": "CV31 3SG",
    "wof:placetype": "postalcode"
  },
  "geometry": {"coordinates":[-1.535945,52.284961],"type":"Point"}
}
