{
  "type": "Feature",
  "properties": {
    "iso:country": "GB",
    "wof:name": "NG2 6BH",
    "wof:placetype": "postalcode"
  },
  "geometry": {"coordinates":[-1.127259,52.928514],"type":"Point"}
}
