{
  "type": "Feature",
  "properties": {
    "iso:country":"GB",
    "wof:name":"GL6 8HY",
    "wof:placetype":"postalcode"
},
  "geometry": {"coordinates":[-2.12088232636178,51.71370754753391],"type":"Point"}
}