{
  "type": "Feature",
  "properties": {
    "date:inception_lower":"1998-06-01",
    "date:inception_upper":"1998-06-30",
    "iso:country":"GB",
    "wof:name":"GL6 8HY",
    "wof:placetype":"postalcode"
},
  "geometry": {"coordinates":[-2.120882,51.713708],"type":"Point"}
}