{
  "type": "Feature",
  "properties": {
    "date:inception_lower": "1980-01-01",
    "date:inception_upper": "1980-01-01",
    "iso:country": "GB",
    "wof:name": "KY15 5QU",
    "wof:placetype": "postalcode"
  },
  "geometry": {"coordinates":[-3.048161,56.295365],"type":"Point"}
}
