{
  "type": "Feature",
  "properties": {
    "date:inception_lower": "1980-01-01",
    "date:inception_upper": "1980-01-01",
    "iso:country": "GB",
    "wof:name": "TN33 9AU",
    "wof:placetype": "postalcode"
  },
  "geometry": {"coordinates":[0.503196,50.878677],"type":"Point"}
}
