{
  "type": "Feature",
  "properties": {
    "iso:country": "GB",
    "wof:name": "TN33 9AU",
    "wof:placetype": "postalcode"
  },
  "geometry": {"coordinates":[0.503166,50.878681],"type":"Point"}
}
