{
  "type": "Feature",
  "properties": {
    "date:inception_lower":"2012-04-01",
    "date:inception_upper":"2012-04-30",
    "iso:country":"GB",
    "wof:name":"M15 6GQ",
    "wof:placetype":"postalcode"
},
  "geometry": {"coordinates":[-2.23121,53.460587],"type":"Point"}
}