{
  "type": "Feature",
  "properties": {
    "iso:country":"GB",
    "wof:name":"M15 6GQ",
    "wof:placetype":"postalcode"
},
  "geometry": {"coordinates":[-2.23121037378496,53.46058671585766],"type":"Point"}
}