{
  "type": "Feature",
  "properties": {
    "iso:country":"GB",
    "wof:name":"FY3 7DX",
    "wof:placetype":"postalcode"
},
  "geometry": {"coordinates":[-3.02700832922808,53.8320111414901],"type":"Point"}
}