{
  "type": "Feature",
  "properties": {
    "date:inception_lower":"1980-01-01",
    "date:inception_upper":"1980-01-31",
    "iso:country":"GB",
    "wof:name":"MK42 9XA",
    "wof:placetype":"postalcode"
},
  "geometry": {"coordinates":[-0.46304,52.115413],"type":"Point"}
}