{
  "type": "Feature",
  "properties": {
    "date:inception_lower": "1980-01-01",
    "date:inception_upper": "1980-01-01",
    "iso:country": "GB",
    "wof:name": "DL12 0BG",
    "wof:placetype": "postalcode"
  },
  "geometry": {"coordinates":[-2.010666,54.609443],"type":"Point"}
}
