{
  "type": "Feature",
  "properties": {
    "date:inception_lower":"1980-01-01",
    "date:inception_upper":"1980-01-31",
    "iso:country":"GB",
    "wof:name":"W12 0LJ",
    "wof:placetype":"postalcode"
},
  "geometry": {"coordinates":[-0.2399,51.510205],"type":"Point"}
}