{
  "type": "Feature",
  "properties": {
    "iso:country":"GB",
    "wof:name":"W12 0LJ",
    "wof:placetype":"postalcode"
},
  "geometry": {"coordinates":[-0.23989982706568,51.51020509358027],"type":"Point"}
}