{
  "type": "Feature",
  "properties": {
    "iso:country": "GB",
    "wof:name": "NG9 6LN",
    "wof:placetype": "postalcode"
  },
  "geometry": {"coordinates":[-1.265443,52.906588],"type":"Point"}
}
