{
  "type": "Feature",
  "properties": {
    "iso:country":"GB",
    "wof:name":"NG9 6LN",
    "wof:placetype":"postalcode"
},
  "geometry": {"coordinates":[-1.26544321935206,52.90658832728004],"type":"Point"}
}