{
  "type": "Feature",
  "properties": {
    "iso:country":"GB",
    "wof:name":"LA1 3DT",
    "wof:placetype":"postalcode"
},
  "geometry": {"coordinates":[-2.78800822321058,54.04517242263878],"type":"Point"}
}