{
  "type": "Feature",
  "properties": {
    "iso:country":"GB",
    "wof:name":"SS2 4AZ",
    "wof:placetype":"postalcode"
},
  "geometry": {"coordinates":[0.72442270547165,51.5540454766781],"type":"Point"}
}