{
  "type": "Feature",
  "properties": {
    "iso:country": "GB",
    "wof:name": "SN16 9PH",
    "wof:placetype": "postalcode"
  },
  "geometry": {"coordinates":[-2.062365,51.577824],"type":"Point"}
}
