{
  "type": "Feature",
  "properties": {
    "date:inception_lower":"1995-12-01",
    "date:inception_upper":"1995-12-31",
    "iso:country":"GB",
    "wof:name":"SN16 9PH",
    "wof:placetype":"postalcode"
},
  "geometry": {"coordinates":[-2.062365,51.577824],"type":"Point"}
}