{
  "type": "Feature",
  "properties": {
    "iso:country":"GB",
    "wof:name":"SN16 9PH",
    "wof:placetype":"postalcode"
},
  "geometry": {"coordinates":[-2.06236479057182,51.57782373786161],"type":"Point"}
}