{
  "type": "Feature",
  "properties": {
    "iso:country": "GB",
    "wof:name": "NG24 3GG",
    "wof:placetype": "postalcode"
  },
  "geometry": {"coordinates":[-0.788899,53.065707],"type":"Point"}
}
