{
  "type": "Feature",
  "properties": {
    "date:inception_lower":"1993-01-01",
    "date:inception_upper":"1993-01-31",
    "iso:country":"GB",
    "wof:name":"NG24 3GG",
    "wof:placetype":"postalcode"
},
  "geometry": {"coordinates":[-0.788899,53.065707],"type":"Point"}
}