{
  "type": "Feature",
  "properties": {
    "iso:country":"GB",
    "wof:name":"NG24 3GG",
    "wof:placetype":"postalcode"
},
  "geometry": {"coordinates":[-0.78889878016136,53.06570677933686],"type":"Point"}
}