{
  "type": "Feature",
  "properties": {
    "iso:country":"GB",
    "wof:name":"LL18 5PG",
    "wof:placetype":"postalcode"
},
  "geometry": {"coordinates":[-3.46030494178145,53.29141270892563],"type":"Point"}
}