{
  "type": "Feature",
  "properties": {
    "date:inception_lower": "1980-01-01",
    "date:inception_upper": "1980-01-01",
    "iso:country": "GB",
    "wof:name": "ML2 7SS",
    "wof:placetype": "postalcode"
  },
  "geometry": {"coordinates":[-3.95113,55.776702],"type":"Point"}
}
