{
  "type": "Feature",
  "properties": {
    "iso:country": "GB",
    "wof:name": "MK12 5GZ",
    "wof:placetype": "postalcode"
  },
  "geometry": {"coordinates":[-0.815694,52.060536],"type":"Point"}
}
