{
  "type": "Feature",
  "properties": {
    "iso:country": "GB",
    "wof:name": "HS8 5SB",
    "wof:placetype": "postalcode"
  },
  "geometry": {"coordinates":[-7.392731,57.258318],"type":"Point"}
}
