{
  "type": "Feature",
  "properties": {
    "date:inception_lower": "1995-07-01",
    "date:inception_upper": "1995-07-01",
    "iso:country": "GB",
    "wof:name": "HS8 5SB",
    "wof:placetype": "postalcode"
  },
  "geometry": {"coordinates":[-7.392731,57.258318],"type":"Point"}
}
