{
  "type": "Feature",
  "properties": {
    "iso:country":"GB",
    "wof:name":"HS8 5SB",
    "wof:placetype":"postalcode"
},
  "geometry": {"coordinates":[-7.39417723147484,57.25762433820785],"type":"Point"}
}