{
  "type": "Feature",
  "properties": {
    "iso:country":"GB",
    "wof:name":"SE9 2NH",
    "wof:placetype":"postalcode"
},
  "geometry": {"coordinates":[0.08587401838697,51.4542158915083],"type":"Point"}
}