{
  "type": "Feature",
  "properties": {
    "iso:country":"GB",
    "wof:name":"SS12 0JN",
    "wof:placetype":"postalcode"
},
  "geometry": {"coordinates":[0.49547497270883,51.61572589429802],"type":"Point"}
}