{
  "type": "Feature",
  "properties": {
    "iso:country": "GB",
    "wof:name": "BL9 9EN",
    "wof:placetype": "postalcode"
  },
  "geometry": {"coordinates":[-2.287039,53.582708],"type":"Point"}
}
