{
  "type": "Feature",
  "properties": {
    "iso:country": "GB",
    "wof:name": "B42 2SQ",
    "wof:placetype": "postalcode"
  },
  "geometry": {"coordinates":[-1.901754,52.536127],"type":"Point"}
}
