{
  "type": "Feature",
  "properties": {
    "iso:country":"GB",
    "wof:name":"CT14 6HN",
    "wof:placetype":"postalcode"
},
  "geometry": {"coordinates":[1.40316042011927,51.22558887154686],"type":"Point"}
}