{
  "type": "Feature",
  "properties": {
    "iso:country":"GB",
    "wof:name":"TN24 0AN",
    "wof:placetype":"postalcode"
},
  "geometry": {"coordinates":[0.89997185644383,51.1445467773996],"type":"Point"}
}