{
  "type": "Feature",
  "properties": {
    "iso:country":"GB",
    "wof:name":"SL4 4YP",
    "wof:placetype":"postalcode"
},
  "geometry": {"coordinates":[-0.65381078339631,51.47316214165111],"type":"Point"}
}