{
  "type": "Feature",
  "properties": {
    "iso:country":"GB",
    "wof:name":"NE34 8NL",
    "wof:placetype":"postalcode"
},
  "geometry": {"coordinates":[-1.42593445963934,54.96063866116047],"type":"Point"}
}