{
  "type": "Feature",
  "properties": {
    "iso:country": "GB",
    "wof:name": "NE34 8NL",
    "wof:placetype": "postalcode"
  },
  "geometry": {"coordinates":[-1.425934,54.960639],"type":"Point"}
}
