{
  "type": "Feature",
  "properties": {
    "iso:country": "GB",
    "wof:name": "CA7 4DD",
    "wof:placetype": "postalcode"
  },
  "geometry": {"coordinates":[-3.384764,54.872354],"type":"Point"}
}
