{
  "type": "Feature",
  "properties": {
    "iso:country":"GB",
    "wof:name":"CA7 4DD",
    "wof:placetype":"postalcode"
},
  "geometry": {"coordinates":[-3.38531747165201,54.87214420807845],"type":"Point"}
}