{
  "type": "Feature",
  "properties": {
    "iso:country":"GB",
    "wof:name":"FK3 0EN",
    "wof:placetype":"postalcode"
},
  "geometry": {"coordinates":[-3.7112296974279,56.00958047729019],"type":"Point"}
}