{
  "type": "Feature",
  "properties": {
    "iso:country": "GB",
    "wof:name": "TN15 0AQ",
    "wof:placetype": "postalcode"
  },
  "geometry": {"coordinates":[0.212169,51.290923],"type":"Point"}
}
