{
  "type": "Feature",
  "properties": {
    "iso:country":"GB",
    "wof:name":"GU35 0HB",
    "wof:placetype":"postalcode"
},
  "geometry": {"coordinates":[-0.85194091764741,51.11340594913904],"type":"Point"}
}