{
  "type": "Feature",
  "properties": {
    "iso:country":"GB",
    "wof:name":"CA7 5DN",
    "wof:placetype":"postalcode"
},
  "geometry": {"coordinates":[-3.13139949646538,54.92523681933515],"type":"Point"}
}