{
  "type": "Feature",
  "properties": {
    "date:inception_lower": "2016-12-01",
    "date:inception_upper": "2016-12-01",
    "iso:country": "GB",
    "wof:name": "CA7 5DN",
    "wof:placetype": "postalcode"
  },
  "geometry": {"coordinates":[-3.140332,54.923731],"type":"Point"}
}
