{
  "type": "Feature",
  "properties": {
    "iso:country": "GB",
    "wof:name": "CF37 4HX",
    "wof:placetype": "postalcode"
  },
  "geometry": {"coordinates":[-3.318228,51.615241],"type":"Point"}
}
