{
  "type": "Feature",
  "properties": {
    "iso:country":"GB",
    "wof:name":"CF37 4HX",
    "wof:placetype":"postalcode"
},
  "geometry": {"coordinates":[-3.31822754645194,51.61524061547195],"type":"Point"}
}