{
  "type": "Feature",
  "properties": {
    "date:inception_lower": "2006-07-01",
    "date:inception_upper": "2006-07-01",
    "iso:country": "GB",
    "wof:name": "UB11 1FE",
    "wof:placetype": "postalcode"
  },
  "geometry": {"coordinates":[-0.446955,51.508689],"type":"Point"}
}
