{
  "type": "Feature",
  "properties": {
    "iso:country":"GB",
    "wof:name":"UB11 1FE",
    "wof:placetype":"postalcode"
},
  "geometry": {"coordinates":[-0.44551100474084,51.50811950906987],"type":"Point"}
}