{
  "type": "Feature",
  "properties": {
    "iso:country": "GB",
    "wof:name": "SA17 5AR",
    "wof:placetype": "postalcode"
  },
  "geometry": {"coordinates":[-4.325026,51.769919],"type":"Point"}
}
