{
  "type": "Feature",
  "properties": {
    "iso:country":"GB",
    "wof:name":"BD23 3PQ",
    "wof:placetype":"postalcode"
},
  "geometry": {"coordinates":[-2.10506590693428,53.98535336519859],"type":"Point"}
}