{
  "type": "Feature",
  "properties": {
    "date:inception_lower": "1997-12-01",
    "date:inception_upper": "1997-12-01",
    "iso:country": "GB",
    "wof:name": "BD23 3PQ",
    "wof:placetype": "postalcode"
  },
  "geometry": {"coordinates":[-2.105066,53.985353],"type":"Point"}
}
