{
  "type": "Feature",
  "properties": {
    "iso:country": "GB",
    "wof:name": "BD23 3PQ",
    "wof:placetype": "postalcode"
  },
  "geometry": {"coordinates":[-2.105066,53.985353],"type":"Point"}
}
