{
  "type": "Feature",
  "properties": {
    "iso:country": "GB",
    "wof:name": "BN12 4EW",
    "wof:placetype": "postalcode"
  },
  "geometry": {"coordinates":[-0.405281,50.815805],"type":"Point"}
}
