{
  "type": "Feature",
  "properties": {
    "iso:country":"GB",
    "wof:name":"BN12 4EW",
    "wof:placetype":"postalcode"
},
  "geometry": {"coordinates":[-0.4052809631961,50.81580496685034],"type":"Point"}
}