{
  "type": "Feature",
  "properties": {
    "iso:country": "GB",
    "wof:name": "SO40 7DW",
    "wof:placetype": "postalcode"
  },
  "geometry": {"coordinates":[-1.512597,50.898127],"type":"Point"}
}
