{
  "type": "Feature",
  "properties": {
    "iso:country":"GB",
    "wof:name":"PO12 4SY",
    "wof:placetype":"postalcode"
},
  "geometry": {"coordinates":[-1.1311746553351,50.79809893334068],"type":"Point"}
}