{
  "type": "Feature",
  "properties": {
    "iso:country":"GB",
    "wof:name":"NN2 7NW",
    "wof:placetype":"postalcode"
},
  "geometry": {"coordinates":[-0.88104627752191,52.26228908262372],"type":"Point"}
}