{
  "type": "Feature",
  "properties": {
    "iso:country":"GB",
    "wof:name":"EX37 9TY",
    "wof:placetype":"postalcode"
},
  "geometry": {"coordinates":[-3.93989793861756,50.9357561188542],"type":"Point"}
}