{
  "type": "Feature",
  "properties": {
    "date:inception_lower": "1990-02-01",
    "date:inception_upper": "1990-02-01",
    "iso:country": "GB",
    "wof:name": "EX37 9TY",
    "wof:placetype": "postalcode"
  },
  "geometry": {"coordinates":[-3.93971,50.936203],"type":"Point"}
}
