{
  "type": "Feature",
  "properties": {
    "iso:country": "GB",
    "wof:name": "IV41 8PP",
    "wof:placetype": "postalcode"
  },
  "geometry": {"coordinates":[-5.737046,57.273318],"type":"Point"}
}
