{
  "type": "Feature",
  "properties": {
    "iso:country":"GB",
    "wof:name":"IV41 8PP",
    "wof:placetype":"postalcode"
},
  "geometry": {"coordinates":[-5.73704555962312,57.27331832016674],"type":"Point"}
}