{
  "type": "Feature",
  "properties": {
    "date:inception_lower": "1980-01-01",
    "date:inception_upper": "1980-01-01",
    "iso:country": "GB",
    "wof:name": "IV41 8PP",
    "wof:placetype": "postalcode"
  },
  "geometry": {"coordinates":[-5.737046,57.273318],"type":"Point"}
}
