{
  "type": "Feature",
  "properties": {
    "iso:country":"GB",
    "wof:name":"BB4 5LJ",
    "wof:placetype":"postalcode"
},
  "geometry": {"coordinates":[-2.32481866545819,53.70507580541432],"type":"Point"}
}