{
  "type": "Feature",
  "properties": {
    "iso:country":"GB",
    "wof:name":"PO30 2NB",
    "wof:placetype":"postalcode"
},
  "geometry": {"coordinates":[-1.26294192773557,50.70851135534896],"type":"Point"}
}