{
  "type": "Feature",
  "properties": {
    "iso:country": "GB",
    "wof:name": "LE1 1DR",
    "wof:placetype": "postalcode"
  },
  "geometry": {"coordinates":[-1.124555,52.634205],"type":"Point"}
}
