{
  "type": "Feature",
  "properties": {
    "iso:country":"GB",
    "wof:name":"LE1 1DR",
    "wof:placetype":"postalcode"
},
  "geometry": {"coordinates":[-1.1245550996955,52.63420508702199],"type":"Point"}
}