{
  "type": "Feature",
  "properties": {
    "iso:country":"GB",
    "wof:name":"NE10 0SZ",
    "wof:placetype":"postalcode"
},
  "geometry": {"coordinates":[-1.53520222420458,54.95705230470841],"type":"Point"}
}