{
  "type": "Feature",
  "properties": {
    "date:inception_lower": "1980-01-01",
    "date:inception_upper": "1980-01-01",
    "iso:country": "GB",
    "wof:name": "WN4 0EG",
    "wof:placetype": "postalcode"
  },
  "geometry": {"coordinates":[-2.644511,53.509515],"type":"Point"}
}
