{
  "type": "Feature",
  "properties": {
    "iso:country":"GB",
    "wof:name":"WN4 0EG",
    "wof:placetype":"postalcode"
},
  "geometry": {"coordinates":[-2.64451077358812,53.50951527705073],"type":"Point"}
}