{
  "type": "Feature",
  "properties": {
    "iso:country":"GB",
    "wof:name":"G72 7NA",
    "wof:placetype":"postalcode"
},
  "geometry": {"coordinates":[-4.16036250046805,55.82329654897112],"type":"Point"}
}