{
  "type": "Feature",
  "properties": {
    "iso:country": "GB",
    "wof:name": "G72 7NA",
    "wof:placetype": "postalcode"
  },
  "geometry": {"coordinates":[-4.160362,55.823297],"type":"Point"}
}
