{
  "type": "Feature",
  "properties": {
    "date:inception_lower":"2011-01-01",
    "date:inception_upper":"2011-01-31",
    "iso:country":"GB",
    "wof:name":"NG13 0HX",
    "wof:placetype":"postalcode"
},
  "geometry": {"coordinates":[-0.844424,52.905748],"type":"Point"}
}