{
  "type": "Feature",
  "properties": {
    "iso:country": "GB",
    "wof:name": "NG13 0HX",
    "wof:placetype": "postalcode"
  },
  "geometry": {"coordinates":[-0.844424,52.905748],"type":"Point"}
}
