{
  "type": "Feature",
  "properties": {
    "iso:country":"GB",
    "wof:name":"NG13 0HX",
    "wof:placetype":"postalcode"
},
  "geometry": {"coordinates":[-0.84442366060454,52.90574801712567],"type":"Point"}
}