{
  "type": "Feature",
  "properties": {
    "date:inception_lower": "2019-12-01",
    "date:inception_upper": "2019-12-01",
    "iso:country": "GB",
    "wof:name": "EX7 0GT",
    "wof:placetype": "postalcode"
  },
  "geometry": {"coordinates":[-3.468485,50.590938],"type":"Point"}
}
