{
  "type": "Feature",
  "properties": {
    "iso:country": "GB",
    "wof:name": "EX7 0GT",
    "wof:placetype": "postalcode"
  },
  "geometry": {"coordinates":[-3.468485,50.590938],"type":"Point"}
}
