{
  "type": "Feature",
  "properties": {
    "date:inception_lower": "2022-02-01",
    "date:inception_upper": "2022-02-01",
    "iso:country": "GB",
    "wof:name": "EH34 5BS",
    "wof:placetype": "postalcode"
  },
  "geometry": {"coordinates":[-2.895534,55.905372],"type":"Point"}
}
