{
  "type": "Feature",
  "properties": {
    "iso:country":"GB",
    "wof:name":"SL6 1QP",
    "wof:placetype":"postalcode"
},
  "geometry": {"coordinates":[-0.71648842777863,51.52186399220429],"type":"Point"}
}