{
  "type": "Feature",
  "properties": {
    "iso:country": "GB",
    "wof:name": "DN15 9JD",
    "wof:placetype": "postalcode"
  },
  "geometry": {"coordinates":[-0.664873,53.685046],"type":"Point"}
}
