{
  "type": "Feature",
  "properties": {
    "iso:country":"GB",
    "wof:name":"DN15 9JD",
    "wof:placetype":"postalcode"
},
  "geometry": {"coordinates":[-0.66487290881319,53.68504591358309],"type":"Point"}
}