{
  "type": "Feature",
  "properties": {
    "date:inception_lower":"1980-01-01",
    "date:inception_upper":"1980-01-31",
    "iso:country":"GB",
    "wof:name":"DN15 9JD",
    "wof:placetype":"postalcode"
},
  "geometry": {"coordinates":[-0.664873,53.685046],"type":"Point"}
}