{
  "type": "Feature",
  "properties": {
    "date:inception_lower": "1980-01-01",
    "date:inception_upper": "1980-01-01",
    "iso:country": "GB",
    "wof:name": "NE9 6QT",
    "wof:placetype": "postalcode"
  },
  "geometry": {"coordinates":[-1.584812,54.940544],"type":"Point"}
}
