{
  "type": "Feature",
  "properties": {
    "iso:country": "GB",
    "wof:name": "EX10 0FG",
    "wof:placetype": "postalcode"
  },
  "geometry": {"coordinates":[-3.219032,50.72093],"type":"Point"}
}
