{
  "type": "Feature",
  "properties": {
    "date:inception_lower": "2010-12-01",
    "date:inception_upper": "2010-12-01",
    "iso:country": "GB",
    "wof:name": "EX10 0FG",
    "wof:placetype": "postalcode"
  },
  "geometry": {"coordinates":[-3.219032,50.72093],"type":"Point"}
}
