{
  "type": "Feature",
  "properties": {
    "date:inception_lower": "1980-01-01",
    "date:inception_upper": "1980-01-01",
    "iso:country": "GB",
    "wof:name": "LL11 6HN",
    "wof:placetype": "postalcode"
  },
  "geometry": {"coordinates":[-3.034447,53.067852],"type":"Point"}
}
