{
  "type": "Feature",
  "properties": {
    "iso:country":"GB",
    "wof:name":"LL11 6HN",
    "wof:placetype":"postalcode"
},
  "geometry": {"coordinates":[-3.03444694091973,53.0678362169781],"type":"Point"}
}