{
  "type": "Feature",
  "properties": {
    "iso:country":"GB",
    "wof:name":"SL1 7HJ",
    "wof:placetype":"postalcode"
},
  "geometry": {"coordinates":[-0.65255675564686,51.53085850899448],"type":"Point"}
}