{
  "type": "Feature",
  "properties": {
    "date:inception_lower":"1980-01-01",
    "date:inception_upper":"1980-01-31",
    "iso:country":"GB",
    "wof:name":"SL1 7HJ",
    "wof:placetype":"postalcode"
},
  "geometry": {"coordinates":[-0.652654,51.530853],"type":"Point"}
}