{
  "type": "Feature",
  "properties": {
    "iso:country":"GB",
    "wof:name":"PR3 2BE",
    "wof:placetype":"postalcode"
},
  "geometry": {"coordinates":[-2.67100738202085,53.82302645709844],"type":"Point"}
}