{
  "type": "Feature",
  "properties": {
    "iso:country":"GB",
    "wof:name":"CM2 7LP",
    "wof:placetype":"postalcode"
},
  "geometry": {"coordinates":[0.48610167576273,51.72456208744676],"type":"Point"}
}