{
  "type": "Feature",
  "properties": {
    "iso:country": "GB",
    "wof:name": "TD3 6NA",
    "wof:placetype": "postalcode"
  },
  "geometry": {"coordinates":[-2.580884,55.734443],"type":"Point"}
}
