{
  "type": "Feature",
  "properties": {
    "iso:country":"GB",
    "wof:name":"TD3 6NA",
    "wof:placetype":"postalcode"
},
  "geometry": {"coordinates":[-2.58088438511287,55.73444311220565],"type":"Point"}
}