{
  "type": "Feature",
  "properties": {
    "date:inception_lower": "1980-01-01",
    "date:inception_upper": "1980-01-01",
    "iso:country": "GB",
    "wof:name": "BL9 0RE",
    "wof:placetype": "postalcode"
  },
  "geometry": {"coordinates":[-2.290234,53.590832],"type":"Point"}
}
