{
  "type": "Feature",
  "properties": {
    "iso:country": "GB",
    "wof:name": "GU8 4RU",
    "wof:placetype": "postalcode"
  },
  "geometry": {"coordinates":[-0.632388,51.11439],"type":"Point"}
}
