{
  "type": "Feature",
  "properties": {
    "iso:country":"GB",
    "wof:name":"GU8 4RU",
    "wof:placetype":"postalcode"
},
  "geometry": {"coordinates":[-0.63238784693868,51.11438975536401],"type":"Point"}
}