{
  "type": "Feature",
  "properties": {
    "iso:country":"GB",
    "wof:name":"GU27 2EX",
    "wof:placetype":"postalcode"
},
  "geometry": {"coordinates":[-0.67825110204957,51.09525933814989],"type":"Point"}
}