{
  "type": "Feature",
  "properties": {
    "iso:country": "GB",
    "wof:name": "GU27 2EX",
    "wof:placetype": "postalcode"
  },
  "geometry": {"coordinates":[-0.678251,51.095259],"type":"Point"}
}
