{
  "type": "Feature",
  "properties": {
    "iso:country": "GB",
    "wof:name": "HU17 8XH",
    "wof:placetype": "postalcode"
  },
  "geometry": {"coordinates":[-0.435473,53.825986],"type":"Point"}
}
