{
  "type": "Feature",
  "properties": {
    "iso:country":"GB",
    "wof:name":"HU17 8XH",
    "wof:placetype":"postalcode"
},
  "geometry": {"coordinates":[-0.43547326568463,53.82598576484637],"type":"Point"}
}