{
  "type": "Feature",
  "properties": {
    "iso:country":"GB",
    "wof:name":"DY8 3DF",
    "wof:placetype":"postalcode"
},
  "geometry": {"coordinates":[-2.15951349785765,52.44531481178934],"type":"Point"}
}