{
  "type": "Feature",
  "properties": {
    "date:inception_lower": "1980-01-01",
    "date:inception_upper": "1980-01-01",
    "iso:country": "GB",
    "wof:name": "DE6 5AE",
    "wof:placetype": "postalcode"
  },
  "geometry": {"coordinates":[-1.734053,52.923689],"type":"Point"}
}
