{
  "type": "Feature",
  "properties": {
    "iso:country": "GB",
    "wof:name": "OL10 2PZ",
    "wof:placetype": "postalcode"
  },
  "geometry": {"coordinates":[-2.219633,53.57806],"type":"Point"}
}
