{
  "type": "Feature",
  "properties": {
    "date:inception_lower":"1980-01-01",
    "date:inception_upper":"1980-01-31",
    "iso:country":"GB",
    "wof:name":"CM4 0EQ",
    "wof:placetype":"postalcode"
},
  "geometry": {"coordinates":[0.409352,51.687793],"type":"Point"}
}