{
  "type": "Feature",
  "properties": {
    "iso:country":"GB",
    "wof:name":"CM4 0EQ",
    "wof:placetype":"postalcode"
},
  "geometry": {"coordinates":[0.40932592453978,51.68778891356389],"type":"Point"}
}