{
  "type": "Feature",
  "properties": {
    "iso:country": "GB",
    "wof:name": "CM4 0EQ",
    "wof:placetype": "postalcode"
  },
  "geometry": {"coordinates":[0.409352,51.687793],"type":"Point"}
}
