{
  "type": "Feature",
  "properties": {
    "iso:country":"GB",
    "wof:name":"DH5 0LT",
    "wof:placetype":"postalcode"
},
  "geometry": {"coordinates":[-1.4346255817737,54.80859228251477],"type":"Point"}
}