{
  "type": "Feature",
  "properties": {
    "date:inception_lower": "1980-01-01",
    "date:inception_upper": "1980-01-01",
    "iso:country": "GB",
    "wof:name": "PE33 0LN",
    "wof:placetype": "postalcode"
  },
  "geometry": {"coordinates":[0.413593,52.72247],"type":"Point"}
}
