{
  "type": "Feature",
  "properties": {
    "iso:country": "GB",
    "wof:name": "PE33 0LN",
    "wof:placetype": "postalcode"
  },
  "geometry": {"coordinates":[0.413593,52.72247],"type":"Point"}
}
