{
  "type": "Feature",
  "properties": {
    "iso:country":"GB",
    "wof:name":"WA10 5ET",
    "wof:placetype":"postalcode"
},
  "geometry": {"coordinates":[-2.77732365533464,53.46081558023266],"type":"Point"}
}