{
  "type": "Feature",
  "properties": {
    "iso:country":"GB",
    "wof:name":"N16 6LJ",
    "wof:placetype":"postalcode"
},
  "geometry": {"coordinates":[-0.06744117841236,51.56845075477035],"type":"Point"}
}