{
  "type": "Feature",
  "properties": {
    "iso:country":"GB",
    "wof:name":"PH1 1WR",
    "wof:placetype":"postalcode"
},
  "geometry": {"coordinates":[-3.60052184138921,56.37294061951318],"type":"Point"}
}