{
  "type": "Feature",
  "properties": {
    "date:inception_lower": "2008-01-01",
    "date:inception_upper": "2008-01-01",
    "iso:country": "GB",
    "wof:name": "PH1 1WR",
    "wof:placetype": "postalcode"
  },
  "geometry": {"coordinates":[-3.600522,56.372941],"type":"Point"}
}
