{
  "type": "Feature",
  "properties": {
    "iso:country":"GB",
    "wof:name":"PO36 8QJ",
    "wof:placetype":"postalcode"
},
  "geometry": {"coordinates":[-1.13961065421807,50.66539095281066],"type":"Point"}
}