{
  "type": "Feature",
  "properties": {
    "iso:country":"GB",
    "wof:name":"PL2 3HF",
    "wof:placetype":"postalcode"
},
  "geometry": {"coordinates":[-4.16022680974921,50.38958313177243],"type":"Point"}
}