{
  "type": "Feature",
  "properties": {
    "iso:country": "GB",
    "wof:name": "PL2 3HF",
    "wof:placetype": "postalcode"
  },
  "geometry": {"coordinates":[-4.160227,50.389583],"type":"Point"}
}
