{
  "type": "Feature",
  "properties": {
    "date:inception_lower":"1990-02-01",
    "date:inception_upper":"1990-02-28",
    "iso:country":"GB",
    "wof:name":"TQ7 2UA",
    "wof:placetype":"postalcode"
},
  "geometry": {"coordinates":[-3.703682,50.273897],"type":"Point"}
}