{
  "type": "Feature",
  "properties": {
    "iso:country": "GB",
    "wof:name": "BS15 8BS",
    "wof:placetype": "postalcode"
  },
  "geometry": {"coordinates":[-2.515585,51.462252],"type":"Point"}
}
