{
  "type": "Feature",
  "properties": {
    "date:inception_lower":"1980-01-01",
    "date:inception_upper":"1980-01-31",
    "iso:country":"GB",
    "wof:name":"PL14 5LG",
    "wof:placetype":"postalcode"
},
  "geometry": {"coordinates":[-4.452325,50.502518],"type":"Point"}
}