{
  "type": "Feature",
  "properties": {
    "iso:country":"GB",
    "wof:name":"B32 1JP",
    "wof:placetype":"postalcode"
},
  "geometry": {"coordinates":[-1.99177379842264,52.45682178545462],"type":"Point"}
}