{
  "type": "Feature",
  "properties": {
    "iso:country":"GB",
    "wof:name":"TS11 7LA",
    "wof:placetype":"postalcode"
},
  "geometry": {"coordinates":[-1.0190594178847,54.592135303661],"type":"Point"}
}