{
  "type": "Feature",
  "properties": {
    "iso:country":"GB",
    "wof:name":"BB4 6DS",
    "wof:placetype":"postalcode"
},
  "geometry": {"coordinates":[-2.29249141979955,53.69189266316375],"type":"Point"}
}