{
  "type": "Feature",
  "properties": {
    "iso:country": "GB",
    "wof:name": "PE22 9PX",
    "wof:placetype": "postalcode"
  },
  "geometry": {"coordinates":[0.084934,53.051814],"type":"Point"}
}
