{
  "type": "Feature",
  "properties": {
    "iso:country":"GB",
    "wof:name":"PE22 9PX",
    "wof:placetype":"postalcode"
},
  "geometry": {"coordinates":[0.08493406899422,53.05181354554404],"type":"Point"}
}