{
  "type": "Feature",
  "properties": {
    "date:inception_lower":"2007-08-01",
    "date:inception_upper":"2007-08-31",
    "iso:country":"GB",
    "wof:name":"BA13 4FD",
    "wof:placetype":"postalcode"
},
  "geometry": {"coordinates":[-2.124089,51.271989],"type":"Point"}
}