{
  "type": "Feature",
  "properties": {
    "iso:country":"GB",
    "wof:name":"BA13 4FD",
    "wof:placetype":"postalcode"
},
  "geometry": {"coordinates":[-2.12408924133836,51.27198876798645],"type":"Point"}
}