{
  "type": "Feature",
  "properties": {
    "iso:country":"GB",
    "wof:name":"CV37 8SW",
    "wof:placetype":"postalcode"
},
  "geometry": {"coordinates":[-1.7440503690372,52.12112762427661],"type":"Point"}
}