{
  "type": "Feature",
  "properties": {
    "iso:country": "GB",
    "wof:name": "CV37 8SW",
    "wof:placetype": "postalcode"
  },
  "geometry": {"coordinates":[-1.74405,52.121128],"type":"Point"}
}
