{
  "type": "Feature",
  "properties": {
    "iso:country":"GB",
    "wof:name":"SO45 4PD",
    "wof:placetype":"postalcode"
},
  "geometry": {"coordinates":[-1.41529946780547,50.85656663162032],"type":"Point"}
}