{
  "type": "Feature",
  "properties": {
    "date:inception_lower": "2005-10-01",
    "date:inception_upper": "2005-10-01",
    "iso:country": "GB",
    "wof:name": "EH12 9SB",
    "wof:placetype": "postalcode"
  },
  "geometry": {"coordinates":[-3.332888,55.935016],"type":"Point"}
}
