{
  "type": "Feature",
  "properties": {
    "iso:country":"GB",
    "wof:name":"B24 8DL",
    "wof:placetype":"postalcode"
},
  "geometry": {"coordinates":[-1.83257088853067,52.50764107487024],"type":"Point"}
}