{
  "type": "Feature",
  "properties": {
    "iso:country": "GB",
    "wof:name": "B24 8DL",
    "wof:placetype": "postalcode"
  },
  "geometry": {"coordinates":[-1.83268,52.508321],"type":"Point"}
}
