{
  "type": "Feature",
  "properties": {
    "iso:country": "GB",
    "wof:name": "RG2 0HG",
    "wof:placetype": "postalcode"
  },
  "geometry": {"coordinates":[-0.970659,51.436159],"type":"Point"}
}
