{
  "type": "Feature",
  "properties": {
    "iso:country":"GB",
    "wof:name":"RG2 0HG",
    "wof:placetype":"postalcode"
},
  "geometry": {"coordinates":[-0.97065913546506,51.43615934140061],"type":"Point"}
}