{
  "type": "Feature",
  "properties": {
    "iso:country":"GB",
    "wof:name":"DE4 2BF",
    "wof:placetype":"postalcode"
},
  "geometry": {"coordinates":[-1.66890263504383,53.14591758670912],"type":"Point"}
}