{
  "type": "Feature",
  "properties": {
    "iso:country": "GB",
    "wof:name": "DE4 2BF",
    "wof:placetype": "postalcode"
  },
  "geometry": {"coordinates":[-1.668903,53.145918],"type":"Point"}
}
