{
  "type": "Feature",
  "properties": {
    "iso:country":"GB",
    "wof:name":"BB18 5SX",
    "wof:placetype":"postalcode"
},
  "geometry": {"coordinates":[-2.19225398214916,53.91358606349604],"type":"Point"}
}