{
  "type": "Feature",
  "properties": {
    "date:inception_lower":"2000-06-01",
    "date:inception_upper":"2000-06-30",
    "iso:country":"GB",
    "wof:name":"BB18 5SX",
    "wof:placetype":"postalcode"
},
  "geometry": {"coordinates":[-2.192254,53.913586],"type":"Point"}
}