{
  "type": "Feature",
  "properties": {
    "iso:country":"GB",
    "wof:name":"RH8 9JT",
    "wof:placetype":"postalcode"
},
  "geometry": {"coordinates":[-0.0177263128716,51.2523880603772],"type":"Point"}
}