{
  "type": "Feature",
  "properties": {
    "iso:country": "GB",
    "wof:name": "DT9 5BN",
    "wof:placetype": "postalcode"
  },
  "geometry": {"coordinates":[-2.46776,50.970252],"type":"Point"}
}
