{
  "type": "Feature",
  "properties": {
    "iso:country":"GB",
    "wof:name":"DT9 5BN",
    "wof:placetype":"postalcode"
},
  "geometry": {"coordinates":[-2.46776022653748,50.9702522529244],"type":"Point"}
}