{
  "type": "Feature",
  "properties": {
    "date:inception_lower": "2000-12-01",
    "date:inception_upper": "2000-12-01",
    "iso:country": "GB",
    "wof:name": "W1T 1TB",
    "wof:placetype": "postalcode"
  },
  "geometry": {"coordinates":[-0.135861,51.519173],"type":"Point"}
}
