{
  "type": "Feature",
  "properties": {
    "iso:country":"GB",
    "wof:name":"W1T 1TB",
    "wof:placetype":"postalcode"
},
  "geometry": {"coordinates":[-0.13586108332976,51.51917286010066],"type":"Point"}
}