{
  "type": "Feature",
  "properties": {
    "date:inception_lower": "1980-01-01",
    "date:inception_upper": "1980-01-01",
    "iso:country": "GB",
    "wof:name": "DT4 7JS",
    "wof:placetype": "postalcode"
  },
  "geometry": {"coordinates":[-2.450671,50.619723],"type":"Point"}
}
