{
  "type": "Feature",
  "properties": {
    "iso:country": "GB",
    "wof:name": "LN11 7LJ",
    "wof:placetype": "postalcode"
  },
  "geometry": {"coordinates":[0.130826,53.452536],"type":"Point"}
}
