{
  "type": "Feature",
  "properties": {
    "iso:country":"GB",
    "wof:name":"LN11 7LJ",
    "wof:placetype":"postalcode"
},
  "geometry": {"coordinates":[0.13082594137364,53.4525359327033],"type":"Point"}
}