{
  "type": "Feature",
  "properties": {
    "iso:country": "GB",
    "wof:name": "LA8 9AZ",
    "wof:placetype": "postalcode"
  },
  "geometry": {"coordinates":[-2.735181,54.386917],"type":"Point"}
}
