{
  "type": "Feature",
  "properties": {
    "iso:country": "GB",
    "wof:name": "EX20 1BY",
    "wof:placetype": "postalcode"
  },
  "geometry": {"coordinates":[-4.000619,50.739428],"type":"Point"}
}
