{
  "type": "Feature",
  "properties": {
    "iso:country":"GB",
    "wof:name":"DY2 8DY",
    "wof:placetype":"postalcode"
},
  "geometry": {"coordinates":[-2.07417246674298,52.50146974987288],"type":"Point"}
}