{
  "type": "Feature",
  "properties": {
    "iso:country":"GB",
    "wof:name":"GU3 1DS",
    "wof:placetype":"postalcode"
},
  "geometry": {"coordinates":[-0.64429120015177,51.21237594977028],"type":"Point"}
}