{
  "type": "Feature",
  "properties": {
    "iso:country":"GB",
    "wof:name":"TS24 9BA",
    "wof:placetype":"postalcode"
},
  "geometry": {"coordinates":[-1.23395343449412,54.70554599689503],"type":"Point"}
}