{
  "type": "Feature",
  "properties": {
    "iso:country":"GB",
    "wof:name":"PH11 8JF",
    "wof:placetype":"postalcode"
},
  "geometry": {"coordinates":[-3.24626238152023,56.61550070789389],"type":"Point"}
}