{
  "type": "Feature",
  "properties": {
    "iso:country":"GB",
    "wof:name":"SA11 3ES",
    "wof:placetype":"postalcode"
},
  "geometry": {"coordinates":[-3.80123854944566,51.66323349805405],"type":"Point"}
}