{
  "type": "Feature",
  "properties": {
    "iso:country": "GB",
    "wof:name": "SA11 3ES",
    "wof:placetype": "postalcode"
  },
  "geometry": {"coordinates":[-3.801239,51.663233],"type":"Point"}
}
