{
  "type": "Feature",
  "properties": {
    "date:inception_lower":"2015-08-01",
    "date:inception_upper":"2015-08-31",
    "iso:country":"GB",
    "wof:name":"SA11 3ES",
    "wof:placetype":"postalcode"
},
  "geometry": {"coordinates":[-3.801239,51.663233],"type":"Point"}
}