{
  "type": "Feature",
  "properties": {
    "iso:country":"GB",
    "wof:name":"NG5 1GT",
    "wof:placetype":"postalcode"
},
  "geometry": {"coordinates":[-1.16188125947972,52.98368931699425],"type":"Point"}
}