{
  "type": "Feature",
  "properties": {
    "iso:country":"GB",
    "wof:name":"BB12 7PH",
    "wof:placetype":"postalcode"
},
  "geometry": {"coordinates":[-2.35132741864837,53.80848057390475],"type":"Point"}
}