{
  "type": "Feature",
  "properties": {
    "iso:country": "GB",
    "wof:name": "BB12 7PH",
    "wof:placetype": "postalcode"
  },
  "geometry": {"coordinates":[-2.351327,53.808481],"type":"Point"}
}
