{
  "type": "Feature",
  "properties": {
    "iso:country": "GB",
    "wof:name": "CV3 2EL",
    "wof:placetype": "postalcode"
  },
  "geometry": {"coordinates":[-1.450852,52.389705],"type":"Point"}
}
