{
  "type": "Feature",
  "properties": {
    "iso:country":"GB",
    "wof:name":"CV3 2EL",
    "wof:placetype":"postalcode"
},
  "geometry": {"coordinates":[-1.45085222430725,52.38970471837271],"type":"Point"}
}