{
  "type": "Feature",
  "properties": {
    "iso:country":"GB",
    "wof:name":"TS23 3QU",
    "wof:placetype":"postalcode"
},
  "geometry": {"coordinates":[-1.27705164540632,54.61900620100959],"type":"Point"}
}