{
  "type": "Feature",
  "properties": {
    "date:inception_lower":"1980-01-01",
    "date:inception_upper":"1980-01-31",
    "iso:country":"GB",
    "wof:name":"SW17 7SZ",
    "wof:placetype":"postalcode"
},
  "geometry": {"coordinates":[-0.158738,51.438664],"type":"Point"}
}