{
  "type": "Feature",
  "properties": {
    "iso:country":"GB",
    "wof:name":"BS3 4HB",
    "wof:placetype":"postalcode"
},
  "geometry": {"coordinates":[-2.59650427278058,51.44197146352009],"type":"Point"}
}