{
  "type": "Feature",
  "properties": {
    "date:inception_lower":"1980-01-01",
    "date:inception_upper":"1980-01-31",
    "iso:country":"GB",
    "wof:name":"TQ6 9HS",
    "wof:placetype":"postalcode"
},
  "geometry": {"coordinates":[-3.59502,50.35035],"type":"Point"}
}