{
  "type": "Feature",
  "properties": {
    "iso:country":"GB",
    "wof:name":"TQ6 9HS",
    "wof:placetype":"postalcode"
},
  "geometry": {"coordinates":[-3.59502005963331,50.35035007606765],"type":"Point"}
}