{
  "type": "Feature",
  "properties": {
    "iso:country": "GB",
    "wof:name": "TQ6 9HS",
    "wof:placetype": "postalcode"
  },
  "geometry": {"coordinates":[-3.59502,50.35035],"type":"Point"}
}
