{
  "type": "Feature",
  "properties": {
    "iso:country":"GB",
    "wof:name":"DL13 1SG",
    "wof:placetype":"postalcode"
},
  "geometry": {"coordinates":[-2.14162441226141,54.7369173784798],"type":"Point"}
}