{
  "type": "Feature",
  "properties": {
    "iso:country":"GB",
    "wof:name":"LA9 4PS",
    "wof:placetype":"postalcode"
},
  "geometry": {"coordinates":[-2.75615193299858,54.32647372487397],"type":"Point"}
}