{
  "type": "Feature",
  "properties": {
    "iso:country": "GB",
    "wof:name": "CV34 5LG",
    "wof:placetype": "postalcode"
  },
  "geometry": {"coordinates":[-1.574291,52.286742],"type":"Point"}
}
