{
  "type": "Feature",
  "properties": {
    "iso:country":"GB",
    "wof:name":"CV34 5LG",
    "wof:placetype":"postalcode"
},
  "geometry": {"coordinates":[-1.5740667024083,52.28688781383033],"type":"Point"}
}