{
  "type": "Feature",
  "properties": {
    "iso:country":"GB",
    "wof:name":"UB4 8QA",
    "wof:placetype":"postalcode"
},
  "geometry": {"coordinates":[-0.43790754434371,51.53619999297008],"type":"Point"}
}