{
  "type": "Feature",
  "properties": {
    "iso:country":"GB",
    "wof:name":"LL24 0UB",
    "wof:placetype":"postalcode"
},
  "geometry": {"coordinates":[-3.80656336399202,53.03780280884111],"type":"Point"}
}