{
  "type": "Feature",
  "properties": {
    "iso:country":"GB",
    "wof:name":"CV34 4EW",
    "wof:placetype":"postalcode"
},
  "geometry": {"coordinates":[-1.58646070122133,52.28149269326639],"type":"Point"}
}