{
  "type": "Feature",
  "properties": {
    "date:inception_lower": "1980-01-01",
    "date:inception_upper": "1980-01-01",
    "iso:country": "GB",
    "wof:name": "CV34 4EW",
    "wof:placetype": "postalcode"
  },
  "geometry": {"coordinates":[-1.586449,52.281507],"type":"Point"}
}
