{
  "type": "Feature",
  "properties": {
    "iso:country":"GB",
    "wof:name":"PE19 6SW",
    "wof:placetype":"postalcode"
},
  "geometry": {"coordinates":[-0.23017904805616,52.2252934987546],"type":"Point"}
}