{
  "type": "Feature",
  "properties": {
    "date:inception_lower": "2000-06-01",
    "date:inception_upper": "2000-06-01",
    "iso:country": "GB",
    "wof:name": "PE19 6SW",
    "wof:placetype": "postalcode"
  },
  "geometry": {"coordinates":[-0.230157,52.225306],"type":"Point"}
}
