{
  "type": "Feature",
  "properties": {
    "iso:country": "GB",
    "wof:name": "PE19 6SW",
    "wof:placetype": "postalcode"
  },
  "geometry": {"coordinates":[-0.228868,52.227526],"type":"Point"}
}
