{
  "type": "Feature",
  "properties": {
    "date:inception_lower": "1992-05-01",
    "date:inception_upper": "1992-05-01",
    "iso:country": "GB",
    "wof:name": "G33 3DB",
    "wof:placetype": "postalcode"
  },
  "geometry": {"coordinates":[-4.175679,55.863137],"type":"Point"}
}
