{
  "type": "Feature",
  "properties": {
    "iso:country":"GB",
    "wof:name":"G33 3DB",
    "wof:placetype":"postalcode"
},
  "geometry": {"coordinates":[-4.17567888549276,55.86313679289766],"type":"Point"}
}