{
  "type": "Feature",
  "properties": {
    "date:inception_lower":"1990-07-01",
    "date:inception_upper":"1990-07-31",
    "iso:country":"GB",
    "wof:name":"CH7 5PP",
    "wof:placetype":"postalcode"
},
  "geometry": {"coordinates":[-3.231182,53.178125],"type":"Point"}
}