{
  "type": "Feature",
  "properties": {
    "iso:country":"GB",
    "wof:name":"CB7 5NP",
    "wof:placetype":"postalcode"
},
  "geometry": {"coordinates":[0.39748141820024,52.31104724550763],"type":"Point"}
}