{
  "type": "Feature",
  "properties": {
    "iso:country": "GB",
    "wof:name": "CB7 5NP",
    "wof:placetype": "postalcode"
  },
  "geometry": {"coordinates":[0.397481,52.311047],"type":"Point"}
}
