{
  "type": "Feature",
  "properties": {
    "iso:country": "GB",
    "wof:name": "WD25 9RF",
    "wof:placetype": "postalcode"
  },
  "geometry": {"coordinates":[-0.38376,51.687199],"type":"Point"}
}
