{
  "type": "Feature",
  "properties": {
    "iso:country":"GB",
    "wof:name":"WD25 9RF",
    "wof:placetype":"postalcode"
},
  "geometry": {"coordinates":[-0.38376015636318,51.68719937428541],"type":"Point"}
}