{
  "type": "Feature",
  "properties": {
    "iso:country":"GB",
    "wof:name":"L17 6AZ",
    "wof:placetype":"postalcode"
},
  "geometry": {"coordinates":[-2.92339653655512,53.36797229751475],"type":"Point"}
}