{
  "type": "Feature",
  "properties": {
    "iso:country":"GB",
    "wof:name":"B12 9NH",
    "wof:placetype":"postalcode"
},
  "geometry": {"coordinates":[-1.8969249386872,52.45762243465857],"type":"Point"}
}