{
  "type": "Feature",
  "properties": {
    "iso:country":"GB",
    "wof:name":"M28 1UY",
    "wof:placetype":"postalcode"
},
  "geometry": {"coordinates":[-2.41396714198272,53.50120633778283],"type":"Point"}
}