{
  "type": "Feature",
  "properties": {
    "date:inception_lower": "1980-01-01",
    "date:inception_upper": "1980-01-01",
    "iso:country": "GB",
    "wof:name": "BS5 8NB",
    "wof:placetype": "postalcode"
  },
  "geometry": {"coordinates":[-2.525156,51.458408],"type":"Point"}
}
