{
  "type": "Feature",
  "properties": {
    "iso:country":"GB",
    "wof:name":"BS5 8NB",
    "wof:placetype":"postalcode"
},
  "geometry": {"coordinates":[-2.52515554905498,51.45840793286389],"type":"Point"}
}