{
  "type": "Feature",
  "properties": {
    "iso:country":"GB",
    "wof:name":"TQ9 7LL",
    "wof:placetype":"postalcode"
},
  "geometry": {"coordinates":[-3.74733747617047,50.42002221381884],"type":"Point"}
}