{
  "type": "Feature",
  "properties": {
    "date:inception_lower": "1980-01-01",
    "date:inception_upper": "1980-01-01",
    "iso:country": "GB",
    "wof:name": "TQ9 7LL",
    "wof:placetype": "postalcode"
  },
  "geometry": {"coordinates":[-3.747337,50.420022],"type":"Point"}
}
