{
  "type": "Feature",
  "properties": {
    "iso:country":"GB",
    "wof:name":"NP44 3FF",
    "wof:placetype":"postalcode"
},
  "geometry": {"coordinates":[-3.02131854227494,51.64555217754366],"type":"Point"}
}