{
  "type": "Feature",
  "properties": {
    "date:inception_lower": "2008-09-01",
    "date:inception_upper": "2008-09-01",
    "iso:country": "GB",
    "wof:name": "NP44 3FF",
    "wof:placetype": "postalcode"
  },
  "geometry": {"coordinates":[-3.021319,51.645552],"type":"Point"}
}
