{
  "type": "Feature",
  "properties": {
    "iso:country": "GB",
    "wof:name": "CR7 6AX",
    "wof:placetype": "postalcode"
  },
  "geometry": {"coordinates":[-0.113745,51.390441],"type":"Point"}
}
