{
  "type": "Feature",
  "properties": {
    "date:inception_lower": "1980-01-01",
    "date:inception_upper": "1980-01-01",
    "iso:country": "GB",
    "wof:name": "EH21 6DX",
    "wof:placetype": "postalcode"
  },
  "geometry": {"coordinates":[-3.073164,55.944435],"type":"Point"}
}
