{
  "type": "Feature",
  "properties": {
    "iso:country":"GB",
    "wof:name":"EH21 6DX",
    "wof:placetype":"postalcode"
},
  "geometry": {"coordinates":[-3.07316453067025,55.94443504264608],"type":"Point"}
}