{
  "type": "Feature",
  "properties": {
    "iso:country":"GB",
    "wof:name":"BA5 2GG",
    "wof:placetype":"postalcode"
},
  "geometry": {"coordinates":[-2.65213495199272,51.20572860804823],"type":"Point"}
}