{
  "type": "Feature",
  "properties": {
    "date:inception_lower": "2012-10-01",
    "date:inception_upper": "2012-10-01",
    "iso:country": "GB",
    "wof:name": "BA5 2GG",
    "wof:placetype": "postalcode"
  },
  "geometry": {"coordinates":[-2.652248,51.205647],"type":"Point"}
}
