{
  "type": "Feature",
  "properties": {
    "iso:country": "GB",
    "wof:name": "DH4 7LU",
    "wof:placetype": "postalcode"
  },
  "geometry": {"coordinates":[-1.500988,54.867502],"type":"Point"}
}
