{
  "type": "Feature",
  "properties": {
    "iso:country":"GB",
    "wof:name":"HA7 4LW",
    "wof:placetype":"postalcode"
},
  "geometry": {"coordinates":[-0.30523282729565,51.63413620425436],"type":"Point"}
}