{
  "type": "Feature",
  "properties": {
    "date:inception_lower": "1980-01-01",
    "date:inception_upper": "1980-01-01",
    "iso:country": "GB",
    "wof:name": "HA7 4LW",
    "wof:placetype": "postalcode"
  },
  "geometry": {"coordinates":[-0.30518,51.634148],"type":"Point"}
}
