{
  "type": "Feature",
  "properties": {
    "iso:country": "GB",
    "wof:name": "GL5 2LD",
    "wof:placetype": "postalcode"
  },
  "geometry": {"coordinates":[-2.210123,51.738276],"type":"Point"}
}
