{
  "type": "Feature",
  "properties": {
    "date:inception_lower":"2017-06-01",
    "date:inception_upper":"2017-06-30",
    "iso:country":"GB",
    "wof:name":"GL5 2LD",
    "wof:placetype":"postalcode"
},
  "geometry": {"coordinates":[-2.210079,51.73824],"type":"Point"}
}