{
  "type": "Feature",
  "properties": {
    "iso:country": "GB",
    "wof:name": "RH19 4DQ",
    "wof:placetype": "postalcode"
  },
  "geometry": {"coordinates":[-0.017491,51.119832],"type":"Point"}
}
