{
  "type": "Feature",
  "properties": {
    "iso:country":"GB",
    "wof:name":"LN5 7TY",
    "wof:placetype":"postalcode"
},
  "geometry": {"coordinates":[-0.53753011332201,53.22066241788798],"type":"Point"}
}