{
  "type": "Feature",
  "properties": {
    "iso:country":"GB",
    "wof:name":"HD9 5QE",
    "wof:placetype":"postalcode"
},
  "geometry": {"coordinates":[-1.85717967836046,53.59589299578671],"type":"Point"}
}