{
  "type": "Feature",
  "properties": {
    "iso:country": "GB",
    "wof:name": "HD9 5QE",
    "wof:placetype": "postalcode"
  },
  "geometry": {"coordinates":[-1.85718,53.595893],"type":"Point"}
}
