{
  "type": "Feature",
  "properties": {
    "iso:country": "GB",
    "wof:name": "GL4 6HY",
    "wof:placetype": "postalcode"
  },
  "geometry": {"coordinates":[-2.218402,51.829434],"type":"Point"}
}
