{
  "type": "Feature",
  "properties": {
    "iso:country":"GB",
    "wof:name":"GL4 6HY",
    "wof:placetype":"postalcode"
},
  "geometry": {"coordinates":[-2.21840193641518,51.82943433967704],"type":"Point"}
}