{
  "type": "Feature",
  "properties": {
    "iso:country":"GB",
    "wof:name":"M8 4JZ",
    "wof:placetype":"postalcode"
},
  "geometry": {"coordinates":[-2.24939885801515,53.52381974160522],"type":"Point"}
}