{
  "type": "Feature",
  "properties": {
    "iso:country":"GB",
    "wof:name":"AB16 5EG",
    "wof:placetype":"postalcode"
},
  "geometry": {"coordinates":[-2.14673272798938,57.15459685832894],"type":"Point"}
}