{
  "type": "Feature",
  "properties": {
    "iso:country": "GB",
    "wof:name": "ME14 4LB",
    "wof:placetype": "postalcode"
  },
  "geometry": {"coordinates":[0.569923,51.273767],"type":"Point"}
}
