{
  "type": "Feature",
  "properties": {
    "iso:country":"GB",
    "wof:name":"ME14 4LB",
    "wof:placetype":"postalcode"
},
  "geometry": {"coordinates":[0.56992342211119,51.27376669105876],"type":"Point"}
}