{
  "type": "Feature",
  "properties": {
    "date:inception_lower": "1980-01-01",
    "date:inception_upper": "1980-01-01",
    "iso:country": "GB",
    "wof:name": "ST17 0SZ",
    "wof:placetype": "postalcode"
  },
  "geometry": {"coordinates":[-2.062448,52.771384],"type":"Point"}
}
