{
  "type": "Feature",
  "properties": {
    "date:inception_lower": "1999-06-01",
    "date:inception_upper": "1999-06-01",
    "iso:country": "GB",
    "wof:name": "CF3 5NG",
    "wof:placetype": "postalcode"
  },
  "geometry": {"coordinates":[-3.125741,51.524126],"type":"Point"}
}
