{
  "type": "Feature",
  "properties": {
    "iso:country":"GB",
    "wof:name":"M22 0HP",
    "wof:placetype":"postalcode"
},
  "geometry": {"coordinates":[-2.25622699533062,53.36806131828966],"type":"Point"}
}