{
  "type": "Feature",
  "properties": {
    "date:inception_lower":"1994-05-01",
    "date:inception_upper":"1994-05-31",
    "iso:country":"GB",
    "wof:name":"M22 0HP",
    "wof:placetype":"postalcode"
},
  "geometry": {"coordinates":[-2.256227,53.368061],"type":"Point"}
}