{
  "type": "Feature",
  "properties": {
    "iso:country":"GB",
    "wof:name":"DN22 8RE",
    "wof:placetype":"postalcode"
},
  "geometry": {"coordinates":[-0.96378618894147,53.36758088814216],"type":"Point"}
}