{
  "type": "Feature",
  "properties": {
    "iso:country": "GB",
    "wof:name": "DN22 8RE",
    "wof:placetype": "postalcode"
  },
  "geometry": {"coordinates":[-0.963786,53.367581],"type":"Point"}
}
