{
  "type": "Feature",
  "properties": {
    "iso:country":"GB",
    "wof:name":"GU27 1HR",
    "wof:placetype":"postalcode"
},
  "geometry": {"coordinates":[-0.7212823273136,51.08893046691335],"type":"Point"}
}