{
  "type": "Feature",
  "properties": {
    "date:inception_lower":"1980-01-01",
    "date:inception_upper":"1980-01-31",
    "iso:country":"GB",
    "wof:name":"GU27 1HR",
    "wof:placetype":"postalcode"
},
  "geometry": {"coordinates":[-0.721282,51.08893],"type":"Point"}
}