{
  "type": "Feature",
  "properties": {
    "iso:country": "GB",
    "wof:name": "PE36 5HN",
    "wof:placetype": "postalcode"
  },
  "geometry": {"coordinates":[0.489206,52.937876],"type":"Point"}
}
