{
  "type": "Feature",
  "properties": {
    "iso:country":"GB",
    "wof:name":"EX22 6TP",
    "wof:placetype":"postalcode"
},
  "geometry": {"coordinates":[-4.47384167397795,50.77113975258887],"type":"Point"}
}