{
  "type": "Feature",
  "properties": {
    "date:inception_lower": "1980-01-01",
    "date:inception_upper": "1980-01-01",
    "iso:country": "GB",
    "wof:name": "CA2 7DR",
    "wof:placetype": "postalcode"
  },
  "geometry": {"coordinates":[-2.961019,54.891105],"type":"Point"}
}
