{
  "type": "Feature",
  "properties": {
    "iso:country":"GB",
    "wof:name":"DN6 7LB",
    "wof:placetype":"postalcode"
},
  "geometry": {"coordinates":[-1.1852414417561,53.5664290151834],"type":"Point"}
}