{
  "type": "Feature",
  "properties": {
    "iso:country":"GB",
    "wof:name":"WF1 3HQ",
    "wof:placetype":"postalcode"
},
  "geometry": {"coordinates":[-1.5026753818637,53.70477334979098],"type":"Point"}
}