{
  "type": "Feature",
  "properties": {
    "date:inception_lower": "1980-01-01",
    "date:inception_upper": "1980-01-01",
    "iso:country": "GB",
    "wof:name": "WF1 3HQ",
    "wof:placetype": "postalcode"
  },
  "geometry": {"coordinates":[-1.502675,53.704773],"type":"Point"}
}
