{
  "type": "Feature",
  "properties": {
    "iso:country":"GB",
    "wof:name":"FY1 2HQ",
    "wof:placetype":"postalcode"
},
  "geometry": {"coordinates":[-3.05372488430411,53.82733015230655],"type":"Point"}
}