{
  "type": "Feature",
  "properties": {
    "iso:country":"GB",
    "wof:name":"BS27 3XD",
    "wof:placetype":"postalcode"
},
  "geometry": {"coordinates":[-2.73972263499611,51.25024866876617],"type":"Point"}
}