{
  "type": "Feature",
  "properties": {
    "iso:country": "GB",
    "wof:name": "RG14 5DW",
    "wof:placetype": "postalcode"
  },
  "geometry": {"coordinates":[-1.300536,51.400277],"type":"Point"}
}
