{
  "type": "Feature",
  "properties": {
    "iso:country":"GB",
    "wof:name":"HA3 7NS",
    "wof:placetype":"postalcode"
},
  "geometry": {"coordinates":[-0.3266804958167,51.59789968758655],"type":"Point"}
}