{
  "type": "Feature",
  "properties": {
    "date:inception_lower": "1980-01-01",
    "date:inception_upper": "1980-01-01",
    "iso:country": "GB",
    "wof:name": "HA3 7NS",
    "wof:placetype": "postalcode"
  },
  "geometry": {"coordinates":[-0.32668,51.5979],"type":"Point"}
}
