{
  "type": "Feature",
  "properties": {
    "iso:country":"GB",
    "wof:name":"SL4 3EZ",
    "wof:placetype":"postalcode"
},
  "geometry": {"coordinates":[-0.61654059684868,51.47671189301613],"type":"Point"}
}