{
  "type": "Feature",
  "properties": {
    "iso:country":"GB",
    "wof:name":"CH62 5DT",
    "wof:placetype":"postalcode"
},
  "geometry": {"coordinates":[-2.99925281841981,53.35403948623093],"type":"Point"}
}