{
  "type": "Feature",
  "properties": {
    "iso:country":"GB",
    "wof:name":"B62 8PG",
    "wof:placetype":"postalcode"
},
  "geometry": {"coordinates":[-2.02285536117821,52.45796152316763],"type":"Point"}
}