{
  "type": "Feature",
  "properties": {
    "iso:country": "GB",
    "wof:name": "CF43 3PW",
    "wof:placetype": "postalcode"
  },
  "geometry": {"coordinates":[-3.437585,51.635204],"type":"Point"}
}
