{
  "type": "Feature",
  "properties": {
    "date:inception_lower": "2022-05-01",
    "date:inception_upper": "2022-05-01",
    "iso:country": "GB",
    "wof:name": "MK17 8BZ",
    "wof:placetype": "postalcode"
  },
  "geometry": {"coordinates":[-0.681092,52.029175],"type":"Point"}
}
