{
  "type": "Feature",
  "properties": {
    "iso:country":"GB",
    "wof:name":"LE2 1LT",
    "wof:placetype":"postalcode"
},
  "geometry": {"coordinates":[-1.11214838296331,52.62444852995441],"type":"Point"}
}