{
  "type": "Feature",
  "properties": {
    "iso:country":"GB",
    "wof:name":"S66 7EG",
    "wof:placetype":"postalcode"
},
  "geometry": {"coordinates":[-1.20137429812926,53.42482246488414],"type":"Point"}
}