{
  "type": "Feature",
  "properties": {
    "date:inception_lower":"1990-02-01",
    "date:inception_upper":"1990-02-28",
    "iso:country":"GB",
    "wof:name":"WD7 8HW",
    "wof:placetype":"postalcode"
},
  "geometry": {"coordinates":[-0.320257,51.684276],"type":"Point"}
}