{
  "type": "Feature",
  "properties": {
    "iso:country": "GB",
    "wof:name": "WD7 8HW",
    "wof:placetype": "postalcode"
  },
  "geometry": {"coordinates":[-0.320257,51.684276],"type":"Point"}
}
