{
  "type": "Feature",
  "properties": {
    "date:inception_lower": "1980-01-01",
    "date:inception_upper": "1980-01-01",
    "iso:country": "GB",
    "wof:name": "LN2 3JZ",
    "wof:placetype": "postalcode"
  },
  "geometry": {"coordinates":[-0.487086,53.306819],"type":"Point"}
}
