{
  "type": "Feature",
  "properties": {
    "iso:country": "GB",
    "wof:name": "LN2 3JZ",
    "wof:placetype": "postalcode"
  },
  "geometry": {"coordinates":[-0.487086,53.306819],"type":"Point"}
}
