{
  "type": "Feature",
  "properties": {
    "date:inception_lower": "1980-01-01",
    "date:inception_upper": "1980-01-01",
    "iso:country": "GB",
    "wof:name": "KA12 9DP",
    "wof:placetype": "postalcode"
  },
  "geometry": {"coordinates":[-4.668839,55.627199],"type":"Point"}
}
