{
  "type": "Feature",
  "properties": {
    "iso:country":"GB",
    "wof:name":"KA12 9DP",
    "wof:placetype":"postalcode"
},
  "geometry": {"coordinates":[-4.6688388620931,55.6271988857091],"type":"Point"}
}