{
  "type": "Feature",
  "properties": {
    "iso:country": "GB",
    "wof:name": "G78 1JU",
    "wof:placetype": "postalcode"
  },
  "geometry": {"coordinates":[-4.402615,55.797288],"type":"Point"}
}
