{
  "type": "Feature",
  "properties": {
    "date:inception_lower":"1980-01-01",
    "date:inception_upper":"1980-01-31",
    "iso:country":"GB",
    "wof:name":"S6 2XE",
    "wof:placetype":"postalcode"
},
  "geometry": {"coordinates":[-1.500838,53.394593],"type":"Point"}
}