{
  "type": "Feature",
  "properties": {
    "iso:country":"GB",
    "wof:name":"S6 2XE",
    "wof:placetype":"postalcode"
},
  "geometry": {"coordinates":[-1.50083828150928,53.39456600117011],"type":"Point"}
}