{
  "type": "Feature",
  "properties": {
    "iso:country": "GB",
    "wof:name": "PE32 1FG",
    "wof:placetype": "postalcode"
  },
  "geometry": {"coordinates":[0.562761,52.699597],"type":"Point"}
}
