{
  "type": "Feature",
  "properties": {
    "iso:country":"GB",
    "wof:name":"N20 0QT",
    "wof:placetype":"postalcode"
},
  "geometry": {"coordinates":[-0.17471128670112,51.62568718200294],"type":"Point"}
}