{
  "type": "Feature",
  "properties": {
    "date:inception_lower": "2021-03-01",
    "date:inception_upper": "2021-03-01",
    "iso:country": "GB",
    "wof:name": "PL15 9GS",
    "wof:placetype": "postalcode"
  },
  "geometry": {"coordinates":[-4.349739,50.627571],"type":"Point"}
}
