{
  "type": "Feature",
  "properties": {
    "iso:country":"GB",
    "wof:name":"NP44 2NX",
    "wof:placetype":"postalcode"
},
  "geometry": {"coordinates":[-3.00493746752741,51.66422511140132],"type":"Point"}
}