{
  "type": "Feature",
  "properties": {
    "iso:country":"GB",
    "wof:name":"SO19 9TQ",
    "wof:placetype":"postalcode"
},
  "geometry": {"coordinates":[-1.38139471274901,50.89464617667763],"type":"Point"}
}