{
  "type": "Feature",
  "properties": {
    "date:inception_lower": "1980-01-01",
    "date:inception_upper": "1980-01-01",
    "iso:country": "GB",
    "wof:name": "CM16 5EU",
    "wof:placetype": "postalcode"
  },
  "geometry": {"coordinates":[0.103691,51.696692],"type":"Point"}
}
