{
  "type": "Feature",
  "properties": {
    "date:inception_lower": "1980-01-01",
    "date:inception_upper": "1980-01-01",
    "iso:country": "GB",
    "wof:name": "NW8 9HP",
    "wof:placetype": "postalcode"
  },
  "geometry": {"coordinates":[-0.174903,51.527952],"type":"Point"}
}
