{
  "type": "Feature",
  "properties": {
    "iso:country": "GB",
    "wof:name": "M9 0RL",
    "wof:placetype": "postalcode"
  },
  "geometry": {"coordinates":[-2.216118,53.534491],"type":"Point"}
}
