{
  "type": "Feature",
  "properties": {
    "iso:country":"GB",
    "wof:name":"M9 0RL",
    "wof:placetype":"postalcode"
},
  "geometry": {"coordinates":[-2.21611846514961,53.53449088617846],"type":"Point"}
}