{
  "type": "Feature",
  "properties": {
    "iso:country": "GB",
    "wof:name": "DL14 8AX",
    "wof:placetype": "postalcode"
  },
  "geometry": {"coordinates":[-1.664544,54.686769],"type":"Point"}
}
