{
  "type": "Feature",
  "properties": {
    "iso:country":"GB",
    "wof:name":"LS26 8HN",
    "wof:placetype":"postalcode"
},
  "geometry": {"coordinates":[-1.45856548786897,53.74473244914263],"type":"Point"}
}