{
  "type": "Feature",
  "properties": {
    "date:inception_lower":"1993-01-01",
    "date:inception_upper":"1993-01-31",
    "iso:country":"GB",
    "wof:name":"LS26 8HN",
    "wof:placetype":"postalcode"
},
  "geometry": {"coordinates":[-1.458565,53.744732],"type":"Point"}
}