{
  "type": "Feature",
  "properties": {
    "iso:country": "GB",
    "wof:name": "CM6 1UQ",
    "wof:placetype": "postalcode"
  },
  "geometry": {"coordinates":[0.354362,51.870791],"type":"Point"}
}
