{
  "type": "Feature",
  "properties": {
    "iso:country":"GB",
    "wof:name":"M27 8UX",
    "wof:placetype":"postalcode"
},
  "geometry": {"coordinates":[-2.32083033971635,53.51124523985197],"type":"Point"}
}