{
  "type": "Feature",
  "properties": {
    "iso:country":"GB",
    "wof:name":"TN15 0DL",
    "wof:placetype":"postalcode"
},
  "geometry": {"coordinates":[0.22008772036247,51.29214931644101],"type":"Point"}
}