{
  "type": "Feature",
  "properties": {
    "iso:country":"GB",
    "wof:name":"WR11 4RD",
    "wof:placetype":"postalcode"
},
  "geometry": {"coordinates":[-1.94555496509945,52.09191241240244],"type":"Point"}
}