{
  "type": "Feature",
  "properties": {
    "iso:country": "GB",
    "wof:name": "RH1 6JP",
    "wof:placetype": "postalcode"
  },
  "geometry": {"coordinates":[-0.181845,51.229306],"type":"Point"}
}
