{
  "type": "Feature",
  "properties": {
    "date:inception_lower":"1995-01-01",
    "date:inception_upper":"1995-01-31",
    "iso:country":"GB",
    "wof:name":"WV16 6QQ",
    "wof:placetype":"postalcode"
},
  "geometry": {"coordinates":[-2.562186,52.462839],"type":"Point"}
}