{
  "type": "Feature",
  "properties": {
    "date:inception_lower": "2005-05-01",
    "date:inception_upper": "2005-05-01",
    "iso:country": "GB",
    "wof:name": "WA14 5QB",
    "wof:placetype": "postalcode"
  },
  "geometry": {"coordinates":[-2.343323,53.40421],"type":"Point"}
}
