{
  "type": "Feature",
  "properties": {
    "iso:country":"GB",
    "wof:name":"SA31 1LP",
    "wof:placetype":"postalcode"
},
  "geometry": {"coordinates":[-4.30235261171341,51.85634420298133],"type":"Point"}
}