{
  "type": "Feature",
  "properties": {
    "date:inception_lower": "1980-01-01",
    "date:inception_upper": "1980-01-01",
    "iso:country": "GB",
    "wof:name": "SW17 0DX",
    "wof:placetype": "postalcode"
  },
  "geometry": {"coordinates":[-0.170416,51.43159],"type":"Point"}
}
