{
  "type": "Feature",
  "properties": {
    "iso:country": "GB",
    "wof:name": "CT3 1NA",
    "wof:placetype": "postalcode"
  },
  "geometry": {"coordinates":[1.18998,51.264655],"type":"Point"}
}
