{
  "type": "Feature",
  "properties": {
    "iso:country":"GB",
    "wof:name":"CT3 1NA",
    "wof:placetype":"postalcode"
},
  "geometry": {"coordinates":[1.18998011292804,51.26465534463451],"type":"Point"}
}