{
  "type": "Feature",
  "properties": {
    "iso:country":"GB",
    "wof:name":"B91 2TH",
    "wof:placetype":"postalcode"
},
  "geometry": {"coordinates":[-1.73850711940785,52.41913501620265],"type":"Point"}
}