{
  "type": "Feature",
  "properties": {
    "iso:country": "GB",
    "wof:name": "GL1 4EU",
    "wof:placetype": "postalcode"
  },
  "geometry": {"coordinates":[-2.23555,51.859906],"type":"Point"}
}
