{
  "type": "Feature",
  "properties": {
    "iso:country":"GB",
    "wof:name":"GL1 4EU",
    "wof:placetype":"postalcode"
},
  "geometry": {"coordinates":[-2.2360041043397,51.85998751366579],"type":"Point"}
}