{
  "type": "Feature",
  "properties": {
    "date:inception_lower": "1980-01-01",
    "date:inception_upper": "1980-01-01",
    "iso:country": "GB",
    "wof:name": "GL1 4EU",
    "wof:placetype": "postalcode"
  },
  "geometry": {"coordinates":[-2.23555,51.859906],"type":"Point"}
}
