{
  "type": "Feature",
  "properties": {
    "iso:country":"GB",
    "wof:name":"RM2 5QS",
    "wof:placetype":"postalcode"
},
  "geometry": {"coordinates":[0.19209876058803,51.59342117872103],"type":"Point"}
}