{
  "type": "Feature",
  "properties": {
    "date:inception_lower": "2012-07-01",
    "date:inception_upper": "2012-07-01",
    "iso:country": "GB",
    "wof:name": "RG30 1BQ",
    "wof:placetype": "postalcode"
  },
  "geometry": {"coordinates":[-0.99734,51.458115],"type":"Point"}
}
