{
  "type": "Feature",
  "properties": {
    "iso:country":"GB",
    "wof:name":"LU3 2UE",
    "wof:placetype":"postalcode"
},
  "geometry": {"coordinates":[-0.44425948385359,51.9109673167223],"type":"Point"}
}