{
  "type": "Feature",
  "properties": {
    "iso:country":"GB",
    "wof:name":"CV23 8FA",
    "wof:placetype":"postalcode"
},
  "geometry": {"coordinates":[-1.20232644739346,52.33022073575611],"type":"Point"}
}