{
  "type": "Feature",
  "properties": {
    "iso:country":"GB",
    "wof:name":"HU8 9UR",
    "wof:placetype":"postalcode"
},
  "geometry": {"coordinates":[-0.29726427375655,53.78529745123128],"type":"Point"}
}