{
  "type": "Feature",
  "properties": {
    "date:inception_lower": "1990-02-01",
    "date:inception_upper": "1990-02-01",
    "iso:country": "GB",
    "wof:name": "HU8 9UR",
    "wof:placetype": "postalcode"
  },
  "geometry": {"coordinates":[-0.297264,53.785297],"type":"Point"}
}
