{
  "type": "Feature",
  "properties": {
    "iso:country": "GB",
    "wof:name": "HU8 9UR",
    "wof:placetype": "postalcode"
  },
  "geometry": {"coordinates":[-0.297264,53.785297],"type":"Point"}
}
