{
  "type": "Feature",
  "properties": {
    "iso:country":"GB",
    "wof:name":"TS5 5HS",
    "wof:placetype":"postalcode"
},
  "geometry": {"coordinates":[-1.26190973962127,54.55201553420282],"type":"Point"}
}