{
  "type": "Feature",
  "properties": {
    "iso:country": "GB",
    "wof:name": "NG23 6SZ",
    "wof:placetype": "postalcode"
  },
  "geometry": {"coordinates":[-0.850273,53.20487],"type":"Point"}
}
