{
  "type": "Feature",
  "properties": {
    "iso:country":"GB",
    "wof:name":"NG23 6SZ",
    "wof:placetype":"postalcode"
},
  "geometry": {"coordinates":[-0.85027332469196,53.20487013298102],"type":"Point"}
}