{
  "type": "Feature",
  "properties": {
    "iso:country":"GB",
    "wof:name":"HG3 5QZ",
    "wof:placetype":"postalcode"
},
  "geometry": {"coordinates":[-1.73297445046353,54.07763115874748],"type":"Point"}
}