{
  "type": "Feature",
  "properties": {
    "iso:country":"GB",
    "wof:name":"CV2 3GR",
    "wof:placetype":"postalcode"
},
  "geometry": {"coordinates":[-1.4708261986349,52.41759338558116],"type":"Point"}
}