{
  "type": "Feature",
  "properties": {
    "iso:country":"GB",
    "wof:name":"NE34 6JH",
    "wof:placetype":"postalcode"
},
  "geometry": {"coordinates":[-1.40647262478087,54.98414345530131],"type":"Point"}
}