{
  "type": "Feature",
  "properties": {
    "iso:country":"GB",
    "wof:name":"TN29 0BW",
    "wof:placetype":"postalcode"
},
  "geometry": {"coordinates":[0.94387989824061,51.01429548533909],"type":"Point"}
}