{
  "type": "Feature",
  "properties": {
    "date:inception_lower": "1993-01-01",
    "date:inception_upper": "1993-01-01",
    "iso:country": "GB",
    "wof:name": "TN29 0BW",
    "wof:placetype": "postalcode"
  },
  "geometry": {"coordinates":[0.943997,51.01424],"type":"Point"}
}
