{
  "type": "Feature",
  "properties": {
    "iso:country":"GB",
    "wof:name":"CM24 8GU",
    "wof:placetype":"postalcode"
},
  "geometry": {"coordinates":[0.19703080067048,51.89602066104077],"type":"Point"}
}