{
  "type": "Feature",
  "properties": {
    "iso:country": "GB",
    "wof:name": "CM24 8GU",
    "wof:placetype": "postalcode"
  },
  "geometry": {"coordinates":[0.197031,51.896021],"type":"Point"}
}
