{
  "type": "Feature",
  "properties": {
    "date:inception_lower":"2012-12-01",
    "date:inception_upper":"2012-12-31",
    "iso:country":"GB",
    "wof:name":"CM24 8GU",
    "wof:placetype":"postalcode"
},
  "geometry": {"coordinates":[0.197031,51.896021],"type":"Point"}
}