{
  "type": "Feature",
  "properties": {
    "date:inception_lower": "1993-08-01",
    "date:inception_upper": "1993-08-01",
    "iso:country": "GB",
    "wof:name": "HD8 0BR",
    "wof:placetype": "postalcode"
  },
  "geometry": {"coordinates":[-1.716853,53.633464],"type":"Point"}
}
