{
  "type": "Feature",
  "properties": {
    "iso:country":"GB",
    "wof:name":"SL9 9QR",
    "wof:placetype":"postalcode"
},
  "geometry": {"coordinates":[-0.55578620907225,51.61023962503595],"type":"Point"}
}