{
  "type": "Feature",
  "properties": {
    "iso:country":"GB",
    "wof:name":"E3 3NP",
    "wof:placetype":"postalcode"
},
  "geometry": {"coordinates":[-0.01524507393268,51.52545807546312],"type":"Point"}
}