{
  "type": "Feature",
  "properties": {
    "iso:country":"GB",
    "wof:name":"DL6 2HJ",
    "wof:placetype":"postalcode"
},
  "geometry": {"coordinates":[-1.44436750470753,54.41722311229088],"type":"Point"}
}