{
  "type": "Feature",
  "properties": {
    "date:inception_lower": "1980-01-01",
    "date:inception_upper": "1980-01-01",
    "iso:country": "GB",
    "wof:name": "DL6 2HJ",
    "wof:placetype": "postalcode"
  },
  "geometry": {"coordinates":[-1.44753,54.417707],"type":"Point"}
}
