{
  "type": "Feature",
  "properties": {
    "iso:country": "GB",
    "wof:name": "DL6 2HJ",
    "wof:placetype": "postalcode"
  },
  "geometry": {"coordinates":[-1.44753,54.417707],"type":"Point"}
}
