{
  "type": "Feature",
  "properties": {
    "iso:country": "GB",
    "wof:name": "ME8 0FD",
    "wof:placetype": "postalcode"
  },
  "geometry": {"coordinates":[0.601735,51.362678],"type":"Point"}
}
