{
  "type": "Feature",
  "properties": {
    "iso:country":"GB",
    "wof:name":"ME8 0FD",
    "wof:placetype":"postalcode"
},
  "geometry": {"coordinates":[0.6017351692212,51.3626776352114],"type":"Point"}
}