{
  "type": "Feature",
  "properties": {
    "iso:country":"GB",
    "wof:name":"HP22 5UX",
    "wof:placetype":"postalcode"
},
  "geometry": {"coordinates":[-0.79241897398047,51.78576672387523],"type":"Point"}
}