{
  "type": "Feature",
  "properties": {
    "date:inception_lower":"1980-01-01",
    "date:inception_upper":"1980-01-31",
    "iso:country":"GB",
    "wof:name":"HP22 5UX",
    "wof:placetype":"postalcode"
},
  "geometry": {"coordinates":[-0.792419,51.785767],"type":"Point"}
}