{
  "type": "Feature",
  "properties": {
    "iso:country": "GB",
    "wof:name": "CM8 1LZ",
    "wof:placetype": "postalcode"
  },
  "geometry": {"coordinates":[0.622592,51.797973],"type":"Point"}
}
