{
  "type": "Feature",
  "properties": {
    "date:inception_lower":"1980-01-01",
    "date:inception_upper":"1980-01-31",
    "iso:country":"GB",
    "wof:name":"WN5 0QE",
    "wof:placetype":"postalcode"
},
  "geometry": {"coordinates":[-2.662813,53.547922],"type":"Point"}
}