{
  "type": "Feature",
  "properties": {
    "iso:country":"GB",
    "wof:name":"CM20 3LZ",
    "wof:placetype":"postalcode"
},
  "geometry": {"coordinates":[0.11312071528219,51.77107972225986],"type":"Point"}
}