{
  "type": "Feature",
  "properties": {
    "iso:country":"GB",
    "wof:name":"TA8 1DJ",
    "wof:placetype":"postalcode"
},
  "geometry": {"coordinates":[-2.99852564190257,51.23127736792183],"type":"Point"}
}