{
  "type": "Feature",
  "properties": {
    "iso:country": "GB",
    "wof:name": "TA8 1DJ",
    "wof:placetype": "postalcode"
  },
  "geometry": {"coordinates":[-2.998533,51.23121],"type":"Point"}
}
