{
  "type": "Feature",
  "properties": {
    "iso:country":"GB",
    "wof:name":"GU4 8PP",
    "wof:placetype":"postalcode"
},
  "geometry": {"coordinates":[-0.54417224936362,51.23141546414066],"type":"Point"}
}