{
  "type": "Feature",
  "properties": {
    "iso:country":"GB",
    "wof:name":"WN2 1QA",
    "wof:placetype":"postalcode"
},
  "geometry": {"coordinates":[-2.56618781728728,53.56121828456434],"type":"Point"}
}