{
  "type": "Feature",
  "properties": {
    "date:inception_lower":"1992-08-01",
    "date:inception_upper":"1992-08-31",
    "iso:country":"GB",
    "wof:name":"DE23 6RW",
    "wof:placetype":"postalcode"
},
  "geometry": {"coordinates":[-1.486618,52.908693],"type":"Point"}
}