{
  "type": "Feature",
  "properties": {
    "iso:country":"GB",
    "wof:name":"IV3 8PW",
    "wof:placetype":"postalcode"
},
  "geometry": {"coordinates":[-4.27933297718242,57.47646980489232],"type":"Point"}
}