{
  "type": "Feature",
  "properties": {
    "iso:country": "GB",
    "wof:name": "SA17 4PS",
    "wof:placetype": "postalcode"
  },
  "geometry": {"coordinates":[-4.289274,51.743515],"type":"Point"}
}
