{
  "type": "Feature",
  "properties": {
    "iso:country":"GB",
    "wof:name":"KY12 7DR",
    "wof:placetype":"postalcode"
},
  "geometry": {"coordinates":[-3.46013424693899,56.07136058367576],"type":"Point"}
}