{
  "type": "Feature",
  "properties": {
    "date:inception_lower": "1980-01-01",
    "date:inception_upper": "1980-01-01",
    "iso:country": "GB",
    "wof:name": "RM16 2YD",
    "wof:placetype": "postalcode"
  },
  "geometry": {"coordinates":[0.333281,51.4895],"type":"Point"}
}
