{
  "type": "Feature",
  "properties": {
    "iso:country": "GB",
    "wof:name": "G61 1HW",
    "wof:placetype": "postalcode"
  },
  "geometry": {"coordinates":[-4.320865,55.898114],"type":"Point"}
}
