{
  "type": "Feature",
  "properties": {
    "iso:country":"GB",
    "wof:name":"G61 1HW",
    "wof:placetype":"postalcode"
},
  "geometry": {"coordinates":[-4.32086497198797,55.89811429718739],"type":"Point"}
}