{
  "type": "Feature",
  "properties": {
    "iso:country":"GB",
    "wof:name":"BR6 7HJ",
    "wof:placetype":"postalcode"
},
  "geometry": {"coordinates":[0.05749634981611,51.34000396900245],"type":"Point"}
}