{
  "type": "Feature",
  "properties": {
    "iso:country": "GB",
    "wof:name": "BR6 7HJ",
    "wof:placetype": "postalcode"
  },
  "geometry": {"coordinates":[0.057496,51.340004],"type":"Point"}
}
