{
  "type": "Feature",
  "properties": {
    "date:inception_lower":"1990-02-01",
    "date:inception_upper":"1990-02-28",
    "iso:country":"GB",
    "wof:name":"NW2 7BS",
    "wof:placetype":"postalcode"
},
  "geometry": {"coordinates":[-0.240158,51.567427],"type":"Point"}
}