{
  "type": "Feature",
  "properties": {
    "iso:country":"GB",
    "wof:name":"DN2 4LT",
    "wof:placetype":"postalcode"
},
  "geometry": {"coordinates":[-1.12007484748489,53.53869601873098],"type":"Point"}
}