{
  "type": "Feature",
  "properties": {
    "iso:country": "GB",
    "wof:name": "NP18 3DZ",
    "wof:placetype": "postalcode"
  },
  "geometry": {"coordinates":[-2.973972,51.617955],"type":"Point"}
}
