{
  "type": "Feature",
  "properties": {
    "date:inception_lower": "1999-06-01",
    "date:inception_upper": "1999-06-01",
    "iso:country": "GB",
    "wof:name": "NP18 3DZ",
    "wof:placetype": "postalcode"
  },
  "geometry": {"coordinates":[-2.973972,51.617955],"type":"Point"}
}
