{
  "type": "Feature",
  "properties": {
    "iso:country":"GB",
    "wof:name":"RH13 6GH",
    "wof:placetype":"postalcode"
},
  "geometry": {"coordinates":[-0.26211237382863,51.0316564243858],"type":"Point"}
}