{
  "type": "Feature",
  "properties": {
    "iso:country":"GB",
    "wof:name":"PE12 9AS",
    "wof:placetype":"postalcode"
},
  "geometry": {"coordinates":[0.11906137323893,52.76854321525101],"type":"Point"}
}