{
  "type": "Feature",
  "properties": {
    "iso:country":"GB",
    "wof:name":"M32 9EF",
    "wof:placetype":"postalcode"
},
  "geometry": {"coordinates":[-2.32519571113228,53.44527596604782],"type":"Point"}
}