{
  "type": "Feature",
  "properties": {
    "date:inception_lower": "1980-01-01",
    "date:inception_upper": "1980-01-01",
    "iso:country": "GB",
    "wof:name": "G75 8JQ",
    "wof:placetype": "postalcode"
  },
  "geometry": {"coordinates":[-4.201619,55.757208],"type":"Point"}
}
