{
  "type": "Feature",
  "properties": {
    "iso:country": "GB",
    "wof:name": "G75 8JQ",
    "wof:placetype": "postalcode"
  },
  "geometry": {"coordinates":[-4.201619,55.757208],"type":"Point"}
}
