{
  "type": "Feature",
  "properties": {
    "iso:country":"GB",
    "wof:name":"HP13 7YA",
    "wof:placetype":"postalcode"
},
  "geometry": {"coordinates":[-0.71383082996082,51.63045654989025],"type":"Point"}
}