{
  "type": "Feature",
  "properties": {
    "iso:country":"GB",
    "wof:name":"G71 6AH",
    "wof:placetype":"postalcode"
},
  "geometry": {"coordinates":[-4.08111827441579,55.82966020697377],"type":"Point"}
}