{
  "type": "Feature",
  "properties": {
    "date:inception_lower": "1995-07-01",
    "date:inception_upper": "1995-07-01",
    "iso:country": "GB",
    "wof:name": "RG20 9ND",
    "wof:placetype": "postalcode"
  },
  "geometry": {"coordinates":[-1.325086,51.339914],"type":"Point"}
}
