{
  "type": "Feature",
  "properties": {
    "iso:country":"GB",
    "wof:name":"RG20 9ND",
    "wof:placetype":"postalcode"
},
  "geometry": {"coordinates":[-1.32498488416972,51.34022933933366],"type":"Point"}
}