{
  "type": "Feature",
  "properties": {
    "date:inception_lower": "2020-02-01",
    "date:inception_upper": "2020-02-01",
    "iso:country": "GB",
    "wof:name": "SW13 0DD",
    "wof:placetype": "postalcode"
  },
  "geometry": {"coordinates":[-0.240368,51.474612],"type":"Point"}
}
