{
  "type": "Feature",
  "properties": {
    "iso:country": "GB",
    "wof:name": "NR32 4PL",
    "wof:placetype": "postalcode"
  },
  "geometry": {"coordinates":[1.753089,52.491644],"type":"Point"}
}
