{
  "type": "Feature",
  "properties": {
    "date:inception_lower": "1999-06-01",
    "date:inception_upper": "1999-06-01",
    "iso:country": "GB",
    "wof:name": "CH45 4LX",
    "wof:placetype": "postalcode"
  },
  "geometry": {"coordinates":[-3.045037,53.423015],"type":"Point"}
}
