{
  "type": "Feature",
  "properties": {
    "iso:country":"GB",
    "wof:name":"CH45 4LX",
    "wof:placetype":"postalcode"
},
  "geometry": {"coordinates":[-3.04503748396355,53.42301540549784],"type":"Point"}
}