{
  "type": "Feature",
  "properties": {
    "iso:country":"GB",
    "wof:name":"RM9 5QL",
    "wof:placetype":"postalcode"
},
  "geometry": {"coordinates":[0.13250843366945,51.55015789665399],"type":"Point"}
}