{
  "type": "Feature",
  "properties": {
    "date:inception_lower":"1980-01-01",
    "date:inception_upper":"1980-01-31",
    "iso:country":"GB",
    "wof:name":"RM9 5QL",
    "wof:placetype":"postalcode"
},
  "geometry": {"coordinates":[0.132508,51.550158],"type":"Point"}
}