{
  "type": "Feature",
  "properties": {
    "iso:country": "GB",
    "wof:name": "CF32 0NE",
    "wof:placetype": "postalcode"
  },
  "geometry": {"coordinates":[-3.652276,51.498484],"type":"Point"}
}
