{
  "type": "Feature",
  "properties": {
    "iso:country": "GB",
    "wof:name": "PE30 5PP",
    "wof:placetype": "postalcode"
  },
  "geometry": {"coordinates":[0.407536,52.749344],"type":"Point"}
}
