{
  "type": "Feature",
  "properties": {
    "date:inception_lower":"1980-01-01",
    "date:inception_upper":"1980-01-31",
    "iso:country":"GB",
    "wof:name":"PE30 5PP",
    "wof:placetype":"postalcode"
},
  "geometry": {"coordinates":[0.407536,52.749344],"type":"Point"}
}