{
  "type": "Feature",
  "properties": {
    "date:inception_lower": "1980-01-01",
    "date:inception_upper": "1980-01-01",
    "iso:country": "GB",
    "wof:name": "TQ1 4TR",
    "wof:placetype": "postalcode"
  },
  "geometry": {"coordinates":[-3.518852,50.505774],"type":"Point"}
}
