{
  "type": "Feature",
  "properties": {
    "iso:country":"GB",
    "wof:name":"SS0 0RR",
    "wof:placetype":"postalcode"
},
  "geometry": {"coordinates":[0.69178618076654,51.55301836860449],"type":"Point"}
}