{
  "type": "Feature",
  "properties": {
    "date:inception_lower": "1980-01-01",
    "date:inception_upper": "1980-01-01",
    "iso:country": "GB",
    "wof:name": "EX3 0AH",
    "wof:placetype": "postalcode"
  },
  "geometry": {"coordinates":[-3.460048,50.682097],"type":"Point"}
}
