{
  "type": "Feature",
  "properties": {
    "iso:country": "GB",
    "wof:name": "EX3 0AH",
    "wof:placetype": "postalcode"
  },
  "geometry": {"coordinates":[-3.460048,50.682097],"type":"Point"}
}
