{
  "type": "Feature",
  "properties": {
    "date:inception_lower": "2017-03-01",
    "date:inception_upper": "2017-03-01",
    "iso:country": "GB",
    "wof:name": "BB11 9TQ",
    "wof:placetype": "postalcode"
  },
  "geometry": {"coordinates":[-2.244649,53.787611],"type":"Point"}
}
