{
  "type": "Feature",
  "properties": {
    "iso:country":"GB",
    "wof:name":"SA4 4BN",
    "wof:placetype":"postalcode"
},
  "geometry": {"coordinates":[-4.03955519777661,51.6710882856509],"type":"Point"}
}