{
  "type": "Feature",
  "properties": {
    "iso:country": "GB",
    "wof:name": "SA4 4BN",
    "wof:placetype": "postalcode"
  },
  "geometry": {"coordinates":[-4.039555,51.671088],"type":"Point"}
}
