{
  "type": "Feature",
  "properties": {
    "iso:country": "GB",
    "wof:name": "DL3 7DU",
    "wof:placetype": "postalcode"
  },
  "geometry": {"coordinates":[-1.561185,54.526736],"type":"Point"}
}
