{
  "type": "Feature",
  "properties": {
    "iso:country": "GB",
    "wof:name": "PL8 1AU",
    "wof:placetype": "postalcode"
  },
  "geometry": {"coordinates":[-4.036415,50.317151],"type":"Point"}
}
