{
  "type": "Feature",
  "properties": {
    "iso:country":"GB",
    "wof:name":"PL8 1AU",
    "wof:placetype":"postalcode"
},
  "geometry": {"coordinates":[-4.03638704495519,50.31716550968954],"type":"Point"}
}