{
  "type": "Feature",
  "properties": {
    "date:inception_lower":"1990-07-01",
    "date:inception_upper":"1990-07-31",
    "iso:country":"GB",
    "wof:name":"IG7 4JL",
    "wof:placetype":"postalcode"
},
  "geometry": {"coordinates":[0.098713,51.609049],"type":"Point"}
}