{
  "type": "Feature",
  "properties": {
    "iso:country": "GB",
    "wof:name": "HU9 5QD",
    "wof:placetype": "postalcode"
  },
  "geometry": {"coordinates":[-0.263475,53.74725],"type":"Point"}
}
