{
  "type": "Feature",
  "properties": {
    "date:inception_lower":"2007-07-01",
    "date:inception_upper":"2007-07-31",
    "iso:country":"GB",
    "wof:name":"CH4 9FH",
    "wof:placetype":"postalcode"
},
  "geometry": {"coordinates":[-2.905651,53.121942],"type":"Point"}
}