{
  "type": "Feature",
  "properties": {
    "iso:country":"GB",
    "wof:name":"CH4 9FH",
    "wof:placetype":"postalcode"
},
  "geometry": {"coordinates":[-2.90565106622049,53.12194151805194],"type":"Point"}
}