{
  "type": "Feature",
  "properties": {
    "date:inception_lower": "1980-01-01",
    "date:inception_upper": "1980-01-01",
    "iso:country": "GB",
    "wof:name": "BN13 1NW",
    "wof:placetype": "postalcode"
  },
  "geometry": {"coordinates":[-0.397498,50.830007],"type":"Point"}
}
