{
  "type": "Feature",
  "properties": {
    "iso:country": "GB",
    "wof:name": "B48 7JF",
    "wof:placetype": "postalcode"
  },
  "geometry": {"coordinates":[-1.886605,52.357972],"type":"Point"}
}
