{
  "type": "Feature",
  "properties": {
    "iso:country": "GB",
    "wof:name": "EH48 3QT",
    "wof:placetype": "postalcode"
  },
  "geometry": {"coordinates":[-3.706779,55.902068],"type":"Point"}
}
