{
  "type": "Feature",
  "properties": {
    "iso:country":"GB",
    "wof:name":"IP22 4TL",
    "wof:placetype":"postalcode"
},
  "geometry": {"coordinates":[1.10193269749592,52.38262980667326],"type":"Point"}
}