{
  "type": "Feature",
  "properties": {
    "iso:country": "GB",
    "wof:name": "IP22 4TL",
    "wof:placetype": "postalcode"
  },
  "geometry": {"coordinates":[1.101933,52.38263],"type":"Point"}
}
