{
  "type": "Feature",
  "properties": {
    "iso:country":"GB",
    "wof:name":"SY8 4AA",
    "wof:placetype":"postalcode"
},
  "geometry": {"coordinates":[-2.72153929782694,52.35538534464224],"type":"Point"}
}