{
  "type": "Feature",
  "properties": {
    "date:inception_lower":"1985-10-01",
    "date:inception_upper":"1985-10-31",
    "iso:country":"GB",
    "wof:name":"CV10 9JX",
    "wof:placetype":"postalcode"
},
  "geometry": {"coordinates":[-1.515683,52.526565],"type":"Point"}
}