{
  "type": "Feature",
  "properties": {
    "date:inception_lower": "1980-01-01",
    "date:inception_upper": "1980-01-01",
    "iso:country": "GB",
    "wof:name": "PO21 5TU",
    "wof:placetype": "postalcode"
  },
  "geometry": {"coordinates":[-0.696571,50.798055],"type":"Point"}
}
