{
  "type": "Feature",
  "properties": {
    "date:inception_lower": "1980-01-01",
    "date:inception_upper": "1980-01-01",
    "iso:country": "GB",
    "wof:name": "IP1 5JL",
    "wof:placetype": "postalcode"
  },
  "geometry": {"coordinates":[1.120291,52.07351],"type":"Point"}
}
