{
  "type": "Feature",
  "properties": {
    "iso:country":"GB",
    "wof:name":"IP1 5JL",
    "wof:placetype":"postalcode"
},
  "geometry": {"coordinates":[1.12029077254687,52.07351044944653],"type":"Point"}
}