{
  "type": "Feature",
  "properties": {
    "iso:country":"GB",
    "wof:name":"EN4 0ER",
    "wof:placetype":"postalcode"
},
  "geometry": {"coordinates":[-0.16644184801009,51.6688112418459],"type":"Point"}
}