{
  "type": "Feature",
  "properties": {
    "date:inception_lower": "1980-01-01",
    "date:inception_upper": "1980-01-01",
    "iso:country": "GB",
    "wof:name": "DA7 4JJ",
    "wof:placetype": "postalcode"
  },
  "geometry": {"coordinates":[0.150141,51.457902],"type":"Point"}
}
