{
  "type": "Feature",
  "properties": {
    "iso:country":"GB",
    "wof:name":"WF3 4EJ",
    "wof:placetype":"postalcode"
},
  "geometry": {"coordinates":[-1.47907857039656,53.71914412161444],"type":"Point"}
}