{
  "type": "Feature",
  "properties": {
    "iso:country":"GB",
    "wof:name":"BN7 3DH",
    "wof:placetype":"postalcode"
},
  "geometry": {"coordinates":[-0.0703149292612,50.94650140665409],"type":"Point"}
}