{
  "type": "Feature",
  "properties": {
    "iso:country": "GB",
    "wof:name": "GU2 8HN",
    "wof:placetype": "postalcode"
  },
  "geometry": {"coordinates":[-0.598174,51.245428],"type":"Point"}
}
