{
  "type": "Feature",
  "properties": {
    "iso:country":"GB",
    "wof:name":"KT15 1JU",
    "wof:placetype":"postalcode"
},
  "geometry": {"coordinates":[-0.50325605827554,51.36049850034998],"type":"Point"}
}