{
  "type": "Feature",
  "properties": {
    "iso:country":"GB",
    "wof:name":"TS18 1AD",
    "wof:placetype":"postalcode"
},
  "geometry": {"coordinates":[-1.31321003043267,54.56206842229991],"type":"Point"}
}