{
  "type": "Feature",
  "properties": {
    "iso:country": "GB",
    "wof:name": "ST16 1GG",
    "wof:placetype": "postalcode"
  },
  "geometry": {"coordinates":[-2.131621,52.835213],"type":"Point"}
}
