{
  "type": "Feature",
  "properties": {
    "date:inception_lower": "2020-01-01",
    "date:inception_upper": "2020-01-01",
    "iso:country": "GB",
    "wof:name": "ST16 1GG",
    "wof:placetype": "postalcode"
  },
  "geometry": {"coordinates":[-2.132258,52.835024],"type":"Point"}
}
