{
  "type": "Feature",
  "properties": {
    "iso:country":"GB",
    "wof:name":"PO9 5HE",
    "wof:placetype":"postalcode"
},
  "geometry": {"coordinates":[-0.98213154168199,50.86577873842323],"type":"Point"}
}