{
  "type": "Feature",
  "properties": {
    "date:inception_lower": "2002-07-01",
    "date:inception_upper": "2002-07-01",
    "iso:country": "GB",
    "wof:name": "BA4 5HB",
    "wof:placetype": "postalcode"
  },
  "geometry": {"coordinates":[-2.548728,51.192457],"type":"Point"}
}
