{
  "type": "Feature",
  "properties": {
    "iso:country":"GB",
    "wof:name":"B36 8DN",
    "wof:placetype":"postalcode"
},
  "geometry": {"coordinates":[-1.8021773168683,52.50077088088279],"type":"Point"}
}