{
  "type": "Feature",
  "properties": {
    "date:inception_lower":"1980-01-01",
    "date:inception_upper":"1980-01-31",
    "iso:country":"GB",
    "wof:name":"B36 8DN",
    "wof:placetype":"postalcode"
},
  "geometry": {"coordinates":[-1.802177,52.500771],"type":"Point"}
}