{
  "type": "Feature",
  "properties": {
    "date:inception_lower":"1980-01-01",
    "date:inception_upper":"1980-01-31",
    "iso:country":"GB",
    "wof:name":"LA4 6AX",
    "wof:placetype":"postalcode"
},
  "geometry": {"coordinates":[-2.838379,54.079553],"type":"Point"}
}