{
  "type": "Feature",
  "properties": {
    "iso:country": "GB",
    "wof:name": "LA4 6AX",
    "wof:placetype": "postalcode"
  },
  "geometry": {"coordinates":[-2.838379,54.079553],"type":"Point"}
}
