{
  "type": "Feature",
  "properties": {
    "iso:country":"GB",
    "wof:name":"LA4 6AX",
    "wof:placetype":"postalcode"
},
  "geometry": {"coordinates":[-2.83842707122501,54.07956045618553],"type":"Point"}
}