{
  "type": "Feature",
  "properties": {
    "iso:country": "GB",
    "wof:name": "G66 3UX",
    "wof:placetype": "postalcode"
  },
  "geometry": {"coordinates":[-4.132942,55.926903],"type":"Point"}
}
