{
  "type": "Feature",
  "properties": {
    "iso:country":"GB",
    "wof:name":"HP6 5LH",
    "wof:placetype":"postalcode"
},
  "geometry": {"coordinates":[-0.60269457330752,51.68450446773709],"type":"Point"}
}