{
  "type": "Feature",
  "properties": {
    "date:inception_lower":"1980-01-01",
    "date:inception_upper":"1980-01-31",
    "iso:country":"GB",
    "wof:name":"HP6 5LH",
    "wof:placetype":"postalcode"
},
  "geometry": {"coordinates":[-0.603234,51.684579],"type":"Point"}
}