{
  "type": "Feature",
  "properties": {
    "date:inception_lower": "1980-01-01",
    "date:inception_upper": "1980-01-01",
    "iso:country": "GB",
    "wof:name": "PO6 1BN",
    "wof:placetype": "postalcode"
  },
  "geometry": {"coordinates":[-1.023221,50.851804],"type":"Point"}
}
