{
  "type": "Feature",
  "properties": {
    "iso:country":"GB",
    "wof:name":"PO6 1BN",
    "wof:placetype":"postalcode"
},
  "geometry": {"coordinates":[-1.02322108275243,50.85180435880509],"type":"Point"}
}