{
  "type": "Feature",
  "properties": {
    "iso:country": "GB",
    "wof:name": "LL29 8AS",
    "wof:placetype": "postalcode"
  },
  "geometry": {"coordinates":[-3.709093,53.289284],"type":"Point"}
}
