{
  "type": "Feature",
  "properties": {
    "date:inception_lower": "1980-01-01",
    "date:inception_upper": "1980-01-01",
    "iso:country": "GB",
    "wof:name": "LL29 8AS",
    "wof:placetype": "postalcode"
  },
  "geometry": {"coordinates":[-3.709093,53.289284],"type":"Point"}
}
