{
  "type": "Feature",
  "properties": {
    "iso:country":"GB",
    "wof:name":"LL29 8AS",
    "wof:placetype":"postalcode"
},
  "geometry": {"coordinates":[-3.70909343757489,53.28928357274985],"type":"Point"}
}