{
  "type": "Feature",
  "properties": {
    "date:inception_lower":"1990-02-01",
    "date:inception_upper":"1990-02-28",
    "iso:country":"GB",
    "wof:name":"AL4 0RT",
    "wof:placetype":"postalcode"
},
  "geometry": {"coordinates":[-0.271179,51.742606],"type":"Point"}
}