{
  "type": "Feature",
  "properties": {
    "iso:country":"GB",
    "wof:name":"AL4 0RT",
    "wof:placetype":"postalcode"
},
  "geometry": {"coordinates":[-0.27106651070169,51.74252361520021],"type":"Point"}
}