{
  "type": "Feature",
  "properties": {
    "iso:country":"GB",
    "wof:name":"M32 8NU",
    "wof:placetype":"postalcode"
},
  "geometry": {"coordinates":[-2.31050861801712,53.44216009956553],"type":"Point"}
}