{
  "type": "Feature",
  "properties": {
    "date:inception_lower": "1994-05-01",
    "date:inception_upper": "1994-05-01",
    "iso:country": "GB",
    "wof:name": "M32 8NU",
    "wof:placetype": "postalcode"
  },
  "geometry": {"coordinates":[-2.310509,53.44216],"type":"Point"}
}
