{
  "type": "Feature",
  "properties": {
    "iso:country":"GB",
    "wof:name":"AB45 3LS",
    "wof:placetype":"postalcode"
},
  "geometry": {"coordinates":[-2.48031984686914,57.6326890169319],"type":"Point"}
}