{
  "type": "Feature",
  "properties": {
    "iso:country":"GB",
    "wof:name":"CM12 0SY",
    "wof:placetype":"postalcode"
},
  "geometry": {"coordinates":[0.41208442381848,51.63733526144722],"type":"Point"}
}