{
  "type": "Feature",
  "properties": {
    "iso:country": "GB",
    "wof:name": "CB22 7PN",
    "wof:placetype": "postalcode"
  },
  "geometry": {"coordinates":[0.100107,52.125876],"type":"Point"}
}
