{
  "type": "Feature",
  "properties": {
    "iso:country":"GB",
    "wof:name":"CF71 7DR",
    "wof:placetype":"postalcode"
},
  "geometry": {"coordinates":[-3.41324341469686,51.45114543080811],"type":"Point"}
}