{
  "type": "Feature",
  "properties": {
    "iso:country":"GB",
    "wof:name":"EN1 3DE",
    "wof:placetype":"postalcode"
},
  "geometry": {"coordinates":[-0.07301439091949,51.65465412049011],"type":"Point"}
}