{
  "type": "Feature",
  "properties": {
    "date:inception_lower":"1980-01-01",
    "date:inception_upper":"1980-01-31",
    "iso:country":"GB",
    "wof:name":"EH10 4QX",
    "wof:placetype":"postalcode"
},
  "geometry": {"coordinates":[-3.208251,55.927352],"type":"Point"}
}