{
  "type": "Feature",
  "properties": {
    "iso:country":"GB",
    "wof:name":"EH10 4QX",
    "wof:placetype":"postalcode"
},
  "geometry": {"coordinates":[-3.20825124888543,55.92735167959307],"type":"Point"}
}