{
  "type": "Feature",
  "properties": {
    "iso:country":"GB",
    "wof:name":"TA6 6BE",
    "wof:placetype":"postalcode"
},
  "geometry": {"coordinates":[-2.99765914409028,51.12094979376156],"type":"Point"}
}