{
  "type": "Feature",
  "properties": {
    "iso:country":"GB",
    "wof:name":"SY13 3LG",
    "wof:placetype":"postalcode"
},
  "geometry": {"coordinates":[-2.67945966933332,52.9265370777907],"type":"Point"}
}