{
  "type": "Feature",
  "properties": {
    "iso:country": "GB",
    "wof:name": "SY13 3LG",
    "wof:placetype": "postalcode"
  },
  "geometry": {"coordinates":[-2.67946,52.926537],"type":"Point"}
}
