{
  "type": "Feature",
  "properties": {
    "iso:country":"GB",
    "wof:name":"CR2 0NS",
    "wof:placetype":"postalcode"
},
  "geometry": {"coordinates":[-0.08960217515663,51.34166842315647],"type":"Point"}
}