{
  "type": "Feature",
  "properties": {
    "iso:country":"GB",
    "wof:name":"RG12 9BB",
    "wof:placetype":"postalcode"
},
  "geometry": {"coordinates":[-0.73329776630437,51.41256903118827],"type":"Point"}
}