{
  "type": "Feature",
  "properties": {
    "iso:country":"GB",
    "wof:name":"IG2 6PQ",
    "wof:placetype":"postalcode"
},
  "geometry": {"coordinates":[0.0769690766457,51.57440049785594],"type":"Point"}
}