{
  "type": "Feature",
  "properties": {
    "iso:country":"GB",
    "wof:name":"EX23 8NH",
    "wof:placetype":"postalcode"
},
  "geometry": {"coordinates":[-4.54819143652606,50.83629389198971],"type":"Point"}
}