{
  "type": "Feature",
  "properties": {
    "iso:country": "GB",
    "wof:name": "EX23 8NH",
    "wof:placetype": "postalcode"
  },
  "geometry": {"coordinates":[-4.548425,50.836581],"type":"Point"}
}
