{
  "type": "Feature",
  "properties": {
    "date:inception_lower": "1990-02-01",
    "date:inception_upper": "1990-02-01",
    "iso:country": "GB",
    "wof:name": "NE7 7JW",
    "wof:placetype": "postalcode"
  },
  "geometry": {"coordinates":[-1.576977,54.996906],"type":"Point"}
}
