{
  "type": "Feature",
  "properties": {
    "iso:country":"GB",
    "wof:name":"NE7 7JW",
    "wof:placetype":"postalcode"
},
  "geometry": {"coordinates":[-1.57697738313577,54.99690605748694],"type":"Point"}
}