{
  "type": "Feature",
  "properties": {
    "iso:country":"GB",
    "wof:name":"BS8 3UQ",
    "wof:placetype":"postalcode"
},
  "geometry": {"coordinates":[-2.69048751896804,51.44103279355448],"type":"Point"}
}