{
  "type": "Feature",
  "properties": {
    "iso:country":"GB",
    "wof:name":"B49 6DA",
    "wof:placetype":"postalcode"
},
  "geometry": {"coordinates":[-1.87127395963818,52.1890689743034],"type":"Point"}
}