{
  "type": "Feature",
  "properties": {
    "date:inception_lower": "1980-01-01",
    "date:inception_upper": "1980-01-01",
    "iso:country": "GB",
    "wof:name": "B49 6DA",
    "wof:placetype": "postalcode"
  },
  "geometry": {"coordinates":[-1.870871,52.189063],"type":"Point"}
}
