{
  "type": "Feature",
  "properties": {
    "iso:country": "GB",
    "wof:name": "B49 6DA",
    "wof:placetype": "postalcode"
  },
  "geometry": {"coordinates":[-1.870813,52.189063],"type":"Point"}
}
