{
  "type": "Feature",
  "properties": {
    "date:inception_lower":"2008-03-01",
    "date:inception_upper":"2008-03-31",
    "iso:country":"GB",
    "wof:name":"WF1 5ND",
    "wof:placetype":"postalcode"
},
  "geometry": {"coordinates":[-1.488889,53.668592],"type":"Point"}
}