{
  "type": "Feature",
  "properties": {
    "iso:country":"GB",
    "wof:name":"WF1 5ND",
    "wof:placetype":"postalcode"
},
  "geometry": {"coordinates":[-1.48888916138773,53.66859166560223],"type":"Point"}
}