{
  "type": "Feature",
  "properties": {
    "iso:country": "GB",
    "wof:name": "B73 5RZ",
    "wof:placetype": "postalcode"
  },
  "geometry": {"coordinates":[-1.840004,52.542029],"type":"Point"}
}
