{
  "type": "Feature",
  "properties": {
    "date:inception_lower": "2011-06-01",
    "date:inception_upper": "2011-06-01",
    "iso:country": "GB",
    "wof:name": "B73 5RZ",
    "wof:placetype": "postalcode"
  },
  "geometry": {"coordinates":[-1.840004,52.542029],"type":"Point"}
}
