{
  "type": "Feature",
  "properties": {
    "iso:country":"GB",
    "wof:name":"B73 5RZ",
    "wof:placetype":"postalcode"
},
  "geometry": {"coordinates":[-1.84000440796953,52.54202871220464],"type":"Point"}
}