{
  "type": "Feature",
  "properties": {
    "iso:country":"GB",
    "wof:name":"B20 2LY",
    "wof:placetype":"postalcode"
},
  "geometry": {"coordinates":[-1.92806040053288,52.52408107675787],"type":"Point"}
}