{
  "type": "Feature",
  "properties": {
    "iso:country": "GB",
    "wof:name": "CW5 6QX",
    "wof:placetype": "postalcode"
  },
  "geometry": {"coordinates":[-2.48386,53.071538],"type":"Point"}
}
