{
  "type": "Feature",
  "properties": {
    "iso:country":"GB",
    "wof:name":"CW5 6QX",
    "wof:placetype":"postalcode"
},
  "geometry": {"coordinates":[-2.48386114044491,53.07152077664375],"type":"Point"}
}