{
  "type": "Feature",
  "properties": {
    "iso:country": "GB",
    "wof:name": "GU9 7DN",
    "wof:placetype": "postalcode"
  },
  "geometry": {"coordinates":[-0.800555,51.214244],"type":"Point"}
}
