{
  "type": "Feature",
  "properties": {
    "date:inception_lower": "1991-09-01",
    "date:inception_upper": "1991-09-01",
    "iso:country": "GB",
    "wof:name": "GU9 7DN",
    "wof:placetype": "postalcode"
  },
  "geometry": {"coordinates":[-0.800555,51.214244],"type":"Point"}
}
