{
  "type": "Feature",
  "properties": {
    "iso:country":"GB",
    "wof:name":"GU9 7DN",
    "wof:placetype":"postalcode"
},
  "geometry": {"coordinates":[-0.80055553743204,51.21424359773194],"type":"Point"}
}