{
  "type": "Feature",
  "properties": {
    "iso:country":"GB",
    "wof:name":"SA33 6DB",
    "wof:placetype":"postalcode"
},
  "geometry": {"coordinates":[-4.29404079776786,51.9403893174197],"type":"Point"}
}