{
  "type": "Feature",
  "properties": {
    "date:inception_lower":"1980-01-01",
    "date:inception_upper":"1980-01-31",
    "iso:country":"GB",
    "wof:name":"SA33 6DB",
    "wof:placetype":"postalcode"
},
  "geometry": {"coordinates":[-4.294041,51.940389],"type":"Point"}
}