{
  "type": "Feature",
  "properties": {
    "iso:country": "GB",
    "wof:name": "SA33 6DB",
    "wof:placetype": "postalcode"
  },
  "geometry": {"coordinates":[-4.294041,51.940389],"type":"Point"}
}
