{
  "type": "Feature",
  "properties": {
    "date:inception_lower": "1980-01-01",
    "date:inception_upper": "1980-01-01",
    "iso:country": "GB",
    "wof:name": "SP4 9QB",
    "wof:placetype": "postalcode"
  },
  "geometry": {"coordinates":[-1.791491,51.241037],"type":"Point"}
}
