{
  "type": "Feature",
  "properties": {
    "iso:country":"GB",
    "wof:name":"SP4 9QB",
    "wof:placetype":"postalcode"
},
  "geometry": {"coordinates":[-1.79149101089052,51.24103655558189],"type":"Point"}
}