{
  "type": "Feature",
  "properties": {
    "iso:country": "GB",
    "wof:name": "B65 8AS",
    "wof:placetype": "postalcode"
  },
  "geometry": {"coordinates":[-2.046099,52.477769],"type":"Point"}
}
