{
  "type": "Feature",
  "properties": {
    "iso:country":"GB",
    "wof:name":"KY8 5LH",
    "wof:placetype":"postalcode"
},
  "geometry": {"coordinates":[-3.0544957186586,56.21557889613072],"type":"Point"}
}