{
  "type": "Feature",
  "properties": {
    "iso:country":"GB",
    "wof:name":"SW20 0QX",
    "wof:placetype":"postalcode"
},
  "geometry": {"coordinates":[-0.24191472159047,51.41174981674854],"type":"Point"}
}