{
  "type": "Feature",
  "properties": {
    "iso:country":"GB",
    "wof:name":"ST1 6ED",
    "wof:placetype":"postalcode"
},
  "geometry": {"coordinates":[-2.16967968078258,53.04309771968787],"type":"Point"}
}