{
  "type": "Feature",
  "properties": {
    "iso:country":"GB",
    "wof:name":"SE18 7JU",
    "wof:placetype":"postalcode"
},
  "geometry": {"coordinates":[0.07292821176621,51.4842657457325],"type":"Point"}
}