{
  "type": "Feature",
  "properties": {
    "iso:country":"GB",
    "wof:name":"BH16 6DE",
    "wof:placetype":"postalcode"
},
  "geometry": {"coordinates":[-2.07758424077009,50.75931083579795],"type":"Point"}
}