{
  "type": "Feature",
  "properties": {
    "date:inception_lower": "1980-01-01",
    "date:inception_upper": "1980-01-01",
    "iso:country": "GB",
    "wof:name": "LD2 3BY",
    "wof:placetype": "postalcode"
  },
  "geometry": {"coordinates":[-3.413723,52.150788],"type":"Point"}
}
