{
  "type": "Feature",
  "properties": {
    "iso:country":"GB",
    "wof:name":"LD2 3BY",
    "wof:placetype":"postalcode"
},
  "geometry": {"coordinates":[-3.41372350805181,52.1507882798439],"type":"Point"}
}