{
  "type": "Feature",
  "properties": {
    "iso:country":"GB",
    "wof:name":"SN14 0TE",
    "wof:placetype":"postalcode"
},
  "geometry": {"coordinates":[-2.14310426801029,51.45829258464794],"type":"Point"}
}