{
  "type": "Feature",
  "properties": {
    "iso:country": "GB",
    "wof:name": "SN14 0TE",
    "wof:placetype": "postalcode"
  },
  "geometry": {"coordinates":[-2.143104,51.458293],"type":"Point"}
}
