{
  "type": "Feature",
  "properties": {
    "date:inception_lower": "2008-08-01",
    "date:inception_upper": "2008-08-01",
    "iso:country": "GB",
    "wof:name": "LS23 7FN",
    "wof:placetype": "postalcode"
  },
  "geometry": {"coordinates":[-1.307236,53.912956],"type":"Point"}
}
