{
  "type": "Feature",
  "properties": {
    "iso:country":"GB",
    "wof:name":"LS23 7FN",
    "wof:placetype":"postalcode"
},
  "geometry": {"coordinates":[-1.30689613397339,53.91202931469395],"type":"Point"}
}