{
  "type": "Feature",
  "properties": {
    "iso:country": "GB",
    "wof:name": "PR1 7BY",
    "wof:placetype": "postalcode"
  },
  "geometry": {"coordinates":[-2.708157,53.763104],"type":"Point"}
}
