{
  "type": "Feature",
  "properties": {
    "iso:country":"GB",
    "wof:name":"W3 7LG",
    "wof:placetype":"postalcode"
},
  "geometry": {"coordinates":[-0.25523058183201,51.50725084405408],"type":"Point"}
}