{
  "type": "Feature",
  "properties": {
    "iso:country": "GB",
    "wof:name": "NE49 0JW",
    "wof:placetype": "postalcode"
  },
  "geometry": {"coordinates":[-2.506434,54.950546],"type":"Point"}
}
