{
  "type": "Feature",
  "properties": {
    "iso:country":"GB",
    "wof:name":"CT14 9HX",
    "wof:placetype":"postalcode"
},
  "geometry": {"coordinates":[1.38135983575543,51.21098342236196],"type":"Point"}
}