{
  "type": "Feature",
  "properties": {
    "iso:country": "GB",
    "wof:name": "DL6 3ST",
    "wof:placetype": "postalcode"
  },
  "geometry": {"coordinates":[-1.377946,54.314232],"type":"Point"}
}
