{
  "type": "Feature",
  "properties": {
    "iso:country":"GB",
    "wof:name":"DL6 3ST",
    "wof:placetype":"postalcode"
},
  "geometry": {"coordinates":[-1.37739777458122,54.31427998254126],"type":"Point"}
}