{
  "type": "Feature",
  "properties": {
    "iso:country":"GB",
    "wof:name":"TW13 4HN",
    "wof:placetype":"postalcode"
},
  "geometry": {"coordinates":[-0.41666555706288,51.4394014265679],"type":"Point"}
}