{
  "type": "Feature",
  "properties": {
    "iso:country":"GB",
    "wof:name":"BA1 6EN",
    "wof:placetype":"postalcode"
},
  "geometry": {"coordinates":[-2.35132156707554,51.39553225852232],"type":"Point"}
}