{
  "type": "Feature",
  "properties": {
    "date:inception_lower":"1980-01-01",
    "date:inception_upper":"1980-01-31",
    "iso:country":"GB",
    "wof:name":"KT17 4DU",
    "wof:placetype":"postalcode"
},
  "geometry": {"coordinates":[-0.259213,51.333746],"type":"Point"}
}