{
  "type": "Feature",
  "properties": {
    "date:inception_lower": "1980-01-01",
    "date:inception_upper": "1980-01-01",
    "iso:country": "GB",
    "wof:name": "EX2 4AP",
    "wof:placetype": "postalcode"
  },
  "geometry": {"coordinates":[-3.528759,50.717414],"type":"Point"}
}
