{
  "type": "Feature",
  "properties": {
    "iso:country": "GB",
    "wof:name": "DD10 0BN",
    "wof:placetype": "postalcode"
  },
  "geometry": {"coordinates":[-2.412514,56.773855],"type":"Point"}
}
