{
  "type": "Feature",
  "properties": {
    "iso:country": "GB",
    "wof:name": "SR2 8RE",
    "wof:placetype": "postalcode"
  },
  "geometry": {"coordinates":[-1.373415,54.895173],"type":"Point"}
}
