{
  "type": "Feature",
  "properties": {
    "iso:country": "GB",
    "wof:name": "DG14 0RQ",
    "wof:placetype": "postalcode"
  },
  "geometry": {"coordinates":[-2.925039,55.085685],"type":"Point"}
}
