{
  "type": "Feature",
  "properties": {
    "iso:country":"GB",
    "wof:name":"DG14 0RQ",
    "wof:placetype":"postalcode"
},
  "geometry": {"coordinates":[-2.92503914815776,55.08568532423815],"type":"Point"}
}