{
  "type": "Feature",
  "properties": {
    "date:inception_lower": "1980-01-01",
    "date:inception_upper": "1980-01-01",
    "iso:country": "GB",
    "wof:name": "DG14 0RQ",
    "wof:placetype": "postalcode"
  },
  "geometry": {"coordinates":[-2.925058,55.085726],"type":"Point"}
}
