{
  "type": "Feature",
  "properties": {
    "iso:country":"GB",
    "wof:name":"TS10 3LA",
    "wof:placetype":"postalcode"
},
  "geometry": {"coordinates":[-1.05546133185416,54.61481173095552],"type":"Point"}
}