{
  "type": "Feature",
  "properties": {
    "iso:country":"GB",
    "wof:name":"PO15 6NY",
    "wof:placetype":"postalcode"
},
  "geometry": {"coordinates":[-1.21568765255292,50.865063428951],"type":"Point"}
}