{
  "type": "Feature",
  "properties": {
    "iso:country":"GB",
    "wof:name":"L19 8LP",
    "wof:placetype":"postalcode"
},
  "geometry": {"coordinates":[-2.89515813951451,53.34867249305315],"type":"Point"}
}