{
  "type": "Feature",
  "properties": {
    "iso:country":"GB",
    "wof:name":"NE37 2EL",
    "wof:placetype":"postalcode"
},
  "geometry": {"coordinates":[-1.52797688611323,54.92064775046343],"type":"Point"}
}