{
  "type": "Feature",
  "properties": {
    "iso:country": "GB",
    "wof:name": "NE43 7WQ",
    "wof:placetype": "postalcode"
  },
  "geometry": {"coordinates":[-1.842345,54.969412],"type":"Point"}
}
