{
  "type": "Feature",
  "properties": {
    "iso:country":"GB",
    "wof:name":"DG5 4BF",
    "wof:placetype":"postalcode"
},
  "geometry": {"coordinates":[-3.82735164773778,54.93279746809461],"type":"Point"}
}