{
  "type": "Feature",
  "properties": {
    "date:inception_lower": "1994-05-01",
    "date:inception_upper": "1994-05-01",
    "iso:country": "GB",
    "wof:name": "DG5 4BF",
    "wof:placetype": "postalcode"
  },
  "geometry": {"coordinates":[-3.827352,54.932797],"type":"Point"}
}
