{
  "type": "Feature",
  "properties": {
    "iso:country": "GB",
    "wof:name": "G81 6JF",
    "wof:placetype": "postalcode"
  },
  "geometry": {"coordinates":[-4.419099,55.925073],"type":"Point"}
}
