{
  "type": "Feature",
  "properties": {
    "date:inception_lower": "1994-12-01",
    "date:inception_upper": "1994-12-01",
    "iso:country": "GB",
    "wof:name": "HU5 5SQ",
    "wof:placetype": "postalcode"
  },
  "geometry": {"coordinates":[-0.402075,53.762937],"type":"Point"}
}
