{
  "type": "Feature",
  "properties": {
    "iso:country":"GB",
    "wof:name":"HU5 5SQ",
    "wof:placetype":"postalcode"
},
  "geometry": {"coordinates":[-0.40207543109204,53.76293705996828],"type":"Point"}
}