{
  "type": "Feature",
  "properties": {
    "iso:country":"GB",
    "wof:name":"CB6 2DU",
    "wof:placetype":"postalcode"
},
  "geometry": {"coordinates":[0.21798750122735,52.43487486680444],"type":"Point"}
}