{
  "type": "Feature",
  "properties": {
    "iso:country": "GB",
    "wof:name": "CB6 2DU",
    "wof:placetype": "postalcode"
  },
  "geometry": {"coordinates":[0.217988,52.434875],"type":"Point"}
}
