{
  "type": "Feature",
  "properties": {
    "date:inception_lower": "2023-07-01",
    "date:inception_upper": "2023-07-01",
    "iso:country": "GB",
    "wof:name": "DN7 5FE",
    "wof:placetype": "postalcode"
  },
  "geometry": {"coordinates":[-1.026757,53.601597],"type":"Point"}
}
