{
  "type": "Feature",
  "properties": {
    "date:inception_lower": "2012-10-01",
    "date:inception_upper": "2012-10-01",
    "iso:country": "GB",
    "wof:name": "S40 2FY",
    "wof:placetype": "postalcode"
  },
  "geometry": {"coordinates":[-1.429319,53.230101],"type":"Point"}
}
