{
  "type": "Feature",
  "properties": {
    "iso:country":"GB",
    "wof:name":"S44 5RP",
    "wof:placetype":"postalcode"
},
  "geometry": {"coordinates":[-1.34711101870139,53.19233887414786],"type":"Point"}
}