{
  "type": "Feature",
  "properties": {
    "date:inception_lower": "1992-08-01",
    "date:inception_upper": "1992-08-01",
    "iso:country": "GB",
    "wof:name": "S44 5RP",
    "wof:placetype": "postalcode"
  },
  "geometry": {"coordinates":[-1.347109,53.192367],"type":"Point"}
}
