{
  "type": "Feature",
  "properties": {
    "iso:country":"GB",
    "wof:name":"SY4 5AU",
    "wof:placetype":"postalcode"
},
  "geometry": {"coordinates":[-2.72189018116697,52.85623142831979],"type":"Point"}
}