{
  "type": "Feature",
  "properties": {
    "iso:country":"GB",
    "wof:name":"M38 9QL",
    "wof:placetype":"postalcode"
},
  "geometry": {"coordinates":[-2.41960088137585,53.53278108583581],"type":"Point"}
}