{
  "type": "Feature",
  "properties": {
    "iso:country":"GB",
    "wof:name":"LA21 8BT",
    "wof:placetype":"postalcode"
},
  "geometry": {"coordinates":[-3.12711188256068,54.32830535620253],"type":"Point"}
}