{
  "type": "Feature",
  "properties": {
    "date:inception_lower": "1980-01-01",
    "date:inception_upper": "1980-01-01",
    "iso:country": "GB",
    "wof:name": "RG22 5QU",
    "wof:placetype": "postalcode"
  },
  "geometry": {"coordinates":[-1.141434,51.243623],"type":"Point"}
}
