{
  "type": "Feature",
  "properties": {
    "date:inception_lower": "1987-04-01",
    "date:inception_upper": "1987-04-01",
    "iso:country": "GB",
    "wof:name": "LS7 1QQ",
    "wof:placetype": "postalcode"
  },
  "geometry": {"coordinates":[-1.527302,53.809243],"type":"Point"}
}
