{
  "type": "Feature",
  "properties": {
    "iso:country":"GB",
    "wof:name":"LS7 1QQ",
    "wof:placetype":"postalcode"
},
  "geometry": {"coordinates":[-1.52730212820398,53.80924290632658],"type":"Point"}
}