{
  "type": "Feature",
  "properties": {
    "iso:country": "GB",
    "wof:name": "BS25 5NF",
    "wof:placetype": "postalcode"
  },
  "geometry": {"coordinates":[-2.801612,51.335391],"type":"Point"}
}
