{
  "type": "Feature",
  "properties": {
    "iso:country":"GB",
    "wof:name":"BS25 5NF",
    "wof:placetype":"postalcode"
},
  "geometry": {"coordinates":[-2.80161235664323,51.33539072234488],"type":"Point"}
}