{
  "type": "Feature",
  "properties": {
    "iso:country":"GB",
    "wof:name":"BH20 4FA",
    "wof:placetype":"postalcode"
},
  "geometry": {"coordinates":[-2.11391689968991,50.69338267652734],"type":"Point"}
}