{
  "type": "Feature",
  "properties": {
    "date:inception_lower": "2012-07-01",
    "date:inception_upper": "2012-07-01",
    "iso:country": "GB",
    "wof:name": "BH20 4FA",
    "wof:placetype": "postalcode"
  },
  "geometry": {"coordinates":[-2.113917,50.693383],"type":"Point"}
}
