{
  "type": "Feature",
  "properties": {
    "iso:country": "GB",
    "wof:name": "DN36 4HJ",
    "wof:placetype": "postalcode"
  },
  "geometry": {"coordinates":[-0.056012,53.527229],"type":"Point"}
}
