{
  "type": "Feature",
  "properties": {
    "iso:country":"GB",
    "wof:name":"DN36 4HJ",
    "wof:placetype":"postalcode"
},
  "geometry": {"coordinates":[-0.05601216354605,53.52722865371985],"type":"Point"}
}