{
  "type": "Feature",
  "properties": {
    "iso:country":"GB",
    "wof:name":"LE12 9TY",
    "wof:placetype":"postalcode"
},
  "geometry": {"coordinates":[-1.33837399373937,52.7805245612531],"type":"Point"}
}