{
  "type": "Feature",
  "properties": {
    "iso:country": "GB",
    "wof:name": "PR26 7AH",
    "wof:placetype": "postalcode"
  },
  "geometry": {"coordinates":[-2.739705,53.691214],"type":"Point"}
}
