{
  "type": "Feature",
  "properties": {
    "iso:country":"GB",
    "wof:name":"PR26 7AH",
    "wof:placetype":"postalcode"
},
  "geometry": {"coordinates":[-2.73970553068906,53.69121427448196],"type":"Point"}
}