{
  "type": "Feature",
  "properties": {
    "iso:country":"GB",
    "wof:name":"WA8 8XX",
    "wof:placetype":"postalcode"
},
  "geometry": {"coordinates":[-2.76577496935632,53.36808116058246],"type":"Point"}
}