{
  "type": "Feature",
  "properties": {
    "date:inception_lower": "2009-12-01",
    "date:inception_upper": "2009-12-01",
    "iso:country": "GB",
    "wof:name": "CF72 8GB",
    "wof:placetype": "postalcode"
  },
  "geometry": {"coordinates":[-3.354796,51.520058],"type":"Point"}
}
