{
  "type": "Feature",
  "properties": {
    "iso:country": "GB",
    "wof:name": "WA4 3HJ",
    "wof:placetype": "postalcode"
  },
  "geometry": {"coordinates":[-2.556589,53.362301],"type":"Point"}
}
