{
  "type": "Feature",
  "properties": {
    "date:inception_lower":"1980-01-01",
    "date:inception_upper":"1980-01-31",
    "iso:country":"GB",
    "wof:name":"WA4 3HJ",
    "wof:placetype":"postalcode"
},
  "geometry": {"coordinates":[-2.556589,53.362301],"type":"Point"}
}