{
  "type": "Feature",
  "properties": {
    "iso:country":"GB",
    "wof:name":"WA4 3HJ",
    "wof:placetype":"postalcode"
},
  "geometry": {"coordinates":[-2.55658890795847,53.36230099190539],"type":"Point"}
}