{
  "type": "Feature",
  "properties": {
    "date:inception_lower": "1980-01-01",
    "date:inception_upper": "1980-01-01",
    "iso:country": "GB",
    "wof:name": "EX23 0NR",
    "wof:placetype": "postalcode"
  },
  "geometry": {"coordinates":[-4.609063,50.739547],"type":"Point"}
}
