{
  "type": "Feature",
  "properties": {
    "iso:country":"GB",
    "wof:name":"SW11 2UA",
    "wof:placetype":"postalcode"
},
  "geometry": {"coordinates":[-0.18313218882442,51.46317199656265],"type":"Point"}
}