{
  "type": "Feature",
  "properties": {
    "iso:country": "GB",
    "wof:name": "CF5 3EU",
    "wof:placetype": "postalcode"
  },
  "geometry": {"coordinates":[-3.238069,51.489463],"type":"Point"}
}
