{
  "type": "Feature",
  "properties": {
    "iso:country": "GB",
    "wof:name": "DN12 2EN",
    "wof:placetype": "postalcode"
  },
  "geometry": {"coordinates":[-1.231355,53.479697],"type":"Point"}
}
