{
  "type": "Feature",
  "properties": {
    "iso:country":"GB",
    "wof:name":"NR3 3JP",
    "wof:placetype":"postalcode"
},
  "geometry": {"coordinates":[1.28673627216971,52.64668777588827],"type":"Point"}
}