{
  "type": "Feature",
  "properties": {
    "date:inception_lower": "2000-12-01",
    "date:inception_upper": "2000-12-01",
    "iso:country": "GB",
    "wof:name": "MK19 6EX",
    "wof:placetype": "postalcode"
  },
  "geometry": {"coordinates":[-0.862069,52.064605],"type":"Point"}
}
