{
  "type": "Feature",
  "properties": {
    "iso:country":"GB",
    "wof:name":"MK19 6EX",
    "wof:placetype":"postalcode"
},
  "geometry": {"coordinates":[-0.86206877374368,52.06460507971684],"type":"Point"}
}