{
  "type": "Feature",
  "properties": {
    "date:inception_lower":"1990-02-01",
    "date:inception_upper":"1990-02-28",
    "iso:country":"GB",
    "wof:name":"HU9 2AX",
    "wof:placetype":"postalcode"
},
  "geometry": {"coordinates":[-0.310741,53.749082],"type":"Point"}
}