{
  "type": "Feature",
  "properties": {
    "iso:country": "GB",
    "wof:name": "HU9 2AX",
    "wof:placetype": "postalcode"
  },
  "geometry": {"coordinates":[-0.310741,53.749082],"type":"Point"}
}
