{
  "type": "Feature",
  "properties": {
    "iso:country":"GB",
    "wof:name":"NP20 1DW",
    "wof:placetype":"postalcode"
},
  "geometry": {"coordinates":[-2.995314504068,51.58730318928896],"type":"Point"}
}