{
  "type": "Feature",
  "properties": {
    "date:inception_lower": "1999-06-01",
    "date:inception_upper": "1999-06-01",
    "iso:country": "GB",
    "wof:name": "NP20 1DW",
    "wof:placetype": "postalcode"
  },
  "geometry": {"coordinates":[-2.995314,51.587303],"type":"Point"}
}
