{
  "type": "Feature",
  "properties": {
    "iso:country":"GB",
    "wof:name":"BB3 1QP",
    "wof:placetype":"postalcode"
},
  "geometry": {"coordinates":[-2.47751764381201,53.70398892735682],"type":"Point"}
}