{
  "type": "Feature",
  "properties": {
    "iso:country":"GB",
    "wof:name":"DN9 3LA",
    "wof:placetype":"postalcode"
},
  "geometry": {"coordinates":[-1.02359436566938,53.50451819530379],"type":"Point"}
}