{
  "type": "Feature",
  "properties": {
    "iso:country": "GB",
    "wof:name": "DN9 3LA",
    "wof:placetype": "postalcode"
  },
  "geometry": {"coordinates":[-1.023594,53.504518],"type":"Point"}
}
