{
  "type": "Feature",
  "properties": {
    "iso:country":"GB",
    "wof:name":"FY5 3DH",
    "wof:placetype":"postalcode"
},
  "geometry": {"coordinates":[-3.02213566562964,53.86589376173492],"type":"Point"}
}