{
  "type": "Feature",
  "properties": {
    "date:inception_lower": "1980-01-01",
    "date:inception_upper": "1980-01-01",
    "iso:country": "GB",
    "wof:name": "NE36 0QT",
    "wof:placetype": "postalcode"
  },
  "geometry": {"coordinates":[-1.450184,54.944935],"type":"Point"}
}
