{
  "type": "Feature",
  "properties": {
    "iso:country":"GB",
    "wof:name":"SA1 8PJ",
    "wof:placetype":"postalcode"
},
  "geometry": {"coordinates":[-3.9330356014678,51.62104917746187],"type":"Point"}
}