{
  "type": "Feature",
  "properties": {
    "iso:country":"GB",
    "wof:name":"CR0 1QE",
    "wof:placetype":"postalcode"
},
  "geometry": {"coordinates":[-0.09996740720574,51.37120741518429],"type":"Point"}
}