{
  "type": "Feature",
  "properties": {
    "iso:country":"GB",
    "wof:name":"GU12 6BW",
    "wof:placetype":"postalcode"
},
  "geometry": {"coordinates":[-0.70722755523186,51.25280736394401],"type":"Point"}
}