{
  "type": "Feature",
  "properties": {
    "date:inception_lower": "1980-01-01",
    "date:inception_upper": "1980-01-01",
    "iso:country": "GB",
    "wof:name": "GU12 6BW",
    "wof:placetype": "postalcode"
  },
  "geometry": {"coordinates":[-0.707228,51.252807],"type":"Point"}
}
