{
  "type": "Feature",
  "properties": {
    "iso:country":"GB",
    "wof:name":"EN1 3DP",
    "wof:placetype":"postalcode"
},
  "geometry": {"coordinates":[-0.07267775831688,51.65611435536674],"type":"Point"}
}