{
  "type": "Feature",
  "properties": {
    "iso:country":"GB",
    "wof:name":"IV7 8JN",
    "wof:placetype":"postalcode"
},
  "geometry": {"coordinates":[-4.33942666431644,57.60044875324389],"type":"Point"}
}