{
  "type": "Feature",
  "properties": {
    "iso:country": "GB",
    "wof:name": "IV7 8JN",
    "wof:placetype": "postalcode"
  },
  "geometry": {"coordinates":[-4.339427,57.600449],"type":"Point"}
}
