{
  "type": "Feature",
  "properties": {
    "date:inception_lower":"1980-01-01",
    "date:inception_upper":"1980-01-31",
    "iso:country":"GB",
    "wof:name":"IV7 8JN",
    "wof:placetype":"postalcode"
},
  "geometry": {"coordinates":[-4.339427,57.600449],"type":"Point"}
}