{
  "type": "Feature",
  "properties": {
    "iso:country": "GB",
    "wof:name": "RG20 6NU",
    "wof:placetype": "postalcode"
  },
  "geometry": {"coordinates":[-1.253698,51.513841],"type":"Point"}
}
