{
  "type": "Feature",
  "properties": {
    "iso:country":"GB",
    "wof:name":"RG20 6NU",
    "wof:placetype":"postalcode"
},
  "geometry": {"coordinates":[-1.25369801379735,51.51384125787302],"type":"Point"}
}