{
  "type": "Feature",
  "properties": {
    "iso:country":"GB",
    "wof:name":"N13 5PP",
    "wof:placetype":"postalcode"
},
  "geometry": {"coordinates":[-0.10371067111448,51.62129755169158],"type":"Point"}
}