{
  "type": "Feature",
  "properties": {
    "iso:country": "GB",
    "wof:name": "NN9 6PQ",
    "wof:placetype": "postalcode"
  },
  "geometry": {"coordinates":[-0.53686,52.342564],"type":"Point"}
}
