{
  "type": "Feature",
  "properties": {
    "iso:country": "GB",
    "wof:name": "TF9 2LF",
    "wof:placetype": "postalcode"
  },
  "geometry": {"coordinates":[-2.514454,52.854318],"type":"Point"}
}
