{
  "type": "Feature",
  "properties": {
    "iso:country":"GB",
    "wof:name":"TF9 2LF",
    "wof:placetype":"postalcode"
},
  "geometry": {"coordinates":[-2.51445376809208,52.85431828512763],"type":"Point"}
}