{
  "type": "Feature",
  "properties": {
    "iso:country":"GB",
    "wof:name":"DH3 1AW",
    "wof:placetype":"postalcode"
},
  "geometry": {"coordinates":[-1.57317911206259,54.8966324509288],"type":"Point"}
}