{
  "type": "Feature",
  "properties": {
    "iso:country": "GB",
    "wof:name": "LS12 4AB",
    "wof:placetype": "postalcode"
  },
  "geometry": {"coordinates":[-1.587376,53.784675],"type":"Point"}
}
