{
  "type": "Feature",
  "properties": {
    "iso:country":"GB",
    "wof:name":"LA4 5NP",
    "wof:placetype":"postalcode"
},
  "geometry": {"coordinates":[-2.85696450761818,54.07273385538177],"type":"Point"}
}