{
  "type": "Feature",
  "properties": {
    "iso:country":"GB",
    "wof:name":"DN37 9RA",
    "wof:placetype":"postalcode"
},
  "geometry": {"coordinates":[-0.14074390932693,53.56540731442617],"type":"Point"}
}