{
  "type": "Feature",
  "properties": {
    "iso:country":"GB",
    "wof:name":"DN15 8PA",
    "wof:placetype":"postalcode"
},
  "geometry": {"coordinates":[-0.66031864970119,53.59995990367486],"type":"Point"}
}