{
  "type": "Feature",
  "properties": {
    "iso:country": "GB",
    "wof:name": "DN15 8PA",
    "wof:placetype": "postalcode"
  },
  "geometry": {"coordinates":[-0.660319,53.59996],"type":"Point"}
}
