{
  "type": "Feature",
  "properties": {
    "iso:country":"GB",
    "wof:name":"DD8 1ST",
    "wof:placetype":"postalcode"
},
  "geometry": {"coordinates":[-3.0924445061172,56.58967876310074],"type":"Point"}
}