{
  "type": "Feature",
  "properties": {
    "date:inception_lower": "2014-06-01",
    "date:inception_upper": "2014-06-01",
    "iso:country": "GB",
    "wof:name": "B17 8LW",
    "wof:placetype": "postalcode"
  },
  "geometry": {"coordinates":[-1.957119,52.478513],"type":"Point"}
}
