{
  "type": "Feature",
  "properties": {
    "iso:country": "GB",
    "wof:name": "B17 8LW",
    "wof:placetype": "postalcode"
  },
  "geometry": {"coordinates":[-1.957105,52.478513],"type":"Point"}
}
