{
  "type": "Feature",
  "properties": {
    "iso:country":"GB",
    "wof:name":"SN4 0BL",
    "wof:placetype":"postalcode"
},
  "geometry": {"coordinates":[-1.70057840131525,51.54815625763488],"type":"Point"}
}