{
  "type": "Feature",
  "properties": {
    "iso:country":"GB",
    "wof:name":"RM15 5JA",
    "wof:placetype":"postalcode"
},
  "geometry": {"coordinates":[0.28065926606847,51.50828735076261],"type":"Point"}
}