{
  "type": "Feature",
  "properties": {
    "iso:country":"GB",
    "wof:name":"TD5 7HA",
    "wof:placetype":"postalcode"
},
  "geometry": {"coordinates":[-2.43327652996448,55.59906068585416],"type":"Point"}
}