{
  "type": "Feature",
  "properties": {
    "iso:country": "GB",
    "wof:name": "TD5 7HA",
    "wof:placetype": "postalcode"
  },
  "geometry": {"coordinates":[-2.433276,55.599061],"type":"Point"}
}
