{
  "type": "Feature",
  "properties": {
    "iso:country":"GB",
    "wof:name":"M24 2FE",
    "wof:placetype":"postalcode"
},
  "geometry": {"coordinates":[-2.17026918646999,53.54607914096206],"type":"Point"}
}