{
  "type": "Feature",
  "properties": {
    "iso:country":"GB",
    "wof:name":"PE11 1QZ",
    "wof:placetype":"postalcode"
},
  "geometry": {"coordinates":[-0.15693819256261,52.79173664887446],"type":"Point"}
}