{
  "type": "Feature",
  "properties": {
    "iso:country":"GB",
    "wof:name":"CB24 5HS",
    "wof:placetype":"postalcode"
},
  "geometry": {"coordinates":[0.06133303421235,52.31458807372405],"type":"Point"}
}