{
  "type": "Feature",
  "properties": {
    "iso:country": "GB",
    "wof:name": "NE8 2GS",
    "wof:placetype": "postalcode"
  },
  "geometry": {"coordinates":[-1.636128,54.95692],"type":"Point"}
}
