{
  "type": "Feature",
  "properties": {
    "date:inception_lower":"2013-09-01",
    "date:inception_upper":"2013-09-30",
    "iso:country":"GB",
    "wof:name":"NE8 2GS",
    "wof:placetype":"postalcode"
},
  "geometry": {"coordinates":[-1.636128,54.95692],"type":"Point"}
}