{
  "type": "Feature",
  "properties": {
    "date:inception_lower": "2019-11-01",
    "date:inception_upper": "2019-11-01",
    "iso:country": "GB",
    "wof:name": "CH48 2AA",
    "wof:placetype": "postalcode"
  },
  "geometry": {"coordinates":[-3.174491,53.365333],"type":"Point"}
}
