{
  "type": "Feature",
  "properties": {
    "iso:country":"GB",
    "wof:name":"YO8 8FU",
    "wof:placetype":"postalcode"
},
  "geometry": {"coordinates":[-1.05783672840306,53.77329003348475],"type":"Point"}
}