{
  "type": "Feature",
  "properties": {
    "date:inception_lower":"1980-01-01",
    "date:inception_upper":"1980-01-31",
    "iso:country":"GB",
    "wof:name":"RG2 8SJ",
    "wof:placetype":"postalcode"
},
  "geometry": {"coordinates":[-0.967084,51.422433],"type":"Point"}
}