{
  "type": "Feature",
  "properties": {
    "iso:country": "GB",
    "wof:name": "WA6 6XQ",
    "wof:placetype": "postalcode"
  },
  "geometry": {"coordinates":[-2.735255,53.267013],"type":"Point"}
}
