{
  "type": "Feature",
  "properties": {
    "iso:country":"GB",
    "wof:name":"SW11 3AT",
    "wof:placetype":"postalcode"
},
  "geometry": {"coordinates":[-0.16835334646072,51.47704233674644],"type":"Point"}
}