{
  "type": "Feature",
  "properties": {
    "iso:country": "GB",
    "wof:name": "HX1 4DS",
    "wof:placetype": "postalcode"
  },
  "geometry": {"coordinates":[-1.880188,53.719991],"type":"Point"}
}
