{
  "type": "Feature",
  "properties": {
    "date:inception_lower":"1998-06-01",
    "date:inception_upper":"1998-06-30",
    "iso:country":"GB",
    "wof:name":"CF44 9UL",
    "wof:placetype":"postalcode"
},
  "geometry": {"coordinates":[-3.548806,51.744093],"type":"Point"}
}