{
  "type": "Feature",
  "properties": {
    "iso:country":"GB",
    "wof:name":"WA10 4NW",
    "wof:placetype":"postalcode"
},
  "geometry": {"coordinates":[-2.75952338692119,53.45083578309665],"type":"Point"}
}