{
  "type": "Feature",
  "properties": {
    "date:inception_lower": "1980-01-01",
    "date:inception_upper": "1980-01-01",
    "iso:country": "GB",
    "wof:name": "CV37 9BA",
    "wof:placetype": "postalcode"
  },
  "geometry": {"coordinates":[-1.723975,52.186218],"type":"Point"}
}
