{
  "type": "Feature",
  "properties": {
    "date:inception_lower": "1980-01-01",
    "date:inception_upper": "1980-01-01",
    "iso:country": "GB",
    "wof:name": "G64 2EX",
    "wof:placetype": "postalcode"
  },
  "geometry": {"coordinates":[-4.230482,55.906391],"type":"Point"}
}
