{
  "type": "Feature",
  "properties": {
    "iso:country":"GB",
    "wof:name":"G64 2EX",
    "wof:placetype":"postalcode"
},
  "geometry": {"coordinates":[-4.2304824711774,55.90639116919814],"type":"Point"}
}