{
  "type": "Feature",
  "properties": {
    "iso:country": "GB",
    "wof:name": "G64 2EX",
    "wof:placetype": "postalcode"
  },
  "geometry": {"coordinates":[-4.230482,55.906391],"type":"Point"}
}
