{
  "type": "Feature",
  "properties": {
    "iso:country": "GB",
    "wof:name": "PR4 0EW",
    "wof:placetype": "postalcode"
  },
  "geometry": {"coordinates":[-2.729526,53.796248],"type":"Point"}
}
