{
  "type": "Feature",
  "properties": {
    "date:inception_lower": "2017-04-01",
    "date:inception_upper": "2017-04-01",
    "iso:country": "GB",
    "wof:name": "PR4 0EW",
    "wof:placetype": "postalcode"
  },
  "geometry": {"coordinates":[-2.729938,53.796335],"type":"Point"}
}
