{
  "type": "Feature",
  "properties": {
    "iso:country":"GB",
    "wof:name":"SS15 5JQ",
    "wof:placetype":"postalcode"
},
  "geometry": {"coordinates":[0.44455619724497,51.57652617547708],"type":"Point"}
}