{
  "type": "Feature",
  "properties": {
    "iso:country": "GB",
    "wof:name": "SS15 5JQ",
    "wof:placetype": "postalcode"
  },
  "geometry": {"coordinates":[0.444556,51.576526],"type":"Point"}
}
