{
  "type": "Feature",
  "properties": {
    "iso:country":"GB",
    "wof:name":"HP9 2NN",
    "wof:placetype":"postalcode"
},
  "geometry": {"coordinates":[-0.64630520276045,51.61715392022905],"type":"Point"}
}