{
  "type": "Feature",
  "properties": {
    "date:inception_lower": "2020-01-01",
    "date:inception_upper": "2020-01-01",
    "iso:country": "GB",
    "wof:name": "TA5 2SS",
    "wof:placetype": "postalcode"
  },
  "geometry": {"coordinates":[-3.01899,51.113368],"type":"Point"}
}
