{
  "type": "Feature",
  "properties": {
    "iso:country": "GB",
    "wof:name": "TA5 2SS",
    "wof:placetype": "postalcode"
  },
  "geometry": {"coordinates":[-3.019074,51.113332],"type":"Point"}
}
