{
  "type": "Feature",
  "properties": {
    "iso:country":"GB",
    "wof:name":"CV34 4PP",
    "wof:placetype":"postalcode"
},
  "geometry": {"coordinates":[-1.57365623520562,52.28535797980766],"type":"Point"}
}