{
  "type": "Feature",
  "properties": {
    "date:inception_lower": "2007-07-01",
    "date:inception_upper": "2007-07-01",
    "iso:country": "GB",
    "wof:name": "CT9 5SY",
    "wof:placetype": "postalcode"
  },
  "geometry": {"coordinates":[1.382989,51.379623],"type":"Point"}
}
