{
  "type": "Feature",
  "properties": {
    "iso:country":"GB",
    "wof:name":"CT9 5SY",
    "wof:placetype":"postalcode"
},
  "geometry": {"coordinates":[1.38298918978305,51.37962316404944],"type":"Point"}
}