{
  "type": "Feature",
  "properties": {
    "iso:country": "GB",
    "wof:name": "HR4 0PE",
    "wof:placetype": "postalcode"
  },
  "geometry": {"coordinates":[-2.740255,52.067248],"type":"Point"}
}
