{
  "type": "Feature",
  "properties": {
    "date:inception_lower": "1980-01-01",
    "date:inception_upper": "1980-01-01",
    "iso:country": "GB",
    "wof:name": "CA10 3AX",
    "wof:placetype": "postalcode"
  },
  "geometry": {"coordinates":[-2.62516,54.596073],"type":"Point"}
}
