{
  "type": "Feature",
  "properties": {
    "iso:country": "GB",
    "wof:name": "CA10 3AX",
    "wof:placetype": "postalcode"
  },
  "geometry": {"coordinates":[-2.624999,54.596048],"type":"Point"}
}
