{
  "type": "Feature",
  "properties": {
    "iso:country": "GB",
    "wof:name": "BL3 1LD",
    "wof:placetype": "postalcode"
  },
  "geometry": {"coordinates":[-2.36153,53.559163],"type":"Point"}
}
