{
  "type": "Feature",
  "properties": {
    "iso:country": "GB",
    "wof:name": "B5 7UA",
    "wof:placetype": "postalcode"
  },
  "geometry": {"coordinates":[-1.907635,52.459151],"type":"Point"}
}
