{
  "type": "Feature",
  "properties": {
    "iso:country":"GB",
    "wof:name":"DA2 6QH",
    "wof:placetype":"postalcode"
},
  "geometry": {"coordinates":[0.25074877171337,51.45403469050574],"type":"Point"}
}