{
  "type": "Feature",
  "properties": {
    "date:inception_lower": "1987-10-01",
    "date:inception_upper": "1987-10-01",
    "iso:country": "GB",
    "wof:name": "SK3 0BR",
    "wof:placetype": "postalcode"
  },
  "geometry": {"coordinates":[-2.170606,53.408519],"type":"Point"}
}
