{
  "type": "Feature",
  "properties": {
    "iso:country":"GB",
    "wof:name":"NE66 4RN",
    "wof:placetype":"postalcode"
},
  "geometry": {"coordinates":[-1.87109111324651,55.40167588617303],"type":"Point"}
}