{
  "type": "Feature",
  "properties": {
    "iso:country": "GB",
    "wof:name": "NE66 4RN",
    "wof:placetype": "postalcode"
  },
  "geometry": {"coordinates":[-1.871091,55.401676],"type":"Point"}
}
