{
  "type": "Feature",
  "properties": {
    "iso:country": "GB",
    "wof:name": "TW12 3JX",
    "wof:placetype": "postalcode"
  },
  "geometry": {"coordinates":[-0.380494,51.43085],"type":"Point"}
}
