{
  "type": "Feature",
  "properties": {
    "date:inception_lower": "1980-01-01",
    "date:inception_upper": "1980-01-01",
    "iso:country": "GB",
    "wof:name": "DY9 7HF",
    "wof:placetype": "postalcode"
  },
  "geometry": {"coordinates":[-2.122285,52.450723],"type":"Point"}
}
