{
  "type": "Feature",
  "properties": {
    "iso:country":"GB",
    "wof:name":"DY9 7HF",
    "wof:placetype":"postalcode"
},
  "geometry": {"coordinates":[-2.12232044823322,52.45070826404158],"type":"Point"}
}