{
  "type": "Feature",
  "properties": {
    "iso:country":"GB",
    "wof:name":"LS13 2SU",
    "wof:placetype":"postalcode"
},
  "geometry": {"coordinates":[-1.62056034238011,53.8192090912415],"type":"Point"}
}