{
  "type": "Feature",
  "properties": {
    "iso:country":"GB",
    "wof:name":"KY1 3JJ",
    "wof:placetype":"postalcode"
},
  "geometry": {"coordinates":[-3.1468539803551,56.13177043850924],"type":"Point"}
}