{
  "type": "Feature",
  "properties": {
    "date:inception_lower": "1980-01-01",
    "date:inception_upper": "1980-01-01",
    "iso:country": "GB",
    "wof:name": "NE65 8HZ",
    "wof:placetype": "postalcode"
  },
  "geometry": {"coordinates":[-1.834912,55.288485],"type":"Point"}
}
