{
  "type": "Feature",
  "properties": {
    "iso:country":"GB",
    "wof:name":"NE65 8HZ",
    "wof:placetype":"postalcode"
},
  "geometry": {"coordinates":[-1.83491234822183,55.28848511154231],"type":"Point"}
}