{
  "type": "Feature",
  "properties": {
    "iso:country":"GB",
    "wof:name":"HX1 2NQ",
    "wof:placetype":"postalcode"
},
  "geometry": {"coordinates":[-1.86606894261401,53.7138820844247],"type":"Point"}
}