{
  "type": "Feature",
  "properties": {
    "iso:country": "GB",
    "wof:name": "TA21 9JT",
    "wof:placetype": "postalcode"
  },
  "geometry": {"coordinates":[-3.17594,50.978019],"type":"Point"}
}
