{
  "type": "Feature",
  "properties": {
    "iso:country":"GB",
    "wof:name":"TA21 9JT",
    "wof:placetype":"postalcode"
},
  "geometry": {"coordinates":[-3.1759397338665,50.97801934905871],"type":"Point"}
}