{
  "type": "Feature",
  "properties": {
    "date:inception_lower": "2005-04-01",
    "date:inception_upper": "2005-04-01",
    "iso:country": "GB",
    "wof:name": "SW16 4LH",
    "wof:placetype": "postalcode"
  },
  "geometry": {"coordinates":[-0.119723,51.409476],"type":"Point"}
}
