{
  "type": "Feature",
  "properties": {
    "iso:country": "GB",
    "wof:name": "SW16 4LH",
    "wof:placetype": "postalcode"
  },
  "geometry": {"coordinates":[-0.119993,51.40948],"type":"Point"}
}
