{
  "type": "Feature",
  "properties": {
    "iso:country":"GB",
    "wof:name":"SW16 4LH",
    "wof:placetype":"postalcode"
},
  "geometry": {"coordinates":[-0.11999350206085,51.40947968848378],"type":"Point"}
}