{
  "type": "Feature",
  "properties": {
    "iso:country":"GB",
    "wof:name":"W3 6HF",
    "wof:placetype":"postalcode"
},
  "geometry": {"coordinates":[-0.26756194152831,51.51342255300784],"type":"Point"}
}