{
  "type": "Feature",
  "properties": {
    "iso:country":"GB",
    "wof:name":"TF10 7TE",
    "wof:placetype":"postalcode"
},
  "geometry": {"coordinates":[-2.36734714951872,52.77378854997902],"type":"Point"}
}