{
  "type": "Feature",
  "properties": {
    "iso:country":"GB",
    "wof:name":"B78 1PZ",
    "wof:placetype":"postalcode"
},
  "geometry": {"coordinates":[-1.61461759936225,52.60393570617243],"type":"Point"}
}