{
  "type": "Feature",
  "properties": {
    "iso:country":"GB",
    "wof:name":"NG2 5GY",
    "wof:placetype":"postalcode"
},
  "geometry": {"coordinates":[-1.12461553599382,52.9363967187121],"type":"Point"}
}