{
  "type": "Feature",
  "properties": {
    "date:inception_lower":"1980-01-01",
    "date:inception_upper":"1980-01-31",
    "iso:country":"GB",
    "wof:name":"EC1R 0BB",
    "wof:placetype":"postalcode"
},
  "geometry": {"coordinates":[-0.107555,51.524387],"type":"Point"}
}