{
  "type": "Feature",
  "properties": {
    "iso:country":"GB",
    "wof:name":"LD2 3YT",
    "wof:placetype":"postalcode"
},
  "geometry": {"coordinates":[-3.33052776243459,52.08361280533262],"type":"Point"}
}