{
  "type": "Feature",
  "properties": {
    "iso:country":"GB",
    "wof:name":"G31 4AN",
    "wof:placetype":"postalcode"
},
  "geometry": {"coordinates":[-4.21406557138824,55.85161313370941],"type":"Point"}
}