{
  "type": "Feature",
  "properties": {
    "date:inception_lower": "2021-12-01",
    "date:inception_upper": "2021-12-01",
    "iso:country": "GB",
    "wof:name": "ST15 0WS",
    "wof:placetype": "postalcode"
  },
  "geometry": {"coordinates":[-2.160704,52.896323],"type":"Point"}
}
