{
  "type": "Feature",
  "properties": {
    "iso:country":"GB",
    "wof:name":"TR7 1EB",
    "wof:placetype":"postalcode"
},
  "geometry": {"coordinates":[-5.07937509558841,50.41472504183574],"type":"Point"}
}