{
  "type": "Feature",
  "properties": {
    "iso:country":"GB",
    "wof:name":"M25 2QW",
    "wof:placetype":"postalcode"
},
  "geometry": {"coordinates":[-2.27250962073135,53.54066742064423],"type":"Point"}
}