{
  "type": "Feature",
  "properties": {
    "iso:country":"GB",
    "wof:name":"RG14 7BY",
    "wof:placetype":"postalcode"
},
  "geometry": {"coordinates":[-1.3235824211309,51.39064731660817],"type":"Point"}
}