{
  "type": "Feature",
  "properties": {
    "iso:country":"GB",
    "wof:name":"PL32 9QG",
    "wof:placetype":"postalcode"
},
  "geometry": {"coordinates":[-4.64265043189136,50.61157604595234],"type":"Point"}
}