{
  "type": "Feature",
  "properties": {
    "iso:country":"GB",
    "wof:name":"RG21 5SX",
    "wof:placetype":"postalcode"
},
  "geometry": {"coordinates":[-1.09040311082553,51.27488089801842],"type":"Point"}
}