{
  "type": "Feature",
  "properties": {
    "iso:country":"GB",
    "wof:name":"HR4 7EZ",
    "wof:placetype":"postalcode"
},
  "geometry": {"coordinates":[-2.81408936434784,52.08025626893745],"type":"Point"}
}