{
  "type": "Feature",
  "properties": {
    "date:inception_lower":"1980-01-01",
    "date:inception_upper":"1980-01-31",
    "iso:country":"GB",
    "wof:name":"LN1 2HS",
    "wof:placetype":"postalcode"
},
  "geometry": {"coordinates":[-0.658059,53.271442],"type":"Point"}
}