{
  "type": "Feature",
  "properties": {
    "iso:country":"GB",
    "wof:name":"LN1 2HS",
    "wof:placetype":"postalcode"
},
  "geometry": {"coordinates":[-0.65805907143663,53.27144166147502],"type":"Point"}
}