{
  "type": "Feature",
  "properties": {
    "iso:country":"GB",
    "wof:name":"SW12 8QQ",
    "wof:placetype":"postalcode"
},
  "geometry": {"coordinates":[-0.1536249060979,51.44878152351029],"type":"Point"}
}