{
  "type": "Feature",
  "properties": {
    "date:inception_lower": "1980-01-01",
    "date:inception_upper": "1980-01-01",
    "iso:country": "GB",
    "wof:name": "KT14 6RL",
    "wof:placetype": "postalcode"
  },
  "geometry": {"coordinates":[-0.502287,51.33296],"type":"Point"}
}
