{
  "type": "Feature",
  "properties": {
    "iso:country":"GB",
    "wof:name":"M28 2WQ",
    "wof:placetype":"postalcode"
},
  "geometry": {"coordinates":[-2.37143807207088,53.50113041811341],"type":"Point"}
}