{
  "type": "Feature",
  "properties": {
    "iso:country":"GB",
    "wof:name":"B94 6LB",
    "wof:placetype":"postalcode"
},
  "geometry": {"coordinates":[-1.72941694060704,52.33786171286691],"type":"Point"}
}