{
  "type": "Feature",
  "properties": {
    "iso:country": "GB",
    "wof:name": "B94 6LB",
    "wof:placetype": "postalcode"
  },
  "geometry": {"coordinates":[-1.72951,52.337868],"type":"Point"}
}
