{
  "type": "Feature",
  "properties": {
    "date:inception_lower": "1980-01-01",
    "date:inception_upper": "1980-01-01",
    "iso:country": "GB",
    "wof:name": "EX39 1RH",
    "wof:placetype": "postalcode"
  },
  "geometry": {"coordinates":[-4.191173,51.054194],"type":"Point"}
}
