{
  "type": "Feature",
  "properties": {
    "iso:country":"GB",
    "wof:name":"EX39 1RH",
    "wof:placetype":"postalcode"
},
  "geometry": {"coordinates":[-4.19114798119383,51.05419845276878],"type":"Point"}
}