{
  "type": "Feature",
  "properties": {
    "iso:country": "GB",
    "wof:name": "EX39 1RH",
    "wof:placetype": "postalcode"
  },
  "geometry": {"coordinates":[-4.191031,51.054215],"type":"Point"}
}
