{
  "type": "Feature",
  "properties": {
    "iso:country": "GB",
    "wof:name": "SK22 3EZ",
    "wof:placetype": "postalcode"
  },
  "geometry": {"coordinates":[-2.004979,53.361101],"type":"Point"}
}
