{
  "type": "Feature",
  "properties": {
    "iso:country":"GB",
    "wof:name":"PE11 4SS",
    "wof:placetype":"postalcode"
},
  "geometry": {"coordinates":[-0.15325869060761,52.88660290515725],"type":"Point"}
}