{
  "type": "Feature",
  "properties": {
    "date:inception_lower": "2002-07-01",
    "date:inception_upper": "2002-07-01",
    "iso:country": "GB",
    "wof:name": "PE11 4SS",
    "wof:placetype": "postalcode"
  },
  "geometry": {"coordinates":[-0.152914,52.887169],"type":"Point"}
}
