{
  "type": "Feature",
  "properties": {
    "iso:country": "GB",
    "wof:name": "TQ13 8RS",
    "wof:placetype": "postalcode"
  },
  "geometry": {"coordinates":[-3.8195,50.627654],"type":"Point"}
}
