{
  "type": "Feature",
  "properties": {
    "iso:country":"GB",
    "wof:name":"LE12 8XA",
    "wof:placetype":"postalcode"
},
  "geometry": {"coordinates":[-1.25362103845932,52.7160508183235],"type":"Point"}
}