{
  "type": "Feature",
  "properties": {
    "date:inception_lower": "2008-03-01",
    "date:inception_upper": "2008-03-01",
    "iso:country": "GB",
    "wof:name": "LE12 8XA",
    "wof:placetype": "postalcode"
  },
  "geometry": {"coordinates":[-1.253613,52.716069],"type":"Point"}
}
