{
  "type": "Feature",
  "properties": {
    "iso:country": "GB",
    "wof:name": "LE12 8XA",
    "wof:placetype": "postalcode"
  },
  "geometry": {"coordinates":[-1.254008,52.716351],"type":"Point"}
}
