{
  "type": "Feature",
  "properties": {
    "date:inception_lower": "1986-01-01",
    "date:inception_upper": "1986-01-01",
    "iso:country": "GB",
    "wof:name": "SO41 8NP",
    "wof:placetype": "postalcode"
  },
  "geometry": {"coordinates":[-1.556561,50.76719],"type":"Point"}
}
