{
  "type": "Feature",
  "properties": {
    "iso:country": "GB",
    "wof:name": "CV31 1XH",
    "wof:placetype": "postalcode"
  },
  "geometry": {"coordinates":[-1.475884,52.258614],"type":"Point"}
}
