{
  "type": "Feature",
  "properties": {
    "iso:country":"GB",
    "wof:name":"LE2 6AU",
    "wof:placetype":"postalcode"
},
  "geometry": {"coordinates":[-1.12636779670967,52.61515065098764],"type":"Point"}
}