{
  "type": "Feature",
  "properties": {
    "iso:country": "GB",
    "wof:name": "LE2 6AU",
    "wof:placetype": "postalcode"
  },
  "geometry": {"coordinates":[-1.126368,52.615151],"type":"Point"}
}
