{
  "type": "Feature",
  "properties": {
    "date:inception_lower":"1999-12-01",
    "date:inception_upper":"1999-12-31",
    "iso:country":"GB",
    "wof:name":"G12 0FE",
    "wof:placetype":"postalcode"
},
  "geometry": {"coordinates":[-4.318107,55.89103],"type":"Point"}
}