{
  "type": "Feature",
  "properties": {
    "iso:country": "GB",
    "wof:name": "G12 0FE",
    "wof:placetype": "postalcode"
  },
  "geometry": {"coordinates":[-4.318107,55.89103],"type":"Point"}
}
