{
  "type": "Feature",
  "properties": {
    "iso:country":"GB",
    "wof:name":"SW7 5AB",
    "wof:placetype":"postalcode"
},
  "geometry": {"coordinates":[-0.17914031864952,51.49328893648512],"type":"Point"}
}