{
  "type": "Feature",
  "properties": {
    "iso:country": "GB",
    "wof:name": "MK46 5EF",
    "wof:placetype": "postalcode"
  },
  "geometry": {"coordinates":[-0.705269,52.1617],"type":"Point"}
}
