{
  "type": "Feature",
  "properties": {
    "date:inception_lower": "2021-09-01",
    "date:inception_upper": "2021-09-01",
    "iso:country": "GB",
    "wof:name": "NE25 0GH",
    "wof:placetype": "postalcode"
  },
  "geometry": {"coordinates":[-1.514222,55.084429],"type":"Point"}
}
