{
  "type": "Feature",
  "properties": {
    "iso:country":"GB",
    "wof:name":"GU21 4TD",
    "wof:placetype":"postalcode"
},
  "geometry": {"coordinates":[-0.57338194476086,51.32615045893556],"type":"Point"}
}