{
  "type": "Feature",
  "properties": {
    "iso:country": "GB",
    "wof:name": "GU21 4TD",
    "wof:placetype": "postalcode"
  },
  "geometry": {"coordinates":[-0.573382,51.32615],"type":"Point"}
}
