{
  "type": "Feature",
  "properties": {
    "date:inception_lower": "2021-07-01",
    "date:inception_upper": "2021-07-01",
    "iso:country": "GB",
    "wof:name": "ME1 3YZ",
    "wof:placetype": "postalcode"
  },
  "geometry": {"coordinates":[0.463039,51.345163],"type":"Point"}
}
