{
  "type": "Feature",
  "properties": {
    "iso:country":"GB",
    "wof:name":"SR3 2BT",
    "wof:placetype":"postalcode"
},
  "geometry": {"coordinates":[-1.39201710387404,54.87345811212175],"type":"Point"}
}