{
  "type": "Feature",
  "properties": {
    "iso:country": "GB",
    "wof:name": "HP4 2DH",
    "wof:placetype": "postalcode"
  },
  "geometry": {"coordinates":[-0.561846,51.758356],"type":"Point"}
}
