{
  "type": "Feature",
  "properties": {
    "iso:country": "GB",
    "wof:name": "DT6 6LX",
    "wof:placetype": "postalcode"
  },
  "geometry": {"coordinates":[-2.895918,50.739722],"type":"Point"}
}
