{
  "type": "Feature",
  "properties": {
    "iso:country": "GB",
    "wof:name": "CH43 8SN",
    "wof:placetype": "postalcode"
  },
  "geometry": {"coordinates":[-3.050887,53.392321],"type":"Point"}
}
