{
  "type": "Feature",
  "properties": {
    "iso:country":"GB",
    "wof:name":"CH43 8SN",
    "wof:placetype":"postalcode"
},
  "geometry": {"coordinates":[-3.05088681383702,53.39232062805666],"type":"Point"}
}