{
  "type": "Feature",
  "properties": {
    "date:inception_lower": "1980-01-01",
    "date:inception_upper": "1980-01-01",
    "iso:country": "GB",
    "wof:name": "SA15 2ND",
    "wof:placetype": "postalcode"
  },
  "geometry": {"coordinates":[-4.162018,51.673384],"type":"Point"}
}
