{
  "type": "Feature",
  "properties": {
    "iso:country":"GB",
    "wof:name":"RG1 5BG",
    "wof:placetype":"postalcode"
},
  "geometry": {"coordinates":[-0.96264707987601,51.45134795004243],"type":"Point"}
}