{
  "type": "Feature",
  "properties": {
    "iso:country": "GB",
    "wof:name": "RG1 5BG",
    "wof:placetype": "postalcode"
  },
  "geometry": {"coordinates":[-0.962647,51.451348],"type":"Point"}
}
