{
  "type": "Feature",
  "properties": {
    "iso:country": "GB",
    "wof:name": "SA62 5SE",
    "wof:placetype": "postalcode"
  },
  "geometry": {"coordinates":[-4.992673,51.927782],"type":"Point"}
}
