{
  "type": "Feature",
  "properties": {
    "iso:country":"GB",
    "wof:name":"SA62 5SE",
    "wof:placetype":"postalcode"
},
  "geometry": {"coordinates":[-4.9923547798482,51.92780110699781],"type":"Point"}
}