{
  "type": "Feature",
  "properties": {
    "iso:country": "GB",
    "wof:name": "OX17 3JS",
    "wof:placetype": "postalcode"
  },
  "geometry": {"coordinates":[-1.309852,52.021747],"type":"Point"}
}
