{
  "type": "Feature",
  "properties": {
    "iso:country":"GB",
    "wof:name":"BL3 1QY",
    "wof:placetype":"postalcode"
},
  "geometry": {"coordinates":[-2.37249603632595,53.56499877269417],"type":"Point"}
}