{
  "type": "Feature",
  "properties": {
    "iso:country":"GB",
    "wof:name":"SM3 8PU",
    "wof:placetype":"postalcode"
},
  "geometry": {"coordinates":[-0.21533487592163,51.3609175723328],"type":"Point"}
}