{
  "type": "Feature",
  "properties": {
    "date:inception_lower": "1985-10-01",
    "date:inception_upper": "1985-10-01",
    "iso:country": "GB",
    "wof:name": "ST6 2HB",
    "wof:placetype": "postalcode"
  },
  "geometry": {"coordinates":[-2.190251,53.040514],"type":"Point"}
}
