{
  "type": "Feature",
  "properties": {
    "iso:country":"GB",
    "wof:name":"B94 6HW",
    "wof:placetype":"postalcode"
},
  "geometry": {"coordinates":[-1.74129385161736,52.34484669693171],"type":"Point"}
}