{
  "type": "Feature",
  "properties": {
    "iso:country":"GB",
    "wof:name":"GU26 6HW",
    "wof:placetype":"postalcode"
},
  "geometry": {"coordinates":[-0.75617286316192,51.10941412386128],"type":"Point"}
}