{
  "type": "Feature",
  "properties": {
    "iso:country": "GB",
    "wof:name": "PO19 6XF",
    "wof:placetype": "postalcode"
  },
  "geometry": {"coordinates":[-0.766171,50.841205],"type":"Point"}
}
