{
  "type": "Feature",
  "properties": {
    "iso:country":"GB",
    "wof:name":"PO19 6XF",
    "wof:placetype":"postalcode"
},
  "geometry": {"coordinates":[-0.76617137723177,50.84120471472681],"type":"Point"}
}