{
  "type": "Feature",
  "properties": {
    "date:inception_lower": "1980-01-01",
    "date:inception_upper": "1980-01-01",
    "iso:country": "GB",
    "wof:name": "WS2 7LU",
    "wof:placetype": "postalcode"
  },
  "geometry": {"coordinates":[-2.024209,52.599954],"type":"Point"}
}
