{
  "type": "Feature",
  "properties": {
    "iso:country": "GB",
    "wof:name": "EX10 9DN",
    "wof:placetype": "postalcode"
  },
  "geometry": {"coordinates":[-3.245441,50.690038],"type":"Point"}
}
