{
  "type": "Feature",
  "properties": {
    "iso:country":"GB",
    "wof:name":"LA12 8QR",
    "wof:placetype":"postalcode"
},
  "geometry": {"coordinates":[-2.98715559206753,54.25155512568613],"type":"Point"}
}