{
  "type": "Feature",
  "properties": {
    "iso:country": "GB",
    "wof:name": "HR8 1HH",
    "wof:placetype": "postalcode"
  },
  "geometry": {"coordinates":[-2.502633,52.104024],"type":"Point"}
}
