{
  "type": "Feature",
  "properties": {
    "iso:country":"GB",
    "wof:name":"HR8 1HH",
    "wof:placetype":"postalcode"
},
  "geometry": {"coordinates":[-2.50263266556419,52.10402353177883],"type":"Point"}
}