{
  "type": "Feature",
  "properties": {
    "iso:country":"GB",
    "wof:name":"S36 1JB",
    "wof:placetype":"postalcode"
},
  "geometry": {"coordinates":[-1.60473876692152,53.48350120866895],"type":"Point"}
}