{
  "type": "Feature",
  "properties": {
    "iso:country": "GB",
    "wof:name": "LE11 2RX",
    "wof:placetype": "postalcode"
  },
  "geometry": {"coordinates":[-1.221017,52.75047],"type":"Point"}
}
