{
  "type": "Feature",
  "properties": {
    "iso:country":"GB",
    "wof:name":"SM5 2PB",
    "wof:placetype":"postalcode"
},
  "geometry": {"coordinates":[-0.17085731639491,51.36360379233133],"type":"Point"}
}