{
  "type": "Feature",
  "properties": {
    "date:inception_lower": "1980-01-01",
    "date:inception_upper": "1980-01-01",
    "iso:country": "GB",
    "wof:name": "NR18 9HS",
    "wof:placetype": "postalcode"
  },
  "geometry": {"coordinates":[1.039897,52.580274],"type":"Point"}
}
