{
  "type": "Feature",
  "properties": {
    "iso:country":"GB",
    "wof:name":"NR18 9HS",
    "wof:placetype":"postalcode"
},
  "geometry": {"coordinates":[1.04045330029021,52.58008284736553],"type":"Point"}
}