{
  "type": "Feature",
  "properties": {
    "iso:country":"GB",
    "wof:name":"NR2 4QU",
    "wof:placetype":"postalcode"
},
  "geometry": {"coordinates":[1.28173005616947,52.63651100314934],"type":"Point"}
}