{
  "type": "Feature",
  "properties": {
    "iso:country":"GB",
    "wof:name":"IV20 1WP",
    "wof:placetype":"postalcode"
},
  "geometry": {"coordinates":[-3.90165939260671,57.77338727483458],"type":"Point"}
}