{
  "type": "Feature",
  "properties": {
    "iso:country":"GB",
    "wof:name":"HR4 9QL",
    "wof:placetype":"postalcode"
},
  "geometry": {"coordinates":[-2.73207029547274,52.06632823390941],"type":"Point"}
}