{
  "type": "Feature",
  "properties": {
    "iso:country":"GB",
    "wof:name":"EH2 1EL",
    "wof:placetype":"postalcode"
},
  "geometry": {"coordinates":[-3.19790447344384,55.95406778858475],"type":"Point"}
}