{
  "type": "Feature",
  "properties": {
    "date:inception_lower": "1980-01-01",
    "date:inception_upper": "1980-01-01",
    "iso:country": "GB",
    "wof:name": "S72 7EF",
    "wof:placetype": "postalcode"
  },
  "geometry": {"coordinates":[-1.377403,53.57703],"type":"Point"}
}
