{
  "type": "Feature",
  "properties": {
    "iso:country": "GB",
    "wof:name": "CV37 9TZ",
    "wof:placetype": "postalcode"
  },
  "geometry": {"coordinates":[-1.803121,52.192778],"type":"Point"}
}
