{
  "type": "Feature",
  "properties": {
    "date:inception_lower": "2004-01-01",
    "date:inception_upper": "2004-01-01",
    "iso:country": "GB",
    "wof:name": "IG2 7NX",
    "wof:placetype": "postalcode"
  },
  "geometry": {"coordinates":[0.085911,51.575222],"type":"Point"}
}
