{
  "type": "Feature",
  "properties": {
    "iso:country":"GB",
    "wof:name":"HR2 8QD",
    "wof:placetype":"postalcode"
},
  "geometry": {"coordinates":[-2.75948852545547,51.91273395988152],"type":"Point"}
}