{
  "type": "Feature",
  "properties": {
    "date:inception_lower": "1983-07-01",
    "date:inception_upper": "1983-07-01",
    "iso:country": "GB",
    "wof:name": "ST17 9SL",
    "wof:placetype": "postalcode"
  },
  "geometry": {"coordinates":[-2.140081,52.792452],"type":"Point"}
}
