{
  "type": "Feature",
  "properties": {
    "iso:country": "GB",
    "wof:name": "AB25 3YA",
    "wof:placetype": "postalcode"
  },
  "geometry": {"coordinates":[-2.107741,57.155265],"type":"Point"}
}
