{
  "type": "Feature",
  "properties": {
    "date:inception_lower": "2005-08-01",
    "date:inception_upper": "2005-08-01",
    "iso:country": "GB",
    "wof:name": "AB25 3YA",
    "wof:placetype": "postalcode"
  },
  "geometry": {"coordinates":[-2.107741,57.155265],"type":"Point"}
}
