{
  "type": "Feature",
  "properties": {
    "iso:country":"GB",
    "wof:name":"BS27 3PD",
    "wof:placetype":"postalcode"
},
  "geometry": {"coordinates":[-2.76911895497736,51.27740383255863],"type":"Point"}
}