{
  "type": "Feature",
  "properties": {
    "date:inception_lower": "1990-07-01",
    "date:inception_upper": "1990-07-01",
    "iso:country": "GB",
    "wof:name": "BS27 3PD",
    "wof:placetype": "postalcode"
  },
  "geometry": {"coordinates":[-2.769095,51.277391],"type":"Point"}
}
