{
  "type": "Feature",
  "properties": {
    "iso:country":"GB",
    "wof:name":"NE33 4HZ",
    "wof:placetype":"postalcode"
},
  "geometry": {"coordinates":[-1.43143269468935,54.98601495684701],"type":"Point"}
}