{
  "type": "Feature",
  "properties": {
    "iso:country":"GB",
    "wof:name":"CV7 9HQ",
    "wof:placetype":"postalcode"
},
  "geometry": {"coordinates":[-1.50366640748381,52.4562313703926],"type":"Point"}
}