{
  "type": "Feature",
  "properties": {
    "date:inception_lower": "1980-01-01",
    "date:inception_upper": "1980-01-01",
    "iso:country": "GB",
    "wof:name": "CV7 9HQ",
    "wof:placetype": "postalcode"
  },
  "geometry": {"coordinates":[-1.503666,52.456231],"type":"Point"}
}
