{
  "type": "Feature",
  "properties": {
    "iso:country":"GB",
    "wof:name":"YO7 2DA",
    "wof:placetype":"postalcode"
},
  "geometry": {"coordinates":[-1.2386673990744,54.18434280138844],"type":"Point"}
}