{
  "type": "Feature",
  "properties": {
    "iso:country":"GB",
    "wof:name":"SO19 7GR",
    "wof:placetype":"postalcode"
},
  "geometry": {"coordinates":[-1.37733151862859,50.90079344244565],"type":"Point"}
}