{
  "type": "Feature",
  "properties": {
    "iso:country": "GB",
    "wof:name": "SO19 7GR",
    "wof:placetype": "postalcode"
  },
  "geometry": {"coordinates":[-1.377331,50.900793],"type":"Point"}
}
