{
  "type": "Feature",
  "properties": {
    "date:inception_lower": "2005-05-01",
    "date:inception_upper": "2005-05-01",
    "iso:country": "GB",
    "wof:name": "NG12 2AL",
    "wof:placetype": "postalcode"
  },
  "geometry": {"coordinates":[-1.027246,52.949034],"type":"Point"}
}
