{
  "type": "Feature",
  "properties": {
    "iso:country":"GB",
    "wof:name":"NG12 2AL",
    "wof:placetype":"postalcode"
},
  "geometry": {"coordinates":[-1.02724633197982,52.94903428337037],"type":"Point"}
}