{
  "type": "Feature",
  "properties": {
    "date:inception_lower": "1980-01-01",
    "date:inception_upper": "1980-01-01",
    "iso:country": "GB",
    "wof:name": "SY21 7HL",
    "wof:placetype": "postalcode"
  },
  "geometry": {"coordinates":[-3.136177,52.663848],"type":"Point"}
}
