{
  "type": "Feature",
  "properties": {
    "iso:country": "GB",
    "wof:name": "HD4 5TY",
    "wof:placetype": "postalcode"
  },
  "geometry": {"coordinates":[-1.832359,53.637063],"type":"Point"}
}
