{
  "type": "Feature",
  "properties": {
    "iso:country":"GB",
    "wof:name":"IP14 6RA",
    "wof:placetype":"postalcode"
},
  "geometry": {"coordinates":[1.18070722537133,52.22446644111277],"type":"Point"}
}