{
  "type": "Feature",
  "properties": {
    "iso:country":"GB",
    "wof:name":"NG24 2LW",
    "wof:placetype":"postalcode"
},
  "geometry": {"coordinates":[-0.77998108341339,53.07866861959652],"type":"Point"}
}