{
  "type": "Feature",
  "properties": {
    "date:inception_lower": "2002-06-01",
    "date:inception_upper": "2002-06-01",
    "iso:country": "GB",
    "wof:name": "NG24 2LW",
    "wof:placetype": "postalcode"
  },
  "geometry": {"coordinates":[-0.779981,53.078669],"type":"Point"}
}
