{
  "type": "Feature",
  "properties": {
    "date:inception_lower": "1980-01-01",
    "date:inception_upper": "1980-01-01",
    "iso:country": "GB",
    "wof:name": "TD8 6LX",
    "wof:placetype": "postalcode"
  },
  "geometry": {"coordinates":[-2.484587,55.480871],"type":"Point"}
}
