{
  "type": "Feature",
  "properties": {
    "iso:country": "GB",
    "wof:name": "TD8 6LX",
    "wof:placetype": "postalcode"
  },
  "geometry": {"coordinates":[-2.484587,55.480871],"type":"Point"}
}
