{
  "type": "Feature",
  "properties": {
    "date:inception_lower": "1999-06-01",
    "date:inception_upper": "1999-06-01",
    "iso:country": "GB",
    "wof:name": "LS27 8HW",
    "wof:placetype": "postalcode"
  },
  "geometry": {"coordinates":[-1.591302,53.747613],"type":"Point"}
}
