{
  "type": "Feature",
  "properties": {
    "iso:country":"GB",
    "wof:name":"SP4 7GN",
    "wof:placetype":"postalcode"
},
  "geometry": {"coordinates":[-1.76497055564852,51.16028368812137],"type":"Point"}
}