{
  "type": "Feature",
  "properties": {
    "date:inception_lower":"2016-04-01",
    "date:inception_upper":"2016-04-30",
    "iso:country":"GB",
    "wof:name":"SP4 7GN",
    "wof:placetype":"postalcode"
},
  "geometry": {"coordinates":[-1.764976,51.159685],"type":"Point"}
}