{
  "type": "Feature",
  "properties": {
    "date:inception_lower":"1981-06-01",
    "date:inception_upper":"1981-06-30",
    "iso:country":"GB",
    "wof:name":"CW5 7JB",
    "wof:placetype":"postalcode"
},
  "geometry": {"coordinates":[-2.478513,53.06436],"type":"Point"}
}