{
  "type": "Feature",
  "properties": {
    "iso:country": "GB",
    "wof:name": "CW5 7JB",
    "wof:placetype": "postalcode"
  },
  "geometry": {"coordinates":[-2.478513,53.06436],"type":"Point"}
}
