{
  "type": "Feature",
  "properties": {
    "iso:country":"GB",
    "wof:name":"WD3 6BH",
    "wof:placetype":"postalcode"
},
  "geometry": {"coordinates":[-0.49567658808089,51.68583541100673],"type":"Point"}
}