{
  "type": "Feature",
  "properties": {
    "iso:country":"GB",
    "wof:name":"BB1 5JT",
    "wof:placetype":"postalcode"
},
  "geometry": {"coordinates":[-2.46549243538666,53.75494514577984],"type":"Point"}
}