{
  "type": "Feature",
  "properties": {
    "date:inception_lower": "1980-01-01",
    "date:inception_upper": "1980-01-01",
    "iso:country": "GB",
    "wof:name": "BB1 5JT",
    "wof:placetype": "postalcode"
  },
  "geometry": {"coordinates":[-2.463429,53.754995],"type":"Point"}
}
