{
  "type": "Feature",
  "properties": {
    "iso:country": "GB",
    "wof:name": "BB1 5JT",
    "wof:placetype": "postalcode"
  },
  "geometry": {"coordinates":[-2.465492,53.754945],"type":"Point"}
}
