{
  "type": "Feature",
  "properties": {
    "iso:country":"GB",
    "wof:name":"ML3 7RP",
    "wof:placetype":"postalcode"
},
  "geometry": {"coordinates":[-4.04486958795391,55.75534301036999],"type":"Point"}
}