{
  "type": "Feature",
  "properties": {
    "iso:country": "GB",
    "wof:name": "ML3 7RP",
    "wof:placetype": "postalcode"
  },
  "geometry": {"coordinates":[-4.04487,55.755343],"type":"Point"}
}
