{
  "type": "Feature",
  "properties": {
    "iso:country": "GB",
    "wof:name": "M43 7PW",
    "wof:placetype": "postalcode"
  },
  "geometry": {"coordinates":[-2.149959,53.491412],"type":"Point"}
}
