{
  "type": "Feature",
  "properties": {
    "date:inception_lower": "2021-02-01",
    "date:inception_upper": "2021-02-01",
    "iso:country": "GB",
    "wof:name": "LE7 7ZH",
    "wof:placetype": "postalcode"
  },
  "geometry": {"coordinates":[-1.134434,52.71428],"type":"Point"}
}
