{
  "type": "Feature",
  "properties": {
    "iso:country":"GB",
    "wof:name":"LE2 5PG",
    "wof:placetype":"postalcode"
},
  "geometry": {"coordinates":[-1.08326130275859,52.59289821697968],"type":"Point"}
}