{
  "type": "Feature",
  "properties": {
    "iso:country":"GB",
    "wof:name":"CH41 9AN",
    "wof:placetype":"postalcode"
},
  "geometry": {"coordinates":[-3.01646346421023,53.38340502755899],"type":"Point"}
}