{
  "type": "Feature",
  "properties": {
    "iso:country":"GB",
    "wof:name":"SP2 9JT",
    "wof:placetype":"postalcode"
},
  "geometry": {"coordinates":[-1.82399022552867,51.08415258637869],"type":"Point"}
}