{
  "type": "Feature",
  "properties": {
    "date:inception_lower":"1980-01-01",
    "date:inception_upper":"1980-01-31",
    "iso:country":"GB",
    "wof:name":"SP2 9JT",
    "wof:placetype":"postalcode"
},
  "geometry": {"coordinates":[-1.82399,51.084153],"type":"Point"}
}