{
  "type": "Feature",
  "properties": {
    "iso:country":"GB",
    "wof:name":"EX38 7DP",
    "wof:placetype":"postalcode"
},
  "geometry": {"coordinates":[-4.12897350661804,50.95829008877979],"type":"Point"}
}