{
  "type": "Feature",
  "properties": {
    "iso:country":"GB",
    "wof:name":"NN3 2NB",
    "wof:placetype":"postalcode"
},
  "geometry": {"coordinates":[-0.86467534964644,52.25498518965816],"type":"Point"}
}