{
  "type": "Feature",
  "properties": {
    "iso:country":"GB",
    "wof:name":"PR2 1JA",
    "wof:placetype":"postalcode"
},
  "geometry": {"coordinates":[-2.74078323045007,53.76892929139789],"type":"Point"}
}