{
  "type": "Feature",
  "properties": {
    "date:inception_lower": "1983-01-01",
    "date:inception_upper": "1983-01-01",
    "iso:country": "GB",
    "wof:name": "WC2H 9SA",
    "wof:placetype": "postalcode"
  },
  "geometry": {"coordinates":[-0.123927,51.513893],"type":"Point"}
}
