{
  "type": "Feature",
  "properties": {
    "iso:country":"GB",
    "wof:name":"WC2H 9SA",
    "wof:placetype":"postalcode"
},
  "geometry": {"coordinates":[-0.12392711253282,51.51389282004687],"type":"Point"}
}