{
  "type": "Feature",
  "properties": {
    "iso:country": "GB",
    "wof:name": "WC2H 9SA",
    "wof:placetype": "postalcode"
  },
  "geometry": {"coordinates":[-0.123927,51.513893],"type":"Point"}
}
