{
  "type": "Feature",
  "properties": {
    "iso:country":"GB",
    "wof:name":"LE10 3BJ",
    "wof:placetype":"postalcode"
},
  "geometry": {"coordinates":[-1.28959054786679,52.52277253535985],"type":"Point"}
}