{
  "type": "Feature",
  "properties": {
    "iso:country": "GB",
    "wof:name": "LE10 3BJ",
    "wof:placetype": "postalcode"
  },
  "geometry": {"coordinates":[-1.289682,52.522872],"type":"Point"}
}
