{
  "type": "Feature",
  "properties": {
    "iso:country": "GB",
    "wof:name": "BA15 2BQ",
    "wof:placetype": "postalcode"
  },
  "geometry": {"coordinates":[-2.282661,51.328163],"type":"Point"}
}
