{
  "type": "Feature",
  "properties": {
    "iso:country":"GB",
    "wof:name":"BA15 2BQ",
    "wof:placetype":"postalcode"
},
  "geometry": {"coordinates":[-2.28266145103097,51.32816346978855],"type":"Point"}
}