{
  "type": "Feature",
  "properties": {
    "date:inception_lower": "1992-08-01",
    "date:inception_upper": "1992-08-01",
    "iso:country": "GB",
    "wof:name": "WV5 8EX",
    "wof:placetype": "postalcode"
  },
  "geometry": {"coordinates":[-2.211491,52.52266],"type":"Point"}
}
