{
  "type": "Feature",
  "properties": {
    "date:inception_lower": "2020-09-01",
    "date:inception_upper": "2020-09-01",
    "iso:country": "GB",
    "wof:name": "CW11 4DE",
    "wof:placetype": "postalcode"
  },
  "geometry": {"coordinates":[-2.348466,53.144355],"type":"Point"}
}
