{
  "type": "Feature",
  "properties": {
    "iso:country":"GB",
    "wof:name":"BR1 4AZ",
    "wof:placetype":"postalcode"
},
  "geometry": {"coordinates":[0.00506002147472,51.40969088342064],"type":"Point"}
}