{
  "type": "Feature",
  "properties": {
    "iso:country": "GB",
    "wof:name": "BR1 4AZ",
    "wof:placetype": "postalcode"
  },
  "geometry": {"coordinates":[0.005086,51.40969],"type":"Point"}
}
