{
  "type": "Feature",
  "properties": {
    "iso:country":"GB",
    "wof:name":"BD7 4NJ",
    "wof:placetype":"postalcode"
},
  "geometry": {"coordinates":[-1.80028615115403,53.7736600650893],"type":"Point"}
}