{
  "type": "Feature",
  "properties": {
    "iso:country": "GB",
    "wof:name": "BD7 4NJ",
    "wof:placetype": "postalcode"
  },
  "geometry": {"coordinates":[-1.800286,53.77366],"type":"Point"}
}
