{
  "type": "Feature",
  "properties": {
    "iso:country":"GB",
    "wof:name":"PA3 3QG",
    "wof:placetype":"postalcode"
},
  "geometry": {"coordinates":[-4.49970147154812,55.85027372142007],"type":"Point"}
}