{
  "type": "Feature",
  "properties": {
    "date:inception_lower": "1980-01-01",
    "date:inception_upper": "1980-01-01",
    "iso:country": "GB",
    "wof:name": "PA3 3QG",
    "wof:placetype": "postalcode"
  },
  "geometry": {"coordinates":[-4.499701,55.850274],"type":"Point"}
}
