{
  "type": "Feature",
  "properties": {
    "iso:country":"GB",
    "wof:name":"EH1 3RZ",
    "wof:placetype":"postalcode"
},
  "geometry": {"coordinates":[-3.18992968186667,55.95879953763788],"type":"Point"}
}