{
  "type": "Feature",
  "properties": {
    "iso:country":"GB",
    "wof:name":"CF64 4PD",
    "wof:placetype":"postalcode"
},
  "geometry": {"coordinates":[-3.207890005634,51.43589817314805],"type":"Point"}
}