{
  "type": "Feature",
  "properties": {
    "iso:country":"GB",
    "wof:name":"PO18 8LP",
    "wof:placetype":"postalcode"
},
  "geometry": {"coordinates":[-0.85733446602593,50.83213279420082],"type":"Point"}
}