{
  "type": "Feature",
  "properties": {
    "date:inception_lower": "1980-01-01",
    "date:inception_upper": "1980-01-01",
    "iso:country": "GB",
    "wof:name": "B21 9HU",
    "wof:placetype": "postalcode"
  },
  "geometry": {"coordinates":[-1.934043,52.505116],"type":"Point"}
}
