{
  "type": "Feature",
  "properties": {
    "iso:country":"GB",
    "wof:name":"CH3 7EE",
    "wof:placetype":"postalcode"
},
  "geometry": {"coordinates":[-2.85297682264856,53.20263115659272],"type":"Point"}
}