{
  "type": "Feature",
  "properties": {
    "date:inception_lower": "1980-01-01",
    "date:inception_upper": "1980-01-01",
    "iso:country": "GB",
    "wof:name": "CH3 7EE",
    "wof:placetype": "postalcode"
  },
  "geometry": {"coordinates":[-2.852978,53.202647],"type":"Point"}
}
