{
  "type": "Feature",
  "properties": {
    "iso:country": "GB",
    "wof:name": "ST19 5PN",
    "wof:placetype": "postalcode"
  },
  "geometry": {"coordinates":[-2.135339,52.693509],"type":"Point"}
}
