{
  "type": "Feature",
  "properties": {
    "iso:country":"GB",
    "wof:name":"BH15 4LP",
    "wof:placetype":"postalcode"
},
  "geometry": {"coordinates":[-2.01701536752555,50.71429137715246],"type":"Point"}
}