{
  "type": "Feature",
  "properties": {
    "date:inception_lower": "1994-05-01",
    "date:inception_upper": "1994-05-01",
    "iso:country": "GB",
    "wof:name": "DH2 2NE",
    "wof:placetype": "postalcode"
  },
  "geometry": {"coordinates":[-1.592533,54.85919],"type":"Point"}
}
