{
  "type": "Feature",
  "properties": {
    "iso:country":"GB",
    "wof:name":"DH2 2NE",
    "wof:placetype":"postalcode"
},
  "geometry": {"coordinates":[-1.59253260848003,54.85918956238653],"type":"Point"}
}