{
  "type": "Feature",
  "properties": {
    "iso:country":"GB",
    "wof:name":"S40 4QT",
    "wof:placetype":"postalcode"
},
  "geometry": {"coordinates":[-1.45991177192261,53.24293579664634],"type":"Point"}
}