{
  "type": "Feature",
  "properties": {
    "iso:country": "GB",
    "wof:name": "DH4 5HQ",
    "wof:placetype": "postalcode"
  },
  "geometry": {"coordinates":[-1.481403,54.846814],"type":"Point"}
}
