{
  "type": "Feature",
  "properties": {
    "iso:country":"GB",
    "wof:name":"CH45 9NB",
    "wof:placetype":"postalcode"
},
  "geometry": {"coordinates":[-3.05464337923485,53.43658516377714],"type":"Point"}
}