{
  "type": "Feature",
  "properties": {
    "iso:country":"GB",
    "wof:name":"NE11 0YL",
    "wof:placetype":"postalcode"
},
  "geometry": {"coordinates":[-1.61547865677651,54.90506799505158],"type":"Point"}
}