{
  "type": "Feature",
  "properties": {
    "iso:country":"GB",
    "wof:name":"GU34 4DP",
    "wof:placetype":"postalcode"
},
  "geometry": {"coordinates":[-0.98163083181554,51.19461157470793],"type":"Point"}
}