{
  "type": "Feature",
  "properties": {
    "iso:country":"GB",
    "wof:name":"KT14 6DX",
    "wof:placetype":"postalcode"
},
  "geometry": {"coordinates":[-0.50163562665843,51.34192653601111],"type":"Point"}
}