{
  "type": "Feature",
  "properties": {
    "iso:country":"GB",
    "wof:name":"BR8 7HY",
    "wof:placetype":"postalcode"
},
  "geometry": {"coordinates":[0.16086995461518,51.39849468527015],"type":"Point"}
}