{
  "type": "Feature",
  "properties": {
    "iso:country":"GB",
    "wof:name":"MK42 8RD",
    "wof:placetype":"postalcode"
},
  "geometry": {"coordinates":[-0.49945188486102,52.12252352518918],"type":"Point"}
}