{
  "type": "Feature",
  "properties": {
    "iso:country":"GB",
    "wof:name":"BD12 7HB",
    "wof:placetype":"postalcode"
},
  "geometry": {"coordinates":[-1.73446984826703,53.7489052903782],"type":"Point"}
}