{
  "type": "Feature",
  "properties": {
    "date:inception_lower": "2015-06-01",
    "date:inception_upper": "2015-06-01",
    "iso:country": "GB",
    "wof:name": "FK10 1SG",
    "wof:placetype": "postalcode"
  },
  "geometry": {"coordinates":[-3.779765,56.108639],"type":"Point"}
}
