{
  "type": "Feature",
  "properties": {
    "iso:country": "GB",
    "wof:name": "ME1 3FW",
    "wof:placetype": "postalcode"
  },
  "geometry": {"coordinates":[0.457645,51.337749],"type":"Point"}
}
