{
  "type": "Feature",
  "properties": {
    "date:inception_lower": "1980-01-01",
    "date:inception_upper": "1980-01-01",
    "iso:country": "GB",
    "wof:name": "G64 3EF",
    "wof:placetype": "postalcode"
  },
  "geometry": {"coordinates":[-4.220641,55.912797],"type":"Point"}
}
