{
  "type": "Feature",
  "properties": {
    "iso:country":"GB",
    "wof:name":"G64 3EF",
    "wof:placetype":"postalcode"
},
  "geometry": {"coordinates":[-4.22064120353717,55.91279731540575],"type":"Point"}
}