{
  "type": "Feature",
  "properties": {
    "iso:country":"GB",
    "wof:name":"BA22 7BD",
    "wof:placetype":"postalcode"
},
  "geometry": {"coordinates":[-2.54556512595783,51.05907324782799],"type":"Point"}
}