{
  "type": "Feature",
  "properties": {
    "date:inception_lower": "1981-06-01",
    "date:inception_upper": "1981-06-01",
    "iso:country": "GB",
    "wof:name": "NE33 4SH",
    "wof:placetype": "postalcode"
  },
  "geometry": {"coordinates":[-1.440895,54.978663],"type":"Point"}
}
