{
  "type": "Feature",
  "properties": {
    "iso:country": "GB",
    "wof:name": "NE33 4SH",
    "wof:placetype": "postalcode"
  },
  "geometry": {"coordinates":[-1.440895,54.978663],"type":"Point"}
}
