{
  "type": "Feature",
  "properties": {
    "iso:country":"GB",
    "wof:name":"BS22 8JY",
    "wof:placetype":"postalcode"
},
  "geometry": {"coordinates":[-2.94167900336567,51.35740352199934],"type":"Point"}
}