{
  "type": "Feature",
  "properties": {
    "iso:country": "GB",
    "wof:name": "BS22 8JY",
    "wof:placetype": "postalcode"
  },
  "geometry": {"coordinates":[-2.941741,51.357364],"type":"Point"}
}
