{
  "type": "Feature",
  "properties": {
    "date:inception_lower": "2021-02-01",
    "date:inception_upper": "2021-02-01",
    "iso:country": "GB",
    "wof:name": "NE20 0FB",
    "wof:placetype": "postalcode"
  },
  "geometry": {"coordinates":[-1.75706,55.061844],"type":"Point"}
}
