{
  "type": "Feature",
  "properties": {
    "date:inception_lower": "1980-01-01",
    "date:inception_upper": "1980-01-01",
    "iso:country": "GB",
    "wof:name": "FY8 4DX",
    "wof:placetype": "postalcode"
  },
  "geometry": {"coordinates":[-2.991197,53.74588],"type":"Point"}
}
