{
  "type": "Feature",
  "properties": {
    "iso:country":"GB",
    "wof:name":"NN14 2QR",
    "wof:placetype":"postalcode"
},
  "geometry": {"coordinates":[-0.81143468800834,52.43680969005845],"type":"Point"}
}