{
  "type": "Feature",
  "properties": {
    "iso:country":"GB",
    "wof:name":"G12 9DL",
    "wof:placetype":"postalcode"
},
  "geometry": {"coordinates":[-4.29956692012624,55.87555994139284],"type":"Point"}
}