{
  "type": "Feature",
  "properties": {
    "iso:country":"GB",
    "wof:name":"BD7 1DD",
    "wof:placetype":"postalcode"
},
  "geometry": {"coordinates":[-1.76231793105695,53.79341842318608],"type":"Point"}
}