{
  "type": "Feature",
  "properties": {
    "date:inception_lower":"2002-09-01",
    "date:inception_upper":"2002-09-30",
    "iso:country":"GB",
    "wof:name":"BD7 1DD",
    "wof:placetype":"postalcode"
},
  "geometry": {"coordinates":[-1.762318,53.793418],"type":"Point"}
}