{
  "type": "Feature",
  "properties": {
    "iso:country":"GB",
    "wof:name":"HD4 5BH",
    "wof:placetype":"postalcode"
},
  "geometry": {"coordinates":[-1.80738103864115,53.6388050870509],"type":"Point"}
}