{
  "type": "Feature",
  "properties": {
    "iso:country": "GB",
    "wof:name": "BS6 5NU",
    "wof:placetype": "postalcode"
  },
  "geometry": {"coordinates":[-2.58222,51.465897],"type":"Point"}
}
