{
  "type": "Feature",
  "properties": {
    "iso:country": "GB",
    "wof:name": "CM0 7RX",
    "wof:placetype": "postalcode"
  },
  "geometry": {"coordinates":[0.824591,51.660833],"type":"Point"}
}
