{
  "type": "Feature",
  "properties": {
    "iso:country":"GB",
    "wof:name":"CM0 7RX",
    "wof:placetype":"postalcode"
},
  "geometry": {"coordinates":[0.82459120680089,51.66083324449669],"type":"Point"}
}