{
  "type": "Feature",
  "properties": {
    "iso:country": "GB",
    "wof:name": "CM4 9HH",
    "wof:placetype": "postalcode"
  },
  "geometry": {"coordinates":[0.376804,51.667687],"type":"Point"}
}
