{
  "type": "Feature",
  "properties": {
    "iso:country":"GB",
    "wof:name":"CM4 9HH",
    "wof:placetype":"postalcode"
},
  "geometry": {"coordinates":[0.37680369758837,51.66768691337647],"type":"Point"}
}