{
  "type": "Feature",
  "properties": {
    "iso:country": "GB",
    "wof:name": "BH31 6TS",
    "wof:placetype": "postalcode"
  },
  "geometry": {"coordinates":[-1.866082,50.869275],"type":"Point"}
}
