{
  "type": "Feature",
  "properties": {
    "iso:country":"GB",
    "wof:name":"IP25 7EW",
    "wof:placetype":"postalcode"
},
  "geometry": {"coordinates":[0.80930832473914,52.59659594233791],"type":"Point"}
}