{
  "type": "Feature",
  "properties": {
    "iso:country": "GB",
    "wof:name": "IP25 7EW",
    "wof:placetype": "postalcode"
  },
  "geometry": {"coordinates":[0.809308,52.596596],"type":"Point"}
}
