{
  "type": "Feature",
  "properties": {
    "iso:country": "GB",
    "wof:name": "PO30 5EE",
    "wof:placetype": "postalcode"
  },
  "geometry": {"coordinates":[-1.301467,50.701635],"type":"Point"}
}
