{
  "type": "Feature",
  "properties": {
    "date:inception_lower": "2015-01-01",
    "date:inception_upper": "2015-01-01",
    "iso:country": "GB",
    "wof:name": "L14 0AD",
    "wof:placetype": "postalcode"
  },
  "geometry": {"coordinates":[-2.875662,53.4184],"type":"Point"}
}
