{
  "type": "Feature",
  "properties": {
    "date:inception_lower": "2008-02-01",
    "date:inception_upper": "2008-02-01",
    "iso:country": "GB",
    "wof:name": "TF7 4PF",
    "wof:placetype": "postalcode"
  },
  "geometry": {"coordinates":[-2.433231,52.637336],"type":"Point"}
}
