{
  "type": "Feature",
  "properties": {
    "iso:country": "GB",
    "wof:name": "TA4 4JX",
    "wof:placetype": "postalcode"
  },
  "geometry": {"coordinates":[-3.305873,51.152696],"type":"Point"}
}
