{
  "type": "Feature",
  "properties": {
    "iso:country":"GB",
    "wof:name":"GL54 2HR",
    "wof:placetype":"postalcode"
},
  "geometry": {"coordinates":[-1.76174933118986,51.9019805242389],"type":"Point"}
}