{
  "type": "Feature",
  "properties": {
    "date:inception_lower":"1980-01-01",
    "date:inception_upper":"1980-01-31",
    "iso:country":"GB",
    "wof:name":"TS25 4EQ",
    "wof:placetype":"postalcode"
},
  "geometry": {"coordinates":[-1.238499,54.662527],"type":"Point"}
}