{
  "type": "Feature",
  "properties": {
    "iso:country": "GB",
    "wof:name": "TS25 4EQ",
    "wof:placetype": "postalcode"
  },
  "geometry": {"coordinates":[-1.238499,54.662527],"type":"Point"}
}
