{
  "type": "Feature",
  "properties": {
    "iso:country":"GB",
    "wof:name":"TS25 4EQ",
    "wof:placetype":"postalcode"
},
  "geometry": {"coordinates":[-1.23849898240309,54.66252743712003],"type":"Point"}
}