{
  "type": "Feature",
  "properties": {
    "iso:country":"GB",
    "wof:name":"DD2 1DL",
    "wof:placetype":"postalcode"
},
  "geometry": {"coordinates":[-2.99722145956299,56.45920713220628],"type":"Point"}
}