{
  "type": "Feature",
  "properties": {
    "date:inception_lower":"1980-01-01",
    "date:inception_upper":"1980-01-31",
    "iso:country":"GB",
    "wof:name":"HR4 8HJ",
    "wof:placetype":"postalcode"
},
  "geometry": {"coordinates":[-2.854611,52.182419],"type":"Point"}
}