{
  "type": "Feature",
  "properties": {
    "iso:country":"GB",
    "wof:name":"HR4 8HJ",
    "wof:placetype":"postalcode"
},
  "geometry": {"coordinates":[-2.85461076436433,52.18241881575548],"type":"Point"}
}