{
  "type": "Feature",
  "properties": {
    "iso:country": "GB",
    "wof:name": "GL3 4PQ",
    "wof:placetype": "postalcode"
  },
  "geometry": {"coordinates":[-2.152287,51.841631],"type":"Point"}
}
