{
  "type": "Feature",
  "properties": {
    "iso:country":"GB",
    "wof:name":"GL3 4PQ",
    "wof:placetype":"postalcode"
},
  "geometry": {"coordinates":[-2.15228735491885,51.841631500789],"type":"Point"}
}