{
  "type": "Feature",
  "properties": {
    "iso:country":"GB",
    "wof:name":"NE3 3HN",
    "wof:placetype":"postalcode"
},
  "geometry": {"coordinates":[-1.63147073199584,55.01191943462477],"type":"Point"}
}