{
  "type": "Feature",
  "properties": {
    "iso:country": "GB",
    "wof:name": "SN6 8DE",
    "wof:placetype": "postalcode"
  },
  "geometry": {"coordinates":[-1.660342,51.600756],"type":"Point"}
}
