{
  "type": "Feature",
  "properties": {
    "date:inception_lower": "2017-04-01",
    "date:inception_upper": "2017-04-01",
    "iso:country": "GB",
    "wof:name": "SN6 8DE",
    "wof:placetype": "postalcode"
  },
  "geometry": {"coordinates":[-1.660342,51.600756],"type":"Point"}
}
