{
  "type": "Feature",
  "properties": {
    "iso:country":"GB",
    "wof:name":"RG30 6BZ",
    "wof:placetype":"postalcode"
},
  "geometry": {"coordinates":[-1.02697731355011,51.46145765025857],"type":"Point"}
}