{
  "type": "Feature",
  "properties": {
    "iso:country":"GB",
    "wof:name":"LN12 2NH",
    "wof:placetype":"postalcode"
},
  "geometry": {"coordinates":[0.27852737829778,53.31557039403965],"type":"Point"}
}