{
  "type": "Feature",
  "properties": {
    "date:inception_lower": "1980-01-01",
    "date:inception_upper": "1980-01-01",
    "iso:country": "GB",
    "wof:name": "DD3 7EZ",
    "wof:placetype": "postalcode"
  },
  "geometry": {"coordinates":[-2.974793,56.471164],"type":"Point"}
}
