{
  "type": "Feature",
  "properties": {
    "date:inception_lower": "2023-03-01",
    "date:inception_upper": "2023-03-01",
    "iso:country": "GB",
    "wof:name": "PE34 4FR",
    "wof:placetype": "postalcode"
  },
  "geometry": {"coordinates":[0.298674,52.748351],"type":"Point"}
}
