{
  "type": "Feature",
  "properties": {
    "iso:country":"GB",
    "wof:name":"CH62 6DN",
    "wof:placetype":"postalcode"
},
  "geometry": {"coordinates":[-2.97740336423013,53.31510920511865],"type":"Point"}
}