{
  "type": "Feature",
  "properties": {
    "date:inception_lower":"1994-06-01",
    "date:inception_upper":"1994-06-30",
    "iso:country":"GB",
    "wof:name":"FK13 6DW",
    "wof:placetype":"postalcode"
},
  "geometry": {"coordinates":[-3.741297,56.152928],"type":"Point"}
}