{
  "type": "Feature",
  "properties": {
    "iso:country":"GB",
    "wof:name":"CF48 4HU",
    "wof:placetype":"postalcode"
},
  "geometry": {"coordinates":[-3.34894120499863,51.71719111725201],"type":"Point"}
}