{
  "type": "Feature",
  "properties": {
    "date:inception_lower": "1990-08-01",
    "date:inception_upper": "1990-08-01",
    "iso:country": "GB",
    "wof:name": "AB36 8YL",
    "wof:placetype": "postalcode"
  },
  "geometry": {"coordinates":[-3.193937,57.161286],"type":"Point"}
}
