{
  "type": "Feature",
  "properties": {
    "date:inception_lower": "2000-06-01",
    "date:inception_upper": "2000-06-01",
    "iso:country": "GB",
    "wof:name": "TQ3 1LB",
    "wof:placetype": "postalcode"
  },
  "geometry": {"coordinates":[-3.595167,50.452788],"type":"Point"}
}
