{
  "type": "Feature",
  "properties": {
    "iso:country": "GB",
    "wof:name": "G72 7QU",
    "wof:placetype": "postalcode"
  },
  "geometry": {"coordinates":[-4.143351,55.812693],"type":"Point"}
}
