{
  "type": "Feature",
  "properties": {
    "iso:country":"GB",
    "wof:name":"N1 1NW",
    "wof:placetype":"postalcode"
},
  "geometry": {"coordinates":[-0.10739778882274,51.5437522147312],"type":"Point"}
}