{
  "type": "Feature",
  "properties": {
    "date:inception_lower": "2023-07-01",
    "date:inception_upper": "2023-07-01",
    "iso:country": "GB",
    "wof:name": "S81 8GR",
    "wof:placetype": "postalcode"
  },
  "geometry": {"coordinates":[-1.055033,53.376169],"type":"Point"}
}
