{
  "type": "Feature",
  "properties": {
    "date:inception_lower":"1980-01-01",
    "date:inception_upper":"1980-01-31",
    "iso:country":"GB",
    "wof:name":"TW15 1RQ",
    "wof:placetype":"postalcode"
},
  "geometry": {"coordinates":[-0.44458,51.42412],"type":"Point"}
}