{
  "type": "Feature",
  "properties": {
    "date:inception_lower": "1980-01-01",
    "date:inception_upper": "1980-01-01",
    "iso:country": "GB",
    "wof:name": "PR1 4QP",
    "wof:placetype": "postalcode"
  },
  "geometry": {"coordinates":[-2.671099,53.762194],"type":"Point"}
}
