{
  "type": "Feature",
  "properties": {
    "iso:country": "GB",
    "wof:name": "PR1 4QP",
    "wof:placetype": "postalcode"
  },
  "geometry": {"coordinates":[-2.671099,53.762194],"type":"Point"}
}
