{
  "type": "Feature",
  "properties": {
    "iso:country":"GB",
    "wof:name":"PR1 4QP",
    "wof:placetype":"postalcode"
},
  "geometry": {"coordinates":[-2.67109864702947,53.76219415328197],"type":"Point"}
}