{
  "type": "Feature",
  "properties": {
    "iso:country":"GB",
    "wof:name":"ME13 7NG",
    "wof:placetype":"postalcode"
},
  "geometry": {"coordinates":[0.87819388068213,51.31458312528426],"type":"Point"}
}