{
  "type": "Feature",
  "properties": {
    "date:inception_lower": "1980-01-01",
    "date:inception_upper": "1980-01-01",
    "iso:country": "GB",
    "wof:name": "ME13 7NG",
    "wof:placetype": "postalcode"
  },
  "geometry": {"coordinates":[0.878194,51.314583],"type":"Point"}
}
