{
  "type": "Feature",
  "properties": {
    "iso:country": "GB",
    "wof:name": "SP2 0EW",
    "wof:placetype": "postalcode"
  },
  "geometry": {"coordinates":[-1.895991,51.075903],"type":"Point"}
}
