{
  "type": "Feature",
  "properties": {
    "iso:country":"GB",
    "wof:name":"SP2 0EW",
    "wof:placetype":"postalcode"
},
  "geometry": {"coordinates":[-1.89599138742238,51.07590295464377],"type":"Point"}
}