{
  "type": "Feature",
  "properties": {
    "date:inception_lower":"2011-05-01",
    "date:inception_upper":"2011-05-31",
    "iso:country":"GB",
    "wof:name":"PE28 4UE",
    "wof:placetype":"postalcode"
},
  "geometry": {"coordinates":[-0.224422,52.323294],"type":"Point"}
}