{
  "type": "Feature",
  "properties": {
    "iso:country": "GB",
    "wof:name": "PE28 4UE",
    "wof:placetype": "postalcode"
  },
  "geometry": {"coordinates":[-0.224422,52.323294],"type":"Point"}
}
