{
  "type": "Feature",
  "properties": {
    "iso:country":"GB",
    "wof:name":"PE28 4UE",
    "wof:placetype":"postalcode"
},
  "geometry": {"coordinates":[-0.22442200343894,52.32329370201771],"type":"Point"}
}