{
  "type": "Feature",
  "properties": {
    "iso:country":"GB",
    "wof:name":"GU3 2JD",
    "wof:placetype":"postalcode"
},
  "geometry": {"coordinates":[-0.67995051679449,51.25358206033229],"type":"Point"}
}