{
  "type": "Feature",
  "properties": {
    "iso:country": "GB",
    "wof:name": "GU3 2JD",
    "wof:placetype": "postalcode"
  },
  "geometry": {"coordinates":[-0.67995,51.253582],"type":"Point"}
}
