{
  "type": "Feature",
  "properties": {
    "iso:country": "GB",
    "wof:name": "SK23 9TP",
    "wof:placetype": "postalcode"
  },
  "geometry": {"coordinates":[-1.931808,53.319599],"type":"Point"}
}
