{
  "type": "Feature",
  "properties": {
    "iso:country":"GB",
    "wof:name":"SK23 9TP",
    "wof:placetype":"postalcode"
},
  "geometry": {"coordinates":[-1.9318084257718,53.31959909351599],"type":"Point"}
}