{
  "type": "Feature",
  "properties": {
    "iso:country":"GB",
    "wof:name":"AB23 8BA",
    "wof:placetype":"postalcode"
},
  "geometry": {"coordinates":[-2.08961052825188,57.19037606611234],"type":"Point"}
}