{
  "type": "Feature",
  "properties": {
    "iso:country": "GB",
    "wof:name": "AB23 8BA",
    "wof:placetype": "postalcode"
  },
  "geometry": {"coordinates":[-2.08961,57.190376],"type":"Point"}
}
