{
  "type": "Feature",
  "properties": {
    "iso:country": "GB",
    "wof:name": "CB23 8HF",
    "wof:placetype": "postalcode"
  },
  "geometry": {"coordinates":[0.001735,52.257617],"type":"Point"}
}
