{
  "type": "Feature",
  "properties": {
    "date:inception_lower":"2006-09-01",
    "date:inception_upper":"2006-09-30",
    "iso:country":"GB",
    "wof:name":"CB23 8HF",
    "wof:placetype":"postalcode"
},
  "geometry": {"coordinates":[0.001735,52.257617],"type":"Point"}
}