{
  "type": "Feature",
  "properties": {
    "iso:country":"GB",
    "wof:name":"LS5 3HP",
    "wof:placetype":"postalcode"
},
  "geometry": {"coordinates":[-1.60237150052231,53.81673245118048],"type":"Point"}
}