{
  "type": "Feature",
  "properties": {
    "date:inception_lower": "1980-01-01",
    "date:inception_upper": "1980-01-01",
    "iso:country": "GB",
    "wof:name": "LS5 3HP",
    "wof:placetype": "postalcode"
  },
  "geometry": {"coordinates":[-1.602371,53.816732],"type":"Point"}
}
