{
  "type": "Feature",
  "properties": {
    "iso:country": "GB",
    "wof:name": "IP31 2GL",
    "wof:placetype": "postalcode"
  },
  "geometry": {"coordinates":[0.831912,52.298134],"type":"Point"}
}
