{
  "type": "Feature",
  "properties": {
    "iso:country": "GB",
    "wof:name": "RG7 3BQ",
    "wof:placetype": "postalcode"
  },
  "geometry": {"coordinates":[-1.049607,51.402459],"type":"Point"}
}
