{
  "type": "Feature",
  "properties": {
    "iso:country":"GB",
    "wof:name":"BN25 4NG",
    "wof:placetype":"postalcode"
},
  "geometry": {"coordinates":[0.12626403964899,50.77168490814226],"type":"Point"}
}