{
  "type": "Feature",
  "properties": {
    "iso:country":"GB",
    "wof:name":"TS6 9LZ",
    "wof:placetype":"postalcode"
},
  "geometry": {"coordinates":[-1.14149442489699,54.56111612240552],"type":"Point"}
}