{
  "type": "Feature",
  "properties": {
    "iso:country":"GB",
    "wof:name":"ML7 5LQ",
    "wof:placetype":"postalcode"
},
  "geometry": {"coordinates":[-3.78044277270765,55.81516774547407],"type":"Point"}
}