{
  "type": "Feature",
  "properties": {
    "iso:country":"GB",
    "wof:name":"LL14 1UH",
    "wof:placetype":"postalcode"
},
  "geometry": {"coordinates":[-3.09384598274926,53.02069404226631],"type":"Point"}
}