{
  "type": "Feature",
  "properties": {
    "iso:country":"GB",
    "wof:name":"BN2 5UY",
    "wof:placetype":"postalcode"
},
  "geometry": {"coordinates":[-0.09930855513721,50.812822003361],"type":"Point"}
}