{
  "type": "Feature",
  "properties": {
    "iso:country":"GB",
    "wof:name":"AB41 6SQ",
    "wof:placetype":"postalcode"
},
  "geometry": {"coordinates":[-2.2156860978314,57.30624553746706],"type":"Point"}
}