{
  "type": "Feature",
  "properties": {
    "iso:country": "GB",
    "wof:name": "LN12 2DZ",
    "wof:placetype": "postalcode"
  },
  "geometry": {"coordinates":[0.263916,53.332814],"type":"Point"}
}
