{
  "type": "Feature",
  "properties": {
    "iso:country":"GB",
    "wof:name":"LN12 2DZ",
    "wof:placetype":"postalcode"
},
  "geometry": {"coordinates":[0.26391638613443,53.3328140610307],"type":"Point"}
}