{
  "type": "Feature",
  "properties": {
    "date:inception_lower": "1980-01-01",
    "date:inception_upper": "1980-01-01",
    "iso:country": "GB",
    "wof:name": "DE13 0TT",
    "wof:placetype": "postalcode"
  },
  "geometry": {"coordinates":[-1.642046,52.820079],"type":"Point"}
}
