{
  "type": "Feature",
  "properties": {
    "iso:country":"GB",
    "wof:name":"WA8 8JQ",
    "wof:placetype":"postalcode"
},
  "geometry": {"coordinates":[-2.77903365020677,53.36825601310697],"type":"Point"}
}