{
  "type": "Feature",
  "properties": {
    "iso:country":"GB",
    "wof:name":"KT2 7NS",
    "wof:placetype":"postalcode"
},
  "geometry": {"coordinates":[-0.27612095706205,51.41872355426653],"type":"Point"}
}