{
  "type": "Feature",
  "properties": {
    "date:inception_lower": "1993-01-01",
    "date:inception_upper": "1993-01-01",
    "iso:country": "GB",
    "wof:name": "MK7 8QU",
    "wof:placetype": "postalcode"
  },
  "geometry": {"coordinates":[-0.678778,52.014932],"type":"Point"}
}
