{
  "type": "Feature",
  "properties": {
    "date:inception_lower": "1997-06-01",
    "date:inception_upper": "1997-06-01",
    "iso:country": "GB",
    "wof:name": "TS17 0AZ",
    "wof:placetype": "postalcode"
  },
  "geometry": {"coordinates":[-1.310187,54.535018],"type":"Point"}
}
