{
  "type": "Feature",
  "properties": {
    "iso:country": "GB",
    "wof:name": "TS17 0AZ",
    "wof:placetype": "postalcode"
  },
  "geometry": {"coordinates":[-1.310187,54.535018],"type":"Point"}
}
