{
  "type": "Feature",
  "properties": {
    "date:inception_lower": "1980-01-01",
    "date:inception_upper": "1980-01-01",
    "iso:country": "GB",
    "wof:name": "W4 1PD",
    "wof:placetype": "postalcode"
  },
  "geometry": {"coordinates":[-0.258202,51.492799],"type":"Point"}
}
