{
  "type": "Feature",
  "properties": {
    "iso:country":"GB",
    "wof:name":"WS11 1EH",
    "wof:placetype":"postalcode"
},
  "geometry": {"coordinates":[-2.04012054441371,52.68548019742587],"type":"Point"}
}