{
  "type": "Feature",
  "properties": {
    "iso:country":"GB",
    "wof:name":"HR2 8BD",
    "wof:placetype":"postalcode"
},
  "geometry": {"coordinates":[-2.71374251776322,51.98362620646243],"type":"Point"}
}