{
  "type": "Feature",
  "properties": {
    "date:inception_lower":"1980-01-01",
    "date:inception_upper":"1980-01-31",
    "iso:country":"GB",
    "wof:name":"CO15 5RN",
    "wof:placetype":"postalcode"
},
  "geometry": {"coordinates":[1.195561,51.808351],"type":"Point"}
}