{
  "type": "Feature",
  "properties": {
    "iso:country":"GB",
    "wof:name":"CO15 5RN",
    "wof:placetype":"postalcode"
},
  "geometry": {"coordinates":[1.19556099589306,51.80835054934783],"type":"Point"}
}