{
  "type": "Feature",
  "properties": {
    "iso:country":"GB",
    "wof:name":"KA29 0AW",
    "wof:placetype":"postalcode"
},
  "geometry": {"coordinates":[-4.85637671452243,55.76176562760839],"type":"Point"}
}