{
  "type": "Feature",
  "properties": {
    "date:inception_lower": "1980-01-01",
    "date:inception_upper": "1980-01-01",
    "iso:country": "GB",
    "wof:name": "KA29 0AW",
    "wof:placetype": "postalcode"
  },
  "geometry": {"coordinates":[-4.856377,55.761766],"type":"Point"}
}
