{
  "type": "Feature",
  "properties": {
    "date:inception_lower": "1980-01-01",
    "date:inception_upper": "1980-01-01",
    "iso:country": "GB",
    "wof:name": "KY12 9XD",
    "wof:placetype": "postalcode"
  },
  "geometry": {"coordinates":[-3.577543,56.086027],"type":"Point"}
}
