{
  "type": "Feature",
  "properties": {
    "date:inception_lower": "1985-10-01",
    "date:inception_upper": "1985-10-01",
    "iso:country": "GB",
    "wof:name": "TN3 0AZ",
    "wof:placetype": "postalcode"
  },
  "geometry": {"coordinates":[0.222583,51.133997],"type":"Point"}
}
