{
  "type": "Feature",
  "properties": {
    "iso:country":"GB",
    "wof:name":"TN3 0AZ",
    "wof:placetype":"postalcode"
},
  "geometry": {"coordinates":[0.22255593028106,51.13399924880886],"type":"Point"}
}