{
  "type": "Feature",
  "properties": {
    "iso:country": "GB",
    "wof:name": "BH1 3AJ",
    "wof:placetype": "postalcode"
  },
  "geometry": {"coordinates":[-1.86986,50.718588],"type":"Point"}
}
