{
  "type": "Feature",
  "properties": {
    "iso:country":"GB",
    "wof:name":"BH1 3AJ",
    "wof:placetype":"postalcode"
},
  "geometry": {"coordinates":[-1.86969806671065,50.71866252967981],"type":"Point"}
}