{
  "type": "Feature",
  "properties": {
    "iso:country": "GB",
    "wof:name": "SO32 1QG",
    "wof:placetype": "postalcode"
  },
  "geometry": {"coordinates":[-1.212131,50.951316],"type":"Point"}
}
