{
  "type": "Feature",
  "properties": {
    "iso:country":"GB",
    "wof:name":"SW6 4SA",
    "wof:placetype":"postalcode"
},
  "geometry": {"coordinates":[-0.19139055897996,51.47749885345136],"type":"Point"}
}