{
  "type": "Feature",
  "properties": {
    "date:inception_lower": "2023-08-01",
    "date:inception_upper": "2023-08-01",
    "iso:country": "GB",
    "wof:name": "GL3 1PW",
    "wof:placetype": "postalcode"
  },
  "geometry": {"coordinates":[-2.216124,51.890827],"type":"Point"}
}
