{
  "type": "Feature",
  "properties": {
    "date:inception_lower": "1998-06-01",
    "date:inception_upper": "1998-06-01",
    "iso:country": "GB",
    "wof:name": "YO10 4ED",
    "wof:placetype": "postalcode"
  },
  "geometry": {"coordinates":[-1.076057,53.946374],"type":"Point"}
}
