{
  "type": "Feature",
  "properties": {
    "iso:country": "GB",
    "wof:name": "YO10 4ED",
    "wof:placetype": "postalcode"
  },
  "geometry": {"coordinates":[-1.076019,53.946356],"type":"Point"}
}
