{
  "type": "Feature",
  "properties": {
    "date:inception_lower": "1980-01-01",
    "date:inception_upper": "1980-01-01",
    "iso:country": "GB",
    "wof:name": "SS6 8UT",
    "wof:placetype": "postalcode"
  },
  "geometry": {"coordinates":[0.631275,51.577663],"type":"Point"}
}
