{
  "type": "Feature",
  "properties": {
    "iso:country":"GB",
    "wof:name":"SS6 8UT",
    "wof:placetype":"postalcode"
},
  "geometry": {"coordinates":[0.63120571541388,51.57768635720702],"type":"Point"}
}