{
  "type": "Feature",
  "properties": {
    "iso:country":"GB",
    "wof:name":"NP20 7RZ",
    "wof:placetype":"postalcode"
},
  "geometry": {"coordinates":[-3.03431171725654,51.60618107856163],"type":"Point"}
}