{
  "type": "Feature",
  "properties": {
    "iso:country": "GB",
    "wof:name": "NP20 7RZ",
    "wof:placetype": "postalcode"
  },
  "geometry": {"coordinates":[-3.034312,51.606181],"type":"Point"}
}
