{
  "type": "Feature",
  "properties": {
    "iso:country": "GB",
    "wof:name": "KA5 6NQ",
    "wof:placetype": "postalcode"
  },
  "geometry": {"coordinates":[-4.29597,55.498879],"type":"Point"}
}
