{
  "type": "Feature",
  "properties": {
    "iso:country":"GB",
    "wof:name":"NE34 9HX",
    "wof:placetype":"postalcode"
},
  "geometry": {"coordinates":[-1.44666450936582,54.96361033887776],"type":"Point"}
}