{
  "type": "Feature",
  "properties": {
    "iso:country": "GB",
    "wof:name": "OX5 3AL",
    "wof:placetype": "postalcode"
  },
  "geometry": {"coordinates":[-1.30527,51.880869],"type":"Point"}
}
