{
  "type": "Feature",
  "properties": {
    "iso:country":"GB",
    "wof:name":"OX5 3AL",
    "wof:placetype":"postalcode"
},
  "geometry": {"coordinates":[-1.30527007289143,51.88086854420794],"type":"Point"}
}