{
  "type": "Feature",
  "properties": {
    "date:inception_lower": "2002-12-01",
    "date:inception_upper": "2002-12-01",
    "iso:country": "GB",
    "wof:name": "OX5 3AL",
    "wof:placetype": "postalcode"
  },
  "geometry": {"coordinates":[-1.30527,51.880869],"type":"Point"}
}
