{
  "type": "Feature",
  "properties": {
    "iso:country":"GB",
    "wof:name":"AB31 6LT",
    "wof:placetype":"postalcode"
},
  "geometry": {"coordinates":[-2.57413403590864,56.96507797876745],"type":"Point"}
}