{
  "type": "Feature",
  "properties": {
    "date:inception_lower":"1992-08-01",
    "date:inception_upper":"1992-08-31",
    "iso:country":"GB",
    "wof:name":"NG31 8AW",
    "wof:placetype":"postalcode"
},
  "geometry": {"coordinates":[-0.649674,52.91454],"type":"Point"}
}