{
  "type": "Feature",
  "properties": {
    "iso:country":"GB",
    "wof:name":"NG31 8AW",
    "wof:placetype":"postalcode"
},
  "geometry": {"coordinates":[-0.64970910407962,52.91451858652865],"type":"Point"}
}