{
  "type": "Feature",
  "properties": {
    "iso:country":"GB",
    "wof:name":"HU9 3AY",
    "wof:placetype":"postalcode"
},
  "geometry": {"coordinates":[-0.30472600391219,53.75759066762698],"type":"Point"}
}