{
  "type": "Feature",
  "properties": {
    "iso:country": "GB",
    "wof:name": "HU9 3AY",
    "wof:placetype": "postalcode"
  },
  "geometry": {"coordinates":[-0.304726,53.757591],"type":"Point"}
}
