{
  "type": "Feature",
  "properties": {
    "date:inception_lower":"1995-12-01",
    "date:inception_upper":"1995-12-31",
    "iso:country":"GB",
    "wof:name":"BB7 2EZ",
    "wof:placetype":"postalcode"
},
  "geometry": {"coordinates":[-2.395236,53.873713],"type":"Point"}
}