{
  "type": "Feature",
  "properties": {
    "iso:country":"GB",
    "wof:name":"BB7 2EZ",
    "wof:placetype":"postalcode"
},
  "geometry": {"coordinates":[-2.39523599988949,53.87371322841106],"type":"Point"}
}