{
  "type": "Feature",
  "properties": {
    "iso:country": "GB",
    "wof:name": "BB7 2EZ",
    "wof:placetype": "postalcode"
  },
  "geometry": {"coordinates":[-2.395236,53.873713],"type":"Point"}
}
