{
  "type": "Feature",
  "properties": {
    "iso:country": "GB",
    "wof:name": "DD8 4GW",
    "wof:placetype": "postalcode"
  },
  "geometry": {"coordinates":[-3.005708,56.674879],"type":"Point"}
}
