{
  "type": "Feature",
  "properties": {
    "date:inception_lower": "1980-01-01",
    "date:inception_upper": "1980-01-01",
    "iso:country": "GB",
    "wof:name": "DA4 9EB",
    "wof:placetype": "postalcode"
  },
  "geometry": {"coordinates":[0.233306,51.4063],"type":"Point"}
}
