{
  "type": "Feature",
  "properties": {
    "iso:country":"GB",
    "wof:name":"DA4 9EB",
    "wof:placetype":"postalcode"
},
  "geometry": {"coordinates":[0.23330564668332,51.40630029773187],"type":"Point"}
}