{
  "type": "Feature",
  "properties": {
    "date:inception_lower": "1980-01-01",
    "date:inception_upper": "1980-01-01",
    "iso:country": "GB",
    "wof:name": "EH25 9QQ",
    "wof:placetype": "postalcode"
  },
  "geometry": {"coordinates":[-3.184982,55.832947],"type":"Point"}
}
