{
  "type": "Feature",
  "properties": {
    "iso:country":"GB",
    "wof:name":"SY16 1LA",
    "wof:placetype":"postalcode"
},
  "geometry": {"coordinates":[-3.3289561665445,52.50593970752567],"type":"Point"}
}