{
  "type": "Feature",
  "properties": {
    "iso:country": "GB",
    "wof:name": "SY16 1LA",
    "wof:placetype": "postalcode"
  },
  "geometry": {"coordinates":[-3.328956,52.50594],"type":"Point"}
}
