{
  "type": "Feature",
  "properties": {
    "date:inception_lower": "1980-01-01",
    "date:inception_upper": "1980-01-01",
    "iso:country": "GB",
    "wof:name": "IP2 9TH",
    "wof:placetype": "postalcode"
  },
  "geometry": {"coordinates":[1.136488,52.03786],"type":"Point"}
}
