{
  "type": "Feature",
  "properties": {
    "iso:country":"GB",
    "wof:name":"IP2 9TH",
    "wof:placetype":"postalcode"
},
  "geometry": {"coordinates":[1.13648756168641,52.03786012625887],"type":"Point"}
}