{
  "type": "Feature",
  "properties": {
    "iso:country":"GB",
    "wof:name":"BA15 1NU",
    "wof:placetype":"postalcode"
},
  "geometry": {"coordinates":[-2.25855347306764,51.34924188955994],"type":"Point"}
}