{
  "type": "Feature",
  "properties": {
    "date:inception_lower": "2009-08-01",
    "date:inception_upper": "2009-08-01",
    "iso:country": "GB",
    "wof:name": "KY9 1EJ",
    "wof:placetype": "postalcode"
  },
  "geometry": {"coordinates":[-2.826023,56.19038],"type":"Point"}
}
