{
  "type": "Feature",
  "properties": {
    "iso:country":"GB",
    "wof:name":"B65 8HP",
    "wof:placetype":"postalcode"
},
  "geometry": {"coordinates":[-2.05972936840211,52.48590738036835],"type":"Point"}
}