{
  "type": "Feature",
  "properties": {
    "iso:country": "GB",
    "wof:name": "B65 8HP",
    "wof:placetype": "postalcode"
  },
  "geometry": {"coordinates":[-2.059729,52.485907],"type":"Point"}
}
