{
  "type": "Feature",
  "properties": {
    "iso:country":"GB",
    "wof:name":"GU32 1QD",
    "wof:placetype":"postalcode"
},
  "geometry": {"coordinates":[-1.02925183835508,50.99368626952855],"type":"Point"}
}