{
  "type": "Feature",
  "properties": {
    "date:inception_lower": "1990-02-01",
    "date:inception_upper": "1990-02-01",
    "iso:country": "GB",
    "wof:name": "BL3 5LE",
    "wof:placetype": "postalcode"
  },
  "geometry": {"coordinates":[-2.442077,53.570279],"type":"Point"}
}
