{
  "type": "Feature",
  "properties": {
    "iso:country":"GB",
    "wof:name":"BL3 5LE",
    "wof:placetype":"postalcode"
},
  "geometry": {"coordinates":[-2.44260707697543,53.57024266941685],"type":"Point"}
}