{
  "type": "Feature",
  "properties": {
    "iso:country": "GB",
    "wof:name": "BL3 5LE",
    "wof:placetype": "postalcode"
  },
  "geometry": {"coordinates":[-2.442605,53.570259],"type":"Point"}
}
