{
  "type": "Feature",
  "properties": {
    "iso:country":"GB",
    "wof:name":"IP30 9RT",
    "wof:placetype":"postalcode"
},
  "geometry": {"coordinates":[0.90530061223481,52.21728209304081],"type":"Point"}
}