{
  "type": "Feature",
  "properties": {
    "iso:country": "GB",
    "wof:name": "IP30 9RT",
    "wof:placetype": "postalcode"
  },
  "geometry": {"coordinates":[0.905048,52.217189],"type":"Point"}
}
