{
  "type": "Feature",
  "properties": {
    "iso:country":"GB",
    "wof:name":"NR10 5PH",
    "wof:placetype":"postalcode"
},
  "geometry": {"coordinates":[1.26326205145963,52.76218400111924],"type":"Point"}
}