{
  "type": "Feature",
  "properties": {
    "iso:country": "GB",
    "wof:name": "DG9 8RE",
    "wof:placetype": "postalcode"
  },
  "geometry": {"coordinates":[-5.028703,54.986002],"type":"Point"}
}
