{
  "type": "Feature",
  "properties": {
    "iso:country":"GB",
    "wof:name":"DG9 8RE",
    "wof:placetype":"postalcode"
},
  "geometry": {"coordinates":[-5.02870267560049,54.98600206835541],"type":"Point"}
}