{
  "type": "Feature",
  "properties": {
    "iso:country": "GB",
    "wof:name": "GL3 2AP",
    "wof:placetype": "postalcode"
  },
  "geometry": {"coordinates":[-2.179751,51.889245],"type":"Point"}
}
