{
  "type": "Feature",
  "properties": {
    "iso:country":"GB",
    "wof:name":"S81 9RY",
    "wof:placetype":"postalcode"
},
  "geometry": {"coordinates":[-1.11883066044499,53.37967542268863],"type":"Point"}
}