{
  "type": "Feature",
  "properties": {
    "iso:country":"GB",
    "wof:name":"GU34 3PA",
    "wof:placetype":"postalcode"
},
  "geometry": {"coordinates":[-1.04082888306299,51.04036287216162],"type":"Point"}
}