{
  "type": "Feature",
  "properties": {
    "date:inception_lower":"1980-01-01",
    "date:inception_upper":"1980-01-31",
    "iso:country":"GB",
    "wof:name":"GU34 3PA",
    "wof:placetype":"postalcode"
},
  "geometry": {"coordinates":[-1.040829,51.040363],"type":"Point"}
}