{
  "type": "Feature",
  "properties": {
    "iso:country":"GB",
    "wof:name":"SP5 5PH",
    "wof:placetype":"postalcode"
},
  "geometry": {"coordinates":[-2.00632698104889,50.95433810327641],"type":"Point"}
}