{
  "type": "Feature",
  "properties": {
    "date:inception_lower": "1992-08-01",
    "date:inception_upper": "1992-08-01",
    "iso:country": "GB",
    "wof:name": "SP5 5PH",
    "wof:placetype": "postalcode"
  },
  "geometry": {"coordinates":[-2.00632,50.954332],"type":"Point"}
}
