{
  "type": "Feature",
  "properties": {
    "iso:country": "GB",
    "wof:name": "SP5 5PH",
    "wof:placetype": "postalcode"
  },
  "geometry": {"coordinates":[-2.006334,50.954287],"type":"Point"}
}
