{
  "type": "Feature",
  "properties": {
    "iso:country":"GB",
    "wof:name":"TS26 8LZ",
    "wof:placetype":"postalcode"
},
  "geometry": {"coordinates":[-1.23307360045282,54.68718924054893],"type":"Point"}
}