{
  "type": "Feature",
  "properties": {
    "iso:country": "GB",
    "wof:name": "HA2 9HF",
    "wof:placetype": "postalcode"
  },
  "geometry": {"coordinates":[-0.381257,51.562579],"type":"Point"}
}
