{
  "type": "Feature",
  "properties": {
    "iso:country":"GB",
    "wof:name":"PE7 1PQ",
    "wof:placetype":"postalcode"
},
  "geometry": {"coordinates":[-0.12988677658991,52.56072316424957],"type":"Point"}
}