{
  "type": "Feature",
  "properties": {
    "date:inception_lower": "1990-02-01",
    "date:inception_upper": "1990-02-01",
    "iso:country": "GB",
    "wof:name": "PE7 1PQ",
    "wof:placetype": "postalcode"
  },
  "geometry": {"coordinates":[-0.129887,52.560723],"type":"Point"}
}
