{
  "type": "Feature",
  "properties": {
    "iso:country":"GB",
    "wof:name":"S42 6LG",
    "wof:placetype":"postalcode"
},
  "geometry": {"coordinates":[-1.4094278441655,53.18193102650677],"type":"Point"}
}