{
  "type": "Feature",
  "properties": {
    "iso:country": "GB",
    "wof:name": "S42 6LG",
    "wof:placetype": "postalcode"
  },
  "geometry": {"coordinates":[-1.409428,53.181931],"type":"Point"}
}
