{
  "type": "Feature",
  "properties": {
    "iso:country": "GB",
    "wof:name": "LE6 0YA",
    "wof:placetype": "postalcode"
  },
  "geometry": {"coordinates":[-1.220258,52.655146],"type":"Point"}
}
