{
  "type": "Feature",
  "properties": {
    "iso:country":"GB",
    "wof:name":"NG9 3DT",
    "wof:placetype":"postalcode"
},
  "geometry": {"coordinates":[-1.25209033845705,52.92736068228718],"type":"Point"}
}