{
  "type": "Feature",
  "properties": {
    "iso:country": "GB",
    "wof:name": "LS23 6FA",
    "wof:placetype": "postalcode"
  },
  "geometry": {"coordinates":[-1.353645,53.9082],"type":"Point"}
}
