{
  "type": "Feature",
  "properties": {
    "iso:country":"GB",
    "wof:name":"S8 7JH",
    "wof:placetype":"postalcode"
},
  "geometry": {"coordinates":[-1.48822050488108,53.32060732710731],"type":"Point"}
}