{
  "type": "Feature",
  "properties": {
    "iso:country": "GB",
    "wof:name": "S8 7JH",
    "wof:placetype": "postalcode"
  },
  "geometry": {"coordinates":[-1.48822,53.320607],"type":"Point"}
}
