{
  "type": "Feature",
  "properties": {
    "iso:country": "GB",
    "wof:name": "CM19 4AR",
    "wof:placetype": "postalcode"
  },
  "geometry": {"coordinates":[0.085057,51.767894],"type":"Point"}
}
