{
  "type": "Feature",
  "properties": {
    "iso:country": "GB",
    "wof:name": "CV11 6RE",
    "wof:placetype": "postalcode"
  },
  "geometry": {"coordinates":[-1.374315,52.504641],"type":"Point"}
}
