{
  "type": "Feature",
  "properties": {
    "date:inception_lower": "1997-12-01",
    "date:inception_upper": "1997-12-01",
    "iso:country": "GB",
    "wof:name": "BS34 6BU",
    "wof:placetype": "postalcode"
  },
  "geometry": {"coordinates":[-2.566203,51.534915],"type":"Point"}
}
