{
  "type": "Feature",
  "properties": {
    "iso:country":"GB",
    "wof:name":"PR25 2NE",
    "wof:placetype":"postalcode"
},
  "geometry": {"coordinates":[-2.70295573815773,53.69326927193158],"type":"Point"}
}