{
  "type": "Feature",
  "properties": {
    "date:inception_lower": "2001-06-01",
    "date:inception_upper": "2001-06-01",
    "iso:country": "GB",
    "wof:name": "PR25 2NE",
    "wof:placetype": "postalcode"
  },
  "geometry": {"coordinates":[-2.702956,53.693269],"type":"Point"}
}
