{
  "type": "Feature",
  "properties": {
    "iso:country":"GB",
    "wof:name":"S65 2ND",
    "wof:placetype":"postalcode"
},
  "geometry": {"coordinates":[-1.32517389745949,53.42719478351929],"type":"Point"}
}