{
  "type": "Feature",
  "properties": {
    "iso:country": "GB",
    "wof:name": "S65 2ND",
    "wof:placetype": "postalcode"
  },
  "geometry": {"coordinates":[-1.325174,53.427195],"type":"Point"}
}
