{
  "type": "Feature",
  "properties": {
    "date:inception_lower": "1980-01-01",
    "date:inception_upper": "1980-01-01",
    "iso:country": "GB",
    "wof:name": "S65 2ND",
    "wof:placetype": "postalcode"
  },
  "geometry": {"coordinates":[-1.325174,53.427195],"type":"Point"}
}
