{
  "type": "Feature",
  "properties": {
    "iso:country":"GB",
    "wof:name":"UB8 3JG",
    "wof:placetype":"postalcode"
},
  "geometry": {"coordinates":[-0.44186246768724,51.51834018113833],"type":"Point"}
}