{
  "type": "Feature",
  "properties": {
    "iso:country":"GB",
    "wof:name":"SK22 4PW",
    "wof:placetype":"postalcode"
},
  "geometry": {"coordinates":[-1.98816581712032,53.35908702635233],"type":"Point"}
}