{
  "type": "Feature",
  "properties": {
    "date:inception_lower": "1996-12-01",
    "date:inception_upper": "1996-12-01",
    "iso:country": "GB",
    "wof:name": "SK22 4PW",
    "wof:placetype": "postalcode"
  },
  "geometry": {"coordinates":[-1.988165,53.359103],"type":"Point"}
}
