{
  "type": "Feature",
  "properties": {
    "iso:country":"GB",
    "wof:name":"TA6 4DW",
    "wof:placetype":"postalcode"
},
  "geometry": {"coordinates":[-2.97475387177668,51.13040510801136],"type":"Point"}
}