{
  "type": "Feature",
  "properties": {
    "iso:country":"GB",
    "wof:name":"TW2 7QY",
    "wof:placetype":"postalcode"
},
  "geometry": {"coordinates":[-0.33980289262986,51.454083769639],"type":"Point"}
}