{
  "type": "Feature",
  "properties": {
    "date:inception_lower": "1980-01-01",
    "date:inception_upper": "1980-01-01",
    "iso:country": "GB",
    "wof:name": "TW2 7QY",
    "wof:placetype": "postalcode"
  },
  "geometry": {"coordinates":[-0.339803,51.454084],"type":"Point"}
}
