{
  "type": "Feature",
  "properties": {
    "iso:country":"GB",
    "wof:name":"W1T 1UW",
    "wof:placetype":"postalcode"
},
  "geometry": {"coordinates":[-0.13260223331289,51.51673800730983],"type":"Point"}
}