{
  "type": "Feature",
  "properties": {
    "iso:country":"GB",
    "wof:name":"CH47 0LT",
    "wof:placetype":"postalcode"
},
  "geometry": {"coordinates":[-3.16361935496691,53.39760319108884],"type":"Point"}
}