{
  "type": "Feature",
  "properties": {
    "iso:country":"GB",
    "wof:name":"FY7 8JW",
    "wof:placetype":"postalcode"
},
  "geometry": {"coordinates":[-3.04306917505326,53.89617489478535],"type":"Point"}
}