{
  "type": "Feature",
  "properties": {
    "iso:country": "GB",
    "wof:name": "FY7 8JW",
    "wof:placetype": "postalcode"
  },
  "geometry": {"coordinates":[-3.043013,53.895452],"type":"Point"}
}
