{
  "type": "Feature",
  "properties": {
    "date:inception_lower":"1980-01-01",
    "date:inception_upper":"1980-01-31",
    "iso:country":"GB",
    "wof:name":"FY7 8JW",
    "wof:placetype":"postalcode"
},
  "geometry": {"coordinates":[-3.043013,53.895452],"type":"Point"}
}