{
  "type": "Feature",
  "properties": {
    "iso:country":"GB",
    "wof:name":"PO7 4QN",
    "wof:placetype":"postalcode"
},
  "geometry": {"coordinates":[-1.08376433576615,50.92080123365822],"type":"Point"}
}