{
  "type": "Feature",
  "properties": {
    "iso:country": "GB",
    "wof:name": "KT15 3JS",
    "wof:placetype": "postalcode"
  },
  "geometry": {"coordinates":[-0.48467,51.354828],"type":"Point"}
}
