{
  "type": "Feature",
  "properties": {
    "iso:country":"GB",
    "wof:name":"PE28 5RG",
    "wof:placetype":"postalcode"
},
  "geometry": {"coordinates":[-0.33407619438038,52.41861412367665],"type":"Point"}
}