{
  "type": "Feature",
  "properties": {
    "iso:country": "GB",
    "wof:name": "PO19 3PU",
    "wof:placetype": "postalcode"
  },
  "geometry": {"coordinates":[-0.815375,50.835977],"type":"Point"}
}
