{
  "type": "Feature",
  "properties": {
    "date:inception_lower":"2004-09-01",
    "date:inception_upper":"2004-09-30",
    "iso:country":"GB",
    "wof:name":"NW6 7SL",
    "wof:placetype":"postalcode"
},
  "geometry": {"coordinates":[-0.206727,51.540987],"type":"Point"}
}