{
  "type": "Feature",
  "properties": {
    "iso:country":"GB",
    "wof:name":"NW6 7SL",
    "wof:placetype":"postalcode"
},
  "geometry": {"coordinates":[-0.20672743247506,51.54098721574877],"type":"Point"}
}