{
  "type": "Feature",
  "properties": {
    "iso:country": "GB",
    "wof:name": "NW6 7SL",
    "wof:placetype": "postalcode"
  },
  "geometry": {"coordinates":[-0.206727,51.540987],"type":"Point"}
}
