{
  "type": "Feature",
  "properties": {
    "date:inception_lower":"1980-01-01",
    "date:inception_upper":"1980-01-31",
    "iso:country":"GB",
    "wof:name":"SK10 2PN",
    "wof:placetype":"postalcode"
},
  "geometry": {"coordinates":[-2.107518,53.266114],"type":"Point"}
}