{
  "type": "Feature",
  "properties": {
    "iso:country": "GB",
    "wof:name": "LE67 2NS",
    "wof:placetype": "postalcode"
  },
  "geometry": {"coordinates":[-1.394286,52.726777],"type":"Point"}
}
