{
  "type": "Feature",
  "properties": {
    "iso:country":"GB",
    "wof:name":"SL6 5HQ",
    "wof:placetype":"postalcode"
},
  "geometry": {"coordinates":[-0.75127808287625,51.52891141271102],"type":"Point"}
}