{
  "type": "Feature",
  "properties": {
    "iso:country":"GB",
    "wof:name":"TN4 9TP",
    "wof:placetype":"postalcode"
},
  "geometry": {"coordinates":[0.26009161956274,51.14070829841763],"type":"Point"}
}