{
  "type": "Feature",
  "properties": {
    "iso:country": "GB",
    "wof:name": "TN4 9TP",
    "wof:placetype": "postalcode"
  },
  "geometry": {"coordinates":[0.26008,51.140788],"type":"Point"}
}
