{
  "type": "Feature",
  "properties": {
    "iso:country":"GB",
    "wof:name":"SO23 7NU",
    "wof:placetype":"postalcode"
},
  "geometry": {"coordinates":[-1.3012919459141,51.1059198964339],"type":"Point"}
}