{
  "type": "Feature",
  "properties": {
    "iso:country": "GB",
    "wof:name": "SO23 7NU",
    "wof:placetype": "postalcode"
  },
  "geometry": {"coordinates":[-1.301292,51.10592],"type":"Point"}
}
