{
  "type": "Feature",
  "properties": {
    "iso:country": "GB",
    "wof:name": "TA2 6UJ",
    "wof:placetype": "postalcode"
  },
  "geometry": {"coordinates":[-3.125981,51.026739],"type":"Point"}
}
