{
  "type": "Feature",
  "properties": {
    "date:inception_lower":"1981-09-01",
    "date:inception_upper":"1981-09-30",
    "iso:country":"GB",
    "wof:name":"TA2 6UJ",
    "wof:placetype":"postalcode"
},
  "geometry": {"coordinates":[-3.125981,51.026739],"type":"Point"}
}