{
  "type": "Feature",
  "properties": {
    "iso:country":"GB",
    "wof:name":"OL2 7JR",
    "wof:placetype":"postalcode"
},
  "geometry": {"coordinates":[-2.10094348113816,53.57964835477316],"type":"Point"}
}