{
  "type": "Feature",
  "properties": {
    "iso:country": "GB",
    "wof:name": "OL2 7JR",
    "wof:placetype": "postalcode"
  },
  "geometry": {"coordinates":[-2.100943,53.579648],"type":"Point"}
}
