{
  "type": "Feature",
  "properties": {
    "iso:country":"GB",
    "wof:name":"SE28 8DB",
    "wof:placetype":"postalcode"
},
  "geometry": {"coordinates":[0.11180169141633,51.5020073482794],"type":"Point"}
}