{
  "type": "Feature",
  "properties": {
    "iso:country": "GB",
    "wof:name": "LS10 1JX",
    "wof:placetype": "postalcode"
  },
  "geometry": {"coordinates":[-1.532359,53.78644],"type":"Point"}
}
