{
  "type": "Feature",
  "properties": {
    "iso:country":"GB",
    "wof:name":"B63 4ES",
    "wof:placetype":"postalcode"
},
  "geometry": {"coordinates":[-2.06551930272785,52.44814639039082],"type":"Point"}
}