{
  "type": "Feature",
  "properties": {
    "iso:country": "GB",
    "wof:name": "MK7 7HF",
    "wof:placetype": "postalcode"
  },
  "geometry": {"coordinates":[-0.702789,52.014048],"type":"Point"}
}
