{
  "type": "Feature",
  "properties": {
    "date:inception_lower": "1980-01-01",
    "date:inception_upper": "1980-01-01",
    "iso:country": "GB",
    "wof:name": "SA48 7RH",
    "wof:placetype": "postalcode"
  },
  "geometry": {"coordinates":[-4.243768,52.188502],"type":"Point"}
}
