{
  "type": "Feature",
  "properties": {
    "iso:country":"GB",
    "wof:name":"SA48 7RH",
    "wof:placetype":"postalcode"
},
  "geometry": {"coordinates":[-4.24376852556435,52.18850237214571],"type":"Point"}
}