{
  "type": "Feature",
  "properties": {
    "iso:country":"GB",
    "wof:name":"E17 9LJ",
    "wof:placetype":"postalcode"
},
  "geometry": {"coordinates":[-0.01164483156893,51.58193360336943],"type":"Point"}
}