{
  "type": "Feature",
  "properties": {
    "iso:country": "GB",
    "wof:name": "HG2 7JW",
    "wof:placetype": "postalcode"
  },
  "geometry": {"coordinates":[-1.497013,53.998773],"type":"Point"}
}
