{
  "type": "Feature",
  "properties": {
    "iso:country":"GB",
    "wof:name":"HG2 7JW",
    "wof:placetype":"postalcode"
},
  "geometry": {"coordinates":[-1.49701350678095,53.99877347778548],"type":"Point"}
}