{
  "type": "Feature",
  "properties": {
    "iso:country":"GB",
    "wof:name":"OX20 1QN",
    "wof:placetype":"postalcode"
},
  "geometry": {"coordinates":[-1.34480995657442,51.84319800223697],"type":"Point"}
}