{
  "type": "Feature",
  "properties": {
    "date:inception_lower": "2018-04-01",
    "date:inception_upper": "2018-04-01",
    "iso:country": "GB",
    "wof:name": "OX20 1QN",
    "wof:placetype": "postalcode"
  },
  "geometry": {"coordinates":[-1.344605,51.843132],"type":"Point"}
}
