{
  "type": "Feature",
  "properties": {
    "date:inception_lower":"2015-11-01",
    "date:inception_upper":"2015-11-30",
    "iso:country":"GB",
    "wof:name":"BS39 4DR",
    "wof:placetype":"postalcode"
},
  "geometry": {"coordinates":[-2.547328,51.367544],"type":"Point"}
}