{
  "type": "Feature",
  "properties": {
    "iso:country":"GB",
    "wof:name":"BS39 4DR",
    "wof:placetype":"postalcode"
},
  "geometry": {"coordinates":[-2.54732835545931,51.36754437318228],"type":"Point"}
}