{
  "type": "Feature",
  "properties": {
    "date:inception_lower": "2012-05-01",
    "date:inception_upper": "2012-05-01",
    "iso:country": "GB",
    "wof:name": "SP11 6RR",
    "wof:placetype": "postalcode"
  },
  "geometry": {"coordinates":[-1.464037,51.229466],"type":"Point"}
}
