{
  "type": "Feature",
  "properties": {
    "iso:country": "GB",
    "wof:name": "SP11 6RR",
    "wof:placetype": "postalcode"
  },
  "geometry": {"coordinates":[-1.464037,51.229466],"type":"Point"}
}
