{
  "type": "Feature",
  "properties": {
    "iso:country":"GB",
    "wof:name":"ME1 1YS",
    "wof:placetype":"postalcode"
},
  "geometry": {"coordinates":[0.49112322104359,51.3797512994221],"type":"Point"}
}