{
  "type": "Feature",
  "properties": {
    "date:inception_lower":"1999-06-01",
    "date:inception_upper":"1999-06-30",
    "iso:country":"GB",
    "wof:name":"ME1 1YS",
    "wof:placetype":"postalcode"
},
  "geometry": {"coordinates":[0.491153,51.379751],"type":"Point"}
}