{
  "type": "Feature",
  "properties": {
    "iso:country": "GB",
    "wof:name": "ME1 1YS",
    "wof:placetype": "postalcode"
  },
  "geometry": {"coordinates":[0.491153,51.379751],"type":"Point"}
}
