{
  "type": "Feature",
  "properties": {
    "iso:country": "GB",
    "wof:name": "SO45 1DG",
    "wof:placetype": "postalcode"
  },
  "geometry": {"coordinates":[-1.349194,50.827206],"type":"Point"}
}
