{
  "type": "Feature",
  "properties": {
    "iso:country":"GB",
    "wof:name":"NR8 6ES",
    "wof:placetype":"postalcode"
},
  "geometry": {"coordinates":[1.22234262577295,52.6824621541273],"type":"Point"}
}