{
  "type": "Feature",
  "properties": {
    "iso:country": "GB",
    "wof:name": "DE55 5NP",
    "wof:placetype": "postalcode"
  },
  "geometry": {"coordinates":[-1.339197,53.157058],"type":"Point"}
}
