{
  "type": "Feature",
  "properties": {
    "iso:country": "GB",
    "wof:name": "DE55 5NP",
    "wof:placetype": "postalcode"
  },
  "geometry": {"coordinates":[-1.338397,53.154511],"type":"Point"}
}
