{
  "type": "Feature",
  "properties": {
    "iso:country":"GB",
    "wof:name":"DN11 8PF",
    "wof:placetype":"postalcode"
},
  "geometry": {"coordinates":[-1.07510705999966,53.42232966159466],"type":"Point"}
}