{
  "type": "Feature",
  "properties": {
    "date:inception_lower":"2004-01-01",
    "date:inception_upper":"2004-01-31",
    "iso:country":"GB",
    "wof:name":"SN1 5JJ",
    "wof:placetype":"postalcode"
},
  "geometry": {"coordinates":[-1.796491,51.555564],"type":"Point"}
}