{
  "type": "Feature",
  "properties": {
    "iso:country":"GB",
    "wof:name":"SN1 5JJ",
    "wof:placetype":"postalcode"
},
  "geometry": {"coordinates":[-1.79649089849209,51.55556368405787],"type":"Point"}
}