{
  "type": "Feature",
  "properties": {
    "date:inception_lower": "1980-01-01",
    "date:inception_upper": "1980-01-01",
    "iso:country": "GB",
    "wof:name": "M5 3HN",
    "wof:placetype": "postalcode"
  },
  "geometry": {"coordinates":[-2.276331,53.474099],"type":"Point"}
}
