{
  "type": "Feature",
  "properties": {
    "iso:country":"GB",
    "wof:name":"WV4 6GB",
    "wof:placetype":"postalcode"
},
  "geometry": {"coordinates":[-2.12438567870243,52.55672431543749],"type":"Point"}
}