{
  "type": "Feature",
  "properties": {
    "iso:country":"GB",
    "wof:name":"LE9 7AX",
    "wof:placetype":"postalcode"
},
  "geometry": {"coordinates":[-1.30052699126922,52.57749699545175],"type":"Point"}
}