{
  "type": "Feature",
  "properties": {
    "iso:country": "GB",
    "wof:name": "BD15 9JD",
    "wof:placetype": "postalcode"
  },
  "geometry": {"coordinates":[-1.835994,53.80714],"type":"Point"}
}
