{
  "type": "Feature",
  "properties": {
    "iso:country":"GB",
    "wof:name":"WN2 2LJ",
    "wof:placetype":"postalcode"
},
  "geometry": {"coordinates":[-2.59439998091933,53.54153143720114],"type":"Point"}
}