{
  "type": "Feature",
  "properties": {
    "date:inception_lower": "1995-07-01",
    "date:inception_upper": "1995-07-01",
    "iso:country": "GB",
    "wof:name": "RG42 5JG",
    "wof:placetype": "postalcode"
  },
  "geometry": {"coordinates":[-0.790201,51.434645],"type":"Point"}
}
