{
  "type": "Feature",
  "properties": {
    "iso:country":"GB",
    "wof:name":"NG5 1LR",
    "wof:placetype":"postalcode"
},
  "geometry": {"coordinates":[-1.17248442259909,52.99160235856921],"type":"Point"}
}