{
  "type": "Feature",
  "properties": {
    "date:inception_lower": "1994-05-01",
    "date:inception_upper": "1994-05-01",
    "iso:country": "GB",
    "wof:name": "NG5 1LR",
    "wof:placetype": "postalcode"
  },
  "geometry": {"coordinates":[-1.172484,52.991602],"type":"Point"}
}
