{
  "type": "Feature",
  "properties": {
    "iso:country": "GB",
    "wof:name": "RH17 6FJ",
    "wof:placetype": "postalcode"
  },
  "geometry": {"coordinates":[-0.197489,51.057105],"type":"Point"}
}
