{
  "type": "Feature",
  "properties": {
    "date:inception_lower": "1980-01-01",
    "date:inception_upper": "1980-01-01",
    "iso:country": "GB",
    "wof:name": "SN1 4HU",
    "wof:placetype": "postalcode"
  },
  "geometry": {"coordinates":[-1.785846,51.549494],"type":"Point"}
}
