{
  "type": "Feature",
  "properties": {
    "iso:country":"GB",
    "wof:name":"SN1 4HU",
    "wof:placetype":"postalcode"
},
  "geometry": {"coordinates":[-1.78584581352838,51.5494935549652],"type":"Point"}
}