{
  "type": "Feature",
  "properties": {
    "iso:country": "GB",
    "wof:name": "SN1 4HU",
    "wof:placetype": "postalcode"
  },
  "geometry": {"coordinates":[-1.785846,51.549494],"type":"Point"}
}
