{
  "type": "Feature",
  "properties": {
    "iso:country":"GB",
    "wof:name":"UB5 5NZ",
    "wof:placetype":"postalcode"
},
  "geometry": {"coordinates":[-0.38708959676369,51.53596199170411],"type":"Point"}
}