{
  "type": "Feature",
  "properties": {
    "date:inception_lower":"1980-01-01",
    "date:inception_upper":"1980-01-31",
    "iso:country":"GB",
    "wof:name":"LN11 9RD",
    "wof:placetype":"postalcode"
},
  "geometry": {"coordinates":[-0.154673,53.330071],"type":"Point"}
}