{
  "type": "Feature",
  "properties": {
    "iso:country": "GB",
    "wof:name": "LN11 9RD",
    "wof:placetype": "postalcode"
  },
  "geometry": {"coordinates":[-0.154673,53.330071],"type":"Point"}
}
