{
  "type": "Feature",
  "properties": {
    "iso:country":"GB",
    "wof:name":"LN11 9RD",
    "wof:placetype":"postalcode"
},
  "geometry": {"coordinates":[-0.15467310572016,53.33007135290988],"type":"Point"}
}