{
  "type": "Feature",
  "properties": {
    "iso:country":"GB",
    "wof:name":"LA16 7EJ",
    "wof:placetype":"postalcode"
},
  "geometry": {"coordinates":[-3.19304459585693,54.18882650137461],"type":"Point"}
}