{
  "type": "Feature",
  "properties": {
    "iso:country":"GB",
    "wof:name":"BS49 4LD",
    "wof:placetype":"postalcode"
},
  "geometry": {"coordinates":[-2.80560075138812,51.38600558514729],"type":"Point"}
}