{
  "type": "Feature",
  "properties": {
    "iso:country":"GB",
    "wof:name":"NG3 5FQ",
    "wof:placetype":"postalcode"
},
  "geometry": {"coordinates":[-1.13721231406582,52.97857768959477],"type":"Point"}
}