{
  "type": "Feature",
  "properties": {
    "iso:country": "GB",
    "wof:name": "S25 5JB",
    "wof:placetype": "postalcode"
  },
  "geometry": {"coordinates":[-1.229861,53.349027],"type":"Point"}
}
