{
  "type": "Feature",
  "properties": {
    "iso:country":"GB",
    "wof:name":"SE15 2LP",
    "wof:placetype":"postalcode"
},
  "geometry": {"coordinates":[-0.05539602744972,51.47632945623663],"type":"Point"}
}