{
  "type": "Feature",
  "properties": {
    "iso:country":"GB",
    "wof:name":"LE8 8DE",
    "wof:placetype":"postalcode"
},
  "geometry": {"coordinates":[-1.03948365856869,52.52904485232692],"type":"Point"}
}