{
  "type": "Feature",
  "properties": {
    "date:inception_lower": "2001-12-01",
    "date:inception_upper": "2001-12-01",
    "iso:country": "GB",
    "wof:name": "LE8 8DE",
    "wof:placetype": "postalcode"
  },
  "geometry": {"coordinates":[-1.039484,52.529045],"type":"Point"}
}
