{
  "type": "Feature",
  "properties": {
    "iso:country": "GB",
    "wof:name": "CO15 6HH",
    "wof:placetype": "postalcode"
  },
  "geometry": {"coordinates":[1.166944,51.797946],"type":"Point"}
}
