{
  "type": "Feature",
  "properties": {
    "iso:country":"GB",
    "wof:name":"CO15 6HH",
    "wof:placetype":"postalcode"
},
  "geometry": {"coordinates":[1.16694391768809,51.79794557155709],"type":"Point"}
}