{
  "type": "Feature",
  "properties": {
    "iso:country":"GB",
    "wof:name":"NG33 4EG",
    "wof:placetype":"postalcode"
},
  "geometry": {"coordinates":[-0.50151903250146,52.86071591529753],"type":"Point"}
}