{
  "type": "Feature",
  "properties": {
    "iso:country":"GB",
    "wof:name":"B34 6QA",
    "wof:placetype":"postalcode"
},
  "geometry": {"coordinates":[-1.78430213415327,52.49906756006148],"type":"Point"}
}