{
  "type": "Feature",
  "properties": {
    "iso:country": "GB",
    "wof:name": "SA73 1LR",
    "wof:placetype": "postalcode"
  },
  "geometry": {"coordinates":[-4.919901,51.712352],"type":"Point"}
}
