{
  "type": "Feature",
  "properties": {
    "iso:country":"GB",
    "wof:name":"SA73 1LR",
    "wof:placetype":"postalcode"
},
  "geometry": {"coordinates":[-4.91990075332941,51.71235193863482],"type":"Point"}
}