{
  "type": "Feature",
  "properties": {
    "iso:country":"GB",
    "wof:name":"CB9 8PJ",
    "wof:placetype":"postalcode"
},
  "geometry": {"coordinates":[0.43898626572762,52.07694290723511],"type":"Point"}
}