{
  "type": "Feature",
  "properties": {
    "iso:country":"GB",
    "wof:name":"BH23 2AB",
    "wof:placetype":"postalcode"
},
  "geometry": {"coordinates":[-1.78571945493496,50.73880810965832],"type":"Point"}
}