{
  "type": "Feature",
  "properties": {
    "iso:country":"GB",
    "wof:name":"SS14 1TD",
    "wof:placetype":"postalcode"
},
  "geometry": {"coordinates":[0.49127249038026,51.56562381809445],"type":"Point"}
}