{
  "type": "Feature",
  "properties": {
    "iso:country":"GB",
    "wof:name":"DY2 0JZ",
    "wof:placetype":"postalcode"
},
  "geometry": {"coordinates":[-2.08421986878791,52.48644980537679],"type":"Point"}
}