{
  "type": "Feature",
  "properties": {
    "date:inception_lower": "1980-01-01",
    "date:inception_upper": "1980-01-01",
    "iso:country": "GB",
    "wof:name": "PR1 4SN",
    "wof:placetype": "postalcode"
  },
  "geometry": {"coordinates":[-2.674999,53.762343],"type":"Point"}
}
