{
  "type": "Feature",
  "properties": {
    "date:inception_lower":"1980-01-01",
    "date:inception_upper":"1980-01-31",
    "iso:country":"GB",
    "wof:name":"SN16 9JN",
    "wof:placetype":"postalcode"
},
  "geometry": {"coordinates":[-2.095551,51.596386],"type":"Point"}
}