{
  "type": "Feature",
  "properties": {
    "iso:country":"GB",
    "wof:name":"CT1 3ED",
    "wof:placetype":"postalcode"
},
  "geometry": {"coordinates":[1.09575912196266,51.26895886918977],"type":"Point"}
}