{
  "type": "Feature",
  "properties": {
    "iso:country":"GB",
    "wof:name":"RH5 4ER",
    "wof:placetype":"postalcode"
},
  "geometry": {"coordinates":[-0.32925443937863,51.20206121670829],"type":"Point"}
}