{
  "type": "Feature",
  "properties": {
    "iso:country": "GB",
    "wof:name": "PA34 4RJ",
    "wof:placetype": "postalcode"
  },
  "geometry": {"coordinates":[-5.618314,56.28436],"type":"Point"}
}
