{
  "type": "Feature",
  "properties": {
    "date:inception_lower": "1980-06-01",
    "date:inception_upper": "1980-06-01",
    "iso:country": "GB",
    "wof:name": "PA34 4RJ",
    "wof:placetype": "postalcode"
  },
  "geometry": {"coordinates":[-5.618314,56.28436],"type":"Point"}
}
