{
  "type": "Feature",
  "properties": {
    "iso:country":"GB",
    "wof:name":"CF83 1NG",
    "wof:placetype":"postalcode"
},
  "geometry": {"coordinates":[-3.23643126770312,51.54973527802552],"type":"Point"}
}