{
  "type": "Feature",
  "properties": {
    "iso:country":"GB",
    "wof:name":"M11 2HU",
    "wof:placetype":"postalcode"
},
  "geometry": {"coordinates":[-2.1786456899987,53.47822246235152],"type":"Point"}
}