{
  "type": "Feature",
  "properties": {
    "iso:country":"GB",
    "wof:name":"SG15 6UU",
    "wof:placetype":"postalcode"
},
  "geometry": {"coordinates":[-0.2612489065339,52.02373391682556],"type":"Point"}
}