{
  "type": "Feature",
  "properties": {
    "date:inception_lower": "2023-06-01",
    "date:inception_upper": "2023-06-01",
    "iso:country": "GB",
    "wof:name": "EX2 8NE",
    "wof:placetype": "postalcode"
  },
  "geometry": {"coordinates":[-3.526272,50.696229],"type":"Point"}
}
