{
  "type": "Feature",
  "properties": {
    "date:inception_lower":"2001-06-01",
    "date:inception_upper":"2001-06-30",
    "iso:country":"GB",
    "wof:name":"OX28 1JY",
    "wof:placetype":"postalcode"
},
  "geometry": {"coordinates":[-1.487509,51.798798],"type":"Point"}
}