{
  "type": "Feature",
  "properties": {
    "iso:country": "GB",
    "wof:name": "ME5 9TR",
    "wof:placetype": "postalcode"
  },
  "geometry": {"coordinates":[0.514077,51.349636],"type":"Point"}
}
