{
  "type": "Feature",
  "properties": {
    "date:inception_lower": "2020-04-01",
    "date:inception_upper": "2020-04-01",
    "iso:country": "GB",
    "wof:name": "OL12 0WB",
    "wof:placetype": "postalcode"
  },
  "geometry": {"coordinates":[-2.154095,53.62232],"type":"Point"}
}
