{
  "type": "Feature",
  "properties": {
    "iso:country": "GB",
    "wof:name": "OL12 0WB",
    "wof:placetype": "postalcode"
  },
  "geometry": {"coordinates":[-2.154095,53.62232],"type":"Point"}
}
