{
  "type": "Feature",
  "properties": {
    "iso:country":"GB",
    "wof:name":"CF82 7HD",
    "wof:placetype":"postalcode"
},
  "geometry": {"coordinates":[-3.23663429596991,51.65552145596464],"type":"Point"}
}