{
  "type": "Feature",
  "properties": {
    "date:inception_lower": "2016-08-01",
    "date:inception_upper": "2016-08-01",
    "iso:country": "GB",
    "wof:name": "YO30 6QL",
    "wof:placetype": "postalcode"
  },
  "geometry": {"coordinates":[-1.095841,53.982027],"type":"Point"}
}
