{
  "type": "Feature",
  "properties": {
    "iso:country":"GB",
    "wof:name":"NR29 4TX",
    "wof:placetype":"postalcode"
},
  "geometry": {"coordinates":[1.68416310157632,52.69769472258351],"type":"Point"}
}