{
  "type": "Feature",
  "properties": {
    "iso:country": "GB",
    "wof:name": "NE3 4QL",
    "wof:placetype": "postalcode"
  },
  "geometry": {"coordinates":[-1.640959,54.999985],"type":"Point"}
}
