{
  "type": "Feature",
  "properties": {
    "date:inception_lower": "2018-03-01",
    "date:inception_upper": "2018-03-01",
    "iso:country": "GB",
    "wof:name": "WS13 8GE",
    "wof:placetype": "postalcode"
  },
  "geometry": {"coordinates":[-1.793919,52.693371],"type":"Point"}
}
