{
  "type": "Feature",
  "properties": {
    "iso:country":"GB",
    "wof:name":"OL6 9EZ",
    "wof:placetype":"postalcode"
},
  "geometry": {"coordinates":[-2.07564372500156,53.50289762387627],"type":"Point"}
}