{
  "type": "Feature",
  "properties": {
    "iso:country":"GB",
    "wof:name":"WN4 0SB",
    "wof:placetype":"postalcode"
},
  "geometry": {"coordinates":[-2.6728449862837,53.48960218869797],"type":"Point"}
}