{
  "type": "Feature",
  "properties": {
    "date:inception_lower": "2017-04-01",
    "date:inception_upper": "2017-04-01",
    "iso:country": "GB",
    "wof:name": "OX15 4SF",
    "wof:placetype": "postalcode"
  },
  "geometry": {"coordinates":[-1.320603,52.042158],"type":"Point"}
}
