{
  "type": "Feature",
  "properties": {
    "iso:country": "GB",
    "wof:name": "M35 9UJ",
    "wof:placetype": "postalcode"
  },
  "geometry": {"coordinates":[-2.136999,53.510771],"type":"Point"}
}
