{
  "type": "Feature",
  "properties": {
    "iso:country":"GB",
    "wof:name":"SY7 9HA",
    "wof:placetype":"postalcode"
},
  "geometry": {"coordinates":[-2.69871482554246,52.49068145650367],"type":"Point"}
}