{
  "type": "Feature",
  "properties": {
    "iso:country": "GB",
    "wof:name": "SY7 9HA",
    "wof:placetype": "postalcode"
  },
  "geometry": {"coordinates":[-2.698715,52.490681],"type":"Point"}
}
