{
  "type": "Feature",
  "properties": {
    "iso:country":"GB",
    "wof:name":"IV30 1JG",
    "wof:placetype":"postalcode"
},
  "geometry": {"coordinates":[-3.31842169312589,57.64675911126169],"type":"Point"}
}