{
  "type": "Feature",
  "properties": {
    "iso:country":"GB",
    "wof:name":"MK3 5QB",
    "wof:placetype":"postalcode"
},
  "geometry": {"coordinates":[-0.73771396731756,51.97011828917619],"type":"Point"}
}