{
  "type": "Feature",
  "properties": {
    "iso:country": "GB",
    "wof:name": "MK3 5QB",
    "wof:placetype": "postalcode"
  },
  "geometry": {"coordinates":[-0.737714,51.970118],"type":"Point"}
}
