{
  "type": "Feature",
  "properties": {
    "iso:country":"GB",
    "wof:name":"CV34 6HA",
    "wof:placetype":"postalcode"
},
  "geometry": {"coordinates":[-1.59226877245918,52.27952601489516],"type":"Point"}
}