{
  "type": "Feature",
  "properties": {
    "iso:country": "GB",
    "wof:name": "LL11 3YF",
    "wof:placetype": "postalcode"
  },
  "geometry": {"coordinates":[-3.087427,53.058896],"type":"Point"}
}
