{
  "type": "Feature",
  "properties": {
    "date:inception_lower": "1980-01-01",
    "date:inception_upper": "1980-01-01",
    "iso:country": "GB",
    "wof:name": "LL11 3YF",
    "wof:placetype": "postalcode"
  },
  "geometry": {"coordinates":[-3.087427,53.058896],"type":"Point"}
}
