{
  "type": "Feature",
  "properties": {
    "iso:country":"GB",
    "wof:name":"LL11 3YF",
    "wof:placetype":"postalcode"
},
  "geometry": {"coordinates":[-3.08742751663943,53.05889558175414],"type":"Point"}
}