{
  "type": "Feature",
  "properties": {
    "date:inception_lower": "1980-01-01",
    "date:inception_upper": "1980-01-01",
    "iso:country": "GB",
    "wof:name": "IP24 3TW",
    "wof:placetype": "postalcode"
  },
  "geometry": {"coordinates":[0.665223,52.384074],"type":"Point"}
}
