{
  "type": "Feature",
  "properties": {
    "iso:country":"GB",
    "wof:name":"SA17 5EP",
    "wof:placetype":"postalcode"
},
  "geometry": {"coordinates":[-4.22912744987737,51.80808938593981],"type":"Point"}
}