{
  "type": "Feature",
  "properties": {
    "date:inception_lower": "1980-01-01",
    "date:inception_upper": "1980-01-01",
    "iso:country": "GB",
    "wof:name": "SA17 5EP",
    "wof:placetype": "postalcode"
  },
  "geometry": {"coordinates":[-4.229127,51.808089],"type":"Point"}
}
