{
  "type": "Feature",
  "properties": {
    "iso:country":"GB",
    "wof:name":"GL4 0HJ",
    "wof:placetype":"postalcode"
},
  "geometry": {"coordinates":[-2.25066369351262,51.82749082531987],"type":"Point"}
}