{
  "type": "Feature",
  "properties": {
    "iso:country": "GB",
    "wof:name": "PO41 0TA",
    "wof:placetype": "postalcode"
  },
  "geometry": {"coordinates":[-1.453069,50.690879],"type":"Point"}
}
