{
  "type": "Feature",
  "properties": {
    "iso:country": "GB",
    "wof:name": "LA2 7ES",
    "wof:placetype": "postalcode"
  },
  "geometry": {"coordinates":[-2.540874,54.122415],"type":"Point"}
}
