{
  "type": "Feature",
  "properties": {
    "iso:country":"GB",
    "wof:name":"BD22 9QP",
    "wof:placetype":"postalcode"
},
  "geometry": {"coordinates":[-1.96057059740132,53.80969951317907],"type":"Point"}
}