{
  "type": "Feature",
  "properties": {
    "date:inception_lower": "1980-01-01",
    "date:inception_upper": "1980-01-01",
    "iso:country": "GB",
    "wof:name": "BD22 9QP",
    "wof:placetype": "postalcode"
  },
  "geometry": {"coordinates":[-1.960571,53.8097],"type":"Point"}
}
