{
  "type": "Feature",
  "properties": {
    "iso:country":"GB",
    "wof:name":"S26 5RU",
    "wof:placetype":"postalcode"
},
  "geometry": {"coordinates":[-1.28049567203156,53.3421968387867],"type":"Point"}
}