{
  "type": "Feature",
  "properties": {
    "date:inception_lower": "2022-07-01",
    "date:inception_upper": "2022-07-01",
    "iso:country": "GB",
    "wof:name": "LA6 1FY",
    "wof:placetype": "postalcode"
  },
  "geometry": {"coordinates":[-2.729337,54.121293],"type":"Point"}
}
