{
  "type": "Feature",
  "properties": {
    "iso:country":"GB",
    "wof:name":"W1J 5RF",
    "wof:placetype":"postalcode"
},
  "geometry": {"coordinates":[-0.14844265222582,51.5092645765089],"type":"Point"}
}