{
  "type": "Feature",
  "properties": {
    "iso:country": "GB",
    "wof:name": "LE15 9RW",
    "wof:placetype": "postalcode"
  },
  "geometry": {"coordinates":[-0.723876,52.59101],"type":"Point"}
}
