{
  "type": "Feature",
  "properties": {
    "iso:country":"GB",
    "wof:name":"IV7 8BE",
    "wof:placetype":"postalcode"
},
  "geometry": {"coordinates":[-4.43202212676967,57.56491314628032],"type":"Point"}
}