{
  "type": "Feature",
  "properties": {
    "iso:country":"GB",
    "wof:name":"SG1 5SP",
    "wof:placetype":"postalcode"
},
  "geometry": {"coordinates":[-0.17183553427152,51.91838964877962],"type":"Point"}
}