{
  "type": "Feature",
  "properties": {
    "date:inception_lower": "1980-01-01",
    "date:inception_upper": "1980-01-01",
    "iso:country": "GB",
    "wof:name": "WA4 4PZ",
    "wof:placetype": "postalcode"
  },
  "geometry": {"coordinates":[-2.566101,53.314847],"type":"Point"}
}
