{
  "type": "Feature",
  "properties": {
    "iso:country": "GB",
    "wof:name": "LA22 9QG",
    "wof:placetype": "postalcode"
  },
  "geometry": {"coordinates":[-3.023864,54.462186],"type":"Point"}
}
