{
  "type": "Feature",
  "properties": {
    "iso:country":"GB",
    "wof:name":"W1T 1HD",
    "wof:placetype":"postalcode"
},
  "geometry": {"coordinates":[-0.13201836137652,51.5169175527619],"type":"Point"}
}