{
  "type": "Feature",
  "properties": {
    "iso:country":"GB",
    "wof:name":"KA3 5DJ",
    "wof:placetype":"postalcode"
},
  "geometry": {"coordinates":[-4.50947036076101,55.68071939464167],"type":"Point"}
}