{
  "type": "Feature",
  "properties": {
    "date:inception_lower":"1980-01-01",
    "date:inception_upper":"1980-01-31",
    "iso:country":"GB",
    "wof:name":"LL22 8NA",
    "wof:placetype":"postalcode"
},
  "geometry": {"coordinates":[-3.637616,53.283588],"type":"Point"}
}