{
  "type": "Feature",
  "properties": {
    "iso:country": "GB",
    "wof:name": "SK13 1EB",
    "wof:placetype": "postalcode"
  },
  "geometry": {"coordinates":[-1.959973,53.461982],"type":"Point"}
}
