{
  "type": "Feature",
  "properties": {
    "iso:country": "GB",
    "wof:name": "BS22 7PJ",
    "wof:placetype": "postalcode"
  },
  "geometry": {"coordinates":[-2.92008,51.366756],"type":"Point"}
}
