{
  "type": "Feature",
  "properties": {
    "iso:country":"GB",
    "wof:name":"DT9 6RJ",
    "wof:placetype":"postalcode"
},
  "geometry": {"coordinates":[-2.58896331143193,50.92789801703248],"type":"Point"}
}