{
  "type": "Feature",
  "properties": {
    "iso:country":"GB",
    "wof:name":"LE16 7JF",
    "wof:placetype":"postalcode"
},
  "geometry": {"coordinates":[-0.92293728847494,52.48275763568656],"type":"Point"}
}