{
  "type": "Feature",
  "properties": {
    "date:inception_lower":"1998-06-01",
    "date:inception_upper":"1998-06-30",
    "iso:country":"GB",
    "wof:name":"SK3 0RA",
    "wof:placetype":"postalcode"
},
  "geometry": {"coordinates":[-2.184703,53.391537],"type":"Point"}
}