{
  "type": "Feature",
  "properties": {
    "date:inception_lower": "2003-08-01",
    "date:inception_upper": "2003-08-01",
    "iso:country": "GB",
    "wof:name": "RG1 3BB",
    "wof:placetype": "postalcode"
  },
  "geometry": {"coordinates":[-0.968383,51.456092],"type":"Point"}
}
