{
  "type": "Feature",
  "properties": {
    "iso:country": "GB",
    "wof:name": "CH66 4UD",
    "wof:placetype": "postalcode"
  },
  "geometry": {"coordinates":[-2.945386,53.28182],"type":"Point"}
}
