{
  "type": "Feature",
  "properties": {
    "iso:country":"GB",
    "wof:name":"CH66 4UD",
    "wof:placetype":"postalcode"
},
  "geometry": {"coordinates":[-2.94538583489418,53.28182013120534],"type":"Point"}
}