{
  "type": "Feature",
  "properties": {
    "date:inception_lower":"1996-12-01",
    "date:inception_upper":"1996-12-31",
    "iso:country":"GB",
    "wof:name":"M16 7UG",
    "wof:placetype":"postalcode"
},
  "geometry": {"coordinates":[-2.25466,53.458022],"type":"Point"}
}