{
  "type": "Feature",
  "properties": {
    "iso:country": "GB",
    "wof:name": "M16 7UG",
    "wof:placetype": "postalcode"
  },
  "geometry": {"coordinates":[-2.25466,53.458022],"type":"Point"}
}
