{
  "type": "Feature",
  "properties": {
    "iso:country":"GB",
    "wof:name":"M16 7UG",
    "wof:placetype":"postalcode"
},
  "geometry": {"coordinates":[-2.25466035105874,53.45802221061845],"type":"Point"}
}