{
  "type": "Feature",
  "properties": {
    "date:inception_lower":"1993-01-01",
    "date:inception_upper":"1993-01-31",
    "iso:country":"GB",
    "wof:name":"DL16 6EF",
    "wof:placetype":"postalcode"
},
  "geometry": {"coordinates":[-1.590943,54.703043],"type":"Point"}
}