{
  "type": "Feature",
  "properties": {
    "date:inception_lower":"1994-12-01",
    "date:inception_upper":"1994-12-31",
    "iso:country":"GB",
    "wof:name":"GU17 9DQ",
    "wof:placetype":"postalcode"
},
  "geometry": {"coordinates":[-0.780568,51.328005],"type":"Point"}
}