{
  "type": "Feature",
  "properties": {
    "date:inception_lower": "2021-09-01",
    "date:inception_upper": "2021-09-01",
    "iso:country": "GB",
    "wof:name": "OX11 6JR",
    "wof:placetype": "postalcode"
  },
  "geometry": {"coordinates":[-1.265422,51.616098],"type":"Point"}
}
