{
  "type": "Feature",
  "properties": {
    "iso:country":"GB",
    "wof:name":"DN14 0UG",
    "wof:placetype":"postalcode"
},
  "geometry": {"coordinates":[-1.0696397168397,53.66967373940613],"type":"Point"}
}