{
  "type": "Feature",
  "properties": {
    "date:inception_lower": "1987-10-01",
    "date:inception_upper": "1987-10-01",
    "iso:country": "GB",
    "wof:name": "DN14 0UG",
    "wof:placetype": "postalcode"
  },
  "geometry": {"coordinates":[-1.06964,53.669674],"type":"Point"}
}
