{
  "type": "Feature",
  "properties": {
    "date:inception_lower": "1982-03-01",
    "date:inception_upper": "1982-03-01",
    "iso:country": "GB",
    "wof:name": "CW10 0DX",
    "wof:placetype": "postalcode"
  },
  "geometry": {"coordinates":[-2.443493,53.179313],"type":"Point"}
}
