{
  "type": "Feature",
  "properties": {
    "iso:country":"GB",
    "wof:name":"CR4 4GA",
    "wof:placetype":"postalcode"
},
  "geometry": {"coordinates":[-0.17063040517908,51.39921116419017],"type":"Point"}
}