{
  "type": "Feature",
  "properties": {
    "iso:country": "GB",
    "wof:name": "CR4 4GA",
    "wof:placetype": "postalcode"
  },
  "geometry": {"coordinates":[-0.17063,51.399211],"type":"Point"}
}
