{
  "type": "Feature",
  "properties": {
    "iso:country": "GB",
    "wof:name": "TQ14 9JP",
    "wof:placetype": "postalcode"
  },
  "geometry": {"coordinates":[-3.503853,50.551198],"type":"Point"}
}
