{
  "type": "Feature",
  "properties": {
    "iso:country":"GB",
    "wof:name":"CT3 1TP",
    "wof:placetype":"postalcode"
},
  "geometry": {"coordinates":[1.16428245500142,51.27584127715659],"type":"Point"}
}