{
  "type": "Feature",
  "properties": {
    "iso:country":"GB",
    "wof:name":"SE18 2EX",
    "wof:placetype":"postalcode"
},
  "geometry": {"coordinates":[0.08566436277635,51.47519094021832],"type":"Point"}
}