{
  "type": "Feature",
  "properties": {
    "iso:country":"GB",
    "wof:name":"LL55 4SZ",
    "wof:placetype":"postalcode"
},
  "geometry": {"coordinates":[-4.12448571010195,53.11885858062912],"type":"Point"}
}