{
  "type": "Feature",
  "properties": {
    "date:inception_lower": "2003-06-01",
    "date:inception_upper": "2003-06-01",
    "iso:country": "GB",
    "wof:name": "LL55 4SZ",
    "wof:placetype": "postalcode"
  },
  "geometry": {"coordinates":[-4.124486,53.118859],"type":"Point"}
}
