{
  "type": "Feature",
  "properties": {
    "date:inception_lower": "2015-06-01",
    "date:inception_upper": "2015-06-01",
    "iso:country": "GB",
    "wof:name": "PL31 2GH",
    "wof:placetype": "postalcode"
  },
  "geometry": {"coordinates":[-4.705441,50.464164],"type":"Point"}
}
