{
  "type": "Feature",
  "properties": {
    "iso:country":"GB",
    "wof:name":"PL31 2GH",
    "wof:placetype":"postalcode"
},
  "geometry": {"coordinates":[-4.70522887364666,50.4643497111224],"type":"Point"}
}