{
  "type": "Feature",
  "properties": {
    "date:inception_lower": "1980-01-01",
    "date:inception_upper": "1980-01-01",
    "iso:country": "GB",
    "wof:name": "EX22 7TR",
    "wof:placetype": "postalcode"
  },
  "geometry": {"coordinates":[-4.435627,50.893788],"type":"Point"}
}
