{
  "type": "Feature",
  "properties": {
    "iso:country":"GB",
    "wof:name":"EX22 7TR",
    "wof:placetype":"postalcode"
},
  "geometry": {"coordinates":[-4.43562714250246,50.89378808886156],"type":"Point"}
}