{
  "type": "Feature",
  "properties": {
    "iso:country": "GB",
    "wof:name": "SS1 2PN",
    "wof:placetype": "postalcode"
  },
  "geometry": {"coordinates":[0.731927,51.540835],"type":"Point"}
}
