{
  "type": "Feature",
  "properties": {
    "iso:country":"GB",
    "wof:name":"SE6 2SW",
    "wof:placetype":"postalcode"
},
  "geometry": {"coordinates":[-0.01223076640549,51.43075879594696],"type":"Point"}
}