{
  "type": "Feature",
  "properties": {
    "iso:country":"GB",
    "wof:name":"B47 5NB",
    "wof:placetype":"postalcode"
},
  "geometry": {"coordinates":[-1.88186734752572,52.39789652617652],"type":"Point"}
}