{
  "type": "Feature",
  "properties": {
    "iso:country":"GB",
    "wof:name":"EH19 2DX",
    "wof:placetype":"postalcode"
},
  "geometry": {"coordinates":[-3.09848927070314,55.87975042242451],"type":"Point"}
}