{
  "type": "Feature",
  "properties": {
    "date:inception_lower": "1980-01-01",
    "date:inception_upper": "1980-01-01",
    "iso:country": "GB",
    "wof:name": "EH19 2DX",
    "wof:placetype": "postalcode"
  },
  "geometry": {"coordinates":[-3.098489,55.87975],"type":"Point"}
}
