{
  "type": "Feature",
  "properties": {
    "iso:country":"GB",
    "wof:name":"LN13 0BT",
    "wof:placetype":"postalcode"
},
  "geometry": {"coordinates":[0.10101821548256,53.25180572140139],"type":"Point"}
}