{
  "type": "Feature",
  "properties": {
    "iso:country": "GB",
    "wof:name": "LN13 0BT",
    "wof:placetype": "postalcode"
  },
  "geometry": {"coordinates":[0.101018,53.251806],"type":"Point"}
}
