{
  "type": "Feature",
  "properties": {
    "iso:country":"GB",
    "wof:name":"WS7 1QA",
    "wof:placetype":"postalcode"
},
  "geometry": {"coordinates":[-1.93863308279796,52.69028977690538],"type":"Point"}
}