{
  "type": "Feature",
  "properties": {
    "iso:country":"GB",
    "wof:name":"DY2 8NA",
    "wof:placetype":"postalcode"
},
  "geometry": {"coordinates":[-2.07566706143854,52.50537941728695],"type":"Point"}
}