{
  "type": "Feature",
  "properties": {
    "date:inception_lower":"1998-12-01",
    "date:inception_upper":"1998-12-31",
    "iso:country":"GB",
    "wof:name":"TQ1 2DB",
    "wof:placetype":"postalcode"
},
  "geometry": {"coordinates":[-3.523235,50.459652],"type":"Point"}
}