{
  "type": "Feature",
  "properties": {
    "iso:country":"GB",
    "wof:name":"TQ1 2DB",
    "wof:placetype":"postalcode"
},
  "geometry": {"coordinates":[-3.52323511108791,50.45965157364819],"type":"Point"}
}