{
  "type": "Feature",
  "properties": {
    "iso:country":"GB",
    "wof:name":"DE4 3DB",
    "wof:placetype":"postalcode"
},
  "geometry": {"coordinates":[-1.55441907603481,53.1318722246135],"type":"Point"}
}