{
  "type": "Feature",
  "properties": {
    "date:inception_lower": "2016-09-01",
    "date:inception_upper": "2016-09-01",
    "iso:country": "GB",
    "wof:name": "B90 1GL",
    "wof:placetype": "postalcode"
  },
  "geometry": {"coordinates":[-1.837817,52.38503],"type":"Point"}
}
