{
  "type": "Feature",
  "properties": {
    "date:inception_lower": "1984-03-01",
    "date:inception_upper": "1984-03-01",
    "iso:country": "GB",
    "wof:name": "EH17 8TA",
    "wof:placetype": "postalcode"
  },
  "geometry": {"coordinates":[-3.16193,55.897813],"type":"Point"}
}
