{
  "type": "Feature",
  "properties": {
    "iso:country":"GB",
    "wof:name":"EH17 8TA",
    "wof:placetype":"postalcode"
},
  "geometry": {"coordinates":[-3.1619299289721,55.89781281545729],"type":"Point"}
}