{
  "type": "Feature",
  "properties": {
    "date:inception_lower": "1980-01-01",
    "date:inception_upper": "1980-01-01",
    "iso:country": "GB",
    "wof:name": "CB11 4QU",
    "wof:placetype": "postalcode"
  },
  "geometry": {"coordinates":[0.156605,51.974867],"type":"Point"}
}
