{
  "type": "Feature",
  "properties": {
    "iso:country":"GB",
    "wof:name":"YO16 7HR",
    "wof:placetype":"postalcode"
},
  "geometry": {"coordinates":[-0.19499080464256,54.10101787149981],"type":"Point"}
}