{
  "type": "Feature",
  "properties": {
    "iso:country": "GB",
    "wof:name": "YO16 7HR",
    "wof:placetype": "postalcode"
  },
  "geometry": {"coordinates":[-0.194991,54.101018],"type":"Point"}
}
