{
  "type": "Feature",
  "properties": {
    "iso:country":"GB",
    "wof:name":"YO18 8TA",
    "wof:placetype":"postalcode"
},
  "geometry": {"coordinates":[-0.78184619379463,54.24137576165038],"type":"Point"}
}