{
  "type": "Feature",
  "properties": {
    "iso:country": "GB",
    "wof:name": "YO18 8TA",
    "wof:placetype": "postalcode"
  },
  "geometry": {"coordinates":[-0.781846,54.241376],"type":"Point"}
}
