{
  "type": "Feature",
  "properties": {
    "date:inception_lower": "2000-06-01",
    "date:inception_upper": "2000-06-01",
    "iso:country": "GB",
    "wof:name": "PE28 3DQ",
    "wof:placetype": "postalcode"
  },
  "geometry": {"coordinates":[0.008332,52.377588],"type":"Point"}
}
