{
  "type": "Feature",
  "properties": {
    "iso:country":"GB",
    "wof:name":"PE28 3DQ",
    "wof:placetype":"postalcode"
},
  "geometry": {"coordinates":[0.00833222955696,52.37758797648827],"type":"Point"}
}