{
  "type": "Feature",
  "properties": {
    "iso:country":"GB",
    "wof:name":"NW5 2HA",
    "wof:placetype":"postalcode"
},
  "geometry": {"coordinates":[-0.14069836647019,51.55257575113765],"type":"Point"}
}