{
  "type": "Feature",
  "properties": {
    "iso:country":"GB",
    "wof:name":"ME19 4RJ",
    "wof:placetype":"postalcode"
},
  "geometry": {"coordinates":[0.4100307310558,51.26732977207989],"type":"Point"}
}