{
  "type": "Feature",
  "properties": {
    "iso:country": "GB",
    "wof:name": "ME19 4RJ",
    "wof:placetype": "postalcode"
  },
  "geometry": {"coordinates":[0.410221,51.267145],"type":"Point"}
}
