{
  "type": "Feature",
  "properties": {
    "iso:country":"GB",
    "wof:name":"TW3 4BG",
    "wof:placetype":"postalcode"
},
  "geometry": {"coordinates":[-0.36297592055478,51.47861697806857],"type":"Point"}
}