{
  "type": "Feature",
  "properties": {
    "iso:country":"GB",
    "wof:name":"ME4 6JQ",
    "wof:placetype":"postalcode"
},
  "geometry": {"coordinates":[0.51757885681989,51.36478691407595],"type":"Point"}
}