{
  "type": "Feature",
  "properties": {
    "iso:country":"GB",
    "wof:name":"BH17 7BZ",
    "wof:placetype":"postalcode"
},
  "geometry": {"coordinates":[-1.99529944774943,50.74151335233761],"type":"Point"}
}