{
  "type": "Feature",
  "properties": {
    "date:inception_lower":"1991-09-01",
    "date:inception_upper":"1991-09-30",
    "iso:country":"GB",
    "wof:name":"BH17 7BZ",
    "wof:placetype":"postalcode"
},
  "geometry": {"coordinates":[-1.995299,50.741513],"type":"Point"}
}