{
  "type": "Feature",
  "properties": {
    "date:inception_lower": "1980-01-01",
    "date:inception_upper": "1980-01-01",
    "iso:country": "GB",
    "wof:name": "LA14 1XY",
    "wof:placetype": "postalcode"
  },
  "geometry": {"coordinates":[-3.236967,54.115877],"type":"Point"}
}
