{
  "type": "Feature",
  "properties": {
    "iso:country": "GB",
    "wof:name": "LA14 1XY",
    "wof:placetype": "postalcode"
  },
  "geometry": {"coordinates":[-3.236967,54.115877],"type":"Point"}
}
