{
  "type": "Feature",
  "properties": {
    "iso:country":"GB",
    "wof:name":"LA14 1XY",
    "wof:placetype":"postalcode"
},
  "geometry": {"coordinates":[-3.2369667714374,54.11587653830809],"type":"Point"}
}