{
  "type": "Feature",
  "properties": {
    "iso:country": "GB",
    "wof:name": "S6 2XH",
    "wof:placetype": "postalcode"
  },
  "geometry": {"coordinates":[-1.50054,53.395634],"type":"Point"}
}
