{
  "type": "Feature",
  "properties": {
    "date:inception_lower": "1984-10-01",
    "date:inception_upper": "1984-10-01",
    "iso:country": "GB",
    "wof:name": "S6 2XH",
    "wof:placetype": "postalcode"
  },
  "geometry": {"coordinates":[-1.50054,53.395661],"type":"Point"}
}
