{
  "type": "Feature",
  "properties": {
    "iso:country":"GB",
    "wof:name":"S6 2XH",
    "wof:placetype":"postalcode"
},
  "geometry": {"coordinates":[-1.50054005754879,53.39563440559341],"type":"Point"}
}