{
  "type": "Feature",
  "properties": {
    "date:inception_lower": "1980-01-01",
    "date:inception_upper": "1980-01-01",
    "iso:country": "GB",
    "wof:name": "LL11 5UH",
    "wof:placetype": "postalcode"
  },
  "geometry": {"coordinates":[-3.113053,53.068365],"type":"Point"}
}
