{
  "type": "Feature",
  "properties": {
    "iso:country":"GB",
    "wof:name":"LL11 5UH",
    "wof:placetype":"postalcode"
},
  "geometry": {"coordinates":[-3.11198585269951,53.06807158854837],"type":"Point"}
}