{
  "type": "Feature",
  "properties": {
    "iso:country":"GB",
    "wof:name":"BH6 5JU",
    "wof:placetype":"postalcode"
},
  "geometry": {"coordinates":[-1.80448056787218,50.73242027381557],"type":"Point"}
}