{
  "type": "Feature",
  "properties": {
    "iso:country":"GB",
    "wof:name":"SK9 3SQ",
    "wof:placetype":"postalcode"
},
  "geometry": {"coordinates":[-2.21204385420568,53.35612128536842],"type":"Point"}
}