{
  "type": "Feature",
  "properties": {
    "iso:country": "GB",
    "wof:name": "SK9 3SQ",
    "wof:placetype": "postalcode"
  },
  "geometry": {"coordinates":[-2.212044,53.356121],"type":"Point"}
}
