{
  "type": "Feature",
  "properties": {
    "iso:country":"GB",
    "wof:name":"DL14 8LF",
    "wof:placetype":"postalcode"
},
  "geometry": {"coordinates":[-1.6253218557419,54.66073668013978],"type":"Point"}
}