{
  "type": "Feature",
  "properties": {
    "iso:country": "GB",
    "wof:name": "SO31 7AA",
    "wof:placetype": "postalcode"
  },
  "geometry": {"coordinates":[-1.290411,50.875748],"type":"Point"}
}
