{
  "type": "Feature",
  "properties": {
    "iso:country":"GB",
    "wof:name":"SO31 7AA",
    "wof:placetype":"postalcode"
},
  "geometry": {"coordinates":[-1.29041135007771,50.87574804078833],"type":"Point"}
}