{
  "type": "Feature",
  "properties": {
    "iso:country":"GB",
    "wof:name":"GL7 5SD",
    "wof:placetype":"postalcode"
},
  "geometry": {"coordinates":[-1.89687353030529,51.71808567686037],"type":"Point"}
}