{
  "type": "Feature",
  "properties": {
    "iso:country": "GB",
    "wof:name": "GL7 5SD",
    "wof:placetype": "postalcode"
  },
  "geometry": {"coordinates":[-1.896873,51.718086],"type":"Point"}
}
