{
  "type": "Feature",
  "properties": {
    "iso:country": "GB",
    "wof:name": "NG6 9LX",
    "wof:placetype": "postalcode"
  },
  "geometry": {"coordinates":[-1.181337,52.998541],"type":"Point"}
}
