{
  "type": "Feature",
  "properties": {
    "iso:country":"GB",
    "wof:name":"NG6 9LX",
    "wof:placetype":"postalcode"
},
  "geometry": {"coordinates":[-1.18133669822045,52.99854052733605],"type":"Point"}
}