{
  "type": "Feature",
  "properties": {
    "iso:country":"GB",
    "wof:name":"BB4 5QU",
    "wof:placetype":"postalcode"
},
  "geometry": {"coordinates":[-2.32480887341137,53.70773632037729],"type":"Point"}
}