{
  "type": "Feature",
  "properties": {
    "iso:country":"GB",
    "wof:name":"BA2 2RY",
    "wof:placetype":"postalcode"
},
  "geometry": {"coordinates":[-2.38110121652756,51.35725139557802],"type":"Point"}
}