{
  "type": "Feature",
  "properties": {
    "iso:country": "GB",
    "wof:name": "BA2 2RY",
    "wof:placetype": "postalcode"
  },
  "geometry": {"coordinates":[-2.381101,51.357251],"type":"Point"}
}
