{
  "type": "Feature",
  "properties": {
    "iso:country":"GB",
    "wof:name":"SY9 5WE",
    "wof:placetype":"postalcode"
},
  "geometry": {"coordinates":[-2.84028776118486,52.44702089387696],"type":"Point"}
}