{
  "type": "Feature",
  "properties": {
    "date:inception_lower": "1980-01-01",
    "date:inception_upper": "1980-01-01",
    "iso:country": "GB",
    "wof:name": "ML5 2LN",
    "wof:placetype": "postalcode"
  },
  "geometry": {"coordinates":[-4.056033,55.872896],"type":"Point"}
}
