{
  "type": "Feature",
  "properties": {
    "iso:country":"GB",
    "wof:name":"ST17 9WN",
    "wof:placetype":"postalcode"
},
  "geometry": {"coordinates":[-2.13567445983391,52.79188159697037],"type":"Point"}
}