{
  "type": "Feature",
  "properties": {
    "iso:country":"GB",
    "wof:name":"DN16 3PL",
    "wof:placetype":"postalcode"
},
  "geometry": {"coordinates":[-0.65036056618202,53.5548849280102],"type":"Point"}
}