{
  "type": "Feature",
  "properties": {
    "iso:country": "GB",
    "wof:name": "DN16 3PL",
    "wof:placetype": "postalcode"
  },
  "geometry": {"coordinates":[-0.650361,53.554885],"type":"Point"}
}
