{
  "type": "Feature",
  "properties": {
    "date:inception_lower":"1980-01-01",
    "date:inception_upper":"1980-01-31",
    "iso:country":"GB",
    "wof:name":"CT19 5LH",
    "wof:placetype":"postalcode"
},
  "geometry": {"coordinates":[1.158001,51.089385],"type":"Point"}
}