{
  "type": "Feature",
  "properties": {
    "iso:country":"GB",
    "wof:name":"CT19 5LH",
    "wof:placetype":"postalcode"
},
  "geometry": {"coordinates":[1.15800083024444,51.08938535493674],"type":"Point"}
}