{
  "type": "Feature",
  "properties": {
    "iso:country":"GB",
    "wof:name":"TS23 4BG",
    "wof:placetype":"postalcode"
},
  "geometry": {"coordinates":[-1.27676532376883,54.60370867137988],"type":"Point"}
}