{
  "type": "Feature",
  "properties": {
    "iso:country": "GB",
    "wof:name": "TS23 4BG",
    "wof:placetype": "postalcode"
  },
  "geometry": {"coordinates":[-1.276765,54.603709],"type":"Point"}
}
