{
  "type": "Feature",
  "properties": {
    "date:inception_lower": "1980-01-01",
    "date:inception_upper": "1980-01-01",
    "iso:country": "GB",
    "wof:name": "TS23 4BG",
    "wof:placetype": "postalcode"
  },
  "geometry": {"coordinates":[-1.276765,54.603709],"type":"Point"}
}
