{
  "type": "Feature",
  "properties": {
    "iso:country":"GB",
    "wof:name":"NN5 5EX",
    "wof:placetype":"postalcode"
},
  "geometry": {"coordinates":[-0.9116027611294,52.24109585180894],"type":"Point"}
}