{
  "type": "Feature",
  "properties": {
    "date:inception_lower": "1980-01-01",
    "date:inception_upper": "1980-01-01",
    "iso:country": "GB",
    "wof:name": "NN5 5EX",
    "wof:placetype": "postalcode"
  },
  "geometry": {"coordinates":[-0.911603,52.241096],"type":"Point"}
}
