{
  "type": "Feature",
  "properties": {
    "iso:country": "GB",
    "wof:name": "SP8 5NY",
    "wof:placetype": "postalcode"
  },
  "geometry": {"coordinates":[-2.331571,51.035457],"type":"Point"}
}
