{
  "type": "Feature",
  "properties": {
    "iso:country":"GB",
    "wof:name":"BD8 0PA",
    "wof:placetype":"postalcode"
},
  "geometry": {"coordinates":[-1.80958311588286,53.79470706803646],"type":"Point"}
}