{
  "type": "Feature",
  "properties": {
    "iso:country": "GB",
    "wof:name": "LE2 0DR",
    "wof:placetype": "postalcode"
  },
  "geometry": {"coordinates":[-1.114043,52.630468],"type":"Point"}
}
