{
  "type": "Feature",
  "properties": {
    "iso:country":"GB",
    "wof:name":"LE2 0DR",
    "wof:placetype":"postalcode"
},
  "geometry": {"coordinates":[-1.11405111966565,52.63045011942106],"type":"Point"}
}