{
  "type": "Feature",
  "properties": {
    "date:inception_lower":"1980-01-01",
    "date:inception_upper":"1980-01-31",
    "iso:country":"GB",
    "wof:name":"LE2 0DR",
    "wof:placetype":"postalcode"
},
  "geometry": {"coordinates":[-1.114043,52.630468],"type":"Point"}
}