{
  "type": "Feature",
  "properties": {
    "iso:country": "GB",
    "wof:name": "BB5 4QG",
    "wof:placetype": "postalcode"
  },
  "geometry": {"coordinates":[-2.406416,53.745156],"type":"Point"}
}
