{
  "type": "Feature",
  "properties": {
    "iso:country":"GB",
    "wof:name":"BB5 4QG",
    "wof:placetype":"postalcode"
},
  "geometry": {"coordinates":[-2.40638593115197,53.74520141360453],"type":"Point"}
}