{
  "type": "Feature",
  "properties": {
    "iso:country": "GB",
    "wof:name": "NW10 0AB",
    "wof:placetype": "postalcode"
  },
  "geometry": {"coordinates":[-0.253283,51.553022],"type":"Point"}
}
