{
  "type": "Feature",
  "properties": {
    "iso:country":"GB",
    "wof:name":"NW10 0AB",
    "wof:placetype":"postalcode"
},
  "geometry": {"coordinates":[-0.25330680857921,51.55302028817332],"type":"Point"}
}