{
  "type": "Feature",
  "properties": {
    "date:inception_lower": "1980-01-01",
    "date:inception_upper": "1980-01-01",
    "iso:country": "GB",
    "wof:name": "EX20 1PA",
    "wof:placetype": "postalcode"
  },
  "geometry": {"coordinates":[-3.99027,50.745584],"type":"Point"}
}
