{
  "type": "Feature",
  "properties": {
    "date:inception_lower": "1980-01-01",
    "date:inception_upper": "1980-01-01",
    "iso:country": "GB",
    "wof:name": "G72 8LL",
    "wof:placetype": "postalcode"
  },
  "geometry": {"coordinates":[-4.163192,55.814448],"type":"Point"}
}
