{
  "type": "Feature",
  "properties": {
    "date:inception_lower": "1980-01-01",
    "date:inception_upper": "1980-01-01",
    "iso:country": "GB",
    "wof:name": "WC1R 5JP",
    "wof:placetype": "postalcode"
  },
  "geometry": {"coordinates":[-0.11228,51.519515],"type":"Point"}
}
