{
  "type": "Feature",
  "properties": {
    "iso:country": "GB",
    "wof:name": "WC1R 5JP",
    "wof:placetype": "postalcode"
  },
  "geometry": {"coordinates":[-0.11228,51.519515],"type":"Point"}
}
