{
  "type": "Feature",
  "properties": {
    "date:inception_lower":"1988-03-01",
    "date:inception_upper":"1988-03-31",
    "iso:country":"GB",
    "wof:name":"BN8 5EN",
    "wof:placetype":"postalcode"
},
  "geometry": {"coordinates":[0.049764,50.886852],"type":"Point"}
}