{
  "type": "Feature",
  "properties": {
    "iso:country":"GB",
    "wof:name":"BN8 5EN",
    "wof:placetype":"postalcode"
},
  "geometry": {"coordinates":[0.04976377743597,50.88685151231426],"type":"Point"}
}