{
  "type": "Feature",
  "properties": {
    "iso:country": "GB",
    "wof:name": "BN8 5EN",
    "wof:placetype": "postalcode"
  },
  "geometry": {"coordinates":[0.049764,50.886852],"type":"Point"}
}
