{
  "type": "Feature",
  "properties": {
    "iso:country": "GB",
    "wof:name": "BA1 7QU",
    "wof:placetype": "postalcode"
  },
  "geometry": {"coordinates":[-2.326665,51.402716],"type":"Point"}
}
