{
  "type": "Feature",
  "properties": {
    "iso:country":"GB",
    "wof:name":"BB9 6QW",
    "wof:placetype":"postalcode"
},
  "geometry": {"coordinates":[-2.23430745309712,53.84664164955791],"type":"Point"}
}