{
  "type": "Feature",
  "properties": {
    "date:inception_lower": "2003-07-01",
    "date:inception_upper": "2003-07-01",
    "iso:country": "GB",
    "wof:name": "CT13 0GX",
    "wof:placetype": "postalcode"
  },
  "geometry": {"coordinates":[1.305291,51.245415],"type":"Point"}
}
