{
  "type": "Feature",
  "properties": {
    "iso:country":"GB",
    "wof:name":"CT13 0GX",
    "wof:placetype":"postalcode"
},
  "geometry": {"coordinates":[1.30529138021807,51.24541529613807],"type":"Point"}
}