{
  "type": "Feature",
  "properties": {
    "iso:country":"GB",
    "wof:name":"SG4 0LD",
    "wof:placetype":"postalcode"
},
  "geometry": {"coordinates":[-0.25274523711574,51.95691654894472],"type":"Point"}
}