{
  "type": "Feature",
  "properties": {
    "iso:country":"GB",
    "wof:name":"B10 9JF",
    "wof:placetype":"postalcode"
},
  "geometry": {"coordinates":[-1.83141941460661,52.46965688476388],"type":"Point"}
}