{
  "type": "Feature",
  "properties": {
    "iso:country": "GB",
    "wof:name": "SA2 0JD",
    "wof:placetype": "postalcode"
  },
  "geometry": {"coordinates":[-3.972188,51.617124],"type":"Point"}
}
