{
  "type": "Feature",
  "properties": {
    "iso:country": "GB",
    "wof:name": "BN1 6LW",
    "wof:placetype": "postalcode"
  },
  "geometry": {"coordinates":[-0.139088,50.84664],"type":"Point"}
}
