{
  "type": "Feature",
  "properties": {
    "iso:country":"GB",
    "wof:name":"BN1 6LW",
    "wof:placetype":"postalcode"
},
  "geometry": {"coordinates":[-0.1390879057896,50.84664021944177],"type":"Point"}
}