{
  "type": "Feature",
  "properties": {
    "iso:country": "GB",
    "wof:name": "CW6 0JH",
    "wof:placetype": "postalcode"
  },
  "geometry": {"coordinates":[-2.656413,53.181509],"type":"Point"}
}
