{
  "type": "Feature",
  "properties": {
    "iso:country":"GB",
    "wof:name":"CW6 0JH",
    "wof:placetype":"postalcode"
},
  "geometry": {"coordinates":[-2.65713098910324,53.18136400012175],"type":"Point"}
}