{
  "type": "Feature",
  "properties": {
    "iso:country": "GB",
    "wof:name": "LE65 1HU",
    "wof:placetype": "postalcode"
  },
  "geometry": {"coordinates":[-1.470323,52.748626],"type":"Point"}
}
