{
  "type": "Feature",
  "properties": {
    "date:inception_lower":"1992-08-01",
    "date:inception_upper":"1992-08-31",
    "iso:country":"GB",
    "wof:name":"LE65 1HU",
    "wof:placetype":"postalcode"
},
  "geometry": {"coordinates":[-1.470323,52.748626],"type":"Point"}
}