{
  "type": "Feature",
  "properties": {
    "iso:country":"GB",
    "wof:name":"GU15 2EJ",
    "wof:placetype":"postalcode"
},
  "geometry": {"coordinates":[-0.73778753919279,51.33511422737201],"type":"Point"}
}