{
  "type": "Feature",
  "properties": {
    "date:inception_lower": "2016-08-01",
    "date:inception_upper": "2016-08-01",
    "iso:country": "GB",
    "wof:name": "NW9 4BS",
    "wof:placetype": "postalcode"
  },
  "geometry": {"coordinates":[-0.245604,51.598473],"type":"Point"}
}
