{
  "type": "Feature",
  "properties": {
    "iso:country":"GB",
    "wof:name":"SP1 2RG",
    "wof:placetype":"postalcode"
},
  "geometry": {"coordinates":[-1.78345051639793,51.0675750634018],"type":"Point"}
}