{
  "type": "Feature",
  "properties": {
    "iso:country": "GB",
    "wof:name": "GU29 9QB",
    "wof:placetype": "postalcode"
  },
  "geometry": {"coordinates":[-0.743842,50.982397],"type":"Point"}
}
