{
  "type": "Feature",
  "properties": {
    "iso:country": "GB",
    "wof:name": "SA17 4SR",
    "wof:placetype": "postalcode"
  },
  "geometry": {"coordinates":[-4.294855,51.739487],"type":"Point"}
}
