{
  "type": "Feature",
  "properties": {
    "iso:country":"GB",
    "wof:name":"CH5 2RA",
    "wof:placetype":"postalcode"
},
  "geometry": {"coordinates":[-3.0118421224038,53.21244443548274],"type":"Point"}
}