{
  "type": "Feature",
  "properties": {
    "iso:country":"GB",
    "wof:name":"W12 9JF",
    "wof:placetype":"postalcode"
},
  "geometry": {"coordinates":[-0.23747615086631,51.50131117533235],"type":"Point"}
}