{
  "type": "Feature",
  "properties": {
    "date:inception_lower":"1980-01-01",
    "date:inception_upper":"1980-01-31",
    "iso:country":"GB",
    "wof:name":"W12 9JF",
    "wof:placetype":"postalcode"
},
  "geometry": {"coordinates":[-0.237476,51.501311],"type":"Point"}
}