{
  "type": "Feature",
  "properties": {
    "iso:country":"GB",
    "wof:name":"BN15 8SH",
    "wof:placetype":"postalcode"
},
  "geometry": {"coordinates":[-0.34172474526433,50.82306682393982],"type":"Point"}
}