{
  "type": "Feature",
  "properties": {
    "iso:country": "GB",
    "wof:name": "GU29 0JS",
    "wof:placetype": "postalcode"
  },
  "geometry": {"coordinates":[-0.809122,50.980535],"type":"Point"}
}
