{
  "type": "Feature",
  "properties": {
    "date:inception_lower": "2018-12-01",
    "date:inception_upper": "2018-12-01",
    "iso:country": "GB",
    "wof:name": "CM17 0GA",
    "wof:placetype": "postalcode"
  },
  "geometry": {"coordinates":[0.14877,51.785907],"type":"Point"}
}
