{
  "type": "Feature",
  "properties": {
    "date:inception_lower":"1980-01-01",
    "date:inception_upper":"1980-01-31",
    "iso:country":"GB",
    "wof:name":"OX16 9JL",
    "wof:placetype":"postalcode"
},
  "geometry": {"coordinates":[-1.345067,52.051357],"type":"Point"}
}