{
  "type": "Feature",
  "properties": {
    "date:inception_lower": "2019-12-01",
    "date:inception_upper": "2019-12-01",
    "iso:country": "GB",
    "wof:name": "WF8 2GH",
    "wof:placetype": "postalcode"
  },
  "geometry": {"coordinates":[-1.30432,53.696704],"type":"Point"}
}
