{
  "type": "Feature",
  "properties": {
    "date:inception_lower":"1999-06-01",
    "date:inception_upper":"1999-06-30",
    "iso:country":"GB",
    "wof:name":"NP10 9YX",
    "wof:placetype":"postalcode"
},
  "geometry": {"coordinates":[-3.049728,51.586514],"type":"Point"}
}