{
  "type": "Feature",
  "properties": {
    "iso:country": "GB",
    "wof:name": "NP10 9YX",
    "wof:placetype": "postalcode"
  },
  "geometry": {"coordinates":[-3.049728,51.586514],"type":"Point"}
}
