{
  "type": "Feature",
  "properties": {
    "date:inception_lower": "1980-01-01",
    "date:inception_upper": "1980-01-01",
    "iso:country": "GB",
    "wof:name": "BD12 8BN",
    "wof:placetype": "postalcode"
  },
  "geometry": {"coordinates":[-1.770381,53.746208],"type":"Point"}
}
