{
  "type": "Feature",
  "properties": {
    "iso:country":"GB",
    "wof:name":"TQ14 8ED",
    "wof:placetype":"postalcode"
},
  "geometry": {"coordinates":[-3.49823593917738,50.54679134615172],"type":"Point"}
}