{
  "type": "Feature",
  "properties": {
    "iso:country": "GB",
    "wof:name": "G71 7HF",
    "wof:placetype": "postalcode"
  },
  "geometry": {"coordinates":[-4.082427,55.818],"type":"Point"}
}
