{
  "type": "Feature",
  "properties": {
    "iso:country":"GB",
    "wof:name":"NE29 8EJ",
    "wof:placetype":"postalcode"
},
  "geometry": {"coordinates":[-1.488863470927,55.02157675065254],"type":"Point"}
}