{
  "type": "Feature",
  "properties": {
    "iso:country": "GB",
    "wof:name": "SS15 6ND",
    "wof:placetype": "postalcode"
  },
  "geometry": {"coordinates":[0.411584,51.583193],"type":"Point"}
}
