{
  "type": "Feature",
  "properties": {
    "date:inception_lower": "1980-01-01",
    "date:inception_upper": "1980-01-01",
    "iso:country": "GB",
    "wof:name": "SY21 9DQ",
    "wof:placetype": "postalcode"
  },
  "geometry": {"coordinates":[-3.17326,52.696346],"type":"Point"}
}
