{
  "type": "Feature",
  "properties": {
    "iso:country":"GB",
    "wof:name":"SY21 9DQ",
    "wof:placetype":"postalcode"
},
  "geometry": {"coordinates":[-3.17326042203296,52.69634585635385],"type":"Point"}
}