{
  "type": "Feature",
  "properties": {
    "iso:country":"GB",
    "wof:name":"S43 1PF",
    "wof:placetype":"postalcode"
},
  "geometry": {"coordinates":[-1.38821639749177,53.24348847777559],"type":"Point"}
}