{
  "type": "Feature",
  "properties": {
    "iso:country": "GB",
    "wof:name": "SL5 8QG",
    "wof:placetype": "postalcode"
  },
  "geometry": {"coordinates":[-0.683869,51.428309],"type":"Point"}
}
