{
  "type": "Feature",
  "properties": {
    "iso:country":"GB",
    "wof:name":"SL5 8QG",
    "wof:placetype":"postalcode"
},
  "geometry": {"coordinates":[-0.68386932695884,51.4283091956518],"type":"Point"}
}