{
  "type": "Feature",
  "properties": {
    "iso:country": "GB",
    "wof:name": "NG6 8JJ",
    "wof:placetype": "postalcode"
  },
  "geometry": {"coordinates":[-1.206574,53.005247],"type":"Point"}
}
