{
  "type": "Feature",
  "properties": {
    "iso:country":"GB",
    "wof:name":"NG6 8JJ",
    "wof:placetype":"postalcode"
},
  "geometry": {"coordinates":[-1.20657408302461,53.0052468376674],"type":"Point"}
}