{
  "type": "Feature",
  "properties": {
    "iso:country": "GB",
    "wof:name": "NE62 5XJ",
    "wof:placetype": "postalcode"
  },
  "geometry": {"coordinates":[-1.567748,55.163297],"type":"Point"}
}
