{
  "type": "Feature",
  "properties": {
    "iso:country":"GB",
    "wof:name":"NE62 5XJ",
    "wof:placetype":"postalcode"
},
  "geometry": {"coordinates":[-1.5677475931952,55.16329663567747],"type":"Point"}
}