{
  "type": "Feature",
  "properties": {
    "iso:country":"GB",
    "wof:name":"YO31 9HF",
    "wof:placetype":"postalcode"
},
  "geometry": {"coordinates":[-1.06621151033583,53.98366135624993],"type":"Point"}
}