{
  "type": "Feature",
  "properties": {
    "date:inception_lower": "1998-06-01",
    "date:inception_upper": "1998-06-01",
    "iso:country": "GB",
    "wof:name": "YO31 9HF",
    "wof:placetype": "postalcode"
  },
  "geometry": {"coordinates":[-1.066266,53.98367],"type":"Point"}
}
