{
  "type": "Feature",
  "properties": {
    "iso:country":"GB",
    "wof:name":"LL11 1SE",
    "wof:placetype":"postalcode"
},
  "geometry": {"coordinates":[-2.99587292834027,53.04673454076396],"type":"Point"}
}