{
  "type": "Feature",
  "properties": {
    "date:inception_lower": "1980-01-01",
    "date:inception_upper": "1980-01-01",
    "iso:country": "GB",
    "wof:name": "LL11 1SE",
    "wof:placetype": "postalcode"
  },
  "geometry": {"coordinates":[-2.995873,53.046735],"type":"Point"}
}
