{
  "type": "Feature",
  "properties": {
    "iso:country":"GB",
    "wof:name":"HP21 7HZ",
    "wof:placetype":"postalcode"
},
  "geometry": {"coordinates":[-0.78925271870857,51.81143179618881],"type":"Point"}
}