{
  "type": "Feature",
  "properties": {
    "date:inception_lower":"1980-01-01",
    "date:inception_upper":"1980-01-31",
    "iso:country":"GB",
    "wof:name":"GU31 4NW",
    "wof:placetype":"postalcode"
},
  "geometry": {"coordinates":[-0.949516,50.982694],"type":"Point"}
}