{
  "type": "Feature",
  "properties": {
    "iso:country":"GB",
    "wof:name":"GU31 4NW",
    "wof:placetype":"postalcode"
},
  "geometry": {"coordinates":[-0.94943508667588,50.98260952486045],"type":"Point"}
}