{
  "type": "Feature",
  "properties": {
    "date:inception_lower": "2013-07-01",
    "date:inception_upper": "2013-07-01",
    "iso:country": "GB",
    "wof:name": "WA5 3TF",
    "wof:placetype": "postalcode"
  },
  "geometry": {"coordinates":[-2.637584,53.395568],"type":"Point"}
}
