{
  "type": "Feature",
  "properties": {
    "iso:country":"GB",
    "wof:name":"WA5 3TF",
    "wof:placetype":"postalcode"
},
  "geometry": {"coordinates":[-2.63758389750101,53.39556750700906],"type":"Point"}
}