{
  "type": "Feature",
  "properties": {
    "date:inception_lower": "2001-12-01",
    "date:inception_upper": "2001-12-01",
    "iso:country": "GB",
    "wof:name": "SE11 4PJ",
    "wof:placetype": "postalcode"
  },
  "geometry": {"coordinates":[-0.107549,51.491076],"type":"Point"}
}
