{
  "type": "Feature",
  "properties": {
    "iso:country": "GB",
    "wof:name": "PL18 9SD",
    "wof:placetype": "postalcode"
  },
  "geometry": {"coordinates":[-4.219517,50.504629],"type":"Point"}
}
