{
  "type": "Feature",
  "properties": {
    "iso:country":"GB",
    "wof:name":"PL18 9SD",
    "wof:placetype":"postalcode"
},
  "geometry": {"coordinates":[-4.21951709683796,50.50462859695608],"type":"Point"}
}