{
  "type": "Feature",
  "properties": {
    "iso:country":"GB",
    "wof:name":"BN3 7AQ",
    "wof:placetype":"postalcode"
},
  "geometry": {"coordinates":[-0.17909591217445,50.8392043422363],"type":"Point"}
}