{
  "type": "Feature",
  "properties": {
    "date:inception_lower":"1983-03-01",
    "date:inception_upper":"1983-03-31",
    "iso:country":"GB",
    "wof:name":"SA4 3JH",
    "wof:placetype":"postalcode"
},
  "geometry": {"coordinates":[-4.098425,51.634638],"type":"Point"}
}