{
  "type": "Feature",
  "properties": {
    "iso:country":"GB",
    "wof:name":"SA4 3JH",
    "wof:placetype":"postalcode"
},
  "geometry": {"coordinates":[-4.09842504468844,51.63463788588683],"type":"Point"}
}