{
  "type": "Feature",
  "properties": {
    "iso:country": "GB",
    "wof:name": "OL6 6BH",
    "wof:placetype": "postalcode"
  },
  "geometry": {"coordinates":[-2.094244,53.488133],"type":"Point"}
}
