{
  "type": "Feature",
  "properties": {
    "iso:country":"GB",
    "wof:name":"MK17 0SN",
    "wof:placetype":"postalcode"
},
  "geometry": {"coordinates":[-0.83688367886794,51.93557017607894],"type":"Point"}
}