{
  "type": "Feature",
  "properties": {
    "date:inception_lower": "2001-12-01",
    "date:inception_upper": "2001-12-01",
    "iso:country": "GB",
    "wof:name": "PA10 2BE",
    "wof:placetype": "postalcode"
  },
  "geometry": {"coordinates":[-4.536704,55.830156],"type":"Point"}
}
