{
  "type": "Feature",
  "properties": {
    "iso:country":"GB",
    "wof:name":"BD18 2AQ",
    "wof:placetype":"postalcode"
},
  "geometry": {"coordinates":[-1.77480161151711,53.823579117172],"type":"Point"}
}