{
  "type": "Feature",
  "properties": {
    "iso:country": "GB",
    "wof:name": "BD18 2AQ",
    "wof:placetype": "postalcode"
  },
  "geometry": {"coordinates":[-1.77485,53.823648],"type":"Point"}
}
