{
  "type": "Feature",
  "properties": {
    "iso:country":"GB",
    "wof:name":"NG18 4NN",
    "wof:placetype":"postalcode"
},
  "geometry": {"coordinates":[-1.16175462187308,53.12480320443569],"type":"Point"}
}