{
  "type": "Feature",
  "properties": {
    "iso:country":"GB",
    "wof:name":"AB31 4PE",
    "wof:placetype":"postalcode"
},
  "geometry": {"coordinates":[-2.6351817336343,57.14558205830951],"type":"Point"}
}