{
  "type": "Feature",
  "properties": {
    "date:inception_lower": "1990-08-01",
    "date:inception_upper": "1990-08-01",
    "iso:country": "GB",
    "wof:name": "AB31 4PE",
    "wof:placetype": "postalcode"
  },
  "geometry": {"coordinates":[-2.638629,57.143961],"type":"Point"}
}
