{
  "type": "Feature",
  "properties": {
    "iso:country": "GB",
    "wof:name": "BB12 0EG",
    "wof:placetype": "postalcode"
  },
  "geometry": {"coordinates":[-2.247008,53.812129],"type":"Point"}
}
