{
  "type": "Feature",
  "properties": {
    "iso:country":"GB",
    "wof:name":"SW16 6RS",
    "wof:placetype":"postalcode"
},
  "geometry": {"coordinates":[-0.14350473008818,51.42542975250042],"type":"Point"}
}