{
  "type": "Feature",
  "properties": {
    "iso:country":"GB",
    "wof:name":"BL2 5DG",
    "wof:placetype":"postalcode"
},
  "geometry": {"coordinates":[-2.39124800448361,53.58950403207265],"type":"Point"}
}