{
  "type": "Feature",
  "properties": {
    "date:inception_lower": "1980-01-01",
    "date:inception_upper": "1980-01-01",
    "iso:country": "GB",
    "wof:name": "TF9 2AW",
    "wof:placetype": "postalcode"
  },
  "geometry": {"coordinates":[-2.474177,52.882809],"type":"Point"}
}
