{
  "type": "Feature",
  "properties": {
    "iso:country":"GB",
    "wof:name":"TF9 2AW",
    "wof:placetype":"postalcode"
},
  "geometry": {"coordinates":[-2.47781717280915,52.88268033342292],"type":"Point"}
}