{
  "type": "Feature",
  "properties": {
    "date:inception_lower":"1980-01-01",
    "date:inception_upper":"1980-01-31",
    "iso:country":"GB",
    "wof:name":"LA23 1AH",
    "wof:placetype":"postalcode"
},
  "geometry": {"coordinates":[-2.903345,54.379602],"type":"Point"}
}