{
  "type": "Feature",
  "properties": {
    "iso:country": "GB",
    "wof:name": "LA23 1AH",
    "wof:placetype": "postalcode"
  },
  "geometry": {"coordinates":[-2.903345,54.379602],"type":"Point"}
}
