{
  "type": "Feature",
  "properties": {
    "date:inception_lower": "1980-01-01",
    "date:inception_upper": "1980-01-01",
    "iso:country": "GB",
    "wof:name": "LA23 1AH",
    "wof:placetype": "postalcode"
  },
  "geometry": {"coordinates":[-2.903348,54.37961],"type":"Point"}
}
