{
  "type": "Feature",
  "properties": {
    "iso:country": "GB",
    "wof:name": "HP1 3JN",
    "wof:placetype": "postalcode"
  },
  "geometry": {"coordinates":[-0.488733,51.762698],"type":"Point"}
}
