{
  "type": "Feature",
  "properties": {
    "iso:country": "GB",
    "wof:name": "PO10 8GB",
    "wof:placetype": "postalcode"
  },
  "geometry": {"coordinates":[-0.915156,50.846812],"type":"Point"}
}
