{
  "type": "Feature",
  "properties": {
    "date:inception_lower":"1986-04-01",
    "date:inception_upper":"1986-04-30",
    "iso:country":"GB",
    "wof:name":"SA73 1AY",
    "wof:placetype":"postalcode"
},
  "geometry": {"coordinates":[-5.019136,51.72434],"type":"Point"}
}