{
  "type": "Feature",
  "properties": {
    "iso:country": "GB",
    "wof:name": "TF10 9DS",
    "wof:placetype": "postalcode"
  },
  "geometry": {"coordinates":[-2.301611,52.753055],"type":"Point"}
}
