{
  "type": "Feature",
  "properties": {
    "iso:country": "GB",
    "wof:name": "BR5 3ST",
    "wof:placetype": "postalcode"
  },
  "geometry": {"coordinates":[0.111421,51.391807],"type":"Point"}
}
