{
  "type": "Feature",
  "properties": {
    "iso:country":"GB",
    "wof:name":"BR5 3ST",
    "wof:placetype":"postalcode"
},
  "geometry": {"coordinates":[0.11139449510805,51.39180664998631],"type":"Point"}
}