{
  "type": "Feature",
  "properties": {
    "iso:country": "GB",
    "wof:name": "NR26 8PJ",
    "wof:placetype": "postalcode"
  },
  "geometry": {"coordinates":[1.212343,52.931552],"type":"Point"}
}
