{
  "type": "Feature",
  "properties": {
    "iso:country":"GB",
    "wof:name":"DN6 8BU",
    "wof:placetype":"postalcode"
},
  "geometry": {"coordinates":[-1.18166841258011,53.58413906365553],"type":"Point"}
}