{
  "type": "Feature",
  "properties": {
    "iso:country": "GB",
    "wof:name": "DN6 8BU",
    "wof:placetype": "postalcode"
  },
  "geometry": {"coordinates":[-1.181668,53.584139],"type":"Point"}
}
