{
  "type": "Feature",
  "properties": {
    "iso:country":"GB",
    "wof:name":"BS24 9JD",
    "wof:placetype":"postalcode"
},
  "geometry": {"coordinates":[-2.96560412895573,51.31702349305444],"type":"Point"}
}