{
  "type": "Feature",
  "properties": {
    "iso:country": "GB",
    "wof:name": "BS24 9JD",
    "wof:placetype": "postalcode"
  },
  "geometry": {"coordinates":[-2.965604,51.317023],"type":"Point"}
}
