{
  "type": "Feature",
  "properties": {
    "iso:country":"GB",
    "wof:name":"SN16 9EL",
    "wof:placetype":"postalcode"
},
  "geometry": {"coordinates":[-2.07080867263833,51.63452706760045],"type":"Point"}
}