{
  "type": "Feature",
  "properties": {
    "iso:country":"GB",
    "wof:name":"NW2 1EW",
    "wof:placetype":"postalcode"
},
  "geometry": {"coordinates":[-0.21216387916133,51.55901896847505],"type":"Point"}
}