{
  "type": "Feature",
  "properties": {
    "date:inception_lower": "1997-12-01",
    "date:inception_upper": "1997-12-01",
    "iso:country": "GB",
    "wof:name": "NW2 1EW",
    "wof:placetype": "postalcode"
  },
  "geometry": {"coordinates":[-0.212799,51.559859],"type":"Point"}
}
