{
  "type": "Feature",
  "properties": {
    "iso:country":"GB",
    "wof:name":"B66 3HR",
    "wof:placetype":"postalcode"
},
  "geometry": {"coordinates":[-1.96055830782612,52.49231694406737],"type":"Point"}
}