{
  "type": "Feature",
  "properties": {
    "date:inception_lower": "1980-01-01",
    "date:inception_upper": "1980-01-01",
    "iso:country": "GB",
    "wof:name": "B66 3HR",
    "wof:placetype": "postalcode"
  },
  "geometry": {"coordinates":[-1.960558,52.492317],"type":"Point"}
}
