{
  "type": "Feature",
  "properties": {
    "iso:country":"GB",
    "wof:name":"NR29 5BF",
    "wof:placetype":"postalcode"
},
  "geometry": {"coordinates":[1.52960015791886,52.72685760681371],"type":"Point"}
}