{
  "type": "Feature",
  "properties": {
    "iso:country": "GB",
    "wof:name": "NR29 5BF",
    "wof:placetype": "postalcode"
  },
  "geometry": {"coordinates":[1.529592,52.726877],"type":"Point"}
}
