{
  "type": "Feature",
  "properties": {
    "iso:country": "GB",
    "wof:name": "B73 5NT",
    "wof:placetype": "postalcode"
  },
  "geometry": {"coordinates":[-1.829504,52.546401],"type":"Point"}
}
