{
  "type": "Feature",
  "properties": {
    "iso:country":"GB",
    "wof:name":"LL13 9GT",
    "wof:placetype":"postalcode"
},
  "geometry": {"coordinates":[-2.96056466653574,53.05748865183955],"type":"Point"}
}