{
  "type": "Feature",
  "properties": {
    "date:inception_lower": "2001-06-01",
    "date:inception_upper": "2001-06-01",
    "iso:country": "GB",
    "wof:name": "LL13 9GT",
    "wof:placetype": "postalcode"
  },
  "geometry": {"coordinates":[-2.960565,53.057489],"type":"Point"}
}
