{
  "type": "Feature",
  "properties": {
    "iso:country": "GB",
    "wof:name": "DL1 2UQ",
    "wof:placetype": "postalcode"
  },
  "geometry": {"coordinates":[-1.546153,54.534057],"type":"Point"}
}
