{
  "type": "Feature",
  "properties": {
    "date:inception_lower": "2003-09-01",
    "date:inception_upper": "2003-09-01",
    "iso:country": "GB",
    "wof:name": "DL1 2UQ",
    "wof:placetype": "postalcode"
  },
  "geometry": {"coordinates":[-1.546153,54.534057],"type":"Point"}
}
