{
  "type": "Feature",
  "properties": {
    "iso:country": "GB",
    "wof:name": "YO23 1BY",
    "wof:placetype": "postalcode"
  },
  "geometry": {"coordinates":[-1.086501,53.951955],"type":"Point"}
}
