{
  "type": "Feature",
  "properties": {
    "iso:country":"GB",
    "wof:name":"YO23 1BY",
    "wof:placetype":"postalcode"
},
  "geometry": {"coordinates":[-1.08650100154278,53.95195461593542],"type":"Point"}
}