{
  "type": "Feature",
  "properties": {
    "date:inception_lower": "2003-07-01",
    "date:inception_upper": "2003-07-01",
    "iso:country": "GB",
    "wof:name": "BA16 0PJ",
    "wof:placetype": "postalcode"
  },
  "geometry": {"coordinates":[-2.736066,51.127934],"type":"Point"}
}
