{
  "type": "Feature",
  "properties": {
    "iso:country":"GB",
    "wof:name":"L31 4EY",
    "wof:placetype":"postalcode"
},
  "geometry": {"coordinates":[-2.96129231753042,53.53563860652806],"type":"Point"}
}