{
  "type": "Feature",
  "properties": {
    "date:inception_lower": "2007-09-01",
    "date:inception_upper": "2007-09-01",
    "iso:country": "GB",
    "wof:name": "SW19 7UZ",
    "wof:placetype": "postalcode"
  },
  "geometry": {"coordinates":[-0.213289,51.416892],"type":"Point"}
}
