{
  "type": "Feature",
  "properties": {
    "iso:country":"GB",
    "wof:name":"SN12 6PS",
    "wof:placetype":"postalcode"
},
  "geometry": {"coordinates":[-2.1028366195916,51.34500454081982],"type":"Point"}
}