{
  "type": "Feature",
  "properties": {
    "date:inception_lower":"1980-01-01",
    "date:inception_upper":"1980-01-31",
    "iso:country":"GB",
    "wof:name":"SY7 9DU",
    "wof:placetype":"postalcode"
},
  "geometry": {"coordinates":[-2.63668,52.457984],"type":"Point"}
}