{
  "type": "Feature",
  "properties": {
    "iso:country":"GB",
    "wof:name":"SY7 9DU",
    "wof:placetype":"postalcode"
},
  "geometry": {"coordinates":[-2.63667982281441,52.457984016693],"type":"Point"}
}