{
  "type": "Feature",
  "properties": {
    "iso:country":"GB",
    "wof:name":"BR1 5EA",
    "wof:placetype":"postalcode"
},
  "geometry": {"coordinates":[0.01600539901557,51.42674232923053],"type":"Point"}
}