{
  "type": "Feature",
  "properties": {
    "iso:country": "GB",
    "wof:name": "BR1 5EA",
    "wof:placetype": "postalcode"
  },
  "geometry": {"coordinates":[0.016005,51.426742],"type":"Point"}
}
