{
  "type": "Feature",
  "properties": {
    "date:inception_lower":"1980-01-01",
    "date:inception_upper":"1980-01-31",
    "iso:country":"GB",
    "wof:name":"BL7 9ES",
    "wof:placetype":"postalcode"
},
  "geometry": {"coordinates":[-2.435752,53.621645],"type":"Point"}
}