{
  "type": "Feature",
  "properties": {
    "iso:country": "GB",
    "wof:name": "KY4 8ER",
    "wof:placetype": "postalcode"
  },
  "geometry": {"coordinates":[-3.371826,56.081773],"type":"Point"}
}
