{
  "type": "Feature",
  "properties": {
    "date:inception_lower":"2011-05-01",
    "date:inception_upper":"2011-05-31",
    "iso:country":"GB",
    "wof:name":"KY4 8ER",
    "wof:placetype":"postalcode"
},
  "geometry": {"coordinates":[-3.371826,56.081773],"type":"Point"}
}