{
  "type": "Feature",
  "properties": {
    "date:inception_lower":"2017-03-01",
    "date:inception_upper":"2017-03-31",
    "iso:country":"GB",
    "wof:name":"B33 3EH",
    "wof:placetype":"postalcode"
},
  "geometry": {"coordinates":[-1.786864,52.485746],"type":"Point"}
}