{
  "type": "Feature",
  "properties": {
    "date:inception_lower":"1993-08-01",
    "date:inception_upper":"1993-08-31",
    "iso:country":"GB",
    "wof:name":"NN15 5UH",
    "wof:placetype":"postalcode"
},
  "geometry": {"coordinates":[-0.696828,52.398264],"type":"Point"}
}