{
  "type": "Feature",
  "properties": {
    "iso:country": "GB",
    "wof:name": "NN15 5UH",
    "wof:placetype": "postalcode"
  },
  "geometry": {"coordinates":[-0.696828,52.398264],"type":"Point"}
}
