{
  "type": "Feature",
  "properties": {
    "iso:country":"GB",
    "wof:name":"HP13 5QE",
    "wof:placetype":"postalcode"
},
  "geometry": {"coordinates":[-0.74385935840829,51.64073546185828],"type":"Point"}
}