{
  "type": "Feature",
  "properties": {
    "iso:country":"GB",
    "wof:name":"PR6 0QH",
    "wof:placetype":"postalcode"
},
  "geometry": {"coordinates":[-2.61548057488958,53.64958234208805],"type":"Point"}
}