{
  "type": "Feature",
  "properties": {
    "iso:country":"GB",
    "wof:name":"NG5 3FU",
    "wof:placetype":"postalcode"
},
  "geometry": {"coordinates":[-1.14166090348108,52.98482160406086],"type":"Point"}
}