{
  "type": "Feature",
  "properties": {
    "iso:country": "GB",
    "wof:name": "WD17 4SL",
    "wof:placetype": "postalcode"
  },
  "geometry": {"coordinates":[-0.415357,51.675326],"type":"Point"}
}
