{
  "type": "Feature",
  "properties": {
    "date:inception_lower":"1980-01-01",
    "date:inception_upper":"1980-01-31",
    "iso:country":"GB",
    "wof:name":"TN38 8AH",
    "wof:placetype":"postalcode"
},
  "geometry": {"coordinates":[0.522795,50.850691],"type":"Point"}
}