{
  "type": "Feature",
  "properties": {
    "date:inception_lower": "1998-06-01",
    "date:inception_upper": "1998-06-01",
    "iso:country": "GB",
    "wof:name": "YO42 4PE",
    "wof:placetype": "postalcode"
  },
  "geometry": {"coordinates":[-0.931807,53.849932],"type":"Point"}
}
