{
  "type": "Feature",
  "properties": {
    "iso:country":"GB",
    "wof:name":"YO42 4PE",
    "wof:placetype":"postalcode"
},
  "geometry": {"coordinates":[-0.93180130696594,53.84991140204227],"type":"Point"}
}