{
  "type": "Feature",
  "properties": {
    "iso:country": "GB",
    "wof:name": "YO42 4PE",
    "wof:placetype": "postalcode"
  },
  "geometry": {"coordinates":[-0.931807,53.849932],"type":"Point"}
}
