{
  "type": "Feature",
  "properties": {
    "date:inception_lower":"1998-06-01",
    "date:inception_upper":"1998-06-30",
    "iso:country":"GB",
    "wof:name":"NE23 7DY",
    "wof:placetype":"postalcode"
},
  "geometry": {"coordinates":[-1.536106,55.062977],"type":"Point"}
}