{
  "type": "Feature",
  "properties": {
    "iso:country":"GB",
    "wof:name":"NE23 7DY",
    "wof:placetype":"postalcode"
},
  "geometry": {"coordinates":[-1.5361056880919,55.06297656138954],"type":"Point"}
}