{
  "type": "Feature",
  "properties": {
    "iso:country":"GB",
    "wof:name":"RH7 6EY",
    "wof:placetype":"postalcode"
},
  "geometry": {"coordinates":[-0.01882998759495,51.17499450147262],"type":"Point"}
}