{
  "type": "Feature",
  "properties": {
    "iso:country": "GB",
    "wof:name": "MK4 1HG",
    "wof:placetype": "postalcode"
  },
  "geometry": {"coordinates":[-0.76794,52.009748],"type":"Point"}
}
