{
  "type": "Feature",
  "properties": {
    "date:inception_lower":"1990-02-01",
    "date:inception_upper":"1990-02-28",
    "iso:country":"GB",
    "wof:name":"MK4 1HG",
    "wof:placetype":"postalcode"
},
  "geometry": {"coordinates":[-0.76794,52.009748],"type":"Point"}
}