{
  "type": "Feature",
  "properties": {
    "iso:country":"GB",
    "wof:name":"MK4 1HG",
    "wof:placetype":"postalcode"
},
  "geometry": {"coordinates":[-0.76793957004297,52.0097479275293],"type":"Point"}
}