{
  "type": "Feature",
  "properties": {
    "iso:country":"GB",
    "wof:name":"BD3 0FA",
    "wof:placetype":"postalcode"
},
  "geometry": {"coordinates":[-1.75076559260464,53.8088363393371],"type":"Point"}
}