{
  "type": "Feature",
  "properties": {
    "date:inception_lower": "2014-01-01",
    "date:inception_upper": "2014-01-01",
    "iso:country": "GB",
    "wof:name": "BD3 0FA",
    "wof:placetype": "postalcode"
  },
  "geometry": {"coordinates":[-1.750766,53.808836],"type":"Point"}
}
