{
  "type": "Feature",
  "properties": {
    "iso:country":"GB",
    "wof:name":"BA2 8BL",
    "wof:placetype":"postalcode"
},
  "geometry": {"coordinates":[-2.41615697623422,51.33343877103961],"type":"Point"}
}