{
  "type": "Feature",
  "properties": {
    "date:inception_lower": "1980-01-01",
    "date:inception_upper": "1980-01-01",
    "iso:country": "GB",
    "wof:name": "BA2 8BL",
    "wof:placetype": "postalcode"
  },
  "geometry": {"coordinates":[-2.416157,51.333439],"type":"Point"}
}
