{
  "type": "Feature",
  "properties": {
    "iso:country":"GB",
    "wof:name":"E18 1PH",
    "wof:placetype":"postalcode"
},
  "geometry": {"coordinates":[0.03108667591994,51.58467291625595],"type":"Point"}
}