{
  "type": "Feature",
  "properties": {
    "iso:country": "GB",
    "wof:name": "NG16 1FE",
    "wof:placetype": "postalcode"
  },
  "geometry": {"coordinates":[-1.248207,52.996078],"type":"Point"}
}
