{
  "type": "Feature",
  "properties": {
    "date:inception_lower": "1980-01-01",
    "date:inception_upper": "1980-01-01",
    "iso:country": "GB",
    "wof:name": "NG16 1FE",
    "wof:placetype": "postalcode"
  },
  "geometry": {"coordinates":[-1.248207,52.996078],"type":"Point"}
}
