{
  "type": "Feature",
  "properties": {
    "iso:country":"GB",
    "wof:name":"WA1 4NU",
    "wof:placetype":"postalcode"
},
  "geometry": {"coordinates":[-2.5381620635972,53.39891561232773],"type":"Point"}
}