{
  "type": "Feature",
  "properties": {
    "iso:country": "GB",
    "wof:name": "WA1 4NU",
    "wof:placetype": "postalcode"
  },
  "geometry": {"coordinates":[-2.538162,53.398916],"type":"Point"}
}
