{
  "type": "Feature",
  "properties": {
    "date:inception_lower": "2007-10-01",
    "date:inception_upper": "2007-10-01",
    "iso:country": "GB",
    "wof:name": "CR2 6PN",
    "wof:placetype": "postalcode"
  },
  "geometry": {"coordinates":[-0.107379,51.352434],"type":"Point"}
}
