{
  "type": "Feature",
  "properties": {
    "iso:country":"GB",
    "wof:name":"CR2 6PN",
    "wof:placetype":"postalcode"
},
  "geometry": {"coordinates":[-0.10737923410207,51.35243361526506],"type":"Point"}
}