{
  "type": "Feature",
  "properties": {
    "iso:country": "GB",
    "wof:name": "CV1 2TL",
    "wof:placetype": "postalcode"
  },
  "geometry": {"coordinates":[-1.504076,52.401339],"type":"Point"}
}
