{
  "type": "Feature",
  "properties": {
    "iso:country":"GB",
    "wof:name":"CV1 2TL",
    "wof:placetype":"postalcode"
},
  "geometry": {"coordinates":[-1.50407649585437,52.40133940405517],"type":"Point"}
}