{
  "type": "Feature",
  "properties": {
    "date:inception_lower": "2004-02-01",
    "date:inception_upper": "2004-02-01",
    "iso:country": "GB",
    "wof:name": "CV1 2TL",
    "wof:placetype": "postalcode"
  },
  "geometry": {"coordinates":[-1.503581,52.401498],"type":"Point"}
}
