{
  "type": "Feature",
  "properties": {
    "iso:country":"GB",
    "wof:name":"ST7 3ST",
    "wof:placetype":"postalcode"
},
  "geometry": {"coordinates":[-2.26922415401948,53.12197272174409],"type":"Point"}
}