{
  "type": "Feature",
  "properties": {
    "iso:country":"GB",
    "wof:name":"NN8 4UR",
    "wof:placetype":"postalcode"
},
  "geometry": {"coordinates":[-0.70019321386578,52.31471450457902],"type":"Point"}
}