{
  "type": "Feature",
  "properties": {
    "iso:country":"GB",
    "wof:name":"CH61 5XN",
    "wof:placetype":"postalcode"
},
  "geometry": {"coordinates":[-3.09968245501061,53.34498501301756],"type":"Point"}
}