{
  "type": "Feature",
  "properties": {
    "date:inception_lower":"1980-01-01",
    "date:inception_upper":"1980-01-31",
    "iso:country":"GB",
    "wof:name":"TA13 5HW",
    "wof:placetype":"postalcode"
},
  "geometry": {"coordinates":[-2.809588,50.965838],"type":"Point"}
}