{
  "type": "Feature",
  "properties": {
    "iso:country": "GB",
    "wof:name": "TA13 5HW",
    "wof:placetype": "postalcode"
  },
  "geometry": {"coordinates":[-2.809588,50.965838],"type":"Point"}
}
