{
  "type": "Feature",
  "properties": {
    "iso:country":"GB",
    "wof:name":"TA13 5HW",
    "wof:placetype":"postalcode"
},
  "geometry": {"coordinates":[-2.80958757001624,50.96583759763467],"type":"Point"}
}