{
  "type": "Feature",
  "properties": {
    "iso:country": "GB",
    "wof:name": "SO50 4FS",
    "wof:placetype": "postalcode"
  },
  "geometry": {"coordinates":[-1.351887,50.975069],"type":"Point"}
}
