{
  "type": "Feature",
  "properties": {
    "iso:country":"GB",
    "wof:name":"DD2 1UB",
    "wof:placetype":"postalcode"
},
  "geometry": {"coordinates":[-3.0319779298634,56.46390045439437],"type":"Point"}
}