{
  "type": "Feature",
  "properties": {
    "iso:country": "GB",
    "wof:name": "DD2 1UB",
    "wof:placetype": "postalcode"
  },
  "geometry": {"coordinates":[-3.030987,56.463729],"type":"Point"}
}
