{
  "type": "Feature",
  "properties": {
    "date:inception_lower":"1996-06-01",
    "date:inception_upper":"1996-06-30",
    "iso:country":"GB",
    "wof:name":"DD2 1UB",
    "wof:placetype":"postalcode"
},
  "geometry": {"coordinates":[-3.031981,56.463891],"type":"Point"}
}