{
  "type": "Feature",
  "properties": {
    "iso:country": "GB",
    "wof:name": "B12 9NJ",
    "wof:placetype": "postalcode"
  },
  "geometry": {"coordinates":[-1.897781,52.456616],"type":"Point"}
}
