{
  "type": "Feature",
  "properties": {
    "date:inception_lower": "2005-10-01",
    "date:inception_upper": "2005-10-01",
    "iso:country": "GB",
    "wof:name": "SS1 2SS",
    "wof:placetype": "postalcode"
  },
  "geometry": {"coordinates":[0.728894,51.533544],"type":"Point"}
}
