{
  "type": "Feature",
  "properties": {
    "iso:country": "GB",
    "wof:name": "SE20 7NW",
    "wof:placetype": "postalcode"
  },
  "geometry": {"coordinates":[-0.047583,51.415454],"type":"Point"}
}
