{
  "type": "Feature",
  "properties": {
    "iso:country":"GB",
    "wof:name":"SY12 9BY",
    "wof:placetype":"postalcode"
},
  "geometry": {"coordinates":[-2.87454372236759,52.84342841755884],"type":"Point"}
}