{
  "type": "Feature",
  "properties": {
    "iso:country":"GB",
    "wof:name":"PE21 8JJ",
    "wof:placetype":"postalcode"
},
  "geometry": {"coordinates":[-0.04512624363459,52.9882650566628],"type":"Point"}
}