{
  "type": "Feature",
  "properties": {
    "iso:country":"GB",
    "wof:name":"SO50 6EB",
    "wof:placetype":"postalcode"
},
  "geometry": {"coordinates":[-1.33014819448059,50.9760510329079],"type":"Point"}
}