{
  "type": "Feature",
  "properties": {
    "iso:country":"GB",
    "wof:name":"BN27 2SH",
    "wof:placetype":"postalcode"
},
  "geometry": {"coordinates":[0.27114456777186,50.85766018484758],"type":"Point"}
}