{
  "type": "Feature",
  "properties": {
    "date:inception_lower":"1994-05-01",
    "date:inception_upper":"1994-05-31",
    "iso:country":"GB",
    "wof:name":"M32 9AB",
    "wof:placetype":"postalcode"
},
  "geometry": {"coordinates":[-2.311649,53.443676],"type":"Point"}
}