{
  "type": "Feature",
  "properties": {
    "iso:country": "GB",
    "wof:name": "TW20 8NL",
    "wof:placetype": "postalcode"
  },
  "geometry": {"coordinates":[-0.538871,51.43062],"type":"Point"}
}
