{
  "type": "Feature",
  "properties": {
    "iso:country":"GB",
    "wof:name":"TW20 8NL",
    "wof:placetype":"postalcode"
},
  "geometry": {"coordinates":[-0.53887142281876,51.43062016870445],"type":"Point"}
}