{
  "type": "Feature",
  "properties": {
    "date:inception_lower": "1987-04-01",
    "date:inception_upper": "1987-04-01",
    "iso:country": "GB",
    "wof:name": "ST7 3TR",
    "wof:placetype": "postalcode"
  },
  "geometry": {"coordinates":[-2.288012,53.111609],"type":"Point"}
}
