{
  "type": "Feature",
  "properties": {
    "iso:country":"GB",
    "wof:name":"PO21 3LH",
    "wof:placetype":"postalcode"
},
  "geometry": {"coordinates":[-0.72637114090692,50.78077603412751],"type":"Point"}
}