{
  "type": "Feature",
  "properties": {
    "date:inception_lower": "1980-01-01",
    "date:inception_upper": "1980-01-01",
    "iso:country": "GB",
    "wof:name": "PO21 3LH",
    "wof:placetype": "postalcode"
  },
  "geometry": {"coordinates":[-0.726371,50.780776],"type":"Point"}
}
