{
  "type": "Feature",
  "properties": {
    "date:inception_lower":"1980-01-01",
    "date:inception_upper":"1980-01-31",
    "iso:country":"GB",
    "wof:name":"CO4 5DA",
    "wof:placetype":"postalcode"
},
  "geometry": {"coordinates":[0.893711,51.905128],"type":"Point"}
}