{
  "type": "Feature",
  "properties": {
    "iso:country": "GB",
    "wof:name": "ME15 9YS",
    "wof:placetype": "postalcode"
  },
  "geometry": {"coordinates":[0.551921,51.239993],"type":"Point"}
}
