{
  "type": "Feature",
  "properties": {
    "date:inception_lower": "1980-01-01",
    "date:inception_upper": "1980-01-01",
    "iso:country": "GB",
    "wof:name": "LN6 7TA",
    "wof:placetype": "postalcode"
  },
  "geometry": {"coordinates":[-0.564111,53.2141],"type":"Point"}
}
