{
  "type": "Feature",
  "properties": {
    "iso:country":"GB",
    "wof:name":"LN6 7TA",
    "wof:placetype":"postalcode"
},
  "geometry": {"coordinates":[-0.56411124250516,53.21409956086882],"type":"Point"}
}