{
  "type": "Feature",
  "properties": {
    "iso:country":"GB",
    "wof:name":"EN1 1SJ",
    "wof:placetype":"postalcode"
},
  "geometry": {"coordinates":[-0.05607572080725,51.65149734847265],"type":"Point"}
}