{
  "type": "Feature",
  "properties": {
    "iso:country":"GB",
    "wof:name":"SW9 8AW",
    "wof:placetype":"postalcode"
},
  "geometry": {"coordinates":[-0.11950040757176,51.4621326623665],"type":"Point"}
}