{
  "type": "Feature",
  "properties": {
    "iso:country": "GB",
    "wof:name": "SW9 8AW",
    "wof:placetype": "postalcode"
  },
  "geometry": {"coordinates":[-0.1195,51.462133],"type":"Point"}
}
