{
  "type": "Feature",
  "properties": {
    "iso:country": "GB",
    "wof:name": "EH32 9GZ",
    "wof:placetype": "postalcode"
  },
  "geometry": {"coordinates":[-2.979483,55.955917],"type":"Point"}
}
