{
  "type": "Feature",
  "properties": {
    "iso:country":"GB",
    "wof:name":"M20 2RY",
    "wof:placetype":"postalcode"
},
  "geometry": {"coordinates":[-2.22635756656309,53.40907379585224],"type":"Point"}
}