{
  "type": "Feature",
  "properties": {
    "iso:country": "GB",
    "wof:name": "M20 2RY",
    "wof:placetype": "postalcode"
  },
  "geometry": {"coordinates":[-2.226358,53.409074],"type":"Point"}
}
