{
  "type": "Feature",
  "properties": {
    "iso:country": "GB",
    "wof:name": "GL7 1TF",
    "wof:placetype": "postalcode"
  },
  "geometry": {"coordinates":[-1.979143,51.70493],"type":"Point"}
}
