{
  "type": "Feature",
  "properties": {
    "iso:country": "GB",
    "wof:name": "DN11 9HG",
    "wof:placetype": "postalcode"
  },
  "geometry": {"coordinates":[-1.073812,53.440416],"type":"Point"}
}
