{
  "type": "Feature",
  "properties": {
    "iso:country":"GB",
    "wof:name":"DN11 9HG",
    "wof:placetype":"postalcode"
},
  "geometry": {"coordinates":[-1.07439937450207,53.43967265905417],"type":"Point"}
}