{
  "type": "Feature",
  "properties": {
    "iso:country":"GB",
    "wof:name":"B14 5EU",
    "wof:placetype":"postalcode"
},
  "geometry": {"coordinates":[-1.88588463131569,52.41305773184885],"type":"Point"}
}