{
  "type": "Feature",
  "properties": {
    "date:inception_lower": "1991-01-01",
    "date:inception_upper": "1991-01-01",
    "iso:country": "GB",
    "wof:name": "CH6 5XP",
    "wof:placetype": "postalcode"
  },
  "geometry": {"coordinates":[-3.146966,53.23959],"type":"Point"}
}
