{
  "type": "Feature",
  "properties": {
    "date:inception_lower": "1996-06-01",
    "date:inception_upper": "1996-06-01",
    "iso:country": "GB",
    "wof:name": "AB41 7QU",
    "wof:placetype": "postalcode"
  },
  "geometry": {"coordinates":[-2.220181,57.371509],"type":"Point"}
}
