{
  "type": "Feature",
  "properties": {
    "iso:country":"GB",
    "wof:name":"SY2 6EA",
    "wof:placetype":"postalcode"
},
  "geometry": {"coordinates":[-2.73343521159326,52.69610799081949],"type":"Point"}
}