{
  "type": "Feature",
  "properties": {
    "iso:country":"GB",
    "wof:name":"SA44 4BU",
    "wof:placetype":"postalcode"
},
  "geometry": {"coordinates":[-4.30944827010574,52.0413970656095],"type":"Point"}
}