{
  "type": "Feature",
  "properties": {
    "iso:country":"GB",
    "wof:name":"CH8 7GR",
    "wof:placetype":"postalcode"
},
  "geometry": {"coordinates":[-3.20849624092063,53.28919680438863],"type":"Point"}
}