{
  "type": "Feature",
  "properties": {
    "iso:country":"GB",
    "wof:name":"NG16 2FG",
    "wof:placetype":"postalcode"
},
  "geometry": {"coordinates":[-1.28932134866641,53.01472333263033],"type":"Point"}
}