{
  "type": "Feature",
  "properties": {
    "date:inception_lower": "1996-06-01",
    "date:inception_upper": "1996-06-01",
    "iso:country": "GB",
    "wof:name": "LS28 9BW",
    "wof:placetype": "postalcode"
  },
  "geometry": {"coordinates":[-1.6579,53.791303],"type":"Point"}
}
