{
  "type": "Feature",
  "properties": {
    "iso:country": "GB",
    "wof:name": "LS28 9BW",
    "wof:placetype": "postalcode"
  },
  "geometry": {"coordinates":[-1.65826,53.791226],"type":"Point"}
}
