{
  "type": "Feature",
  "properties": {
    "iso:country": "GB",
    "wof:name": "TF7 5FH",
    "wof:placetype": "postalcode"
  },
  "geometry": {"coordinates":[-2.466582,52.637476],"type":"Point"}
}
