{
  "type": "Feature",
  "properties": {
    "iso:country":"GB",
    "wof:name":"NG3 5JJ",
    "wof:placetype":"postalcode"
},
  "geometry": {"coordinates":[-1.13469927994254,52.97763351442517],"type":"Point"}
}