{
  "type": "Feature",
  "properties": {
    "iso:country": "GB",
    "wof:name": "NG3 5JJ",
    "wof:placetype": "postalcode"
  },
  "geometry": {"coordinates":[-1.134699,52.977634],"type":"Point"}
}
