{
  "type": "Feature",
  "properties": {
    "iso:country":"GB",
    "wof:name":"G40 2PE",
    "wof:placetype":"postalcode"
},
  "geometry": {"coordinates":[-4.22263333050473,55.85504457680225],"type":"Point"}
}