{
  "type": "Feature",
  "properties": {
    "iso:country": "GB",
    "wof:name": "SK5 6ZL",
    "wof:placetype": "postalcode"
  },
  "geometry": {"coordinates":[-2.163859,53.449875],"type":"Point"}
}
