{
  "type": "Feature",
  "properties": {
    "iso:country":"GB",
    "wof:name":"CB23 2NQ",
    "wof:placetype":"postalcode"
},
  "geometry": {"coordinates":[-0.03206059629602,52.17864514262686],"type":"Point"}
}