{
  "type": "Feature",
  "properties": {
    "date:inception_lower": "2006-09-01",
    "date:inception_upper": "2006-09-01",
    "iso:country": "GB",
    "wof:name": "CB23 2NQ",
    "wof:placetype": "postalcode"
  },
  "geometry": {"coordinates":[-0.032061,52.178645],"type":"Point"}
}
