{
  "type": "Feature",
  "properties": {
    "iso:country":"GB",
    "wof:name":"M41 0XU",
    "wof:placetype":"postalcode"
},
  "geometry": {"coordinates":[-2.34709701655959,53.45021191995302],"type":"Point"}
}