{
  "type": "Feature",
  "properties": {
    "iso:country":"GB",
    "wof:name":"GL6 6SG",
    "wof:placetype":"postalcode"
},
  "geometry": {"coordinates":[-2.19181311727298,51.77716208764042],"type":"Point"}
}