{
  "type": "Feature",
  "properties": {
    "date:inception_lower": "1980-01-01",
    "date:inception_upper": "1980-01-01",
    "iso:country": "GB",
    "wof:name": "PA16 8BN",
    "wof:placetype": "postalcode"
  },
  "geometry": {"coordinates":[-4.77391,55.957087],"type":"Point"}
}
