{
  "type": "Feature",
  "properties": {
    "iso:country":"GB",
    "wof:name":"PA16 8BN",
    "wof:placetype":"postalcode"
},
  "geometry": {"coordinates":[-4.7739623005365,55.95710235229222],"type":"Point"}
}