{
  "type": "Feature",
  "properties": {
    "iso:country": "GB",
    "wof:name": "PA16 8BN",
    "wof:placetype": "postalcode"
  },
  "geometry": {"coordinates":[-4.773962,55.957102],"type":"Point"}
}
