{
  "type": "Feature",
  "properties": {
    "date:inception_lower": "1980-01-01",
    "date:inception_upper": "1980-01-01",
    "iso:country": "GB",
    "wof:name": "TN15 7EG",
    "wof:placetype": "postalcode"
  },
  "geometry": {"coordinates":[0.284968,51.331227],"type":"Point"}
}
