{
  "type": "Feature",
  "properties": {
    "iso:country":"GB",
    "wof:name":"TN15 7EG",
    "wof:placetype":"postalcode"
},
  "geometry": {"coordinates":[0.28496754835702,51.33122685185681],"type":"Point"}
}