{
  "type": "Feature",
  "properties": {
    "date:inception_lower":"1982-12-01",
    "date:inception_upper":"1982-12-31",
    "iso:country":"GB",
    "wof:name":"DD10 0SL",
    "wof:placetype":"postalcode"
},
  "geometry": {"coordinates":[-2.282442,56.839896],"type":"Point"}
}