{
  "type": "Feature",
  "properties": {
    "iso:country":"GB",
    "wof:name":"DD10 0SL",
    "wof:placetype":"postalcode"
},
  "geometry": {"coordinates":[-2.28244175428527,56.83989616932387],"type":"Point"}
}