{
  "type": "Feature",
  "properties": {
    "iso:country": "GB",
    "wof:name": "DD10 0SL",
    "wof:placetype": "postalcode"
  },
  "geometry": {"coordinates":[-2.282442,56.839896],"type":"Point"}
}
