{
  "type": "Feature",
  "properties": {
    "iso:country":"GB",
    "wof:name":"LL28 5BN",
    "wof:placetype":"postalcode"
},
  "geometry": {"coordinates":[-3.76079944354036,53.29527356969263],"type":"Point"}
}