{
  "type": "Feature",
  "properties": {
    "date:inception_lower": "1994-05-01",
    "date:inception_upper": "1994-05-01",
    "iso:country": "GB",
    "wof:name": "M21 7NU",
    "wof:placetype": "postalcode"
  },
  "geometry": {"coordinates":[-2.26217,53.422969],"type":"Point"}
}
