{
  "type": "Feature",
  "properties": {
    "iso:country": "GB",
    "wof:name": "ML11 8HG",
    "wof:placetype": "postalcode"
  },
  "geometry": {"coordinates":[-3.628118,55.698479],"type":"Point"}
}
