{
  "type": "Feature",
  "properties": {
    "iso:country":"GB",
    "wof:name":"ML11 8HG",
    "wof:placetype":"postalcode"
},
  "geometry": {"coordinates":[-3.62811843714281,55.69847936873943],"type":"Point"}
}