{
  "type": "Feature",
  "properties": {
    "iso:country":"GB",
    "wof:name":"TN4 8LT",
    "wof:placetype":"postalcode"
},
  "geometry": {"coordinates":[0.24195050319769,51.11948217683678],"type":"Point"}
}