{
  "type": "Feature",
  "properties": {
    "iso:country":"GB",
    "wof:name":"M20 1ER",
    "wof:placetype":"postalcode"
},
  "geometry": {"coordinates":[-2.23544660103327,53.43411626940371],"type":"Point"}
}