{
  "type": "Feature",
  "properties": {
    "date:inception_lower": "1980-01-01",
    "date:inception_upper": "1980-01-01",
    "iso:country": "GB",
    "wof:name": "RG26 5DF",
    "wof:placetype": "postalcode"
  },
  "geometry": {"coordinates":[-1.075299,51.326431],"type":"Point"}
}
