{
  "type": "Feature",
  "properties": {
    "iso:country":"GB",
    "wof:name":"DL14 7PY",
    "wof:placetype":"postalcode"
},
  "geometry": {"coordinates":[-1.68163457849226,54.66538198353771],"type":"Point"}
}