{
  "type": "Feature",
  "properties": {
    "date:inception_lower":"1980-01-01",
    "date:inception_upper":"1980-01-31",
    "iso:country":"GB",
    "wof:name":"SA44 6DX",
    "wof:placetype":"postalcode"
},
  "geometry": {"coordinates":[-4.437388,52.135758],"type":"Point"}
}