{
  "type": "Feature",
  "properties": {
    "iso:country":"GB",
    "wof:name":"SA44 6DX",
    "wof:placetype":"postalcode"
},
  "geometry": {"coordinates":[-4.4373876251741,52.13575816882912],"type":"Point"}
}