{
  "type": "Feature",
  "properties": {
    "date:inception_lower": "2018-07-01",
    "date:inception_upper": "2018-07-01",
    "iso:country": "GB",
    "wof:name": "BB7 1FL",
    "wof:placetype": "postalcode"
  },
  "geometry": {"coordinates":[-2.402869,53.862377],"type":"Point"}
}
