{
  "type": "Feature",
  "properties": {
    "iso:country":"GB",
    "wof:name":"LS15 4DX",
    "wof:placetype":"postalcode"
},
  "geometry": {"coordinates":[-1.39146075838697,53.83246731310368],"type":"Point"}
}