{
  "type": "Feature",
  "properties": {
    "date:inception_lower":"1980-01-01",
    "date:inception_upper":"1980-01-31",
    "iso:country":"GB",
    "wof:name":"L19 5PG",
    "wof:placetype":"postalcode"
},
  "geometry": {"coordinates":[-2.889436,53.356688],"type":"Point"}
}