{
  "type": "Feature",
  "properties": {
    "iso:country":"GB",
    "wof:name":"NR1 2AR",
    "wof:placetype":"postalcode"
},
  "geometry": {"coordinates":[1.30300179143705,52.61865152461691],"type":"Point"}
}