{
  "type": "Feature",
  "properties": {
    "iso:country": "GB",
    "wof:name": "NR1 2AR",
    "wof:placetype": "postalcode"
  },
  "geometry": {"coordinates":[1.303002,52.618652],"type":"Point"}
}
