{
  "type": "Feature",
  "properties": {
    "iso:country": "GB",
    "wof:name": "TR26 2NX",
    "wof:placetype": "postalcode"
  },
  "geometry": {"coordinates":[-5.459145,50.196118],"type":"Point"}
}
