{
  "type": "Feature",
  "properties": {
    "iso:country":"GB",
    "wof:name":"LU4 9JQ",
    "wof:placetype":"postalcode"
},
  "geometry": {"coordinates":[-0.47205723947597,51.90882280754898],"type":"Point"}
}