{
  "type": "Feature",
  "properties": {
    "iso:country": "GB",
    "wof:name": "WR10 2NF",
    "wof:placetype": "postalcode"
  },
  "geometry": {"coordinates":[-2.014837,52.162877],"type":"Point"}
}
