{
  "type": "Feature",
  "properties": {
    "iso:country":"GB",
    "wof:name":"WR10 2NF",
    "wof:placetype":"postalcode"
},
  "geometry": {"coordinates":[-2.01483700353281,52.16287690673872],"type":"Point"}
}