{
  "type": "Feature",
  "properties": {
    "iso:country":"GB",
    "wof:name":"HR2 8EE",
    "wof:placetype":"postalcode"
},
  "geometry": {"coordinates":[-2.7360086267197,52.01039881126204],"type":"Point"}
}