{
  "type": "Feature",
  "properties": {
    "iso:country":"GB",
    "wof:name":"ST6 4HG",
    "wof:placetype":"postalcode"
},
  "geometry": {"coordinates":[-2.20229255766477,53.05437293756],"type":"Point"}
}