{
  "type": "Feature",
  "properties": {
    "iso:country":"GB",
    "wof:name":"WA3 3HN",
    "wof:placetype":"postalcode"
},
  "geometry": {"coordinates":[-2.58575926272698,53.47746790693735],"type":"Point"}
}