{
  "type": "Feature",
  "properties": {
    "iso:country":"GB",
    "wof:name":"G66 7EG",
    "wof:placetype":"postalcode"
},
  "geometry": {"coordinates":[-4.19381958397676,55.97362736787951],"type":"Point"}
}