{
  "type": "Feature",
  "properties": {
    "iso:country": "GB",
    "wof:name": "CO7 7FE",
    "wof:placetype": "postalcode"
  },
  "geometry": {"coordinates":[0.986631,51.921704],"type":"Point"}
}
