{
  "type": "Feature",
  "properties": {
    "iso:country":"GB",
    "wof:name":"NR6 5RR",
    "wof:placetype":"postalcode"
},
  "geometry": {"coordinates":[1.25232491708782,52.66236950618612],"type":"Point"}
}