{
  "type": "Feature",
  "properties": {
    "iso:country":"GB",
    "wof:name":"AB42 2FT",
    "wof:placetype":"postalcode"
},
  "geometry": {"coordinates":[-1.8066755261763,57.49857460236502],"type":"Point"}
}