{
  "type": "Feature",
  "properties": {
    "iso:country":"GB",
    "wof:name":"SA4 3SL",
    "wof:placetype":"postalcode"
},
  "geometry": {"coordinates":[-4.1279951612605,51.63748669635523],"type":"Point"}
}