{
  "type": "Feature",
  "properties": {
    "date:inception_lower": "1980-01-01",
    "date:inception_upper": "1980-01-01",
    "iso:country": "GB",
    "wof:name": "LS15 4LS",
    "wof:placetype": "postalcode"
  },
  "geometry": {"coordinates":[-1.395152,53.825161],"type":"Point"}
}
