{
  "type": "Feature",
  "properties": {
    "iso:country":"GB",
    "wof:name":"LS15 4LS",
    "wof:placetype":"postalcode"
},
  "geometry": {"coordinates":[-1.39515188025334,53.82516070141717],"type":"Point"}
}