{
  "type": "Feature",
  "properties": {
    "iso:country": "GB",
    "wof:name": "PE21 7JP",
    "wof:placetype": "postalcode"
  },
  "geometry": {"coordinates":[-0.032069,52.965447],"type":"Point"}
}
