{
  "type": "Feature",
  "properties": {
    "date:inception_lower": "1980-01-01",
    "date:inception_upper": "1980-01-01",
    "iso:country": "GB",
    "wof:name": "PE21 7JP",
    "wof:placetype": "postalcode"
  },
  "geometry": {"coordinates":[-0.032061,52.965471],"type":"Point"}
}
