{
  "type": "Feature",
  "properties": {
    "iso:country": "GB",
    "wof:name": "LL17 0AT",
    "wof:placetype": "postalcode"
  },
  "geometry": {"coordinates":[-3.381621,53.252545],"type":"Point"}
}
