{
  "type": "Feature",
  "properties": {
    "iso:country":"GB",
    "wof:name":"LL17 0AT",
    "wof:placetype":"postalcode"
},
  "geometry": {"coordinates":[-3.38162079725426,53.2525449646912],"type":"Point"}
}