{
  "type": "Feature",
  "properties": {
    "iso:country": "GB",
    "wof:name": "BS31 3HT",
    "wof:placetype": "postalcode"
  },
  "geometry": {"coordinates":[-2.454893,51.396677],"type":"Point"}
}
