{
  "type": "Feature",
  "properties": {
    "date:inception_lower":"1980-01-01",
    "date:inception_upper":"1980-01-31",
    "iso:country":"GB",
    "wof:name":"TR26 3JR",
    "wof:placetype":"postalcode"
},
  "geometry": {"coordinates":[-5.439977,50.183319],"type":"Point"}
}