{
  "type": "Feature",
  "properties": {
    "iso:country":"GB",
    "wof:name":"PO16 9LN",
    "wof:placetype":"postalcode"
},
  "geometry": {"coordinates":[-1.12661441844164,50.83949438646323],"type":"Point"}
}