{
  "type": "Feature",
  "properties": {
    "date:inception_lower": "1999-06-01",
    "date:inception_upper": "1999-06-01",
    "iso:country": "GB",
    "wof:name": "RG12 1LP",
    "wof:placetype": "postalcode"
  },
  "geometry": {"coordinates":[-0.751986,51.414334],"type":"Point"}
}
