{
  "type": "Feature",
  "properties": {
    "iso:country": "GB",
    "wof:name": "RG12 1LP",
    "wof:placetype": "postalcode"
  },
  "geometry": {"coordinates":[-0.751986,51.414334],"type":"Point"}
}
