{
  "type": "Feature",
  "properties": {
    "iso:country":"GB",
    "wof:name":"LL22 8TN",
    "wof:placetype":"postalcode"
},
  "geometry": {"coordinates":[-3.59351165885751,53.2013282884003],"type":"Point"}
}