{
  "type": "Feature",
  "properties": {
    "date:inception_lower": "1980-01-01",
    "date:inception_upper": "1980-01-01",
    "iso:country": "GB",
    "wof:name": "LL22 8TN",
    "wof:placetype": "postalcode"
  },
  "geometry": {"coordinates":[-3.592888,53.200598],"type":"Point"}
}
