{
  "type": "Feature",
  "properties": {
    "iso:country":"GB",
    "wof:name":"CW11 3GB",
    "wof:placetype":"postalcode"
},
  "geometry": {"coordinates":[-2.39217761248977,53.14228772637043],"type":"Point"}
}