{
  "type": "Feature",
  "properties": {
    "date:inception_lower":"1999-06-01",
    "date:inception_upper":"1999-06-30",
    "iso:country":"GB",
    "wof:name":"NE32 3LE",
    "wof:placetype":"postalcode"
},
  "geometry": {"coordinates":[-1.489949,54.981583],"type":"Point"}
}