{
  "type": "Feature",
  "properties": {
    "date:inception_lower": "1980-01-01",
    "date:inception_upper": "1980-01-01",
    "iso:country": "GB",
    "wof:name": "DN9 1LQ",
    "wof:placetype": "postalcode"
  },
  "geometry": {"coordinates":[-0.869066,53.539597],"type":"Point"}
}
