{
  "type": "Feature",
  "properties": {
    "iso:country":"GB",
    "wof:name":"DN9 1LQ",
    "wof:placetype":"postalcode"
},
  "geometry": {"coordinates":[-0.86906645436036,53.53959734188552],"type":"Point"}
}