{
  "type": "Feature",
  "properties": {
    "iso:country": "GB",
    "wof:name": "DH8 5UA",
    "wof:placetype": "postalcode"
  },
  "geometry": {"coordinates":[-1.840277,54.860289],"type":"Point"}
}
