{
  "type": "Feature",
  "properties": {
    "iso:country":"GB",
    "wof:name":"DH8 5UA",
    "wof:placetype":"postalcode"
},
  "geometry": {"coordinates":[-1.84027734438324,54.86028870426922],"type":"Point"}
}