{
  "type": "Feature",
  "properties": {
    "date:inception_lower": "2006-04-01",
    "date:inception_upper": "2006-04-01",
    "iso:country": "GB",
    "wof:name": "NE30 4HS",
    "wof:placetype": "postalcode"
  },
  "geometry": {"coordinates":[-1.422733,55.02165],"type":"Point"}
}
