{
  "type": "Feature",
  "properties": {
    "iso:country":"GB",
    "wof:name":"NE30 4HS",
    "wof:placetype":"postalcode"
},
  "geometry": {"coordinates":[-1.42273287863344,55.02164963070732],"type":"Point"}
}