{
  "type": "Feature",
  "properties": {
    "iso:country":"GB",
    "wof:name":"N3 1SB",
    "wof:placetype":"postalcode"
},
  "geometry": {"coordinates":[-0.20115938837631,51.59805741326594],"type":"Point"}
}