{
  "type": "Feature",
  "properties": {
    "iso:country":"GB",
    "wof:name":"S75 2ND",
    "wof:placetype":"postalcode"
},
  "geometry": {"coordinates":[-1.50199811067666,53.55920492130651],"type":"Point"}
}