{
  "type": "Feature",
  "properties": {
    "iso:country": "GB",
    "wof:name": "HD2 2NL",
    "wof:placetype": "postalcode"
  },
  "geometry": {"coordinates":[-1.793236,53.66731],"type":"Point"}
}
