{
  "type": "Feature",
  "properties": {
    "date:inception_lower": "1980-01-01",
    "date:inception_upper": "1980-01-01",
    "iso:country": "GB",
    "wof:name": "HD2 2NL",
    "wof:placetype": "postalcode"
  },
  "geometry": {"coordinates":[-1.793236,53.66731],"type":"Point"}
}
