{
  "type": "Feature",
  "properties": {
    "iso:country":"GB",
    "wof:name":"HD2 2NL",
    "wof:placetype":"postalcode"
},
  "geometry": {"coordinates":[-1.79299414227109,53.66733659103286],"type":"Point"}
}