{
  "type": "Feature",
  "properties": {
    "date:inception_lower": "1980-01-01",
    "date:inception_upper": "1980-01-01",
    "iso:country": "GB",
    "wof:name": "S42 5LB",
    "wof:placetype": "postalcode"
  },
  "geometry": {"coordinates":[-1.387509,53.189031],"type":"Point"}
}
