{
  "type": "Feature",
  "properties": {
    "date:inception_lower":"1980-01-01",
    "date:inception_upper":"1980-01-31",
    "iso:country":"GB",
    "wof:name":"BR6 9LY",
    "wof:placetype":"postalcode"
},
  "geometry": {"coordinates":[0.08335,51.362677],"type":"Point"}
}