{
  "type": "Feature",
  "properties": {
    "iso:country":"GB",
    "wof:name":"TW1 2QF",
    "wof:placetype":"postalcode"
},
  "geometry": {"coordinates":[-0.31091274968102,51.45768172223961],"type":"Point"}
}