{
  "type": "Feature",
  "properties": {
    "date:inception_lower": "1980-01-01",
    "date:inception_upper": "1980-01-01",
    "iso:country": "GB",
    "wof:name": "DE13 0BT",
    "wof:placetype": "postalcode"
  },
  "geometry": {"coordinates":[-1.620419,52.834521],"type":"Point"}
}
