{
  "type": "Feature",
  "properties": {
    "iso:country":"GB",
    "wof:name":"DE13 0BT",
    "wof:placetype":"postalcode"
},
  "geometry": {"coordinates":[-1.62041879896537,52.83452082759426],"type":"Point"}
}