{
  "type": "Feature",
  "properties": {
    "iso:country":"GB",
    "wof:name":"CM17 0PQ",
    "wof:placetype":"postalcode"
},
  "geometry": {"coordinates":[0.16541543625939,51.78224077017962],"type":"Point"}
}