{
  "type": "Feature",
  "properties": {
    "date:inception_lower":"1980-01-01",
    "date:inception_upper":"1980-01-31",
    "iso:country":"GB",
    "wof:name":"CM17 0PQ",
    "wof:placetype":"postalcode"
},
  "geometry": {"coordinates":[0.165415,51.782241],"type":"Point"}
}