{
  "type": "Feature",
  "properties": {
    "iso:country":"GB",
    "wof:name":"DE45 1LY",
    "wof:placetype":"postalcode"
},
  "geometry": {"coordinates":[-1.73104451062432,53.15694165119545],"type":"Point"}
}