{
  "type": "Feature",
  "properties": {
    "iso:country": "GB",
    "wof:name": "PO10 8BN",
    "wof:placetype": "postalcode"
  },
  "geometry": {"coordinates":[-0.927811,50.845706],"type":"Point"}
}
