{
  "type": "Feature",
  "properties": {
    "iso:country":"GB",
    "wof:name":"PO10 8BN",
    "wof:placetype":"postalcode"
},
  "geometry": {"coordinates":[-0.92781114961292,50.84570620542734],"type":"Point"}
}