{
  "type": "Feature",
  "properties": {
    "iso:country":"GB",
    "wof:name":"SG6 4UJ",
    "wof:placetype":"postalcode"
},
  "geometry": {"coordinates":[-0.23937631286855,51.97942158642189],"type":"Point"}
}