{
  "type": "Feature",
  "properties": {
    "iso:country":"GB",
    "wof:name":"SG1 3DT",
    "wof:placetype":"postalcode"
},
  "geometry": {"coordinates":[-0.20846956459162,51.91097720341384],"type":"Point"}
}