{
  "type": "Feature",
  "properties": {
    "iso:country":"GB",
    "wof:name":"TN38 9RZ",
    "wof:placetype":"postalcode"
},
  "geometry": {"coordinates":[0.5342905257436,50.87797289014334],"type":"Point"}
}