{
  "type": "Feature",
  "properties": {
    "iso:country":"GB",
    "wof:name":"B71 4LP",
    "wof:placetype":"postalcode"
},
  "geometry": {"coordinates":[-1.96400712300168,52.50751101366261],"type":"Point"}
}