{
  "type": "Feature",
  "properties": {
    "iso:country": "GB",
    "wof:name": "NE5 4EE",
    "wof:placetype": "postalcode"
  },
  "geometry": {"coordinates":[-1.681691,55.004746],"type":"Point"}
}
