{
  "type": "Feature",
  "properties": {
    "iso:country":"GB",
    "wof:name":"NE5 4EE",
    "wof:placetype":"postalcode"
},
  "geometry": {"coordinates":[-1.68169084274584,55.00474629014652],"type":"Point"}
}