{
  "type": "Feature",
  "properties": {
    "iso:country":"GB",
    "wof:name":"PO4 0NG",
    "wof:placetype":"postalcode"
},
  "geometry": {"coordinates":[-1.07018987016726,50.78511096051665],"type":"Point"}
}