{
  "type": "Feature",
  "properties": {
    "iso:country":"GB",
    "wof:name":"BL1 8AN",
    "wof:placetype":"postalcode"
},
  "geometry": {"coordinates":[-2.44397854171126,53.59447919219787],"type":"Point"}
}