{
  "type": "Feature",
  "properties": {
    "date:inception_lower": "1994-05-01",
    "date:inception_upper": "1994-05-01",
    "iso:country": "GB",
    "wof:name": "M40 7UJ",
    "wof:placetype": "postalcode"
  },
  "geometry": {"coordinates":[-2.221241,53.492721],"type":"Point"}
}
