{
  "type": "Feature",
  "properties": {
    "iso:country":"GB",
    "wof:name":"CH63 9YN",
    "wof:placetype":"postalcode"
},
  "geometry": {"coordinates":[-3.0076031061819,53.33543386146425],"type":"Point"}
}