{
  "type": "Feature",
  "properties": {
    "date:inception_lower": "1996-06-01",
    "date:inception_upper": "1996-06-01",
    "iso:country": "GB",
    "wof:name": "AB15 6WT",
    "wof:placetype": "postalcode"
  },
  "geometry": {"coordinates":[-2.176978,57.149009],"type":"Point"}
}
