{
  "type": "Feature",
  "properties": {
    "iso:country": "GB",
    "wof:name": "IV17 0PX",
    "wof:placetype": "postalcode"
  },
  "geometry": {"coordinates":[-4.257016,57.696554],"type":"Point"}
}
