{
  "type": "Feature",
  "properties": {
    "iso:country": "GB",
    "wof:name": "S40 3QE",
    "wof:placetype": "postalcode"
  },
  "geometry": {"coordinates":[-1.46632,53.236062],"type":"Point"}
}
