{
  "type": "Feature",
  "properties": {
    "iso:country": "GB",
    "wof:name": "S40 3QE",
    "wof:placetype": "postalcode"
  },
  "geometry": {"coordinates":[-1.46641,53.236071],"type":"Point"}
}
