{
  "type": "Feature",
  "properties": {
    "iso:country":"GB",
    "wof:name":"S40 3QE",
    "wof:placetype":"postalcode"
},
  "geometry": {"coordinates":[-1.46632106661682,53.23604318596728],"type":"Point"}
}