{
  "type": "Feature",
  "properties": {
    "date:inception_lower": "1980-01-01",
    "date:inception_upper": "1980-01-01",
    "iso:country": "GB",
    "wof:name": "S40 3QE",
    "wof:placetype": "postalcode"
  },
  "geometry": {"coordinates":[-1.46641,53.236071],"type":"Point"}
}
