{
  "type": "Feature",
  "properties": {
    "iso:country": "GB",
    "wof:name": "PO19 7LW",
    "wof:placetype": "postalcode"
  },
  "geometry": {"coordinates":[-0.768567,50.838487],"type":"Point"}
}
