{
  "type": "Feature",
  "properties": {
    "iso:country":"GB",
    "wof:name":"PO19 7LW",
    "wof:placetype":"postalcode"
},
  "geometry": {"coordinates":[-0.76865785173161,50.83847015329066],"type":"Point"}
}