{
  "type": "Feature",
  "properties": {
    "iso:country": "GB",
    "wof:name": "WA11 9SR",
    "wof:placetype": "postalcode"
  },
  "geometry": {"coordinates":[-2.642437,53.474102],"type":"Point"}
}
