{
  "type": "Feature",
  "properties": {
    "iso:country":"GB",
    "wof:name":"WA11 9SR",
    "wof:placetype":"postalcode"
},
  "geometry": {"coordinates":[-2.64243710201845,53.47410243930903],"type":"Point"}
}