{
  "type": "Feature",
  "properties": {
    "iso:country": "GB",
    "wof:name": "CF5 1AU",
    "wof:placetype": "postalcode"
  },
  "geometry": {"coordinates":[-3.207318,51.482384],"type":"Point"}
}
