{
  "type": "Feature",
  "properties": {
    "iso:country":"GB",
    "wof:name":"CF5 1AU",
    "wof:placetype":"postalcode"
},
  "geometry": {"coordinates":[-3.20731791042582,51.4823835688444],"type":"Point"}
}