{
  "type": "Feature",
  "properties": {
    "date:inception_lower": "1980-01-01",
    "date:inception_upper": "1980-01-01",
    "iso:country": "GB",
    "wof:name": "LN7 6AZ",
    "wof:placetype": "postalcode"
  },
  "geometry": {"coordinates":[-0.269506,53.48139],"type":"Point"}
}
