{
  "type": "Feature",
  "properties": {
    "iso:country":"GB",
    "wof:name":"M32 9RQ",
    "wof:placetype":"postalcode"
},
  "geometry": {"coordinates":[-2.32208704659202,53.45427291679115],"type":"Point"}
}