{
  "type": "Feature",
  "properties": {
    "iso:country": "GB",
    "wof:name": "M32 9RQ",
    "wof:placetype": "postalcode"
  },
  "geometry": {"coordinates":[-2.322087,53.454273],"type":"Point"}
}
