{
  "type": "Feature",
  "properties": {
    "iso:country":"GB",
    "wof:name":"BD6 1HL",
    "wof:placetype":"postalcode"
},
  "geometry": {"coordinates":[-1.77146399115523,53.76405439076278],"type":"Point"}
}