{
  "type": "Feature",
  "properties": {
    "iso:country":"GB",
    "wof:name":"PE8 6PW",
    "wof:placetype":"postalcode"
},
  "geometry": {"coordinates":[-0.4279680794219,52.56814919533115],"type":"Point"}
}