{
  "type": "Feature",
  "properties": {
    "iso:country":"GB",
    "wof:name":"N19 3NA",
    "wof:placetype":"postalcode"
},
  "geometry": {"coordinates":[-0.12983901208974,51.57256423192285],"type":"Point"}
}