{
  "type": "Feature",
  "properties": {
    "iso:country":"GB",
    "wof:name":"LS12 3AE",
    "wof:placetype":"postalcode"
},
  "geometry": {"coordinates":[-1.59117345349871,53.79684031885559],"type":"Point"}
}