{
  "type": "Feature",
  "properties": {
    "iso:country": "GB",
    "wof:name": "LS12 3AE",
    "wof:placetype": "postalcode"
  },
  "geometry": {"coordinates":[-1.591173,53.79684],"type":"Point"}
}
