{
  "type": "Feature",
  "properties": {
    "iso:country": "GB",
    "wof:name": "OX10 7DD",
    "wof:placetype": "postalcode"
  },
  "geometry": {"coordinates":[-1.137069,51.638933],"type":"Point"}
}
