{
  "type": "Feature",
  "properties": {
    "iso:country": "GB",
    "wof:name": "LS22 7UZ",
    "wof:placetype": "postalcode"
  },
  "geometry": {"coordinates":[-1.37683,53.939195],"type":"Point"}
}
