{
  "type": "Feature",
  "properties": {
    "date:inception_lower": "2018-09-01",
    "date:inception_upper": "2018-09-01",
    "iso:country": "GB",
    "wof:name": "AB39 9AP",
    "wof:placetype": "postalcode"
  },
  "geometry": {"coordinates":[-2.207895,56.96523],"type":"Point"}
}
