{
  "type": "Feature",
  "properties": {
    "iso:country":"GB",
    "wof:name":"NG17 7BE",
    "wof:placetype":"postalcode"
},
  "geometry": {"coordinates":[-1.24485480166654,53.09938025156368],"type":"Point"}
}