{
  "type": "Feature",
  "properties": {
    "iso:country": "GB",
    "wof:name": "NG17 7BE",
    "wof:placetype": "postalcode"
  },
  "geometry": {"coordinates":[-1.244866,53.099462],"type":"Point"}
}
