{
  "type": "Feature",
  "properties": {
    "iso:country":"GB",
    "wof:name":"TA2 7RE",
    "wof:placetype":"postalcode"
},
  "geometry": {"coordinates":[-3.09319641135493,51.03758065308048],"type":"Point"}
}