{
  "type": "Feature",
  "properties": {
    "date:inception_lower": "2012-04-01",
    "date:inception_upper": "2012-04-01",
    "iso:country": "GB",
    "wof:name": "ML11 7TA",
    "wof:placetype": "postalcode"
  },
  "geometry": {"coordinates":[-3.733443,55.687582],"type":"Point"}
}
