{
  "type": "Feature",
  "properties": {
    "iso:country":"GB",
    "wof:name":"DN17 4BL",
    "wof:placetype":"postalcode"
},
  "geometry": {"coordinates":[-0.85439362701999,53.61913454796824],"type":"Point"}
}