{
  "type": "Feature",
  "properties": {
    "date:inception_lower": "1980-01-01",
    "date:inception_upper": "1980-01-01",
    "iso:country": "GB",
    "wof:name": "GU6 7EQ",
    "wof:placetype": "postalcode"
  },
  "geometry": {"coordinates":[-0.4726,51.145676],"type":"Point"}
}
