{
  "type": "Feature",
  "properties": {
    "iso:country":"GB",
    "wof:name":"GU6 7EQ",
    "wof:placetype":"postalcode"
},
  "geometry": {"coordinates":[-0.4726002659884,51.14567588232682],"type":"Point"}
}