{
  "type": "Feature",
  "properties": {
    "iso:country": "GB",
    "wof:name": "NR12 9BS",
    "wof:placetype": "postalcode"
  },
  "geometry": {"coordinates":[1.516259,52.775678],"type":"Point"}
}
