{
  "type": "Feature",
  "properties": {
    "iso:country":"GB",
    "wof:name":"NR12 9BS",
    "wof:placetype":"postalcode"
},
  "geometry": {"coordinates":[1.51625942186466,52.77567843488437],"type":"Point"}
}