{
  "type": "Feature",
  "properties": {
    "iso:country": "GB",
    "wof:name": "BS48 3AF",
    "wof:placetype": "postalcode"
  },
  "geometry": {"coordinates":[-2.742518,51.421796],"type":"Point"}
}
