{
  "type": "Feature",
  "properties": {
    "iso:country":"GB",
    "wof:name":"B97 5NF",
    "wof:placetype":"postalcode"
},
  "geometry": {"coordinates":[-1.94877587808164,52.27526432727326],"type":"Point"}
}