{
  "type": "Feature",
  "properties": {
    "iso:country":"GB",
    "wof:name":"TW5 9BA",
    "wof:placetype":"postalcode"
},
  "geometry": {"coordinates":[-0.39479125324623,51.47726732986347],"type":"Point"}
}