{
  "type": "Feature",
  "properties": {
    "iso:country":"GB",
    "wof:name":"NE12 7EE",
    "wof:placetype":"postalcode"
},
  "geometry": {"coordinates":[-1.58368485437543,55.02997149207692],"type":"Point"}
}