{
  "type": "Feature",
  "properties": {
    "date:inception_lower":"2007-09-01",
    "date:inception_upper":"2007-09-30",
    "iso:country":"GB",
    "wof:name":"B50 4LX",
    "wof:placetype":"postalcode"
},
  "geometry": {"coordinates":[-1.834944,52.171789],"type":"Point"}
}