{
  "type": "Feature",
  "properties": {
    "iso:country": "GB",
    "wof:name": "B50 4LX",
    "wof:placetype": "postalcode"
  },
  "geometry": {"coordinates":[-1.834944,52.171789],"type":"Point"}
}
