{
  "type": "Feature",
  "properties": {
    "iso:country":"GB",
    "wof:name":"B50 4LX",
    "wof:placetype":"postalcode"
},
  "geometry": {"coordinates":[-1.83494383265205,52.17178918336086],"type":"Point"}
}