{
  "type": "Feature",
  "properties": {
    "iso:country":"GB",
    "wof:name":"WA10 6SF",
    "wof:placetype":"postalcode"
},
  "geometry": {"coordinates":[-2.75691614810164,53.46256460976493],"type":"Point"}
}