{
  "type": "Feature",
  "properties": {
    "date:inception_lower": "1980-01-01",
    "date:inception_upper": "1980-01-01",
    "iso:country": "GB",
    "wof:name": "SR4 8BJ",
    "wof:placetype": "postalcode"
  },
  "geometry": {"coordinates":[-1.42915,54.896796],"type":"Point"}
}
