{
  "type": "Feature",
  "properties": {
    "iso:country":"GB",
    "wof:name":"SR4 8BJ",
    "wof:placetype":"postalcode"
},
  "geometry": {"coordinates":[-1.42915013164418,54.89679635286241],"type":"Point"}
}