{
  "type": "Feature",
  "properties": {
    "iso:country":"GB",
    "wof:name":"SE11 5RB",
    "wof:placetype":"postalcode"
},
  "geometry": {"coordinates":[-0.1156727940156,51.48725045250914],"type":"Point"}
}