{
  "type": "Feature",
  "properties": {
    "date:inception_lower": "1980-01-01",
    "date:inception_upper": "1980-01-01",
    "iso:country": "GB",
    "wof:name": "SE11 5RB",
    "wof:placetype": "postalcode"
  },
  "geometry": {"coordinates":[-0.115673,51.48725],"type":"Point"}
}
