{
  "type": "Feature",
  "properties": {
    "iso:country":"GB",
    "wof:name":"CM17 9EA",
    "wof:placetype":"postalcode"
},
  "geometry": {"coordinates":[0.1288950710195,51.75700054046968],"type":"Point"}
}