{
  "type": "Feature",
  "properties": {
    "iso:country": "GB",
    "wof:name": "CM17 9EA",
    "wof:placetype": "postalcode"
  },
  "geometry": {"coordinates":[0.128895,51.757001],"type":"Point"}
}
