{
  "type": "Feature",
  "properties": {
    "date:inception_lower":"1980-01-01",
    "date:inception_upper":"1980-01-31",
    "iso:country":"GB",
    "wof:name":"BS4 2DD",
    "wof:placetype":"postalcode"
},
  "geometry": {"coordinates":[-2.574959,51.439184],"type":"Point"}
}