{
  "type": "Feature",
  "properties": {
    "iso:country": "GB",
    "wof:name": "BS10 7RT",
    "wof:placetype": "postalcode"
  },
  "geometry": {"coordinates":[-2.650729,51.516511],"type":"Point"}
}
