{
  "type": "Feature",
  "properties": {
    "iso:country":"GB",
    "wof:name":"BS10 7RT",
    "wof:placetype":"postalcode"
},
  "geometry": {"coordinates":[-2.6507285582648,51.51651122304616],"type":"Point"}
}