{
  "type": "Feature",
  "properties": {
    "iso:country":"GB",
    "wof:name":"DL10 6RT",
    "wof:placetype":"postalcode"
},
  "geometry": {"coordinates":[-1.61578795210624,54.46324726065554],"type":"Point"}
}