{
  "type": "Feature",
  "properties": {
    "iso:country": "GB",
    "wof:name": "DL10 6RT",
    "wof:placetype": "postalcode"
  },
  "geometry": {"coordinates":[-1.615797,54.463258],"type":"Point"}
}
