{
  "type": "Feature",
  "properties": {
    "iso:country": "GB",
    "wof:name": "SA5 8HE",
    "wof:placetype": "postalcode"
  },
  "geometry": {"coordinates":[-3.958647,51.636672],"type":"Point"}
}
