{
  "type": "Feature",
  "properties": {
    "date:inception_lower": "1980-01-01",
    "date:inception_upper": "1980-01-01",
    "iso:country": "GB",
    "wof:name": "SA5 8HE",
    "wof:placetype": "postalcode"
  },
  "geometry": {"coordinates":[-3.958647,51.636672],"type":"Point"}
}
