{
  "type": "Feature",
  "properties": {
    "iso:country":"GB",
    "wof:name":"E1 3ED",
    "wof:placetype":"postalcode"
},
  "geometry": {"coordinates":[-0.05160873659333,51.51686832243611],"type":"Point"}
}