{
  "type": "Feature",
  "properties": {
    "date:inception_lower": "1980-01-01",
    "date:inception_upper": "1980-01-01",
    "iso:country": "GB",
    "wof:name": "E1 3ED",
    "wof:placetype": "postalcode"
  },
  "geometry": {"coordinates":[-0.051609,51.516868],"type":"Point"}
}
