{
  "type": "Feature",
  "properties": {
    "iso:country":"GB",
    "wof:name":"IP15 5AR",
    "wof:placetype":"postalcode"
},
  "geometry": {"coordinates":[1.60092591726947,52.15209768335286],"type":"Point"}
}