{
  "type": "Feature",
  "properties": {
    "iso:country":"GB",
    "wof:name":"PO7 7DH",
    "wof:placetype":"postalcode"
},
  "geometry": {"coordinates":[-1.03126475855646,50.87223088475824],"type":"Point"}
}