{
  "type": "Feature",
  "properties": {
    "date:inception_lower": "1980-01-01",
    "date:inception_upper": "1980-01-01",
    "iso:country": "GB",
    "wof:name": "PO7 7DH",
    "wof:placetype": "postalcode"
  },
  "geometry": {"coordinates":[-1.031265,50.872231],"type":"Point"}
}
