{
  "type": "Feature",
  "properties": {
    "iso:country":"GB",
    "wof:name":"SN10 3FL",
    "wof:placetype":"postalcode"
},
  "geometry": {"coordinates":[-1.98118137451486,51.35510115501533],"type":"Point"}
}