{
  "type": "Feature",
  "properties": {
    "iso:country": "GB",
    "wof:name": "SN10 3FL",
    "wof:placetype": "postalcode"
  },
  "geometry": {"coordinates":[-1.981181,51.355101],"type":"Point"}
}
