{
  "type": "Feature",
  "properties": {
    "date:inception_lower":"2008-01-01",
    "date:inception_upper":"2008-01-31",
    "iso:country":"GB",
    "wof:name":"SN10 3FL",
    "wof:placetype":"postalcode"
},
  "geometry": {"coordinates":[-1.981181,51.355101],"type":"Point"}
}