{
  "type": "Feature",
  "properties": {
    "iso:country": "GB",
    "wof:name": "N1 0GN",
    "wof:placetype": "postalcode"
  },
  "geometry": {"coordinates":[-0.121015,51.540878],"type":"Point"}
}
