{
  "type": "Feature",
  "properties": {
    "iso:country":"GB",
    "wof:name":"N1 0GN",
    "wof:placetype":"postalcode"
},
  "geometry": {"coordinates":[-0.12101493778854,51.54087768617502],"type":"Point"}
}