{
  "type": "Feature",
  "properties": {
    "date:inception_lower": "1985-04-01",
    "date:inception_upper": "1985-04-01",
    "iso:country": "GB",
    "wof:name": "PL6 7HL",
    "wof:placetype": "postalcode"
  },
  "geometry": {"coordinates":[-4.104879,50.434958],"type":"Point"}
}
