{
  "type": "Feature",
  "properties": {
    "date:inception_lower":"2014-12-01",
    "date:inception_upper":"2014-12-31",
    "iso:country":"GB",
    "wof:name":"ST2 8PL",
    "wof:placetype":"postalcode"
},
  "geometry": {"coordinates":[-2.1442,53.028443],"type":"Point"}
}