{
  "type": "Feature",
  "properties": {
    "iso:country":"GB",
    "wof:name":"ST2 8PL",
    "wof:placetype":"postalcode"
},
  "geometry": {"coordinates":[-2.14420017994362,53.02844316860774],"type":"Point"}
}