{
  "type": "Feature",
  "properties": {
    "date:inception_lower": "1980-01-01",
    "date:inception_upper": "1980-01-01",
    "iso:country": "GB",
    "wof:name": "TD4 6EY",
    "wof:placetype": "postalcode"
  },
  "geometry": {"coordinates":[-2.670665,55.64043],"type":"Point"}
}
