{
  "type": "Feature",
  "properties": {
    "iso:country":"GB",
    "wof:name":"RG9 5BJ",
    "wof:placetype":"postalcode"
},
  "geometry": {"coordinates":[-0.97782776642692,51.57573843386665],"type":"Point"}
}