{
  "type": "Feature",
  "properties": {
    "iso:country": "GB",
    "wof:name": "RG9 5BJ",
    "wof:placetype": "postalcode"
  },
  "geometry": {"coordinates":[-0.977828,51.575738],"type":"Point"}
}
