{
  "type": "Feature",
  "properties": {
    "iso:country": "GB",
    "wof:name": "NG24 4DJ",
    "wof:placetype": "postalcode"
  },
  "geometry": {"coordinates":[-0.802774,53.063708],"type":"Point"}
}
