{
  "type": "Feature",
  "properties": {
    "iso:country":"GB",
    "wof:name":"NG24 4DJ",
    "wof:placetype":"postalcode"
},
  "geometry": {"coordinates":[-0.80277379766624,53.06370764471964],"type":"Point"}
}