{
  "type": "Feature",
  "properties": {
    "iso:country":"GB",
    "wof:name":"PH7 4LP",
    "wof:placetype":"postalcode"
},
  "geometry": {"coordinates":[-3.85400629388693,56.37940931618468],"type":"Point"}
}