{
  "type": "Feature",
  "properties": {
    "date:inception_lower":"1991-03-01",
    "date:inception_upper":"1991-03-31",
    "iso:country":"GB",
    "wof:name":"PH7 4LP",
    "wof:placetype":"postalcode"
},
  "geometry": {"coordinates":[-3.854006,56.379409],"type":"Point"}
}