{
  "type": "Feature",
  "properties": {
    "date:inception_lower": "2002-05-01",
    "date:inception_upper": "2002-05-01",
    "iso:country": "GB",
    "wof:name": "B45 9QF",
    "wof:placetype": "postalcode"
  },
  "geometry": {"coordinates":[-2.010611,52.397379],"type":"Point"}
}
