{
  "type": "Feature",
  "properties": {
    "date:inception_lower": "2009-10-01",
    "date:inception_upper": "2009-10-01",
    "iso:country": "GB",
    "wof:name": "TW17 9DA",
    "wof:placetype": "postalcode"
  },
  "geometry": {"coordinates":[-0.446315,51.395844],"type":"Point"}
}
