{
  "type": "Feature",
  "properties": {
    "iso:country":"GB",
    "wof:name":"OL11 1QX",
    "wof:placetype":"postalcode"
},
  "geometry": {"coordinates":[-2.15821433868968,53.6075307471903],"type":"Point"}
}