{
  "type": "Feature",
  "properties": {
    "iso:country": "GB",
    "wof:name": "TA18 7RQ",
    "wof:placetype": "postalcode"
  },
  "geometry": {"coordinates":[-2.751729,50.895328],"type":"Point"}
}
