{
  "type": "Feature",
  "properties": {
    "iso:country":"GB",
    "wof:name":"WF9 3HH",
    "wof:placetype":"postalcode"
},
  "geometry": {"coordinates":[-1.32974002944705,53.59125291058375],"type":"Point"}
}