{
  "type": "Feature",
  "properties": {
    "date:inception_lower": "1980-01-01",
    "date:inception_upper": "1980-01-01",
    "iso:country": "GB",
    "wof:name": "WF9 3HH",
    "wof:placetype": "postalcode"
  },
  "geometry": {"coordinates":[-1.32974,53.591253],"type":"Point"}
}
