{
  "type": "Feature",
  "properties": {
    "iso:country": "GB",
    "wof:name": "WF9 3HH",
    "wof:placetype": "postalcode"
  },
  "geometry": {"coordinates":[-1.32974,53.591253],"type":"Point"}
}
