{
  "type": "Feature",
  "properties": {
    "iso:country":"GB",
    "wof:name":"DH7 6NL",
    "wof:placetype":"postalcode"
},
  "geometry": {"coordinates":[-1.62763999286575,54.81742529581129],"type":"Point"}
}