{
  "type": "Feature",
  "properties": {
    "date:inception_lower": "1980-01-01",
    "date:inception_upper": "1980-01-01",
    "iso:country": "GB",
    "wof:name": "N9 8BB",
    "wof:placetype": "postalcode"
  },
  "geometry": {"coordinates":[-0.042247,51.638948],"type":"Point"}
}
