{
  "type": "Feature",
  "properties": {
    "iso:country":"GB",
    "wof:name":"HA6 3NY",
    "wof:placetype":"postalcode"
},
  "geometry": {"coordinates":[-0.41346796542146,51.61328529708237],"type":"Point"}
}