{
  "type": "Feature",
  "properties": {
    "iso:country":"GB",
    "wof:name":"PO37 7ND",
    "wof:placetype":"postalcode"
},
  "geometry": {"coordinates":[-1.19156216279555,50.62944022265081],"type":"Point"}
}