{
  "type": "Feature",
  "properties": {
    "iso:country": "GB",
    "wof:name": "M9 4LZ",
    "wof:placetype": "postalcode"
  },
  "geometry": {"coordinates":[-2.201612,53.507954],"type":"Point"}
}
