{
  "type": "Feature",
  "properties": {
    "date:inception_lower": "1980-01-01",
    "date:inception_upper": "1980-01-01",
    "iso:country": "GB",
    "wof:name": "LS23 6JB",
    "wof:placetype": "postalcode"
  },
  "geometry": {"coordinates":[-1.349602,53.894112],"type":"Point"}
}
