{
  "type": "Feature",
  "properties": {
    "date:inception_lower": "1980-01-01",
    "date:inception_upper": "1980-01-01",
    "iso:country": "GB",
    "wof:name": "IP28 8BL",
    "wof:placetype": "postalcode"
  },
  "geometry": {"coordinates":[0.498092,52.375342],"type":"Point"}
}
