{
  "type": "Feature",
  "properties": {
    "date:inception_lower":"1980-01-01",
    "date:inception_upper":"1980-01-31",
    "iso:country":"GB",
    "wof:name":"SP7 9AP",
    "wof:placetype":"postalcode"
},
  "geometry": {"coordinates":[-2.162714,51.042762],"type":"Point"}
}