{
  "type": "Feature",
  "properties": {
    "iso:country":"GB",
    "wof:name":"SP7 9AP",
    "wof:placetype":"postalcode"
},
  "geometry": {"coordinates":[-2.16271453249668,51.04276224251433],"type":"Point"}
}