{
  "type": "Feature",
  "properties": {
    "iso:country":"GB",
    "wof:name":"NE5 1SH",
    "wof:placetype":"postalcode"
},
  "geometry": {"coordinates":[-1.71004928597875,54.99849981527802],"type":"Point"}
}