{
  "type": "Feature",
  "properties": {
    "date:inception_lower": "1980-01-01",
    "date:inception_upper": "1980-01-01",
    "iso:country": "GB",
    "wof:name": "NE5 1SH",
    "wof:placetype": "postalcode"
  },
  "geometry": {"coordinates":[-1.710049,54.9985],"type":"Point"}
}
