{
  "type": "Feature",
  "properties": {
    "iso:country": "GB",
    "wof:name": "LA16 7DZ",
    "wof:placetype": "postalcode"
  },
  "geometry": {"coordinates":[-3.198922,54.190665],"type":"Point"}
}
