{
  "type": "Feature",
  "properties": {
    "iso:country":"GB",
    "wof:name":"LA16 7DZ",
    "wof:placetype":"postalcode"
},
  "geometry": {"coordinates":[-3.19892155547211,54.1906646015929],"type":"Point"}
}