{
  "type": "Feature",
  "properties": {
    "iso:country":"GB",
    "wof:name":"MK40 2TP",
    "wof:placetype":"postalcode"
},
  "geometry": {"coordinates":[-0.46738703557441,52.14301586389115],"type":"Point"}
}