{
  "type": "Feature",
  "properties": {
    "iso:country": "GB",
    "wof:name": "MK40 2TP",
    "wof:placetype": "postalcode"
  },
  "geometry": {"coordinates":[-0.467387,52.143016],"type":"Point"}
}
