{
  "type": "Feature",
  "properties": {
    "iso:country":"GB",
    "wof:name":"E11 4DT",
    "wof:placetype":"postalcode"
},
  "geometry": {"coordinates":[-0.00022837953096,51.5618569804036],"type":"Point"}
}