{
  "type": "Feature",
  "properties": {
    "iso:country":"GB",
    "wof:name":"SG8 7EH",
    "wof:placetype":"postalcode"
},
  "geometry": {"coordinates":[0.06634143978269,52.0986427309298],"type":"Point"}
}