{
  "type": "Feature",
  "properties": {
    "iso:country": "GB",
    "wof:name": "SG8 7EH",
    "wof:placetype": "postalcode"
  },
  "geometry": {"coordinates":[0.066561,52.099001],"type":"Point"}
}
