{
  "type": "Feature",
  "properties": {
    "date:inception_lower": "2006-02-01",
    "date:inception_upper": "2006-02-01",
    "iso:country": "GB",
    "wof:name": "SG8 7EH",
    "wof:placetype": "postalcode"
  },
  "geometry": {"coordinates":[0.066561,52.099001],"type":"Point"}
}
