{
  "type": "Feature",
  "properties": {
    "iso:country":"GB",
    "wof:name":"CO9 1DZ",
    "wof:placetype":"postalcode"
},
  "geometry": {"coordinates":[0.6334974116285,51.94112529472783],"type":"Point"}
}