{
  "type": "Feature",
  "properties": {
    "date:inception_lower": "1994-12-01",
    "date:inception_upper": "1994-12-01",
    "iso:country": "GB",
    "wof:name": "CO9 1DZ",
    "wof:placetype": "postalcode"
  },
  "geometry": {"coordinates":[0.633528,51.941135],"type":"Point"}
}
