{
  "type": "Feature",
  "properties": {
    "date:inception_lower": "1980-01-01",
    "date:inception_upper": "1980-01-01",
    "iso:country": "GB",
    "wof:name": "NN14 3BH",
    "wof:placetype": "postalcode"
  },
  "geometry": {"coordinates":[-0.563852,52.416924],"type":"Point"}
}
