{
  "type": "Feature",
  "properties": {
    "date:inception_lower": "2022-02-01",
    "date:inception_upper": "2022-02-01",
    "iso:country": "GB",
    "wof:name": "DN21 3FF",
    "wof:placetype": "postalcode"
  },
  "geometry": {"coordinates":[-0.793875,53.415258],"type":"Point"}
}
