{
  "type": "Feature",
  "properties": {
    "iso:country":"GB",
    "wof:name":"DN10 4EU",
    "wof:placetype":"postalcode"
},
  "geometry": {"coordinates":[-0.81497126519085,53.44324210628164],"type":"Point"}
}