{
  "type": "Feature",
  "properties": {
    "iso:country": "GB",
    "wof:name": "DN10 4EU",
    "wof:placetype": "postalcode"
  },
  "geometry": {"coordinates":[-0.814971,53.443242],"type":"Point"}
}
