{
  "type": "Feature",
  "properties": {
    "iso:country": "GB",
    "wof:name": "B74 2DJ",
    "wof:placetype": "postalcode"
  },
  "geometry": {"coordinates":[-1.892024,52.572033],"type":"Point"}
}
