{
  "type": "Feature",
  "properties": {
    "date:inception_lower":"1995-12-01",
    "date:inception_upper":"1995-12-31",
    "iso:country":"GB",
    "wof:name":"PL34 0HE",
    "wof:placetype":"postalcode"
},
  "geometry": {"coordinates":[-4.753876,50.664343],"type":"Point"}
}