{
  "type": "Feature",
  "properties": {
    "iso:country":"GB",
    "wof:name":"PL34 0HE",
    "wof:placetype":"postalcode"
},
  "geometry": {"coordinates":[-4.75387623981536,50.66434315047162],"type":"Point"}
}