{
  "type": "Feature",
  "properties": {
    "iso:country": "GB",
    "wof:name": "PL34 0HE",
    "wof:placetype": "postalcode"
  },
  "geometry": {"coordinates":[-4.753876,50.664343],"type":"Point"}
}
