{
  "type": "Feature",
  "properties": {
    "iso:country": "GB",
    "wof:name": "WN8 9ER",
    "wof:placetype": "postalcode"
  },
  "geometry": {"coordinates":[-2.764048,53.54179],"type":"Point"}
}
