{
  "type": "Feature",
  "properties": {
    "iso:country":"GB",
    "wof:name":"WA3 4BQ",
    "wof:placetype":"postalcode"
},
  "geometry": {"coordinates":[-2.52527658011708,53.45898106091474],"type":"Point"}
}