{
  "type": "Feature",
  "properties": {
    "date:inception_lower": "1980-01-01",
    "date:inception_upper": "1980-01-01",
    "iso:country": "GB",
    "wof:name": "LL22 8UP",
    "wof:placetype": "postalcode"
  },
  "geometry": {"coordinates":[-3.689574,53.153445],"type":"Point"}
}
