{
  "type": "Feature",
  "properties": {
    "iso:country":"GB",
    "wof:name":"LL22 8UP",
    "wof:placetype":"postalcode"
},
  "geometry": {"coordinates":[-3.68957425378827,53.15344523261957],"type":"Point"}
}