{
  "type": "Feature",
  "properties": {
    "iso:country":"GB",
    "wof:name":"SL6 4QH",
    "wof:placetype":"postalcode"
},
  "geometry": {"coordinates":[-0.74306482877215,51.51515600410325],"type":"Point"}
}