{
  "type": "Feature",
  "properties": {
    "iso:country": "GB",
    "wof:name": "SL6 4QH",
    "wof:placetype": "postalcode"
  },
  "geometry": {"coordinates":[-0.743065,51.515156],"type":"Point"}
}
