{
  "type": "Feature",
  "properties": {
    "date:inception_lower": "1980-01-01",
    "date:inception_upper": "1980-01-01",
    "iso:country": "GB",
    "wof:name": "SL6 4QH",
    "wof:placetype": "postalcode"
  },
  "geometry": {"coordinates":[-0.743065,51.515156],"type":"Point"}
}
