{
  "type": "Feature",
  "properties": {
    "iso:country": "GB",
    "wof:name": "LL11 2ET",
    "wof:placetype": "postalcode"
  },
  "geometry": {"coordinates":[-2.998833,53.05863],"type":"Point"}
}
