{
  "type": "Feature",
  "properties": {
    "iso:country":"GB",
    "wof:name":"LL11 2ET",
    "wof:placetype":"postalcode"
},
  "geometry": {"coordinates":[-2.99883311595942,53.05862974402834],"type":"Point"}
}