{
  "type": "Feature",
  "properties": {
    "iso:country":"GB",
    "wof:name":"BB2 4LU",
    "wof:placetype":"postalcode"
},
  "geometry": {"coordinates":[-2.49681042546973,53.72919418326217],"type":"Point"}
}