{
  "type": "Feature",
  "properties": {
    "iso:country": "GB",
    "wof:name": "SR7 9QG",
    "wof:placetype": "postalcode"
  },
  "geometry": {"coordinates":[-1.394921,54.8179],"type":"Point"}
}
