{
  "type": "Feature",
  "properties": {
    "iso:country":"GB",
    "wof:name":"SR7 9QG",
    "wof:placetype":"postalcode"
},
  "geometry": {"coordinates":[-1.39492124749683,54.8178997673642],"type":"Point"}
}