{
  "type": "Feature",
  "properties": {
    "iso:country":"GB",
    "wof:name":"RM10 9XX",
    "wof:placetype":"postalcode"
},
  "geometry": {"coordinates":[0.16951672202196,51.53642167138143],"type":"Point"}
}