{
  "type": "Feature",
  "properties": {
    "iso:country": "GB",
    "wof:name": "DG8 9TH",
    "wof:placetype": "postalcode"
  },
  "geometry": {"coordinates":[-4.468316,54.889321],"type":"Point"}
}
