{
  "type": "Feature",
  "properties": {
    "date:inception_lower": "1980-01-01",
    "date:inception_upper": "1980-01-01",
    "iso:country": "GB",
    "wof:name": "PL15 8SQ",
    "wof:placetype": "postalcode"
  },
  "geometry": {"coordinates":[-4.458816,50.63898],"type":"Point"}
}
