{
  "type": "Feature",
  "properties": {
    "iso:country":"GB",
    "wof:name":"PL15 8SQ",
    "wof:placetype":"postalcode"
},
  "geometry": {"coordinates":[-4.45881620347215,50.63898022954493],"type":"Point"}
}