{
  "type": "Feature",
  "properties": {
    "iso:country":"GB",
    "wof:name":"TR12 7AJ",
    "wof:placetype":"postalcode"
},
  "geometry": {"coordinates":[-5.24163603350293,50.02795325095701],"type":"Point"}
}