{
  "type": "Feature",
  "properties": {
    "iso:country":"GB",
    "wof:name":"TQ5 9NE",
    "wof:placetype":"postalcode"
},
  "geometry": {"coordinates":[-3.52351724490566,50.38991952295159],"type":"Point"}
}