{
  "type": "Feature",
  "properties": {
    "date:inception_lower": "1990-02-01",
    "date:inception_upper": "1990-02-01",
    "iso:country": "GB",
    "wof:name": "ME5 7NF",
    "wof:placetype": "postalcode"
  },
  "geometry": {"coordinates":[0.536786,51.349434],"type":"Point"}
}
