{
  "type": "Feature",
  "properties": {
    "iso:country":"GB",
    "wof:name":"M33 7RG",
    "wof:placetype":"postalcode"
},
  "geometry": {"coordinates":[-2.32966918241896,53.42219907940594],"type":"Point"}
}