{
  "type": "Feature",
  "properties": {
    "date:inception_lower": "1980-01-01",
    "date:inception_upper": "1980-01-01",
    "iso:country": "GB",
    "wof:name": "FK19 8PT",
    "wof:placetype": "postalcode"
  },
  "geometry": {"coordinates":[-4.279522,56.386638],"type":"Point"}
}
