{
  "type": "Feature",
  "properties": {
    "date:inception_lower":"2010-07-01",
    "date:inception_upper":"2010-07-31",
    "iso:country":"GB",
    "wof:name":"NR13 6FB",
    "wof:placetype":"postalcode"
},
  "geometry": {"coordinates":[1.38751,52.666331],"type":"Point"}
}