{
  "type": "Feature",
  "properties": {
    "iso:country":"GB",
    "wof:name":"E15 1SJ",
    "wof:placetype":"postalcode"
},
  "geometry": {"coordinates":[0.00788054719931,51.55040576593611],"type":"Point"}
}