{
  "type": "Feature",
  "properties": {
    "iso:country":"GB",
    "wof:name":"SK16 4UP",
    "wof:placetype":"postalcode"
},
  "geometry": {"coordinates":[-2.08910531982091,53.46637730826945],"type":"Point"}
}