{
  "type": "Feature",
  "properties": {
    "iso:country": "GB",
    "wof:name": "SK16 4UP",
    "wof:placetype": "postalcode"
  },
  "geometry": {"coordinates":[-2.089105,53.466377],"type":"Point"}
}
