{
  "type": "Feature",
  "properties": {
    "iso:country":"GB",
    "wof:name":"WV12 5HH",
    "wof:placetype":"postalcode"
},
  "geometry": {"coordinates":[-2.03111599009518,52.60909742098617],"type":"Point"}
}