{
  "type": "Feature",
  "properties": {
    "iso:country":"GB",
    "wof:name":"TA11 7DN",
    "wof:placetype":"postalcode"
},
  "geometry": {"coordinates":[-2.61419472310993,51.08783148565208],"type":"Point"}
}