{
  "type": "Feature",
  "properties": {
    "iso:country":"GB",
    "wof:name":"FY1 5JN",
    "wof:placetype":"postalcode"
},
  "geometry": {"coordinates":[-3.04575306315692,53.80494695489271],"type":"Point"}
}