{
  "type": "Feature",
  "properties": {
    "iso:country": "GB",
    "wof:name": "WF11 8FB",
    "wof:placetype": "postalcode"
  },
  "geometry": {"coordinates":[-1.255789,53.708241],"type":"Point"}
}
