{
  "type": "Feature",
  "properties": {
    "date:inception_lower": "2019-06-01",
    "date:inception_upper": "2019-06-01",
    "iso:country": "GB",
    "wof:name": "WF11 8FB",
    "wof:placetype": "postalcode"
  },
  "geometry": {"coordinates":[-1.255789,53.708241],"type":"Point"}
}
