{
  "type": "Feature",
  "properties": {
    "iso:country": "GB",
    "wof:name": "ME7 2BY",
    "wof:placetype": "postalcode"
  },
  "geometry": {"coordinates":[0.567013,51.377852],"type":"Point"}
}
