{
  "type": "Feature",
  "properties": {
    "iso:country":"GB",
    "wof:name":"ME7 2BY",
    "wof:placetype":"postalcode"
},
  "geometry": {"coordinates":[0.56701318159274,51.37785174905659],"type":"Point"}
}