{
  "type": "Feature",
  "properties": {
    "iso:country":"GB",
    "wof:name":"DN7 5BL",
    "wof:placetype":"postalcode"
},
  "geometry": {"coordinates":[-1.02169243761894,53.60017848056204],"type":"Point"}
}