{
  "type": "Feature",
  "properties": {
    "date:inception_lower": "1980-01-01",
    "date:inception_upper": "1980-01-01",
    "iso:country": "GB",
    "wof:name": "DN7 5BL",
    "wof:placetype": "postalcode"
  },
  "geometry": {"coordinates":[-1.021692,53.600178],"type":"Point"}
}
