{
  "type": "Feature",
  "properties": {
    "iso:country":"GB",
    "wof:name":"OX39 4HT",
    "wof:placetype":"postalcode"
},
  "geometry": {"coordinates":[-0.91865468913739,51.69880705439322],"type":"Point"}
}