{
  "type": "Feature",
  "properties": {
    "iso:country":"GB",
    "wof:name":"HX7 5LX",
    "wof:placetype":"postalcode"
},
  "geometry": {"coordinates":[-1.97830199193479,53.73184996860772],"type":"Point"}
}