{
  "type": "Feature",
  "properties": {
    "iso:country":"GB",
    "wof:name":"L17 4JX",
    "wof:placetype":"postalcode"
},
  "geometry": {"coordinates":[-2.95159251526093,53.38017351351218],"type":"Point"}
}