{
  "type": "Feature",
  "properties": {
    "iso:country":"GB",
    "wof:name":"N14 4PF",
    "wof:placetype":"postalcode"
},
  "geometry": {"coordinates":[-0.14497845373306,51.64055306876119],"type":"Point"}
}