{
  "type": "Feature",
  "properties": {
    "date:inception_lower": "1991-09-01",
    "date:inception_upper": "1991-09-01",
    "iso:country": "GB",
    "wof:name": "N14 4PF",
    "wof:placetype": "postalcode"
  },
  "geometry": {"coordinates":[-0.144925,51.640519],"type":"Point"}
}
