{
  "type": "Feature",
  "properties": {
    "date:inception_lower":"1980-01-01",
    "date:inception_upper":"1980-01-31",
    "iso:country":"GB",
    "wof:name":"CV35 0ET",
    "wof:placetype":"postalcode"
},
  "geometry": {"coordinates":[-1.469227,52.18293],"type":"Point"}
}