{
  "type": "Feature",
  "properties": {
    "iso:country": "GB",
    "wof:name": "CV35 0ET",
    "wof:placetype": "postalcode"
  },
  "geometry": {"coordinates":[-1.469227,52.18293],"type":"Point"}
}
