{
  "type": "Feature",
  "properties": {
    "iso:country": "GB",
    "wof:name": "L39 4TJ",
    "wof:placetype": "postalcode"
  },
  "geometry": {"coordinates":[-2.89877,53.560044],"type":"Point"}
}
