{
  "type": "Feature",
  "properties": {
    "date:inception_lower":"1996-12-01",
    "date:inception_upper":"1996-12-31",
    "iso:country":"GB",
    "wof:name":"HG3 1RG",
    "wof:placetype":"postalcode"
},
  "geometry": {"coordinates":[-1.531183,53.955438],"type":"Point"}
}