{
  "type": "Feature",
  "properties": {
    "iso:country": "GB",
    "wof:name": "S10 4EN",
    "wof:placetype": "postalcode"
  },
  "geometry": {"coordinates":[-1.555795,53.372132],"type":"Point"}
}
