{
  "type": "Feature",
  "properties": {
    "iso:country":"GB",
    "wof:name":"S10 4EN",
    "wof:placetype":"postalcode"
},
  "geometry": {"coordinates":[-1.55579492198558,53.3721315516671],"type":"Point"}
}