{
  "type": "Feature",
  "properties": {
    "iso:country":"GB",
    "wof:name":"CA7 9JY",
    "wof:placetype":"postalcode"
},
  "geometry": {"coordinates":[-3.15884165987819,54.81859052149284],"type":"Point"}
}