{
  "type": "Feature",
  "properties": {
    "iso:country":"GB",
    "wof:name":"WV11 3TU",
    "wof:placetype":"postalcode"
},
  "geometry": {"coordinates":[-2.07928714774792,52.60911082567161],"type":"Point"}
}