{
  "type": "Feature",
  "properties": {
    "iso:country":"GB",
    "wof:name":"BH22 0NA",
    "wof:placetype":"postalcode"
},
  "geometry": {"coordinates":[-1.88703454520185,50.83155555436969],"type":"Point"}
}