{
  "type": "Feature",
  "properties": {
    "iso:country": "GB",
    "wof:name": "WA7 3NB",
    "wof:placetype": "postalcode"
  },
  "geometry": {"coordinates":[-2.653131,53.318782],"type":"Point"}
}
