{
  "type": "Feature",
  "properties": {
    "iso:country":"GB",
    "wof:name":"WA7 3NB",
    "wof:placetype":"postalcode"
},
  "geometry": {"coordinates":[-2.65313115960828,53.31878210190617],"type":"Point"}
}