{
  "type": "Feature",
  "properties": {
    "date:inception_lower": "2000-06-01",
    "date:inception_upper": "2000-06-01",
    "iso:country": "GB",
    "wof:name": "WA7 3NB",
    "wof:placetype": "postalcode"
  },
  "geometry": {"coordinates":[-2.653131,53.318782],"type":"Point"}
}
