{
  "type": "Feature",
  "properties": {
    "iso:country":"GB",
    "wof:name":"HU18 1UE",
    "wof:placetype":"postalcode"
},
  "geometry": {"coordinates":[-0.17341383321431,53.90056886131315],"type":"Point"}
}