{
  "type": "Feature",
  "properties": {
    "iso:country": "GB",
    "wof:name": "HU18 1UE",
    "wof:placetype": "postalcode"
  },
  "geometry": {"coordinates":[-0.173414,53.900569],"type":"Point"}
}
