{
  "type": "Feature",
  "properties": {
    "iso:country":"GB",
    "wof:name":"MK45 3PB",
    "wof:placetype":"postalcode"
},
  "geometry": {"coordinates":[-0.40079015668768,52.06466181486412],"type":"Point"}
}