{
  "type": "Feature",
  "properties": {
    "iso:country":"GB",
    "wof:name":"WA7 4TY",
    "wof:placetype":"postalcode"
},
  "geometry": {"coordinates":[-2.74053787813927,53.33668061873629],"type":"Point"}
}