{
  "type": "Feature",
  "properties": {
    "iso:country":"GB",
    "wof:name":"SN10 3EF",
    "wof:placetype":"postalcode"
},
  "geometry": {"coordinates":[-1.97844246842549,51.34651362123845],"type":"Point"}
}