{
  "type": "Feature",
  "properties": {
    "iso:country": "GB",
    "wof:name": "SN10 3EF",
    "wof:placetype": "postalcode"
  },
  "geometry": {"coordinates":[-1.978442,51.346514],"type":"Point"}
}
