{
  "type": "Feature",
  "properties": {
    "iso:country":"GB",
    "wof:name":"CA11 8PR",
    "wof:placetype":"postalcode"
},
  "geometry": {"coordinates":[-2.74877071939994,54.65493768055529],"type":"Point"}
}