{
  "type": "Feature",
  "properties": {
    "date:inception_lower": "1980-01-01",
    "date:inception_upper": "1980-01-01",
    "iso:country": "GB",
    "wof:name": "CA11 8PR",
    "wof:placetype": "postalcode"
  },
  "geometry": {"coordinates":[-2.748771,54.654938],"type":"Point"}
}
