{
  "type": "Feature",
  "properties": {
    "iso:country": "GB",
    "wof:name": "LE2 4LF",
    "wof:placetype": "postalcode"
  },
  "geometry": {"coordinates":[-1.079379,52.599916],"type":"Point"}
}
