{
  "type": "Feature",
  "properties": {
    "iso:country":"GB",
    "wof:name":"LE2 4LF",
    "wof:placetype":"postalcode"
},
  "geometry": {"coordinates":[-1.0793793485155,52.59991633847593],"type":"Point"}
}