{
  "type": "Feature",
  "properties": {
    "iso:country": "GB",
    "wof:name": "DN22 9BF",
    "wof:placetype": "postalcode"
  },
  "geometry": {"coordinates":[-0.824142,53.385967],"type":"Point"}
}
