{
  "type": "Feature",
  "properties": {
    "iso:country":"GB",
    "wof:name":"PO14 4SH",
    "wof:placetype":"postalcode"
},
  "geometry": {"coordinates":[-1.25766605050369,50.86669575298522],"type":"Point"}
}