{
  "type": "Feature",
  "properties": {
    "iso:country":"GB",
    "wof:name":"RH12 4PL",
    "wof:placetype":"postalcode"
},
  "geometry": {"coordinates":[-0.29086259461132,51.08130807748653],"type":"Point"}
}