{
  "type": "Feature",
  "properties": {
    "iso:country": "GB",
    "wof:name": "TF9 3RY",
    "wof:placetype": "postalcode"
  },
  "geometry": {"coordinates":[-2.562098,52.908569],"type":"Point"}
}
