{
  "type": "Feature",
  "properties": {
    "iso:country":"GB",
    "wof:name":"G82 1LX",
    "wof:placetype":"postalcode"
},
  "geometry": {"coordinates":[-4.56952616661548,55.94294987573268],"type":"Point"}
}