{
  "type": "Feature",
  "properties": {
    "iso:country": "GB",
    "wof:name": "N2 9JL",
    "wof:placetype": "postalcode"
  },
  "geometry": {"coordinates":[-0.161456,51.589754],"type":"Point"}
}
