{
  "type": "Feature",
  "properties": {
    "iso:country":"GB",
    "wof:name":"N2 9JL",
    "wof:placetype":"postalcode"
},
  "geometry": {"coordinates":[-0.16145589590224,51.58975372742967],"type":"Point"}
}