{
  "type": "Feature",
  "properties": {
    "iso:country": "GB",
    "wof:name": "BH21 3DD",
    "wof:placetype": "postalcode"
  },
  "geometry": {"coordinates":[-2.004146,50.779435],"type":"Point"}
}
