{
  "type": "Feature",
  "properties": {
    "iso:country":"GB",
    "wof:name":"BH21 3DD",
    "wof:placetype":"postalcode"
},
  "geometry": {"coordinates":[-2.00414644662616,50.77943518297349],"type":"Point"}
}