{
  "type": "Feature",
  "properties": {
    "iso:country":"GB",
    "wof:name":"DL3 7UU",
    "wof:placetype":"postalcode"
},
  "geometry": {"coordinates":[-1.56783790596276,54.52647067149443],"type":"Point"}
}