{
  "type": "Feature",
  "properties": {
    "iso:country": "GB",
    "wof:name": "BN10 7LE",
    "wof:placetype": "postalcode"
  },
  "geometry": {"coordinates":[-0.006421,50.79931],"type":"Point"}
}
