{
  "type": "Feature",
  "properties": {
    "iso:country":"GB",
    "wof:name":"BN10 7LE",
    "wof:placetype":"postalcode"
},
  "geometry": {"coordinates":[-0.0064214214631,50.79930997907474],"type":"Point"}
}