{
  "type": "Feature",
  "properties": {
    "date:inception_lower":"1985-10-01",
    "date:inception_upper":"1985-10-31",
    "iso:country":"GB",
    "wof:name":"BL4 7QJ",
    "wof:placetype":"postalcode"
},
  "geometry": {"coordinates":[-2.391381,53.549982],"type":"Point"}
}