{
  "type": "Feature",
  "properties": {
    "iso:country":"GB",
    "wof:name":"BL4 7QJ",
    "wof:placetype":"postalcode"
},
  "geometry": {"coordinates":[-2.39138120802517,53.54998177028283],"type":"Point"}
}