{
  "type": "Feature",
  "properties": {
    "iso:country": "GB",
    "wof:name": "SA4 6UR",
    "wof:placetype": "postalcode"
  },
  "geometry": {"coordinates":[-4.071884,51.661062],"type":"Point"}
}
