{
  "type": "Feature",
  "properties": {
    "date:inception_lower": "2000-06-01",
    "date:inception_upper": "2000-06-01",
    "iso:country": "GB",
    "wof:name": "SA4 6UR",
    "wof:placetype": "postalcode"
  },
  "geometry": {"coordinates":[-4.071884,51.661062],"type":"Point"}
}
