{
  "type": "Feature",
  "properties": {
    "iso:country":"GB",
    "wof:name":"SW8 2TP",
    "wof:placetype":"postalcode"
},
  "geometry": {"coordinates":[-0.12435854795289,51.47776765768178],"type":"Point"}
}