{
  "type": "Feature",
  "properties": {
    "iso:country":"GB",
    "wof:name":"CF81 9GA",
    "wof:placetype":"postalcode"
},
  "geometry": {"coordinates":[-3.26485433320706,51.7126597112339],"type":"Point"}
}