{
  "type": "Feature",
  "properties": {
    "date:inception_lower": "1998-06-01",
    "date:inception_upper": "1998-06-01",
    "iso:country": "GB",
    "wof:name": "CF81 9GA",
    "wof:placetype": "postalcode"
  },
  "geometry": {"coordinates":[-3.264854,51.71266],"type":"Point"}
}
