{
  "type": "Feature",
  "properties": {
    "iso:country": "GB",
    "wof:name": "CF81 9GA",
    "wof:placetype": "postalcode"
  },
  "geometry": {"coordinates":[-3.264854,51.71266],"type":"Point"}
}
