{
  "type": "Feature",
  "properties": {
    "iso:country":"GB",
    "wof:name":"PE27 4SH",
    "wof:placetype":"postalcode"
},
  "geometry": {"coordinates":[-0.02784452590383,52.32999384028505],"type":"Point"}
}