{
  "type": "Feature",
  "properties": {
    "iso:country": "GB",
    "wof:name": "PE27 4SH",
    "wof:placetype": "postalcode"
  },
  "geometry": {"coordinates":[-0.027844,52.329994],"type":"Point"}
}
