{
  "type": "Feature",
  "properties": {
    "date:inception_lower": "2000-06-01",
    "date:inception_upper": "2000-06-01",
    "iso:country": "GB",
    "wof:name": "PE27 4SH",
    "wof:placetype": "postalcode"
  },
  "geometry": {"coordinates":[-0.027844,52.329994],"type":"Point"}
}
