{
  "type": "Feature",
  "properties": {
    "date:inception_lower": "1981-06-01",
    "date:inception_upper": "1981-06-01",
    "iso:country": "GB",
    "wof:name": "NR12 0YU",
    "wof:placetype": "postalcode"
  },
  "geometry": {"coordinates":[1.571401,52.750987],"type":"Point"}
}
