{
  "type": "Feature",
  "properties": {
    "iso:country": "GB",
    "wof:name": "NR12 0YU",
    "wof:placetype": "postalcode"
  },
  "geometry": {"coordinates":[1.571401,52.750987],"type":"Point"}
}
