{
  "type": "Feature",
  "properties": {
    "iso:country": "GB",
    "wof:name": "CW1 5RG",
    "wof:placetype": "postalcode"
  },
  "geometry": {"coordinates":[-2.393831,53.102405],"type":"Point"}
}
