{
  "type": "Feature",
  "properties": {
    "iso:country":"GB",
    "wof:name":"CW1 5RG",
    "wof:placetype":"postalcode"
},
  "geometry": {"coordinates":[-2.3939200071448,53.10235266658121],"type":"Point"}
}