{
  "type": "Feature",
  "properties": {
    "iso:country": "GB",
    "wof:name": "SO19 1DD",
    "wof:placetype": "postalcode"
  },
  "geometry": {"coordinates":[-1.338891,50.902974],"type":"Point"}
}
