{
  "type": "Feature",
  "properties": {
    "date:inception_lower": "1980-01-01",
    "date:inception_upper": "1980-01-01",
    "iso:country": "GB",
    "wof:name": "HD4 7EX",
    "wof:placetype": "postalcode"
  },
  "geometry": {"coordinates":[-1.814217,53.614682],"type":"Point"}
}
