{
  "type": "Feature",
  "properties": {
    "iso:country":"GB",
    "wof:name":"CV3 1AW",
    "wof:placetype":"postalcode"
},
  "geometry": {"coordinates":[-1.48872958625101,52.4040700085829],"type":"Point"}
}