{
  "type": "Feature",
  "properties": {
    "iso:country":"GB",
    "wof:name":"SL6 9RN",
    "wof:placetype":"postalcode"
},
  "geometry": {"coordinates":[-0.72287189063656,51.55902525763177],"type":"Point"}
}