{
  "type": "Feature",
  "properties": {
    "iso:country":"GB",
    "wof:name":"BB5 0FE",
    "wof:placetype":"postalcode"
},
  "geometry": {"coordinates":[-2.38857805547983,53.74940401745605],"type":"Point"}
}