{
  "type": "Feature",
  "properties": {
    "iso:country": "GB",
    "wof:name": "BB5 0FE",
    "wof:placetype": "postalcode"
  },
  "geometry": {"coordinates":[-2.388578,53.749404],"type":"Point"}
}
