{
  "type": "Feature",
  "properties": {
    "date:inception_lower":"1999-12-01",
    "date:inception_upper":"1999-12-31",
    "iso:country":"GB",
    "wof:name":"BB5 0FE",
    "wof:placetype":"postalcode"
},
  "geometry": {"coordinates":[-2.388578,53.749404],"type":"Point"}
}