{
  "type": "Feature",
  "properties": {
    "date:inception_lower": "1980-01-01",
    "date:inception_upper": "1980-01-01",
    "iso:country": "GB",
    "wof:name": "IP7 6PB",
    "wof:placetype": "postalcode"
  },
  "geometry": {"coordinates":[1.004079,52.082555],"type":"Point"}
}
