{
  "type": "Feature",
  "properties": {
    "iso:country":"GB",
    "wof:name":"IP7 6PB",
    "wof:placetype":"postalcode"
},
  "geometry": {"coordinates":[1.00404902355555,52.08254046246672],"type":"Point"}
}