{
  "type": "Feature",
  "properties": {
    "iso:country": "GB",
    "wof:name": "IP7 6PB",
    "wof:placetype": "postalcode"
  },
  "geometry": {"coordinates":[1.004079,52.082555],"type":"Point"}
}
