{
  "type": "Feature",
  "properties": {
    "date:inception_lower": "1995-07-01",
    "date:inception_upper": "1995-07-01",
    "iso:country": "GB",
    "wof:name": "CF32 9DT",
    "wof:placetype": "postalcode"
  },
  "geometry": {"coordinates":[-3.593133,51.54834],"type":"Point"}
}
