{
  "type": "Feature",
  "properties": {
    "iso:country":"GB",
    "wof:name":"CF32 9DT",
    "wof:placetype":"postalcode"
},
  "geometry": {"coordinates":[-3.59311702683123,51.54832870835497],"type":"Point"}
}