{
  "type": "Feature",
  "properties": {
    "iso:country":"GB",
    "wof:name":"BA15 2HG",
    "wof:placetype":"postalcode"
},
  "geometry": {"coordinates":[-2.28016892880243,51.34541561965315],"type":"Point"}
}