{
  "type": "Feature",
  "properties": {
    "date:inception_lower":"1980-01-01",
    "date:inception_upper":"1980-01-31",
    "iso:country":"GB",
    "wof:name":"BA15 2HG",
    "wof:placetype":"postalcode"
},
  "geometry": {"coordinates":[-2.280169,51.345416],"type":"Point"}
}