{
  "type": "Feature",
  "properties": {
    "date:inception_lower":"2002-06-01",
    "date:inception_upper":"2002-06-30",
    "iso:country":"GB",
    "wof:name":"DE3 0RZ",
    "wof:placetype":"postalcode"
},
  "geometry": {"coordinates":[-1.545702,52.916359],"type":"Point"}
}