{
  "type": "Feature",
  "properties": {
    "iso:country": "GB",
    "wof:name": "BL6 6RJ",
    "wof:placetype": "postalcode"
  },
  "geometry": {"coordinates":[-2.531796,53.584063],"type":"Point"}
}
