{
  "type": "Feature",
  "properties": {
    "date:inception_lower":"1999-12-01",
    "date:inception_upper":"1999-12-31",
    "iso:country":"GB",
    "wof:name":"BL6 6RJ",
    "wof:placetype":"postalcode"
},
  "geometry": {"coordinates":[-2.531796,53.584063],"type":"Point"}
}