{
  "type": "Feature",
  "properties": {
    "iso:country":"GB",
    "wof:name":"BL6 6RJ",
    "wof:placetype":"postalcode"
},
  "geometry": {"coordinates":[-2.53179653184339,53.58406294486973],"type":"Point"}
}