{
  "type": "Feature",
  "properties": {
    "iso:country":"GB",
    "wof:name":"DH2 2AH",
    "wof:placetype":"postalcode"
},
  "geometry": {"coordinates":[-1.60541036422089,54.85811773667356],"type":"Point"}
}