{
  "type": "Feature",
  "properties": {
    "iso:country": "GB",
    "wof:name": "DH2 2AH",
    "wof:placetype": "postalcode"
  },
  "geometry": {"coordinates":[-1.60541,54.858118],"type":"Point"}
}
