{
  "type": "Feature",
  "properties": {
    "iso:country": "GB",
    "wof:name": "NR35 1LT",
    "wof:placetype": "postalcode"
  },
  "geometry": {"coordinates":[1.450945,52.449465],"type":"Point"}
}
