{
  "type": "Feature",
  "properties": {
    "date:inception_lower":"1982-03-01",
    "date:inception_upper":"1982-03-31",
    "iso:country":"GB",
    "wof:name":"NP4 0RT",
    "wof:placetype":"postalcode"
},
  "geometry": {"coordinates":[-3.007682,51.694071],"type":"Point"}
}