{
  "type": "Feature",
  "properties": {
    "iso:country":"GB",
    "wof:name":"NP4 0RT",
    "wof:placetype":"postalcode"
},
  "geometry": {"coordinates":[-3.00768198575415,51.69407137837761],"type":"Point"}
}