{
  "type": "Feature",
  "properties": {
    "date:inception_lower":"1990-07-01",
    "date:inception_upper":"1990-07-31",
    "iso:country":"GB",
    "wof:name":"SA18 2EZ",
    "wof:placetype":"postalcode"
},
  "geometry": {"coordinates":[-3.987177,51.78672],"type":"Point"}
}