{
  "type": "Feature",
  "properties": {
    "iso:country": "GB",
    "wof:name": "SA18 2EZ",
    "wof:placetype": "postalcode"
  },
  "geometry": {"coordinates":[-3.987177,51.78672],"type":"Point"}
}
