{
  "type": "Feature",
  "properties": {
    "iso:country":"GB",
    "wof:name":"L21 8LS",
    "wof:placetype":"postalcode"
},
  "geometry": {"coordinates":[-2.99695889538078,53.46422707437723],"type":"Point"}
}