{
  "type": "Feature",
  "properties": {
    "date:inception_lower": "1980-01-01",
    "date:inception_upper": "1980-01-01",
    "iso:country": "GB",
    "wof:name": "CF39 9LX",
    "wof:placetype": "postalcode"
  },
  "geometry": {"coordinates":[-3.41981,51.599992],"type":"Point"}
}
