{
  "type": "Feature",
  "properties": {
    "iso:country": "GB",
    "wof:name": "TQ14 8UL",
    "wof:placetype": "postalcode"
  },
  "geometry": {"coordinates":[-3.487547,50.55832],"type":"Point"}
}
