{
  "type": "Feature",
  "properties": {
    "date:inception_lower": "1980-01-01",
    "date:inception_upper": "1980-01-01",
    "iso:country": "GB",
    "wof:name": "TQ14 8UL",
    "wof:placetype": "postalcode"
  },
  "geometry": {"coordinates":[-3.487547,50.55832],"type":"Point"}
}
