{
  "type": "Feature",
  "properties": {
    "date:inception_lower": "1996-12-01",
    "date:inception_upper": "1996-12-01",
    "iso:country": "GB",
    "wof:name": "L36 5RT",
    "wof:placetype": "postalcode"
  },
  "geometry": {"coordinates":[-2.838925,53.410322],"type":"Point"}
}
