{
  "type": "Feature",
  "properties": {
    "iso:country":"GB",
    "wof:name":"L36 5RT",
    "wof:placetype":"postalcode"
},
  "geometry": {"coordinates":[-2.83892457510906,53.41032230439482],"type":"Point"}
}