{
  "type": "Feature",
  "properties": {
    "iso:country": "GB",
    "wof:name": "W10 4BB",
    "wof:placetype": "postalcode"
  },
  "geometry": {"coordinates":[-0.215426,51.531687],"type":"Point"}
}
