{
  "type": "Feature",
  "properties": {
    "iso:country": "GB",
    "wof:name": "HS2 0BA",
    "wof:placetype": "postalcode"
  },
  "geometry": {"coordinates":[-6.339225,58.203431],"type":"Point"}
}
