{
  "type": "Feature",
  "properties": {
    "date:inception_lower":"2015-05-01",
    "date:inception_upper":"2015-05-31",
    "iso:country":"GB",
    "wof:name":"HS2 0BA",
    "wof:placetype":"postalcode"
},
  "geometry": {"coordinates":[-6.339225,58.203431],"type":"Point"}
}