{
  "type": "Feature",
  "properties": {
    "date:inception_lower":"1980-01-01",
    "date:inception_upper":"1980-01-31",
    "iso:country":"GB",
    "wof:name":"TR15 3NS",
    "wof:placetype":"postalcode"
},
  "geometry": {"coordinates":[-5.263757,50.230412],"type":"Point"}
}