{
  "type": "Feature",
  "properties": {
    "iso:country":"GB",
    "wof:name":"M14 4QB",
    "wof:placetype":"postalcode"
},
  "geometry": {"coordinates":[-2.23619849904825,53.45839274616255],"type":"Point"}
}