{
  "type": "Feature",
  "properties": {
    "iso:country":"GB",
    "wof:name":"B70 0RD",
    "wof:placetype":"postalcode"
},
  "geometry": {"coordinates":[-2.01526022849119,52.53793718510558],"type":"Point"}
}