{
  "type": "Feature",
  "properties": {
    "iso:country": "GB",
    "wof:name": "B70 0RD",
    "wof:placetype": "postalcode"
  },
  "geometry": {"coordinates":[-2.015491,52.538258],"type":"Point"}
}
