{
  "type": "Feature",
  "properties": {
    "iso:country": "GB",
    "wof:name": "SY4 2BJ",
    "wof:placetype": "postalcode"
  },
  "geometry": {"coordinates":[-2.847043,52.799003],"type":"Point"}
}
