{
  "type": "Feature",
  "properties": {
    "date:inception_lower": "2011-12-01",
    "date:inception_upper": "2011-12-01",
    "iso:country": "GB",
    "wof:name": "OX11 9FA",
    "wof:placetype": "postalcode"
  },
  "geometry": {"coordinates":[-1.226248,51.573224],"type":"Point"}
}
