{
  "type": "Feature",
  "properties": {
    "iso:country":"GB",
    "wof:name":"HD7 4RA",
    "wof:placetype":"postalcode"
},
  "geometry": {"coordinates":[-1.84545988348548,53.64428009685316],"type":"Point"}
}