{
  "type": "Feature",
  "properties": {
    "iso:country": "GB",
    "wof:name": "HD7 4RA",
    "wof:placetype": "postalcode"
  },
  "geometry": {"coordinates":[-1.84546,53.64428],"type":"Point"}
}
