{
  "type": "Feature",
  "properties": {
    "iso:country":"GB",
    "wof:name":"FY8 5HR",
    "wof:placetype":"postalcode"
},
  "geometry": {"coordinates":[-2.95801583003693,53.73773697301925],"type":"Point"}
}