{
  "type": "Feature",
  "properties": {
    "date:inception_lower": "1993-01-01",
    "date:inception_upper": "1993-01-01",
    "iso:country": "GB",
    "wof:name": "LL14 6PP",
    "wof:placetype": "postalcode"
  },
  "geometry": {"coordinates":[-3.038659,52.991047],"type":"Point"}
}
