{
  "type": "Feature",
  "properties": {
    "iso:country":"GB",
    "wof:name":"LS13 4LH",
    "wof:placetype":"postalcode"
},
  "geometry": {"coordinates":[-1.61991525488666,53.79983791653739],"type":"Point"}
}