{
  "type": "Feature",
  "properties": {
    "iso:country":"GB",
    "wof:name":"N21 2DN",
    "wof:placetype":"postalcode"
},
  "geometry": {"coordinates":[-0.08423276225196,51.640602736159],"type":"Point"}
}