{
  "type": "Feature",
  "properties": {
    "iso:country": "GB",
    "wof:name": "CF14 6DZ",
    "wof:placetype": "postalcode"
  },
  "geometry": {"coordinates":[-3.214915,51.522193],"type":"Point"}
}
