{
  "type": "Feature",
  "properties": {
    "iso:country": "GB",
    "wof:name": "SW6 2RF",
    "wof:placetype": "postalcode"
  },
  "geometry": {"coordinates":[-0.185692,51.470505],"type":"Point"}
}
