{
  "type": "Feature",
  "properties": {
    "iso:country":"GB",
    "wof:name":"TQ12 3QF",
    "wof:placetype":"postalcode"
},
  "geometry": {"coordinates":[-3.57627705602991,50.56543871577022],"type":"Point"}
}