{
  "type": "Feature",
  "properties": {
    "iso:country":"GB",
    "wof:name":"WR5 1RF",
    "wof:placetype":"postalcode"
},
  "geometry": {"coordinates":[-2.19635256487776,52.18352689716743],"type":"Point"}
}