{
  "type": "Feature",
  "properties": {
    "iso:country": "GB",
    "wof:name": "WR5 1RF",
    "wof:placetype": "postalcode"
  },
  "geometry": {"coordinates":[-2.196319,52.183566],"type":"Point"}
}
