{
  "type": "Feature",
  "properties": {
    "date:inception_lower": "1980-01-01",
    "date:inception_upper": "1980-01-01",
    "iso:country": "GB",
    "wof:name": "PE21 0LX",
    "wof:placetype": "postalcode"
  },
  "geometry": {"coordinates":[-0.002961,52.975714],"type":"Point"}
}
