{
  "type": "Feature",
  "properties": {
    "iso:country":"GB",
    "wof:name":"YO18 7EL",
    "wof:placetype":"postalcode"
},
  "geometry": {"coordinates":[-0.77206998212408,54.24142038736105],"type":"Point"}
}