{
  "type": "Feature",
  "properties": {
    "iso:country": "GB",
    "wof:name": "YO18 7EL",
    "wof:placetype": "postalcode"
  },
  "geometry": {"coordinates":[-0.77207,54.24142],"type":"Point"}
}
