{
  "type": "Feature",
  "properties": {
    "date:inception_lower": "2020-10-01",
    "date:inception_upper": "2020-10-01",
    "iso:country": "GB",
    "wof:name": "CM22 6YL",
    "wof:placetype": "postalcode"
  },
  "geometry": {"coordinates":[0.273332,51.899057],"type":"Point"}
}
