{
  "type": "Feature",
  "properties": {
    "date:inception_lower": "1980-01-01",
    "date:inception_upper": "1980-01-01",
    "iso:country": "GB",
    "wof:name": "CH1 3JF",
    "wof:placetype": "postalcode"
  },
  "geometry": {"coordinates":[-2.888212,53.197223],"type":"Point"}
}
