{
  "type": "Feature",
  "properties": {
    "iso:country":"GB",
    "wof:name":"TR12 6RL",
    "wof:placetype":"postalcode"
},
  "geometry": {"coordinates":[-5.13747456872834,50.03955425502792],"type":"Point"}
}