{
  "type": "Feature",
  "properties": {
    "iso:country": "GB",
    "wof:name": "UB4 0TD",
    "wof:placetype": "postalcode"
  },
  "geometry": {"coordinates":[-0.407906,51.51873],"type":"Point"}
}
