{
  "type": "Feature",
  "properties": {
    "iso:country":"GB",
    "wof:name":"NG23 6LX",
    "wof:placetype":"postalcode"
},
  "geometry": {"coordinates":[-0.8754564181626,53.19343324528947],"type":"Point"}
}