{
  "type": "Feature",
  "properties": {
    "date:inception_lower": "2019-05-01",
    "date:inception_upper": "2019-05-01",
    "iso:country": "GB",
    "wof:name": "IP25 6YQ",
    "wof:placetype": "postalcode"
  },
  "geometry": {"coordinates":[0.743575,52.587494],"type":"Point"}
}
