{
  "type": "Feature",
  "properties": {
    "date:inception_lower": "1980-01-01",
    "date:inception_upper": "1980-01-01",
    "iso:country": "GB",
    "wof:name": "NG5 4FH",
    "wof:placetype": "postalcode"
  },
  "geometry": {"coordinates":[-1.135944,52.991396],"type":"Point"}
}
