{
  "type": "Feature",
  "properties": {
    "date:inception_lower": "2005-02-01",
    "date:inception_upper": "2005-02-01",
    "iso:country": "GB",
    "wof:name": "B74 4AY",
    "wof:placetype": "postalcode"
  },
  "geometry": {"coordinates":[-1.834102,52.586385],"type":"Point"}
}
