{
  "type": "Feature",
  "properties": {
    "date:inception_lower": "2018-04-01",
    "date:inception_upper": "2018-04-01",
    "iso:country": "GB",
    "wof:name": "HD7 5ZD",
    "wof:placetype": "postalcode"
  },
  "geometry": {"coordinates":[-1.856434,53.619896],"type":"Point"}
}
