{
  "type": "Feature",
  "properties": {
    "iso:country":"GB",
    "wof:name":"SL2 3YJ",
    "wof:placetype":"postalcode"
},
  "geometry": {"coordinates":[-0.6016834749904,51.57072719454728],"type":"Point"}
}