{
  "type": "Feature",
  "properties": {
    "iso:country":"GB",
    "wof:name":"SO15 5LF",
    "wof:placetype":"postalcode"
},
  "geometry": {"coordinates":[-1.43260627460045,50.92309757286622],"type":"Point"}
}