{
  "type": "Feature",
  "properties": {
    "iso:country": "GB",
    "wof:name": "BN1 1HA",
    "wof:placetype": "postalcode"
  },
  "geometry": {"coordinates":[-0.141281,50.822186],"type":"Point"}
}
