{
  "type": "Feature",
  "properties": {
    "iso:country":"GB",
    "wof:name":"BN1 1HA",
    "wof:placetype":"postalcode"
},
  "geometry": {"coordinates":[-0.14128130785844,50.82218602575242],"type":"Point"}
}