{
  "type": "Feature",
  "properties": {
    "iso:country":"GB",
    "wof:name":"L36 9UJ",
    "wof:placetype":"postalcode"
},
  "geometry": {"coordinates":[-2.83987116873833,53.41178981503167],"type":"Point"}
}