{
  "type": "Feature",
  "properties": {
    "date:inception_lower":"1987-04-01",
    "date:inception_upper":"1987-04-30",
    "iso:country":"GB",
    "wof:name":"BD11 1DF",
    "wof:placetype":"postalcode"
},
  "geometry": {"coordinates":[-1.671802,53.752031],"type":"Point"}
}