{
  "type": "Feature",
  "properties": {
    "iso:country":"GB",
    "wof:name":"HP5 3DY",
    "wof:placetype":"postalcode"
},
  "geometry": {"coordinates":[-0.61041975531231,51.70810957830842],"type":"Point"}
}