{
  "type": "Feature",
  "properties": {
    "iso:country":"GB",
    "wof:name":"CA1 2SQ",
    "wof:placetype":"postalcode"
},
  "geometry": {"coordinates":[-2.91698659319672,54.87938756437893],"type":"Point"}
}