{
  "type": "Feature",
  "properties": {
    "date:inception_lower": "1993-01-01",
    "date:inception_upper": "1993-01-01",
    "iso:country": "GB",
    "wof:name": "CA1 2SQ",
    "wof:placetype": "postalcode"
  },
  "geometry": {"coordinates":[-2.916595,54.879802],"type":"Point"}
}
