{
  "type": "Feature",
  "properties": {
    "iso:country": "GB",
    "wof:name": "CA1 2SQ",
    "wof:placetype": "postalcode"
  },
  "geometry": {"coordinates":[-2.916595,54.879802],"type":"Point"}
}
