{
  "type": "Feature",
  "properties": {
    "iso:country":"GB",
    "wof:name":"NN17 3DT",
    "wof:placetype":"postalcode"
},
  "geometry": {"coordinates":[-0.66979470189389,52.53905267934761],"type":"Point"}
}