{
  "type": "Feature",
  "properties": {
    "date:inception_lower": "2004-10-01",
    "date:inception_upper": "2004-10-01",
    "iso:country": "GB",
    "wof:name": "HD8 9TY",
    "wof:placetype": "postalcode"
  },
  "geometry": {"coordinates":[-1.63617,53.612405],"type":"Point"}
}
