{
  "type": "Feature",
  "properties": {
    "iso:country": "GB",
    "wof:name": "HD8 9TY",
    "wof:placetype": "postalcode"
  },
  "geometry": {"coordinates":[-1.63617,53.612405],"type":"Point"}
}
