{
  "type": "Feature",
  "properties": {
    "iso:country": "GB",
    "wof:name": "WV15 6PU",
    "wof:placetype": "postalcode"
  },
  "geometry": {"coordinates":[-2.350719,52.458387],"type":"Point"}
}
