{
  "type": "Feature",
  "properties": {
    "iso:country":"GB",
    "wof:name":"HA2 9BS",
    "wof:placetype":"postalcode"
},
  "geometry": {"coordinates":[-0.36481384388186,51.56529196932983],"type":"Point"}
}