{
  "type": "Feature",
  "properties": {
    "iso:country":"GB",
    "wof:name":"BL5 2RX",
    "wof:placetype":"postalcode"
},
  "geometry": {"coordinates":[-2.5371222655953,53.53948350579756],"type":"Point"}
}