{
  "type": "Feature",
  "properties": {
    "date:inception_lower":"1990-02-01",
    "date:inception_upper":"1990-02-28",
    "iso:country":"GB",
    "wof:name":"BL5 2RX",
    "wof:placetype":"postalcode"
},
  "geometry": {"coordinates":[-2.537122,53.539484],"type":"Point"}
}