{
  "type": "Feature",
  "properties": {
    "iso:country":"GB",
    "wof:name":"CM1 4XN",
    "wof:placetype":"postalcode"
},
  "geometry": {"coordinates":[0.45322628953793,51.75388705989091],"type":"Point"}
}