{
  "type": "Feature",
  "properties": {
    "iso:country": "GB",
    "wof:name": "CM1 4XN",
    "wof:placetype": "postalcode"
  },
  "geometry": {"coordinates":[0.453226,51.753887],"type":"Point"}
}
