{
  "type": "Feature",
  "properties": {
    "iso:country":"GB",
    "wof:name":"SK3 0TP",
    "wof:placetype":"postalcode"
},
  "geometry": {"coordinates":[-2.18379804085986,53.39793823228281],"type":"Point"}
}