{
  "type": "Feature",
  "properties": {
    "iso:country":"GB",
    "wof:name":"SM6 8ET",
    "wof:placetype":"postalcode"
},
  "geometry": {"coordinates":[-0.14078126368875,51.3649198718924],"type":"Point"}
}