{
  "type": "Feature",
  "properties": {
    "date:inception_lower": "1980-01-01",
    "date:inception_upper": "1980-01-01",
    "iso:country": "GB",
    "wof:name": "PO14 1QP",
    "wof:placetype": "postalcode"
  },
  "geometry": {"coordinates":[-1.207003,50.847577],"type":"Point"}
}
