{
  "type": "Feature",
  "properties": {
    "iso:country": "GB",
    "wof:name": "M44 6DU",
    "wof:placetype": "postalcode"
  },
  "geometry": {"coordinates":[-2.413648,53.446782],"type":"Point"}
}
