{
  "type": "Feature",
  "properties": {
    "iso:country": "GB",
    "wof:name": "DE13 0FZ",
    "wof:placetype": "postalcode"
  },
  "geometry": {"coordinates":[-1.626132,52.83649],"type":"Point"}
}
