{
  "type": "Feature",
  "properties": {
    "iso:country":"GB",
    "wof:name":"NW3 4HT",
    "wof:placetype":"postalcode"
},
  "geometry": {"coordinates":[-0.17039591638944,51.54688280456122],"type":"Point"}
}