{
  "type": "Feature",
  "properties": {
    "iso:country":"GB",
    "wof:name":"LL46 2RT",
    "wof:placetype":"postalcode"
},
  "geometry": {"coordinates":[-4.11395535835139,52.84138994080432],"type":"Point"}
}