{
  "type": "Feature",
  "properties": {
    "date:inception_lower": "1980-01-01",
    "date:inception_upper": "1980-01-01",
    "iso:country": "GB",
    "wof:name": "LL46 2RT",
    "wof:placetype": "postalcode"
  },
  "geometry": {"coordinates":[-4.113955,52.84139],"type":"Point"}
}
