{
  "type": "Feature",
  "properties": {
    "iso:country": "GB",
    "wof:name": "EX35 6PZ",
    "wof:placetype": "postalcode"
  },
  "geometry": {"coordinates":[-3.847822,51.196494],"type":"Point"}
}
