{
  "type": "Feature",
  "properties": {
    "iso:country":"GB",
    "wof:name":"EX35 6PZ",
    "wof:placetype":"postalcode"
},
  "geometry": {"coordinates":[-3.8478221468748,51.19649450043489],"type":"Point"}
}