{
  "type": "Feature",
  "properties": {
    "iso:country":"GB",
    "wof:name":"BH25 7HP",
    "wof:placetype":"postalcode"
},
  "geometry": {"coordinates":[-1.66928280707081,50.73945354597271],"type":"Point"}
}