{
  "type": "Feature",
  "properties": {
    "iso:country":"GB",
    "wof:name":"CR5 2HW",
    "wof:placetype":"postalcode"
},
  "geometry": {"coordinates":[-0.12687320936142,51.31355647369827],"type":"Point"}
}