{
  "type": "Feature",
  "properties": {
    "iso:country":"GB",
    "wof:name":"LN6 0JW",
    "wof:placetype":"postalcode"
},
  "geometry": {"coordinates":[-0.59508580448358,53.21808253994212],"type":"Point"}
}