{
  "type": "Feature",
  "properties": {
    "iso:country":"GB",
    "wof:name":"KA12 0EP",
    "wof:placetype":"postalcode"
},
  "geometry": {"coordinates":[-4.65662320297728,55.61032269378745],"type":"Point"}
}