{
  "type": "Feature",
  "properties": {
    "iso:country": "GB",
    "wof:name": "TW6 2FG",
    "wof:placetype": "postalcode"
  },
  "geometry": {"coordinates":[-0.451057,51.479265],"type":"Point"}
}
