{
  "type": "Feature",
  "properties": {
    "date:inception_lower": "2016-05-01",
    "date:inception_upper": "2016-05-01",
    "iso:country": "GB",
    "wof:name": "TW6 2FG",
    "wof:placetype": "postalcode"
  },
  "geometry": {"coordinates":[-0.451057,51.479265],"type":"Point"}
}
