{
  "type": "Feature",
  "properties": {
    "iso:country":"GB",
    "wof:name":"AB45 2LG",
    "wof:placetype":"postalcode"
},
  "geometry": {"coordinates":[-2.57779212473606,57.67742696881848],"type":"Point"}
}