{
  "type": "Feature",
  "properties": {
    "iso:country":"GB",
    "wof:name":"AL1 3NL",
    "wof:placetype":"postalcode"
},
  "geometry": {"coordinates":[-0.33322847611319,51.75370848556864],"type":"Point"}
}