{
  "type": "Feature",
  "properties": {
    "iso:country": "GB",
    "wof:name": "AL1 3NL",
    "wof:placetype": "postalcode"
  },
  "geometry": {"coordinates":[-0.333228,51.753708],"type":"Point"}
}
