{
  "type": "Feature",
  "properties": {
    "date:inception_lower": "2009-01-01",
    "date:inception_upper": "2009-01-01",
    "iso:country": "GB",
    "wof:name": "S20 3GL",
    "wof:placetype": "postalcode"
  },
  "geometry": {"coordinates":[-1.332692,53.332415],"type":"Point"}
}
