{
  "type": "Feature",
  "properties": {
    "iso:country":"GB",
    "wof:name":"S20 3GL",
    "wof:placetype":"postalcode"
},
  "geometry": {"coordinates":[-1.33261335680994,53.33262085324663],"type":"Point"}
}