{
  "type": "Feature",
  "properties": {
    "iso:country":"GB",
    "wof:name":"RG10 9DN",
    "wof:placetype":"postalcode"
},
  "geometry": {"coordinates":[-0.86604367053392,51.47724051068552],"type":"Point"}
}