{
  "type": "Feature",
  "properties": {
    "iso:country": "GB",
    "wof:name": "BD20 9AB",
    "wof:placetype": "postalcode"
  },
  "geometry": {"coordinates":[-1.962027,53.912341],"type":"Point"}
}
