{
  "type": "Feature",
  "properties": {
    "iso:country":"GB",
    "wof:name":"BD20 9AB",
    "wof:placetype":"postalcode"
},
  "geometry": {"coordinates":[-1.96202739081072,53.91234134742194],"type":"Point"}
}