{
  "type": "Feature",
  "properties": {
    "iso:country":"GB",
    "wof:name":"IV2 5BE",
    "wof:placetype":"postalcode"
},
  "geometry": {"coordinates":[-4.15980239715258,57.45750389625326],"type":"Point"}
}