{
  "type": "Feature",
  "properties": {
    "iso:country":"GB",
    "wof:name":"EH47 9LH",
    "wof:placetype":"postalcode"
},
  "geometry": {"coordinates":[-3.70086206641967,55.82971104387011],"type":"Point"}
}