{
  "type": "Feature",
  "properties": {
    "date:inception_lower": "2014-09-01",
    "date:inception_upper": "2014-09-01",
    "iso:country": "GB",
    "wof:name": "BA5 1WE",
    "wof:placetype": "postalcode"
  },
  "geometry": {"coordinates":[-2.65595,51.202236],"type":"Point"}
}
