{
  "type": "Feature",
  "properties": {
    "iso:country":"GB",
    "wof:name":"CO2 7AX",
    "wof:placetype":"postalcode"
},
  "geometry": {"coordinates":[0.8971138134962,51.88594138154657],"type":"Point"}
}