{
  "type": "Feature",
  "properties": {
    "date:inception_lower": "1980-01-01",
    "date:inception_upper": "1980-01-01",
    "iso:country": "GB",
    "wof:name": "DE6 1LD",
    "wof:placetype": "postalcode"
  },
  "geometry": {"coordinates":[-1.742194,53.048028],"type":"Point"}
}
