{
  "type": "Feature",
  "properties": {
    "iso:country": "GB",
    "wof:name": "DE6 1LD",
    "wof:placetype": "postalcode"
  },
  "geometry": {"coordinates":[-1.742194,53.048028],"type":"Point"}
}
