{
  "type": "Feature",
  "properties": {
    "iso:country":"GB",
    "wof:name":"DE6 1LD",
    "wof:placetype":"postalcode"
},
  "geometry": {"coordinates":[-1.74219405819219,53.04802818151536],"type":"Point"}
}