{
  "type": "Feature",
  "properties": {
    "iso:country":"GB",
    "wof:name":"E1 8AY",
    "wof:placetype":"postalcode"
},
  "geometry": {"coordinates":[-0.06919837528554,51.51162876183446],"type":"Point"}
}