{
  "type": "Feature",
  "properties": {
    "iso:country":"GB",
    "wof:name":"SE10 8BL",
    "wof:placetype":"postalcode"
},
  "geometry": {"coordinates":[-0.00630640663697,51.47694383515446],"type":"Point"}
}