{
  "type": "Feature",
  "properties": {
    "iso:country": "GB",
    "wof:name": "NG17 8SW",
    "wof:placetype": "postalcode"
  },
  "geometry": {"coordinates":[-1.259955,53.111494],"type":"Point"}
}
