{
  "type": "Feature",
  "properties": {
    "iso:country":"GB",
    "wof:name":"NG17 8SW",
    "wof:placetype":"postalcode"
},
  "geometry": {"coordinates":[-1.25995540480243,53.11149363498839],"type":"Point"}
}