{
  "type": "Feature",
  "properties": {
    "iso:country":"GB",
    "wof:name":"DA6 7NT",
    "wof:placetype":"postalcode"
},
  "geometry": {"coordinates":[0.15480029069592,51.45010932544305],"type":"Point"}
}