{
  "type": "Feature",
  "properties": {
    "date:inception_lower": "1980-01-01",
    "date:inception_upper": "1980-01-01",
    "iso:country": "GB",
    "wof:name": "IP2 0SN",
    "wof:placetype": "postalcode"
  },
  "geometry": {"coordinates":[1.10996,52.042059],"type":"Point"}
}
