{
  "type": "Feature",
  "properties": {
    "iso:country": "GB",
    "wof:name": "IP2 0SN",
    "wof:placetype": "postalcode"
  },
  "geometry": {"coordinates":[1.109959,52.042044],"type":"Point"}
}
