{
  "type": "Feature",
  "properties": {
    "iso:country":"GB",
    "wof:name":"IP2 0SN",
    "wof:placetype":"postalcode"
},
  "geometry": {"coordinates":[1.10995883610911,52.04204450591545],"type":"Point"}
}