{
  "type": "Feature",
  "properties": {
    "iso:country": "GB",
    "wof:name": "SO50 4RT",
    "wof:placetype": "postalcode"
  },
  "geometry": {"coordinates":[-1.352371,50.985323],"type":"Point"}
}
