{
  "type": "Feature",
  "properties": {
    "iso:country":"GB",
    "wof:name":"GU9 0LF",
    "wof:placetype":"postalcode"
},
  "geometry": {"coordinates":[-0.78938652487683,51.23995453616594],"type":"Point"}
}