{
  "type": "Feature",
  "properties": {
    "iso:country": "GB",
    "wof:name": "N1 8LH",
    "wof:placetype": "postalcode"
  },
  "geometry": {"coordinates":[-0.098985,51.531755],"type":"Point"}
}
