{
  "type": "Feature",
  "properties": {
    "iso:country":"GB",
    "wof:name":"SN10 3AA",
    "wof:placetype":"postalcode"
},
  "geometry": {"coordinates":[-1.98576336927692,51.35199965795677],"type":"Point"}
}