{
  "type": "Feature",
  "properties": {
    "iso:country": "GB",
    "wof:name": "BL4 7PG",
    "wof:placetype": "postalcode"
  },
  "geometry": {"coordinates":[-2.396753,53.551411],"type":"Point"}
}
