{
  "type": "Feature",
  "properties": {
    "date:inception_lower": "1980-01-01",
    "date:inception_upper": "1980-01-01",
    "iso:country": "GB",
    "wof:name": "EX17 2AH",
    "wof:placetype": "postalcode"
  },
  "geometry": {"coordinates":[-3.651886,50.790181],"type":"Point"}
}
