{
  "type": "Feature",
  "properties": {
    "iso:country":"GB",
    "wof:name":"NR1 1EG",
    "wof:placetype":"postalcode"
},
  "geometry": {"coordinates":[1.30674466735123,52.62674024586423],"type":"Point"}
}