{
  "type": "Feature",
  "properties": {
    "date:inception_lower": "1992-08-01",
    "date:inception_upper": "1992-08-01",
    "iso:country": "GB",
    "wof:name": "NR1 1EG",
    "wof:placetype": "postalcode"
  },
  "geometry": {"coordinates":[1.306745,52.62674],"type":"Point"}
}
