{
  "type": "Feature",
  "properties": {
    "date:inception_lower": "1980-01-01",
    "date:inception_upper": "1980-01-01",
    "iso:country": "GB",
    "wof:name": "NW8 8QR",
    "wof:placetype": "postalcode"
  },
  "geometry": {"coordinates":[-0.172935,51.527777],"type":"Point"}
}
