{
  "type": "Feature",
  "properties": {
    "iso:country":"GB",
    "wof:name":"NW8 8QR",
    "wof:placetype":"postalcode"
},
  "geometry": {"coordinates":[-0.17293514700149,51.52777747857062],"type":"Point"}
}