{
  "type": "Feature",
  "properties": {
    "iso:country": "GB",
    "wof:name": "SP2 0FD",
    "wof:placetype": "postalcode"
  },
  "geometry": {"coordinates":[-1.867462,51.081083],"type":"Point"}
}
