{
  "type": "Feature",
  "properties": {
    "iso:country":"GB",
    "wof:name":"CA14 5BW",
    "wof:placetype":"postalcode"
},
  "geometry": {"coordinates":[-3.55924687964772,54.62573336289464],"type":"Point"}
}