{
  "type": "Feature",
  "properties": {
    "iso:country": "GB",
    "wof:name": "CA14 5BW",
    "wof:placetype": "postalcode"
  },
  "geometry": {"coordinates":[-3.559247,54.625733],"type":"Point"}
}
