{
  "type": "Feature",
  "properties": {
    "date:inception_lower": "1980-01-01",
    "date:inception_upper": "1980-01-01",
    "iso:country": "GB",
    "wof:name": "NE33 4JU",
    "wof:placetype": "postalcode"
  },
  "geometry": {"coordinates":[-1.432027,54.983744],"type":"Point"}
}
