{
  "type": "Feature",
  "properties": {
    "date:inception_lower": "2005-05-01",
    "date:inception_upper": "2005-05-01",
    "iso:country": "GB",
    "wof:name": "LL11 6AZ",
    "wof:placetype": "postalcode"
  },
  "geometry": {"coordinates":[-3.036959,53.070518],"type":"Point"}
}
