{
  "type": "Feature",
  "properties": {
    "iso:country": "GB",
    "wof:name": "LL11 6AZ",
    "wof:placetype": "postalcode"
  },
  "geometry": {"coordinates":[-3.036959,53.070518],"type":"Point"}
}
