{
  "type": "Feature",
  "properties": {
    "date:inception_lower":"2016-03-01",
    "date:inception_upper":"2016-03-31",
    "iso:country":"GB",
    "wof:name":"WF4 5FB",
    "wof:placetype":"postalcode"
},
  "geometry": {"coordinates":[-1.544943,53.665392],"type":"Point"}
}