{
  "type": "Feature",
  "properties": {
    "iso:country":"GB",
    "wof:name":"CM5 9PN",
    "wof:placetype":"postalcode"
},
  "geometry": {"coordinates":[0.22554307528731,51.67913158656651],"type":"Point"}
}