{
  "type": "Feature",
  "properties": {
    "date:inception_lower": "1980-01-01",
    "date:inception_upper": "1980-01-01",
    "iso:country": "GB",
    "wof:name": "CM5 9PN",
    "wof:placetype": "postalcode"
  },
  "geometry": {"coordinates":[0.225543,51.679132],"type":"Point"}
}
