{
  "type": "Feature",
  "properties": {
    "date:inception_lower": "2001-12-01",
    "date:inception_upper": "2001-12-01",
    "iso:country": "GB",
    "wof:name": "FY2 0WS",
    "wof:placetype": "postalcode"
  },
  "geometry": {"coordinates":[-3.037928,53.838754],"type":"Point"}
}
