{
  "type": "Feature",
  "properties": {
    "iso:country":"GB",
    "wof:name":"FY2 0WS",
    "wof:placetype":"postalcode"
},
  "geometry": {"coordinates":[-3.02751865817143,53.84912953716535],"type":"Point"}
}