{
  "type": "Feature",
  "properties": {
    "iso:country":"GB",
    "wof:name":"ST6 3AZ",
    "wof:placetype":"postalcode"
},
  "geometry": {"coordinates":[-2.19954526924584,53.04422888379175],"type":"Point"}
}