{
  "type": "Feature",
  "properties": {
    "iso:country": "GB",
    "wof:name": "SN5 4DP",
    "wof:placetype": "postalcode"
  },
  "geometry": {"coordinates":[-1.86835,51.58703],"type":"Point"}
}
