{
  "type": "Feature",
  "properties": {
    "iso:country":"GB",
    "wof:name":"NE19 1BX",
    "wof:placetype":"postalcode"
},
  "geometry": {"coordinates":[-2.07319271239296,55.23161344388565],"type":"Point"}
}