{
  "type": "Feature",
  "properties": {
    "iso:country":"GB",
    "wof:name":"M5 4AQ",
    "wof:placetype":"postalcode"
},
  "geometry": {"coordinates":[-2.28185704020201,53.48267941785629],"type":"Point"}
}