{
  "type": "Feature",
  "properties": {
    "iso:country": "GB",
    "wof:name": "SK5 7SU",
    "wof:placetype": "postalcode"
  },
  "geometry": {"coordinates":[-2.15964,53.432561],"type":"Point"}
}
