{
  "type": "Feature",
  "properties": {
    "iso:country":"GB",
    "wof:name":"SK5 7SU",
    "wof:placetype":"postalcode"
},
  "geometry": {"coordinates":[-2.1596398006434,53.4325609427107],"type":"Point"}
}