{
  "type": "Feature",
  "properties": {
    "date:inception_lower": "1980-01-01",
    "date:inception_upper": "1980-01-01",
    "iso:country": "GB",
    "wof:name": "CT1 2QG",
    "wof:placetype": "postalcode"
  },
  "geometry": {"coordinates":[1.077791,51.276638],"type":"Point"}
}
