{
  "type": "Feature",
  "properties": {
    "iso:country":"GB",
    "wof:name":"SG5 4NX",
    "wof:placetype":"postalcode"
},
  "geometry": {"coordinates":[-0.22245982174199,52.01390254768693],"type":"Point"}
}