{
  "type": "Feature",
  "properties": {
    "iso:country":"GB",
    "wof:name":"RH14 0RA",
    "wof:placetype":"postalcode"
},
  "geometry": {"coordinates":[-0.50990110895328,51.08568113643292],"type":"Point"}
}