{
  "type": "Feature",
  "properties": {
    "iso:country": "GB",
    "wof:name": "RH14 0RA",
    "wof:placetype": "postalcode"
  },
  "geometry": {"coordinates":[-0.509901,51.085681],"type":"Point"}
}
