{
  "type": "Feature",
  "properties": {
    "date:inception_lower":"2000-10-01",
    "date:inception_upper":"2000-10-31",
    "iso:country":"GB",
    "wof:name":"OX26 6XF",
    "wof:placetype":"postalcode"
},
  "geometry": {"coordinates":[-1.138019,51.892602],"type":"Point"}
}