{
  "type": "Feature",
  "properties": {
    "iso:country":"GB",
    "wof:name":"OX26 6XF",
    "wof:placetype":"postalcode"
},
  "geometry": {"coordinates":[-1.13801862184741,51.89260189246792],"type":"Point"}
}