{
  "type": "Feature",
  "properties": {
    "iso:country":"GB",
    "wof:name":"BA2 3NX",
    "wof:placetype":"postalcode"
},
  "geometry": {"coordinates":[-2.37632857032463,51.37244484836157],"type":"Point"}
}