{
  "type": "Feature",
  "properties": {
    "iso:country":"GB",
    "wof:name":"SA13 1YA",
    "wof:placetype":"postalcode"
},
  "geometry": {"coordinates":[-3.7814604826925,51.59729831137386],"type":"Point"}
}