{
  "type": "Feature",
  "properties": {
    "iso:country":"GB",
    "wof:name":"TR4 8TW",
    "wof:placetype":"postalcode"
},
  "geometry": {"coordinates":[-5.14659872922151,50.21677113654694],"type":"Point"}
}