{
  "type": "Feature",
  "properties": {
    "date:inception_lower": "2011-05-01",
    "date:inception_upper": "2011-05-01",
    "iso:country": "GB",
    "wof:name": "TR4 8TW",
    "wof:placetype": "postalcode"
  },
  "geometry": {"coordinates":[-5.146599,50.216771],"type":"Point"}
}
