{
  "type": "Feature",
  "properties": {
    "iso:country":"GB",
    "wof:name":"WR11 1YE",
    "wof:placetype":"postalcode"
},
  "geometry": {"coordinates":[-1.9334803825383,52.08454297662487],"type":"Point"}
}