{
  "type": "Feature",
  "properties": {
    "iso:country":"GB",
    "wof:name":"OX9 2AA",
    "wof:placetype":"postalcode"
},
  "geometry": {"coordinates":[-0.98200411509694,51.74905965952595],"type":"Point"}
}