{
  "type": "Feature",
  "properties": {
    "iso:country":"GB",
    "wof:name":"CV36 5EH",
    "wof:placetype":"postalcode"
},
  "geometry": {"coordinates":[-1.55595109808424,52.08369930704446],"type":"Point"}
}