{
  "type": "Feature",
  "properties": {
    "iso:country": "GB",
    "wof:name": "CV36 5EH",
    "wof:placetype": "postalcode"
  },
  "geometry": {"coordinates":[-1.555951,52.083699],"type":"Point"}
}
