{
  "type": "Feature",
  "properties": {
    "date:inception_lower": "2015-02-01",
    "date:inception_upper": "2015-02-01",
    "iso:country": "GB",
    "wof:name": "LE12 8FW",
    "wof:placetype": "postalcode"
  },
  "geometry": {"coordinates":[-1.169798,52.744721],"type":"Point"}
}
