{
  "type": "Feature",
  "properties": {
    "iso:country":"GB",
    "wof:name":"LE12 8FW",
    "wof:placetype":"postalcode"
},
  "geometry": {"coordinates":[-1.16965890034585,52.74462880961025],"type":"Point"}
}