{
  "type": "Feature",
  "properties": {
    "iso:country":"GB",
    "wof:name":"S10 1GN",
    "wof:placetype":"postalcode"
},
  "geometry": {"coordinates":[-1.50225872065101,53.38365968122816],"type":"Point"}
}