{
  "type": "Feature",
  "properties": {
    "iso:country": "GB",
    "wof:name": "BD3 7AY",
    "wof:placetype": "postalcode"
  },
  "geometry": {"coordinates":[-1.704885,53.798675],"type":"Point"}
}
