{
  "type": "Feature",
  "properties": {
    "date:inception_lower":"2000-12-01",
    "date:inception_upper":"2000-12-31",
    "iso:country":"GB",
    "wof:name":"BD3 7AY",
    "wof:placetype":"postalcode"
},
  "geometry": {"coordinates":[-1.704885,53.798675],"type":"Point"}
}