{
  "type": "Feature",
  "properties": {
    "iso:country": "GB",
    "wof:name": "CF63 4JX",
    "wof:placetype": "postalcode"
  },
  "geometry": {"coordinates":[-3.265885,51.403724],"type":"Point"}
}
