{
  "type": "Feature",
  "properties": {
    "date:inception_lower": "1993-08-01",
    "date:inception_upper": "1993-08-01",
    "iso:country": "GB",
    "wof:name": "CF63 4JX",
    "wof:placetype": "postalcode"
  },
  "geometry": {"coordinates":[-3.265885,51.403724],"type":"Point"}
}
