{
  "type": "Feature",
  "properties": {
    "iso:country":"GB",
    "wof:name":"CF63 4JX",
    "wof:placetype":"postalcode"
},
  "geometry": {"coordinates":[-3.26588546874981,51.40372390633137],"type":"Point"}
}