{
  "type": "Feature",
  "properties": {
    "iso:country":"GB",
    "wof:name":"S70 4ST",
    "wof:placetype":"postalcode"
},
  "geometry": {"coordinates":[-1.45537498258711,53.53023876844028],"type":"Point"}
}