{
  "type": "Feature",
  "properties": {
    "date:inception_lower": "1980-01-01",
    "date:inception_upper": "1980-01-01",
    "iso:country": "GB",
    "wof:name": "NW11 6TG",
    "wof:placetype": "postalcode"
  },
  "geometry": {"coordinates":[-0.177125,51.57374],"type":"Point"}
}
