{
  "type": "Feature",
  "properties": {
    "iso:country":"GB",
    "wof:name":"NW11 6TG",
    "wof:placetype":"postalcode"
},
  "geometry": {"coordinates":[-0.17712492832911,51.5737399370478],"type":"Point"}
}