{
  "type": "Feature",
  "properties": {
    "iso:country": "GB",
    "wof:name": "PO22 8EQ",
    "wof:placetype": "postalcode"
  },
  "geometry": {"coordinates":[-0.645758,50.796038],"type":"Point"}
}
