{
  "type": "Feature",
  "properties": {
    "iso:country": "GB",
    "wof:name": "OL12 9BE",
    "wof:placetype": "postalcode"
  },
  "geometry": {"coordinates":[-2.144639,53.62423],"type":"Point"}
}
