{
  "type": "Feature",
  "properties": {
    "iso:country":"GB",
    "wof:name":"OL12 9BE",
    "wof:placetype":"postalcode"
},
  "geometry": {"coordinates":[-2.14463922087047,53.62423012357307],"type":"Point"}
}