{
  "type": "Feature",
  "properties": {
    "date:inception_lower": "1994-05-01",
    "date:inception_upper": "1994-05-01",
    "iso:country": "GB",
    "wof:name": "NN29 7DN",
    "wof:placetype": "postalcode"
  },
  "geometry": {"coordinates":[-0.655677,52.280506],"type":"Point"}
}
