{
  "type": "Feature",
  "properties": {
    "iso:country":"GB",
    "wof:name":"LN6 0YZ",
    "wof:placetype":"postalcode"
},
  "geometry": {"coordinates":[-0.61116783832522,53.21633826489544],"type":"Point"}
}