{
  "type": "Feature",
  "properties": {
    "iso:country": "GB",
    "wof:name": "YO31 7EN",
    "wof:placetype": "postalcode"
  },
  "geometry": {"coordinates":[-1.080957,53.967749],"type":"Point"}
}
