{
  "type": "Feature",
  "properties": {
    "iso:country": "GB",
    "wof:name": "HU12 8XJ",
    "wof:placetype": "postalcode"
  },
  "geometry": {"coordinates":[-0.209754,53.741108],"type":"Point"}
}
