{
  "type": "Feature",
  "properties": {
    "iso:country":"GB",
    "wof:name":"HU12 8XJ",
    "wof:placetype":"postalcode"
},
  "geometry": {"coordinates":[-0.20975414446891,53.74110768846629],"type":"Point"}
}