{
  "type": "Feature",
  "properties": {
    "date:inception_lower":"1990-07-01",
    "date:inception_upper":"1990-07-31",
    "iso:country":"GB",
    "wof:name":"HU12 8XJ",
    "wof:placetype":"postalcode"
},
  "geometry": {"coordinates":[-0.209754,53.741108],"type":"Point"}
}