{
  "type": "Feature",
  "properties": {
    "iso:country":"GB",
    "wof:name":"NE30 1BB",
    "wof:placetype":"postalcode"
},
  "geometry": {"coordinates":[-1.44366135725581,55.01028056572018],"type":"Point"}
}