{
  "type": "Feature",
  "properties": {
    "date:inception_lower": "1980-01-01",
    "date:inception_upper": "1980-01-01",
    "iso:country": "GB",
    "wof:name": "LE5 0QE",
    "wof:placetype": "postalcode"
  },
  "geometry": {"coordinates":[-1.099986,52.642256],"type":"Point"}
}
