{
  "type": "Feature",
  "properties": {
    "iso:country":"GB",
    "wof:name":"LE5 0QE",
    "wof:placetype":"postalcode"
},
  "geometry": {"coordinates":[-1.09991966998799,52.64229135874594],"type":"Point"}
}