{
  "type": "Feature",
  "properties": {
    "iso:country": "GB",
    "wof:name": "TS16 0DW",
    "wof:placetype": "postalcode"
  },
  "geometry": {"coordinates":[-1.352498,54.522499],"type":"Point"}
}
