{
  "type": "Feature",
  "properties": {
    "iso:country":"GB",
    "wof:name":"BD22 8RS",
    "wof:placetype":"postalcode"
},
  "geometry": {"coordinates":[-1.94408607751701,53.82697677879777],"type":"Point"}
}