{
  "type": "Feature",
  "properties": {
    "iso:country": "GB",
    "wof:name": "G83 0AU",
    "wof:placetype": "postalcode"
  },
  "geometry": {"coordinates":[-4.584414,55.982015],"type":"Point"}
}
