{
  "type": "Feature",
  "properties": {
    "date:inception_lower": "1980-01-01",
    "date:inception_upper": "1980-01-01",
    "iso:country": "GB",
    "wof:name": "G83 0AU",
    "wof:placetype": "postalcode"
  },
  "geometry": {"coordinates":[-4.584414,55.982015],"type":"Point"}
}
