{
  "type": "Feature",
  "properties": {
    "iso:country":"GB",
    "wof:name":"LE5 4GP",
    "wof:placetype":"postalcode"
},
  "geometry": {"coordinates":[-1.09462613775594,52.63597601500205],"type":"Point"}
}