{
  "type": "Feature",
  "properties": {
    "iso:country":"GB",
    "wof:name":"B61 0UP",
    "wof:placetype":"postalcode"
},
  "geometry": {"coordinates":[-2.06233547767661,52.35064168285501],"type":"Point"}
}