{
  "type": "Feature",
  "properties": {
    "date:inception_lower": "2002-05-01",
    "date:inception_upper": "2002-05-01",
    "iso:country": "GB",
    "wof:name": "B61 0UP",
    "wof:placetype": "postalcode"
  },
  "geometry": {"coordinates":[-2.062335,52.350642],"type":"Point"}
}
