{
  "type": "Feature",
  "properties": {
    "iso:country": "GB",
    "wof:name": "B61 0UP",
    "wof:placetype": "postalcode"
  },
  "geometry": {"coordinates":[-2.062335,52.350642],"type":"Point"}
}
