{
  "type": "Feature",
  "properties": {
    "iso:country":"GB",
    "wof:name":"CM2 7QA",
    "wof:placetype":"postalcode"
},
  "geometry": {"coordinates":[0.48759650966253,51.72277678695593],"type":"Point"}
}