{
  "type": "Feature",
  "properties": {
    "iso:country":"GB",
    "wof:name":"WD7 8LQ",
    "wof:placetype":"postalcode"
},
  "geometry": {"coordinates":[-0.32350104772985,51.68536569176532],"type":"Point"}
}