{
  "type": "Feature",
  "properties": {
    "iso:country":"GB",
    "wof:name":"SW11 6HH",
    "wof:placetype":"postalcode"
},
  "geometry": {"coordinates":[-0.16232762804867,51.45533896344831],"type":"Point"}
}