{
  "type": "Feature",
  "properties": {
    "date:inception_lower": "1990-07-01",
    "date:inception_upper": "1990-07-01",
    "iso:country": "GB",
    "wof:name": "IG1 2XH",
    "wof:placetype": "postalcode"
  },
  "geometry": {"coordinates":[0.080921,51.550023],"type":"Point"}
}
