{
  "type": "Feature",
  "properties": {
    "iso:country":"GB",
    "wof:name":"DN11 0SW",
    "wof:placetype":"postalcode"
},
  "geometry": {"coordinates":[-1.0778732987001,53.47599632018721],"type":"Point"}
}