{
  "type": "Feature",
  "properties": {
    "date:inception_lower":"2005-05-01",
    "date:inception_upper":"2005-05-31",
    "iso:country":"GB",
    "wof:name":"PE36 5PW",
    "wof:placetype":"postalcode"
},
  "geometry": {"coordinates":[0.497329,52.937319],"type":"Point"}
}