{
  "type": "Feature",
  "properties": {
    "iso:country":"GB",
    "wof:name":"PE36 5PW",
    "wof:placetype":"postalcode"
},
  "geometry": {"coordinates":[0.49732941625531,52.93731917238958],"type":"Point"}
}