{
  "type": "Feature",
  "properties": {
    "iso:country":"GB",
    "wof:name":"TS9 6QA",
    "wof:placetype":"postalcode"
},
  "geometry": {"coordinates":[-1.16881967613023,54.47742951268018],"type":"Point"}
}