{
  "type": "Feature",
  "properties": {
    "iso:country":"GB",
    "wof:name":"CH45 7LN",
    "wof:placetype":"postalcode"
},
  "geometry": {"coordinates":[-3.04188037216105,53.42314187436259],"type":"Point"}
}