{
  "type": "Feature",
  "properties": {
    "iso:country":"GB",
    "wof:name":"DN4 6LQ",
    "wof:placetype":"postalcode"
},
  "geometry": {"coordinates":[-1.07855857514969,53.51252290595298],"type":"Point"}
}