{
  "type": "Feature",
  "properties": {
    "date:inception_lower": "1980-01-01",
    "date:inception_upper": "1980-01-01",
    "iso:country": "GB",
    "wof:name": "IP22 1NH",
    "wof:placetype": "postalcode"
  },
  "geometry": {"coordinates":[0.954541,52.332073],"type":"Point"}
}
