{
  "type": "Feature",
  "properties": {
    "iso:country":"GB",
    "wof:name":"IP22 1NH",
    "wof:placetype":"postalcode"
},
  "geometry": {"coordinates":[0.95447161150183,52.33212770467318],"type":"Point"}
}