{
  "type": "Feature",
  "properties": {
    "iso:country":"GB",
    "wof:name":"ME13 8LU",
    "wof:placetype":"postalcode"
},
  "geometry": {"coordinates":[0.89381067159027,51.30800098809014],"type":"Point"}
}