{
  "type": "Feature",
  "properties": {
    "iso:country": "GB",
    "wof:name": "BA14 6FN",
    "wof:placetype": "postalcode"
  },
  "geometry": {"coordinates":[-2.193418,51.314219],"type":"Point"}
}
