{
  "type": "Feature",
  "properties": {
    "iso:country":"GB",
    "wof:name":"BA14 6FN",
    "wof:placetype":"postalcode"
},
  "geometry": {"coordinates":[-2.19341767975632,51.31421898707035],"type":"Point"}
}