{
  "type": "Feature",
  "properties": {
    "iso:country":"GB",
    "wof:name":"S42 7DS",
    "wof:placetype":"postalcode"
},
  "geometry": {"coordinates":[-1.487861832429,53.22758018411928],"type":"Point"}
}