{
  "type": "Feature",
  "properties": {
    "date:inception_lower": "1992-10-01",
    "date:inception_upper": "1992-10-01",
    "iso:country": "GB",
    "wof:name": "ML8 4BS",
    "wof:placetype": "postalcode"
  },
  "geometry": {"coordinates":[-3.839336,55.736314],"type":"Point"}
}
