{
  "type": "Feature",
  "properties": {
    "iso:country":"GB",
    "wof:name":"ML8 4BS",
    "wof:placetype":"postalcode"
},
  "geometry": {"coordinates":[-3.83933593965558,55.73631417301952],"type":"Point"}
}