{
  "type": "Feature",
  "properties": {
    "iso:country":"GB",
    "wof:name":"S20 4TQ",
    "wof:placetype":"postalcode"
},
  "geometry": {"coordinates":[-1.35489029762254,53.32015895719847],"type":"Point"}
}