{
  "type": "Feature",
  "properties": {
    "date:inception_lower": "1997-06-01",
    "date:inception_upper": "1997-06-01",
    "iso:country": "GB",
    "wof:name": "S20 4TQ",
    "wof:placetype": "postalcode"
  },
  "geometry": {"coordinates":[-1.354876,53.320169],"type":"Point"}
}
