{
  "type": "Feature",
  "properties": {
    "iso:country":"GB",
    "wof:name":"HA4 6HQ",
    "wof:placetype":"postalcode"
},
  "geometry": {"coordinates":[-0.42445343888354,51.56588302959607],"type":"Point"}
}