{
  "type": "Feature",
  "properties": {
    "date:inception_lower": "1980-01-01",
    "date:inception_upper": "1980-01-01",
    "iso:country": "GB",
    "wof:name": "NG9 3JX",
    "wof:placetype": "postalcode"
  },
  "geometry": {"coordinates":[-1.257682,52.938749],"type":"Point"}
}
