{
  "type": "Feature",
  "properties": {
    "iso:country":"GB",
    "wof:name":"PR9 0LL",
    "wof:placetype":"postalcode"
},
  "geometry": {"coordinates":[-2.99684523362541,53.65262253395064],"type":"Point"}
}