{
  "type": "Feature",
  "properties": {
    "date:inception_lower": "1980-01-01",
    "date:inception_upper": "1980-01-01",
    "iso:country": "GB",
    "wof:name": "PR9 0LL",
    "wof:placetype": "postalcode"
  },
  "geometry": {"coordinates":[-2.996845,53.652623],"type":"Point"}
}
