{
  "type": "Feature",
  "properties": {
    "iso:country": "GB",
    "wof:name": "SM2 5EZ",
    "wof:placetype": "postalcode"
  },
  "geometry": {"coordinates":[-0.187814,51.358355],"type":"Point"}
}
