{
  "type": "Feature",
  "properties": {
    "iso:country":"GB",
    "wof:name":"SM2 5EZ",
    "wof:placetype":"postalcode"
},
  "geometry": {"coordinates":[-0.18781398624847,51.35835482062392],"type":"Point"}
}