{
  "type": "Feature",
  "properties": {
    "iso:country":"GB",
    "wof:name":"EH21 6UG",
    "wof:placetype":"postalcode"
},
  "geometry": {"coordinates":[-3.07447253653171,55.93847533840731],"type":"Point"}
}