{
  "type": "Feature",
  "properties": {
    "date:inception_lower":"1988-11-01",
    "date:inception_upper":"1988-11-30",
    "iso:country":"GB",
    "wof:name":"EH21 6UG",
    "wof:placetype":"postalcode"
},
  "geometry": {"coordinates":[-3.074472,55.938475],"type":"Point"}
}