{
  "type": "Feature",
  "properties": {
    "iso:country":"GB",
    "wof:name":"DE4 4NP",
    "wof:placetype":"postalcode"
},
  "geometry": {"coordinates":[-1.58936288995647,53.10207322804905],"type":"Point"}
}