{
  "type": "Feature",
  "properties": {
    "iso:country":"GB",
    "wof:name":"LU1 3EF",
    "wof:placetype":"postalcode"
},
  "geometry": {"coordinates":[-0.40961436181504,51.87226264781089],"type":"Point"}
}