{
  "type": "Feature",
  "properties": {
    "iso:country":"GB",
    "wof:name":"GU10 4JH",
    "wof:placetype":"postalcode"
},
  "geometry": {"coordinates":[-0.82844477266148,51.15953787373564],"type":"Point"}
}