{
  "type": "Feature",
  "properties": {
    "iso:country": "GB",
    "wof:name": "CT1 1WZ",
    "wof:placetype": "postalcode"
  },
  "geometry": {"coordinates":[1.105957,51.293852],"type":"Point"}
}
