{
  "type": "Feature",
  "properties": {
    "iso:country":"GB",
    "wof:name":"CT1 1WZ",
    "wof:placetype":"postalcode"
},
  "geometry": {"coordinates":[1.10576519308417,51.29378876875146],"type":"Point"}
}