{
  "type": "Feature",
  "properties": {
    "date:inception_lower": "1997-12-01",
    "date:inception_upper": "1997-12-01",
    "iso:country": "GB",
    "wof:name": "CT1 1WZ",
    "wof:placetype": "postalcode"
  },
  "geometry": {"coordinates":[1.105957,51.293852],"type":"Point"}
}
