{
  "type": "Feature",
  "properties": {
    "iso:country":"GB",
    "wof:name":"YO13 0EQ",
    "wof:placetype":"postalcode"
},
  "geometry": {"coordinates":[-0.45379943606918,54.32521394605361],"type":"Point"}
}