{
  "type": "Feature",
  "properties": {
    "iso:country": "GB",
    "wof:name": "G13 1UY",
    "wof:placetype": "postalcode"
  },
  "geometry": {"coordinates":[-4.352902,55.885088],"type":"Point"}
}
