{
  "type": "Feature",
  "properties": {
    "iso:country":"GB",
    "wof:name":"G13 1UY",
    "wof:placetype":"postalcode"
},
  "geometry": {"coordinates":[-4.35286337178372,55.88526553723814],"type":"Point"}
}