{
  "type": "Feature",
  "properties": {
    "date:inception_lower": "1992-08-01",
    "date:inception_upper": "1992-08-01",
    "iso:country": "GB",
    "wof:name": "PE21 6DB",
    "wof:placetype": "postalcode"
  },
  "geometry": {"coordinates":[-0.01548,52.970341],"type":"Point"}
}
