{
  "type": "Feature",
  "properties": {
    "iso:country": "GB",
    "wof:name": "PE21 6DB",
    "wof:placetype": "postalcode"
  },
  "geometry": {"coordinates":[-0.01548,52.970341],"type":"Point"}
}
