{
  "type": "Feature",
  "properties": {
    "date:inception_lower": "2007-01-01",
    "date:inception_upper": "2007-01-01",
    "iso:country": "GB",
    "wof:name": "B60 3GS",
    "wof:placetype": "postalcode"
  },
  "geometry": {"coordinates":[-2.056466,52.318729],"type":"Point"}
}
