{
  "type": "Feature",
  "properties": {
    "iso:country":"GB",
    "wof:name":"B60 3GS",
    "wof:placetype":"postalcode"
},
  "geometry": {"coordinates":[-2.05646624343559,52.3187295022496],"type":"Point"}
}