{
  "type": "Feature",
  "properties": {
    "iso:country":"GB",
    "wof:name":"LS29 7RN",
    "wof:placetype":"postalcode"
},
  "geometry": {"coordinates":[-1.74968642120107,53.91610448690641],"type":"Point"}
}