{
  "type": "Feature",
  "properties": {
    "date:inception_lower": "1980-01-01",
    "date:inception_upper": "1980-01-01",
    "iso:country": "GB",
    "wof:name": "SY4 4JL",
    "wof:placetype": "postalcode"
  },
  "geometry": {"coordinates":[-2.638701,52.76576],"type":"Point"}
}
