{
  "type": "Feature",
  "properties": {
    "iso:country":"GB",
    "wof:name":"SY4 4JL",
    "wof:placetype":"postalcode"
},
  "geometry": {"coordinates":[-2.63870142846302,52.76576040905336],"type":"Point"}
}