{
  "type": "Feature",
  "properties": {
    "iso:country":"GB",
    "wof:name":"PO21 2SQ",
    "wof:placetype":"postalcode"
},
  "geometry": {"coordinates":[-0.68733204993003,50.78289730338504],"type":"Point"}
}