{
  "type": "Feature",
  "properties": {
    "date:inception_lower": "2019-12-01",
    "date:inception_upper": "2019-12-01",
    "iso:country": "GB",
    "wof:name": "B15 1ER",
    "wof:placetype": "postalcode"
  },
  "geometry": {"coordinates":[-1.915948,52.47334],"type":"Point"}
}
