{
  "type": "Feature",
  "properties": {
    "iso:country": "GB",
    "wof:name": "B15 1ER",
    "wof:placetype": "postalcode"
  },
  "geometry": {"coordinates":[-1.912003,52.47313],"type":"Point"}
}
