{
  "type": "Feature",
  "properties": {
    "iso:country":"GB",
    "wof:name":"TN29 0JB",
    "wof:placetype":"postalcode"
},
  "geometry": {"coordinates":[0.9658810046766,51.04755877479752],"type":"Point"}
}