{
  "type": "Feature",
  "properties": {
    "iso:country": "GB",
    "wof:name": "TN29 0JB",
    "wof:placetype": "postalcode"
  },
  "geometry": {"coordinates":[0.965881,51.047559],"type":"Point"}
}
