{
  "type": "Feature",
  "properties": {
    "date:inception_lower": "1993-01-01",
    "date:inception_upper": "1993-01-01",
    "iso:country": "GB",
    "wof:name": "CO10 0UG",
    "wof:placetype": "postalcode"
  },
  "geometry": {"coordinates":[0.759178,52.071656],"type":"Point"}
}
