{
  "type": "Feature",
  "properties": {
    "iso:country":"GB",
    "wof:name":"CO10 0UG",
    "wof:placetype":"postalcode"
},
  "geometry": {"coordinates":[0.75912959555965,52.07160657174961],"type":"Point"}
}