{
  "type": "Feature",
  "properties": {
    "iso:country":"GB",
    "wof:name":"W1H 4NU",
    "wof:placetype":"postalcode"
},
  "geometry": {"coordinates":[-0.16496845155636,51.51938904802831],"type":"Point"}
}