{
  "type": "Feature",
  "properties": {
    "iso:country":"GB",
    "wof:name":"SW1P 2AP",
    "wof:placetype":"postalcode"
},
  "geometry": {"coordinates":[-0.13053733959157,51.49570756163625],"type":"Point"}
}