{
  "type": "Feature",
  "properties": {
    "date:inception_lower": "1980-01-01",
    "date:inception_upper": "1980-01-01",
    "iso:country": "GB",
    "wof:name": "MK46 4HJ",
    "wof:placetype": "postalcode"
  },
  "geometry": {"coordinates":[-0.677835,52.163304],"type":"Point"}
}
