{
  "type": "Feature",
  "properties": {
    "iso:country":"GB",
    "wof:name":"MK46 4HJ",
    "wof:placetype":"postalcode"
},
  "geometry": {"coordinates":[-0.67783911048829,52.16330204720906],"type":"Point"}
}