{
  "type": "Feature",
  "properties": {
    "iso:country":"GB",
    "wof:name":"N10 3DP",
    "wof:placetype":"postalcode"
},
  "geometry": {"coordinates":[-0.13853465189752,51.58366425307715],"type":"Point"}
}