{
  "type": "Feature",
  "properties": {
    "iso:country":"GB",
    "wof:name":"WA10 4NP",
    "wof:placetype":"postalcode"
},
  "geometry": {"coordinates":[-2.75768314777502,53.45065870905052],"type":"Point"}
}