{
  "type": "Feature",
  "properties": {
    "date:inception_lower": "1996-06-01",
    "date:inception_upper": "1996-06-01",
    "iso:country": "GB",
    "wof:name": "DT7 3LE",
    "wof:placetype": "postalcode"
  },
  "geometry": {"coordinates":[-2.944161,50.719314],"type":"Point"}
}
