{
  "type": "Feature",
  "properties": {
    "iso:country":"GB",
    "wof:name":"SW15 4AN",
    "wof:placetype":"postalcode"
},
  "geometry": {"coordinates":[-0.23597800900176,51.44605699063761],"type":"Point"}
}