{
  "type": "Feature",
  "properties": {
    "date:inception_lower": "1994-05-01",
    "date:inception_upper": "1994-05-01",
    "iso:country": "GB",
    "wof:name": "M34 6JD",
    "wof:placetype": "postalcode"
  },
  "geometry": {"coordinates":[-2.104842,53.45263],"type":"Point"}
}
