{
  "type": "Feature",
  "properties": {
    "iso:country":"GB",
    "wof:name":"TW3 3AN",
    "wof:placetype":"postalcode"
},
  "geometry": {"coordinates":[-0.37198163927841,51.46997484473181],"type":"Point"}
}