{
  "type": "Feature",
  "properties": {
    "iso:country":"GB",
    "wof:name":"BD11 1EB",
    "wof:placetype":"postalcode"
},
  "geometry": {"coordinates":[-1.642450731357,53.75105716103005],"type":"Point"}
}