{
  "type": "Feature",
  "properties": {
    "iso:country": "GB",
    "wof:name": "L3 4AQ",
    "wof:placetype": "postalcode"
  },
  "geometry": {"coordinates":[-2.993259,53.401219],"type":"Point"}
}
