{
  "type": "Feature",
  "properties": {
    "date:inception_lower": "1980-01-01",
    "date:inception_upper": "1980-01-01",
    "iso:country": "GB",
    "wof:name": "CM8 3LQ",
    "wof:placetype": "postalcode"
  },
  "geometry": {"coordinates":[0.662664,51.78584],"type":"Point"}
}
