{
  "type": "Feature",
  "properties": {
    "iso:country":"GB",
    "wof:name":"CM8 3LQ",
    "wof:placetype":"postalcode"
},
  "geometry": {"coordinates":[0.66266382581831,51.78583976545963],"type":"Point"}
}