{
  "type": "Feature",
  "properties": {
    "iso:country": "GB",
    "wof:name": "BD18 2AL",
    "wof:placetype": "postalcode"
  },
  "geometry": {"coordinates":[-1.774039,53.82409],"type":"Point"}
}
