{
  "type": "Feature",
  "properties": {
    "iso:country":"GB",
    "wof:name":"RG2 0WW",
    "wof:placetype":"postalcode"
},
  "geometry": {"coordinates":[-0.97498763870695,51.43238470041673],"type":"Point"}
}