{
  "type": "Feature",
  "properties": {
    "iso:country": "GB",
    "wof:name": "CB22 5BX",
    "wof:placetype": "postalcode"
  },
  "geometry": {"coordinates":[0.158224,52.146762],"type":"Point"}
}
