{
  "type": "Feature",
  "properties": {
    "iso:country":"GB",
    "wof:name":"LS25 5PD",
    "wof:placetype":"postalcode"
},
  "geometry": {"coordinates":[-1.2676632461169,53.77710975658928],"type":"Point"}
}