{
  "type": "Feature",
  "properties": {
    "iso:country": "GB",
    "wof:name": "LS25 5PD",
    "wof:placetype": "postalcode"
  },
  "geometry": {"coordinates":[-1.267663,53.77711],"type":"Point"}
}
