{
  "type": "Feature",
  "properties": {
    "date:inception_lower":"1998-06-01",
    "date:inception_upper":"1998-06-30",
    "iso:country":"GB",
    "wof:name":"LS25 5PD",
    "wof:placetype":"postalcode"
},
  "geometry": {"coordinates":[-1.267663,53.77711],"type":"Point"}
}