{
  "type": "Feature",
  "properties": {
    "iso:country":"GB",
    "wof:name":"FY3 8FB",
    "wof:placetype":"postalcode"
},
  "geometry": {"coordinates":[-3.0079094883921,53.82446117495454],"type":"Point"}
}