{
  "type": "Feature",
  "properties": {
    "date:inception_lower":"1980-01-01",
    "date:inception_upper":"1980-01-31",
    "iso:country":"GB",
    "wof:name":"LL12 0EU",
    "wof:placetype":"postalcode"
},
  "geometry": {"coordinates":[-2.932038,53.104577],"type":"Point"}
}