{
  "type": "Feature",
  "properties": {
    "date:inception_lower": "1980-01-01",
    "date:inception_upper": "1980-01-01",
    "iso:country": "GB",
    "wof:name": "BA10 0NZ",
    "wof:placetype": "postalcode"
  },
  "geometry": {"coordinates":[-2.465605,51.096368],"type":"Point"}
}
