{
  "type": "Feature",
  "properties": {
    "iso:country": "GB",
    "wof:name": "BA10 0NZ",
    "wof:placetype": "postalcode"
  },
  "geometry": {"coordinates":[-2.465605,51.096368],"type":"Point"}
}
