{
  "type": "Feature",
  "properties": {
    "iso:country":"GB",
    "wof:name":"BA10 0NZ",
    "wof:placetype":"postalcode"
},
  "geometry": {"coordinates":[-2.46560496354301,51.09636814340771],"type":"Point"}
}