{
  "type": "Feature",
  "properties": {
    "iso:country":"GB",
    "wof:name":"NG19 6HT",
    "wof:placetype":"postalcode"
},
  "geometry": {"coordinates":[-1.22267316698923,53.14429143238114],"type":"Point"}
}