{
  "type": "Feature",
  "properties": {
    "iso:country":"GB",
    "wof:name":"DH3 1DX",
    "wof:placetype":"postalcode"
},
  "geometry": {"coordinates":[-1.58047614098477,54.89664886075687],"type":"Point"}
}