{
  "type": "Feature",
  "properties": {
    "date:inception_lower":"1980-01-01",
    "date:inception_upper":"1980-01-31",
    "iso:country":"GB",
    "wof:name":"DH3 1DX",
    "wof:placetype":"postalcode"
},
  "geometry": {"coordinates":[-1.580476,54.896649],"type":"Point"}
}