{
  "type": "Feature",
  "properties": {
    "iso:country":"GB",
    "wof:name":"BS20 8HU",
    "wof:placetype":"postalcode"
},
  "geometry": {"coordinates":[-2.79978259351681,51.47670940825346],"type":"Point"}
}