{
  "type": "Feature",
  "properties": {
    "iso:country":"GB",
    "wof:name":"EX39 5HF",
    "wof:placetype":"postalcode"
},
  "geometry": {"coordinates":[-4.1996740378957,50.99502235716177],"type":"Point"}
}