{
  "type": "Feature",
  "properties": {
    "iso:country":"GB",
    "wof:name":"BS23 4SX",
    "wof:placetype":"postalcode"
},
  "geometry": {"coordinates":[-2.97653577502823,51.32096125709553],"type":"Point"}
}