{
  "type": "Feature",
  "properties": {
    "iso:country":"GB",
    "wof:name":"B16 9JA",
    "wof:placetype":"postalcode"
},
  "geometry": {"coordinates":[-1.94106889002972,52.47317826251],"type":"Point"}
}