{
  "type": "Feature",
  "properties": {
    "iso:country":"GB",
    "wof:name":"DA14 4JU",
    "wof:placetype":"postalcode"
},
  "geometry": {"coordinates":[0.11342466908422,51.43210343821418],"type":"Point"}
}