{
  "type": "Feature",
  "properties": {
    "iso:country":"GB",
    "wof:name":"HD1 3BS",
    "wof:placetype":"postalcode"
},
  "geometry": {"coordinates":[-1.77352412844052,53.64314113876644],"type":"Point"}
}