{
  "type": "Feature",
  "properties": {
    "date:inception_lower": "1980-01-01",
    "date:inception_upper": "1980-01-01",
    "iso:country": "GB",
    "wof:name": "HD1 3BS",
    "wof:placetype": "postalcode"
  },
  "geometry": {"coordinates":[-1.773524,53.643141],"type":"Point"}
}
