{
  "type": "Feature",
  "properties": {
    "date:inception_lower": "2019-11-01",
    "date:inception_upper": "2019-11-01",
    "iso:country": "GB",
    "wof:name": "CV34 8AB",
    "wof:placetype": "postalcode"
  },
  "geometry": {"coordinates":[-1.553926,52.27826],"type":"Point"}
}
