{
  "type": "Feature",
  "properties": {
    "iso:country":"GB",
    "wof:name":"E17 5RE",
    "wof:placetype":"postalcode"
},
  "geometry": {"coordinates":[-0.03263376736668,51.59725992474682],"type":"Point"}
}