{
  "type": "Feature",
  "properties": {
    "iso:country": "GB",
    "wof:name": "E17 5RE",
    "wof:placetype": "postalcode"
  },
  "geometry": {"coordinates":[-0.032634,51.59726],"type":"Point"}
}
