{
  "type": "Feature",
  "properties": {
    "iso:country": "GB",
    "wof:name": "ME14 4FG",
    "wof:placetype": "postalcode"
  },
  "geometry": {"coordinates":[0.565833,51.272129],"type":"Point"}
}
