{
  "type": "Feature",
  "properties": {
    "date:inception_lower": "2013-03-01",
    "date:inception_upper": "2013-03-01",
    "iso:country": "GB",
    "wof:name": "ME14 4FG",
    "wof:placetype": "postalcode"
  },
  "geometry": {"coordinates":[0.565833,51.272129],"type":"Point"}
}
