{
  "type": "Feature",
  "properties": {
    "iso:country":"GB",
    "wof:name":"ME14 4FG",
    "wof:placetype":"postalcode"
},
  "geometry": {"coordinates":[0.56562228114462,51.27197237909135],"type":"Point"}
}