{
  "type": "Feature",
  "properties": {
    "iso:country":"GB",
    "wof:name":"RH14 9ES",
    "wof:placetype":"postalcode"
},
  "geometry": {"coordinates":[-0.4570597047209,51.01778322291808],"type":"Point"}
}