{
  "type": "Feature",
  "properties": {
    "iso:country":"GB",
    "wof:name":"NG34 0AB",
    "wof:placetype":"postalcode"
},
  "geometry": {"coordinates":[-0.37430339919015,52.95180419790059],"type":"Point"}
}