{
  "type": "Feature",
  "properties": {
    "iso:country": "GB",
    "wof:name": "OX9 2EE",
    "wof:placetype": "postalcode"
  },
  "geometry": {"coordinates":[-0.981104,51.747874],"type":"Point"}
}
