{
  "type": "Feature",
  "properties": {
    "iso:country":"GB",
    "wof:name":"MK41 0NW",
    "wof:placetype":"postalcode"
},
  "geometry": {"coordinates":[-0.42233032656344,52.15340013746009],"type":"Point"}
}