{
  "type": "Feature",
  "properties": {
    "iso:country": "GB",
    "wof:name": "MK41 0NW",
    "wof:placetype": "postalcode"
  },
  "geometry": {"coordinates":[-0.42233,52.1534],"type":"Point"}
}
