{
  "type": "Feature",
  "properties": {
    "iso:country":"GB",
    "wof:name":"BS39 6AA",
    "wof:placetype":"postalcode"
},
  "geometry": {"coordinates":[-2.51088168827405,51.32335258235854],"type":"Point"}
}