{
  "type": "Feature",
  "properties": {
    "date:inception_lower": "2016-01-01",
    "date:inception_upper": "2016-01-01",
    "iso:country": "GB",
    "wof:name": "BS39 6AA",
    "wof:placetype": "postalcode"
  },
  "geometry": {"coordinates":[-2.510882,51.323353],"type":"Point"}
}
