{
  "type": "Feature",
  "properties": {
    "iso:country": "GB",
    "wof:name": "HP7 9AN",
    "wof:placetype": "postalcode"
  },
  "geometry": {"coordinates":[-0.606273,51.673487],"type":"Point"}
}
