{
  "type": "Feature",
  "properties": {
    "date:inception_lower":"1986-07-01",
    "date:inception_upper":"1986-07-31",
    "iso:country":"GB",
    "wof:name":"HP7 9AN",
    "wof:placetype":"postalcode"
},
  "geometry": {"coordinates":[-0.606273,51.673487],"type":"Point"}
}