{
  "type": "Feature",
  "properties": {
    "iso:country":"GB",
    "wof:name":"BR3 3JY",
    "wof:placetype":"postalcode"
},
  "geometry": {"coordinates":[-0.02646255130247,51.39394006290337],"type":"Point"}
}