{
  "type": "Feature",
  "properties": {
    "date:inception_lower":"1980-01-01",
    "date:inception_upper":"1980-01-31",
    "iso:country":"GB",
    "wof:name":"CF40 2DP",
    "wof:placetype":"postalcode"
},
  "geometry": {"coordinates":[-3.484075,51.626946],"type":"Point"}
}