{
  "type": "Feature",
  "properties": {
    "iso:country":"GB",
    "wof:name":"DL2 2UN",
    "wof:placetype":"postalcode"
},
  "geometry": {"coordinates":[-1.70381507940367,54.60847127419827],"type":"Point"}
}