{
  "type": "Feature",
  "properties": {
    "iso:country": "GB",
    "wof:name": "DL2 2UN",
    "wof:placetype": "postalcode"
  },
  "geometry": {"coordinates":[-1.703824,54.608481],"type":"Point"}
}
