{
  "type": "Feature",
  "properties": {
    "iso:country":"GB",
    "wof:name":"ML5 4LG",
    "wof:placetype":"postalcode"
},
  "geometry": {"coordinates":[-4.02260654472004,55.84456636553205],"type":"Point"}
}