{
  "type": "Feature",
  "properties": {
    "iso:country": "GB",
    "wof:name": "ML5 4LG",
    "wof:placetype": "postalcode"
  },
  "geometry": {"coordinates":[-4.022606,55.844566],"type":"Point"}
}
