{
  "type": "Feature",
  "properties": {
    "iso:country":"GB",
    "wof:name":"DH2 2AU",
    "wof:placetype":"postalcode"
},
  "geometry": {"coordinates":[-1.58134169307284,54.85676113243266],"type":"Point"}
}