{
  "type": "Feature",
  "properties": {
    "iso:country":"GB",
    "wof:name":"M23 2QP",
    "wof:placetype":"postalcode"
},
  "geometry": {"coordinates":[-2.28140091792027,53.38873233404806],"type":"Point"}
}