{
  "type": "Feature",
  "properties": {
    "iso:country":"GB",
    "wof:name":"WA1 3BW",
    "wof:placetype":"postalcode"
},
  "geometry": {"coordinates":[-2.56514047314703,53.39758643360269],"type":"Point"}
}