{
  "type": "Feature",
  "properties": {
    "date:inception_lower": "1980-01-01",
    "date:inception_upper": "1980-01-01",
    "iso:country": "GB",
    "wof:name": "WA1 3BW",
    "wof:placetype": "postalcode"
  },
  "geometry": {"coordinates":[-2.56514,53.397586],"type":"Point"}
}
