{
  "type": "Feature",
  "properties": {
    "iso:country": "GB",
    "wof:name": "YO8 3GB",
    "wof:placetype": "postalcode"
  },
  "geometry": {"coordinates":[-1.070408,53.787356],"type":"Point"}
}
