{
  "type": "Feature",
  "properties": {
    "date:inception_lower":"1998-06-01",
    "date:inception_upper":"1998-06-30",
    "iso:country":"GB",
    "wof:name":"YO8 3GB",
    "wof:placetype":"postalcode"
},
  "geometry": {"coordinates":[-1.070408,53.787356],"type":"Point"}
}