{
  "type": "Feature",
  "properties": {
    "date:inception_lower": "2001-12-01",
    "date:inception_upper": "2001-12-01",
    "iso:country": "GB",
    "wof:name": "CV34 6SN",
    "wof:placetype": "postalcode"
  },
  "geometry": {"coordinates":[-1.546666,52.272919],"type":"Point"}
}
