{
  "type": "Feature",
  "properties": {
    "iso:country": "GB",
    "wof:name": "NG23 5FE",
    "wof:placetype": "postalcode"
  },
  "geometry": {"coordinates":[-0.752423,52.989277],"type":"Point"}
}
