{
  "type": "Feature",
  "properties": {
    "iso:country":"GB",
    "wof:name":"NG23 5FE",
    "wof:placetype":"postalcode"
},
  "geometry": {"coordinates":[-0.75242289285765,52.98927703460495],"type":"Point"}
}