{
  "type": "Feature",
  "properties": {
    "iso:country":"GB",
    "wof:name":"CT13 0BG",
    "wof:placetype":"postalcode"
},
  "geometry": {"coordinates":[1.33193457514291,51.27018736987837],"type":"Point"}
}