{
  "type": "Feature",
  "properties": {
    "date:inception_lower": "1995-01-01",
    "date:inception_upper": "1995-01-01",
    "iso:country": "GB",
    "wof:name": "TA1 3RZ",
    "wof:placetype": "postalcode"
  },
  "geometry": {"coordinates":[-3.099221,51.011311],"type":"Point"}
}
