{
  "type": "Feature",
  "properties": {
    "iso:country": "GB",
    "wof:name": "OL3 6EE",
    "wof:placetype": "postalcode"
  },
  "geometry": {"coordinates":[-1.998661,53.552563],"type":"Point"}
}
