{
  "type": "Feature",
  "properties": {
    "date:inception_lower": "1980-01-01",
    "date:inception_upper": "1980-01-01",
    "iso:country": "GB",
    "wof:name": "OL3 6EE",
    "wof:placetype": "postalcode"
  },
  "geometry": {"coordinates":[-1.998209,53.552275],"type":"Point"}
}
