{
  "type": "Feature",
  "properties": {
    "date:inception_lower": "1980-01-01",
    "date:inception_upper": "1980-01-01",
    "iso:country": "GB",
    "wof:name": "G31 5BW",
    "wof:placetype": "postalcode"
  },
  "geometry": {"coordinates":[-4.193102,55.851535],"type":"Point"}
}
