{
  "type": "Feature",
  "properties": {
    "iso:country":"GB",
    "wof:name":"B63 1DZ",
    "wof:placetype":"postalcode"
},
  "geometry": {"coordinates":[-2.07890175151861,52.43613651655639],"type":"Point"}
}