{
  "type": "Feature",
  "properties": {
    "iso:country": "GB",
    "wof:name": "B63 1DZ",
    "wof:placetype": "postalcode"
  },
  "geometry": {"coordinates":[-2.078881,52.436151],"type":"Point"}
}
