{
  "type": "Feature",
  "properties": {
    "date:inception_lower":"1980-01-01",
    "date:inception_upper":"1980-01-31",
    "iso:country":"GB",
    "wof:name":"B63 1DZ",
    "wof:placetype":"postalcode"
},
  "geometry": {"coordinates":[-2.078881,52.436151],"type":"Point"}
}