{
  "type": "Feature",
  "properties": {
    "iso:country":"GB",
    "wof:name":"HA9 8QY",
    "wof:placetype":"postalcode"
},
  "geometry": {"coordinates":[-0.30681745599243,51.57098886962033],"type":"Point"}
}