{
  "type": "Feature",
  "properties": {
    "iso:country":"GB",
    "wof:name":"TF4 2GW",
    "wof:placetype":"postalcode"
},
  "geometry": {"coordinates":[-2.47326392410935,52.67724168261175],"type":"Point"}
}