{
  "type": "Feature",
  "properties": {
    "iso:country": "GB",
    "wof:name": "TF4 2GW",
    "wof:placetype": "postalcode"
  },
  "geometry": {"coordinates":[-2.473264,52.677242],"type":"Point"}
}
