{
  "type": "Feature",
  "properties": {
    "date:inception_lower":"2000-06-01",
    "date:inception_upper":"2000-06-30",
    "iso:country":"GB",
    "wof:name":"TF4 2GW",
    "wof:placetype":"postalcode"
},
  "geometry": {"coordinates":[-2.473264,52.677242],"type":"Point"}
}