{
  "type": "Feature",
  "properties": {
    "iso:country":"GB",
    "wof:name":"B37 6EU",
    "wof:placetype":"postalcode"
},
  "geometry": {"coordinates":[-1.75250250062957,52.4931888953168],"type":"Point"}
}