{
  "type": "Feature",
  "properties": {
    "iso:country":"GB",
    "wof:name":"TS7 0DT",
    "wof:placetype":"postalcode"
},
  "geometry": {"coordinates":[-1.16881910816239,54.53149650684649],"type":"Point"}
}