{
  "type": "Feature",
  "properties": {
    "date:inception_lower": "2016-07-01",
    "date:inception_upper": "2016-07-01",
    "iso:country": "GB",
    "wof:name": "NN13 5BF",
    "wof:placetype": "postalcode"
  },
  "geometry": {"coordinates":[-1.099632,52.015691],"type":"Point"}
}
