{
  "type": "Feature",
  "properties": {
    "iso:country": "GB",
    "wof:name": "RG8 0PL",
    "wof:placetype": "postalcode"
  },
  "geometry": {"coordinates":[-1.076043,51.535119],"type":"Point"}
}
