{
  "type": "Feature",
  "properties": {
    "iso:country":"GB",
    "wof:name":"KT3 5PJ",
    "wof:placetype":"postalcode"
},
  "geometry": {"coordinates":[-0.25898142408437,51.38568344016236],"type":"Point"}
}