{
  "type": "Feature",
  "properties": {
    "iso:country":"GB",
    "wof:name":"WN3 6RF",
    "wof:placetype":"postalcode"
},
  "geometry": {"coordinates":[-2.65767832923679,53.52533529510817],"type":"Point"}
}