{
  "type": "Feature",
  "properties": {
    "iso:country": "GB",
    "wof:name": "LA22 9EL",
    "wof:placetype": "postalcode"
  },
  "geometry": {"coordinates":[-2.958402,54.433631],"type":"Point"}
}
