{
  "type": "Feature",
  "properties": {
    "iso:country":"GB",
    "wof:name":"LA22 9EL",
    "wof:placetype":"postalcode"
},
  "geometry": {"coordinates":[-2.95833770519279,54.43364156796911],"type":"Point"}
}