{
  "type": "Feature",
  "properties": {
    "iso:country":"GB",
    "wof:name":"BA5 1QH",
    "wof:placetype":"postalcode"
},
  "geometry": {"coordinates":[-2.66159318573208,51.2014851996552],"type":"Point"}
}