{
  "type": "Feature",
  "properties": {
    "iso:country": "GB",
    "wof:name": "BA5 1QH",
    "wof:placetype": "postalcode"
  },
  "geometry": {"coordinates":[-2.661593,51.201485],"type":"Point"}
}
