{
  "type": "Feature",
  "properties": {
    "iso:country":"GB",
    "wof:name":"RH8 9LT",
    "wof:placetype":"postalcode"
},
  "geometry": {"coordinates":[-0.01635511726118,51.25394759744412],"type":"Point"}
}