{
  "type": "Feature",
  "properties": {
    "iso:country":"GB",
    "wof:name":"BS23 3YU",
    "wof:placetype":"postalcode"
},
  "geometry": {"coordinates":[-2.95618256013259,51.33662245607582],"type":"Point"}
}