{
  "type": "Feature",
  "properties": {
    "date:inception_lower":"1980-01-01",
    "date:inception_upper":"1980-01-31",
    "iso:country":"GB",
    "wof:name":"BS23 3YU",
    "wof:placetype":"postalcode"
},
  "geometry": {"coordinates":[-2.956183,51.336622],"type":"Point"}
}