{
  "type": "Feature",
  "properties": {
    "iso:country":"GB",
    "wof:name":"SY10 9LT",
    "wof:placetype":"postalcode"
},
  "geometry": {"coordinates":[-3.20820372027294,52.81060024281314],"type":"Point"}
}