{
  "type": "Feature",
  "properties": {
    "date:inception_lower":"1980-01-01",
    "date:inception_upper":"1980-01-31",
    "iso:country":"GB",
    "wof:name":"SY10 9LT",
    "wof:placetype":"postalcode"
},
  "geometry": {"coordinates":[-3.208204,52.8106],"type":"Point"}
}