{
  "type": "Feature",
  "properties": {
    "iso:country": "GB",
    "wof:name": "SY10 9LT",
    "wof:placetype": "postalcode"
  },
  "geometry": {"coordinates":[-3.208204,52.8106],"type":"Point"}
}
