{
  "type": "Feature",
  "properties": {
    "iso:country":"GB",
    "wof:name":"PR25 1DA",
    "wof:placetype":"postalcode"
},
  "geometry": {"coordinates":[-2.71975034795892,53.68791132996071],"type":"Point"}
}