{
  "type": "Feature",
  "properties": {
    "iso:country": "GB",
    "wof:name": "PR25 1DA",
    "wof:placetype": "postalcode"
  },
  "geometry": {"coordinates":[-2.71975,53.687911],"type":"Point"}
}
