{
  "type": "Feature",
  "properties": {
    "iso:country":"GB",
    "wof:name":"BR5 3JT",
    "wof:placetype":"postalcode"
},
  "geometry": {"coordinates":[0.11969495537377,51.40096450390483],"type":"Point"}
}