{
  "type": "Feature",
  "properties": {
    "iso:country": "GB",
    "wof:name": "DE23 3SR",
    "wof:placetype": "postalcode"
  },
  "geometry": {"coordinates":[-1.522228,52.899358],"type":"Point"}
}
