{
  "type": "Feature",
  "properties": {
    "date:inception_lower":"2002-06-01",
    "date:inception_upper":"2002-06-30",
    "iso:country":"GB",
    "wof:name":"DE23 3SR",
    "wof:placetype":"postalcode"
},
  "geometry": {"coordinates":[-1.522228,52.899358],"type":"Point"}
}