{
  "type": "Feature",
  "properties": {
    "iso:country": "GB",
    "wof:name": "S43 4BT",
    "wof:placetype": "postalcode"
  },
  "geometry": {"coordinates":[-1.256797,53.270275],"type":"Point"}
}
