{
  "type": "Feature",
  "properties": {
    "iso:country":"GB",
    "wof:name":"NE66 3RY",
    "wof:placetype":"postalcode"
},
  "geometry": {"coordinates":[-1.64918350663852,55.46644050021878],"type":"Point"}
}