{
  "type": "Feature",
  "properties": {
    "date:inception_lower":"2004-10-01",
    "date:inception_upper":"2004-10-31",
    "iso:country":"GB",
    "wof:name":"M4 5AJ",
    "wof:placetype":"postalcode"
},
  "geometry": {"coordinates":[-2.231324,53.484208],"type":"Point"}
}