{
  "type": "Feature",
  "properties": {
    "iso:country": "GB",
    "wof:name": "M4 5AJ",
    "wof:placetype": "postalcode"
  },
  "geometry": {"coordinates":[-2.231324,53.484208],"type":"Point"}
}
