{
  "type": "Feature",
  "properties": {
    "date:inception_lower":"1996-06-01",
    "date:inception_upper":"1996-06-30",
    "iso:country":"GB",
    "wof:name":"ML6 8HJ",
    "wof:placetype":"postalcode"
},
  "geometry": {"coordinates":[-3.943029,55.863122],"type":"Point"}
}