{
  "type": "Feature",
  "properties": {
    "iso:country":"GB",
    "wof:name":"ML6 8HJ",
    "wof:placetype":"postalcode"
},
  "geometry": {"coordinates":[-3.9430290603089,55.86312185679962],"type":"Point"}
}