{
  "type": "Feature",
  "properties": {
    "iso:country":"GB",
    "wof:name":"NE24 3AZ",
    "wof:placetype":"postalcode"
},
  "geometry": {"coordinates":[-1.50154537209803,55.12264278987635],"type":"Point"}
}