{
  "type": "Feature",
  "properties": {
    "date:inception_lower": "1980-01-01",
    "date:inception_upper": "1980-01-01",
    "iso:country": "GB",
    "wof:name": "NE24 3AZ",
    "wof:placetype": "postalcode"
  },
  "geometry": {"coordinates":[-1.501545,55.122643],"type":"Point"}
}
