{
  "type": "Feature",
  "properties": {
    "iso:country": "GB",
    "wof:name": "AB22 8LT",
    "wof:placetype": "postalcode"
  },
  "geometry": {"coordinates":[-2.108538,57.178827],"type":"Point"}
}
