{
  "type": "Feature",
  "properties": {
    "iso:country":"GB",
    "wof:name":"N15 6JA",
    "wof:placetype":"postalcode"
},
  "geometry": {"coordinates":[-0.08071011463572,51.57750816541063],"type":"Point"}
}