{
  "type": "Feature",
  "properties": {
    "iso:country":"GB",
    "wof:name":"CV34 6DE",
    "wof:placetype":"postalcode"
},
  "geometry": {"coordinates":[-1.61016268089325,52.2614888642265],"type":"Point"}
}