{
  "type": "Feature",
  "properties": {
    "iso:country":"GB",
    "wof:name":"MK3 6PY",
    "wof:placetype":"postalcode"
},
  "geometry": {"coordinates":[-0.7448952336088,52.00954964381371],"type":"Point"}
}