{
  "type": "Feature",
  "properties": {
    "iso:country": "GB",
    "wof:name": "MK3 6PY",
    "wof:placetype": "postalcode"
  },
  "geometry": {"coordinates":[-0.744895,52.00955],"type":"Point"}
}
