{
  "type": "Feature",
  "properties": {
    "iso:country": "GB",
    "wof:name": "OL4 4JS",
    "wof:placetype": "postalcode"
  },
  "geometry": {"coordinates":[-2.049965,53.537364],"type":"Point"}
}
