{
  "type": "Feature",
  "properties": {
    "date:inception_lower": "1980-01-01",
    "date:inception_upper": "1980-01-01",
    "iso:country": "GB",
    "wof:name": "OL4 4JS",
    "wof:placetype": "postalcode"
  },
  "geometry": {"coordinates":[-2.049965,53.537364],"type":"Point"}
}
