{
  "type": "Feature",
  "properties": {
    "iso:country":"GB",
    "wof:name":"OL4 4JS",
    "wof:placetype":"postalcode"
},
  "geometry": {"coordinates":[-2.04996456442699,53.53736361591272],"type":"Point"}
}