{
  "type": "Feature",
  "properties": {
    "iso:country": "GB",
    "wof:name": "WD19 7PE",
    "wof:placetype": "postalcode"
  },
  "geometry": {"coordinates":[-0.405959,51.628083],"type":"Point"}
}
