{
  "type": "Feature",
  "properties": {
    "iso:country":"GB",
    "wof:name":"SN15 4HJ",
    "wof:placetype":"postalcode"
},
  "geometry": {"coordinates":[-2.01247838667494,51.52865689760482],"type":"Point"}
}