{
  "type": "Feature",
  "properties": {
    "iso:country": "GB",
    "wof:name": "LS12 1HW",
    "wof:placetype": "postalcode"
  },
  "geometry": {"coordinates":[-1.579119,53.790822],"type":"Point"}
}
