{
  "type": "Feature",
  "properties": {
    "iso:country":"GB",
    "wof:name":"LS12 1HW",
    "wof:placetype":"postalcode"
},
  "geometry": {"coordinates":[-1.57911885131051,53.79082160436048],"type":"Point"}
}