{
  "type": "Feature",
  "properties": {
    "iso:country":"GB",
    "wof:name":"M27 0NA",
    "wof:placetype":"postalcode"
},
  "geometry": {"coordinates":[-2.34170983685617,53.51060309194926],"type":"Point"}
}