{
  "type": "Feature",
  "properties": {
    "iso:country":"GB",
    "wof:name":"SE14 5SE",
    "wof:placetype":"postalcode"
},
  "geometry": {"coordinates":[-0.04412060813615,51.46992796878337],"type":"Point"}
}