{
  "type": "Feature",
  "properties": {
    "date:inception_lower": "2021-06-01",
    "date:inception_upper": "2021-06-01",
    "iso:country": "GB",
    "wof:name": "SS8 0DD",
    "wof:placetype": "postalcode"
  },
  "geometry": {"coordinates":[0.557789,51.519004],"type":"Point"}
}
