{
  "type": "Feature",
  "properties": {
    "iso:country":"GB",
    "wof:name":"RH1 5JW",
    "wof:placetype":"postalcode"
},
  "geometry": {"coordinates":[-0.15769986764762,51.20338862345791],"type":"Point"}
}