{
  "type": "Feature",
  "properties": {
    "iso:country":"GB",
    "wof:name":"WV6 8NA",
    "wof:placetype":"postalcode"
},
  "geometry": {"coordinates":[-2.17658071354432,52.59596136257177],"type":"Point"}
}