{
  "type": "Feature",
  "properties": {
    "date:inception_lower": "1980-01-01",
    "date:inception_upper": "1980-01-01",
    "iso:country": "GB",
    "wof:name": "WV6 8NA",
    "wof:placetype": "postalcode"
  },
  "geometry": {"coordinates":[-2.176581,52.595961],"type":"Point"}
}
