{
  "type": "Feature",
  "properties": {
    "date:inception_lower": "1980-01-01",
    "date:inception_upper": "1980-01-01",
    "iso:country": "GB",
    "wof:name": "LS18 5DA",
    "wof:placetype": "postalcode"
  },
  "geometry": {"coordinates":[-1.621367,53.83761],"type":"Point"}
}
