{
  "type": "Feature",
  "properties": {
    "iso:country": "GB",
    "wof:name": "SO21 1US",
    "wof:placetype": "postalcode"
  },
  "geometry": {"coordinates":[-1.311962,50.994173],"type":"Point"}
}
