{
  "type": "Feature",
  "properties": {
    "iso:country":"GB",
    "wof:name":"CF24 3QS",
    "wof:placetype":"postalcode"
},
  "geometry": {"coordinates":[-3.16358235010368,51.48808605225982],"type":"Point"}
}