{
  "type": "Feature",
  "properties": {
    "iso:country":"GB",
    "wof:name":"B31 3UB",
    "wof:placetype":"postalcode"
},
  "geometry": {"coordinates":[-1.9633226668873,52.40861190462563],"type":"Point"}
}