{
  "type": "Feature",
  "properties": {
    "iso:country":"GB",
    "wof:name":"WR14 4QZ",
    "wof:placetype":"postalcode"
},
  "geometry": {"coordinates":[-2.33003227013099,52.11213150780768],"type":"Point"}
}