{
  "type": "Feature",
  "properties": {
    "iso:country": "GB",
    "wof:name": "GL7 1FY",
    "wof:placetype": "postalcode"
  },
  "geometry": {"coordinates":[-1.967087,51.706743],"type":"Point"}
}
