{
  "type": "Feature",
  "properties": {
    "iso:country":"GB",
    "wof:name":"GL7 1FY",
    "wof:placetype":"postalcode"
},
  "geometry": {"coordinates":[-1.9670871397375,51.70674338115984],"type":"Point"}
}