{
  "type": "Feature",
  "properties": {
    "iso:country":"GB",
    "wof:name":"NR30 3BJ",
    "wof:placetype":"postalcode"
},
  "geometry": {"coordinates":[1.73332416270758,52.60170112033035],"type":"Point"}
}