{
  "type": "Feature",
  "properties": {
    "iso:country": "GB",
    "wof:name": "SN5 4ER",
    "wof:placetype": "postalcode"
  },
  "geometry": {"coordinates":[-1.869087,51.591661],"type":"Point"}
}
