{
  "type": "Feature",
  "properties": {
    "iso:country": "GB",
    "wof:name": "CO10 2TD",
    "wof:placetype": "postalcode"
  },
  "geometry": {"coordinates":[0.730385,52.036286],"type":"Point"}
}
