{
  "type": "Feature",
  "properties": {
    "date:inception_lower": "1985-10-01",
    "date:inception_upper": "1985-10-01",
    "iso:country": "GB",
    "wof:name": "HU12 0NZ",
    "wof:placetype": "postalcode"
  },
  "geometry": {"coordinates":[-0.01644,53.685204],"type":"Point"}
}
