{
  "type": "Feature",
  "properties": {
    "date:inception_lower": "1980-01-01",
    "date:inception_upper": "1980-01-01",
    "iso:country": "GB",
    "wof:name": "LL53 7LN",
    "wof:placetype": "postalcode"
  },
  "geometry": {"coordinates":[-4.531294,52.830379],"type":"Point"}
}
