{
  "type": "Feature",
  "properties": {
    "iso:country":"GB",
    "wof:name":"EN1 2HQ",
    "wof:placetype":"postalcode"
},
  "geometry": {"coordinates":[-0.07953390904502,51.63859260370541],"type":"Point"}
}