{
  "type": "Feature",
  "properties": {
    "date:inception_lower": "1980-01-01",
    "date:inception_upper": "1980-01-01",
    "iso:country": "GB",
    "wof:name": "ME7 5AL",
    "wof:placetype": "postalcode"
  },
  "geometry": {"coordinates":[0.53006,51.390258],"type":"Point"}
}
