{
  "type": "Feature",
  "properties": {
    "iso:country":"GB",
    "wof:name":"SK11 8NW",
    "wof:placetype":"postalcode"
},
  "geometry": {"coordinates":[-2.14551809801242,53.25094528970196],"type":"Point"}
}