{
  "type": "Feature",
  "properties": {
    "date:inception_lower":"1980-01-01",
    "date:inception_upper":"1980-01-31",
    "iso:country":"GB",
    "wof:name":"PA4 9PX",
    "wof:placetype":"postalcode"
},
  "geometry": {"coordinates":[-4.430736,55.891068],"type":"Point"}
}