{
  "type": "Feature",
  "properties": {
    "iso:country": "GB",
    "wof:name": "PA4 9PX",
    "wof:placetype": "postalcode"
  },
  "geometry": {"coordinates":[-4.430736,55.891068],"type":"Point"}
}
