{
  "type": "Feature",
  "properties": {
    "iso:country":"GB",
    "wof:name":"PA4 9PX",
    "wof:placetype":"postalcode"
},
  "geometry": {"coordinates":[-4.43073594573429,55.89106791979436],"type":"Point"}
}