{
  "type": "Feature",
  "properties": {
    "iso:country":"GB",
    "wof:name":"PR1 6SS",
    "wof:placetype":"postalcode"
},
  "geometry": {"coordinates":[-2.68776514615842,53.76841836258117],"type":"Point"}
}