{
  "type": "Feature",
  "properties": {
    "iso:country":"GB",
    "wof:name":"RM7 0JB",
    "wof:placetype":"postalcode"
},
  "geometry": {"coordinates":[0.16390884966048,51.56927715525957],"type":"Point"}
}