{
  "type": "Feature",
  "properties": {
    "iso:country":"GB",
    "wof:name":"PH3 1FE",
    "wof:placetype":"postalcode"
},
  "geometry": {"coordinates":[-3.70016558186771,56.2975805611471],"type":"Point"}
}