{
  "type": "Feature",
  "properties": {
    "date:inception_lower": "2007-01-01",
    "date:inception_upper": "2007-01-01",
    "iso:country": "GB",
    "wof:name": "PH3 1FE",
    "wof:placetype": "postalcode"
  },
  "geometry": {"coordinates":[-3.700166,56.297581],"type":"Point"}
}
