{
  "type": "Feature",
  "properties": {
    "iso:country": "GB",
    "wof:name": "LL32 8ND",
    "wof:placetype": "postalcode"
  },
  "geometry": {"coordinates":[-3.83561,53.27452],"type":"Point"}
}
