{
  "type": "Feature",
  "properties": {
    "iso:country":"GB",
    "wof:name":"LL32 8ND",
    "wof:placetype":"postalcode"
},
  "geometry": {"coordinates":[-3.83560987712869,53.2745199776062],"type":"Point"}
}