{
  "type": "Feature",
  "properties": {
    "iso:country":"GB",
    "wof:name":"SN25 2PJ",
    "wof:placetype":"postalcode"
},
  "geometry": {"coordinates":[-1.81647411280949,51.60421282586121],"type":"Point"}
}