{
  "type": "Feature",
  "properties": {
    "iso:country": "GB",
    "wof:name": "SN25 2PJ",
    "wof:placetype": "postalcode"
  },
  "geometry": {"coordinates":[-1.816474,51.604213],"type":"Point"}
}
