{
  "type": "Feature",
  "properties": {
    "iso:country":"GB",
    "wof:name":"E18 2EH",
    "wof:placetype":"postalcode"
},
  "geometry": {"coordinates":[0.02243745430467,51.58753806583354],"type":"Point"}
}