{
  "type": "Feature",
  "properties": {
    "iso:country":"GB",
    "wof:name":"LL62 5NT",
    "wof:placetype":"postalcode"
},
  "geometry": {"coordinates":[-4.37728167739986,53.22205927226987],"type":"Point"}
}