{
  "type": "Feature",
  "properties": {
    "iso:country":"GB",
    "wof:name":"CA10 3AT",
    "wof:placetype":"postalcode"
},
  "geometry": {"coordinates":[-2.6249872430877,54.593225841075],"type":"Point"}
}