{
  "type": "Feature",
  "properties": {
    "iso:country": "GB",
    "wof:name": "CA10 3AT",
    "wof:placetype": "postalcode"
  },
  "geometry": {"coordinates":[-2.624987,54.593226],"type":"Point"}
}
