{
  "type": "Feature",
  "properties": {
    "iso:country": "GB",
    "wof:name": "DN22 8EY",
    "wof:placetype": "postalcode"
  },
  "geometry": {"coordinates":[-0.977046,53.312161],"type":"Point"}
}
