{
  "type": "Feature",
  "properties": {
    "iso:country": "GB",
    "wof:name": "DN22 8EY",
    "wof:placetype": "postalcode"
  },
  "geometry": {"coordinates":[-0.976761,53.312116],"type":"Point"}
}
