{
  "type": "Feature",
  "properties": {
    "iso:country":"GB",
    "wof:name":"TW19 6DA",
    "wof:placetype":"postalcode"
},
  "geometry": {"coordinates":[-0.50129292918099,51.4641453879132],"type":"Point"}
}