{
  "type": "Feature",
  "properties": {
    "iso:country":"GB",
    "wof:name":"PO2 9AB",
    "wof:placetype":"postalcode"
},
  "geometry": {"coordinates":[-1.07944727103392,50.81791807246879],"type":"Point"}
}