{
  "type": "Feature",
  "properties": {
    "iso:country": "GB",
    "wof:name": "PO2 9AB",
    "wof:placetype": "postalcode"
  },
  "geometry": {"coordinates":[-1.079447,50.817918],"type":"Point"}
}
