{
  "type": "Feature",
  "properties": {
    "iso:country": "GB",
    "wof:name": "NE69 7BU",
    "wof:placetype": "postalcode"
  },
  "geometry": {"coordinates":[-1.715983,55.606256],"type":"Point"}
}
