{
  "type": "Feature",
  "properties": {
    "iso:country":"GB",
    "wof:name":"BN16 3BB",
    "wof:placetype":"postalcode"
},
  "geometry": {"coordinates":[-0.49764853376553,50.81238145095862],"type":"Point"}
}