{
  "type": "Feature",
  "properties": {
    "iso:country":"GB",
    "wof:name":"NN10 0SP",
    "wof:placetype":"postalcode"
},
  "geometry": {"coordinates":[-0.54081275407878,52.28178055028393],"type":"Point"}
}