{
  "type": "Feature",
  "properties": {
    "date:inception_lower": "1980-01-01",
    "date:inception_upper": "1980-01-01",
    "iso:country": "GB",
    "wof:name": "NN10 0SP",
    "wof:placetype": "postalcode"
  },
  "geometry": {"coordinates":[-0.540813,52.281781],"type":"Point"}
}
