{
  "type": "Feature",
  "properties": {
    "iso:country":"GB",
    "wof:name":"HP2 4DX",
    "wof:placetype":"postalcode"
},
  "geometry": {"coordinates":[-0.457137759022,51.75263980143128],"type":"Point"}
}