{
  "type": "Feature",
  "properties": {
    "date:inception_lower":"2008-06-01",
    "date:inception_upper":"2008-06-30",
    "iso:country":"GB",
    "wof:name":"PO33 2SW",
    "wof:placetype":"postalcode"
},
  "geometry": {"coordinates":[-1.163425,50.725239],"type":"Point"}
}