{
  "type": "Feature",
  "properties": {
    "date:inception_lower": "1994-05-01",
    "date:inception_upper": "1994-05-01",
    "iso:country": "GB",
    "wof:name": "M23 2ZP",
    "wof:placetype": "postalcode"
  },
  "geometry": {"coordinates":[-2.277793,53.38884],"type":"Point"}
}
