{
  "type": "Feature",
  "properties": {
    "iso:country":"GB",
    "wof:name":"M23 2ZP",
    "wof:placetype":"postalcode"
},
  "geometry": {"coordinates":[-2.27779301779969,53.38883966523429],"type":"Point"}
}