{
  "type": "Feature",
  "properties": {
    "iso:country":"GB",
    "wof:name":"NR20 5DP",
    "wof:placetype":"postalcode"
},
  "geometry": {"coordinates":[0.87775678287051,52.76395943580043],"type":"Point"}
}