{
  "type": "Feature",
  "properties": {
    "iso:country": "GB",
    "wof:name": "IV3 5HF",
    "wof:placetype": "postalcode"
  },
  "geometry": {"coordinates":[-4.242363,57.470915],"type":"Point"}
}
