{
  "type": "Feature",
  "properties": {
    "iso:country":"GB",
    "wof:name":"IV3 5HF",
    "wof:placetype":"postalcode"
},
  "geometry": {"coordinates":[-4.24236288321134,57.47091490574418],"type":"Point"}
}