{
  "type": "Feature",
  "properties": {
    "date:inception_lower":"1980-01-01",
    "date:inception_upper":"1980-01-31",
    "iso:country":"GB",
    "wof:name":"IV3 5HF",
    "wof:placetype":"postalcode"
},
  "geometry": {"coordinates":[-4.242363,57.470915],"type":"Point"}
}