{
  "type": "Feature",
  "properties": {
    "iso:country":"GB",
    "wof:name":"SK11 8HL",
    "wof:placetype":"postalcode"
},
  "geometry": {"coordinates":[-2.15690000523278,53.25679151935504],"type":"Point"}
}