{
  "type": "Feature",
  "properties": {
    "date:inception_lower": "1980-01-01",
    "date:inception_upper": "1980-01-01",
    "iso:country": "GB",
    "wof:name": "NE3 2XW",
    "wof:placetype": "postalcode"
  },
  "geometry": {"coordinates":[-1.663634,55.017746],"type":"Point"}
}
