{
  "type": "Feature",
  "properties": {
    "iso:country":"GB",
    "wof:name":"NE3 2XW",
    "wof:placetype":"postalcode"
},
  "geometry": {"coordinates":[-1.66363414021817,55.01774570299169],"type":"Point"}
}