{
  "type": "Feature",
  "properties": {
    "iso:country": "GB",
    "wof:name": "PE27 6SD",
    "wof:placetype": "postalcode"
  },
  "geometry": {"coordinates":[-0.076818,52.330702],"type":"Point"}
}
