{
  "type": "Feature",
  "properties": {
    "iso:country":"GB",
    "wof:name":"DL13 3AY",
    "wof:placetype":"postalcode"
},
  "geometry": {"coordinates":[-1.88766967392614,54.72966948736939],"type":"Point"}
}