{
  "type": "Feature",
  "properties": {
    "iso:country": "GB",
    "wof:name": "M33 2TX",
    "wof:placetype": "postalcode"
  },
  "geometry": {"coordinates":[-2.301338,53.414166],"type":"Point"}
}
