{
  "type": "Feature",
  "properties": {
    "iso:country":"GB",
    "wof:name":"M33 2TX",
    "wof:placetype":"postalcode"
},
  "geometry": {"coordinates":[-2.30133780507689,53.41416629271917],"type":"Point"}
}