{
  "type": "Feature",
  "properties": {
    "iso:country": "GB",
    "wof:name": "N3 2JG",
    "wof:placetype": "postalcode"
  },
  "geometry": {"coordinates":[-0.19405,51.600452],"type":"Point"}
}
