{
  "type": "Feature",
  "properties": {
    "date:inception_lower": "2018-04-01",
    "date:inception_upper": "2018-04-01",
    "iso:country": "GB",
    "wof:name": "CV22 7ZQ",
    "wof:placetype": "postalcode"
  },
  "geometry": {"coordinates":[-1.314028,52.357999],"type":"Point"}
}
