{
  "type": "Feature",
  "properties": {
    "iso:country": "GB",
    "wof:name": "CV22 7ZQ",
    "wof:placetype": "postalcode"
  },
  "geometry": {"coordinates":[-1.313862,52.358322],"type":"Point"}
}
