{
  "type": "Feature",
  "properties": {
    "date:inception_lower":"2018-04-01",
    "date:inception_upper":"2018-04-30",
    "iso:country":"GB",
    "wof:name":"CV22 7ZQ",
    "wof:placetype":"postalcode"
},
  "geometry": {"coordinates":[-1.313862,52.358322],"type":"Point"}
}