{
  "type": "Feature",
  "properties": {
    "date:inception_lower": "2021-11-01",
    "date:inception_upper": "2021-11-01",
    "iso:country": "GB",
    "wof:name": "KA10 7GF",
    "wof:placetype": "postalcode"
  },
  "geometry": {"coordinates":[-4.631318,55.557403],"type":"Point"}
}
