{
  "type": "Feature",
  "properties": {
    "iso:country": "GB",
    "wof:name": "NG34 7UR",
    "wof:placetype": "postalcode"
  },
  "geometry": {"coordinates":[-0.42591,52.996092],"type":"Point"}
}
