{
  "type": "Feature",
  "properties": {
    "iso:country":"GB",
    "wof:name":"NG34 7UR",
    "wof:placetype":"postalcode"
},
  "geometry": {"coordinates":[-0.42591021652885,52.99609204798108],"type":"Point"}
}