{
  "type": "Feature",
  "properties": {
    "iso:country":"GB",
    "wof:name":"PH8 0JD",
    "wof:placetype":"postalcode"
},
  "geometry": {"coordinates":[-3.52319548593569,56.54780633428091],"type":"Point"}
}