{
  "type": "Feature",
  "properties": {
    "iso:country":"GB",
    "wof:name":"BS22 8DQ",
    "wof:placetype":"postalcode"
},
  "geometry": {"coordinates":[-2.93338642964269,51.34863980520312],"type":"Point"}
}