{
  "type": "Feature",
  "properties": {
    "date:inception_lower": "1996-06-01",
    "date:inception_upper": "1996-06-01",
    "iso:country": "GB",
    "wof:name": "BS22 8DQ",
    "wof:placetype": "postalcode"
  },
  "geometry": {"coordinates":[-2.933391,51.34861],"type":"Point"}
}
