{
  "type": "Feature",
  "properties": {
    "iso:country":"GB",
    "wof:name":"S45 0DE",
    "wof:placetype":"postalcode"
},
  "geometry": {"coordinates":[-1.49531814150969,53.17942219452372],"type":"Point"}
}