{
  "type": "Feature",
  "properties": {
    "iso:country":"GB",
    "wof:name":"KA1 4SN",
    "wof:placetype":"postalcode"
},
  "geometry": {"coordinates":[-4.49757024095468,55.58510186152476],"type":"Point"}
}