{
  "type": "Feature",
  "properties": {
    "iso:country":"GB",
    "wof:name":"TS3 7HS",
    "wof:placetype":"postalcode"
},
  "geometry": {"coordinates":[-1.20116369626092,54.55360699935847],"type":"Point"}
}