{
  "type": "Feature",
  "properties": {
    "iso:country": "GB",
    "wof:name": "TN14 5JL",
    "wof:placetype": "postalcode"
  },
  "geometry": {"coordinates":[0.172999,51.311927],"type":"Point"}
}
