{
  "type": "Feature",
  "properties": {
    "iso:country":"GB",
    "wof:name":"HU6 9LT",
    "wof:placetype":"postalcode"
},
  "geometry": {"coordinates":[-0.37628859990077,53.78642958071512],"type":"Point"}
}