{
  "type": "Feature",
  "properties": {
    "date:inception_lower": "2019-02-01",
    "date:inception_upper": "2019-02-01",
    "iso:country": "GB",
    "wof:name": "CO16 9FJ",
    "wof:placetype": "postalcode"
  },
  "geometry": {"coordinates":[1.122512,51.842175],"type":"Point"}
}
