{
  "type": "Feature",
  "properties": {
    "iso:country":"GB",
    "wof:name":"BL0 0JP",
    "wof:placetype":"postalcode"
},
  "geometry": {"coordinates":[-2.30380698091051,53.66922327492086],"type":"Point"}
}