{
  "type": "Feature",
  "properties": {
    "iso:country": "GB",
    "wof:name": "TQ12 5AG",
    "wof:placetype": "postalcode"
  },
  "geometry": {"coordinates":[-3.579723,50.503304],"type":"Point"}
}
