{
  "type": "Feature",
  "properties": {
    "iso:country":"GB",
    "wof:name":"NE34 8HY",
    "wof:placetype":"postalcode"
},
  "geometry": {"coordinates":[-1.42689186252132,54.95810901918241],"type":"Point"}
}