{
  "type": "Feature",
  "properties": {
    "date:inception_lower": "1980-01-01",
    "date:inception_upper": "1980-01-01",
    "iso:country": "GB",
    "wof:name": "EX5 2BE",
    "wof:placetype": "postalcode"
  },
  "geometry": {"coordinates":[-3.415917,50.730197],"type":"Point"}
}
