{
  "type": "Feature",
  "properties": {
    "iso:country":"GB",
    "wof:name":"DN17 4EU",
    "wof:placetype":"postalcode"
},
  "geometry": {"coordinates":[-0.8422161549154,53.60779041018311],"type":"Point"}
}