{
  "type": "Feature",
  "properties": {
    "date:inception_lower": "1980-01-01",
    "date:inception_upper": "1980-01-01",
    "iso:country": "GB",
    "wof:name": "DN17 4EU",
    "wof:placetype": "postalcode"
  },
  "geometry": {"coordinates":[-0.839086,53.608554],"type":"Point"}
}
