{
  "type": "Feature",
  "properties": {
    "iso:country": "GB",
    "wof:name": "DN17 4EU",
    "wof:placetype": "postalcode"
  },
  "geometry": {"coordinates":[-0.842216,53.60779],"type":"Point"}
}
