{
  "type": "Feature",
  "properties": {
    "iso:country":"GB",
    "wof:name":"EX39 1QU",
    "wof:placetype":"postalcode"
},
  "geometry": {"coordinates":[-4.19193024108052,51.05384202314117],"type":"Point"}
}