{
  "type": "Feature",
  "properties": {
    "iso:country":"GB",
    "wof:name":"PR25 1YB",
    "wof:placetype":"postalcode"
},
  "geometry": {"coordinates":[-2.72044613399462,53.69407313886509],"type":"Point"}
}