{
  "type": "Feature",
  "properties": {
    "date:inception_lower":"2001-06-01",
    "date:inception_upper":"2001-06-30",
    "iso:country":"GB",
    "wof:name":"PR25 1YB",
    "wof:placetype":"postalcode"
},
  "geometry": {"coordinates":[-2.720446,53.694073],"type":"Point"}
}