{
  "type": "Feature",
  "properties": {
    "iso:country": "GB",
    "wof:name": "PR25 1YB",
    "wof:placetype": "postalcode"
  },
  "geometry": {"coordinates":[-2.720446,53.694073],"type":"Point"}
}
