{
  "type": "Feature",
  "properties": {
    "iso:country":"GB",
    "wof:name":"WA9 1RU",
    "wof:placetype":"postalcode"
},
  "geometry": {"coordinates":[-2.70791330197703,53.4531842892347],"type":"Point"}
}