{
  "type": "Feature",
  "properties": {
    "iso:country": "GB",
    "wof:name": "DL13 1NH",
    "wof:placetype": "postalcode"
  },
  "geometry": {"coordinates":[-2.165226,54.735575],"type":"Point"}
}
