{
  "type": "Feature",
  "properties": {
    "date:inception_lower":"2000-06-01",
    "date:inception_upper":"2000-06-30",
    "iso:country":"GB",
    "wof:name":"PE19 6YP",
    "wof:placetype":"postalcode"
},
  "geometry": {"coordinates":[-0.223741,52.258573],"type":"Point"}
}