{
  "type": "Feature",
  "properties": {
    "date:inception_lower": "1980-01-01",
    "date:inception_upper": "1980-01-01",
    "iso:country": "GB",
    "wof:name": "CO15 3LQ",
    "wof:placetype": "postalcode"
  },
  "geometry": {"coordinates":[1.14078,51.796975],"type":"Point"}
}
