{
  "type": "Feature",
  "properties": {
    "iso:country":"GB",
    "wof:name":"DN31 2BP",
    "wof:placetype":"postalcode"
},
  "geometry": {"coordinates":[-0.10747617431236,53.56813082329931],"type":"Point"}
}