{
  "type": "Feature",
  "properties": {
    "iso:country":"GB",
    "wof:name":"SS6 9GZ",
    "wof:placetype":"postalcode"
},
  "geometry": {"coordinates":[0.58899178315851,51.59682830353233],"type":"Point"}
}