{
  "type": "Feature",
  "properties": {
    "iso:country":"GB",
    "wof:name":"N1 5SZ",
    "wof:placetype":"postalcode"
},
  "geometry": {"coordinates":[-0.08174909418244,51.53808398823591],"type":"Point"}
}