{
  "type": "Feature",
  "properties": {
    "date:inception_lower": "2006-05-01",
    "date:inception_upper": "2006-05-01",
    "iso:country": "GB",
    "wof:name": "N1 5SZ",
    "wof:placetype": "postalcode"
  },
  "geometry": {"coordinates":[-0.081749,51.538084],"type":"Point"}
}
