{
  "type": "Feature",
  "properties": {
    "iso:country": "GB",
    "wof:name": "BB1 9TY",
    "wof:placetype": "postalcode"
  },
  "geometry": {"coordinates":[-2.476404,53.759567],"type":"Point"}
}
