{
  "type": "Feature",
  "properties": {
    "iso:country":"GB",
    "wof:name":"BB1 9TY",
    "wof:placetype":"postalcode"
},
  "geometry": {"coordinates":[-2.47640391198347,53.75956708321201],"type":"Point"}
}