{
  "type": "Feature",
  "properties": {
    "iso:country":"GB",
    "wof:name":"SA18 3AP",
    "wof:placetype":"postalcode"
},
  "geometry": {"coordinates":[-3.99534156030994,51.79233684595747],"type":"Point"}
}