{
  "type": "Feature",
  "properties": {
    "date:inception_lower": "1980-01-01",
    "date:inception_upper": "1980-01-01",
    "iso:country": "GB",
    "wof:name": "SA18 3AP",
    "wof:placetype": "postalcode"
  },
  "geometry": {"coordinates":[-3.996045,51.791739],"type":"Point"}
}
