{
  "type": "Feature",
  "properties": {
    "iso:country": "GB",
    "wof:name": "WA15 6TL",
    "wof:placetype": "postalcode"
  },
  "geometry": {"coordinates":[-2.338293,53.401591],"type":"Point"}
}
