{
  "type": "Feature",
  "properties": {
    "iso:country": "GB",
    "wof:name": "DN10 4JJ",
    "wof:placetype": "postalcode"
  },
  "geometry": {"coordinates":[-0.838146,53.423235],"type":"Point"}
}
