{
  "type": "Feature",
  "properties": {
    "date:inception_lower": "1980-01-01",
    "date:inception_upper": "1980-01-01",
    "iso:country": "GB",
    "wof:name": "M14 4TH",
    "wof:placetype": "postalcode"
  },
  "geometry": {"coordinates":[-2.244696,53.456425],"type":"Point"}
}
