{
  "type": "Feature",
  "properties": {
    "iso:country":"GB",
    "wof:name":"FY1 3NR",
    "wof:placetype":"postalcode"
},
  "geometry": {"coordinates":[-3.04245719177162,53.82510962465381],"type":"Point"}
}