{
  "type": "Feature",
  "properties": {
    "iso:country":"GB",
    "wof:name":"LL61 6TJ",
    "wof:placetype":"postalcode"
},
  "geometry": {"coordinates":[-4.29206569508074,53.17119577115719],"type":"Point"}
}