{
  "type": "Feature",
  "properties": {
    "iso:country":"GB",
    "wof:name":"EH6 6DL",
    "wof:placetype":"postalcode"
},
  "geometry": {"coordinates":[-3.17191685267011,55.9744001566348],"type":"Point"}
}