{
  "type": "Feature",
  "properties": {
    "iso:country":"GB",
    "wof:name":"OX28 1BX",
    "wof:placetype":"postalcode"
},
  "geometry": {"coordinates":[-1.46370070088155,51.79486147938301],"type":"Point"}
}