{
  "type": "Feature",
  "properties": {
    "date:inception_lower": "2017-06-01",
    "date:inception_upper": "2017-06-01",
    "iso:country": "GB",
    "wof:name": "BS13 0DD",
    "wof:placetype": "postalcode"
  },
  "geometry": {"coordinates":[-2.591351,51.407216],"type":"Point"}
}
