{
  "type": "Feature",
  "properties": {
    "iso:country":"GB",
    "wof:name":"M19 3GW",
    "wof:placetype":"postalcode"
},
  "geometry": {"coordinates":[-2.17664482685114,53.44998366117788],"type":"Point"}
}