{
  "type": "Feature",
  "properties": {
    "date:inception_lower": "2015-03-01",
    "date:inception_upper": "2015-03-01",
    "iso:country": "GB",
    "wof:name": "M19 3GW",
    "wof:placetype": "postalcode"
  },
  "geometry": {"coordinates":[-2.176971,53.449289],"type":"Point"}
}
