{
  "type": "Feature",
  "properties": {
    "iso:country":"GB",
    "wof:name":"KT3 5AG",
    "wof:placetype":"postalcode"
},
  "geometry": {"coordinates":[-0.26143931547341,51.39705053972033],"type":"Point"}
}