{
  "type": "Feature",
  "properties": {
    "date:inception_lower":"1980-01-01",
    "date:inception_upper":"1980-01-31",
    "iso:country":"GB",
    "wof:name":"KT3 5AG",
    "wof:placetype":"postalcode"
},
  "geometry": {"coordinates":[-0.261439,51.397051],"type":"Point"}
}