{
  "type": "Feature",
  "properties": {
    "iso:country": "GB",
    "wof:name": "KT3 3TB",
    "wof:placetype": "postalcode"
  },
  "geometry": {"coordinates":[-0.277518,51.401074],"type":"Point"}
}
