{
  "type": "Feature",
  "properties": {
    "date:inception_lower":"2000-12-01",
    "date:inception_upper":"2000-12-31",
    "iso:country":"GB",
    "wof:name":"KT3 3TB",
    "wof:placetype":"postalcode"
},
  "geometry": {"coordinates":[-0.277518,51.401074],"type":"Point"}
}