{
  "type": "Feature",
  "properties": {
    "iso:country":"GB",
    "wof:name":"KT3 3TB",
    "wof:placetype":"postalcode"
},
  "geometry": {"coordinates":[-0.27751783366648,51.40107382760491],"type":"Point"}
}