{
  "type": "Feature",
  "properties": {
    "date:inception_lower": "1994-05-01",
    "date:inception_upper": "1994-05-01",
    "iso:country": "GB",
    "wof:name": "M20 1AJ",
    "wof:placetype": "postalcode"
  },
  "geometry": {"coordinates":[-2.233696,53.435989],"type":"Point"}
}
