{
  "type": "Feature",
  "properties": {
    "date:inception_lower": "2017-12-01",
    "date:inception_upper": "2017-12-01",
    "iso:country": "GB",
    "wof:name": "BN16 4QA",
    "wof:placetype": "postalcode"
  },
  "geometry": {"coordinates":[-0.472479,50.822137],"type":"Point"}
}
