{
  "type": "Feature",
  "properties": {
    "date:inception_lower": "2018-04-01",
    "date:inception_upper": "2018-04-01",
    "iso:country": "GB",
    "wof:name": "S63 9GR",
    "wof:placetype": "postalcode"
  },
  "geometry": {"coordinates":[-1.291157,53.5316],"type":"Point"}
}
