{
  "type": "Feature",
  "properties": {
    "iso:country":"GB",
    "wof:name":"KW15 1UB",
    "wof:placetype":"postalcode"
},
  "geometry": {"coordinates":[-2.98965613993953,58.99189420557185],"type":"Point"}
}