{
  "type": "Feature",
  "properties": {
    "iso:country":"GB",
    "wof:name":"NW10 9QG",
    "wof:placetype":"postalcode"
},
  "geometry": {"coordinates":[-0.25176994853754,51.5445715831633],"type":"Point"}
}