{
  "type": "Feature",
  "properties": {
    "iso:country":"GB",
    "wof:name":"AB31 4EX",
    "wof:placetype":"postalcode"
},
  "geometry": {"coordinates":[-2.48505899282887,57.07474632190805],"type":"Point"}
}