{
  "type": "Feature",
  "properties": {
    "iso:country": "GB",
    "wof:name": "NW5 9QB",
    "wof:placetype": "postalcode"
  },
  "geometry": {"coordinates":[-0.143423,51.550922],"type":"Point"}
}
