{
  "type": "Feature",
  "properties": {
    "iso:country":"GB",
    "wof:name":"FY5 2RE",
    "wof:placetype":"postalcode"
},
  "geometry": {"coordinates":[-3.02335696455477,53.88165777725199],"type":"Point"}
}