{
  "type": "Feature",
  "properties": {
    "iso:country":"GB",
    "wof:name":"CH41 9BX",
    "wof:placetype":"postalcode"
},
  "geometry": {"coordinates":[-3.02190147329628,53.38761038262969],"type":"Point"}
}