{
  "type": "Feature",
  "properties": {
    "iso:country":"GB",
    "wof:name":"BL1 6EU",
    "wof:placetype":"postalcode"
},
  "geometry": {"coordinates":[-2.45798949983226,53.59215230481784],"type":"Point"}
}