{
  "type": "Feature",
  "properties": {
    "date:inception_lower": "1980-01-01",
    "date:inception_upper": "1980-01-01",
    "iso:country": "GB",
    "wof:name": "BL1 6EU",
    "wof:placetype": "postalcode"
  },
  "geometry": {"coordinates":[-2.457989,53.592152],"type":"Point"}
}
