{
  "type": "Feature",
  "properties": {
    "iso:country": "GB",
    "wof:name": "PE28 3QA",
    "wof:placetype": "postalcode"
  },
  "geometry": {"coordinates":[0.031323,52.356389],"type":"Point"}
}
