{
  "type": "Feature",
  "properties": {
    "iso:country":"GB",
    "wof:name":"PE28 3QA",
    "wof:placetype":"postalcode"
},
  "geometry": {"coordinates":[0.03132256137519,52.3563885316],"type":"Point"}
}