{
  "type": "Feature",
  "properties": {
    "date:inception_lower": "1980-01-01",
    "date:inception_upper": "1980-01-01",
    "iso:country": "GB",
    "wof:name": "TS13 5NB",
    "wof:placetype": "postalcode"
  },
  "geometry": {"coordinates":[-0.758427,54.507368],"type":"Point"}
}
