{
  "type": "Feature",
  "properties": {
    "iso:country": "GB",
    "wof:name": "TS13 5NB",
    "wof:placetype": "postalcode"
  },
  "geometry": {"coordinates":[-0.758634,54.507164],"type":"Point"}
}
