{
  "type": "Feature",
  "properties": {
    "iso:country":"GB",
    "wof:name":"GL51 8DS",
    "wof:placetype":"postalcode"
},
  "geometry": {"coordinates":[-2.11055681930608,51.90069445558682],"type":"Point"}
}