{
  "type": "Feature",
  "properties": {
    "iso:country":"GB",
    "wof:name":"G40 4SD",
    "wof:placetype":"postalcode"
},
  "geometry": {"coordinates":[-4.2123458211296,55.84075137671385],"type":"Point"}
}