{
  "type": "Feature",
  "properties": {
    "date:inception_lower": "1980-01-01",
    "date:inception_upper": "1980-01-01",
    "iso:country": "GB",
    "wof:name": "G40 4SD",
    "wof:placetype": "postalcode"
  },
  "geometry": {"coordinates":[-4.212346,55.840751],"type":"Point"}
}
