{
  "type": "Feature",
  "properties": {
    "date:inception_lower": "2022-05-01",
    "date:inception_upper": "2022-05-01",
    "iso:country": "GB",
    "wof:name": "CA3 0FG",
    "wof:placetype": "postalcode"
  },
  "geometry": {"coordinates":[-2.935289,54.919119],"type":"Point"}
}
