{
  "type": "Feature",
  "properties": {
    "date:inception_lower":"1980-01-01",
    "date:inception_upper":"1980-01-31",
    "iso:country":"GB",
    "wof:name":"NE26 3EL",
    "wof:placetype":"postalcode"
},
  "geometry": {"coordinates":[-1.461124,55.052505],"type":"Point"}
}