{
  "type": "Feature",
  "properties": {
    "iso:country":"GB",
    "wof:name":"NE26 3EL",
    "wof:placetype":"postalcode"
},
  "geometry": {"coordinates":[-1.4611241973625,55.05250459371427],"type":"Point"}
}