{
  "type": "Feature",
  "properties": {
    "iso:country": "GB",
    "wof:name": "HP20 1NW",
    "wof:placetype": "postalcode"
  },
  "geometry": {"coordinates":[-0.785539,51.815745],"type":"Point"}
}
