{
  "type": "Feature",
  "properties": {
    "iso:country":"GB",
    "wof:name":"HU5 1NA",
    "wof:placetype":"postalcode"
},
  "geometry": {"coordinates":[-0.35287800166532,53.76792532146661],"type":"Point"}
}