{
  "type": "Feature",
  "properties": {
    "iso:country":"GB",
    "wof:name":"HX7 5RF",
    "wof:placetype":"postalcode"
},
  "geometry": {"coordinates":[-1.98004286096786,53.73675774334048],"type":"Point"}
}