{
  "type": "Feature",
  "properties": {
    "iso:country": "GB",
    "wof:name": "GL5 2NQ",
    "wof:placetype": "postalcode"
  },
  "geometry": {"coordinates":[-2.209878,51.731456],"type":"Point"}
}
