{
  "type": "Feature",
  "properties": {
    "iso:country":"GB",
    "wof:name":"GL5 2NQ",
    "wof:placetype":"postalcode"
},
  "geometry": {"coordinates":[-2.20987814693309,51.73145647074034],"type":"Point"}
}