{
  "type": "Feature",
  "properties": {
    "iso:country":"GB",
    "wof:name":"N16 6DF",
    "wof:placetype":"postalcode"
},
  "geometry": {"coordinates":[-0.06213376346326,51.57687014235216],"type":"Point"}
}