{
  "type": "Feature",
  "properties": {
    "date:inception_lower": "1980-01-01",
    "date:inception_upper": "1980-01-01",
    "iso:country": "GB",
    "wof:name": "BD24 0JT",
    "wof:placetype": "postalcode"
  },
  "geometry": {"coordinates":[-2.346753,54.057789],"type":"Point"}
}
