{
  "type": "Feature",
  "properties": {
    "iso:country": "GB",
    "wof:name": "BD24 0JT",
    "wof:placetype": "postalcode"
  },
  "geometry": {"coordinates":[-2.346753,54.057789],"type":"Point"}
}
