{
  "type": "Feature",
  "properties": {
    "iso:country":"GB",
    "wof:name":"N20 9AZ",
    "wof:placetype":"postalcode"
},
  "geometry": {"coordinates":[-0.16862040687631,51.63235454495263],"type":"Point"}
}