{
  "type": "Feature",
  "properties": {
    "iso:country":"GB",
    "wof:name":"BH12 4BN",
    "wof:placetype":"postalcode"
},
  "geometry": {"coordinates":[-1.91958776535045,50.74382398218686],"type":"Point"}
}