{
  "type": "Feature",
  "properties": {
    "date:inception_lower": "1980-01-01",
    "date:inception_upper": "1980-01-01",
    "iso:country": "GB",
    "wof:name": "DN20 0PY",
    "wof:placetype": "postalcode"
  },
  "geometry": {"coordinates":[-0.486102,53.626297],"type":"Point"}
}
