{
  "type": "Feature",
  "properties": {
    "date:inception_lower": "1997-12-01",
    "date:inception_upper": "1997-12-01",
    "iso:country": "GB",
    "wof:name": "BS20 7BN",
    "wof:placetype": "postalcode"
  },
  "geometry": {"coordinates":[-2.756873,51.478415],"type":"Point"}
}
