{
  "type": "Feature",
  "properties": {
    "iso:country": "GB",
    "wof:name": "BS20 7BN",
    "wof:placetype": "postalcode"
  },
  "geometry": {"coordinates":[-2.756873,51.478415],"type":"Point"}
}
