{
  "type": "Feature",
  "properties": {
    "iso:country": "GB",
    "wof:name": "AB39 3QX",
    "wof:placetype": "postalcode"
  },
  "geometry": {"coordinates":[-2.214842,57.046435],"type":"Point"}
}
