{
  "type": "Feature",
  "properties": {
    "date:inception_lower":"2016-07-01",
    "date:inception_upper":"2016-07-31",
    "iso:country":"GB",
    "wof:name":"B73 9AA",
    "wof:placetype":"postalcode"
},
  "geometry": {"coordinates":[-1.829167,52.568642],"type":"Point"}
}