{
  "type": "Feature",
  "properties": {
    "iso:country": "GB",
    "wof:name": "PE11 2BN",
    "wof:placetype": "postalcode"
  },
  "geometry": {"coordinates":[-0.143178,52.794213],"type":"Point"}
}
