{
  "type": "Feature",
  "properties": {
    "date:inception_lower":"1980-01-01",
    "date:inception_upper":"1980-01-31",
    "iso:country":"GB",
    "wof:name":"PE11 2BN",
    "wof:placetype":"postalcode"
},
  "geometry": {"coordinates":[-0.143178,52.794213],"type":"Point"}
}