{
  "type": "Feature",
  "properties": {
    "iso:country":"GB",
    "wof:name":"SY8 4EH",
    "wof:placetype":"postalcode"
},
  "geometry": {"coordinates":[-2.72743665104802,52.32377504612768],"type":"Point"}
}