{
  "type": "Feature",
  "properties": {
    "date:inception_lower": "1980-01-01",
    "date:inception_upper": "1980-01-01",
    "iso:country": "GB",
    "wof:name": "SY8 4EH",
    "wof:placetype": "postalcode"
  },
  "geometry": {"coordinates":[-2.727435,52.323788],"type":"Point"}
}
