{
  "type": "Feature",
  "properties": {
    "iso:country":"GB",
    "wof:name":"DH4 7RH",
    "wof:placetype":"postalcode"
},
  "geometry": {"coordinates":[-1.48892128405344,54.87296965862118],"type":"Point"}
}