{
  "type": "Feature",
  "properties": {
    "date:inception_lower": "1980-01-01",
    "date:inception_upper": "1980-01-01",
    "iso:country": "GB",
    "wof:name": "DH4 7RH",
    "wof:placetype": "postalcode"
  },
  "geometry": {"coordinates":[-1.488921,54.87297],"type":"Point"}
}
