{
  "type": "Feature",
  "properties": {
    "iso:country": "GB",
    "wof:name": "TA18 8HY",
    "wof:placetype": "postalcode"
  },
  "geometry": {"coordinates":[-2.79302,50.875145],"type":"Point"}
}
