{
  "type": "Feature",
  "properties": {
    "iso:country":"GB",
    "wof:name":"W2 4EW",
    "wof:placetype":"postalcode"
},
  "geometry": {"coordinates":[-0.19720267631985,51.51123817566463],"type":"Point"}
}