{
  "type": "Feature",
  "properties": {
    "iso:country":"GB",
    "wof:name":"LN10 5HS",
    "wof:placetype":"postalcode"
},
  "geometry": {"coordinates":[-0.25513817721823,53.18311386307634],"type":"Point"}
}