{
  "type": "Feature",
  "properties": {
    "iso:country":"GB",
    "wof:name":"M41 9ER",
    "wof:placetype":"postalcode"
},
  "geometry": {"coordinates":[-2.36723277985161,53.43843960992338],"type":"Point"}
}