{
  "type": "Feature",
  "properties": {
    "iso:country": "GB",
    "wof:name": "M41 9ER",
    "wof:placetype": "postalcode"
  },
  "geometry": {"coordinates":[-2.367233,53.43844],"type":"Point"}
}
