{
  "type": "Feature",
  "properties": {
    "iso:country":"GB",
    "wof:name":"BL3 5PQ",
    "wof:placetype":"postalcode"
},
  "geometry": {"coordinates":[-2.45234693932716,53.56884897062407],"type":"Point"}
}