{
  "type": "Feature",
  "properties": {
    "date:inception_lower": "2011-12-01",
    "date:inception_upper": "2011-12-01",
    "iso:country": "GB",
    "wof:name": "PR7 5FQ",
    "wof:placetype": "postalcode"
  },
  "geometry": {"coordinates":[-2.664356,53.62614],"type":"Point"}
}
