{
  "type": "Feature",
  "properties": {
    "iso:country":"GB",
    "wof:name":"PR7 5FQ",
    "wof:placetype":"postalcode"
},
  "geometry": {"coordinates":[-2.66435590116707,53.62613999518501],"type":"Point"}
}