{
  "type": "Feature",
  "properties": {
    "iso:country":"GB",
    "wof:name":"SW6 3SA",
    "wof:placetype":"postalcode"
},
  "geometry": {"coordinates":[-0.20555874954974,51.4672762503458],"type":"Point"}
}