{
  "type": "Feature",
  "properties": {
    "date:inception_lower": "1980-01-01",
    "date:inception_upper": "1980-01-01",
    "iso:country": "GB",
    "wof:name": "SW6 3SA",
    "wof:placetype": "postalcode"
  },
  "geometry": {"coordinates":[-0.205559,51.467276],"type":"Point"}
}
