{
  "type": "Feature",
  "properties": {
    "iso:country":"GB",
    "wof:name":"WF9 4SU",
    "wof:placetype":"postalcode"
},
  "geometry": {"coordinates":[-1.34747628469678,53.60697279396206],"type":"Point"}
}