{
  "type": "Feature",
  "properties": {
    "date:inception_lower": "2003-04-01",
    "date:inception_upper": "2003-04-01",
    "iso:country": "GB",
    "wof:name": "WF9 4SU",
    "wof:placetype": "postalcode"
  },
  "geometry": {"coordinates":[-1.347476,53.606973],"type":"Point"}
}
