{
  "type": "Feature",
  "properties": {
    "iso:country":"GB",
    "wof:name":"CH44 5TP",
    "wof:placetype":"postalcode"
},
  "geometry": {"coordinates":[-3.04350816016051,53.4195590439997],"type":"Point"}
}