{
  "type": "Feature",
  "properties": {
    "iso:country": "GB",
    "wof:name": "CH44 5TP",
    "wof:placetype": "postalcode"
  },
  "geometry": {"coordinates":[-3.043433,53.419613],"type":"Point"}
}
