{
  "type": "Feature",
  "properties": {
    "iso:country":"GB",
    "wof:name":"SY25 6NL",
    "wof:placetype":"postalcode"
},
  "geometry": {"coordinates":[-3.91272397482543,52.20936108609808],"type":"Point"}
}