{
  "type": "Feature",
  "properties": {
    "iso:country":"GB",
    "wof:name":"SK12 1EL",
    "wof:placetype":"postalcode"
},
  "geometry": {"coordinates":[-2.12763839527625,53.35651123462887],"type":"Point"}
}