{
  "type": "Feature",
  "properties": {
    "iso:country":"GB",
    "wof:name":"OX13 6QW",
    "wof:placetype":"postalcode"
},
  "geometry": {"coordinates":[-1.34688651919524,51.68542311295305],"type":"Point"}
}