{
  "type": "Feature",
  "properties": {
    "iso:country": "GB",
    "wof:name": "NR34 0BS",
    "wof:placetype": "postalcode"
  },
  "geometry": {"coordinates":[1.629262,52.483945],"type":"Point"}
}
