{
  "type": "Feature",
  "properties": {
    "iso:country":"GB",
    "wof:name":"NR34 0BS",
    "wof:placetype":"postalcode"
},
  "geometry": {"coordinates":[1.62926226880089,52.4839445516938],"type":"Point"}
}