{
  "type": "Feature",
  "properties": {
    "date:inception_lower": "1980-01-01",
    "date:inception_upper": "1980-01-01",
    "iso:country": "GB",
    "wof:name": "NR34 0BS",
    "wof:placetype": "postalcode"
  },
  "geometry": {"coordinates":[1.628569,52.484001],"type":"Point"}
}
