{
  "type": "Feature",
  "properties": {
    "iso:country":"GB",
    "wof:name":"HA3 0HP",
    "wof:placetype":"postalcode"
},
  "geometry": {"coordinates":[-0.30929650438435,51.58545714133314],"type":"Point"}
}