{
  "type": "Feature",
  "properties": {
    "iso:country":"GB",
    "wof:name":"DY8 5HZ",
    "wof:placetype":"postalcode"
},
  "geometry": {"coordinates":[-2.17474542319528,52.47612894817354],"type":"Point"}
}