{
  "type": "Feature",
  "properties": {
    "iso:country":"GB",
    "wof:name":"DY1 3TN",
    "wof:placetype":"postalcode"
},
  "geometry": {"coordinates":[-2.10757394020185,52.52786536886993],"type":"Point"}
}