{
  "type": "Feature",
  "properties": {
    "iso:country":"GB",
    "wof:name":"CF81 8JS",
    "wof:placetype":"postalcode"
},
  "geometry": {"coordinates":[-3.22606533283655,51.67527912546526],"type":"Point"}
}