{
  "type": "Feature",
  "properties": {
    "date:inception_lower": "1980-01-01",
    "date:inception_upper": "1980-01-01",
    "iso:country": "GB",
    "wof:name": "CV2 3HX",
    "wof:placetype": "postalcode"
  },
  "geometry": {"coordinates":[-1.47707,52.421739],"type":"Point"}
}
