{
  "type": "Feature",
  "properties": {
    "iso:country":"GB",
    "wof:name":"CV2 3HX",
    "wof:placetype":"postalcode"
},
  "geometry": {"coordinates":[-1.47707026694303,52.42173863730886],"type":"Point"}
}