{
  "type": "Feature",
  "properties": {
    "iso:country": "GB",
    "wof:name": "BS7 8AR",
    "wof:placetype": "postalcode"
  },
  "geometry": {"coordinates":[-2.591436,51.472747],"type":"Point"}
}
