{
  "type": "Feature",
  "properties": {
    "date:inception_lower": "2023-05-01",
    "date:inception_upper": "2023-05-01",
    "iso:country": "GB",
    "wof:name": "FK6 6FF",
    "wof:placetype": "postalcode"
  },
  "geometry": {"coordinates":[-3.916825,56.035405],"type":"Point"}
}
