{
  "type": "Feature",
  "properties": {
    "iso:country":"GB",
    "wof:name":"NN1 1UG",
    "wof:placetype":"postalcode"
},
  "geometry": {"coordinates":[-0.89198564996861,52.23548297353542],"type":"Point"}
}