{
  "type": "Feature",
  "properties": {
    "iso:country":"GB",
    "wof:name":"SL1 8PL",
    "wof:placetype":"postalcode"
},
  "geometry": {"coordinates":[-0.64075013675599,51.57052072610627],"type":"Point"}
}