{
  "type": "Feature",
  "properties": {
    "iso:country":"GB",
    "wof:name":"PL20 6HH",
    "wof:placetype":"postalcode"
},
  "geometry": {"coordinates":[-4.13072924085941,50.47497956063815],"type":"Point"}
}