{
  "type": "Feature",
  "properties": {
    "iso:country":"GB",
    "wof:name":"OX44 7LN",
    "wof:placetype":"postalcode"
},
  "geometry": {"coordinates":[-1.07323125514318,51.69967821304366],"type":"Point"}
}