{
  "type": "Feature",
  "properties": {
    "date:inception_lower": "1993-08-01",
    "date:inception_upper": "1993-08-01",
    "iso:country": "GB",
    "wof:name": "OX44 7LN",
    "wof:placetype": "postalcode"
  },
  "geometry": {"coordinates":[-1.07299,51.699888],"type":"Point"}
}
