{
  "type": "Feature",
  "properties": {
    "iso:country": "GB",
    "wof:name": "SW6 3SP",
    "wof:placetype": "postalcode"
  },
  "geometry": {"coordinates":[-0.194202,51.473397],"type":"Point"}
}
