{
  "type": "Feature",
  "properties": {
    "date:inception_lower": "1980-01-01",
    "date:inception_upper": "1980-01-01",
    "iso:country": "GB",
    "wof:name": "SW6 3SP",
    "wof:placetype": "postalcode"
  },
  "geometry": {"coordinates":[-0.194202,51.473397],"type":"Point"}
}
