{
  "type": "Feature",
  "properties": {
    "iso:country":"GB",
    "wof:name":"TS17 9PA",
    "wof:placetype":"postalcode"
},
  "geometry": {"coordinates":[-1.29792321321701,54.53279977762278],"type":"Point"}
}