{
  "type": "Feature",
  "properties": {
    "iso:country":"GB",
    "wof:name":"NE34 8HS",
    "wof:placetype":"postalcode"
},
  "geometry": {"coordinates":[-1.42694405419633,54.95663550030978],"type":"Point"}
}