{
  "type": "Feature",
  "properties": {
    "iso:country":"GB",
    "wof:name":"PE21 9NP",
    "wof:placetype":"postalcode"
},
  "geometry": {"coordinates":[-0.04696333031504,52.99840069751027],"type":"Point"}
}