{
  "type": "Feature",
  "properties": {
    "date:inception_lower": "1991-09-01",
    "date:inception_upper": "1991-09-01",
    "iso:country": "GB",
    "wof:name": "PE21 9NP",
    "wof:placetype": "postalcode"
  },
  "geometry": {"coordinates":[-0.046963,52.998401],"type":"Point"}
}
