{
  "type": "Feature",
  "properties": {
    "iso:country": "GB",
    "wof:name": "PE21 9NP",
    "wof:placetype": "postalcode"
  },
  "geometry": {"coordinates":[-0.046963,52.998401],"type":"Point"}
}
