{
  "type": "Feature",
  "properties": {
    "iso:country":"GB",
    "wof:name":"BA7 7JQ",
    "wof:placetype":"postalcode"
},
  "geometry": {"coordinates":[-2.51322331526944,51.09444222004407],"type":"Point"}
}