{
  "type": "Feature",
  "properties": {
    "iso:country": "GB",
    "wof:name": "BA7 7JQ",
    "wof:placetype": "postalcode"
  },
  "geometry": {"coordinates":[-2.513223,51.094442],"type":"Point"}
}
