{
  "type": "Feature",
  "properties": {
    "date:inception_lower": "1980-01-01",
    "date:inception_upper": "1980-01-01",
    "iso:country": "GB",
    "wof:name": "HP22 5AB",
    "wof:placetype": "postalcode"
  },
  "geometry": {"coordinates":[-0.763856,51.80918],"type":"Point"}
}
