{
  "type": "Feature",
  "properties": {
    "iso:country":"GB",
    "wof:name":"HP22 5AB",
    "wof:placetype":"postalcode"
},
  "geometry": {"coordinates":[-0.76385626221903,51.80918050055782],"type":"Point"}
}