{
  "type": "Feature",
  "properties": {
    "iso:country": "GB",
    "wof:name": "CM23 4PQ",
    "wof:placetype": "postalcode"
  },
  "geometry": {"coordinates":[0.135327,51.871421],"type":"Point"}
}
