{
  "type": "Feature",
  "properties": {
    "iso:country":"GB",
    "wof:name":"CM23 4PQ",
    "wof:placetype":"postalcode"
},
  "geometry": {"coordinates":[0.13532657227693,51.87142063722554],"type":"Point"}
}