{
  "type": "Feature",
  "properties": {
    "iso:country":"GB",
    "wof:name":"TW10 7AP",
    "wof:placetype":"postalcode"
},
  "geometry": {"coordinates":[-0.30203133165149,51.441780731469],"type":"Point"}
}