{
  "type": "Feature",
  "properties": {
    "iso:country": "GB",
    "wof:name": "HU10 6BU",
    "wof:placetype": "postalcode"
  },
  "geometry": {"coordinates":[-0.446758,53.758715],"type":"Point"}
}
