{
  "type": "Feature",
  "properties": {
    "iso:country":"GB",
    "wof:name":"HU10 6BU",
    "wof:placetype":"postalcode"
},
  "geometry": {"coordinates":[-0.44675769270873,53.75871521311617],"type":"Point"}
}