{
  "type": "Feature",
  "properties": {
    "iso:country":"GB",
    "wof:name":"LE12 7DH",
    "wof:placetype":"postalcode"
},
  "geometry": {"coordinates":[-1.13622210883176,52.72227508036448],"type":"Point"}
}