{
  "type": "Feature",
  "properties": {
    "date:inception_lower": "2017-03-01",
    "date:inception_upper": "2017-03-01",
    "iso:country": "GB",
    "wof:name": "CM1 6AZ",
    "wof:placetype": "postalcode"
  },
  "geometry": {"coordinates":[0.503777,51.762496],"type":"Point"}
}
