{
  "type": "Feature",
  "properties": {
    "iso:country":"GB",
    "wof:name":"RM7 9AL",
    "wof:placetype":"postalcode"
},
  "geometry": {"coordinates":[0.17164086325683,51.57345983893711],"type":"Point"}
}