{
  "type": "Feature",
  "properties": {
    "iso:country": "GB",
    "wof:name": "RM7 9AL",
    "wof:placetype": "postalcode"
  },
  "geometry": {"coordinates":[0.171695,51.573416],"type":"Point"}
}
