{
  "type": "Feature",
  "properties": {
    "iso:country":"GB",
    "wof:name":"WR14 4LD",
    "wof:placetype":"postalcode"
},
  "geometry": {"coordinates":[-2.3193146267966,52.06319827143078],"type":"Point"}
}