{
  "type": "Feature",
  "properties": {
    "date:inception_lower": "2014-08-01",
    "date:inception_upper": "2014-08-01",
    "iso:country": "GB",
    "wof:name": "GL1 1XB",
    "wof:placetype": "postalcode"
  },
  "geometry": {"coordinates":[-2.246861,51.859667],"type":"Point"}
}
