{
  "type": "Feature",
  "properties": {
    "iso:country":"GB",
    "wof:name":"GL1 1XB",
    "wof:placetype":"postalcode"
},
  "geometry": {"coordinates":[-2.24686391858879,51.85965951274292],"type":"Point"}
}