{
  "type": "Feature",
  "properties": {
    "date:inception_lower": "2021-07-01",
    "date:inception_upper": "2021-07-01",
    "iso:country": "GB",
    "wof:name": "HU10 7GE",
    "wof:placetype": "postalcode"
  },
  "geometry": {"coordinates":[-0.467,53.757423],"type":"Point"}
}
