{
  "type": "Feature",
  "properties": {
    "iso:country":"GB",
    "wof:name":"LE2 6HD",
    "wof:placetype":"postalcode"
},
  "geometry": {"coordinates":[-1.12579886127912,52.59624939301163],"type":"Point"}
}