{
  "type": "Feature",
  "properties": {
    "iso:country":"GB",
    "wof:name":"NR31 9DS",
    "wof:placetype":"postalcode"
},
  "geometry": {"coordinates":[1.675274055386,52.55506470699252],"type":"Point"}
}