{
  "type": "Feature",
  "properties": {
    "iso:country":"GB",
    "wof:name":"BD8 7JR",
    "wof:placetype":"postalcode"
},
  "geometry": {"coordinates":[-1.75870964513324,53.80320812219207],"type":"Point"}
}