{
  "type": "Feature",
  "properties": {
    "date:inception_lower": "1999-12-01",
    "date:inception_upper": "1999-12-01",
    "iso:country": "GB",
    "wof:name": "SE5 7TR",
    "wof:placetype": "postalcode"
  },
  "geometry": {"coordinates":[-0.085207,51.480481],"type":"Point"}
}
