{
  "type": "Feature",
  "properties": {
    "iso:country":"GB",
    "wof:name":"EN1 4SH",
    "wof:placetype":"postalcode"
},
  "geometry": {"coordinates":[-0.05303271985792,51.67864894605096],"type":"Point"}
}