{
  "type": "Feature",
  "properties": {
    "iso:country":"GB",
    "wof:name":"EX36 3HL",
    "wof:placetype":"postalcode"
},
  "geometry": {"coordinates":[-3.80504929203133,51.0530408290236],"type":"Point"}
}