{
  "type": "Feature",
  "properties": {
    "iso:country":"GB",
    "wof:name":"M6 8JD",
    "wof:placetype":"postalcode"
},
  "geometry": {"coordinates":[-2.32877400711131,53.48748514615551],"type":"Point"}
}