{
  "type": "Feature",
  "properties": {
    "date:inception_lower": "1980-01-01",
    "date:inception_upper": "1980-01-01",
    "iso:country": "GB",
    "wof:name": "M6 8JD",
    "wof:placetype": "postalcode"
  },
  "geometry": {"coordinates":[-2.328774,53.487485],"type":"Point"}
}
