{
  "type": "Feature",
  "properties": {
    "iso:country": "GB",
    "wof:name": "CH8 7PB",
    "wof:placetype": "postalcode"
  },
  "geometry": {"coordinates":[-3.195325,53.281689],"type":"Point"}
}
