{
  "type": "Feature",
  "properties": {
    "date:inception_lower": "1980-01-01",
    "date:inception_upper": "1980-01-01",
    "iso:country": "GB",
    "wof:name": "CH8 7PB",
    "wof:placetype": "postalcode"
  },
  "geometry": {"coordinates":[-3.195134,53.281806],"type":"Point"}
}
