{
  "type": "Feature",
  "properties": {
    "date:inception_lower": "1980-01-01",
    "date:inception_upper": "1980-01-01",
    "iso:country": "GB",
    "wof:name": "LA17 7XP",
    "wof:placetype": "postalcode"
  },
  "geometry": {"coordinates":[-3.158888,54.273798],"type":"Point"}
}
