{
  "type": "Feature",
  "properties": {
    "iso:country":"GB",
    "wof:name":"LA17 7XP",
    "wof:placetype":"postalcode"
},
  "geometry": {"coordinates":[-3.15866951908738,54.27371115882082],"type":"Point"}
}