{
  "type": "Feature",
  "properties": {
    "date:inception_lower":"1980-01-01",
    "date:inception_upper":"1980-01-31",
    "iso:country":"GB",
    "wof:name":"NG25 0PH",
    "wof:placetype":"postalcode"
},
  "geometry": {"coordinates":[-0.945074,53.104895],"type":"Point"}
}