{
  "type": "Feature",
  "properties": {
    "iso:country": "GB",
    "wof:name": "NG25 0PH",
    "wof:placetype": "postalcode"
  },
  "geometry": {"coordinates":[-0.945074,53.104895],"type":"Point"}
}
