{
  "type": "Feature",
  "properties": {
    "iso:country": "GB",
    "wof:name": "SE24 0GF",
    "wof:placetype": "postalcode"
  },
  "geometry": {"coordinates":[-0.102186,51.458922],"type":"Point"}
}
