{
  "type": "Feature",
  "properties": {
    "iso:country":"GB",
    "wof:name":"PL2 2NT",
    "wof:placetype":"postalcode"
},
  "geometry": {"coordinates":[-4.15985121968418,50.39896224258076],"type":"Point"}
}