{
  "type": "Feature",
  "properties": {
    "date:inception_lower":"1980-01-01",
    "date:inception_upper":"1980-01-31",
    "iso:country":"GB",
    "wof:name":"PL2 2NT",
    "wof:placetype":"postalcode"
},
  "geometry": {"coordinates":[-4.159851,50.398962],"type":"Point"}
}