{
  "type": "Feature",
  "properties": {
    "iso:country":"GB",
    "wof:name":"SG9 0RT",
    "wof:placetype":"postalcode"
},
  "geometry": {"coordinates":[-0.05013977132842,51.96966011313047],"type":"Point"}
}