{
  "type": "Feature",
  "properties": {
    "iso:country": "GB",
    "wof:name": "SG9 0RT",
    "wof:placetype": "postalcode"
  },
  "geometry": {"coordinates":[-0.050096,51.969687],"type":"Point"}
}
