{
  "type": "Feature",
  "properties": {
    "iso:country":"GB",
    "wof:name":"KY16 0BG",
    "wof:placetype":"postalcode"
},
  "geometry": {"coordinates":[-2.92693981130443,56.37985260313732],"type":"Point"}
}