{
  "type": "Feature",
  "properties": {
    "iso:country":"GB",
    "wof:name":"SO17 2LH",
    "wof:placetype":"postalcode"
},
  "geometry": {"coordinates":[-1.38436618731718,50.92702581570532],"type":"Point"}
}