{
  "type": "Feature",
  "properties": {
    "iso:country":"GB",
    "wof:name":"PR5 6QT",
    "wof:placetype":"postalcode"
},
  "geometry": {"coordinates":[-2.65958129715373,53.73194086539708],"type":"Point"}
}