{
  "type": "Feature",
  "properties": {
    "date:inception_lower": "1995-12-01",
    "date:inception_upper": "1995-12-01",
    "iso:country": "GB",
    "wof:name": "LN4 3YH",
    "wof:placetype": "postalcode"
  },
  "geometry": {"coordinates":[-0.402574,53.144161],"type":"Point"}
}
