{
  "type": "Feature",
  "properties": {
    "iso:country":"GB",
    "wof:name":"LN4 3YH",
    "wof:placetype":"postalcode"
},
  "geometry": {"coordinates":[-0.40257431189807,53.14416121316932],"type":"Point"}
}