{
  "type": "Feature",
  "properties": {
    "iso:country":"GB",
    "wof:name":"AL2 3EN",
    "wof:placetype":"postalcode"
},
  "geometry": {"coordinates":[-0.36504206250567,51.72207206568245],"type":"Point"}
}