{
  "type": "Feature",
  "properties": {
    "iso:country": "GB",
    "wof:name": "AL2 3EN",
    "wof:placetype": "postalcode"
  },
  "geometry": {"coordinates":[-0.365042,51.722072],"type":"Point"}
}
