{
  "type": "Feature",
  "properties": {
    "date:inception_lower":"1995-07-01",
    "date:inception_upper":"1995-07-31",
    "iso:country":"GB",
    "wof:name":"AL2 3EN",
    "wof:placetype":"postalcode"
},
  "geometry": {"coordinates":[-0.365042,51.722072],"type":"Point"}
}