{
  "type": "Feature",
  "properties": {
    "iso:country":"GB",
    "wof:name":"DE55 2EZ",
    "wof:placetype":"postalcode"
},
  "geometry": {"coordinates":[-1.33504375125513,53.1102735636385],"type":"Point"}
}