{
  "type": "Feature",
  "properties": {
    "date:inception_lower": "1980-01-01",
    "date:inception_upper": "1980-01-01",
    "iso:country": "GB",
    "wof:name": "LS23 6HR",
    "wof:placetype": "postalcode"
  },
  "geometry": {"coordinates":[-1.348601,53.89293],"type":"Point"}
}
