{
  "type": "Feature",
  "properties": {
    "iso:country":"GB",
    "wof:name":"LS23 6HR",
    "wof:placetype":"postalcode"
},
  "geometry": {"coordinates":[-1.34860092692191,53.89292956289704],"type":"Point"}
}