{
  "type": "Feature",
  "properties": {
    "iso:country": "GB",
    "wof:name": "PE11 3BN",
    "wof:placetype": "postalcode"
  },
  "geometry": {"coordinates":[-0.186824,52.747192],"type":"Point"}
}
