{
  "type": "Feature",
  "properties": {
    "date:inception_lower": "1997-06-01",
    "date:inception_upper": "1997-06-01",
    "iso:country": "GB",
    "wof:name": "EN1 3RR",
    "wof:placetype": "postalcode"
  },
  "geometry": {"coordinates":[-0.0578,51.650432],"type":"Point"}
}
