{
  "type": "Feature",
  "properties": {
    "iso:country":"GB",
    "wof:name":"LS19 6NY",
    "wof:placetype":"postalcode"
},
  "geometry": {"coordinates":[-1.67442457161522,53.84834438707454],"type":"Point"}
}