{
  "type": "Feature",
  "properties": {
    "iso:country":"GB",
    "wof:name":"OX18 1TQ",
    "wof:placetype":"postalcode"
},
  "geometry": {"coordinates":[-1.59597047545087,51.76882140766823],"type":"Point"}
}