{
  "type": "Feature",
  "properties": {
    "iso:country": "GB",
    "wof:name": "SW1Y 4JZ",
    "wof:placetype": "postalcode"
  },
  "geometry": {"coordinates":[-0.135835,51.506477],"type":"Point"}
}
