{
  "type": "Feature",
  "properties": {
    "iso:country":"GB",
    "wof:name":"BB7 9DF",
    "wof:placetype":"postalcode"
},
  "geometry": {"coordinates":[-2.38862863414237,53.8320128224108],"type":"Point"}
}