{
  "type": "Feature",
  "properties": {
    "iso:country": "GB",
    "wof:name": "BB7 9DF",
    "wof:placetype": "postalcode"
  },
  "geometry": {"coordinates":[-2.388629,53.832013],"type":"Point"}
}
