{
  "type": "Feature",
  "properties": {
    "iso:country":"GB",
    "wof:name":"ME9 9QW",
    "wof:placetype":"postalcode"
},
  "geometry": {"coordinates":[0.80359885557186,51.32715067996211],"type":"Point"}
}