{
  "type": "Feature",
  "properties": {
    "iso:country": "GB",
    "wof:name": "ME9 9QW",
    "wof:placetype": "postalcode"
  },
  "geometry": {"coordinates":[0.803599,51.327151],"type":"Point"}
}
