{
  "type": "Feature",
  "properties": {
    "iso:country": "GB",
    "wof:name": "EX8 3PZ",
    "wof:placetype": "postalcode"
  },
  "geometry": {"coordinates":[-3.40261,50.626666],"type":"Point"}
}
