{
  "type": "Feature",
  "properties": {
    "iso:country":"GB",
    "wof:name":"DD5 4TA",
    "wof:placetype":"postalcode"
},
  "geometry": {"coordinates":[-2.81508298028081,56.48926884800697],"type":"Point"}
}