{
  "type": "Feature",
  "properties": {
    "date:inception_lower": "2019-07-01",
    "date:inception_upper": "2019-07-01",
    "iso:country": "GB",
    "wof:name": "SR3 2FZ",
    "wof:placetype": "postalcode"
  },
  "geometry": {"coordinates":[-1.424742,54.861315],"type":"Point"}
}
