{
  "type": "Feature",
  "properties": {
    "iso:country": "GB",
    "wof:name": "SR3 2FZ",
    "wof:placetype": "postalcode"
  },
  "geometry": {"coordinates":[-1.42368,54.860366],"type":"Point"}
}
