{
  "type": "Feature",
  "properties": {
    "date:inception_lower": "1980-01-01",
    "date:inception_upper": "1980-01-01",
    "iso:country": "GB",
    "wof:name": "LN13 9LB",
    "wof:placetype": "postalcode"
  },
  "geometry": {"coordinates":[0.258402,53.239199],"type":"Point"}
}
