{
  "type": "Feature",
  "properties": {
    "iso:country":"GB",
    "wof:name":"S26 7XB",
    "wof:placetype":"postalcode"
},
  "geometry": {"coordinates":[-1.26470019271461,53.3200508881346],"type":"Point"}
}