{
  "type": "Feature",
  "properties": {
    "iso:country":"GB",
    "wof:name":"SA15 3EF",
    "wof:placetype":"postalcode"
},
  "geometry": {"coordinates":[-4.17054643540238,51.68658095873424],"type":"Point"}
}