{
  "type": "Feature",
  "properties": {
    "iso:country": "GB",
    "wof:name": "SA15 3EF",
    "wof:placetype": "postalcode"
  },
  "geometry": {"coordinates":[-4.170546,51.686581],"type":"Point"}
}
