{
  "type": "Feature",
  "properties": {
    "iso:country":"GB",
    "wof:name":"TN8 5PE",
    "wof:placetype":"postalcode"
},
  "geometry": {"coordinates":[0.11223941946586,51.15761019355813],"type":"Point"}
}