{
  "type": "Feature",
  "properties": {
    "iso:country":"GB",
    "wof:name":"CV5 7BT",
    "wof:placetype":"postalcode"
},
  "geometry": {"coordinates":[-1.57647660052847,52.41079969483136],"type":"Point"}
}