{
  "type": "Feature",
  "properties": {
    "iso:country":"GB",
    "wof:name":"NN16 9UD",
    "wof:placetype":"postalcode"
},
  "geometry": {"coordinates":[-0.70641242042268,52.40778277054042],"type":"Point"}
}