{
  "type": "Feature",
  "properties": {
    "iso:country":"GB",
    "wof:name":"RH19 4EN",
    "wof:placetype":"postalcode"
},
  "geometry": {"coordinates":[-0.01338951414849,51.12381212507933],"type":"Point"}
}