{
  "type": "Feature",
  "properties": {
    "iso:country": "GB",
    "wof:name": "CT7 9PF",
    "wof:placetype": "postalcode"
  },
  "geometry": {"coordinates":[1.288573,51.379291],"type":"Point"}
}
