{
  "type": "Feature",
  "properties": {
    "iso:country":"GB",
    "wof:name":"CT7 9PF",
    "wof:placetype":"postalcode"
},
  "geometry": {"coordinates":[1.28857323445777,51.37929129315292],"type":"Point"}
}