{
  "type": "Feature",
  "properties": {
    "iso:country": "GB",
    "wof:name": "BS39 5SW",
    "wof:placetype": "postalcode"
  },
  "geometry": {"coordinates":[-2.540197,51.329147],"type":"Point"}
}
