{
  "type": "Feature",
  "properties": {
    "iso:country":"GB",
    "wof:name":"NN8 2HB",
    "wof:placetype":"postalcode"
},
  "geometry": {"coordinates":[-0.70739262450974,52.29066217856514],"type":"Point"}
}