{
  "type": "Feature",
  "properties": {
    "iso:country":"GB",
    "wof:name":"LL18 5LA",
    "wof:placetype":"postalcode"
},
  "geometry": {"coordinates":[-3.5202541773976,53.30315895170921],"type":"Point"}
}