{
  "type": "Feature",
  "properties": {
    "date:inception_lower":"2006-01-01",
    "date:inception_upper":"2006-01-31",
    "iso:country":"GB",
    "wof:name":"HP22 5WQ",
    "wof:placetype":"postalcode"
},
  "geometry": {"coordinates":[-0.783684,51.796835],"type":"Point"}
}