{
  "type": "Feature",
  "properties": {
    "iso:country":"GB",
    "wof:name":"WF17 9PG",
    "wof:placetype":"postalcode"
},
  "geometry": {"coordinates":[-1.66600303924463,53.73177369814144],"type":"Point"}
}