{
  "type": "Feature",
  "properties": {
    "iso:country":"GB",
    "wof:name":"S5 8TF",
    "wof:placetype":"postalcode"
},
  "geometry": {"coordinates":[-1.48464379802894,53.41437115477984],"type":"Point"}
}