{
  "type": "Feature",
  "properties": {
    "iso:country":"GB",
    "wof:name":"CM77 8JN",
    "wof:placetype":"postalcode"
},
  "geometry": {"coordinates":[0.58331338774273,51.85501439086896],"type":"Point"}
}