{
  "type": "Feature",
  "properties": {
    "iso:country": "GB",
    "wof:name": "CM77 8JN",
    "wof:placetype": "postalcode"
  },
  "geometry": {"coordinates":[0.583313,51.855014],"type":"Point"}
}
