{
  "type": "Feature",
  "properties": {
    "iso:country":"GB",
    "wof:name":"WA9 1HH",
    "wof:placetype":"postalcode"
},
  "geometry": {"coordinates":[-2.70494574866012,53.45585350018254],"type":"Point"}
}