{
  "type": "Feature",
  "properties": {
    "date:inception_lower": "2009-08-01",
    "date:inception_upper": "2009-08-01",
    "iso:country": "GB",
    "wof:name": "WA9 1HH",
    "wof:placetype": "postalcode"
  },
  "geometry": {"coordinates":[-2.704946,53.455853],"type":"Point"}
}
