{
  "type": "Feature",
  "properties": {
    "date:inception_lower": "1980-01-01",
    "date:inception_upper": "1980-01-01",
    "iso:country": "GB",
    "wof:name": "BA1 3JR",
    "wof:placetype": "postalcode"
  },
  "geometry": {"coordinates":[-2.394952,51.383066],"type":"Point"}
}
