{
  "type": "Feature",
  "properties": {
    "iso:country": "GB",
    "wof:name": "BA1 3JR",
    "wof:placetype": "postalcode"
  },
  "geometry": {"coordinates":[-2.394952,51.383066],"type":"Point"}
}
