{
  "type": "Feature",
  "properties": {
    "iso:country":"GB",
    "wof:name":"TS28 5LD",
    "wof:placetype":"postalcode"
},
  "geometry": {"coordinates":[-1.37770423434052,54.7381999288222],"type":"Point"}
}