{
  "type": "Feature",
  "properties": {
    "date:inception_lower": "1980-01-01",
    "date:inception_upper": "1980-01-01",
    "iso:country": "GB",
    "wof:name": "TS28 5LD",
    "wof:placetype": "postalcode"
  },
  "geometry": {"coordinates":[-1.377662,54.737903],"type":"Point"}
}
