{
  "type": "Feature",
  "properties": {
    "iso:country":"GB",
    "wof:name":"DY4 0JL",
    "wof:placetype":"postalcode"
},
  "geometry": {"coordinates":[-2.0410313670364,52.5374545372934],"type":"Point"}
}