{
  "type": "Feature",
  "properties": {
    "iso:country": "GB",
    "wof:name": "DY4 0JL",
    "wof:placetype": "postalcode"
  },
  "geometry": {"coordinates":[-2.041031,52.537455],"type":"Point"}
}
