{
  "type": "Feature",
  "properties": {
    "date:inception_lower": "1980-01-01",
    "date:inception_upper": "1980-01-01",
    "iso:country": "GB",
    "wof:name": "DY4 0JL",
    "wof:placetype": "postalcode"
  },
  "geometry": {"coordinates":[-2.041031,52.537455],"type":"Point"}
}
