{
  "type": "Feature",
  "properties": {
    "date:inception_lower": "1980-01-01",
    "date:inception_upper": "1980-01-01",
    "iso:country": "GB",
    "wof:name": "LL55 4LU",
    "wof:placetype": "postalcode"
  },
  "geometry": {"coordinates":[-4.100603,53.012309],"type":"Point"}
}
