{
  "type": "Feature",
  "properties": {
    "iso:country":"GB",
    "wof:name":"LL55 4LU",
    "wof:placetype":"postalcode"
},
  "geometry": {"coordinates":[-4.10059658158379,53.01229287926322],"type":"Point"}
}