{
  "type": "Feature",
  "properties": {
    "date:inception_lower": "2017-05-01",
    "date:inception_upper": "2017-05-01",
    "iso:country": "GB",
    "wof:name": "DY11 7DZ",
    "wof:placetype": "postalcode"
  },
  "geometry": {"coordinates":[-2.25496,52.370696],"type":"Point"}
}
