{
  "type": "Feature",
  "properties": {
    "iso:country":"GB",
    "wof:name":"RH9 8HA",
    "wof:placetype":"postalcode"
},
  "geometry": {"coordinates":[-0.04892173483717,51.21823527754216],"type":"Point"}
}