{
  "type": "Feature",
  "properties": {
    "date:inception_lower": "1980-01-01",
    "date:inception_upper": "1980-01-01",
    "iso:country": "GB",
    "wof:name": "KY11 2HX",
    "wof:placetype": "postalcode"
  },
  "geometry": {"coordinates":[-3.422842,56.025871],"type":"Point"}
}
