{
  "type": "Feature",
  "properties": {
    "iso:country": "GB",
    "wof:name": "NW8 8PS",
    "wof:placetype": "postalcode"
  },
  "geometry": {"coordinates":[-0.173354,51.522703],"type":"Point"}
}
