{
  "type": "Feature",
  "properties": {
    "iso:country": "GB",
    "wof:name": "NN5 4FS",
    "wof:placetype": "postalcode"
  },
  "geometry": {"coordinates":[-0.944246,52.235033],"type":"Point"}
}
