{
  "type": "Feature",
  "properties": {
    "iso:country":"GB",
    "wof:name":"NE38 8PF",
    "wof:placetype":"postalcode"
},
  "geometry": {"coordinates":[-1.51033364480946,54.88317655019568],"type":"Point"}
}