{
  "type": "Feature",
  "properties": {
    "iso:country":"GB",
    "wof:name":"OL2 7BT",
    "wof:placetype":"postalcode"
},
  "geometry": {"coordinates":[-2.10057255073104,53.57609829275786],"type":"Point"}
}