{
  "type": "Feature",
  "properties": {
    "date:inception_lower": "1980-01-01",
    "date:inception_upper": "1980-01-01",
    "iso:country": "GB",
    "wof:name": "OL2 7BT",
    "wof:placetype": "postalcode"
  },
  "geometry": {"coordinates":[-2.100573,53.576098],"type":"Point"}
}
