{
  "type": "Feature",
  "properties": {
    "iso:country":"GB",
    "wof:name":"SL6 0JB",
    "wof:placetype":"postalcode"
},
  "geometry": {"coordinates":[-0.68193448865674,51.55045293350406],"type":"Point"}
}