{
  "type": "Feature",
  "properties": {
    "iso:country": "GB",
    "wof:name": "SL6 0JB",
    "wof:placetype": "postalcode"
  },
  "geometry": {"coordinates":[-0.681934,51.550453],"type":"Point"}
}
