{
  "type": "Feature",
  "properties": {
    "date:inception_lower":"1999-06-01",
    "date:inception_upper":"1999-06-30",
    "iso:country":"GB",
    "wof:name":"NP26 5AH",
    "wof:placetype":"postalcode"
},
  "geometry": {"coordinates":[-2.771655,51.596226],"type":"Point"}
}