{
  "type": "Feature",
  "properties": {
    "iso:country":"GB",
    "wof:name":"HD6 2JP",
    "wof:placetype":"postalcode"
},
  "geometry": {"coordinates":[-1.79059866599534,53.71096084955237],"type":"Point"}
}