{
  "type": "Feature",
  "properties": {
    "date:inception_lower":"1985-04-01",
    "date:inception_upper":"1985-04-30",
    "iso:country":"GB",
    "wof:name":"CV31 1YF",
    "wof:placetype":"postalcode"
},
  "geometry": {"coordinates":[-1.512501,52.275903],"type":"Point"}
}