{
  "type": "Feature",
  "properties": {
    "iso:country":"GB",
    "wof:name":"NW6 7UP",
    "wof:placetype":"postalcode"
},
  "geometry": {"coordinates":[-0.19889007323264,51.54006683202197],"type":"Point"}
}