{
  "type": "Feature",
  "properties": {
    "iso:country": "GB",
    "wof:name": "LL12 0NT",
    "wof:placetype": "postalcode"
  },
  "geometry": {"coordinates":[-2.998066,53.099662],"type":"Point"}
}
