{
  "type": "Feature",
  "properties": {
    "iso:country":"GB",
    "wof:name":"PH3 1BT",
    "wof:placetype":"postalcode"
},
  "geometry": {"coordinates":[-3.70481074182392,56.2941110771298],"type":"Point"}
}