{
  "type": "Feature",
  "properties": {
    "iso:country": "GB",
    "wof:name": "PH3 1BT",
    "wof:placetype": "postalcode"
  },
  "geometry": {"coordinates":[-3.704811,56.294111],"type":"Point"}
}
