{
  "type": "Feature",
  "properties": {
    "iso:country":"GB",
    "wof:name":"WN2 5JE",
    "wof:placetype":"postalcode"
},
  "geometry": {"coordinates":[-2.59904541205878,53.51678985880501],"type":"Point"}
}