{
  "type": "Feature",
  "properties": {
    "iso:country":"GB",
    "wof:name":"PA77 6TS",
    "wof:placetype":"postalcode"
},
  "geometry": {"coordinates":[-6.74486041212313,56.54132410814768],"type":"Point"}
}