{
  "type": "Feature",
  "properties": {
    "iso:country":"GB",
    "wof:name":"SA72 6XS",
    "wof:placetype":"postalcode"
},
  "geometry": {"coordinates":[-4.95086050098949,51.69221390344619],"type":"Point"}
}