{
  "type": "Feature",
  "properties": {
    "iso:country":"GB",
    "wof:name":"HP11 1AS",
    "wof:placetype":"postalcode"
},
  "geometry": {"coordinates":[-0.71151738534676,51.6167456819891],"type":"Point"}
}