{
  "type": "Feature",
  "properties": {
    "date:inception_lower":"1980-01-01",
    "date:inception_upper":"1980-01-31",
    "iso:country":"GB",
    "wof:name":"HR1 4ES",
    "wof:placetype":"postalcode"
},
  "geometry": {"coordinates":[-2.609541,52.058413],"type":"Point"}
}