{
  "type": "Feature",
  "properties": {
    "iso:country":"GB",
    "wof:name":"HR1 4ES",
    "wof:placetype":"postalcode"
},
  "geometry": {"coordinates":[-2.60954073061735,52.05841275895528],"type":"Point"}
}