{
  "type": "Feature",
  "properties": {
    "iso:country": "GB",
    "wof:name": "HR1 4ES",
    "wof:placetype": "postalcode"
  },
  "geometry": {"coordinates":[-2.609541,52.058413],"type":"Point"}
}
