{
  "type": "Feature",
  "properties": {
    "iso:country": "GB",
    "wof:name": "PH37 4LU",
    "wof:placetype": "postalcode"
  },
  "geometry": {"coordinates":[-5.540581,56.802388],"type":"Point"}
}
