{
  "type": "Feature",
  "properties": {
    "iso:country":"GB",
    "wof:name":"B23 7YR",
    "wof:placetype":"postalcode"
},
  "geometry": {"coordinates":[-1.86973425274224,52.52063320554],"type":"Point"}
}