{
  "type": "Feature",
  "properties": {
    "iso:country":"GB",
    "wof:name":"SA5 7JN",
    "wof:placetype":"postalcode"
},
  "geometry": {"coordinates":[-3.96967895547764,51.65189554304506],"type":"Point"}
}