{
  "type": "Feature",
  "properties": {
    "iso:country":"GB",
    "wof:name":"TA10 0NJ",
    "wof:placetype":"postalcode"
},
  "geometry": {"coordinates":[-2.84270117921414,51.0360590544062],"type":"Point"}
}