{
  "type": "Feature",
  "properties": {
    "iso:country":"GB",
    "wof:name":"YO16 4QA",
    "wof:placetype":"postalcode"
},
  "geometry": {"coordinates":[-0.20848394403242,54.09348909252762],"type":"Point"}
}