{
  "type": "Feature",
  "properties": {
    "iso:country":"GB",
    "wof:name":"ST5 2JY",
    "wof:placetype":"postalcode"
},
  "geometry": {"coordinates":[-2.24429700117947,53.00816175265549],"type":"Point"}
}