{
  "type": "Feature",
  "properties": {
    "iso:country":"GB",
    "wof:name":"BL4 9SP",
    "wof:placetype":"postalcode"
},
  "geometry": {"coordinates":[-2.40899253134519,53.5403681322784],"type":"Point"}
}