{
  "type": "Feature",
  "properties": {
    "iso:country":"GB",
    "wof:name":"W1H 7NS",
    "wof:placetype":"postalcode"
},
  "geometry": {"coordinates":[-0.16110434951103,51.51583945126959],"type":"Point"}
}