{
  "type": "Feature",
  "properties": {
    "iso:country":"GB",
    "wof:name":"SO21 3EL",
    "wof:placetype":"postalcode"
},
  "geometry": {"coordinates":[-1.32749535213818,51.11919308801617],"type":"Point"}
}