{
  "type": "Feature",
  "properties": {
    "iso:country":"GB",
    "wof:name":"NW10 5HS",
    "wof:placetype":"postalcode"
},
  "geometry": {"coordinates":[-0.22672167705742,51.53560795094837],"type":"Point"}
}