{
  "type": "Feature",
  "properties": {
    "iso:country":"GB",
    "wof:name":"M21 9FQ",
    "wof:placetype":"postalcode"
},
  "geometry": {"coordinates":[-2.28228623661981,53.43840106835226],"type":"Point"}
}