{
  "type": "Feature",
  "properties": {
    "date:inception_lower":"2001-06-01",
    "date:inception_upper":"2001-06-30",
    "iso:country":"GB",
    "wof:name":"LD7 1HQ",
    "wof:placetype":"postalcode"
},
  "geometry": {"coordinates":[-3.055302,52.341862],"type":"Point"}
}