{
  "type": "Feature",
  "properties": {
    "iso:country":"GB",
    "wof:name":"LD7 1HQ",
    "wof:placetype":"postalcode"
},
  "geometry": {"coordinates":[-3.05530174938613,52.34186184899743],"type":"Point"}
}