{
  "type": "Feature",
  "properties": {
    "date:inception_lower": "1980-01-01",
    "date:inception_upper": "1980-01-01",
    "iso:country": "GB",
    "wof:name": "GU34 5QA",
    "wof:placetype": "postalcode"
  },
  "geometry": {"coordinates":[-1.089192,51.11764],"type":"Point"}
}
