{
  "type": "Feature",
  "properties": {
    "date:inception_lower":"1980-01-01",
    "date:inception_upper":"1980-01-31",
    "iso:country":"GB",
    "wof:name":"B71 1AJ",
    "wof:placetype":"postalcode"
},
  "geometry": {"coordinates":[-1.990875,52.532922],"type":"Point"}
}