{
  "type": "Feature",
  "properties": {
    "iso:country":"GB",
    "wof:name":"B71 1AJ",
    "wof:placetype":"postalcode"
},
  "geometry": {"coordinates":[-1.99087553404627,52.53292152225037],"type":"Point"}
}