{
  "type": "Feature",
  "properties": {
    "date:inception_lower": "1980-01-01",
    "date:inception_upper": "1980-01-01",
    "iso:country": "GB",
    "wof:name": "SA12 9AR",
    "wof:placetype": "postalcode"
  },
  "geometry": {"coordinates":[-3.761924,51.613671],"type":"Point"}
}
