{
  "type": "Feature",
  "properties": {
    "iso:country":"GB",
    "wof:name":"SA12 9AR",
    "wof:placetype":"postalcode"
},
  "geometry": {"coordinates":[-3.76192382695004,51.61367147069689],"type":"Point"}
}