{
  "type": "Feature",
  "properties": {
    "iso:country": "GB",
    "wof:name": "IP12 2TB",
    "wof:placetype": "postalcode"
  },
  "geometry": {"coordinates":[1.418773,52.132438],"type":"Point"}
}
