{
  "type": "Feature",
  "properties": {
    "iso:country":"GB",
    "wof:name":"IP12 2TB",
    "wof:placetype":"postalcode"
},
  "geometry": {"coordinates":[1.41877267483949,52.13243843763465],"type":"Point"}
}