{
  "type": "Feature",
  "properties": {
    "date:inception_lower": "1982-03-01",
    "date:inception_upper": "1982-03-01",
    "iso:country": "GB",
    "wof:name": "IP12 2TB",
    "wof:placetype": "postalcode"
  },
  "geometry": {"coordinates":[1.418773,52.132438],"type":"Point"}
}
