{
  "type": "Feature",
  "properties": {
    "iso:country":"GB",
    "wof:name":"LN2 5BU",
    "wof:placetype":"postalcode"
},
  "geometry": {"coordinates":[-0.53410665857099,53.22968193079181],"type":"Point"}
}