{
  "type": "Feature",
  "properties": {
    "date:inception_lower": "2006-02-01",
    "date:inception_upper": "2006-02-01",
    "iso:country": "GB",
    "wof:name": "LN2 5BU",
    "wof:placetype": "postalcode"
  },
  "geometry": {"coordinates":[-0.534107,53.229682],"type":"Point"}
}
