{
  "type": "Feature",
  "properties": {
    "iso:country": "GB",
    "wof:name": "SA19 8LN",
    "wof:placetype": "postalcode"
  },
  "geometry": {"coordinates":[-3.900948,51.95646],"type":"Point"}
}
