{
  "type": "Feature",
  "properties": {
    "iso:country":"GB",
    "wof:name":"RH5 5QT",
    "wof:placetype":"postalcode"
},
  "geometry": {"coordinates":[-0.38976813024226,51.13202891070154],"type":"Point"}
}