{
  "type": "Feature",
  "properties": {
    "date:inception_lower":"1980-01-01",
    "date:inception_upper":"1980-01-31",
    "iso:country":"GB",
    "wof:name":"RH5 5QT",
    "wof:placetype":"postalcode"
},
  "geometry": {"coordinates":[-0.389743,51.132025],"type":"Point"}
}