{
  "type": "Feature",
  "properties": {
    "iso:country": "GB",
    "wof:name": "RH5 5QT",
    "wof:placetype": "postalcode"
  },
  "geometry": {"coordinates":[-0.389743,51.132025],"type":"Point"}
}
