{
  "type": "Feature",
  "properties": {
    "iso:country":"GB",
    "wof:name":"LA10 5BW",
    "wof:placetype":"postalcode"
},
  "geometry": {"coordinates":[-2.5285651472212,54.32362353467243],"type":"Point"}
}