{
  "type": "Feature",
  "properties": {
    "date:inception_lower": "1981-06-01",
    "date:inception_upper": "1981-06-01",
    "iso:country": "GB",
    "wof:name": "MK18 4HE",
    "wof:placetype": "postalcode"
  },
  "geometry": {"coordinates":[-1.033317,51.933921],"type":"Point"}
}
