{
  "type": "Feature",
  "properties": {
    "iso:country": "GB",
    "wof:name": "MK18 4HE",
    "wof:placetype": "postalcode"
  },
  "geometry": {"coordinates":[-1.033317,51.933921],"type":"Point"}
}
