{
  "type": "Feature",
  "properties": {
    "iso:country":"GB",
    "wof:name":"MK18 4HE",
    "wof:placetype":"postalcode"
},
  "geometry": {"coordinates":[-1.03331686743635,51.93392106630429],"type":"Point"}
}