{
  "type": "Feature",
  "properties": {
    "date:inception_lower": "2018-06-01",
    "date:inception_upper": "2018-06-01",
    "iso:country": "GB",
    "wof:name": "SE17 1EN",
    "wof:placetype": "postalcode"
  },
  "geometry": {"coordinates":[-0.097836,51.494356],"type":"Point"}
}
