{
  "type": "Feature",
  "properties": {
    "date:inception_lower": "1980-01-01",
    "date:inception_upper": "1980-01-01",
    "iso:country": "GB",
    "wof:name": "EH1 1JN",
    "wof:placetype": "postalcode"
  },
  "geometry": {"coordinates":[-3.190513,55.948528],"type":"Point"}
}
