{
  "type": "Feature",
  "properties": {
    "iso:country":"GB",
    "wof:name":"M6 8AY",
    "wof:placetype":"postalcode"
},
  "geometry": {"coordinates":[-2.31854392571357,53.49189923956603],"type":"Point"}
}