{
  "type": "Feature",
  "properties": {
    "iso:country": "GB",
    "wof:name": "TQ3 1PN",
    "wof:placetype": "postalcode"
  },
  "geometry": {"coordinates":[-3.600231,50.457997],"type":"Point"}
}
