{
  "type": "Feature",
  "properties": {
    "iso:country":"GB",
    "wof:name":"WA5 0DG",
    "wof:placetype":"postalcode"
},
  "geometry": {"coordinates":[-2.60410320026768,53.40263599803063],"type":"Point"}
}