{
  "type": "Feature",
  "properties": {
    "date:inception_lower":"2015-11-01",
    "date:inception_upper":"2015-11-30",
    "iso:country":"GB",
    "wof:name":"GL14 3FA",
    "wof:placetype":"postalcode"
},
  "geometry": {"coordinates":[-2.50545,51.811618],"type":"Point"}
}