{
  "type": "Feature",
  "properties": {
    "iso:country":"GB",
    "wof:name":"GL14 3FA",
    "wof:placetype":"postalcode"
},
  "geometry": {"coordinates":[-2.50549490420984,51.81179991834954],"type":"Point"}
}