{
  "type": "Feature",
  "properties": {
    "iso:country": "GB",
    "wof:name": "GL14 3FA",
    "wof:placetype": "postalcode"
  },
  "geometry": {"coordinates":[-2.50545,51.811618],"type":"Point"}
}
