{
  "type": "Feature",
  "properties": {
    "iso:country": "GB",
    "wof:name": "NG17 3DH",
    "wof:placetype": "postalcode"
  },
  "geometry": {"coordinates":[-1.242677,53.140052],"type":"Point"}
}
