{
  "type": "Feature",
  "properties": {
    "iso:country": "GB",
    "wof:name": "AB42 2UA",
    "wof:placetype": "postalcode"
  },
  "geometry": {"coordinates":[-1.818898,57.506731],"type":"Point"}
}
