{
  "type": "Feature",
  "properties": {
    "date:inception_lower": "2009-11-01",
    "date:inception_upper": "2009-11-01",
    "iso:country": "GB",
    "wof:name": "AB42 2UA",
    "wof:placetype": "postalcode"
  },
  "geometry": {"coordinates":[-1.818898,57.506731],"type":"Point"}
}
