{
  "type": "Feature",
  "properties": {
    "iso:country":"GB",
    "wof:name":"EH25 9NJ",
    "wof:placetype":"postalcode"
},
  "geometry": {"coordinates":[-3.17219222924057,55.85628313992072],"type":"Point"}
}