{
  "type": "Feature",
  "properties": {
    "iso:country":"GB",
    "wof:name":"AL1 2ET",
    "wof:placetype":"postalcode"
},
  "geometry": {"coordinates":[-0.3328482282495,51.73963965446634],"type":"Point"}
}