{
  "type": "Feature",
  "properties": {
    "date:inception_lower": "1992-08-01",
    "date:inception_upper": "1992-08-01",
    "iso:country": "GB",
    "wof:name": "EC2Y 8PQ",
    "wof:placetype": "postalcode"
  },
  "geometry": {"coordinates":[-0.093767,51.521374],"type":"Point"}
}
