{
  "type": "Feature",
  "properties": {
    "iso:country":"GB",
    "wof:name":"S36 1BN",
    "wof:placetype":"postalcode"
},
  "geometry": {"coordinates":[-1.59696219407198,53.48199215318093],"type":"Point"}
}