{
  "type": "Feature",
  "properties": {
    "date:inception_lower":"1997-06-01",
    "date:inception_upper":"1997-06-30",
    "iso:country":"GB",
    "wof:name":"S36 1BN",
    "wof:placetype":"postalcode"
},
  "geometry": {"coordinates":[-1.596962,53.481992],"type":"Point"}
}