{
  "type": "Feature",
  "properties": {
    "date:inception_lower":"1980-01-01",
    "date:inception_upper":"1980-01-31",
    "iso:country":"GB",
    "wof:name":"NE61 2SA",
    "wof:placetype":"postalcode"
},
  "geometry": {"coordinates":[-1.677857,55.159252],"type":"Point"}
}