{
  "type": "Feature",
  "properties": {
    "iso:country":"GB",
    "wof:name":"NE61 2SA",
    "wof:placetype":"postalcode"
},
  "geometry": {"coordinates":[-1.67785727861968,55.15925187522342],"type":"Point"}
}