{
  "type": "Feature",
  "properties": {
    "date:inception_lower": "1980-01-01",
    "date:inception_upper": "1980-01-01",
    "iso:country": "GB",
    "wof:name": "BH21 5RD",
    "wof:placetype": "postalcode"
  },
  "geometry": {"coordinates":[-1.921454,50.90766],"type":"Point"}
}
