{
  "type": "Feature",
  "properties": {
    "iso:country":"GB",
    "wof:name":"EX6 7DH",
    "wof:placetype":"postalcode"
},
  "geometry": {"coordinates":[-3.70973986945489,50.69238841782945],"type":"Point"}
}