{
  "type": "Feature",
  "properties": {
    "iso:country": "GB",
    "wof:name": "PA29 6UB",
    "wof:placetype": "postalcode"
  },
  "geometry": {"coordinates":[-5.413519,55.863251],"type":"Point"}
}
