{
  "type": "Feature",
  "properties": {
    "iso:country":"GB",
    "wof:name":"IP17 1HE",
    "wof:placetype":"postalcode"
},
  "geometry": {"coordinates":[1.48984971090379,52.20285047159555],"type":"Point"}
}