{
  "type": "Feature",
  "properties": {
    "date:inception_lower": "1980-01-01",
    "date:inception_upper": "1980-01-01",
    "iso:country": "GB",
    "wof:name": "KT3 4PP",
    "wof:placetype": "postalcode"
  },
  "geometry": {"coordinates":[-0.236848,51.404399],"type":"Point"}
}
