{
  "type": "Feature",
  "properties": {
    "iso:country":"GB",
    "wof:name":"KT3 4PP",
    "wof:placetype":"postalcode"
},
  "geometry": {"coordinates":[-0.23684817832837,51.40439873352018],"type":"Point"}
}