{
  "type": "Feature",
  "properties": {
    "iso:country":"GB",
    "wof:name":"NP19 7GA",
    "wof:placetype":"postalcode"
},
  "geometry": {"coordinates":[-2.97976626590817,51.59590414959302],"type":"Point"}
}