{
  "type": "Feature",
  "properties": {
    "date:inception_lower":"2011-07-01",
    "date:inception_upper":"2011-07-31",
    "iso:country":"GB",
    "wof:name":"NE10 0BD",
    "wof:placetype":"postalcode"
},
  "geometry": {"coordinates":[-1.577758,54.953757],"type":"Point"}
}