{
  "type": "Feature",
  "properties": {
    "date:inception_lower": "2023-11-01",
    "date:inception_upper": "2023-11-01",
    "iso:country": "GB",
    "wof:name": "EX2 0BZ",
    "wof:placetype": "postalcode"
  },
  "geometry": {"coordinates":[-3.525551,50.687973],"type":"Point"}
}
