{
  "type": "Feature",
  "properties": {
    "iso:country": "GB",
    "wof:name": "ST14 5GA",
    "wof:placetype": "postalcode"
  },
  "geometry": {"coordinates":[-1.855895,52.952854],"type":"Point"}
}
