{
  "type": "Feature",
  "properties": {
    "date:inception_lower":"2006-07-01",
    "date:inception_upper":"2006-07-31",
    "iso:country":"GB",
    "wof:name":"ST14 5GA",
    "wof:placetype":"postalcode"
},
  "geometry": {"coordinates":[-1.855895,52.952854],"type":"Point"}
}