{
  "type": "Feature",
  "properties": {
    "iso:country":"GB",
    "wof:name":"ST14 5GA",
    "wof:placetype":"postalcode"
},
  "geometry": {"coordinates":[-1.85589460907671,52.95285385407812],"type":"Point"}
}