{
  "type": "Feature",
  "properties": {
    "iso:country": "GB",
    "wof:name": "PR2 6YX",
    "wof:placetype": "postalcode"
  },
  "geometry": {"coordinates":[-2.670791,53.777311],"type":"Point"}
}
