{
  "type": "Feature",
  "properties": {
    "date:inception_lower": "2022-02-01",
    "date:inception_upper": "2022-02-01",
    "iso:country": "GB",
    "wof:name": "S5 8ED",
    "wof:placetype": "postalcode"
  },
  "geometry": {"coordinates":[-1.473098,53.422159],"type":"Point"}
}
