{
  "type": "Feature",
  "properties": {
    "iso:country":"GB",
    "wof:name":"TW18 2PU",
    "wof:placetype":"postalcode"
},
  "geometry": {"coordinates":[-0.50535890363233,51.42339953811403],"type":"Point"}
}