{
  "type": "Feature",
  "properties": {
    "iso:country":"GB",
    "wof:name":"PE21 7EJ",
    "wof:placetype":"postalcode"
},
  "geometry": {"coordinates":[-0.03058181612972,52.96573715189197],"type":"Point"}
}