{
  "type": "Feature",
  "properties": {
    "iso:country": "GB",
    "wof:name": "EH8 7QU",
    "wof:placetype": "postalcode"
  },
  "geometry": {"coordinates":[-3.133118,55.951221],"type":"Point"}
}
