{
  "type": "Feature",
  "properties": {
    "iso:country":"GB",
    "wof:name":"NW10 1HF",
    "wof:placetype":"postalcode"
},
  "geometry": {"coordinates":[-0.234137170752,51.55151938171959],"type":"Point"}
}