{
  "type": "Feature",
  "properties": {
    "iso:country":"GB",
    "wof:name":"NP4 7AJ",
    "wof:placetype":"postalcode"
},
  "geometry": {"coordinates":[-3.0661140531035,51.72524154793109],"type":"Point"}
}