{
  "type": "Feature",
  "properties": {
    "date:inception_lower": "2023-04-01",
    "date:inception_upper": "2023-04-01",
    "iso:country": "GB",
    "wof:name": "PE20 2DY",
    "wof:placetype": "postalcode"
  },
  "geometry": {"coordinates":[-0.097932,52.905523],"type":"Point"}
}
