{
  "type": "Feature",
  "properties": {
    "date:inception_lower": "2022-10-01",
    "date:inception_upper": "2022-10-01",
    "iso:country": "GB",
    "wof:name": "PE20 2DY",
    "wof:placetype": "postalcode"
  },
  "geometry": {"coordinates":[-0.043457,52.90498],"type":"Point"}
}
