{
  "type": "Feature",
  "properties": {
    "iso:country":"GB",
    "wof:name":"HU12 9JG",
    "wof:placetype":"postalcode"
},
  "geometry": {"coordinates":[-0.14262833124855,53.72968526513451],"type":"Point"}
}