{
  "type": "Feature",
  "properties": {
    "iso:country": "GB",
    "wof:name": "HU12 9JG",
    "wof:placetype": "postalcode"
  },
  "geometry": {"coordinates":[-0.142628,53.729685],"type":"Point"}
}
