{
  "type": "Feature",
  "properties": {
    "date:inception_lower": "1980-01-01",
    "date:inception_upper": "1980-01-01",
    "iso:country": "GB",
    "wof:name": "DL12 0RQ",
    "wof:placetype": "postalcode"
  },
  "geometry": {"coordinates":[-2.083849,54.624045],"type":"Point"}
}
