{
  "type": "Feature",
  "properties": {
    "iso:country":"GB",
    "wof:name":"IP12 1AN",
    "wof:placetype":"postalcode"
},
  "geometry": {"coordinates":[1.32502793692174,52.09632935421831],"type":"Point"}
}