{
  "type": "Feature",
  "properties": {
    "iso:country": "GB",
    "wof:name": "L24 7RN",
    "wof:placetype": "postalcode"
  },
  "geometry": {"coordinates":[-2.826886,53.341875],"type":"Point"}
}
