{
  "type": "Feature",
  "properties": {
    "iso:country":"GB",
    "wof:name":"YO26 6LR",
    "wof:placetype":"postalcode"
},
  "geometry": {"coordinates":[-1.14111529740508,53.98381539973567],"type":"Point"}
}