{
  "type": "Feature",
  "properties": {
    "iso:country": "GB",
    "wof:name": "YO26 6LR",
    "wof:placetype": "postalcode"
  },
  "geometry": {"coordinates":[-1.140747,53.983614],"type":"Point"}
}
