{
  "type": "Feature",
  "properties": {
    "date:inception_lower":"1998-06-01",
    "date:inception_upper":"1998-06-30",
    "iso:country":"GB",
    "wof:name":"YO26 6LR",
    "wof:placetype":"postalcode"
},
  "geometry": {"coordinates":[-1.141115,53.983815],"type":"Point"}
}