{
  "type": "Feature",
  "properties": {
    "date:inception_lower": "2002-06-01",
    "date:inception_upper": "2002-06-01",
    "iso:country": "GB",
    "wof:name": "M23 2BA",
    "wof:placetype": "postalcode"
  },
  "geometry": {"coordinates":[-2.285346,53.385074],"type":"Point"}
}
