{
  "type": "Feature",
  "properties": {
    "date:inception_lower":"2014-02-01",
    "date:inception_upper":"2014-02-28",
    "iso:country":"GB",
    "wof:name":"KA6 5JF",
    "wof:placetype":"postalcode"
},
  "geometry": {"coordinates":[-4.576548,55.480852],"type":"Point"}
}