{
  "type": "Feature",
  "properties": {
    "iso:country":"GB",
    "wof:name":"KA6 5JF",
    "wof:placetype":"postalcode"
},
  "geometry": {"coordinates":[-4.57654765765668,55.48085232897481],"type":"Point"}
}