{
  "type": "Feature",
  "properties": {
    "iso:country": "GB",
    "wof:name": "SL6 4DS",
    "wof:placetype": "postalcode"
  },
  "geometry": {"coordinates":[-0.731554,51.520202],"type":"Point"}
}
