{
  "type": "Feature",
  "properties": {
    "date:inception_lower":"1980-01-01",
    "date:inception_upper":"1980-01-31",
    "iso:country":"GB",
    "wof:name":"EN2 0RP",
    "wof:placetype":"postalcode"
},
  "geometry": {"coordinates":[-0.088752,51.659596],"type":"Point"}
}