{
  "type": "Feature",
  "properties": {
    "iso:country":"GB",
    "wof:name":"HA7 3HS",
    "wof:placetype":"postalcode"
},
  "geometry": {"coordinates":[-0.33440636360147,51.63061511763136],"type":"Point"}
}