{
  "type": "Feature",
  "properties": {
    "date:inception_lower": "1999-06-01",
    "date:inception_upper": "1999-06-01",
    "iso:country": "GB",
    "wof:name": "CF23 7JA",
    "wof:placetype": "postalcode"
  },
  "geometry": {"coordinates":[-3.145154,51.52633],"type":"Point"}
}
