{
  "type": "Feature",
  "properties": {
    "date:inception_lower": "1999-06-01",
    "date:inception_upper": "1999-06-01",
    "iso:country": "GB",
    "wof:name": "SW19 1UP",
    "wof:placetype": "postalcode"
  },
  "geometry": {"coordinates":[-0.180207,51.423883],"type":"Point"}
}
