{
  "type": "Feature",
  "properties": {
    "date:inception_lower": "1994-12-01",
    "date:inception_upper": "1994-12-01",
    "iso:country": "GB",
    "wof:name": "B90 3LD",
    "wof:placetype": "postalcode"
  },
  "geometry": {"coordinates":[-1.814152,52.413596],"type":"Point"}
}
