{
  "type": "Feature",
  "properties": {
    "iso:country": "GB",
    "wof:name": "B90 3LD",
    "wof:placetype": "postalcode"
  },
  "geometry": {"coordinates":[-1.814152,52.413596],"type":"Point"}
}
