{
  "type": "Feature",
  "properties": {
    "iso:country":"GB",
    "wof:name":"SY10 7ER",
    "wof:placetype":"postalcode"
},
  "geometry": {"coordinates":[-3.06357316429916,52.90813069433955],"type":"Point"}
}