{
  "type": "Feature",
  "properties": {
    "iso:country":"GB",
    "wof:name":"S40 3EF",
    "wof:placetype":"postalcode"
},
  "geometry": {"coordinates":[-1.44935694061898,53.22584453254232],"type":"Point"}
}