{
  "type": "Feature",
  "properties": {
    "date:inception_lower": "1980-01-01",
    "date:inception_upper": "1980-01-01",
    "iso:country": "GB",
    "wof:name": "S40 3EF",
    "wof:placetype": "postalcode"
  },
  "geometry": {"coordinates":[-1.449357,53.225845],"type":"Point"}
}
