{
  "type": "Feature",
  "properties": {
    "iso:country":"GB",
    "wof:name":"SN5 8WQ",
    "wof:placetype":"postalcode"
},
  "geometry": {"coordinates":[-1.80848838756677,51.55285046621072],"type":"Point"}
}