{
  "type": "Feature",
  "properties": {
    "iso:country":"GB",
    "wof:name":"BD2 1LH",
    "wof:placetype":"postalcode"
},
  "geometry": {"coordinates":[-1.73811223096538,53.82405298040209],"type":"Point"}
}