{
  "type": "Feature",
  "properties": {
    "iso:country":"GB",
    "wof:name":"WD4 8LB",
    "wof:placetype":"postalcode"
},
  "geometry": {"coordinates":[-0.44000319039342,51.70961228694249],"type":"Point"}
}