{
  "type": "Feature",
  "properties": {
    "iso:country":"GB",
    "wof:name":"DA8 2JW",
    "wof:placetype":"postalcode"
},
  "geometry": {"coordinates":[0.19493022628693,51.47297131416487],"type":"Point"}
}