{
  "type": "Feature",
  "properties": {
    "iso:country":"GB",
    "wof:name":"BR1 3BU",
    "wof:placetype":"postalcode"
},
  "geometry": {"coordinates":[0.0323729342527,51.40495774014418],"type":"Point"}
}