{
  "type": "Feature",
  "properties": {
    "iso:country": "GB",
    "wof:name": "M7 4JE",
    "wof:placetype": "postalcode"
  },
  "geometry": {"coordinates":[-2.262347,53.515181],"type":"Point"}
}
