{
  "type": "Feature",
  "properties": {
    "date:inception_lower":"1994-05-01",
    "date:inception_upper":"1994-05-31",
    "iso:country":"GB",
    "wof:name":"M7 4JE",
    "wof:placetype":"postalcode"
},
  "geometry": {"coordinates":[-2.262347,53.515181],"type":"Point"}
}