{
  "type": "Feature",
  "properties": {
    "date:inception_lower": "2016-04-01",
    "date:inception_upper": "2016-04-01",
    "iso:country": "GB",
    "wof:name": "LN6 9XQ",
    "wof:placetype": "postalcode"
  },
  "geometry": {"coordinates":[-0.590258,53.176668],"type":"Point"}
}
