{
  "type": "Feature",
  "properties": {
    "iso:country": "GB",
    "wof:name": "LN6 9XQ",
    "wof:placetype": "postalcode"
  },
  "geometry": {"coordinates":[-0.590533,53.176959],"type":"Point"}
}
