{
  "type": "Feature",
  "properties": {
    "iso:country":"GB",
    "wof:name":"LN6 9XQ",
    "wof:placetype":"postalcode"
},
  "geometry": {"coordinates":[-0.59212546199437,53.1827453560153],"type":"Point"}
}