{
  "type": "Feature",
  "properties": {
    "iso:country":"GB",
    "wof:name":"CF47 9LF",
    "wof:placetype":"postalcode"
},
  "geometry": {"coordinates":[-3.37050142562879,51.75613635526043],"type":"Point"}
}