{
  "type": "Feature",
  "properties": {
    "iso:country":"GB",
    "wof:name":"DD4 7JJ",
    "wof:placetype":"postalcode"
},
  "geometry": {"coordinates":[-2.94754509680583,56.47074606570745],"type":"Point"}
}