{
  "type": "Feature",
  "properties": {
    "date:inception_lower": "1995-12-01",
    "date:inception_upper": "1995-12-01",
    "iso:country": "GB",
    "wof:name": "KY15 7BE",
    "wof:placetype": "postalcode"
  },
  "geometry": {"coordinates":[-3.207596,56.252419],"type":"Point"}
}
