{
  "type": "Feature",
  "properties": {
    "iso:country":"GB",
    "wof:name":"TA19 0NQ",
    "wof:placetype":"postalcode"
},
  "geometry": {"coordinates":[-2.86086382731335,50.9640679864597],"type":"Point"}
}