{
  "type": "Feature",
  "properties": {
    "iso:country":"GB",
    "wof:name":"BS6 7EX",
    "wof:placetype":"postalcode"
},
  "geometry": {"coordinates":[-2.60335629014454,51.47059274972503],"type":"Point"}
}