{
  "type": "Feature",
  "properties": {
    "iso:country":"GB",
    "wof:name":"LL26 0SF",
    "wof:placetype":"postalcode"
},
  "geometry": {"coordinates":[-3.77362562837874,53.12810211651894],"type":"Point"}
}