{
  "type": "Feature",
  "properties": {
    "date:inception_lower":"1980-01-01",
    "date:inception_upper":"1980-01-31",
    "iso:country":"GB",
    "wof:name":"LL26 0SF",
    "wof:placetype":"postalcode"
},
  "geometry": {"coordinates":[-3.773626,53.128102],"type":"Point"}
}