{
  "type": "Feature",
  "properties": {
    "iso:country":"GB",
    "wof:name":"IV21 2DY",
    "wof:placetype":"postalcode"
},
  "geometry": {"coordinates":[-5.79994319048653,57.7999207390781],"type":"Point"}
}