{
  "type": "Feature",
  "properties": {
    "date:inception_lower": "1980-01-01",
    "date:inception_upper": "1980-01-01",
    "iso:country": "GB",
    "wof:name": "IV21 2DY",
    "wof:placetype": "postalcode"
  },
  "geometry": {"coordinates":[-5.799427,57.80062],"type":"Point"}
}
