{
  "type": "Feature",
  "properties": {
    "date:inception_lower": "2015-09-01",
    "date:inception_upper": "2015-09-01",
    "iso:country": "GB",
    "wof:name": "MK45 1FW",
    "wof:placetype": "postalcode"
  },
  "geometry": {"coordinates":[-0.491443,52.007639],"type":"Point"}
}
