{
  "type": "Feature",
  "properties": {
    "iso:country":"GB",
    "wof:name":"MK45 1FW",
    "wof:placetype":"postalcode"
},
  "geometry": {"coordinates":[-0.49146736842683,52.00762007355475],"type":"Point"}
}