{
  "type": "Feature",
  "properties": {
    "iso:country":"GB",
    "wof:name":"PL5 2SF",
    "wof:placetype":"postalcode"
},
  "geometry": {"coordinates":[-4.17958144320322,50.4183187129992],"type":"Point"}
}