{
  "type": "Feature",
  "properties": {
    "iso:country":"GB",
    "wof:name":"DY1 4AS",
    "wof:placetype":"postalcode"
},
  "geometry": {"coordinates":[-2.08262280616227,52.51425678568862],"type":"Point"}
}