{
  "type": "Feature",
  "properties": {
    "date:inception_lower":"2008-12-01",
    "date:inception_upper":"2008-12-31",
    "iso:country":"GB",
    "wof:name":"L1 3DE",
    "wof:placetype":"postalcode"
},
  "geometry": {"coordinates":[-2.98492,53.404209],"type":"Point"}
}