{
  "type": "Feature",
  "properties": {
    "iso:country":"GB",
    "wof:name":"L1 3DE",
    "wof:placetype":"postalcode"
},
  "geometry": {"coordinates":[-2.98492018728081,53.40420924986645],"type":"Point"}
}