{
  "type": "Feature",
  "properties": {
    "iso:country": "GB",
    "wof:name": "L1 3DE",
    "wof:placetype": "postalcode"
  },
  "geometry": {"coordinates":[-2.98492,53.404209],"type":"Point"}
}
