{
  "type": "Feature",
  "properties": {
    "iso:country":"GB",
    "wof:name":"EH54 5ER",
    "wof:placetype":"postalcode"
},
  "geometry": {"coordinates":[-3.50370862316847,55.90140005478494],"type":"Point"}
}