{
  "type": "Feature",
  "properties": {
    "date:inception_lower":"1980-01-01",
    "date:inception_upper":"1980-01-31",
    "iso:country":"GB",
    "wof:name":"SA18 1NW",
    "wof:placetype":"postalcode"
},
  "geometry": {"coordinates":[-3.900307,51.799028],"type":"Point"}
}