{
  "type": "Feature",
  "properties": {
    "iso:country":"GB",
    "wof:name":"SA18 1NW",
    "wof:placetype":"postalcode"
},
  "geometry": {"coordinates":[-3.90030742683287,51.79902843365787],"type":"Point"}
}