{
  "type": "Feature",
  "properties": {
    "iso:country": "GB",
    "wof:name": "SA18 1NW",
    "wof:placetype": "postalcode"
  },
  "geometry": {"coordinates":[-3.900307,51.799028],"type":"Point"}
}
