{
  "type": "Feature",
  "properties": {
    "date:inception_lower":"2006-09-01",
    "date:inception_upper":"2006-09-30",
    "iso:country":"GB",
    "wof:name":"L15 4HY",
    "wof:placetype":"postalcode"
},
  "geometry": {"coordinates":[-2.924467,53.403497],"type":"Point"}
}