{
  "type": "Feature",
  "properties": {
    "iso:country": "GB",
    "wof:name": "W3 7QN",
    "wof:placetype": "postalcode"
  },
  "geometry": {"coordinates":[-0.256588,51.506958],"type":"Point"}
}
