{
  "type": "Feature",
  "properties": {
    "date:inception_lower": "2017-01-01",
    "date:inception_upper": "2017-01-01",
    "iso:country": "GB",
    "wof:name": "W3 7QN",
    "wof:placetype": "postalcode"
  },
  "geometry": {"coordinates":[-0.256588,51.506958],"type":"Point"}
}
