{
  "type": "Feature",
  "properties": {
    "date:inception_lower": "2007-05-01",
    "date:inception_upper": "2007-05-01",
    "iso:country": "GB",
    "wof:name": "HA0 1HD",
    "wof:placetype": "postalcode"
  },
  "geometry": {"coordinates":[-0.297949,51.534882],"type":"Point"}
}
