{
  "type": "Feature",
  "properties": {
    "iso:country":"GB",
    "wof:name":"HA0 1HD",
    "wof:placetype":"postalcode"
},
  "geometry": {"coordinates":[-0.29794919633583,51.53488247701046],"type":"Point"}
}