{
  "type": "Feature",
  "properties": {
    "iso:country": "GB",
    "wof:name": "BL6 5AX",
    "wof:placetype": "postalcode"
  },
  "geometry": {"coordinates":[-2.578183,53.591809],"type":"Point"}
}
