{
  "type": "Feature",
  "properties": {
    "iso:country":"GB",
    "wof:name":"BL6 5AX",
    "wof:placetype":"postalcode"
},
  "geometry": {"coordinates":[-2.57818497549388,53.59182937447834],"type":"Point"}
}