{
  "type": "Feature",
  "properties": {
    "iso:country": "GB",
    "wof:name": "TF13 6FE",
    "wof:placetype": "postalcode"
  },
  "geometry": {"coordinates":[-2.561097,52.593771],"type":"Point"}
}
