{
  "type": "Feature",
  "properties": {
    "date:inception_lower": "1984-02-01",
    "date:inception_upper": "1984-02-01",
    "iso:country": "GB",
    "wof:name": "TF10 7NB",
    "wof:placetype": "postalcode"
  },
  "geometry": {"coordinates":[-2.374168,52.762009],"type":"Point"}
}
