{
  "type": "Feature",
  "properties": {
    "iso:country":"GB",
    "wof:name":"NN15 5LP",
    "wof:placetype":"postalcode"
},
  "geometry": {"coordinates":[-0.67998472489062,52.36624132679565],"type":"Point"}
}