{
  "type": "Feature",
  "properties": {
    "date:inception_lower": "1980-01-01",
    "date:inception_upper": "1980-01-01",
    "iso:country": "GB",
    "wof:name": "NN15 5LP",
    "wof:placetype": "postalcode"
  },
  "geometry": {"coordinates":[-0.679985,52.366241],"type":"Point"}
}
