{
  "type": "Feature",
  "properties": {
    "iso:country":"GB",
    "wof:name":"S64 8QS",
    "wof:placetype":"postalcode"
},
  "geometry": {"coordinates":[-1.31299216822615,53.49107065452613],"type":"Point"}
}