{
  "type": "Feature",
  "properties": {
    "date:inception_lower": "1980-01-01",
    "date:inception_upper": "1980-01-01",
    "iso:country": "GB",
    "wof:name": "S64 8QS",
    "wof:placetype": "postalcode"
  },
  "geometry": {"coordinates":[-1.312992,53.491071],"type":"Point"}
}
