{
  "type": "Feature",
  "properties": {
    "date:inception_lower":"2007-02-01",
    "date:inception_upper":"2007-02-28",
    "iso:country":"GB",
    "wof:name":"SA34 0AQ",
    "wof:placetype":"postalcode"
},
  "geometry": {"coordinates":[-4.613893,51.820459],"type":"Point"}
}