{
  "type": "Feature",
  "properties": {
    "iso:country": "GB",
    "wof:name": "SA34 0AQ",
    "wof:placetype": "postalcode"
  },
  "geometry": {"coordinates":[-4.613893,51.820459],"type":"Point"}
}
