{
  "type": "Feature",
  "properties": {
    "iso:country":"GB",
    "wof:name":"SA34 0AQ",
    "wof:placetype":"postalcode"
},
  "geometry": {"coordinates":[-4.61389283450601,51.82045858607838],"type":"Point"}
}