{
  "type": "Feature",
  "properties": {
    "iso:country":"GB",
    "wof:name":"WV12 4TY",
    "wof:placetype":"postalcode"
},
  "geometry": {"coordinates":[-2.0402731467033,52.59461211850662],"type":"Point"}
}