{
  "type": "Feature",
  "properties": {
    "iso:country": "GB",
    "wof:name": "EH21 7QE",
    "wof:placetype": "postalcode"
  },
  "geometry": {"coordinates":[-3.026877,55.945719],"type":"Point"}
}
