{
  "type": "Feature",
  "properties": {
    "iso:country":"GB",
    "wof:name":"SN11 8QN",
    "wof:placetype":"postalcode"
},
  "geometry": {"coordinates":[-1.96916749802961,51.43236369709022],"type":"Point"}
}