{
  "type": "Feature",
  "properties": {
    "iso:country":"GB",
    "wof:name":"OL6 8UR",
    "wof:placetype":"postalcode"
},
  "geometry": {"coordinates":[-2.08800158588849,53.50794960782454],"type":"Point"}
}