{
  "type": "Feature",
  "properties": {
    "date:inception_lower":"1980-01-01",
    "date:inception_upper":"1980-01-31",
    "iso:country":"GB",
    "wof:name":"OL6 8UR",
    "wof:placetype":"postalcode"
},
  "geometry": {"coordinates":[-2.088002,53.50795],"type":"Point"}
}