{
  "type": "Feature",
  "properties": {
    "iso:country":"GB",
    "wof:name":"PL3 4PH",
    "wof:placetype":"postalcode"
},
  "geometry": {"coordinates":[-4.13676329520644,50.38965695334932],"type":"Point"}
}