{
  "type": "Feature",
  "properties": {
    "iso:country": "GB",
    "wof:name": "PL3 4PH",
    "wof:placetype": "postalcode"
  },
  "geometry": {"coordinates":[-4.136763,50.389657],"type":"Point"}
}
