{
  "type": "Feature",
  "properties": {
    "iso:country": "GB",
    "wof:name": "NR9 3LL",
    "wof:placetype": "postalcode"
  },
  "geometry": {"coordinates":[1.185153,52.630315],"type":"Point"}
}
