{
  "type": "Feature",
  "properties": {
    "iso:country":"GB",
    "wof:name":"NR9 3LL",
    "wof:placetype":"postalcode"
},
  "geometry": {"coordinates":[1.18572009259765,52.63026622009477],"type":"Point"}
}