{
  "type": "Feature",
  "properties": {
    "date:inception_lower":"1991-09-01",
    "date:inception_upper":"1991-09-30",
    "iso:country":"GB",
    "wof:name":"ST5 7RF",
    "wof:placetype":"postalcode"
},
  "geometry": {"coordinates":[-2.242214,53.051332],"type":"Point"}
}