{
  "type": "Feature",
  "properties": {
    "date:inception_lower": "1985-10-01",
    "date:inception_upper": "1985-10-01",
    "iso:country": "GB",
    "wof:name": "CF38 1RB",
    "wof:placetype": "postalcode"
  },
  "geometry": {"coordinates":[-3.317821,51.565781],"type":"Point"}
}
