{
  "type": "Feature",
  "properties": {
    "iso:country":"GB",
    "wof:name":"LN7 6EB",
    "wof:placetype":"postalcode"
},
  "geometry": {"coordinates":[-0.42747004865439,53.50227125674939],"type":"Point"}
}