{
  "type": "Feature",
  "properties": {
    "iso:country":"GB",
    "wof:name":"UB1 2XJ",
    "wof:placetype":"postalcode"
},
  "geometry": {"coordinates":[-0.36749510114266,51.52707641398158],"type":"Point"}
}