{
  "type": "Feature",
  "properties": {
    "date:inception_lower": "2021-08-01",
    "date:inception_upper": "2021-08-01",
    "iso:country": "GB",
    "wof:name": "LN2 5BY",
    "wof:placetype": "postalcode"
  },
  "geometry": {"coordinates":[-0.529184,53.23083],"type":"Point"}
}
