{
  "type": "Feature",
  "properties": {
    "date:inception_lower": "2018-06-01",
    "date:inception_upper": "2018-06-01",
    "iso:country": "GB",
    "wof:name": "SY5 6LS",
    "wof:placetype": "postalcode"
  },
  "geometry": {"coordinates":[-2.684597,52.661741],"type":"Point"}
}
