{
  "type": "Feature",
  "properties": {
    "iso:country":"GB",
    "wof:name":"KY12 0PQ",
    "wof:placetype":"postalcode"
},
  "geometry": {"coordinates":[-3.46436657118805,56.0817158417569],"type":"Point"}
}