{
  "type": "Feature",
  "properties": {
    "iso:country":"GB",
    "wof:name":"HU6 8TB",
    "wof:placetype":"postalcode"
},
  "geometry": {"coordinates":[-0.39153572647501,53.77870674208876],"type":"Point"}
}