{
  "type": "Feature",
  "properties": {
    "iso:country":"GB",
    "wof:name":"UB8 3RY",
    "wof:placetype":"postalcode"
},
  "geometry": {"coordinates":[-0.47510099513291,51.52605159914826],"type":"Point"}
}