{
  "type": "Feature",
  "properties": {
    "iso:country": "GB",
    "wof:name": "CV32 5SG",
    "wof:placetype": "postalcode"
  },
  "geometry": {"coordinates":[-1.536345,52.295814],"type":"Point"}
}
