{
  "type": "Feature",
  "properties": {
    "iso:country":"GB",
    "wof:name":"CV32 5SG",
    "wof:placetype":"postalcode"
},
  "geometry": {"coordinates":[-1.53632609587044,52.29584396098244],"type":"Point"}
}