{
  "type": "Feature",
  "properties": {
    "date:inception_lower": "1980-01-01",
    "date:inception_upper": "1980-01-01",
    "iso:country": "GB",
    "wof:name": "SE1 8HA",
    "wof:placetype": "postalcode"
  },
  "geometry": {"coordinates":[-0.10501,51.503051],"type":"Point"}
}
