{
  "type": "Feature",
  "properties": {
    "iso:country":"GB",
    "wof:name":"SE1 8HA",
    "wof:placetype":"postalcode"
},
  "geometry": {"coordinates":[-0.10503577402681,51.50304984852195],"type":"Point"}
}