{
  "type": "Feature",
  "properties": {
    "iso:country":"GB",
    "wof:name":"N14 4RJ",
    "wof:placetype":"postalcode"
},
  "geometry": {"coordinates":[-0.12989479619914,51.64570919271807],"type":"Point"}
}