{
  "type": "Feature",
  "properties": {
    "date:inception_lower": "1980-01-01",
    "date:inception_upper": "1980-01-01",
    "iso:country": "GB",
    "wof:name": "PH2 0NF",
    "wof:placetype": "postalcode"
  },
  "geometry": {"coordinates":[-3.456607,56.387331],"type":"Point"}
}
