{
  "type": "Feature",
  "properties": {
    "iso:country":"GB",
    "wof:name":"PH2 0NF",
    "wof:placetype":"postalcode"
},
  "geometry": {"coordinates":[-3.45660680876413,56.38733067932581],"type":"Point"}
}