{
  "type": "Feature",
  "properties": {
    "iso:country":"GB",
    "wof:name":"KA7 2TD",
    "wof:placetype":"postalcode"
},
  "geometry": {"coordinates":[-4.63574196565505,55.45546534940948],"type":"Point"}
}