{
  "type": "Feature",
  "properties": {
    "iso:country":"GB",
    "wof:name":"S20 5EU",
    "wof:placetype":"postalcode"
},
  "geometry": {"coordinates":[-1.36567027305841,53.32614037359211],"type":"Point"}
}