{
  "type": "Feature",
  "properties": {
    "iso:country": "GB",
    "wof:name": "S20 5EU",
    "wof:placetype": "postalcode"
  },
  "geometry": {"coordinates":[-1.36567,53.32614],"type":"Point"}
}
