{
  "type": "Feature",
  "properties": {
    "date:inception_lower": "2005-01-01",
    "date:inception_upper": "2005-01-01",
    "iso:country": "GB",
    "wof:name": "S20 5EU",
    "wof:placetype": "postalcode"
  },
  "geometry": {"coordinates":[-1.36567,53.32614],"type":"Point"}
}
