{
  "type": "Feature",
  "properties": {
    "iso:country": "GB",
    "wof:name": "GL7 3PR",
    "wof:placetype": "postalcode"
  },
  "geometry": {"coordinates":[-1.713938,51.726657],"type":"Point"}
}
