{
  "type": "Feature",
  "properties": {
    "iso:country":"GB",
    "wof:name":"SR4 8PG",
    "wof:placetype":"postalcode"
},
  "geometry": {"coordinates":[-1.43864736106679,54.89557348801638],"type":"Point"}
}