{
  "type": "Feature",
  "properties": {
    "iso:country":"GB",
    "wof:name":"M22 9UH",
    "wof:placetype":"postalcode"
},
  "geometry": {"coordinates":[-2.25563174112542,53.3865971240584],"type":"Point"}
}