{
  "type": "Feature",
  "properties": {
    "date:inception_lower": "1980-01-01",
    "date:inception_upper": "1980-01-01",
    "iso:country": "GB",
    "wof:name": "SK3 8TZ",
    "wof:placetype": "postalcode"
  },
  "geometry": {"coordinates":[-2.154658,53.386987],"type":"Point"}
}
