{
  "type": "Feature",
  "properties": {
    "date:inception_lower": "1985-04-01",
    "date:inception_upper": "1985-04-01",
    "iso:country": "GB",
    "wof:name": "NG31 8RP",
    "wof:placetype": "postalcode"
  },
  "geometry": {"coordinates":[-0.668425,52.915138],"type":"Point"}
}
