{
  "type": "Feature",
  "properties": {
    "date:inception_lower":"1985-04-01",
    "date:inception_upper":"1985-04-30",
    "iso:country":"GB",
    "wof:name":"NG31 8RP",
    "wof:placetype":"postalcode"
},
  "geometry": {"coordinates":[-0.668402,52.915053],"type":"Point"}
}