{
  "type": "Feature",
  "properties": {
    "iso:country":"GB",
    "wof:name":"W3 7DY",
    "wof:placetype":"postalcode"
},
  "geometry": {"coordinates":[-0.25264789513517,51.50357047676526],"type":"Point"}
}