{
  "type": "Feature",
  "properties": {
    "date:inception_lower": "2009-08-01",
    "date:inception_upper": "2009-08-01",
    "iso:country": "GB",
    "wof:name": "W3 7DY",
    "wof:placetype": "postalcode"
  },
  "geometry": {"coordinates":[-0.252648,51.50357],"type":"Point"}
}
