{
  "type": "Feature",
  "properties": {
    "iso:country":"GB",
    "wof:name":"PE21 7RL",
    "wof:placetype":"postalcode"
},
  "geometry": {"coordinates":[-0.0210251063132,52.96370834077639],"type":"Point"}
}