{
  "type": "Feature",
  "properties": {
    "date:inception_lower": "1980-01-01",
    "date:inception_upper": "1980-01-01",
    "iso:country": "GB",
    "wof:name": "PE21 7RL",
    "wof:placetype": "postalcode"
  },
  "geometry": {"coordinates":[-0.021025,52.963708],"type":"Point"}
}
