{
  "type": "Feature",
  "properties": {
    "iso:country":"GB",
    "wof:name":"SK23 7EZ",
    "wof:placetype":"postalcode"
},
  "geometry": {"coordinates":[-1.9792313879218,53.3160032182247],"type":"Point"}
}