{
  "type": "Feature",
  "properties": {
    "date:inception_lower": "1996-12-01",
    "date:inception_upper": "1996-12-01",
    "iso:country": "GB",
    "wof:name": "SK23 7EZ",
    "wof:placetype": "postalcode"
  },
  "geometry": {"coordinates":[-1.979231,53.316003],"type":"Point"}
}
