{
  "type": "Feature",
  "properties": {
    "iso:country": "GB",
    "wof:name": "SK23 7EZ",
    "wof:placetype": "postalcode"
  },
  "geometry": {"coordinates":[-1.979231,53.316003],"type":"Point"}
}
