{
  "type": "Feature",
  "properties": {
    "date:inception_lower": "1980-01-01",
    "date:inception_upper": "1980-01-01",
    "iso:country": "GB",
    "wof:name": "SS1 1EP",
    "wof:placetype": "postalcode"
  },
  "geometry": {"coordinates":[0.705832,51.536147],"type":"Point"}
}
