{
  "type": "Feature",
  "properties": {
    "iso:country":"GB",
    "wof:name":"SS1 1EP",
    "wof:placetype":"postalcode"
},
  "geometry": {"coordinates":[0.70583154022088,51.53614681331409],"type":"Point"}
}