{
  "type": "Feature",
  "properties": {
    "iso:country":"GB",
    "wof:name":"NN3 6PJ",
    "wof:placetype":"postalcode"
},
  "geometry": {"coordinates":[-0.8556185379695,52.26648682883379],"type":"Point"}
}