{
  "type": "Feature",
  "properties": {
    "iso:country":"GB",
    "wof:name":"SN13 0BL",
    "wof:placetype":"postalcode"
},
  "geometry": {"coordinates":[-2.18924997163389,51.43435449866199],"type":"Point"}
}