{
  "type": "Feature",
  "properties": {
    "iso:country":"GB",
    "wof:name":"CM16 6BD",
    "wof:placetype":"postalcode"
},
  "geometry": {"coordinates":[0.12758301606872,51.72168364004821],"type":"Point"}
}