{
  "type": "Feature",
  "properties": {
    "iso:country": "GB",
    "wof:name": "CO7 8JG",
    "wof:placetype": "postalcode"
  },
  "geometry": {"coordinates":[1.025816,51.842749],"type":"Point"}
}
