{
  "type": "Feature",
  "properties": {
    "iso:country":"GB",
    "wof:name":"CO7 8JG",
    "wof:placetype":"postalcode"
},
  "geometry": {"coordinates":[1.02581584294582,51.84274915082892],"type":"Point"}
}