{
  "type": "Feature",
  "properties": {
    "date:inception_lower":"1980-01-01",
    "date:inception_upper":"1980-01-31",
    "iso:country":"GB",
    "wof:name":"CO7 8JG",
    "wof:placetype":"postalcode"
},
  "geometry": {"coordinates":[1.025816,51.842749],"type":"Point"}
}