{
  "type": "Feature",
  "properties": {
    "iso:country":"GB",
    "wof:name":"SO19 7BB",
    "wof:placetype":"postalcode"
},
  "geometry": {"coordinates":[-1.36542104561268,50.90973982001925],"type":"Point"}
}