{
  "type": "Feature",
  "properties": {
    "iso:country":"GB",
    "wof:name":"TW1 1NA",
    "wof:placetype":"postalcode"
},
  "geometry": {"coordinates":[-0.32387943087811,51.45892891126177],"type":"Point"}
}