{
  "type": "Feature",
  "properties": {
    "iso:country":"GB",
    "wof:name":"CT3 1JT",
    "wof:placetype":"postalcode"
},
  "geometry": {"coordinates":[1.25309259448255,51.2784423463142],"type":"Point"}
}