{
  "type": "Feature",
  "properties": {
    "iso:country":"GB",
    "wof:name":"G40 2AS",
    "wof:placetype":"postalcode"
},
  "geometry": {"coordinates":[-4.23273083428143,55.85503246298381],"type":"Point"}
}