{
  "type": "Feature",
  "properties": {
    "iso:country": "GB",
    "wof:name": "WD23 2PR",
    "wof:placetype": "postalcode"
  },
  "geometry": {"coordinates":[-0.368535,51.653705],"type":"Point"}
}
