{
  "type": "Feature",
  "properties": {
    "date:inception_lower":"1980-01-01",
    "date:inception_upper":"1980-01-31",
    "iso:country":"GB",
    "wof:name":"NE26 3AY",
    "wof:placetype":"postalcode"
},
  "geometry": {"coordinates":[-1.459193,55.048308],"type":"Point"}
}