{
  "type": "Feature",
  "properties": {
    "date:inception_lower": "1980-01-01",
    "date:inception_upper": "1980-01-01",
    "iso:country": "GB",
    "wof:name": "PA2 6SE",
    "wof:placetype": "postalcode"
  },
  "geometry": {"coordinates":[-4.411658,55.82976],"type":"Point"}
}
