{
  "type": "Feature",
  "properties": {
    "iso:country": "GB",
    "wof:name": "PA2 6SE",
    "wof:placetype": "postalcode"
  },
  "geometry": {"coordinates":[-4.411658,55.82976],"type":"Point"}
}
