{
  "type": "Feature",
  "properties": {
    "iso:country":"GB",
    "wof:name":"PA2 6SE",
    "wof:placetype":"postalcode"
},
  "geometry": {"coordinates":[-4.41165849358978,55.82975982518233],"type":"Point"}
}