{
  "type": "Feature",
  "properties": {
    "date:inception_lower": "2014-07-01",
    "date:inception_upper": "2014-07-01",
    "iso:country": "GB",
    "wof:name": "B60 2TS",
    "wof:placetype": "postalcode"
  },
  "geometry": {"coordinates":[-2.041831,52.332279],"type":"Point"}
}
