{
  "type": "Feature",
  "properties": {
    "iso:country":"GB",
    "wof:name":"B60 2TS",
    "wof:placetype":"postalcode"
},
  "geometry": {"coordinates":[-2.04188187038401,52.33219392742262],"type":"Point"}
}