{
  "type": "Feature",
  "properties": {
    "iso:country":"GB",
    "wof:name":"SS8 7LJ",
    "wof:placetype":"postalcode"
},
  "geometry": {"coordinates":[0.60571331970672,51.51860156521447],"type":"Point"}
}