{
  "type": "Feature",
  "properties": {
    "date:inception_lower": "1980-01-01",
    "date:inception_upper": "1980-01-01",
    "iso:country": "GB",
    "wof:name": "SS8 7LJ",
    "wof:placetype": "postalcode"
  },
  "geometry": {"coordinates":[0.605713,51.518602],"type":"Point"}
}
