{
  "type": "Feature",
  "properties": {
    "date:inception_lower": "1991-09-01",
    "date:inception_upper": "1991-09-01",
    "iso:country": "GB",
    "wof:name": "MK4 1JT",
    "wof:placetype": "postalcode"
  },
  "geometry": {"coordinates":[-0.768091,52.012204],"type":"Point"}
}
