{
  "type": "Feature",
  "properties": {
    "iso:country":"GB",
    "wof:name":"MK4 1JT",
    "wof:placetype":"postalcode"
},
  "geometry": {"coordinates":[-0.76809067954274,52.01220409931625],"type":"Point"}
}