{
  "type": "Feature",
  "properties": {
    "date:inception_lower": "1980-01-01",
    "date:inception_upper": "1980-01-01",
    "iso:country": "GB",
    "wof:name": "TQ10 9JQ",
    "wof:placetype": "postalcode"
  },
  "geometry": {"coordinates":[-3.843067,50.431842],"type":"Point"}
}
