{
  "type": "Feature",
  "properties": {
    "iso:country":"GB",
    "wof:name":"TQ10 9JQ",
    "wof:placetype":"postalcode"
},
  "geometry": {"coordinates":[-3.84310031377514,50.43185513349941],"type":"Point"}
}