{
  "type": "Feature",
  "properties": {
    "iso:country":"GB",
    "wof:name":"DN9 2DH",
    "wof:placetype":"postalcode"
},
  "geometry": {"coordinates":[-0.85662446813967,53.48889847374284],"type":"Point"}
}