{
  "type": "Feature",
  "properties": {
    "iso:country":"GB",
    "wof:name":"CF5 4DY",
    "wof:placetype":"postalcode"
},
  "geometry": {"coordinates":[-3.25608155127149,51.48293232017176],"type":"Point"}
}