{
  "type": "Feature",
  "properties": {
    "iso:country":"GB",
    "wof:name":"L19 8JW",
    "wof:placetype":"postalcode"
},
  "geometry": {"coordinates":[-2.89413215743399,53.34558798763212],"type":"Point"}
}