{
  "type": "Feature",
  "properties": {
    "iso:country":"GB",
    "wof:name":"TA1 3YE",
    "wof:placetype":"postalcode"
},
  "geometry": {"coordinates":[-3.08979130115956,50.99882761197431],"type":"Point"}
}