{
  "type": "Feature",
  "properties": {
    "date:inception_lower":"1988-03-01",
    "date:inception_upper":"1988-03-31",
    "iso:country":"GB",
    "wof:name":"TA1 3YE",
    "wof:placetype":"postalcode"
},
  "geometry": {"coordinates":[-3.089791,50.998828],"type":"Point"}
}