{
  "type": "Feature",
  "properties": {
    "iso:country": "GB",
    "wof:name": "B19 3JP",
    "wof:placetype": "postalcode"
  },
  "geometry": {"coordinates":[-1.906527,52.48932],"type":"Point"}
}
