{
  "type": "Feature",
  "properties": {
    "iso:country":"GB",
    "wof:name":"M44 5DY",
    "wof:placetype":"postalcode"
},
  "geometry": {"coordinates":[-2.44382567525563,53.42265614306691],"type":"Point"}
}