{
  "type": "Feature",
  "properties": {
    "iso:country": "GB",
    "wof:name": "M44 5DY",
    "wof:placetype": "postalcode"
  },
  "geometry": {"coordinates":[-2.443826,53.422656],"type":"Point"}
}
