{
  "type": "Feature",
  "properties": {
    "iso:country":"GB",
    "wof:name":"AB30 1NG",
    "wof:placetype":"postalcode"
},
  "geometry": {"coordinates":[-2.41160928776359,56.87197644229076],"type":"Point"}
}