{
  "type": "Feature",
  "properties": {
    "date:inception_lower": "1996-06-01",
    "date:inception_upper": "1996-06-01",
    "iso:country": "GB",
    "wof:name": "AB30 1NG",
    "wof:placetype": "postalcode"
  },
  "geometry": {"coordinates":[-2.411609,56.871976],"type":"Point"}
}
