{
  "type": "Feature",
  "properties": {
    "iso:country":"GB",
    "wof:name":"WA3 6NS",
    "wof:placetype":"postalcode"
},
  "geometry": {"coordinates":[-2.52181643465081,53.41999467214382],"type":"Point"}
}