{
  "type": "Feature",
  "properties": {
    "iso:country":"GB",
    "wof:name":"SO31 8EZ",
    "wof:placetype":"postalcode"
},
  "geometry": {"coordinates":[-1.32572852758718,50.88969792058263],"type":"Point"}
}