{
  "type": "Feature",
  "properties": {
    "iso:country":"GB",
    "wof:name":"BA14 9BG",
    "wof:placetype":"postalcode"
},
  "geometry": {"coordinates":[-2.22418351307217,51.32383920233587],"type":"Point"}
}