{
  "type": "Feature",
  "properties": {
    "date:inception_lower": "2004-01-01",
    "date:inception_upper": "2004-01-01",
    "iso:country": "GB",
    "wof:name": "BN23 5AU",
    "wof:placetype": "postalcode"
  },
  "geometry": {"coordinates":[0.33011,50.792838],"type":"Point"}
}
