{
  "type": "Feature",
  "properties": {
    "date:inception_lower": "2022-11-01",
    "date:inception_upper": "2022-11-01",
    "iso:country": "GB",
    "wof:name": "SA46 0LZ",
    "wof:placetype": "postalcode"
  },
  "geometry": {"coordinates":[-4.221888,52.253422],"type":"Point"}
}
