{
  "type": "Feature",
  "properties": {
    "iso:country": "GB",
    "wof:name": "NE23 3AP",
    "wof:placetype": "postalcode"
  },
  "geometry": {"coordinates":[-1.581527,55.106418],"type":"Point"}
}
