{
  "type": "Feature",
  "properties": {
    "date:inception_lower":"1999-06-01",
    "date:inception_upper":"1999-06-30",
    "iso:country":"GB",
    "wof:name":"NE23 3AP",
    "wof:placetype":"postalcode"
},
  "geometry": {"coordinates":[-1.581527,55.106418],"type":"Point"}
}