{
  "type": "Feature",
  "properties": {
    "iso:country":"GB",
    "wof:name":"LS2 7JF",
    "wof:placetype":"postalcode"
},
  "geometry": {"coordinates":[-1.54005437560833,53.79711366906493],"type":"Point"}
}