{
  "type": "Feature",
  "properties": {
    "date:inception_lower": "1980-01-01",
    "date:inception_upper": "1980-01-01",
    "iso:country": "GB",
    "wof:name": "LS2 7JF",
    "wof:placetype": "postalcode"
  },
  "geometry": {"coordinates":[-1.54006,53.797031],"type":"Point"}
}
