{
  "type": "Feature",
  "properties": {
    "iso:country":"GB",
    "wof:name":"HU1 2JT",
    "wof:placetype":"postalcode"
},
  "geometry": {"coordinates":[-0.33637573610668,53.74244690661985],"type":"Point"}
}