{
  "type": "Feature",
  "properties": {
    "iso:country": "GB",
    "wof:name": "HU1 2JT",
    "wof:placetype": "postalcode"
  },
  "geometry": {"coordinates":[-0.336376,53.742447],"type":"Point"}
}
