{
  "type": "Feature",
  "properties": {
    "iso:country":"GB",
    "wof:name":"SP7 9JF",
    "wof:placetype":"postalcode"
},
  "geometry": {"coordinates":[-2.2110127631819,51.05231553456946],"type":"Point"}
}