{
  "type": "Feature",
  "properties": {
    "date:inception_lower": "1980-01-01",
    "date:inception_upper": "1980-01-01",
    "iso:country": "GB",
    "wof:name": "SP7 9JF",
    "wof:placetype": "postalcode"
  },
  "geometry": {"coordinates":[-2.211008,51.052309],"type":"Point"}
}
