{
  "type": "Feature",
  "properties": {
    "iso:country": "GB",
    "wof:name": "NE24 1EN",
    "wof:placetype": "postalcode"
  },
  "geometry": {"coordinates":[-1.514522,55.130971],"type":"Point"}
}
