{
  "type": "Feature",
  "properties": {
    "iso:country": "GB",
    "wof:name": "CV5 6NP",
    "wof:placetype": "postalcode"
  },
  "geometry": {"coordinates":[-1.524629,52.400893],"type":"Point"}
}
