{
  "type": "Feature",
  "properties": {
    "date:inception_lower": "1980-01-01",
    "date:inception_upper": "1980-01-01",
    "iso:country": "GB",
    "wof:name": "HP21 8NY",
    "wof:placetype": "postalcode"
  },
  "geometry": {"coordinates":[-0.825,51.810122],"type":"Point"}
}
