{
  "type": "Feature",
  "properties": {
    "date:inception_lower":"2015-04-01",
    "date:inception_upper":"2015-04-30",
    "iso:country":"GB",
    "wof:name":"PA4 8ZY",
    "wof:placetype":"postalcode"
},
  "geometry": {"coordinates":[-4.374156,55.876483],"type":"Point"}
}