{
  "type": "Feature",
  "properties": {
    "date:inception_lower":"1980-01-01",
    "date:inception_upper":"1980-01-31",
    "iso:country":"GB",
    "wof:name":"KY12 0SY",
    "wof:placetype":"postalcode"
},
  "geometry": {"coordinates":[-3.426602,56.085573],"type":"Point"}
}