{
  "type": "Feature",
  "properties": {
    "iso:country":"GB",
    "wof:name":"DN6 8AR",
    "wof:placetype":"postalcode"
},
  "geometry": {"coordinates":[-1.19156418592351,53.58642648627487],"type":"Point"}
}