{
  "type": "Feature",
  "properties": {
    "iso:country": "GB",
    "wof:name": "NE24 5NH",
    "wof:placetype": "postalcode"
  },
  "geometry": {"coordinates":[-1.52881,55.12693],"type":"Point"}
}
