{
  "type": "Feature",
  "properties": {
    "date:inception_lower":"1991-01-01",
    "date:inception_upper":"1991-01-31",
    "iso:country":"GB",
    "wof:name":"NE24 5NH",
    "wof:placetype":"postalcode"
},
  "geometry": {"coordinates":[-1.52881,55.12693],"type":"Point"}
}