{
  "type": "Feature",
  "properties": {
    "iso:country":"GB",
    "wof:name":"NE24 5NH",
    "wof:placetype":"postalcode"
},
  "geometry": {"coordinates":[-1.52880997622761,55.12692972300201],"type":"Point"}
}