{
  "type": "Feature",
  "properties": {
    "iso:country":"GB",
    "wof:name":"GU17 0JJ",
    "wof:placetype":"postalcode"
},
  "geometry": {"coordinates":[-0.7825142669937,51.33363628483399],"type":"Point"}
}