{
  "type": "Feature",
  "properties": {
    "date:inception_lower": "1980-01-01",
    "date:inception_upper": "1980-01-01",
    "iso:country": "GB",
    "wof:name": "M33 4PX",
    "wof:placetype": "postalcode"
  },
  "geometry": {"coordinates":[-2.345534,53.41535],"type":"Point"}
}
