{
  "type": "Feature",
  "properties": {
    "iso:country":"GB",
    "wof:name":"IP6 8NQ",
    "wof:placetype":"postalcode"
},
  "geometry": {"coordinates":[1.0622688413569,52.16842360235758],"type":"Point"}
}