{
  "type": "Feature",
  "properties": {
    "iso:country": "GB",
    "wof:name": "DD8 1LZ",
    "wof:placetype": "postalcode"
  },
  "geometry": {"coordinates":[-2.8933,56.637232],"type":"Point"}
}
