{
  "type": "Feature",
  "properties": {
    "iso:country":"GB",
    "wof:name":"DD8 1LZ",
    "wof:placetype":"postalcode"
},
  "geometry": {"coordinates":[-2.89330004131587,56.63723197574695],"type":"Point"}
}