{
  "type": "Feature",
  "properties": {
    "iso:country":"GB",
    "wof:name":"SE6 3EH",
    "wof:placetype":"postalcode"
},
  "geometry": {"coordinates":[-0.02140781997942,51.42712812699122],"type":"Point"}
}