{
  "type": "Feature",
  "properties": {
    "iso:country": "GB",
    "wof:name": "MK45 3BX",
    "wof:placetype": "postalcode"
  },
  "geometry": {"coordinates":[-0.446229,52.080339],"type":"Point"}
}
