{
  "type": "Feature",
  "properties": {
    "iso:country":"GB",
    "wof:name":"MK45 3BX",
    "wof:placetype":"postalcode"
},
  "geometry": {"coordinates":[-0.44622886570701,52.08033917961161],"type":"Point"}
}