{
  "type": "Feature",
  "properties": {
    "date:inception_lower":"1980-01-01",
    "date:inception_upper":"1980-01-31",
    "iso:country":"GB",
    "wof:name":"CO9 2HF",
    "wof:placetype":"postalcode"
},
  "geometry": {"coordinates":[0.647753,51.940554],"type":"Point"}
}