{
  "type": "Feature",
  "properties": {
    "iso:country":"GB",
    "wof:name":"CO9 2HF",
    "wof:placetype":"postalcode"
},
  "geometry": {"coordinates":[0.64775254160738,51.94055358085656],"type":"Point"}
}