{
  "type": "Feature",
  "properties": {
    "iso:country": "GB",
    "wof:name": "CO9 2HF",
    "wof:placetype": "postalcode"
  },
  "geometry": {"coordinates":[0.647753,51.940554],"type":"Point"}
}
