{
  "type": "Feature",
  "properties": {
    "date:inception_lower": "1980-01-01",
    "date:inception_upper": "1980-01-01",
    "iso:country": "GB",
    "wof:name": "PE25 3EX",
    "wof:placetype": "postalcode"
  },
  "geometry": {"coordinates":[0.340843,53.13476],"type":"Point"}
}
