{
  "type": "Feature",
  "properties": {
    "date:inception_lower": "2001-12-01",
    "date:inception_upper": "2001-12-01",
    "iso:country": "GB",
    "wof:name": "BN2 9XG",
    "wof:placetype": "postalcode"
  },
  "geometry": {"coordinates":[-0.12425,50.828757],"type":"Point"}
}
