{
  "type": "Feature",
  "properties": {
    "iso:country":"GB",
    "wof:name":"BN2 9XG",
    "wof:placetype":"postalcode"
},
  "geometry": {"coordinates":[-0.12425001268452,50.82875746634782],"type":"Point"}
}