{
  "type": "Feature",
  "properties": {
    "iso:country": "GB",
    "wof:name": "B9 4TL",
    "wof:placetype": "postalcode"
  },
  "geometry": {"coordinates":[-1.856683,52.480996],"type":"Point"}
}
