{
  "type": "Feature",
  "properties": {
    "iso:country":"GB",
    "wof:name":"RG8 7RE",
    "wof:placetype":"postalcode"
},
  "geometry": {"coordinates":[-1.06021954722655,51.50113961795822],"type":"Point"}
}