{
  "type": "Feature",
  "properties": {
    "date:inception_lower": "1980-01-01",
    "date:inception_upper": "1980-01-01",
    "iso:country": "GB",
    "wof:name": "RG8 7RE",
    "wof:placetype": "postalcode"
  },
  "geometry": {"coordinates":[-1.06022,51.50114],"type":"Point"}
}
