{
  "type": "Feature",
  "properties": {
    "iso:country":"GB",
    "wof:name":"N3 3QD",
    "wof:placetype":"postalcode"
},
  "geometry": {"coordinates":[-0.19011284192524,51.59590029036519],"type":"Point"}
}