{
  "type": "Feature",
  "properties": {
    "iso:country":"GB",
    "wof:name":"RM7 7AB",
    "wof:placetype":"postalcode"
},
  "geometry": {"coordinates":[0.17421697904607,51.57784558731115],"type":"Point"}
}