{
  "type": "Feature",
  "properties": {
    "iso:country":"GB",
    "wof:name":"LE15 8EQ",
    "wof:placetype":"postalcode"
},
  "geometry": {"coordinates":[-0.60266655741075,52.58994790830514],"type":"Point"}
}