{
  "type": "Feature",
  "properties": {
    "iso:country": "GB",
    "wof:name": "LE15 8EQ",
    "wof:placetype": "postalcode"
  },
  "geometry": {"coordinates":[-0.602667,52.589948],"type":"Point"}
}
