{
  "type": "Feature",
  "properties": {
    "iso:country": "GB",
    "wof:name": "PO12 3HB",
    "wof:placetype": "postalcode"
  },
  "geometry": {"coordinates":[-1.142406,50.801563],"type":"Point"}
}
