{
  "type": "Feature",
  "properties": {
    "iso:country":"GB",
    "wof:name":"PO12 3HB",
    "wof:placetype":"postalcode"
},
  "geometry": {"coordinates":[-1.14240618576123,50.80156328919854],"type":"Point"}
}