{
  "type": "Feature",
  "properties": {
    "date:inception_lower": "2017-10-01",
    "date:inception_upper": "2017-10-01",
    "iso:country": "GB",
    "wof:name": "CM18 7FL",
    "wof:placetype": "postalcode"
  },
  "geometry": {"coordinates":[0.10488,51.750398],"type":"Point"}
}
