{
  "type": "Feature",
  "properties": {
    "iso:country":"GB",
    "wof:name":"LU6 3TT",
    "wof:placetype":"postalcode"
},
  "geometry": {"coordinates":[-0.51201349854201,51.87826883064375],"type":"Point"}
}