{
  "type": "Feature",
  "properties": {
    "date:inception_lower": "1994-12-01",
    "date:inception_upper": "1994-12-01",
    "iso:country": "GB",
    "wof:name": "LU6 3TT",
    "wof:placetype": "postalcode"
  },
  "geometry": {"coordinates":[-0.512013,51.878269],"type":"Point"}
}
