{
  "type": "Feature",
  "properties": {
    "iso:country":"GB",
    "wof:name":"DE73 6PJ",
    "wof:placetype":"postalcode"
},
  "geometry": {"coordinates":[-1.43597047140789,52.87683894515879],"type":"Point"}
}