{
  "type": "Feature",
  "properties": {
    "iso:country":"GB",
    "wof:name":"LA5 9AN",
    "wof:placetype":"postalcode"
},
  "geometry": {"coordinates":[-2.76316445611438,54.12367909993569],"type":"Point"}
}