{
  "type": "Feature",
  "properties": {
    "iso:country":"GB",
    "wof:name":"HX3 8EE",
    "wof:placetype":"postalcode"
},
  "geometry": {"coordinates":[-1.81182762206075,53.72384899354736],"type":"Point"}
}