{
  "type": "Feature",
  "properties": {
    "iso:country":"GB",
    "wof:name":"PA5 9RR",
    "wof:placetype":"postalcode"
},
  "geometry": {"coordinates":[-4.50387994696088,55.82457267681752],"type":"Point"}
}