{
  "type": "Feature",
  "properties": {
    "iso:country": "GB",
    "wof:name": "TS26 0FJ",
    "wof:placetype": "postalcode"
  },
  "geometry": {"coordinates":[-1.249769,54.679288],"type":"Point"}
}
