{
  "type": "Feature",
  "properties": {
    "iso:country": "GB",
    "wof:name": "NR25 7ND",
    "wof:placetype": "postalcode"
  },
  "geometry": {"coordinates":[1.019446,52.956127],"type":"Point"}
}
