{
  "type": "Feature",
  "properties": {
    "iso:country":"GB",
    "wof:name":"SY20 9DP",
    "wof:placetype":"postalcode"
},
  "geometry": {"coordinates":[-3.92061237503611,52.58698735294097],"type":"Point"}
}