{
  "type": "Feature",
  "properties": {
    "iso:country": "GB",
    "wof:name": "SN4 8DN",
    "wof:placetype": "postalcode"
  },
  "geometry": {"coordinates":[-1.899481,51.54302],"type":"Point"}
}
