{
  "type": "Feature",
  "properties": {
    "iso:country":"GB",
    "wof:name":"SN4 8DN",
    "wof:placetype":"postalcode"
},
  "geometry": {"coordinates":[-1.89946047277503,51.54303696402997],"type":"Point"}
}