{
  "type": "Feature",
  "properties": {
    "iso:country":"GB",
    "wof:name":"FY4 4AE",
    "wof:placetype":"postalcode"
},
  "geometry": {"coordinates":[-3.02902304760656,53.79580669841418],"type":"Point"}
}