{
  "type": "Feature",
  "properties": {
    "iso:country":"GB",
    "wof:name":"GU16 6HD",
    "wof:placetype":"postalcode"
},
  "geometry": {"coordinates":[-0.73003215056593,51.30406119418005],"type":"Point"}
}