{
  "type": "Feature",
  "properties": {
    "iso:country": "GB",
    "wof:name": "GU16 6HD",
    "wof:placetype": "postalcode"
  },
  "geometry": {"coordinates":[-0.730032,51.304061],"type":"Point"}
}
