{
  "type": "Feature",
  "properties": {
    "iso:country": "GB",
    "wof:name": "DN14 9BJ",
    "wof:placetype": "postalcode"
  },
  "geometry": {"coordinates":[-1.052275,53.649583],"type":"Point"}
}
