{
  "type": "Feature",
  "properties": {
    "iso:country":"GB",
    "wof:name":"DN14 9BJ",
    "wof:placetype":"postalcode"
},
  "geometry": {"coordinates":[-1.05227507228093,53.64958307901743],"type":"Point"}
}