{
  "type": "Feature",
  "properties": {
    "iso:country":"GB",
    "wof:name":"ME13 0JS",
    "wof:placetype":"postalcode"
},
  "geometry": {"coordinates":[0.85454046661173,51.24750786456362],"type":"Point"}
}