{
  "type": "Feature",
  "properties": {
    "iso:country": "GB",
    "wof:name": "LS20 9BN",
    "wof:placetype": "postalcode"
  },
  "geometry": {"coordinates":[-1.703411,53.874179],"type":"Point"}
}
