{
  "type": "Feature",
  "properties": {
    "iso:country":"GB",
    "wof:name":"RH20 2PU",
    "wof:placetype":"postalcode"
},
  "geometry": {"coordinates":[-0.46070219309641,50.94778530809916],"type":"Point"}
}