{
  "type": "Feature",
  "properties": {
    "iso:country": "GB",
    "wof:name": "RH20 2PU",
    "wof:placetype": "postalcode"
  },
  "geometry": {"coordinates":[-0.460702,50.947785],"type":"Point"}
}
