{
  "type": "Feature",
  "properties": {
    "date:inception_lower": "1980-01-01",
    "date:inception_upper": "1980-01-01",
    "iso:country": "GB",
    "wof:name": "RH20 2PU",
    "wof:placetype": "postalcode"
  },
  "geometry": {"coordinates":[-0.460702,50.947785],"type":"Point"}
}
