{
  "type": "Feature",
  "properties": {
    "iso:country":"GB",
    "wof:name":"RH1 2EU",
    "wof:placetype":"postalcode"
},
  "geometry": {"coordinates":[-0.167821969107,51.2505982804928],"type":"Point"}
}