{
  "type": "Feature",
  "properties": {
    "iso:country":"GB",
    "wof:name":"PL31 2LZ",
    "wof:placetype":"postalcode"
},
  "geometry": {"coordinates":[-4.72627464100067,50.47253839839881],"type":"Point"}
}