{
  "type": "Feature",
  "properties": {
    "date:inception_lower":"1980-01-01",
    "date:inception_upper":"1980-01-31",
    "iso:country":"GB",
    "wof:name":"PL31 2LZ",
    "wof:placetype":"postalcode"
},
  "geometry": {"coordinates":[-4.726275,50.472538],"type":"Point"}
}