{
  "type": "Feature",
  "properties": {
    "iso:country":"GB",
    "wof:name":"HP21 8AG",
    "wof:placetype":"postalcode"
},
  "geometry": {"coordinates":[-0.80904462086877,51.80295712664018],"type":"Point"}
}