{
  "type": "Feature",
  "properties": {
    "iso:country":"GB",
    "wof:name":"LA13 0NZ",
    "wof:placetype":"postalcode"
},
  "geometry": {"coordinates":[-3.20383866468413,54.13360447943126],"type":"Point"}
}