{
  "type": "Feature",
  "properties": {
    "date:inception_lower": "2007-03-01",
    "date:inception_upper": "2007-03-01",
    "iso:country": "GB",
    "wof:name": "PH22 1TS",
    "wof:placetype": "postalcode"
  },
  "geometry": {"coordinates":[-3.822936,57.2045],"type":"Point"}
}
