{
  "type": "Feature",
  "properties": {
    "iso:country": "GB",
    "wof:name": "LL42 1TL",
    "wof:placetype": "postalcode"
  },
  "geometry": {"coordinates":[-3.999774,52.743543],"type":"Point"}
}
