{
  "type": "Feature",
  "properties": {
    "date:inception_lower":"1980-01-01",
    "date:inception_upper":"1980-01-31",
    "iso:country":"GB",
    "wof:name":"LL42 1TL",
    "wof:placetype":"postalcode"
},
  "geometry": {"coordinates":[-3.999774,52.743543],"type":"Point"}
}