{
  "type": "Feature",
  "properties": {
    "iso:country":"GB",
    "wof:name":"WS7 1JN",
    "wof:placetype":"postalcode"
},
  "geometry": {"coordinates":[-1.93927582459443,52.68553458613096],"type":"Point"}
}