{
  "type": "Feature",
  "properties": {
    "iso:country": "GB",
    "wof:name": "WS7 1JN",
    "wof:placetype": "postalcode"
  },
  "geometry": {"coordinates":[-1.939217,52.68549],"type":"Point"}
}
