{
  "type": "Feature",
  "properties": {
    "iso:country":"GB",
    "wof:name":"TQ7 3NR",
    "wof:placetype":"postalcode"
},
  "geometry": {"coordinates":[-3.86456011717508,50.27077907273093],"type":"Point"}
}