{
  "type": "Feature",
  "properties": {
    "iso:country": "GB",
    "wof:name": "TW18 4HW",
    "wof:placetype": "postalcode"
  },
  "geometry": {"coordinates":[-0.497247,51.439176],"type":"Point"}
}
