{
  "type": "Feature",
  "properties": {
    "iso:country":"GB",
    "wof:name":"CM9 6DL",
    "wof:placetype":"postalcode"
},
  "geometry": {"coordinates":[0.67594883757836,51.72217077961538],"type":"Point"}
}