{
  "type": "Feature",
  "properties": {
    "iso:country":"GB",
    "wof:name":"AB45 2YS",
    "wof:placetype":"postalcode"
},
  "geometry": {"coordinates":[-2.69798345433801,57.64097152344106],"type":"Point"}
}