{
  "type": "Feature",
  "properties": {
    "iso:country":"GB",
    "wof:name":"BA14 8QD",
    "wof:placetype":"postalcode"
},
  "geometry": {"coordinates":[-2.20664065625593,51.32568783688847],"type":"Point"}
}