{
  "type": "Feature",
  "properties": {
    "iso:country":"GB",
    "wof:name":"B98 8DW",
    "wof:placetype":"postalcode"
},
  "geometry": {"coordinates":[-1.93825153683826,52.30791189607845],"type":"Point"}
}