{
  "type": "Feature",
  "properties": {
    "date:inception_lower":"2015-06-01",
    "date:inception_upper":"2015-06-30",
    "iso:country":"GB",
    "wof:name":"ML1 1AH",
    "wof:placetype":"postalcode"
},
  "geometry": {"coordinates":[-3.955387,55.796941],"type":"Point"}
}