{
  "type": "Feature",
  "properties": {
    "iso:country":"GB",
    "wof:name":"ML1 1AH",
    "wof:placetype":"postalcode"
},
  "geometry": {"coordinates":[-3.95434136249176,55.79656576539775],"type":"Point"}
}