{
  "type": "Feature",
  "properties": {
    "iso:country":"GB",
    "wof:name":"SY11 2PD",
    "wof:placetype":"postalcode"
},
  "geometry": {"coordinates":[-3.0552540155651,52.85827580033573],"type":"Point"}
}