{
  "type": "Feature",
  "properties": {
    "iso:country": "GB",
    "wof:name": "G51 3AW",
    "wof:placetype": "postalcode"
  },
  "geometry": {"coordinates":[-4.31683,55.864514],"type":"Point"}
}
