{
  "type": "Feature",
  "properties": {
    "iso:country":"GB",
    "wof:name":"RM5 2SJ",
    "wof:placetype":"postalcode"
},
  "geometry": {"coordinates":[0.16722002323541,51.60763323258076],"type":"Point"}
}