{
  "type": "Feature",
  "properties": {
    "iso:country":"GB",
    "wof:name":"CB7 5UE",
    "wof:placetype":"postalcode"
},
  "geometry": {"coordinates":[0.33446993366364,52.34534672024762],"type":"Point"}
}