{
  "type": "Feature",
  "properties": {
    "date:inception_lower": "1980-01-01",
    "date:inception_upper": "1980-01-01",
    "iso:country": "GB",
    "wof:name": "CB7 5UE",
    "wof:placetype": "postalcode"
  },
  "geometry": {"coordinates":[0.33447,52.345347],"type":"Point"}
}
