{
  "type": "Feature",
  "properties": {
    "iso:country":"GB",
    "wof:name":"BB18 5BS",
    "wof:placetype":"postalcode"
},
  "geometry": {"coordinates":[-2.1842961250875,53.91452429984639],"type":"Point"}
}