{
  "type": "Feature",
  "properties": {
    "date:inception_lower": "1980-01-01",
    "date:inception_upper": "1980-01-01",
    "iso:country": "GB",
    "wof:name": "S7 2NH",
    "wof:placetype": "postalcode"
  },
  "geometry": {"coordinates":[-1.499486,53.345743],"type":"Point"}
}
