{
  "type": "Feature",
  "properties": {
    "iso:country":"GB",
    "wof:name":"S7 2NH",
    "wof:placetype":"postalcode"
},
  "geometry": {"coordinates":[-1.49948574358279,53.34574271019768],"type":"Point"}
}