{
  "type": "Feature",
  "properties": {
    "date:inception_lower": "2012-12-01",
    "date:inception_upper": "2012-12-01",
    "iso:country": "GB",
    "wof:name": "WN6 8FP",
    "wof:placetype": "postalcode"
  },
  "geometry": {"coordinates":[-2.694141,53.562449],"type":"Point"}
}
