{
  "type": "Feature",
  "properties": {
    "date:inception_lower": "1980-01-01",
    "date:inception_upper": "1980-01-01",
    "iso:country": "GB",
    "wof:name": "PH7 3HQ",
    "wof:placetype": "postalcode"
  },
  "geometry": {"coordinates":[-3.848518,56.368753],"type":"Point"}
}
