{
  "type": "Feature",
  "properties": {
    "iso:country":"GB",
    "wof:name":"NW4 4NJ",
    "wof:placetype":"postalcode"
},
  "geometry": {"coordinates":[-0.23317578528206,51.58451573945334],"type":"Point"}
}