{
  "type": "Feature",
  "properties": {
    "iso:country":"GB",
    "wof:name":"SW15 4BB",
    "wof:placetype":"postalcode"
},
  "geometry": {"coordinates":[-0.24473805580173,51.45403891492928],"type":"Point"}
}