{
  "type": "Feature",
  "properties": {
    "iso:country": "GB",
    "wof:name": "SW15 4BB",
    "wof:placetype": "postalcode"
  },
  "geometry": {"coordinates":[-0.244738,51.454039],"type":"Point"}
}
