{
  "type": "Feature",
  "properties": {
    "iso:country":"GB",
    "wof:name":"TA9 4NB",
    "wof:placetype":"postalcode"
},
  "geometry": {"coordinates":[-2.89233521873725,51.22814291246218],"type":"Point"}
}