{
  "type": "Feature",
  "properties": {
    "iso:country": "GB",
    "wof:name": "TA9 4NB",
    "wof:placetype": "postalcode"
  },
  "geometry": {"coordinates":[-2.892257,51.228121],"type":"Point"}
}
