{
  "type": "Feature",
  "properties": {
    "iso:country":"GB",
    "wof:name":"ME19 4NT",
    "wof:placetype":"postalcode"
},
  "geometry": {"coordinates":[0.39417766734477,51.2651729639725],"type":"Point"}
}