{
  "type": "Feature",
  "properties": {
    "date:inception_lower":"1992-08-01",
    "date:inception_upper":"1992-08-31",
    "iso:country":"GB",
    "wof:name":"DE65 6FD",
    "wof:placetype":"postalcode"
},
  "geometry": {"coordinates":[-1.531796,52.818437],"type":"Point"}
}