{
  "type": "Feature",
  "properties": {
    "iso:country": "GB",
    "wof:name": "BH21 1UD",
    "wof:placetype": "postalcode"
  },
  "geometry": {"coordinates":[-1.97403,50.787409],"type":"Point"}
}
