{
  "type": "Feature",
  "properties": {
    "iso:country": "GB",
    "wof:name": "TA7 8PP",
    "wof:placetype": "postalcode"
  },
  "geometry": {"coordinates":[-2.934144,51.155829],"type":"Point"}
}
