{
  "type": "Feature",
  "properties": {
    "iso:country":"GB",
    "wof:name":"TA7 8PP",
    "wof:placetype":"postalcode"
},
  "geometry": {"coordinates":[-2.93415095193603,51.15582500862115],"type":"Point"}
}