{
  "type": "Feature",
  "properties": {
    "iso:country":"GB",
    "wof:name":"S81 0UG",
    "wof:placetype":"postalcode"
},
  "geometry": {"coordinates":[-1.04059394378743,53.3176236923262],"type":"Point"}
}