{
  "type": "Feature",
  "properties": {
    "iso:country": "GB",
    "wof:name": "S81 0UG",
    "wof:placetype": "postalcode"
  },
  "geometry": {"coordinates":[-1.039956,53.317944],"type":"Point"}
}
