{
  "type": "Feature",
  "properties": {
    "date:inception_lower": "2016-11-01",
    "date:inception_upper": "2016-11-01",
    "iso:country": "GB",
    "wof:name": "M5 3LH",
    "wof:placetype": "postalcode"
  },
  "geometry": {"coordinates":[-2.280786,53.471239],"type":"Point"}
}
