{
  "type": "Feature",
  "properties": {
    "iso:country":"GB",
    "wof:name":"CR4 1LU",
    "wof:placetype":"postalcode"
},
  "geometry": {"coordinates":[-0.13259712752941,51.39977128718409],"type":"Point"}
}