{
  "type": "Feature",
  "properties": {
    "iso:country":"GB",
    "wof:name":"IP24 3RY",
    "wof:placetype":"postalcode"
},
  "geometry": {"coordinates":[0.72870411863027,52.40866662429293],"type":"Point"}
}