{
  "type": "Feature",
  "properties": {
    "date:inception_lower": "2000-06-01",
    "date:inception_upper": "2000-06-01",
    "iso:country": "GB",
    "wof:name": "PE19 8PT",
    "wof:placetype": "postalcode"
  },
  "geometry": {"coordinates":[-0.294027,52.216208],"type":"Point"}
}
