{
  "type": "Feature",
  "properties": {
    "iso:country":"GB",
    "wof:name":"PE19 8PT",
    "wof:placetype":"postalcode"
},
  "geometry": {"coordinates":[-0.29402691098987,52.21620833990509],"type":"Point"}
}