{
  "type": "Feature",
  "properties": {
    "date:inception_lower": "1980-01-01",
    "date:inception_upper": "1980-01-01",
    "iso:country": "GB",
    "wof:name": "KY1 3HH",
    "wof:placetype": "postalcode"
  },
  "geometry": {"coordinates":[-3.132346,56.133515],"type":"Point"}
}
