{
  "type": "Feature",
  "properties": {
    "iso:country":"GB",
    "wof:name":"KY1 3HH",
    "wof:placetype":"postalcode"
},
  "geometry": {"coordinates":[-3.13279334813907,56.13346360422346],"type":"Point"}
}