{
  "type": "Feature",
  "properties": {
    "iso:country":"GB",
    "wof:name":"SG1 4FG",
    "wof:placetype":"postalcode"
},
  "geometry": {"coordinates":[-0.21024329151274,51.92304430043503],"type":"Point"}
}