{
  "type": "Feature",
  "properties": {
    "date:inception_lower": "2008-09-01",
    "date:inception_upper": "2008-09-01",
    "iso:country": "GB",
    "wof:name": "SG1 4FG",
    "wof:placetype": "postalcode"
  },
  "geometry": {"coordinates":[-0.210243,51.923044],"type":"Point"}
}
