{
  "type": "Feature",
  "properties": {
    "date:inception_lower": "2006-03-01",
    "date:inception_upper": "2006-03-01",
    "iso:country": "GB",
    "wof:name": "BL9 6DN",
    "wof:placetype": "postalcode"
  },
  "geometry": {"coordinates":[-2.288263,53.600547],"type":"Point"}
}
