{
  "type": "Feature",
  "properties": {
    "iso:country":"GB",
    "wof:name":"BL9 6DN",
    "wof:placetype":"postalcode"
},
  "geometry": {"coordinates":[-2.28808197414278,53.60058306374047],"type":"Point"}
}