{
  "type": "Feature",
  "properties": {
    "iso:country": "GB",
    "wof:name": "NG24 1LH",
    "wof:placetype": "postalcode"
  },
  "geometry": {"coordinates":[-0.805281,53.078685],"type":"Point"}
}
