{
  "type": "Feature",
  "properties": {
    "iso:country":"GB",
    "wof:name":"PE13 5DF",
    "wof:placetype":"postalcode"
},
  "geometry": {"coordinates":[0.13489079602057,52.67724097175685],"type":"Point"}
}