{
  "type": "Feature",
  "properties": {
    "iso:country":"GB",
    "wof:name":"SN10 5UQ",
    "wof:placetype":"postalcode"
},
  "geometry": {"coordinates":[-2.0295823686757,51.29733593300935],"type":"Point"}
}