{
  "type": "Feature",
  "properties": {
    "iso:country": "GB",
    "wof:name": "NE15 9EW",
    "wof:placetype": "postalcode"
  },
  "geometry": {"coordinates":[-1.752198,55.000183],"type":"Point"}
}
