{
  "type": "Feature",
  "properties": {
    "date:inception_lower":"2003-07-01",
    "date:inception_upper":"2003-07-31",
    "iso:country":"GB",
    "wof:name":"IP17 3AU",
    "wof:placetype":"postalcode"
},
  "geometry": {"coordinates":[1.580318,52.267575],"type":"Point"}
}