{
  "type": "Feature",
  "properties": {
    "iso:country":"GB",
    "wof:name":"IP17 3AU",
    "wof:placetype":"postalcode"
},
  "geometry": {"coordinates":[1.58089632370321,52.26746314047889],"type":"Point"}
}