{
  "type": "Feature",
  "properties": {
    "iso:country":"GB",
    "wof:name":"BN5 9HS",
    "wof:placetype":"postalcode"
},
  "geometry": {"coordinates":[-0.26831429857938,50.93214977957984],"type":"Point"}
}