{
  "type": "Feature",
  "properties": {
    "iso:country": "GB",
    "wof:name": "BN5 9HS",
    "wof:placetype": "postalcode"
  },
  "geometry": {"coordinates":[-0.268314,50.93215],"type":"Point"}
}
