{
  "type": "Feature",
  "properties": {
    "date:inception_lower": "1980-01-01",
    "date:inception_upper": "1980-01-01",
    "iso:country": "GB",
    "wof:name": "BN5 9HS",
    "wof:placetype": "postalcode"
  },
  "geometry": {"coordinates":[-0.268314,50.93215],"type":"Point"}
}
