{
  "type": "Feature",
  "properties": {
    "date:inception_lower":"2005-04-01",
    "date:inception_upper":"2005-04-30",
    "iso:country":"GB",
    "wof:name":"DH1 5SE",
    "wof:placetype":"postalcode"
},
  "geometry": {"coordinates":[-1.589212,54.785795],"type":"Point"}
}