{
  "type": "Feature",
  "properties": {
    "date:inception_lower": "1980-01-01",
    "date:inception_upper": "1980-01-01",
    "iso:country": "GB",
    "wof:name": "WS2 8PP",
    "wof:placetype": "postalcode"
  },
  "geometry": {"coordinates":[-1.999307,52.586897],"type":"Point"}
}
