{
  "type": "Feature",
  "properties": {
    "date:inception_lower":"2015-06-01",
    "date:inception_upper":"2015-06-30",
    "iso:country":"GB",
    "wof:name":"LE11 2US",
    "wof:placetype":"postalcode"
},
  "geometry": {"coordinates":[-1.208408,52.747231],"type":"Point"}
}