{
  "type": "Feature",
  "properties": {
    "iso:country":"GB",
    "wof:name":"TS17 5LA",
    "wof:placetype":"postalcode"
},
  "geometry": {"coordinates":[-1.32708919864619,54.52966723111986],"type":"Point"}
}