{
  "type": "Feature",
  "properties": {
    "iso:country": "GB",
    "wof:name": "LS15 0DY",
    "wof:placetype": "postalcode"
  },
  "geometry": {"coordinates":[-1.475501,53.795968],"type":"Point"}
}
