{
  "type": "Feature",
  "properties": {
    "iso:country": "GB",
    "wof:name": "TS7 8EY",
    "wof:placetype": "postalcode"
  },
  "geometry": {"coordinates":[-1.202817,54.530656],"type":"Point"}
}
