{
  "type": "Feature",
  "properties": {
    "date:inception_lower": "1995-07-01",
    "date:inception_upper": "1995-07-01",
    "iso:country": "GB",
    "wof:name": "LA16 7HZ",
    "wof:placetype": "postalcode"
  },
  "geometry": {"coordinates":[-3.210789,54.18873],"type":"Point"}
}
