{
  "type": "Feature",
  "properties": {
    "iso:country":"GB",
    "wof:name":"LA16 7HZ",
    "wof:placetype":"postalcode"
},
  "geometry": {"coordinates":[-3.21078892236752,54.18873029857924],"type":"Point"}
}