{
  "type": "Feature",
  "properties": {
    "date:inception_lower":"2002-10-01",
    "date:inception_upper":"2002-10-31",
    "iso:country":"GB",
    "wof:name":"CB7 5RJ",
    "wof:placetype":"postalcode"
},
  "geometry": {"coordinates":[0.405958,52.336673],"type":"Point"}
}