{
  "type": "Feature",
  "properties": {
    "date:inception_lower": "1990-08-01",
    "date:inception_upper": "1990-08-01",
    "iso:country": "GB",
    "wof:name": "AB44 1XA",
    "wof:placetype": "postalcode"
  },
  "geometry": {"coordinates":[-2.499597,57.668194],"type":"Point"}
}
