{
  "type": "Feature",
  "properties": {
    "date:inception_lower": "1980-01-01",
    "date:inception_upper": "1980-01-01",
    "iso:country": "GB",
    "wof:name": "LS8 1JG",
    "wof:placetype": "postalcode"
  },
  "geometry": {"coordinates":[-1.511734,53.836891],"type":"Point"}
}
