{
  "type": "Feature",
  "properties": {
    "iso:country": "GB",
    "wof:name": "LS8 1JG",
    "wof:placetype": "postalcode"
  },
  "geometry": {"coordinates":[-1.511734,53.836891],"type":"Point"}
}
