{
  "type": "Feature",
  "properties": {
    "iso:country":"GB",
    "wof:name":"TR14 7DX",
    "wof:placetype":"postalcode"
},
  "geometry": {"coordinates":[-5.30504708694038,50.21180054883465],"type":"Point"}
}