{
  "type": "Feature",
  "properties": {
    "iso:country":"GB",
    "wof:name":"SA18 1TR",
    "wof:placetype":"postalcode"
},
  "geometry": {"coordinates":[-3.87996203480353,51.80083032780511],"type":"Point"}
}