{
  "type": "Feature",
  "properties": {
    "date:inception_lower": "2018-03-01",
    "date:inception_upper": "2018-03-01",
    "iso:country": "GB",
    "wof:name": "RG28 7FS",
    "wof:placetype": "postalcode"
  },
  "geometry": {"coordinates":[-1.336161,51.221245],"type":"Point"}
}
