{
  "type": "Feature",
  "properties": {
    "iso:country":"GB",
    "wof:name":"G76 0DR",
    "wof:placetype":"postalcode"
},
  "geometry": {"coordinates":[-4.27115600598501,55.74787122489607],"type":"Point"}
}