{
  "type": "Feature",
  "properties": {
    "iso:country":"GB",
    "wof:name":"CV8 3EQ",
    "wof:placetype":"postalcode"
},
  "geometry": {"coordinates":[-1.42046069478552,52.35295143787132],"type":"Point"}
}