{
  "type": "Feature",
  "properties": {
    "date:inception_lower": "1980-01-01",
    "date:inception_upper": "1980-01-01",
    "iso:country": "GB",
    "wof:name": "CF5 3AX",
    "wof:placetype": "postalcode"
  },
  "geometry": {"coordinates":[-3.234448,51.486579],"type":"Point"}
}
