{
  "type": "Feature",
  "properties": {
    "iso:country": "GB",
    "wof:name": "CF5 3AX",
    "wof:placetype": "postalcode"
  },
  "geometry": {"coordinates":[-3.234448,51.486579],"type":"Point"}
}
