{
  "type": "Feature",
  "properties": {
    "iso:country": "GB",
    "wof:name": "G33 6JE",
    "wof:placetype": "postalcode"
  },
  "geometry": {"coordinates":[-4.138437,55.890949],"type":"Point"}
}
