{
  "type": "Feature",
  "properties": {
    "iso:country":"GB",
    "wof:name":"G33 6JE",
    "wof:placetype":"postalcode"
},
  "geometry": {"coordinates":[-4.1384374317735,55.89094903448958],"type":"Point"}
}