{
  "type": "Feature",
  "properties": {
    "date:inception_lower": "2005-10-01",
    "date:inception_upper": "2005-10-01",
    "iso:country": "GB",
    "wof:name": "G33 6JE",
    "wof:placetype": "postalcode"
  },
  "geometry": {"coordinates":[-4.138437,55.890949],"type":"Point"}
}
