{
  "type": "Feature",
  "properties": {
    "iso:country":"GB",
    "wof:name":"M20 2JL",
    "wof:placetype":"postalcode"
},
  "geometry": {"coordinates":[-2.24501487236974,53.42284335740716],"type":"Point"}
}