{
  "type": "Feature",
  "properties": {
    "iso:country": "GB",
    "wof:name": "DL1 5BD",
    "wof:placetype": "postalcode"
  },
  "geometry": {"coordinates":[-1.551246,54.512121],"type":"Point"}
}
