{
  "type": "Feature",
  "properties": {
    "iso:country":"GB",
    "wof:name":"LS28 9LX",
    "wof:placetype":"postalcode"
},
  "geometry": {"coordinates":[-1.65776396356004,53.78880667609033],"type":"Point"}
}