{
  "type": "Feature",
  "properties": {
    "iso:country":"GB",
    "wof:name":"KT9 1XD",
    "wof:placetype":"postalcode"
},
  "geometry": {"coordinates":[-0.28793197115366,51.36665017090963],"type":"Point"}
}