{
  "type": "Feature",
  "properties": {
    "iso:country":"GB",
    "wof:name":"EC2N 1EX",
    "wof:placetype":"postalcode"
},
  "geometry": {"coordinates":[-0.08444425026955,51.51579052714781],"type":"Point"}
}