{
  "type": "Feature",
  "properties": {
    "iso:country": "GB",
    "wof:name": "KA1 3XB",
    "wof:placetype": "postalcode"
  },
  "geometry": {"coordinates":[-4.490074,55.602601],"type":"Point"}
}
