{
  "type": "Feature",
  "properties": {
    "iso:country":"GB",
    "wof:name":"KA1 3XB",
    "wof:placetype":"postalcode"
},
  "geometry": {"coordinates":[-4.48985444642882,55.60008066748092],"type":"Point"}
}