{
  "type": "Feature",
  "properties": {
    "date:inception_lower": "1998-12-01",
    "date:inception_upper": "1998-12-01",
    "iso:country": "GB",
    "wof:name": "KA1 3XB",
    "wof:placetype": "postalcode"
  },
  "geometry": {"coordinates":[-4.49091,55.602278],"type":"Point"}
}
