{
  "type": "Feature",
  "properties": {
    "date:inception_lower": "2024-01-01",
    "date:inception_upper": "2024-01-01",
    "iso:country": "GB",
    "wof:name": "NE6 9EG",
    "wof:placetype": "postalcode"
  },
  "geometry": {"coordinates":[-1.578941,54.977833],"type":"Point"}
}
