{
  "type": "Feature",
  "properties": {
    "iso:country":"GB",
    "wof:name":"SA62 5ES",
    "wof:placetype":"postalcode"
},
  "geometry": {"coordinates":[-5.06773717386336,51.93819849527119],"type":"Point"}
}