{
  "type": "Feature",
  "properties": {
    "iso:country": "GB",
    "wof:name": "WV13 2HQ",
    "wof:placetype": "postalcode"
  },
  "geometry": {"coordinates":[-2.046698,52.583606],"type":"Point"}
}
