{
  "type": "Feature",
  "properties": {
    "iso:country":"GB",
    "wof:name":"WV13 2HQ",
    "wof:placetype":"postalcode"
},
  "geometry": {"coordinates":[-2.04669782618403,52.58360624031597],"type":"Point"}
}