{
  "type": "Feature",
  "properties": {
    "iso:country":"GB",
    "wof:name":"OX7 7DD",
    "wof:placetype":"postalcode"
},
  "geometry": {"coordinates":[-1.35529132167969,51.92947961148434],"type":"Point"}
}