{
  "type": "Feature",
  "properties": {
    "date:inception_lower": "1991-09-01",
    "date:inception_upper": "1991-09-01",
    "iso:country": "GB",
    "wof:name": "OX7 7DD",
    "wof:placetype": "postalcode"
  },
  "geometry": {"coordinates":[-1.355291,51.92948],"type":"Point"}
}
