{
  "type": "Feature",
  "properties": {
    "iso:country": "GB",
    "wof:name": "BS34 6FD",
    "wof:placetype": "postalcode"
  },
  "geometry": {"coordinates":[-2.565856,51.521905],"type":"Point"}
}
