{
  "type": "Feature",
  "properties": {
    "iso:country": "GB",
    "wof:name": "WC2R 0DA",
    "wof:placetype": "postalcode"
  },
  "geometry": {"coordinates":[-0.1197,51.510498],"type":"Point"}
}
