{
  "type": "Feature",
  "properties": {
    "date:inception_lower": "1999-12-01",
    "date:inception_upper": "1999-12-01",
    "iso:country": "GB",
    "wof:name": "PR6 0PF",
    "wof:placetype": "postalcode"
  },
  "geometry": {"coordinates":[-2.621959,53.649783],"type":"Point"}
}
