{
  "type": "Feature",
  "properties": {
    "iso:country":"GB",
    "wof:name":"N1 1BL",
    "wof:placetype":"postalcode"
},
  "geometry": {"coordinates":[-0.11594538551088,51.54141686120794],"type":"Point"}
}