{
  "type": "Feature",
  "properties": {
    "iso:country": "GB",
    "wof:name": "IP23 8HT",
    "wof:placetype": "postalcode"
  },
  "geometry": {"coordinates":[1.043084,52.303958],"type":"Point"}
}
