{
  "type": "Feature",
  "properties": {
    "date:inception_lower": "1980-01-01",
    "date:inception_upper": "1980-01-01",
    "iso:country": "GB",
    "wof:name": "IP23 8HT",
    "wof:placetype": "postalcode"
  },
  "geometry": {"coordinates":[1.043703,52.304006],"type":"Point"}
}
