{
  "type": "Feature",
  "properties": {
    "iso:country":"GB",
    "wof:name":"S71 5HW",
    "wof:placetype":"postalcode"
},
  "geometry": {"coordinates":[-1.43978419103409,53.56277691310986],"type":"Point"}
}