{
  "type": "Feature",
  "properties": {
    "date:inception_lower":"1995-07-01",
    "date:inception_upper":"1995-07-31",
    "iso:country":"GB",
    "wof:name":"S71 5HW",
    "wof:placetype":"postalcode"
},
  "geometry": {"coordinates":[-1.439784,53.562777],"type":"Point"}
}