{
  "type": "Feature",
  "properties": {
    "date:inception_lower": "1980-01-01",
    "date:inception_upper": "1980-01-01",
    "iso:country": "GB",
    "wof:name": "CH1 5JG",
    "wof:placetype": "postalcode"
  },
  "geometry": {"coordinates":[-2.933185,53.204374],"type":"Point"}
}
