{
  "type": "Feature",
  "properties": {
    "iso:country":"GB",
    "wof:name":"TS14 7EZ",
    "wof:placetype":"postalcode"
},
  "geometry": {"coordinates":[-1.06361949275781,54.5291912607599],"type":"Point"}
}