{
  "type": "Feature",
  "properties": {
    "iso:country":"GB",
    "wof:name":"WV5 7JJ",
    "wof:placetype":"postalcode"
},
  "geometry": {"coordinates":[-2.23254967620884,52.55186832998483],"type":"Point"}
}