{
  "type": "Feature",
  "properties": {
    "iso:country": "GB",
    "wof:name": "WV5 7JJ",
    "wof:placetype": "postalcode"
  },
  "geometry": {"coordinates":[-2.23255,52.551868],"type":"Point"}
}
