{
  "type": "Feature",
  "properties": {
    "date:inception_lower":"2000-12-01",
    "date:inception_upper":"2000-12-31",
    "iso:country":"GB",
    "wof:name":"WV5 7JJ",
    "wof:placetype":"postalcode"
},
  "geometry": {"coordinates":[-2.23255,52.551868],"type":"Point"}
}