{
  "type": "Feature",
  "properties": {
    "iso:country":"GB",
    "wof:name":"DL13 1SQ",
    "wof:placetype":"postalcode"
},
  "geometry": {"coordinates":[-2.13988202469955,54.73606568173094],"type":"Point"}
}