{
  "type": "Feature",
  "properties": {
    "iso:country":"GB",
    "wof:name":"W9 1LG",
    "wof:placetype":"postalcode"
},
  "geometry": {"coordinates":[-0.19290529818542,51.52878823019721],"type":"Point"}
}