{
  "type": "Feature",
  "properties": {
    "iso:country": "GB",
    "wof:name": "S36 2QD",
    "wof:placetype": "postalcode"
  },
  "geometry": {"coordinates":[-1.579695,53.478724],"type":"Point"}
}
