{
  "type": "Feature",
  "properties": {
    "iso:country":"GB",
    "wof:name":"NE61 2YL",
    "wof:placetype":"postalcode"
},
  "geometry": {"coordinates":[-1.70037874207203,55.16765720257141],"type":"Point"}
}