{
  "type": "Feature",
  "properties": {
    "date:inception_lower": "1980-01-01",
    "date:inception_upper": "1980-01-01",
    "iso:country": "GB",
    "wof:name": "EX31 4QR",
    "wof:placetype": "postalcode"
  },
  "geometry": {"coordinates":[-3.914613,51.214944],"type":"Point"}
}
