{
  "type": "Feature",
  "properties": {
    "iso:country": "GB",
    "wof:name": "EX31 4QR",
    "wof:placetype": "postalcode"
  },
  "geometry": {"coordinates":[-3.914613,51.214944],"type":"Point"}
}
