{
  "type": "Feature",
  "properties": {
    "iso:country":"GB",
    "wof:name":"TQ5 0NF",
    "wof:placetype":"postalcode"
},
  "geometry": {"coordinates":[-3.56828655040195,50.39517931988218],"type":"Point"}
}