{
  "type": "Feature",
  "properties": {
    "iso:country":"GB",
    "wof:name":"DY1 3DG",
    "wof:placetype":"postalcode"
},
  "geometry": {"coordinates":[-2.10345570102542,52.51916683060226],"type":"Point"}
}