{
  "type": "Feature",
  "properties": {
    "iso:country":"GB",
    "wof:name":"NR14 7QA",
    "wof:placetype":"postalcode"
},
  "geometry": {"coordinates":[1.35193942416114,52.58650778707533],"type":"Point"}
}