{
  "type": "Feature",
  "properties": {
    "date:inception_lower":"2006-07-01",
    "date:inception_upper":"2006-07-31",
    "iso:country":"GB",
    "wof:name":"OL2 6WJ",
    "wof:placetype":"postalcode"
},
  "geometry": {"coordinates":[-2.111588,53.56692],"type":"Point"}
}