{
  "type": "Feature",
  "properties": {
    "iso:country":"GB",
    "wof:name":"SO19 6HJ",
    "wof:placetype":"postalcode"
},
  "geometry": {"coordinates":[-1.33106284122087,50.90240805359986],"type":"Point"}
}