{
  "type": "Feature",
  "properties": {
    "date:inception_lower": "1980-01-01",
    "date:inception_upper": "1980-01-01",
    "iso:country": "GB",
    "wof:name": "SY3 8PP",
    "wof:placetype": "postalcode"
  },
  "geometry": {"coordinates":[-2.768108,52.712295],"type":"Point"}
}
