{
  "type": "Feature",
  "properties": {
    "iso:country":"GB",
    "wof:name":"PE13 3JS",
    "wof:placetype":"postalcode"
},
  "geometry": {"coordinates":[0.1545455996236,52.67653457663934],"type":"Point"}
}