{
  "type": "Feature",
  "properties": {
    "iso:country":"GB",
    "wof:name":"S80 1EH",
    "wof:placetype":"postalcode"
},
  "geometry": {"coordinates":[-1.12549275209646,53.30465772546624],"type":"Point"}
}