{
  "type": "Feature",
  "properties": {
    "date:inception_lower": "2024-08-01",
    "date:inception_upper": "2024-08-01",
    "iso:country": "GB",
    "wof:name": "GL13 9FT",
    "wof:placetype": "postalcode"
  },
  "geometry": {"coordinates":[-2.461122,51.69796],"type":"Point"}
}
