{
  "type": "Feature",
  "properties": {
    "iso:country":"GB",
    "wof:name":"L37 2EH",
    "wof:placetype":"postalcode"
},
  "geometry": {"coordinates":[-3.08852403646399,53.5458557299791],"type":"Point"}
}