{
  "type": "Feature",
  "properties": {
    "date:inception_lower": "1997-12-01",
    "date:inception_upper": "1997-12-01",
    "iso:country": "GB",
    "wof:name": "SK15 3AL",
    "wof:placetype": "postalcode"
  },
  "geometry": {"coordinates":[-2.050459,53.484978],"type":"Point"}
}
