{
  "type": "Feature",
  "properties": {
    "iso:country":"GB",
    "wof:name":"SK15 3AL",
    "wof:placetype":"postalcode"
},
  "geometry": {"coordinates":[-2.0507615566368,53.48490703691719],"type":"Point"}
}