{
  "type": "Feature",
  "properties": {
    "iso:country":"GB",
    "wof:name":"B60 4ET",
    "wof:placetype":"postalcode"
},
  "geometry": {"coordinates":[-2.08788371295515,52.2931600127905],"type":"Point"}
}