{
  "type": "Feature",
  "properties": {
    "iso:country":"GB",
    "wof:name":"CM18 7QR",
    "wof:placetype":"postalcode"
},
  "geometry": {"coordinates":[0.08804981019998,51.75233792327281],"type":"Point"}
}