{
  "type": "Feature",
  "properties": {
    "iso:country":"GB",
    "wof:name":"RM8 3HD",
    "wof:placetype":"postalcode"
},
  "geometry": {"coordinates":[0.14671720457904,51.55997967494434],"type":"Point"}
}