{
  "type": "Feature",
  "properties": {
    "iso:country":"GB",
    "wof:name":"RH9 8EA",
    "wof:placetype":"postalcode"
},
  "geometry": {"coordinates":[-0.06625603317014,51.24471059480651],"type":"Point"}
}