{
  "type": "Feature",
  "properties": {
    "iso:country":"GB",
    "wof:name":"OX26 4UL",
    "wof:placetype":"postalcode"
},
  "geometry": {"coordinates":[-1.13663025474938,51.90438803067426],"type":"Point"}
}