{
  "type": "Feature",
  "properties": {
    "date:inception_lower": "2006-09-01",
    "date:inception_upper": "2006-09-01",
    "iso:country": "GB",
    "wof:name": "CB23 7QX",
    "wof:placetype": "postalcode"
  },
  "geometry": {"coordinates":[-0.002549,52.196227],"type":"Point"}
}
