{
  "type": "Feature",
  "properties": {
    "iso:country":"GB",
    "wof:name":"B66 1RE",
    "wof:placetype":"postalcode"
},
  "geometry": {"coordinates":[-1.99281163860623,52.50157386700132],"type":"Point"}
}