{
  "type": "Feature",
  "properties": {
    "date:inception_lower":"2009-01-01",
    "date:inception_upper":"2009-01-31",
    "iso:country":"GB",
    "wof:name":"SY23 3GL",
    "wof:placetype":"postalcode"
},
  "geometry": {"coordinates":[-4.06177,52.415563],"type":"Point"}
}