{
  "type": "Feature",
  "properties": {
    "iso:country":"GB",
    "wof:name":"SY23 3GL",
    "wof:placetype":"postalcode"
},
  "geometry": {"coordinates":[-4.06180235766507,52.41551946721999],"type":"Point"}
}