{
  "type": "Feature",
  "properties": {
    "iso:country":"GB",
    "wof:name":"SA62 4HN",
    "wof:placetype":"postalcode"
},
  "geometry": {"coordinates":[-4.90110705817192,51.74894592427443],"type":"Point"}
}