{
  "type": "Feature",
  "properties": {
    "date:inception_lower": "1980-01-01",
    "date:inception_upper": "1980-01-01",
    "iso:country": "GB",
    "wof:name": "SA62 4HN",
    "wof:placetype": "postalcode"
  },
  "geometry": {"coordinates":[-4.901107,51.748946],"type":"Point"}
}
