{
  "type": "Feature",
  "properties": {
    "iso:country": "GB",
    "wof:name": "DY6 7XQ",
    "wof:placetype": "postalcode"
  },
  "geometry": {"coordinates":[-2.154469,52.506297],"type":"Point"}
}
