{
  "type": "Feature",
  "properties": {
    "date:inception_lower":"1999-06-01",
    "date:inception_upper":"1999-06-30",
    "iso:country":"GB",
    "wof:name":"DY6 7XQ",
    "wof:placetype":"postalcode"
},
  "geometry": {"coordinates":[-2.154469,52.506297],"type":"Point"}
}