{
  "type": "Feature",
  "properties": {
    "date:inception_lower": "2019-04-01",
    "date:inception_upper": "2019-04-01",
    "iso:country": "GB",
    "wof:name": "PR4 0QE",
    "wof:placetype": "postalcode"
  },
  "geometry": {"coordinates":[-2.749516,53.79431],"type":"Point"}
}
