{
  "type": "Feature",
  "properties": {
    "iso:country":"GB",
    "wof:name":"B98 0EX",
    "wof:placetype":"postalcode"
},
  "geometry": {"coordinates":[-1.90098687563822,52.29290888883954],"type":"Point"}
}