{
  "type": "Feature",
  "properties": {
    "iso:country": "GB",
    "wof:name": "B98 0EX",
    "wof:placetype": "postalcode"
  },
  "geometry": {"coordinates":[-1.900987,52.292909],"type":"Point"}
}
