{
  "type": "Feature",
  "properties": {
    "iso:country":"GB",
    "wof:name":"PO7 7UF",
    "wof:placetype":"postalcode"
},
  "geometry": {"coordinates":[-1.04830852271174,50.89021252234591],"type":"Point"}
}