{
  "type": "Feature",
  "properties": {
    "date:inception_lower": "2011-09-01",
    "date:inception_upper": "2011-09-01",
    "iso:country": "GB",
    "wof:name": "PO7 7UF",
    "wof:placetype": "postalcode"
  },
  "geometry": {"coordinates":[-1.048308,50.890213],"type":"Point"}
}
