{
  "type": "Feature",
  "properties": {
    "iso:country":"GB",
    "wof:name":"BD24 9EJ",
    "wof:placetype":"postalcode"
},
  "geometry": {"coordinates":[-2.27603286735042,54.06837940893726],"type":"Point"}
}