{
  "type": "Feature",
  "properties": {
    "iso:country":"GB",
    "wof:name":"DE4 3BD",
    "wof:placetype":"postalcode"
},
  "geometry": {"coordinates":[-1.5704352517596,53.14597189823945],"type":"Point"}
}