{
  "type": "Feature",
  "properties": {
    "iso:country":"GB",
    "wof:name":"M4 1PQ",
    "wof:placetype":"postalcode"
},
  "geometry": {"coordinates":[-2.23771643845283,53.48206537052217],"type":"Point"}
}