{
  "type": "Feature",
  "properties": {
    "iso:country": "GB",
    "wof:name": "CA11 7TN",
    "wof:placetype": "postalcode"
  },
  "geometry": {"coordinates":[-2.750381,54.665802],"type":"Point"}
}
