{
  "type": "Feature",
  "properties": {
    "iso:country": "GB",
    "wof:name": "TW3 3BW",
    "wof:placetype": "postalcode"
  },
  "geometry": {"coordinates":[-0.368106,51.468653],"type":"Point"}
}
