{
  "type": "Feature",
  "properties": {
    "date:inception_lower": "2019-02-01",
    "date:inception_upper": "2019-02-01",
    "iso:country": "GB",
    "wof:name": "PL19 1EU",
    "wof:placetype": "postalcode"
  },
  "geometry": {"coordinates":[-4.147065,50.544311],"type":"Point"}
}
