{
  "type": "Feature",
  "properties": {
    "date:inception_lower": "2019-12-01",
    "date:inception_upper": "2019-12-01",
    "iso:country": "GB",
    "wof:name": "SK12 2GF",
    "wof:placetype": "postalcode"
  },
  "geometry": {"coordinates":[-2.012791,53.357458],"type":"Point"}
}
