{
  "type": "Feature",
  "properties": {
    "iso:country": "GB",
    "wof:name": "SK12 2GF",
    "wof:placetype": "postalcode"
  },
  "geometry": {"coordinates":[-2.012791,53.357458],"type":"Point"}
}
