{
  "type": "Feature",
  "properties": {
    "iso:country": "GB",
    "wof:name": "HP20 9SJ",
    "wof:placetype": "postalcode"
  },
  "geometry": {"coordinates":[-0.826547,51.822617],"type":"Point"}
}
