{
  "type": "Feature",
  "properties": {
    "date:inception_lower":"1980-01-01",
    "date:inception_upper":"1980-01-31",
    "iso:country":"GB",
    "wof:name":"IP18 6UH",
    "wof:placetype":"postalcode"
},
  "geometry": {"coordinates":[1.655549,52.313547],"type":"Point"}
}