{
  "type": "Feature",
  "properties": {
    "iso:country":"GB",
    "wof:name":"IP18 6UH",
    "wof:placetype":"postalcode"
},
  "geometry": {"coordinates":[1.65554876991234,52.31354712577917],"type":"Point"}
}