{
  "type": "Feature",
  "properties": {
    "iso:country": "GB",
    "wof:name": "IP18 6UH",
    "wof:placetype": "postalcode"
  },
  "geometry": {"coordinates":[1.655549,52.313547],"type":"Point"}
}
