{
  "type": "Feature",
  "properties": {
    "date:inception_lower":"1993-01-01",
    "date:inception_upper":"1993-01-31",
    "iso:country":"GB",
    "wof:name":"CF64 4HQ",
    "wof:placetype":"postalcode"
},
  "geometry": {"coordinates":[-3.22219,51.449903],"type":"Point"}
}