{
  "type": "Feature",
  "properties": {
    "iso:country": "GB",
    "wof:name": "CF64 4HQ",
    "wof:placetype": "postalcode"
  },
  "geometry": {"coordinates":[-3.22219,51.449903],"type":"Point"}
}
