{
  "type": "Feature",
  "properties": {
    "iso:country":"GB",
    "wof:name":"NR1 2LX",
    "wof:placetype":"postalcode"
},
  "geometry": {"coordinates":[1.30145884644595,52.60895442866821],"type":"Point"}
}