{
  "type": "Feature",
  "properties": {
    "date:inception_lower": "1980-01-01",
    "date:inception_upper": "1980-01-01",
    "iso:country": "GB",
    "wof:name": "NR1 2LX",
    "wof:placetype": "postalcode"
  },
  "geometry": {"coordinates":[1.301459,52.608954],"type":"Point"}
}
