{
  "type": "Feature",
  "properties": {
    "iso:country": "GB",
    "wof:name": "TW18 1DS",
    "wof:placetype": "postalcode"
  },
  "geometry": {"coordinates":[-0.502908,51.429744],"type":"Point"}
}
