{
  "type": "Feature",
  "properties": {
    "iso:country":"GB",
    "wof:name":"TW18 1DS",
    "wof:placetype":"postalcode"
},
  "geometry": {"coordinates":[-0.5029078283183,51.4297437699875],"type":"Point"}
}