{
  "type": "Feature",
  "properties": {
    "date:inception_lower": "1980-01-01",
    "date:inception_upper": "1980-01-01",
    "iso:country": "GB",
    "wof:name": "SP5 2NU",
    "wof:placetype": "postalcode"
  },
  "geometry": {"coordinates":[-1.700371,50.988683],"type":"Point"}
}
