{
  "type": "Feature",
  "properties": {
    "date:inception_lower": "1980-01-01",
    "date:inception_upper": "1980-01-01",
    "iso:country": "GB",
    "wof:name": "UB7 7AJ",
    "wof:placetype": "postalcode"
  },
  "geometry": {"coordinates":[-0.482451,51.50747],"type":"Point"}
}
