{
  "type": "Feature",
  "properties": {
    "iso:country":"GB",
    "wof:name":"UB7 7AJ",
    "wof:placetype":"postalcode"
},
  "geometry": {"coordinates":[-0.48245067802287,51.50747021270735],"type":"Point"}
}