{
  "type": "Feature",
  "properties": {
    "iso:country":"GB",
    "wof:name":"DL7 0TR",
    "wof:placetype":"postalcode"
},
  "geometry": {"coordinates":[-1.60210285780356,54.35190666534169],"type":"Point"}
}