{
  "type": "Feature",
  "properties": {
    "iso:country": "GB",
    "wof:name": "DL7 0TR",
    "wof:placetype": "postalcode"
  },
  "geometry": {"coordinates":[-1.602103,54.351907],"type":"Point"}
}
