{
  "type": "Feature",
  "properties": {
    "iso:country":"GB",
    "wof:name":"WF8 3RA",
    "wof:placetype":"postalcode"
},
  "geometry": {"coordinates":[-1.30794076149949,53.67713882722803],"type":"Point"}
}