{
  "type": "Feature",
  "properties": {
    "iso:country": "GB",
    "wof:name": "WF8 3RA",
    "wof:placetype": "postalcode"
  },
  "geometry": {"coordinates":[-1.307941,53.677139],"type":"Point"}
}
