{
  "type": "Feature",
  "properties": {
    "iso:country": "GB",
    "wof:name": "NE5 4AU",
    "wof:placetype": "postalcode"
  },
  "geometry": {"coordinates":[-1.683044,55.001605],"type":"Point"}
}
