{
  "type": "Feature",
  "properties": {
    "date:inception_lower": "2018-04-01",
    "date:inception_upper": "2018-04-01",
    "iso:country": "GB",
    "wof:name": "TR6 0FJ",
    "wof:placetype": "postalcode"
  },
  "geometry": {"coordinates":[-5.153128,50.347197],"type":"Point"}
}
