{
  "type": "Feature",
  "properties": {
    "iso:country": "GB",
    "wof:name": "TR6 0FJ",
    "wof:placetype": "postalcode"
  },
  "geometry": {"coordinates":[-5.153128,50.347197],"type":"Point"}
}
