{
  "type": "Feature",
  "properties": {
    "iso:country":"GB",
    "wof:name":"CR5 1JU",
    "wof:placetype":"postalcode"
},
  "geometry": {"coordinates":[-0.11194667827203,51.30629336301404],"type":"Point"}
}