{
  "type": "Feature",
  "properties": {
    "iso:country":"GB",
    "wof:name":"N17 7QU",
    "wof:placetype":"postalcode"
},
  "geometry": {"coordinates":[-0.08622821953297,51.59800219615398],"type":"Point"}
}