{
  "type": "Feature",
  "properties": {
    "date:inception_lower": "2016-01-01",
    "date:inception_upper": "2016-01-01",
    "iso:country": "GB",
    "wof:name": "AB12 9UX",
    "wof:placetype": "postalcode"
  },
  "geometry": {"coordinates":[-2.095564,57.148127],"type":"Point"}
}
