{
  "type": "Feature",
  "properties": {
    "iso:country": "GB",
    "wof:name": "HA5 1NS",
    "wof:placetype": "postalcode"
  },
  "geometry": {"coordinates":[-0.383928,51.578193],"type":"Point"}
}
