{
  "type": "Feature",
  "properties": {
    "iso:country":"GB",
    "wof:name":"HA5 1NS",
    "wof:placetype":"postalcode"
},
  "geometry": {"coordinates":[-0.38429604081373,51.57819580826709],"type":"Point"}
}