{
  "type": "Feature",
  "properties": {
    "date:inception_lower": "1980-01-01",
    "date:inception_upper": "1980-01-01",
    "iso:country": "GB",
    "wof:name": "HA5 1NS",
    "wof:placetype": "postalcode"
  },
  "geometry": {"coordinates":[-0.383928,51.578193],"type":"Point"}
}
