{
  "type": "Feature",
  "properties": {
    "iso:country":"GB",
    "wof:name":"L23 6XA",
    "wof:placetype":"postalcode"
},
  "geometry": {"coordinates":[-3.03840751346011,53.48437757386984],"type":"Point"}
}