{
  "type": "Feature",
  "properties": {
    "iso:country":"GB",
    "wof:name":"SP2 7SW",
    "wof:placetype":"postalcode"
},
  "geometry": {"coordinates":[-1.80322015977793,51.07010079187052],"type":"Point"}
}