{
  "type": "Feature",
  "properties": {
    "date:inception_lower": "1980-01-01",
    "date:inception_upper": "1980-01-01",
    "iso:country": "GB",
    "wof:name": "NE45 5RH",
    "wof:placetype": "postalcode"
  },
  "geometry": {"coordinates":[-2.03412,54.964627],"type":"Point"}
}
