{
  "type": "Feature",
  "properties": {
    "iso:country":"GB",
    "wof:name":"NE45 5RH",
    "wof:placetype":"postalcode"
},
  "geometry": {"coordinates":[-2.03411151749808,54.96462043562452],"type":"Point"}
}