{
  "type": "Feature",
  "properties": {
    "iso:country":"GB",
    "wof:name":"SE15 4LF",
    "wof:placetype":"postalcode"
},
  "geometry": {"coordinates":[-0.07226077422372,51.46501643058596],"type":"Point"}
}