{
  "type": "Feature",
  "properties": {
    "iso:country":"GB",
    "wof:name":"SA62 6HL",
    "wof:placetype":"postalcode"
},
  "geometry": {"coordinates":[-5.04813949311514,51.83670827897128],"type":"Point"}
}