{
  "type": "Feature",
  "properties": {
    "iso:country": "GB",
    "wof:name": "YO7 3LR",
    "wof:placetype": "postalcode"
  },
  "geometry": {"coordinates":[-1.418235,54.153596],"type":"Point"}
}
