{
  "type": "Feature",
  "properties": {
    "iso:country":"GB",
    "wof:name":"LN6 8RR",
    "wof:placetype":"postalcode"
},
  "geometry": {"coordinates":[-0.55820414045225,53.20225180295594],"type":"Point"}
}