{
  "type": "Feature",
  "properties": {
    "iso:country":"GB",
    "wof:name":"DL6 2LD",
    "wof:placetype":"postalcode"
},
  "geometry": {"coordinates":[-1.34857466592781,54.42237069863653],"type":"Point"}
}