{
  "type": "Feature",
  "properties": {
    "iso:country": "GB",
    "wof:name": "DL6 2LD",
    "wof:placetype": "postalcode"
  },
  "geometry": {"coordinates":[-1.348575,54.422371],"type":"Point"}
}
