{
  "type": "Feature",
  "properties": {
    "iso:country": "GB",
    "wof:name": "DY1 9LH",
    "wof:placetype": "postalcode"
  },
  "geometry": {"coordinates":[-2.088889,52.511498],"type":"Point"}
}
