{
  "type": "Feature",
  "properties": {
    "iso:country":"GB",
    "wof:name":"TN29 0AU",
    "wof:placetype":"postalcode"
},
  "geometry": {"coordinates":[0.88287219704242,51.01968536052936],"type":"Point"}
}