{
  "type": "Feature",
  "properties": {
    "iso:country": "GB",
    "wof:name": "TN29 0AU",
    "wof:placetype": "postalcode"
  },
  "geometry": {"coordinates":[0.882872,51.019685],"type":"Point"}
}
