{
  "type": "Feature",
  "properties": {
    "iso:country":"GB",
    "wof:name":"BD12 7BB",
    "wof:placetype":"postalcode"
},
  "geometry": {"coordinates":[-1.74977896087427,53.75002574619996],"type":"Point"}
}