{
  "type": "Feature",
  "properties": {
    "date:inception_lower":"1980-01-01",
    "date:inception_upper":"1980-01-31",
    "iso:country":"GB",
    "wof:name":"TW19 7HW",
    "wof:placetype":"postalcode"
},
  "geometry": {"coordinates":[-0.475774,51.454051],"type":"Point"}
}