{
  "type": "Feature",
  "properties": {
    "iso:country":"GB",
    "wof:name":"TW19 7HW",
    "wof:placetype":"postalcode"
},
  "geometry": {"coordinates":[-0.47577403744055,51.45405088290376],"type":"Point"}
}