{
  "type": "Feature",
  "properties": {
    "date:inception_lower": "1983-01-01",
    "date:inception_upper": "1983-01-01",
    "iso:country": "GB",
    "wof:name": "RG6 3BD",
    "wof:placetype": "postalcode"
  },
  "geometry": {"coordinates":[-0.901998,51.431085],"type":"Point"}
}
