{
  "type": "Feature",
  "properties": {
    "iso:country": "GB",
    "wof:name": "RG6 3BD",
    "wof:placetype": "postalcode"
  },
  "geometry": {"coordinates":[-0.901998,51.431085],"type":"Point"}
}
