{
  "type": "Feature",
  "properties": {
    "iso:country":"GB",
    "wof:name":"RG6 3BD",
    "wof:placetype":"postalcode"
},
  "geometry": {"coordinates":[-0.90199835651163,51.43108548238425],"type":"Point"}
}