{
  "type": "Feature",
  "properties": {
    "iso:country":"GB",
    "wof:name":"L31 2JZ",
    "wof:placetype":"postalcode"
},
  "geometry": {"coordinates":[-2.94683011951377,53.5271877785848],"type":"Point"}
}