{
  "type": "Feature",
  "properties": {
    "date:inception_lower": "1980-01-01",
    "date:inception_upper": "1980-01-01",
    "iso:country": "GB",
    "wof:name": "L31 2JZ",
    "wof:placetype": "postalcode"
  },
  "geometry": {"coordinates":[-2.94683,53.527188],"type":"Point"}
}
