{
  "type": "Feature",
  "properties": {
    "iso:country": "GB",
    "wof:name": "L31 2JZ",
    "wof:placetype": "postalcode"
  },
  "geometry": {"coordinates":[-2.94683,53.527188],"type":"Point"}
}
