{
  "type": "Feature",
  "properties": {
    "iso:country":"GB",
    "wof:name":"DL7 0TU",
    "wof:placetype":"postalcode"
},
  "geometry": {"coordinates":[-1.53936356120134,54.32554879703929],"type":"Point"}
}