{
  "type": "Feature",
  "properties": {
    "iso:country": "GB",
    "wof:name": "DL7 0TU",
    "wof:placetype": "postalcode"
  },
  "geometry": {"coordinates":[-1.539364,54.325549],"type":"Point"}
}
