{
  "type": "Feature",
  "properties": {
    "iso:country": "GB",
    "wof:name": "GL5 3PE",
    "wof:placetype": "postalcode"
  },
  "geometry": {"coordinates":[-2.232628,51.73274],"type":"Point"}
}
