{
  "type": "Feature",
  "properties": {
    "iso:country":"GB",
    "wof:name":"GL5 3PE",
    "wof:placetype":"postalcode"
},
  "geometry": {"coordinates":[-2.23263223732808,51.73273527750064],"type":"Point"}
}