{
  "type": "Feature",
  "properties": {
    "iso:country":"GB",
    "wof:name":"TS13 4YD",
    "wof:placetype":"postalcode"
},
  "geometry": {"coordinates":[-0.89107250710014,54.55324789889671],"type":"Point"}
}