{
  "type": "Feature",
  "properties": {
    "date:inception_lower": "2018-05-01",
    "date:inception_upper": "2018-05-01",
    "iso:country": "GB",
    "wof:name": "NP4 4DW",
    "wof:placetype": "postalcode"
  },
  "geometry": {"coordinates":[-3.061055,51.70862],"type":"Point"}
}
