{
  "type": "Feature",
  "properties": {
    "iso:country": "GB",
    "wof:name": "CH43 1XF",
    "wof:placetype": "postalcode"
  },
  "geometry": {"coordinates":[-3.046723,53.385049],"type":"Point"}
}
