{
  "type": "Feature",
  "properties": {
    "date:inception_lower": "2022-06-01",
    "date:inception_upper": "2022-06-01",
    "iso:country": "GB",
    "wof:name": "CB2 9GP",
    "wof:placetype": "postalcode"
  },
  "geometry": {"coordinates":[0.103793,52.165379],"type":"Point"}
}
