{
  "type": "Feature",
  "properties": {
    "iso:country":"GB",
    "wof:name":"RM9 5AQ",
    "wof:placetype":"postalcode"
},
  "geometry": {"coordinates":[0.14757706684011,51.54240097607661],"type":"Point"}
}