{
  "type": "Feature",
  "properties": {
    "iso:country":"GB",
    "wof:name":"TS13 5DE",
    "wof:placetype":"postalcode"
},
  "geometry": {"coordinates":[-0.79098637870937,54.55850864258617],"type":"Point"}
}