{
  "type": "Feature",
  "properties": {
    "iso:country":"GB",
    "wof:name":"DH5 8HD",
    "wof:placetype":"postalcode"
},
  "geometry": {"coordinates":[-1.46481720758071,54.83859139382979],"type":"Point"}
}