{
  "type": "Feature",
  "properties": {
    "iso:country": "GB",
    "wof:name": "YO31 0NL",
    "wof:placetype": "postalcode"
  },
  "geometry": {"coordinates":[-1.042225,53.967618],"type":"Point"}
}
