{
  "type": "Feature",
  "properties": {
    "iso:country":"GB",
    "wof:name":"M35 9LR",
    "wof:placetype":"postalcode"
},
  "geometry": {"coordinates":[-2.14094114382485,53.5127525367743],"type":"Point"}
}