{
  "type": "Feature",
  "properties": {
    "iso:country": "GB",
    "wof:name": "G2 2BA",
    "wof:placetype": "postalcode"
  },
  "geometry": {"coordinates":[-4.258689,55.863145],"type":"Point"}
}
