{
  "type": "Feature",
  "properties": {
    "iso:country":"GB",
    "wof:name":"G2 2BA",
    "wof:placetype":"postalcode"
},
  "geometry": {"coordinates":[-4.25870327857054,55.86315028510491],"type":"Point"}
}