{
  "type": "Feature",
  "properties": {
    "iso:country":"GB",
    "wof:name":"OL16 5QG",
    "wof:placetype":"postalcode"
},
  "geometry": {"coordinates":[-2.1405875713807,53.61070766479732],"type":"Point"}
}