{
  "type": "Feature",
  "properties": {
    "iso:country": "GB",
    "wof:name": "M8 0ET",
    "wof:placetype": "postalcode"
  },
  "geometry": {"coordinates":[-2.241586,53.502785],"type":"Point"}
}
