{
  "type": "Feature",
  "properties": {
    "date:inception_lower": "2000-06-01",
    "date:inception_upper": "2000-06-01",
    "iso:country": "GB",
    "wof:name": "M8 0ET",
    "wof:placetype": "postalcode"
  },
  "geometry": {"coordinates":[-2.241586,53.502785],"type":"Point"}
}
