{
  "type": "Feature",
  "properties": {
    "date:inception_lower":"1980-01-01",
    "date:inception_upper":"1980-01-31",
    "iso:country":"GB",
    "wof:name":"SK6 7DD",
    "wof:placetype":"postalcode"
},
  "geometry": {"coordinates":[-2.05607,53.397015],"type":"Point"}
}