{
  "type": "Feature",
  "properties": {
    "iso:country":"GB",
    "wof:name":"SK6 7DD",
    "wof:placetype":"postalcode"
},
  "geometry": {"coordinates":[-2.0560702988801,53.39701513816023],"type":"Point"}
}