{
  "type": "Feature",
  "properties": {
    "date:inception_lower": "2012-10-01",
    "date:inception_upper": "2012-10-01",
    "iso:country": "GB",
    "wof:name": "G84 8SF",
    "wof:placetype": "postalcode"
  },
  "geometry": {"coordinates":[-4.760686,56.008016],"type":"Point"}
}
