{
  "type": "Feature",
  "properties": {
    "date:inception_lower": "2020-11-01",
    "date:inception_upper": "2020-11-01",
    "iso:country": "GB",
    "wof:name": "BH23 9NH",
    "wof:placetype": "postalcode"
  },
  "geometry": {"coordinates":[-1.782094,50.739933],"type":"Point"}
}
