{
  "type": "Feature",
  "properties": {
    "iso:country":"GB",
    "wof:name":"SO22 5FN",
    "wof:placetype":"postalcode"
},
  "geometry": {"coordinates":[-1.33979440066282,51.07222487129965],"type":"Point"}
}