{
  "type": "Feature",
  "properties": {
    "date:inception_lower":"2008-03-01",
    "date:inception_upper":"2008-03-31",
    "iso:country":"GB",
    "wof:name":"PE9 4ED",
    "wof:placetype":"postalcode"
},
  "geometry": {"coordinates":[-0.446927,52.715072],"type":"Point"}
}