{
  "type": "Feature",
  "properties": {
    "iso:country":"GB",
    "wof:name":"PE9 4ED",
    "wof:placetype":"postalcode"
},
  "geometry": {"coordinates":[-0.44692654880967,52.71507167465122],"type":"Point"}
}