{
  "type": "Feature",
  "properties": {
    "iso:country":"GB",
    "wof:name":"SG8 7XY",
    "wof:placetype":"postalcode"
},
  "geometry": {"coordinates":[-0.01174209266613,52.05659984605047],"type":"Point"}
}