{
  "type": "Feature",
  "properties": {
    "date:inception_lower":"2003-04-01",
    "date:inception_upper":"2003-04-30",
    "iso:country":"GB",
    "wof:name":"SG8 7XY",
    "wof:placetype":"postalcode"
},
  "geometry": {"coordinates":[-0.011775,52.056845],"type":"Point"}
}