{
  "type": "Feature",
  "properties": {
    "date:inception_lower": "1995-07-01",
    "date:inception_upper": "1995-07-01",
    "iso:country": "GB",
    "wof:name": "RG12 9JN",
    "wof:placetype": "postalcode"
  },
  "geometry": {"coordinates":[-0.727947,51.406414],"type":"Point"}
}
