{
  "type": "Feature",
  "properties": {
    "iso:country":"GB",
    "wof:name":"EH22 1PR",
    "wof:placetype":"postalcode"
},
  "geometry": {"coordinates":[-3.10549798707799,55.91093008227998],"type":"Point"}
}