{
  "type": "Feature",
  "properties": {
    "iso:country":"GB",
    "wof:name":"B5 7LX",
    "wof:placetype":"postalcode"
},
  "geometry": {"coordinates":[-1.90085158972585,52.46539313322395],"type":"Point"}
}