{
  "type": "Feature",
  "properties": {
    "iso:country": "GB",
    "wof:name": "KA21 6JJ",
    "wof:placetype": "postalcode"
  },
  "geometry": {"coordinates":[-4.783828,55.647294],"type":"Point"}
}
