{
  "type": "Feature",
  "properties": {
    "iso:country":"GB",
    "wof:name":"KA21 6JJ",
    "wof:placetype":"postalcode"
},
  "geometry": {"coordinates":[-4.7838278948973,55.64729391857888],"type":"Point"}
}