{
  "type": "Feature",
  "properties": {
    "iso:country":"GB",
    "wof:name":"DA1 2QX",
    "wof:placetype":"postalcode"
},
  "geometry": {"coordinates":[0.2061947826384,51.43722845205156],"type":"Point"}
}