{
  "type": "Feature",
  "properties": {
    "iso:country": "GB",
    "wof:name": "YO14 9BG",
    "wof:placetype": "postalcode"
  },
  "geometry": {"coordinates":[-0.289899,54.204875],"type":"Point"}
}
