{
  "type": "Feature",
  "properties": {
    "iso:country":"GB",
    "wof:name":"CF45 4PR",
    "wof:placetype":"postalcode"
},
  "geometry": {"coordinates":[-3.32994280980155,51.64789260589014],"type":"Point"}
}