{
  "type": "Feature",
  "properties": {
    "iso:country": "GB",
    "wof:name": "CF62 6FG",
    "wof:placetype": "postalcode"
  },
  "geometry": {"coordinates":[-3.286517,51.398778],"type":"Point"}
}
