{
  "type": "Feature",
  "properties": {
    "date:inception_lower": "2019-09-01",
    "date:inception_upper": "2019-09-01",
    "iso:country": "GB",
    "wof:name": "CF62 6FG",
    "wof:placetype": "postalcode"
  },
  "geometry": {"coordinates":[-3.286517,51.398778],"type":"Point"}
}
