{
  "type": "Feature",
  "properties": {
    "iso:country":"GB",
    "wof:name":"NN15 7ED",
    "wof:placetype":"postalcode"
},
  "geometry": {"coordinates":[-0.70662028854697,52.395647652684],"type":"Point"}
}