{
  "type": "Feature",
  "properties": {
    "iso:country": "GB",
    "wof:name": "NN15 7ED",
    "wof:placetype": "postalcode"
  },
  "geometry": {"coordinates":[-0.70662,52.395648],"type":"Point"}
}
