{
  "type": "Feature",
  "properties": {
    "iso:country": "GB",
    "wof:name": "SG6 2NE",
    "wof:placetype": "postalcode"
  },
  "geometry": {"coordinates":[-0.20972,51.975],"type":"Point"}
}
