{
  "type": "Feature",
  "properties": {
    "iso:country":"GB",
    "wof:name":"SG6 2NE",
    "wof:placetype":"postalcode"
},
  "geometry": {"coordinates":[-0.20976125728273,51.97498272858783],"type":"Point"}
}