{
  "type": "Feature",
  "properties": {
    "date:inception_lower": "1980-01-01",
    "date:inception_upper": "1980-01-01",
    "iso:country": "GB",
    "wof:name": "SG6 2NE",
    "wof:placetype": "postalcode"
  },
  "geometry": {"coordinates":[-0.20972,51.975],"type":"Point"}
}
