{
  "type": "Feature",
  "properties": {
    "iso:country":"GB",
    "wof:name":"CF72 8GJ",
    "wof:placetype":"postalcode"
},
  "geometry": {"coordinates":[-3.37215306501224,51.49953447205048],"type":"Point"}
}