{
  "type": "Feature",
  "properties": {
    "date:inception_lower": "2010-03-01",
    "date:inception_upper": "2010-03-01",
    "iso:country": "GB",
    "wof:name": "CF72 8GJ",
    "wof:placetype": "postalcode"
  },
  "geometry": {"coordinates":[-3.372153,51.499534],"type":"Point"}
}
