{
  "type": "Feature",
  "properties": {
    "iso:country":"GB",
    "wof:name":"DN33 2AE",
    "wof:placetype":"postalcode"
},
  "geometry": {"coordinates":[-0.09104247461409,53.54774153499969],"type":"Point"}
}