{
  "type": "Feature",
  "properties": {
    "iso:country":"GB",
    "wof:name":"LS29 9HY",
    "wof:placetype":"postalcode"
},
  "geometry": {"coordinates":[-1.83415025968371,53.9205468104045],"type":"Point"}
}