{
  "type": "Feature",
  "properties": {
    "iso:country": "GB",
    "wof:name": "LS29 9HY",
    "wof:placetype": "postalcode"
  },
  "geometry": {"coordinates":[-1.83415,53.920547],"type":"Point"}
}
