{
  "type": "Feature",
  "properties": {
    "date:inception_lower": "1980-01-01",
    "date:inception_upper": "1980-01-01",
    "iso:country": "GB",
    "wof:name": "ME10 4DU",
    "wof:placetype": "postalcode"
  },
  "geometry": {"coordinates":[0.736624,51.335724],"type":"Point"}
}
