{
  "type": "Feature",
  "properties": {
    "iso:country": "GB",
    "wof:name": "EX22 6XT",
    "wof:placetype": "postalcode"
  },
  "geometry": {"coordinates":[-4.499904,50.75097],"type":"Point"}
}
