{
  "type": "Feature",
  "properties": {
    "iso:country": "GB",
    "wof:name": "GU14 7LQ",
    "wof:placetype": "postalcode"
  },
  "geometry": {"coordinates":[-0.756718,51.288395],"type":"Point"}
}
