{
  "type": "Feature",
  "properties": {
    "iso:country":"GB",
    "wof:name":"IP7 6EB",
    "wof:placetype":"postalcode"
},
  "geometry": {"coordinates":[0.91673933922164,52.05858187534089],"type":"Point"}
}