{
  "type": "Feature",
  "properties": {
    "date:inception_lower": "1984-02-01",
    "date:inception_upper": "1984-02-01",
    "iso:country": "GB",
    "wof:name": "HX7 6AG",
    "wof:placetype": "postalcode"
  },
  "geometry": {"coordinates":[-2.013669,53.742619],"type":"Point"}
}
