{
  "type": "Feature",
  "properties": {
    "iso:country":"GB",
    "wof:name":"HX7 6AG",
    "wof:placetype":"postalcode"
},
  "geometry": {"coordinates":[-2.01366902167061,53.74261875582341],"type":"Point"}
}