{
  "type": "Feature",
  "properties": {
    "iso:country":"GB",
    "wof:name":"DG2 9JT",
    "wof:placetype":"postalcode"
},
  "geometry": {"coordinates":[-3.64007801642957,55.07871054011675],"type":"Point"}
}