{
  "type": "Feature",
  "properties": {
    "iso:country":"GB",
    "wof:name":"W6 0QR",
    "wof:placetype":"postalcode"
},
  "geometry": {"coordinates":[-0.230728523779,51.49287359610802],"type":"Point"}
}