{
  "type": "Feature",
  "properties": {
    "date:inception_lower": "2009-05-01",
    "date:inception_upper": "2009-05-01",
    "iso:country": "GB",
    "wof:name": "ME10 4RB",
    "wof:placetype": "postalcode"
  },
  "geometry": {"coordinates":[0.73675,51.326997],"type":"Point"}
}
