{
  "type": "Feature",
  "properties": {
    "iso:country": "GB",
    "wof:name": "PL31 2BE",
    "wof:placetype": "postalcode"
  },
  "geometry": {"coordinates":[-4.71157,50.470741],"type":"Point"}
}
