{
  "type": "Feature",
  "properties": {
    "iso:country":"GB",
    "wof:name":"PL31 2BE",
    "wof:placetype":"postalcode"
},
  "geometry": {"coordinates":[-4.71156975486206,50.47074137822729],"type":"Point"}
}