{
  "type": "Feature",
  "properties": {
    "iso:country": "GB",
    "wof:name": "IP3 8XT",
    "wof:placetype": "postalcode"
  },
  "geometry": {"coordinates":[1.193018,52.050386],"type":"Point"}
}
