{
  "type": "Feature",
  "properties": {
    "iso:country": "GB",
    "wof:name": "PO8 0DX",
    "wof:placetype": "postalcode"
  },
  "geometry": {"coordinates":[-1.00094,50.929196],"type":"Point"}
}
