{
  "type": "Feature",
  "properties": {
    "iso:country":"GB",
    "wof:name":"PO8 0DX",
    "wof:placetype":"postalcode"
},
  "geometry": {"coordinates":[-1.0009401306055,50.92919567903245],"type":"Point"}
}