{
  "type": "Feature",
  "properties": {
    "date:inception_lower":"1982-03-01",
    "date:inception_upper":"1982-03-31",
    "iso:country":"GB",
    "wof:name":"PO8 0DX",
    "wof:placetype":"postalcode"
},
  "geometry": {"coordinates":[-1.00094,50.929196],"type":"Point"}
}