{
  "type": "Feature",
  "properties": {
    "date:inception_lower": "1980-01-01",
    "date:inception_upper": "1980-01-01",
    "iso:country": "GB",
    "wof:name": "PE32 1JN",
    "wof:placetype": "postalcode"
  },
  "geometry": {"coordinates":[0.553488,52.694946],"type":"Point"}
}
