{
  "type": "Feature",
  "properties": {
    "iso:country":"GB",
    "wof:name":"PE32 1JN",
    "wof:placetype":"postalcode"
},
  "geometry": {"coordinates":[0.55348818916213,52.69494584355371],"type":"Point"}
}