{
  "type": "Feature",
  "properties": {
    "iso:country": "GB",
    "wof:name": "PE32 1JN",
    "wof:placetype": "postalcode"
  },
  "geometry": {"coordinates":[0.553488,52.694946],"type":"Point"}
}
