{
  "type": "Feature",
  "properties": {
    "iso:country":"GB",
    "wof:name":"CV6 2JQ",
    "wof:placetype":"postalcode"
},
  "geometry": {"coordinates":[-1.52916957578271,52.43415702683291],"type":"Point"}
}