{
  "type": "Feature",
  "properties": {
    "date:inception_lower": "1980-01-01",
    "date:inception_upper": "1980-01-01",
    "iso:country": "GB",
    "wof:name": "TD11 3HA",
    "wof:placetype": "postalcode"
  },
  "geometry": {"coordinates":[-2.336614,55.7748],"type":"Point"}
}
