{
  "type": "Feature",
  "properties": {
    "iso:country":"GB",
    "wof:name":"TD11 3HA",
    "wof:placetype":"postalcode"
},
  "geometry": {"coordinates":[-2.33661416040179,55.77480019915609],"type":"Point"}
}