{
  "type": "Feature",
  "properties": {
    "iso:country":"GB",
    "wof:name":"WF6 2LT",
    "wof:placetype":"postalcode"
},
  "geometry": {"coordinates":[-1.43143526489748,53.70456446255137],"type":"Point"}
}