{
  "type": "Feature",
  "properties": {
    "iso:country":"GB",
    "wof:name":"BL3 1PE",
    "wof:placetype":"postalcode"
},
  "geometry": {"coordinates":[-2.35845626907125,53.56162612014784],"type":"Point"}
}