{
  "type": "Feature",
  "properties": {
    "iso:country": "GB",
    "wof:name": "L35 6PY",
    "wof:placetype": "postalcode"
  },
  "geometry": {"coordinates":[-2.753027,53.407911],"type":"Point"}
}
