{
  "type": "Feature",
  "properties": {
    "iso:country": "GB",
    "wof:name": "DL2 1QN",
    "wof:placetype": "postalcode"
  },
  "geometry": {"coordinates":[-1.506598,54.48684],"type":"Point"}
}
