{
  "type": "Feature",
  "properties": {
    "iso:country":"GB",
    "wof:name":"DT7 3XE",
    "wof:placetype":"postalcode"
},
  "geometry": {"coordinates":[-2.97110257719723,50.74413143012846],"type":"Point"}
}