{
  "type": "Feature",
  "properties": {
    "iso:country": "GB",
    "wof:name": "DT7 3XE",
    "wof:placetype": "postalcode"
  },
  "geometry": {"coordinates":[-2.971109,50.74412],"type":"Point"}
}
