{
  "type": "Feature",
  "properties": {
    "date:inception_lower": "2024-09-01",
    "date:inception_upper": "2024-09-01",
    "iso:country": "GB",
    "wof:name": "HP11 9QQ",
    "wof:placetype": "postalcode"
  },
  "geometry": {"coordinates":[-0.747998,51.627754],"type":"Point"}
}
