{
  "type": "Feature",
  "properties": {
    "date:inception_lower": "2024-06-01",
    "date:inception_upper": "2024-06-01",
    "iso:country": "GB",
    "wof:name": "CF35 5FL",
    "wof:placetype": "postalcode"
  },
  "geometry": {"coordinates":[-3.499719,51.52389],"type":"Point"}
}
