{
  "type": "Feature",
  "properties": {
    "iso:country": "GB",
    "wof:name": "S33 6RQ",
    "wof:placetype": "postalcode"
  },
  "geometry": {"coordinates":[-1.740674,53.348182],"type":"Point"}
}
