{
  "type": "Feature",
  "properties": {
    "iso:country":"GB",
    "wof:name":"S33 6RQ",
    "wof:placetype":"postalcode"
},
  "geometry": {"coordinates":[-1.74067414228505,53.34818186526084],"type":"Point"}
}