{
  "type": "Feature",
  "properties": {
    "iso:country": "GB",
    "wof:name": "DL13 2RF",
    "wof:placetype": "postalcode"
  },
  "geometry": {"coordinates":[-1.957936,54.727746],"type":"Point"}
}
