{
  "type": "Feature",
  "properties": {
    "iso:country":"GB",
    "wof:name":"LL53 7YL",
    "wof:placetype":"postalcode"
},
  "geometry": {"coordinates":[-4.48740911098226,52.88542791068364],"type":"Point"}
}