{
  "type": "Feature",
  "properties": {
    "date:inception_lower": "1992-10-01",
    "date:inception_upper": "1992-10-01",
    "iso:country": "GB",
    "wof:name": "PA15 1RL",
    "wof:placetype": "postalcode"
  },
  "geometry": {"coordinates":[-4.766215,55.948281],"type":"Point"}
}
