{
  "type": "Feature",
  "properties": {
    "iso:country": "GB",
    "wof:name": "PA15 1RL",
    "wof:placetype": "postalcode"
  },
  "geometry": {"coordinates":[-4.765887,55.948349],"type":"Point"}
}
