{
  "type": "Feature",
  "properties": {
    "iso:country":"GB",
    "wof:name":"YO15 1LT",
    "wof:placetype":"postalcode"
},
  "geometry": {"coordinates":[-0.1808064833196,54.13364965657695],"type":"Point"}
}