{
  "type": "Feature",
  "properties": {
    "iso:country": "GB",
    "wof:name": "MK8 0BG",
    "wof:placetype": "postalcode"
  },
  "geometry": {"coordinates":[-0.803591,52.024564],"type":"Point"}
}
