{
  "type": "Feature",
  "properties": {
    "iso:country":"GB",
    "wof:name":"MK8 0BG",
    "wof:placetype":"postalcode"
},
  "geometry": {"coordinates":[-0.80359075069632,52.02456411259273],"type":"Point"}
}