{
  "type": "Feature",
  "properties": {
    "iso:country":"GB",
    "wof:name":"LD1 6DZ",
    "wof:placetype":"postalcode"
},
  "geometry": {"coordinates":[-3.37903771250951,52.24668382910924],"type":"Point"}
}