{
  "type": "Feature",
  "properties": {
    "date:inception_lower": "2013-10-01",
    "date:inception_upper": "2013-10-01",
    "iso:country": "GB",
    "wof:name": "LD1 6DZ",
    "wof:placetype": "postalcode"
  },
  "geometry": {"coordinates":[-3.379031,52.246712],"type":"Point"}
}
