{
  "type": "Feature",
  "properties": {
    "iso:country":"GB",
    "wof:name":"SM6 9AF",
    "wof:placetype":"postalcode"
},
  "geometry": {"coordinates":[-0.12983309084499,51.35332483508481],"type":"Point"}
}