{
  "type": "Feature",
  "properties": {
    "iso:country":"GB",
    "wof:name":"CM7 4QQ",
    "wof:placetype":"postalcode"
},
  "geometry": {"coordinates":[0.45896459223716,51.94804027860106],"type":"Point"}
}