{
  "type": "Feature",
  "properties": {
    "iso:country": "GB",
    "wof:name": "CM7 4QQ",
    "wof:placetype": "postalcode"
  },
  "geometry": {"coordinates":[0.458993,51.948049],"type":"Point"}
}
