{
  "type": "Feature",
  "properties": {
    "date:inception_lower": "1980-01-01",
    "date:inception_upper": "1980-01-01",
    "iso:country": "GB",
    "wof:name": "CM7 4QQ",
    "wof:placetype": "postalcode"
  },
  "geometry": {"coordinates":[0.459744,51.947935],"type":"Point"}
}
