{
  "type": "Feature",
  "properties": {
    "iso:country": "GB",
    "wof:name": "TA7 9PD",
    "wof:placetype": "postalcode"
  },
  "geometry": {"coordinates":[-2.811968,51.129113],"type":"Point"}
}
