{
  "type": "Feature",
  "properties": {
    "iso:country":"GB",
    "wof:name":"TA7 9PD",
    "wof:placetype":"postalcode"
},
  "geometry": {"coordinates":[-2.81196834709057,51.12911318410881],"type":"Point"}
}