{
  "type": "Feature",
  "properties": {
    "iso:country":"GB",
    "wof:name":"OX16 2WD",
    "wof:placetype":"postalcode"
},
  "geometry": {"coordinates":[-1.33772231917831,52.06578218619706],"type":"Point"}
}