{
  "type": "Feature",
  "properties": {
    "iso:country":"GB",
    "wof:name":"TA7 8PS",
    "wof:placetype":"postalcode"
},
  "geometry": {"coordinates":[-2.9439047929054,51.15381334760782],"type":"Point"}
}