{
  "type": "Feature",
  "properties": {
    "iso:country": "GB",
    "wof:name": "MK14 6HQ",
    "wof:placetype": "postalcode"
  },
  "geometry": {"coordinates":[-0.750896,52.058274],"type":"Point"}
}
