{
  "type": "Feature",
  "properties": {
    "date:inception_lower": "2002-12-01",
    "date:inception_upper": "2002-12-01",
    "iso:country": "GB",
    "wof:name": "BS2 8JQ",
    "wof:placetype": "postalcode"
  },
  "geometry": {"coordinates":[-2.59333,51.46112],"type":"Point"}
}
