{
  "type": "Feature",
  "properties": {
    "iso:country":"GB",
    "wof:name":"BS2 8JQ",
    "wof:placetype":"postalcode"
},
  "geometry": {"coordinates":[-2.59317186808367,51.46127545847111],"type":"Point"}
}