{
  "type": "Feature",
  "properties": {
    "date:inception_lower":"1983-10-01",
    "date:inception_upper":"1983-10-31",
    "iso:country":"GB",
    "wof:name":"DG1 2PX",
    "wof:placetype":"postalcode"
},
  "geometry": {"coordinates":[-3.608125,55.065135],"type":"Point"}
}