{
  "type": "Feature",
  "properties": {
    "iso:country":"GB",
    "wof:name":"EN8 9LR",
    "wof:placetype":"postalcode"
},
  "geometry": {"coordinates":[-0.03553105966237,51.70202547106301],"type":"Point"}
}