{
  "type": "Feature",
  "properties": {
    "iso:country":"GB",
    "wof:name":"NW4 2HY",
    "wof:placetype":"postalcode"
},
  "geometry": {"coordinates":[-0.21889453960043,51.58539693617247],"type":"Point"}
}