{
  "type": "Feature",
  "properties": {
    "date:inception_lower":"1981-06-01",
    "date:inception_upper":"1981-06-30",
    "iso:country":"GB",
    "wof:name":"S61 4DA",
    "wof:placetype":"postalcode"
},
  "geometry": {"coordinates":[-1.37641,53.456524],"type":"Point"}
}