{
  "type": "Feature",
  "properties": {
    "iso:country":"GB",
    "wof:name":"S61 4DA",
    "wof:placetype":"postalcode"
},
  "geometry": {"coordinates":[-1.37641012710758,53.45652445885953],"type":"Point"}
}