{
  "type": "Feature",
  "properties": {
    "iso:country":"GB",
    "wof:name":"W1U 8NN",
    "wof:placetype":"postalcode"
},
  "geometry": {"coordinates":[-0.1569638959021,51.51736613393198],"type":"Point"}
}