{
  "type": "Feature",
  "properties": {
    "date:inception_lower": "2016-09-01",
    "date:inception_upper": "2016-09-01",
    "iso:country": "GB",
    "wof:name": "LE3 3QD",
    "wof:placetype": "postalcode"
  },
  "geometry": {"coordinates":[-1.211287,52.619289],"type":"Point"}
}
