{
  "type": "Feature",
  "properties": {
    "iso:country": "GB",
    "wof:name": "DH8 9NL",
    "wof:placetype": "postalcode"
  },
  "geometry": {"coordinates":[-1.974804,54.845078],"type":"Point"}
}
