{
  "type": "Feature",
  "properties": {
    "iso:country": "GB",
    "wof:name": "FY7 7JX",
    "wof:placetype": "postalcode"
  },
  "geometry": {"coordinates":[-3.035081,53.91902],"type":"Point"}
}
