{
  "type": "Feature",
  "properties": {
    "date:inception_lower": "1980-01-01",
    "date:inception_upper": "1980-01-01",
    "iso:country": "GB",
    "wof:name": "LS29 9HN",
    "wof:placetype": "postalcode"
  },
  "geometry": {"coordinates":[-1.825506,53.926826],"type":"Point"}
}
