{
  "type": "Feature",
  "properties": {
    "iso:country":"GB",
    "wof:name":"TW13 4JR",
    "wof:placetype":"postalcode"
},
  "geometry": {"coordinates":[-0.41640775818735,51.44477534921066],"type":"Point"}
}