{
  "type": "Feature",
  "properties": {
    "date:inception_lower": "1995-07-01",
    "date:inception_upper": "1995-07-01",
    "iso:country": "GB",
    "wof:name": "WA8 3JS",
    "wof:placetype": "postalcode"
  },
  "geometry": {"coordinates":[-2.70684,53.375843],"type":"Point"}
}
