{
  "type": "Feature",
  "properties": {
    "iso:country":"GB",
    "wof:name":"WA8 3JS",
    "wof:placetype":"postalcode"
},
  "geometry": {"coordinates":[-2.70684006308256,53.37584260253948],"type":"Point"}
}