{
  "type": "Feature",
  "properties": {
    "date:inception_lower": "2010-11-01",
    "date:inception_upper": "2010-11-01",
    "iso:country": "GB",
    "wof:name": "IP7 7GA",
    "wof:placetype": "postalcode"
  },
  "geometry": {"coordinates":[0.9484,52.109711],"type":"Point"}
}
