{
  "type": "Feature",
  "properties": {
    "iso:country": "GB",
    "wof:name": "IP7 7GA",
    "wof:placetype": "postalcode"
  },
  "geometry": {"coordinates":[0.94849,52.109765],"type":"Point"}
}
