{
  "type": "Feature",
  "properties": {
    "date:inception_lower":"2010-11-01",
    "date:inception_upper":"2010-11-30",
    "iso:country":"GB",
    "wof:name":"IP7 7GA",
    "wof:placetype":"postalcode"
},
  "geometry": {"coordinates":[0.94849,52.109765],"type":"Point"}
}