{
  "type": "Feature",
  "properties": {
    "iso:country":"GB",
    "wof:name":"SS9 5SY",
    "wof:placetype":"postalcode"
},
  "geometry": {"coordinates":[0.66675590752428,51.56928398835595],"type":"Point"}
}