{
  "type": "Feature",
  "properties": {
    "iso:country":"GB",
    "wof:name":"S26 7YP",
    "wof:placetype":"postalcode"
},
  "geometry": {"coordinates":[-1.26190426415812,53.30895031741264],"type":"Point"}
}