{
  "type": "Feature",
  "properties": {
    "iso:country": "GB",
    "wof:name": "DE21 4LU",
    "wof:placetype": "postalcode"
  },
  "geometry": {"coordinates":[-1.431599,52.931618],"type":"Point"}
}
