{
  "type": "Feature",
  "properties": {
    "iso:country":"GB",
    "wof:name":"SE22 9EH",
    "wof:placetype":"postalcode"
},
  "geometry": {"coordinates":[-0.07587366508359,51.45202743600444],"type":"Point"}
}