{
  "type": "Feature",
  "properties": {
    "iso:country":"GB",
    "wof:name":"AB51 5HA",
    "wof:placetype":"postalcode"
},
  "geometry": {"coordinates":[-2.4488957311826,57.29226245684379],"type":"Point"}
}