{
  "type": "Feature",
  "properties": {
    "date:inception_lower": "1994-05-01",
    "date:inception_upper": "1994-05-01",
    "iso:country": "GB",
    "wof:name": "AB51 5HA",
    "wof:placetype": "postalcode"
  },
  "geometry": {"coordinates":[-2.448896,57.292262],"type":"Point"}
}
