{
  "type": "Feature",
  "properties": {
    "iso:country":"GB",
    "wof:name":"BB5 3JU",
    "wof:placetype":"postalcode"
},
  "geometry": {"coordinates":[-2.39715141519648,53.74195173000551],"type":"Point"}
}