{
  "type": "Feature",
  "properties": {
    "iso:country":"GB",
    "wof:name":"NG19 0PR",
    "wof:placetype":"postalcode"
},
  "geometry": {"coordinates":[-1.15712933862045,53.15727558614498],"type":"Point"}
}