{
  "type": "Feature",
  "properties": {
    "iso:country": "GB",
    "wof:name": "NG19 0PR",
    "wof:placetype": "postalcode"
  },
  "geometry": {"coordinates":[-1.157129,53.157276],"type":"Point"}
}
