{
  "type": "Feature",
  "properties": {
    "date:inception_lower": "1982-03-01",
    "date:inception_upper": "1982-03-01",
    "iso:country": "GB",
    "wof:name": "NG19 0PR",
    "wof:placetype": "postalcode"
  },
  "geometry": {"coordinates":[-1.157129,53.157276],"type":"Point"}
}
