{
  "type": "Feature",
  "properties": {
    "iso:country":"GB",
    "wof:name":"LU3 1NP",
    "wof:placetype":"postalcode"
},
  "geometry": {"coordinates":[-0.4332924240201,51.8931442720833],"type":"Point"}
}