{
  "type": "Feature",
  "properties": {
    "iso:country": "GB",
    "wof:name": "LU3 1NP",
    "wof:placetype": "postalcode"
  },
  "geometry": {"coordinates":[-0.433292,51.893144],"type":"Point"}
}
