{
  "type": "Feature",
  "properties": {
    "date:inception_lower": "1980-01-01",
    "date:inception_upper": "1980-01-01",
    "iso:country": "GB",
    "wof:name": "LU3 1NP",
    "wof:placetype": "postalcode"
  },
  "geometry": {"coordinates":[-0.433292,51.893144],"type":"Point"}
}
