{
  "type": "Feature",
  "properties": {
    "iso:country":"GB",
    "wof:name":"TS23 2QQ",
    "wof:placetype":"postalcode"
},
  "geometry": {"coordinates":[-1.29126100115622,54.6033629926557],"type":"Point"}
}