{
  "type": "Feature",
  "properties": {
    "iso:country": "GB",
    "wof:name": "IP14 3LE",
    "wof:placetype": "postalcode"
  },
  "geometry": {"coordinates":[0.93761,52.227849],"type":"Point"}
}
