{
  "type": "Feature",
  "properties": {
    "iso:country": "GB",
    "wof:name": "SS15 6UJ",
    "wof:placetype": "postalcode"
  },
  "geometry": {"coordinates":[0.419748,51.584149],"type":"Point"}
}
