{
  "type": "Feature",
  "properties": {
    "iso:country": "GB",
    "wof:name": "GL54 4EA",
    "wof:placetype": "postalcode"
  },
  "geometry": {"coordinates":[-1.874741,51.861128],"type":"Point"}
}
