{
  "type": "Feature",
  "properties": {
    "iso:country": "GB",
    "wof:name": "GL54 4EA",
    "wof:placetype": "postalcode"
  },
  "geometry": {"coordinates":[-1.879781,51.860765],"type":"Point"}
}
