{
  "type": "Feature",
  "properties": {
    "iso:country":"GB",
    "wof:name":"BS49 4EW",
    "wof:placetype":"postalcode"
},
  "geometry": {"coordinates":[-2.8197256465655,51.38431604174613],"type":"Point"}
}