{
  "type": "Feature",
  "properties": {
    "date:inception_lower": "1997-12-01",
    "date:inception_upper": "1997-12-01",
    "iso:country": "GB",
    "wof:name": "BS49 4EW",
    "wof:placetype": "postalcode"
  },
  "geometry": {"coordinates":[-2.81973,51.384287],"type":"Point"}
}
