{
  "type": "Feature",
  "properties": {
    "date:inception_lower": "1985-10-01",
    "date:inception_upper": "1985-10-01",
    "iso:country": "GB",
    "wof:name": "PE30 3TX",
    "wof:placetype": "postalcode"
  },
  "geometry": {"coordinates":[0.444991,52.771992],"type":"Point"}
}
