{
  "type": "Feature",
  "properties": {
    "iso:country":"GB",
    "wof:name":"PE30 3TX",
    "wof:placetype":"postalcode"
},
  "geometry": {"coordinates":[0.44499107484713,52.77199152793484],"type":"Point"}
}