{
  "type": "Feature",
  "properties": {
    "date:inception_lower": "2019-06-01",
    "date:inception_upper": "2019-06-01",
    "iso:country": "GB",
    "wof:name": "W3 8YP",
    "wof:placetype": "postalcode"
  },
  "geometry": {"coordinates":[-0.270159,51.50438],"type":"Point"}
}
