{
  "type": "Feature",
  "properties": {
    "date:inception_lower": "1987-05-01",
    "date:inception_upper": "1987-05-01",
    "iso:country": "GB",
    "wof:name": "DG2 7TJ",
    "wof:placetype": "postalcode"
  },
  "geometry": {"coordinates":[-3.61804,55.068688],"type":"Point"}
}
