{
  "type": "Feature",
  "properties": {
    "date:inception_lower": "2008-06-01",
    "date:inception_upper": "2008-06-01",
    "iso:country": "GB",
    "wof:name": "HX5 9AN",
    "wof:placetype": "postalcode"
  },
  "geometry": {"coordinates":[-1.833155,53.684797],"type":"Point"}
}
