{
  "type": "Feature",
  "properties": {
    "date:inception_lower":"2002-07-01",
    "date:inception_upper":"2002-07-31",
    "iso:country":"GB",
    "wof:name":"BS1 5TU",
    "wof:placetype":"postalcode"
},
  "geometry": {"coordinates":[-2.606376,51.450814],"type":"Point"}
}