{
  "type": "Feature",
  "properties": {
    "iso:country": "GB",
    "wof:name": "BS1 5TU",
    "wof:placetype": "postalcode"
  },
  "geometry": {"coordinates":[-2.606376,51.450814],"type":"Point"}
}
