{
  "type": "Feature",
  "properties": {
    "iso:country":"GB",
    "wof:name":"DG11 2FG",
    "wof:placetype":"postalcode"
},
  "geometry": {"coordinates":[-3.35447993085671,55.12092019308978],"type":"Point"}
}