{
  "type": "Feature",
  "properties": {
    "iso:country":"GB",
    "wof:name":"CH42 6RT",
    "wof:placetype":"postalcode"
},
  "geometry": {"coordinates":[-3.02374386419639,53.37039863425849],"type":"Point"}
}