{
  "type": "Feature",
  "properties": {
    "date:inception_lower":"1980-01-01",
    "date:inception_upper":"1980-01-31",
    "iso:country":"GB",
    "wof:name":"PE22 0JA",
    "wof:placetype":"postalcode"
},
  "geometry": {"coordinates":[0.063775,52.983997],"type":"Point"}
}