{
  "type": "Feature",
  "properties": {
    "iso:country": "GB",
    "wof:name": "WS6 7DN",
    "wof:placetype": "postalcode"
  },
  "geometry": {"coordinates":[-2.032693,52.663701],"type":"Point"}
}
