{
  "type": "Feature",
  "properties": {
    "iso:country":"GB",
    "wof:name":"CT19 5RG",
    "wof:placetype":"postalcode"
},
  "geometry": {"coordinates":[1.17718271339426,51.08813659522183],"type":"Point"}
}