{
  "type": "Feature",
  "properties": {
    "date:inception_lower": "1980-01-01",
    "date:inception_upper": "1980-01-01",
    "iso:country": "GB",
    "wof:name": "CT19 5RG",
    "wof:placetype": "postalcode"
  },
  "geometry": {"coordinates":[1.177183,51.088137],"type":"Point"}
}
