{
  "type": "Feature",
  "properties": {
    "date:inception_lower": "1980-01-01",
    "date:inception_upper": "1980-01-01",
    "iso:country": "GB",
    "wof:name": "CO5 9BW",
    "wof:placetype": "postalcode"
  },
  "geometry": {"coordinates":[0.698446,51.816833],"type":"Point"}
}
