{
  "type": "Feature",
  "properties": {
    "iso:country":"GB",
    "wof:name":"CO5 9BW",
    "wof:placetype":"postalcode"
},
  "geometry": {"coordinates":[0.69844632778095,51.81683293699941],"type":"Point"}
}