{
  "type": "Feature",
  "properties": {
    "iso:country":"GB",
    "wof:name":"HX6 2PA",
    "wof:placetype":"postalcode"
},
  "geometry": {"coordinates":[-1.90734538708129,53.71215036794636],"type":"Point"}
}