{
  "type": "Feature",
  "properties": {
    "iso:country": "GB",
    "wof:name": "HX6 2PA",
    "wof:placetype": "postalcode"
  },
  "geometry": {"coordinates":[-1.907345,53.71215],"type":"Point"}
}
