{
  "type": "Feature",
  "properties": {
    "iso:country":"GB",
    "wof:name":"M19 3HY",
    "wof:placetype":"postalcode"
},
  "geometry": {"coordinates":[-2.17889178183988,53.44363443297673],"type":"Point"}
}