{
  "type": "Feature",
  "properties": {
    "iso:country": "GB",
    "wof:name": "EH32 0DP",
    "wof:placetype": "postalcode"
  },
  "geometry": {"coordinates":[-2.955209,55.971751],"type":"Point"}
}
