{
  "type": "Feature",
  "properties": {
    "iso:country":"GB",
    "wof:name":"LU7 4TU",
    "wof:placetype":"postalcode"
},
  "geometry": {"coordinates":[-0.6563204896351,51.91034224501316],"type":"Point"}
}