{
  "type": "Feature",
  "properties": {
    "iso:country":"GB",
    "wof:name":"DG1 4XU",
    "wof:placetype":"postalcode"
},
  "geometry": {"coordinates":[-3.57874666275818,55.05796093718004],"type":"Point"}
}