{
  "type": "Feature",
  "properties": {
    "iso:country": "GB",
    "wof:name": "DG1 4XU",
    "wof:placetype": "postalcode"
  },
  "geometry": {"coordinates":[-3.578747,55.057961],"type":"Point"}
}
