{
  "type": "Feature",
  "properties": {
    "iso:country": "GB",
    "wof:name": "PL1 1QD",
    "wof:placetype": "postalcode"
  },
  "geometry": {"coordinates":[-4.147768,50.371663],"type":"Point"}
}
