{
  "type": "Feature",
  "properties": {
    "iso:country":"GB",
    "wof:name":"PL1 1QD",
    "wof:placetype":"postalcode"
},
  "geometry": {"coordinates":[-4.14776795913447,50.3716633093994],"type":"Point"}
}