{
  "type": "Feature",
  "properties": {
    "iso:country":"GB",
    "wof:name":"DH8 9NQ",
    "wof:placetype":"postalcode"
},
  "geometry": {"coordinates":[-1.9785416385487,54.84457551204614],"type":"Point"}
}