{
  "type": "Feature",
  "properties": {
    "iso:country": "GB",
    "wof:name": "DH8 9NQ",
    "wof:placetype": "postalcode"
  },
  "geometry": {"coordinates":[-1.978542,54.844576],"type":"Point"}
}
