{
  "type": "Feature",
  "properties": {
    "date:inception_lower": "1994-12-01",
    "date:inception_upper": "1994-12-01",
    "iso:country": "GB",
    "wof:name": "SO23 0LD",
    "wof:placetype": "postalcode"
  },
  "geometry": {"coordinates":[-1.298322,51.066295],"type":"Point"}
}
