{
  "type": "Feature",
  "properties": {
    "iso:country": "GB",
    "wof:name": "SO23 0LD",
    "wof:placetype": "postalcode"
  },
  "geometry": {"coordinates":[-1.298594,51.066242],"type":"Point"}
}
