{
  "type": "Feature",
  "properties": {
    "iso:country":"GB",
    "wof:name":"PO38 1JH",
    "wof:placetype":"postalcode"
},
  "geometry": {"coordinates":[-1.21036250513765,50.5942176059393],"type":"Point"}
}