{
  "type": "Feature",
  "properties": {
    "iso:country":"GB",
    "wof:name":"EX8 5QD",
    "wof:placetype":"postalcode"
},
  "geometry": {"coordinates":[-3.38787243566793,50.64472126806351],"type":"Point"}
}