{
  "type": "Feature",
  "properties": {
    "date:inception_lower": "1983-03-01",
    "date:inception_upper": "1983-03-01",
    "iso:country": "GB",
    "wof:name": "EX8 5QD",
    "wof:placetype": "postalcode"
  },
  "geometry": {"coordinates":[-3.387872,50.644721],"type":"Point"}
}
