{
  "type": "Feature",
  "properties": {
    "iso:country":"GB",
    "wof:name":"G76 0BL",
    "wof:placetype":"postalcode"
},
  "geometry": {"coordinates":[-4.28619047948941,55.73657339301574],"type":"Point"}
}