{
  "type": "Feature",
  "properties": {
    "iso:country": "GB",
    "wof:name": "YO1 7EN",
    "wof:placetype": "postalcode"
  },
  "geometry": {"coordinates":[-1.084688,53.962358],"type":"Point"}
}
