{
  "type": "Feature",
  "properties": {
    "iso:country":"GB",
    "wof:name":"YO1 7EN",
    "wof:placetype":"postalcode"
},
  "geometry": {"coordinates":[-1.08468844162494,53.96235799269945],"type":"Point"}
}