{
  "type": "Feature",
  "properties": {
    "iso:country":"GB",
    "wof:name":"M31 4HR",
    "wof:placetype":"postalcode"
},
  "geometry": {"coordinates":[-2.43978005929113,53.41558809603017],"type":"Point"}
}