{
  "type": "Feature",
  "properties": {
    "iso:country":"GB",
    "wof:name":"NP7 8PY",
    "wof:placetype":"postalcode"
},
  "geometry": {"coordinates":[-2.89839436189776,51.8584829016831],"type":"Point"}
}