{
  "type": "Feature",
  "properties": {
    "iso:country": "GB",
    "wof:name": "NP7 8PY",
    "wof:placetype": "postalcode"
  },
  "geometry": {"coordinates":[-2.898394,51.858483],"type":"Point"}
}
