{
  "type": "Feature",
  "properties": {
    "iso:country":"GB",
    "wof:name":"M33 6NJ",
    "wof:placetype":"postalcode"
},
  "geometry": {"coordinates":[-2.33692080054298,53.42773376081736],"type":"Point"}
}