{
  "type": "Feature",
  "properties": {
    "iso:country": "GB",
    "wof:name": "BB3 3PB",
    "wof:placetype": "postalcode"
  },
  "geometry": {"coordinates":[-2.435366,53.70617],"type":"Point"}
}
