{
  "type": "Feature",
  "properties": {
    "date:inception_lower": "1980-01-01",
    "date:inception_upper": "1980-01-01",
    "iso:country": "GB",
    "wof:name": "BB3 3PB",
    "wof:placetype": "postalcode"
  },
  "geometry": {"coordinates":[-2.435366,53.70617],"type":"Point"}
}
