{
  "type": "Feature",
  "properties": {
    "iso:country":"GB",
    "wof:name":"BB3 3PB",
    "wof:placetype":"postalcode"
},
  "geometry": {"coordinates":[-2.43541332100756,53.70616278815771],"type":"Point"}
}