{
  "type": "Feature",
  "properties": {
    "date:inception_lower": "2019-03-01",
    "date:inception_upper": "2019-03-01",
    "iso:country": "GB",
    "wof:name": "L24 0AA",
    "wof:placetype": "postalcode"
  },
  "geometry": {"coordinates":[-2.846699,53.340467],"type":"Point"}
}
