{
  "type": "Feature",
  "properties": {
    "iso:country": "GB",
    "wof:name": "L24 0AA",
    "wof:placetype": "postalcode"
  },
  "geometry": {"coordinates":[-2.846699,53.340467],"type":"Point"}
}
