{
  "type": "Feature",
  "properties": {
    "iso:country": "GB",
    "wof:name": "DA12 4XH",
    "wof:placetype": "postalcode"
  },
  "geometry": {"coordinates":[0.410091,51.429922],"type":"Point"}
}
