{
  "type": "Feature",
  "properties": {
    "iso:country":"GB",
    "wof:name":"RH17 7SR",
    "wof:placetype":"postalcode"
},
  "geometry": {"coordinates":[-0.07876780025776,50.98938607965327],"type":"Point"}
}