{
  "type": "Feature",
  "properties": {
    "iso:country":"GB",
    "wof:name":"EH5 3LH",
    "wof:placetype":"postalcode"
},
  "geometry": {"coordinates":[-3.21249006270149,55.97337867919623],"type":"Point"}
}