{
  "type": "Feature",
  "properties": {
    "iso:country": "GB",
    "wof:name": "WS14 9LA",
    "wof:placetype": "postalcode"
  },
  "geometry": {"coordinates":[-1.778824,52.670555],"type":"Point"}
}
