{
  "type": "Feature",
  "properties": {
    "iso:country": "GB",
    "wof:name": "WS14 9LA",
    "wof:placetype": "postalcode"
  },
  "geometry": {"coordinates":[-1.780989,52.67233],"type":"Point"}
}
