{
  "type": "Feature",
  "properties": {
    "iso:country": "GB",
    "wof:name": "LL57 3DG",
    "wof:placetype": "postalcode"
  },
  "geometry": {"coordinates":[-4.085387,53.199593],"type":"Point"}
}
