{
  "type": "Feature",
  "properties": {
    "iso:country":"GB",
    "wof:name":"OL9 7UX",
    "wof:placetype":"postalcode"
},
  "geometry": {"coordinates":[-2.13559406911462,53.53354885003257],"type":"Point"}
}