{
  "type": "Feature",
  "properties": {
    "iso:country": "GB",
    "wof:name": "CM22 6GA",
    "wof:placetype": "postalcode"
  },
  "geometry": {"coordinates":[0.223492,51.912699],"type":"Point"}
}
