{
  "type": "Feature",
  "properties": {
    "iso:country":"GB",
    "wof:name":"KA26 9RB",
    "wof:placetype":"postalcode"
},
  "geometry": {"coordinates":[-4.7947492482975,55.25541763246563],"type":"Point"}
}