{
  "type": "Feature",
  "properties": {
    "iso:country": "GB",
    "wof:name": "CV6 2NY",
    "wof:placetype": "postalcode"
  },
  "geometry": {"coordinates":[-1.528141,52.449256],"type":"Point"}
}
