{
  "type": "Feature",
  "properties": {
    "date:inception_lower":"2008-05-01",
    "date:inception_upper":"2008-05-31",
    "iso:country":"GB",
    "wof:name":"CV6 2NY",
    "wof:placetype":"postalcode"
},
  "geometry": {"coordinates":[-1.528141,52.449256],"type":"Point"}
}