{
  "type": "Feature",
  "properties": {
    "iso:country":"GB",
    "wof:name":"CV6 2NY",
    "wof:placetype":"postalcode"
},
  "geometry": {"coordinates":[-1.52814055219671,52.44925628632045],"type":"Point"}
}