{
  "type": "Feature",
  "properties": {
    "date:inception_lower": "2020-09-01",
    "date:inception_upper": "2020-09-01",
    "iso:country": "GB",
    "wof:name": "B49 6FW",
    "wof:placetype": "postalcode"
  },
  "geometry": {"coordinates":[-1.822763,52.236031],"type":"Point"}
}
