{
  "type": "Feature",
  "properties": {
    "iso:country":"GB",
    "wof:name":"SK6 5GF",
    "wof:placetype":"postalcode"
},
  "geometry": {"coordinates":[-2.05540117036755,53.41437234096392],"type":"Point"}
}