{
  "type": "Feature",
  "properties": {
    "iso:country": "GB",
    "wof:name": "SK6 5GF",
    "wof:placetype": "postalcode"
  },
  "geometry": {"coordinates":[-2.055401,53.414372],"type":"Point"}
}
