{
  "type": "Feature",
  "properties": {
    "iso:country":"GB",
    "wof:name":"G64 2FG",
    "wof:placetype":"postalcode"
},
  "geometry": {"coordinates":[-4.21693559509408,55.91459865435464],"type":"Point"}
}