{
  "type": "Feature",
  "properties": {
    "date:inception_lower": "2016-01-01",
    "date:inception_upper": "2016-01-01",
    "iso:country": "GB",
    "wof:name": "G64 2FG",
    "wof:placetype": "postalcode"
  },
  "geometry": {"coordinates":[-4.216909,55.914648],"type":"Point"}
}
