{
  "type": "Feature",
  "properties": {
    "date:inception_lower": "1997-12-01",
    "date:inception_upper": "1997-12-01",
    "iso:country": "GB",
    "wof:name": "KY1 3PS",
    "wof:placetype": "postalcode"
  },
  "geometry": {"coordinates":[-3.145471,56.137671],"type":"Point"}
}
