{
  "type": "Feature",
  "properties": {
    "iso:country":"GB",
    "wof:name":"KY1 3PS",
    "wof:placetype":"postalcode"
},
  "geometry": {"coordinates":[-3.14627119782692,56.13759823224328],"type":"Point"}
}