{
  "type": "Feature",
  "properties": {
    "iso:country":"GB",
    "wof:name":"SE24 9EQ",
    "wof:placetype":"postalcode"
},
  "geometry": {"coordinates":[-0.10100616394356,51.44745533519158],"type":"Point"}
}