{
  "type": "Feature",
  "properties": {
    "iso:country":"GB",
    "wof:name":"NG16 1GF",
    "wof:placetype":"postalcode"
},
  "geometry": {"coordinates":[-1.25329534544612,53.00341879928689],"type":"Point"}
}