{
  "type": "Feature",
  "properties": {
    "date:inception_lower":"2001-06-01",
    "date:inception_upper":"2001-06-30",
    "iso:country":"GB",
    "wof:name":"NG16 1GF",
    "wof:placetype":"postalcode"
},
  "geometry": {"coordinates":[-1.253295,53.003419],"type":"Point"}
}