{
  "type": "Feature",
  "properties": {
    "iso:country": "GB",
    "wof:name": "NG16 1GF",
    "wof:placetype": "postalcode"
  },
  "geometry": {"coordinates":[-1.253295,53.003419],"type":"Point"}
}
