{
  "type": "Feature",
  "properties": {
    "date:inception_lower":"1980-01-01",
    "date:inception_upper":"1980-01-31",
    "iso:country":"GB",
    "wof:name":"TN13 2LX",
    "wof:placetype":"postalcode"
},
  "geometry": {"coordinates":[0.180342,51.265503],"type":"Point"}
}