{
  "type": "Feature",
  "properties": {
    "iso:country":"GB",
    "wof:name":"TQ8 8AL",
    "wof:placetype":"postalcode"
},
  "geometry": {"coordinates":[-3.77690509311446,50.23638286573347],"type":"Point"}
}