{
  "type": "Feature",
  "properties": {
    "iso:country":"GB",
    "wof:name":"PL30 5AS",
    "wof:placetype":"postalcode"
},
  "geometry": {"coordinates":[-4.70651376738577,50.4056544141658],"type":"Point"}
}