{
  "type": "Feature",
  "properties": {
    "iso:country": "GB",
    "wof:name": "PL30 5AS",
    "wof:placetype": "postalcode"
  },
  "geometry": {"coordinates":[-4.706514,50.405654],"type":"Point"}
}
