{
  "type": "Feature",
  "properties": {
    "iso:country":"GB",
    "wof:name":"NG21 0SN",
    "wof:placetype":"postalcode"
},
  "geometry": {"coordinates":[-1.1085947699676,53.10043374533281],"type":"Point"}
}