{
  "type": "Feature",
  "properties": {
    "iso:country": "GB",
    "wof:name": "NG21 0SN",
    "wof:placetype": "postalcode"
  },
  "geometry": {"coordinates":[-1.108595,53.100434],"type":"Point"}
}
