{
  "type": "Feature",
  "properties": {
    "iso:country":"GB",
    "wof:name":"HG3 1NH",
    "wof:placetype":"postalcode"
},
  "geometry": {"coordinates":[-1.53685815462974,53.96586751787674],"type":"Point"}
}