{
  "type": "Feature",
  "properties": {
    "iso:country": "GB",
    "wof:name": "HD5 8LX",
    "wof:placetype": "postalcode"
  },
  "geometry": {"coordinates":[-1.755704,53.635502],"type":"Point"}
}
