{
  "type": "Feature",
  "properties": {
    "iso:country":"GB",
    "wof:name":"HA1 3QB",
    "wof:placetype":"postalcode"
},
  "geometry": {"coordinates":[-0.33818167313114,51.56404560051543],"type":"Point"}
}