{
  "type": "Feature",
  "properties": {
    "iso:country":"GB",
    "wof:name":"GL4 6DW",
    "wof:placetype":"postalcode"
},
  "geometry": {"coordinates":[-2.23055749323647,51.84270874841133],"type":"Point"}
}