{
  "type": "Feature",
  "properties": {
    "iso:country":"GB",
    "wof:name":"PL21 9AU",
    "wof:placetype":"postalcode"
},
  "geometry": {"coordinates":[-3.92771068609845,50.38777053381339],"type":"Point"}
}