{
  "type": "Feature",
  "properties": {
    "iso:country": "GB",
    "wof:name": "PL21 9AU",
    "wof:placetype": "postalcode"
  },
  "geometry": {"coordinates":[-3.927711,50.387771],"type":"Point"}
}
