{
  "type": "Feature",
  "properties": {
    "iso:country":"GB",
    "wof:name":"DT10 1AN",
    "wof:placetype":"postalcode"
},
  "geometry": {"coordinates":[-2.30521051489219,50.92546902005942],"type":"Point"}
}