{
  "type": "Feature",
  "properties": {
    "iso:country":"GB",
    "wof:name":"BS30 9PU",
    "wof:placetype":"postalcode"
},
  "geometry": {"coordinates":[-2.48351418724246,51.44188970681613],"type":"Point"}
}