{
  "type": "Feature",
  "properties": {
    "iso:country": "GB",
    "wof:name": "BS30 9PU",
    "wof:placetype": "postalcode"
  },
  "geometry": {"coordinates":[-2.483402,51.442086],"type":"Point"}
}
