{
  "type": "Feature",
  "properties": {
    "iso:country":"GB",
    "wof:name":"KT12 3JE",
    "wof:placetype":"postalcode"
},
  "geometry": {"coordinates":[-0.40218119822829,51.38069152029966],"type":"Point"}
}