{
  "type": "Feature",
  "properties": {
    "date:inception_lower":"1985-04-01",
    "date:inception_upper":"1985-04-30",
    "iso:country":"GB",
    "wof:name":"LE1 6PL",
    "wof:placetype":"postalcode"
},
  "geometry": {"coordinates":[-1.128991,52.631073],"type":"Point"}
}