{
  "type": "Feature",
  "properties": {
    "iso:country":"GB",
    "wof:name":"IP17 3DS",
    "wof:placetype":"postalcode"
},
  "geometry": {"coordinates":[1.63254234505275,52.27780181133694],"type":"Point"}
}