{
  "type": "Feature",
  "properties": {
    "iso:country": "GB",
    "wof:name": "BH21 4HX",
    "wof:placetype": "postalcode"
  },
  "geometry": {"coordinates":[-1.977751,50.822822],"type":"Point"}
}
