{
  "type": "Feature",
  "properties": {
    "iso:country":"GB",
    "wof:name":"BH21 4HX",
    "wof:placetype":"postalcode"
},
  "geometry": {"coordinates":[-1.97994486450351,50.82324526768817],"type":"Point"}
}