{
  "type": "Feature",
  "properties": {
    "iso:country":"GB",
    "wof:name":"PA8 7EG",
    "wof:placetype":"postalcode"
},
  "geometry": {"coordinates":[-4.44772583527726,55.89291519139123],"type":"Point"}
}