{
  "type": "Feature",
  "properties": {
    "iso:country": "GB",
    "wof:name": "DE6 3DB",
    "wof:placetype": "postalcode"
  },
  "geometry": {"coordinates":[-1.620625,52.970926],"type":"Point"}
}
