{
  "type": "Feature",
  "properties": {
    "iso:country":"GB",
    "wof:name":"DE6 3DB",
    "wof:placetype":"postalcode"
},
  "geometry": {"coordinates":[-1.62062537548184,52.97092612519013],"type":"Point"}
}