{
  "type": "Feature",
  "properties": {
    "iso:country":"GB",
    "wof:name":"CT17 9LY",
    "wof:placetype":"postalcode"
},
  "geometry": {"coordinates":[1.28789882411714,51.12411168163744],"type":"Point"}
}