{
  "type": "Feature",
  "properties": {
    "iso:country":"GB",
    "wof:name":"WV14 9AX",
    "wof:placetype":"postalcode"
},
  "geometry": {"coordinates":[-2.09746599355118,52.54284229033682],"type":"Point"}
}