{
  "type": "Feature",
  "properties": {
    "iso:country":"GB",
    "wof:name":"DH9 8EN",
    "wof:placetype":"postalcode"
},
  "geometry": {"coordinates":[-1.74879669746661,54.86370174745823],"type":"Point"}
}