{
  "type": "Feature",
  "properties": {
    "date:inception_lower":"1980-01-01",
    "date:inception_upper":"1980-01-31",
    "iso:country":"GB",
    "wof:name":"SG6 1SN",
    "wof:placetype":"postalcode"
},
  "geometry": {"coordinates":[-0.219003,51.97435],"type":"Point"}
}