{
  "type": "Feature",
  "properties": {
    "iso:country":"GB",
    "wof:name":"SG6 1SN",
    "wof:placetype":"postalcode"
},
  "geometry": {"coordinates":[-0.21900264440933,51.97434957331838],"type":"Point"}
}