{
  "type": "Feature",
  "properties": {
    "iso:country":"GB",
    "wof:name":"BD12 0TR",
    "wof:placetype":"postalcode"
},
  "geometry": {"coordinates":[-1.77416911805802,53.75464005105822],"type":"Point"}
}