{
  "type": "Feature",
  "properties": {
    "iso:country":"GB",
    "wof:name":"WF11 0DT",
    "wof:placetype":"postalcode"
},
  "geometry": {"coordinates":[-1.23522200839543,53.70431793131415],"type":"Point"}
}