{
  "type": "Feature",
  "properties": {
    "iso:country": "GB",
    "wof:name": "WA12 0BQ",
    "wof:placetype": "postalcode"
  },
  "geometry": {"coordinates":[-2.609574,53.453844],"type":"Point"}
}
