{
  "type": "Feature",
  "properties": {
    "date:inception_lower":"1994-12-01",
    "date:inception_upper":"1994-12-31",
    "iso:country":"GB",
    "wof:name":"WA12 0BQ",
    "wof:placetype":"postalcode"
},
  "geometry": {"coordinates":[-2.609574,53.453844],"type":"Point"}
}