{
  "type": "Feature",
  "properties": {
    "iso:country":"GB",
    "wof:name":"BH23 2NL",
    "wof:placetype":"postalcode"
},
  "geometry": {"coordinates":[-1.79402151946224,50.75228503685219],"type":"Point"}
}