{
  "type": "Feature",
  "properties": {
    "iso:country":"GB",
    "wof:name":"DN15 7SA",
    "wof:placetype":"postalcode"
},
  "geometry": {"coordinates":[-0.6588895815158,53.59545839489947],"type":"Point"}
}