{
  "type": "Feature",
  "properties": {
    "iso:country":"GB",
    "wof:name":"CM16 7JR",
    "wof:placetype":"postalcode"
},
  "geometry": {"coordinates":[0.09641667917448,51.66922385879408],"type":"Point"}
}