{
  "type": "Feature",
  "properties": {
    "iso:country": "GB",
    "wof:name": "CM16 7JR",
    "wof:placetype": "postalcode"
  },
  "geometry": {"coordinates":[0.096417,51.669224],"type":"Point"}
}
