{
  "type": "Feature",
  "properties": {
    "date:inception_lower":"1980-01-01",
    "date:inception_upper":"1980-01-31",
    "iso:country":"GB",
    "wof:name":"CM16 7JR",
    "wof:placetype":"postalcode"
},
  "geometry": {"coordinates":[0.096417,51.669224],"type":"Point"}
}