{
  "type": "Feature",
  "properties": {
    "iso:country":"GB",
    "wof:name":"NG12 3RA",
    "wof:placetype":"postalcode"
},
  "geometry": {"coordinates":[-0.9932197857489,52.87218589857057],"type":"Point"}
}