{
  "type": "Feature",
  "properties": {
    "iso:country":"GB",
    "wof:name":"EN7 6HR",
    "wof:placetype":"postalcode"
},
  "geometry": {"coordinates":[-0.05999867303523,51.71397826371734],"type":"Point"}
}