{
  "type": "Feature",
  "properties": {
    "iso:country":"GB",
    "wof:name":"LN5 0RZ",
    "wof:placetype":"postalcode"
},
  "geometry": {"coordinates":[-0.6323587304315,53.07752231232691],"type":"Point"}
}