{
  "type": "Feature",
  "properties": {
    "date:inception_lower":"1980-01-01",
    "date:inception_upper":"1980-01-31",
    "iso:country":"GB",
    "wof:name":"LN5 0RZ",
    "wof:placetype":"postalcode"
},
  "geometry": {"coordinates":[-0.632359,53.077522],"type":"Point"}
}