{
  "type": "Feature",
  "properties": {
    "iso:country":"GB",
    "wof:name":"LL18 3SD",
    "wof:placetype":"postalcode"
},
  "geometry": {"coordinates":[-3.47237421003708,53.32431882837765],"type":"Point"}
}