{
  "type": "Feature",
  "properties": {
    "iso:country": "GB",
    "wof:name": "TD9 7JD",
    "wof:placetype": "postalcode"
  },
  "geometry": {"coordinates":[-2.809108,55.421629],"type":"Point"}
}
