{
  "type": "Feature",
  "properties": {
    "iso:country":"GB",
    "wof:name":"LS7 3RE",
    "wof:placetype":"postalcode"
},
  "geometry": {"coordinates":[-1.54527718736753,53.82937359199215],"type":"Point"}
}