{
  "type": "Feature",
  "properties": {
    "date:inception_lower": "1980-01-01",
    "date:inception_upper": "1980-01-01",
    "iso:country": "GB",
    "wof:name": "BD23 5RP",
    "wof:placetype": "postalcode"
  },
  "geometry": {"coordinates":[-2.028759,54.159938],"type":"Point"}
}
