{
  "type": "Feature",
  "properties": {
    "iso:country": "GB",
    "wof:name": "BD23 5RP",
    "wof:placetype": "postalcode"
  },
  "geometry": {"coordinates":[-2.036422,54.166631],"type":"Point"}
}
