{
  "type": "Feature",
  "properties": {
    "date:inception_lower": "1980-01-01",
    "date:inception_upper": "1980-01-01",
    "iso:country": "GB",
    "wof:name": "DL8 2BE",
    "wof:placetype": "postalcode"
  },
  "geometry": {"coordinates":[-1.595742,54.283538],"type":"Point"}
}
