{
  "type": "Feature",
  "properties": {
    "iso:country":"GB",
    "wof:name":"DL8 2BE",
    "wof:placetype":"postalcode"
},
  "geometry": {"coordinates":[-1.59574209518954,54.28353754985149],"type":"Point"}
}