{
  "type": "Feature",
  "properties": {
    "iso:country": "GB",
    "wof:name": "DL8 2BE",
    "wof:placetype": "postalcode"
  },
  "geometry": {"coordinates":[-1.595742,54.283538],"type":"Point"}
}
