{
  "type": "Feature",
  "properties": {
    "date:inception_lower": "1984-02-01",
    "date:inception_upper": "1984-02-01",
    "iso:country": "GB",
    "wof:name": "NN11 4DU",
    "wof:placetype": "postalcode"
  },
  "geometry": {"coordinates":[-1.16398,52.257079],"type":"Point"}
}
