{
  "type": "Feature",
  "properties": {
    "iso:country":"GB",
    "wof:name":"SK8 2BF",
    "wof:placetype":"postalcode"
},
  "geometry": {"coordinates":[-2.20277873938945,53.38875708921588],"type":"Point"}
}