{
  "type": "Feature",
  "properties": {
    "iso:country": "GB",
    "wof:name": "SK8 2BF",
    "wof:placetype": "postalcode"
  },
  "geometry": {"coordinates":[-2.202779,53.388757],"type":"Point"}
}
