{
  "type": "Feature",
  "properties": {
    "iso:country":"GB",
    "wof:name":"WR4 9QJ",
    "wof:placetype":"postalcode"
},
  "geometry": {"coordinates":[-2.20055815616246,52.19827308420399],"type":"Point"}
}