{
  "type": "Feature",
  "properties": {
    "date:inception_lower": "2022-12-01",
    "date:inception_upper": "2022-12-01",
    "iso:country": "GB",
    "wof:name": "HD3 4ZU",
    "wof:placetype": "postalcode"
  },
  "geometry": {"coordinates":[-1.832467,53.651935],"type":"Point"}
}
