{
  "type": "Feature",
  "properties": {
    "iso:country": "GB",
    "wof:name": "ST5 5HB",
    "wof:placetype": "postalcode"
  },
  "geometry": {"coordinates":[-2.302247,52.966417],"type":"Point"}
}
