{
  "type": "Feature",
  "properties": {
    "date:inception_lower": "2018-11-01",
    "date:inception_upper": "2018-11-01",
    "iso:country": "GB",
    "wof:name": "WA3 2UG",
    "wof:placetype": "postalcode"
  },
  "geometry": {"coordinates":[-2.559743,53.475631],"type":"Point"}
}
