{
  "type": "Feature",
  "properties": {
    "iso:country": "GB",
    "wof:name": "BN22 8BE",
    "wof:placetype": "postalcode"
  },
  "geometry": {"coordinates":[0.29284,50.772387],"type":"Point"}
}
