{
  "type": "Feature",
  "properties": {
    "iso:country":"GB",
    "wof:name":"NG8 3NF",
    "wof:placetype":"postalcode"
},
  "geometry": {"coordinates":[-1.1936717719253,52.96505823044219],"type":"Point"}
}