{
  "type": "Feature",
  "properties": {
    "iso:country":"GB",
    "wof:name":"S61 4PG",
    "wof:placetype":"postalcode"
},
  "geometry": {"coordinates":[-1.36194918469769,53.45373357467948],"type":"Point"}
}