{
  "type": "Feature",
  "properties": {
    "iso:country":"GB",
    "wof:name":"LN4 2BJ",
    "wof:placetype":"postalcode"
},
  "geometry": {"coordinates":[-0.41752534438651,53.16411161911831],"type":"Point"}
}