{
  "type": "Feature",
  "properties": {
    "iso:country": "GB",
    "wof:name": "LN4 2BJ",
    "wof:placetype": "postalcode"
  },
  "geometry": {"coordinates":[-0.417525,53.164112],"type":"Point"}
}
