{
  "type": "Feature",
  "properties": {
    "iso:country":"GB",
    "wof:name":"NW10 3JA",
    "wof:placetype":"postalcode"
},
  "geometry": {"coordinates":[-0.22009350180226,51.53475221424755],"type":"Point"}
}