{
  "type": "Feature",
  "properties": {
    "date:inception_lower": "1998-12-01",
    "date:inception_upper": "1998-12-01",
    "iso:country": "GB",
    "wof:name": "NW10 3JA",
    "wof:placetype": "postalcode"
  },
  "geometry": {"coordinates":[-0.220093,51.534752],"type":"Point"}
}
