{
  "type": "Feature",
  "properties": {
    "iso:country":"GB",
    "wof:name":"B26 3PP",
    "wof:placetype":"postalcode"
},
  "geometry": {"coordinates":[-1.76871722458846,52.45128336644372],"type":"Point"}
}