{
  "type": "Feature",
  "properties": {
    "date:inception_lower": "1980-01-01",
    "date:inception_upper": "1980-01-01",
    "iso:country": "GB",
    "wof:name": "BD2 2HN",
    "wof:placetype": "postalcode"
  },
  "geometry": {"coordinates":[-1.725195,53.820776],"type":"Point"}
}
