{
  "type": "Feature",
  "properties": {
    "iso:country":"GB",
    "wof:name":"BD2 2HN",
    "wof:placetype":"postalcode"
},
  "geometry": {"coordinates":[-1.72519080556119,53.82076148018893],"type":"Point"}
}