{
  "type": "Feature",
  "properties": {
    "iso:country":"GB",
    "wof:name":"OL9 7EZ",
    "wof:placetype":"postalcode"
},
  "geometry": {"coordinates":[-2.13771445008262,53.52678717009186],"type":"Point"}
}