{
  "type": "Feature",
  "properties": {
    "iso:country": "GB",
    "wof:name": "SG6 1UE",
    "wof:placetype": "postalcode"
  },
  "geometry": {"coordinates":[-0.20837,51.989493],"type":"Point"}
}
