{
  "type": "Feature",
  "properties": {
    "date:inception_lower": "1990-02-01",
    "date:inception_upper": "1990-02-01",
    "iso:country": "GB",
    "wof:name": "SG6 1UE",
    "wof:placetype": "postalcode"
  },
  "geometry": {"coordinates":[-0.20837,51.989493],"type":"Point"}
}
