{
  "type": "Feature",
  "properties": {
    "iso:country":"GB",
    "wof:name":"B1 1LB",
    "wof:placetype":"postalcode"
},
  "geometry": {"coordinates":[-1.90698520799346,52.47444201727698],"type":"Point"}
}