{
  "type": "Feature",
  "properties": {
    "iso:country":"GB",
    "wof:name":"TQ7 4EF",
    "wof:placetype":"postalcode"
},
  "geometry": {"coordinates":[-3.81626655891879,50.34177933146046],"type":"Point"}
}