{
  "type": "Feature",
  "properties": {
    "date:inception_lower": "1990-07-01",
    "date:inception_upper": "1990-07-01",
    "iso:country": "GB",
    "wof:name": "PE6 8AU",
    "wof:placetype": "postalcode"
  },
  "geometry": {"coordinates":[-0.317437,52.685632],"type":"Point"}
}
