{
  "type": "Feature",
  "properties": {
    "iso:country":"GB",
    "wof:name":"PE6 8AU",
    "wof:placetype":"postalcode"
},
  "geometry": {"coordinates":[-0.31743741294853,52.68563166177395],"type":"Point"}
}