{
  "type": "Feature",
  "properties": {
    "iso:country": "GB",
    "wof:name": "WV11 2LD",
    "wof:placetype": "postalcode"
  },
  "geometry": {"coordinates":[-2.055894,52.619507],"type":"Point"}
}
