{
  "type": "Feature",
  "properties": {
    "iso:country":"GB",
    "wof:name":"WV11 2LD",
    "wof:placetype":"postalcode"
},
  "geometry": {"coordinates":[-2.05589417160635,52.6195073904934],"type":"Point"}
}