{
  "type": "Feature",
  "properties": {
    "date:inception_lower": "2012-05-01",
    "date:inception_upper": "2012-05-01",
    "iso:country": "GB",
    "wof:name": "N12 8BF",
    "wof:placetype": "postalcode"
  },
  "geometry": {"coordinates":[-0.182797,51.616775],"type":"Point"}
}
