{
  "type": "Feature",
  "properties": {
    "iso:country": "GB",
    "wof:name": "PR5 8BP",
    "wof:placetype": "postalcode"
  },
  "geometry": {"coordinates":[-2.645963,53.721883],"type":"Point"}
}
