{
  "type": "Feature",
  "properties": {
    "iso:country":"GB",
    "wof:name":"PR5 8BP",
    "wof:placetype":"postalcode"
},
  "geometry": {"coordinates":[-2.64613240955946,53.72183049157972],"type":"Point"}
}