{
  "type": "Feature",
  "properties": {
    "iso:country": "GB",
    "wof:name": "RG24 8SG",
    "wof:placetype": "postalcode"
  },
  "geometry": {"coordinates":[-1.056052,51.274294],"type":"Point"}
}
