{
  "type": "Feature",
  "properties": {
    "date:inception_lower": "1980-01-01",
    "date:inception_upper": "1980-01-01",
    "iso:country": "GB",
    "wof:name": "ST5 6BW",
    "wof:placetype": "postalcode"
  },
  "geometry": {"coordinates":[-2.279071,53.038882],"type":"Point"}
}
