{
  "type": "Feature",
  "properties": {
    "iso:country": "GB",
    "wof:name": "ST5 6BW",
    "wof:placetype": "postalcode"
  },
  "geometry": {"coordinates":[-2.279071,53.038882],"type":"Point"}
}
