{
  "type": "Feature",
  "properties": {
    "iso:country":"GB",
    "wof:name":"DG4 6LA",
    "wof:placetype":"postalcode"
},
  "geometry": {"coordinates":[-3.93340760671196,55.35729964632563],"type":"Point"}
}