{
  "type": "Feature",
  "properties": {
    "iso:country":"GB",
    "wof:name":"ML5 3RX",
    "wof:placetype":"postalcode"
},
  "geometry": {"coordinates":[-4.00418232469719,55.86117923448437],"type":"Point"}
}