{
  "type": "Feature",
  "properties": {
    "iso:country":"GB",
    "wof:name":"NR25 6JT",
    "wof:placetype":"postalcode"
},
  "geometry": {"coordinates":[1.08660382021712,52.90804210241335],"type":"Point"}
}