{
  "type": "Feature",
  "properties": {
    "iso:country":"GB",
    "wof:name":"CV3 3JE",
    "wof:placetype":"postalcode"
},
  "geometry": {"coordinates":[-1.47098418434974,52.38593968615786],"type":"Point"}
}