{
  "type": "Feature",
  "properties": {
    "iso:country":"GB",
    "wof:name":"KA2 0BX",
    "wof:placetype":"postalcode"
},
  "geometry": {"coordinates":[-4.54745281228675,55.60500909623067],"type":"Point"}
}