{
  "type": "Feature",
  "properties": {
    "date:inception_lower": "1980-01-01",
    "date:inception_upper": "1980-01-01",
    "iso:country": "GB",
    "wof:name": "PO13 8JL",
    "wof:placetype": "postalcode"
  },
  "geometry": {"coordinates":[-1.194817,50.804608],"type":"Point"}
}
