{
  "type": "Feature",
  "properties": {
    "iso:country":"GB",
    "wof:name":"NG8 3DA",
    "wof:placetype":"postalcode"
},
  "geometry": {"coordinates":[-1.22056266785866,52.97323813736669],"type":"Point"}
}