{
  "type": "Feature",
  "properties": {
    "iso:country":"GB",
    "wof:name":"WA9 1LP",
    "wof:placetype":"postalcode"
},
  "geometry": {"coordinates":[-2.7231986196547,53.45498932241544],"type":"Point"}
}