{
  "type": "Feature",
  "properties": {
    "iso:country": "GB",
    "wof:name": "WA9 1LP",
    "wof:placetype": "postalcode"
  },
  "geometry": {"coordinates":[-2.723199,53.454989],"type":"Point"}
}
