{
  "type": "Feature",
  "properties": {
    "iso:country":"GB",
    "wof:name":"DE1 3QW",
    "wof:placetype":"postalcode"
},
  "geometry": {"coordinates":[-1.46921664763904,52.93094657231327],"type":"Point"}
}