{
  "type": "Feature",
  "properties": {
    "iso:country":"GB",
    "wof:name":"LE15 6BN",
    "wof:placetype":"postalcode"
},
  "geometry": {"coordinates":[-0.7216539309394,52.67796746176833],"type":"Point"}
}