{
  "type": "Feature",
  "properties": {
    "date:inception_lower":"1991-09-01",
    "date:inception_upper":"1991-09-30",
    "iso:country":"GB",
    "wof:name":"LE15 6BN",
    "wof:placetype":"postalcode"
},
  "geometry": {"coordinates":[-0.721654,52.677967],"type":"Point"}
}