{
  "type": "Feature",
  "properties": {
    "iso:country": "GB",
    "wof:name": "PE28 5XY",
    "wof:placetype": "postalcode"
  },
  "geometry": {"coordinates":[-0.302983,52.404218],"type":"Point"}
}
