{
  "type": "Feature",
  "properties": {
    "iso:country":"GB",
    "wof:name":"WA6 6HW",
    "wof:placetype":"postalcode"
},
  "geometry": {"coordinates":[-2.72316656462007,53.27301091384938],"type":"Point"}
}