{
  "type": "Feature",
  "properties": {
    "date:inception_lower":"1980-01-01",
    "date:inception_upper":"1980-01-31",
    "iso:country":"GB",
    "wof:name":"WA6 6HW",
    "wof:placetype":"postalcode"
},
  "geometry": {"coordinates":[-2.723167,53.273011],"type":"Point"}
}