{
  "type": "Feature",
  "properties": {
    "iso:country":"GB",
    "wof:name":"EX18 7NF",
    "wof:placetype":"postalcode"
},
  "geometry": {"coordinates":[-3.9456663336581,50.89697938202148],"type":"Point"}
}