{
  "type": "Feature",
  "properties": {
    "iso:country":"GB",
    "wof:name":"SO45 2PT",
    "wof:placetype":"postalcode"
},
  "geometry": {"coordinates":[-1.39065458808007,50.8278531958513],"type":"Point"}
}