{
  "type": "Feature",
  "properties": {
    "iso:country":"GB",
    "wof:name":"DN20 0HN",
    "wof:placetype":"postalcode"
},
  "geometry": {"coordinates":[-0.54427396450573,53.56829319050858],"type":"Point"}
}