{
  "type": "Feature",
  "properties": {
    "iso:country":"GB",
    "wof:name":"NW9 5FG",
    "wof:placetype":"postalcode"
},
  "geometry": {"coordinates":[-0.2451032688684,51.59937908766541],"type":"Point"}
}