{
  "type": "Feature",
  "properties": {
    "date:inception_lower":"1980-01-01",
    "date:inception_upper":"1980-01-31",
    "iso:country":"GB",
    "wof:name":"NW9 5FG",
    "wof:placetype":"postalcode"
},
  "geometry": {"coordinates":[-0.245103,51.599379],"type":"Point"}
}