{
  "type": "Feature",
  "properties": {
    "iso:country":"GB",
    "wof:name":"M46 0HE",
    "wof:placetype":"postalcode"
},
  "geometry": {"coordinates":[-2.4959976940752,53.52863239843978],"type":"Point"}
}