{
  "type": "Feature",
  "properties": {
    "iso:country":"GB",
    "wof:name":"ML1 2RP",
    "wof:placetype":"postalcode"
},
  "geometry": {"coordinates":[-3.9898908038473,55.7791627675717],"type":"Point"}
}