{
  "type": "Feature",
  "properties": {
    "iso:country": "GB",
    "wof:name": "BH31 6HW",
    "wof:placetype": "postalcode"
  },
  "geometry": {"coordinates":[-1.881377,50.873257],"type":"Point"}
}
