{
  "type": "Feature",
  "properties": {
    "iso:country":"GB",
    "wof:name":"BB4 6RJ",
    "wof:placetype":"postalcode"
},
  "geometry": {"coordinates":[-2.29863221670824,53.69938260053171],"type":"Point"}
}