{
  "type": "Feature",
  "properties": {
    "date:inception_lower": "1983-01-01",
    "date:inception_upper": "1983-01-01",
    "iso:country": "GB",
    "wof:name": "BB4 6RJ",
    "wof:placetype": "postalcode"
  },
  "geometry": {"coordinates":[-2.299195,53.699828],"type":"Point"}
}
