{
  "type": "Feature",
  "properties": {
    "iso:country":"GB",
    "wof:name":"B38 8PG",
    "wof:placetype":"postalcode"
},
  "geometry": {"coordinates":[-1.94300339296157,52.39982958790095],"type":"Point"}
}