{
  "type": "Feature",
  "properties": {
    "date:inception_lower": "1980-01-01",
    "date:inception_upper": "1980-01-01",
    "iso:country": "GB",
    "wof:name": "B38 8PG",
    "wof:placetype": "postalcode"
  },
  "geometry": {"coordinates":[-1.943003,52.39983],"type":"Point"}
}
