{
  "type": "Feature",
  "properties": {
    "iso:country":"GB",
    "wof:name":"LU4 9LJ",
    "wof:placetype":"postalcode"
},
  "geometry": {"coordinates":[-0.47063669477321,51.9005680503685],"type":"Point"}
}