{
  "type": "Feature",
  "properties": {
    "date:inception_lower":"1980-01-01",
    "date:inception_upper":"1980-01-31",
    "iso:country":"GB",
    "wof:name":"LU4 9LJ",
    "wof:placetype":"postalcode"
},
  "geometry": {"coordinates":[-0.470537,51.900602],"type":"Point"}
}