{
  "type": "Feature",
  "properties": {
    "iso:country": "GB",
    "wof:name": "LL29 8FE",
    "wof:placetype": "postalcode"
  },
  "geometry": {"coordinates":[-3.65551,53.285572],"type":"Point"}
}
