{
  "type": "Feature",
  "properties": {
    "iso:country": "GB",
    "wof:name": "WD18 7NZ",
    "wof:placetype": "postalcode"
  },
  "geometry": {"coordinates":[-0.409222,51.654354],"type":"Point"}
}
