{
  "type": "Feature",
  "properties": {
    "iso:country": "GB",
    "wof:name": "DA7 6GS",
    "wof:placetype": "postalcode"
  },
  "geometry": {"coordinates":[0.158115,51.463322],"type":"Point"}
}
