{
  "type": "Feature",
  "properties": {
    "iso:country":"GB",
    "wof:name":"UB3 1EN",
    "wof:placetype":"postalcode"
},
  "geometry": {"coordinates":[-0.43031258477061,51.50506657843896],"type":"Point"}
}