{
  "type": "Feature",
  "properties": {
    "iso:country": "GB",
    "wof:name": "UB3 1EN",
    "wof:placetype": "postalcode"
  },
  "geometry": {"coordinates":[-0.430313,51.505067],"type":"Point"}
}
