{
  "type": "Feature",
  "properties": {
    "iso:country":"GB",
    "wof:name":"HU4 6LF",
    "wof:placetype":"postalcode"
},
  "geometry": {"coordinates":[-0.38902224364596,53.73693668767185],"type":"Point"}
}