{
  "type": "Feature",
  "properties": {
    "iso:country": "GB",
    "wof:name": "HU4 6LF",
    "wof:placetype": "postalcode"
  },
  "geometry": {"coordinates":[-0.389022,53.736937],"type":"Point"}
}
