{
  "type": "Feature",
  "properties": {
    "date:inception_lower": "1995-01-01",
    "date:inception_upper": "1995-01-01",
    "iso:country": "GB",
    "wof:name": "LA3 3FB",
    "wof:placetype": "postalcode"
  },
  "geometry": {"coordinates":[-2.850277,54.055976],"type":"Point"}
}
