{
  "type": "Feature",
  "properties": {
    "iso:country":"GB",
    "wof:name":"LA3 3FB",
    "wof:placetype":"postalcode"
},
  "geometry": {"coordinates":[-2.83854517371962,54.0535757600256],"type":"Point"}
}