{
  "type": "Feature",
  "properties": {
    "date:inception_lower": "1980-01-01",
    "date:inception_upper": "1980-01-01",
    "iso:country": "GB",
    "wof:name": "EX39 4RD",
    "wof:placetype": "postalcode"
  },
  "geometry": {"coordinates":[-4.187905,51.01538],"type":"Point"}
}
