{
  "type": "Feature",
  "properties": {
    "iso:country": "GB",
    "wof:name": "ML1 5UU",
    "wof:placetype": "postalcode"
  },
  "geometry": {"coordinates":[-3.947199,55.821156],"type":"Point"}
}
