{
  "type": "Feature",
  "properties": {
    "iso:country":"GB",
    "wof:name":"E16 1SG",
    "wof:placetype":"postalcode"
},
  "geometry": {"coordinates":[0.0193923576038,51.50449838923611],"type":"Point"}
}