{
  "type": "Feature",
  "properties": {
    "date:inception_lower": "1996-12-01",
    "date:inception_upper": "1996-12-01",
    "iso:country": "GB",
    "wof:name": "E16 1SG",
    "wof:placetype": "postalcode"
  },
  "geometry": {"coordinates":[0.019392,51.504498],"type":"Point"}
}
