{
  "type": "Feature",
  "properties": {
    "iso:country":"GB",
    "wof:name":"CV10 9JY",
    "wof:placetype":"postalcode"
},
  "geometry": {"coordinates":[-1.52060141861916,52.52837416902494],"type":"Point"}
}