{
  "type": "Feature",
  "properties": {
    "iso:country": "GB",
    "wof:name": "DL5 6RT",
    "wof:placetype": "postalcode"
  },
  "geometry": {"coordinates":[-1.61208,54.598552],"type":"Point"}
}
