{
  "type": "Feature",
  "properties": {
    "date:inception_lower": "2022-03-01",
    "date:inception_upper": "2022-03-01",
    "iso:country": "GB",
    "wof:name": "CF48 2SF",
    "wof:placetype": "postalcode"
  },
  "geometry": {"coordinates":[-3.368258,51.77023],"type":"Point"}
}
