{
  "type": "Feature",
  "properties": {
    "iso:country": "GB",
    "wof:name": "GU29 9LF",
    "wof:placetype": "postalcode"
  },
  "geometry": {"coordinates":[-0.751046,50.985765],"type":"Point"}
}
