{
  "type": "Feature",
  "properties": {
    "date:inception_lower": "1980-01-01",
    "date:inception_upper": "1980-01-01",
    "iso:country": "GB",
    "wof:name": "GU29 9LF",
    "wof:placetype": "postalcode"
  },
  "geometry": {"coordinates":[-0.751046,50.985765],"type":"Point"}
}
