{
  "type": "Feature",
  "properties": {
    "iso:country":"GB",
    "wof:name":"GU29 9LF",
    "wof:placetype":"postalcode"
},
  "geometry": {"coordinates":[-0.75104558770729,50.98576506547913],"type":"Point"}
}