{
  "type": "Feature",
  "properties": {
    "iso:country":"GB",
    "wof:name":"BB7 3ET",
    "wof:placetype":"postalcode"
},
  "geometry": {"coordinates":[-2.44099470492151,53.96699144793048],"type":"Point"}
}