{
  "type": "Feature",
  "properties": {
    "iso:country": "GB",
    "wof:name": "TS27 4LD",
    "wof:placetype": "postalcode"
  },
  "geometry": {"coordinates":[-1.291987,54.747876],"type":"Point"}
}
