{
  "type": "Feature",
  "properties": {
    "date:inception_lower": "1980-01-01",
    "date:inception_upper": "1980-01-01",
    "iso:country": "GB",
    "wof:name": "TS27 4LD",
    "wof:placetype": "postalcode"
  },
  "geometry": {"coordinates":[-1.291987,54.747876],"type":"Point"}
}
