{
  "type": "Feature",
  "properties": {
    "date:inception_lower": "1980-01-01",
    "date:inception_upper": "1980-01-01",
    "iso:country": "GB",
    "wof:name": "E4 9HU",
    "wof:placetype": "postalcode"
  },
  "geometry": {"coordinates":[-0.00002,51.612949],"type":"Point"}
}
