{
  "type": "Feature",
  "properties": {
    "iso:country":"GB",
    "wof:name":"TS11 6DZ",
    "wof:placetype":"postalcode"
},
  "geometry": {"coordinates":[-1.02787698140207,54.589051917791],"type":"Point"}
}