{
  "type": "Feature",
  "properties": {
    "iso:country": "GB",
    "wof:name": "HP18 0FQ",
    "wof:placetype": "postalcode"
  },
  "geometry": {"coordinates":[-0.859114,51.83495],"type":"Point"}
}
