{
  "type": "Feature",
  "properties": {
    "iso:country":"GB",
    "wof:name":"SY4 3AU",
    "wof:placetype":"postalcode"
},
  "geometry": {"coordinates":[-2.79050288187952,52.810405582382],"type":"Point"}
}