{
  "type": "Feature",
  "properties": {
    "date:inception_lower":"2008-05-01",
    "date:inception_upper":"2008-05-31",
    "iso:country":"GB",
    "wof:name":"SY4 3AU",
    "wof:placetype":"postalcode"
},
  "geometry": {"coordinates":[-2.790503,52.810406],"type":"Point"}
}