{
  "type": "Feature",
  "properties": {
    "iso:country":"GB",
    "wof:name":"M41 9AW",
    "wof:placetype":"postalcode"
},
  "geometry": {"coordinates":[-2.34842419222712,53.446792412025],"type":"Point"}
}