{
  "type": "Feature",
  "properties": {
    "iso:country":"GB",
    "wof:name":"SW20 9DG",
    "wof:placetype":"postalcode"
},
  "geometry": {"coordinates":[-0.22975241700735,51.40571258518115],"type":"Point"}
}