{
  "type": "Feature",
  "properties": {
    "date:inception_lower":"1981-06-01",
    "date:inception_upper":"1981-06-30",
    "iso:country":"GB",
    "wof:name":"SW20 9DG",
    "wof:placetype":"postalcode"
},
  "geometry": {"coordinates":[-0.229752,51.405713],"type":"Point"}
}