{
  "type": "Feature",
  "properties": {
    "iso:country": "GB",
    "wof:name": "SW20 9DG",
    "wof:placetype": "postalcode"
  },
  "geometry": {"coordinates":[-0.229752,51.405713],"type":"Point"}
}
