{
  "type": "Feature",
  "properties": {
    "iso:country":"GB",
    "wof:name":"WS15 1SB",
    "wof:placetype":"postalcode"
},
  "geometry": {"coordinates":[-1.92991109237537,52.75085683165047],"type":"Point"}
}