{
  "type": "Feature",
  "properties": {
    "iso:country":"GB",
    "wof:name":"CV1 3JS",
    "wof:placetype":"postalcode"
},
  "geometry": {"coordinates":[-1.51623187794706,52.40536338927455],"type":"Point"}
}