{
  "type": "Feature",
  "properties": {
    "iso:country": "GB",
    "wof:name": "CV1 3JS",
    "wof:placetype": "postalcode"
  },
  "geometry": {"coordinates":[-1.516232,52.405363],"type":"Point"}
}
