{
  "type": "Feature",
  "properties": {
    "iso:country":"GB",
    "wof:name":"AB12 4BA",
    "wof:placetype":"postalcode"
},
  "geometry": {"coordinates":[-2.14614983389949,57.06138912853675],"type":"Point"}
}