{
  "type": "Feature",
  "properties": {
    "iso:country":"GB",
    "wof:name":"KT7 0BY",
    "wof:placetype":"postalcode"
},
  "geometry": {"coordinates":[-0.33275315681975,51.38760162292134],"type":"Point"}
}