{
  "type": "Feature",
  "properties": {
    "iso:country": "GB",
    "wof:name": "SA72 6PR",
    "wof:placetype": "postalcode"
  },
  "geometry": {"coordinates":[-4.936098,51.686535],"type":"Point"}
}
