{
  "type": "Feature",
  "properties": {
    "date:inception_lower":"2002-08-01",
    "date:inception_upper":"2002-08-31",
    "iso:country":"GB",
    "wof:name":"EH23 4FB",
    "wof:placetype":"postalcode"
},
  "geometry": {"coordinates":[-3.061678,55.854627],"type":"Point"}
}