{
  "type": "Feature",
  "properties": {
    "iso:country": "GB",
    "wof:name": "EH23 4FB",
    "wof:placetype": "postalcode"
  },
  "geometry": {"coordinates":[-3.061678,55.854627],"type":"Point"}
}
