{
  "type": "Feature",
  "properties": {
    "iso:country":"GB",
    "wof:name":"EH23 4FB",
    "wof:placetype":"postalcode"
},
  "geometry": {"coordinates":[-3.06167765093421,55.85462669371555],"type":"Point"}
}