{
  "type": "Feature",
  "properties": {
    "iso:country":"GB",
    "wof:name":"CH43 2HL",
    "wof:placetype":"postalcode"
},
  "geometry": {"coordinates":[-3.05748313710397,53.37330451944869],"type":"Point"}
}