{
  "type": "Feature",
  "properties": {
    "iso:country":"GB",
    "wof:name":"WR10 1EW",
    "wof:placetype":"postalcode"
},
  "geometry": {"coordinates":[-2.07636072939991,52.1153203089967],"type":"Point"}
}