{
  "type": "Feature",
  "properties": {
    "iso:country":"GB",
    "wof:name":"HA7 4QR",
    "wof:placetype":"postalcode"
},
  "geometry": {"coordinates":[-0.29102327689495,51.61850864924748],"type":"Point"}
}