{
  "type": "Feature",
  "properties": {
    "iso:country":"GB",
    "wof:name":"EX34 8HG",
    "wof:placetype":"postalcode"
},
  "geometry": {"coordinates":[-4.12433683730759,51.20393960504511],"type":"Point"}
}