{
  "type": "Feature",
  "properties": {
    "date:inception_lower": "2018-08-01",
    "date:inception_upper": "2018-08-01",
    "iso:country": "GB",
    "wof:name": "CV47 2UY",
    "wof:placetype": "postalcode"
  },
  "geometry": {"coordinates":[-1.426561,52.169682],"type":"Point"}
}
