{
  "type": "Feature",
  "properties": {
    "iso:country":"GB",
    "wof:name":"CW4 8AU",
    "wof:placetype":"postalcode"
},
  "geometry": {"coordinates":[-2.34055382963803,53.18916226173702],"type":"Point"}
}