{
  "type": "Feature",
  "properties": {
    "iso:country": "GB",
    "wof:name": "CW4 8AU",
    "wof:placetype": "postalcode"
  },
  "geometry": {"coordinates":[-2.340554,53.189162],"type":"Point"}
}
