{
  "type": "Feature",
  "properties": {
    "iso:country":"GB",
    "wof:name":"GU29 0BX",
    "wof:placetype":"postalcode"
},
  "geometry": {"coordinates":[-0.69673704316458,50.97807660407656],"type":"Point"}
}