{
  "type": "Feature",
  "properties": {
    "iso:country":"GB",
    "wof:name":"SE15 1PQ",
    "wof:placetype":"postalcode"
},
  "geometry": {"coordinates":[-0.0513482330005,51.48244020800701],"type":"Point"}
}