{
  "type": "Feature",
  "properties": {
    "iso:country":"GB",
    "wof:name":"EC2Y 9NY",
    "wof:placetype":"postalcode"
},
  "geometry": {"coordinates":[-0.08965706952431,51.51934667539604],"type":"Point"}
}