{
  "type": "Feature",
  "properties": {
    "iso:country": "GB",
    "wof:name": "ST4 8JN",
    "wof:placetype": "postalcode"
  },
  "geometry": {"coordinates":[-2.19604,52.968555],"type":"Point"}
}
