{
  "type": "Feature",
  "properties": {
    "iso:country":"GB",
    "wof:name":"ST4 8JN",
    "wof:placetype":"postalcode"
},
  "geometry": {"coordinates":[-2.19603954563911,52.96855490474778],"type":"Point"}
}