{
  "type": "Feature",
  "properties": {
    "iso:country":"GB",
    "wof:name":"CM7 5BX",
    "wof:placetype":"postalcode"
},
  "geometry": {"coordinates":[0.55217362463749,51.90061442765243],"type":"Point"}
}