{
  "type": "Feature",
  "properties": {
    "date:inception_lower": "2010-03-01",
    "date:inception_upper": "2010-03-01",
    "iso:country": "GB",
    "wof:name": "CM7 5BX",
    "wof:placetype": "postalcode"
  },
  "geometry": {"coordinates":[0.552174,51.900614],"type":"Point"}
}
