{
  "type": "Feature",
  "properties": {
    "iso:country":"GB",
    "wof:name":"LE15 8DG",
    "wof:placetype":"postalcode"
},
  "geometry": {"coordinates":[-0.75119552867705,52.6467355861838],"type":"Point"}
}