{
  "type": "Feature",
  "properties": {
    "iso:country": "GB",
    "wof:name": "LE15 8DG",
    "wof:placetype": "postalcode"
  },
  "geometry": {"coordinates":[-0.751195,52.646736],"type":"Point"}
}
