{
  "type": "Feature",
  "properties": {
    "iso:country": "GB",
    "wof:name": "DN11 8EF",
    "wof:placetype": "postalcode"
  },
  "geometry": {"coordinates":[-1.054187,53.421105],"type":"Point"}
}
