{
  "type": "Feature",
  "properties": {
    "date:inception_lower": "1980-01-01",
    "date:inception_upper": "1980-01-01",
    "iso:country": "GB",
    "wof:name": "S8 9TZ",
    "wof:placetype": "postalcode"
  },
  "geometry": {"coordinates":[-1.470671,53.360657],"type":"Point"}
}
