{
  "type": "Feature",
  "properties": {
    "iso:country":"GB",
    "wof:name":"S8 9TZ",
    "wof:placetype":"postalcode"
},
  "geometry": {"coordinates":[-1.47065671576193,53.36062957705312],"type":"Point"}
}