{
  "type": "Feature",
  "properties": {
    "iso:country": "GB",
    "wof:name": "L14 3LZ",
    "wof:placetype": "postalcode"
  },
  "geometry": {"coordinates":[-2.899842,53.408431],"type":"Point"}
}
