{
  "type": "Feature",
  "properties": {
    "iso:country":"GB",
    "wof:name":"EH55 8HZ",
    "wof:placetype":"postalcode"
},
  "geometry": {"coordinates":[-3.62461167752283,55.84163329308613],"type":"Point"}
}