{
  "type": "Feature",
  "properties": {
    "iso:country": "GB",
    "wof:name": "PO16 7NN",
    "wof:placetype": "postalcode"
  },
  "geometry": {"coordinates":[-1.189042,50.855349],"type":"Point"}
}
