{
  "type": "Feature",
  "properties": {
    "date:inception_lower": "1980-01-01",
    "date:inception_upper": "1980-01-01",
    "iso:country": "GB",
    "wof:name": "NE39 2ET",
    "wof:placetype": "postalcode"
  },
  "geometry": {"coordinates":[-1.782376,54.937895],"type":"Point"}
}
