{
  "type": "Feature",
  "properties": {
    "iso:country": "GB",
    "wof:name": "NE39 2ET",
    "wof:placetype": "postalcode"
  },
  "geometry": {"coordinates":[-1.782376,54.937895],"type":"Point"}
}
