{
  "type": "Feature",
  "properties": {
    "date:inception_lower":"1980-01-01",
    "date:inception_upper":"1980-01-31",
    "iso:country":"GB",
    "wof:name":"CA12 5XP",
    "wof:placetype":"postalcode"
},
  "geometry": {"coordinates":[-3.168514,54.513784],"type":"Point"}
}