{
  "type": "Feature",
  "properties": {
    "iso:country":"GB",
    "wof:name":"CA12 5XP",
    "wof:placetype":"postalcode"
},
  "geometry": {"coordinates":[-3.16851454223159,54.51378438901682],"type":"Point"}
}