{
  "type": "Feature",
  "properties": {
    "iso:country":"GB",
    "wof:name":"BL4 0AB",
    "wof:placetype":"postalcode"
},
  "geometry": {"coordinates":[-2.4103827830733,53.54837203632776],"type":"Point"}
}