{
  "type": "Feature",
  "properties": {
    "iso:country": "GB",
    "wof:name": "GU29 0BE",
    "wof:placetype": "postalcode"
  },
  "geometry": {"coordinates":[-0.717377,50.999834],"type":"Point"}
}
