{
  "type": "Feature",
  "properties": {
    "iso:country":"GB",
    "wof:name":"GU29 0BE",
    "wof:placetype":"postalcode"
},
  "geometry": {"coordinates":[-0.71737659476608,50.99983359713583],"type":"Point"}
}