{
  "type": "Feature",
  "properties": {
    "iso:country":"GB",
    "wof:name":"N17 6ND",
    "wof:placetype":"postalcode"
},
  "geometry": {"coordinates":[-0.08024553419189,51.59401075436013],"type":"Point"}
}