{
  "type": "Feature",
  "properties": {
    "iso:country":"GB",
    "wof:name":"SK4 3QR",
    "wof:placetype":"postalcode"
},
  "geometry": {"coordinates":[-2.20210874208166,53.40917127959735],"type":"Point"}
}