{
  "type": "Feature",
  "properties": {
    "date:inception_lower":"2007-10-01",
    "date:inception_upper":"2007-10-31",
    "iso:country":"GB",
    "wof:name":"SK4 3QR",
    "wof:placetype":"postalcode"
},
  "geometry": {"coordinates":[-2.202109,53.409171],"type":"Point"}
}