{
  "type": "Feature",
  "properties": {
    "date:inception_lower": "1980-01-01",
    "date:inception_upper": "1980-01-01",
    "iso:country": "GB",
    "wof:name": "LL11 5YE",
    "wof:placetype": "postalcode"
  },
  "geometry": {"coordinates":[-3.093796,53.073499],"type":"Point"}
}
