{
  "type": "Feature",
  "properties": {
    "iso:country":"GB",
    "wof:name":"LL11 5YE",
    "wof:placetype":"postalcode"
},
  "geometry": {"coordinates":[-3.09379595975476,53.07349909412376],"type":"Point"}
}