{
  "type": "Feature",
  "properties": {
    "date:inception_lower": "1991-01-01",
    "date:inception_upper": "1991-01-01",
    "iso:country": "GB",
    "wof:name": "W3 6TB",
    "wof:placetype": "postalcode"
  },
  "geometry": {"coordinates":[-0.260316,51.520527],"type":"Point"}
}
