{
  "type": "Feature",
  "properties": {
    "iso:country":"GB",
    "wof:name":"W3 6TB",
    "wof:placetype":"postalcode"
},
  "geometry": {"coordinates":[-0.26031592098055,51.52052718575101],"type":"Point"}
}