{
  "type": "Feature",
  "properties": {
    "date:inception_lower": "1987-04-01",
    "date:inception_upper": "1987-04-01",
    "iso:country": "GB",
    "wof:name": "PO7 6UW",
    "wof:placetype": "postalcode"
  },
  "geometry": {"coordinates":[-1.065157,50.897273],"type":"Point"}
}
