{
  "type": "Feature",
  "properties": {
    "iso:country":"GB",
    "wof:name":"PO7 6UW",
    "wof:placetype":"postalcode"
},
  "geometry": {"coordinates":[-1.06515729409325,50.89727296589007],"type":"Point"}
}