{
  "type": "Feature",
  "properties": {
    "date:inception_lower": "1994-12-01",
    "date:inception_upper": "1994-12-01",
    "iso:country": "GB",
    "wof:name": "NN15 6YA",
    "wof:placetype": "postalcode"
  },
  "geometry": {"coordinates":[-0.718115,52.374767],"type":"Point"}
}
