{
  "type": "Feature",
  "properties": {
    "iso:country":"GB",
    "wof:name":"UB6 8LA",
    "wof:placetype":"postalcode"
},
  "geometry": {"coordinates":[-0.32695228468408,51.53664850815527],"type":"Point"}
}