{
  "type": "Feature",
  "properties": {
    "iso:country":"GB",
    "wof:name":"LL12 9LR",
    "wof:placetype":"postalcode"
},
  "geometry": {"coordinates":[-3.04517413681534,53.11451451580076],"type":"Point"}
}