{
  "type": "Feature",
  "properties": {
    "iso:country": "GB",
    "wof:name": "DL1 3PP",
    "wof:placetype": "postalcode"
  },
  "geometry": {"coordinates":[-1.524559,54.547268],"type":"Point"}
}
