{
  "type": "Feature",
  "properties": {
    "date:inception_lower": "1980-01-01",
    "date:inception_upper": "1980-01-01",
    "iso:country": "GB",
    "wof:name": "DL1 3PP",
    "wof:placetype": "postalcode"
  },
  "geometry": {"coordinates":[-1.524559,54.547268],"type":"Point"}
}
