{
  "type": "Feature",
  "properties": {
    "date:inception_lower": "2021-07-01",
    "date:inception_upper": "2021-07-01",
    "iso:country": "GB",
    "wof:name": "G53 7RD",
    "wof:placetype": "postalcode"
  },
  "geometry": {"coordinates":[-4.337872,55.800505],"type":"Point"}
}
