{
  "type": "Feature",
  "properties": {
    "iso:country":"GB",
    "wof:name":"NG19 7EU",
    "wof:placetype":"postalcode"
},
  "geometry": {"coordinates":[-1.21385095967558,53.15664758625735],"type":"Point"}
}