{
  "type": "Feature",
  "properties": {
    "iso:country": "GB",
    "wof:name": "CT7 0BW",
    "wof:placetype": "postalcode"
  },
  "geometry": {"coordinates":[1.311692,51.372035],"type":"Point"}
}
