{
  "type": "Feature",
  "properties": {
    "iso:country":"GB",
    "wof:name":"M32 8NZ",
    "wof:placetype":"postalcode"
},
  "geometry": {"coordinates":[-2.29757406956138,53.44825131096355],"type":"Point"}
}