{
  "type": "Feature",
  "properties": {
    "iso:country": "GB",
    "wof:name": "M32 8NZ",
    "wof:placetype": "postalcode"
  },
  "geometry": {"coordinates":[-2.297574,53.448251],"type":"Point"}
}
