{
  "type": "Feature",
  "properties": {
    "iso:country":"GB",
    "wof:name":"S63 6LH",
    "wof:placetype":"postalcode"
},
  "geometry": {"coordinates":[-1.35177730246461,53.49474780884978],"type":"Point"}
}