{
  "type": "Feature",
  "properties": {
    "iso:country":"GB",
    "wof:name":"OX1 5RY",
    "wof:placetype":"postalcode"
},
  "geometry": {"coordinates":[-1.24546318756025,51.7102701643272],"type":"Point"}
}