{
  "type": "Feature",
  "properties": {
    "iso:country": "GB",
    "wof:name": "OX1 5RY",
    "wof:placetype": "postalcode"
  },
  "geometry": {"coordinates":[-1.245463,51.71027],"type":"Point"}
}
