{
  "type": "Feature",
  "properties": {
    "iso:country":"GB",
    "wof:name":"EX7 9AJ",
    "wof:placetype":"postalcode"
},
  "geometry": {"coordinates":[-3.47514271187382,50.58154930897138],"type":"Point"}
}