{
  "type": "Feature",
  "properties": {
    "iso:country": "GB",
    "wof:name": "BS30 9AQ",
    "wof:placetype": "postalcode"
  },
  "geometry": {"coordinates":[-2.494075,51.435273],"type":"Point"}
}
