{
  "type": "Feature",
  "properties": {
    "date:inception_lower":"1980-01-01",
    "date:inception_upper":"1980-01-31",
    "iso:country":"GB",
    "wof:name":"CM4 9JA",
    "wof:placetype":"postalcode"
},
  "geometry": {"coordinates":[0.417807,51.689737],"type":"Point"}
}