{
  "type": "Feature",
  "properties": {
    "iso:country": "GB",
    "wof:name": "PA3 3BW",
    "wof:placetype": "postalcode"
  },
  "geometry": {"coordinates":[-4.480668,55.840673],"type":"Point"}
}
