{
  "type": "Feature",
  "properties": {
    "date:inception_lower": "1997-06-01",
    "date:inception_upper": "1997-06-01",
    "iso:country": "GB",
    "wof:name": "PA3 3BW",
    "wof:placetype": "postalcode"
  },
  "geometry": {"coordinates":[-4.480668,55.840673],"type":"Point"}
}
