{
  "type": "Feature",
  "properties": {
    "iso:country":"GB",
    "wof:name":"PA3 3BW",
    "wof:placetype":"postalcode"
},
  "geometry": {"coordinates":[-4.48066773886895,55.84067344146569],"type":"Point"}
}