{
  "type": "Feature",
  "properties": {
    "iso:country":"GB",
    "wof:name":"WR12 7NE",
    "wof:placetype":"postalcode"
},
  "geometry": {"coordinates":[-1.89960859361709,52.00625566271511],"type":"Point"}
}