{
  "type": "Feature",
  "properties": {
    "date:inception_lower": "1980-01-01",
    "date:inception_upper": "1980-01-01",
    "iso:country": "GB",
    "wof:name": "WR12 7NE",
    "wof:placetype": "postalcode"
  },
  "geometry": {"coordinates":[-1.899934,52.006346],"type":"Point"}
}
