{
  "type": "Feature",
  "properties": {
    "iso:country": "GB",
    "wof:name": "ST1 4BA",
    "wof:placetype": "postalcode"
  },
  "geometry": {"coordinates":[-2.188306,53.021855],"type":"Point"}
}
