{
  "type": "Feature",
  "properties": {
    "date:inception_lower":"1980-01-01",
    "date:inception_upper":"1980-01-31",
    "iso:country":"GB",
    "wof:name":"ST1 4BA",
    "wof:placetype":"postalcode"
},
  "geometry": {"coordinates":[-2.188306,53.021855],"type":"Point"}
}