{
  "type": "Feature",
  "properties": {
    "date:inception_lower":"1991-01-01",
    "date:inception_upper":"1991-01-31",
    "iso:country":"GB",
    "wof:name":"S81 8TG",
    "wof:placetype":"postalcode"
},
  "geometry": {"coordinates":[-1.145427,53.326205],"type":"Point"}
}