{
  "type": "Feature",
  "properties": {
    "date:inception_lower":"1990-02-01",
    "date:inception_upper":"1990-02-28",
    "iso:country":"GB",
    "wof:name":"NN14 3HS",
    "wof:placetype":"postalcode"
},
  "geometry": {"coordinates":[-0.599466,52.454539],"type":"Point"}
}