{
  "type": "Feature",
  "properties": {
    "date:inception_lower": "1980-01-01",
    "date:inception_upper": "1980-01-01",
    "iso:country": "GB",
    "wof:name": "WR3 8SZ",
    "wof:placetype": "postalcode"
  },
  "geometry": {"coordinates":[-2.158975,52.228171],"type":"Point"}
}
