{
  "type": "Feature",
  "properties": {
    "iso:country":"GB",
    "wof:name":"WR3 8SZ",
    "wof:placetype":"postalcode"
},
  "geometry": {"coordinates":[-2.15903972559922,52.22800467334633],"type":"Point"}
}