{
  "type": "Feature",
  "properties": {
    "date:inception_lower": "1992-08-01",
    "date:inception_upper": "1992-08-01",
    "iso:country": "GB",
    "wof:name": "B60 2RE",
    "wof:placetype": "postalcode"
  },
  "geometry": {"coordinates":[-2.045668,52.332498],"type":"Point"}
}
