{
  "type": "Feature",
  "properties": {
    "iso:country":"GB",
    "wof:name":"BL2 5RB",
    "wof:placetype":"postalcode"
},
  "geometry": {"coordinates":[-2.35825999935406,53.58840298426676],"type":"Point"}
}