{
  "type": "Feature",
  "properties": {
    "iso:country": "GB",
    "wof:name": "BL2 5RB",
    "wof:placetype": "postalcode"
  },
  "geometry": {"coordinates":[-2.35826,53.588403],"type":"Point"}
}
