{
  "type": "Feature",
  "properties": {
    "iso:country":"GB",
    "wof:name":"WS12 4DU",
    "wof:placetype":"postalcode"
},
  "geometry": {"coordinates":[-1.99319131377294,52.72212856945534],"type":"Point"}
}