{
  "type": "Feature",
  "properties": {
    "date:inception_lower": "1980-01-01",
    "date:inception_upper": "1980-01-01",
    "iso:country": "GB",
    "wof:name": "WS12 4DU",
    "wof:placetype": "postalcode"
  },
  "geometry": {"coordinates":[-1.993394,52.722064],"type":"Point"}
}
