{
  "type": "Feature",
  "properties": {
    "date:inception_lower": "1980-01-01",
    "date:inception_upper": "1980-01-01",
    "iso:country": "GB",
    "wof:name": "CO15 3RQ",
    "wof:placetype": "postalcode"
  },
  "geometry": {"coordinates":[1.15323,51.80202],"type":"Point"}
}
