{
  "type": "Feature",
  "properties": {
    "iso:country": "GB",
    "wof:name": "CF83 8GF",
    "wof:placetype": "postalcode"
  },
  "geometry": {"coordinates":[-3.203324,51.59059],"type":"Point"}
}
