{
  "type": "Feature",
  "properties": {
    "iso:country":"GB",
    "wof:name":"CF83 8GF",
    "wof:placetype":"postalcode"
},
  "geometry": {"coordinates":[-3.20332958755785,51.59064153943347],"type":"Point"}
}