{
  "type": "Feature",
  "properties": {
    "iso:country":"GB",
    "wof:name":"TR10 8DL",
    "wof:placetype":"postalcode"
},
  "geometry": {"coordinates":[-5.10908657625494,50.172226887074],"type":"Point"}
}