{
  "type": "Feature",
  "properties": {
    "iso:country": "GB",
    "wof:name": "IP6 0BZ",
    "wof:placetype": "postalcode"
  },
  "geometry": {"coordinates":[1.110365,52.102245],"type":"Point"}
}
