{
  "type": "Feature",
  "properties": {
    "iso:country": "GB",
    "wof:name": "LU7 9GY",
    "wof:placetype": "postalcode"
  },
  "geometry": {"coordinates":[-0.641201,51.824543],"type":"Point"}
}
