{
  "type": "Feature",
  "properties": {
    "iso:country":"GB",
    "wof:name":"LU7 9GY",
    "wof:placetype":"postalcode"
},
  "geometry": {"coordinates":[-0.64101293325862,51.82452251246892],"type":"Point"}
}