{
  "type": "Feature",
  "properties": {
    "iso:country":"GB",
    "wof:name":"ME1 2HD",
    "wof:placetype":"postalcode"
},
  "geometry": {"coordinates":[0.50370963520501,51.38075101065547],"type":"Point"}
}