{
  "type": "Feature",
  "properties": {
    "date:inception_lower":"1986-07-01",
    "date:inception_upper":"1986-07-31",
    "iso:country":"GB",
    "wof:name":"LE9 6NE",
    "wof:placetype":"postalcode"
},
  "geometry": {"coordinates":[-1.218289,52.528311],"type":"Point"}
}