{
  "type": "Feature",
  "properties": {
    "iso:country": "GB",
    "wof:name": "LE9 6NE",
    "wof:placetype": "postalcode"
  },
  "geometry": {"coordinates":[-1.218289,52.528311],"type":"Point"}
}
