{
  "type": "Feature",
  "properties": {
    "iso:country":"GB",
    "wof:name":"LE9 6NE",
    "wof:placetype":"postalcode"
},
  "geometry": {"coordinates":[-1.21828951695945,52.52831066258099],"type":"Point"}
}