{
  "type": "Feature",
  "properties": {
    "iso:country": "GB",
    "wof:name": "S71 3TD",
    "wof:placetype": "postalcode"
  },
  "geometry": {"coordinates":[-1.46816,53.578007],"type":"Point"}
}
