{
  "type": "Feature",
  "properties": {
    "iso:country":"GB",
    "wof:name":"GL54 5TB",
    "wof:placetype":"postalcode"
},
  "geometry": {"coordinates":[-1.92459514832188,51.90047090022467],"type":"Point"}
}