{
  "type": "Feature",
  "properties": {
    "iso:country": "GB",
    "wof:name": "TQ3 2SJ",
    "wof:placetype": "postalcode"
  },
  "geometry": {"coordinates":[-3.570708,50.438986],"type":"Point"}
}
