{
  "type": "Feature",
  "properties": {
    "iso:country":"GB",
    "wof:name":"TQ3 2SJ",
    "wof:placetype":"postalcode"
},
  "geometry": {"coordinates":[-3.57056616417634,50.43902018515097],"type":"Point"}
}