{
  "type": "Feature",
  "properties": {
    "iso:country":"GB",
    "wof:name":"M32 8BB",
    "wof:placetype":"postalcode"
},
  "geometry": {"coordinates":[-2.31286235502086,53.44696281619743],"type":"Point"}
}