{
  "type": "Feature",
  "properties": {
    "iso:country": "GB",
    "wof:name": "M32 8BB",
    "wof:placetype": "postalcode"
  },
  "geometry": {"coordinates":[-2.312862,53.446963],"type":"Point"}
}
