{
  "type": "Feature",
  "properties": {
    "date:inception_lower": "1980-01-01",
    "date:inception_upper": "1980-01-01",
    "iso:country": "GB",
    "wof:name": "LL63 5SN",
    "wof:placetype": "postalcode"
  },
  "geometry": {"coordinates":[-4.484368,53.228029],"type":"Point"}
}
