{
  "type": "Feature",
  "properties": {
    "iso:country":"GB",
    "wof:name":"DL8 1JX",
    "wof:placetype":"postalcode"
},
  "geometry": {"coordinates":[-1.65890150903149,54.32821942438777],"type":"Point"}
}