{
  "type": "Feature",
  "properties": {
    "date:inception_lower": "1980-01-01",
    "date:inception_upper": "1980-01-01",
    "iso:country": "GB",
    "wof:name": "DL8 1JX",
    "wof:placetype": "postalcode"
  },
  "geometry": {"coordinates":[-1.658939,54.32824],"type":"Point"}
}
