{
  "type": "Feature",
  "properties": {
    "iso:country": "GB",
    "wof:name": "SL6 7UR",
    "wof:placetype": "postalcode"
  },
  "geometry": {"coordinates":[-0.73014,51.540455],"type":"Point"}
}
