{
  "type": "Feature",
  "properties": {
    "iso:country": "GB",
    "wof:name": "LD3 9EA",
    "wof:placetype": "postalcode"
  },
  "geometry": {"coordinates":[-3.393722,51.953336],"type":"Point"}
}
