{
  "type": "Feature",
  "properties": {
    "iso:country":"GB",
    "wof:name":"LD3 9EA",
    "wof:placetype":"postalcode"
},
  "geometry": {"coordinates":[-3.39372241370811,51.95333555705642],"type":"Point"}
}