{
  "type": "Feature",
  "properties": {
    "date:inception_lower":"1994-05-01",
    "date:inception_upper":"1994-05-31",
    "iso:country":"GB",
    "wof:name":"SA44 4BL",
    "wof:placetype":"postalcode"
},
  "geometry": {"coordinates":[-4.311126,52.040573],"type":"Point"}
}