{
  "type": "Feature",
  "properties": {
    "iso:country": "GB",
    "wof:name": "SA44 4BL",
    "wof:placetype": "postalcode"
  },
  "geometry": {"coordinates":[-4.311126,52.040573],"type":"Point"}
}
