{
  "type": "Feature",
  "properties": {
    "date:inception_lower": "1980-01-01",
    "date:inception_upper": "1980-01-01",
    "iso:country": "GB",
    "wof:name": "MK18 2DW",
    "wof:placetype": "postalcode"
  },
  "geometry": {"coordinates":[-0.916198,51.994124],"type":"Point"}
}
