{
  "type": "Feature",
  "properties": {
    "iso:country": "GB",
    "wof:name": "ME14 3DU",
    "wof:placetype": "postalcode"
  },
  "geometry": {"coordinates":[0.541817,51.302783],"type":"Point"}
}
