{
  "type": "Feature",
  "properties": {
    "date:inception_lower": "2017-12-01",
    "date:inception_upper": "2017-12-01",
    "iso:country": "GB",
    "wof:name": "S2 3BY",
    "wof:placetype": "postalcode"
  },
  "geometry": {"coordinates":[-1.452514,53.366948],"type":"Point"}
}
