{
  "type": "Feature",
  "properties": {
    "date:inception_lower": "1980-01-01",
    "date:inception_upper": "1980-01-01",
    "iso:country": "GB",
    "wof:name": "TW20 8UF",
    "wof:placetype": "postalcode"
  },
  "geometry": {"coordinates":[-0.533595,51.409863],"type":"Point"}
}
