{
  "type": "Feature",
  "properties": {
    "iso:country":"GB",
    "wof:name":"TW20 8UF",
    "wof:placetype":"postalcode"
},
  "geometry": {"coordinates":[-0.53359466094844,51.40986314085398],"type":"Point"}
}