{
  "type": "Feature",
  "properties": {
    "date:inception_lower": "1980-01-01",
    "date:inception_upper": "1980-01-01",
    "iso:country": "GB",
    "wof:name": "CO10 7LR",
    "wof:placetype": "postalcode"
  },
  "geometry": {"coordinates":[0.725972,52.01672],"type":"Point"}
}
