{
  "type": "Feature",
  "properties": {
    "iso:country":"GB",
    "wof:name":"CO10 7LR",
    "wof:placetype":"postalcode"
},
  "geometry": {"coordinates":[0.72597174320006,52.01672027766097],"type":"Point"}
}