{
  "type": "Feature",
  "properties": {
    "iso:country":"GB",
    "wof:name":"TN12 9JQ",
    "wof:placetype":"postalcode"
},
  "geometry": {"coordinates":[0.48827456492996,51.17302093134752],"type":"Point"}
}