{
  "type": "Feature",
  "properties": {
    "iso:country": "GB",
    "wof:name": "TN12 9JQ",
    "wof:placetype": "postalcode"
  },
  "geometry": {"coordinates":[0.488304,51.17302],"type":"Point"}
}
