{
  "type": "Feature",
  "properties": {
    "iso:country":"GB",
    "wof:name":"BN2 5FE",
    "wof:placetype":"postalcode"
},
  "geometry": {"coordinates":[-0.10812927793164,50.82357772505139],"type":"Point"}
}