{
  "type": "Feature",
  "properties": {
    "iso:country":"GB",
    "wof:name":"B24 0UE",
    "wof:placetype":"postalcode"
},
  "geometry": {"coordinates":[-1.81605158217428,52.52254883911328],"type":"Point"}
}