{
  "type": "Feature",
  "properties": {
    "iso:country":"GB",
    "wof:name":"S43 1NG",
    "wof:placetype":"postalcode"
},
  "geometry": {"coordinates":[-1.39334029792341,53.25521823536545],"type":"Point"}
}