{
  "type": "Feature",
  "properties": {
    "iso:country": "GB",
    "wof:name": "AL8 6XF",
    "wof:placetype": "postalcode"
  },
  "geometry": {"coordinates":[-0.217249,51.787192],"type":"Point"}
}
