{
  "type": "Feature",
  "properties": {
    "iso:country": "GB",
    "wof:name": "NN6 0LL",
    "wof:placetype": "postalcode"
  },
  "geometry": {"coordinates":[-0.748847,52.269144],"type":"Point"}
}
