{
  "type": "Feature",
  "properties": {
    "date:inception_lower": "1980-01-01",
    "date:inception_upper": "1980-01-01",
    "iso:country": "GB",
    "wof:name": "DN22 8AJ",
    "wof:placetype": "postalcode"
  },
  "geometry": {"coordinates":[-0.970273,53.273009],"type":"Point"}
}
