{
  "type": "Feature",
  "properties": {
    "iso:country": "GB",
    "wof:name": "DN22 8AJ",
    "wof:placetype": "postalcode"
  },
  "geometry": {"coordinates":[-0.970273,53.273009],"type":"Point"}
}
