{
  "type": "Feature",
  "properties": {
    "iso:country":"GB",
    "wof:name":"DN22 8AJ",
    "wof:placetype":"postalcode"
},
  "geometry": {"coordinates":[-0.9702729742353,53.2730088411707],"type":"Point"}
}