{
  "type": "Feature",
  "properties": {
    "iso:country": "GB",
    "wof:name": "DL10 4EE",
    "wof:placetype": "postalcode"
  },
  "geometry": {"coordinates":[-1.743415,54.404064],"type":"Point"}
}
