{
  "type": "Feature",
  "properties": {
    "iso:country":"GB",
    "wof:name":"DL10 4EE",
    "wof:placetype":"postalcode"
},
  "geometry": {"coordinates":[-1.74341537307267,54.40406422100224],"type":"Point"}
}