{
  "type": "Feature",
  "properties": {
    "date:inception_lower": "2019-10-01",
    "date:inception_upper": "2019-10-01",
    "iso:country": "GB",
    "wof:name": "CV47 2EP",
    "wof:placetype": "postalcode"
  },
  "geometry": {"coordinates":[-1.390721,52.244799],"type":"Point"}
}
