{
  "type": "Feature",
  "properties": {
    "iso:country":"GB",
    "wof:name":"DT3 4NW",
    "wof:placetype":"postalcode"
},
  "geometry": {"coordinates":[-2.50037749970415,50.62529502283719],"type":"Point"}
}