{
  "type": "Feature",
  "properties": {
    "iso:country": "GB",
    "wof:name": "DT3 4NW",
    "wof:placetype": "postalcode"
  },
  "geometry": {"coordinates":[-2.500377,50.625295],"type":"Point"}
}
