{
  "type": "Feature",
  "properties": {
    "date:inception_lower":"1997-12-01",
    "date:inception_upper":"1997-12-31",
    "iso:country":"GB",
    "wof:name":"DT3 4NW",
    "wof:placetype":"postalcode"
},
  "geometry": {"coordinates":[-2.500377,50.625295],"type":"Point"}
}