{
  "type": "Feature",
  "properties": {
    "iso:country":"GB",
    "wof:name":"M50 3ZP",
    "wof:placetype":"postalcode"
},
  "geometry": {"coordinates":[-2.28432035688412,53.47472777054131],"type":"Point"}
}