{
  "type": "Feature",
  "properties": {
    "iso:country":"GB",
    "wof:name":"NE46 2DU",
    "wof:placetype":"postalcode"
},
  "geometry": {"coordinates":[-2.11315644291161,54.96453646404797],"type":"Point"}
}