{
  "type": "Feature",
  "properties": {
    "date:inception_lower": "1994-05-01",
    "date:inception_upper": "1994-05-01",
    "iso:country": "GB",
    "wof:name": "M5 4HJ",
    "wof:placetype": "postalcode"
  },
  "geometry": {"coordinates":[-2.282783,53.481428],"type":"Point"}
}
