{
  "type": "Feature",
  "properties": {
    "iso:country":"GB",
    "wof:name":"M5 4HJ",
    "wof:placetype":"postalcode"
},
  "geometry": {"coordinates":[-2.28278298949694,53.48142783204816],"type":"Point"}
}