{
  "type": "Feature",
  "properties": {
    "iso:country":"GB",
    "wof:name":"SW3 1LR",
    "wof:placetype":"postalcode"
},
  "geometry": {"coordinates":[-0.16454018845657,51.49705400405802],"type":"Point"}
}