{
  "type": "Feature",
  "properties": {
    "date:inception_lower": "1980-01-01",
    "date:inception_upper": "1980-01-01",
    "iso:country": "GB",
    "wof:name": "SW3 1LR",
    "wof:placetype": "postalcode"
  },
  "geometry": {"coordinates":[-0.16454,51.497054],"type":"Point"}
}
