{
  "type": "Feature",
  "properties": {
    "iso:country":"GB",
    "wof:name":"SA13 1TH",
    "wof:placetype":"postalcode"
},
  "geometry": {"coordinates":[-3.77054618004296,51.58656484106695],"type":"Point"}
}