{
  "type": "Feature",
  "properties": {
    "iso:country":"GB",
    "wof:name":"NR25 6BJ",
    "wof:placetype":"postalcode"
},
  "geometry": {"coordinates":[1.08590189120697,52.90591105927719],"type":"Point"}
}