{
  "type": "Feature",
  "properties": {
    "date:inception_lower": "2019-02-01",
    "date:inception_upper": "2019-02-01",
    "iso:country": "GB",
    "wof:name": "HG1 9YA",
    "wof:placetype": "postalcode"
  },
  "geometry": {"coordinates":[-1.522392,54.002442],"type":"Point"}
}
