{
  "type": "Feature",
  "properties": {
    "iso:country":"GB",
    "wof:name":"CA3 9LN",
    "wof:placetype":"postalcode"
},
  "geometry": {"coordinates":[-2.94437130400204,54.90802509218818],"type":"Point"}
}