{
  "type": "Feature",
  "properties": {
    "date:inception_lower": "1995-07-01",
    "date:inception_upper": "1995-07-01",
    "iso:country": "GB",
    "wof:name": "CM1 6JZ",
    "wof:placetype": "postalcode"
  },
  "geometry": {"coordinates":[0.497647,51.74644],"type":"Point"}
}
