{
  "type": "Feature",
  "properties": {
    "iso:country": "GB",
    "wof:name": "CM1 6JZ",
    "wof:placetype": "postalcode"
  },
  "geometry": {"coordinates":[0.497647,51.74644],"type":"Point"}
}
