{
  "type": "Feature",
  "properties": {
    "date:inception_lower": "1980-01-01",
    "date:inception_upper": "1980-01-01",
    "iso:country": "GB",
    "wof:name": "SY17 5PT",
    "wof:placetype": "postalcode"
  },
  "geometry": {"coordinates":[-3.520119,52.501198],"type":"Point"}
}
