{
  "type": "Feature",
  "properties": {
    "iso:country":"GB",
    "wof:name":"SY17 5PT",
    "wof:placetype":"postalcode"
},
  "geometry": {"coordinates":[-3.52067310379188,52.501212102994],"type":"Point"}
}