{
  "type": "Feature",
  "properties": {
    "iso:country": "GB",
    "wof:name": "SY17 5PT",
    "wof:placetype": "postalcode"
  },
  "geometry": {"coordinates":[-3.520673,52.501212],"type":"Point"}
}
