{
  "type": "Feature",
  "properties": {
    "iso:country":"GB",
    "wof:name":"BD4 8QQ",
    "wof:placetype":"postalcode"
},
  "geometry": {"coordinates":[-1.72063164174562,53.78450243559928],"type":"Point"}
}