{
  "type": "Feature",
  "properties": {
    "iso:country":"GB",
    "wof:name":"NE8 2SB",
    "wof:placetype":"postalcode"
},
  "geometry": {"coordinates":[-1.6235079451945,54.95381697101981],"type":"Point"}
}