{
  "type": "Feature",
  "properties": {
    "iso:country":"GB",
    "wof:name":"IP33 2NY",
    "wof:placetype":"postalcode"
},
  "geometry": {"coordinates":[0.72358749225916,52.22903724301682],"type":"Point"}
}