{
  "type": "Feature",
  "properties": {
    "iso:country":"GB",
    "wof:name":"KT6 7HJ",
    "wof:placetype":"postalcode"
},
  "geometry": {"coordinates":[-0.28477361019684,51.38197223019831],"type":"Point"}
}