{
  "type": "Feature",
  "properties": {
    "iso:country": "GB",
    "wof:name": "BR5 3PS",
    "wof:placetype": "postalcode"
  },
  "geometry": {"coordinates":[0.124556,51.392621],"type":"Point"}
}
