{
  "type": "Feature",
  "properties": {
    "iso:country":"GB",
    "wof:name":"BR5 3PS",
    "wof:placetype":"postalcode"
},
  "geometry": {"coordinates":[0.12455596960792,51.39262089906635],"type":"Point"}
}