{
  "type": "Feature",
  "properties": {
    "date:inception_lower": "1984-10-01",
    "date:inception_upper": "1984-10-01",
    "iso:country": "GB",
    "wof:name": "PR8 6XS",
    "wof:placetype": "postalcode"
  },
  "geometry": {"coordinates":[-2.975476,53.628817],"type":"Point"}
}
