{
  "type": "Feature",
  "properties": {
    "iso:country":"GB",
    "wof:name":"BN12 6LA",
    "wof:placetype":"postalcode"
},
  "geometry": {"coordinates":[-0.41379686387416,50.8263261955559],"type":"Point"}
}