{
  "type": "Feature",
  "properties": {
    "date:inception_lower":"1980-01-01",
    "date:inception_upper":"1980-01-31",
    "iso:country":"GB",
    "wof:name":"G2 3DX",
    "wof:placetype":"postalcode"
},
  "geometry": {"coordinates":[-4.260472,55.865544],"type":"Point"}
}