{
  "type": "Feature",
  "properties": {
    "iso:country": "GB",
    "wof:name": "AL3 5RJ",
    "wof:placetype": "postalcode"
  },
  "geometry": {"coordinates":[-0.339733,51.763997],"type":"Point"}
}
