{
  "type": "Feature",
  "properties": {
    "iso:country": "GB",
    "wof:name": "BB9 5JZ",
    "wof:placetype": "postalcode"
  },
  "geometry": {"coordinates":[-2.237305,53.820391],"type":"Point"}
}
