{
  "type": "Feature",
  "properties": {
    "iso:country": "GB",
    "wof:name": "PL7 1UN",
    "wof:placetype": "postalcode"
  },
  "geometry": {"coordinates":[-4.074958,50.384166],"type":"Point"}
}
