{
  "type": "Feature",
  "properties": {
    "iso:country": "GB",
    "wof:name": "GL10 3JB",
    "wof:placetype": "postalcode"
  },
  "geometry": {"coordinates":[-2.27445,51.730289],"type":"Point"}
}
