{
  "type": "Feature",
  "properties": {
    "iso:country":"GB",
    "wof:name":"M8 8UD",
    "wof:placetype":"postalcode"
},
  "geometry": {"coordinates":[-2.23203128715091,53.50060173016109],"type":"Point"}
}