{
  "type": "Feature",
  "properties": {
    "iso:country":"GB",
    "wof:name":"CT6 7JH",
    "wof:placetype":"postalcode"
},
  "geometry": {"coordinates":[1.13713811778556,51.35430449953774],"type":"Point"}
}