{
  "type": "Feature",
  "properties": {
    "date:inception_lower":"1980-01-01",
    "date:inception_upper":"1980-01-31",
    "iso:country":"GB",
    "wof:name":"CT6 7JH",
    "wof:placetype":"postalcode"
},
  "geometry": {"coordinates":[1.137138,51.354304],"type":"Point"}
}