{
  "type": "Feature",
  "properties": {
    "iso:country":"GB",
    "wof:name":"OX15 5QL",
    "wof:placetype":"postalcode"
},
  "geometry": {"coordinates":[-1.47811229577367,52.03087491041713],"type":"Point"}
}