{
  "type": "Feature",
  "properties": {
    "date:inception_lower": "1980-01-01",
    "date:inception_upper": "1980-01-01",
    "iso:country": "GB",
    "wof:name": "OX15 5QL",
    "wof:placetype": "postalcode"
  },
  "geometry": {"coordinates":[-1.478112,52.030875],"type":"Point"}
}
