{
  "type": "Feature",
  "properties": {
    "iso:country": "GB",
    "wof:name": "CO10 7EE",
    "wof:placetype": "postalcode"
  },
  "geometry": {"coordinates":[0.689086,52.016286],"type":"Point"}
}
