{
  "type": "Feature",
  "properties": {
    "date:inception_lower": "1980-01-01",
    "date:inception_upper": "1980-01-01",
    "iso:country": "GB",
    "wof:name": "PR9 8HF",
    "wof:placetype": "postalcode"
  },
  "geometry": {"coordinates":[-2.917932,53.680723],"type":"Point"}
}
