{
  "type": "Feature",
  "properties": {
    "iso:country":"GB",
    "wof:name":"PR9 8HF",
    "wof:placetype":"postalcode"
},
  "geometry": {"coordinates":[-2.91793194102678,53.68072255479365],"type":"Point"}
}