{
  "type": "Feature",
  "properties": {
    "date:inception_lower": "1980-01-01",
    "date:inception_upper": "1980-01-01",
    "iso:country": "GB",
    "wof:name": "HD5 9XP",
    "wof:placetype": "postalcode"
  },
  "geometry": {"coordinates":[-1.737438,53.645186],"type":"Point"}
}
