{
  "type": "Feature",
  "properties": {
    "iso:country":"GB",
    "wof:name":"HD5 9XP",
    "wof:placetype":"postalcode"
},
  "geometry": {"coordinates":[-1.73749622139688,53.64516190169788],"type":"Point"}
}