{
  "type": "Feature",
  "properties": {
    "date:inception_lower": "2018-09-01",
    "date:inception_upper": "2018-09-01",
    "iso:country": "GB",
    "wof:name": "WF8 4TE",
    "wof:placetype": "postalcode"
  },
  "geometry": {"coordinates":[-1.314984,53.69947],"type":"Point"}
}
