{
  "type": "Feature",
  "properties": {
    "iso:country": "GB",
    "wof:name": "WF8 4TE",
    "wof:placetype": "postalcode"
  },
  "geometry": {"coordinates":[-1.314984,53.69947],"type":"Point"}
}
