{
  "type": "Feature",
  "properties": {
    "iso:country":"GB",
    "wof:name":"E11 2AH",
    "wof:placetype":"postalcode"
},
  "geometry": {"coordinates":[0.02550458496605,51.57827673281832],"type":"Point"}
}