{
  "type": "Feature",
  "properties": {
    "iso:country":"GB",
    "wof:name":"HR8 2JR",
    "wof:placetype":"postalcode"
},
  "geometry": {"coordinates":[-2.47355231553659,52.04228826610757],"type":"Point"}
}