{
  "type": "Feature",
  "properties": {
    "iso:country":"GB",
    "wof:name":"CM16 7EZ",
    "wof:placetype":"postalcode"
},
  "geometry": {"coordinates":[0.10312647131708,51.67358218866234],"type":"Point"}
}