{
  "type": "Feature",
  "properties": {
    "iso:country":"GB",
    "wof:name":"KA12 8RT",
    "wof:placetype":"postalcode"
},
  "geometry": {"coordinates":[-4.67277570765537,55.62411985485713],"type":"Point"}
}