{
  "type": "Feature",
  "properties": {
    "iso:country":"GB",
    "wof:name":"G3 8JN",
    "wof:placetype":"postalcode"
},
  "geometry": {"coordinates":[-4.27909179537094,55.85762439073653],"type":"Point"}
}