{
  "type": "Feature",
  "properties": {
    "iso:country":"GB",
    "wof:name":"BN7 3EU",
    "wof:placetype":"postalcode"
},
  "geometry": {"coordinates":[0.00014902029843,50.84648590613075],"type":"Point"}
}