{
  "type": "Feature",
  "properties": {
    "iso:country":"GB",
    "wof:name":"WF7 6JQ",
    "wof:placetype":"postalcode"
},
  "geometry": {"coordinates":[-1.35798321998308,53.68249581316899],"type":"Point"}
}