{
  "type": "Feature",
  "properties": {
    "iso:country": "GB",
    "wof:name": "WF7 6JQ",
    "wof:placetype": "postalcode"
  },
  "geometry": {"coordinates":[-1.357983,53.682496],"type":"Point"}
}
