{
  "type": "Feature",
  "properties": {
    "iso:country": "GB",
    "wof:name": "TR26 2GQ",
    "wof:placetype": "postalcode"
  },
  "geometry": {"coordinates":[-5.481349,50.207979],"type":"Point"}
}
