{
  "type": "Feature",
  "properties": {
    "iso:country":"GB",
    "wof:name":"KA25 7AH",
    "wof:placetype":"postalcode"
},
  "geometry": {"coordinates":[-4.69089312113703,55.7554985142077],"type":"Point"}
}