{
  "type": "Feature",
  "properties": {
    "date:inception_lower": "1996-12-01",
    "date:inception_upper": "1996-12-01",
    "iso:country": "GB",
    "wof:name": "KA25 7AH",
    "wof:placetype": "postalcode"
  },
  "geometry": {"coordinates":[-4.690893,55.755499],"type":"Point"}
}
