{
  "type": "Feature",
  "properties": {
    "date:inception_lower": "1980-01-01",
    "date:inception_upper": "1980-01-01",
    "iso:country": "GB",
    "wof:name": "S8 8PY",
    "wof:placetype": "postalcode"
  },
  "geometry": {"coordinates":[-1.469885,53.342873],"type":"Point"}
}
