{
  "type": "Feature",
  "properties": {
    "iso:country":"GB",
    "wof:name":"S8 8PY",
    "wof:placetype":"postalcode"
},
  "geometry": {"coordinates":[-1.46988522863762,53.34287339319094],"type":"Point"}
}