{
  "type": "Feature",
  "properties": {
    "iso:country":"GB",
    "wof:name":"CR2 6PH",
    "wof:placetype":"postalcode"
},
  "geometry": {"coordinates":[-0.09483658458669,51.35740112959103],"type":"Point"}
}