{
  "type": "Feature",
  "properties": {
    "iso:country":"GB",
    "wof:name":"M34 5BZ",
    "wof:placetype":"postalcode"
},
  "geometry": {"coordinates":[-2.11267025791038,53.46866739576861],"type":"Point"}
}