{
  "type": "Feature",
  "properties": {
    "iso:country":"GB",
    "wof:name":"LA1 1GE",
    "wof:placetype":"postalcode"
},
  "geometry": {"coordinates":[-2.79252767778074,54.05153307232318],"type":"Point"}
}