{
  "type": "Feature",
  "properties": {
    "iso:country":"GB",
    "wof:name":"LE12 6SH",
    "wof:placetype":"postalcode"
},
  "geometry": {"coordinates":[-1.05106974966384,52.82195105330094],"type":"Point"}
}