{
  "type": "Feature",
  "properties": {
    "date:inception_lower":"2003-01-01",
    "date:inception_upper":"2003-01-31",
    "iso:country":"GB",
    "wof:name":"LE12 6SH",
    "wof:placetype":"postalcode"
},
  "geometry": {"coordinates":[-1.05107,52.821951],"type":"Point"}
}