{
  "type": "Feature",
  "properties": {
    "iso:country": "GB",
    "wof:name": "LE12 6SH",
    "wof:placetype": "postalcode"
  },
  "geometry": {"coordinates":[-1.05107,52.821951],"type":"Point"}
}
