{
  "type": "Feature",
  "properties": {
    "iso:country":"GB",
    "wof:name":"B43 6NB",
    "wof:placetype":"postalcode"
},
  "geometry": {"coordinates":[-1.93913883023792,52.54925890961943],"type":"Point"}
}