{
  "type": "Feature",
  "properties": {
    "iso:country": "GB",
    "wof:name": "NE25 0EZ",
    "wof:placetype": "postalcode"
  },
  "geometry": {"coordinates":[-1.53077,55.074773],"type":"Point"}
}
