{
  "type": "Feature",
  "properties": {
    "date:inception_lower": "2006-07-01",
    "date:inception_upper": "2006-07-01",
    "iso:country": "GB",
    "wof:name": "NE25 0EZ",
    "wof:placetype": "postalcode"
  },
  "geometry": {"coordinates":[-1.53077,55.074773],"type":"Point"}
}
