{
  "type": "Feature",
  "properties": {
    "iso:country":"GB",
    "wof:name":"TQ12 1DR",
    "wof:placetype":"postalcode"
},
  "geometry": {"coordinates":[-3.59875219202058,50.52566827715346],"type":"Point"}
}