{
  "type": "Feature",
  "properties": {
    "date:inception_lower": "2001-12-01",
    "date:inception_upper": "2001-12-01",
    "iso:country": "GB",
    "wof:name": "TQ12 1DR",
    "wof:placetype": "postalcode"
  },
  "geometry": {"coordinates":[-3.598752,50.525668],"type":"Point"}
}
