{
  "type": "Feature",
  "properties": {
    "iso:country": "GB",
    "wof:name": "BA1 7NE",
    "wof:placetype": "postalcode"
  },
  "geometry": {"coordinates":[-2.314333,51.40516],"type":"Point"}
}
