{
  "type": "Feature",
  "properties": {
    "iso:country":"GB",
    "wof:name":"BA1 7NE",
    "wof:placetype":"postalcode"
},
  "geometry": {"coordinates":[-2.31433305426221,51.40515953794644],"type":"Point"}
}