{
  "type": "Feature",
  "properties": {
    "date:inception_lower":"1980-01-01",
    "date:inception_upper":"1980-01-31",
    "iso:country":"GB",
    "wof:name":"RG5 3NP",
    "wof:placetype":"postalcode"
},
  "geometry": {"coordinates":[-0.906265,51.44759],"type":"Point"}
}