{
  "type": "Feature",
  "properties": {
    "iso:country":"GB",
    "wof:name":"RG5 3NP",
    "wof:placetype":"postalcode"
},
  "geometry": {"coordinates":[-0.9062650538639,51.44758956792499],"type":"Point"}
}