{
  "type": "Feature",
  "properties": {
    "iso:country":"GB",
    "wof:name":"OL8 4JF",
    "wof:placetype":"postalcode"
},
  "geometry": {"coordinates":[-2.12323083756114,53.52597607505692],"type":"Point"}
}