{
  "type": "Feature",
  "properties": {
    "date:inception_lower": "1980-01-01",
    "date:inception_upper": "1980-01-01",
    "iso:country": "GB",
    "wof:name": "W11 1QY",
    "wof:placetype": "postalcode"
  },
  "geometry": {"coordinates":[-0.211887,51.515303],"type":"Point"}
}
