{
  "type": "Feature",
  "properties": {
    "iso:country":"GB",
    "wof:name":"W11 1QY",
    "wof:placetype":"postalcode"
},
  "geometry": {"coordinates":[-0.21188715056006,51.51530272897788],"type":"Point"}
}