{
  "type": "Feature",
  "properties": {
    "date:inception_lower": "1980-01-01",
    "date:inception_upper": "1980-01-01",
    "iso:country": "GB",
    "wof:name": "SK14 8JF",
    "wof:placetype": "postalcode"
  },
  "geometry": {"coordinates":[-1.991662,53.464478],"type":"Point"}
}
