{
  "type": "Feature",
  "properties": {
    "iso:country": "GB",
    "wof:name": "N22 6SR",
    "wof:placetype": "postalcode"
  },
  "geometry": {"coordinates":[-0.109439,51.594008],"type":"Point"}
}
