{
  "type": "Feature",
  "properties": {
    "date:inception_lower": "1981-06-01",
    "date:inception_upper": "1981-06-01",
    "iso:country": "GB",
    "wof:name": "N22 6SR",
    "wof:placetype": "postalcode"
  },
  "geometry": {"coordinates":[-0.109987,51.59411],"type":"Point"}
}
