{
  "type": "Feature",
  "properties": {
    "iso:country":"GB",
    "wof:name":"N22 6SR",
    "wof:placetype":"postalcode"
},
  "geometry": {"coordinates":[-0.10943865196331,51.5940080431656],"type":"Point"}
}