{
  "type": "Feature",
  "properties": {
    "iso:country": "GB",
    "wof:name": "GL51 3RP",
    "wof:placetype": "postalcode"
  },
  "geometry": {"coordinates":[-2.094111,51.883024],"type":"Point"}
}
