{
  "type": "Feature",
  "properties": {
    "iso:country": "GB",
    "wof:name": "RG22 4UB",
    "wof:placetype": "postalcode"
  },
  "geometry": {"coordinates":[-1.133562,51.237091],"type":"Point"}
}
