{
  "type": "Feature",
  "properties": {
    "iso:country":"GB",
    "wof:name":"RG22 4UB",
    "wof:placetype":"postalcode"
},
  "geometry": {"coordinates":[-1.13356247890627,51.23709080255852],"type":"Point"}
}