{
  "type": "Feature",
  "properties": {
    "date:inception_lower": "1990-02-01",
    "date:inception_upper": "1990-02-01",
    "iso:country": "GB",
    "wof:name": "RG22 4UB",
    "wof:placetype": "postalcode"
  },
  "geometry": {"coordinates":[-1.133562,51.237091],"type":"Point"}
}
