{
  "type": "Feature",
  "properties": {
    "iso:country":"GB",
    "wof:name":"TN9 2JP",
    "wof:placetype":"postalcode"
},
  "geometry": {"coordinates":[0.28044603087515,51.18412940116431],"type":"Point"}
}