{
  "type": "Feature",
  "properties": {
    "iso:country":"GB",
    "wof:name":"ME10 5BH",
    "wof:placetype":"postalcode"
},
  "geometry": {"coordinates":[0.71347825024194,51.35030219883682],"type":"Point"}
}