{
  "type": "Feature",
  "properties": {
    "iso:country": "GB",
    "wof:name": "ME10 5BH",
    "wof:placetype": "postalcode"
  },
  "geometry": {"coordinates":[0.713353,51.350352],"type":"Point"}
}
