{
  "type": "Feature",
  "properties": {
    "date:inception_lower":"2007-11-01",
    "date:inception_upper":"2007-11-30",
    "iso:country":"GB",
    "wof:name":"ME10 5BH",
    "wof:placetype":"postalcode"
},
  "geometry": {"coordinates":[0.713353,51.350352],"type":"Point"}
}