{
  "type": "Feature",
  "properties": {
    "iso:country": "GB",
    "wof:name": "WF11 8BU",
    "wof:placetype": "postalcode"
  },
  "geometry": {"coordinates":[-1.236286,53.707471],"type":"Point"}
}
