{
  "type": "Feature",
  "properties": {
    "date:inception_lower": "2008-04-01",
    "date:inception_upper": "2008-04-01",
    "iso:country": "GB",
    "wof:name": "WF11 8BU",
    "wof:placetype": "postalcode"
  },
  "geometry": {"coordinates":[-1.236286,53.707471],"type":"Point"}
}
