{
  "type": "Feature",
  "properties": {
    "date:inception_lower": "1997-12-01",
    "date:inception_upper": "1997-12-01",
    "iso:country": "GB",
    "wof:name": "PO15 7JZ",
    "wof:placetype": "postalcode"
  },
  "geometry": {"coordinates":[-1.242902,50.881574],"type":"Point"}
}
