{
  "type": "Feature",
  "properties": {
    "iso:country": "GB",
    "wof:name": "TN13 3BT",
    "wof:placetype": "postalcode"
  },
  "geometry": {"coordinates":[0.171855,51.283413],"type":"Point"}
}
