{
  "type": "Feature",
  "properties": {
    "date:inception_lower":"2004-07-01",
    "date:inception_upper":"2004-07-31",
    "iso:country":"GB",
    "wof:name":"TN13 3BT",
    "wof:placetype":"postalcode"
},
  "geometry": {"coordinates":[0.171855,51.283413],"type":"Point"}
}