{
  "type": "Feature",
  "properties": {
    "date:inception_lower":"1980-01-01",
    "date:inception_upper":"1980-01-31",
    "iso:country":"GB",
    "wof:name":"LL28 4SH",
    "wof:placetype":"postalcode"
},
  "geometry": {"coordinates":[-3.758629,53.307737],"type":"Point"}
}