{
  "type": "Feature",
  "properties": {
    "iso:country": "GB",
    "wof:name": "LL28 4SH",
    "wof:placetype": "postalcode"
  },
  "geometry": {"coordinates":[-3.758629,53.307737],"type":"Point"}
}
