{
  "type": "Feature",
  "properties": {
    "iso:country":"GB",
    "wof:name":"LL28 4SH",
    "wof:placetype":"postalcode"
},
  "geometry": {"coordinates":[-3.75897473618347,53.30746385823004],"type":"Point"}
}