{
  "type": "Feature",
  "properties": {
    "iso:country":"GB",
    "wof:name":"KY6 2SQ",
    "wof:placetype":"postalcode"
},
  "geometry": {"coordinates":[-3.1752779368047,56.18850511102644],"type":"Point"}
}