{
  "type": "Feature",
  "properties": {
    "iso:country":"GB",
    "wof:name":"TQ7 4JD",
    "wof:placetype":"postalcode"
},
  "geometry": {"coordinates":[-3.8356766104128,50.31410528125924],"type":"Point"}
}