{
  "type": "Feature",
  "properties": {
    "date:inception_lower": "2004-02-01",
    "date:inception_upper": "2004-02-01",
    "iso:country": "GB",
    "wof:name": "TQ7 4JD",
    "wof:placetype": "postalcode"
  },
  "geometry": {"coordinates":[-3.835677,50.314105],"type":"Point"}
}
