{
  "type": "Feature",
  "properties": {
    "date:inception_lower": "1997-12-01",
    "date:inception_upper": "1997-12-01",
    "iso:country": "GB",
    "wof:name": "BS37 4ER",
    "wof:placetype": "postalcode"
  },
  "geometry": {"coordinates":[-2.413171,51.535806],"type":"Point"}
}
