{
  "type": "Feature",
  "properties": {
    "iso:country":"GB",
    "wof:name":"NW2 6UN",
    "wof:placetype":"postalcode"
},
  "geometry": {"coordinates":[-0.22313054941577,51.55673064089747],"type":"Point"}
}