{
  "type": "Feature",
  "properties": {
    "iso:country":"GB",
    "wof:name":"W8 6SN",
    "wof:placetype":"postalcode"
},
  "geometry": {"coordinates":[-0.19792765119616,51.49907353516775],"type":"Point"}
}