{
  "type": "Feature",
  "properties": {
    "date:inception_lower": "2014-06-01",
    "date:inception_upper": "2014-06-01",
    "iso:country": "GB",
    "wof:name": "W8 6SN",
    "wof:placetype": "postalcode"
  },
  "geometry": {"coordinates":[-0.197928,51.499074],"type":"Point"}
}
