{
  "type": "Feature",
  "properties": {
    "date:inception_lower": "2022-05-01",
    "date:inception_upper": "2022-05-01",
    "iso:country": "GB",
    "wof:name": "DD10 9FZ",
    "wof:placetype": "postalcode"
  },
  "geometry": {"coordinates":[-2.480272,56.746713],"type":"Point"}
}
