{
  "type": "Feature",
  "properties": {
    "iso:country": "GB",
    "wof:name": "L12 0NL",
    "wof:placetype": "postalcode"
  },
  "geometry": {"coordinates":[-2.88507,53.452596],"type":"Point"}
}
