{
  "type": "Feature",
  "properties": {
    "date:inception_lower": "1994-12-01",
    "date:inception_upper": "1994-12-01",
    "iso:country": "GB",
    "wof:name": "NG22 8RN",
    "wof:placetype": "postalcode"
  },
  "geometry": {"coordinates":[-1.037071,53.139079],"type":"Point"}
}
