{
  "type": "Feature",
  "properties": {
    "iso:country": "GB",
    "wof:name": "NG22 8RN",
    "wof:placetype": "postalcode"
  },
  "geometry": {"coordinates":[-1.037071,53.139079],"type":"Point"}
}
