{
  "type": "Feature",
  "properties": {
    "iso:country":"GB",
    "wof:name":"CF3 1NR",
    "wof:placetype":"postalcode"
},
  "geometry": {"coordinates":[-3.11322005134974,51.52198870787214],"type":"Point"}
}