{
  "type": "Feature",
  "properties": {
    "date:inception_lower": "1999-06-01",
    "date:inception_upper": "1999-06-01",
    "iso:country": "GB",
    "wof:name": "CF3 1NR",
    "wof:placetype": "postalcode"
  },
  "geometry": {"coordinates":[-3.11322,51.521989],"type":"Point"}
}
