{
  "type": "Feature",
  "properties": {
    "date:inception_lower":"2009-04-01",
    "date:inception_upper":"2009-04-30",
    "iso:country":"GB",
    "wof:name":"ML6 9FD",
    "wof:placetype":"postalcode"
},
  "geometry": {"coordinates":[-3.994221,55.857953],"type":"Point"}
}