{
  "type": "Feature",
  "properties": {
    "iso:country":"GB",
    "wof:name":"ML6 9FD",
    "wof:placetype":"postalcode"
},
  "geometry": {"coordinates":[-3.9942213553778,55.85795304571231],"type":"Point"}
}