{
  "type": "Feature",
  "properties": {
    "date:inception_lower": "1980-01-01",
    "date:inception_upper": "1980-01-01",
    "iso:country": "GB",
    "wof:name": "BN6 8RN",
    "wof:placetype": "postalcode"
  },
  "geometry": {"coordinates":[-0.084462,50.905378],"type":"Point"}
}
