{
  "type": "Feature",
  "properties": {
    "iso:country":"GB",
    "wof:name":"BN6 8RN",
    "wof:placetype":"postalcode"
},
  "geometry": {"coordinates":[-0.08448963870931,50.90538324084898],"type":"Point"}
}