{
  "type": "Feature",
  "properties": {
    "iso:country":"GB",
    "wof:name":"E18 2LX",
    "wof:placetype":"postalcode"
},
  "geometry": {"coordinates":[0.0234632598163,51.59502920127719],"type":"Point"}
}