{
  "type": "Feature",
  "properties": {
    "iso:country":"GB",
    "wof:name":"KT9 1PF",
    "wof:placetype":"postalcode"
},
  "geometry": {"coordinates":[-0.30648957329708,51.36984246212988],"type":"Point"}
}