{
  "type": "Feature",
  "properties": {
    "date:inception_lower": "1980-01-01",
    "date:inception_upper": "1980-01-01",
    "iso:country": "GB",
    "wof:name": "CV5 8HQ",
    "wof:placetype": "postalcode"
  },
  "geometry": {"coordinates":[-1.54837,52.413474],"type":"Point"}
}
