{
  "type": "Feature",
  "properties": {
    "date:inception_lower":"1980-01-01",
    "date:inception_upper":"1980-01-31",
    "iso:country":"GB",
    "wof:name":"PL26 8XP",
    "wof:placetype":"postalcode"
},
  "geometry": {"coordinates":[-4.786814,50.35799],"type":"Point"}
}