{
  "type": "Feature",
  "properties": {
    "iso:country":"GB",
    "wof:name":"PL26 8XP",
    "wof:placetype":"postalcode"
},
  "geometry": {"coordinates":[-4.78681448894308,50.35798954790825],"type":"Point"}
}