{
  "type": "Feature",
  "properties": {
    "date:inception_lower":"1980-01-01",
    "date:inception_upper":"1980-01-31",
    "iso:country":"GB",
    "wof:name":"OL1 3LT",
    "wof:placetype":"postalcode"
},
  "geometry": {"coordinates":[-2.095716,53.54643],"type":"Point"}
}