{
  "type": "Feature",
  "properties": {
    "iso:country":"GB",
    "wof:name":"SN25 2DD",
    "wof:placetype":"postalcode"
},
  "geometry": {"coordinates":[-1.82002228965749,51.60152990767693],"type":"Point"}
}