{
  "type": "Feature",
  "properties": {
    "iso:country":"GB",
    "wof:name":"SP2 9JB",
    "wof:placetype":"postalcode"
},
  "geometry": {"coordinates":[-1.83048851793468,51.08739933431091],"type":"Point"}
}