{
  "type": "Feature",
  "properties": {
    "iso:country":"GB",
    "wof:name":"WS11 7YN",
    "wof:placetype":"postalcode"
},
  "geometry": {"coordinates":[-2.00420341723458,52.69085380671476],"type":"Point"}
}