{
  "type": "Feature",
  "properties": {
    "iso:country":"GB",
    "wof:name":"SW19 3LB",
    "wof:placetype":"postalcode"
},
  "geometry": {"coordinates":[-0.2022424748012,51.40583335171102],"type":"Point"}
}