{
  "type": "Feature",
  "properties": {
    "iso:country":"GB",
    "wof:name":"RM3 0HD",
    "wof:placetype":"postalcode"
},
  "geometry": {"coordinates":[0.24978944240729,51.6029768722485],"type":"Point"}
}