{
  "type": "Feature",
  "properties": {
    "iso:country":"GB",
    "wof:name":"NE28 7RY",
    "wof:placetype":"postalcode"
},
  "geometry": {"coordinates":[-1.52543964751482,54.99307662632622],"type":"Point"}
}