{
  "type": "Feature",
  "properties": {
    "date:inception_lower": "2024-01-01",
    "date:inception_upper": "2024-01-01",
    "iso:country": "GB",
    "wof:name": "GU5 0FF",
    "wof:placetype": "postalcode"
  },
  "geometry": {"coordinates":[-0.535991,51.157652],"type":"Point"}
}
