{
  "type": "Feature",
  "properties": {
    "iso:country":"GB",
    "wof:name":"ST9 9PB",
    "wof:placetype":"postalcode"
},
  "geometry": {"coordinates":[-2.13399867570936,53.06110354267739],"type":"Point"}
}