{
  "type": "Feature",
  "properties": {
    "iso:country":"GB",
    "wof:name":"RM17 6UU",
    "wof:placetype":"postalcode"
},
  "geometry": {"coordinates":[0.34644740673093,51.47238360032402],"type":"Point"}
}