{
  "type": "Feature",
  "properties": {
    "iso:country":"GB",
    "wof:name":"PR3 0RL",
    "wof:placetype":"postalcode"
},
  "geometry": {"coordinates":[-2.74207529474667,53.85330217276207],"type":"Point"}
}