{
  "type": "Feature",
  "properties": {
    "iso:country":"GB",
    "wof:name":"M34 7AX",
    "wof:placetype":"postalcode"
},
  "geometry": {"coordinates":[-2.10472850843911,53.43691833278568],"type":"Point"}
}