{
  "type": "Feature",
  "properties": {
    "date:inception_lower":"1994-12-01",
    "date:inception_upper":"1994-12-31",
    "iso:country":"GB",
    "wof:name":"M34 7AX",
    "wof:placetype":"postalcode"
},
  "geometry": {"coordinates":[-2.104728,53.436918],"type":"Point"}
}