{
  "type": "Feature",
  "properties": {
    "iso:country": "GB",
    "wof:name": "M34 7AX",
    "wof:placetype": "postalcode"
  },
  "geometry": {"coordinates":[-2.104728,53.436918],"type":"Point"}
}
