{
  "type": "Feature",
  "properties": {
    "date:inception_lower": "1996-12-01",
    "date:inception_upper": "1996-12-01",
    "iso:country": "GB",
    "wof:name": "OL1 2RJ",
    "wof:placetype": "postalcode"
  },
  "geometry": {"coordinates":[-2.155196,53.555286],"type":"Point"}
}
