{
  "type": "Feature",
  "properties": {
    "iso:country":"GB",
    "wof:name":"PH7 3NQ",
    "wof:placetype":"postalcode"
},
  "geometry": {"coordinates":[-3.75318283775818,56.38314975563804],"type":"Point"}
}