{
  "type": "Feature",
  "properties": {
    "date:inception_lower": "1980-01-01",
    "date:inception_upper": "1980-01-01",
    "iso:country": "GB",
    "wof:name": "PH7 3NQ",
    "wof:placetype": "postalcode"
  },
  "geometry": {"coordinates":[-3.753195,56.383069],"type":"Point"}
}
