{
  "type": "Feature",
  "properties": {
    "iso:country": "GB",
    "wof:name": "KT13 8HJ",
    "wof:placetype": "postalcode"
  },
  "geometry": {"coordinates":[-0.463914,51.373397],"type":"Point"}
}
