{
  "type": "Feature",
  "properties": {
    "date:inception_lower": "1995-07-01",
    "date:inception_upper": "1995-07-01",
    "iso:country": "GB",
    "wof:name": "KT13 8HJ",
    "wof:placetype": "postalcode"
  },
  "geometry": {"coordinates":[-0.463914,51.373397],"type":"Point"}
}
