{
  "type": "Feature",
  "properties": {
    "iso:country":"GB",
    "wof:name":"SA1 8LZ",
    "wof:placetype":"postalcode"
},
  "geometry": {"coordinates":[-3.91867324766873,51.62269667773536],"type":"Point"}
}