{
  "type": "Feature",
  "properties": {
    "iso:country": "GB",
    "wof:name": "SA1 8LZ",
    "wof:placetype": "postalcode"
  },
  "geometry": {"coordinates":[-3.918673,51.622697],"type":"Point"}
}
