{
  "type": "Feature",
  "properties": {
    "date:inception_lower": "1980-01-01",
    "date:inception_upper": "1980-01-01",
    "iso:country": "GB",
    "wof:name": "SL5 8EB",
    "wof:placetype": "postalcode"
  },
  "geometry": {"coordinates":[-0.707382,51.414246],"type":"Point"}
}
