{
  "type": "Feature",
  "properties": {
    "iso:country":"GB",
    "wof:name":"SL5 8EB",
    "wof:placetype":"postalcode"
},
  "geometry": {"coordinates":[-0.70738183307309,51.4142463964486],"type":"Point"}
}