{
  "type": "Feature",
  "properties": {
    "iso:country": "GB",
    "wof:name": "SL5 8EB",
    "wof:placetype": "postalcode"
  },
  "geometry": {"coordinates":[-0.707382,51.414246],"type":"Point"}
}
