{
  "type": "Feature",
  "properties": {
    "iso:country": "GB",
    "wof:name": "WV14 9AZ",
    "wof:placetype": "postalcode"
  },
  "geometry": {"coordinates":[-2.098521,52.540001],"type":"Point"}
}
