{
  "type": "Feature",
  "properties": {
    "iso:country":"GB",
    "wof:name":"NE24 4EE",
    "wof:placetype":"postalcode"
},
  "geometry": {"coordinates":[-1.54328931524882,55.12237495980025],"type":"Point"}
}