{
  "type": "Feature",
  "properties": {
    "date:inception_lower": "2019-04-01",
    "date:inception_upper": "2019-04-01",
    "iso:country": "GB",
    "wof:name": "TR9 6GF",
    "wof:placetype": "postalcode"
  },
  "geometry": {"coordinates":[-4.923273,50.398165],"type":"Point"}
}
