{
  "type": "Feature",
  "properties": {
    "iso:country": "GB",
    "wof:name": "TR9 6GF",
    "wof:placetype": "postalcode"
  },
  "geometry": {"coordinates":[-4.923395,50.398099],"type":"Point"}
}
