{
  "type": "Feature",
  "properties": {
    "date:inception_lower":"1980-01-01",
    "date:inception_upper":"1980-01-31",
    "iso:country":"GB",
    "wof:name":"SE5 0NX",
    "wof:placetype":"postalcode"
},
  "geometry": {"coordinates":[-0.098233,51.483021],"type":"Point"}
}