{
  "type": "Feature",
  "properties": {
    "date:inception_lower": "1995-07-01",
    "date:inception_upper": "1995-07-01",
    "iso:country": "GB",
    "wof:name": "RG41 2PR",
    "wof:placetype": "postalcode"
  },
  "geometry": {"coordinates":[-0.845828,51.404101],"type":"Point"}
}
