{
  "type": "Feature",
  "properties": {
    "date:inception_lower":"2009-02-01",
    "date:inception_upper":"2009-02-28",
    "iso:country":"GB",
    "wof:name":"L5 2BJ",
    "wof:placetype":"postalcode"
},
  "geometry": {"coordinates":[-2.988839,53.422056],"type":"Point"}
}