{
  "type": "Feature",
  "properties": {
    "iso:country":"GB",
    "wof:name":"L5 2BJ",
    "wof:placetype":"postalcode"
},
  "geometry": {"coordinates":[-2.98883894474304,53.42205582290374],"type":"Point"}
}