{
  "type": "Feature",
  "properties": {
    "date:inception_lower": "2019-04-01",
    "date:inception_upper": "2019-04-01",
    "iso:country": "GB",
    "wof:name": "CW7 3RX",
    "wof:placetype": "postalcode"
  },
  "geometry": {"coordinates":[-2.495619,53.196058],"type":"Point"}
}
