{
  "type": "Feature",
  "properties": {
    "iso:country":"GB",
    "wof:name":"RG5 4AS",
    "wof:placetype":"postalcode"
},
  "geometry": {"coordinates":[-0.89869857389573,51.43969578064996],"type":"Point"}
}