{
  "type": "Feature",
  "properties": {
    "date:inception_lower": "1995-12-01",
    "date:inception_upper": "1995-12-01",
    "iso:country": "GB",
    "wof:name": "BB12 0TF",
    "wof:placetype": "postalcode"
  },
  "geometry": {"coordinates":[-2.258573,53.798569],"type":"Point"}
}
