{
  "type": "Feature",
  "properties": {
    "iso:country":"GB",
    "wof:name":"BB12 0TF",
    "wof:placetype":"postalcode"
},
  "geometry": {"coordinates":[-2.25857326625513,53.79856916854623],"type":"Point"}
}