{
  "type": "Feature",
  "properties": {
    "iso:country": "GB",
    "wof:name": "BB12 0TF",
    "wof:placetype": "postalcode"
  },
  "geometry": {"coordinates":[-2.258573,53.798569],"type":"Point"}
}
