{
  "type": "Feature",
  "properties": {
    "iso:country":"GB",
    "wof:name":"CO13 0HA",
    "wof:placetype":"postalcode"
},
  "geometry": {"coordinates":[1.24608790966857,51.83847267430623],"type":"Point"}
}