{
  "type": "Feature",
  "properties": {
    "iso:country":"GB",
    "wof:name":"EH19 3LA",
    "wof:placetype":"postalcode"
},
  "geometry": {"coordinates":[-3.10026905579695,55.87146788933729],"type":"Point"}
}