{
  "type": "Feature",
  "properties": {
    "iso:country": "GB",
    "wof:name": "EH19 3LA",
    "wof:placetype": "postalcode"
  },
  "geometry": {"coordinates":[-3.100269,55.871468],"type":"Point"}
}
