{
  "type": "Feature",
  "properties": {
    "date:inception_lower": "2003-08-01",
    "date:inception_upper": "2003-08-01",
    "iso:country": "GB",
    "wof:name": "ME19 4BX",
    "wof:placetype": "postalcode"
  },
  "geometry": {"coordinates":[0.405866,51.273234],"type":"Point"}
}
