{
  "type": "Feature",
  "properties": {
    "iso:country":"GB",
    "wof:name":"S4 7PS",
    "wof:placetype":"postalcode"
},
  "geometry": {"coordinates":[-1.4535808966197,53.39518615639109],"type":"Point"}
}