{
  "type": "Feature",
  "properties": {
    "iso:country": "GB",
    "wof:name": "S4 7PS",
    "wof:placetype": "postalcode"
  },
  "geometry": {"coordinates":[-1.453581,53.395186],"type":"Point"}
}
