{
  "type": "Feature",
  "properties": {
    "iso:country":"GB",
    "wof:name":"W3 0EY",
    "wof:placetype":"postalcode"
},
  "geometry": {"coordinates":[-0.28631748044724,51.51903052782863],"type":"Point"}
}