{
  "type": "Feature",
  "properties": {
    "date:inception_lower": "2014-09-01",
    "date:inception_upper": "2014-09-01",
    "iso:country": "GB",
    "wof:name": "MK12 5QY",
    "wof:placetype": "postalcode"
  },
  "geometry": {"coordinates":[-0.805575,52.061699],"type":"Point"}
}
