{
  "type": "Feature",
  "properties": {
    "iso:country": "GB",
    "wof:name": "RM9 6RL",
    "wof:placetype": "postalcode"
  },
  "geometry": {"coordinates":[0.137125,51.525579],"type":"Point"}
}
