{
  "type": "Feature",
  "properties": {
    "date:inception_lower": "2017-05-01",
    "date:inception_upper": "2017-05-01",
    "iso:country": "GB",
    "wof:name": "RM9 6RL",
    "wof:placetype": "postalcode"
  },
  "geometry": {"coordinates":[0.137125,51.525579],"type":"Point"}
}
