{
  "type": "Feature",
  "properties": {
    "iso:country":"GB",
    "wof:name":"HR6 8DJ",
    "wof:placetype":"postalcode"
},
  "geometry": {"coordinates":[-2.74291446110337,52.22991720208782],"type":"Point"}
}