{
  "type": "Feature",
  "properties": {
    "iso:country":"GB",
    "wof:name":"TQ14 8RQ",
    "wof:placetype":"postalcode"
},
  "geometry": {"coordinates":[-3.49520727826566,50.56125588685861],"type":"Point"}
}