{
  "type": "Feature",
  "properties": {
    "iso:country": "GB",
    "wof:name": "WF3 1RH",
    "wof:placetype": "postalcode"
  },
  "geometry": {"coordinates":[-1.573778,53.732423],"type":"Point"}
}
