{
  "type": "Feature",
  "properties": {
    "iso:country":"GB",
    "wof:name":"WF3 1RH",
    "wof:placetype":"postalcode"
},
  "geometry": {"coordinates":[-1.56141045107306,53.73199405904261],"type":"Point"}
}