{
  "type": "Feature",
  "properties": {
    "iso:country":"GB",
    "wof:name":"CT15 4LN",
    "wof:placetype":"postalcode"
},
  "geometry": {"coordinates":[1.23318137897941,51.22589723292108],"type":"Point"}
}