{
  "type": "Feature",
  "properties": {
    "iso:country": "GB",
    "wof:name": "CT15 4LN",
    "wof:placetype": "postalcode"
  },
  "geometry": {"coordinates":[1.233181,51.225897],"type":"Point"}
}
