{
  "type": "Feature",
  "properties": {
    "iso:country":"GB",
    "wof:name":"TF4 3AW",
    "wof:placetype":"postalcode"
},
  "geometry": {"coordinates":[-2.47209214545964,52.65910504073982],"type":"Point"}
}