{
  "type": "Feature",
  "properties": {
    "iso:country":"GB",
    "wof:name":"M3 7ND",
    "wof:placetype":"postalcode"
},
  "geometry": {"coordinates":[-2.2494562665269,53.48740752494663],"type":"Point"}
}