{
  "type": "Feature",
  "properties": {
    "date:inception_lower": "1980-01-01",
    "date:inception_upper": "1980-01-01",
    "iso:country": "GB",
    "wof:name": "PE11 3BJ",
    "wof:placetype": "postalcode"
  },
  "geometry": {"coordinates":[-0.188305,52.750692],"type":"Point"}
}
