{
  "type": "Feature",
  "properties": {
    "iso:country": "GB",
    "wof:name": "PE26 2UP",
    "wof:placetype": "postalcode"
  },
  "geometry": {"coordinates":[-0.154779,52.479394],"type":"Point"}
}
