{
  "type": "Feature",
  "properties": {
    "date:inception_lower": "1980-01-01",
    "date:inception_upper": "1980-01-01",
    "iso:country": "GB",
    "wof:name": "LL19 7LU",
    "wof:placetype": "postalcode"
  },
  "geometry": {"coordinates":[-3.408175,53.339909],"type":"Point"}
}
