{
  "type": "Feature",
  "properties": {
    "iso:country":"GB",
    "wof:name":"KT23 4EF",
    "wof:placetype":"postalcode"
},
  "geometry": {"coordinates":[-0.38860292070318,51.2766421545909],"type":"Point"}
}