{
  "type": "Feature",
  "properties": {
    "iso:country":"GB",
    "wof:name":"HU17 9JJ",
    "wof:placetype":"postalcode"
},
  "geometry": {"coordinates":[-0.42548601278627,53.84637681311738],"type":"Point"}
}