{
  "type": "Feature",
  "properties": {
    "date:inception_lower": "2008-11-01",
    "date:inception_upper": "2008-11-01",
    "iso:country": "GB",
    "wof:name": "WS15 3RL",
    "wof:placetype": "postalcode"
  },
  "geometry": {"coordinates":[-1.88498,52.760576],"type":"Point"}
}
