{
  "type": "Feature",
  "properties": {
    "iso:country": "GB",
    "wof:name": "WS15 3RL",
    "wof:placetype": "postalcode"
  },
  "geometry": {"coordinates":[-1.88498,52.760576],"type":"Point"}
}
