{
  "type": "Feature",
  "properties": {
    "iso:country":"GB",
    "wof:name":"BH23 4PW",
    "wof:placetype":"postalcode"
},
  "geometry": {"coordinates":[-1.72685239082204,50.74597826254355],"type":"Point"}
}