{
  "type": "Feature",
  "properties": {
    "iso:country":"GB",
    "wof:name":"LL19 7TB",
    "wof:placetype":"postalcode"
},
  "geometry": {"coordinates":[-3.41457256245624,53.33669565212818],"type":"Point"}
}