{
  "type": "Feature",
  "properties": {
    "iso:country": "GB",
    "wof:name": "LL19 7TB",
    "wof:placetype": "postalcode"
  },
  "geometry": {"coordinates":[-3.414573,53.336696],"type":"Point"}
}
