{
  "type": "Feature",
  "properties": {
    "iso:country": "GB",
    "wof:name": "NN11 3SY",
    "wof:placetype": "postalcode"
  },
  "geometry": {"coordinates":[-1.203224,52.168173],"type":"Point"}
}
