{
  "type": "Feature",
  "properties": {
    "iso:country":"GB",
    "wof:name":"CT12 5DT",
    "wof:placetype":"postalcode"
},
  "geometry": {"coordinates":[1.34474095800555,51.33528825391699],"type":"Point"}
}