{
  "type": "Feature",
  "properties": {
    "iso:country":"GB",
    "wof:name":"HS2 9JF",
    "wof:placetype":"postalcode"
},
  "geometry": {"coordinates":[-7.03837453062244,58.19260628909223],"type":"Point"}
}