{
  "type": "Feature",
  "properties": {
    "iso:country":"GB",
    "wof:name":"CM8 1HD",
    "wof:placetype":"postalcode"
},
  "geometry": {"coordinates":[0.63188242453922,51.79909676740041],"type":"Point"}
}