{
  "type": "Feature",
  "properties": {
    "iso:country":"GB",
    "wof:name":"SW1X 9NB",
    "wof:placetype":"postalcode"
},
  "geometry": {"coordinates":[-0.1601312270435,51.50028516553385],"type":"Point"}
}