{
  "type": "Feature",
  "properties": {
    "iso:country": "GB",
    "wof:name": "SW1X 9NB",
    "wof:placetype": "postalcode"
  },
  "geometry": {"coordinates":[-0.160131,51.500285],"type":"Point"}
}
