{
  "type": "Feature",
  "properties": {
    "iso:country":"GB",
    "wof:name":"SE6 3AH",
    "wof:placetype":"postalcode"
},
  "geometry": {"coordinates":[-0.01656250241937,51.42574227522393],"type":"Point"}
}