{
  "type": "Feature",
  "properties": {
    "iso:country":"GB",
    "wof:name":"LN13 9RG",
    "wof:placetype":"postalcode"
},
  "geometry": {"coordinates":[0.26810388402727,53.26649989596019],"type":"Point"}
}