{
  "type": "Feature",
  "properties": {
    "iso:country": "GB",
    "wof:name": "LN13 9RG",
    "wof:placetype": "postalcode"
  },
  "geometry": {"coordinates":[0.268104,53.2665],"type":"Point"}
}
