{
  "type": "Feature",
  "properties": {
    "iso:country": "GB",
    "wof:name": "SS16 4FH",
    "wof:placetype": "postalcode"
  },
  "geometry": {"coordinates":[0.481129,51.565371],"type":"Point"}
}
