{
  "type": "Feature",
  "properties": {
    "iso:country":"GB",
    "wof:name":"HR2 7UN",
    "wof:placetype":"postalcode"
},
  "geometry": {"coordinates":[-2.75295824003702,52.04279354675672],"type":"Point"}
}