{
  "type": "Feature",
  "properties": {
    "date:inception_lower":"2003-05-01",
    "date:inception_upper":"2003-05-31",
    "iso:country":"GB",
    "wof:name":"HR2 7UN",
    "wof:placetype":"postalcode"
},
  "geometry": {"coordinates":[-2.752958,52.042794],"type":"Point"}
}