{
  "type": "Feature",
  "properties": {
    "iso:country":"GB",
    "wof:name":"DG3 5NF",
    "wof:placetype":"postalcode"
},
  "geometry": {"coordinates":[-3.7662373969319,55.23970742031168],"type":"Point"}
}