{
  "type": "Feature",
  "properties": {
    "date:inception_lower": "1980-01-01",
    "date:inception_upper": "1980-01-01",
    "iso:country": "GB",
    "wof:name": "SY4 2EU",
    "wof:placetype": "postalcode"
  },
  "geometry": {"coordinates":[-2.876101,52.810874],"type":"Point"}
}
