{
  "type": "Feature",
  "properties": {
    "iso:country":"GB",
    "wof:name":"SY4 2EU",
    "wof:placetype":"postalcode"
},
  "geometry": {"coordinates":[-2.87610062786532,52.81087418327454],"type":"Point"}
}