{
  "type": "Feature",
  "properties": {
    "date:inception_lower": "1996-06-01",
    "date:inception_upper": "1996-06-01",
    "iso:country": "GB",
    "wof:name": "TA5 1YA",
    "wof:placetype": "postalcode"
  },
  "geometry": {"coordinates":[-3.127632,51.20676],"type":"Point"}
}
