{
  "type": "Feature",
  "properties": {
    "date:inception_lower": "1980-01-01",
    "date:inception_upper": "1980-01-01",
    "iso:country": "GB",
    "wof:name": "TA8 2LU",
    "wof:placetype": "postalcode"
  },
  "geometry": {"coordinates":[-3.006152,51.263755],"type":"Point"}
}
