{
  "type": "Feature",
  "properties": {
    "iso:country":"GB",
    "wof:name":"BN1 9SJ",
    "wof:placetype":"postalcode"
},
  "geometry": {"coordinates":[-0.08927939600791,50.86689791682958],"type":"Point"}
}