{
  "type": "Feature",
  "properties": {
    "iso:country":"GB",
    "wof:name":"GU17 9EQ",
    "wof:placetype":"postalcode"
},
  "geometry": {"coordinates":[-0.76563146877929,51.31659026787587],"type":"Point"}
}