{
  "type": "Feature",
  "properties": {
    "date:inception_lower":"2002-10-01",
    "date:inception_upper":"2002-10-31",
    "iso:country":"GB",
    "wof:name":"SW8 3TD",
    "wof:placetype":"postalcode"
},
  "geometry": {"coordinates":[-0.147234,51.470219],"type":"Point"}
}