{
  "type": "Feature",
  "properties": {
    "iso:country": "GB",
    "wof:name": "SW8 3TD",
    "wof:placetype": "postalcode"
  },
  "geometry": {"coordinates":[-0.147234,51.470219],"type":"Point"}
}
