{
  "type": "Feature",
  "properties": {
    "iso:country":"GB",
    "wof:name":"SW8 3TD",
    "wof:placetype":"postalcode"
},
  "geometry": {"coordinates":[-0.14694500674835,51.47015938076437],"type":"Point"}
}