{
  "type": "Feature",
  "properties": {
    "date:inception_lower": "2009-06-01",
    "date:inception_upper": "2009-06-01",
    "iso:country": "GB",
    "wof:name": "M4 4HU",
    "wof:placetype": "postalcode"
  },
  "geometry": {"coordinates":[-2.232551,53.488125],"type":"Point"}
}
