{
  "type": "Feature",
  "properties": {
    "date:inception_lower": "1980-01-01",
    "date:inception_upper": "1980-01-01",
    "iso:country": "GB",
    "wof:name": "DT5 2HG",
    "wof:placetype": "postalcode"
  },
  "geometry": {"coordinates":[-2.447939,50.541667],"type":"Point"}
}
