{
  "type": "Feature",
  "properties": {
    "iso:country":"GB",
    "wof:name":"DT5 2HG",
    "wof:placetype":"postalcode"
},
  "geometry": {"coordinates":[-2.44793942342832,50.54166738770117],"type":"Point"}
}