{
  "type": "Feature",
  "properties": {
    "iso:country":"GB",
    "wof:name":"ME17 3PZ",
    "wof:placetype":"postalcode"
},
  "geometry": {"coordinates":[0.63268558578351,51.22665549972951],"type":"Point"}
}