{
  "type": "Feature",
  "properties": {
    "iso:country": "GB",
    "wof:name": "PE6 0DN",
    "wof:placetype": "postalcode"
  },
  "geometry": {"coordinates":[-0.172133,52.66835],"type":"Point"}
}
