{
  "type": "Feature",
  "properties": {
    "iso:country":"GB",
    "wof:name":"DL10 6LX",
    "wof:placetype":"postalcode"
},
  "geometry": {"coordinates":[-1.64986494474352,54.47245454244256],"type":"Point"}
}