{
  "type": "Feature",
  "properties": {
    "iso:country":"GB",
    "wof:name":"EN7 6UG",
    "wof:placetype":"postalcode"
},
  "geometry": {"coordinates":[-0.0749001700081,51.71997846720142],"type":"Point"}
}