{
  "type": "Feature",
  "properties": {
    "iso:country":"GB",
    "wof:name":"CM1 4RY",
    "wof:placetype":"postalcode"
},
  "geometry": {"coordinates":[0.35845286016632,51.77676298700575],"type":"Point"}
}