{
  "type": "Feature",
  "properties": {
    "iso:country": "GB",
    "wof:name": "TN16 3ST",
    "wof:placetype": "postalcode"
  },
  "geometry": {"coordinates":[0.040371,51.316167],"type":"Point"}
}
