{
  "type": "Feature",
  "properties": {
    "iso:country":"GB",
    "wof:name":"TN16 3ST",
    "wof:placetype":"postalcode"
},
  "geometry": {"coordinates":[0.04045540467986,51.3161200029512],"type":"Point"}
}