{
  "type": "Feature",
  "properties": {
    "date:inception_lower": "1980-01-01",
    "date:inception_upper": "1980-01-01",
    "iso:country": "GB",
    "wof:name": "EX39 2RN",
    "wof:placetype": "postalcode"
  },
  "geometry": {"coordinates":[-4.208558,51.033307],"type":"Point"}
}
