{
  "type": "Feature",
  "properties": {
    "iso:country":"GB",
    "wof:name":"EX39 2RN",
    "wof:placetype":"postalcode"
},
  "geometry": {"coordinates":[-4.20851944543917,51.03332102806633],"type":"Point"}
}