{
  "type": "Feature",
  "properties": {
    "date:inception_lower": "2024-06-01",
    "date:inception_upper": "2024-06-01",
    "iso:country": "GB",
    "wof:name": "TF2 9WW",
    "wof:placetype": "postalcode"
  },
  "geometry": {"coordinates":[-2.421471,52.697715],"type":"Point"}
}
