{
  "type": "Feature",
  "properties": {
    "iso:country": "GB",
    "wof:name": "TW7 6JE",
    "wof:placetype": "postalcode"
  },
  "geometry": {"coordinates":[-0.337033,51.469718],"type":"Point"}
}
