{
  "type": "Feature",
  "properties": {
    "iso:country": "GB",
    "wof:name": "NG22 8FR",
    "wof:placetype": "postalcode"
  },
  "geometry": {"coordinates":[-1.014043,53.096786],"type":"Point"}
}
