{
  "type": "Feature",
  "properties": {
    "date:inception_lower":"1997-06-01",
    "date:inception_upper":"1997-06-30",
    "iso:country":"GB",
    "wof:name":"WV13 2SE",
    "wof:placetype":"postalcode"
},
  "geometry": {"coordinates":[-2.037151,52.585569],"type":"Point"}
}