{
  "type": "Feature",
  "properties": {
    "date:inception_lower": "1980-01-01",
    "date:inception_upper": "1980-01-01",
    "iso:country": "GB",
    "wof:name": "CV21 3QF",
    "wof:placetype": "postalcode"
  },
  "geometry": {"coordinates":[-1.252062,52.371909],"type":"Point"}
}
