{
  "type": "Feature",
  "properties": {
    "iso:country":"GB",
    "wof:name":"DD7 7NY",
    "wof:placetype":"postalcode"
},
  "geometry": {"coordinates":[-2.74311650189868,56.50048355028216],"type":"Point"}
}