{
  "type": "Feature",
  "properties": {
    "iso:country":"GB",
    "wof:name":"TA21 8BW",
    "wof:placetype":"postalcode"
},
  "geometry": {"coordinates":[-3.23046329632251,50.97136052248209],"type":"Point"}
}