{
  "type": "Feature",
  "properties": {
    "iso:country":"GB",
    "wof:name":"GU9 8TZ",
    "wof:placetype":"postalcode"
},
  "geometry": {"coordinates":[-0.81701754008674,51.2037462467713],"type":"Point"}
}