{
  "type": "Feature",
  "properties": {
    "date:inception_lower": "1986-07-01",
    "date:inception_upper": "1986-07-01",
    "iso:country": "GB",
    "wof:name": "GU34 4HG",
    "wof:placetype": "postalcode"
  },
  "geometry": {"coordinates":[-0.947662,51.163474],"type":"Point"}
}
