{
  "type": "Feature",
  "properties": {
    "iso:country":"GB",
    "wof:name":"LL11 5EA",
    "wof:placetype":"postalcode"
},
  "geometry": {"coordinates":[-3.05236974124127,53.07756743465318],"type":"Point"}
}