{
  "type": "Feature",
  "properties": {
    "iso:country":"GB",
    "wof:name":"AB11 6HS",
    "wof:placetype":"postalcode"
},
  "geometry": {"coordinates":[-2.10123949991438,57.14115839656436],"type":"Point"}
}