{
  "type": "Feature",
  "properties": {
    "date:inception_lower": "1985-10-01",
    "date:inception_upper": "1985-10-01",
    "iso:country": "GB",
    "wof:name": "DN35 0TD",
    "wof:placetype": "postalcode"
  },
  "geometry": {"coordinates":[-0.028441,53.545566],"type":"Point"}
}
