{
  "type": "Feature",
  "properties": {
    "iso:country":"GB",
    "wof:name":"DN35 0TD",
    "wof:placetype":"postalcode"
},
  "geometry": {"coordinates":[-0.02844056877238,53.54556603612017],"type":"Point"}
}