{
  "type": "Feature",
  "properties": {
    "iso:country":"GB",
    "wof:name":"LE4 2FZ",
    "wof:placetype":"postalcode"
},
  "geometry": {"coordinates":[-1.14011117388777,52.65924815611808],"type":"Point"}
}