{
  "type": "Feature",
  "properties": {
    "date:inception_lower": "1980-01-01",
    "date:inception_upper": "1980-01-01",
    "iso:country": "GB",
    "wof:name": "GU8 4AD",
    "wof:placetype": "postalcode"
  },
  "geometry": {"coordinates":[-0.584005,51.159973],"type":"Point"}
}
