{
  "type": "Feature",
  "properties": {
    "iso:country":"GB",
    "wof:name":"CB3 0FT",
    "wof:placetype":"postalcode"
},
  "geometry": {"coordinates":[0.08930689151731,52.20912636808079],"type":"Point"}
}