{
  "type": "Feature",
  "properties": {
    "iso:country": "GB",
    "wof:name": "CB3 0FT",
    "wof:placetype": "postalcode"
  },
  "geometry": {"coordinates":[0.089307,52.209126],"type":"Point"}
}
