{
  "type": "Feature",
  "properties": {
    "iso:country":"GB",
    "wof:name":"HA5 4PT",
    "wof:placetype":"postalcode"
},
  "geometry": {"coordinates":[-0.37760076781354,51.60814618218504],"type":"Point"}
}