{
  "type": "Feature",
  "properties": {
    "iso:country":"GB",
    "wof:name":"PE13 5PB",
    "wof:placetype":"postalcode"
},
  "geometry": {"coordinates":[0.09007201219605,52.71821265836686],"type":"Point"}
}