{
  "type": "Feature",
  "properties": {
    "date:inception_lower": "1980-01-01",
    "date:inception_upper": "1980-01-01",
    "iso:country": "GB",
    "wof:name": "PE13 5PB",
    "wof:placetype": "postalcode"
  },
  "geometry": {"coordinates":[0.090072,52.718213],"type":"Point"}
}
