{
  "type": "Feature",
  "properties": {
    "iso:country":"GB",
    "wof:name":"SA4 8DE",
    "wof:placetype":"postalcode"
},
  "geometry": {"coordinates":[-4.03669545643788,51.69083149358534],"type":"Point"}
}