{
  "type": "Feature",
  "properties": {
    "date:inception_lower":"1980-01-01",
    "date:inception_upper":"1980-01-31",
    "iso:country":"GB",
    "wof:name":"PA28 6EL",
    "wof:placetype":"postalcode"
},
  "geometry": {"coordinates":[-5.600002,55.429075],"type":"Point"}
}