{
  "type": "Feature",
  "properties": {
    "date:inception_lower": "1980-01-01",
    "date:inception_upper": "1980-01-01",
    "iso:country": "GB",
    "wof:name": "S41 0RL",
    "wof:placetype": "postalcode"
  },
  "geometry": {"coordinates":[-1.420016,53.224501],"type":"Point"}
}
