{
  "type": "Feature",
  "properties": {
    "iso:country":"GB",
    "wof:name":"S41 0RL",
    "wof:placetype":"postalcode"
},
  "geometry": {"coordinates":[-1.42001650346768,53.22450091965694],"type":"Point"}
}