{
  "type": "Feature",
  "properties": {
    "date:inception_lower": "2011-11-01",
    "date:inception_upper": "2011-11-01",
    "iso:country": "GB",
    "wof:name": "L34 5NH",
    "wof:placetype": "postalcode"
  },
  "geometry": {"coordinates":[-2.801146,53.423732],"type":"Point"}
}
