{
  "type": "Feature",
  "properties": {
    "iso:country": "GB",
    "wof:name": "WF1 4FA",
    "wof:placetype": "postalcode"
  },
  "geometry": {"coordinates":[-1.479997,53.695247],"type":"Point"}
}
