{
  "type": "Feature",
  "properties": {
    "iso:country":"GB",
    "wof:name":"EH29 9FR",
    "wof:placetype":"postalcode"
},
  "geometry": {"coordinates":[-3.40548084889448,55.96139056034298],"type":"Point"}
}