{
  "type": "Feature",
  "properties": {
    "iso:country":"GB",
    "wof:name":"WF4 6AL",
    "wof:placetype":"postalcode"
},
  "geometry": {"coordinates":[-1.5672852550424,53.66022676766516],"type":"Point"}
}