{
  "type": "Feature",
  "properties": {
    "iso:country":"GB",
    "wof:name":"SO31 8FY",
    "wof:placetype":"postalcode"
},
  "geometry": {"coordinates":[-1.31991866617205,50.88544673106005],"type":"Point"}
}