{
  "type": "Feature",
  "properties": {
    "iso:country": "GB",
    "wof:name": "HD1 1BS",
    "wof:placetype": "postalcode"
  },
  "geometry": {"coordinates":[-1.782895,53.6475],"type":"Point"}
}
