{
  "type": "Feature",
  "properties": {
    "date:inception_lower": "1980-01-01",
    "date:inception_upper": "1980-01-01",
    "iso:country": "GB",
    "wof:name": "AL10 8NP",
    "wof:placetype": "postalcode"
  },
  "geometry": {"coordinates":[-0.2257,51.756366],"type":"Point"}
}
