{
  "type": "Feature",
  "properties": {
    "iso:country": "GB",
    "wof:name": "AL10 8NP",
    "wof:placetype": "postalcode"
  },
  "geometry": {"coordinates":[-0.225724,51.756343],"type":"Point"}
}
