{
  "type": "Feature",
  "properties": {
    "iso:country":"GB",
    "wof:name":"BA11 6SA",
    "wof:placetype":"postalcode"
},
  "geometry": {"coordinates":[-2.28377990540233,51.26524512599615],"type":"Point"}
}