{
  "type": "Feature",
  "properties": {
    "iso:country":"GB",
    "wof:name":"M19 1QF",
    "wof:placetype":"postalcode"
},
  "geometry": {"coordinates":[-2.19534601401223,53.43028764466585],"type":"Point"}
}