{
  "type": "Feature",
  "properties": {
    "iso:country":"GB",
    "wof:name":"WA12 8BF",
    "wof:placetype":"postalcode"
},
  "geometry": {"coordinates":[-2.61436250609443,53.45281229075662],"type":"Point"}
}