{
  "type": "Feature",
  "properties": {
    "iso:country": "GB",
    "wof:name": "BH15 4LD",
    "wof:placetype": "postalcode"
  },
  "geometry": {"coordinates":[-2.015644,50.721198],"type":"Point"}
}
