{
  "type": "Feature",
  "properties": {
    "iso:country": "GB",
    "wof:name": "CH62 9EB",
    "wof:placetype": "postalcode"
  },
  "geometry": {"coordinates":[-2.971412,53.307724],"type":"Point"}
}
