{
  "type": "Feature",
  "properties": {
    "iso:country":"GB",
    "wof:name":"CH62 9EB",
    "wof:placetype":"postalcode"
},
  "geometry": {"coordinates":[-2.97141156361723,53.30772420668679],"type":"Point"}
}