{
  "type": "Feature",
  "properties": {
    "iso:country":"GB",
    "wof:name":"LA12 0TH",
    "wof:placetype":"postalcode"
},
  "geometry": {"coordinates":[-3.1365740140271,54.16049443284669],"type":"Point"}
}