{
  "type": "Feature",
  "properties": {
    "iso:country":"GB",
    "wof:name":"BL9 8PP",
    "wof:placetype":"postalcode"
},
  "geometry": {"coordinates":[-2.27761954443599,53.55596283938011],"type":"Point"}
}