{
  "type": "Feature",
  "properties": {
    "date:inception_lower": "1980-01-01",
    "date:inception_upper": "1980-01-01",
    "iso:country": "GB",
    "wof:name": "BL9 8PP",
    "wof:placetype": "postalcode"
  },
  "geometry": {"coordinates":[-2.277572,53.555997],"type":"Point"}
}
