{
  "type": "Feature",
  "properties": {
    "iso:country":"GB",
    "wof:name":"WA3 7HL",
    "wof:placetype":"postalcode"
},
  "geometry": {"coordinates":[-2.55335789433822,53.43759619877724],"type":"Point"}
}