{
  "type": "Feature",
  "properties": {
    "iso:country": "GB",
    "wof:name": "EX36 3NZ",
    "wof:placetype": "postalcode"
  },
  "geometry": {"coordinates":[-3.653945,51.040574],"type":"Point"}
}
