{
  "type": "Feature",
  "properties": {
    "iso:country": "GB",
    "wof:name": "BH20 6HX",
    "wof:placetype": "postalcode"
  },
  "geometry": {"coordinates":[-2.236368,50.67676],"type":"Point"}
}
