{
  "type": "Feature",
  "properties": {
    "iso:country":"GB",
    "wof:name":"BH20 6HX",
    "wof:placetype":"postalcode"
},
  "geometry": {"coordinates":[-2.23636796539071,50.67675970060044],"type":"Point"}
}