{
  "type": "Feature",
  "properties": {
    "date:inception_lower":"1996-12-01",
    "date:inception_upper":"1996-12-31",
    "iso:country":"GB",
    "wof:name":"TF4 2GY",
    "wof:placetype":"postalcode"
},
  "geometry": {"coordinates":[-2.469593,52.677023],"type":"Point"}
}