{
  "type": "Feature",
  "properties": {
    "iso:country":"GB",
    "wof:name":"TF4 2GY",
    "wof:placetype":"postalcode"
},
  "geometry": {"coordinates":[-2.46959353874475,52.6770225549205],"type":"Point"}
}