{
  "type": "Feature",
  "properties": {
    "date:inception_lower": "2020-10-01",
    "date:inception_upper": "2020-10-01",
    "iso:country": "GB",
    "wof:name": "GU51 2AB",
    "wof:placetype": "postalcode"
  },
  "geometry": {"coordinates":[-0.830666,51.297753],"type":"Point"}
}
