{
  "type": "Feature",
  "properties": {
    "iso:country": "GB",
    "wof:name": "S6 5AR",
    "wof:placetype": "postalcode"
  },
  "geometry": {"coordinates":[-1.510361,53.396844],"type":"Point"}
}
