{
  "type": "Feature",
  "properties": {
    "iso:country":"GB",
    "wof:name":"BD23 6RZ",
    "wof:placetype":"postalcode"
},
  "geometry": {"coordinates":[-1.98453305138567,53.98032950656136],"type":"Point"}
}