{
  "type": "Feature",
  "properties": {
    "iso:country":"GB",
    "wof:name":"CM13 3HE",
    "wof:placetype":"postalcode"
},
  "geometry": {"coordinates":[0.3379667851887,51.56020900776529],"type":"Point"}
}