{
  "type": "Feature",
  "properties": {
    "iso:country":"GB",
    "wof:name":"LL18 2SQ",
    "wof:placetype":"postalcode"
},
  "geometry": {"coordinates":[-3.46751099568082,53.29679887361041],"type":"Point"}
}