{
  "type": "Feature",
  "properties": {
    "iso:country": "GB",
    "wof:name": "LL18 2SQ",
    "wof:placetype": "postalcode"
  },
  "geometry": {"coordinates":[-3.467511,53.296799],"type":"Point"}
}
