{
  "type": "Feature",
  "properties": {
    "iso:country":"GB",
    "wof:name":"PL26 6DW",
    "wof:placetype":"postalcode"
},
  "geometry": {"coordinates":[-4.76567754641543,50.32793785078113],"type":"Point"}
}