{
  "type": "Feature",
  "properties": {
    "iso:country": "GB",
    "wof:name": "PL26 6DW",
    "wof:placetype": "postalcode"
  },
  "geometry": {"coordinates":[-4.765775,50.327905],"type":"Point"}
}
