{
  "type": "Feature",
  "properties": {
    "date:inception_lower":"2013-08-01",
    "date:inception_upper":"2013-08-31",
    "iso:country":"GB",
    "wof:name":"PL26 6DW",
    "wof:placetype":"postalcode"
},
  "geometry": {"coordinates":[-4.765775,50.327905],"type":"Point"}
}