{
  "type": "Feature",
  "properties": {
    "iso:country": "GB",
    "wof:name": "WV10 6FE",
    "wof:placetype": "postalcode"
  },
  "geometry": {"coordinates":[-2.126754,52.612591],"type":"Point"}
}
