{
  "type": "Feature",
  "properties": {
    "iso:country": "GB",
    "wof:name": "EN11 8FN",
    "wof:placetype": "postalcode"
  },
  "geometry": {"coordinates":[-0.011056,51.760196],"type":"Point"}
}
