{
  "type": "Feature",
  "properties": {
    "date:inception_lower": "1994-05-01",
    "date:inception_upper": "1994-05-01",
    "iso:country": "GB",
    "wof:name": "M20 2XL",
    "wof:placetype": "postalcode"
  },
  "geometry": {"coordinates":[-2.255659,53.421176],"type":"Point"}
}
