{
  "type": "Feature",
  "properties": {
    "iso:country":"GB",
    "wof:name":"SG5 3JJ",
    "wof:placetype":"postalcode"
},
  "geometry": {"coordinates":[-0.39303742954414,51.96071320292163],"type":"Point"}
}