{
  "type": "Feature",
  "properties": {
    "date:inception_lower": "1980-01-01",
    "date:inception_upper": "1980-01-01",
    "iso:country": "GB",
    "wof:name": "M18 7QT",
    "wof:placetype": "postalcode"
  },
  "geometry": {"coordinates":[-2.180862,53.45724],"type":"Point"}
}
