{
  "type": "Feature",
  "properties": {
    "iso:country": "GB",
    "wof:name": "NP19 4LJ",
    "wof:placetype": "postalcode"
  },
  "geometry": {"coordinates":[-2.952335,51.582031],"type":"Point"}
}
