{
  "type": "Feature",
  "properties": {
    "iso:country": "GB",
    "wof:name": "EH49 7HY",
    "wof:placetype": "postalcode"
  },
  "geometry": {"coordinates":[-3.582165,55.982324],"type":"Point"}
}
