{
  "type": "Feature",
  "properties": {
    "iso:country":"GB",
    "wof:name":"KY2 6QF",
    "wof:placetype":"postalcode"
},
  "geometry": {"coordinates":[-3.19892169964549,56.13028764710149],"type":"Point"}
}