{
  "type": "Feature",
  "properties": {
    "date:inception_lower": "2017-04-01",
    "date:inception_upper": "2017-04-01",
    "iso:country": "GB",
    "wof:name": "BS3 1FH",
    "wof:placetype": "postalcode"
  },
  "geometry": {"coordinates":[-2.610309,51.445549],"type":"Point"}
}
