{
  "type": "Feature",
  "properties": {
    "date:inception_lower": "2019-06-01",
    "date:inception_upper": "2019-06-01",
    "iso:country": "GB",
    "wof:name": "OX39 4FW",
    "wof:placetype": "postalcode"
  },
  "geometry": {"coordinates":[-0.913384,51.695022],"type":"Point"}
}
