{
  "type": "Feature",
  "properties": {
    "iso:country": "GB",
    "wof:name": "SR2 7TA",
    "wof:placetype": "postalcode"
  },
  "geometry": {"coordinates":[-1.373587,54.891239],"type":"Point"}
}
