{
  "type": "Feature",
  "properties": {
    "iso:country":"GB",
    "wof:name":"SR2 7TA",
    "wof:placetype":"postalcode"
},
  "geometry": {"coordinates":[-1.37358666748762,54.89123867894161],"type":"Point"}
}