{
  "type": "Feature",
  "properties": {
    "iso:country":"GB",
    "wof:name":"G82 5DP",
    "wof:placetype":"postalcode"
},
  "geometry": {"coordinates":[-4.60014344533771,55.94788883670805],"type":"Point"}
}