{
  "type": "Feature",
  "properties": {
    "iso:country":"GB",
    "wof:name":"BL2 5JA",
    "wof:placetype":"postalcode"
},
  "geometry": {"coordinates":[-2.38407993051898,53.59202602595617],"type":"Point"}
}