{
  "type": "Feature",
  "properties": {
    "date:inception_lower": "1980-01-01",
    "date:inception_upper": "1980-01-01",
    "iso:country": "GB",
    "wof:name": "DD8 2NE",
    "wof:placetype": "postalcode"
  },
  "geometry": {"coordinates":[-2.796359,56.59075],"type":"Point"}
}
