{
  "type": "Feature",
  "properties": {
    "date:inception_lower": "1980-01-01",
    "date:inception_upper": "1980-01-01",
    "iso:country": "GB",
    "wof:name": "KY15 5TF",
    "wof:placetype": "postalcode"
  },
  "geometry": {"coordinates":[-2.94175,56.307361],"type":"Point"}
}
