{
  "type": "Feature",
  "properties": {
    "date:inception_lower": "2016-05-01",
    "date:inception_upper": "2016-05-01",
    "iso:country": "GB",
    "wof:name": "PL4 8FA",
    "wof:placetype": "postalcode"
  },
  "geometry": {"coordinates":[-4.133339,50.379777],"type":"Point"}
}
