{
  "type": "Feature",
  "properties": {
    "iso:country":"GB",
    "wof:name":"M3 7FY",
    "wof:placetype":"postalcode"
},
  "geometry": {"coordinates":[-2.25851465087271,53.49003086054253],"type":"Point"}
}