{
  "type": "Feature",
  "properties": {
    "iso:country": "GB",
    "wof:name": "AL6 0EG",
    "wof:placetype": "postalcode"
  },
  "geometry": {"coordinates":[-0.19239,51.822197],"type":"Point"}
}
