{
  "type": "Feature",
  "properties": {
    "date:inception_lower": "1990-07-01",
    "date:inception_upper": "1990-07-01",
    "iso:country": "GB",
    "wof:name": "AL6 0EG",
    "wof:placetype": "postalcode"
  },
  "geometry": {"coordinates":[-0.192323,51.822176],"type":"Point"}
}
