{
  "type": "Feature",
  "properties": {
    "iso:country": "GB",
    "wof:name": "SN25 1WP",
    "wof:placetype": "postalcode"
  },
  "geometry": {"coordinates":[-1.825518,51.591558],"type":"Point"}
}
