{
  "type": "Feature",
  "properties": {
    "date:inception_lower": "2020-04-01",
    "date:inception_upper": "2020-04-01",
    "iso:country": "GB",
    "wof:name": "FY6 0FS",
    "wof:placetype": "postalcode"
  },
  "geometry": {"coordinates":[-2.9517,53.898449],"type":"Point"}
}
