{
  "type": "Feature",
  "properties": {
    "iso:country": "GB",
    "wof:name": "FY6 0FS",
    "wof:placetype": "postalcode"
  },
  "geometry": {"coordinates":[-2.951276,53.898533],"type":"Point"}
}
