{
  "type": "Feature",
  "properties": {
    "iso:country":"GB",
    "wof:name":"CM16 4PR",
    "wof:placetype":"postalcode"
},
  "geometry": {"coordinates":[0.11540289651364,51.695861145789],"type":"Point"}
}