{
  "type": "Feature",
  "properties": {
    "iso:country":"GB",
    "wof:name":"TF7 4HT",
    "wof:placetype":"postalcode"
},
  "geometry": {"coordinates":[-2.4369731825717,52.64070290687325],"type":"Point"}
}