{
  "type": "Feature",
  "properties": {
    "iso:country": "GB",
    "wof:name": "TF7 4HT",
    "wof:placetype": "postalcode"
  },
  "geometry": {"coordinates":[-2.436973,52.640703],"type":"Point"}
}
