{
  "type": "Feature",
  "properties": {
    "date:inception_lower": "1981-06-01",
    "date:inception_upper": "1981-06-01",
    "iso:country": "GB",
    "wof:name": "TF7 4HT",
    "wof:placetype": "postalcode"
  },
  "geometry": {"coordinates":[-2.436973,52.640703],"type":"Point"}
}
