{
  "type": "Feature",
  "properties": {
    "iso:country":"GB",
    "wof:name":"DT11 7SJ",
    "wof:placetype":"postalcode"
},
  "geometry": {"coordinates":[-2.15040462410366,50.86659235936836],"type":"Point"}
}