{
  "type": "Feature",
  "properties": {
    "date:inception_lower": "2004-08-01",
    "date:inception_upper": "2004-08-01",
    "iso:country": "GB",
    "wof:name": "DT11 7SJ",
    "wof:placetype": "postalcode"
  },
  "geometry": {"coordinates":[-2.150405,50.866592],"type":"Point"}
}
