{
  "type": "Feature",
  "properties": {
    "iso:country":"GB",
    "wof:name":"NR5 0LA",
    "wof:placetype":"postalcode"
},
  "geometry": {"coordinates":[1.22862659170659,52.65331413075914],"type":"Point"}
}