{
  "type": "Feature",
  "properties": {
    "iso:country": "GB",
    "wof:name": "GL1 1RD",
    "wof:placetype": "postalcode"
  },
  "geometry": {"coordinates":[-2.242866,51.861448],"type":"Point"}
}
