{
  "type": "Feature",
  "properties": {
    "iso:country": "GB",
    "wof:name": "CM0 7BZ",
    "wof:placetype": "postalcode"
  },
  "geometry": {"coordinates":[0.829109,51.662323],"type":"Point"}
}
