{
  "type": "Feature",
  "properties": {
    "iso:country":"GB",
    "wof:name":"CM0 7BZ",
    "wof:placetype":"postalcode"
},
  "geometry": {"coordinates":[0.82907986062877,51.66231702907778],"type":"Point"}
}