{
  "type": "Feature",
  "properties": {
    "iso:country":"GB",
    "wof:name":"PE12 9AD",
    "wof:placetype":"postalcode"
},
  "geometry": {"coordinates":[0.12627752679469,52.77790873946671],"type":"Point"}
}