{
  "type": "Feature",
  "properties": {
    "iso:country":"GB",
    "wof:name":"W10 5DL",
    "wof:placetype":"postalcode"
},
  "geometry": {"coordinates":[-0.22067252401809,51.52397012477624],"type":"Point"}
}