{
  "type": "Feature",
  "properties": {
    "date:inception_lower": "1980-01-01",
    "date:inception_upper": "1980-01-01",
    "iso:country": "GB",
    "wof:name": "TA4 2UX",
    "wof:placetype": "postalcode"
  },
  "geometry": {"coordinates":[-3.304259,51.057973],"type":"Point"}
}
