{
  "type": "Feature",
  "properties": {
    "iso:country":"GB",
    "wof:name":"TA4 2UX",
    "wof:placetype":"postalcode"
},
  "geometry": {"coordinates":[-3.3222068641703,51.04725449458363],"type":"Point"}
}