{
  "type": "Feature",
  "properties": {
    "iso:country": "GB",
    "wof:name": "TA4 2UX",
    "wof:placetype": "postalcode"
  },
  "geometry": {"coordinates":[-3.304259,51.057973],"type":"Point"}
}
