{
  "type": "Feature",
  "properties": {
    "date:inception_lower": "1980-01-01",
    "date:inception_upper": "1980-01-01",
    "iso:country": "GB",
    "wof:name": "WR6 5LN",
    "wof:placetype": "postalcode"
  },
  "geometry": {"coordinates":[-2.313933,52.194178],"type":"Point"}
}
