{
  "type": "Feature",
  "properties": {
    "iso:country": "GB",
    "wof:name": "WR6 5LN",
    "wof:placetype": "postalcode"
  },
  "geometry": {"coordinates":[-2.313933,52.194178],"type":"Point"}
}
