{
  "type": "Feature",
  "properties": {
    "iso:country":"GB",
    "wof:name":"WR6 5LN",
    "wof:placetype":"postalcode"
},
  "geometry": {"coordinates":[-2.31393308991182,52.1941777809279],"type":"Point"}
}