{
  "type": "Feature",
  "properties": {
    "iso:country":"GB",
    "wof:name":"HP12 3UZ",
    "wof:placetype":"postalcode"
},
  "geometry": {"coordinates":[-0.77582431858812,51.63113714535772],"type":"Point"}
}