{
  "type": "Feature",
  "properties": {
    "iso:country":"GB",
    "wof:name":"BS8 3QG",
    "wof:placetype":"postalcode"
},
  "geometry": {"coordinates":[-2.6604433614718,51.45980973114566],"type":"Point"}
}