{
  "type": "Feature",
  "properties": {
    "iso:country": "GB",
    "wof:name": "BS8 3QG",
    "wof:placetype": "postalcode"
  },
  "geometry": {"coordinates":[-2.660443,51.45981],"type":"Point"}
}
