{
  "type": "Feature",
  "properties": {
    "date:inception_lower":"1980-01-01",
    "date:inception_upper":"1980-01-31",
    "iso:country":"GB",
    "wof:name":"BS8 3QG",
    "wof:placetype":"postalcode"
},
  "geometry": {"coordinates":[-2.660443,51.45981],"type":"Point"}
}