{
  "type": "Feature",
  "properties": {
    "date:inception_lower": "1985-10-01",
    "date:inception_upper": "1985-10-01",
    "iso:country": "GB",
    "wof:name": "ST4 8UU",
    "wof:placetype": "postalcode"
  },
  "geometry": {"coordinates":[-2.176959,52.959569],"type":"Point"}
}
