{
  "type": "Feature",
  "properties": {
    "iso:country": "GB",
    "wof:name": "ST4 8UU",
    "wof:placetype": "postalcode"
  },
  "geometry": {"coordinates":[-2.176959,52.959569],"type":"Point"}
}
