{
  "type": "Feature",
  "properties": {
    "date:inception_lower": "1980-01-01",
    "date:inception_upper": "1980-01-01",
    "iso:country": "GB",
    "wof:name": "WF10 1QH",
    "wof:placetype": "postalcode"
  },
  "geometry": {"coordinates":[-1.380509,53.722954],"type":"Point"}
}
