{
  "type": "Feature",
  "properties": {
    "iso:country": "GB",
    "wof:name": "NP44 2PF",
    "wof:placetype": "postalcode"
  },
  "geometry": {"coordinates":[-3.003336,51.663052],"type":"Point"}
}
