{
  "type": "Feature",
  "properties": {
    "iso:country": "GB",
    "wof:name": "LA1 5TE",
    "wof:placetype": "postalcode"
  },
  "geometry": {"coordinates":[-2.825268,54.058072],"type":"Point"}
}
