{
  "type": "Feature",
  "properties": {
    "date:inception_lower": "1983-03-01",
    "date:inception_upper": "1983-03-01",
    "iso:country": "GB",
    "wof:name": "LA1 5TE",
    "wof:placetype": "postalcode"
  },
  "geometry": {"coordinates":[-2.825268,54.058072],"type":"Point"}
}
