{
  "type": "Feature",
  "properties": {
    "date:inception_lower": "2011-10-01",
    "date:inception_upper": "2011-10-01",
    "iso:country": "GB",
    "wof:name": "TA6 4GG",
    "wof:placetype": "postalcode"
  },
  "geometry": {"coordinates":[-2.982258,51.148642],"type":"Point"}
}
