{
  "type": "Feature",
  "properties": {
    "iso:country":"GB",
    "wof:name":"SS1 3DD",
    "wof:placetype":"postalcode"
},
  "geometry": {"coordinates":[0.74950800844195,51.5377299901655],"type":"Point"}
}