{
  "type": "Feature",
  "properties": {
    "date:inception_lower": "1980-01-01",
    "date:inception_upper": "1980-01-01",
    "iso:country": "GB",
    "wof:name": "SS1 3DD",
    "wof:placetype": "postalcode"
  },
  "geometry": {"coordinates":[0.749508,51.53773],"type":"Point"}
}
