{
  "type": "Feature",
  "properties": {
    "iso:country":"GB",
    "wof:name":"SW6 2BQ",
    "wof:placetype":"postalcode"
},
  "geometry": {"coordinates":[-0.18907828310657,51.47443269163809],"type":"Point"}
}