{
  "type": "Feature",
  "properties": {
    "date:inception_lower": "2020-11-01",
    "date:inception_upper": "2020-11-01",
    "iso:country": "GB",
    "wof:name": "WR5 1FA",
    "wof:placetype": "postalcode"
  },
  "geometry": {"coordinates":[-2.177868,52.181725],"type":"Point"}
}
