{
  "type": "Feature",
  "properties": {
    "iso:country":"GB",
    "wof:name":"SO30 4FS",
    "wof:placetype":"postalcode"
},
  "geometry": {"coordinates":[-1.29485355740393,50.91573778419433],"type":"Point"}
}