{
  "type": "Feature",
  "properties": {
    "iso:country":"GB",
    "wof:name":"PA1 2ET",
    "wof:placetype":"postalcode"
},
  "geometry": {"coordinates":[-4.43429672841826,55.84270567717011],"type":"Point"}
}