{
  "type": "Feature",
  "properties": {
    "date:inception_lower":"2017-09-01",
    "date:inception_upper":"2017-09-30",
    "iso:country":"GB",
    "wof:name":"B7 5JJ",
    "wof:placetype":"postalcode"
},
  "geometry": {"coordinates":[-1.870737,52.498794],"type":"Point"}
}