{
  "type": "Feature",
  "properties": {
    "date:inception_lower": "2018-08-01",
    "date:inception_upper": "2018-08-01",
    "iso:country": "GB",
    "wof:name": "NP19 4DU",
    "wof:placetype": "postalcode"
  },
  "geometry": {"coordinates":[-2.93461,51.578165],"type":"Point"}
}
