{
  "type": "Feature",
  "properties": {
    "iso:country": "GB",
    "wof:name": "NP19 4DU",
    "wof:placetype": "postalcode"
  },
  "geometry": {"coordinates":[-2.93461,51.578165],"type":"Point"}
}
