{
  "type": "Feature",
  "properties": {
    "date:inception_lower":"2002-06-01",
    "date:inception_upper":"2002-06-30",
    "iso:country":"GB",
    "wof:name":"TW1 2AG",
    "wof:placetype":"postalcode"
},
  "geometry": {"coordinates":[-0.308906,51.456682],"type":"Point"}
}