{
  "type": "Feature",
  "properties": {
    "iso:country":"GB",
    "wof:name":"TW1 2AG",
    "wof:placetype":"postalcode"
},
  "geometry": {"coordinates":[-0.30890573133335,51.4566816114348],"type":"Point"}
}