{
  "type": "Feature",
  "properties": {
    "iso:country":"GB",
    "wof:name":"PR3 2AL",
    "wof:placetype":"postalcode"
},
  "geometry": {"coordinates":[-2.63400269750492,53.82509733532671],"type":"Point"}
}