{
  "type": "Feature",
  "properties": {
    "date:inception_lower":"1980-01-01",
    "date:inception_upper":"1980-01-31",
    "iso:country":"GB",
    "wof:name":"PR3 2AL",
    "wof:placetype":"postalcode"
},
  "geometry": {"coordinates":[-2.634003,53.825097],"type":"Point"}
}