{
  "type": "Feature",
  "properties": {
    "iso:country":"GB",
    "wof:name":"DD8 4TA",
    "wof:placetype":"postalcode"
},
  "geometry": {"coordinates":[-3.00367903158244,56.68462716132372],"type":"Point"}
}