{
  "type": "Feature",
  "properties": {
    "date:inception_lower": "1980-01-01",
    "date:inception_upper": "1980-01-01",
    "iso:country": "GB",
    "wof:name": "DD8 4TA",
    "wof:placetype": "postalcode"
  },
  "geometry": {"coordinates":[-3.003679,56.684627],"type":"Point"}
}
