{
  "type": "Feature",
  "properties": {
    "iso:country": "GB",
    "wof:name": "DE7 4FU",
    "wof:placetype": "postalcode"
  },
  "geometry": {"coordinates":[-1.329805,52.953832],"type":"Point"}
}
