{
  "type": "Feature",
  "properties": {
    "iso:country": "GB",
    "wof:name": "FK20 8QW",
    "wof:placetype": "postalcode"
  },
  "geometry": {"coordinates":[-4.617995,56.392073],"type":"Point"}
}
