{
  "type": "Feature",
  "properties": {
    "iso:country":"GB",
    "wof:name":"FK20 8QW",
    "wof:placetype":"postalcode"
},
  "geometry": {"coordinates":[-4.61800918234857,56.39208346183696],"type":"Point"}
}