{
  "type": "Feature",
  "properties": {
    "iso:country":"GB",
    "wof:name":"SY18 6QA",
    "wof:placetype":"postalcode"
},
  "geometry": {"coordinates":[-3.53880143763971,52.42335094586883],"type":"Point"}
}