{
  "type": "Feature",
  "properties": {
    "iso:country": "GB",
    "wof:name": "SY18 6QA",
    "wof:placetype": "postalcode"
  },
  "geometry": {"coordinates":[-3.538801,52.423351],"type":"Point"}
}
