{
  "type": "Feature",
  "properties": {
    "iso:country":"GB",
    "wof:name":"SK4 3DZ",
    "wof:placetype":"postalcode"
},
  "geometry": {"coordinates":[-2.20341359416725,53.4115060863237],"type":"Point"}
}