{
  "type": "Feature",
  "properties": {
    "iso:country":"GB",
    "wof:name":"NE9 5DB",
    "wof:placetype":"postalcode"
},
  "geometry": {"coordinates":[-1.59676442162102,54.94561665439297],"type":"Point"}
}