{
  "type": "Feature",
  "properties": {
    "iso:country":"GB",
    "wof:name":"AL9 7PQ",
    "wof:placetype":"postalcode"
},
  "geometry": {"coordinates":[-0.21258508072791,51.73204510080186],"type":"Point"}
}