{
  "type": "Feature",
  "properties": {
    "iso:country":"GB",
    "wof:name":"GU8 6DN",
    "wof:placetype":"postalcode"
},
  "geometry": {"coordinates":[-0.71048231115101,51.17995094782282],"type":"Point"}
}