{
  "type": "Feature",
  "properties": {
    "iso:country": "GB",
    "wof:name": "GU8 6DN",
    "wof:placetype": "postalcode"
  },
  "geometry": {"coordinates":[-0.710383,51.179914],"type":"Point"}
}
