{
  "type": "Feature",
  "properties": {
    "date:inception_lower":"2004-01-01",
    "date:inception_upper":"2004-01-31",
    "iso:country":"GB",
    "wof:name":"OX18 3BH",
    "wof:placetype":"postalcode"
},
  "geometry": {"coordinates":[-1.596496,51.760255],"type":"Point"}
}