{
  "type": "Feature",
  "properties": {
    "iso:country": "GB",
    "wof:name": "CO3 3ST",
    "wof:placetype": "postalcode"
  },
  "geometry": {"coordinates":[0.870445,51.888232],"type":"Point"}
}
