{
  "type": "Feature",
  "properties": {
    "iso:country":"GB",
    "wof:name":"CO3 3ST",
    "wof:placetype":"postalcode"
},
  "geometry": {"coordinates":[0.87044539601474,51.88823220452531],"type":"Point"}
}