{
  "type": "Feature",
  "properties": {
    "iso:country":"GB",
    "wof:name":"KT6 7TB",
    "wof:placetype":"postalcode"
},
  "geometry": {"coordinates":[-0.29619823639563,51.38003466332463],"type":"Point"}
}