{
  "type": "Feature",
  "properties": {
    "date:inception_lower": "1992-01-01",
    "date:inception_upper": "1992-01-01",
    "iso:country": "GB",
    "wof:name": "LA5 9UN",
    "wof:placetype": "postalcode"
  },
  "geometry": {"coordinates":[-2.779528,54.125677],"type":"Point"}
}
