{
  "type": "Feature",
  "properties": {
    "iso:country":"GB",
    "wof:name":"LA5 9UN",
    "wof:placetype":"postalcode"
},
  "geometry": {"coordinates":[-2.77952814834482,54.12567733386869],"type":"Point"}
}