{
  "type": "Feature",
  "properties": {
    "iso:country":"GB",
    "wof:name":"NP16 6TF",
    "wof:placetype":"postalcode"
},
  "geometry": {"coordinates":[-2.68380642293067,51.69736574256918],"type":"Point"}
}