{
  "type": "Feature",
  "properties": {
    "date:inception_lower": "2024-06-01",
    "date:inception_upper": "2024-06-01",
    "iso:country": "GB",
    "wof:name": "SN25 4DQ",
    "wof:placetype": "postalcode"
  },
  "geometry": {"coordinates":[-1.790886,51.608191],"type":"Point"}
}
