{
  "type": "Feature",
  "properties": {
    "date:inception_lower": "2023-09-01",
    "date:inception_upper": "2023-09-01",
    "iso:country": "GB",
    "wof:name": "SN25 4DQ",
    "wof:placetype": "postalcode"
  },
  "geometry": {"coordinates":[-1.783947,51.603754],"type":"Point"}
}
