{
  "type": "Feature",
  "properties": {
    "iso:country":"GB",
    "wof:name":"SG4 7DS",
    "wof:placetype":"postalcode"
},
  "geometry": {"coordinates":[-0.1463144911906,51.94135147086715],"type":"Point"}
}