{
  "type": "Feature",
  "properties": {
    "iso:country":"GB",
    "wof:name":"TS19 0PD",
    "wof:placetype":"postalcode"
},
  "geometry": {"coordinates":[-1.32845271677446,54.58122434454928],"type":"Point"}
}