{
  "type": "Feature",
  "properties": {
    "date:inception_lower": "2009-11-01",
    "date:inception_upper": "2009-11-01",
    "iso:country": "GB",
    "wof:name": "IP22 2BA",
    "wof:placetype": "postalcode"
  },
  "geometry": {"coordinates":[1.053394,52.391233],"type":"Point"}
}
