{
  "type": "Feature",
  "properties": {
    "iso:country":"GB",
    "wof:name":"IP22 2BA",
    "wof:placetype":"postalcode"
},
  "geometry": {"coordinates":[1.05339439199595,52.39123322190456],"type":"Point"}
}