{
  "type": "Feature",
  "properties": {
    "iso:country": "GB",
    "wof:name": "BA4 5FG",
    "wof:placetype": "postalcode"
  },
  "geometry": {"coordinates":[-2.534912,51.186955],"type":"Point"}
}
