{
  "type": "Feature",
  "properties": {
    "iso:country":"GB",
    "wof:name":"BA4 5FG",
    "wof:placetype":"postalcode"
},
  "geometry": {"coordinates":[-2.53491208877353,51.18695461751871],"type":"Point"}
}