{
  "type": "Feature",
  "properties": {
    "iso:country":"GB",
    "wof:name":"ST8 7RT",
    "wof:placetype":"postalcode"
},
  "geometry": {"coordinates":[-2.14336172343405,53.13055980628489],"type":"Point"}
}