{
  "type": "Feature",
  "properties": {
    "iso:country": "GB",
    "wof:name": "ST8 7RT",
    "wof:placetype": "postalcode"
  },
  "geometry": {"coordinates":[-2.143362,53.13056],"type":"Point"}
}
