{
  "type": "Feature",
  "properties": {
    "date:inception_lower":"2002-06-01",
    "date:inception_upper":"2002-06-30",
    "iso:country":"GB",
    "wof:name":"SG1 6BW",
    "wof:placetype":"postalcode"
},
  "geometry": {"coordinates":[-0.164199,51.929493],"type":"Point"}
}