{
  "type": "Feature",
  "properties": {
    "iso:country": "GB",
    "wof:name": "SG1 6BW",
    "wof:placetype": "postalcode"
  },
  "geometry": {"coordinates":[-0.164199,51.929493],"type":"Point"}
}
