{
  "type": "Feature",
  "properties": {
    "iso:country":"GB",
    "wof:name":"SG1 6BW",
    "wof:placetype":"postalcode"
},
  "geometry": {"coordinates":[-0.16419909546194,51.92949268625519],"type":"Point"}
}