{
  "type": "Feature",
  "properties": {
    "iso:country":"GB",
    "wof:name":"E8 1BG",
    "wof:placetype":"postalcode"
},
  "geometry": {"coordinates":[-0.06155424556527,51.54571043550185],"type":"Point"}
}