{
  "type": "Feature",
  "properties": {
    "date:inception_lower": "2000-12-01",
    "date:inception_upper": "2000-12-01",
    "iso:country": "GB",
    "wof:name": "NN4 6RZ",
    "wof:placetype": "postalcode"
  },
  "geometry": {"coordinates":[-0.885104,52.207969],"type":"Point"}
}
