{
  "type": "Feature",
  "properties": {
    "iso:country":"GB",
    "wof:name":"NN4 6RZ",
    "wof:placetype":"postalcode"
},
  "geometry": {"coordinates":[-0.8851039695689,52.2079693484414],"type":"Point"}
}