{
  "type": "Feature",
  "properties": {
    "iso:country":"GB",
    "wof:name":"UB4 8JR",
    "wof:placetype":"postalcode"
},
  "geometry": {"coordinates":[-0.4383215517483,51.52705147875177],"type":"Point"}
}