{
  "type": "Feature",
  "properties": {
    "date:inception_lower":"1980-01-01",
    "date:inception_upper":"1980-01-31",
    "iso:country":"GB",
    "wof:name":"NE66 1JQ",
    "wof:placetype":"postalcode"
},
  "geometry": {"coordinates":[-1.708699,55.4151],"type":"Point"}
}