{
  "type": "Feature",
  "properties": {
    "date:inception_lower": "1980-01-01",
    "date:inception_upper": "1980-01-01",
    "iso:country": "GB",
    "wof:name": "LS10 3JS",
    "wof:placetype": "postalcode"
  },
  "geometry": {"coordinates":[-1.520173,53.756598],"type":"Point"}
}
