{
  "type": "Feature",
  "properties": {
    "iso:country":"GB",
    "wof:name":"B28 9AL",
    "wof:placetype":"postalcode"
},
  "geometry": {"coordinates":[-1.82651486426229,52.42530204596201],"type":"Point"}
}