{
  "type": "Feature",
  "properties": {
    "date:inception_lower": "2009-05-01",
    "date:inception_upper": "2009-05-01",
    "iso:country": "GB",
    "wof:name": "B28 9AL",
    "wof:placetype": "postalcode"
  },
  "geometry": {"coordinates":[-1.826515,52.425302],"type":"Point"}
}
