{
  "type": "Feature",
  "properties": {
    "iso:country":"GB",
    "wof:name":"NP25 3TH",
    "wof:placetype":"postalcode"
},
  "geometry": {"coordinates":[-2.69910580968912,51.80934234460961],"type":"Point"}
}