{
  "type": "Feature",
  "properties": {
    "iso:country":"GB",
    "wof:name":"FY2 0NS",
    "wof:placetype":"postalcode"
},
  "geometry": {"coordinates":[-3.03235635837825,53.84434216708991],"type":"Point"}
}