{
  "type": "Feature",
  "properties": {
    "iso:country":"GB",
    "wof:name":"YO26 5PQ",
    "wof:placetype":"postalcode"
},
  "geometry": {"coordinates":[-1.13251767796213,53.96824037221491],"type":"Point"}
}