{
  "type": "Feature",
  "properties": {
    "iso:country":"GB",
    "wof:name":"TR13 0NH",
    "wof:placetype":"postalcode"
},
  "geometry": {"coordinates":[-5.23348042792781,50.11993322747291],"type":"Point"}
}