{
  "type": "Feature",
  "properties": {
    "iso:country": "GB",
    "wof:name": "NR33 8PZ",
    "wof:placetype": "postalcode"
  },
  "geometry": {"coordinates":[1.706065,52.464489],"type":"Point"}
}
