{
  "type": "Feature",
  "properties": {
    "date:inception_lower":"2011-06-01",
    "date:inception_upper":"2011-06-30",
    "iso:country":"GB",
    "wof:name":"NR33 8PZ",
    "wof:placetype":"postalcode"
},
  "geometry": {"coordinates":[1.706065,52.464489],"type":"Point"}
}