{
  "type": "Feature",
  "properties": {
    "date:inception_lower":"1994-05-01",
    "date:inception_upper":"1994-05-31",
    "iso:country":"GB",
    "wof:name":"LS7 2TG",
    "wof:placetype":"postalcode"
},
  "geometry": {"coordinates":[-1.562551,53.829438],"type":"Point"}
}