{
  "type": "Feature",
  "properties": {
    "date:inception_lower": "2021-12-01",
    "date:inception_upper": "2021-12-01",
    "iso:country": "GB",
    "wof:name": "PL9 8LZ",
    "wof:placetype": "postalcode"
  },
  "geometry": {"coordinates":[-4.049591,50.367746],"type":"Point"}
}
