{
  "type": "Feature",
  "properties": {
    "date:inception_lower":"2013-11-01",
    "date:inception_upper":"2013-11-30",
    "iso:country":"GB",
    "wof:name":"LS20 9FB",
    "wof:placetype":"postalcode"
},
  "geometry": {"coordinates":[-1.7154,53.878037],"type":"Point"}
}