{
  "type": "Feature",
  "properties": {
    "iso:country":"GB",
    "wof:name":"W1F 9UW",
    "wof:placetype":"postalcode"
},
  "geometry": {"coordinates":[-0.13558830230104,51.51138101134998],"type":"Point"}
}