{
  "type": "Feature",
  "properties": {
    "date:inception_lower": "2012-05-01",
    "date:inception_upper": "2012-05-01",
    "iso:country": "GB",
    "wof:name": "NG33 5GG",
    "wof:placetype": "postalcode"
  },
  "geometry": {"coordinates":[-0.626669,52.808756],"type":"Point"}
}
