{
  "type": "Feature",
  "properties": {
    "iso:country":"GB",
    "wof:name":"NG33 5GG",
    "wof:placetype":"postalcode"
},
  "geometry": {"coordinates":[-0.62666897140539,52.80875601346174],"type":"Point"}
}