{
  "type": "Feature",
  "properties": {
    "iso:country": "GB",
    "wof:name": "DL8 4JX",
    "wof:placetype": "postalcode"
  },
  "geometry": {"coordinates":[-1.974934,54.275099],"type":"Point"}
}
