{
  "type": "Feature",
  "properties": {
    "iso:country":"GB",
    "wof:name":"DL8 4JX",
    "wof:placetype":"postalcode"
},
  "geometry": {"coordinates":[-1.9749343600705,54.2750985819145],"type":"Point"}
}