{
  "type": "Feature",
  "properties": {
    "iso:country":"GB",
    "wof:name":"SL2 2AN",
    "wof:placetype":"postalcode"
},
  "geometry": {"coordinates":[-0.6380704827141,51.53415316690513],"type":"Point"}
}