{
  "type": "Feature",
  "properties": {
    "iso:country": "GB",
    "wof:name": "SL2 2AN",
    "wof:placetype": "postalcode"
  },
  "geometry": {"coordinates":[-0.63807,51.534153],"type":"Point"}
}
