{
  "type": "Feature",
  "properties": {
    "iso:country":"GB",
    "wof:name":"DL13 2WX",
    "wof:placetype":"postalcode"
},
  "geometry": {"coordinates":[-1.99802665430763,54.74205979150337],"type":"Point"}
}