{
  "type": "Feature",
  "properties": {
    "date:inception_lower": "2014-11-01",
    "date:inception_upper": "2014-11-01",
    "iso:country": "GB",
    "wof:name": "DL13 2WX",
    "wof:placetype": "postalcode"
  },
  "geometry": {"coordinates":[-1.998027,54.74206],"type":"Point"}
}
