{
  "type": "Feature",
  "properties": {
    "iso:country":"GB",
    "wof:name":"OL4 5QA",
    "wof:placetype":"postalcode"
},
  "geometry": {"coordinates":[-2.0717825221358,53.52856184856647],"type":"Point"}
}