{
  "type": "Feature",
  "properties": {
    "date:inception_lower": "1980-01-01",
    "date:inception_upper": "1980-01-01",
    "iso:country": "GB",
    "wof:name": "OL4 5QA",
    "wof:placetype": "postalcode"
  },
  "geometry": {"coordinates":[-2.071782,53.528562],"type":"Point"}
}
