{
  "type": "Feature",
  "properties": {
    "date:inception_lower": "2021-12-01",
    "date:inception_upper": "2021-12-01",
    "iso:country": "GB",
    "wof:name": "CH44 8AX",
    "wof:placetype": "postalcode"
  },
  "geometry": {"coordinates":[-3.029815,53.423335],"type":"Point"}
}
