{
  "type": "Feature",
  "properties": {
    "iso:country":"GB",
    "wof:name":"NW1 8SY",
    "wof:placetype":"postalcode"
},
  "geometry": {"coordinates":[-0.14623432886458,51.54448921211164],"type":"Point"}
}