{
  "type": "Feature",
  "properties": {
    "date:inception_lower": "1980-01-01",
    "date:inception_upper": "1980-01-01",
    "iso:country": "GB",
    "wof:name": "NW1 8SY",
    "wof:placetype": "postalcode"
  },
  "geometry": {"coordinates":[-0.146234,51.544489],"type":"Point"}
}
