{
  "type": "Feature",
  "properties": {
    "iso:country": "GB",
    "wof:name": "LA5 0AD",
    "wof:placetype": "postalcode"
  },
  "geometry": {"coordinates":[-2.837455,54.200507],"type":"Point"}
}
