{
  "type": "Feature",
  "properties": {
    "iso:country": "GB",
    "wof:name": "LL21 0RB",
    "wof:placetype": "postalcode"
  },
  "geometry": {"coordinates":[-3.545211,52.982511],"type":"Point"}
}
