{
  "type": "Feature",
  "properties": {
    "iso:country":"GB",
    "wof:name":"WV12 5JL",
    "wof:placetype":"postalcode"
},
  "geometry": {"coordinates":[-2.02823945477632,52.61387170905952],"type":"Point"}
}