{
  "type": "Feature",
  "properties": {
    "iso:country": "GB",
    "wof:name": "WV12 5JL",
    "wof:placetype": "postalcode"
  },
  "geometry": {"coordinates":[-2.028239,52.613872],"type":"Point"}
}
