{
  "type": "Feature",
  "properties": {
    "date:inception_lower": "1981-06-01",
    "date:inception_upper": "1981-06-01",
    "iso:country": "GB",
    "wof:name": "CT6 8HT",
    "wof:placetype": "postalcode"
  },
  "geometry": {"coordinates":[1.102039,51.369739],"type":"Point"}
}
