{
  "type": "Feature",
  "properties": {
    "iso:country": "GB",
    "wof:name": "CF48 3SG",
    "wof:placetype": "postalcode"
  },
  "geometry": {"coordinates":[-3.357716,51.765236],"type":"Point"}
}
