{
  "type": "Feature",
  "properties": {
    "iso:country":"GB",
    "wof:name":"CF48 3SG",
    "wof:placetype":"postalcode"
},
  "geometry": {"coordinates":[-3.35776283387645,51.76520395507905],"type":"Point"}
}