{
  "type": "Feature",
  "properties": {
    "iso:country":"GB",
    "wof:name":"B21 0AT",
    "wof:placetype":"postalcode"
},
  "geometry": {"coordinates":[-1.95499008727959,52.50776865550356],"type":"Point"}
}