{
  "type": "Feature",
  "properties": {
    "iso:country": "GB",
    "wof:name": "LN5 7BN",
    "wof:placetype": "postalcode"
  },
  "geometry": {"coordinates":[-0.542458,53.225105],"type":"Point"}
}
