{
  "type": "Feature",
  "properties": {
    "iso:country": "GB",
    "wof:name": "GL19 3NQ",
    "wof:placetype": "postalcode"
  },
  "geometry": {"coordinates":[-2.336473,51.9861],"type":"Point"}
}
