{
  "type": "Feature",
  "properties": {
    "iso:country": "GB",
    "wof:name": "CT16 3FP",
    "wof:placetype": "postalcode"
  },
  "geometry": {"coordinates":[1.307447,51.160385],"type":"Point"}
}
