{
  "type": "Feature",
  "properties": {
    "date:inception_lower": "1991-01-01",
    "date:inception_upper": "1991-01-01",
    "iso:country": "GB",
    "wof:name": "DA11 0BX",
    "wof:placetype": "postalcode"
  },
  "geometry": {"coordinates":[0.368732,51.44501],"type":"Point"}
}
