{
  "type": "Feature",
  "properties": {
    "iso:country":"GB",
    "wof:name":"NW7 2HA",
    "wof:placetype":"postalcode"
},
  "geometry": {"coordinates":[-0.21620508296235,51.61351997802692],"type":"Point"}
}