{
  "type": "Feature",
  "properties": {
    "iso:country":"GB",
    "wof:name":"L24 5RF",
    "wof:placetype":"postalcode"
},
  "geometry": {"coordinates":[-2.81855122294146,53.33723148956089],"type":"Point"}
}