{
  "type": "Feature",
  "properties": {
    "iso:country":"GB",
    "wof:name":"EX6 7AF",
    "wof:placetype":"postalcode"
},
  "geometry": {"coordinates":[-3.67670332274343,50.70258141094078],"type":"Point"}
}