{
  "type": "Feature",
  "properties": {
    "iso:country":"GB",
    "wof:name":"RG21 4PT",
    "wof:placetype":"postalcode"
},
  "geometry": {"coordinates":[-1.07127655244305,51.26574770078099],"type":"Point"}
}