{
  "type": "Feature",
  "properties": {
    "date:inception_lower":"2015-02-01",
    "date:inception_upper":"2015-02-28",
    "iso:country":"GB",
    "wof:name":"LD3 0DX",
    "wof:placetype":"postalcode"
},
  "geometry": {"coordinates":[-3.235041,51.99698],"type":"Point"}
}