{
  "type": "Feature",
  "properties": {
    "iso:country":"GB",
    "wof:name":"LD3 0DX",
    "wof:placetype":"postalcode"
},
  "geometry": {"coordinates":[-3.23504062935324,51.99697964680807],"type":"Point"}
}