{
  "type": "Feature",
  "properties": {
    "iso:country": "GB",
    "wof:name": "LD3 0DX",
    "wof:placetype": "postalcode"
  },
  "geometry": {"coordinates":[-3.235041,51.99698],"type":"Point"}
}
