{
  "type": "Feature",
  "properties": {
    "iso:country": "GB",
    "wof:name": "IP8 4HP",
    "wof:placetype": "postalcode"
  },
  "geometry": {"coordinates":[1.100383,52.077085],"type":"Point"}
}
