{
  "type": "Feature",
  "properties": {
    "iso:country": "GB",
    "wof:name": "EX31 4LH",
    "wof:placetype": "postalcode"
  },
  "geometry": {"coordinates":[-4.137161,51.100622],"type":"Point"}
}
