{
  "type": "Feature",
  "properties": {
    "iso:country": "GB",
    "wof:name": "CA12 4BQ",
    "wof:placetype": "postalcode"
  },
  "geometry": {"coordinates":[-3.123887,54.595722],"type":"Point"}
}
