{
  "type": "Feature",
  "properties": {
    "date:inception_lower": "1980-01-01",
    "date:inception_upper": "1980-01-01",
    "iso:country": "GB",
    "wof:name": "KY8 2DZ",
    "wof:placetype": "postalcode"
  },
  "geometry": {"coordinates":[-3.038702,56.185487],"type":"Point"}
}
