{
  "type": "Feature",
  "properties": {
    "iso:country": "GB",
    "wof:name": "PE7 8PN",
    "wof:placetype": "postalcode"
  },
  "geometry": {"coordinates":[-0.260872,52.537734],"type":"Point"}
}
