{
  "type": "Feature",
  "properties": {
    "iso:country": "GB",
    "wof:name": "PA19 1FR",
    "wof:placetype": "postalcode"
  },
  "geometry": {"coordinates":[-4.833689,55.951592],"type":"Point"}
}
