{
  "type": "Feature",
  "properties": {
    "date:inception_lower": "2017-12-01",
    "date:inception_upper": "2017-12-01",
    "iso:country": "GB",
    "wof:name": "PA19 1FR",
    "wof:placetype": "postalcode"
  },
  "geometry": {"coordinates":[-4.833689,55.951592],"type":"Point"}
}
