{
  "type": "Feature",
  "properties": {
    "date:inception_lower":"1981-06-01",
    "date:inception_upper":"1981-06-30",
    "iso:country":"GB",
    "wof:name":"SP6 1QP",
    "wof:placetype":"postalcode"
},
  "geometry": {"coordinates":[-1.790667,50.932255],"type":"Point"}
}