{
  "type": "Feature",
  "properties": {
    "iso:country": "GB",
    "wof:name": "NG31 9NQ",
    "wof:placetype": "postalcode"
  },
  "geometry": {"coordinates":[-0.615394,52.917795],"type":"Point"}
}
