{
  "type": "Feature",
  "properties": {
    "iso:country":"GB",
    "wof:name":"DN18 5PG",
    "wof:placetype":"postalcode"
},
  "geometry": {"coordinates":[-0.44213403742482,53.68523254552142],"type":"Point"}
}