{
  "type": "Feature",
  "properties": {
    "date:inception_lower":"1980-01-01",
    "date:inception_upper":"1980-01-31",
    "iso:country":"GB",
    "wof:name":"LE15 7PS",
    "wof:placetype":"postalcode"
},
  "geometry": {"coordinates":[-0.685333,52.738308],"type":"Point"}
}