{
  "type": "Feature",
  "properties": {
    "date:inception_lower": "1980-01-01",
    "date:inception_upper": "1980-01-01",
    "iso:country": "GB",
    "wof:name": "BB7 2PZ",
    "wof:placetype": "postalcode"
  },
  "geometry": {"coordinates":[-2.40345,53.86592],"type":"Point"}
}
