{
  "type": "Feature",
  "properties": {
    "iso:country":"GB",
    "wof:name":"BB7 2PZ",
    "wof:placetype":"postalcode"
},
  "geometry": {"coordinates":[-2.40345002004021,53.86592032511264],"type":"Point"}
}