{
  "type": "Feature",
  "properties": {
    "date:inception_lower": "2022-02-01",
    "date:inception_upper": "2022-02-01",
    "iso:country": "GB",
    "wof:name": "SE16 7FF",
    "wof:placetype": "postalcode"
  },
  "geometry": {"coordinates":[-0.035321,51.49248],"type":"Point"}
}
