{
  "type": "Feature",
  "properties": {
    "iso:country":"GB",
    "wof:name":"SE16 7FF",
    "wof:placetype":"postalcode"
},
  "geometry": {"coordinates":[-0.03675773009415,51.49285312554609],"type":"Point"}
}