{
  "type": "Feature",
  "properties": {
    "date:inception_lower": "2017-10-01",
    "date:inception_upper": "2017-10-01",
    "iso:country": "GB",
    "wof:name": "PL5 3FD",
    "wof:placetype": "postalcode"
  },
  "geometry": {"coordinates":[-4.14721,50.408484],"type":"Point"}
}
