{
  "type": "Feature",
  "properties": {
    "iso:country":"GB",
    "wof:name":"KY16 8RD",
    "wof:placetype":"postalcode"
},
  "geometry": {"coordinates":[-2.82231107605111,56.32932515845619],"type":"Point"}
}