{
  "type": "Feature",
  "properties": {
    "iso:country":"GB",
    "wof:name":"OX1 3PH",
    "wof:placetype":"postalcode"
},
  "geometry": {"coordinates":[-1.25936327274688,51.76042199108576],"type":"Point"}
}