{
  "type": "Feature",
  "properties": {
    "date:inception_lower": "1980-01-01",
    "date:inception_upper": "1980-01-01",
    "iso:country": "GB",
    "wof:name": "OX1 3PH",
    "wof:placetype": "postalcode"
  },
  "geometry": {"coordinates":[-1.259363,51.760422],"type":"Point"}
}
