{
  "type": "Feature",
  "properties": {
    "iso:country": "GB",
    "wof:name": "CF83 1NQ",
    "wof:placetype": "postalcode"
  },
  "geometry": {"coordinates":[-3.230951,51.567372],"type":"Point"}
}
