{
  "type": "Feature",
  "properties": {
    "iso:country":"GB",
    "wof:name":"WN6 0GH",
    "wof:placetype":"postalcode"
},
  "geometry": {"coordinates":[-2.66967382247754,53.58957240832535],"type":"Point"}
}