{
  "type": "Feature",
  "properties": {
    "iso:country": "GB",
    "wof:name": "WN6 0GH",
    "wof:placetype": "postalcode"
  },
  "geometry": {"coordinates":[-2.669674,53.589572],"type":"Point"}
}
