{
  "type": "Feature",
  "properties": {
    "iso:country":"GB",
    "wof:name":"CF62 4QP",
    "wof:placetype":"postalcode"
},
  "geometry": {"coordinates":[-3.436365472942,51.41795292990434],"type":"Point"}
}