{
  "type": "Feature",
  "properties": {
    "date:inception_lower": "1999-12-01",
    "date:inception_upper": "1999-12-01",
    "iso:country": "GB",
    "wof:name": "DT9 4HT",
    "wof:placetype": "postalcode"
  },
  "geometry": {"coordinates":[-2.518328,50.955759],"type":"Point"}
}
