{
  "type": "Feature",
  "properties": {
    "iso:country": "GB",
    "wof:name": "RM12 5BJ",
    "wof:placetype": "postalcode"
  },
  "geometry": {"coordinates":[0.202442,51.547582],"type":"Point"}
}
