{
  "type": "Feature",
  "properties": {
    "date:inception_lower": "2000-10-01",
    "date:inception_upper": "2000-10-01",
    "iso:country": "GB",
    "wof:name": "WD19 5DH",
    "wof:placetype": "postalcode"
  },
  "geometry": {"coordinates":[-0.378782,51.630939],"type":"Point"}
}
