{
  "type": "Feature",
  "properties": {
    "iso:country":"GB",
    "wof:name":"WD19 5DH",
    "wof:placetype":"postalcode"
},
  "geometry": {"coordinates":[-0.37878165874927,51.63093948652494],"type":"Point"}
}