{
  "type": "Feature",
  "properties": {
    "iso:country":"GB",
    "wof:name":"PL21 0UL",
    "wof:placetype":"postalcode"
},
  "geometry": {"coordinates":[-3.91873106489333,50.38592236806808],"type":"Point"}
}