{
  "type": "Feature",
  "properties": {
    "iso:country": "GB",
    "wof:name": "PL21 0UL",
    "wof:placetype": "postalcode"
  },
  "geometry": {"coordinates":[-3.918731,50.385922],"type":"Point"}
}
