{
  "type": "Feature",
  "properties": {
    "iso:country": "GB",
    "wof:name": "KY1 1UR",
    "wof:placetype": "postalcode"
  },
  "geometry": {"coordinates":[-3.165539,56.109061],"type":"Point"}
}
