{
  "type": "Feature",
  "properties": {
    "iso:country":"GB",
    "wof:name":"RH16 1BL",
    "wof:placetype":"postalcode"
},
  "geometry": {"coordinates":[-0.1069440545156,51.00255360541857],"type":"Point"}
}