{
  "type": "Feature",
  "properties": {
    "iso:country": "GB",
    "wof:name": "IG11 9YA",
    "wof:placetype": "postalcode"
  },
  "geometry": {"coordinates":[0.095108,51.542352],"type":"Point"}
}
