{
  "type": "Feature",
  "properties": {
    "iso:country": "GB",
    "wof:name": "RG40 1TX",
    "wof:placetype": "postalcode"
  },
  "geometry": {"coordinates":[-0.827939,51.41439],"type":"Point"}
}
