{
  "type": "Feature",
  "properties": {
    "iso:country":"GB",
    "wof:name":"TQ8 8HQ",
    "wof:placetype":"postalcode"
},
  "geometry": {"coordinates":[-3.76870418094932,50.23683181827329],"type":"Point"}
}