{
  "type": "Feature",
  "properties": {
    "iso:country": "GB",
    "wof:name": "TQ8 8HQ",
    "wof:placetype": "postalcode"
  },
  "geometry": {"coordinates":[-3.768704,50.236832],"type":"Point"}
}
