{
  "type": "Feature",
  "properties": {
    "iso:country": "GB",
    "wof:name": "CR5 3DE",
    "wof:placetype": "postalcode"
  },
  "geometry": {"coordinates":[-0.151378,51.314728],"type":"Point"}
}
