{
  "type": "Feature",
  "properties": {
    "iso:country":"GB",
    "wof:name":"CR5 3DE",
    "wof:placetype":"postalcode"
},
  "geometry": {"coordinates":[-0.15137782557072,51.31472825569919],"type":"Point"}
}