{
  "type": "Feature",
  "properties": {
    "iso:country":"GB",
    "wof:name":"LE9 4TS",
    "wof:placetype":"postalcode"
},
  "geometry": {"coordinates":[-1.27583021198126,52.54842771205752],"type":"Point"}
}