{
  "type": "Feature",
  "properties": {
    "iso:country": "GB",
    "wof:name": "BN41 1XR",
    "wof:placetype": "postalcode"
  },
  "geometry": {"coordinates":[-0.210215,50.838103],"type":"Point"}
}
