{
  "type": "Feature",
  "properties": {
    "iso:country":"GB",
    "wof:name":"NE17 7QD",
    "wof:placetype":"postalcode"
},
  "geometry": {"coordinates":[-1.83604407066076,54.90544842220417],"type":"Point"}
}