{
  "type": "Feature",
  "properties": {
    "date:inception_lower": "1980-01-01",
    "date:inception_upper": "1980-01-01",
    "iso:country": "GB",
    "wof:name": "NE17 7QD",
    "wof:placetype": "postalcode"
  },
  "geometry": {"coordinates":[-1.836044,54.905448],"type":"Point"}
}
