{
  "type": "Feature",
  "properties": {
    "iso:country": "GB",
    "wof:name": "NE17 7QD",
    "wof:placetype": "postalcode"
  },
  "geometry": {"coordinates":[-1.836044,54.905448],"type":"Point"}
}
