{
  "type": "Feature",
  "properties": {
    "iso:country":"GB",
    "wof:name":"OX2 7RF",
    "wof:placetype":"postalcode"
},
  "geometry": {"coordinates":[-1.27069281477201,51.7874664367162],"type":"Point"}
}