{
  "type": "Feature",
  "properties": {
    "iso:country": "GB",
    "wof:name": "OX2 7RF",
    "wof:placetype": "postalcode"
  },
  "geometry": {"coordinates":[-1.270693,51.787466],"type":"Point"}
}
