{
  "type": "Feature",
  "properties": {
    "iso:country":"GB",
    "wof:name":"WA14 4EN",
    "wof:placetype":"postalcode"
},
  "geometry": {"coordinates":[-2.35995896938823,53.39535252258452],"type":"Point"}
}