{
  "type": "Feature",
  "properties": {
    "iso:country": "GB",
    "wof:name": "WA14 4EN",
    "wof:placetype": "postalcode"
  },
  "geometry": {"coordinates":[-2.359959,53.395353],"type":"Point"}
}
