{
  "type": "Feature",
  "properties": {
    "iso:country": "GB",
    "wof:name": "CH1 5HU",
    "wof:placetype": "postalcode"
  },
  "geometry": {"coordinates":[-2.932365,53.208688],"type":"Point"}
}
