{
  "type": "Feature",
  "properties": {
    "iso:country":"GB",
    "wof:name":"CH1 5HU",
    "wof:placetype":"postalcode"
},
  "geometry": {"coordinates":[-2.93235025988753,53.20868835539951],"type":"Point"}
}