{
  "type": "Feature",
  "properties": {
    "iso:country": "GB",
    "wof:name": "NG18 1EB",
    "wof:placetype": "postalcode"
  },
  "geometry": {"coordinates":[-1.195871,53.142334],"type":"Point"}
}
