{
  "type": "Feature",
  "properties": {
    "iso:country":"GB",
    "wof:name":"NG18 1EB",
    "wof:placetype":"postalcode"
},
  "geometry": {"coordinates":[-1.19600544788972,53.14246042419084],"type":"Point"}
}