{
  "type": "Feature",
  "properties": {
    "date:inception_lower": "1980-01-01",
    "date:inception_upper": "1980-01-01",
    "iso:country": "GB",
    "wof:name": "NG18 1EB",
    "wof:placetype": "postalcode"
  },
  "geometry": {"coordinates":[-1.195871,53.142334],"type":"Point"}
}
