{
  "type": "Feature",
  "properties": {
    "iso:country":"GB",
    "wof:name":"BH31 6EY",
    "wof:placetype":"postalcode"
},
  "geometry": {"coordinates":[-1.87309655456241,50.87661150885693],"type":"Point"}
}