{
  "type": "Feature",
  "properties": {
    "iso:country":"GB",
    "wof:name":"S62 6NT",
    "wof:placetype":"postalcode"
},
  "geometry": {"coordinates":[-1.34286954674923,53.45958068337702],"type":"Point"}
}