{
  "type": "Feature",
  "properties": {
    "date:inception_lower": "2022-11-01",
    "date:inception_upper": "2022-11-01",
    "iso:country": "GB",
    "wof:name": "EX17 4BP",
    "wof:placetype": "postalcode"
  },
  "geometry": {"coordinates":[-3.603166,50.845306],"type":"Point"}
}
