{
  "type": "Feature",
  "properties": {
    "iso:country":"GB",
    "wof:name":"SK11 6UT",
    "wof:placetype":"postalcode"
},
  "geometry": {"coordinates":[-2.12702873554756,53.2577260290195],"type":"Point"}
}