{
  "type": "Feature",
  "properties": {
    "iso:country": "GB",
    "wof:name": "SK11 6UT",
    "wof:placetype": "postalcode"
  },
  "geometry": {"coordinates":[-2.127074,53.257726],"type":"Point"}
}
