{
  "type": "Feature",
  "properties": {
    "iso:country":"GB",
    "wof:name":"CF62 8AQ",
    "wof:placetype":"postalcode"
},
  "geometry": {"coordinates":[-3.29652224281371,51.41795611068761],"type":"Point"}
}