{
  "type": "Feature",
  "properties": {
    "date:inception_lower": "1993-01-01",
    "date:inception_upper": "1993-01-01",
    "iso:country": "GB",
    "wof:name": "CF62 8AQ",
    "wof:placetype": "postalcode"
  },
  "geometry": {"coordinates":[-3.296522,51.417956],"type":"Point"}
}
