{
  "type": "Feature",
  "properties": {
    "iso:country":"GB",
    "wof:name":"B66 3TJ",
    "wof:placetype":"postalcode"
},
  "geometry": {"coordinates":[-1.95346051971423,52.4911636688142],"type":"Point"}
}