{
  "type": "Feature",
  "properties": {
    "iso:country":"GB",
    "wof:name":"CA8 7HJ",
    "wof:placetype":"postalcode"
},
  "geometry": {"coordinates":[-2.53491087756959,54.98384676373237],"type":"Point"}
}