{
  "type": "Feature",
  "properties": {
    "iso:country":"GB",
    "wof:name":"NE28 7BP",
    "wof:placetype":"postalcode"
},
  "geometry": {"coordinates":[-1.51246375328027,54.99721295099407],"type":"Point"}
}