{
  "type": "Feature",
  "properties": {
    "date:inception_lower": "1980-01-01",
    "date:inception_upper": "1980-01-01",
    "iso:country": "GB",
    "wof:name": "NE28 7BP",
    "wof:placetype": "postalcode"
  },
  "geometry": {"coordinates":[-1.512464,54.997213],"type":"Point"}
}
