{
  "type": "Feature",
  "properties": {
    "iso:country": "GB",
    "wof:name": "NE28 7BP",
    "wof:placetype": "postalcode"
  },
  "geometry": {"coordinates":[-1.512464,54.997213],"type":"Point"}
}
