{
  "type": "Feature",
  "properties": {
    "iso:country":"GB",
    "wof:name":"LS19 7HX",
    "wof:placetype":"postalcode"
},
  "geometry": {"coordinates":[-1.70090228865675,53.86552621224646],"type":"Point"}
}