{
  "type": "Feature",
  "properties": {
    "iso:country": "GB",
    "wof:name": "CV11 6HP",
    "wof:placetype": "postalcode"
  },
  "geometry": {"coordinates":[-1.443236,52.531299],"type":"Point"}
}
