{
  "type": "Feature",
  "properties": {
    "iso:country":"GB",
    "wof:name":"CV11 6HP",
    "wof:placetype":"postalcode"
},
  "geometry": {"coordinates":[-1.44323617091479,52.5312990894483],"type":"Point"}
}