{
  "type": "Feature",
  "properties": {
    "date:inception_lower": "1980-01-01",
    "date:inception_upper": "1980-01-01",
    "iso:country": "GB",
    "wof:name": "CV11 6HP",
    "wof:placetype": "postalcode"
  },
  "geometry": {"coordinates":[-1.443236,52.531299],"type":"Point"}
}
