{
  "type": "Feature",
  "properties": {
    "iso:country":"GB",
    "wof:name":"SS4 1QP",
    "wof:placetype":"postalcode"
},
  "geometry": {"coordinates":[0.70405197296094,51.5888096303124],"type":"Point"}
}