{
  "type": "Feature",
  "properties": {
    "iso:country":"GB",
    "wof:name":"OX5 1JJ",
    "wof:placetype":"postalcode"
},
  "geometry": {"coordinates":[-1.3113933168996,51.84710714262568],"type":"Point"}
}