{
  "type": "Feature",
  "properties": {
    "iso:country": "GB",
    "wof:name": "OX5 1JJ",
    "wof:placetype": "postalcode"
  },
  "geometry": {"coordinates":[-1.311393,51.847107],"type":"Point"}
}
