{
  "type": "Feature",
  "properties": {
    "iso:country":"GB",
    "wof:name":"MK16 9BQ",
    "wof:placetype":"postalcode"
},
  "geometry": {"coordinates":[-0.71991376215593,52.08538208447084],"type":"Point"}
}