{
  "type": "Feature",
  "properties": {
    "iso:country":"GB",
    "wof:name":"B18 5JD",
    "wof:placetype":"postalcode"
},
  "geometry": {"coordinates":[-1.92309942850963,52.49521135309858],"type":"Point"}
}