{
  "type": "Feature",
  "properties": {
    "iso:country":"GB",
    "wof:name":"S21 1JN",
    "wof:placetype":"postalcode"
},
  "geometry": {"coordinates":[-1.32150289820206,53.31926371126377],"type":"Point"}
}