{
  "type": "Feature",
  "properties": {
    "iso:country": "GB",
    "wof:name": "S21 1JN",
    "wof:placetype": "postalcode"
  },
  "geometry": {"coordinates":[-1.321503,53.319264],"type":"Point"}
}
