{
  "type": "Feature",
  "properties": {
    "date:inception_lower": "1980-01-01",
    "date:inception_upper": "1980-01-01",
    "iso:country": "GB",
    "wof:name": "NN6 8LN",
    "wof:placetype": "postalcode"
  },
  "geometry": {"coordinates":[-0.983794,52.326194],"type":"Point"}
}
