{
  "type": "Feature",
  "properties": {
    "iso:country":"GB",
    "wof:name":"NN6 8LN",
    "wof:placetype":"postalcode"
},
  "geometry": {"coordinates":[-0.98341186540131,52.32621175541423],"type":"Point"}
}