{
  "type": "Feature",
  "properties": {
    "date:inception_lower":"1980-01-01",
    "date:inception_upper":"1980-01-31",
    "iso:country":"GB",
    "wof:name":"ME10 4PS",
    "wof:placetype":"postalcode"
},
  "geometry": {"coordinates":[0.738948,51.333963],"type":"Point"}
}