{
  "type": "Feature",
  "properties": {
    "iso:country":"GB",
    "wof:name":"ME10 4PS",
    "wof:placetype":"postalcode"
},
  "geometry": {"coordinates":[0.73893090115021,51.33396111808725],"type":"Point"}
}