{
  "type": "Feature",
  "properties": {
    "iso:country":"GB",
    "wof:name":"KT2 7SS",
    "wof:placetype":"postalcode"
},
  "geometry": {"coordinates":[-0.28660821236374,51.41980355822264],"type":"Point"}
}