{
  "type": "Feature",
  "properties": {
    "iso:country":"GB",
    "wof:name":"HU6 9AY",
    "wof:placetype":"postalcode"
},
  "geometry": {"coordinates":[-0.3878880614421,53.78913898097261],"type":"Point"}
}