{
  "type": "Feature",
  "properties": {
    "iso:country":"GB",
    "wof:name":"PE28 2NQ",
    "wof:placetype":"postalcode"
},
  "geometry": {"coordinates":[-0.15507640328332,52.40254141218929],"type":"Point"}
}