{
  "type": "Feature",
  "properties": {
    "iso:country":"GB",
    "wof:name":"BA1 8AP",
    "wof:placetype":"postalcode"
},
  "geometry": {"coordinates":[-2.36135361880124,51.41733345487559],"type":"Point"}
}