{
  "type": "Feature",
  "properties": {
    "iso:country":"GB",
    "wof:name":"RG8 0RD",
    "wof:placetype":"postalcode"
},
  "geometry": {"coordinates":[-1.06658360523855,51.52883093321604],"type":"Point"}
}