{
  "type": "Feature",
  "properties": {
    "date:inception_lower": "1980-01-01",
    "date:inception_upper": "1980-01-01",
    "iso:country": "GB",
    "wof:name": "RG8 0RD",
    "wof:placetype": "postalcode"
  },
  "geometry": {"coordinates":[-1.066584,51.528831],"type":"Point"}
}
