{
  "type": "Feature",
  "properties": {
    "iso:country": "GB",
    "wof:name": "PR8 6QB",
    "wof:placetype": "postalcode"
  },
  "geometry": {"coordinates":[-2.981361,53.628922],"type":"Point"}
}
