{
  "type": "Feature",
  "properties": {
    "iso:country":"GB",
    "wof:name":"PE13 2UQ",
    "wof:placetype":"postalcode"
},
  "geometry": {"coordinates":[0.1759842733821,52.65369134474095],"type":"Point"}
}