{
  "type": "Feature",
  "properties": {
    "iso:country":"GB",
    "wof:name":"HX6 1EA",
    "wof:placetype":"postalcode"
},
  "geometry": {"coordinates":[-1.91948964221452,53.70772798814914],"type":"Point"}
}