{
  "type": "Feature",
  "properties": {
    "iso:country":"GB",
    "wof:name":"BD22 6HL",
    "wof:placetype":"postalcode"
},
  "geometry": {"coordinates":[-1.92950770104844,53.86868189054221],"type":"Point"}
}