{
  "type": "Feature",
  "properties": {
    "iso:country": "GB",
    "wof:name": "BD22 6HL",
    "wof:placetype": "postalcode"
  },
  "geometry": {"coordinates":[-1.929508,53.868682],"type":"Point"}
}
