{
  "type": "Feature",
  "properties": {
    "date:inception_lower": "2024-01-01",
    "date:inception_upper": "2024-01-01",
    "iso:country": "GB",
    "wof:name": "CF71 9EJ",
    "wof:placetype": "postalcode"
  },
  "geometry": {"coordinates":[-3.49494,51.439971],"type":"Point"}
}
