{
  "type": "Feature",
  "properties": {
    "iso:country": "GB",
    "wof:name": "LS7 4RH",
    "wof:placetype": "postalcode"
  },
  "geometry": {"coordinates":[-1.528224,53.812311],"type":"Point"}
}
