{
  "type": "Feature",
  "properties": {
    "iso:country":"GB",
    "wof:name":"LS7 4RH",
    "wof:placetype":"postalcode"
},
  "geometry": {"coordinates":[-1.52822441087632,53.81231145277128],"type":"Point"}
}