{
  "type": "Feature",
  "properties": {
    "iso:country": "GB",
    "wof:name": "NE9 7AS",
    "wof:placetype": "postalcode"
  },
  "geometry": {"coordinates":[-1.573816,54.921994],"type":"Point"}
}
