{
  "type": "Feature",
  "properties": {
    "iso:country":"GB",
    "wof:name":"CH66 2RT",
    "wof:placetype":"postalcode"
},
  "geometry": {"coordinates":[-2.92500977576415,53.26340851984946],"type":"Point"}
}