{
  "type": "Feature",
  "properties": {
    "iso:country":"GB",
    "wof:name":"SA44 6SD",
    "wof:placetype":"postalcode"
},
  "geometry": {"coordinates":[-4.4644214547288,52.15901716372968],"type":"Point"}
}