{
  "type": "Feature",
  "properties": {
    "iso:country":"GB",
    "wof:name":"IV31 6FB",
    "wof:placetype":"postalcode"
},
  "geometry": {"coordinates":[-3.28512033162327,57.70995748147575],"type":"Point"}
}