{
  "type": "Feature",
  "properties": {
    "date:inception_lower": "2013-07-01",
    "date:inception_upper": "2013-07-01",
    "iso:country": "GB",
    "wof:name": "IV31 6FB",
    "wof:placetype": "postalcode"
  },
  "geometry": {"coordinates":[-3.28544,57.710047],"type":"Point"}
}
