{
  "type": "Feature",
  "properties": {
    "iso:country":"GB",
    "wof:name":"NP10 8NR",
    "wof:placetype":"postalcode"
},
  "geometry": {"coordinates":[-3.04937441262408,51.57931514636326],"type":"Point"}
}