{
  "type": "Feature",
  "properties": {
    "date:inception_lower": "1980-01-01",
    "date:inception_upper": "1980-01-01",
    "iso:country": "GB",
    "wof:name": "TN2 3TX",
    "wof:placetype": "postalcode"
  },
  "geometry": {"coordinates":[0.286999,51.147092],"type":"Point"}
}
