{
  "type": "Feature",
  "properties": {
    "iso:country":"GB",
    "wof:name":"TN2 3TX",
    "wof:placetype":"postalcode"
},
  "geometry": {"coordinates":[0.28699854217741,51.14709210996669],"type":"Point"}
}