{
  "type": "Feature",
  "properties": {
    "iso:country": "GB",
    "wof:name": "SO18 5GW",
    "wof:placetype": "postalcode"
  },
  "geometry": {"coordinates":[-1.344068,50.922157],"type":"Point"}
}
