{
  "type": "Feature",
  "properties": {
    "iso:country":"GB",
    "wof:name":"NW9 9NH",
    "wof:placetype":"postalcode"
},
  "geometry": {"coordinates":[-0.2726531451138,51.58491456609048],"type":"Point"}
}