{
  "type": "Feature",
  "properties": {
    "date:inception_lower":"1995-07-01",
    "date:inception_upper":"1995-07-31",
    "iso:country":"GB",
    "wof:name":"RH9 8JS",
    "wof:placetype":"postalcode"
},
  "geometry": {"coordinates":[-0.049382,51.204978],"type":"Point"}
}