{
  "type": "Feature",
  "properties": {
    "iso:country":"GB",
    "wof:name":"TS23 2PJ",
    "wof:placetype":"postalcode"
},
  "geometry": {"coordinates":[-1.28926828117218,54.60578678389955],"type":"Point"}
}