{
  "type": "Feature",
  "properties": {
    "iso:country": "GB",
    "wof:name": "CO4 5BJ",
    "wof:placetype": "postalcode"
  },
  "geometry": {"coordinates":[0.871214,51.906443],"type":"Point"}
}
