{
  "type": "Feature",
  "properties": {
    "date:inception_lower":"1990-02-01",
    "date:inception_upper":"1990-02-28",
    "iso:country":"GB",
    "wof:name":"CO4 5BJ",
    "wof:placetype":"postalcode"
},
  "geometry": {"coordinates":[0.871214,51.906443],"type":"Point"}
}