{
  "type": "Feature",
  "properties": {
    "iso:country":"GB",
    "wof:name":"OX3 8NZ",
    "wof:placetype":"postalcode"
},
  "geometry": {"coordinates":[-1.20159452619562,51.75551234197596],"type":"Point"}
}