{
  "type": "Feature",
  "properties": {
    "iso:country":"GB",
    "wof:name":"BS6 6AA",
    "wof:placetype":"postalcode"
},
  "geometry": {"coordinates":[-2.5944189142458,51.46862429055557],"type":"Point"}
}