{
  "type": "Feature",
  "properties": {
    "date:inception_lower":"1980-01-01",
    "date:inception_upper":"1980-01-31",
    "iso:country":"GB",
    "wof:name":"BS6 6AA",
    "wof:placetype":"postalcode"
},
  "geometry": {"coordinates":[-2.594419,51.468624],"type":"Point"}
}