{
  "type": "Feature",
  "properties": {
    "iso:country": "GB",
    "wof:name": "BB10 4JE",
    "wof:placetype": "postalcode"
  },
  "geometry": {"coordinates":[-2.203385,53.782605],"type":"Point"}
}
