{
  "type": "Feature",
  "properties": {
    "date:inception_lower":"1980-01-01",
    "date:inception_upper":"1980-01-31",
    "iso:country":"GB",
    "wof:name":"BB10 4JE",
    "wof:placetype":"postalcode"
},
  "geometry": {"coordinates":[-2.203385,53.782605],"type":"Point"}
}