{
  "type": "Feature",
  "properties": {
    "iso:country": "GB",
    "wof:name": "S21 4DZ",
    "wof:placetype": "postalcode"
  },
  "geometry": {"coordinates":[-1.358758,53.311497],"type":"Point"}
}
