{
  "type": "Feature",
  "properties": {
    "iso:country":"GB",
    "wof:name":"S21 4DZ",
    "wof:placetype":"postalcode"
},
  "geometry": {"coordinates":[-1.35875806228513,53.31149657500135],"type":"Point"}
}