{
  "type": "Feature",
  "properties": {
    "date:inception_lower": "1996-12-01",
    "date:inception_upper": "1996-12-01",
    "iso:country": "GB",
    "wof:name": "G68 0BS",
    "wof:placetype": "postalcode"
  },
  "geometry": {"coordinates":[-3.995596,55.958547],"type":"Point"}
}
