{
  "type": "Feature",
  "properties": {
    "iso:country": "GB",
    "wof:name": "G68 0BS",
    "wof:placetype": "postalcode"
  },
  "geometry": {"coordinates":[-3.995596,55.958547],"type":"Point"}
}
