{
  "type": "Feature",
  "properties": {
    "iso:country":"GB",
    "wof:name":"G68 0BS",
    "wof:placetype":"postalcode"
},
  "geometry": {"coordinates":[-3.99559610995085,55.95854736970746],"type":"Point"}
}