{
  "type": "Feature",
  "properties": {
    "date:inception_lower": "1980-01-01",
    "date:inception_upper": "1980-01-01",
    "iso:country": "GB",
    "wof:name": "NR5 0ES",
    "wof:placetype": "postalcode"
  },
  "geometry": {"coordinates":[1.230736,52.645019],"type":"Point"}
}
