{
  "type": "Feature",
  "properties": {
    "iso:country":"GB",
    "wof:name":"B65 8DB",
    "wof:placetype":"postalcode"
},
  "geometry": {"coordinates":[-2.05349674703197,52.48304258165842],"type":"Point"}
}