{
  "type": "Feature",
  "properties": {
    "date:inception_lower": "1980-01-01",
    "date:inception_upper": "1980-01-01",
    "iso:country": "GB",
    "wof:name": "DH1 1PP",
    "wof:placetype": "postalcode"
  },
  "geometry": {"coordinates":[-1.550434,54.781317],"type":"Point"}
}
