{
  "type": "Feature",
  "properties": {
    "iso:country":"GB",
    "wof:name":"DH1 1PP",
    "wof:placetype":"postalcode"
},
  "geometry": {"coordinates":[-1.55043410294907,54.78131675826346],"type":"Point"}
}