{
  "type": "Feature",
  "properties": {
    "iso:country":"GB",
    "wof:name":"NE49 9EW",
    "wof:placetype":"postalcode"
},
  "geometry": {"coordinates":[-2.46212548883768,54.97307409296653],"type":"Point"}
}