{
  "type": "Feature",
  "properties": {
    "iso:country": "GB",
    "wof:name": "PO30 3LU",
    "wof:placetype": "postalcode"
  },
  "geometry": {"coordinates":[-1.362027,50.633328],"type":"Point"}
}
