{
  "type": "Feature",
  "properties": {
    "date:inception_lower": "2007-04-01",
    "date:inception_upper": "2007-04-01",
    "iso:country": "GB",
    "wof:name": "PO30 3LU",
    "wof:placetype": "postalcode"
  },
  "geometry": {"coordinates":[-1.362027,50.633328],"type":"Point"}
}
