{
  "type": "Feature",
  "properties": {
    "iso:country":"GB",
    "wof:name":"PO30 3LU",
    "wof:placetype":"postalcode"
},
  "geometry": {"coordinates":[-1.36203590853093,50.63333967424703],"type":"Point"}
}