{
  "type": "Feature",
  "properties": {
    "iso:country": "GB",
    "wof:name": "S12 4TU",
    "wof:placetype": "postalcode"
  },
  "geometry": {"coordinates":[-1.390974,53.351117],"type":"Point"}
}
