{
  "type": "Feature",
  "properties": {
    "iso:country":"GB",
    "wof:name":"LA4 4JD",
    "wof:placetype":"postalcode"
},
  "geometry": {"coordinates":[-2.87644039966137,54.06577170342559],"type":"Point"}
}