{
  "type": "Feature",
  "properties": {
    "iso:country": "GB",
    "wof:name": "LA4 4JD",
    "wof:placetype": "postalcode"
  },
  "geometry": {"coordinates":[-2.87644,54.065772],"type":"Point"}
}
