{
  "type": "Feature",
  "properties": {
    "date:inception_lower": "1980-01-01",
    "date:inception_upper": "1980-01-01",
    "iso:country": "GB",
    "wof:name": "DG7 3BH",
    "wof:placetype": "postalcode"
  },
  "geometry": {"coordinates":[-4.004419,54.999085],"type":"Point"}
}
