{
  "type": "Feature",
  "properties": {
    "iso:country": "GB",
    "wof:name": "DG7 3BH",
    "wof:placetype": "postalcode"
  },
  "geometry": {"coordinates":[-4.004722,54.999047],"type":"Point"}
}
