{
  "type": "Feature",
  "properties": {
    "date:inception_lower": "2021-07-01",
    "date:inception_upper": "2021-07-01",
    "iso:country": "GB",
    "wof:name": "CV9 2FT",
    "wof:placetype": "postalcode"
  },
  "geometry": {"coordinates":[-1.588747,52.592081],"type":"Point"}
}
