{
  "type": "Feature",
  "properties": {
    "date:inception_lower": "2018-06-01",
    "date:inception_upper": "2018-06-01",
    "iso:country": "GB",
    "wof:name": "BA3 3FX",
    "wof:placetype": "postalcode"
  },
  "geometry": {"coordinates":[-2.446515,51.291924],"type":"Point"}
}
