{
  "type": "Feature",
  "properties": {
    "iso:country": "GB",
    "wof:name": "AB42 4JW",
    "wof:placetype": "postalcode"
  },
  "geometry": {"coordinates":[-1.97318,57.579912],"type":"Point"}
}
