{
  "type": "Feature",
  "properties": {
    "iso:country":"GB",
    "wof:name":"KT23 3BY",
    "wof:placetype":"postalcode"
},
  "geometry": {"coordinates":[-0.38747924475055,51.2853944423644],"type":"Point"}
}