{
  "type": "Feature",
  "properties": {
    "iso:country": "GB",
    "wof:name": "SA6 6ST",
    "wof:placetype": "postalcode"
  },
  "geometry": {"coordinates":[-3.926551,51.684489],"type":"Point"}
}
