{
  "type": "Feature",
  "properties": {
    "iso:country":"GB",
    "wof:name":"SA6 6ST",
    "wof:placetype":"postalcode"
},
  "geometry": {"coordinates":[-3.92655116393608,51.68448924176549],"type":"Point"}
}