{
  "type": "Feature",
  "properties": {
    "date:inception_lower": "1997-12-01",
    "date:inception_upper": "1997-12-01",
    "iso:country": "GB",
    "wof:name": "SK13 7BQ",
    "wof:placetype": "postalcode"
  },
  "geometry": {"coordinates":[-1.957061,53.451329],"type":"Point"}
}
