{
  "type": "Feature",
  "properties": {
    "iso:country":"GB",
    "wof:name":"SK13 7BQ",
    "wof:placetype":"postalcode"
},
  "geometry": {"coordinates":[-1.95706130031916,53.45132944388894],"type":"Point"}
}