{
  "type": "Feature",
  "properties": {
    "iso:country":"GB",
    "wof:name":"CT2 7RR",
    "wof:placetype":"postalcode"
},
  "geometry": {"coordinates":[1.06858300798674,51.28823976462291],"type":"Point"}
}