{
  "type": "Feature",
  "properties": {
    "iso:country": "GB",
    "wof:name": "CO15 6AW",
    "wof:placetype": "postalcode"
  },
  "geometry": {"coordinates":[1.160588,51.791695],"type":"Point"}
}
