{
  "type": "Feature",
  "properties": {
    "iso:country": "GB",
    "wof:name": "EX2 8AR",
    "wof:placetype": "postalcode"
  },
  "geometry": {"coordinates":[-3.535709,50.715946],"type":"Point"}
}
