{
  "type": "Feature",
  "properties": {
    "iso:country":"GB",
    "wof:name":"EX2 8AR",
    "wof:placetype":"postalcode"
},
  "geometry": {"coordinates":[-3.53570887627986,50.71594623586955],"type":"Point"}
}