{
  "type": "Feature",
  "properties": {
    "iso:country":"GB",
    "wof:name":"BA10 0PL",
    "wof:placetype":"postalcode"
},
  "geometry": {"coordinates":[-2.4779228512389,51.0999242676456],"type":"Point"}
}