{
  "type": "Feature",
  "properties": {
    "iso:country": "GB",
    "wof:name": "BA10 0PL",
    "wof:placetype": "postalcode"
  },
  "geometry": {"coordinates":[-2.477923,51.099924],"type":"Point"}
}
