{
  "type": "Feature",
  "properties": {
    "date:inception_lower": "1980-01-01",
    "date:inception_upper": "1980-01-01",
    "iso:country": "GB",
    "wof:name": "DE6 3FF",
    "wof:placetype": "postalcode"
  },
  "geometry": {"coordinates":[-1.617444,53.020932],"type":"Point"}
}
