{
  "type": "Feature",
  "properties": {
    "iso:country":"GB",
    "wof:name":"ME15 8PU",
    "wof:placetype":"postalcode"
},
  "geometry": {"coordinates":[0.56061284799745,51.2481496650095],"type":"Point"}
}