{
  "type": "Feature",
  "properties": {
    "date:inception_lower": "1984-02-01",
    "date:inception_upper": "1984-02-01",
    "iso:country": "GB",
    "wof:name": "ME15 8PU",
    "wof:placetype": "postalcode"
  },
  "geometry": {"coordinates":[0.560613,51.24815],"type":"Point"}
}
