{
  "type": "Feature",
  "properties": {
    "iso:country": "GB",
    "wof:name": "LS24 9QZ",
    "wof:placetype": "postalcode"
  },
  "geometry": {"coordinates":[-1.228079,53.821659],"type":"Point"}
}
