{
  "type": "Feature",
  "properties": {
    "iso:country": "GB",
    "wof:name": "LS24 9QZ",
    "wof:placetype": "postalcode"
  },
  "geometry": {"coordinates":[-1.227697,53.821539],"type":"Point"}
}
