{
  "type": "Feature",
  "properties": {
    "date:inception_lower": "1980-01-01",
    "date:inception_upper": "1980-01-01",
    "iso:country": "GB",
    "wof:name": "TA3 6BD",
    "wof:placetype": "postalcode"
  },
  "geometry": {"coordinates":[-2.99454,51.024218],"type":"Point"}
}
