{
  "type": "Feature",
  "properties": {
    "date:inception_lower":"2005-07-01",
    "date:inception_upper":"2005-07-31",
    "iso:country":"GB",
    "wof:name":"NP12 2DS",
    "wof:placetype":"postalcode"
},
  "geometry": {"coordinates":[-3.174525,51.656429],"type":"Point"}
}