{
  "type": "Feature",
  "properties": {
    "iso:country":"GB",
    "wof:name":"W1F 0EF",
    "wof:placetype":"postalcode"
},
  "geometry": {"coordinates":[-0.1329974655755,51.5134170694555],"type":"Point"}
}