{
  "type": "Feature",
  "properties": {
    "iso:country":"GB",
    "wof:name":"HX3 0PX",
    "wof:placetype":"postalcode"
},
  "geometry": {"coordinates":[-1.85162957076622,53.7052545091306],"type":"Point"}
}