{
  "type": "Feature",
  "properties": {
    "iso:country":"GB",
    "wof:name":"DL17 8QW",
    "wof:placetype":"postalcode"
},
  "geometry": {"coordinates":[-1.5412435061026,54.68932204816179],"type":"Point"}
}