{
  "type": "Feature",
  "properties": {
    "date:inception_lower":"1980-01-01",
    "date:inception_upper":"1980-01-31",
    "iso:country":"GB",
    "wof:name":"DL17 8QW",
    "wof:placetype":"postalcode"
},
  "geometry": {"coordinates":[-1.541243,54.689322],"type":"Point"}
}