{
  "type": "Feature",
  "properties": {
    "iso:country":"GB",
    "wof:name":"LS8 1BU",
    "wof:placetype":"postalcode"
},
  "geometry": {"coordinates":[-1.51168622753744,53.84363142852881],"type":"Point"}
}