{
  "type": "Feature",
  "properties": {
    "iso:country":"GB",
    "wof:name":"LS14 3ED",
    "wof:placetype":"postalcode"
},
  "geometry": {"coordinates":[-1.42431331325243,53.8600248591927],"type":"Point"}
}