{
  "type": "Feature",
  "properties": {
    "iso:country":"GB",
    "wof:name":"PR2 5LJ",
    "wof:placetype":"postalcode"
},
  "geometry": {"coordinates":[-2.62463494077215,53.804033470298],"type":"Point"}
}