{
  "type": "Feature",
  "properties": {
    "iso:country":"GB",
    "wof:name":"L34 6LN",
    "wof:placetype":"postalcode"
},
  "geometry": {"coordinates":[-2.79599469378913,53.43154213452453],"type":"Point"}
}