{
  "type": "Feature",
  "properties": {
    "date:inception_lower": "1996-12-01",
    "date:inception_upper": "1996-12-01",
    "iso:country": "GB",
    "wof:name": "L34 6LN",
    "wof:placetype": "postalcode"
  },
  "geometry": {"coordinates":[-2.795995,53.431542],"type":"Point"}
}
