{
  "type": "Feature",
  "properties": {
    "iso:country":"GB",
    "wof:name":"DH4 7JG",
    "wof:placetype":"postalcode"
},
  "geometry": {"coordinates":[-1.50038504961357,54.87719602525299],"type":"Point"}
}