{
  "type": "Feature",
  "properties": {
    "date:inception_lower": "1980-01-01",
    "date:inception_upper": "1980-01-01",
    "iso:country": "GB",
    "wof:name": "EH21 8HJ",
    "wof:placetype": "postalcode"
  },
  "geometry": {"coordinates":[-3.0229,55.941067],"type":"Point"}
}
