{
  "type": "Feature",
  "properties": {
    "iso:country": "GB",
    "wof:name": "B63 1DX",
    "wof:placetype": "postalcode"
  },
  "geometry": {"coordinates":[-2.078296,52.437806],"type":"Point"}
}
