{
  "type": "Feature",
  "properties": {
    "date:inception_lower":"1980-01-01",
    "date:inception_upper":"1980-01-31",
    "iso:country":"GB",
    "wof:name":"B63 1DX",
    "wof:placetype":"postalcode"
},
  "geometry": {"coordinates":[-2.078296,52.437806],"type":"Point"}
}