{
  "type": "Feature",
  "properties": {
    "date:inception_lower":"1984-10-01",
    "date:inception_upper":"1984-10-31",
    "iso:country":"GB",
    "wof:name":"HU16 4EQ",
    "wof:placetype":"postalcode"
},
  "geometry": {"coordinates":[-0.415017,53.785078],"type":"Point"}
}