{
  "type": "Feature",
  "properties": {
    "date:inception_lower": "2004-10-01",
    "date:inception_upper": "2004-10-01",
    "iso:country": "GB",
    "wof:name": "NE12 8RG",
    "wof:placetype": "postalcode"
  },
  "geometry": {"coordinates":[-1.59119,55.010335],"type":"Point"}
}
