{
  "type": "Feature",
  "properties": {
    "iso:country":"GB",
    "wof:name":"NE12 8RG",
    "wof:placetype":"postalcode"
},
  "geometry": {"coordinates":[-1.59119033859565,55.01033510440526],"type":"Point"}
}