{
  "type": "Feature",
  "properties": {
    "iso:country":"GB",
    "wof:name":"CH44 0BR",
    "wof:placetype":"postalcode"
},
  "geometry": {"coordinates":[-3.0305159291349,53.41867411414029],"type":"Point"}
}