{
  "type": "Feature",
  "properties": {
    "date:inception_lower":"1999-06-01",
    "date:inception_upper":"1999-06-30",
    "iso:country":"GB",
    "wof:name":"CH44 0BR",
    "wof:placetype":"postalcode"
},
  "geometry": {"coordinates":[-3.030516,53.418674],"type":"Point"}
}