{
  "type": "Feature",
  "properties": {
    "iso:country":"GB",
    "wof:name":"EH54 6AA",
    "wof:placetype":"postalcode"
},
  "geometry": {"coordinates":[-3.52353903430406,55.89397642163352],"type":"Point"}
}