{
  "type": "Feature",
  "properties": {
    "iso:country": "GB",
    "wof:name": "TN15 6NU",
    "wof:placetype": "postalcode"
  },
  "geometry": {"coordinates":[0.227738,51.30321],"type":"Point"}
}
