{
  "type": "Feature",
  "properties": {
    "iso:country":"GB",
    "wof:name":"TN15 6NU",
    "wof:placetype":"postalcode"
},
  "geometry": {"coordinates":[0.22773748610028,51.30320957890347],"type":"Point"}
}