{
  "type": "Feature",
  "properties": {
    "date:inception_lower": "1980-01-01",
    "date:inception_upper": "1980-01-01",
    "iso:country": "GB",
    "wof:name": "NN9 6HH",
    "wof:placetype": "postalcode"
  },
  "geometry": {"coordinates":[-0.544057,52.349136],"type":"Point"}
}
