{
  "type": "Feature",
  "properties": {
    "iso:country":"GB",
    "wof:name":"NN9 6HH",
    "wof:placetype":"postalcode"
},
  "geometry": {"coordinates":[-0.54405753011993,52.34913576737687],"type":"Point"}
}