{
  "type": "Feature",
  "properties": {
    "iso:country":"GB",
    "wof:name":"HU9 1DD",
    "wof:placetype":"postalcode"
},
  "geometry": {"coordinates":[-0.32166472645716,53.7482106162608],"type":"Point"}
}