{
  "type": "Feature",
  "properties": {
    "date:inception_lower":"2010-03-01",
    "date:inception_upper":"2010-03-31",
    "iso:country":"GB",
    "wof:name":"HU9 1DD",
    "wof:placetype":"postalcode"
},
  "geometry": {"coordinates":[-0.321665,53.748211],"type":"Point"}
}