{
  "type": "Feature",
  "properties": {
    "iso:country": "GB",
    "wof:name": "HR9 7XG",
    "wof:placetype": "postalcode"
  },
  "geometry": {"coordinates":[-2.574878,51.921405],"type":"Point"}
}
