{
  "type": "Feature",
  "properties": {
    "iso:country":"GB",
    "wof:name":"GU1 4QD",
    "wof:placetype":"postalcode"
},
  "geometry": {"coordinates":[-0.57534848991324,51.23807583046615],"type":"Point"}
}