{
  "type": "Feature",
  "properties": {
    "iso:country": "GB",
    "wof:name": "G2 2EJ",
    "wof:placetype": "postalcode"
  },
  "geometry": {"coordinates":[-4.257872,55.864253],"type":"Point"}
}
