{
  "type": "Feature",
  "properties": {
    "iso:country":"GB",
    "wof:name":"DY8 5XB",
    "wof:placetype":"postalcode"
},
  "geometry": {"coordinates":[-2.14531255814666,52.47553952677849],"type":"Point"}
}