{
  "type": "Feature",
  "properties": {
    "iso:country":"GB",
    "wof:name":"AB12 3HY",
    "wof:placetype":"postalcode"
},
  "geometry": {"coordinates":[-2.08887881834258,57.10635847977673],"type":"Point"}
}