{
  "type": "Feature",
  "properties": {
    "iso:country":"GB",
    "wof:name":"RG22 5RE",
    "wof:placetype":"postalcode"
},
  "geometry": {"coordinates":[-1.13619705806918,51.24403417448485],"type":"Point"}
}