{
  "type": "Feature",
  "properties": {
    "iso:country": "GB",
    "wof:name": "S12 3DD",
    "wof:placetype": "postalcode"
  },
  "geometry": {"coordinates":[-1.415435,53.3475],"type":"Point"}
}
