{
  "type": "Feature",
  "properties": {
    "iso:country":"GB",
    "wof:name":"NG5 5GE",
    "wof:placetype":"postalcode"
},
  "geometry": {"coordinates":[-1.17560270997876,52.99761996137693],"type":"Point"}
}