{
  "type": "Feature",
  "properties": {
    "iso:country":"GB",
    "wof:name":"BN27 3UA",
    "wof:placetype":"postalcode"
},
  "geometry": {"coordinates":[0.2432972116643,50.86483640601121],"type":"Point"}
}