{
  "type": "Feature",
  "properties": {
    "iso:country":"GB",
    "wof:name":"WV15 6QG",
    "wof:placetype":"postalcode"
},
  "geometry": {"coordinates":[-2.39061007909961,52.52076939510252],"type":"Point"}
}