{
  "type": "Feature",
  "properties": {
    "iso:country":"GB",
    "wof:name":"DL2 3EE",
    "wof:placetype":"postalcode"
},
  "geometry": {"coordinates":[-1.73783116288961,54.5477897839959],"type":"Point"}
}