{
  "type": "Feature",
  "properties": {
    "iso:country": "GB",
    "wof:name": "DL2 3EE",
    "wof:placetype": "postalcode"
  },
  "geometry": {"coordinates":[-1.737831,54.54779],"type":"Point"}
}
