{
  "type": "Feature",
  "properties": {
    "iso:country":"GB",
    "wof:name":"E5 0DL",
    "wof:placetype":"postalcode"
},
  "geometry": {"coordinates":[-0.04230238901749,51.55775553204033],"type":"Point"}
}