{
  "type": "Feature",
  "properties": {
    "iso:country":"GB",
    "wof:name":"NW8 8EU",
    "wof:placetype":"postalcode"
},
  "geometry": {"coordinates":[-0.17039332300378,51.52321465575888],"type":"Point"}
}