{
  "type": "Feature",
  "properties": {
    "iso:country":"GB",
    "wof:name":"KY16 8AP",
    "wof:placetype":"postalcode"
},
  "geometry": {"coordinates":[-2.80249919132037,56.33619349108014],"type":"Point"}
}