{
  "type": "Feature",
  "properties": {
    "date:inception_lower":"1980-01-01",
    "date:inception_upper":"1980-01-31",
    "iso:country":"GB",
    "wof:name":"KY16 8AP",
    "wof:placetype":"postalcode"
},
  "geometry": {"coordinates":[-2.802499,56.336193],"type":"Point"}
}