{
  "type": "Feature",
  "properties": {
    "iso:country": "GB",
    "wof:name": "FK1 2QD",
    "wof:placetype": "postalcode"
  },
  "geometry": {"coordinates":[-3.774276,55.987383],"type":"Point"}
}
