{
  "type": "Feature",
  "properties": {
    "iso:country":"GB",
    "wof:name":"SL7 3RJ",
    "wof:placetype":"postalcode"
},
  "geometry": {"coordinates":[-0.74827936094628,51.58515052267382],"type":"Point"}
}