{
  "type": "Feature",
  "properties": {
    "iso:country": "GB",
    "wof:name": "SL7 3RJ",
    "wof:placetype": "postalcode"
  },
  "geometry": {"coordinates":[-0.748279,51.585151],"type":"Point"}
}
