{
  "type": "Feature",
  "properties": {
    "date:inception_lower": "1990-02-01",
    "date:inception_upper": "1990-02-01",
    "iso:country": "GB",
    "wof:name": "EX5 4RJ",
    "wof:placetype": "postalcode"
  },
  "geometry": {"coordinates":[-3.511276,50.76356],"type":"Point"}
}
