{
  "type": "Feature",
  "properties": {
    "iso:country":"GB",
    "wof:name":"G43 1AP",
    "wof:placetype":"postalcode"
},
  "geometry": {"coordinates":[-4.29836063653882,55.82132451193047],"type":"Point"}
}