{
  "type": "Feature",
  "properties": {
    "iso:country":"GB",
    "wof:name":"WA6 8EA",
    "wof:placetype":"postalcode"
},
  "geometry": {"coordinates":[-2.67976042236749,53.26770219009374],"type":"Point"}
}