{
  "type": "Feature",
  "properties": {
    "iso:country":"GB",
    "wof:name":"E6 5RU",
    "wof:placetype":"postalcode"
},
  "geometry": {"coordinates":[0.05115722786737,51.51297581105189],"type":"Point"}
}