{
  "type": "Feature",
  "properties": {
    "iso:country": "GB",
    "wof:name": "BL9 5QD",
    "wof:placetype": "postalcode"
  },
  "geometry": {"coordinates":[-2.317824,53.627275],"type":"Point"}
}
