{
  "type": "Feature",
  "properties": {
    "iso:country":"GB",
    "wof:name":"BL9 5QD",
    "wof:placetype":"postalcode"
},
  "geometry": {"coordinates":[-2.31782447187362,53.62727478455073],"type":"Point"}
}