{
  "type": "Feature",
  "properties": {
    "iso:country":"GB",
    "wof:name":"SG12 0RJ",
    "wof:placetype":"postalcode"
},
  "geometry": {"coordinates":[-0.03338596692698,51.82114647622527],"type":"Point"}
}