{
  "type": "Feature",
  "properties": {
    "iso:country":"GB",
    "wof:name":"LE5 3HB",
    "wof:placetype":"postalcode"
},
  "geometry": {"coordinates":[-1.11040033196089,52.63707537652395],"type":"Point"}
}