{
  "type": "Feature",
  "properties": {
    "date:inception_lower": "1980-01-01",
    "date:inception_upper": "1980-01-01",
    "iso:country": "GB",
    "wof:name": "E15 1EE",
    "wof:placetype": "postalcode"
  },
  "geometry": {"coordinates":[-0.001605,51.548886],"type":"Point"}
}
