{
  "type": "Feature",
  "properties": {
    "iso:country": "GB",
    "wof:name": "TS11 7AW",
    "wof:placetype": "postalcode"
  },
  "geometry": {"coordinates":[-1.016008,54.592901],"type":"Point"}
}
