{
  "type": "Feature",
  "properties": {
    "date:inception_lower": "1980-01-01",
    "date:inception_upper": "1980-01-01",
    "iso:country": "GB",
    "wof:name": "WF3 3LR",
    "wof:placetype": "postalcode"
  },
  "geometry": {"coordinates":[-1.495641,53.727024],"type":"Point"}
}
