{
  "type": "Feature",
  "properties": {
    "iso:country":"GB",
    "wof:name":"WF3 3LR",
    "wof:placetype":"postalcode"
},
  "geometry": {"coordinates":[-1.49560486118176,53.72600086095143],"type":"Point"}
}