{
  "type": "Feature",
  "properties": {
    "date:inception_lower":"1980-01-01",
    "date:inception_upper":"1980-01-31",
    "iso:country":"GB",
    "wof:name":"WF3 3LR",
    "wof:placetype":"postalcode"
},
  "geometry": {"coordinates":[-1.495608,53.726017],"type":"Point"}
}