{
  "type": "Feature",
  "properties": {
    "iso:country": "GB",
    "wof:name": "SW19 3PS",
    "wof:placetype": "postalcode"
  },
  "geometry": {"coordinates":[-0.212519,51.414515],"type":"Point"}
}
