{
  "type": "Feature",
  "properties": {
    "date:inception_lower": "1980-01-01",
    "date:inception_upper": "1980-01-01",
    "iso:country": "GB",
    "wof:name": "SW19 3PS",
    "wof:placetype": "postalcode"
  },
  "geometry": {"coordinates":[-0.212519,51.414515],"type":"Point"}
}
