{
  "type": "Feature",
  "properties": {
    "iso:country": "GB",
    "wof:name": "TA5 2FR",
    "wof:placetype": "postalcode"
  },
  "geometry": {"coordinates":[-3.016027,51.112186],"type":"Point"}
}
