{
  "type": "Feature",
  "properties": {
    "date:inception_lower":"2010-12-01",
    "date:inception_upper":"2010-12-31",
    "iso:country":"GB",
    "wof:name":"TA5 2FR",
    "wof:placetype":"postalcode"
},
  "geometry": {"coordinates":[-3.016027,51.112186],"type":"Point"}
}