{
  "type": "Feature",
  "properties": {
    "iso:country":"GB",
    "wof:name":"TA5 2FR",
    "wof:placetype":"postalcode"
},
  "geometry": {"coordinates":[-3.01602750134287,51.11218591323286],"type":"Point"}
}