{
  "type": "Feature",
  "properties": {
    "iso:country":"GB",
    "wof:name":"PL10 1EP",
    "wof:placetype":"postalcode"
},
  "geometry": {"coordinates":[-4.20933405594736,50.35310522480935],"type":"Point"}
}