{
  "type": "Feature",
  "properties": {
    "iso:country":"GB",
    "wof:name":"M24 1PQ",
    "wof:placetype":"postalcode"
},
  "geometry": {"coordinates":[-2.19225769199695,53.53614059723972],"type":"Point"}
}