{
  "type": "Feature",
  "properties": {
    "date:inception_lower":"1980-01-01",
    "date:inception_upper":"1980-01-31",
    "iso:country":"GB",
    "wof:name":"M24 1PQ",
    "wof:placetype":"postalcode"
},
  "geometry": {"coordinates":[-2.192258,53.536141],"type":"Point"}
}