{
  "type": "Feature",
  "properties": {
    "iso:country": "GB",
    "wof:name": "EX2 8FU",
    "wof:placetype": "postalcode"
  },
  "geometry": {"coordinates":[-3.52996,50.695994],"type":"Point"}
}
