{
  "type": "Feature",
  "properties": {
    "iso:country":"GB",
    "wof:name":"WD17 2HX",
    "wof:placetype":"postalcode"
},
  "geometry": {"coordinates":[-0.38659614496923,51.64892334748065],"type":"Point"}
}