{
  "type": "Feature",
  "properties": {
    "iso:country":"GB",
    "wof:name":"B36 0LX",
    "wof:placetype":"postalcode"
},
  "geometry": {"coordinates":[-1.73990620773813,52.49376423427703],"type":"Point"}
}