{
  "type": "Feature",
  "properties": {
    "date:inception_lower":"2010-10-01",
    "date:inception_upper":"2010-10-31",
    "iso:country":"GB",
    "wof:name":"TS21 1NY",
    "wof:placetype":"postalcode"
},
  "geometry": {"coordinates":[-1.408793,54.599698],"type":"Point"}
}