{
  "type": "Feature",
  "properties": {
    "iso:country": "GB",
    "wof:name": "TS21 1NY",
    "wof:placetype": "postalcode"
  },
  "geometry": {"coordinates":[-1.408793,54.599698],"type":"Point"}
}
