{
  "type": "Feature",
  "properties": {
    "iso:country":"GB",
    "wof:name":"TS21 1NY",
    "wof:placetype":"postalcode"
},
  "geometry": {"coordinates":[-1.40832733146495,54.59982153181009],"type":"Point"}
}