{
  "type": "Feature",
  "properties": {
    "iso:country":"GB",
    "wof:name":"DL2 3JP",
    "wof:placetype":"postalcode"
},
  "geometry": {"coordinates":[-1.80931771218537,54.57997940173512],"type":"Point"}
}