{
  "type": "Feature",
  "properties": {
    "date:inception_lower": "1995-12-01",
    "date:inception_upper": "1995-12-01",
    "iso:country": "GB",
    "wof:name": "S81 9TA",
    "wof:placetype": "postalcode"
  },
  "geometry": {"coordinates":[-1.115433,53.360874],"type":"Point"}
}
