{
  "type": "Feature",
  "properties": {
    "iso:country":"GB",
    "wof:name":"B34 7QE",
    "wof:placetype":"postalcode"
},
  "geometry": {"coordinates":[-1.76723508244846,52.49521452963097],"type":"Point"}
}