{
  "type": "Feature",
  "properties": {
    "iso:country": "GB",
    "wof:name": "B34 7QE",
    "wof:placetype": "postalcode"
  },
  "geometry": {"coordinates":[-1.767235,52.495215],"type":"Point"}
}
