{
  "type": "Feature",
  "properties": {
    "date:inception_lower": "1980-01-01",
    "date:inception_upper": "1980-01-01",
    "iso:country": "GB",
    "wof:name": "B34 7QE",
    "wof:placetype": "postalcode"
  },
  "geometry": {"coordinates":[-1.767235,52.495215],"type":"Point"}
}
