{
  "type": "Feature",
  "properties": {
    "iso:country":"GB",
    "wof:name":"HA9 0TU",
    "wof:placetype":"postalcode"
},
  "geometry": {"coordinates":[-0.27467232431545,51.55675347623261],"type":"Point"}
}