{
  "type": "Feature",
  "properties": {
    "iso:country":"GB",
    "wof:name":"HP9 1EQ",
    "wof:placetype":"postalcode"
},
  "geometry": {"coordinates":[-0.6596904192208,51.60651725551686],"type":"Point"}
}