{
  "type": "Feature",
  "properties": {
    "iso:country":"GB",
    "wof:name":"WV14 8DD",
    "wof:placetype":"postalcode"
},
  "geometry": {"coordinates":[-2.06022044500255,52.55402358750242],"type":"Point"}
}