{
  "type": "Feature",
  "properties": {
    "iso:country":"GB",
    "wof:name":"TR15 2NH",
    "wof:placetype":"postalcode"
},
  "geometry": {"coordinates":[-5.21406448186,50.22075195739954],"type":"Point"}
}