{
  "type": "Feature",
  "properties": {
    "iso:country": "GB",
    "wof:name": "HP14 3UF",
    "wof:placetype": "postalcode"
  },
  "geometry": {"coordinates":[-0.901634,51.660732],"type":"Point"}
}
