{
  "type": "Feature",
  "properties": {
    "iso:country": "GB",
    "wof:name": "DD10 8LJ",
    "wof:placetype": "postalcode"
  },
  "geometry": {"coordinates":[-2.470643,56.715965],"type":"Point"}
}
