{
  "type": "Feature",
  "properties": {
    "iso:country":"GB",
    "wof:name":"DD3 6PZ",
    "wof:placetype":"postalcode"
},
  "geometry": {"coordinates":[-2.98258309860018,56.47046468050356],"type":"Point"}
}