{
  "type": "Feature",
  "properties": {
    "iso:country": "GB",
    "wof:name": "LN11 0QR",
    "wof:placetype": "postalcode"
  },
  "geometry": {"coordinates":[-0.031125,53.365253],"type":"Point"}
}
