{
  "type": "Feature",
  "properties": {
    "iso:country":"GB",
    "wof:name":"PO2 0DN",
    "wof:placetype":"postalcode"
},
  "geometry": {"coordinates":[-1.07366075275878,50.81477877786571],"type":"Point"}
}