{
  "type": "Feature",
  "properties": {
    "iso:country":"GB",
    "wof:name":"IV55 8ZT",
    "wof:placetype":"postalcode"
},
  "geometry": {"coordinates":[-6.65009464408205,57.44634162829663],"type":"Point"}
}