{
  "type": "Feature",
  "properties": {
    "iso:country":"GB",
    "wof:name":"TA4 1AR",
    "wof:placetype":"postalcode"
},
  "geometry": {"coordinates":[-3.19820301805689,51.01669523534134],"type":"Point"}
}