{
  "type": "Feature",
  "properties": {
    "date:inception_lower": "1980-01-01",
    "date:inception_upper": "1980-01-01",
    "iso:country": "GB",
    "wof:name": "N3 2QD",
    "wof:placetype": "postalcode"
  },
  "geometry": {"coordinates":[-0.186397,51.601916],"type":"Point"}
}
