{
  "type": "Feature",
  "properties": {
    "iso:country":"GB",
    "wof:name":"N3 2QD",
    "wof:placetype":"postalcode"
},
  "geometry": {"coordinates":[-0.18605491861393,51.60171863396256],"type":"Point"}
}