{
  "type": "Feature",
  "properties": {
    "iso:country":"GB",
    "wof:name":"BD22 9AB",
    "wof:placetype":"postalcode"
},
  "geometry": {"coordinates":[-1.92458615048246,53.84007950036996],"type":"Point"}
}