{
  "type": "Feature",
  "properties": {
    "date:inception_lower":"1980-01-01",
    "date:inception_upper":"1980-01-31",
    "iso:country":"GB",
    "wof:name":"BD22 9AB",
    "wof:placetype":"postalcode"
},
  "geometry": {"coordinates":[-1.924586,53.840079],"type":"Point"}
}