{
  "type": "Feature",
  "properties": {
    "iso:country": "GB",
    "wof:name": "BD22 9AB",
    "wof:placetype": "postalcode"
  },
  "geometry": {"coordinates":[-1.924586,53.840079],"type":"Point"}
}
