{
  "type": "Feature",
  "properties": {
    "iso:country":"GB",
    "wof:name":"BD22 7AT",
    "wof:placetype":"postalcode"
},
  "geometry": {"coordinates":[-1.9274311056796,53.84709180140757],"type":"Point"}
}