{
  "type": "Feature",
  "properties": {
    "iso:country":"GB",
    "wof:name":"GU31 5AT",
    "wof:placetype":"postalcode"
},
  "geometry": {"coordinates":[-0.9081635629294,51.0124102390027],"type":"Point"}
}