{
  "type": "Feature",
  "properties": {
    "iso:country": "GB",
    "wof:name": "NN3 5AB",
    "wof:placetype": "postalcode"
  },
  "geometry": {"coordinates":[-0.805795,52.257192],"type":"Point"}
}
