{
  "type": "Feature",
  "properties": {
    "iso:country": "GB",
    "wof:name": "L3 4DZ",
    "wof:placetype": "postalcode"
  },
  "geometry": {"coordinates":[-2.981272,53.387502],"type":"Point"}
}
