{
  "type": "Feature",
  "properties": {
    "iso:country": "GB",
    "wof:name": "LS10 1DR",
    "wof:placetype": "postalcode"
  },
  "geometry": {"coordinates":[-1.516392,53.776824],"type":"Point"}
}
