{
  "type": "Feature",
  "properties": {
    "date:inception_lower": "2006-07-01",
    "date:inception_upper": "2006-07-01",
    "iso:country": "GB",
    "wof:name": "LS10 1DR",
    "wof:placetype": "postalcode"
  },
  "geometry": {"coordinates":[-1.516392,53.776824],"type":"Point"}
}
