{
  "type": "Feature",
  "properties": {
    "iso:country": "GB",
    "wof:name": "CA11 9NQ",
    "wof:placetype": "postalcode"
  },
  "geometry": {"coordinates":[-2.773189,54.685221],"type":"Point"}
}
