{
  "type": "Feature",
  "properties": {
    "iso:country":"GB",
    "wof:name":"CA11 9NQ",
    "wof:placetype":"postalcode"
},
  "geometry": {"coordinates":[-2.77316155284713,54.68480970368469],"type":"Point"}
}