{
  "type": "Feature",
  "properties": {
    "date:inception_lower": "2021-06-01",
    "date:inception_upper": "2021-06-01",
    "iso:country": "GB",
    "wof:name": "CH4 0TT",
    "wof:placetype": "postalcode"
  },
  "geometry": {"coordinates":[-3.037283,53.153496],"type":"Point"}
}
