{
  "type": "Feature",
  "properties": {
    "iso:country": "GB",
    "wof:name": "LL11 3LQ",
    "wof:placetype": "postalcode"
  },
  "geometry": {"coordinates":[-3.062821,53.05098],"type":"Point"}
}
