{
  "type": "Feature",
  "properties": {
    "date:inception_lower":"2001-12-01",
    "date:inception_upper":"2001-12-31",
    "iso:country":"GB",
    "wof:name":"LL11 3LQ",
    "wof:placetype":"postalcode"
},
  "geometry": {"coordinates":[-3.062821,53.05098],"type":"Point"}
}