{
  "type": "Feature",
  "properties": {
    "iso:country":"GB",
    "wof:name":"LL11 3LQ",
    "wof:placetype":"postalcode"
},
  "geometry": {"coordinates":[-3.06264095911927,53.05093015656775],"type":"Point"}
}