{
  "type": "Feature",
  "properties": {
    "iso:country": "GB",
    "wof:name": "LA2 6HJ",
    "wof:placetype": "postalcode"
  },
  "geometry": {"coordinates":[-2.811363,54.091583],"type":"Point"}
}
