{
  "type": "Feature",
  "properties": {
    "iso:country":"GB",
    "wof:name":"LA2 6HJ",
    "wof:placetype":"postalcode"
},
  "geometry": {"coordinates":[-2.81136293564134,54.09158301199545],"type":"Point"}
}