{
  "type": "Feature",
  "properties": {
    "date:inception_lower":"1998-06-01",
    "date:inception_upper":"1998-06-30",
    "iso:country":"GB",
    "wof:name":"LL65 1WY",
    "wof:placetype":"postalcode"
},
  "geometry": {"coordinates":[-4.632844,53.311993],"type":"Point"}
}