{
  "type": "Feature",
  "properties": {
    "iso:country":"GB",
    "wof:name":"DE1 2TU",
    "wof:placetype":"postalcode"
},
  "geometry": {"coordinates":[-1.46742727059977,52.91188106457577],"type":"Point"}
}