{
  "type": "Feature",
  "properties": {
    "date:inception_lower": "1980-01-01",
    "date:inception_upper": "1980-01-01",
    "iso:country": "GB",
    "wof:name": "LN2 2UP",
    "wof:placetype": "postalcode"
  },
  "geometry": {"coordinates":[-0.431973,53.283921],"type":"Point"}
}
