{
  "type": "Feature",
  "properties": {
    "iso:country":"GB",
    "wof:name":"LN2 2UP",
    "wof:placetype":"postalcode"
},
  "geometry": {"coordinates":[-0.43197302472729,53.28392062615043],"type":"Point"}
}