{
  "type": "Feature",
  "properties": {
    "iso:country":"GB",
    "wof:name":"TR26 1BB",
    "wof:placetype":"postalcode"
},
  "geometry": {"coordinates":[-5.48826131102949,50.20928082116863],"type":"Point"}
}