{
  "type": "Feature",
  "properties": {
    "date:inception_lower":"1980-01-01",
    "date:inception_upper":"1980-01-31",
    "iso:country":"GB",
    "wof:name":"TR26 1BB",
    "wof:placetype":"postalcode"
},
  "geometry": {"coordinates":[-5.488261,50.209281],"type":"Point"}
}