{
  "type": "Feature",
  "properties": {
    "iso:country":"GB",
    "wof:name":"HR6 9SR",
    "wof:placetype":"postalcode"
},
  "geometry": {"coordinates":[-2.85630196320222,52.27342732177091],"type":"Point"}
}