{
  "type": "Feature",
  "properties": {
    "iso:country": "GB",
    "wof:name": "HR6 9SR",
    "wof:placetype": "postalcode"
  },
  "geometry": {"coordinates":[-2.856302,52.273427],"type":"Point"}
}
