{
  "type": "Feature",
  "properties": {
    "date:inception_lower": "1996-06-01",
    "date:inception_upper": "1996-06-01",
    "iso:country": "GB",
    "wof:name": "HX1 4UB",
    "wof:placetype": "postalcode"
  },
  "geometry": {"coordinates":[-1.887953,53.728995],"type":"Point"}
}
