{
  "type": "Feature",
  "properties": {
    "iso:country":"GB",
    "wof:name":"IP25 6AY",
    "wof:placetype":"postalcode"
},
  "geometry": {"coordinates":[0.82378636458889,52.5693633924157],"type":"Point"}
}