{
  "type": "Feature",
  "properties": {
    "iso:country": "GB",
    "wof:name": "IP25 6AY",
    "wof:placetype": "postalcode"
  },
  "geometry": {"coordinates":[0.823786,52.569363],"type":"Point"}
}
