{
  "type": "Feature",
  "properties": {
    "iso:country":"GB",
    "wof:name":"OL12 9SZ",
    "wof:placetype":"postalcode"
},
  "geometry": {"coordinates":[-2.14895263151794,53.6297615694026],"type":"Point"}
}