{
  "type": "Feature",
  "properties": {
    "iso:country": "GB",
    "wof:name": "SO50 8PY",
    "wof:placetype": "postalcode"
  },
  "geometry": {"coordinates":[-1.311285,50.967695],"type":"Point"}
}
