{
  "type": "Feature",
  "properties": {
    "iso:country":"GB",
    "wof:name":"SW17 9ET",
    "wof:placetype":"postalcode"
},
  "geometry": {"coordinates":[-0.15915189531604,51.41977740129666],"type":"Point"}
}