{
  "type": "Feature",
  "properties": {
    "iso:country":"GB",
    "wof:name":"KW17 2HD",
    "wof:placetype":"postalcode"
},
  "geometry": {"coordinates":[-3.05151756124607,59.08987468306996],"type":"Point"}
}