{
  "type": "Feature",
  "properties": {
    "date:inception_lower": "1980-01-01",
    "date:inception_upper": "1980-01-01",
    "iso:country": "GB",
    "wof:name": "KW17 2HD",
    "wof:placetype": "postalcode"
  },
  "geometry": {"coordinates":[-3.051517,59.089875],"type":"Point"}
}
