{
  "type": "Feature",
  "properties": {
    "iso:country":"GB",
    "wof:name":"ST7 1HQ",
    "wof:placetype":"postalcode"
},
  "geometry": {"coordinates":[-2.23882992759147,53.09215812105976],"type":"Point"}
}