{
  "type": "Feature",
  "properties": {
    "iso:country":"GB",
    "wof:name":"W1U 3HB",
    "wof:placetype":"postalcode"
},
  "geometry": {"coordinates":[-0.15401517154744,51.51686114658111],"type":"Point"}
}