{
  "type": "Feature",
  "properties": {
    "iso:country": "GB",
    "wof:name": "W1U 3HB",
    "wof:placetype": "postalcode"
  },
  "geometry": {"coordinates":[-0.154015,51.516861],"type":"Point"}
}
