{
  "type": "Feature",
  "properties": {
    "iso:country":"GB",
    "wof:name":"PH1 2SX",
    "wof:placetype":"postalcode"
},
  "geometry": {"coordinates":[-3.48260088915552,56.40432816215171],"type":"Point"}
}