{
  "type": "Feature",
  "properties": {
    "date:inception_lower":"1996-12-01",
    "date:inception_upper":"1996-12-31",
    "iso:country":"GB",
    "wof:name":"PH1 2SX",
    "wof:placetype":"postalcode"
},
  "geometry": {"coordinates":[-3.482601,56.404328],"type":"Point"}
}