{
  "type": "Feature",
  "properties": {
    "iso:country": "GB",
    "wof:name": "M26 2TW",
    "wof:placetype": "postalcode"
  },
  "geometry": {"coordinates":[-2.31891,53.560945],"type":"Point"}
}
