{
  "type": "Feature",
  "properties": {
    "date:inception_lower": "1980-01-01",
    "date:inception_upper": "1980-01-01",
    "iso:country": "GB",
    "wof:name": "UB3 5LH",
    "wof:placetype": "postalcode"
  },
  "geometry": {"coordinates":[-0.437152,51.483289],"type":"Point"}
}
