{
  "type": "Feature",
  "properties": {
    "iso:country":"GB",
    "wof:name":"LN1 2EA",
    "wof:placetype":"postalcode"
},
  "geometry": {"coordinates":[-0.66154706517404,53.31387495280183],"type":"Point"}
}