{
  "type": "Feature",
  "properties": {
    "iso:country":"GB",
    "wof:name":"HA3 9LA",
    "wof:placetype":"postalcode"
},
  "geometry": {"coordinates":[-0.29314328962509,51.59164379187204],"type":"Point"}
}