{
  "type": "Feature",
  "properties": {
    "iso:country":"GB",
    "wof:name":"NR1 2NE",
    "wof:placetype":"postalcode"
},
  "geometry": {"coordinates":[1.29976601180055,52.60883975722366],"type":"Point"}
}