{
  "type": "Feature",
  "properties": {
    "date:inception_lower":"2002-07-01",
    "date:inception_upper":"2002-07-31",
    "iso:country":"GB",
    "wof:name":"S64 0LB",
    "wof:placetype":"postalcode"
},
  "geometry": {"coordinates":[-1.258057,53.493466],"type":"Point"}
}