{
  "type": "Feature",
  "properties": {
    "iso:country":"GB",
    "wof:name":"S64 0LB",
    "wof:placetype":"postalcode"
},
  "geometry": {"coordinates":[-1.25805708838752,53.49346595101421],"type":"Point"}
}