{
  "type": "Feature",
  "properties": {
    "iso:country":"GB",
    "wof:name":"AL4 9LA",
    "wof:placetype":"postalcode"
},
  "geometry": {"coordinates":[-0.30892993901661,51.77741490234036],"type":"Point"}
}