{
  "type": "Feature",
  "properties": {
    "date:inception_lower":"2000-06-01",
    "date:inception_upper":"2000-06-30",
    "iso:country":"GB",
    "wof:name":"E6 1HJ",
    "wof:placetype":"postalcode"
},
  "geometry": {"coordinates":[0.051945,51.534679],"type":"Point"}
}