{
  "type": "Feature",
  "properties": {
    "iso:country":"GB",
    "wof:name":"E6 1HJ",
    "wof:placetype":"postalcode"
},
  "geometry": {"coordinates":[0.05194538108044,51.53467945286098],"type":"Point"}
}