{
  "type": "Feature",
  "properties": {
    "iso:country":"GB",
    "wof:name":"HA3 9UW",
    "wof:placetype":"postalcode"
},
  "geometry": {"coordinates":[-0.29298850811043,51.57612992732916],"type":"Point"}
}