{
  "type": "Feature",
  "properties": {
    "iso:country":"GB",
    "wof:name":"CF15 7LB",
    "wof:placetype":"postalcode"
},
  "geometry": {"coordinates":[-3.25032410149214,51.53199090363446],"type":"Point"}
}