{
  "type": "Feature",
  "properties": {
    "iso:country": "GB",
    "wof:name": "DL1 3AB",
    "wof:placetype": "postalcode"
  },
  "geometry": {"coordinates":[-1.547857,54.551921],"type":"Point"}
}
