{
  "type": "Feature",
  "properties": {
    "iso:country":"GB",
    "wof:name":"NW7 2RA",
    "wof:placetype":"postalcode"
},
  "geometry": {"coordinates":[-0.23597526218345,51.61546431287508],"type":"Point"}
}