{
  "type": "Feature",
  "properties": {
    "iso:country":"GB",
    "wof:name":"SE1 4HB",
    "wof:placetype":"postalcode"
},
  "geometry": {"coordinates":[-0.09463590299608,51.4981332644313],"type":"Point"}
}