{
  "type": "Feature",
  "properties": {
    "date:inception_lower":"2000-06-01",
    "date:inception_upper":"2000-06-30",
    "iso:country":"GB",
    "wof:name":"SE1 4HB",
    "wof:placetype":"postalcode"
},
  "geometry": {"coordinates":[-0.09461,51.498135],"type":"Point"}
}