{
  "type": "Feature",
  "properties": {
    "iso:country": "GB",
    "wof:name": "SE1 4HB",
    "wof:placetype": "postalcode"
  },
  "geometry": {"coordinates":[-0.094641,51.498099],"type":"Point"}
}
