{
  "type": "Feature",
  "properties": {
    "date:inception_lower": "1980-01-01",
    "date:inception_upper": "1980-01-01",
    "iso:country": "GB",
    "wof:name": "EX15 3LR",
    "wof:placetype": "postalcode"
  },
  "geometry": {"coordinates":[-3.289915,50.908201],"type":"Point"}
}
