{
  "type": "Feature",
  "properties": {
    "iso:country":"GB",
    "wof:name":"BD18 1HW",
    "wof:placetype":"postalcode"
},
  "geometry": {"coordinates":[-1.75414573097686,53.83588802874547],"type":"Point"}
}