{
  "type": "Feature",
  "properties": {
    "iso:country": "GB",
    "wof:name": "BD18 1HW",
    "wof:placetype": "postalcode"
  },
  "geometry": {"coordinates":[-1.754146,53.835888],"type":"Point"}
}
