{
  "type": "Feature",
  "properties": {
    "iso:country":"GB",
    "wof:name":"B46 3NN",
    "wof:placetype":"postalcode"
},
  "geometry": {"coordinates":[-1.71058909265826,52.49481997414801],"type":"Point"}
}