{
  "type": "Feature",
  "properties": {
    "iso:country": "GB",
    "wof:name": "BS3 2DL",
    "wof:placetype": "postalcode"
  },
  "geometry": {"coordinates":[-2.617707,51.439443],"type":"Point"}
}
