{
  "type": "Feature",
  "properties": {
    "iso:country":"GB",
    "wof:name":"BS3 2DL",
    "wof:placetype":"postalcode"
},
  "geometry": {"coordinates":[-2.61770693751954,51.43944286234429],"type":"Point"}
}