{
  "type": "Feature",
  "properties": {
    "iso:country":"GB",
    "wof:name":"WR14 4EL",
    "wof:placetype":"postalcode"
},
  "geometry": {"coordinates":[-2.34089843885629,52.09514434776654],"type":"Point"}
}