{
  "type": "Feature",
  "properties": {
    "date:inception_lower":"1980-01-01",
    "date:inception_upper":"1980-01-31",
    "iso:country":"GB",
    "wof:name":"WR14 4EL",
    "wof:placetype":"postalcode"
},
  "geometry": {"coordinates":[-2.340898,52.095144],"type":"Point"}
}