{
  "type": "Feature",
  "properties": {
    "iso:country":"GB",
    "wof:name":"SW6 1JW",
    "wof:placetype":"postalcode"
},
  "geometry": {"coordinates":[-0.1957781860812,51.48491331078314],"type":"Point"}
}