{
  "type": "Feature",
  "properties": {
    "iso:country":"GB",
    "wof:name":"SW19 6EB",
    "wof:placetype":"postalcode"
},
  "geometry": {"coordinates":[-0.21942978894106,51.44417916530667],"type":"Point"}
}