{
  "type": "Feature",
  "properties": {
    "iso:country":"GB",
    "wof:name":"DN4 7RW",
    "wof:placetype":"postalcode"
},
  "geometry": {"coordinates":[-1.09691892929797,53.50505851571005],"type":"Point"}
}