{
  "type": "Feature",
  "properties": {
    "date:inception_lower": "1980-01-01",
    "date:inception_upper": "1980-01-01",
    "iso:country": "GB",
    "wof:name": "GU35 8PG",
    "wof:placetype": "postalcode"
  },
  "geometry": {"coordinates":[-0.829222,51.120923],"type":"Point"}
}
