{
  "type": "Feature",
  "properties": {
    "iso:country":"GB",
    "wof:name":"GU35 8PG",
    "wof:placetype":"postalcode"
},
  "geometry": {"coordinates":[-0.82922157475965,51.12092321909328],"type":"Point"}
}