{
  "type": "Feature",
  "properties": {
    "iso:country":"GB",
    "wof:name":"WS9 0DT",
    "wof:placetype":"postalcode"
},
  "geometry": {"coordinates":[-1.93161160649406,52.6008114019285],"type":"Point"}
}