{
  "type": "Feature",
  "properties": {
    "iso:country":"GB",
    "wof:name":"AL8 6XY",
    "wof:placetype":"postalcode"
},
  "geometry": {"coordinates":[-0.2154671868683,51.79230883641884],"type":"Point"}
}