{
  "type": "Feature",
  "properties": {
    "iso:country": "GB",
    "wof:name": "AL8 6XY",
    "wof:placetype": "postalcode"
  },
  "geometry": {"coordinates":[-0.215443,51.792315],"type":"Point"}
}
