{
  "type": "Feature",
  "properties": {
    "date:inception_lower": "1980-01-01",
    "date:inception_upper": "1980-01-01",
    "iso:country": "GB",
    "wof:name": "AL8 6XY",
    "wof:placetype": "postalcode"
  },
  "geometry": {"coordinates":[-0.215513,51.79237],"type":"Point"}
}
