{
  "type": "Feature",
  "properties": {
    "iso:country":"GB",
    "wof:name":"WS10 9FD",
    "wof:placetype":"postalcode"
},
  "geometry": {"coordinates":[-2.02121695690887,52.56888829291932],"type":"Point"}
}