{
  "type": "Feature",
  "properties": {
    "date:inception_lower": "2007-09-01",
    "date:inception_upper": "2007-09-01",
    "iso:country": "GB",
    "wof:name": "WS10 9FD",
    "wof:placetype": "postalcode"
  },
  "geometry": {"coordinates":[-2.021217,52.568888],"type":"Point"}
}
