{
  "type": "Feature",
  "properties": {
    "iso:country":"GB",
    "wof:name":"SL4 3JF",
    "wof:placetype":"postalcode"
},
  "geometry": {"coordinates":[-0.61064014495303,51.47185834659501],"type":"Point"}
}