{
  "type": "Feature",
  "properties": {
    "date:inception_lower":"2010-08-01",
    "date:inception_upper":"2010-08-31",
    "iso:country":"GB",
    "wof:name":"DE56 1AB",
    "wof:placetype":"postalcode"
},
  "geometry": {"coordinates":[-1.485432,53.019914],"type":"Point"}
}