{
  "type": "Feature",
  "properties": {
    "iso:country":"GB",
    "wof:name":"LS29 6AA",
    "wof:placetype":"postalcode"
},
  "geometry": {"coordinates":[-1.72990549088035,53.89548854467603],"type":"Point"}
}