{
  "type": "Feature",
  "properties": {
    "iso:country": "GB",
    "wof:name": "LS29 6AA",
    "wof:placetype": "postalcode"
  },
  "geometry": {"coordinates":[-1.729905,53.895489],"type":"Point"}
}
