{
  "type": "Feature",
  "properties": {
    "iso:country":"GB",
    "wof:name":"BS41 9BN",
    "wof:placetype":"postalcode"
},
  "geometry": {"coordinates":[-2.66863585875657,51.42846322307221],"type":"Point"}
}