{
  "type": "Feature",
  "properties": {
    "iso:country":"GB",
    "wof:name":"M24 6HH",
    "wof:placetype":"postalcode"
},
  "geometry": {"coordinates":[-2.20260073866059,53.56301663313211],"type":"Point"}
}