{
  "type": "Feature",
  "properties": {
    "iso:country":"GB",
    "wof:name":"DE24 9EN",
    "wof:placetype":"postalcode"
},
  "geometry": {"coordinates":[-1.44961910359126,52.88084932070312],"type":"Point"}
}