{
  "type": "Feature",
  "properties": {
    "date:inception_lower":"1992-08-01",
    "date:inception_upper":"1992-08-31",
    "iso:country":"GB",
    "wof:name":"DE24 9EN",
    "wof:placetype":"postalcode"
},
  "geometry": {"coordinates":[-1.449619,52.880849],"type":"Point"}
}