{
  "type": "Feature",
  "properties": {
    "iso:country": "GB",
    "wof:name": "DE24 9EN",
    "wof:placetype": "postalcode"
  },
  "geometry": {"coordinates":[-1.449619,52.880849],"type":"Point"}
}
