{
  "type": "Feature",
  "properties": {
    "iso:country":"GB",
    "wof:name":"B45 9LG",
    "wof:placetype":"postalcode"
},
  "geometry": {"coordinates":[-2.0096534296907,52.38793091487553],"type":"Point"}
}