{
  "type": "Feature",
  "properties": {
    "iso:country": "GB",
    "wof:name": "PO16 7AD",
    "wof:placetype": "postalcode"
  },
  "geometry": {"coordinates":[-1.173999,50.855253],"type":"Point"}
}
