{
  "type": "Feature",
  "properties": {
    "iso:country":"GB",
    "wof:name":"BS23 2TF",
    "wof:placetype":"postalcode"
},
  "geometry": {"coordinates":[-2.96556083824435,51.35390002932283],"type":"Point"}
}