{
  "type": "Feature",
  "properties": {
    "date:inception_lower": "1980-01-01",
    "date:inception_upper": "1980-01-01",
    "iso:country": "GB",
    "wof:name": "AL10 9NR",
    "wof:placetype": "postalcode"
  },
  "geometry": {"coordinates":[-0.24811,51.757443],"type":"Point"}
}
