{
  "type": "Feature",
  "properties": {
    "iso:country":"GB",
    "wof:name":"B28 0NG",
    "wof:placetype":"postalcode"
},
  "geometry": {"coordinates":[-1.84605476756615,52.41805609899553],"type":"Point"}
}