{
  "type": "Feature",
  "properties": {
    "iso:country":"GB",
    "wof:name":"BS22 7BU",
    "wof:placetype":"postalcode"
},
  "geometry": {"coordinates":[-2.90291693011755,51.36326577111453],"type":"Point"}
}