{
  "type": "Feature",
  "properties": {
    "iso:country":"GB",
    "wof:name":"NR11 8BH",
    "wof:placetype":"postalcode"
},
  "geometry": {"coordinates":[1.43736400811817,52.87723039784887],"type":"Point"}
}