{
  "type": "Feature",
  "properties": {
    "date:inception_lower":"1980-01-01",
    "date:inception_upper":"1980-01-31",
    "iso:country":"GB",
    "wof:name":"NR11 8BH",
    "wof:placetype":"postalcode"
},
  "geometry": {"coordinates":[1.43751,52.877345],"type":"Point"}
}