{
  "type": "Feature",
  "properties": {
    "date:inception_lower": "2018-01-01",
    "date:inception_upper": "2018-01-01",
    "iso:country": "GB",
    "wof:name": "TA21 8FF",
    "wof:placetype": "postalcode"
  },
  "geometry": {"coordinates":[-3.228422,50.98697],"type":"Point"}
}
