{
  "type": "Feature",
  "properties": {
    "date:inception_lower": "1984-02-01",
    "date:inception_upper": "1984-02-01",
    "iso:country": "GB",
    "wof:name": "BB1 5HA",
    "wof:placetype": "postalcode"
  },
  "geometry": {"coordinates":[-2.469438,53.755118],"type":"Point"}
}
