{
  "type": "Feature",
  "properties": {
    "iso:country": "GB",
    "wof:name": "TN12 9NN",
    "wof:placetype": "postalcode"
  },
  "geometry": {"coordinates":[0.484517,51.165644],"type":"Point"}
}
