{
  "type": "Feature",
  "properties": {
    "iso:country":"GB",
    "wof:name":"EH33 2RA",
    "wof:placetype":"postalcode"
},
  "geometry": {"coordinates":[-2.95413787691707,55.93931346578999],"type":"Point"}
}