{
  "type": "Feature",
  "properties": {
    "date:inception_lower": "2011-02-01",
    "date:inception_upper": "2011-02-01",
    "iso:country": "GB",
    "wof:name": "EH33 2RA",
    "wof:placetype": "postalcode"
  },
  "geometry": {"coordinates":[-2.954138,55.939313],"type":"Point"}
}
