{
  "type": "Feature",
  "properties": {
    "iso:country":"GB",
    "wof:name":"ML9 2QJ",
    "wof:placetype":"postalcode"
},
  "geometry": {"coordinates":[-3.96187083350664,55.7340493940922],"type":"Point"}
}