{
  "type": "Feature",
  "properties": {
    "date:inception_lower": "1980-01-01",
    "date:inception_upper": "1980-01-01",
    "iso:country": "GB",
    "wof:name": "ML9 2QJ",
    "wof:placetype": "postalcode"
  },
  "geometry": {"coordinates":[-3.961871,55.734049],"type":"Point"}
}
