{
  "type": "Feature",
  "properties": {
    "iso:country":"GB",
    "wof:name":"FY3 7BH",
    "wof:placetype":"postalcode"
},
  "geometry": {"coordinates":[-3.03015969106128,53.82916177468604],"type":"Point"}
}