{
  "type": "Feature",
  "properties": {
    "iso:country":"GB",
    "wof:name":"ML5 5QA",
    "wof:placetype":"postalcode"
},
  "geometry": {"coordinates":[-4.05460192647476,55.84791844291401],"type":"Point"}
}