{
  "type": "Feature",
  "properties": {
    "iso:country":"GB",
    "wof:name":"CA20 1BS",
    "wof:placetype":"postalcode"
},
  "geometry": {"coordinates":[-3.4615353956665,54.42896896065437],"type":"Point"}
}