{
  "type": "Feature",
  "properties": {
    "iso:country": "GB",
    "wof:name": "CA20 1BS",
    "wof:placetype": "postalcode"
  },
  "geometry": {"coordinates":[-3.457929,54.428043],"type":"Point"}
}
