{
  "type": "Feature",
  "properties": {
    "iso:country":"GB",
    "wof:name":"TS3 7QZ",
    "wof:placetype":"postalcode"
},
  "geometry": {"coordinates":[-1.20999501830307,54.56226561351904],"type":"Point"}
}