{
  "type": "Feature",
  "properties": {
    "date:inception_lower":"1994-05-01",
    "date:inception_upper":"1994-05-31",
    "iso:country":"GB",
    "wof:name":"M40 2RF",
    "wof:placetype":"postalcode"
},
  "geometry": {"coordinates":[-2.181004,53.49411],"type":"Point"}
}