{
  "type": "Feature",
  "properties": {
    "iso:country": "GB",
    "wof:name": "OX12 0GE",
    "wof:placetype": "postalcode"
  },
  "geometry": {"coordinates":[-1.433536,51.607209],"type":"Point"}
}
