{
  "type": "Feature",
  "properties": {
    "date:inception_lower": "2019-03-01",
    "date:inception_upper": "2019-03-01",
    "iso:country": "GB",
    "wof:name": "OX12 0GE",
    "wof:placetype": "postalcode"
  },
  "geometry": {"coordinates":[-1.43341,51.606921],"type":"Point"}
}
