{
  "type": "Feature",
  "properties": {
    "iso:country":"GB",
    "wof:name":"PO38 3AJ",
    "wof:placetype":"postalcode"
},
  "geometry": {"coordinates":[-1.22744279221731,50.63310089480554],"type":"Point"}
}