{
  "type": "Feature",
  "properties": {
    "date:inception_lower":"1980-01-01",
    "date:inception_upper":"1980-01-31",
    "iso:country":"GB",
    "wof:name":"PO38 3AJ",
    "wof:placetype":"postalcode"
},
  "geometry": {"coordinates":[-1.227443,50.633101],"type":"Point"}
}