{
  "type": "Feature",
  "properties": {
    "iso:country": "GB",
    "wof:name": "LE8 8TU",
    "wof:placetype": "postalcode"
  },
  "geometry": {"coordinates":[-1.042764,52.534106],"type":"Point"}
}
