{
  "type": "Feature",
  "properties": {
    "iso:country": "GB",
    "wof:name": "RH10 6LW",
    "wof:placetype": "postalcode"
  },
  "geometry": {"coordinates":[-0.184041,51.11156],"type":"Point"}
}
