{
  "type": "Feature",
  "properties": {
    "iso:country": "GB",
    "wof:name": "SG4 9HS",
    "wof:placetype": "postalcode"
  },
  "geometry": {"coordinates":[-0.267204,51.943139],"type":"Point"}
}
