{
  "type": "Feature",
  "properties": {
    "iso:country": "GB",
    "wof:name": "IP12 4UN",
    "wof:placetype": "postalcode"
  },
  "geometry": {"coordinates":[1.300358,52.095665],"type":"Point"}
}
