{
  "type": "Feature",
  "properties": {
    "iso:country": "GB",
    "wof:name": "CA7 5BP",
    "wof:placetype": "postalcode"
  },
  "geometry": {"coordinates":[-3.211375,54.953907],"type":"Point"}
}
