{
  "type": "Feature",
  "properties": {
    "iso:country":"GB",
    "wof:name":"KT13 9QQ",
    "wof:placetype":"postalcode"
},
  "geometry": {"coordinates":[-0.43577092383306,51.37583922395186],"type":"Point"}
}