{
  "type": "Feature",
  "properties": {
    "date:inception_lower":"1980-01-01",
    "date:inception_upper":"1980-01-31",
    "iso:country":"GB",
    "wof:name":"PO4 0QR",
    "wof:placetype":"postalcode"
},
  "geometry": {"coordinates":[-1.076946,50.781334],"type":"Point"}
}