{
  "type": "Feature",
  "properties": {
    "iso:country": "GB",
    "wof:name": "PO4 0QR",
    "wof:placetype": "postalcode"
  },
  "geometry": {"coordinates":[-1.076946,50.781334],"type":"Point"}
}
