{
  "type": "Feature",
  "properties": {
    "iso:country":"GB",
    "wof:name":"PO4 0QR",
    "wof:placetype":"postalcode"
},
  "geometry": {"coordinates":[-1.07686078108216,50.78132400222454],"type":"Point"}
}