{
  "type": "Feature",
  "properties": {
    "iso:country":"GB",
    "wof:name":"LS19 6RX",
    "wof:placetype":"postalcode"
},
  "geometry": {"coordinates":[-1.68316268692808,53.85262803003997],"type":"Point"}
}