{
  "type": "Feature",
  "properties": {
    "iso:country":"GB",
    "wof:name":"RH20 4JE",
    "wof:placetype":"postalcode"
},
  "geometry": {"coordinates":[-0.46156852990321,50.91851550322743],"type":"Point"}
}