{
  "type": "Feature",
  "properties": {
    "iso:country":"GB",
    "wof:name":"ST6 6AW",
    "wof:placetype":"postalcode"
},
  "geometry": {"coordinates":[-2.21019309291464,53.05607614321521],"type":"Point"}
}