{
  "type": "Feature",
  "properties": {
    "iso:country":"GB",
    "wof:name":"BA1 6DF",
    "wof:placetype":"postalcode"
},
  "geometry": {"coordinates":[-2.35563431834373,51.39192257491379],"type":"Point"}
}