{
  "type": "Feature",
  "properties": {
    "iso:country": "GB",
    "wof:name": "PO30 4PP",
    "wof:placetype": "postalcode"
  },
  "geometry": {"coordinates":[-1.420898,50.700257],"type":"Point"}
}
