{
  "type": "Feature",
  "properties": {
    "iso:country":"GB",
    "wof:name":"PO30 4PP",
    "wof:placetype":"postalcode"
},
  "geometry": {"coordinates":[-1.42089770807274,50.7002569284682],"type":"Point"}
}