{
  "type": "Feature",
  "properties": {
    "date:inception_lower":"1980-01-01",
    "date:inception_upper":"1980-01-31",
    "iso:country":"GB",
    "wof:name":"PO30 4PP",
    "wof:placetype":"postalcode"
},
  "geometry": {"coordinates":[-1.420898,50.700257],"type":"Point"}
}