{
  "type": "Feature",
  "properties": {
    "date:inception_lower": "1980-01-01",
    "date:inception_upper": "1980-01-01",
    "iso:country": "GB",
    "wof:name": "LS9 8EE",
    "wof:placetype": "postalcode"
  },
  "geometry": {"coordinates":[-1.52887,53.791648],"type":"Point"}
}
