{
  "type": "Feature",
  "properties": {
    "iso:country":"GB",
    "wof:name":"LE15 7FU",
    "wof:placetype":"postalcode"
},
  "geometry": {"coordinates":[-0.74167416716857,52.68183169073727],"type":"Point"}
}