{
  "type": "Feature",
  "properties": {
    "iso:country":"GB",
    "wof:name":"GU15 1JN",
    "wof:placetype":"postalcode"
},
  "geometry": {"coordinates":[-0.72677359526415,51.33005832001643],"type":"Point"}
}