{
  "type": "Feature",
  "properties": {
    "iso:country":"GB",
    "wof:name":"E17 7NY",
    "wof:placetype":"postalcode"
},
  "geometry": {"coordinates":[-0.02825425761554,51.58036139406344],"type":"Point"}
}