{
  "type": "Feature",
  "properties": {
    "iso:country": "GB",
    "wof:name": "NE12 8DX",
    "wof:placetype": "postalcode"
  },
  "geometry": {"coordinates":[-1.582469,55.015976],"type":"Point"}
}
