{
  "type": "Feature",
  "properties": {
    "iso:country": "GB",
    "wof:name": "BD9 6ER",
    "wof:placetype": "postalcode"
  },
  "geometry": {"coordinates":[-1.813253,53.81268],"type":"Point"}
}
