{
  "type": "Feature",
  "properties": {
    "iso:country":"GB",
    "wof:name":"BD9 6ER",
    "wof:placetype":"postalcode"
},
  "geometry": {"coordinates":[-1.81325299593287,53.81267976419286],"type":"Point"}
}