{
  "type": "Feature",
  "properties": {
    "iso:country":"GB",
    "wof:name":"CF24 5EU",
    "wof:placetype":"postalcode"
},
  "geometry": {"coordinates":[-3.15953617811208,51.47393691233194],"type":"Point"}
}