{
  "type": "Feature",
  "properties": {
    "date:inception_lower": "1999-06-01",
    "date:inception_upper": "1999-06-01",
    "iso:country": "GB",
    "wof:name": "CF24 5EU",
    "wof:placetype": "postalcode"
  },
  "geometry": {"coordinates":[-3.159545,51.473938],"type":"Point"}
}
