{
  "type": "Feature",
  "properties": {
    "iso:country": "GB",
    "wof:name": "CF24 5EU",
    "wof:placetype": "postalcode"
  },
  "geometry": {"coordinates":[-3.160003,51.474383],"type":"Point"}
}
