{
  "type": "Feature",
  "properties": {
    "iso:country":"GB",
    "wof:name":"M8 0AB",
    "wof:placetype":"postalcode"
},
  "geometry": {"coordinates":[-2.24142140791449,53.50558067838676],"type":"Point"}
}