{
  "type": "Feature",
  "properties": {
    "date:inception_lower":"1998-06-01",
    "date:inception_upper":"1998-06-30",
    "iso:country":"GB",
    "wof:name":"SK8 7GF",
    "wof:placetype":"postalcode"
},
  "geometry": {"coordinates":[-2.179298,53.375689],"type":"Point"}
}