{
  "type": "Feature",
  "properties": {
    "iso:country":"GB",
    "wof:name":"SK8 7GF",
    "wof:placetype":"postalcode"
},
  "geometry": {"coordinates":[-2.17929795869597,53.37568933616453],"type":"Point"}
}