{
  "type": "Feature",
  "properties": {
    "iso:country":"GB",
    "wof:name":"NG24 3RZ",
    "wof:placetype":"postalcode"
},
  "geometry": {"coordinates":[-0.76823133297659,53.04836038015806],"type":"Point"}
}