{
  "type": "Feature",
  "properties": {
    "date:inception_lower": "2006-10-01",
    "date:inception_upper": "2006-10-01",
    "iso:country": "GB",
    "wof:name": "NG24 3RZ",
    "wof:placetype": "postalcode"
  },
  "geometry": {"coordinates":[-0.768231,53.04836],"type":"Point"}
}
