{
  "type": "Feature",
  "properties": {
    "date:inception_lower": "2018-12-01",
    "date:inception_upper": "2018-12-01",
    "iso:country": "GB",
    "wof:name": "DA1 5RQ",
    "wof:placetype": "postalcode"
  },
  "geometry": {"coordinates":[0.222902,51.460394],"type":"Point"}
}
