{
  "type": "Feature",
  "properties": {
    "iso:country":"GB",
    "wof:name":"CB6 1BZ",
    "wof:placetype":"postalcode"
},
  "geometry": {"coordinates":[0.27413229562004,52.41095086596894],"type":"Point"}
}