{
  "type": "Feature",
  "properties": {
    "iso:country":"GB",
    "wof:name":"DY1 3EN",
    "wof:placetype":"postalcode"
},
  "geometry": {"coordinates":[-2.08893399946545,52.51641876502512],"type":"Point"}
}