{
  "type": "Feature",
  "properties": {
    "date:inception_lower": "1980-01-01",
    "date:inception_upper": "1980-01-01",
    "iso:country": "GB",
    "wof:name": "DY1 3EN",
    "wof:placetype": "postalcode"
  },
  "geometry": {"coordinates":[-2.088934,52.516419],"type":"Point"}
}
