{
  "type": "Feature",
  "properties": {
    "iso:country": "GB",
    "wof:name": "NE15 8AF",
    "wof:placetype": "postalcode"
  },
  "geometry": {"coordinates":[-1.711416,54.97788],"type":"Point"}
}
