{
  "type": "Feature",
  "properties": {
    "iso:country":"GB",
    "wof:name":"NE15 8AF",
    "wof:placetype":"postalcode"
},
  "geometry": {"coordinates":[-1.71141639529366,54.97787970927828],"type":"Point"}
}