{
  "type": "Feature",
  "properties": {
    "date:inception_lower": "2006-07-01",
    "date:inception_upper": "2006-07-01",
    "iso:country": "GB",
    "wof:name": "NE15 8AF",
    "wof:placetype": "postalcode"
  },
  "geometry": {"coordinates":[-1.711416,54.97788],"type":"Point"}
}
