{
  "type": "Feature",
  "properties": {
    "iso:country":"GB",
    "wof:name":"PR7 1RD",
    "wof:placetype":"postalcode"
},
  "geometry": {"coordinates":[-2.63286407421518,53.65871371486689],"type":"Point"}
}