{
  "type": "Feature",
  "properties": {
    "date:inception_lower": "1980-01-01",
    "date:inception_upper": "1980-01-01",
    "iso:country": "GB",
    "wof:name": "PR7 1RD",
    "wof:placetype": "postalcode"
  },
  "geometry": {"coordinates":[-2.632864,53.658714],"type":"Point"}
}
