{
  "type": "Feature",
  "properties": {
    "iso:country":"GB",
    "wof:name":"ST10 4HY",
    "wof:placetype":"postalcode"
},
  "geometry": {"coordinates":[-1.9561999459135,52.95203399197192],"type":"Point"}
}