{
  "type": "Feature",
  "properties": {
    "iso:country":"GB",
    "wof:name":"M3 5JH",
    "wof:placetype":"postalcode"
},
  "geometry": {"coordinates":[-2.26243433826308,53.48288547823793],"type":"Point"}
}