{
  "type": "Feature",
  "properties": {
    "date:inception_lower": "2015-05-01",
    "date:inception_upper": "2015-05-01",
    "iso:country": "GB",
    "wof:name": "M3 5JH",
    "wof:placetype": "postalcode"
  },
  "geometry": {"coordinates":[-2.262359,53.48294],"type":"Point"}
}
