{
  "type": "Feature",
  "properties": {
    "iso:country":"GB",
    "wof:name":"LU7 9GW",
    "wof:placetype":"postalcode"
},
  "geometry": {"coordinates":[-0.64449415937462,51.82504822691246],"type":"Point"}
}