{
  "type": "Feature",
  "properties": {
    "iso:country": "GB",
    "wof:name": "CV37 6EJ",
    "wof:placetype": "postalcode"
  },
  "geometry": {"coordinates":[-1.706622,52.191436],"type":"Point"}
}
