{
  "type": "Feature",
  "properties": {
    "iso:country": "GB",
    "wof:name": "HU4 6HJ",
    "wof:placetype": "postalcode"
  },
  "geometry": {"coordinates":[-0.393358,53.738946],"type":"Point"}
}
