{
  "type": "Feature",
  "properties": {
    "iso:country":"GB",
    "wof:name":"HU4 6HJ",
    "wof:placetype":"postalcode"
},
  "geometry": {"coordinates":[-0.39335764130696,53.73894552386231],"type":"Point"}
}