{
  "type": "Feature",
  "properties": {
    "iso:country":"GB",
    "wof:name":"BH25 6LL",
    "wof:placetype":"postalcode"
},
  "geometry": {"coordinates":[-1.65483401253001,50.75210934841595],"type":"Point"}
}