{
  "type": "Feature",
  "properties": {
    "iso:country":"GB",
    "wof:name":"DY1 4SB",
    "wof:placetype":"postalcode"
},
  "geometry": {"coordinates":[-2.07516783995949,52.52357530852592],"type":"Point"}
}