{
  "type": "Feature",
  "properties": {
    "iso:country":"GB",
    "wof:name":"CM4 0EG",
    "wof:placetype":"postalcode"
},
  "geometry": {"coordinates":[0.40835801827987,51.68699939814464],"type":"Point"}
}