{
  "type": "Feature",
  "properties": {
    "iso:country": "GB",
    "wof:name": "CM4 0EG",
    "wof:placetype": "postalcode"
  },
  "geometry": {"coordinates":[0.408358,51.686999],"type":"Point"}
}
