{
  "type": "Feature",
  "properties": {
    "date:inception_lower": "2000-12-01",
    "date:inception_upper": "2000-12-01",
    "iso:country": "GB",
    "wof:name": "N11 3NY",
    "wof:placetype": "postalcode"
  },
  "geometry": {"coordinates":[-0.148968,51.61497],"type":"Point"}
}
