{
  "type": "Feature",
  "properties": {
    "iso:country":"GB",
    "wof:name":"N11 3NY",
    "wof:placetype":"postalcode"
},
  "geometry": {"coordinates":[-0.14896836372034,51.61496988884905],"type":"Point"}
}