{
  "type": "Feature",
  "properties": {
    "iso:country":"GB",
    "wof:name":"HA1 1TX",
    "wof:placetype":"postalcode"
},
  "geometry": {"coordinates":[-0.33750949021328,51.5903832328464],"type":"Point"}
}