{
  "type": "Feature",
  "properties": {
    "iso:country":"GB",
    "wof:name":"LD2 3AL",
    "wof:placetype":"postalcode"
},
  "geometry": {"coordinates":[-3.40558442546951,52.14853889872595],"type":"Point"}
}