{
  "type": "Feature",
  "properties": {
    "date:inception_lower":"1980-01-01",
    "date:inception_upper":"1980-01-31",
    "iso:country":"GB",
    "wof:name":"LD2 3AL",
    "wof:placetype":"postalcode"
},
  "geometry": {"coordinates":[-3.405584,52.148539],"type":"Point"}
}