{
  "type": "Feature",
  "properties": {
    "date:inception_lower": "1980-01-01",
    "date:inception_upper": "1980-01-01",
    "iso:country": "GB",
    "wof:name": "EX22 7AN",
    "wof:placetype": "postalcode"
  },
  "geometry": {"coordinates":[-4.235314,50.837944],"type":"Point"}
}
