{
  "type": "Feature",
  "properties": {
    "iso:country":"GB",
    "wof:name":"EX22 7AN",
    "wof:placetype":"postalcode"
},
  "geometry": {"coordinates":[-4.23531357187882,50.83794392478906],"type":"Point"}
}