{
  "type": "Feature",
  "properties": {
    "iso:country":"GB",
    "wof:name":"WA15 8NH",
    "wof:placetype":"postalcode"
},
  "geometry": {"coordinates":[-2.31727693974802,53.37465601284352],"type":"Point"}
}