{
  "type": "Feature",
  "properties": {
    "iso:country":"GB",
    "wof:name":"G42 7LW",
    "wof:placetype":"postalcode"
},
  "geometry": {"coordinates":[-4.25609917880102,55.83863531357563],"type":"Point"}
}