{
  "type": "Feature",
  "properties": {
    "iso:country": "GB",
    "wof:name": "PL17 7LX",
    "wof:placetype": "postalcode"
  },
  "geometry": {"coordinates":[-4.367036,50.534479],"type":"Point"}
}
