{
  "type": "Feature",
  "properties": {
    "iso:country":"GB",
    "wof:name":"PL17 7LX",
    "wof:placetype":"postalcode"
},
  "geometry": {"coordinates":[-4.36703614118473,50.53447867296352],"type":"Point"}
}