{
  "type": "Feature",
  "properties": {
    "iso:country":"GB",
    "wof:name":"KY14 6DQ",
    "wof:placetype":"postalcode"
},
  "geometry": {"coordinates":[-3.24044141020012,56.34867458267421],"type":"Point"}
}