{
  "type": "Feature",
  "properties": {
    "iso:country": "GB",
    "wof:name": "KY14 6DQ",
    "wof:placetype": "postalcode"
  },
  "geometry": {"coordinates":[-3.240441,56.348675],"type":"Point"}
}
