{
  "type": "Feature",
  "properties": {
    "date:inception_lower": "1980-01-01",
    "date:inception_upper": "1980-01-01",
    "iso:country": "GB",
    "wof:name": "KY14 6DQ",
    "wof:placetype": "postalcode"
  },
  "geometry": {"coordinates":[-3.240441,56.348675],"type":"Point"}
}
