{
  "type": "Feature",
  "properties": {
    "iso:country":"GB",
    "wof:name":"RH19 4NJ",
    "wof:placetype":"postalcode"
},
  "geometry": {"coordinates":[-0.00540656634231,51.11406247763602],"type":"Point"}
}