{
  "type": "Feature",
  "properties": {
    "iso:country":"GB",
    "wof:name":"SA44 6QB",
    "wof:placetype":"postalcode"
},
  "geometry": {"coordinates":[-4.48281792039438,52.13648248316771],"type":"Point"}
}