{
  "type": "Feature",
  "properties": {
    "iso:country": "GB",
    "wof:name": "SA44 6QB",
    "wof:placetype": "postalcode"
  },
  "geometry": {"coordinates":[-4.482838,52.136496],"type":"Point"}
}
