{
  "type": "Feature",
  "properties": {
    "date:inception_lower": "1980-01-01",
    "date:inception_upper": "1980-01-01",
    "iso:country": "GB",
    "wof:name": "ST7 1HF",
    "wof:placetype": "postalcode"
  },
  "geometry": {"coordinates":[-2.240869,53.090967],"type":"Point"}
}
