{
  "type": "Feature",
  "properties": {
    "iso:country":"GB",
    "wof:name":"SK5 7AL",
    "wof:placetype":"postalcode"
},
  "geometry": {"coordinates":[-2.16124647136014,53.43552499138575],"type":"Point"}
}