{
  "type": "Feature",
  "properties": {
    "iso:country": "GB",
    "wof:name": "SK5 7AL",
    "wof:placetype": "postalcode"
  },
  "geometry": {"coordinates":[-2.161246,53.435525],"type":"Point"}
}
