{
  "type": "Feature",
  "properties": {
    "iso:country":"GB",
    "wof:name":"LU5 6JA",
    "wof:placetype":"postalcode"
},
  "geometry": {"coordinates":[-0.54005961473556,51.94529229262353],"type":"Point"}
}