{
  "type": "Feature",
  "properties": {
    "date:inception_lower": "1991-09-01",
    "date:inception_upper": "1991-09-01",
    "iso:country": "GB",
    "wof:name": "LU5 6JA",
    "wof:placetype": "postalcode"
  },
  "geometry": {"coordinates":[-0.54006,51.945292],"type":"Point"}
}
