{
  "type": "Feature",
  "properties": {
    "iso:country":"GB",
    "wof:name":"BN2 1LA",
    "wof:placetype":"postalcode"
},
  "geometry": {"coordinates":[-0.12392517205404,50.81985769315567],"type":"Point"}
}