{
  "type": "Feature",
  "properties": {
    "iso:country": "GB",
    "wof:name": "BN2 1LA",
    "wof:placetype": "postalcode"
  },
  "geometry": {"coordinates":[-0.123827,50.819842],"type":"Point"}
}
