{
  "type": "Feature",
  "properties": {
    "iso:country":"GB",
    "wof:name":"S45 9SL",
    "wof:placetype":"postalcode"
},
  "geometry": {"coordinates":[-1.40369560317156,53.16150635516919],"type":"Point"}
}