{
  "type": "Feature",
  "properties": {
    "iso:country": "GB",
    "wof:name": "S45 9SL",
    "wof:placetype": "postalcode"
  },
  "geometry": {"coordinates":[-1.403696,53.161506],"type":"Point"}
}
