{
  "type": "Feature",
  "properties": {
    "iso:country":"GB",
    "wof:name":"SW3 2QD",
    "wof:placetype":"postalcode"
},
  "geometry": {"coordinates":[-0.16379148016529,51.49453337493387],"type":"Point"}
}