{
  "type": "Feature",
  "properties": {
    "iso:country": "GB",
    "wof:name": "PH15 2DZ",
    "wof:placetype": "postalcode"
  },
  "geometry": {"coordinates":[-3.856423,56.618153],"type":"Point"}
}
