{
  "type": "Feature",
  "properties": {
    "iso:country":"GB",
    "wof:name":"KA26 0JL",
    "wof:placetype":"postalcode"
},
  "geometry": {"coordinates":[-4.93199812062916,55.16548736713276],"type":"Point"}
}