{
  "type": "Feature",
  "properties": {
    "iso:country": "GB",
    "wof:name": "KA26 0JL",
    "wof:placetype": "postalcode"
  },
  "geometry": {"coordinates":[-4.932656,55.164393],"type":"Point"}
}
