{
  "type": "Feature",
  "properties": {
    "iso:country": "GB",
    "wof:name": "WS11 0EJ",
    "wof:placetype": "postalcode"
  },
  "geometry": {"coordinates":[-2.020824,52.6856],"type":"Point"}
}
