{
  "type": "Feature",
  "properties": {
    "iso:country": "GB",
    "wof:name": "SP10 3RH",
    "wof:placetype": "postalcode"
  },
  "geometry": {"coordinates":[-1.4999,51.21634],"type":"Point"}
}
