{
  "type": "Feature",
  "properties": {
    "iso:country":"GB",
    "wof:name":"SP10 3RH",
    "wof:placetype":"postalcode"
},
  "geometry": {"coordinates":[-1.49991167378069,51.21634397286977],"type":"Point"}
}