{
  "type": "Feature",
  "properties": {
    "date:inception_lower": "1993-01-01",
    "date:inception_upper": "1993-01-01",
    "iso:country": "GB",
    "wof:name": "SP10 3RH",
    "wof:placetype": "postalcode"
  },
  "geometry": {"coordinates":[-1.4999,51.21634],"type":"Point"}
}
