{
  "type": "Feature",
  "properties": {
    "iso:country": "GB",
    "wof:name": "CB6 3XS",
    "wof:placetype": "postalcode"
  },
  "geometry": {"coordinates":[0.176603,52.352138],"type":"Point"}
}
