{
  "type": "Feature",
  "properties": {
    "iso:country":"GB",
    "wof:name":"CB6 3XS",
    "wof:placetype":"postalcode"
},
  "geometry": {"coordinates":[0.176602826557,52.35213774379253],"type":"Point"}
}