{
  "type": "Feature",
  "properties": {
    "date:inception_lower": "2006-08-01",
    "date:inception_upper": "2006-08-01",
    "iso:country": "GB",
    "wof:name": "DL5 4ZF",
    "wof:placetype": "postalcode"
  },
  "geometry": {"coordinates":[-1.582013,54.636277],"type":"Point"}
}
