{
  "type": "Feature",
  "properties": {
    "iso:country":"GB",
    "wof:name":"DL5 4ZF",
    "wof:placetype":"postalcode"
},
  "geometry": {"coordinates":[-1.58201263481792,54.6362769337772],"type":"Point"}
}