{
  "type": "Feature",
  "properties": {
    "iso:country":"GB",
    "wof:name":"BD5 8BS",
    "wof:placetype":"postalcode"
},
  "geometry": {"coordinates":[-1.75301092020723,53.77557643219762],"type":"Point"}
}