{
  "type": "Feature",
  "properties": {
    "iso:country":"GB",
    "wof:name":"ST3 3NW",
    "wof:placetype":"postalcode"
},
  "geometry": {"coordinates":[-2.15988655823052,52.96826751460357],"type":"Point"}
}