{
  "type": "Feature",
  "properties": {
    "iso:country": "GB",
    "wof:name": "E16 1FJ",
    "wof:placetype": "postalcode"
  },
  "geometry": {"coordinates":[0.01302,51.512261],"type":"Point"}
}
