{
  "type": "Feature",
  "properties": {
    "iso:country":"GB",
    "wof:name":"E16 1FJ",
    "wof:placetype":"postalcode"
},
  "geometry": {"coordinates":[0.01301962801242,51.51226073768741],"type":"Point"}
}