{
  "type": "Feature",
  "properties": {
    "iso:country": "GB",
    "wof:name": "SY23 5PD",
    "wof:placetype": "postalcode"
  },
  "geometry": {"coordinates":[-4.151891,52.251791],"type":"Point"}
}
