{
  "type": "Feature",
  "properties": {
    "iso:country":"GB",
    "wof:name":"SY23 5PD",
    "wof:placetype":"postalcode"
},
  "geometry": {"coordinates":[-4.15189113589219,52.25179146886662],"type":"Point"}
}