{
  "type": "Feature",
  "properties": {
    "date:inception_lower": "2019-01-01",
    "date:inception_upper": "2019-01-01",
    "iso:country": "GB",
    "wof:name": "CV23 9FU",
    "wof:placetype": "postalcode"
  },
  "geometry": {"coordinates":[-1.31556,52.353882],"type":"Point"}
}
