{
  "type": "Feature",
  "properties": {
    "iso:country": "GB",
    "wof:name": "CV23 9FU",
    "wof:placetype": "postalcode"
  },
  "geometry": {"coordinates":[-1.31518,52.353772],"type":"Point"}
}
