{
  "type": "Feature",
  "properties": {
    "iso:country":"GB",
    "wof:name":"IG4 5LU",
    "wof:placetype":"postalcode"
},
  "geometry": {"coordinates":[0.05264911723587,51.58395600466288],"type":"Point"}
}