{
  "type": "Feature",
  "properties": {
    "iso:country":"GB",
    "wof:name":"TR7 2DH",
    "wof:placetype":"postalcode"
},
  "geometry": {"coordinates":[-5.08190761141847,50.41079881048543],"type":"Point"}
}