{
  "type": "Feature",
  "properties": {
    "iso:country":"GB",
    "wof:name":"TS3 6NJ",
    "wof:placetype":"postalcode"
},
  "geometry": {"coordinates":[-1.21134110137052,54.56944608099461],"type":"Point"}
}