{
  "type": "Feature",
  "properties": {
    "date:inception_lower":"1980-01-01",
    "date:inception_upper":"1980-01-31",
    "iso:country":"GB",
    "wof:name":"TS3 6NJ",
    "wof:placetype":"postalcode"
},
  "geometry": {"coordinates":[-1.211341,54.569446],"type":"Point"}
}