{
  "type": "Feature",
  "properties": {
    "date:inception_lower":"1980-01-01",
    "date:inception_upper":"1980-01-31",
    "iso:country":"GB",
    "wof:name":"S2 1WX",
    "wof:placetype":"postalcode"
},
  "geometry": {"coordinates":[-1.43067,53.372041],"type":"Point"}
}