{
  "type": "Feature",
  "properties": {
    "iso:country":"GB",
    "wof:name":"S2 1WX",
    "wof:placetype":"postalcode"
},
  "geometry": {"coordinates":[-1.4306705236206,53.3720411050088],"type":"Point"}
}