{
  "type": "Feature",
  "properties": {
    "iso:country":"GB",
    "wof:name":"DL1 5TE",
    "wof:placetype":"postalcode"
},
  "geometry": {"coordinates":[-1.55908326952442,54.51299460663999],"type":"Point"}
}