{
  "type": "Feature",
  "properties": {
    "iso:country":"GB",
    "wof:name":"HA7 1LU",
    "wof:placetype":"postalcode"
},
  "geometry": {"coordinates":[-0.30060339311165,51.59792969383757],"type":"Point"}
}