{
  "type": "Feature",
  "properties": {
    "iso:country":"GB",
    "wof:name":"CO10 2EA",
    "wof:placetype":"postalcode"
},
  "geometry": {"coordinates":[0.73023934250721,52.03868153181448],"type":"Point"}
}