{
  "type": "Feature",
  "properties": {
    "iso:country": "GB",
    "wof:name": "CO10 2EA",
    "wof:placetype": "postalcode"
  },
  "geometry": {"coordinates":[0.730239,52.038682],"type":"Point"}
}
