{
  "type": "Feature",
  "properties": {
    "iso:country":"GB",
    "wof:name":"WD7 8PZ",
    "wof:placetype":"postalcode"
},
  "geometry": {"coordinates":[-0.32353497845118,51.67543892914991],"type":"Point"}
}