{
  "type": "Feature",
  "properties": {
    "iso:country": "GB",
    "wof:name": "SE9 1AB",
    "wof:placetype": "postalcode"
  },
  "geometry": {"coordinates":[0.06165,51.4504],"type":"Point"}
}
