{
  "type": "Feature",
  "properties": {
    "iso:country":"GB",
    "wof:name":"TD7 4DQ",
    "wof:placetype":"postalcode"
},
  "geometry": {"coordinates":[-2.84355232863008,55.54687391415744],"type":"Point"}
}