{
  "type": "Feature",
  "properties": {
    "iso:country":"GB",
    "wof:name":"PO36 0EX",
    "wof:placetype":"postalcode"
},
  "geometry": {"coordinates":[-1.18199108802635,50.66850181294626],"type":"Point"}
}