{
  "type": "Feature",
  "properties": {
    "date:inception_lower": "1980-01-01",
    "date:inception_upper": "1980-01-01",
    "iso:country": "GB",
    "wof:name": "PO36 0EX",
    "wof:placetype": "postalcode"
  },
  "geometry": {"coordinates":[-1.181991,50.668502],"type":"Point"}
}
