{
  "type": "Feature",
  "properties": {
    "date:inception_lower": "1994-05-01",
    "date:inception_upper": "1994-05-01",
    "iso:country": "GB",
    "wof:name": "BN11 1DZ",
    "wof:placetype": "postalcode"
  },
  "geometry": {"coordinates":[-0.367328,50.8161],"type":"Point"}
}
