{
  "type": "Feature",
  "properties": {
    "date:inception_lower": "1980-01-01",
    "date:inception_upper": "1980-01-01",
    "iso:country": "GB",
    "wof:name": "IP14 5TG",
    "wof:placetype": "postalcode"
  },
  "geometry": {"coordinates":[1.050604,52.247761],"type":"Point"}
}
