{
  "type": "Feature",
  "properties": {
    "date:inception_lower":"1980-01-01",
    "date:inception_upper":"1980-01-31",
    "iso:country":"GB",
    "wof:name":"CF31 3ED",
    "wof:placetype":"postalcode"
},
  "geometry": {"coordinates":[-3.577619,51.501806],"type":"Point"}
}