{
  "type": "Feature",
  "properties": {
    "iso:country":"GB",
    "wof:name":"CF31 3ED",
    "wof:placetype":"postalcode"
},
  "geometry": {"coordinates":[-3.57761883675192,51.50180575673583],"type":"Point"}
}