{
  "type": "Feature",
  "properties": {
    "iso:country":"GB",
    "wof:name":"CO6 1EH",
    "wof:placetype":"postalcode"
},
  "geometry": {"coordinates":[0.78136128058563,51.87521899957441],"type":"Point"}
}