{
  "type": "Feature",
  "properties": {
    "iso:country":"GB",
    "wof:name":"SO16 7QH",
    "wof:placetype":"postalcode"
},
  "geometry": {"coordinates":[-1.40385947496539,50.95931080177802],"type":"Point"}
}