{
  "type": "Feature",
  "properties": {
    "date:inception_lower": "2001-06-01",
    "date:inception_upper": "2001-06-01",
    "iso:country": "GB",
    "wof:name": "SO16 7QH",
    "wof:placetype": "postalcode"
  },
  "geometry": {"coordinates":[-1.403859,50.959311],"type":"Point"}
}
