{
  "type": "Feature",
  "properties": {
    "iso:country":"GB",
    "wof:name":"PL17 7LR",
    "wof:placetype":"postalcode"
},
  "geometry": {"coordinates":[-4.35238139702205,50.53690751466326],"type":"Point"}
}