{
  "type": "Feature",
  "properties": {
    "iso:country": "GB",
    "wof:name": "CH49 7LP",
    "wof:placetype": "postalcode"
  },
  "geometry": {"coordinates":[-3.086369,53.370187],"type":"Point"}
}
