{
  "type": "Feature",
  "properties": {
    "iso:country":"GB",
    "wof:name":"CH49 7LP",
    "wof:placetype":"postalcode"
},
  "geometry": {"coordinates":[-3.08636870851217,53.3701865380182],"type":"Point"}
}