{
  "type": "Feature",
  "properties": {
    "iso:country":"GB",
    "wof:name":"PH2 7UA",
    "wof:placetype":"postalcode"
},
  "geometry": {"coordinates":[-3.30196561271094,56.37301283073515],"type":"Point"}
}