{
  "type": "Feature",
  "properties": {
    "date:inception_lower":"1980-01-01",
    "date:inception_upper":"1980-01-31",
    "iso:country":"GB",
    "wof:name":"PH2 7UA",
    "wof:placetype":"postalcode"
},
  "geometry": {"coordinates":[-3.301966,56.373013],"type":"Point"}
}