{
  "type": "Feature",
  "properties": {
    "iso:country": "GB",
    "wof:name": "SE18 6BD",
    "wof:placetype": "postalcode"
  },
  "geometry": {"coordinates":[0.06645,51.484696],"type":"Point"}
}
