{
  "type": "Feature",
  "properties": {
    "iso:country": "GB",
    "wof:name": "BN44 3SN",
    "wof:placetype": "postalcode"
  },
  "geometry": {"coordinates":[-0.32429,50.894856],"type":"Point"}
}
