{
  "type": "Feature",
  "properties": {
    "iso:country": "GB",
    "wof:name": "BN44 3SN",
    "wof:placetype": "postalcode"
  },
  "geometry": {"coordinates":[-0.324331,50.894863],"type":"Point"}
}
