{
  "type": "Feature",
  "properties": {
    "iso:country":"GB",
    "wof:name":"BN44 3SN",
    "wof:placetype":"postalcode"
},
  "geometry": {"coordinates":[-0.32433059909424,50.8948630937192],"type":"Point"}
}