{
  "type": "Feature",
  "properties": {
    "iso:country":"GB",
    "wof:name":"LE17 5LD",
    "wof:placetype":"postalcode"
},
  "geometry": {"coordinates":[-1.1880528028813,52.51411853481018],"type":"Point"}
}