{
  "type": "Feature",
  "properties": {
    "date:inception_lower": "1980-01-01",
    "date:inception_upper": "1980-01-01",
    "iso:country": "GB",
    "wof:name": "GU22 0SP",
    "wof:placetype": "postalcode"
  },
  "geometry": {"coordinates":[-0.579421,51.288159],"type":"Point"}
}
