{
  "type": "Feature",
  "properties": {
    "iso:country": "GB",
    "wof:name": "GU22 0SP",
    "wof:placetype": "postalcode"
  },
  "geometry": {"coordinates":[-0.579421,51.288159],"type":"Point"}
}
