{
  "type": "Feature",
  "properties": {
    "iso:country":"GB",
    "wof:name":"GL6 0EB",
    "wof:placetype":"postalcode"
},
  "geometry": {"coordinates":[-2.22593110747896,51.69854604067518],"type":"Point"}
}