{
  "type": "Feature",
  "properties": {
    "iso:country": "GB",
    "wof:name": "GL6 0EB",
    "wof:placetype": "postalcode"
  },
  "geometry": {"coordinates":[-2.225931,51.698546],"type":"Point"}
}
