{
  "type": "Feature",
  "properties": {
    "iso:country": "GB",
    "wof:name": "BH6 5DQ",
    "wof:placetype": "postalcode"
  },
  "geometry": {"coordinates":[-1.811781,50.72799],"type":"Point"}
}
