{
  "type": "Feature",
  "properties": {
    "iso:country":"GB",
    "wof:name":"BH6 5DQ",
    "wof:placetype":"postalcode"
},
  "geometry": {"coordinates":[-1.81178138932577,50.7279898933345],"type":"Point"}
}