{
  "type": "Feature",
  "properties": {
    "iso:country":"GB",
    "wof:name":"EH31 2BD",
    "wof:placetype":"postalcode"
},
  "geometry": {"coordinates":[-2.84151947715673,56.03400121997937],"type":"Point"}
}