{
  "type": "Feature",
  "properties": {
    "date:inception_lower": "1995-01-01",
    "date:inception_upper": "1995-01-01",
    "iso:country": "GB",
    "wof:name": "WV6 0JB",
    "wof:placetype": "postalcode"
  },
  "geometry": {"coordinates":[-2.156902,52.596196],"type":"Point"}
}
