{
  "type": "Feature",
  "properties": {
    "iso:country":"GB",
    "wof:name":"BS16 1NP",
    "wof:placetype":"postalcode"
},
  "geometry": {"coordinates":[-2.51958767862529,51.50294105226325],"type":"Point"}
}