{
  "type": "Feature",
  "properties": {
    "date:inception_lower": "1980-01-01",
    "date:inception_upper": "1980-01-01",
    "iso:country": "GB",
    "wof:name": "HP4 2PJ",
    "wof:placetype": "postalcode"
  },
  "geometry": {"coordinates":[-0.548293,51.765507],"type":"Point"}
}
