{
  "type": "Feature",
  "properties": {
    "iso:country":"GB",
    "wof:name":"HP4 2PJ",
    "wof:placetype":"postalcode"
},
  "geometry": {"coordinates":[-0.54925551642682,51.7655650431447],"type":"Point"}
}