{
  "type": "Feature",
  "properties": {
    "iso:country":"GB",
    "wof:name":"RM16 4DA",
    "wof:placetype":"postalcode"
},
  "geometry": {"coordinates":[0.36523926763251,51.4790566101387],"type":"Point"}
}