{
  "type": "Feature",
  "properties": {
    "iso:country":"GB",
    "wof:name":"LU5 6ND",
    "wof:placetype":"postalcode"
},
  "geometry": {"coordinates":[-0.48887147502162,51.96572253494585],"type":"Point"}
}