{
  "type": "Feature",
  "properties": {
    "iso:country": "GB",
    "wof:name": "LU5 6ND",
    "wof:placetype": "postalcode"
  },
  "geometry": {"coordinates":[-0.488871,51.965723],"type":"Point"}
}
