{
  "type": "Feature",
  "properties": {
    "iso:country":"GB",
    "wof:name":"PA1 1XW",
    "wof:placetype":"postalcode"
},
  "geometry": {"coordinates":[-4.42356011666659,55.84472431040239],"type":"Point"}
}