{
  "type": "Feature",
  "properties": {
    "iso:country":"GB",
    "wof:name":"TQ1 1NZ",
    "wof:placetype":"postalcode"
},
  "geometry": {"coordinates":[-3.52357481575396,50.46978298937208],"type":"Point"}
}