{
  "type": "Feature",
  "properties": {
    "iso:country": "GB",
    "wof:name": "CO4 9BL",
    "wof:placetype": "postalcode"
  },
  "geometry": {"coordinates":[0.936122,51.918676],"type":"Point"}
}
