{
  "type": "Feature",
  "properties": {
    "date:inception_lower": "2020-02-01",
    "date:inception_upper": "2020-02-01",
    "iso:country": "GB",
    "wof:name": "CO4 9BL",
    "wof:placetype": "postalcode"
  },
  "geometry": {"coordinates":[0.935787,51.918451],"type":"Point"}
}
