{
  "type": "Feature",
  "properties": {
    "iso:country":"GB",
    "wof:name":"RM2 5NA",
    "wof:placetype":"postalcode"
},
  "geometry": {"coordinates":[0.19917632702718,51.58541103284453],"type":"Point"}
}