{
  "type": "Feature",
  "properties": {
    "iso:country":"GB",
    "wof:name":"DT4 9XY",
    "wof:placetype":"postalcode"
},
  "geometry": {"coordinates":[-2.46879533906299,50.59834882616992],"type":"Point"}
}