{
  "type": "Feature",
  "properties": {
    "iso:country": "GB",
    "wof:name": "DT4 9XY",
    "wof:placetype": "postalcode"
  },
  "geometry": {"coordinates":[-2.468792,50.59832],"type":"Point"}
}
