{
  "type": "Feature",
  "properties": {
    "iso:country":"GB",
    "wof:name":"TQ4 7SR",
    "wof:placetype":"postalcode"
},
  "geometry": {"coordinates":[-3.57335376192224,50.40968981777188],"type":"Point"}
}