{
  "type": "Feature",
  "properties": {
    "date:inception_lower":"2015-05-01",
    "date:inception_upper":"2015-05-31",
    "iso:country":"GB",
    "wof:name":"TQ4 7SR",
    "wof:placetype":"postalcode"
},
  "geometry": {"coordinates":[-3.573354,50.40969],"type":"Point"}
}