{
  "type": "Feature",
  "properties": {
    "iso:country": "GB",
    "wof:name": "TQ4 7SR",
    "wof:placetype": "postalcode"
  },
  "geometry": {"coordinates":[-3.573354,50.40969],"type":"Point"}
}
