{
  "type": "Feature",
  "properties": {
    "date:inception_lower": "2015-05-01",
    "date:inception_upper": "2015-05-01",
    "iso:country": "GB",
    "wof:name": "TQ4 7SR",
    "wof:placetype": "postalcode"
  },
  "geometry": {"coordinates":[-3.588917,50.412017],"type":"Point"}
}
