{
  "type": "Feature",
  "properties": {
    "iso:country":"GB",
    "wof:name":"IP33 2NL",
    "wof:placetype":"postalcode"
},
  "geometry": {"coordinates":[0.72945540726045,52.2291983816642],"type":"Point"}
}