{
  "type": "Feature",
  "properties": {
    "iso:country":"GB",
    "wof:name":"B31 1SH",
    "wof:placetype":"postalcode"
},
  "geometry": {"coordinates":[-1.98007744213758,52.41667996216064],"type":"Point"}
}