{
  "type": "Feature",
  "properties": {
    "iso:country":"GB",
    "wof:name":"BL1 5EU",
    "wof:placetype":"postalcode"
},
  "geometry": {"coordinates":[-2.48477075489621,53.58641104045169],"type":"Point"}
}