{
  "type": "Feature",
  "properties": {
    "iso:country":"GB",
    "wof:name":"HR1 2TS",
    "wof:placetype":"postalcode"
},
  "geometry": {"coordinates":[-2.69977997179729,52.05747074825066],"type":"Point"}
}