{
  "type": "Feature",
  "properties": {
    "date:inception_lower": "1980-01-01",
    "date:inception_upper": "1980-01-01",
    "iso:country": "GB",
    "wof:name": "HR1 2TS",
    "wof:placetype": "postalcode"
  },
  "geometry": {"coordinates":[-2.69978,52.057471],"type":"Point"}
}
