{
  "type": "Feature",
  "properties": {
    "date:inception_lower": "1980-01-01",
    "date:inception_upper": "1980-01-01",
    "iso:country": "GB",
    "wof:name": "HP23 4PP",
    "wof:placetype": "postalcode"
  },
  "geometry": {"coordinates":[-0.714832,51.824363],"type":"Point"}
}
