{
  "type": "Feature",
  "properties": {
    "iso:country":"GB",
    "wof:name":"HP23 4PP",
    "wof:placetype":"postalcode"
},
  "geometry": {"coordinates":[-0.71483158032526,51.8243631681325],"type":"Point"}
}