{
  "type": "Feature",
  "properties": {
    "iso:country":"GB",
    "wof:name":"SG14 3TS",
    "wof:placetype":"postalcode"
},
  "geometry": {"coordinates":[-0.11433256801893,51.85951080949171],"type":"Point"}
}