{
  "type": "Feature",
  "properties": {
    "iso:country": "GB",
    "wof:name": "SG14 3TS",
    "wof:placetype": "postalcode"
  },
  "geometry": {"coordinates":[-0.114333,51.859511],"type":"Point"}
}
