{
  "type": "Feature",
  "properties": {
    "iso:country":"GB",
    "wof:name":"NG9 5GX",
    "wof:placetype":"postalcode"
},
  "geometry": {"coordinates":[-1.2506769726152,52.91444286804093],"type":"Point"}
}