{
  "type": "Feature",
  "properties": {
    "date:inception_lower": "1999-06-01",
    "date:inception_upper": "1999-06-01",
    "iso:country": "GB",
    "wof:name": "CH62 4SE",
    "wof:placetype": "postalcode"
  },
  "geometry": {"coordinates":[-2.991065,53.356013],"type":"Point"}
}
