{
  "type": "Feature",
  "properties": {
    "iso:country":"GB",
    "wof:name":"CH62 4SE",
    "wof:placetype":"postalcode"
},
  "geometry": {"coordinates":[-2.99106535248095,53.35601344604905],"type":"Point"}
}