{
  "type": "Feature",
  "properties": {
    "iso:country": "GB",
    "wof:name": "CR0 7AF",
    "wof:placetype": "postalcode"
  },
  "geometry": {"coordinates":[-0.06613,51.38292],"type":"Point"}
}
