{
  "type": "Feature",
  "properties": {
    "iso:country":"GB",
    "wof:name":"CR0 7AF",
    "wof:placetype":"postalcode"
},
  "geometry": {"coordinates":[-0.06628757833705,51.38285953155498],"type":"Point"}
}