{
  "type": "Feature",
  "properties": {
    "iso:country": "GB",
    "wof:name": "DG2 9EH",
    "wof:placetype": "postalcode"
  },
  "geometry": {"coordinates":[-3.630466,55.067695],"type":"Point"}
}
