{
  "type": "Feature",
  "properties": {
    "iso:country":"GB",
    "wof:name":"IG11 9TH",
    "wof:placetype":"postalcode"
},
  "geometry": {"coordinates":[0.08637286480572,51.54023217558321],"type":"Point"}
}