{
  "type": "Feature",
  "properties": {
    "iso:country":"GB",
    "wof:name":"AB39 2BE",
    "wof:placetype":"postalcode"
},
  "geometry": {"coordinates":[-2.2096246200853,56.9640734158384],"type":"Point"}
}