{
  "type": "Feature",
  "properties": {
    "date:inception_lower": "1980-01-01",
    "date:inception_upper": "1980-01-01",
    "iso:country": "GB",
    "wof:name": "SY1 3ED",
    "wof:placetype": "postalcode"
  },
  "geometry": {"coordinates":[-2.746477,52.730374],"type":"Point"}
}
