{
  "type": "Feature",
  "properties": {
    "iso:country": "GB",
    "wof:name": "SY1 3ED",
    "wof:placetype": "postalcode"
  },
  "geometry": {"coordinates":[-2.746252,52.730063],"type":"Point"}
}
