{
  "type": "Feature",
  "properties": {
    "iso:country": "GB",
    "wof:name": "DH5 9AA",
    "wof:placetype": "postalcode"
  },
  "geometry": {"coordinates":[-1.452267,54.825963],"type":"Point"}
}
