{
  "type": "Feature",
  "properties": {
    "iso:country":"GB",
    "wof:name":"DH5 9AA",
    "wof:placetype":"postalcode"
},
  "geometry": {"coordinates":[-1.45226741100683,54.82596328634561],"type":"Point"}
}