{
  "type": "Feature",
  "properties": {
    "date:inception_lower":"1980-01-01",
    "date:inception_upper":"1980-01-31",
    "iso:country":"GB",
    "wof:name":"DH5 9AA",
    "wof:placetype":"postalcode"
},
  "geometry": {"coordinates":[-1.452267,54.825963],"type":"Point"}
}