{
  "type": "Feature",
  "properties": {
    "iso:country":"GB",
    "wof:name":"NE34 6HX",
    "wof:placetype":"postalcode"
},
  "geometry": {"coordinates":[-1.40810894473525,54.98550836187184],"type":"Point"}
}