{
  "type": "Feature",
  "properties": {
    "iso:country":"GB",
    "wof:name":"BD18 4RN",
    "wof:placetype":"postalcode"
},
  "geometry": {"coordinates":[-1.79000302108687,53.83367313426471],"type":"Point"}
}