{
  "type": "Feature",
  "properties": {
    "iso:country": "GB",
    "wof:name": "CH62 3LA",
    "wof:placetype": "postalcode"
  },
  "geometry": {"coordinates":[-2.984688,53.345315],"type":"Point"}
}
