{
  "type": "Feature",
  "properties": {
    "date:inception_lower":"1999-06-01",
    "date:inception_upper":"1999-06-30",
    "iso:country":"GB",
    "wof:name":"CH62 3LA",
    "wof:placetype":"postalcode"
},
  "geometry": {"coordinates":[-2.984688,53.345315],"type":"Point"}
}