{
  "type": "Feature",
  "properties": {
    "iso:country":"GB",
    "wof:name":"WV14 7LZ",
    "wof:placetype":"postalcode"
},
  "geometry": {"coordinates":[-2.07120054795506,52.56737636584747],"type":"Point"}
}