{
  "type": "Feature",
  "properties": {
    "date:inception_lower":"1980-01-01",
    "date:inception_upper":"1980-01-31",
    "iso:country":"GB",
    "wof:name":"WV14 7LZ",
    "wof:placetype":"postalcode"
},
  "geometry": {"coordinates":[-2.071201,52.567376],"type":"Point"}
}