{
  "type": "Feature",
  "properties": {
    "date:inception_lower": "2021-07-01",
    "date:inception_upper": "2021-07-01",
    "iso:country": "GB",
    "wof:name": "CB8 9FX",
    "wof:placetype": "postalcode"
  },
  "geometry": {"coordinates":[0.466157,52.216002],"type":"Point"}
}
