{
  "type": "Feature",
  "properties": {
    "iso:country":"GB",
    "wof:name":"E10 7NN",
    "wof:placetype":"postalcode"
},
  "geometry": {"coordinates":[-0.03362052492987,51.570065045817],"type":"Point"}
}