{
  "type": "Feature",
  "properties": {
    "iso:country": "GB",
    "wof:name": "M6 5RQ",
    "wof:placetype": "postalcode"
  },
  "geometry": {"coordinates":[-2.289512,53.487137],"type":"Point"}
}
