{
  "type": "Feature",
  "properties": {
    "iso:country":"GB",
    "wof:name":"M6 5RQ",
    "wof:placetype":"postalcode"
},
  "geometry": {"coordinates":[-2.28951234872757,53.48713735665667],"type":"Point"}
}