{
  "type": "Feature",
  "properties": {
    "iso:country": "GB",
    "wof:name": "WF1 4FZ",
    "wof:placetype": "postalcode"
  },
  "geometry": {"coordinates":[-1.475419,53.695586],"type":"Point"}
}
