{
  "type": "Feature",
  "properties": {
    "iso:country":"GB",
    "wof:name":"PH7 4EA",
    "wof:placetype":"postalcode"
},
  "geometry": {"coordinates":[-3.84681240627637,56.37633569263441],"type":"Point"}
}