{
  "type": "Feature",
  "properties": {
    "date:inception_lower": "1980-01-01",
    "date:inception_upper": "1980-01-01",
    "iso:country": "GB",
    "wof:name": "NR21 8JT",
    "wof:placetype": "postalcode"
  },
  "geometry": {"coordinates":[0.853546,52.839343],"type":"Point"}
}
