{
  "type": "Feature",
  "properties": {
    "iso:country":"GB",
    "wof:name":"SE5 8QF",
    "wof:placetype":"postalcode"
},
  "geometry": {"coordinates":[-0.07893473186307,51.47304849418883],"type":"Point"}
}