{
  "type": "Feature",
  "properties": {
    "date:inception_lower": "1980-01-01",
    "date:inception_upper": "1980-01-01",
    "iso:country": "GB",
    "wof:name": "SE5 8QF",
    "wof:placetype": "postalcode"
  },
  "geometry": {"coordinates":[-0.078895,51.472958],"type":"Point"}
}
