{
  "type": "Feature",
  "properties": {
    "iso:country": "GB",
    "wof:name": "SW20 8EZ",
    "wof:placetype": "postalcode"
  },
  "geometry": {"coordinates":[-0.22444,51.415911],"type":"Point"}
}
