{
  "type": "Feature",
  "properties": {
    "date:inception_lower": "1999-06-01",
    "date:inception_upper": "1999-06-01",
    "iso:country": "GB",
    "wof:name": "NP26 5BJ",
    "wof:placetype": "postalcode"
  },
  "geometry": {"coordinates":[-2.760518,51.609129],"type":"Point"}
}
