{
  "type": "Feature",
  "properties": {
    "iso:country":"GB",
    "wof:name":"NP26 5BJ",
    "wof:placetype":"postalcode"
},
  "geometry": {"coordinates":[-2.7605181775668,51.60912889067356],"type":"Point"}
}