{
  "type": "Feature",
  "properties": {
    "iso:country":"GB",
    "wof:name":"KA6 7NP",
    "wof:placetype":"postalcode"
},
  "geometry": {"coordinates":[-4.50328476962346,55.36004755559215],"type":"Point"}
}