{
  "type": "Feature",
  "properties": {
    "date:inception_lower": "2006-05-01",
    "date:inception_upper": "2006-05-01",
    "iso:country": "GB",
    "wof:name": "DN10 4RU",
    "wof:placetype": "postalcode"
  },
  "geometry": {"coordinates":[-0.911502,53.407575],"type":"Point"}
}
