{
  "type": "Feature",
  "properties": {
    "iso:country":"GB",
    "wof:name":"DN10 4RU",
    "wof:placetype":"postalcode"
},
  "geometry": {"coordinates":[-0.91150245472503,53.40757533507663],"type":"Point"}
}