{
  "type": "Feature",
  "properties": {
    "iso:country":"GB",
    "wof:name":"NP4 8LU",
    "wof:placetype":"postalcode"
},
  "geometry": {"coordinates":[-3.05509735560266,51.71410166079255],"type":"Point"}
}