{
  "type": "Feature",
  "properties": {
    "date:inception_lower":"1992-01-01",
    "date:inception_upper":"1992-01-31",
    "iso:country":"GB",
    "wof:name":"RH12 1NS",
    "wof:placetype":"postalcode"
},
  "geometry": {"coordinates":[-0.344533,51.058429],"type":"Point"}
}