{
  "type": "Feature",
  "properties": {
    "iso:country":"GB",
    "wof:name":"RH12 1NS",
    "wof:placetype":"postalcode"
},
  "geometry": {"coordinates":[-0.34453262955433,51.05842909070847],"type":"Point"}
}