{
  "type": "Feature",
  "properties": {
    "iso:country": "GB",
    "wof:name": "RH12 1NS",
    "wof:placetype": "postalcode"
  },
  "geometry": {"coordinates":[-0.344533,51.058429],"type":"Point"}
}
