{
  "type": "Feature",
  "properties": {
    "iso:country":"GB",
    "wof:name":"N16 6TW",
    "wof:placetype":"postalcode"
},
  "geometry": {"coordinates":[-0.0719415091065,51.57428898596992],"type":"Point"}
}