{
  "type": "Feature",
  "properties": {
    "date:inception_lower": "1980-01-01",
    "date:inception_upper": "1980-01-01",
    "iso:country": "GB",
    "wof:name": "N16 6TW",
    "wof:placetype": "postalcode"
  },
  "geometry": {"coordinates":[-0.071941,51.574289],"type":"Point"}
}
