{
  "type": "Feature",
  "properties": {
    "iso:country":"GB",
    "wof:name":"YO31 0XF",
    "wof:placetype":"postalcode"
},
  "geometry": {"coordinates":[-1.06638703876406,53.9642125658246],"type":"Point"}
}