{
  "type": "Feature",
  "properties": {
    "iso:country":"GB",
    "wof:name":"G22 7JW",
    "wof:placetype":"postalcode"
},
  "geometry": {"coordinates":[-4.24657249110434,55.90049042799851],"type":"Point"}
}