{
  "type": "Feature",
  "properties": {
    "iso:country": "GB",
    "wof:name": "AB33 8DJ",
    "wof:placetype": "postalcode"
  },
  "geometry": {"coordinates":[-2.634182,57.224262],"type":"Point"}
}
