{
  "type": "Feature",
  "properties": {
    "iso:country":"GB",
    "wof:name":"M28 0AS",
    "wof:placetype":"postalcode"
},
  "geometry": {"coordinates":[-2.40726171052453,53.52512068995664],"type":"Point"}
}