{
  "type": "Feature",
  "properties": {
    "iso:country": "GB",
    "wof:name": "M28 0AS",
    "wof:placetype": "postalcode"
  },
  "geometry": {"coordinates":[-2.407262,53.525121],"type":"Point"}
}
