{
  "type": "Feature",
  "properties": {
    "iso:country": "GB",
    "wof:name": "PO10 8LG",
    "wof:placetype": "postalcode"
  },
  "geometry": {"coordinates":[-0.906857,50.849478],"type":"Point"}
}
