{
  "type": "Feature",
  "properties": {
    "date:inception_lower": "1980-01-01",
    "date:inception_upper": "1980-01-01",
    "iso:country": "GB",
    "wof:name": "CF45 3UU",
    "wof:placetype": "postalcode"
  },
  "geometry": {"coordinates":[-3.366807,51.671648],"type":"Point"}
}
