{
  "type": "Feature",
  "properties": {
    "date:inception_lower": "2023-07-01",
    "date:inception_upper": "2023-07-01",
    "iso:country": "GB",
    "wof:name": "BN10 8GY",
    "wof:placetype": "postalcode"
  },
  "geometry": {"coordinates":[0.007617,50.797077],"type":"Point"}
}
