{
  "type": "Feature",
  "properties": {
    "date:inception_lower": "1980-01-01",
    "date:inception_upper": "1980-01-01",
    "iso:country": "GB",
    "wof:name": "DL1 5HG",
    "wof:placetype": "postalcode"
  },
  "geometry": {"coordinates":[-1.556658,54.523808],"type":"Point"}
}
