{
  "type": "Feature",
  "properties": {
    "iso:country":"GB",
    "wof:name":"DL1 5HG",
    "wof:placetype":"postalcode"
},
  "geometry": {"coordinates":[-1.55649507714042,54.52378747438313],"type":"Point"}
}