{
  "type": "Feature",
  "properties": {
    "date:inception_lower": "1980-01-01",
    "date:inception_upper": "1980-01-01",
    "iso:country": "GB",
    "wof:name": "NN11 4AG",
    "wof:placetype": "postalcode"
  },
  "geometry": {"coordinates":[-1.164683,52.256273],"type":"Point"}
}
