{
  "type": "Feature",
  "properties": {
    "iso:country": "GB",
    "wof:name": "NN11 4AG",
    "wof:placetype": "postalcode"
  },
  "geometry": {"coordinates":[-1.164813,52.256372],"type":"Point"}
}
