{
  "type": "Feature",
  "properties": {
    "iso:country": "GB",
    "wof:name": "BS15 1HY",
    "wof:placetype": "postalcode"
  },
  "geometry": {"coordinates":[-2.515661,51.46398],"type":"Point"}
}
