{
  "type": "Feature",
  "properties": {
    "iso:country":"GB",
    "wof:name":"HA8 9DT",
    "wof:placetype":"postalcode"
},
  "geometry": {"coordinates":[-0.25330042116517,51.61115531509296],"type":"Point"}
}