{
  "type": "Feature",
  "properties": {
    "iso:country":"GB",
    "wof:name":"SS16 5UE",
    "wof:placetype":"postalcode"
},
  "geometry": {"coordinates":[0.42526461031022,51.56443504577582],"type":"Point"}
}