{
  "type": "Feature",
  "properties": {
    "iso:country":"GB",
    "wof:name":"NR7 0WF",
    "wof:placetype":"postalcode"
},
  "geometry": {"coordinates":[1.37485999174158,52.63108627490251],"type":"Point"}
}