{
  "type": "Feature",
  "properties": {
    "date:inception_lower": "2004-01-01",
    "date:inception_upper": "2004-01-01",
    "iso:country": "GB",
    "wof:name": "NR7 0WF",
    "wof:placetype": "postalcode"
  },
  "geometry": {"coordinates":[1.37486,52.631086],"type":"Point"}
}
