{
  "type": "Feature",
  "properties": {
    "iso:country":"GB",
    "wof:name":"EX14 4QD",
    "wof:placetype":"postalcode"
},
  "geometry": {"coordinates":[-3.22053342431992,50.85490920956138],"type":"Point"}
}