{
  "type": "Feature",
  "properties": {
    "iso:country":"GB",
    "wof:name":"YO17 8AD",
    "wof:placetype":"postalcode"
},
  "geometry": {"coordinates":[-0.7756762453544,54.13819381533629],"type":"Point"}
}