{
  "type": "Feature",
  "properties": {
    "date:inception_lower":"1980-01-01",
    "date:inception_upper":"1980-01-31",
    "iso:country":"GB",
    "wof:name":"TW12 2DD",
    "wof:placetype":"postalcode"
},
  "geometry": {"coordinates":[-0.370938,51.415584],"type":"Point"}
}