{
  "type": "Feature",
  "properties": {
    "iso:country":"GB",
    "wof:name":"TW12 2DD",
    "wof:placetype":"postalcode"
},
  "geometry": {"coordinates":[-0.37093774371136,51.41558355101375],"type":"Point"}
}