{
  "type": "Feature",
  "properties": {
    "iso:country": "GB",
    "wof:name": "EH47 7EJ",
    "wof:placetype": "postalcode"
  },
  "geometry": {"coordinates":[-3.619298,55.871699],"type":"Point"}
}
