{
  "type": "Feature",
  "properties": {
    "iso:country":"GB",
    "wof:name":"G41 4QJ",
    "wof:placetype":"postalcode"
},
  "geometry": {"coordinates":[-4.27706032655212,55.83929151873322],"type":"Point"}
}