{
  "type": "Feature",
  "properties": {
    "iso:country": "GB",
    "wof:name": "G41 4QJ",
    "wof:placetype": "postalcode"
  },
  "geometry": {"coordinates":[-4.276567,55.839287],"type":"Point"}
}
