{
  "type": "Feature",
  "properties": {
    "date:inception_lower": "1995-07-01",
    "date:inception_upper": "1995-07-01",
    "iso:country": "GB",
    "wof:name": "OL7 9EJ",
    "wof:placetype": "postalcode"
  },
  "geometry": {"coordinates":[-2.103916,53.498778],"type":"Point"}
}
