{
  "type": "Feature",
  "properties": {
    "iso:country": "GB",
    "wof:name": "SA62 5BJ",
    "wof:placetype": "postalcode"
  },
  "geometry": {"coordinates":[-5.181107,51.94499],"type":"Point"}
}
