{
  "type": "Feature",
  "properties": {
    "iso:country": "GB",
    "wof:name": "GU6 7JS",
    "wof:placetype": "postalcode"
  },
  "geometry": {"coordinates":[-0.474609,51.137636],"type":"Point"}
}
