{
  "type": "Feature",
  "properties": {
    "iso:country":"GB",
    "wof:name":"GU6 7JS",
    "wof:placetype":"postalcode"
},
  "geometry": {"coordinates":[-0.4746094694942,51.13763565786876],"type":"Point"}
}