{
  "type": "Feature",
  "properties": {
    "iso:country": "GB",
    "wof:name": "KW1 5TH",
    "wof:placetype": "postalcode"
  },
  "geometry": {"coordinates":[-3.086878,58.43011],"type":"Point"}
}
