{
  "type": "Feature",
  "properties": {
    "iso:country":"GB",
    "wof:name":"KW1 5TH",
    "wof:placetype":"postalcode"
},
  "geometry": {"coordinates":[-3.0868782527908,58.43011037024073],"type":"Point"}
}