{
  "type": "Feature",
  "properties": {
    "iso:country":"GB",
    "wof:name":"NN4 9XQ",
    "wof:placetype":"postalcode"
},
  "geometry": {"coordinates":[-0.93659243692112,52.2182353839687],"type":"Point"}
}