{
  "type": "Feature",
  "properties": {
    "iso:country": "GB",
    "wof:name": "RG42 6JL",
    "wof:placetype": "postalcode"
  },
  "geometry": {"coordinates":[-0.722001,51.444774],"type":"Point"}
}
