{
  "type": "Feature",
  "properties": {
    "date:inception_lower": "1980-01-01",
    "date:inception_upper": "1980-01-01",
    "iso:country": "GB",
    "wof:name": "PE20 2HA",
    "wof:placetype": "postalcode"
  },
  "geometry": {"coordinates":[-0.096311,52.903676],"type":"Point"}
}
