{
  "type": "Feature",
  "properties": {
    "iso:country":"GB",
    "wof:name":"PE20 2HA",
    "wof:placetype":"postalcode"
},
  "geometry": {"coordinates":[-0.09631117169723,52.90367604384043],"type":"Point"}
}