{
  "type": "Feature",
  "properties": {
    "date:inception_lower": "2021-03-01",
    "date:inception_upper": "2021-03-01",
    "iso:country": "GB",
    "wof:name": "TN5 7FJ",
    "wof:placetype": "postalcode"
  },
  "geometry": {"coordinates":[0.455395,51.052235],"type":"Point"}
}
