{
  "type": "Feature",
  "properties": {
    "iso:country":"GB",
    "wof:name":"CW3 9BJ",
    "wof:placetype":"postalcode"
},
  "geometry": {"coordinates":[-2.3686414171348,53.02465982726659],"type":"Point"}
}