{
  "type": "Feature",
  "properties": {
    "iso:country": "GB",
    "wof:name": "BL1 8EJ",
    "wof:placetype": "postalcode"
  },
  "geometry": {"coordinates":[-2.43295,53.593286],"type":"Point"}
}
