{
  "type": "Feature",
  "properties": {
    "iso:country":"GB",
    "wof:name":"BL1 8EJ",
    "wof:placetype":"postalcode"
},
  "geometry": {"coordinates":[-2.43295181769528,53.59327024100689],"type":"Point"}
}