{
  "type": "Feature",
  "properties": {
    "iso:country":"GB",
    "wof:name":"BL9 7QH",
    "wof:placetype":"postalcode"
},
  "geometry": {"coordinates":[-2.27922035151385,53.59500438326987],"type":"Point"}
}