{
  "type": "Feature",
  "properties": {
    "date:inception_lower": "1980-01-01",
    "date:inception_upper": "1980-01-01",
    "iso:country": "GB",
    "wof:name": "BL9 7QH",
    "wof:placetype": "postalcode"
  },
  "geometry": {"coordinates":[-2.27922,53.595004],"type":"Point"}
}
