{
  "type": "Feature",
  "properties": {
    "iso:country":"GB",
    "wof:name":"NE66 1AT",
    "wof:placetype":"postalcode"
},
  "geometry": {"coordinates":[-1.70060490252152,55.40758681127954],"type":"Point"}
}