{
  "type": "Feature",
  "properties": {
    "iso:country":"GB",
    "wof:name":"SS3 9FH",
    "wof:placetype":"postalcode"
},
  "geometry": {"coordinates":[0.78346468552333,51.53265677407435],"type":"Point"}
}