{
  "type": "Feature",
  "properties": {
    "iso:country": "GB",
    "wof:name": "BD24 9LT",
    "wof:placetype": "postalcode"
  },
  "geometry": {"coordinates":[-2.279261,54.078007],"type":"Point"}
}
