{
  "type": "Feature",
  "properties": {
    "iso:country":"GB",
    "wof:name":"BD24 9LT",
    "wof:placetype":"postalcode"
},
  "geometry": {"coordinates":[-2.27830556535351,54.07690337583416],"type":"Point"}
}