{
  "type": "Feature",
  "properties": {
    "iso:country":"GB",
    "wof:name":"SO19 6AP",
    "wof:placetype":"postalcode"
},
  "geometry": {"coordinates":[-1.32253856206132,50.90476891453841],"type":"Point"}
}