{
  "type": "Feature",
  "properties": {
    "iso:country": "GB",
    "wof:name": "SO19 6AP",
    "wof:placetype": "postalcode"
  },
  "geometry": {"coordinates":[-1.322528,50.90476],"type":"Point"}
}
