{
  "type": "Feature",
  "properties": {
    "iso:country":"GB",
    "wof:name":"N1 2BS",
    "wof:placetype":"postalcode"
},
  "geometry": {"coordinates":[-0.09890562682324,51.53989200570315],"type":"Point"}
}