{
  "type": "Feature",
  "properties": {
    "iso:country":"GB",
    "wof:name":"S71 1RB",
    "wof:placetype":"postalcode"
},
  "geometry": {"coordinates":[-1.48108974197554,53.56537203134332],"type":"Point"}
}