{
  "type": "Feature",
  "properties": {
    "iso:country": "GB",
    "wof:name": "N2 9LY",
    "wof:placetype": "postalcode"
  },
  "geometry": {"coordinates":[-0.153732,51.589758],"type":"Point"}
}
