{
  "type": "Feature",
  "properties": {
    "iso:country":"GB",
    "wof:name":"PR5 4JH",
    "wof:placetype":"postalcode"
},
  "geometry": {"coordinates":[-2.66511231845644,53.74142881863869],"type":"Point"}
}