{
  "type": "Feature",
  "properties": {
    "date:inception_lower": "1980-01-01",
    "date:inception_upper": "1980-01-01",
    "iso:country": "GB",
    "wof:name": "NN9 6LB",
    "wof:placetype": "postalcode"
  },
  "geometry": {"coordinates":[-0.538098,52.346437],"type":"Point"}
}
