{
  "type": "Feature",
  "properties": {
    "iso:country":"GB",
    "wof:name":"NN9 6LB",
    "wof:placetype":"postalcode"
},
  "geometry": {"coordinates":[-0.53809766913402,52.34643684295406],"type":"Point"}
}