{
  "type": "Feature",
  "properties": {
    "date:inception_lower":"1992-05-01",
    "date:inception_upper":"1992-05-31",
    "iso:country":"GB",
    "wof:name":"PH20 1EG",
    "wof:placetype":"postalcode"
},
  "geometry": {"coordinates":[-4.124719,57.063812],"type":"Point"}
}