{
  "type": "Feature",
  "properties": {
    "iso:country": "GB",
    "wof:name": "PH20 1EG",
    "wof:placetype": "postalcode"
  },
  "geometry": {"coordinates":[-4.124719,57.063812],"type":"Point"}
}
