{
  "type": "Feature",
  "properties": {
    "iso:country":"GB",
    "wof:name":"PH20 1EG",
    "wof:placetype":"postalcode"
},
  "geometry": {"coordinates":[-4.12471885936522,57.06381153702998],"type":"Point"}
}