{
  "type": "Feature",
  "properties": {
    "iso:country": "GB",
    "wof:name": "GU14 8JE",
    "wof:placetype": "postalcode"
  },
  "geometry": {"coordinates":[-0.756498,51.313041],"type":"Point"}
}
