{
  "type": "Feature",
  "properties": {
    "date:inception_lower": "1980-01-01",
    "date:inception_upper": "1980-01-01",
    "iso:country": "GB",
    "wof:name": "G65 9JD",
    "wof:placetype": "postalcode"
  },
  "geometry": {"coordinates":[-4.039468,55.955681],"type":"Point"}
}
