{
  "type": "Feature",
  "properties": {
    "iso:country":"GB",
    "wof:name":"G65 9JD",
    "wof:placetype":"postalcode"
},
  "geometry": {"coordinates":[-4.03946827960949,55.95568100302718],"type":"Point"}
}