{
  "type": "Feature",
  "properties": {
    "iso:country":"GB",
    "wof:name":"HR3 5EN",
    "wof:placetype":"postalcode"
},
  "geometry": {"coordinates":[-3.12088127403233,52.07771044856617],"type":"Point"}
}