{
  "type": "Feature",
  "properties": {
    "date:inception_lower": "1980-01-01",
    "date:inception_upper": "1980-01-01",
    "iso:country": "GB",
    "wof:name": "HR3 5EN",
    "wof:placetype": "postalcode"
  },
  "geometry": {"coordinates":[-3.120881,52.07771],"type":"Point"}
}
