{
  "type": "Feature",
  "properties": {
    "iso:country":"GB",
    "wof:name":"TF2 7DL",
    "wof:placetype":"postalcode"
},
  "geometry": {"coordinates":[-2.45408410198303,52.71462401514535],"type":"Point"}
}