{
  "type": "Feature",
  "properties": {
    "iso:country": "GB",
    "wof:name": "TF2 7DL",
    "wof:placetype": "postalcode"
  },
  "geometry": {"coordinates":[-2.454084,52.714624],"type":"Point"}
}
