{
  "type": "Feature",
  "properties": {
    "iso:country":"GB",
    "wof:name":"SR6 7PH",
    "wof:placetype":"postalcode"
},
  "geometry": {"coordinates":[-1.40302106391683,54.95556790566906],"type":"Point"}
}