{
  "type": "Feature",
  "properties": {
    "iso:country":"GB",
    "wof:name":"GL7 5PU",
    "wof:placetype":"postalcode"
},
  "geometry": {"coordinates":[-1.90000983009571,51.70054665802198],"type":"Point"}
}