{
  "type": "Feature",
  "properties": {
    "date:inception_lower":"1980-01-01",
    "date:inception_upper":"1980-01-31",
    "iso:country":"GB",
    "wof:name":"GL7 5PU",
    "wof:placetype":"postalcode"
},
  "geometry": {"coordinates":[-1.900776,51.701051],"type":"Point"}
}