{
  "type": "Feature",
  "properties": {
    "iso:country": "GB",
    "wof:name": "GL7 5PU",
    "wof:placetype": "postalcode"
  },
  "geometry": {"coordinates":[-1.900448,51.701118],"type":"Point"}
}
