{
  "type": "Feature",
  "properties": {
    "iso:country": "GB",
    "wof:name": "GL7 5PU",
    "wof:placetype": "postalcode"
  },
  "geometry": {"coordinates":[-1.900776,51.701051],"type":"Point"}
}
