{
  "type": "Feature",
  "properties": {
    "iso:country":"GB",
    "wof:name":"RH2 9PJ",
    "wof:placetype":"postalcode"
},
  "geometry": {"coordinates":[-0.20176373047384,51.25109769546285],"type":"Point"}
}