{
  "type": "Feature",
  "properties": {
    "iso:country":"GB",
    "wof:name":"CM11 1DT",
    "wof:placetype":"postalcode"
},
  "geometry": {"coordinates":[0.43388028085862,51.64275782961664],"type":"Point"}
}