{
  "type": "Feature",
  "properties": {
    "date:inception_lower": "2008-03-01",
    "date:inception_upper": "2008-03-01",
    "iso:country": "GB",
    "wof:name": "DY4 9ER",
    "wof:placetype": "postalcode"
  },
  "geometry": {"coordinates":[-2.073698,52.534814],"type":"Point"}
}
