{
  "type": "Feature",
  "properties": {
    "iso:country":"GB",
    "wof:name":"DY4 9ER",
    "wof:placetype":"postalcode"
},
  "geometry": {"coordinates":[-2.07369811122049,52.53481359169047],"type":"Point"}
}