{
  "type": "Feature",
  "properties": {
    "iso:country":"GB",
    "wof:name":"MK3 6JW",
    "wof:placetype":"postalcode"
},
  "geometry": {"coordinates":[-0.74451613528808,52.0069561385387],"type":"Point"}
}