{
  "type": "Feature",
  "properties": {
    "date:inception_lower": "1980-01-01",
    "date:inception_upper": "1980-01-01",
    "iso:country": "GB",
    "wof:name": "MK3 6JW",
    "wof:placetype": "postalcode"
  },
  "geometry": {"coordinates":[-0.744516,52.006956],"type":"Point"}
}
