{
  "type": "Feature",
  "properties": {
    "date:inception_lower":"1997-12-01",
    "date:inception_upper":"1997-12-31",
    "iso:country":"GB",
    "wof:name":"BS40 7TJ",
    "wof:placetype":"postalcode"
},
  "geometry": {"coordinates":[-2.71832,51.326522],"type":"Point"}
}