{
  "type": "Feature",
  "properties": {
    "iso:country": "GB",
    "wof:name": "BS40 7TJ",
    "wof:placetype": "postalcode"
  },
  "geometry": {"coordinates":[-2.71832,51.326522],"type":"Point"}
}
