{
  "type": "Feature",
  "properties": {
    "iso:country":"GB",
    "wof:name":"BS40 7TJ",
    "wof:placetype":"postalcode"
},
  "geometry": {"coordinates":[-2.71807088534386,51.32641941401933],"type":"Point"}
}