{
  "type": "Feature",
  "properties": {
    "iso:country":"GB",
    "wof:name":"SG4 0RY",
    "wof:placetype":"postalcode"
},
  "geometry": {"coordinates":[-0.26397710207533,51.96793572970329],"type":"Point"}
}