{
  "type": "Feature",
  "properties": {
    "iso:country":"GB",
    "wof:name":"HR9 7PA",
    "wof:placetype":"postalcode"
},
  "geometry": {"coordinates":[-2.5348494414624,51.90566196726511],"type":"Point"}
}