{
  "type": "Feature",
  "properties": {
    "date:inception_lower":"1980-01-01",
    "date:inception_upper":"1980-01-31",
    "iso:country":"GB",
    "wof:name":"BA2 6LU",
    "wof:placetype":"postalcode"
},
  "geometry": {"coordinates":[-2.357438,51.385683],"type":"Point"}
}