{
  "type": "Feature",
  "properties": {
    "iso:country":"GB",
    "wof:name":"BA2 6LU",
    "wof:placetype":"postalcode"
},
  "geometry": {"coordinates":[-2.35748295689479,51.38570369964425],"type":"Point"}
}