{
  "type": "Feature",
  "properties": {
    "date:inception_lower":"1980-01-01",
    "date:inception_upper":"1980-01-31",
    "iso:country":"GB",
    "wof:name":"TS5 4NR",
    "wof:placetype":"postalcode"
},
  "geometry": {"coordinates":[-1.264353,54.561467],"type":"Point"}
}