{
  "type": "Feature",
  "properties": {
    "iso:country":"GB",
    "wof:name":"TS5 4NR",
    "wof:placetype":"postalcode"
},
  "geometry": {"coordinates":[-1.26435259974058,54.56146681659416],"type":"Point"}
}