{
  "type": "Feature",
  "properties": {
    "iso:country":"GB",
    "wof:name":"KA24 5LQ",
    "wof:placetype":"postalcode"
},
  "geometry": {"coordinates":[-4.72861692595009,55.72074240581745],"type":"Point"}
}