{
  "type": "Feature",
  "properties": {
    "date:inception_lower":"1980-01-01",
    "date:inception_upper":"1980-01-31",
    "iso:country":"GB",
    "wof:name":"OL13 9QE",
    "wof:placetype":"postalcode"
},
  "geometry": {"coordinates":[-2.196938,53.695833],"type":"Point"}
}