{
  "type": "Feature",
  "properties": {
    "iso:country":"GB",
    "wof:name":"OL13 9QE",
    "wof:placetype":"postalcode"
},
  "geometry": {"coordinates":[-2.19693835610783,53.69581814340745],"type":"Point"}
}