{
  "type": "Feature",
  "properties": {
    "iso:country":"GB",
    "wof:name":"BN6 9JB",
    "wof:placetype":"postalcode"
},
  "geometry": {"coordinates":[-0.19879811411507,50.94751075828828],"type":"Point"}
}