{
  "type": "Feature",
  "properties": {
    "iso:country":"GB",
    "wof:name":"BA4 4AD",
    "wof:placetype":"postalcode"
},
  "geometry": {"coordinates":[-2.62461311724961,51.1732736079802],"type":"Point"}
}