{
  "type": "Feature",
  "properties": {
    "iso:country": "GB",
    "wof:name": "BA4 4AD",
    "wof:placetype": "postalcode"
  },
  "geometry": {"coordinates":[-2.624613,51.173274],"type":"Point"}
}
