{
  "type": "Feature",
  "properties": {
    "iso:country":"GB",
    "wof:name":"TS17 0LB",
    "wof:placetype":"postalcode"
},
  "geometry": {"coordinates":[-1.30778313873597,54.53550776588143],"type":"Point"}
}