{
  "type": "Feature",
  "properties": {
    "date:inception_lower": "2005-12-01",
    "date:inception_upper": "2005-12-01",
    "iso:country": "GB",
    "wof:name": "SO42 7PY",
    "wof:placetype": "postalcode"
  },
  "geometry": {"coordinates":[-1.572785,50.817664],"type":"Point"}
}
