{
  "type": "Feature",
  "properties": {
    "date:inception_lower": "1980-01-01",
    "date:inception_upper": "1980-01-01",
    "iso:country": "GB",
    "wof:name": "FY1 4HW",
    "wof:placetype": "postalcode"
  },
  "geometry": {"coordinates":[-3.042342,53.816814],"type":"Point"}
}
