{
  "type": "Feature",
  "properties": {
    "iso:country":"GB",
    "wof:name":"FY1 4HW",
    "wof:placetype":"postalcode"
},
  "geometry": {"coordinates":[-3.04234238421509,53.81681435677373],"type":"Point"}
}