{
  "type": "Feature",
  "properties": {
    "iso:country":"GB",
    "wof:name":"NE4 6PP",
    "wof:placetype":"postalcode"
},
  "geometry": {"coordinates":[-1.63774006068789,54.97210229999697],"type":"Point"}
}