{
  "type": "Feature",
  "properties": {
    "iso:country":"GB",
    "wof:name":"CM2 6XE",
    "wof:placetype":"postalcode"
},
  "geometry": {"coordinates":[0.49569800926558,51.73263222433577],"type":"Point"}
}