{
  "type": "Feature",
  "properties": {
    "iso:country":"GB",
    "wof:name":"KY16 9JD",
    "wof:placetype":"postalcode"
},
  "geometry": {"coordinates":[-2.80234692314519,56.34357975222586],"type":"Point"}
}