{
  "type": "Feature",
  "properties": {
    "iso:country": "GB",
    "wof:name": "DE13 8JA",
    "wof:placetype": "postalcode"
  },
  "geometry": {"coordinates":[-1.724072,52.761965],"type":"Point"}
}
