{
  "type": "Feature",
  "properties": {
    "date:inception_lower": "1997-06-01",
    "date:inception_upper": "1997-06-01",
    "iso:country": "GB",
    "wof:name": "S33 6RH",
    "wof:placetype": "postalcode"
  },
  "geometry": {"coordinates":[-1.741475,53.347447],"type":"Point"}
}
