{
  "type": "Feature",
  "properties": {
    "iso:country":"GB",
    "wof:name":"S33 6RH",
    "wof:placetype":"postalcode"
},
  "geometry": {"coordinates":[-1.741474728489,53.3474465300699],"type":"Point"}
}