{
  "type": "Feature",
  "properties": {
    "iso:country": "GB",
    "wof:name": "KY13 9SN",
    "wof:placetype": "postalcode"
  },
  "geometry": {"coordinates":[-3.369685,56.239535],"type":"Point"}
}
