{
  "type": "Feature",
  "properties": {
    "iso:country":"GB",
    "wof:name":"KY13 9TB",
    "wof:placetype":"postalcode"
},
  "geometry": {"coordinates":[-3.41050079507912,56.22664104177083],"type":"Point"}
}