{
  "type": "Feature",
  "properties": {
    "iso:country": "GB",
    "wof:name": "SG19 3BG",
    "wof:placetype": "postalcode"
  },
  "geometry": {"coordinates":[-0.134601,52.191353],"type":"Point"}
}
