{
  "type": "Feature",
  "properties": {
    "iso:country":"GB",
    "wof:name":"SG19 3BG",
    "wof:placetype":"postalcode"
},
  "geometry": {"coordinates":[-0.13460110189824,52.1913529295162],"type":"Point"}
}