{
  "type": "Feature",
  "properties": {
    "iso:country":"GB",
    "wof:name":"EX8 5QG",
    "wof:placetype":"postalcode"
},
  "geometry": {"coordinates":[-3.38871096032414,50.64437852278937],"type":"Point"}
}