{
  "type": "Feature",
  "properties": {
    "date:inception_lower": "1984-10-01",
    "date:inception_upper": "1984-10-01",
    "iso:country": "GB",
    "wof:name": "EX8 5QG",
    "wof:placetype": "postalcode"
  },
  "geometry": {"coordinates":[-3.388711,50.644379],"type":"Point"}
}
