{
  "type": "Feature",
  "properties": {
    "iso:country": "GB",
    "wof:name": "EX8 5QG",
    "wof:placetype": "postalcode"
  },
  "geometry": {"coordinates":[-3.388711,50.644379],"type":"Point"}
}
