{
  "type": "Feature",
  "properties": {
    "date:inception_lower": "1980-01-01",
    "date:inception_upper": "1980-01-01",
    "iso:country": "GB",
    "wof:name": "SK10 1QF",
    "wof:placetype": "postalcode"
  },
  "geometry": {"coordinates":[-2.106429,53.262214],"type":"Point"}
}
