{
  "type": "Feature",
  "properties": {
    "date:inception_lower": "2001-12-01",
    "date:inception_upper": "2001-12-01",
    "iso:country": "GB",
    "wof:name": "AB34 5GG",
    "wof:placetype": "postalcode"
  },
  "geometry": {"coordinates":[-2.891726,57.07792],"type":"Point"}
}
