{
  "type": "Feature",
  "properties": {
    "iso:country":"GB",
    "wof:name":"SE23 1SJ",
    "wof:placetype":"postalcode"
},
  "geometry": {"coordinates":[-0.03718082073019,51.44509104637569],"type":"Point"}
}