{
  "type": "Feature",
  "properties": {
    "iso:country": "GB",
    "wof:name": "BB11 3RD",
    "wof:placetype": "postalcode"
  },
  "geometry": {"coordinates":[-2.207211,53.755199],"type":"Point"}
}
