{
  "type": "Feature",
  "properties": {
    "iso:country":"GB",
    "wof:name":"ME17 4LZ",
    "wof:placetype":"postalcode"
},
  "geometry": {"coordinates":[0.53454985402338,51.23779874928441],"type":"Point"}
}