{
  "type": "Feature",
  "properties": {
    "iso:country":"GB",
    "wof:name":"SN1 3PS",
    "wof:placetype":"postalcode"
},
  "geometry": {"coordinates":[-1.79229019340199,51.55631161050683],"type":"Point"}
}