{
  "type": "Feature",
  "properties": {
    "date:inception_lower": "1980-01-01",
    "date:inception_upper": "1980-01-01",
    "iso:country": "GB",
    "wof:name": "HP5 1RJ",
    "wof:placetype": "postalcode"
  },
  "geometry": {"coordinates":[-0.59998,51.699345],"type":"Point"}
}
