{
  "type": "Feature",
  "properties": {
    "iso:country":"GB",
    "wof:name":"SW15 2JR",
    "wof:placetype":"postalcode"
},
  "geometry": {"coordinates":[-0.21167024548506,51.45715414794073],"type":"Point"}
}