{
  "type": "Feature",
  "properties": {
    "iso:country":"GB",
    "wof:name":"CM15 8PS",
    "wof:placetype":"postalcode"
},
  "geometry": {"coordinates":[0.32768769299371,51.63321178323998],"type":"Point"}
}