{
  "type": "Feature",
  "properties": {
    "iso:country": "GB",
    "wof:name": "WN2 2RZ",
    "wof:placetype": "postalcode"
  },
  "geometry": {"coordinates":[-2.579366,53.537911],"type":"Point"}
}
