{
  "type": "Feature",
  "properties": {
    "iso:country":"GB",
    "wof:name":"WN2 2RZ",
    "wof:placetype":"postalcode"
},
  "geometry": {"coordinates":[-2.57936605611609,53.53791098187046],"type":"Point"}
}