{
  "type": "Feature",
  "properties": {
    "date:inception_lower":"1983-03-01",
    "date:inception_upper":"1983-03-31",
    "iso:country":"GB",
    "wof:name":"WN2 2RZ",
    "wof:placetype":"postalcode"
},
  "geometry": {"coordinates":[-2.579366,53.537911],"type":"Point"}
}