{
  "type": "Feature",
  "properties": {
    "date:inception_lower": "2018-05-01",
    "date:inception_upper": "2018-05-01",
    "iso:country": "GB",
    "wof:name": "WR9 7JN",
    "wof:placetype": "postalcode"
  },
  "geometry": {"coordinates":[-2.171764,52.252751],"type":"Point"}
}
