{
  "type": "Feature",
  "properties": {
    "iso:country": "GB",
    "wof:name": "WR9 7JN",
    "wof:placetype": "postalcode"
  },
  "geometry": {"coordinates":[-2.171764,52.252751],"type":"Point"}
}
