{
  "type": "Feature",
  "properties": {
    "date:inception_lower": "1980-01-01",
    "date:inception_upper": "1980-01-01",
    "iso:country": "GB",
    "wof:name": "TN4 0XA",
    "wof:placetype": "postalcode"
  },
  "geometry": {"coordinates":[0.243503,51.169195],"type":"Point"}
}
