{
  "type": "Feature",
  "properties": {
    "iso:country":"GB",
    "wof:name":"TN4 0XA",
    "wof:placetype":"postalcode"
},
  "geometry": {"coordinates":[0.24350261983292,51.16919531286956],"type":"Point"}
}