{
  "type": "Feature",
  "properties": {
    "iso:country": "GB",
    "wof:name": "DA14 4DT",
    "wof:placetype": "postalcode"
  },
  "geometry": {"coordinates":[0.103346,51.427285],"type":"Point"}
}
