{
  "type": "Feature",
  "properties": {
    "date:inception_lower": "2019-07-01",
    "date:inception_upper": "2019-07-01",
    "iso:country": "GB",
    "wof:name": "DA14 4DT",
    "wof:placetype": "postalcode"
  },
  "geometry": {"coordinates":[0.103346,51.427285],"type":"Point"}
}
