{
  "type": "Feature",
  "properties": {
    "iso:country":"GB",
    "wof:name":"W6 0TB",
    "wof:placetype":"postalcode"
},
  "geometry": {"coordinates":[-0.24417269878256,51.49427164443669],"type":"Point"}
}