{
  "type": "Feature",
  "properties": {
    "iso:country":"GB",
    "wof:name":"TN30 6EF",
    "wof:placetype":"postalcode"
},
  "geometry": {"coordinates":[0.68468561456631,51.08559739515193],"type":"Point"}
}