{
  "type": "Feature",
  "properties": {
    "date:inception_lower": "1980-01-01",
    "date:inception_upper": "1980-01-01",
    "iso:country": "GB",
    "wof:name": "L10 7LN",
    "wof:placetype": "postalcode"
  },
  "geometry": {"coordinates":[-2.924072,53.469245],"type":"Point"}
}
