{
  "type": "Feature",
  "properties": {
    "iso:country":"GB",
    "wof:name":"CB22 4PT",
    "wof:placetype":"postalcode"
},
  "geometry": {"coordinates":[0.16031331514941,52.09445797310133],"type":"Point"}
}