{
  "type": "Feature",
  "properties": {
    "iso:country":"GB",
    "wof:name":"GL54 5QY",
    "wof:placetype":"postalcode"
},
  "geometry": {"coordinates":[-1.97287443352378,51.95304308508451],"type":"Point"}
}