{
  "type": "Feature",
  "properties": {
    "iso:country": "GB",
    "wof:name": "GL54 5QY",
    "wof:placetype": "postalcode"
  },
  "geometry": {"coordinates":[-1.972874,51.953043],"type":"Point"}
}
