{
  "type": "Feature",
  "properties": {
    "iso:country": "GB",
    "wof:name": "CA9 3JL",
    "wof:placetype": "postalcode"
  },
  "geometry": {"coordinates":[-2.440279,54.813276],"type":"Point"}
}
