{
  "type": "Feature",
  "properties": {
    "iso:country": "GB",
    "wof:name": "DT11 8EJ",
    "wof:placetype": "postalcode"
  },
  "geometry": {"coordinates":[-2.235735,50.911359],"type":"Point"}
}
