{
  "type": "Feature",
  "properties": {
    "iso:country":"GB",
    "wof:name":"SK4 4BU",
    "wof:placetype":"postalcode"
},
  "geometry": {"coordinates":[-2.19362936916852,53.42016935466234],"type":"Point"}
}