{
  "type": "Feature",
  "properties": {
    "iso:country":"GB",
    "wof:name":"SN3 3HL",
    "wof:placetype":"postalcode"
},
  "geometry": {"coordinates":[-1.75377857840957,51.56426652584167],"type":"Point"}
}