{
  "type": "Feature",
  "properties": {
    "iso:country":"GB",
    "wof:name":"EH23 4TG",
    "wof:placetype":"postalcode"
},
  "geometry": {"coordinates":[-3.04981338503082,55.84295755230181],"type":"Point"}
}