{
  "type": "Feature",
  "properties": {
    "date:inception_lower":"1996-06-01",
    "date:inception_upper":"1996-06-30",
    "iso:country":"GB",
    "wof:name":"EH23 4TG",
    "wof:placetype":"postalcode"
},
  "geometry": {"coordinates":[-3.049813,55.842958],"type":"Point"}
}