{
  "type": "Feature",
  "properties": {
    "iso:country":"GB",
    "wof:name":"BN10 8EH",
    "wof:placetype":"postalcode"
},
  "geometry": {"coordinates":[0.00971678217959,50.80466304731672],"type":"Point"}
}