{
  "type": "Feature",
  "properties": {
    "iso:country": "GB",
    "wof:name": "CF15 7PH",
    "wof:placetype": "postalcode"
  },
  "geometry": {"coordinates":[-3.266914,51.542747],"type":"Point"}
}
