{
  "type": "Feature",
  "properties": {
    "iso:country":"GB",
    "wof:name":"CF15 7PH",
    "wof:placetype":"postalcode"
},
  "geometry": {"coordinates":[-3.26691404713779,51.54274702827848],"type":"Point"}
}