{
  "type": "Feature",
  "properties": {
    "date:inception_lower":"1999-06-01",
    "date:inception_upper":"1999-06-30",
    "iso:country":"GB",
    "wof:name":"CF15 7PH",
    "wof:placetype":"postalcode"
},
  "geometry": {"coordinates":[-3.266914,51.542747],"type":"Point"}
}