{
  "type": "Feature",
  "properties": {
    "iso:country": "GB",
    "wof:name": "LS13 2DW",
    "wof:placetype": "postalcode"
  },
  "geometry": {"coordinates":[-1.626573,53.811343],"type":"Point"}
}
