{
  "type": "Feature",
  "properties": {
    "date:inception_lower": "2006-03-01",
    "date:inception_upper": "2006-03-01",
    "iso:country": "GB",
    "wof:name": "BB3 2SW",
    "wof:placetype": "postalcode"
  },
  "geometry": {"coordinates":[-2.466336,53.690351],"type":"Point"}
}
