{
  "type": "Feature",
  "properties": {
    "iso:country": "GB",
    "wof:name": "DD8 1ND",
    "wof:placetype": "postalcode"
  },
  "geometry": {"coordinates":[-2.889734,56.638111],"type":"Point"}
}
