{
  "type": "Feature",
  "properties": {
    "iso:country": "GB",
    "wof:name": "W12 0JL",
    "wof:placetype": "postalcode"
  },
  "geometry": {"coordinates":[-0.23731,51.508979],"type":"Point"}
}
