{
  "type": "Feature",
  "properties": {
    "date:inception_lower": "1980-01-01",
    "date:inception_upper": "1980-01-01",
    "iso:country": "GB",
    "wof:name": "W12 0JL",
    "wof:placetype": "postalcode"
  },
  "geometry": {"coordinates":[-0.23731,51.508979],"type":"Point"}
}
