{
  "type": "Feature",
  "properties": {
    "iso:country":"GB",
    "wof:name":"W12 0JL",
    "wof:placetype":"postalcode"
},
  "geometry": {"coordinates":[-0.23730994643478,51.50897920315291],"type":"Point"}
}