{
  "type": "Feature",
  "properties": {
    "iso:country":"GB",
    "wof:name":"EX35 6PX",
    "wof:placetype":"postalcode"
},
  "geometry": {"coordinates":[-3.75448929538851,51.20970339346061],"type":"Point"}
}