{
  "type": "Feature",
  "properties": {
    "iso:country": "GB",
    "wof:name": "EX35 6PX",
    "wof:placetype": "postalcode"
  },
  "geometry": {"coordinates":[-3.754489,51.209703],"type":"Point"}
}
