{
  "type": "Feature",
  "properties": {
    "date:inception_lower":"1980-01-01",
    "date:inception_upper":"1980-01-31",
    "iso:country":"GB",
    "wof:name":"RG28 7RR",
    "wof:placetype":"postalcode"
},
  "geometry": {"coordinates":[-1.386504,51.235614],"type":"Point"}
}