{
  "type": "Feature",
  "properties": {
    "iso:country":"GB",
    "wof:name":"LS11 0AA",
    "wof:placetype":"postalcode"
},
  "geometry": {"coordinates":[-1.55924024286479,53.78297556960494],"type":"Point"}
}