{
  "type": "Feature",
  "properties": {
    "date:inception_lower": "1980-01-01",
    "date:inception_upper": "1980-01-01",
    "iso:country": "GB",
    "wof:name": "LS11 0AA",
    "wof:placetype": "postalcode"
  },
  "geometry": {"coordinates":[-1.55924,53.782976],"type":"Point"}
}
