{
  "type": "Feature",
  "properties": {
    "iso:country":"GB",
    "wof:name":"FK3 8YG",
    "wof:placetype":"postalcode"
},
  "geometry": {"coordinates":[-3.73737988780684,56.00611450817848],"type":"Point"}
}