{
  "type": "Feature",
  "properties": {
    "date:inception_lower": "1980-01-01",
    "date:inception_upper": "1980-01-01",
    "iso:country": "GB",
    "wof:name": "SR4 0AZ",
    "wof:placetype": "postalcode"
  },
  "geometry": {"coordinates":[-1.425724,54.903107],"type":"Point"}
}
