{
  "type": "Feature",
  "properties": {
    "iso:country":"GB",
    "wof:name":"BN15 9LB",
    "wof:placetype":"postalcode"
},
  "geometry": {"coordinates":[-0.32917196047795,50.82788799736389],"type":"Point"}
}