{
  "type": "Feature",
  "properties": {
    "iso:country": "GB",
    "wof:name": "BN15 9LB",
    "wof:placetype": "postalcode"
  },
  "geometry": {"coordinates":[-0.329172,50.827888],"type":"Point"}
}
