{
  "type": "Feature",
  "properties": {
    "date:inception_lower": "1980-01-01",
    "date:inception_upper": "1980-01-01",
    "iso:country": "GB",
    "wof:name": "DL15 9JG",
    "wof:placetype": "postalcode"
  },
  "geometry": {"coordinates":[-1.751183,54.718719],"type":"Point"}
}
