{
  "type": "Feature",
  "properties": {
    "iso:country":"GB",
    "wof:name":"DL15 9JG",
    "wof:placetype":"postalcode"
},
  "geometry": {"coordinates":[-1.75118324198835,54.71871857006153],"type":"Point"}
}