{
  "type": "Feature",
  "properties": {
    "iso:country":"GB",
    "wof:name":"B10 9AB",
    "wof:placetype":"postalcode"
},
  "geometry": {"coordinates":[-1.85062128352948,52.47219983988396],"type":"Point"}
}