{
  "type": "Feature",
  "properties": {
    "iso:country":"GB",
    "wof:name":"NR23 1JT",
    "wof:placetype":"postalcode"
},
  "geometry": {"coordinates":[0.85354981725392,52.95681994130305],"type":"Point"}
}