{
  "type": "Feature",
  "properties": {
    "iso:country":"GB",
    "wof:name":"BH25 5PG",
    "wof:placetype":"postalcode"
},
  "geometry": {"coordinates":[-1.65376866056749,50.75817623118282],"type":"Point"}
}