{
  "type": "Feature",
  "properties": {
    "date:inception_lower": "1982-03-01",
    "date:inception_upper": "1982-03-01",
    "iso:country": "GB",
    "wof:name": "BH25 5PG",
    "wof:placetype": "postalcode"
  },
  "geometry": {"coordinates":[-1.653769,50.758176],"type":"Point"}
}
