{
  "type": "Feature",
  "properties": {
    "iso:country": "GB",
    "wof:name": "BB12 9HN",
    "wof:placetype": "postalcode"
  },
  "geometry": {"coordinates":[-2.266858,53.831294],"type":"Point"}
}
