{
  "type": "Feature",
  "properties": {
    "iso:country":"GB",
    "wof:name":"BB12 9HN",
    "wof:placetype":"postalcode"
},
  "geometry": {"coordinates":[-2.26685811180269,53.83129413713829],"type":"Point"}
}