{
  "type": "Feature",
  "properties": {
    "iso:country": "GB",
    "wof:name": "TN28 8BP",
    "wof:placetype": "postalcode"
  },
  "geometry": {"coordinates":[0.94217,50.988632],"type":"Point"}
}
