{
  "type": "Feature",
  "properties": {
    "date:inception_lower":"1980-01-01",
    "date:inception_upper":"1980-01-31",
    "iso:country":"GB",
    "wof:name":"TN28 8BP",
    "wof:placetype":"postalcode"
},
  "geometry": {"coordinates":[0.94217,50.988632],"type":"Point"}
}