{
  "type": "Feature",
  "properties": {
    "iso:country":"GB",
    "wof:name":"TN28 8BP",
    "wof:placetype":"postalcode"
},
  "geometry": {"coordinates":[0.94216946506167,50.98863175885443],"type":"Point"}
}