{
  "type": "Feature",
  "properties": {
    "iso:country":"GB",
    "wof:name":"BH4 8HJ",
    "wof:placetype":"postalcode"
},
  "geometry": {"coordinates":[-1.9009431137087,50.7136213175555],"type":"Point"}
}