{
  "type": "Feature",
  "properties": {
    "date:inception_lower": "2017-09-01",
    "date:inception_upper": "2017-09-01",
    "iso:country": "GB",
    "wof:name": "CF35 6GL",
    "wof:placetype": "postalcode"
  },
  "geometry": {"coordinates":[-3.559995,51.52616],"type":"Point"}
}
