{
  "type": "Feature",
  "properties": {
    "date:inception_lower":"2007-02-01",
    "date:inception_upper":"2007-02-28",
    "iso:country":"GB",
    "wof:name":"SW7 3AX",
    "wof:placetype":"postalcode"
},
  "geometry": {"coordinates":[-0.174505,51.497993],"type":"Point"}
}