{
  "type": "Feature",
  "properties": {
    "date:inception_lower": "2002-06-01",
    "date:inception_upper": "2002-06-01",
    "iso:country": "GB",
    "wof:name": "CF40 2JP",
    "wof:placetype": "postalcode"
  },
  "geometry": {"coordinates":[-3.451767,51.63283],"type":"Point"}
}
