{
  "type": "Feature",
  "properties": {
    "iso:country":"GB",
    "wof:name":"CF40 2JP",
    "wof:placetype":"postalcode"
},
  "geometry": {"coordinates":[-3.4526801671924,51.63143950307126],"type":"Point"}
}