{
  "type": "Feature",
  "properties": {
    "iso:country": "GB",
    "wof:name": "CF40 2JP",
    "wof:placetype": "postalcode"
  },
  "geometry": {"coordinates":[-3.452691,51.631443],"type":"Point"}
}
