{
  "type": "Feature",
  "properties": {
    "iso:country": "GB",
    "wof:name": "TN36 4LT",
    "wof:placetype": "postalcode"
  },
  "geometry": {"coordinates":[0.72812,50.914229],"type":"Point"}
}
