{
  "type": "Feature",
  "properties": {
    "date:inception_lower": "1980-01-01",
    "date:inception_upper": "1980-01-01",
    "iso:country": "GB",
    "wof:name": "TN36 4LT",
    "wof:placetype": "postalcode"
  },
  "geometry": {"coordinates":[0.72812,50.914229],"type":"Point"}
}
