{
  "type": "Feature",
  "properties": {
    "iso:country": "GB",
    "wof:name": "KY11 8BF",
    "wof:placetype": "postalcode"
  },
  "geometry": {"coordinates":[-3.410713,56.072978],"type":"Point"}
}
