{
  "type": "Feature",
  "properties": {
    "iso:country":"GB",
    "wof:name":"L20 4JR",
    "wof:placetype":"postalcode"
},
  "geometry": {"coordinates":[-3.00466108922076,53.45678268394517],"type":"Point"}
}