{
  "type": "Feature",
  "properties": {
    "date:inception_lower": "1980-01-01",
    "date:inception_upper": "1980-01-01",
    "iso:country": "GB",
    "wof:name": "L20 4JR",
    "wof:placetype": "postalcode"
  },
  "geometry": {"coordinates":[-3.004765,53.45678],"type":"Point"}
}
