{
  "type": "Feature",
  "properties": {
    "iso:country":"GB",
    "wof:name":"SW7 3DY",
    "wof:placetype":"postalcode"
},
  "geometry": {"coordinates":[-0.17649203519939,51.4932298019635],"type":"Point"}
}