{
  "type": "Feature",
  "properties": {
    "date:inception_lower": "2017-09-01",
    "date:inception_upper": "2017-09-01",
    "iso:country": "GB",
    "wof:name": "LE2 0BL",
    "wof:placetype": "postalcode"
  },
  "geometry": {"coordinates":[-1.123782,52.630361],"type":"Point"}
}
