{
  "type": "Feature",
  "properties": {
    "date:inception_lower":"1998-06-01",
    "date:inception_upper":"1998-06-30",
    "iso:country":"GB",
    "wof:name":"YO32 9TR",
    "wof:placetype":"postalcode"
},
  "geometry": {"coordinates":[-0.987307,54.01076],"type":"Point"}
}