{
  "type": "Feature",
  "properties": {
    "iso:country":"GB",
    "wof:name":"HU12 8HD",
    "wof:placetype":"postalcode"
},
  "geometry": {"coordinates":[-0.19970424960909,53.73747824396354],"type":"Point"}
}