{
  "type": "Feature",
  "properties": {
    "iso:country": "GB",
    "wof:name": "AB41 9WH",
    "wof:placetype": "postalcode"
  },
  "geometry": {"coordinates":[-2.078454,57.359324],"type":"Point"}
}
