{
  "type": "Feature",
  "properties": {
    "iso:country":"GB",
    "wof:name":"AB41 9WH",
    "wof:placetype":"postalcode"
},
  "geometry": {"coordinates":[-2.07845446120824,57.35932361253035],"type":"Point"}
}