{
  "type": "Feature",
  "properties": {
    "date:inception_lower": "1981-06-01",
    "date:inception_upper": "1981-06-01",
    "iso:country": "GB",
    "wof:name": "SE28 8DT",
    "wof:placetype": "postalcode"
  },
  "geometry": {"coordinates":[0.113247,51.508015],"type":"Point"}
}
