{
  "type": "Feature",
  "properties": {
    "iso:country": "GB",
    "wof:name": "EN5 1QL",
    "wof:placetype": "postalcode"
  },
  "geometry": {"coordinates":[-0.178652,51.649209],"type":"Point"}
}
