{
  "type": "Feature",
  "properties": {
    "iso:country":"GB",
    "wof:name":"EN5 1QL",
    "wof:placetype":"postalcode"
},
  "geometry": {"coordinates":[-0.17865241779015,51.64920927838546],"type":"Point"}
}