{
  "type": "Feature",
  "properties": {
    "date:inception_lower": "1980-01-01",
    "date:inception_upper": "1980-01-01",
    "iso:country": "GB",
    "wof:name": "RH2 7JX",
    "wof:placetype": "postalcode"
  },
  "geometry": {"coordinates":[-0.198007,51.233567],"type":"Point"}
}
