{
  "type": "Feature",
  "properties": {
    "iso:country":"GB",
    "wof:name":"GU17 0EL",
    "wof:placetype":"postalcode"
},
  "geometry": {"coordinates":[-0.78841749507863,51.3367728027238],"type":"Point"}
}