{
  "type": "Feature",
  "properties": {
    "iso:country":"GB",
    "wof:name":"TA6 4JZ",
    "wof:placetype":"postalcode"
},
  "geometry": {"coordinates":[-2.99253363751525,51.13180219833422],"type":"Point"}
}