{
  "type": "Feature",
  "properties": {
    "date:inception_lower":"1998-12-01",
    "date:inception_upper":"1998-12-31",
    "iso:country":"GB",
    "wof:name":"TA6 4JZ",
    "wof:placetype":"postalcode"
},
  "geometry": {"coordinates":[-2.992528,51.131825],"type":"Point"}
}