{
  "type": "Feature",
  "properties": {
    "date:inception_lower": "2017-09-01",
    "date:inception_upper": "2017-09-01",
    "iso:country": "GB",
    "wof:name": "SK1 1DU",
    "wof:placetype": "postalcode"
  },
  "geometry": {"coordinates":[-2.161384,53.408702],"type":"Point"}
}
