{
  "type": "Feature",
  "properties": {
    "iso:country":"GB",
    "wof:name":"HP6 5JE",
    "wof:placetype":"postalcode"
},
  "geometry": {"coordinates":[-0.61155098509654,51.68060812633388],"type":"Point"}
}