{
  "type": "Feature",
  "properties": {
    "iso:country": "GB",
    "wof:name": "HP6 5JE",
    "wof:placetype": "postalcode"
  },
  "geometry": {"coordinates":[-0.611551,51.680608],"type":"Point"}
}
