{
  "type": "Feature",
  "properties": {
    "date:inception_lower":"1980-01-01",
    "date:inception_upper":"1980-01-31",
    "iso:country":"GB",
    "wof:name":"BA13 4LU",
    "wof:placetype":"postalcode"
},
  "geometry": {"coordinates":[-2.175128,51.269981],"type":"Point"}
}