{
  "type": "Feature",
  "properties": {
    "iso:country":"GB",
    "wof:name":"RH16 4ED",
    "wof:placetype":"postalcode"
},
  "geometry": {"coordinates":[-0.09993818040352,50.99296995576451],"type":"Point"}
}