{
  "type": "Feature",
  "properties": {
    "iso:country": "GB",
    "wof:name": "LL61 6SJ",
    "wof:placetype": "postalcode"
  },
  "geometry": {"coordinates":[-4.270454,53.191201],"type":"Point"}
}
