{
  "type": "Feature",
  "properties": {
    "date:inception_lower": "1980-01-01",
    "date:inception_upper": "1980-01-01",
    "iso:country": "GB",
    "wof:name": "LL61 6SJ",
    "wof:placetype": "postalcode"
  },
  "geometry": {"coordinates":[-4.270454,53.191201],"type":"Point"}
}
