{
  "type": "Feature",
  "properties": {
    "date:inception_lower":"1980-01-01",
    "date:inception_upper":"1980-01-31",
    "iso:country":"GB",
    "wof:name":"TA6 4QP",
    "wof:placetype":"postalcode"
},
  "geometry": {"coordinates":[-2.980755,51.136726],"type":"Point"}
}