{
  "type": "Feature",
  "properties": {
    "iso:country":"GB",
    "wof:name":"CM3 4JA",
    "wof:placetype":"postalcode"
},
  "geometry": {"coordinates":[0.59065491641674,51.71321032338614],"type":"Point"}
}