{
  "type": "Feature",
  "properties": {
    "iso:country":"GB",
    "wof:name":"LS11 8AR",
    "wof:placetype":"postalcode"
},
  "geometry": {"coordinates":[-1.57042379968324,53.77271581262284],"type":"Point"}
}