{
  "type": "Feature",
  "properties": {
    "iso:country":"GB",
    "wof:name":"GU7 3LB",
    "wof:placetype":"postalcode"
},
  "geometry": {"coordinates":[-0.60794438695563,51.1908618631353],"type":"Point"}
}