{
  "type": "Feature",
  "properties": {
    "date:inception_lower":"1987-10-01",
    "date:inception_upper":"1987-10-31",
    "iso:country":"GB",
    "wof:name":"GU7 3LB",
    "wof:placetype":"postalcode"
},
  "geometry": {"coordinates":[-0.607944,51.190862],"type":"Point"}
}