{
  "type": "Feature",
  "properties": {
    "iso:country": "GB",
    "wof:name": "SP11 9GS",
    "wof:placetype": "postalcode"
  },
  "geometry": {"coordinates":[-1.628833,51.251538],"type":"Point"}
}
