{
  "type": "Feature",
  "properties": {
    "iso:country": "GB",
    "wof:name": "SY13 3HP",
    "wof:placetype": "postalcode"
  },
  "geometry": {"coordinates":[-2.766359,52.94236],"type":"Point"}
}
