{
  "type": "Feature",
  "properties": {
    "iso:country":"GB",
    "wof:name":"SY13 3HP",
    "wof:placetype":"postalcode"
},
  "geometry": {"coordinates":[-2.76635911370542,52.94236007709019],"type":"Point"}
}