{
  "type": "Feature",
  "properties": {
    "iso:country":"GB",
    "wof:name":"WA16 6SA",
    "wof:placetype":"postalcode"
},
  "geometry": {"coordinates":[-2.38550158560572,53.34630251694632],"type":"Point"}
}