{
  "type": "Feature",
  "properties": {
    "date:inception_lower":"1983-07-01",
    "date:inception_upper":"1983-07-31",
    "iso:country":"GB",
    "wof:name":"SS2 5PZ",
    "wof:placetype":"postalcode"
},
  "geometry": {"coordinates":[0.717667,51.557368],"type":"Point"}
}