{
  "type": "Feature",
  "properties": {
    "date:inception_lower": "1980-01-01",
    "date:inception_upper": "1980-01-01",
    "iso:country": "GB",
    "wof:name": "SS14 2DU",
    "wof:placetype": "postalcode"
  },
  "geometry": {"coordinates":[0.46268,51.575104],"type":"Point"}
}
