{
  "type": "Feature",
  "properties": {
    "date:inception_lower": "1980-01-01",
    "date:inception_upper": "1980-01-01",
    "iso:country": "GB",
    "wof:name": "CV10 0EL",
    "wof:placetype": "postalcode"
  },
  "geometry": {"coordinates":[-1.467383,52.533739],"type":"Point"}
}
