{
  "type": "Feature",
  "properties": {
    "iso:country":"GB",
    "wof:name":"CT3 1RB",
    "wof:placetype":"postalcode"
},
  "geometry": {"coordinates":[1.18769474301817,51.27740936314338],"type":"Point"}
}