{
  "type": "Feature",
  "properties": {
    "iso:country":"GB",
    "wof:name":"L31 7FB",
    "wof:placetype":"postalcode"
},
  "geometry": {"coordinates":[-2.94448982517687,53.51150297624508],"type":"Point"}
}