{
  "type": "Feature",
  "properties": {
    "date:inception_lower": "2004-08-01",
    "date:inception_upper": "2004-08-01",
    "iso:country": "GB",
    "wof:name": "L31 7FB",
    "wof:placetype": "postalcode"
  },
  "geometry": {"coordinates":[-2.94449,53.511503],"type":"Point"}
}
