{
  "type": "Feature",
  "properties": {
    "date:inception_lower": "1994-05-01",
    "date:inception_upper": "1994-05-01",
    "iso:country": "GB",
    "wof:name": "M14 6WE",
    "wof:placetype": "postalcode"
  },
  "geometry": {"coordinates":[-2.218583,53.435946],"type":"Point"}
}
