{
  "type": "Feature",
  "properties": {
    "iso:country": "GB",
    "wof:name": "M14 6WE",
    "wof:placetype": "postalcode"
  },
  "geometry": {"coordinates":[-2.218583,53.435946],"type":"Point"}
}
