{
  "type": "Feature",
  "properties": {
    "iso:country":"GB",
    "wof:name":"W1W 7DQ",
    "wof:placetype":"postalcode"
},
  "geometry": {"coordinates":[-0.1394279285519,51.51936438076922],"type":"Point"}
}