{
  "type": "Feature",
  "properties": {
    "iso:country": "GB",
    "wof:name": "TS27 4DB",
    "wof:placetype": "postalcode"
  },
  "geometry": {"coordinates":[-1.278868,54.739567],"type":"Point"}
}
