{
  "type": "Feature",
  "properties": {
    "iso:country":"GB",
    "wof:name":"AB53 4BX",
    "wof:placetype":"postalcode"
},
  "geometry": {"coordinates":[-2.45012765411573,57.53807072863354],"type":"Point"}
}