{
  "type": "Feature",
  "properties": {
    "iso:country":"GB",
    "wof:name":"EH4 1AZ",
    "wof:placetype":"postalcode"
},
  "geometry": {"coordinates":[-3.2198720979901,55.95794963192071],"type":"Point"}
}