{
  "type": "Feature",
  "properties": {
    "iso:country": "GB",
    "wof:name": "LU3 2BW",
    "wof:placetype": "postalcode"
  },
  "geometry": {"coordinates":[-0.429445,51.918881],"type":"Point"}
}
