{
  "type": "Feature",
  "properties": {
    "iso:country":"GB",
    "wof:name":"LU3 2BW",
    "wof:placetype":"postalcode"
},
  "geometry": {"coordinates":[-0.42944482835422,51.91888101291122],"type":"Point"}
}