{
  "type": "Feature",
  "properties": {
    "iso:country":"GB",
    "wof:name":"UB2 5LJ",
    "wof:placetype":"postalcode"
},
  "geometry": {"coordinates":[-0.40069277672285,51.50204071841409],"type":"Point"}
}