{
  "type": "Feature",
  "properties": {
    "iso:country":"GB",
    "wof:name":"S61 4BS",
    "wof:placetype":"postalcode"
},
  "geometry": {"coordinates":[-1.38166880251329,53.45114961234219],"type":"Point"}
}