{
  "type": "Feature",
  "properties": {
    "iso:country":"GB",
    "wof:name":"DD6 8EX",
    "wof:placetype":"postalcode"
},
  "geometry": {"coordinates":[-2.94445953443318,56.43734728447429],"type":"Point"}
}