{
  "type": "Feature",
  "properties": {
    "date:inception_lower": "1980-01-01",
    "date:inception_upper": "1980-01-01",
    "iso:country": "GB",
    "wof:name": "SN8 3NB",
    "wof:placetype": "postalcode"
  },
  "geometry": {"coordinates":[-1.578669,51.370405],"type":"Point"}
}
