{
  "type": "Feature",
  "properties": {
    "iso:country":"GB",
    "wof:name":"SN8 3NB",
    "wof:placetype":"postalcode"
},
  "geometry": {"coordinates":[-1.57866883149292,51.37040522154667],"type":"Point"}
}