{
  "type": "Feature",
  "properties": {
    "date:inception_lower":"1990-02-01",
    "date:inception_upper":"1990-02-28",
    "iso:country":"GB",
    "wof:name":"DA4 9DN",
    "wof:placetype":"postalcode"
},
  "geometry": {"coordinates":[0.249017,51.406485],"type":"Point"}
}