{
  "type": "Feature",
  "properties": {
    "iso:country": "GB",
    "wof:name": "DA4 9DN",
    "wof:placetype": "postalcode"
  },
  "geometry": {"coordinates":[0.249017,51.406485],"type":"Point"}
}
