{
  "type": "Feature",
  "properties": {
    "iso:country":"GB",
    "wof:name":"PR25 3YD",
    "wof:placetype":"postalcode"
},
  "geometry": {"coordinates":[-2.702526457411,53.7002287427769],"type":"Point"}
}