{
  "type": "Feature",
  "properties": {
    "date:inception_lower": "1980-01-01",
    "date:inception_upper": "1980-01-01",
    "iso:country": "GB",
    "wof:name": "SG12 9RL",
    "wof:placetype": "postalcode"
  },
  "geometry": {"coordinates":[-0.01845,51.789171],"type":"Point"}
}
