{
  "type": "Feature",
  "properties": {
    "iso:country":"GB",
    "wof:name":"SG12 9RL",
    "wof:placetype":"postalcode"
},
  "geometry": {"coordinates":[-0.01845008431709,51.78917105057661],"type":"Point"}
}