{
  "type": "Feature",
  "properties": {
    "iso:country": "GB",
    "wof:name": "SG12 9RL",
    "wof:placetype": "postalcode"
  },
  "geometry": {"coordinates":[-0.01845,51.789171],"type":"Point"}
}
