{
  "type": "Feature",
  "properties": {
    "iso:country":"GB",
    "wof:name":"L20 5EN",
    "wof:placetype":"postalcode"
},
  "geometry": {"coordinates":[-2.99663171634987,53.45990616393437],"type":"Point"}
}