{
  "type": "Feature",
  "properties": {
    "iso:country": "GB",
    "wof:name": "GL15 5BJ",
    "wof:placetype": "postalcode"
  },
  "geometry": {"coordinates":[-2.519972,51.722356],"type":"Point"}
}
