{
  "type": "Feature",
  "properties": {
    "date:inception_lower": "1994-05-01",
    "date:inception_upper": "1994-05-01",
    "iso:country": "GB",
    "wof:name": "L4 3QR",
    "wof:placetype": "postalcode"
  },
  "geometry": {"coordinates":[-2.974432,53.436952],"type":"Point"}
}
