{
  "type": "Feature",
  "properties": {
    "iso:country":"GB",
    "wof:name":"NG15 7FF",
    "wof:placetype":"postalcode"
},
  "geometry": {"coordinates":[-1.21119165633984,53.03970681276311],"type":"Point"}
}