{
  "type": "Feature",
  "properties": {
    "iso:country": "GB",
    "wof:name": "NG15 7FF",
    "wof:placetype": "postalcode"
  },
  "geometry": {"coordinates":[-1.211192,53.039707],"type":"Point"}
}
