{
  "type": "Feature",
  "properties": {
    "iso:country": "GB",
    "wof:name": "AB56 1TD",
    "wof:placetype": "postalcode"
  },
  "geometry": {"coordinates":[-2.938506,57.684374],"type":"Point"}
}
