{
  "type": "Feature",
  "properties": {
    "iso:country":"GB",
    "wof:name":"CR2 8DE",
    "wof:placetype":"postalcode"
},
  "geometry": {"coordinates":[-0.06600546076757,51.34317864411997],"type":"Point"}
}