{
  "type": "Feature",
  "properties": {
    "iso:country": "GB",
    "wof:name": "PR4 2ES",
    "wof:placetype": "postalcode"
  },
  "geometry": {"coordinates":[-2.90223,53.784852],"type":"Point"}
}
