{
  "type": "Feature",
  "properties": {
    "date:inception_lower": "2017-12-01",
    "date:inception_upper": "2017-12-01",
    "iso:country": "GB",
    "wof:name": "PR4 2ES",
    "wof:placetype": "postalcode"
  },
  "geometry": {"coordinates":[-2.90223,53.784852],"type":"Point"}
}
