{
  "type": "Feature",
  "properties": {
    "iso:country": "GB",
    "wof:name": "EN4 9FA",
    "wof:placetype": "postalcode"
  },
  "geometry": {"coordinates":[-0.165098,51.646673],"type":"Point"}
}
