{
  "type": "Feature",
  "properties": {
    "iso:country": "GB",
    "wof:name": "NR8 6TN",
    "wof:placetype": "postalcode"
  },
  "geometry": {"coordinates":[1.193242,52.682907],"type":"Point"}
}
