{
  "type": "Feature",
  "properties": {
    "iso:country":"GB",
    "wof:name":"NR8 6TN",
    "wof:placetype":"postalcode"
},
  "geometry": {"coordinates":[1.19323554205348,52.68288180570008],"type":"Point"}
}