{
  "type": "Feature",
  "properties": {
    "iso:country":"GB",
    "wof:name":"BS13 9BJ",
    "wof:placetype":"postalcode"
},
  "geometry": {"coordinates":[-2.61486063996969,51.40855337232988],"type":"Point"}
}