{
  "type": "Feature",
  "properties": {
    "iso:country": "GB",
    "wof:name": "MK9 1AX",
    "wof:placetype": "postalcode"
  },
  "geometry": {"coordinates":[-0.765482,52.03603],"type":"Point"}
}
