{
  "type": "Feature",
  "properties": {
    "iso:country":"GB",
    "wof:name":"MK9 1AX",
    "wof:placetype":"postalcode"
},
  "geometry": {"coordinates":[-0.76548241997243,52.03603034921132],"type":"Point"}
}