{
  "type": "Feature",
  "properties": {
    "date:inception_lower": "1980-01-01",
    "date:inception_upper": "1980-01-01",
    "iso:country": "GB",
    "wof:name": "WA10 2SR",
    "wof:placetype": "postalcode"
  },
  "geometry": {"coordinates":[-2.735898,53.459577],"type":"Point"}
}
