{
  "type": "Feature",
  "properties": {
    "date:inception_lower": "1991-01-01",
    "date:inception_upper": "1991-01-01",
    "iso:country": "GB",
    "wof:name": "LS26 8ET",
    "wof:placetype": "postalcode"
  },
  "geometry": {"coordinates":[-1.451683,53.74231],"type":"Point"}
}
