{
  "type": "Feature",
  "properties": {
    "iso:country":"GB",
    "wof:name":"NE19 2AH",
    "wof:placetype":"postalcode"
},
  "geometry": {"coordinates":[-1.95009910069659,55.11697439964811],"type":"Point"}
}