{
  "type": "Feature",
  "properties": {
    "iso:country":"GB",
    "wof:name":"BR4 9JJ",
    "wof:placetype":"postalcode"
},
  "geometry": {"coordinates":[-0.00033110148202,51.36818211837341],"type":"Point"}
}