{
  "type": "Feature",
  "properties": {
    "iso:country":"GB",
    "wof:name":"BR2 8LZ",
    "wof:placetype":"postalcode"
},
  "geometry": {"coordinates":[0.04562067137379,51.37994279861782],"type":"Point"}
}