{
  "type": "Feature",
  "properties": {
    "date:inception_lower": "1980-01-01",
    "date:inception_upper": "1980-01-01",
    "iso:country": "GB",
    "wof:name": "KY8 4LS",
    "wof:placetype": "postalcode"
  },
  "geometry": {"coordinates":[-3.001821,56.196422],"type":"Point"}
}
