{
  "type": "Feature",
  "properties": {
    "iso:country":"GB",
    "wof:name":"LL12 8HY",
    "wof:placetype":"postalcode"
},
  "geometry": {"coordinates":[-2.97356890617257,53.08762331200642],"type":"Point"}
}