{
  "type": "Feature",
  "properties": {
    "date:inception_lower":"1992-01-01",
    "date:inception_upper":"1992-01-31",
    "iso:country":"GB",
    "wof:name":"LL12 8HY",
    "wof:placetype":"postalcode"
},
  "geometry": {"coordinates":[-2.973569,53.087623],"type":"Point"}
}