{
  "type": "Feature",
  "properties": {
    "iso:country":"GB",
    "wof:name":"TQ2 8NW",
    "wof:placetype":"postalcode"
},
  "geometry": {"coordinates":[-3.52771616077165,50.49726722340773],"type":"Point"}
}