{
  "type": "Feature",
  "properties": {
    "iso:country":"GB",
    "wof:name":"DE24 3DZ",
    "wof:placetype":"postalcode"
},
  "geometry": {"coordinates":[-1.49260555862286,52.87088256187872],"type":"Point"}
}