{
  "type": "Feature",
  "properties": {
    "date:inception_lower": "1980-01-01",
    "date:inception_upper": "1980-01-01",
    "iso:country": "GB",
    "wof:name": "SK10 2NB",
    "wof:placetype": "postalcode"
  },
  "geometry": {"coordinates":[-2.116872,53.271893],"type":"Point"}
}
