{
  "type": "Feature",
  "properties": {
    "iso:country":"GB",
    "wof:name":"WA8 0EA",
    "wof:placetype":"postalcode"
},
  "geometry": {"coordinates":[-2.73626422825828,53.35099935238711],"type":"Point"}
}