{
  "type": "Feature",
  "properties": {
    "iso:country":"GB",
    "wof:name":"BL0 9DD",
    "wof:placetype":"postalcode"
},
  "geometry": {"coordinates":[-2.319287315806,53.64877974210003],"type":"Point"}
}