{
  "type": "Feature",
  "properties": {
    "date:inception_lower":"1980-01-01",
    "date:inception_upper":"1980-01-31",
    "iso:country":"GB",
    "wof:name":"BL0 9DD",
    "wof:placetype":"postalcode"
},
  "geometry": {"coordinates":[-2.319287,53.64878],"type":"Point"}
}