{
  "type": "Feature",
  "properties": {
    "iso:country": "GB",
    "wof:name": "BL0 9DD",
    "wof:placetype": "postalcode"
  },
  "geometry": {"coordinates":[-2.319287,53.64878],"type":"Point"}
}
