{
  "type": "Feature",
  "properties": {
    "date:inception_lower": "2017-01-01",
    "date:inception_upper": "2017-01-01",
    "iso:country": "GB",
    "wof:name": "NE4 5TG",
    "wof:placetype": "postalcode"
  },
  "geometry": {"coordinates":[-1.624408,54.97259],"type":"Point"}
}
