{
  "type": "Feature",
  "properties": {
    "iso:country": "GB",
    "wof:name": "NE4 5TG",
    "wof:placetype": "postalcode"
  },
  "geometry": {"coordinates":[-1.625569,54.973717],"type":"Point"}
}
