{
  "type": "Feature",
  "properties": {
    "iso:country": "GB",
    "wof:name": "LN4 2EQ",
    "wof:placetype": "postalcode"
  },
  "geometry": {"coordinates":[-0.426443,53.177939],"type":"Point"}
}
