{
  "type": "Feature",
  "properties": {
    "iso:country":"GB",
    "wof:name":"LN4 2EQ",
    "wof:placetype":"postalcode"
},
  "geometry": {"coordinates":[-0.42644352313353,53.17793930046919],"type":"Point"}
}