{
  "type": "Feature",
  "properties": {
    "iso:country":"GB",
    "wof:name":"LL54 7EW",
    "wof:placetype":"postalcode"
},
  "geometry": {"coordinates":[-4.26509099928497,53.0809125910331],"type":"Point"}
}