{
  "type": "Feature",
  "properties": {
    "iso:country":"GB",
    "wof:name":"B7 4PA",
    "wof:placetype":"postalcode"
},
  "geometry": {"coordinates":[-1.87728655596893,52.49174764692329],"type":"Point"}
}