{
  "type": "Feature",
  "properties": {
    "iso:country":"GB",
    "wof:name":"G22 6QF",
    "wof:placetype":"postalcode"
},
  "geometry": {"coordinates":[-4.25455630962916,55.89279501563666],"type":"Point"}
}