{
  "type": "Feature",
  "properties": {
    "date:inception_lower": "1980-01-01",
    "date:inception_upper": "1980-01-01",
    "iso:country": "GB",
    "wof:name": "G22 6QF",
    "wof:placetype": "postalcode"
  },
  "geometry": {"coordinates":[-4.254556,55.892795],"type":"Point"}
}
