{
  "type": "Feature",
  "properties": {
    "iso:country":"GB",
    "wof:name":"B26 3JT",
    "wof:placetype":"postalcode"
},
  "geometry": {"coordinates":[-1.77871933243376,52.45203966000312],"type":"Point"}
}