{
  "type": "Feature",
  "properties": {
    "date:inception_lower":"2009-11-01",
    "date:inception_upper":"2009-11-30",
    "iso:country":"GB",
    "wof:name":"LA13 0NX",
    "wof:placetype":"postalcode"
},
  "geometry": {"coordinates":[-3.167822,54.141707],"type":"Point"}
}