{
  "type": "Feature",
  "properties": {
    "date:inception_lower": "2009-11-01",
    "date:inception_upper": "2009-11-01",
    "iso:country": "GB",
    "wof:name": "LA13 0NX",
    "wof:placetype": "postalcode"
  },
  "geometry": {"coordinates":[-3.163464,54.135358],"type":"Point"}
}
