{
  "type": "Feature",
  "properties": {
    "iso:country": "GB",
    "wof:name": "LA13 0NX",
    "wof:placetype": "postalcode"
  },
  "geometry": {"coordinates":[-3.167822,54.141707],"type":"Point"}
}
