{
  "type": "Feature",
  "properties": {
    "iso:country":"GB",
    "wof:name":"LA13 0NX",
    "wof:placetype":"postalcode"
},
  "geometry": {"coordinates":[-3.16782355797558,54.14169803167836],"type":"Point"}
}