{
  "type": "Feature",
  "properties": {
    "iso:country":"GB",
    "wof:name":"CF3 1RF",
    "wof:placetype":"postalcode"
},
  "geometry": {"coordinates":[-3.11042939474254,51.52044159695173],"type":"Point"}
}