{
  "type": "Feature",
  "properties": {
    "iso:country": "GB",
    "wof:name": "ST5 6SU",
    "wof:placetype": "postalcode"
  },
  "geometry": {"coordinates":[-2.276427,53.019571],"type":"Point"}
}
