{
  "type": "Feature",
  "properties": {
    "iso:country":"GB",
    "wof:name":"ST5 6SU",
    "wof:placetype":"postalcode"
},
  "geometry": {"coordinates":[-2.27642683077702,53.01957051490759],"type":"Point"}
}