{
  "type": "Feature",
  "properties": {
    "iso:country": "GB",
    "wof:name": "M22 4LX",
    "wof:placetype": "postalcode"
  },
  "geometry": {"coordinates":[-2.253899,53.40365],"type":"Point"}
}
