{
  "type": "Feature",
  "properties": {
    "iso:country":"GB",
    "wof:name":"M22 4LX",
    "wof:placetype":"postalcode"
},
  "geometry": {"coordinates":[-2.25391414577811,53.40366113621302],"type":"Point"}
}