{
  "type": "Feature",
  "properties": {
    "date:inception_lower": "1980-01-01",
    "date:inception_upper": "1980-01-01",
    "iso:country": "GB",
    "wof:name": "DE6 1AA",
    "wof:placetype": "postalcode"
  },
  "geometry": {"coordinates":[-1.735321,53.015769],"type":"Point"}
}
