{
  "type": "Feature",
  "properties": {
    "iso:country": "GB",
    "wof:name": "DE6 1AA",
    "wof:placetype": "postalcode"
  },
  "geometry": {"coordinates":[-1.735321,53.015769],"type":"Point"}
}
