{
  "type": "Feature",
  "properties": {
    "iso:country": "GB",
    "wof:name": "NR32 3LY",
    "wof:placetype": "postalcode"
  },
  "geometry": {"coordinates":[1.718103,52.476262],"type":"Point"}
}
