{
  "type": "Feature",
  "properties": {
    "iso:country": "GB",
    "wof:name": "NW5 3DT",
    "wof:placetype": "postalcode"
  },
  "geometry": {"coordinates":[-0.144406,51.547673],"type":"Point"}
}
