{
  "type": "Feature",
  "properties": {
    "date:inception_lower":"1980-01-01",
    "date:inception_upper":"1980-01-31",
    "iso:country":"GB",
    "wof:name":"NW5 3DT",
    "wof:placetype":"postalcode"
},
  "geometry": {"coordinates":[-0.144406,51.547673],"type":"Point"}
}