{
  "type": "Feature",
  "properties": {
    "iso:country":"GB",
    "wof:name":"NW5 3DT",
    "wof:placetype":"postalcode"
},
  "geometry": {"coordinates":[-0.14443194406651,51.54767102565715],"type":"Point"}
}