{
  "type": "Feature",
  "properties": {
    "iso:country":"GB",
    "wof:name":"RG21 8AU",
    "wof:placetype":"postalcode"
},
  "geometry": {"coordinates":[-1.10206767175276,51.26042175899642],"type":"Point"}
}