{
  "type": "Feature",
  "properties": {
    "date:inception_lower": "1980-01-01",
    "date:inception_upper": "1980-01-01",
    "iso:country": "GB",
    "wof:name": "S65 3QS",
    "wof:placetype": "postalcode"
  },
  "geometry": {"coordinates":[-1.31385,53.439768],"type":"Point"}
}
