{
  "type": "Feature",
  "properties": {
    "iso:country":"GB",
    "wof:name":"S65 3QS",
    "wof:placetype":"postalcode"
},
  "geometry": {"coordinates":[-1.31384978700757,53.43976839500257],"type":"Point"}
}