{
  "type": "Feature",
  "properties": {
    "iso:country":"GB",
    "wof:name":"NR18 9BU",
    "wof:placetype":"postalcode"
},
  "geometry": {"coordinates":[1.07383969899814,52.55824811912053],"type":"Point"}
}