{
  "type": "Feature",
  "properties": {
    "iso:country":"GB",
    "wof:name":"TN22 1LD",
    "wof:placetype":"postalcode"
},
  "geometry": {"coordinates":[0.10623476342406,50.9790735282378],"type":"Point"}
}