{
  "type": "Feature",
  "properties": {
    "iso:country":"GB",
    "wof:name":"BD19 3NB",
    "wof:placetype":"postalcode"
},
  "geometry": {"coordinates":[-1.71386531110849,53.72604617507815],"type":"Point"}
}