{
  "type": "Feature",
  "properties": {
    "iso:country":"GB",
    "wof:name":"S61 3HP",
    "wof:placetype":"postalcode"
},
  "geometry": {"coordinates":[-1.3930643876093,53.44610247889809],"type":"Point"}
}