{
  "type": "Feature",
  "properties": {
    "iso:country":"GB",
    "wof:name":"CT19 6AW",
    "wof:placetype":"postalcode"
},
  "geometry": {"coordinates":[1.18842748769493,51.08176754043437],"type":"Point"}
}