{
  "type": "Feature",
  "properties": {
    "date:inception_lower": "1980-01-01",
    "date:inception_upper": "1980-01-01",
    "iso:country": "GB",
    "wof:name": "PO1 3JL",
    "wof:placetype": "postalcode"
  },
  "geometry": {"coordinates":[-1.102305,50.801469],"type":"Point"}
}
