{
  "type": "Feature",
  "properties": {
    "iso:country":"GB",
    "wof:name":"TR20 8AH",
    "wof:placetype":"postalcode"
},
  "geometry": {"coordinates":[-5.49488240037218,50.13971839661398],"type":"Point"}
}