{
  "type": "Feature",
  "properties": {
    "iso:country":"GB",
    "wof:name":"SG8 7ST",
    "wof:placetype":"postalcode"
},
  "geometry": {"coordinates":[0.07679744154336,52.09365723767839],"type":"Point"}
}