{
  "type": "Feature",
  "properties": {
    "iso:country": "GB",
    "wof:name": "FK3 0JR",
    "wof:placetype": "postalcode"
  },
  "geometry": {"coordinates":[-3.720133,56.000587],"type":"Point"}
}
