{
  "type": "Feature",
  "properties": {
    "date:inception_lower": "1994-05-01",
    "date:inception_upper": "1994-05-01",
    "iso:country": "GB",
    "wof:name": "FK3 0JR",
    "wof:placetype": "postalcode"
  },
  "geometry": {"coordinates":[-3.720133,56.000587],"type":"Point"}
}
