{
  "type": "Feature",
  "properties": {
    "iso:country": "GB",
    "wof:name": "LL65 2JF",
    "wof:placetype": "postalcode"
  },
  "geometry": {"coordinates":[-4.62726,53.307288],"type":"Point"}
}
