{
  "type": "Feature",
  "properties": {
    "iso:country":"GB",
    "wof:name":"B96 6DH",
    "wof:placetype":"postalcode"
},
  "geometry": {"coordinates":[-1.94057113109263,52.26222459201261],"type":"Point"}
}