{
  "type": "Feature",
  "properties": {
    "iso:country": "GB",
    "wof:name": "OL11 1EU",
    "wof:placetype": "postalcode"
  },
  "geometry": {"coordinates":[-2.15661,53.611495],"type":"Point"}
}
