{
  "type": "Feature",
  "properties": {
    "date:inception_lower": "2018-03-01",
    "date:inception_upper": "2018-03-01",
    "iso:country": "GB",
    "wof:name": "ME10 4FG",
    "wof:placetype": "postalcode"
  },
  "geometry": {"coordinates":[0.743548,51.338388],"type":"Point"}
}
