{
  "type": "Feature",
  "properties": {
    "iso:country":"GB",
    "wof:name":"TW4 7PH",
    "wof:placetype":"postalcode"
},
  "geometry": {"coordinates":[-0.39992113055607,51.47264346510978],"type":"Point"}
}