{
  "type": "Feature",
  "properties": {
    "iso:country":"GB",
    "wof:name":"TR3 6JE",
    "wof:placetype":"postalcode"
},
  "geometry": {"coordinates":[-5.08806212449208,50.22409153927796],"type":"Point"}
}