{
  "type": "Feature",
  "properties": {
    "iso:country":"GB",
    "wof:name":"PO9 2TL",
    "wof:placetype":"postalcode"
},
  "geometry": {"coordinates":[-0.96796588793854,50.84959331370018],"type":"Point"}
}