{
  "type": "Feature",
  "properties": {
    "iso:country":"GB",
    "wof:name":"NP12 1JG",
    "wof:placetype":"postalcode"
},
  "geometry": {"coordinates":[-3.19897824021417,51.67203409215295],"type":"Point"}
}