{
  "type": "Feature",
  "properties": {
    "date:inception_lower":"1999-06-01",
    "date:inception_upper":"1999-06-30",
    "iso:country":"GB",
    "wof:name":"NP12 1JG",
    "wof:placetype":"postalcode"
},
  "geometry": {"coordinates":[-3.198978,51.672034],"type":"Point"}
}