{
  "type": "Feature",
  "properties": {
    "iso:country":"GB",
    "wof:name":"EH11 3BZ",
    "wof:placetype":"postalcode"
},
  "geometry": {"coordinates":[-3.26070629967489,55.93546104711119],"type":"Point"}
}