{
  "type": "Feature",
  "properties": {
    "iso:country":"GB",
    "wof:name":"L36 0TD",
    "wof:placetype":"postalcode"
},
  "geometry": {"coordinates":[-2.82772251768243,53.40441394657162],"type":"Point"}
}