{
  "type": "Feature",
  "properties": {
    "iso:country":"GB",
    "wof:name":"PE2 5PX",
    "wof:placetype":"postalcode"
},
  "geometry": {"coordinates":[-0.27963306674298,52.54592921682259],"type":"Point"}
}