{
  "type": "Feature",
  "properties": {
    "iso:country":"GB",
    "wof:name":"BS20 6BP",
    "wof:placetype":"postalcode"
},
  "geometry": {"coordinates":[-2.76914506436159,51.48549247916209],"type":"Point"}
}