{
  "type": "Feature",
  "properties": {
    "iso:country": "GB",
    "wof:name": "L11 3DU",
    "wof:placetype": "postalcode"
  },
  "geometry": {"coordinates":[-2.922016,53.452901],"type":"Point"}
}
