{
  "type": "Feature",
  "properties": {
    "iso:country":"GB",
    "wof:name":"L11 3DU",
    "wof:placetype":"postalcode"
},
  "geometry": {"coordinates":[-2.92201572256595,53.45290089688022],"type":"Point"}
}