{
  "type": "Feature",
  "properties": {
    "iso:country": "GB",
    "wof:name": "TA24 8TL",
    "wof:placetype": "postalcode"
  },
  "geometry": {"coordinates":[-3.551224,51.20807],"type":"Point"}
}
