{
  "type": "Feature",
  "properties": {
    "iso:country":"GB",
    "wof:name":"AL4 8FB",
    "wof:placetype":"postalcode"
},
  "geometry": {"coordinates":[-0.30223633326548,51.80165061466676],"type":"Point"}
}