{
  "type": "Feature",
  "properties": {
    "iso:country": "GB",
    "wof:name": "GL51 8HU",
    "wof:placetype": "postalcode"
  },
  "geometry": {"coordinates":[-2.099552,51.90609],"type":"Point"}
}
