{
  "type": "Feature",
  "properties": {
    "iso:country":"GB",
    "wof:name":"GL51 8HU",
    "wof:placetype":"postalcode"
},
  "geometry": {"coordinates":[-2.09955203047716,51.90608981950763],"type":"Point"}
}