{
  "type": "Feature",
  "properties": {
    "iso:country":"GB",
    "wof:name":"KT10 9TY",
    "wof:placetype":"postalcode"
},
  "geometry": {"coordinates":[-0.35958938506225,51.36901527669092],"type":"Point"}
}