{
  "type": "Feature",
  "properties": {
    "date:inception_lower": "2006-08-01",
    "date:inception_upper": "2006-08-01",
    "iso:country": "GB",
    "wof:name": "PO9 1HN",
    "wof:placetype": "postalcode"
  },
  "geometry": {"coordinates":[-0.984238,50.850509],"type":"Point"}
}
