{
  "type": "Feature",
  "properties": {
    "iso:country":"GB",
    "wof:name":"PO9 1HN",
    "wof:placetype":"postalcode"
},
  "geometry": {"coordinates":[-0.98422845313029,50.85036545675688],"type":"Point"}
}