{
  "type": "Feature",
  "properties": {
    "date:inception_lower": "1980-01-01",
    "date:inception_upper": "1980-01-01",
    "iso:country": "GB",
    "wof:name": "CT15 7PL",
    "wof:placetype": "postalcode"
  },
  "geometry": {"coordinates":[1.236622,51.190602],"type":"Point"}
}
