{
  "type": "Feature",
  "properties": {
    "date:inception_lower":"1980-01-01",
    "date:inception_upper":"1980-01-31",
    "iso:country":"GB",
    "wof:name":"KA29 0DL",
    "wof:placetype":"postalcode"
},
  "geometry": {"coordinates":[-4.856083,55.75513],"type":"Point"}
}