{
  "type": "Feature",
  "properties": {
    "iso:country":"GB",
    "wof:name":"KA7 2SR",
    "wof:placetype":"postalcode"
},
  "geometry": {"coordinates":[-4.63070878770494,55.45161861222186],"type":"Point"}
}