{
  "type": "Feature",
  "properties": {
    "iso:country":"GB",
    "wof:name":"PL25 5HR",
    "wof:placetype":"postalcode"
},
  "geometry": {"coordinates":[-4.80008296815635,50.33664871024696],"type":"Point"}
}