{
  "type": "Feature",
  "properties": {
    "iso:country":"GB",
    "wof:name":"HA2 9RD",
    "wof:placetype":"postalcode"
},
  "geometry": {"coordinates":[-0.37942339848455,51.57317394594163],"type":"Point"}
}