{
  "type": "Feature",
  "properties": {
    "date:inception_lower":"1980-01-01",
    "date:inception_upper":"1980-01-31",
    "iso:country":"GB",
    "wof:name":"LA14 3TH",
    "wof:placetype":"postalcode"
},
  "geometry": {"coordinates":[-3.255404,54.12151],"type":"Point"}
}