{
  "type": "Feature",
  "properties": {
    "iso:country": "GB",
    "wof:name": "LA14 3TH",
    "wof:placetype": "postalcode"
  },
  "geometry": {"coordinates":[-3.255404,54.12151],"type":"Point"}
}
