{
  "type": "Feature",
  "properties": {
    "iso:country":"GB",
    "wof:name":"LA14 3TH",
    "wof:placetype":"postalcode"
},
  "geometry": {"coordinates":[-3.25540386311476,54.12150990790258],"type":"Point"}
}