{
  "type": "Feature",
  "properties": {
    "iso:country":"GB",
    "wof:name":"LL18 4BL",
    "wof:placetype":"postalcode"
},
  "geometry": {"coordinates":[-3.4723678681492,53.32195466240392],"type":"Point"}
}