{
  "type": "Feature",
  "properties": {
    "iso:country":"GB",
    "wof:name":"BD20 5QQ",
    "wof:placetype":"postalcode"
},
  "geometry": {"coordinates":[-1.87122739266829,53.8754913713182],"type":"Point"}
}