{
  "type": "Feature",
  "properties": {
    "iso:country": "GB",
    "wof:name": "BD20 5QQ",
    "wof:placetype": "postalcode"
  },
  "geometry": {"coordinates":[-1.871227,53.875491],"type":"Point"}
}
