{
  "type": "Feature",
  "properties": {
    "date:inception_lower":"2004-07-01",
    "date:inception_upper":"2004-07-31",
    "iso:country":"GB",
    "wof:name":"BD20 5QQ",
    "wof:placetype":"postalcode"
},
  "geometry": {"coordinates":[-1.871227,53.875491],"type":"Point"}
}