{
  "type": "Feature",
  "properties": {
    "iso:country":"GB",
    "wof:name":"RM20 2ZQ",
    "wof:placetype":"postalcode"
},
  "geometry": {"coordinates":[0.28315937408349,51.48767155278001],"type":"Point"}
}