{
  "type": "Feature",
  "properties": {
    "iso:country":"GB",
    "wof:name":"RG9 2BG",
    "wof:placetype":"postalcode"
},
  "geometry": {"coordinates":[-0.90454802711052,51.538544005223],"type":"Point"}
}