{
  "type": "Feature",
  "properties": {
    "date:inception_lower": "1980-01-01",
    "date:inception_upper": "1980-01-01",
    "iso:country": "GB",
    "wof:name": "RG9 2BG",
    "wof:placetype": "postalcode"
  },
  "geometry": {"coordinates":[-0.904548,51.538544],"type":"Point"}
}
