{
  "type": "Feature",
  "properties": {
    "iso:country": "GB",
    "wof:name": "RG9 2BG",
    "wof:placetype": "postalcode"
  },
  "geometry": {"coordinates":[-0.904548,51.538544],"type":"Point"}
}
