{
  "type": "Feature",
  "properties": {
    "iso:country":"GB",
    "wof:name":"PH2 9DA",
    "wof:placetype":"postalcode"
},
  "geometry": {"coordinates":[-3.53579849697689,56.32977591548707],"type":"Point"}
}