{
  "type": "Feature",
  "properties": {
    "date:inception_lower": "1980-01-01",
    "date:inception_upper": "1980-01-01",
    "iso:country": "GB",
    "wof:name": "PH2 9DA",
    "wof:placetype": "postalcode"
  },
  "geometry": {"coordinates":[-3.535798,56.329776],"type":"Point"}
}
