{
  "type": "Feature",
  "properties": {
    "iso:country":"GB",
    "wof:name":"W1S 4RP",
    "wof:placetype":"postalcode"
},
  "geometry": {"coordinates":[-0.14132451618688,51.50889120476101],"type":"Point"}
}