{
  "type": "Feature",
  "properties": {
    "iso:country":"GB",
    "wof:name":"CH63 9HS",
    "wof:placetype":"postalcode"
},
  "geometry": {"coordinates":[-2.99992747103255,53.33343995627605],"type":"Point"}
}