{
  "type": "Feature",
  "properties": {
    "iso:country":"GB",
    "wof:name":"WN7 4EY",
    "wof:placetype":"postalcode"
},
  "geometry": {"coordinates":[-2.521905234046,53.49598371677979],"type":"Point"}
}