{
  "type": "Feature",
  "properties": {
    "date:inception_lower":"2009-05-01",
    "date:inception_upper":"2009-05-31",
    "iso:country":"GB",
    "wof:name":"WN7 4EY",
    "wof:placetype":"postalcode"
},
  "geometry": {"coordinates":[-2.521905,53.495984],"type":"Point"}
}