{
  "type": "Feature",
  "properties": {
    "iso:country": "GB",
    "wof:name": "WN7 4EY",
    "wof:placetype": "postalcode"
  },
  "geometry": {"coordinates":[-2.521905,53.495984],"type":"Point"}
}
