{
  "type": "Feature",
  "properties": {
    "iso:country":"GB",
    "wof:name":"HA3 5NR",
    "wof:placetype":"postalcode"
},
  "geometry": {"coordinates":[-0.35225595160043,51.60135479288977],"type":"Point"}
}