{
  "type": "Feature",
  "properties": {
    "iso:country": "GB",
    "wof:name": "EX4 0AF",
    "wof:placetype": "postalcode"
  },
  "geometry": {"coordinates":[-3.471137,50.765936],"type":"Point"}
}
