{
  "type": "Feature",
  "properties": {
    "iso:country":"GB",
    "wof:name":"EX4 0AF",
    "wof:placetype":"postalcode"
},
  "geometry": {"coordinates":[-3.47113656156495,50.76593615154895],"type":"Point"}
}