{
  "type": "Feature",
  "properties": {
    "date:inception_lower": "1980-01-01",
    "date:inception_upper": "1980-01-01",
    "iso:country": "GB",
    "wof:name": "WV10 9TZ",
    "wof:placetype": "postalcode"
  },
  "geometry": {"coordinates":[-2.12162,52.612644],"type":"Point"}
}
