{
  "type": "Feature",
  "properties": {
    "iso:country":"GB",
    "wof:name":"DL4 2BQ",
    "wof:placetype":"postalcode"
},
  "geometry": {"coordinates":[-1.63129893660323,54.63233892509283],"type":"Point"}
}