{
  "type": "Feature",
  "properties": {
    "iso:country": "GB",
    "wof:name": "L37 2JW",
    "wof:placetype": "postalcode"
  },
  "geometry": {"coordinates":[-3.076669,53.55506],"type":"Point"}
}
