{
  "type": "Feature",
  "properties": {
    "date:inception_lower": "1980-01-01",
    "date:inception_upper": "1980-01-01",
    "iso:country": "GB",
    "wof:name": "L37 2JW",
    "wof:placetype": "postalcode"
  },
  "geometry": {"coordinates":[-3.076669,53.55506],"type":"Point"}
}
