{
  "type": "Feature",
  "properties": {
    "iso:country":"GB",
    "wof:name":"IV3 8GB",
    "wof:placetype":"postalcode"
},
  "geometry": {"coordinates":[-4.26344615552375,57.47122997170796],"type":"Point"}
}