{
  "type": "Feature",
  "properties": {
    "date:inception_lower":"2012-06-01",
    "date:inception_upper":"2012-06-30",
    "iso:country":"GB",
    "wof:name":"IV3 8GB",
    "wof:placetype":"postalcode"
},
  "geometry": {"coordinates":[-4.263446,57.47123],"type":"Point"}
}