{
  "type": "Feature",
  "properties": {
    "iso:country": "GB",
    "wof:name": "IV3 8GB",
    "wof:placetype": "postalcode"
  },
  "geometry": {"coordinates":[-4.263446,57.47123],"type":"Point"}
}
