{
  "type": "Feature",
  "properties": {
    "iso:country":"GB",
    "wof:name":"LE2 5WA",
    "wof:placetype":"postalcode"
},
  "geometry": {"coordinates":[-1.07942617536857,52.58922749081918],"type":"Point"}
}