{
  "type": "Feature",
  "properties": {
    "iso:country": "GB",
    "wof:name": "LE2 5WA",
    "wof:placetype": "postalcode"
  },
  "geometry": {"coordinates":[-1.079426,52.589227],"type":"Point"}
}
