{
  "type": "Feature",
  "properties": {
    "date:inception_lower": "1980-01-01",
    "date:inception_upper": "1980-01-01",
    "iso:country": "GB",
    "wof:name": "BR2 6AG",
    "wof:placetype": "postalcode"
  },
  "geometry": {"coordinates":[0.03062,51.352389],"type":"Point"}
}
