{
  "type": "Feature",
  "properties": {
    "iso:country":"GB",
    "wof:name":"BR2 6AG",
    "wof:placetype":"postalcode"
},
  "geometry": {"coordinates":[0.0306200983311,51.3523886951292],"type":"Point"}
}