{
  "type": "Feature",
  "properties": {
    "iso:country":"GB",
    "wof:name":"ST1 2JP",
    "wof:placetype":"postalcode"
},
  "geometry": {"coordinates":[-2.17430349784151,53.0283488656984],"type":"Point"}
}