{
  "type": "Feature",
  "properties": {
    "iso:country":"GB",
    "wof:name":"UB9 6PL",
    "wof:placetype":"postalcode"
},
  "geometry": {"coordinates":[-0.47886664251881,51.60421468320054],"type":"Point"}
}