{
  "type": "Feature",
  "properties": {
    "date:inception_lower": "1990-02-01",
    "date:inception_upper": "1990-02-01",
    "iso:country": "GB",
    "wof:name": "LS21 3NZ",
    "wof:placetype": "postalcode"
  },
  "geometry": {"coordinates":[-1.715666,53.899347],"type":"Point"}
}
