{
  "type": "Feature",
  "properties": {
    "iso:country":"GB",
    "wof:name":"LS21 3NZ",
    "wof:placetype":"postalcode"
},
  "geometry": {"coordinates":[-1.71566650228203,53.89934743416877],"type":"Point"}
}