{
  "type": "Feature",
  "properties": {
    "iso:country":"GB",
    "wof:name":"ME12 2EA",
    "wof:placetype":"postalcode"
},
  "geometry": {"coordinates":[0.79385854679626,51.42376338219609],"type":"Point"}
}