{
  "type": "Feature",
  "properties": {
    "iso:country":"GB",
    "wof:name":"NG22 9ED",
    "wof:placetype":"postalcode"
},
  "geometry": {"coordinates":[-1.02310298823286,53.23089859736496],"type":"Point"}
}