{
  "type": "Feature",
  "properties": {
    "iso:country":"GB",
    "wof:name":"SS9 4DS",
    "wof:placetype":"postalcode"
},
  "geometry": {"coordinates":[0.63563002947951,51.56883634885227],"type":"Point"}
}