{
  "type": "Feature",
  "properties": {
    "iso:country": "GB",
    "wof:name": "SS9 4DS",
    "wof:placetype": "postalcode"
  },
  "geometry": {"coordinates":[0.63563,51.568836],"type":"Point"}
}
