{
  "type": "Feature",
  "properties": {
    "date:inception_lower": "2016-02-01",
    "date:inception_upper": "2016-02-01",
    "iso:country": "GB",
    "wof:name": "WF10 9DD",
    "wof:placetype": "postalcode"
  },
  "geometry": {"coordinates":[-1.390333,53.716434],"type":"Point"}
}
