{
  "type": "Feature",
  "properties": {
    "iso:country": "GB",
    "wof:name": "WN8 6AL",
    "wof:placetype": "postalcode"
  },
  "geometry": {"coordinates":[-2.758251,53.547571],"type":"Point"}
}
