{
  "type": "Feature",
  "properties": {
    "iso:country":"GB",
    "wof:name":"WN8 6AL",
    "wof:placetype":"postalcode"
},
  "geometry": {"coordinates":[-2.7582514650362,53.54757057995566],"type":"Point"}
}