{
  "type": "Feature",
  "properties": {
    "iso:country": "GB",
    "wof:name": "NN9 6AY",
    "wof:placetype": "postalcode"
  },
  "geometry": {"coordinates":[-0.546415,52.316204],"type":"Point"}
}
