{
  "type": "Feature",
  "properties": {
    "iso:country":"GB",
    "wof:name":"BN25 1LY",
    "wof:placetype":"postalcode"
},
  "geometry": {"coordinates":[0.1028544990859,50.77183960961312],"type":"Point"}
}