{
  "type": "Feature",
  "properties": {
    "iso:country":"GB",
    "wof:name":"CF62 7BN",
    "wof:placetype":"postalcode"
},
  "geometry": {"coordinates":[-3.29178698978109,51.40863863692456],"type":"Point"}
}