{
  "type": "Feature",
  "properties": {
    "iso:country":"GB",
    "wof:name":"KT8 1PX",
    "wof:placetype":"postalcode"
},
  "geometry": {"coordinates":[-0.37086339062493,51.40675197673771],"type":"Point"}
}