{
  "type": "Feature",
  "properties": {
    "iso:country":"GB",
    "wof:name":"TN12 7NU",
    "wof:placetype":"postalcode"
},
  "geometry": {"coordinates":[0.3968927295593,51.15142028076528],"type":"Point"}
}