{
  "type": "Feature",
  "properties": {
    "iso:country": "GB",
    "wof:name": "TN12 7NU",
    "wof:placetype": "postalcode"
  },
  "geometry": {"coordinates":[0.396893,51.15142],"type":"Point"}
}
