{
  "type": "Feature",
  "properties": {
    "date:inception_lower": "1980-01-01",
    "date:inception_upper": "1980-01-01",
    "iso:country": "GB",
    "wof:name": "TN12 7NU",
    "wof:placetype": "postalcode"
  },
  "geometry": {"coordinates":[0.396893,51.15142],"type":"Point"}
}
