{
  "type": "Feature",
  "properties": {
    "iso:country": "GB",
    "wof:name": "WV4 6AY",
    "wof:placetype": "postalcode"
  },
  "geometry": {"coordinates":[-2.122444,52.555618],"type":"Point"}
}
