{
  "type": "Feature",
  "properties": {
    "iso:country":"GB",
    "wof:name":"NE32 3SB",
    "wof:placetype":"postalcode"
},
  "geometry": {"coordinates":[-1.47058202075428,54.97029475304399],"type":"Point"}
}