{
  "type": "Feature",
  "properties": {
    "iso:country":"GB",
    "wof:name":"AB38 7RB",
    "wof:placetype":"postalcode"
},
  "geometry": {"coordinates":[-3.27361747718108,57.48154734830072],"type":"Point"}
}