{
  "type": "Feature",
  "properties": {
    "iso:country":"GB",
    "wof:name":"BD16 1PF",
    "wof:placetype":"postalcode"
},
  "geometry": {"coordinates":[-1.82141663615665,53.83222295245574],"type":"Point"}
}