{
  "type": "Feature",
  "properties": {
    "date:inception_lower": "1985-10-01",
    "date:inception_upper": "1985-10-01",
    "iso:country": "GB",
    "wof:name": "DN14 9DE",
    "wof:placetype": "postalcode"
  },
  "geometry": {"coordinates":[-1.034373,53.69147],"type":"Point"}
}
