{
  "type": "Feature",
  "properties": {
    "iso:country": "GB",
    "wof:name": "NR18 0HF",
    "wof:placetype": "postalcode"
  },
  "geometry": {"coordinates":[1.130023,52.57969],"type":"Point"}
}
