{
  "type": "Feature",
  "properties": {
    "iso:country":"GB",
    "wof:name":"TN39 4DP",
    "wof:placetype":"postalcode"
},
  "geometry": {"coordinates":[0.46392196136254,50.85159835902883],"type":"Point"}
}