{
  "type": "Feature",
  "properties": {
    "iso:country":"GB",
    "wof:name":"SN14 6QR",
    "wof:placetype":"postalcode"
},
  "geometry": {"coordinates":[-2.24053358978032,51.55450358032023],"type":"Point"}
}