{
  "type": "Feature",
  "properties": {
    "iso:country": "GB",
    "wof:name": "SN14 6QR",
    "wof:placetype": "postalcode"
  },
  "geometry": {"coordinates":[-2.240534,51.554504],"type":"Point"}
}
