{
  "type": "Feature",
  "properties": {
    "date:inception_lower":"1997-06-01",
    "date:inception_upper":"1997-06-30",
    "iso:country":"GB",
    "wof:name":"SN14 6QR",
    "wof:placetype":"postalcode"
},
  "geometry": {"coordinates":[-2.240534,51.554504],"type":"Point"}
}