{
  "type": "Feature",
  "properties": {
    "iso:country":"GB",
    "wof:name":"NE63 0AH",
    "wof:placetype":"postalcode"
},
  "geometry": {"coordinates":[-1.56500650169271,55.18008170673878],"type":"Point"}
}