{
  "type": "Feature",
  "properties": {
    "iso:country": "GB",
    "wof:name": "NE63 0AH",
    "wof:placetype": "postalcode"
  },
  "geometry": {"coordinates":[-1.565006,55.180082],"type":"Point"}
}
