{
  "type": "Feature",
  "properties": {
    "date:inception_lower": "2003-11-01",
    "date:inception_upper": "2003-11-01",
    "iso:country": "GB",
    "wof:name": "NE63 0AH",
    "wof:placetype": "postalcode"
  },
  "geometry": {"coordinates":[-1.564773,55.179834],"type":"Point"}
}
