{
  "type": "Feature",
  "properties": {
    "date:inception_lower":"1980-01-01",
    "date:inception_upper":"1980-01-31",
    "iso:country":"GB",
    "wof:name":"LE17 4LD",
    "wof:placetype":"postalcode"
},
  "geometry": {"coordinates":[-1.159572,52.459844],"type":"Point"}
}