{
  "type": "Feature",
  "properties": {
    "iso:country": "GB",
    "wof:name": "LE17 4LD",
    "wof:placetype": "postalcode"
  },
  "geometry": {"coordinates":[-1.159572,52.459844],"type":"Point"}
}
