{
  "type": "Feature",
  "properties": {
    "iso:country":"GB",
    "wof:name":"LE17 4LD",
    "wof:placetype":"postalcode"
},
  "geometry": {"coordinates":[-1.15957162905429,52.45984373939024],"type":"Point"}
}