{
  "type": "Feature",
  "properties": {
    "iso:country":"GB",
    "wof:name":"SY2 5EP",
    "wof:placetype":"postalcode"
},
  "geometry": {"coordinates":[-2.73405196109693,52.70552549937211],"type":"Point"}
}