{
  "type": "Feature",
  "properties": {
    "iso:country": "GB",
    "wof:name": "HU12 8HT",
    "wof:placetype": "postalcode"
  },
  "geometry": {"coordinates":[-0.192501,53.737505],"type":"Point"}
}
