{
  "type": "Feature",
  "properties": {
    "date:inception_lower":"1980-01-01",
    "date:inception_upper":"1980-01-31",
    "iso:country":"GB",
    "wof:name":"HU12 8HT",
    "wof:placetype":"postalcode"
},
  "geometry": {"coordinates":[-0.192501,53.737505],"type":"Point"}
}