{
  "type": "Feature",
  "properties": {
    "iso:country":"GB",
    "wof:name":"HU12 8HT",
    "wof:placetype":"postalcode"
},
  "geometry": {"coordinates":[-0.1925010649075,53.73750465086039],"type":"Point"}
}