{
  "type": "Feature",
  "properties": {
    "date:inception_lower": "1986-07-01",
    "date:inception_upper": "1986-07-01",
    "iso:country": "GB",
    "wof:name": "HP13 7EH",
    "wof:placetype": "postalcode"
  },
  "geometry": {"coordinates":[-0.716553,51.621027],"type":"Point"}
}
