{
  "type": "Feature",
  "properties": {
    "iso:country": "GB",
    "wof:name": "MK40 4TR",
    "wof:placetype": "postalcode"
  },
  "geometry": {"coordinates":[-0.511833,52.126037],"type":"Point"}
}
