{
  "type": "Feature",
  "properties": {
    "iso:country":"GB",
    "wof:name":"YO30 6RE",
    "wof:placetype":"postalcode"
},
  "geometry": {"coordinates":[-1.09265615420667,53.9835942269295],"type":"Point"}
}