{
  "type": "Feature",
  "properties": {
    "iso:country":"GB",
    "wof:name":"HR2 0QG",
    "wof:placetype":"postalcode"
},
  "geometry": {"coordinates":[-2.97617425923517,52.0068637068687],"type":"Point"}
}