{
  "type": "Feature",
  "properties": {
    "iso:country": "GB",
    "wof:name": "PL14 5LZ",
    "wof:placetype": "postalcode"
  },
  "geometry": {"coordinates":[-4.468824,50.487616],"type":"Point"}
}
