{
  "type": "Feature",
  "properties": {
    "iso:country":"GB",
    "wof:name":"CH5 4EB",
    "wof:placetype":"postalcode"
},
  "geometry": {"coordinates":[-3.05470631648302,53.21759208123603],"type":"Point"}
}