{
  "type": "Feature",
  "properties": {
    "date:inception_lower": "1980-01-01",
    "date:inception_upper": "1980-01-01",
    "iso:country": "GB",
    "wof:name": "CH5 4EB",
    "wof:placetype": "postalcode"
  },
  "geometry": {"coordinates":[-3.054807,53.217499],"type":"Point"}
}
