{
  "type": "Feature",
  "properties": {
    "iso:country": "GB",
    "wof:name": "CO11 2EH",
    "wof:placetype": "postalcode"
  },
  "geometry": {"coordinates":[1.04511,51.938117],"type":"Point"}
}
