{
  "type": "Feature",
  "properties": {
    "iso:country":"GB",
    "wof:name":"CO11 2EH",
    "wof:placetype":"postalcode"
},
  "geometry": {"coordinates":[1.04511012934529,51.93811667537513],"type":"Point"}
}