{
  "type": "Feature",
  "properties": {
    "iso:country":"GB",
    "wof:name":"CF44 6AQ",
    "wof:placetype":"postalcode"
},
  "geometry": {"coordinates":[-3.41312747655808,51.69024342808918],"type":"Point"}
}