{
  "type": "Feature",
  "properties": {
    "iso:country": "GB",
    "wof:name": "CT11 8JH",
    "wof:placetype": "postalcode"
  },
  "geometry": {"coordinates":[1.424423,51.334693],"type":"Point"}
}
