{
  "type": "Feature",
  "properties": {
    "date:inception_lower":"1980-01-01",
    "date:inception_upper":"1980-01-31",
    "iso:country":"GB",
    "wof:name":"CT11 8JH",
    "wof:placetype":"postalcode"
},
  "geometry": {"coordinates":[1.424423,51.334693],"type":"Point"}
}