{
  "type": "Feature",
  "properties": {
    "iso:country":"GB",
    "wof:name":"CT11 8JH",
    "wof:placetype":"postalcode"
},
  "geometry": {"coordinates":[1.4244230445183,51.3346926170678],"type":"Point"}
}