{
  "type": "Feature",
  "properties": {
    "iso:country":"GB",
    "wof:name":"SO18 2LY",
    "wof:placetype":"postalcode"
},
  "geometry": {"coordinates":[-1.36900973269094,50.93887686457355],"type":"Point"}
}