{
  "type": "Feature",
  "properties": {
    "date:inception_lower": "2021-07-01",
    "date:inception_upper": "2021-07-01",
    "iso:country": "GB",
    "wof:name": "NE65 9FN",
    "wof:placetype": "postalcode"
  },
  "geometry": {"coordinates":[-1.737382,55.326695],"type":"Point"}
}
