{
  "type": "Feature",
  "properties": {
    "iso:country":"GB",
    "wof:name":"PL6 7BP",
    "wof:placetype":"postalcode"
},
  "geometry": {"coordinates":[-4.11693861932386,50.43918242706386],"type":"Point"}
}