{
  "type": "Feature",
  "properties": {
    "iso:country": "GB",
    "wof:name": "PL6 7BP",
    "wof:placetype": "postalcode"
  },
  "geometry": {"coordinates":[-4.115193,50.44172],"type":"Point"}
}
