{
  "type": "Feature",
  "properties": {
    "date:inception_lower":"2005-03-01",
    "date:inception_upper":"2005-03-31",
    "iso:country":"GB",
    "wof:name":"AL10 1AL",
    "wof:placetype":"postalcode"
},
  "geometry": {"coordinates":[-0.226254,51.764264],"type":"Point"}
}