{
  "type": "Feature",
  "properties": {
    "iso:country":"GB",
    "wof:name":"PL31 1QY",
    "wof:placetype":"postalcode"
},
  "geometry": {"coordinates":[-4.74013388208545,50.4689564898262],"type":"Point"}
}