{
  "type": "Feature",
  "properties": {
    "date:inception_lower":"2001-06-01",
    "date:inception_upper":"2001-06-30",
    "iso:country":"GB",
    "wof:name":"PL31 1QY",
    "wof:placetype":"postalcode"
},
  "geometry": {"coordinates":[-4.740134,50.468956],"type":"Point"}
}