{
  "type": "Feature",
  "properties": {
    "iso:country":"GB",
    "wof:name":"EH6 8RF",
    "wof:placetype":"postalcode"
},
  "geometry": {"coordinates":[-3.17512440361322,55.96444970207114],"type":"Point"}
}