{
  "type": "Feature",
  "properties": {
    "iso:country":"GB",
    "wof:name":"IP31 3AZ",
    "wof:placetype":"postalcode"
},
  "geometry": {"coordinates":[0.93566092823793,52.3030093706268],"type":"Point"}
}