{
  "type": "Feature",
  "properties": {
    "date:inception_lower": "1980-01-01",
    "date:inception_upper": "1980-01-01",
    "iso:country": "GB",
    "wof:name": "IP31 3AZ",
    "wof:placetype": "postalcode"
  },
  "geometry": {"coordinates":[0.935722,52.303036],"type":"Point"}
}
