{
  "type": "Feature",
  "properties": {
    "iso:country":"GB",
    "wof:name":"E7 8AY",
    "wof:placetype":"postalcode"
},
  "geometry": {"coordinates":[0.04393633470256,51.54901874130847],"type":"Point"}
}