{
  "type": "Feature",
  "properties": {
    "iso:country":"GB",
    "wof:name":"GU9 8QL",
    "wof:placetype":"postalcode"
},
  "geometry": {"coordinates":[-0.80617196111042,51.20689134132908],"type":"Point"}
}