{
  "type": "Feature",
  "properties": {
    "date:inception_lower":"2009-06-01",
    "date:inception_upper":"2009-06-30",
    "iso:country":"GB",
    "wof:name":"CT1 2FR",
    "wof:placetype":"postalcode"
},
  "geometry": {"coordinates":[1.073503,51.277722],"type":"Point"}
}