{
  "type": "Feature",
  "properties": {
    "date:inception_lower": "1991-09-01",
    "date:inception_upper": "1991-09-01",
    "iso:country": "GB",
    "wof:name": "CA28 6SP",
    "wof:placetype": "postalcode"
  },
  "geometry": {"coordinates":[-3.577901,54.550982],"type":"Point"}
}
