{
  "type": "Feature",
  "properties": {
    "iso:country": "GB",
    "wof:name": "DT3 6AG",
    "wof:placetype": "postalcode"
  },
  "geometry": {"coordinates":[-2.448603,50.65163],"type":"Point"}
}
