{
  "type": "Feature",
  "properties": {
    "iso:country": "GB",
    "wof:name": "EH22 4DS",
    "wof:placetype": "postalcode"
  },
  "geometry": {"coordinates":[-3.049155,55.876012],"type":"Point"}
}
