{
  "type": "Feature",
  "properties": {
    "iso:country":"GB",
    "wof:name":"W1G 6NU",
    "wof:placetype":"postalcode"
},
  "geometry": {"coordinates":[-0.15115344128483,51.52026019547566],"type":"Point"}
}