{
  "type": "Feature",
  "properties": {
    "iso:country":"GB",
    "wof:name":"SE19 1HT",
    "wof:placetype":"postalcode"
},
  "geometry": {"coordinates":[-0.08539528788737,51.41983667648836],"type":"Point"}
}