{
  "type": "Feature",
  "properties": {
    "iso:country": "GB",
    "wof:name": "DG8 8EQ",
    "wof:placetype": "postalcode"
  },
  "geometry": {"coordinates":[-4.428832,54.791354],"type":"Point"}
}
