{
  "type": "Feature",
  "properties": {
    "iso:country":"GB",
    "wof:name":"DG8 8EQ",
    "wof:placetype":"postalcode"
},
  "geometry": {"coordinates":[-4.42883177070212,54.79135360643165],"type":"Point"}
}