{
  "type": "Feature",
  "properties": {
    "iso:country":"GB",
    "wof:name":"RG4 6RT",
    "wof:placetype":"postalcode"
},
  "geometry": {"coordinates":[-0.95797388579821,51.48467525323727],"type":"Point"}
}