{
  "type": "Feature",
  "properties": {
    "iso:country": "GB",
    "wof:name": "S10 5QA",
    "wof:placetype": "postalcode"
  },
  "geometry": {"coordinates":[-1.52482,53.381405],"type":"Point"}
}
