{
  "type": "Feature",
  "properties": {
    "iso:country":"GB",
    "wof:name":"S10 5QA",
    "wof:placetype":"postalcode"
},
  "geometry": {"coordinates":[-1.52507594785818,53.38137057736922],"type":"Point"}
}