{
  "type": "Feature",
  "properties": {
    "iso:country":"GB",
    "wof:name":"LS7 1SJ",
    "wof:placetype":"postalcode"
},
  "geometry": {"coordinates":[-1.53840203529609,53.80795588388868],"type":"Point"}
}