{
  "type": "Feature",
  "properties": {
    "iso:country":"GB",
    "wof:name":"HP7 9JB",
    "wof:placetype":"postalcode"
},
  "geometry": {"coordinates":[-0.58942690728104,51.67062439867581],"type":"Point"}
}