{
  "type": "Feature",
  "properties": {
    "iso:country": "GB",
    "wof:name": "HP7 9JB",
    "wof:placetype": "postalcode"
  },
  "geometry": {"coordinates":[-0.589427,51.670624],"type":"Point"}
}
