{
  "type": "Feature",
  "properties": {
    "iso:country":"GB",
    "wof:name":"RG8 8QQ",
    "wof:placetype":"postalcode"
},
  "geometry": {"coordinates":[-1.14338020738134,51.47094368742448],"type":"Point"}
}