{
  "type": "Feature",
  "properties": {
    "date:inception_lower": "1986-04-01",
    "date:inception_upper": "1986-04-01",
    "iso:country": "GB",
    "wof:name": "RG8 8QQ",
    "wof:placetype": "postalcode"
  },
  "geometry": {"coordinates":[-1.14338,51.470944],"type":"Point"}
}
