{
  "type": "Feature",
  "properties": {
    "date:inception_lower": "1980-01-01",
    "date:inception_upper": "1980-01-01",
    "iso:country": "GB",
    "wof:name": "G12 0XX",
    "wof:placetype": "postalcode"
  },
  "geometry": {"coordinates":[-4.316319,55.884916],"type":"Point"}
}
