{
  "type": "Feature",
  "properties": {
    "date:inception_lower":"1980-01-01",
    "date:inception_upper":"1980-01-31",
    "iso:country":"GB",
    "wof:name":"NR6 5BL",
    "wof:placetype":"postalcode"
},
  "geometry": {"coordinates":[1.249847,52.66286],"type":"Point"}
}