{
  "type": "Feature",
  "properties": {
    "iso:country":"GB",
    "wof:name":"GL54 3LS",
    "wof:placetype":"postalcode"
},
  "geometry": {"coordinates":[-1.84172644159646,51.83313683953057],"type":"Point"}
}