{
  "type": "Feature",
  "properties": {
    "iso:country": "GB",
    "wof:name": "TA7 8DZ",
    "wof:placetype": "postalcode"
  },
  "geometry": {"coordinates":[-2.937534,51.167824],"type":"Point"}
}
