{
  "type": "Feature",
  "properties": {
    "iso:country":"GB",
    "wof:name":"LN6 8QF",
    "wof:placetype":"postalcode"
},
  "geometry": {"coordinates":[-0.59490022565185,53.18987992881735],"type":"Point"}
}