{
  "type": "Feature",
  "properties": {
    "iso:country": "GB",
    "wof:name": "CB7 5FA",
    "wof:placetype": "postalcode"
  },
  "geometry": {"coordinates":[0.271486,52.389214],"type":"Point"}
}
