{
  "type": "Feature",
  "properties": {
    "iso:country":"GB",
    "wof:name":"CB7 5FA",
    "wof:placetype":"postalcode"
},
  "geometry": {"coordinates":[0.27148615547692,52.38921442447162],"type":"Point"}
}