{
  "type": "Feature",
  "properties": {
    "iso:country":"GB",
    "wof:name":"BN11 3SA",
    "wof:placetype":"postalcode"
},
  "geometry": {"coordinates":[-0.38057027051461,50.80829696868721],"type":"Point"}
}