{
  "type": "Feature",
  "properties": {
    "date:inception_lower":"1980-01-01",
    "date:inception_upper":"1980-01-31",
    "iso:country":"GB",
    "wof:name":"BB5 6HN",
    "wof:placetype":"postalcode"
},
  "geometry": {"coordinates":[-2.348501,53.766146],"type":"Point"}
}