{
  "type": "Feature",
  "properties": {
    "iso:country":"GB",
    "wof:name":"BB5 6HN",
    "wof:placetype":"postalcode"
},
  "geometry": {"coordinates":[-2.34850087515784,53.76614625749549],"type":"Point"}
}