{
  "type": "Feature",
  "properties": {
    "iso:country":"GB",
    "wof:name":"LS25 2LS",
    "wof:placetype":"postalcode"
},
  "geometry": {"coordinates":[-1.36969986918115,53.79211529976966],"type":"Point"}
}