{
  "type": "Feature",
  "properties": {
    "date:inception_lower": "2018-06-01",
    "date:inception_upper": "2018-06-01",
    "iso:country": "GB",
    "wof:name": "CB24 1AW",
    "wof:placetype": "postalcode"
  },
  "geometry": {"coordinates":[0.052643,52.287285],"type":"Point"}
}
