{
  "type": "Feature",
  "properties": {
    "iso:country": "GB",
    "wof:name": "CW8 1RU",
    "wof:placetype": "postalcode"
  },
  "geometry": {"coordinates":[-2.555,53.245883],"type":"Point"}
}
