{
  "type": "Feature",
  "properties": {
    "date:inception_lower": "1994-12-01",
    "date:inception_upper": "1994-12-01",
    "iso:country": "GB",
    "wof:name": "SO45 4QJ",
    "wof:placetype": "postalcode"
  },
  "geometry": {"coordinates":[-1.411898,50.849491],"type":"Point"}
}
