{
  "type": "Feature",
  "properties": {
    "iso:country": "GB",
    "wof:name": "DD5 1HJ",
    "wof:placetype": "postalcode"
  },
  "geometry": {"coordinates":[-2.878795,56.46623],"type":"Point"}
}
