{
  "type": "Feature",
  "properties": {
    "iso:country":"GB",
    "wof:name":"DD5 1HJ",
    "wof:placetype":"postalcode"
},
  "geometry": {"coordinates":[-2.87879524452818,56.46622953434044],"type":"Point"}
}