{
  "type": "Feature",
  "properties": {
    "iso:country": "GB",
    "wof:name": "OL16 2NE",
    "wof:placetype": "postalcode"
  },
  "geometry": {"coordinates":[-2.146613,53.618339],"type":"Point"}
}
