{
  "type": "Feature",
  "properties": {
    "date:inception_lower": "2016-07-01",
    "date:inception_upper": "2016-07-01",
    "iso:country": "GB",
    "wof:name": "OL16 2NE",
    "wof:placetype": "postalcode"
  },
  "geometry": {"coordinates":[-2.146613,53.618339],"type":"Point"}
}
