{
  "type": "Feature",
  "properties": {
    "iso:country":"GB",
    "wof:name":"CF83 8FU",
    "wof:placetype":"postalcode"
},
  "geometry": {"coordinates":[-3.1790317078002,51.59610340616825],"type":"Point"}
}