{
  "type": "Feature",
  "properties": {
    "date:inception_lower": "1980-01-01",
    "date:inception_upper": "1980-01-01",
    "iso:country": "GB",
    "wof:name": "NE41 8HT",
    "wof:placetype": "postalcode"
  },
  "geometry": {"coordinates":[-1.817384,54.972792],"type":"Point"}
}
