{
  "type": "Feature",
  "properties": {
    "iso:country": "GB",
    "wof:name": "BH21 1NA",
    "wof:placetype": "postalcode"
  },
  "geometry": {"coordinates":[-1.994825,50.803032],"type":"Point"}
}
