{
  "type": "Feature",
  "properties": {
    "iso:country":"GB",
    "wof:name":"SO45 4EY",
    "wof:placetype":"postalcode"
},
  "geometry": {"coordinates":[-1.41239284145578,50.86062566637909],"type":"Point"}
}