{
  "type": "Feature",
  "properties": {
    "iso:country": "GB",
    "wof:name": "G23 5HZ",
    "wof:placetype": "postalcode"
  },
  "geometry": {"coordinates":[-4.294173,55.904987],"type":"Point"}
}
