{
  "type": "Feature",
  "properties": {
    "iso:country":"GB",
    "wof:name":"BH20 7BJ",
    "wof:placetype":"postalcode"
},
  "geometry": {"coordinates":[-2.09780565588165,50.70704826902655],"type":"Point"}
}