{
  "type": "Feature",
  "properties": {
    "date:inception_lower": "2006-07-01",
    "date:inception_upper": "2006-07-01",
    "iso:country": "GB",
    "wof:name": "OX25 6EP",
    "wof:placetype": "postalcode"
  },
  "geometry": {"coordinates":[-1.122516,51.899932],"type":"Point"}
}
