{
  "type": "Feature",
  "properties": {
    "iso:country":"GB",
    "wof:name":"CH49 4QD",
    "wof:placetype":"postalcode"
},
  "geometry": {"coordinates":[-3.12168284774325,53.38938411499647],"type":"Point"}
}