{
  "type": "Feature",
  "properties": {
    "date:inception_lower":"1984-10-01",
    "date:inception_upper":"1984-10-31",
    "iso:country":"GB",
    "wof:name":"L4 5XL",
    "wof:placetype":"postalcode"
},
  "geometry": {"coordinates":[-2.96364,53.439664],"type":"Point"}
}