{
  "type": "Feature",
  "properties": {
    "iso:country": "GB",
    "wof:name": "L4 5XL",
    "wof:placetype": "postalcode"
  },
  "geometry": {"coordinates":[-2.96364,53.439664],"type":"Point"}
}
