{
  "type": "Feature",
  "properties": {
    "iso:country": "GB",
    "wof:name": "BA3 3EH",
    "wof:placetype": "postalcode"
  },
  "geometry": {"coordinates":[-2.458654,51.283996],"type":"Point"}
}
