{
  "type": "Feature",
  "properties": {
    "iso:country":"GB",
    "wof:name":"BA3 3EH",
    "wof:placetype":"postalcode"
},
  "geometry": {"coordinates":[-2.45865372199376,51.28399581423601],"type":"Point"}
}