{
  "type": "Feature",
  "properties": {
    "iso:country":"GB",
    "wof:name":"PO13 9XS",
    "wof:placetype":"postalcode"
},
  "geometry": {"coordinates":[-1.21231040609133,50.80908836003438],"type":"Point"}
}