{
  "type": "Feature",
  "properties": {
    "iso:country": "GB",
    "wof:name": "PO13 9XS",
    "wof:placetype": "postalcode"
  },
  "geometry": {"coordinates":[-1.21231,50.809088],"type":"Point"}
}
