{
  "type": "Feature",
  "properties": {
    "iso:country":"GB",
    "wof:name":"NE40 4BT",
    "wof:placetype":"postalcode"
},
  "geometry": {"coordinates":[-1.78942362640417,54.9513145546041],"type":"Point"}
}