{
  "type": "Feature",
  "properties": {
    "iso:country":"GB",
    "wof:name":"S72 7ER",
    "wof:placetype":"postalcode"
},
  "geometry": {"coordinates":[-1.37778565734911,53.57975542016622],"type":"Point"}
}