{
  "type": "Feature",
  "properties": {
    "iso:country":"GB",
    "wof:name":"NG10 5HG",
    "wof:placetype":"postalcode"
},
  "geometry": {"coordinates":[-1.30333911973911,52.92075918790195],"type":"Point"}
}