{
  "type": "Feature",
  "properties": {
    "iso:country": "GB",
    "wof:name": "NG10 5HG",
    "wof:placetype": "postalcode"
  },
  "geometry": {"coordinates":[-1.303339,52.920759],"type":"Point"}
}
