{
  "type": "Feature",
  "properties": {
    "iso:country":"GB",
    "wof:name":"LL12 7BG",
    "wof:placetype":"postalcode"
},
  "geometry": {"coordinates":[-2.98310883705736,53.05612683890237],"type":"Point"}
}