{
  "type": "Feature",
  "properties": {
    "iso:country": "GB",
    "wof:name": "E14 2EB",
    "wof:placetype": "postalcode"
  },
  "geometry": {"coordinates":[-0.001903,51.509153],"type":"Point"}
}
