{
  "type": "Feature",
  "properties": {
    "iso:country":"GB",
    "wof:name":"E1 1HD",
    "wof:placetype":"postalcode"
},
  "geometry": {"coordinates":[-0.06812526580869,51.51587357844996],"type":"Point"}
}