{
  "type": "Feature",
  "properties": {
    "iso:country":"GB",
    "wof:name":"SG8 8ED",
    "wof:placetype":"postalcode"
},
  "geometry": {"coordinates":[0.01431812893372,51.99840161307296],"type":"Point"}
}