{
  "type": "Feature",
  "properties": {
    "iso:country": "GB",
    "wof:name": "SG8 8ED",
    "wof:placetype": "postalcode"
  },
  "geometry": {"coordinates":[0.014318,51.998402],"type":"Point"}
}
