{
  "type": "Feature",
  "properties": {
    "date:inception_lower":"2004-05-01",
    "date:inception_upper":"2004-05-31",
    "iso:country":"GB",
    "wof:name":"BH24 1JZ",
    "wof:placetype":"postalcode"
},
  "geometry": {"coordinates":[-1.790143,50.846115],"type":"Point"}
}