{
  "type": "Feature",
  "properties": {
    "iso:country":"GB",
    "wof:name":"BH24 1JZ",
    "wof:placetype":"postalcode"
},
  "geometry": {"coordinates":[-1.79014342636797,50.84611549927059],"type":"Point"}
}