{
  "type": "Feature",
  "properties": {
    "iso:country":"GB",
    "wof:name":"WA4 5SB",
    "wof:placetype":"postalcode"
},
  "geometry": {"coordinates":[-2.58767424795574,53.3543047409175],"type":"Point"}
}