{
  "type": "Feature",
  "properties": {
    "date:inception_lower":"2003-02-01",
    "date:inception_upper":"2003-02-28",
    "iso:country":"GB",
    "wof:name":"WA4 5SB",
    "wof:placetype":"postalcode"
},
  "geometry": {"coordinates":[-2.587674,53.354305],"type":"Point"}
}