{
  "type": "Feature",
  "properties": {
    "iso:country": "GB",
    "wof:name": "WA4 5SB",
    "wof:placetype": "postalcode"
  },
  "geometry": {"coordinates":[-2.587674,53.354305],"type":"Point"}
}
