{
  "type": "Feature",
  "properties": {
    "iso:country":"GB",
    "wof:name":"OX14 1BN",
    "wof:placetype":"postalcode"
},
  "geometry": {"coordinates":[-1.29292985685252,51.67902372902695],"type":"Point"}
}