{
  "type": "Feature",
  "properties": {
    "iso:country":"GB",
    "wof:name":"SO32 2QH",
    "wof:placetype":"postalcode"
},
  "geometry": {"coordinates":[-1.18622202106821,50.94797107199575],"type":"Point"}
}