{
  "type": "Feature",
  "properties": {
    "date:inception_lower": "2024-04-01",
    "date:inception_upper": "2024-04-01",
    "iso:country": "GB",
    "wof:name": "GL3 4XH",
    "wof:placetype": "postalcode"
  },
  "geometry": {"coordinates":[-2.147154,51.849161],"type":"Point"}
}
