{
  "type": "Feature",
  "properties": {
    "iso:country":"GB",
    "wof:name":"BA3 3NX",
    "wof:placetype":"postalcode"
},
  "geometry": {"coordinates":[-2.4398174467443,51.29047931158978],"type":"Point"}
}