{
  "type": "Feature",
  "properties": {
    "date:inception_lower":"1980-01-01",
    "date:inception_upper":"1980-01-31",
    "iso:country":"GB",
    "wof:name":"M23 0DB",
    "wof:placetype":"postalcode"
},
  "geometry": {"coordinates":[-2.273163,53.410135],"type":"Point"}
}