{
  "type": "Feature",
  "properties": {
    "iso:country":"GB",
    "wof:name":"M23 0DB",
    "wof:placetype":"postalcode"
},
  "geometry": {"coordinates":[-2.27316312530311,53.41013533183927],"type":"Point"}
}