{
  "type": "Feature",
  "properties": {
    "date:inception_lower":"2017-01-01",
    "date:inception_upper":"2017-01-31",
    "iso:country":"GB",
    "wof:name":"B74 2HN",
    "wof:placetype":"postalcode"
},
  "geometry": {"coordinates":[-1.880517,52.569223],"type":"Point"}
}