{
  "type": "Feature",
  "properties": {
    "iso:country": "GB",
    "wof:name": "B74 2HN",
    "wof:placetype": "postalcode"
  },
  "geometry": {"coordinates":[-1.880517,52.569223],"type":"Point"}
}
