{
  "type": "Feature",
  "properties": {
    "iso:country": "GB",
    "wof:name": "DL12 9RA",
    "wof:placetype": "postalcode"
  },
  "geometry": {"coordinates":[-1.934726,54.536652],"type":"Point"}
}
