{
  "type": "Feature",
  "properties": {
    "date:inception_lower": "1980-01-01",
    "date:inception_upper": "1980-01-01",
    "iso:country": "GB",
    "wof:name": "DL12 9RA",
    "wof:placetype": "postalcode"
  },
  "geometry": {"coordinates":[-1.934726,54.536652],"type":"Point"}
}
