{
  "type": "Feature",
  "properties": {
    "iso:country":"GB",
    "wof:name":"WN6 0DB",
    "wof:placetype":"postalcode"
},
  "geometry": {"coordinates":[-2.65731536715719,53.58466136451536],"type":"Point"}
}