{
  "type": "Feature",
  "properties": {
    "iso:country": "GB",
    "wof:name": "SM1 2JQ",
    "wof:placetype": "postalcode"
  },
  "geometry": {"coordinates":[-0.210672,51.367033],"type":"Point"}
}
