{
  "type": "Feature",
  "properties": {
    "date:inception_lower": "1980-01-01",
    "date:inception_upper": "1980-01-01",
    "iso:country": "GB",
    "wof:name": "SM1 2JQ",
    "wof:placetype": "postalcode"
  },
  "geometry": {"coordinates":[-0.210672,51.367033],"type":"Point"}
}
