{
  "type": "Feature",
  "properties": {
    "iso:country":"GB",
    "wof:name":"SM1 2JQ",
    "wof:placetype":"postalcode"
},
  "geometry": {"coordinates":[-0.21067241475956,51.3670333837511],"type":"Point"}
}