{
  "type": "Feature",
  "properties": {
    "iso:country":"GB",
    "wof:name":"CR7 8FL",
    "wof:placetype":"postalcode"
},
  "geometry": {"coordinates":[-0.10194881828895,51.40076265443528],"type":"Point"}
}