{
  "type": "Feature",
  "properties": {
    "iso:country":"GB",
    "wof:name":"SL7 3RR",
    "wof:placetype":"postalcode"
},
  "geometry": {"coordinates":[-0.74097554710651,51.58620538423208],"type":"Point"}
}