{
  "type": "Feature",
  "properties": {
    "iso:country":"GB",
    "wof:name":"M3 1SX",
    "wof:placetype":"postalcode"
},
  "geometry": {"coordinates":[-2.24470791591947,53.48460396610258],"type":"Point"}
}