{
  "type": "Feature",
  "properties": {
    "iso:country": "GB",
    "wof:name": "DH9 6DX",
    "wof:placetype": "postalcode"
  },
  "geometry": {"coordinates":[-1.661509,54.853839],"type":"Point"}
}
