{
  "type": "Feature",
  "properties": {
    "iso:country": "GB",
    "wof:name": "S11 8NR",
    "wof:placetype": "postalcode"
  },
  "geometry": {"coordinates":[-1.491577,53.369161],"type":"Point"}
}
