{
  "type": "Feature",
  "properties": {
    "date:inception_lower": "1980-01-01",
    "date:inception_upper": "1980-01-01",
    "iso:country": "GB",
    "wof:name": "S11 8NR",
    "wof:placetype": "postalcode"
  },
  "geometry": {"coordinates":[-1.491577,53.369161],"type":"Point"}
}
