{
  "type": "Feature",
  "properties": {
    "iso:country":"GB",
    "wof:name":"DE15 0BE",
    "wof:placetype":"postalcode"
},
  "geometry": {"coordinates":[-1.60488191951347,52.81109749189677],"type":"Point"}
}