{
  "type": "Feature",
  "properties": {
    "iso:country": "GB",
    "wof:name": "DE15 0BE",
    "wof:placetype": "postalcode"
  },
  "geometry": {"coordinates":[-1.604882,52.811097],"type":"Point"}
}
