{
  "type": "Feature",
  "properties": {
    "iso:country": "GB",
    "wof:name": "TD1 2UE",
    "wof:placetype": "postalcode"
  },
  "geometry": {"coordinates":[-2.791027,55.611453],"type":"Point"}
}
