{
  "type": "Feature",
  "properties": {
    "date:inception_lower": "1990-02-01",
    "date:inception_upper": "1990-02-01",
    "iso:country": "GB",
    "wof:name": "TD1 2UE",
    "wof:placetype": "postalcode"
  },
  "geometry": {"coordinates":[-2.791027,55.611453],"type":"Point"}
}
