{
  "type": "Feature",
  "properties": {
    "iso:country":"GB",
    "wof:name":"EN11 0PE",
    "wof:placetype":"postalcode"
},
  "geometry": {"coordinates":[-0.00814035195396,51.7664620941986],"type":"Point"}
}