{
  "type": "Feature",
  "properties": {
    "date:inception_lower": "2023-09-01",
    "date:inception_upper": "2023-09-01",
    "iso:country": "GB",
    "wof:name": "G61 4BX",
    "wof:placetype": "postalcode"
  },
  "geometry": {"coordinates":[-4.350355,55.917807],"type":"Point"}
}
