{
  "type": "Feature",
  "properties": {
    "date:inception_lower": "1994-05-01",
    "date:inception_upper": "1994-05-01",
    "iso:country": "GB",
    "wof:name": "CB3 0AZ",
    "wof:placetype": "postalcode"
  },
  "geometry": {"coordinates":[0.104801,52.212403],"type":"Point"}
}
