{
  "type": "Feature",
  "properties": {
    "date:inception_lower": "1985-10-01",
    "date:inception_upper": "1985-10-01",
    "iso:country": "GB",
    "wof:name": "FY8 2PF",
    "wof:placetype": "postalcode"
  },
  "geometry": {"coordinates":[-3.038245,53.757469],"type":"Point"}
}
