{
  "type": "Feature",
  "properties": {
    "iso:country": "GB",
    "wof:name": "CF47 9SD",
    "wof:placetype": "postalcode"
  },
  "geometry": {"coordinates":[-3.378684,51.763162],"type":"Point"}
}
