{
  "type": "Feature",
  "properties": {
    "iso:country":"GB",
    "wof:name":"CF47 9SD",
    "wof:placetype":"postalcode"
},
  "geometry": {"coordinates":[-3.37868412215297,51.76316203607054],"type":"Point"}
}