{
  "type": "Feature",
  "properties": {
    "iso:country": "GB",
    "wof:name": "TN5 6HH",
    "wof:placetype": "postalcode"
  },
  "geometry": {"coordinates":[0.376395,51.07977],"type":"Point"}
}
