{
  "type": "Feature",
  "properties": {
    "iso:country":"GB",
    "wof:name":"TN5 6HH",
    "wof:placetype":"postalcode"
},
  "geometry": {"coordinates":[0.37631163264903,51.0797919265439],"type":"Point"}
}