{
  "type": "Feature",
  "properties": {
    "date:inception_lower": "1980-01-01",
    "date:inception_upper": "1980-01-01",
    "iso:country": "GB",
    "wof:name": "GU35 0QL",
    "wof:placetype": "postalcode"
  },
  "geometry": {"coordinates":[-0.842454,51.122436],"type":"Point"}
}
