{
  "type": "Feature",
  "properties": {
    "iso:country": "GB",
    "wof:name": "GU35 0QL",
    "wof:placetype": "postalcode"
  },
  "geometry": {"coordinates":[-0.84229,51.122303],"type":"Point"}
}
