{
  "type": "Feature",
  "properties": {
    "iso:country":"GB",
    "wof:name":"TN28 8DL",
    "wof:placetype":"postalcode"
},
  "geometry": {"coordinates":[0.93756919792182,50.98551851038857],"type":"Point"}
}