{
  "type": "Feature",
  "properties": {
    "date:inception_lower": "2022-09-01",
    "date:inception_upper": "2022-09-01",
    "iso:country": "GB",
    "wof:name": "TR18 2FY",
    "wof:placetype": "postalcode"
  },
  "geometry": {"coordinates":[-5.546286,50.122172],"type":"Point"}
}
