{
  "type": "Feature",
  "properties": {
    "date:inception_lower": "2024-08-01",
    "date:inception_upper": "2024-08-01",
    "iso:country": "GB",
    "wof:name": "TR18 2FY",
    "wof:placetype": "postalcode"
  },
  "geometry": {"coordinates":[-5.546113,50.122096],"type":"Point"}
}
