{
  "type": "Feature",
  "properties": {
    "iso:country":"GB",
    "wof:name":"ST4 7PS",
    "wof:placetype":"postalcode"
},
  "geometry": {"coordinates":[-2.20696729365462,53.00876301813679],"type":"Point"}
}