{
  "type": "Feature",
  "properties": {
    "iso:country":"GB",
    "wof:name":"S61 3QL",
    "wof:placetype":"postalcode"
},
  "geometry": {"coordinates":[-1.39089366645037,53.44207351536464],"type":"Point"}
}