{
  "type": "Feature",
  "properties": {
    "date:inception_lower":"1980-01-01",
    "date:inception_upper":"1980-01-31",
    "iso:country":"GB",
    "wof:name":"S61 3QL",
    "wof:placetype":"postalcode"
},
  "geometry": {"coordinates":[-1.390894,53.442074],"type":"Point"}
}