{
  "type": "Feature",
  "properties": {
    "iso:country":"GB",
    "wof:name":"PE20 3HY",
    "wof:placetype":"postalcode"
},
  "geometry": {"coordinates":[-0.16155467189817,52.94554780421299],"type":"Point"}
}