{
  "type": "Feature",
  "properties": {
    "iso:country": "GB",
    "wof:name": "PE20 3HY",
    "wof:placetype": "postalcode"
  },
  "geometry": {"coordinates":[-0.161555,52.945548],"type":"Point"}
}
