{
  "type": "Feature",
  "properties": {
    "iso:country":"GB",
    "wof:name":"TN40 2SP",
    "wof:placetype":"postalcode"
},
  "geometry": {"coordinates":[0.49783169719362,50.85229826521222],"type":"Point"}
}