{
  "type": "Feature",
  "properties": {
    "iso:country": "GB",
    "wof:name": "NN5 5EB",
    "wof:placetype": "postalcode"
  },
  "geometry": {"coordinates":[-0.912733,52.2392],"type":"Point"}
}
