{
  "type": "Feature",
  "properties": {
    "iso:country":"GB",
    "wof:name":"NN5 5EB",
    "wof:placetype":"postalcode"
},
  "geometry": {"coordinates":[-0.91273285260973,52.23920022956273],"type":"Point"}
}