{
  "type": "Feature",
  "properties": {
    "date:inception_lower": "1980-01-01",
    "date:inception_upper": "1980-01-01",
    "iso:country": "GB",
    "wof:name": "KY15 5HX",
    "wof:placetype": "postalcode"
  },
  "geometry": {"coordinates":[-3.009138,56.317271],"type":"Point"}
}
