{
  "type": "Feature",
  "properties": {
    "iso:country":"GB",
    "wof:name":"KY15 5HX",
    "wof:placetype":"postalcode"
},
  "geometry": {"coordinates":[-3.00932541599964,56.31711589934059],"type":"Point"}
}