{
  "type": "Feature",
  "properties": {
    "iso:country": "GB",
    "wof:name": "KY15 5HX",
    "wof:placetype": "postalcode"
  },
  "geometry": {"coordinates":[-3.009138,56.317271],"type":"Point"}
}
