{
  "type": "Feature",
  "properties": {
    "iso:country": "GB",
    "wof:name": "G52 3RP",
    "wof:placetype": "postalcode"
  },
  "geometry": {"coordinates":[-4.344269,55.840827],"type":"Point"}
}
