{
  "type": "Feature",
  "properties": {
    "iso:country":"GB",
    "wof:name":"SE4 2NS",
    "wof:placetype":"postalcode"
},
  "geometry": {"coordinates":[-0.04084037245812,51.47053865900983],"type":"Point"}
}