{
  "type": "Feature",
  "properties": {
    "iso:country": "GB",
    "wof:name": "SR8 1EX",
    "wof:placetype": "postalcode"
  },
  "geometry": {"coordinates":[-1.345283,54.752031],"type":"Point"}
}
