{
  "type": "Feature",
  "properties": {
    "iso:country":"GB",
    "wof:name":"SR8 1EX",
    "wof:placetype":"postalcode"
},
  "geometry": {"coordinates":[-1.34491768486378,54.75164221798337],"type":"Point"}
}