{
  "type": "Feature",
  "properties": {
    "date:inception_lower":"1980-01-01",
    "date:inception_upper":"1980-01-31",
    "iso:country":"GB",
    "wof:name":"SR8 1EX",
    "wof:placetype":"postalcode"
},
  "geometry": {"coordinates":[-1.344932,54.751652],"type":"Point"}
}