{
  "type": "Feature",
  "properties": {
    "iso:country":"GB",
    "wof:name":"LA13 9UW",
    "wof:placetype":"postalcode"
},
  "geometry": {"coordinates":[-3.20448278075932,54.13312166698794],"type":"Point"}
}