{
  "type": "Feature",
  "properties": {
    "date:inception_lower":"1990-02-01",
    "date:inception_upper":"1990-02-28",
    "iso:country":"GB",
    "wof:name":"LA13 9UW",
    "wof:placetype":"postalcode"
},
  "geometry": {"coordinates":[-3.204483,54.133122],"type":"Point"}
}