{
  "type": "Feature",
  "properties": {
    "date:inception_lower":"1980-01-01",
    "date:inception_upper":"1980-01-31",
    "iso:country":"GB",
    "wof:name":"SS8 9AN",
    "wof:placetype":"postalcode"
},
  "geometry": {"coordinates":[0.585224,51.523858],"type":"Point"}
}