{
  "type": "Feature",
  "properties": {
    "iso:country": "GB",
    "wof:name": "SS8 9AN",
    "wof:placetype": "postalcode"
  },
  "geometry": {"coordinates":[0.585224,51.523858],"type":"Point"}
}
