{
  "type": "Feature",
  "properties": {
    "iso:country":"GB",
    "wof:name":"SS8 9AN",
    "wof:placetype":"postalcode"
},
  "geometry": {"coordinates":[0.58522413721677,51.52385764243819],"type":"Point"}
}