{
  "type": "Feature",
  "properties": {
    "iso:country":"GB",
    "wof:name":"IP7 7JP",
    "wof:placetype":"postalcode"
},
  "geometry": {"coordinates":[0.89804344635667,52.11680784539124],"type":"Point"}
}