{
  "type": "Feature",
  "properties": {
    "date:inception_lower": "1997-12-01",
    "date:inception_upper": "1997-12-01",
    "iso:country": "GB",
    "wof:name": "GL54 1BX",
    "wof:placetype": "postalcode"
  },
  "geometry": {"coordinates":[-1.721918,51.933766],"type":"Point"}
}
