{
  "type": "Feature",
  "properties": {
    "date:inception_lower": "2002-06-01",
    "date:inception_upper": "2002-06-01",
    "iso:country": "GB",
    "wof:name": "SE8 3EA",
    "wof:placetype": "postalcode"
  },
  "geometry": {"coordinates":[-0.018915,51.481475],"type":"Point"}
}
