{
  "type": "Feature",
  "properties": {
    "iso:country":"GB",
    "wof:name":"SE8 3EA",
    "wof:placetype":"postalcode"
},
  "geometry": {"coordinates":[-0.01886926305714,51.48147327831366],"type":"Point"}
}