{
  "type": "Feature",
  "properties": {
    "iso:country": "GB",
    "wof:name": "HP4 3HH",
    "wof:placetype": "postalcode"
  },
  "geometry": {"coordinates":[-0.56325,51.759775],"type":"Point"}
}
