{
  "type": "Feature",
  "properties": {
    "iso:country":"GB",
    "wof:name":"HP4 3HH",
    "wof:placetype":"postalcode"
},
  "geometry": {"coordinates":[-0.56353662592875,51.75986882435353],"type":"Point"}
}