{
  "type": "Feature",
  "properties": {
    "iso:country":"GB",
    "wof:name":"N16 8QR",
    "wof:placetype":"postalcode"
},
  "geometry": {"coordinates":[-0.08386934684743,51.55420627094932],"type":"Point"}
}