{
  "type": "Feature",
  "properties": {
    "iso:country":"GB",
    "wof:name":"N16 8TJ",
    "wof:placetype":"postalcode"
},
  "geometry": {"coordinates":[-0.08232994527499,51.55410917944049],"type":"Point"}
}