{
  "type": "Feature",
  "properties": {
    "iso:country":"GB",
    "wof:name":"W1J 7SE",
    "wof:placetype":"postalcode"
},
  "geometry": {"coordinates":[-0.14893143479346,51.50573823738582],"type":"Point"}
}