{
  "type": "Feature",
  "properties": {
    "iso:country":"GB",
    "wof:name":"TS8 0RQ",
    "wof:placetype":"postalcode"
},
  "geometry": {"coordinates":[-1.23422253019635,54.5303733392138],"type":"Point"}
}