{
  "type": "Feature",
  "properties": {
    "iso:country":"GB",
    "wof:name":"LE11 1JD",
    "wof:placetype":"postalcode"
},
  "geometry": {"coordinates":[-1.20514597029586,52.78160399412469],"type":"Point"}
}