{
  "type": "Feature",
  "properties": {
    "iso:country":"GB",
    "wof:name":"B60 2PQ",
    "wof:placetype":"postalcode"
},
  "geometry": {"coordinates":[-2.05321622888519,52.32440383527359],"type":"Point"}
}