{
  "type": "Feature",
  "properties": {
    "iso:country": "GB",
    "wof:name": "B60 2PQ",
    "wof:placetype": "postalcode"
  },
  "geometry": {"coordinates":[-2.053216,52.324404],"type":"Point"}
}
