{
  "type": "Feature",
  "properties": {
    "iso:country":"GB",
    "wof:name":"W1J 9EH",
    "wof:placetype":"postalcode"
},
  "geometry": {"coordinates":[-0.13963515619651,51.50791121376003],"type":"Point"}
}