{
  "type": "Feature",
  "properties": {
    "iso:country":"GB",
    "wof:name":"DL13 1SB",
    "wof:placetype":"postalcode"
},
  "geometry": {"coordinates":[-2.14290100488573,54.73778757398816],"type":"Point"}
}