{
  "type": "Feature",
  "properties": {
    "iso:country":"GB",
    "wof:name":"NR31 9DT",
    "wof:placetype":"postalcode"
},
  "geometry": {"coordinates":[1.68228351934471,52.56615294865116],"type":"Point"}
}