{
  "type": "Feature",
  "properties": {
    "date:inception_lower":"1980-01-01",
    "date:inception_upper":"1980-01-31",
    "iso:country":"GB",
    "wof:name":"TS19 7HA",
    "wof:placetype":"postalcode"
},
  "geometry": {"coordinates":[-1.355975,54.569547],"type":"Point"}
}