{
  "type": "Feature",
  "properties": {
    "iso:country":"GB",
    "wof:name":"TS9 5QH",
    "wof:placetype":"postalcode"
},
  "geometry": {"coordinates":[-1.19245031904178,54.46865633371456],"type":"Point"}
}