{
  "type": "Feature",
  "properties": {
    "iso:country": "GB",
    "wof:name": "RG31 5AX",
    "wof:placetype": "postalcode"
  },
  "geometry": {"coordinates":[-1.04237,51.457772],"type":"Point"}
}
