{
  "type": "Feature",
  "properties": {
    "date:inception_lower": "1980-01-01",
    "date:inception_upper": "1980-01-01",
    "iso:country": "GB",
    "wof:name": "RH13 6LW",
    "wof:placetype": "postalcode"
  },
  "geometry": {"coordinates":[-0.299057,51.061868],"type":"Point"}
}
