{
  "type": "Feature",
  "properties": {
    "iso:country": "GB",
    "wof:name": "HU4 6BD",
    "wof:placetype": "postalcode"
  },
  "geometry": {"coordinates":[-0.389792,53.739797],"type":"Point"}
}
