{
  "type": "Feature",
  "properties": {
    "iso:country":"GB",
    "wof:name":"KA18 1FE",
    "wof:placetype":"postalcode"
},
  "geometry": {"coordinates":[-4.2795838763776,55.45892704382194],"type":"Point"}
}