{
  "type": "Feature",
  "properties": {
    "iso:country":"GB",
    "wof:name":"SA7 9GB",
    "wof:placetype":"postalcode"
},
  "geometry": {"coordinates":[-3.87943169534031,51.66522702111512],"type":"Point"}
}