{
  "type": "Feature",
  "properties": {
    "date:inception_lower":"2004-11-01",
    "date:inception_upper":"2004-11-30",
    "iso:country":"GB",
    "wof:name":"SW6 6SQ",
    "wof:placetype":"postalcode"
},
  "geometry": {"coordinates":[-0.215772,51.477459],"type":"Point"}
}