{
  "type": "Feature",
  "properties": {
    "iso:country":"GB",
    "wof:name":"SW6 6SQ",
    "wof:placetype":"postalcode"
},
  "geometry": {"coordinates":[-0.21577241704031,51.47745873598658],"type":"Point"}
}