{
  "type": "Feature",
  "properties": {
    "iso:country": "GB",
    "wof:name": "PH3 1HR",
    "wof:placetype": "postalcode"
  },
  "geometry": {"coordinates":[-3.607576,56.353593],"type":"Point"}
}
