{
  "type": "Feature",
  "properties": {
    "date:inception_lower": "1980-01-01",
    "date:inception_upper": "1980-01-01",
    "iso:country": "GB",
    "wof:name": "LS13 3HY",
    "wof:placetype": "postalcode"
  },
  "geometry": {"coordinates":[-1.648192,53.80813],"type":"Point"}
}
