{
  "type": "Feature",
  "properties": {
    "iso:country":"GB",
    "wof:name":"LS13 3HY",
    "wof:placetype":"postalcode"
},
  "geometry": {"coordinates":[-1.64819169609605,53.80813017262279],"type":"Point"}
}