{
  "type": "Feature",
  "properties": {
    "iso:country": "GB",
    "wof:name": "TN39 4PY",
    "wof:placetype": "postalcode"
  },
  "geometry": {"coordinates":[0.429812,50.845658],"type":"Point"}
}
