{
  "type": "Feature",
  "properties": {
    "iso:country":"GB",
    "wof:name":"TN39 4PY",
    "wof:placetype":"postalcode"
},
  "geometry": {"coordinates":[0.42981209078257,50.84565819240169],"type":"Point"}
}