{
  "type": "Feature",
  "properties": {
    "iso:country":"GB",
    "wof:name":"S2 3GY",
    "wof:placetype":"postalcode"
},
  "geometry": {"coordinates":[-1.46395524394346,53.36540865229326],"type":"Point"}
}