{
  "type": "Feature",
  "properties": {
    "iso:country": "GB",
    "wof:name": "ME12 4RT",
    "wof:placetype": "postalcode"
  },
  "geometry": {"coordinates":[0.919387,51.39774],"type":"Point"}
}
