{
  "type": "Feature",
  "properties": {
    "iso:country": "GB",
    "wof:name": "EX38 8DA",
    "wof:placetype": "postalcode"
  },
  "geometry": {"coordinates":[-4.149334,50.952359],"type":"Point"}
}
