{
  "type": "Feature",
  "properties": {
    "iso:country": "GB",
    "wof:name": "OL9 9BS",
    "wof:placetype": "postalcode"
  },
  "geometry": {"coordinates":[-2.14504,53.5391],"type":"Point"}
}
