{
  "type": "Feature",
  "properties": {
    "iso:country": "GB",
    "wof:name": "OL9 9BS",
    "wof:placetype": "postalcode"
  },
  "geometry": {"coordinates":[-2.145297,53.539153],"type":"Point"}
}
