{
  "type": "Feature",
  "properties": {
    "iso:country": "GB",
    "wof:name": "TN34 1QL",
    "wof:placetype": "postalcode"
  },
  "geometry": {"coordinates":[0.583612,50.857239],"type":"Point"}
}
