{
  "type": "Feature",
  "properties": {
    "iso:country": "GB",
    "wof:name": "DN4 0AW",
    "wof:placetype": "postalcode"
  },
  "geometry": {"coordinates":[-1.155477,53.506082],"type":"Point"}
}
