{
  "type": "Feature",
  "properties": {
    "date:inception_lower": "2018-04-01",
    "date:inception_upper": "2018-04-01",
    "iso:country": "GB",
    "wof:name": "DN4 0AW",
    "wof:placetype": "postalcode"
  },
  "geometry": {"coordinates":[-1.155172,53.505504],"type":"Point"}
}
