{
  "type": "Feature",
  "properties": {
    "iso:country":"GB",
    "wof:name":"WA10 3JJ",
    "wof:placetype":"postalcode"
},
  "geometry": {"coordinates":[-2.76030249490912,53.44387356067755],"type":"Point"}
}