{
  "type": "Feature",
  "properties": {
    "iso:country":"GB",
    "wof:name":"ML3 9DZ",
    "wof:placetype":"postalcode"
},
  "geometry": {"coordinates":[-4.06630682057984,55.77858457224344],"type":"Point"}
}