{
  "type": "Feature",
  "properties": {
    "iso:country":"GB",
    "wof:name":"LS6 3LR",
    "wof:placetype":"postalcode"
},
  "geometry": {"coordinates":[-1.60095635431876,53.82340582978762],"type":"Point"}
}