{
  "type": "Feature",
  "properties": {
    "date:inception_lower":"1980-01-01",
    "date:inception_upper":"1980-01-31",
    "iso:country":"GB",
    "wof:name":"BB9 9RJ",
    "wof:placetype":"postalcode"
},
  "geometry": {"coordinates":[-2.205584,53.834983],"type":"Point"}
}