{
  "type": "Feature",
  "properties": {
    "iso:country":"GB",
    "wof:name":"BB9 9RJ",
    "wof:placetype":"postalcode"
},
  "geometry": {"coordinates":[-2.20562963279906,53.83495607314301],"type":"Point"}
}