{
  "type": "Feature",
  "properties": {
    "iso:country":"GB",
    "wof:name":"LD4 4BL",
    "wof:placetype":"postalcode"
},
  "geometry": {"coordinates":[-3.51217478799433,52.12691780121408],"type":"Point"}
}