{
  "type": "Feature",
  "properties": {
    "iso:country":"GB",
    "wof:name":"S62 7TZ",
    "wof:placetype":"postalcode"
},
  "geometry": {"coordinates":[-1.42994364710067,53.47599136195506],"type":"Point"}
}