{
  "type": "Feature",
  "properties": {
    "iso:country": "GB",
    "wof:name": "S62 7TZ",
    "wof:placetype": "postalcode"
  },
  "geometry": {"coordinates":[-1.429944,53.475991],"type":"Point"}
}
