{
  "type": "Feature",
  "properties": {
    "iso:country":"GB",
    "wof:name":"BS16 1SA",
    "wof:placetype":"postalcode"
},
  "geometry": {"coordinates":[-2.51233593854681,51.50763957385612],"type":"Point"}
}