{
  "type": "Feature",
  "properties": {
    "iso:country":"GB",
    "wof:name":"BH16 5AN",
    "wof:placetype":"postalcode"
},
  "geometry": {"coordinates":[-2.03254551370476,50.72352351648097],"type":"Point"}
}