{
  "type": "Feature",
  "properties": {
    "iso:country": "GB",
    "wof:name": "BH16 5AN",
    "wof:placetype": "postalcode"
  },
  "geometry": {"coordinates":[-2.032545,50.723524],"type":"Point"}
}
