{
  "type": "Feature",
  "properties": {
    "iso:country":"GB",
    "wof:name":"SR7 8SB",
    "wof:placetype":"postalcode"
},
  "geometry": {"coordinates":[-1.35191013017596,54.8021759122091],"type":"Point"}
}