{
  "type": "Feature",
  "properties": {
    "date:inception_lower":"1980-01-01",
    "date:inception_upper":"1980-01-31",
    "iso:country":"GB",
    "wof:name":"SR7 8SB",
    "wof:placetype":"postalcode"
},
  "geometry": {"coordinates":[-1.35191,54.802176],"type":"Point"}
}