{
  "type": "Feature",
  "properties": {
    "iso:country": "GB",
    "wof:name": "SG6 3HZ",
    "wof:placetype": "postalcode"
  },
  "geometry": {"coordinates":[-0.230192,51.973844],"type":"Point"}
}
