{
  "type": "Feature",
  "properties": {
    "iso:country":"GB",
    "wof:name":"SE7 7QG",
    "wof:placetype":"postalcode"
},
  "geometry": {"coordinates":[0.03094164524755,51.48683504985483],"type":"Point"}
}