{
  "type": "Feature",
  "properties": {
    "date:inception_lower": "1992-01-01",
    "date:inception_upper": "1992-01-01",
    "iso:country": "GB",
    "wof:name": "CF44 8PT",
    "wof:placetype": "postalcode"
  },
  "geometry": {"coordinates":[-3.472742,51.718564],"type":"Point"}
}
