{
  "type": "Feature",
  "properties": {
    "iso:country":"GB",
    "wof:name":"CF44 8PT",
    "wof:placetype":"postalcode"
},
  "geometry": {"coordinates":[-3.4727417935677,51.71856358578365],"type":"Point"}
}