{
  "type": "Feature",
  "properties": {
    "iso:country":"GB",
    "wof:name":"L37 3WF",
    "wof:placetype":"postalcode"
},
  "geometry": {"coordinates":[-3.06354081417034,53.55646262280261],"type":"Point"}
}