{
  "type": "Feature",
  "properties": {
    "date:inception_lower": "2011-11-01",
    "date:inception_upper": "2011-11-01",
    "iso:country": "GB",
    "wof:name": "OX11 6AN",
    "wof:placetype": "postalcode"
  },
  "geometry": {"coordinates":[-1.266858,51.613254],"type":"Point"}
}
