{
  "type": "Feature",
  "properties": {
    "date:inception_lower": "1980-01-01",
    "date:inception_upper": "1980-01-01",
    "iso:country": "GB",
    "wof:name": "NE13 7DZ",
    "wof:placetype": "postalcode"
  },
  "geometry": {"coordinates":[-1.639825,55.04815],"type":"Point"}
}
