{
  "type": "Feature",
  "properties": {
    "iso:country": "GB",
    "wof:name": "NE13 7DZ",
    "wof:placetype": "postalcode"
  },
  "geometry": {"coordinates":[-1.639825,55.04815],"type":"Point"}
}
