{
  "type": "Feature",
  "properties": {
    "iso:country":"GB",
    "wof:name":"NE13 7DZ",
    "wof:placetype":"postalcode"
},
  "geometry": {"coordinates":[-1.6398247183332,55.04814970855333],"type":"Point"}
}