{
  "type": "Feature",
  "properties": {
    "iso:country": "GB",
    "wof:name": "CT2 9LY",
    "wof:placetype": "postalcode"
  },
  "geometry": {"coordinates":[1.067706,51.308213],"type":"Point"}
}
