{
  "type": "Feature",
  "properties": {
    "iso:country":"GB",
    "wof:name":"CT2 9LY",
    "wof:placetype":"postalcode"
},
  "geometry": {"coordinates":[1.06770607038884,51.3082127440976],"type":"Point"}
}