{
  "type": "Feature",
  "properties": {
    "iso:country":"GB",
    "wof:name":"EH22 5ES",
    "wof:placetype":"postalcode"
},
  "geometry": {"coordinates":[-3.03743734328267,55.8741431479182],"type":"Point"}
}