{
  "type": "Feature",
  "properties": {
    "iso:country":"GB",
    "wof:name":"NP44 1DW",
    "wof:placetype":"postalcode"
},
  "geometry": {"coordinates":[-3.02557436619755,51.66057593634777],"type":"Point"}
}