{
  "type": "Feature",
  "properties": {
    "iso:country":"GB",
    "wof:name":"DL16 6SZ",
    "wof:placetype":"postalcode"
},
  "geometry": {"coordinates":[-1.58711180885522,54.71100998239877],"type":"Point"}
}