{
  "type": "Feature",
  "properties": {
    "date:inception_lower":"1980-01-01",
    "date:inception_upper":"1980-01-31",
    "iso:country":"GB",
    "wof:name":"EX8 3AR",
    "wof:placetype":"postalcode"
},
  "geometry": {"coordinates":[-3.404022,50.628987],"type":"Point"}
}