{
  "type": "Feature",
  "properties": {
    "iso:country":"GB",
    "wof:name":"EX8 3AR",
    "wof:placetype":"postalcode"
},
  "geometry": {"coordinates":[-3.40402247490468,50.62898727206102],"type":"Point"}
}