{
  "type": "Feature",
  "properties": {
    "iso:country":"GB",
    "wof:name":"S11 8YQ",
    "wof:placetype":"postalcode"
},
  "geometry": {"coordinates":[-1.49423033132795,53.3659002509312],"type":"Point"}
}