{
  "type": "Feature",
  "properties": {
    "date:inception_lower": "2024-09-01",
    "date:inception_upper": "2024-09-01",
    "iso:country": "GB",
    "wof:name": "CH65 3FD",
    "wof:placetype": "postalcode"
  },
  "geometry": {"coordinates":[-2.903881,53.283111],"type":"Point"}
}
