{
  "type": "Feature",
  "properties": {
    "iso:country": "GB",
    "wof:name": "RM3 0GU",
    "wof:placetype": "postalcode"
  },
  "geometry": {"coordinates":[0.222674,51.596272],"type":"Point"}
}
