{
  "type": "Feature",
  "properties": {
    "date:inception_lower":"2008-10-01",
    "date:inception_upper":"2008-10-31",
    "iso:country":"GB",
    "wof:name":"RM3 0GU",
    "wof:placetype":"postalcode"
},
  "geometry": {"coordinates":[0.222674,51.596272],"type":"Point"}
}