{
  "type": "Feature",
  "properties": {
    "iso:country":"GB",
    "wof:name":"RM3 0GU",
    "wof:placetype":"postalcode"
},
  "geometry": {"coordinates":[0.22267353248057,51.59627231821841],"type":"Point"}
}