{
  "type": "Feature",
  "properties": {
    "date:inception_lower": "1980-01-01",
    "date:inception_upper": "1980-01-01",
    "iso:country": "GB",
    "wof:name": "EX39 3DZ",
    "wof:placetype": "postalcode"
  },
  "geometry": {"coordinates":[-4.218148,51.013631],"type":"Point"}
}
