{
  "type": "Feature",
  "properties": {
    "iso:country": "GB",
    "wof:name": "EX39 3DZ",
    "wof:placetype": "postalcode"
  },
  "geometry": {"coordinates":[-4.218148,51.013631],"type":"Point"}
}
