{
  "type": "Feature",
  "properties": {
    "date:inception_lower": "1992-08-01",
    "date:inception_upper": "1992-08-01",
    "iso:country": "GB",
    "wof:name": "LE67 1AE",
    "wof:placetype": "postalcode"
  },
  "geometry": {"coordinates":[-1.308881,52.661817],"type":"Point"}
}
