{
  "type": "Feature",
  "properties": {
    "date:inception_lower": "1980-01-01",
    "date:inception_upper": "1980-01-01",
    "iso:country": "GB",
    "wof:name": "AL6 9BY",
    "wof:placetype": "postalcode"
  },
  "geometry": {"coordinates":[-0.272598,51.836511],"type":"Point"}
}
