{
  "type": "Feature",
  "properties": {
    "iso:country":"GB",
    "wof:name":"AL6 9BY",
    "wof:placetype":"postalcode"
},
  "geometry": {"coordinates":[-0.27257833432839,51.83650297610074],"type":"Point"}
}