{
  "type": "Feature",
  "properties": {
    "iso:country":"GB",
    "wof:name":"BH25 6LD",
    "wof:placetype":"postalcode"
},
  "geometry": {"coordinates":[-1.65642971653975,50.75488379308901],"type":"Point"}
}