{
  "type": "Feature",
  "properties": {
    "date:inception_lower": "1980-01-01",
    "date:inception_upper": "1980-01-01",
    "iso:country": "GB",
    "wof:name": "EX17 5NX",
    "wof:placetype": "postalcode"
  },
  "geometry": {"coordinates":[-3.736197,50.815207],"type":"Point"}
}
