{
  "type": "Feature",
  "properties": {
    "iso:country":"GB",
    "wof:name":"EX17 5NX",
    "wof:placetype":"postalcode"
},
  "geometry": {"coordinates":[-3.73619701503055,50.81520733339278],"type":"Point"}
}