{
  "type": "Feature",
  "properties": {
    "iso:country": "GB",
    "wof:name": "AB54 7PH",
    "wof:placetype": "postalcode"
  },
  "geometry": {"coordinates":[-2.776174,57.540439],"type":"Point"}
}
