{
  "type": "Feature",
  "properties": {
    "iso:country":"GB",
    "wof:name":"AB54 7PH",
    "wof:placetype":"postalcode"
},
  "geometry": {"coordinates":[-2.77617448897278,57.5404391742784],"type":"Point"}
}