{
  "type": "Feature",
  "properties": {
    "iso:country":"GB",
    "wof:name":"CO5 9NE",
    "wof:placetype":"postalcode"
},
  "geometry": {"coordinates":[0.70644468726228,51.83842186820306],"type":"Point"}
}