{
  "type": "Feature",
  "properties": {
    "iso:country": "GB",
    "wof:name": "CO5 9NE",
    "wof:placetype": "postalcode"
  },
  "geometry": {"coordinates":[0.706445,51.838422],"type":"Point"}
}
