{
  "type": "Feature",
  "properties": {
    "iso:country":"GB",
    "wof:name":"NG32 1AE",
    "wof:placetype":"postalcode"
},
  "geometry": {"coordinates":[-0.6891773599161,52.89094839727185],"type":"Point"}
}