{
  "type": "Feature",
  "properties": {
    "date:inception_lower":"1980-01-01",
    "date:inception_upper":"1980-01-31",
    "iso:country":"GB",
    "wof:name":"NG32 1AE",
    "wof:placetype":"postalcode"
},
  "geometry": {"coordinates":[-0.689039,52.890596],"type":"Point"}
}