{
  "type": "Feature",
  "properties": {
    "iso:country": "GB",
    "wof:name": "TA11 6JA",
    "wof:placetype": "postalcode"
  },
  "geometry": {"coordinates":[-2.761564,51.06623],"type":"Point"}
}
