{
  "type": "Feature",
  "properties": {
    "date:inception_lower": "1980-01-01",
    "date:inception_upper": "1980-01-01",
    "iso:country": "GB",
    "wof:name": "DL3 9DS",
    "wof:placetype": "postalcode"
  },
  "geometry": {"coordinates":[-1.59457,54.534058],"type":"Point"}
}
