{
  "type": "Feature",
  "properties": {
    "iso:country": "GB",
    "wof:name": "DL3 9DS",
    "wof:placetype": "postalcode"
  },
  "geometry": {"coordinates":[-1.59457,54.534058],"type":"Point"}
}
