{
  "type": "Feature",
  "properties": {
    "iso:country":"GB",
    "wof:name":"DL3 9DS",
    "wof:placetype":"postalcode"
},
  "geometry": {"coordinates":[-1.59457013535125,54.53405826818177],"type":"Point"}
}