{
  "type": "Feature",
  "properties": {
    "iso:country":"GB",
    "wof:name":"PL8 2EN",
    "wof:placetype":"postalcode"
},
  "geometry": {"coordinates":[-3.97415548041557,50.33981655915856],"type":"Point"}
}