{
  "type": "Feature",
  "properties": {
    "date:inception_lower": "1980-01-01",
    "date:inception_upper": "1980-01-01",
    "iso:country": "GB",
    "wof:name": "BD22 8AP",
    "wof:placetype": "postalcode"
  },
  "geometry": {"coordinates":[-1.951562,53.825955],"type":"Point"}
}
