{
  "type": "Feature",
  "properties": {
    "iso:country":"GB",
    "wof:name":"BD22 8AP",
    "wof:placetype":"postalcode"
},
  "geometry": {"coordinates":[-1.95156183990175,53.82595539152597],"type":"Point"}
}