{
  "type": "Feature",
  "properties": {
    "iso:country":"GB",
    "wof:name":"YO8 5LB",
    "wof:placetype":"postalcode"
},
  "geometry": {"coordinates":[-1.03287847624482,53.81148059423352],"type":"Point"}
}