{
  "type": "Feature",
  "properties": {
    "date:inception_lower": "1998-06-01",
    "date:inception_upper": "1998-06-01",
    "iso:country": "GB",
    "wof:name": "YO8 5LB",
    "wof:placetype": "postalcode"
  },
  "geometry": {"coordinates":[-1.032878,53.811481],"type":"Point"}
}
