{
  "type": "Feature",
  "properties": {
    "iso:country": "GB",
    "wof:name": "GU11 1QE",
    "wof:placetype": "postalcode"
  },
  "geometry": {"coordinates":[-0.771404,51.249245],"type":"Point"}
}
