{
  "type": "Feature",
  "properties": {
    "iso:country":"GB",
    "wof:name":"DN4 6ST",
    "wof:placetype":"postalcode"
},
  "geometry": {"coordinates":[-1.05821976527828,53.49463863254809],"type":"Point"}
}