{
  "type": "Feature",
  "properties": {
    "date:inception_lower": "1980-01-01",
    "date:inception_upper": "1980-01-01",
    "iso:country": "GB",
    "wof:name": "DN4 6ST",
    "wof:placetype": "postalcode"
  },
  "geometry": {"coordinates":[-1.05822,53.494639],"type":"Point"}
}
