{
  "type": "Feature",
  "properties": {
    "iso:country":"GB",
    "wof:name":"CM6 3BP",
    "wof:placetype":"postalcode"
},
  "geometry": {"coordinates":[0.40454799720191,51.9101273885675],"type":"Point"}
}