{
  "type": "Feature",
  "properties": {
    "iso:country":"GB",
    "wof:name":"BB5 1PL",
    "wof:placetype":"postalcode"
},
  "geometry": {"coordinates":[-2.36643203429003,53.75393189903172],"type":"Point"}
}