{
  "type": "Feature",
  "properties": {
    "date:inception_lower": "2020-10-01",
    "date:inception_upper": "2020-10-01",
    "iso:country": "GB",
    "wof:name": "CV23 8WB",
    "wof:placetype": "postalcode"
  },
  "geometry": {"coordinates":[-1.207459,52.327988],"type":"Point"}
}
