{
  "type": "Feature",
  "properties": {
    "iso:country": "GB",
    "wof:name": "WV10 9YB",
    "wof:placetype": "postalcode"
  },
  "geometry": {"coordinates":[-2.11474,52.602205],"type":"Point"}
}
