{
  "type": "Feature",
  "properties": {
    "iso:country":"GB",
    "wof:name":"YO41 1NA",
    "wof:placetype":"postalcode"
},
  "geometry": {"coordinates":[-0.92791451612977,53.99714017637141],"type":"Point"}
}