{
  "type": "Feature",
  "properties": {
    "date:inception_lower": "2023-07-01",
    "date:inception_upper": "2023-07-01",
    "iso:country": "GB",
    "wof:name": "PL9 8XY",
    "wof:placetype": "postalcode"
  },
  "geometry": {"coordinates":[-4.040633,50.371339],"type":"Point"}
}
