{
  "type": "Feature",
  "properties": {
    "iso:country":"GB",
    "wof:name":"CO9 2EA",
    "wof:placetype":"postalcode"
},
  "geometry": {"coordinates":[0.64132012042584,51.94523964922437],"type":"Point"}
}