{
  "type": "Feature",
  "properties": {
    "iso:country": "GB",
    "wof:name": "NE63 9AY",
    "wof:placetype": "postalcode"
  },
  "geometry": {"coordinates":[-1.558497,55.176608],"type":"Point"}
}
