{
  "type": "Feature",
  "properties": {
    "iso:country":"GB",
    "wof:name":"NE63 9AY",
    "wof:placetype":"postalcode"
},
  "geometry": {"coordinates":[-1.55849681969099,55.17660771145984],"type":"Point"}
}