{
  "type": "Feature",
  "properties": {
    "iso:country": "GB",
    "wof:name": "CV36 5AZ",
    "wof:placetype": "postalcode"
  },
  "geometry": {"coordinates":[-1.584901,52.060501],"type":"Point"}
}
