{
  "type": "Feature",
  "properties": {
    "date:inception_lower":"2006-05-01",
    "date:inception_upper":"2006-05-31",
    "iso:country":"GB",
    "wof:name":"AB21 0GA",
    "wof:placetype":"postalcode"
},
  "geometry": {"coordinates":[-2.282583,57.212116],"type":"Point"}
}