{
  "type": "Feature",
  "properties": {
    "date:inception_lower": "1993-01-01",
    "date:inception_upper": "1993-01-01",
    "iso:country": "GB",
    "wof:name": "CF40 1RF",
    "wof:placetype": "postalcode"
  },
  "geometry": {"coordinates":[-3.442891,51.606626],"type":"Point"}
}
