{
  "type": "Feature",
  "properties": {
    "iso:country": "GB",
    "wof:name": "PL30 4PU",
    "wof:placetype": "postalcode"
  },
  "geometry": {"coordinates":[-4.698955,50.506088],"type":"Point"}
}
