{
  "type": "Feature",
  "properties": {
    "iso:country":"GB",
    "wof:name":"PL30 4PU",
    "wof:placetype":"postalcode"
},
  "geometry": {"coordinates":[-4.69895457836033,50.50608805156468],"type":"Point"}
}