{
  "type": "Feature",
  "properties": {
    "iso:country":"GB",
    "wof:name":"TN5 6EA",
    "wof:placetype":"postalcode"
},
  "geometry": {"coordinates":[0.33702505054889,51.07084404576943],"type":"Point"}
}