{
  "type": "Feature",
  "properties": {
    "date:inception_lower": "1980-01-01",
    "date:inception_upper": "1980-01-01",
    "iso:country": "GB",
    "wof:name": "TN5 6EA",
    "wof:placetype": "postalcode"
  },
  "geometry": {"coordinates":[0.337025,51.070844],"type":"Point"}
}
