{
  "type": "Feature",
  "properties": {
    "iso:country":"GB",
    "wof:name":"WN3 4LY",
    "wof:placetype":"postalcode"
},
  "geometry": {"coordinates":[-2.61927923553323,53.53606596956028],"type":"Point"}
}