{
  "type": "Feature",
  "properties": {
    "iso:country":"GB",
    "wof:name":"NE33 5BD",
    "wof:placetype":"postalcode"
},
  "geometry": {"coordinates":[-1.44599720436449,54.98373669547141],"type":"Point"}
}