{
  "type": "Feature",
  "properties": {
    "iso:country": "GB",
    "wof:name": "NE33 5BD",
    "wof:placetype": "postalcode"
  },
  "geometry": {"coordinates":[-1.44601,54.983745],"type":"Point"}
}
