{
  "type": "Feature",
  "properties": {
    "date:inception_lower":"2006-07-01",
    "date:inception_upper":"2006-07-31",
    "iso:country":"GB",
    "wof:name":"NE33 5BD",
    "wof:placetype":"postalcode"
},
  "geometry": {"coordinates":[-1.44601,54.983745],"type":"Point"}
}