{
  "type": "Feature",
  "properties": {
    "iso:country": "GB",
    "wof:name": "RG10 9RY",
    "wof:placetype": "postalcode"
  },
  "geometry": {"coordinates":[-0.875667,51.485839],"type":"Point"}
}
