{
  "type": "Feature",
  "properties": {
    "iso:country":"GB",
    "wof:name":"BS3 5AZ",
    "wof:placetype":"postalcode"
},
  "geometry": {"coordinates":[-2.59478223736986,51.43567705850607],"type":"Point"}
}