{
  "type": "Feature",
  "properties": {
    "date:inception_lower": "1980-01-01",
    "date:inception_upper": "1980-01-01",
    "iso:country": "GB",
    "wof:name": "S43 3JY",
    "wof:placetype": "postalcode"
  },
  "geometry": {"coordinates":[-1.337411,53.25842],"type":"Point"}
}
