{
  "type": "Feature",
  "properties": {
    "iso:country":"GB",
    "wof:name":"SO40 7AN",
    "wof:placetype":"postalcode"
},
  "geometry": {"coordinates":[-1.53794588304137,50.89865262664697],"type":"Point"}
}