{
  "type": "Feature",
  "properties": {
    "date:inception_lower":"2017-03-01",
    "date:inception_upper":"2017-03-31",
    "iso:country":"GB",
    "wof:name":"DE55 2EG",
    "wof:placetype":"postalcode"
},
  "geometry": {"coordinates":[-1.316877,53.1093],"type":"Point"}
}