{
  "type": "Feature",
  "properties": {
    "iso:country": "GB",
    "wof:name": "HP4 2HS",
    "wof:placetype": "postalcode"
  },
  "geometry": {"coordinates":[-0.564856,51.756189],"type":"Point"}
}
