{
  "type": "Feature",
  "properties": {
    "date:inception_lower":"1980-01-01",
    "date:inception_upper":"1980-01-31",
    "iso:country":"GB",
    "wof:name":"HP4 2HS",
    "wof:placetype":"postalcode"
},
  "geometry": {"coordinates":[-0.564856,51.756189],"type":"Point"}
}