{
  "type": "Feature",
  "properties": {
    "iso:country":"GB",
    "wof:name":"G44 3NE",
    "wof:placetype":"postalcode"
},
  "geometry": {"coordinates":[-4.26195571010289,55.81352446044016],"type":"Point"}
}