{
  "type": "Feature",
  "properties": {
    "date:inception_lower": "2003-11-01",
    "date:inception_upper": "2003-11-01",
    "iso:country": "GB",
    "wof:name": "OL6 7BF",
    "wof:placetype": "postalcode"
  },
  "geometry": {"coordinates":[-2.100061,53.487698],"type":"Point"}
}
