{
  "type": "Feature",
  "properties": {
    "iso:country":"GB",
    "wof:name":"SR8 5HX",
    "wof:placetype":"postalcode"
},
  "geometry": {"coordinates":[-1.33416954430638,54.76280812500187],"type":"Point"}
}