{
  "type": "Feature",
  "properties": {
    "date:inception_lower": "1980-01-01",
    "date:inception_upper": "1980-01-01",
    "iso:country": "GB",
    "wof:name": "SR8 5HX",
    "wof:placetype": "postalcode"
  },
  "geometry": {"coordinates":[-1.334169,54.762808],"type":"Point"}
}
