{
  "type": "Feature",
  "properties": {
    "date:inception_lower":"2016-03-01",
    "date:inception_upper":"2016-03-31",
    "iso:country":"GB",
    "wof:name":"DT10 9BN",
    "wof:placetype":"postalcode"
},
  "geometry": {"coordinates":[-2.301238,50.929463],"type":"Point"}
}