{
  "type": "Feature",
  "properties": {
    "iso:country": "GB",
    "wof:name": "G5 9AR",
    "wof:placetype": "postalcode"
  },
  "geometry": {"coordinates":[-4.256026,55.851115],"type":"Point"}
}
