{
  "type": "Feature",
  "properties": {
    "date:inception_lower": "2015-03-01",
    "date:inception_upper": "2015-03-01",
    "iso:country": "GB",
    "wof:name": "CW9 6RG",
    "wof:placetype": "postalcode"
  },
  "geometry": {"coordinates":[-2.493778,53.274063],"type":"Point"}
}
