{
  "type": "Feature",
  "properties": {
    "iso:country": "GB",
    "wof:name": "EX4 2JD",
    "wof:placetype": "postalcode"
  },
  "geometry": {"coordinates":[-3.562803,50.726027],"type":"Point"}
}
