{
  "type": "Feature",
  "properties": {
    "date:inception_lower":"1995-12-01",
    "date:inception_upper":"1995-12-31",
    "iso:country":"GB",
    "wof:name":"EX4 2JD",
    "wof:placetype":"postalcode"
},
  "geometry": {"coordinates":[-3.562803,50.726027],"type":"Point"}
}