{
  "type": "Feature",
  "properties": {
    "iso:country":"GB",
    "wof:name":"EX4 2JD",
    "wof:placetype":"postalcode"
},
  "geometry": {"coordinates":[-3.5628028671182,50.7260273374121],"type":"Point"}
}