{
  "type": "Feature",
  "properties": {
    "date:inception_lower": "2004-11-01",
    "date:inception_upper": "2004-11-01",
    "iso:country": "GB",
    "wof:name": "ST4 5BY",
    "wof:placetype": "postalcode"
  },
  "geometry": {"coordinates":[-2.191151,52.994478],"type":"Point"}
}
