{
  "type": "Feature",
  "properties": {
    "iso:country": "GB",
    "wof:name": "DD8 1ER",
    "wof:placetype": "postalcode"
  },
  "geometry": {"coordinates":[-2.902641,56.636518],"type":"Point"}
}
