{
  "type": "Feature",
  "properties": {
    "iso:country":"GB",
    "wof:name":"BL3 3HX",
    "wof:placetype":"postalcode"
},
  "geometry": {"coordinates":[-2.44736865610777,53.55927709093469],"type":"Point"}
}