{
  "type": "Feature",
  "properties": {
    "date:inception_lower": "1980-01-01",
    "date:inception_upper": "1980-01-01",
    "iso:country": "GB",
    "wof:name": "NG2 2ND",
    "wof:placetype": "postalcode"
  },
  "geometry": {"coordinates":[-1.152475,52.93988],"type":"Point"}
}
