{
  "type": "Feature",
  "properties": {
    "iso:country":"GB",
    "wof:name":"NG2 2ND",
    "wof:placetype":"postalcode"
},
  "geometry": {"coordinates":[-1.15247536504055,52.93987979487502],"type":"Point"}
}