{
  "type": "Feature",
  "properties": {
    "iso:country": "GB",
    "wof:name": "IP27 9EA",
    "wof:placetype": "postalcode"
  },
  "geometry": {"coordinates":[0.529904,52.414358],"type":"Point"}
}
