{
  "type": "Feature",
  "properties": {
    "iso:country":"GB",
    "wof:name":"IP27 9EA",
    "wof:placetype":"postalcode"
},
  "geometry": {"coordinates":[0.52990443953099,52.41435792772907],"type":"Point"}
}