{
  "type": "Feature",
  "properties": {
    "date:inception_lower":"1980-01-01",
    "date:inception_upper":"1980-01-31",
    "iso:country":"GB",
    "wof:name":"DD11 1HR",
    "wof:placetype":"postalcode"
},
  "geometry": {"coordinates":[-2.582347,56.558831],"type":"Point"}
}