{
  "type": "Feature",
  "properties": {
    "date:inception_lower": "2020-04-01",
    "date:inception_upper": "2020-04-01",
    "iso:country": "GB",
    "wof:name": "SG5 4SJ",
    "wof:placetype": "postalcode"
  },
  "geometry": {"coordinates":[-0.241969,52.00141],"type":"Point"}
}
