{
  "type": "Feature",
  "properties": {
    "date:inception_lower": "2023-07-01",
    "date:inception_upper": "2023-07-01",
    "iso:country": "GB",
    "wof:name": "SG5 4SJ",
    "wof:placetype": "postalcode"
  },
  "geometry": {"coordinates":[-0.242171,52.001835],"type":"Point"}
}
