{
  "type": "Feature",
  "properties": {
    "iso:country":"GB",
    "wof:name":"BA14 8BN",
    "wof:placetype":"postalcode"
},
  "geometry": {"coordinates":[-2.2088789717326,51.31610764435441],"type":"Point"}
}