{
  "type": "Feature",
  "properties": {
    "iso:country":"GB",
    "wof:name":"TA20 4PL",
    "wof:placetype":"postalcode"
},
  "geometry": {"coordinates":[-2.90356350626791,50.8190179387329],"type":"Point"}
}