{
  "type": "Feature",
  "properties": {
    "iso:country":"GB",
    "wof:name":"HU5 2QZ",
    "wof:placetype":"postalcode"
},
  "geometry": {"coordinates":[-0.35594785526705,53.76158518803872],"type":"Point"}
}