{
  "type": "Feature",
  "properties": {
    "iso:country": "GB",
    "wof:name": "HU5 2QZ",
    "wof:placetype": "postalcode"
  },
  "geometry": {"coordinates":[-0.355948,53.761585],"type":"Point"}
}
