{
  "type": "Feature",
  "properties": {
    "date:inception_lower":"1980-01-01",
    "date:inception_upper":"1980-01-31",
    "iso:country":"GB",
    "wof:name":"TA20 4JX",
    "wof:placetype":"postalcode"
},
  "geometry": {"coordinates":[-2.924476,50.860805],"type":"Point"}
}