{
  "type": "Feature",
  "properties": {
    "iso:country":"GB",
    "wof:name":"TA20 4JX",
    "wof:placetype":"postalcode"
},
  "geometry": {"coordinates":[-2.924476409165,50.86080510471531],"type":"Point"}
}