{
  "type": "Feature",
  "properties": {
    "date:inception_lower":"2010-02-01",
    "date:inception_upper":"2010-02-28",
    "iso:country":"GB",
    "wof:name":"EH22 3ND",
    "wof:placetype":"postalcode"
},
  "geometry": {"coordinates":[-3.090146,55.880233],"type":"Point"}
}