{
  "type": "Feature",
  "properties": {
    "iso:country":"GB",
    "wof:name":"EH22 3ND",
    "wof:placetype":"postalcode"
},
  "geometry": {"coordinates":[-3.09012659102059,55.88022912224491],"type":"Point"}
}