{
  "type": "Feature",
  "properties": {
    "date:inception_lower": "1980-01-01",
    "date:inception_upper": "1980-01-01",
    "iso:country": "GB",
    "wof:name": "SA1 6UD",
    "wof:placetype": "postalcode"
  },
  "geometry": {"coordinates":[-3.95597,51.627962],"type":"Point"}
}
