{
  "type": "Feature",
  "properties": {
    "date:inception_lower": "2024-06-01",
    "date:inception_upper": "2024-06-01",
    "iso:country": "GB",
    "wof:name": "PL31 2XF",
    "wof:placetype": "postalcode"
  },
  "geometry": {"coordinates":[-4.708556,50.474769],"type":"Point"}
}
