{
  "type": "Feature",
  "properties": {
    "iso:country":"GB",
    "wof:name":"B65 0AJ",
    "wof:placetype":"postalcode"
},
  "geometry": {"coordinates":[-2.03601237613044,52.47616292563684],"type":"Point"}
}