{
  "type": "Feature",
  "properties": {
    "date:inception_lower":"2012-02-01",
    "date:inception_upper":"2012-02-29",
    "iso:country":"GB",
    "wof:name":"B65 0AJ",
    "wof:placetype":"postalcode"
},
  "geometry": {"coordinates":[-2.036012,52.476163],"type":"Point"}
}