{
  "type": "Feature",
  "properties": {
    "date:inception_lower": "2018-10-01",
    "date:inception_upper": "2018-10-01",
    "iso:country": "GB",
    "wof:name": "SA62 3QT",
    "wof:placetype": "postalcode"
  },
  "geometry": {"coordinates":[-4.993637,51.758932],"type":"Point"}
}
