{
  "type": "Feature",
  "properties": {
    "iso:country":"GB",
    "wof:name":"NE28 6SE",
    "wof:placetype":"postalcode"
},
  "geometry": {"coordinates":[-1.53775239831474,54.98929585450382],"type":"Point"}
}