{
  "type": "Feature",
  "properties": {
    "iso:country":"GB",
    "wof:name":"SM7 1ET",
    "wof:placetype":"postalcode"
},
  "geometry": {"coordinates":[-0.21497887811061,51.32055307359247],"type":"Point"}
}