{
  "type": "Feature",
  "properties": {
    "iso:country":"GB",
    "wof:name":"LL12 8AQ",
    "wof:placetype":"postalcode"
},
  "geometry": {"coordinates":[-2.98929361770441,53.06948780372927],"type":"Point"}
}