{
  "type": "Feature",
  "properties": {
    "date:inception_lower": "1980-01-01",
    "date:inception_upper": "1980-01-01",
    "iso:country": "GB",
    "wof:name": "L4 4PW",
    "wof:placetype": "postalcode"
  },
  "geometry": {"coordinates":[-2.973728,53.436427],"type":"Point"}
}
