{
  "type": "Feature",
  "properties": {
    "date:inception_lower": "1980-01-01",
    "date:inception_upper": "1980-01-01",
    "iso:country": "GB",
    "wof:name": "OX4 4EQ",
    "wof:placetype": "postalcode"
  },
  "geometry": {"coordinates":[-1.23834,51.726804],"type":"Point"}
}
