{
  "type": "Feature",
  "properties": {
    "iso:country": "GB",
    "wof:name": "OX4 4EQ",
    "wof:placetype": "postalcode"
  },
  "geometry": {"coordinates":[-1.23834,51.726804],"type":"Point"}
}
