{
  "type": "Feature",
  "properties": {
    "iso:country": "GB",
    "wof:name": "B38 8XQ",
    "wof:placetype": "postalcode"
  },
  "geometry": {"coordinates":[-1.94507,52.404047],"type":"Point"}
}
