{
  "type": "Feature",
  "properties": {
    "iso:country":"GB",
    "wof:name":"PE4 6GQ",
    "wof:placetype":"postalcode"
},
  "geometry": {"coordinates":[-0.26744305329278,52.61650961093883],"type":"Point"}
}