{
  "type": "Feature",
  "properties": {
    "iso:country": "GB",
    "wof:name": "PE4 6GQ",
    "wof:placetype": "postalcode"
  },
  "geometry": {"coordinates":[-0.26712,52.616506],"type":"Point"}
}
