{
  "type": "Feature",
  "properties": {
    "iso:country": "GB",
    "wof:name": "HX5 9DW",
    "wof:placetype": "postalcode"
  },
  "geometry": {"coordinates":[-1.836388,53.686351],"type":"Point"}
}
