{
  "type": "Feature",
  "properties": {
    "iso:country": "GB",
    "wof:name": "GL52 3LY",
    "wof:placetype": "postalcode"
  },
  "geometry": {"coordinates":[-2.055473,51.912736],"type":"Point"}
}
