{
  "type": "Feature",
  "properties": {
    "date:inception_lower":"2009-01-01",
    "date:inception_upper":"2009-01-31",
    "iso:country":"GB",
    "wof:name":"NE36 0PD",
    "wof:placetype":"postalcode"
},
  "geometry": {"coordinates":[-1.452218,54.942257],"type":"Point"}
}