{
  "type": "Feature",
  "properties": {
    "iso:country": "GB",
    "wof:name": "NE36 0PD",
    "wof:placetype": "postalcode"
  },
  "geometry": {"coordinates":[-1.452218,54.942257],"type":"Point"}
}
