{
  "type": "Feature",
  "properties": {
    "iso:country": "GB",
    "wof:name": "WF4 3AA",
    "wof:placetype": "postalcode"
  },
  "geometry": {"coordinates":[-1.532721,53.64808],"type":"Point"}
}
