{
  "type": "Feature",
  "properties": {
    "iso:country":"GB",
    "wof:name":"KT4 8JF",
    "wof:placetype":"postalcode"
},
  "geometry": {"coordinates":[-0.23755562296464,51.37963485045346],"type":"Point"}
}