{
  "type": "Feature",
  "properties": {
    "iso:country":"GB",
    "wof:name":"TR1 2HH",
    "wof:placetype":"postalcode"
},
  "geometry": {"coordinates":[-5.04820153812848,50.26325995610457],"type":"Point"}
}