{
  "type": "Feature",
  "properties": {
    "iso:country": "GB",
    "wof:name": "NN7 4PN",
    "wof:placetype": "postalcode"
  },
  "geometry": {"coordinates":[-1.0781,52.228722],"type":"Point"}
}
