{
  "type": "Feature",
  "properties": {
    "iso:country":"GB",
    "wof:name":"NN7 4PN",
    "wof:placetype":"postalcode"
},
  "geometry": {"coordinates":[-1.07818798874596,52.22870431140554],"type":"Point"}
}