{
  "type": "Feature",
  "properties": {
    "date:inception_lower": "1980-01-01",
    "date:inception_upper": "1980-01-01",
    "iso:country": "GB",
    "wof:name": "LL65 4SE",
    "wof:placetype": "postalcode"
  },
  "geometry": {"coordinates":[-4.412759,53.253255],"type":"Point"}
}
