{
  "type": "Feature",
  "properties": {
    "iso:country":"GB",
    "wof:name":"SY7 8LD",
    "wof:placetype":"postalcode"
},
  "geometry": {"coordinates":[-3.02704537865868,52.42226099465613],"type":"Point"}
}