{
  "type": "Feature",
  "properties": {
    "iso:country": "GB",
    "wof:name": "SY7 8LD",
    "wof:placetype": "postalcode"
  },
  "geometry": {"coordinates":[-3.027045,52.422261],"type":"Point"}
}
