{
  "type": "Feature",
  "properties": {
    "iso:country":"GB",
    "wof:name":"PR5 6FY",
    "wof:placetype":"postalcode"
},
  "geometry": {"coordinates":[-2.66174668390958,53.725043931814],"type":"Point"}
}