{
  "type": "Feature",
  "properties": {
    "date:inception_lower": "2006-02-01",
    "date:inception_upper": "2006-02-01",
    "iso:country": "GB",
    "wof:name": "ST6 5SB",
    "wof:placetype": "postalcode"
  },
  "geometry": {"coordinates":[-2.20669,53.062923],"type":"Point"}
}
