{
  "type": "Feature",
  "properties": {
    "iso:country":"GB",
    "wof:name":"WS12 4AP",
    "wof:placetype":"postalcode"
},
  "geometry": {"coordinates":[-2.00472348834474,52.7105860030597],"type":"Point"}
}