{
  "type": "Feature",
  "properties": {
    "iso:country":"GB",
    "wof:name":"LN8 6HW",
    "wof:placetype":"postalcode"
},
  "geometry": {"coordinates":[-0.19008481577511,53.43604705515712],"type":"Point"}
}