{
  "type": "Feature",
  "properties": {
    "iso:country":"GB",
    "wof:name":"BD8 8DJ",
    "wof:placetype":"postalcode"
},
  "geometry": {"coordinates":[-1.77148627742603,53.80468916771064],"type":"Point"}
}