{
  "type": "Feature",
  "properties": {
    "iso:country": "GB",
    "wof:name": "SN5 4AP",
    "wof:placetype": "postalcode"
  },
  "geometry": {"coordinates":[-1.866802,51.588422],"type":"Point"}
}
