{
  "type": "Feature",
  "properties": {
    "iso:country":"GB",
    "wof:name":"SN5 4AP",
    "wof:placetype":"postalcode"
},
  "geometry": {"coordinates":[-1.86682622020635,51.58838397202881],"type":"Point"}
}