{
  "type": "Feature",
  "properties": {
    "iso:country":"GB",
    "wof:name":"NP25 5QE",
    "wof:placetype":"postalcode"
},
  "geometry": {"coordinates":[-2.75782886777789,51.83399183703634],"type":"Point"}
}