{
  "type": "Feature",
  "properties": {
    "iso:country":"GB",
    "wof:name":"DN17 1QU",
    "wof:placetype":"postalcode"
},
  "geometry": {"coordinates":[-0.68143863116683,53.57055780790098],"type":"Point"}
}