{
  "type": "Feature",
  "properties": {
    "iso:country":"GB",
    "wof:name":"LS23 6PF",
    "wof:placetype":"postalcode"
},
  "geometry": {"coordinates":[-1.36232029483118,53.90231472762324],"type":"Point"}
}