{
  "type": "Feature",
  "properties": {
    "iso:country": "GB",
    "wof:name": "L32 7RR",
    "wof:placetype": "postalcode"
  },
  "geometry": {"coordinates":[-2.884635,53.467889],"type":"Point"}
}
