{
  "type": "Feature",
  "properties": {
    "iso:country":"GB",
    "wof:name":"L32 7RR",
    "wof:placetype":"postalcode"
},
  "geometry": {"coordinates":[-2.88463471081571,53.46788925284726],"type":"Point"}
}