{
  "type": "Feature",
  "properties": {
    "date:inception_lower": "2022-02-01",
    "date:inception_upper": "2022-02-01",
    "iso:country": "GB",
    "wof:name": "CF31 4PD",
    "wof:placetype": "postalcode"
  },
  "geometry": {"coordinates":[-3.588669,51.510821],"type":"Point"}
}
