{
  "type": "Feature",
  "properties": {
    "iso:country": "GB",
    "wof:name": "TD1 2DY",
    "wof:placetype": "postalcode"
  },
  "geometry": {"coordinates":[-2.782624,55.611229],"type":"Point"}
}
