{
  "type": "Feature",
  "properties": {
    "iso:country":"GB",
    "wof:name":"NP4 7PD",
    "wof:placetype":"postalcode"
},
  "geometry": {"coordinates":[-3.06524779111529,51.73088705939192],"type":"Point"}
}