{
  "type": "Feature",
  "properties": {
    "iso:country":"GB",
    "wof:name":"N11 2AS",
    "wof:placetype":"postalcode"
},
  "geometry": {"coordinates":[-0.13358020084855,51.60452886920769],"type":"Point"}
}