{
  "type": "Feature",
  "properties": {
    "iso:country":"GB",
    "wof:name":"WS1 2QG",
    "wof:placetype":"postalcode"
},
  "geometry": {"coordinates":[-1.97059861940256,52.58794504871336],"type":"Point"}
}