{
  "type": "Feature",
  "properties": {
    "iso:country": "GB",
    "wof:name": "WS1 2QG",
    "wof:placetype": "postalcode"
  },
  "geometry": {"coordinates":[-1.970599,52.587945],"type":"Point"}
}
