{
  "type": "Feature",
  "properties": {
    "iso:country":"GB",
    "wof:name":"TW1 3ND",
    "wof:placetype":"postalcode"
},
  "geometry": {"coordinates":[-0.32773691727916,51.44830103739969],"type":"Point"}
}