{
  "type": "Feature",
  "properties": {
    "date:inception_lower": "1981-09-01",
    "date:inception_upper": "1981-09-01",
    "iso:country": "GB",
    "wof:name": "TW1 3ND",
    "wof:placetype": "postalcode"
  },
  "geometry": {"coordinates":[-0.327737,51.448301],"type":"Point"}
}
