{
  "type": "Feature",
  "properties": {
    "date:inception_lower": "2008-01-01",
    "date:inception_upper": "2008-01-01",
    "iso:country": "GB",
    "wof:name": "WN5 7GB",
    "wof:placetype": "postalcode"
  },
  "geometry": {"coordinates":[-2.712684,53.520427],"type":"Point"}
}
