{
  "type": "Feature",
  "properties": {
    "iso:country": "GB",
    "wof:name": "WN5 7GB",
    "wof:placetype": "postalcode"
  },
  "geometry": {"coordinates":[-2.712684,53.520427],"type":"Point"}
}
