{
  "type": "Feature",
  "properties": {
    "iso:country":"GB",
    "wof:name":"WN5 7GB",
    "wof:placetype":"postalcode"
},
  "geometry": {"coordinates":[-2.71268423493272,53.52042680709916],"type":"Point"}
}