{
  "type": "Feature",
  "properties": {
    "iso:country":"GB",
    "wof:name":"SE23 1RL",
    "wof:placetype":"postalcode"
},
  "geometry": {"coordinates":[-0.04033657279642,51.44297660187821],"type":"Point"}
}