{
  "type": "Feature",
  "properties": {
    "iso:country": "GB",
    "wof:name": "NP19 4BJ",
    "wof:placetype": "postalcode"
  },
  "geometry": {"coordinates":[-2.937931,51.576125],"type":"Point"}
}
