{
  "type": "Feature",
  "properties": {
    "iso:country":"GB",
    "wof:name":"NP19 4BJ",
    "wof:placetype":"postalcode"
},
  "geometry": {"coordinates":[-2.93809806005247,51.57613042529528],"type":"Point"}
}