{
  "type": "Feature",
  "properties": {
    "date:inception_lower": "1991-01-01",
    "date:inception_upper": "1991-01-01",
    "iso:country": "GB",
    "wof:name": "WA9 4GF",
    "wof:placetype": "postalcode"
  },
  "geometry": {"coordinates":[-2.720095,53.419314],"type":"Point"}
}
