{
  "type": "Feature",
  "properties": {
    "date:inception_lower": "2019-07-01",
    "date:inception_upper": "2019-07-01",
    "iso:country": "GB",
    "wof:name": "WA6 0GB",
    "wof:placetype": "postalcode"
  },
  "geometry": {"coordinates":[-2.760985,53.278076],"type":"Point"}
}
