{
  "type": "Feature",
  "properties": {
    "date:inception_lower": "1980-01-01",
    "date:inception_upper": "1980-01-01",
    "iso:country": "GB",
    "wof:name": "OL14 8DW",
    "wof:placetype": "postalcode"
  },
  "geometry": {"coordinates":[-2.098012,53.722365],"type":"Point"}
}
