{
  "type": "Feature",
  "properties": {
    "iso:country": "GB",
    "wof:name": "WV4 4JR",
    "wof:placetype": "postalcode"
  },
  "geometry": {"coordinates":[-2.170357,52.557275],"type":"Point"}
}
