{
  "type": "Feature",
  "properties": {
    "date:inception_lower": "1980-01-01",
    "date:inception_upper": "1980-01-01",
    "iso:country": "GB",
    "wof:name": "WV4 4JR",
    "wof:placetype": "postalcode"
  },
  "geometry": {"coordinates":[-2.170357,52.557275],"type":"Point"}
}
