{
  "type": "Feature",
  "properties": {
    "iso:country":"GB",
    "wof:name":"GL1 4AE",
    "wof:placetype":"postalcode"
},
  "geometry": {"coordinates":[-2.23240398616072,51.8601924885427],"type":"Point"}
}