{
  "type": "Feature",
  "properties": {
    "iso:country": "GB",
    "wof:name": "WV16 6SB",
    "wof:placetype": "postalcode"
  },
  "geometry": {"coordinates":[-2.552464,52.537466],"type":"Point"}
}
