{
  "type": "Feature",
  "properties": {
    "iso:country": "GB",
    "wof:name": "SL1 2AS",
    "wof:placetype": "postalcode"
  },
  "geometry": {"coordinates":[-0.587931,51.503592],"type":"Point"}
}
