{
  "type": "Feature",
  "properties": {
    "iso:country": "GB",
    "wof:name": "B18 4ND",
    "wof:placetype": "postalcode"
  },
  "geometry": {"coordinates":[-1.94095,52.495833],"type":"Point"}
}
