{
  "type": "Feature",
  "properties": {
    "iso:country":"GB",
    "wof:name":"KA24 5JE",
    "wof:placetype":"postalcode"
},
  "geometry": {"coordinates":[-4.72203036896069,55.71465941077649],"type":"Point"}
}