{
  "type": "Feature",
  "properties": {
    "date:inception_lower":"1980-01-01",
    "date:inception_upper":"1980-01-31",
    "iso:country":"GB",
    "wof:name":"KA24 5JE",
    "wof:placetype":"postalcode"
},
  "geometry": {"coordinates":[-4.72203,55.714659],"type":"Point"}
}