{
  "type": "Feature",
  "properties": {
    "iso:country": "GB",
    "wof:name": "KA24 5JE",
    "wof:placetype": "postalcode"
  },
  "geometry": {"coordinates":[-4.72203,55.714659],"type":"Point"}
}
