{
  "type": "Feature",
  "properties": {
    "iso:country":"GB",
    "wof:name":"BR2 6EE",
    "wof:placetype":"postalcode"
},
  "geometry": {"coordinates":[0.04261313202968,51.36403284736506],"type":"Point"}
}