{
  "type": "Feature",
  "properties": {
    "iso:country":"GB",
    "wof:name":"B98 9DA",
    "wof:placetype":"postalcode"
},
  "geometry": {"coordinates":[-1.87946172425785,52.34211033925843],"type":"Point"}
}