{
  "type": "Feature",
  "properties": {
    "date:inception_lower": "1980-01-01",
    "date:inception_upper": "1980-01-01",
    "iso:country": "GB",
    "wof:name": "B98 9DA",
    "wof:placetype": "postalcode"
  },
  "geometry": {"coordinates":[-1.879462,52.34211],"type":"Point"}
}
