{
  "type": "Feature",
  "properties": {
    "date:inception_lower": "1980-01-01",
    "date:inception_upper": "1980-01-01",
    "iso:country": "GB",
    "wof:name": "BR8 8DS",
    "wof:placetype": "postalcode"
  },
  "geometry": {"coordinates":[0.188275,51.391043],"type":"Point"}
}
