{
  "type": "Feature",
  "properties": {
    "iso:country":"GB",
    "wof:name":"BR8 8DS",
    "wof:placetype":"postalcode"
},
  "geometry": {"coordinates":[0.18827538762995,51.39104337467295],"type":"Point"}
}