{
  "type": "Feature",
  "properties": {
    "date:inception_lower": "2006-05-01",
    "date:inception_upper": "2006-05-01",
    "iso:country": "GB",
    "wof:name": "CF38 2FD",
    "wof:placetype": "postalcode"
  },
  "geometry": {"coordinates":[-3.355245,51.555535],"type":"Point"}
}
