{
  "type": "Feature",
  "properties": {
    "iso:country":"GB",
    "wof:name":"NN18 8JL",
    "wof:placetype":"postalcode"
},
  "geometry": {"coordinates":[-0.72174911441428,52.46815957253725],"type":"Point"}
}