{
  "type": "Feature",
  "properties": {
    "date:inception_lower": "1992-01-01",
    "date:inception_upper": "1992-01-01",
    "iso:country": "GB",
    "wof:name": "NN18 8JL",
    "wof:placetype": "postalcode"
  },
  "geometry": {"coordinates":[-0.721749,52.46816],"type":"Point"}
}
