{
  "type": "Feature",
  "properties": {
    "iso:country":"GB",
    "wof:name":"NP15 2AA",
    "wof:placetype":"postalcode"
},
  "geometry": {"coordinates":[-2.8662237042749,51.76734645104697],"type":"Point"}
}