{
  "type": "Feature",
  "properties": {
    "iso:country": "GB",
    "wof:name": "NG21 0EG",
    "wof:placetype": "postalcode"
  },
  "geometry": {"coordinates":[-1.121852,53.119796],"type":"Point"}
}
