{
  "type": "Feature",
  "properties": {
    "iso:country":"GB",
    "wof:name":"BS16 3LZ",
    "wof:placetype":"postalcode"
},
  "geometry": {"coordinates":[-2.5255174184358,51.4711114451605],"type":"Point"}
}