{
  "type": "Feature",
  "properties": {
    "date:inception_lower": "1980-01-01",
    "date:inception_upper": "1980-01-01",
    "iso:country": "GB",
    "wof:name": "BS16 3LZ",
    "wof:placetype": "postalcode"
  },
  "geometry": {"coordinates":[-2.525517,51.471111],"type":"Point"}
}
