{
  "type": "Feature",
  "properties": {
    "iso:country":"GB",
    "wof:name":"IP2 9TJ",
    "wof:placetype":"postalcode"
},
  "geometry": {"coordinates":[1.12940125308868,52.03662766464273],"type":"Point"}
}