{
  "type": "Feature",
  "properties": {
    "iso:country":"GB",
    "wof:name":"S20 3PP",
    "wof:placetype":"postalcode"
},
  "geometry": {"coordinates":[-1.33651182786862,53.33299314972466],"type":"Point"}
}