{
  "type": "Feature",
  "properties": {
    "iso:country": "GB",
    "wof:name": "S20 3PP",
    "wof:placetype": "postalcode"
  },
  "geometry": {"coordinates":[-1.336512,53.332993],"type":"Point"}
}
