{
  "type": "Feature",
  "properties": {
    "date:inception_lower": "2005-04-01",
    "date:inception_upper": "2005-04-01",
    "iso:country": "GB",
    "wof:name": "S20 3PP",
    "wof:placetype": "postalcode"
  },
  "geometry": {"coordinates":[-1.336512,53.332993],"type":"Point"}
}
