{
  "type": "Feature",
  "properties": {
    "date:inception_lower": "1980-01-01",
    "date:inception_upper": "1980-01-01",
    "iso:country": "GB",
    "wof:name": "PL26 6ES",
    "wof:placetype": "postalcode"
  },
  "geometry": {"coordinates":[-4.830738,50.29009],"type":"Point"}
}
