{
  "type": "Feature",
  "properties": {
    "date:inception_lower": "1980-01-01",
    "date:inception_upper": "1980-01-01",
    "iso:country": "GB",
    "wof:name": "PL3 5NJ",
    "wof:placetype": "postalcode"
  },
  "geometry": {"coordinates":[-4.133013,50.390733],"type":"Point"}
}
