{
  "type": "Feature",
  "properties": {
    "iso:country":"GB",
    "wof:name":"RG1 2QG",
    "wof:placetype":"postalcode"
},
  "geometry": {"coordinates":[-0.96730716443087,51.44891631655211],"type":"Point"}
}