{
  "type": "Feature",
  "properties": {
    "iso:country":"GB",
    "wof:name":"CW10 9LN",
    "wof:placetype":"postalcode"
},
  "geometry": {"coordinates":[-2.41741074929336,53.20678762344804],"type":"Point"}
}