{
  "type": "Feature",
  "properties": {
    "iso:country": "GB",
    "wof:name": "CW10 9LN",
    "wof:placetype": "postalcode"
  },
  "geometry": {"coordinates":[-2.417411,53.206788],"type":"Point"}
}
