{
  "type": "Feature",
  "properties": {
    "date:inception_lower": "2018-04-01",
    "date:inception_upper": "2018-04-01",
    "iso:country": "GB",
    "wof:name": "CM16 7FG",
    "wof:placetype": "postalcode"
  },
  "geometry": {"coordinates":[0.133507,51.705476],"type":"Point"}
}
