{
  "type": "Feature",
  "properties": {
    "date:inception_lower": "1996-06-01",
    "date:inception_upper": "1996-06-01",
    "iso:country": "GB",
    "wof:name": "EX20 1UZ",
    "wof:placetype": "postalcode"
  },
  "geometry": {"coordinates":[-3.99387,50.744911],"type":"Point"}
}
