{
  "type": "Feature",
  "properties": {
    "iso:country": "GB",
    "wof:name": "GU32 3DG",
    "wof:placetype": "postalcode"
  },
  "geometry": {"coordinates":[-0.935882,51.004531],"type":"Point"}
}
