{
  "type": "Feature",
  "properties": {
    "iso:country":"GB",
    "wof:name":"PH2 6HW",
    "wof:placetype":"postalcode"
},
  "geometry": {"coordinates":[-3.31544969166444,56.47199274185053],"type":"Point"}
}