{
  "type": "Feature",
  "properties": {
    "date:inception_lower": "1991-09-01",
    "date:inception_upper": "1991-09-01",
    "iso:country": "GB",
    "wof:name": "GU34 2BN",
    "wof:placetype": "postalcode"
  },
  "geometry": {"coordinates":[-0.976567,51.15055],"type":"Point"}
}
