{
  "type": "Feature",
  "properties": {
    "iso:country":"GB",
    "wof:name":"GU34 2BN",
    "wof:placetype":"postalcode"
},
  "geometry": {"coordinates":[-0.9765671448197,51.15055021818713],"type":"Point"}
}