{
  "type": "Feature",
  "properties": {
    "iso:country":"GB",
    "wof:name":"KT2 7RZ",
    "wof:placetype":"postalcode"
},
  "geometry": {"coordinates":[-0.27870941142017,51.42294310217284],"type":"Point"}
}