{
  "type": "Feature",
  "properties": {
    "iso:country":"GB",
    "wof:name":"ST13 8TX",
    "wof:placetype":"postalcode"
},
  "geometry": {"coordinates":[-1.96943196109954,53.14311024882586],"type":"Point"}
}