{
  "type": "Feature",
  "properties": {
    "iso:country": "GB",
    "wof:name": "ST13 8TX",
    "wof:placetype": "postalcode"
  },
  "geometry": {"coordinates":[-1.969429,53.143128],"type":"Point"}
}
