{
  "type": "Feature",
  "properties": {
    "iso:country":"GB",
    "wof:name":"CH1 5EF",
    "wof:placetype":"postalcode"
},
  "geometry": {"coordinates":[-2.92736088908951,53.20992285990044],"type":"Point"}
}