{
  "type": "Feature",
  "properties": {
    "iso:country":"GB",
    "wof:name":"SG8 7SB",
    "wof:placetype":"postalcode"
},
  "geometry": {"coordinates":[0.07639303735903,52.09092180459405],"type":"Point"}
}