{
  "type": "Feature",
  "properties": {
    "iso:country":"GB",
    "wof:name":"DD7 6HG",
    "wof:placetype":"postalcode"
},
  "geometry": {"coordinates":[-2.7115458771033,56.50441487478454],"type":"Point"}
}