{
  "type": "Feature",
  "properties": {
    "date:inception_lower": "1996-12-01",
    "date:inception_upper": "1996-12-01",
    "iso:country": "GB",
    "wof:name": "NE4 6BQ",
    "wof:placetype": "postalcode"
  },
  "geometry": {"coordinates":[-1.62834,54.973377],"type":"Point"}
}
