{
  "type": "Feature",
  "properties": {
    "iso:country":"GB",
    "wof:name":"NE4 6BQ",
    "wof:placetype":"postalcode"
},
  "geometry": {"coordinates":[-1.6283722675787,54.97324227251612],"type":"Point"}
}