{
  "type": "Feature",
  "properties": {
    "date:inception_lower": "1980-01-01",
    "date:inception_upper": "1980-01-01",
    "iso:country": "GB",
    "wof:name": "HG3 5RG",
    "wof:placetype": "postalcode"
  },
  "geometry": {"coordinates":[-1.833493,54.150746],"type":"Point"}
}
