{
  "type": "Feature",
  "properties": {
    "iso:country":"GB",
    "wof:name":"HG3 5RG",
    "wof:placetype":"postalcode"
},
  "geometry": {"coordinates":[-1.83349324677223,54.15074552300439],"type":"Point"}
}