{
  "type": "Feature",
  "properties": {
    "iso:country":"GB",
    "wof:name":"NW8 6QU",
    "wof:placetype":"postalcode"
},
  "geometry": {"coordinates":[-0.17349775245414,51.54037565636146],"type":"Point"}
}