{
  "type": "Feature",
  "properties": {
    "iso:country":"GB",
    "wof:name":"IP31 1EB",
    "wof:placetype":"postalcode"
},
  "geometry": {"coordinates":[0.84816309674845,52.35796000093805],"type":"Point"}
}