{
  "type": "Feature",
  "properties": {
    "iso:country":"GB",
    "wof:name":"PE15 9DN",
    "wof:placetype":"postalcode"
},
  "geometry": {"coordinates":[0.09204040892678,52.53977250187676],"type":"Point"}
}