{
  "type": "Feature",
  "properties": {
    "iso:country":"GB",
    "wof:name":"PE23 5AF",
    "wof:placetype":"postalcode"
},
  "geometry": {"coordinates":[0.08336727339039,53.15411877511048],"type":"Point"}
}