{
  "type": "Feature",
  "properties": {
    "iso:country":"GB",
    "wof:name":"TA6 6DL",
    "wof:placetype":"postalcode"
},
  "geometry": {"coordinates":[-3.00009623828997,51.11801545188943],"type":"Point"}
}