{
  "type": "Feature",
  "properties": {
    "iso:country": "GB",
    "wof:name": "PR7 4EP",
    "wof:placetype": "postalcode"
  },
  "geometry": {"coordinates":[-2.611968,53.622222],"type":"Point"}
}
