{
  "type": "Feature",
  "properties": {
    "iso:country":"GB",
    "wof:name":"WA5 1TH",
    "wof:placetype":"postalcode"
},
  "geometry": {"coordinates":[-2.61093072686499,53.39206648185664],"type":"Point"}
}