{
  "type": "Feature",
  "properties": {
    "iso:country":"GB",
    "wof:name":"M4 4TG",
    "wof:placetype":"postalcode"
},
  "geometry": {"coordinates":[-2.23368143423911,53.48816750559886],"type":"Point"}
}