{
  "type": "Feature",
  "properties": {
    "iso:country":"GB",
    "wof:name":"WD3 1QP",
    "wof:placetype":"postalcode"
},
  "geometry": {"coordinates":[-0.47212366545175,51.63946569742293],"type":"Point"}
}