{
  "type": "Feature",
  "properties": {
    "iso:country": "GB",
    "wof:name": "WD3 1QP",
    "wof:placetype": "postalcode"
  },
  "geometry": {"coordinates":[-0.472124,51.639466],"type":"Point"}
}
