{
  "type": "Feature",
  "properties": {
    "date:inception_lower":"1980-01-01",
    "date:inception_upper":"1980-01-31",
    "iso:country":"GB",
    "wof:name":"PE6 8JY",
    "wof:placetype":"postalcode"
},
  "geometry": {"coordinates":[-0.31536,52.676935],"type":"Point"}
}