{
  "type": "Feature",
  "properties": {
    "iso:country":"GB",
    "wof:name":"PE6 8JY",
    "wof:placetype":"postalcode"
},
  "geometry": {"coordinates":[-0.31536052503456,52.6769351505675],"type":"Point"}
}