{
  "type": "Feature",
  "properties": {
    "iso:country": "GB",
    "wof:name": "HX3 6NF",
    "wof:placetype": "postalcode"
  },
  "geometry": {"coordinates":[-1.865048,53.734545],"type":"Point"}
}
