{
  "type": "Feature",
  "properties": {
    "date:inception_lower": "1980-01-01",
    "date:inception_upper": "1980-01-01",
    "iso:country": "GB",
    "wof:name": "HX3 6NF",
    "wof:placetype": "postalcode"
  },
  "geometry": {"coordinates":[-1.865048,53.734545],"type":"Point"}
}
