{
  "type": "Feature",
  "properties": {
    "iso:country": "GB",
    "wof:name": "G68 9LU",
    "wof:placetype": "postalcode"
  },
  "geometry": {"coordinates":[-4.033853,55.938717],"type":"Point"}
}
