{
  "type": "Feature",
  "properties": {
    "date:inception_lower": "1980-10-01",
    "date:inception_upper": "1980-10-01",
    "iso:country": "GB",
    "wof:name": "G68 9LU",
    "wof:placetype": "postalcode"
  },
  "geometry": {"coordinates":[-4.033853,55.938717],"type":"Point"}
}
