{
  "type": "Feature",
  "properties": {
    "iso:country":"GB",
    "wof:name":"SK11 9PZ",
    "wof:placetype":"postalcode"
},
  "geometry": {"coordinates":[-2.16898105982222,53.2528738491387],"type":"Point"}
}