{
  "type": "Feature",
  "properties": {
    "date:inception_lower": "1980-01-01",
    "date:inception_upper": "1980-01-01",
    "iso:country": "GB",
    "wof:name": "SK11 9PZ",
    "wof:placetype": "postalcode"
  },
  "geometry": {"coordinates":[-2.168981,53.252874],"type":"Point"}
}
