{
  "type": "Feature",
  "properties": {
    "date:inception_lower": "1980-01-01",
    "date:inception_upper": "1980-01-01",
    "iso:country": "GB",
    "wof:name": "SY10 7JJ",
    "wof:placetype": "postalcode"
  },
  "geometry": {"coordinates":[-3.194727,52.880705],"type":"Point"}
}
