{
  "type": "Feature",
  "properties": {
    "iso:country":"GB",
    "wof:name":"TF6 5AJ",
    "wof:placetype":"postalcode"
},
  "geometry": {"coordinates":[-2.5465382962884,52.68098070311891],"type":"Point"}
}