{
  "type": "Feature",
  "properties": {
    "iso:country":"GB",
    "wof:name":"BS2 0SH",
    "wof:placetype":"postalcode"
},
  "geometry": {"coordinates":[-2.57179180041719,51.44937788240921],"type":"Point"}
}