{
  "type": "Feature",
  "properties": {
    "iso:country":"GB",
    "wof:name":"TR7 1DQ",
    "wof:placetype":"postalcode"
},
  "geometry": {"coordinates":[-5.0839411983375,50.41328162625908],"type":"Point"}
}