{
  "type": "Feature",
  "properties": {
    "iso:country":"GB",
    "wof:name":"NG22 9XN",
    "wof:placetype":"postalcode"
},
  "geometry": {"coordinates":[-1.01133538983574,53.20845442344631],"type":"Point"}
}