{
  "type": "Feature",
  "properties": {
    "date:inception_lower": "1993-08-01",
    "date:inception_upper": "1993-08-01",
    "iso:country": "GB",
    "wof:name": "NG22 9XN",
    "wof:placetype": "postalcode"
  },
  "geometry": {"coordinates":[-1.011335,53.208454],"type":"Point"}
}
