{
  "type": "Feature",
  "properties": {
    "iso:country":"GB",
    "wof:name":"SS5 5LA",
    "wof:placetype":"postalcode"
},
  "geometry": {"coordinates":[0.66881605196918,51.61625536244479],"type":"Point"}
}