{
  "type": "Feature",
  "properties": {
    "date:inception_lower": "1980-01-01",
    "date:inception_upper": "1980-01-01",
    "iso:country": "GB",
    "wof:name": "SS5 5LA",
    "wof:placetype": "postalcode"
  },
  "geometry": {"coordinates":[0.668814,51.616253],"type":"Point"}
}
