{
  "type": "Feature",
  "properties": {
    "iso:country": "GB",
    "wof:name": "ST4 8TW",
    "wof:placetype": "postalcode"
  },
  "geometry": {"coordinates":[-2.18184,52.962582],"type":"Point"}
}
