{
  "type": "Feature",
  "properties": {
    "date:inception_lower": "1981-06-01",
    "date:inception_upper": "1981-06-01",
    "iso:country": "GB",
    "wof:name": "ST4 8TW",
    "wof:placetype": "postalcode"
  },
  "geometry": {"coordinates":[-2.18184,52.962582],"type":"Point"}
}
