{
  "type": "Feature",
  "properties": {
    "date:inception_lower": "1980-01-01",
    "date:inception_upper": "1980-01-01",
    "iso:country": "GB",
    "wof:name": "PO11 0BX",
    "wof:placetype": "postalcode"
  },
  "geometry": {"coordinates":[-1.007349,50.787678],"type":"Point"}
}
