{
  "type": "Feature",
  "properties": {
    "iso:country": "GB",
    "wof:name": "PO11 0BX",
    "wof:placetype": "postalcode"
  },
  "geometry": {"coordinates":[-1.007349,50.787678],"type":"Point"}
}
