{
  "type": "Feature",
  "properties": {
    "iso:country":"GB",
    "wof:name":"PO11 0BX",
    "wof:placetype":"postalcode"
},
  "geometry": {"coordinates":[-1.00734942573889,50.78767779675058],"type":"Point"}
}