{
  "type": "Feature",
  "properties": {
    "date:inception_lower": "1995-12-01",
    "date:inception_upper": "1995-12-01",
    "iso:country": "GB",
    "wof:name": "CW11 3HQ",
    "wof:placetype": "postalcode"
  },
  "geometry": {"coordinates":[-2.389857,53.1419],"type":"Point"}
}
