{
  "type": "Feature",
  "properties": {
    "date:inception_lower":"1980-01-01",
    "date:inception_upper":"1980-01-31",
    "iso:country":"GB",
    "wof:name":"WS10 8AL",
    "wof:placetype":"postalcode"
},
  "geometry": {"coordinates":[-2.032169,52.575179],"type":"Point"}
}