{
  "type": "Feature",
  "properties": {
    "iso:country":"GB",
    "wof:name":"WS10 8AL",
    "wof:placetype":"postalcode"
},
  "geometry": {"coordinates":[-2.03216895460212,52.57517867198143],"type":"Point"}
}