{
  "type": "Feature",
  "properties": {
    "iso:country":"GB",
    "wof:name":"AL1 5PG",
    "wof:placetype":"postalcode"
},
  "geometry": {"coordinates":[-0.31041504468563,51.74696246922949],"type":"Point"}
}