{
  "type": "Feature",
  "properties": {
    "iso:country": "GB",
    "wof:name": "ST1 5HE",
    "wof:placetype": "postalcode"
  },
  "geometry": {"coordinates":[-2.177992,53.026356],"type":"Point"}
}
