{
  "type": "Feature",
  "properties": {
    "iso:country":"GB",
    "wof:name":"TR14 8PD",
    "wof:placetype":"postalcode"
},
  "geometry": {"coordinates":[-5.28839972228146,50.22331168950208],"type":"Point"}
}