{
  "type": "Feature",
  "properties": {
    "iso:country": "GB",
    "wof:name": "L36 9SE",
    "wof:placetype": "postalcode"
  },
  "geometry": {"coordinates":[-2.840475,53.411156],"type":"Point"}
}
