{
  "type": "Feature",
  "properties": {
    "iso:country":"GB",
    "wof:name":"CH5 4BZ",
    "wof:placetype":"postalcode"
},
  "geometry": {"coordinates":[-3.07528326174905,53.2235388336259],"type":"Point"}
}