{
  "type": "Feature",
  "properties": {
    "date:inception_lower":"1980-01-01",
    "date:inception_upper":"1980-01-31",
    "iso:country":"GB",
    "wof:name":"DT11 0AB",
    "wof:placetype":"postalcode"
},
  "geometry": {"coordinates":[-2.228541,50.801665],"type":"Point"}
}