{
  "type": "Feature",
  "properties": {
    "iso:country":"GB",
    "wof:name":"EX14 2RU",
    "wof:placetype":"postalcode"
},
  "geometry": {"coordinates":[-3.19342484549027,50.79361525408103],"type":"Point"}
}