{
  "type": "Feature",
  "properties": {
    "iso:country":"GB",
    "wof:name":"CV8 2DT",
    "wof:placetype":"postalcode"
},
  "geometry": {"coordinates":[-1.56559985223855,52.34017833005682],"type":"Point"}
}