{
  "type": "Feature",
  "properties": {
    "iso:country":"GB",
    "wof:name":"RG7 4JB",
    "wof:placetype":"postalcode"
},
  "geometry": {"coordinates":[-1.11408490696351,51.38074498490887],"type":"Point"}
}