{
  "type": "Feature",
  "properties": {
    "iso:country": "GB",
    "wof:name": "BN13 2EY",
    "wof:placetype": "postalcode"
  },
  "geometry": {"coordinates":[-0.401791,50.838195],"type":"Point"}
}
