{
  "type": "Feature",
  "properties": {
    "iso:country":"GB",
    "wof:name":"TR21 0NF",
    "wof:placetype":"postalcode"
},
  "geometry": {"coordinates":[-6.30745391485396,49.92309970248233],"type":"Point"}
}