{
  "type": "Feature",
  "properties": {
    "iso:country":"GB",
    "wof:name":"LL55 3DN",
    "wof:placetype":"postalcode"
},
  "geometry": {"coordinates":[-4.1317032535234,53.14390347420686],"type":"Point"}
}