{
  "type": "Feature",
  "properties": {
    "iso:country": "GB",
    "wof:name": "LL55 3DN",
    "wof:placetype": "postalcode"
  },
  "geometry": {"coordinates":[-4.131709,53.14392],"type":"Point"}
}
