{
  "type": "Feature",
  "properties": {
    "date:inception_lower": "2006-01-01",
    "date:inception_upper": "2006-01-01",
    "iso:country": "GB",
    "wof:name": "CA13 0GU",
    "wof:placetype": "postalcode"
  },
  "geometry": {"coordinates":[-3.375148,54.662468],"type":"Point"}
}
