{
  "type": "Feature",
  "properties": {
    "date:inception_lower": "1980-01-01",
    "date:inception_upper": "1980-01-01",
    "iso:country": "GB",
    "wof:name": "TA4 2JJ",
    "wof:placetype": "postalcode"
  },
  "geometry": {"coordinates":[-3.431219,51.077971],"type":"Point"}
}
