{
  "type": "Feature",
  "properties": {
    "date:inception_lower": "1980-01-01",
    "date:inception_upper": "1980-01-01",
    "iso:country": "GB",
    "wof:name": "WS10 7AQ",
    "wof:placetype": "postalcode"
  },
  "geometry": {"coordinates":[-2.018859,52.551841],"type":"Point"}
}
