{
  "type": "Feature",
  "properties": {
    "iso:country":"GB",
    "wof:name":"WD3 3AE",
    "wof:placetype":"postalcode"
},
  "geometry": {"coordinates":[-0.45641657817412,51.64537483223158],"type":"Point"}
}