{
  "type": "Feature",
  "properties": {
    "date:inception_lower": "1980-01-01",
    "date:inception_upper": "1980-01-01",
    "iso:country": "GB",
    "wof:name": "OL10 2LX",
    "wof:placetype": "postalcode"
  },
  "geometry": {"coordinates":[-2.20603,53.582111],"type":"Point"}
}
