{
  "type": "Feature",
  "properties": {
    "iso:country":"GB",
    "wof:name":"OL10 2LX",
    "wof:placetype":"postalcode"
},
  "geometry": {"coordinates":[-2.20603020901546,53.58211093267236],"type":"Point"}
}