{
  "type": "Feature",
  "properties": {
    "iso:country": "GB",
    "wof:name": "W1W 6RG",
    "wof:placetype": "postalcode"
  },
  "geometry": {"coordinates":[-0.141269,51.519448],"type":"Point"}
}
