{
  "type": "Feature",
  "properties": {
    "iso:country":"GB",
    "wof:name":"W1W 6RG",
    "wof:placetype":"postalcode"
},
  "geometry": {"coordinates":[-0.14126953107307,51.51944753356493],"type":"Point"}
}