{
  "type": "Feature",
  "properties": {
    "iso:country": "GB",
    "wof:name": "L23 8SQ",
    "wof:placetype": "postalcode"
  },
  "geometry": {"coordinates":[-3.038278,53.487829],"type":"Point"}
}
