{
  "type": "Feature",
  "properties": {
    "iso:country": "GB",
    "wof:name": "PL19 9ED",
    "wof:placetype": "postalcode"
  },
  "geometry": {"coordinates":[-4.12869,50.534028],"type":"Point"}
}
