{
  "type": "Feature",
  "properties": {
    "iso:country":"GB",
    "wof:name":"PL19 9ED",
    "wof:placetype":"postalcode"
},
  "geometry": {"coordinates":[-4.12869023670987,50.53402775023069],"type":"Point"}
}