{
  "type": "Feature",
  "properties": {
    "iso:country":"GB",
    "wof:name":"NE3 3AT",
    "wof:placetype":"postalcode"
},
  "geometry": {"coordinates":[-1.64973451283374,55.00655465669313],"type":"Point"}
}