{
  "type": "Feature",
  "properties": {
    "iso:country": "GB",
    "wof:name": "BD13 1QL",
    "wof:placetype": "postalcode"
  },
  "geometry": {"coordinates":[-1.837066,53.769482],"type":"Point"}
}
