{
  "type": "Feature",
  "properties": {
    "date:inception_lower":"1987-04-01",
    "date:inception_upper":"1987-04-30",
    "iso:country":"GB",
    "wof:name":"BD13 1QL",
    "wof:placetype":"postalcode"
},
  "geometry": {"coordinates":[-1.837066,53.769482],"type":"Point"}
}