{
  "type": "Feature",
  "properties": {
    "iso:country":"GB",
    "wof:name":"BD13 1QL",
    "wof:placetype":"postalcode"
},
  "geometry": {"coordinates":[-1.83706653000678,53.76948225560852],"type":"Point"}
}