{
  "type": "Feature",
  "properties": {
    "iso:country":"GB",
    "wof:name":"LS14 5EJ",
    "wof:placetype":"postalcode"
},
  "geometry": {"coordinates":[-1.44529241103135,53.82344351758231],"type":"Point"}
}