{
  "type": "Feature",
  "properties": {
    "iso:country": "GB",
    "wof:name": "SR6 7RJ",
    "wof:placetype": "postalcode"
  },
  "geometry": {"coordinates":[-1.403746,54.951968],"type":"Point"}
}
