{
  "type": "Feature",
  "properties": {
    "date:inception_lower": "2004-11-01",
    "date:inception_upper": "2004-11-01",
    "iso:country": "GB",
    "wof:name": "M30 7EH",
    "wof:placetype": "postalcode"
  },
  "geometry": {"coordinates":[-2.370018,53.480066],"type":"Point"}
}
