{
  "type": "Feature",
  "properties": {
    "iso:country":"GB",
    "wof:name":"NW3 7NJ",
    "wof:placetype":"postalcode"
},
  "geometry": {"coordinates":[-0.19301413879635,51.56207978098842],"type":"Point"}
}