{
  "type": "Feature",
  "properties": {
    "iso:country":"GB",
    "wof:name":"L33 1ZX",
    "wof:placetype":"postalcode"
},
  "geometry": {"coordinates":[-2.88540105643693,53.49384307607749],"type":"Point"}
}