{
  "type": "Feature",
  "properties": {
    "date:inception_lower": "1991-09-01",
    "date:inception_upper": "1991-09-01",
    "iso:country": "GB",
    "wof:name": "SL6 0ND",
    "wof:placetype": "postalcode"
  },
  "geometry": {"coordinates":[-0.673231,51.524377],"type":"Point"}
}
