{
  "type": "Feature",
  "properties": {
    "iso:country": "GB",
    "wof:name": "SL6 0ND",
    "wof:placetype": "postalcode"
  },
  "geometry": {"coordinates":[-0.673231,51.524377],"type":"Point"}
}
