{
  "type": "Feature",
  "properties": {
    "iso:country":"GB",
    "wof:name":"SL6 0ND",
    "wof:placetype":"postalcode"
},
  "geometry": {"coordinates":[-0.67323138059745,51.52437711895362],"type":"Point"}
}