{
  "type": "Feature",
  "properties": {
    "iso:country":"GB",
    "wof:name":"CF47 8HJ",
    "wof:placetype":"postalcode"
},
  "geometry": {"coordinates":[-3.38101197999341,51.75397218658435],"type":"Point"}
}