{
  "type": "Feature",
  "properties": {
    "iso:country": "GB",
    "wof:name": "SW2 5DL",
    "wof:placetype": "postalcode"
  },
  "geometry": {"coordinates":[-0.126378,51.456254],"type":"Point"}
}
