{
  "type": "Feature",
  "properties": {
    "iso:country":"GB",
    "wof:name":"SW2 5DL",
    "wof:placetype":"postalcode"
},
  "geometry": {"coordinates":[-0.12637771122545,51.45625370225164],"type":"Point"}
}