{
  "type": "Feature",
  "properties": {
    "iso:country": "GB",
    "wof:name": "SW2 5DL",
    "wof:placetype": "postalcode"
  },
  "geometry": {"coordinates":[-0.126409,51.456255],"type":"Point"}
}
