{
  "type": "Feature",
  "properties": {
    "iso:country":"GB",
    "wof:name":"GL18 2DW",
    "wof:placetype":"postalcode"
},
  "geometry": {"coordinates":[-2.40025104907428,51.98755495042056],"type":"Point"}
}