{
  "type": "Feature",
  "properties": {
    "date:inception_lower": "1980-01-01",
    "date:inception_upper": "1980-01-01",
    "iso:country": "GB",
    "wof:name": "CF44 8UA",
    "wof:placetype": "postalcode"
  },
  "geometry": {"coordinates":[-3.474552,51.719597],"type":"Point"}
}
