{
  "type": "Feature",
  "properties": {
    "iso:country": "GB",
    "wof:name": "CF44 8UA",
    "wof:placetype": "postalcode"
  },
  "geometry": {"coordinates":[-3.474005,51.719703],"type":"Point"}
}
