{
  "type": "Feature",
  "properties": {
    "iso:country":"GB",
    "wof:name":"CF44 8UA",
    "wof:placetype":"postalcode"
},
  "geometry": {"coordinates":[-3.47454143604855,51.71959305133933],"type":"Point"}
}