{
  "type": "Feature",
  "properties": {
    "iso:country": "GB",
    "wof:name": "TA18 7HT",
    "wof:placetype": "postalcode"
  },
  "geometry": {"coordinates":[-2.798194,50.883508],"type":"Point"}
}
