{
  "type": "Feature",
  "properties": {
    "iso:country":"GB",
    "wof:name":"TA18 7HT",
    "wof:placetype":"postalcode"
},
  "geometry": {"coordinates":[-2.79819433791067,50.88350847274742],"type":"Point"}
}