{
  "type": "Feature",
  "properties": {
    "date:inception_lower": "1992-08-01",
    "date:inception_upper": "1992-08-01",
    "iso:country": "GB",
    "wof:name": "TA18 7HT",
    "wof:placetype": "postalcode"
  },
  "geometry": {"coordinates":[-2.798194,50.883508],"type":"Point"}
}
