{
  "type": "Feature",
  "properties": {
    "iso:country": "GB",
    "wof:name": "TQ1 4PY",
    "wof:placetype": "postalcode"
  },
  "geometry": {"coordinates":[-3.524412,50.483532],"type":"Point"}
}
