{
  "type": "Feature",
  "properties": {
    "date:inception_lower": "2019-03-01",
    "date:inception_upper": "2019-03-01",
    "iso:country": "GB",
    "wof:name": "LS12 2AQ",
    "wof:placetype": "postalcode"
  },
  "geometry": {"coordinates":[-1.606754,53.811352],"type":"Point"}
}
