{
  "type": "Feature",
  "properties": {
    "iso:country": "GB",
    "wof:name": "GL16 8LW",
    "wof:placetype": "postalcode"
  },
  "geometry": {"coordinates":[-2.589854,51.759137],"type":"Point"}
}
