{
  "type": "Feature",
  "properties": {
    "iso:country":"GB",
    "wof:name":"CM77 7FD",
    "wof:placetype":"postalcode"
},
  "geometry": {"coordinates":[0.5290258713819,51.86378461754688],"type":"Point"}
}