{
  "type": "Feature",
  "properties": {
    "date:inception_lower": "2002-07-01",
    "date:inception_upper": "2002-07-01",
    "iso:country": "GB",
    "wof:name": "CM77 7FD",
    "wof:placetype": "postalcode"
  },
  "geometry": {"coordinates":[0.529026,51.863785],"type":"Point"}
}
