{
  "type": "Feature",
  "properties": {
    "date:inception_lower": "2007-04-01",
    "date:inception_upper": "2007-04-01",
    "iso:country": "GB",
    "wof:name": "PO20 7BG",
    "wof:placetype": "postalcode"
  },
  "geometry": {"coordinates":[-0.832793,50.802096],"type":"Point"}
}
