{
  "type": "Feature",
  "properties": {
    "iso:country":"GB",
    "wof:name":"PO20 7BG",
    "wof:placetype":"postalcode"
},
  "geometry": {"coordinates":[-0.83180760071003,50.80233840871126],"type":"Point"}
}