{
  "type": "Feature",
  "properties": {
    "iso:country": "GB",
    "wof:name": "DL8 4RH",
    "wof:placetype": "postalcode"
  },
  "geometry": {"coordinates":[-1.814189,54.280117],"type":"Point"}
}
