{
  "type": "Feature",
  "properties": {
    "iso:country":"GB",
    "wof:name":"DL8 4RH",
    "wof:placetype":"postalcode"
},
  "geometry": {"coordinates":[-1.81418942139706,54.28011706936989],"type":"Point"}
}