{
  "type": "Feature",
  "properties": {
    "date:inception_lower": "2019-09-01",
    "date:inception_upper": "2019-09-01",
    "iso:country": "GB",
    "wof:name": "L40 3AE",
    "wof:placetype": "postalcode"
  },
  "geometry": {"coordinates":[-2.76694,53.625776],"type":"Point"}
}
