{
  "type": "Feature",
  "properties": {
    "iso:country": "GB",
    "wof:name": "L40 3AE",
    "wof:placetype": "postalcode"
  },
  "geometry": {"coordinates":[-2.766342,53.625348],"type":"Point"}
}
