{
  "type": "Feature",
  "properties": {
    "iso:country":"GB",
    "wof:name":"W1G 6EL",
    "wof:placetype":"postalcode"
},
  "geometry": {"coordinates":[-0.1512151234591,51.52087265663675],"type":"Point"}
}