{
  "type": "Feature",
  "properties": {
    "date:inception_lower":"2005-04-01",
    "date:inception_upper":"2005-04-30",
    "iso:country":"GB",
    "wof:name":"CB6 2WX",
    "wof:placetype":"postalcode"
},
  "geometry": {"coordinates":[0.262119,52.407782],"type":"Point"}
}