{
  "type": "Feature",
  "properties": {
    "iso:country": "GB",
    "wof:name": "CB6 2WX",
    "wof:placetype": "postalcode"
  },
  "geometry": {"coordinates":[0.262119,52.407782],"type":"Point"}
}
