{
  "type": "Feature",
  "properties": {
    "iso:country":"GB",
    "wof:name":"CB6 2WX",
    "wof:placetype":"postalcode"
},
  "geometry": {"coordinates":[0.26211868955272,52.40778248873234],"type":"Point"}
}