{
  "type": "Feature",
  "properties": {
    "iso:country": "GB",
    "wof:name": "TS25 1DH",
    "wof:placetype": "postalcode"
  },
  "geometry": {"coordinates":[-1.195994,54.663134],"type":"Point"}
}
