{
  "type": "Feature",
  "properties": {
    "date:inception_lower": "1988-03-01",
    "date:inception_upper": "1988-03-01",
    "iso:country": "GB",
    "wof:name": "TS25 1DH",
    "wof:placetype": "postalcode"
  },
  "geometry": {"coordinates":[-1.195994,54.663134],"type":"Point"}
}
