{
  "type": "Feature",
  "properties": {
    "iso:country": "GB",
    "wof:name": "NN1 4LF",
    "wof:placetype": "postalcode"
  },
  "geometry": {"coordinates":[-0.875875,52.245427],"type":"Point"}
}
