{
  "type": "Feature",
  "properties": {
    "iso:country":"GB",
    "wof:name":"NN1 4LF",
    "wof:placetype":"postalcode"
},
  "geometry": {"coordinates":[-0.87587526932359,52.24542729596133],"type":"Point"}
}