{
  "type": "Feature",
  "properties": {
    "iso:country":"GB",
    "wof:name":"DL5 6QH",
    "wof:placetype":"postalcode"
},
  "geometry": {"coordinates":[-1.60010289463626,54.60834412599816],"type":"Point"}
}