{
  "type": "Feature",
  "properties": {
    "iso:country": "GB",
    "wof:name": "DL5 6QH",
    "wof:placetype": "postalcode"
  },
  "geometry": {"coordinates":[-1.600103,54.608344],"type":"Point"}
}
