{
  "type": "Feature",
  "properties": {
    "iso:country":"GB",
    "wof:name":"BN20 0BT",
    "wof:placetype":"postalcode"
},
  "geometry": {"coordinates":[0.20462187501338,50.75921214367261],"type":"Point"}
}