{
  "type": "Feature",
  "properties": {
    "iso:country": "GB",
    "wof:name": "BN20 0BT",
    "wof:placetype": "postalcode"
  },
  "geometry": {"coordinates":[0.204622,50.759212],"type":"Point"}
}
