{
  "type": "Feature",
  "properties": {
    "iso:country":"GB",
    "wof:name":"HA4 7DH",
    "wof:placetype":"postalcode"
},
  "geometry": {"coordinates":[-0.43502407596706,51.57107804005289],"type":"Point"}
}