{
  "type": "Feature",
  "properties": {
    "iso:country":"GB",
    "wof:name":"EH47 8AB",
    "wof:placetype":"postalcode"
},
  "geometry": {"coordinates":[-3.66034005290583,55.86677610564752],"type":"Point"}
}