{
  "type": "Feature",
  "properties": {
    "iso:country": "GB",
    "wof:name": "B61 0TG",
    "wof:placetype": "postalcode"
  },
  "geometry": {"coordinates":[-2.055461,52.34757],"type":"Point"}
}
