{
  "type": "Feature",
  "properties": {
    "iso:country":"GB",
    "wof:name":"B61 0TG",
    "wof:placetype":"postalcode"
},
  "geometry": {"coordinates":[-2.05546086980087,52.34757049009055],"type":"Point"}
}