{
  "type": "Feature",
  "properties": {
    "date:inception_lower":"1994-12-01",
    "date:inception_upper":"1994-12-31",
    "iso:country":"GB",
    "wof:name":"SO16 9PP",
    "wof:placetype":"postalcode"
},
  "geometry": {"coordinates":[-1.461104,50.931703],"type":"Point"}
}