{
  "type": "Feature",
  "properties": {
    "iso:country":"GB",
    "wof:name":"SO16 9PP",
    "wof:placetype":"postalcode"
},
  "geometry": {"coordinates":[-1.46110397192917,50.9317033725097],"type":"Point"}
}