{
  "type": "Feature",
  "properties": {
    "iso:country":"GB",
    "wof:name":"WV2 4BU",
    "wof:placetype":"postalcode"
},
  "geometry": {"coordinates":[-2.13039945424557,52.5801543150288],"type":"Point"}
}