{
  "type": "Feature",
  "properties": {
    "iso:country":"GB",
    "wof:name":"PE30 2AF",
    "wof:placetype":"postalcode"
},
  "geometry": {"coordinates":[0.39948145583421,52.75916386645676],"type":"Point"}
}