{
  "type": "Feature",
  "properties": {
    "iso:country": "GB",
    "wof:name": "PE30 2AF",
    "wof:placetype": "postalcode"
  },
  "geometry": {"coordinates":[0.399482,52.759164],"type":"Point"}
}
