{
  "type": "Feature",
  "properties": {
    "iso:country":"GB",
    "wof:name":"CW9 8AS",
    "wof:placetype":"postalcode"
},
  "geometry": {"coordinates":[-2.51267421181664,53.25279847266626],"type":"Point"}
}