{
  "type": "Feature",
  "properties": {
    "iso:country":"GB",
    "wof:name":"G78 3HU",
    "wof:placetype":"postalcode"
},
  "geometry": {"coordinates":[-4.428050949819,55.77839470427394],"type":"Point"}
}