{
  "type": "Feature",
  "properties": {
    "date:inception_lower":"1999-06-01",
    "date:inception_upper":"1999-06-30",
    "iso:country":"GB",
    "wof:name":"CF14 2TF",
    "wof:placetype":"postalcode"
},
  "geometry": {"coordinates":[-3.230324,51.515298],"type":"Point"}
}