{
  "type": "Feature",
  "properties": {
    "iso:country": "GB",
    "wof:name": "CF14 2TF",
    "wof:placetype": "postalcode"
  },
  "geometry": {"coordinates":[-3.230324,51.515298],"type":"Point"}
}
