{
  "type": "Feature",
  "properties": {
    "iso:country":"GB",
    "wof:name":"DA3 8JQ",
    "wof:placetype":"postalcode"
},
  "geometry": {"coordinates":[0.30801796126079,51.36342043907771],"type":"Point"}
}