{
  "type": "Feature",
  "properties": {
    "iso:country":"GB",
    "wof:name":"PO20 2JH",
    "wof:placetype":"postalcode"
},
  "geometry": {"coordinates":[-0.71696362599806,50.85187032015835],"type":"Point"}
}