{
  "type": "Feature",
  "properties": {
    "iso:country": "GB",
    "wof:name": "PO20 2JH",
    "wof:placetype": "postalcode"
  },
  "geometry": {"coordinates":[-0.716964,50.85187],"type":"Point"}
}
