{
  "type": "Feature",
  "properties": {
    "iso:country":"GB",
    "wof:name":"BS8 2XZ",
    "wof:placetype":"postalcode"
},
  "geometry": {"coordinates":[-2.61480540365989,51.46977796137335],"type":"Point"}
}