{
  "type": "Feature",
  "properties": {
    "iso:country":"GB",
    "wof:name":"SY10 7LY",
    "wof:placetype":"postalcode"
},
  "geometry": {"coordinates":[-3.08880301211158,52.92398471194974],"type":"Point"}
}