{
  "type": "Feature",
  "properties": {
    "iso:country": "GB",
    "wof:name": "BS16 5HU",
    "wof:placetype": "postalcode"
  },
  "geometry": {"coordinates":[-2.509026,51.482154],"type":"Point"}
}
