{
  "type": "Feature",
  "properties": {
    "date:inception_lower": "1999-12-01",
    "date:inception_upper": "1999-12-01",
    "iso:country": "GB",
    "wof:name": "CV47 2BH",
    "wof:placetype": "postalcode"
  },
  "geometry": {"coordinates":[-1.404237,52.25811],"type":"Point"}
}
