{
  "type": "Feature",
  "properties": {
    "iso:country": "GB",
    "wof:name": "SP10 3JN",
    "wof:placetype": "postalcode"
  },
  "geometry": {"coordinates":[-1.491241,51.21324],"type":"Point"}
}
