{
  "type": "Feature",
  "properties": {
    "iso:country":"GB",
    "wof:name":"EN7 6SX",
    "wof:placetype":"postalcode"
},
  "geometry": {"coordinates":[-0.07355180412597,51.71287042801905],"type":"Point"}
}