{
  "type": "Feature",
  "properties": {
    "date:inception_lower": "1980-01-01",
    "date:inception_upper": "1980-01-01",
    "iso:country": "GB",
    "wof:name": "SL1 6EY",
    "wof:placetype": "postalcode"
  },
  "geometry": {"coordinates":[-0.650394,51.524036],"type":"Point"}
}
