{
  "type": "Feature",
  "properties": {
    "iso:country":"GB",
    "wof:name":"SL1 6EY",
    "wof:placetype":"postalcode"
},
  "geometry": {"coordinates":[-0.65039412787029,51.52403571465263],"type":"Point"}
}