{
  "type": "Feature",
  "properties": {
    "date:inception_lower": "1980-01-01",
    "date:inception_upper": "1980-01-01",
    "iso:country": "GB",
    "wof:name": "EH4 5HR",
    "wof:placetype": "postalcode"
  },
  "geometry": {"coordinates":[-3.274343,55.967552],"type":"Point"}
}
