{
  "type": "Feature",
  "properties": {
    "iso:country":"GB",
    "wof:name":"S70 4ET",
    "wof:placetype":"postalcode"
},
  "geometry": {"coordinates":[-1.47977077064182,53.54118741998006],"type":"Point"}
}