{
  "type": "Feature",
  "properties": {
    "date:inception_lower": "1997-06-01",
    "date:inception_upper": "1997-06-01",
    "iso:country": "GB",
    "wof:name": "S35 8QT",
    "wof:placetype": "postalcode"
  },
  "geometry": {"coordinates":[-1.505725,53.440086],"type":"Point"}
}
