{
  "type": "Feature",
  "properties": {
    "date:inception_lower":"1996-06-01",
    "date:inception_upper":"1996-06-30",
    "iso:country":"GB",
    "wof:name":"AB54 8BL",
    "wof:placetype":"postalcode"
},
  "geometry": {"coordinates":[-2.783282,57.445033],"type":"Point"}
}