{
  "type": "Feature",
  "properties": {
    "iso:country":"GB",
    "wof:name":"SA1 2AE",
    "wof:placetype":"postalcode"
},
  "geometry": {"coordinates":[-3.94002537959109,51.61998063707762],"type":"Point"}
}