{
  "type": "Feature",
  "properties": {
    "iso:country": "GB",
    "wof:name": "LS28 6HX",
    "wof:placetype": "postalcode"
  },
  "geometry": {"coordinates":[-1.6608,53.809425],"type":"Point"}
}
