{
  "type": "Feature",
  "properties": {
    "iso:country":"GB",
    "wof:name":"G74 4LY",
    "wof:placetype":"postalcode"
},
  "geometry": {"coordinates":[-4.17447036150741,55.76454013805161],"type":"Point"}
}