{
  "type": "Feature",
  "properties": {
    "iso:country": "GB",
    "wof:name": "G74 4LY",
    "wof:placetype": "postalcode"
  },
  "geometry": {"coordinates":[-4.17447,55.76454],"type":"Point"}
}
