{
  "type": "Feature",
  "properties": {
    "iso:country": "GB",
    "wof:name": "CF15 8LA",
    "wof:placetype": "postalcode"
  },
  "geometry": {"coordinates":[-3.262642,51.53757],"type":"Point"}
}
