{
  "type": "Feature",
  "properties": {
    "iso:country":"GB",
    "wof:name":"CF15 8LA",
    "wof:placetype":"postalcode"
},
  "geometry": {"coordinates":[-3.26280303269996,51.53801666293479],"type":"Point"}
}