{
  "type": "Feature",
  "properties": {
    "date:inception_lower":"1999-06-01",
    "date:inception_upper":"1999-06-30",
    "iso:country":"GB",
    "wof:name":"CF15 8LA",
    "wof:placetype":"postalcode"
},
  "geometry": {"coordinates":[-3.262803,51.538017],"type":"Point"}
}