{
  "type": "Feature",
  "properties": {
    "date:inception_lower": "1999-06-01",
    "date:inception_upper": "1999-06-01",
    "iso:country": "GB",
    "wof:name": "CF15 8LA",
    "wof:placetype": "postalcode"
  },
  "geometry": {"coordinates":[-3.263141,51.537915],"type":"Point"}
}
