{
  "type": "Feature",
  "properties": {
    "iso:country": "GB",
    "wof:name": "NN4 0TA",
    "wof:placetype": "postalcode"
  },
  "geometry": {"coordinates":[-0.909617,52.21095],"type":"Point"}
}
