{
  "type": "Feature",
  "properties": {
    "iso:country":"GB",
    "wof:name":"CM77 7LJ",
    "wof:placetype":"postalcode"
},
  "geometry": {"coordinates":[0.53412105368964,51.86734406610063],"type":"Point"}
}