{
  "type": "Feature",
  "properties": {
    "iso:country": "GB",
    "wof:name": "CM77 7LJ",
    "wof:placetype": "postalcode"
  },
  "geometry": {"coordinates":[0.534121,51.867344],"type":"Point"}
}
