{
  "type": "Feature",
  "properties": {
    "date:inception_lower":"1995-12-01",
    "date:inception_upper":"1995-12-31",
    "iso:country":"GB",
    "wof:name":"S81 9TG",
    "wof:placetype":"postalcode"
},
  "geometry": {"coordinates":[-1.11576,53.360255],"type":"Point"}
}