{
  "type": "Feature",
  "properties": {
    "iso:country":"GB",
    "wof:name":"S81 9TG",
    "wof:placetype":"postalcode"
},
  "geometry": {"coordinates":[-1.11576018089305,53.36025465916236],"type":"Point"}
}