{
  "type": "Feature",
  "properties": {
    "iso:country": "GB",
    "wof:name": "CF32 9TF",
    "wof:placetype": "postalcode"
  },
  "geometry": {"coordinates":[-3.593893,51.539975],"type":"Point"}
}
