{
  "type": "Feature",
  "properties": {
    "date:inception_lower":"2017-08-01",
    "date:inception_upper":"2017-08-31",
    "iso:country":"GB",
    "wof:name":"CF32 9TF",
    "wof:placetype":"postalcode"
},
  "geometry": {"coordinates":[-3.593893,51.539975],"type":"Point"}
}