{
  "type": "Feature",
  "properties": {
    "date:inception_lower":"2009-04-01",
    "date:inception_upper":"2009-04-30",
    "iso:country":"GB",
    "wof:name":"LL65 2FE",
    "wof:placetype":"postalcode"
},
  "geometry": {"coordinates":[-4.633527,53.306997],"type":"Point"}
}