{
  "type": "Feature",
  "properties": {
    "iso:country": "GB",
    "wof:name": "LL65 2FE",
    "wof:placetype": "postalcode"
  },
  "geometry": {"coordinates":[-4.633527,53.306997],"type":"Point"}
}
