{
  "type": "Feature",
  "properties": {
    "date:inception_lower": "1980-01-01",
    "date:inception_upper": "1980-01-01",
    "iso:country": "GB",
    "wof:name": "GL50 4HB",
    "wof:placetype": "postalcode"
  },
  "geometry": {"coordinates":[-2.075687,51.907897],"type":"Point"}
}
