{
  "type": "Feature",
  "properties": {
    "iso:country":"GB",
    "wof:name":"GL13 9UE",
    "wof:placetype":"postalcode"
},
  "geometry": {"coordinates":[-2.48162630812743,51.71586587268273],"type":"Point"}
}