{
  "type": "Feature",
  "properties": {
    "iso:country":"GB",
    "wof:name":"M26 4WQ",
    "wof:placetype":"postalcode"
},
  "geometry": {"coordinates":[-2.34802835271659,53.57316202760276],"type":"Point"}
}