{
  "type": "Feature",
  "properties": {
    "iso:country": "GB",
    "wof:name": "M26 4WQ",
    "wof:placetype": "postalcode"
  },
  "geometry": {"coordinates":[-2.348028,53.573162],"type":"Point"}
}
