{
  "type": "Feature",
  "properties": {
    "date:inception_lower": "1994-05-01",
    "date:inception_upper": "1994-05-01",
    "iso:country": "GB",
    "wof:name": "M26 4WQ",
    "wof:placetype": "postalcode"
  },
  "geometry": {"coordinates":[-2.348012,53.573205],"type":"Point"}
}
