{
  "type": "Feature",
  "properties": {
    "iso:country": "GB",
    "wof:name": "OX14 4BE",
    "wof:placetype": "postalcode"
  },
  "geometry": {"coordinates":[-1.280972,51.63769],"type":"Point"}
}
