{
  "type": "Feature",
  "properties": {
    "date:inception_lower": "1980-01-01",
    "date:inception_upper": "1980-01-01",
    "iso:country": "GB",
    "wof:name": "OX14 4BE",
    "wof:placetype": "postalcode"
  },
  "geometry": {"coordinates":[-1.280972,51.63769],"type":"Point"}
}
