{
  "type": "Feature",
  "properties": {
    "date:inception_lower": "1980-01-01",
    "date:inception_upper": "1980-01-01",
    "iso:country": "GB",
    "wof:name": "PL30 4EF",
    "wof:placetype": "postalcode"
  },
  "geometry": {"coordinates":[-4.640031,50.477101],"type":"Point"}
}
