{
  "type": "Feature",
  "properties": {
    "date:inception_lower": "1980-01-01",
    "date:inception_upper": "1980-01-01",
    "iso:country": "GB",
    "wof:name": "SA44 5LD",
    "wof:placetype": "postalcode"
  },
  "geometry": {"coordinates":[-4.382587,52.076054],"type":"Point"}
}
