{
  "type": "Feature",
  "properties": {
    "iso:country": "GB",
    "wof:name": "SA44 5LD",
    "wof:placetype": "postalcode"
  },
  "geometry": {"coordinates":[-4.382587,52.076054],"type":"Point"}
}
