{
  "type": "Feature",
  "properties": {
    "iso:country":"GB",
    "wof:name":"SA44 5LD",
    "wof:placetype":"postalcode"
},
  "geometry": {"coordinates":[-4.38258655533282,52.07605390240526],"type":"Point"}
}