{
  "type": "Feature",
  "properties": {
    "iso:country": "GB",
    "wof:name": "TA10 0ET",
    "wof:placetype": "postalcode"
  },
  "geometry": {"coordinates":[-2.868813,51.022669],"type":"Point"}
}
