{
  "type": "Feature",
  "properties": {
    "iso:country":"GB",
    "wof:name":"TA10 0ET",
    "wof:placetype":"postalcode"
},
  "geometry": {"coordinates":[-2.8689641341029,51.02267480149678],"type":"Point"}
}