{
  "type": "Feature",
  "properties": {
    "iso:country":"GB",
    "wof:name":"RG24 9LA",
    "wof:placetype":"postalcode"
},
  "geometry": {"coordinates":[-1.11491211482403,51.29606507310032],"type":"Point"}
}