{
  "type": "Feature",
  "properties": {
    "iso:country": "GB",
    "wof:name": "RG24 9LA",
    "wof:placetype": "postalcode"
  },
  "geometry": {"coordinates":[-1.114718,51.296217],"type":"Point"}
}
