{
  "type": "Feature",
  "properties": {
    "iso:country":"GB",
    "wof:name":"CW9 8DJ",
    "wof:placetype":"postalcode"
},
  "geometry": {"coordinates":[-2.50659094594874,53.24408729148725],"type":"Point"}
}