{
  "type": "Feature",
  "properties": {
    "date:inception_lower": "1980-01-01",
    "date:inception_upper": "1980-01-01",
    "iso:country": "GB",
    "wof:name": "CB4 2RW",
    "wof:placetype": "postalcode"
  },
  "geometry": {"coordinates":[0.127123,52.227693],"type":"Point"}
}
