{
  "type": "Feature",
  "properties": {
    "iso:country":"GB",
    "wof:name":"ME13 0LL",
    "wof:placetype":"postalcode"
},
  "geometry": {"coordinates":[0.88729731551299,51.29134259881283],"type":"Point"}
}