{
  "type": "Feature",
  "properties": {
    "date:inception_lower": "2022-02-01",
    "date:inception_upper": "2022-02-01",
    "iso:country": "GB",
    "wof:name": "SO50 9SE",
    "wof:placetype": "postalcode"
  },
  "geometry": {"coordinates":[-1.357291,50.970521],"type":"Point"}
}
