{
  "type": "Feature",
  "properties": {
    "iso:country": "GB",
    "wof:name": "DE6 3GN",
    "wof:placetype": "postalcode"
  },
  "geometry": {"coordinates":[-1.622967,52.973487],"type":"Point"}
}
