{
  "type": "Feature",
  "properties": {
    "date:inception_lower":"2016-04-01",
    "date:inception_upper":"2016-04-30",
    "iso:country":"GB",
    "wof:name":"DE6 3GN",
    "wof:placetype":"postalcode"
},
  "geometry": {"coordinates":[-1.622967,52.973487],"type":"Point"}
}