{
  "type": "Feature",
  "properties": {
    "iso:country": "GB",
    "wof:name": "LA12 9DT",
    "wof:placetype": "postalcode"
  },
  "geometry": {"coordinates":[-3.074617,54.193869],"type":"Point"}
}
