{
  "type": "Feature",
  "properties": {
    "date:inception_lower": "1980-01-01",
    "date:inception_upper": "1980-01-01",
    "iso:country": "GB",
    "wof:name": "G78 4DF",
    "wof:placetype": "postalcode"
  },
  "geometry": {"coordinates":[-4.499175,55.764902],"type":"Point"}
}
