{
  "type": "Feature",
  "properties": {
    "iso:country": "GB",
    "wof:name": "FK3 9BU",
    "wof:placetype": "postalcode"
  },
  "geometry": {"coordinates":[-3.706941,56.015256],"type":"Point"}
}
