{
  "type": "Feature",
  "properties": {
    "iso:country":"GB",
    "wof:name":"FK3 9BU",
    "wof:placetype":"postalcode"
},
  "geometry": {"coordinates":[-3.70694072954875,56.01525627680884],"type":"Point"}
}