{
  "type": "Feature",
  "properties": {
    "iso:country":"GB",
    "wof:name":"GU33 6BU",
    "wof:placetype":"postalcode"
},
  "geometry": {"coordinates":[-0.89615149208664,51.09983037567505],"type":"Point"}
}