{
  "type": "Feature",
  "properties": {
    "iso:country":"GB",
    "wof:name":"LL46 2NX",
    "wof:placetype":"postalcode"
},
  "geometry": {"coordinates":[-4.11165900219589,52.86596736863945],"type":"Point"}
}