{
  "type": "Feature",
  "properties": {
    "iso:country": "GB",
    "wof:name": "S62 6BS",
    "wof:placetype": "postalcode"
  },
  "geometry": {"coordinates":[-1.338974,53.453429],"type":"Point"}
}
