{
  "type": "Feature",
  "properties": {
    "date:inception_lower":"1995-12-01",
    "date:inception_upper":"1995-12-31",
    "iso:country":"GB",
    "wof:name":"S62 6BS",
    "wof:placetype":"postalcode"
},
  "geometry": {"coordinates":[-1.338974,53.453429],"type":"Point"}
}