{
  "type": "Feature",
  "properties": {
    "iso:country":"GB",
    "wof:name":"BS34 6DR",
    "wof:placetype":"postalcode"
},
  "geometry": {"coordinates":[-2.56165878278662,51.53238315056706],"type":"Point"}
}