{
  "type": "Feature",
  "properties": {
    "iso:country": "GB",
    "wof:name": "CW7 2YD",
    "wof:placetype": "postalcode"
  },
  "geometry": {"coordinates":[-2.548652,53.190039],"type":"Point"}
}
