{
  "type": "Feature",
  "properties": {
    "iso:country":"GB",
    "wof:name":"CW7 2YD",
    "wof:placetype":"postalcode"
},
  "geometry": {"coordinates":[-2.54865238557541,53.1900392495535],"type":"Point"}
}