{
  "type": "Feature",
  "properties": {
    "iso:country":"GB",
    "wof:name":"GL52 8AA",
    "wof:placetype":"postalcode"
},
  "geometry": {"coordinates":[-2.05942320112208,51.94218814567799],"type":"Point"}
}