{
  "type": "Feature",
  "properties": {
    "iso:country":"GB",
    "wof:name":"M29 7PX",
    "wof:placetype":"postalcode"
},
  "geometry": {"coordinates":[-2.45715041197395,53.51021715191942],"type":"Point"}
}