{
  "type": "Feature",
  "properties": {
    "date:inception_lower":"1983-01-01",
    "date:inception_upper":"1983-01-31",
    "iso:country":"GB",
    "wof:name":"M29 7PX",
    "wof:placetype":"postalcode"
},
  "geometry": {"coordinates":[-2.45715,53.510217],"type":"Point"}
}