{
  "type": "Feature",
  "properties": {
    "iso:country":"GB",
    "wof:name":"ML6 7JX",
    "wof:placetype":"postalcode"
},
  "geometry": {"coordinates":[-3.93217917222219,55.87922625387064],"type":"Point"}
}