{
  "type": "Feature",
  "properties": {
    "date:inception_lower": "1980-01-01",
    "date:inception_upper": "1980-01-01",
    "iso:country": "GB",
    "wof:name": "ML6 7JX",
    "wof:placetype": "postalcode"
  },
  "geometry": {"coordinates":[-3.932179,55.879226],"type":"Point"}
}
