{
  "type": "Feature",
  "properties": {
    "iso:country":"GB",
    "wof:name":"WA14 2QP",
    "wof:placetype":"postalcode"
},
  "geometry": {"coordinates":[-2.35526631338913,53.38443642258504],"type":"Point"}
}