{
  "type": "Feature",
  "properties": {
    "iso:country":"GB",
    "wof:name":"WA7 1AP",
    "wof:placetype":"postalcode"
},
  "geometry": {"coordinates":[-2.73066755691787,53.34173929169501],"type":"Point"}
}