{
  "type": "Feature",
  "properties": {
    "iso:country": "GB",
    "wof:name": "PO19 8HA",
    "wof:placetype": "postalcode"
  },
  "geometry": {"coordinates":[-0.766354,50.829974],"type":"Point"}
}
