{
  "type": "Feature",
  "properties": {
    "iso:country":"GB",
    "wof:name":"CO3 9BY",
    "wof:placetype":"postalcode"
},
  "geometry": {"coordinates":[0.8527266932296,51.88797985991375],"type":"Point"}
}