{
  "type": "Feature",
  "properties": {
    "iso:country":"GB",
    "wof:name":"G12 0HS",
    "wof:placetype":"postalcode"
},
  "geometry": {"coordinates":[-4.30403620040061,55.88973955742664],"type":"Point"}
}