{
  "type": "Feature",
  "properties": {
    "iso:country":"GB",
    "wof:name":"DD7 6DH",
    "wof:placetype":"postalcode"
},
  "geometry": {"coordinates":[-2.70529840414182,56.50305796074053],"type":"Point"}
}