{
  "type": "Feature",
  "properties": {
    "date:inception_lower":"1980-01-01",
    "date:inception_upper":"1980-01-31",
    "iso:country":"GB",
    "wof:name":"DD7 6DH",
    "wof:placetype":"postalcode"
},
  "geometry": {"coordinates":[-2.705298,56.503058],"type":"Point"}
}