{
  "type": "Feature",
  "properties": {
    "iso:country": "GB",
    "wof:name": "BB9 8NE",
    "wof:placetype": "postalcode"
  },
  "geometry": {"coordinates":[-2.217189,53.848822],"type":"Point"}
}
