{
  "type": "Feature",
  "properties": {
    "iso:country":"GB",
    "wof:name":"BB9 8NE",
    "wof:placetype":"postalcode"
},
  "geometry": {"coordinates":[-2.21718901712987,53.84882199895253],"type":"Point"}
}