{
  "type": "Feature",
  "properties": {
    "date:inception_lower":"1991-09-01",
    "date:inception_upper":"1991-09-30",
    "iso:country":"GB",
    "wof:name":"NR10 5JP",
    "wof:placetype":"postalcode"
},
  "geometry": {"coordinates":[1.341482,52.761021],"type":"Point"}
}