{
  "type": "Feature",
  "properties": {
    "iso:country":"GB",
    "wof:name":"B32 1DD",
    "wof:placetype":"postalcode"
},
  "geometry": {"coordinates":[-2.00156032434925,52.46026520576536],"type":"Point"}
}