{
  "type": "Feature",
  "properties": {
    "date:inception_lower": "1980-01-01",
    "date:inception_upper": "1980-01-01",
    "iso:country": "GB",
    "wof:name": "B32 1DD",
    "wof:placetype": "postalcode"
  },
  "geometry": {"coordinates":[-2.00156,52.460265],"type":"Point"}
}
