{
  "type": "Feature",
  "properties": {
    "iso:country": "GB",
    "wof:name": "TA19 0PA",
    "wof:placetype": "postalcode"
  },
  "geometry": {"coordinates":[-2.891951,50.907613],"type":"Point"}
}
