{
  "type": "Feature",
  "properties": {
    "iso:country":"GB",
    "wof:name":"TA19 0PA",
    "wof:placetype":"postalcode"
},
  "geometry": {"coordinates":[-2.89195126704333,50.90761316752399],"type":"Point"}
}