{
  "type": "Feature",
  "properties": {
    "date:inception_lower":"1980-01-01",
    "date:inception_upper":"1980-01-31",
    "iso:country":"GB",
    "wof:name":"TA19 0PA",
    "wof:placetype":"postalcode"
},
  "geometry": {"coordinates":[-2.891951,50.907613],"type":"Point"}
}