{
  "type": "Feature",
  "properties": {
    "iso:country": "GB",
    "wof:name": "EX13 5RE",
    "wof:placetype": "postalcode"
  },
  "geometry": {"coordinates":[-2.996792,50.773843],"type":"Point"}
}
