{
  "type": "Feature",
  "properties": {
    "iso:country":"GB",
    "wof:name":"DN32 8NR",
    "wof:placetype":"postalcode"
},
  "geometry": {"coordinates":[-0.04416785027747,53.55867083716453],"type":"Point"}
}