{
  "type": "Feature",
  "properties": {
    "date:inception_lower": "1993-01-01",
    "date:inception_upper": "1993-01-01",
    "iso:country": "GB",
    "wof:name": "HD4 6NU",
    "wof:placetype": "postalcode"
  },
  "geometry": {"coordinates":[-1.778267,53.638647],"type":"Point"}
}
