{
  "type": "Feature",
  "properties": {
    "iso:country":"GB",
    "wof:name":"BL2 5AJ",
    "wof:placetype":"postalcode"
},
  "geometry": {"coordinates":[-2.39241278926046,53.5847813390461],"type":"Point"}
}