{
  "type": "Feature",
  "properties": {
    "iso:country":"GB",
    "wof:name":"LU2 8PN",
    "wof:placetype":"postalcode"
},
  "geometry": {"coordinates":[-0.34017068618183,51.87091681318752],"type":"Point"}
}