{
  "type": "Feature",
  "properties": {
    "date:inception_lower": "2023-12-01",
    "date:inception_upper": "2023-12-01",
    "iso:country": "GB",
    "wof:name": "GL2 4EX",
    "wof:placetype": "postalcode"
  },
  "geometry": {"coordinates":[-2.279794,51.805781],"type":"Point"}
}
