{
  "type": "Feature",
  "properties": {
    "iso:country":"GB",
    "wof:name":"PE19 1DS",
    "wof:placetype":"postalcode"
},
  "geometry": {"coordinates":[-0.26262820433387,52.23119744595881],"type":"Point"}
}