{
  "type": "Feature",
  "properties": {
    "iso:country":"GB",
    "wof:name":"PE12 6AU",
    "wof:placetype":"postalcode"
},
  "geometry": {"coordinates":[-0.13979167568072,52.77925960713547],"type":"Point"}
}