{
  "type": "Feature",
  "properties": {
    "iso:country": "GB",
    "wof:name": "PE12 6AU",
    "wof:placetype": "postalcode"
  },
  "geometry": {"coordinates":[-0.139792,52.77926],"type":"Point"}
}
