{
  "type": "Feature",
  "properties": {
    "date:inception_lower":"1997-12-01",
    "date:inception_upper":"1997-12-31",
    "iso:country":"GB",
    "wof:name":"HR7 4XY",
    "wof:placetype":"postalcode"
},
  "geometry": {"coordinates":[-2.472853,52.247815],"type":"Point"}
}