{
  "type": "Feature",
  "properties": {
    "iso:country": "GB",
    "wof:name": "HR7 4XY",
    "wof:placetype": "postalcode"
  },
  "geometry": {"coordinates":[-2.472853,52.247815],"type":"Point"}
}
