{
  "type": "Feature",
  "properties": {
    "iso:country":"GB",
    "wof:name":"SO51 0GE",
    "wof:placetype":"postalcode"
},
  "geometry": {"coordinates":[-1.51813408842901,50.99542056042642],"type":"Point"}
}