{
  "type": "Feature",
  "properties": {
    "date:inception_lower": "2005-10-01",
    "date:inception_upper": "2005-10-01",
    "iso:country": "GB",
    "wof:name": "SO51 0GE",
    "wof:placetype": "postalcode"
  },
  "geometry": {"coordinates":[-1.518122,50.995629],"type":"Point"}
}
