{
  "type": "Feature",
  "properties": {
    "iso:country": "GB",
    "wof:name": "SO51 0GE",
    "wof:placetype": "postalcode"
  },
  "geometry": {"coordinates":[-1.518122,50.995629],"type":"Point"}
}
