{
  "type": "Feature",
  "properties": {
    "iso:country":"GB",
    "wof:name":"N15 4DW",
    "wof:placetype":"postalcode"
},
  "geometry": {"coordinates":[-0.06759230033333,51.58462176786938],"type":"Point"}
}