{
  "type": "Feature",
  "properties": {
    "date:inception_lower": "1987-04-01",
    "date:inception_upper": "1987-04-01",
    "iso:country": "GB",
    "wof:name": "S75 1AW",
    "wof:placetype": "postalcode"
  },
  "geometry": {"coordinates":[-1.487591,53.560906],"type":"Point"}
}
