{
  "type": "Feature",
  "properties": {
    "iso:country":"GB",
    "wof:name":"S75 1AW",
    "wof:placetype":"postalcode"
},
  "geometry": {"coordinates":[-1.48759076648615,53.56090583315597],"type":"Point"}
}