{
  "type": "Feature",
  "properties": {
    "iso:country":"GB",
    "wof:name":"NW2 3AG",
    "wof:placetype":"postalcode"
},
  "geometry": {"coordinates":[-0.21521102700016,51.55525259650131],"type":"Point"}
}