{
  "type": "Feature",
  "properties": {
    "iso:country": "GB",
    "wof:name": "HA2 8AT",
    "wof:placetype": "postalcode"
  },
  "geometry": {"coordinates":[-0.355762,51.566649],"type":"Point"}
}
