{
  "type": "Feature",
  "properties": {
    "date:inception_lower": "1980-01-01",
    "date:inception_upper": "1980-01-01",
    "iso:country": "GB",
    "wof:name": "HA2 8AT",
    "wof:placetype": "postalcode"
  },
  "geometry": {"coordinates":[-0.355762,51.566649],"type":"Point"}
}
