{
  "type": "Feature",
  "properties": {
    "iso:country":"GB",
    "wof:name":"HA2 8AT",
    "wof:placetype":"postalcode"
},
  "geometry": {"coordinates":[-0.35576174208363,51.56664919880475],"type":"Point"}
}