{
  "type": "Feature",
  "properties": {
    "iso:country": "GB",
    "wof:name": "TS15 9GB",
    "wof:placetype": "postalcode"
  },
  "geometry": {"coordinates":[-1.353431,54.491609],"type":"Point"}
}
