{
  "type": "Feature",
  "properties": {
    "iso:country":"GB",
    "wof:name":"SW6 7HY",
    "wof:placetype":"postalcode"
},
  "geometry": {"coordinates":[-0.20723446542837,51.48182474860707],"type":"Point"}
}