{
  "type": "Feature",
  "properties": {
    "iso:country":"GB",
    "wof:name":"TQ3 2BL",
    "wof:placetype":"postalcode"
},
  "geometry": {"coordinates":[-3.56324911980942,50.43834528710852],"type":"Point"}
}