{
  "type": "Feature",
  "properties": {
    "iso:country": "GB",
    "wof:name": "SS15 5NN",
    "wof:placetype": "postalcode"
  },
  "geometry": {"coordinates":[0.431005,51.574119],"type":"Point"}
}
