{
  "type": "Feature",
  "properties": {
    "iso:country":"GB",
    "wof:name":"L21 9LQ",
    "wof:placetype":"postalcode"
},
  "geometry": {"coordinates":[-3.00381483334109,53.47836305213804],"type":"Point"}
}