{
  "type": "Feature",
  "properties": {
    "iso:country": "GB",
    "wof:name": "EH25 9QB",
    "wof:placetype": "postalcode"
  },
  "geometry": {"coordinates":[-3.171239,55.842131],"type":"Point"}
}
