{
  "type": "Feature",
  "properties": {
    "iso:country":"GB",
    "wof:name":"EH25 9QB",
    "wof:placetype":"postalcode"
},
  "geometry": {"coordinates":[-3.17123923374903,55.84213092257563],"type":"Point"}
}