{
  "type": "Feature",
  "properties": {
    "iso:country": "GB",
    "wof:name": "PO18 8DX",
    "wof:placetype": "postalcode"
  },
  "geometry": {"coordinates":[-0.855318,50.859991],"type":"Point"}
}
