{
  "type": "Feature",
  "properties": {
    "iso:country":"GB",
    "wof:name":"PO18 8DX",
    "wof:placetype":"postalcode"
},
  "geometry": {"coordinates":[-0.85531822674323,50.85999083137504],"type":"Point"}
}