{
  "type": "Feature",
  "properties": {
    "iso:country": "GB",
    "wof:name": "CB6 3AE",
    "wof:placetype": "postalcode"
  },
  "geometry": {"coordinates":[0.246674,52.404175],"type":"Point"}
}
