{
  "type": "Feature",
  "properties": {
    "iso:country":"GB",
    "wof:name":"CF5 2JP",
    "wof:placetype":"postalcode"
},
  "geometry": {"coordinates":[-3.23158840811351,51.49162662117305],"type":"Point"}
}