{
  "type": "Feature",
  "properties": {
    "iso:country":"GB",
    "wof:name":"LE2 4AG",
    "wof:placetype":"postalcode"
},
  "geometry": {"coordinates":[-1.0871875625978,52.60429198832837],"type":"Point"}
}