{
  "type": "Feature",
  "properties": {
    "iso:country":"GB",
    "wof:name":"M30 7BD",
    "wof:placetype":"postalcode"
},
  "geometry": {"coordinates":[-2.36214184218052,53.47524518673077],"type":"Point"}
}