{
  "type": "Feature",
  "properties": {
    "date:inception_lower": "1980-01-01",
    "date:inception_upper": "1980-01-01",
    "iso:country": "GB",
    "wof:name": "OX10 8EH",
    "wof:placetype": "postalcode"
  },
  "geometry": {"coordinates":[-1.107781,51.597515],"type":"Point"}
}
