{
  "type": "Feature",
  "properties": {
    "iso:country":"GB",
    "wof:name":"OX10 8EH",
    "wof:placetype":"postalcode"
},
  "geometry": {"coordinates":[-1.10778137767479,51.59751461599873],"type":"Point"}
}