{
  "type": "Feature",
  "properties": {
    "iso:country":"GB",
    "wof:name":"BS34 7QN",
    "wof:placetype":"postalcode"
},
  "geometry": {"coordinates":[-2.57805447377615,51.50653373587261],"type":"Point"}
}