{
  "type": "Feature",
  "properties": {
    "iso:country":"GB",
    "wof:name":"EH34 5HB",
    "wof:placetype":"postalcode"
},
  "geometry": {"coordinates":[-2.89628406190147,55.91103132363052],"type":"Point"}
}