{
  "type": "Feature",
  "properties": {
    "date:inception_lower": "1981-07-01",
    "date:inception_upper": "1981-07-01",
    "iso:country": "GB",
    "wof:name": "EH34 5HB",
    "wof:placetype": "postalcode"
  },
  "geometry": {"coordinates":[-2.897701,55.910541],"type":"Point"}
}
