{
  "type": "Feature",
  "properties": {
    "iso:country": "GB",
    "wof:name": "BD20 9FF",
    "wof:placetype": "postalcode"
  },
  "geometry": {"coordinates":[-1.982872,53.909394],"type":"Point"}
}
