{
  "type": "Feature",
  "properties": {
    "date:inception_lower": "2019-06-01",
    "date:inception_upper": "2019-06-01",
    "iso:country": "GB",
    "wof:name": "BD20 9FF",
    "wof:placetype": "postalcode"
  },
  "geometry": {"coordinates":[-1.982872,53.909385],"type":"Point"}
}
