{
  "type": "Feature",
  "properties": {
    "date:inception_lower": "2021-07-01",
    "date:inception_upper": "2021-07-01",
    "iso:country": "GB",
    "wof:name": "SL5 7BT",
    "wof:placetype": "postalcode"
  },
  "geometry": {"coordinates":[-0.654388,51.402491],"type":"Point"}
}
