{
  "type": "Feature",
  "properties": {
    "iso:country":"GB",
    "wof:name":"SL5 7BT",
    "wof:placetype":"postalcode"
},
  "geometry": {"coordinates":[-0.65440576016311,51.40249098763415],"type":"Point"}
}