{
  "type": "Feature",
  "properties": {
    "iso:country": "GB",
    "wof:name": "TN27 0ET",
    "wof:placetype": "postalcode"
  },
  "geometry": {"coordinates":[0.787649,51.196874],"type":"Point"}
}
