{
  "type": "Feature",
  "properties": {
    "iso:country":"GB",
    "wof:name":"TN27 0ET",
    "wof:placetype":"postalcode"
},
  "geometry": {"coordinates":[0.78872985681058,51.19771149833749],"type":"Point"}
}