{
  "type": "Feature",
  "properties": {
    "date:inception_lower":"1987-10-01",
    "date:inception_upper":"1987-10-31",
    "iso:country":"GB",
    "wof:name":"PA1 2DW",
    "wof:placetype":"postalcode"
},
  "geometry": {"coordinates":[-4.427259,55.841029],"type":"Point"}
}