{
  "type": "Feature",
  "properties": {
    "iso:country":"GB",
    "wof:name":"PA1 2DW",
    "wof:placetype":"postalcode"
},
  "geometry": {"coordinates":[-4.42725951281167,55.84102922924295],"type":"Point"}
}