{
  "type": "Feature",
  "properties": {
    "iso:country": "GB",
    "wof:name": "PA1 2DW",
    "wof:placetype": "postalcode"
  },
  "geometry": {"coordinates":[-4.427259,55.841029],"type":"Point"}
}
