{
  "type": "Feature",
  "properties": {
    "iso:country":"GB",
    "wof:name":"NE2 4BP",
    "wof:placetype":"postalcode"
},
  "geometry": {"coordinates":[-1.62781585388345,54.98442845387885],"type":"Point"}
}