{
  "type": "Feature",
  "properties": {
    "date:inception_lower": "1980-01-01",
    "date:inception_upper": "1980-01-01",
    "iso:country": "GB",
    "wof:name": "LN6 8AL",
    "wof:placetype": "postalcode"
  },
  "geometry": {"coordinates":[-0.566021,53.198593],"type":"Point"}
}
