{
  "type": "Feature",
  "properties": {
    "iso:country":"GB",
    "wof:name":"LN6 8AL",
    "wof:placetype":"postalcode"
},
  "geometry": {"coordinates":[-0.56600843378479,53.19854335109023],"type":"Point"}
}