{
  "type": "Feature",
  "properties": {
    "date:inception_lower": "1980-01-01",
    "date:inception_upper": "1980-01-01",
    "iso:country": "GB",
    "wof:name": "L13 1DD",
    "wof:placetype": "postalcode"
  },
  "geometry": {"coordinates":[-2.917814,53.40752],"type":"Point"}
}
