{
  "type": "Feature",
  "properties": {
    "iso:country": "GB",
    "wof:name": "DE3 9LG",
    "wof:placetype": "postalcode"
  },
  "geometry": {"coordinates":[-1.530608,52.913541],"type":"Point"}
}
