{
  "type": "Feature",
  "properties": {
    "date:inception_lower": "2000-06-01",
    "date:inception_upper": "2000-06-01",
    "iso:country": "GB",
    "wof:name": "CF11 0AB",
    "wof:placetype": "postalcode"
  },
  "geometry": {"coordinates":[-3.19097,51.453012],"type":"Point"}
}
