{
  "type": "Feature",
  "properties": {
    "date:inception_lower": "1980-01-01",
    "date:inception_upper": "1980-01-01",
    "iso:country": "GB",
    "wof:name": "CV3 3GW",
    "wof:placetype": "postalcode"
  },
  "geometry": {"coordinates":[-1.451996,52.379667],"type":"Point"}
}
