{
  "type": "Feature",
  "properties": {
    "iso:country":"GB",
    "wof:name":"CV3 3GW",
    "wof:placetype":"postalcode"
},
  "geometry": {"coordinates":[-1.44283135280584,52.38019152135679],"type":"Point"}
}