{
  "type": "Feature",
  "properties": {
    "date:inception_lower": "1993-08-01",
    "date:inception_upper": "1993-08-01",
    "iso:country": "GB",
    "wof:name": "G4 0HX",
    "wof:placetype": "postalcode"
  },
  "geometry": {"coordinates":[-4.256907,55.868238],"type":"Point"}
}
