{
  "type": "Feature",
  "properties": {
    "date:inception_lower": "2021-10-01",
    "date:inception_upper": "2021-10-01",
    "iso:country": "GB",
    "wof:name": "KA9 2FN",
    "wof:placetype": "postalcode"
  },
  "geometry": {"coordinates":[-4.593335,55.517181],"type":"Point"}
}
