{
  "type": "Feature",
  "properties": {
    "date:inception_lower": "2016-09-01",
    "date:inception_upper": "2016-09-01",
    "iso:country": "GB",
    "wof:name": "NG2 4DN",
    "wof:placetype": "postalcode"
  },
  "geometry": {"coordinates":[-1.12424,52.943813],"type":"Point"}
}
