{
  "type": "Feature",
  "properties": {
    "iso:country": "GB",
    "wof:name": "SL6 9PL",
    "wof:placetype": "postalcode"
  },
  "geometry": {"coordinates":[-0.746831,51.55578],"type":"Point"}
}
