{
  "type": "Feature",
  "properties": {
    "date:inception_lower": "1980-01-01",
    "date:inception_upper": "1980-01-01",
    "iso:country": "GB",
    "wof:name": "SL6 9PL",
    "wof:placetype": "postalcode"
  },
  "geometry": {"coordinates":[-0.747004,51.555791],"type":"Point"}
}
