{
  "type": "Feature",
  "properties": {
    "iso:country":"GB",
    "wof:name":"SL6 9PL",
    "wof:placetype":"postalcode"
},
  "geometry": {"coordinates":[-0.74684993388221,51.55577690879596],"type":"Point"}
}