{
  "type": "Feature",
  "properties": {
    "iso:country":"GB",
    "wof:name":"DD5 3BZ",
    "wof:placetype":"postalcode"
},
  "geometry": {"coordinates":[-2.86763677347872,56.48009008414201],"type":"Point"}
}