{
  "type": "Feature",
  "properties": {
    "iso:country": "GB",
    "wof:name": "AB42 4EZ",
    "wof:placetype": "postalcode"
  },
  "geometry": {"coordinates":[-2.009312,57.545793],"type":"Point"}
}
