{
  "type": "Feature",
  "properties": {
    "iso:country":"GB",
    "wof:name":"AB42 4EZ",
    "wof:placetype":"postalcode"
},
  "geometry": {"coordinates":[-2.00658448543311,57.54565551487434],"type":"Point"}
}