{
  "type": "Feature",
  "properties": {
    "date:inception_lower":"1980-01-01",
    "date:inception_upper":"1980-01-31",
    "iso:country":"GB",
    "wof:name":"B70 7HR",
    "wof:placetype":"postalcode"
},
  "geometry": {"coordinates":[-2.004598,52.513081],"type":"Point"}
}