{
  "type": "Feature",
  "properties": {
    "iso:country":"GB",
    "wof:name":"DY2 9BX",
    "wof:placetype":"postalcode"
},
  "geometry": {"coordinates":[-2.0840275701234,52.49370482807393],"type":"Point"}
}