{
  "type": "Feature",
  "properties": {
    "iso:country":"GB",
    "wof:name":"EH48 1BL",
    "wof:placetype":"postalcode"
},
  "geometry": {"coordinates":[-3.63142772129445,55.89833596466868],"type":"Point"}
}