{
  "type": "Feature",
  "properties": {
    "iso:country": "GB",
    "wof:name": "EH48 1BL",
    "wof:placetype": "postalcode"
  },
  "geometry": {"coordinates":[-3.631428,55.898336],"type":"Point"}
}
