{
  "type": "Feature",
  "properties": {
    "iso:country":"GB",
    "wof:name":"WA9 3HJ",
    "wof:placetype":"postalcode"
},
  "geometry": {"coordinates":[-2.69554588006958,53.4400346089655],"type":"Point"}
}