{
  "type": "Feature",
  "properties": {
    "iso:country":"GB",
    "wof:name":"CM23 5EU",
    "wof:placetype":"postalcode"
},
  "geometry": {"coordinates":[0.18012932173469,51.8774599974998],"type":"Point"}
}