{
  "type": "Feature",
  "properties": {
    "iso:country": "GB",
    "wof:name": "CM23 5EU",
    "wof:placetype": "postalcode"
  },
  "geometry": {"coordinates":[0.180129,51.87746],"type":"Point"}
}
