{
  "type": "Feature",
  "properties": {
    "iso:country":"GB",
    "wof:name":"SS14 3RJ",
    "wof:placetype":"postalcode"
},
  "geometry": {"coordinates":[0.49412309567089,51.57789303590693],"type":"Point"}
}