{
  "type": "Feature",
  "properties": {
    "iso:country":"GB",
    "wof:name":"W5 3AS",
    "wof:placetype":"postalcode"
},
  "geometry": {"coordinates":[-0.289958495807,51.51879590885647],"type":"Point"}
}