{
  "type": "Feature",
  "properties": {
    "iso:country":"GB",
    "wof:name":"BL1 1PS",
    "wof:placetype":"postalcode"
},
  "geometry": {"coordinates":[-2.42304553050725,53.57863671178451],"type":"Point"}
}