{
  "type": "Feature",
  "properties": {
    "date:inception_lower": "1980-01-01",
    "date:inception_upper": "1980-01-01",
    "iso:country": "GB",
    "wof:name": "BL1 1PS",
    "wof:placetype": "postalcode"
  },
  "geometry": {"coordinates":[-2.423074,53.578652],"type":"Point"}
}
