{
  "type": "Feature",
  "properties": {
    "date:inception_lower":"1980-01-01",
    "date:inception_upper":"1980-01-31",
    "iso:country":"GB",
    "wof:name":"ST5 8EJ",
    "wof:placetype":"postalcode"
},
  "geometry": {"coordinates":[-2.230107,53.035751],"type":"Point"}
}