{
  "type": "Feature",
  "properties": {
    "iso:country":"GB",
    "wof:name":"ST5 8EJ",
    "wof:placetype":"postalcode"
},
  "geometry": {"coordinates":[-2.23010701101646,53.03575082264295],"type":"Point"}
}