{
  "type": "Feature",
  "properties": {
    "iso:country":"GB",
    "wof:name":"NR15 1UT",
    "wof:placetype":"postalcode"
},
  "geometry": {"coordinates":[1.29498150472578,52.55418351037707],"type":"Point"}
}