{
  "type": "Feature",
  "properties": {
    "iso:country": "GB",
    "wof:name": "RG30 2PJ",
    "wof:placetype": "postalcode"
  },
  "geometry": {"coordinates":[-1.010921,51.459741],"type":"Point"}
}
