{
  "type": "Feature",
  "properties": {
    "date:inception_lower": "1981-06-01",
    "date:inception_upper": "1981-06-01",
    "iso:country": "GB",
    "wof:name": "PA1 2YA",
    "wof:placetype": "postalcode"
  },
  "geometry": {"coordinates":[-4.423187,55.845657],"type":"Point"}
}
