{
  "type": "Feature",
  "properties": {
    "iso:country":"GB",
    "wof:name":"PA1 2YA",
    "wof:placetype":"postalcode"
},
  "geometry": {"coordinates":[-4.42318688287061,55.84565741648039],"type":"Point"}
}