{
  "type": "Feature",
  "properties": {
    "date:inception_lower": "2021-02-01",
    "date:inception_upper": "2021-02-01",
    "iso:country": "GB",
    "wof:name": "YO8 5DN",
    "wof:placetype": "postalcode"
  },
  "geometry": {"coordinates":[-1.041351,53.800485],"type":"Point"}
}
