{
  "type": "Feature",
  "properties": {
    "iso:country":"GB",
    "wof:name":"KY12 9FD",
    "wof:placetype":"postalcode"
},
  "geometry": {"coordinates":[-3.46228325939656,56.07762510751975],"type":"Point"}
}