{
  "type": "Feature",
  "properties": {
    "iso:country":"GB",
    "wof:name":"TS5 6EF",
    "wof:placetype":"postalcode"
},
  "geometry": {"coordinates":[-1.24651316822963,54.55943385277767],"type":"Point"}
}