{
  "type": "Feature",
  "properties": {
    "date:inception_lower":"2013-09-01",
    "date:inception_upper":"2013-09-30",
    "iso:country":"GB",
    "wof:name":"OL11 3DE",
    "wof:placetype":"postalcode"
},
  "geometry": {"coordinates":[-2.186654,53.59292],"type":"Point"}
}