{
  "type": "Feature",
  "properties": {
    "iso:country": "GB",
    "wof:name": "OL11 3DE",
    "wof:placetype": "postalcode"
  },
  "geometry": {"coordinates":[-2.186654,53.59292],"type":"Point"}
}
