{
  "type": "Feature",
  "properties": {
    "iso:country":"GB",
    "wof:name":"OL11 3DE",
    "wof:placetype":"postalcode"
},
  "geometry": {"coordinates":[-2.18665371083544,53.59291972795251],"type":"Point"}
}