{
  "type": "Feature",
  "properties": {
    "iso:country": "GB",
    "wof:name": "RM10 9HP",
    "wof:placetype": "postalcode"
  },
  "geometry": {"coordinates":[0.15131,51.53655],"type":"Point"}
}
