{
  "type": "Feature",
  "properties": {
    "iso:country":"GB",
    "wof:name":"RM10 9HP",
    "wof:placetype":"postalcode"
},
  "geometry": {"coordinates":[0.15131037277563,51.53655017468355],"type":"Point"}
}