{
  "type": "Feature",
  "properties": {
    "date:inception_lower": "1980-01-01",
    "date:inception_upper": "1980-01-01",
    "iso:country": "GB",
    "wof:name": "RM10 9HP",
    "wof:placetype": "postalcode"
  },
  "geometry": {"coordinates":[0.15131,51.53655],"type":"Point"}
}
