{
  "type": "Feature",
  "properties": {
    "iso:country":"GB",
    "wof:name":"WV12 5BT",
    "wof:placetype":"postalcode"
},
  "geometry": {"coordinates":[-2.02930331068947,52.61459961830465],"type":"Point"}
}