{
  "type": "Feature",
  "properties": {
    "date:inception_lower": "1980-01-01",
    "date:inception_upper": "1980-01-01",
    "iso:country": "GB",
    "wof:name": "WV12 5BT",
    "wof:placetype": "postalcode"
  },
  "geometry": {"coordinates":[-2.029303,52.6146],"type":"Point"}
}
