{
  "type": "Feature",
  "properties": {
    "date:inception_lower": "1980-01-01",
    "date:inception_upper": "1980-01-01",
    "iso:country": "GB",
    "wof:name": "BA14 8PE",
    "wof:placetype": "postalcode"
  },
  "geometry": {"coordinates":[-2.208941,51.324269],"type":"Point"}
}
