{
  "type": "Feature",
  "properties": {
    "iso:country":"GB",
    "wof:name":"BA14 8PE",
    "wof:placetype":"postalcode"
},
  "geometry": {"coordinates":[-2.20891602162372,51.3242541078136],"type":"Point"}
}