{
  "type": "Feature",
  "properties": {
    "iso:country":"GB",
    "wof:name":"M32 9HW",
    "wof:placetype":"postalcode"
},
  "geometry": {"coordinates":[-2.32692205184939,53.44853408651664],"type":"Point"}
}