{
  "type": "Feature",
  "properties": {
    "iso:country":"GB",
    "wof:name":"NG8 2FX",
    "wof:placetype":"postalcode"
},
  "geometry": {"coordinates":[-1.22569550090815,52.95183184063075],"type":"Point"}
}