{
  "type": "Feature",
  "properties": {
    "iso:country":"GB",
    "wof:name":"S71 3RN",
    "wof:placetype":"postalcode"
},
  "geometry": {"coordinates":[-1.44933833952835,53.57577357189115],"type":"Point"}
}