{
  "type": "Feature",
  "properties": {
    "iso:country":"GB",
    "wof:name":"LE19 4AG",
    "wof:placetype":"postalcode"
},
  "geometry": {"coordinates":[-1.21003318912642,52.59000857856194],"type":"Point"}
}