{
  "type": "Feature",
  "properties": {
    "iso:country":"GB",
    "wof:name":"G11 6SQ",
    "wof:placetype":"postalcode"
},
  "geometry": {"coordinates":[-4.31216049393347,55.87092000537132],"type":"Point"}
}