{
  "type": "Feature",
  "properties": {
    "iso:country": "GB",
    "wof:name": "G11 6SQ",
    "wof:placetype": "postalcode"
  },
  "geometry": {"coordinates":[-4.31216,55.87092],"type":"Point"}
}
