{
  "type": "Feature",
  "properties": {
    "date:inception_lower": "2006-07-01",
    "date:inception_upper": "2006-07-01",
    "iso:country": "GB",
    "wof:name": "HP15 7RY",
    "wof:placetype": "postalcode"
  },
  "geometry": {"coordinates":[-0.715462,51.650976],"type":"Point"}
}
