{
  "type": "Feature",
  "properties": {
    "iso:country":"GB",
    "wof:name":"CM2 6AR",
    "wof:placetype":"postalcode"
},
  "geometry": {"coordinates":[0.49332266997464,51.74078543003852],"type":"Point"}
}