{
  "type": "Feature",
  "properties": {
    "date:inception_lower": "2018-04-01",
    "date:inception_upper": "2018-04-01",
    "iso:country": "GB",
    "wof:name": "CV23 8YP",
    "wof:placetype": "postalcode"
  },
  "geometry": {"coordinates":[-1.174864,52.33137],"type":"Point"}
}
