{
  "type": "Feature",
  "properties": {
    "date:inception_lower": "1980-01-01",
    "date:inception_upper": "1980-01-01",
    "iso:country": "GB",
    "wof:name": "WA15 8PE",
    "wof:placetype": "postalcode"
  },
  "geometry": {"coordinates":[-2.315166,53.37788],"type":"Point"}
}
