{
  "type": "Feature",
  "properties": {
    "iso:country": "GB",
    "wof:name": "BN14 7BX",
    "wof:placetype": "postalcode"
  },
  "geometry": {"coordinates":[-0.375114,50.819517],"type":"Point"}
}
