{
  "type": "Feature",
  "properties": {
    "date:inception_lower": "2019-07-01",
    "date:inception_upper": "2019-07-01",
    "iso:country": "GB",
    "wof:name": "BA9 0BG",
    "wof:placetype": "postalcode"
  },
  "geometry": {"coordinates":[-2.409923,51.057347],"type":"Point"}
}
