{
  "type": "Feature",
  "properties": {
    "iso:country":"GB",
    "wof:name":"DA7 6AH",
    "wof:placetype":"postalcode"
},
  "geometry": {"coordinates":[0.15471327794727,51.45681966652841],"type":"Point"}
}