{
  "type": "Feature",
  "properties": {
    "date:inception_lower": "1980-01-01",
    "date:inception_upper": "1980-01-01",
    "iso:country": "GB",
    "wof:name": "RH1 6LX",
    "wof:placetype": "postalcode"
  },
  "geometry": {"coordinates":[-0.184893,51.227195],"type":"Point"}
}
