{
  "type": "Feature",
  "properties": {
    "iso:country": "GB",
    "wof:name": "RH1 6LX",
    "wof:placetype": "postalcode"
  },
  "geometry": {"coordinates":[-0.184893,51.227195],"type":"Point"}
}
