{
  "type": "Feature",
  "properties": {
    "date:inception_lower": "1996-06-01",
    "date:inception_upper": "1996-06-01",
    "iso:country": "GB",
    "wof:name": "AB16 6WH",
    "wof:placetype": "postalcode"
  },
  "geometry": {"coordinates":[-2.18427,57.154287],"type":"Point"}
}
