{
  "type": "Feature",
  "properties": {
    "iso:country": "GB",
    "wof:name": "TF10 7EE",
    "wof:placetype": "postalcode"
  },
  "geometry": {"coordinates":[-2.376361,52.763674],"type":"Point"}
}
