{
  "type": "Feature",
  "properties": {
    "iso:country":"GB",
    "wof:name":"LS9 7QZ",
    "wof:placetype":"postalcode"
},
  "geometry": {"coordinates":[-1.51294039924113,53.79839083903433],"type":"Point"}
}