{
  "type": "Feature",
  "properties": {
    "iso:country": "GB",
    "wof:name": "NN14 1PU",
    "wof:placetype": "postalcode"
  },
  "geometry": {"coordinates":[-0.779235,52.382439],"type":"Point"}
}
