{
  "type": "Feature",
  "properties": {
    "iso:country":"GB",
    "wof:name":"NN14 1PU",
    "wof:placetype":"postalcode"
},
  "geometry": {"coordinates":[-0.77923469658923,52.38243931887658],"type":"Point"}
}