{
  "type": "Feature",
  "properties": {
    "iso:country":"GB",
    "wof:name":"NE39 1JJ",
    "wof:placetype":"postalcode"
},
  "geometry": {"coordinates":[-1.7426575946694,54.92013214594819],"type":"Point"}
}