{
  "type": "Feature",
  "properties": {
    "iso:country": "GB",
    "wof:name": "TS2 1AY",
    "wof:placetype": "postalcode"
  },
  "geometry": {"coordinates":[-1.2341,54.580655],"type":"Point"}
}
