{
  "type": "Feature",
  "properties": {
    "date:inception_lower":"2015-10-01",
    "date:inception_upper":"2015-10-31",
    "iso:country":"GB",
    "wof:name":"TS2 1AY",
    "wof:placetype":"postalcode"
},
  "geometry": {"coordinates":[-1.2341,54.580655],"type":"Point"}
}