{
  "type": "Feature",
  "properties": {
    "iso:country": "GB",
    "wof:name": "PE13 4HL",
    "wof:placetype": "postalcode"
  },
  "geometry": {"coordinates":[-0.006272,52.62863],"type":"Point"}
}
