{
  "type": "Feature",
  "properties": {
    "date:inception_lower": "1980-01-01",
    "date:inception_upper": "1980-01-01",
    "iso:country": "GB",
    "wof:name": "PE13 4HL",
    "wof:placetype": "postalcode"
  },
  "geometry": {"coordinates":[-0.006272,52.62863],"type":"Point"}
}
