{
  "type": "Feature",
  "properties": {
    "iso:country":"GB",
    "wof:name":"UB6 9TT",
    "wof:placetype":"postalcode"
},
  "geometry": {"coordinates":[-0.36485756409031,51.53229115029786],"type":"Point"}
}