{
  "type": "Feature",
  "properties": {
    "date:inception_lower":"2005-02-01",
    "date:inception_upper":"2005-02-28",
    "iso:country":"GB",
    "wof:name":"CH44 4SS",
    "wof:placetype":"postalcode"
},
  "geometry": {"coordinates":[-3.0229,53.416079],"type":"Point"}
}