{
  "type": "Feature",
  "properties": {
    "iso:country":"GB",
    "wof:name":"S75 5AE",
    "wof:placetype":"postalcode"
},
  "geometry": {"coordinates":[-1.52555225830197,53.5858523060424],"type":"Point"}
}