{
  "type": "Feature",
  "properties": {
    "iso:country": "GB",
    "wof:name": "S75 5AE",
    "wof:placetype": "postalcode"
  },
  "geometry": {"coordinates":[-1.525552,53.585852],"type":"Point"}
}
