{
  "type": "Feature",
  "properties": {
    "date:inception_lower": "2024-04-01",
    "date:inception_upper": "2024-04-01",
    "iso:country": "GB",
    "wof:name": "G69 0DG",
    "wof:placetype": "postalcode"
  },
  "geometry": {"coordinates":[-4.081883,55.920304],"type":"Point"}
}
