{
  "type": "Feature",
  "properties": {
    "date:inception_lower": "1980-01-01",
    "date:inception_upper": "1980-01-01",
    "iso:country": "GB",
    "wof:name": "IP30 9AX",
    "wof:placetype": "postalcode"
  },
  "geometry": {"coordinates":[0.833269,52.220796],"type":"Point"}
}
