{
  "type": "Feature",
  "properties": {
    "iso:country": "GB",
    "wof:name": "IP30 9AX",
    "wof:placetype": "postalcode"
  },
  "geometry": {"coordinates":[0.833238,52.220789],"type":"Point"}
}
