{
  "type": "Feature",
  "properties": {
    "iso:country":"GB",
    "wof:name":"IP30 9AX",
    "wof:placetype":"postalcode"
},
  "geometry": {"coordinates":[0.83323813932035,52.22078887069635],"type":"Point"}
}