{
  "type": "Feature",
  "properties": {
    "date:inception_lower": "1999-06-01",
    "date:inception_upper": "1999-06-01",
    "iso:country": "GB",
    "wof:name": "CF14 7BU",
    "wof:placetype": "postalcode"
  },
  "geometry": {"coordinates":[-3.226233,51.521239],"type":"Point"}
}
