{
  "type": "Feature",
  "properties": {
    "iso:country":"GB",
    "wof:name":"CF14 7BU",
    "wof:placetype":"postalcode"
},
  "geometry": {"coordinates":[-3.22623267695481,51.52123918306818],"type":"Point"}
}