{
  "type": "Feature",
  "properties": {
    "date:inception_lower":"1980-01-01",
    "date:inception_upper":"1980-01-31",
    "iso:country":"GB",
    "wof:name":"LD1 6SD",
    "wof:placetype":"postalcode"
},
  "geometry": {"coordinates":[-3.328751,52.300064],"type":"Point"}
}