{
  "type": "Feature",
  "properties": {
    "iso:country":"GB",
    "wof:name":"LD1 6SD",
    "wof:placetype":"postalcode"
},
  "geometry": {"coordinates":[-3.32875112615471,52.30006415857108],"type":"Point"}
}