{
  "type": "Feature",
  "properties": {
    "date:inception_lower":"1980-01-01",
    "date:inception_upper":"1980-01-31",
    "iso:country":"GB",
    "wof:name":"NE2 1NJ",
    "wof:placetype":"postalcode"
},
  "geometry": {"coordinates":[-1.600895,54.984101],"type":"Point"}
}