{
  "type": "Feature",
  "properties": {
    "iso:country":"GB",
    "wof:name":"NE2 1NJ",
    "wof:placetype":"postalcode"
},
  "geometry": {"coordinates":[-1.60089500483841,54.98410054077313],"type":"Point"}
}