{
  "type": "Feature",
  "properties": {
    "iso:country": "GB",
    "wof:name": "L39 1NG",
    "wof:placetype": "postalcode"
  },
  "geometry": {"coordinates":[-2.886197,53.570987],"type":"Point"}
}
