{
  "type": "Feature",
  "properties": {
    "iso:country":"GB",
    "wof:name":"L39 1NG",
    "wof:placetype":"postalcode"
},
  "geometry": {"coordinates":[-2.88619680318274,53.57098694215075],"type":"Point"}
}