{
  "type": "Feature",
  "properties": {
    "iso:country":"GB",
    "wof:name":"CV9 3QF",
    "wof:placetype":"postalcode"
},
  "geometry": {"coordinates":[-1.49915952815996,52.66261208396234],"type":"Point"}
}