{
  "type": "Feature",
  "properties": {
    "iso:country":"GB",
    "wof:name":"DY9 0NJ",
    "wof:placetype":"postalcode"
},
  "geometry": {"coordinates":[-2.14374431657271,52.41905718089527],"type":"Point"}
}