{
  "type": "Feature",
  "properties": {
    "date:inception_lower": "1980-01-01",
    "date:inception_upper": "1980-01-01",
    "iso:country": "GB",
    "wof:name": "EX16 9BD",
    "wof:placetype": "postalcode"
  },
  "geometry": {"coordinates":[-3.435095,51.01032],"type":"Point"}
}
