{
  "type": "Feature",
  "properties": {
    "iso:country":"GB",
    "wof:name":"L10 3LG",
    "wof:placetype":"postalcode"
},
  "geometry": {"coordinates":[-2.94373935414005,53.48587295234883],"type":"Point"}
}