{
  "type": "Feature",
  "properties": {
    "date:inception_lower": "1980-01-01",
    "date:inception_upper": "1980-01-01",
    "iso:country": "GB",
    "wof:name": "TS24 0EQ",
    "wof:placetype": "postalcode"
  },
  "geometry": {"coordinates":[-1.193605,54.701555],"type":"Point"}
}
