{
  "type": "Feature",
  "properties": {
    "date:inception_lower": "1980-01-01",
    "date:inception_upper": "1980-01-01",
    "iso:country": "GB",
    "wof:name": "DL2 2EE",
    "wof:placetype": "postalcode"
  },
  "geometry": {"coordinates":[-1.535902,54.489041],"type":"Point"}
}
