{
  "type": "Feature",
  "properties": {
    "iso:country":"GB",
    "wof:name":"DL2 2EE",
    "wof:placetype":"postalcode"
},
  "geometry": {"coordinates":[-1.5358033188412,54.4887235387205],"type":"Point"}
}