{
  "type": "Feature",
  "properties": {
    "iso:country": "GB",
    "wof:name": "DL2 2EE",
    "wof:placetype": "postalcode"
  },
  "geometry": {"coordinates":[-1.535902,54.489041],"type":"Point"}
}
