{
  "type": "Feature",
  "properties": {
    "iso:country":"GB",
    "wof:name":"SP1 1EL",
    "wof:placetype":"postalcode"
},
  "geometry": {"coordinates":[-1.79363235971534,51.06938289448989],"type":"Point"}
}