{
  "type": "Feature",
  "properties": {
    "iso:country":"GB",
    "wof:name":"SE12 0JQ",
    "wof:placetype":"postalcode"
},
  "geometry": {"coordinates":[0.01871039090295,51.44176770635151],"type":"Point"}
}