{
  "type": "Feature",
  "properties": {
    "date:inception_lower": "1995-07-01",
    "date:inception_upper": "1995-07-01",
    "iso:country": "GB",
    "wof:name": "RM19 1TT",
    "wof:placetype": "postalcode"
  },
  "geometry": {"coordinates":[0.247862,51.481411],"type":"Point"}
}
