{
  "type": "Feature",
  "properties": {
    "iso:country": "GB",
    "wof:name": "RM19 1TT",
    "wof:placetype": "postalcode"
  },
  "geometry": {"coordinates":[0.247862,51.481411],"type":"Point"}
}
