{
  "type": "Feature",
  "properties": {
    "iso:country":"GB",
    "wof:name":"EN8 8QL",
    "wof:placetype":"postalcode"
},
  "geometry": {"coordinates":[-0.04166622981739,51.70171426395414],"type":"Point"}
}