{
  "type": "Feature",
  "properties": {
    "date:inception_lower": "1986-04-01",
    "date:inception_upper": "1986-04-01",
    "iso:country": "GB",
    "wof:name": "BB5 6TN",
    "wof:placetype": "postalcode"
  },
  "geometry": {"coordinates":[-2.351139,53.751425],"type":"Point"}
}
