{
  "type": "Feature",
  "properties": {
    "iso:country":"GB",
    "wof:name":"BB5 6TN",
    "wof:placetype":"postalcode"
},
  "geometry": {"coordinates":[-2.35113897484862,53.75142509186674],"type":"Point"}
}