{
  "type": "Feature",
  "properties": {
    "iso:country": "GB",
    "wof:name": "BB5 6TN",
    "wof:placetype": "postalcode"
  },
  "geometry": {"coordinates":[-2.351139,53.751425],"type":"Point"}
}
