{
  "type": "Feature",
  "properties": {
    "iso:country":"GB",
    "wof:name":"TA24 8SR",
    "wof:placetype":"postalcode"
},
  "geometry": {"coordinates":[-3.51890591914743,51.20091348016933],"type":"Point"}
}