{
  "type": "Feature",
  "properties": {
    "iso:country": "GB",
    "wof:name": "TA24 8SR",
    "wof:placetype": "postalcode"
  },
  "geometry": {"coordinates":[-3.518935,51.20092],"type":"Point"}
}
