{
  "type": "Feature",
  "properties": {
    "iso:country": "GB",
    "wof:name": "WA5 2NF",
    "wof:placetype": "postalcode"
  },
  "geometry": {"coordinates":[-2.660178,53.382366],"type":"Point"}
}
