{
  "type": "Feature",
  "properties": {
    "iso:country":"GB",
    "wof:name":"WA5 2NF",
    "wof:placetype":"postalcode"
},
  "geometry": {"coordinates":[-2.66017784652839,53.38236604940955],"type":"Point"}
}