{
  "type": "Feature",
  "properties": {
    "iso:country": "GB",
    "wof:name": "BH20 4JZ",
    "wof:placetype": "postalcode"
  },
  "geometry": {"coordinates":[-2.113147,50.685281],"type":"Point"}
}
