{
  "type": "Feature",
  "properties": {
    "iso:country":"GB",
    "wof:name":"LS11 8PB",
    "wof:placetype":"postalcode"
},
  "geometry": {"coordinates":[-1.55392544847251,53.77896522817301],"type":"Point"}
}