{
  "type": "Feature",
  "properties": {
    "iso:country": "GB",
    "wof:name": "TS6 9HA",
    "wof:placetype": "postalcode"
  },
  "geometry": {"coordinates":[-1.137536,54.555228],"type":"Point"}
}
