{
  "type": "Feature",
  "properties": {
    "iso:country":"GB",
    "wof:name":"TS6 9HA",
    "wof:placetype":"postalcode"
},
  "geometry": {"coordinates":[-1.13753602506201,54.55522836232282],"type":"Point"}
}