{
  "type": "Feature",
  "properties": {
    "iso:country":"GB",
    "wof:name":"N2 0TW",
    "wof:placetype":"postalcode"
},
  "geometry": {"coordinates":[-0.16918853218166,51.58377777890616],"type":"Point"}
}