{
  "type": "Feature",
  "properties": {
    "iso:country":"GB",
    "wof:name":"TQ7 3JY",
    "wof:placetype":"postalcode"
},
  "geometry": {"coordinates":[-3.85673172662655,50.25640572866858],"type":"Point"}
}