{
  "type": "Feature",
  "properties": {
    "date:inception_lower":"1980-01-01",
    "date:inception_upper":"1980-01-31",
    "iso:country":"GB",
    "wof:name":"BD21 1EF",
    "wof:placetype":"postalcode"
},
  "geometry": {"coordinates":[-1.911838,53.860572],"type":"Point"}
}