{
  "type": "Feature",
  "properties": {
    "iso:country":"GB",
    "wof:name":"BD21 1EF",
    "wof:placetype":"postalcode"
},
  "geometry": {"coordinates":[-1.91183853343699,53.86057219196387],"type":"Point"}
}