{
  "type": "Feature",
  "properties": {
    "date:inception_lower":"1980-01-01",
    "date:inception_upper":"1980-01-31",
    "iso:country":"GB",
    "wof:name":"BH10 6EU",
    "wof:placetype":"postalcode"
},
  "geometry": {"coordinates":[-1.89114,50.763522],"type":"Point"}
}