{
  "type": "Feature",
  "properties": {
    "iso:country":"GB",
    "wof:name":"BH10 6EU",
    "wof:placetype":"postalcode"
},
  "geometry": {"coordinates":[-1.8911397635575,50.76352178229948],"type":"Point"}
}