{
  "type": "Feature",
  "properties": {
    "date:inception_lower": "1980-01-01",
    "date:inception_upper": "1980-01-01",
    "iso:country": "GB",
    "wof:name": "SW18 5PW",
    "wof:placetype": "postalcode"
  },
  "geometry": {"coordinates":[-0.213464,51.448072],"type":"Point"}
}
