{
  "type": "Feature",
  "properties": {
    "iso:country":"GB",
    "wof:name":"SW18 5PW",
    "wof:placetype":"postalcode"
},
  "geometry": {"coordinates":[-0.21346424627298,51.44807208764119],"type":"Point"}
}