{
  "type": "Feature",
  "properties": {
    "iso:country": "GB",
    "wof:name": "BL4 0NU",
    "wof:placetype": "postalcode"
  },
  "geometry": {"coordinates":[-2.429454,53.54782],"type":"Point"}
}
