{
  "type": "Feature",
  "properties": {
    "iso:country":"GB",
    "wof:name":"BL4 0NU",
    "wof:placetype":"postalcode"
},
  "geometry": {"coordinates":[-2.42945400715341,53.54781966273892],"type":"Point"}
}