{
  "type": "Feature",
  "properties": {
    "iso:country":"GB",
    "wof:name":"LA1 4EE",
    "wof:placetype":"postalcode"
},
  "geometry": {"coordinates":[-2.79173996708582,54.03260085538177],"type":"Point"}
}