{
  "type": "Feature",
  "properties": {
    "iso:country":"GB",
    "wof:name":"IP4 3HG",
    "wof:placetype":"postalcode"
},
  "geometry": {"coordinates":[1.19088485439992,52.07202357528824],"type":"Point"}
}