{
  "type": "Feature",
  "properties": {
    "iso:country":"GB",
    "wof:name":"B21 0SJ",
    "wof:placetype":"postalcode"
},
  "geometry": {"coordinates":[-1.93560924343357,52.5020781107492],"type":"Point"}
}