{
  "type": "Feature",
  "properties": {
    "iso:country":"GB",
    "wof:name":"HU4 6XT",
    "wof:placetype":"postalcode"
},
  "geometry": {"coordinates":[-0.41044236792033,53.74023405618289],"type":"Point"}
}