{
  "type": "Feature",
  "properties": {
    "date:inception_lower": "2024-01-01",
    "date:inception_upper": "2024-01-01",
    "iso:country": "GB",
    "wof:name": "CW5 6YS",
    "wof:placetype": "postalcode"
  },
  "geometry": {"coordinates":[-2.533878,53.07776],"type":"Point"}
}
