{
  "type": "Feature",
  "properties": {
    "iso:country":"GB",
    "wof:name":"S72 9DQ",
    "wof:placetype":"postalcode"
},
  "geometry": {"coordinates":[-1.41100298552173,53.60988182976511],"type":"Point"}
}