{
  "type": "Feature",
  "properties": {
    "iso:country": "GB",
    "wof:name": "TD9 9EF",
    "wof:placetype": "postalcode"
  },
  "geometry": {"coordinates":[-2.786073,55.422408],"type":"Point"}
}
