{
  "type": "Feature",
  "properties": {
    "date:inception_lower": "1980-01-01",
    "date:inception_upper": "1980-01-01",
    "iso:country": "GB",
    "wof:name": "TD9 9EF",
    "wof:placetype": "postalcode"
  },
  "geometry": {"coordinates":[-2.786073,55.422408],"type":"Point"}
}
