{
  "type": "Feature",
  "properties": {
    "iso:country":"GB",
    "wof:name":"TD9 9EF",
    "wof:placetype":"postalcode"
},
  "geometry": {"coordinates":[-2.78607330891182,55.42240836338759],"type":"Point"}
}