{
  "type": "Feature",
  "properties": {
    "iso:country":"GB",
    "wof:name":"WA1 2BW",
    "wof:placetype":"postalcode"
},
  "geometry": {"coordinates":[-2.58726752826865,53.38808641473656],"type":"Point"}
}