{
  "type": "Feature",
  "properties": {
    "date:inception_lower": "1991-09-01",
    "date:inception_upper": "1991-09-01",
    "iso:country": "GB",
    "wof:name": "WA1 2BW",
    "wof:placetype": "postalcode"
  },
  "geometry": {"coordinates":[-2.587448,53.388103],"type":"Point"}
}
