{
  "type": "Feature",
  "properties": {
    "date:inception_lower": "2007-10-01",
    "date:inception_upper": "2007-10-01",
    "iso:country": "GB",
    "wof:name": "EH4 1QX",
    "wof:placetype": "postalcode"
  },
  "geometry": {"coordinates":[-3.226347,55.963654],"type":"Point"}
}
