{
  "type": "Feature",
  "properties": {
    "date:inception_lower": "2022-10-01",
    "date:inception_upper": "2022-10-01",
    "iso:country": "GB",
    "wof:name": "DE7 6QE",
    "wof:placetype": "postalcode"
  },
  "geometry": {"coordinates":[-1.37423,53.006913],"type":"Point"}
}
