{
  "type": "Feature",
  "properties": {
    "iso:country":"GB",
    "wof:name":"CM23 4PZ",
    "wof:placetype":"postalcode"
},
  "geometry": {"coordinates":[0.13312462523779,51.86479724188732],"type":"Point"}
}