{
  "type": "Feature",
  "properties": {
    "date:inception_lower": "1995-01-01",
    "date:inception_upper": "1995-01-01",
    "iso:country": "GB",
    "wof:name": "CM23 4PZ",
    "wof:placetype": "postalcode"
  },
  "geometry": {"coordinates":[0.133125,51.864797],"type":"Point"}
}
