{
  "type": "Feature",
  "properties": {
    "iso:country":"GB",
    "wof:name":"DY11 7XG",
    "wof:placetype":"postalcode"
},
  "geometry": {"coordinates":[-2.23215995322963,52.32982417913104],"type":"Point"}
}