{
  "type": "Feature",
  "properties": {
    "iso:country":"GB",
    "wof:name":"UB5 6NE",
    "wof:placetype":"postalcode"
},
  "geometry": {"coordinates":[-0.39931801183468,51.53633628570336],"type":"Point"}
}