{
  "type": "Feature",
  "properties": {
    "iso:country":"GB",
    "wof:name":"ST7 1DA",
    "wof:placetype":"postalcode"
},
  "geometry": {"coordinates":[-2.24812488944942,53.08561303543013],"type":"Point"}
}