{
  "type": "Feature",
  "properties": {
    "iso:country": "GB",
    "wof:name": "IP25 7RD",
    "wof:placetype": "postalcode"
  },
  "geometry": {"coordinates":[0.856531,52.630996],"type":"Point"}
}
