{
  "type": "Feature",
  "properties": {
    "iso:country":"GB",
    "wof:name":"IP25 7RD",
    "wof:placetype":"postalcode"
},
  "geometry": {"coordinates":[0.8565307661245,52.63099579781121],"type":"Point"}
}