{
  "type": "Feature",
  "properties": {
    "iso:country": "GB",
    "wof:name": "SE15 3BB",
    "wof:placetype": "postalcode"
  },
  "geometry": {"coordinates":[-0.050309,51.459195],"type":"Point"}
}
