{
  "type": "Feature",
  "properties": {
    "iso:country":"GB",
    "wof:name":"SE15 3BB",
    "wof:placetype":"postalcode"
},
  "geometry": {"coordinates":[-0.05030877570255,51.45919486101408],"type":"Point"}
}