{
  "type": "Feature",
  "properties": {
    "iso:country":"GB",
    "wof:name":"SE4 1BE",
    "wof:placetype":"postalcode"
},
  "geometry": {"coordinates":[-0.0357846673642,51.46588577999058],"type":"Point"}
}