{
  "type": "Feature",
  "properties": {
    "date:inception_lower":"2015-07-01",
    "date:inception_upper":"2015-07-31",
    "iso:country":"GB",
    "wof:name":"SK6 7JZ",
    "wof:placetype":"postalcode"
},
  "geometry": {"coordinates":[-2.054119,53.376037],"type":"Point"}
}