{
  "type": "Feature",
  "properties": {
    "iso:country":"GB",
    "wof:name":"SK6 7JZ",
    "wof:placetype":"postalcode"
},
  "geometry": {"coordinates":[-2.05411860511646,53.37603670083355],"type":"Point"}
}