{
  "type": "Feature",
  "properties": {
    "iso:country":"GB",
    "wof:name":"YO11 2RP",
    "wof:placetype":"postalcode"
},
  "geometry": {"coordinates":[-0.4044845353818,54.27236778949619],"type":"Point"}
}