{
  "type": "Feature",
  "properties": {
    "date:inception_lower": "2022-03-01",
    "date:inception_upper": "2022-03-01",
    "iso:country": "GB",
    "wof:name": "GL11 5FG",
    "wof:placetype": "postalcode"
  },
  "geometry": {"coordinates":[-2.361032,51.713578],"type":"Point"}
}
