{
  "type": "Feature",
  "properties": {
    "iso:country": "GB",
    "wof:name": "NN17 3LS",
    "wof:placetype": "postalcode"
  },
  "geometry": {"coordinates":[-0.627652,52.493681],"type":"Point"}
}
