{
  "type": "Feature",
  "properties": {
    "date:inception_lower": "2016-11-01",
    "date:inception_upper": "2016-11-01",
    "iso:country": "GB",
    "wof:name": "NN17 3LS",
    "wof:placetype": "postalcode"
  },
  "geometry": {"coordinates":[-0.627652,52.493681],"type":"Point"}
}
