{
  "type": "Feature",
  "properties": {
    "iso:country": "GB",
    "wof:name": "PH13 9BT",
    "wof:placetype": "postalcode"
  },
  "geometry": {"coordinates":[-3.268854,56.547689],"type":"Point"}
}
