{
  "type": "Feature",
  "properties": {
    "date:inception_lower":"1980-01-01",
    "date:inception_upper":"1980-01-31",
    "iso:country":"GB",
    "wof:name":"PH13 9BT",
    "wof:placetype":"postalcode"
},
  "geometry": {"coordinates":[-3.268854,56.547689],"type":"Point"}
}