{
  "type": "Feature",
  "properties": {
    "iso:country":"GB",
    "wof:name":"LS21 3PD",
    "wof:placetype":"postalcode"
},
  "geometry": {"coordinates":[-1.69549071971681,53.90298301942916],"type":"Point"}
}