{
  "type": "Feature",
  "properties": {
    "date:inception_lower": "1995-12-01",
    "date:inception_upper": "1995-12-01",
    "iso:country": "GB",
    "wof:name": "LS21 3PD",
    "wof:placetype": "postalcode"
  },
  "geometry": {"coordinates":[-1.695491,53.902983],"type":"Point"}
}
