{
  "type": "Feature",
  "properties": {
    "iso:country":"GB",
    "wof:name":"BH23 4FF",
    "wof:placetype":"postalcode"
},
  "geometry": {"coordinates":[-1.73885119181953,50.73944108347334],"type":"Point"}
}