{
  "type": "Feature",
  "properties": {
    "date:inception_lower":"2015-08-01",
    "date:inception_upper":"2015-08-31",
    "iso:country":"GB",
    "wof:name":"BH23 4FF",
    "wof:placetype":"postalcode"
},
  "geometry": {"coordinates":[-1.738851,50.739441],"type":"Point"}
}