{
  "type": "Feature",
  "properties": {
    "iso:country": "GB",
    "wof:name": "BH23 4FF",
    "wof:placetype": "postalcode"
  },
  "geometry": {"coordinates":[-1.738851,50.739441],"type":"Point"}
}
