{
  "type": "Feature",
  "properties": {
    "iso:country": "GB",
    "wof:name": "PE4 7DX",
    "wof:placetype": "postalcode"
  },
  "geometry": {"coordinates":[-0.238866,52.607511],"type":"Point"}
}
