{
  "type": "Feature",
  "properties": {
    "iso:country":"GB",
    "wof:name":"PE4 7DX",
    "wof:placetype":"postalcode"
},
  "geometry": {"coordinates":[-0.2388665182462,52.60751089483291],"type":"Point"}
}