{
  "type": "Feature",
  "properties": {
    "iso:country":"GB",
    "wof:name":"SG15 6UP",
    "wof:placetype":"postalcode"
},
  "geometry": {"coordinates":[-0.26200009742296,52.02202759474824],"type":"Point"}
}