{
  "type": "Feature",
  "properties": {
    "iso:country":"GB",
    "wof:name":"B13 0RT",
    "wof:placetype":"postalcode"
},
  "geometry": {"coordinates":[-1.88101045015129,52.42694257249768],"type":"Point"}
}