{
  "type": "Feature",
  "properties": {
    "iso:country":"GB",
    "wof:name":"SK17 6DY",
    "wof:placetype":"postalcode"
},
  "geometry": {"coordinates":[-1.9130809873472,53.25689057512741],"type":"Point"}
}