{
  "type": "Feature",
  "properties": {
    "date:inception_lower": "2017-08-01",
    "date:inception_upper": "2017-08-01",
    "iso:country": "GB",
    "wof:name": "LS12 9BE",
    "wof:placetype": "postalcode"
  },
  "geometry": {"coordinates":[-1.596422,53.792838],"type":"Point"}
}
