{
  "type": "Feature",
  "properties": {
    "iso:country":"GB",
    "wof:name":"BD21 4JE",
    "wof:placetype":"postalcode"
},
  "geometry": {"coordinates":[-1.89890927464055,53.86918138264821],"type":"Point"}
}