{
  "type": "Feature",
  "properties": {
    "iso:country":"GB",
    "wof:name":"PO14 2QN",
    "wof:placetype":"postalcode"
},
  "geometry": {"coordinates":[-1.20763312464511,50.82297738917806],"type":"Point"}
}