{
  "type": "Feature",
  "properties": {
    "iso:country":"GB",
    "wof:name":"DY4 7QP",
    "wof:placetype":"postalcode"
},
  "geometry": {"coordinates":[-2.04380730313219,52.52691739856402],"type":"Point"}
}