{
  "type": "Feature",
  "properties": {
    "iso:country": "GB",
    "wof:name": "DY4 7QP",
    "wof:placetype": "postalcode"
  },
  "geometry": {"coordinates":[-2.043807,52.526917],"type":"Point"}
}
