{
  "type": "Feature",
  "properties": {
    "iso:country":"GB",
    "wof:name":"PE8 6AR",
    "wof:placetype":"postalcode"
},
  "geometry": {"coordinates":[-0.43819871160749,52.6061982163319],"type":"Point"}
}