{
  "type": "Feature",
  "properties": {
    "iso:country":"GB",
    "wof:name":"PA28 6PX",
    "wof:placetype":"postalcode"
},
  "geometry": {"coordinates":[-5.73299135031143,55.42225138568168],"type":"Point"}
}