{
  "type": "Feature",
  "properties": {
    "iso:country":"GB",
    "wof:name":"B29 4DJ",
    "wof:placetype":"postalcode"
},
  "geometry": {"coordinates":[-1.96764864528714,52.42323997923044],"type":"Point"}
}