{
  "type": "Feature",
  "properties": {
    "iso:country": "GB",
    "wof:name": "B29 4DJ",
    "wof:placetype": "postalcode"
  },
  "geometry": {"coordinates":[-1.967649,52.42324],"type":"Point"}
}
