{
  "type": "Feature",
  "properties": {
    "date:inception_lower":"2009-07-01",
    "date:inception_upper":"2009-07-31",
    "iso:country":"GB",
    "wof:name":"B29 4DJ",
    "wof:placetype":"postalcode"
},
  "geometry": {"coordinates":[-1.967649,52.42324],"type":"Point"}
}