{
  "type": "Feature",
  "properties": {
    "date:inception_lower": "2017-10-01",
    "date:inception_upper": "2017-10-01",
    "iso:country": "GB",
    "wof:name": "EH54 0HH",
    "wof:placetype": "postalcode"
  },
  "geometry": {"coordinates":[-3.52951,55.891391],"type":"Point"}
}
