{
  "type": "Feature",
  "properties": {
    "iso:country": "GB",
    "wof:name": "LN5 9FW",
    "wof:placetype": "postalcode"
  },
  "geometry": {"coordinates":[-0.554243,53.17665],"type":"Point"}
}
