{
  "type": "Feature",
  "properties": {
    "date:inception_lower": "2014-12-01",
    "date:inception_upper": "2014-12-01",
    "iso:country": "GB",
    "wof:name": "LN5 9FW",
    "wof:placetype": "postalcode"
  },
  "geometry": {"coordinates":[-0.554243,53.17665],"type":"Point"}
}
