{
  "type": "Feature",
  "properties": {
    "iso:country":"GB",
    "wof:name":"LN5 9FW",
    "wof:placetype":"postalcode"
},
  "geometry": {"coordinates":[-0.55507598451738,53.17595505691661],"type":"Point"}
}