{
  "type": "Feature",
  "properties": {
    "iso:country": "GB",
    "wof:name": "LE4 0UT",
    "wof:placetype": "postalcode"
  },
  "geometry": {"coordinates":[-1.158154,52.658182],"type":"Point"}
}
