{
  "type": "Feature",
  "properties": {
    "date:inception_lower":"1980-01-01",
    "date:inception_upper":"1980-01-31",
    "iso:country":"GB",
    "wof:name":"TA9 4RE",
    "wof:placetype":"postalcode"
},
  "geometry": {"coordinates":[-2.933304,51.218961],"type":"Point"}
}