{
  "type": "Feature",
  "properties": {
    "iso:country":"GB",
    "wof:name":"TA9 4RE",
    "wof:placetype":"postalcode"
},
  "geometry": {"coordinates":[-2.93332386608537,51.21896585956299],"type":"Point"}
}