{
  "type": "Feature",
  "properties": {
    "iso:country": "GB",
    "wof:name": "TA9 4RE",
    "wof:placetype": "postalcode"
  },
  "geometry": {"coordinates":[-2.933304,51.218961],"type":"Point"}
}
