{
  "type": "Feature",
  "properties": {
    "iso:country": "GB",
    "wof:name": "BA4 6HR",
    "wof:placetype": "postalcode"
  },
  "geometry": {"coordinates":[-2.502227,51.145727],"type":"Point"}
}
