{
  "type": "Feature",
  "properties": {
    "date:inception_lower": "1981-06-01",
    "date:inception_upper": "1981-06-01",
    "iso:country": "GB",
    "wof:name": "BA4 6HR",
    "wof:placetype": "postalcode"
  },
  "geometry": {"coordinates":[-2.502227,51.145727],"type":"Point"}
}
