{
  "type": "Feature",
  "properties": {
    "date:inception_lower":"1980-01-01",
    "date:inception_upper":"1980-01-31",
    "iso:country":"GB",
    "wof:name":"BN12 5JA",
    "wof:placetype":"postalcode"
},
  "geometry": {"coordinates":[-0.451477,50.812713],"type":"Point"}
}