{
  "type": "Feature",
  "properties": {
    "iso:country":"GB",
    "wof:name":"BN22 0HR",
    "wof:placetype":"postalcode"
},
  "geometry": {"coordinates":[0.25675176710276,50.80145774757062],"type":"Point"}
}