{
  "type": "Feature",
  "properties": {
    "iso:country":"GB",
    "wof:name":"LL53 5LF",
    "wof:placetype":"postalcode"
},
  "geometry": {"coordinates":[-4.4131498253205,52.8916723809384],"type":"Point"}
}