{
  "type": "Feature",
  "properties": {
    "iso:country": "GB",
    "wof:name": "LL53 5LF",
    "wof:placetype": "postalcode"
  },
  "geometry": {"coordinates":[-4.41315,52.891672],"type":"Point"}
}
