{
  "type": "Feature",
  "properties": {
    "iso:country":"GB",
    "wof:name":"DN21 1RX",
    "wof:placetype":"postalcode"
},
  "geometry": {"coordinates":[-0.75999400127391,53.40057907579757],"type":"Point"}
}