{
  "type": "Feature",
  "properties": {
    "date:inception_lower": "1980-01-01",
    "date:inception_upper": "1980-01-01",
    "iso:country": "GB",
    "wof:name": "DN21 1RX",
    "wof:placetype": "postalcode"
  },
  "geometry": {"coordinates":[-0.759994,53.400579],"type":"Point"}
}
