{
  "type": "Feature",
  "properties": {
    "date:inception_lower": "1980-01-01",
    "date:inception_upper": "1980-01-01",
    "iso:country": "GB",
    "wof:name": "L6 8NL",
    "wof:placetype": "postalcode"
  },
  "geometry": {"coordinates":[-2.938689,53.415485],"type":"Point"}
}
