{
  "type": "Feature",
  "properties": {
    "iso:country":"GB",
    "wof:name":"L6 8NL",
    "wof:placetype":"postalcode"
},
  "geometry": {"coordinates":[-2.93868918099617,53.4154852519917],"type":"Point"}
}