{
  "type": "Feature",
  "properties": {
    "iso:country":"GB",
    "wof:name":"TN12 7LB",
    "wof:placetype":"postalcode"
},
  "geometry": {"coordinates":[0.37086405867502,51.14913596350033],"type":"Point"}
}