{
  "type": "Feature",
  "properties": {
    "iso:country": "GB",
    "wof:name": "TN12 7LB",
    "wof:placetype": "postalcode"
  },
  "geometry": {"coordinates":[0.370864,51.149136],"type":"Point"}
}
