{
  "type": "Feature",
  "properties": {
    "iso:country":"GB",
    "wof:name":"RM1 4YL",
    "wof:placetype":"postalcode"
},
  "geometry": {"coordinates":[0.18010521712817,51.59833884924073],"type":"Point"}
}