{
  "type": "Feature",
  "properties": {
    "iso:country":"GB",
    "wof:name":"BB1 1PW",
    "wof:placetype":"postalcode"
},
  "geometry": {"coordinates":[-2.45414803143904,53.74370860390948],"type":"Point"}
}