{
  "type": "Feature",
  "properties": {
    "iso:country":"GB",
    "wof:name":"OX2 9FG",
    "wof:placetype":"postalcode"
},
  "geometry": {"coordinates":[-1.310360442787,51.74550099410214],"type":"Point"}
}