{
  "type": "Feature",
  "properties": {
    "iso:country": "GB",
    "wof:name": "OX2 9FG",
    "wof:placetype": "postalcode"
  },
  "geometry": {"coordinates":[-1.310169,51.745505],"type":"Point"}
}
