{
  "type": "Feature",
  "properties": {
    "iso:country":"GB",
    "wof:name":"PA1 3HE",
    "wof:placetype":"postalcode"
},
  "geometry": {"coordinates":[-4.380412938572,55.84917115928025],"type":"Point"}
}