{
  "type": "Feature",
  "properties": {
    "date:inception_lower": "1980-01-01",
    "date:inception_upper": "1980-01-01",
    "iso:country": "GB",
    "wof:name": "PA1 3HE",
    "wof:placetype": "postalcode"
  },
  "geometry": {"coordinates":[-4.380413,55.849171],"type":"Point"}
}
