{
  "type": "Feature",
  "properties": {
    "iso:country": "GB",
    "wof:name": "PA1 3HE",
    "wof:placetype": "postalcode"
  },
  "geometry": {"coordinates":[-4.380413,55.849171],"type":"Point"}
}
