{
  "type": "Feature",
  "properties": {
    "iso:country": "GB",
    "wof:name": "RG17 9QN",
    "wof:placetype": "postalcode"
  },
  "geometry": {"coordinates":[-1.46313,51.368881],"type":"Point"}
}
