{
  "type": "Feature",
  "properties": {
    "iso:country":"GB",
    "wof:name":"MK4 3EF",
    "wof:placetype":"postalcode"
},
  "geometry": {"coordinates":[-0.78819234555961,51.9989437925042],"type":"Point"}
}