{
  "type": "Feature",
  "properties": {
    "date:inception_lower": "2001-06-01",
    "date:inception_upper": "2001-06-01",
    "iso:country": "GB",
    "wof:name": "MK4 3EF",
    "wof:placetype": "postalcode"
  },
  "geometry": {"coordinates":[-0.788192,51.998944],"type":"Point"}
}
