{
  "type": "Feature",
  "properties": {
    "date:inception_lower": "1980-01-01",
    "date:inception_upper": "1980-01-01",
    "iso:country": "GB",
    "wof:name": "SE9 4EE",
    "wof:placetype": "postalcode"
  },
  "geometry": {"coordinates":[0.046299,51.424203],"type":"Point"}
}
