{
  "type": "Feature",
  "properties": {
    "date:inception_lower": "1980-01-01",
    "date:inception_upper": "1980-01-01",
    "iso:country": "GB",
    "wof:name": "PO40 9UA",
    "wof:placetype": "postalcode"
  },
  "geometry": {"coordinates":[-1.50574,50.673624],"type":"Point"}
}
