{
  "type": "Feature",
  "properties": {
    "iso:country":"GB",
    "wof:name":"BN10 7QJ",
    "wof:placetype":"postalcode"
},
  "geometry": {"coordinates":[-0.00074289177061,50.79902391461169],"type":"Point"}
}