{
  "type": "Feature",
  "properties": {
    "date:inception_lower": "1980-01-01",
    "date:inception_upper": "1980-01-01",
    "iso:country": "GB",
    "wof:name": "NN12 8HF",
    "wof:placetype": "postalcode"
  },
  "geometry": {"coordinates":[-1.118154,52.171942],"type":"Point"}
}
