{
  "type": "Feature",
  "properties": {
    "iso:country": "GB",
    "wof:name": "S1 2JJ",
    "wof:placetype": "postalcode"
  },
  "geometry": {"coordinates":[-1.469115,53.37949],"type":"Point"}
}
