{
  "type": "Feature",
  "properties": {
    "iso:country":"GB",
    "wof:name":"SR8 1HU",
    "wof:placetype":"postalcode"
},
  "geometry": {"coordinates":[-1.34705585846876,54.75297479020632],"type":"Point"}
}