{
  "type": "Feature",
  "properties": {
    "date:inception_lower":"1995-07-01",
    "date:inception_upper":"1995-07-31",
    "iso:country":"GB",
    "wof:name":"RG30 2DL",
    "wof:placetype":"postalcode"
},
  "geometry": {"coordinates":[-0.997513,51.449592],"type":"Point"}
}