{
  "type": "Feature",
  "properties": {
    "iso:country": "GB",
    "wof:name": "RG30 2DL",
    "wof:placetype": "postalcode"
  },
  "geometry": {"coordinates":[-0.997513,51.449592],"type":"Point"}
}
