{
  "type": "Feature",
  "properties": {
    "iso:country":"GB",
    "wof:name":"RG30 2DL",
    "wof:placetype":"postalcode"
},
  "geometry": {"coordinates":[-0.99751258062317,51.44959204401115],"type":"Point"}
}