{
  "type": "Feature",
  "properties": {
    "iso:country":"GB",
    "wof:name":"WF10 3NF",
    "wof:placetype":"postalcode"
},
  "geometry": {"coordinates":[-1.30696566931626,53.72271285492293],"type":"Point"}
}