{
  "type": "Feature",
  "properties": {
    "iso:country":"GB",
    "wof:name":"KT12 2PU",
    "wof:placetype":"postalcode"
},
  "geometry": {"coordinates":[-0.42136259413674,51.38744401554027],"type":"Point"}
}