{
  "type": "Feature",
  "properties": {
    "iso:country":"GB",
    "wof:name":"B73 6TL",
    "wof:placetype":"postalcode"
},
  "geometry": {"coordinates":[-1.88023748740023,52.56581835321388],"type":"Point"}
}