{
  "type": "Feature",
  "properties": {
    "iso:country": "GB",
    "wof:name": "TQ9 7UE",
    "wof:placetype": "postalcode"
  },
  "geometry": {"coordinates":[-3.681623,50.384988],"type":"Point"}
}
