{
  "type": "Feature",
  "properties": {
    "iso:country":"GB",
    "wof:name":"TQ9 7UE",
    "wof:placetype":"postalcode"
},
  "geometry": {"coordinates":[-3.68162327288831,50.38498840392433],"type":"Point"}
}