{
  "type": "Feature",
  "properties": {
    "iso:country":"GB",
    "wof:name":"SY13 4PS",
    "wof:placetype":"postalcode"
},
  "geometry": {"coordinates":[-2.58936124696243,52.91463089364634],"type":"Point"}
}