{
  "type": "Feature",
  "properties": {
    "iso:country": "GB",
    "wof:name": "SY13 4PS",
    "wof:placetype": "postalcode"
  },
  "geometry": {"coordinates":[-2.589361,52.914631],"type":"Point"}
}
