{
  "type": "Feature",
  "properties": {
    "date:inception_lower": "1980-01-01",
    "date:inception_upper": "1980-01-01",
    "iso:country": "GB",
    "wof:name": "SY13 4PS",
    "wof:placetype": "postalcode"
  },
  "geometry": {"coordinates":[-2.589361,52.914631],"type":"Point"}
}
