{
  "type": "Feature",
  "properties": {
    "date:inception_lower":"1980-01-01",
    "date:inception_upper":"1980-01-31",
    "iso:country":"GB",
    "wof:name":"FK2 8AT",
    "wof:placetype":"postalcode"
},
  "geometry": {"coordinates":[-3.783872,56.030729],"type":"Point"}
}