{
  "type": "Feature",
  "properties": {
    "date:inception_lower": "2019-08-01",
    "date:inception_upper": "2019-08-01",
    "iso:country": "GB",
    "wof:name": "CA15 7FB",
    "wof:placetype": "postalcode"
  },
  "geometry": {"coordinates":[-3.455532,54.680112],"type":"Point"}
}
