{
  "type": "Feature",
  "properties": {
    "date:inception_lower": "2005-10-01",
    "date:inception_upper": "2005-10-01",
    "iso:country": "GB",
    "wof:name": "CF10 4FB",
    "wof:placetype": "postalcode"
  },
  "geometry": {"coordinates":[-3.170325,51.478038],"type":"Point"}
}
