{
  "type": "Feature",
  "properties": {
    "iso:country":"GB",
    "wof:name":"L32 7QQ",
    "wof:placetype":"postalcode"
},
  "geometry": {"coordinates":[-2.88082458090034,53.46721628444654],"type":"Point"}
}