{
  "type": "Feature",
  "properties": {
    "iso:country":"GB",
    "wof:name":"EN3 5SS",
    "wof:placetype":"postalcode"
},
  "geometry": {"coordinates":[-0.04281924896147,51.66727465015767],"type":"Point"}
}