{
  "type": "Feature",
  "properties": {
    "iso:country":"GB",
    "wof:name":"SN4 0RN",
    "wof:placetype":"postalcode"
},
  "geometry": {"coordinates":[-1.78731302073298,51.5193389821272],"type":"Point"}
}