{
  "type": "Feature",
  "properties": {
    "iso:country": "GB",
    "wof:name": "EH33 1NN",
    "wof:placetype": "postalcode"
  },
  "geometry": {"coordinates":[-2.96745,55.943523],"type":"Point"}
}
