{
  "type": "Feature",
  "properties": {
    "date:inception_lower": "1982-06-01",
    "date:inception_upper": "1982-06-01",
    "iso:country": "GB",
    "wof:name": "EH33 1NN",
    "wof:placetype": "postalcode"
  },
  "geometry": {"coordinates":[-2.96745,55.943523],"type":"Point"}
}
