{
  "type": "Feature",
  "properties": {
    "iso:country":"GB",
    "wof:name":"EH33 1NN",
    "wof:placetype":"postalcode"
},
  "geometry": {"coordinates":[-2.96745040981844,55.94352254441819],"type":"Point"}
}