{
  "type": "Feature",
  "properties": {
    "iso:country":"GB",
    "wof:name":"TS20 2NL",
    "wof:placetype":"postalcode"
},
  "geometry": {"coordinates":[-1.31553967212623,54.58271577241894],"type":"Point"}
}