{
  "type": "Feature",
  "properties": {
    "date:inception_lower":"1980-01-01",
    "date:inception_upper":"1980-01-31",
    "iso:country":"GB",
    "wof:name":"TS20 2NL",
    "wof:placetype":"postalcode"
},
  "geometry": {"coordinates":[-1.31554,54.582716],"type":"Point"}
}