{
  "type": "Feature",
  "properties": {
    "iso:country": "GB",
    "wof:name": "OX33 1BF",
    "wof:placetype": "postalcode"
  },
  "geometry": {"coordinates":[-1.143391,51.802559],"type":"Point"}
}
