{
  "type": "Feature",
  "properties": {
    "iso:country": "GB",
    "wof:name": "L13 1DQ",
    "wof:placetype": "postalcode"
  },
  "geometry": {"coordinates":[-2.914978,53.406411],"type":"Point"}
}
