{
  "type": "Feature",
  "properties": {
    "iso:country":"GB",
    "wof:name":"L13 1DQ",
    "wof:placetype":"postalcode"
},
  "geometry": {"coordinates":[-2.91497779190757,53.40641078746582],"type":"Point"}
}