{
  "type": "Feature",
  "properties": {
    "iso:country":"GB",
    "wof:name":"LN6 3RH",
    "wof:placetype":"postalcode"
},
  "geometry": {"coordinates":[-0.60126956657739,53.20526418901525],"type":"Point"}
}