{
  "type": "Feature",
  "properties": {
    "date:inception_lower": "1983-07-01",
    "date:inception_upper": "1983-07-01",
    "iso:country": "GB",
    "wof:name": "LN6 3RH",
    "wof:placetype": "postalcode"
  },
  "geometry": {"coordinates":[-0.60127,53.205264],"type":"Point"}
}
