{
  "type": "Feature",
  "properties": {
    "iso:country":"GB",
    "wof:name":"LE4 8BE",
    "wof:placetype":"postalcode"
},
  "geometry": {"coordinates":[-1.09737255797279,52.68130645365142],"type":"Point"}
}