{
  "type": "Feature",
  "properties": {
    "iso:country":"GB",
    "wof:name":"DD2 4QR",
    "wof:placetype":"postalcode"
},
  "geometry": {"coordinates":[-3.0363647270572,56.47420513686043],"type":"Point"}
}