{
  "type": "Feature",
  "properties": {
    "date:inception_lower": "1980-01-01",
    "date:inception_upper": "1980-01-01",
    "iso:country": "GB",
    "wof:name": "WN4 8AU",
    "wof:placetype": "postalcode"
  },
  "geometry": {"coordinates":[-2.63284,53.493362],"type":"Point"}
}
