{
  "type": "Feature",
  "properties": {
    "iso:country":"GB",
    "wof:name":"WR9 0PU",
    "wof:placetype":"postalcode"
},
  "geometry": {"coordinates":[-2.2020384198066,52.3244045588856],"type":"Point"}
}