{
  "type": "Feature",
  "properties": {
    "iso:country": "GB",
    "wof:name": "EX2 6GB",
    "wof:placetype": "postalcode"
  },
  "geometry": {"coordinates":[-3.508248,50.705979],"type":"Point"}
}
