{
  "type": "Feature",
  "properties": {
    "date:inception_lower": "1993-01-01",
    "date:inception_upper": "1993-01-01",
    "iso:country": "GB",
    "wof:name": "CH3 7JS",
    "wof:placetype": "postalcode"
  },
  "geometry": {"coordinates":[-2.786322,53.21631],"type":"Point"}
}
