{
  "type": "Feature",
  "properties": {
    "iso:country": "GB",
    "wof:name": "CH3 7JS",
    "wof:placetype": "postalcode"
  },
  "geometry": {"coordinates":[-2.786322,53.21631],"type":"Point"}
}
