{
  "type": "Feature",
  "properties": {
    "date:inception_lower": "1980-01-01",
    "date:inception_upper": "1980-01-01",
    "iso:country": "GB",
    "wof:name": "DH4 7EP",
    "wof:placetype": "postalcode"
  },
  "geometry": {"coordinates":[-1.486418,54.877461],"type":"Point"}
}
