{
  "type": "Feature",
  "properties": {
    "date:inception_lower": "2016-08-01",
    "date:inception_upper": "2016-08-01",
    "iso:country": "GB",
    "wof:name": "B65 9AB",
    "wof:placetype": "postalcode"
  },
  "geometry": {"coordinates":[-2.037449,52.493178],"type":"Point"}
}
