{
  "type": "Feature",
  "properties": {
    "iso:country":"GB",
    "wof:name":"SK6 7EN",
    "wof:placetype":"postalcode"
},
  "geometry": {"coordinates":[-2.0685511142549,53.37755731514779],"type":"Point"}
}