{
  "type": "Feature",
  "properties": {
    "iso:country":"GB",
    "wof:name":"L25 2YE",
    "wof:placetype":"postalcode"
},
  "geometry": {"coordinates":[-2.86742945630379,53.39833421197917],"type":"Point"}
}