{
  "type": "Feature",
  "properties": {
    "iso:country": "GB",
    "wof:name": "PO17 5FW",
    "wof:placetype": "postalcode"
  },
  "geometry": {"coordinates":[-1.202531,50.879929],"type":"Point"}
}
