{
  "type": "Feature",
  "properties": {
    "iso:country": "GB",
    "wof:name": "TR19 7EL",
    "wof:placetype": "postalcode"
  },
  "geometry": {"coordinates":[-5.671787,50.154774],"type":"Point"}
}
