{
  "type": "Feature",
  "properties": {
    "iso:country": "GB",
    "wof:name": "NG8 2FF",
    "wof:placetype": "postalcode"
  },
  "geometry": {"coordinates":[-1.222147,52.957016],"type":"Point"}
}
