{
  "type": "Feature",
  "properties": {
    "iso:country": "GB",
    "wof:name": "DE72 2DZ",
    "wof:placetype": "postalcode"
  },
  "geometry": {"coordinates":[-1.381519,52.862976],"type":"Point"}
}
