{
  "type": "Feature",
  "properties": {
    "iso:country":"GB",
    "wof:name":"DE72 2DZ",
    "wof:placetype":"postalcode"
},
  "geometry": {"coordinates":[-1.38151856545856,52.86297586241304],"type":"Point"}
}