{
  "type": "Feature",
  "properties": {
    "iso:country":"GB",
    "wof:name":"BA12 7EJ",
    "wof:placetype":"postalcode"
},
  "geometry": {"coordinates":[-2.19792962033203,51.14907538000973],"type":"Point"}
}