{
  "type": "Feature",
  "properties": {
    "date:inception_lower":"1990-02-01",
    "date:inception_upper":"1990-02-28",
    "iso:country":"GB",
    "wof:name":"LN2 4UA",
    "wof:placetype":"postalcode"
},
  "geometry": {"coordinates":[-0.51005,53.250757],"type":"Point"}
}