{
  "type": "Feature",
  "properties": {
    "iso:country": "GB",
    "wof:name": "LN2 4UA",
    "wof:placetype": "postalcode"
  },
  "geometry": {"coordinates":[-0.51005,53.250757],"type":"Point"}
}
