{
  "type": "Feature",
  "properties": {
    "iso:country":"GB",
    "wof:name":"CV35 0NQ",
    "wof:placetype":"postalcode"
},
  "geometry": {"coordinates":[-1.53698393237868,52.14816081536893],"type":"Point"}
}