{
  "type": "Feature",
  "properties": {
    "iso:country":"GB",
    "wof:name":"M20 4QN",
    "wof:placetype":"postalcode"
},
  "geometry": {"coordinates":[-2.22302037025379,53.42962790088476],"type":"Point"}
}