{
  "type": "Feature",
  "properties": {
    "iso:country":"GB",
    "wof:name":"BN6 9TD",
    "wof:placetype":"postalcode"
},
  "geometry": {"coordinates":[-0.18376553579376,50.93653097825575],"type":"Point"}
}