{
  "type": "Feature",
  "properties": {
    "iso:country": "GB",
    "wof:name": "BN6 9TD",
    "wof:placetype": "postalcode"
  },
  "geometry": {"coordinates":[-0.183765,50.936531],"type":"Point"}
}
