{
  "type": "Feature",
  "properties": {
    "iso:country":"GB",
    "wof:name":"GL56 0LU",
    "wof:placetype":"postalcode"
},
  "geometry": {"coordinates":[-1.69992704743344,51.98819599011668],"type":"Point"}
}