{
  "type": "Feature",
  "properties": {
    "iso:country":"GB",
    "wof:name":"LA13 9HD",
    "wof:placetype":"postalcode"
},
  "geometry": {"coordinates":[-3.2054952867156,54.12055517909529],"type":"Point"}
}