{
  "type": "Feature",
  "properties": {
    "iso:country": "GB",
    "wof:name": "FY4 5QL",
    "wof:placetype": "postalcode"
  },
  "geometry": {"coordinates":[-3.024068,53.788853],"type":"Point"}
}
