{
  "type": "Feature",
  "properties": {
    "iso:country":"GB",
    "wof:name":"MK40 2QG",
    "wof:placetype":"postalcode"
},
  "geometry": {"coordinates":[-0.47397626320822,52.139217079769],"type":"Point"}
}