{
  "type": "Feature",
  "properties": {
    "iso:country": "GB",
    "wof:name": "ST11 9AJ",
    "wof:placetype": "postalcode"
  },
  "geometry": {"coordinates":[-2.044729,52.966111],"type":"Point"}
}
