{
  "type": "Feature",
  "properties": {
    "iso:country":"GB",
    "wof:name":"ST11 9AJ",
    "wof:placetype":"postalcode"
},
  "geometry": {"coordinates":[-2.04472908837809,52.96611057981464],"type":"Point"}
}