{
  "type": "Feature",
  "properties": {
    "iso:country":"GB",
    "wof:name":"SK7 4AR",
    "wof:placetype":"postalcode"
},
  "geometry": {"coordinates":[-2.12573612448162,53.38395547880904],"type":"Point"}
}