{
  "type": "Feature",
  "properties": {
    "date:inception_lower": "2018-09-01",
    "date:inception_upper": "2018-09-01",
    "iso:country": "GB",
    "wof:name": "GU34 4FG",
    "wof:placetype": "postalcode"
  },
  "geometry": {"coordinates":[-0.971707,51.165243],"type":"Point"}
}
