{
  "type": "Feature",
  "properties": {
    "iso:country": "GB",
    "wof:name": "DH9 7BH",
    "wof:placetype": "postalcode"
  },
  "geometry": {"coordinates":[-1.709452,54.860289],"type":"Point"}
}
