{
  "type": "Feature",
  "properties": {
    "iso:country":"GB",
    "wof:name":"DH9 7BH",
    "wof:placetype":"postalcode"
},
  "geometry": {"coordinates":[-1.70945177999032,54.86028912233984],"type":"Point"}
}