{
  "type": "Feature",
  "properties": {
    "iso:country": "GB",
    "wof:name": "CO16 8YZ",
    "wof:placetype": "postalcode"
  },
  "geometry": {"coordinates":[1.128739,51.806587],"type":"Point"}
}
