{
  "type": "Feature",
  "properties": {
    "iso:country": "GB",
    "wof:name": "KT17 1LU",
    "wof:placetype": "postalcode"
  },
  "geometry": {"coordinates":[-0.253285,51.345806],"type":"Point"}
}
