{
  "type": "Feature",
  "properties": {
    "iso:country": "GB",
    "wof:name": "CW5 8DN",
    "wof:placetype": "postalcode"
  },
  "geometry": {"coordinates":[-2.584868,53.005946],"type":"Point"}
}
