{
  "type": "Feature",
  "properties": {
    "iso:country":"GB",
    "wof:name":"CW5 8DN",
    "wof:placetype":"postalcode"
},
  "geometry": {"coordinates":[-2.58489822112407,53.0060297308283],"type":"Point"}
}