{
  "type": "Feature",
  "properties": {
    "iso:country":"GB",
    "wof:name":"SE27 9EP",
    "wof:placetype":"postalcode"
},
  "geometry": {"coordinates":[-0.10326334751671,51.43465936923884],"type":"Point"}
}