{
  "type": "Feature",
  "properties": {
    "date:inception_lower": "1980-01-01",
    "date:inception_upper": "1980-01-01",
    "iso:country": "GB",
    "wof:name": "CO16 8QE",
    "wof:placetype": "postalcode"
  },
  "geometry": {"coordinates":[1.085118,51.802012],"type":"Point"}
}
