{
  "type": "Feature",
  "properties": {
    "iso:country":"GB",
    "wof:name":"DY12 2UL",
    "wof:placetype":"postalcode"
},
  "geometry": {"coordinates":[-2.36219145914845,52.36430690811901],"type":"Point"}
}