{
  "type": "Feature",
  "properties": {
    "iso:country":"GB",
    "wof:name":"RH12 1RL",
    "wof:placetype":"postalcode"
},
  "geometry": {"coordinates":[-0.32251165153328,51.06441916566983],"type":"Point"}
}