{
  "type": "Feature",
  "properties": {
    "date:inception_lower": "1997-12-01",
    "date:inception_upper": "1997-12-01",
    "iso:country": "GB",
    "wof:name": "SN14 0TW",
    "wof:placetype": "postalcode"
  },
  "geometry": {"coordinates":[-2.144766,51.446637],"type":"Point"}
}
