{
  "type": "Feature",
  "properties": {
    "iso:country": "GB",
    "wof:name": "DL8 1SQ",
    "wof:placetype": "postalcode"
  },
  "geometry": {"coordinates":[-1.669894,54.301468],"type":"Point"}
}
