{
  "type": "Feature",
  "properties": {
    "iso:country":"GB",
    "wof:name":"SN13 0HF",
    "wof:placetype":"postalcode"
},
  "geometry": {"coordinates":[-2.18474199579381,51.43303993742826],"type":"Point"}
}