{
  "type": "Feature",
  "properties": {
    "iso:country": "GB",
    "wof:name": "KT11 3HE",
    "wof:placetype": "postalcode"
  },
  "geometry": {"coordinates":[-0.398961,51.323607],"type":"Point"}
}
