{
  "type": "Feature",
  "properties": {
    "iso:country":"GB",
    "wof:name":"HA7 1LJ",
    "wof:placetype":"postalcode"
},
  "geometry": {"coordinates":[-0.30172189192634,51.59658805804545],"type":"Point"}
}