{
  "type": "Feature",
  "properties": {
    "iso:country":"GB",
    "wof:name":"S8 0NQ",
    "wof:placetype":"postalcode"
},
  "geometry": {"coordinates":[-1.48444911286446,53.3470540112778],"type":"Point"}
}