{
  "type": "Feature",
  "properties": {
    "date:inception_lower":"2000-12-01",
    "date:inception_upper":"2000-12-31",
    "iso:country":"GB",
    "wof:name":"W1H 4NJ",
    "wof:placetype":"postalcode"
},
  "geometry": {"coordinates":[-0.165045,51.519642],"type":"Point"}
}