{
  "type": "Feature",
  "properties": {
    "iso:country":"GB",
    "wof:name":"EH47 7EB",
    "wof:placetype":"postalcode"
},
  "geometry": {"coordinates":[-3.5917334019398,55.87574329950078],"type":"Point"}
}