{
  "type": "Feature",
  "properties": {
    "date:inception_lower": "2021-10-01",
    "date:inception_upper": "2021-10-01",
    "iso:country": "GB",
    "wof:name": "ML1 3GN",
    "wof:placetype": "postalcode"
  },
  "geometry": {"coordinates":[-4.005293,55.79079],"type":"Point"}
}
