{
  "type": "Feature",
  "properties": {
    "iso:country":"GB",
    "wof:name":"B94 5LR",
    "wof:placetype":"postalcode"
},
  "geometry": {"coordinates":[-1.84160443024328,52.37148152908037],"type":"Point"}
}