{
  "type": "Feature",
  "properties": {
    "iso:country":"GB",
    "wof:name":"SG6 2BT",
    "wof:placetype":"postalcode"
},
  "geometry": {"coordinates":[-0.21598306364359,51.96863004783598],"type":"Point"}
}