{
  "type": "Feature",
  "properties": {
    "date:inception_lower": "1980-01-01",
    "date:inception_upper": "1980-01-01",
    "iso:country": "GB",
    "wof:name": "SG6 2BT",
    "wof:placetype": "postalcode"
  },
  "geometry": {"coordinates":[-0.215983,51.96863],"type":"Point"}
}
