{
  "type": "Feature",
  "properties": {
    "iso:country": "GB",
    "wof:name": "IP31 3ET",
    "wof:placetype": "postalcode"
  },
  "geometry": {"coordinates":[0.916703,52.281527],"type":"Point"}
}
