{
  "type": "Feature",
  "properties": {
    "iso:country":"GB",
    "wof:name":"EN5 5HU",
    "wof:placetype":"postalcode"
},
  "geometry": {"coordinates":[-0.17563152331717,51.65280425386928],"type":"Point"}
}