{
  "type": "Feature",
  "properties": {
    "iso:country":"GB",
    "wof:name":"WA15 8TB",
    "wof:placetype":"postalcode"
},
  "geometry": {"coordinates":[-2.30999816692387,53.3679246842717],"type":"Point"}
}