{
  "type": "Feature",
  "properties": {
    "iso:country": "GB",
    "wof:name": "DG9 8NA",
    "wof:placetype": "postalcode"
  },
  "geometry": {"coordinates":[-5.007115,54.882458],"type":"Point"}
}
