{
  "type": "Feature",
  "properties": {
    "date:inception_lower": "1980-01-01",
    "date:inception_upper": "1980-01-01",
    "iso:country": "GB",
    "wof:name": "DG9 8NA",
    "wof:placetype": "postalcode"
  },
  "geometry": {"coordinates":[-5.007115,54.882458],"type":"Point"}
}
