{
  "type": "Feature",
  "properties": {
    "iso:country":"GB",
    "wof:name":"TW12 3BP",
    "wof:placetype":"postalcode"
},
  "geometry": {"coordinates":[-0.38086084374841,51.42208765881097],"type":"Point"}
}