{
  "type": "Feature",
  "properties": {
    "iso:country":"GB",
    "wof:name":"KY4 8BQ",
    "wof:placetype":"postalcode"
},
  "geometry": {"coordinates":[-3.37187371450202,56.0840185368957],"type":"Point"}
}