{
  "type": "Feature",
  "properties": {
    "iso:country":"GB",
    "wof:name":"W8 4RA",
    "wof:placetype":"postalcode"
},
  "geometry": {"coordinates":[-0.19270394180423,51.50802158311349],"type":"Point"}
}