{
  "type": "Feature",
  "properties": {
    "iso:country":"GB",
    "wof:name":"CT9 4BS",
    "wof:placetype":"postalcode"
},
  "geometry": {"coordinates":[1.37737497520968,51.3771677057277],"type":"Point"}
}