{
  "type": "Feature",
  "properties": {
    "date:inception_lower":"2002-08-01",
    "date:inception_upper":"2002-08-31",
    "iso:country":"GB",
    "wof:name":"SS8 8QN",
    "wof:placetype":"postalcode"
},
  "geometry": {"coordinates":[0.614472,51.525035],"type":"Point"}
}