{
  "type": "Feature",
  "properties": {
    "date:inception_lower":"1980-01-01",
    "date:inception_upper":"1980-01-31",
    "iso:country":"GB",
    "wof:name":"KT10 8QG",
    "wof:placetype":"postalcode"
},
  "geometry": {"coordinates":[-0.372121,51.373345],"type":"Point"}
}