{
  "type": "Feature",
  "properties": {
    "iso:country":"GB",
    "wof:name":"SW19 8BQ",
    "wof:placetype":"postalcode"
},
  "geometry": {"coordinates":[-0.19920107609109,51.43896023476911],"type":"Point"}
}