{
  "type": "Feature",
  "properties": {
    "iso:country": "GB",
    "wof:name": "DD1 5DQ",
    "wof:placetype": "postalcode"
  },
  "geometry": {"coordinates":[-2.984058,56.460345],"type":"Point"}
}
