{
  "type": "Feature",
  "properties": {
    "date:inception_lower":"1980-01-01",
    "date:inception_upper":"1980-01-31",
    "iso:country":"GB",
    "wof:name":"B32 1ER",
    "wof:placetype":"postalcode"
},
  "geometry": {"coordinates":[-1.994128,52.461775],"type":"Point"}
}