{
  "type": "Feature",
  "properties": {
    "iso:country":"GB",
    "wof:name":"B32 1ER",
    "wof:placetype":"postalcode"
},
  "geometry": {"coordinates":[-1.9941277876999,52.46177540469576],"type":"Point"}
}