{
  "type": "Feature",
  "properties": {
    "iso:country":"GB",
    "wof:name":"NR3 2PR",
    "wof:placetype":"postalcode"
},
  "geometry": {"coordinates":[1.27040250671236,52.65329172034073],"type":"Point"}
}