{
  "type": "Feature",
  "properties": {
    "iso:country":"GB",
    "wof:name":"WS8 7DG",
    "wof:placetype":"postalcode"
},
  "geometry": {"coordinates":[-1.93244564592406,52.63463131401393],"type":"Point"}
}