{
  "type": "Feature",
  "properties": {
    "iso:country":"GB",
    "wof:name":"DD5 2AA",
    "wof:placetype":"postalcode"
},
  "geometry": {"coordinates":[-2.87641303823861,56.46709091149994],"type":"Point"}
}