{
  "type": "Feature",
  "properties": {
    "iso:country": "GB",
    "wof:name": "CW9 5UR",
    "wof:placetype": "postalcode"
  },
  "geometry": {"coordinates":[-2.511443,53.256417],"type":"Point"}
}
