{
  "type": "Feature",
  "properties": {
    "iso:country": "GB",
    "wof:name": "CH45 6TT",
    "wof:placetype": "postalcode"
  },
  "geometry": {"coordinates":[-3.061835,53.42498],"type":"Point"}
}
