{
  "type": "Feature",
  "properties": {
    "date:inception_lower": "1999-06-01",
    "date:inception_upper": "1999-06-01",
    "iso:country": "GB",
    "wof:name": "CH45 6TT",
    "wof:placetype": "postalcode"
  },
  "geometry": {"coordinates":[-3.061835,53.42498],"type":"Point"}
}
