{
  "type": "Feature",
  "properties": {
    "date:inception_lower": "1980-01-01",
    "date:inception_upper": "1980-01-01",
    "iso:country": "GB",
    "wof:name": "KA1 1UF",
    "wof:placetype": "postalcode"
  },
  "geometry": {"coordinates":[-4.515435,55.600655],"type":"Point"}
}
