{
  "type": "Feature",
  "properties": {
    "iso:country": "GB",
    "wof:name": "EN11 8RG",
    "wof:placetype": "postalcode"
  },
  "geometry": {"coordinates":[-0.016385,51.764183],"type":"Point"}
}
