{
  "type": "Feature",
  "properties": {
    "date:inception_lower":"2000-06-01",
    "date:inception_upper":"2000-06-30",
    "iso:country":"GB",
    "wof:name":"DN14 7SF",
    "wof:placetype":"postalcode"
},
  "geometry": {"coordinates":[-0.865018,53.74656],"type":"Point"}
}