{
  "type": "Feature",
  "properties": {
    "iso:country":"GB",
    "wof:name":"DN14 7SF",
    "wof:placetype":"postalcode"
},
  "geometry": {"coordinates":[-0.86501813328072,53.74656002829239],"type":"Point"}
}