{
  "type": "Feature",
  "properties": {
    "iso:country": "GB",
    "wof:name": "DN14 7SF",
    "wof:placetype": "postalcode"
  },
  "geometry": {"coordinates":[-0.865018,53.74656],"type":"Point"}
}
