{
  "type": "Feature",
  "properties": {
    "iso:country": "GB",
    "wof:name": "M41 6JG",
    "wof:placetype": "postalcode"
  },
  "geometry": {"coordinates":[-2.385367,53.449528],"type":"Point"}
}
