{
  "type": "Feature",
  "properties": {
    "iso:country":"GB",
    "wof:name":"M41 6JG",
    "wof:placetype":"postalcode"
},
  "geometry": {"coordinates":[-2.3853671727255,53.44952824858962],"type":"Point"}
}