{
  "type": "Feature",
  "properties": {
    "iso:country":"GB",
    "wof:name":"HG2 7PQ",
    "wof:placetype":"postalcode"
},
  "geometry": {"coordinates":[-1.50169713327845,53.99618652450698],"type":"Point"}
}