{
  "type": "Feature",
  "properties": {
    "iso:country":"GB",
    "wof:name":"BH12 1PH",
    "wof:placetype":"postalcode"
},
  "geometry": {"coordinates":[-1.9077784397016,50.73828479427844],"type":"Point"}
}