{
  "type": "Feature",
  "properties": {
    "iso:country":"GB",
    "wof:name":"PE30 5AF",
    "wof:placetype":"postalcode"
},
  "geometry": {"coordinates":[0.39767039327066,52.74886011462088],"type":"Point"}
}