{
  "type": "Feature",
  "properties": {
    "iso:country": "GB",
    "wof:name": "SA8 4EG",
    "wof:placetype": "postalcode"
  },
  "geometry": {"coordinates":[-3.850058,51.717606],"type":"Point"}
}
