{
  "type": "Feature",
  "properties": {
    "iso:country":"GB",
    "wof:name":"SA8 4EG",
    "wof:placetype":"postalcode"
},
  "geometry": {"coordinates":[-3.85005795963952,51.71760583308166],"type":"Point"}
}