{
  "type": "Feature",
  "properties": {
    "iso:country":"GB",
    "wof:name":"YO7 1TE",
    "wof:placetype":"postalcode"
},
  "geometry": {"coordinates":[-1.3462023548368,54.23317428310916],"type":"Point"}
}