{
  "type": "Feature",
  "properties": {
    "date:inception_lower": "2004-06-01",
    "date:inception_upper": "2004-06-01",
    "iso:country": "GB",
    "wof:name": "YO7 1TE",
    "wof:placetype": "postalcode"
  },
  "geometry": {"coordinates":[-1.346165,54.233178],"type":"Point"}
}
