{
  "type": "Feature",
  "properties": {
    "date:inception_lower":"1980-01-01",
    "date:inception_upper":"1980-01-31",
    "iso:country":"GB",
    "wof:name":"NE30 3SJ",
    "wof:placetype":"postalcode"
},
  "geometry": {"coordinates":[-1.439094,55.028295],"type":"Point"}
}