{
  "type": "Feature",
  "properties": {
    "iso:country":"GB",
    "wof:name":"NE30 3SJ",
    "wof:placetype":"postalcode"
},
  "geometry": {"coordinates":[-1.43909437112419,55.02829505951919],"type":"Point"}
}