{
  "type": "Feature",
  "properties": {
    "iso:country":"GB",
    "wof:name":"CB3 9DY",
    "wof:placetype":"postalcode"
},
  "geometry": {"coordinates":[0.10443701770858,52.19602604017341],"type":"Point"}
}