{
  "type": "Feature",
  "properties": {
    "iso:country": "GB",
    "wof:name": "PL2 2LD",
    "wof:placetype": "postalcode"
  },
  "geometry": {"coordinates":[-4.165191,50.390768],"type":"Point"}
}
