{
  "type": "Feature",
  "properties": {
    "date:inception_lower": "1980-01-01",
    "date:inception_upper": "1980-01-01",
    "iso:country": "GB",
    "wof:name": "DN17 4LY",
    "wof:placetype": "postalcode"
  },
  "geometry": {"coordinates":[-0.833841,53.611682],"type":"Point"}
}
