{
  "type": "Feature",
  "properties": {
    "date:inception_lower":"1980-01-01",
    "date:inception_upper":"1980-01-31",
    "iso:country":"GB",
    "wof:name":"DL15 0RH",
    "wof:placetype":"postalcode"
},
  "geometry": {"coordinates":[-1.702223,54.697256],"type":"Point"}
}