{
  "type": "Feature",
  "properties": {
    "date:inception_lower": "1980-01-01",
    "date:inception_upper": "1980-01-01",
    "iso:country": "GB",
    "wof:name": "DL15 0RH",
    "wof:placetype": "postalcode"
  },
  "geometry": {"coordinates":[-1.70214,54.697292],"type":"Point"}
}
