{
  "type": "Feature",
  "properties": {
    "date:inception_lower": "1980-01-01",
    "date:inception_upper": "1980-01-01",
    "iso:country": "GB",
    "wof:name": "EH12 0AS",
    "wof:placetype": "postalcode"
  },
  "geometry": {"coordinates":[-3.33858,55.95846],"type":"Point"}
}
