{
  "type": "Feature",
  "properties": {
    "iso:country": "GB",
    "wof:name": "CT4 7AL",
    "wof:placetype": "postalcode"
  },
  "geometry": {"coordinates":[1.074665,51.240364],"type":"Point"}
}
