{
  "type": "Feature",
  "properties": {
    "iso:country":"GB",
    "wof:name":"HX3 8FL",
    "wof:placetype":"postalcode"
},
  "geometry": {"coordinates":[-1.81415436582596,53.72547047380618],"type":"Point"}
}