{
  "type": "Feature",
  "properties": {
    "date:inception_lower": "2009-03-01",
    "date:inception_upper": "2009-03-01",
    "iso:country": "GB",
    "wof:name": "HX3 8FL",
    "wof:placetype": "postalcode"
  },
  "geometry": {"coordinates":[-1.814154,53.72547],"type":"Point"}
}
