{
  "type": "Feature",
  "properties": {
    "iso:country": "GB",
    "wof:name": "FK20 8RX",
    "wof:placetype": "postalcode"
  },
  "geometry": {"coordinates":[-4.690273,56.424768],"type":"Point"}
}
