{
  "type": "Feature",
  "properties": {
    "iso:country":"GB",
    "wof:name":"BH15 4GB",
    "wof:placetype":"postalcode"
},
  "geometry": {"coordinates":[-1.99688858105205,50.71097432321626],"type":"Point"}
}