{
  "type": "Feature",
  "properties": {
    "iso:country":"GB",
    "wof:name":"RG8 0PT",
    "wof:placetype":"postalcode"
},
  "geometry": {"coordinates":[-1.0811390630046,51.53406206816137],"type":"Point"}
}