{
  "type": "Feature",
  "properties": {
    "iso:country":"GB",
    "wof:name":"DH4 4EU",
    "wof:placetype":"postalcode"
},
  "geometry": {"coordinates":[-1.47626980092433,54.85717148397586],"type":"Point"}
}