{
  "type": "Feature",
  "properties": {
    "date:inception_lower": "1980-01-01",
    "date:inception_upper": "1980-01-01",
    "iso:country": "GB",
    "wof:name": "TW9 3DZ",
    "wof:placetype": "postalcode"
  },
  "geometry": {"coordinates":[-0.287737,51.480789],"type":"Point"}
}
