{
  "type": "Feature",
  "properties": {
    "iso:country":"GB",
    "wof:name":"TW9 3DZ",
    "wof:placetype":"postalcode"
},
  "geometry": {"coordinates":[-0.28773686365525,51.48078874902946],"type":"Point"}
}