{
  "type": "Feature",
  "properties": {
    "iso:country":"GB",
    "wof:name":"EH16 6BH",
    "wof:placetype":"postalcode"
},
  "geometry": {"coordinates":[-3.1594422361964,55.91949131108036],"type":"Point"}
}