{
  "type": "Feature",
  "properties": {
    "iso:country":"GB",
    "wof:name":"B68 8SJ",
    "wof:placetype":"postalcode"
},
  "geometry": {"coordinates":[-1.99949968465441,52.49532606826676],"type":"Point"}
}