{
  "type": "Feature",
  "properties": {
    "iso:country": "GB",
    "wof:name": "B68 8SJ",
    "wof:placetype": "postalcode"
  },
  "geometry": {"coordinates":[-1.9995,52.495326],"type":"Point"}
}
