{
  "type": "Feature",
  "properties": {
    "iso:country": "GB",
    "wof:name": "RG42 3EQ",
    "wof:placetype": "postalcode"
  },
  "geometry": {"coordinates":[-0.732349,51.421911],"type":"Point"}
}
