{
  "type": "Feature",
  "properties": {
    "date:inception_lower":"1995-07-01",
    "date:inception_upper":"1995-07-31",
    "iso:country":"GB",
    "wof:name":"RG42 3EQ",
    "wof:placetype":"postalcode"
},
  "geometry": {"coordinates":[-0.732349,51.421911],"type":"Point"}
}