{
  "type": "Feature",
  "properties": {
    "iso:country":"GB",
    "wof:name":"OL16 3HH",
    "wof:placetype":"postalcode"
},
  "geometry": {"coordinates":[-2.10373052517211,53.61367553045609],"type":"Point"}
}