{
  "type": "Feature",
  "properties": {
    "date:inception_lower": "1980-01-01",
    "date:inception_upper": "1980-01-01",
    "iso:country": "GB",
    "wof:name": "OL16 3HH",
    "wof:placetype": "postalcode"
  },
  "geometry": {"coordinates":[-2.10373,53.613676],"type":"Point"}
}
