{
  "type": "Feature",
  "properties": {
    "iso:country":"GB",
    "wof:name":"SA44 4UA",
    "wof:placetype":"postalcode"
},
  "geometry": {"coordinates":[-4.27738884002562,52.11233226253736],"type":"Point"}
}