{
  "type": "Feature",
  "properties": {
    "iso:country": "GB",
    "wof:name": "SA44 4UA",
    "wof:placetype": "postalcode"
  },
  "geometry": {"coordinates":[-4.277389,52.112332],"type":"Point"}
}
