{
  "type": "Feature",
  "properties": {
    "iso:country": "GB",
    "wof:name": "NR10 3DL",
    "wof:placetype": "postalcode"
  },
  "geometry": {"coordinates":[1.242544,52.697254],"type":"Point"}
}
