{
  "type": "Feature",
  "properties": {
    "date:inception_lower": "1980-01-01",
    "date:inception_upper": "1980-01-01",
    "iso:country": "GB",
    "wof:name": "TS3 8HE",
    "wof:placetype": "postalcode"
  },
  "geometry": {"coordinates":[-1.200122,54.56735],"type":"Point"}
}
