{
  "type": "Feature",
  "properties": {
    "iso:country": "GB",
    "wof:name": "IP6 9LR",
    "wof:placetype": "postalcode"
  },
  "geometry": {"coordinates":[1.192125,52.126583],"type":"Point"}
}
