{
  "type": "Feature",
  "properties": {
    "date:inception_lower":"1980-01-01",
    "date:inception_upper":"1980-01-31",
    "iso:country":"GB",
    "wof:name":"IP6 9LR",
    "wof:placetype":"postalcode"
},
  "geometry": {"coordinates":[1.192125,52.126583],"type":"Point"}
}