{
  "type": "Feature",
  "properties": {
    "iso:country":"GB",
    "wof:name":"IP6 9LR",
    "wof:placetype":"postalcode"
},
  "geometry": {"coordinates":[1.1921245231906,52.12658332460167],"type":"Point"}
}