{
  "type": "Feature",
  "properties": {
    "iso:country":"GB",
    "wof:name":"FY1 3RZ",
    "wof:placetype":"postalcode"
},
  "geometry": {"coordinates":[-3.04124152524348,53.82693583464572],"type":"Point"}
}