{
  "type": "Feature",
  "properties": {
    "iso:country": "GB",
    "wof:name": "FY1 3RZ",
    "wof:placetype": "postalcode"
  },
  "geometry": {"coordinates":[-3.041241,53.826936],"type":"Point"}
}
