{
  "type": "Feature",
  "properties": {
    "iso:country": "GB",
    "wof:name": "YO41 4EN",
    "wof:placetype": "postalcode"
  },
  "geometry": {"coordinates":[-0.96529,53.924162],"type":"Point"}
}
