{
  "type": "Feature",
  "properties": {
    "iso:country": "GB",
    "wof:name": "GU27 3ES",
    "wof:placetype": "postalcode"
  },
  "geometry": {"coordinates":[-0.722971,51.047286],"type":"Point"}
}
