{
  "type": "Feature",
  "properties": {
    "date:inception_lower": "1988-03-01",
    "date:inception_upper": "1988-03-01",
    "iso:country": "GB",
    "wof:name": "GU27 3ES",
    "wof:placetype": "postalcode"
  },
  "geometry": {"coordinates":[-0.722971,51.047286],"type":"Point"}
}
