{
  "type": "Feature",
  "properties": {
    "iso:country": "GB",
    "wof:name": "TA3 6PJ",
    "wof:placetype": "postalcode"
  },
  "geometry": {"coordinates":[-2.922873,51.001795],"type":"Point"}
}
