{
  "type": "Feature",
  "properties": {
    "iso:country":"GB",
    "wof:name":"LU3 1EZ",
    "wof:placetype":"postalcode"
},
  "geometry": {"coordinates":[-0.42311665197334,51.89322415870183],"type":"Point"}
}