{
  "type": "Feature",
  "properties": {
    "iso:country":"GB",
    "wof:name":"BH16 6HQ",
    "wof:placetype":"postalcode"
},
  "geometry": {"coordinates":[-2.06611816477265,50.76182686359856],"type":"Point"}
}