{
  "type": "Feature",
  "properties": {
    "iso:country":"GB",
    "wof:name":"SE9 2EZ",
    "wof:placetype":"postalcode"
},
  "geometry": {"coordinates":[0.08072845646566,51.44013458835586],"type":"Point"}
}