{
  "type": "Feature",
  "properties": {
    "iso:country":"GB",
    "wof:name":"GL1 5NZ",
    "wof:placetype":"postalcode"
},
  "geometry": {"coordinates":[-2.25262513442842,51.84866933431998],"type":"Point"}
}