{
  "type": "Feature",
  "properties": {
    "date:inception_lower": "1988-03-01",
    "date:inception_upper": "1988-03-01",
    "iso:country": "GB",
    "wof:name": "GL1 5NZ",
    "wof:placetype": "postalcode"
  },
  "geometry": {"coordinates":[-2.252625,51.848669],"type":"Point"}
}
