{
  "type": "Feature",
  "properties": {
    "date:inception_lower": "1994-12-01",
    "date:inception_upper": "1994-12-01",
    "iso:country": "GB",
    "wof:name": "SO14 5QL",
    "wof:placetype": "postalcode"
  },
  "geometry": {"coordinates":[-1.380127,50.91016],"type":"Point"}
}
