{
  "type": "Feature",
  "properties": {
    "date:inception_lower": "1980-01-01",
    "date:inception_upper": "1980-01-01",
    "iso:country": "GB",
    "wof:name": "BD20 0ES",
    "wof:placetype": "postalcode"
  },
  "geometry": {"coordinates":[-1.937152,53.91261],"type":"Point"}
}
