{
  "type": "Feature",
  "properties": {
    "iso:country":"GB",
    "wof:name":"BD20 0ES",
    "wof:placetype":"postalcode"
},
  "geometry": {"coordinates":[-1.93715224543089,53.91260958120233],"type":"Point"}
}