{
  "type": "Feature",
  "properties": {
    "date:inception_lower": "1980-01-01",
    "date:inception_upper": "1980-01-01",
    "iso:country": "GB",
    "wof:name": "NR15 1DS",
    "wof:placetype": "postalcode"
  },
  "geometry": {"coordinates":[1.395272,52.535437],"type":"Point"}
}
