{
  "type": "Feature",
  "properties": {
    "iso:country":"GB",
    "wof:name":"NR15 1DS",
    "wof:placetype":"postalcode"
},
  "geometry": {"coordinates":[1.39527208190096,52.53543664473976],"type":"Point"}
}