{
  "type": "Feature",
  "properties": {
    "iso:country":"GB",
    "wof:name":"NP20 6QA",
    "wof:placetype":"postalcode"
},
  "geometry": {"coordinates":[-3.00993308492223,51.61903560021347],"type":"Point"}
}