{
  "type": "Feature",
  "properties": {
    "iso:country":"GB",
    "wof:name":"KT2 7TE",
    "wof:placetype":"postalcode"
},
  "geometry": {"coordinates":[-0.27830966391751,51.4209498922422],"type":"Point"}
}