{
  "type": "Feature",
  "properties": {
    "iso:country": "GB",
    "wof:name": "KT2 7TE",
    "wof:placetype": "postalcode"
  },
  "geometry": {"coordinates":[-0.27831,51.42095],"type":"Point"}
}
