{
  "type": "Feature",
  "properties": {
    "iso:country":"GB",
    "wof:name":"MK41 7QP",
    "wof:placetype":"postalcode"
},
  "geometry": {"coordinates":[-0.46292381709411,52.15210189592064],"type":"Point"}
}