{
  "type": "Feature",
  "properties": {
    "iso:country":"GB",
    "wof:name":"PA3 2NT",
    "wof:placetype":"postalcode"
},
  "geometry": {"coordinates":[-4.43127107710272,55.85513287074507],"type":"Point"}
}