{
  "type": "Feature",
  "properties": {
    "iso:country":"GB",
    "wof:name":"CT18 7JH",
    "wof:placetype":"postalcode"
},
  "geometry": {"coordinates":[1.19852158238561,51.09642334192382],"type":"Point"}
}