{
  "type": "Feature",
  "properties": {
    "iso:country": "GB",
    "wof:name": "CT18 7JH",
    "wof:placetype": "postalcode"
  },
  "geometry": {"coordinates":[1.198522,51.096423],"type":"Point"}
}
