{
  "type": "Feature",
  "properties": {
    "iso:country": "GB",
    "wof:name": "HU5 2BH",
    "wof:placetype": "postalcode"
  },
  "geometry": {"coordinates":[-0.36295,53.763086],"type":"Point"}
}
