{
  "type": "Feature",
  "properties": {
    "iso:country": "GB",
    "wof:name": "CH1 6AE",
    "wof:placetype": "postalcode"
  },
  "geometry": {"coordinates":[-2.941168,53.21137],"type":"Point"}
}
