{
  "type": "Feature",
  "properties": {
    "date:inception_lower":"1980-01-01",
    "date:inception_upper":"1980-01-31",
    "iso:country":"GB",
    "wof:name":"CH1 6AE",
    "wof:placetype":"postalcode"
},
  "geometry": {"coordinates":[-2.941168,53.21137],"type":"Point"}
}