{
  "type": "Feature",
  "properties": {
    "iso:country": "GB",
    "wof:name": "LN13 0EX",
    "wof:placetype": "postalcode"
  },
  "geometry": {"coordinates":[0.129254,53.245946],"type":"Point"}
}
