{
  "type": "Feature",
  "properties": {
    "iso:country":"GB",
    "wof:name":"LN13 0EX",
    "wof:placetype":"postalcode"
},
  "geometry": {"coordinates":[0.12925436634037,53.2459462736031],"type":"Point"}
}