{
  "type": "Feature",
  "properties": {
    "iso:country": "GB",
    "wof:name": "KT19 8BS",
    "wof:placetype": "postalcode"
  },
  "geometry": {"coordinates":[-0.268695,51.333643],"type":"Point"}
}
