{
  "type": "Feature",
  "properties": {
    "iso:country":"GB",
    "wof:name":"S70 3HG",
    "wof:placetype":"postalcode"
},
  "geometry": {"coordinates":[-1.4507900589522,53.54414094816607],"type":"Point"}
}