{
  "type": "Feature",
  "properties": {
    "iso:country":"GB",
    "wof:name":"SN2 2PF",
    "wof:placetype":"postalcode"
},
  "geometry": {"coordinates":[-1.79845644350366,51.58081484175595],"type":"Point"}
}