{
  "type": "Feature",
  "properties": {
    "iso:country":"GB",
    "wof:name":"M50 2GZ",
    "wof:placetype":"postalcode"
},
  "geometry": {"coordinates":[-2.29861886373359,53.47696695146355],"type":"Point"}
}