{
  "type": "Feature",
  "properties": {
    "iso:country": "GB",
    "wof:name": "M50 2GZ",
    "wof:placetype": "postalcode"
  },
  "geometry": {"coordinates":[-2.29889,53.476984],"type":"Point"}
}
