{
  "type": "Feature",
  "properties": {
    "date:inception_lower":"1980-01-01",
    "date:inception_upper":"1980-01-31",
    "iso:country":"GB",
    "wof:name":"SW3 4TD",
    "wof:placetype":"postalcode"
},
  "geometry": {"coordinates":[-0.157309,51.489522],"type":"Point"}
}