{
  "type": "Feature",
  "properties": {
    "iso:country":"GB",
    "wof:name":"SW3 4TD",
    "wof:placetype":"postalcode"
},
  "geometry": {"coordinates":[-0.15730914589645,51.48952178279061],"type":"Point"}
}