{
  "type": "Feature",
  "properties": {
    "iso:country":"GB",
    "wof:name":"OX16 5BY",
    "wof:placetype":"postalcode"
},
  "geometry": {"coordinates":[-1.33463420773041,52.05958815881959],"type":"Point"}
}