{
  "type": "Feature",
  "properties": {
    "date:inception_lower":"2000-06-01",
    "date:inception_upper":"2000-06-30",
    "iso:country":"GB",
    "wof:name":"OX16 5BY",
    "wof:placetype":"postalcode"
},
  "geometry": {"coordinates":[-1.334634,52.059588],"type":"Point"}
}