{
  "type": "Feature",
  "properties": {
    "date:inception_lower": "1980-01-01",
    "date:inception_upper": "1980-01-01",
    "iso:country": "GB",
    "wof:name": "PE10 9QT",
    "wof:placetype": "postalcode"
  },
  "geometry": {"coordinates":[-0.388838,52.769966],"type":"Point"}
}
