{
  "type": "Feature",
  "properties": {
    "iso:country":"GB",
    "wof:name":"PE10 9QT",
    "wof:placetype":"postalcode"
},
  "geometry": {"coordinates":[-0.38883813200308,52.76996579669923],"type":"Point"}
}