{
  "type": "Feature",
  "properties": {
    "iso:country": "GB",
    "wof:name": "EH3 9PF",
    "wof:placetype": "postalcode"
  },
  "geometry": {"coordinates":[-3.211029,55.94047],"type":"Point"}
}
