{
  "type": "Feature",
  "properties": {
    "iso:country": "GB",
    "wof:name": "ME14 1FG",
    "wof:placetype": "postalcode"
  },
  "geometry": {"coordinates":[0.524438,51.275512],"type":"Point"}
}
