{
  "type": "Feature",
  "properties": {
    "date:inception_lower": "2011-12-01",
    "date:inception_upper": "2011-12-01",
    "iso:country": "GB",
    "wof:name": "ME14 1FG",
    "wof:placetype": "postalcode"
  },
  "geometry": {"coordinates":[0.524438,51.275512],"type":"Point"}
}
