{
  "type": "Feature",
  "properties": {
    "iso:country":"GB",
    "wof:name":"ME14 1FG",
    "wof:placetype":"postalcode"
},
  "geometry": {"coordinates":[0.52443747484954,51.27551223333199],"type":"Point"}
}