{
  "type": "Feature",
  "properties": {
    "date:inception_lower":"1981-06-01",
    "date:inception_upper":"1981-06-30",
    "iso:country":"GB",
    "wof:name":"RM12 6LG",
    "wof:placetype":"postalcode"
},
  "geometry": {"coordinates":[0.221103,51.55757],"type":"Point"}
}