{
  "type": "Feature",
  "properties": {
    "iso:country":"GB",
    "wof:name":"RM12 6LG",
    "wof:placetype":"postalcode"
},
  "geometry": {"coordinates":[0.22110321329754,51.55756972654439],"type":"Point"}
}