{
  "type": "Feature",
  "properties": {
    "iso:country":"GB",
    "wof:name":"IP8 3SZ",
    "wof:placetype":"postalcode"
},
  "geometry": {"coordinates":[1.10293560664698,52.04045802469814],"type":"Point"}
}