{
  "type": "Feature",
  "properties": {
    "iso:country": "GB",
    "wof:name": "DY10 3LQ",
    "wof:placetype": "postalcode"
  },
  "geometry": {"coordinates":[-2.171265,52.406434],"type":"Point"}
}
