{
  "type": "Feature",
  "properties": {
    "iso:country":"GB",
    "wof:name":"PA20 9BE",
    "wof:placetype":"postalcode"
},
  "geometry": {"coordinates":[-5.05380781828879,55.83435258762976],"type":"Point"}
}