{
  "type": "Feature",
  "properties": {
    "iso:country":"GB",
    "wof:name":"S62 7HT",
    "wof:placetype":"postalcode"
},
  "geometry": {"coordinates":[-1.34609373655956,53.47127459185268],"type":"Point"}
}