{
  "type": "Feature",
  "properties": {
    "iso:country": "GB",
    "wof:name": "TA11 7LD",
    "wof:placetype": "postalcode"
  },
  "geometry": {"coordinates":[-2.692276,51.03488],"type":"Point"}
}
