{
  "type": "Feature",
  "properties": {
    "iso:country":"GB",
    "wof:name":"SO18 2LB",
    "wof:placetype":"postalcode"
},
  "geometry": {"coordinates":[-1.37560790050452,50.9414212042996],"type":"Point"}
}