{
  "type": "Feature",
  "properties": {
    "date:inception_lower": "1980-01-01",
    "date:inception_upper": "1980-01-01",
    "iso:country": "GB",
    "wof:name": "KT1 3AG",
    "wof:placetype": "postalcode"
  },
  "geometry": {"coordinates":[-0.287458,51.4113],"type":"Point"}
}
