{
  "type": "Feature",
  "properties": {
    "iso:country": "GB",
    "wof:name": "KT1 3AG",
    "wof:placetype": "postalcode"
  },
  "geometry": {"coordinates":[-0.287458,51.4113],"type":"Point"}
}
