{
  "type": "Feature",
  "properties": {
    "iso:country":"GB",
    "wof:name":"KT1 3AG",
    "wof:placetype":"postalcode"
},
  "geometry": {"coordinates":[-0.28745816234191,51.41130009931857],"type":"Point"}
}