{
  "type": "Feature",
  "properties": {
    "iso:country":"GB",
    "wof:name":"KA22 7LN",
    "wof:placetype":"postalcode"
},
  "geometry": {"coordinates":[-4.81304787159071,55.65442959620218],"type":"Point"}
}