{
  "type": "Feature",
  "properties": {
    "iso:country": "GB",
    "wof:name": "KA22 7LN",
    "wof:placetype": "postalcode"
  },
  "geometry": {"coordinates":[-4.813048,55.65443],"type":"Point"}
}
