{
  "type": "Feature",
  "properties": {
    "iso:country":"GB",
    "wof:name":"IP7 5BE",
    "wof:placetype":"postalcode"
},
  "geometry": {"coordinates":[0.95672588419006,52.04460707863777],"type":"Point"}
}