{
  "type": "Feature",
  "properties": {
    "date:inception_lower": "1980-01-01",
    "date:inception_upper": "1980-01-01",
    "iso:country": "GB",
    "wof:name": "IP7 5BE",
    "wof:placetype": "postalcode"
  },
  "geometry": {"coordinates":[0.956729,52.044639],"type":"Point"}
}
