{
  "type": "Feature",
  "properties": {
    "iso:country":"GB",
    "wof:name":"TN22 1DD",
    "wof:placetype":"postalcode"
},
  "geometry": {"coordinates":[0.09425261919306,50.97651901246665],"type":"Point"}
}