{
  "type": "Feature",
  "properties": {
    "iso:country":"GB",
    "wof:name":"NN8 4BX",
    "wof:placetype":"postalcode"
},
  "geometry": {"coordinates":[-0.68397314636018,52.32344481407575],"type":"Point"}
}