{
  "type": "Feature",
  "properties": {
    "date:inception_lower":"1980-01-01",
    "date:inception_upper":"1980-01-31",
    "iso:country":"GB",
    "wof:name":"LL49 9SD",
    "wof:placetype":"postalcode"
},
  "geometry": {"coordinates":[-4.167823,52.943761],"type":"Point"}
}