{
  "type": "Feature",
  "properties": {
    "iso:country":"GB",
    "wof:name":"GU46 6AH",
    "wof:placetype":"postalcode"
},
  "geometry": {"coordinates":[-0.81132800555148,51.33570363653757],"type":"Point"}
}