{
  "type": "Feature",
  "properties": {
    "iso:country": "GB",
    "wof:name": "EX4 4AR",
    "wof:placetype": "postalcode"
  },
  "geometry": {"coordinates":[-3.542575,50.731763],"type":"Point"}
}
