{
  "type": "Feature",
  "properties": {
    "iso:country": "GB",
    "wof:name": "CW8 4RT",
    "wof:placetype": "postalcode"
  },
  "geometry": {"coordinates":[-2.573407,53.27974],"type":"Point"}
}
