{
  "type": "Feature",
  "properties": {
    "iso:country":"GB",
    "wof:name":"CW8 4RT",
    "wof:placetype":"postalcode"
},
  "geometry": {"coordinates":[-2.57340743496975,53.27974006736891],"type":"Point"}
}