{
  "type": "Feature",
  "properties": {
    "iso:country":"GB",
    "wof:name":"SR5 5AB",
    "wof:placetype":"postalcode"
},
  "geometry": {"coordinates":[-1.41362442405281,54.92333132641823],"type":"Point"}
}