{
  "type": "Feature",
  "properties": {
    "iso:country":"GB",
    "wof:name":"NW9 5WJ",
    "wof:placetype":"postalcode"
},
  "geometry": {"coordinates":[-0.25018052417355,51.60440063061118],"type":"Point"}
}