{
  "type": "Feature",
  "properties": {
    "iso:country": "GB",
    "wof:name": "LN4 1DB",
    "wof:placetype": "postalcode"
  },
  "geometry": {"coordinates":[-0.465748,53.222511],"type":"Point"}
}
