{
  "type": "Feature",
  "properties": {
    "iso:country":"GB",
    "wof:name":"LN4 1DB",
    "wof:placetype":"postalcode"
},
  "geometry": {"coordinates":[-0.46574795094689,53.22251083452279],"type":"Point"}
}