{
  "type": "Feature",
  "properties": {
    "iso:country":"GB",
    "wof:name":"LD3 7AD",
    "wof:placetype":"postalcode"
},
  "geometry": {"coordinates":[-3.38980314356347,51.94659338876345],"type":"Point"}
}