{
  "type": "Feature",
  "properties": {
    "date:inception_lower":"1980-01-01",
    "date:inception_upper":"1980-01-31",
    "iso:country":"GB",
    "wof:name":"LA3 1AE",
    "wof:placetype":"postalcode"
},
  "geometry": {"coordinates":[-2.877098,54.064457],"type":"Point"}
}