{
  "type": "Feature",
  "properties": {
    "iso:country": "GB",
    "wof:name": "LA3 1AE",
    "wof:placetype": "postalcode"
  },
  "geometry": {"coordinates":[-2.876958,54.064377],"type":"Point"}
}
