{
  "type": "Feature",
  "properties": {
    "iso:country":"GB",
    "wof:name":"LA3 1AE",
    "wof:placetype":"postalcode"
},
  "geometry": {"coordinates":[-2.87705307235661,54.06439209098272],"type":"Point"}
}