{
  "type": "Feature",
  "properties": {
    "iso:country":"GB",
    "wof:name":"NG9 5FJ",
    "wof:placetype":"postalcode"
},
  "geometry": {"coordinates":[-1.23876931732569,52.91843944444049],"type":"Point"}
}