{
  "type": "Feature",
  "properties": {
    "iso:country":"GB",
    "wof:name":"CO1 2EX",
    "wof:placetype":"postalcode"
},
  "geometry": {"coordinates":[0.9187909508711,51.87753587871197],"type":"Point"}
}