{
  "type": "Feature",
  "properties": {
    "iso:country":"GB",
    "wof:name":"WF9 4TE",
    "wof:placetype":"postalcode"
},
  "geometry": {"coordinates":[-1.34348373887979,53.60713972396398],"type":"Point"}
}