{
  "type": "Feature",
  "properties": {
    "iso:country":"GB",
    "wof:name":"BR5 2QJ",
    "wof:placetype":"postalcode"
},
  "geometry": {"coordinates":[0.110574355426,51.40927677097152],"type":"Point"}
}