{
  "type": "Feature",
  "properties": {
    "iso:country": "GB",
    "wof:name": "SA15 4RT",
    "wof:placetype": "postalcode"
  },
  "geometry": {"coordinates":[-4.180308,51.721112],"type":"Point"}
}
