{
  "type": "Feature",
  "properties": {
    "iso:country":"GB",
    "wof:name":"SA15 4RT",
    "wof:placetype":"postalcode"
},
  "geometry": {"coordinates":[-4.18030847924862,51.72111173473427],"type":"Point"}
}