{
  "type": "Feature",
  "properties": {
    "iso:country":"GB",
    "wof:name":"SA12 6TL",
    "wof:placetype":"postalcode"
},
  "geometry": {"coordinates":[-3.80980823618798,51.59742202872364],"type":"Point"}
}