{
  "type": "Feature",
  "properties": {
    "date:inception_lower": "1980-01-01",
    "date:inception_upper": "1980-01-01",
    "iso:country": "GB",
    "wof:name": "SA12 6TL",
    "wof:placetype": "postalcode"
  },
  "geometry": {"coordinates":[-3.809808,51.597422],"type":"Point"}
}
