{
  "type": "Feature",
  "properties": {
    "iso:country":"GB",
    "wof:name":"NW8 7AA",
    "wof:placetype":"postalcode"
},
  "geometry": {"coordinates":[-0.16775025377934,51.53267842530069],"type":"Point"}
}