{
  "type": "Feature",
  "properties": {
    "iso:country":"GB",
    "wof:name":"BL1 5BE",
    "wof:placetype":"postalcode"
},
  "geometry": {"coordinates":[-2.47411750801508,53.58070119467897],"type":"Point"}
}