{
  "type": "Feature",
  "properties": {
    "iso:country": "GB",
    "wof:name": "OX26 1BN",
    "wof:placetype": "postalcode"
  },
  "geometry": {"coordinates":[-1.16965,51.895732],"type":"Point"}
}
