{
  "type": "Feature",
  "properties": {
    "date:inception_lower": "2005-06-01",
    "date:inception_upper": "2005-06-01",
    "iso:country": "GB",
    "wof:name": "ST8 6TN",
    "wof:placetype": "postalcode"
  },
  "geometry": {"coordinates":[-2.1669,53.11487],"type":"Point"}
}
