{
  "type": "Feature",
  "properties": {
    "iso:country": "GB",
    "wof:name": "ST8 6TN",
    "wof:placetype": "postalcode"
  },
  "geometry": {"coordinates":[-2.1669,53.11487],"type":"Point"}
}
