{
  "type": "Feature",
  "properties": {
    "iso:country": "GB",
    "wof:name": "LA4 5LU",
    "wof:placetype": "postalcode"
  },
  "geometry": {"coordinates":[-2.85992,54.072299],"type":"Point"}
}
