{
  "type": "Feature",
  "properties": {
    "iso:country":"GB",
    "wof:name":"NG4 1GL",
    "wof:placetype":"postalcode"
},
  "geometry": {"coordinates":[-1.10865516360608,52.96585368366605],"type":"Point"}
}