{
  "type": "Feature",
  "properties": {
    "iso:country": "GB",
    "wof:name": "NG4 1GL",
    "wof:placetype": "postalcode"
  },
  "geometry": {"coordinates":[-1.108655,52.965854],"type":"Point"}
}
