{
  "type": "Feature",
  "properties": {
    "date:inception_lower": "1980-01-01",
    "date:inception_upper": "1980-01-01",
    "iso:country": "GB",
    "wof:name": "NG4 1GL",
    "wof:placetype": "postalcode"
  },
  "geometry": {"coordinates":[-1.108655,52.965854],"type":"Point"}
}
