{
  "type": "Feature",
  "properties": {
    "date:inception_lower":"1985-10-01",
    "date:inception_upper":"1985-10-31",
    "iso:country":"GB",
    "wof:name":"HD6 2RL",
    "wof:placetype":"postalcode"
},
  "geometry": {"coordinates":[-1.790042,53.704084],"type":"Point"}
}