{
  "type": "Feature",
  "properties": {
    "iso:country":"GB",
    "wof:name":"HD6 2RL",
    "wof:placetype":"postalcode"
},
  "geometry": {"coordinates":[-1.79004199236895,53.70408397280703],"type":"Point"}
}