{
  "type": "Feature",
  "properties": {
    "date:inception_lower": "1980-01-01",
    "date:inception_upper": "1980-01-01",
    "iso:country": "GB",
    "wof:name": "SE5 8PF",
    "wof:placetype": "postalcode"
  },
  "geometry": {"coordinates":[-0.084326,51.471194],"type":"Point"}
}
