{
  "type": "Feature",
  "properties": {
    "iso:country":"GB",
    "wof:name":"SE5 8PF",
    "wof:placetype":"postalcode"
},
  "geometry": {"coordinates":[-0.0843258111055,51.47119429424283],"type":"Point"}
}