{
  "type": "Feature",
  "properties": {
    "iso:country":"GB",
    "wof:name":"KT18 7SS",
    "wof:placetype":"postalcode"
},
  "geometry": {"coordinates":[-0.28310464094785,51.33054625469288],"type":"Point"}
}