{
  "type": "Feature",
  "properties": {
    "iso:country":"GB",
    "wof:name":"S64 5SR",
    "wof:placetype":"postalcode"
},
  "geometry": {"coordinates":[-1.30377054706955,53.47341758703481],"type":"Point"}
}