{
  "type": "Feature",
  "properties": {
    "date:inception_lower": "1980-01-01",
    "date:inception_upper": "1980-01-01",
    "iso:country": "GB",
    "wof:name": "IP14 3AG",
    "wof:placetype": "postalcode"
  },
  "geometry": {"coordinates":[0.941386,52.179496],"type":"Point"}
}
