{
  "type": "Feature",
  "properties": {
    "iso:country":"GB",
    "wof:name":"DD8 3QJ",
    "wof:placetype":"postalcode"
},
  "geometry": {"coordinates":[-2.78926109364481,56.71413784868575],"type":"Point"}
}