{
  "type": "Feature",
  "properties": {
    "iso:country":"GB",
    "wof:name":"WS10 8XL",
    "wof:placetype":"postalcode"
},
  "geometry": {"coordinates":[-2.02511405909399,52.57250142923918],"type":"Point"}
}