{
  "type": "Feature",
  "properties": {
    "iso:country":"GB",
    "wof:name":"RM16 4SX",
    "wof:placetype":"postalcode"
},
  "geometry": {"coordinates":[0.36927429611907,51.48993784780092],"type":"Point"}
}