{
  "type": "Feature",
  "properties": {
    "date:inception_lower": "1980-01-01",
    "date:inception_upper": "1980-01-01",
    "iso:country": "GB",
    "wof:name": "SL6 3SX",
    "wof:placetype": "postalcode"
  },
  "geometry": {"coordinates":[-0.722485,51.472375],"type":"Point"}
}
