{
  "type": "Feature",
  "properties": {
    "iso:country":"GB",
    "wof:name":"WA3 1BG",
    "wof:placetype":"postalcode"
},
  "geometry": {"coordinates":[-2.55651193145498,53.48309975295147],"type":"Point"}
}