{
  "type": "Feature",
  "properties": {
    "iso:country":"GB",
    "wof:name":"DN2 5LB",
    "wof:placetype":"postalcode"
},
  "geometry": {"coordinates":[-1.1051352872697,53.53087290731452],"type":"Point"}
}