{
  "type": "Feature",
  "properties": {
    "iso:country":"GB",
    "wof:name":"SW1P 2AY",
    "wof:placetype":"postalcode"
},
  "geometry": {"coordinates":[-0.12993139859984,51.49467275056118],"type":"Point"}
}