{
  "type": "Feature",
  "properties": {
    "date:inception_lower":"2008-06-01",
    "date:inception_upper":"2008-06-30",
    "iso:country":"GB",
    "wof:name":"KA3 1PD",
    "wof:placetype":"postalcode"
},
  "geometry": {"coordinates":[-4.510889,55.621682],"type":"Point"}
}