{
  "type": "Feature",
  "properties": {
    "iso:country":"GB",
    "wof:name":"M29 8FQ",
    "wof:placetype":"postalcode"
},
  "geometry": {"coordinates":[-2.47314574866021,53.51668051607798],"type":"Point"}
}