{
  "type": "Feature",
  "properties": {
    "iso:country":"GB",
    "wof:name":"EN6 1HB",
    "wof:placetype":"postalcode"
},
  "geometry": {"coordinates":[-0.18575334939726,51.70304777545652],"type":"Point"}
}