{
  "type": "Feature",
  "properties": {
    "iso:country": "GB",
    "wof:name": "N21 3PT",
    "wof:placetype": "postalcode"
  },
  "geometry": {"coordinates":[-0.104682,51.631951],"type":"Point"}
}
