{
  "type": "Feature",
  "properties": {
    "iso:country":"GB",
    "wof:name":"N21 3PT",
    "wof:placetype":"postalcode"
},
  "geometry": {"coordinates":[-0.10468245279046,51.63195124530299],"type":"Point"}
}