{
  "type": "Feature",
  "properties": {
    "iso:country":"GB",
    "wof:name":"M33 4GT",
    "wof:placetype":"postalcode"
},
  "geometry": {"coordinates":[-2.35516375137349,53.41724513786311],"type":"Point"}
}