{
  "type": "Feature",
  "properties": {
    "iso:country": "GB",
    "wof:name": "CH5 1QF",
    "wof:placetype": "postalcode"
  },
  "geometry": {"coordinates":[-3.044644,53.204134],"type":"Point"}
}
