{
  "type": "Feature",
  "properties": {
    "iso:country":"GB",
    "wof:name":"CH5 1QF",
    "wof:placetype":"postalcode"
},
  "geometry": {"coordinates":[-3.0446440874016,53.20413390933992],"type":"Point"}
}