{
  "type": "Feature",
  "properties": {
    "date:inception_lower": "1980-01-01",
    "date:inception_upper": "1980-01-01",
    "iso:country": "GB",
    "wof:name": "KA4 8HX",
    "wof:placetype": "postalcode"
  },
  "geometry": {"coordinates":[-4.37938,55.597476],"type":"Point"}
}
