{
  "type": "Feature",
  "properties": {
    "iso:country":"GB",
    "wof:name":"KA4 8HX",
    "wof:placetype":"postalcode"
},
  "geometry": {"coordinates":[-4.37938040627166,55.59747556075556],"type":"Point"}
}