{
  "type": "Feature",
  "properties": {
    "iso:country":"GB",
    "wof:name":"DE55 5AF",
    "wof:placetype":"postalcode"
},
  "geometry": {"coordinates":[-1.37024357578024,53.12021811041044],"type":"Point"}
}