{
  "type": "Feature",
  "properties": {
    "iso:country": "GB",
    "wof:name": "NR9 5LN",
    "wof:placetype": "postalcode"
  },
  "geometry": {"coordinates":[1.086368,52.715032],"type":"Point"}
}
