{
  "type": "Feature",
  "properties": {
    "date:inception_lower": "1980-01-01",
    "date:inception_upper": "1980-01-01",
    "iso:country": "GB",
    "wof:name": "TA21 8PG",
    "wof:placetype": "postalcode"
  },
  "geometry": {"coordinates":[-3.222148,50.975243],"type":"Point"}
}
