{
  "type": "Feature",
  "properties": {
    "iso:country":"GB",
    "wof:name":"TA21 8PG",
    "wof:placetype":"postalcode"
},
  "geometry": {"coordinates":[-3.22214780022243,50.97524276847356],"type":"Point"}
}