{
  "type": "Feature",
  "properties": {
    "iso:country":"GB",
    "wof:name":"B13 9QR",
    "wof:placetype":"postalcode"
},
  "geometry": {"coordinates":[-1.86553257858917,52.43883781846974],"type":"Point"}
}