{
  "type": "Feature",
  "properties": {
    "date:inception_lower": "1980-01-01",
    "date:inception_upper": "1980-01-01",
    "iso:country": "GB",
    "wof:name": "DD11 1NN",
    "wof:placetype": "postalcode"
  },
  "geometry": {"coordinates":[-2.586421,56.558228],"type":"Point"}
}
