{
  "type": "Feature",
  "properties": {
    "iso:country": "GB",
    "wof:name": "SK12 1EG",
    "wof:placetype": "postalcode"
  },
  "geometry": {"coordinates":[-2.133733,53.359669],"type":"Point"}
}
