{
  "type": "Feature",
  "properties": {
    "iso:country":"GB",
    "wof:name":"CA2 6HB",
    "wof:placetype":"postalcode"
},
  "geometry": {"coordinates":[-2.95528046971699,54.88130312438967],"type":"Point"}
}