{
  "type": "Feature",
  "properties": {
    "iso:country":"GB",
    "wof:name":"BA6 8BE",
    "wof:placetype":"postalcode"
},
  "geometry": {"coordinates":[-2.71229449650068,51.14423136805951],"type":"Point"}
}