{
  "type": "Feature",
  "properties": {
    "iso:country": "GB",
    "wof:name": "LE7 3DS",
    "wof:placetype": "postalcode"
  },
  "geometry": {"coordinates":[-1.054546,52.706091],"type":"Point"}
}
