{
  "type": "Feature",
  "properties": {
    "iso:country":"GB",
    "wof:name":"LE7 3DS",
    "wof:placetype":"postalcode"
},
  "geometry": {"coordinates":[-1.05454648610322,52.70609063019187],"type":"Point"}
}