{
  "type": "Feature",
  "properties": {
    "iso:country":"GB",
    "wof:name":"N1 0PJ",
    "wof:placetype":"postalcode"
},
  "geometry": {"coordinates":[-0.10573243262932,51.53419327442943],"type":"Point"}
}