{
  "type": "Feature",
  "properties": {
    "iso:country":"GB",
    "wof:name":"S72 7NX",
    "wof:placetype":"postalcode"
},
  "geometry": {"coordinates":[-1.37609361063664,53.572600797083],"type":"Point"}
}