{
  "type": "Feature",
  "properties": {
    "iso:country":"GB",
    "wof:name":"BD12 0PY",
    "wof:placetype":"postalcode"
},
  "geometry": {"coordinates":[-1.75587768017117,53.75743547042075],"type":"Point"}
}