{
  "type": "Feature",
  "properties": {
    "date:inception_lower": "2007-03-01",
    "date:inception_upper": "2007-03-01",
    "iso:country": "GB",
    "wof:name": "GU12 4JY",
    "wof:placetype": "postalcode"
  },
  "geometry": {"coordinates":[-0.750172,51.238589],"type":"Point"}
}
