{
  "type": "Feature",
  "properties": {
    "iso:country": "GB",
    "wof:name": "SP3 5HP",
    "wof:placetype": "postalcode"
  },
  "geometry": {"coordinates":[-1.986031,51.081218],"type":"Point"}
}
