{
  "type": "Feature",
  "properties": {
    "date:inception_lower": "1980-01-01",
    "date:inception_upper": "1980-01-01",
    "iso:country": "GB",
    "wof:name": "SE8 5SW",
    "wof:placetype": "postalcode"
  },
  "geometry": {"coordinates":[-0.031659,51.482462],"type":"Point"}
}
