{
  "type": "Feature",
  "properties": {
    "iso:country":"GB",
    "wof:name":"SE8 5SW",
    "wof:placetype":"postalcode"
},
  "geometry": {"coordinates":[-0.03165907271541,51.48246205232471],"type":"Point"}
}