{
  "type": "Feature",
  "properties": {
    "iso:country": "GB",
    "wof:name": "KT11 2ET",
    "wof:placetype": "postalcode"
  },
  "geometry": {"coordinates":[-0.373538,51.341459],"type":"Point"}
}
