{
  "type": "Feature",
  "properties": {
    "iso:country": "GB",
    "wof:name": "BL9 6TH",
    "wof:placetype": "postalcode"
  },
  "geometry": {"coordinates":[-2.282044,53.62643],"type":"Point"}
}
