{
  "type": "Feature",
  "properties": {
    "date:inception_lower": "2007-07-01",
    "date:inception_upper": "2007-07-01",
    "iso:country": "GB",
    "wof:name": "EH12 8AS",
    "wof:placetype": "postalcode"
  },
  "geometry": {"coordinates":[-3.310667,55.948706],"type":"Point"}
}
