{
  "type": "Feature",
  "properties": {
    "iso:country":"GB",
    "wof:name":"EH12 8AS",
    "wof:placetype":"postalcode"
},
  "geometry": {"coordinates":[-3.31066722136554,55.94870554639751],"type":"Point"}
}