{
  "type": "Feature",
  "properties": {
    "iso:country": "GB",
    "wof:name": "G34 9QP",
    "wof:placetype": "postalcode"
  },
  "geometry": {"coordinates":[-4.123414,55.871509],"type":"Point"}
}
