{
  "type": "Feature",
  "properties": {
    "date:inception_lower": "2013-05-01",
    "date:inception_upper": "2013-05-01",
    "iso:country": "GB",
    "wof:name": "G34 9QP",
    "wof:placetype": "postalcode"
  },
  "geometry": {"coordinates":[-4.123414,55.871509],"type":"Point"}
}
