{
  "type": "Feature",
  "properties": {
    "iso:country":"GB",
    "wof:name":"CT20 2AJ",
    "wof:placetype":"postalcode"
},
  "geometry": {"coordinates":[1.17791984623937,51.07806011127616],"type":"Point"}
}