{
  "type": "Feature",
  "properties": {
    "iso:country":"GB",
    "wof:name":"SK3 9QE",
    "wof:placetype":"postalcode"
},
  "geometry": {"coordinates":[-2.17092061893699,53.39694167848676],"type":"Point"}
}