{
  "type": "Feature",
  "properties": {
    "iso:country": "GB",
    "wof:name": "YO11 3UF",
    "wof:placetype": "postalcode"
  },
  "geometry": {"coordinates":[-0.399632,54.200972],"type":"Point"}
}
