{
  "type": "Feature",
  "properties": {
    "iso:country": "GB",
    "wof:name": "SL5 8EE",
    "wof:placetype": "postalcode"
  },
  "geometry": {"coordinates":[-0.69799,51.412686],"type":"Point"}
}
