{
  "type": "Feature",
  "properties": {
    "iso:country":"GB",
    "wof:name":"SL5 8EE",
    "wof:placetype":"postalcode"
},
  "geometry": {"coordinates":[-0.6980080235074,51.41265895804543],"type":"Point"}
}