{
  "type": "Feature",
  "properties": {
    "date:inception_lower": "1980-01-01",
    "date:inception_upper": "1980-01-01",
    "iso:country": "GB",
    "wof:name": "LN7 6TA",
    "wof:placetype": "postalcode"
  },
  "geometry": {"coordinates":[-0.324293,53.481641],"type":"Point"}
}
