{
  "type": "Feature",
  "properties": {
    "iso:country":"GB",
    "wof:name":"LN7 6TA",
    "wof:placetype":"postalcode"
},
  "geometry": {"coordinates":[-0.32429274297797,53.48164073333282],"type":"Point"}
}