{
  "type": "Feature",
  "properties": {
    "iso:country":"GB",
    "wof:name":"SS0 0BP",
    "wof:placetype":"postalcode"
},
  "geometry": {"coordinates":[0.66940697874661,51.55295429808707],"type":"Point"}
}