{
  "type": "Feature",
  "properties": {
    "iso:country":"GB",
    "wof:name":"BD24 9HH",
    "wof:placetype":"postalcode"
},
  "geometry": {"coordinates":[-2.27327977954125,54.06565347556997],"type":"Point"}
}