{
  "type": "Feature",
  "properties": {
    "date:inception_lower": "1986-09-01",
    "date:inception_upper": "1986-09-01",
    "iso:country": "GB",
    "wof:name": "EH15 3SB",
    "wof:placetype": "postalcode"
  },
  "geometry": {"coordinates":[-3.112474,55.938318],"type":"Point"}
}
