{
  "type": "Feature",
  "properties": {
    "iso:country":"GB",
    "wof:name":"CM77 8EP",
    "wof:placetype":"postalcode"
},
  "geometry": {"coordinates":[0.62561777173834,51.87171287806827],"type":"Point"}
}