{
  "type": "Feature",
  "properties": {
    "iso:country": "GB",
    "wof:name": "PO22 0FG",
    "wof:placetype": "postalcode"
  },
  "geometry": {"coordinates":[-0.633294,50.830515],"type":"Point"}
}
