{
  "type": "Feature",
  "properties": {
    "date:inception_lower": "1980-01-01",
    "date:inception_upper": "1980-01-01",
    "iso:country": "GB",
    "wof:name": "ST6 1HA",
    "wof:placetype": "postalcode"
  },
  "geometry": {"coordinates":[-2.186277,53.049123],"type":"Point"}
}
