{
  "type": "Feature",
  "properties": {
    "iso:country": "GB",
    "wof:name": "NG18 5LP",
    "wof:placetype": "postalcode"
  },
  "geometry": {"coordinates":[-1.210489,53.14414],"type":"Point"}
}
