{
  "type": "Feature",
  "properties": {
    "iso:country":"GB",
    "wof:name":"NG5 9BS",
    "wof:placetype":"postalcode"
},
  "geometry": {"coordinates":[-1.17261773865038,53.00723589178855],"type":"Point"}
}