{
  "type": "Feature",
  "properties": {
    "iso:country": "GB",
    "wof:name": "CW5 5SL",
    "wof:placetype": "postalcode"
  },
  "geometry": {"coordinates":[-2.523562,53.066624],"type":"Point"}
}
