{
  "type": "Feature",
  "properties": {
    "iso:country":"GB",
    "wof:name":"CW5 5SL",
    "wof:placetype":"postalcode"
},
  "geometry": {"coordinates":[-2.5235625141996,53.06662434237209],"type":"Point"}
}