{
  "type": "Feature",
  "properties": {
    "iso:country":"GB",
    "wof:name":"GU1 4BP",
    "wof:placetype":"postalcode"
},
  "geometry": {"coordinates":[-0.56905909530437,51.24225255026021],"type":"Point"}
}