{
  "type": "Feature",
  "properties": {
    "iso:country": "GB",
    "wof:name": "GL1 5ES",
    "wof:placetype": "postalcode"
  },
  "geometry": {"coordinates":[-2.246319,51.84505],"type":"Point"}
}
