{
  "type": "Feature",
  "properties": {
    "iso:country":"GB",
    "wof:name":"GL1 5ES",
    "wof:placetype":"postalcode"
},
  "geometry": {"coordinates":[-2.24631939823207,51.8450503769735],"type":"Point"}
}