{
  "type": "Feature",
  "properties": {
    "iso:country":"GB",
    "wof:name":"BD2 1EZ",
    "wof:placetype":"postalcode"
},
  "geometry": {"coordinates":[-1.74633078548589,53.81648479364308],"type":"Point"}
}