{
  "type": "Feature",
  "properties": {
    "iso:country":"GB",
    "wof:name":"NE32 3RZ",
    "wof:placetype":"postalcode"
},
  "geometry": {"coordinates":[-1.46808835046568,54.97104771635524],"type":"Point"}
}