{
  "type": "Feature",
  "properties": {
    "date:inception_lower": "1980-01-01",
    "date:inception_upper": "1980-01-01",
    "iso:country": "GB",
    "wof:name": "NR33 8AQ",
    "wof:placetype": "postalcode"
  },
  "geometry": {"coordinates":[1.694546,52.452508],"type":"Point"}
}
