{
  "type": "Feature",
  "properties": {
    "iso:country": "GB",
    "wof:name": "ST10 3HG",
    "wof:placetype": "postalcode"
  },
  "geometry": {"coordinates":[-1.884801,53.053528],"type":"Point"}
}
