{
  "type": "Feature",
  "properties": {
    "date:inception_lower":"2004-02-01",
    "date:inception_upper":"2004-02-29",
    "iso:country":"GB",
    "wof:name":"ST10 3HG",
    "wof:placetype":"postalcode"
},
  "geometry": {"coordinates":[-1.884801,53.053528],"type":"Point"}
}