{
  "type": "Feature",
  "properties": {
    "iso:country": "GB",
    "wof:name": "HP10 9PP",
    "wof:placetype": "postalcode"
  },
  "geometry": {"coordinates":[-0.704244,51.596218],"type":"Point"}
}
