{
  "type": "Feature",
  "properties": {
    "iso:country":"GB",
    "wof:name":"HP10 9PP",
    "wof:placetype":"postalcode"
},
  "geometry": {"coordinates":[-0.70424433170033,51.59621824089904],"type":"Point"}
}