{
  "type": "Feature",
  "properties": {
    "iso:country":"GB",
    "wof:name":"WF5 8AU",
    "wof:placetype":"postalcode"
},
  "geometry": {"coordinates":[-1.57896641486123,53.67704040497692],"type":"Point"}
}