{
  "type": "Feature",
  "properties": {
    "date:inception_lower":"2001-12-01",
    "date:inception_upper":"2001-12-31",
    "iso:country":"GB",
    "wof:name":"NR10 3SZ",
    "wof:placetype":"postalcode"
},
  "geometry": {"coordinates":[1.239705,52.695424],"type":"Point"}
}