{
  "type": "Feature",
  "properties": {
    "iso:country": "GB",
    "wof:name": "NR10 3SZ",
    "wof:placetype": "postalcode"
  },
  "geometry": {"coordinates":[1.239705,52.695424],"type":"Point"}
}
