{
  "type": "Feature",
  "properties": {
    "iso:country":"GB",
    "wof:name":"PR7 7GT",
    "wof:placetype":"postalcode"
},
  "geometry": {"coordinates":[-2.65983209757199,53.67923225395106],"type":"Point"}
}