{
  "type": "Feature",
  "properties": {
    "iso:country": "GB",
    "wof:name": "PR7 7GT",
    "wof:placetype": "postalcode"
  },
  "geometry": {"coordinates":[-2.659825,53.679006],"type":"Point"}
}
