{
  "type": "Feature",
  "properties": {
    "iso:country": "GB",
    "wof:name": "SL6 0DU",
    "wof:placetype": "postalcode"
  },
  "geometry": {"coordinates":[-0.679667,51.506196],"type":"Point"}
}
