{
  "type": "Feature",
  "properties": {
    "date:inception_lower": "1980-01-01",
    "date:inception_upper": "1980-01-01",
    "iso:country": "GB",
    "wof:name": "SL6 0DU",
    "wof:placetype": "postalcode"
  },
  "geometry": {"coordinates":[-0.679667,51.506196],"type":"Point"}
}
