{
  "type": "Feature",
  "properties": {
    "iso:country":"GB",
    "wof:name":"SL6 0DU",
    "wof:placetype":"postalcode"
},
  "geometry": {"coordinates":[-0.67966713206202,51.50619600916288],"type":"Point"}
}