{
  "type": "Feature",
  "properties": {
    "iso:country":"GB",
    "wof:name":"NR5 8XR",
    "wof:placetype":"postalcode"
},
  "geometry": {"coordinates":[1.24209562563095,52.64088578678619],"type":"Point"}
}