{
  "type": "Feature",
  "properties": {
    "iso:country":"GB",
    "wof:name":"SO32 2DS",
    "wof:placetype":"postalcode"
},
  "geometry": {"coordinates":[-1.24343827193344,50.92571250664734],"type":"Point"}
}