{
  "type": "Feature",
  "properties": {
    "iso:country": "GB",
    "wof:name": "G12 0TD",
    "wof:placetype": "postalcode"
  },
  "geometry": {"coordinates":[-4.293437,55.878703],"type":"Point"}
}
