{
  "type": "Feature",
  "properties": {
    "date:inception_lower": "1980-01-01",
    "date:inception_upper": "1980-01-01",
    "iso:country": "GB",
    "wof:name": "G12 0TD",
    "wof:placetype": "postalcode"
  },
  "geometry": {"coordinates":[-4.293437,55.878703],"type":"Point"}
}
