{
  "type": "Feature",
  "properties": {
    "date:inception_lower": "2002-06-01",
    "date:inception_upper": "2002-06-01",
    "iso:country": "GB",
    "wof:name": "EH51 9QZ",
    "wof:placetype": "postalcode"
  },
  "geometry": {"coordinates":[-3.59715,56.011426],"type":"Point"}
}
