{
  "type": "Feature",
  "properties": {
    "iso:country":"GB",
    "wof:name":"EH51 9QZ",
    "wof:placetype":"postalcode"
},
  "geometry": {"coordinates":[-3.59714983198534,56.01142553543667],"type":"Point"}
}