{
  "type": "Feature",
  "properties": {
    "iso:country":"GB",
    "wof:name":"CV21 4LG",
    "wof:placetype":"postalcode"
},
  "geometry": {"coordinates":[-1.22331445617511,52.36355297569214],"type":"Point"}
}