{
  "type": "Feature",
  "properties": {
    "iso:country": "GB",
    "wof:name": "NP4 9LH",
    "wof:placetype": "postalcode"
  },
  "geometry": {"coordinates":[-3.078937,51.770612],"type":"Point"}
}
