{
  "type": "Feature",
  "properties": {
    "iso:country":"GB",
    "wof:name":"NP4 9LH",
    "wof:placetype":"postalcode"
},
  "geometry": {"coordinates":[-3.07893663014999,51.77061224043257],"type":"Point"}
}