{
  "type": "Feature",
  "properties": {
    "iso:country":"GB",
    "wof:name":"SY9 5AG",
    "wof:placetype":"postalcode"
},
  "geometry": {"coordinates":[-3.00171010688911,52.48654363104678],"type":"Point"}
}