{
  "type": "Feature",
  "properties": {
    "date:inception_lower": "2018-02-01",
    "date:inception_upper": "2018-02-01",
    "iso:country": "GB",
    "wof:name": "OL1 2AD",
    "wof:placetype": "postalcode"
  },
  "geometry": {"coordinates":[-2.115223,53.544274],"type":"Point"}
}
