{
  "type": "Feature",
  "properties": {
    "iso:country":"GB",
    "wof:name":"MK41 7JY",
    "wof:placetype":"postalcode"
},
  "geometry": {"coordinates":[-0.45846021627135,52.15268202369954],"type":"Point"}
}