{
  "type": "Feature",
  "properties": {
    "date:inception_lower": "1980-01-01",
    "date:inception_upper": "1980-01-01",
    "iso:country": "GB",
    "wof:name": "MK41 7JY",
    "wof:placetype": "postalcode"
  },
  "geometry": {"coordinates":[-0.45846,52.152682],"type":"Point"}
}
