{
  "type": "Feature",
  "properties": {
    "iso:country":"GB",
    "wof:name":"BD8 8BW",
    "wof:placetype":"postalcode"
},
  "geometry": {"coordinates":[-1.77060247188158,53.80247644238944],"type":"Point"}
}