{
  "type": "Feature",
  "properties": {
    "iso:country": "GB",
    "wof:name": "BD8 8BW",
    "wof:placetype": "postalcode"
  },
  "geometry": {"coordinates":[-1.770602,53.802476],"type":"Point"}
}
