{
  "type": "Feature",
  "properties": {
    "iso:country":"GB",
    "wof:name":"BR4 0SQ",
    "wof:placetype":"postalcode"
},
  "geometry": {"coordinates":[-0.00769968100596,51.37483648410434],"type":"Point"}
}