{
  "type": "Feature",
  "properties": {
    "iso:country":"GB",
    "wof:name":"SO53 2GG",
    "wof:placetype":"postalcode"
},
  "geometry": {"coordinates":[-1.37690234168593,50.98727137725074],"type":"Point"}
}