{
  "type": "Feature",
  "properties": {
    "date:inception_lower": "1994-12-01",
    "date:inception_upper": "1994-12-01",
    "iso:country": "GB",
    "wof:name": "SO53 2GG",
    "wof:placetype": "postalcode"
  },
  "geometry": {"coordinates":[-1.376906,50.987264],"type":"Point"}
}
