{
  "type": "Feature",
  "properties": {
    "iso:country":"GB",
    "wof:name":"TD1 3PP",
    "wof:placetype":"postalcode"
},
  "geometry": {"coordinates":[-2.8638359421001,55.58573043639912],"type":"Point"}
}