{
  "type": "Feature",
  "properties": {
    "iso:country":"GB",
    "wof:name":"NP23 5JL",
    "wof:placetype":"postalcode"
},
  "geometry": {"coordinates":[-3.20943651111846,51.79741314997183],"type":"Point"}
}