{
  "type": "Feature",
  "properties": {
    "iso:country":"GB",
    "wof:name":"SR3 2NX",
    "wof:placetype":"postalcode"
},
  "geometry": {"coordinates":[-1.41915571224094,54.86099176675091],"type":"Point"}
}