{
  "type": "Feature",
  "properties": {
    "iso:country":"GB",
    "wof:name":"CT2 7EH",
    "wof:placetype":"postalcode"
},
  "geometry": {"coordinates":[1.07328048661316,51.28361916401608],"type":"Point"}
}