{
  "type": "Feature",
  "properties": {
    "iso:country": "GB",
    "wof:name": "CT2 7EH",
    "wof:placetype": "postalcode"
  },
  "geometry": {"coordinates":[1.073281,51.283619],"type":"Point"}
}
