{
  "type": "Feature",
  "properties": {
    "iso:country":"GB",
    "wof:name":"G15 6QY",
    "wof:placetype":"postalcode"
},
  "geometry": {"coordinates":[-4.36360006574405,55.90378108226292],"type":"Point"}
}