{
  "type": "Feature",
  "properties": {
    "iso:country": "GB",
    "wof:name": "FK8 2PD",
    "wof:placetype": "postalcode"
  },
  "geometry": {"coordinates":[-3.950175,56.108632],"type":"Point"}
}
