{
  "type": "Feature",
  "properties": {
    "iso:country": "GB",
    "wof:name": "LL48 6ER",
    "wof:placetype": "postalcode"
  },
  "geometry": {"coordinates":[-4.099341,52.912067],"type":"Point"}
}
