{
  "type": "Feature",
  "properties": {
    "date:inception_lower": "1980-01-01",
    "date:inception_upper": "1980-01-01",
    "iso:country": "GB",
    "wof:name": "LL48 6ER",
    "wof:placetype": "postalcode"
  },
  "geometry": {"coordinates":[-4.099341,52.912067],"type":"Point"}
}
