{
  "type": "Feature",
  "properties": {
    "iso:country":"GB",
    "wof:name":"PO30 1NT",
    "wof:placetype":"postalcode"
},
  "geometry": {"coordinates":[-1.31452781756455,50.69155972407128],"type":"Point"}
}