{
  "type": "Feature",
  "properties": {
    "date:inception_lower":"1980-01-01",
    "date:inception_upper":"1980-01-31",
    "iso:country":"GB",
    "wof:name":"PO30 1NT",
    "wof:placetype":"postalcode"
},
  "geometry": {"coordinates":[-1.314528,50.69156],"type":"Point"}
}