{
  "type": "Feature",
  "properties": {
    "iso:country":"GB",
    "wof:name":"IP13 0EQ",
    "wof:placetype":"postalcode"
},
  "geometry": {"coordinates":[1.32912344540733,52.17691883665905],"type":"Point"}
}