{
  "type": "Feature",
  "properties": {
    "iso:country":"GB",
    "wof:name":"M21 9ES",
    "wof:placetype":"postalcode"
},
  "geometry": {"coordinates":[-2.2834367061028,53.43710399321618],"type":"Point"}
}