{
  "type": "Feature",
  "properties": {
    "iso:country":"GB",
    "wof:name":"BN18 9SU",
    "wof:placetype":"postalcode"
},
  "geometry": {"coordinates":[-0.55530471426486,50.85338957756968],"type":"Point"}
}