{
  "type": "Feature",
  "properties": {
    "iso:country": "GB",
    "wof:name": "TQ7 2DQ",
    "wof:placetype": "postalcode"
  },
  "geometry": {"coordinates":[-3.721318,50.27102],"type":"Point"}
}
