{
  "type": "Feature",
  "properties": {
    "iso:country":"GB",
    "wof:name":"TQ7 2DQ",
    "wof:placetype":"postalcode"
},
  "geometry": {"coordinates":[-3.72131765128765,50.27101983974106],"type":"Point"}
}