{
  "type": "Feature",
  "properties": {
    "date:inception_lower": "2007-11-01",
    "date:inception_upper": "2007-11-01",
    "iso:country": "GB",
    "wof:name": "TQ7 2DQ",
    "wof:placetype": "postalcode"
  },
  "geometry": {"coordinates":[-3.721318,50.27102],"type":"Point"}
}
