{
  "type": "Feature",
  "properties": {
    "iso:country":"GB",
    "wof:name":"DY5 2LA",
    "wof:placetype":"postalcode"
},
  "geometry": {"coordinates":[-2.11470745473662,52.46547748225269],"type":"Point"}
}