{
  "type": "Feature",
  "properties": {
    "date:inception_lower": "2017-11-01",
    "date:inception_upper": "2017-11-01",
    "iso:country": "GB",
    "wof:name": "LA2 8RP",
    "wof:placetype": "postalcode"
  },
  "geometry": {"coordinates":[-2.390904,54.116102],"type":"Point"}
}
