{
  "type": "Feature",
  "properties": {
    "iso:country": "GB",
    "wof:name": "LA2 8RP",
    "wof:placetype": "postalcode"
  },
  "geometry": {"coordinates":[-2.391258,54.116326],"type":"Point"}
}
