{
  "type": "Feature",
  "properties": {
    "iso:country":"GB",
    "wof:name":"BL1 7NA",
    "wof:placetype":"postalcode"
},
  "geometry": {"coordinates":[-2.4705707439332,53.59996826778357],"type":"Point"}
}