{
  "type": "Feature",
  "properties": {
    "iso:country": "GB",
    "wof:name": "M27 8HF",
    "wof:placetype": "postalcode"
  },
  "geometry": {"coordinates":[-2.330156,53.523705],"type":"Point"}
}
