{
  "type": "Feature",
  "properties": {
    "iso:country":"GB",
    "wof:name":"LU2 0EY",
    "wof:placetype":"postalcode"
},
  "geometry": {"coordinates":[-0.40956809361385,51.8851021711578],"type":"Point"}
}