{
  "type": "Feature",
  "properties": {
    "date:inception_lower":"1980-01-01",
    "date:inception_upper":"1980-01-31",
    "iso:country":"GB",
    "wof:name":"RG8 9QZ",
    "wof:placetype":"postalcode"
},
  "geometry": {"coordinates":[-1.156151,51.520841],"type":"Point"}
}