{
  "type": "Feature",
  "properties": {
    "date:inception_lower": "1986-07-01",
    "date:inception_upper": "1986-07-01",
    "iso:country": "GB",
    "wof:name": "RG5 4UE",
    "wof:placetype": "postalcode"
  },
  "geometry": {"coordinates":[-0.881919,51.452207],"type":"Point"}
}
