{
  "type": "Feature",
  "properties": {
    "iso:country":"GB",
    "wof:name":"RG5 4UE",
    "wof:placetype":"postalcode"
},
  "geometry": {"coordinates":[-0.88191911996825,51.45220660845725],"type":"Point"}
}