{
  "type": "Feature",
  "properties": {
    "iso:country": "GB",
    "wof:name": "CO4 5LN",
    "wof:placetype": "postalcode"
  },
  "geometry": {"coordinates":[0.90265,51.917031],"type":"Point"}
}
