{
  "type": "Feature",
  "properties": {
    "iso:country": "GB",
    "wof:name": "S32 1BT",
    "wof:placetype": "postalcode"
  },
  "geometry": {"coordinates":[-1.648931,53.332478],"type":"Point"}
}
