{
  "type": "Feature",
  "properties": {
    "iso:country":"GB",
    "wof:name":"S32 1BT",
    "wof:placetype":"postalcode"
},
  "geometry": {"coordinates":[-1.64893112144361,53.332477916307],"type":"Point"}
}