{
  "type": "Feature",
  "properties": {
    "iso:country":"GB",
    "wof:name":"NG19 7DB",
    "wof:placetype":"postalcode"
},
  "geometry": {"coordinates":[-1.19683353900822,53.15336989317763],"type":"Point"}
}