{
  "type": "Feature",
  "properties": {
    "date:inception_lower": "1980-01-01",
    "date:inception_upper": "1980-01-01",
    "iso:country": "GB",
    "wof:name": "NG19 7DB",
    "wof:placetype": "postalcode"
  },
  "geometry": {"coordinates":[-1.196833,53.15337],"type":"Point"}
}
