{
  "type": "Feature",
  "properties": {
    "date:inception_lower": "1991-09-01",
    "date:inception_upper": "1991-09-01",
    "iso:country": "GB",
    "wof:name": "B8 3TF",
    "wof:placetype": "postalcode"
  },
  "geometry": {"coordinates":[-1.852731,52.484042],"type":"Point"}
}
