{
  "type": "Feature",
  "properties": {
    "iso:country":"GB",
    "wof:name":"SL6 9NE",
    "wof:placetype":"postalcode"
},
  "geometry": {"coordinates":[-0.72821193670748,51.5527259886911],"type":"Point"}
}