{
  "type": "Feature",
  "properties": {
    "date:inception_lower": "1994-05-01",
    "date:inception_upper": "1994-05-01",
    "iso:country": "GB",
    "wof:name": "HR1 1JZ",
    "wof:placetype": "postalcode"
  },
  "geometry": {"coordinates":[-2.71503,52.075388],"type":"Point"}
}
