{
  "type": "Feature",
  "properties": {
    "iso:country": "GB",
    "wof:name": "HR1 1JZ",
    "wof:placetype": "postalcode"
  },
  "geometry": {"coordinates":[-2.71503,52.075388],"type":"Point"}
}
