{
  "type": "Feature",
  "properties": {
    "iso:country":"GB",
    "wof:name":"B63 4DT",
    "wof:placetype":"postalcode"
},
  "geometry": {"coordinates":[-2.07247021774144,52.45188216263448],"type":"Point"}
}