{
  "type": "Feature",
  "properties": {
    "iso:country": "GB",
    "wof:name": "B63 4DT",
    "wof:placetype": "postalcode"
  },
  "geometry": {"coordinates":[-2.07247,52.451882],"type":"Point"}
}
