{
  "type": "Feature",
  "properties": {
    "date:inception_lower": "1980-01-01",
    "date:inception_upper": "1980-01-01",
    "iso:country": "GB",
    "wof:name": "B63 4DT",
    "wof:placetype": "postalcode"
  },
  "geometry": {"coordinates":[-2.07247,52.451882],"type":"Point"}
}
