{
  "type": "Feature",
  "properties": {
    "date:inception_lower": "1993-08-01",
    "date:inception_upper": "1993-08-01",
    "iso:country": "GB",
    "wof:name": "BB7 2NF",
    "wof:placetype": "postalcode"
  },
  "geometry": {"coordinates":[-2.396029,53.878717],"type":"Point"}
}
