{
  "type": "Feature",
  "properties": {
    "iso:country":"GB",
    "wof:name":"M24 6AF",
    "wof:placetype":"postalcode"
},
  "geometry": {"coordinates":[-2.19507190588183,53.55095783073135],"type":"Point"}
}