{
  "type": "Feature",
  "properties": {
    "date:inception_lower": "1994-12-01",
    "date:inception_upper": "1994-12-01",
    "iso:country": "GB",
    "wof:name": "TF7 5TX",
    "wof:placetype": "postalcode"
  },
  "geometry": {"coordinates":[-2.464848,52.642395],"type":"Point"}
}
