{
  "type": "Feature",
  "properties": {
    "iso:country":"GB",
    "wof:name":"TF7 5TX",
    "wof:placetype":"postalcode"
},
  "geometry": {"coordinates":[-2.46484788702597,52.6423947312549],"type":"Point"}
}