{
  "type": "Feature",
  "properties": {
    "iso:country":"GB",
    "wof:name":"AL5 1DY",
    "wof:placetype":"postalcode"
},
  "geometry": {"coordinates":[-0.32567444861219,51.80633878010553],"type":"Point"}
}