{
  "type": "Feature",
  "properties": {
    "iso:country": "GB",
    "wof:name": "AL5 1DY",
    "wof:placetype": "postalcode"
  },
  "geometry": {"coordinates":[-0.325674,51.806339],"type":"Point"}
}
