{
  "type": "Feature",
  "properties": {
    "iso:country":"GB",
    "wof:name":"LL13 9JD",
    "wof:placetype":"postalcode"
},
  "geometry": {"coordinates":[-2.88200888697108,53.07949176766334],"type":"Point"}
}