{
  "type": "Feature",
  "properties": {
    "iso:country": "GB",
    "wof:name": "PO36 9QG",
    "wof:placetype": "postalcode"
  },
  "geometry": {"coordinates":[-1.177039,50.644408],"type":"Point"}
}
