{
  "type": "Feature",
  "properties": {
    "iso:country":"GB",
    "wof:name":"PO36 9QG",
    "wof:placetype":"postalcode"
},
  "geometry": {"coordinates":[-1.17706316317755,50.64441098988007],"type":"Point"}
}