{
  "type": "Feature",
  "properties": {
    "iso:country":"GB",
    "wof:name":"KT14 6HB",
    "wof:placetype":"postalcode"
},
  "geometry": {"coordinates":[-0.49149715965363,51.33980010805166],"type":"Point"}
}