{
  "type": "Feature",
  "properties": {
    "date:inception_lower": "2007-07-01",
    "date:inception_upper": "2007-07-01",
    "iso:country": "GB",
    "wof:name": "KT14 6HB",
    "wof:placetype": "postalcode"
  },
  "geometry": {"coordinates":[-0.491497,51.3398],"type":"Point"}
}
