{
  "type": "Feature",
  "properties": {
    "iso:country":"GB",
    "wof:name":"G41 3BT",
    "wof:placetype":"postalcode"
},
  "geometry": {"coordinates":[-4.27842929366568,55.82965847912573],"type":"Point"}
}