{
  "type": "Feature",
  "properties": {
    "iso:country": "GB",
    "wof:name": "G41 3BT",
    "wof:placetype": "postalcode"
  },
  "geometry": {"coordinates":[-4.278429,55.829658],"type":"Point"}
}
