{
  "type": "Feature",
  "properties": {
    "iso:country":"GB",
    "wof:name":"RG22 5AS",
    "wof:placetype":"postalcode"
},
  "geometry": {"coordinates":[-1.1305727076974,51.25588006641733],"type":"Point"}
}