{
  "type": "Feature",
  "properties": {
    "date:inception_lower": "1980-01-01",
    "date:inception_upper": "1980-01-01",
    "iso:country": "GB",
    "wof:name": "CO11 2QB",
    "wof:placetype": "postalcode"
  },
  "geometry": {"coordinates":[1.034066,51.916556],"type":"Point"}
}
