{
  "type": "Feature",
  "properties": {
    "iso:country": "GB",
    "wof:name": "CO11 2QB",
    "wof:placetype": "postalcode"
  },
  "geometry": {"coordinates":[1.034066,51.916556],"type":"Point"}
}
