{
  "type": "Feature",
  "properties": {
    "iso:country":"GB",
    "wof:name":"CO11 2QB",
    "wof:placetype":"postalcode"
},
  "geometry": {"coordinates":[1.03406566496127,51.91655606461527],"type":"Point"}
}