{
  "type": "Feature",
  "properties": {
    "iso:country":"GB",
    "wof:name":"RH6 9RU",
    "wof:placetype":"postalcode"
},
  "geometry": {"coordinates":[-0.11571686929662,51.16331272356632],"type":"Point"}
}