{
  "type": "Feature",
  "properties": {
    "iso:country":"GB",
    "wof:name":"BD2 4PN",
    "wof:placetype":"postalcode"
},
  "geometry": {"coordinates":[-1.73380659136558,53.80828762520581],"type":"Point"}
}