{
  "type": "Feature",
  "properties": {
    "iso:country":"GB",
    "wof:name":"DN21 1WE",
    "wof:placetype":"postalcode"
},
  "geometry": {"coordinates":[-0.75786806515128,53.40282225153859],"type":"Point"}
}