{
  "type": "Feature",
  "properties": {
    "iso:country": "GB",
    "wof:name": "GU14 7QD",
    "wof:placetype": "postalcode"
  },
  "geometry": {"coordinates":[-0.762531,51.294203],"type":"Point"}
}
