{
  "type": "Feature",
  "properties": {
    "iso:country":"GB",
    "wof:name":"EH39 4LY",
    "wof:placetype":"postalcode"
},
  "geometry": {"coordinates":[-2.73446670592713,56.05955530502484],"type":"Point"}
}