{
  "type": "Feature",
  "properties": {
    "iso:country": "GB",
    "wof:name": "GU24 9AZ",
    "wof:placetype": "postalcode"
  },
  "geometry": {"coordinates":[-0.635276,51.317725],"type":"Point"}
}
