{
  "type": "Feature",
  "properties": {
    "iso:country": "GB",
    "wof:name": "GL2 9HZ",
    "wof:placetype": "postalcode"
  },
  "geometry": {"coordinates":[-2.22183,51.874338],"type":"Point"}
}
