{
  "type": "Feature",
  "properties": {
    "iso:country":"GB",
    "wof:name":"TW1 1BN",
    "wof:placetype":"postalcode"
},
  "geometry": {"coordinates":[-0.33215020979998,51.45198783788558],"type":"Point"}
}