{
  "type": "Feature",
  "properties": {
    "date:inception_lower": "1980-01-01",
    "date:inception_upper": "1980-01-01",
    "iso:country": "GB",
    "wof:name": "TW1 1BN",
    "wof:placetype": "postalcode"
  },
  "geometry": {"coordinates":[-0.33215,51.451988],"type":"Point"}
}
