{
  "type": "Feature",
  "properties": {
    "date:inception_lower":"1990-07-01",
    "date:inception_upper":"1990-07-31",
    "iso:country":"GB",
    "wof:name":"CR8 5LW",
    "wof:placetype":"postalcode"
},
  "geometry": {"coordinates":[-0.109611,51.319493],"type":"Point"}
}