{
  "type": "Feature",
  "properties": {
    "iso:country":"GB",
    "wof:name":"CR8 5LW",
    "wof:placetype":"postalcode"
},
  "geometry": {"coordinates":[-0.10961082660095,51.31949310355453],"type":"Point"}
}