{
  "type": "Feature",
  "properties": {
    "iso:country": "GB",
    "wof:name": "LL11 3LA",
    "wof:placetype": "postalcode"
  },
  "geometry": {"coordinates":[-3.062026,53.055646],"type":"Point"}
}
