{
  "type": "Feature",
  "properties": {
    "iso:country":"GB",
    "wof:name":"LL11 3LA",
    "wof:placetype":"postalcode"
},
  "geometry": {"coordinates":[-3.06202592624862,53.05564615353232],"type":"Point"}
}