{
  "type": "Feature",
  "properties": {
    "date:inception_lower": "1980-01-01",
    "date:inception_upper": "1980-01-01",
    "iso:country": "GB",
    "wof:name": "LL11 3LA",
    "wof:placetype": "postalcode"
  },
  "geometry": {"coordinates":[-3.062026,53.055646],"type":"Point"}
}
