{
  "type": "Feature",
  "properties": {
    "iso:country":"GB",
    "wof:name":"WS4 1SW",
    "wof:placetype":"postalcode"
},
  "geometry": {"coordinates":[-1.96030520168159,52.61054236612483],"type":"Point"}
}