{
  "type": "Feature",
  "properties": {
    "iso:country":"GB",
    "wof:name":"LN1 3JA",
    "wof:placetype":"postalcode"
},
  "geometry": {"coordinates":[-0.54466453584901,53.23996059413184],"type":"Point"}
}