{
  "type": "Feature",
  "properties": {
    "iso:country": "GB",
    "wof:name": "CB4 3SP",
    "wof:placetype": "postalcode"
  },
  "geometry": {"coordinates":[0.115167,52.227845],"type":"Point"}
}
