{
  "type": "Feature",
  "properties": {
    "date:inception_lower":"1980-01-01",
    "date:inception_upper":"1980-01-31",
    "iso:country":"GB",
    "wof:name":"CB4 3SP",
    "wof:placetype":"postalcode"
},
  "geometry": {"coordinates":[0.115167,52.227845],"type":"Point"}
}