{
  "type": "Feature",
  "properties": {
    "iso:country": "GB",
    "wof:name": "NE48 2AS",
    "wof:placetype": "postalcode"
  },
  "geometry": {"coordinates":[-2.255602,55.14322],"type":"Point"}
}
