{
  "type": "Feature",
  "properties": {
    "iso:country":"GB",
    "wof:name":"NE48 2AS",
    "wof:placetype":"postalcode"
},
  "geometry": {"coordinates":[-2.2555635117339,55.14342234566033],"type":"Point"}
}