{
  "type": "Feature",
  "properties": {
    "date:inception_lower":"1980-01-01",
    "date:inception_upper":"1980-01-31",
    "iso:country":"GB",
    "wof:name":"NE48 2AS",
    "wof:placetype":"postalcode"
},
  "geometry": {"coordinates":[-2.255602,55.14322],"type":"Point"}
}