{
  "type": "Feature",
  "properties": {
    "iso:country":"GB",
    "wof:name":"PE6 7LS",
    "wof:placetype":"postalcode"
},
  "geometry": {"coordinates":[-0.2933446647877,52.63835560699515],"type":"Point"}
}