{
  "type": "Feature",
  "properties": {
    "iso:country":"GB",
    "wof:name":"SE11 6BA",
    "wof:placetype":"postalcode"
},
  "geometry": {"coordinates":[-0.11537594464744,51.49235346050035],"type":"Point"}
}