{
  "type": "Feature",
  "properties": {
    "date:inception_lower":"2015-06-01",
    "date:inception_upper":"2015-06-30",
    "iso:country":"GB",
    "wof:name":"SE11 6BA",
    "wof:placetype":"postalcode"
},
  "geometry": {"coordinates":[-0.115376,51.492353],"type":"Point"}
}