{
  "type": "Feature",
  "properties": {
    "iso:country":"GB",
    "wof:name":"CF23 6TF",
    "wof:placetype":"postalcode"
},
  "geometry": {"coordinates":[-3.15839540993965,51.51982476332711],"type":"Point"}
}