{
  "type": "Feature",
  "properties": {
    "iso:country":"GB",
    "wof:name":"TN22 5SJ",
    "wof:placetype":"postalcode"
},
  "geometry": {"coordinates":[0.09870437925031,50.95898265355338],"type":"Point"}
}