{
  "type": "Feature",
  "properties": {
    "iso:country": "GB",
    "wof:name": "TS4 2WA",
    "wof:placetype": "postalcode"
  },
  "geometry": {"coordinates":[-1.217477,54.561613],"type":"Point"}
}
