{
  "type": "Feature",
  "properties": {
    "iso:country":"GB",
    "wof:name":"TS4 2WA",
    "wof:placetype":"postalcode"
},
  "geometry": {"coordinates":[-1.21747700479002,54.5616132217091],"type":"Point"}
}