{
  "type": "Feature",
  "properties": {
    "iso:country":"GB",
    "wof:name":"PR2 2ZB",
    "wof:placetype":"postalcode"
},
  "geometry": {"coordinates":[-2.73129738037921,53.76174304014194],"type":"Point"}
}