{
  "type": "Feature",
  "properties": {
    "iso:country": "GB",
    "wof:name": "PR2 2ZB",
    "wof:placetype": "postalcode"
  },
  "geometry": {"coordinates":[-2.731297,53.761743],"type":"Point"}
}
