{
  "type": "Feature",
  "properties": {
    "iso:country":"GB",
    "wof:name":"ML11 7RF",
    "wof:placetype":"postalcode"
},
  "geometry": {"coordinates":[-3.80474584176513,55.69398762242421],"type":"Point"}
}