{
  "type": "Feature",
  "properties": {
    "iso:country":"GB",
    "wof:name":"WS11 9SB",
    "wof:placetype":"postalcode"
},
  "geometry": {"coordinates":[-1.97200280117013,52.67831908136464],"type":"Point"}
}