{
  "type": "Feature",
  "properties": {
    "iso:country":"GB",
    "wof:name":"TQ12 3DY",
    "wof:placetype":"postalcode"
},
  "geometry": {"coordinates":[-3.5843289725504,50.54827758470014],"type":"Point"}
}