{
  "type": "Feature",
  "properties": {
    "iso:country": "GB",
    "wof:name": "PO22 0DL",
    "wof:placetype": "postalcode"
  },
  "geometry": {"coordinates":[-0.633111,50.831898],"type":"Point"}
}
