{
  "type": "Feature",
  "properties": {
    "iso:country":"GB",
    "wof:name":"PO22 0DL",
    "wof:placetype":"postalcode"
},
  "geometry": {"coordinates":[-0.63410780781223,50.8311005180258],"type":"Point"}
}