{
  "type": "Feature",
  "properties": {
    "iso:country":"GB",
    "wof:name":"CA28 6BU",
    "wof:placetype":"postalcode"
},
  "geometry": {"coordinates":[-3.58372792750585,54.55411461000432],"type":"Point"}
}