{
  "type": "Feature",
  "properties": {
    "date:inception_lower": "1980-01-01",
    "date:inception_upper": "1980-01-01",
    "iso:country": "GB",
    "wof:name": "CA28 6BU",
    "wof:placetype": "postalcode"
  },
  "geometry": {"coordinates":[-3.583728,54.554115],"type":"Point"}
}
