{
  "type": "Feature",
  "properties": {
    "iso:country":"GB",
    "wof:name":"CH5 4WQ",
    "wof:placetype":"postalcode"
},
  "geometry": {"coordinates":[-3.07643130060544,53.21974398249031],"type":"Point"}
}