{
  "type": "Feature",
  "properties": {
    "date:inception_lower":"1995-07-01",
    "date:inception_upper":"1995-07-31",
    "iso:country":"GB",
    "wof:name":"CH5 4WQ",
    "wof:placetype":"postalcode"
},
  "geometry": {"coordinates":[-3.076431,53.219744],"type":"Point"}
}