{
  "type": "Feature",
  "properties": {
    "iso:country": "GB",
    "wof:name": "DL5 4DS",
    "wof:placetype": "postalcode"
  },
  "geometry": {"coordinates":[-1.572765,54.619862],"type":"Point"}
}
