{
  "type": "Feature",
  "properties": {
    "iso:country":"GB",
    "wof:name":"DL5 4DS",
    "wof:placetype":"postalcode"
},
  "geometry": {"coordinates":[-1.57276513417612,54.61986176778785],"type":"Point"}
}