{
  "type": "Feature",
  "properties": {
    "date:inception_lower": "1993-01-01",
    "date:inception_upper": "1993-01-01",
    "iso:country": "GB",
    "wof:name": "KT12 2YH",
    "wof:placetype": "postalcode"
  },
  "geometry": {"coordinates":[-0.403695,51.390883],"type":"Point"}
}
