{
  "type": "Feature",
  "properties": {
    "iso:country": "GB",
    "wof:name": "TN24 0TA",
    "wof:placetype": "postalcode"
  },
  "geometry": {"coordinates":[0.90881,51.143437],"type":"Point"}
}
