{
  "type": "Feature",
  "properties": {
    "iso:country":"GB",
    "wof:name":"CV37 0TS",
    "wof:placetype":"postalcode"
},
  "geometry": {"coordinates":[-1.72672831351895,52.20471813509473],"type":"Point"}
}