{
  "type": "Feature",
  "properties": {
    "date:inception_lower":"2010-01-01",
    "date:inception_upper":"2010-01-31",
    "iso:country":"GB",
    "wof:name":"DE3 9EB",
    "wof:placetype":"postalcode"
},
  "geometry": {"coordinates":[-1.526722,52.913984],"type":"Point"}
}