{
  "type": "Feature",
  "properties": {
    "iso:country": "GB",
    "wof:name": "DE3 9EB",
    "wof:placetype": "postalcode"
  },
  "geometry": {"coordinates":[-1.526722,52.913984],"type":"Point"}
}
