{
  "type": "Feature",
  "properties": {
    "iso:country":"GB",
    "wof:name":"DE3 9EB",
    "wof:placetype":"postalcode"
},
  "geometry": {"coordinates":[-1.5267219273058,52.91398373763817],"type":"Point"}
}