{
  "type": "Feature",
  "properties": {
    "iso:country": "GB",
    "wof:name": "DN16 3JE",
    "wof:placetype": "postalcode"
  },
  "geometry": {"coordinates":[-0.651096,53.563082],"type":"Point"}
}
