{
  "type": "Feature",
  "properties": {
    "date:inception_lower":"1997-06-01",
    "date:inception_upper":"1997-06-30",
    "iso:country":"GB",
    "wof:name":"S20 6RR",
    "wof:placetype":"postalcode"
},
  "geometry": {"coordinates":[-1.379816,53.34252],"type":"Point"}
}