{
  "type": "Feature",
  "properties": {
    "iso:country":"GB",
    "wof:name":"S20 6RR",
    "wof:placetype":"postalcode"
},
  "geometry": {"coordinates":[-1.37981624983675,53.34252040433706],"type":"Point"}
}