{
  "type": "Feature",
  "properties": {
    "date:inception_lower": "2016-05-01",
    "date:inception_upper": "2016-05-01",
    "iso:country": "GB",
    "wof:name": "SY5 8BF",
    "wof:placetype": "postalcode"
  },
  "geometry": {"coordinates":[-2.833787,52.601181],"type":"Point"}
}
