{
  "type": "Feature",
  "properties": {
    "iso:country": "GB",
    "wof:name": "SY5 8BF",
    "wof:placetype": "postalcode"
  },
  "geometry": {"coordinates":[-2.834204,52.601349],"type":"Point"}
}
