{
  "type": "Feature",
  "properties": {
    "iso:country": "GB",
    "wof:name": "SY5 8BF",
    "wof:placetype": "postalcode"
  },
  "geometry": {"coordinates":[-2.833787,52.601181],"type":"Point"}
}
