{
  "type": "Feature",
  "properties": {
    "iso:country":"GB",
    "wof:name":"AB42 5PF",
    "wof:placetype":"postalcode"
},
  "geometry": {"coordinates":[-2.10529779597125,57.50959188608656],"type":"Point"}
}