{
  "type": "Feature",
  "properties": {
    "iso:country":"GB",
    "wof:name":"HG3 1DS",
    "wof:placetype":"postalcode"
},
  "geometry": {"coordinates":[-1.48412127823481,53.96805253699444],"type":"Point"}
}