{
  "type": "Feature",
  "properties": {
    "iso:country":"GB",
    "wof:name":"AL8 7BL",
    "wof:placetype":"postalcode"
},
  "geometry": {"coordinates":[-0.21896614741094,51.80287356882793],"type":"Point"}
}