{
  "type": "Feature",
  "properties": {
    "iso:country":"GB",
    "wof:name":"TD11 3DW",
    "wof:placetype":"postalcode"
},
  "geometry": {"coordinates":[-2.34211714413769,55.77881929067998],"type":"Point"}
}