{
  "type": "Feature",
  "properties": {
    "date:inception_lower": "1980-01-01",
    "date:inception_upper": "1980-01-01",
    "iso:country": "GB",
    "wof:name": "NG32 3SN",
    "wof:placetype": "postalcode"
  },
  "geometry": {"coordinates":[-0.562634,52.980473],"type":"Point"}
}
