{
  "type": "Feature",
  "properties": {
    "iso:country":"GB",
    "wof:name":"NG32 3SN",
    "wof:placetype":"postalcode"
},
  "geometry": {"coordinates":[-0.5626338814392,52.98047273611289],"type":"Point"}
}