{
  "type": "Feature",
  "properties": {
    "iso:country":"GB",
    "wof:name":"CW9 5DH",
    "wof:placetype":"postalcode"
},
  "geometry": {"coordinates":[-2.51244062567871,53.26209397422083],"type":"Point"}
}