{
  "type": "Feature",
  "properties": {
    "date:inception_lower": "1995-07-01",
    "date:inception_upper": "1995-07-01",
    "iso:country": "GB",
    "wof:name": "NG8 6AR",
    "wof:placetype": "postalcode"
  },
  "geometry": {"coordinates":[-1.202937,52.989798],"type":"Point"}
}
