{
  "type": "Feature",
  "properties": {
    "iso:country": "GB",
    "wof:name": "NG8 6AR",
    "wof:placetype": "postalcode"
  },
  "geometry": {"coordinates":[-1.202673,52.989678],"type":"Point"}
}
