{
  "type": "Feature",
  "properties": {
    "iso:country":"GB",
    "wof:name":"NG8 6AR",
    "wof:placetype":"postalcode"
},
  "geometry": {"coordinates":[-1.20293951115639,52.98977873928706],"type":"Point"}
}