{
  "type": "Feature",
  "properties": {
    "date:inception_lower": "1980-01-01",
    "date:inception_upper": "1980-01-01",
    "iso:country": "GB",
    "wof:name": "HX7 7AX",
    "wof:placetype": "postalcode"
  },
  "geometry": {"coordinates":[-2.041709,53.778501],"type":"Point"}
}
