{
  "type": "Feature",
  "properties": {
    "iso:country":"GB",
    "wof:name":"HX7 7AX",
    "wof:placetype":"postalcode"
},
  "geometry": {"coordinates":[-2.04170865399962,53.77850134983984],"type":"Point"}
}