{
  "type": "Feature",
  "properties": {
    "iso:country":"GB",
    "wof:name":"WV14 9XF",
    "wof:placetype":"postalcode"
},
  "geometry": {"coordinates":[-2.09839883421437,52.55115713600565],"type":"Point"}
}