{
  "type": "Feature",
  "properties": {
    "date:inception_lower": "1996-06-01",
    "date:inception_upper": "1996-06-01",
    "iso:country": "GB",
    "wof:name": "KY6 3EQ",
    "wof:placetype": "postalcode"
  },
  "geometry": {"coordinates":[-3.196057,56.214686],"type":"Point"}
}
