{
  "type": "Feature",
  "properties": {
    "iso:country":"GB",
    "wof:name":"TN8 5PX",
    "wof:placetype":"postalcode"
},
  "geometry": {"coordinates":[0.05708925079335,51.17840534286824],"type":"Point"}
}