{
  "type": "Feature",
  "properties": {
    "iso:country":"GB",
    "wof:name":"NN9 5ZP",
    "wof:placetype":"postalcode"
},
  "geometry": {"coordinates":[-0.67650541624379,52.30177444289463],"type":"Point"}
}