{
  "type": "Feature",
  "properties": {
    "iso:country":"GB",
    "wof:name":"SR5 2SH",
    "wof:placetype":"postalcode"
},
  "geometry": {"coordinates":[-1.39568026574142,54.92339624661467],"type":"Point"}
}