{
  "type": "Feature",
  "properties": {
    "date:inception_lower": "2015-12-01",
    "date:inception_upper": "2015-12-01",
    "iso:country": "GB",
    "wof:name": "CO1 9QF",
    "wof:placetype": "postalcode"
  },
  "geometry": {"coordinates":[0.745399,51.816996],"type":"Point"}
}
