{
  "type": "Feature",
  "properties": {
    "date:inception_lower": "2022-09-01",
    "date:inception_upper": "2022-09-01",
    "iso:country": "GB",
    "wof:name": "WA4 3EE",
    "wof:placetype": "postalcode"
  },
  "geometry": {"coordinates":[-2.550614,53.36514],"type":"Point"}
}
