{
  "type": "Feature",
  "properties": {
    "date:inception_lower": "2023-05-01",
    "date:inception_upper": "2023-05-01",
    "iso:country": "GB",
    "wof:name": "WA4 3EE",
    "wof:placetype": "postalcode"
  },
  "geometry": {"coordinates":[-2.550988,53.365004],"type":"Point"}
}
