{
  "type": "Feature",
  "properties": {
    "iso:country":"GB",
    "wof:name":"G64 1BF",
    "wof:placetype":"postalcode"
},
  "geometry": {"coordinates":[-4.22859862192915,55.89558655189581],"type":"Point"}
}