{
  "type": "Feature",
  "properties": {
    "iso:country": "GB",
    "wof:name": "G64 1BF",
    "wof:placetype": "postalcode"
  },
  "geometry": {"coordinates":[-4.228599,55.895587],"type":"Point"}
}
