{
  "type": "Feature",
  "properties": {
    "iso:country":"GB",
    "wof:name":"LU3 2NE",
    "wof:placetype":"postalcode"
},
  "geometry": {"coordinates":[-0.4441357797418,51.90318792589632],"type":"Point"}
}