{
  "type": "Feature",
  "properties": {
    "iso:country": "GB",
    "wof:name": "WA10 4DF",
    "wof:placetype": "postalcode"
  },
  "geometry": {"coordinates":[-2.76157,53.454113],"type":"Point"}
}
