{
  "type": "Feature",
  "properties": {
    "iso:country":"GB",
    "wof:name":"NG32 1PQ",
    "wof:placetype":"postalcode"
},
  "geometry": {"coordinates":[-0.77080872095475,52.88784756273103],"type":"Point"}
}