{
  "type": "Feature",
  "properties": {
    "iso:country": "GB",
    "wof:name": "IP25 6GF",
    "wof:placetype": "postalcode"
  },
  "geometry": {"coordinates":[0.861244,52.569035],"type":"Point"}
}
