{
  "type": "Feature",
  "properties": {
    "date:inception_lower":"2012-04-01",
    "date:inception_upper":"2012-04-30",
    "iso:country":"GB",
    "wof:name":"DA11 9BN",
    "wof:placetype":"postalcode"
},
  "geometry": {"coordinates":[0.340882,51.441864],"type":"Point"}
}