{
  "type": "Feature",
  "properties": {
    "iso:country":"GB",
    "wof:name":"DA11 9BN",
    "wof:placetype":"postalcode"
},
  "geometry": {"coordinates":[0.34088187047883,51.44186402842948],"type":"Point"}
}