{
  "type": "Feature",
  "properties": {
    "iso:country": "GB",
    "wof:name": "DA11 9BN",
    "wof:placetype": "postalcode"
  },
  "geometry": {"coordinates":[0.340882,51.441864],"type":"Point"}
}
