{
  "type": "Feature",
  "properties": {
    "date:inception_lower": "1980-01-01",
    "date:inception_upper": "1980-01-01",
    "iso:country": "GB",
    "wof:name": "WS10 9PS",
    "wof:placetype": "postalcode"
  },
  "geometry": {"coordinates":[-2.016405,52.562335],"type":"Point"}
}
