{
  "type": "Feature",
  "properties": {
    "iso:country":"GB",
    "wof:name":"BR3 3AX",
    "wof:placetype":"postalcode"
},
  "geometry": {"coordinates":[-0.0243669840173,51.39119791213046],"type":"Point"}
}