{
  "type": "Feature",
  "properties": {
    "iso:country":"GB",
    "wof:name":"SN3 6DN",
    "wof:placetype":"postalcode"
},
  "geometry": {"coordinates":[-1.73774479971936,51.55274981726485],"type":"Point"}
}