{
  "type": "Feature",
  "properties": {
    "iso:country":"GB",
    "wof:name":"B69 1DP",
    "wof:placetype":"postalcode"
},
  "geometry": {"coordinates":[-2.03307876106264,52.49064660305841],"type":"Point"}
}