{
  "type": "Feature",
  "properties": {
    "iso:country": "GB",
    "wof:name": "PE28 9NU",
    "wof:placetype": "postalcode"
  },
  "geometry": {"coordinates":[-0.11266,52.276864],"type":"Point"}
}
