{
  "type": "Feature",
  "properties": {
    "date:inception_lower": "2000-06-01",
    "date:inception_upper": "2000-06-01",
    "iso:country": "GB",
    "wof:name": "PE28 9NU",
    "wof:placetype": "postalcode"
  },
  "geometry": {"coordinates":[-0.11266,52.276864],"type":"Point"}
}
