{
  "type": "Feature",
  "properties": {
    "iso:country":"GB",
    "wof:name":"NW6 5FS",
    "wof:placetype":"postalcode"
},
  "geometry": {"coordinates":[-0.20315941170772,51.5338196321924],"type":"Point"}
}