{
  "type": "Feature",
  "properties": {
    "iso:country":"GB",
    "wof:name":"M38 9GZ",
    "wof:placetype":"postalcode"
},
  "geometry": {"coordinates":[-2.42404991551612,53.53262156737829],"type":"Point"}
}