{
  "type": "Feature",
  "properties": {
    "iso:country":"GB",
    "wof:name":"BH13 7BH",
    "wof:placetype":"postalcode"
},
  "geometry": {"coordinates":[-1.91665998767595,50.71639432816528],"type":"Point"}
}