{
  "type": "Feature",
  "properties": {
    "iso:country": "GB",
    "wof:name": "SO32 2RJ",
    "wof:placetype": "postalcode"
  },
  "geometry": {"coordinates":[-1.179834,50.942927],"type":"Point"}
}
