{
  "type": "Feature",
  "properties": {
    "iso:country":"GB",
    "wof:name":"OX3 0QN",
    "wof:placetype":"postalcode"
},
  "geometry": {"coordinates":[-1.23721666589455,51.77804709496844],"type":"Point"}
}