{
  "type": "Feature",
  "properties": {
    "date:inception_lower": "1980-01-01",
    "date:inception_upper": "1980-01-01",
    "iso:country": "GB",
    "wof:name": "OX3 0QN",
    "wof:placetype": "postalcode"
  },
  "geometry": {"coordinates":[-1.237097,51.778007],"type":"Point"}
}
