{
  "type": "Feature",
  "properties": {
    "iso:country": "GB",
    "wof:name": "DA12 3HD",
    "wof:placetype": "postalcode"
  },
  "geometry": {"coordinates":[0.419253,51.401826],"type":"Point"}
}
