{
  "type": "Feature",
  "properties": {
    "iso:country":"GB",
    "wof:name":"DA12 3HD",
    "wof:placetype":"postalcode"
},
  "geometry": {"coordinates":[0.41925280128155,51.40182572667925],"type":"Point"}
}