{
  "type": "Feature",
  "properties": {
    "iso:country":"GB",
    "wof:name":"N18 1FG",
    "wof:placetype":"postalcode"
},
  "geometry": {"coordinates":[-0.08261431411606,51.61695324105009],"type":"Point"}
}