{
  "type": "Feature",
  "properties": {
    "iso:country": "GB",
    "wof:name": "WA16 8TU",
    "wof:placetype": "postalcode"
  },
  "geometry": {"coordinates":[-2.321248,53.261181],"type":"Point"}
}
