{
  "type": "Feature",
  "properties": {
    "date:inception_lower":"2003-05-01",
    "date:inception_upper":"2003-05-31",
    "iso:country":"GB",
    "wof:name":"TN28 8NG",
    "wof:placetype":"postalcode"
},
  "geometry": {"coordinates":[0.966317,50.978666],"type":"Point"}
}