{
  "type": "Feature",
  "properties": {
    "iso:country":"GB",
    "wof:name":"TN28 8NG",
    "wof:placetype":"postalcode"
},
  "geometry": {"coordinates":[0.96631667940791,50.97866612326565],"type":"Point"}
}