{
  "type": "Feature",
  "properties": {
    "iso:country": "GB",
    "wof:name": "TN28 8NG",
    "wof:placetype": "postalcode"
  },
  "geometry": {"coordinates":[0.966317,50.978666],"type":"Point"}
}
