{
  "type": "Feature",
  "properties": {
    "iso:country": "GB",
    "wof:name": "CM13 3TP",
    "wof:placetype": "postalcode"
  },
  "geometry": {"coordinates":[0.3433,51.570202],"type":"Point"}
}
