{
  "type": "Feature",
  "properties": {
    "iso:country":"GB",
    "wof:name":"CM13 3TP",
    "wof:placetype":"postalcode"
},
  "geometry": {"coordinates":[0.34329952702857,51.57020181617568],"type":"Point"}
}