{
  "type": "Feature",
  "properties": {
    "iso:country":"GB",
    "wof:name":"BH20 7ED",
    "wof:placetype":"postalcode"
},
  "geometry": {"coordinates":[-2.1526643034082,50.74495626286786],"type":"Point"}
}