{
  "type": "Feature",
  "properties": {
    "iso:country": "GB",
    "wof:name": "CW9 6NN",
    "wof:placetype": "postalcode"
  },
  "geometry": {"coordinates":[-2.523107,53.30567],"type":"Point"}
}
