{
  "type": "Feature",
  "properties": {
    "iso:country":"GB",
    "wof:name":"CW9 6NN",
    "wof:placetype":"postalcode"
},
  "geometry": {"coordinates":[-2.52310705169092,53.30567047190922],"type":"Point"}
}