{
  "type": "Feature",
  "properties": {
    "iso:country":"GB",
    "wof:name":"BB1 2HN",
    "wof:placetype":"postalcode"
},
  "geometry": {"coordinates":[-2.44769868969414,53.74463169292644],"type":"Point"}
}