{
  "type": "Feature",
  "properties": {
    "iso:country": "GB",
    "wof:name": "BB1 2HN",
    "wof:placetype": "postalcode"
  },
  "geometry": {"coordinates":[-2.447699,53.744632],"type":"Point"}
}
