{
  "type": "Feature",
  "properties": {
    "iso:country":"GB",
    "wof:name":"G71 6TF",
    "wof:placetype":"postalcode"
},
  "geometry": {"coordinates":[-4.07142846999571,55.83150440475364],"type":"Point"}
}