{
  "type": "Feature",
  "properties": {
    "iso:country":"GB",
    "wof:name":"CT21 5AN",
    "wof:placetype":"postalcode"
},
  "geometry": {"coordinates":[1.08277045099995,51.07108455665535],"type":"Point"}
}