{
  "type": "Feature",
  "properties": {
    "iso:country":"GB",
    "wof:name":"G82 2HH",
    "wof:placetype":"postalcode"
},
  "geometry": {"coordinates":[-4.55660204128207,55.95000489717479],"type":"Point"}
}