{
  "type": "Feature",
  "properties": {
    "iso:country": "GB",
    "wof:name": "KA24 4EQ",
    "wof:placetype": "postalcode"
  },
  "geometry": {"coordinates":[-4.692033,55.686508],"type":"Point"}
}
