{
  "type": "Feature",
  "properties": {
    "date:inception_lower": "2016-11-01",
    "date:inception_upper": "2016-11-01",
    "iso:country": "GB",
    "wof:name": "KA24 4EQ",
    "wof:placetype": "postalcode"
  },
  "geometry": {"coordinates":[-4.692033,55.686508],"type":"Point"}
}
