{
  "type": "Feature",
  "properties": {
    "date:inception_lower":"1980-01-01",
    "date:inception_upper":"1980-01-31",
    "iso:country":"GB",
    "wof:name":"LS16 5QQ",
    "wof:placetype":"postalcode"
},
  "geometry": {"coordinates":[-1.584818,53.842424],"type":"Point"}
}