{
  "type": "Feature",
  "properties": {
    "iso:country":"GB",
    "wof:name":"B60 2SF",
    "wof:placetype":"postalcode"
},
  "geometry": {"coordinates":[-2.03944477124282,52.33101705731207],"type":"Point"}
}