{
  "type": "Feature",
  "properties": {
    "date:inception_lower": "2000-12-01",
    "date:inception_upper": "2000-12-01",
    "iso:country": "GB",
    "wof:name": "B60 2SF",
    "wof:placetype": "postalcode"
  },
  "geometry": {"coordinates":[-2.039445,52.331017],"type":"Point"}
}
