{
  "type": "Feature",
  "properties": {
    "date:inception_lower": "1980-01-01",
    "date:inception_upper": "1980-01-01",
    "iso:country": "GB",
    "wof:name": "DL1 1JZ",
    "wof:placetype": "postalcode"
  },
  "geometry": {"coordinates":[-1.546284,54.530607],"type":"Point"}
}
