{
  "type": "Feature",
  "properties": {
    "iso:country": "GB",
    "wof:name": "GU21 4LQ",
    "wof:placetype": "postalcode"
  },
  "geometry": {"coordinates":[-0.564408,51.322111],"type":"Point"}
}
