{
  "type": "Feature",
  "properties": {
    "iso:country": "GB",
    "wof:name": "SY2 6JW",
    "wof:placetype": "postalcode"
  },
  "geometry": {"coordinates":[-2.731716,52.702124],"type":"Point"}
}
