{
  "type": "Feature",
  "properties": {
    "iso:country":"GB",
    "wof:name":"B69 4AN",
    "wof:placetype":"postalcode"
},
  "geometry": {"coordinates":[-2.01281834946806,52.50695830899241],"type":"Point"}
}