{
  "type": "Feature",
  "properties": {
    "iso:country":"GB",
    "wof:name":"NG16 1DA",
    "wof:placetype":"postalcode"
},
  "geometry": {"coordinates":[-1.23671482140543,52.99466577937111],"type":"Point"}
}