{
  "type": "Feature",
  "properties": {
    "date:inception_lower":"1980-01-01",
    "date:inception_upper":"1980-01-31",
    "iso:country":"GB",
    "wof:name":"NG16 1DA",
    "wof:placetype":"postalcode"
},
  "geometry": {"coordinates":[-1.236715,52.994666],"type":"Point"}
}