{
  "type": "Feature",
  "properties": {
    "iso:country":"GB",
    "wof:name":"SW3 3RD",
    "wof:placetype":"postalcode"
},
  "geometry": {"coordinates":[-0.16788831208132,51.49116231393841],"type":"Point"}
}