{
  "type": "Feature",
  "properties": {
    "iso:country":"GB",
    "wof:name":"SS6 7HY",
    "wof:placetype":"postalcode"
},
  "geometry": {"coordinates":[0.60468286844719,51.58664218231077],"type":"Point"}
}