{
  "type": "Feature",
  "properties": {
    "iso:country": "GB",
    "wof:name": "SS6 7HY",
    "wof:placetype": "postalcode"
  },
  "geometry": {"coordinates":[0.604683,51.586642],"type":"Point"}
}
