{
  "type": "Feature",
  "properties": {
    "iso:country":"GB",
    "wof:name":"RH1 3HP",
    "wof:placetype":"postalcode"
},
  "geometry": {"coordinates":[-0.14602330113567,51.25352841665027],"type":"Point"}
}