{
  "type": "Feature",
  "properties": {
    "iso:country": "GB",
    "wof:name": "SW20 0DN",
    "wof:placetype": "postalcode"
  },
  "geometry": {"coordinates":[-0.239529,51.414709],"type":"Point"}
}
