{
  "type": "Feature",
  "properties": {
    "date:inception_lower": "1980-01-01",
    "date:inception_upper": "1980-01-01",
    "iso:country": "GB",
    "wof:name": "SW20 0DN",
    "wof:placetype": "postalcode"
  },
  "geometry": {"coordinates":[-0.239529,51.414709],"type":"Point"}
}
