{
  "type": "Feature",
  "properties": {
    "date:inception_lower": "2022-04-01",
    "date:inception_upper": "2022-04-01",
    "iso:country": "GB",
    "wof:name": "TA4 2ER",
    "wof:placetype": "postalcode"
  },
  "geometry": {"coordinates":[-3.303982,51.040989],"type":"Point"}
}
