{
  "type": "Feature",
  "properties": {
    "iso:country":"GB",
    "wof:name":"M27 8XE",
    "wof:placetype":"postalcode"
},
  "geometry": {"coordinates":[-2.308239800463,53.50301802186624],"type":"Point"}
}