{
  "type": "Feature",
  "properties": {
    "iso:country":"GB",
    "wof:name":"LU2 9HG",
    "wof:placetype":"postalcode"
},
  "geometry": {"coordinates":[-0.38485322436026,51.88547587352118],"type":"Point"}
}