{
  "type": "Feature",
  "properties": {
    "date:inception_lower": "2023-12-01",
    "date:inception_upper": "2023-12-01",
    "iso:country": "GB",
    "wof:name": "CB5 8XE",
    "wof:placetype": "postalcode"
  },
  "geometry": {"coordinates":[0.180594,52.216255],"type":"Point"}
}
