{
  "type": "Feature",
  "properties": {
    "iso:country":"GB",
    "wof:name":"BN14 9DL",
    "wof:placetype":"postalcode"
},
  "geometry": {"coordinates":[-0.38016898567781,50.83261810331628],"type":"Point"}
}