{
  "type": "Feature",
  "properties": {
    "iso:country": "GB",
    "wof:name": "GL50 4GQ",
    "wof:placetype": "postalcode"
  },
  "geometry": {"coordinates":[-2.076107,51.906539],"type":"Point"}
}
