{
  "type": "Feature",
  "properties": {
    "date:inception_lower":"2007-11-01",
    "date:inception_upper":"2007-11-30",
    "iso:country":"GB",
    "wof:name":"GL50 4GQ",
    "wof:placetype":"postalcode"
},
  "geometry": {"coordinates":[-2.076107,51.906539],"type":"Point"}
}