{
  "type": "Feature",
  "properties": {
    "iso:country": "GB",
    "wof:name": "CT11 7AL",
    "wof:placetype": "postalcode"
  },
  "geometry": {"coordinates":[1.416351,51.342816],"type":"Point"}
}
