{
  "type": "Feature",
  "properties": {
    "iso:country": "GB",
    "wof:name": "EN9 2LG",
    "wof:placetype": "postalcode"
  },
  "geometry": {"coordinates":[0.018407,51.73584],"type":"Point"}
}
