{
  "type": "Feature",
  "properties": {
    "iso:country":"GB",
    "wof:name":"EN9 2LG",
    "wof:placetype":"postalcode"
},
  "geometry": {"coordinates":[0.0184071735889,51.7358397529916],"type":"Point"}
}