{
  "type": "Feature",
  "properties": {
    "date:inception_lower": "1994-12-01",
    "date:inception_upper": "1994-12-01",
    "iso:country": "GB",
    "wof:name": "LA14 2BF",
    "wof:placetype": "postalcode"
  },
  "geometry": {"coordinates":[-3.21699,54.112871],"type":"Point"}
}
