{
  "type": "Feature",
  "properties": {
    "iso:country":"GB",
    "wof:name":"LA14 2BF",
    "wof:placetype":"postalcode"
},
  "geometry": {"coordinates":[-3.21699028350991,54.11287148535251],"type":"Point"}
}