{
  "type": "Feature",
  "properties": {
    "date:inception_lower": "2005-01-01",
    "date:inception_upper": "2005-01-01",
    "iso:country": "GB",
    "wof:name": "LS25 5EF",
    "wof:placetype": "postalcode"
  },
  "geometry": {"coordinates":[-1.2282,53.760243],"type":"Point"}
}
