{
  "type": "Feature",
  "properties": {
    "iso:country":"GB",
    "wof:name":"CR3 6EQ",
    "wof:placetype":"postalcode"
},
  "geometry": {"coordinates":[-0.09291708778666,51.26349363191625],"type":"Point"}
}