{
  "type": "Feature",
  "properties": {
    "iso:country": "GB",
    "wof:name": "W9 2DL",
    "wof:placetype": "postalcode"
  },
  "geometry": {"coordinates":[-0.199422,51.523036],"type":"Point"}
}
