{
  "type": "Feature",
  "properties": {
    "iso:country": "GB",
    "wof:name": "WA9 2AS",
    "wof:placetype": "postalcode"
  },
  "geometry": {"coordinates":[-2.697177,53.450488],"type":"Point"}
}
