{
  "type": "Feature",
  "properties": {
    "iso:country":"GB",
    "wof:name":"CR0 6AD",
    "wof:placetype":"postalcode"
},
  "geometry": {"coordinates":[-0.08256317822318,51.37924215508205],"type":"Point"}
}