{
  "type": "Feature",
  "properties": {
    "date:inception_lower": "1999-06-01",
    "date:inception_upper": "1999-06-01",
    "iso:country": "GB",
    "wof:name": "CF14 0FL",
    "wof:placetype": "postalcode"
  },
  "geometry": {"coordinates":[-3.190435,51.54523],"type":"Point"}
}
