{
  "type": "Feature",
  "properties": {
    "iso:country":"GB",
    "wof:name":"CF14 0FL",
    "wof:placetype":"postalcode"
},
  "geometry": {"coordinates":[-3.19043538464532,51.54522959769702],"type":"Point"}
}