{
  "type": "Feature",
  "properties": {
    "iso:country":"GB",
    "wof:name":"SP4 7XU",
    "wof:placetype":"postalcode"
},
  "geometry": {"coordinates":[-1.76404573548172,51.16217014924342],"type":"Point"}
}