{
  "type": "Feature",
  "properties": {
    "date:inception_lower": "2023-06-01",
    "date:inception_upper": "2023-06-01",
    "iso:country": "GB",
    "wof:name": "CV35 0QL",
    "wof:placetype": "postalcode"
  },
  "geometry": {"coordinates":[-1.515623,52.160128],"type":"Point"}
}
