{
  "type": "Feature",
  "properties": {
    "date:inception_lower":"1980-01-01",
    "date:inception_upper":"1980-01-31",
    "iso:country":"GB",
    "wof:name":"PL9 9ED",
    "wof:placetype":"postalcode"
},
  "geometry": {"coordinates":[-4.096571,50.355904],"type":"Point"}
}