{
  "type": "Feature",
  "properties": {
    "iso:country":"GB",
    "wof:name":"PL9 9ED",
    "wof:placetype":"postalcode"
},
  "geometry": {"coordinates":[-4.09657118886072,50.35590441668218],"type":"Point"}
}