{
  "type": "Feature",
  "properties": {
    "iso:country":"GB",
    "wof:name":"M25 9WU",
    "wof:placetype":"postalcode"
},
  "geometry": {"coordinates":[-2.27951276833538,53.52259356943825],"type":"Point"}
}