{
  "type": "Feature",
  "properties": {
    "iso:country": "GB",
    "wof:name": "G82 4JT",
    "wof:placetype": "postalcode"
  },
  "geometry": {"coordinates":[-4.579325,55.946763],"type":"Point"}
}
