{
  "type": "Feature",
  "properties": {
    "iso:country":"GB",
    "wof:name":"G82 4JT",
    "wof:placetype":"postalcode"
},
  "geometry": {"coordinates":[-4.57932522840241,55.94676270880971],"type":"Point"}
}