{
  "type": "Feature",
  "properties": {
    "iso:country": "GB",
    "wof:name": "HP12 4TZ",
    "wof:placetype": "postalcode"
  },
  "geometry": {"coordinates":[-0.776349,51.616468],"type":"Point"}
}
