{
  "type": "Feature",
  "properties": {
    "iso:country":"GB",
    "wof:name":"HP12 4TZ",
    "wof:placetype":"postalcode"
},
  "geometry": {"coordinates":[-0.77634896718484,51.61646809279858],"type":"Point"}
}