{
  "type": "Feature",
  "properties": {
    "date:inception_lower": "1980-01-01",
    "date:inception_upper": "1980-01-01",
    "iso:country": "GB",
    "wof:name": "BN21 1QF",
    "wof:placetype": "postalcode"
  },
  "geometry": {"coordinates":[0.263982,50.773679],"type":"Point"}
}
