{
  "type": "Feature",
  "properties": {
    "iso:country":"GB",
    "wof:name":"TN17 4NJ",
    "wof:placetype":"postalcode"
},
  "geometry": {"coordinates":[0.64245291905927,51.04214705826402],"type":"Point"}
}