{
  "type": "Feature",
  "properties": {
    "date:inception_lower":"1980-01-01",
    "date:inception_upper":"1980-01-31",
    "iso:country":"GB",
    "wof:name":"TN17 4NJ",
    "wof:placetype":"postalcode"
},
  "geometry": {"coordinates":[0.642453,51.042147],"type":"Point"}
}