{
  "type": "Feature",
  "properties": {
    "iso:country":"GB",
    "wof:name":"S4 8JP",
    "wof:placetype":"postalcode"
},
  "geometry": {"coordinates":[-1.44213403954288,53.41150162628099],"type":"Point"}
}