{
  "type": "Feature",
  "properties": {
    "iso:country":"GB",
    "wof:name":"S70 3BA",
    "wof:placetype":"postalcode"
},
  "geometry": {"coordinates":[-1.45363441651903,53.54123272033379],"type":"Point"}
}