{
  "type": "Feature",
  "properties": {
    "iso:country": "GB",
    "wof:name": "DE13 0PA",
    "wof:placetype": "postalcode"
  },
  "geometry": {"coordinates":[-1.651718,52.826023],"type":"Point"}
}
