{
  "type": "Feature",
  "properties": {
    "iso:country":"GB",
    "wof:name":"M40 8GA",
    "wof:placetype":"postalcode"
},
  "geometry": {"coordinates":[-2.2089764418495,53.49966456875338],"type":"Point"}
}