{
  "type": "Feature",
  "properties": {
    "iso:country":"GB",
    "wof:name":"UB8 3WU",
    "wof:placetype":"postalcode"
},
  "geometry": {"coordinates":[-0.45927364476667,51.5277331589967],"type":"Point"}
}