{
  "type": "Feature",
  "properties": {
    "iso:country": "GB",
    "wof:name": "UB8 3WU",
    "wof:placetype": "postalcode"
  },
  "geometry": {"coordinates":[-0.459274,51.527733],"type":"Point"}
}
