{
  "type": "Feature",
  "properties": {
    "iso:country":"GB",
    "wof:name":"SE6 2AB",
    "wof:placetype":"postalcode"
},
  "geometry": {"coordinates":[-0.01476820741636,51.44788804000762],"type":"Point"}
}