{
  "type": "Feature",
  "properties": {
    "iso:country":"GB",
    "wof:name":"SS5 4EH",
    "wof:placetype":"postalcode"
},
  "geometry": {"coordinates":[0.66696162137154,51.59596317371708],"type":"Point"}
}