{
  "type": "Feature",
  "properties": {
    "iso:country": "GB",
    "wof:name": "SS5 4EH",
    "wof:placetype": "postalcode"
  },
  "geometry": {"coordinates":[0.666883,51.595872],"type":"Point"}
}
