{
  "type": "Feature",
  "properties": {
    "iso:country": "GB",
    "wof:name": "RG25 2QP",
    "wof:placetype": "postalcode"
  },
  "geometry": {"coordinates":[-1.093168,51.209404],"type":"Point"}
}
