{
  "type": "Feature",
  "properties": {
    "date:inception_lower": "1986-07-01",
    "date:inception_upper": "1986-07-01",
    "iso:country": "GB",
    "wof:name": "CV35 7RS",
    "wof:placetype": "postalcode"
  },
  "geometry": {"coordinates":[-1.577736,52.319084],"type":"Point"}
}
