{
  "type": "Feature",
  "properties": {
    "iso:country":"GB",
    "wof:name":"CV35 7RS",
    "wof:placetype":"postalcode"
},
  "geometry": {"coordinates":[-1.57774852273029,52.3190592942208],"type":"Point"}
}