{
  "type": "Feature",
  "properties": {
    "iso:country":"GB",
    "wof:name":"DD3 9AD",
    "wof:placetype":"postalcode"
},
  "geometry": {"coordinates":[-3.0008622266084,56.48903337986879],"type":"Point"}
}