{
  "type": "Feature",
  "properties": {
    "iso:country": "GB",
    "wof:name": "DD3 9AD",
    "wof:placetype": "postalcode"
  },
  "geometry": {"coordinates":[-3.000862,56.489033],"type":"Point"}
}
