{
  "type": "Feature",
  "properties": {
    "date:inception_lower": "1980-01-01",
    "date:inception_upper": "1980-01-01",
    "iso:country": "GB",
    "wof:name": "E5 8PZ",
    "wof:placetype": "postalcode"
  },
  "geometry": {"coordinates":[-0.062,51.55659],"type":"Point"}
}
