{
  "type": "Feature",
  "properties": {
    "date:inception_lower": "2008-07-01",
    "date:inception_upper": "2008-07-01",
    "iso:country": "GB",
    "wof:name": "IP14 5US",
    "wof:placetype": "postalcode"
  },
  "geometry": {"coordinates":[1.007387,52.193471],"type":"Point"}
}
