{
  "type": "Feature",
  "properties": {
    "iso:country":"GB",
    "wof:name":"YO16 6TS",
    "wof:placetype":"postalcode"
},
  "geometry": {"coordinates":[-0.1758795618732,54.10120607897997],"type":"Point"}
}