{
  "type": "Feature",
  "properties": {
    "iso:country": "GB",
    "wof:name": "LE5 4HH",
    "wof:placetype": "postalcode"
  },
  "geometry": {"coordinates":[-1.098192,52.632866],"type":"Point"}
}
