{
  "type": "Feature",
  "properties": {
    "date:inception_lower": "1998-06-01",
    "date:inception_upper": "1998-06-01",
    "iso:country": "GB",
    "wof:name": "YO32 3ER",
    "wof:placetype": "postalcode"
  },
  "geometry": {"coordinates":[-1.072652,54.007861],"type":"Point"}
}
