{
  "type": "Feature",
  "properties": {
    "iso:country": "GB",
    "wof:name": "YO32 3ER",
    "wof:placetype": "postalcode"
  },
  "geometry": {"coordinates":[-1.072689,54.007835],"type":"Point"}
}
