{
  "type": "Feature",
  "properties": {
    "iso:country":"GB",
    "wof:name":"YO32 3ER",
    "wof:placetype":"postalcode"
},
  "geometry": {"coordinates":[-1.07268952503124,54.00783534661074],"type":"Point"}
}