{
  "type": "Feature",
  "properties": {
    "date:inception_lower":"1998-06-01",
    "date:inception_upper":"1998-06-30",
    "iso:country":"GB",
    "wof:name":"YO32 3ER",
    "wof:placetype":"postalcode"
},
  "geometry": {"coordinates":[-1.072689,54.007835],"type":"Point"}
}