{
  "type": "Feature",
  "properties": {
    "iso:country": "GB",
    "wof:name": "CF64 4AX",
    "wof:placetype": "postalcode"
  },
  "geometry": {"coordinates":[-3.206763,51.432457],"type":"Point"}
}
