{
  "type": "Feature",
  "properties": {
    "iso:country": "GB",
    "wof:name": "FY6 0FA",
    "wof:placetype": "postalcode"
  },
  "geometry": {"coordinates":[-2.976492,53.928203],"type":"Point"}
}
