{
  "type": "Feature",
  "properties": {
    "iso:country":"GB",
    "wof:name":"DN9 1QA",
    "wof:placetype":"postalcode"
},
  "geometry": {"coordinates":[-0.83697273303042,53.5576628320926],"type":"Point"}
}