{
  "type": "Feature",
  "properties": {
    "iso:country": "GB",
    "wof:name": "TF6 6NH",
    "wof:placetype": "postalcode"
  },
  "geometry": {"coordinates":[-2.594422,52.728123],"type":"Point"}
}
