{
  "type": "Feature",
  "properties": {
    "date:inception_lower": "2015-11-01",
    "date:inception_upper": "2015-11-01",
    "iso:country": "GB",
    "wof:name": "TF6 6NH",
    "wof:placetype": "postalcode"
  },
  "geometry": {"coordinates":[-2.593994,52.728224],"type":"Point"}
}
