{
  "type": "Feature",
  "properties": {
    "iso:country":"GB",
    "wof:name":"TF6 6NH",
    "wof:placetype":"postalcode"
},
  "geometry": {"coordinates":[-2.60609613278437,52.71238890737178],"type":"Point"}
}