{
  "type": "Feature",
  "properties": {
    "iso:country": "GB",
    "wof:name": "IP19 9HR",
    "wof:placetype": "postalcode"
  },
  "geometry": {"coordinates":[1.519225,52.315794],"type":"Point"}
}
