{
  "type": "Feature",
  "properties": {
    "iso:country":"GB",
    "wof:name":"EX8 1LL",
    "wof:placetype":"postalcode"
},
  "geometry": {"coordinates":[-3.41059410141631,50.62132648099422],"type":"Point"}
}