{
  "type": "Feature",
  "properties": {
    "iso:country": "GB",
    "wof:name": "LE67 2HH",
    "wof:placetype": "postalcode"
  },
  "geometry": {"coordinates":[-1.409951,52.720707],"type":"Point"}
}
