{
  "type": "Feature",
  "properties": {
    "iso:country":"GB",
    "wof:name":"ME4 6PS",
    "wof:placetype":"postalcode"
},
  "geometry": {"coordinates":[0.52062461460713,51.37995651391947],"type":"Point"}
}