{
  "type": "Feature",
  "properties": {
    "iso:country":"GB",
    "wof:name":"CT18 7AP",
    "wof:placetype":"postalcode"
},
  "geometry": {"coordinates":[1.17566767877118,51.12249368594755],"type":"Point"}
}