{
  "type": "Feature",
  "properties": {
    "iso:country":"GB",
    "wof:name":"AB56 1FL",
    "wof:placetype":"postalcode"
},
  "geometry": {"coordinates":[-2.98141822102895,57.66993622125685],"type":"Point"}
}