{
  "type": "Feature",
  "properties": {
    "date:inception_lower": "1996-06-01",
    "date:inception_upper": "1996-06-01",
    "iso:country": "GB",
    "wof:name": "AB56 1FL",
    "wof:placetype": "postalcode"
  },
  "geometry": {"coordinates":[-2.981418,57.669936],"type":"Point"}
}
