{
  "type": "Feature",
  "properties": {
    "iso:country":"GB",
    "wof:name":"GU8 5FH",
    "wof:placetype":"postalcode"
},
  "geometry": {"coordinates":[-0.66475718440239,51.15617448497179],"type":"Point"}
}