{
  "type": "Feature",
  "properties": {
    "date:inception_lower": "2013-07-01",
    "date:inception_upper": "2013-07-01",
    "iso:country": "GB",
    "wof:name": "GU8 5FH",
    "wof:placetype": "postalcode"
  },
  "geometry": {"coordinates":[-0.664757,51.156174],"type":"Point"}
}
