{
  "type": "Feature",
  "properties": {
    "iso:country": "GB",
    "wof:name": "GU8 5FH",
    "wof:placetype": "postalcode"
  },
  "geometry": {"coordinates":[-0.664757,51.156174],"type":"Point"}
}
