{
  "type": "Feature",
  "properties": {
    "iso:country":"GB",
    "wof:name":"WD3 1LJ",
    "wof:placetype":"postalcode"
},
  "geometry": {"coordinates":[-0.44263936120638,51.63238830922373],"type":"Point"}
}