{
  "type": "Feature",
  "properties": {
    "date:inception_lower": "1980-01-01",
    "date:inception_upper": "1980-01-01",
    "iso:country": "GB",
    "wof:name": "WD3 1LJ",
    "wof:placetype": "postalcode"
  },
  "geometry": {"coordinates":[-0.442639,51.632388],"type":"Point"}
}
