{
  "type": "Feature",
  "properties": {
    "iso:country":"GB",
    "wof:name":"TA15 6UL",
    "wof:placetype":"postalcode"
},
  "geometry": {"coordinates":[-2.71873267603533,50.95384277684933],"type":"Point"}
}