{
  "type": "Feature",
  "properties": {
    "iso:country": "GB",
    "wof:name": "TA15 6UL",
    "wof:placetype": "postalcode"
  },
  "geometry": {"coordinates":[-2.718733,50.953843],"type":"Point"}
}
