{
  "type": "Feature",
  "properties": {
    "iso:country":"GB",
    "wof:name":"YO26 4TE",
    "wof:placetype":"postalcode"
},
  "geometry": {"coordinates":[-1.11722903970651,53.95808043340131],"type":"Point"}
}