{
  "type": "Feature",
  "properties": {
    "iso:country": "GB",
    "wof:name": "YO26 4TE",
    "wof:placetype": "postalcode"
  },
  "geometry": {"coordinates":[-1.117222,53.958098],"type":"Point"}
}
