{
  "type": "Feature",
  "properties": {
    "date:inception_lower": "1980-01-01",
    "date:inception_upper": "1980-01-01",
    "iso:country": "GB",
    "wof:name": "B26 1EL",
    "wof:placetype": "postalcode"
  },
  "geometry": {"coordinates":[-1.807629,52.453151],"type":"Point"}
}
