{
  "type": "Feature",
  "properties": {
    "date:inception_lower": "1980-01-01",
    "date:inception_upper": "1980-01-01",
    "iso:country": "GB",
    "wof:name": "LU7 0QR",
    "wof:placetype": "postalcode"
  },
  "geometry": {"coordinates":[-0.657442,51.865892],"type":"Point"}
}
