{
  "type": "Feature",
  "properties": {
    "iso:country":"GB",
    "wof:name":"LU7 0QR",
    "wof:placetype":"postalcode"
},
  "geometry": {"coordinates":[-0.65780237410551,51.86500627113279],"type":"Point"}
}