{
  "type": "Feature",
  "properties": {
    "iso:country":"GB",
    "wof:name":"HU15 1JD",
    "wof:placetype":"postalcode"
},
  "geometry": {"coordinates":[-0.57096407837774,53.74079931018401],"type":"Point"}
}