{
  "type": "Feature",
  "properties": {
    "iso:country": "GB",
    "wof:name": "HU15 1JD",
    "wof:placetype": "postalcode"
  },
  "geometry": {"coordinates":[-0.570964,53.740799],"type":"Point"}
}
