{
  "type": "Feature",
  "properties": {
    "iso:country":"GB",
    "wof:name":"SO41 8AD",
    "wof:placetype":"postalcode"
},
  "geometry": {"coordinates":[-1.54445345642574,50.74589442987698],"type":"Point"}
}