{
  "type": "Feature",
  "properties": {
    "iso:country": "GB",
    "wof:name": "DY11 5RB",
    "wof:placetype": "postalcode"
  },
  "geometry": {"coordinates":[-2.287973,52.398629],"type":"Point"}
}
