{
  "type": "Feature",
  "properties": {
    "date:inception_lower": "1980-01-01",
    "date:inception_upper": "1980-01-01",
    "iso:country": "GB",
    "wof:name": "SA18 3NZ",
    "wof:placetype": "postalcode"
  },
  "geometry": {"coordinates":[-4.037959,51.838267],"type":"Point"}
}
