{
  "type": "Feature",
  "properties": {
    "iso:country": "GB",
    "wof:name": "OX20 1BH",
    "wof:placetype": "postalcode"
  },
  "geometry": {"coordinates":[-1.408708,51.891971],"type":"Point"}
}
