{
  "type": "Feature",
  "properties": {
    "iso:country":"GB",
    "wof:name":"OX20 1BH",
    "wof:placetype":"postalcode"
},
  "geometry": {"coordinates":[-1.40870756648838,51.89197096805098],"type":"Point"}
}