{
  "type": "Feature",
  "properties": {
    "iso:country":"GB",
    "wof:name":"AL8 7QJ",
    "wof:placetype":"postalcode"
},
  "geometry": {"coordinates":[-0.20591206010162,51.81566857408318],"type":"Point"}
}