{
  "type": "Feature",
  "properties": {
    "date:inception_lower":"2001-12-01",
    "date:inception_upper":"2001-12-31",
    "iso:country":"GB",
    "wof:name":"GU4 8WB",
    "wof:placetype":"postalcode"
},
  "geometry": {"coordinates":[-0.582332,51.245283],"type":"Point"}
}