{
  "type": "Feature",
  "properties": {
    "iso:country":"GB",
    "wof:name":"OX14 5LH",
    "wof:placetype":"postalcode"
},
  "geometry": {"coordinates":[-1.28580133222164,51.66051236243633],"type":"Point"}
}