{
  "type": "Feature",
  "properties": {
    "iso:country":"GB",
    "wof:name":"S42 7JE",
    "wof:placetype":"postalcode"
},
  "geometry": {"coordinates":[-1.4794765885042,53.23966992416675],"type":"Point"}
}