{
  "type": "Feature",
  "properties": {
    "date:inception_lower": "1980-01-01",
    "date:inception_upper": "1980-01-01",
    "iso:country": "GB",
    "wof:name": "S42 7JE",
    "wof:placetype": "postalcode"
  },
  "geometry": {"coordinates":[-1.480648,53.239334],"type":"Point"}
}
