{
  "type": "Feature",
  "properties": {
    "date:inception_lower": "2001-06-01",
    "date:inception_upper": "2001-06-01",
    "iso:country": "GB",
    "wof:name": "L11 4UR",
    "wof:placetype": "postalcode"
  },
  "geometry": {"coordinates":[-2.897362,53.45423],"type":"Point"}
}
