{
  "type": "Feature",
  "properties": {
    "iso:country":"GB",
    "wof:name":"L11 4UR",
    "wof:placetype":"postalcode"
},
  "geometry": {"coordinates":[-2.89736207878006,53.45423024638061],"type":"Point"}
}