{
  "type": "Feature",
  "properties": {
    "iso:country": "GB",
    "wof:name": "ST10 1RF",
    "wof:placetype": "postalcode"
  },
  "geometry": {"coordinates":[-1.964472,52.972019],"type":"Point"}
}
