{
  "type": "Feature",
  "properties": {
    "iso:country":"GB",
    "wof:name":"LL16 5TU",
    "wof:placetype":"postalcode"
},
  "geometry": {"coordinates":[-3.42156849118021,53.22500753757346],"type":"Point"}
}