{
  "type": "Feature",
  "properties": {
    "iso:country":"GB",
    "wof:name":"FY6 0HE",
    "wof:placetype":"postalcode"
},
  "geometry": {"coordinates":[-2.96896989882512,53.92959382913206],"type":"Point"}
}