{
  "type": "Feature",
  "properties": {
    "date:inception_lower": "1980-01-01",
    "date:inception_upper": "1980-01-01",
    "iso:country": "GB",
    "wof:name": "FY6 0HE",
    "wof:placetype": "postalcode"
  },
  "geometry": {"coordinates":[-2.96897,53.929594],"type":"Point"}
}
