{
  "type": "Feature",
  "properties": {
    "date:inception_lower": "2020-09-01",
    "date:inception_upper": "2020-09-01",
    "iso:country": "GB",
    "wof:name": "BB2 2BN",
    "wof:placetype": "postalcode"
  },
  "geometry": {"coordinates":[-2.498181,53.737671],"type":"Point"}
}
