{
  "type": "Feature",
  "properties": {
    "date:inception_lower":"2013-10-01",
    "date:inception_upper":"2013-10-31",
    "iso:country":"GB",
    "wof:name":"CH7 3GG",
    "wof:placetype":"postalcode"
},
  "geometry": {"coordinates":[-3.089239,53.173791],"type":"Point"}
}