{
  "type": "Feature",
  "properties": {
    "iso:country": "GB",
    "wof:name": "BS40 6HU",
    "wof:placetype": "postalcode"
  },
  "geometry": {"coordinates":[-2.630578,51.308382],"type":"Point"}
}
