{
  "type": "Feature",
  "properties": {
    "iso:country":"GB",
    "wof:name":"BS16 6HD",
    "wof:placetype":"postalcode"
},
  "geometry": {"coordinates":[-2.50669784570556,51.4968652373518],"type":"Point"}
}