{
  "type": "Feature",
  "properties": {
    "iso:country":"GB",
    "wof:name":"HU11 4JG",
    "wof:placetype":"postalcode"
},
  "geometry": {"coordinates":[-0.26223838485383,53.80971299041882],"type":"Point"}
}