{
  "type": "Feature",
  "properties": {
    "iso:country": "GB",
    "wof:name": "HU11 4JG",
    "wof:placetype": "postalcode"
  },
  "geometry": {"coordinates":[-0.262238,53.809713],"type":"Point"}
}
