{
  "type": "Feature",
  "properties": {
    "date:inception_lower": "1980-01-01",
    "date:inception_upper": "1980-01-01",
    "iso:country": "GB",
    "wof:name": "HU11 4JG",
    "wof:placetype": "postalcode"
  },
  "geometry": {"coordinates":[-0.262238,53.809713],"type":"Point"}
}
