{
  "type": "Feature",
  "properties": {
    "date:inception_lower": "2012-05-01",
    "date:inception_upper": "2012-05-01",
    "iso:country": "GB",
    "wof:name": "EH16 4GU",
    "wof:placetype": "postalcode"
  },
  "geometry": {"coordinates":[-3.129073,55.930529],"type":"Point"}
}
