{
  "type": "Feature",
  "properties": {
    "iso:country": "GB",
    "wof:name": "EH33 1AA",
    "wof:placetype": "postalcode"
  },
  "geometry": {"coordinates":[-2.954076,55.945244],"type":"Point"}
}
