{
  "type": "Feature",
  "properties": {
    "iso:country":"GB",
    "wof:name":"EH33 1AA",
    "wof:placetype":"postalcode"
},
  "geometry": {"coordinates":[-2.95407558724238,55.94524419727369],"type":"Point"}
}