{
  "type": "Feature",
  "properties": {
    "iso:country":"GB",
    "wof:name":"UB3 2NY",
    "wof:placetype":"postalcode"
},
  "geometry": {"coordinates":[-0.42965400281739,51.51709832486945],"type":"Point"}
}