{
  "type": "Feature",
  "properties": {
    "date:inception_lower": "1993-08-01",
    "date:inception_upper": "1993-08-01",
    "iso:country": "GB",
    "wof:name": "CH2 4LG",
    "wof:placetype": "postalcode"
  },
  "geometry": {"coordinates":[-2.822447,53.268826],"type":"Point"}
}
