{
  "type": "Feature",
  "properties": {
    "iso:country":"GB",
    "wof:name":"DD4 9FJ",
    "wof:placetype":"postalcode"
},
  "geometry": {"coordinates":[-2.96395622225601,56.49509339838072],"type":"Point"}
}