{
  "type": "Feature",
  "properties": {
    "iso:country": "GB",
    "wof:name": "DD4 9FJ",
    "wof:placetype": "postalcode"
  },
  "geometry": {"coordinates":[-2.963956,56.495093],"type":"Point"}
}
