{
  "type": "Feature",
  "properties": {
    "iso:country": "GB",
    "wof:name": "KY15 4TH",
    "wof:placetype": "postalcode"
  },
  "geometry": {"coordinates":[-3.009772,56.319323],"type":"Point"}
}
