{
  "type": "Feature",
  "properties": {
    "iso:country":"GB",
    "wof:name":"KY15 4TH",
    "wof:placetype":"postalcode"
},
  "geometry": {"coordinates":[-3.00977167490326,56.31932250980923],"type":"Point"}
}