{
  "type": "Feature",
  "properties": {
    "iso:country":"GB",
    "wof:name":"HR2 6GN",
    "wof:placetype":"postalcode"
},
  "geometry": {"coordinates":[-2.7194729767439,52.04405475161534],"type":"Point"}
}