{
  "type": "Feature",
  "properties": {
    "iso:country":"GB",
    "wof:name":"EX2 8JR",
    "wof:placetype":"postalcode"
},
  "geometry": {"coordinates":[-3.53407873556126,50.71070661331106],"type":"Point"}
}