{
  "type": "Feature",
  "properties": {
    "iso:country":"GB",
    "wof:name":"MK44 3PA",
    "wof:placetype":"postalcode"
},
  "geometry": {"coordinates":[-0.3187104127709,52.14475747596602],"type":"Point"}
}