{
  "type": "Feature",
  "properties": {
    "iso:country": "GB",
    "wof:name": "MK44 3PA",
    "wof:placetype": "postalcode"
  },
  "geometry": {"coordinates":[-0.31871,52.144757],"type":"Point"}
}
