{
  "type": "Feature",
  "properties": {
    "iso:country": "GB",
    "wof:name": "WR11 2SL",
    "wof:placetype": "postalcode"
  },
  "geometry": {"coordinates":[-1.971574,52.086808],"type":"Point"}
}
