{
  "type": "Feature",
  "properties": {
    "iso:country": "GB",
    "wof:name": "NG31 7XG",
    "wof:placetype": "postalcode"
  },
  "geometry": {"coordinates":[-0.65689,52.901124],"type":"Point"}
}
