{
  "type": "Feature",
  "properties": {
    "iso:country":"GB",
    "wof:name":"NG31 7XG",
    "wof:placetype":"postalcode"
},
  "geometry": {"coordinates":[-0.65689026201863,52.90112400487125],"type":"Point"}
}