{
  "type": "Feature",
  "properties": {
    "date:inception_lower": "2006-07-01",
    "date:inception_upper": "2006-07-01",
    "iso:country": "GB",
    "wof:name": "CM23 3BD",
    "wof:placetype": "postalcode"
  },
  "geometry": {"coordinates":[0.162752,51.866],"type":"Point"}
}
