{
  "type": "Feature",
  "properties": {
    "iso:country":"GB",
    "wof:name":"CM23 3BD",
    "wof:placetype":"postalcode"
},
  "geometry": {"coordinates":[0.16286664683768,51.8659086907447],"type":"Point"}
}