{
  "type": "Feature",
  "properties": {
    "date:inception_lower": "1980-01-01",
    "date:inception_upper": "1980-01-01",
    "iso:country": "GB",
    "wof:name": "NR31 6BZ",
    "wof:placetype": "postalcode"
  },
  "geometry": {"coordinates":[1.73114,52.573589],"type":"Point"}
}
