{
  "type": "Feature",
  "properties": {
    "iso:country":"GB",
    "wof:name":"NR31 6BZ",
    "wof:placetype":"postalcode"
},
  "geometry": {"coordinates":[1.73113962128092,52.57358937464857],"type":"Point"}
}