{
  "type": "Feature",
  "properties": {
    "iso:country": "GB",
    "wof:name": "E11 4JP",
    "wof:placetype": "postalcode"
  },
  "geometry": {"coordinates":[0.003899,51.553684],"type":"Point"}
}
