{
  "type": "Feature",
  "properties": {
    "iso:country":"GB",
    "wof:name":"E11 4JP",
    "wof:placetype":"postalcode"
},
  "geometry": {"coordinates":[0.00389934206591,51.55368420452542],"type":"Point"}
}