{
  "type": "Feature",
  "properties": {
    "date:inception_lower": "1998-06-01",
    "date:inception_upper": "1998-06-01",
    "iso:country": "GB",
    "wof:name": "E11 4JP",
    "wof:placetype": "postalcode"
  },
  "geometry": {"coordinates":[0.003899,51.553684],"type":"Point"}
}
