{
  "type": "Feature",
  "properties": {
    "iso:country":"GB",
    "wof:name":"OL13 9JJ",
    "wof:placetype":"postalcode"
},
  "geometry": {"coordinates":[-2.19700997190113,53.70141762484354],"type":"Point"}
}