{
  "type": "Feature",
  "properties": {
    "iso:country":"GB",
    "wof:name":"HU8 0JP",
    "wof:placetype":"postalcode"
},
  "geometry": {"coordinates":[-0.30466467018128,53.774929938593],"type":"Point"}
}