{
  "type": "Feature",
  "properties": {
    "date:inception_lower": "1980-01-01",
    "date:inception_upper": "1980-01-01",
    "iso:country": "GB",
    "wof:name": "HU8 0JP",
    "wof:placetype": "postalcode"
  },
  "geometry": {"coordinates":[-0.304665,53.77493],"type":"Point"}
}
