{
  "type": "Feature",
  "properties": {
    "iso:country":"GB",
    "wof:name":"NE13 6JH",
    "wof:placetype":"postalcode"
},
  "geometry": {"coordinates":[-1.62607674985737,55.04546636277555],"type":"Point"}
}