{
  "type": "Feature",
  "properties": {
    "iso:country":"GB",
    "wof:name":"ST3 4LH",
    "wof:placetype":"postalcode"
},
  "geometry": {"coordinates":[-2.13227725633816,52.98149766124837],"type":"Point"}
}