{
  "type": "Feature",
  "properties": {
    "iso:country":"GB",
    "wof:name":"SP11 0QS",
    "wof:placetype":"postalcode"
},
  "geometry": {"coordinates":[-1.54574635177316,51.21737599332707],"type":"Point"}
}