{
  "type": "Feature",
  "properties": {
    "date:inception_lower": "1980-01-01",
    "date:inception_upper": "1980-01-01",
    "iso:country": "GB",
    "wof:name": "TR18 3AB",
    "wof:placetype": "postalcode"
  },
  "geometry": {"coordinates":[-5.533127,50.123419],"type":"Point"}
}
