{
  "type": "Feature",
  "properties": {
    "iso:country": "GB",
    "wof:name": "KY9 1AP",
    "wof:placetype": "postalcode"
  },
  "geometry": {"coordinates":[-2.835138,56.18792],"type":"Point"}
}
