{
  "type": "Feature",
  "properties": {
    "iso:country": "GB",
    "wof:name": "PE28 5RD",
    "wof:placetype": "postalcode"
  },
  "geometry": {"coordinates":[-0.278237,52.441344],"type":"Point"}
}
