{
  "type": "Feature",
  "properties": {
    "iso:country":"GB",
    "wof:name":"PE28 5RD",
    "wof:placetype":"postalcode"
},
  "geometry": {"coordinates":[-0.27823697386208,52.44134378256494],"type":"Point"}
}