{
  "type": "Feature",
  "properties": {
    "iso:country":"GB",
    "wof:name":"NG19 7HQ",
    "wof:placetype":"postalcode"
},
  "geometry": {"coordinates":[-1.21739314635692,53.15758780056063],"type":"Point"}
}