{
  "type": "Feature",
  "properties": {
    "date:inception_lower": "1999-06-01",
    "date:inception_upper": "1999-06-01",
    "iso:country": "GB",
    "wof:name": "NG19 7HQ",
    "wof:placetype": "postalcode"
  },
  "geometry": {"coordinates":[-1.217346,53.157633],"type":"Point"}
}
