{
  "type": "Feature",
  "properties": {
    "iso:country":"GB",
    "wof:name":"SM2 6QT",
    "wof:placetype":"postalcode"
},
  "geometry": {"coordinates":[-0.20067269027985,51.35166465777288],"type":"Point"}
}