{
  "type": "Feature",
  "properties": {
    "iso:country":"GB",
    "wof:name":"G52 1EZ",
    "wof:placetype":"postalcode"
},
  "geometry": {"coordinates":[-4.32941306535562,55.84430571934441],"type":"Point"}
}