{
  "type": "Feature",
  "properties": {
    "iso:country": "GB",
    "wof:name": "SA1 6UW",
    "wof:placetype": "postalcode"
  },
  "geometry": {"coordinates":[-3.952499,51.630897],"type":"Point"}
}
