{
  "type": "Feature",
  "properties": {
    "date:inception_lower":"1980-01-01",
    "date:inception_upper":"1980-01-31",
    "iso:country":"GB",
    "wof:name":"SA1 6UW",
    "wof:placetype":"postalcode"
},
  "geometry": {"coordinates":[-3.952499,51.630897],"type":"Point"}
}