{
  "type": "Feature",
  "properties": {
    "date:inception_lower":"1990-02-01",
    "date:inception_upper":"1990-02-28",
    "iso:country":"GB",
    "wof:name":"E11 2UB",
    "wof:placetype":"postalcode"
},
  "geometry": {"coordinates":[0.026896,51.575816],"type":"Point"}
}