{
  "type": "Feature",
  "properties": {
    "iso:country":"GB",
    "wof:name":"E11 2UB",
    "wof:placetype":"postalcode"
},
  "geometry": {"coordinates":[0.02689610781588,51.57581570451075],"type":"Point"}
}