{
  "type": "Feature",
  "properties": {
    "iso:country": "GB",
    "wof:name": "E11 2UB",
    "wof:placetype": "postalcode"
  },
  "geometry": {"coordinates":[0.026896,51.575816],"type":"Point"}
}
