{
  "type": "Feature",
  "properties": {
    "iso:country":"GB",
    "wof:name":"SO18 5RS",
    "wof:placetype":"postalcode"
},
  "geometry": {"coordinates":[-1.36151757051742,50.91435867140243],"type":"Point"}
}