{
  "type": "Feature",
  "properties": {
    "date:inception_lower": "1994-12-01",
    "date:inception_upper": "1994-12-01",
    "iso:country": "GB",
    "wof:name": "SO18 5RS",
    "wof:placetype": "postalcode"
  },
  "geometry": {"coordinates":[-1.361608,50.914332],"type":"Point"}
}
