{
  "type": "Feature",
  "properties": {
    "date:inception_lower": "2005-03-01",
    "date:inception_upper": "2005-03-01",
    "iso:country": "GB",
    "wof:name": "PR5 6ZF",
    "wof:placetype": "postalcode"
  },
  "geometry": {"coordinates":[-2.650453,53.733708],"type":"Point"}
}
