{
  "type": "Feature",
  "properties": {
    "iso:country":"GB",
    "wof:name":"PE22 0SH",
    "wof:placetype":"postalcode"
},
  "geometry": {"coordinates":[0.02321705089493,53.03643543291943],"type":"Point"}
}