{
  "type": "Feature",
  "properties": {
    "iso:country": "GB",
    "wof:name": "PE22 0SH",
    "wof:placetype": "postalcode"
  },
  "geometry": {"coordinates":[0.023234,53.036038],"type":"Point"}
}
