{
  "type": "Feature",
  "properties": {
    "date:inception_lower": "1980-01-01",
    "date:inception_upper": "1980-01-01",
    "iso:country": "GB",
    "wof:name": "TN27 9NY",
    "wof:placetype": "postalcode"
  },
  "geometry": {"coordinates":[0.599619,51.174645],"type":"Point"}
}
