{
  "type": "Feature",
  "properties": {
    "iso:country":"GB",
    "wof:name":"TN27 9NY",
    "wof:placetype":"postalcode"
},
  "geometry": {"coordinates":[0.59454225054446,51.16987481680877],"type":"Point"}
}