{
  "type": "Feature",
  "properties": {
    "date:inception_lower":"1980-01-01",
    "date:inception_upper":"1980-01-31",
    "iso:country":"GB",
    "wof:name":"PO21 2QB",
    "wof:placetype":"postalcode"
},
  "geometry": {"coordinates":[-0.687783,50.78096],"type":"Point"}
}