{
  "type": "Feature",
  "properties": {
    "iso:country": "GB",
    "wof:name": "PO21 2QB",
    "wof:placetype": "postalcode"
  },
  "geometry": {"coordinates":[-0.687783,50.78096],"type":"Point"}
}
