{
  "type": "Feature",
  "properties": {
    "iso:country":"GB",
    "wof:name":"SN5 4LW",
    "wof:placetype":"postalcode"
},
  "geometry": {"coordinates":[-1.88516439041099,51.57991547977599],"type":"Point"}
}