{
  "type": "Feature",
  "properties": {
    "iso:country":"GB",
    "wof:name":"UB3 4RD",
    "wof:placetype":"postalcode"
},
  "geometry": {"coordinates":[-0.41715848987989,51.49421602740132],"type":"Point"}
}