{
  "type": "Feature",
  "properties": {
    "iso:country":"GB",
    "wof:name":"SW2 4PW",
    "wof:placetype":"postalcode"
},
  "geometry": {"coordinates":[-0.13420862927974,51.44035377492789],"type":"Point"}
}