{
  "type": "Feature",
  "properties": {
    "iso:country":"GB",
    "wof:name":"HA3 8TQ",
    "wof:placetype":"postalcode"
},
  "geometry": {"coordinates":[-0.31537135801247,51.59370941873684],"type":"Point"}
}