{
  "type": "Feature",
  "properties": {
    "date:inception_lower": "2018-09-01",
    "date:inception_upper": "2018-09-01",
    "iso:country": "GB",
    "wof:name": "AB41 7AD",
    "wof:placetype": "postalcode"
  },
  "geometry": {"coordinates":[-2.177389,57.335071],"type":"Point"}
}
