{
  "type": "Feature",
  "properties": {
    "iso:country":"GB",
    "wof:name":"DH9 7PL",
    "wof:placetype":"postalcode"
},
  "geometry": {"coordinates":[-1.70083465975822,54.86060970511117],"type":"Point"}
}