{
  "type": "Feature",
  "properties": {
    "iso:country":"GB",
    "wof:name":"LL20 7LR",
    "wof:placetype":"postalcode"
},
  "geometry": {"coordinates":[-3.18757371076103,52.97451372273039],"type":"Point"}
}