{
  "type": "Feature",
  "properties": {
    "iso:country": "GB",
    "wof:name": "B21 8EE",
    "wof:placetype": "postalcode"
  },
  "geometry": {"coordinates":[-1.942827,52.513877],"type":"Point"}
}
