{
  "type": "Feature",
  "properties": {
    "iso:country": "GB",
    "wof:name": "E9 5LL",
    "wof:placetype": "postalcode"
  },
  "geometry": {"coordinates":[-0.025942,51.544784],"type":"Point"}
}
