{
  "type": "Feature",
  "properties": {
    "date:inception_lower": "1996-06-01",
    "date:inception_upper": "1996-06-01",
    "iso:country": "GB",
    "wof:name": "E9 5LL",
    "wof:placetype": "postalcode"
  },
  "geometry": {"coordinates":[-0.025942,51.544784],"type":"Point"}
}
