{
  "type": "Feature",
  "properties": {
    "iso:country":"GB",
    "wof:name":"E9 5LL",
    "wof:placetype":"postalcode"
},
  "geometry": {"coordinates":[-0.02594197616171,51.54478386331456],"type":"Point"}
}