{
  "type": "Feature",
  "properties": {
    "iso:country": "GB",
    "wof:name": "GL3 2HB",
    "wof:placetype": "postalcode"
  },
  "geometry": {"coordinates":[-2.168014,51.878518],"type":"Point"}
}
