{
  "type": "Feature",
  "properties": {
    "iso:country":"GB",
    "wof:name":"GL3 2HB",
    "wof:placetype":"postalcode"
},
  "geometry": {"coordinates":[-2.16801396546842,51.87851777403508],"type":"Point"}
}