{
  "type": "Feature",
  "properties": {
    "iso:country": "GB",
    "wof:name": "PO10 8BW",
    "wof:placetype": "postalcode"
  },
  "geometry": {"coordinates":[-0.929497,50.842744],"type":"Point"}
}
