{
  "type": "Feature",
  "properties": {
    "date:inception_lower": "2009-06-01",
    "date:inception_upper": "2009-06-01",
    "iso:country": "GB",
    "wof:name": "HA2 0FA",
    "wof:placetype": "postalcode"
  },
  "geometry": {"coordinates":[-0.363283,51.571349],"type":"Point"}
}
