{
  "type": "Feature",
  "properties": {
    "iso:country":"GB",
    "wof:name":"DE23 8RN",
    "wof:placetype":"postalcode"
},
  "geometry": {"coordinates":[-1.47659276268214,52.90032543754708],"type":"Point"}
}