{
  "type": "Feature",
  "properties": {
    "iso:country":"GB",
    "wof:name":"DG3 5JP",
    "wof:placetype":"postalcode"
},
  "geometry": {"coordinates":[-3.71684949195296,55.20174935146344],"type":"Point"}
}