{
  "type": "Feature",
  "properties": {
    "iso:country":"GB",
    "wof:name":"G72 0BS",
    "wof:placetype":"postalcode"
},
  "geometry": {"coordinates":[-4.09272865174824,55.79045887026425],"type":"Point"}
}