{
  "type": "Feature",
  "properties": {
    "date:inception_lower": "1980-01-01",
    "date:inception_upper": "1980-01-01",
    "iso:country": "GB",
    "wof:name": "G72 0BS",
    "wof:placetype": "postalcode"
  },
  "geometry": {"coordinates":[-4.092729,55.790459],"type":"Point"}
}
