{
  "type": "Feature",
  "properties": {
    "iso:country": "GB",
    "wof:name": "DN40 2EQ",
    "wof:placetype": "postalcode"
  },
  "geometry": {"coordinates":[-0.221841,53.614177],"type":"Point"}
}
