{
  "type": "Feature",
  "properties": {
    "date:inception_lower": "1980-01-01",
    "date:inception_upper": "1980-01-01",
    "iso:country": "GB",
    "wof:name": "HX3 8EF",
    "wof:placetype": "postalcode"
  },
  "geometry": {"coordinates":[-1.810695,53.720033],"type":"Point"}
}
