{
  "type": "Feature",
  "properties": {
    "iso:country":"GB",
    "wof:name":"TW8 0NR",
    "wof:placetype":"postalcode"
},
  "geometry": {"coordinates":[-0.30196290620585,51.48745213097908],"type":"Point"}
}