{
  "type": "Feature",
  "properties": {
    "iso:country":"GB",
    "wof:name":"E3 2TD",
    "wof:placetype":"postalcode"
},
  "geometry": {"coordinates":[-0.01741638466319,51.52923573206215],"type":"Point"}
}