{
  "type": "Feature",
  "properties": {
    "date:inception_lower": "2000-06-01",
    "date:inception_upper": "2000-06-01",
    "iso:country": "GB",
    "wof:name": "E3 2TD",
    "wof:placetype": "postalcode"
  },
  "geometry": {"coordinates":[-0.017142,51.528945],"type":"Point"}
}
