{
  "type": "Feature",
  "properties": {
    "date:inception_lower":"2015-10-01",
    "date:inception_upper":"2015-10-31",
    "iso:country":"GB",
    "wof:name":"E14 0GE",
    "wof:placetype":"postalcode"
},
  "geometry": {"coordinates":[-0.001129,51.513672],"type":"Point"}
}