{
  "type": "Feature",
  "properties": {
    "iso:country":"GB",
    "wof:name":"E14 0GE",
    "wof:placetype":"postalcode"
},
  "geometry": {"coordinates":[-0.00112883849245,51.51367177978752],"type":"Point"}
}