{
  "type": "Feature",
  "properties": {
    "iso:country": "GB",
    "wof:name": "E14 0GE",
    "wof:placetype": "postalcode"
  },
  "geometry": {"coordinates":[-0.001129,51.513672],"type":"Point"}
}
