{
  "type": "Feature",
  "properties": {
    "iso:country":"GB",
    "wof:name":"KA10 6JG",
    "wof:placetype":"postalcode"
},
  "geometry": {"coordinates":[-4.65303328902506,55.54023405369804],"type":"Point"}
}