{
  "type": "Feature",
  "properties": {
    "iso:country": "GB",
    "wof:name": "KA10 6JG",
    "wof:placetype": "postalcode"
  },
  "geometry": {"coordinates":[-4.653033,55.540234],"type":"Point"}
}
