{
  "type": "Feature",
  "properties": {
    "iso:country":"GB",
    "wof:name":"PO3 5TB",
    "wof:placetype":"postalcode"
},
  "geometry": {"coordinates":[-1.0485248499509,50.82721138505423],"type":"Point"}
}