{
  "type": "Feature",
  "properties": {
    "date:inception_lower": "1992-01-01",
    "date:inception_upper": "1992-01-01",
    "iso:country": "GB",
    "wof:name": "KA6 7BL",
    "wof:placetype": "postalcode"
  },
  "geometry": {"coordinates":[-4.460715,55.437595],"type":"Point"}
}
