{
  "type": "Feature",
  "properties": {
    "iso:country":"GB",
    "wof:name":"KA6 7BL",
    "wof:placetype":"postalcode"
},
  "geometry": {"coordinates":[-4.46073196617669,55.43759305149359],"type":"Point"}
}