{
  "type": "Feature",
  "properties": {
    "date:inception_lower": "1980-01-01",
    "date:inception_upper": "1980-01-01",
    "iso:country": "GB",
    "wof:name": "WS12 4NJ",
    "wof:placetype": "postalcode"
  },
  "geometry": {"coordinates":[-2.038705,52.707496],"type":"Point"}
}
