{
  "type": "Feature",
  "properties": {
    "iso:country":"GB",
    "wof:name":"N19 5EU",
    "wof:placetype":"postalcode"
},
  "geometry": {"coordinates":[-0.13513486086782,51.55564380494757],"type":"Point"}
}