{
  "type": "Feature",
  "properties": {
    "date:inception_lower": "1980-01-01",
    "date:inception_upper": "1980-01-01",
    "iso:country": "GB",
    "wof:name": "N19 5EU",
    "wof:placetype": "postalcode"
  },
  "geometry": {"coordinates":[-0.135135,51.555644],"type":"Point"}
}
