{
  "type": "Feature",
  "properties": {
    "date:inception_lower": "1980-01-01",
    "date:inception_upper": "1980-01-01",
    "iso:country": "GB",
    "wof:name": "TQ7 1AL",
    "wof:placetype": "postalcode"
  },
  "geometry": {"coordinates":[-3.777661,50.287593],"type":"Point"}
}
