{
  "type": "Feature",
  "properties": {
    "iso:country":"GB",
    "wof:name":"TQ7 1AL",
    "wof:placetype":"postalcode"
},
  "geometry": {"coordinates":[-3.77766100678675,50.28759310159317],"type":"Point"}
}