{
  "type": "Feature",
  "properties": {
    "iso:country": "GB",
    "wof:name": "TQ7 1AL",
    "wof:placetype": "postalcode"
  },
  "geometry": {"coordinates":[-3.777661,50.287593],"type":"Point"}
}
