{
  "type": "Feature",
  "properties": {
    "iso:country":"GB",
    "wof:name":"TS6 0PW",
    "wof:placetype":"postalcode"
},
  "geometry": {"coordinates":[-1.15206786627367,54.55088240971453],"type":"Point"}
}