{
  "type": "Feature",
  "properties": {
    "iso:country":"GB",
    "wof:name":"BA2 7AQ",
    "wof:placetype":"postalcode"
},
  "geometry": {"coordinates":[-2.32267304667205,51.3666075439256],"type":"Point"}
}