{
  "type": "Feature",
  "properties": {
    "date:inception_lower":"1980-01-01",
    "date:inception_upper":"1980-01-31",
    "iso:country":"GB",
    "wof:name":"BA2 7AQ",
    "wof:placetype":"postalcode"
},
  "geometry": {"coordinates":[-2.322673,51.366608],"type":"Point"}
}