{
  "type": "Feature",
  "properties": {
    "iso:country":"GB",
    "wof:name":"DD3 9QX",
    "wof:placetype":"postalcode"
},
  "geometry": {"coordinates":[-3.0017591701485,56.49718406578201],"type":"Point"}
}