{
  "type": "Feature",
  "properties": {
    "iso:country":"GB",
    "wof:name":"GL52 8SN",
    "wof:placetype":"postalcode"
},
  "geometry": {"coordinates":[-2.07048711260327,51.94721685405132],"type":"Point"}
}