{
  "type": "Feature",
  "properties": {
    "iso:country": "GB",
    "wof:name": "GL52 8SN",
    "wof:placetype": "postalcode"
  },
  "geometry": {"coordinates":[-2.070487,51.947217],"type":"Point"}
}
