{
  "type": "Feature",
  "properties": {
    "iso:country": "GB",
    "wof:name": "PH3 1DF",
    "wof:placetype": "postalcode"
  },
  "geometry": {"coordinates":[-3.70069,56.297753],"type":"Point"}
}
