{
  "type": "Feature",
  "properties": {
    "iso:country":"GB",
    "wof:name":"RG9 1BT",
    "wof:placetype":"postalcode"
},
  "geometry": {"coordinates":[-0.90111060741368,51.53279309458637],"type":"Point"}
}