{
  "type": "Feature",
  "properties": {
    "date:inception_lower": "1987-04-01",
    "date:inception_upper": "1987-04-01",
    "iso:country": "GB",
    "wof:name": "WF17 7SF",
    "wof:placetype": "postalcode"
  },
  "geometry": {"coordinates":[-1.65034,53.714094],"type":"Point"}
}
