{
  "type": "Feature",
  "properties": {
    "date:inception_lower": "1980-01-01",
    "date:inception_upper": "1980-01-01",
    "iso:country": "GB",
    "wof:name": "PO10 8SJ",
    "wof:placetype": "postalcode"
  },
  "geometry": {"coordinates":[-0.92558,50.862439],"type":"Point"}
}
