{
  "type": "Feature",
  "properties": {
    "iso:country":"GB",
    "wof:name":"PO10 8SJ",
    "wof:placetype":"postalcode"
},
  "geometry": {"coordinates":[-0.9255802811783,50.86243924491215],"type":"Point"}
}