{
  "type": "Feature",
  "properties": {
    "iso:country":"GB",
    "wof:name":"DA1 1LN",
    "wof:placetype":"postalcode"
},
  "geometry": {"coordinates":[0.21640930145218,51.43749436623224],"type":"Point"}
}