{
  "type": "Feature",
  "properties": {
    "date:inception_lower": "1998-12-01",
    "date:inception_upper": "1998-12-01",
    "iso:country": "GB",
    "wof:name": "DA1 1LN",
    "wof:placetype": "postalcode"
  },
  "geometry": {"coordinates":[0.216409,51.437494],"type":"Point"}
}
