{
  "type": "Feature",
  "properties": {
    "iso:country": "GB",
    "wof:name": "DA1 1LN",
    "wof:placetype": "postalcode"
  },
  "geometry": {"coordinates":[0.216409,51.437494],"type":"Point"}
}
