{
  "type": "Feature",
  "properties": {
    "date:inception_lower": "2005-11-01",
    "date:inception_upper": "2005-11-01",
    "iso:country": "GB",
    "wof:name": "LA18 4GY",
    "wof:placetype": "postalcode"
  },
  "geometry": {"coordinates":[-3.29147,54.195379],"type":"Point"}
}
