{
  "type": "Feature",
  "properties": {
    "iso:country": "GB",
    "wof:name": "LA18 4GY",
    "wof:placetype": "postalcode"
  },
  "geometry": {"coordinates":[-3.290897,54.195169],"type":"Point"}
}
