{
  "type": "Feature",
  "properties": {
    "iso:country":"GB",
    "wof:name":"TF11 9JR",
    "wof:placetype":"postalcode"
},
  "geometry": {"coordinates":[-2.36847295937745,52.62443963095439],"type":"Point"}
}