{
  "type": "Feature",
  "properties": {
    "iso:country": "GB",
    "wof:name": "TF11 9JR",
    "wof:placetype": "postalcode"
  },
  "geometry": {"coordinates":[-2.368441,52.624464],"type":"Point"}
}
