{
  "type": "Feature",
  "properties": {
    "iso:country":"GB",
    "wof:name":"B73 5HD",
    "wof:placetype":"postalcode"
},
  "geometry": {"coordinates":[-1.83418099675209,52.53789435876233],"type":"Point"}
}