{
  "type": "Feature",
  "properties": {
    "iso:country": "GB",
    "wof:name": "KT12 2DX",
    "wof:placetype": "postalcode"
  },
  "geometry": {"coordinates":[-0.410527,51.392387],"type":"Point"}
}
