{
  "type": "Feature",
  "properties": {
    "iso:country":"GB",
    "wof:name":"KT12 2DX",
    "wof:placetype":"postalcode"
},
  "geometry": {"coordinates":[-0.41052729891151,51.3923872424343],"type":"Point"}
}