{
  "type": "Feature",
  "properties": {
    "iso:country":"GB",
    "wof:name":"CT14 6QQ",
    "wof:placetype":"postalcode"
},
  "geometry": {"coordinates":[1.39429522624675,51.23554349839508],"type":"Point"}
}