{
  "type": "Feature",
  "properties": {
    "iso:country":"GB",
    "wof:name":"WA10 1EN",
    "wof:placetype":"postalcode"
},
  "geometry": {"coordinates":[-2.7296540582325,53.45557027857526],"type":"Point"}
}