{
  "type": "Feature",
  "properties": {
    "iso:country":"GB",
    "wof:name":"G74 1DW",
    "wof:placetype":"postalcode"
},
  "geometry": {"coordinates":[-4.19514361369762,55.76620363725245],"type":"Point"}
}