{
  "type": "Feature",
  "properties": {
    "iso:country":"GB",
    "wof:name":"ML3 6TN",
    "wof:placetype":"postalcode"
},
  "geometry": {"coordinates":[-4.04934886695837,55.7669067046353],"type":"Point"}
}