{
  "type": "Feature",
  "properties": {
    "iso:country": "GB",
    "wof:name": "GL6 9LE",
    "wof:placetype": "postalcode"
  },
  "geometry": {"coordinates":[-2.178752,51.707169],"type":"Point"}
}
