{
  "type": "Feature",
  "properties": {
    "iso:country":"GB",
    "wof:name":"GL6 9LE",
    "wof:placetype":"postalcode"
},
  "geometry": {"coordinates":[-2.17875235520868,51.70716899921194],"type":"Point"}
}