{
  "type": "Feature",
  "properties": {
    "iso:country": "GB",
    "wof:name": "LA11 7RX",
    "wof:placetype": "postalcode"
  },
  "geometry": {"coordinates":[-2.938062,54.17744],"type":"Point"}
}
