{
  "type": "Feature",
  "properties": {
    "iso:country":"GB",
    "wof:name":"GU8 5NR",
    "wof:placetype":"postalcode"
},
  "geometry": {"coordinates":[-0.64980017199172,51.15468989886487],"type":"Point"}
}