{
  "type": "Feature",
  "properties": {
    "date:inception_lower": "1984-10-01",
    "date:inception_upper": "1984-10-01",
    "iso:country": "GB",
    "wof:name": "TN12 6LJ",
    "wof:placetype": "postalcode"
  },
  "geometry": {"coordinates":[0.386576,51.173728],"type":"Point"}
}
