{
  "type": "Feature",
  "properties": {
    "date:inception_lower": "1995-12-01",
    "date:inception_upper": "1995-12-01",
    "iso:country": "GB",
    "wof:name": "CW1 6HD",
    "wof:placetype": "postalcode"
  },
  "geometry": {"coordinates":[-2.421151,53.096496],"type":"Point"}
}
