{
  "type": "Feature",
  "properties": {
    "date:inception_lower": "1980-01-01",
    "date:inception_upper": "1980-01-01",
    "iso:country": "GB",
    "wof:name": "CB11 4XE",
    "wof:placetype": "postalcode"
  },
  "geometry": {"coordinates":[0.169692,52.02385],"type":"Point"}
}
