{
  "type": "Feature",
  "properties": {
    "iso:country": "GB",
    "wof:name": "E16 2GD",
    "wof:placetype": "postalcode"
  },
  "geometry": {"coordinates":[0.068818,51.49941],"type":"Point"}
}
