{
  "type": "Feature",
  "properties": {
    "date:inception_lower":"2002-06-01",
    "date:inception_upper":"2002-06-30",
    "iso:country":"GB",
    "wof:name":"E16 2GD",
    "wof:placetype":"postalcode"
},
  "geometry": {"coordinates":[0.068818,51.49941],"type":"Point"}
}