{
  "type": "Feature",
  "properties": {
    "iso:country":"GB",
    "wof:name":"E16 2GD",
    "wof:placetype":"postalcode"
},
  "geometry": {"coordinates":[0.06881747711662,51.49941026394504],"type":"Point"}
}