{
  "type": "Feature",
  "properties": {
    "date:inception_lower": "2023-07-01",
    "date:inception_upper": "2023-07-01",
    "iso:country": "GB",
    "wof:name": "G13 1FG",
    "wof:placetype": "postalcode"
  },
  "geometry": {"coordinates":[-4.343182,55.885139],"type":"Point"}
}
