{
  "type": "Feature",
  "properties": {
    "date:inception_lower":"1996-12-01",
    "date:inception_upper":"1996-12-31",
    "iso:country":"GB",
    "wof:name":"WF7 7QU",
    "wof:placetype":"postalcode"
},
  "geometry": {"coordinates":[-1.344676,53.643351],"type":"Point"}
}