{
  "type": "Feature",
  "properties": {
    "iso:country":"GB",
    "wof:name":"WF7 7QU",
    "wof:placetype":"postalcode"
},
  "geometry": {"coordinates":[-1.34467639097461,53.64335149117974],"type":"Point"}
}