{
  "type": "Feature",
  "properties": {
    "date:inception_lower": "1980-01-01",
    "date:inception_upper": "1980-01-01",
    "iso:country": "GB",
    "wof:name": "NN12 8TD",
    "wof:placetype": "postalcode"
  },
  "geometry": {"coordinates":[-0.990298,52.096153],"type":"Point"}
}
