{
  "type": "Feature",
  "properties": {
    "iso:country":"GB",
    "wof:name":"NN12 8TD",
    "wof:placetype":"postalcode"
},
  "geometry": {"coordinates":[-0.99029822751522,52.09615342977882],"type":"Point"}
}