{
  "type": "Feature",
  "properties": {
    "date:inception_lower": "2022-08-01",
    "date:inception_upper": "2022-08-01",
    "iso:country": "GB",
    "wof:name": "CM0 7YJ",
    "wof:placetype": "postalcode"
  },
  "geometry": {"coordinates":[0.851899,51.677035],"type":"Point"}
}
