{
  "type": "Feature",
  "properties": {
    "date:inception_lower": "2004-09-01",
    "date:inception_upper": "2004-09-01",
    "iso:country": "GB",
    "wof:name": "NN8 2QD",
    "wof:placetype": "postalcode"
  },
  "geometry": {"coordinates":[-0.696217,52.287761],"type":"Point"}
}
