{
  "type": "Feature",
  "properties": {
    "iso:country":"GB",
    "wof:name":"NN8 2QD",
    "wof:placetype":"postalcode"
},
  "geometry": {"coordinates":[-0.69621722793676,52.28776117962749],"type":"Point"}
}