{
  "type": "Feature",
  "properties": {
    "iso:country":"GB",
    "wof:name":"BD20 8ED",
    "wof:placetype":"postalcode"
},
  "geometry": {"coordinates":[-2.03869137725501,53.91217917027144],"type":"Point"}
}