{
  "type": "Feature",
  "properties": {
    "date:inception_lower": "1980-01-01",
    "date:inception_upper": "1980-01-01",
    "iso:country": "GB",
    "wof:name": "PA15 2LG",
    "wof:placetype": "postalcode"
  },
  "geometry": {"coordinates":[-4.738872,55.940362],"type":"Point"}
}
