{
  "type": "Feature",
  "properties": {
    "iso:country":"GB",
    "wof:name":"ME7 3SD",
    "wof:placetype":"postalcode"
},
  "geometry": {"coordinates":[0.57499704277759,51.34035273148645],"type":"Point"}
}