{
  "type": "Feature",
  "properties": {
    "iso:country":"GB",
    "wof:name":"SY12 0FH",
    "wof:placetype":"postalcode"
},
  "geometry": {"coordinates":[-2.8979787134667,52.90341220483262],"type":"Point"}
}