{
  "type": "Feature",
  "properties": {
    "date:inception_lower": "2012-11-01",
    "date:inception_upper": "2012-11-01",
    "iso:country": "GB",
    "wof:name": "SY12 0FH",
    "wof:placetype": "postalcode"
  },
  "geometry": {"coordinates":[-2.898014,52.903724],"type":"Point"}
}
