{
  "type": "Feature",
  "properties": {
    "date:inception_lower":"1983-03-01",
    "date:inception_upper":"1983-03-31",
    "iso:country":"GB",
    "wof:name":"SS17 8EU",
    "wof:placetype":"postalcode"
},
  "geometry": {"coordinates":[0.434435,51.523776],"type":"Point"}
}