{
  "type": "Feature",
  "properties": {
    "date:inception_lower": "2011-05-01",
    "date:inception_upper": "2011-05-01",
    "iso:country": "GB",
    "wof:name": "DN22 7HN",
    "wof:placetype": "postalcode"
  },
  "geometry": {"coordinates":[-0.946078,53.312296],"type":"Point"}
}
