{
  "type": "Feature",
  "properties": {
    "iso:country":"GB",
    "wof:name":"KA3 7QJ",
    "wof:placetype":"postalcode"
},
  "geometry": {"coordinates":[-4.47702158142622,55.62063626483923],"type":"Point"}
}