{
  "type": "Feature",
  "properties": {
    "iso:country": "GB",
    "wof:name": "KA3 7QJ",
    "wof:placetype": "postalcode"
  },
  "geometry": {"coordinates":[-4.477022,55.620636],"type":"Point"}
}
