{
  "type": "Feature",
  "properties": {
    "date:inception_lower": "1980-01-01",
    "date:inception_upper": "1980-01-01",
    "iso:country": "GB",
    "wof:name": "KA3 7QJ",
    "wof:placetype": "postalcode"
  },
  "geometry": {"coordinates":[-4.477022,55.620636],"type":"Point"}
}
