{
  "type": "Feature",
  "properties": {
    "iso:country":"GB",
    "wof:name":"B31 3AU",
    "wof:placetype":"postalcode"
},
  "geometry": {"coordinates":[-1.94944493834826,52.40916420050932],"type":"Point"}
}