{
  "type": "Feature",
  "properties": {
    "iso:country": "GB",
    "wof:name": "S42 6ER",
    "wof:placetype": "postalcode"
  },
  "geometry": {"coordinates":[-1.414419,53.183493],"type":"Point"}
}
