{
  "type": "Feature",
  "properties": {
    "iso:country":"GB",
    "wof:name":"S42 6ER",
    "wof:placetype":"postalcode"
},
  "geometry": {"coordinates":[-1.4143893332199,53.18350161779403],"type":"Point"}
}