{
  "type": "Feature",
  "properties": {
    "iso:country":"GB",
    "wof:name":"YO23 1PF",
    "wof:placetype":"postalcode"
},
  "geometry": {"coordinates":[-1.09049689198884,53.95039403715567],"type":"Point"}
}