{
  "type": "Feature",
  "properties": {
    "date:inception_lower": "2000-06-01",
    "date:inception_upper": "2000-06-01",
    "iso:country": "GB",
    "wof:name": "CA8 7HA",
    "wof:placetype": "postalcode"
  },
  "geometry": {"coordinates":[-2.539539,54.981759],"type":"Point"}
}
