{
  "type": "Feature",
  "properties": {
    "iso:country":"GB",
    "wof:name":"CA8 7HA",
    "wof:placetype":"postalcode"
},
  "geometry": {"coordinates":[-2.53953947287328,54.98175946014398],"type":"Point"}
}