{
  "type": "Feature",
  "properties": {
    "iso:country":"GB",
    "wof:name":"IG3 9QT",
    "wof:placetype":"postalcode"
},
  "geometry": {"coordinates":[0.11470113774733,51.56149638813827],"type":"Point"}
}