{
  "type": "Feature",
  "properties": {
    "date:inception_lower": "1996-06-01",
    "date:inception_upper": "1996-06-01",
    "iso:country": "GB",
    "wof:name": "AB11 6FG",
    "wof:placetype": "postalcode"
  },
  "geometry": {"coordinates":[-2.104367,57.142961],"type":"Point"}
}
