{
  "type": "Feature",
  "properties": {
    "iso:country": "GB",
    "wof:name": "HA6 2PX",
    "wof:placetype": "postalcode"
  },
  "geometry": {"coordinates":[-0.425944,51.612104],"type":"Point"}
}
