{
  "type": "Feature",
  "properties": {
    "iso:country":"GB",
    "wof:name":"HA6 2PX",
    "wof:placetype":"postalcode"
},
  "geometry": {"coordinates":[-0.4259444409626,51.61210443077069],"type":"Point"}
}