{
  "type": "Feature",
  "properties": {
    "iso:country":"GB",
    "wof:name":"PO38 2QF",
    "wof:placetype":"postalcode"
},
  "geometry": {"coordinates":[-1.26885551974834,50.6013530323577],"type":"Point"}
}