{
  "type": "Feature",
  "properties": {
    "iso:country": "GB",
    "wof:name": "PO38 2QF",
    "wof:placetype": "postalcode"
  },
  "geometry": {"coordinates":[-1.268855,50.601353],"type":"Point"}
}
