{
  "type": "Feature",
  "properties": {
    "date:inception_lower":"2011-10-01",
    "date:inception_upper":"2011-10-31",
    "iso:country":"GB",
    "wof:name":"CM6 1FT",
    "wof:placetype":"postalcode"
},
  "geometry": {"coordinates":[0.28644,51.871179],"type":"Point"}
}