{
  "type": "Feature",
  "properties": {
    "iso:country":"GB",
    "wof:name":"ST17 0LZ",
    "wof:placetype":"postalcode"
},
  "geometry": {"coordinates":[-2.06695871583327,52.78401168618119],"type":"Point"}
}