{
  "type": "Feature",
  "properties": {
    "iso:country": "GB",
    "wof:name": "ST17 0LZ",
    "wof:placetype": "postalcode"
  },
  "geometry": {"coordinates":[-2.066959,52.784012],"type":"Point"}
}
