{
  "type": "Feature",
  "properties": {
    "iso:country":"GB",
    "wof:name":"NR10 4HD",
    "wof:placetype":"postalcode"
},
  "geometry": {"coordinates":[1.17860535447584,52.76009588139947],"type":"Point"}
}