{
  "type": "Feature",
  "properties": {
    "iso:country":"GB",
    "wof:name":"LE5 5HL",
    "wof:placetype":"postalcode"
},
  "geometry": {"coordinates":[-1.10976117929413,52.62706469643033],"type":"Point"}
}