{
  "type": "Feature",
  "properties": {
    "date:inception_lower": "1980-01-01",
    "date:inception_upper": "1980-01-01",
    "iso:country": "GB",
    "wof:name": "LE5 5HL",
    "wof:placetype": "postalcode"
  },
  "geometry": {"coordinates":[-1.109708,52.627119],"type":"Point"}
}
