{
  "type": "Feature",
  "properties": {
    "date:inception_lower":"2008-09-01",
    "date:inception_upper":"2008-09-30",
    "iso:country":"GB",
    "wof:name":"NN15 6RW",
    "wof:placetype":"postalcode"
},
  "geometry": {"coordinates":[-0.685607,52.384142],"type":"Point"}
}