{
  "type": "Feature",
  "properties": {
    "iso:country": "GB",
    "wof:name": "NN15 6RW",
    "wof:placetype": "postalcode"
  },
  "geometry": {"coordinates":[-0.685607,52.384142],"type":"Point"}
}
