{
  "type": "Feature",
  "properties": {
    "iso:country":"GB",
    "wof:name":"NN15 6RW",
    "wof:placetype":"postalcode"
},
  "geometry": {"coordinates":[-0.68560738416938,52.38414157315771],"type":"Point"}
}