{
  "type": "Feature",
  "properties": {
    "iso:country":"GB",
    "wof:name":"BA14 0LF",
    "wof:placetype":"postalcode"
},
  "geometry": {"coordinates":[-2.225318824875,51.30660880091334],"type":"Point"}
}