{
  "type": "Feature",
  "properties": {
    "iso:country": "GB",
    "wof:name": "BA14 0LF",
    "wof:placetype": "postalcode"
  },
  "geometry": {"coordinates":[-2.225319,51.306609],"type":"Point"}
}
