{
  "type": "Feature",
  "properties": {
    "iso:country":"GB",
    "wof:name":"DY1 4LG",
    "wof:placetype":"postalcode"
},
  "geometry": {"coordinates":[-2.09270976151049,52.5319324151466],"type":"Point"}
}