{
  "type": "Feature",
  "properties": {
    "date:inception_lower": "2017-05-01",
    "date:inception_upper": "2017-05-01",
    "iso:country": "GB",
    "wof:name": "WF10 1FF",
    "wof:placetype": "postalcode"
  },
  "geometry": {"coordinates":[-1.360694,53.727685],"type":"Point"}
}
