{
  "type": "Feature",
  "properties": {
    "iso:country": "GB",
    "wof:name": "CV12 0DT",
    "wof:placetype": "postalcode"
  },
  "geometry": {"coordinates":[-1.493578,52.481325],"type":"Point"}
}
