{
  "type": "Feature",
  "properties": {
    "iso:country":"GB",
    "wof:name":"CV12 0DT",
    "wof:placetype":"postalcode"
},
  "geometry": {"coordinates":[-1.4935775665238,52.48132485176713],"type":"Point"}
}