{
  "type": "Feature",
  "properties": {
    "iso:country": "GB",
    "wof:name": "KT16 0HW",
    "wof:placetype": "postalcode"
  },
  "geometry": {"coordinates":[-0.528809,51.365408],"type":"Point"}
}
