{
  "type": "Feature",
  "properties": {
    "iso:country":"GB",
    "wof:name":"KT16 0HW",
    "wof:placetype":"postalcode"
},
  "geometry": {"coordinates":[-0.5288092585369,51.36540823883065],"type":"Point"}
}