{
  "type": "Feature",
  "properties": {
    "iso:country": "GB",
    "wof:name": "PO13 8GS",
    "wof:placetype": "postalcode"
  },
  "geometry": {"coordinates":[-1.168776,50.798948],"type":"Point"}
}
