{
  "type": "Feature",
  "properties": {
    "iso:country":"GB",
    "wof:name":"PO13 8GS",
    "wof:placetype":"postalcode"
},
  "geometry": {"coordinates":[-1.16877619180485,50.79894836576752],"type":"Point"}
}