{
  "type": "Feature",
  "properties": {
    "date:inception_lower": "1980-01-01",
    "date:inception_upper": "1980-01-01",
    "iso:country": "GB",
    "wof:name": "OX1 4EH",
    "wof:placetype": "postalcode"
  },
  "geometry": {"coordinates":[-1.255546,51.751781],"type":"Point"}
}
