{
  "type": "Feature",
  "properties": {
    "iso:country":"GB",
    "wof:name":"OX1 4EH",
    "wof:placetype":"postalcode"
},
  "geometry": {"coordinates":[-1.25586780620936,51.75182227528153],"type":"Point"}
}