{
  "type": "Feature",
  "properties": {
    "iso:country":"GB",
    "wof:name":"PO20 8ND",
    "wof:placetype":"postalcode"
},
  "geometry": {"coordinates":[-0.89330296814293,50.78048262241793],"type":"Point"}
}