{
  "type": "Feature",
  "properties": {
    "date:inception_lower": "1980-01-01",
    "date:inception_upper": "1980-01-01",
    "iso:country": "GB",
    "wof:name": "PO20 8ND",
    "wof:placetype": "postalcode"
  },
  "geometry": {"coordinates":[-0.893303,50.780483],"type":"Point"}
}
