{
  "type": "Feature",
  "properties": {
    "iso:country":"GB",
    "wof:name":"SR5 2QE",
    "wof:placetype":"postalcode"
},
  "geometry": {"coordinates":[-1.40170399609643,54.92648141911836],"type":"Point"}
}