{
  "type": "Feature",
  "properties": {
    "iso:country":"GB",
    "wof:name":"RH5 5LQ",
    "wof:placetype":"postalcode"
},
  "geometry": {"coordinates":[-0.32113340526993,51.15453502051531],"type":"Point"}
}