{
  "type": "Feature",
  "properties": {
    "date:inception_lower":"1987-04-01",
    "date:inception_upper":"1987-04-30",
    "iso:country":"GB",
    "wof:name":"RH5 5LQ",
    "wof:placetype":"postalcode"
},
  "geometry": {"coordinates":[-0.321133,51.154535],"type":"Point"}
}