{
  "type": "Feature",
  "properties": {
    "iso:country":"GB",
    "wof:name":"W11 1AZ",
    "wof:placetype":"postalcode"
},
  "geometry": {"coordinates":[-0.20235128713076,51.52066033719291],"type":"Point"}
}