{
  "type": "Feature",
  "properties": {
    "iso:country": "GB",
    "wof:name": "CO3 3AF",
    "wof:placetype": "postalcode"
  },
  "geometry": {"coordinates":[0.892261,51.890495],"type":"Point"}
}
