{
  "type": "Feature",
  "properties": {
    "iso:country":"GB",
    "wof:name":"SO14 0YR",
    "wof:placetype":"postalcode"
},
  "geometry": {"coordinates":[-1.40047280271039,50.9115346387637],"type":"Point"}
}