{
  "type": "Feature",
  "properties": {
    "iso:country":"GB",
    "wof:name":"B11 3LU",
    "wof:placetype":"postalcode"
},
  "geometry": {"coordinates":[-1.86008781173401,52.45340433162006],"type":"Point"}
}