{
  "type": "Feature",
  "properties": {
    "date:inception_lower": "1990-02-01",
    "date:inception_upper": "1990-02-01",
    "iso:country": "GB",
    "wof:name": "PL21 9EL",
    "wof:placetype": "postalcode"
  },
  "geometry": {"coordinates":[-3.975055,50.384512],"type":"Point"}
}
