{
  "type": "Feature",
  "properties": {
    "iso:country":"GB",
    "wof:name":"IG3 8PD",
    "wof:placetype":"postalcode"
},
  "geometry": {"coordinates":[0.10024075831079,51.57174706490326],"type":"Point"}
}