{
  "type": "Feature",
  "properties": {
    "iso:country": "GB",
    "wof:name": "SA31 3NF",
    "wof:placetype": "postalcode"
  },
  "geometry": {"coordinates":[-4.322783,51.848973],"type":"Point"}
}
