{
  "type": "Feature",
  "properties": {
    "iso:country": "GB",
    "wof:name": "SO30 2LR",
    "wof:placetype": "postalcode"
  },
  "geometry": {"coordinates":[-1.302814,50.927764],"type":"Point"}
}
