{
  "type": "Feature",
  "properties": {
    "date:inception_lower": "1983-03-01",
    "date:inception_upper": "1983-03-01",
    "iso:country": "GB",
    "wof:name": "CM20 2LF",
    "wof:placetype": "postalcode"
  },
  "geometry": {"coordinates":[0.123843,51.778719],"type":"Point"}
}
