{
  "type": "Feature",
  "properties": {
    "iso:country":"GB",
    "wof:name":"SY1 4BU",
    "wof:placetype":"postalcode"
},
  "geometry": {"coordinates":[-2.74068131524735,52.72380546607413],"type":"Point"}
}