{
  "type": "Feature",
  "properties": {
    "iso:country": "GB",
    "wof:name": "SE20 8FQ",
    "wof:placetype": "postalcode"
  },
  "geometry": {"coordinates":[-0.071694,51.411914],"type":"Point"}
}
