{
  "type": "Feature",
  "properties": {
    "iso:country": "GB",
    "wof:name": "CF72 9TL",
    "wof:placetype": "postalcode"
  },
  "geometry": {"coordinates":[-3.450571,51.541744],"type":"Point"}
}
