{
  "type": "Feature",
  "properties": {
    "iso:country":"GB",
    "wof:name":"N1 6RX",
    "wof:placetype":"postalcode"
},
  "geometry": {"coordinates":[-0.07761527274291,51.53146974201415],"type":"Point"}
}