{
  "type": "Feature",
  "properties": {
    "iso:country":"GB",
    "wof:name":"LS12 4UJ",
    "wof:placetype":"postalcode"
},
  "geometry": {"coordinates":[-1.59982871016748,53.78388178514087],"type":"Point"}
}