{
  "type": "Feature",
  "properties": {
    "date:inception_lower":"1980-01-01",
    "date:inception_upper":"1980-01-31",
    "iso:country":"GB",
    "wof:name":"LS12 4UJ",
    "wof:placetype":"postalcode"
},
  "geometry": {"coordinates":[-1.599829,53.783882],"type":"Point"}
}