{
  "type": "Feature",
  "properties": {
    "iso:country":"GB",
    "wof:name":"S71 4FX",
    "wof:placetype":"postalcode"
},
  "geometry": {"coordinates":[-1.45379577790656,53.60138394602727],"type":"Point"}
}