{
  "type": "Feature",
  "properties": {
    "iso:country":"GB",
    "wof:name":"SP11 6DX",
    "wof:placetype":"postalcode"
},
  "geometry": {"coordinates":[-1.40226840694903,51.25373345587522],"type":"Point"}
}