{
  "type": "Feature",
  "properties": {
    "date:inception_lower": "2007-04-01",
    "date:inception_upper": "2007-04-01",
    "iso:country": "GB",
    "wof:name": "SP11 6DX",
    "wof:placetype": "postalcode"
  },
  "geometry": {"coordinates":[-1.402254,51.25373],"type":"Point"}
}
