{
  "type": "Feature",
  "properties": {
    "date:inception_lower": "1980-01-01",
    "date:inception_upper": "1980-01-01",
    "iso:country": "GB",
    "wof:name": "CT17 9AY",
    "wof:placetype": "postalcode"
  },
  "geometry": {"coordinates":[1.310752,51.124465],"type":"Point"}
}
