{
  "type": "Feature",
  "properties": {
    "iso:country": "GB",
    "wof:name": "NE28 0QY",
    "wof:placetype": "postalcode"
  },
  "geometry": {"coordinates":[-1.499866,55.007146],"type":"Point"}
}
