{
  "type": "Feature",
  "properties": {
    "iso:country":"GB",
    "wof:name":"NE28 0QY",
    "wof:placetype":"postalcode"
},
  "geometry": {"coordinates":[-1.49986646480709,55.00714559108117],"type":"Point"}
}