{
  "type": "Feature",
  "properties": {
    "iso:country":"GB",
    "wof:name":"LN8 5JL",
    "wof:placetype":"postalcode"
},
  "geometry": {"coordinates":[-0.33625975936168,53.23625411356743],"type":"Point"}
}