{
  "type": "Feature",
  "properties": {
    "iso:country": "GB",
    "wof:name": "LN8 5JL",
    "wof:placetype": "postalcode"
  },
  "geometry": {"coordinates":[-0.33626,53.236254],"type":"Point"}
}
