{
  "type": "Feature",
  "properties": {
    "date:inception_lower": "1996-12-01",
    "date:inception_upper": "1996-12-01",
    "iso:country": "GB",
    "wof:name": "LN8 5JL",
    "wof:placetype": "postalcode"
  },
  "geometry": {"coordinates":[-0.33626,53.236254],"type":"Point"}
}
