{
  "type": "Feature",
  "properties": {
    "iso:country":"GB",
    "wof:name":"ST4 7HP",
    "wof:placetype":"postalcode"
},
  "geometry": {"coordinates":[-2.19336720171668,53.00360817678554],"type":"Point"}
}