{
  "type": "Feature",
  "properties": {
    "date:inception_lower": "1980-01-01",
    "date:inception_upper": "1980-01-01",
    "iso:country": "GB",
    "wof:name": "CM3 6PT",
    "wof:placetype": "postalcode"
  },
  "geometry": {"coordinates":[0.650859,51.686847],"type":"Point"}
}
