{
  "type": "Feature",
  "properties": {
    "iso:country":"GB",
    "wof:name":"NP12 1HF",
    "wof:placetype":"postalcode"
},
  "geometry": {"coordinates":[-3.19526895429815,51.67505713428611],"type":"Point"}
}