{
  "type": "Feature",
  "properties": {
    "iso:country": "GB",
    "wof:name": "NP12 1HF",
    "wof:placetype": "postalcode"
  },
  "geometry": {"coordinates":[-3.195269,51.675057],"type":"Point"}
}
