{
  "type": "Feature",
  "properties": {
    "iso:country": "GB",
    "wof:name": "HU1 1ZA",
    "wof:placetype": "postalcode"
  },
  "geometry": {"coordinates":[-0.334923,53.738921],"type":"Point"}
}
