{
  "type": "Feature",
  "properties": {
    "date:inception_lower": "1980-01-01",
    "date:inception_upper": "1980-01-01",
    "iso:country": "GB",
    "wof:name": "TR2 5TY",
    "wof:placetype": "postalcode"
  },
  "geometry": {"coordinates":[-4.923736,50.264956],"type":"Point"}
}
