{
  "type": "Feature",
  "properties": {
    "iso:country":"GB",
    "wof:name":"TR2 5TY",
    "wof:placetype":"postalcode"
},
  "geometry": {"coordinates":[-4.92004221954916,50.26657147703922],"type":"Point"}
}