{
  "type": "Feature",
  "properties": {
    "iso:country":"GB",
    "wof:name":"NE27 0FE",
    "wof:placetype":"postalcode"
},
  "geometry": {"coordinates":[-1.51212945787848,55.0299305305961],"type":"Point"}
}