{
  "type": "Feature",
  "properties": {
    "iso:country": "GB",
    "wof:name": "BB7 3DB",
    "wof:placetype": "postalcode"
  },
  "geometry": {"coordinates":[-2.462624,53.885732],"type":"Point"}
}
