{
  "type": "Feature",
  "properties": {
    "date:inception_lower": "1980-01-01",
    "date:inception_upper": "1980-01-01",
    "iso:country": "GB",
    "wof:name": "DD11 2RJ",
    "wof:placetype": "postalcode"
  },
  "geometry": {"coordinates":[-2.744232,56.578945],"type":"Point"}
}
