{
  "type": "Feature",
  "properties": {
    "iso:country": "GB",
    "wof:name": "GU22 9DU",
    "wof:placetype": "postalcode"
  },
  "geometry": {"coordinates":[-0.546378,51.305469],"type":"Point"}
}
