{
  "type": "Feature",
  "properties": {
    "date:inception_lower":"2013-10-01",
    "date:inception_upper":"2013-10-31",
    "iso:country":"GB",
    "wof:name":"GU22 9DU",
    "wof:placetype":"postalcode"
},
  "geometry": {"coordinates":[-0.546378,51.305469],"type":"Point"}
}