{
  "type": "Feature",
  "properties": {
    "iso:country": "GB",
    "wof:name": "WS13 6LR",
    "wof:placetype": "postalcode"
  },
  "geometry": {"coordinates":[-1.842519,52.675854],"type":"Point"}
}
