{
  "type": "Feature",
  "properties": {
    "iso:country":"GB",
    "wof:name":"WS13 6LR",
    "wof:placetype":"postalcode"
},
  "geometry": {"coordinates":[-1.84251909002309,52.67585378777678],"type":"Point"}
}