{
  "type": "Feature",
  "properties": {
    "iso:country":"GB",
    "wof:name":"KT10 9LF",
    "wof:placetype":"postalcode"
},
  "geometry": {"coordinates":[-0.36745577554888,51.36717378481585],"type":"Point"}
}