{
  "type": "Feature",
  "properties": {
    "date:inception_lower": "1980-01-01",
    "date:inception_upper": "1980-01-01",
    "iso:country": "GB",
    "wof:name": "KT10 9LF",
    "wof:placetype": "postalcode"
  },
  "geometry": {"coordinates":[-0.367456,51.367174],"type":"Point"}
}
