{
  "type": "Feature",
  "properties": {
    "iso:country": "GB",
    "wof:name": "KT10 9LF",
    "wof:placetype": "postalcode"
  },
  "geometry": {"coordinates":[-0.367456,51.367174],"type":"Point"}
}
