{
  "type": "Feature",
  "properties": {
    "date:inception_lower": "2002-06-01",
    "date:inception_upper": "2002-06-01",
    "iso:country": "GB",
    "wof:name": "GL1 1DT",
    "wof:placetype": "postalcode"
  },
  "geometry": {"coordinates":[-2.238909,51.862886],"type":"Point"}
}
