{
  "type": "Feature",
  "properties": {
    "date:inception_lower": "1994-05-01",
    "date:inception_upper": "1994-05-01",
    "iso:country": "GB",
    "wof:name": "M27 0LN",
    "wof:placetype": "postalcode"
  },
  "geometry": {"coordinates":[-2.349814,53.508008],"type":"Point"}
}
