{
  "type": "Feature",
  "properties": {
    "iso:country":"GB",
    "wof:name":"M27 0LN",
    "wof:placetype":"postalcode"
},
  "geometry": {"coordinates":[-2.34981587059823,53.50799096000991],"type":"Point"}
}