{
  "type": "Feature",
  "properties": {
    "date:inception_lower": "2006-07-01",
    "date:inception_upper": "2006-07-01",
    "iso:country": "GB",
    "wof:name": "SS11 8AW",
    "wof:placetype": "postalcode"
  },
  "geometry": {"coordinates":[0.524587,51.613439],"type":"Point"}
}
