{
  "type": "Feature",
  "properties": {
    "iso:country":"GB",
    "wof:name":"SK7 2EP",
    "wof:placetype":"postalcode"
},
  "geometry": {"coordinates":[-2.16035041032162,53.36151431991667],"type":"Point"}
}