{
  "type": "Feature",
  "properties": {
    "iso:country":"GB",
    "wof:name":"NG16 5LG",
    "wof:placetype":"postalcode"
},
  "geometry": {"coordinates":[-1.33864358873025,53.06158113533942],"type":"Point"}
}