{
  "type": "Feature",
  "properties": {
    "iso:country":"GB",
    "wof:name":"ML9 1NH",
    "wof:placetype":"postalcode"
},
  "geometry": {"coordinates":[-3.97185744979538,55.72583708009912],"type":"Point"}
}