{
  "type": "Feature",
  "properties": {
    "iso:country":"GB",
    "wof:name":"G81 4BP",
    "wof:placetype":"postalcode"
},
  "geometry": {"coordinates":[-4.43179903707332,55.91265365118675],"type":"Point"}
}