{
  "type": "Feature",
  "properties": {
    "date:inception_lower": "1980-01-01",
    "date:inception_upper": "1980-01-01",
    "iso:country": "GB",
    "wof:name": "G81 4BP",
    "wof:placetype": "postalcode"
  },
  "geometry": {"coordinates":[-4.431723,55.912694],"type":"Point"}
}
