{
  "type": "Feature",
  "properties": {
    "iso:country":"GB",
    "wof:name":"RH10 7FN",
    "wof:placetype":"postalcode"
},
  "geometry": {"coordinates":[-0.14650185890283,51.12248173445531],"type":"Point"}
}