{
  "type": "Feature",
  "properties": {
    "iso:country":"GB",
    "wof:name":"ZE2 9XG",
    "wof:placetype":"postalcode"
},
  "geometry": {"coordinates":[-1.33743731847604,60.58580360115582],"type":"Point"}
}