{
  "type": "Feature",
  "properties": {
    "iso:country": "GB",
    "wof:name": "N10 2NY",
    "wof:placetype": "postalcode"
  },
  "geometry": {"coordinates":[-0.145444,51.606102],"type":"Point"}
}
