{
  "type": "Feature",
  "properties": {
    "date:inception_lower": "1999-06-01",
    "date:inception_upper": "1999-06-01",
    "iso:country": "GB",
    "wof:name": "CF31 5AE",
    "wof:placetype": "postalcode"
  },
  "geometry": {"coordinates":[-3.605996,51.505296],"type":"Point"}
}
