{
  "type": "Feature",
  "properties": {
    "date:inception_lower":"2019-01-01",
    "date:inception_upper":"2019-01-31",
    "iso:country":"GB",
    "wof:name":"PE22 7AD",
    "wof:placetype":"postalcode"
},
  "geometry": {"coordinates":[-0.089416,53.015244],"type":"Point"}
}