{
  "type": "Feature",
  "properties": {
    "iso:country":"GB",
    "wof:name":"ST11 9DD",
    "wof:placetype":"postalcode"
},
  "geometry": {"coordinates":[-2.0552794652509,52.97325254188326],"type":"Point"}
}