{
  "type": "Feature",
  "properties": {
    "iso:country":"GB",
    "wof:name":"KT4 8WD",
    "wof:placetype":"postalcode"
},
  "geometry": {"coordinates":[-0.24274315223191,51.38000952246113],"type":"Point"}
}