{
  "type": "Feature",
  "properties": {
    "iso:country": "GB",
    "wof:name": "TW15 3JE",
    "wof:placetype": "postalcode"
  },
  "geometry": {"coordinates":[-0.480167,51.436186],"type":"Point"}
}
