{
  "type": "Feature",
  "properties": {
    "iso:country":"GB",
    "wof:name":"SK11 9PW",
    "wof:placetype":"postalcode"
},
  "geometry": {"coordinates":[-2.206310582745,53.24542622111117],"type":"Point"}
}