{
  "type": "Feature",
  "properties": {
    "iso:country":"GB",
    "wof:name":"BB2 7FL",
    "wof:placetype":"postalcode"
},
  "geometry": {"coordinates":[-2.51859884129308,53.76180968711174],"type":"Point"}
}