{
  "type": "Feature",
  "properties": {
    "date:inception_lower":"2003-09-01",
    "date:inception_upper":"2003-09-30",
    "iso:country":"GB",
    "wof:name":"BB2 7FL",
    "wof:placetype":"postalcode"
},
  "geometry": {"coordinates":[-2.518599,53.76181],"type":"Point"}
}