{
  "type": "Feature",
  "properties": {
    "iso:country": "GB",
    "wof:name": "BB2 7FL",
    "wof:placetype": "postalcode"
  },
  "geometry": {"coordinates":[-2.518599,53.76181],"type":"Point"}
}
