{
  "type": "Feature",
  "properties": {
    "iso:country": "GB",
    "wof:name": "TS11 8BD",
    "wof:placetype": "postalcode"
  },
  "geometry": {"coordinates":[-1.041076,54.579882],"type":"Point"}
}
