{
  "type": "Feature",
  "properties": {
    "iso:country":"GB",
    "wof:name":"TS11 8BD",
    "wof:placetype":"postalcode"
},
  "geometry": {"coordinates":[-1.04107598332834,54.57988240073931],"type":"Point"}
}