{
  "type": "Feature",
  "properties": {
    "date:inception_lower": "1980-01-01",
    "date:inception_upper": "1980-01-01",
    "iso:country": "GB",
    "wof:name": "ST18 0JJ",
    "wof:placetype": "postalcode"
  },
  "geometry": {"coordinates":[-2.03734,52.840586],"type":"Point"}
}
