{
  "type": "Feature",
  "properties": {
    "iso:country": "GB",
    "wof:name": "ST18 0JJ",
    "wof:placetype": "postalcode"
  },
  "geometry": {"coordinates":[-2.03734,52.840586],"type":"Point"}
}
