{
  "type": "Feature",
  "properties": {
    "date:inception_lower": "2017-03-01",
    "date:inception_upper": "2017-03-01",
    "iso:country": "GB",
    "wof:name": "S64 8FB",
    "wof:placetype": "postalcode"
  },
  "geometry": {"coordinates":[-1.303469,53.483673],"type":"Point"}
}
