{
  "type": "Feature",
  "properties": {
    "date:inception_lower": "1980-01-01",
    "date:inception_upper": "1980-01-01",
    "iso:country": "GB",
    "wof:name": "IP27 0TL",
    "wof:placetype": "postalcode"
  },
  "geometry": {"coordinates":[0.665787,52.457466],"type":"Point"}
}
