{
  "type": "Feature",
  "properties": {
    "date:inception_lower": "2006-07-01",
    "date:inception_upper": "2006-07-01",
    "iso:country": "GB",
    "wof:name": "W12 7RP",
    "wof:placetype": "postalcode"
  },
  "geometry": {"coordinates":[-0.223599,51.51397],"type":"Point"}
}
