{
  "type": "Feature",
  "properties": {
    "iso:country":"GB",
    "wof:name":"W12 7RP",
    "wof:placetype":"postalcode"
},
  "geometry": {"coordinates":[-0.22359875013168,51.51396995815102],"type":"Point"}
}