{
  "type": "Feature",
  "properties": {
    "iso:country": "GB",
    "wof:name": "CF83 2ST",
    "wof:placetype": "postalcode"
  },
  "geometry": {"coordinates":[-3.238304,51.57938],"type":"Point"}
}
