{
  "type": "Feature",
  "properties": {
    "iso:country":"GB",
    "wof:name":"CF83 2ST",
    "wof:placetype":"postalcode"
},
  "geometry": {"coordinates":[-3.23830379436878,51.57937960463308],"type":"Point"}
}