{
  "type": "Feature",
  "properties": {
    "iso:country":"GB",
    "wof:name":"PA5 0BA",
    "wof:placetype":"postalcode"
},
  "geometry": {"coordinates":[-4.5256079444701,55.81935549707513],"type":"Point"}
}