{
  "type": "Feature",
  "properties": {
    "date:inception_lower":"2000-12-01",
    "date:inception_upper":"2000-12-31",
    "iso:country":"GB",
    "wof:name":"PA5 0BA",
    "wof:placetype":"postalcode"
},
  "geometry": {"coordinates":[-4.525608,55.819355],"type":"Point"}
}