{
  "type": "Feature",
  "properties": {
    "iso:country":"GB",
    "wof:name":"LE18 2QW",
    "wof:placetype":"postalcode"
},
  "geometry": {"coordinates":[-1.10587834099351,52.57108132176905],"type":"Point"}
}