{
  "type": "Feature",
  "properties": {
    "iso:country": "GB",
    "wof:name": "SA2 7LF",
    "wof:placetype": "postalcode"
  },
  "geometry": {"coordinates":[-4.014971,51.622252],"type":"Point"}
}
