{
  "type": "Feature",
  "properties": {
    "iso:country":"GB",
    "wof:name":"SA2 7LF",
    "wof:placetype":"postalcode"
},
  "geometry": {"coordinates":[-4.01497114775259,51.62225181187993],"type":"Point"}
}