{
  "type": "Feature",
  "properties": {
    "iso:country":"GB",
    "wof:name":"ZE1 0RS",
    "wof:placetype":"postalcode"
},
  "geometry": {"coordinates":[-1.16434338415275,60.14617468655698],"type":"Point"}
}