{
  "type": "Feature",
  "properties": {
    "date:inception_lower": "1980-01-01",
    "date:inception_upper": "1980-01-01",
    "iso:country": "GB",
    "wof:name": "ZE1 0RS",
    "wof:placetype": "postalcode"
  },
  "geometry": {"coordinates":[-1.164421,60.14622],"type":"Point"}
}
