{
  "type": "Feature",
  "properties": {
    "iso:country": "GB",
    "wof:name": "ZE1 0RS",
    "wof:placetype": "postalcode"
  },
  "geometry": {"coordinates":[-1.164343,60.146175],"type":"Point"}
}
