{
  "type": "Feature",
  "properties": {
    "iso:country": "GB",
    "wof:name": "WA12 9DT",
    "wof:placetype": "postalcode"
  },
  "geometry": {"coordinates":[-2.645491,53.450039],"type":"Point"}
}
