{
  "type": "Feature",
  "properties": {
    "date:inception_lower": "1985-10-01",
    "date:inception_upper": "1985-10-01",
    "iso:country": "GB",
    "wof:name": "HU6 7XP",
    "wof:placetype": "postalcode"
  },
  "geometry": {"coordinates":[-0.363775,53.788516],"type":"Point"}
}
