{
  "type": "Feature",
  "properties": {
    "iso:country": "GB",
    "wof:name": "IP30 0NS",
    "wof:placetype": "postalcode"
  },
  "geometry": {"coordinates":[0.838426,52.156542],"type":"Point"}
}
