{
  "type": "Feature",
  "properties": {
    "iso:country":"GB",
    "wof:name":"W11 3PE",
    "wof:placetype":"postalcode"
},
  "geometry": {"coordinates":[-0.20002346928914,51.50914129706137],"type":"Point"}
}