{
  "type": "Feature",
  "properties": {
    "date:inception_lower": "1980-01-01",
    "date:inception_upper": "1980-01-01",
    "iso:country": "GB",
    "wof:name": "W11 3PE",
    "wof:placetype": "postalcode"
  },
  "geometry": {"coordinates":[-0.200026,51.509188],"type":"Point"}
}
