{
  "type": "Feature",
  "properties": {
    "date:inception_lower":"1980-01-01",
    "date:inception_upper":"1980-01-31",
    "iso:country":"GB",
    "wof:name":"PO20 7AT",
    "wof:placetype":"postalcode"
},
  "geometry": {"coordinates":[-0.829635,50.7954],"type":"Point"}
}