{
  "type": "Feature",
  "properties": {
    "iso:country": "GB",
    "wof:name": "HD9 6PY",
    "wof:placetype": "postalcode"
  },
  "geometry": {"coordinates":[-1.790871,53.603795],"type":"Point"}
}
