{
  "type": "Feature",
  "properties": {
    "date:inception_lower":"2009-05-01",
    "date:inception_upper":"2009-05-31",
    "iso:country":"GB",
    "wof:name":"HD9 6PY",
    "wof:placetype":"postalcode"
},
  "geometry": {"coordinates":[-1.790871,53.603795],"type":"Point"}
}