{
  "type": "Feature",
  "properties": {
    "iso:country":"GB",
    "wof:name":"HD9 6PY",
    "wof:placetype":"postalcode"
},
  "geometry": {"coordinates":[-1.79087151960992,53.60379519499657],"type":"Point"}
}