{
  "type": "Feature",
  "properties": {
    "iso:country": "GB",
    "wof:name": "BL9 8QL",
    "wof:placetype": "postalcode"
  },
  "geometry": {"coordinates":[-2.27189,53.559338],"type":"Point"}
}
