{
  "type": "Feature",
  "properties": {
    "iso:country":"GB",
    "wof:name":"BL9 8QL",
    "wof:placetype":"postalcode"
},
  "geometry": {"coordinates":[-2.27188998604622,53.55933765491402],"type":"Point"}
}