{
  "type": "Feature",
  "properties": {
    "date:inception_lower": "1980-01-01",
    "date:inception_upper": "1980-01-01",
    "iso:country": "GB",
    "wof:name": "BL9 8QL",
    "wof:placetype": "postalcode"
  },
  "geometry": {"coordinates":[-2.27189,53.559338],"type":"Point"}
}
