{
  "type": "Feature",
  "properties": {
    "iso:country":"GB",
    "wof:name":"TN6 3LX",
    "wof:placetype":"postalcode"
},
  "geometry": {"coordinates":[0.21959578278105,51.04718712012443],"type":"Point"}
}