{
  "type": "Feature",
  "properties": {
    "date:inception_lower":"1980-01-01",
    "date:inception_upper":"1980-01-31",
    "iso:country":"GB",
    "wof:name":"TN6 3LX",
    "wof:placetype":"postalcode"
},
  "geometry": {"coordinates":[0.219581,51.047176],"type":"Point"}
}