{
  "type": "Feature",
  "properties": {
    "date:inception_lower": "2002-08-01",
    "date:inception_upper": "2002-08-01",
    "iso:country": "GB",
    "wof:name": "NP44 3YS",
    "wof:placetype": "postalcode"
  },
  "geometry": {"coordinates":[-3.021399,51.642683],"type":"Point"}
}
