{
  "type": "Feature",
  "properties": {
    "iso:country":"GB",
    "wof:name":"LS10 4AP",
    "wof:placetype":"postalcode"
},
  "geometry": {"coordinates":[-1.51818980416536,53.75363339864042],"type":"Point"}
}