{
  "type": "Feature",
  "properties": {
    "date:inception_lower": "2020-10-01",
    "date:inception_upper": "2020-10-01",
    "iso:country": "GB",
    "wof:name": "TA11 6FJ",
    "wof:placetype": "postalcode"
  },
  "geometry": {"coordinates":[-2.649192,51.072376],"type":"Point"}
}
