{
  "type": "Feature",
  "properties": {
    "date:inception_lower":"1980-01-01",
    "date:inception_upper":"1980-01-31",
    "iso:country":"GB",
    "wof:name":"HR9 7DW",
    "wof:placetype":"postalcode"
},
  "geometry": {"coordinates":[-2.57825,51.914466],"type":"Point"}
}