{
  "type": "Feature",
  "properties": {
    "iso:country":"GB",
    "wof:name":"HR9 7DW",
    "wof:placetype":"postalcode"
},
  "geometry": {"coordinates":[-2.57824994426533,51.91446556882832],"type":"Point"}
}