{
  "type": "Feature",
  "properties": {
    "date:inception_lower":"2008-12-01",
    "date:inception_upper":"2008-12-31",
    "iso:country":"GB",
    "wof:name":"BD3 9TN",
    "wof:placetype":"postalcode"
},
  "geometry": {"coordinates":[-1.728268,53.791207],"type":"Point"}
}