{
  "type": "Feature",
  "properties": {
    "iso:country":"GB",
    "wof:name":"WA6 0EF",
    "wof:placetype":"postalcode"
},
  "geometry": {"coordinates":[-2.77330738195266,53.26198131068409],"type":"Point"}
}