{
  "type": "Feature",
  "properties": {
    "date:inception_lower": "2021-08-01",
    "date:inception_upper": "2021-08-01",
    "iso:country": "GB",
    "wof:name": "TA19 9GB",
    "wof:placetype": "postalcode"
  },
  "geometry": {"coordinates":[-2.926944,50.929023],"type":"Point"}
}
