{
  "type": "Feature",
  "properties": {
    "iso:country": "GB",
    "wof:name": "BA16 0JG",
    "wof:placetype": "postalcode"
  },
  "geometry": {"coordinates":[-2.743323,51.123374],"type":"Point"}
}
