{
  "type": "Feature",
  "properties": {
    "date:inception_lower":"1980-01-01",
    "date:inception_upper":"1980-01-31",
    "iso:country":"GB",
    "wof:name":"BA16 0JG",
    "wof:placetype":"postalcode"
},
  "geometry": {"coordinates":[-2.743323,51.123374],"type":"Point"}
}