{
  "type": "Feature",
  "properties": {
    "iso:country":"GB",
    "wof:name":"YO62 6ES",
    "wof:placetype":"postalcode"
},
  "geometry": {"coordinates":[-0.94069860861802,54.27190661180124],"type":"Point"}
}