{
  "type": "Feature",
  "properties": {
    "iso:country": "GB",
    "wof:name": "YO62 6ES",
    "wof:placetype": "postalcode"
  },
  "geometry": {"coordinates":[-0.940699,54.271907],"type":"Point"}
}
