{
  "type": "Feature",
  "properties": {
    "iso:country":"GB",
    "wof:name":"CR7 8QB",
    "wof:placetype":"postalcode"
},
  "geometry": {"coordinates":[-0.09395104671906,51.40086664527418],"type":"Point"}
}