{
  "type": "Feature",
  "properties": {
    "iso:country":"GB",
    "wof:name":"SW11 2SN",
    "wof:placetype":"postalcode"
},
  "geometry": {"coordinates":[-0.17488658283952,51.46958149855648],"type":"Point"}
}