{
  "type": "Feature",
  "properties": {
    "date:inception_lower": "2003-06-01",
    "date:inception_upper": "2003-06-01",
    "iso:country": "GB",
    "wof:name": "S74 8DJ",
    "wof:placetype": "postalcode"
  },
  "geometry": {"coordinates":[-1.428432,53.501026],"type":"Point"}
}
