{
  "type": "Feature",
  "properties": {
    "date:inception_lower": "2023-01-01",
    "date:inception_upper": "2023-01-01",
    "iso:country": "GB",
    "wof:name": "PE12 7FT",
    "wof:placetype": "postalcode"
  },
  "geometry": {"coordinates":[0.027498,52.803144],"type":"Point"}
}
