{
  "type": "Feature",
  "properties": {
    "date:inception_lower": "1997-12-01",
    "date:inception_upper": "1997-12-01",
    "iso:country": "GB",
    "wof:name": "BS31 3EQ",
    "wof:placetype": "postalcode"
  },
  "geometry": {"coordinates":[-2.452732,51.401937],"type":"Point"}
}
