{
  "type": "Feature",
  "properties": {
    "iso:country":"GB",
    "wof:name":"BS31 3EQ",
    "wof:placetype":"postalcode"
},
  "geometry": {"coordinates":[-2.45273164474625,51.40193691622832],"type":"Point"}
}