{
  "type": "Feature",
  "properties": {
    "iso:country":"GB",
    "wof:name":"SK6 2HL",
    "wof:placetype":"postalcode"
},
  "geometry": {"coordinates":[-2.12340262295197,53.41915712169838],"type":"Point"}
}