{
  "type": "Feature",
  "properties": {
    "date:inception_lower": "1980-01-01",
    "date:inception_upper": "1980-01-01",
    "iso:country": "GB",
    "wof:name": "SA5 7AJ",
    "wof:placetype": "postalcode"
  },
  "geometry": {"coordinates":[-3.957945,51.648657],"type":"Point"}
}
