{
  "type": "Feature",
  "properties": {
    "iso:country":"GB",
    "wof:name":"SA5 7AJ",
    "wof:placetype":"postalcode"
},
  "geometry": {"coordinates":[-3.95794547208053,51.64865672820324],"type":"Point"}
}