{
  "type": "Feature",
  "properties": {
    "iso:country":"GB",
    "wof:name":"OL8 1LB",
    "wof:placetype":"postalcode"
},
  "geometry": {"coordinates":[-2.11074606255728,53.53368235768998],"type":"Point"}
}