{
  "type": "Feature",
  "properties": {
    "iso:country": "GB",
    "wof:name": "DL15 8LA",
    "wof:placetype": "postalcode"
  },
  "geometry": {"coordinates":[-1.749299,54.708748],"type":"Point"}
}
