{
  "type": "Feature",
  "properties": {
    "iso:country":"GB",
    "wof:name":"S17 3EX",
    "wof:placetype":"postalcode"
},
  "geometry": {"coordinates":[-1.54732783768075,53.33289101456383],"type":"Point"}
}