{
  "type": "Feature",
  "properties": {
    "iso:country": "GB",
    "wof:name": "S17 3EX",
    "wof:placetype": "postalcode"
  },
  "geometry": {"coordinates":[-1.547328,53.332891],"type":"Point"}
}
