{
  "type": "Feature",
  "properties": {
    "iso:country":"GB",
    "wof:name":"LS18 4QS",
    "wof:placetype":"postalcode"
},
  "geometry": {"coordinates":[-1.63980117413163,53.83389178487032],"type":"Point"}
}