{
  "type": "Feature",
  "properties": {
    "iso:country": "GB",
    "wof:name": "RG9 9JQ",
    "wof:placetype": "postalcode"
  },
  "geometry": {"coordinates":[-0.904,51.535934],"type":"Point"}
}
