{
  "type": "Feature",
  "properties": {
    "iso:country": "GB",
    "wof:name": "ME10 1YH",
    "wof:placetype": "postalcode"
  },
  "geometry": {"coordinates":[0.706959,51.344472],"type":"Point"}
}
