{
  "type": "Feature",
  "properties": {
    "date:inception_lower": "1980-01-01",
    "date:inception_upper": "1980-01-01",
    "iso:country": "GB",
    "wof:name": "WV15 5PU",
    "wof:placetype": "postalcode"
  },
  "geometry": {"coordinates":[-2.331414,52.555153],"type":"Point"}
}
