{
  "type": "Feature",
  "properties": {
    "iso:country":"GB",
    "wof:name":"WV15 5PU",
    "wof:placetype":"postalcode"
},
  "geometry": {"coordinates":[-2.33140173954126,52.55511176617578],"type":"Point"}
}