{
  "type": "Feature",
  "properties": {
    "iso:country": "GB",
    "wof:name": "WV15 5PU",
    "wof:placetype": "postalcode"
  },
  "geometry": {"coordinates":[-2.331402,52.555112],"type":"Point"}
}
