{
  "type": "Feature",
  "properties": {
    "iso:country": "GB",
    "wof:name": "EN11 8JQ",
    "wof:placetype": "postalcode"
  },
  "geometry": {"coordinates":[-0.010482,51.764955],"type":"Point"}
}
