{
  "type": "Feature",
  "properties": {
    "iso:country":"GB",
    "wof:name":"EN11 8JQ",
    "wof:placetype":"postalcode"
},
  "geometry": {"coordinates":[-0.01048199407681,51.76495507766835],"type":"Point"}
}