{
  "type": "Feature",
  "properties": {
    "iso:country":"GB",
    "wof:name":"PE19 2HA",
    "wof:placetype":"postalcode"
},
  "geometry": {"coordinates":[-0.26974198306262,52.21281568752835],"type":"Point"}
}