{
  "type": "Feature",
  "properties": {
    "iso:country":"GB",
    "wof:name":"MK18 1AF",
    "wof:placetype":"postalcode"
},
  "geometry": {"coordinates":[-0.98589703572853,51.99788939155304],"type":"Point"}
}