{
  "type": "Feature",
  "properties": {
    "iso:country":"GB",
    "wof:name":"HX7 5DP",
    "wof:placetype":"postalcode"
},
  "geometry": {"coordinates":[-1.98388029207095,53.73137446956647],"type":"Point"}
}