{
  "type": "Feature",
  "properties": {
    "iso:country": "GB",
    "wof:name": "HX7 5DP",
    "wof:placetype": "postalcode"
  },
  "geometry": {"coordinates":[-1.98388,53.731374],"type":"Point"}
}
