{
  "type": "Feature",
  "properties": {
    "iso:country":"GB",
    "wof:name":"GL15 5PD",
    "wof:placetype":"postalcode"
},
  "geometry": {"coordinates":[-2.52633551683376,51.73177726926237],"type":"Point"}
}