{
  "type": "Feature",
  "properties": {
    "iso:country":"GB",
    "wof:name":"EX1 2DA",
    "wof:placetype":"postalcode"
},
  "geometry": {"coordinates":[-3.5217375733563,50.72543755337634],"type":"Point"}
}