{
  "type": "Feature",
  "properties": {
    "iso:country":"GB",
    "wof:name":"NW10 0JU",
    "wof:placetype":"postalcode"
},
  "geometry": {"coordinates":[-0.26126822241344,51.55115123438156],"type":"Point"}
}