{
  "type": "Feature",
  "properties": {
    "date:inception_lower":"2007-11-01",
    "date:inception_upper":"2007-11-30",
    "iso:country":"GB",
    "wof:name":"LA3 2GS",
    "wof:placetype":"postalcode"
},
  "geometry": {"coordinates":[-2.891606,54.038337],"type":"Point"}
}