{
  "type": "Feature",
  "properties": {
    "iso:country":"GB",
    "wof:name":"LA3 2GS",
    "wof:placetype":"postalcode"
},
  "geometry": {"coordinates":[-2.8916061360585,54.03833697018277],"type":"Point"}
}