{
  "type": "Feature",
  "properties": {
    "iso:country": "GB",
    "wof:name": "LA3 2GS",
    "wof:placetype": "postalcode"
  },
  "geometry": {"coordinates":[-2.891606,54.038337],"type":"Point"}
}
