{
  "type": "Feature",
  "properties": {
    "iso:country": "GB",
    "wof:name": "PO19 6YQ",
    "wof:placetype": "postalcode"
  },
  "geometry": {"coordinates":[-0.765697,50.848223],"type":"Point"}
}
