{
  "type": "Feature",
  "properties": {
    "iso:country":"GB",
    "wof:name":"PO19 6YQ",
    "wof:placetype":"postalcode"
},
  "geometry": {"coordinates":[-0.76556086068402,50.84819473372148],"type":"Point"}
}