{
  "type": "Feature",
  "properties": {
    "iso:country":"GB",
    "wof:name":"DL8 3HE",
    "wof:placetype":"postalcode"
},
  "geometry": {"coordinates":[-2.08512513976629,54.31565714314304],"type":"Point"}
}