{
  "type": "Feature",
  "properties": {
    "iso:country": "GB",
    "wof:name": "DL8 3HE",
    "wof:placetype": "postalcode"
  },
  "geometry": {"coordinates":[-2.085125,54.315657],"type":"Point"}
}
