{
  "type": "Feature",
  "properties": {
    "date:inception_lower": "2005-03-01",
    "date:inception_upper": "2005-03-01",
    "iso:country": "GB",
    "wof:name": "DL8 3HE",
    "wof:placetype": "postalcode"
  },
  "geometry": {"coordinates":[-2.085125,54.315657],"type":"Point"}
}
