{
  "type": "Feature",
  "properties": {
    "iso:country":"GB",
    "wof:name":"E14 0GS",
    "wof:placetype":"postalcode"
},
  "geometry": {"coordinates":[0.00015654941644,51.51471999339513],"type":"Point"}
}