{
  "type": "Feature",
  "properties": {
    "iso:country": "GB",
    "wof:name": "E14 0GS",
    "wof:placetype": "postalcode"
  },
  "geometry": {"coordinates":[0.000157,51.51472],"type":"Point"}
}
