{
  "type": "Feature",
  "properties": {
    "date:inception_lower": "2010-03-01",
    "date:inception_upper": "2010-03-01",
    "iso:country": "GB",
    "wof:name": "SO31 0BP",
    "wof:placetype": "postalcode"
  },
  "geometry": {"coordinates":[-1.27362,50.871526],"type":"Point"}
}
