{
  "type": "Feature",
  "properties": {
    "date:inception_lower": "1995-01-01",
    "date:inception_upper": "1995-01-01",
    "iso:country": "GB",
    "wof:name": "SA15 2PH",
    "wof:placetype": "postalcode"
  },
  "geometry": {"coordinates":[-4.168985,51.672831],"type":"Point"}
}
