{
  "type": "Feature",
  "properties": {
    "date:inception_lower":"1980-01-01",
    "date:inception_upper":"1980-01-31",
    "iso:country":"GB",
    "wof:name":"PL30 3EE",
    "wof:placetype":"postalcode"
},
  "geometry": {"coordinates":[-4.779151,50.54349],"type":"Point"}
}