{
  "type": "Feature",
  "properties": {
    "iso:country": "GB",
    "wof:name": "PL30 3EE",
    "wof:placetype": "postalcode"
  },
  "geometry": {"coordinates":[-4.779151,50.54349],"type":"Point"}
}
