{
  "type": "Feature",
  "properties": {
    "iso:country":"GB",
    "wof:name":"TN24 0HN",
    "wof:placetype":"postalcode"
},
  "geometry": {"coordinates":[0.89388710806233,51.14122573227235],"type":"Point"}
}