{
  "type": "Feature",
  "properties": {
    "iso:country":"GB",
    "wof:name":"RM13 9SN",
    "wof:placetype":"postalcode"
},
  "geometry": {"coordinates":[0.21928598565108,51.52586809925779],"type":"Point"}
}