{
  "type": "Feature",
  "properties": {
    "iso:country":"GB",
    "wof:name":"LS17 7AY",
    "wof:placetype":"postalcode"
},
  "geometry": {"coordinates":[-1.56352391722064,53.85865220695633],"type":"Point"}
}