{
  "type": "Feature",
  "properties": {
    "iso:country":"GB",
    "wof:name":"N1 7PL",
    "wof:placetype":"postalcode"
},
  "geometry": {"coordinates":[-0.08771869347901,51.53155395093614],"type":"Point"}
}