{
  "type": "Feature",
  "properties": {
    "iso:country": "GB",
    "wof:name": "DN3 1PB",
    "wof:placetype": "postalcode"
  },
  "geometry": {"coordinates":[-1.065587,53.56337],"type":"Point"}
}
