{
  "type": "Feature",
  "properties": {
    "iso:country":"GB",
    "wof:name":"DN3 1PB",
    "wof:placetype":"postalcode"
},
  "geometry": {"coordinates":[-1.0655869252246,53.56337018848439],"type":"Point"}
}