{
  "type": "Feature",
  "properties": {
    "iso:country":"GB",
    "wof:name":"TQ12 6DL",
    "wof:placetype":"postalcode"
},
  "geometry": {"coordinates":[-3.65985462589221,50.50833645354835],"type":"Point"}
}