{
  "type": "Feature",
  "properties": {
    "iso:country": "GB",
    "wof:name": "GU21 4XB",
    "wof:placetype": "postalcode"
  },
  "geometry": {"coordinates":[-0.583151,51.326314],"type":"Point"}
}
