{
  "type": "Feature",
  "properties": {
    "iso:country": "GB",
    "wof:name": "WA15 8LT",
    "wof:placetype": "postalcode"
  },
  "geometry": {"coordinates":[-2.319626,53.379225],"type":"Point"}
}
