{
  "type": "Feature",
  "properties": {
    "iso:country": "GB",
    "wof:name": "NG23 7EH",
    "wof:placetype": "postalcode"
  },
  "geometry": {"coordinates":[-0.682568,53.23466],"type":"Point"}
}
