{
  "type": "Feature",
  "properties": {
    "date:inception_lower": "1980-01-01",
    "date:inception_upper": "1980-01-01",
    "iso:country": "GB",
    "wof:name": "NG23 7EH",
    "wof:placetype": "postalcode"
  },
  "geometry": {"coordinates":[-0.682611,53.234691],"type":"Point"}
}
