{
  "type": "Feature",
  "properties": {
    "date:inception_lower": "1993-08-01",
    "date:inception_upper": "1993-08-01",
    "iso:country": "GB",
    "wof:name": "TA9 3YA",
    "wof:placetype": "postalcode"
  },
  "geometry": {"coordinates":[-2.979117,51.227372],"type":"Point"}
}
