{
  "type": "Feature",
  "properties": {
    "iso:country":"GB",
    "wof:name":"TA9 3YA",
    "wof:placetype":"postalcode"
},
  "geometry": {"coordinates":[-2.97922119171081,51.227340092957],"type":"Point"}
}