{
  "type": "Feature",
  "properties": {
    "iso:country": "GB",
    "wof:name": "TA9 3YA",
    "wof:placetype": "postalcode"
  },
  "geometry": {"coordinates":[-2.979117,51.227372],"type":"Point"}
}
