{
  "type": "Feature",
  "properties": {
    "date:inception_lower": "2001-06-01",
    "date:inception_upper": "2001-06-01",
    "iso:country": "GB",
    "wof:name": "HP18 0ED",
    "wof:placetype": "postalcode"
  },
  "geometry": {"coordinates":[-0.936915,51.811481],"type":"Point"}
}
