{
  "type": "Feature",
  "properties": {
    "iso:country": "GB",
    "wof:name": "HP18 0ED",
    "wof:placetype": "postalcode"
  },
  "geometry": {"coordinates":[-0.936915,51.811481],"type":"Point"}
}
