{
  "type": "Feature",
  "properties": {
    "iso:country":"GB",
    "wof:name":"HP18 0ED",
    "wof:placetype":"postalcode"
},
  "geometry": {"coordinates":[-0.93705294875698,51.81144871740757],"type":"Point"}
}