{
  "type": "Feature",
  "properties": {
    "iso:country":"GB",
    "wof:name":"L16 8NA",
    "wof:placetype":"postalcode"
},
  "geometry": {"coordinates":[-2.90039097769404,53.39095295893163],"type":"Point"}
}