{
  "type": "Feature",
  "properties": {
    "iso:country": "GB",
    "wof:name": "E11 2DZ",
    "wof:placetype": "postalcode"
  },
  "geometry": {"coordinates":[0.033058,51.581294],"type":"Point"}
}
