{
  "type": "Feature",
  "properties": {
    "date:inception_lower":"1980-01-01",
    "date:inception_upper":"1980-01-31",
    "iso:country":"GB",
    "wof:name":"E11 2DZ",
    "wof:placetype":"postalcode"
},
  "geometry": {"coordinates":[0.033058,51.581294],"type":"Point"}
}