{
  "type": "Feature",
  "properties": {
    "iso:country":"GB",
    "wof:name":"PA72 6JZ",
    "wof:placetype":"postalcode"
},
  "geometry": {"coordinates":[-6.08077123824524,56.48260408148455],"type":"Point"}
}