{
  "type": "Feature",
  "properties": {
    "iso:country": "GB",
    "wof:name": "HR6 9HE",
    "wof:placetype": "postalcode"
  },
  "geometry": {"coordinates":[-2.873225,52.212033],"type":"Point"}
}
