{
  "type": "Feature",
  "properties": {
    "iso:country":"GB",
    "wof:name":"HR6 9HE",
    "wof:placetype":"postalcode"
},
  "geometry": {"coordinates":[-2.87322501310715,52.2120325332481],"type":"Point"}
}