{
  "type": "Feature",
  "properties": {
    "date:inception_lower": "1980-01-01",
    "date:inception_upper": "1980-01-01",
    "iso:country": "GB",
    "wof:name": "NN2 7LL",
    "wof:placetype": "postalcode"
  },
  "geometry": {"coordinates":[-0.881039,52.259673],"type":"Point"}
}
