{
  "type": "Feature",
  "properties": {
    "iso:country":"GB",
    "wof:name":"BH5 2EG",
    "wof:placetype":"postalcode"
},
  "geometry": {"coordinates":[-1.82512412714518,50.72515096762547],"type":"Point"}
}