{
  "type": "Feature",
  "properties": {
    "iso:country":"GB",
    "wof:name":"SE15 2BH",
    "wof:placetype":"postalcode"
},
  "geometry": {"coordinates":[-0.05821109484967,51.46870537340527],"type":"Point"}
}