{
  "type": "Feature",
  "properties": {
    "date:inception_lower": "1985-04-01",
    "date:inception_upper": "1985-04-01",
    "iso:country": "GB",
    "wof:name": "OL12 6TH",
    "wof:placetype": "postalcode"
  },
  "geometry": {"coordinates":[-2.163091,53.618398],"type":"Point"}
}
