{
  "type": "Feature",
  "properties": {
    "iso:country": "GB",
    "wof:name": "L36 7UG",
    "wof:placetype": "postalcode"
  },
  "geometry": {"coordinates":[-2.843883,53.416858],"type":"Point"}
}
