{
  "type": "Feature",
  "properties": {
    "iso:country":"GB",
    "wof:name":"TN39 3JE",
    "wof:placetype":"postalcode"
},
  "geometry": {"coordinates":[0.46958255285338,50.83879688757462],"type":"Point"}
}