{
  "type": "Feature",
  "properties": {
    "date:inception_lower": "1980-01-01",
    "date:inception_upper": "1980-01-01",
    "iso:country": "GB",
    "wof:name": "TN39 3JE",
    "wof:placetype": "postalcode"
  },
  "geometry": {"coordinates":[0.469583,50.838797],"type":"Point"}
}
