{
  "type": "Feature",
  "properties": {
    "date:inception_lower": "1980-01-01",
    "date:inception_upper": "1980-01-01",
    "iso:country": "GB",
    "wof:name": "B24 9DX",
    "wof:placetype": "postalcode"
  },
  "geometry": {"coordinates":[-1.827412,52.523348],"type":"Point"}
}
