{
  "type": "Feature",
  "properties": {
    "date:inception_lower": "1998-06-01",
    "date:inception_upper": "1998-06-01",
    "iso:country": "GB",
    "wof:name": "G77 5FW",
    "wof:placetype": "postalcode"
  },
  "geometry": {"coordinates":[-4.330841,55.765672],"type":"Point"}
}
