{
  "type": "Feature",
  "properties": {
    "iso:country":"GB",
    "wof:name":"E16 3HY",
    "wof:placetype":"postalcode"
},
  "geometry": {"coordinates":[0.04042924301047,51.51092376084006],"type":"Point"}
}