{
  "type": "Feature",
  "properties": {
    "date:inception_lower":"1983-01-01",
    "date:inception_upper":"1983-01-31",
    "iso:country":"GB",
    "wof:name":"E16 3HY",
    "wof:placetype":"postalcode"
},
  "geometry": {"coordinates":[0.040429,51.510924],"type":"Point"}
}