{
  "type": "Feature",
  "properties": {
    "iso:country": "GB",
    "wof:name": "M9 6HU",
    "wof:placetype": "postalcode"
  },
  "geometry": {"coordinates":[-2.200989,53.528882],"type":"Point"}
}
