{
  "type": "Feature",
  "properties": {
    "iso:country":"GB",
    "wof:name":"M9 6HU",
    "wof:placetype":"postalcode"
},
  "geometry": {"coordinates":[-2.2009893873502,53.5288815935598],"type":"Point"}
}