{
  "type": "Feature",
  "properties": {
    "iso:country":"GB",
    "wof:name":"HA8 6HR",
    "wof:placetype":"postalcode"
},
  "geometry": {"coordinates":[-0.28551890222324,51.60741293900531],"type":"Point"}
}