{
  "type": "Feature",
  "properties": {
    "date:inception_lower":"1980-01-01",
    "date:inception_upper":"1980-01-31",
    "iso:country":"GB",
    "wof:name":"HA8 6HR",
    "wof:placetype":"postalcode"
},
  "geometry": {"coordinates":[-0.285519,51.607413],"type":"Point"}
}