{
  "type": "Feature",
  "properties": {
    "iso:country":"GB",
    "wof:name":"PO33 2TQ",
    "wof:placetype":"postalcode"
},
  "geometry": {"coordinates":[-1.16716252101544,50.72202146812339],"type":"Point"}
}