{
  "type": "Feature",
  "properties": {
    "iso:country": "GB",
    "wof:name": "PO33 2TQ",
    "wof:placetype": "postalcode"
  },
  "geometry": {"coordinates":[-1.167152,50.72201],"type":"Point"}
}
