{
  "type": "Feature",
  "properties": {
    "iso:country": "GB",
    "wof:name": "AL8 7NH",
    "wof:placetype": "postalcode"
  },
  "geometry": {"coordinates":[-0.209626,51.817279],"type":"Point"}
}
