{
  "type": "Feature",
  "properties": {
    "iso:country":"GB",
    "wof:name":"CO5 9HD",
    "wof:placetype":"postalcode"
},
  "geometry": {"coordinates":[0.77697714766071,51.85925140906835],"type":"Point"}
}