{
  "type": "Feature",
  "properties": {
    "date:inception_lower": "1980-01-01",
    "date:inception_upper": "1980-01-01",
    "iso:country": "GB",
    "wof:name": "ML11 9TR",
    "wof:placetype": "postalcode"
  },
  "geometry": {"coordinates":[-3.758982,55.618615],"type":"Point"}
}
