{
  "type": "Feature",
  "properties": {
    "iso:country":"GB",
    "wof:name":"ML11 9TR",
    "wof:placetype":"postalcode"
},
  "geometry": {"coordinates":[-3.75285354464126,55.62377160897783],"type":"Point"}
}