{
  "type": "Feature",
  "properties": {
    "iso:country": "GB",
    "wof:name": "NE1 7EL",
    "wof:placetype": "postalcode"
  },
  "geometry": {"coordinates":[-1.611752,54.974754],"type":"Point"}
}
