{
  "type": "Feature",
  "properties": {
    "iso:country":"GB",
    "wof:name":"NE1 7EL",
    "wof:placetype":"postalcode"
},
  "geometry": {"coordinates":[-1.61175156754246,54.97475400077235],"type":"Point"}
}