{
  "type": "Feature",
  "properties": {
    "date:inception_lower":"1998-06-01",
    "date:inception_upper":"1998-06-30",
    "iso:country":"GB",
    "wof:name":"NE1 7EL",
    "wof:placetype":"postalcode"
},
  "geometry": {"coordinates":[-1.611752,54.974754],"type":"Point"}
}