{
  "type": "Feature",
  "properties": {
    "iso:country": "GB",
    "wof:name": "GL7 5XP",
    "wof:placetype": "postalcode"
  },
  "geometry": {"coordinates":[-1.926171,51.673943],"type":"Point"}
}
