{
  "type": "Feature",
  "properties": {
    "iso:country":"GB",
    "wof:name":"WR11 7JH",
    "wof:placetype":"postalcode"
},
  "geometry": {"coordinates":[-1.86966350324427,52.0942445971004],"type":"Point"}
}