{
  "type": "Feature",
  "properties": {
    "iso:country": "GB",
    "wof:name": "SR4 0DB",
    "wof:placetype": "postalcode"
  },
  "geometry": {"coordinates":[-1.427605,54.905523],"type":"Point"}
}
