{
  "type": "Feature",
  "properties": {
    "iso:country":"GB",
    "wof:name":"SR4 0DB",
    "wof:placetype":"postalcode"
},
  "geometry": {"coordinates":[-1.4275771957284,54.90546088353734],"type":"Point"}
}