{
  "type": "Feature",
  "properties": {
    "iso:country":"GB",
    "wof:name":"PR2 1DX",
    "wof:placetype":"postalcode"
},
  "geometry": {"coordinates":[-2.73120327498352,53.76854770044748],"type":"Point"}
}