{
  "type": "Feature",
  "properties": {
    "iso:country":"GB",
    "wof:name":"CW4 7BD",
    "wof:placetype":"postalcode"
},
  "geometry": {"coordinates":[-2.35528710721518,53.19721822370154],"type":"Point"}
}