{
  "type": "Feature",
  "properties": {
    "iso:country":"GB",
    "wof:name":"DE72 3JR",
    "wof:placetype":"postalcode"
},
  "geometry": {"coordinates":[-1.37615372394127,52.91184159397667],"type":"Point"}
}