{
  "type": "Feature",
  "properties": {
    "date:inception_lower": "2024-03-01",
    "date:inception_upper": "2024-03-01",
    "iso:country": "GB",
    "wof:name": "BH23 6DT",
    "wof:placetype": "postalcode"
  },
  "geometry": {"coordinates":[-1.843796,50.774322],"type":"Point"}
}
