{
  "type": "Feature",
  "properties": {
    "iso:country":"GB",
    "wof:name":"B93 9HA",
    "wof:placetype":"postalcode"
},
  "geometry": {"coordinates":[-1.75005861331192,52.38630116362815],"type":"Point"}
}