{
  "type": "Feature",
  "properties": {
    "iso:country":"GB",
    "wof:name":"KT9 2JE",
    "wof:placetype":"postalcode"
},
  "geometry": {"coordinates":[-0.30572659643051,51.36054214295552],"type":"Point"}
}