{
  "type": "Feature",
  "properties": {
    "iso:country":"GB",
    "wof:name":"DA9 9QX",
    "wof:placetype":"postalcode"
},
  "geometry": {"coordinates":[0.28082763722637,51.45249096436534],"type":"Point"}
}