{
  "type": "Feature",
  "properties": {
    "date:inception_lower":"1990-07-01",
    "date:inception_upper":"1990-07-31",
    "iso:country":"GB",
    "wof:name":"DA9 9QX",
    "wof:placetype":"postalcode"
},
  "geometry": {"coordinates":[0.280828,51.452491],"type":"Point"}
}