{
  "type": "Feature",
  "properties": {
    "iso:country":"GB",
    "wof:name":"ST1 2NE",
    "wof:placetype":"postalcode"
},
  "geometry": {"coordinates":[-2.16357168207617,53.03320927056278],"type":"Point"}
}