{
  "type": "Feature",
  "properties": {
    "iso:country":"GB",
    "wof:name":"LL14 1ER",
    "wof:placetype":"postalcode"
},
  "geometry": {"coordinates":[-3.05382363074365,53.0148347221163],"type":"Point"}
}