{
  "type": "Feature",
  "properties": {
    "date:inception_lower": "1980-01-01",
    "date:inception_upper": "1980-01-01",
    "iso:country": "GB",
    "wof:name": "LL14 1ER",
    "wof:placetype": "postalcode"
  },
  "geometry": {"coordinates":[-3.053901,53.014993],"type":"Point"}
}
