{
  "type": "Feature",
  "properties": {
    "iso:country":"GB",
    "wof:name":"DY2 8HP",
    "wof:placetype":"postalcode"
},
  "geometry": {"coordinates":[-2.08058661990011,52.49673683786419],"type":"Point"}
}