{
  "type": "Feature",
  "properties": {
    "iso:country":"GB",
    "wof:name":"SP2 8DH",
    "wof:placetype":"postalcode"
},
  "geometry": {"coordinates":[-1.79889452222495,51.05387159733136],"type":"Point"}
}