{
  "type": "Feature",
  "properties": {
    "iso:country":"GB",
    "wof:name":"KY15 5PN",
    "wof:placetype":"postalcode"
},
  "geometry": {"coordinates":[-2.99418260398237,56.25759744053837],"type":"Point"}
}