{
  "type": "Feature",
  "properties": {
    "date:inception_lower":"1980-01-01",
    "date:inception_upper":"1980-01-31",
    "iso:country":"GB",
    "wof:name":"LN13 9JT",
    "wof:placetype":"postalcode"
},
  "geometry": {"coordinates":[0.267921,53.246625],"type":"Point"}
}