{
  "type": "Feature",
  "properties": {
    "iso:country":"GB",
    "wof:name":"LN13 9JT",
    "wof:placetype":"postalcode"
},
  "geometry": {"coordinates":[0.2671675608316,53.24681893010322],"type":"Point"}
}