{
  "type": "Feature",
  "properties": {
    "iso:country":"GB",
    "wof:name":"BL1 1EE",
    "wof:placetype":"postalcode"
},
  "geometry": {"coordinates":[-2.4262333678976,53.57874223907497],"type":"Point"}
}