{
  "type": "Feature",
  "properties": {
    "iso:country":"GB",
    "wof:name":"M24 5ND",
    "wof:placetype":"postalcode"
},
  "geometry": {"coordinates":[-2.21738788295015,53.56431192670667],"type":"Point"}
}