{
  "type": "Feature",
  "properties": {
    "date:inception_lower": "1994-05-01",
    "date:inception_upper": "1994-05-01",
    "iso:country": "GB",
    "wof:name": "M24 5ND",
    "wof:placetype": "postalcode"
  },
  "geometry": {"coordinates":[-2.217388,53.564312],"type":"Point"}
}
