{
  "type": "Feature",
  "properties": {
    "iso:country": "GB",
    "wof:name": "SG1 6DN",
    "wof:placetype": "postalcode"
  },
  "geometry": {"coordinates":[-0.182265,51.930555],"type":"Point"}
}
