{
  "type": "Feature",
  "properties": {
    "date:inception_lower":"2002-06-01",
    "date:inception_upper":"2002-06-30",
    "iso:country":"GB",
    "wof:name":"SG1 6DN",
    "wof:placetype":"postalcode"
},
  "geometry": {"coordinates":[-0.182265,51.930555],"type":"Point"}
}