{
  "type": "Feature",
  "properties": {
    "iso:country":"GB",
    "wof:name":"SG1 6DN",
    "wof:placetype":"postalcode"
},
  "geometry": {"coordinates":[-0.18226471146208,51.9305553588763],"type":"Point"}
}