{
  "type": "Feature",
  "properties": {
    "iso:country": "GB",
    "wof:name": "PE11 3LU",
    "wof:placetype": "postalcode"
  },
  "geometry": {"coordinates":[-0.171552,52.77889],"type":"Point"}
}
