{
  "type": "Feature",
  "properties": {
    "date:inception_lower":"2002-12-01",
    "date:inception_upper":"2002-12-31",
    "iso:country":"GB",
    "wof:name":"PE11 3LU",
    "wof:placetype":"postalcode"
},
  "geometry": {"coordinates":[-0.171552,52.77889],"type":"Point"}
}