{
  "type": "Feature",
  "properties": {
    "iso:country":"GB",
    "wof:name":"PE11 3LU",
    "wof:placetype":"postalcode"
},
  "geometry": {"coordinates":[-0.17155164137052,52.77889024790792],"type":"Point"}
}