{
  "type": "Feature",
  "properties": {
    "date:inception_lower": "1980-01-01",
    "date:inception_upper": "1980-01-01",
    "iso:country": "GB",
    "wof:name": "PA1 3UA",
    "wof:placetype": "postalcode"
  },
  "geometry": {"coordinates":[-4.403381,55.851915],"type":"Point"}
}
