{
  "type": "Feature",
  "properties": {
    "iso:country":"GB",
    "wof:name":"PA1 3UA",
    "wof:placetype":"postalcode"
},
  "geometry": {"coordinates":[-4.40338074958769,55.85191513620013],"type":"Point"}
}