{
  "type": "Feature",
  "properties": {
    "date:inception_lower":"1980-01-01",
    "date:inception_upper":"1980-01-31",
    "iso:country":"GB",
    "wof:name":"IG8 9PF",
    "wof:placetype":"postalcode"
},
  "geometry": {"coordinates":[0.00365,51.603795],"type":"Point"}
}