{
  "type": "Feature",
  "properties": {
    "iso:country":"GB",
    "wof:name":"IG8 9PF",
    "wof:placetype":"postalcode"
},
  "geometry": {"coordinates":[0.00365000848508,51.60379517095182],"type":"Point"}
}