{
  "type": "Feature",
  "properties": {
    "iso:country": "GB",
    "wof:name": "IP24 3GD",
    "wof:placetype": "postalcode"
  },
  "geometry": {"coordinates":[0.72573,52.414329],"type":"Point"}
}
