{
  "type": "Feature",
  "properties": {
    "iso:country": "GB",
    "wof:name": "L21 3AB",
    "wof:placetype": "postalcode"
  },
  "geometry": {"coordinates":[-3.00677,53.463217],"type":"Point"}
}
