{
  "type": "Feature",
  "properties": {
    "date:inception_lower": "2017-02-01",
    "date:inception_upper": "2017-02-01",
    "iso:country": "GB",
    "wof:name": "L21 3AB",
    "wof:placetype": "postalcode"
  },
  "geometry": {"coordinates":[-3.007057,53.463278],"type":"Point"}
}
