{
  "type": "Feature",
  "properties": {
    "date:inception_lower": "2023-01-01",
    "date:inception_upper": "2023-01-01",
    "iso:country": "GB",
    "wof:name": "GU14 7JD",
    "wof:placetype": "postalcode"
  },
  "geometry": {"coordinates":[-0.755685,51.287889],"type":"Point"}
}
