{
  "type": "Feature",
  "properties": {
    "date:inception_lower": "1980-01-01",
    "date:inception_upper": "1980-01-01",
    "iso:country": "GB",
    "wof:name": "HA4 8SB",
    "wof:placetype": "postalcode"
  },
  "geometry": {"coordinates":[-0.409533,51.577515],"type":"Point"}
}
