{
  "type": "Feature",
  "properties": {
    "date:inception_lower": "2024-01-01",
    "date:inception_upper": "2024-01-01",
    "iso:country": "GB",
    "wof:name": "CB4 1UT",
    "wof:placetype": "postalcode"
  },
  "geometry": {"coordinates":[0.154646,52.220653],"type":"Point"}
}
