{
  "type": "Feature",
  "properties": {
    "iso:country":"GB",
    "wof:name":"WR8 0DL",
    "wof:placetype":"postalcode"
},
  "geometry": {"coordinates":[-2.2720804916548,52.08438186585223],"type":"Point"}
}