{
  "type": "Feature",
  "properties": {
    "date:inception_lower": "1980-01-01",
    "date:inception_upper": "1980-01-01",
    "iso:country": "GB",
    "wof:name": "WR8 0DL",
    "wof:placetype": "postalcode"
  },
  "geometry": {"coordinates":[-2.27208,52.084382],"type":"Point"}
}
