{
  "type": "Feature",
  "properties": {
    "iso:country": "GB",
    "wof:name": "WR8 0DL",
    "wof:placetype": "postalcode"
  },
  "geometry": {"coordinates":[-2.27208,52.084382],"type":"Point"}
}
