{
  "type": "Feature",
  "properties": {
    "iso:country": "GB",
    "wof:name": "BD17 5FA",
    "wof:placetype": "postalcode"
  },
  "geometry": {"coordinates":[-1.771039,53.842713],"type":"Point"}
}
