{
  "type": "Feature",
  "properties": {
    "iso:country":"GB",
    "wof:name":"AL1 4TH",
    "wof:placetype":"postalcode"
},
  "geometry": {"coordinates":[-0.30697913363075,51.75323439314391],"type":"Point"}
}