{
  "type": "Feature",
  "properties": {
    "iso:country": "GB",
    "wof:name": "AL1 4TH",
    "wof:placetype": "postalcode"
  },
  "geometry": {"coordinates":[-0.306979,51.753234],"type":"Point"}
}
