{
  "type": "Feature",
  "properties": {
    "iso:country":"GB",
    "wof:name":"CV1 1HL",
    "wof:placetype":"postalcode"
},
  "geometry": {"coordinates":[-1.51062356915286,52.41006015087972],"type":"Point"}
}