{
  "type": "Feature",
  "properties": {
    "date:inception_lower":"1980-01-01",
    "date:inception_upper":"1980-01-31",
    "iso:country":"GB",
    "wof:name":"CV1 1HL",
    "wof:placetype":"postalcode"
},
  "geometry": {"coordinates":[-1.510624,52.41006],"type":"Point"}
}