{
  "type": "Feature",
  "properties": {
    "iso:country":"GB",
    "wof:name":"NN6 8PS",
    "wof:placetype":"postalcode"
},
  "geometry": {"coordinates":[-1.01341366595986,52.3515315951324],"type":"Point"}
}