{
  "type": "Feature",
  "properties": {
    "iso:country": "GB",
    "wof:name": "NN6 8PS",
    "wof:placetype": "postalcode"
  },
  "geometry": {"coordinates":[-1.013354,52.351558],"type":"Point"}
}
