{
  "type": "Feature",
  "properties": {
    "date:inception_lower":"1980-01-01",
    "date:inception_upper":"1980-01-31",
    "iso:country":"GB",
    "wof:name":"WA11 8NG",
    "wof:placetype":"postalcode"
},
  "geometry": {"coordinates":[-2.768503,53.496117],"type":"Point"}
}