{
  "type": "Feature",
  "properties": {
    "date:inception_lower": "1980-01-01",
    "date:inception_upper": "1980-01-01",
    "iso:country": "GB",
    "wof:name": "G78 2JH",
    "wof:placetype": "postalcode"
  },
  "geometry": {"coordinates":[-4.389188,55.795344],"type":"Point"}
}
