{
  "type": "Feature",
  "properties": {
    "iso:country": "GB",
    "wof:name": "G78 2JH",
    "wof:placetype": "postalcode"
  },
  "geometry": {"coordinates":[-4.389188,55.795344],"type":"Point"}
}
