{
  "type": "Feature",
  "properties": {
    "iso:country":"GB",
    "wof:name":"E8 1HY",
    "wof:placetype":"postalcode"
},
  "geometry": {"coordinates":[-0.05532542189143,51.54837705741019],"type":"Point"}
}