{
  "type": "Feature",
  "properties": {
    "iso:country":"GB",
    "wof:name":"WN2 5XB",
    "wof:placetype":"postalcode"
},
  "geometry": {"coordinates":[-2.59228235504178,53.50658563463315],"type":"Point"}
}