{
  "type": "Feature",
  "properties": {
    "iso:country": "GB",
    "wof:name": "IV12 4QU",
    "wof:placetype": "postalcode"
  },
  "geometry": {"coordinates":[-3.870754,57.582697],"type":"Point"}
}
