{
  "type": "Feature",
  "properties": {
    "iso:country":"GB",
    "wof:name":"ST7 4RY",
    "wof:placetype":"postalcode"
},
  "geometry": {"coordinates":[-2.22509048807182,53.09467489058238],"type":"Point"}
}