{
  "type": "Feature",
  "properties": {
    "iso:country":"GB",
    "wof:name":"WD23 1HR",
    "wof:placetype":"postalcode"
},
  "geometry": {"coordinates":[-0.34782750197332,51.63663162854063],"type":"Point"}
}