{
  "type": "Feature",
  "properties": {
    "iso:country": "GB",
    "wof:name": "CA7 5AE",
    "wof:placetype": "postalcode"
  },
  "geometry": {"coordinates":[-3.207829,54.944916],"type":"Point"}
}
