{
  "type": "Feature",
  "properties": {
    "date:inception_lower": "2006-07-01",
    "date:inception_upper": "2006-07-01",
    "iso:country": "GB",
    "wof:name": "LN5 7FD",
    "wof:placetype": "postalcode"
  },
  "geometry": {"coordinates":[-0.534896,53.225902],"type":"Point"}
}
