{
  "type": "Feature",
  "properties": {
    "iso:country":"GB",
    "wof:name":"LN5 7FD",
    "wof:placetype":"postalcode"
},
  "geometry": {"coordinates":[-0.5347766959385,53.22629208224181],"type":"Point"}
}