{
  "type": "Feature",
  "properties": {
    "iso:country":"GB",
    "wof:name":"G53 5HL",
    "wof:placetype":"postalcode"
},
  "geometry": {"coordinates":[-4.33869678789894,55.82600136411127],"type":"Point"}
}