{
  "type": "Feature",
  "properties": {
    "date:inception_lower": "1980-01-01",
    "date:inception_upper": "1980-01-01",
    "iso:country": "GB",
    "wof:name": "G53 5HL",
    "wof:placetype": "postalcode"
  },
  "geometry": {"coordinates":[-4.338697,55.826001],"type":"Point"}
}
