{
  "type": "Feature",
  "properties": {
    "iso:country": "GB",
    "wof:name": "NE12 6GT",
    "wof:placetype": "postalcode"
  },
  "geometry": {"coordinates":[-1.579318,55.039185],"type":"Point"}
}
