{
  "type": "Feature",
  "properties": {
    "iso:country":"GB",
    "wof:name":"NE12 6GT",
    "wof:placetype":"postalcode"
},
  "geometry": {"coordinates":[-1.57931757882055,55.03918529862005],"type":"Point"}
}