{
  "type": "Feature",
  "properties": {
    "iso:country":"GB",
    "wof:name":"CA16 6PZ",
    "wof:placetype":"postalcode"
},
  "geometry": {"coordinates":[-2.42833798639795,54.53202735162498],"type":"Point"}
}