{
  "type": "Feature",
  "properties": {
    "iso:country": "GB",
    "wof:name": "CA16 6PZ",
    "wof:placetype": "postalcode"
  },
  "geometry": {"coordinates":[-2.428957,54.531675],"type":"Point"}
}
