{
  "type": "Feature",
  "properties": {
    "iso:country": "GB",
    "wof:name": "WA12 9DS",
    "wof:placetype": "postalcode"
  },
  "geometry": {"coordinates":[-2.644587,53.450035],"type":"Point"}
}
