{
  "type": "Feature",
  "properties": {
    "iso:country":"GB",
    "wof:name":"KT12 5BW",
    "wof:placetype":"postalcode"
},
  "geometry": {"coordinates":[-0.42390105504781,51.36961028772776],"type":"Point"}
}