{
  "type": "Feature",
  "properties": {
    "date:inception_lower": "1980-01-01",
    "date:inception_upper": "1980-01-01",
    "iso:country": "GB",
    "wof:name": "KT12 5BW",
    "wof:placetype": "postalcode"
  },
  "geometry": {"coordinates":[-0.422388,51.368717],"type":"Point"}
}
