{
  "type": "Feature",
  "properties": {
    "iso:country":"GB",
    "wof:name":"BS3 2BY",
    "wof:placetype":"postalcode"
},
  "geometry": {"coordinates":[-2.61497694093944,51.43863897837942],"type":"Point"}
}