{
  "type": "Feature",
  "properties": {
    "iso:country":"GB",
    "wof:name":"LU2 8DX",
    "wof:placetype":"postalcode"
},
  "geometry": {"coordinates":[-0.38068072802615,51.90049762619903],"type":"Point"}
}