{
  "type": "Feature",
  "properties": {
    "iso:country":"GB",
    "wof:name":"SR5 3PZ",
    "wof:placetype":"postalcode"
},
  "geometry": {"coordinates":[-1.45145627248801,54.92253732709469],"type":"Point"}
}