{
  "type": "Feature",
  "properties": {
    "iso:country": "GB",
    "wof:name": "CM1 3SN",
    "wof:placetype": "postalcode"
  },
  "geometry": {"coordinates":[0.372525,51.721668],"type":"Point"}
}
