{
  "type": "Feature",
  "properties": {
    "iso:country":"GB",
    "wof:name":"HA7 4EQ",
    "wof:placetype":"postalcode"
},
  "geometry": {"coordinates":[-0.30875639426162,51.61360394113051],"type":"Point"}
}