{
  "type": "Feature",
  "properties": {
    "iso:country":"GB",
    "wof:name":"G63 0HD",
    "wof:placetype":"postalcode"
},
  "geometry": {"coordinates":[-4.45233097397581,56.04304556751959],"type":"Point"}
}