{
  "type": "Feature",
  "properties": {
    "iso:country":"GB",
    "wof:name":"BD12 8QD",
    "wof:placetype":"postalcode"
},
  "geometry": {"coordinates":[-1.77045558510946,53.73474243569319],"type":"Point"}
}