{
  "type": "Feature",
  "properties": {
    "iso:country":"GB",
    "wof:name":"NG5 3EG",
    "wof:placetype":"postalcode"
},
  "geometry": {"coordinates":[-1.14256764840813,52.98717439424426],"type":"Point"}
}