{
  "type": "Feature",
  "properties": {
    "iso:country": "GB",
    "wof:name": "NG5 3EG",
    "wof:placetype": "postalcode"
  },
  "geometry": {"coordinates":[-1.142568,52.987174],"type":"Point"}
}
