{
  "type": "Feature",
  "properties": {
    "iso:country":"GB",
    "wof:name":"WS1 4SB",
    "wof:placetype":"postalcode"
},
  "geometry": {"coordinates":[-1.99225557100354,52.56640881361749],"type":"Point"}
}