{
  "type": "Feature",
  "properties": {
    "date:inception_lower": "1996-12-01",
    "date:inception_upper": "1996-12-01",
    "iso:country": "GB",
    "wof:name": "WS1 4SB",
    "wof:placetype": "postalcode"
  },
  "geometry": {"coordinates":[-1.992256,52.566409],"type":"Point"}
}
