{
  "type": "Feature",
  "properties": {
    "date:inception_lower": "1990-02-01",
    "date:inception_upper": "1990-02-01",
    "iso:country": "GB",
    "wof:name": "YO7 2NZ",
    "wof:placetype": "postalcode"
  },
  "geometry": {"coordinates":[-1.34916,54.249988],"type":"Point"}
}
