{
  "type": "Feature",
  "properties": {
    "iso:country":"GB",
    "wof:name":"YO7 2NZ",
    "wof:placetype":"postalcode"
},
  "geometry": {"coordinates":[-1.34915957806329,54.24998786393954],"type":"Point"}
}