{
  "type": "Feature",
  "properties": {
    "iso:country":"GB",
    "wof:name":"HP3 9WA",
    "wof:placetype":"postalcode"
},
  "geometry": {"coordinates":[-0.46242899634597,51.73590338950125],"type":"Point"}
}