{
  "type": "Feature",
  "properties": {
    "iso:country": "GB",
    "wof:name": "HP3 9WA",
    "wof:placetype": "postalcode"
  },
  "geometry": {"coordinates":[-0.462429,51.735903],"type":"Point"}
}
