{
  "type": "Feature",
  "properties": {
    "date:inception_lower":"2002-06-01",
    "date:inception_upper":"2002-06-30",
    "iso:country":"GB",
    "wof:name":"HP3 9WA",
    "wof:placetype":"postalcode"
},
  "geometry": {"coordinates":[-0.462429,51.735903],"type":"Point"}
}