{
  "type": "Feature",
  "properties": {
    "iso:country":"GB",
    "wof:name":"PE34 4PR",
    "wof:placetype":"postalcode"
},
  "geometry": {"coordinates":[0.28661232725305,52.73984149695706],"type":"Point"}
}