{
  "type": "Feature",
  "properties": {
    "iso:country": "GB",
    "wof:name": "PE34 4PR",
    "wof:placetype": "postalcode"
  },
  "geometry": {"coordinates":[0.286612,52.739841],"type":"Point"}
}
