{
  "type": "Feature",
  "properties": {
    "date:inception_lower": "1987-04-01",
    "date:inception_upper": "1987-04-01",
    "iso:country": "GB",
    "wof:name": "PE34 4PR",
    "wof:placetype": "postalcode"
  },
  "geometry": {"coordinates":[0.285556,52.739775],"type":"Point"}
}
