{
  "type": "Feature",
  "properties": {
    "iso:country": "GB",
    "wof:name": "EH29 9BQ",
    "wof:placetype": "postalcode"
  },
  "geometry": {"coordinates":[-3.402857,55.958383],"type":"Point"}
}
