{
  "type": "Feature",
  "properties": {
    "iso:country":"GB",
    "wof:name":"CF44 6YW",
    "wof:placetype":"postalcode"
},
  "geometry": {"coordinates":[-3.43384497229853,51.70443315707799],"type":"Point"}
}