{
  "type": "Feature",
  "properties": {
    "date:inception_lower": "1980-01-01",
    "date:inception_upper": "1980-01-01",
    "iso:country": "GB",
    "wof:name": "CF44 6YW",
    "wof:placetype": "postalcode"
  },
  "geometry": {"coordinates":[-3.433845,51.704433],"type":"Point"}
}
