{
  "type": "Feature",
  "properties": {
    "iso:country":"GB",
    "wof:name":"BL7 9BT",
    "wof:placetype":"postalcode"
},
  "geometry": {"coordinates":[-2.4219564397878,53.61635559216637],"type":"Point"}
}