{
  "type": "Feature",
  "properties": {
    "iso:country": "GB",
    "wof:name": "CV23 9NX",
    "wof:placetype": "postalcode"
  },
  "geometry": {"coordinates":[-1.371562,52.33072],"type":"Point"}
}
