{
  "type": "Feature",
  "properties": {
    "iso:country": "GB",
    "wof:name": "HR4 0PA",
    "wof:placetype": "postalcode"
  },
  "geometry": {"coordinates":[-2.740393,52.067688],"type":"Point"}
}
