{
  "type": "Feature",
  "properties": {
    "iso:country":"GB",
    "wof:name":"BN7 1YY",
    "wof:placetype":"postalcode"
},
  "geometry": {"coordinates":[0.0065867121911,50.87335607673823],"type":"Point"}
}