{
  "type": "Feature",
  "properties": {
    "iso:country":"GB",
    "wof:name":"S60 4NA",
    "wof:placetype":"postalcode"
},
  "geometry": {"coordinates":[-1.34271725919312,53.40503654314331],"type":"Point"}
}