{
  "type": "Feature",
  "properties": {
    "iso:country":"GB",
    "wof:name":"N19 3UL",
    "wof:placetype":"postalcode"
},
  "geometry": {"coordinates":[-0.13402496433539,51.5672533932443],"type":"Point"}
}