{
  "type": "Feature",
  "properties": {
    "iso:country": "GB",
    "wof:name": "N19 3UL",
    "wof:placetype": "postalcode"
  },
  "geometry": {"coordinates":[-0.134025,51.567253],"type":"Point"}
}
