{
  "type": "Feature",
  "properties": {
    "iso:country": "GB",
    "wof:name": "CV10 8HR",
    "wof:placetype": "postalcode"
  },
  "geometry": {"coordinates":[-1.503732,52.521086],"type":"Point"}
}
