{
  "type": "Feature",
  "properties": {
    "date:inception_lower": "1980-01-01",
    "date:inception_upper": "1980-01-01",
    "iso:country": "GB",
    "wof:name": "CV10 8HR",
    "wof:placetype": "postalcode"
  },
  "geometry": {"coordinates":[-1.503732,52.521086],"type":"Point"}
}
