{
  "type": "Feature",
  "properties": {
    "iso:country": "GB",
    "wof:name": "IP9 2RY",
    "wof:placetype": "postalcode"
  },
  "geometry": {"coordinates":[1.134581,51.970794],"type":"Point"}
}
