{
  "type": "Feature",
  "properties": {
    "iso:country":"GB",
    "wof:name":"BR2 9BZ",
    "wof:placetype":"postalcode"
},
  "geometry": {"coordinates":[0.01124493495026,51.39268734674981],"type":"Point"}
}