{
  "type": "Feature",
  "properties": {
    "iso:country":"GB",
    "wof:name":"M23 0JP",
    "wof:placetype":"postalcode"
},
  "geometry": {"coordinates":[-2.29218011354567,53.41044982156883],"type":"Point"}
}