{
  "type": "Feature",
  "properties": {
    "iso:country": "GB",
    "wof:name": "BS36 2DD",
    "wof:placetype": "postalcode"
  },
  "geometry": {"coordinates":[-2.491985,51.533865],"type":"Point"}
}
