{
  "type": "Feature",
  "properties": {
    "iso:country":"GB",
    "wof:name":"WV6 9JW",
    "wof:placetype":"postalcode"
},
  "geometry": {"coordinates":[-2.15774313338175,52.60825903944536],"type":"Point"}
}