{
  "type": "Feature",
  "properties": {
    "date:inception_lower":"1980-01-01",
    "date:inception_upper":"1980-01-31",
    "iso:country":"GB",
    "wof:name":"AL3 7EW",
    "wof:placetype":"postalcode"
},
  "geometry": {"coordinates":[-0.401653,51.801776],"type":"Point"}
}