{
  "type": "Feature",
  "properties": {
    "iso:country":"GB",
    "wof:name":"AL3 7EW",
    "wof:placetype":"postalcode"
},
  "geometry": {"coordinates":[-0.4016533698399,51.80177619880657],"type":"Point"}
}