{
  "type": "Feature",
  "properties": {
    "iso:country": "GB",
    "wof:name": "OL11 1AD",
    "wof:placetype": "postalcode"
  },
  "geometry": {"coordinates":[-2.147479,53.606581],"type":"Point"}
}
