{
  "type": "Feature",
  "properties": {
    "iso:country":"GB",
    "wof:name":"OL11 1AD",
    "wof:placetype":"postalcode"
},
  "geometry": {"coordinates":[-2.14761807064049,53.60702299054942],"type":"Point"}
}