{
  "type": "Feature",
  "properties": {
    "date:inception_lower":"1992-08-01",
    "date:inception_upper":"1992-08-31",
    "iso:country":"GB",
    "wof:name":"OL11 1AD",
    "wof:placetype":"postalcode"
},
  "geometry": {"coordinates":[-2.147479,53.606581],"type":"Point"}
}