{
  "type": "Feature",
  "properties": {
    "iso:country":"GB",
    "wof:name":"EX36 4HJ",
    "wof:placetype":"postalcode"
},
  "geometry": {"coordinates":[-3.84267649737766,51.01891796536455],"type":"Point"}
}