{
  "type": "Feature",
  "properties": {
    "iso:country": "GB",
    "wof:name": "EX36 4HJ",
    "wof:placetype": "postalcode"
  },
  "geometry": {"coordinates":[-3.842676,51.018918],"type":"Point"}
}
