{
  "type": "Feature",
  "properties": {
    "iso:country":"GB",
    "wof:name":"EX2 5QZ",
    "wof:placetype":"postalcode"
},
  "geometry": {"coordinates":[-3.48530481857884,50.72121303002015],"type":"Point"}
}