{
  "type": "Feature",
  "properties": {
    "iso:country":"GB",
    "wof:name":"LL53 5TA",
    "wof:placetype":"postalcode"
},
  "geometry": {"coordinates":[-4.43208588393075,52.88522563061279],"type":"Point"}
}