{
  "type": "Feature",
  "properties": {
    "date:inception_lower": "1980-01-01",
    "date:inception_upper": "1980-01-01",
    "iso:country": "GB",
    "wof:name": "SY16 2LZ",
    "wof:placetype": "postalcode"
  },
  "geometry": {"coordinates":[-3.315871,52.51576],"type":"Point"}
}
