{
  "type": "Feature",
  "properties": {
    "iso:country":"GB",
    "wof:name":"BN3 2DG",
    "wof:placetype":"postalcode"
},
  "geometry": {"coordinates":[-0.1793322474887,50.82729176293671],"type":"Point"}
}