{
  "type": "Feature",
  "properties": {
    "iso:country": "GB",
    "wof:name": "BN3 2DG",
    "wof:placetype": "postalcode"
  },
  "geometry": {"coordinates":[-0.179332,50.827292],"type":"Point"}
}
