{
  "type": "Feature",
  "properties": {
    "date:inception_lower": "1980-01-01",
    "date:inception_upper": "1980-01-01",
    "iso:country": "GB",
    "wof:name": "FK1 5QJ",
    "wof:placetype": "postalcode"
  },
  "geometry": {"coordinates":[-3.796265,55.995206],"type":"Point"}
}
