{
  "type": "Feature",
  "properties": {
    "iso:country":"GB",
    "wof:name":"NW8 6EA",
    "wof:placetype":"postalcode"
},
  "geometry": {"coordinates":[-0.1749929143783,51.53580379181321],"type":"Point"}
}