{
  "type": "Feature",
  "properties": {
    "iso:country":"GB",
    "wof:name":"GU3 2JQ",
    "wof:placetype":"postalcode"
},
  "geometry": {"coordinates":[-0.67318350574198,51.24124895827568],"type":"Point"}
}