{
  "type": "Feature",
  "properties": {
    "date:inception_lower": "1980-01-01",
    "date:inception_upper": "1980-01-01",
    "iso:country": "GB",
    "wof:name": "GU3 2JQ",
    "wof:placetype": "postalcode"
  },
  "geometry": {"coordinates":[-0.673183,51.241249],"type":"Point"}
}
