{
  "type": "Feature",
  "properties": {
    "iso:country":"GB",
    "wof:name":"NW3 2SJ",
    "wof:placetype":"postalcode"
},
  "geometry": {"coordinates":[-0.16463148022566,51.5571610349058],"type":"Point"}
}