{
  "type": "Feature",
  "properties": {
    "iso:country":"GB",
    "wof:name":"BS22 9BS",
    "wof:placetype":"postalcode"
},
  "geometry": {"coordinates":[-2.94040286302693,51.35890643887702],"type":"Point"}
}