{
  "type": "Feature",
  "properties": {
    "iso:country":"GB",
    "wof:name":"PR2 9UE",
    "wof:placetype":"postalcode"
},
  "geometry": {"coordinates":[-2.71616208351188,53.79491100843678],"type":"Point"}
}