{
  "type": "Feature",
  "properties": {
    "iso:country": "GB",
    "wof:name": "CH1 4QS",
    "wof:placetype": "postalcode"
  },
  "geometry": {"coordinates":[-2.921524,53.193974],"type":"Point"}
}
