{
  "type": "Feature",
  "properties": {
    "iso:country":"GB",
    "wof:name":"CH1 4QS",
    "wof:placetype":"postalcode"
},
  "geometry": {"coordinates":[-2.92153771692006,53.19394931942789],"type":"Point"}
}