{
  "type": "Feature",
  "properties": {
    "iso:country":"GB",
    "wof:name":"S62 7QN",
    "wof:placetype":"postalcode"
},
  "geometry": {"coordinates":[-1.35018753509822,53.47251936565326],"type":"Point"}
}