{
  "type": "Feature",
  "properties": {
    "iso:country":"GB",
    "wof:name":"EX16 7SN",
    "wof:placetype":"postalcode"
},
  "geometry": {"coordinates":[-3.38024941972432,50.92121459497569],"type":"Point"}
}