{
  "type": "Feature",
  "properties": {
    "iso:country": "GB",
    "wof:name": "EX16 7SN",
    "wof:placetype": "postalcode"
  },
  "geometry": {"coordinates":[-3.380249,50.921215],"type":"Point"}
}
