{
  "type": "Feature",
  "properties": {
    "date:inception_lower":"1992-01-01",
    "date:inception_upper":"1992-01-31",
    "iso:country":"GB",
    "wof:name":"EX16 7SN",
    "wof:placetype":"postalcode"
},
  "geometry": {"coordinates":[-3.380249,50.921215],"type":"Point"}
}