{
  "type": "Feature",
  "properties": {
    "date:inception_lower": "2005-01-01",
    "date:inception_upper": "2005-01-01",
    "iso:country": "GB",
    "wof:name": "WA10 6JG",
    "wof:placetype": "postalcode"
  },
  "geometry": {"coordinates":[-2.754813,53.466263],"type":"Point"}
}
