{
  "type": "Feature",
  "properties": {
    "iso:country":"GB",
    "wof:name":"BN3 3YS",
    "wof:placetype":"postalcode"
},
  "geometry": {"coordinates":[-0.17540082690138,50.83052193653018],"type":"Point"}
}