{
  "type": "Feature",
  "properties": {
    "iso:country": "GB",
    "wof:name": "BN3 3YS",
    "wof:placetype": "postalcode"
  },
  "geometry": {"coordinates":[-0.175401,50.830522],"type":"Point"}
}
