{
  "type": "Feature",
  "properties": {
    "date:inception_lower":"1980-01-01",
    "date:inception_upper":"1980-01-31",
    "iso:country":"GB",
    "wof:name":"BN3 3YS",
    "wof:placetype":"postalcode"
},
  "geometry": {"coordinates":[-0.175401,50.830522],"type":"Point"}
}