{
  "type": "Feature",
  "properties": {
    "iso:country":"GB",
    "wof:name":"KA3 4DY",
    "wof:placetype":"postalcode"
},
  "geometry": {"coordinates":[-4.52835874737511,55.74411254594386],"type":"Point"}
}