{
  "type": "Feature",
  "properties": {
    "iso:country":"GB",
    "wof:name":"WR15 8LN",
    "wof:placetype":"postalcode"
},
  "geometry": {"coordinates":[-2.55939932665888,52.313776356452],"type":"Point"}
}