{
  "type": "Feature",
  "properties": {
    "iso:country":"GB",
    "wof:name":"B31 2QE",
    "wof:placetype":"postalcode"
},
  "geometry": {"coordinates":[-1.96889356580536,52.40935966458267],"type":"Point"}
}