{
  "type": "Feature",
  "properties": {
    "date:inception_lower": "1980-01-01",
    "date:inception_upper": "1980-01-01",
    "iso:country": "GB",
    "wof:name": "SY24 5LL",
    "wof:placetype": "postalcode"
  },
  "geometry": {"coordinates":[-4.050929,52.479989],"type":"Point"}
}
