{
  "type": "Feature",
  "properties": {
    "date:inception_lower":"2005-07-01",
    "date:inception_upper":"2005-07-31",
    "iso:country":"GB",
    "wof:name":"ST5 1BA",
    "wof:placetype":"postalcode"
},
  "geometry": {"coordinates":[-2.222149,53.010794],"type":"Point"}
}