{
  "type": "Feature",
  "properties": {
    "date:inception_lower": "1987-10-01",
    "date:inception_upper": "1987-10-01",
    "iso:country": "GB",
    "wof:name": "E17 4TA",
    "wof:placetype": "postalcode"
  },
  "geometry": {"coordinates":[-0.007017,51.595991],"type":"Point"}
}
