{
  "type": "Feature",
  "properties": {
    "iso:country":"GB",
    "wof:name":"E17 4TA",
    "wof:placetype":"postalcode"
},
  "geometry": {"coordinates":[-0.00701700048965,51.59599140536855],"type":"Point"}
}