{
  "type": "Feature",
  "properties": {
    "iso:country":"GB",
    "wof:name":"B33 0QQ",
    "wof:placetype":"postalcode"
},
  "geometry": {"coordinates":[-1.76839619779962,52.46761758362305],"type":"Point"}
}