{
  "type": "Feature",
  "properties": {
    "iso:country":"GB",
    "wof:name":"W1F 9JR",
    "wof:placetype":"postalcode"
},
  "geometry": {"coordinates":[-0.13767917555503,51.51135128210639],"type":"Point"}
}