{
  "type": "Feature",
  "properties": {
    "iso:country": "GB",
    "wof:name": "TS12 3BL",
    "wof:placetype": "postalcode"
  },
  "geometry": {"coordinates":[-0.984002,54.541953],"type":"Point"}
}
