{
  "type": "Feature",
  "properties": {
    "date:inception_lower": "1980-01-01",
    "date:inception_upper": "1980-01-01",
    "iso:country": "GB",
    "wof:name": "TS12 3BL",
    "wof:placetype": "postalcode"
  },
  "geometry": {"coordinates":[-0.984002,54.541953],"type":"Point"}
}
