{
  "type": "Feature",
  "properties": {
    "iso:country":"GB",
    "wof:name":"KT21 2PA",
    "wof:placetype":"postalcode"
},
  "geometry": {"coordinates":[-0.30957263810482,51.30638146474175],"type":"Point"}
}