{
  "type": "Feature",
  "properties": {
    "iso:country":"GB",
    "wof:name":"FK5 3HR",
    "wof:placetype":"postalcode"
},
  "geometry": {"coordinates":[-3.82243850743917,56.02391957584038],"type":"Point"}
}