{
  "type": "Feature",
  "properties": {
    "iso:country":"GB",
    "wof:name":"SE19 3QJ",
    "wof:placetype":"postalcode"
},
  "geometry": {"coordinates":[-0.09278975832453,51.42152197213971],"type":"Point"}
}