{
  "type": "Feature",
  "properties": {
    "date:inception_lower": "1980-01-01",
    "date:inception_upper": "1980-01-01",
    "iso:country": "GB",
    "wof:name": "SE19 3QJ",
    "wof:placetype": "postalcode"
  },
  "geometry": {"coordinates":[-0.092912,51.421425],"type":"Point"}
}
