{
  "type": "Feature",
  "properties": {
    "iso:country": "GB",
    "wof:name": "SE19 3QJ",
    "wof:placetype": "postalcode"
  },
  "geometry": {"coordinates":[-0.092912,51.421425],"type":"Point"}
}
