{
  "type": "Feature",
  "properties": {
    "date:inception_lower": "1980-01-01",
    "date:inception_upper": "1980-01-01",
    "iso:country": "GB",
    "wof:name": "CF41 7AX",
    "wof:placetype": "postalcode"
  },
  "geometry": {"coordinates":[-3.490418,51.644131],"type":"Point"}
}
