{
  "type": "Feature",
  "properties": {
    "iso:country": "GB",
    "wof:name": "CF41 7AX",
    "wof:placetype": "postalcode"
  },
  "geometry": {"coordinates":[-3.490418,51.644131],"type":"Point"}
}
