{
  "type": "Feature",
  "properties": {
    "iso:country":"GB",
    "wof:name":"CF41 7AX",
    "wof:placetype":"postalcode"
},
  "geometry": {"coordinates":[-3.49041763537686,51.64413061598403],"type":"Point"}
}