{
  "type": "Feature",
  "properties": {
    "iso:country":"GB",
    "wof:name":"SA48 7BG",
    "wof:placetype":"postalcode"
},
  "geometry": {"coordinates":[-4.08098934154536,52.11290672953795],"type":"Point"}
}