{
  "type": "Feature",
  "properties": {
    "iso:country":"GB",
    "wof:name":"PH1 1DH",
    "wof:placetype":"postalcode"
},
  "geometry": {"coordinates":[-3.46899186666635,56.38969143233996],"type":"Point"}
}