{
  "type": "Feature",
  "properties": {
    "iso:country":"GB",
    "wof:name":"TA24 7AY",
    "wof:placetype":"postalcode"
},
  "geometry": {"coordinates":[-3.51269001213223,51.16015851556667],"type":"Point"}
}