{
  "type": "Feature",
  "properties": {
    "date:inception_lower":"1980-01-01",
    "date:inception_upper":"1980-01-31",
    "iso:country":"GB",
    "wof:name":"LS20 9DL",
    "wof:placetype":"postalcode"
},
  "geometry": {"coordinates":[-1.715526,53.88473],"type":"Point"}
}