{
  "type": "Feature",
  "properties": {
    "iso:country": "GB",
    "wof:name": "LS20 9DL",
    "wof:placetype": "postalcode"
  },
  "geometry": {"coordinates":[-1.717219,53.884087],"type":"Point"}
}
