{
  "type": "Feature",
  "properties": {
    "iso:country":"GB",
    "wof:name":"LS20 9DL",
    "wof:placetype":"postalcode"
},
  "geometry": {"coordinates":[-1.71552230019767,53.88471487823445],"type":"Point"}
}