{
  "type": "Feature",
  "properties": {
    "iso:country":"GB",
    "wof:name":"CT5 4QY",
    "wof:placetype":"postalcode"
},
  "geometry": {"coordinates":[0.99760111499599,51.34600723505353],"type":"Point"}
}