{
  "type": "Feature",
  "properties": {
    "iso:country": "GB",
    "wof:name": "YO25 1BX",
    "wof:placetype": "postalcode"
  },
  "geometry": {"coordinates":[-0.459166,53.999409],"type":"Point"}
}
