{
  "type": "Feature",
  "properties": {
    "iso:country": "GB",
    "wof:name": "HX5 0LQ",
    "wof:placetype": "postalcode"
  },
  "geometry": {"coordinates":[-1.841977,53.681873],"type":"Point"}
}
