{
  "type": "Feature",
  "properties": {
    "date:inception_lower": "2022-12-01",
    "date:inception_upper": "2022-12-01",
    "iso:country": "GB",
    "wof:name": "SY2 5WG",
    "wof:placetype": "postalcode"
  },
  "geometry": {"coordinates":[-2.714343,52.702379],"type":"Point"}
}
