{
  "type": "Feature",
  "properties": {
    "iso:country":"GB",
    "wof:name":"FK8 3LP",
    "wof:placetype":"postalcode"
},
  "geometry": {"coordinates":[-4.29236663612811,56.11537863705306],"type":"Point"}
}