{
  "type": "Feature",
  "properties": {
    "iso:country": "GB",
    "wof:name": "TR14 8NX",
    "wof:placetype": "postalcode"
  },
  "geometry": {"coordinates":[-5.299834,50.214351],"type":"Point"}
}
