{
  "type": "Feature",
  "properties": {
    "iso:country":"GB",
    "wof:name":"SW11 2PE",
    "wof:placetype":"postalcode"
},
  "geometry": {"coordinates":[-0.16921291305301,51.46636364086712],"type":"Point"}
}