{
  "type": "Feature",
  "properties": {
    "iso:country":"GB",
    "wof:name":"W11 1JN",
    "wof:placetype":"postalcode"
},
  "geometry": {"coordinates":[-0.20084399134612,51.51721111153805],"type":"Point"}
}