{
  "type": "Feature",
  "properties": {
    "iso:country":"GB",
    "wof:name":"SN13 9ST",
    "wof:placetype":"postalcode"
},
  "geometry": {"coordinates":[-2.20089970344928,51.41412198682981],"type":"Point"}
}