{
  "type": "Feature",
  "properties": {
    "iso:country": "GB",
    "wof:name": "SN13 9ST",
    "wof:placetype": "postalcode"
  },
  "geometry": {"coordinates":[-2.2009,51.414122],"type":"Point"}
}
