{
  "type": "Feature",
  "properties": {
    "iso:country": "GB",
    "wof:name": "PO5 3JL",
    "wof:placetype": "postalcode"
  },
  "geometry": {"coordinates":[-1.093671,50.787094],"type":"Point"}
}
