{
  "type": "Feature",
  "properties": {
    "iso:country":"GB",
    "wof:name":"HD3 3SY",
    "wof:placetype":"postalcode"
},
  "geometry": {"coordinates":[-1.83928275623765,53.66963661758422],"type":"Point"}
}