{
  "type": "Feature",
  "properties": {
    "iso:country":"GB",
    "wof:name":"B35 6PG",
    "wof:placetype":"postalcode"
},
  "geometry": {"coordinates":[-1.78465447062129,52.5234578711379],"type":"Point"}
}