{
  "type": "Feature",
  "properties": {
    "iso:country": "GB",
    "wof:name": "BD2 1LA",
    "wof:placetype": "postalcode"
  },
  "geometry": {"coordinates":[-1.754041,53.814766],"type":"Point"}
}
