{
  "type": "Feature",
  "properties": {
    "iso:country": "GB",
    "wof:name": "L13 4AY",
    "wof:placetype": "postalcode"
  },
  "geometry": {"coordinates":[-2.910388,53.406347],"type":"Point"}
}
