{
  "type": "Feature",
  "properties": {
    "iso:country":"GB",
    "wof:name":"BS34 8TZ",
    "wof:placetype":"postalcode"
},
  "geometry": {"coordinates":[-2.54144409934423,51.52000699484872],"type":"Point"}
}