{
  "type": "Feature",
  "properties": {
    "iso:country":"GB",
    "wof:name":"HP2 4JG",
    "wof:placetype":"postalcode"
},
  "geometry": {"coordinates":[-0.44867891623572,51.75046933109038],"type":"Point"}
}