{
  "type": "Feature",
  "properties": {
    "date:inception_lower":"1980-01-01",
    "date:inception_upper":"1980-01-31",
    "iso:country":"GB",
    "wof:name":"HP2 4JG",
    "wof:placetype":"postalcode"
},
  "geometry": {"coordinates":[-0.448679,51.750469],"type":"Point"}
}