{
  "type": "Feature",
  "properties": {
    "iso:country":"GB",
    "wof:name":"PE21 7LP",
    "wof:placetype":"postalcode"
},
  "geometry": {"coordinates":[-0.0484391525985,52.95806600640476],"type":"Point"}
}