{
  "type": "Feature",
  "properties": {
    "iso:country":"GB",
    "wof:name":"TA20 2TE",
    "wof:placetype":"postalcode"
},
  "geometry": {"coordinates":[-2.95154485365551,50.84479628053599],"type":"Point"}
}