{
  "type": "Feature",
  "properties": {
    "iso:country": "GB",
    "wof:name": "LL48 6AX",
    "wof:placetype": "postalcode"
  },
  "geometry": {"coordinates":[-4.067286,52.954308],"type":"Point"}
}
