{
  "type": "Feature",
  "properties": {
    "date:inception_lower": "1980-01-01",
    "date:inception_upper": "1980-01-01",
    "iso:country": "GB",
    "wof:name": "LL48 6AX",
    "wof:placetype": "postalcode"
  },
  "geometry": {"coordinates":[-4.067286,52.954308],"type":"Point"}
}
