{
  "type": "Feature",
  "properties": {
    "iso:country":"GB",
    "wof:name":"LU7 0NQ",
    "wof:placetype":"postalcode"
},
  "geometry": {"coordinates":[-0.71729883321146,51.89890215195501],"type":"Point"}
}