{
  "type": "Feature",
  "properties": {
    "iso:country": "GB",
    "wof:name": "B98 8RW",
    "wof:placetype": "postalcode"
  },
  "geometry": {"coordinates":[-1.915862,52.319954],"type":"Point"}
}
