{
  "type": "Feature",
  "properties": {
    "date:inception_lower":"1980-01-01",
    "date:inception_upper":"1980-01-31",
    "iso:country":"GB",
    "wof:name":"B98 8RW",
    "wof:placetype":"postalcode"
},
  "geometry": {"coordinates":[-1.915862,52.319954],"type":"Point"}
}