{
  "type": "Feature",
  "properties": {
    "iso:country":"GB",
    "wof:name":"PA2 8JF",
    "wof:placetype":"postalcode"
},
  "geometry": {"coordinates":[-4.42549814827177,55.82044574805963],"type":"Point"}
}