{
  "type": "Feature",
  "properties": {
    "iso:country":"GB",
    "wof:name":"BL9 6EZ",
    "wof:placetype":"postalcode"
},
  "geometry": {"coordinates":[-2.28394754990073,53.60147380596156],"type":"Point"}
}