{
  "type": "Feature",
  "properties": {
    "date:inception_lower": "1980-01-01",
    "date:inception_upper": "1980-01-01",
    "iso:country": "GB",
    "wof:name": "LL26 0RN",
    "wof:placetype": "postalcode"
  },
  "geometry": {"coordinates":[-3.768544,53.083335],"type":"Point"}
}
