{
  "type": "Feature",
  "properties": {
    "iso:country":"GB",
    "wof:name":"DN4 8DX",
    "wof:placetype":"postalcode"
},
  "geometry": {"coordinates":[-1.13110202460696,53.49092087030479],"type":"Point"}
}