{
  "type": "Feature",
  "properties": {
    "iso:country": "GB",
    "wof:name": "DN4 8DX",
    "wof:placetype": "postalcode"
  },
  "geometry": {"coordinates":[-1.131668,53.491368],"type":"Point"}
}
