{
  "type": "Feature",
  "properties": {
    "date:inception_lower":"2015-03-01",
    "date:inception_upper":"2015-03-31",
    "iso:country":"GB",
    "wof:name":"DN4 8DX",
    "wof:placetype":"postalcode"
},
  "geometry": {"coordinates":[-1.131668,53.491368],"type":"Point"}
}