{
  "type": "Feature",
  "properties": {
    "iso:country":"GB",
    "wof:name":"LD5 4RW",
    "wof:placetype":"postalcode"
},
  "geometry": {"coordinates":[-3.63696830998967,52.10633297388685],"type":"Point"}
}