{
  "type": "Feature",
  "properties": {
    "iso:country":"GB",
    "wof:name":"L40 2RQ",
    "wof:placetype":"postalcode"
},
  "geometry": {"coordinates":[-2.74883720644076,53.6374519150225],"type":"Point"}
}