{
  "type": "Feature",
  "properties": {
    "iso:country":"GB",
    "wof:name":"DT2 9SX",
    "wof:placetype":"postalcode"
},
  "geometry": {"coordinates":[-2.49636474066479,50.74351346376828],"type":"Point"}
}