{
  "type": "Feature",
  "properties": {
    "date:inception_lower": "1985-04-01",
    "date:inception_upper": "1985-04-01",
    "iso:country": "GB",
    "wof:name": "DT2 9SX",
    "wof:placetype": "postalcode"
  },
  "geometry": {"coordinates":[-2.496349,50.743486],"type":"Point"}
}
