{
  "type": "Feature",
  "properties": {
    "iso:country":"GB",
    "wof:name":"S60 5EU",
    "wof:placetype":"postalcode"
},
  "geometry": {"coordinates":[-1.37500931006626,53.40008628247511],"type":"Point"}
}