{
  "type": "Feature",
  "properties": {
    "iso:country": "GB",
    "wof:name": "S60 5EU",
    "wof:placetype": "postalcode"
  },
  "geometry": {"coordinates":[-1.375009,53.400086],"type":"Point"}
}
