{
  "type": "Feature",
  "properties": {
    "iso:country":"GB",
    "wof:name":"EH51 9BP",
    "wof:placetype":"postalcode"
},
  "geometry": {"coordinates":[-3.60454205464508,56.01059270832146],"type":"Point"}
}