{
  "type": "Feature",
  "properties": {
    "iso:country":"GB",
    "wof:name":"YO12 4NG",
    "wof:placetype":"postalcode"
},
  "geometry": {"coordinates":[-0.42354759190757,54.2420671524143],"type":"Point"}
}