{
  "type": "Feature",
  "properties": {
    "date:inception_lower": "1990-07-01",
    "date:inception_upper": "1990-07-01",
    "iso:country": "GB",
    "wof:name": "YO12 4NG",
    "wof:placetype": "postalcode"
  },
  "geometry": {"coordinates":[-0.423548,54.242067],"type":"Point"}
}
