{
  "type": "Feature",
  "properties": {
    "iso:country": "GB",
    "wof:name": "ST18 9JH",
    "wof:placetype": "postalcode"
  },
  "geometry": {"coordinates":[-2.215049,52.784546],"type":"Point"}
}
