{
  "type": "Feature",
  "properties": {
    "iso:country":"GB",
    "wof:name":"KA8 9PH",
    "wof:placetype":"postalcode"
},
  "geometry": {"coordinates":[-4.6102833255808,55.47066307266781],"type":"Point"}
}