{
  "type": "Feature",
  "properties": {
    "iso:country":"GB",
    "wof:name":"SL4 2EW",
    "wof:placetype":"postalcode"
},
  "geometry": {"coordinates":[-0.67320769098108,51.43486115927139],"type":"Point"}
}