{
  "type": "Feature",
  "properties": {
    "date:inception_lower": "2019-12-01",
    "date:inception_upper": "2019-12-01",
    "iso:country": "GB",
    "wof:name": "G75 9PG",
    "wof:placetype": "postalcode"
  },
  "geometry": {"coordinates":[-4.19688,55.734972],"type":"Point"}
}
