{
  "type": "Feature",
  "properties": {
    "iso:country": "GB",
    "wof:name": "G75 9PG",
    "wof:placetype": "postalcode"
  },
  "geometry": {"coordinates":[-4.198513,55.735123],"type":"Point"}
}
