{
  "type": "Feature",
  "properties": {
    "iso:country":"GB",
    "wof:name":"HU7 4YF",
    "wof:placetype":"postalcode"
},
  "geometry": {"coordinates":[-0.31114999681804,53.7842443483808],"type":"Point"}
}