{
  "type": "Feature",
  "properties": {
    "date:inception_lower": "2016-06-01",
    "date:inception_upper": "2016-06-01",
    "iso:country": "GB",
    "wof:name": "UB7 9GA",
    "wof:placetype": "postalcode"
  },
  "geometry": {"coordinates":[-0.463293,51.508364],"type":"Point"}
}
