{
  "type": "Feature",
  "properties": {
    "iso:country": "GB",
    "wof:name": "UB7 9GA",
    "wof:placetype": "postalcode"
  },
  "geometry": {"coordinates":[-0.463293,51.508364],"type":"Point"}
}
