{
  "type": "Feature",
  "properties": {
    "iso:country":"GB",
    "wof:name":"OX12 8JE",
    "wof:placetype":"postalcode"
},
  "geometry": {"coordinates":[-1.33624639638081,51.60083552841258],"type":"Point"}
}