{
  "type": "Feature",
  "properties": {
    "iso:country": "GB",
    "wof:name": "OX12 8JE",
    "wof:placetype": "postalcode"
  },
  "geometry": {"coordinates":[-1.336246,51.600836],"type":"Point"}
}
