{
  "type": "Feature",
  "properties": {
    "iso:country":"GB",
    "wof:name":"CT5 3LJ",
    "wof:placetype":"postalcode"
},
  "geometry": {"coordinates":[1.06693189774227,51.35853950892474],"type":"Point"}
}