{
  "type": "Feature",
  "properties": {
    "iso:country":"GB",
    "wof:name":"CA7 3RG",
    "wof:placetype":"postalcode"
},
  "geometry": {"coordinates":[-3.27771908257785,54.76106520617932],"type":"Point"}
}