{
  "type": "Feature",
  "properties": {
    "iso:country":"GB",
    "wof:name":"RH12 4DG",
    "wof:placetype":"postalcode"
},
  "geometry": {"coordinates":[-0.30001110867934,51.07827596342084],"type":"Point"}
}