{
  "type": "Feature",
  "properties": {
    "iso:country":"GB",
    "wof:name":"SA4 0YB",
    "wof:placetype":"postalcode"
},
  "geometry": {"coordinates":[-4.07375086015206,51.71109949884768],"type":"Point"}
}