{
  "type": "Feature",
  "properties": {
    "iso:country": "GB",
    "wof:name": "LN5 7HE",
    "wof:placetype": "postalcode"
  },
  "geometry": {"coordinates":[-0.539615,53.227659],"type":"Point"}
}
