{
  "type": "Feature",
  "properties": {
    "iso:country":"GB",
    "wof:name":"LN5 7HE",
    "wof:placetype":"postalcode"
},
  "geometry": {"coordinates":[-0.53986874259907,53.2276490784571],"type":"Point"}
}