{
  "type": "Feature",
  "properties": {
    "iso:country":"GB",
    "wof:name":"CW6 0RY",
    "wof:placetype":"postalcode"
},
  "geometry": {"coordinates":[-2.71360548652266,53.20763762873063],"type":"Point"}
}