{
  "type": "Feature",
  "properties": {
    "iso:country": "GB",
    "wof:name": "IV30 5PX",
    "wof:placetype": "postalcode"
  },
  "geometry": {"coordinates":[-3.370727,57.671563],"type":"Point"}
}
