{
  "type": "Feature",
  "properties": {
    "iso:country": "GB",
    "wof:name": "BR5 2PZ",
    "wof:placetype": "postalcode"
  },
  "geometry": {"coordinates":[0.103105,51.402558],"type":"Point"}
}
