{
  "type": "Feature",
  "properties": {
    "iso:country":"GB",
    "wof:name":"BR5 2PZ",
    "wof:placetype":"postalcode"
},
  "geometry": {"coordinates":[0.10310493455451,51.40255844632699],"type":"Point"}
}