{
  "type": "Feature",
  "properties": {
    "iso:country": "GB",
    "wof:name": "OL16 4AT",
    "wof:placetype": "postalcode"
  },
  "geometry": {"coordinates":[-2.135588,53.612168],"type":"Point"}
}
