{
  "type": "Feature",
  "properties": {
    "iso:country":"GB",
    "wof:name":"PR1 5LE",
    "wof:placetype":"postalcode"
},
  "geometry": {"coordinates":[-2.68211843765836,53.76543060223799],"type":"Point"}
}