{
  "type": "Feature",
  "properties": {
    "date:inception_lower":"2016-03-01",
    "date:inception_upper":"2016-03-31",
    "iso:country":"GB",
    "wof:name":"SA18 2QE",
    "wof:placetype":"postalcode"
},
  "geometry": {"coordinates":[-4.001661,51.798488],"type":"Point"}
}