{
  "type": "Feature",
  "properties": {
    "iso:country":"GB",
    "wof:name":"SA18 2QE",
    "wof:placetype":"postalcode"
},
  "geometry": {"coordinates":[-4.00113252528858,51.79834415083186],"type":"Point"}
}