{
  "type": "Feature",
  "properties": {
    "iso:country": "GB",
    "wof:name": "LS22 4BU",
    "wof:placetype": "postalcode"
  },
  "geometry": {"coordinates":[-1.483536,53.914777],"type":"Point"}
}
