{
  "type": "Feature",
  "properties": {
    "iso:country":"GB",
    "wof:name":"PE6 0RZ",
    "wof:placetype":"postalcode"
},
  "geometry": {"coordinates":[-0.09498599739812,52.62050585823162],"type":"Point"}
}