{
  "type": "Feature",
  "properties": {
    "iso:country": "GB",
    "wof:name": "PE6 0RZ",
    "wof:placetype": "postalcode"
  },
  "geometry": {"coordinates":[-0.094986,52.620506],"type":"Point"}
}
