{
  "type": "Feature",
  "properties": {
    "iso:country":"GB",
    "wof:name":"LN7 6GA",
    "wof:placetype":"postalcode"
},
  "geometry": {"coordinates":[-0.31585329744985,53.49685827230972],"type":"Point"}
}