{
  "type": "Feature",
  "properties": {
    "iso:country":"GB",
    "wof:name":"LS9 0PT",
    "wof:placetype":"postalcode"
},
  "geometry": {"coordinates":[-1.50838135785924,53.78837752313481],"type":"Point"}
}