{
  "type": "Feature",
  "properties": {
    "iso:country": "GB",
    "wof:name": "PE32 1AA",
    "wof:placetype": "postalcode"
  },
  "geometry": {"coordinates":[0.546373,52.77328],"type":"Point"}
}
