{
  "type": "Feature",
  "properties": {
    "iso:country":"GB",
    "wof:name":"PE32 1AA",
    "wof:placetype":"postalcode"
},
  "geometry": {"coordinates":[0.54656212344585,52.77320782131493],"type":"Point"}
}