{
  "type": "Feature",
  "properties": {
    "iso:country":"GB",
    "wof:name":"WS12 4PT",
    "wof:placetype":"postalcode"
},
  "geometry": {"coordinates":[-2.02232261941211,52.73929668733444],"type":"Point"}
}