{
  "type": "Feature",
  "properties": {
    "date:inception_lower": "1980-01-01",
    "date:inception_upper": "1980-01-01",
    "iso:country": "GB",
    "wof:name": "WS12 4PT",
    "wof:placetype": "postalcode"
  },
  "geometry": {"coordinates":[-2.022323,52.739297],"type":"Point"}
}
