{
  "type": "Feature",
  "properties": {
    "iso:country": "GB",
    "wof:name": "WS5 3QF",
    "wof:placetype": "postalcode"
  },
  "geometry": {"coordinates":[-1.952472,52.57476],"type":"Point"}
}
