{
  "type": "Feature",
  "properties": {
    "date:inception_lower": "1980-01-01",
    "date:inception_upper": "1980-01-01",
    "iso:country": "GB",
    "wof:name": "S65 1HF",
    "wof:placetype": "postalcode"
  },
  "geometry": {"coordinates":[-1.350949,53.434448],"type":"Point"}
}
