{
  "type": "Feature",
  "properties": {
    "date:inception_lower": "1980-01-01",
    "date:inception_upper": "1980-01-01",
    "iso:country": "GB",
    "wof:name": "G62 7EQ",
    "wof:placetype": "postalcode"
  },
  "geometry": {"coordinates":[-4.327801,55.942319],"type":"Point"}
}
