{
  "type": "Feature",
  "properties": {
    "iso:country":"GB",
    "wof:name":"G62 7EQ",
    "wof:placetype":"postalcode"
},
  "geometry": {"coordinates":[-4.32780121669666,55.94231889568914],"type":"Point"}
}