{
  "type": "Feature",
  "properties": {
    "iso:country":"GB",
    "wof:name":"NE24 2UF",
    "wof:placetype":"postalcode"
},
  "geometry": {"coordinates":[-1.52324601373153,55.11481283003327],"type":"Point"}
}