{
  "type": "Feature",
  "properties": {
    "date:inception_lower": "1980-01-01",
    "date:inception_upper": "1980-01-01",
    "iso:country": "GB",
    "wof:name": "NE24 2UF",
    "wof:placetype": "postalcode"
  },
  "geometry": {"coordinates":[-1.523246,55.114813],"type":"Point"}
}
