{
  "type": "Feature",
  "properties": {
    "iso:country": "GB",
    "wof:name": "AB22 8QX",
    "wof:placetype": "postalcode"
  },
  "geometry": {"coordinates":[-2.121547,57.201551],"type":"Point"}
}
