{
  "type": "Feature",
  "properties": {
    "date:inception_lower": "1997-06-01",
    "date:inception_upper": "1997-06-01",
    "iso:country": "GB",
    "wof:name": "S18 1PN",
    "wof:placetype": "postalcode"
  },
  "geometry": {"coordinates":[-1.479749,53.307384],"type":"Point"}
}
