{
  "type": "Feature",
  "properties": {
    "iso:country":"GB",
    "wof:name":"S18 1PN",
    "wof:placetype":"postalcode"
},
  "geometry": {"coordinates":[-1.47932324598991,53.30786768660218],"type":"Point"}
}