{
  "type": "Feature",
  "properties": {
    "iso:country":"GB",
    "wof:name":"TN12 8NL",
    "wof:placetype":"postalcode"
},
  "geometry": {"coordinates":[0.42909091131291,51.1382454943758],"type":"Point"}
}