{
  "type": "Feature",
  "properties": {
    "date:inception_lower":"1981-09-01",
    "date:inception_upper":"1981-09-30",
    "iso:country":"GB",
    "wof:name":"TN12 8NL",
    "wof:placetype":"postalcode"
},
  "geometry": {"coordinates":[0.429091,51.138245],"type":"Point"}
}