{
  "type": "Feature",
  "properties": {
    "iso:country":"GB",
    "wof:name":"CH49 1SW",
    "wof:placetype":"postalcode"
},
  "geometry": {"coordinates":[-3.10829390968213,53.37757170869193],"type":"Point"}
}