{
  "type": "Feature",
  "properties": {
    "iso:country": "GB",
    "wof:name": "CH49 1SW",
    "wof:placetype": "postalcode"
  },
  "geometry": {"coordinates":[-3.108294,53.377572],"type":"Point"}
}
