{
  "type": "Feature",
  "properties": {
    "date:inception_lower": "1999-06-01",
    "date:inception_upper": "1999-06-01",
    "iso:country": "GB",
    "wof:name": "CH49 1SW",
    "wof:placetype": "postalcode"
  },
  "geometry": {"coordinates":[-3.108294,53.377572],"type":"Point"}
}
