{
  "type": "Feature",
  "properties": {
    "iso:country":"GB",
    "wof:name":"EX17 4EF",
    "wof:placetype":"postalcode"
},
  "geometry": {"coordinates":[-3.6749056382764,50.82528579332683],"type":"Point"}
}