{
  "type": "Feature",
  "properties": {
    "date:inception_lower":"2002-11-01",
    "date:inception_upper":"2002-11-30",
    "iso:country":"GB",
    "wof:name":"S6 1XD",
    "wof:placetype":"postalcode"
},
  "geometry": {"coordinates":[-1.51788,53.415517],"type":"Point"}
}