{
  "type": "Feature",
  "properties": {
    "iso:country":"GB",
    "wof:name":"S6 1XD",
    "wof:placetype":"postalcode"
},
  "geometry": {"coordinates":[-1.51788026791044,53.41551660242645],"type":"Point"}
}