{
  "type": "Feature",
  "properties": {
    "iso:country": "GB",
    "wof:name": "RM7 7JN",
    "wof:placetype": "postalcode"
  },
  "geometry": {"coordinates":[0.170866,51.58479],"type":"Point"}
}
