{
  "type": "Feature",
  "properties": {
    "iso:country":"GB",
    "wof:name":"RM7 7JN",
    "wof:placetype":"postalcode"
},
  "geometry": {"coordinates":[0.17067602732018,51.58470970766641],"type":"Point"}
}