{
  "type": "Feature",
  "properties": {
    "iso:country":"GB",
    "wof:name":"SK14 5AH",
    "wof:placetype":"postalcode"
},
  "geometry": {"coordinates":[-2.07931654302657,53.44344563671276],"type":"Point"}
}