{
  "type": "Feature",
  "properties": {
    "date:inception_lower": "1980-01-01",
    "date:inception_upper": "1980-01-01",
    "iso:country": "GB",
    "wof:name": "OL4 4BE",
    "wof:placetype": "postalcode"
  },
  "geometry": {"coordinates":[-2.054775,53.546682],"type":"Point"}
}
