{
  "type": "Feature",
  "properties": {
    "iso:country":"GB",
    "wof:name":"OL4 4BE",
    "wof:placetype":"postalcode"
},
  "geometry": {"coordinates":[-2.05477475760833,53.54668241062654],"type":"Point"}
}