{
  "type": "Feature",
  "properties": {
    "iso:country": "GB",
    "wof:name": "OL4 4BE",
    "wof:placetype": "postalcode"
  },
  "geometry": {"coordinates":[-2.054775,53.546682],"type":"Point"}
}
