{
  "type": "Feature",
  "properties": {
    "date:inception_lower": "1994-12-01",
    "date:inception_upper": "1994-12-01",
    "iso:country": "GB",
    "wof:name": "CB5 8DS",
    "wof:placetype": "postalcode"
  },
  "geometry": {"coordinates":[0.133414,52.209263],"type":"Point"}
}
