{
  "type": "Feature",
  "properties": {
    "iso:country":"GB",
    "wof:name":"CB5 8DS",
    "wof:placetype":"postalcode"
},
  "geometry": {"coordinates":[0.13341429691234,52.20926319988877],"type":"Point"}
}