{
  "type": "Feature",
  "properties": {
    "iso:country":"GB",
    "wof:name":"W1G 9TL",
    "wof:placetype":"postalcode"
},
  "geometry": {"coordinates":[-0.14958670333727,51.51908445129068],"type":"Point"}
}