{
  "type": "Feature",
  "properties": {
    "iso:country": "GB",
    "wof:name": "DA13 9NA",
    "wof:placetype": "postalcode"
  },
  "geometry": {"coordinates":[0.298708,51.406708],"type":"Point"}
}
