{
  "type": "Feature",
  "properties": {
    "iso:country":"GB",
    "wof:name":"CW5 6LF",
    "wof:placetype":"postalcode"
},
  "geometry": {"coordinates":[-2.51214753368205,53.06423798010723],"type":"Point"}
}