{
  "type": "Feature",
  "properties": {
    "date:inception_lower": "1980-01-01",
    "date:inception_upper": "1980-01-01",
    "iso:country": "GB",
    "wof:name": "NR31 8AN",
    "wof:placetype": "postalcode"
  },
  "geometry": {"coordinates":[1.7115,52.582096],"type":"Point"}
}
