{
  "type": "Feature",
  "properties": {
    "iso:country":"GB",
    "wof:name":"SA73 1HA",
    "wof:placetype":"postalcode"
},
  "geometry": {"coordinates":[-5.0156244168784,51.73337033679451],"type":"Point"}
}