{
  "type": "Feature",
  "properties": {
    "date:inception_lower": "1980-01-01",
    "date:inception_upper": "1980-01-01",
    "iso:country": "GB",
    "wof:name": "SA73 1HA",
    "wof:placetype": "postalcode"
  },
  "geometry": {"coordinates":[-5.015624,51.73337],"type":"Point"}
}
