{
  "type": "Feature",
  "properties": {
    "iso:country":"GB",
    "wof:name":"L30 1QQ",
    "wof:placetype":"postalcode"
},
  "geometry": {"coordinates":[-2.96603362398496,53.47944755831109],"type":"Point"}
}