{
  "type": "Feature",
  "properties": {
    "iso:country":"GB",
    "wof:name":"DT6 5DL",
    "wof:placetype":"postalcode"
},
  "geometry": {"coordinates":[-2.76289045133091,50.73849469171905],"type":"Point"}
}