{
  "type": "Feature",
  "properties": {
    "iso:country": "GB",
    "wof:name": "DT6 5DL",
    "wof:placetype": "postalcode"
  },
  "geometry": {"coordinates":[-2.763076,50.73851],"type":"Point"}
}
