{
  "type": "Feature",
  "properties": {
    "date:inception_lower": "1996-06-01",
    "date:inception_upper": "1996-06-01",
    "iso:country": "GB",
    "wof:name": "AB11 5AD",
    "wof:placetype": "postalcode"
  },
  "geometry": {"coordinates":[-2.092878,57.147525],"type":"Point"}
}
