{
  "type": "Feature",
  "properties": {
    "iso:country":"GB",
    "wof:name":"S63 5DE",
    "wof:placetype":"postalcode"
},
  "geometry": {"coordinates":[-1.36506522358729,53.51338047832967],"type":"Point"}
}