{
  "type": "Feature",
  "properties": {
    "iso:country": "GB",
    "wof:name": "S63 5DE",
    "wof:placetype": "postalcode"
  },
  "geometry": {"coordinates":[-1.364977,53.513363],"type":"Point"}
}
