{
  "type": "Feature",
  "properties": {
    "iso:country": "GB",
    "wof:name": "M19 3LX",
    "wof:placetype": "postalcode"
  },
  "geometry": {"coordinates":[-2.182251,53.444007],"type":"Point"}
}
