{
  "type": "Feature",
  "properties": {
    "date:inception_lower": "1980-01-01",
    "date:inception_upper": "1980-01-01",
    "iso:country": "GB",
    "wof:name": "IP6 8JY",
    "wof:placetype": "postalcode"
  },
  "geometry": {"coordinates":[1.054735,52.122714],"type":"Point"}
}
