{
  "type": "Feature",
  "properties": {
    "iso:country":"GB",
    "wof:name":"IP6 8JY",
    "wof:placetype":"postalcode"
},
  "geometry": {"coordinates":[1.05477321504252,52.12413564601864],"type":"Point"}
}