{
  "type": "Feature",
  "properties": {
    "date:inception_lower": "1996-06-01",
    "date:inception_upper": "1996-06-01",
    "iso:country": "GB",
    "wof:name": "AB16 6NP",
    "wof:placetype": "postalcode"
  },
  "geometry": {"coordinates":[-2.170957,57.152877],"type":"Point"}
}
