{
  "type": "Feature",
  "properties": {
    "iso:country":"GB",
    "wof:name":"ML6 9JT",
    "wof:placetype":"postalcode"
},
  "geometry": {"coordinates":[-3.97650756042896,55.8593353204113],"type":"Point"}
}