{
  "type": "Feature",
  "properties": {
    "iso:country":"GB",
    "wof:name":"L22 6QW",
    "wof:placetype":"postalcode"
},
  "geometry": {"coordinates":[-3.04276617148193,53.48205644127759],"type":"Point"}
}