{
  "type": "Feature",
  "properties": {
    "date:inception_lower": "2002-06-01",
    "date:inception_upper": "2002-06-01",
    "iso:country": "GB",
    "wof:name": "SN8 1BA",
    "wof:placetype": "postalcode"
  },
  "geometry": {"coordinates":[-1.725845,51.420736],"type":"Point"}
}
