{
  "type": "Feature",
  "properties": {
    "date:inception_lower": "1995-07-01",
    "date:inception_upper": "1995-07-01",
    "iso:country": "GB",
    "wof:name": "RG22 6NE",
    "wof:placetype": "postalcode"
  },
  "geometry": {"coordinates":[-1.108888,51.263243],"type":"Point"}
}
