{
  "type": "Feature",
  "properties": {
    "date:inception_lower": "1998-06-01",
    "date:inception_upper": "1998-06-01",
    "iso:country": "GB",
    "wof:name": "L3 3AN",
    "wof:placetype": "postalcode"
  },
  "geometry": {"coordinates":[-2.980262,53.415555],"type":"Point"}
}
