{
  "type": "Feature",
  "properties": {
    "iso:country":"GB",
    "wof:name":"TR15 2NB",
    "wof:placetype":"postalcode"
},
  "geometry": {"coordinates":[-5.22066033242516,50.22603870308084],"type":"Point"}
}