{
  "type": "Feature",
  "properties": {
    "date:inception_lower":"1980-01-01",
    "date:inception_upper":"1980-01-31",
    "iso:country":"GB",
    "wof:name":"ME5 0BS",
    "wof:placetype":"postalcode"
},
  "geometry": {"coordinates":[0.545685,51.36927],"type":"Point"}
}