{
  "type": "Feature",
  "properties": {
    "iso:country": "GB",
    "wof:name": "ME5 0BS",
    "wof:placetype": "postalcode"
  },
  "geometry": {"coordinates":[0.545685,51.36927],"type":"Point"}
}
