{
  "type": "Feature",
  "properties": {
    "iso:country":"GB",
    "wof:name":"AB14 0UN",
    "wof:placetype":"postalcode"
},
  "geometry": {"coordinates":[-2.26886669215609,57.09718112501253],"type":"Point"}
}