{
  "type": "Feature",
  "properties": {
    "iso:country":"GB",
    "wof:name":"GL20 7RH",
    "wof:placetype":"postalcode"
},
  "geometry": {"coordinates":[-2.14233651214232,51.98135259219067],"type":"Point"}
}