{
  "type": "Feature",
  "properties": {
    "date:inception_lower": "1980-01-01",
    "date:inception_upper": "1980-01-01",
    "iso:country": "GB",
    "wof:name": "DA5 2DT",
    "wof:placetype": "postalcode"
  },
  "geometry": {"coordinates":[0.161786,51.438335],"type":"Point"}
}
