{
  "type": "Feature",
  "properties": {
    "iso:country":"GB",
    "wof:name":"DA5 2DT",
    "wof:placetype":"postalcode"
},
  "geometry": {"coordinates":[0.16178587573591,51.43833479548042],"type":"Point"}
}