{
  "type": "Feature",
  "properties": {
    "date:inception_lower": "1980-01-01",
    "date:inception_upper": "1980-01-01",
    "iso:country": "GB",
    "wof:name": "ML2 0HU",
    "wof:placetype": "postalcode"
  },
  "geometry": {"coordinates":[-3.923342,55.770301],"type":"Point"}
}
