{
  "type": "Feature",
  "properties": {
    "iso:country":"GB",
    "wof:name":"ML2 0HU",
    "wof:placetype":"postalcode"
},
  "geometry": {"coordinates":[-3.92334178088178,55.77030087925242],"type":"Point"}
}