{
  "type": "Feature",
  "properties": {
    "iso:country":"GB",
    "wof:name":"SN2 1DY",
    "wof:placetype":"postalcode"
},
  "geometry": {"coordinates":[-1.78751727293789,51.56840547591851],"type":"Point"}
}