{
  "type": "Feature",
  "properties": {
    "iso:country": "GB",
    "wof:name": "SN2 1DY",
    "wof:placetype": "postalcode"
  },
  "geometry": {"coordinates":[-1.787517,51.568405],"type":"Point"}
}
