{
  "type": "Feature",
  "properties": {
    "date:inception_lower": "2023-12-01",
    "date:inception_upper": "2023-12-01",
    "iso:country": "GB",
    "wof:name": "HR7 4FX",
    "wof:placetype": "postalcode"
  },
  "geometry": {"coordinates":[-2.553913,52.122199],"type":"Point"}
}
