{
  "type": "Feature",
  "properties": {
    "iso:country":"GB",
    "wof:name":"G32 8UQ",
    "wof:placetype":"postalcode"
},
  "geometry": {"coordinates":[-4.17278980939128,55.84373937826528],"type":"Point"}
}