{
  "type": "Feature",
  "properties": {
    "iso:country": "GB",
    "wof:name": "G32 8UQ",
    "wof:placetype": "postalcode"
  },
  "geometry": {"coordinates":[-4.17279,55.843739],"type":"Point"}
}
