{
  "type": "Feature",
  "properties": {
    "iso:country":"GB",
    "wof:name":"BN16 3EY",
    "wof:placetype":"postalcode"
},
  "geometry": {"coordinates":[-0.50738088490813,50.81254233773628],"type":"Point"}
}