{
  "type": "Feature",
  "properties": {
    "iso:country":"GB",
    "wof:name":"ME19 5LA",
    "wof:placetype":"postalcode"
},
  "geometry": {"coordinates":[0.39177050342466,51.30493746349516],"type":"Point"}
}