{
  "type": "Feature",
  "properties": {
    "iso:country":"GB",
    "wof:name":"DN21 1QW",
    "wof:placetype":"postalcode"
},
  "geometry": {"coordinates":[-0.76000919900843,53.3891899543145],"type":"Point"}
}