{
  "type": "Feature",
  "properties": {
    "iso:country": "GB",
    "wof:name": "BD23 3NY",
    "wof:placetype": "postalcode"
  },
  "geometry": {"coordinates":[-2.112648,53.980916],"type":"Point"}
}
