{
  "type": "Feature",
  "properties": {
    "iso:country":"GB",
    "wof:name":"BR5 1DE",
    "wof:placetype":"postalcode"
},
  "geometry": {"coordinates":[0.07227477138108,51.38973528854115],"type":"Point"}
}