{
  "type": "Feature",
  "properties": {
    "date:inception_lower": "1999-06-01",
    "date:inception_upper": "1999-06-01",
    "iso:country": "GB",
    "wof:name": "NP16 6RL",
    "wof:placetype": "postalcode"
  },
  "geometry": {"coordinates":[-2.757536,51.637318],"type":"Point"}
}
