{
  "type": "Feature",
  "properties": {
    "iso:country":"GB",
    "wof:name":"NP16 6RL",
    "wof:placetype":"postalcode"
},
  "geometry": {"coordinates":[-2.75753624400472,51.63731839943704],"type":"Point"}
}