{
  "type": "Feature",
  "properties": {
    "iso:country":"GB",
    "wof:name":"HU7 4SE",
    "wof:placetype":"postalcode"
},
  "geometry": {"coordinates":[-0.32309897038516,53.7883492990842],"type":"Point"}
}