{
  "type": "Feature",
  "properties": {
    "iso:country": "GB",
    "wof:name": "HU7 4SE",
    "wof:placetype": "postalcode"
  },
  "geometry": {"coordinates":[-0.323099,53.788349],"type":"Point"}
}
