{
  "type": "Feature",
  "properties": {
    "iso:country": "GB",
    "wof:name": "TS10 5HZ",
    "wof:placetype": "postalcode"
  },
  "geometry": {"coordinates":[-1.086814,54.605319],"type":"Point"}
}
