{
  "type": "Feature",
  "properties": {
    "iso:country":"GB",
    "wof:name":"KA12 9JY",
    "wof:placetype":"postalcode"
},
  "geometry": {"coordinates":[-4.65655318489141,55.62454439549403],"type":"Point"}
}