{
  "type": "Feature",
  "properties": {
    "iso:country": "GB",
    "wof:name": "NW6 7RH",
    "wof:placetype": "postalcode"
  },
  "geometry": {"coordinates":[-0.201293,51.540194],"type":"Point"}
}
