{
  "type": "Feature",
  "properties": {
    "iso:country":"GB",
    "wof:name":"NW6 7RH",
    "wof:placetype":"postalcode"
},
  "geometry": {"coordinates":[-0.20129328160965,51.54019362654068],"type":"Point"}
}