{
  "type": "Feature",
  "properties": {
    "date:inception_lower":"2001-06-01",
    "date:inception_upper":"2001-06-30",
    "iso:country":"GB",
    "wof:name":"GU51 3HJ",
    "wof:placetype":"postalcode"
},
  "geometry": {"coordinates":[-0.81701,51.277222],"type":"Point"}
}