{
  "type": "Feature",
  "properties": {
    "iso:country":"GB",
    "wof:name":"GU51 3HJ",
    "wof:placetype":"postalcode"
},
  "geometry": {"coordinates":[-0.81700977289183,51.27722206166114],"type":"Point"}
}