{
  "type": "Feature",
  "properties": {
    "date:inception_lower": "2016-05-01",
    "date:inception_upper": "2016-05-01",
    "iso:country": "GB",
    "wof:name": "G74 3FA",
    "wof:placetype": "postalcode"
  },
  "geometry": {"coordinates":[-4.157715,55.772534],"type":"Point"}
}
