{
  "type": "Feature",
  "properties": {
    "iso:country": "GB",
    "wof:name": "PL6 6FZ",
    "wof:placetype": "postalcode"
  },
  "geometry": {"coordinates":[-4.139393,50.426788],"type":"Point"}
}
