{
  "type": "Feature",
  "properties": {
    "date:inception_lower": "2014-02-01",
    "date:inception_upper": "2014-02-01",
    "iso:country": "GB",
    "wof:name": "EH23 4GN",
    "wof:placetype": "postalcode"
  },
  "geometry": {"coordinates":[-3.039401,55.845364],"type":"Point"}
}
