{
  "type": "Feature",
  "properties": {
    "iso:country": "GB",
    "wof:name": "EH23 4GN",
    "wof:placetype": "postalcode"
  },
  "geometry": {"coordinates":[-3.039401,55.845364],"type":"Point"}
}
