{
  "type": "Feature",
  "properties": {
    "iso:country":"GB",
    "wof:name":"IV30 4HU",
    "wof:placetype":"postalcode"
},
  "geometry": {"coordinates":[-3.30714546167255,57.65606607756921],"type":"Point"}
}