{
  "type": "Feature",
  "properties": {
    "iso:country": "GB",
    "wof:name": "IV30 4HU",
    "wof:placetype": "postalcode"
  },
  "geometry": {"coordinates":[-3.307145,57.656066],"type":"Point"}
}
