{
  "type": "Feature",
  "properties": {
    "iso:country":"GB",
    "wof:name":"GL4 0HP",
    "wof:placetype":"postalcode"
},
  "geometry": {"coordinates":[-2.24613897022288,51.83327259651457],"type":"Point"}
}