{
  "type": "Feature",
  "properties": {
    "date:inception_lower": "1980-01-01",
    "date:inception_upper": "1980-01-01",
    "iso:country": "GB",
    "wof:name": "GL4 0HP",
    "wof:placetype": "postalcode"
  },
  "geometry": {"coordinates":[-2.246139,51.833273],"type":"Point"}
}
