{
  "type": "Feature",
  "properties": {
    "iso:country": "GB",
    "wof:name": "GL4 0HP",
    "wof:placetype": "postalcode"
  },
  "geometry": {"coordinates":[-2.246139,51.833273],"type":"Point"}
}
