{
  "type": "Feature",
  "properties": {
    "iso:country":"GB",
    "wof:name":"W2 4DT",
    "wof:placetype":"postalcode"
},
  "geometry": {"coordinates":[-0.19681848244792,51.5118437560779],"type":"Point"}
}