{
  "type": "Feature",
  "properties": {
    "date:inception_lower": "1980-01-01",
    "date:inception_upper": "1980-01-01",
    "iso:country": "GB",
    "wof:name": "W2 4DT",
    "wof:placetype": "postalcode"
  },
  "geometry": {"coordinates":[-0.196818,51.511844],"type":"Point"}
}
