{
  "type": "Feature",
  "properties": {
    "iso:country":"GB",
    "wof:name":"LL57 4PN",
    "wof:placetype":"postalcode"
},
  "geometry": {"coordinates":[-4.09206240427808,53.18939795633907],"type":"Point"}
}