{
  "type": "Feature",
  "properties": {
    "date:inception_lower":"1980-01-01",
    "date:inception_upper":"1980-01-31",
    "iso:country":"GB",
    "wof:name":"N2 0SZ",
    "wof:placetype":"postalcode"
},
  "geometry": {"coordinates":[-0.177908,51.591674],"type":"Point"}
}