{
  "type": "Feature",
  "properties": {
    "date:inception_lower": "2008-01-01",
    "date:inception_upper": "2008-01-01",
    "iso:country": "GB",
    "wof:name": "WS14 9AD",
    "wof:placetype": "postalcode"
  },
  "geometry": {"coordinates":[-1.828945,52.671223],"type":"Point"}
}
