{
  "type": "Feature",
  "properties": {
    "date:inception_lower":"1980-01-01",
    "date:inception_upper":"1980-01-31",
    "iso:country":"GB",
    "wof:name":"TR14 8SH",
    "wof:placetype":"postalcode"
},
  "geometry": {"coordinates":[-5.300414,50.211186],"type":"Point"}
}