{
  "type": "Feature",
  "properties": {
    "iso:country":"GB",
    "wof:name":"TR14 8SH",
    "wof:placetype":"postalcode"
},
  "geometry": {"coordinates":[-5.30036509806452,50.21119610283534],"type":"Point"}
}