{
  "type": "Feature",
  "properties": {
    "iso:country": "GB",
    "wof:name": "SO45 6YU",
    "wof:placetype": "postalcode"
  },
  "geometry": {"coordinates":[-1.398782,50.869423],"type":"Point"}
}
