{
  "type": "Feature",
  "properties": {
    "iso:country":"GB",
    "wof:name":"SO45 6YU",
    "wof:placetype":"postalcode"
},
  "geometry": {"coordinates":[-1.39878177435168,50.86942302898311],"type":"Point"}
}