{
  "type": "Feature",
  "properties": {
    "iso:country":"GB",
    "wof:name":"BB3 0ST",
    "wof:placetype":"postalcode"
},
  "geometry": {"coordinates":[-2.46635339856894,53.71630179044205],"type":"Point"}
}