{
  "type": "Feature",
  "properties": {
    "iso:country": "GB",
    "wof:name": "ST18 0UB",
    "wof:placetype": "postalcode"
  },
  "geometry": {"coordinates":[-1.991001,52.789208],"type":"Point"}
}
