{
  "type": "Feature",
  "properties": {
    "date:inception_lower": "1980-01-01",
    "date:inception_upper": "1980-01-01",
    "iso:country": "GB",
    "wof:name": "ST18 0UB",
    "wof:placetype": "postalcode"
  },
  "geometry": {"coordinates":[-1.991001,52.789208],"type":"Point"}
}
