{
  "type": "Feature",
  "properties": {
    "iso:country":"GB",
    "wof:name":"ST18 0UB",
    "wof:placetype":"postalcode"
},
  "geometry": {"coordinates":[-1.99100149651333,52.78920835125864],"type":"Point"}
}