{
  "type": "Feature",
  "properties": {
    "iso:country":"GB",
    "wof:name":"CB24 4SL",
    "wof:placetype":"postalcode"
},
  "geometry": {"coordinates":[-0.04305963076269,52.29783241971678],"type":"Point"}
}