{
  "type": "Feature",
  "properties": {
    "iso:country": "GB",
    "wof:name": "CB24 4SL",
    "wof:placetype": "postalcode"
  },
  "geometry": {"coordinates":[-0.04306,52.297832],"type":"Point"}
}
