{
  "type": "Feature",
  "properties": {
    "iso:country": "GB",
    "wof:name": "DA16 1BN",
    "wof:placetype": "postalcode"
  },
  "geometry": {"coordinates":[0.115851,51.476188],"type":"Point"}
}
