{
  "type": "Feature",
  "properties": {
    "iso:country":"GB",
    "wof:name":"LS9 9ED",
    "wof:placetype":"postalcode"
},
  "geometry": {"coordinates":[-1.50308036788725,53.80025588014647],"type":"Point"}
}