{
  "type": "Feature",
  "properties": {
    "iso:country":"GB",
    "wof:name":"M25 0EN",
    "wof:placetype":"postalcode"
},
  "geometry": {"coordinates":[-2.25887376959192,53.52421304930485],"type":"Point"}
}