{
  "type": "Feature",
  "properties": {
    "date:inception_lower": "1994-05-01",
    "date:inception_upper": "1994-05-01",
    "iso:country": "GB",
    "wof:name": "M25 0EN",
    "wof:placetype": "postalcode"
  },
  "geometry": {"coordinates":[-2.258874,53.524213],"type":"Point"}
}
