{
  "type": "Feature",
  "properties": {
    "iso:country": "GB",
    "wof:name": "SW19 8EW",
    "wof:placetype": "postalcode"
  },
  "geometry": {"coordinates":[-0.194814,51.440008],"type":"Point"}
}
