{
  "type": "Feature",
  "properties": {
    "iso:country":"GB",
    "wof:name":"HP7 0QF",
    "wof:placetype":"postalcode"
},
  "geometry": {"coordinates":[-0.63488293254209,51.66421979348907],"type":"Point"}
}