{
  "type": "Feature",
  "properties": {
    "iso:country":"GB",
    "wof:name":"CR5 3QH",
    "wof:placetype":"postalcode"
},
  "geometry": {"coordinates":[-0.16351442688209,51.30223043009837],"type":"Point"}
}