{
  "type": "Feature",
  "properties": {
    "iso:country": "GB",
    "wof:name": "SA13 3BL",
    "wof:placetype": "postalcode"
  },
  "geometry": {"coordinates":[-3.628921,51.680852],"type":"Point"}
}
