{
  "type": "Feature",
  "properties": {
    "date:inception_lower": "1980-01-01",
    "date:inception_upper": "1980-01-01",
    "iso:country": "GB",
    "wof:name": "CT9 2EB",
    "wof:placetype": "postalcode"
  },
  "geometry": {"coordinates":[1.394035,51.391168],"type":"Point"}
}
