{
  "type": "Feature",
  "properties": {
    "iso:country": "GB",
    "wof:name": "CT9 2EB",
    "wof:placetype": "postalcode"
  },
  "geometry": {"coordinates":[1.394035,51.391168],"type":"Point"}
}
