{
  "type": "Feature",
  "properties": {
    "date:inception_lower": "1980-01-01",
    "date:inception_upper": "1980-01-01",
    "iso:country": "GB",
    "wof:name": "B32 1EN",
    "wof:placetype": "postalcode"
  },
  "geometry": {"coordinates":[-1.996203,52.460787],"type":"Point"}
}
