{
  "type": "Feature",
  "properties": {
    "date:inception_lower":"1998-12-01",
    "date:inception_upper":"1998-12-31",
    "iso:country":"GB",
    "wof:name":"BD6 2QW",
    "wof:placetype":"postalcode"
},
  "geometry": {"coordinates":[-1.787886,53.756274],"type":"Point"}
}