{
  "type": "Feature",
  "properties": {
    "iso:country":"GB",
    "wof:name":"BD6 2QW",
    "wof:placetype":"postalcode"
},
  "geometry": {"coordinates":[-1.78788628469173,53.75627393624161],"type":"Point"}
}