{
  "type": "Feature",
  "properties": {
    "iso:country":"GB",
    "wof:name":"PE26 2NT",
    "wof:placetype":"postalcode"
},
  "geometry": {"coordinates":[-0.1054718782739,52.43595072128299],"type":"Point"}
}