{
  "type": "Feature",
  "properties": {
    "iso:country": "GB",
    "wof:name": "HP14 3BT",
    "wof:placetype": "postalcode"
  },
  "geometry": {"coordinates":[-0.829879,51.639412],"type":"Point"}
}
