{
  "type": "Feature",
  "properties": {
    "iso:country": "GB",
    "wof:name": "BH22 8PW",
    "wof:placetype": "postalcode"
  },
  "geometry": {"coordinates":[-1.887187,50.791908],"type":"Point"}
}
