{
  "type": "Feature",
  "properties": {
    "iso:country":"GB",
    "wof:name":"BH22 8PW",
    "wof:placetype":"postalcode"
},
  "geometry": {"coordinates":[-1.88718665799717,50.79190762602772],"type":"Point"}
}