{
  "type": "Feature",
  "properties": {
    "date:inception_lower": "1993-08-01",
    "date:inception_upper": "1993-08-01",
    "iso:country": "GB",
    "wof:name": "BH22 8PW",
    "wof:placetype": "postalcode"
  },
  "geometry": {"coordinates":[-1.887187,50.791908],"type":"Point"}
}
