{
  "type": "Feature",
  "properties": {
    "date:inception_lower": "2006-03-01",
    "date:inception_upper": "2006-03-01",
    "iso:country": "GB",
    "wof:name": "NN8 2FL",
    "wof:placetype": "postalcode"
  },
  "geometry": {"coordinates":[-0.703604,52.299405],"type":"Point"}
}
