{
  "type": "Feature",
  "properties": {
    "iso:country":"GB",
    "wof:name":"NN8 2FL",
    "wof:placetype":"postalcode"
},
  "geometry": {"coordinates":[-0.70360382543949,52.29940468319883],"type":"Point"}
}