{
  "type": "Feature",
  "properties": {
    "iso:country":"GB",
    "wof:name":"TW4 6AB",
    "wof:placetype":"postalcode"
},
  "geometry": {"coordinates":[-0.3869522197165,51.46353642251951],"type":"Point"}
}