{
  "type": "Feature",
  "properties": {
    "date:inception_lower": "1980-01-01",
    "date:inception_upper": "1980-01-01",
    "iso:country": "GB",
    "wof:name": "KA11 1JP",
    "wof:placetype": "postalcode"
  },
  "geometry": {"coordinates":[-4.630817,55.617891],"type":"Point"}
}
