{
  "type": "Feature",
  "properties": {
    "iso:country":"GB",
    "wof:name":"KA11 1JP",
    "wof:placetype":"postalcode"
},
  "geometry": {"coordinates":[-4.63081674150571,55.61789050688186],"type":"Point"}
}