{
  "type": "Feature",
  "properties": {
    "iso:country":"GB",
    "wof:name":"EH21 8QL",
    "wof:placetype":"postalcode"
},
  "geometry": {"coordinates":[-3.00734334620421,55.93834174934884],"type":"Point"}
}