{
  "type": "Feature",
  "properties": {
    "date:inception_lower":"1980-01-01",
    "date:inception_upper":"1980-01-31",
    "iso:country":"GB",
    "wof:name":"EH21 8QL",
    "wof:placetype":"postalcode"
},
  "geometry": {"coordinates":[-3.007343,55.938342],"type":"Point"}
}