{
  "type": "Feature",
  "properties": {
    "date:inception_lower":"1992-08-01",
    "date:inception_upper":"1992-08-31",
    "iso:country":"GB",
    "wof:name":"HP22 4JR",
    "wof:placetype":"postalcode"
},
  "geometry": {"coordinates":[-0.83402,51.878798],"type":"Point"}
}