{
  "type": "Feature",
  "properties": {
    "iso:country":"GB",
    "wof:name":"HP22 4JR",
    "wof:placetype":"postalcode"
},
  "geometry": {"coordinates":[-0.83401982767601,51.87879788914216],"type":"Point"}
}