{
  "type": "Feature",
  "properties": {
    "iso:country": "GB",
    "wof:name": "HP22 4JR",
    "wof:placetype": "postalcode"
  },
  "geometry": {"coordinates":[-0.83402,51.878798],"type":"Point"}
}
