{
  "type": "Feature",
  "properties": {
    "iso:country": "GB",
    "wof:name": "TF5 0DG",
    "wof:placetype": "postalcode"
  },
  "geometry": {"coordinates":[-2.546419,52.711699],"type":"Point"}
}
