{
  "type": "Feature",
  "properties": {
    "date:inception_lower": "1980-01-01",
    "date:inception_upper": "1980-01-01",
    "iso:country": "GB",
    "wof:name": "WS6 7DZ",
    "wof:placetype": "postalcode"
  },
  "geometry": {"coordinates":[-2.03182,52.663278],"type":"Point"}
}
