{
  "type": "Feature",
  "properties": {
    "iso:country": "GB",
    "wof:name": "CM1 3JY",
    "wof:placetype": "postalcode"
  },
  "geometry": {"coordinates":[0.425453,51.727719],"type":"Point"}
}
