{
  "type": "Feature",
  "properties": {
    "iso:country":"GB",
    "wof:name":"CM1 3JY",
    "wof:placetype":"postalcode"
},
  "geometry": {"coordinates":[0.42545257089901,51.7277186184678],"type":"Point"}
}