{
  "type": "Feature",
  "properties": {
    "iso:country": "GB",
    "wof:name": "KY15 4UA",
    "wof:placetype": "postalcode"
  },
  "geometry": {"coordinates":[-2.999245,56.321142],"type":"Point"}
}
