{
  "type": "Feature",
  "properties": {
    "iso:country":"GB",
    "wof:name":"CF23 6BQ",
    "wof:placetype":"postalcode"
},
  "geometry": {"coordinates":[-3.16342221930066,51.51403820038673],"type":"Point"}
}