{
  "type": "Feature",
  "properties": {
    "iso:country":"GB",
    "wof:name":"SW2 3JW",
    "wof:placetype":"postalcode"
},
  "geometry": {"coordinates":[-0.11222405792523,51.43821224253239],"type":"Point"}
}