{
  "type": "Feature",
  "properties": {
    "iso:country":"GB",
    "wof:name":"WF3 1DW",
    "wof:placetype":"postalcode"
},
  "geometry": {"coordinates":[-1.58158763150482,53.71501565830833],"type":"Point"}
}