{
  "type": "Feature",
  "properties": {
    "iso:country":"GB",
    "wof:name":"NR14 6DS",
    "wof:placetype":"postalcode"
},
  "geometry": {"coordinates":[1.49035718200049,52.53667054009688],"type":"Point"}
}