{
  "type": "Feature",
  "properties": {
    "iso:country": "GB",
    "wof:name": "ST5 8ET",
    "wof:placetype": "postalcode"
  },
  "geometry": {"coordinates":[-2.231507,53.03538],"type":"Point"}
}
