{
  "type": "Feature",
  "properties": {
    "iso:country":"GB",
    "wof:name":"LE17 4DE",
    "wof:placetype":"postalcode"
},
  "geometry": {"coordinates":[-1.20277270255236,52.45307638885308],"type":"Point"}
}