{
  "type": "Feature",
  "properties": {
    "date:inception_lower":"2005-03-01",
    "date:inception_upper":"2005-03-31",
    "iso:country":"GB",
    "wof:name":"LE17 4DE",
    "wof:placetype":"postalcode"
},
  "geometry": {"coordinates":[-1.202773,52.453076],"type":"Point"}
}