{
  "type": "Feature",
  "properties": {
    "iso:country": "GB",
    "wof:name": "BS35 3PH",
    "wof:placetype": "postalcode"
  },
  "geometry": {"coordinates":[-2.53651,51.59056],"type":"Point"}
}
