{
  "type": "Feature",
  "properties": {
    "date:inception_lower": "1980-01-01",
    "date:inception_upper": "1980-01-01",
    "iso:country": "GB",
    "wof:name": "SS1 2JZ",
    "wof:placetype": "postalcode"
  },
  "geometry": {"coordinates":[0.714073,51.538196],"type":"Point"}
}
