{
  "type": "Feature",
  "properties": {
    "iso:country":"GB",
    "wof:name":"SS1 2JZ",
    "wof:placetype":"postalcode"
},
  "geometry": {"coordinates":[0.71407261701674,51.53819578199112],"type":"Point"}
}