{
  "type": "Feature",
  "properties": {
    "iso:country":"GB",
    "wof:name":"DL3 7DD",
    "wof:placetype":"postalcode"
},
  "geometry": {"coordinates":[-1.56182108633054,54.52706913677799],"type":"Point"}
}