{
  "type": "Feature",
  "properties": {
    "iso:country":"GB",
    "wof:name":"FK9 4HS",
    "wof:placetype":"postalcode"
},
  "geometry": {"coordinates":[-3.94711231938616,56.15464577789937],"type":"Point"}
}