{
  "type": "Feature",
  "properties": {
    "date:inception_lower": "1980-01-01",
    "date:inception_upper": "1980-01-01",
    "iso:country": "GB",
    "wof:name": "FK9 4HS",
    "wof:placetype": "postalcode"
  },
  "geometry": {"coordinates":[-3.94709,56.154658],"type":"Point"}
}
