{
  "type": "Feature",
  "properties": {
    "iso:country":"GB",
    "wof:name":"ML6 7JG",
    "wof:placetype":"postalcode"
},
  "geometry": {"coordinates":[-3.92658095304908,55.8791702386786],"type":"Point"}
}