{
  "type": "Feature",
  "properties": {
    "iso:country":"GB",
    "wof:name":"L32 0SX",
    "wof:placetype":"postalcode"
},
  "geometry": {"coordinates":[-2.90318864198216,53.48324704607951],"type":"Point"}
}