{
  "type": "Feature",
  "properties": {
    "iso:country": "GB",
    "wof:name": "L32 0SX",
    "wof:placetype": "postalcode"
  },
  "geometry": {"coordinates":[-2.903189,53.483247],"type":"Point"}
}
