{
  "type": "Feature",
  "properties": {
    "date:inception_lower": "1980-01-01",
    "date:inception_upper": "1980-01-01",
    "iso:country": "GB",
    "wof:name": "ML2 7DE",
    "wof:placetype": "postalcode"
  },
  "geometry": {"coordinates":[-3.907878,55.778468],"type":"Point"}
}
