{
  "type": "Feature",
  "properties": {
    "iso:country":"GB",
    "wof:name":"ML2 7DE",
    "wof:placetype":"postalcode"
},
  "geometry": {"coordinates":[-3.9078783079508,55.77846835074814],"type":"Point"}
}