{
  "type": "Feature",
  "properties": {
    "iso:country":"GB",
    "wof:name":"S75 1BQ",
    "wof:placetype":"postalcode"
},
  "geometry": {"coordinates":[-1.48472564660744,53.56436306087187],"type":"Point"}
}