{
  "type": "Feature",
  "properties": {
    "iso:country": "GB",
    "wof:name": "SK6 4BH",
    "wof:placetype": "postalcode"
  },
  "geometry": {"coordinates":[-2.091123,53.416975],"type":"Point"}
}
