{
  "type": "Feature",
  "properties": {
    "iso:country":"GB",
    "wof:name":"SK6 4BH",
    "wof:placetype":"postalcode"
},
  "geometry": {"coordinates":[-2.09112316390579,53.4169750024658],"type":"Point"}
}