{
  "type": "Feature",
  "properties": {
    "iso:country":"GB",
    "wof:name":"PE15 0HU",
    "wof:placetype":"postalcode"
},
  "geometry": {"coordinates":[0.17271643069012,52.48324538845625],"type":"Point"}
}