{
  "type": "Feature",
  "properties": {
    "date:inception_lower": "1993-01-01",
    "date:inception_upper": "1993-01-01",
    "iso:country": "GB",
    "wof:name": "PE15 0HU",
    "wof:placetype": "postalcode"
  },
  "geometry": {"coordinates":[0.172716,52.483245],"type":"Point"}
}
