{
  "type": "Feature",
  "properties": {
    "iso:country": "GB",
    "wof:name": "SK15 1HT",
    "wof:placetype": "postalcode"
  },
  "geometry": {"coordinates":[-2.061442,53.49229],"type":"Point"}
}
