{
  "type": "Feature",
  "properties": {
    "iso:country":"GB",
    "wof:name":"CM8 2PT",
    "wof:placetype":"postalcode"
},
  "geometry": {"coordinates":[0.64688530394592,51.81205184180048],"type":"Point"}
}