{
  "type": "Feature",
  "properties": {
    "date:inception_lower": "1980-01-01",
    "date:inception_upper": "1980-01-01",
    "iso:country": "GB",
    "wof:name": "CM8 2PT",
    "wof:placetype": "postalcode"
  },
  "geometry": {"coordinates":[0.646885,51.812052],"type":"Point"}
}
