{
  "type": "Feature",
  "properties": {
    "iso:country": "GB",
    "wof:name": "M28 3BN",
    "wof:placetype": "postalcode"
  },
  "geometry": {"coordinates":[-2.399755,53.52893],"type":"Point"}
}
