{
  "type": "Feature",
  "properties": {
    "iso:country":"GB",
    "wof:name":"HX4 8EE",
    "wof:placetype":"postalcode"
},
  "geometry": {"coordinates":[-1.85609570175386,53.68823645460539],"type":"Point"}
}