{
  "type": "Feature",
  "properties": {
    "date:inception_lower": "1990-07-01",
    "date:inception_upper": "1990-07-01",
    "iso:country": "GB",
    "wof:name": "HP20 2XF",
    "wof:placetype": "postalcode"
  },
  "geometry": {"coordinates":[-0.797719,51.827442],"type":"Point"}
}
