{
  "type": "Feature",
  "properties": {
    "iso:country":"GB",
    "wof:name":"HP20 2XF",
    "wof:placetype":"postalcode"
},
  "geometry": {"coordinates":[-0.79771886170947,51.82744247652164],"type":"Point"}
}