{
  "type": "Feature",
  "properties": {
    "iso:country":"GB",
    "wof:name":"LE7 4YT",
    "wof:placetype":"postalcode"
},
  "geometry": {"coordinates":[-1.01577073342202,52.72968842137124],"type":"Point"}
}