{
  "type": "Feature",
  "properties": {
    "date:inception_lower": "1980-01-01",
    "date:inception_upper": "1980-01-01",
    "iso:country": "GB",
    "wof:name": "G84 7EL",
    "wof:placetype": "postalcode"
  },
  "geometry": {"coordinates":[-4.726682,56.005439],"type":"Point"}
}
