{
  "type": "Feature",
  "properties": {
    "iso:country":"GB",
    "wof:name":"G84 7EL",
    "wof:placetype":"postalcode"
},
  "geometry": {"coordinates":[-4.726701011359,56.00544639632156],"type":"Point"}
}