{
  "type": "Feature",
  "properties": {
    "date:inception_lower":"2011-03-01",
    "date:inception_upper":"2011-03-31",
    "iso:country":"GB",
    "wof:name":"DL16 7EP",
    "wof:placetype":"postalcode"
},
  "geometry": {"coordinates":[-1.623213,54.691015],"type":"Point"}
}