{
  "type": "Feature",
  "properties": {
    "iso:country":"GB",
    "wof:name":"DL16 7EP",
    "wof:placetype":"postalcode"
},
  "geometry": {"coordinates":[-1.62321259621365,54.69101532692282],"type":"Point"}
}