{
  "type": "Feature",
  "properties": {
    "iso:country":"GB",
    "wof:name":"NW10 5TA",
    "wof:placetype":"postalcode"
},
  "geometry": {"coordinates":[-0.22757739879191,51.53250951904013],"type":"Point"}
}