{
  "type": "Feature",
  "properties": {
    "date:inception_lower": "1980-01-01",
    "date:inception_upper": "1980-01-01",
    "iso:country": "GB",
    "wof:name": "NW10 5TA",
    "wof:placetype": "postalcode"
  },
  "geometry": {"coordinates":[-0.227577,51.53251],"type":"Point"}
}
