{
  "type": "Feature",
  "properties": {
    "iso:country": "GB",
    "wof:name": "GU3 2AP",
    "wof:placetype": "postalcode"
  },
  "geometry": {"coordinates":[-0.671455,51.258495],"type":"Point"}
}
