{
  "type": "Feature",
  "properties": {
    "date:inception_lower":"1980-01-01",
    "date:inception_upper":"1980-01-31",
    "iso:country":"GB",
    "wof:name":"GU3 2AP",
    "wof:placetype":"postalcode"
},
  "geometry": {"coordinates":[-0.671455,51.258495],"type":"Point"}
}