{
  "type": "Feature",
  "properties": {
    "iso:country":"GB",
    "wof:name":"GU3 2AP",
    "wof:placetype":"postalcode"
},
  "geometry": {"coordinates":[-0.67145464317283,51.25849470161997],"type":"Point"}
}