{
  "type": "Feature",
  "properties": {
    "iso:country":"GB",
    "wof:name":"SW6 2SS",
    "wof:placetype":"postalcode"
},
  "geometry": {"coordinates":[-0.18193047496069,51.47348577575584],"type":"Point"}
}