{
  "type": "Feature",
  "properties": {
    "date:inception_lower": "2003-05-01",
    "date:inception_upper": "2003-05-01",
    "iso:country": "GB",
    "wof:name": "SW6 2SS",
    "wof:placetype": "postalcode"
  },
  "geometry": {"coordinates":[-0.18193,51.473486],"type":"Point"}
}
