{
  "type": "Feature",
  "properties": {
    "iso:country":"GB",
    "wof:name":"CF38 2PH",
    "wof:placetype":"postalcode"
},
  "geometry": {"coordinates":[-3.33801690164335,51.55192956861598],"type":"Point"}
}