{
  "type": "Feature",
  "properties": {
    "date:inception_lower": "1990-02-01",
    "date:inception_upper": "1990-02-01",
    "iso:country": "GB",
    "wof:name": "CF38 2PH",
    "wof:placetype": "postalcode"
  },
  "geometry": {"coordinates":[-3.338017,51.55193],"type":"Point"}
}
