{
  "type": "Feature",
  "properties": {
    "iso:country":"GB",
    "wof:name":"SA39 9EB",
    "wof:placetype":"postalcode"
},
  "geometry": {"coordinates":[-4.18692164591226,52.02932152774247],"type":"Point"}
}