{
  "type": "Feature",
  "properties": {
    "iso:country":"GB",
    "wof:name":"SY1 3RN",
    "wof:placetype":"postalcode"
},
  "geometry": {"coordinates":[-2.74184246898269,52.74161593379031],"type":"Point"}
}