{
  "type": "Feature",
  "properties": {
    "iso:country":"GB",
    "wof:name":"YO25 8RP",
    "wof:placetype":"postalcode"
},
  "geometry": {"coordinates":[-0.30123085292506,53.91057156659615],"type":"Point"}
}