{
  "type": "Feature",
  "properties": {
    "date:inception_lower": "1993-01-01",
    "date:inception_upper": "1993-01-01",
    "iso:country": "GB",
    "wof:name": "L26 7ZU",
    "wof:placetype": "postalcode"
  },
  "geometry": {"coordinates":[-2.84336,53.371423],"type":"Point"}
}
