{
  "type": "Feature",
  "properties": {
    "iso:country":"GB",
    "wof:name":"L26 7ZU",
    "wof:placetype":"postalcode"
},
  "geometry": {"coordinates":[-2.84336023942942,53.37142325858898],"type":"Point"}
}