{
  "type": "Feature",
  "properties": {
    "iso:country": "GB",
    "wof:name": "CW9 6LZ",
    "wof:placetype": "postalcode"
  },
  "geometry": {"coordinates":[-2.492506,53.323893],"type":"Point"}
}
