{
  "type": "Feature",
  "properties": {
    "date:inception_lower": "1980-01-01",
    "date:inception_upper": "1980-01-01",
    "iso:country": "GB",
    "wof:name": "CW9 6LZ",
    "wof:placetype": "postalcode"
  },
  "geometry": {"coordinates":[-2.492506,53.323893],"type":"Point"}
}
