{
  "type": "Feature",
  "properties": {
    "iso:country":"GB",
    "wof:name":"MK15 9LP",
    "wof:placetype":"postalcode"
},
  "geometry": {"coordinates":[-0.72837834107229,52.06331058164952],"type":"Point"}
}