{
  "type": "Feature",
  "properties": {
    "date:inception_lower":"1990-02-01",
    "date:inception_upper":"1990-02-28",
    "iso:country":"GB",
    "wof:name":"MK15 9LP",
    "wof:placetype":"postalcode"
},
  "geometry": {"coordinates":[-0.728378,52.063311],"type":"Point"}
}