{
  "type": "Feature",
  "properties": {
    "iso:country":"GB",
    "wof:name":"CF5 4FN",
    "wof:placetype":"postalcode"
},
  "geometry": {"coordinates":[-3.24989603057177,51.48161366366078],"type":"Point"}
}