{
  "type": "Feature",
  "properties": {
    "iso:country": "GB",
    "wof:name": "TR14 0ER",
    "wof:placetype": "postalcode"
  },
  "geometry": {"coordinates":[-5.287574,50.231072],"type":"Point"}
}
