{
  "type": "Feature",
  "properties": {
    "iso:country":"GB",
    "wof:name":"TR14 0ER",
    "wof:placetype":"postalcode"
},
  "geometry": {"coordinates":[-5.28757361748128,50.23107175591457],"type":"Point"}
}