{
  "type": "Feature",
  "properties": {
    "date:inception_lower":"2003-05-01",
    "date:inception_upper":"2003-05-31",
    "iso:country":"GB",
    "wof:name":"DT1 3RN",
    "wof:placetype":"postalcode"
},
  "geometry": {"coordinates":[-2.465177,50.712941],"type":"Point"}
}