{
  "type": "Feature",
  "properties": {
    "iso:country":"GB",
    "wof:name":"DT1 3RN",
    "wof:placetype":"postalcode"
},
  "geometry": {"coordinates":[-2.46515061230387,50.71293208716533],"type":"Point"}
}