{
  "type": "Feature",
  "properties": {
    "iso:country": "GB",
    "wof:name": "DT1 3RN",
    "wof:placetype": "postalcode"
  },
  "geometry": {"coordinates":[-2.465177,50.712941],"type":"Point"}
}
