{
  "type": "Feature",
  "properties": {
    "date:inception_lower": "1980-01-01",
    "date:inception_upper": "1980-01-01",
    "iso:country": "GB",
    "wof:name": "RH17 5SZ",
    "wof:placetype": "postalcode"
  },
  "geometry": {"coordinates":[-0.228455,51.014456],"type":"Point"}
}
