{
  "type": "Feature",
  "properties": {
    "iso:country":"GB",
    "wof:name":"RH17 5SZ",
    "wof:placetype":"postalcode"
},
  "geometry": {"coordinates":[-0.23071445161547,51.0120029595374],"type":"Point"}
}