{
  "type": "Feature",
  "properties": {
    "date:inception_lower": "1996-06-01",
    "date:inception_upper": "1996-06-01",
    "iso:country": "GB",
    "wof:name": "FK5 3HQ",
    "wof:placetype": "postalcode"
  },
  "geometry": {"coordinates":[-3.82346,56.024147],"type":"Point"}
}
