{
  "type": "Feature",
  "properties": {
    "iso:country":"GB",
    "wof:name":"FK5 3HQ",
    "wof:placetype":"postalcode"
},
  "geometry": {"coordinates":[-3.8234601578274,56.02414710418248],"type":"Point"}
}