{
  "type": "Feature",
  "properties": {
    "iso:country": "GB",
    "wof:name": "TD9 8AD",
    "wof:placetype": "postalcode"
  },
  "geometry": {"coordinates":[-2.7806,55.429273],"type":"Point"}
}
