{
  "type": "Feature",
  "properties": {
    "iso:country":"GB",
    "wof:name":"TD9 8AD",
    "wof:placetype":"postalcode"
},
  "geometry": {"coordinates":[-2.78060005208646,55.4292726415431],"type":"Point"}
}