{
  "type": "Feature",
  "properties": {
    "iso:country":"GB",
    "wof:name":"EX17 6BD",
    "wof:placetype":"postalcode"
},
  "geometry": {"coordinates":[-3.83923286738915,50.84560857037968],"type":"Point"}
}