{
  "type": "Feature",
  "properties": {
    "iso:country": "GB",
    "wof:name": "BL4 8SA",
    "wof:placetype": "postalcode"
  },
  "geometry": {"coordinates":[-2.365135,53.535998],"type":"Point"}
}
