{
  "type": "Feature",
  "properties": {
    "date:inception_lower":"1980-01-01",
    "date:inception_upper":"1980-01-31",
    "iso:country":"GB",
    "wof:name":"BL4 8SA",
    "wof:placetype":"postalcode"
},
  "geometry": {"coordinates":[-2.365135,53.535998],"type":"Point"}
}