{
  "type": "Feature",
  "properties": {
    "date:inception_lower":"1980-01-01",
    "date:inception_upper":"1980-01-31",
    "iso:country":"GB",
    "wof:name":"LL59 5NB",
    "wof:placetype":"postalcode"
},
  "geometry": {"coordinates":[-4.176497,53.231543],"type":"Point"}
}