{
  "type": "Feature",
  "properties": {
    "iso:country":"GB",
    "wof:name":"DL17 0BE",
    "wof:placetype":"postalcode"
},
  "geometry": {"coordinates":[-1.55675857484914,54.66489092557765],"type":"Point"}
}