{
  "type": "Feature",
  "properties": {
    "date:inception_lower":"2015-10-01",
    "date:inception_upper":"2015-10-31",
    "iso:country":"GB",
    "wof:name":"DL17 0BE",
    "wof:placetype":"postalcode"
},
  "geometry": {"coordinates":[-1.556759,54.664891],"type":"Point"}
}