{
  "type": "Feature",
  "properties": {
    "iso:country":"GB",
    "wof:name":"PR3 1AQ",
    "wof:placetype":"postalcode"
},
  "geometry": {"coordinates":[-2.76089378480711,53.93442728947078],"type":"Point"}
}