{
  "type": "Feature",
  "properties": {
    "date:inception_lower":"2004-02-01",
    "date:inception_upper":"2004-02-29",
    "iso:country":"GB",
    "wof:name":"PR3 1AQ",
    "wof:placetype":"postalcode"
},
  "geometry": {"coordinates":[-2.760894,53.934427],"type":"Point"}
}