{
  "type": "Feature",
  "properties": {
    "iso:country":"GB",
    "wof:name":"BS13 0LX",
    "wof:placetype":"postalcode"
},
  "geometry": {"coordinates":[-2.59652983689964,51.40639122072869],"type":"Point"}
}