{
  "type": "Feature",
  "properties": {
    "iso:country":"GB",
    "wof:name":"OX44 7LH",
    "wof:placetype":"postalcode"
},
  "geometry": {"coordinates":[-1.0746622316803,51.7011730743923],"type":"Point"}
}