{
  "type": "Feature",
  "properties": {
    "iso:country": "GB",
    "wof:name": "OX44 7LH",
    "wof:placetype": "postalcode"
  },
  "geometry": {"coordinates":[-1.074662,51.701173],"type":"Point"}
}
