{
  "type": "Feature",
  "properties": {
    "date:inception_lower": "1980-01-01",
    "date:inception_upper": "1980-01-01",
    "iso:country": "GB",
    "wof:name": "M33 3JR",
    "wof:placetype": "postalcode"
  },
  "geometry": {"coordinates":[-2.304738,53.414194],"type":"Point"}
}
