{
  "type": "Feature",
  "properties": {
    "date:inception_lower":"1997-12-01",
    "date:inception_upper":"1997-12-31",
    "iso:country":"GB",
    "wof:name":"BS22 7UT",
    "wof:placetype":"postalcode"
},
  "geometry": {"coordinates":[-2.911517,51.368154],"type":"Point"}
}