{
  "type": "Feature",
  "properties": {
    "iso:country":"GB",
    "wof:name":"LN4 4QD",
    "wof:placetype":"postalcode"
},
  "geometry": {"coordinates":[-0.19923014359389,53.06181290843589],"type":"Point"}
}