{
  "type": "Feature",
  "properties": {
    "iso:country":"GB",
    "wof:name":"CB10 2PL",
    "wof:placetype":"postalcode"
},
  "geometry": {"coordinates":[0.38322518587019,52.02055891126719],"type":"Point"}
}