{
  "type": "Feature",
  "properties": {
    "date:inception_lower": "1980-01-01",
    "date:inception_upper": "1980-01-01",
    "iso:country": "GB",
    "wof:name": "LS17 8DZ",
    "wof:placetype": "postalcode"
  },
  "geometry": {"coordinates":[-1.527425,53.853689],"type":"Point"}
}
