{
  "type": "Feature",
  "properties": {
    "iso:country":"GB",
    "wof:name":"SK8 7DW",
    "wof:placetype":"postalcode"
},
  "geometry": {"coordinates":[-2.18343554720613,53.36963370564818],"type":"Point"}
}