{
  "type": "Feature",
  "properties": {
    "date:inception_lower": "1980-01-01",
    "date:inception_upper": "1980-01-01",
    "iso:country": "GB",
    "wof:name": "SK8 7DW",
    "wof:placetype": "postalcode"
  },
  "geometry": {"coordinates":[-2.183436,53.369634],"type":"Point"}
}
