{
  "type": "Feature",
  "properties": {
    "iso:country": "GB",
    "wof:name": "BD20 8NT",
    "wof:placetype": "postalcode"
  },
  "geometry": {"coordinates":[-2.019821,53.918786],"type":"Point"}
}
