{
  "type": "Feature",
  "properties": {
    "iso:country":"GB",
    "wof:name":"BD20 8NT",
    "wof:placetype":"postalcode"
},
  "geometry": {"coordinates":[-2.01972646189621,53.91876287804864],"type":"Point"}
}