{
  "type": "Feature",
  "properties": {
    "date:inception_lower": "1980-01-01",
    "date:inception_upper": "1980-01-01",
    "iso:country": "GB",
    "wof:name": "BD20 8NT",
    "wof:placetype": "postalcode"
  },
  "geometry": {"coordinates":[-2.019821,53.918786],"type":"Point"}
}
