{
  "type": "Feature",
  "properties": {
    "date:inception_lower": "2023-05-01",
    "date:inception_upper": "2023-05-01",
    "iso:country": "GB",
    "wof:name": "CT9 2UP",
    "wof:placetype": "postalcode"
  },
  "geometry": {"coordinates":[1.398253,51.389722],"type":"Point"}
}
