{
  "type": "Feature",
  "properties": {
    "iso:country": "GB",
    "wof:name": "HU5 3BQ",
    "wof:placetype": "postalcode"
  },
  "geometry": {"coordinates":[-0.370328,53.760607],"type":"Point"}
}
