{
  "type": "Feature",
  "properties": {
    "date:inception_lower": "1980-01-01",
    "date:inception_upper": "1980-01-01",
    "iso:country": "GB",
    "wof:name": "BB8 8HG",
    "wof:placetype": "postalcode"
  },
  "geometry": {"coordinates":[-2.165982,53.849434],"type":"Point"}
}
