{
  "type": "Feature",
  "properties": {
    "iso:country":"GB",
    "wof:name":"M24 1NY",
    "wof:placetype":"postalcode"
},
  "geometry": {"coordinates":[-2.20294831301215,53.53472971199669],"type":"Point"}
}