{
  "type": "Feature",
  "properties": {
    "date:inception_lower": "1980-01-01",
    "date:inception_upper": "1980-01-01",
    "iso:country": "GB",
    "wof:name": "M24 1NY",
    "wof:placetype": "postalcode"
  },
  "geometry": {"coordinates":[-2.202976,53.534611],"type":"Point"}
}
