{
  "type": "Feature",
  "properties": {
    "iso:country": "GB",
    "wof:name": "LA13 9FD",
    "wof:placetype": "postalcode"
  },
  "geometry": {"coordinates":[-3.214162,54.120899],"type":"Point"}
}
