{
  "type": "Feature",
  "properties": {
    "date:inception_lower": "1980-01-01",
    "date:inception_upper": "1980-01-01",
    "iso:country": "GB",
    "wof:name": "BS6 5SL",
    "wof:placetype": "postalcode"
  },
  "geometry": {"coordinates":[-2.593665,51.465893],"type":"Point"}
}
