{
  "type": "Feature",
  "properties": {
    "iso:country":"GB",
    "wof:name":"GL17 0DF",
    "wof:placetype":"postalcode"
},
  "geometry": {"coordinates":[-2.48711973533735,51.86452891425765],"type":"Point"}
}