{
  "type": "Feature",
  "properties": {
    "iso:country": "GB",
    "wof:name": "GL17 0DF",
    "wof:placetype": "postalcode"
  },
  "geometry": {"coordinates":[-2.48712,51.864529],"type":"Point"}
}
