{
  "type": "Feature",
  "properties": {
    "iso:country":"GB",
    "wof:name":"LE15 6QL",
    "wof:placetype":"postalcode"
},
  "geometry": {"coordinates":[-0.73018437314248,52.67454395933012],"type":"Point"}
}