{
  "type": "Feature",
  "properties": {
    "iso:country":"GB",
    "wof:name":"B34 6TU",
    "wof:placetype":"postalcode"
},
  "geometry": {"coordinates":[-1.78087107680286,52.49290314813869],"type":"Point"}
}