{
  "type": "Feature",
  "properties": {
    "iso:country": "GB",
    "wof:name": "NG5 9DT",
    "wof:placetype": "postalcode"
  },
  "geometry": {"coordinates":[-1.160365,53.006584],"type":"Point"}
}
