{
  "type": "Feature",
  "properties": {
    "iso:country":"GB",
    "wof:name":"NG5 9DT",
    "wof:placetype":"postalcode"
},
  "geometry": {"coordinates":[-1.16036496613189,53.00658370610189],"type":"Point"}
}