{
  "type": "Feature",
  "properties": {
    "date:inception_lower": "2005-03-01",
    "date:inception_upper": "2005-03-01",
    "iso:country": "GB",
    "wof:name": "SE15 6GS",
    "wof:placetype": "postalcode"
  },
  "geometry": {"coordinates":[-0.079568,51.479219],"type":"Point"}
}
