{
  "type": "Feature",
  "properties": {
    "iso:country":"GB",
    "wof:name":"G46 6HF",
    "wof:placetype":"postalcode"
},
  "geometry": {"coordinates":[-4.29274961710539,55.8065458131944],"type":"Point"}
}