{
  "type": "Feature",
  "properties": {
    "date:inception_lower": "1980-01-01",
    "date:inception_upper": "1980-01-01",
    "iso:country": "GB",
    "wof:name": "BD4 7LP",
    "wof:placetype": "postalcode"
  },
  "geometry": {"coordinates":[-1.739025,53.779807],"type":"Point"}
}
