{
  "type": "Feature",
  "properties": {
    "iso:country":"GB",
    "wof:name":"PO19 5BY",
    "wof:placetype":"postalcode"
},
  "geometry": {"coordinates":[-0.77597611975164,50.85785486227988],"type":"Point"}
}