{
  "type": "Feature",
  "properties": {
    "date:inception_lower":"1994-06-01",
    "date:inception_upper":"1994-06-30",
    "iso:country":"GB",
    "wof:name":"G72 9RP",
    "wof:placetype":"postalcode"
},
  "geometry": {"coordinates":[-4.106489,55.799508],"type":"Point"}
}