{
  "type": "Feature",
  "properties": {
    "iso:country":"GB",
    "wof:name":"RM13 7LS",
    "wof:placetype":"postalcode"
},
  "geometry": {"coordinates":[0.19014527110348,51.54109230093281],"type":"Point"}
}