{
  "type": "Feature",
  "properties": {
    "iso:country": "GB",
    "wof:name": "RM13 7LS",
    "wof:placetype": "postalcode"
  },
  "geometry": {"coordinates":[0.190174,51.541094],"type":"Point"}
}
