{
  "type": "Feature",
  "properties": {
    "iso:country": "GB",
    "wof:name": "LL17 0AD",
    "wof:placetype": "postalcode"
  },
  "geometry": {"coordinates":[-3.426098,53.267097],"type":"Point"}
}
