{
  "type": "Feature",
  "properties": {
    "iso:country":"GB",
    "wof:name":"LL17 0AD",
    "wof:placetype":"postalcode"
},
  "geometry": {"coordinates":[-3.42609842738048,53.26709655174522],"type":"Point"}
}