{
  "type": "Feature",
  "properties": {
    "date:inception_lower": "1980-01-01",
    "date:inception_upper": "1980-01-01",
    "iso:country": "GB",
    "wof:name": "LL17 0AD",
    "wof:placetype": "postalcode"
  },
  "geometry": {"coordinates":[-3.426098,53.267097],"type":"Point"}
}
