{
  "type": "Feature",
  "properties": {
    "date:inception_lower": "1985-10-01",
    "date:inception_upper": "1985-10-01",
    "iso:country": "GB",
    "wof:name": "NR30 5SG",
    "wof:placetype": "postalcode"
  },
  "geometry": {"coordinates":[1.718535,52.657763],"type":"Point"}
}
