{
  "type": "Feature",
  "properties": {
    "iso:country":"GB",
    "wof:name":"DA1 4TL",
    "wof:placetype":"postalcode"
},
  "geometry": {"coordinates":[0.18622865251571,51.46204557403598],"type":"Point"}
}