{
  "type": "Feature",
  "properties": {
    "date:inception_lower":"1984-10-01",
    "date:inception_upper":"1984-10-31",
    "iso:country":"GB",
    "wof:name":"DA1 4TL",
    "wof:placetype":"postalcode"
},
  "geometry": {"coordinates":[0.186229,51.462046],"type":"Point"}
}