{
  "type": "Feature",
  "properties": {
    "date:inception_lower": "2018-11-01",
    "date:inception_upper": "2018-11-01",
    "iso:country": "GB",
    "wof:name": "DG7 1BF",
    "wof:placetype": "postalcode"
  },
  "geometry": {"coordinates":[-3.936652,54.939857],"type":"Point"}
}
