{
  "type": "Feature",
  "properties": {
    "iso:country":"GB",
    "wof:name":"L20 8TL",
    "wof:placetype":"postalcode"
},
  "geometry": {"coordinates":[-2.99482303576584,53.43279280286127],"type":"Point"}
}