{
  "type": "Feature",
  "properties": {
    "date:inception_lower": "2001-06-01",
    "date:inception_upper": "2001-06-01",
    "iso:country": "GB",
    "wof:name": "L20 8TL",
    "wof:placetype": "postalcode"
  },
  "geometry": {"coordinates":[-2.994823,53.432793],"type":"Point"}
}
