{
  "type": "Feature",
  "properties": {
    "date:inception_lower": "1980-01-01",
    "date:inception_upper": "1980-01-01",
    "iso:country": "GB",
    "wof:name": "MK42 8DW",
    "wof:placetype": "postalcode"
  },
  "geometry": {"coordinates":[-0.490318,52.119425],"type":"Point"}
}
