{
  "type": "Feature",
  "properties": {
    "iso:country":"GB",
    "wof:name":"MK42 8DW",
    "wof:placetype":"postalcode"
},
  "geometry": {"coordinates":[-0.49065035605259,52.11930021705944],"type":"Point"}
}