{
  "type": "Feature",
  "properties": {
    "iso:country": "GB",
    "wof:name": "MK42 8DW",
    "wof:placetype": "postalcode"
  },
  "geometry": {"coordinates":[-0.49065,52.1193],"type":"Point"}
}
