{
  "type": "Feature",
  "properties": {
    "iso:country":"GB",
    "wof:name":"NE3 4RA",
    "wof:placetype":"postalcode"
},
  "geometry": {"coordinates":[-1.64839440240422,54.99888555944037],"type":"Point"}
}