{
  "type": "Feature",
  "properties": {
    "iso:country":"GB",
    "wof:name":"RH1 5GJ",
    "wof:placetype":"postalcode"
},
  "geometry": {"coordinates":[-0.1646402863478,51.1998465807994],"type":"Point"}
}