{
  "type": "Feature",
  "properties": {
    "iso:country":"GB",
    "wof:name":"IV30 5TW",
    "wof:placetype":"postalcode"
},
  "geometry": {"coordinates":[-3.44132941455699,57.70661324322815],"type":"Point"}
}