{
  "type": "Feature",
  "properties": {
    "iso:country":"GB",
    "wof:name":"TN13 1JN",
    "wof:placetype":"postalcode"
},
  "geometry": {"coordinates":[0.19436499469511,51.27007930547139],"type":"Point"}
}