{
  "type": "Feature",
  "properties": {
    "iso:country":"GB",
    "wof:name":"RG24 9AG",
    "wof:placetype":"postalcode"
},
  "geometry": {"coordinates":[-1.07673196221354,51.28390984799574],"type":"Point"}
}