{
  "type": "Feature",
  "properties": {
    "iso:country": "GB",
    "wof:name": "RG24 9AG",
    "wof:placetype": "postalcode"
  },
  "geometry": {"coordinates":[-1.076732,51.28391],"type":"Point"}
}
