{
  "type": "Feature",
  "properties": {
    "iso:country":"GB",
    "wof:name":"WV10 7TL",
    "wof:placetype":"postalcode"
},
  "geometry": {"coordinates":[-2.09559639223569,52.64569596526509],"type":"Point"}
}