{
  "type": "Feature",
  "properties": {
    "iso:country": "GB",
    "wof:name": "WV10 7TL",
    "wof:placetype": "postalcode"
  },
  "geometry": {"coordinates":[-2.095596,52.645696],"type":"Point"}
}
