{
  "type": "Feature",
  "properties": {
    "iso:country":"GB",
    "wof:name":"CV37 7EW",
    "wof:placetype":"postalcode"
},
  "geometry": {"coordinates":[-1.68544951295548,52.18800111705141],"type":"Point"}
}