{
  "type": "Feature",
  "properties": {
    "iso:country": "GB",
    "wof:name": "PL21 0BJ",
    "wof:placetype": "postalcode"
  },
  "geometry": {"coordinates":[-3.918866,50.39066],"type":"Point"}
}
