{
  "type": "Feature",
  "properties": {
    "date:inception_lower":"1994-12-01",
    "date:inception_upper":"1994-12-31",
    "iso:country":"GB",
    "wof:name":"HP2 7TS",
    "wof:placetype":"postalcode"
},
  "geometry": {"coordinates":[-0.432982,51.777479],"type":"Point"}
}