{
  "type": "Feature",
  "properties": {
    "iso:country":"GB",
    "wof:name":"NW5 4AS",
    "wof:placetype":"postalcode"
},
  "geometry": {"coordinates":[-0.15345680373347,51.55310996314503],"type":"Point"}
}