{
  "type": "Feature",
  "properties": {
    "iso:country": "GB",
    "wof:name": "NP11 6AG",
    "wof:placetype": "postalcode"
  },
  "geometry": {"coordinates":[-3.085168,51.606099],"type":"Point"}
}
