{
  "type": "Feature",
  "properties": {
    "iso:country":"GB",
    "wof:name":"NP13 2NG",
    "wof:placetype":"postalcode"
},
  "geometry": {"coordinates":[-3.13103878359413,51.72367231742781],"type":"Point"}
}