{
  "type": "Feature",
  "properties": {
    "iso:country": "GB",
    "wof:name": "ML3 9FL",
    "wof:placetype": "postalcode"
  },
  "geometry": {"coordinates":[-4.053957,55.776015],"type":"Point"}
}
