{
  "type": "Feature",
  "properties": {
    "date:inception_lower": "2010-05-01",
    "date:inception_upper": "2010-05-01",
    "iso:country": "GB",
    "wof:name": "ML3 9FL",
    "wof:placetype": "postalcode"
  },
  "geometry": {"coordinates":[-4.053957,55.776015],"type":"Point"}
}
