{
  "type": "Feature",
  "properties": {
    "iso:country":"GB",
    "wof:name":"ML3 9FL",
    "wof:placetype":"postalcode"
},
  "geometry": {"coordinates":[-4.05395679632663,55.77601460485851],"type":"Point"}
}