{
  "type": "Feature",
  "properties": {
    "iso:country":"GB",
    "wof:name":"WF12 7PE",
    "wof:placetype":"postalcode"
},
  "geometry": {"coordinates":[-1.61709247879135,53.70124760879838],"type":"Point"}
}