{
  "type": "Feature",
  "properties": {
    "date:inception_lower": "2019-02-01",
    "date:inception_upper": "2019-02-01",
    "iso:country": "GB",
    "wof:name": "BS49 4FW",
    "wof:placetype": "postalcode"
  },
  "geometry": {"coordinates":[-2.83745,51.396993],"type":"Point"}
}
