{
  "type": "Feature",
  "properties": {
    "iso:country": "GB",
    "wof:name": "BS49 4FW",
    "wof:placetype": "postalcode"
  },
  "geometry": {"coordinates":[-2.837392,51.396966],"type":"Point"}
}
