{
  "type": "Feature",
  "properties": {
    "iso:country":"GB",
    "wof:name":"NR9 4NP",
    "wof:placetype":"postalcode"
},
  "geometry": {"coordinates":[0.94781266266465,52.57453111930555],"type":"Point"}
}