{
  "type": "Feature",
  "properties": {
    "iso:country":"GB",
    "wof:name":"E4 6AX",
    "wof:placetype":"postalcode"
},
  "geometry": {"coordinates":[0.01376917407598,51.63307258105462],"type":"Point"}
}