{
  "type": "Feature",
  "properties": {
    "iso:country": "GB",
    "wof:name": "NE61 1TZ",
    "wof:placetype": "postalcode"
  },
  "geometry": {"coordinates":[-1.680376,55.168119],"type":"Point"}
}
