{
  "type": "Feature",
  "properties": {
    "iso:country": "GB",
    "wof:name": "NR12 9HY",
    "wof:placetype": "postalcode"
  },
  "geometry": {"coordinates":[1.488112,52.80905],"type":"Point"}
}
