{
  "type": "Feature",
  "properties": {
    "iso:country":"GB",
    "wof:name":"NR12 9HY",
    "wof:placetype":"postalcode"
},
  "geometry": {"coordinates":[1.48811176151443,52.8090503496911],"type":"Point"}
}