{
  "type": "Feature",
  "properties": {
    "iso:country": "GB",
    "wof:name": "TR6 0HP",
    "wof:placetype": "postalcode"
  },
  "geometry": {"coordinates":[-5.151982,50.342918],"type":"Point"}
}
