{
  "type": "Feature",
  "properties": {
    "iso:country":"GB",
    "wof:name":"TR6 0HP",
    "wof:placetype":"postalcode"
},
  "geometry": {"coordinates":[-5.15198249851446,50.34291774361951],"type":"Point"}
}