{
  "type": "Feature",
  "properties": {
    "date:inception_lower":"1980-01-01",
    "date:inception_upper":"1980-01-31",
    "iso:country":"GB",
    "wof:name":"TR6 0HP",
    "wof:placetype":"postalcode"
},
  "geometry": {"coordinates":[-5.151982,50.342918],"type":"Point"}
}