{
  "type": "Feature",
  "properties": {
    "date:inception_lower": "2021-09-01",
    "date:inception_upper": "2021-09-01",
    "iso:country": "GB",
    "wof:name": "ME4 4SB",
    "wof:placetype": "postalcode"
  },
  "geometry": {"coordinates":[0.549636,51.398215],"type":"Point"}
}
