{
  "type": "Feature",
  "properties": {
    "iso:country": "GB",
    "wof:name": "GU4 7DU",
    "wof:placetype": "postalcode"
  },
  "geometry": {"coordinates":[-0.52775,51.250058],"type":"Point"}
}
