{
  "type": "Feature",
  "properties": {
    "date:inception_lower": "1981-06-01",
    "date:inception_upper": "1981-06-01",
    "iso:country": "GB",
    "wof:name": "GU4 7DU",
    "wof:placetype": "postalcode"
  },
  "geometry": {"coordinates":[-0.52775,51.250058],"type":"Point"}
}
