{
  "type": "Feature",
  "properties": {
    "iso:country":"GB",
    "wof:name":"GU4 7DU",
    "wof:placetype":"postalcode"
},
  "geometry": {"coordinates":[-0.52775018532359,51.25005833614583],"type":"Point"}
}