{
  "type": "Feature",
  "properties": {
    "iso:country":"GB",
    "wof:name":"HA7 4QX",
    "wof:placetype":"postalcode"
},
  "geometry": {"coordinates":[-0.29456179743554,51.61813747347949],"type":"Point"}
}