{
  "type": "Feature",
  "properties": {
    "iso:country":"GB",
    "wof:name":"OX11 9BZ",
    "wof:placetype":"postalcode"
},
  "geometry": {"coordinates":[-1.2215195317933,51.60506736728156],"type":"Point"}
}