{
  "type": "Feature",
  "properties": {
    "iso:country": "GB",
    "wof:name": "OX11 9BZ",
    "wof:placetype": "postalcode"
  },
  "geometry": {"coordinates":[-1.221519,51.605067],"type":"Point"}
}
