{
  "type": "Feature",
  "properties": {
    "date:inception_lower": "1992-08-01",
    "date:inception_upper": "1992-08-01",
    "iso:country": "GB",
    "wof:name": "OX11 9BZ",
    "wof:placetype": "postalcode"
  },
  "geometry": {"coordinates":[-1.221519,51.605067],"type":"Point"}
}
