{
  "type": "Feature",
  "properties": {
    "date:inception_lower":"2015-07-01",
    "date:inception_upper":"2015-07-31",
    "iso:country":"GB",
    "wof:name":"WV12 4JL",
    "wof:placetype":"postalcode"
},
  "geometry": {"coordinates":[-2.047701,52.596596],"type":"Point"}
}