{
  "type": "Feature",
  "properties": {
    "iso:country":"GB",
    "wof:name":"IP28 8GB",
    "wof:placetype":"postalcode"
},
  "geometry": {"coordinates":[0.50103473076213,52.30953757709732],"type":"Point"}
}