{
  "type": "Feature",
  "properties": {
    "date:inception_lower":"2009-01-01",
    "date:inception_upper":"2009-01-31",
    "iso:country":"GB",
    "wof:name":"IP28 8GB",
    "wof:placetype":"postalcode"
},
  "geometry": {"coordinates":[0.501035,52.309538],"type":"Point"}
}