{
  "type": "Feature",
  "properties": {
    "iso:country":"GB",
    "wof:name":"FK4 1UR",
    "wof:placetype":"postalcode"
},
  "geometry": {"coordinates":[-3.90491040492245,55.99933513149484],"type":"Point"}
}