{
  "type": "Feature",
  "properties": {
    "date:inception_lower": "2010-02-01",
    "date:inception_upper": "2010-02-01",
    "iso:country": "GB",
    "wof:name": "FK4 1UR",
    "wof:placetype": "postalcode"
  },
  "geometry": {"coordinates":[-3.90491,55.999335],"type":"Point"}
}
