{
  "type": "Feature",
  "properties": {
    "iso:country":"GB",
    "wof:name":"SR5 5PZ",
    "wof:placetype":"postalcode"
},
  "geometry": {"coordinates":[-1.42451923968036,54.92413823098989],"type":"Point"}
}