{
  "type": "Feature",
  "properties": {
    "iso:country": "GB",
    "wof:name": "NR4 7JR",
    "wof:placetype": "postalcode"
  },
  "geometry": {"coordinates":[1.233397,52.606892],"type":"Point"}
}
