{
  "type": "Feature",
  "properties": {
    "iso:country":"GB",
    "wof:name":"NR4 7JR",
    "wof:placetype":"postalcode"
},
  "geometry": {"coordinates":[1.23315301182256,52.60664927638455],"type":"Point"}
}