{
  "type": "Feature",
  "properties": {
    "iso:country": "GB",
    "wof:name": "AB56 1BY",
    "wof:placetype": "postalcode"
  },
  "geometry": {"coordinates":[-2.975194,57.672275],"type":"Point"}
}
