{
  "type": "Feature",
  "properties": {
    "iso:country":"GB",
    "wof:name":"AB56 1BY",
    "wof:placetype":"postalcode"
},
  "geometry": {"coordinates":[-2.97519436332556,57.67227497149031],"type":"Point"}
}