{
  "type": "Feature",
  "properties": {
    "iso:country":"GB",
    "wof:name":"EX31 2PQ",
    "wof:placetype":"postalcode"
},
  "geometry": {"coordinates":[-4.12295842781338,51.06957725214429],"type":"Point"}
}