{
  "type": "Feature",
  "properties": {
    "date:inception_lower":"1981-06-01",
    "date:inception_upper":"1981-06-30",
    "iso:country":"GB",
    "wof:name":"EX31 2PQ",
    "wof:placetype":"postalcode"
},
  "geometry": {"coordinates":[-4.122958,51.069577],"type":"Point"}
}