{
  "type": "Feature",
  "properties": {
    "iso:country":"GB",
    "wof:name":"DL7 0PF",
    "wof:placetype":"postalcode"
},
  "geometry": {"coordinates":[-1.46996502734538,54.32980263700484],"type":"Point"}
}