{
  "type": "Feature",
  "properties": {
    "date:inception_lower": "1995-07-01",
    "date:inception_upper": "1995-07-01",
    "iso:country": "GB",
    "wof:name": "CF83 3EG",
    "wof:placetype": "postalcode"
  },
  "geometry": {"coordinates":[-3.171604,51.577521],"type":"Point"}
}
