{
  "type": "Feature",
  "properties": {
    "iso:country":"GB",
    "wof:name":"CF83 3EG",
    "wof:placetype":"postalcode"
},
  "geometry": {"coordinates":[-3.17149465931208,51.57755696180044],"type":"Point"}
}