{
  "type": "Feature",
  "properties": {
    "iso:country":"GB",
    "wof:name":"SP1 2RJ",
    "wof:placetype":"postalcode"
},
  "geometry": {"coordinates":[-1.78092583429796,51.06728261639291],"type":"Point"}
}