{
  "type": "Feature",
  "properties": {
    "iso:country": "GB",
    "wof:name": "DA8 1FN",
    "wof:placetype": "postalcode"
  },
  "geometry": {"coordinates":[0.164009,51.48111],"type":"Point"}
}
