{
  "type": "Feature",
  "properties": {
    "date:inception_lower": "2018-11-01",
    "date:inception_upper": "2018-11-01",
    "iso:country": "GB",
    "wof:name": "DA8 1FN",
    "wof:placetype": "postalcode"
  },
  "geometry": {"coordinates":[0.163784,51.481222],"type":"Point"}
}
