{
  "type": "Feature",
  "properties": {
    "iso:country":"GB",
    "wof:name":"NG25 0EP",
    "wof:placetype":"postalcode"
},
  "geometry": {"coordinates":[-0.9508475342388,53.08003663966553],"type":"Point"}
}