{
  "type": "Feature",
  "properties": {
    "iso:country":"GB",
    "wof:name":"RG9 3JW",
    "wof:placetype":"postalcode"
},
  "geometry": {"coordinates":[-0.88944704086411,51.51146262132995],"type":"Point"}
}