{
  "type": "Feature",
  "properties": {
    "iso:country": "GB",
    "wof:name": "PE7 3GJ",
    "wof:placetype": "postalcode"
  },
  "geometry": {"coordinates":[-0.261534,52.52138],"type":"Point"}
}
