{
  "type": "Feature",
  "properties": {
    "iso:country":"GB",
    "wof:name":"M33 5GY",
    "wof:placetype":"postalcode"
},
  "geometry": {"coordinates":[-2.33854597043091,53.43149536775486],"type":"Point"}
}