{
  "type": "Feature",
  "properties": {
    "date:inception_lower": "1994-05-01",
    "date:inception_upper": "1994-05-01",
    "iso:country": "GB",
    "wof:name": "M33 5GY",
    "wof:placetype": "postalcode"
  },
  "geometry": {"coordinates":[-2.338546,53.431495],"type":"Point"}
}
