{
  "type": "Feature",
  "properties": {
    "iso:country":"GB",
    "wof:name":"B26 3YJ",
    "wof:placetype":"postalcode"
},
  "geometry": {"coordinates":[-1.77855481949072,52.46137997352123],"type":"Point"}
}