{
  "type": "Feature",
  "properties": {
    "date:inception_lower": "1980-01-01",
    "date:inception_upper": "1980-01-01",
    "iso:country": "GB",
    "wof:name": "B26 3YJ",
    "wof:placetype": "postalcode"
  },
  "geometry": {"coordinates":[-1.778224,52.461601],"type":"Point"}
}
