{
  "type": "Feature",
  "properties": {
    "iso:country":"GB",
    "wof:name":"CF39 9HY",
    "wof:placetype":"postalcode"
},
  "geometry": {"coordinates":[-3.40385978737201,51.60717094567588],"type":"Point"}
}