{
  "type": "Feature",
  "properties": {
    "iso:country":"GB",
    "wof:name":"M4 5HU",
    "wof:placetype":"postalcode"
},
  "geometry": {"coordinates":[-2.22906191544718,53.48672032974235],"type":"Point"}
}