{
  "type": "Feature",
  "properties": {
    "date:inception_lower": "1986-07-01",
    "date:inception_upper": "1986-07-01",
    "iso:country": "GB",
    "wof:name": "M4 5HU",
    "wof:placetype": "postalcode"
  },
  "geometry": {"coordinates":[-2.229062,53.48672],"type":"Point"}
}
