{
  "type": "Feature",
  "properties": {
    "iso:country": "GB",
    "wof:name": "CW8 4JZ",
    "wof:placetype": "postalcode"
  },
  "geometry": {"coordinates":[-2.541714,53.271196],"type":"Point"}
}
