{
  "type": "Feature",
  "properties": {
    "iso:country":"GB",
    "wof:name":"WA7 3EH",
    "wof:placetype":"postalcode"
},
  "geometry": {"coordinates":[-2.70054660762853,53.30742971414143],"type":"Point"}
}