{
  "type": "Feature",
  "properties": {
    "iso:country": "GB",
    "wof:name": "S4 7SA",
    "wof:placetype": "postalcode"
  },
  "geometry": {"coordinates":[-1.449477,53.398529],"type":"Point"}
}
