{
  "type": "Feature",
  "properties": {
    "iso:country":"GB",
    "wof:name":"S4 7SA",
    "wof:placetype":"postalcode"
},
  "geometry": {"coordinates":[-1.44693522496189,53.39741173372296],"type":"Point"}
}