{
  "type": "Feature",
  "properties": {
    "date:inception_lower":"2006-08-01",
    "date:inception_upper":"2006-08-31",
    "iso:country":"GB",
    "wof:name":"S4 7SA",
    "wof:placetype":"postalcode"
},
  "geometry": {"coordinates":[-1.449477,53.398529],"type":"Point"}
}