{
  "type": "Feature",
  "properties": {
    "iso:country":"GB",
    "wof:name":"SG1 6GW",
    "wof:placetype":"postalcode"
},
  "geometry": {"coordinates":[-0.17681776150572,51.93288094024391],"type":"Point"}
}