{
  "type": "Feature",
  "properties": {
    "iso:country":"GB",
    "wof:name":"EH26 0HF",
    "wof:placetype":"postalcode"
},
  "geometry": {"coordinates":[-3.22201151222498,55.83718911815198],"type":"Point"}
}