{
  "type": "Feature",
  "properties": {
    "iso:country":"GB",
    "wof:name":"BL5 3RW",
    "wof:placetype":"postalcode"
},
  "geometry": {"coordinates":[-2.52890093233519,53.54572219886068],"type":"Point"}
}