{
  "type": "Feature",
  "properties": {
    "iso:country":"GB",
    "wof:name":"CO3 3EN",
    "wof:placetype":"postalcode"
},
  "geometry": {"coordinates":[0.89483385675965,51.88777826252629],"type":"Point"}
}