{
  "type": "Feature",
  "properties": {
    "iso:country":"GB",
    "wof:name":"HA5 3UF",
    "wof:placetype":"postalcode"
},
  "geometry": {"coordinates":[-0.40416980253749,51.5995991965255],"type":"Point"}
}