{
  "type": "Feature",
  "properties": {
    "iso:country":"GB",
    "wof:name":"NG5 5LL",
    "wof:placetype":"postalcode"
},
  "geometry": {"coordinates":[-1.16148288908211,53.00118894839535],"type":"Point"}
}