{
  "type": "Feature",
  "properties": {
    "iso:country":"GB",
    "wof:name":"SA3 5AZ",
    "wof:placetype":"postalcode"
},
  "geometry": {"coordinates":[-4.00146310031717,51.60025339851926],"type":"Point"}
}