{
  "type": "Feature",
  "properties": {
    "iso:country":"GB",
    "wof:name":"CV5 6PJ",
    "wof:placetype":"postalcode"
},
  "geometry": {"coordinates":[-1.52693978686842,52.39785496346948],"type":"Point"}
}