{
  "type": "Feature",
  "properties": {
    "date:inception_lower": "1980-01-01",
    "date:inception_upper": "1980-01-01",
    "iso:country": "GB",
    "wof:name": "CV5 6PJ",
    "wof:placetype": "postalcode"
  },
  "geometry": {"coordinates":[-1.52694,52.397855],"type":"Point"}
}
