{
  "type": "Feature",
  "properties": {
    "iso:country":"GB",
    "wof:name":"YO25 6EB",
    "wof:placetype":"postalcode"
},
  "geometry": {"coordinates":[-0.4393789860825,54.00929116523514],"type":"Point"}
}