{
  "type": "Feature",
  "properties": {
    "iso:country":"GB",
    "wof:name":"B62 9NN",
    "wof:placetype":"postalcode"
},
  "geometry": {"coordinates":[-2.02197761137976,52.4683900725995],"type":"Point"}
}