{
  "type": "Feature",
  "properties": {
    "iso:country":"GB",
    "wof:name":"NN16 8YD",
    "wof:placetype":"postalcode"
},
  "geometry": {"coordinates":[-0.72122203891265,52.40199205879708],"type":"Point"}
}