{
  "type": "Feature",
  "properties": {
    "iso:country":"GB",
    "wof:name":"N1 7PE",
    "wof:placetype":"postalcode"
},
  "geometry": {"coordinates":[-0.08752244556004,51.53210828917467],"type":"Point"}
}