{
  "type": "Feature",
  "properties": {
    "date:inception_lower": "2020-11-01",
    "date:inception_upper": "2020-11-01",
    "iso:country": "GB",
    "wof:name": "CB24 4AL",
    "wof:placetype": "postalcode"
  },
  "geometry": {"coordinates":[-0.008108,52.296346],"type":"Point"}
}
