{
  "type": "Feature",
  "properties": {
    "iso:country":"GB",
    "wof:name":"PE25 2TS",
    "wof:placetype":"postalcode"
},
  "geometry": {"coordinates":[0.34059577177445,53.14891718434566],"type":"Point"}
}