{
  "type": "Feature",
  "properties": {
    "date:inception_lower": "1996-12-01",
    "date:inception_upper": "1996-12-01",
    "iso:country": "GB",
    "wof:name": "LN4 2TA",
    "wof:placetype": "postalcode"
  },
  "geometry": {"coordinates":[-0.532821,53.198467],"type":"Point"}
}
