{
  "type": "Feature",
  "properties": {
    "iso:country":"GB",
    "wof:name":"LN4 2TA",
    "wof:placetype":"postalcode"
},
  "geometry": {"coordinates":[-0.5328222050233,53.19844500396281],"type":"Point"}
}