{
  "type": "Feature",
  "properties": {
    "iso:country":"GB",
    "wof:name":"SM6 9NJ",
    "wof:placetype":"postalcode"
},
  "geometry": {"coordinates":[-0.13983875933333,51.34882592016984],"type":"Point"}
}