{
  "type": "Feature",
  "properties": {
    "date:inception_lower": "1980-01-01",
    "date:inception_upper": "1980-01-01",
    "iso:country": "GB",
    "wof:name": "SM6 9NJ",
    "wof:placetype": "postalcode"
  },
  "geometry": {"coordinates":[-0.139839,51.348826],"type":"Point"}
}
