{
  "type": "Feature",
  "properties": {
    "iso:country":"GB",
    "wof:name":"DL15 9AP",
    "wof:placetype":"postalcode"
},
  "geometry": {"coordinates":[-1.72575088199239,54.74697151245591],"type":"Point"}
}