{
  "type": "Feature",
  "properties": {
    "iso:country": "GB",
    "wof:name": "DL15 9AP",
    "wof:placetype": "postalcode"
  },
  "geometry": {"coordinates":[-1.725751,54.746972],"type":"Point"}
}
