{
  "type": "Feature",
  "properties": {
    "iso:country": "GB",
    "wof:name": "SK14 5NR",
    "wof:placetype": "postalcode"
  },
  "geometry": {"coordinates":[-2.062455,53.443608],"type":"Point"}
}
