{
  "type": "Feature",
  "properties": {
    "date:inception_lower": "1980-01-01",
    "date:inception_upper": "1980-01-01",
    "iso:country": "GB",
    "wof:name": "SK14 5NR",
    "wof:placetype": "postalcode"
  },
  "geometry": {"coordinates":[-2.062455,53.443608],"type":"Point"}
}
