{
  "type": "Feature",
  "properties": {
    "iso:country":"GB",
    "wof:name":"SK14 5NR",
    "wof:placetype":"postalcode"
},
  "geometry": {"coordinates":[-2.06245507791579,53.44360848270308],"type":"Point"}
}