{
  "type": "Feature",
  "properties": {
    "date:inception_lower": "1992-08-01",
    "date:inception_upper": "1992-08-01",
    "iso:country": "GB",
    "wof:name": "LE1 3WL",
    "wof:placetype": "postalcode"
  },
  "geometry": {"coordinates":[-1.133566,52.640727],"type":"Point"}
}
