{
  "type": "Feature",
  "properties": {
    "date:inception_lower": "1980-01-01",
    "date:inception_upper": "1980-01-01",
    "iso:country": "GB",
    "wof:name": "KW1 4PB",
    "wof:placetype": "postalcode"
  },
  "geometry": {"coordinates":[-3.085338,58.444602],"type":"Point"}
}
