{
  "type": "Feature",
  "properties": {
    "iso:country":"GB",
    "wof:name":"NW9 0XH",
    "wof:placetype":"postalcode"
},
  "geometry": {"coordinates":[-0.26025470325936,51.58376026741229],"type":"Point"}
}