{
  "type": "Feature",
  "properties": {
    "iso:country":"GB",
    "wof:name":"DH9 8NQ",
    "wof:placetype":"postalcode"
},
  "geometry": {"coordinates":[-1.75085075664131,54.85650787453287],"type":"Point"}
}