{
  "type": "Feature",
  "properties": {
    "iso:country":"GB",
    "wof:name":"EX21 5XB",
    "wof:placetype":"postalcode"
},
  "geometry": {"coordinates":[-4.2072979254217,50.77549340445992],"type":"Point"}
}