{
  "type": "Feature",
  "properties": {
    "iso:country": "GB",
    "wof:name": "EX21 5XB",
    "wof:placetype": "postalcode"
  },
  "geometry": {"coordinates":[-4.207249,50.77535],"type":"Point"}
}
