{
  "type": "Feature",
  "properties": {
    "date:inception_lower":"1998-06-01",
    "date:inception_upper":"1998-06-30",
    "iso:country":"GB",
    "wof:name":"PE6 7WG",
    "wof:placetype":"postalcode"
},
  "geometry": {"coordinates":[-0.195487,52.605446],"type":"Point"}
}