{
  "type": "Feature",
  "properties": {
    "iso:country":"GB",
    "wof:name":"PE6 7WG",
    "wof:placetype":"postalcode"
},
  "geometry": {"coordinates":[-0.19548711625683,52.60544634414031],"type":"Point"}
}