{
  "type": "Feature",
  "properties": {
    "iso:country":"GB",
    "wof:name":"PE28 5QH",
    "wof:placetype":"postalcode"
},
  "geometry": {"coordinates":[-0.28632347347427,52.43276689457316],"type":"Point"}
}