{
  "type": "Feature",
  "properties": {
    "date:inception_lower": "2022-05-01",
    "date:inception_upper": "2022-05-01",
    "iso:country": "GB",
    "wof:name": "CO6 3FG",
    "wof:placetype": "postalcode"
  },
  "geometry": {"coordinates":[0.854948,51.91633],"type":"Point"}
}
