{
  "type": "Feature",
  "properties": {
    "iso:country": "GB",
    "wof:name": "SO21 2PW",
    "wof:placetype": "postalcode"
  },
  "geometry": {"coordinates":[-1.3786,51.116131],"type":"Point"}
}
