{
  "type": "Feature",
  "properties": {
    "date:inception_lower": "1980-01-01",
    "date:inception_upper": "1980-01-01",
    "iso:country": "GB",
    "wof:name": "SR4 9JP",
    "wof:placetype": "postalcode"
  },
  "geometry": {"coordinates":[-1.478635,54.889829],"type":"Point"}
}
