{
  "type": "Feature",
  "properties": {
    "iso:country":"GB",
    "wof:name":"SR4 9JP",
    "wof:placetype":"postalcode"
},
  "geometry": {"coordinates":[-1.47862153301216,54.88982044827792],"type":"Point"}
}