{
  "type": "Feature",
  "properties": {
    "date:inception_lower": "1980-01-01",
    "date:inception_upper": "1980-01-01",
    "iso:country": "GB",
    "wof:name": "PE12 8JB",
    "wof:placetype": "postalcode"
  },
  "geometry": {"coordinates":[0.041816,52.809813],"type":"Point"}
}
