{
  "type": "Feature",
  "properties": {
    "iso:country":"GB",
    "wof:name":"MK10 9EJ",
    "wof:placetype":"postalcode"
},
  "geometry": {"coordinates":[-0.69622561573995,52.03630945687669],"type":"Point"}
}