{
  "type": "Feature",
  "properties": {
    "date:inception_lower": "1993-01-01",
    "date:inception_upper": "1993-01-01",
    "iso:country": "GB",
    "wof:name": "MK10 9EJ",
    "wof:placetype": "postalcode"
  },
  "geometry": {"coordinates":[-0.696226,52.036309],"type":"Point"}
}
