{
  "type": "Feature",
  "properties": {
    "iso:country": "GB",
    "wof:name": "MK10 9EJ",
    "wof:placetype": "postalcode"
  },
  "geometry": {"coordinates":[-0.696226,52.036309],"type":"Point"}
}
