{
  "type": "Feature",
  "properties": {
    "iso:country": "GB",
    "wof:name": "DA5 2HX",
    "wof:placetype": "postalcode"
  },
  "geometry": {"coordinates":[0.174984,51.4272],"type":"Point"}
}
