{
  "type": "Feature",
  "properties": {
    "iso:country":"GB",
    "wof:name":"LS11 5BJ",
    "wof:placetype":"postalcode"
},
  "geometry": {"coordinates":[-1.54217965842671,53.79294235491777],"type":"Point"}
}