{
  "type": "Feature",
  "properties": {
    "iso:country": "GB",
    "wof:name": "LS11 5BJ",
    "wof:placetype": "postalcode"
  },
  "geometry": {"coordinates":[-1.54238,53.79171],"type":"Point"}
}
