{
  "type": "Feature",
  "properties": {
    "date:inception_lower": "1980-01-01",
    "date:inception_upper": "1980-01-01",
    "iso:country": "GB",
    "wof:name": "LS11 5BJ",
    "wof:placetype": "postalcode"
  },
  "geometry": {"coordinates":[-1.54238,53.79171],"type":"Point"}
}
