{
  "type": "Feature",
  "properties": {
    "iso:country":"GB",
    "wof:name":"SE26 4EU",
    "wof:placetype":"postalcode"
},
  "geometry": {"coordinates":[-0.0422366706209,51.42781963487904],"type":"Point"}
}