{
  "type": "Feature",
  "properties": {
    "iso:country": "GB",
    "wof:name": "SE21 8PL",
    "wof:placetype": "postalcode"
  },
  "geometry": {"coordinates":[-0.083433,51.430308],"type":"Point"}
}
