{
  "type": "Feature",
  "properties": {
    "iso:country":"GB",
    "wof:name":"PL1 4JU",
    "wof:placetype":"postalcode"
},
  "geometry": {"coordinates":[-4.17557845057467,50.36812403957115],"type":"Point"}
}