{
  "type": "Feature",
  "properties": {
    "date:inception_lower": "1980-01-01",
    "date:inception_upper": "1980-01-01",
    "iso:country": "GB",
    "wof:name": "PH15 2BP",
    "wof:placetype": "postalcode"
  },
  "geometry": {"coordinates":[-3.873041,56.61935],"type":"Point"}
}
