{
  "type": "Feature",
  "properties": {
    "date:inception_lower": "2020-10-01",
    "date:inception_upper": "2020-10-01",
    "iso:country": "GB",
    "wof:name": "YO7 1UL",
    "wof:placetype": "postalcode"
  },
  "geometry": {"coordinates":[-1.342091,54.236589],"type":"Point"}
}
