{
  "type": "Feature",
  "properties": {
    "iso:country":"GB",
    "wof:name":"PH2 6EQ",
    "wof:placetype":"postalcode"
},
  "geometry": {"coordinates":[-3.39993084662142,56.55930117011641],"type":"Point"}
}