{
  "type": "Feature",
  "properties": {
    "iso:country": "GB",
    "wof:name": "PH2 6EQ",
    "wof:placetype": "postalcode"
  },
  "geometry": {"coordinates":[-3.400236,56.560977],"type":"Point"}
}
