{
  "type": "Feature",
  "properties": {
    "date:inception_lower": "1986-07-01",
    "date:inception_upper": "1986-07-01",
    "iso:country": "GB",
    "wof:name": "PO38 3DR",
    "wof:placetype": "postalcode"
  },
  "geometry": {"coordinates":[-1.255731,50.632842],"type":"Point"}
}
