{
  "type": "Feature",
  "properties": {
    "iso:country":"GB",
    "wof:name":"PO38 3DR",
    "wof:placetype":"postalcode"
},
  "geometry": {"coordinates":[-1.25531385461809,50.63300350614822],"type":"Point"}
}