{
  "type": "Feature",
  "properties": {
    "iso:country":"GB",
    "wof:name":"HA6 2BH",
    "wof:placetype":"postalcode"
},
  "geometry": {"coordinates":[-0.4327888892501,51.61508244935263],"type":"Point"}
}