{
  "type": "Feature",
  "properties": {
    "date:inception_lower":"1987-10-01",
    "date:inception_upper":"1987-10-31",
    "iso:country":"GB",
    "wof:name":"WA7 4DX",
    "wof:placetype":"postalcode"
},
  "geometry": {"coordinates":[-2.748348,53.332461],"type":"Point"}
}