{
  "type": "Feature",
  "properties": {
    "iso:country":"GB",
    "wof:name":"WA7 4DX",
    "wof:placetype":"postalcode"
},
  "geometry": {"coordinates":[-2.74834835061622,53.33246103656667],"type":"Point"}
}