{
  "type": "Feature",
  "properties": {
    "iso:country":"GB",
    "wof:name":"RG22 5AR",
    "wof:placetype":"postalcode"
},
  "geometry": {"coordinates":[-1.13620918574765,51.2540963917435],"type":"Point"}
}