{
  "type": "Feature",
  "properties": {
    "date:inception_lower": "1993-01-01",
    "date:inception_upper": "1993-01-01",
    "iso:country": "GB",
    "wof:name": "BA11 3QN",
    "wof:placetype": "postalcode"
  },
  "geometry": {"coordinates":[-2.391677,51.238309],"type":"Point"}
}
