{
  "type": "Feature",
  "properties": {
    "iso:country":"GB",
    "wof:name":"PO2 0PA",
    "wof:placetype":"postalcode"
},
  "geometry": {"coordinates":[-1.07737593748506,50.81857617236712],"type":"Point"}
}