{
  "type": "Feature",
  "properties": {
    "iso:country": "GB",
    "wof:name": "GL7 5TD",
    "wof:placetype": "postalcode"
  },
  "geometry": {"coordinates":[-1.895064,51.718192],"type":"Point"}
}
