{
  "type": "Feature",
  "properties": {
    "date:inception_lower": "1980-01-01",
    "date:inception_upper": "1980-01-01",
    "iso:country": "GB",
    "wof:name": "GL7 5TD",
    "wof:placetype": "postalcode"
  },
  "geometry": {"coordinates":[-1.895064,51.718192],"type":"Point"}
}
