{
  "type": "Feature",
  "properties": {
    "iso:country":"GB",
    "wof:name":"GL7 5TD",
    "wof:placetype":"postalcode"
},
  "geometry": {"coordinates":[-1.89506386591361,51.71819197246108],"type":"Point"}
}