{
  "type": "Feature",
  "properties": {
    "date:inception_lower": "1995-07-01",
    "date:inception_upper": "1995-07-01",
    "iso:country": "GB",
    "wof:name": "CO6 2QP",
    "wof:placetype": "postalcode"
  },
  "geometry": {"coordinates":[0.755303,51.922607],"type":"Point"}
}
