{
  "type": "Feature",
  "properties": {
    "iso:country":"GB",
    "wof:name":"TN24 8LG",
    "wof:placetype":"postalcode"
},
  "geometry": {"coordinates":[0.8721906092721,51.1503325927272],"type":"Point"}
}