{
  "type": "Feature",
  "properties": {
    "iso:country": "GB",
    "wof:name": "TN29 9NB",
    "wof:placetype": "postalcode"
  },
  "geometry": {"coordinates":[0.970588,50.912095],"type":"Point"}
}
