{
  "type": "Feature",
  "properties": {
    "iso:country":"GB",
    "wof:name":"TN29 9NB",
    "wof:placetype":"postalcode"
},
  "geometry": {"coordinates":[0.97058807218725,50.91209487037102],"type":"Point"}
}