{
  "type": "Feature",
  "properties": {
    "date:inception_lower": "2008-01-01",
    "date:inception_upper": "2008-01-01",
    "iso:country": "GB",
    "wof:name": "DE73 5UH",
    "wof:placetype": "postalcode"
  },
  "geometry": {"coordinates":[-1.43992,52.861701],"type":"Point"}
}
