{
  "type": "Feature",
  "properties": {
    "iso:country":"GB",
    "wof:name":"KT15 2TH",
    "wof:placetype":"postalcode"
},
  "geometry": {"coordinates":[-0.49825516906213,51.37506505385437],"type":"Point"}
}