{
  "type": "Feature",
  "properties": {
    "date:inception_lower": "1980-01-01",
    "date:inception_upper": "1980-01-01",
    "iso:country": "GB",
    "wof:name": "SK8 4QL",
    "wof:placetype": "postalcode"
  },
  "geometry": {"coordinates":[-2.224257,53.384485],"type":"Point"}
}
