{
  "type": "Feature",
  "properties": {
    "iso:country": "GB",
    "wof:name": "SK8 4QL",
    "wof:placetype": "postalcode"
  },
  "geometry": {"coordinates":[-2.224257,53.384485],"type":"Point"}
}
