{
  "type": "Feature",
  "properties": {
    "iso:country": "GB",
    "wof:name": "YO17 7YP",
    "wof:placetype": "postalcode"
  },
  "geometry": {"coordinates":[-0.794583,54.139697],"type":"Point"}
}
