{
  "type": "Feature",
  "properties": {
    "iso:country":"GB",
    "wof:name":"YO17 7YP",
    "wof:placetype":"postalcode"
},
  "geometry": {"coordinates":[-0.79458266882796,54.1396968292842],"type":"Point"}
}