{
  "type": "Feature",
  "properties": {
    "iso:country":"GB",
    "wof:name":"HU7 0BS",
    "wof:placetype":"postalcode"
},
  "geometry": {"coordinates":[-0.33162135066965,53.77173941352407],"type":"Point"}
}