{
  "type": "Feature",
  "properties": {
    "iso:country":"GB",
    "wof:name":"SW6 7SJ",
    "wof:placetype":"postalcode"
},
  "geometry": {"coordinates":[-0.20397849537026,51.48295293890264],"type":"Point"}
}