{
  "type": "Feature",
  "properties": {
    "iso:country":"GB",
    "wof:name":"GU34 4PN",
    "wof:placetype":"postalcode"
},
  "geometry": {"coordinates":[-0.89430992450776,51.1770035399873],"type":"Point"}
}