{
  "type": "Feature",
  "properties": {
    "date:inception_lower": "2020-06-01",
    "date:inception_upper": "2020-06-01",
    "iso:country": "GB",
    "wof:name": "CW11 4AS",
    "wof:placetype": "postalcode"
  },
  "geometry": {"coordinates":[-2.348156,53.150379],"type":"Point"}
}
