{
  "type": "Feature",
  "properties": {
    "date:inception_lower":"2013-03-01",
    "date:inception_upper":"2013-03-31",
    "iso:country":"GB",
    "wof:name":"LE14 2BY",
    "wof:placetype":"postalcode"
},
  "geometry": {"coordinates":[-0.842681,52.685657],"type":"Point"}
}