{
  "type": "Feature",
  "properties": {
    "iso:country":"GB",
    "wof:name":"LE14 2BY",
    "wof:placetype":"postalcode"
},
  "geometry": {"coordinates":[-0.84268149560022,52.68565667606455],"type":"Point"}
}