{
  "type": "Feature",
  "properties": {
    "iso:country": "GB",
    "wof:name": "EX8 2EQ",
    "wof:placetype": "postalcode"
  },
  "geometry": {"coordinates":[-3.397801,50.620887],"type":"Point"}
}
