{
  "type": "Feature",
  "properties": {
    "iso:country":"GB",
    "wof:name":"OL11 1DX",
    "wof:placetype":"postalcode"
},
  "geometry": {"coordinates":[-2.15433184116293,53.61211983216438],"type":"Point"}
}