{
  "type": "Feature",
  "properties": {
    "date:inception_lower": "1980-01-01",
    "date:inception_upper": "1980-01-01",
    "iso:country": "GB",
    "wof:name": "OX10 9PG",
    "wof:placetype": "postalcode"
  },
  "geometry": {"coordinates":[-1.150694,51.576325],"type":"Point"}
}
