{
  "type": "Feature",
  "properties": {
    "iso:country": "GB",
    "wof:name": "OX10 9PG",
    "wof:placetype": "postalcode"
  },
  "geometry": {"coordinates":[-1.150694,51.576325],"type":"Point"}
}
