{
  "type": "Feature",
  "properties": {
    "date:inception_lower": "1987-04-01",
    "date:inception_upper": "1987-04-01",
    "iso:country": "GB",
    "wof:name": "CA1 2SH",
    "wof:placetype": "postalcode"
  },
  "geometry": {"coordinates":[-2.899609,54.892027],"type":"Point"}
}
