{
  "type": "Feature",
  "properties": {
    "iso:country":"GB",
    "wof:name":"NW9 5QQ",
    "wof:placetype":"postalcode"
},
  "geometry": {"coordinates":[-0.25010556875143,51.60296974417775],"type":"Point"}
}