{
  "type": "Feature",
  "properties": {
    "date:inception_lower":"2012-02-01",
    "date:inception_upper":"2012-02-29",
    "iso:country":"GB",
    "wof:name":"NW9 5QQ",
    "wof:placetype":"postalcode"
},
  "geometry": {"coordinates":[-0.250106,51.60297],"type":"Point"}
}