{
  "type": "Feature",
  "properties": {
    "iso:country":"GB",
    "wof:name":"LS8 3AN",
    "wof:placetype":"postalcode"
},
  "geometry": {"coordinates":[-1.50851477884314,53.81722970173011],"type":"Point"}
}