{
  "type": "Feature",
  "properties": {
    "date:inception_lower": "1980-01-01",
    "date:inception_upper": "1980-01-01",
    "iso:country": "GB",
    "wof:name": "LS8 3AN",
    "wof:placetype": "postalcode"
  },
  "geometry": {"coordinates":[-1.508515,53.81723],"type":"Point"}
}
