{
  "type": "Feature",
  "properties": {
    "iso:country":"GB",
    "wof:name":"G53 7LX",
    "wof:placetype":"postalcode"
},
  "geometry": {"coordinates":[-4.36470428827649,55.80833725976926],"type":"Point"}
}