{
  "type": "Feature",
  "properties": {
    "iso:country":"GB",
    "wof:name":"NN1 5BW",
    "wof:placetype":"postalcode"
},
  "geometry": {"coordinates":[-0.87909987806236,52.23603564362478],"type":"Point"}
}