{
  "type": "Feature",
  "properties": {
    "date:inception_lower":"2014-03-01",
    "date:inception_upper":"2014-03-31",
    "iso:country":"GB",
    "wof:name":"CB22 5FE",
    "wof:placetype":"postalcode"
},
  "geometry": {"coordinates":[0.131338,52.153335],"type":"Point"}
}