{
  "type": "Feature",
  "properties": {
    "iso:country": "GB",
    "wof:name": "CB22 5FE",
    "wof:placetype": "postalcode"
  },
  "geometry": {"coordinates":[0.131338,52.153335],"type":"Point"}
}
