{
  "type": "Feature",
  "properties": {
    "iso:country":"GB",
    "wof:name":"CB22 5FE",
    "wof:placetype":"postalcode"
},
  "geometry": {"coordinates":[0.13133829403112,52.15333479939092],"type":"Point"}
}