{
  "type": "Feature",
  "properties": {
    "iso:country": "GB",
    "wof:name": "L40 6HU",
    "wof:placetype": "postalcode"
  },
  "geometry": {"coordinates":[-2.847851,53.56473],"type":"Point"}
}
