{
  "type": "Feature",
  "properties": {
    "iso:country":"GB",
    "wof:name":"BR6 7RF",
    "wof:placetype":"postalcode"
},
  "geometry": {"coordinates":[0.1272612915703,51.35704038757879],"type":"Point"}
}