{
  "type": "Feature",
  "properties": {
    "iso:country": "GB",
    "wof:name": "CF47 9LA",
    "wof:placetype": "postalcode"
  },
  "geometry": {"coordinates":[-3.369908,51.7576],"type":"Point"}
}
