{
  "type": "Feature",
  "properties": {
    "iso:country":"GB",
    "wof:name":"CF47 9LA",
    "wof:placetype":"postalcode"
},
  "geometry": {"coordinates":[-3.36990823381851,51.75759992227019],"type":"Point"}
}