{
  "type": "Feature",
  "properties": {
    "iso:country": "GB",
    "wof:name": "CA11 0AU",
    "wof:placetype": "postalcode"
  },
  "geometry": {"coordinates":[-2.809184,54.675722],"type":"Point"}
}
