{
  "type": "Feature",
  "properties": {
    "iso:country":"GB",
    "wof:name":"SW8 3RJ",
    "wof:placetype":"postalcode"
},
  "geometry": {"coordinates":[-0.14973709210634,51.47054519247215],"type":"Point"}
}