{
  "type": "Feature",
  "properties": {
    "iso:country": "GB",
    "wof:name": "SW8 3RJ",
    "wof:placetype": "postalcode"
  },
  "geometry": {"coordinates":[-0.149722,51.470554],"type":"Point"}
}
