{
  "type": "Feature",
  "properties": {
    "iso:country":"GB",
    "wof:name":"S40 2PY",
    "wof:placetype":"postalcode"
},
  "geometry": {"coordinates":[-1.44504651558099,53.23021115195912],"type":"Point"}
}