{
  "type": "Feature",
  "properties": {
    "iso:country": "GB",
    "wof:name": "SY8 1ES",
    "wof:placetype": "postalcode"
  },
  "geometry": {"coordinates":[-2.693971,52.365188],"type":"Point"}
}
