{
  "type": "Feature",
  "properties": {
    "iso:country":"GB",
    "wof:name":"SY8 1ES",
    "wof:placetype":"postalcode"
},
  "geometry": {"coordinates":[-2.69397153560417,52.36518812411436],"type":"Point"}
}