{
  "type": "Feature",
  "properties": {
    "iso:country": "GB",
    "wof:name": "SY13 4QQ",
    "wof:placetype": "postalcode"
  },
  "geometry": {"coordinates":[-2.701695,52.976892],"type":"Point"}
}
