{
  "type": "Feature",
  "properties": {
    "iso:country":"GB",
    "wof:name":"SY13 4QQ",
    "wof:placetype":"postalcode"
},
  "geometry": {"coordinates":[-2.70169513510444,52.97689239884214],"type":"Point"}
}