{
  "type": "Feature",
  "properties": {
    "iso:country":"GB",
    "wof:name":"DN7 5HJ",
    "wof:placetype":"postalcode"
},
  "geometry": {"coordinates":[-1.02540895476653,53.58971006259523],"type":"Point"}
}