{
  "type": "Feature",
  "properties": {
    "iso:country":"GB",
    "wof:name":"SW12 9LX",
    "wof:placetype":"postalcode"
},
  "geometry": {"coordinates":[-0.14412347230784,51.438559776567],"type":"Point"}
}