{
  "type": "Feature",
  "properties": {
    "date:inception_lower": "1980-01-01",
    "date:inception_upper": "1980-01-01",
    "iso:country": "GB",
    "wof:name": "ST20 0PL",
    "wof:placetype": "postalcode"
  },
  "geometry": {"coordinates":[-2.316435,52.807125],"type":"Point"}
}
