{
  "type": "Feature",
  "properties": {
    "iso:country":"GB",
    "wof:name":"ST20 0PL",
    "wof:placetype":"postalcode"
},
  "geometry": {"coordinates":[-2.3164346169662,52.80712467617019],"type":"Point"}
}