{
  "type": "Feature",
  "properties": {
    "iso:country":"GB",
    "wof:name":"BS20 0HF",
    "wof:placetype":"postalcode"
},
  "geometry": {"coordinates":[-2.67942995398314,51.47442954158634],"type":"Point"}
}