{
  "type": "Feature",
  "properties": {
    "date:inception_lower": "1980-01-01",
    "date:inception_upper": "1980-01-01",
    "iso:country": "GB",
    "wof:name": "BS20 0HF",
    "wof:placetype": "postalcode"
  },
  "geometry": {"coordinates":[-2.679416,51.474303],"type":"Point"}
}
