{
  "type": "Feature",
  "properties": {
    "iso:country": "GB",
    "wof:name": "BS20 0HF",
    "wof:placetype": "postalcode"
  },
  "geometry": {"coordinates":[-2.67943,51.47443],"type":"Point"}
}
