{
  "type": "Feature",
  "properties": {
    "iso:country": "GB",
    "wof:name": "S66 8AF",
    "wof:placetype": "postalcode"
  },
  "geometry": {"coordinates":[-1.207385,53.430957],"type":"Point"}
}
