{
  "type": "Feature",
  "properties": {
    "iso:country":"GB",
    "wof:name":"W1T 7QJ",
    "wof:placetype":"postalcode"
},
  "geometry": {"coordinates":[-0.13229647671242,51.51892731131691],"type":"Point"}
}