{
  "type": "Feature",
  "properties": {
    "iso:country":"GB",
    "wof:name":"SK10 5HT",
    "wof:placetype":"postalcode"
},
  "geometry": {"coordinates":[-2.10973526643938,53.29463306417487],"type":"Point"}
}