{
  "type": "Feature",
  "properties": {
    "date:inception_lower": "1980-01-01",
    "date:inception_upper": "1980-01-01",
    "iso:country": "GB",
    "wof:name": "SK10 5HT",
    "wof:placetype": "postalcode"
  },
  "geometry": {"coordinates":[-2.109779,53.29465],"type":"Point"}
}
