{
  "type": "Feature",
  "properties": {
    "iso:country":"GB",
    "wof:name":"HU10 7JU",
    "wof:placetype":"postalcode"
},
  "geometry": {"coordinates":[-0.4530956256429,53.74475633894169],"type":"Point"}
}