{
  "type": "Feature",
  "properties": {
    "iso:country":"GB",
    "wof:name":"AL5 1BZ",
    "wof:placetype":"postalcode"
},
  "geometry": {"coordinates":[-0.34425416035438,51.79924651424053],"type":"Point"}
}