{
  "type": "Feature",
  "properties": {
    "iso:country": "GB",
    "wof:name": "AL5 1BZ",
    "wof:placetype": "postalcode"
  },
  "geometry": {"coordinates":[-0.344254,51.799247],"type":"Point"}
}
