{
  "type": "Feature",
  "properties": {
    "date:inception_lower": "1995-07-01",
    "date:inception_upper": "1995-07-01",
    "iso:country": "GB",
    "wof:name": "WF17 5DE",
    "wof:placetype": "postalcode"
  },
  "geometry": {"coordinates":[-1.633143,53.714034],"type":"Point"}
}
