{
  "type": "Feature",
  "properties": {
    "iso:country":"GB",
    "wof:name":"DE73 8EH",
    "wof:placetype":"postalcode"
},
  "geometry": {"coordinates":[-1.42841860892154,52.82397149211408],"type":"Point"}
}