{
  "type": "Feature",
  "properties": {
    "iso:country": "GB",
    "wof:name": "DE73 8EH",
    "wof:placetype": "postalcode"
  },
  "geometry": {"coordinates":[-1.427753,52.824489],"type":"Point"}
}
