{
  "type": "Feature",
  "properties": {
    "iso:country":"GB",
    "wof:name":"PO6 4YA",
    "wof:placetype":"postalcode"
},
  "geometry": {"coordinates":[-1.06961731621021,50.84468344137402],"type":"Point"}
}