{
  "type": "Feature",
  "properties": {
    "date:inception_lower": "2002-07-01",
    "date:inception_upper": "2002-07-01",
    "iso:country": "GB",
    "wof:name": "PO6 4YA",
    "wof:placetype": "postalcode"
  },
  "geometry": {"coordinates":[-1.069617,50.844683],"type":"Point"}
}
