{
  "type": "Feature",
  "properties": {
    "iso:country": "GB",
    "wof:name": "YO60 6RG",
    "wof:placetype": "postalcode"
  },
  "geometry": {"coordinates":[-1.010994,54.087175],"type":"Point"}
}
