{
  "type": "Feature",
  "properties": {
    "iso:country":"GB",
    "wof:name":"YO60 6RG",
    "wof:placetype":"postalcode"
},
  "geometry": {"coordinates":[-1.01099361723613,54.08717507760886],"type":"Point"}
}