{
  "type": "Feature",
  "properties": {
    "iso:country":"GB",
    "wof:name":"LL26 0TN",
    "wof:placetype":"postalcode"
},
  "geometry": {"coordinates":[-3.76319686141245,53.11396270060796],"type":"Point"}
}