{
  "type": "Feature",
  "properties": {
    "iso:country":"GB",
    "wof:name":"HA4 8RZ",
    "wof:placetype":"postalcode"
},
  "geometry": {"coordinates":[-0.40600524740746,51.5768650852513],"type":"Point"}
}