{
  "type": "Feature",
  "properties": {
    "iso:country":"GB",
    "wof:name":"ST7 2JA",
    "wof:placetype":"postalcode"
},
  "geometry": {"coordinates":[-2.3142599725071,53.09520078986882],"type":"Point"}
}