{
  "type": "Feature",
  "properties": {
    "iso:country": "GB",
    "wof:name": "WF17 9TD",
    "wof:placetype": "postalcode"
  },
  "geometry": {"coordinates":[-1.643586,53.742297],"type":"Point"}
}
