{
  "type": "Feature",
  "properties": {
    "date:inception_lower": "1996-12-01",
    "date:inception_upper": "1996-12-01",
    "iso:country": "GB",
    "wof:name": "WF17 9TD",
    "wof:placetype": "postalcode"
  },
  "geometry": {"coordinates":[-1.643904,53.742799],"type":"Point"}
}
