{
  "type": "Feature",
  "properties": {
    "iso:country":"GB",
    "wof:name":"OX2 0BH",
    "wof:placetype":"postalcode"
},
  "geometry": {"coordinates":[-1.27472885608743,51.75093310702979],"type":"Point"}
}