{
  "type": "Feature",
  "properties": {
    "date:inception_lower":"1996-06-01",
    "date:inception_upper":"1996-06-30",
    "iso:country":"GB",
    "wof:name":"IP17 2PY",
    "wof:placetype":"postalcode"
},
  "geometry": {"coordinates":[1.493366,52.225637],"type":"Point"}
}