{
  "type": "Feature",
  "properties": {
    "iso:country":"GB",
    "wof:name":"NG13 9NW",
    "wof:placetype":"postalcode"
},
  "geometry": {"coordinates":[-0.85512954935049,52.96325122795162],"type":"Point"}
}