{
  "type": "Feature",
  "properties": {
    "iso:country":"GB",
    "wof:name":"SE15 3PS",
    "wof:placetype":"postalcode"
},
  "geometry": {"coordinates":[-0.06069606353997,51.46307213243317],"type":"Point"}
}