{
  "type": "Feature",
  "properties": {
    "iso:country":"GB",
    "wof:name":"HA4 9HB",
    "wof:placetype":"postalcode"
},
  "geometry": {"coordinates":[-0.39394992765425,51.56512783175426],"type":"Point"}
}