{
  "type": "Feature",
  "properties": {
    "iso:country":"GB",
    "wof:name":"EX2 8XG",
    "wof:placetype":"postalcode"
},
  "geometry": {"coordinates":[-3.52950891764459,50.69867964597643],"type":"Point"}
}