{
  "type": "Feature",
  "properties": {
    "iso:country": "GB",
    "wof:name": "EX2 8XG",
    "wof:placetype": "postalcode"
  },
  "geometry": {"coordinates":[-3.529509,50.69868],"type":"Point"}
}
