{
  "type": "Feature",
  "properties": {
    "iso:country":"GB",
    "wof:name":"CM7 4DB",
    "wof:placetype":"postalcode"
},
  "geometry": {"coordinates":[0.52296370381742,51.95187450922744],"type":"Point"}
}