{
  "type": "Feature",
  "properties": {
    "date:inception_lower": "1980-01-01",
    "date:inception_upper": "1980-01-01",
    "iso:country": "GB",
    "wof:name": "CM7 4DB",
    "wof:placetype": "postalcode"
  },
  "geometry": {"coordinates":[0.522964,51.951875],"type":"Point"}
}
