{
  "type": "Feature",
  "properties": {
    "iso:country":"GB",
    "wof:name":"SK11 6UN",
    "wof:placetype":"postalcode"
},
  "geometry": {"coordinates":[-2.12657024156266,53.25475123105001],"type":"Point"}
}