{
  "type": "Feature",
  "properties": {
    "iso:country":"GB",
    "wof:name":"BB7 4SW",
    "wof:placetype":"postalcode"
},
  "geometry": {"coordinates":[-2.39008447000575,53.8954178650826],"type":"Point"}
}