{
  "type": "Feature",
  "properties": {
    "date:inception_lower": "1980-01-01",
    "date:inception_upper": "1980-01-01",
    "iso:country": "GB",
    "wof:name": "BB7 4SW",
    "wof:placetype": "postalcode"
  },
  "geometry": {"coordinates":[-2.390084,53.895418],"type":"Point"}
}
