{
  "type": "Feature",
  "properties": {
    "iso:country":"GB",
    "wof:name":"PH15 2NU",
    "wof:placetype":"postalcode"
},
  "geometry": {"coordinates":[-3.99926242276167,56.5852247166465],"type":"Point"}
}