{
  "type": "Feature",
  "properties": {
    "iso:country":"GB",
    "wof:name":"CF14 3NL",
    "wof:placetype":"postalcode"
},
  "geometry": {"coordinates":[-3.18868855160624,51.50365096166895],"type":"Point"}
}