{
  "type": "Feature",
  "properties": {
    "iso:country":"GB",
    "wof:name":"DD8 2HL",
    "wof:placetype":"postalcode"
},
  "geometry": {"coordinates":[-2.88035795497973,56.64645211187878],"type":"Point"}
}