{
  "type": "Feature",
  "properties": {
    "iso:country":"GB",
    "wof:name":"BS26 2BG",
    "wof:placetype":"postalcode"
},
  "geometry": {"coordinates":[-2.81932673539748,51.28629792321638],"type":"Point"}
}