{
  "type": "Feature",
  "properties": {
    "iso:country":"GB",
    "wof:name":"LE2 8GF",
    "wof:placetype":"postalcode"
},
  "geometry": {"coordinates":[-1.14058976778846,52.60767606337179],"type":"Point"}
}