{
  "type": "Feature",
  "properties": {
    "date:inception_lower":"2013-07-01",
    "date:inception_upper":"2013-07-31",
    "iso:country":"GB",
    "wof:name":"N20 8BG",
    "wof:placetype":"postalcode"
},
  "geometry": {"coordinates":[-0.173771,51.629749],"type":"Point"}
}