{
  "type": "Feature",
  "properties": {
    "iso:country":"GB",
    "wof:name":"PR8 9AB",
    "wof:placetype":"postalcode"
},
  "geometry": {"coordinates":[-2.98582245435397,53.62698848455604],"type":"Point"}
}