{
  "type": "Feature",
  "properties": {
    "iso:country":"GB",
    "wof:name":"BB1 3LY",
    "wof:placetype":"postalcode"
},
  "geometry": {"coordinates":[-2.43318599503751,53.74885553597115],"type":"Point"}
}