{
  "type": "Feature",
  "properties": {
    "date:inception_lower": "1993-01-01",
    "date:inception_upper": "1993-01-01",
    "iso:country": "GB",
    "wof:name": "TA1 3FA",
    "wof:placetype": "postalcode"
  },
  "geometry": {"coordinates":[-3.090057,51.015012],"type":"Point"}
}
