{
  "type": "Feature",
  "properties": {
    "iso:country":"GB",
    "wof:name":"TR1 1LA",
    "wof:placetype":"postalcode"
},
  "geometry": {"coordinates":[-5.04184581492547,50.26614332974933],"type":"Point"}
}