{
  "type": "Feature",
  "properties": {
    "date:inception_lower": "1980-01-01",
    "date:inception_upper": "1980-01-01",
    "iso:country": "GB",
    "wof:name": "S63 8AF",
    "wof:placetype": "postalcode"
  },
  "geometry": {"coordinates":[-1.3181,53.519505],"type":"Point"}
}
