{
  "type": "Feature",
  "properties": {
    "iso:country": "GB",
    "wof:name": "S63 8AF",
    "wof:placetype": "postalcode"
  },
  "geometry": {"coordinates":[-1.318098,53.519649],"type":"Point"}
}
