{
  "type": "Feature",
  "properties": {
    "iso:country": "GB",
    "wof:name": "PE7 1GB",
    "wof:placetype": "postalcode"
  },
  "geometry": {"coordinates":[-0.131267,52.556717],"type":"Point"}
}
