{
  "type": "Feature",
  "properties": {
    "date:inception_lower":"2007-11-01",
    "date:inception_upper":"2007-11-30",
    "iso:country":"GB",
    "wof:name":"PE7 1GB",
    "wof:placetype":"postalcode"
},
  "geometry": {"coordinates":[-0.131267,52.556717],"type":"Point"}
}