{
  "type": "Feature",
  "properties": {
    "iso:country":"GB",
    "wof:name":"HA3 5RX",
    "wof:placetype":"postalcode"
},
  "geometry": {"coordinates":[-0.33701287322956,51.5948902726246],"type":"Point"}
}