{
  "type": "Feature",
  "properties": {
    "iso:country":"GB",
    "wof:name":"BA3 3JA",
    "wof:placetype":"postalcode"
},
  "geometry": {"coordinates":[-2.44388991959249,51.29639855113252],"type":"Point"}
}