{
  "type": "Feature",
  "properties": {
    "iso:country":"GB",
    "wof:name":"M28 1ZA",
    "wof:placetype":"postalcode"
},
  "geometry": {"coordinates":[-2.41337172885391,53.50818344959099],"type":"Point"}
}