{
  "type": "Feature",
  "properties": {
    "iso:country":"GB",
    "wof:name":"L10 7LH",
    "wof:placetype":"postalcode"
},
  "geometry": {"coordinates":[-2.92121348682047,53.46870940142561],"type":"Point"}
}