{
  "type": "Feature",
  "properties": {
    "iso:country":"GB",
    "wof:name":"BH21 5PZ",
    "wof:placetype":"postalcode"
},
  "geometry": {"coordinates":[-1.92021291763932,50.91841380841254],"type":"Point"}
}