{
  "type": "Feature",
  "properties": {
    "iso:country": "GB",
    "wof:name": "BH21 5PZ",
    "wof:placetype": "postalcode"
  },
  "geometry": {"coordinates":[-1.920213,50.918414],"type":"Point"}
}
