{
  "type": "Feature",
  "properties": {
    "iso:country": "GB",
    "wof:name": "FY8 5AU",
    "wof:placetype": "postalcode"
  },
  "geometry": {"coordinates":[-2.950642,53.740151],"type":"Point"}
}
