{
  "type": "Feature",
  "properties": {
    "iso:country":"GB",
    "wof:name":"FY8 5AU",
    "wof:placetype":"postalcode"
},
  "geometry": {"coordinates":[-2.95064157984531,53.74015067614585],"type":"Point"}
}