{
  "type": "Feature",
  "properties": {
    "iso:country":"GB",
    "wof:name":"KA21 6EJ",
    "wof:placetype":"postalcode"
},
  "geometry": {"coordinates":[-4.78156786161229,55.64994304101916],"type":"Point"}
}