{
  "type": "Feature",
  "properties": {
    "iso:country":"GB",
    "wof:name":"SW9 0EL",
    "wof:placetype":"postalcode"
},
  "geometry": {"coordinates":[-0.11522310597106,51.47684780445751],"type":"Point"}
}