{
  "type": "Feature",
  "properties": {
    "iso:country": "GB",
    "wof:name": "RG22 5LG",
    "wof:placetype": "postalcode"
  },
  "geometry": {"coordinates":[-1.138498,51.248143],"type":"Point"}
}
