{
  "type": "Feature",
  "properties": {
    "iso:country":"GB",
    "wof:name":"RG22 5LG",
    "wof:placetype":"postalcode"
},
  "geometry": {"coordinates":[-1.13849850757407,51.24814252459011],"type":"Point"}
}