{
  "type": "Feature",
  "properties": {
    "iso:country": "GB",
    "wof:name": "EH45 8AW",
    "wof:placetype": "postalcode"
  },
  "geometry": {"coordinates":[-3.192639,55.651077],"type":"Point"}
}
