{
  "type": "Feature",
  "properties": {
    "date:inception_lower": "1999-06-01",
    "date:inception_upper": "1999-06-01",
    "iso:country": "GB",
    "wof:name": "CB1 1BH",
    "wof:placetype": "postalcode"
  },
  "geometry": {"coordinates":[0.13179,52.203489],"type":"Point"}
}
