{
  "type": "Feature",
  "properties": {
    "iso:country":"GB",
    "wof:name":"CB1 1BH",
    "wof:placetype":"postalcode"
},
  "geometry": {"coordinates":[0.13176132839753,52.20347530537806],"type":"Point"}
}