{
  "type": "Feature",
  "properties": {
    "iso:country":"GB",
    "wof:name":"BS16 4PH",
    "wof:placetype":"postalcode"
},
  "geometry": {"coordinates":[-2.51076599164578,51.47419782877439],"type":"Point"}
}