{
  "type": "Feature",
  "properties": {
    "iso:country":"GB",
    "wof:name":"DY5 1DE",
    "wof:placetype":"postalcode"
},
  "geometry": {"coordinates":[-2.10603271139647,52.47558133822565],"type":"Point"}
}