{
  "type": "Feature",
  "properties": {
    "iso:country": "GB",
    "wof:name": "RH16 4XP",
    "wof:placetype": "postalcode"
  },
  "geometry": {"coordinates":[-0.095365,50.994043],"type":"Point"}
}
