{
  "type": "Feature",
  "properties": {
    "date:inception_lower": "1980-01-01",
    "date:inception_upper": "1980-01-01",
    "iso:country": "GB",
    "wof:name": "SA37 0JX",
    "wof:placetype": "postalcode"
  },
  "geometry": {"coordinates":[-4.550788,52.009937],"type":"Point"}
}
