{
  "type": "Feature",
  "properties": {
    "iso:country":"GB",
    "wof:name":"SA37 0JX",
    "wof:placetype":"postalcode"
},
  "geometry": {"coordinates":[-4.55526373412354,52.00678708083375],"type":"Point"}
}