{
  "type": "Feature",
  "properties": {
    "iso:country":"GB",
    "wof:name":"L35 4PE",
    "wof:placetype":"postalcode"
},
  "geometry": {"coordinates":[-2.76523507780274,53.41926683726154],"type":"Point"}
}