{
  "type": "Feature",
  "properties": {
    "iso:country": "GB",
    "wof:name": "WF4 1ET",
    "wof:placetype": "postalcode"
  },
  "geometry": {"coordinates":[-1.409917,53.672606],"type":"Point"}
}
