{
  "type": "Feature",
  "properties": {
    "iso:country":"GB",
    "wof:name":"WF4 1ET",
    "wof:placetype":"postalcode"
},
  "geometry": {"coordinates":[-1.40991694631837,53.67260605685698],"type":"Point"}
}