{
  "type": "Feature",
  "properties": {
    "iso:country":"GB",
    "wof:name":"DG9 7SG",
    "wof:placetype":"postalcode"
},
  "geometry": {"coordinates":[-5.02316135035816,54.89233316144846],"type":"Point"}
}