{
  "type": "Feature",
  "properties": {
    "iso:country": "GB",
    "wof:name": "PL6 8RD",
    "wof:placetype": "postalcode"
  },
  "geometry": {"coordinates":[-4.094717,50.403824],"type":"Point"}
}
