{
  "type": "Feature",
  "properties": {
    "iso:country":"GB",
    "wof:name":"PL6 8RD",
    "wof:placetype":"postalcode"
},
  "geometry": {"coordinates":[-4.09471713662272,50.40382359057256],"type":"Point"}
}