{
  "type": "Feature",
  "properties": {
    "iso:country": "GB",
    "wof:name": "CM7 2AH",
    "wof:placetype": "postalcode"
  },
  "geometry": {"coordinates":[0.542634,51.879715],"type":"Point"}
}
