{
  "type": "Feature",
  "properties": {
    "iso:country":"GB",
    "wof:name":"CM7 2AH",
    "wof:placetype":"postalcode"
},
  "geometry": {"coordinates":[0.54263430858718,51.87971451632671],"type":"Point"}
}