{
  "type": "Feature",
  "properties": {
    "date:inception_lower":"2009-12-01",
    "date:inception_upper":"2009-12-31",
    "iso:country":"GB",
    "wof:name":"CM7 2AH",
    "wof:placetype":"postalcode"
},
  "geometry": {"coordinates":[0.542634,51.879715],"type":"Point"}
}