{
  "type": "Feature",
  "properties": {
    "iso:country":"GB",
    "wof:name":"TQ13 7HF",
    "wof:placetype":"postalcode"
},
  "geometry": {"coordinates":[-3.78622092646317,50.52438114155841],"type":"Point"}
}