{
  "type": "Feature",
  "properties": {
    "iso:country": "GB",
    "wof:name": "TQ13 7HF",
    "wof:placetype": "postalcode"
  },
  "geometry": {"coordinates":[-3.775996,50.523951],"type":"Point"}
}
