{
  "type": "Feature",
  "properties": {
    "iso:country":"GB",
    "wof:name":"S81 9HS",
    "wof:placetype":"postalcode"
},
  "geometry": {"coordinates":[-1.12701370861038,53.36031050858964],"type":"Point"}
}