{
  "type": "Feature",
  "properties": {
    "iso:country":"GB",
    "wof:name":"SE26 6EU",
    "wof:placetype":"postalcode"
},
  "geometry": {"coordinates":[-0.05826095117538,51.42376970462357],"type":"Point"}
}