{
  "type": "Feature",
  "properties": {
    "date:inception_lower": "1980-01-01",
    "date:inception_upper": "1980-01-01",
    "iso:country": "GB",
    "wof:name": "SE26 6EU",
    "wof:placetype": "postalcode"
  },
  "geometry": {"coordinates":[-0.058261,51.42377],"type":"Point"}
}
