{
  "type": "Feature",
  "properties": {
    "iso:country": "GB",
    "wof:name": "SE26 6EU",
    "wof:placetype": "postalcode"
  },
  "geometry": {"coordinates":[-0.058261,51.42377],"type":"Point"}
}
