{
  "type": "Feature",
  "properties": {
    "iso:country": "GB",
    "wof:name": "ME13 9PJ",
    "wof:placetype": "postalcode"
  },
  "geometry": {"coordinates":[0.965259,51.276396],"type":"Point"}
}
