{
  "type": "Feature",
  "properties": {
    "iso:country":"GB",
    "wof:name":"FK3 8RH",
    "wof:placetype":"postalcode"
},
  "geometry": {"coordinates":[-3.72489221129726,56.00122164102863],"type":"Point"}
}