{
  "type": "Feature",
  "properties": {
    "iso:country":"GB",
    "wof:name":"S62 7GA",
    "wof:placetype":"postalcode"
},
  "geometry": {"coordinates":[-1.34843589060733,53.46589420702573],"type":"Point"}
}