{
  "type": "Feature",
  "properties": {
    "date:inception_lower": "1980-01-01",
    "date:inception_upper": "1980-01-01",
    "iso:country": "GB",
    "wof:name": "CO15 6DE",
    "wof:placetype": "postalcode"
  },
  "geometry": {"coordinates":[1.158709,51.794075],"type":"Point"}
}
