{
  "type": "Feature",
  "properties": {
    "iso:country":"GB",
    "wof:name":"HP7 9JD",
    "wof:placetype":"postalcode"
},
  "geometry": {"coordinates":[-0.58721015955063,51.67215334406738],"type":"Point"}
}