{
  "type": "Feature",
  "properties": {
    "iso:country": "GB",
    "wof:name": "HP7 9JD",
    "wof:placetype": "postalcode"
  },
  "geometry": {"coordinates":[-0.58721,51.672153],"type":"Point"}
}
