{
  "type": "Feature",
  "properties": {
    "date:inception_lower": "2009-02-01",
    "date:inception_upper": "2009-02-01",
    "iso:country": "GB",
    "wof:name": "SR5 2BF",
    "wof:placetype": "postalcode"
  },
  "geometry": {"coordinates":[-1.40456,54.92433],"type":"Point"}
}
