{
  "type": "Feature",
  "properties": {
    "iso:country":"GB",
    "wof:name":"SR5 2BF",
    "wof:placetype":"postalcode"
},
  "geometry": {"coordinates":[-1.40456008278145,54.92432970732498],"type":"Point"}
}