{
  "type": "Feature",
  "properties": {
    "date:inception_lower": "1997-06-01",
    "date:inception_upper": "1997-06-01",
    "iso:country": "GB",
    "wof:name": "CT3 4DQ",
    "wof:placetype": "postalcode"
  },
  "geometry": {"coordinates":[1.201579,51.324415],"type":"Point"}
}
