{
  "type": "Feature",
  "properties": {
    "iso:country":"GB",
    "wof:name":"CT3 4DQ",
    "wof:placetype":"postalcode"
},
  "geometry": {"coordinates":[1.20157872417646,51.32441496607263],"type":"Point"}
}