{
  "type": "Feature",
  "properties": {
    "iso:country":"GB",
    "wof:name":"TF9 2EG",
    "wof:placetype":"postalcode"
},
  "geometry": {"coordinates":[-2.43246419328062,52.91258213294159],"type":"Point"}
}