{
  "type": "Feature",
  "properties": {
    "iso:country": "GB",
    "wof:name": "M19 3QF",
    "wof:placetype": "postalcode"
  },
  "geometry": {"coordinates":[-2.188079,53.444492],"type":"Point"}
}
