{
  "type": "Feature",
  "properties": {
    "iso:country":"GB",
    "wof:name":"M19 3QF",
    "wof:placetype":"postalcode"
},
  "geometry": {"coordinates":[-2.18807923493406,53.44449218730561],"type":"Point"}
}