{
  "type": "Feature",
  "properties": {
    "iso:country":"GB",
    "wof:name":"B19 3SG",
    "wof:placetype":"postalcode"
},
  "geometry": {"coordinates":[-1.89794510777237,52.4874790167767],"type":"Point"}
}