{
  "type": "Feature",
  "properties": {
    "iso:country": "GB",
    "wof:name": "B19 3SG",
    "wof:placetype": "postalcode"
  },
  "geometry": {"coordinates":[-1.897945,52.487479],"type":"Point"}
}
