{
  "type": "Feature",
  "properties": {
    "iso:country":"GB",
    "wof:name":"L1 1JJ",
    "wof:placetype":"postalcode"
},
  "geometry": {"coordinates":[-2.98016341957506,53.40863499722578],"type":"Point"}
}