{
  "type": "Feature",
  "properties": {
    "date:inception_lower": "1980-01-01",
    "date:inception_upper": "1980-01-01",
    "iso:country": "GB",
    "wof:name": "RG4 9QH",
    "wof:placetype": "postalcode"
  },
  "geometry": {"coordinates":[-0.935317,51.490112],"type":"Point"}
}
