{
  "type": "Feature",
  "properties": {
    "iso:country":"GB",
    "wof:name":"RG4 9QH",
    "wof:placetype":"postalcode"
},
  "geometry": {"coordinates":[-0.93529276543891,51.49016340601041],"type":"Point"}
}