{
  "type": "Feature",
  "properties": {
    "iso:country": "GB",
    "wof:name": "WS11 1RU",
    "wof:placetype": "postalcode"
  },
  "geometry": {"coordinates":[-2.069539,52.682509],"type":"Point"}
}
