{
  "type": "Feature",
  "properties": {
    "iso:country":"GB",
    "wof:name":"HD2 1QG",
    "wof:placetype":"postalcode"
},
  "geometry": {"coordinates":[-1.74987928959199,53.68452965338349],"type":"Point"}
}