{
  "type": "Feature",
  "properties": {
    "date:inception_lower": "1980-01-01",
    "date:inception_upper": "1980-01-01",
    "iso:country": "GB",
    "wof:name": "HD2 1QG",
    "wof:placetype": "postalcode"
  },
  "geometry": {"coordinates":[-1.749879,53.68453],"type":"Point"}
}
