{
  "type": "Feature",
  "properties": {
    "iso:country": "GB",
    "wof:name": "TS10 4BW",
    "wof:placetype": "postalcode"
  },
  "geometry": {"coordinates":[-1.071666,54.60497],"type":"Point"}
}
