{
  "type": "Feature",
  "properties": {
    "date:inception_lower": "2014-09-01",
    "date:inception_upper": "2014-09-01",
    "iso:country": "GB",
    "wof:name": "TS10 4BW",
    "wof:placetype": "postalcode"
  },
  "geometry": {"coordinates":[-1.071666,54.60497],"type":"Point"}
}
