{
  "type": "Feature",
  "properties": {
    "date:inception_lower":"1980-01-01",
    "date:inception_upper":"1980-01-31",
    "iso:country":"GB",
    "wof:name":"AL6 9HS",
    "wof:placetype":"postalcode"
},
  "geometry": {"coordinates":[-0.211651,51.826447],"type":"Point"}
}