{
  "type": "Feature",
  "properties": {
    "iso:country":"GB",
    "wof:name":"CM19 4EU",
    "wof:placetype":"postalcode"
},
  "geometry": {"coordinates":[0.08415200560846,51.76554508929694],"type":"Point"}
}