{
  "type": "Feature",
  "properties": {
    "date:inception_lower":"1980-01-01",
    "date:inception_upper":"1980-01-31",
    "iso:country":"GB",
    "wof:name":"IP16 4QN",
    "wof:placetype":"postalcode"
},
  "geometry": {"coordinates":[1.579976,52.179091],"type":"Point"}
}