{
  "type": "Feature",
  "properties": {
    "iso:country":"GB",
    "wof:name":"IP16 4QN",
    "wof:placetype":"postalcode"
},
  "geometry": {"coordinates":[1.57997547672588,52.17909088232621],"type":"Point"}
}