{
  "type": "Feature",
  "properties": {
    "iso:country": "GB",
    "wof:name": "IP16 4QN",
    "wof:placetype": "postalcode"
  },
  "geometry": {"coordinates":[1.579976,52.179091],"type":"Point"}
}
