{
  "type": "Feature",
  "properties": {
    "iso:country":"GB",
    "wof:name":"WV6 0SF",
    "wof:placetype":"postalcode"
},
  "geometry": {"coordinates":[-2.13591988810483,52.59954807649867],"type":"Point"}
}