{
  "type": "Feature",
  "properties": {
    "date:inception_lower": "1980-01-01",
    "date:inception_upper": "1980-01-01",
    "iso:country": "GB",
    "wof:name": "DE7 6BU",
    "wof:placetype": "postalcode"
  },
  "geometry": {"coordinates":[-1.353375,52.982538],"type":"Point"}
}
