{
  "type": "Feature",
  "properties": {
    "iso:country":"GB",
    "wof:name":"DE7 6BU",
    "wof:placetype":"postalcode"
},
  "geometry": {"coordinates":[-1.35337517764286,52.98253835556443],"type":"Point"}
}