{
  "type": "Feature",
  "properties": {
    "iso:country":"GB",
    "wof:name":"AL3 4DA",
    "wof:placetype":"postalcode"
},
  "geometry": {"coordinates":[-0.34140184072541,51.75207067878283],"type":"Point"}
}