{
  "type": "Feature",
  "properties": {
    "iso:country":"GB",
    "wof:name":"CA7 2QD",
    "wof:placetype":"postalcode"
},
  "geometry": {"coordinates":[-3.37150050030502,54.73086771454512],"type":"Point"}
}