{
  "type": "Feature",
  "properties": {
    "iso:country": "GB",
    "wof:name": "CA7 2QD",
    "wof:placetype": "postalcode"
  },
  "geometry": {"coordinates":[-3.3715,54.730868],"type":"Point"}
}
