{
  "type": "Feature",
  "properties": {
    "date:inception_lower": "2024-10-01",
    "date:inception_upper": "2024-10-01",
    "iso:country": "GB",
    "wof:name": "ME18 5FB",
    "wof:placetype": "postalcode"
  },
  "geometry": {"coordinates":[0.433351,51.26806],"type":"Point"}
}
