{
  "type": "Feature",
  "properties": {
    "iso:country": "GB",
    "wof:name": "LN4 3QT",
    "wof:placetype": "postalcode"
  },
  "geometry": {"coordinates":[-0.32208,53.124409],"type":"Point"}
}
