{
  "type": "Feature",
  "properties": {
    "iso:country":"GB",
    "wof:name":"PO7 7UG",
    "wof:placetype":"postalcode"
},
  "geometry": {"coordinates":[-1.03353383540244,50.88346356900384],"type":"Point"}
}