{
  "type": "Feature",
  "properties": {
    "iso:country": "GB",
    "wof:name": "M20 5NA",
    "wof:placetype": "postalcode"
  },
  "geometry": {"coordinates":[-2.22422,53.411676],"type":"Point"}
}
