{
  "type": "Feature",
  "properties": {
    "iso:country":"GB",
    "wof:name":"M20 5NA",
    "wof:placetype":"postalcode"
},
  "geometry": {"coordinates":[-2.22422011722221,53.4116755268635],"type":"Point"}
}