{
  "type": "Feature",
  "properties": {
    "iso:country":"GB",
    "wof:name":"EH22 5EG",
    "wof:placetype":"postalcode"
},
  "geometry": {"coordinates":[-3.03933824997431,55.87350711568867],"type":"Point"}
}