{
  "type": "Feature",
  "properties": {
    "iso:country": "GB",
    "wof:name": "EH22 5EG",
    "wof:placetype": "postalcode"
  },
  "geometry": {"coordinates":[-3.039338,55.873507],"type":"Point"}
}
