{
  "type": "Feature",
  "properties": {
    "iso:country": "GB",
    "wof:name": "DE21 4GD",
    "wof:placetype": "postalcode"
  },
  "geometry": {"coordinates":[-1.456415,52.943133],"type":"Point"}
}
