{
  "type": "Feature",
  "properties": {
    "iso:country":"GB",
    "wof:name":"DE21 4GD",
    "wof:placetype":"postalcode"
},
  "geometry": {"coordinates":[-1.45691371463295,52.94281990489944],"type":"Point"}
}