{
  "type": "Feature",
  "properties": {
    "iso:country":"GB",
    "wof:name":"NW6 4TD",
    "wof:placetype":"postalcode"
},
  "geometry": {"coordinates":[-0.1950176506394,51.54135617788026],"type":"Point"}
}