{
  "type": "Feature",
  "properties": {
    "iso:country":"GB",
    "wof:name":"OL13 8BL",
    "wof:placetype":"postalcode"
},
  "geometry": {"coordinates":[-2.20309061512697,53.70594645582062],"type":"Point"}
}