{
  "type": "Feature",
  "properties": {
    "iso:country":"GB",
    "wof:name":"HD6 3DN",
    "wof:placetype":"postalcode"
},
  "geometry": {"coordinates":[-1.78348525392161,53.69771771617182],"type":"Point"}
}