{
  "type": "Feature",
  "properties": {
    "iso:country": "GB",
    "wof:name": "SY10 0DY",
    "wof:placetype": "postalcode"
  },
  "geometry": {"coordinates":[-3.267445,52.834543],"type":"Point"}
}
