{
  "type": "Feature",
  "properties": {
    "iso:country": "GB",
    "wof:name": "B14 7NU",
    "wof:placetype": "postalcode"
  },
  "geometry": {"coordinates":[-1.908067,52.428477],"type":"Point"}
}
