{
  "type": "Feature",
  "properties": {
    "iso:country":"GB",
    "wof:name":"B14 7NU",
    "wof:placetype":"postalcode"
},
  "geometry": {"coordinates":[-1.90806708089855,52.42847696781669],"type":"Point"}
}