{
  "type": "Feature",
  "properties": {
    "date:inception_lower":"1982-03-01",
    "date:inception_upper":"1982-03-31",
    "iso:country":"GB",
    "wof:name":"B14 7NU",
    "wof:placetype":"postalcode"
},
  "geometry": {"coordinates":[-1.908067,52.428477],"type":"Point"}
}