{
  "type": "Feature",
  "properties": {
    "iso:country":"GB",
    "wof:name":"DD11 5SG",
    "wof:placetype":"postalcode"
},
  "geometry": {"coordinates":[-2.5199981690119,56.58691265969758],"type":"Point"}
}