{
  "type": "Feature",
  "properties": {
    "iso:country":"GB",
    "wof:name":"DN7 4EL",
    "wof:placetype":"postalcode"
},
  "geometry": {"coordinates":[-1.02210064003312,53.58511683774499],"type":"Point"}
}