{
  "type": "Feature",
  "properties": {
    "date:inception_lower": "1997-12-01",
    "date:inception_upper": "1997-12-01",
    "iso:country": "GB",
    "wof:name": "AB31 5ED",
    "wof:placetype": "postalcode"
  },
  "geometry": {"coordinates":[-2.345966,57.080373],"type":"Point"}
}
