{
  "type": "Feature",
  "properties": {
    "iso:country":"GB",
    "wof:name":"AB31 5ED",
    "wof:placetype":"postalcode"
},
  "geometry": {"coordinates":[-2.34596588053121,57.08037307463825],"type":"Point"}
}