{
  "type": "Feature",
  "properties": {
    "iso:country": "GB",
    "wof:name": "AB31 5ED",
    "wof:placetype": "postalcode"
  },
  "geometry": {"coordinates":[-2.345966,57.080373],"type":"Point"}
}
