{
  "type": "Feature",
  "properties": {
    "iso:country":"GB",
    "wof:name":"HP2 5YU",
    "wof:placetype":"postalcode"
},
  "geometry": {"coordinates":[-0.47030316086769,51.76433038725408],"type":"Point"}
}