{
  "type": "Feature",
  "properties": {
    "iso:country": "GB",
    "wof:name": "HP2 5YU",
    "wof:placetype": "postalcode"
  },
  "geometry": {"coordinates":[-0.470366,51.764375],"type":"Point"}
}
