{
  "type": "Feature",
  "properties": {
    "date:inception_lower":"1980-01-01",
    "date:inception_upper":"1980-01-31",
    "iso:country":"GB",
    "wof:name":"CV37 8NR",
    "wof:placetype":"postalcode"
},
  "geometry": {"coordinates":[-1.697316,52.129216],"type":"Point"}
}