{
  "type": "Feature",
  "properties": {
    "iso:country":"GB",
    "wof:name":"CV37 8NR",
    "wof:placetype":"postalcode"
},
  "geometry": {"coordinates":[-1.6973161426575,52.12921640047664],"type":"Point"}
}