{
  "type": "Feature",
  "properties": {
    "iso:country":"GB",
    "wof:name":"KA10 7EZ",
    "wof:placetype":"postalcode"
},
  "geometry": {"coordinates":[-4.62534517511169,55.54981957302164],"type":"Point"}
}