{
  "type": "Feature",
  "properties": {
    "date:inception_lower": "1980-01-01",
    "date:inception_upper": "1980-01-01",
    "iso:country": "GB",
    "wof:name": "TQ5 8BB",
    "wof:placetype": "postalcode"
  },
  "geometry": {"coordinates":[-3.516267,50.399433],"type":"Point"}
}
