{
  "type": "Feature",
  "properties": {
    "iso:country":"GB",
    "wof:name":"TQ5 8BB",
    "wof:placetype":"postalcode"
},
  "geometry": {"coordinates":[-3.51620905624666,50.39940453156554],"type":"Point"}
}