{
  "type": "Feature",
  "properties": {
    "iso:country": "GB",
    "wof:name": "SG11 2RL",
    "wof:placetype": "postalcode"
  },
  "geometry": {"coordinates":[0.026254,51.911027],"type":"Point"}
}
