{
  "type": "Feature",
  "properties": {
    "iso:country":"GB",
    "wof:name":"RG4 6TG",
    "wof:placetype":"postalcode"
},
  "geometry": {"coordinates":[-0.90303213799463,51.46900503845011],"type":"Point"}
}