{
  "type": "Feature",
  "properties": {
    "iso:country":"GB",
    "wof:name":"G51 2PW",
    "wof:placetype":"postalcode"
},
  "geometry": {"coordinates":[-4.29978374248457,55.85732913190025],"type":"Point"}
}