{
  "type": "Feature",
  "properties": {
    "iso:country":"GB",
    "wof:name":"SE15 2SE",
    "wof:placetype":"postalcode"
},
  "geometry": {"coordinates":[-0.0607059223873,51.47981662310042],"type":"Point"}
}