{
  "type": "Feature",
  "properties": {
    "date:inception_lower":"1992-01-01",
    "date:inception_upper":"1992-01-31",
    "iso:country":"GB",
    "wof:name":"PL24 2AX",
    "wof:placetype":"postalcode"
},
  "geometry": {"coordinates":[-4.715338,50.362803],"type":"Point"}
}