{
  "type": "Feature",
  "properties": {
    "iso:country":"GB",
    "wof:name":"PL24 2AX",
    "wof:placetype":"postalcode"
},
  "geometry": {"coordinates":[-4.7153377144888,50.36280298218566],"type":"Point"}
}