{
  "type": "Feature",
  "properties": {
    "date:inception_lower": "1980-01-01",
    "date:inception_upper": "1980-01-01",
    "iso:country": "GB",
    "wof:name": "LE16 8DT",
    "wof:placetype": "postalcode"
  },
  "geometry": {"coordinates":[-0.821792,52.530584],"type":"Point"}
}
