{
  "type": "Feature",
  "properties": {
    "date:inception_lower": "1994-05-01",
    "date:inception_upper": "1994-05-01",
    "iso:country": "GB",
    "wof:name": "M22 9SW",
    "wof:placetype": "postalcode"
  },
  "geometry": {"coordinates":[-2.263355,53.383479],"type":"Point"}
}
