{
  "type": "Feature",
  "properties": {
    "iso:country":"GB",
    "wof:name":"M22 9SW",
    "wof:placetype":"postalcode"
},
  "geometry": {"coordinates":[-2.26335554301816,53.38347925097702],"type":"Point"}
}