{
  "type": "Feature",
  "properties": {
    "iso:country": "GB",
    "wof:name": "FY4 3RW",
    "wof:placetype": "postalcode"
  },
  "geometry": {"coordinates":[-3.021998,53.782231],"type":"Point"}
}
