{
  "type": "Feature",
  "properties": {
    "iso:country": "GB",
    "wof:name": "CM0 7GP",
    "wof:placetype": "postalcode"
  },
  "geometry": {"coordinates":[0.825181,51.659857],"type":"Point"}
}
