{
  "type": "Feature",
  "properties": {
    "date:inception_lower": "1980-01-01",
    "date:inception_upper": "1980-01-01",
    "iso:country": "GB",
    "wof:name": "TN34 1RE",
    "wof:placetype": "postalcode"
  },
  "geometry": {"coordinates":[0.582936,50.858126],"type":"Point"}
}
