{
  "type": "Feature",
  "properties": {
    "iso:country":"GB",
    "wof:name":"TN34 1RE",
    "wof:placetype":"postalcode"
},
  "geometry": {"coordinates":[0.58293610175141,50.85812597225936],"type":"Point"}
}