{
  "type": "Feature",
  "properties": {
    "date:inception_lower":"1980-01-01",
    "date:inception_upper":"1980-01-31",
    "iso:country":"GB",
    "wof:name":"GL5 1LN",
    "wof:placetype":"postalcode"
},
  "geometry": {"coordinates":[-2.210492,51.74514],"type":"Point"}
}