{
  "type": "Feature",
  "properties": {
    "iso:country":"GB",
    "wof:name":"GL5 1LN",
    "wof:placetype":"postalcode"
},
  "geometry": {"coordinates":[-2.21049201916919,51.74513984169637],"type":"Point"}
}