{
  "type": "Feature",
  "properties": {
    "iso:country": "GB",
    "wof:name": "KT10 9HN",
    "wof:placetype": "postalcode"
  },
  "geometry": {"coordinates":[-0.36258,51.346783],"type":"Point"}
}
