{
  "type": "Feature",
  "properties": {
    "iso:country":"GB",
    "wof:name":"KT10 9HN",
    "wof:placetype":"postalcode"
},
  "geometry": {"coordinates":[-0.36258033641816,51.34678272260648],"type":"Point"}
}