{
  "type": "Feature",
  "properties": {
    "date:inception_lower":"1980-01-01",
    "date:inception_upper":"1980-01-31",
    "iso:country":"GB",
    "wof:name":"EX15 2AD",
    "wof:placetype":"postalcode"
},
  "geometry": {"coordinates":[-3.324541,50.866311],"type":"Point"}
}