{
  "type": "Feature",
  "properties": {
    "date:inception_lower":"1995-01-01",
    "date:inception_upper":"1995-01-31",
    "iso:country":"GB",
    "wof:name":"NG15 7QT",
    "wof:placetype":"postalcode"
},
  "geometry": {"coordinates":[-1.190078,53.027501],"type":"Point"}
}