{
  "type": "Feature",
  "properties": {
    "iso:country":"GB",
    "wof:name":"LS11 8AD",
    "wof:placetype":"postalcode"
},
  "geometry": {"coordinates":[-1.56555160724909,53.77141297381931],"type":"Point"}
}