{
  "type": "Feature",
  "properties": {
    "date:inception_lower": "1980-01-01",
    "date:inception_upper": "1980-01-01",
    "iso:country": "GB",
    "wof:name": "LS11 8AD",
    "wof:placetype": "postalcode"
  },
  "geometry": {"coordinates":[-1.565552,53.771413],"type":"Point"}
}
