{
  "type": "Feature",
  "properties": {
    "iso:country": "GB",
    "wof:name": "LL24 0AZ",
    "wof:placetype": "postalcode"
  },
  "geometry": {"coordinates":[-3.801402,53.03912],"type":"Point"}
}
