{
  "type": "Feature",
  "properties": {
    "iso:country":"GB",
    "wof:name":"LL24 0AZ",
    "wof:placetype":"postalcode"
},
  "geometry": {"coordinates":[-3.80187908534245,53.03921344399018],"type":"Point"}
}