{
  "type": "Feature",
  "properties": {
    "iso:country":"GB",
    "wof:name":"OX7 6BT",
    "wof:placetype":"postalcode"
},
  "geometry": {"coordinates":[-1.59612782421022,51.85836364313472],"type":"Point"}
}