{
  "type": "Feature",
  "properties": {
    "iso:country":"GB",
    "wof:name":"WD25 8AZ",
    "wof:placetype":"postalcode"
},
  "geometry": {"coordinates":[-0.35403369653801,51.67395497246132],"type":"Point"}
}