{
  "type": "Feature",
  "properties": {
    "date:inception_lower":"2000-10-01",
    "date:inception_upper":"2000-10-31",
    "iso:country":"GB",
    "wof:name":"WD25 8AZ",
    "wof:placetype":"postalcode"
},
  "geometry": {"coordinates":[-0.35401,51.67396],"type":"Point"}
}