{
  "type": "Feature",
  "properties": {
    "iso:country": "GB",
    "wof:name": "NG12 4JP",
    "wof:placetype": "postalcode"
  },
  "geometry": {"coordinates":[-1.117369,52.90624],"type":"Point"}
}
