{
  "type": "Feature",
  "properties": {
    "iso:country":"GB",
    "wof:name":"HU15 1FR",
    "wof:placetype":"postalcode"
},
  "geometry": {"coordinates":[-0.5577957111994,53.7246233495568],"type":"Point"}
}