{
  "type": "Feature",
  "properties": {
    "date:inception_lower": "2008-06-01",
    "date:inception_upper": "2008-06-01",
    "iso:country": "GB",
    "wof:name": "HU15 1FR",
    "wof:placetype": "postalcode"
  },
  "geometry": {"coordinates":[-0.557796,53.724623],"type":"Point"}
}
