{
  "type": "Feature",
  "properties": {
    "iso:country": "GB",
    "wof:name": "PH16 5SR",
    "wof:placetype": "postalcode"
  },
  "geometry": {"coordinates":[-3.728132,56.696655],"type":"Point"}
}
