{
  "type": "Feature",
  "properties": {
    "iso:country":"GB",
    "wof:name":"TA22 9ED",
    "wof:placetype":"postalcode"
},
  "geometry": {"coordinates":[-3.54123774520379,51.03743011859067],"type":"Point"}
}