{
  "type": "Feature",
  "properties": {
    "iso:country":"GB",
    "wof:name":"WF4 3NU",
    "wof:placetype":"postalcode"
},
  "geometry": {"coordinates":[-1.5317855692707,53.63828776555149],"type":"Point"}
}