{
  "type": "Feature",
  "properties": {
    "iso:country":"GB",
    "wof:name":"SA4 4BE",
    "wof:placetype":"postalcode"
},
  "geometry": {"coordinates":[-4.03837373179459,51.67247566598714],"type":"Point"}
}