{
  "type": "Feature",
  "properties": {
    "date:inception_lower": "2007-05-01",
    "date:inception_upper": "2007-05-01",
    "iso:country": "GB",
    "wof:name": "SA4 4BE",
    "wof:placetype": "postalcode"
  },
  "geometry": {"coordinates":[-4.038374,51.672476],"type":"Point"}
}
