{
  "type": "Feature",
  "properties": {
    "date:inception_lower": "1987-04-01",
    "date:inception_upper": "1987-04-01",
    "iso:country": "GB",
    "wof:name": "ST8 7JF",
    "wof:placetype": "postalcode"
  },
  "geometry": {"coordinates":[-2.160881,53.119499],"type":"Point"}
}
