{
  "type": "Feature",
  "properties": {
    "date:inception_lower": "1980-01-01",
    "date:inception_upper": "1980-01-01",
    "iso:country": "GB",
    "wof:name": "YO22 4AG",
    "wof:placetype": "postalcode"
  },
  "geometry": {"coordinates":[-0.609423,54.483476],"type":"Point"}
}
