{
  "type": "Feature",
  "properties": {
    "iso:country":"GB",
    "wof:name":"YO22 4AG",
    "wof:placetype":"postalcode"
},
  "geometry": {"coordinates":[-0.60946546259016,54.4835335687636],"type":"Point"}
}