{
  "type": "Feature",
  "properties": {
    "iso:country": "GB",
    "wof:name": "YO22 4AG",
    "wof:placetype": "postalcode"
  },
  "geometry": {"coordinates":[-0.609465,54.483534],"type":"Point"}
}
