{
  "type": "Feature",
  "properties": {
    "iso:country":"GB",
    "wof:name":"BL3 4HL",
    "wof:placetype":"postalcode"
},
  "geometry": {"coordinates":[-2.45855465933113,53.56621869059283],"type":"Point"}
}