{
  "type": "Feature",
  "properties": {
    "iso:country":"GB",
    "wof:name":"DA1 1JJ",
    "wof:placetype":"postalcode"
},
  "geometry": {"coordinates":[0.21528356333825,51.43831603240511],"type":"Point"}
}