{
  "type": "Feature",
  "properties": {
    "iso:country": "GB",
    "wof:name": "DA1 1JJ",
    "wof:placetype": "postalcode"
  },
  "geometry": {"coordinates":[0.215284,51.438316],"type":"Point"}
}
