{
  "type": "Feature",
  "properties": {
    "iso:country":"GB",
    "wof:name":"WA3 2EB",
    "wof:placetype":"postalcode"
},
  "geometry": {"coordinates":[-2.58201166516216,53.47557165804778],"type":"Point"}
}