{
  "type": "Feature",
  "properties": {
    "iso:country": "GB",
    "wof:name": "HD6 3AB",
    "wof:placetype": "postalcode"
  },
  "geometry": {"coordinates":[-1.799829,53.685052],"type":"Point"}
}
