{
  "type": "Feature",
  "properties": {
    "date:inception_lower": "2016-12-01",
    "date:inception_upper": "2016-12-01",
    "iso:country": "GB",
    "wof:name": "HD6 3AB",
    "wof:placetype": "postalcode"
  },
  "geometry": {"coordinates":[-1.799829,53.685052],"type":"Point"}
}
