{
  "type": "Feature",
  "properties": {
    "iso:country":"GB",
    "wof:name":"W14 9LS",
    "wof:placetype":"postalcode"
},
  "geometry": {"coordinates":[-0.20538135727825,51.49014141621457],"type":"Point"}
}