{
  "type": "Feature",
  "properties": {
    "iso:country":"GB",
    "wof:name":"SW9 0PL",
    "wof:placetype":"postalcode"
},
  "geometry": {"coordinates":[-0.11335468703446,51.47396710452488],"type":"Point"}
}