{
  "type": "Feature",
  "properties": {
    "iso:country": "GB",
    "wof:name": "SW9 0PL",
    "wof:placetype": "postalcode"
  },
  "geometry": {"coordinates":[-0.113355,51.473967],"type":"Point"}
}
