{
  "type": "Feature",
  "properties": {
    "iso:country":"GB",
    "wof:name":"PA20 9JB",
    "wof:placetype":"postalcode"
},
  "geometry": {"coordinates":[-5.05060689758821,55.83386572504518],"type":"Point"}
}