{
  "type": "Feature",
  "properties": {
    "iso:country":"GB",
    "wof:name":"LL11 2EW",
    "wof:placetype":"postalcode"
},
  "geometry": {"coordinates":[-2.99422898163511,53.05696931084335],"type":"Point"}
}