{
  "type": "Feature",
  "properties": {
    "iso:country": "GB",
    "wof:name": "LL11 2EW",
    "wof:placetype": "postalcode"
  },
  "geometry": {"coordinates":[-2.994229,53.056969],"type":"Point"}
}
