{
  "type": "Feature",
  "properties": {
    "date:inception_lower":"2007-09-01",
    "date:inception_upper":"2007-09-30",
    "iso:country":"GB",
    "wof:name":"HR4 9SZ",
    "wof:placetype":"postalcode"
},
  "geometry": {"coordinates":[-2.716551,52.071054],"type":"Point"}
}