{
  "type": "Feature",
  "properties": {
    "iso:country":"GB",
    "wof:name":"HR4 9SZ",
    "wof:placetype":"postalcode"
},
  "geometry": {"coordinates":[-2.71655144171575,52.07105387924775],"type":"Point"}
}