{
  "type": "Feature",
  "properties": {
    "iso:country":"GB",
    "wof:name":"EH8 9PG",
    "wof:placetype":"postalcode"
},
  "geometry": {"coordinates":[-3.17739175240414,55.94046385281102],"type":"Point"}
}