{
  "type": "Feature",
  "properties": {
    "iso:country":"GB",
    "wof:name":"NG22 8LA",
    "wof:placetype":"postalcode"
},
  "geometry": {"coordinates":[-1.03686773857925,53.10539460706752],"type":"Point"}
}