{
  "type": "Feature",
  "properties": {
    "iso:country": "GB",
    "wof:name": "MK45 3AG",
    "wof:placetype": "postalcode"
  },
  "geometry": {"coordinates":[-0.418683,52.097662],"type":"Point"}
}
