{
  "type": "Feature",
  "properties": {
    "date:inception_lower":"1980-01-01",
    "date:inception_upper":"1980-01-31",
    "iso:country":"GB",
    "wof:name":"MK45 3AG",
    "wof:placetype":"postalcode"
},
  "geometry": {"coordinates":[-0.418683,52.097662],"type":"Point"}
}