{
  "type": "Feature",
  "properties": {
    "date:inception_lower": "1997-12-01",
    "date:inception_upper": "1997-12-01",
    "iso:country": "GB",
    "wof:name": "BS36 1HF",
    "wof:placetype": "postalcode"
  },
  "geometry": {"coordinates":[-2.506813,51.521493],"type":"Point"}
}
