{
  "type": "Feature",
  "properties": {
    "iso:country":"GB",
    "wof:name":"PO7 7PY",
    "wof:placetype":"postalcode"
},
  "geometry": {"coordinates":[-1.02252953458622,50.88624962153512],"type":"Point"}
}