{
  "type": "Feature",
  "properties": {
    "date:inception_lower": "1980-01-01",
    "date:inception_upper": "1980-01-01",
    "iso:country": "GB",
    "wof:name": "PO7 7PY",
    "wof:placetype": "postalcode"
  },
  "geometry": {"coordinates":[-1.022529,50.88625],"type":"Point"}
}
