{
  "type": "Feature",
  "properties": {
    "iso:country":"GB",
    "wof:name":"NW1 0RA",
    "wof:placetype":"postalcode"
},
  "geometry": {"coordinates":[-0.13562065919308,51.54093985461999],"type":"Point"}
}