{
  "type": "Feature",
  "properties": {
    "iso:country":"GB",
    "wof:name":"LS26 8LB",
    "wof:placetype":"postalcode"
},
  "geometry": {"coordinates":[-1.45283530393208,53.74929938722358],"type":"Point"}
}