{
  "type": "Feature",
  "properties": {
    "iso:country":"GB",
    "wof:name":"DA12 2NT",
    "wof:placetype":"postalcode"
},
  "geometry": {"coordinates":[0.39819702797735,51.43549801439475],"type":"Point"}
}