{
  "type": "Feature",
  "properties": {
    "iso:country": "GB",
    "wof:name": "DA12 2NT",
    "wof:placetype": "postalcode"
  },
  "geometry": {"coordinates":[0.398197,51.435498],"type":"Point"}
}
