{
  "type": "Feature",
  "properties": {
    "date:inception_lower": "1990-07-01",
    "date:inception_upper": "1990-07-01",
    "iso:country": "GB",
    "wof:name": "DA12 2NT",
    "wof:placetype": "postalcode"
  },
  "geometry": {"coordinates":[0.398197,51.435498],"type":"Point"}
}
