{
  "type": "Feature",
  "properties": {
    "iso:country":"GB",
    "wof:name":"DL6 2EW",
    "wof:placetype":"postalcode"
},
  "geometry": {"coordinates":[-1.46858852732908,54.43536023513418],"type":"Point"}
}