{
  "type": "Feature",
  "properties": {
    "iso:country": "GB",
    "wof:name": "DL6 2EW",
    "wof:placetype": "postalcode"
  },
  "geometry": {"coordinates":[-1.468598,54.435426],"type":"Point"}
}
