{
  "type": "Feature",
  "properties": {
    "date:inception_lower": "1980-01-01",
    "date:inception_upper": "1980-01-01",
    "iso:country": "GB",
    "wof:name": "DL6 2EW",
    "wof:placetype": "postalcode"
  },
  "geometry": {"coordinates":[-1.468598,54.435372],"type":"Point"}
}
