{
  "type": "Feature",
  "properties": {
    "iso:country":"GB",
    "wof:name":"SN25 1WA",
    "wof:placetype":"postalcode"
},
  "geometry": {"coordinates":[-1.82773027587824,51.59442931844823],"type":"Point"}
}