{
  "type": "Feature",
  "properties": {
    "date:inception_lower": "1980-01-01",
    "date:inception_upper": "1980-01-01",
    "iso:country": "GB",
    "wof:name": "WF5 9DE",
    "wof:placetype": "postalcode"
  },
  "geometry": {"coordinates":[-1.579815,53.681877],"type":"Point"}
}
