{
  "type": "Feature",
  "properties": {
    "iso:country":"GB",
    "wof:name":"LS12 3NG",
    "wof:placetype":"postalcode"
},
  "geometry": {"coordinates":[-1.59680580805137,53.80000518153633],"type":"Point"}
}