{
  "type": "Feature",
  "properties": {
    "date:inception_lower": "1980-01-01",
    "date:inception_upper": "1980-01-01",
    "iso:country": "GB",
    "wof:name": "LS12 3NG",
    "wof:placetype": "postalcode"
  },
  "geometry": {"coordinates":[-1.596806,53.800005],"type":"Point"}
}
