{
  "type": "Feature",
  "properties": {
    "iso:country":"GB",
    "wof:name":"PH33 7JA",
    "wof:placetype":"postalcode"
},
  "geometry": {"coordinates":[-5.09856646239816,56.84102660190929],"type":"Point"}
}