{
  "type": "Feature",
  "properties": {
    "iso:country": "GB",
    "wof:name": "HD4 6BT",
    "wof:placetype": "postalcode"
  },
  "geometry": {"coordinates":[-1.749914,53.612175],"type":"Point"}
}
