{
  "type": "Feature",
  "properties": {
    "iso:country":"GB",
    "wof:name":"CF11 6LW",
    "wof:placetype":"postalcode"
},
  "geometry": {"coordinates":[-3.18862225080032,51.47950835562807],"type":"Point"}
}