{
  "type": "Feature",
  "properties": {
    "date:inception_lower":"1999-06-01",
    "date:inception_upper":"1999-06-30",
    "iso:country":"GB",
    "wof:name":"CF11 6LW",
    "wof:placetype":"postalcode"
},
  "geometry": {"coordinates":[-3.188622,51.479508],"type":"Point"}
}