{
  "type": "Feature",
  "properties": {
    "iso:country":"GB",
    "wof:name":"IP28 8ER",
    "wof:placetype":"postalcode"
},
  "geometry": {"coordinates":[0.49248875637932,52.30836045311855],"type":"Point"}
}