{
  "type": "Feature",
  "properties": {
    "date:inception_lower": "2022-11-01",
    "date:inception_upper": "2022-11-01",
    "iso:country": "GB",
    "wof:name": "SA62 4AZ",
    "wof:placetype": "postalcode"
  },
  "geometry": {"coordinates":[-4.959462,51.762469],"type":"Point"}
}
