{
  "type": "Feature",
  "properties": {
    "date:inception_lower":"1980-01-01",
    "date:inception_upper":"1980-01-31",
    "iso:country":"GB",
    "wof:name":"KA1 5LL",
    "wof:placetype":"postalcode"
},
  "geometry": {"coordinates":[-4.48101,55.570886],"type":"Point"}
}