{
  "type": "Feature",
  "properties": {
    "iso:country":"GB",
    "wof:name":"KA1 5LL",
    "wof:placetype":"postalcode"
},
  "geometry": {"coordinates":[-4.48101007221001,55.57088617218965],"type":"Point"}
}