{
  "type": "Feature",
  "properties": {
    "iso:country":"GB",
    "wof:name":"PE9 2SZ",
    "wof:placetype":"postalcode"
},
  "geometry": {"coordinates":[-0.50317857163019,52.65377894059606],"type":"Point"}
}