{
  "type": "Feature",
  "properties": {
    "date:inception_lower": "1980-01-01",
    "date:inception_upper": "1980-01-01",
    "iso:country": "GB",
    "wof:name": "PE9 2SZ",
    "wof:placetype": "postalcode"
  },
  "geometry": {"coordinates":[-0.503179,52.653779],"type":"Point"}
}
