{
  "type": "Feature",
  "properties": {
    "date:inception_lower": "1995-12-01",
    "date:inception_upper": "1995-12-01",
    "iso:country": "GB",
    "wof:name": "DD10 8NZ",
    "wof:placetype": "postalcode"
  },
  "geometry": {"coordinates":[-2.464898,56.713749],"type":"Point"}
}
