{
  "type": "Feature",
  "properties": {
    "iso:country":"GB",
    "wof:name":"DD10 8NZ",
    "wof:placetype":"postalcode"
},
  "geometry": {"coordinates":[-2.46489825670489,56.71374921407804],"type":"Point"}
}