{
  "type": "Feature",
  "properties": {
    "iso:country":"GB",
    "wof:name":"PL9 0DY",
    "wof:placetype":"postalcode"
},
  "geometry": {"coordinates":[-4.09032818671882,50.32996018290612],"type":"Point"}
}