{
  "type": "Feature",
  "properties": {
    "date:inception_lower": "1980-01-01",
    "date:inception_upper": "1980-01-01",
    "iso:country": "GB",
    "wof:name": "PL9 0DY",
    "wof:placetype": "postalcode"
  },
  "geometry": {"coordinates":[-4.090328,50.32996],"type":"Point"}
}
