{
  "type": "Feature",
  "properties": {
    "iso:country":"GB",
    "wof:name":"SE17 1PZ",
    "wof:placetype":"postalcode"
},
  "geometry": {"coordinates":[-0.09001370545374,51.49324703896033],"type":"Point"}
}