{
  "type": "Feature",
  "properties": {
    "iso:country": "GB",
    "wof:name": "SE17 1PZ",
    "wof:placetype": "postalcode"
  },
  "geometry": {"coordinates":[-0.090014,51.493247],"type":"Point"}
}
