{
  "type": "Feature",
  "properties": {
    "iso:country":"GB",
    "wof:name":"NW5 2BY",
    "wof:placetype":"postalcode"
},
  "geometry": {"coordinates":[-0.14098697883387,51.54832689346331],"type":"Point"}
}