{
  "type": "Feature",
  "properties": {
    "date:inception_lower":"1980-01-01",
    "date:inception_upper":"1980-01-31",
    "iso:country":"GB",
    "wof:name":"NW5 2BY",
    "wof:placetype":"postalcode"
},
  "geometry": {"coordinates":[-0.140987,51.548327],"type":"Point"}
}