{
  "type": "Feature",
  "properties": {
    "iso:country":"GB",
    "wof:name":"GU14 7NW",
    "wof:placetype":"postalcode"
},
  "geometry": {"coordinates":[-0.75500439318984,51.29410513928087],"type":"Point"}
}