{
  "type": "Feature",
  "properties": {
    "iso:country":"GB",
    "wof:name":"GL20 8LL",
    "wof:placetype":"postalcode"
},
  "geometry": {"coordinates":[-2.1007388090535,51.9944681111163],"type":"Point"}
}