{
  "type": "Feature",
  "properties": {
    "date:inception_lower": "1980-01-01",
    "date:inception_upper": "1980-01-01",
    "iso:country": "GB",
    "wof:name": "GL20 8LL",
    "wof:placetype": "postalcode"
  },
  "geometry": {"coordinates":[-2.100746,51.994469],"type":"Point"}
}
