{
  "type": "Feature",
  "properties": {
    "iso:country":"GB",
    "wof:name":"TS10 2PZ",
    "wof:placetype":"postalcode"
},
  "geometry": {"coordinates":[-1.05261378366121,54.60006855019601],"type":"Point"}
}