{
  "type": "Feature",
  "properties": {
    "date:inception_lower": "1990-02-01",
    "date:inception_upper": "1990-02-01",
    "iso:country": "GB",
    "wof:name": "TS10 2PZ",
    "wof:placetype": "postalcode"
  },
  "geometry": {"coordinates":[-1.052614,54.600069],"type":"Point"}
}
