{
  "type": "Feature",
  "properties": {
    "iso:country": "GB",
    "wof:name": "RG45 6GU",
    "wof:placetype": "postalcode"
  },
  "geometry": {"coordinates":[-0.79351,51.38166],"type":"Point"}
}
