{
  "type": "Feature",
  "properties": {
    "date:inception_lower": "1990-02-01",
    "date:inception_upper": "1990-02-01",
    "iso:country": "GB",
    "wof:name": "WR3 8DW",
    "wof:placetype": "postalcode"
  },
  "geometry": {"coordinates":[-2.215102,52.211404],"type":"Point"}
}
