{
  "type": "Feature",
  "properties": {
    "date:inception_lower":"1990-02-01",
    "date:inception_upper":"1990-02-28",
    "iso:country":"GB",
    "wof:name":"WR3 8DW",
    "wof:placetype":"postalcode"
},
  "geometry": {"coordinates":[-2.215135,52.211373],"type":"Point"}
}