{
  "type": "Feature",
  "properties": {
    "iso:country":"GB",
    "wof:name":"WR3 8DW",
    "wof:placetype":"postalcode"
},
  "geometry": {"coordinates":[-2.21513529145371,52.21137335381215],"type":"Point"}
}