{
  "type": "Feature",
  "properties": {
    "iso:country": "GB",
    "wof:name": "WR3 8DW",
    "wof:placetype": "postalcode"
  },
  "geometry": {"coordinates":[-2.215135,52.211373],"type":"Point"}
}
