{
  "type": "Feature",
  "properties": {
    "iso:country":"GB",
    "wof:name":"CO16 0BY",
    "wof:placetype":"postalcode"
},
  "geometry": {"coordinates":[1.11652798611682,51.87452929629519],"type":"Point"}
}