{
  "type": "Feature",
  "properties": {
    "iso:country": "GB",
    "wof:name": "CO16 0BY",
    "wof:placetype": "postalcode"
  },
  "geometry": {"coordinates":[1.116528,51.874529],"type":"Point"}
}
