{
  "type": "Feature",
  "properties": {
    "date:inception_lower":"1987-04-01",
    "date:inception_upper":"1987-04-30",
    "iso:country":"GB",
    "wof:name":"CO16 0BY",
    "wof:placetype":"postalcode"
},
  "geometry": {"coordinates":[1.116528,51.874529],"type":"Point"}
}