{
  "type": "Feature",
  "properties": {
    "iso:country": "GB",
    "wof:name": "L34 2SF",
    "wof:placetype": "postalcode"
  },
  "geometry": {"coordinates":[-2.793765,53.430649],"type":"Point"}
}
