{
  "type": "Feature",
  "properties": {
    "iso:country":"GB",
    "wof:name":"BB9 7XD",
    "wof:placetype":"postalcode"
},
  "geometry": {"coordinates":[-2.21277722541419,53.83910499960665],"type":"Point"}
}