{
  "type": "Feature",
  "properties": {
    "iso:country":"GB",
    "wof:name":"AB34 5JG",
    "wof:placetype":"postalcode"
},
  "geometry": {"coordinates":[-2.77673646677896,57.07658330694199],"type":"Point"}
}