{
  "type": "Feature",
  "properties": {
    "iso:country":"GB",
    "wof:name":"WF9 5EQ",
    "wof:placetype":"postalcode"
},
  "geometry": {"coordinates":[-1.36745871530858,53.62502086299032],"type":"Point"}
}