{
  "type": "Feature",
  "properties": {
    "iso:country":"GB",
    "wof:name":"SW12 9LL",
    "wof:placetype":"postalcode"
},
  "geometry": {"coordinates":[-0.14703758951053,51.45045811797945],"type":"Point"}
}