{
  "type": "Feature",
  "properties": {
    "iso:country": "GB",
    "wof:name": "SW12 9LL",
    "wof:placetype": "postalcode"
  },
  "geometry": {"coordinates":[-0.14701,51.450495],"type":"Point"}
}
