{
  "type": "Feature",
  "properties": {
    "iso:country":"GB",
    "wof:name":"UB3 2LP",
    "wof:placetype":"postalcode"
},
  "geometry": {"coordinates":[-0.42073153788838,51.51420894395536],"type":"Point"}
}