{
  "type": "Feature",
  "properties": {
    "iso:country":"GB",
    "wof:name":"SG2 9QZ",
    "wof:placetype":"postalcode"
},
  "geometry": {"coordinates":[-0.16753229476301,51.89086135903562],"type":"Point"}
}