{
  "type": "Feature",
  "properties": {
    "iso:country":"GB",
    "wof:name":"E18 2EU",
    "wof:placetype":"postalcode"
},
  "geometry": {"coordinates":[0.0225924804249,51.59005332186611],"type":"Point"}
}