{
  "type": "Feature",
  "properties": {
    "iso:country":"GB",
    "wof:name":"WR4 9AN",
    "wof:placetype":"postalcode"
},
  "geometry": {"coordinates":[-2.20796106380721,52.19507765003637],"type":"Point"}
}