{
  "type": "Feature",
  "properties": {
    "date:inception_lower": "2007-05-01",
    "date:inception_upper": "2007-05-01",
    "iso:country": "GB",
    "wof:name": "WR4 9AN",
    "wof:placetype": "postalcode"
  },
  "geometry": {"coordinates":[-2.207961,52.195078],"type":"Point"}
}
