{
  "type": "Feature",
  "properties": {
    "date:inception_lower": "1998-06-01",
    "date:inception_upper": "1998-06-01",
    "iso:country": "GB",
    "wof:name": "YO90 1WR",
    "wof:placetype": "postalcode"
  },
  "geometry": {"coordinates":[-1.087143,53.95924],"type":"Point"}
}
