{
  "type": "Feature",
  "properties": {
    "iso:country": "GB",
    "wof:name": "WD18 7NB",
    "wof:placetype": "postalcode"
  },
  "geometry": {"coordinates":[-0.407565,51.653184],"type":"Point"}
}
