{
  "type": "Feature",
  "properties": {
    "iso:country":"GB",
    "wof:name":"TQ7 2LB",
    "wof:placetype":"postalcode"
},
  "geometry": {"coordinates":[-3.6936449736146,50.27262272782721],"type":"Point"}
}