{
  "type": "Feature",
  "properties": {
    "date:inception_lower":"1980-01-01",
    "date:inception_upper":"1980-01-31",
    "iso:country":"GB",
    "wof:name":"TQ7 2LB",
    "wof:placetype":"postalcode"
},
  "geometry": {"coordinates":[-3.693645,50.272623],"type":"Point"}
}