{
  "type": "Feature",
  "properties": {
    "iso:country": "GB",
    "wof:name": "CV1 5LN",
    "wof:placetype": "postalcode"
  },
  "geometry": {"coordinates":[-1.493037,52.409159],"type":"Point"}
}
