{
  "type": "Feature",
  "properties": {
    "iso:country": "GB",
    "wof:name": "EX13 7TE",
    "wof:placetype": "postalcode"
  },
  "geometry": {"coordinates":[-3.020386,50.819197],"type":"Point"}
}
