{
  "type": "Feature",
  "properties": {
    "iso:country":"GB",
    "wof:name":"PR2 9PQ",
    "wof:placetype":"postalcode"
},
  "geometry": {"coordinates":[-2.70301406303963,53.79392823010752],"type":"Point"}
}