{
  "type": "Feature",
  "properties": {
    "iso:country":"GB",
    "wof:name":"RH19 4EA",
    "wof:placetype":"postalcode"
},
  "geometry": {"coordinates":[-0.00617968070414,51.12265518075198],"type":"Point"}
}