{
  "type": "Feature",
  "properties": {
    "date:inception_lower": "2002-05-01",
    "date:inception_upper": "2002-05-01",
    "iso:country": "GB",
    "wof:name": "SW18 4GZ",
    "wof:placetype": "postalcode"
  },
  "geometry": {"coordinates":[-0.191032,51.45271],"type":"Point"}
}
