{
  "type": "Feature",
  "properties": {
    "date:inception_lower": "1980-01-01",
    "date:inception_upper": "1980-01-01",
    "iso:country": "GB",
    "wof:name": "SG6 1TB",
    "wof:placetype": "postalcode"
  },
  "geometry": {"coordinates":[-0.225033,51.973532],"type":"Point"}
}
