{
  "type": "Feature",
  "properties": {
    "iso:country":"GB",
    "wof:name":"SG6 1TB",
    "wof:placetype":"postalcode"
},
  "geometry": {"coordinates":[-0.225033435193,51.97353246529],"type":"Point"}
}