{
  "type": "Feature",
  "properties": {
    "iso:country": "GB",
    "wof:name": "GL50 1PY",
    "wof:placetype": "postalcode"
  },
  "geometry": {"coordinates":[-2.076793,51.899813],"type":"Point"}
}
