{
  "type": "Feature",
  "properties": {
    "iso:country": "GB",
    "wof:name": "LL22 9YW",
    "wof:placetype": "postalcode"
  },
  "geometry": {"coordinates":[-3.570489,53.295954],"type":"Point"}
}
