{
  "type": "Feature",
  "properties": {
    "date:inception_lower": "1981-06-01",
    "date:inception_upper": "1981-06-01",
    "iso:country": "GB",
    "wof:name": "LL22 9YW",
    "wof:placetype": "postalcode"
  },
  "geometry": {"coordinates":[-3.570489,53.295954],"type":"Point"}
}
