{
  "type": "Feature",
  "properties": {
    "iso:country":"GB",
    "wof:name":"SE23 3UW",
    "wof:placetype":"postalcode"
},
  "geometry": {"coordinates":[-0.05989217803255,51.43891346976378],"type":"Point"}
}