{
  "type": "Feature",
  "properties": {
    "date:inception_lower": "1980-01-01",
    "date:inception_upper": "1980-01-01",
    "iso:country": "GB",
    "wof:name": "HX7 5JD",
    "wof:placetype": "postalcode"
  },
  "geometry": {"coordinates":[-1.980229,53.727338],"type":"Point"}
}
