{
  "type": "Feature",
  "properties": {
    "date:inception_lower":"1980-01-01",
    "date:inception_upper":"1980-01-31",
    "iso:country":"GB",
    "wof:name":"S8 8LL",
    "wof:placetype":"postalcode"
},
  "geometry": {"coordinates":[-1.461652,53.340643],"type":"Point"}
}