{
  "type": "Feature",
  "properties": {
    "iso:country":"GB",
    "wof:name":"S8 8LL",
    "wof:placetype":"postalcode"
},
  "geometry": {"coordinates":[-1.46189359304104,53.34057247650298],"type":"Point"}
}