{
  "type": "Feature",
  "properties": {
    "iso:country":"GB",
    "wof:name":"WF14 0LT",
    "wof:placetype":"postalcode"
},
  "geometry": {"coordinates":[-1.70107068368572,53.68796822130732],"type":"Point"}
}