{
  "type": "Feature",
  "properties": {
    "iso:country":"GB",
    "wof:name":"NE61 4PL",
    "wof:placetype":"postalcode"
},
  "geometry": {"coordinates":[-1.92297700746166,55.23920441551469],"type":"Point"}
}