{
  "type": "Feature",
  "properties": {
    "iso:country": "GB",
    "wof:name": "NE61 4PL",
    "wof:placetype": "postalcode"
  },
  "geometry": {"coordinates":[-1.922977,55.239204],"type":"Point"}
}
