{
  "type": "Feature",
  "properties": {
    "iso:country":"GB",
    "wof:name":"SE6 4HQ",
    "wof:placetype":"postalcode"
},
  "geometry": {"coordinates":[-0.0196757007694,51.44622645930735],"type":"Point"}
}