{
  "type": "Feature",
  "properties": {
    "iso:country":"GB",
    "wof:name":"PL1 4JZ",
    "wof:placetype":"postalcode"
},
  "geometry": {"coordinates":[-4.16784540376845,50.37000443093583],"type":"Point"}
}