{
  "type": "Feature",
  "properties": {
    "iso:country": "GB",
    "wof:name": "WV6 8QW",
    "wof:placetype": "postalcode"
  },
  "geometry": {"coordinates":[-2.167854,52.596924],"type":"Point"}
}
