{
  "type": "Feature",
  "properties": {
    "date:inception_lower": "2015-11-01",
    "date:inception_upper": "2015-11-01",
    "iso:country": "GB",
    "wof:name": "WV6 8QW",
    "wof:placetype": "postalcode"
  },
  "geometry": {"coordinates":[-2.167854,52.596924],"type":"Point"}
}
