{
  "type": "Feature",
  "properties": {
    "iso:country":"GB",
    "wof:name":"WV6 8QW",
    "wof:placetype":"postalcode"
},
  "geometry": {"coordinates":[-2.1678742979898,52.59693594903842],"type":"Point"}
}