{
  "type": "Feature",
  "properties": {
    "iso:country":"GB",
    "wof:name":"SY21 0QG",
    "wof:placetype":"postalcode"
},
  "geometry": {"coordinates":[-3.43079893003793,52.73471925266352],"type":"Point"}
}