{
  "type": "Feature",
  "properties": {
    "date:inception_lower":"1980-01-01",
    "date:inception_upper":"1980-01-31",
    "iso:country":"GB",
    "wof:name":"SY21 0QG",
    "wof:placetype":"postalcode"
},
  "geometry": {"coordinates":[-3.430799,52.734719],"type":"Point"}
}