{
  "type": "Feature",
  "properties": {
    "iso:country": "GB",
    "wof:name": "CV35 7QW",
    "wof:placetype": "postalcode"
  },
  "geometry": {"coordinates":[-1.572338,52.319037],"type":"Point"}
}
