{
  "type": "Feature",
  "properties": {
    "date:inception_lower": "1980-01-01",
    "date:inception_upper": "1980-01-01",
    "iso:country": "GB",
    "wof:name": "NW5 4SF",
    "wof:placetype": "postalcode"
  },
  "geometry": {"coordinates":[-0.156879,51.552753],"type":"Point"}
}
