{
  "type": "Feature",
  "properties": {
    "iso:country":"GB",
    "wof:name":"SW1X 9PB",
    "wof:placetype":"postalcode"
},
  "geometry": {"coordinates":[-0.15896162272377,51.49605831767155],"type":"Point"}
}