{
  "type": "Feature",
  "properties": {
    "iso:country":"GB",
    "wof:name":"G46 8AQ",
    "wof:placetype":"postalcode"
},
  "geometry": {"coordinates":[-4.33276806458404,55.80484911600525],"type":"Point"}
}