{
  "type": "Feature",
  "properties": {
    "date:inception_lower": "1980-01-01",
    "date:inception_upper": "1980-01-01",
    "iso:country": "GB",
    "wof:name": "G46 8AQ",
    "wof:placetype": "postalcode"
  },
  "geometry": {"coordinates":[-4.332769,55.804858],"type":"Point"}
}
