{
  "type": "Feature",
  "properties": {
    "iso:country":"GB",
    "wof:name":"DL5 7NU",
    "wof:placetype":"postalcode"
},
  "geometry": {"coordinates":[-1.57858437392179,54.62620885058865],"type":"Point"}
}