{
  "type": "Feature",
  "properties": {
    "iso:country": "GB",
    "wof:name": "DL5 7NU",
    "wof:placetype": "postalcode"
  },
  "geometry": {"coordinates":[-1.578584,54.626209],"type":"Point"}
}
