{
  "type": "Feature",
  "properties": {
    "date:inception_lower":"2010-12-01",
    "date:inception_upper":"2010-12-31",
    "iso:country":"GB",
    "wof:name":"RG4 8EJ",
    "wof:placetype":"postalcode"
},
  "geometry": {"coordinates":[-0.975895,51.478026],"type":"Point"}
}