{
  "type": "Feature",
  "properties": {
    "iso:country": "GB",
    "wof:name": "RG4 8EJ",
    "wof:placetype": "postalcode"
  },
  "geometry": {"coordinates":[-0.975895,51.478026],"type":"Point"}
}
