{
  "type": "Feature",
  "properties": {
    "iso:country":"GB",
    "wof:name":"RG4 8EJ",
    "wof:placetype":"postalcode"
},
  "geometry": {"coordinates":[-0.97589467118748,51.47802627570318],"type":"Point"}
}