{
  "type": "Feature",
  "properties": {
    "iso:country":"GB",
    "wof:name":"CM9 8ET",
    "wof:placetype":"postalcode"
},
  "geometry": {"coordinates":[0.77584292983684,51.79882426392111],"type":"Point"}
}