{
  "type": "Feature",
  "properties": {
    "date:inception_lower":"1980-01-01",
    "date:inception_upper":"1980-01-31",
    "iso:country":"GB",
    "wof:name":"CM9 8ET",
    "wof:placetype":"postalcode"
},
  "geometry": {"coordinates":[0.775843,51.798824],"type":"Point"}
}