{
  "type": "Feature",
  "properties": {
    "iso:country": "GB",
    "wof:name": "CM9 8ET",
    "wof:placetype": "postalcode"
  },
  "geometry": {"coordinates":[0.775843,51.798824],"type":"Point"}
}
