{
  "type": "Feature",
  "properties": {
    "iso:country": "GB",
    "wof:name": "SY10 8LR",
    "wof:placetype": "postalcode"
  },
  "geometry": {"coordinates":[-3.081107,52.810244],"type":"Point"}
}
