{
  "type": "Feature",
  "properties": {
    "date:inception_lower": "1980-01-01",
    "date:inception_upper": "1980-01-01",
    "iso:country": "GB",
    "wof:name": "SY10 8LR",
    "wof:placetype": "postalcode"
  },
  "geometry": {"coordinates":[-3.081107,52.810244],"type":"Point"}
}
