{
  "type": "Feature",
  "properties": {
    "iso:country":"GB",
    "wof:name":"SY10 8LR",
    "wof:placetype":"postalcode"
},
  "geometry": {"coordinates":[-3.08110676809595,52.81024414431307],"type":"Point"}
}