{
  "type": "Feature",
  "properties": {
    "date:inception_lower": "2000-06-01",
    "date:inception_upper": "2000-06-01",
    "iso:country": "GB",
    "wof:name": "SN5 8WF",
    "wof:placetype": "postalcode"
  },
  "geometry": {"coordinates":[-1.811046,51.555273],"type":"Point"}
}
