{
  "type": "Feature",
  "properties": {
    "date:inception_lower": "1980-01-01",
    "date:inception_upper": "1980-01-01",
    "iso:country": "GB",
    "wof:name": "LU2 9HN",
    "wof:placetype": "postalcode"
  },
  "geometry": {"coordinates":[-0.382745,51.885914],"type":"Point"}
}
