{
  "type": "Feature",
  "properties": {
    "iso:country": "GB",
    "wof:name": "DN1 1SB",
    "wof:placetype": "postalcode"
  },
  "geometry": {"coordinates":[-1.136888,53.522172],"type":"Point"}
}
