{
  "type": "Feature",
  "properties": {
    "date:inception_lower": "1980-01-01",
    "date:inception_upper": "1980-01-01",
    "iso:country": "GB",
    "wof:name": "NP7 0PR",
    "wof:placetype": "postalcode"
  },
  "geometry": {"coordinates":[-3.127111,51.800875],"type":"Point"}
}
