{
  "type": "Feature",
  "properties": {
    "date:inception_lower": "2019-10-01",
    "date:inception_upper": "2019-10-01",
    "iso:country": "GB",
    "wof:name": "EN6 1DP",
    "wof:placetype": "postalcode"
  },
  "geometry": {"coordinates":[-0.178814,51.696128],"type":"Point"}
}
