{
  "type": "Feature",
  "properties": {
    "iso:country": "GB",
    "wof:name": "L8 0UF",
    "wof:placetype": "postalcode"
  },
  "geometry": {"coordinates":[-2.951688,53.39389],"type":"Point"}
}
