{
  "type": "Feature",
  "properties": {
    "iso:country": "GB",
    "wof:name": "HP21 9RH",
    "wof:placetype": "postalcode"
  },
  "geometry": {"coordinates":[-0.793312,51.800117],"type":"Point"}
}
