{
  "type": "Feature",
  "properties": {
    "iso:country":"GB",
    "wof:name":"EX31 2LA",
    "wof:placetype":"postalcode"
},
  "geometry": {"coordinates":[-4.09167662569847,51.07163437430066],"type":"Point"}
}