{
  "type": "Feature",
  "properties": {
    "iso:country":"GB",
    "wof:name":"CM5 0EW",
    "wof:placetype":"postalcode"
},
  "geometry": {"coordinates":[0.16929631286239,51.75100999933751],"type":"Point"}
}