{
  "type": "Feature",
  "properties": {
    "date:inception_lower": "1980-01-01",
    "date:inception_upper": "1980-01-01",
    "iso:country": "GB",
    "wof:name": "CM5 0EW",
    "wof:placetype": "postalcode"
  },
  "geometry": {"coordinates":[0.169411,51.751032],"type":"Point"}
}
