{
  "type": "Feature",
  "properties": {
    "iso:country":"GB",
    "wof:name":"EH8 7BX",
    "wof:placetype":"postalcode"
},
  "geometry": {"coordinates":[-3.14250184431637,55.95609455985218],"type":"Point"}
}