{
  "type": "Feature",
  "properties": {
    "iso:country":"GB",
    "wof:name":"LL56 4JF",
    "wof:placetype":"postalcode"
},
  "geometry": {"coordinates":[-4.20856937048818,53.18626913583459],"type":"Point"}
}