{
  "type": "Feature",
  "properties": {
    "iso:country":"GB",
    "wof:name":"LN11 0JZ",
    "wof:placetype":"postalcode"
},
  "geometry": {"coordinates":[0.00026779404124,53.3738106486205],"type":"Point"}
}