{
  "type": "Feature",
  "properties": {
    "iso:country":"GB",
    "wof:name":"TN8 7ED",
    "wof:placetype":"postalcode"
},
  "geometry": {"coordinates":[0.08268182653431,51.13163715316637],"type":"Point"}
}