{
  "type": "Feature",
  "properties": {
    "iso:country": "GB",
    "wof:name": "TN8 7ED",
    "wof:placetype": "postalcode"
  },
  "geometry": {"coordinates":[0.082682,51.131637],"type":"Point"}
}
