{
  "type": "Feature",
  "properties": {
    "date:inception_lower": "1980-01-01",
    "date:inception_upper": "1980-01-01",
    "iso:country": "GB",
    "wof:name": "TN8 7ED",
    "wof:placetype": "postalcode"
  },
  "geometry": {"coordinates":[0.082682,51.131637],"type":"Point"}
}
