{
  "type": "Feature",
  "properties": {
    "iso:country":"GB",
    "wof:name":"WN7 1NW",
    "wof:placetype":"postalcode"
},
  "geometry": {"coordinates":[-2.5173703351808,53.50483914781326],"type":"Point"}
}