{
  "type": "Feature",
  "properties": {
    "date:inception_lower": "2020-02-01",
    "date:inception_upper": "2020-02-01",
    "iso:country": "GB",
    "wof:name": "PR25 3DJ",
    "wof:placetype": "postalcode"
  },
  "geometry": {"coordinates":[-2.692281,53.702866],"type":"Point"}
}
