{
  "type": "Feature",
  "properties": {
    "iso:country": "GB",
    "wof:name": "PR25 3DJ",
    "wof:placetype": "postalcode"
  },
  "geometry": {"coordinates":[-2.692702,53.702648],"type":"Point"}
}
