{
  "type": "Feature",
  "properties": {
    "iso:country": "GB",
    "wof:name": "GU27 1JG",
    "wof:placetype": "postalcode"
  },
  "geometry": {"coordinates":[-0.732633,51.090538],"type":"Point"}
}
