{
  "type": "Feature",
  "properties": {
    "date:inception_lower":"1980-01-01",
    "date:inception_upper":"1980-01-31",
    "iso:country":"GB",
    "wof:name":"B5 4HQ",
    "wof:placetype":"postalcode"
},
  "geometry": {"coordinates":[-1.898675,52.475349],"type":"Point"}
}