{
  "type": "Feature",
  "properties": {
    "date:inception_lower":"1993-01-01",
    "date:inception_upper":"1993-01-31",
    "iso:country":"GB",
    "wof:name":"W3 7GA",
    "wof:placetype":"postalcode"
},
  "geometry": {"coordinates":[-0.252982,51.507408],"type":"Point"}
}