{
  "type": "Feature",
  "properties": {
    "iso:country":"GB",
    "wof:name":"W3 7GA",
    "wof:placetype":"postalcode"
},
  "geometry": {"coordinates":[-0.25263001706014,51.5074279469627],"type":"Point"}
}