{
  "type": "Feature",
  "properties": {
    "iso:country": "GB",
    "wof:name": "W3 7GA",
    "wof:placetype": "postalcode"
  },
  "geometry": {"coordinates":[-0.252982,51.507408],"type":"Point"}
}
