{
  "type": "Feature",
  "properties": {
    "iso:country":"GB",
    "wof:name":"SO41 9GF",
    "wof:placetype":"postalcode"
},
  "geometry": {"coordinates":[-1.54964657430984,50.75713744933805],"type":"Point"}
}