{
  "type": "Feature",
  "properties": {
    "iso:country":"GB",
    "wof:name":"BD4 0RY",
    "wof:placetype":"postalcode"
},
  "geometry": {"coordinates":[-1.67677317296222,53.76237164773934],"type":"Point"}
}