{
  "type": "Feature",
  "properties": {
    "date:inception_lower":"2015-02-01",
    "date:inception_upper":"2015-02-28",
    "iso:country":"GB",
    "wof:name":"CO15 4AA",
    "wof:placetype":"postalcode"
},
  "geometry": {"coordinates":[1.166356,51.820145],"type":"Point"}
}