{
  "type": "Feature",
  "properties": {
    "iso:country":"GB",
    "wof:name":"CO15 4AA",
    "wof:placetype":"postalcode"
},
  "geometry": {"coordinates":[1.16642007948812,51.82047221669412],"type":"Point"}
}