{
  "type": "Feature",
  "properties": {
    "iso:country": "GB",
    "wof:name": "CO15 4AA",
    "wof:placetype": "postalcode"
  },
  "geometry": {"coordinates":[1.166356,51.820145],"type":"Point"}
}
