{
  "type": "Feature",
  "properties": {
    "iso:country":"GB",
    "wof:name":"CV4 8FZ",
    "wof:placetype":"postalcode"
},
  "geometry": {"coordinates":[-1.56097689143501,52.39497448330073],"type":"Point"}
}