{
  "type": "Feature",
  "properties": {
    "iso:country":"GB",
    "wof:name":"YO7 2BB",
    "wof:placetype":"postalcode"
},
  "geometry": {"coordinates":[-1.25719955458666,54.20451877675927],"type":"Point"}
}