{
  "type": "Feature",
  "properties": {
    "iso:country": "GB",
    "wof:name": "YO7 2BB",
    "wof:placetype": "postalcode"
  },
  "geometry": {"coordinates":[-1.257216,54.20411],"type":"Point"}
}
