{
  "type": "Feature",
  "properties": {
    "date:inception_lower": "1993-01-01",
    "date:inception_upper": "1993-01-01",
    "iso:country": "GB",
    "wof:name": "YO7 2BB",
    "wof:placetype": "postalcode"
  },
  "geometry": {"coordinates":[-1.257216,54.20411],"type":"Point"}
}
