{
  "type": "Feature",
  "properties": {
    "iso:country":"GB",
    "wof:name":"HA1 3PN",
    "wof:placetype":"postalcode"
},
  "geometry": {"coordinates":[-0.33594669652175,51.55966169131761],"type":"Point"}
}