{
  "type": "Feature",
  "properties": {
    "iso:country":"GB",
    "wof:name":"CT16 1RA",
    "wof:placetype":"postalcode"
},
  "geometry": {"coordinates":[1.30779434497866,51.13128596671002],"type":"Point"}
}