{
  "type": "Feature",
  "properties": {
    "iso:country":"GB",
    "wof:name":"N15 5RA",
    "wof:placetype":"postalcode"
},
  "geometry": {"coordinates":[-0.08653091663078,51.58152394436846],"type":"Point"}
}