{
  "type": "Feature",
  "properties": {
    "iso:country": "GB",
    "wof:name": "NE62 5RD",
    "wof:placetype": "postalcode"
  },
  "geometry": {"coordinates":[-1.603828,55.155795],"type":"Point"}
}
