{
  "type": "Feature",
  "properties": {
    "iso:country":"GB",
    "wof:name":"KW14 8SZ",
    "wof:placetype":"postalcode"
},
  "geometry": {"coordinates":[-3.2823803432671,58.62310640947247],"type":"Point"}
}