{
  "type": "Feature",
  "properties": {
    "date:inception_lower": "1994-09-01",
    "date:inception_upper": "1994-09-01",
    "iso:country": "GB",
    "wof:name": "KW14 8SZ",
    "wof:placetype": "postalcode"
  },
  "geometry": {"coordinates":[-3.28238,58.623106],"type":"Point"}
}
