{
  "type": "Feature",
  "properties": {
    "iso:country": "GB",
    "wof:name": "KW14 8SZ",
    "wof:placetype": "postalcode"
  },
  "geometry": {"coordinates":[-3.28238,58.623106],"type":"Point"}
}
