{
  "type": "Feature",
  "properties": {
    "iso:country":"GB",
    "wof:name":"RG20 8UZ",
    "wof:placetype":"postalcode"
},
  "geometry": {"coordinates":[-1.31078479086547,51.46472748927997],"type":"Point"}
}