{
  "type": "Feature",
  "properties": {
    "iso:country": "GB",
    "wof:name": "RG20 8UZ",
    "wof:placetype": "postalcode"
  },
  "geometry": {"coordinates":[-1.310785,51.464727],"type":"Point"}
}
