{
  "type": "Feature",
  "properties": {
    "iso:country":"GB",
    "wof:name":"SY3 9EY",
    "wof:placetype":"postalcode"
},
  "geometry": {"coordinates":[-2.76079675807714,52.6911079568003],"type":"Point"}
}