{
  "type": "Feature",
  "properties": {
    "iso:country": "GB",
    "wof:name": "WS3 2QG",
    "wof:placetype": "postalcode"
  },
  "geometry": {"coordinates":[-2.017046,52.616382],"type":"Point"}
}
