{
  "type": "Feature",
  "properties": {
    "date:inception_lower":"1980-01-01",
    "date:inception_upper":"1980-01-31",
    "iso:country":"GB",
    "wof:name":"WS3 2QG",
    "wof:placetype":"postalcode"
},
  "geometry": {"coordinates":[-2.017046,52.616382],"type":"Point"}
}