{
  "type": "Feature",
  "properties": {
    "iso:country":"GB",
    "wof:name":"YO25 3YN",
    "wof:placetype":"postalcode"
},
  "geometry": {"coordinates":[-0.39897279276566,54.14028142373205],"type":"Point"}
}