{
  "type": "Feature",
  "properties": {
    "iso:country": "GB",
    "wof:name": "AB43 9LZ",
    "wof:placetype": "postalcode"
  },
  "geometry": {"coordinates":[-2.026616,57.682849],"type":"Point"}
}
