{
  "type": "Feature",
  "properties": {
    "date:inception_lower": "1980-01-01",
    "date:inception_upper": "1980-01-01",
    "iso:country": "GB",
    "wof:name": "EH6 8PD",
    "wof:placetype": "postalcode"
  },
  "geometry": {"coordinates":[-3.175765,55.965486],"type":"Point"}
}
