{
  "type": "Feature",
  "properties": {
    "iso:country":"GB",
    "wof:name":"TN17 2AP",
    "wof:placetype":"postalcode"
},
  "geometry": {"coordinates":[0.55952924254474,51.12144978287238],"type":"Point"}
}