{
  "type": "Feature",
  "properties": {
    "date:inception_lower":"1991-01-01",
    "date:inception_upper":"1991-01-31",
    "iso:country":"GB",
    "wof:name":"BA11 2PN",
    "wof:placetype":"postalcode"
},
  "geometry": {"coordinates":[-2.257242,51.250991],"type":"Point"}
}