{
  "type": "Feature",
  "properties": {
    "iso:country": "GB",
    "wof:name": "G41 2SE",
    "wof:placetype": "postalcode"
  },
  "geometry": {"coordinates":[-4.269142,55.842893],"type":"Point"}
}
