{
  "type": "Feature",
  "properties": {
    "date:inception_lower": "1992-01-01",
    "date:inception_upper": "1992-01-01",
    "iso:country": "GB",
    "wof:name": "NN1 1SH",
    "wof:placetype": "postalcode"
  },
  "geometry": {"coordinates":[-0.902939,52.236071],"type":"Point"}
}
