{
  "type": "Feature",
  "properties": {
    "iso:country":"GB",
    "wof:name":"SY20 9RE",
    "wof:placetype":"postalcode"
},
  "geometry": {"coordinates":[-3.84542798211575,52.65296320647096],"type":"Point"}
}