{
  "type": "Feature",
  "properties": {
    "date:inception_lower":"1980-01-01",
    "date:inception_upper":"1980-01-31",
    "iso:country":"GB",
    "wof:name":"EX10 9TX",
    "wof:placetype":"postalcode"
},
  "geometry": {"coordinates":[-3.238787,50.697546],"type":"Point"}
}