{
  "type": "Feature",
  "properties": {
    "iso:country": "GB",
    "wof:name": "EX10 9TX",
    "wof:placetype": "postalcode"
  },
  "geometry": {"coordinates":[-3.238787,50.697546],"type":"Point"}
}
