{
  "type": "Feature",
  "properties": {
    "iso:country":"GB",
    "wof:name":"EX10 9TX",
    "wof:placetype":"postalcode"
},
  "geometry": {"coordinates":[-3.23878690224377,50.69754610910847],"type":"Point"}
}