{
  "type": "Feature",
  "properties": {
    "iso:country":"GB",
    "wof:name":"DD5 2PA",
    "wof:placetype":"postalcode"
},
  "geometry": {"coordinates":[-2.8513469212106,56.4769595044283],"type":"Point"}
}