{
  "type": "Feature",
  "properties": {
    "iso:country": "GB",
    "wof:name": "EC2V 7WT",
    "wof:placetype": "postalcode"
  },
  "geometry": {"coordinates":[-0.094491,51.514722],"type":"Point"}
}
