{
  "type": "Feature",
  "properties": {
    "iso:country": "GB",
    "wof:name": "DT6 4ER",
    "wof:placetype": "postalcode"
  },
  "geometry": {"coordinates":[-2.762748,50.710537],"type":"Point"}
}
