{
  "type": "Feature",
  "properties": {
    "date:inception_lower": "1980-01-01",
    "date:inception_upper": "1980-01-01",
    "iso:country": "GB",
    "wof:name": "DT6 4ER",
    "wof:placetype": "postalcode"
  },
  "geometry": {"coordinates":[-2.762748,50.710537],"type":"Point"}
}
