{
  "type": "Feature",
  "properties": {
    "iso:country":"GB",
    "wof:name":"DT6 4ER",
    "wof:placetype":"postalcode"
},
  "geometry": {"coordinates":[-2.76274801385456,50.71053694104984],"type":"Point"}
}