{
  "type": "Feature",
  "properties": {
    "iso:country":"GB",
    "wof:name":"LS12 3QQ",
    "wof:placetype":"postalcode"
},
  "geometry": {"coordinates":[-1.61134215373724,53.80257876789502],"type":"Point"}
}