{
  "type": "Feature",
  "properties": {
    "iso:country":"GB",
    "wof:name":"S80 4ER",
    "wof:placetype":"postalcode"
},
  "geometry": {"coordinates":[-1.21312550362454,53.26416122115243],"type":"Point"}
}