{
  "type": "Feature",
  "properties": {
    "iso:country":"GB",
    "wof:name":"IV30 6GJ",
    "wof:placetype":"postalcode"
},
  "geometry": {"coordinates":[-3.28534845938873,57.64060472078669],"type":"Point"}
}