{
  "type": "Feature",
  "properties": {
    "iso:country":"GB",
    "wof:name":"SS13 1FG",
    "wof:placetype":"postalcode"
},
  "geometry": {"coordinates":[0.50957806391875,51.57756343862165],"type":"Point"}
}