{
  "type": "Feature",
  "properties": {
    "date:inception_lower": "2011-06-01",
    "date:inception_upper": "2011-06-01",
    "iso:country": "GB",
    "wof:name": "SS13 1FG",
    "wof:placetype": "postalcode"
  },
  "geometry": {"coordinates":[0.510077,51.577467],"type":"Point"}
}
