{
  "type": "Feature",
  "properties": {
    "iso:country":"GB",
    "wof:name":"MK41 9EJ",
    "wof:placetype":"postalcode"
},
  "geometry": {"coordinates":[-0.44781338789426,52.14653622435479],"type":"Point"}
}