{
  "type": "Feature",
  "properties": {
    "iso:country":"GB",
    "wof:name":"CT9 9SR",
    "wof:placetype":"postalcode"
},
  "geometry": {"coordinates":[1.38230867936033,51.38715374061975],"type":"Point"}
}