{
  "type": "Feature",
  "properties": {
    "date:inception_lower": "1980-01-01",
    "date:inception_upper": "1980-01-01",
    "iso:country": "GB",
    "wof:name": "WF15 8AJ",
    "wof:placetype": "postalcode"
  },
  "geometry": {"coordinates":[-1.723892,53.699213],"type":"Point"}
}
