{
  "type": "Feature",
  "properties": {
    "iso:country": "GB",
    "wof:name": "WF15 8AJ",
    "wof:placetype": "postalcode"
  },
  "geometry": {"coordinates":[-1.723892,53.699213],"type":"Point"}
}
