{
  "type": "Feature",
  "properties": {
    "iso:country":"GB",
    "wof:name":"WF15 8AJ",
    "wof:placetype":"postalcode"
},
  "geometry": {"coordinates":[-1.72389223659646,53.6992131872986],"type":"Point"}
}