{
  "type": "Feature",
  "properties": {
    "iso:country":"GB",
    "wof:name":"CB10 1DZ",
    "wof:placetype":"postalcode"
},
  "geometry": {"coordinates":[0.23952258730265,52.02024088212566],"type":"Point"}
}