{
  "type": "Feature",
  "properties": {
    "iso:country":"GB",
    "wof:name":"WV2 2HU",
    "wof:placetype":"postalcode"
},
  "geometry": {"coordinates":[-2.10658606189595,52.57632156507792],"type":"Point"}
}