{
  "type": "Feature",
  "properties": {
    "iso:country": "GB",
    "wof:name": "LU7 9QN",
    "wof:placetype": "postalcode"
  },
  "geometry": {"coordinates":[-0.546575,51.926014],"type":"Point"}
}
