{
  "type": "Feature",
  "properties": {
    "iso:country":"GB",
    "wof:name":"LU7 9QN",
    "wof:placetype":"postalcode"
},
  "geometry": {"coordinates":[-0.54657519380648,51.92601424069409],"type":"Point"}
}