{
  "type": "Feature",
  "properties": {
    "iso:country": "GB",
    "wof:name": "ST10 4HU",
    "wof:placetype": "postalcode"
  },
  "geometry": {"coordinates":[-1.939264,52.949167],"type":"Point"}
}
