{
  "type": "Feature",
  "properties": {
    "iso:country":"GB",
    "wof:name":"ST10 4HU",
    "wof:placetype":"postalcode"
},
  "geometry": {"coordinates":[-1.93926609231026,52.949150026148],"type":"Point"}
}