{
  "type": "Feature",
  "properties": {
    "iso:country": "GB",
    "wof:name": "CT3 3GT",
    "wof:placetype": "postalcode"
  },
  "geometry": {"coordinates":[1.201596,51.231071],"type":"Point"}
}
