{
  "type": "Feature",
  "properties": {
    "iso:country":"GB",
    "wof:name":"DY5 1TH",
    "wof:placetype":"postalcode"
},
  "geometry": {"coordinates":[-2.10692670790455,52.48601787596094],"type":"Point"}
}