{
  "type": "Feature",
  "properties": {
    "iso:country": "GB",
    "wof:name": "CA12 4TJ",
    "wof:placetype": "postalcode"
  },
  "geometry": {"coordinates":[-3.054874,54.561222],"type":"Point"}
}
