{
  "type": "Feature",
  "properties": {
    "iso:country":"GB",
    "wof:name":"DH3 3NP",
    "wof:placetype":"postalcode"
},
  "geometry": {"coordinates":[-1.56733152385616,54.85008904024556],"type":"Point"}
}