{
  "type": "Feature",
  "properties": {
    "iso:country": "GB",
    "wof:name": "DH3 3NP",
    "wof:placetype": "postalcode"
  },
  "geometry": {"coordinates":[-1.567331,54.850089],"type":"Point"}
}
