{
  "type": "Feature",
  "properties": {
    "iso:country":"GB",
    "wof:name":"KW14 8NQ",
    "wof:placetype":"postalcode"
},
  "geometry": {"coordinates":[-3.51381856447219,58.59135277845358],"type":"Point"}
}