{
  "type": "Feature",
  "properties": {
    "iso:country": "GB",
    "wof:name": "DT10 2EW",
    "wof:placetype": "postalcode"
  },
  "geometry": {"coordinates":[-2.392016,50.854394],"type":"Point"}
}
