{
  "type": "Feature",
  "properties": {
    "iso:country":"GB",
    "wof:name":"ST3 4NF",
    "wof:placetype":"postalcode"
},
  "geometry": {"coordinates":[-2.12876967205043,52.97898454339489],"type":"Point"}
}