{
  "type": "Feature",
  "properties": {
    "iso:country":"GB",
    "wof:name":"L4 1XX",
    "wof:placetype":"postalcode"
},
  "geometry": {"coordinates":[-2.98372209559131,53.43246229027701],"type":"Point"}
}