{
  "type": "Feature",
  "properties": {
    "iso:country":"GB",
    "wof:name":"DD8 4JP",
    "wof:placetype":"postalcode"
},
  "geometry": {"coordinates":[-3.01549610639324,56.67729006123594],"type":"Point"}
}