{
  "type": "Feature",
  "properties": {
    "date:inception_lower": "1980-01-01",
    "date:inception_upper": "1980-01-01",
    "iso:country": "GB",
    "wof:name": "TQ12 4RQ",
    "wof:placetype": "postalcode"
  },
  "geometry": {"coordinates":[-3.556463,50.534911],"type":"Point"}
}
