{
  "type": "Feature",
  "properties": {
    "iso:country":"GB",
    "wof:name":"TQ12 4RQ",
    "wof:placetype":"postalcode"
},
  "geometry": {"coordinates":[-3.55646300299065,50.53491130709414],"type":"Point"}
}