{
  "type": "Feature",
  "properties": {
    "iso:country":"GB",
    "wof:name":"CM15 9BJ",
    "wof:placetype":"postalcode"
},
  "geometry": {"coordinates":[0.30357895125411,51.62456856930237],"type":"Point"}
}