{
  "type": "Feature",
  "properties": {
    "iso:country": "GB",
    "wof:name": "SA7 9YE",
    "wof:placetype": "postalcode"
  },
  "geometry": {"coordinates":[-3.890424,51.649238],"type":"Point"}
}
