{
  "type": "Feature",
  "properties": {
    "iso:country":"GB",
    "wof:name":"SA7 9YE",
    "wof:placetype":"postalcode"
},
  "geometry": {"coordinates":[-3.88916566607261,51.64963992940072],"type":"Point"}
}