{
  "type": "Feature",
  "properties": {
    "date:inception_lower": "1980-01-01",
    "date:inception_upper": "1980-01-01",
    "iso:country": "GB",
    "wof:name": "SA7 9YE",
    "wof:placetype": "postalcode"
  },
  "geometry": {"coordinates":[-3.890438,51.649238],"type":"Point"}
}
