{
  "type": "Feature",
  "properties": {
    "iso:country":"GB",
    "wof:name":"DD2 5QW",
    "wof:placetype":"postalcode"
},
  "geometry": {"coordinates":[-3.08967184514456,56.50065753742329],"type":"Point"}
}