{
  "type": "Feature",
  "properties": {
    "iso:country":"GB",
    "wof:name":"DT2 8XR",
    "wof:placetype":"postalcode"
},
  "geometry": {"coordinates":[-2.33410266155199,50.69812989967313],"type":"Point"}
}