{
  "type": "Feature",
  "properties": {
    "date:inception_lower": "1980-01-01",
    "date:inception_upper": "1980-01-01",
    "iso:country": "GB",
    "wof:name": "LS21 3AB",
    "wof:placetype": "postalcode"
  },
  "geometry": {"coordinates":[-1.692791,53.903785],"type":"Point"}
}
