{
  "type": "Feature",
  "properties": {
    "date:inception_lower": "1981-09-01",
    "date:inception_upper": "1981-09-01",
    "iso:country": "GB",
    "wof:name": "WA3 7PJ",
    "wof:placetype": "postalcode"
  },
  "geometry": {"coordinates":[-2.5265,53.41548],"type":"Point"}
}
