{
  "type": "Feature",
  "properties": {
    "iso:country":"GB",
    "wof:name":"WA3 7PJ",
    "wof:placetype":"postalcode"
},
  "geometry": {"coordinates":[-2.52650043731547,53.41547978584883],"type":"Point"}
}