{
  "type": "Feature",
  "properties": {
    "iso:country": "GB",
    "wof:name": "RG40 5QA",
    "wof:placetype": "postalcode"
  },
  "geometry": {"coordinates":[-0.821968,51.42182],"type":"Point"}
}
