{
  "type": "Feature",
  "properties": {
    "iso:country": "GB",
    "wof:name": "NW10 4XJ",
    "wof:placetype": "postalcode"
  },
  "geometry": {"coordinates":[-0.246326,51.542512],"type":"Point"}
}
