{
  "type": "Feature",
  "properties": {
    "iso:country": "GB",
    "wof:name": "CT14 0DP",
    "wof:placetype": "postalcode"
  },
  "geometry": {"coordinates":[1.3477,51.253906],"type":"Point"}
}
