{
  "type": "Feature",
  "properties": {
    "iso:country": "GB",
    "wof:name": "WA14 5SN",
    "wof:placetype": "postalcode"
  },
  "geometry": {"coordinates":[-2.401509,53.395301],"type":"Point"}
}
