{
  "type": "Feature",
  "properties": {
    "iso:country":"GB",
    "wof:name":"WA14 5SN",
    "wof:placetype":"postalcode"
},
  "geometry": {"coordinates":[-2.40150905347894,53.39530084467221],"type":"Point"}
}