{
  "type": "Feature",
  "properties": {
    "iso:country": "GB",
    "wof:name": "PE6 9SF",
    "wof:placetype": "postalcode"
  },
  "geometry": {"coordinates":[-0.363221,52.686974],"type":"Point"}
}
