{
  "type": "Feature",
  "properties": {
    "iso:country":"GB",
    "wof:name":"HR1 2PU",
    "wof:placetype":"postalcode"
},
  "geometry": {"coordinates":[-2.71072496096319,52.05418652935355],"type":"Point"}
}