{
  "type": "Feature",
  "properties": {
    "iso:country": "GB",
    "wof:name": "CF24 4QY",
    "wof:placetype": "postalcode"
  },
  "geometry": {"coordinates":[-3.176571,51.498594],"type":"Point"}
}
