{
  "type": "Feature",
  "properties": {
    "iso:country":"GB",
    "wof:name":"SG2 8TX",
    "wof:placetype":"postalcode"
},
  "geometry": {"coordinates":[-0.1734189475101,51.87829221657957],"type":"Point"}
}