{
  "type": "Feature",
  "properties": {
    "iso:country":"GB",
    "wof:name":"G44 5TQ",
    "wof:placetype":"postalcode"
},
  "geometry": {"coordinates":[-4.25777349018741,55.81572239853298],"type":"Point"}
}