{
  "type": "Feature",
  "properties": {
    "iso:country":"GB",
    "wof:name":"SS0 9XP",
    "wof:placetype":"postalcode"
},
  "geometry": {"coordinates":[0.67445495443302,51.55047397346699],"type":"Point"}
}