{
  "type": "Feature",
  "properties": {
    "iso:country":"GB",
    "wof:name":"SG2 0BU",
    "wof:placetype":"postalcode"
},
  "geometry": {"coordinates":[-0.17435334393236,51.90973355226146],"type":"Point"}
}