{
  "type": "Feature",
  "properties": {
    "iso:country": "GB",
    "wof:name": "SG2 0BU",
    "wof:placetype": "postalcode"
  },
  "geometry": {"coordinates":[-0.174353,51.909734],"type":"Point"}
}
