{
  "type": "Feature",
  "properties": {
    "date:inception_lower":"1980-01-01",
    "date:inception_upper":"1980-01-31",
    "iso:country":"GB",
    "wof:name":"NR12 0PF",
    "wof:placetype":"postalcode"
},
  "geometry": {"coordinates":[1.494515,52.83427],"type":"Point"}
}