{
  "type": "Feature",
  "properties": {
    "iso:country":"GB",
    "wof:name":"NR12 0PF",
    "wof:placetype":"postalcode"
},
  "geometry": {"coordinates":[1.4945150922533,52.83426967611199],"type":"Point"}
}