{
  "type": "Feature",
  "properties": {
    "iso:country":"GB",
    "wof:name":"CO7 6HL",
    "wof:placetype":"postalcode"
},
  "geometry": {"coordinates":[0.9887317248056,51.95724417984066],"type":"Point"}
}