{
  "type": "Feature",
  "properties": {
    "date:inception_lower": "1980-01-01",
    "date:inception_upper": "1980-01-01",
    "iso:country": "GB",
    "wof:name": "CV4 9NA",
    "wof:placetype": "postalcode"
  },
  "geometry": {"coordinates":[-1.583844,52.406455],"type":"Point"}
}
