{
  "type": "Feature",
  "properties": {
    "date:inception_lower":"1988-11-01",
    "date:inception_upper":"1988-11-30",
    "iso:country":"GB",
    "wof:name":"G75 8SY",
    "wof:placetype":"postalcode"
},
  "geometry": {"coordinates":[-4.216728,55.749063],"type":"Point"}
}