{
  "type": "Feature",
  "properties": {
    "iso:country":"GB",
    "wof:name":"CA9 3EL",
    "wof:placetype":"postalcode"
},
  "geometry": {"coordinates":[-2.45694957341149,54.78814397473954],"type":"Point"}
}