{
  "type": "Feature",
  "properties": {
    "iso:country":"GB",
    "wof:name":"DH6 1NE",
    "wof:placetype":"postalcode"
},
  "geometry": {"coordinates":[-1.44040698799829,54.76623819110579],"type":"Point"}
}