{
  "type": "Feature",
  "properties": {
    "iso:country": "GB",
    "wof:name": "WN3 6SY",
    "wof:placetype": "postalcode"
  },
  "geometry": {"coordinates":[-2.66111,53.522898],"type":"Point"}
}
