{
  "type": "Feature",
  "properties": {
    "date:inception_lower":"1980-01-01",
    "date:inception_upper":"1980-01-31",
    "iso:country":"GB",
    "wof:name":"WN3 6SY",
    "wof:placetype":"postalcode"
},
  "geometry": {"coordinates":[-2.66111,53.522898],"type":"Point"}
}