{
  "type": "Feature",
  "properties": {
    "iso:country":"GB",
    "wof:name":"B60 3EN",
    "wof:placetype":"postalcode"
},
  "geometry": {"coordinates":[-2.0510425838104,52.32256180855725],"type":"Point"}
}