{
  "type": "Feature",
  "properties": {
    "iso:country":"GB",
    "wof:name":"SS1 2EN",
    "wof:placetype":"postalcode"
},
  "geometry": {"coordinates":[0.72200074947285,51.53305648339085],"type":"Point"}
}