{
  "type": "Feature",
  "properties": {
    "date:inception_lower":"1980-01-01",
    "date:inception_upper":"1980-01-31",
    "iso:country":"GB",
    "wof:name":"DG6 4XU",
    "wof:placetype":"postalcode"
},
  "geometry": {"coordinates":[-4.015339,54.84521],"type":"Point"}
}