{
  "type": "Feature",
  "properties": {
    "iso:country":"GB",
    "wof:name":"HR2 8AY",
    "wof:placetype":"postalcode"
},
  "geometry": {"coordinates":[-2.72341069858087,51.9872174980615],"type":"Point"}
}