{
  "type": "Feature",
  "properties": {
    "iso:country": "GB",
    "wof:name": "HR2 8AY",
    "wof:placetype": "postalcode"
  },
  "geometry": {"coordinates":[-2.723411,51.987217],"type":"Point"}
}
