{
  "type": "Feature",
  "properties": {
    "date:inception_lower": "1990-02-01",
    "date:inception_upper": "1990-02-01",
    "iso:country": "GB",
    "wof:name": "TS25 2HY",
    "wof:placetype": "postalcode"
  },
  "geometry": {"coordinates":[-1.23615,54.643937],"type":"Point"}
}
