{
  "type": "Feature",
  "properties": {
    "iso:country": "GB",
    "wof:name": "TS25 2HY",
    "wof:placetype": "postalcode"
  },
  "geometry": {"coordinates":[-1.23615,54.643937],"type":"Point"}
}
