{
  "type": "Feature",
  "properties": {
    "iso:country":"GB",
    "wof:name":"TS25 2HY",
    "wof:placetype":"postalcode"
},
  "geometry": {"coordinates":[-1.23615012396043,54.64393666277019],"type":"Point"}
}