{
  "type": "Feature",
  "properties": {
    "iso:country":"GB",
    "wof:name":"CM1 2TL",
    "wof:placetype":"postalcode"
},
  "geometry": {"coordinates":[0.44932517016244,51.72758298119226],"type":"Point"}
}