{
  "type": "Feature",
  "properties": {
    "iso:country": "GB",
    "wof:name": "TS4 3GN",
    "wof:placetype": "postalcode"
  },
  "geometry": {"coordinates":[-1.213792,54.548998],"type":"Point"}
}
