{
  "type": "Feature",
  "properties": {
    "iso:country":"GB",
    "wof:name":"TS4 3GN",
    "wof:placetype":"postalcode"
},
  "geometry": {"coordinates":[-1.21379160291754,54.54899842216406],"type":"Point"}
}