{
  "type": "Feature",
  "properties": {
    "iso:country":"GB",
    "wof:name":"BR2 8QE",
    "wof:placetype":"postalcode"
},
  "geometry": {"coordinates":[0.04272812624491,51.37145899660304],"type":"Point"}
}