{
  "type": "Feature",
  "properties": {
    "iso:country": "GB",
    "wof:name": "LE1 3JR",
    "wof:placetype": "postalcode"
  },
  "geometry": {"coordinates":[-1.129374,52.63968],"type":"Point"}
}
