{
  "type": "Feature",
  "properties": {
    "iso:country":"GB",
    "wof:name":"LE1 3JR",
    "wof:placetype":"postalcode"
},
  "geometry": {"coordinates":[-1.12909741205635,52.63985729621086],"type":"Point"}
}