{
  "type": "Feature",
  "properties": {
    "iso:country":"GB",
    "wof:name":"TN35 5JA",
    "wof:placetype":"postalcode"
},
  "geometry": {"coordinates":[0.60585673228459,50.86728510366376],"type":"Point"}
}