{
  "type": "Feature",
  "properties": {
    "iso:country": "GB",
    "wof:name": "GL11 6JH",
    "wof:placetype": "postalcode"
  },
  "geometry": {"coordinates":[-2.375195,51.70046],"type":"Point"}
}
