{
  "type": "Feature",
  "properties": {
    "iso:country":"GB",
    "wof:name":"GL11 6JH",
    "wof:placetype":"postalcode"
},
  "geometry": {"coordinates":[-2.37519628711825,51.70045661703649],"type":"Point"}
}