{
  "type": "Feature",
  "properties": {
    "iso:country":"GB",
    "wof:name":"CV32 7BL",
    "wof:placetype":"postalcode"
},
  "geometry": {"coordinates":[-1.50989906001626,52.30286663912025],"type":"Point"}
}