{
  "type": "Feature",
  "properties": {
    "iso:country": "GB",
    "wof:name": "SK8 2HH",
    "wof:placetype": "postalcode"
  },
  "geometry": {"coordinates":[-2.192032,53.392964],"type":"Point"}
}
