{
  "type": "Feature",
  "properties": {
    "iso:country":"GB",
    "wof:name":"SK8 2HH",
    "wof:placetype":"postalcode"
},
  "geometry": {"coordinates":[-2.19203205320423,53.39296356124677],"type":"Point"}
}