{
  "type": "Feature",
  "properties": {
    "iso:country":"GB",
    "wof:name":"RH16 2DB",
    "wof:placetype":"postalcode"
},
  "geometry": {"coordinates":[-0.09117727354052,51.01512142004126],"type":"Point"}
}