{
  "type": "Feature",
  "properties": {
    "iso:country": "GB",
    "wof:name": "WA5 8DS",
    "wof:placetype": "postalcode"
  },
  "geometry": {"coordinates":[-2.631823,53.396488],"type":"Point"}
}
