{
  "type": "Feature",
  "properties": {
    "iso:country":"GB",
    "wof:name":"PO21 4HL",
    "wof:placetype":"postalcode"
},
  "geometry": {"coordinates":[-0.72700679640373,50.77512636059945],"type":"Point"}
}