{
  "type": "Feature",
  "properties": {
    "date:inception_lower":"2004-02-01",
    "date:inception_upper":"2004-02-29",
    "iso:country":"GB",
    "wof:name":"GL20 8UJ",
    "wof:placetype":"postalcode"
},
  "geometry": {"coordinates":[-2.110514,52.001229],"type":"Point"}
}