{
  "type": "Feature",
  "properties": {
    "iso:country":"GB",
    "wof:name":"GL20 8UJ",
    "wof:placetype":"postalcode"
},
  "geometry": {"coordinates":[-2.11051358272181,52.00122932202596],"type":"Point"}
}