{
  "type": "Feature",
  "properties": {
    "date:inception_lower": "1995-07-01",
    "date:inception_upper": "1995-07-01",
    "iso:country": "GB",
    "wof:name": "MK44 1AL",
    "wof:placetype": "postalcode"
  },
  "geometry": {"coordinates":[-0.511616,52.304763],"type":"Point"}
}
