{
  "type": "Feature",
  "properties": {
    "date:inception_lower": "1991-09-01",
    "date:inception_upper": "1991-09-01",
    "iso:country": "GB",
    "wof:name": "BH20 5SE",
    "wof:placetype": "postalcode"
  },
  "geometry": {"coordinates":[-2.244423,50.625968],"type":"Point"}
}
