{
  "type": "Feature",
  "properties": {
    "iso:country":"GB",
    "wof:name":"BH20 5SE",
    "wof:placetype":"postalcode"
},
  "geometry": {"coordinates":[-2.24434094350993,50.6259699279062],"type":"Point"}
}