{
  "type": "Feature",
  "properties": {
    "iso:country": "GB",
    "wof:name": "BH20 5SE",
    "wof:placetype": "postalcode"
  },
  "geometry": {"coordinates":[-2.244423,50.625968],"type":"Point"}
}
