{
  "type": "Feature",
  "properties": {
    "iso:country": "GB",
    "wof:name": "M13 9LG",
    "wof:placetype": "postalcode"
  },
  "geometry": {"coordinates":[-2.222913,53.463784],"type":"Point"}
}
