{
  "type": "Feature",
  "properties": {
    "iso:country":"GB",
    "wof:name":"M13 9LG",
    "wof:placetype":"postalcode"
},
  "geometry": {"coordinates":[-2.22291336710106,53.4637844231532],"type":"Point"}
}