{
  "type": "Feature",
  "properties": {
    "date:inception_lower": "2023-03-01",
    "date:inception_upper": "2023-03-01",
    "iso:country": "GB",
    "wof:name": "TN5 7FL",
    "wof:placetype": "postalcode"
  },
  "geometry": {"coordinates":[0.455302,51.052111],"type":"Point"}
}
