{
  "type": "Feature",
  "properties": {
    "iso:country":"GB",
    "wof:name":"DY2 7QY",
    "wof:placetype":"postalcode"
},
  "geometry": {"coordinates":[-2.06475887840511,52.51124733858798],"type":"Point"}
}