{
  "type": "Feature",
  "properties": {
    "iso:country": "GB",
    "wof:name": "NG24 3EJ",
    "wof:placetype": "postalcode"
  },
  "geometry": {"coordinates":[-0.794895,53.056212],"type":"Point"}
}
