{
  "type": "Feature",
  "properties": {
    "iso:country":"GB",
    "wof:name":"NG24 3EJ",
    "wof:placetype":"postalcode"
},
  "geometry": {"coordinates":[-0.7948945617201,53.05621167745126],"type":"Point"}
}