{
  "type": "Feature",
  "properties": {
    "iso:country":"GB",
    "wof:name":"TN24 9SA",
    "wof:placetype":"postalcode"
},
  "geometry": {"coordinates":[0.8955917462585,51.1593163155034],"type":"Point"}
}