{
  "type": "Feature",
  "properties": {
    "date:inception_lower": "1997-12-01",
    "date:inception_upper": "1997-12-01",
    "iso:country": "GB",
    "wof:name": "TN24 9SA",
    "wof:placetype": "postalcode"
  },
  "geometry": {"coordinates":[0.895592,51.159316],"type":"Point"}
}
