{
  "type": "Feature",
  "properties": {
    "date:inception_lower":"1980-01-01",
    "date:inception_upper":"1980-01-31",
    "iso:country":"GB",
    "wof:name":"WA16 8JF",
    "wof:placetype":"postalcode"
},
  "geometry": {"coordinates":[-2.353611,53.310103],"type":"Point"}
}