{
  "type": "Feature",
  "properties": {
    "iso:country":"GB",
    "wof:name":"G72 9PS",
    "wof:placetype":"postalcode"
},
  "geometry": {"coordinates":[-4.10085274075567,55.7949936085427],"type":"Point"}
}