{
  "type": "Feature",
  "properties": {
    "iso:country":"GB",
    "wof:name":"BN2 1HP",
    "wof:placetype":"postalcode"
},
  "geometry": {"coordinates":[-0.12134122753021,50.81915059236171],"type":"Point"}
}