{
  "type": "Feature",
  "properties": {
    "date:inception_lower": "2005-11-01",
    "date:inception_upper": "2005-11-01",
    "iso:country": "GB",
    "wof:name": "EH49 7AW",
    "wof:placetype": "postalcode"
  },
  "geometry": {"coordinates":[-3.613156,55.975588],"type":"Point"}
}
