{
  "type": "Feature",
  "properties": {
    "iso:country":"GB",
    "wof:name":"EH49 7AW",
    "wof:placetype":"postalcode"
},
  "geometry": {"coordinates":[-3.61315630703959,55.97558759074219],"type":"Point"}
}