{
  "type": "Feature",
  "properties": {
    "date:inception_lower": "2022-02-01",
    "date:inception_upper": "2022-02-01",
    "iso:country": "GB",
    "wof:name": "GU14 4FN",
    "wof:placetype": "postalcode"
  },
  "geometry": {"coordinates":[-0.750863,51.279583],"type":"Point"}
}
