{
  "type": "Feature",
  "properties": {
    "iso:country": "GB",
    "wof:name": "CO10 8NT",
    "wof:placetype": "postalcode"
  },
  "geometry": {"coordinates":[0.57361,52.072442],"type":"Point"}
}
