{
  "type": "Feature",
  "properties": {
    "iso:country":"GB",
    "wof:name":"CO10 8NT",
    "wof:placetype":"postalcode"
},
  "geometry": {"coordinates":[0.57361000860662,52.07244235406765],"type":"Point"}
}