{
  "type": "Feature",
  "properties": {
    "iso:country": "GB",
    "wof:name": "NG3 3AA",
    "wof:placetype": "postalcode"
  },
  "geometry": {"coordinates":[-1.123992,52.973168],"type":"Point"}
}
