{
  "type": "Feature",
  "properties": {
    "iso:country":"GB",
    "wof:name":"NG3 3AA",
    "wof:placetype":"postalcode"
},
  "geometry": {"coordinates":[-1.12399201807513,52.97316825186406],"type":"Point"}
}