{
  "type": "Feature",
  "properties": {
    "date:inception_lower":"1980-01-01",
    "date:inception_upper":"1980-01-31",
    "iso:country":"GB",
    "wof:name":"NG3 3AA",
    "wof:placetype":"postalcode"
},
  "geometry": {"coordinates":[-1.123992,52.973168],"type":"Point"}
}