{
  "type": "Feature",
  "properties": {
    "iso:country":"GB",
    "wof:name":"SG6 2QP",
    "wof:placetype":"postalcode"
},
  "geometry": {"coordinates":[-0.20239607811218,51.96947544278853],"type":"Point"}
}