{
  "type": "Feature",
  "properties": {
    "iso:country":"GB",
    "wof:name":"EH4 1NP",
    "wof:placetype":"postalcode"
},
  "geometry": {"coordinates":[-3.21176082419815,55.95722996241648],"type":"Point"}
}