{
  "type": "Feature",
  "properties": {
    "date:inception_lower": "2008-09-01",
    "date:inception_upper": "2008-09-01",
    "iso:country": "GB",
    "wof:name": "M11 3LH",
    "wof:placetype": "postalcode"
  },
  "geometry": {"coordinates":[-2.198476,53.475414],"type":"Point"}
}
