{
  "type": "Feature",
  "properties": {
    "date:inception_lower": "1980-01-01",
    "date:inception_upper": "1980-01-01",
    "iso:country": "GB",
    "wof:name": "OL8 4QT",
    "wof:placetype": "postalcode"
  },
  "geometry": {"coordinates":[-2.139102,53.522667],"type":"Point"}
}
