{
  "type": "Feature",
  "properties": {
    "date:inception_lower": "1980-01-01",
    "date:inception_upper": "1980-01-01",
    "iso:country": "GB",
    "wof:name": "NE63 0TW",
    "wof:placetype": "postalcode"
  },
  "geometry": {"coordinates":[-1.551308,55.17083],"type":"Point"}
}
