{
  "type": "Feature",
  "properties": {
    "iso:country": "GB",
    "wof:name": "NE63 0TW",
    "wof:placetype": "postalcode"
  },
  "geometry": {"coordinates":[-1.551308,55.17083],"type":"Point"}
}
