{
  "type": "Feature",
  "properties": {
    "iso:country": "GB",
    "wof:name": "WR11 3JT",
    "wof:placetype": "postalcode"
  },
  "geometry": {"coordinates":[-1.92952,52.097352],"type":"Point"}
}
