{
  "type": "Feature",
  "properties": {
    "date:inception_lower": "2014-05-01",
    "date:inception_upper": "2014-05-01",
    "iso:country": "GB",
    "wof:name": "WR11 3JT",
    "wof:placetype": "postalcode"
  },
  "geometry": {"coordinates":[-1.92952,52.097352],"type":"Point"}
}
