{
  "type": "Feature",
  "properties": {
    "iso:country":"GB",
    "wof:name":"DN10 6RL",
    "wof:placetype":"postalcode"
},
  "geometry": {"coordinates":[-1.00635849457864,53.44140039758253],"type":"Point"}
}