{
  "type": "Feature",
  "properties": {
    "date:inception_lower":"1992-01-01",
    "date:inception_upper":"1992-01-31",
    "iso:country":"GB",
    "wof:name":"DN10 6RL",
    "wof:placetype":"postalcode"
},
  "geometry": {"coordinates":[-1.006358,53.4414],"type":"Point"}
}