{
  "type": "Feature",
  "properties": {
    "iso:country":"GB",
    "wof:name":"SL9 9JU",
    "wof:placetype":"postalcode"
},
  "geometry": {"coordinates":[-0.56979585961341,51.60653560151692],"type":"Point"}
}