{
  "type": "Feature",
  "properties": {
    "date:inception_lower": "1999-06-01",
    "date:inception_upper": "1999-06-01",
    "iso:country": "GB",
    "wof:name": "NP23 4AB",
    "wof:placetype": "postalcode"
  },
  "geometry": {"coordinates":[-3.175211,51.798462],"type":"Point"}
}
