{
  "type": "Feature",
  "properties": {
    "iso:country":"GB",
    "wof:name":"AL7 2AJ",
    "wof:placetype":"postalcode"
},
  "geometry": {"coordinates":[-0.17487638584088,51.80387894917325],"type":"Point"}
}