{
  "type": "Feature",
  "properties": {
    "date:inception_lower":"1980-01-01",
    "date:inception_upper":"1980-01-31",
    "iso:country":"GB",
    "wof:name":"TQ5 8JZ",
    "wof:placetype":"postalcode"
},
  "geometry": {"coordinates":[-3.528511,50.395583],"type":"Point"}
}