{
  "type": "Feature",
  "properties": {
    "iso:country":"GB",
    "wof:name":"TQ5 8JZ",
    "wof:placetype":"postalcode"
},
  "geometry": {"coordinates":[-3.52851066267729,50.39558302923035],"type":"Point"}
}