{
  "type": "Feature",
  "properties": {
    "iso:country": "GB",
    "wof:name": "PL21 9AB",
    "wof:placetype": "postalcode"
  },
  "geometry": {"coordinates":[-3.921808,50.388957],"type":"Point"}
}
