{
  "type": "Feature",
  "properties": {
    "date:inception_lower": "1980-01-01",
    "date:inception_upper": "1980-01-01",
    "iso:country": "GB",
    "wof:name": "PL21 9AB",
    "wof:placetype": "postalcode"
  },
  "geometry": {"coordinates":[-3.921691,50.388917],"type":"Point"}
}
