{
  "type": "Feature",
  "properties": {
    "iso:country": "GB",
    "wof:name": "WD25 9AW",
    "wof:placetype": "postalcode"
  },
  "geometry": {"coordinates":[-0.377775,51.685049],"type":"Point"}
}
