{
  "type": "Feature",
  "properties": {
    "iso:country":"GB",
    "wof:name":"NG32 1AN",
    "wof:placetype":"postalcode"
},
  "geometry": {"coordinates":[-0.69856417466601,52.85842695929585],"type":"Point"}
}