{
  "type": "Feature",
  "properties": {
    "date:inception_lower":"1980-01-01",
    "date:inception_upper":"1980-01-31",
    "iso:country":"GB",
    "wof:name":"NG32 1AN",
    "wof:placetype":"postalcode"
},
  "geometry": {"coordinates":[-0.698564,52.858427],"type":"Point"}
}