{
  "type": "Feature",
  "properties": {
    "iso:country":"GB",
    "wof:name":"NG1 4BA",
    "wof:placetype":"postalcode"
},
  "geometry": {"coordinates":[-1.14951937366263,52.95707360074864],"type":"Point"}
}