{
  "type": "Feature",
  "properties": {
    "iso:country":"GB",
    "wof:name":"NR15 1YA",
    "wof:placetype":"postalcode"
},
  "geometry": {"coordinates":[1.31996986541798,52.53553314192377],"type":"Point"}
}