{
  "type": "Feature",
  "properties": {
    "date:inception_lower": "1980-01-01",
    "date:inception_upper": "1980-01-01",
    "iso:country": "GB",
    "wof:name": "NR15 1YA",
    "wof:placetype": "postalcode"
  },
  "geometry": {"coordinates":[1.320105,52.534268],"type":"Point"}
}
