{
  "type": "Feature",
  "properties": {
    "iso:country": "GB",
    "wof:name": "NR15 1YA",
    "wof:placetype": "postalcode"
  },
  "geometry": {"coordinates":[1.319996,52.535557],"type":"Point"}
}
