{
  "type": "Feature",
  "properties": {
    "iso:country":"GB",
    "wof:name":"FY7 8RA",
    "wof:placetype":"postalcode"
},
  "geometry": {"coordinates":[-3.0481685415526,53.90230540575644],"type":"Point"}
}