{
  "type": "Feature",
  "properties": {
    "iso:country":"GB",
    "wof:name":"YO17 7BP",
    "wof:placetype":"postalcode"
},
  "geometry": {"coordinates":[-0.80561157869721,54.13996851703526],"type":"Point"}
}