{
  "type": "Feature",
  "properties": {
    "iso:country":"GB",
    "wof:name":"SY3 9LH",
    "wof:placetype":"postalcode"
},
  "geometry": {"coordinates":[-2.75764153529411,52.68576123191739],"type":"Point"}
}