{
  "type": "Feature",
  "properties": {
    "iso:country":"GB",
    "wof:name":"LS12 1TU",
    "wof:placetype":"postalcode"
},
  "geometry": {"coordinates":[-1.59028211698656,53.79483294895667],"type":"Point"}
}