{
  "type": "Feature",
  "properties": {
    "iso:country": "GB",
    "wof:name": "NG24 2HH",
    "wof:placetype": "postalcode"
  },
  "geometry": {"coordinates":[-0.795102,53.086203],"type":"Point"}
}
