{
  "type": "Feature",
  "properties": {
    "iso:country":"GB",
    "wof:name":"NG24 2HH",
    "wof:placetype":"postalcode"
},
  "geometry": {"coordinates":[-0.79510226155835,53.08620310871027],"type":"Point"}
}