{
  "type": "Feature",
  "properties": {
    "iso:country":"GB",
    "wof:name":"SK13 1NT",
    "wof:placetype":"postalcode"
},
  "geometry": {"coordinates":[-1.97035029401601,53.46163423987517],"type":"Point"}
}