{
  "type": "Feature",
  "properties": {
    "date:inception_lower": "2021-02-01",
    "date:inception_upper": "2021-02-01",
    "iso:country": "GB",
    "wof:name": "DA15 8FE",
    "wof:placetype": "postalcode"
  },
  "geometry": {"coordinates":[0.094095,51.451156],"type":"Point"}
}
