{
  "type": "Feature",
  "properties": {
    "date:inception_lower": "2011-12-01",
    "date:inception_upper": "2011-12-01",
    "iso:country": "GB",
    "wof:name": "GL7 5DN",
    "wof:placetype": "postalcode"
  },
  "geometry": {"coordinates":[-1.845381,51.761798],"type":"Point"}
}
