{
  "type": "Feature",
  "properties": {
    "iso:country":"GB",
    "wof:name":"GL7 5DN",
    "wof:placetype":"postalcode"
},
  "geometry": {"coordinates":[-1.84538057892896,51.76179800402009],"type":"Point"}
}