{
  "type": "Feature",
  "properties": {
    "iso:country": "GB",
    "wof:name": "GL7 5DN",
    "wof:placetype": "postalcode"
  },
  "geometry": {"coordinates":[-1.845381,51.761798],"type":"Point"}
}
