{
  "type": "Feature",
  "properties": {
    "iso:country":"GB",
    "wof:name":"CF35 6HZ",
    "wof:placetype":"postalcode"
},
  "geometry": {"coordinates":[-3.52287249042884,51.54900094845102],"type":"Point"}
}