{
  "type": "Feature",
  "properties": {
    "iso:country":"GB",
    "wof:name":"SP2 9ET",
    "wof:placetype":"postalcode"
},
  "geometry": {"coordinates":[-1.82747624044045,51.08347437372126],"type":"Point"}
}