{
  "type": "Feature",
  "properties": {
    "iso:country": "GB",
    "wof:name": "SP2 9ET",
    "wof:placetype": "postalcode"
  },
  "geometry": {"coordinates":[-1.827395,51.083486],"type":"Point"}
}
