{
  "type": "Feature",
  "properties": {
    "date:inception_lower":"2010-06-01",
    "date:inception_upper":"2010-06-30",
    "iso:country":"GB",
    "wof:name":"SP2 9ET",
    "wof:placetype":"postalcode"
},
  "geometry": {"coordinates":[-1.827395,51.083486],"type":"Point"}
}