{
  "type": "Feature",
  "properties": {
    "date:inception_lower": "1980-01-01",
    "date:inception_upper": "1980-01-01",
    "iso:country": "GB",
    "wof:name": "G3 8SR",
    "wof:placetype": "postalcode"
  },
  "geometry": {"coordinates":[-4.293711,55.86545],"type":"Point"}
}
