{
  "type": "Feature",
  "properties": {
    "iso:country":"GB",
    "wof:name":"G3 8SR",
    "wof:placetype":"postalcode"
},
  "geometry": {"coordinates":[-4.2937109422574,55.86545042715466],"type":"Point"}
}