{
  "type": "Feature",
  "properties": {
    "iso:country":"GB",
    "wof:name":"CT19 4HJ",
    "wof:placetype":"postalcode"
},
  "geometry": {"coordinates":[1.13975954088581,51.08850985072099],"type":"Point"}
}