{
  "type": "Feature",
  "properties": {
    "date:inception_lower": "1980-01-01",
    "date:inception_upper": "1980-01-01",
    "iso:country": "GB",
    "wof:name": "CT19 4HJ",
    "wof:placetype": "postalcode"
  },
  "geometry": {"coordinates":[1.13976,51.08851],"type":"Point"}
}
