{
  "type": "Feature",
  "properties": {
    "date:inception_lower":"2001-12-01",
    "date:inception_upper":"2001-12-31",
    "iso:country":"GB",
    "wof:name":"TN2 5GT",
    "wof:placetype":"postalcode"
},
  "geometry": {"coordinates":[0.260356,51.122114],"type":"Point"}
}