{
  "type": "Feature",
  "properties": {
    "iso:country":"GB",
    "wof:name":"TN2 5GT",
    "wof:placetype":"postalcode"
},
  "geometry": {"coordinates":[0.26035564551049,51.12211359985833],"type":"Point"}
}