{
  "type": "Feature",
  "properties": {
    "iso:country":"GB",
    "wof:name":"NE40 3NH",
    "wof:placetype":"postalcode"
},
  "geometry": {"coordinates":[-1.7647184268872,54.97087728664581],"type":"Point"}
}