{
  "type": "Feature",
  "properties": {
    "iso:country":"GB",
    "wof:name":"ST3 5HT",
    "wof:placetype":"postalcode"
},
  "geometry": {"coordinates":[-2.09725182927886,52.9970918246774],"type":"Point"}
}