{
  "type": "Feature",
  "properties": {
    "iso:country":"GB",
    "wof:name":"HP9 1SZ",
    "wof:placetype":"postalcode"
},
  "geometry": {"coordinates":[-0.65258599537715,51.61528392461756],"type":"Point"}
}