{
  "type": "Feature",
  "properties": {
    "iso:country":"GB",
    "wof:name":"E1 0FU",
    "wof:placetype":"postalcode"
},
  "geometry": {"coordinates":[-0.04825186398474,51.51514887641437],"type":"Point"}
}