{
  "type": "Feature",
  "properties": {
    "date:inception_lower": "1980-01-01",
    "date:inception_upper": "1980-01-01",
    "iso:country": "GB",
    "wof:name": "PL14 4DQ",
    "wof:placetype": "postalcode"
  },
  "geometry": {"coordinates":[-4.468642,50.451947],"type":"Point"}
}
