{
  "type": "Feature",
  "properties": {
    "iso:country": "GB",
    "wof:name": "PL14 4DQ",
    "wof:placetype": "postalcode"
  },
  "geometry": {"coordinates":[-4.468642,50.451947],"type":"Point"}
}
