{
  "type": "Feature",
  "properties": {
    "iso:country": "GB",
    "wof:name": "TQ7 1HQ",
    "wof:placetype": "postalcode"
  },
  "geometry": {"coordinates":[-3.778828,50.282754],"type":"Point"}
}
