{
  "type": "Feature",
  "properties": {
    "iso:country":"GB",
    "wof:name":"KY8 4HT",
    "wof:placetype":"postalcode"
},
  "geometry": {"coordinates":[-2.98862250905447,56.19907871282573],"type":"Point"}
}