{
  "type": "Feature",
  "properties": {
    "iso:country": "GB",
    "wof:name": "S11 9DY",
    "wof:placetype": "postalcode"
  },
  "geometry": {"coordinates":[-1.49339,53.364485],"type":"Point"}
}
