{
  "type": "Feature",
  "properties": {
    "iso:country":"GB",
    "wof:name":"S11 9DY",
    "wof:placetype":"postalcode"
},
  "geometry": {"coordinates":[-1.49337506205688,53.36452135326232],"type":"Point"}
}