{
  "type": "Feature",
  "properties": {
    "date:inception_lower": "1980-01-01",
    "date:inception_upper": "1980-01-01",
    "iso:country": "GB",
    "wof:name": "CF40 2QD",
    "wof:placetype": "postalcode"
  },
  "geometry": {"coordinates":[-3.446421,51.620466],"type":"Point"}
}
