{
  "type": "Feature",
  "properties": {
    "date:inception_lower": "1980-01-01",
    "date:inception_upper": "1980-01-01",
    "iso:country": "GB",
    "wof:name": "G5 8QB",
    "wof:placetype": "postalcode"
  },
  "geometry": {"coordinates":[-4.275797,55.849619],"type":"Point"}
}
