{
  "type": "Feature",
  "properties": {
    "date:inception_lower": "1999-12-01",
    "date:inception_upper": "1999-12-01",
    "iso:country": "GB",
    "wof:name": "RG9 1NZ",
    "wof:placetype": "postalcode"
  },
  "geometry": {"coordinates":[-0.897039,51.52647],"type":"Point"}
}
