{
  "type": "Feature",
  "properties": {
    "date:inception_lower": "1998-06-01",
    "date:inception_upper": "1998-06-01",
    "iso:country": "GB",
    "wof:name": "YO26 4UF",
    "wof:placetype": "postalcode"
  },
  "geometry": {"coordinates":[-1.111519,53.957122],"type":"Point"}
}
