{
  "type": "Feature",
  "properties": {
    "iso:country": "GB",
    "wof:name": "PE25 2SP",
    "wof:placetype": "postalcode"
  },
  "geometry": {"coordinates":[0.33934,53.148366],"type":"Point"}
}
