{
  "type": "Feature",
  "properties": {
    "date:inception_lower":"1980-01-01",
    "date:inception_upper":"1980-01-31",
    "iso:country":"GB",
    "wof:name":"PE25 2SP",
    "wof:placetype":"postalcode"
},
  "geometry": {"coordinates":[0.33934,53.148366],"type":"Point"}
}