{
  "type": "Feature",
  "properties": {
    "iso:country":"GB",
    "wof:name":"PE25 2SP",
    "wof:placetype":"postalcode"
},
  "geometry": {"coordinates":[0.3393394886975,53.14836645106262],"type":"Point"}
}