{
  "type": "Feature",
  "properties": {
    "iso:country": "GB",
    "wof:name": "M16 9EA",
    "wof:placetype": "postalcode"
  },
  "geometry": {"coordinates":[-2.267618,53.466173],"type":"Point"}
}
