{
  "type": "Feature",
  "properties": {
    "iso:country":"GB",
    "wof:name":"M16 9EA",
    "wof:placetype":"postalcode"
},
  "geometry": {"coordinates":[-2.26761832498961,53.46617338976078],"type":"Point"}
}