{
  "type": "Feature",
  "properties": {
    "iso:country":"GB",
    "wof:name":"CB4 3QH",
    "wof:placetype":"postalcode"
},
  "geometry": {"coordinates":[0.10812162146223,52.21637183763244],"type":"Point"}
}