{
  "type": "Feature",
  "properties": {
    "iso:country":"GB",
    "wof:name":"WD19 4NL",
    "wof:placetype":"postalcode"
},
  "geometry": {"coordinates":[-0.39161095411906,51.63996411830828],"type":"Point"}
}