{
  "type": "Feature",
  "properties": {
    "iso:country": "GB",
    "wof:name": "PE15 9LN",
    "wof:placetype": "postalcode"
  },
  "geometry": {"coordinates":[0.087667,52.535858],"type":"Point"}
}
