{
  "type": "Feature",
  "properties": {
    "date:inception_lower":"1992-01-01",
    "date:inception_upper":"1992-01-31",
    "iso:country":"GB",
    "wof:name":"PE15 9LN",
    "wof:placetype":"postalcode"
},
  "geometry": {"coordinates":[0.087667,52.535858],"type":"Point"}
}