{
  "type": "Feature",
  "properties": {
    "date:inception_lower": "1980-01-01",
    "date:inception_upper": "1980-01-01",
    "iso:country": "GB",
    "wof:name": "PO20 8LX",
    "wof:placetype": "postalcode"
  },
  "geometry": {"coordinates":[-0.89445,50.782373],"type":"Point"}
}
