{
  "type": "Feature",
  "properties": {
    "iso:country":"GB",
    "wof:name":"PO20 8LX",
    "wof:placetype":"postalcode"
},
  "geometry": {"coordinates":[-0.89444989590891,50.78237301475886],"type":"Point"}
}