{
  "type": "Feature",
  "properties": {
    "iso:country":"GB",
    "wof:name":"B97 4HY",
    "wof:placetype":"postalcode"
},
  "geometry": {"coordinates":[-1.94242470032864,52.30190852281427],"type":"Point"}
}