{
  "type": "Feature",
  "properties": {
    "date:inception_lower": "1985-04-01",
    "date:inception_upper": "1985-04-01",
    "iso:country": "GB",
    "wof:name": "FY5 3TQ",
    "wof:placetype": "postalcode"
  },
  "geometry": {"coordinates":[-3.023073,53.863189],"type":"Point"}
}
