{
  "type": "Feature",
  "properties": {
    "date:inception_lower":"1980-01-01",
    "date:inception_upper":"1980-01-31",
    "iso:country":"GB",
    "wof:name":"SA11 4DE",
    "wof:placetype":"postalcode"
},
  "geometry": {"coordinates":[-3.729614,51.699097],"type":"Point"}
}