{
  "type": "Feature",
  "properties": {
    "iso:country": "GB",
    "wof:name": "SA11 4DE",
    "wof:placetype": "postalcode"
  },
  "geometry": {"coordinates":[-3.729614,51.699097],"type":"Point"}
}
