{
  "type": "Feature",
  "properties": {
    "iso:country":"GB",
    "wof:name":"SA11 4DE",
    "wof:placetype":"postalcode"
},
  "geometry": {"coordinates":[-3.72956881688694,51.69905677216084],"type":"Point"}
}