{
  "type": "Feature",
  "properties": {
    "date:inception_lower": "1987-04-01",
    "date:inception_upper": "1987-04-01",
    "iso:country": "GB",
    "wof:name": "GL51 0QL",
    "wof:placetype": "postalcode"
  },
  "geometry": {"coordinates":[-2.118839,51.916384],"type":"Point"}
}
