{
  "type": "Feature",
  "properties": {
    "iso:country": "GB",
    "wof:name": "GL51 0QL",
    "wof:placetype": "postalcode"
  },
  "geometry": {"coordinates":[-2.118839,51.916384],"type":"Point"}
}
