{
  "type": "Feature",
  "properties": {
    "iso:country": "GB",
    "wof:name": "SY3 0JZ",
    "wof:placetype": "postalcode"
  },
  "geometry": {"coordinates":[-2.778364,52.674776],"type":"Point"}
}
