{
  "type": "Feature",
  "properties": {
    "iso:country":"GB",
    "wof:name":"SY3 0JZ",
    "wof:placetype":"postalcode"
},
  "geometry": {"coordinates":[-2.77836425252699,52.67477615517991],"type":"Point"}
}