{
  "type": "Feature",
  "properties": {
    "iso:country": "GB",
    "wof:name": "GL51 8DL",
    "wof:placetype": "postalcode"
  },
  "geometry": {"coordinates":[-2.104808,51.906282],"type":"Point"}
}
