{
  "type": "Feature",
  "properties": {
    "iso:country":"GB",
    "wof:name":"AB21 9TX",
    "wof:placetype":"postalcode"
},
  "geometry": {"coordinates":[-2.19803187971118,57.19001809713259],"type":"Point"}
}