{
  "type": "Feature",
  "properties": {
    "iso:country":"GB",
    "wof:name":"ME7 4AW",
    "wof:placetype":"postalcode"
},
  "geometry": {"coordinates":[0.55018290024785,51.38505456977325],"type":"Point"}
}