{
  "type": "Feature",
  "properties": {
    "date:inception_lower": "2022-10-01",
    "date:inception_upper": "2022-10-01",
    "iso:country": "GB",
    "wof:name": "OX39 4GH",
    "wof:placetype": "postalcode"
  },
  "geometry": {"coordinates":[-0.912001,51.696583],"type":"Point"}
}
