{
  "type": "Feature",
  "properties": {
    "date:inception_lower": "1980-01-01",
    "date:inception_upper": "1980-01-01",
    "iso:country": "GB",
    "wof:name": "B79 0BD",
    "wof:placetype": "postalcode"
  },
  "geometry": {"coordinates":[-1.618834,52.694881],"type":"Point"}
}
