{
  "type": "Feature",
  "properties": {
    "iso:country":"GB",
    "wof:name":"B79 0BD",
    "wof:placetype":"postalcode"
},
  "geometry": {"coordinates":[-1.61883374504679,52.69488067066307],"type":"Point"}
}