{
  "type": "Feature",
  "properties": {
    "iso:country": "GB",
    "wof:name": "DN14 6YD",
    "wof:placetype": "postalcode"
  },
  "geometry": {"coordinates":[-0.859357,53.71483],"type":"Point"}
}
