{
  "type": "Feature",
  "properties": {
    "date:inception_lower":"1990-07-01",
    "date:inception_upper":"1990-07-31",
    "iso:country":"GB",
    "wof:name":"DN14 6YD",
    "wof:placetype":"postalcode"
},
  "geometry": {"coordinates":[-0.859357,53.71483],"type":"Point"}
}