{
  "type": "Feature",
  "properties": {
    "iso:country": "GB",
    "wof:name": "CH5 2DU",
    "wof:placetype": "postalcode"
  },
  "geometry": {"coordinates":[-3.014127,53.209043],"type":"Point"}
}
