{
  "type": "Feature",
  "properties": {
    "date:inception_lower":"1998-06-01",
    "date:inception_upper":"1998-06-30",
    "iso:country":"GB",
    "wof:name":"CH5 2DU",
    "wof:placetype":"postalcode"
},
  "geometry": {"coordinates":[-3.013622,53.2092],"type":"Point"}
}