{
  "type": "Feature",
  "properties": {
    "iso:country": "GB",
    "wof:name": "CH5 2DU",
    "wof:placetype": "postalcode"
  },
  "geometry": {"coordinates":[-3.013622,53.2092],"type":"Point"}
}
