{
  "type": "Feature",
  "properties": {
    "iso:country":"GB",
    "wof:name":"CH5 2DU",
    "wof:placetype":"postalcode"
},
  "geometry": {"coordinates":[-3.0141273937857,53.20902707119046],"type":"Point"}
}