{
  "type": "Feature",
  "properties": {
    "iso:country":"GB",
    "wof:name":"BS37 4BH",
    "wof:placetype":"postalcode"
},
  "geometry": {"coordinates":[-2.42187594510381,51.53856203718745],"type":"Point"}
}