{
  "type": "Feature",
  "properties": {
    "iso:country":"GB",
    "wof:name":"YO25 5NT",
    "wof:placetype":"postalcode"
},
  "geometry": {"coordinates":[-0.42481757807322,54.0012900715918],"type":"Point"}
}