{
  "type": "Feature",
  "properties": {
    "date:inception_lower": "2001-06-01",
    "date:inception_upper": "2001-06-01",
    "iso:country": "GB",
    "wof:name": "YO25 5NT",
    "wof:placetype": "postalcode"
  },
  "geometry": {"coordinates":[-0.424818,54.00129],"type":"Point"}
}
