{
  "type": "Feature",
  "properties": {
    "iso:country":"GB",
    "wof:name":"TA6 7HR",
    "wof:placetype":"postalcode"
},
  "geometry": {"coordinates":[-3.01459726276527,51.124499872131],"type":"Point"}
}