{
  "type": "Feature",
  "properties": {
    "iso:country": "GB",
    "wof:name": "ST6 8QJ",
    "wof:placetype": "postalcode"
  },
  "geometry": {"coordinates":[-2.136095,53.077488],"type":"Point"}
}
