{
  "type": "Feature",
  "properties": {
    "iso:country":"GB",
    "wof:name":"ST6 8QJ",
    "wof:placetype":"postalcode"
},
  "geometry": {"coordinates":[-2.13609465852898,53.07748822660492],"type":"Point"}
}