{
  "type": "Feature",
  "properties": {
    "iso:country":"GB",
    "wof:name":"EH7 5HL",
    "wof:placetype":"postalcode"
},
  "geometry": {"coordinates":[-3.17837923577417,55.9624328372829],"type":"Point"}
}