{
  "type": "Feature",
  "properties": {
    "iso:country": "GB",
    "wof:name": "SN4 7RT",
    "wof:placetype": "postalcode"
  },
  "geometry": {"coordinates":[-1.868743,51.498868],"type":"Point"}
}
