{
  "type": "Feature",
  "properties": {
    "date:inception_lower": "1997-06-01",
    "date:inception_upper": "1997-06-01",
    "iso:country": "GB",
    "wof:name": "SN4 7RT",
    "wof:placetype": "postalcode"
  },
  "geometry": {"coordinates":[-1.868743,51.498868],"type":"Point"}
}
