{
  "type": "Feature",
  "properties": {
    "iso:country":"GB",
    "wof:name":"IP22 4NE",
    "wof:placetype":"postalcode"
},
  "geometry": {"coordinates":[1.09866224381803,52.38105186924896],"type":"Point"}
}