{
  "type": "Feature",
  "properties": {
    "iso:country": "GB",
    "wof:name": "YO62 6RJ",
    "wof:placetype": "postalcode"
  },
  "geometry": {"coordinates":[-0.873664,54.222495],"type":"Point"}
}
