{
  "type": "Feature",
  "properties": {
    "iso:country":"GB",
    "wof:name":"BD23 2PS",
    "wof:placetype":"postalcode"
},
  "geometry": {"coordinates":[-2.01601116658464,53.9572399712014],"type":"Point"}
}