{
  "type": "Feature",
  "properties": {
    "iso:country": "GB",
    "wof:name": "BD23 2PS",
    "wof:placetype": "postalcode"
  },
  "geometry": {"coordinates":[-2.016011,53.95724],"type":"Point"}
}
