{
  "type": "Feature",
  "properties": {
    "iso:country": "GB",
    "wof:name": "SE15 4LN",
    "wof:placetype": "postalcode"
  },
  "geometry": {"coordinates":[-0.071369,51.466018],"type":"Point"}
}
