{
  "type": "Feature",
  "properties": {
    "iso:country":"GB",
    "wof:name":"EH22 2NU",
    "wof:placetype":"postalcode"
},
  "geometry": {"coordinates":[-2.99920215918443,55.90442565195976],"type":"Point"}
}