{
  "type": "Feature",
  "properties": {
    "date:inception_lower": "1980-01-01",
    "date:inception_upper": "1980-01-01",
    "iso:country": "GB",
    "wof:name": "MK3 6HX",
    "wof:placetype": "postalcode"
  },
  "geometry": {"coordinates":[-0.744572,52.000789],"type":"Point"}
}
