{
  "type": "Feature",
  "properties": {
    "iso:country":"GB",
    "wof:name":"MK3 6HX",
    "wof:placetype":"postalcode"
},
  "geometry": {"coordinates":[-0.74457213258354,52.00078876657582],"type":"Point"}
}