{
  "type": "Feature",
  "properties": {
    "iso:country": "GB",
    "wof:name": "WV4 4UG",
    "wof:placetype": "postalcode"
  },
  "geometry": {"coordinates":[-2.19391,52.562052],"type":"Point"}
}
