{
  "type": "Feature",
  "properties": {
    "iso:country":"GB",
    "wof:name":"WV4 4UG",
    "wof:placetype":"postalcode"
},
  "geometry": {"coordinates":[-2.19391018249609,52.5620515901652],"type":"Point"}
}