{
  "type": "Feature",
  "properties": {
    "iso:country": "GB",
    "wof:name": "HU8 9TY",
    "wof:placetype": "postalcode"
  },
  "geometry": {"coordinates":[-0.30292,53.784308],"type":"Point"}
}
