{
  "type": "Feature",
  "properties": {
    "iso:country":"GB",
    "wof:name":"EH9 1NL",
    "wof:placetype":"postalcode"
},
  "geometry": {"coordinates":[-3.18230962651194,55.93792777145785],"type":"Point"}
}