{
  "type": "Feature",
  "properties": {
    "iso:country":"GB",
    "wof:name":"IP3 9DG",
    "wof:placetype":"postalcode"
},
  "geometry": {"coordinates":[1.19081932252977,52.04409897334254],"type":"Point"}
}