{
  "type": "Feature",
  "properties": {
    "date:inception_lower": "1994-12-01",
    "date:inception_upper": "1994-12-01",
    "iso:country": "GB",
    "wof:name": "TN2 4BN",
    "wof:placetype": "postalcode"
  },
  "geometry": {"coordinates":[0.325429,51.163512],"type":"Point"}
}
