{
  "type": "Feature",
  "properties": {
    "iso:country": "GB",
    "wof:name": "TN2 4BN",
    "wof:placetype": "postalcode"
  },
  "geometry": {"coordinates":[0.325429,51.163512],"type":"Point"}
}
