{
  "type": "Feature",
  "properties": {
    "iso:country": "GB",
    "wof:name": "WV8 1UA",
    "wof:placetype": "postalcode"
  },
  "geometry": {"coordinates":[-2.161851,52.621046],"type":"Point"}
}
