{
  "type": "Feature",
  "properties": {
    "date:inception_lower":"2002-07-01",
    "date:inception_upper":"2002-07-31",
    "iso:country":"GB",
    "wof:name":"SW6 6PW",
    "wof:placetype":"postalcode"
},
  "geometry": {"coordinates":[-0.220192,51.477859],"type":"Point"}
}