{
  "type": "Feature",
  "properties": {
    "iso:country":"GB",
    "wof:name":"BH25 6EN",
    "wof:placetype":"postalcode"
},
  "geometry": {"coordinates":[-1.65489944067692,50.75478035942122],"type":"Point"}
}