{
  "type": "Feature",
  "properties": {
    "date:inception_lower": "2000-06-01",
    "date:inception_upper": "2000-06-01",
    "iso:country": "GB",
    "wof:name": "BH25 6EN",
    "wof:placetype": "postalcode"
  },
  "geometry": {"coordinates":[-1.654977,50.754771],"type":"Point"}
}
