{
  "type": "Feature",
  "properties": {
    "date:inception_lower":"1980-01-01",
    "date:inception_upper":"1980-01-31",
    "iso:country":"GB",
    "wof:name":"LE15 9QG",
    "wof:placetype":"postalcode"
},
  "geometry": {"coordinates":[-0.726617,52.5881],"type":"Point"}
}