{
  "type": "Feature",
  "properties": {
    "iso:country":"GB",
    "wof:name":"LE15 9QG",
    "wof:placetype":"postalcode"
},
  "geometry": {"coordinates":[-0.72661732323908,52.58809983765872],"type":"Point"}
}