{
  "type": "Feature",
  "properties": {
    "iso:country": "GB",
    "wof:name": "LE15 9QG",
    "wof:placetype": "postalcode"
  },
  "geometry": {"coordinates":[-0.726617,52.5881],"type":"Point"}
}
