{
  "type": "Feature",
  "properties": {
    "date:inception_lower":"2004-10-01",
    "date:inception_upper":"2004-10-31",
    "iso:country":"GB",
    "wof:name":"G52 4UB",
    "wof:placetype":"postalcode"
},
  "geometry": {"coordinates":[-4.366288,55.868318],"type":"Point"}
}