{
  "type": "Feature",
  "properties": {
    "iso:country": "GB",
    "wof:name": "G52 4UB",
    "wof:placetype": "postalcode"
  },
  "geometry": {"coordinates":[-4.366288,55.868318],"type":"Point"}
}
