{
  "type": "Feature",
  "properties": {
    "iso:country":"GB",
    "wof:name":"G52 4UB",
    "wof:placetype":"postalcode"
},
  "geometry": {"coordinates":[-4.36628773255709,55.86831795596567],"type":"Point"}
}