{
  "type": "Feature",
  "properties": {
    "iso:country":"GB",
    "wof:name":"TW19 5JT",
    "wof:placetype":"postalcode"
},
  "geometry": {"coordinates":[-0.57147694020635,51.45986889568904],"type":"Point"}
}