{
  "type": "Feature",
  "properties": {
    "date:inception_lower": "1980-01-01",
    "date:inception_upper": "1980-01-01",
    "iso:country": "GB",
    "wof:name": "TW19 5JT",
    "wof:placetype": "postalcode"
  },
  "geometry": {"coordinates":[-0.571477,51.459869],"type":"Point"}
}
