{
  "type": "Feature",
  "properties": {
    "iso:country":"GB",
    "wof:name":"TW12 2UW",
    "wof:placetype":"postalcode"
},
  "geometry": {"coordinates":[-0.36325427087859,51.42213987555581],"type":"Point"}
}