{
  "type": "Feature",
  "properties": {
    "iso:country":"GB",
    "wof:name":"NG33 4PJ",
    "wof:placetype":"postalcode"
},
  "geometry": {"coordinates":[-0.48320703844631,52.78689798243241],"type":"Point"}
}