{
  "type": "Feature",
  "properties": {
    "iso:country": "GB",
    "wof:name": "NG33 4PJ",
    "wof:placetype": "postalcode"
  },
  "geometry": {"coordinates":[-0.483207,52.786898],"type":"Point"}
}
