{
  "type": "Feature",
  "properties": {
    "iso:country":"GB",
    "wof:name":"NE24 5HT",
    "wof:placetype":"postalcode"
},
  "geometry": {"coordinates":[-1.53345469243935,55.13072172967993],"type":"Point"}
}