{
  "type": "Feature",
  "properties": {
    "iso:country":"GB",
    "wof:name":"DL6 1EB",
    "wof:placetype":"postalcode"
},
  "geometry": {"coordinates":[-1.43118334081879,54.3443203539001],"type":"Point"}
}