{
  "type": "Feature",
  "properties": {
    "date:inception_lower": "1980-01-01",
    "date:inception_upper": "1980-01-01",
    "iso:country": "GB",
    "wof:name": "DL6 1EB",
    "wof:placetype": "postalcode"
  },
  "geometry": {"coordinates":[-1.431183,54.34432],"type":"Point"}
}
