{
  "type": "Feature",
  "properties": {
    "iso:country":"GB",
    "wof:name":"B60 4FN",
    "wof:placetype":"postalcode"
},
  "geometry": {"coordinates":[-2.06583326083535,52.28418415879239],"type":"Point"}
}