{
  "type": "Feature",
  "properties": {
    "iso:country":"GB",
    "wof:name":"M34 6AQ",
    "wof:placetype":"postalcode"
},
  "geometry": {"coordinates":[-2.11080181371037,53.45115960538879],"type":"Point"}
}