{
  "type": "Feature",
  "properties": {
    "iso:country": "GB",
    "wof:name": "M34 6AQ",
    "wof:placetype": "postalcode"
  },
  "geometry": {"coordinates":[-2.110802,53.45116],"type":"Point"}
}
