{
  "type": "Feature",
  "properties": {
    "iso:country":"GB",
    "wof:name":"S71 1JJ",
    "wof:placetype":"postalcode"
},
  "geometry": {"coordinates":[-1.4805915474306,53.56043522856503],"type":"Point"}
}