{
  "type": "Feature",
  "properties": {
    "date:inception_lower": "2006-05-01",
    "date:inception_upper": "2006-05-01",
    "iso:country": "GB",
    "wof:name": "WV4 6DY",
    "wof:placetype": "postalcode"
  },
  "geometry": {"coordinates":[-2.1103,52.56295],"type":"Point"}
}
