{
  "type": "Feature",
  "properties": {
    "date:inception_lower": "2018-12-01",
    "date:inception_upper": "2018-12-01",
    "iso:country": "GB",
    "wof:name": "DL12 8GY",
    "wof:placetype": "postalcode"
  },
  "geometry": {"coordinates":[-1.90944,54.544616],"type":"Point"}
}
