{
  "type": "Feature",
  "properties": {
    "date:inception_lower": "1980-01-01",
    "date:inception_upper": "1980-01-01",
    "iso:country": "GB",
    "wof:name": "RM15 6JB",
    "wof:placetype": "postalcode"
  },
  "geometry": {"coordinates":[0.292567,51.518991],"type":"Point"}
}
