{
  "type": "Feature",
  "properties": {
    "iso:country":"GB",
    "wof:name":"RM15 6JB",
    "wof:placetype":"postalcode"
},
  "geometry": {"coordinates":[0.29256724647253,51.5189907008581],"type":"Point"}
}