{
  "type": "Feature",
  "properties": {
    "iso:country":"GB",
    "wof:name":"CW12 2GD",
    "wof:placetype":"postalcode"
},
  "geometry": {"coordinates":[-2.1979578884119,53.16955641081827],"type":"Point"}
}