{
  "type": "Feature",
  "properties": {
    "iso:country": "GB",
    "wof:name": "TA5 2RJ",
    "wof:placetype": "postalcode"
  },
  "geometry": {"coordinates":[-3.060114,51.14592],"type":"Point"}
}
