{
  "type": "Feature",
  "properties": {
    "iso:country":"GB",
    "wof:name":"TA5 2RJ",
    "wof:placetype":"postalcode"
},
  "geometry": {"coordinates":[-3.06011415610492,51.14592043309059],"type":"Point"}
}