{
  "type": "Feature",
  "properties": {
    "date:inception_lower": "1995-07-01",
    "date:inception_upper": "1995-07-01",
    "iso:country": "GB",
    "wof:name": "TA5 2RJ",
    "wof:placetype": "postalcode"
  },
  "geometry": {"coordinates":[-3.060114,51.14592],"type":"Point"}
}
