{
  "type": "Feature",
  "properties": {
    "iso:country":"GB",
    "wof:name":"HP4 1NN",
    "wof:placetype":"postalcode"
},
  "geometry": {"coordinates":[-0.54448303869589,51.77832824438134],"type":"Point"}
}