{
  "type": "Feature",
  "properties": {
    "iso:country":"GB",
    "wof:name":"ME20 7RE",
    "wof:placetype":"postalcode"
},
  "geometry": {"coordinates":[0.47321122764714,51.29804680663491],"type":"Point"}
}