{
  "type": "Feature",
  "properties": {
    "date:inception_lower": "1980-01-01",
    "date:inception_upper": "1980-01-01",
    "iso:country": "GB",
    "wof:name": "ME20 7RE",
    "wof:placetype": "postalcode"
  },
  "geometry": {"coordinates":[0.473211,51.298047],"type":"Point"}
}
