{
  "type": "Feature",
  "properties": {
    "iso:country":"GB",
    "wof:name":"TF2 9DH",
    "wof:placetype":"postalcode"
},
  "geometry": {"coordinates":[-2.4404337684341,52.69239908779868],"type":"Point"}
}