{
  "type": "Feature",
  "properties": {
    "iso:country":"GB",
    "wof:name":"SN3 2FH",
    "wof:placetype":"postalcode"
},
  "geometry": {"coordinates":[-1.74744971355029,51.55304981609013],"type":"Point"}
}