{
  "type": "Feature",
  "properties": {
    "date:inception_lower": "1980-01-01",
    "date:inception_upper": "1980-01-01",
    "iso:country": "GB",
    "wof:name": "PE11 4JD",
    "wof:placetype": "postalcode"
  },
  "geometry": {"coordinates":[-0.183441,52.857921],"type":"Point"}
}
