{
  "type": "Feature",
  "properties": {
    "iso:country":"GB",
    "wof:name":"PE11 4JD",
    "wof:placetype":"postalcode"
},
  "geometry": {"coordinates":[-0.18347225951818,52.85789444819727],"type":"Point"}
}