{
  "type": "Feature",
  "properties": {
    "iso:country":"GB",
    "wof:name":"BL7 9DF",
    "wof:placetype":"postalcode"
},
  "geometry": {"coordinates":[-2.42394327795252,53.6139936313671],"type":"Point"}
}