{
  "type": "Feature",
  "properties": {
    "iso:country":"GB",
    "wof:name":"ST5 0JY",
    "wof:placetype":"postalcode"
},
  "geometry": {"coordinates":[-2.20922920422555,53.02344733690547],"type":"Point"}
}