{
  "type": "Feature",
  "properties": {
    "iso:country":"GB",
    "wof:name":"BS16 2QW",
    "wof:placetype":"postalcode"
},
  "geometry": {"coordinates":[-2.51485104130073,51.48790109868927],"type":"Point"}
}