{
  "type": "Feature",
  "properties": {
    "date:inception_lower": "1980-01-01",
    "date:inception_upper": "1980-01-01",
    "iso:country": "GB",
    "wof:name": "BS16 2QW",
    "wof:placetype": "postalcode"
  },
  "geometry": {"coordinates":[-2.514851,51.487901],"type":"Point"}
}
