{
  "type": "Feature",
  "properties": {
    "iso:country": "GB",
    "wof:name": "WS13 6BX",
    "wof:placetype": "postalcode"
  },
  "geometry": {"coordinates":[-1.815033,52.691366],"type":"Point"}
}
