{
  "type": "Feature",
  "properties": {
    "iso:country":"GB",
    "wof:name":"GU21 5JT",
    "wof:placetype":"postalcode"
},
  "geometry": {"coordinates":[-0.54128778353511,51.32620478927527],"type":"Point"}
}