{
  "type": "Feature",
  "properties": {
    "iso:country":"GB",
    "wof:name":"CV5 6NQ",
    "wof:placetype":"postalcode"
},
  "geometry": {"coordinates":[-1.5246331943636,52.40051579400749],"type":"Point"}
}