{
  "type": "Feature",
  "properties": {
    "iso:country": "GB",
    "wof:name": "CV5 6NQ",
    "wof:placetype": "postalcode"
  },
  "geometry": {"coordinates":[-1.524989,52.400695],"type":"Point"}
}
