{
  "type": "Feature",
  "properties": {
    "iso:country": "GB",
    "wof:name": "LS23 7AP",
    "wof:placetype": "postalcode"
  },
  "geometry": {"coordinates":[-1.344547,53.909877],"type":"Point"}
}
