{
  "type": "Feature",
  "properties": {
    "date:inception_lower": "1980-01-01",
    "date:inception_upper": "1980-01-01",
    "iso:country": "GB",
    "wof:name": "LL35 0SE",
    "wof:placetype": "postalcode"
  },
  "geometry": {"coordinates":[-4.069628,52.552646],"type":"Point"}
}
