{
  "type": "Feature",
  "properties": {
    "iso:country":"GB",
    "wof:name":"LL35 0SE",
    "wof:placetype":"postalcode"
},
  "geometry": {"coordinates":[-4.06962836055465,52.55264635432227],"type":"Point"}
}