{
  "type": "Feature",
  "properties": {
    "iso:country":"GB",
    "wof:name":"BH15 1AZ",
    "wof:placetype":"postalcode"
},
  "geometry": {"coordinates":[-1.98200079597578,50.71763658540778],"type":"Point"}
}