{
  "type": "Feature",
  "properties": {
    "iso:country": "GB",
    "wof:name": "PO40 9SZ",
    "wof:placetype": "postalcode"
  },
  "geometry": {"coordinates":[-1.532373,50.694219],"type":"Point"}
}
