{
  "type": "Feature",
  "properties": {
    "iso:country":"GB",
    "wof:name":"PO40 9SZ",
    "wof:placetype":"postalcode"
},
  "geometry": {"coordinates":[-1.53238129323572,50.69424638990301],"type":"Point"}
}