{
  "type": "Feature",
  "properties": {
    "iso:country":"GB",
    "wof:name":"DN41 7JD",
    "wof:placetype":"postalcode"
},
  "geometry": {"coordinates":[-0.17304594701144,53.57902996627575],"type":"Point"}
}