{
  "type": "Feature",
  "properties": {
    "iso:country": "GB",
    "wof:name": "DN41 7JD",
    "wof:placetype": "postalcode"
  },
  "geometry": {"coordinates":[-0.173046,53.57903],"type":"Point"}
}
