{
  "type": "Feature",
  "properties": {
    "date:inception_lower": "1996-06-01",
    "date:inception_upper": "1996-06-01",
    "iso:country": "GB",
    "wof:name": "RM17 6QR",
    "wof:placetype": "postalcode"
  },
  "geometry": {"coordinates":[0.317378,51.474743],"type":"Point"}
}
