{
  "type": "Feature",
  "properties": {
    "iso:country": "GB",
    "wof:name": "RM17 6QR",
    "wof:placetype": "postalcode"
  },
  "geometry": {"coordinates":[0.317378,51.474743],"type":"Point"}
}
