{
  "type": "Feature",
  "properties": {
    "iso:country":"GB",
    "wof:name":"ME4 5DL",
    "wof:placetype":"postalcode"
},
  "geometry": {"coordinates":[0.54175549740848,51.3725208064926],"type":"Point"}
}