{
  "type": "Feature",
  "properties": {
    "date:inception_lower":"2013-12-01",
    "date:inception_upper":"2013-12-31",
    "iso:country":"GB",
    "wof:name":"DN5 0PY",
    "wof:placetype":"postalcode"
},
  "geometry": {"coordinates":[-1.137854,53.557818],"type":"Point"}
}