{
  "type": "Feature",
  "properties": {
    "iso:country":"GB",
    "wof:name":"DN5 0PY",
    "wof:placetype":"postalcode"
},
  "geometry": {"coordinates":[-1.13785400667246,53.5578184570511],"type":"Point"}
}