{
  "type": "Feature",
  "properties": {
    "iso:country":"GB",
    "wof:name":"M45 7TT",
    "wof:placetype":"postalcode"
},
  "geometry": {"coordinates":[-2.30001144657693,53.55466833021891],"type":"Point"}
}