{
  "type": "Feature",
  "properties": {
    "iso:country": "GB",
    "wof:name": "M45 7TT",
    "wof:placetype": "postalcode"
  },
  "geometry": {"coordinates":[-2.300011,53.554668],"type":"Point"}
}
