{
  "type": "Feature",
  "properties": {
    "iso:country":"GB",
    "wof:name":"IP3 8RD",
    "wof:placetype":"postalcode"
},
  "geometry": {"coordinates":[1.20737440758294,52.03799186603123],"type":"Point"}
}