{
  "type": "Feature",
  "properties": {
    "iso:country":"GB",
    "wof:name":"SW4 7TR",
    "wof:placetype":"postalcode"
},
  "geometry": {"coordinates":[-0.13087462219772,51.4642119876736],"type":"Point"}
}