{
  "type": "Feature",
  "properties": {
    "iso:country":"GB",
    "wof:name":"OX3 7BA",
    "wof:placetype":"postalcode"
},
  "geometry": {"coordinates":[-1.21302980622218,51.75941971205999],"type":"Point"}
}