{
  "type": "Feature",
  "properties": {
    "iso:country": "GB",
    "wof:name": "OX3 7BA",
    "wof:placetype": "postalcode"
  },
  "geometry": {"coordinates":[-1.21303,51.75942],"type":"Point"}
}
