{
  "type": "Feature",
  "properties": {
    "iso:country":"GB",
    "wof:name":"HA5 1JY",
    "wof:placetype":"postalcode"
},
  "geometry": {"coordinates":[-0.38378354793766,51.58531952593291],"type":"Point"}
}