{
  "type": "Feature",
  "properties": {
    "date:inception_lower": "1981-06-01",
    "date:inception_upper": "1981-06-01",
    "iso:country": "GB",
    "wof:name": "GL16 7RR",
    "wof:placetype": "postalcode"
  },
  "geometry": {"coordinates":[-2.601799,51.793427],"type":"Point"}
}
