{
  "type": "Feature",
  "properties": {
    "iso:country": "GB",
    "wof:name": "PL19 8BQ",
    "wof:placetype": "postalcode"
  },
  "geometry": {"coordinates":[-4.146277,50.549031],"type":"Point"}
}
