{
  "type": "Feature",
  "properties": {
    "iso:country": "GB",
    "wof:name": "CB24 8XY",
    "wof:placetype": "postalcode"
  },
  "geometry": {"coordinates":[0.121734,52.28969],"type":"Point"}
}
