{
  "type": "Feature",
  "properties": {
    "iso:country":"GB",
    "wof:name":"SK4 2JJ",
    "wof:placetype":"postalcode"
},
  "geometry": {"coordinates":[-2.17848465884179,53.41119544531926],"type":"Point"}
}