{
  "type": "Feature",
  "properties": {
    "iso:country":"GB",
    "wof:name":"CV7 7ES",
    "wof:placetype":"postalcode"
},
  "geometry": {"coordinates":[-1.65291459750002,52.39680826974809],"type":"Point"}
}