{
  "type": "Feature",
  "properties": {
    "iso:country":"GB",
    "wof:name":"EH39 5DG",
    "wof:placetype":"postalcode"
},
  "geometry": {"coordinates":[-2.74047709230037,56.05308620923088],"type":"Point"}
}