{
  "type": "Feature",
  "properties": {
    "date:inception_lower":"1998-12-01",
    "date:inception_upper":"1998-12-31",
    "iso:country":"GB",
    "wof:name":"TR19 6DR",
    "wof:placetype":"postalcode"
},
  "geometry": {"coordinates":[-5.61723,50.069256],"type":"Point"}
}