{
  "type": "Feature",
  "properties": {
    "iso:country":"GB",
    "wof:name":"PA12 4BW",
    "wof:placetype":"postalcode"
},
  "geometry": {"coordinates":[-4.62911818366366,55.79606227069935],"type":"Point"}
}