{
  "type": "Feature",
  "properties": {
    "iso:country":"GB",
    "wof:name":"NP11 7HX",
    "wof:placetype":"postalcode"
},
  "geometry": {"coordinates":[-3.17803176039017,51.61938404715572],"type":"Point"}
}