{
  "type": "Feature",
  "properties": {
    "date:inception_lower":"1999-06-01",
    "date:inception_upper":"1999-06-30",
    "iso:country":"GB",
    "wof:name":"NP11 7HX",
    "wof:placetype":"postalcode"
},
  "geometry": {"coordinates":[-3.178038,51.619279],"type":"Point"}
}