{
  "type": "Feature",
  "properties": {
    "iso:country":"GB",
    "wof:name":"HU17 9HL",
    "wof:placetype":"postalcode"
},
  "geometry": {"coordinates":[-0.42727185661977,53.84739800258315],"type":"Point"}
}