{
  "type": "Feature",
  "properties": {
    "iso:country":"GB",
    "wof:name":"TN22 1DS",
    "wof:placetype":"postalcode"
},
  "geometry": {"coordinates":[0.09625275133342,50.97443260544382],"type":"Point"}
}