{
  "type": "Feature",
  "properties": {
    "iso:country":"GB",
    "wof:name":"CW12 3HR",
    "wof:placetype":"postalcode"
},
  "geometry": {"coordinates":[-2.1964760402399,53.16608914266573],"type":"Point"}
}