{
  "type": "Feature",
  "properties": {
    "iso:country":"GB",
    "wof:name":"EH49 6DD",
    "wof:placetype":"postalcode"
},
  "geometry": {"coordinates":[-3.61517387718825,55.9728563636767],"type":"Point"}
}