{
  "type": "Feature",
  "properties": {
    "iso:country": "GB",
    "wof:name": "S18 2FX",
    "wof:placetype": "postalcode"
  },
  "geometry": {"coordinates":[-1.458985,53.305728],"type":"Point"}
}
