{
  "type": "Feature",
  "properties": {
    "iso:country":"GB",
    "wof:name":"CF3 2EU",
    "wof:placetype":"postalcode"
},
  "geometry": {"coordinates":[-3.09813498175554,51.50965928555881],"type":"Point"}
}