{
  "type": "Feature",
  "properties": {
    "iso:country":"GB",
    "wof:name":"ME9 9NS",
    "wof:placetype":"postalcode"
},
  "geometry": {"coordinates":[0.77624368285405,51.32678634115148],"type":"Point"}
}