{
  "type": "Feature",
  "properties": {
    "date:inception_lower": "1980-01-01",
    "date:inception_upper": "1980-01-01",
    "iso:country": "GB",
    "wof:name": "BD17 5PU",
    "wof:placetype": "postalcode"
  },
  "geometry": {"coordinates":[-1.767629,53.845909],"type":"Point"}
}
