{
  "type": "Feature",
  "properties": {
    "iso:country":"GB",
    "wof:name":"BD17 5PU",
    "wof:placetype":"postalcode"
},
  "geometry": {"coordinates":[-1.76762952392821,53.84590942923943],"type":"Point"}
}