{
  "type": "Feature",
  "properties": {
    "iso:country":"GB",
    "wof:name":"NG5 5JN",
    "wof:placetype":"postalcode"
},
  "geometry": {"coordinates":[-1.159216510328,52.99742435760706],"type":"Point"}
}