{
  "type": "Feature",
  "properties": {
    "iso:country":"GB",
    "wof:name":"B23 6AN",
    "wof:placetype":"postalcode"
},
  "geometry": {"coordinates":[-1.85485412190247,52.51913259254869],"type":"Point"}
}