{
  "type": "Feature",
  "properties": {
    "iso:country": "GB",
    "wof:name": "B23 6AN",
    "wof:placetype": "postalcode"
  },
  "geometry": {"coordinates":[-1.854854,52.519133],"type":"Point"}
}
