{
  "type": "Feature",
  "properties": {
    "date:inception_lower": "1980-01-01",
    "date:inception_upper": "1980-01-01",
    "iso:country": "GB",
    "wof:name": "UB3 2PG",
    "wof:placetype": "postalcode"
  },
  "geometry": {"coordinates":[-0.438636,51.518101],"type":"Point"}
}
