{
  "type": "Feature",
  "properties": {
    "iso:country":"GB",
    "wof:name":"OX33 1JD",
    "wof:placetype":"postalcode"
},
  "geometry": {"coordinates":[-1.16905262935687,51.73749308071557],"type":"Point"}
}