{
  "type": "Feature",
  "properties": {
    "date:inception_lower": "1980-01-01",
    "date:inception_upper": "1980-01-01",
    "iso:country": "GB",
    "wof:name": "CV9 3PT",
    "wof:placetype": "postalcode"
  },
  "geometry": {"coordinates":[-1.523435,52.653273],"type":"Point"}
}
