{
  "type": "Feature",
  "properties": {
    "iso:country": "GB",
    "wof:name": "CV9 3PT",
    "wof:placetype": "postalcode"
  },
  "geometry": {"coordinates":[-1.523435,52.653273],"type":"Point"}
}
