{
  "type": "Feature",
  "properties": {
    "iso:country":"GB",
    "wof:name":"SK14 4EP",
    "wof:placetype":"postalcode"
},
  "geometry": {"coordinates":[-2.05168306472097,53.4620759855891],"type":"Point"}
}