{
  "type": "Feature",
  "properties": {
    "date:inception_lower": "1980-01-01",
    "date:inception_upper": "1980-01-01",
    "iso:country": "GB",
    "wof:name": "SK14 4EP",
    "wof:placetype": "postalcode"
  },
  "geometry": {"coordinates":[-2.051683,53.462076],"type":"Point"}
}
