{
  "type": "Feature",
  "properties": {
    "iso:country":"GB",
    "wof:name":"SM6 0JQ",
    "wof:placetype":"postalcode"
},
  "geometry": {"coordinates":[-0.1517006242445,51.35952617745954],"type":"Point"}
}