{
  "type": "Feature",
  "properties": {
    "date:inception_lower": "1980-01-01",
    "date:inception_upper": "1980-01-01",
    "iso:country": "GB",
    "wof:name": "BL2 2RF",
    "wof:placetype": "postalcode"
  },
  "geometry": {"coordinates":[-2.40549,53.585906],"type":"Point"}
}
