{
  "type": "Feature",
  "properties": {
    "iso:country":"GB",
    "wof:name":"BL2 2RF",
    "wof:placetype":"postalcode"
},
  "geometry": {"coordinates":[-2.40548971326368,53.58590619252404],"type":"Point"}
}