{
  "type": "Feature",
  "properties": {
    "iso:country":"GB",
    "wof:name":"SY12 0AN",
    "wof:placetype":"postalcode"
},
  "geometry": {"coordinates":[-2.89474523001478,52.90739203694714],"type":"Point"}
}