{
  "type": "Feature",
  "properties": {
    "date:inception_lower": "1980-01-01",
    "date:inception_upper": "1980-01-01",
    "iso:country": "GB",
    "wof:name": "SY12 0AN",
    "wof:placetype": "postalcode"
  },
  "geometry": {"coordinates":[-2.894536,52.907391],"type":"Point"}
}
