{
  "type": "Feature",
  "properties": {
    "iso:country":"GB",
    "wof:name":"LL14 6RH",
    "wof:placetype":"postalcode"
},
  "geometry": {"coordinates":[-3.0516158818547,52.99147238264795],"type":"Point"}
}