{
  "type": "Feature",
  "properties": {
    "iso:country":"GB",
    "wof:name":"KW9 6NN",
    "wof:placetype":"postalcode"
},
  "geometry": {"coordinates":[-3.89867753239557,58.00713509898247],"type":"Point"}
}