{
  "type": "Feature",
  "properties": {
    "iso:country":"GB",
    "wof:name":"SG12 0TT",
    "wof:placetype":"postalcode"
},
  "geometry": {"coordinates":[-0.02739153348753,51.84343666064137],"type":"Point"}
}