{
  "type": "Feature",
  "properties": {
    "iso:country": "GB",
    "wof:name": "SG12 0TT",
    "wof:placetype": "postalcode"
  },
  "geometry": {"coordinates":[-0.027391,51.843437],"type":"Point"}
}
