{
  "type": "Feature",
  "properties": {
    "iso:country":"GB",
    "wof:name":"SA31 1BX",
    "wof:placetype":"postalcode"
},
  "geometry": {"coordinates":[-4.30441615212301,51.85807532546946],"type":"Point"}
}