{
  "type": "Feature",
  "properties": {
    "iso:country": "GB",
    "wof:name": "SA31 1BX",
    "wof:placetype": "postalcode"
  },
  "geometry": {"coordinates":[-4.304325,51.857844],"type":"Point"}
}
