{
  "type": "Feature",
  "properties": {
    "iso:country":"GB",
    "wof:name":"IP22 2DW",
    "wof:placetype":"postalcode"
},
  "geometry": {"coordinates":[1.09552923913966,52.41250312288218],"type":"Point"}
}