{
  "type": "Feature",
  "properties": {
    "iso:country": "GB",
    "wof:name": "IP22 2DW",
    "wof:placetype": "postalcode"
  },
  "geometry": {"coordinates":[1.095529,52.412503],"type":"Point"}
}
