{
  "type": "Feature",
  "properties": {
    "iso:country":"GB",
    "wof:name":"BD10 8WL",
    "wof:placetype":"postalcode"
},
  "geometry": {"coordinates":[-1.74589893621522,53.83767743790872],"type":"Point"}
}