{
  "type": "Feature",
  "properties": {
    "date:inception_lower": "2024-02-01",
    "date:inception_upper": "2024-02-01",
    "iso:country": "GB",
    "wof:name": "CW12 2SJ",
    "wof:placetype": "postalcode"
  },
  "geometry": {"coordinates":[-2.255836,53.185086],"type":"Point"}
}
