{
  "type": "Feature",
  "properties": {
    "iso:country":"GB",
    "wof:name":"AB42 3GZ",
    "wof:placetype":"postalcode"
},
  "geometry": {"coordinates":[-1.80892218777486,57.49328731035613],"type":"Point"}
}