{
  "type": "Feature",
  "properties": {
    "iso:country":"GB",
    "wof:name":"SA44 5UL",
    "wof:placetype":"postalcode"
},
  "geometry": {"coordinates":[-4.39902657778389,52.02393223422543],"type":"Point"}
}