{
  "type": "Feature",
  "properties": {
    "date:inception_lower":"1991-09-01",
    "date:inception_upper":"1991-09-30",
    "iso:country":"GB",
    "wof:name":"SA44 5UL",
    "wof:placetype":"postalcode"
},
  "geometry": {"coordinates":[-4.399027,52.023932],"type":"Point"}
}