{
  "type": "Feature",
  "properties": {
    "iso:country":"GB",
    "wof:name":"SN16 9LT",
    "wof:placetype":"postalcode"
},
  "geometry": {"coordinates":[-2.09454868215278,51.57942059476769],"type":"Point"}
}