{
  "type": "Feature",
  "properties": {
    "date:inception_lower":"1980-01-01",
    "date:inception_upper":"1980-01-31",
    "iso:country":"GB",
    "wof:name":"SN16 9LT",
    "wof:placetype":"postalcode"
},
  "geometry": {"coordinates":[-2.094544,51.579422],"type":"Point"}
}