{
  "type": "Feature",
  "properties": {
    "iso:country": "GB",
    "wof:name": "MK6 3HF",
    "wof:placetype": "postalcode"
  },
  "geometry": {"coordinates":[-0.737125,52.043336],"type":"Point"}
}
