{
  "type": "Feature",
  "properties": {
    "iso:country":"GB",
    "wof:name":"MK6 3HF",
    "wof:placetype":"postalcode"
},
  "geometry": {"coordinates":[-0.73712520419705,52.04333639192775],"type":"Point"}
}