{
  "type": "Feature",
  "properties": {
    "iso:country":"GB",
    "wof:name":"L18 3HP",
    "wof:placetype":"postalcode"
},
  "geometry": {"coordinates":[-2.89746980505298,53.38576140184897],"type":"Point"}
}