{
  "type": "Feature",
  "properties": {
    "date:inception_lower": "1980-01-01",
    "date:inception_upper": "1980-01-01",
    "iso:country": "GB",
    "wof:name": "AL9 6AU",
    "wof:placetype": "postalcode"
  },
  "geometry": {"coordinates":[-0.156455,51.763456],"type":"Point"}
}
