{
  "type": "Feature",
  "properties": {
    "iso:country":"GB",
    "wof:name":"AL9 6AU",
    "wof:placetype":"postalcode"
},
  "geometry": {"coordinates":[-0.15645134066602,51.76344170185597],"type":"Point"}
}