{
  "type": "Feature",
  "properties": {
    "date:inception_lower": "1994-09-01",
    "date:inception_upper": "1994-09-01",
    "iso:country": "GB",
    "wof:name": "AB53 8JF",
    "wof:placetype": "postalcode"
  },
  "geometry": {"coordinates":[-2.340124,57.52398],"type":"Point"}
}
