{
  "type": "Feature",
  "properties": {
    "iso:country":"GB",
    "wof:name":"HP18 0JQ",
    "wof:placetype":"postalcode"
},
  "geometry": {"coordinates":[-0.92504724702471,51.84659460916048],"type":"Point"}
}