{
  "type": "Feature",
  "properties": {
    "iso:country":"GB",
    "wof:name":"OL12 0PT",
    "wof:placetype":"postalcode"
},
  "geometry": {"coordinates":[-2.16014343652006,53.6220531765258],"type":"Point"}
}