{
  "type": "Feature",
  "properties": {
    "iso:country": "GB",
    "wof:name": "OL12 0PT",
    "wof:placetype": "postalcode"
  },
  "geometry": {"coordinates":[-2.160143,53.622053],"type":"Point"}
}
