{
  "type": "Feature",
  "properties": {
    "date:inception_lower":"1980-01-01",
    "date:inception_upper":"1980-01-31",
    "iso:country":"GB",
    "wof:name":"PL27 6LW",
    "wof:placetype":"postalcode"
},
  "geometry": {"coordinates":[-4.913495,50.543513],"type":"Point"}
}