{
  "type": "Feature",
  "properties": {
    "iso:country": "GB",
    "wof:name": "DL12 8SD",
    "wof:placetype": "postalcode"
  },
  "geometry": {"coordinates":[-1.909043,54.598545],"type":"Point"}
}
