{
  "type": "Feature",
  "properties": {
    "iso:country":"GB",
    "wof:name":"DL12 8SD",
    "wof:placetype":"postalcode"
},
  "geometry": {"coordinates":[-1.90660903246584,54.60300063109804],"type":"Point"}
}