{
  "type": "Feature",
  "properties": {
    "iso:country":"GB",
    "wof:name":"W10 5JR",
    "wof:placetype":"postalcode"
},
  "geometry": {"coordinates":[-0.22390195095967,51.52321874281257],"type":"Point"}
}