{
  "type": "Feature",
  "properties": {
    "iso:country":"GB",
    "wof:name":"WN1 3HQ",
    "wof:placetype":"postalcode"
},
  "geometry": {"coordinates":[-2.6087372823255,53.54690630994256],"type":"Point"}
}