{
  "type": "Feature",
  "properties": {
    "iso:country": "GB",
    "wof:name": "WN1 3HQ",
    "wof:placetype": "postalcode"
  },
  "geometry": {"coordinates":[-2.608737,53.546906],"type":"Point"}
}
