{
  "type": "Feature",
  "properties": {
    "iso:country":"GB",
    "wof:name":"CF41 7AS",
    "wof:placetype":"postalcode"
},
  "geometry": {"coordinates":[-3.48832514737332,51.64511030874807],"type":"Point"}
}