{
  "type": "Feature",
  "properties": {
    "date:inception_lower":"1980-01-01",
    "date:inception_upper":"1980-01-31",
    "iso:country":"GB",
    "wof:name":"CF41 7AS",
    "wof:placetype":"postalcode"
},
  "geometry": {"coordinates":[-3.488325,51.64511],"type":"Point"}
}