{
  "type": "Feature",
  "properties": {
    "iso:country":"GB",
    "wof:name":"DN7 4NN",
    "wof:placetype":"postalcode"
},
  "geometry": {"coordinates":[-1.01819556027645,53.57371419249272],"type":"Point"}
}