{
  "type": "Feature",
  "properties": {
    "iso:country": "GB",
    "wof:name": "DL10 4BD",
    "wof:placetype": "postalcode"
  },
  "geometry": {"coordinates":[-1.740708,54.404383],"type":"Point"}
}
