{
  "type": "Feature",
  "properties": {
    "iso:country":"GB",
    "wof:name":"TA2 8EN",
    "wof:placetype":"postalcode"
},
  "geometry": {"coordinates":[-3.08837503877766,51.03268877373019],"type":"Point"}
}