{
  "type": "Feature",
  "properties": {
    "iso:country": "GB",
    "wof:name": "TA2 8EN",
    "wof:placetype": "postalcode"
  },
  "geometry": {"coordinates":[-3.088375,51.032689],"type":"Point"}
}
