{
  "type": "Feature",
  "properties": {
    "iso:country":"GB",
    "wof:name":"PL14 3BJ",
    "wof:placetype":"postalcode"
},
  "geometry": {"coordinates":[-4.45912468333025,50.45477474973656],"type":"Point"}
}