{
  "type": "Feature",
  "properties": {
    "date:inception_lower": "1980-01-01",
    "date:inception_upper": "1980-01-01",
    "iso:country": "GB",
    "wof:name": "CA14 3PE",
    "wof:placetype": "postalcode"
  },
  "geometry": {"coordinates":[-3.545693,54.633088],"type":"Point"}
}
