{
  "type": "Feature",
  "properties": {
    "date:inception_lower": "1980-01-01",
    "date:inception_upper": "1980-01-01",
    "iso:country": "GB",
    "wof:name": "L33 1DZ",
    "wof:placetype": "postalcode"
  },
  "geometry": {"coordinates":[-2.88021,53.498014],"type":"Point"}
}
