{
  "type": "Feature",
  "properties": {
    "iso:country": "GB",
    "wof:name": "WF9 3RZ",
    "wof:placetype": "postalcode"
  },
  "geometry": {"coordinates":[-1.314462,53.597233],"type":"Point"}
}
