{
  "type": "Feature",
  "properties": {
    "iso:country": "GB",
    "wof:name": "CF47 0YR",
    "wof:placetype": "postalcode"
  },
  "geometry": {"coordinates":[-3.372128,51.739069],"type":"Point"}
}
