{
  "type": "Feature",
  "properties": {
    "iso:country":"GB",
    "wof:name":"CF47 0YR",
    "wof:placetype":"postalcode"
},
  "geometry": {"coordinates":[-3.37212833812451,51.7390691401702],"type":"Point"}
}