{
  "type": "Feature",
  "properties": {
    "iso:country":"GB",
    "wof:name":"N16 6BW",
    "wof:placetype":"postalcode"
},
  "geometry": {"coordinates":[-0.07112317460277,51.56396112700613],"type":"Point"}
}