{
  "type": "Feature",
  "properties": {
    "iso:country": "GB",
    "wof:name": "CT20 2RS",
    "wof:placetype": "postalcode"
  },
  "geometry": {"coordinates":[1.16939,51.077563],"type":"Point"}
}
