{
  "type": "Feature",
  "properties": {
    "date:inception_lower": "2005-12-01",
    "date:inception_upper": "2005-12-01",
    "iso:country": "GB",
    "wof:name": "DG16 5QB",
    "wof:placetype": "postalcode"
  },
  "geometry": {"coordinates":[-3.072428,54.997707],"type":"Point"}
}
