{
  "type": "Feature",
  "properties": {
    "iso:country": "GB",
    "wof:name": "DG16 5QB",
    "wof:placetype": "postalcode"
  },
  "geometry": {"coordinates":[-3.072428,54.997707],"type":"Point"}
}
