{
  "type": "Feature",
  "properties": {
    "date:inception_lower": "2017-05-01",
    "date:inception_upper": "2017-05-01",
    "iso:country": "GB",
    "wof:name": "G65 0DN",
    "wof:placetype": "postalcode"
  },
  "geometry": {"coordinates":[-4.031009,55.97662],"type":"Point"}
}
