{
  "type": "Feature",
  "properties": {
    "iso:country":"GB",
    "wof:name":"BS5 8DB",
    "wof:placetype":"postalcode"
},
  "geometry": {"coordinates":[-2.53722912388401,51.45330891167983],"type":"Point"}
}