{
  "type": "Feature",
  "properties": {
    "iso:country": "GB",
    "wof:name": "BS5 8DB",
    "wof:placetype": "postalcode"
  },
  "geometry": {"coordinates":[-2.537229,51.453309],"type":"Point"}
}
