{
  "type": "Feature",
  "properties": {
    "iso:country":"GB",
    "wof:name":"OL14 6JF",
    "wof:placetype":"postalcode"
},
  "geometry": {"coordinates":[-2.07269264626975,53.70683384085719],"type":"Point"}
}