{
  "type": "Feature",
  "properties": {
    "iso:country": "GB",
    "wof:name": "CA11 9QN",
    "wof:placetype": "postalcode"
  },
  "geometry": {"coordinates":[-2.829168,54.75432],"type":"Point"}
}
