{
  "type": "Feature",
  "properties": {
    "iso:country":"GB",
    "wof:name":"CA11 9QN",
    "wof:placetype":"postalcode"
},
  "geometry": {"coordinates":[-2.82931916619774,54.75431131904093],"type":"Point"}
}