{
  "type": "Feature",
  "properties": {
    "iso:country":"GB",
    "wof:name":"B71 3AP",
    "wof:placetype":"postalcode"
},
  "geometry": {"coordinates":[-1.98149548874419,52.54321384868062],"type":"Point"}
}