{
  "type": "Feature",
  "properties": {
    "date:inception_lower": "1980-01-01",
    "date:inception_upper": "1980-01-01",
    "iso:country": "GB",
    "wof:name": "DG6 4DJ",
    "wof:placetype": "postalcode"
  },
  "geometry": {"coordinates":[-4.049724,54.837093],"type":"Point"}
}
