{
  "type": "Feature",
  "properties": {
    "iso:country":"GB",
    "wof:name":"TW9 3HT",
    "wof:placetype":"postalcode"
},
  "geometry": {"coordinates":[-0.28770384368755,51.47859412325968],"type":"Point"}
}