{
  "type": "Feature",
  "properties": {
    "date:inception_lower": "1980-01-01",
    "date:inception_upper": "1980-01-01",
    "iso:country": "GB",
    "wof:name": "LE2 1FZ",
    "wof:placetype": "postalcode"
  },
  "geometry": {"coordinates":[-1.110969,52.626498],"type":"Point"}
}
