{
  "type": "Feature",
  "properties": {
    "iso:country":"GB",
    "wof:name":"HP2 7JP",
    "wof:placetype":"postalcode"
},
  "geometry": {"coordinates":[-0.44271959432247,51.77799544386237],"type":"Point"}
}