{
  "type": "Feature",
  "properties": {
    "date:inception_lower": "1980-01-01",
    "date:inception_upper": "1980-01-01",
    "iso:country": "GB",
    "wof:name": "HP2 7JP",
    "wof:placetype": "postalcode"
  },
  "geometry": {"coordinates":[-0.44272,51.777995],"type":"Point"}
}
