{
  "type": "Feature",
  "properties": {
    "date:inception_lower":"1980-01-01",
    "date:inception_upper":"1980-01-31",
    "iso:country":"GB",
    "wof:name":"CV8 1EQ",
    "wof:placetype":"postalcode"
},
  "geometry": {"coordinates":[-1.581051,52.342167],"type":"Point"}
}