{
  "type": "Feature",
  "properties": {
    "iso:country":"GB",
    "wof:name":"CV8 1EQ",
    "wof:placetype":"postalcode"
},
  "geometry": {"coordinates":[-1.58105138234633,52.3421669904407],"type":"Point"}
}