{
  "type": "Feature",
  "properties": {
    "iso:country":"GB",
    "wof:name":"SS2 4QB",
    "wof:placetype":"postalcode"
},
  "geometry": {"coordinates":[0.73416513152899,51.55050906293256],"type":"Point"}
}