{
  "type": "Feature",
  "properties": {
    "iso:country": "GB",
    "wof:name": "NE15 6AG",
    "wof:placetype": "postalcode"
  },
  "geometry": {"coordinates":[-1.67362,54.974307],"type":"Point"}
}
