{
  "type": "Feature",
  "properties": {
    "iso:country":"GB",
    "wof:name":"NE15 6AG",
    "wof:placetype":"postalcode"
},
  "geometry": {"coordinates":[-1.67362036379071,54.97430657546927],"type":"Point"}
}