{
  "type": "Feature",
  "properties": {
    "date:inception_lower":"1980-01-01",
    "date:inception_upper":"1980-01-31",
    "iso:country":"GB",
    "wof:name":"KA26 9BQ",
    "wof:placetype":"postalcode"
},
  "geometry": {"coordinates":[-4.85585,55.238333],"type":"Point"}
}