{
  "type": "Feature",
  "properties": {
    "iso:country":"GB",
    "wof:name":"KA26 9BQ",
    "wof:placetype":"postalcode"
},
  "geometry": {"coordinates":[-4.855849709721,55.23833325341214],"type":"Point"}
}