{
  "type": "Feature",
  "properties": {
    "iso:country": "GB",
    "wof:name": "KA26 9BQ",
    "wof:placetype": "postalcode"
  },
  "geometry": {"coordinates":[-4.85585,55.238333],"type":"Point"}
}
