{
  "type": "Feature",
  "properties": {
    "iso:country":"GB",
    "wof:name":"SP10 5EN",
    "wof:placetype":"postalcode"
},
  "geometry": {"coordinates":[-1.46722786634163,51.21854672948298],"type":"Point"}
}