{
  "type": "Feature",
  "properties": {
    "iso:country":"GB",
    "wof:name":"OL7 9QG",
    "wof:placetype":"postalcode"
},
  "geometry": {"coordinates":[-2.0994399419893,53.49905108420128],"type":"Point"}
}