{
  "type": "Feature",
  "properties": {
    "iso:country": "GB",
    "wof:name": "OL7 9QG",
    "wof:placetype": "postalcode"
  },
  "geometry": {"coordinates":[-2.099455,53.499051],"type":"Point"}
}
