{
  "type": "Feature",
  "properties": {
    "date:inception_lower":"2016-11-01",
    "date:inception_upper":"2016-11-30",
    "iso:country":"GB",
    "wof:name":"SA1 2ET",
    "wof:placetype":"postalcode"
},
  "geometry": {"coordinates":[-3.935423,51.633604],"type":"Point"}
}