{
  "type": "Feature",
  "properties": {
    "iso:country": "GB",
    "wof:name": "WR6 5SL",
    "wof:placetype": "postalcode"
  },
  "geometry": {"coordinates":[-2.415372,52.208324],"type":"Point"}
}
