{
  "type": "Feature",
  "properties": {
    "iso:country":"GB",
    "wof:name":"MK40 1RA",
    "wof:placetype":"postalcode"
},
  "geometry": {"coordinates":[-0.46843511726886,52.13546782132575],"type":"Point"}
}