{
  "type": "Feature",
  "properties": {
    "iso:country":"GB",
    "wof:name":"DE5 3EG",
    "wof:placetype":"postalcode"
},
  "geometry": {"coordinates":[-1.40239162613783,53.04958503329149],"type":"Point"}
}