{
  "type": "Feature",
  "properties": {
    "iso:country":"GB",
    "wof:name":"CO15 3SA",
    "wof:placetype":"postalcode"
},
  "geometry": {"coordinates":[1.15409814594524,51.80219463022921],"type":"Point"}
}