{
  "type": "Feature",
  "properties": {
    "iso:country":"GB",
    "wof:name":"PH33 6HL",
    "wof:placetype":"postalcode"
},
  "geometry": {"coordinates":[-5.10200432055779,56.81776814608671],"type":"Point"}
}