{
  "type": "Feature",
  "properties": {
    "iso:country": "GB",
    "wof:name": "PH33 6HL",
    "wof:placetype": "postalcode"
  },
  "geometry": {"coordinates":[-5.102004,56.817768],"type":"Point"}
}
