{
  "type": "Feature",
  "properties": {
    "date:inception_lower": "1997-06-01",
    "date:inception_upper": "1997-06-01",
    "iso:country": "GB",
    "wof:name": "EH47 7BX",
    "wof:placetype": "postalcode"
  },
  "geometry": {"coordinates":[-3.588158,55.879788],"type":"Point"}
}
