{
  "type": "Feature",
  "properties": {
    "iso:country": "GB",
    "wof:name": "NG16 1QW",
    "wof:placetype": "postalcode"
  },
  "geometry": {"coordinates":[-1.229429,52.982142],"type":"Point"}
}
