{
  "type": "Feature",
  "properties": {
    "iso:country":"GB",
    "wof:name":"NG16 1QW",
    "wof:placetype":"postalcode"
},
  "geometry": {"coordinates":[-1.2294286237795,52.98214150663793],"type":"Point"}
}