{
  "type": "Feature",
  "properties": {
    "iso:country": "GB",
    "wof:name": "EX4 4JQ",
    "wof:placetype": "postalcode"
  },
  "geometry": {"coordinates":[-3.540586,50.738545],"type":"Point"}
}
