{
  "type": "Feature",
  "properties": {
    "iso:country":"GB",
    "wof:name":"EX4 4JQ",
    "wof:placetype":"postalcode"
},
  "geometry": {"coordinates":[-3.54058642731042,50.73854498796619],"type":"Point"}
}