{
  "type": "Feature",
  "properties": {
    "iso:country":"GB",
    "wof:name":"LU2 9DA",
    "wof:placetype":"postalcode"
},
  "geometry": {"coordinates":[-0.39101843456159,51.89634138775708],"type":"Point"}
}