{
  "type": "Feature",
  "properties": {
    "iso:country": "GB",
    "wof:name": "BL3 6UQ",
    "wof:placetype": "postalcode"
  },
  "geometry": {"coordinates":[-2.444646,53.564492],"type":"Point"}
}
