{
  "type": "Feature",
  "properties": {
    "date:inception_lower": "1980-01-01",
    "date:inception_upper": "1980-01-01",
    "iso:country": "GB",
    "wof:name": "WF12 7DF",
    "wof:placetype": "postalcode"
  },
  "geometry": {"coordinates":[-1.623464,53.691686],"type":"Point"}
}
