{
  "type": "Feature",
  "properties": {
    "iso:country": "GB",
    "wof:name": "WF12 7DF",
    "wof:placetype": "postalcode"
  },
  "geometry": {"coordinates":[-1.623464,53.691686],"type":"Point"}
}
