{
  "type": "Feature",
  "properties": {
    "iso:country":"GB",
    "wof:name":"HP13 7BF",
    "wof:placetype":"postalcode"
},
  "geometry": {"coordinates":[-0.72921715560939,51.62480638439289],"type":"Point"}
}