{
  "type": "Feature",
  "properties": {
    "date:inception_lower": "2019-11-01",
    "date:inception_upper": "2019-11-01",
    "iso:country": "GB",
    "wof:name": "TD11 3FA",
    "wof:placetype": "postalcode"
  },
  "geometry": {"coordinates":[-2.344477,55.770894],"type":"Point"}
}
