{
  "type": "Feature",
  "properties": {
    "iso:country":"GB",
    "wof:name":"DH3 1AD",
    "wof:placetype":"postalcode"
},
  "geometry": {"coordinates":[-1.57524714408504,54.89569612173941],"type":"Point"}
}