{
  "type": "Feature",
  "properties": {
    "iso:country": "GB",
    "wof:name": "MK8 1ED",
    "wof:placetype": "postalcode"
  },
  "geometry": {"coordinates":[-0.812997,52.031889],"type":"Point"}
}
