{
  "type": "Feature",
  "properties": {
    "date:inception_lower": "1980-01-01",
    "date:inception_upper": "1980-01-01",
    "iso:country": "GB",
    "wof:name": "LA1 4EQ",
    "wof:placetype": "postalcode"
  },
  "geometry": {"coordinates":[-2.793701,54.032183],"type":"Point"}
}
