{
  "type": "Feature",
  "properties": {
    "iso:country":"GB",
    "wof:name":"SO51 8NA",
    "wof:placetype":"postalcode"
},
  "geometry": {"coordinates":[-1.4994488531598,50.98918230493365],"type":"Point"}
}