{
  "type": "Feature",
  "properties": {
    "iso:country":"GB",
    "wof:name":"S36 2RP",
    "wof:placetype":"postalcode"
},
  "geometry": {"coordinates":[-1.56820257872984,53.47835030009281],"type":"Point"}
}