{
  "type": "Feature",
  "properties": {
    "date:inception_lower": "1997-06-01",
    "date:inception_upper": "1997-06-01",
    "iso:country": "GB",
    "wof:name": "S36 2RP",
    "wof:placetype": "postalcode"
  },
  "geometry": {"coordinates":[-1.568023,53.478322],"type":"Point"}
}
