{
  "type": "Feature",
  "properties": {
    "iso:country":"GB",
    "wof:name":"TR8 4HZ",
    "wof:placetype":"postalcode"
},
  "geometry": {"coordinates":[-4.96158201879045,50.42936307874753],"type":"Point"}
}