{
  "type": "Feature",
  "properties": {
    "date:inception_lower": "1980-01-01",
    "date:inception_upper": "1980-01-01",
    "iso:country": "GB",
    "wof:name": "BB7 4AL",
    "wof:placetype": "postalcode"
  },
  "geometry": {"coordinates":[-2.35786,53.894305],"type":"Point"}
}
