{
  "type": "Feature",
  "properties": {
    "iso:country":"GB",
    "wof:name":"BB7 4AL",
    "wof:placetype":"postalcode"
},
  "geometry": {"coordinates":[-2.35786021087179,53.89430494499354],"type":"Point"}
}