{
  "type": "Feature",
  "properties": {
    "iso:country":"GB",
    "wof:name":"TN6 2ER",
    "wof:placetype":"postalcode"
},
  "geometry": {"coordinates":[0.1893933990783,51.04964561470159],"type":"Point"}
}