{
  "type": "Feature",
  "properties": {
    "iso:country":"GB",
    "wof:name":"PR3 0ZA",
    "wof:placetype":"postalcode"
},
  "geometry": {"coordinates":[-2.86791256612796,53.85517218122659],"type":"Point"}
}