{
  "type": "Feature",
  "properties": {
    "iso:country": "GB",
    "wof:name": "PR3 0ZA",
    "wof:placetype": "postalcode"
  },
  "geometry": {"coordinates":[-2.867913,53.855172],"type":"Point"}
}
