{
  "type": "Feature",
  "properties": {
    "iso:country": "GB",
    "wof:name": "DD6 9PB",
    "wof:placetype": "postalcode"
  },
  "geometry": {"coordinates":[-2.885699,56.435813],"type":"Point"}
}
