{
  "type": "Feature",
  "properties": {
    "iso:country":"GB",
    "wof:name":"DD6 9PB",
    "wof:placetype":"postalcode"
},
  "geometry": {"coordinates":[-2.88569901239017,56.43581307245294],"type":"Point"}
}