{
  "type": "Feature",
  "properties": {
    "date:inception_lower": "2020-10-01",
    "date:inception_upper": "2020-10-01",
    "iso:country": "GB",
    "wof:name": "BB7 2RW",
    "wof:placetype": "postalcode"
  },
  "geometry": {"coordinates":[-2.398316,53.876072],"type":"Point"}
}
