{
  "type": "Feature",
  "properties": {
    "date:inception_lower":"1980-01-01",
    "date:inception_upper":"1980-01-31",
    "iso:country":"GB",
    "wof:name":"SR5 1AH",
    "wof:placetype":"postalcode"
},
  "geometry": {"coordinates":[-1.383344,54.9137],"type":"Point"}
}