{
  "type": "Feature",
  "properties": {
    "iso:country": "GB",
    "wof:name": "SR5 1AH",
    "wof:placetype": "postalcode"
  },
  "geometry": {"coordinates":[-1.383344,54.9137],"type":"Point"}
}
