{
  "type": "Feature",
  "properties": {
    "iso:country":"GB",
    "wof:name":"CV6 4EQ",
    "wof:placetype":"postalcode"
},
  "geometry": {"coordinates":[-1.51971710715988,52.44043009075134],"type":"Point"}
}