{
  "type": "Feature",
  "properties": {
    "date:inception_lower": "1980-01-01",
    "date:inception_upper": "1980-01-01",
    "iso:country": "GB",
    "wof:name": "CV6 4EQ",
    "wof:placetype": "postalcode"
  },
  "geometry": {"coordinates":[-1.519717,52.44043],"type":"Point"}
}
