{
  "type": "Feature",
  "properties": {
    "iso:country": "GB",
    "wof:name": "CV6 4EQ",
    "wof:placetype": "postalcode"
  },
  "geometry": {"coordinates":[-1.519717,52.44043],"type":"Point"}
}
