{
  "type": "Feature",
  "properties": {
    "iso:country": "GB",
    "wof:name": "E11 4QH",
    "wof:placetype": "postalcode"
  },
  "geometry": {"coordinates":[0.00688,51.559499],"type":"Point"}
}
