{
  "type": "Feature",
  "properties": {
    "iso:country":"GB",
    "wof:name":"E11 4QH",
    "wof:placetype":"postalcode"
},
  "geometry": {"coordinates":[0.00686671909069,51.55948767993978],"type":"Point"}
}