{
  "type": "Feature",
  "properties": {
    "date:inception_lower": "1980-01-01",
    "date:inception_upper": "1980-01-01",
    "iso:country": "GB",
    "wof:name": "CO2 8RA",
    "wof:placetype": "postalcode"
  },
  "geometry": {"coordinates":[0.907811,51.863445],"type":"Point"}
}
