{
  "type": "Feature",
  "properties": {
    "date:inception_lower": "2019-11-01",
    "date:inception_upper": "2019-11-01",
    "iso:country": "GB",
    "wof:name": "AL2 3FX",
    "wof:placetype": "postalcode"
  },
  "geometry": {"coordinates":[-0.350459,51.704456],"type":"Point"}
}
