{
  "type": "Feature",
  "properties": {
    "date:inception_lower": "2016-06-01",
    "date:inception_upper": "2016-06-01",
    "iso:country": "GB",
    "wof:name": "RG40 1JT",
    "wof:placetype": "postalcode"
  },
  "geometry": {"coordinates":[-0.81068,51.408875],"type":"Point"}
}
