{
  "type": "Feature",
  "properties": {
    "date:inception_lower": "2023-10-01",
    "date:inception_upper": "2023-10-01",
    "iso:country": "GB",
    "wof:name": "LA1 4AW",
    "wof:placetype": "postalcode"
  },
  "geometry": {"coordinates":[-2.786881,54.009177],"type":"Point"}
}
