{
  "type": "Feature",
  "properties": {
    "iso:country":"GB",
    "wof:name":"GU15 2HH",
    "wof:placetype":"postalcode"
},
  "geometry": {"coordinates":[-0.73635149394695,51.33617780954241],"type":"Point"}
}