{
  "type": "Feature",
  "properties": {
    "date:inception_lower": "1995-12-01",
    "date:inception_upper": "1995-12-01",
    "iso:country": "GB",
    "wof:name": "BB4 4AX",
    "wof:placetype": "postalcode"
  },
  "geometry": {"coordinates":[-2.334159,53.681348],"type":"Point"}
}
