{
  "type": "Feature",
  "properties": {
    "iso:country":"GB",
    "wof:name":"BB4 4AX",
    "wof:placetype":"postalcode"
},
  "geometry": {"coordinates":[-2.3341589056778,53.68134832334894],"type":"Point"}
}