{
  "type": "Feature",
  "properties": {
    "iso:country":"GB",
    "wof:name":"S43 1QL",
    "wof:placetype":"postalcode"
},
  "geometry": {"coordinates":[-1.39108579636186,53.24403350948793],"type":"Point"}
}