{
  "type": "Feature",
  "properties": {
    "iso:country":"GB",
    "wof:name":"SN11 0QF",
    "wof:placetype":"postalcode"
},
  "geometry": {"coordinates":[-1.99908806964853,51.42973315017613],"type":"Point"}
}