{
  "type": "Feature",
  "properties": {
    "iso:country": "GB",
    "wof:name": "SN11 0QF",
    "wof:placetype": "postalcode"
  },
  "geometry": {"coordinates":[-1.999088,51.429733],"type":"Point"}
}
