{
  "type": "Feature",
  "properties": {
    "iso:country":"GB",
    "wof:name":"PR4 2AP",
    "wof:placetype":"postalcode"
},
  "geometry": {"coordinates":[-2.87388604393163,53.78212633070938],"type":"Point"}
}