{
  "type": "Feature",
  "properties": {
    "iso:country":"GB",
    "wof:name":"B45 9HW",
    "wof:placetype":"postalcode"
},
  "geometry": {"coordinates":[-2.02473142328318,52.39238777571078],"type":"Point"}
}