{
  "type": "Feature",
  "properties": {
    "iso:country": "GB",
    "wof:name": "B45 9HW",
    "wof:placetype": "postalcode"
  },
  "geometry": {"coordinates":[-2.024731,52.392388],"type":"Point"}
}
