{
  "type": "Feature",
  "properties": {
    "iso:country": "GB",
    "wof:name": "LS12 6NA",
    "wof:placetype": "postalcode"
  },
  "geometry": {"coordinates":[-1.596426,53.769984],"type":"Point"}
}
