{
  "type": "Feature",
  "properties": {
    "date:inception_lower":"2006-02-01",
    "date:inception_upper":"2006-02-28",
    "iso:country":"GB",
    "wof:name":"LS12 6NA",
    "wof:placetype":"postalcode"
},
  "geometry": {"coordinates":[-1.596426,53.769984],"type":"Point"}
}