{
  "type": "Feature",
  "properties": {
    "date:inception_lower": "2006-02-01",
    "date:inception_upper": "2006-02-01",
    "iso:country": "GB",
    "wof:name": "LS12 6NA",
    "wof:placetype": "postalcode"
  },
  "geometry": {"coordinates":[-1.59518,53.770607],"type":"Point"}
}
