{
  "type": "Feature",
  "properties": {
    "iso:country":"GB",
    "wof:name":"CH8 7BQ",
    "wof:placetype":"postalcode"
},
  "geometry": {"coordinates":[-3.21211337258886,53.27706947011695],"type":"Point"}
}