{
  "type": "Feature",
  "properties": {
    "iso:country": "GB",
    "wof:name": "LE3 1AA",
    "wof:placetype": "postalcode"
  },
  "geometry": {"coordinates":[-1.159386,52.624793],"type":"Point"}
}
