{
  "type": "Feature",
  "properties": {
    "date:inception_lower": "2013-12-01",
    "date:inception_upper": "2013-12-01",
    "iso:country": "GB",
    "wof:name": "CH3 8DP",
    "wof:placetype": "postalcode"
  },
  "geometry": {"coordinates":[-2.759943,53.190559],"type":"Point"}
}
