{
  "type": "Feature",
  "properties": {
    "iso:country": "GB",
    "wof:name": "CH3 8DP",
    "wof:placetype": "postalcode"
  },
  "geometry": {"coordinates":[-2.759943,53.190559],"type":"Point"}
}
