{
  "type": "Feature",
  "properties": {
    "iso:country":"GB",
    "wof:name":"CH3 8DP",
    "wof:placetype":"postalcode"
},
  "geometry": {"coordinates":[-2.7599430998238,53.19055942363087],"type":"Point"}
}