{
  "type": "Feature",
  "properties": {
    "iso:country":"GB",
    "wof:name":"CT21 6BX",
    "wof:placetype":"postalcode"
},
  "geometry": {"coordinates":[1.08243413747013,51.06538169480559],"type":"Point"}
}