{
  "type": "Feature",
  "properties": {
    "iso:country": "GB",
    "wof:name": "TW13 4JS",
    "wof:placetype": "postalcode"
  },
  "geometry": {"coordinates":[-0.417943,51.4395],"type":"Point"}
}
