{
  "type": "Feature",
  "properties": {
    "iso:country": "GB",
    "wof:name": "CB8 9YA",
    "wof:placetype": "postalcode"
  },
  "geometry": {"coordinates":[0.516785,52.139604],"type":"Point"}
}
