{
  "type": "Feature",
  "properties": {
    "iso:country":"GB",
    "wof:name":"CB8 9YA",
    "wof:placetype":"postalcode"
},
  "geometry": {"coordinates":[0.51678462561673,52.13960416854518],"type":"Point"}
}