{
  "type": "Feature",
  "properties": {
    "date:inception_lower": "1980-01-01",
    "date:inception_upper": "1980-01-01",
    "iso:country": "GB",
    "wof:name": "M12 4QL",
    "wof:placetype": "postalcode"
  },
  "geometry": {"coordinates":[-2.192542,53.449222],"type":"Point"}
}
