{
  "type": "Feature",
  "properties": {
    "iso:country":"GB",
    "wof:name":"M12 4QL",
    "wof:placetype":"postalcode"
},
  "geometry": {"coordinates":[-2.19254201834536,53.44922200835734],"type":"Point"}
}