{
  "type": "Feature",
  "properties": {
    "iso:country": "GB",
    "wof:name": "SN16 9BX",
    "wof:placetype": "postalcode"
  },
  "geometry": {"coordinates":[-2.096676,51.582161],"type":"Point"}
}
