{
  "type": "Feature",
  "properties": {
    "iso:country":"GB",
    "wof:name":"SN16 9BX",
    "wof:placetype":"postalcode"
},
  "geometry": {"coordinates":[-2.09667590769883,51.58216121650455],"type":"Point"}
}