{
  "type": "Feature",
  "properties": {
    "iso:country":"GB",
    "wof:name":"BA2 2QU",
    "wof:placetype":"postalcode"
},
  "geometry": {"coordinates":[-2.38842996030375,51.36286512304475],"type":"Point"}
}