{
  "type": "Feature",
  "properties": {
    "iso:country":"GB",
    "wof:name":"GU35 9NS",
    "wof:placetype":"postalcode"
},
  "geometry": {"coordinates":[-0.88747752443263,51.14643673969799],"type":"Point"}
}