{
  "type": "Feature",
  "properties": {
    "date:inception_lower":"1980-01-01",
    "date:inception_upper":"1980-01-31",
    "iso:country":"GB",
    "wof:name":"GU35 9NS",
    "wof:placetype":"postalcode"
},
  "geometry": {"coordinates":[-0.887477,51.146437],"type":"Point"}
}