{
  "type": "Feature",
  "properties": {
    "iso:country": "GB",
    "wof:name": "GU35 9NS",
    "wof:placetype": "postalcode"
  },
  "geometry": {"coordinates":[-0.887477,51.146437],"type":"Point"}
}
