{
  "type": "Feature",
  "properties": {
    "iso:country":"GB",
    "wof:name":"SG18 9EF",
    "wof:placetype":"postalcode"
},
  "geometry": {"coordinates":[-0.32384505325619,52.09751754909533],"type":"Point"}
}