{
  "type": "Feature",
  "properties": {
    "iso:country":"GB",
    "wof:name":"GL51 6RH",
    "wof:placetype":"postalcode"
},
  "geometry": {"coordinates":[-2.14063473752818,51.88903710701001],"type":"Point"}
}