{
  "type": "Feature",
  "properties": {
    "iso:country":"GB",
    "wof:name":"SO40 7LA",
    "wof:placetype":"postalcode"
},
  "geometry": {"coordinates":[-1.5460756883721,50.91515864743408],"type":"Point"}
}