{
  "type": "Feature",
  "properties": {
    "date:inception_lower": "1994-12-01",
    "date:inception_upper": "1994-12-01",
    "iso:country": "GB",
    "wof:name": "SO40 7LA",
    "wof:placetype": "postalcode"
  },
  "geometry": {"coordinates":[-1.54648,50.915144],"type":"Point"}
}
