{
  "type": "Feature",
  "properties": {
    "date:inception_lower":"1994-12-01",
    "date:inception_upper":"1994-12-31",
    "iso:country":"GB",
    "wof:name":"SO40 7LA",
    "wof:placetype":"postalcode"
},
  "geometry": {"coordinates":[-1.546076,50.915159],"type":"Point"}
}