{
  "type": "Feature",
  "properties": {
    "iso:country":"GB",
    "wof:name":"G46 7BU",
    "wof:placetype":"postalcode"
},
  "geometry": {"coordinates":[-4.31022922675507,55.80474454659482],"type":"Point"}
}