{
  "type": "Feature",
  "properties": {
    "iso:country":"GB",
    "wof:name":"PO16 0AF",
    "wof:placetype":"postalcode"
},
  "geometry": {"coordinates":[-1.18474614809138,50.84424932373321],"type":"Point"}
}