{
  "type": "Feature",
  "properties": {
    "date:inception_lower": "1980-01-01",
    "date:inception_upper": "1980-01-01",
    "iso:country": "GB",
    "wof:name": "TN19 7HE",
    "wof:placetype": "postalcode"
  },
  "geometry": {"coordinates":[0.380568,50.996063],"type":"Point"}
}
