{
  "type": "Feature",
  "properties": {
    "iso:country": "GB",
    "wof:name": "LL30 3DX",
    "wof:placetype": "postalcode"
  },
  "geometry": {"coordinates":[-3.783887,53.315302],"type":"Point"}
}
