{
  "type": "Feature",
  "properties": {
    "iso:country":"GB",
    "wof:name":"LL30 3DX",
    "wof:placetype":"postalcode"
},
  "geometry": {"coordinates":[-3.78388676191496,53.31530158181659],"type":"Point"}
}