{
  "type": "Feature",
  "properties": {
    "date:inception_lower": "2018-04-01",
    "date:inception_upper": "2018-04-01",
    "iso:country": "GB",
    "wof:name": "CW7 2XR",
    "wof:placetype": "postalcode"
  },
  "geometry": {"coordinates":[-2.556901,53.194942],"type":"Point"}
}
