{
  "type": "Feature",
  "properties": {
    "iso:country": "GB",
    "wof:name": "SE22 9BJ",
    "wof:placetype": "postalcode"
  },
  "geometry": {"coordinates":[-0.067745,51.461211],"type":"Point"}
}
