{
  "type": "Feature",
  "properties": {
    "iso:country": "GB",
    "wof:name": "E14 9FE",
    "wof:placetype": "postalcode"
  },
  "geometry": {"coordinates":[-0.012639,51.500558],"type":"Point"}
}
