{
  "type": "Feature",
  "properties": {
    "date:inception_lower": "2022-07-01",
    "date:inception_upper": "2022-07-01",
    "iso:country": "GB",
    "wof:name": "B47 6AZ",
    "wof:placetype": "postalcode"
  },
  "geometry": {"coordinates":[-1.866613,52.380562],"type":"Point"}
}
