{
  "type": "Feature",
  "properties": {
    "iso:country":"GB",
    "wof:name":"PL14 3SY",
    "wof:placetype":"postalcode"
},
  "geometry": {"coordinates":[-4.45301902897543,50.45930206859235],"type":"Point"}
}