{
  "type": "Feature",
  "properties": {
    "iso:country": "GB",
    "wof:name": "PL14 3SY",
    "wof:placetype": "postalcode"
  },
  "geometry": {"coordinates":[-4.453019,50.459302],"type":"Point"}
}
