{
  "type": "Feature",
  "properties": {
    "iso:country":"GB",
    "wof:name":"G52 3LB",
    "wof:placetype":"postalcode"
},
  "geometry": {"coordinates":[-4.35819446866099,55.84239104781204],"type":"Point"}
}