{
  "type": "Feature",
  "properties": {
    "iso:country":"GB",
    "wof:name":"NE5 5QF",
    "wof:placetype":"postalcode"
},
  "geometry": {"coordinates":[-1.7002562187265,55.00162127359006],"type":"Point"}
}