{
  "type": "Feature",
  "properties": {
    "iso:country": "GB",
    "wof:name": "NE5 5QF",
    "wof:placetype": "postalcode"
  },
  "geometry": {"coordinates":[-1.700256,55.001621],"type":"Point"}
}
