{
  "type": "Feature",
  "properties": {
    "iso:country":"GB",
    "wof:name":"HD5 0PP",
    "wof:placetype":"postalcode"
},
  "geometry": {"coordinates":[-1.7333121882646,53.66818941401028],"type":"Point"}
}