{
  "type": "Feature",
  "properties": {
    "iso:country":"GB",
    "wof:name":"BN3 5LX",
    "wof:placetype":"postalcode"
},
  "geometry": {"coordinates":[-0.19304177227924,50.83483451969686],"type":"Point"}
}