{
  "type": "Feature",
  "properties": {
    "date:inception_lower":"1980-01-01",
    "date:inception_upper":"1980-01-31",
    "iso:country":"GB",
    "wof:name":"LE16 7UH",
    "wof:placetype":"postalcode"
},
  "geometry": {"coordinates":[-0.88027,52.537526],"type":"Point"}
}