{
  "type": "Feature",
  "properties": {
    "iso:country": "GB",
    "wof:name": "LE16 7UH",
    "wof:placetype": "postalcode"
  },
  "geometry": {"coordinates":[-0.88027,52.537526],"type":"Point"}
}
