{
  "type": "Feature",
  "properties": {
    "iso:country":"GB",
    "wof:name":"DE75 7AJ",
    "wof:placetype":"postalcode"
},
  "geometry": {"coordinates":[-1.34761377567684,53.01498532972642],"type":"Point"}
}