{
  "type": "Feature",
  "properties": {
    "iso:country": "GB",
    "wof:name": "DE75 7AJ",
    "wof:placetype": "postalcode"
  },
  "geometry": {"coordinates":[-1.347821,53.014862],"type":"Point"}
}
