{
  "type": "Feature",
  "properties": {
    "iso:country": "GB",
    "wof:name": "CB10 2DZ",
    "wof:placetype": "postalcode"
  },
  "geometry": {"coordinates":[0.242249,52.026367],"type":"Point"}
}
