{
  "type": "Feature",
  "properties": {
    "iso:country":"GB",
    "wof:name":"CB10 2DZ",
    "wof:placetype":"postalcode"
},
  "geometry": {"coordinates":[0.24224851629778,52.0263667428663],"type":"Point"}
}