{
  "type": "Feature",
  "properties": {
    "iso:country":"GB",
    "wof:name":"WV13 3EJ",
    "wof:placetype":"postalcode"
},
  "geometry": {"coordinates":[-2.06463798679031,52.57918377388896],"type":"Point"}
}