{
  "type": "Feature",
  "properties": {
    "date:inception_lower": "1998-12-01",
    "date:inception_upper": "1998-12-01",
    "iso:country": "GB",
    "wof:name": "TR3 6JU",
    "wof:placetype": "postalcode"
  },
  "geometry": {"coordinates":[-5.087687,50.22349],"type":"Point"}
}
