{
  "type": "Feature",
  "properties": {
    "iso:country":"GB",
    "wof:name":"ML8 4DU",
    "wof:placetype":"postalcode"
},
  "geometry": {"coordinates":[-3.8265890215901,55.73281086411419],"type":"Point"}
}