{
  "type": "Feature",
  "properties": {
    "iso:country":"GB",
    "wof:name":"W1J 5JW",
    "wof:placetype":"postalcode"
},
  "geometry": {"coordinates":[-0.14824283542094,51.50850605155153],"type":"Point"}
}