{
  "type": "Feature",
  "properties": {
    "date:inception_lower": "1980-01-01",
    "date:inception_upper": "1980-01-01",
    "iso:country": "GB",
    "wof:name": "DA15 9AT",
    "wof:placetype": "postalcode"
  },
  "geometry": {"coordinates":[0.11781,51.43608],"type":"Point"}
}
