{
  "type": "Feature",
  "properties": {
    "iso:country":"GB",
    "wof:name":"DA1 2NJ",
    "wof:placetype":"postalcode"
},
  "geometry": {"coordinates":[0.20036918309794,51.44445145798936],"type":"Point"}
}