{
  "type": "Feature",
  "properties": {
    "iso:country":"GB",
    "wof:name":"DN14 5BF",
    "wof:placetype":"postalcode"
},
  "geometry": {"coordinates":[-0.87077595652113,53.7048624222089],"type":"Point"}
}