{
  "type": "Feature",
  "properties": {
    "iso:country":"GB",
    "wof:name":"NW2 5BB",
    "wof:placetype":"postalcode"
},
  "geometry": {"coordinates":[-0.22902404169429,51.54835793751467],"type":"Point"}
}