{
  "type": "Feature",
  "properties": {
    "iso:country": "GB",
    "wof:name": "NW2 5BB",
    "wof:placetype": "postalcode"
  },
  "geometry": {"coordinates":[-0.229024,51.548358],"type":"Point"}
}
