{
  "type": "Feature",
  "properties": {
    "iso:country":"GB",
    "wof:name":"N19 3UX",
    "wof:placetype":"postalcode"
},
  "geometry": {"coordinates":[-0.13020524827049,51.57067266376448],"type":"Point"}
}