{
  "type": "Feature",
  "properties": {
    "date:inception_lower": "1980-01-01",
    "date:inception_upper": "1980-01-01",
    "iso:country": "GB",
    "wof:name": "HD5 9SZ",
    "wof:placetype": "postalcode"
  },
  "geometry": {"coordinates":[-1.74099,53.655146],"type":"Point"}
}
