{
  "type": "Feature",
  "properties": {
    "iso:country":"GB",
    "wof:name":"HD5 9SZ",
    "wof:placetype":"postalcode"
},
  "geometry": {"coordinates":[-1.74098991973424,53.65514641081343],"type":"Point"}
}