{
  "type": "Feature",
  "properties": {
    "date:inception_lower": "1980-01-01",
    "date:inception_upper": "1980-01-01",
    "iso:country": "GB",
    "wof:name": "BD17 6HP",
    "wof:placetype": "postalcode"
  },
  "geometry": {"coordinates":[-1.753288,53.847364],"type":"Point"}
}
