{
  "type": "Feature",
  "properties": {
    "iso:country":"GB",
    "wof:name":"BD17 6HP",
    "wof:placetype":"postalcode"
},
  "geometry": {"coordinates":[-1.75328818413849,53.84736383704666],"type":"Point"}
}