{
  "type": "Feature",
  "properties": {
    "iso:country": "GB",
    "wof:name": "BB3 2SR",
    "wof:placetype": "postalcode"
  },
  "geometry": {"coordinates":[-2.463688,53.683397],"type":"Point"}
}
