{
  "type": "Feature",
  "properties": {
    "iso:country":"GB",
    "wof:name":"PR7 4DT",
    "wof:placetype":"postalcode"
},
  "geometry": {"coordinates":[-2.61793253544494,53.60206617294463],"type":"Point"}
}