{
  "type": "Feature",
  "properties": {
    "date:inception_lower": "2006-11-01",
    "date:inception_upper": "2006-11-01",
    "iso:country": "GB",
    "wof:name": "CV21 3QR",
    "wof:placetype": "postalcode"
  },
  "geometry": {"coordinates":[-1.246123,52.370344],"type":"Point"}
}
