{
  "type": "Feature",
  "properties": {
    "date:inception_lower": "1980-01-01",
    "date:inception_upper": "1980-01-01",
    "iso:country": "GB",
    "wof:name": "BN25 2RR",
    "wof:placetype": "postalcode"
  },
  "geometry": {"coordinates":[0.086055,50.78029],"type":"Point"}
}
