{
  "type": "Feature",
  "properties": {
    "iso:country":"GB",
    "wof:name":"S63 9LY",
    "wof:placetype":"postalcode"
},
  "geometry": {"coordinates":[-1.3047310756478,53.53539951579847],"type":"Point"}
}