{
  "type": "Feature",
  "properties": {
    "iso:country": "GB",
    "wof:name": "FY5 1EW",
    "wof:placetype": "postalcode"
  },
  "geometry": {"coordinates":[-3.045423,53.880146],"type":"Point"}
}
