{
  "type": "Feature",
  "properties": {
    "iso:country":"GB",
    "wof:name":"BS14 9BA",
    "wof:placetype":"postalcode"
},
  "geometry": {"coordinates":[-2.56256793648183,51.42248351307552],"type":"Point"}
}