{
  "type": "Feature",
  "properties": {
    "iso:country":"GB",
    "wof:name":"G32 7SS",
    "wof:placetype":"postalcode"
},
  "geometry": {"coordinates":[-4.16448041505464,55.8448295630273],"type":"Point"}
}