{
  "type": "Feature",
  "properties": {
    "iso:country":"GB",
    "wof:name":"S45 0LQ",
    "wof:placetype":"postalcode"
},
  "geometry": {"coordinates":[-1.47617652351004,53.18469705099166],"type":"Point"}
}