{
  "type": "Feature",
  "properties": {
    "iso:country": "GB",
    "wof:name": "CA2 7FD",
    "wof:placetype": "postalcode"
  },
  "geometry": {"coordinates":[-2.963,54.890478],"type":"Point"}
}
