{
  "type": "Feature",
  "properties": {
    "iso:country":"GB",
    "wof:name":"W1U 2LL",
    "wof:placetype":"postalcode"
},
  "geometry": {"coordinates":[-0.14675941122647,51.51700751106027],"type":"Point"}
}