{
  "type": "Feature",
  "properties": {
    "date:inception_lower": "1992-08-01",
    "date:inception_upper": "1992-08-01",
    "iso:country": "GB",
    "wof:name": "TW16 7TA",
    "wof:placetype": "postalcode"
  },
  "geometry": {"coordinates":[-0.420204,51.423587],"type":"Point"}
}
