{
  "type": "Feature",
  "properties": {
    "iso:country": "GB",
    "wof:name": "GL2 4LH",
    "wof:placetype": "postalcode"
  },
  "geometry": {"coordinates":[-2.297001,51.826115],"type":"Point"}
}
