{
  "type": "Feature",
  "properties": {
    "date:inception_lower": "1997-12-01",
    "date:inception_upper": "1997-12-01",
    "iso:country": "GB",
    "wof:name": "GL2 4LH",
    "wof:placetype": "postalcode"
  },
  "geometry": {"coordinates":[-2.297001,51.826115],"type":"Point"}
}
