{
  "type": "Feature",
  "properties": {
    "date:inception_lower":"1980-01-01",
    "date:inception_upper":"1980-01-31",
    "iso:country":"GB",
    "wof:name":"TR8 5DQ",
    "wof:placetype":"postalcode"
},
  "geometry": {"coordinates":[-4.979458,50.383245],"type":"Point"}
}