{
  "type": "Feature",
  "properties": {
    "date:inception_lower": "1980-01-01",
    "date:inception_upper": "1980-01-01",
    "iso:country": "GB",
    "wof:name": "DH4 4EF",
    "wof:placetype": "postalcode"
  },
  "geometry": {"coordinates":[-1.476778,54.855215],"type":"Point"}
}
