{
  "type": "Feature",
  "properties": {
    "iso:country":"GB",
    "wof:name":"DH4 4EF",
    "wof:placetype":"postalcode"
},
  "geometry": {"coordinates":[-1.47677800997258,54.85521461759745],"type":"Point"}
}