{
  "type": "Feature",
  "properties": {
    "iso:country":"GB",
    "wof:name":"NE38 7RH",
    "wof:placetype":"postalcode"
},
  "geometry": {"coordinates":[-1.51816979254756,54.89659763718848],"type":"Point"}
}