{
  "type": "Feature",
  "properties": {
    "iso:country":"GB",
    "wof:name":"HD1 4BJ",
    "wof:placetype":"postalcode"
},
  "geometry": {"coordinates":[-1.7915205829666,53.6438838566665],"type":"Point"}
}