{
  "type": "Feature",
  "properties": {
    "date:inception_lower": "1980-01-01",
    "date:inception_upper": "1980-01-01",
    "iso:country": "GB",
    "wof:name": "HD1 4BJ",
    "wof:placetype": "postalcode"
  },
  "geometry": {"coordinates":[-1.791521,53.643884],"type":"Point"}
}
