{
  "type": "Feature",
  "properties": {
    "date:inception_lower": "1980-01-01",
    "date:inception_upper": "1980-01-01",
    "iso:country": "GB",
    "wof:name": "E12 5EY",
    "wof:placetype": "postalcode"
  },
  "geometry": {"coordinates":[0.041762,51.563274],"type":"Point"}
}
