{
  "type": "Feature",
  "properties": {
    "iso:country":"GB",
    "wof:name":"FY3 7NU",
    "wof:placetype":"postalcode"
},
  "geometry": {"coordinates":[-3.02438895681427,53.82990330567473],"type":"Point"}
}