{
  "type": "Feature",
  "properties": {
    "date:inception_lower": "1980-01-01",
    "date:inception_upper": "1980-01-01",
    "iso:country": "GB",
    "wof:name": "EH51 0AW",
    "wof:placetype": "postalcode"
  },
  "geometry": {"coordinates":[-3.610724,56.016137],"type":"Point"}
}
