{
  "type": "Feature",
  "properties": {
    "iso:country": "GB",
    "wof:name": "TS17 0SU",
    "wof:placetype": "postalcode"
  },
  "geometry": {"coordinates":[-1.314137,54.523411],"type":"Point"}
}
