{
  "type": "Feature",
  "properties": {
    "iso:country":"GB",
    "wof:name":"TS17 0SU",
    "wof:placetype":"postalcode"
},
  "geometry": {"coordinates":[-1.31413678302807,54.52341140483183],"type":"Point"}
}