{
  "type": "Feature",
  "properties": {
    "date:inception_lower":"1980-01-01",
    "date:inception_upper":"1980-01-31",
    "iso:country":"GB",
    "wof:name":"BL6 7LT",
    "wof:placetype":"postalcode"
},
  "geometry": {"coordinates":[-2.549628,53.605687],"type":"Point"}
}