{
  "type": "Feature",
  "properties": {
    "iso:country":"GB",
    "wof:name":"BH25 6LJ",
    "wof:placetype":"postalcode"
},
  "geometry": {"coordinates":[-1.65487739680311,50.75199257220979],"type":"Point"}
}