{
  "type": "Feature",
  "properties": {
    "iso:country":"GB",
    "wof:name":"EX39 4EE",
    "wof:placetype":"postalcode"
},
  "geometry": {"coordinates":[-4.20179153367433,51.01415681820178],"type":"Point"}
}