{
  "type": "Feature",
  "properties": {
    "iso:country": "GB",
    "wof:name": "EX39 4EE",
    "wof:placetype": "postalcode"
  },
  "geometry": {"coordinates":[-4.201816,51.014152],"type":"Point"}
}
