{
  "type": "Feature",
  "properties": {
    "iso:country":"GB",
    "wof:name":"LN10 5HA",
    "wof:placetype":"postalcode"
},
  "geometry": {"coordinates":[-0.21216518826674,53.21204508702923],"type":"Point"}
}