{
  "type": "Feature",
  "properties": {
    "iso:country":"GB",
    "wof:name":"MK16 8HJ",
    "wof:placetype":"postalcode"
},
  "geometry": {"coordinates":[-0.72146870389522,52.08612723748574],"type":"Point"}
}