{
  "type": "Feature",
  "properties": {
    "iso:country":"GB",
    "wof:name":"LA8 8EP",
    "wof:placetype":"postalcode"
},
  "geometry": {"coordinates":[-2.81331985176662,54.26174233246687],"type":"Point"}
}