{
  "type": "Feature",
  "properties": {
    "iso:country":"GB",
    "wof:name":"BL3 4NY",
    "wof:placetype":"postalcode"
},
  "geometry": {"coordinates":[-2.47441716054033,53.57239474280811],"type":"Point"}
}