{
  "type": "Feature",
  "properties": {
    "iso:country": "GB",
    "wof:name": "BL3 4NY",
    "wof:placetype": "postalcode"
  },
  "geometry": {"coordinates":[-2.474417,53.572395],"type":"Point"}
}
