{
  "type": "Feature",
  "properties": {
    "iso:country":"GB",
    "wof:name":"KT1 3DQ",
    "wof:placetype":"postalcode"
},
  "geometry": {"coordinates":[-0.29472335049823,51.40927481634961],"type":"Point"}
}