{
  "type": "Feature",
  "properties": {
    "iso:country":"GB",
    "wof:name":"YO8 8EH",
    "wof:placetype":"postalcode"
},
  "geometry": {"coordinates":[-1.00686259572122,53.76455546228627],"type":"Point"}
}