{
  "type": "Feature",
  "properties": {
    "iso:country":"GB",
    "wof:name":"BS5 9LR",
    "wof:placetype":"postalcode"
},
  "geometry": {"coordinates":[-2.55759917487788,51.45851882386163],"type":"Point"}
}