{
  "type": "Feature",
  "properties": {
    "iso:country": "GB",
    "wof:name": "M16 8NW",
    "wof:placetype": "postalcode"
  },
  "geometry": {"coordinates":[-2.253424,53.440129],"type":"Point"}
}
