{
  "type": "Feature",
  "properties": {
    "iso:country":"GB",
    "wof:name":"CA6 6PJ",
    "wof:placetype":"postalcode"
},
  "geometry": {"coordinates":[-2.71595103011737,55.08703133671593],"type":"Point"}
}