{
  "type": "Feature",
  "properties": {
    "iso:country": "GB",
    "wof:name": "CA6 6PJ",
    "wof:placetype": "postalcode"
  },
  "geometry": {"coordinates":[-2.715956,55.087045],"type":"Point"}
}
