{
  "type": "Feature",
  "properties": {
    "iso:country":"GB",
    "wof:name":"PO41 0XZ",
    "wof:placetype":"postalcode"
},
  "geometry": {"coordinates":[-1.44023356950975,50.71032432133748],"type":"Point"}
}