{
  "type": "Feature",
  "properties": {
    "iso:country":"GB",
    "wof:name":"ST7 2HB",
    "wof:placetype":"postalcode"
},
  "geometry": {"coordinates":[-2.31243259413425,53.09650002835441],"type":"Point"}
}