{
  "type": "Feature",
  "properties": {
    "iso:country": "GB",
    "wof:name": "WV12 4AS",
    "wof:placetype": "postalcode"
  },
  "geometry": {"coordinates":[-2.033781,52.598696],"type":"Point"}
}
