{
  "type": "Feature",
  "properties": {
    "iso:country":"GB",
    "wof:name":"SA72 6TT",
    "wof:placetype":"postalcode"
},
  "geometry": {"coordinates":[-4.93268954870429,51.69475591076073],"type":"Point"}
}