{
  "type": "Feature",
  "properties": {
    "iso:country":"GB",
    "wof:name":"BD7 3JU",
    "wof:placetype":"postalcode"
},
  "geometry": {"coordinates":[-1.78079526380813,53.78116699551955],"type":"Point"}
}