{
  "type": "Feature",
  "properties": {
    "iso:country":"GB",
    "wof:name":"NW11 7TP",
    "wof:placetype":"postalcode"
},
  "geometry": {"coordinates":[-0.19740294210891,51.5817056701655],"type":"Point"}
}