{
  "type": "Feature",
  "properties": {
    "iso:country":"GB",
    "wof:name":"TS8 9RE",
    "wof:placetype":"postalcode"
},
  "geometry": {"coordinates":[-1.25266928502285,54.5246560454561],"type":"Point"}
}