{
  "type": "Feature",
  "properties": {
    "iso:country":"GB",
    "wof:name":"OX10 9AS",
    "wof:placetype":"postalcode"
},
  "geometry": {"coordinates":[-1.12703344669737,51.59714680592344],"type":"Point"}
}