{
  "type": "Feature",
  "properties": {
    "date:inception_lower":"1994-05-01",
    "date:inception_upper":"1994-05-31",
    "iso:country":"GB",
    "wof:name":"M22 9JG",
    "wof:placetype":"postalcode"
},
  "geometry": {"coordinates":[-2.268432,53.387387],"type":"Point"}
}