{
  "type": "Feature",
  "properties": {
    "iso:country":"GB",
    "wof:name":"DE21 7QP",
    "wof:placetype":"postalcode"
},
  "geometry": {"coordinates":[-1.39323667534206,52.92057785747734],"type":"Point"}
}