{
  "type": "Feature",
  "properties": {
    "iso:country":"GB",
    "wof:name":"NN6 6JZ",
    "wof:placetype":"postalcode"
},
  "geometry": {"coordinates":[-1.05627768852742,52.41734081009499],"type":"Point"}
}