{
  "type": "Feature",
  "properties": {
    "date:inception_lower": "1999-06-01",
    "date:inception_upper": "1999-06-01",
    "iso:country": "GB",
    "wof:name": "CH65 9JG",
    "wof:placetype": "postalcode"
  },
  "geometry": {"coordinates":[-2.897559,53.262719],"type":"Point"}
}
