{
  "type": "Feature",
  "properties": {
    "iso:country":"GB",
    "wof:name":"SW12 8NW",
    "wof:placetype":"postalcode"
},
  "geometry": {"coordinates":[-0.16168019251261,51.4492408451469],"type":"Point"}
}