{
  "type": "Feature",
  "properties": {
    "iso:country": "GB",
    "wof:name": "SW12 8NW",
    "wof:placetype": "postalcode"
  },
  "geometry": {"coordinates":[-0.16168,51.449241],"type":"Point"}
}
