{
  "type": "Feature",
  "properties": {
    "iso:country":"GB",
    "wof:name":"SG14 1LB",
    "wof:placetype":"postalcode"
},
  "geometry": {"coordinates":[-0.0887365351162,51.79591895450044],"type":"Point"}
}