{
  "type": "Feature",
  "properties": {
    "iso:country":"GB",
    "wof:name":"B96 6LL",
    "wof:placetype":"postalcode"
},
  "geometry": {"coordinates":[-1.94306930599052,52.24495544018624],"type":"Point"}
}