{
  "type": "Feature",
  "properties": {
    "iso:country":"GB",
    "wof:name":"SA71 4HB",
    "wof:placetype":"postalcode"
},
  "geometry": {"coordinates":[-4.92122414705435,51.67179263694369],"type":"Point"}
}