{
  "type": "Feature",
  "properties": {
    "iso:country": "GB",
    "wof:name": "SA71 4HB",
    "wof:placetype": "postalcode"
  },
  "geometry": {"coordinates":[-4.921224,51.671793],"type":"Point"}
}
