{
  "type": "Feature",
  "properties": {
    "iso:country":"GB",
    "wof:name":"YO61 1HS",
    "wof:placetype":"postalcode"
},
  "geometry": {"coordinates":[-1.13503439515845,54.08296245131672],"type":"Point"}
}