{
  "type": "Feature",
  "properties": {
    "iso:country":"GB",
    "wof:name":"DY1 2RD",
    "wof:placetype":"postalcode"
},
  "geometry": {"coordinates":[-2.10123224099274,52.51357703671098],"type":"Point"}
}