{
  "type": "Feature",
  "properties": {
    "iso:country":"GB",
    "wof:name":"S9 1PJ",
    "wof:placetype":"postalcode"
},
  "geometry": {"coordinates":[-1.42444173687635,53.42380408446969],"type":"Point"}
}