{
  "type": "Feature",
  "properties": {
    "iso:country":"GB",
    "wof:name":"TS12 1QS",
    "wof:placetype":"postalcode"
},
  "geometry": {"coordinates":[-0.98982526382291,54.5814697375265],"type":"Point"}
}