{
  "type": "Feature",
  "properties": {
    "iso:country": "GB",
    "wof:name": "NW10 8EY",
    "wof:placetype": "postalcode"
  },
  "geometry": {"coordinates":[-0.260948,51.540643],"type":"Point"}
}
