{
  "type": "Feature",
  "properties": {
    "date:inception_lower":"2002-05-01",
    "date:inception_upper":"2002-05-31",
    "iso:country":"GB",
    "wof:name":"NW10 8EY",
    "wof:placetype":"postalcode"
},
  "geometry": {"coordinates":[-0.260948,51.540643],"type":"Point"}
}