{
  "type": "Feature",
  "properties": {
    "date:inception_lower": "1980-01-01",
    "date:inception_upper": "1980-01-01",
    "iso:country": "GB",
    "wof:name": "PR5 0AX",
    "wof:placetype": "postalcode"
  },
  "geometry": {"coordinates":[-2.6223,53.730406],"type":"Point"}
}
