{
  "type": "Feature",
  "properties": {
    "iso:country": "GB",
    "wof:name": "FY3 9ET",
    "wof:placetype": "postalcode"
  },
  "geometry": {"coordinates":[-3.032195,53.813064],"type":"Point"}
}
