{
  "type": "Feature",
  "properties": {
    "iso:country":"GB",
    "wof:name":"B69 4TA",
    "wof:placetype":"postalcode"
},
  "geometry": {"coordinates":[-2.01343194029142,52.49022798086631],"type":"Point"}
}