{
  "type": "Feature",
  "properties": {
    "date:inception_lower": "1980-01-01",
    "date:inception_upper": "1980-01-01",
    "iso:country": "GB",
    "wof:name": "B69 4TA",
    "wof:placetype": "postalcode"
  },
  "geometry": {"coordinates":[-2.013432,52.490228],"type":"Point"}
}
