{
  "type": "Feature",
  "properties": {
    "iso:country": "GB",
    "wof:name": "B69 4TA",
    "wof:placetype": "postalcode"
  },
  "geometry": {"coordinates":[-2.013432,52.490228],"type":"Point"}
}
