{
  "type": "Feature",
  "properties": {
    "date:inception_lower": "1980-01-01",
    "date:inception_upper": "1980-01-01",
    "iso:country": "GB",
    "wof:name": "HA5 3LJ",
    "wof:placetype": "postalcode"
  },
  "geometry": {"coordinates":[-0.391473,51.597295],"type":"Point"}
}
