{
  "type": "Feature",
  "properties": {
    "iso:country": "GB",
    "wof:name": "IP2 8NG",
    "wof:placetype": "postalcode"
  },
  "geometry": {"coordinates":[1.145003,52.030974],"type":"Point"}
}
