{
  "type": "Feature",
  "properties": {
    "iso:country":"GB",
    "wof:name":"IP2 8NG",
    "wof:placetype":"postalcode"
},
  "geometry": {"coordinates":[1.14495802418788,52.03096965491306],"type":"Point"}
}