{
  "type": "Feature",
  "properties": {
    "iso:country":"GB",
    "wof:name":"BS3 2AW",
    "wof:placetype":"postalcode"
},
  "geometry": {"coordinates":[-2.61684709899809,51.44183018433959],"type":"Point"}
}