{
  "type": "Feature",
  "properties": {
    "iso:country": "GB",
    "wof:name": "WD25 7DT",
    "wof:placetype": "postalcode"
  },
  "geometry": {"coordinates":[-0.407492,51.694025],"type":"Point"}
}
