{
  "type": "Feature",
  "properties": {
    "iso:country":"GB",
    "wof:name":"WD25 7DT",
    "wof:placetype":"postalcode"
},
  "geometry": {"coordinates":[-0.40749213335497,51.69402469002183],"type":"Point"}
}