{
  "type": "Feature",
  "properties": {
    "iso:country":"GB",
    "wof:name":"RH15 0LQ",
    "wof:placetype":"postalcode"
},
  "geometry": {"coordinates":[-0.12087451589964,50.96078897541932],"type":"Point"}
}