{
  "type": "Feature",
  "properties": {
    "date:inception_lower": "1980-01-01",
    "date:inception_upper": "1980-01-01",
    "iso:country": "GB",
    "wof:name": "LL77 7UX",
    "wof:placetype": "postalcode"
  },
  "geometry": {"coordinates":[-4.307096,53.249917],"type":"Point"}
}
