{
  "type": "Feature",
  "properties": {
    "iso:country":"GB",
    "wof:name":"LL77 7UX",
    "wof:placetype":"postalcode"
},
  "geometry": {"coordinates":[-4.30709648429721,53.2499174827982],"type":"Point"}
}