{
  "type": "Feature",
  "properties": {
    "iso:country":"GB",
    "wof:name":"SW6 6QH",
    "wof:placetype":"postalcode"
},
  "geometry": {"coordinates":[-0.21220818506859,51.47543509503662],"type":"Point"}
}