{
  "type": "Feature",
  "properties": {
    "iso:country":"GB",
    "wof:name":"SK8 3RX",
    "wof:placetype":"postalcode"
},
  "geometry": {"coordinates":[-2.2373413909697,53.37441041572399],"type":"Point"}
}