{
  "type": "Feature",
  "properties": {
    "iso:country": "GB",
    "wof:name": "SK8 3RX",
    "wof:placetype": "postalcode"
  },
  "geometry": {"coordinates":[-2.237341,53.37441],"type":"Point"}
}
