{
  "type": "Feature",
  "properties": {
    "iso:country":"GB",
    "wof:name":"AB41 9RD",
    "wof:placetype":"postalcode"
},
  "geometry": {"coordinates":[-2.05138868484608,57.36692800580788],"type":"Point"}
}