{
  "type": "Feature",
  "properties": {
    "date:inception_lower":"1980-01-01",
    "date:inception_upper":"1980-01-31",
    "iso:country":"GB",
    "wof:name":"NE37 1TJ",
    "wof:placetype":"postalcode"
},
  "geometry": {"coordinates":[-1.537705,54.907628],"type":"Point"}
}