{
  "type": "Feature",
  "properties": {
    "iso:country":"GB",
    "wof:name":"CF3 2TB",
    "wof:placetype":"postalcode"
},
  "geometry": {"coordinates":[-3.06251311825676,51.53252984150006],"type":"Point"}
}