{
  "type": "Feature",
  "properties": {
    "date:inception_lower":"2006-03-01",
    "date:inception_upper":"2006-03-31",
    "iso:country":"GB",
    "wof:name":"CF3 2TB",
    "wof:placetype":"postalcode"
},
  "geometry": {"coordinates":[-3.062513,51.53253],"type":"Point"}
}