{
  "type": "Feature",
  "properties": {
    "iso:country": "GB",
    "wof:name": "CF3 2TB",
    "wof:placetype": "postalcode"
  },
  "geometry": {"coordinates":[-3.062513,51.53253],"type":"Point"}
}
