{
  "type": "Feature",
  "properties": {
    "date:inception_lower": "1980-01-01",
    "date:inception_upper": "1980-01-01",
    "iso:country": "GB",
    "wof:name": "S64 9RP",
    "wof:placetype": "postalcode"
  },
  "geometry": {"coordinates":[-1.298474,53.499526],"type":"Point"}
}
