{
  "type": "Feature",
  "properties": {
    "iso:country":"GB",
    "wof:name":"S64 9RP",
    "wof:placetype":"postalcode"
},
  "geometry": {"coordinates":[-1.29847373592624,53.4995255339978],"type":"Point"}
}