{
  "type": "Feature",
  "properties": {
    "iso:country":"GB",
    "wof:name":"TW2 5AN",
    "wof:placetype":"postalcode"
},
  "geometry": {"coordinates":[-0.35118781639909,51.4428960596138],"type":"Point"}
}