{
  "type": "Feature",
  "properties": {
    "iso:country": "GB",
    "wof:name": "WD3 4AB",
    "wof:placetype": "postalcode"
  },
  "geometry": {"coordinates":[-0.460351,51.64655],"type":"Point"}
}
