{
  "type": "Feature",
  "properties": {
    "iso:country":"GB",
    "wof:name":"WD3 4AB",
    "wof:placetype":"postalcode"
},
  "geometry": {"coordinates":[-0.4603514334076,51.64655048518654],"type":"Point"}
}