{
  "type": "Feature",
  "properties": {
    "date:inception_lower": "1980-01-01",
    "date:inception_upper": "1980-01-01",
    "iso:country": "GB",
    "wof:name": "TN12 5DH",
    "wof:placetype": "postalcode"
  },
  "geometry": {"coordinates":[0.379409,51.213752],"type":"Point"}
}
