{
  "type": "Feature",
  "properties": {
    "iso:country": "GB",
    "wof:name": "TN12 5DH",
    "wof:placetype": "postalcode"
  },
  "geometry": {"coordinates":[0.379409,51.213752],"type":"Point"}
}
