{
  "type": "Feature",
  "properties": {
    "iso:country":"GB",
    "wof:name":"B16 9DJ",
    "wof:placetype":"postalcode"
},
  "geometry": {"coordinates":[-1.93598546066188,52.47622323146583],"type":"Point"}
}