{
  "type": "Feature",
  "properties": {
    "iso:country": "GB",
    "wof:name": "SA18 2TW",
    "wof:placetype": "postalcode"
  },
  "geometry": {"coordinates":[-3.996451,51.826633],"type":"Point"}
}
