{
  "type": "Feature",
  "properties": {
    "iso:country":"GB",
    "wof:name":"SA18 2TW",
    "wof:placetype":"postalcode"
},
  "geometry": {"coordinates":[-3.99645097103041,51.82663250251755],"type":"Point"}
}