{
  "type": "Feature",
  "properties": {
    "iso:country":"GB",
    "wof:name":"SL4 6LJ",
    "wof:placetype":"postalcode"
},
  "geometry": {"coordinates":[-0.6341622133548,51.49756419747014],"type":"Point"}
}