{
  "type": "Feature",
  "properties": {
    "iso:country":"GB",
    "wof:name":"DA5 1BE",
    "wof:placetype":"postalcode"
},
  "geometry": {"coordinates":[0.14343731012473,51.44473305071558],"type":"Point"}
}