{
  "type": "Feature",
  "properties": {
    "iso:country":"GB",
    "wof:name":"BH14 0NL",
    "wof:placetype":"postalcode"
},
  "geometry": {"coordinates":[-1.95495364756508,50.72416700623171],"type":"Point"}
}