{
  "type": "Feature",
  "properties": {
    "iso:country":"GB",
    "wof:name":"PR7 2DJ",
    "wof:placetype":"postalcode"
},
  "geometry": {"coordinates":[-2.63608208645704,53.65033750435911],"type":"Point"}
}