{
  "type": "Feature",
  "properties": {
    "iso:country": "GB",
    "wof:name": "PR7 2DJ",
    "wof:placetype": "postalcode"
  },
  "geometry": {"coordinates":[-2.636082,53.650338],"type":"Point"}
}
