{
  "type": "Feature",
  "properties": {
    "iso:country":"GB",
    "wof:name":"SR5 4EE",
    "wof:placetype":"postalcode"
},
  "geometry": {"coordinates":[-1.44806320769369,54.92763524020624],"type":"Point"}
}