{
  "type": "Feature",
  "properties": {
    "iso:country":"GB",
    "wof:name":"BA6 9JX",
    "wof:placetype":"postalcode"
},
  "geometry": {"coordinates":[-2.71950283350261,51.14996919011199],"type":"Point"}
}