{
  "type": "Feature",
  "properties": {
    "date:inception_lower": "2018-11-01",
    "date:inception_upper": "2018-11-01",
    "iso:country": "GB",
    "wof:name": "BS40 5AD",
    "wof:placetype": "postalcode"
  },
  "geometry": {"coordinates":[-2.782807,51.341773],"type":"Point"}
}
