{
  "type": "Feature",
  "properties": {
    "iso:country":"GB",
    "wof:name":"SL6 5DB",
    "wof:placetype":"postalcode"
},
  "geometry": {"coordinates":[-0.74789876876733,51.52544948432482],"type":"Point"}
}