{
  "type": "Feature",
  "properties": {
    "iso:country": "GB",
    "wof:name": "RH19 3JY",
    "wof:placetype": "postalcode"
  },
  "geometry": {"coordinates":[-0.014,51.129227],"type":"Point"}
}
