{
  "type": "Feature",
  "properties": {
    "date:inception_lower": "1980-01-01",
    "date:inception_upper": "1980-01-01",
    "iso:country": "GB",
    "wof:name": "RH19 3JY",
    "wof:placetype": "postalcode"
  },
  "geometry": {"coordinates":[-0.014,51.129227],"type":"Point"}
}
