{
  "type": "Feature",
  "properties": {
    "iso:country": "GB",
    "wof:name": "SG8 9HG",
    "wof:placetype": "postalcode"
  },
  "geometry": {"coordinates":[-0.014875,52.04715],"type":"Point"}
}
