{
  "type": "Feature",
  "properties": {
    "iso:country":"GB",
    "wof:name":"EH7 5HP",
    "wof:placetype":"postalcode"
},
  "geometry": {"coordinates":[-3.18063019098077,55.96112637187323],"type":"Point"}
}