{
  "type": "Feature",
  "properties": {
    "date:inception_lower": "1999-06-01",
    "date:inception_upper": "1999-06-01",
    "iso:country": "GB",
    "wof:name": "NP18 3QW",
    "wof:placetype": "postalcode"
  },
  "geometry": {"coordinates":[-2.972962,51.613953],"type":"Point"}
}
