{
  "type": "Feature",
  "properties": {
    "iso:country":"GB",
    "wof:name":"SS4 1QF",
    "wof:placetype":"postalcode"
},
  "geometry": {"coordinates":[0.70690409109091,51.58894171237397],"type":"Point"}
}