{
  "type": "Feature",
  "properties": {
    "iso:country":"GB",
    "wof:name":"GL52 8DP",
    "wof:placetype":"postalcode"
},
  "geometry": {"coordinates":[-2.06296178616116,51.94473068992971],"type":"Point"}
}