{
  "type": "Feature",
  "properties": {
    "date:inception_lower": "1980-01-01",
    "date:inception_upper": "1980-01-01",
    "iso:country": "GB",
    "wof:name": "WD5 0SF",
    "wof:placetype": "postalcode"
  },
  "geometry": {"coordinates":[-0.402843,51.720865],"type":"Point"}
}
