{
  "type": "Feature",
  "properties": {
    "iso:country": "GB",
    "wof:name": "WD5 0SF",
    "wof:placetype": "postalcode"
  },
  "geometry": {"coordinates":[-0.402843,51.720865],"type":"Point"}
}
