{
  "type": "Feature",
  "properties": {
    "iso:country":"GB",
    "wof:name":"ME12 3SA",
    "wof:placetype":"postalcode"
},
  "geometry": {"coordinates":[0.81181150132986,51.41695709761796],"type":"Point"}
}