{
  "type": "Feature",
  "properties": {
    "iso:country": "GB",
    "wof:name": "BS3 1JP",
    "wof:placetype": "postalcode"
  },
  "geometry": {"coordinates":[-2.614306,51.442221],"type":"Point"}
}
