{
  "type": "Feature",
  "properties": {
    "iso:country":"GB",
    "wof:name":"BS3 1JP",
    "wof:placetype":"postalcode"
},
  "geometry": {"coordinates":[-2.61430566562574,51.44222118407669],"type":"Point"}
}