{
  "type": "Feature",
  "properties": {
    "iso:country": "GB",
    "wof:name": "NR10 5LX",
    "wof:placetype": "postalcode"
  },
  "geometry": {"coordinates":[1.26617,52.738451],"type":"Point"}
}
