{
  "type": "Feature",
  "properties": {
    "iso:country":"GB",
    "wof:name":"SO32 2HF",
    "wof:placetype":"postalcode"
},
  "geometry": {"coordinates":[-1.24973000180926,50.92111295108064],"type":"Point"}
}