{
  "type": "Feature",
  "properties": {
    "date:inception_lower":"1994-12-01",
    "date:inception_upper":"1994-12-31",
    "iso:country":"GB",
    "wof:name":"SO32 2HF",
    "wof:placetype":"postalcode"
},
  "geometry": {"coordinates":[-1.24973,50.921113],"type":"Point"}
}