{
  "type": "Feature",
  "properties": {
    "date:inception_lower": "2017-10-01",
    "date:inception_upper": "2017-10-01",
    "iso:country": "GB",
    "wof:name": "EN9 1FH",
    "wof:placetype": "postalcode"
  },
  "geometry": {"coordinates":[0.000332,51.68405],"type":"Point"}
}
