{
  "type": "Feature",
  "properties": {
    "iso:country": "GB",
    "wof:name": "EN9 1FH",
    "wof:placetype": "postalcode"
  },
  "geometry": {"coordinates":[0.000304,51.684069],"type":"Point"}
}
