{
  "type": "Feature",
  "properties": {
    "iso:country":"GB",
    "wof:name":"SA1 6YT",
    "wof:placetype":"postalcode"
},
  "geometry": {"coordinates":[-3.94437738522024,51.6285143922956],"type":"Point"}
}