{
  "type": "Feature",
  "properties": {
    "iso:country": "GB",
    "wof:name": "SA1 6YT",
    "wof:placetype": "postalcode"
  },
  "geometry": {"coordinates":[-3.944377,51.628514],"type":"Point"}
}
