{
  "type": "Feature",
  "properties": {
    "iso:country": "GB",
    "wof:name": "S25 5GX",
    "wof:placetype": "postalcode"
  },
  "geometry": {"coordinates":[-1.222464,53.344395],"type":"Point"}
}
