{
  "type": "Feature",
  "properties": {
    "iso:country":"GB",
    "wof:name":"S25 5GX",
    "wof:placetype":"postalcode"
},
  "geometry": {"coordinates":[-1.22246436133021,53.3443947991588],"type":"Point"}
}