{
  "type": "Feature",
  "properties": {
    "iso:country":"GB",
    "wof:name":"LA12 8AZ",
    "wof:placetype":"postalcode"
},
  "geometry": {"coordinates":[-2.96662092234492,54.31000638821572],"type":"Point"}
}