{
  "type": "Feature",
  "properties": {
    "date:inception_lower": "1980-01-01",
    "date:inception_upper": "1980-01-01",
    "iso:country": "GB",
    "wof:name": "LA12 8AZ",
    "wof:placetype": "postalcode"
  },
  "geometry": {"coordinates":[-2.966621,54.310006],"type":"Point"}
}
