{
  "type": "Feature",
  "properties": {
    "iso:country":"GB",
    "wof:name":"TN15 7PR",
    "wof:placetype":"postalcode"
},
  "geometry": {"coordinates":[0.30436651590419,51.33303206066724],"type":"Point"}
}