{
  "type": "Feature",
  "properties": {
    "iso:country": "GB",
    "wof:name": "TN15 7PR",
    "wof:placetype": "postalcode"
  },
  "geometry": {"coordinates":[0.304367,51.333032],"type":"Point"}
}
