{
  "type": "Feature",
  "properties": {
    "date:inception_lower": "1980-01-01",
    "date:inception_upper": "1980-01-01",
    "iso:country": "GB",
    "wof:name": "BB9 6PA",
    "wof:placetype": "postalcode"
  },
  "geometry": {"coordinates":[-2.251461,53.868218],"type":"Point"}
}
