{
  "type": "Feature",
  "properties": {
    "iso:country":"GB",
    "wof:name":"BB9 6PA",
    "wof:placetype":"postalcode"
},
  "geometry": {"coordinates":[-2.24579946015473,53.86758738492281],"type":"Point"}
}