{
  "type": "Feature",
  "properties": {
    "iso:country":"GB",
    "wof:name":"KY5 0DA",
    "wof:placetype":"postalcode"
},
  "geometry": {"coordinates":[-3.26208992451448,56.13823032413373],"type":"Point"}
}