{
  "type": "Feature",
  "properties": {
    "iso:country":"GB",
    "wof:name":"BB8 9HB",
    "wof:placetype":"postalcode"
},
  "geometry": {"coordinates":[-2.17142261960102,53.86030182521237],"type":"Point"}
}