{
  "type": "Feature",
  "properties": {
    "iso:country":"GB",
    "wof:name":"CB6 3BP",
    "wof:placetype":"postalcode"
},
  "geometry": {"coordinates":[0.24905805873414,52.39815870347636],"type":"Point"}
}