{
  "type": "Feature",
  "properties": {
    "iso:country":"GB",
    "wof:name":"CH4 7JU",
    "wof:placetype":"postalcode"
},
  "geometry": {"coordinates":[-2.89177032068811,53.18188768659139],"type":"Point"}
}