{
  "type": "Feature",
  "properties": {
    "iso:country":"GB",
    "wof:name":"WA12 9LN",
    "wof:placetype":"postalcode"
},
  "geometry": {"coordinates":[-2.64045620345113,53.45161454833406],"type":"Point"}
}