{
  "type": "Feature",
  "properties": {
    "iso:country":"GB",
    "wof:name":"HA5 3UZ",
    "wof:placetype":"postalcode"
},
  "geometry": {"coordinates":[-0.39972572999174,51.60320747506935],"type":"Point"}
}