{
  "type": "Feature",
  "properties": {
    "iso:country":"GB",
    "wof:name":"WN6 0DN",
    "wof:placetype":"postalcode"
},
  "geometry": {"coordinates":[-2.65552491957615,53.58512061387638],"type":"Point"}
}