{
  "type": "Feature",
  "properties": {
    "iso:country": "GB",
    "wof:name": "NW2 4NX",
    "wof:placetype": "postalcode"
  },
  "geometry": {"coordinates":[-0.22262,51.549844],"type":"Point"}
}
