{
  "type": "Feature",
  "properties": {
    "iso:country":"GB",
    "wof:name":"LE10 2AL",
    "wof:placetype":"postalcode"
},
  "geometry": {"coordinates":[-1.35108874003884,52.530200700385],"type":"Point"}
}