{
  "type": "Feature",
  "properties": {
    "iso:country": "GB",
    "wof:name": "IP5 1EB",
    "wof:placetype": "postalcode"
  },
  "geometry": {"coordinates":[1.210751,52.072869],"type":"Point"}
}
