{
  "type": "Feature",
  "properties": {
    "iso:country":"GB",
    "wof:name":"NP10 0AP",
    "wof:placetype":"postalcode"
},
  "geometry": {"coordinates":[-3.05100388238004,51.59489212285983],"type":"Point"}
}