{
  "type": "Feature",
  "properties": {
    "date:inception_lower": "2015-10-01",
    "date:inception_upper": "2015-10-01",
    "iso:country": "GB",
    "wof:name": "LN9 6BF",
    "wof:placetype": "postalcode"
  },
  "geometry": {"coordinates":[-0.115488,53.206723],"type":"Point"}
}
