{
  "type": "Feature",
  "properties": {
    "iso:country":"GB",
    "wof:name":"LN9 6BF",
    "wof:placetype":"postalcode"
},
  "geometry": {"coordinates":[-0.11558058509287,53.20668196489424],"type":"Point"}
}