{
  "type": "Feature",
  "properties": {
    "iso:country":"GB",
    "wof:name":"CV12 0DB",
    "wof:placetype":"postalcode"
},
  "geometry": {"coordinates":[-1.49589501506138,52.47180528771307],"type":"Point"}
}