{
  "type": "Feature",
  "properties": {
    "date:inception_lower": "1980-01-01",
    "date:inception_upper": "1980-01-01",
    "iso:country": "GB",
    "wof:name": "CV12 0DB",
    "wof:placetype": "postalcode"
  },
  "geometry": {"coordinates":[-1.495895,52.471805],"type":"Point"}
}
