{
  "type": "Feature",
  "properties": {
    "date:inception_lower": "1980-01-01",
    "date:inception_upper": "1980-01-01",
    "iso:country": "GB",
    "wof:name": "EX21 5BS",
    "wof:placetype": "postalcode"
  },
  "geometry": {"coordinates":[-4.220011,50.732441],"type":"Point"}
}
