{
  "type": "Feature",
  "properties": {
    "iso:country":"GB",
    "wof:name":"SS17 8HG",
    "wof:placetype":"postalcode"
},
  "geometry": {"coordinates":[0.43942491228089,51.52921171067707],"type":"Point"}
}