{
  "type": "Feature",
  "properties": {
    "iso:country":"GB",
    "wof:name":"PO18 0PT",
    "wof:placetype":"postalcode"
},
  "geometry": {"coordinates":[-0.75893131561147,50.89673983892014],"type":"Point"}
}