{
  "type": "Feature",
  "properties": {
    "iso:country": "GB",
    "wof:name": "PO18 0PT",
    "wof:placetype": "postalcode"
  },
  "geometry": {"coordinates":[-0.758931,50.89674],"type":"Point"}
}
