{
  "type": "Feature",
  "properties": {
    "iso:country":"GB",
    "wof:name":"SY23 4PE",
    "wof:placetype":"postalcode"
},
  "geometry": {"coordinates":[-4.02013609312313,52.35680507841121],"type":"Point"}
}