{
  "type": "Feature",
  "properties": {
    "iso:country":"GB",
    "wof:name":"S36 6UE",
    "wof:placetype":"postalcode"
},
  "geometry": {"coordinates":[-1.62864041345306,53.51956759628633],"type":"Point"}
}