{
  "type": "Feature",
  "properties": {
    "iso:country":"GB",
    "wof:name":"SR1 1PJ",
    "wof:placetype":"postalcode"
},
  "geometry": {"coordinates":[-1.37355416828157,54.90639871354534],"type":"Point"}
}