{
  "type": "Feature",
  "properties": {
    "iso:country":"GB",
    "wof:name":"PL34 0DX",
    "wof:placetype":"postalcode"
},
  "geometry": {"coordinates":[-4.75294690716988,50.65474968450879],"type":"Point"}
}