{
  "type": "Feature",
  "properties": {
    "iso:country":"GB",
    "wof:name":"IV18 0EQ",
    "wof:placetype":"postalcode"
},
  "geometry": {"coordinates":[-4.16778147841306,57.6871256640696],"type":"Point"}
}