{
  "type": "Feature",
  "properties": {
    "iso:country":"GB",
    "wof:name":"SA44 6RF",
    "wof:placetype":"postalcode"
},
  "geometry": {"coordinates":[-4.46064213769407,52.12841364929548],"type":"Point"}
}