{
  "type": "Feature",
  "properties": {
    "iso:country":"GB",
    "wof:name":"GL13 9UP",
    "wof:placetype":"postalcode"
},
  "geometry": {"coordinates":[-2.46836801307005,51.72292363681833],"type":"Point"}
}