{
  "type": "Feature",
  "properties": {
    "date:inception_lower": "1980-01-01",
    "date:inception_upper": "1980-01-01",
    "iso:country": "GB",
    "wof:name": "TN10 4JE",
    "wof:placetype": "postalcode"
  },
  "geometry": {"coordinates":[0.29354,51.210935],"type":"Point"}
}
