{
  "type": "Feature",
  "properties": {
    "iso:country": "GB",
    "wof:name": "SW8 3ST",
    "wof:placetype": "postalcode"
  },
  "geometry": {"coordinates":[-0.148583,51.469169],"type":"Point"}
}
