{
  "type": "Feature",
  "properties": {
    "iso:country":"GB",
    "wof:name":"SW8 3ST",
    "wof:placetype":"postalcode"
},
  "geometry": {"coordinates":[-0.14858332109229,51.46916910325187],"type":"Point"}
}