{
  "type": "Feature",
  "properties": {
    "iso:country": "GB",
    "wof:name": "BD11 2NY",
    "wof:placetype": "postalcode"
  },
  "geometry": {"coordinates":[-1.689502,53.751853],"type":"Point"}
}
