{
  "type": "Feature",
  "properties": {
    "iso:country":"GB",
    "wof:name":"BD11 2NY",
    "wof:placetype":"postalcode"
},
  "geometry": {"coordinates":[-1.68950163821004,53.75185328365325],"type":"Point"}
}