{
  "type": "Feature",
  "properties": {
    "iso:country": "GB",
    "wof:name": "OX9 2FT",
    "wof:placetype": "postalcode"
  },
  "geometry": {"coordinates":[-0.993606,51.749462],"type":"Point"}
}
