{
  "type": "Feature",
  "properties": {
    "date:inception_lower": "2017-12-01",
    "date:inception_upper": "2017-12-01",
    "iso:country": "GB",
    "wof:name": "RM10 7FR",
    "wof:placetype": "postalcode"
  },
  "geometry": {"coordinates":[0.152575,51.551763],"type":"Point"}
}
