{
  "type": "Feature",
  "properties": {
    "iso:country": "GB",
    "wof:name": "DA1 2BZ",
    "wof:placetype": "postalcode"
  },
  "geometry": {"coordinates":[0.212336,51.452978],"type":"Point"}
}
