{
  "type": "Feature",
  "properties": {
    "iso:country":"GB",
    "wof:name":"DA1 2BZ",
    "wof:placetype":"postalcode"
},
  "geometry": {"coordinates":[0.21230852671767,51.45297692337106],"type":"Point"}
}