{
  "type": "Feature",
  "properties": {
    "iso:country":"GB",
    "wof:name":"ME8 7JQ",
    "wof:placetype":"postalcode"
},
  "geometry": {"coordinates":[0.60719086300855,51.36337472294278],"type":"Point"}
}