{
  "type": "Feature",
  "properties": {
    "iso:country":"GB",
    "wof:name":"HA2 9SP",
    "wof:placetype":"postalcode"
},
  "geometry": {"coordinates":[-0.37365175652502,51.57356169765094],"type":"Point"}
}