{
  "type": "Feature",
  "properties": {
    "date:inception_lower": "1980-01-01",
    "date:inception_upper": "1980-01-01",
    "iso:country": "GB",
    "wof:name": "HA2 9SP",
    "wof:placetype": "postalcode"
  },
  "geometry": {"coordinates":[-0.373652,51.573562],"type":"Point"}
}
