{
  "type": "Feature",
  "properties": {
    "iso:country": "GB",
    "wof:name": "IP9 2DS",
    "wof:placetype": "postalcode"
  },
  "geometry": {"coordinates":[1.076015,51.990795],"type":"Point"}
}
