{
  "type": "Feature",
  "properties": {
    "iso:country":"GB",
    "wof:name":"IP9 2DS",
    "wof:placetype":"postalcode"
},
  "geometry": {"coordinates":[1.07598479916168,51.99078191010379],"type":"Point"}
}