{
  "type": "Feature",
  "properties": {
    "iso:country": "GB",
    "wof:name": "CM11 2TH",
    "wof:placetype": "postalcode"
  },
  "geometry": {"coordinates":[0.43035,51.610519],"type":"Point"}
}
