{
  "type": "Feature",
  "properties": {
    "iso:country": "GB",
    "wof:name": "EH20 9DD",
    "wof:placetype": "postalcode"
  },
  "geometry": {"coordinates":[-3.147163,55.875416],"type":"Point"}
}
