{
  "type": "Feature",
  "properties": {
    "iso:country":"GB",
    "wof:name":"EH20 9DD",
    "wof:placetype":"postalcode"
},
  "geometry": {"coordinates":[-3.14716354424592,55.87541563725372],"type":"Point"}
}