{
  "type": "Feature",
  "properties": {
    "date:inception_lower": "1980-01-01",
    "date:inception_upper": "1980-01-01",
    "iso:country": "GB",
    "wof:name": "DD8 3PX",
    "wof:placetype": "postalcode"
  },
  "geometry": {"coordinates":[-2.827797,56.697663],"type":"Point"}
}
