{
  "type": "Feature",
  "properties": {
    "iso:country":"GB",
    "wof:name":"PH2 0AJ",
    "wof:placetype":"postalcode"
},
  "geometry": {"coordinates":[-3.4379423907444,56.38033344021088],"type":"Point"}
}