{
  "type": "Feature",
  "properties": {
    "iso:country":"GB",
    "wof:name":"SK12 1AY",
    "wof:placetype":"postalcode"
},
  "geometry": {"coordinates":[-2.11341863830105,53.34837293394128],"type":"Point"}
}