{
  "type": "Feature",
  "properties": {
    "iso:country":"GB",
    "wof:name":"EN6 2NY",
    "wof:placetype":"postalcode"
},
  "geometry": {"coordinates":[-0.18379483977476,51.69268547346037],"type":"Point"}
}