{
  "type": "Feature",
  "properties": {
    "date:inception_lower":"1980-01-01",
    "date:inception_upper":"1980-01-31",
    "iso:country":"GB",
    "wof:name":"EN6 2NY",
    "wof:placetype":"postalcode"
},
  "geometry": {"coordinates":[-0.183795,51.692685],"type":"Point"}
}