{
  "type": "Feature",
  "properties": {
    "iso:country":"GB",
    "wof:name":"HA6 2DD",
    "wof:placetype":"postalcode"
},
  "geometry": {"coordinates":[-0.43363759161054,51.61392480881269],"type":"Point"}
}