{
  "type": "Feature",
  "properties": {
    "iso:country": "GB",
    "wof:name": "LE2 4FG",
    "wof:placetype": "postalcode"
  },
  "geometry": {"coordinates":[-1.071288,52.60549],"type":"Point"}
}
