{
  "type": "Feature",
  "properties": {
    "iso:country":"GB",
    "wof:name":"BH6 5LB",
    "wof:placetype":"postalcode"
},
  "geometry": {"coordinates":[-1.80699540476833,50.7342050043685],"type":"Point"}
}