{
  "type": "Feature",
  "properties": {
    "iso:country":"GB",
    "wof:name":"EH4 5NS",
    "wof:placetype":"postalcode"
},
  "geometry": {"coordinates":[-3.27010022717144,55.97009376526114],"type":"Point"}
}