{
  "type": "Feature",
  "properties": {
    "iso:country":"GB",
    "wof:name":"WA8 0RH",
    "wof:placetype":"postalcode"
},
  "geometry": {"coordinates":[-2.7061650808672,53.37229602565972],"type":"Point"}
}