{
  "type": "Feature",
  "properties": {
    "iso:country":"GB",
    "wof:name":"SS17 8PU",
    "wof:placetype":"postalcode"
},
  "geometry": {"coordinates":[0.39336607479274,51.52770561583638],"type":"Point"}
}