{
  "type": "Feature",
  "properties": {
    "iso:country":"GB",
    "wof:name":"M34 3EL",
    "wof:placetype":"postalcode"
},
  "geometry": {"coordinates":[-2.09802666926017,53.45503584429152],"type":"Point"}
}