{
  "type": "Feature",
  "properties": {
    "iso:country":"GB",
    "wof:name":"DN15 6XQ",
    "wof:placetype":"postalcode"
},
  "geometry": {"coordinates":[-0.65458516087553,53.5858817402632],"type":"Point"}
}