{
  "type": "Feature",
  "properties": {
    "iso:country":"GB",
    "wof:name":"PL31 2LD",
    "wof:placetype":"postalcode"
},
  "geometry": {"coordinates":[-4.71764702938978,50.47152600541427],"type":"Point"}
}