{
  "type": "Feature",
  "properties": {
    "date:inception_lower": "1999-12-01",
    "date:inception_upper": "1999-12-01",
    "iso:country": "GB",
    "wof:name": "PL31 2LD",
    "wof:placetype": "postalcode"
  },
  "geometry": {"coordinates":[-4.717647,50.471526],"type":"Point"}
}
