{
  "type": "Feature",
  "properties": {
    "iso:country": "GB",
    "wof:name": "PL31 2LD",
    "wof:placetype": "postalcode"
  },
  "geometry": {"coordinates":[-4.717647,50.471526],"type":"Point"}
}
