{
  "type": "Feature",
  "properties": {
    "iso:country": "GB",
    "wof:name": "OL10 3QL",
    "wof:placetype": "postalcode"
  },
  "geometry": {"coordinates":[-2.242542,53.585593],"type":"Point"}
}
