{
  "type": "Feature",
  "properties": {
    "iso:country":"GB",
    "wof:name":"OL10 3QL",
    "wof:placetype":"postalcode"
},
  "geometry": {"coordinates":[-2.24254227396276,53.58559278851815],"type":"Point"}
}