{
  "type": "Feature",
  "properties": {
    "iso:country":"GB",
    "wof:name":"BS15 3RA",
    "wof:placetype":"postalcode"
},
  "geometry": {"coordinates":[-2.50796494753402,51.44757687345005],"type":"Point"}
}