{
  "type": "Feature",
  "properties": {
    "iso:country": "GB",
    "wof:name": "OL12 8BB",
    "wof:placetype": "postalcode"
  },
  "geometry": {"coordinates":[-2.17541,53.661256],"type":"Point"}
}
