{
  "type": "Feature",
  "properties": {
    "iso:country": "GB",
    "wof:name": "EH6 5PH",
    "wof:placetype": "postalcode"
  },
  "geometry": {"coordinates":[-3.185765,55.969281],"type":"Point"}
}
