{
  "type": "Feature",
  "properties": {
    "iso:country":"GB",
    "wof:name":"S36 1EN",
    "wof:placetype":"postalcode"
},
  "geometry": {"coordinates":[-1.60639640995935,53.48187076972109],"type":"Point"}
}