{
  "type": "Feature",
  "properties": {
    "iso:country":"GB",
    "wof:name":"CF10 4GA",
    "wof:placetype":"postalcode"
},
  "geometry": {"coordinates":[-3.15858845636421,51.46153742776302],"type":"Point"}
}