{
  "type": "Feature",
  "properties": {
    "date:inception_lower":"2011-09-01",
    "date:inception_upper":"2011-09-30",
    "iso:country":"GB",
    "wof:name":"CF10 4GA",
    "wof:placetype":"postalcode"
},
  "geometry": {"coordinates":[-3.158588,51.461537],"type":"Point"}
}