{
  "type": "Feature",
  "properties": {
    "date:inception_lower":"2013-07-01",
    "date:inception_upper":"2013-07-31",
    "iso:country":"GB",
    "wof:name":"G4 0HT",
    "wof:placetype":"postalcode"
},
  "geometry": {"coordinates":[-4.252989,55.868522],"type":"Point"}
}