{
  "type": "Feature",
  "properties": {
    "iso:country":"GB",
    "wof:name":"SG6 2BL",
    "wof:placetype":"postalcode"
},
  "geometry": {"coordinates":[-0.2168792858464,51.9709904793777],"type":"Point"}
}