{
  "type": "Feature",
  "properties": {
    "iso:country":"GB",
    "wof:name":"SO32 1GG",
    "wof:placetype":"postalcode"
},
  "geometry": {"coordinates":[-1.21339101709875,50.95338179879143],"type":"Point"}
}