{
  "type": "Feature",
  "properties": {
    "iso:country":"GB",
    "wof:name":"SY10 9QR",
    "wof:placetype":"postalcode"
},
  "geometry": {"coordinates":[-3.08145007956923,52.79120041267606],"type":"Point"}
}