{
  "type": "Feature",
  "properties": {
    "iso:country": "GB",
    "wof:name": "CM1 4HH",
    "wof:placetype": "postalcode"
  },
  "geometry": {"coordinates":[0.465727,51.749021],"type":"Point"}
}
