{
  "type": "Feature",
  "properties": {
    "iso:country":"GB",
    "wof:name":"NE10 9NU",
    "wof:placetype":"postalcode"
},
  "geometry": {"coordinates":[-1.5686744678463,54.95048974724529],"type":"Point"}
}