{
  "type": "Feature",
  "properties": {
    "date:inception_lower": "1980-01-01",
    "date:inception_upper": "1980-01-01",
    "iso:country": "GB",
    "wof:name": "NE10 9NU",
    "wof:placetype": "postalcode"
  },
  "geometry": {"coordinates":[-1.568674,54.95049],"type":"Point"}
}
