{
  "type": "Feature",
  "properties": {
    "iso:country": "GB",
    "wof:name": "PL21 0WF",
    "wof:placetype": "postalcode"
  },
  "geometry": {"coordinates":[-3.911322,50.386395],"type":"Point"}
}
