{
  "type": "Feature",
  "properties": {
    "iso:country":"GB",
    "wof:name":"GL54 5GF",
    "wof:placetype":"postalcode"
},
  "geometry": {"coordinates":[-1.96161934154223,51.96160817384224],"type":"Point"}
}