{
  "type": "Feature",
  "properties": {
    "date:inception_lower": "2014-07-01",
    "date:inception_upper": "2014-07-01",
    "iso:country": "GB",
    "wof:name": "GL54 5GF",
    "wof:placetype": "postalcode"
  },
  "geometry": {"coordinates":[-1.960955,51.961752],"type":"Point"}
}
