{
  "type": "Feature",
  "properties": {
    "iso:country":"GB",
    "wof:name":"NN7 3RA",
    "wof:placetype":"postalcode"
},
  "geometry": {"coordinates":[-1.0080865633969,52.20958836154604],"type":"Point"}
}