{
  "type": "Feature",
  "properties": {
    "iso:country":"GB",
    "wof:name":"S71 5JF",
    "wof:placetype":"postalcode"
},
  "geometry": {"coordinates":[-1.43635041015092,53.56554720511993],"type":"Point"}
}