{
  "type": "Feature",
  "properties": {
    "date:inception_lower": "1998-06-01",
    "date:inception_upper": "1998-06-01",
    "iso:country": "GB",
    "wof:name": "YO8 5SP",
    "wof:placetype": "postalcode"
  },
  "geometry": {"coordinates":[-0.991778,53.837839],"type":"Point"}
}
