{
  "type": "Feature",
  "properties": {
    "iso:country":"GB",
    "wof:name":"YO8 5SP",
    "wof:placetype":"postalcode"
},
  "geometry": {"coordinates":[-0.99201204278846,53.83795640621849],"type":"Point"}
}