{
  "type": "Feature",
  "properties": {
    "iso:country": "GB",
    "wof:name": "HD2 1RN",
    "wof:placetype": "postalcode"
  },
  "geometry": {"coordinates":[-1.75162,53.6795],"type":"Point"}
}
