{
  "type": "Feature",
  "properties": {
    "iso:country":"GB",
    "wof:name":"BD8 7AJ",
    "wof:placetype":"postalcode"
},
  "geometry": {"coordinates":[-1.76406584025314,53.81198203050386],"type":"Point"}
}