{
  "type": "Feature",
  "properties": {
    "date:inception_lower": "1980-01-01",
    "date:inception_upper": "1980-01-01",
    "iso:country": "GB",
    "wof:name": "BD8 7AJ",
    "wof:placetype": "postalcode"
  },
  "geometry": {"coordinates":[-1.764066,53.811982],"type":"Point"}
}
