{
  "type": "Feature",
  "properties": {
    "date:inception_lower": "1999-06-01",
    "date:inception_upper": "1999-06-01",
    "iso:country": "GB",
    "wof:name": "NP16 5JY",
    "wof:placetype": "postalcode"
  },
  "geometry": {"coordinates":[-2.673334,51.633201],"type":"Point"}
}
