{
  "type": "Feature",
  "properties": {
    "date:inception_lower": "1980-01-01",
    "date:inception_upper": "1980-01-01",
    "iso:country": "GB",
    "wof:name": "DN35 0LR",
    "wof:placetype": "postalcode"
  },
  "geometry": {"coordinates":[-0.029787,53.551351],"type":"Point"}
}
