{
  "type": "Feature",
  "properties": {
    "iso:country":"GB",
    "wof:name":"DN35 0LR",
    "wof:placetype":"postalcode"
},
  "geometry": {"coordinates":[-0.0297869094108,53.55135074799917],"type":"Point"}
}