{
  "type": "Feature",
  "properties": {
    "iso:country":"GB",
    "wof:name":"DL6 3RT",
    "wof:placetype":"postalcode"
},
  "geometry": {"coordinates":[-1.41998885737983,54.34293698123385],"type":"Point"}
}