{
  "type": "Feature",
  "properties": {
    "iso:country": "GB",
    "wof:name": "DL6 3RT",
    "wof:placetype": "postalcode"
  },
  "geometry": {"coordinates":[-1.419989,54.342937],"type":"Point"}
}
