{
  "type": "Feature",
  "properties": {
    "iso:country": "GB",
    "wof:name": "TA6 5HP",
    "wof:placetype": "postalcode"
  },
  "geometry": {"coordinates":[-2.99662,51.128422],"type":"Point"}
}
