{
  "type": "Feature",
  "properties": {
    "iso:country":"GB",
    "wof:name":"CH7 4RG",
    "wof:placetype":"postalcode"
},
  "geometry": {"coordinates":[-3.08602511950238,53.13005105855736],"type":"Point"}
}