{
  "type": "Feature",
  "properties": {
    "date:inception_lower":"1980-01-01",
    "date:inception_upper":"1980-01-31",
    "iso:country":"GB",
    "wof:name":"SA3 5QQ",
    "wof:placetype":"postalcode"
},
  "geometry": {"coordinates":[-4.011037,51.582941],"type":"Point"}
}