{
  "type": "Feature",
  "properties": {
    "iso:country":"GB",
    "wof:name":"SA3 5QQ",
    "wof:placetype":"postalcode"
},
  "geometry": {"coordinates":[-4.0110370381804,51.58294084219334],"type":"Point"}
}