{
  "type": "Feature",
  "properties": {
    "iso:country":"GB",
    "wof:name":"SE18 5SY",
    "wof:placetype":"postalcode"
},
  "geometry": {"coordinates":[0.04717428372082,51.49421459511026],"type":"Point"}
}