{
  "type": "Feature",
  "properties": {
    "date:inception_lower": "1980-01-01",
    "date:inception_upper": "1980-01-01",
    "iso:country": "GB",
    "wof:name": "BS13 7AX",
    "wof:placetype": "postalcode"
  },
  "geometry": {"coordinates":[-2.627026,51.422118],"type":"Point"}
}
