{
  "type": "Feature",
  "properties": {
    "date:inception_lower":"1987-04-01",
    "date:inception_upper":"1987-04-30",
    "iso:country":"GB",
    "wof:name":"WD5 0XF",
    "wof:placetype":"postalcode"
},
  "geometry": {"coordinates":[-0.416357,51.699549],"type":"Point"}
}