{
  "type": "Feature",
  "properties": {
    "iso:country":"GB",
    "wof:name":"WD5 0XF",
    "wof:placetype":"postalcode"
},
  "geometry": {"coordinates":[-0.41635688523487,51.69954868700547],"type":"Point"}
}