{
  "type": "Feature",
  "properties": {
    "iso:country": "GB",
    "wof:name": "CW6 9UU",
    "wof:placetype": "postalcode"
  },
  "geometry": {"coordinates":[-2.668462,53.153738],"type":"Point"}
}
