{
  "type": "Feature",
  "properties": {
    "iso:country":"GB",
    "wof:name":"CW6 9UU",
    "wof:placetype":"postalcode"
},
  "geometry": {"coordinates":[-2.66850753558219,53.15374015727076],"type":"Point"}
}