{
  "type": "Feature",
  "properties": {
    "iso:country":"GB",
    "wof:name":"L35 2YQ",
    "wof:placetype":"postalcode"
},
  "geometry": {"coordinates":[-2.79205054755826,53.41531666607814],"type":"Point"}
}