{
  "type": "Feature",
  "properties": {
    "iso:country": "GB",
    "wof:name": "FY6 0NX",
    "wof:placetype": "postalcode"
  },
  "geometry": {"coordinates":[-2.956298,53.920249],"type":"Point"}
}
