{
  "type": "Feature",
  "properties": {
    "iso:country": "GB",
    "wof:name": "WD25 7LP",
    "wof:placetype": "postalcode"
  },
  "geometry": {"coordinates":[-0.420252,51.693253],"type":"Point"}
}
