{
  "type": "Feature",
  "properties": {
    "date:inception_lower":"2011-10-01",
    "date:inception_upper":"2011-10-31",
    "iso:country":"GB",
    "wof:name":"WD25 7LP",
    "wof:placetype":"postalcode"
},
  "geometry": {"coordinates":[-0.420252,51.693253],"type":"Point"}
}