{
  "type": "Feature",
  "properties": {
    "iso:country":"GB",
    "wof:name":"SE26 4AY",
    "wof:placetype":"postalcode"
},
  "geometry": {"coordinates":[-0.03992076452551,51.43050572667427],"type":"Point"}
}