{
  "type": "Feature",
  "properties": {
    "iso:country":"GB",
    "wof:name":"PR25 1TG",
    "wof:placetype":"postalcode"
},
  "geometry": {"coordinates":[-2.71564059020332,53.68754946514299],"type":"Point"}
}