{
  "type": "Feature",
  "properties": {
    "date:inception_lower": "2008-04-01",
    "date:inception_upper": "2008-04-01",
    "iso:country": "GB",
    "wof:name": "PR25 1TG",
    "wof:placetype": "postalcode"
  },
  "geometry": {"coordinates":[-2.715641,53.687549],"type":"Point"}
}
