{
  "type": "Feature",
  "properties": {
    "iso:country": "GB",
    "wof:name": "WA16 6HG",
    "wof:placetype": "postalcode"
  },
  "geometry": {"coordinates":[-2.374735,53.305591],"type":"Point"}
}
