{
  "type": "Feature",
  "properties": {
    "iso:country":"GB",
    "wof:name":"WA16 6HG",
    "wof:placetype":"postalcode"
},
  "geometry": {"coordinates":[-2.37473494154448,53.3055909463119],"type":"Point"}
}