{
  "type": "Feature",
  "properties": {
    "iso:country": "GB",
    "wof:name": "L36 2AD",
    "wof:placetype": "postalcode"
  },
  "geometry": {"coordinates":[-2.847041,53.416009],"type":"Point"}
}
