{
  "type": "Feature",
  "properties": {
    "date:inception_lower": "2015-08-01",
    "date:inception_upper": "2015-08-01",
    "iso:country": "GB",
    "wof:name": "L36 2AD",
    "wof:placetype": "postalcode"
  },
  "geometry": {"coordinates":[-2.847085,53.415988],"type":"Point"}
}
