{
  "type": "Feature",
  "properties": {
    "iso:country":"GB",
    "wof:name":"RG18 3HJ",
    "wof:placetype":"postalcode"
},
  "geometry": {"coordinates":[-1.27601391482374,51.40503779163976],"type":"Point"}
}