{
  "type": "Feature",
  "properties": {
    "iso:country":"GB",
    "wof:name":"G22 7SE",
    "wof:placetype":"postalcode"
},
  "geometry": {"coordinates":[-4.25674483120582,55.89385136801653],"type":"Point"}
}