{
  "type": "Feature",
  "properties": {
    "date:inception_lower":"2006-07-01",
    "date:inception_upper":"2006-07-31",
    "iso:country":"GB",
    "wof:name":"IP7 7GZ",
    "wof:placetype":"postalcode"
},
  "geometry": {"coordinates":[0.949308,52.110643],"type":"Point"}
}