{
  "type": "Feature",
  "properties": {
    "iso:country": "GB",
    "wof:name": "IP7 7GZ",
    "wof:placetype": "postalcode"
  },
  "geometry": {"coordinates":[0.949372,52.110712],"type":"Point"}
}
