{
  "type": "Feature",
  "properties": {
    "iso:country":"GB",
    "wof:name":"IP7 7GZ",
    "wof:placetype":"postalcode"
},
  "geometry": {"coordinates":[0.94930767678864,52.11064340187097],"type":"Point"}
}