{
  "type": "Feature",
  "properties": {
    "iso:country": "GB",
    "wof:name": "G46 7HG",
    "wof:placetype": "postalcode"
  },
  "geometry": {"coordinates":[-4.310777,55.803485],"type":"Point"}
}
