{
  "type": "Feature",
  "properties": {
    "date:inception_lower": "2007-03-01",
    "date:inception_upper": "2007-03-01",
    "iso:country": "GB",
    "wof:name": "TS28 5AB",
    "wof:placetype": "postalcode"
  },
  "geometry": {"coordinates":[-1.373679,54.724143],"type":"Point"}
}
