{
  "type": "Feature",
  "properties": {
    "iso:country":"GB",
    "wof:name":"TS28 5AB",
    "wof:placetype":"postalcode"
},
  "geometry": {"coordinates":[-1.37366548815622,54.72413288175348],"type":"Point"}
}