{
  "type": "Feature",
  "properties": {
    "date:inception_lower": "2023-02-01",
    "date:inception_upper": "2023-02-01",
    "iso:country": "GB",
    "wof:name": "MK17 9GU",
    "wof:placetype": "postalcode"
  },
  "geometry": {"coordinates":[-0.709411,51.990268],"type":"Point"}
}
