{
  "type": "Feature",
  "properties": {
    "date:inception_lower":"1980-01-01",
    "date:inception_upper":"1980-01-31",
    "iso:country":"GB",
    "wof:name":"YO14 0JP",
    "wof:placetype":"postalcode"
},
  "geometry": {"coordinates":[-0.320374,54.179722],"type":"Point"}
}