{
  "type": "Feature",
  "properties": {
    "iso:country": "GB",
    "wof:name": "YO14 0JP",
    "wof:placetype": "postalcode"
  },
  "geometry": {"coordinates":[-0.320374,54.179722],"type":"Point"}
}
