{
  "type": "Feature",
  "properties": {
    "iso:country":"GB",
    "wof:name":"LU2 7GE",
    "wof:placetype":"postalcode"
},
  "geometry": {"coordinates":[-0.41625006307558,51.91367788751298],"type":"Point"}
}