{
  "type": "Feature",
  "properties": {
    "date:inception_lower": "1994-05-01",
    "date:inception_upper": "1994-05-01",
    "iso:country": "GB",
    "wof:name": "LU2 7GE",
    "wof:placetype": "postalcode"
  },
  "geometry": {"coordinates":[-0.41625,51.913678],"type":"Point"}
}
