{
  "type": "Feature",
  "properties": {
    "iso:country":"GB",
    "wof:name":"CM16 6NH",
    "wof:placetype":"postalcode"
},
  "geometry": {"coordinates":[0.13057461481369,51.7203344930874],"type":"Point"}
}