{
  "type": "Feature",
  "properties": {
    "iso:country": "GB",
    "wof:name": "N13 4PP",
    "wof:placetype": "postalcode"
  },
  "geometry": {"coordinates":[-0.113256,51.619302],"type":"Point"}
}
