{
  "type": "Feature",
  "properties": {
    "iso:country":"GB",
    "wof:name":"N13 4PP",
    "wof:placetype":"postalcode"
},
  "geometry": {"coordinates":[-0.11325578282564,51.61930216970389],"type":"Point"}
}