{
  "type": "Feature",
  "properties": {
    "date:inception_lower":"1980-01-01",
    "date:inception_upper":"1980-01-31",
    "iso:country":"GB",
    "wof:name":"N13 4PP",
    "wof:placetype":"postalcode"
},
  "geometry": {"coordinates":[-0.113256,51.619302],"type":"Point"}
}