{
  "type": "Feature",
  "properties": {
    "date:inception_lower": "2018-05-01",
    "date:inception_upper": "2018-05-01",
    "iso:country": "GB",
    "wof:name": "NG31 8XF",
    "wof:placetype": "postalcode"
  },
  "geometry": {"coordinates":[-0.666316,52.920841],"type":"Point"}
}
