{
  "type": "Feature",
  "properties": {
    "iso:country":"GB",
    "wof:name":"CT5 2JL",
    "wof:placetype":"postalcode"
},
  "geometry": {"coordinates":[1.04882772884614,51.35914732852703],"type":"Point"}
}