{
  "type": "Feature",
  "properties": {
    "iso:country":"GB",
    "wof:name":"DY4 9JR",
    "wof:placetype":"postalcode"
},
  "geometry": {"coordinates":[-2.06262351441851,52.543009763803],"type":"Point"}
}