{
  "type": "Feature",
  "properties": {
    "iso:country": "GB",
    "wof:name": "DY4 9JR",
    "wof:placetype": "postalcode"
  },
  "geometry": {"coordinates":[-2.062623,52.54301],"type":"Point"}
}
