{
  "type": "Feature",
  "properties": {
    "iso:country":"GB",
    "wof:name":"NG32 3PY",
    "wof:placetype":"postalcode"
},
  "geometry": {"coordinates":[-0.5377160557705,52.97469396685555],"type":"Point"}
}