{
  "type": "Feature",
  "properties": {
    "iso:country":"GB",
    "wof:name":"G77 6DR",
    "wof:placetype":"postalcode"
},
  "geometry": {"coordinates":[-4.33060175634717,55.77367586083691],"type":"Point"}
}