{
  "type": "Feature",
  "properties": {
    "iso:country": "GB",
    "wof:name": "LL53 5EB",
    "wof:placetype": "postalcode"
  },
  "geometry": {"coordinates":[-4.418496,52.891833],"type":"Point"}
}
