{
  "type": "Feature",
  "properties": {
    "iso:country":"GB",
    "wof:name":"BH16 5NG",
    "wof:placetype":"postalcode"
},
  "geometry": {"coordinates":[-2.03890432990947,50.73805368414126],"type":"Point"}
}