{
  "type": "Feature",
  "properties": {
    "iso:country":"GB",
    "wof:name":"DN1 2AA",
    "wof:placetype":"postalcode"
},
  "geometry": {"coordinates":[-1.12849704438255,53.52094214385681],"type":"Point"}
}