{
  "type": "Feature",
  "properties": {
    "iso:country":"GB",
    "wof:name":"TF8 7NB",
    "wof:placetype":"postalcode"
},
  "geometry": {"coordinates":[-2.47428921584092,52.6257980796337],"type":"Point"}
}