{
  "type": "Feature",
  "properties": {
    "date:inception_lower":"1999-06-01",
    "date:inception_upper":"1999-06-30",
    "iso:country":"GB",
    "wof:name":"CF23 8SJ",
    "wof:placetype":"postalcode"
},
  "geometry": {"coordinates":[-3.154271,51.531123],"type":"Point"}
}