{
  "type": "Feature",
  "properties": {
    "iso:country":"GB",
    "wof:name":"CR4 3NA",
    "wof:placetype":"postalcode"
},
  "geometry": {"coordinates":[-0.16441440205796,51.40545376501012],"type":"Point"}
}