{
  "type": "Feature",
  "properties": {
    "iso:country":"GB",
    "wof:name":"RG19 8AU",
    "wof:placetype":"postalcode"
},
  "geometry": {"coordinates":[-1.22391548133071,51.36156172993707],"type":"Point"}
}