{
  "type": "Feature",
  "properties": {
    "date:inception_lower": "1995-07-01",
    "date:inception_upper": "1995-07-01",
    "iso:country": "GB",
    "wof:name": "RG19 8AU",
    "wof:placetype": "postalcode"
  },
  "geometry": {"coordinates":[-1.223915,51.361562],"type":"Point"}
}
