{
  "type": "Feature",
  "properties": {
    "iso:country": "GB",
    "wof:name": "NG23 6RS",
    "wof:placetype": "postalcode"
  },
  "geometry": {"coordinates":[-0.828423,53.21712],"type":"Point"}
}
