{
  "type": "Feature",
  "properties": {
    "iso:country":"GB",
    "wof:name":"NG23 6RS",
    "wof:placetype":"postalcode"
},
  "geometry": {"coordinates":[-0.82836609517682,53.21705312773211],"type":"Point"}
}