{
  "type": "Feature",
  "properties": {
    "iso:country":"GB",
    "wof:name":"DL5 6NA",
    "wof:placetype":"postalcode"
},
  "geometry": {"coordinates":[-1.56158108539163,54.59562928338682],"type":"Point"}
}