{
  "type": "Feature",
  "properties": {
    "iso:country": "GB",
    "wof:name": "DL5 6NA",
    "wof:placetype": "postalcode"
  },
  "geometry": {"coordinates":[-1.561581,54.595629],"type":"Point"}
}
