{
  "type": "Feature",
  "properties": {
    "iso:country":"GB",
    "wof:name":"SE26 6XU",
    "wof:placetype":"postalcode"
},
  "geometry": {"coordinates":[-0.0719582502223,51.42812349107503],"type":"Point"}
}