{
  "type": "Feature",
  "properties": {
    "iso:country": "GB",
    "wof:name": "WF3 2NB",
    "wof:placetype": "postalcode"
  },
  "geometry": {"coordinates":[-1.523366,53.72775],"type":"Point"}
}
