{
  "type": "Feature",
  "properties": {
    "iso:country":"GB",
    "wof:name":"WF3 2NB",
    "wof:placetype":"postalcode"
},
  "geometry": {"coordinates":[-1.52336603571467,53.72775027699145],"type":"Point"}
}