{
  "type": "Feature",
  "properties": {
    "iso:country":"GB",
    "wof:name":"AB43 9TW",
    "wof:placetype":"postalcode"
},
  "geometry": {"coordinates":[-2.02287593244341,57.68185279093284],"type":"Point"}
}