{
  "type": "Feature",
  "properties": {
    "iso:country":"GB",
    "wof:name":"YO23 1AE",
    "wof:placetype":"postalcode"
},
  "geometry": {"coordinates":[-1.08928202239736,53.95370143405348],"type":"Point"}
}