{
  "type": "Feature",
  "properties": {
    "iso:country":"GB",
    "wof:name":"L4 3QA",
    "wof:placetype":"postalcode"
},
  "geometry": {"coordinates":[-2.97133876365936,53.43925138641715],"type":"Point"}
}