{
  "type": "Feature",
  "properties": {
    "date:inception_lower": "1980-01-01",
    "date:inception_upper": "1980-01-01",
    "iso:country": "GB",
    "wof:name": "L4 3QA",
    "wof:placetype": "postalcode"
  },
  "geometry": {"coordinates":[-2.971338,53.439268],"type":"Point"}
}
