{
  "type": "Feature",
  "properties": {
    "iso:country":"GB",
    "wof:name":"YO42 2BB",
    "wof:placetype":"postalcode"
},
  "geometry": {"coordinates":[-0.77920441925447,53.93152733432223],"type":"Point"}
}