{
  "type": "Feature",
  "properties": {
    "iso:country": "GB",
    "wof:name": "CW5 5DQ",
    "wof:placetype": "postalcode"
  },
  "geometry": {"coordinates":[-2.52116,53.06791],"type":"Point"}
}
