{
  "type": "Feature",
  "properties": {
    "iso:country": "GB",
    "wof:name": "CV37 6RJ",
    "wof:placetype": "postalcode"
  },
  "geometry": {"coordinates":[-1.705651,52.198914],"type":"Point"}
}
