{
  "type": "Feature",
  "properties": {
    "date:inception_lower":"2000-12-01",
    "date:inception_upper":"2000-12-31",
    "iso:country":"GB",
    "wof:name":"CV37 6RJ",
    "wof:placetype":"postalcode"
},
  "geometry": {"coordinates":[-1.705651,52.198914],"type":"Point"}
}