{
  "type": "Feature",
  "properties": {
    "date:inception_lower": "2022-05-01",
    "date:inception_upper": "2022-05-01",
    "iso:country": "GB",
    "wof:name": "HU16 5GP",
    "wof:placetype": "postalcode"
  },
  "geometry": {"coordinates":[-0.43488,53.784577],"type":"Point"}
}
