{
  "type": "Feature",
  "properties": {
    "date:inception_lower": "1980-01-01",
    "date:inception_upper": "1980-01-01",
    "iso:country": "GB",
    "wof:name": "IP13 8EB",
    "wof:placetype": "postalcode"
  },
  "geometry": {"coordinates":[1.36421,52.300252],"type":"Point"}
}
