{
  "type": "Feature",
  "properties": {
    "iso:country":"GB",
    "wof:name":"LU4 8DE",
    "wof:placetype":"postalcode"
},
  "geometry": {"coordinates":[-0.45000528690292,51.89187297537981],"type":"Point"}
}