{
  "type": "Feature",
  "properties": {
    "iso:country": "GB",
    "wof:name": "CT10 2YW",
    "wof:placetype": "postalcode"
  },
  "geometry": {"coordinates":[1.423693,51.351138],"type":"Point"}
}
