{
  "type": "Feature",
  "properties": {
    "iso:country":"GB",
    "wof:name":"SR2 9BU",
    "wof:placetype":"postalcode"
},
  "geometry": {"coordinates":[-1.38941468490769,54.89202016183973],"type":"Point"}
}