{
  "type": "Feature",
  "properties": {
    "iso:country": "GB",
    "wof:name": "IP1 1SB",
    "wof:placetype": "postalcode"
  },
  "geometry": {"coordinates":[1.145186,52.052268],"type":"Point"}
}
