{
  "type": "Feature",
  "properties": {
    "date:inception_lower": "2019-09-01",
    "date:inception_upper": "2019-09-01",
    "iso:country": "GB",
    "wof:name": "IP1 1SB",
    "wof:placetype": "postalcode"
  },
  "geometry": {"coordinates":[1.145265,52.052355],"type":"Point"}
}
