{
  "type": "Feature",
  "properties": {
    "date:inception_lower":"2018-03-01",
    "date:inception_upper":"2018-03-31",
    "iso:country":"GB",
    "wof:name":"IP1 1SB",
    "wof:placetype":"postalcode"
},
  "geometry": {"coordinates":[1.145186,52.052268],"type":"Point"}
}