{
  "type": "Feature",
  "properties": {
    "iso:country": "GB",
    "wof:name": "IP1 1SB",
    "wof:placetype": "postalcode"
  },
  "geometry": {"coordinates":[1.145265,52.052355],"type":"Point"}
}
