{
  "type": "Feature",
  "properties": {
    "iso:country": "GB",
    "wof:name": "PH2 6DE",
    "wof:placetype": "postalcode"
  },
  "geometry": {"coordinates":[-3.377345,56.479084],"type":"Point"}
}
