{
  "type": "Feature",
  "properties": {
    "iso:country":"GB",
    "wof:name":"PH2 6DE",
    "wof:placetype":"postalcode"
},
  "geometry": {"coordinates":[-3.37977776101814,56.47989302636832],"type":"Point"}
}