{
  "type": "Feature",
  "properties": {
    "date:inception_lower": "2018-07-01",
    "date:inception_upper": "2018-07-01",
    "iso:country": "GB",
    "wof:name": "CT16 3FS",
    "wof:placetype": "postalcode"
  },
  "geometry": {"coordinates":[1.306538,51.160474],"type":"Point"}
}
