{
  "type": "Feature",
  "properties": {
    "iso:country": "GB",
    "wof:name": "CT16 3FS",
    "wof:placetype": "postalcode"
  },
  "geometry": {"coordinates":[1.306479,51.160439],"type":"Point"}
}
