{
  "type": "Feature",
  "properties": {
    "iso:country":"GB",
    "wof:name":"M25 0DD",
    "wof:placetype":"postalcode"
},
  "geometry": {"coordinates":[-2.25217848368437,53.52453297713163],"type":"Point"}
}