{
  "type": "Feature",
  "properties": {
    "iso:country":"GB",
    "wof:name":"BR7 6LR",
    "wof:placetype":"postalcode"
},
  "geometry": {"coordinates":[0.08306215997897,51.4142565523647],"type":"Point"}
}