{
  "type": "Feature",
  "properties": {
    "iso:country":"GB",
    "wof:name":"CV34 6NP",
    "wof:placetype":"postalcode"
},
  "geometry": {"coordinates":[-1.61188358829593,52.27248071955511],"type":"Point"}
}