{
  "type": "Feature",
  "properties": {
    "iso:country": "GB",
    "wof:name": "CV34 6NP",
    "wof:placetype": "postalcode"
  },
  "geometry": {"coordinates":[-1.611872,52.272495],"type":"Point"}
}
