{
  "type": "Feature",
  "properties": {
    "iso:country":"GB",
    "wof:name":"NG6 0DD",
    "wof:placetype":"postalcode"
},
  "geometry": {"coordinates":[-1.18101508619883,52.98718466698118],"type":"Point"}
}