{
  "type": "Feature",
  "properties": {
    "iso:country":"GB",
    "wof:name":"NR30 4AZ",
    "wof:placetype":"postalcode"
},
  "geometry": {"coordinates":[1.72885869197933,52.62493150967082],"type":"Point"}
}