{
  "type": "Feature",
  "properties": {
    "date:inception_lower": "1980-01-01",
    "date:inception_upper": "1980-01-01",
    "iso:country": "GB",
    "wof:name": "L13 4DR",
    "wof:placetype": "postalcode"
  },
  "geometry": {"coordinates":[-2.907349,53.411986],"type":"Point"}
}
