{
  "type": "Feature",
  "properties": {
    "iso:country":"GB",
    "wof:name":"L13 4DR",
    "wof:placetype":"postalcode"
},
  "geometry": {"coordinates":[-2.90703504915651,53.41205348753966],"type":"Point"}
}