{
  "type": "Feature",
  "properties": {
    "iso:country":"GB",
    "wof:name":"HA6 2DW",
    "wof:placetype":"postalcode"
},
  "geometry": {"coordinates":[-0.43444355942112,51.61274860815904],"type":"Point"}
}