{
  "type": "Feature",
  "properties": {
    "date:inception_lower":"1981-06-01",
    "date:inception_upper":"1981-06-30",
    "iso:country":"GB",
    "wof:name":"BA9 9AR",
    "wof:placetype":"postalcode"
},
  "geometry": {"coordinates":[-2.420284,51.057631],"type":"Point"}
}