{
  "type": "Feature",
  "properties": {
    "iso:country": "GB",
    "wof:name": "BA9 9AR",
    "wof:placetype": "postalcode"
  },
  "geometry": {"coordinates":[-2.420284,51.057631],"type":"Point"}
}
