{
  "type": "Feature",
  "properties": {
    "iso:country":"GB",
    "wof:name":"SP4 9RE",
    "wof:placetype":"postalcode"
},
  "geometry": {"coordinates":[-1.79774397755511,51.23611996252102],"type":"Point"}
}