{
  "type": "Feature",
  "properties": {
    "date:inception_lower": "1980-01-01",
    "date:inception_upper": "1980-01-01",
    "iso:country": "GB",
    "wof:name": "BB6 7QX",
    "wof:placetype": "postalcode"
  },
  "geometry": {"coordinates":[-2.406722,53.787867],"type":"Point"}
}
