{
  "type": "Feature",
  "properties": {
    "iso:country":"GB",
    "wof:name":"BB6 7QX",
    "wof:placetype":"postalcode"
},
  "geometry": {"coordinates":[-2.40672251508646,53.78786664255028],"type":"Point"}
}