{
  "type": "Feature",
  "properties": {
    "iso:country":"GB",
    "wof:name":"WF9 4UH",
    "wof:placetype":"postalcode"
},
  "geometry": {"coordinates":[-1.34580954835254,53.61703071611026],"type":"Point"}
}