{
  "type": "Feature",
  "properties": {
    "iso:country":"GB",
    "wof:name":"TD7 5DF",
    "wof:placetype":"postalcode"
},
  "geometry": {"coordinates":[-2.84432394498916,55.55033707592899],"type":"Point"}
}