{
  "type": "Feature",
  "properties": {
    "iso:country":"GB",
    "wof:name":"UB9 4DS",
    "wof:placetype":"postalcode"
},
  "geometry": {"coordinates":[-0.50164664917327,51.56711878725452],"type":"Point"}
}