{
  "type": "Feature",
  "properties": {
    "date:inception_lower": "1980-01-01",
    "date:inception_upper": "1980-01-01",
    "iso:country": "GB",
    "wof:name": "UB9 4DS",
    "wof:placetype": "postalcode"
  },
  "geometry": {"coordinates":[-0.501647,51.567119],"type":"Point"}
}
