{
  "type": "Feature",
  "properties": {
    "iso:country": "GB",
    "wof:name": "GU34 4LA",
    "wof:placetype": "postalcode"
  },
  "geometry": {"coordinates":[-0.920559,51.179533],"type":"Point"}
}
