{
  "type": "Feature",
  "properties": {
    "iso:country": "GB",
    "wof:name": "HR6 8HS",
    "wof:placetype": "postalcode"
  },
  "geometry": {"coordinates":[-2.745694,52.225422],"type":"Point"}
}
