{
  "type": "Feature",
  "properties": {
    "iso:country":"GB",
    "wof:name":"HR6 8HS",
    "wof:placetype":"postalcode"
},
  "geometry": {"coordinates":[-2.74569422394256,52.22542238152128],"type":"Point"}
}