{
  "type": "Feature",
  "properties": {
    "date:inception_lower": "2021-09-01",
    "date:inception_upper": "2021-09-01",
    "iso:country": "GB",
    "wof:name": "LE8 8EP",
    "wof:placetype": "postalcode"
  },
  "geometry": {"coordinates":[-1.042173,52.535719],"type":"Point"}
}
