{
  "type": "Feature",
  "properties": {
    "iso:country":"GB",
    "wof:name":"RM14 1AX",
    "wof:placetype":"postalcode"
},
  "geometry": {"coordinates":[0.25655262493869,51.57044554864174],"type":"Point"}
}