{
  "type": "Feature",
  "properties": {
    "date:inception_lower": "2007-05-01",
    "date:inception_upper": "2007-05-01",
    "iso:country": "GB",
    "wof:name": "KT19 8FD",
    "wof:placetype": "postalcode"
  },
  "geometry": {"coordinates":[-0.279474,51.343937],"type":"Point"}
}
