{
  "type": "Feature",
  "properties": {
    "iso:country":"GB",
    "wof:name":"KT19 8FD",
    "wof:placetype":"postalcode"
},
  "geometry": {"coordinates":[-0.27947412394847,51.34393691734228],"type":"Point"}
}