{
  "type": "Feature",
  "properties": {
    "iso:country":"GB",
    "wof:name":"PE29 3AR",
    "wof:placetype":"postalcode"
},
  "geometry": {"coordinates":[-0.18295707868002,52.32750946361281],"type":"Point"}
}