{
  "type": "Feature",
  "properties": {
    "iso:country":"GB",
    "wof:name":"BS20 6QW",
    "wof:placetype":"postalcode"
},
  "geometry": {"coordinates":[-2.77226489247155,51.47665113633173],"type":"Point"}
}