{
  "type": "Feature",
  "properties": {
    "iso:country": "GB",
    "wof:name": "BS20 6QW",
    "wof:placetype": "postalcode"
  },
  "geometry": {"coordinates":[-2.772265,51.476651],"type":"Point"}
}
