{
  "type": "Feature",
  "properties": {
    "date:inception_lower": "2021-01-01",
    "date:inception_upper": "2021-01-01",
    "iso:country": "GB",
    "wof:name": "TN23 8AZ",
    "wof:placetype": "postalcode"
  },
  "geometry": {"coordinates":[0.821415,51.134461],"type":"Point"}
}
