{
  "type": "Feature",
  "properties": {
    "iso:country": "GB",
    "wof:name": "TF10 8JL",
    "wof:placetype": "postalcode"
  },
  "geometry": {"coordinates":[-2.407505,52.772417],"type":"Point"}
}
