{
  "type": "Feature",
  "properties": {
    "iso:country":"GB",
    "wof:name":"SS0 8FG",
    "wof:placetype":"postalcode"
},
  "geometry": {"coordinates":[0.68656318000239,51.53660784443436],"type":"Point"}
}