{
  "type": "Feature",
  "properties": {
    "date:inception_lower":"2011-01-01",
    "date:inception_upper":"2011-01-31",
    "iso:country":"GB",
    "wof:name":"SS0 8FG",
    "wof:placetype":"postalcode"
},
  "geometry": {"coordinates":[0.68668,51.536628],"type":"Point"}
}