{
  "type": "Feature",
  "properties": {
    "iso:country":"GB",
    "wof:name":"LL58 8RT",
    "wof:placetype":"postalcode"
},
  "geometry": {"coordinates":[-4.07003932397379,53.29889099098636],"type":"Point"}
}