{
  "type": "Feature",
  "properties": {
    "date:inception_lower": "2006-09-01",
    "date:inception_upper": "2006-09-01",
    "iso:country": "GB",
    "wof:name": "CB23 6FH",
    "wof:placetype": "postalcode"
  },
  "geometry": {"coordinates":[-0.082107,52.218205],"type":"Point"}
}
