{
  "type": "Feature",
  "properties": {
    "date:inception_lower":"1999-06-01",
    "date:inception_upper":"1999-06-30",
    "iso:country":"GB",
    "wof:name":"CH48 4EY",
    "wof:placetype":"postalcode"
},
  "geometry": {"coordinates":[-3.186966,53.373471],"type":"Point"}
}