{
  "type": "Feature",
  "properties": {
    "iso:country": "GB",
    "wof:name": "CH48 4EY",
    "wof:placetype": "postalcode"
  },
  "geometry": {"coordinates":[-3.186966,53.373471],"type":"Point"}
}
