{
  "type": "Feature",
  "properties": {
    "date:inception_lower": "1980-01-01",
    "date:inception_upper": "1980-01-01",
    "iso:country": "GB",
    "wof:name": "ST7 2QX",
    "wof:placetype": "postalcode"
  },
  "geometry": {"coordinates":[-2.29433,53.08958],"type":"Point"}
}
