{
  "type": "Feature",
  "properties": {
    "iso:country":"GB",
    "wof:name":"ST7 2QX",
    "wof:placetype":"postalcode"
},
  "geometry": {"coordinates":[-2.29433040805631,53.08957968646566],"type":"Point"}
}