{
  "type": "Feature",
  "properties": {
    "iso:country":"GB",
    "wof:name":"PE7 3SL",
    "wof:placetype":"postalcode"
},
  "geometry": {"coordinates":[-0.33174091608552,52.48668784451965],"type":"Point"}
}