{
  "type": "Feature",
  "properties": {
    "date:inception_lower":"1980-01-01",
    "date:inception_upper":"1980-01-31",
    "iso:country":"GB",
    "wof:name":"PE7 3SL",
    "wof:placetype":"postalcode"
},
  "geometry": {"coordinates":[-0.331741,52.486688],"type":"Point"}
}