{
  "type": "Feature",
  "properties": {
    "iso:country": "GB",
    "wof:name": "PE7 3SL",
    "wof:placetype": "postalcode"
  },
  "geometry": {"coordinates":[-0.331741,52.486688],"type":"Point"}
}
