{
  "type": "Feature",
  "properties": {
    "date:inception_lower": "1995-07-01",
    "date:inception_upper": "1995-07-01",
    "iso:country": "GB",
    "wof:name": "LL22 7HZ",
    "wof:placetype": "postalcode"
  },
  "geometry": {"coordinates":[-3.568171,53.284225],"type":"Point"}
}
