{
  "type": "Feature",
  "properties": {
    "date:inception_lower":"1995-07-01",
    "date:inception_upper":"1995-07-31",
    "iso:country":"GB",
    "wof:name":"LL22 7HZ",
    "wof:placetype":"postalcode"
},
  "geometry": {"coordinates":[-3.568871,53.284899],"type":"Point"}
}