{
  "type": "Feature",
  "properties": {
    "iso:country":"GB",
    "wof:name":"B69 1UN",
    "wof:placetype":"postalcode"
},
  "geometry": {"coordinates":[-2.05946417265114,52.50755527438849],"type":"Point"}
}