{
  "type": "Feature",
  "properties": {
    "iso:country":"GB",
    "wof:name":"TS7 0QQ",
    "wof:placetype":"postalcode"
},
  "geometry": {"coordinates":[-1.18494833615459,54.52548597955877],"type":"Point"}
}