{
  "type": "Feature",
  "properties": {
    "iso:country": "GB",
    "wof:name": "IP22 1DZ",
    "wof:placetype": "postalcode"
  },
  "geometry": {"coordinates":[1.001302,52.340596],"type":"Point"}
}
