{
  "type": "Feature",
  "properties": {
    "date:inception_lower": "1980-01-01",
    "date:inception_upper": "1980-01-01",
    "iso:country": "GB",
    "wof:name": "IP22 1DZ",
    "wof:placetype": "postalcode"
  },
  "geometry": {"coordinates":[1.001575,52.340743],"type":"Point"}
}
