{
  "type": "Feature",
  "properties": {
    "iso:country":"GB",
    "wof:name":"IP22 1DZ",
    "wof:placetype":"postalcode"
},
  "geometry": {"coordinates":[1.00130185202892,52.34059625699117],"type":"Point"}
}