{
  "type": "Feature",
  "properties": {
    "iso:country":"GB",
    "wof:name":"BD7 2BY",
    "wof:placetype":"postalcode"
},
  "geometry": {"coordinates":[-1.77744185669556,53.78969942037084],"type":"Point"}
}