{
  "type": "Feature",
  "properties": {
    "iso:country":"GB",
    "wof:name":"OX3 0JA",
    "wof:placetype":"postalcode"
},
  "geometry": {"coordinates":[-1.23491176565835,51.7634843079266],"type":"Point"}
}