{
  "type": "Feature",
  "properties": {
    "iso:country":"GB",
    "wof:name":"SA73 2PF",
    "wof:placetype":"postalcode"
},
  "geometry": {"coordinates":[-5.02889761367558,51.72023914809489],"type":"Point"}
}