{
  "type": "Feature",
  "properties": {
    "date:inception_lower": "1998-12-01",
    "date:inception_upper": "1998-12-01",
    "iso:country": "GB",
    "wof:name": "SA73 2PF",
    "wof:placetype": "postalcode"
  },
  "geometry": {"coordinates":[-5.028898,51.720239],"type":"Point"}
}
