{
  "type": "Feature",
  "properties": {
    "iso:country": "GB",
    "wof:name": "DN39 6YS",
    "wof:placetype": "postalcode"
  },
  "geometry": {"coordinates":[-0.332921,53.585149],"type":"Point"}
}
