{
  "type": "Feature",
  "properties": {
    "iso:country":"GB",
    "wof:name":"DN39 6YS",
    "wof:placetype":"postalcode"
},
  "geometry": {"coordinates":[-0.33292119365248,53.58514928846254],"type":"Point"}
}