{
  "type": "Feature",
  "properties": {
    "iso:country":"GB",
    "wof:name":"PA13 4ET",
    "wof:placetype":"postalcode"
},
  "geometry": {"coordinates":[-4.62744694923449,55.89434119139486],"type":"Point"}
}