{
  "type": "Feature",
  "properties": {
    "date:inception_lower":"1980-01-01",
    "date:inception_upper":"1980-01-31",
    "iso:country":"GB",
    "wof:name":"PA13 4ET",
    "wof:placetype":"postalcode"
},
  "geometry": {"coordinates":[-4.627447,55.894341],"type":"Point"}
}