{
  "type": "Feature",
  "properties": {
    "iso:country":"GB",
    "wof:name":"NR18 9BS",
    "wof:placetype":"postalcode"
},
  "geometry": {"coordinates":[1.09221858888035,52.56255355209828],"type":"Point"}
}