{
  "type": "Feature",
  "properties": {
    "iso:country":"GB",
    "wof:name":"MK18 7EN",
    "wof:placetype":"postalcode"
},
  "geometry": {"coordinates":[-0.97867596953586,51.99132648843468],"type":"Point"}
}