{
  "type": "Feature",
  "properties": {
    "iso:country":"GB",
    "wof:name":"CM24 8EY",
    "wof:placetype":"postalcode"
},
  "geometry": {"coordinates":[0.19122563334524,51.89739685678929],"type":"Point"}
}