{
  "type": "Feature",
  "properties": {
    "date:inception_lower":"1980-01-01",
    "date:inception_upper":"1980-01-31",
    "iso:country":"GB",
    "wof:name":"CM24 8EY",
    "wof:placetype":"postalcode"
},
  "geometry": {"coordinates":[0.191226,51.897397],"type":"Point"}
}