{
  "type": "Feature",
  "properties": {
    "date:inception_lower": "1987-04-01",
    "date:inception_upper": "1987-04-01",
    "iso:country": "GB",
    "wof:name": "SG8 6LQ",
    "wof:placetype": "postalcode"
  },
  "geometry": {"coordinates":[0.005303,52.095857],"type":"Point"}
}
