{
  "type": "Feature",
  "properties": {
    "iso:country":"GB",
    "wof:name":"SG8 6LQ",
    "wof:placetype":"postalcode"
},
  "geometry": {"coordinates":[0.00530339086163,52.0958574390747],"type":"Point"}
}