{
  "type": "Feature",
  "properties": {
    "iso:country":"GB",
    "wof:name":"SE27 9UF",
    "wof:placetype":"postalcode"
},
  "geometry": {"coordinates":[-0.09937396702203,51.42853530876412],"type":"Point"}
}