{
  "type": "Feature",
  "properties": {
    "date:inception_lower": "1987-04-01",
    "date:inception_upper": "1987-04-01",
    "iso:country": "GB",
    "wof:name": "CT18 7NJ",
    "wof:placetype": "postalcode"
  },
  "geometry": {"coordinates":[1.151164,51.113811],"type":"Point"}
}
