{
  "type": "Feature",
  "properties": {
    "iso:country":"GB",
    "wof:name":"CT18 7NJ",
    "wof:placetype":"postalcode"
},
  "geometry": {"coordinates":[1.15116422579236,51.11381137345389],"type":"Point"}
}