{
  "type": "Feature",
  "properties": {
    "iso:country": "GB",
    "wof:name": "NN7 2BE",
    "wof:placetype": "postalcode"
  },
  "geometry": {"coordinates":[-0.800962,52.183665],"type":"Point"}
}
