{
  "type": "Feature",
  "properties": {
    "date:inception_lower": "1980-01-01",
    "date:inception_upper": "1980-01-01",
    "iso:country": "GB",
    "wof:name": "NN7 2BE",
    "wof:placetype": "postalcode"
  },
  "geometry": {"coordinates":[-0.801168,52.183631],"type":"Point"}
}
