{
  "type": "Feature",
  "properties": {
    "iso:country":"GB",
    "wof:name":"SN25 2FT",
    "wof:placetype":"postalcode"
},
  "geometry": {"coordinates":[-1.81401314463241,51.60222187785513],"type":"Point"}
}