{
  "type": "Feature",
  "properties": {
    "date:inception_lower": "1993-01-01",
    "date:inception_upper": "1993-01-01",
    "iso:country": "GB",
    "wof:name": "PE31 7SW",
    "wof:placetype": "postalcode"
  },
  "geometry": {"coordinates":[0.481963,52.907286],"type":"Point"}
}
