{
  "type": "Feature",
  "properties": {
    "iso:country": "GB",
    "wof:name": "HS6 5EW",
    "wof:placetype": "postalcode"
  },
  "geometry": {"coordinates":[-7.40276,57.574758],"type":"Point"}
}
