{
  "type": "Feature",
  "properties": {
    "iso:country":"GB",
    "wof:name":"HS6 5EW",
    "wof:placetype":"postalcode"
},
  "geometry": {"coordinates":[-7.40269612893735,57.5748312167076],"type":"Point"}
}