{
  "type": "Feature",
  "properties": {
    "iso:country":"GB",
    "wof:name":"LL30 1RF",
    "wof:placetype":"postalcode"
},
  "geometry": {"coordinates":[-3.81743350235709,53.30493301960616],"type":"Point"}
}