{
  "type": "Feature",
  "properties": {
    "iso:country": "GB",
    "wof:name": "LL30 1RF",
    "wof:placetype": "postalcode"
  },
  "geometry": {"coordinates":[-3.817433,53.304933],"type":"Point"}
}
