{
  "type": "Feature",
  "properties": {
    "date:inception_lower":"1998-06-01",
    "date:inception_upper":"1998-06-30",
    "iso:country":"GB",
    "wof:name":"LL30 1RF",
    "wof:placetype":"postalcode"
},
  "geometry": {"coordinates":[-3.817433,53.304933],"type":"Point"}
}