{
  "type": "Feature",
  "properties": {
    "date:inception_lower": "1980-01-01",
    "date:inception_upper": "1980-01-01",
    "iso:country": "GB",
    "wof:name": "L10 3LF",
    "wof:placetype": "postalcode"
  },
  "geometry": {"coordinates":[-2.946998,53.486701],"type":"Point"}
}
