{
  "type": "Feature",
  "properties": {
    "date:inception_lower": "1980-01-01",
    "date:inception_upper": "1980-01-01",
    "iso:country": "GB",
    "wof:name": "HP12 3PY",
    "wof:placetype": "postalcode"
  },
  "geometry": {"coordinates":[-0.772529,51.620289],"type":"Point"}
}
