{
  "type": "Feature",
  "properties": {
    "date:inception_lower": "2023-02-01",
    "date:inception_upper": "2023-02-01",
    "iso:country": "GB",
    "wof:name": "GL14 1FA",
    "wof:placetype": "postalcode"
  },
  "geometry": {"coordinates":[-2.448448,51.807704],"type":"Point"}
}
