{
  "type": "Feature",
  "properties": {
    "iso:country":"GB",
    "wof:name":"RG4 8TA",
    "wof:placetype":"postalcode"
},
  "geometry": {"coordinates":[-0.9675050986001,51.48926443056006],"type":"Point"}
}