{
  "type": "Feature",
  "properties": {
    "iso:country":"GB",
    "wof:name":"OX16 1AG",
    "wof:placetype":"postalcode"
},
  "geometry": {"coordinates":[-1.36374751829007,52.07805396957463],"type":"Point"}
}