{
  "type": "Feature",
  "properties": {
    "iso:country":"GB",
    "wof:name":"HG2 9PE",
    "wof:placetype":"postalcode"
},
  "geometry": {"coordinates":[-1.54544547155923,53.97236250762275],"type":"Point"}
}