{
  "type": "Feature",
  "properties": {
    "date:inception_lower": "2008-03-01",
    "date:inception_upper": "2008-03-01",
    "iso:country": "GB",
    "wof:name": "PO20 1AF",
    "wof:placetype": "postalcode"
  },
  "geometry": {"coordinates":[-0.777028,50.811651],"type":"Point"}
}
