{
  "type": "Feature",
  "properties": {
    "iso:country":"GB",
    "wof:name":"PO20 1AF",
    "wof:placetype":"postalcode"
},
  "geometry": {"coordinates":[-0.77702780282145,50.81165134629472],"type":"Point"}
}