{
  "type": "Feature",
  "properties": {
    "iso:country": "GB",
    "wof:name": "L23 3DH",
    "wof:placetype": "postalcode"
  },
  "geometry": {"coordinates":[-3.027321,53.485202],"type":"Point"}
}
