{
  "type": "Feature",
  "properties": {
    "iso:country":"GB",
    "wof:name":"L23 3DH",
    "wof:placetype":"postalcode"
},
  "geometry": {"coordinates":[-3.02732062193255,53.48520151353239],"type":"Point"}
}