{
  "type": "Feature",
  "properties": {
    "iso:country":"GB",
    "wof:name":"B36 8UW",
    "wof:placetype":"postalcode"
},
  "geometry": {"coordinates":[-1.82280258446356,52.5039949425694],"type":"Point"}
}