{
  "type": "Feature",
  "properties": {
    "date:inception_lower": "1980-01-01",
    "date:inception_upper": "1980-01-01",
    "iso:country": "GB",
    "wof:name": "B36 8UW",
    "wof:placetype": "postalcode"
  },
  "geometry": {"coordinates":[-1.822803,52.503995],"type":"Point"}
}
