{
  "type": "Feature",
  "properties": {
    "iso:country":"GB",
    "wof:name":"WV6 7HY",
    "wof:placetype":"postalcode"
},
  "geometry": {"coordinates":[-2.29478487918899,52.6065046731859],"type":"Point"}
}