{
  "type": "Feature",
  "properties": {
    "iso:country":"GB",
    "wof:name":"ST7 4JA",
    "wof:placetype":"postalcode"
},
  "geometry": {"coordinates":[-2.23919464988945,53.07985137113788],"type":"Point"}
}