{
  "type": "Feature",
  "properties": {
    "iso:country": "GB",
    "wof:name": "ST7 4JA",
    "wof:placetype": "postalcode"
  },
  "geometry": {"coordinates":[-2.239195,53.079851],"type":"Point"}
}
