{
  "type": "Feature",
  "properties": {
    "iso:country": "GB",
    "wof:name": "MK7 6AA",
    "wof:placetype": "postalcode"
  },
  "geometry": {"coordinates":[-0.709747,52.024914],"type":"Point"}
}
