{
  "type": "Feature",
  "properties": {
    "iso:country":"GB",
    "wof:name":"FY3 8QB",
    "wof:placetype":"postalcode"
},
  "geometry": {"coordinates":[-3.0060694548086,53.82565409688149],"type":"Point"}
}