{
  "type": "Feature",
  "properties": {
    "date:inception_lower": "1980-01-01",
    "date:inception_upper": "1980-01-01",
    "iso:country": "GB",
    "wof:name": "FY3 8QB",
    "wof:placetype": "postalcode"
  },
  "geometry": {"coordinates":[-3.006033,53.825642],"type":"Point"}
}
