{
  "type": "Feature",
  "properties": {
    "date:inception_lower": "1980-01-01",
    "date:inception_upper": "1980-01-01",
    "iso:country": "GB",
    "wof:name": "SL9 7PG",
    "wof:placetype": "postalcode"
  },
  "geometry": {"coordinates":[-0.5662,51.578581],"type":"Point"}
}
