{
  "type": "Feature",
  "properties": {
    "date:inception_lower": "2002-06-01",
    "date:inception_upper": "2002-06-01",
    "iso:country": "GB",
    "wof:name": "NN29 7QG",
    "wof:placetype": "postalcode"
  },
  "geometry": {"coordinates":[-0.67145,52.253113],"type":"Point"}
}
