{
  "type": "Feature",
  "properties": {
    "iso:country":"GB",
    "wof:name":"CA14 5UH",
    "wof:placetype":"postalcode"
},
  "geometry": {"coordinates":[-3.53830235219031,54.59613486858751],"type":"Point"}
}