{
  "type": "Feature",
  "properties": {
    "iso:country": "GB",
    "wof:name": "CA14 5UH",
    "wof:placetype": "postalcode"
  },
  "geometry": {"coordinates":[-3.538302,54.596135],"type":"Point"}
}
