{
  "type": "Feature",
  "properties": {
    "date:inception_lower": "1980-01-01",
    "date:inception_upper": "1980-01-01",
    "iso:country": "GB",
    "wof:name": "CA14 5UH",
    "wof:placetype": "postalcode"
  },
  "geometry": {"coordinates":[-3.538302,54.596135],"type":"Point"}
}
