{
  "type": "Feature",
  "properties": {
    "date:inception_lower":"1992-08-01",
    "date:inception_upper":"1992-08-31",
    "iso:country":"GB",
    "wof:name":"DE72 2WD",
    "wof:placetype":"postalcode"
},
  "geometry": {"coordinates":[-1.360862,52.869699],"type":"Point"}
}