{
  "type": "Feature",
  "properties": {
    "iso:country": "GB",
    "wof:name": "DE72 2WD",
    "wof:placetype": "postalcode"
  },
  "geometry": {"coordinates":[-1.360862,52.869699],"type":"Point"}
}
