{
  "type": "Feature",
  "properties": {
    "iso:country": "GB",
    "wof:name": "WF2 9LX",
    "wof:placetype": "postalcode"
  },
  "geometry": {"coordinates":[-1.534996,53.686019],"type":"Point"}
}
