{
  "type": "Feature",
  "properties": {
    "iso:country":"GB",
    "wof:name":"WF2 9LX",
    "wof:placetype":"postalcode"
},
  "geometry": {"coordinates":[-1.53499653191336,53.68601888121791],"type":"Point"}
}