{
  "type": "Feature",
  "properties": {
    "iso:country":"GB",
    "wof:name":"LN6 4RT",
    "wof:placetype":"postalcode"
},
  "geometry": {"coordinates":[-0.65168550626918,53.21900595708343],"type":"Point"}
}