{
  "type": "Feature",
  "properties": {
    "iso:country": "GB",
    "wof:name": "LN6 4RT",
    "wof:placetype": "postalcode"
  },
  "geometry": {"coordinates":[-0.651685,53.219006],"type":"Point"}
}
