{
  "type": "Feature",
  "properties": {
    "iso:country":"GB",
    "wof:name":"CV2 5FZ",
    "wof:placetype":"postalcode"
},
  "geometry": {"coordinates":[-1.45741646974689,52.41281280908289],"type":"Point"}
}