{
  "type": "Feature",
  "properties": {
    "iso:country": "GB",
    "wof:name": "IP6 8JW",
    "wof:placetype": "postalcode"
  },
  "geometry": {"coordinates":[1.07978,52.13057],"type":"Point"}
}
