{
  "type": "Feature",
  "properties": {
    "iso:country":"GB",
    "wof:name":"HX3 6DJ",
    "wof:placetype":"postalcode"
},
  "geometry": {"coordinates":[-1.86090904537427,53.73023451826236],"type":"Point"}
}