{
  "type": "Feature",
  "properties": {
    "date:inception_lower": "2020-04-01",
    "date:inception_upper": "2020-04-01",
    "iso:country": "GB",
    "wof:name": "LE7 9WQ",
    "wof:placetype": "postalcode"
  },
  "geometry": {"coordinates":[-1.038168,52.638076],"type":"Point"}
}
