{
  "type": "Feature",
  "properties": {
    "iso:country":"GB",
    "wof:name":"WN2 2NY",
    "wof:placetype":"postalcode"
},
  "geometry": {"coordinates":[-2.59945006683713,53.54437354603353],"type":"Point"}
}