{
  "type": "Feature",
  "properties": {
    "iso:country":"GB",
    "wof:name":"PL11 2JH",
    "wof:placetype":"postalcode"
},
  "geometry": {"coordinates":[-4.19893654017526,50.37816305709423],"type":"Point"}
}