{
  "type": "Feature",
  "properties": {
    "iso:country": "GB",
    "wof:name": "PL11 2JH",
    "wof:placetype": "postalcode"
  },
  "geometry": {"coordinates":[-4.198966,50.378149],"type":"Point"}
}
