{
  "type": "Feature",
  "properties": {
    "date:inception_lower":"2002-06-01",
    "date:inception_upper":"2002-06-30",
    "iso:country":"GB",
    "wof:name":"CF14 4US",
    "wof:placetype":"postalcode"
},
  "geometry": {"coordinates":[-3.197874,51.506922],"type":"Point"}
}