{
  "type": "Feature",
  "properties": {
    "iso:country":"GB",
    "wof:name":"CF24 1DJ",
    "wof:placetype":"postalcode"
},
  "geometry": {"coordinates":[-3.15741904768385,51.48927104304519],"type":"Point"}
}