{
  "type": "Feature",
  "properties": {
    "iso:country":"GB",
    "wof:name":"LL18 2YN",
    "wof:placetype":"postalcode"
},
  "geometry": {"coordinates":[-3.46874536333292,53.29516555509311],"type":"Point"}
}