{
  "type": "Feature",
  "properties": {
    "date:inception_lower":"1995-12-01",
    "date:inception_upper":"1995-12-31",
    "iso:country":"GB",
    "wof:name":"TN38 0WL",
    "wof:placetype":"postalcode"
},
  "geometry": {"coordinates":[0.539232,50.856675],"type":"Point"}
}