{
  "type": "Feature",
  "properties": {
    "iso:country": "GB",
    "wof:name": "TN38 0WL",
    "wof:placetype": "postalcode"
  },
  "geometry": {"coordinates":[0.539232,50.856675],"type":"Point"}
}
