{
  "type": "Feature",
  "properties": {
    "date:inception_lower":"1980-01-01",
    "date:inception_upper":"1980-01-31",
    "iso:country":"GB",
    "wof:name":"BA14 9JP",
    "wof:placetype":"postalcode"
},
  "geometry": {"coordinates":[-2.226308,51.312353],"type":"Point"}
}