{
  "type": "Feature",
  "properties": {
    "iso:country":"GB",
    "wof:name":"SL4 2JH",
    "wof:placetype":"postalcode"
},
  "geometry": {"coordinates":[-0.59350345901392,51.46117825219314],"type":"Point"}
}