{
  "type": "Feature",
  "properties": {
    "iso:country": "GB",
    "wof:name": "NR7 0DD",
    "wof:placetype": "postalcode"
  },
  "geometry": {"coordinates":[1.329175,52.632695],"type":"Point"}
}
