{
  "type": "Feature",
  "properties": {
    "iso:country": "GB",
    "wof:name": "B17 8JG",
    "wof:placetype": "postalcode"
  },
  "geometry": {"coordinates":[-1.959554,52.479263],"type":"Point"}
}
