{
  "type": "Feature",
  "properties": {
    "iso:country":"GB",
    "wof:name":"LL55 4NE",
    "wof:placetype":"postalcode"
},
  "geometry": {"coordinates":[-4.08856071491745,53.01649687637255],"type":"Point"}
}