{
  "type": "Feature",
  "properties": {
    "date:inception_lower":"1980-01-01",
    "date:inception_upper":"1980-01-31",
    "iso:country":"GB",
    "wof:name":"PL5 1HH",
    "wof:placetype":"postalcode"
},
  "geometry": {"coordinates":[-4.195135,50.400316],"type":"Point"}
}