{
  "type": "Feature",
  "properties": {
    "iso:country": "GB",
    "wof:name": "PL5 1HH",
    "wof:placetype": "postalcode"
  },
  "geometry": {"coordinates":[-4.195135,50.400316],"type":"Point"}
}
