{
  "type": "Feature",
  "properties": {
    "date:inception_lower": "2017-01-01",
    "date:inception_upper": "2017-01-01",
    "iso:country": "GB",
    "wof:name": "NE61 2GH",
    "wof:placetype": "postalcode"
  },
  "geometry": {"coordinates":[-1.684109,55.17409],"type":"Point"}
}
