{
  "type": "Feature",
  "properties": {
    "iso:country": "GB",
    "wof:name": "NE61 2GH",
    "wof:placetype": "postalcode"
  },
  "geometry": {"coordinates":[-1.684188,55.174082],"type":"Point"}
}
