{
  "type": "Feature",
  "properties": {
    "iso:country":"GB",
    "wof:name":"TF4 2EH",
    "wof:placetype":"postalcode"
},
  "geometry": {"coordinates":[-2.46066798549153,52.67355160085391],"type":"Point"}
}