{
  "type": "Feature",
  "properties": {
    "date:inception_lower": "1980-01-01",
    "date:inception_upper": "1980-01-01",
    "iso:country": "GB",
    "wof:name": "TF4 2EH",
    "wof:placetype": "postalcode"
  },
  "geometry": {"coordinates":[-2.460668,52.673552],"type":"Point"}
}
