{
  "type": "Feature",
  "properties": {
    "date:inception_lower":"1980-01-01",
    "date:inception_upper":"1980-01-31",
    "iso:country":"GB",
    "wof:name":"CM1 3DQ",
    "wof:placetype":"postalcode"
},
  "geometry": {"coordinates":[0.446644,51.73022],"type":"Point"}
}