{
  "type": "Feature",
  "properties": {
    "iso:country":"GB",
    "wof:name":"CM1 3DQ",
    "wof:placetype":"postalcode"
},
  "geometry": {"coordinates":[0.44664371046547,51.73021985873423],"type":"Point"}
}