{
  "type": "Feature",
  "properties": {
    "iso:country":"GB",
    "wof:name":"NG4 4BT",
    "wof:placetype":"postalcode"
},
  "geometry": {"coordinates":[-1.07746247806124,52.98053837003618],"type":"Point"}
}