{
  "type": "Feature",
  "properties": {
    "iso:country":"GB",
    "wof:name":"CT16 1QB",
    "wof:placetype":"postalcode"
},
  "geometry": {"coordinates":[1.31545231559831,51.12583368357605],"type":"Point"}
}