{
  "type": "Feature",
  "properties": {
    "date:inception_lower": "2007-07-01",
    "date:inception_upper": "2007-07-01",
    "iso:country": "GB",
    "wof:name": "CT16 1QB",
    "wof:placetype": "postalcode"
  },
  "geometry": {"coordinates":[1.315452,51.125834],"type":"Point"}
}
