{
  "type": "Feature",
  "properties": {
    "iso:country": "GB",
    "wof:name": "LN9 5RT",
    "wof:placetype": "postalcode"
  },
  "geometry": {"coordinates":[-0.224007,53.245449],"type":"Point"}
}
