{
  "type": "Feature",
  "properties": {
    "iso:country":"GB",
    "wof:name":"LN9 5RT",
    "wof:placetype":"postalcode"
},
  "geometry": {"coordinates":[-0.22400700771146,53.24544934756905],"type":"Point"}
}