{
  "type": "Feature",
  "properties": {
    "iso:country":"GB",
    "wof:name":"DH2 3QN",
    "wof:placetype":"postalcode"
},
  "geometry": {"coordinates":[-1.59789509727993,54.81806736923431],"type":"Point"}
}