{
  "type": "Feature",
  "properties": {
    "iso:country": "GB",
    "wof:name": "DH2 3QN",
    "wof:placetype": "postalcode"
  },
  "geometry": {"coordinates":[-1.597895,54.818067],"type":"Point"}
}
