{
  "type": "Feature",
  "properties": {
    "iso:country":"GB",
    "wof:name":"HX3 9TH",
    "wof:placetype":"postalcode"
},
  "geometry": {"coordinates":[-1.82551399244549,53.70885956173802],"type":"Point"}
}