{
  "type": "Feature",
  "properties": {
    "iso:country": "GB",
    "wof:name": "HX3 9TH",
    "wof:placetype": "postalcode"
  },
  "geometry": {"coordinates":[-1.825683,53.708839],"type":"Point"}
}
