{
  "type": "Feature",
  "properties": {
    "date:inception_lower": "2023-03-01",
    "date:inception_upper": "2023-03-01",
    "iso:country": "GB",
    "wof:name": "TF3 4TH",
    "wof:placetype": "postalcode"
  },
  "geometry": {"coordinates":[-2.459821,52.68175],"type":"Point"}
}
