{
  "type": "Feature",
  "properties": {
    "iso:country":"GB",
    "wof:name":"LN13 9AG",
    "wof:placetype":"postalcode"
},
  "geometry": {"coordinates":[0.18045584228459,53.25980109484459],"type":"Point"}
}