{
  "type": "Feature",
  "properties": {
    "iso:country": "GB",
    "wof:name": "LN13 9AG",
    "wof:placetype": "postalcode"
  },
  "geometry": {"coordinates":[0.180456,53.259801],"type":"Point"}
}
