{
  "type": "Feature",
  "properties": {
    "iso:country":"GB",
    "wof:name":"B33 0PR",
    "wof:placetype":"postalcode"
},
  "geometry": {"coordinates":[-1.7708393356387,52.46485341678424],"type":"Point"}
}