{
  "type": "Feature",
  "properties": {
    "iso:country":"GB",
    "wof:name":"DH7 9QZ",
    "wof:placetype":"postalcode"
},
  "geometry": {"coordinates":[-1.69468205277947,54.79029335647906],"type":"Point"}
}