{
  "type": "Feature",
  "properties": {
    "date:inception_lower":"1980-01-01",
    "date:inception_upper":"1980-01-31",
    "iso:country":"GB",
    "wof:name":"DN31 2AU",
    "wof:placetype":"postalcode"
},
  "geometry": {"coordinates":[-0.093082,53.56347],"type":"Point"}
}