{
  "type": "Feature",
  "properties": {
    "iso:country": "GB",
    "wof:name": "DN31 2AU",
    "wof:placetype": "postalcode"
  },
  "geometry": {"coordinates":[-0.093082,53.56347],"type":"Point"}
}
