{
  "type": "Feature",
  "properties": {
    "iso:country":"GB",
    "wof:name":"NE32 3SN",
    "wof:placetype":"postalcode"
},
  "geometry": {"coordinates":[-1.47494527679684,54.97350380296594],"type":"Point"}
}