{
  "type": "Feature",
  "properties": {
    "date:inception_lower": "1980-01-01",
    "date:inception_upper": "1980-01-01",
    "iso:country": "GB",
    "wof:name": "NE32 3SN",
    "wof:placetype": "postalcode"
  },
  "geometry": {"coordinates":[-1.474978,54.973215],"type":"Point"}
}
