{
  "type": "Feature",
  "properties": {
    "date:inception_lower": "1990-02-01",
    "date:inception_upper": "1990-02-01",
    "iso:country": "GB",
    "wof:name": "MK7 7EA",
    "wof:placetype": "postalcode"
  },
  "geometry": {"coordinates":[-0.69457,52.019576],"type":"Point"}
}
