{
  "type": "Feature",
  "properties": {
    "iso:country":"GB",
    "wof:name":"BR7 5LQ",
    "wof:placetype":"postalcode"
},
  "geometry": {"coordinates":[0.05089251472128,51.40946423628785],"type":"Point"}
}