{
  "type": "Feature",
  "properties": {
    "iso:country": "GB",
    "wof:name": "LD6 5DJ",
    "wof:placetype": "postalcode"
  },
  "geometry": {"coordinates":[-3.51076,52.303369],"type":"Point"}
}
