{
  "type": "Feature",
  "properties": {
    "iso:country":"GB",
    "wof:name":"LD6 5DJ",
    "wof:placetype":"postalcode"
},
  "geometry": {"coordinates":[-3.51075960045523,52.30336909106396],"type":"Point"}
}