{
  "type": "Feature",
  "properties": {
    "date:inception_lower": "2006-08-01",
    "date:inception_upper": "2006-08-01",
    "iso:country": "GB",
    "wof:name": "LD6 5DJ",
    "wof:placetype": "postalcode"
  },
  "geometry": {"coordinates":[-3.51076,52.303369],"type":"Point"}
}
