{
  "type": "Feature",
  "properties": {
    "iso:country":"GB",
    "wof:name":"EN7 6RZ",
    "wof:placetype":"postalcode"
},
  "geometry": {"coordinates":[-0.07765733144156,51.71334233295821],"type":"Point"}
}