{
  "type": "Feature",
  "properties": {
    "iso:country":"GB",
    "wof:name":"GU1 3UL",
    "wof:placetype":"postalcode"
},
  "geometry": {"coordinates":[-0.5733540018075,51.23494014379664],"type":"Point"}
}