{
  "type": "Feature",
  "properties": {
    "iso:country": "GB",
    "wof:name": "LL12 0UE",
    "wof:placetype": "postalcode"
  },
  "geometry": {"coordinates":[-2.992169,53.095875],"type":"Point"}
}
