{
  "type": "Feature",
  "properties": {
    "iso:country": "GB",
    "wof:name": "M46 0AL",
    "wof:placetype": "postalcode"
  },
  "geometry": {"coordinates":[-2.496045,53.522394],"type":"Point"}
}
