{
  "type": "Feature",
  "properties": {
    "iso:country":"GB",
    "wof:name":"M46 0AL",
    "wof:placetype":"postalcode"
},
  "geometry": {"coordinates":[-2.49604545015417,53.5223942052472],"type":"Point"}
}