{
  "type": "Feature",
  "properties": {
    "iso:country":"GB",
    "wof:name":"SY10 7UD",
    "wof:placetype":"postalcode"
},
  "geometry": {"coordinates":[-3.0337977099531,52.90160637624371],"type":"Point"}
}