{
  "type": "Feature",
  "properties": {
    "iso:country": "GB",
    "wof:name": "SY10 7UD",
    "wof:placetype": "postalcode"
  },
  "geometry": {"coordinates":[-3.033798,52.901606],"type":"Point"}
}
