{
  "type": "Feature",
  "properties": {
    "iso:country":"GB",
    "wof:name":"SE26 4SH",
    "wof:placetype":"postalcode"
},
  "geometry": {"coordinates":[-0.05180378846515,51.4311804653093],"type":"Point"}
}