{
  "type": "Feature",
  "properties": {
    "iso:country": "GB",
    "wof:name": "WD6 4TN",
    "wof:placetype": "postalcode"
  },
  "geometry": {"coordinates":[-0.295433,51.668111],"type":"Point"}
}
