{
  "type": "Feature",
  "properties": {
    "date:inception_lower": "2023-05-01",
    "date:inception_upper": "2023-05-01",
    "iso:country": "GB",
    "wof:name": "AB22 9BF",
    "wof:placetype": "postalcode"
  },
  "geometry": {"coordinates":[-2.133707,57.189226],"type":"Point"}
}
