{
  "type": "Feature",
  "properties": {
    "iso:country":"GB",
    "wof:name":"SL2 3DA",
    "wof:placetype":"postalcode"
},
  "geometry": {"coordinates":[-0.61622912073273,51.54645942688492],"type":"Point"}
}