{
  "type": "Feature",
  "properties": {
    "iso:country": "GB",
    "wof:name": "CM0 8NS",
    "wof:placetype": "postalcode"
  },
  "geometry": {"coordinates":[0.797497,51.642146],"type":"Point"}
}
