{
  "type": "Feature",
  "properties": {
    "iso:country":"GB",
    "wof:name":"CM0 8NS",
    "wof:placetype":"postalcode"
},
  "geometry": {"coordinates":[0.79749661321733,51.64214571266215],"type":"Point"}
}