{
  "type": "Feature",
  "properties": {
    "date:inception_lower": "2000-10-01",
    "date:inception_upper": "2000-10-01",
    "iso:country": "GB",
    "wof:name": "W1G 6LR",
    "wof:placetype": "postalcode"
  },
  "geometry": {"coordinates":[-0.149932,51.521239],"type":"Point"}
}
