{
  "type": "Feature",
  "properties": {
    "iso:country":"GB",
    "wof:name":"W1G 6LR",
    "wof:placetype":"postalcode"
},
  "geometry": {"coordinates":[-0.1499318032494,51.5212390992141],"type":"Point"}
}