{
  "type": "Feature",
  "properties": {
    "date:inception_lower": "1995-12-01",
    "date:inception_upper": "1995-12-01",
    "iso:country": "GB",
    "wof:name": "CA6 4NP",
    "wof:placetype": "postalcode"
  },
  "geometry": {"coordinates":[-2.783137,54.947032],"type":"Point"}
}
