{
  "type": "Feature",
  "properties": {
    "iso:country":"GB",
    "wof:name":"G52 1EU",
    "wof:placetype":"postalcode"
},
  "geometry": {"coordinates":[-4.32840384011914,55.84479218913117],"type":"Point"}
}