{
  "type": "Feature",
  "properties": {
    "iso:country":"GB",
    "wof:name":"FK2 9QU",
    "wof:placetype":"postalcode"
},
  "geometry": {"coordinates":[-3.74209831603353,55.9958485523685],"type":"Point"}
}