{
  "type": "Feature",
  "properties": {
    "iso:country":"GB",
    "wof:name":"DT11 8SH",
    "wof:placetype":"postalcode"
},
  "geometry": {"coordinates":[-2.10659817607206,50.85555298784133],"type":"Point"}
}