{
  "type": "Feature",
  "properties": {
    "iso:country": "GB",
    "wof:name": "LL53 5LN",
    "wof:placetype": "postalcode"
  },
  "geometry": {"coordinates":[-4.409998,52.892204],"type":"Point"}
}
