{
  "type": "Feature",
  "properties": {
    "date:inception_lower":"1980-01-01",
    "date:inception_upper":"1980-01-31",
    "iso:country":"GB",
    "wof:name":"LL53 5LN",
    "wof:placetype":"postalcode"
},
  "geometry": {"coordinates":[-4.409998,52.892204],"type":"Point"}
}