{
  "type": "Feature",
  "properties": {
    "iso:country": "GB",
    "wof:name": "CV22 5DP",
    "wof:placetype": "postalcode"
  },
  "geometry": {"coordinates":[-1.261177,52.36882],"type":"Point"}
}
