{
  "type": "Feature",
  "properties": {
    "date:inception_lower":"2017-01-01",
    "date:inception_upper":"2017-01-31",
    "iso:country":"GB",
    "wof:name":"CV22 5DP",
    "wof:placetype":"postalcode"
},
  "geometry": {"coordinates":[-1.261177,52.36882],"type":"Point"}
}