{
  "type": "Feature",
  "properties": {
    "iso:country":"GB",
    "wof:name":"LS16 6QN",
    "wof:placetype":"postalcode"
},
  "geometry": {"coordinates":[-1.61075850966176,53.83938266646028],"type":"Point"}
}