{
  "type": "Feature",
  "properties": {
    "iso:country":"GB",
    "wof:name":"TA3 5BJ",
    "wof:placetype":"postalcode"
},
  "geometry": {"coordinates":[-3.06305801001776,50.95835554661704],"type":"Point"}
}