{
  "type": "Feature",
  "properties": {
    "date:inception_lower": "1980-01-01",
    "date:inception_upper": "1980-01-01",
    "iso:country": "GB",
    "wof:name": "TA3 5BJ",
    "wof:placetype": "postalcode"
  },
  "geometry": {"coordinates":[-3.063058,50.958356],"type":"Point"}
}
