{
  "type": "Feature",
  "properties": {
    "iso:country":"GB",
    "wof:name":"MK2 3QL",
    "wof:placetype":"postalcode"
},
  "geometry": {"coordinates":[-0.72603289567946,51.98060220649184],"type":"Point"}
}