{
  "type": "Feature",
  "properties": {
    "date:inception_lower": "1980-01-01",
    "date:inception_upper": "1980-01-01",
    "iso:country": "GB",
    "wof:name": "RM17 5DX",
    "wof:placetype": "postalcode"
  },
  "geometry": {"coordinates":[0.324584,51.479375],"type":"Point"}
}
