{
  "type": "Feature",
  "properties": {
    "iso:country":"GB",
    "wof:name":"DE12 6DW",
    "wof:placetype":"postalcode"
},
  "geometry": {"coordinates":[-1.52081402376751,52.74295261999934],"type":"Point"}
}