{
  "type": "Feature",
  "properties": {
    "iso:country":"GB",
    "wof:name":"E8 2AY",
    "wof:placetype":"postalcode"
},
  "geometry": {"coordinates":[-0.06525734281872,51.55157175680561],"type":"Point"}
}