{
  "type": "Feature",
  "properties": {
    "iso:country": "GB",
    "wof:name": "E8 2AY",
    "wof:placetype": "postalcode"
  },
  "geometry": {"coordinates":[-0.065257,51.551572],"type":"Point"}
}
