{
  "type": "Feature",
  "properties": {
    "iso:country":"GB",
    "wof:name":"HU7 5DJ",
    "wof:placetype":"postalcode"
},
  "geometry": {"coordinates":[-0.32844512997901,53.81004274813179],"type":"Point"}
}