{
  "type": "Feature",
  "properties": {
    "date:inception_lower":"1980-01-01",
    "date:inception_upper":"1980-01-31",
    "iso:country":"GB",
    "wof:name":"HU7 5DJ",
    "wof:placetype":"postalcode"
},
  "geometry": {"coordinates":[-0.328445,53.810043],"type":"Point"}
}