{
  "type": "Feature",
  "properties": {
    "iso:country":"GB",
    "wof:name":"B90 2DG",
    "wof:placetype":"postalcode"
},
  "geometry": {"coordinates":[-1.83373252070134,52.40650518109813],"type":"Point"}
}