{
  "type": "Feature",
  "properties": {
    "iso:country":"GB",
    "wof:name":"EN1 1ET",
    "wof:placetype":"postalcode"
},
  "geometry": {"coordinates":[-0.06099247318472,51.63960074331045],"type":"Point"}
}