{
  "type": "Feature",
  "properties": {
    "date:inception_lower": "1995-07-01",
    "date:inception_upper": "1995-07-01",
    "iso:country": "GB",
    "wof:name": "RG45 7BZ",
    "wof:placetype": "postalcode"
  },
  "geometry": {"coordinates":[-0.789528,51.37028],"type":"Point"}
}
