{
  "type": "Feature",
  "properties": {
    "date:inception_lower": "2004-03-01",
    "date:inception_upper": "2004-03-01",
    "iso:country": "GB",
    "wof:name": "LL22 8FH",
    "wof:placetype": "postalcode"
  },
  "geometry": {"coordinates":[-3.636732,53.288798],"type":"Point"}
}
