{
  "type": "Feature",
  "properties": {
    "iso:country":"GB",
    "wof:name":"LL22 8FH",
    "wof:placetype":"postalcode"
},
  "geometry": {"coordinates":[-3.63673201602697,53.28879764220616],"type":"Point"}
}