{
  "type": "Feature",
  "properties": {
    "iso:country": "GB",
    "wof:name": "SA2 0ND",
    "wof:placetype": "postalcode"
  },
  "geometry": {"coordinates":[-3.97239,51.620116],"type":"Point"}
}
