{
  "type": "Feature",
  "properties": {
    "iso:country":"GB",
    "wof:name":"SA2 0ND",
    "wof:placetype":"postalcode"
},
  "geometry": {"coordinates":[-3.9723903515154,51.62011557561016],"type":"Point"}
}