{
  "type": "Feature",
  "properties": {
    "date:inception_lower":"1980-01-01",
    "date:inception_upper":"1980-01-31",
    "iso:country":"GB",
    "wof:name":"SA2 0ND",
    "wof:placetype":"postalcode"
},
  "geometry": {"coordinates":[-3.97239,51.620116],"type":"Point"}
}