{
  "type": "Feature",
  "properties": {
    "date:inception_lower": "1980-01-01",
    "date:inception_upper": "1980-01-01",
    "iso:country": "GB",
    "wof:name": "SR6 0JY",
    "wof:placetype": "postalcode"
  },
  "geometry": {"coordinates":[-1.375314,54.91862],"type":"Point"}
}
