{
  "type": "Feature",
  "properties": {
    "iso:country":"GB",
    "wof:name":"GL6 0EF",
    "wof:placetype":"postalcode"
},
  "geometry": {"coordinates":[-2.22695264262243,51.69739319921183],"type":"Point"}
}