{
  "type": "Feature",
  "properties": {
    "date:inception_lower": "1980-01-01",
    "date:inception_upper": "1980-01-01",
    "iso:country": "GB",
    "wof:name": "SY15 6SB",
    "wof:placetype": "postalcode"
  },
  "geometry": {"coordinates":[-3.206102,52.573542],"type":"Point"}
}
