{
  "type": "Feature",
  "properties": {
    "date:inception_lower": "1980-01-01",
    "date:inception_upper": "1980-01-01",
    "iso:country": "GB",
    "wof:name": "EX36 4NS",
    "wof:placetype": "postalcode"
  },
  "geometry": {"coordinates":[-3.770442,50.985767],"type":"Point"}
}
