{
  "type": "Feature",
  "properties": {
    "iso:country":"GB",
    "wof:name":"EX36 4NS",
    "wof:placetype":"postalcode"
},
  "geometry": {"coordinates":[-3.77042314507295,50.98577169705174],"type":"Point"}
}