{
  "type": "Feature",
  "properties": {
    "iso:country":"GB",
    "wof:name":"NR14 8NR",
    "wof:placetype":"postalcode"
},
  "geometry": {"coordinates":[1.33078149746852,52.57466693781591],"type":"Point"}
}