{
  "type": "Feature",
  "properties": {
    "iso:country":"GB",
    "wof:name":"L25 7RG",
    "wof:placetype":"postalcode"
},
  "geometry": {"coordinates":[-2.87000462075065,53.37417134949056],"type":"Point"}
}