{
  "type": "Feature",
  "properties": {
    "iso:country": "GB",
    "wof:name": "S43 4WY",
    "wof:placetype": "postalcode"
  },
  "geometry": {"coordinates":[-1.28126,53.285958],"type":"Point"}
}
