{
  "type": "Feature",
  "properties": {
    "iso:country":"GB",
    "wof:name":"S43 4WY",
    "wof:placetype":"postalcode"
},
  "geometry": {"coordinates":[-1.28126044466809,53.28595796903714],"type":"Point"}
}