{
  "type": "Feature",
  "properties": {
    "iso:country":"GB",
    "wof:name":"PO19 8RJ",
    "wof:placetype":"postalcode"
},
  "geometry": {"coordinates":[-0.78764701048136,50.82692422668659],"type":"Point"}
}