{
  "type": "Feature",
  "properties": {
    "date:inception_lower": "2002-06-01",
    "date:inception_upper": "2002-06-01",
    "iso:country": "GB",
    "wof:name": "PO19 8RJ",
    "wof:placetype": "postalcode"
  },
  "geometry": {"coordinates":[-0.787647,50.826924],"type":"Point"}
}
