{
  "type": "Feature",
  "properties": {
    "date:inception_lower": "2020-10-01",
    "date:inception_upper": "2020-10-01",
    "iso:country": "GB",
    "wof:name": "SG5 4TE",
    "wof:placetype": "postalcode"
  },
  "geometry": {"coordinates":[-0.226002,52.026123],"type":"Point"}
}
