{
  "type": "Feature",
  "properties": {
    "date:inception_lower": "1980-01-01",
    "date:inception_upper": "1980-01-01",
    "iso:country": "GB",
    "wof:name": "SY21 0NX",
    "wof:placetype": "postalcode"
  },
  "geometry": {"coordinates":[-3.517914,52.691974],"type":"Point"}
}
