{
  "type": "Feature",
  "properties": {
    "iso:country":"GB",
    "wof:name":"SY21 0NX",
    "wof:placetype":"postalcode"
},
  "geometry": {"coordinates":[-3.51791391593772,52.69197422140801],"type":"Point"}
}