{
  "type": "Feature",
  "properties": {
    "date:inception_lower": "2019-05-01",
    "date:inception_upper": "2019-05-01",
    "iso:country": "GB",
    "wof:name": "DY3 4AR",
    "wof:placetype": "postalcode"
  },
  "geometry": {"coordinates":[-2.149563,52.536519],"type":"Point"}
}
