{
  "type": "Feature",
  "properties": {
    "iso:country": "GB",
    "wof:name": "CA20 1LU",
    "wof:placetype": "postalcode"
  },
  "geometry": {"coordinates":[-3.478884,54.39916],"type":"Point"}
}
