{
  "type": "Feature",
  "properties": {
    "iso:country":"GB",
    "wof:name":"CA20 1LU",
    "wof:placetype":"postalcode"
},
  "geometry": {"coordinates":[-3.47888357611674,54.39916030342123],"type":"Point"}
}