{
  "type": "Feature",
  "properties": {
    "iso:country":"GB",
    "wof:name":"M22 1PJ",
    "wof:placetype":"postalcode"
},
  "geometry": {"coordinates":[-2.26934068190686,53.37183461237805],"type":"Point"}
}