{
  "type": "Feature",
  "properties": {
    "date:inception_lower":"1994-05-01",
    "date:inception_upper":"1994-05-31",
    "iso:country":"GB",
    "wof:name":"M22 1PJ",
    "wof:placetype":"postalcode"
},
  "geometry": {"coordinates":[-2.269341,53.371835],"type":"Point"}
}