{
  "type": "Feature",
  "properties": {
    "iso:country":"GB",
    "wof:name":"LA12 8JQ",
    "wof:placetype":"postalcode"
},
  "geometry": {"coordinates":[-3.03189058086839,54.26421260030605],"type":"Point"}
}