{
  "type": "Feature",
  "properties": {
    "iso:country": "GB",
    "wof:name": "LA12 8JQ",
    "wof:placetype": "postalcode"
  },
  "geometry": {"coordinates":[-3.031891,54.26424],"type":"Point"}
}
