{
  "type": "Feature",
  "properties": {
    "iso:country":"GB",
    "wof:name":"HU14 3PL",
    "wof:placetype":"postalcode"
},
  "geometry": {"coordinates":[-0.50201947731589,53.73696411290587],"type":"Point"}
}