{
  "type": "Feature",
  "properties": {
    "iso:country": "GB",
    "wof:name": "LA11 7AL",
    "wof:placetype": "postalcode"
  },
  "geometry": {"coordinates":[-2.924265,54.180503],"type":"Point"}
}
