{
  "type": "Feature",
  "properties": {
    "date:inception_lower":"2012-03-01",
    "date:inception_upper":"2012-03-31",
    "iso:country":"GB",
    "wof:name":"NE24 3BS",
    "wof:placetype":"postalcode"
},
  "geometry": {"coordinates":[-1.49806,55.125513],"type":"Point"}
}