{
  "type": "Feature",
  "properties": {
    "iso:country": "GB",
    "wof:name": "NE24 3BS",
    "wof:placetype": "postalcode"
  },
  "geometry": {"coordinates":[-1.49806,55.125513],"type":"Point"}
}
