{
  "type": "Feature",
  "properties": {
    "iso:country":"GB",
    "wof:name":"NE24 3BS",
    "wof:placetype":"postalcode"
},
  "geometry": {"coordinates":[-1.49805972996335,55.12551302505911],"type":"Point"}
}