{
  "type": "Feature",
  "properties": {
    "date:inception_lower":"2015-01-01",
    "date:inception_upper":"2015-01-31",
    "iso:country":"GB",
    "wof:name":"NN7 1NJ",
    "wof:placetype":"postalcode"
},
  "geometry": {"coordinates":[-0.783729,52.237429],"type":"Point"}
}