{
  "type": "Feature",
  "properties": {
    "iso:country": "GB",
    "wof:name": "PR6 8AF",
    "wof:placetype": "postalcode"
  },
  "geometry": {"coordinates":[-2.618508,53.681736],"type":"Point"}
}
