{
  "type": "Feature",
  "properties": {
    "iso:country":"GB",
    "wof:name":"E10 6DB",
    "wof:placetype":"postalcode"
},
  "geometry": {"coordinates":[-0.00796718535847,51.57658359752669],"type":"Point"}
}