{
  "type": "Feature",
  "properties": {
    "date:inception_lower": "1998-06-01",
    "date:inception_upper": "1998-06-01",
    "iso:country": "GB",
    "wof:name": "B35 7AF",
    "wof:placetype": "postalcode"
  },
  "geometry": {"coordinates":[-1.798177,52.51065],"type":"Point"}
}
