{
  "type": "Feature",
  "properties": {
    "date:inception_lower":"1980-01-01",
    "date:inception_upper":"1980-01-31",
    "iso:country":"GB",
    "wof:name":"CM13 2PS",
    "wof:placetype":"postalcode"
},
  "geometry": {"coordinates":[0.339418,51.629511],"type":"Point"}
}