{
  "type": "Feature",
  "properties": {
    "iso:country":"GB",
    "wof:name":"NG1 3NA",
    "wof:placetype":"postalcode"
},
  "geometry": {"coordinates":[-1.14458410188397,52.95672356304718],"type":"Point"}
}