{
  "type": "Feature",
  "properties": {
    "date:inception_lower": "1981-06-01",
    "date:inception_upper": "1981-06-01",
    "iso:country": "GB",
    "wof:name": "EX9 6RQ",
    "wof:placetype": "postalcode"
  },
  "geometry": {"coordinates":[-3.329522,50.63095],"type":"Point"}
}
