{
  "type": "Feature",
  "properties": {
    "iso:country":"GB",
    "wof:name":"EX9 6RQ",
    "wof:placetype":"postalcode"
},
  "geometry": {"coordinates":[-3.32952238256077,50.63094963808108],"type":"Point"}
}