{
  "type": "Feature",
  "properties": {
    "date:inception_lower": "1980-01-01",
    "date:inception_upper": "1980-01-01",
    "iso:country": "GB",
    "wof:name": "CO5 0QJ",
    "wof:placetype": "postalcode"
  },
  "geometry": {"coordinates":[0.721769,51.803417],"type":"Point"}
}
