{
  "type": "Feature",
  "properties": {
    "iso:country": "GB",
    "wof:name": "CO5 0QJ",
    "wof:placetype": "postalcode"
  },
  "geometry": {"coordinates":[0.721769,51.803417],"type":"Point"}
}
