{
  "type": "Feature",
  "properties": {
    "iso:country":"GB",
    "wof:name":"CO5 0QJ",
    "wof:placetype":"postalcode"
},
  "geometry": {"coordinates":[0.72176900781924,51.80341666012288],"type":"Point"}
}