{
  "type": "Feature",
  "properties": {
    "iso:country": "GB",
    "wof:name": "N1 2GB",
    "wof:placetype": "postalcode"
  },
  "geometry": {"coordinates":[-0.092122,51.544521],"type":"Point"}
}
