{
  "type": "Feature",
  "properties": {
    "iso:country":"GB",
    "wof:name":"N1 2GB",
    "wof:placetype":"postalcode"
},
  "geometry": {"coordinates":[-0.09212183969799,51.54452093449941],"type":"Point"}
}