{
  "type": "Feature",
  "properties": {
    "date:inception_lower":"2016-06-01",
    "date:inception_upper":"2016-06-30",
    "iso:country":"GB",
    "wof:name":"BN52 9BF",
    "wof:placetype":"postalcode"
},
  "geometry": {"coordinates":[-0.168063,50.834409],"type":"Point"}
}