{
  "type": "Feature",
  "properties": {
    "iso:country": "GB",
    "wof:name": "PL17 7LT",
    "wof:placetype": "postalcode"
  },
  "geometry": {"coordinates":[-4.360471,50.521984],"type":"Point"}
}
