{
  "type": "Feature",
  "properties": {
    "date:inception_lower":"1985-10-01",
    "date:inception_upper":"1985-10-31",
    "iso:country":"GB",
    "wof:name":"PL17 7LT",
    "wof:placetype":"postalcode"
},
  "geometry": {"coordinates":[-4.360471,50.521984],"type":"Point"}
}