{
  "type": "Feature",
  "properties": {
    "iso:country":"GB",
    "wof:name":"PL17 7LT",
    "wof:placetype":"postalcode"
},
  "geometry": {"coordinates":[-4.36047095735918,50.52198385235288],"type":"Point"}
}