{
  "type": "Feature",
  "properties": {
    "iso:country":"GB",
    "wof:name":"CV35 0QQ",
    "wof:placetype":"postalcode"
},
  "geometry": {"coordinates":[-1.55407004657164,52.1406655669303],"type":"Point"}
}