{
  "type": "Feature",
  "properties": {
    "iso:country": "GB",
    "wof:name": "CV35 0QQ",
    "wof:placetype": "postalcode"
  },
  "geometry": {"coordinates":[-1.55407,52.140666],"type":"Point"}
}
