{
  "type": "Feature",
  "properties": {
    "iso:country": "GB",
    "wof:name": "GL20 6BE",
    "wof:placetype": "postalcode"
  },
  "geometry": {"coordinates":[-2.238452,52.024578],"type":"Point"}
}
