{
  "type": "Feature",
  "properties": {
    "date:inception_lower": "2012-10-01",
    "date:inception_upper": "2012-10-01",
    "iso:country": "GB",
    "wof:name": "M40 5NN",
    "wof:placetype": "postalcode"
  },
  "geometry": {"coordinates":[-2.190826,53.506463],"type":"Point"}
}
