{
  "type": "Feature",
  "properties": {
    "iso:country":"GB",
    "wof:name":"MK5 7EP",
    "wof:placetype":"postalcode"
},
  "geometry": {"coordinates":[-0.78078525478761,52.0158337110454],"type":"Point"}
}