{
  "type": "Feature",
  "properties": {
    "iso:country": "GB",
    "wof:name": "MK5 7EP",
    "wof:placetype": "postalcode"
  },
  "geometry": {"coordinates":[-0.780785,52.015834],"type":"Point"}
}
