{
  "type": "Feature",
  "properties": {
    "iso:country":"GB",
    "wof:name":"PO7 8NU",
    "wof:placetype":"postalcode"
},
  "geometry": {"coordinates":[-1.00755804800219,50.88766107706657],"type":"Point"}
}