{
  "type": "Feature",
  "properties": {
    "iso:country":"GB",
    "wof:name":"SW15 2AT",
    "wof:placetype":"postalcode"
},
  "geometry": {"coordinates":[-0.21497968346364,51.45829267510621],"type":"Point"}
}