{
  "type": "Feature",
  "properties": {
    "iso:country":"GB",
    "wof:name":"SR7 9HL",
    "wof:placetype":"postalcode"
},
  "geometry": {"coordinates":[-1.40034257818254,54.81856470535952],"type":"Point"}
}