{
  "type": "Feature",
  "properties": {
    "iso:country": "GB",
    "wof:name": "SR7 9HL",
    "wof:placetype": "postalcode"
  },
  "geometry": {"coordinates":[-1.400343,54.818565],"type":"Point"}
}
