{
  "type": "Feature",
  "properties": {
    "iso:country": "GB",
    "wof:name": "DN22 0AB",
    "wof:placetype": "postalcode"
  },
  "geometry": {"coordinates":[-0.822245,53.332038],"type":"Point"}
}
