{
  "type": "Feature",
  "properties": {
    "iso:country":"GB",
    "wof:name":"DN22 0AB",
    "wof:placetype":"postalcode"
},
  "geometry": {"coordinates":[-0.82224481852798,53.33203768666969],"type":"Point"}
}