{
  "type": "Feature",
  "properties": {
    "date:inception_lower": "1980-01-01",
    "date:inception_upper": "1980-01-01",
    "iso:country": "GB",
    "wof:name": "DN22 0AB",
    "wof:placetype": "postalcode"
  },
  "geometry": {"coordinates":[-0.822245,53.332038],"type":"Point"}
}
