{
  "type": "Feature",
  "properties": {
    "date:inception_lower": "2001-06-01",
    "date:inception_upper": "2001-06-01",
    "iso:country": "GB",
    "wof:name": "OX28 6NL",
    "wof:placetype": "postalcode"
  },
  "geometry": {"coordinates":[-1.49157,51.785787],"type":"Point"}
}
