{
  "type": "Feature",
  "properties": {
    "iso:country":"GB",
    "wof:name":"OX28 6NL",
    "wof:placetype":"postalcode"
},
  "geometry": {"coordinates":[-1.49157029170143,51.78578732980974],"type":"Point"}
}