{
  "type": "Feature",
  "properties": {
    "iso:country":"GB",
    "wof:name":"BB3 2PG",
    "wof:placetype":"postalcode"
},
  "geometry": {"coordinates":[-2.46533355912157,53.68980858260754],"type":"Point"}
}