{
  "type": "Feature",
  "properties": {
    "date:inception_lower": "1980-01-01",
    "date:inception_upper": "1980-01-01",
    "iso:country": "GB",
    "wof:name": "BB3 2PG",
    "wof:placetype": "postalcode"
  },
  "geometry": {"coordinates":[-2.465331,53.689824],"type":"Point"}
}
