{
  "type": "Feature",
  "properties": {
    "date:inception_lower": "2023-08-01",
    "date:inception_upper": "2023-08-01",
    "iso:country": "GB",
    "wof:name": "BN18 0XD",
    "wof:placetype": "postalcode"
  },
  "geometry": {"coordinates":[-0.618106,50.847622],"type":"Point"}
}
