{
  "type": "Feature",
  "properties": {
    "iso:country": "GB",
    "wof:name": "CT18 7FZ",
    "wof:placetype": "postalcode"
  },
  "geometry": {"coordinates":[1.150835,51.114018],"type":"Point"}
}
