{
  "type": "Feature",
  "properties": {
    "iso:country":"GB",
    "wof:name":"CT18 7FZ",
    "wof:placetype":"postalcode"
},
  "geometry": {"coordinates":[1.15083533198835,51.11401813232026],"type":"Point"}
}