{
  "type": "Feature",
  "properties": {
    "iso:country":"GB",
    "wof:name":"KT6 6HT",
    "wof:placetype":"postalcode"
},
  "geometry": {"coordinates":[-0.30004912292029,51.3936153315144],"type":"Point"}
}