{
  "type": "Feature",
  "properties": {
    "date:inception_lower": "1980-01-01",
    "date:inception_upper": "1980-01-01",
    "iso:country": "GB",
    "wof:name": "TW3 2HB",
    "wof:placetype": "postalcode"
  },
  "geometry": {"coordinates":[-0.358239,51.460548],"type":"Point"}
}
