{
  "type": "Feature",
  "properties": {
    "iso:country":"GB",
    "wof:name":"TW3 2HB",
    "wof:placetype":"postalcode"
},
  "geometry": {"coordinates":[-0.35823873653923,51.46054809979328],"type":"Point"}
}