{
  "type": "Feature",
  "properties": {
    "iso:country":"GB",
    "wof:name":"CF83 2RA",
    "wof:placetype":"postalcode"
},
  "geometry": {"coordinates":[-3.23873366684496,51.58404181888237],"type":"Point"}
}