{
  "type": "Feature",
  "properties": {
    "iso:country":"GB",
    "wof:name":"CR0 7JU",
    "wof:placetype":"postalcode"
},
  "geometry": {"coordinates":[-0.06555349014477,51.37743376186179],"type":"Point"}
}