{
  "type": "Feature",
  "properties": {
    "date:inception_lower":"1980-01-01",
    "date:inception_upper":"1980-01-31",
    "iso:country":"GB",
    "wof:name":"CR0 7JU",
    "wof:placetype":"postalcode"
},
  "geometry": {"coordinates":[-0.065553,51.377434],"type":"Point"}
}