{
  "type": "Feature",
  "properties": {
    "iso:country":"GB",
    "wof:name":"SO52 9AA",
    "wof:placetype":"postalcode"
},
  "geometry": {"coordinates":[-1.44203596129549,50.97926455822469],"type":"Point"}
}