{
  "type": "Feature",
  "properties": {
    "date:inception_lower":"2010-01-01",
    "date:inception_upper":"2010-01-31",
    "iso:country":"GB",
    "wof:name":"SO52 9AA",
    "wof:placetype":"postalcode"
},
  "geometry": {"coordinates":[-1.442036,50.979265],"type":"Point"}
}