{
  "type": "Feature",
  "properties": {
    "iso:country":"GB",
    "wof:name":"DN6 0DL",
    "wof:placetype":"postalcode"
},
  "geometry": {"coordinates":[-1.08779010061306,53.61418333434778],"type":"Point"}
}