{
  "type": "Feature",
  "properties": {
    "iso:country": "GB",
    "wof:name": "DN6 0DL",
    "wof:placetype": "postalcode"
  },
  "geometry": {"coordinates":[-1.08779,53.614183],"type":"Point"}
}
