{
  "type": "Feature",
  "properties": {
    "iso:country":"GB",
    "wof:name":"DT4 9LB",
    "wof:placetype":"postalcode"
},
  "geometry": {"coordinates":[-2.46166159217194,50.59850323173856],"type":"Point"}
}