{
  "type": "Feature",
  "properties": {
    "iso:country":"GB",
    "wof:name":"EX10 9NY",
    "wof:placetype":"postalcode"
},
  "geometry": {"coordinates":[-3.22969439158198,50.70179722342964],"type":"Point"}
}