{
  "type": "Feature",
  "properties": {
    "iso:country": "GB",
    "wof:name": "SN15 3RP",
    "wof:placetype": "postalcode"
  },
  "geometry": {"coordinates":[-2.089626,51.44707],"type":"Point"}
}
