{
  "type": "Feature",
  "properties": {
    "iso:country":"GB",
    "wof:name":"SN15 3RP",
    "wof:placetype":"postalcode"
},
  "geometry": {"coordinates":[-2.0896265208495,51.44707038500442],"type":"Point"}
}