{
  "type": "Feature",
  "properties": {
    "iso:country":"GB",
    "wof:name":"LL12 7YG",
    "wof:placetype":"postalcode"
},
  "geometry": {"coordinates":[-2.97778806165964,53.05967657882323],"type":"Point"}
}