{
  "type": "Feature",
  "properties": {
    "date:inception_lower": "1980-01-01",
    "date:inception_upper": "1980-01-01",
    "iso:country": "GB",
    "wof:name": "LL12 7YG",
    "wof:placetype": "postalcode"
  },
  "geometry": {"coordinates":[-2.977788,53.059677],"type":"Point"}
}
