{
  "type": "Feature",
  "properties": {
    "iso:country": "GB",
    "wof:name": "CF62 3AG",
    "wof:placetype": "postalcode"
  },
  "geometry": {"coordinates":[-3.363672,51.419523],"type":"Point"}
}
