{
  "type": "Feature",
  "properties": {
    "iso:country":"GB",
    "wof:name":"LL12 7NJ",
    "wof:placetype":"postalcode"
},
  "geometry": {"coordinates":[-2.98530063421089,53.05540752593298],"type":"Point"}
}