{
  "type": "Feature",
  "properties": {
    "date:inception_lower": "2008-09-01",
    "date:inception_upper": "2008-09-01",
    "iso:country": "GB",
    "wof:name": "LL12 7NJ",
    "wof:placetype": "postalcode"
  },
  "geometry": {"coordinates":[-2.985301,53.055408],"type":"Point"}
}
