{
  "type": "Feature",
  "properties": {
    "iso:country": "GB",
    "wof:name": "LL12 7NJ",
    "wof:placetype": "postalcode"
  },
  "geometry": {"coordinates":[-2.985301,53.055408],"type":"Point"}
}
