{
  "type": "Feature",
  "properties": {
    "date:inception_lower": "1980-01-01",
    "date:inception_upper": "1980-01-01",
    "iso:country": "GB",
    "wof:name": "WF3 4NF",
    "wof:placetype": "postalcode"
  },
  "geometry": {"coordinates":[-1.48089,53.701203],"type":"Point"}
}
