{
  "type": "Feature",
  "properties": {
    "iso:country":"GB",
    "wof:name":"WF3 4NF",
    "wof:placetype":"postalcode"
},
  "geometry": {"coordinates":[-1.48089048509886,53.7012025503711],"type":"Point"}
}