{
  "type": "Feature",
  "properties": {
    "iso:country": "GB",
    "wof:name": "DL6 2QF",
    "wof:placetype": "postalcode"
  },
  "geometry": {"coordinates":[-1.432894,54.355266],"type":"Point"}
}
