{
  "type": "Feature",
  "properties": {
    "date:inception_lower": "1980-01-01",
    "date:inception_upper": "1980-01-01",
    "iso:country": "GB",
    "wof:name": "G46 7JF",
    "wof:placetype": "postalcode"
  },
  "geometry": {"coordinates":[-4.31304,55.799398],"type":"Point"}
}
