{
  "type": "Feature",
  "properties": {
    "iso:country":"GB",
    "wof:name":"G46 7JF",
    "wof:placetype":"postalcode"
},
  "geometry": {"coordinates":[-4.31303978797542,55.79939795413478],"type":"Point"}
}