{
  "type": "Feature",
  "properties": {
    "iso:country": "GB",
    "wof:name": "G46 7JF",
    "wof:placetype": "postalcode"
  },
  "geometry": {"coordinates":[-4.31304,55.799398],"type":"Point"}
}
