{
  "type": "Feature",
  "properties": {
    "date:inception_lower": "1995-01-01",
    "date:inception_upper": "1995-01-01",
    "iso:country": "GB",
    "wof:name": "LE6 0HL",
    "wof:placetype": "postalcode"
  },
  "geometry": {"coordinates":[-1.233943,52.644357],"type":"Point"}
}
