{
  "type": "Feature",
  "properties": {
    "iso:country":"GB",
    "wof:name":"LE6 0HL",
    "wof:placetype":"postalcode"
},
  "geometry": {"coordinates":[-1.23394342095076,52.64435706416685],"type":"Point"}
}