{
  "type": "Feature",
  "properties": {
    "iso:country":"GB",
    "wof:name":"DN5 9ES",
    "wof:placetype":"postalcode"
},
  "geometry": {"coordinates":[-1.16468328475996,53.54077760910566],"type":"Point"}
}