{
  "type": "Feature",
  "properties": {
    "date:inception_lower":"1980-01-01",
    "date:inception_upper":"1980-01-31",
    "iso:country":"GB",
    "wof:name":"CH3 8HD",
    "wof:placetype":"postalcode"
},
  "geometry": {"coordinates":[-2.76233,53.187569],"type":"Point"}
}