{
  "type": "Feature",
  "properties": {
    "iso:country":"GB",
    "wof:name":"CH3 8HD",
    "wof:placetype":"postalcode"
},
  "geometry": {"coordinates":[-2.76232961443957,53.18756878020608],"type":"Point"}
}