{
  "type": "Feature",
  "properties": {
    "iso:country": "GB",
    "wof:name": "DE74 2RS",
    "wof:placetype": "postalcode"
  },
  "geometry": {"coordinates":[-1.374964,52.841555],"type":"Point"}
}
