{
  "type": "Feature",
  "properties": {
    "iso:country":"GB",
    "wof:name":"DE74 2RS",
    "wof:placetype":"postalcode"
},
  "geometry": {"coordinates":[-1.37496382179348,52.84155545752453],"type":"Point"}
}