{
  "type": "Feature",
  "properties": {
    "date:inception_lower": "1997-06-01",
    "date:inception_upper": "1997-06-01",
    "iso:country": "GB",
    "wof:name": "PR4 0LX",
    "wof:placetype": "postalcode"
  },
  "geometry": {"coordinates":[-2.751637,53.788816],"type":"Point"}
}
