{
  "type": "Feature",
  "properties": {
    "iso:country":"GB",
    "wof:name":"NN6 0PB",
    "wof:placetype":"postalcode"
},
  "geometry": {"coordinates":[-0.74861697010149,52.26171518886069],"type":"Point"}
}