{
  "type": "Feature",
  "properties": {
    "date:inception_lower": "1980-01-01",
    "date:inception_upper": "1980-01-01",
    "iso:country": "GB",
    "wof:name": "NN6 0PB",
    "wof:placetype": "postalcode"
  },
  "geometry": {"coordinates":[-0.748617,52.261715],"type":"Point"}
}
