{
  "type": "Feature",
  "properties": {
    "date:inception_lower": "2023-06-01",
    "date:inception_upper": "2023-06-01",
    "iso:country": "GB",
    "wof:name": "SO16 0AZ",
    "wof:placetype": "postalcode"
  },
  "geometry": {"coordinates":[-1.467166,50.93844],"type":"Point"}
}
