{
  "type": "Feature",
  "properties": {
    "iso:country":"GB",
    "wof:name":"M9 4NE",
    "wof:placetype":"postalcode"
},
  "geometry": {"coordinates":[-2.20316382330862,53.50728779042538],"type":"Point"}
}