{
  "type": "Feature",
  "properties": {
    "iso:country": "GB",
    "wof:name": "BS24 8FE",
    "wof:placetype": "postalcode"
  },
  "geometry": {"coordinates":[-2.952474,51.334023],"type":"Point"}
}
