{
  "type": "Feature",
  "properties": {
    "date:inception_lower":"1998-12-01",
    "date:inception_upper":"1998-12-31",
    "iso:country":"GB",
    "wof:name":"TA6 4RN",
    "wof:placetype":"postalcode"
},
  "geometry": {"coordinates":[-2.994789,51.148585],"type":"Point"}
}