{
  "type": "Feature",
  "properties": {
    "date:inception_lower": "2002-12-01",
    "date:inception_upper": "2002-12-01",
    "iso:country": "GB",
    "wof:name": "BB7 9RA",
    "wof:placetype": "postalcode"
  },
  "geometry": {"coordinates":[-2.424976,53.832339],"type":"Point"}
}
