{
  "type": "Feature",
  "properties": {
    "iso:country":"GB",
    "wof:name":"BB7 9RA",
    "wof:placetype":"postalcode"
},
  "geometry": {"coordinates":[-2.42497644866004,53.83233889964609],"type":"Point"}
}