{
  "type": "Feature",
  "properties": {
    "iso:country": "GB",
    "wof:name": "LA1 1ST",
    "wof:placetype": "postalcode"
  },
  "geometry": {"coordinates":[-2.803543,54.042957],"type":"Point"}
}
