{
  "type": "Feature",
  "properties": {
    "iso:country": "GB",
    "wof:name": "DE7 9JE",
    "wof:placetype": "postalcode"
  },
  "geometry": {"coordinates":[-1.327062,52.984073],"type":"Point"}
}
