{
  "type": "Feature",
  "properties": {
    "iso:country":"GB",
    "wof:name":"DE7 9JE",
    "wof:placetype":"postalcode"
},
  "geometry": {"coordinates":[-1.32706227999712,52.98407340477144],"type":"Point"}
}