{
  "type": "Feature",
  "properties": {
    "date:inception_lower": "1992-08-01",
    "date:inception_upper": "1992-08-01",
    "iso:country": "GB",
    "wof:name": "DE7 9JE",
    "wof:placetype": "postalcode"
  },
  "geometry": {"coordinates":[-1.327062,52.984073],"type":"Point"}
}
