{
  "type": "Feature",
  "properties": {
    "iso:country":"GB",
    "wof:name":"S12 3AQ",
    "wof:placetype":"postalcode"
},
  "geometry": {"coordinates":[-1.39668633761715,53.34337988222828],"type":"Point"}
}