{
  "type": "Feature",
  "properties": {
    "iso:country": "GB",
    "wof:name": "S12 3AQ",
    "wof:placetype": "postalcode"
  },
  "geometry": {"coordinates":[-1.396671,53.343381],"type":"Point"}
}
