{
  "type": "Feature",
  "properties": {
    "date:inception_lower": "1984-10-01",
    "date:inception_upper": "1984-10-01",
    "iso:country": "GB",
    "wof:name": "LS15 8XB",
    "wof:placetype": "postalcode"
  },
  "geometry": {"coordinates":[-1.425821,53.809825],"type":"Point"}
}
