{
  "type": "Feature",
  "properties": {
    "iso:country":"GB",
    "wof:name":"LS15 8XB",
    "wof:placetype":"postalcode"
},
  "geometry": {"coordinates":[-1.42582109659171,53.80982491135732],"type":"Point"}
}