{
  "type": "Feature",
  "properties": {
    "iso:country": "GB",
    "wof:name": "LN1 2SA",
    "wof:placetype": "postalcode"
  },
  "geometry": {"coordinates":[-0.65801,53.31089],"type":"Point"}
}
