{
  "type": "Feature",
  "properties": {
    "date:inception_lower":"2018-10-01",
    "date:inception_upper":"2018-10-31",
    "iso:country":"GB",
    "wof:name":"LN1 2SA",
    "wof:placetype":"postalcode"
},
  "geometry": {"coordinates":[-0.65801,53.31089],"type":"Point"}
}