{
  "type": "Feature",
  "properties": {
    "iso:country":"GB",
    "wof:name":"GL7 2RN",
    "wof:placetype":"postalcode"
},
  "geometry": {"coordinates":[-1.97555264445015,51.73473479614032],"type":"Point"}
}