{
  "type": "Feature",
  "properties": {
    "date:inception_lower":"1982-12-01",
    "date:inception_upper":"1982-12-31",
    "iso:country":"GB",
    "wof:name":"G23 5LP",
    "wof:placetype":"postalcode"
},
  "geometry": {"coordinates":[-4.284179,55.901811],"type":"Point"}
}