{
  "type": "Feature",
  "properties": {
    "iso:country":"GB",
    "wof:name":"NE23 2AA",
    "wof:placetype":"postalcode"
},
  "geometry": {"coordinates":[-1.57150130579243,55.08540975640695],"type":"Point"}
}