{
  "type": "Feature",
  "properties": {
    "iso:country":"GB",
    "wof:name":"S75 3SG",
    "wof:placetype":"postalcode"
},
  "geometry": {"coordinates":[-1.52941125725883,53.54302883829318],"type":"Point"}
}