{
  "type": "Feature",
  "properties": {
    "iso:country":"GB",
    "wof:name":"TS5 7DE",
    "wof:placetype":"postalcode"
},
  "geometry": {"coordinates":[-1.25452727001293,54.5464971602306],"type":"Point"}
}