{
  "type": "Feature",
  "properties": {
    "date:inception_lower": "2022-08-01",
    "date:inception_upper": "2022-08-01",
    "iso:country": "GB",
    "wof:name": "NP44 1FU",
    "wof:placetype": "postalcode"
  },
  "geometry": {"coordinates":[-3.029,51.673011],"type":"Point"}
}
