{
  "type": "Feature",
  "properties": {
    "iso:country":"GB",
    "wof:name":"PE6 0JU",
    "wof:placetype":"postalcode"
},
  "geometry": {"coordinates":[-0.08158210100933,52.69422263105036],"type":"Point"}
}