{
  "type": "Feature",
  "properties": {
    "iso:country": "GB",
    "wof:name": "PE6 0JU",
    "wof:placetype": "postalcode"
  },
  "geometry": {"coordinates":[-0.081582,52.694223],"type":"Point"}
}
