{
  "type": "Feature",
  "properties": {
    "date:inception_lower":"1992-08-01",
    "date:inception_upper":"1992-08-31",
    "iso:country":"GB",
    "wof:name":"LE65 1ER",
    "wof:placetype":"postalcode"
},
  "geometry": {"coordinates":[-1.463589,52.742016],"type":"Point"}
}