{
  "type": "Feature",
  "properties": {
    "iso:country":"GB",
    "wof:name":"RG42 1YT",
    "wof:placetype":"postalcode"
},
  "geometry": {"coordinates":[-0.75970813552755,51.42017997107926],"type":"Point"}
}