{
  "type": "Feature",
  "properties": {
    "iso:country":"GB",
    "wof:name":"PL14 4AQ",
    "wof:placetype":"postalcode"
},
  "geometry": {"coordinates":[-4.46598558520046,50.45368503611525],"type":"Point"}
}