{
  "type": "Feature",
  "properties": {
    "iso:country": "GB",
    "wof:name": "PL14 4AQ",
    "wof:placetype": "postalcode"
  },
  "geometry": {"coordinates":[-4.465986,50.453685],"type":"Point"}
}
