{
  "type": "Feature",
  "properties": {
    "iso:country":"GB",
    "wof:name":"PA34 5NS",
    "wof:placetype":"postalcode"
},
  "geometry": {"coordinates":[-5.4735434067217,56.41587629184853],"type":"Point"}
}