{
  "type": "Feature",
  "properties": {
    "date:inception_lower": "1980-01-01",
    "date:inception_upper": "1980-01-01",
    "iso:country": "GB",
    "wof:name": "PA34 5NS",
    "wof:placetype": "postalcode"
  },
  "geometry": {"coordinates":[-5.473543,56.415876],"type":"Point"}
}
