{
  "type": "Feature",
  "properties": {
    "iso:country":"GB",
    "wof:name":"IP20 0LH",
    "wof:placetype":"postalcode"
},
  "geometry": {"coordinates":[1.36758066941731,52.37262778226021],"type":"Point"}
}