{
  "type": "Feature",
  "properties": {
    "date:inception_lower": "1980-01-01",
    "date:inception_upper": "1980-01-01",
    "iso:country": "GB",
    "wof:name": "IP20 0LH",
    "wof:placetype": "postalcode"
  },
  "geometry": {"coordinates":[1.367568,52.372677],"type":"Point"}
}
