{
  "type": "Feature",
  "properties": {
    "iso:country":"GB",
    "wof:name":"FY6 7RR",
    "wof:placetype":"postalcode"
},
  "geometry": {"coordinates":[-3.0061232381176,53.84310896301655],"type":"Point"}
}