{
  "type": "Feature",
  "properties": {
    "date:inception_lower": "1980-01-01",
    "date:inception_upper": "1980-01-01",
    "iso:country": "GB",
    "wof:name": "FY6 7RR",
    "wof:placetype": "postalcode"
  },
  "geometry": {"coordinates":[-3.006123,53.843109],"type":"Point"}
}
