{
  "type": "Feature",
  "properties": {
    "iso:country":"GB",
    "wof:name":"SR8 4EJ",
    "wof:placetype":"postalcode"
},
  "geometry": {"coordinates":[-1.31120697774162,54.76055909577293],"type":"Point"}
}