{
  "type": "Feature",
  "properties": {
    "iso:country": "GB",
    "wof:name": "SR8 4EJ",
    "wof:placetype": "postalcode"
  },
  "geometry": {"coordinates":[-1.311207,54.760559],"type":"Point"}
}
