{
  "type": "Feature",
  "properties": {
    "iso:country": "GB",
    "wof:name": "BS20 7FE",
    "wof:placetype": "postalcode"
  },
  "geometry": {"coordinates":[-2.769183,51.482606],"type":"Point"}
}
