{
  "type": "Feature",
  "properties": {
    "iso:country": "GB",
    "wof:name": "TN28 8ST",
    "wof:placetype": "postalcode"
  },
  "geometry": {"coordinates":[0.962346,50.96855],"type":"Point"}
}
