{
  "type": "Feature",
  "properties": {
    "iso:country":"GB",
    "wof:name":"TN28 8ST",
    "wof:placetype":"postalcode"
},
  "geometry": {"coordinates":[0.96224342395411,50.96862347262308],"type":"Point"}
}