{
  "type": "Feature",
  "properties": {
    "iso:country":"GB",
    "wof:name":"BS4 5BY",
    "wof:placetype":"postalcode"
},
  "geometry": {"coordinates":[-2.55244835843146,51.43007567568435],"type":"Point"}
}