{
  "type": "Feature",
  "properties": {
    "iso:country":"GB",
    "wof:name":"NN17 1TU",
    "wof:placetype":"postalcode"
},
  "geometry": {"coordinates":[-0.6988573186385,52.48864224714081],"type":"Point"}
}