{
  "type": "Feature",
  "properties": {
    "date:inception_lower":"1998-12-01",
    "date:inception_upper":"1998-12-31",
    "iso:country":"GB",
    "wof:name":"NN17 1TU",
    "wof:placetype":"postalcode"
},
  "geometry": {"coordinates":[-0.698857,52.488642],"type":"Point"}
}