{
  "type": "Feature",
  "properties": {
    "iso:country": "GB",
    "wof:name": "NN17 1TU",
    "wof:placetype": "postalcode"
  },
  "geometry": {"coordinates":[-0.698857,52.488642],"type":"Point"}
}
