{
  "type": "Feature",
  "properties": {
    "iso:country":"GB",
    "wof:name":"LS27 9QS",
    "wof:placetype":"postalcode"
},
  "geometry": {"coordinates":[-1.61276920034532,53.75311316965662],"type":"Point"}
}