{
  "type": "Feature",
  "properties": {
    "date:inception_lower": "1980-01-01",
    "date:inception_upper": "1980-01-01",
    "iso:country": "GB",
    "wof:name": "LS27 9QS",
    "wof:placetype": "postalcode"
  },
  "geometry": {"coordinates":[-1.612788,53.75312],"type":"Point"}
}
