{
  "type": "Feature",
  "properties": {
    "date:inception_lower": "2022-05-01",
    "date:inception_upper": "2022-05-01",
    "iso:country": "GB",
    "wof:name": "W13 3AL",
    "wof:placetype": "postalcode"
  },
  "geometry": {"coordinates":[-0.321609,51.513922],"type":"Point"}
}
