{
  "type": "Feature",
  "properties": {
    "iso:country": "GB",
    "wof:name": "W13 3AL",
    "wof:placetype": "postalcode"
  },
  "geometry": {"coordinates":[-0.321609,51.513922],"type":"Point"}
}
