{
  "type": "Feature",
  "properties": {
    "iso:country":"GB",
    "wof:name":"BD21 4PL",
    "wof:placetype":"postalcode"
},
  "geometry": {"coordinates":[-1.89376005972729,53.86675022613336],"type":"Point"}
}