{
  "type": "Feature",
  "properties": {
    "iso:country":"GB",
    "wof:name":"PO22 9JP",
    "wof:placetype":"postalcode"
},
  "geometry": {"coordinates":[-0.67700517834219,50.79948071805178],"type":"Point"}
}