{
  "type": "Feature",
  "properties": {
    "date:inception_lower": "1980-01-01",
    "date:inception_upper": "1980-01-01",
    "iso:country": "GB",
    "wof:name": "PO22 9JP",
    "wof:placetype": "postalcode"
  },
  "geometry": {"coordinates":[-0.677005,50.799481],"type":"Point"}
}
