{
  "type": "Feature",
  "properties": {
    "iso:country":"GB",
    "wof:name":"WF17 0RH",
    "wof:placetype":"postalcode"
},
  "geometry": {"coordinates":[-1.64176772183071,53.7332856658248],"type":"Point"}
}