{
  "type": "Feature",
  "properties": {
    "date:inception_lower":"1980-01-01",
    "date:inception_upper":"1980-01-31",
    "iso:country":"GB",
    "wof:name":"TD5 7SW",
    "wof:placetype":"postalcode"
},
  "geometry": {"coordinates":[-2.422537,55.606826],"type":"Point"}
}