{
  "type": "Feature",
  "properties": {
    "iso:country": "GB",
    "wof:name": "B92 7PJ",
    "wof:placetype": "postalcode"
  },
  "geometry": {"coordinates":[-1.793183,52.453995],"type":"Point"}
}
