{
  "type": "Feature",
  "properties": {
    "iso:country":"GB",
    "wof:name":"PE12 8SY",
    "wof:placetype":"postalcode"
},
  "geometry": {"coordinates":[0.0289774855227,52.75452797995797],"type":"Point"}
}