{
  "type": "Feature",
  "properties": {
    "iso:country": "GB",
    "wof:name": "CA2 6SP",
    "wof:placetype": "postalcode"
  },
  "geometry": {"coordinates":[-2.978106,54.886702],"type":"Point"}
}
