{
  "type": "Feature",
  "properties": {
    "iso:country":"GB",
    "wof:name":"CA2 6SP",
    "wof:placetype":"postalcode"
},
  "geometry": {"coordinates":[-2.97810594402976,54.88670222337446],"type":"Point"}
}