{
  "type": "Feature",
  "properties": {
    "iso:country":"GB",
    "wof:name":"M22 1BT",
    "wof:placetype":"postalcode"
},
  "geometry": {"coordinates":[-2.27665263661795,53.37761553848421],"type":"Point"}
}