{
  "type": "Feature",
  "properties": {
    "iso:country": "GB",
    "wof:name": "M22 1BT",
    "wof:placetype": "postalcode"
  },
  "geometry": {"coordinates":[-2.276653,53.377616],"type":"Point"}
}
