{
  "type": "Feature",
  "properties": {
    "iso:country":"GB",
    "wof:name":"LE14 4QG",
    "wof:placetype":"postalcode"
},
  "geometry": {"coordinates":[-0.8528032039044,52.81586766112032],"type":"Point"}
}