{
  "type": "Feature",
  "properties": {
    "date:inception_lower": "1980-01-01",
    "date:inception_upper": "1980-01-01",
    "iso:country": "GB",
    "wof:name": "EX19 8AQ",
    "wof:placetype": "postalcode"
  },
  "geometry": {"coordinates":[-4.055846,50.921711],"type":"Point"}
}
