{
  "type": "Feature",
  "properties": {
    "iso:country":"GB",
    "wof:name":"EX19 8AQ",
    "wof:placetype":"postalcode"
},
  "geometry": {"coordinates":[-4.05584586765432,50.92171114298017],"type":"Point"}
}