{
  "type": "Feature",
  "properties": {
    "iso:country": "GB",
    "wof:name": "TF9 4LF",
    "wof:placetype": "postalcode"
  },
  "geometry": {"coordinates":[-2.355514,52.925782],"type":"Point"}
}
