{
  "type": "Feature",
  "properties": {
    "iso:country":"GB",
    "wof:name":"TF9 4LF",
    "wof:placetype":"postalcode"
},
  "geometry": {"coordinates":[-2.35551361707553,52.92578211537109],"type":"Point"}
}