{
  "type": "Feature",
  "properties": {
    "date:inception_lower": "2003-06-01",
    "date:inception_upper": "2003-06-01",
    "iso:country": "GB",
    "wof:name": "SE13 6TQ",
    "wof:placetype": "postalcode"
  },
  "geometry": {"coordinates":[-0.002466,51.447823],"type":"Point"}
}
