{
  "type": "Feature",
  "properties": {
    "iso:country": "GB",
    "wof:name": "SE13 6TQ",
    "wof:placetype": "postalcode"
  },
  "geometry": {"coordinates":[-0.002466,51.447823],"type":"Point"}
}
