{
  "type": "Feature",
  "properties": {
    "iso:country":"GB",
    "wof:name":"KA18 3AX",
    "wof:placetype":"postalcode"
},
  "geometry": {"coordinates":[-4.24087201088648,55.44320334191267],"type":"Point"}
}