{
  "type": "Feature",
  "properties": {
    "iso:country":"GB",
    "wof:name":"MK42 0UL",
    "wof:placetype":"postalcode"
},
  "geometry": {"coordinates":[-0.43468180722412,52.10921953148129],"type":"Point"}
}