{
  "type": "Feature",
  "properties": {
    "iso:country": "GB",
    "wof:name": "NE5 3TJ",
    "wof:placetype": "postalcode"
  },
  "geometry": {"coordinates":[-1.674559,54.997386],"type":"Point"}
}
