{
  "type": "Feature",
  "properties": {
    "iso:country": "GB",
    "wof:name": "L6 9AF",
    "wof:placetype": "postalcode"
  },
  "geometry": {"coordinates":[-2.957154,53.415014],"type":"Point"}
}
