{
  "type": "Feature",
  "properties": {
    "date:inception_lower": "1994-05-01",
    "date:inception_upper": "1994-05-01",
    "iso:country": "GB",
    "wof:name": "SL1 2EL",
    "wof:placetype": "postalcode"
  },
  "geometry": {"coordinates":[-0.596438,51.507208],"type":"Point"}
}
