{
  "type": "Feature",
  "properties": {
    "date:inception_lower": "1980-01-01",
    "date:inception_upper": "1980-01-01",
    "iso:country": "GB",
    "wof:name": "NN16 8DB",
    "wof:placetype": "postalcode"
  },
  "geometry": {"coordinates":[-0.73342,52.399498],"type":"Point"}
}
