{
  "type": "Feature",
  "properties": {
    "date:inception_lower": "2003-08-01",
    "date:inception_upper": "2003-08-01",
    "iso:country": "GB",
    "wof:name": "PL5 3UW",
    "wof:placetype": "postalcode"
  },
  "geometry": {"coordinates":[-4.143828,50.405618],"type":"Point"}
}
