{
  "type": "Feature",
  "properties": {
    "iso:country":"GB",
    "wof:name":"PL5 3UW",
    "wof:placetype":"postalcode"
},
  "geometry": {"coordinates":[-4.1438285100083,50.40561777679467],"type":"Point"}
}