{
  "type": "Feature",
  "properties": {
    "iso:country":"GB",
    "wof:name":"CV12 9BQ",
    "wof:placetype":"postalcode"
},
  "geometry": {"coordinates":[-1.46299079187101,52.48645821724096],"type":"Point"}
}