{
  "type": "Feature",
  "properties": {
    "iso:country": "GB",
    "wof:name": "NE62 5DZ",
    "wof:placetype": "postalcode"
  },
  "geometry": {"coordinates":[-1.59992,55.162193],"type":"Point"}
}
