{
  "type": "Feature",
  "properties": {
    "iso:country":"GB",
    "wof:name":"AB56 5UN",
    "wof:placetype":"postalcode"
},
  "geometry": {"coordinates":[-2.85134769530442,57.62287483341097],"type":"Point"}
}