{
  "type": "Feature",
  "properties": {
    "iso:country": "GB",
    "wof:name": "AB56 5UN",
    "wof:placetype": "postalcode"
  },
  "geometry": {"coordinates":[-2.853523,57.62279],"type":"Point"}
}
