{
  "type": "Feature",
  "properties": {
    "date:inception_lower":"1980-01-01",
    "date:inception_upper":"1980-01-31",
    "iso:country":"GB",
    "wof:name":"B78 1LP",
    "wof:placetype":"postalcode"
},
  "geometry": {"coordinates":[-1.613986,52.615315],"type":"Point"}
}