{
  "type": "Feature",
  "properties": {
    "date:inception_lower":"2008-03-01",
    "date:inception_upper":"2008-03-31",
    "iso:country":"GB",
    "wof:name":"DH9 7JA",
    "wof:placetype":"postalcode"
},
  "geometry": {"coordinates":[-1.725075,54.860496],"type":"Point"}
}