{
  "type": "Feature",
  "properties": {
    "iso:country": "GB",
    "wof:name": "DH9 7JA",
    "wof:placetype": "postalcode"
  },
  "geometry": {"coordinates":[-1.725075,54.860496],"type":"Point"}
}
