{
  "type": "Feature",
  "properties": {
    "date:inception_lower": "1980-01-01",
    "date:inception_upper": "1980-01-01",
    "iso:country": "GB",
    "wof:name": "DN9 3NJ",
    "wof:placetype": "postalcode"
  },
  "geometry": {"coordinates":[-1.023184,53.487589],"type":"Point"}
}
