{
  "type": "Feature",
  "properties": {
    "iso:country":"GB",
    "wof:name":"DN9 3NJ",
    "wof:placetype":"postalcode"
},
  "geometry": {"coordinates":[-1.02318433901795,53.48758895139561],"type":"Point"}
}