{
  "type": "Feature",
  "properties": {
    "iso:country": "GB",
    "wof:name": "DN9 3NJ",
    "wof:placetype": "postalcode"
  },
  "geometry": {"coordinates":[-1.023184,53.487589],"type":"Point"}
}
