{
  "type": "Feature",
  "properties": {
    "iso:country":"GB",
    "wof:name":"SM4 6RS",
    "wof:placetype":"postalcode"
},
  "geometry": {"coordinates":[-0.18937927621748,51.38968242193277],"type":"Point"}
}