{
  "type": "Feature",
  "properties": {
    "date:inception_lower":"1980-01-01",
    "date:inception_upper":"1980-01-31",
    "iso:country":"GB",
    "wof:name":"LS20 8EH",
    "wof:placetype":"postalcode"
},
  "geometry": {"coordinates":[-1.717175,53.869664],"type":"Point"}
}