{
  "type": "Feature",
  "properties": {
    "iso:country":"GB",
    "wof:name":"LS20 8EH",
    "wof:placetype":"postalcode"
},
  "geometry": {"coordinates":[-1.71717553423809,53.86966410060498],"type":"Point"}
}