{
  "type": "Feature",
  "properties": {
    "date:inception_lower": "2003-05-01",
    "date:inception_upper": "2003-05-01",
    "iso:country": "GB",
    "wof:name": "DD8 2DS",
    "wof:placetype": "postalcode"
  },
  "geometry": {"coordinates":[-2.8799,56.639412],"type":"Point"}
}
