{
  "type": "Feature",
  "properties": {
    "date:inception_lower": "1992-01-01",
    "date:inception_upper": "1992-01-01",
    "iso:country": "GB",
    "wof:name": "CM24 1RL",
    "wof:placetype": "postalcode"
  },
  "geometry": {"coordinates":[0.243471,51.877942],"type":"Point"}
}
