{
  "type": "Feature",
  "properties": {
    "iso:country":"GB",
    "wof:name":"EN10 6BN",
    "wof:placetype":"postalcode"
},
  "geometry": {"coordinates":[-0.02240486631618,51.72326102692934],"type":"Point"}
}