{
  "type": "Feature",
  "properties": {
    "date:inception_lower": "1980-01-01",
    "date:inception_upper": "1980-01-01",
    "iso:country": "GB",
    "wof:name": "S60 3BX",
    "wof:placetype": "postalcode"
  },
  "geometry": {"coordinates":[-1.343646,53.410156],"type":"Point"}
}
