{
  "type": "Feature",
  "properties": {
    "iso:country":"GB",
    "wof:name":"S60 3BX",
    "wof:placetype":"postalcode"
},
  "geometry": {"coordinates":[-1.34364629005773,53.4101562299856],"type":"Point"}
}