{
  "type": "Feature",
  "properties": {
    "date:inception_lower":"1995-01-01",
    "date:inception_upper":"1995-01-31",
    "iso:country":"GB",
    "wof:name":"PO4 9XX",
    "wof:placetype":"postalcode"
},
  "geometry": {"coordinates":[-1.052582,50.786669],"type":"Point"}
}