{
  "type": "Feature",
  "properties": {
    "date:inception_lower": "1980-01-01",
    "date:inception_upper": "1980-01-01",
    "iso:country": "GB",
    "wof:name": "WA4 4RX",
    "wof:placetype": "postalcode"
  },
  "geometry": {"coordinates":[-2.545079,53.34701],"type":"Point"}
}
