{
  "type": "Feature",
  "properties": {
    "iso:country":"GB",
    "wof:name":"WA4 4RX",
    "wof:placetype":"postalcode"
},
  "geometry": {"coordinates":[-2.54507861027036,53.34701035146161],"type":"Point"}
}