{
  "type": "Feature",
  "properties": {
    "iso:country":"GB",
    "wof:name":"CV3 5GL",
    "wof:placetype":"postalcode"
},
  "geometry": {"coordinates":[-1.50283266056495,52.39561643557462],"type":"Point"}
}