{
  "type": "Feature",
  "properties": {
    "iso:country":"GB",
    "wof:name":"TQ1 1SQ",
    "wof:placetype":"postalcode"
},
  "geometry": {"coordinates":[-3.50819638891114,50.46876021661671],"type":"Point"}
}