{
  "type": "Feature",
  "properties": {
    "date:inception_lower": "1980-01-01",
    "date:inception_upper": "1980-01-01",
    "iso:country": "GB",
    "wof:name": "TQ1 1SQ",
    "wof:placetype": "postalcode"
  },
  "geometry": {"coordinates":[-3.508196,50.46876],"type":"Point"}
}
