{
  "type": "Feature",
  "properties": {
    "iso:country":"GB",
    "wof:name":"NE33 5LF",
    "wof:placetype":"postalcode"
},
  "geometry": {"coordinates":[-1.43722235600369,54.98211484199395],"type":"Point"}
}