{
  "type": "Feature",
  "properties": {
    "iso:country":"GB",
    "wof:name":"SP2 0QF",
    "wof:placetype":"postalcode"
},
  "geometry": {"coordinates":[-1.87872926075913,51.11055988713108],"type":"Point"}
}