{
  "type": "Feature",
  "properties": {
    "date:inception_lower": "2017-07-01",
    "date:inception_upper": "2017-07-01",
    "iso:country": "GB",
    "wof:name": "ST18 0GD",
    "wof:placetype": "postalcode"
  },
  "geometry": {"coordinates":[-2.075951,52.80753],"type":"Point"}
}
