{
  "type": "Feature",
  "properties": {
    "iso:country": "GB",
    "wof:name": "L9 1AF",
    "wof:placetype": "postalcode"
  },
  "geometry": {"coordinates":[-2.96284,53.453584],"type":"Point"}
}
