{
  "type": "Feature",
  "properties": {
    "date:inception_lower": "1980-01-01",
    "date:inception_upper": "1980-01-01",
    "iso:country": "GB",
    "wof:name": "L9 1AF",
    "wof:placetype": "postalcode"
  },
  "geometry": {"coordinates":[-2.962768,53.453719],"type":"Point"}
}
