{
  "type": "Feature",
  "properties": {
    "iso:country":"GB",
    "wof:name":"CB9 7ED",
    "wof:placetype":"postalcode"
},
  "geometry": {"coordinates":[0.44707895845833,52.03998637988322],"type":"Point"}
}