{
  "type": "Feature",
  "properties": {
    "iso:country":"GB",
    "wof:name":"IG6 2TW",
    "wof:placetype":"postalcode"
},
  "geometry": {"coordinates":[0.07980160462418,51.60451174595654],"type":"Point"}
}