{
  "type": "Feature",
  "properties": {
    "iso:country":"GB",
    "wof:name":"RG12 9YT",
    "wof:placetype":"postalcode"
},
  "geometry": {"coordinates":[-0.72381406842764,51.40354600547196],"type":"Point"}
}