{
  "type": "Feature",
  "properties": {
    "iso:country":"GB",
    "wof:name":"WA9 2HS",
    "wof:placetype":"postalcode"
},
  "geometry": {"coordinates":[-2.69171414145767,53.45344100451281],"type":"Point"}
}