{
  "type": "Feature",
  "properties": {
    "iso:country":"GB",
    "wof:name":"BN22 0AH",
    "wof:placetype":"postalcode"
},
  "geometry": {"coordinates":[0.2668960006814,50.79698887510046],"type":"Point"}
}