{
  "type": "Feature",
  "properties": {
    "iso:country": "GB",
    "wof:name": "M34 3EA",
    "wof:placetype": "postalcode"
  },
  "geometry": {"coordinates":[-2.105107,53.455902],"type":"Point"}
}
