{
  "type": "Feature",
  "properties": {
    "iso:country":"GB",
    "wof:name":"SK16 4XX",
    "wof:placetype":"postalcode"
},
  "geometry": {"coordinates":[-2.08873065774829,53.46729441066901],"type":"Point"}
}