{
  "type": "Feature",
  "properties": {
    "date:inception_lower": "1990-07-01",
    "date:inception_upper": "1990-07-01",
    "iso:country": "GB",
    "wof:name": "SK16 4XX",
    "wof:placetype": "postalcode"
  },
  "geometry": {"coordinates":[-2.088731,53.467294],"type":"Point"}
}
