{
  "type": "Feature",
  "properties": {
    "iso:country":"GB",
    "wof:name":"EH26 9BP",
    "wof:placetype":"postalcode"
},
  "geometry": {"coordinates":[-3.22461597797979,55.82759346629572],"type":"Point"}
}