{
  "type": "Feature",
  "properties": {
    "iso:country": "GB",
    "wof:name": "EH26 9BP",
    "wof:placetype": "postalcode"
  },
  "geometry": {"coordinates":[-3.224616,55.827593],"type":"Point"}
}
