{
  "type": "Feature",
  "properties": {
    "iso:country":"GB",
    "wof:name":"ME1 2HY",
    "wof:placetype":"postalcode"
},
  "geometry": {"coordinates":[0.50575675623413,51.37692095031555],"type":"Point"}
}