{
  "type": "Feature",
  "properties": {
    "iso:country": "GB",
    "wof:name": "ME1 2HY",
    "wof:placetype": "postalcode"
  },
  "geometry": {"coordinates":[0.505757,51.376921],"type":"Point"}
}
