{
  "type": "Feature",
  "properties": {
    "iso:country":"GB",
    "wof:name":"SY1 4PN",
    "wof:placetype":"postalcode"
},
  "geometry": {"coordinates":[-2.7197113685802,52.73254683095376],"type":"Point"}
}