{
  "type": "Feature",
  "properties": {
    "date:inception_lower": "2023-04-01",
    "date:inception_upper": "2023-04-01",
    "iso:country": "GB",
    "wof:name": "S35 0BY",
    "wof:placetype": "postalcode"
  },
  "geometry": {"coordinates":[-1.545449,53.443354],"type":"Point"}
}
