{
  "type": "Feature",
  "properties": {
    "iso:country":"GB",
    "wof:name":"S65 1QT",
    "wof:placetype":"postalcode"
},
  "geometry": {"coordinates":[-1.34570879272952,53.43751113797057],"type":"Point"}
}