{
  "type": "Feature",
  "properties": {
    "iso:country":"GB",
    "wof:name":"EX21 5ST",
    "wof:placetype":"postalcode"
},
  "geometry": {"coordinates":[-4.20109719386592,50.85151881899352],"type":"Point"}
}