{
  "type": "Feature",
  "properties": {
    "iso:country":"GB",
    "wof:name":"TN28 8BE",
    "wof:placetype":"postalcode"
},
  "geometry": {"coordinates":[0.94740326370587,50.99048756577923],"type":"Point"}
}