{
  "type": "Feature",
  "properties": {
    "iso:country": "GB",
    "wof:name": "NG10 1BG",
    "wof:placetype": "postalcode"
  },
  "geometry": {"coordinates":[-1.273208,52.894842],"type":"Point"}
}
