{
  "type": "Feature",
  "properties": {
    "iso:country":"GB",
    "wof:name":"DE4 4DJ",
    "wof:placetype":"postalcode"
},
  "geometry": {"coordinates":[-1.57953367469576,53.07923360737748],"type":"Point"}
}