{
  "type": "Feature",
  "properties": {
    "iso:country": "GB",
    "wof:name": "NP24 6DL",
    "wof:placetype": "postalcode"
  },
  "geometry": {"coordinates":[-3.233472,51.716842],"type":"Point"}
}
