{
  "type": "Feature",
  "properties": {
    "iso:country":"GB",
    "wof:name":"NR14 6NW",
    "wof:placetype":"postalcode"
},
  "geometry": {"coordinates":[1.52587956050073,52.51777190258035],"type":"Point"}
}