{
  "type": "Feature",
  "properties": {
    "date:inception_lower": "1980-01-01",
    "date:inception_upper": "1980-01-01",
    "iso:country": "GB",
    "wof:name": "NR14 6NW",
    "wof:placetype": "postalcode"
  },
  "geometry": {"coordinates":[1.52588,52.517772],"type":"Point"}
}
