{
  "type": "Feature",
  "properties": {
    "iso:country": "GB",
    "wof:name": "PE20 1BP",
    "wof:placetype": "postalcode"
  },
  "geometry": {"coordinates":[-0.054056,52.943063],"type":"Point"}
}
