{
  "type": "Feature",
  "properties": {
    "iso:country": "GB",
    "wof:name": "WV14 8SF",
    "wof:placetype": "postalcode"
  },
  "geometry": {"coordinates":[-2.081785,52.55025],"type":"Point"}
}
