{
  "type": "Feature",
  "properties": {
    "iso:country":"GB",
    "wof:name":"WR7 4NZ",
    "wof:placetype":"postalcode"
},
  "geometry": {"coordinates":[-2.0787245437164,52.1802748873287],"type":"Point"}
}