{
  "type": "Feature",
  "properties": {
    "iso:country": "GB",
    "wof:name": "WR7 4NZ",
    "wof:placetype": "postalcode"
  },
  "geometry": {"coordinates":[-2.07964,52.180583],"type":"Point"}
}
