{
  "type": "Feature",
  "properties": {
    "date:inception_lower":"1987-04-01",
    "date:inception_upper":"1987-04-30",
    "iso:country":"GB",
    "wof:name":"HP13 6BG",
    "wof:placetype":"postalcode"
},
  "geometry": {"coordinates":[-0.733362,51.641953],"type":"Point"}
}