{
  "type": "Feature",
  "properties": {
    "iso:country":"GB",
    "wof:name":"HP13 6BG",
    "wof:placetype":"postalcode"
},
  "geometry": {"coordinates":[-0.73336253430056,51.64195349956008],"type":"Point"}
}