{
  "type": "Feature",
  "properties": {
    "date:inception_lower": "2022-06-01",
    "date:inception_upper": "2022-06-01",
    "iso:country": "GB",
    "wof:name": "PE22 0BP",
    "wof:placetype": "postalcode"
  },
  "geometry": {"coordinates":[0.094905,53.005263],"type":"Point"}
}
