{
  "type": "Feature",
  "properties": {
    "date:inception_lower": "2016-09-01",
    "date:inception_upper": "2016-09-01",
    "iso:country": "GB",
    "wof:name": "OX13 6FX",
    "wof:placetype": "postalcode"
  },
  "geometry": {"coordinates":[-1.317898,51.62938],"type":"Point"}
}
