{
  "type": "Feature",
  "properties": {
    "date:inception_lower":"2016-06-01",
    "date:inception_upper":"2016-06-30",
    "iso:country":"GB",
    "wof:name":"DN14 9PR",
    "wof:placetype":"postalcode"
},
  "geometry": {"coordinates":[-1.026623,53.715623],"type":"Point"}
}