{
  "type": "Feature",
  "properties": {
    "iso:country": "GB",
    "wof:name": "BA12 7BA",
    "wof:placetype": "postalcode"
  },
  "geometry": {"coordinates":[-2.127575,51.18498],"type":"Point"}
}
