{
  "type": "Feature",
  "properties": {
    "date:inception_lower": "1980-01-01",
    "date:inception_upper": "1980-01-01",
    "iso:country": "GB",
    "wof:name": "BA12 7BA",
    "wof:placetype": "postalcode"
  },
  "geometry": {"coordinates":[-2.127575,51.18498],"type":"Point"}
}
