{
  "type": "Feature",
  "properties": {
    "iso:country":"GB",
    "wof:name":"MK45 5BE",
    "wof:placetype":"postalcode"
},
  "geometry": {"coordinates":[-0.48459956881106,52.00217302456837],"type":"Point"}
}