{
  "type": "Feature",
  "properties": {
    "date:inception_lower": "2018-05-01",
    "date:inception_upper": "2018-05-01",
    "iso:country": "GB",
    "wof:name": "SA18 3UD",
    "wof:placetype": "postalcode"
  },
  "geometry": {"coordinates":[-4.015384,51.794215],"type":"Point"}
}
