{
  "type": "Feature",
  "properties": {
    "iso:country": "GB",
    "wof:name": "SA18 3UD",
    "wof:placetype": "postalcode"
  },
  "geometry": {"coordinates":[-4.015384,51.794215],"type":"Point"}
}
