{
  "type": "Feature",
  "properties": {
    "date:inception_lower": "2012-02-01",
    "date:inception_upper": "2012-02-01",
    "iso:country": "GB",
    "wof:name": "KT10 1SZ",
    "wof:placetype": "postalcode"
  },
  "geometry": {"coordinates":[-0.361898,51.369929],"type":"Point"}
}
