{
  "type": "Feature",
  "properties": {
    "iso:country": "GB",
    "wof:name": "GL1 5SG",
    "wof:placetype": "postalcode"
  },
  "geometry": {"coordinates":[-2.25393,51.856685],"type":"Point"}
}
