{
  "type": "Feature",
  "properties": {
    "date:inception_lower": "1980-01-01",
    "date:inception_upper": "1980-01-01",
    "iso:country": "GB",
    "wof:name": "NE46 1JF",
    "wof:placetype": "postalcode"
  },
  "geometry": {"coordinates":[-2.088722,54.968511],"type":"Point"}
}
