{
  "type": "Feature",
  "properties": {
    "iso:country":"GB",
    "wof:name":"NE46 1JF",
    "wof:placetype":"postalcode"
},
  "geometry": {"coordinates":[-2.08872234051571,54.96851072707598],"type":"Point"}
}