{
  "type": "Feature",
  "properties": {
    "iso:country":"GB",
    "wof:name":"TD3 6JP",
    "wof:placetype":"postalcode"
},
  "geometry": {"coordinates":[-2.56707376000589,55.67925724094378],"type":"Point"}
}