{
  "type": "Feature",
  "properties": {
    "date:inception_lower":"1980-01-01",
    "date:inception_upper":"1980-01-31",
    "iso:country":"GB",
    "wof:name":"TD3 6JP",
    "wof:placetype":"postalcode"
},
  "geometry": {"coordinates":[-2.567074,55.679257],"type":"Point"}
}