{
  "type": "Feature",
  "properties": {
    "iso:country": "GB",
    "wof:name": "BS14 8AF",
    "wof:placetype": "postalcode"
  },
  "geometry": {"coordinates":[-2.553637,51.422517],"type":"Point"}
}
