{
  "type": "Feature",
  "properties": {
    "iso:country":"GB",
    "wof:name":"BS14 8AF",
    "wof:placetype":"postalcode"
},
  "geometry": {"coordinates":[-2.55363716878783,51.42251706135639],"type":"Point"}
}