{
  "type": "Feature",
  "properties": {
    "iso:country": "GB",
    "wof:name": "EX22 7JT",
    "wof:placetype": "postalcode"
  },
  "geometry": {"coordinates":[-4.423769,50.822334],"type":"Point"}
}
