{
  "type": "Feature",
  "properties": {
    "date:inception_lower": "1980-01-01",
    "date:inception_upper": "1980-01-01",
    "iso:country": "GB",
    "wof:name": "DA1 1NL",
    "wof:placetype": "postalcode"
  },
  "geometry": {"coordinates":[0.232226,51.432554],"type":"Point"}
}
