{
  "type": "Feature",
  "properties": {
    "iso:country":"GB",
    "wof:name":"DA1 1NL",
    "wof:placetype":"postalcode"
},
  "geometry": {"coordinates":[0.23222640563932,51.43255373575765],"type":"Point"}
}