{
  "type": "Feature",
  "properties": {
    "iso:country":"GB",
    "wof:name":"L35 9LL",
    "wof:placetype":"postalcode"
},
  "geometry": {"coordinates":[-2.77693163341753,53.4170699463175],"type":"Point"}
}