{
  "type": "Feature",
  "properties": {
    "iso:country":"GB",
    "wof:name":"PO19 1DL",
    "wof:placetype":"postalcode"
},
  "geometry": {"coordinates":[-0.77990449931871,50.83743717940963],"type":"Point"}
}