{
  "type": "Feature",
  "properties": {
    "date:inception_lower": "1987-10-01",
    "date:inception_upper": "1987-10-01",
    "iso:country": "GB",
    "wof:name": "PO19 1DL",
    "wof:placetype": "postalcode"
  },
  "geometry": {"coordinates":[-0.779843,50.837427],"type":"Point"}
}
