{
  "type": "Feature",
  "properties": {
    "iso:country":"GB",
    "wof:name":"SM5 1RD",
    "wof:placetype":"postalcode"
},
  "geometry": {"coordinates":[-0.17678998146284,51.37698743140147],"type":"Point"}
}