{
  "type": "Feature",
  "properties": {
    "iso:country":"GB",
    "wof:name":"YO18 7PJ",
    "wof:placetype":"postalcode"
},
  "geometry": {"coordinates":[-0.6565075210259,54.23518151411913],"type":"Point"}
}