{
  "type": "Feature",
  "properties": {
    "iso:country": "GB",
    "wof:name": "YO18 7PJ",
    "wof:placetype": "postalcode"
  },
  "geometry": {"coordinates":[-0.656507,54.235182],"type":"Point"}
}
