{
  "type": "Feature",
  "properties": {
    "date:inception_lower": "1980-01-01",
    "date:inception_upper": "1980-01-01",
    "iso:country": "GB",
    "wof:name": "YO18 7PJ",
    "wof:placetype": "postalcode"
  },
  "geometry": {"coordinates":[-0.656507,54.235182],"type":"Point"}
}
