{
  "type": "Feature",
  "properties": {
    "iso:country":"GB",
    "wof:name":"SE5 7QL",
    "wof:placetype":"postalcode"
},
  "geometry": {"coordinates":[-0.09001338788574,51.47774378568815],"type":"Point"}
}