{
  "type": "Feature",
  "properties": {
    "iso:country":"GB",
    "wof:name":"UB1 3BQ",
    "wof:placetype":"postalcode"
},
  "geometry": {"coordinates":[-0.37490497748675,51.51047169839728],"type":"Point"}
}