{
  "type": "Feature",
  "properties": {
    "iso:country": "GB",
    "wof:name": "LL16 4LA",
    "wof:placetype": "postalcode"
  },
  "geometry": {"coordinates":[-3.343499,53.19116],"type":"Point"}
}
