{
  "type": "Feature",
  "properties": {
    "date:inception_lower": "1985-10-01",
    "date:inception_upper": "1985-10-01",
    "iso:country": "GB",
    "wof:name": "GL6 8HE",
    "wof:placetype": "postalcode"
  },
  "geometry": {"coordinates":[-2.164999,51.733524],"type":"Point"}
}
