{
  "type": "Feature",
  "properties": {
    "iso:country": "GB",
    "wof:name": "GL6 8HE",
    "wof:placetype": "postalcode"
  },
  "geometry": {"coordinates":[-2.164999,51.733524],"type":"Point"}
}
