{
  "type": "Feature",
  "properties": {
    "date:inception_lower":"1997-12-01",
    "date:inception_upper":"1997-12-31",
    "iso:country":"GB",
    "wof:name":"BS35 4JW",
    "wof:placetype":"postalcode"
},
  "geometry": {"coordinates":[-2.622173,51.557245],"type":"Point"}
}