{
  "type": "Feature",
  "properties": {
    "iso:country":"GB",
    "wof:name":"BS35 4JW",
    "wof:placetype":"postalcode"
},
  "geometry": {"coordinates":[-2.62217257675095,51.55724497065461],"type":"Point"}
}