{
  "type": "Feature",
  "properties": {
    "iso:country":"GB",
    "wof:name":"G74 3LW",
    "wof:placetype":"postalcode"
},
  "geometry": {"coordinates":[-4.14886663821903,55.77665621579118],"type":"Point"}
}