{
  "type": "Feature",
  "properties": {
    "iso:country": "GB",
    "wof:name": "CW11 4PF",
    "wof:placetype": "postalcode"
  },
  "geometry": {"coordinates":[-2.367155,53.139158],"type":"Point"}
}
