{
  "type": "Feature",
  "properties": {
    "iso:country": "GB",
    "wof:name": "KT5 9ND",
    "wof:placetype": "postalcode"
  },
  "geometry": {"coordinates":[-0.271842,51.38689],"type":"Point"}
}
