{
  "type": "Feature",
  "properties": {
    "iso:country":"GB",
    "wof:name":"KT5 9ND",
    "wof:placetype":"postalcode"
},
  "geometry": {"coordinates":[-0.27184174340807,51.38688997538105],"type":"Point"}
}