{
  "type": "Feature",
  "properties": {
    "date:inception_lower": "2016-09-01",
    "date:inception_upper": "2016-09-01",
    "iso:country": "GB",
    "wof:name": "PL30 5FA",
    "wof:placetype": "postalcode"
  },
  "geometry": {"coordinates":[-4.739592,50.395712],"type":"Point"}
}
