{
  "type": "Feature",
  "properties": {
    "iso:country":"GB",
    "wof:name":"S40 9TP",
    "wof:placetype":"postalcode"
},
  "geometry": {"coordinates":[-1.43258630678902,53.23788299907356],"type":"Point"}
}