{
  "type": "Feature",
  "properties": {
    "iso:country":"GB",
    "wof:name":"BR4 9QG",
    "wof:placetype":"postalcode"
},
  "geometry": {"coordinates":[-0.00561332142993,51.37258874133509],"type":"Point"}
}