{
  "type": "Feature",
  "properties": {
    "iso:country":"GB",
    "wof:name":"G62 7BJ",
    "wof:placetype":"postalcode"
},
  "geometry": {"coordinates":[-4.33123825172923,55.94594775484799],"type":"Point"}
}