{
  "type": "Feature",
  "properties": {
    "iso:country":"GB",
    "wof:name":"G12 0HD",
    "wof:placetype":"postalcode"
},
  "geometry": {"coordinates":[-4.30554584106438,55.89011572220482],"type":"Point"}
}