{
  "type": "Feature",
  "properties": {
    "iso:country":"GB",
    "wof:name":"BD21 1EJ",
    "wof:placetype":"postalcode"
},
  "geometry": {"coordinates":[-1.91141510038098,53.8594843494789],"type":"Point"}
}