{
  "type": "Feature",
  "properties": {
    "iso:country":"GB",
    "wof:name":"CV5 9FT",
    "wof:placetype":"postalcode"
},
  "geometry": {"coordinates":[-1.56897376037719,52.4294450659282],"type":"Point"}
}