{
  "type": "Feature",
  "properties": {
    "iso:country":"GB",
    "wof:name":"HD2 1WA",
    "wof:placetype":"postalcode"
},
  "geometry": {"coordinates":[-1.74846947752586,53.66955242422951],"type":"Point"}
}