{
  "type": "Feature",
  "properties": {
    "iso:country": "GB",
    "wof:name": "HD2 1WA",
    "wof:placetype": "postalcode"
  },
  "geometry": {"coordinates":[-1.748469,53.669552],"type":"Point"}
}
