{
  "type": "Feature",
  "properties": {
    "iso:country":"GB",
    "wof:name":"PO7 6YR",
    "wof:placetype":"postalcode"
},
  "geometry": {"coordinates":[-1.07083614040399,50.90130202673217],"type":"Point"}
}