{
  "type": "Feature",
  "properties": {
    "iso:country":"GB",
    "wof:name":"SW4 0AN",
    "wof:placetype":"postalcode"
},
  "geometry": {"coordinates":[-0.13935796796077,51.46341169895938],"type":"Point"}
}