{
  "type": "Feature",
  "properties": {
    "date:inception_lower": "2009-02-01",
    "date:inception_upper": "2009-02-01",
    "iso:country": "GB",
    "wof:name": "SW4 0AN",
    "wof:placetype": "postalcode"
  },
  "geometry": {"coordinates":[-0.139358,51.463412],"type":"Point"}
}
