{
  "type": "Feature",
  "properties": {
    "iso:country":"GB",
    "wof:name":"LL59 5SE",
    "wof:placetype":"postalcode"
},
  "geometry": {"coordinates":[-4.17425465635174,53.2597159653285],"type":"Point"}
}