{
  "type": "Feature",
  "properties": {
    "date:inception_lower": "1980-01-01",
    "date:inception_upper": "1980-01-01",
    "iso:country": "GB",
    "wof:name": "LL59 5SE",
    "wof:placetype": "postalcode"
  },
  "geometry": {"coordinates":[-4.174255,53.259716],"type":"Point"}
}
