{
  "type": "Feature",
  "properties": {
    "date:inception_lower": "2006-10-01",
    "date:inception_upper": "2006-10-01",
    "iso:country": "GB",
    "wof:name": "WF9 5FW",
    "wof:placetype": "postalcode"
  },
  "geometry": {"coordinates":[-1.371535,53.622391],"type":"Point"}
}
