{
  "type": "Feature",
  "properties": {
    "iso:country":"GB",
    "wof:name":"WF9 5FW",
    "wof:placetype":"postalcode"
},
  "geometry": {"coordinates":[-1.37153478709413,53.62239075260044],"type":"Point"}
}