{
  "type": "Feature",
  "properties": {
    "date:inception_lower": "2013-07-01",
    "date:inception_upper": "2013-07-01",
    "iso:country": "GB",
    "wof:name": "CV3 1LN",
    "wof:placetype": "postalcode"
  },
  "geometry": {"coordinates":[-1.469107,52.405233],"type":"Point"}
}
