{
  "type": "Feature",
  "properties": {
    "iso:country":"GB",
    "wof:name":"CV3 1LN",
    "wof:placetype":"postalcode"
},
  "geometry": {"coordinates":[-1.46897557513121,52.40517867087647],"type":"Point"}
}