{
  "type": "Feature",
  "properties": {
    "iso:country": "GB",
    "wof:name": "WA8 3JT",
    "wof:placetype": "postalcode"
  },
  "geometry": {"coordinates":[-2.707567,53.377097],"type":"Point"}
}
