{
  "type": "Feature",
  "properties": {
    "iso:country":"GB",
    "wof:name":"WA8 3JT",
    "wof:placetype":"postalcode"
},
  "geometry": {"coordinates":[-2.70756734156679,53.37709672305078],"type":"Point"}
}