{
  "type": "Feature",
  "properties": {
    "iso:country":"GB",
    "wof:name":"M29 7AF",
    "wof:placetype":"postalcode"
},
  "geometry": {"coordinates":[-2.46386590567962,53.50380944831254],"type":"Point"}
}