{
  "type": "Feature",
  "properties": {
    "iso:country": "GB",
    "wof:name": "PO16 7LT",
    "wof:placetype": "postalcode"
  },
  "geometry": {"coordinates":[-1.193993,50.859889],"type":"Point"}
}
