{
  "type": "Feature",
  "properties": {
    "iso:country":"GB",
    "wof:name":"PO16 7LT",
    "wof:placetype":"postalcode"
},
  "geometry": {"coordinates":[-1.19399311610054,50.85988879806879],"type":"Point"}
}