{
  "type": "Feature",
  "properties": {
    "iso:country": "GB",
    "wof:name": "CM8 1YS",
    "wof:placetype": "postalcode"
  },
  "geometry": {"coordinates":[0.619541,51.787681],"type":"Point"}
}
