{
  "type": "Feature",
  "properties": {
    "iso:country":"GB",
    "wof:name":"EH51 9JE",
    "wof:placetype":"postalcode"
},
  "geometry": {"coordinates":[-3.60627720597574,56.00486401291968],"type":"Point"}
}