{
  "type": "Feature",
  "properties": {
    "iso:country":"GB",
    "wof:name":"GU6 8BE",
    "wof:placetype":"postalcode"
},
  "geometry": {"coordinates":[-0.49119061399339,51.14202334358198],"type":"Point"}
}