{
  "type": "Feature",
  "properties": {
    "date:inception_lower": "1980-01-01",
    "date:inception_upper": "1980-01-01",
    "iso:country": "GB",
    "wof:name": "GU6 8BE",
    "wof:placetype": "postalcode"
  },
  "geometry": {"coordinates":[-0.491191,51.142023],"type":"Point"}
}
