{
  "type": "Feature",
  "properties": {
    "date:inception_lower": "1994-05-01",
    "date:inception_upper": "1994-05-01",
    "iso:country": "GB",
    "wof:name": "M7 1LF",
    "wof:placetype": "postalcode"
  },
  "geometry": {"coordinates":[-2.261057,53.498996],"type":"Point"}
}
