{
  "type": "Feature",
  "properties": {
    "iso:country":"GB",
    "wof:name":"M7 1LF",
    "wof:placetype":"postalcode"
},
  "geometry": {"coordinates":[-2.26105657826704,53.49899579438295],"type":"Point"}
}