{
  "type": "Feature",
  "properties": {
    "date:inception_lower": "2008-06-01",
    "date:inception_upper": "2008-06-01",
    "iso:country": "GB",
    "wof:name": "ME12 3GB",
    "wof:placetype": "postalcode"
  },
  "geometry": {"coordinates":[0.79712,51.4131],"type":"Point"}
}
