{
  "type": "Feature",
  "properties": {
    "iso:country":"GB",
    "wof:name":"ME12 3GB",
    "wof:placetype":"postalcode"
},
  "geometry": {"coordinates":[0.79712014382741,51.41309965208279],"type":"Point"}
}