{
  "type": "Feature",
  "properties": {
    "iso:country": "GB",
    "wof:name": "GU46 7TH",
    "wof:placetype": "postalcode"
  },
  "geometry": {"coordinates":[-0.823053,51.34369],"type":"Point"}
}
