{
  "type": "Feature",
  "properties": {
    "iso:country":"GB",
    "wof:name":"W1U 5AL",
    "wof:placetype":"postalcode"
},
  "geometry": {"coordinates":[-0.15593848153895,51.521342678408],"type":"Point"}
}