{
  "type": "Feature",
  "properties": {
    "iso:country":"GB",
    "wof:name":"CV10 9JD",
    "wof:placetype":"postalcode"
},
  "geometry": {"coordinates":[-1.51116636136249,52.52449688365027],"type":"Point"}
}