{
  "type": "Feature",
  "properties": {
    "iso:country":"GB",
    "wof:name":"CF83 2RB",
    "wof:placetype":"postalcode"
},
  "geometry": {"coordinates":[-3.23547092631572,51.58401327550548],"type":"Point"}
}