{
  "type": "Feature",
  "properties": {
    "iso:country": "GB",
    "wof:name": "DT5 2EP",
    "wof:placetype": "postalcode"
  },
  "geometry": {"coordinates":[-2.451241,50.543031],"type":"Point"}
}
