{
  "type": "Feature",
  "properties": {
    "iso:country": "GB",
    "wof:name": "DH4 7AY",
    "wof:placetype": "postalcode"
  },
  "geometry": {"coordinates":[-1.493749,54.869314],"type":"Point"}
}
