{
  "type": "Feature",
  "properties": {
    "iso:country": "GB",
    "wof:name": "EH21 7DQ",
    "wof:placetype": "postalcode"
  },
  "geometry": {"coordinates":[-3.029683,55.942254],"type":"Point"}
}
