{
  "type": "Feature",
  "properties": {
    "date:inception_lower": "2013-12-01",
    "date:inception_upper": "2013-12-01",
    "iso:country": "GB",
    "wof:name": "EH21 7DQ",
    "wof:placetype": "postalcode"
  },
  "geometry": {"coordinates":[-3.029705,55.942304],"type":"Point"}
}
