{
  "type": "Feature",
  "properties": {
    "iso:country":"GB",
    "wof:name":"HR1 1LR",
    "wof:placetype":"postalcode"
},
  "geometry": {"coordinates":[-2.69959021312072,52.06119405223058],"type":"Point"}
}