{
  "type": "Feature",
  "properties": {
    "iso:country":"GB",
    "wof:name":"BL0 0AY",
    "wof:placetype":"postalcode"
},
  "geometry": {"coordinates":[-2.30527035797257,53.64763887343398],"type":"Point"}
}