{
  "type": "Feature",
  "properties": {
    "date:inception_lower":"1980-01-01",
    "date:inception_upper":"1980-01-31",
    "iso:country":"GB",
    "wof:name":"BL0 0AY",
    "wof:placetype":"postalcode"
},
  "geometry": {"coordinates":[-2.30527,53.647639],"type":"Point"}
}