{
  "type": "Feature",
  "properties": {
    "iso:country":"GB",
    "wof:name":"BR3 3BQ",
    "wof:placetype":"postalcode"
},
  "geometry": {"coordinates":[-0.02225818006511,51.38476844206433],"type":"Point"}
}