{
  "type": "Feature",
  "properties": {
    "iso:country": "GB",
    "wof:name": "BR3 3BQ",
    "wof:placetype": "postalcode"
  },
  "geometry": {"coordinates":[-0.022106,51.384667],"type":"Point"}
}
