{
  "type": "Feature",
  "properties": {
    "iso:country": "GB",
    "wof:name": "S60 5WP",
    "wof:placetype": "postalcode"
  },
  "geometry": {"coordinates":[-1.369859,53.39037],"type":"Point"}
}
