{
  "type": "Feature",
  "properties": {
    "date:inception_lower": "2019-12-01",
    "date:inception_upper": "2019-12-01",
    "iso:country": "GB",
    "wof:name": "S60 5WP",
    "wof:placetype": "postalcode"
  },
  "geometry": {"coordinates":[-1.369376,53.39052],"type":"Point"}
}
