{
  "type": "Feature",
  "properties": {
    "iso:country":"GB",
    "wof:name":"W1T 1DJ",
    "wof:placetype":"postalcode"
},
  "geometry": {"coordinates":[-0.13356759186656,51.51815620417997],"type":"Point"}
}