{
  "type": "Feature",
  "properties": {
    "iso:country": "GB",
    "wof:name": "CR5 3GL",
    "wof:placetype": "postalcode"
  },
  "geometry": {"coordinates":[-0.14864,51.313299],"type":"Point"}
}
