{
  "type": "Feature",
  "properties": {
    "iso:country": "GB",
    "wof:name": "LL40 1UA",
    "wof:placetype": "postalcode"
  },
  "geometry": {"coordinates":[-3.896173,52.743057],"type":"Point"}
}
