{
  "type": "Feature",
  "properties": {
    "iso:country":"GB",
    "wof:name":"B23 7PH",
    "wof:placetype":"postalcode"
},
  "geometry": {"coordinates":[-1.86152700042228,52.5107170258075],"type":"Point"}
}