{
  "type": "Feature",
  "properties": {
    "iso:country": "GB",
    "wof:name": "WA16 0SG",
    "wof:placetype": "postalcode"
  },
  "geometry": {"coordinates":[-2.49786,53.356781],"type":"Point"}
}
