{
  "type": "Feature",
  "properties": {
    "iso:country":"GB",
    "wof:name":"TF4 2FT",
    "wof:placetype":"postalcode"
},
  "geometry": {"coordinates":[-2.49042815881484,52.67129257780161],"type":"Point"}
}