{
  "type": "Feature",
  "properties": {
    "date:inception_lower": "2009-05-01",
    "date:inception_upper": "2009-05-01",
    "iso:country": "GB",
    "wof:name": "TF4 2FT",
    "wof:placetype": "postalcode"
  },
  "geometry": {"coordinates":[-2.490428,52.671293],"type":"Point"}
}
