{
  "type": "Feature",
  "properties": {
    "iso:country":"GB",
    "wof:name":"B79 8LJ",
    "wof:placetype":"postalcode"
},
  "geometry": {"coordinates":[-1.71241688270495,52.64586288067147],"type":"Point"}
}