{
  "type": "Feature",
  "properties": {
    "date:inception_lower": "1980-01-01",
    "date:inception_upper": "1980-01-01",
    "iso:country": "GB",
    "wof:name": "B79 8LJ",
    "wof:placetype": "postalcode"
  },
  "geometry": {"coordinates":[-1.712417,52.645863],"type":"Point"}
}
