{
  "type": "Feature",
  "properties": {
    "iso:country": "GB",
    "wof:name": "KA11 4FN",
    "wof:placetype": "postalcode"
  },
  "geometry": {"coordinates":[-4.65428,55.605562],"type":"Point"}
}
