{
  "type": "Feature",
  "properties": {
    "date:inception_lower": "2019-09-01",
    "date:inception_upper": "2019-09-01",
    "iso:country": "GB",
    "wof:name": "KA11 4FN",
    "wof:placetype": "postalcode"
  },
  "geometry": {"coordinates":[-4.653265,55.605575],"type":"Point"}
}
