{
  "type": "Feature",
  "properties": {
    "iso:country":"GB",
    "wof:name":"N22 8PY",
    "wof:placetype":"postalcode"
},
  "geometry": {"coordinates":[-0.11391595676995,51.60337824176151],"type":"Point"}
}