{
  "type": "Feature",
  "properties": {
    "iso:country":"GB",
    "wof:name":"CM11 1EZ",
    "wof:placetype":"postalcode"
},
  "geometry": {"coordinates":[0.43844066726322,51.62915551757639],"type":"Point"}
}