{
  "type": "Feature",
  "properties": {
    "date:inception_lower": "1980-01-01",
    "date:inception_upper": "1980-01-01",
    "iso:country": "GB",
    "wof:name": "CM11 1EZ",
    "wof:placetype": "postalcode"
  },
  "geometry": {"coordinates":[0.437501,51.62863],"type":"Point"}
}
