{
  "type": "Feature",
  "properties": {
    "iso:country":"GB",
    "wof:name":"HP23 5HH",
    "wof:placetype":"postalcode"
},
  "geometry": {"coordinates":[-0.66197034099079,51.8042890168763],"type":"Point"}
}