{
  "type": "Feature",
  "properties": {
    "date:inception_lower":"1980-01-01",
    "date:inception_upper":"1980-01-31",
    "iso:country":"GB",
    "wof:name":"BR2 7DH",
    "wof:placetype":"postalcode"
},
  "geometry": {"coordinates":[0.015703,51.37637],"type":"Point"}
}