{
  "type": "Feature",
  "properties": {
    "iso:country": "GB",
    "wof:name": "BR2 7DH",
    "wof:placetype": "postalcode"
  },
  "geometry": {"coordinates":[0.015703,51.37637],"type":"Point"}
}
