{
  "type": "Feature",
  "properties": {
    "iso:country":"GB",
    "wof:name":"BR2 7DH",
    "wof:placetype":"postalcode"
},
  "geometry": {"coordinates":[0.01570254598908,51.37636962464448],"type":"Point"}
}