{
  "type": "Feature",
  "properties": {
    "iso:country":"GB",
    "wof:name":"NG9 7FT",
    "wof:placetype":"postalcode"
},
  "geometry": {"coordinates":[-1.27943380462665,52.92456305383212],"type":"Point"}
}