{
  "type": "Feature",
  "properties": {
    "iso:country":"GB",
    "wof:name":"G32 0JU",
    "wof:placetype":"postalcode"
},
  "geometry": {"coordinates":[-4.15515997621461,55.85796183510288],"type":"Point"}
}