{
  "type": "Feature",
  "properties": {
    "iso:country":"GB",
    "wof:name":"RH11 8SQ",
    "wof:placetype":"postalcode"
},
  "geometry": {"coordinates":[-0.20278111455035,51.10613873191602],"type":"Point"}
}