{
  "type": "Feature",
  "properties": {
    "iso:country":"GB",
    "wof:name":"NR10 4AP",
    "wof:placetype":"postalcode"
},
  "geometry": {"coordinates":[1.16450718151296,52.769493300974],"type":"Point"}
}