{
  "type": "Feature",
  "properties": {
    "iso:country": "GB",
    "wof:name": "NR10 4AP",
    "wof:placetype": "postalcode"
  },
  "geometry": {"coordinates":[1.164507,52.769493],"type":"Point"}
}
