{
  "type": "Feature",
  "properties": {
    "iso:country":"GB",
    "wof:name":"OL11 4BB",
    "wof:placetype":"postalcode"
},
  "geometry": {"coordinates":[-2.2050696122804,53.6082954399168],"type":"Point"}
}