{
  "type": "Feature",
  "properties": {
    "date:inception_lower": "2023-11-01",
    "date:inception_upper": "2023-11-01",
    "iso:country": "GB",
    "wof:name": "IP30 9ZN",
    "wof:placetype": "postalcode"
  },
  "geometry": {"coordinates":[0.906866,52.238971],"type":"Point"}
}
