{
  "type": "Feature",
  "properties": {
    "iso:country":"GB",
    "wof:name":"DL4 1JJ",
    "wof:placetype":"postalcode"
},
  "geometry": {"coordinates":[-1.65370361991622,54.63178492353673],"type":"Point"}
}