{
  "type": "Feature",
  "properties": {
    "iso:country":"GB",
    "wof:name":"TN14 5RA",
    "wof:placetype":"postalcode"
},
  "geometry": {"coordinates":[0.19305190761393,51.31264182840334],"type":"Point"}
}