{
  "type": "Feature",
  "properties": {
    "iso:country": "GB",
    "wof:name": "TN14 5RA",
    "wof:placetype": "postalcode"
  },
  "geometry": {"coordinates":[0.193052,51.312642],"type":"Point"}
}
