{
  "type": "Feature",
  "properties": {
    "date:inception_lower": "2021-08-01",
    "date:inception_upper": "2021-08-01",
    "iso:country": "GB",
    "wof:name": "TA18 8FL",
    "wof:placetype": "postalcode"
  },
  "geometry": {"coordinates":[-2.7768,50.873187],"type":"Point"}
}
