{
  "type": "Feature",
  "properties": {
    "iso:country":"GB",
    "wof:name":"NR21 9PX",
    "wof:placetype":"postalcode"
},
  "geometry": {"coordinates":[0.81678194424531,52.84746132185722],"type":"Point"}
}