{
  "type": "Feature",
  "properties": {
    "iso:country": "GB",
    "wof:name": "NR21 9PX",
    "wof:placetype": "postalcode"
  },
  "geometry": {"coordinates":[0.816916,52.8477],"type":"Point"}
}
