{
  "type": "Feature",
  "properties": {
    "date:inception_lower": "1980-01-01",
    "date:inception_upper": "1980-01-01",
    "iso:country": "GB",
    "wof:name": "NR21 9PX",
    "wof:placetype": "postalcode"
  },
  "geometry": {"coordinates":[0.816917,52.847709],"type":"Point"}
}
