{
  "type": "Feature",
  "properties": {
    "iso:country": "GB",
    "wof:name": "NP7 6PT",
    "wof:placetype": "postalcode"
  },
  "geometry": {"coordinates":[-3.003099,51.84036],"type":"Point"}
}
