{
  "type": "Feature",
  "properties": {
    "iso:country": "GB",
    "wof:name": "CF62 5DP",
    "wof:placetype": "postalcode"
  },
  "geometry": {"coordinates":[-3.272005,51.396436],"type":"Point"}
}
