{
  "type": "Feature",
  "properties": {
    "date:inception_lower": "2019-12-01",
    "date:inception_upper": "2019-12-01",
    "iso:country": "GB",
    "wof:name": "CF62 5DP",
    "wof:placetype": "postalcode"
  },
  "geometry": {"coordinates":[-3.271343,51.396929],"type":"Point"}
}
