{
  "type": "Feature",
  "properties": {
    "date:inception_lower": "2019-12-01",
    "date:inception_upper": "2019-12-01",
    "iso:country": "GB",
    "wof:name": "CF62 5DP",
    "wof:placetype": "postalcode"
  },
  "geometry": {"coordinates":[-3.272005,51.396436],"type":"Point"}
}
