{
  "type": "Feature",
  "properties": {
    "date:inception_lower": "2001-12-01",
    "date:inception_upper": "2001-12-01",
    "iso:country": "GB",
    "wof:name": "SR6 0FB",
    "wof:placetype": "postalcode"
  },
  "geometry": {"coordinates":[-1.373016,54.915913],"type":"Point"}
}
