{
  "type": "Feature",
  "properties": {
    "iso:country": "GB",
    "wof:name": "BN1 3EJ",
    "wof:placetype": "postalcode"
  },
  "geometry": {"coordinates":[-0.144975,50.823909],"type":"Point"}
}
