{
  "type": "Feature",
  "properties": {
    "iso:country":"GB",
    "wof:name":"BN1 3EJ",
    "wof:placetype":"postalcode"
},
  "geometry": {"coordinates":[-0.14497553048098,50.82390861506274],"type":"Point"}
}