{
  "type": "Feature",
  "properties": {
    "date:inception_lower": "1980-01-01",
    "date:inception_upper": "1980-01-01",
    "iso:country": "GB",
    "wof:name": "CW2 8ET",
    "wof:placetype": "postalcode"
  },
  "geometry": {"coordinates":[-2.473104,53.081451],"type":"Point"}
}
