{
  "type": "Feature",
  "properties": {
    "iso:country":"GB",
    "wof:name":"DE56 0JP",
    "wof:placetype":"postalcode"
},
  "geometry": {"coordinates":[-1.43333001402563,53.00526655614787],"type":"Point"}
}