{
  "type": "Feature",
  "properties": {
    "iso:country": "GB",
    "wof:name": "DE56 0JP",
    "wof:placetype": "postalcode"
  },
  "geometry": {"coordinates":[-1.43333,53.005267],"type":"Point"}
}
