{
  "type": "Feature",
  "properties": {
    "iso:country":"GB",
    "wof:name":"EN1 4TL",
    "wof:placetype":"postalcode"
},
  "geometry": {"coordinates":[-0.06910676741307,51.66665771345667],"type":"Point"}
}