{
  "type": "Feature",
  "properties": {
    "iso:country":"GB",
    "wof:name":"B77 3NP",
    "wof:placetype":"postalcode"
},
  "geometry": {"coordinates":[-1.67789702091627,52.6370271318136],"type":"Point"}
}