{
  "type": "Feature",
  "properties": {
    "iso:country":"GB",
    "wof:name":"CM16 6HS",
    "wof:placetype":"postalcode"
},
  "geometry": {"coordinates":[0.16876673356594,51.71787305893026],"type":"Point"}
}