{
  "type": "Feature",
  "properties": {
    "iso:country":"GB",
    "wof:name":"AL4 8LB",
    "wof:placetype":"postalcode"
},
  "geometry": {"coordinates":[-0.30104237481059,51.83456171345641],"type":"Point"}
}