{
  "type": "Feature",
  "properties": {
    "iso:country":"GB",
    "wof:name":"PE1 3HP",
    "wof:placetype":"postalcode"
},
  "geometry": {"coordinates":[-0.25462523980955,52.59523787707669],"type":"Point"}
}