{
  "type": "Feature",
  "properties": {
    "date:inception_lower":"1980-01-01",
    "date:inception_upper":"1980-01-31",
    "iso:country":"GB",
    "wof:name":"PE1 3HP",
    "wof:placetype":"postalcode"
},
  "geometry": {"coordinates":[-0.254566,52.595274],"type":"Point"}
}