{
  "type": "Feature",
  "properties": {
    "iso:country":"GB",
    "wof:name":"WA16 7LU",
    "wof:placetype":"postalcode"
},
  "geometry": {"coordinates":[-2.29273942798128,53.33199565081089],"type":"Point"}
}