{
  "type": "Feature",
  "properties": {
    "iso:country": "GB",
    "wof:name": "GU25 4BF",
    "wof:placetype": "postalcode"
  },
  "geometry": {"coordinates":[-0.559891,51.407204],"type":"Point"}
}
