{
  "type": "Feature",
  "properties": {
    "iso:country":"GB",
    "wof:name":"GU25 4BF",
    "wof:placetype":"postalcode"
},
  "geometry": {"coordinates":[-0.55989081505888,51.40720375667418],"type":"Point"}
}