{
  "type": "Feature",
  "properties": {
    "iso:country":"GB",
    "wof:name":"S66 3RP",
    "wof:placetype":"postalcode"
},
  "geometry": {"coordinates":[-1.27597248983244,53.42831801167217],"type":"Point"}
}