{
  "type": "Feature",
  "properties": {
    "date:inception_lower": "2007-07-01",
    "date:inception_upper": "2007-07-01",
    "iso:country": "GB",
    "wof:name": "FY4 2RH",
    "wof:placetype": "postalcode"
  },
  "geometry": {"coordinates":[-3.027984,53.775202],"type":"Point"}
}
