{
  "type": "Feature",
  "properties": {
    "iso:country":"GB",
    "wof:name":"FY4 2RH",
    "wof:placetype":"postalcode"
},
  "geometry": {"coordinates":[-3.02821691813749,53.77464590844919],"type":"Point"}
}