{
  "type": "Feature",
  "properties": {
    "iso:country": "GB",
    "wof:name": "FY4 2RH",
    "wof:placetype": "postalcode"
  },
  "geometry": {"coordinates":[-3.027984,53.775202],"type":"Point"}
}
