{
  "type": "Feature",
  "properties": {
    "iso:country":"GB",
    "wof:name":"TS6 9LJ",
    "wof:placetype":"postalcode"
},
  "geometry": {"coordinates":[-1.1364415336822,54.56092739593061],"type":"Point"}
}