{
  "type": "Feature",
  "properties": {
    "iso:country": "GB",
    "wof:name": "TS6 9LJ",
    "wof:placetype": "postalcode"
  },
  "geometry": {"coordinates":[-1.136441,54.560927],"type":"Point"}
}
