{
  "type": "Feature",
  "properties": {
    "iso:country":"GB",
    "wof:name":"NW10 0PS",
    "wof:placetype":"postalcode"
},
  "geometry": {"coordinates":[-0.2656752374909,51.54867163344829],"type":"Point"}
}