{
  "type": "Feature",
  "properties": {
    "iso:country":"GB",
    "wof:name":"B64 6RN",
    "wof:placetype":"postalcode"
},
  "geometry": {"coordinates":[-2.05108565845856,52.47368510294356],"type":"Point"}
}