{
  "type": "Feature",
  "properties": {
    "iso:country": "GB",
    "wof:name": "HU7 3AS",
    "wof:placetype": "postalcode"
  },
  "geometry": {"coordinates":[-0.356135,53.801436],"type":"Point"}
}
