{
  "type": "Feature",
  "properties": {
    "iso:country":"GB",
    "wof:name":"HU7 3AS",
    "wof:placetype":"postalcode"
},
  "geometry": {"coordinates":[-0.35613554023738,53.80143641295582],"type":"Point"}
}