{
  "type": "Feature",
  "properties": {
    "date:inception_lower":"2011-01-01",
    "date:inception_upper":"2011-01-31",
    "iso:country":"GB",
    "wof:name":"HU7 3AS",
    "wof:placetype":"postalcode"
},
  "geometry": {"coordinates":[-0.356135,53.801436],"type":"Point"}
}