{
  "type": "Feature",
  "properties": {
    "date:inception_lower": "2021-02-01",
    "date:inception_upper": "2021-02-01",
    "iso:country": "GB",
    "wof:name": "EX20 3FG",
    "wof:placetype": "postalcode"
  },
  "geometry": {"coordinates":[-4.022169,50.765237],"type":"Point"}
}
