{
  "type": "Feature",
  "properties": {
    "date:inception_lower": "1980-01-01",
    "date:inception_upper": "1980-01-01",
    "iso:country": "GB",
    "wof:name": "DL11 6RD",
    "wof:placetype": "postalcode"
  },
  "geometry": {"coordinates":[-1.994163,54.417548],"type":"Point"}
}
