{
  "type": "Feature",
  "properties": {
    "date:inception_lower": "2005-08-01",
    "date:inception_upper": "2005-08-01",
    "iso:country": "GB",
    "wof:name": "DA2 7WG",
    "wof:placetype": "postalcode"
  },
  "geometry": {"coordinates":[0.174741,51.434795],"type":"Point"}
}
