{
  "type": "Feature",
  "properties": {
    "iso:country":"GB",
    "wof:name":"LN11 9LD",
    "wof:placetype":"postalcode"
},
  "geometry": {"coordinates":[-0.01232623761148,53.3612999813259],"type":"Point"}
}