{
  "type": "Feature",
  "properties": {
    "iso:country":"GB",
    "wof:name":"G81 1QY",
    "wof:placetype":"postalcode"
},
  "geometry": {"coordinates":[-4.39660363565582,55.89908039679004],"type":"Point"}
}