{
  "type": "Feature",
  "properties": {
    "date:inception_lower": "1980-01-01",
    "date:inception_upper": "1980-01-01",
    "iso:country": "GB",
    "wof:name": "G81 1QY",
    "wof:placetype": "postalcode"
  },
  "geometry": {"coordinates":[-4.396604,55.89908],"type":"Point"}
}
