{
  "type": "Feature",
  "properties": {
    "iso:country":"GB",
    "wof:name":"B15 2JD",
    "wof:placetype":"postalcode"
},
  "geometry": {"coordinates":[-1.90590044885699,52.46531633585284],"type":"Point"}
}