{
  "type": "Feature",
  "properties": {
    "iso:country": "GB",
    "wof:name": "PO22 8PQ",
    "wof:placetype": "postalcode"
  },
  "geometry": {"coordinates":[-0.6652,50.791945],"type":"Point"}
}
