{
  "type": "Feature",
  "properties": {
    "iso:country": "GB",
    "wof:name": "DH5 0EL",
    "wof:placetype": "postalcode"
  },
  "geometry": {"coordinates":[-1.448884,54.813798],"type":"Point"}
}
