{
  "type": "Feature",
  "properties": {
    "iso:country":"GB",
    "wof:name":"DH5 0EL",
    "wof:placetype":"postalcode"
},
  "geometry": {"coordinates":[-1.44888413426517,54.8137981509908],"type":"Point"}
}