{
  "type": "Feature",
  "properties": {
    "iso:country":"GB",
    "wof:name":"TN21 8JD",
    "wof:placetype":"postalcode"
},
  "geometry": {"coordinates":[0.24815651841983,50.97077953089823],"type":"Point"}
}