{
  "type": "Feature",
  "properties": {
    "iso:country": "GB",
    "wof:name": "TN21 8JD",
    "wof:placetype": "postalcode"
  },
  "geometry": {"coordinates":[0.248157,50.97078],"type":"Point"}
}
