{
  "type": "Feature",
  "properties": {
    "iso:country":"GB",
    "wof:name":"BS8 3XD",
    "wof:placetype":"postalcode"
},
  "geometry": {"coordinates":[-2.69493754711914,51.44225633653836],"type":"Point"}
}