{
  "type": "Feature",
  "properties": {
    "iso:country":"GB",
    "wof:name":"B20 2NQ",
    "wof:placetype":"postalcode"
},
  "geometry": {"coordinates":[-1.92618625790086,52.52546437030291],"type":"Point"}
}