{
  "type": "Feature",
  "properties": {
    "iso:country":"GB",
    "wof:name":"CH2 1PB",
    "wof:placetype":"postalcode"
},
  "geometry": {"coordinates":[-2.87849853588281,53.20902573059187],"type":"Point"}
}