{
  "type": "Feature",
  "properties": {
    "date:inception_lower": "2010-07-01",
    "date:inception_upper": "2010-07-01",
    "iso:country": "GB",
    "wof:name": "HA4 8GN",
    "wof:placetype": "postalcode"
  },
  "geometry": {"coordinates":[-0.405384,51.581838],"type":"Point"}
}
