{
  "type": "Feature",
  "properties": {
    "iso:country":"GB",
    "wof:name":"HA4 8GN",
    "wof:placetype":"postalcode"
},
  "geometry": {"coordinates":[-0.40538381064869,51.58183828389746],"type":"Point"}
}