{
  "type": "Feature",
  "properties": {
    "iso:country":"GB",
    "wof:name":"M43 7EQ",
    "wof:placetype":"postalcode"
},
  "geometry": {"coordinates":[-2.14109608657707,53.48227263114993],"type":"Point"}
}