{
  "type": "Feature",
  "properties": {
    "iso:country": "GB",
    "wof:name": "M43 7EQ",
    "wof:placetype": "postalcode"
  },
  "geometry": {"coordinates":[-2.141096,53.482273],"type":"Point"}
}
