{
  "type": "Feature",
  "properties": {
    "date:inception_lower": "1980-01-01",
    "date:inception_upper": "1980-01-01",
    "iso:country": "GB",
    "wof:name": "PO32 6HZ",
    "wof:placetype": "postalcode"
  },
  "geometry": {"coordinates":[-1.277116,50.749185],"type":"Point"}
}
