{
  "type": "Feature",
  "properties": {
    "iso:country": "GB",
    "wof:name": "EH45 8BB",
    "wof:placetype": "postalcode"
  },
  "geometry": {"coordinates":[-3.183978,55.653182],"type":"Point"}
}
