{
  "type": "Feature",
  "properties": {
    "date:inception_lower": "2005-06-01",
    "date:inception_upper": "2005-06-01",
    "iso:country": "GB",
    "wof:name": "RG24 8EG",
    "wof:placetype": "postalcode"
  },
  "geometry": {"coordinates":[-1.063285,51.287301],"type":"Point"}
}
