{
  "type": "Feature",
  "properties": {
    "iso:country":"GB",
    "wof:name":"RG24 8EG",
    "wof:placetype":"postalcode"
},
  "geometry": {"coordinates":[-1.06328483893845,51.28730098049585],"type":"Point"}
}