{
  "type": "Feature",
  "properties": {
    "date:inception_lower":"1980-01-01",
    "date:inception_upper":"1980-01-31",
    "iso:country":"GB",
    "wof:name":"SY2 5NB",
    "wof:placetype":"postalcode"
},
  "geometry": {"coordinates":[-2.729743,52.708069],"type":"Point"}
}