{
  "type": "Feature",
  "properties": {
    "iso:country":"GB",
    "wof:name":"SK6 1RE",
    "wof:placetype":"postalcode"
},
  "geometry": {"coordinates":[-2.10219448386871,53.42851627478535],"type":"Point"}
}