{
  "type": "Feature",
  "properties": {
    "date:inception_lower": "1980-01-01",
    "date:inception_upper": "1980-01-01",
    "iso:country": "GB",
    "wof:name": "SK6 1RE",
    "wof:placetype": "postalcode"
  },
  "geometry": {"coordinates":[-2.102194,53.428516],"type":"Point"}
}
