{
  "type": "Feature",
  "properties": {
    "iso:country":"GB",
    "wof:name":"DN7 5RD",
    "wof:placetype":"postalcode"
},
  "geometry": {"coordinates":[-1.03045908678136,53.59678918841167],"type":"Point"}
}