{
  "type": "Feature",
  "properties": {
    "iso:country":"GB",
    "wof:name":"FK7 8BA",
    "wof:placetype":"postalcode"
},
  "geometry": {"coordinates":[-3.88665306974051,56.05114432228137],"type":"Point"}
}