{
  "type": "Feature",
  "properties": {
    "iso:country": "GB",
    "wof:name": "WA8 0RE",
    "wof:placetype": "postalcode"
  },
  "geometry": {"coordinates":[-2.711701,53.364479],"type":"Point"}
}
