{
  "type": "Feature",
  "properties": {
    "iso:country":"GB",
    "wof:name":"HP13 7RA",
    "wof:placetype":"postalcode"
},
  "geometry": {"coordinates":[-0.72933097921414,51.63004082734685],"type":"Point"}
}