{
  "type": "Feature",
  "properties": {
    "iso:country": "GB",
    "wof:name": "BS4 2LT",
    "wof:placetype": "postalcode"
  },
  "geometry": {"coordinates":[-2.560652,51.432779],"type":"Point"}
}
