{
  "type": "Feature",
  "properties": {
    "iso:country":"GB",
    "wof:name":"BS4 2LT",
    "wof:placetype":"postalcode"
},
  "geometry": {"coordinates":[-2.56065174805557,51.43277916935697],"type":"Point"}
}