{
  "type": "Feature",
  "properties": {
    "iso:country":"GB",
    "wof:name":"CH1 4PH",
    "wof:placetype":"postalcode"
},
  "geometry": {"coordinates":[-2.92641331442935,53.19515200800594],"type":"Point"}
}