{
  "type": "Feature",
  "properties": {
    "iso:country":"GB",
    "wof:name":"HU9 4SN",
    "wof:placetype":"postalcode"
},
  "geometry": {"coordinates":[-0.27325639499653,53.76519580450981],"type":"Point"}
}