{
  "type": "Feature",
  "properties": {
    "date:inception_lower":"1990-07-01",
    "date:inception_upper":"1990-07-31",
    "iso:country":"GB",
    "wof:name":"TS19 0XR",
    "wof:placetype":"postalcode"
},
  "geometry": {"coordinates":[-1.350217,54.574702],"type":"Point"}
}