{
  "type": "Feature",
  "properties": {
    "iso:country":"GB",
    "wof:name":"BS32 9AZ",
    "wof:placetype":"postalcode"
},
  "geometry": {"coordinates":[-2.55252807920437,51.53553758635761],"type":"Point"}
}