{
  "type": "Feature",
  "properties": {
    "iso:country": "GB",
    "wof:name": "BS32 9AZ",
    "wof:placetype": "postalcode"
  },
  "geometry": {"coordinates":[-2.552385,51.535475],"type":"Point"}
}
