{
  "type": "Feature",
  "properties": {
    "iso:country":"GB",
    "wof:name":"B63 4RR",
    "wof:placetype":"postalcode"
},
  "geometry": {"coordinates":[-2.0572901978471,52.44486932711025],"type":"Point"}
}