{
  "type": "Feature",
  "properties": {
    "date:inception_lower": "1980-01-01",
    "date:inception_upper": "1980-01-01",
    "iso:country": "GB",
    "wof:name": "B63 4RR",
    "wof:placetype": "postalcode"
  },
  "geometry": {"coordinates":[-2.057151,52.44483],"type":"Point"}
}
