{
  "type": "Feature",
  "properties": {
    "date:inception_lower": "1995-07-01",
    "date:inception_upper": "1995-07-01",
    "iso:country": "GB",
    "wof:name": "SE8 3EB",
    "wof:placetype": "postalcode"
  },
  "geometry": {"coordinates":[-0.021954,51.480087],"type":"Point"}
}
