{
  "type": "Feature",
  "properties": {
    "iso:country": "GB",
    "wof:name": "EC3V 3NB",
    "wof:placetype": "postalcode"
  },
  "geometry": {"coordinates":[-0.084844,51.513542],"type":"Point"}
}
