{
  "type": "Feature",
  "properties": {
    "iso:country": "GB",
    "wof:name": "PE8 4AG",
    "wof:placetype": "postalcode"
  },
  "geometry": {"coordinates":[-0.475401,52.483564],"type":"Point"}
}
