{
  "type": "Feature",
  "properties": {
    "iso:country":"GB",
    "wof:name":"DL17 0QP",
    "wof:placetype":"postalcode"
},
  "geometry": {"coordinates":[-1.55177685535708,54.66394697475721],"type":"Point"}
}