{
  "type": "Feature",
  "properties": {
    "date:inception_lower":"1980-01-01",
    "date:inception_upper":"1980-01-31",
    "iso:country":"GB",
    "wof:name":"DL17 0QP",
    "wof:placetype":"postalcode"
},
  "geometry": {"coordinates":[-1.551777,54.663947],"type":"Point"}
}