{
  "type": "Feature",
  "properties": {
    "date:inception_lower": "2018-02-01",
    "date:inception_upper": "2018-02-01",
    "iso:country": "GB",
    "wof:name": "LE9 6TJ",
    "wof:placetype": "postalcode"
  },
  "geometry": {"coordinates":[-1.217754,52.531364],"type":"Point"}
}
