{
  "type": "Feature",
  "properties": {
    "iso:country":"GB",
    "wof:name":"BS5 0YW",
    "wof:placetype":"postalcode"
},
  "geometry": {"coordinates":[-2.57285727783714,51.4666635810553],"type":"Point"}
}