{
  "type": "Feature",
  "properties": {
    "date:inception_lower":"2002-10-01",
    "date:inception_upper":"2002-10-31",
    "iso:country":"GB",
    "wof:name":"SY10 9HZ",
    "wof:placetype":"postalcode"
},
  "geometry": {"coordinates":[-3.171472,52.805197],"type":"Point"}
}