{
  "type": "Feature",
  "properties": {
    "iso:country":"GB",
    "wof:name":"L20 2AH",
    "wof:placetype":"postalcode"
},
  "geometry": {"coordinates":[-2.99100634736419,53.45376863123352],"type":"Point"}
}