{
  "type": "Feature",
  "properties": {
    "iso:country":"GB",
    "wof:name":"MK40 4HR",
    "wof:placetype":"postalcode"
},
  "geometry": {"coordinates":[-0.49307523629155,52.1331508011158],"type":"Point"}
}