{
  "type": "Feature",
  "properties": {
    "date:inception_lower": "1980-01-01",
    "date:inception_upper": "1980-01-01",
    "iso:country": "GB",
    "wof:name": "EN3 4AG",
    "wof:placetype": "postalcode"
  },
  "geometry": {"coordinates":[-0.051006,51.643644],"type":"Point"}
}
