{
  "type": "Feature",
  "properties": {
    "iso:country":"GB",
    "wof:name":"EN3 4AG",
    "wof:placetype":"postalcode"
},
  "geometry": {"coordinates":[-0.05100603095103,51.64364384930382],"type":"Point"}
}