{
  "type": "Feature",
  "properties": {
    "iso:country": "GB",
    "wof:name": "TA24 7DQ",
    "wof:placetype": "postalcode"
  },
  "geometry": {"coordinates":[-3.45376,51.109792],"type":"Point"}
}
