{
  "type": "Feature",
  "properties": {
    "iso:country":"GB",
    "wof:name":"AB54 4QU",
    "wof:placetype":"postalcode"
},
  "geometry": {"coordinates":[-2.80880211893609,57.44179080935779],"type":"Point"}
}