{
  "type": "Feature",
  "properties": {
    "iso:country":"GB",
    "wof:name":"CF11 8UU",
    "wof:placetype":"postalcode"
},
  "geometry": {"coordinates":[-3.19334399102663,51.46289722892285],"type":"Point"}
}