{
  "type": "Feature",
  "properties": {
    "iso:country":"GB",
    "wof:name":"BD11 2JY",
    "wof:placetype":"postalcode"
},
  "geometry": {"coordinates":[-1.68987260718775,53.75090150830465],"type":"Point"}
}