{
  "type": "Feature",
  "properties": {
    "iso:country": "GB",
    "wof:name": "CV22 6AR",
    "wof:placetype": "postalcode"
  },
  "geometry": {"coordinates":[-1.264971,52.368377],"type":"Point"}
}
