{
  "type": "Feature",
  "properties": {
    "iso:country":"GB",
    "wof:name":"SW4 8QQ",
    "wof:placetype":"postalcode"
},
  "geometry": {"coordinates":[-0.13766122708113,51.45310623333241],"type":"Point"}
}