{
  "type": "Feature",
  "properties": {
    "iso:country": "GB",
    "wof:name": "ST14 7HU",
    "wof:placetype": "postalcode"
  },
  "geometry": {"coordinates":[-1.864607,52.898524],"type":"Point"}
}
