{
  "type": "Feature",
  "properties": {
    "iso:country":"GB",
    "wof:name":"ST14 7HU",
    "wof:placetype":"postalcode"
},
  "geometry": {"coordinates":[-1.86460740702839,52.89852385501386],"type":"Point"}
}