{
  "type": "Feature",
  "properties": {
    "iso:country": "GB",
    "wof:name": "G77 6SB",
    "wof:placetype": "postalcode"
  },
  "geometry": {"coordinates":[-4.364255,55.732471],"type":"Point"}
}
