{
  "type": "Feature",
  "properties": {
    "iso:country": "GB",
    "wof:name": "WR11 1GP",
    "wof:placetype": "postalcode"
  },
  "geometry": {"coordinates":[-1.933077,52.074826],"type":"Point"}
}
