{
  "type": "Feature",
  "properties": {
    "date:inception_lower": "2001-12-01",
    "date:inception_upper": "2001-12-01",
    "iso:country": "GB",
    "wof:name": "WR11 1GP",
    "wof:placetype": "postalcode"
  },
  "geometry": {"coordinates":[-1.932083,52.076003],"type":"Point"}
}
