{
  "type": "Feature",
  "properties": {
    "iso:country":"GB",
    "wof:name":"WR11 1GP",
    "wof:placetype":"postalcode"
},
  "geometry": {"coordinates":[-1.93402007839018,52.07478850717469],"type":"Point"}
}