{
  "type": "Feature",
  "properties": {
    "date:inception_lower": "2018-06-01",
    "date:inception_upper": "2018-06-01",
    "iso:country": "GB",
    "wof:name": "PR25 3NT",
    "wof:placetype": "postalcode"
  },
  "geometry": {"coordinates":[-2.694163,53.702136],"type":"Point"}
}
