{
  "type": "Feature",
  "properties": {
    "iso:country": "GB",
    "wof:name": "PE15 9LZ",
    "wof:placetype": "postalcode"
  },
  "geometry": {"coordinates":[0.091597,52.543161],"type":"Point"}
}
