{
  "type": "Feature",
  "properties": {
    "iso:country":"GB",
    "wof:name":"PE15 9LZ",
    "wof:placetype":"postalcode"
},
  "geometry": {"coordinates":[0.0915968932106,52.54316111457142],"type":"Point"}
}