{
  "type": "Feature",
  "properties": {
    "iso:country":"GB",
    "wof:name":"DA2 6EW",
    "wof:placetype":"postalcode"
},
  "geometry": {"coordinates":[0.25198775462295,51.43884854026491],"type":"Point"}
}