{
  "type": "Feature",
  "properties": {
    "date:inception_lower": "2003-05-01",
    "date:inception_upper": "2003-05-01",
    "iso:country": "GB",
    "wof:name": "SY10 8BZ",
    "wof:placetype": "postalcode"
  },
  "geometry": {"coordinates":[-2.981222,52.778902],"type":"Point"}
}
