{
  "type": "Feature",
  "properties": {
    "iso:country":"GB",
    "wof:name":"G42 8PE",
    "wof:placetype":"postalcode"
},
  "geometry": {"coordinates":[-4.26562086717702,55.83538652807902],"type":"Point"}
}