{
  "type": "Feature",
  "properties": {
    "iso:country":"GB",
    "wof:name":"CO6 1EX",
    "wof:placetype":"postalcode"
},
  "geometry": {"coordinates":[0.76995881857051,51.87078461088831],"type":"Point"}
}