{
  "type": "Feature",
  "properties": {
    "date:inception_lower":"2006-09-01",
    "date:inception_upper":"2006-09-30",
    "iso:country":"GB",
    "wof:name":"DN33 3RZ",
    "wof:placetype":"postalcode"
},
  "geometry": {"coordinates":[-0.1093,53.542467],"type":"Point"}
}