{
  "type": "Feature",
  "properties": {
    "iso:country": "GB",
    "wof:name": "DN33 3RZ",
    "wof:placetype": "postalcode"
  },
  "geometry": {"coordinates":[-0.1093,53.542467],"type":"Point"}
}
