{
  "type": "Feature",
  "properties": {
    "iso:country":"GB",
    "wof:name":"CB7 5YJ",
    "wof:placetype":"postalcode"
},
  "geometry": {"coordinates":[0.2474667749165,52.29128410604046],"type":"Point"}
}