{
  "type": "Feature",
  "properties": {
    "date:inception_lower": "1980-01-01",
    "date:inception_upper": "1980-01-01",
    "iso:country": "GB",
    "wof:name": "CB7 5YJ",
    "wof:placetype": "postalcode"
  },
  "geometry": {"coordinates":[0.247233,52.292466],"type":"Point"}
}
