{
  "type": "Feature",
  "properties": {
    "date:inception_lower": "2019-04-01",
    "date:inception_upper": "2019-04-01",
    "iso:country": "GB",
    "wof:name": "NR15 1BF",
    "wof:placetype": "postalcode"
  },
  "geometry": {"coordinates":[1.413501,52.527885],"type":"Point"}
}
