{
  "type": "Feature",
  "properties": {
    "iso:country": "GB",
    "wof:name": "DE13 0TU",
    "wof:placetype": "postalcode"
  },
  "geometry": {"coordinates":[-1.643226,52.822788],"type":"Point"}
}
