{
  "type": "Feature",
  "properties": {
    "date:inception_lower": "1986-07-01",
    "date:inception_upper": "1986-07-01",
    "iso:country": "GB",
    "wof:name": "DE13 0TU",
    "wof:placetype": "postalcode"
  },
  "geometry": {"coordinates":[-1.643226,52.822788],"type":"Point"}
}
