{
  "type": "Feature",
  "properties": {
    "iso:country":"GB",
    "wof:name":"DE13 0TU",
    "wof:placetype":"postalcode"
},
  "geometry": {"coordinates":[-1.64322583464396,52.82278832905133],"type":"Point"}
}