{
  "type": "Feature",
  "properties": {
    "date:inception_lower": "1980-01-01",
    "date:inception_upper": "1980-01-01",
    "iso:country": "GB",
    "wof:name": "BH21 4BU",
    "wof:placetype": "postalcode"
  },
  "geometry": {"coordinates":[-2.070703,50.802659],"type":"Point"}
}
