{
  "type": "Feature",
  "properties": {
    "date:inception_lower": "1980-01-01",
    "date:inception_upper": "1980-01-01",
    "iso:country": "GB",
    "wof:name": "TQ5 0JF",
    "wof:placetype": "postalcode"
  },
  "geometry": {"coordinates":[-3.545031,50.39827],"type":"Point"}
}
