{
  "type": "Feature",
  "properties": {
    "date:inception_lower": "1980-01-01",
    "date:inception_upper": "1980-01-01",
    "iso:country": "GB",
    "wof:name": "PE10 0JW",
    "wof:placetype": "postalcode"
  },
  "geometry": {"coordinates":[-0.438965,52.735304],"type":"Point"}
}
