{
  "type": "Feature",
  "properties": {
    "date:inception_lower": "2015-08-01",
    "date:inception_upper": "2015-08-01",
    "iso:country": "GB",
    "wof:name": "CF35 6GA",
    "wof:placetype": "postalcode"
  },
  "geometry": {"coordinates":[-3.553329,51.519225],"type":"Point"}
}
