{
  "type": "Feature",
  "properties": {
    "iso:country":"GB",
    "wof:name":"B78 3QT",
    "wof:placetype":"postalcode"
},
  "geometry": {"coordinates":[-1.71759324463105,52.61776435634179],"type":"Point"}
}