{
  "type": "Feature",
  "properties": {
    "date:inception_lower":"1991-09-01",
    "date:inception_upper":"1991-09-30",
    "iso:country":"GB",
    "wof:name":"B78 3QT",
    "wof:placetype":"postalcode"
},
  "geometry": {"coordinates":[-1.717593,52.617764],"type":"Point"}
}