{
  "type": "Feature",
  "properties": {
    "date:inception_lower": "1994-05-01",
    "date:inception_upper": "1994-05-01",
    "iso:country": "GB",
    "wof:name": "M9 6SD",
    "wof:placetype": "postalcode"
  },
  "geometry": {"coordinates":[-2.207191,53.526559],"type":"Point"}
}
