{
  "type": "Feature",
  "properties": {
    "iso:country":"GB",
    "wof:name":"M9 6SD",
    "wof:placetype":"postalcode"
},
  "geometry": {"coordinates":[-2.20702690799915,53.5264803707372],"type":"Point"}
}