{
  "type": "Feature",
  "properties": {
    "date:inception_lower": "2020-02-01",
    "date:inception_upper": "2020-02-01",
    "iso:country": "GB",
    "wof:name": "BN18 0XH",
    "wof:placetype": "postalcode"
  },
  "geometry": {"coordinates":[-0.611222,50.825398],"type":"Point"}
}
