{
  "type": "Feature",
  "properties": {
    "iso:country": "GB",
    "wof:name": "BN18 0XH",
    "wof:placetype": "postalcode"
  },
  "geometry": {"coordinates":[-0.611222,50.825398],"type":"Point"}
}
