{
  "type": "Feature",
  "properties": {
    "date:inception_lower": "2017-09-01",
    "date:inception_upper": "2017-09-01",
    "iso:country": "GB",
    "wof:name": "BA16 0GX",
    "wof:placetype": "postalcode"
  },
  "geometry": {"coordinates":[-2.756098,51.127449],"type":"Point"}
}
