{
  "type": "Feature",
  "properties": {
    "iso:country":"GB",
    "wof:name":"EX8 4DJ",
    "wof:placetype":"postalcode"
},
  "geometry": {"coordinates":[-3.39066015039022,50.63422880031987],"type":"Point"}
}