{
  "type": "Feature",
  "properties": {
    "iso:country": "GB",
    "wof:name": "EX8 4DJ",
    "wof:placetype": "postalcode"
  },
  "geometry": {"coordinates":[-3.39066,50.634229],"type":"Point"}
}
