{
  "type": "Feature",
  "properties": {
    "iso:country":"GB",
    "wof:name":"N21 1JU",
    "wof:placetype":"postalcode"
},
  "geometry": {"coordinates":[-0.11059590447613,51.63916852145438],"type":"Point"}
}