{
  "type": "Feature",
  "properties": {
    "date:inception_lower": "2019-02-01",
    "date:inception_upper": "2019-02-01",
    "iso:country": "GB",
    "wof:name": "CF71 7FG",
    "wof:placetype": "postalcode"
  },
  "geometry": {"coordinates":[-3.466471,51.461291],"type":"Point"}
}
