{
  "type": "Feature",
  "properties": {
    "iso:country": "GB",
    "wof:name": "PO15 5NS",
    "wof:placetype": "postalcode"
  },
  "geometry": {"coordinates":[-1.224215,50.852144],"type":"Point"}
}
