{
  "type": "Feature",
  "properties": {
    "iso:country": "GB",
    "wof:name": "KA11 2FH",
    "wof:placetype": "postalcode"
  },
  "geometry": {"coordinates":[-4.648713,55.629361],"type":"Point"}
}
