{
  "type": "Feature",
  "properties": {
    "iso:country":"GB",
    "wof:name":"KA11 2FH",
    "wof:placetype":"postalcode"
},
  "geometry": {"coordinates":[-4.64871286557161,55.62936121135844],"type":"Point"}
}