{
  "type": "Feature",
  "properties": {
    "date:inception_lower":"2007-11-01",
    "date:inception_upper":"2007-11-30",
    "iso:country":"GB",
    "wof:name":"KA11 2FH",
    "wof:placetype":"postalcode"
},
  "geometry": {"coordinates":[-4.648713,55.629361],"type":"Point"}
}