{
  "type": "Feature",
  "properties": {
    "date:inception_lower": "2008-06-01",
    "date:inception_upper": "2008-06-01",
    "iso:country": "GB",
    "wof:name": "BD2 3JF",
    "wof:placetype": "postalcode"
  },
  "geometry": {"coordinates":[-1.720146,53.807957],"type":"Point"}
}
