{
  "type": "Feature",
  "properties": {
    "iso:country":"GB",
    "wof:name":"BD2 3JF",
    "wof:placetype":"postalcode"
},
  "geometry": {"coordinates":[-1.7200959823226,53.80799579321402],"type":"Point"}
}