{
  "type": "Feature",
  "properties": {
    "iso:country":"GB",
    "wof:name":"NE63 8PN",
    "wof:placetype":"postalcode"
},
  "geometry": {"coordinates":[-1.59008918784914,55.18262170569557],"type":"Point"}
}