{
  "type": "Feature",
  "properties": {
    "iso:country":"GB",
    "wof:name":"IP22 4AW",
    "wof:placetype":"postalcode"
},
  "geometry": {"coordinates":[1.11067155338728,52.37439575714831],"type":"Point"}
}