{
  "type": "Feature",
  "properties": {
    "iso:country":"GB",
    "wof:name":"WV10 9PX",
    "wof:placetype":"postalcode"
},
  "geometry": {"coordinates":[-2.11271295341491,52.60618895832057],"type":"Point"}
}