{
  "type": "Feature",
  "properties": {
    "iso:country":"GB",
    "wof:name":"DA12 5HB",
    "wof:placetype":"postalcode"
},
  "geometry": {"coordinates":[0.37216099838388,51.43091977276986],"type":"Point"}
}