{
  "type": "Feature",
  "properties": {
    "iso:country": "GB",
    "wof:name": "DA12 5HB",
    "wof:placetype": "postalcode"
  },
  "geometry": {"coordinates":[0.372161,51.43092],"type":"Point"}
}
