{
  "type": "Feature",
  "properties": {
    "iso:country": "GB",
    "wof:name": "SK16 5EL",
    "wof:placetype": "postalcode"
  },
  "geometry": {"coordinates":[-2.064038,53.475004],"type":"Point"}
}
