{
  "type": "Feature",
  "properties": {
    "iso:country":"GB",
    "wof:name":"B12 9RT",
    "wof:placetype":"postalcode"
},
  "geometry": {"coordinates":[-1.89089795667094,52.45484812339384],"type":"Point"}
}