{
  "type": "Feature",
  "properties": {
    "date:inception_lower": "1991-01-01",
    "date:inception_upper": "1991-01-01",
    "iso:country": "GB",
    "wof:name": "DA3 7RN",
    "wof:placetype": "postalcode"
  },
  "geometry": {"coordinates":[0.297283,51.396628],"type":"Point"}
}
