{
  "type": "Feature",
  "properties": {
    "iso:country":"GB",
    "wof:name":"DA3 7RN",
    "wof:placetype":"postalcode"
},
  "geometry": {"coordinates":[0.29728267588079,51.39662769737753],"type":"Point"}
}