{
  "type": "Feature",
  "properties": {
    "iso:country": "GB",
    "wof:name": "DA3 7RN",
    "wof:placetype": "postalcode"
  },
  "geometry": {"coordinates":[0.297283,51.396628],"type":"Point"}
}
