{
  "type": "Feature",
  "properties": {
    "date:inception_lower": "2006-01-01",
    "date:inception_upper": "2006-01-01",
    "iso:country": "GB",
    "wof:name": "EH49 7RZ",
    "wof:placetype": "postalcode"
  },
  "geometry": {"coordinates":[-3.532312,55.979369],"type":"Point"}
}
