{
  "type": "Feature",
  "properties": {
    "iso:country":"GB",
    "wof:name":"DN22 7NN",
    "wof:placetype":"postalcode"
},
  "geometry": {"coordinates":[-0.95553129225282,53.32040623443908],"type":"Point"}
}