{
  "type": "Feature",
  "properties": {
    "date:inception_lower": "2024-04-01",
    "date:inception_upper": "2024-04-01",
    "iso:country": "GB",
    "wof:name": "BN3 3GW",
    "wof:placetype": "postalcode"
  },
  "geometry": {"coordinates":[-0.172145,50.834638],"type":"Point"}
}
