{
  "type": "Feature",
  "properties": {
    "iso:country":"GB",
    "wof:name":"SE14 5BZ",
    "wof:placetype":"postalcode"
},
  "geometry": {"coordinates":[-0.05200521777235,51.47378220195518],"type":"Point"}
}