{
  "type": "Feature",
  "properties": {
    "date:inception_lower": "2003-04-01",
    "date:inception_upper": "2003-04-01",
    "iso:country": "GB",
    "wof:name": "SE14 5BZ",
    "wof:placetype": "postalcode"
  },
  "geometry": {"coordinates":[-0.052005,51.473782],"type":"Point"}
}
