{
  "type": "Feature",
  "properties": {
    "iso:country":"GB",
    "wof:name":"CV3 2PT",
    "wof:placetype":"postalcode"
},
  "geometry": {"coordinates":[-1.46384681072197,52.39657890479231],"type":"Point"}
}