{
  "type": "Feature",
  "properties": {
    "iso:country":"GB",
    "wof:name":"HA6 3LY",
    "wof:placetype":"postalcode"
},
  "geometry": {"coordinates":[-0.417397216369,51.61575719751591],"type":"Point"}
}