{
  "type": "Feature",
  "properties": {
    "iso:country": "GB",
    "wof:name": "HA6 3LY",
    "wof:placetype": "postalcode"
  },
  "geometry": {"coordinates":[-0.417397,51.615757],"type":"Point"}
}
