{
  "type": "Feature",
  "properties": {
    "iso:country": "GB",
    "wof:name": "ST4 8GX",
    "wof:placetype": "postalcode"
  },
  "geometry": {"coordinates":[-2.181237,52.964524],"type":"Point"}
}
