{
  "type": "Feature",
  "properties": {
    "date:inception_lower": "1980-01-01",
    "date:inception_upper": "1980-01-01",
    "iso:country": "GB",
    "wof:name": "PL5 1DJ",
    "wof:placetype": "postalcode"
  },
  "geometry": {"coordinates":[-4.1931,50.399203],"type":"Point"}
}
