{
  "type": "Feature",
  "properties": {
    "iso:country":"GB",
    "wof:name":"PL5 1DJ",
    "wof:placetype":"postalcode"
},
  "geometry": {"coordinates":[-4.19309964137752,50.39920331747958],"type":"Point"}
}