{
  "type": "Feature",
  "properties": {
    "iso:country": "GB",
    "wof:name": "DN34 5QP",
    "wof:placetype": "postalcode"
  },
  "geometry": {"coordinates":[-0.130599,53.551297],"type":"Point"}
}
