{
  "type": "Feature",
  "properties": {
    "iso:country":"GB",
    "wof:name":"DN34 5QP",
    "wof:placetype":"postalcode"
},
  "geometry": {"coordinates":[-0.1305993445768,53.55129713475979],"type":"Point"}
}