{
  "type": "Feature",
  "properties": {
    "iso:country":"GB",
    "wof:name":"WD17 4QQ",
    "wof:placetype":"postalcode"
},
  "geometry": {"coordinates":[-0.4032502276043,51.66695517618675],"type":"Point"}
}