{
  "type": "Feature",
  "properties": {
    "iso:country": "GB",
    "wof:name": "SR7 7JP",
    "wof:placetype": "postalcode"
  },
  "geometry": {"coordinates":[-1.331964,54.835272],"type":"Point"}
}
