{
  "type": "Feature",
  "properties": {
    "iso:country": "GB",
    "wof:name": "KT15 1FR",
    "wof:placetype": "postalcode"
  },
  "geometry": {"coordinates":[-0.505574,51.359008],"type":"Point"}
}
