{
  "type": "Feature",
  "properties": {
    "iso:country":"GB",
    "wof:name":"CM3 4DS",
    "wof:placetype":"postalcode"
},
  "geometry": {"coordinates":[0.56192167048667,51.72045065059477],"type":"Point"}
}