{
  "type": "Feature",
  "properties": {
    "iso:country":"GB",
    "wof:name":"HU6 7NG",
    "wof:placetype":"postalcode"
},
  "geometry": {"coordinates":[-0.34822914880796,53.77232895000936],"type":"Point"}
}