{
  "type": "Feature",
  "properties": {
    "date:inception_lower": "1987-04-01",
    "date:inception_upper": "1987-04-01",
    "iso:country": "GB",
    "wof:name": "HU6 7NG",
    "wof:placetype": "postalcode"
  },
  "geometry": {"coordinates":[-0.348229,53.772329],"type":"Point"}
}
