{
  "type": "Feature",
  "properties": {
    "iso:country":"GB",
    "wof:name":"SW15 6JR",
    "wof:placetype":"postalcode"
},
  "geometry": {"coordinates":[-0.23327374991613,51.46466667843234],"type":"Point"}
}