{
  "type": "Feature",
  "properties": {
    "iso:country": "GB",
    "wof:name": "SW15 6JR",
    "wof:placetype": "postalcode"
  },
  "geometry": {"coordinates":[-0.233223,51.464631],"type":"Point"}
}
