{
  "type": "Feature",
  "properties": {
    "iso:country":"GB",
    "wof:name":"SG16 6HX",
    "wof:placetype":"postalcode"
},
  "geometry": {"coordinates":[-0.29503422310984,52.01071330251876],"type":"Point"}
}