{
  "type": "Feature",
  "properties": {
    "iso:country":"GB",
    "wof:name":"IP24 2YH",
    "wof:placetype":"postalcode"
},
  "geometry": {"coordinates":[0.76276463558756,52.41932287482086],"type":"Point"}
}