{
  "type": "Feature",
  "properties": {
    "iso:country":"GB",
    "wof:name":"KY1 1NQ",
    "wof:placetype":"postalcode"
},
  "geometry": {"coordinates":[-3.15867657425084,56.11026635331339],"type":"Point"}
}