{
  "type": "Feature",
  "properties": {
    "iso:country":"GB",
    "wof:name":"TS19 8AW",
    "wof:placetype":"postalcode"
},
  "geometry": {"coordinates":[-1.34194561060599,54.57921344937855],"type":"Point"}
}