{
  "type": "Feature",
  "properties": {
    "date:inception_lower":"1980-01-01",
    "date:inception_upper":"1980-01-31",
    "iso:country":"GB",
    "wof:name":"SY18 6DE",
    "wof:placetype":"postalcode"
},
  "geometry": {"coordinates":[-3.537629,52.446531],"type":"Point"}
}