{
  "type": "Feature",
  "properties": {
    "iso:country": "GB",
    "wof:name": "SY18 6DE",
    "wof:placetype": "postalcode"
  },
  "geometry": {"coordinates":[-3.537629,52.446531],"type":"Point"}
}
