{
  "type": "Feature",
  "properties": {
    "iso:country":"GB",
    "wof:name":"DN22 6LD",
    "wof:placetype":"postalcode"
},
  "geometry": {"coordinates":[-0.93915493843851,53.32213150888905],"type":"Point"}
}