{
  "type": "Feature",
  "properties": {
    "iso:country":"GB",
    "wof:name":"PO30 5SD",
    "wof:placetype":"postalcode"
},
  "geometry": {"coordinates":[-1.30878320789818,50.70964636786475],"type":"Point"}
}