{
  "type": "Feature",
  "properties": {
    "iso:country":"GB",
    "wof:name":"RG9 5ER",
    "wof:placetype":"postalcode"
},
  "geometry": {"coordinates":[-0.98357960856972,51.52486835004916],"type":"Point"}
}