{
  "type": "Feature",
  "properties": {
    "iso:country": "GB",
    "wof:name": "S66 3XH",
    "wof:placetype": "postalcode"
  },
  "geometry": {"coordinates":[-1.27855,53.436155],"type":"Point"}
}
