{
  "type": "Feature",
  "properties": {
    "date:inception_lower": "2008-01-01",
    "date:inception_upper": "2008-01-01",
    "iso:country": "GB",
    "wof:name": "S66 3XH",
    "wof:placetype": "postalcode"
  },
  "geometry": {"coordinates":[-1.27855,53.436155],"type":"Point"}
}
