{
  "type": "Feature",
  "properties": {
    "iso:country":"GB",
    "wof:name":"S66 3XH",
    "wof:placetype":"postalcode"
},
  "geometry": {"coordinates":[-1.2785496289523,53.4361088373891],"type":"Point"}
}