{
  "type": "Feature",
  "properties": {
    "iso:country": "GB",
    "wof:name": "SP11 0SG",
    "wof:placetype": "postalcode"
  },
  "geometry": {"coordinates":[-1.52316,51.270698],"type":"Point"}
}
