{
  "type": "Feature",
  "properties": {
    "iso:country": "GB",
    "wof:name": "LE5 5AP",
    "wof:placetype": "postalcode"
  },
  "geometry": {"coordinates":[-1.107913,52.630746],"type":"Point"}
}
