{
  "type": "Feature",
  "properties": {
    "iso:country":"GB",
    "wof:name":"MK7 8AD",
    "wof:placetype":"postalcode"
},
  "geometry": {"coordinates":[-0.70064312944467,52.01065236092573],"type":"Point"}
}