{
  "type": "Feature",
  "properties": {
    "iso:country": "GB",
    "wof:name": "MK7 8AD",
    "wof:placetype": "postalcode"
  },
  "geometry": {"coordinates":[-0.700643,52.010652],"type":"Point"}
}
