{
  "type": "Feature",
  "properties": {
    "iso:country":"GB",
    "wof:name":"PO17 5DW",
    "wof:placetype":"postalcode"
},
  "geometry": {"coordinates":[-1.17373844225491,50.88766929881352],"type":"Point"}
}