{
  "type": "Feature",
  "properties": {
    "iso:country":"GB",
    "wof:name":"SW5 9HA",
    "wof:placetype":"postalcode"
},
  "geometry": {"coordinates":[-0.19928040919612,51.49180142440733],"type":"Point"}
}