{
  "type": "Feature",
  "properties": {
    "iso:country":"GB",
    "wof:name":"RH14 0RG",
    "wof:placetype":"postalcode"
},
  "geometry": {"coordinates":[-0.51611860354131,51.06807147799373],"type":"Point"}
}