{
  "type": "Feature",
  "properties": {
    "iso:country": "GB",
    "wof:name": "CA8 2BS",
    "wof:placetype": "postalcode"
  },
  "geometry": {"coordinates":[-2.655893,54.994613],"type":"Point"}
}
