{
  "type": "Feature",
  "properties": {
    "iso:country":"GB",
    "wof:name":"CA8 2BS",
    "wof:placetype":"postalcode"
},
  "geometry": {"coordinates":[-2.65589290027428,54.99461312623013],"type":"Point"}
}