{
  "type": "Feature",
  "properties": {
    "iso:country": "GB",
    "wof:name": "OX26 1DQ",
    "wof:placetype": "postalcode"
  },
  "geometry": {"coordinates":[-1.174722,51.895741],"type":"Point"}
}
