{
  "type": "Feature",
  "properties": {
    "iso:country":"GB",
    "wof:name":"BS3 3PT",
    "wof:placetype":"postalcode"
},
  "geometry": {"coordinates":[-2.60684347903289,51.43502176828795],"type":"Point"}
}