{
  "type": "Feature",
  "properties": {
    "iso:country":"GB",
    "wof:name":"TA24 8TG",
    "wof:placetype":"postalcode"
},
  "geometry": {"coordinates":[-3.55162331753011,51.20207575867794],"type":"Point"}
}