{
  "type": "Feature",
  "properties": {
    "iso:country":"GB",
    "wof:name":"ME14 3HD",
    "wof:placetype":"postalcode"
},
  "geometry": {"coordinates":[0.58251647174303,51.30731502886279],"type":"Point"}
}