{
  "type": "Feature",
  "properties": {
    "iso:country": "GB",
    "wof:name": "SA67 7AT",
    "wof:placetype": "postalcode"
  },
  "geometry": {"coordinates":[-4.743476,51.797893],"type":"Point"}
}
