{
  "type": "Feature",
  "properties": {
    "iso:country":"GB",
    "wof:name":"SA67 7AT",
    "wof:placetype":"postalcode"
},
  "geometry": {"coordinates":[-4.74354919991218,51.79789750426595],"type":"Point"}
}