{
  "type": "Feature",
  "properties": {
    "date:inception_lower":"1980-01-01",
    "date:inception_upper":"1980-01-31",
    "iso:country":"GB",
    "wof:name":"SA67 7AT",
    "wof:placetype":"postalcode"
},
  "geometry": {"coordinates":[-4.743476,51.797893],"type":"Point"}
}