{
  "type": "Feature",
  "properties": {
    "iso:country": "GB",
    "wof:name": "ST3 2AP",
    "wof:placetype": "postalcode"
  },
  "geometry": {"coordinates":[-2.161186,52.98539],"type":"Point"}
}
