{
  "type": "Feature",
  "properties": {
    "iso:country":"GB",
    "wof:name":"ST3 2AP",
    "wof:placetype":"postalcode"
},
  "geometry": {"coordinates":[-2.16118619150642,52.98539020065006],"type":"Point"}
}