{
  "type": "Feature",
  "properties": {
    "iso:country":"GB",
    "wof:name":"BN5 9JT",
    "wof:placetype":"postalcode"
},
  "geometry": {"coordinates":[-0.26966294952002,50.93837506523811],"type":"Point"}
}