{
  "type": "Feature",
  "properties": {
    "iso:country":"GB",
    "wof:name":"B93 8HE",
    "wof:placetype":"postalcode"
},
  "geometry": {"coordinates":[-1.75421322072804,52.37368772056659],"type":"Point"}
}