{
  "type": "Feature",
  "properties": {
    "iso:country":"GB",
    "wof:name":"GL20 7AE",
    "wof:placetype":"postalcode"
},
  "geometry": {"coordinates":[-2.03336988854516,52.02131682610912],"type":"Point"}
}