{
  "type": "Feature",
  "properties": {
    "iso:country": "GB",
    "wof:name": "NN6 9QA",
    "wof:placetype": "postalcode"
  },
  "geometry": {"coordinates":[-0.807598,52.368011],"type":"Point"}
}
