{
  "type": "Feature",
  "properties": {
    "date:inception_lower": "1991-09-01",
    "date:inception_upper": "1991-09-01",
    "iso:country": "GB",
    "wof:name": "CB5 8LJ",
    "wof:placetype": "postalcode"
  },
  "geometry": {"coordinates":[0.146732,52.214084],"type":"Point"}
}
