{
  "type": "Feature",
  "properties": {
    "iso:country":"GB",
    "wof:name":"WR10 2LG",
    "wof:placetype":"postalcode"
},
  "geometry": {"coordinates":[-2.06327907163838,52.16892031667923],"type":"Point"}
}