{
  "type": "Feature",
  "properties": {
    "date:inception_lower": "1980-01-01",
    "date:inception_upper": "1980-01-01",
    "iso:country": "GB",
    "wof:name": "WR10 2LG",
    "wof:placetype": "postalcode"
  },
  "geometry": {"coordinates":[-2.062716,52.168502],"type":"Point"}
}
