{
  "type": "Feature",
  "properties": {
    "date:inception_lower": "2007-07-01",
    "date:inception_upper": "2007-07-01",
    "iso:country": "GB",
    "wof:name": "PR2 5DB",
    "wof:placetype": "postalcode"
  },
  "geometry": {"coordinates":[-2.648533,53.78733],"type":"Point"}
}
