{
  "type": "Feature",
  "properties": {
    "iso:country":"GB",
    "wof:name":"LA3 3JF",
    "wof:placetype":"postalcode"
},
  "geometry": {"coordinates":[-2.87996523220694,53.99904653396749],"type":"Point"}
}