{
  "type": "Feature",
  "properties": {
    "date:inception_lower": "1980-01-01",
    "date:inception_upper": "1980-01-01",
    "iso:country": "GB",
    "wof:name": "CV35 8JP",
    "wof:placetype": "postalcode"
  },
  "geometry": {"coordinates":[-1.676151,52.2679],"type":"Point"}
}
