{
  "type": "Feature",
  "properties": {
    "iso:country": "GB",
    "wof:name": "CV35 8JP",
    "wof:placetype": "postalcode"
  },
  "geometry": {"coordinates":[-1.676151,52.2679],"type":"Point"}
}
