{
  "type": "Feature",
  "properties": {
    "iso:country":"GB",
    "wof:name":"CV35 8JP",
    "wof:placetype":"postalcode"
},
  "geometry": {"coordinates":[-1.67615118241323,52.26790045823],"type":"Point"}
}