{
  "type": "Feature",
  "properties": {
    "date:inception_lower": "1980-01-01",
    "date:inception_upper": "1980-01-01",
    "iso:country": "GB",
    "wof:name": "LL18 4RG",
    "wof:placetype": "postalcode"
  },
  "geometry": {"coordinates":[-3.479781,53.32011],"type":"Point"}
}
