{
  "type": "Feature",
  "properties": {
    "iso:country":"GB",
    "wof:name":"NG7 5AQ",
    "wof:placetype":"postalcode"
},
  "geometry": {"coordinates":[-1.17111715949209,52.9634019036222],"type":"Point"}
}