{
  "type": "Feature",
  "properties": {
    "iso:country":"GB",
    "wof:name":"RM13 8BF",
    "wof:placetype":"postalcode"
},
  "geometry": {"coordinates":[0.17318052385979,51.52494189031714],"type":"Point"}
}