{
  "type": "Feature",
  "properties": {
    "iso:country": "GB",
    "wof:name": "RM13 8BF",
    "wof:placetype": "postalcode"
  },
  "geometry": {"coordinates":[0.173181,51.524942],"type":"Point"}
}
