{
  "type": "Feature",
  "properties": {
    "date:inception_lower": "1999-06-01",
    "date:inception_upper": "1999-06-01",
    "iso:country": "GB",
    "wof:name": "NP20 6PH",
    "wof:placetype": "postalcode"
  },
  "geometry": {"coordinates":[-3.009556,51.615409],"type":"Point"}
}
