{
  "type": "Feature",
  "properties": {
    "iso:country": "GB",
    "wof:name": "LE67 2DP",
    "wof:placetype": "postalcode"
  },
  "geometry": {"coordinates":[-1.40072,52.714799],"type":"Point"}
}
