{
  "type": "Feature",
  "properties": {
    "iso:country": "GB",
    "wof:name": "SP6 3LT",
    "wof:placetype": "postalcode"
  },
  "geometry": {"coordinates":[-1.911821,50.981338],"type":"Point"}
}
