{
  "type": "Feature",
  "properties": {
    "iso:country":"GB",
    "wof:name":"SP6 3LT",
    "wof:placetype":"postalcode"
},
  "geometry": {"coordinates":[-1.91200021324568,50.98124623700419],"type":"Point"}
}