{
  "type": "Feature",
  "properties": {
    "iso:country":"GB",
    "wof:name":"TQ13 8JR",
    "wof:placetype":"postalcode"
},
  "geometry": {"coordinates":[-3.822218825555,50.69464090129768],"type":"Point"}
}