{
  "type": "Feature",
  "properties": {
    "iso:country": "GB",
    "wof:name": "TQ13 8JR",
    "wof:placetype": "postalcode"
  },
  "geometry": {"coordinates":[-3.822219,50.694641],"type":"Point"}
}
