{
  "type": "Feature",
  "properties": {
    "date:inception_lower": "1993-01-01",
    "date:inception_upper": "1993-01-01",
    "iso:country": "GB",
    "wof:name": "CV35 7RT",
    "wof:placetype": "postalcode"
  },
  "geometry": {"coordinates":[-1.577156,52.316852],"type":"Point"}
}
