{
  "type": "Feature",
  "properties": {
    "iso:country":"GB",
    "wof:name":"CV35 7RT",
    "wof:placetype":"postalcode"
},
  "geometry": {"coordinates":[-1.57715352427453,52.31683657132172],"type":"Point"}
}