{
  "type": "Feature",
  "properties": {
    "iso:country": "GB",
    "wof:name": "CV35 7RT",
    "wof:placetype": "postalcode"
  },
  "geometry": {"coordinates":[-1.577156,52.316852],"type":"Point"}
}
