{
  "type": "Feature",
  "properties": {
    "iso:country":"GB",
    "wof:name":"BH17 7AL",
    "wof:placetype":"postalcode"
},
  "geometry": {"coordinates":[-1.992578563763,50.74038014464876],"type":"Point"}
}