{
  "type": "Feature",
  "properties": {
    "iso:country": "GB",
    "wof:name": "YO21 2HJ",
    "wof:placetype": "postalcode"
  },
  "geometry": {"coordinates":[-0.982899,54.486146],"type":"Point"}
}
