{
  "type": "Feature",
  "properties": {
    "date:inception_lower":"1980-01-01",
    "date:inception_upper":"1980-01-31",
    "iso:country":"GB",
    "wof:name":"YO21 2HJ",
    "wof:placetype":"postalcode"
},
  "geometry": {"coordinates":[-0.982899,54.486146],"type":"Point"}
}