{
  "type": "Feature",
  "properties": {
    "iso:country":"GB",
    "wof:name":"TR5 0YP",
    "wof:placetype":"postalcode"
},
  "geometry": {"coordinates":[-5.19420058280078,50.30381998469726],"type":"Point"}
}