{
  "type": "Feature",
  "properties": {
    "date:inception_lower": "1987-04-01",
    "date:inception_upper": "1987-04-01",
    "iso:country": "GB",
    "wof:name": "TR5 0YP",
    "wof:placetype": "postalcode"
  },
  "geometry": {"coordinates":[-5.194201,50.30382],"type":"Point"}
}
