{
  "type": "Feature",
  "properties": {
    "date:inception_lower": "2009-07-01",
    "date:inception_upper": "2009-07-01",
    "iso:country": "GB",
    "wof:name": "BB9 8AL",
    "wof:placetype": "postalcode"
  },
  "geometry": {"coordinates":[-2.216444,53.848742],"type":"Point"}
}
