{
  "type": "Feature",
  "properties": {
    "iso:country":"GB",
    "wof:name":"NE36 0AN",
    "wof:placetype":"postalcode"
},
  "geometry": {"coordinates":[-1.43350938961913,54.93949327472121],"type":"Point"}
}