{
  "type": "Feature",
  "properties": {
    "iso:country":"GB",
    "wof:name":"OX11 9AF",
    "wof:placetype":"postalcode"
},
  "geometry": {"coordinates":[-1.19489306914677,51.58953033077614],"type":"Point"}
}