{
  "type": "Feature",
  "properties": {
    "iso:country": "GB",
    "wof:name": "OX11 9AF",
    "wof:placetype": "postalcode"
  },
  "geometry": {"coordinates":[-1.194893,51.58953],"type":"Point"}
}
