{
  "type": "Feature",
  "properties": {
    "iso:country":"GB",
    "wof:name":"SY11 4LF",
    "wof:placetype":"postalcode"
},
  "geometry": {"coordinates":[-2.9737148765928,52.82380471201432],"type":"Point"}
}