{
  "type": "Feature",
  "properties": {
    "date:inception_lower": "1980-01-01",
    "date:inception_upper": "1980-01-01",
    "iso:country": "GB",
    "wof:name": "G44 3YY",
    "wof:placetype": "postalcode"
  },
  "geometry": {"coordinates":[-4.260235,55.812208],"type":"Point"}
}
