{
  "type": "Feature",
  "properties": {
    "iso:country":"GB",
    "wof:name":"N3 3NS",
    "wof:placetype":"postalcode"
},
  "geometry": {"coordinates":[-0.19288667009815,51.59549341396185],"type":"Point"}
}