{
  "type": "Feature",
  "properties": {
    "iso:country":"GB",
    "wof:name":"HS6 5AW",
    "wof:placetype":"postalcode"
},
  "geometry": {"coordinates":[-7.18183498922938,57.61118376484461],"type":"Point"}
}