{
  "type": "Feature",
  "properties": {
    "iso:country": "GB",
    "wof:name": "PR4 2BF",
    "wof:placetype": "postalcode"
  },
  "geometry": {"coordinates":[-2.885025,53.779932],"type":"Point"}
}
