{
  "type": "Feature",
  "properties": {
    "date:inception_lower":"2005-09-01",
    "date:inception_upper":"2005-09-30",
    "iso:country":"GB",
    "wof:name":"PR4 2BF",
    "wof:placetype":"postalcode"
},
  "geometry": {"coordinates":[-2.885025,53.779932],"type":"Point"}
}