{
  "type": "Feature",
  "properties": {
    "iso:country": "GB",
    "wof:name": "SL6 8ET",
    "wof:placetype": "postalcode"
  },
  "geometry": {"coordinates":[-0.707413,51.53286],"type":"Point"}
}
