{
  "type": "Feature",
  "properties": {
    "iso:country":"GB",
    "wof:name":"L6 0AL",
    "wof:placetype":"postalcode"
},
  "geometry": {"coordinates":[-2.94854163292578,53.42618505094003],"type":"Point"}
}