{
  "type": "Feature",
  "properties": {
    "iso:country":"GB",
    "wof:name":"SY22 5LS",
    "wof:placetype":"postalcode"
},
  "geometry": {"coordinates":[-3.23506965756397,52.74138781568579],"type":"Point"}
}