{
  "type": "Feature",
  "properties": {
    "date:inception_lower": "1980-01-01",
    "date:inception_upper": "1980-01-01",
    "iso:country": "GB",
    "wof:name": "SY22 5LS",
    "wof:placetype": "postalcode"
  },
  "geometry": {"coordinates":[-3.23507,52.741388],"type":"Point"}
}
