{
  "type": "Feature",
  "properties": {
    "iso:country":"GB",
    "wof:name":"AB12 5GE",
    "wof:placetype":"postalcode"
},
  "geometry": {"coordinates":[-2.25743434177037,57.09076424484782],"type":"Point"}
}