{
  "type": "Feature",
  "properties": {
    "iso:country":"GB",
    "wof:name":"EX1 2EZ",
    "wof:placetype":"postalcode"
},
  "geometry": {"coordinates":[-3.50858773489088,50.7227396354378],"type":"Point"}
}