{
  "type": "Feature",
  "properties": {
    "date:inception_lower": "2009-10-01",
    "date:inception_upper": "2009-10-01",
    "iso:country": "GB",
    "wof:name": "EX1 2EZ",
    "wof:placetype": "postalcode"
  },
  "geometry": {"coordinates":[-3.508588,50.72274],"type":"Point"}
}
