{
  "type": "Feature",
  "properties": {
    "date:inception_lower": "2019-04-01",
    "date:inception_upper": "2019-04-01",
    "iso:country": "GB",
    "wof:name": "WN1 3BG",
    "wof:placetype": "postalcode"
  },
  "geometry": {"coordinates":[-2.613071,53.545039],"type":"Point"}
}
