{
  "type": "Feature",
  "properties": {
    "iso:country":"GB",
    "wof:name":"DG7 2DW",
    "wof:placetype":"postalcode"
},
  "geometry": {"coordinates":[-4.17350729821326,54.85728459477283],"type":"Point"}
}