{
  "type": "Feature",
  "properties": {
    "iso:country":"GB",
    "wof:name":"HU12 8UT",
    "wof:placetype":"postalcode"
},
  "geometry": {"coordinates":[-0.19903950104699,53.75586049418387],"type":"Point"}
}