{
  "type": "Feature",
  "properties": {
    "iso:country": "GB",
    "wof:name": "HU12 8UT",
    "wof:placetype": "postalcode"
  },
  "geometry": {"coordinates":[-0.199489,53.755826],"type":"Point"}
}
