{
  "type": "Feature",
  "properties": {
    "iso:country": "GB",
    "wof:name": "EX4 4FN",
    "wof:placetype": "postalcode"
  },
  "geometry": {"coordinates":[-3.537878,50.724631],"type":"Point"}
}
