{
  "type": "Feature",
  "properties": {
    "iso:country": "GB",
    "wof:name": "OX2 0HF",
    "wof:placetype": "postalcode"
  },
  "geometry": {"coordinates":[-1.284615,51.751398],"type":"Point"}
}
