{
  "type": "Feature",
  "properties": {
    "date:inception_lower": "2001-06-01",
    "date:inception_upper": "2001-06-01",
    "iso:country": "GB",
    "wof:name": "OX2 0HF",
    "wof:placetype": "postalcode"
  },
  "geometry": {"coordinates":[-1.284615,51.751398],"type":"Point"}
}
