{
  "type": "Feature",
  "properties": {
    "iso:country":"GB",
    "wof:name":"HU16 5SN",
    "wof:placetype":"postalcode"
},
  "geometry": {"coordinates":[-0.42440194719532,53.78454553699687],"type":"Point"}
}