{
  "type": "Feature",
  "properties": {
    "iso:country":"GB",
    "wof:name":"CF3 1AB",
    "wof:placetype":"postalcode"
},
  "geometry": {"coordinates":[-3.10874779258192,51.5176700450306],"type":"Point"}
}