{
  "type": "Feature",
  "properties": {
    "date:inception_lower": "2012-02-01",
    "date:inception_upper": "2012-02-01",
    "iso:country": "GB",
    "wof:name": "CF3 1AB",
    "wof:placetype": "postalcode"
  },
  "geometry": {"coordinates":[-3.108744,51.517761],"type":"Point"}
}
