{
  "type": "Feature",
  "properties": {
    "iso:country": "GB",
    "wof:name": "WA12 9BP",
    "wof:placetype": "postalcode"
  },
  "geometry": {"coordinates":[-2.644726,53.454135],"type":"Point"}
}
