{
  "type": "Feature",
  "properties": {
    "iso:country":"GB",
    "wof:name":"RM11 3TL",
    "wof:placetype":"postalcode"
},
  "geometry": {"coordinates":[0.23461241435985,51.56033479241231],"type":"Point"}
}