{
  "type": "Feature",
  "properties": {
    "date:inception_lower": "1980-01-01",
    "date:inception_upper": "1980-01-01",
    "iso:country": "GB",
    "wof:name": "RM11 3TL",
    "wof:placetype": "postalcode"
  },
  "geometry": {"coordinates":[0.234702,51.560443],"type":"Point"}
}
