{
  "type": "Feature",
  "properties": {
    "iso:country":"GB",
    "wof:name":"SP10 4DZ",
    "wof:placetype":"postalcode"
},
  "geometry": {"coordinates":[-1.49602831611627,51.2232061812305],"type":"Point"}
}