{
  "type": "Feature",
  "properties": {
    "iso:country": "GB",
    "wof:name": "SP10 4DZ",
    "wof:placetype": "postalcode"
  },
  "geometry": {"coordinates":[-1.496028,51.223206],"type":"Point"}
}
