{
  "type": "Feature",
  "properties": {
    "date:inception_lower":"2004-02-01",
    "date:inception_upper":"2004-02-29",
    "iso:country":"GB",
    "wof:name":"NP11 3AA",
    "wof:placetype":"postalcode"
},
  "geometry": {"coordinates":[-3.160869,51.695651],"type":"Point"}
}