{
  "type": "Feature",
  "properties": {
    "iso:country":"GB",
    "wof:name":"HA9 8AB",
    "wof:placetype":"postalcode"
},
  "geometry": {"coordinates":[-0.28812064367885,51.55396501007513],"type":"Point"}
}