{
  "type": "Feature",
  "properties": {
    "date:inception_lower":"1998-06-01",
    "date:inception_upper":"1998-06-30",
    "iso:country":"GB",
    "wof:name":"YO8 5XB",
    "wof:placetype":"postalcode"
},
  "geometry": {"coordinates":[-1.037705,53.804302],"type":"Point"}
}