{
  "type": "Feature",
  "properties": {
    "iso:country":"GB",
    "wof:name":"YO8 5XB",
    "wof:placetype":"postalcode"
},
  "geometry": {"coordinates":[-1.03770536057415,53.80430178415098],"type":"Point"}
}