{
  "type": "Feature",
  "properties": {
    "iso:country":"GB",
    "wof:name":"CO7 7LH",
    "wof:placetype":"postalcode"
},
  "geometry": {"coordinates":[0.98616913757372,51.93336800162754],"type":"Point"}
}