{
  "type": "Feature",
  "properties": {
    "iso:country":"GB",
    "wof:name":"N2 8DA",
    "wof:placetype":"postalcode"
},
  "geometry": {"coordinates":[-0.16763847579502,51.59145105845495],"type":"Point"}
}