{
  "type": "Feature",
  "properties": {
    "iso:country":"GB",
    "wof:name":"ST16 2BS",
    "wof:placetype":"postalcode"
},
  "geometry": {"coordinates":[-2.11730454913415,52.80416286449605],"type":"Point"}
}