{
  "type": "Feature",
  "properties": {
    "iso:country":"GB",
    "wof:name":"M22 9PP",
    "wof:placetype":"postalcode"
},
  "geometry": {"coordinates":[-2.2629873587973,53.38228457821181],"type":"Point"}
}