{
  "type": "Feature",
  "properties": {
    "date:inception_lower": "2010-12-01",
    "date:inception_upper": "2010-12-01",
    "iso:country": "GB",
    "wof:name": "WV14 0RZ",
    "wof:placetype": "postalcode"
  },
  "geometry": {"coordinates":[-2.088421,52.554338],"type":"Point"}
}
