{
  "type": "Feature",
  "properties": {
    "iso:country":"GB",
    "wof:name":"TR16 5QU",
    "wof:placetype":"postalcode"
},
  "geometry": {"coordinates":[-5.17731919847708,50.23199202066191],"type":"Point"}
}