{
  "type": "Feature",
  "properties": {
    "iso:country":"GB",
    "wof:name":"TS29 6HE",
    "wof:placetype":"postalcode"
},
  "geometry": {"coordinates":[-1.42640088796765,54.71142587196312],"type":"Point"}
}