{
  "type": "Feature",
  "properties": {
    "iso:country":"GB",
    "wof:name":"CH6 5NH",
    "wof:placetype":"postalcode"
},
  "geometry": {"coordinates":[-3.13654666218555,53.24392428366082],"type":"Point"}
}