{
  "type": "Feature",
  "properties": {
    "date:inception_lower":"1980-01-01",
    "date:inception_upper":"1980-01-31",
    "iso:country":"GB",
    "wof:name":"CH6 5NH",
    "wof:placetype":"postalcode"
},
  "geometry": {"coordinates":[-3.136547,53.243924],"type":"Point"}
}