{
  "type": "Feature",
  "properties": {
    "iso:country": "GB",
    "wof:name": "CH6 5NH",
    "wof:placetype": "postalcode"
  },
  "geometry": {"coordinates":[-3.136547,53.243924],"type":"Point"}
}
