{
  "type": "Feature",
  "properties": {
    "iso:country":"GB",
    "wof:name":"LS25 7JX",
    "wof:placetype":"postalcode"
},
  "geometry": {"coordinates":[-1.37311499009326,53.76565411663056],"type":"Point"}
}