{
  "type": "Feature",
  "properties": {
    "iso:country": "GB",
    "wof:name": "LS25 7JX",
    "wof:placetype": "postalcode"
  },
  "geometry": {"coordinates":[-1.373115,53.765654],"type":"Point"}
}
