{
  "type": "Feature",
  "properties": {
    "date:inception_lower":"1996-06-01",
    "date:inception_upper":"1996-06-30",
    "iso:country":"GB",
    "wof:name":"DH9 8TT",
    "wof:placetype":"postalcode"
},
  "geometry": {"coordinates":[-1.736735,54.864242],"type":"Point"}
}