{
  "type": "Feature",
  "properties": {
    "iso:country":"GB",
    "wof:name":"DH9 8TT",
    "wof:placetype":"postalcode"
},
  "geometry": {"coordinates":[-1.7367346402139,54.86424237123095],"type":"Point"}
}