{
  "type": "Feature",
  "properties": {
    "iso:country":"GB",
    "wof:name":"BA14 6AY",
    "wof:placetype":"postalcode"
},
  "geometry": {"coordinates":[-2.17030222600406,51.2946079036528],"type":"Point"}
}