{
  "type": "Feature",
  "properties": {
    "iso:country":"GB",
    "wof:name":"NG15 0ZU",
    "wof:placetype":"postalcode"
},
  "geometry": {"coordinates":[-1.20434869221693,53.03793530223546],"type":"Point"}
}