{
  "type": "Feature",
  "properties": {
    "iso:country":"GB",
    "wof:name":"HP13 7LD",
    "wof:placetype":"postalcode"
},
  "geometry": {"coordinates":[-0.73400148090199,51.63250106396535],"type":"Point"}
}