{
  "type": "Feature",
  "properties": {
    "iso:country":"GB",
    "wof:name":"BH22 8HU",
    "wof:placetype":"postalcode"
},
  "geometry": {"coordinates":[-1.892027664113,50.7967322075568],"type":"Point"}
}