{
  "type": "Feature",
  "properties": {
    "iso:country":"GB",
    "wof:name":"DG2 9DB",
    "wof:placetype":"postalcode"
},
  "geometry": {"coordinates":[-3.62232485835948,55.07279211406932],"type":"Point"}
}