{
  "type": "Feature",
  "properties": {
    "iso:country":"GB",
    "wof:name":"SS7 5SJ",
    "wof:placetype":"postalcode"
},
  "geometry": {"coordinates":[0.55562701637026,51.56684744539386],"type":"Point"}
}