{
  "type": "Feature",
  "properties": {
    "iso:country":"GB",
    "wof:name":"OX11 7XS",
    "wof:placetype":"postalcode"
},
  "geometry": {"coordinates":[-1.24416517915625,51.61872947986559],"type":"Point"}
}