{
  "type": "Feature",
  "properties": {
    "date:inception_lower":"1997-12-01",
    "date:inception_upper":"1997-12-31",
    "iso:country":"GB",
    "wof:name":"OX11 7XS",
    "wof:placetype":"postalcode"
},
  "geometry": {"coordinates":[-1.244165,51.618729],"type":"Point"}
}