{
  "type": "Feature",
  "properties": {
    "iso:country":"GB",
    "wof:name":"WN6 8DY",
    "wof:placetype":"postalcode"
},
  "geometry": {"coordinates":[-2.7106240539035,53.57303100692921],"type":"Point"}
}