{
  "type": "Feature",
  "properties": {
    "date:inception_lower":"1983-03-01",
    "date:inception_upper":"1983-03-31",
    "iso:country":"GB",
    "wof:name":"WN6 8DY",
    "wof:placetype":"postalcode"
},
  "geometry": {"coordinates":[-2.710624,53.573031],"type":"Point"}
}