{
  "type": "Feature",
  "properties": {
    "iso:country":"GB",
    "wof:name":"CR2 8QL",
    "wof:placetype":"postalcode"
},
  "geometry": {"coordinates":[-0.05530018543786,51.33454810964852],"type":"Point"}
}