{
  "type": "Feature",
  "properties": {
    "date:inception_lower": "1996-06-01",
    "date:inception_upper": "1996-06-01",
    "iso:country": "GB",
    "wof:name": "AB10 7PP",
    "wof:placetype": "postalcode"
  },
  "geometry": {"coordinates":[-2.135359,57.13155],"type":"Point"}
}
