{
  "type": "Feature",
  "properties": {
    "iso:country":"GB",
    "wof:name":"DA4 0AL",
    "wof:placetype":"postalcode"
},
  "geometry": {"coordinates":[0.21386983234782,51.36858330249778],"type":"Point"}
}