{
  "type": "Feature",
  "properties": {
    "iso:country":"GB",
    "wof:name":"DA11 7JH",
    "wof:placetype":"postalcode"
},
  "geometry": {"coordinates":[0.35625302882465,51.42345256150387],"type":"Point"}
}