{
  "type": "Feature",
  "properties": {
    "iso:country":"GB",
    "wof:name":"CO9 2EE",
    "wof:placetype":"postalcode"
},
  "geometry": {"coordinates":[0.64480853830617,51.9456649061857],"type":"Point"}
}