{
  "type": "Feature",
  "properties": {
    "iso:country": "GB",
    "wof:name": "CO9 2EE",
    "wof:placetype": "postalcode"
  },
  "geometry": {"coordinates":[0.644809,51.945665],"type":"Point"}
}
