{
  "type": "Feature",
  "properties": {
    "date:inception_lower": "1980-01-01",
    "date:inception_upper": "1980-01-01",
    "iso:country": "GB",
    "wof:name": "TS5 4HP",
    "wof:placetype": "postalcode"
  },
  "geometry": {"coordinates":[-1.265062,54.556393],"type":"Point"}
}
