{
  "type": "Feature",
  "properties": {
    "iso:country":"GB",
    "wof:name":"SW20 0HU",
    "wof:placetype":"postalcode"
},
  "geometry": {"coordinates":[-0.2352593029547,51.41878087160676],"type":"Point"}
}