{
  "type": "Feature",
  "properties": {
    "iso:country":"GB",
    "wof:name":"SA69 9AX",
    "wof:placetype":"postalcode"
},
  "geometry": {"coordinates":[-4.68872175404957,51.72232558559036],"type":"Point"}
}