{
  "type": "Feature",
  "properties": {
    "iso:country": "GB",
    "wof:name": "NE42 6PP",
    "wof:placetype": "postalcode"
  },
  "geometry": {"coordinates":[-1.867243,54.960024],"type":"Point"}
}
