{
  "type": "Feature",
  "properties": {
    "iso:country":"GB",
    "wof:name":"NE63 9SE",
    "wof:placetype":"postalcode"
},
  "geometry": {"coordinates":[-1.54160698781466,55.17891773307072],"type":"Point"}
}