{
  "type": "Feature",
  "properties": {
    "iso:country":"GB",
    "wof:name":"B74 2DZ",
    "wof:placetype":"postalcode"
},
  "geometry": {"coordinates":[-1.89299832589764,52.57204251312666],"type":"Point"}
}