{
  "type": "Feature",
  "properties": {
    "iso:country": "GB",
    "wof:name": "CH1 6BG",
    "wof:placetype": "postalcode"
  },
  "geometry": {"coordinates":[-2.958288,53.221607],"type":"Point"}
}
