{
  "type": "Feature",
  "properties": {
    "date:inception_lower":"1980-01-01",
    "date:inception_upper":"1980-01-31",
    "iso:country":"GB",
    "wof:name":"CH1 6BG",
    "wof:placetype":"postalcode"
},
  "geometry": {"coordinates":[-2.958288,53.221607],"type":"Point"}
}