{
  "type": "Feature",
  "properties": {
    "date:inception_lower": "1980-01-01",
    "date:inception_upper": "1980-01-01",
    "iso:country": "GB",
    "wof:name": "SG2 8NZ",
    "wof:placetype": "postalcode"
  },
  "geometry": {"coordinates":[-0.17413,51.886918],"type":"Point"}
}
