{
  "type": "Feature",
  "properties": {
    "iso:country":"GB",
    "wof:name":"SG2 8NZ",
    "wof:placetype":"postalcode"
},
  "geometry": {"coordinates":[-0.17413005996397,51.88691754921943],"type":"Point"}
}