{
  "type": "Feature",
  "properties": {
    "iso:country": "GB",
    "wof:name": "SG2 8NZ",
    "wof:placetype": "postalcode"
  },
  "geometry": {"coordinates":[-0.17413,51.886918],"type":"Point"}
}
