{
  "type": "Feature",
  "properties": {
    "iso:country": "GB",
    "wof:name": "CF24 2RL",
    "wof:placetype": "postalcode"
  },
  "geometry": {"coordinates":[-3.136057,51.49153],"type":"Point"}
}
