{
  "type": "Feature",
  "properties": {
    "date:inception_lower": "1999-06-01",
    "date:inception_upper": "1999-06-01",
    "iso:country": "GB",
    "wof:name": "CF24 2RL",
    "wof:placetype": "postalcode"
  },
  "geometry": {"coordinates":[-3.136057,51.49153],"type":"Point"}
}
