{
  "type": "Feature",
  "properties": {
    "date:inception_lower": "2002-06-01",
    "date:inception_upper": "2002-06-01",
    "iso:country": "GB",
    "wof:name": "W13 0HT",
    "wof:placetype": "postalcode"
  },
  "geometry": {"coordinates":[-0.330789,51.52834],"type":"Point"}
}
