{
  "type": "Feature",
  "properties": {
    "iso:country":"GB",
    "wof:name":"W13 0HT",
    "wof:placetype":"postalcode"
},
  "geometry": {"coordinates":[-0.33078888076293,51.52834034348115],"type":"Point"}
}