{
  "type": "Feature",
  "properties": {
    "date:inception_lower":"1980-01-01",
    "date:inception_upper":"1980-01-31",
    "iso:country":"GB",
    "wof:name":"WF10 2EF",
    "wof:placetype":"postalcode"
},
  "geometry": {"coordinates":[-1.378225,53.750383],"type":"Point"}
}