{
  "type": "Feature",
  "properties": {
    "iso:country":"GB",
    "wof:name":"EN6 1DA",
    "wof:placetype":"postalcode"
},
  "geometry": {"coordinates":[-0.18757024001067,51.70285101588737],"type":"Point"}
}