{
  "type": "Feature",
  "properties": {
    "iso:country":"GB",
    "wof:name":"RH12 4UP",
    "wof:placetype":"postalcode"
},
  "geometry": {"coordinates":[-0.29258422615929,51.07836556308678],"type":"Point"}
}