{
  "type": "Feature",
  "properties": {
    "iso:country": "GB",
    "wof:name": "NE11 0HE",
    "wof:placetype": "postalcode"
  },
  "geometry": {"coordinates":[-1.630533,54.928443],"type":"Point"}
}
