{
  "type": "Feature",
  "properties": {
    "iso:country":"GB",
    "wof:name":"CH63 3JW",
    "wof:placetype":"postalcode"
},
  "geometry": {"coordinates":[-2.99828392362605,53.3460114095182],"type":"Point"}
}