{
  "type": "Feature",
  "properties": {
    "iso:country": "GB",
    "wof:name": "CH8 9DN",
    "wof:placetype": "postalcode"
  },
  "geometry": {"coordinates":[-3.218412,53.293904],"type":"Point"}
}
