{
  "type": "Feature",
  "properties": {
    "iso:country":"GB",
    "wof:name":"CH8 9DN",
    "wof:placetype":"postalcode"
},
  "geometry": {"coordinates":[-3.21754034837815,53.29334774216625],"type":"Point"}
}