{
  "type": "Feature",
  "properties": {
    "date:inception_lower": "1980-01-01",
    "date:inception_upper": "1980-01-01",
    "iso:country": "GB",
    "wof:name": "EX9 6AF",
    "wof:placetype": "postalcode"
  },
  "geometry": {"coordinates":[-3.34081,50.630604],"type":"Point"}
}
