{
  "type": "Feature",
  "properties": {
    "iso:country":"GB",
    "wof:name":"DE75 7PF",
    "wof:placetype":"postalcode"
},
  "geometry": {"coordinates":[-1.33578438222792,53.01266356270182],"type":"Point"}
}