{
  "type": "Feature",
  "properties": {
    "iso:country": "GB",
    "wof:name": "DE75 7PF",
    "wof:placetype": "postalcode"
  },
  "geometry": {"coordinates":[-1.335784,53.012664],"type":"Point"}
}
