{
  "type": "Feature",
  "properties": {
    "date:inception_lower": "1998-06-01",
    "date:inception_upper": "1998-06-01",
    "iso:country": "GB",
    "wof:name": "DE75 7PF",
    "wof:placetype": "postalcode"
  },
  "geometry": {"coordinates":[-1.335784,53.012664],"type":"Point"}
}
