{
  "type": "Feature",
  "properties": {
    "iso:country": "GB",
    "wof:name": "LL28 5UA",
    "wof:placetype": "postalcode"
  },
  "geometry": {"coordinates":[-3.793662,53.217946],"type":"Point"}
}
