{
  "type": "Feature",
  "properties": {
    "date:inception_lower": "1980-01-01",
    "date:inception_upper": "1980-01-01",
    "iso:country": "GB",
    "wof:name": "LL28 5UA",
    "wof:placetype": "postalcode"
  },
  "geometry": {"coordinates":[-3.793662,53.217946],"type":"Point"}
}
