{
  "type": "Feature",
  "properties": {
    "iso:country": "GB",
    "wof:name": "RG12 0TU",
    "wof:placetype": "postalcode"
  },
  "geometry": {"coordinates":[-0.7389,51.393953],"type":"Point"}
}
