{
  "type": "Feature",
  "properties": {
    "iso:country":"GB",
    "wof:name":"RG12 0TU",
    "wof:placetype":"postalcode"
},
  "geometry": {"coordinates":[-0.73890016056112,51.3939528582858],"type":"Point"}
}