{
  "type": "Feature",
  "properties": {
    "date:inception_lower": "1995-07-01",
    "date:inception_upper": "1995-07-01",
    "iso:country": "GB",
    "wof:name": "RG12 0TU",
    "wof:placetype": "postalcode"
  },
  "geometry": {"coordinates":[-0.7389,51.393953],"type":"Point"}
}
