{
  "type": "Feature",
  "properties": {
    "iso:country":"GB",
    "wof:name":"OL9 0NW",
    "wof:placetype":"postalcode"
},
  "geometry": {"coordinates":[-2.16415711735398,53.54997066397049],"type":"Point"}
}