{
  "type": "Feature",
  "properties": {
    "date:inception_lower":"1997-06-01",
    "date:inception_upper":"1997-06-30",
    "iso:country":"GB",
    "wof:name":"CV36 5BD",
    "wof:placetype":"postalcode"
},
  "geometry": {"coordinates":[-1.612775,52.038434],"type":"Point"}
}