{
  "type": "Feature",
  "properties": {
    "iso:country":"GB",
    "wof:name":"CV36 5BD",
    "wof:placetype":"postalcode"
},
  "geometry": {"coordinates":[-1.61277522640362,52.03843381395993],"type":"Point"}
}