{
  "type": "Feature",
  "properties": {
    "date:inception_lower": "1992-08-01",
    "date:inception_upper": "1992-08-01",
    "iso:country": "GB",
    "wof:name": "LL11 4QA",
    "wof:placetype": "postalcode"
  },
  "geometry": {"coordinates":[-3.029152,53.073608],"type":"Point"}
}
