{
  "type": "Feature",
  "properties": {
    "iso:country":"GB",
    "wof:name":"SG1 5RG",
    "wof:placetype":"postalcode"
},
  "geometry": {"coordinates":[-0.16323989724361,51.91593589895662],"type":"Point"}
}