{
  "type": "Feature",
  "properties": {
    "date:inception_lower": "1994-05-01",
    "date:inception_upper": "1994-05-01",
    "iso:country": "GB",
    "wof:name": "SG1 5RG",
    "wof:placetype": "postalcode"
  },
  "geometry": {"coordinates":[-0.16324,51.915936],"type":"Point"}
}
