{
  "type": "Feature",
  "properties": {
    "iso:country":"GB",
    "wof:name":"DE15 9FN",
    "wof:placetype":"postalcode"
},
  "geometry": {"coordinates":[-1.61247931875035,52.79757531997813],"type":"Point"}
}