{
  "type": "Feature",
  "properties": {
    "date:inception_lower": "1980-01-01",
    "date:inception_upper": "1980-01-01",
    "iso:country": "GB",
    "wof:name": "DL8 5PH",
    "wof:placetype": "postalcode"
  },
  "geometry": {"coordinates":[-1.801623,54.301129],"type":"Point"}
}
