{
  "type": "Feature",
  "properties": {
    "iso:country":"GB",
    "wof:name":"DL8 5PH",
    "wof:placetype":"postalcode"
},
  "geometry": {"coordinates":[-1.80002120301251,54.30075608405613],"type":"Point"}
}