{
  "type": "Feature",
  "properties": {
    "iso:country": "GB",
    "wof:name": "DL8 5PH",
    "wof:placetype": "postalcode"
  },
  "geometry": {"coordinates":[-1.80193,54.301183],"type":"Point"}
}
