{
  "type": "Feature",
  "properties": {
    "iso:country":"GB",
    "wof:name":"HP20 2EB",
    "wof:placetype":"postalcode"
},
  "geometry": {"coordinates":[-0.81202953485044,51.82678763559591],"type":"Point"}
}