{
  "type": "Feature",
  "properties": {
    "date:inception_lower": "2003-05-01",
    "date:inception_upper": "2003-05-01",
    "iso:country": "GB",
    "wof:name": "NN4 8ZG",
    "wof:placetype": "postalcode"
  },
  "geometry": {"coordinates":[-0.898245,52.24527],"type":"Point"}
}
