{
  "type": "Feature",
  "properties": {
    "iso:country":"GB",
    "wof:name":"DN4 9HH",
    "wof:placetype":"postalcode"
},
  "geometry": {"coordinates":[-1.16507232373516,53.49643928595938],"type":"Point"}
}