{
  "type": "Feature",
  "properties": {
    "iso:country":"GB",
    "wof:name":"TN31 6XR",
    "wof:placetype":"postalcode"
},
  "geometry": {"coordinates":[0.64532812964418,50.9528412558557],"type":"Point"}
}