{
  "type": "Feature",
  "properties": {
    "iso:country":"GB",
    "wof:name":"PL32 9RF",
    "wof:placetype":"postalcode"
},
  "geometry": {"coordinates":[-4.69505206665526,50.61205673243983],"type":"Point"}
}