{
  "type": "Feature",
  "properties": {
    "iso:country":"GB",
    "wof:name":"S66 7BH",
    "wof:placetype":"postalcode"
},
  "geometry": {"coordinates":[-1.19347118932563,53.42972219053884],"type":"Point"}
}