{
  "type": "Feature",
  "properties": {
    "iso:country":"GB",
    "wof:name":"CB8 7DG",
    "wof:placetype":"postalcode"
},
  "geometry": {"coordinates":[0.41650722300454,52.25469152749844],"type":"Point"}
}