{
  "type": "Feature",
  "properties": {
    "iso:country":"GB",
    "wof:name":"OL3 7AJ",
    "wof:placetype":"postalcode"
},
  "geometry": {"coordinates":[-2.00995116395807,53.54152634307268],"type":"Point"}
}