{
  "type": "Feature",
  "properties": {
    "date:inception_lower": "1980-01-01",
    "date:inception_upper": "1980-01-01",
    "iso:country": "GB",
    "wof:name": "OL3 7AJ",
    "wof:placetype": "postalcode"
  },
  "geometry": {"coordinates":[-2.009919,53.54157],"type":"Point"}
}
