{
  "type": "Feature",
  "properties": {
    "date:inception_lower": "1980-01-01",
    "date:inception_upper": "1980-01-01",
    "iso:country": "GB",
    "wof:name": "PE13 1JE",
    "wof:placetype": "postalcode"
  },
  "geometry": {"coordinates":[0.156895,52.664481],"type":"Point"}
}
