{
  "type": "Feature",
  "properties": {
    "date:inception_lower": "1980-01-01",
    "date:inception_upper": "1980-01-01",
    "iso:country": "GB",
    "wof:name": "PE13 1JE",
    "wof:placetype": "postalcode"
  },
  "geometry": {"coordinates":[0.15687,52.664562],"type":"Point"}
}
