{
  "type": "Feature",
  "properties": {
    "iso:country":"GB",
    "wof:name":"PE13 1JE",
    "wof:placetype":"postalcode"
},
  "geometry": {"coordinates":[0.15687981746576,52.66446168911944],"type":"Point"}
}