{
  "type": "Feature",
  "properties": {
    "iso:country":"GB",
    "wof:name":"HA3 5ES",
    "wof:placetype":"postalcode"
},
  "geometry": {"coordinates":[-0.33996178971035,51.60350155223973],"type":"Point"}
}