{
  "type": "Feature",
  "properties": {
    "iso:country":"GB",
    "wof:name":"SS9 5NH",
    "wof:placetype":"postalcode"
},
  "geometry": {"coordinates":[0.64982199136903,51.56645707440276],"type":"Point"}
}