{
  "type": "Feature",
  "properties": {
    "iso:country":"GB",
    "wof:name":"HP21 8JD",
    "wof:placetype":"postalcode"
},
  "geometry": {"coordinates":[-0.8138193402881,51.80725833450003],"type":"Point"}
}