{
  "type": "Feature",
  "properties": {
    "iso:country": "GB",
    "wof:name": "HP21 8JD",
    "wof:placetype": "postalcode"
  },
  "geometry": {"coordinates":[-0.813819,51.807258],"type":"Point"}
}
