{
  "type": "Feature",
  "properties": {
    "iso:country":"GB",
    "wof:name":"AB42 5RQ",
    "wof:placetype":"postalcode"
},
  "geometry": {"coordinates":[-2.14188287822888,57.51415502397862],"type":"Point"}
}