{
  "type": "Feature",
  "properties": {
    "date:inception_lower": "1996-06-01",
    "date:inception_upper": "1996-06-01",
    "iso:country": "GB",
    "wof:name": "AB42 5RQ",
    "wof:placetype": "postalcode"
  },
  "geometry": {"coordinates":[-2.141883,57.514155],"type":"Point"}
}
