{
  "type": "Feature",
  "properties": {
    "iso:country":"GB",
    "wof:name":"KA10 6JD",
    "wof:placetype":"postalcode"
},
  "geometry": {"coordinates":[-4.65726432418286,55.54232659238242],"type":"Point"}
}