{
  "type": "Feature",
  "properties": {
    "iso:country":"GB",
    "wof:name":"OX4 4TQ",
    "wof:placetype":"postalcode"
},
  "geometry": {"coordinates":[-1.23456637573032,51.72304829719594],"type":"Point"}
}