{
  "type": "Feature",
  "properties": {
    "iso:country":"GB",
    "wof:name":"RH1 6HH",
    "wof:placetype":"postalcode"
},
  "geometry": {"coordinates":[-0.17120785417631,51.22592987933773],"type":"Point"}
}