{
  "type": "Feature",
  "properties": {
    "iso:country":"GB",
    "wof:name":"BL6 7JJ",
    "wof:placetype":"postalcode"
},
  "geometry": {"coordinates":[-2.55292371446113,53.6021865923809],"type":"Point"}
}