{
  "type": "Feature",
  "properties": {
    "iso:country": "GB",
    "wof:name": "BL6 7JJ",
    "wof:placetype": "postalcode"
  },
  "geometry": {"coordinates":[-2.552863,53.602169],"type":"Point"}
}
