{
  "type": "Feature",
  "properties": {
    "iso:country":"GB",
    "wof:name":"DN15 8LZ",
    "wof:placetype":"postalcode"
},
  "geometry": {"coordinates":[-0.66540842184906,53.59717625621648],"type":"Point"}
}