{
  "type": "Feature",
  "properties": {
    "iso:country":"GB",
    "wof:name":"DY1 3TG",
    "wof:placetype":"postalcode"
},
  "geometry": {"coordinates":[-2.10594971280855,52.52669815179864],"type":"Point"}
}