{
  "type": "Feature",
  "properties": {
    "date:inception_lower":"1992-08-01",
    "date:inception_upper":"1992-08-31",
    "iso:country":"GB",
    "wof:name":"DE24 9DB",
    "wof:placetype":"postalcode"
},
  "geometry": {"coordinates":[-1.4484,52.889069],"type":"Point"}
}