{
  "type": "Feature",
  "properties": {
    "iso:country": "GB",
    "wof:name": "DE24 9DB",
    "wof:placetype": "postalcode"
  },
  "geometry": {"coordinates":[-1.448425,52.889123],"type":"Point"}
}
