{
  "type": "Feature",
  "properties": {
    "iso:country":"GB",
    "wof:name":"DE24 9DB",
    "wof:placetype":"postalcode"
},
  "geometry": {"coordinates":[-1.44840036396338,52.88906901848794],"type":"Point"}
}