{
  "type": "Feature",
  "properties": {
    "date:inception_lower": "2009-05-01",
    "date:inception_upper": "2009-05-01",
    "iso:country": "GB",
    "wof:name": "AL5 1DZ",
    "wof:placetype": "postalcode"
  },
  "geometry": {"coordinates":[-0.345518,51.809225],"type":"Point"}
}
