{
  "type": "Feature",
  "properties": {
    "date:inception_lower": "1980-01-01",
    "date:inception_upper": "1980-01-01",
    "iso:country": "GB",
    "wof:name": "DL12 9UR",
    "wof:placetype": "postalcode"
  },
  "geometry": {"coordinates":[-2.04638,54.573263],"type":"Point"}
}
