{
  "type": "Feature",
  "properties": {
    "iso:country":"GB",
    "wof:name":"DL12 9UR",
    "wof:placetype":"postalcode"
},
  "geometry": {"coordinates":[-2.04637274609894,54.57325430084192],"type":"Point"}
}