{
  "type": "Feature",
  "properties": {
    "date:inception_lower": "1980-01-01",
    "date:inception_upper": "1980-01-01",
    "iso:country": "GB",
    "wof:name": "SY8 3HE",
    "wof:placetype": "postalcode"
  },
  "geometry": {"coordinates":[-2.655612,52.386197],"type":"Point"}
}
