{
  "type": "Feature",
  "properties": {
    "iso:country":"GB",
    "wof:name":"SY8 3HE",
    "wof:placetype":"postalcode"
},
  "geometry": {"coordinates":[-2.65614697913705,52.38844630978809],"type":"Point"}
}