{
  "type": "Feature",
  "properties": {
    "date:inception_lower":"1980-01-01",
    "date:inception_upper":"1980-01-31",
    "iso:country":"GB",
    "wof:name":"TR1 1HS",
    "wof:placetype":"postalcode"
},
  "geometry": {"coordinates":[-5.047546,50.266839],"type":"Point"}
}