{
  "type": "Feature",
  "properties": {
    "iso:country": "GB",
    "wof:name": "TR1 1HS",
    "wof:placetype": "postalcode"
  },
  "geometry": {"coordinates":[-5.047546,50.266839],"type":"Point"}
}
