{
  "type": "Feature",
  "properties": {
    "date:inception_lower":"1980-01-01",
    "date:inception_upper":"1980-01-31",
    "iso:country":"GB",
    "wof:name":"EN2 9EG",
    "wof:placetype":"postalcode"
},
  "geometry": {"coordinates":[-0.070254,51.667234],"type":"Point"}
}