{
  "type": "Feature",
  "properties": {
    "iso:country":"GB",
    "wof:name":"EN2 9EG",
    "wof:placetype":"postalcode"
},
  "geometry": {"coordinates":[-0.07025360149369,51.66723409200181],"type":"Point"}
}