{
  "type": "Feature",
  "properties": {
    "iso:country":"GB",
    "wof:name":"CV2 2HN",
    "wof:placetype":"postalcode"
},
  "geometry": {"coordinates":[-1.4383297640482,52.428150837157],"type":"Point"}
}