{
  "type": "Feature",
  "properties": {
    "iso:country": "GB",
    "wof:name": "CV2 2HN",
    "wof:placetype": "postalcode"
  },
  "geometry": {"coordinates":[-1.43833,52.428151],"type":"Point"}
}
