{
  "type": "Feature",
  "properties": {
    "date:inception_lower": "1980-01-01",
    "date:inception_upper": "1980-01-01",
    "iso:country": "GB",
    "wof:name": "G77 5LA",
    "wof:placetype": "postalcode"
  },
  "geometry": {"coordinates":[-4.315556,55.770284],"type":"Point"}
}
