{
  "type": "Feature",
  "properties": {
    "iso:country":"GB",
    "wof:name":"G77 5LA",
    "wof:placetype":"postalcode"
},
  "geometry": {"coordinates":[-4.31555557686225,55.77028439100559],"type":"Point"}
}