{
  "type": "Feature",
  "properties": {
    "iso:country":"GB",
    "wof:name":"BD23 5NG",
    "wof:placetype":"postalcode"
},
  "geometry": {"coordinates":[-2.00033129622851,54.07313653118885],"type":"Point"}
}