{
  "type": "Feature",
  "properties": {
    "iso:country": "GB",
    "wof:name": "BD23 5NG",
    "wof:placetype": "postalcode"
  },
  "geometry": {"coordinates":[-2.000331,54.073137],"type":"Point"}
}
