{
  "type": "Feature",
  "properties": {
    "date:inception_lower": "1986-04-01",
    "date:inception_upper": "1986-04-01",
    "iso:country": "GB",
    "wof:name": "BD23 5NG",
    "wof:placetype": "postalcode"
  },
  "geometry": {"coordinates":[-2.000331,54.073137],"type":"Point"}
}
