{
  "type": "Feature",
  "properties": {
    "iso:country":"GB",
    "wof:name":"PO6 1SQ",
    "wof:placetype":"postalcode"
},
  "geometry": {"coordinates":[-1.0313537305301,50.84255565556463],"type":"Point"}
}