{
  "type": "Feature",
  "properties": {
    "date:inception_lower": "1980-01-01",
    "date:inception_upper": "1980-01-01",
    "iso:country": "GB",
    "wof:name": "CV3 6JH",
    "wof:placetype": "postalcode"
  },
  "geometry": {"coordinates":[-1.519974,52.377437],"type":"Point"}
}
