{
  "type": "Feature",
  "properties": {
    "iso:country":"GB",
    "wof:name":"LL39 1AZ",
    "wof:placetype":"postalcode"
},
  "geometry": {"coordinates":[-4.02803100761956,52.70183844586089],"type":"Point"}
}