{
  "type": "Feature",
  "properties": {
    "iso:country": "GB",
    "wof:name": "LL39 1AZ",
    "wof:placetype": "postalcode"
  },
  "geometry": {"coordinates":[-4.02804,52.701854],"type":"Point"}
}
