{
  "type": "Feature",
  "properties": {
    "iso:country":"GB",
    "wof:name":"PO13 9JY",
    "wof:placetype":"postalcode"
},
  "geometry": {"coordinates":[-1.20069975587064,50.80997163863213],"type":"Point"}
}