{
  "type": "Feature",
  "properties": {
    "iso:country":"GB",
    "wof:name":"KA27 8FE",
    "wof:placetype":"postalcode"
},
  "geometry": {"coordinates":[-5.16353861628965,55.59387881741893],"type":"Point"}
}