{
  "type": "Feature",
  "properties": {
    "date:inception_lower":"2014-08-01",
    "date:inception_upper":"2014-08-31",
    "iso:country":"GB",
    "wof:name":"KA27 8FE",
    "wof:placetype":"postalcode"
},
  "geometry": {"coordinates":[-5.163539,55.593879],"type":"Point"}
}