{
  "type": "Feature",
  "properties": {
    "iso:country":"GB",
    "wof:name":"BD4 6QB",
    "wof:placetype":"postalcode"
},
  "geometry": {"coordinates":[-1.74218258603573,53.75977068452961],"type":"Point"}
}