{
  "type": "Feature",
  "properties": {
    "iso:country":"GB",
    "wof:name":"E9 5AP",
    "wof:placetype":"postalcode"
},
  "geometry": {"coordinates":[-0.03740477600256,51.54485029475068],"type":"Point"}
}