{
  "type": "Feature",
  "properties": {
    "iso:country": "GB",
    "wof:name": "WF5 8LN",
    "wof:placetype": "postalcode"
  },
  "geometry": {"coordinates":[-1.581447,53.672645],"type":"Point"}
}
