{
  "type": "Feature",
  "properties": {
    "date:inception_lower":"1993-01-01",
    "date:inception_upper":"1993-01-31",
    "iso:country":"GB",
    "wof:name":"LL22 9YJ",
    "wof:placetype":"postalcode"
},
  "geometry": {"coordinates":[-3.565268,53.29516],"type":"Point"}
}