{
  "type": "Feature",
  "properties": {
    "iso:country":"GB",
    "wof:name":"LL22 9YJ",
    "wof:placetype":"postalcode"
},
  "geometry": {"coordinates":[-3.56526847875197,53.29516008294551],"type":"Point"}
}