{
  "type": "Feature",
  "properties": {
    "date:inception_lower":"1982-03-01",
    "date:inception_upper":"1982-03-31",
    "iso:country":"GB",
    "wof:name":"PE2 8HP",
    "wof:placetype":"postalcode"
},
  "geometry": {"coordinates":[-0.227272,52.55742],"type":"Point"}
}