{
  "type": "Feature",
  "properties": {
    "iso:country":"GB",
    "wof:name":"DE11 0DP",
    "wof:placetype":"postalcode"
},
  "geometry": {"coordinates":[-1.55561645127732,52.78737976508231],"type":"Point"}
}