{
  "type": "Feature",
  "properties": {
    "date:inception_lower": "2020-02-01",
    "date:inception_upper": "2020-02-01",
    "iso:country": "GB",
    "wof:name": "MK45 3GY",
    "wof:placetype": "postalcode"
  },
  "geometry": {"coordinates":[-0.482759,52.080458],"type":"Point"}
}
