{
  "type": "Feature",
  "properties": {
    "iso:country": "GB",
    "wof:name": "MK45 3GY",
    "wof:placetype": "postalcode"
  },
  "geometry": {"coordinates":[-0.482763,52.080341],"type":"Point"}
}
