{
  "type": "Feature",
  "properties": {
    "date:inception_lower": "1990-07-01",
    "date:inception_upper": "1990-07-01",
    "iso:country": "GB",
    "wof:name": "CW7 3PZ",
    "wof:placetype": "postalcode"
  },
  "geometry": {"coordinates":[-2.491924,53.192289],"type":"Point"}
}
