{
  "type": "Feature",
  "properties": {
    "iso:country":"GB",
    "wof:name":"CW7 3PZ",
    "wof:placetype":"postalcode"
},
  "geometry": {"coordinates":[-2.49292209848277,53.19303358857101],"type":"Point"}
}