{
  "type": "Feature",
  "properties": {
    "iso:country":"GB",
    "wof:name":"KT2 7PB",
    "wof:placetype":"postalcode"
},
  "geometry": {"coordinates":[-0.27070155794631,51.41751066485561],"type":"Point"}
}