{
  "type": "Feature",
  "properties": {
    "iso:country":"GB",
    "wof:name":"BD19 5AY",
    "wof:placetype":"postalcode"
},
  "geometry": {"coordinates":[-1.7115391930677,53.72045899234304],"type":"Point"}
}