{
  "type": "Feature",
  "properties": {
    "iso:country": "GB",
    "wof:name": "SE13 5FL",
    "wof:placetype": "postalcode"
  },
  "geometry": {"coordinates":[-0.012728,51.46512],"type":"Point"}
}
