{
  "type": "Feature",
  "properties": {
    "iso:country":"GB",
    "wof:name":"HG5 8HN",
    "wof:placetype":"postalcode"
},
  "geometry": {"coordinates":[-1.45654369108685,53.99982873539492],"type":"Point"}
}