{
  "type": "Feature",
  "properties": {
    "iso:country":"GB",
    "wof:name":"TS17 7JW",
    "wof:placetype":"postalcode"
},
  "geometry": {"coordinates":[-1.29346812991678,54.55185337468993],"type":"Point"}
}