{
  "type": "Feature",
  "properties": {
    "iso:country":"GB",
    "wof:name":"B61 8TD",
    "wof:placetype":"postalcode"
},
  "geometry": {"coordinates":[-2.07179874331528,52.34693234488039],"type":"Point"}
}