{
  "type": "Feature",
  "properties": {
    "iso:country":"GB",
    "wof:name":"EX32 9PG",
    "wof:placetype":"postalcode"
},
  "geometry": {"coordinates":[-4.0377702830503,51.06827018961609],"type":"Point"}
}