{
  "type": "Feature",
  "properties": {
    "iso:country": "GB",
    "wof:name": "GU52 7LB",
    "wof:placetype": "postalcode"
  },
  "geometry": {"coordinates":[-0.828214,51.275806],"type":"Point"}
}
