{
  "type": "Feature",
  "properties": {
    "date:inception_lower":"2001-06-01",
    "date:inception_upper":"2001-06-30",
    "iso:country":"GB",
    "wof:name":"GU52 7LB",
    "wof:placetype":"postalcode"
},
  "geometry": {"coordinates":[-0.828214,51.275806],"type":"Point"}
}