{
  "type": "Feature",
  "properties": {
    "date:inception_lower":"2015-10-01",
    "date:inception_upper":"2015-10-31",
    "iso:country":"GB",
    "wof:name":"TR4 9FG",
    "wof:placetype":"postalcode"
},
  "geometry": {"coordinates":[-5.104791,50.337865],"type":"Point"}
}