{
  "type": "Feature",
  "properties": {
    "date:inception_lower": "1999-12-01",
    "date:inception_upper": "1999-12-01",
    "iso:country": "GB",
    "wof:name": "IP11 2UE",
    "wof:placetype": "postalcode"
  },
  "geometry": {"coordinates":[1.32568,51.959786],"type":"Point"}
}
