{
  "type": "Feature",
  "properties": {
    "iso:country": "GB",
    "wof:name": "N8 8EW",
    "wof:placetype": "postalcode"
  },
  "geometry": {"coordinates":[-0.130696,51.576642],"type":"Point"}
}
