{
  "type": "Feature",
  "properties": {
    "iso:country":"GB",
    "wof:name":"N8 8EW",
    "wof:placetype":"postalcode"
},
  "geometry": {"coordinates":[-0.13069628837174,51.57664247122626],"type":"Point"}
}