{
  "type": "Feature",
  "properties": {
    "iso:country": "GB",
    "wof:name": "WD19 7PR",
    "wof:placetype": "postalcode"
  },
  "geometry": {"coordinates":[-0.40492,51.63012],"type":"Point"}
}
