{
  "type": "Feature",
  "properties": {
    "iso:country": "GB",
    "wof:name": "LL30 1NF",
    "wof:placetype": "postalcode"
  },
  "geometry": {"coordinates":[-3.82392,53.302459],"type":"Point"}
}
