{
  "type": "Feature",
  "properties": {
    "iso:country":"GB",
    "wof:name":"LL30 1NF",
    "wof:placetype":"postalcode"
},
  "geometry": {"coordinates":[-3.82423637719889,53.3025636542307],"type":"Point"}
}