{
  "type": "Feature",
  "properties": {
    "date:inception_lower":"1980-01-01",
    "date:inception_upper":"1980-01-31",
    "iso:country":"GB",
    "wof:name":"CH2 3NR",
    "wof:placetype":"postalcode"
},
  "geometry": {"coordinates":[-2.875919,53.200002],"type":"Point"}
}