{
  "type": "Feature",
  "properties": {
    "iso:country": "GB",
    "wof:name": "CH2 3NR",
    "wof:placetype": "postalcode"
  },
  "geometry": {"coordinates":[-2.875919,53.200002],"type":"Point"}
}
