{
  "type": "Feature",
  "properties": {
    "date:inception_lower": "2020-05-01",
    "date:inception_upper": "2020-05-01",
    "iso:country": "GB",
    "wof:name": "PR2 5DH",
    "wof:placetype": "postalcode"
  },
  "geometry": {"coordinates":[-2.617917,53.805764],"type":"Point"}
}
