{
  "type": "Feature",
  "properties": {
    "date:inception_lower": "1994-12-01",
    "date:inception_upper": "1994-12-01",
    "iso:country": "GB",
    "wof:name": "S8 9QS",
    "wof:placetype": "postalcode"
  },
  "geometry": {"coordinates":[-1.466596,53.356009],"type":"Point"}
}
