{
  "type": "Feature",
  "properties": {
    "iso:country": "GB",
    "wof:name": "AB30 1FA",
    "wof:placetype": "postalcode"
  },
  "geometry": {"coordinates":[-2.476343,56.829398],"type":"Point"}
}
