{
  "type": "Feature",
  "properties": {
    "iso:country":"GB",
    "wof:name":"AB30 1FA",
    "wof:placetype":"postalcode"
},
  "geometry": {"coordinates":[-2.47634286345781,56.8293977526823],"type":"Point"}
}