{
  "type": "Feature",
  "properties": {
    "iso:country": "GB",
    "wof:name": "WA11 9NY",
    "wof:placetype": "postalcode"
  },
  "geometry": {"coordinates":[-2.727271,53.465913],"type":"Point"}
}
