{
  "type": "Feature",
  "properties": {
    "date:inception_lower": "1980-01-01",
    "date:inception_upper": "1980-01-01",
    "iso:country": "GB",
    "wof:name": "WA11 9NY",
    "wof:placetype": "postalcode"
  },
  "geometry": {"coordinates":[-2.727271,53.465913],"type":"Point"}
}
