{
  "type": "Feature",
  "properties": {
    "iso:country":"GB",
    "wof:name":"LE9 7DQ",
    "wof:placetype":"postalcode"
},
  "geometry": {"coordinates":[-1.31144402043981,52.5795836959623],"type":"Point"}
}