{
  "type": "Feature",
  "properties": {
    "iso:country":"GB",
    "wof:name":"YO23 3GG",
    "wof:placetype":"postalcode"
},
  "geometry": {"coordinates":[-1.1414504339002,53.91556265287645],"type":"Point"}
}