{
  "type": "Feature",
  "properties": {
    "iso:country": "GB",
    "wof:name": "ML4 2AP",
    "wof:placetype": "postalcode"
  },
  "geometry": {"coordinates":[-4.033798,55.809288],"type":"Point"}
}
