{
  "type": "Feature",
  "properties": {
    "date:inception_lower":"1998-06-01",
    "date:inception_upper":"1998-06-30",
    "iso:country":"GB",
    "wof:name":"ML4 2AP",
    "wof:placetype":"postalcode"
},
  "geometry": {"coordinates":[-4.033798,55.809288],"type":"Point"}
}