{
  "type": "Feature",
  "properties": {
    "iso:country":"GB",
    "wof:name":"EN6 3NX",
    "wof:placetype":"postalcode"
},
  "geometry": {"coordinates":[-0.23233124324845,51.69322805800739],"type":"Point"}
}