{
  "type": "Feature",
  "properties": {
    "iso:country": "GB",
    "wof:name": "EN6 3NX",
    "wof:placetype": "postalcode"
  },
  "geometry": {"coordinates":[-0.232781,51.693698],"type":"Point"}
}
