{
  "type": "Feature",
  "properties": {
    "iso:country":"GB",
    "wof:name":"NG16 5FP",
    "wof:placetype":"postalcode"
},
  "geometry": {"coordinates":[-1.29917271802428,53.04885122152574],"type":"Point"}
}