{
  "type": "Feature",
  "properties": {
    "iso:country": "GB",
    "wof:name": "ME4 6QF",
    "wof:placetype": "postalcode"
  },
  "geometry": {"coordinates":[0.520881,51.375724],"type":"Point"}
}
