{
  "type": "Feature",
  "properties": {
    "date:inception_lower":"1980-01-01",
    "date:inception_upper":"1980-01-31",
    "iso:country":"GB",
    "wof:name":"ME4 6QF",
    "wof:placetype":"postalcode"
},
  "geometry": {"coordinates":[0.520881,51.375724],"type":"Point"}
}