{
  "type": "Feature",
  "properties": {
    "iso:country":"GB",
    "wof:name":"ME4 6QF",
    "wof:placetype":"postalcode"
},
  "geometry": {"coordinates":[0.5208806328365,51.37572402648954],"type":"Point"}
}