{
  "type": "Feature",
  "properties": {
    "date:inception_lower": "1980-01-01",
    "date:inception_upper": "1980-01-01",
    "iso:country": "GB",
    "wof:name": "KY2 6RN",
    "wof:placetype": "postalcode"
  },
  "geometry": {"coordinates":[-3.191327,56.130792],"type":"Point"}
}
