{
  "type": "Feature",
  "properties": {
    "iso:country":"GB",
    "wof:name":"KY7 5DW",
    "wof:placetype":"postalcode"
},
  "geometry": {"coordinates":[-3.15037882964946,56.1905183702693],"type":"Point"}
}