{
  "type": "Feature",
  "properties": {
    "iso:country":"GB",
    "wof:name":"TN4 0RY",
    "wof:placetype":"postalcode"
},
  "geometry": {"coordinates":[0.2539595134637,51.16215021413883],"type":"Point"}
}