{
  "type": "Feature",
  "properties": {
    "iso:country":"GB",
    "wof:name":"SW9 0LP",
    "wof:placetype":"postalcode"
},
  "geometry": {"coordinates":[-0.1130838179738,51.47948419504357],"type":"Point"}
}