{
  "type": "Feature",
  "properties": {
    "iso:country":"GB",
    "wof:name":"PR3 2XA",
    "wof:placetype":"postalcode"
},
  "geometry": {"coordinates":[-2.60513464199826,53.82485101306205],"type":"Point"}
}