{
  "type": "Feature",
  "properties": {
    "date:inception_lower": "2019-01-01",
    "date:inception_upper": "2019-01-01",
    "iso:country": "GB",
    "wof:name": "WF9 2GH",
    "wof:placetype": "postalcode"
  },
  "geometry": {"coordinates":[-1.295744,53.594365],"type":"Point"}
}
