{
  "type": "Feature",
  "properties": {
    "iso:country":"GB",
    "wof:name":"CF41 7SS",
    "wof:placetype":"postalcode"
},
  "geometry": {"coordinates":[-3.46004761521866,51.64533951936989],"type":"Point"}
}