{
  "type": "Feature",
  "properties": {
    "date:inception_lower":"2006-11-01",
    "date:inception_upper":"2006-11-30",
    "iso:country":"GB",
    "wof:name":"CF41 7SS",
    "wof:placetype":"postalcode"
},
  "geometry": {"coordinates":[-3.460048,51.64534],"type":"Point"}
}