{
  "type": "Feature",
  "properties": {
    "iso:country":"GB",
    "wof:name":"SY18 6LX",
    "wof:placetype":"postalcode"
},
  "geometry": {"coordinates":[-3.48012052527877,52.45708748248323],"type":"Point"}
}