{
  "type": "Feature",
  "properties": {
    "iso:country":"GB",
    "wof:name":"CV37 6YX",
    "wof:placetype":"postalcode"
},
  "geometry": {"coordinates":[-1.70028532083158,52.19400934595938],"type":"Point"}
}