{
  "type": "Feature",
  "properties": {
    "date:inception_lower": "2012-07-01",
    "date:inception_upper": "2012-07-01",
    "iso:country": "GB",
    "wof:name": "CV37 6YX",
    "wof:placetype": "postalcode"
  },
  "geometry": {"coordinates":[-1.700285,52.194009],"type":"Point"}
}
