{
  "type": "Feature",
  "properties": {
    "date:inception_lower": "1980-01-01",
    "date:inception_upper": "1980-01-01",
    "iso:country": "GB",
    "wof:name": "G1 1TS",
    "wof:placetype": "postalcode"
  },
  "geometry": {"coordinates":[-4.250116,55.858922],"type":"Point"}
}
