{
  "type": "Feature",
  "properties": {
    "iso:country":"GB",
    "wof:name":"G1 1TS",
    "wof:placetype":"postalcode"
},
  "geometry": {"coordinates":[-4.25011632092578,55.85892177879602],"type":"Point"}
}