{
  "type": "Feature",
  "properties": {
    "iso:country":"GB",
    "wof:name":"NR33 8LR",
    "wof:placetype":"postalcode"
},
  "geometry": {"coordinates":[1.70728745923447,52.45713740373363],"type":"Point"}
}