{
  "type": "Feature",
  "properties": {
    "iso:country":"GB",
    "wof:name":"SE4 1LE",
    "wof:placetype":"postalcode"
},
  "geometry": {"coordinates":[-0.02597597958711,51.45930923000547],"type":"Point"}
}