{
  "type": "Feature",
  "properties": {
    "date:inception_lower": "1980-01-01",
    "date:inception_upper": "1980-01-01",
    "iso:country": "GB",
    "wof:name": "B26 2LW",
    "wof:placetype": "postalcode"
  },
  "geometry": {"coordinates":[-1.798226,52.469335],"type":"Point"}
}
