{
  "type": "Feature",
  "properties": {
    "iso:country":"GB",
    "wof:name":"B26 2LW",
    "wof:placetype":"postalcode"
},
  "geometry": {"coordinates":[-1.79822578022224,52.46933530261072],"type":"Point"}
}