{
  "type": "Feature",
  "properties": {
    "iso:country":"GB",
    "wof:name":"CV31 3QG",
    "wof:placetype":"postalcode"
},
  "geometry": {"coordinates":[-1.53270681909009,52.27608694115175],"type":"Point"}
}