{
  "type": "Feature",
  "properties": {
    "date:inception_lower": "2007-11-01",
    "date:inception_upper": "2007-11-01",
    "iso:country": "GB",
    "wof:name": "E1 1AG",
    "wof:placetype": "postalcode"
  },
  "geometry": {"coordinates":[-0.066014,51.516028],"type":"Point"}
}
