{
  "type": "Feature",
  "properties": {
    "iso:country":"GB",
    "wof:name":"TR16 5SY",
    "wof:placetype":"postalcode"
},
  "geometry": {"coordinates":[-5.21503127494093,50.22220052762957],"type":"Point"}
}