{
  "type": "Feature",
  "properties": {
    "iso:country": "GB",
    "wof:name": "TR16 5SY",
    "wof:placetype": "postalcode"
  },
  "geometry": {"coordinates":[-5.21505,50.222164],"type":"Point"}
}
