{
  "type": "Feature",
  "properties": {
    "date:inception_lower": "1980-01-01",
    "date:inception_upper": "1980-01-01",
    "iso:country": "GB",
    "wof:name": "TR16 5SY",
    "wof:placetype": "postalcode"
  },
  "geometry": {"coordinates":[-5.21505,50.222164],"type":"Point"}
}
