{
  "type": "Feature",
  "properties": {
    "iso:country":"GB",
    "wof:name":"BS4 1ND",
    "wof:placetype":"postalcode"
},
  "geometry": {"coordinates":[-2.58897544092684,51.42825229028367],"type":"Point"}
}