{
  "type": "Feature",
  "properties": {
    "iso:country":"GB",
    "wof:name":"FK1 2DX",
    "wof:placetype":"postalcode"
},
  "geometry": {"coordinates":[-3.76860892203521,55.97209766384719],"type":"Point"}
}