{
  "type": "Feature",
  "properties": {
    "date:inception_lower": "1980-01-01",
    "date:inception_upper": "1980-01-01",
    "iso:country": "GB",
    "wof:name": "FK1 2DX",
    "wof:placetype": "postalcode"
  },
  "geometry": {"coordinates":[-3.768609,55.972098],"type":"Point"}
}
