{
  "type": "Feature",
  "properties": {
    "iso:country":"GB",
    "wof:name":"WF13 4BB",
    "wof:placetype":"postalcode"
},
  "geometry": {"coordinates":[-1.65642733768531,53.70707425555506],"type":"Point"}
}