{
  "type": "Feature",
  "properties": {
    "date:inception_lower": "1980-01-01",
    "date:inception_upper": "1980-01-01",
    "iso:country": "GB",
    "wof:name": "DL8 2BG",
    "wof:placetype": "postalcode"
  },
  "geometry": {"coordinates":[-1.595268,54.283284],"type":"Point"}
}
