{
  "type": "Feature",
  "properties": {
    "iso:country":"GB",
    "wof:name":"TQ12 3HT",
    "wof:placetype":"postalcode"
},
  "geometry": {"coordinates":[-3.59226264353085,50.55039975065323],"type":"Point"}
}