{
  "type": "Feature",
  "properties": {
    "date:inception_lower": "1980-01-01",
    "date:inception_upper": "1980-01-01",
    "iso:country": "GB",
    "wof:name": "TQ12 1RU",
    "wof:placetype": "postalcode"
  },
  "geometry": {"coordinates":[-3.632586,50.535119],"type":"Point"}
}
