{
  "type": "Feature",
  "properties": {
    "iso:country":"GB",
    "wof:name":"TQ12 1RU",
    "wof:placetype":"postalcode"
},
  "geometry": {"coordinates":[-3.63258608771762,50.53511862374479],"type":"Point"}
}