{
  "type": "Feature",
  "properties": {
    "iso:country":"GB",
    "wof:name":"UB8 1NB",
    "wof:placetype":"postalcode"
},
  "geometry": {"coordinates":[-0.48292302131153,51.55180750928555],"type":"Point"}
}