{
  "type": "Feature",
  "properties": {
    "iso:country": "GB",
    "wof:name": "UB8 1NB",
    "wof:placetype": "postalcode"
  },
  "geometry": {"coordinates":[-0.482923,51.551808],"type":"Point"}
}
