{
  "type": "Feature",
  "properties": {
    "iso:country":"GB",
    "wof:name":"ST4 6AY",
    "wof:placetype":"postalcode"
},
  "geometry": {"coordinates":[-2.20963917155931,53.00962129250723],"type":"Point"}
}