{
  "type": "Feature",
  "properties": {
    "iso:country": "GB",
    "wof:name": "WA7 5GF",
    "wof:placetype": "postalcode"
  },
  "geometry": {"coordinates":[-2.71651,53.327776],"type":"Point"}
}
