{
  "type": "Feature",
  "properties": {
    "iso:country":"GB",
    "wof:name":"WA7 5GF",
    "wof:placetype":"postalcode"
},
  "geometry": {"coordinates":[-2.71651025496988,53.3277755826618],"type":"Point"}
}