{
  "type": "Feature",
  "properties": {
    "date:inception_lower":"1980-01-01",
    "date:inception_upper":"1980-01-31",
    "iso:country":"GB",
    "wof:name":"LL21 9EG",
    "wof:placetype":"postalcode"
},
  "geometry": {"coordinates":[-3.339863,52.979203],"type":"Point"}
}