{
  "type": "Feature",
  "properties": {
    "iso:country": "GB",
    "wof:name": "CR3 0BD",
    "wof:placetype": "postalcode"
  },
  "geometry": {"coordinates":[-0.078404,51.30662],"type":"Point"}
}
