{
  "type": "Feature",
  "properties": {
    "iso:country":"GB",
    "wof:name":"SS14 2EZ",
    "wof:placetype":"postalcode"
},
  "geometry": {"coordinates":[0.47301745776151,51.57809702874731],"type":"Point"}
}