{
  "type": "Feature",
  "properties": {
    "iso:country": "GB",
    "wof:name": "SS14 2EZ",
    "wof:placetype": "postalcode"
  },
  "geometry": {"coordinates":[0.473018,51.578097],"type":"Point"}
}
