{
  "type": "Feature",
  "properties": {
    "iso:country": "GB",
    "wof:name": "WR15 8NP",
    "wof:placetype": "postalcode"
  },
  "geometry": {"coordinates":[-2.488429,52.311017],"type":"Point"}
}
