{
  "type": "Feature",
  "properties": {
    "date:inception_lower": "1980-01-01",
    "date:inception_upper": "1980-01-01",
    "iso:country": "GB",
    "wof:name": "WR15 8NP",
    "wof:placetype": "postalcode"
  },
  "geometry": {"coordinates":[-2.486544,52.311883],"type":"Point"}
}
