{
  "type": "Feature",
  "properties": {
    "iso:country": "GB",
    "wof:name": "BD9 4AH",
    "wof:placetype": "postalcode"
  },
  "geometry": {"coordinates":[-1.781972,53.814667],"type":"Point"}
}
