{
  "type": "Feature",
  "properties": {
    "date:inception_lower": "1980-01-01",
    "date:inception_upper": "1980-01-01",
    "iso:country": "GB",
    "wof:name": "EX31 4TY",
    "wof:placetype": "postalcode"
  },
  "geometry": {"coordinates":[-3.917912,51.133591],"type":"Point"}
}
