{
  "type": "Feature",
  "properties": {
    "iso:country":"GB",
    "wof:name":"EH48 3EY",
    "wof:placetype":"postalcode"
},
  "geometry": {"coordinates":[-3.70090600473112,55.89578701705634],"type":"Point"}
}