{
  "type": "Feature",
  "properties": {
    "iso:country":"GB",
    "wof:name":"N12 7JE",
    "wof:placetype":"postalcode"
},
  "geometry": {"coordinates":[-0.19047180266057,51.61919593142162],"type":"Point"}
}