{
  "type": "Feature",
  "properties": {
    "iso:country":"GB",
    "wof:name":"DE7 6FB",
    "wof:placetype":"postalcode"
},
  "geometry": {"coordinates":[-1.37657968095911,52.96089002865127],"type":"Point"}
}