{
  "type": "Feature",
  "properties": {
    "iso:country":"GB",
    "wof:name":"TW20 8RF",
    "wof:placetype":"postalcode"
},
  "geometry": {"coordinates":[-0.53236045953157,51.41338164837861],"type":"Point"}
}