{
  "type": "Feature",
  "properties": {
    "iso:country": "GB",
    "wof:name": "FK15 9JX",
    "wof:placetype": "postalcode"
  },
  "geometry": {"coordinates":[-3.97267,56.192433],"type":"Point"}
}
