{
  "type": "Feature",
  "properties": {
    "iso:country":"GB",
    "wof:name":"NR7 0UG",
    "wof:placetype":"postalcode"
},
  "geometry": {"coordinates":[1.35737227017276,52.63454257495138],"type":"Point"}
}