{
  "type": "Feature",
  "properties": {
    "iso:country":"GB",
    "wof:name":"CA1 1LW",
    "wof:placetype":"postalcode"
},
  "geometry": {"coordinates":[-2.91828417894882,54.89532018660348],"type":"Point"}
}