{
  "type": "Feature",
  "properties": {
    "date:inception_lower": "2023-11-01",
    "date:inception_upper": "2023-11-01",
    "iso:country": "GB",
    "wof:name": "CA1 1LW",
    "wof:placetype": "postalcode"
  },
  "geometry": {"coordinates":[-2.918288,54.895327],"type":"Point"}
}
