{
  "type": "Feature",
  "properties": {
    "date:inception_lower": "2019-05-01",
    "date:inception_upper": "2019-05-01",
    "iso:country": "GB",
    "wof:name": "BB8 0AR",
    "wof:placetype": "postalcode"
  },
  "geometry": {"coordinates":[-2.161569,53.85544],"type":"Point"}
}
