{
  "type": "Feature",
  "properties": {
    "iso:country": "GB",
    "wof:name": "ME2 1LZ",
    "wof:placetype": "postalcode"
  },
  "geometry": {"coordinates":[0.447108,51.349921],"type":"Point"}
}
