{
  "type": "Feature",
  "properties": {
    "iso:country":"GB",
    "wof:name":"LD4 4BS",
    "wof:placetype":"postalcode"
},
  "geometry": {"coordinates":[-3.54253026751473,52.11503361207591],"type":"Point"}
}