{
  "type": "Feature",
  "properties": {
    "date:inception_lower": "1980-01-01",
    "date:inception_upper": "1980-01-01",
    "iso:country": "GB",
    "wof:name": "SW19 8UJ",
    "wof:placetype": "postalcode"
  },
  "geometry": {"coordinates":[-0.19018,51.429847],"type":"Point"}
}
