{
  "type": "Feature",
  "properties": {
    "iso:country":"GB",
    "wof:name":"SW19 8UJ",
    "wof:placetype":"postalcode"
},
  "geometry": {"coordinates":[-0.19017996646272,51.42984672569826],"type":"Point"}
}