{
  "type": "Feature",
  "properties": {
    "iso:country": "GB",
    "wof:name": "HR1 2DU",
    "wof:placetype": "postalcode"
  },
  "geometry": {"coordinates":[-2.712207,52.05843],"type":"Point"}
}
