{
  "type": "Feature",
  "properties": {
    "iso:country":"GB",
    "wof:name":"NE35 9BL",
    "wof:placetype":"postalcode"
},
  "geometry": {"coordinates":[-1.45784871514329,54.94609235746731],"type":"Point"}
}