{
  "type": "Feature",
  "properties": {
    "iso:country":"GB",
    "wof:name":"SA2 9AS",
    "wof:placetype":"postalcode"
},
  "geometry": {"coordinates":[-3.99049883103527,51.61698617404969],"type":"Point"}
}