{
  "type": "Feature",
  "properties": {
    "iso:country":"GB",
    "wof:name":"CW7 3RT",
    "wof:placetype":"postalcode"
},
  "geometry": {"coordinates":[-2.50194952392868,53.20089717871848],"type":"Point"}
}