{
  "type": "Feature",
  "properties": {
    "date:inception_lower": "2013-10-01",
    "date:inception_upper": "2013-10-01",
    "iso:country": "GB",
    "wof:name": "CW7 3RT",
    "wof:placetype": "postalcode"
  },
  "geometry": {"coordinates":[-2.501949,53.200897],"type":"Point"}
}
