{
  "type": "Feature",
  "properties": {
    "date:inception_lower": "1981-09-01",
    "date:inception_upper": "1981-09-01",
    "iso:country": "GB",
    "wof:name": "WA10 2DZ",
    "wof:placetype": "postalcode"
  },
  "geometry": {"coordinates":[-2.747013,53.453602],"type":"Point"}
}
