{
  "type": "Feature",
  "properties": {
    "iso:country":"GB",
    "wof:name":"LE67 4QS",
    "wof:placetype":"postalcode"
},
  "geometry": {"coordinates":[-1.32407307312403,52.72269409513144],"type":"Point"}
}