{
  "type": "Feature",
  "properties": {
    "iso:country":"GB",
    "wof:name":"DY5 4HB",
    "wof:placetype":"postalcode"
},
  "geometry": {"coordinates":[-2.12632966923625,52.49929483503326],"type":"Point"}
}