{
  "type": "Feature",
  "properties": {
    "iso:country":"GB",
    "wof:name":"GL1 2BG",
    "wof:placetype":"postalcode"
},
  "geometry": {"coordinates":[-2.24436777372671,51.86795435991573],"type":"Point"}
}