{
  "type": "Feature",
  "properties": {
    "iso:country": "GB",
    "wof:name": "GL1 2BG",
    "wof:placetype": "postalcode"
  },
  "geometry": {"coordinates":[-2.244368,51.867954],"type":"Point"}
}
