{
  "type": "Feature",
  "properties": {
    "iso:country":"GB",
    "wof:name":"PR9 8QG",
    "wof:placetype":"postalcode"
},
  "geometry": {"coordinates":[-2.96019124701726,53.66621622558756],"type":"Point"}
}