{
  "type": "Feature",
  "properties": {
    "iso:country":"GB",
    "wof:name":"W1F 7DE",
    "wof:placetype":"postalcode"
},
  "geometry": {"coordinates":[-0.13894983822141,51.51341275096017],"type":"Point"}
}