{
  "type": "Feature",
  "properties": {
    "date:inception_lower": "1996-06-01",
    "date:inception_upper": "1996-06-01",
    "iso:country": "GB",
    "wof:name": "LE11 4LZ",
    "wof:placetype": "postalcode"
  },
  "geometry": {"coordinates":[-1.231239,52.773227],"type":"Point"}
}
