{
  "type": "Feature",
  "properties": {
    "date:inception_lower": "1980-01-01",
    "date:inception_upper": "1980-01-01",
    "iso:country": "GB",
    "wof:name": "TS19 9EW",
    "wof:placetype": "postalcode"
  },
  "geometry": {"coordinates":[-1.33327,54.588459],"type":"Point"}
}
