{
  "type": "Feature",
  "properties": {
    "iso:country": "GB",
    "wof:name": "GU28 0BF",
    "wof:placetype": "postalcode"
  },
  "geometry": {"coordinates":[-0.61045,50.984474],"type":"Point"}
}
