{
  "type": "Feature",
  "properties": {
    "date:inception_lower": "1995-07-01",
    "date:inception_upper": "1995-07-01",
    "iso:country": "GB",
    "wof:name": "GU28 0BF",
    "wof:placetype": "postalcode"
  },
  "geometry": {"coordinates":[-0.61045,50.984474],"type":"Point"}
}
