{
  "type": "Feature",
  "properties": {
    "iso:country": "GB",
    "wof:name": "SE20 8SY",
    "wof:placetype": "postalcode"
  },
  "geometry": {"coordinates":[-0.067067,51.407],"type":"Point"}
}
