{
  "type": "Feature",
  "properties": {
    "date:inception_lower":"1980-01-01",
    "date:inception_upper":"1980-01-31",
    "iso:country":"GB",
    "wof:name":"SE20 8SY",
    "wof:placetype":"postalcode"
},
  "geometry": {"coordinates":[-0.067067,51.407],"type":"Point"}
}