{
  "type": "Feature",
  "properties": {
    "iso:country":"GB",
    "wof:name":"WA16 9DW",
    "wof:placetype":"postalcode"
},
  "geometry": {"coordinates":[-2.37967745479838,53.29604721781624],"type":"Point"}
}