{
  "type": "Feature",
  "properties": {
    "date:inception_lower": "1980-01-01",
    "date:inception_upper": "1980-01-01",
    "iso:country": "GB",
    "wof:name": "WA16 9DW",
    "wof:placetype": "postalcode"
  },
  "geometry": {"coordinates":[-2.379677,53.296047],"type":"Point"}
}
