{
  "type": "Feature",
  "properties": {
    "iso:country": "GB",
    "wof:name": "TS18 1QN",
    "wof:placetype": "postalcode"
  },
  "geometry": {"coordinates":[-1.318736,54.566422],"type":"Point"}
}
