{
  "type": "Feature",
  "properties": {
    "iso:country":"GB",
    "wof:name":"SS11 8XD",
    "wof:placetype":"postalcode"
},
  "geometry": {"coordinates":[0.54882962048898,51.60422783034867],"type":"Point"}
}