{
  "type": "Feature",
  "properties": {
    "date:inception_lower":"1988-03-01",
    "date:inception_upper":"1988-03-31",
    "iso:country":"GB",
    "wof:name":"SS11 8XD",
    "wof:placetype":"postalcode"
},
  "geometry": {"coordinates":[0.54883,51.604228],"type":"Point"}
}