{
  "type": "Feature",
  "properties": {
    "iso:country":"GB",
    "wof:name":"PO33 1NW",
    "wof:placetype":"postalcode"
},
  "geometry": {"coordinates":[-1.14252843380274,50.72426203930789],"type":"Point"}
}