{
  "type": "Feature",
  "properties": {
    "iso:country": "GB",
    "wof:name": "PO33 1NW",
    "wof:placetype": "postalcode"
  },
  "geometry": {"coordinates":[-1.142528,50.724262],"type":"Point"}
}
