{
  "type": "Feature",
  "properties": {
    "date:inception_lower": "1980-01-01",
    "date:inception_upper": "1980-01-01",
    "iso:country": "GB",
    "wof:name": "PO33 1NW",
    "wof:placetype": "postalcode"
  },
  "geometry": {"coordinates":[-1.142489,50.724251],"type":"Point"}
}
