{
  "type": "Feature",
  "properties": {
    "iso:country": "GB",
    "wof:name": "BH13 7AW",
    "wof:placetype": "postalcode"
  },
  "geometry": {"coordinates":[-1.9294,50.712401],"type":"Point"}
}
