{
  "type": "Feature",
  "properties": {
    "iso:country":"GB",
    "wof:name":"HG4 4AN",
    "wof:placetype":"postalcode"
},
  "geometry": {"coordinates":[-1.63838778470658,54.26346043333937],"type":"Point"}
}