{
  "type": "Feature",
  "properties": {
    "iso:country": "GB",
    "wof:name": "HG4 4AN",
    "wof:placetype": "postalcode"
  },
  "geometry": {"coordinates":[-1.63838,54.263481],"type":"Point"}
}
