{
  "type": "Feature",
  "properties": {
    "iso:country":"GB",
    "wof:name":"TW9 2DQ",
    "wof:placetype":"postalcode"
},
  "geometry": {"coordinates":[-0.29241781159876,51.47113622913588],"type":"Point"}
}