{
  "type": "Feature",
  "properties": {
    "date:inception_lower": "1980-01-01",
    "date:inception_upper": "1980-01-01",
    "iso:country": "GB",
    "wof:name": "TW9 2DQ",
    "wof:placetype": "postalcode"
  },
  "geometry": {"coordinates":[-0.292418,51.471136],"type":"Point"}
}
