{
  "type": "Feature",
  "properties": {
    "iso:country":"GB",
    "wof:name":"KA7 3EG",
    "wof:placetype":"postalcode"
},
  "geometry": {"coordinates":[-4.61606158354934,55.45088110286483],"type":"Point"}
}