{
  "type": "Feature",
  "properties": {
    "iso:country":"GB",
    "wof:name":"M25 1PW",
    "wof:placetype":"postalcode"
},
  "geometry": {"coordinates":[-2.27303510632489,53.53556981082465],"type":"Point"}
}