{
  "type": "Feature",
  "properties": {
    "date:inception_lower": "1994-05-01",
    "date:inception_upper": "1994-05-01",
    "iso:country": "GB",
    "wof:name": "M25 1PW",
    "wof:placetype": "postalcode"
  },
  "geometry": {"coordinates":[-2.273035,53.53557],"type":"Point"}
}
