{
  "type": "Feature",
  "properties": {
    "iso:country":"GB",
    "wof:name":"N1 6LD",
    "wof:placetype":"postalcode"
},
  "geometry": {"coordinates":[-0.08081125478043,51.52918401131212],"type":"Point"}
}