{
  "type": "Feature",
  "properties": {
    "iso:country":"GB",
    "wof:name":"EH55 8JF",
    "wof:placetype":"postalcode"
},
  "geometry": {"coordinates":[-3.66686068677003,55.82947565711056],"type":"Point"}
}