{
  "type": "Feature",
  "properties": {
    "iso:country":"GB",
    "wof:name":"EH3 7PE",
    "wof:placetype":"postalcode"
},
  "geometry": {"coordinates":[-3.21213425405663,55.95072977691321],"type":"Point"}
}