{
  "type": "Feature",
  "properties": {
    "iso:country":"GB",
    "wof:name":"BH14 9JS",
    "wof:placetype":"postalcode"
},
  "geometry": {"coordinates":[-1.93758834606626,50.72162311190559],"type":"Point"}
}