{
  "type": "Feature",
  "properties": {
    "iso:country":"GB",
    "wof:name":"KT3 3UL",
    "wof:placetype":"postalcode"
},
  "geometry": {"coordinates":[-0.26806717978243,51.41301148451957],"type":"Point"}
}