{
  "type": "Feature",
  "properties": {
    "iso:country":"GB",
    "wof:name":"SL3 7EB",
    "wof:placetype":"postalcode"
},
  "geometry": {"coordinates":[-0.55561400633913,51.50546249009152],"type":"Point"}
}