{
  "type": "Feature",
  "properties": {
    "date:inception_lower": "1980-01-01",
    "date:inception_upper": "1980-01-01",
    "iso:country": "GB",
    "wof:name": "SL3 7EB",
    "wof:placetype": "postalcode"
  },
  "geometry": {"coordinates":[-0.555614,51.505462],"type":"Point"}
}
