{
  "type": "Feature",
  "properties": {
    "date:inception_lower": "1981-06-01",
    "date:inception_upper": "1981-06-01",
    "iso:country": "GB",
    "wof:name": "DN18 5BP",
    "wof:placetype": "postalcode"
  },
  "geometry": {"coordinates":[-0.449535,53.689059],"type":"Point"}
}
