{
  "type": "Feature",
  "properties": {
    "iso:country":"GB",
    "wof:name":"DN18 5BP",
    "wof:placetype":"postalcode"
},
  "geometry": {"coordinates":[-0.44953460835995,53.68905905027744],"type":"Point"}
}