{
  "type": "Feature",
  "properties": {
    "iso:country": "GB",
    "wof:name": "BH19 2JP",
    "wof:placetype": "postalcode"
  },
  "geometry": {"coordinates":[-1.98272,50.608824],"type":"Point"}
}
