{
  "type": "Feature",
  "properties": {
    "iso:country":"GB",
    "wof:name":"BH19 2JP",
    "wof:placetype":"postalcode"
},
  "geometry": {"coordinates":[-1.98272007834886,50.60882430243033],"type":"Point"}
}