{
  "type": "Feature",
  "properties": {
    "date:inception_lower": "1980-01-01",
    "date:inception_upper": "1980-01-01",
    "iso:country": "GB",
    "wof:name": "BH19 2JP",
    "wof:placetype": "postalcode"
  },
  "geometry": {"coordinates":[-1.98272,50.608824],"type":"Point"}
}
