{
  "type": "Feature",
  "properties": {
    "iso:country":"GB",
    "wof:name":"GU52 8JY",
    "wof:placetype":"postalcode"
},
  "geometry": {"coordinates":[-0.8383990402924,51.26022508029637],"type":"Point"}
}