{
  "type": "Feature",
  "properties": {
    "date:inception_lower": "2016-03-01",
    "date:inception_upper": "2016-03-01",
    "iso:country": "GB",
    "wof:name": "DN11 8SQ",
    "wof:placetype": "postalcode"
  },
  "geometry": {"coordinates":[-1.063488,53.425198],"type":"Point"}
}
