{
  "type": "Feature",
  "properties": {
    "iso:country":"GB",
    "wof:name":"DN11 8SQ",
    "wof:placetype":"postalcode"
},
  "geometry": {"coordinates":[-1.06058603609322,53.42435571040675],"type":"Point"}
}