{
  "type": "Feature",
  "properties": {
    "iso:country": "GB",
    "wof:name": "CF39 8UH",
    "wof:placetype": "postalcode"
  },
  "geometry": {"coordinates":[-3.468703,51.582647],"type":"Point"}
}
