{
  "type": "Feature",
  "properties": {
    "iso:country":"GB",
    "wof:name":"CF39 8UH",
    "wof:placetype":"postalcode"
},
  "geometry": {"coordinates":[-3.46870305196092,51.58264749767623],"type":"Point"}
}