{
  "type": "Feature",
  "properties": {
    "iso:country":"GB",
    "wof:name":"YO10 3JU",
    "wof:placetype":"postalcode"
},
  "geometry": {"coordinates":[-1.0504448319995,53.95407493182803],"type":"Point"}
}