{
  "type": "Feature",
  "properties": {
    "iso:country":"GB",
    "wof:name":"PO7 4SR",
    "wof:placetype":"postalcode"
},
  "geometry": {"coordinates":[-1.09114674042334,50.92598468794222],"type":"Point"}
}