{
  "type": "Feature",
  "properties": {
    "iso:country":"GB",
    "wof:name":"SN25 3PZ",
    "wof:placetype":"postalcode"
},
  "geometry": {"coordinates":[-1.80452763471813,51.59198335135225],"type":"Point"}
}