{
  "type": "Feature",
  "properties": {
    "iso:country": "GB",
    "wof:name": "PO40 9QG",
    "wof:placetype": "postalcode"
  },
  "geometry": {"coordinates":[-1.514283,50.672743],"type":"Point"}
}
