{
  "type": "Feature",
  "properties": {
    "iso:country": "GB",
    "wof:name": "BS27 3BP",
    "wof:placetype": "postalcode"
  },
  "geometry": {"coordinates":[-2.785361,51.282876],"type":"Point"}
}
