{
  "type": "Feature",
  "properties": {
    "date:inception_lower": "1980-01-01",
    "date:inception_upper": "1980-01-01",
    "iso:country": "GB",
    "wof:name": "BS27 3BP",
    "wof:placetype": "postalcode"
  },
  "geometry": {"coordinates":[-2.785361,51.282876],"type":"Point"}
}
