{
  "type": "Feature",
  "properties": {
    "iso:country":"GB",
    "wof:name":"BS27 3BP",
    "wof:placetype":"postalcode"
},
  "geometry": {"coordinates":[-2.78521213543518,51.28288099799038],"type":"Point"}
}