{
  "type": "Feature",
  "properties": {
    "iso:country":"GB",
    "wof:name":"FK8 3UB",
    "wof:placetype":"postalcode"
},
  "geometry": {"coordinates":[-4.61548747065931,56.28368101539184],"type":"Point"}
}