{
  "type": "Feature",
  "properties": {
    "iso:country": "GB",
    "wof:name": "FK8 3UB",
    "wof:placetype": "postalcode"
  },
  "geometry": {"coordinates":[-4.615487,56.283681],"type":"Point"}
}
