{
  "type": "Feature",
  "properties": {
    "date:inception_lower":"1980-01-01",
    "date:inception_upper":"1980-01-31",
    "iso:country":"GB",
    "wof:name":"FK8 3UB",
    "wof:placetype":"postalcode"
},
  "geometry": {"coordinates":[-4.615487,56.283681],"type":"Point"}
}