{
  "type": "Feature",
  "properties": {
    "iso:country": "GB",
    "wof:name": "SW7 1NY",
    "wof:placetype": "postalcode"
  },
  "geometry": {"coordinates":[-0.168684,51.49909],"type":"Point"}
}
