{
  "type": "Feature",
  "properties": {
    "iso:country":"GB",
    "wof:name":"CV34 5YW",
    "wof:placetype":"postalcode"
},
  "geometry": {"coordinates":[-1.58132545253551,52.29601194338319],"type":"Point"}
}