{
  "type": "Feature",
  "properties": {
    "iso:country":"GB",
    "wof:name":"WN6 7PN",
    "wof:placetype":"postalcode"
},
  "geometry": {"coordinates":[-2.64564899694097,53.5595662025362],"type":"Point"}
}