{
  "type": "Feature",
  "properties": {
    "iso:country": "GB",
    "wof:name": "WN6 7PN",
    "wof:placetype": "postalcode"
  },
  "geometry": {"coordinates":[-2.645649,53.559566],"type":"Point"}
}
