{
  "type": "Feature",
  "properties": {
    "iso:country": "GB",
    "wof:name": "LE5 6HJ",
    "wof:placetype": "postalcode"
  },
  "geometry": {"coordinates":[-1.06896,52.624081],"type":"Point"}
}
