{
  "type": "Feature",
  "properties": {
    "iso:country":"GB",
    "wof:name":"WC1X 9NP",
    "wof:placetype":"postalcode"
},
  "geometry": {"coordinates":[-0.11744119602234,51.52893230263648],"type":"Point"}
}