{
  "type": "Feature",
  "properties": {
    "date:inception_lower": "1980-01-01",
    "date:inception_upper": "1980-01-01",
    "iso:country": "GB",
    "wof:name": "WC1X 9NP",
    "wof:placetype": "postalcode"
  },
  "geometry": {"coordinates":[-0.117441,51.528932],"type":"Point"}
}
