{
  "type": "Feature",
  "properties": {
    "iso:country": "GB",
    "wof:name": "WC1X 9NP",
    "wof:placetype": "postalcode"
  },
  "geometry": {"coordinates":[-0.117441,51.528932],"type":"Point"}
}
