{
  "type": "Feature",
  "properties": {
    "iso:country":"GB",
    "wof:name":"DL3 7HU",
    "wof:placetype":"postalcode"
},
  "geometry": {"coordinates":[-1.5638370291633,54.51913195459726],"type":"Point"}
}