{
  "type": "Feature",
  "properties": {
    "date:inception_lower": "1980-01-01",
    "date:inception_upper": "1980-01-01",
    "iso:country": "GB",
    "wof:name": "TQ13 7RZ",
    "wof:placetype": "postalcode"
  },
  "geometry": {"coordinates":[-3.815784,50.502114],"type":"Point"}
}
