{
  "type": "Feature",
  "properties": {
    "iso:country": "GB",
    "wof:name": "WV4 5JY",
    "wof:placetype": "postalcode"
  },
  "geometry": {"coordinates":[-2.155262,52.545558],"type":"Point"}
}
