{
  "type": "Feature",
  "properties": {
    "date:inception_lower":"1985-10-01",
    "date:inception_upper":"1985-10-31",
    "iso:country":"GB",
    "wof:name":"WV4 5JY",
    "wof:placetype":"postalcode"
},
  "geometry": {"coordinates":[-2.155262,52.545558],"type":"Point"}
}