{
  "type": "Feature",
  "properties": {
    "date:inception_lower": "1980-01-01",
    "date:inception_upper": "1980-01-01",
    "iso:country": "GB",
    "wof:name": "SN3 4BS",
    "wof:placetype": "postalcode"
  },
  "geometry": {"coordinates":[-1.734033,51.573341],"type":"Point"}
}
