{
  "type": "Feature",
  "properties": {
    "iso:country": "GB",
    "wof:name": "NG8 6LW",
    "wof:placetype": "postalcode"
  },
  "geometry": {"coordinates":[-1.23063,52.977385],"type":"Point"}
}
