{
  "type": "Feature",
  "properties": {
    "iso:country":"GB",
    "wof:name":"NG8 6LW",
    "wof:placetype":"postalcode"
},
  "geometry": {"coordinates":[-1.2306301921137,52.97738489460396],"type":"Point"}
}