{
  "type": "Feature",
  "properties": {
    "iso:country":"GB",
    "wof:name":"DH7 6RE",
    "wof:placetype":"postalcode"
},
  "geometry": {"coordinates":[-1.63122271987753,54.81190953201212],"type":"Point"}
}