{
  "type": "Feature",
  "properties": {
    "date:inception_lower":"1980-01-01",
    "date:inception_upper":"1980-01-31",
    "iso:country":"GB",
    "wof:name":"PO22 9PX",
    "wof:placetype":"postalcode"
},
  "geometry": {"coordinates":[-0.675011,50.79524],"type":"Point"}
}