{
  "type": "Feature",
  "properties": {
    "date:inception_lower": "2018-08-01",
    "date:inception_upper": "2018-08-01",
    "iso:country": "GB",
    "wof:name": "MK43 9RF",
    "wof:placetype": "postalcode"
  },
  "geometry": {"coordinates":[-0.531001,52.090852],"type":"Point"}
}
