{
  "type": "Feature",
  "properties": {
    "date:inception_lower": "2016-10-01",
    "date:inception_upper": "2016-10-01",
    "iso:country": "GB",
    "wof:name": "NE19 1TQ",
    "wof:placetype": "postalcode"
  },
  "geometry": {"coordinates":[-2.375783,55.3177],"type":"Point"}
}
