{
  "type": "Feature",
  "properties": {
    "iso:country": "GB",
    "wof:name": "NE19 1TQ",
    "wof:placetype": "postalcode"
  },
  "geometry": {"coordinates":[-2.375783,55.3177],"type":"Point"}
}
