{
  "type": "Feature",
  "properties": {
    "iso:country":"GB",
    "wof:name":"MK2 2LY",
    "wof:placetype":"postalcode"
},
  "geometry": {"coordinates":[-0.73439544156444,51.99231803526165],"type":"Point"}
}