{
  "type": "Feature",
  "properties": {
    "date:inception_lower": "1991-09-01",
    "date:inception_upper": "1991-09-01",
    "iso:country": "GB",
    "wof:name": "NG18 3FF",
    "wof:placetype": "postalcode"
  },
  "geometry": {"coordinates":[-1.166392,53.143866],"type":"Point"}
}
