{
  "type": "Feature",
  "properties": {
    "iso:country":"GB",
    "wof:name":"B3 3HG",
    "wof:placetype":"postalcode"
},
  "geometry": {"coordinates":[-1.90550280769032,52.47920552772114],"type":"Point"}
}