{
  "type": "Feature",
  "properties": {
    "iso:country":"GB",
    "wof:name":"BS37 8QP",
    "wof:placetype":"postalcode"
},
  "geometry": {"coordinates":[-2.43585110496448,51.51480938148928],"type":"Point"}
}