{
  "type": "Feature",
  "properties": {
    "iso:country":"GB",
    "wof:name":"TR19 7HD",
    "wof:placetype":"postalcode"
},
  "geometry": {"coordinates":[-5.67938514746714,50.1242591669878],"type":"Point"}
}