{
  "type": "Feature",
  "properties": {
    "iso:country": "GB",
    "wof:name": "BS32 8TP",
    "wof:placetype": "postalcode"
  },
  "geometry": {"coordinates":[-2.536447,51.527727],"type":"Point"}
}
