{
  "type": "Feature",
  "properties": {
    "iso:country":"GB",
    "wof:name":"CR9 1ET",
    "wof:placetype":"postalcode"
},
  "geometry": {"coordinates":[-0.09953599115243,51.37191084459001],"type":"Point"}
}