{
  "type": "Feature",
  "properties": {
    "iso:country": "GB",
    "wof:name": "HX3 8FW",
    "wof:placetype": "postalcode"
  },
  "geometry": {"coordinates":[-1.809198,53.732195],"type":"Point"}
}
