{
  "type": "Feature",
  "properties": {
    "iso:country":"GB",
    "wof:name":"W6 8AU",
    "wof:placetype":"postalcode"
},
  "geometry": {"coordinates":[-0.22325054116377,51.49106096761405],"type":"Point"}
}