{
  "type": "Feature",
  "properties": {
    "iso:country": "GB",
    "wof:name": "WA6 8PR",
    "wof:placetype": "postalcode"
  },
  "geometry": {"coordinates":[-2.637099,53.242158],"type":"Point"}
}
