{
  "type": "Feature",
  "properties": {
    "iso:country":"GB",
    "wof:name":"SE19 3PL",
    "wof:placetype":"postalcode"
},
  "geometry": {"coordinates":[-0.0880693011141,51.41641814176231],"type":"Point"}
}