{
  "type": "Feature",
  "properties": {
    "date:inception_lower": "2024-10-01",
    "date:inception_upper": "2024-10-01",
    "iso:country": "GB",
    "wof:name": "CM9 6WD",
    "wof:placetype": "postalcode"
  },
  "geometry": {"coordinates":[0.665169,51.713214],"type":"Point"}
}
