{
  "type": "Feature",
  "properties": {
    "iso:country": "GB",
    "wof:name": "CV9 2SE",
    "wof:placetype": "postalcode"
  },
  "geometry": {"coordinates":[-1.630382,52.581709],"type":"Point"}
}
