{
  "type": "Feature",
  "properties": {
    "iso:country":"GB",
    "wof:name":"CV9 2SE",
    "wof:placetype":"postalcode"
},
  "geometry": {"coordinates":[-1.63038236147205,52.58170910267919],"type":"Point"}
}