{
  "type": "Feature",
  "properties": {
    "iso:country":"GB",
    "wof:name":"M18 8GA",
    "wof:placetype":"postalcode"
},
  "geometry": {"coordinates":[-2.16335329169881,53.46673915026703],"type":"Point"}
}