{
  "type": "Feature",
  "properties": {
    "iso:country": "GB",
    "wof:name": "M18 8GA",
    "wof:placetype": "postalcode"
  },
  "geometry": {"coordinates":[-2.163353,53.466739],"type":"Point"}
}
