{
  "type": "Feature",
  "properties": {
    "iso:country":"GB",
    "wof:name":"TR6 0FD",
    "wof:placetype":"postalcode"
},
  "geometry": {"coordinates":[-5.15345483639967,50.34201419053686],"type":"Point"}
}