{
  "type": "Feature",
  "properties": {
    "date:inception_lower": "2010-08-01",
    "date:inception_upper": "2010-08-01",
    "iso:country": "GB",
    "wof:name": "TR6 0FD",
    "wof:placetype": "postalcode"
  },
  "geometry": {"coordinates":[-5.153455,50.342014],"type":"Point"}
}
