{
  "type": "Feature",
  "properties": {
    "date:inception_lower":"1996-12-01",
    "date:inception_upper":"1996-12-31",
    "iso:country":"GB",
    "wof:name":"KA23 9PL",
    "wof:placetype":"postalcode"
},
  "geometry": {"coordinates":[-4.856524,55.694331],"type":"Point"}
}