{
  "type": "Feature",
  "properties": {
    "iso:country":"GB",
    "wof:name":"KA23 9PL",
    "wof:placetype":"postalcode"
},
  "geometry": {"coordinates":[-4.85654661861464,55.69433396236614],"type":"Point"}
}