{
  "type": "Feature",
  "properties": {
    "iso:country":"GB",
    "wof:name":"SY22 6HD",
    "wof:placetype":"postalcode"
},
  "geometry": {"coordinates":[-3.087073293925,52.78714850292604],"type":"Point"}
}