{
  "type": "Feature",
  "properties": {
    "date:inception_lower": "1980-01-01",
    "date:inception_upper": "1980-01-01",
    "iso:country": "GB",
    "wof:name": "SY22 6HD",
    "wof:placetype": "postalcode"
  },
  "geometry": {"coordinates":[-3.087073,52.787149],"type":"Point"}
}
