{
  "type": "Feature",
  "properties": {
    "iso:country":"GB",
    "wof:name":"NG18 4PG",
    "wof:placetype":"postalcode"
},
  "geometry": {"coordinates":[-1.1702044904807,53.12523992390349],"type":"Point"}
}