{
  "type": "Feature",
  "properties": {
    "iso:country":"GB",
    "wof:name":"M13 0RF",
    "wof:placetype":"postalcode"
},
  "geometry": {"coordinates":[-2.20418314436876,53.45276209999115],"type":"Point"}
}