{
  "type": "Feature",
  "properties": {
    "iso:country":"GB",
    "wof:name":"DL4 2EG",
    "wof:placetype":"postalcode"
},
  "geometry": {"coordinates":[-1.63996602826004,54.63147529167147],"type":"Point"}
}