{
  "type": "Feature",
  "properties": {
    "iso:country": "GB",
    "wof:name": "M35 9LT",
    "wof:placetype": "postalcode"
  },
  "geometry": {"coordinates":[-2.14407,53.515014],"type":"Point"}
}
