{
  "type": "Feature",
  "properties": {
    "date:inception_lower": "1980-01-01",
    "date:inception_upper": "1980-01-01",
    "iso:country": "GB",
    "wof:name": "M35 9LT",
    "wof:placetype": "postalcode"
  },
  "geometry": {"coordinates":[-2.14407,53.515014],"type":"Point"}
}
