{
  "type": "Feature",
  "properties": {
    "iso:country":"GB",
    "wof:name":"M35 9LT",
    "wof:placetype":"postalcode"
},
  "geometry": {"coordinates":[-2.14407031652044,53.51501387511012],"type":"Point"}
}