{
  "type": "Feature",
  "properties": {
    "iso:country":"GB",
    "wof:name":"NR14 7TF",
    "wof:placetype":"postalcode"
},
  "geometry": {"coordinates":[1.35503158779397,52.57151735345024],"type":"Point"}
}