{
  "type": "Feature",
  "properties": {
    "iso:country": "GB",
    "wof:name": "NR14 7TF",
    "wof:placetype": "postalcode"
  },
  "geometry": {"coordinates":[1.355032,52.571517],"type":"Point"}
}
