{
  "type": "Feature",
  "properties": {
    "iso:country":"GB",
    "wof:name":"BB2 5AJ",
    "wof:placetype":"postalcode"
},
  "geometry": {"coordinates":[-2.52397951651508,53.72857507334674],"type":"Point"}
}