{
  "type": "Feature",
  "properties": {
    "date:inception_lower": "1980-01-01",
    "date:inception_upper": "1980-01-01",
    "iso:country": "GB",
    "wof:name": "EX5 1NN",
    "wof:placetype": "postalcode"
  },
  "geometry": {"coordinates":[-3.398108,50.672206],"type":"Point"}
}
