{
  "type": "Feature",
  "properties": {
    "iso:country":"GB",
    "wof:name":"EX5 1NN",
    "wof:placetype":"postalcode"
},
  "geometry": {"coordinates":[-3.39764016958491,50.67216892025053],"type":"Point"}
}