{
  "type": "Feature",
  "properties": {
    "date:inception_lower": "1980-01-01",
    "date:inception_upper": "1980-01-01",
    "iso:country": "GB",
    "wof:name": "NP4 7JA",
    "wof:placetype": "postalcode"
  },
  "geometry": {"coordinates":[-3.071094,51.731328],"type":"Point"}
}
