{
  "type": "Feature",
  "properties": {
    "date:inception_lower":"1980-01-01",
    "date:inception_upper":"1980-01-31",
    "iso:country":"GB",
    "wof:name":"MK44 3NG",
    "wof:placetype":"postalcode"
},
  "geometry": {"coordinates":[-0.320244,52.147117],"type":"Point"}
}