{
  "type": "Feature",
  "properties": {
    "iso:country":"GB",
    "wof:name":"MK44 3NG",
    "wof:placetype":"postalcode"
},
  "geometry": {"coordinates":[-0.32024386548904,52.14711709600851],"type":"Point"}
}