{
  "type": "Feature",
  "properties": {
    "iso:country": "GB",
    "wof:name": "CO10 9GY",
    "wof:placetype": "postalcode"
  },
  "geometry": {"coordinates":[0.715624,52.074695],"type":"Point"}
}
