{
  "type": "Feature",
  "properties": {
    "iso:country": "GB",
    "wof:name": "CO10 9GY",
    "wof:placetype": "postalcode"
  },
  "geometry": {"coordinates":[0.71564,52.0747],"type":"Point"}
}
