{
  "type": "Feature",
  "properties": {
    "iso:country":"GB",
    "wof:name":"CO10 9GY",
    "wof:placetype":"postalcode"
},
  "geometry": {"coordinates":[0.7156242969958,52.07469495152895],"type":"Point"}
}