{
  "type": "Feature",
  "properties": {
    "iso:country":"GB",
    "wof:name":"HR6 9PP",
    "wof:placetype":"postalcode"
},
  "geometry": {"coordinates":[-2.79122672064197,52.27573348769581],"type":"Point"}
}