{
  "type": "Feature",
  "properties": {
    "iso:country": "GB",
    "wof:name": "HR6 9PP",
    "wof:placetype": "postalcode"
  },
  "geometry": {"coordinates":[-2.791227,52.275733],"type":"Point"}
}
