{
  "type": "Feature",
  "properties": {
    "date:inception_lower": "2018-09-01",
    "date:inception_upper": "2018-09-01",
    "iso:country": "GB",
    "wof:name": "SS11 8GH",
    "wof:placetype": "postalcode"
  },
  "geometry": {"coordinates":[0.59182,51.621674],"type":"Point"}
}
