{
  "type": "Feature",
  "properties": {
    "iso:country":"GB",
    "wof:name":"YO32 9TH",
    "wof:placetype":"postalcode"
},
  "geometry": {"coordinates":[-1.02660270436343,53.99106789759399],"type":"Point"}
}