{
  "type": "Feature",
  "properties": {
    "iso:country": "GB",
    "wof:name": "YO32 9TH",
    "wof:placetype": "postalcode"
  },
  "geometry": {"coordinates":[-1.026603,53.991068],"type":"Point"}
}
