{
  "type": "Feature",
  "properties": {
    "iso:country": "GB",
    "wof:name": "BS22 6EW",
    "wof:placetype": "postalcode"
  },
  "geometry": {"coordinates":[-2.930511,51.3574],"type":"Point"}
}
