{
  "type": "Feature",
  "properties": {
    "date:inception_lower":"1997-12-01",
    "date:inception_upper":"1997-12-31",
    "iso:country":"GB",
    "wof:name":"BS22 6EW",
    "wof:placetype":"postalcode"
},
  "geometry": {"coordinates":[-2.930511,51.3574],"type":"Point"}
}