{
  "type": "Feature",
  "properties": {
    "iso:country":"GB",
    "wof:name":"BD1 1QR",
    "wof:placetype":"postalcode"
},
  "geometry": {"coordinates":[-1.75555490095871,53.79477101761977],"type":"Point"}
}