{
  "type": "Feature",
  "properties": {
    "iso:country": "GB",
    "wof:name": "GL51 3HZ",
    "wof:placetype": "postalcode"
  },
  "geometry": {"coordinates":[-2.101149,51.879583],"type":"Point"}
}
