{
  "type": "Feature",
  "properties": {
    "date:inception_lower": "2000-10-01",
    "date:inception_upper": "2000-10-01",
    "iso:country": "GB",
    "wof:name": "GL51 3HZ",
    "wof:placetype": "postalcode"
  },
  "geometry": {"coordinates":[-2.101149,51.879583],"type":"Point"}
}
