{
  "type": "Feature",
  "properties": {
    "iso:country":"GB",
    "wof:name":"PE28 2SS",
    "wof:placetype":"postalcode"
},
  "geometry": {"coordinates":[-0.07293357798108,52.40045752666526],"type":"Point"}
}