{
  "type": "Feature",
  "properties": {
    "iso:country": "GB",
    "wof:name": "PE28 2SS",
    "wof:placetype": "postalcode"
  },
  "geometry": {"coordinates":[-0.072934,52.400458],"type":"Point"}
}
