{
  "type": "Feature",
  "properties": {
    "iso:country":"GB",
    "wof:name":"GU34 3QR",
    "wof:placetype":"postalcode"
},
  "geometry": {"coordinates":[-0.99353219694254,51.08571870047806],"type":"Point"}
}