{
  "type": "Feature",
  "properties": {
    "date:inception_lower": "1980-01-01",
    "date:inception_upper": "1980-01-01",
    "iso:country": "GB",
    "wof:name": "DL14 8HG",
    "wof:placetype": "postalcode"
  },
  "geometry": {"coordinates":[-1.625327,54.666956],"type":"Point"}
}
