{
  "type": "Feature",
  "properties": {
    "date:inception_lower": "1980-01-01",
    "date:inception_upper": "1980-01-01",
    "iso:country": "GB",
    "wof:name": "CV2 3DH",
    "wof:placetype": "postalcode"
  },
  "geometry": {"coordinates":[-1.464199,52.419667],"type":"Point"}
}
