{
  "type": "Feature",
  "properties": {
    "iso:country": "GB",
    "wof:name": "WA3 3YL",
    "wof:placetype": "postalcode"
  },
  "geometry": {"coordinates":[-2.589818,53.482308],"type":"Point"}
}
