{
  "type": "Feature",
  "properties": {
    "date:inception_lower": "1980-01-01",
    "date:inception_upper": "1980-01-01",
    "iso:country": "GB",
    "wof:name": "BD16 3EW",
    "wof:placetype": "postalcode"
  },
  "geometry": {"coordinates":[-1.815836,53.857399],"type":"Point"}
}
