{
  "type": "Feature",
  "properties": {
    "iso:country":"GB",
    "wof:name":"BD16 3EW",
    "wof:placetype":"postalcode"
},
  "geometry": {"coordinates":[-1.8158364360264,53.85739862046918],"type":"Point"}
}