{
  "type": "Feature",
  "properties": {
    "iso:country":"GB",
    "wof:name":"IP11 2GB",
    "wof:placetype":"postalcode"
},
  "geometry": {"coordinates":[1.33581438284211,51.94981209862739],"type":"Point"}
}