{
  "type": "Feature",
  "properties": {
    "iso:country": "GB",
    "wof:name": "IP11 2GB",
    "wof:placetype": "postalcode"
  },
  "geometry": {"coordinates":[1.335814,51.949812],"type":"Point"}
}
