{
  "type": "Feature",
  "properties": {
    "date:inception_lower":"1997-06-01",
    "date:inception_upper":"1997-06-30",
    "iso:country":"GB",
    "wof:name":"S18 2GQ",
    "wof:placetype":"postalcode"
},
  "geometry": {"coordinates":[-1.470014,53.306991],"type":"Point"}
}