{
  "type": "Feature",
  "properties": {
    "iso:country":"GB",
    "wof:name":"L74 4AP",
    "wof:placetype":"postalcode"
},
  "geometry": {"coordinates":[-2.98828542762409,53.39299919030078],"type":"Point"}
}