{
  "type": "Feature",
  "properties": {
    "iso:country":"GB",
    "wof:name":"CR0 5ED",
    "wof:placetype":"postalcode"
},
  "geometry": {"coordinates":[-0.04907775655218,51.37289796962956],"type":"Point"}
}