{
  "type": "Feature",
  "properties": {
    "iso:country":"GB",
    "wof:name":"SL1 5HS",
    "wof:placetype":"postalcode"
},
  "geometry": {"coordinates":[-0.64270251137273,51.51850682576226],"type":"Point"}
}