{
  "type": "Feature",
  "properties": {
    "iso:country": "GB",
    "wof:name": "SL1 5HS",
    "wof:placetype": "postalcode"
  },
  "geometry": {"coordinates":[-0.642636,51.518212],"type":"Point"}
}
