{
  "type": "Feature",
  "properties": {
    "date:inception_lower":"1980-01-01",
    "date:inception_upper":"1980-01-31",
    "iso:country":"GB",
    "wof:name":"CF38 2LE",
    "wof:placetype":"postalcode"
},
  "geometry": {"coordinates":[-3.351264,51.550681],"type":"Point"}
}