{
  "type": "Feature",
  "properties": {
    "iso:country":"GB",
    "wof:name":"CF38 2LE",
    "wof:placetype":"postalcode"
},
  "geometry": {"coordinates":[-3.35126388364253,51.5506807042828],"type":"Point"}
}