{
  "type": "Feature",
  "properties": {
    "iso:country":"GB",
    "wof:name":"W11 3SB",
    "wof:placetype":"postalcode"
},
  "geometry": {"coordinates":[-0.20906978792392,51.50555690961704],"type":"Point"}
}