{
  "type": "Feature",
  "properties": {
    "iso:country":"GB",
    "wof:name":"EH48 3LQ",
    "wof:placetype":"postalcode"
},
  "geometry": {"coordinates":[-3.69900720793722,55.88857028169814],"type":"Point"}
}