{
  "type": "Feature",
  "properties": {
    "iso:country":"GB",
    "wof:name":"SA62 5HZ",
    "wof:placetype":"postalcode"
},
  "geometry": {"coordinates":[-5.08251483046341,51.92728923362347],"type":"Point"}
}