{
  "type": "Feature",
  "properties": {
    "date:inception_lower": "1993-08-01",
    "date:inception_upper": "1993-08-01",
    "iso:country": "GB",
    "wof:name": "NW9 9AE",
    "wof:placetype": "postalcode"
  },
  "geometry": {"coordinates":[-0.266058,51.588777],"type":"Point"}
}
