{
  "type": "Feature",
  "properties": {
    "iso:country": "GB",
    "wof:name": "CB6 1DG",
    "wof:placetype": "postalcode"
  },
  "geometry": {"coordinates":[0.267982,52.407273],"type":"Point"}
}
