{
  "type": "Feature",
  "properties": {
    "iso:country":"GB",
    "wof:name":"CB6 1DG",
    "wof:placetype":"postalcode"
},
  "geometry": {"coordinates":[0.26812531457229,52.40736164624374],"type":"Point"}
}