{
  "type": "Feature",
  "properties": {
    "date:inception_lower": "1980-01-01",
    "date:inception_upper": "1980-01-01",
    "iso:country": "GB",
    "wof:name": "CB6 1DG",
    "wof:placetype": "postalcode"
  },
  "geometry": {"coordinates":[0.267982,52.407273],"type":"Point"}
}
