{
  "type": "Feature",
  "properties": {
    "iso:country":"GB",
    "wof:name":"PL26 7RZ",
    "wof:placetype":"postalcode"
},
  "geometry": {"coordinates":[-4.90176194509455,50.34853731723883],"type":"Point"}
}