{
  "type": "Feature",
  "properties": {
    "iso:country":"GB",
    "wof:name":"W1G 0HY",
    "wof:placetype":"postalcode"
},
  "geometry": {"coordinates":[-0.14272257504142,51.51597246884452],"type":"Point"}
}