{
  "type": "Feature",
  "properties": {
    "iso:country": "GB",
    "wof:name": "LL41 3AN",
    "wof:placetype": "postalcode"
  },
  "geometry": {"coordinates":[-3.93177,52.993885],"type":"Point"}
}
