{
  "type": "Feature",
  "properties": {
    "iso:country":"GB",
    "wof:name":"LL41 3AN",
    "wof:placetype":"postalcode"
},
  "geometry": {"coordinates":[-3.93177052103484,52.99388466868486],"type":"Point"}
}