{
  "type": "Feature",
  "properties": {
    "date:inception_lower": "1996-06-01",
    "date:inception_upper": "1996-06-01",
    "iso:country": "GB",
    "wof:name": "GU46 6XE",
    "wof:placetype": "postalcode"
  },
  "geometry": {"coordinates":[-0.82106,51.340766],"type":"Point"}
}
