{
  "type": "Feature",
  "properties": {
    "iso:country": "GB",
    "wof:name": "PE2 8JQ",
    "wof:placetype": "postalcode"
  },
  "geometry": {"coordinates":[-0.225772,52.544864],"type":"Point"}
}
