{
  "type": "Feature",
  "properties": {
    "iso:country":"GB",
    "wof:name":"PE2 8JQ",
    "wof:placetype":"postalcode"
},
  "geometry": {"coordinates":[-0.22577232189411,52.54486444058087],"type":"Point"}
}