{
  "type": "Feature",
  "properties": {
    "iso:country":"GB",
    "wof:name":"BA2 8AE",
    "wof:placetype":"postalcode"
},
  "geometry": {"coordinates":[-2.43419584239479,51.3178174600877],"type":"Point"}
}