{
  "type": "Feature",
  "properties": {
    "iso:country": "GB",
    "wof:name": "BA2 8AE",
    "wof:placetype": "postalcode"
  },
  "geometry": {"coordinates":[-2.434153,51.317823],"type":"Point"}
}
