{
  "type": "Feature",
  "properties": {
    "date:inception_lower": "1980-01-01",
    "date:inception_upper": "1980-01-01",
    "iso:country": "GB",
    "wof:name": "RG8 0AB",
    "wof:placetype": "postalcode"
  },
  "geometry": {"coordinates":[-1.132873,51.523207],"type":"Point"}
}
