{
  "type": "Feature",
  "properties": {
    "iso:country":"GB",
    "wof:name":"RG8 0AB",
    "wof:placetype":"postalcode"
},
  "geometry": {"coordinates":[-1.13287266395059,51.52320715972851],"type":"Point"}
}