{
  "type": "Feature",
  "properties": {
    "iso:country":"GB",
    "wof:name":"M23 0JB",
    "wof:placetype":"postalcode"
},
  "geometry": {"coordinates":[-2.2922145777599,53.41108792594983],"type":"Point"}
}