{
  "type": "Feature",
  "properties": {
    "date:inception_lower": "1980-01-01",
    "date:inception_upper": "1980-01-01",
    "iso:country": "GB",
    "wof:name": "M23 0JB",
    "wof:placetype": "postalcode"
  },
  "geometry": {"coordinates":[-2.292215,53.411088],"type":"Point"}
}
