{
  "type": "Feature",
  "properties": {
    "iso:country": "GB",
    "wof:name": "WS1 1EN",
    "wof:placetype": "postalcode"
  },
  "geometry": {"coordinates":[-1.97848,52.588576],"type":"Point"}
}
