{
  "type": "Feature",
  "properties": {
    "date:inception_lower": "2010-04-01",
    "date:inception_upper": "2010-04-01",
    "iso:country": "GB",
    "wof:name": "CF36 3LU",
    "wof:placetype": "postalcode"
  },
  "geometry": {"coordinates":[-3.708419,51.476485],"type":"Point"}
}
