{
  "type": "Feature",
  "properties": {
    "iso:country": "GB",
    "wof:name": "CF36 3LU",
    "wof:placetype": "postalcode"
  },
  "geometry": {"coordinates":[-3.708419,51.476485],"type":"Point"}
}
