{
  "type": "Feature",
  "properties": {
    "date:inception_lower": "1980-01-01",
    "date:inception_upper": "1980-01-01",
    "iso:country": "GB",
    "wof:name": "WS2 8RX",
    "wof:placetype": "postalcode"
  },
  "geometry": {"coordinates":[-2.002761,52.589117],"type":"Point"}
}
