{
  "type": "Feature",
  "properties": {
    "iso:country":"GB",
    "wof:name":"WS2 8RX",
    "wof:placetype":"postalcode"
},
  "geometry": {"coordinates":[-2.00276128254698,52.58911726711659],"type":"Point"}
}