{
  "type": "Feature",
  "properties": {
    "iso:country":"GB",
    "wof:name":"BA1 2TU",
    "wof:placetype":"postalcode"
},
  "geometry": {"coordinates":[-2.36836953586698,51.38852032263289],"type":"Point"}
}