{
  "type": "Feature",
  "properties": {
    "iso:country":"GB",
    "wof:name":"W11 1EH",
    "wof:placetype":"postalcode"
},
  "geometry": {"coordinates":[-0.20646887984204,51.51674871675631],"type":"Point"}
}