{
  "type": "Feature",
  "properties": {
    "date:inception_lower": "2023-11-01",
    "date:inception_upper": "2023-11-01",
    "iso:country": "GB",
    "wof:name": "HU18 1FD",
    "wof:placetype": "postalcode"
  },
  "geometry": {"coordinates":[-0.171962,53.909296],"type":"Point"}
}
