{
  "type": "Feature",
  "properties": {
    "iso:country": "GB",
    "wof:name": "M31 4GR",
    "wof:placetype": "postalcode"
  },
  "geometry": {"coordinates":[-2.440402,53.416107],"type":"Point"}
}
