{
  "type": "Feature",
  "properties": {
    "date:inception_lower": "1994-05-01",
    "date:inception_upper": "1994-05-01",
    "iso:country": "GB",
    "wof:name": "M31 4GR",
    "wof:placetype": "postalcode"
  },
  "geometry": {"coordinates":[-2.440402,53.416107],"type":"Point"}
}
