{
  "type": "Feature",
  "properties": {
    "iso:country":"GB",
    "wof:name":"M31 4GR",
    "wof:placetype":"postalcode"
},
  "geometry": {"coordinates":[-2.44040228537124,53.41610714120346],"type":"Point"}
}