{
  "type": "Feature",
  "properties": {
    "iso:country":"GB",
    "wof:name":"NE19 2RU",
    "wof:placetype":"postalcode"
},
  "geometry": {"coordinates":[-2.00607486136128,55.15347630184317],"type":"Point"}
}