{
  "type": "Feature",
  "properties": {
    "iso:country":"GB",
    "wof:name":"CH65 9EY",
    "wof:placetype":"postalcode"
},
  "geometry": {"coordinates":[-2.89197669293456,53.26748963170535],"type":"Point"}
}