{
  "type": "Feature",
  "properties": {
    "iso:country":"GB",
    "wof:name":"L26 1TH",
    "wof:placetype":"postalcode"
},
  "geometry": {"coordinates":[-2.8433025288127,53.36013362254015],"type":"Point"}
}