{
  "type": "Feature",
  "properties": {
    "iso:country":"GB",
    "wof:name":"EX39 4QG",
    "wof:placetype":"postalcode"
},
  "geometry": {"coordinates":[-4.14104407990599,50.99935879105415],"type":"Point"}
}