{
  "type": "Feature",
  "properties": {
    "iso:country": "GB",
    "wof:name": "EX39 4QG",
    "wof:placetype": "postalcode"
  },
  "geometry": {"coordinates":[-4.14324,50.99542],"type":"Point"}
}
