{
  "type": "Feature",
  "properties": {
    "iso:country":"GB",
    "wof:name":"YO24 2TD",
    "wof:placetype":"postalcode"
},
  "geometry": {"coordinates":[-1.1187112132153,53.94199371142518],"type":"Point"}
}