{
  "type": "Feature",
  "properties": {
    "iso:country":"GB",
    "wof:name":"LA12 8QU",
    "wof:placetype":"postalcode"
},
  "geometry": {"coordinates":[-2.9872444385575,54.25013434191423],"type":"Point"}
}