{
  "type": "Feature",
  "properties": {
    "iso:country": "GB",
    "wof:name": "LA12 8QU",
    "wof:placetype": "postalcode"
  },
  "geometry": {"coordinates":[-2.987167,54.250126],"type":"Point"}
}
