{
  "type": "Feature",
  "properties": {
    "iso:country":"GB",
    "wof:name":"W3 9SS",
    "wof:placetype":"postalcode"
},
  "geometry": {"coordinates":[-0.28374262700511,51.51122349585667],"type":"Point"}
}