{
  "type": "Feature",
  "properties": {
    "date:inception_lower": "1980-01-01",
    "date:inception_upper": "1980-01-01",
    "iso:country": "GB",
    "wof:name": "B31 4QN",
    "wof:placetype": "postalcode"
  },
  "geometry": {"coordinates":[-1.97396,52.393359],"type":"Point"}
}
