{
  "type": "Feature",
  "properties": {
    "iso:country":"GB",
    "wof:name":"B31 4QN",
    "wof:placetype":"postalcode"
},
  "geometry": {"coordinates":[-1.97395988672837,52.39335853802727],"type":"Point"}
}