{
  "type": "Feature",
  "properties": {
    "date:inception_lower": "1995-12-01",
    "date:inception_upper": "1995-12-01",
    "iso:country": "GB",
    "wof:name": "BR3 6QP",
    "wof:placetype": "postalcode"
  },
  "geometry": {"coordinates":[-0.016016,51.403143],"type":"Point"}
}
