{
  "type": "Feature",
  "properties": {
    "iso:country":"GB",
    "wof:name":"DL12 8LG",
    "wof:placetype":"postalcode"
},
  "geometry": {"coordinates":[-1.9092276629553,54.54599939322907],"type":"Point"}
}