{
  "type": "Feature",
  "properties": {
    "date:inception_lower": "1980-01-01",
    "date:inception_upper": "1980-01-01",
    "iso:country": "GB",
    "wof:name": "DL12 8LG",
    "wof:placetype": "postalcode"
  },
  "geometry": {"coordinates":[-1.909228,54.545999],"type":"Point"}
}
