{
  "type": "Feature",
  "properties": {
    "date:inception_lower":"2007-08-01",
    "date:inception_upper":"2007-08-31",
    "iso:country":"GB",
    "wof:name":"EC3M 3AJ",
    "wof:placetype":"postalcode"
},
  "geometry": {"coordinates":[-0.082262,51.511133],"type":"Point"}
}