{
  "type": "Feature",
  "properties": {
    "date:inception_lower": "1980-01-01",
    "date:inception_upper": "1980-01-01",
    "iso:country": "GB",
    "wof:name": "CT21 6HN",
    "wof:placetype": "postalcode"
  },
  "geometry": {"coordinates":[1.079822,51.065819],"type":"Point"}
}
