{
  "type": "Feature",
  "properties": {
    "iso:country":"GB",
    "wof:name":"DT4 7ET",
    "wof:placetype":"postalcode"
},
  "geometry": {"coordinates":[-2.45229425497135,50.61622004024278],"type":"Point"}
}