{
  "type": "Feature",
  "properties": {
    "date:inception_lower":"1980-01-01",
    "date:inception_upper":"1980-01-31",
    "iso:country":"GB",
    "wof:name":"DT4 7ET",
    "wof:placetype":"postalcode"
},
  "geometry": {"coordinates":[-2.452294,50.61622],"type":"Point"}
}