{
  "type": "Feature",
  "properties": {
    "iso:country":"GB",
    "wof:name":"HX3 0HP",
    "wof:placetype":"postalcode"
},
  "geometry": {"coordinates":[-1.87608657912275,53.7078618306354],"type":"Point"}
}