{
  "type": "Feature",
  "properties": {
    "iso:country": "GB",
    "wof:name": "HX3 0HP",
    "wof:placetype": "postalcode"
  },
  "geometry": {"coordinates":[-1.876087,53.707862],"type":"Point"}
}
