{
  "type": "Feature",
  "properties": {
    "date:inception_lower": "2000-12-01",
    "date:inception_upper": "2000-12-01",
    "iso:country": "GB",
    "wof:name": "TN13 1YD",
    "wof:placetype": "postalcode"
  },
  "geometry": {"coordinates":[0.190049,51.271607],"type":"Point"}
}
