{
  "type": "Feature",
  "properties": {
    "iso:country":"GB",
    "wof:name":"IP17 1LA",
    "wof:placetype":"postalcode"
},
  "geometry": {"coordinates":[1.45519891013004,52.18795104853051],"type":"Point"}
}