{
  "type": "Feature",
  "properties": {
    "iso:country": "GB",
    "wof:name": "SY11 2BL",
    "wof:placetype": "postalcode"
  },
  "geometry": {"coordinates":[-3.057193,52.854357],"type":"Point"}
}
