{
  "type": "Feature",
  "properties": {
    "iso:country":"GB",
    "wof:name":"SY11 2BL",
    "wof:placetype":"postalcode"
},
  "geometry": {"coordinates":[-3.05719354377376,52.85435697131339],"type":"Point"}
}