{
  "type": "Feature",
  "properties": {
    "iso:country":"GB",
    "wof:name":"LS29 8PW",
    "wof:placetype":"postalcode"
},
  "geometry": {"coordinates":[-1.79839938515344,53.92364691046393],"type":"Point"}
}