{
  "type": "Feature",
  "properties": {
    "iso:country":"GB",
    "wof:name":"BL3 4ES",
    "wof:placetype":"postalcode"
},
  "geometry": {"coordinates":[-2.46176173917148,53.56678160406572],"type":"Point"}
}