{
  "type": "Feature",
  "properties": {
    "iso:country": "GB",
    "wof:name": "DG8 7BJ",
    "wof:placetype": "postalcode"
  },
  "geometry": {"coordinates":[-4.383428,54.997767],"type":"Point"}
}
