{
  "type": "Feature",
  "properties": {
    "iso:country":"GB",
    "wof:name":"BS21 5DB",
    "wof:placetype":"postalcode"
},
  "geometry": {"coordinates":[-2.85315983990241,51.42651875208879],"type":"Point"}
}