{
  "type": "Feature",
  "properties": {
    "date:inception_lower": "1983-01-01",
    "date:inception_upper": "1983-01-01",
    "iso:country": "GB",
    "wof:name": "BS21 5DB",
    "wof:placetype": "postalcode"
  },
  "geometry": {"coordinates":[-2.853179,51.426508],"type":"Point"}
}
