{
  "type": "Feature",
  "properties": {
    "iso:country":"GB",
    "wof:name":"PL1 3SH",
    "wof:placetype":"postalcode"
},
  "geometry": {"coordinates":[-4.16232247395275,50.37008930586053],"type":"Point"}
}