{
  "type": "Feature",
  "properties": {
    "iso:country":"GB",
    "wof:name":"BS16 9JF",
    "wof:placetype":"postalcode"
},
  "geometry": {"coordinates":[-2.48561085756654,51.48218136255425],"type":"Point"}
}