{
  "type": "Feature",
  "properties": {
    "date:inception_lower":"1997-12-01",
    "date:inception_upper":"1997-12-31",
    "iso:country":"GB",
    "wof:name":"BS16 9JF",
    "wof:placetype":"postalcode"
},
  "geometry": {"coordinates":[-2.485611,51.482181],"type":"Point"}
}