{
  "type": "Feature",
  "properties": {
    "date:inception_lower": "1996-12-01",
    "date:inception_upper": "1996-12-01",
    "iso:country": "GB",
    "wof:name": "SK23 0NR",
    "wof:placetype": "postalcode"
  },
  "geometry": {"coordinates":[-1.907336,53.320776],"type":"Point"}
}
