{
  "type": "Feature",
  "properties": {
    "iso:country": "GB",
    "wof:name": "SK23 0NR",
    "wof:placetype": "postalcode"
  },
  "geometry": {"coordinates":[-1.90666,53.320991],"type":"Point"}
}
