{
  "type": "Feature",
  "properties": {
    "iso:country":"GB",
    "wof:name":"IP27 0DQ",
    "wof:placetype":"postalcode"
},
  "geometry": {"coordinates":[0.63733458277097,52.44716077925877],"type":"Point"}
}