{
  "type": "Feature",
  "properties": {
    "iso:country":"GB",
    "wof:name":"DL13 3BE",
    "wof:placetype":"postalcode"
},
  "geometry": {"coordinates":[-1.88142213990124,54.72614980524877],"type":"Point"}
}