{
  "type": "Feature",
  "properties": {
    "iso:country": "GB",
    "wof:name": "DL13 3BE",
    "wof:placetype": "postalcode"
  },
  "geometry": {"coordinates":[-1.881422,54.72615],"type":"Point"}
}
