{
  "type": "Feature",
  "properties": {
    "iso:country": "GB",
    "wof:name": "PE7 3XF",
    "wof:placetype": "postalcode"
  },
  "geometry": {"coordinates":[-0.29115,52.490892],"type":"Point"}
}
