{
  "type": "Feature",
  "properties": {
    "iso:country":"GB",
    "wof:name":"PE7 3XF",
    "wof:placetype":"postalcode"
},
  "geometry": {"coordinates":[-0.29114967503204,52.49089170323037],"type":"Point"}
}