{
  "type": "Feature",
  "properties": {
    "iso:country":"GB",
    "wof:name":"DN8 4PE",
    "wof:placetype":"postalcode"
},
  "geometry": {"coordinates":[-0.94847660495176,53.63124273809604],"type":"Point"}
}