{
  "type": "Feature",
  "properties": {
    "iso:country":"GB",
    "wof:name":"BB4 5UE",
    "wof:placetype":"postalcode"
},
  "geometry": {"coordinates":[-2.33193104760402,53.71952718467587],"type":"Point"}
}