{
  "type": "Feature",
  "properties": {
    "date:inception_lower": "2016-08-01",
    "date:inception_upper": "2016-08-01",
    "iso:country": "GB",
    "wof:name": "PE3 6GX",
    "wof:placetype": "postalcode"
  },
  "geometry": {"coordinates":[-0.259999,52.574783],"type":"Point"}
}
