{
  "type": "Feature",
  "properties": {
    "iso:country": "GB",
    "wof:name": "PE3 6GX",
    "wof:placetype": "postalcode"
  },
  "geometry": {"coordinates":[-0.259999,52.574783],"type":"Point"}
}
