{
  "type": "Feature",
  "properties": {
    "iso:country": "GB",
    "wof:name": "SN5 7YT",
    "wof:placetype": "postalcode"
  },
  "geometry": {"coordinates":[-1.815816,51.564256],"type":"Point"}
}
