{
  "type": "Feature",
  "properties": {
    "iso:country": "GB",
    "wof:name": "PH11 8HH",
    "wof:placetype": "postalcode"
  },
  "geometry": {"coordinates":[-3.214329,56.641438],"type":"Point"}
}
