{
  "type": "Feature",
  "properties": {
    "date:inception_lower":"1980-01-01",
    "date:inception_upper":"1980-01-31",
    "iso:country":"GB",
    "wof:name":"PH11 8HH",
    "wof:placetype":"postalcode"
},
  "geometry": {"coordinates":[-3.214329,56.641438],"type":"Point"}
}