{
  "type": "Feature",
  "properties": {
    "date:inception_lower": "2021-05-01",
    "date:inception_upper": "2021-05-01",
    "iso:country": "GB",
    "wof:name": "IP22 1FL",
    "wof:placetype": "postalcode"
  },
  "geometry": {"coordinates":[0.953305,52.356044],"type":"Point"}
}
