{
  "type": "Feature",
  "properties": {
    "iso:country":"GB",
    "wof:name":"CO2 8RG",
    "wof:placetype":"postalcode"
},
  "geometry": {"coordinates":[0.90241482249955,51.85904562792657],"type":"Point"}
}