{
  "type": "Feature",
  "properties": {
    "date:inception_lower": "1980-01-01",
    "date:inception_upper": "1980-01-01",
    "iso:country": "GB",
    "wof:name": "DY2 9DL",
    "wof:placetype": "postalcode"
  },
  "geometry": {"coordinates":[-2.082044,52.496331],"type":"Point"}
}
