{
  "type": "Feature",
  "properties": {
    "iso:country":"GB",
    "wof:name":"DA9 9NN",
    "wof:placetype":"postalcode"
},
  "geometry": {"coordinates":[0.28230057153157,51.45316375566858],"type":"Point"}
}