{
  "type": "Feature",
  "properties": {
    "iso:country": "GB",
    "wof:name": "LE12 5LF",
    "wof:placetype": "postalcode"
  },
  "geometry": {"coordinates":[-1.255579,52.797537],"type":"Point"}
}
