{
  "type": "Feature",
  "properties": {
    "iso:country":"GB",
    "wof:name":"LE12 5LF",
    "wof:placetype":"postalcode"
},
  "geometry": {"coordinates":[-1.2555792104717,52.79753710973111],"type":"Point"}
}