{
  "type": "Feature",
  "properties": {
    "iso:country":"GB",
    "wof:name":"LS27 9EY",
    "wof:placetype":"postalcode"
},
  "geometry": {"coordinates":[-1.59654364154672,53.74026063968961],"type":"Point"}
}