{
  "type": "Feature",
  "properties": {
    "date:inception_lower": "2017-08-01",
    "date:inception_upper": "2017-08-01",
    "iso:country": "GB",
    "wof:name": "EX7 0GA",
    "wof:placetype": "postalcode"
  },
  "geometry": {"coordinates":[-3.457458,50.600781],"type":"Point"}
}
