{
  "type": "Feature",
  "properties": {
    "iso:country": "GB",
    "wof:name": "WS7 2AL",
    "wof:placetype": "postalcode"
  },
  "geometry": {"coordinates":[-1.932106,52.682402],"type":"Point"}
}
