{
  "type": "Feature",
  "properties": {
    "iso:country":"GB",
    "wof:name":"WS7 2AL",
    "wof:placetype":"postalcode"
},
  "geometry": {"coordinates":[-1.9321059941009,52.68240231528682],"type":"Point"}
}