{
  "type": "Feature",
  "properties": {
    "date:inception_lower": "1990-08-01",
    "date:inception_upper": "1990-08-01",
    "iso:country": "GB",
    "wof:name": "AB34 4XS",
    "wof:placetype": "postalcode"
  },
  "geometry": {"coordinates":[-2.932787,57.158086],"type":"Point"}
}
