{
  "type": "Feature",
  "properties": {
    "iso:country":"GB",
    "wof:name":"BR1 3LG",
    "wof:placetype":"postalcode"
},
  "geometry": {"coordinates":[0.02185381452611,51.40997786750429],"type":"Point"}
}