{
  "type": "Feature",
  "properties": {
    "iso:country":"GB",
    "wof:name":"SW2 5HB",
    "wof:placetype":"postalcode"
},
  "geometry": {"coordinates":[-0.1220770671635,51.45442233925421],"type":"Point"}
}