{
  "type": "Feature",
  "properties": {
    "iso:country": "GB",
    "wof:name": "SW2 5HB",
    "wof:placetype": "postalcode"
  },
  "geometry": {"coordinates":[-0.122077,51.454422],"type":"Point"}
}
