{
  "type": "Feature",
  "properties": {
    "date:inception_lower": "2023-01-01",
    "date:inception_upper": "2023-01-01",
    "iso:country": "GB",
    "wof:name": "G66 1FE",
    "wof:placetype": "postalcode"
  },
  "geometry": {"coordinates":[-4.171116,55.937357],"type":"Point"}
}
