{
  "type": "Feature",
  "properties": {
    "iso:country":"GB",
    "wof:name":"EX8 3AQ",
    "wof:placetype":"postalcode"
},
  "geometry": {"coordinates":[-3.40140530023349,50.62941449636961],"type":"Point"}
}