{
  "type": "Feature",
  "properties": {
    "iso:country":"GB",
    "wof:name":"PH11 8NZ",
    "wof:placetype":"postalcode"
},
  "geometry": {"coordinates":[-3.210928130531,56.59695509058684],"type":"Point"}
}