{
  "type": "Feature",
  "properties": {
    "iso:country":"GB",
    "wof:name":"M7 3PZ",
    "wof:placetype":"postalcode"
},
  "geometry": {"coordinates":[-2.27835362394563,53.51374269319818],"type":"Point"}
}