{
  "type": "Feature",
  "properties": {
    "iso:country": "GB",
    "wof:name": "SO19 6EG",
    "wof:placetype": "postalcode"
  },
  "geometry": {"coordinates":[-1.337379,50.910259],"type":"Point"}
}
