{
  "type": "Feature",
  "properties": {
    "iso:country":"GB",
    "wof:name":"CA3 9NQ",
    "wof:placetype":"postalcode"
},
  "geometry": {"coordinates":[-2.94067288319951,54.9032638713492],"type":"Point"}
}