{
  "type": "Feature",
  "properties": {
    "iso:country": "GB",
    "wof:name": "LN10 6TG",
    "wof:placetype": "postalcode"
  },
  "geometry": {"coordinates":[-0.211051,53.14997],"type":"Point"}
}
