{
  "type": "Feature",
  "properties": {
    "date:inception_lower": "1980-01-01",
    "date:inception_upper": "1980-01-01",
    "iso:country": "GB",
    "wof:name": "LN10 6TG",
    "wof:placetype": "postalcode"
  },
  "geometry": {"coordinates":[-0.211051,53.14997],"type":"Point"}
}
