{
  "type": "Feature",
  "properties": {
    "iso:country":"GB",
    "wof:name":"SE12 8JQ",
    "wof:placetype":"postalcode"
},
  "geometry": {"coordinates":[0.02247070515194,51.45750321058854],"type":"Point"}
}