{
  "type": "Feature",
  "properties": {
    "iso:country": "GB",
    "wof:name": "MK19 7EW",
    "wof:placetype": "postalcode"
  },
  "geometry": {"coordinates":[-0.833932,52.093038],"type":"Point"}
}
