{
  "type": "Feature",
  "properties": {
    "date:inception_lower": "1980-01-01",
    "date:inception_upper": "1980-01-01",
    "iso:country": "GB",
    "wof:name": "PO21 4XR",
    "wof:placetype": "postalcode"
  },
  "geometry": {"coordinates":[-0.705794,50.779057],"type":"Point"}
}
