{
  "type": "Feature",
  "properties": {
    "iso:country":"GB",
    "wof:name":"W1W 7DJ",
    "wof:placetype":"postalcode"
},
  "geometry": {"coordinates":[-0.13984969154609,51.51927215270654],"type":"Point"}
}