{
  "type": "Feature",
  "properties": {
    "iso:country": "GB",
    "wof:name": "SK17 0NU",
    "wof:placetype": "postalcode"
  },
  "geometry": {"coordinates":[-1.868971,53.181614],"type":"Point"}
}
