{
  "type": "Feature",
  "properties": {
    "iso:country":"GB",
    "wof:name":"SK17 0NU",
    "wof:placetype":"postalcode"
},
  "geometry": {"coordinates":[-1.86897146502144,53.18161378743292],"type":"Point"}
}