{
  "type": "Feature",
  "properties": {
    "date:inception_lower": "2020-12-01",
    "date:inception_upper": "2020-12-01",
    "iso:country": "GB",
    "wof:name": "SG9 0FD",
    "wof:placetype": "postalcode"
  },
  "geometry": {"coordinates":[0.035753,51.981839],"type":"Point"}
}
