{
  "type": "Feature",
  "properties": {
    "date:inception_lower": "1980-01-01",
    "date:inception_upper": "1980-01-01",
    "iso:country": "GB",
    "wof:name": "PO4 0NZ",
    "wof:placetype": "postalcode"
  },
  "geometry": {"coordinates":[-1.074282,50.781915],"type":"Point"}
}
