{
  "type": "Feature",
  "properties": {
    "iso:country":"GB",
    "wof:name":"PO4 0NZ",
    "wof:placetype":"postalcode"
},
  "geometry": {"coordinates":[-1.07428170657073,50.78191507905041],"type":"Point"}
}