{
  "type": "Feature",
  "properties": {
    "iso:country":"GB",
    "wof:name":"WA8 9PD",
    "wof:placetype":"postalcode"
},
  "geometry": {"coordinates":[-2.75009806329578,53.38251789854929],"type":"Point"}
}