{
  "type": "Feature",
  "properties": {
    "iso:country": "GB",
    "wof:name": "WA8 9PD",
    "wof:placetype": "postalcode"
  },
  "geometry": {"coordinates":[-2.750098,53.382518],"type":"Point"}
}
