{
  "type": "Feature",
  "properties": {
    "date:inception_lower": "1980-01-01",
    "date:inception_upper": "1980-01-01",
    "iso:country": "GB",
    "wof:name": "PO13 0LS",
    "wof:placetype": "postalcode"
  },
  "geometry": {"coordinates":[-1.1691,50.819112],"type":"Point"}
}
