{
  "type": "Feature",
  "properties": {
    "iso:country":"GB",
    "wof:name":"CB2 9AS",
    "wof:placetype":"postalcode"
},
  "geometry": {"coordinates":[0.11969754241922,52.16831842023754],"type":"Point"}
}