{
  "type": "Feature",
  "properties": {
    "iso:country": "GB",
    "wof:name": "CB2 9AS",
    "wof:placetype": "postalcode"
  },
  "geometry": {"coordinates":[0.119488,52.16856],"type":"Point"}
}
