{
  "type": "Feature",
  "properties": {
    "date:inception_lower": "1996-12-01",
    "date:inception_upper": "1996-12-01",
    "iso:country": "GB",
    "wof:name": "BD18 1QF",
    "wof:placetype": "postalcode"
  },
  "geometry": {"coordinates":[-1.76556,53.835425],"type":"Point"}
}
