{
  "type": "Feature",
  "properties": {
    "iso:country": "GB",
    "wof:name": "SW19 6RX",
    "wof:placetype": "postalcode"
  },
  "geometry": {"coordinates":[-0.220162,51.449415],"type":"Point"}
}
