{
  "type": "Feature",
  "properties": {
    "iso:country":"GB",
    "wof:name":"SW19 6RX",
    "wof:placetype":"postalcode"
},
  "geometry": {"coordinates":[-0.22016157578133,51.44941492655268],"type":"Point"}
}