{
  "type": "Feature",
  "properties": {
    "date:inception_lower": "2017-08-01",
    "date:inception_upper": "2017-08-01",
    "iso:country": "GB",
    "wof:name": "WD5 0PA",
    "wof:placetype": "postalcode"
  },
  "geometry": {"coordinates":[-0.408566,51.704835],"type":"Point"}
}
