{
  "type": "Feature",
  "properties": {
    "date:inception_lower":"1980-01-01",
    "date:inception_upper":"1980-01-31",
    "iso:country":"GB",
    "wof:name":"WV14 0LZ",
    "wof:placetype":"postalcode"
},
  "geometry": {"coordinates":[-2.086692,52.567618],"type":"Point"}
}