{
  "type": "Feature",
  "properties": {
    "iso:country":"GB",
    "wof:name":"WV14 0LZ",
    "wof:placetype":"postalcode"
},
  "geometry": {"coordinates":[-2.08669203898768,52.56761771839198],"type":"Point"}
}