{
  "type": "Feature",
  "properties": {
    "iso:country":"GB",
    "wof:name":"DN22 7SW",
    "wof:placetype":"postalcode"
},
  "geometry": {"coordinates":[-0.95014661636837,53.31531609063789],"type":"Point"}
}