{
  "type": "Feature",
  "properties": {
    "iso:country": "GB",
    "wof:name": "ZE1 0FN",
    "wof:placetype": "postalcode"
  },
  "geometry": {"coordinates":[-1.139962,60.152592],"type":"Point"}
}
