{
  "type": "Feature",
  "properties": {
    "date:inception_lower":"2001-06-01",
    "date:inception_upper":"2001-06-30",
    "iso:country":"GB",
    "wof:name":"ZE1 0FN",
    "wof:placetype":"postalcode"
},
  "geometry": {"coordinates":[-1.139962,60.152592],"type":"Point"}
}