{
  "type": "Feature",
  "properties": {
    "iso:country":"GB",
    "wof:name":"ZE1 0FN",
    "wof:placetype":"postalcode"
},
  "geometry": {"coordinates":[-1.13995497417896,60.15258252227861],"type":"Point"}
}