{
  "type": "Feature",
  "properties": {
    "iso:country":"GB",
    "wof:name":"M30 8UW",
    "wof:placetype":"postalcode"
},
  "geometry": {"coordinates":[-2.3589071675614,53.49184768913413],"type":"Point"}
}