{
  "type": "Feature",
  "properties": {
    "date:inception_lower":"1995-07-01",
    "date:inception_upper":"1995-07-31",
    "iso:country":"GB",
    "wof:name":"M30 8UW",
    "wof:placetype":"postalcode"
},
  "geometry": {"coordinates":[-2.358907,53.491848],"type":"Point"}
}