{
  "type": "Feature",
  "properties": {
    "date:inception_lower": "1980-01-01",
    "date:inception_upper": "1980-01-01",
    "iso:country": "GB",
    "wof:name": "ST1 5JP",
    "wof:placetype": "postalcode"
  },
  "geometry": {"coordinates":[-2.187788,53.033003],"type":"Point"}
}
