{
  "type": "Feature",
  "properties": {
    "iso:country": "GB",
    "wof:name": "ST1 5JP",
    "wof:placetype": "postalcode"
  },
  "geometry": {"coordinates":[-2.187788,53.033003],"type":"Point"}
}
