{
  "type": "Feature",
  "properties": {
    "iso:country":"GB",
    "wof:name":"DH9 6PY",
    "wof:placetype":"postalcode"
},
  "geometry": {"coordinates":[-1.69833760909502,54.86539328556723],"type":"Point"}
}