{
  "type": "Feature",
  "properties": {
    "iso:country":"GB",
    "wof:name":"DA14 6TU",
    "wof:placetype":"postalcode"
},
  "geometry": {"coordinates":[0.09727568842764,51.42347257285822],"type":"Point"}
}