{
  "type": "Feature",
  "properties": {
    "date:inception_lower":"1981-06-01",
    "date:inception_upper":"1981-06-30",
    "iso:country":"GB",
    "wof:name":"DE7 9HZ",
    "wof:placetype":"postalcode"
},
  "geometry": {"coordinates":[-1.323588,52.984314],"type":"Point"}
}