{
  "type": "Feature",
  "properties": {
    "iso:country":"GB",
    "wof:name":"EN4 8JR",
    "wof:placetype":"postalcode"
},
  "geometry": {"coordinates":[-0.14788305771316,51.63594989107689],"type":"Point"}
}