{
  "type": "Feature",
  "properties": {
    "date:inception_lower": "1980-01-01",
    "date:inception_upper": "1980-01-01",
    "iso:country": "GB",
    "wof:name": "CA28 9UX",
    "wof:placetype": "postalcode"
  },
  "geometry": {"coordinates":[-3.626683,54.515984],"type":"Point"}
}
