{
  "type": "Feature",
  "properties": {
    "iso:country":"GB",
    "wof:name":"CA28 9UX",
    "wof:placetype":"postalcode"
},
  "geometry": {"coordinates":[-3.62668256418911,54.5159835432386],"type":"Point"}
}