{
  "type": "Feature",
  "properties": {
    "iso:country":"GB",
    "wof:name":"LA13 9JW",
    "wof:placetype":"postalcode"
},
  "geometry": {"coordinates":[-3.20755066210358,54.13072705985955],"type":"Point"}
}