{
  "type": "Feature",
  "properties": {
    "iso:country": "GB",
    "wof:name": "SY23 1RG",
    "wof:placetype": "postalcode"
  },
  "geometry": {"coordinates":[-4.070687,52.402713],"type":"Point"}
}
