{
  "type": "Feature",
  "properties": {
    "iso:country": "GB",
    "wof:name": "RH13 8AW",
    "wof:placetype": "postalcode"
  },
  "geometry": {"coordinates":[-0.250371,50.998432],"type":"Point"}
}
