{
  "type": "Feature",
  "properties": {
    "iso:country": "GB",
    "wof:name": "OX7 6NA",
    "wof:placetype": "postalcode"
  },
  "geometry": {"coordinates":[-1.592763,51.917467],"type":"Point"}
}
