{
  "type": "Feature",
  "properties": {
    "iso:country": "GB",
    "wof:name": "SW16 4AS",
    "wof:placetype": "postalcode"
  },
  "geometry": {"coordinates":[-0.120944,51.405943],"type":"Point"}
}
