{
  "type": "Feature",
  "properties": {
    "iso:country":"GB",
    "wof:name":"EX22 7JU",
    "wof:placetype":"postalcode"
},
  "geometry": {"coordinates":[-4.4473380393769,50.82555648371218],"type":"Point"}
}