{
  "type": "Feature",
  "properties": {
    "iso:country": "GB",
    "wof:name": "EX22 7JU",
    "wof:placetype": "postalcode"
  },
  "geometry": {"coordinates":[-4.447369,50.825551],"type":"Point"}
}
