{
  "type": "Feature",
  "properties": {
    "date:inception_lower": "1980-01-01",
    "date:inception_upper": "1980-01-01",
    "iso:country": "GB",
    "wof:name": "DN15 7ES",
    "wof:placetype": "postalcode"
  },
  "geometry": {"coordinates":[-0.687717,53.588374],"type":"Point"}
}
