{
  "type": "Feature",
  "properties": {
    "iso:country":"GB",
    "wof:name":"DN15 7ES",
    "wof:placetype":"postalcode"
},
  "geometry": {"coordinates":[-0.68771264547016,53.58838002398788],"type":"Point"}
}