{
  "type": "Feature",
  "properties": {
    "iso:country":"GB",
    "wof:name":"DN3 1EX",
    "wof:placetype":"postalcode"
},
  "geometry": {"coordinates":[-1.07362699231698,53.57683477722195],"type":"Point"}
}