{
  "type": "Feature",
  "properties": {
    "iso:country": "GB",
    "wof:name": "CH7 6FX",
    "wof:placetype": "postalcode"
  },
  "geometry": {"coordinates":[-3.093777,53.179276],"type":"Point"}
}
