{
  "type": "Feature",
  "properties": {
    "iso:country":"GB",
    "wof:name":"SM5 3EP",
    "wof:placetype":"postalcode"
},
  "geometry": {"coordinates":[-0.16299169655124,51.35877753690806],"type":"Point"}
}