{
  "type": "Feature",
  "properties": {
    "iso:country":"GB",
    "wof:name":"RG1 5AY",
    "wof:placetype":"postalcode"
},
  "geometry": {"coordinates":[-0.94898594674614,51.45276392106117],"type":"Point"}
}