{
  "type": "Feature",
  "properties": {
    "iso:country": "GB",
    "wof:name": "RG1 5AY",
    "wof:placetype": "postalcode"
  },
  "geometry": {"coordinates":[-0.948986,51.452764],"type":"Point"}
}
