{
  "type": "Feature",
  "properties": {
    "iso:country":"GB",
    "wof:name":"WD3 0NA",
    "wof:placetype":"postalcode"
},
  "geometry": {"coordinates":[-0.47462328369852,51.63948020981128],"type":"Point"}
}