{
  "type": "Feature",
  "properties": {
    "date:inception_lower":"1995-07-01",
    "date:inception_upper":"1995-07-31",
    "iso:country":"GB",
    "wof:name":"RG20 7AU",
    "wof:placetype":"postalcode"
},
  "geometry": {"coordinates":[-1.335692,51.530923],"type":"Point"}
}