{
  "type": "Feature",
  "properties": {
    "iso:country":"GB",
    "wof:name":"RG20 7AU",
    "wof:placetype":"postalcode"
},
  "geometry": {"coordinates":[-1.33569184074853,51.53092349082313],"type":"Point"}
}