{
  "type": "Feature",
  "properties": {
    "iso:country":"GB",
    "wof:name":"DY2 0EH",
    "wof:placetype":"postalcode"
},
  "geometry": {"coordinates":[-2.09027061420335,52.47842628875826],"type":"Point"}
}