{
  "type": "Feature",
  "properties": {
    "date:inception_lower":"1980-01-01",
    "date:inception_upper":"1980-01-31",
    "iso:country":"GB",
    "wof:name":"ME20 6JT",
    "wof:placetype":"postalcode"
},
  "geometry": {"coordinates":[0.432557,51.300787],"type":"Point"}
}