{
  "type": "Feature",
  "properties": {
    "iso:country": "GB",
    "wof:name": "ME20 6JT",
    "wof:placetype": "postalcode"
  },
  "geometry": {"coordinates":[0.432557,51.300787],"type":"Point"}
}
