{
  "type": "Feature",
  "properties": {
    "date:inception_lower": "2023-09-01",
    "date:inception_upper": "2023-09-01",
    "iso:country": "GB",
    "wof:name": "TN38 9TY",
    "wof:placetype": "postalcode"
  },
  "geometry": {"coordinates":[0.53713,50.865316],"type":"Point"}
}
