{
  "type": "Feature",
  "properties": {
    "iso:country":"GB",
    "wof:name":"SR3 4PH",
    "wof:placetype":"postalcode"
},
  "geometry": {"coordinates":[-1.43750860837022,54.88217839054078],"type":"Point"}
}