{
  "type": "Feature",
  "properties": {
    "iso:country": "GB",
    "wof:name": "SR3 4PH",
    "wof:placetype": "postalcode"
  },
  "geometry": {"coordinates":[-1.437509,54.882178],"type":"Point"}
}
