{
  "type": "Feature",
  "properties": {
    "iso:country": "GB",
    "wof:name": "B4 7UL",
    "wof:placetype": "postalcode"
  },
  "geometry": {"coordinates":[-1.892105,52.478691],"type":"Point"}
}
