{
  "type": "Feature",
  "properties": {
    "iso:country": "GB",
    "wof:name": "TA7 0AU",
    "wof:placetype": "postalcode"
  },
  "geometry": {"coordinates":[-2.948695,51.0743],"type":"Point"}
}
