{
  "type": "Feature",
  "properties": {
    "iso:country": "GB",
    "wof:name": "PE38 9QU",
    "wof:placetype": "postalcode"
  },
  "geometry": {"coordinates":[0.389162,52.611665],"type":"Point"}
}
