{
  "type": "Feature",
  "properties": {
    "date:inception_lower": "1980-01-01",
    "date:inception_upper": "1980-01-01",
    "iso:country": "GB",
    "wof:name": "PE38 9QU",
    "wof:placetype": "postalcode"
  },
  "geometry": {"coordinates":[0.389162,52.611665],"type":"Point"}
}
