{
  "type": "Feature",
  "properties": {
    "iso:country":"GB",
    "wof:name":"PE38 9QU",
    "wof:placetype":"postalcode"
},
  "geometry": {"coordinates":[0.3891617305778,52.61166539984512],"type":"Point"}
}