{
  "type": "Feature",
  "properties": {
    "iso:country": "GB",
    "wof:name": "LA12 8DU",
    "wof:placetype": "postalcode"
  },
  "geometry": {"coordinates":[-3.07855,54.257764],"type":"Point"}
}
