{
  "type": "Feature",
  "properties": {
    "iso:country":"GB",
    "wof:name":"ML6 7RZ",
    "wof:placetype":"postalcode"
},
  "geometry": {"coordinates":[-3.90581504543758,55.89419581241741],"type":"Point"}
}