{
  "type": "Feature",
  "properties": {
    "date:inception_lower": "1980-01-01",
    "date:inception_upper": "1980-01-01",
    "iso:country": "GB",
    "wof:name": "PH1 3DA",
    "wof:placetype": "postalcode"
  },
  "geometry": {"coordinates":[-3.45076,56.416727],"type":"Point"}
}
