{
  "type": "Feature",
  "properties": {
    "iso:country": "GB",
    "wof:name": "PH1 3DA",
    "wof:placetype": "postalcode"
  },
  "geometry": {"coordinates":[-3.45076,56.416727],"type":"Point"}
}
