{
  "type": "Feature",
  "properties": {
    "iso:country":"GB",
    "wof:name":"CH46 3RG",
    "wof:placetype":"postalcode"
},
  "geometry": {"coordinates":[-3.10088631984559,53.41557402065429],"type":"Point"}
}