{
  "type": "Feature",
  "properties": {
    "iso:country":"GB",
    "wof:name":"YO7 1LU",
    "wof:placetype":"postalcode"
},
  "geometry": {"coordinates":[-1.34239076634933,54.23167960764732],"type":"Point"}
}