{
  "type": "Feature",
  "properties": {
    "iso:country": "GB",
    "wof:name": "YO7 1LU",
    "wof:placetype": "postalcode"
  },
  "geometry": {"coordinates":[-1.342391,54.23168],"type":"Point"}
}
