{
  "type": "Feature",
  "properties": {
    "iso:country": "GB",
    "wof:name": "SE24 0NZ",
    "wof:placetype": "postalcode"
  },
  "geometry": {"coordinates":[-0.10835,51.457106],"type":"Point"}
}
