{
  "type": "Feature",
  "properties": {
    "iso:country": "GB",
    "wof:name": "DY6 8XF",
    "wof:placetype": "postalcode"
  },
  "geometry": {"coordinates":[-2.145304,52.499615],"type":"Point"}
}
