{
  "type": "Feature",
  "properties": {
    "date:inception_lower":"1987-04-01",
    "date:inception_upper":"1987-04-30",
    "iso:country":"GB",
    "wof:name":"DY6 8XF",
    "wof:placetype":"postalcode"
},
  "geometry": {"coordinates":[-2.145304,52.499615],"type":"Point"}
}