{
  "type": "Feature",
  "properties": {
    "iso:country":"GB",
    "wof:name":"DY6 8XF",
    "wof:placetype":"postalcode"
},
  "geometry": {"coordinates":[-2.14487687662022,52.49973202714688],"type":"Point"}
}