{
  "type": "Feature",
  "properties": {
    "iso:country":"GB",
    "wof:name":"WF1 5TB",
    "wof:placetype":"postalcode"
},
  "geometry": {"coordinates":[-1.44835024372245,53.6841413397216],"type":"Point"}
}