{
  "type": "Feature",
  "properties": {
    "iso:country":"GB",
    "wof:name":"PE1 5DU",
    "wof:placetype":"postalcode"
},
  "geometry": {"coordinates":[-0.23055965644739,52.57543340312537],"type":"Point"}
}