{
  "type": "Feature",
  "properties": {
    "iso:country":"GB",
    "wof:name":"SL9 0QJ",
    "wof:placetype":"postalcode"
},
  "geometry": {"coordinates":[-0.54445273147034,51.60967703947297],"type":"Point"}
}