{
  "type": "Feature",
  "properties": {
    "iso:country": "GB",
    "wof:name": "SL9 0QJ",
    "wof:placetype": "postalcode"
  },
  "geometry": {"coordinates":[-0.544453,51.609677],"type":"Point"}
}
