{
  "type": "Feature",
  "properties": {
    "date:inception_lower": "1980-01-01",
    "date:inception_upper": "1980-01-01",
    "iso:country": "GB",
    "wof:name": "L37 8EB",
    "wof:placetype": "postalcode"
  },
  "geometry": {"coordinates":[-3.05335,53.554593],"type":"Point"}
}
