{
  "type": "Feature",
  "properties": {
    "iso:country":"GB",
    "wof:name":"L37 8EB",
    "wof:placetype":"postalcode"
},
  "geometry": {"coordinates":[-3.05334989906358,53.55459328050526],"type":"Point"}
}