{
  "type": "Feature",
  "properties": {
    "iso:country": "GB",
    "wof:name": "TQ9 6RU",
    "wof:placetype": "postalcode"
  },
  "geometry": {"coordinates":[-3.621603,50.403199],"type":"Point"}
}
