{
  "type": "Feature",
  "properties": {
    "iso:country":"GB",
    "wof:name":"TQ9 6RU",
    "wof:placetype":"postalcode"
},
  "geometry": {"coordinates":[-3.62160292614503,50.40319906150287],"type":"Point"}
}