{
  "type": "Feature",
  "properties": {
    "date:inception_lower": "1980-01-01",
    "date:inception_upper": "1980-01-01",
    "iso:country": "GB",
    "wof:name": "SE14 5QZ",
    "wof:placetype": "postalcode"
  },
  "geometry": {"coordinates":[-0.045322,51.478203],"type":"Point"}
}
