{
  "type": "Feature",
  "properties": {
    "iso:country":"GB",
    "wof:name":"SE14 5QZ",
    "wof:placetype":"postalcode"
},
  "geometry": {"coordinates":[-0.04532193022618,51.47820327639215],"type":"Point"}
}