{
  "type": "Feature",
  "properties": {
    "iso:country":"GB",
    "wof:name":"ST19 9AL",
    "wof:placetype":"postalcode"
},
  "geometry": {"coordinates":[-2.24757730474296,52.68512012910632],"type":"Point"}
}