{
  "type": "Feature",
  "properties": {
    "iso:country":"GB",
    "wof:name":"BS6 6TQ",
    "wof:placetype":"postalcode"
},
  "geometry": {"coordinates":[-2.61237034433525,51.46962885883892],"type":"Point"}
}