{
  "type": "Feature",
  "properties": {
    "iso:country": "GB",
    "wof:name": "SN7 8JJ",
    "wof:placetype": "postalcode"
  },
  "geometry": {"coordinates":[-1.547373,51.67234],"type":"Point"}
}
