{
  "type": "Feature",
  "properties": {
    "date:inception_lower": "1991-01-01",
    "date:inception_upper": "1991-01-01",
    "iso:country": "GB",
    "wof:name": "SN7 8JJ",
    "wof:placetype": "postalcode"
  },
  "geometry": {"coordinates":[-1.547373,51.67234],"type":"Point"}
}
