{
  "type": "Feature",
  "properties": {
    "iso:country":"GB",
    "wof:name":"SN7 8JJ",
    "wof:placetype":"postalcode"
},
  "geometry": {"coordinates":[-1.54737278020649,51.67233983295286],"type":"Point"}
}