{
  "type": "Feature",
  "properties": {
    "iso:country":"GB",
    "wof:name":"W1H 1QW",
    "wof:placetype":"postalcode"
},
  "geometry": {"coordinates":[-0.16262250463322,51.52001776635171],"type":"Point"}
}