{
  "type": "Feature",
  "properties": {
    "date:inception_lower":"2000-12-01",
    "date:inception_upper":"2000-12-31",
    "iso:country":"GB",
    "wof:name":"W1H 1QW",
    "wof:placetype":"postalcode"
},
  "geometry": {"coordinates":[-0.162622,51.520018],"type":"Point"}
}