{
  "type": "Feature",
  "properties": {
    "iso:country": "GB",
    "wof:name": "CB7 4EL",
    "wof:placetype": "postalcode"
  },
  "geometry": {"coordinates":[0.262291,52.399496],"type":"Point"}
}
