{
  "type": "Feature",
  "properties": {
    "iso:country":"GB",
    "wof:name":"CB7 4EL",
    "wof:placetype":"postalcode"
},
  "geometry": {"coordinates":[0.26226723635763,52.39948015745881],"type":"Point"}
}