{
  "type": "Feature",
  "properties": {
    "iso:country":"GB",
    "wof:name":"BS27 3XT",
    "wof:placetype":"postalcode"
},
  "geometry": {"coordinates":[-2.77512153858564,51.27032350521173],"type":"Point"}
}