{
  "type": "Feature",
  "properties": {
    "date:inception_lower": "2001-06-01",
    "date:inception_upper": "2001-06-01",
    "iso:country": "GB",
    "wof:name": "BS27 3XT",
    "wof:placetype": "postalcode"
  },
  "geometry": {"coordinates":[-2.775121,51.270324],"type":"Point"}
}
