{
  "type": "Feature",
  "properties": {
    "iso:country": "GB",
    "wof:name": "NE29 0DJ",
    "wof:placetype": "postalcode"
  },
  "geometry": {"coordinates":[-1.450389,55.008864],"type":"Point"}
}
