{
  "type": "Feature",
  "properties": {
    "iso:country":"GB",
    "wof:name":"OL4 1RJ",
    "wof:placetype":"postalcode"
},
  "geometry": {"coordinates":[-2.09538857436242,53.53419897558398],"type":"Point"}
}