{
  "type": "Feature",
  "properties": {
    "iso:country": "GB",
    "wof:name": "OL4 1RJ",
    "wof:placetype": "postalcode"
  },
  "geometry": {"coordinates":[-2.095389,53.534199],"type":"Point"}
}
