{
  "type": "Feature",
  "properties": {
    "iso:country":"GB",
    "wof:name":"BH22 8XH",
    "wof:placetype":"postalcode"
},
  "geometry": {"coordinates":[-1.86858056390272,50.80433388798107],"type":"Point"}
}