{
  "type": "Feature",
  "properties": {
    "iso:country":"GB",
    "wof:name":"DD11 5BG",
    "wof:placetype":"postalcode"
},
  "geometry": {"coordinates":[-2.57301738673121,56.56264737135275],"type":"Point"}
}