{
  "type": "Feature",
  "properties": {
    "iso:country": "GB",
    "wof:name": "NG14 7BF",
    "wof:placetype": "postalcode"
  },
  "geometry": {"coordinates":[-1.006084,53.012568],"type":"Point"}
}
