{
  "type": "Feature",
  "properties": {
    "date:inception_lower":"2009-03-01",
    "date:inception_upper":"2009-03-31",
    "iso:country":"GB",
    "wof:name":"NG14 7BF",
    "wof:placetype":"postalcode"
},
  "geometry": {"coordinates":[-1.006084,53.012568],"type":"Point"}
}