{
  "type": "Feature",
  "properties": {
    "iso:country":"GB",
    "wof:name":"YO18 8RQ",
    "wof:placetype":"postalcode"
},
  "geometry": {"coordinates":[-0.90448238380542,54.36820977125534],"type":"Point"}
}