{
  "type": "Feature",
  "properties": {
    "date:inception_lower": "1980-01-01",
    "date:inception_upper": "1980-01-01",
    "iso:country": "GB",
    "wof:name": "B36 0AF",
    "wof:placetype": "postalcode"
  },
  "geometry": {"coordinates":[-1.773953,52.503489],"type":"Point"}
}
