{
  "type": "Feature",
  "properties": {
    "date:inception_lower": "1980-01-01",
    "date:inception_upper": "1980-01-01",
    "iso:country": "GB",
    "wof:name": "LS12 2DF",
    "wof:placetype": "postalcode"
  },
  "geometry": {"coordinates":[-1.585288,53.796692],"type":"Point"}
}
