{
  "type": "Feature",
  "properties": {
    "iso:country": "GB",
    "wof:name": "G72 9RF",
    "wof:placetype": "postalcode"
  },
  "geometry": {"coordinates":[-4.10472,55.793337],"type":"Point"}
}
