{
  "type": "Feature",
  "properties": {
    "iso:country":"GB",
    "wof:name":"NR21 9AN",
    "wof:placetype":"postalcode"
},
  "geometry": {"coordinates":[0.84836851036,52.82900120136779],"type":"Point"}
}