{
  "type": "Feature",
  "properties": {
    "iso:country":"GB",
    "wof:name":"WS4 2DY",
    "wof:placetype":"postalcode"
},
  "geometry": {"coordinates":[-1.96976865453386,52.59291619510368],"type":"Point"}
}