{
  "type": "Feature",
  "properties": {
    "iso:country":"GB",
    "wof:name":"LE12 6XD",
    "wof:placetype":"postalcode"
},
  "geometry": {"coordinates":[-1.15063678936588,52.83153293327791],"type":"Point"}
}