{
  "type": "Feature",
  "properties": {
    "iso:country": "GB",
    "wof:name": "LE12 6XD",
    "wof:placetype": "postalcode"
  },
  "geometry": {"coordinates":[-1.150898,52.831591],"type":"Point"}
}
