{
  "type": "Feature",
  "properties": {
    "iso:country": "GB",
    "wof:name": "DY8 4QN",
    "wof:placetype": "postalcode"
  },
  "geometry": {"coordinates":[-2.165885,52.461344],"type":"Point"}
}
