{
  "type": "Feature",
  "properties": {
    "date:inception_lower": "1994-05-01",
    "date:inception_upper": "1994-05-01",
    "iso:country": "GB",
    "wof:name": "M38 0DA",
    "wof:placetype": "postalcode"
  },
  "geometry": {"coordinates":[-2.42823,53.528265],"type":"Point"}
}
