{
  "type": "Feature",
  "properties": {
    "iso:country":"GB",
    "wof:name":"M38 0DA",
    "wof:placetype":"postalcode"
},
  "geometry": {"coordinates":[-2.42823025046076,53.5282652482428],"type":"Point"}
}