{
  "type": "Feature",
  "properties": {
    "iso:country":"GB",
    "wof:name":"EX1 3RP",
    "wof:placetype":"postalcode"
},
  "geometry": {"coordinates":[-3.46831827742419,50.73071828173072],"type":"Point"}
}