{
  "type": "Feature",
  "properties": {
    "iso:country": "GB",
    "wof:name": "EX1 3RP",
    "wof:placetype": "postalcode"
  },
  "geometry": {"coordinates":[-3.468349,50.730788],"type":"Point"}
}
