{
  "type": "Feature",
  "properties": {
    "iso:country":"GB",
    "wof:name":"SA2 8NN",
    "wof:placetype":"postalcode"
},
  "geometry": {"coordinates":[-4.00375719550602,51.6152947520589],"type":"Point"}
}