{
  "type": "Feature",
  "properties": {
    "iso:country":"GB",
    "wof:name":"EX15 2TU",
    "wof:placetype":"postalcode"
},
  "geometry": {"coordinates":[-3.36471655842222,50.8926469262443],"type":"Point"}
}