{
  "type": "Feature",
  "properties": {
    "date:inception_lower":"2001-06-01",
    "date:inception_upper":"2001-06-30",
    "iso:country":"GB",
    "wof:name":"EX15 2TU",
    "wof:placetype":"postalcode"
},
  "geometry": {"coordinates":[-3.364717,50.892647],"type":"Point"}
}