{
  "type": "Feature",
  "properties": {
    "iso:country":"GB",
    "wof:name":"RH1 3QQ",
    "wof:placetype":"postalcode"
},
  "geometry": {"coordinates":[-0.13422057530178,51.25905133869814],"type":"Point"}
}