{
  "type": "Feature",
  "properties": {
    "iso:country": "GB",
    "wof:name": "SL4 4RJ",
    "wof:placetype": "postalcode"
  },
  "geometry": {"coordinates":[-0.659646,51.444941],"type":"Point"}
}
