{
  "type": "Feature",
  "properties": {
    "iso:country": "GB",
    "wof:name": "BS40 6HQ",
    "wof:placetype": "postalcode"
  },
  "geometry": {"coordinates":[-2.637057,51.315253],"type":"Point"}
}
