{
  "type": "Feature",
  "properties": {
    "iso:country":"GB",
    "wof:name":"CW9 8QP",
    "wof:placetype":"postalcode"
},
  "geometry": {"coordinates":[-2.51801624228287,53.22106250216655],"type":"Point"}
}