{
  "type": "Feature",
  "properties": {
    "date:inception_lower": "1980-01-01",
    "date:inception_upper": "1980-01-01",
    "iso:country": "GB",
    "wof:name": "CW9 8QP",
    "wof:placetype": "postalcode"
  },
  "geometry": {"coordinates":[-2.51803,53.221069],"type":"Point"}
}
