{
  "type": "Feature",
  "properties": {
    "date:inception_lower": "1985-04-01",
    "date:inception_upper": "1985-04-01",
    "iso:country": "GB",
    "wof:name": "WS13 6TY",
    "wof:placetype": "postalcode"
  },
  "geometry": {"coordinates":[-1.821506,52.682413],"type":"Point"}
}
