{
  "type": "Feature",
  "properties": {
    "date:inception_lower": "1980-01-01",
    "date:inception_upper": "1980-01-01",
    "iso:country": "GB",
    "wof:name": "WR14 4DS",
    "wof:placetype": "postalcode"
  },
  "geometry": {"coordinates":[-2.347934,52.108268],"type":"Point"}
}
