{
  "type": "Feature",
  "properties": {
    "iso:country":"GB",
    "wof:name":"WR14 4DS",
    "wof:placetype":"postalcode"
},
  "geometry": {"coordinates":[-2.34793425730353,52.10826800341934],"type":"Point"}
}