{
  "type": "Feature",
  "properties": {
    "iso:country":"GB",
    "wof:name":"GL11 5EP",
    "wof:placetype":"postalcode"
},
  "geometry": {"coordinates":[-2.33318511608093,51.71153461475848],"type":"Point"}
}