{
  "type": "Feature",
  "properties": {
    "iso:country":"GB",
    "wof:name":"BL4 0NB",
    "wof:placetype":"postalcode"
},
  "geometry": {"coordinates":[-2.42656780912419,53.55046360008456],"type":"Point"}
}