{
  "type": "Feature",
  "properties": {
    "date:inception_lower":"2002-07-01",
    "date:inception_upper":"2002-07-31",
    "iso:country":"GB",
    "wof:name":"NG10 3AG",
    "wof:placetype":"postalcode"
},
  "geometry": {"coordinates":[-1.30029,52.879201],"type":"Point"}
}