{
  "type": "Feature",
  "properties": {
    "iso:country":"GB",
    "wof:name":"NG10 3AG",
    "wof:placetype":"postalcode"
},
  "geometry": {"coordinates":[-1.30029027097737,52.87920080745671],"type":"Point"}
}