{
  "type": "Feature",
  "properties": {
    "iso:country": "GB",
    "wof:name": "NG10 3AG",
    "wof:placetype": "postalcode"
  },
  "geometry": {"coordinates":[-1.30029,52.879201],"type":"Point"}
}
