{
  "type": "Feature",
  "properties": {
    "iso:country":"GB",
    "wof:name":"ST10 4ET",
    "wof:placetype":"postalcode"
},
  "geometry": {"coordinates":[-1.9820371514477,52.95507001965691],"type":"Point"}
}