{
  "type": "Feature",
  "properties": {
    "iso:country": "GB",
    "wof:name": "ST10 4ET",
    "wof:placetype": "postalcode"
  },
  "geometry": {"coordinates":[-1.982037,52.95507],"type":"Point"}
}
