{
  "type": "Feature",
  "properties": {
    "date:inception_lower":"2013-03-01",
    "date:inception_upper":"2013-03-31",
    "iso:country":"GB",
    "wof:name":"NE9 9BY",
    "wof:placetype":"postalcode"
},
  "geometry": {"coordinates":[-1.610575,54.933189],"type":"Point"}
}