{
  "type": "Feature",
  "properties": {
    "date:inception_lower":"1980-01-01",
    "date:inception_upper":"1980-01-31",
    "iso:country":"GB",
    "wof:name":"FK3 8QJ",
    "wof:placetype":"postalcode"
},
  "geometry": {"coordinates":[-3.725447,56.007199],"type":"Point"}
}