{
  "type": "Feature",
  "properties": {
    "date:inception_lower": "2007-07-01",
    "date:inception_upper": "2007-07-01",
    "iso:country": "GB",
    "wof:name": "M27 8WD",
    "wof:placetype": "postalcode"
  },
  "geometry": {"coordinates":[-2.30953,53.510376],"type":"Point"}
}
