{
  "type": "Feature",
  "properties": {
    "iso:country": "GB",
    "wof:name": "M27 8WD",
    "wof:placetype": "postalcode"
  },
  "geometry": {"coordinates":[-2.30953,53.510376],"type":"Point"}
}
