{
  "type": "Feature",
  "properties": {
    "iso:country":"GB",
    "wof:name":"M27 8WD",
    "wof:placetype":"postalcode"
},
  "geometry": {"coordinates":[-2.30952970043097,53.51037621328081],"type":"Point"}
}