{
  "type": "Feature",
  "properties": {
    "iso:country":"GB",
    "wof:name":"BL0 9DX",
    "wof:placetype":"postalcode"
},
  "geometry": {"coordinates":[-2.32000548641959,53.64772620122262],"type":"Point"}
}