{
  "type": "Feature",
  "properties": {
    "date:inception_lower":"1980-01-01",
    "date:inception_upper":"1980-01-31",
    "iso:country":"GB",
    "wof:name":"BL0 9DX",
    "wof:placetype":"postalcode"
},
  "geometry": {"coordinates":[-2.320005,53.647726],"type":"Point"}
}