{
  "type": "Feature",
  "properties": {
    "iso:country": "GB",
    "wof:name": "BL0 9DX",
    "wof:placetype": "postalcode"
  },
  "geometry": {"coordinates":[-2.320005,53.647726],"type":"Point"}
}
