{
  "type": "Feature",
  "properties": {
    "iso:country":"GB",
    "wof:name":"BN1 8NX",
    "wof:placetype":"postalcode"
},
  "geometry": {"coordinates":[-0.14322659349787,50.86118555324308],"type":"Point"}
}