{
  "type": "Feature",
  "properties": {
    "date:inception_lower":"2014-06-01",
    "date:inception_upper":"2014-06-30",
    "iso:country":"GB",
    "wof:name":"LE18 4TQ",
    "wof:placetype":"postalcode"
},
  "geometry": {"coordinates":[-1.139088,52.580299],"type":"Point"}
}