{
  "type": "Feature",
  "properties": {
    "iso:country":"GB",
    "wof:name":"LE18 4TQ",
    "wof:placetype":"postalcode"
},
  "geometry": {"coordinates":[-1.13908849524318,52.58029945799111],"type":"Point"}
}