{
  "type": "Feature",
  "properties": {
    "date:inception_lower": "1980-01-01",
    "date:inception_upper": "1980-01-01",
    "iso:country": "GB",
    "wof:name": "M14 5DS",
    "wof:placetype": "postalcode"
  },
  "geometry": {"coordinates":[-2.211029,53.454737],"type":"Point"}
}
