{
  "type": "Feature",
  "properties": {
    "iso:country": "GB",
    "wof:name": "DN19 7DB",
    "wof:placetype": "postalcode"
  },
  "geometry": {"coordinates":[-0.380776,53.674935],"type":"Point"}
}
