{
  "type": "Feature",
  "properties": {
    "iso:country":"GB",
    "wof:name":"HR9 5QA",
    "wof:placetype":"postalcode"
},
  "geometry": {"coordinates":[-2.58973160155243,51.90307998423204],"type":"Point"}
}