{
  "type": "Feature",
  "properties": {
    "iso:country":"GB",
    "wof:name":"CF37 5PP",
    "wof:placetype":"postalcode"
},
  "geometry": {"coordinates":[-3.3159590144777,51.59024176764531],"type":"Point"}
}