{
  "type": "Feature",
  "properties": {
    "iso:country": "GB",
    "wof:name": "ML11 9GG",
    "wof:placetype": "postalcode"
  },
  "geometry": {"coordinates":[-3.762521,55.669996],"type":"Point"}
}
