{
  "type": "Feature",
  "properties": {
    "date:inception_lower": "2008-09-01",
    "date:inception_upper": "2008-09-01",
    "iso:country": "GB",
    "wof:name": "YO16 7QT",
    "wof:placetype": "postalcode"
  },
  "geometry": {"coordinates":[-0.208366,54.094458],"type":"Point"}
}
