{
  "type": "Feature",
  "properties": {
    "iso:country": "GB",
    "wof:name": "S70 5UL",
    "wof:placetype": "postalcode"
  },
  "geometry": {"coordinates":[-1.48182,53.505548],"type":"Point"}
}
