{
  "type": "Feature",
  "properties": {
    "iso:country": "GB",
    "wof:name": "OX15 5DL",
    "wof:placetype": "postalcode"
  },
  "geometry": {"coordinates":[-1.509781,52.019469],"type":"Point"}
}
