{
  "type": "Feature",
  "properties": {
    "iso:country": "GB",
    "wof:name": "OX15 5DL",
    "wof:placetype": "postalcode"
  },
  "geometry": {"coordinates":[-1.51406,52.009129],"type":"Point"}
}
