{
  "type": "Feature",
  "properties": {
    "date:inception_lower":"1995-01-01",
    "date:inception_upper":"1995-01-31",
    "iso:country":"GB",
    "wof:name":"OX15 5DL",
    "wof:placetype":"postalcode"
},
  "geometry": {"coordinates":[-1.51406,52.009129],"type":"Point"}
}