{
  "type": "Feature",
  "properties": {
    "iso:country":"GB",
    "wof:name":"CA3 8UE",
    "wof:placetype":"postalcode"
},
  "geometry": {"coordinates":[-2.93793434341429,54.89347155564462],"type":"Point"}
}