{
  "type": "Feature",
  "properties": {
    "iso:country":"GB",
    "wof:name":"GU22 8ES",
    "wof:placetype":"postalcode"
},
  "geometry": {"coordinates":[-0.53312864204872,51.32416953358555],"type":"Point"}
}