{
  "type": "Feature",
  "properties": {
    "iso:country": "GB",
    "wof:name": "AL9 7TA",
    "wof:placetype": "postalcode"
  },
  "geometry": {"coordinates":[-0.210795,51.713575],"type":"Point"}
}
