{
  "type": "Feature",
  "properties": {
    "iso:country":"GB",
    "wof:name":"AL9 7TA",
    "wof:placetype":"postalcode"
},
  "geometry": {"coordinates":[-0.21079462089235,51.71357498152889],"type":"Point"}
}