{
  "type": "Feature",
  "properties": {
    "date:inception_lower": "1980-01-01",
    "date:inception_upper": "1980-01-01",
    "iso:country": "GB",
    "wof:name": "WV5 9JD",
    "wof:placetype": "postalcode"
  },
  "geometry": {"coordinates":[-2.186597,52.53634],"type":"Point"}
}
