{
  "type": "Feature",
  "properties": {
    "iso:country":"GB",
    "wof:name":"PE29 2AG",
    "wof:placetype":"postalcode"
},
  "geometry": {"coordinates":[-0.17450833972892,52.32241597752418],"type":"Point"}
}