{
  "type": "Feature",
  "properties": {
    "iso:country": "GB",
    "wof:name": "PE29 2AG",
    "wof:placetype": "postalcode"
  },
  "geometry": {"coordinates":[-0.174508,52.322416],"type":"Point"}
}
