{
  "type": "Feature",
  "properties": {
    "date:inception_lower": "1996-12-01",
    "date:inception_upper": "1996-12-01",
    "iso:country": "GB",
    "wof:name": "OL2 6AG",
    "wof:placetype": "postalcode"
  },
  "geometry": {"coordinates":[-2.117264,53.555581],"type":"Point"}
}
