{
  "type": "Feature",
  "properties": {
    "iso:country": "GB",
    "wof:name": "OX11 0QH",
    "wof:placetype": "postalcode"
  },
  "geometry": {"coordinates":[-1.310148,51.583296],"type":"Point"}
}
