{
  "type": "Feature",
  "properties": {
    "date:inception_lower": "1980-01-01",
    "date:inception_upper": "1980-01-01",
    "iso:country": "GB",
    "wof:name": "OX11 0QH",
    "wof:placetype": "postalcode"
  },
  "geometry": {"coordinates":[-1.310148,51.583296],"type":"Point"}
}
