{
  "type": "Feature",
  "properties": {
    "iso:country":"GB",
    "wof:name":"WA2 7DU",
    "wof:placetype":"postalcode"
},
  "geometry": {"coordinates":[-2.58437671848515,53.39548033109356],"type":"Point"}
}