{
  "type": "Feature",
  "properties": {
    "date:inception_lower":"2007-09-01",
    "date:inception_upper":"2007-09-30",
    "iso:country":"GB",
    "wof:name":"WA2 7DU",
    "wof:placetype":"postalcode"
},
  "geometry": {"coordinates":[-2.584377,53.39548],"type":"Point"}
}