{
  "type": "Feature",
  "properties": {
    "iso:country":"GB",
    "wof:name":"NE10 8TL",
    "wof:placetype":"postalcode"
},
  "geometry": {"coordinates":[-1.5351560184915,54.94887457287074],"type":"Point"}
}