{
  "type": "Feature",
  "properties": {
    "iso:country":"GB",
    "wof:name":"AL2 3UX",
    "wof:placetype":"postalcode"
},
  "geometry": {"coordinates":[-0.37787321995286,51.70619024484404],"type":"Point"}
}