{
  "type": "Feature",
  "properties": {
    "date:inception_lower": "1980-01-01",
    "date:inception_upper": "1980-01-01",
    "iso:country": "GB",
    "wof:name": "AL2 3UX",
    "wof:placetype": "postalcode"
  },
  "geometry": {"coordinates":[-0.377873,51.70619],"type":"Point"}
}
