{
  "type": "Feature",
  "properties": {
    "date:inception_lower": "1980-01-01",
    "date:inception_upper": "1980-01-01",
    "iso:country": "GB",
    "wof:name": "TA20 1JZ",
    "wof:placetype": "postalcode"
  },
  "geometry": {"coordinates":[-2.970865,50.880527],"type":"Point"}
}
