{
  "type": "Feature",
  "properties": {
    "iso:country":"GB",
    "wof:name":"KY3 0EL",
    "wof:placetype":"postalcode"
},
  "geometry": {"coordinates":[-3.23195715740752,56.06349816010144],"type":"Point"}
}