{
  "type": "Feature",
  "properties": {
    "date:inception_lower": "1980-01-01",
    "date:inception_upper": "1980-01-01",
    "iso:country": "GB",
    "wof:name": "DA1 5BY",
    "wof:placetype": "postalcode"
  },
  "geometry": {"coordinates":[0.219448,51.451493],"type":"Point"}
}
