{
  "type": "Feature",
  "properties": {
    "iso:country":"GB",
    "wof:name":"DA1 5BY",
    "wof:placetype":"postalcode"
},
  "geometry": {"coordinates":[0.21944781181295,51.45149299877575],"type":"Point"}
}