{
  "type": "Feature",
  "properties": {
    "date:inception_lower": "2019-08-01",
    "date:inception_upper": "2019-08-01",
    "iso:country": "GB",
    "wof:name": "BB7 9ZT",
    "wof:placetype": "postalcode"
  },
  "geometry": {"coordinates":[-2.405105,53.838875],"type":"Point"}
}
