{
  "type": "Feature",
  "properties": {
    "iso:country": "GB",
    "wof:name": "BB7 9ZT",
    "wof:placetype": "postalcode"
  },
  "geometry": {"coordinates":[-2.405105,53.838875],"type":"Point"}
}
