{
  "type": "Feature",
  "properties": {
    "iso:country": "GB",
    "wof:name": "HU5 4QY",
    "wof:placetype": "postalcode"
  },
  "geometry": {"coordinates":[-0.385152,53.76867],"type":"Point"}
}
