{
  "type": "Feature",
  "properties": {
    "iso:country":"GB",
    "wof:name":"HU5 4QY",
    "wof:placetype":"postalcode"
},
  "geometry": {"coordinates":[-0.3851522619901,53.76867003999922],"type":"Point"}
}