{
  "type": "Feature",
  "properties": {
    "date:inception_lower": "1980-01-01",
    "date:inception_upper": "1980-01-01",
    "iso:country": "GB",
    "wof:name": "CV37 7RH",
    "wof:placetype": "postalcode"
  },
  "geometry": {"coordinates":[-1.656646,52.205299],"type":"Point"}
}
