{
  "type": "Feature",
  "properties": {
    "iso:country": "GB",
    "wof:name": "CV37 7RH",
    "wof:placetype": "postalcode"
  },
  "geometry": {"coordinates":[-1.656646,52.205299],"type":"Point"}
}
