{
  "type": "Feature",
  "properties": {
    "iso:country":"GB",
    "wof:name":"CV37 7RH",
    "wof:placetype":"postalcode"
},
  "geometry": {"coordinates":[-1.65664642919701,52.20529938853646],"type":"Point"}
}