{
  "type": "Feature",
  "properties": {
    "iso:country":"GB",
    "wof:name":"NW9 8JE",
    "wof:placetype":"postalcode"
},
  "geometry": {"coordinates":[-0.26307913193237,51.57631153483065],"type":"Point"}
}