{
  "type": "Feature",
  "properties": {
    "date:inception_lower": "1980-01-01",
    "date:inception_upper": "1980-01-01",
    "iso:country": "GB",
    "wof:name": "LL62 5HR",
    "wof:placetype": "postalcode"
  },
  "geometry": {"coordinates":[-4.420004,53.202767],"type":"Point"}
}
