{
  "type": "Feature",
  "properties": {
    "date:inception_lower": "1996-12-01",
    "date:inception_upper": "1996-12-01",
    "iso:country": "GB",
    "wof:name": "BB3 0PG",
    "wof:placetype": "postalcode"
  },
  "geometry": {"coordinates":[-2.484715,53.712103],"type":"Point"}
}
