{
  "type": "Feature",
  "properties": {
    "iso:country": "GB",
    "wof:name": "BB3 0PG",
    "wof:placetype": "postalcode"
  },
  "geometry": {"coordinates":[-2.484715,53.712103],"type":"Point"}
}
