{
  "type": "Feature",
  "properties": {
    "iso:country": "GB",
    "wof:name": "NE13 9EH",
    "wof:placetype": "postalcode"
  },
  "geometry": {"coordinates":[-1.658023,55.028197],"type":"Point"}
}
