{
  "type": "Feature",
  "properties": {
    "iso:country":"GB",
    "wof:name":"PO2 7ST",
    "wof:placetype":"postalcode"
},
  "geometry": {"coordinates":[-1.08510074920896,50.81191939824486],"type":"Point"}
}