{
  "type": "Feature",
  "properties": {
    "date:inception_lower":"1980-01-01",
    "date:inception_upper":"1980-01-31",
    "iso:country":"GB",
    "wof:name":"LE14 2HZ",
    "wof:placetype":"postalcode"
},
  "geometry": {"coordinates":[-0.926448,52.681914],"type":"Point"}
}