{
  "type": "Feature",
  "properties": {
    "iso:country":"GB",
    "wof:name":"SN15 1AB",
    "wof:placetype":"postalcode"
},
  "geometry": {"coordinates":[-2.11737608538104,51.46644056698612],"type":"Point"}
}