{
  "type": "Feature",
  "properties": {
    "date:inception_lower": "1980-01-01",
    "date:inception_upper": "1980-01-01",
    "iso:country": "GB",
    "wof:name": "LS6 1PE",
    "wof:placetype": "postalcode"
  },
  "geometry": {"coordinates":[-1.569719,53.80747],"type":"Point"}
}
