{
  "type": "Feature",
  "properties": {
    "iso:country":"GB",
    "wof:name":"DL10 4SE",
    "wof:placetype":"postalcode"
},
  "geometry": {"coordinates":[-1.7774866668433,54.40197482663957],"type":"Point"}
}