{
  "type": "Feature",
  "properties": {
    "date:inception_lower": "2013-12-01",
    "date:inception_upper": "2013-12-01",
    "iso:country": "GB",
    "wof:name": "HU4 6DF",
    "wof:placetype": "postalcode"
  },
  "geometry": {"coordinates":[-0.394914,53.748003],"type":"Point"}
}
