{
  "type": "Feature",
  "properties": {
    "iso:country":"GB",
    "wof:name":"FY7 8NR",
    "wof:placetype":"postalcode"
},
  "geometry": {"coordinates":[-3.04085807812434,53.90272855105338],"type":"Point"}
}