{
  "type": "Feature",
  "properties": {
    "date:inception_lower":"2011-10-01",
    "date:inception_upper":"2011-10-31",
    "iso:country":"GB",
    "wof:name":"SY25 6AT",
    "wof:placetype":"postalcode"
},
  "geometry": {"coordinates":[-3.941272,52.217904],"type":"Point"}
}