{
  "type": "Feature",
  "properties": {
    "iso:country": "GB",
    "wof:name": "SY25 6AT",
    "wof:placetype": "postalcode"
  },
  "geometry": {"coordinates":[-3.941272,52.217904],"type":"Point"}
}
