{
  "type": "Feature",
  "properties": {
    "date:inception_lower": "1980-01-01",
    "date:inception_upper": "1980-01-01",
    "iso:country": "GB",
    "wof:name": "LE5 4GH",
    "wof:placetype": "postalcode"
  },
  "geometry": {"coordinates":[-1.101032,52.635216],"type":"Point"}
}
