{
  "type": "Feature",
  "properties": {
    "iso:country": "GB",
    "wof:name": "LE5 4GH",
    "wof:placetype": "postalcode"
  },
  "geometry": {"coordinates":[-1.101032,52.635216],"type":"Point"}
}
