{
  "type": "Feature",
  "properties": {
    "date:inception_lower": "1980-01-01",
    "date:inception_upper": "1980-01-01",
    "iso:country": "GB",
    "wof:name": "WS3 1BT",
    "wof:placetype": "postalcode"
  },
  "geometry": {"coordinates":[-1.980695,52.608145],"type":"Point"}
}
