{
  "type": "Feature",
  "properties": {
    "iso:country":"GB",
    "wof:name":"WS3 1BT",
    "wof:placetype":"postalcode"
},
  "geometry": {"coordinates":[-1.98070064370655,52.60812915357363],"type":"Point"}
}