{
  "type": "Feature",
  "properties": {
    "iso:country":"GB",
    "wof:name":"LL19 9AY",
    "wof:placetype":"postalcode"
},
  "geometry": {"coordinates":[-3.4013616179722,53.33274341417903],"type":"Point"}
}