{
  "type": "Feature",
  "properties": {
    "iso:country":"GB",
    "wof:name":"E5 9HH",
    "wof:placetype":"postalcode"
},
  "geometry": {"coordinates":[-0.05433179763693,51.56862078835545],"type":"Point"}
}