{
  "type": "Feature",
  "properties": {
    "date:inception_lower": "2018-02-01",
    "date:inception_upper": "2018-02-01",
    "iso:country": "GB",
    "wof:name": "CM19 5FY",
    "wof:placetype": "postalcode"
  },
  "geometry": {"coordinates":[0.059359,51.768866],"type":"Point"}
}
