{
  "type": "Feature",
  "properties": {
    "date:inception_lower": "1981-06-01",
    "date:inception_upper": "1981-06-01",
    "iso:country": "GB",
    "wof:name": "IP30 9RA",
    "wof:placetype": "postalcode"
  },
  "geometry": {"coordinates":[0.893778,52.224013],"type":"Point"}
}
