{
  "type": "Feature",
  "properties": {
    "date:inception_lower": "1980-01-01",
    "date:inception_upper": "1980-01-01",
    "iso:country": "GB",
    "wof:name": "NE26 2TE",
    "wof:placetype": "postalcode"
  },
  "geometry": {"coordinates":[-1.445327,55.042385],"type":"Point"}
}
