{
  "type": "Feature",
  "properties": {
    "iso:country": "GB",
    "wof:name": "NE26 2TE",
    "wof:placetype": "postalcode"
  },
  "geometry": {"coordinates":[-1.445518,55.042316],"type":"Point"}
}
