{
  "type": "Feature",
  "properties": {
    "iso:country":"GB",
    "wof:name":"NE26 2TE",
    "wof:placetype":"postalcode"
},
  "geometry": {"coordinates":[-1.44531378310596,55.04237803643499],"type":"Point"}
}