{
  "type": "Feature",
  "properties": {
    "date:inception_lower": "1980-01-01",
    "date:inception_upper": "1980-01-01",
    "iso:country": "GB",
    "wof:name": "EX21 5XS",
    "wof:placetype": "postalcode"
  },
  "geometry": {"coordinates":[-4.208082,50.783764],"type":"Point"}
}
