{
  "type": "Feature",
  "properties": {
    "iso:country":"GB",
    "wof:name":"NW2 4HS",
    "wof:placetype":"postalcode"
},
  "geometry": {"coordinates":[-0.21046661308635,51.54896660132211],"type":"Point"}
}