{
  "type": "Feature",
  "properties": {
    "iso:country":"GB",
    "wof:name":"NW7 4RB",
    "wof:placetype":"postalcode"
},
  "geometry": {"coordinates":[-0.24650806904687,51.61876040635249],"type":"Point"}
}