{
  "type": "Feature",
  "properties": {
    "date:inception_lower": "1980-01-01",
    "date:inception_upper": "1980-01-01",
    "iso:country": "GB",
    "wof:name": "NW7 4RB",
    "wof:placetype": "postalcode"
  },
  "geometry": {"coordinates":[-0.246595,51.618882],"type":"Point"}
}
