{
  "type": "Feature",
  "properties": {
    "iso:country":"GB",
    "wof:name":"IG1 4JT",
    "wof:placetype":"postalcode"
},
  "geometry": {"coordinates":[0.06989814172264,51.5620256124666],"type":"Point"}
}