{
  "type": "Feature",
  "properties": {
    "date:inception_lower": "2001-06-01",
    "date:inception_upper": "2001-06-01",
    "iso:country": "GB",
    "wof:name": "WF17 0RP",
    "wof:placetype": "postalcode"
  },
  "geometry": {"coordinates":[-1.642047,53.732487],"type":"Point"}
}
