{
  "type": "Feature",
  "properties": {
    "iso:country":"GB",
    "wof:name":"WF17 0RP",
    "wof:placetype":"postalcode"
},
  "geometry": {"coordinates":[-1.64204735921761,53.73248655934062],"type":"Point"}
}