{
  "type": "Feature",
  "properties": {
    "date:inception_lower": "2000-06-01",
    "date:inception_upper": "2000-06-01",
    "iso:country": "GB",
    "wof:name": "PE28 4RR",
    "wof:placetype": "postalcode"
  },
  "geometry": {"coordinates":[-0.237446,52.326024],"type":"Point"}
}
