{
  "type": "Feature",
  "properties": {
    "iso:country": "GB",
    "wof:name": "ST7 4AJ",
    "wof:placetype": "postalcode"
  },
  "geometry": {"coordinates":[-2.222057,53.0914],"type":"Point"}
}
