{
  "type": "Feature",
  "properties": {
    "date:inception_lower": "1981-06-01",
    "date:inception_upper": "1981-06-01",
    "iso:country": "GB",
    "wof:name": "ST7 4AJ",
    "wof:placetype": "postalcode"
  },
  "geometry": {"coordinates":[-2.222057,53.091515],"type":"Point"}
}
