{
  "type": "Feature",
  "properties": {
    "iso:country": "GB",
    "wof:name": "GU27 1FD",
    "wof:placetype": "postalcode"
  },
  "geometry": {"coordinates":[-0.742941,51.087218],"type":"Point"}
}
