{
  "type": "Feature",
  "properties": {
    "iso:country": "GB",
    "wof:name": "GU27 1FD",
    "wof:placetype": "postalcode"
  },
  "geometry": {"coordinates":[-0.742971,51.087164],"type":"Point"}
}
