{
  "type": "Feature",
  "properties": {
    "date:inception_lower": "2014-08-01",
    "date:inception_upper": "2014-08-01",
    "iso:country": "GB",
    "wof:name": "GU27 1FD",
    "wof:placetype": "postalcode"
  },
  "geometry": {"coordinates":[-0.742941,51.087218],"type":"Point"}
}
