{
  "type": "Feature",
  "properties": {
    "date:inception_lower":"1999-06-01",
    "date:inception_upper":"1999-06-30",
    "iso:country":"GB",
    "wof:name":"TN27 0HS",
    "wof:placetype":"postalcode"
},
  "geometry": {"coordinates":[0.79671,51.204204],"type":"Point"}
}