{
  "type": "Feature",
  "properties": {
    "iso:country":"GB",
    "wof:name":"TN27 0HS",
    "wof:placetype":"postalcode"
},
  "geometry": {"coordinates":[0.79671032806409,51.20420361132761],"type":"Point"}
}