{
  "type": "Feature",
  "properties": {
    "iso:country": "GB",
    "wof:name": "TN27 0HS",
    "wof:placetype": "postalcode"
  },
  "geometry": {"coordinates":[0.79671,51.204204],"type":"Point"}
}
