{
  "type": "Feature",
  "properties": {
    "iso:country":"GB",
    "wof:name":"FY6 7LW",
    "wof:placetype":"postalcode"
},
  "geometry": {"coordinates":[-3.00437746697617,53.85843065893984],"type":"Point"}
}