{
  "type": "Feature",
  "properties": {
    "iso:country":"GB",
    "wof:name":"NE5 4QE",
    "wof:placetype":"postalcode"
},
  "geometry": {"coordinates":[-1.69415980034027,55.00979253441863],"type":"Point"}
}