{
  "type": "Feature",
  "properties": {
    "iso:country": "GB",
    "wof:name": "SG14 1EJ",
    "wof:placetype": "postalcode"
  },
  "geometry": {"coordinates":[-0.076915,51.795627],"type":"Point"}
}
