{
  "type": "Feature",
  "properties": {
    "iso:country":"GB",
    "wof:name":"SN5 8QF",
    "wof:placetype":"postalcode"
},
  "geometry": {"coordinates":[-1.83808499831271,51.54852515024508],"type":"Point"}
}