{
  "type": "Feature",
  "properties": {
    "iso:country":"GB",
    "wof:name":"TS22 5HB",
    "wof:placetype":"postalcode"
},
  "geometry": {"coordinates":[-1.30258227226028,54.61211910279901],"type":"Point"}
}