{
  "type": "Feature",
  "properties": {
    "iso:country": "GB",
    "wof:name": "G81 4BX",
    "wof:placetype": "postalcode"
  },
  "geometry": {"coordinates":[-4.432766,55.912745],"type":"Point"}
}
