{
  "type": "Feature",
  "properties": {
    "iso:country":"GB",
    "wof:name":"G81 4BX",
    "wof:placetype":"postalcode"
},
  "geometry": {"coordinates":[-4.43342095930703,55.91299908606945],"type":"Point"}
}