{
  "type": "Feature",
  "properties": {
    "date:inception_lower": "1980-01-01",
    "date:inception_upper": "1980-01-01",
    "iso:country": "GB",
    "wof:name": "LN5 0JW",
    "wof:placetype": "postalcode"
  },
  "geometry": {"coordinates":[-0.526783,53.104688],"type":"Point"}
}
