{
  "type": "Feature",
  "properties": {
    "iso:country":"GB",
    "wof:name":"LN5 0JW",
    "wof:placetype":"postalcode"
},
  "geometry": {"coordinates":[-0.52678308573966,53.10468814523755],"type":"Point"}
}