{
  "type": "Feature",
  "properties": {
    "iso:country":"GB",
    "wof:name":"BB10 4TG",
    "wof:placetype":"postalcode"
},
  "geometry": {"coordinates":[-2.19626438819773,53.76569252532473],"type":"Point"}
}