{
  "type": "Feature",
  "properties": {
    "iso:country":"GB",
    "wof:name":"DH4 5HT",
    "wof:placetype":"postalcode"
},
  "geometry": {"coordinates":[-1.48300333395498,54.8483126745417],"type":"Point"}
}