{
  "type": "Feature",
  "properties": {
    "iso:country":"GB",
    "wof:name":"LE17 4QR",
    "wof:placetype":"postalcode"
},
  "geometry": {"coordinates":[-1.21332226389334,52.45398309118699],"type":"Point"}
}