{
  "type": "Feature",
  "properties": {
    "date:inception_lower": "1980-01-01",
    "date:inception_upper": "1980-01-01",
    "iso:country": "GB",
    "wof:name": "GL14 3AL",
    "wof:placetype": "postalcode"
  },
  "geometry": {"coordinates":[-2.506085,51.803616],"type":"Point"}
}
