{
  "type": "Feature",
  "properties": {
    "iso:country":"GB",
    "wof:name":"GL14 3AL",
    "wof:placetype":"postalcode"
},
  "geometry": {"coordinates":[-2.50608494820573,51.80361550398113],"type":"Point"}
}