{
  "type": "Feature",
  "properties": {
    "date:inception_lower": "2008-03-01",
    "date:inception_upper": "2008-03-01",
    "iso:country": "GB",
    "wof:name": "CW9 7TQ",
    "wof:placetype": "postalcode"
  },
  "geometry": {"coordinates":[-2.476669,53.251319],"type":"Point"}
}
