{
  "type": "Feature",
  "properties": {
    "iso:country":"GB",
    "wof:name":"CM12 0QD",
    "wof:placetype":"postalcode"
},
  "geometry": {"coordinates":[0.42637525789394,51.63728352802998],"type":"Point"}
}