{
  "type": "Feature",
  "properties": {
    "iso:country": "GB",
    "wof:name": "CM12 0QD",
    "wof:placetype": "postalcode"
  },
  "geometry": {"coordinates":[0.426375,51.637284],"type":"Point"}
}
