{
  "type": "Feature",
  "properties": {
    "date:inception_lower": "1980-01-01",
    "date:inception_upper": "1980-01-01",
    "iso:country": "GB",
    "wof:name": "CM12 0QD",
    "wof:placetype": "postalcode"
  },
  "geometry": {"coordinates":[0.426375,51.637284],"type":"Point"}
}
