{
  "type": "Feature",
  "properties": {
    "iso:country":"GB",
    "wof:name":"MK14 6GA",
    "wof:placetype":"postalcode"
},
  "geometry": {"coordinates":[-0.77538857577659,52.06937384574486],"type":"Point"}
}