{
  "type": "Feature",
  "properties": {
    "date:inception_lower": "2009-09-01",
    "date:inception_upper": "2009-09-01",
    "iso:country": "GB",
    "wof:name": "MK14 6GA",
    "wof:placetype": "postalcode"
  },
  "geometry": {"coordinates":[-0.775389,52.069374],"type":"Point"}
}
