{
  "type": "Feature",
  "properties": {
    "iso:country": "GB",
    "wof:name": "IP6 0HS",
    "wof:placetype": "postalcode"
  },
  "geometry": {"coordinates":[1.108256,52.106987],"type":"Point"}
}
