{
  "type": "Feature",
  "properties": {
    "iso:country": "GB",
    "wof:name": "IP6 0HS",
    "wof:placetype": "postalcode"
  },
  "geometry": {"coordinates":[1.108025,52.10702],"type":"Point"}
}
