{
  "type": "Feature",
  "properties": {
    "date:inception_lower": "2022-03-01",
    "date:inception_upper": "2022-03-01",
    "iso:country": "GB",
    "wof:name": "ST18 0XH",
    "wof:placetype": "postalcode"
  },
  "geometry": {"coordinates":[-1.995977,52.800777],"type":"Point"}
}
