{
  "type": "Feature",
  "properties": {
    "iso:country": "GB",
    "wof:name": "PR3 2GS",
    "wof:placetype": "postalcode"
  },
  "geometry": {"coordinates":[-2.567622,53.896399],"type":"Point"}
}
