{
  "type": "Feature",
  "properties": {
    "iso:country":"GB",
    "wof:name":"PR3 2GS",
    "wof:placetype":"postalcode"
},
  "geometry": {"coordinates":[-2.56762200902065,53.89639912706988],"type":"Point"}
}