{
  "type": "Feature",
  "properties": {
    "iso:country": "GB",
    "wof:name": "PL26 8RL",
    "wof:placetype": "postalcode"
  },
  "geometry": {"coordinates":[-4.779038,50.388534],"type":"Point"}
}
