{
  "type": "Feature",
  "properties": {
    "date:inception_lower":"1980-01-01",
    "date:inception_upper":"1980-01-31",
    "iso:country":"GB",
    "wof:name":"PL26 8RL",
    "wof:placetype":"postalcode"
},
  "geometry": {"coordinates":[-4.779038,50.388534],"type":"Point"}
}