{
  "type": "Feature",
  "properties": {
    "iso:country": "GB",
    "wof:name": "TQ14 8DU",
    "wof:placetype": "postalcode"
  },
  "geometry": {"coordinates":[-3.497842,50.547714],"type":"Point"}
}
