{
  "type": "Feature",
  "properties": {
    "iso:country": "GB",
    "wof:name": "S13 9XW",
    "wof:placetype": "postalcode"
  },
  "geometry": {"coordinates":[-1.357317,53.367498],"type":"Point"}
}
