{
  "type": "Feature",
  "properties": {
    "iso:country":"GB",
    "wof:name":"S13 9XW",
    "wof:placetype":"postalcode"
},
  "geometry": {"coordinates":[-1.35731663070223,53.36749809803594],"type":"Point"}
}