{
  "type": "Feature",
  "properties": {
    "iso:country":"GB",
    "wof:name":"WR5 3DU",
    "wof:placetype":"postalcode"
},
  "geometry": {"coordinates":[-2.21684636754555,52.17808771772752],"type":"Point"}
}