{
  "type": "Feature",
  "properties": {
    "date:inception_lower": "2020-11-01",
    "date:inception_upper": "2020-11-01",
    "iso:country": "GB",
    "wof:name": "ST7 2UP",
    "wof:placetype": "postalcode"
  },
  "geometry": {"coordinates":[-2.309922,53.092173],"type":"Point"}
}
