{
  "type": "Feature",
  "properties": {
    "iso:country": "GB",
    "wof:name": "L4 8TX",
    "wof:placetype": "postalcode"
  },
  "geometry": {"coordinates":[-2.936257,53.434911],"type":"Point"}
}
