{
  "type": "Feature",
  "properties": {
    "iso:country":"GB",
    "wof:name":"L4 8TX",
    "wof:placetype":"postalcode"
},
  "geometry": {"coordinates":[-2.93625733938341,53.43491130852065],"type":"Point"}
}