{
  "type": "Feature",
  "properties": {
    "iso:country":"GB",
    "wof:name":"GU9 9JP",
    "wof:placetype":"postalcode"
},
  "geometry": {"coordinates":[-0.767320155106,51.2288885106228],"type":"Point"}
}