{
  "type": "Feature",
  "properties": {
    "date:inception_lower": "1980-01-01",
    "date:inception_upper": "1980-01-01",
    "iso:country": "GB",
    "wof:name": "GU9 9JP",
    "wof:placetype": "postalcode"
  },
  "geometry": {"coordinates":[-0.76732,51.228889],"type":"Point"}
}
