{
  "type": "Feature",
  "properties": {
    "date:inception_lower":"1980-01-01",
    "date:inception_upper":"1980-01-31",
    "iso:country":"GB",
    "wof:name":"CA10 3LY",
    "wof:placetype":"postalcode"
},
  "geometry": {"coordinates":[-2.679456,54.533214],"type":"Point"}
}