{
  "type": "Feature",
  "properties": {
    "iso:country":"GB",
    "wof:name":"PL33 9AP",
    "wof:placetype":"postalcode"
},
  "geometry": {"coordinates":[-4.72845101767046,50.6227111296509],"type":"Point"}
}