{
  "type": "Feature",
  "properties": {
    "iso:country":"GB",
    "wof:name":"GL4 5GX",
    "wof:placetype":"postalcode"
},
  "geometry": {"coordinates":[-2.19178003632544,51.84786731830523],"type":"Point"}
}