{
  "type": "Feature",
  "properties": {
    "iso:country": "GB",
    "wof:name": "SY16 4JW",
    "wof:placetype": "postalcode"
  },
  "geometry": {"coordinates":[-3.367919,52.474352],"type":"Point"}
}
