{
  "type": "Feature",
  "properties": {
    "iso:country":"GB",
    "wof:name":"SY16 4JW",
    "wof:placetype":"postalcode"
},
  "geometry": {"coordinates":[-3.36791880984722,52.47435214540106],"type":"Point"}
}