{
  "type": "Feature",
  "properties": {
    "date:inception_lower":"1980-01-01",
    "date:inception_upper":"1980-01-31",
    "iso:country":"GB",
    "wof:name":"SY16 4JW",
    "wof:placetype":"postalcode"
},
  "geometry": {"coordinates":[-3.367919,52.474352],"type":"Point"}
}