{
  "type": "Feature",
  "properties": {
    "iso:country":"GB",
    "wof:name":"IV3 8HF",
    "wof:placetype":"postalcode"
},
  "geometry": {"coordinates":[-4.23569616219127,57.48435870027073],"type":"Point"}
}