{
  "type": "Feature",
  "properties": {
    "iso:country": "GB",
    "wof:name": "S63 7FH",
    "wof:placetype": "postalcode"
  },
  "geometry": {"coordinates":[-1.355035,53.510522],"type":"Point"}
}
