{
  "type": "Feature",
  "properties": {
    "iso:country":"GB",
    "wof:name":"S63 7FH",
    "wof:placetype":"postalcode"
},
  "geometry": {"coordinates":[-1.35503507009408,53.510522382739],"type":"Point"}
}