{
  "type": "Feature",
  "properties": {
    "iso:country":"GB",
    "wof:name":"ST10 2LH",
    "wof:placetype":"postalcode"
},
  "geometry": {"coordinates":[-1.98148717601411,53.05925422659491],"type":"Point"}
}