{
  "type": "Feature",
  "properties": {
    "iso:country":"GB",
    "wof:name":"TS27 4DD",
    "wof:placetype":"postalcode"
},
  "geometry": {"coordinates":[-1.27761946940464,54.73989194856727],"type":"Point"}
}