{
  "type": "Feature",
  "properties": {
    "date:inception_lower":"2015-03-01",
    "date:inception_upper":"2015-03-31",
    "iso:country":"GB",
    "wof:name":"LE16 8ET",
    "wof:placetype":"postalcode"
},
  "geometry": {"coordinates":[-0.796628,52.523525],"type":"Point"}
}