{
  "type": "Feature",
  "properties": {
    "iso:country":"GB",
    "wof:name":"LE16 8ET",
    "wof:placetype":"postalcode"
},
  "geometry": {"coordinates":[-0.86846419625113,52.5006526177628],"type":"Point"}
}