{
  "type": "Feature",
  "properties": {
    "iso:country":"GB",
    "wof:name":"EN8 0DU",
    "wof:placetype":"postalcode"
},
  "geometry": {"coordinates":[-0.04628617627341,51.70936275664924],"type":"Point"}
}