{
  "type": "Feature",
  "properties": {
    "iso:country": "GB",
    "wof:name": "SW3 3SR",
    "wof:placetype": "postalcode"
  },
  "geometry": {"coordinates":[-0.167001,51.488864],"type":"Point"}
}
