{
  "type": "Feature",
  "properties": {
    "iso:country":"GB",
    "wof:name":"SW3 3SR",
    "wof:placetype":"postalcode"
},
  "geometry": {"coordinates":[-0.16700093936809,51.48886434978535],"type":"Point"}
}