{
  "type": "Feature",
  "properties": {
    "iso:country":"GB",
    "wof:name":"CM14 5AY",
    "wof:placetype":"postalcode"
},
  "geometry": {"coordinates":[0.23748948258915,51.6259639439107],"type":"Point"}
}