{
  "type": "Feature",
  "properties": {
    "iso:country": "GB",
    "wof:name": "CM14 5AY",
    "wof:placetype": "postalcode"
  },
  "geometry": {"coordinates":[0.23749,51.625964],"type":"Point"}
}
