{
  "type": "Feature",
  "properties": {
    "iso:country": "GB",
    "wof:name": "PL19 8SB",
    "wof:placetype": "postalcode"
  },
  "geometry": {"coordinates":[-4.213827,50.566572],"type":"Point"}
}
