{
  "type": "Feature",
  "properties": {
    "iso:country":"GB",
    "wof:name":"PL19 8SB",
    "wof:placetype":"postalcode"
},
  "geometry": {"coordinates":[-4.21382738025945,50.56657241076623],"type":"Point"}
}