{
  "type": "Feature",
  "properties": {
    "date:inception_lower": "1980-01-01",
    "date:inception_upper": "1980-01-01",
    "iso:country": "GB",
    "wof:name": "DT2 9HG",
    "wof:placetype": "postalcode"
  },
  "geometry": {"coordinates":[-2.586605,50.700567],"type":"Point"}
}
