{
  "type": "Feature",
  "properties": {
    "iso:country": "GB",
    "wof:name": "DT2 9HG",
    "wof:placetype": "postalcode"
  },
  "geometry": {"coordinates":[-2.586605,50.700567],"type":"Point"}
}
