{
  "type": "Feature",
  "properties": {
    "iso:country":"GB",
    "wof:name":"DT2 9HG",
    "wof:placetype":"postalcode"
},
  "geometry": {"coordinates":[-2.58660549281712,50.70056747359457],"type":"Point"}
}