{
  "type": "Feature",
  "properties": {
    "iso:country":"GB",
    "wof:name":"TA6 3BP",
    "wof:placetype":"postalcode"
},
  "geometry": {"coordinates":[-3.00414776499285,51.12893338822144],"type":"Point"}
}