{
  "type": "Feature",
  "properties": {
    "iso:country":"GB",
    "wof:name":"CW4 7ES",
    "wof:placetype":"postalcode"
},
  "geometry": {"coordinates":[-2.37411462279056,53.20200558324301],"type":"Point"}
}