{
  "type": "Feature",
  "properties": {
    "iso:country": "GB",
    "wof:name": "NR31 7DX",
    "wof:placetype": "postalcode"
  },
  "geometry": {"coordinates":[1.719883,52.563753],"type":"Point"}
}
