{
  "type": "Feature",
  "properties": {
    "iso:country": "GB",
    "wof:name": "LL11 2LR",
    "wof:placetype": "postalcode"
  },
  "geometry": {"coordinates":[-2.994917,53.051856],"type":"Point"}
}
