{
  "type": "Feature",
  "properties": {
    "iso:country":"GB",
    "wof:name":"LL11 2LR",
    "wof:placetype":"postalcode"
},
  "geometry": {"coordinates":[-2.99485848616244,53.05191197268871],"type":"Point"}
}