{
  "type": "Feature",
  "properties": {
    "iso:country":"GB",
    "wof:name":"PO31 7UG",
    "wof:placetype":"postalcode"
},
  "geometry": {"coordinates":[-1.30667849579046,50.75536217092079],"type":"Point"}
}