{
  "type": "Feature",
  "properties": {
    "date:inception_lower": "2001-12-01",
    "date:inception_upper": "2001-12-01",
    "iso:country": "GB",
    "wof:name": "PO31 7UG",
    "wof:placetype": "postalcode"
  },
  "geometry": {"coordinates":[-1.306678,50.755362],"type":"Point"}
}
