{
  "type": "Feature",
  "properties": {
    "date:inception_lower": "1998-12-01",
    "date:inception_upper": "1998-12-01",
    "iso:country": "GB",
    "wof:name": "IV30 6HT",
    "wof:placetype": "postalcode"
  },
  "geometry": {"coordinates":[-3.284491,57.643371],"type":"Point"}
}
