{
  "type": "Feature",
  "properties": {
    "iso:country":"GB",
    "wof:name":"GU17 0NH",
    "wof:placetype":"postalcode"
},
  "geometry": {"coordinates":[-0.78683620956945,51.33359119905314],"type":"Point"}
}