{
  "type": "Feature",
  "properties": {
    "iso:country":"GB",
    "wof:name":"E5 8QN",
    "wof:placetype":"postalcode"
},
  "geometry": {"coordinates":[-0.06610210657271,51.5571610578226],"type":"Point"}
}