{
  "type": "Feature",
  "properties": {
    "iso:country":"GB",
    "wof:name":"S74 0LR",
    "wof:placetype":"postalcode"
},
  "geometry": {"coordinates":[-1.45411964861801,53.49526776258058],"type":"Point"}
}