{
  "type": "Feature",
  "properties": {
    "iso:country":"GB",
    "wof:name":"SS1 2SA",
    "wof:placetype":"postalcode"
},
  "geometry": {"coordinates":[0.72566176845125,51.53761218981581],"type":"Point"}
}