{
  "type": "Feature",
  "properties": {
    "date:inception_lower":"1980-01-01",
    "date:inception_upper":"1980-01-31",
    "iso:country":"GB",
    "wof:name":"EX33 2LY",
    "wof:placetype":"postalcode"
},
  "geometry": {"coordinates":[-4.154905,51.125183],"type":"Point"}
}