{
  "type": "Feature",
  "properties": {
    "date:inception_lower":"1980-01-01",
    "date:inception_upper":"1980-01-31",
    "iso:country":"GB",
    "wof:name":"PE7 3BL",
    "wof:placetype":"postalcode"
},
  "geometry": {"coordinates":[-0.230864,52.539276],"type":"Point"}
}