{
  "type": "Feature",
  "properties": {
    "iso:country":"GB",
    "wof:name":"PE7 3BL",
    "wof:placetype":"postalcode"
},
  "geometry": {"coordinates":[-0.23086373650202,52.53927633184837],"type":"Point"}
}