{
  "type": "Feature",
  "properties": {
    "iso:country":"GB",
    "wof:name":"RH14 0SH",
    "wof:placetype":"postalcode"
},
  "geometry": {"coordinates":[-0.51753817890657,51.07635383155888],"type":"Point"}
}