{
  "type": "Feature",
  "properties": {
    "iso:country":"GB",
    "wof:name":"SE24 9QL",
    "wof:placetype":"postalcode"
},
  "geometry": {"coordinates":[-0.1014427799588,51.45323568124326],"type":"Point"}
}