{
  "type": "Feature",
  "properties": {
    "iso:country":"GB",
    "wof:name":"YO25 9XT",
    "wof:placetype":"postalcode"
},
  "geometry": {"coordinates":[-0.57546892003152,54.01868394705883],"type":"Point"}
}