{
  "type": "Feature",
  "properties": {
    "date:inception_lower": "1980-01-01",
    "date:inception_upper": "1980-01-01",
    "iso:country": "GB",
    "wof:name": "YO25 9XT",
    "wof:placetype": "postalcode"
  },
  "geometry": {"coordinates":[-0.575469,54.018684],"type":"Point"}
}
