{
  "type": "Feature",
  "properties": {
    "date:inception_lower": "1980-01-01",
    "date:inception_upper": "1980-01-01",
    "iso:country": "GB",
    "wof:name": "DN2 6PU",
    "wof:placetype": "postalcode"
  },
  "geometry": {"coordinates":[-1.094973,53.532001],"type":"Point"}
}
