{
  "type": "Feature",
  "properties": {
    "iso:country":"GB",
    "wof:name":"DN2 6PU",
    "wof:placetype":"postalcode"
},
  "geometry": {"coordinates":[-1.09497303200544,53.5320009289768],"type":"Point"}
}