{
  "type": "Feature",
  "properties": {
    "iso:country": "GB",
    "wof:name": "DN2 6PU",
    "wof:placetype": "postalcode"
  },
  "geometry": {"coordinates":[-1.094973,53.532001],"type":"Point"}
}
