{
  "type": "Feature",
  "properties": {
    "iso:country":"GB",
    "wof:name":"NW1 1LQ",
    "wof:placetype":"postalcode"
},
  "geometry": {"coordinates":[-0.1310707737505,51.52915024800922],"type":"Point"}
}