{
  "type": "Feature",
  "properties": {
    "iso:country":"GB",
    "wof:name":"N17 0JJ",
    "wof:placetype":"postalcode"
},
  "geometry": {"coordinates":[-0.05934040578883,51.60144543818432],"type":"Point"}
}