{
  "type": "Feature",
  "properties": {
    "iso:country":"GB",
    "wof:name":"BB12 7JD",
    "wof:placetype":"postalcode"
},
  "geometry": {"coordinates":[-2.33802726764424,53.80878846155473],"type":"Point"}
}