{
  "type": "Feature",
  "properties": {
    "iso:country": "GB",
    "wof:name": "BB12 7JD",
    "wof:placetype": "postalcode"
  },
  "geometry": {"coordinates":[-2.338027,53.808788],"type":"Point"}
}
