{
  "type": "Feature",
  "properties": {
    "iso:country":"GB",
    "wof:name":"UB3 2HU",
    "wof:placetype":"postalcode"
},
  "geometry": {"coordinates":[-0.41303854433681,51.51370946276433],"type":"Point"}
}