{
  "type": "Feature",
  "properties": {
    "date:inception_lower": "1980-01-01",
    "date:inception_upper": "1980-01-01",
    "iso:country": "GB",
    "wof:name": "G43 2XN",
    "wof:placetype": "postalcode"
  },
  "geometry": {"coordinates":[-4.294726,55.817348],"type":"Point"}
}
