{
  "type": "Feature",
  "properties": {
    "iso:country": "GB",
    "wof:name": "G43 2XN",
    "wof:placetype": "postalcode"
  },
  "geometry": {"coordinates":[-4.294726,55.817348],"type":"Point"}
}
