{
  "type": "Feature",
  "properties": {
    "date:inception_lower": "2019-06-01",
    "date:inception_upper": "2019-06-01",
    "iso:country": "GB",
    "wof:name": "YO7 3FG",
    "wof:placetype": "postalcode"
  },
  "geometry": {"coordinates":[-1.357153,54.222057],"type":"Point"}
}
