{
  "type": "Feature",
  "properties": {
    "date:inception_lower": "1990-07-01",
    "date:inception_upper": "1990-07-01",
    "iso:country": "GB",
    "wof:name": "OL11 3TS",
    "wof:placetype": "postalcode"
  },
  "geometry": {"coordinates":[-2.164003,53.607496],"type":"Point"}
}
