{
  "type": "Feature",
  "properties": {
    "iso:country":"GB",
    "wof:name":"SK10 4RP",
    "wof:placetype":"postalcode"
},
  "geometry": {"coordinates":[-2.18557710592063,53.2711323139192],"type":"Point"}
}