{
  "type": "Feature",
  "properties": {
    "iso:country": "GB",
    "wof:name": "BN1 2TE",
    "wof:placetype": "postalcode"
  },
  "geometry": {"coordinates":[-0.145989,50.822696],"type":"Point"}
}
