{
  "type": "Feature",
  "properties": {
    "iso:country":"GB",
    "wof:name":"M3 4DQ",
    "wof:placetype":"postalcode"
},
  "geometry": {"coordinates":[-2.2514328433677,53.47761494923583],"type":"Point"}
}