{
  "type": "Feature",
  "properties": {
    "iso:country":"GB",
    "wof:name":"LE2 6NB",
    "wof:placetype":"postalcode"
},
  "geometry": {"coordinates":[-1.14095666727743,52.59873364080177],"type":"Point"}
}