{
  "type": "Feature",
  "properties": {
    "iso:country":"GB",
    "wof:name":"PE29 6JZ",
    "wof:placetype":"postalcode"
},
  "geometry": {"coordinates":[-0.21232727079995,52.33466509087035],"type":"Point"}
}