{
  "type": "Feature",
  "properties": {
    "iso:country":"GB",
    "wof:name":"ME2 2NF",
    "wof:placetype":"postalcode"
},
  "geometry": {"coordinates":[0.4817409711226,51.3840425184834],"type":"Point"}
}