{
  "type": "Feature",
  "properties": {
    "iso:country":"GB",
    "wof:name":"S70 2NN",
    "wof:placetype":"postalcode"
},
  "geometry": {"coordinates":[-1.49094018471664,53.55479002312112],"type":"Point"}
}