{
  "type": "Feature",
  "properties": {
    "iso:country":"GB",
    "wof:name":"TS4 2RD",
    "wof:placetype":"postalcode"
},
  "geometry": {"coordinates":[-1.2278037052908,54.56262318380409],"type":"Point"}
}