{
  "type": "Feature",
  "properties": {
    "iso:country":"GB",
    "wof:name":"ST9 0PW",
    "wof:placetype":"postalcode"
},
  "geometry": {"coordinates":[-2.10327871749161,53.02515086062984],"type":"Point"}
}