{
  "type": "Feature",
  "properties": {
    "date:inception_lower": "1985-04-01",
    "date:inception_upper": "1985-04-01",
    "iso:country": "GB",
    "wof:name": "ST9 0PW",
    "wof:placetype": "postalcode"
  },
  "geometry": {"coordinates":[-2.103279,53.025151],"type":"Point"}
}
