{
  "type": "Feature",
  "properties": {
    "iso:country":"GB",
    "wof:name":"DE73 7HW",
    "wof:placetype":"postalcode"
},
  "geometry": {"coordinates":[-1.48209327647838,52.83917624476869],"type":"Point"}
}