{
  "type": "Feature",
  "properties": {
    "iso:country": "GB",
    "wof:name": "DE73 7HW",
    "wof:placetype": "postalcode"
  },
  "geometry": {"coordinates":[-1.482093,52.839176],"type":"Point"}
}
