{
  "type": "Feature",
  "properties": {
    "iso:country":"GB",
    "wof:name":"HX3 0RY",
    "wof:placetype":"postalcode"
},
  "geometry": {"coordinates":[-1.8642870314983,53.70259103227072],"type":"Point"}
}