{
  "type": "Feature",
  "properties": {
    "iso:country":"GB",
    "wof:name":"CV10 0DR",
    "wof:placetype":"postalcode"
},
  "geometry": {"coordinates":[-1.46122708817571,52.53800791659258],"type":"Point"}
}