{
  "type": "Feature",
  "properties": {
    "iso:country":"GB",
    "wof:name":"ST3 5RG",
    "wof:placetype":"postalcode"
},
  "geometry": {"coordinates":[-2.10854478417762,52.99085252749337],"type":"Point"}
}