{
  "type": "Feature",
  "properties": {
    "iso:country":"GB",
    "wof:name":"BS24 7BZ",
    "wof:placetype":"postalcode"
},
  "geometry": {"coordinates":[-2.92219969312313,51.35073363360872],"type":"Point"}
}