{
  "type": "Feature",
  "properties": {
    "date:inception_lower": "2000-12-01",
    "date:inception_upper": "2000-12-01",
    "iso:country": "GB",
    "wof:name": "BS24 7BZ",
    "wof:placetype": "postalcode"
  },
  "geometry": {"coordinates":[-2.9222,51.350734],"type":"Point"}
}
