{
  "type": "Feature",
  "properties": {
    "iso:country": "GB",
    "wof:name": "SY3 0JT",
    "wof:placetype": "postalcode"
  },
  "geometry": {"coordinates":[-2.778815,52.676032],"type":"Point"}
}
