{
  "type": "Feature",
  "properties": {
    "iso:country":"GB",
    "wof:name":"SY3 0JT",
    "wof:placetype":"postalcode"
},
  "geometry": {"coordinates":[-2.77881549586803,52.67603177307539],"type":"Point"}
}