{
  "type": "Feature",
  "properties": {
    "iso:country":"GB",
    "wof:name":"B69 2DZ",
    "wof:placetype":"postalcode"
},
  "geometry": {"coordinates":[-2.03011327787164,52.5044379561601],"type":"Point"}
}