{
  "type": "Feature",
  "properties": {
    "date:inception_lower": "1980-01-01",
    "date:inception_upper": "1980-01-01",
    "iso:country": "GB",
    "wof:name": "CO9 3JG",
    "wof:placetype": "postalcode"
  },
  "geometry": {"coordinates":[0.588466,51.975273],"type":"Point"}
}
