{
  "type": "Feature",
  "properties": {
    "date:inception_lower":"1980-01-01",
    "date:inception_upper":"1980-01-31",
    "iso:country":"GB",
    "wof:name":"DG3 4BP",
    "wof:placetype":"postalcode"
},
  "geometry": {"coordinates":[-3.814617,55.232401],"type":"Point"}
}