{
  "type": "Feature",
  "properties": {
    "date:inception_lower": "1996-06-01",
    "date:inception_upper": "1996-06-01",
    "iso:country": "GB",
    "wof:name": "GU47 8HX",
    "wof:placetype": "postalcode"
  },
  "geometry": {"coordinates":[-0.812135,51.352257],"type":"Point"}
}
