{
  "type": "Feature",
  "properties": {
    "iso:country":"GB",
    "wof:name":"SG17 5JW",
    "wof:placetype":"postalcode"
},
  "geometry": {"coordinates":[-0.30209050066325,52.03485879842199],"type":"Point"}
}