{
  "type": "Feature",
  "properties": {
    "date:inception_lower":"2002-09-01",
    "date:inception_upper":"2002-09-30",
    "iso:country":"GB",
    "wof:name":"SG17 5JW",
    "wof:placetype":"postalcode"
},
  "geometry": {"coordinates":[-0.30209,52.034859],"type":"Point"}
}