{
  "type": "Feature",
  "properties": {
    "date:inception_lower":"1980-01-01",
    "date:inception_upper":"1980-01-31",
    "iso:country":"GB",
    "wof:name":"SA20 0SR",
    "wof:placetype":"postalcode"
},
  "geometry": {"coordinates":[-3.820084,52.042576],"type":"Point"}
}