{
  "type": "Feature",
  "properties": {
    "iso:country":"GB",
    "wof:name":"SA20 0SR",
    "wof:placetype":"postalcode"
},
  "geometry": {"coordinates":[-3.81964515007021,52.04287028304277],"type":"Point"}
}