{
  "type": "Feature",
  "properties": {
    "date:inception_lower": "1985-04-01",
    "date:inception_upper": "1985-04-01",
    "iso:country": "GB",
    "wof:name": "CV2 2QF",
    "wof:placetype": "postalcode"
  },
  "geometry": {"coordinates":[-1.437485,52.427535],"type":"Point"}
}
