{
  "type": "Feature",
  "properties": {
    "iso:country": "GB",
    "wof:name": "ML5 5BS",
    "wof:placetype": "postalcode"
  },
  "geometry": {"coordinates":[-4.039028,55.844888],"type":"Point"}
}
