{
  "type": "Feature",
  "properties": {
    "iso:country":"GB",
    "wof:name":"NG19 0HP",
    "wof:placetype":"postalcode"
},
  "geometry": {"coordinates":[-1.14532625677265,53.15518690563118],"type":"Point"}
}