{
  "type": "Feature",
  "properties": {
    "iso:country":"GB",
    "wof:name":"GU31 4EF",
    "wof:placetype":"postalcode"
},
  "geometry": {"coordinates":[-0.93108881003205,51.00421413922059],"type":"Point"}
}