{
  "type": "Feature",
  "properties": {
    "iso:country":"GB",
    "wof:name":"NR33 8JH",
    "wof:placetype":"postalcode"
},
  "geometry": {"coordinates":[1.70135737498982,52.44964176954814],"type":"Point"}
}