{
  "type": "Feature",
  "properties": {
    "iso:country": "GB",
    "wof:name": "NR33 8JH",
    "wof:placetype": "postalcode"
  },
  "geometry": {"coordinates":[1.701357,52.449642],"type":"Point"}
}
