{
  "type": "Feature",
  "properties": {
    "iso:country": "GB",
    "wof:name": "BN8 5UT",
    "wof:placetype": "postalcode"
  },
  "geometry": {"coordinates":[0.09076,50.894902],"type":"Point"}
}
