{
  "type": "Feature",
  "properties": {
    "date:inception_lower":"2005-06-01",
    "date:inception_upper":"2005-06-30",
    "iso:country":"GB",
    "wof:name":"HU13 0RA",
    "wof:placetype":"postalcode"
},
  "geometry": {"coordinates":[-0.436844,53.723376],"type":"Point"}
}