{
  "type": "Feature",
  "properties": {
    "date:inception_lower": "1980-01-01",
    "date:inception_upper": "1980-01-01",
    "iso:country": "GB",
    "wof:name": "CO16 8PZ",
    "wof:placetype": "postalcode"
  },
  "geometry": {"coordinates":[1.081882,51.802429],"type":"Point"}
}
