{
  "type": "Feature",
  "properties": {
    "iso:country":"GB",
    "wof:name":"CO16 8PZ",
    "wof:placetype":"postalcode"
},
  "geometry": {"coordinates":[1.08188224508142,51.80242920464717],"type":"Point"}
}