{
  "type": "Feature",
  "properties": {
    "iso:country":"GB",
    "wof:name":"NW3 5ED",
    "wof:placetype":"postalcode"
},
  "geometry": {"coordinates":[-0.17446381976694,51.54218018651468],"type":"Point"}
}