{
  "type": "Feature",
  "properties": {
    "iso:country":"GB",
    "wof:name":"NW7 3EH",
    "wof:placetype":"postalcode"
},
  "geometry": {"coordinates":[-0.26341403174755,51.61219559607837],"type":"Point"}
}