{
  "type": "Feature",
  "properties": {
    "iso:country":"GB",
    "wof:name":"LU6 1TR",
    "wof:placetype":"postalcode"
},
  "geometry": {"coordinates":[-0.54392798480762,51.88736291596314],"type":"Point"}
}