{
  "type": "Feature",
  "properties": {
    "iso:country":"GB",
    "wof:name":"NR20 4LE",
    "wof:placetype":"postalcode"
},
  "geometry": {"coordinates":[0.97772030826067,52.72789355838412],"type":"Point"}
}