{
  "type": "Feature",
  "properties": {
    "iso:country":"GB",
    "wof:name":"SE1 4YB",
    "wof:placetype":"postalcode"
},
  "geometry": {"coordinates":[-0.09217088741242,51.5009258514346],"type":"Point"}
}