{
  "type": "Feature",
  "properties": {
    "date:inception_lower":"2017-12-01",
    "date:inception_upper":"2017-12-31",
    "iso:country":"GB",
    "wof:name":"GL7 1ZU",
    "wof:placetype":"postalcode"
},
  "geometry": {"coordinates":[-1.971825,51.707891],"type":"Point"}
}