{
  "type": "Feature",
  "properties": {
    "iso:country": "GB",
    "wof:name": "GL7 1ZU",
    "wof:placetype": "postalcode"
  },
  "geometry": {"coordinates":[-1.971825,51.707891],"type":"Point"}
}
