{
  "type": "Feature",
  "properties": {
    "date:inception_lower": "2019-02-01",
    "date:inception_upper": "2019-02-01",
    "iso:country": "GB",
    "wof:name": "YO25 9FJ",
    "wof:placetype": "postalcode"
  },
  "geometry": {"coordinates":[-0.436564,53.956403],"type":"Point"}
}
