{
  "type": "Feature",
  "properties": {
    "iso:country":"GB",
    "wof:name":"SS0 0SR",
    "wof:placetype":"postalcode"
},
  "geometry": {"coordinates":[0.70111456514296,51.55146383406002],"type":"Point"}
}