{
  "type": "Feature",
  "properties": {
    "date:inception_lower":"1992-01-01",
    "date:inception_upper":"1992-01-31",
    "iso:country":"GB",
    "wof:name":"PE2 7DD",
    "wof:placetype":"postalcode"
},
  "geometry": {"coordinates":[-0.269314,52.560056],"type":"Point"}
}