{
  "type": "Feature",
  "properties": {
    "iso:country":"GB",
    "wof:name":"B60 3NB",
    "wof:placetype":"postalcode"
},
  "geometry": {"coordinates":[-2.07242032993044,52.32314394375057],"type":"Point"}
}