{
  "type": "Feature",
  "properties": {
    "iso:country":"GB",
    "wof:name":"DN9 3JD",
    "wof:placetype":"postalcode"
},
  "geometry": {"coordinates":[-1.01948764781483,53.50280368668075],"type":"Point"}
}