{
  "type": "Feature",
  "properties": {
    "date:inception_lower": "1980-01-01",
    "date:inception_upper": "1980-01-01",
    "iso:country": "GB",
    "wof:name": "DN9 3JD",
    "wof:placetype": "postalcode"
  },
  "geometry": {"coordinates":[-1.019488,53.502804],"type":"Point"}
}
