{
  "type": "Feature",
  "properties": {
    "iso:country": "GB",
    "wof:name": "RM12 6RZ",
    "wof:placetype": "postalcode"
  },
  "geometry": {"coordinates":[0.211242,51.5497],"type":"Point"}
}
