{
  "type": "Feature",
  "properties": {
    "date:inception_lower": "2019-05-01",
    "date:inception_upper": "2019-05-01",
    "iso:country": "GB",
    "wof:name": "CH64 5AB",
    "wof:placetype": "postalcode"
  },
  "geometry": {"coordinates":[-3.017222,53.264444],"type":"Point"}
}
