{
  "type": "Feature",
  "properties": {
    "iso:country":"GB",
    "wof:name":"DL2 2BW",
    "wof:placetype":"postalcode"
},
  "geometry": {"coordinates":[-1.54705532445794,54.48325715428674],"type":"Point"}
}