{
  "type": "Feature",
  "properties": {
    "iso:country":"GB",
    "wof:name":"MK40 1TN",
    "wof:placetype":"postalcode"
},
  "geometry": {"coordinates":[-0.46878865423647,52.13623667031266],"type":"Point"}
}