{
  "type": "Feature",
  "properties": {
    "iso:country":"GB",
    "wof:name":"TA5 1QG",
    "wof:placetype":"postalcode"
},
  "geometry": {"coordinates":[-3.13631742532719,51.19090385110122],"type":"Point"}
}