{
  "type": "Feature",
  "properties": {
    "iso:country": "GB",
    "wof:name": "TA5 1QG",
    "wof:placetype": "postalcode"
  },
  "geometry": {"coordinates":[-3.136317,51.190904],"type":"Point"}
}
