{
  "type": "Feature",
  "properties": {
    "date:inception_lower": "1994-12-01",
    "date:inception_upper": "1994-12-01",
    "iso:country": "GB",
    "wof:name": "TN23 5WN",
    "wof:placetype": "postalcode"
  },
  "geometry": {"coordinates":[0.84279,51.137101],"type":"Point"}
}
