{
  "type": "Feature",
  "properties": {
    "iso:country":"GB",
    "wof:name":"TN23 5WN",
    "wof:placetype":"postalcode"
},
  "geometry": {"coordinates":[0.84278988688018,51.13710107088041],"type":"Point"}
}