{
  "type": "Feature",
  "properties": {
    "date:inception_lower": "1999-12-01",
    "date:inception_upper": "1999-12-01",
    "iso:country": "GB",
    "wof:name": "ML6 8GH",
    "wof:placetype": "postalcode"
  },
  "geometry": {"coordinates":[-3.945024,55.846456],"type":"Point"}
}
