{
  "type": "Feature",
  "properties": {
    "iso:country": "GB",
    "wof:name": "LN5 9PN",
    "wof:placetype": "postalcode"
  },
  "geometry": {"coordinates":[-0.534202,53.167654],"type":"Point"}
}
