{
  "type": "Feature",
  "properties": {
    "iso:country":"GB",
    "wof:name":"TN29 9PU",
    "wof:placetype":"postalcode"
},
  "geometry": {"coordinates":[0.90436066642308,50.95712577145418],"type":"Point"}
}