{
  "type": "Feature",
  "properties": {
    "iso:country": "GB",
    "wof:name": "NG31 6LT",
    "wof:placetype": "postalcode"
  },
  "geometry": {"coordinates":[-0.643645,52.911882],"type":"Point"}
}
