{
  "type": "Feature",
  "properties": {
    "iso:country": "GB",
    "wof:name": "SO41 0TP",
    "wof:placetype": "postalcode"
  },
  "geometry": {"coordinates":[-1.567611,50.721495],"type":"Point"}
}
