{
  "type": "Feature",
  "properties": {
    "iso:country":"GB",
    "wof:name":"SO41 0TP",
    "wof:placetype":"postalcode"
},
  "geometry": {"coordinates":[-1.56841516247003,50.72184011450509],"type":"Point"}
}