{
  "type": "Feature",
  "properties": {
    "date:inception_lower": "1986-01-01",
    "date:inception_upper": "1986-01-01",
    "iso:country": "GB",
    "wof:name": "SO41 0TP",
    "wof:placetype": "postalcode"
  },
  "geometry": {"coordinates":[-1.567611,50.721495],"type":"Point"}
}
