{
  "type": "Feature",
  "properties": {
    "date:inception_lower": "1980-01-01",
    "date:inception_upper": "1980-01-01",
    "iso:country": "GB",
    "wof:name": "LA13 0RH",
    "wof:placetype": "postalcode"
  },
  "geometry": {"coordinates":[-3.1865,54.122973],"type":"Point"}
}
