{
  "type": "Feature",
  "properties": {
    "iso:country":"GB",
    "wof:name":"LA13 0RH",
    "wof:placetype":"postalcode"
},
  "geometry": {"coordinates":[-3.18649999493401,54.12297301635146],"type":"Point"}
}