{
  "type": "Feature",
  "properties": {
    "iso:country": "GB",
    "wof:name": "RH16 3JW",
    "wof:placetype": "postalcode"
  },
  "geometry": {"coordinates":[-0.099145,50.999126],"type":"Point"}
}
