{
  "type": "Feature",
  "properties": {
    "iso:country":"GB",
    "wof:name":"RH16 3JW",
    "wof:placetype":"postalcode"
},
  "geometry": {"coordinates":[-0.0991451140846,50.99912643370998],"type":"Point"}
}