{
  "type": "Feature",
  "properties": {
    "iso:country":"GB",
    "wof:name":"PE7 1XN",
    "wof:placetype":"postalcode"
},
  "geometry": {"coordinates":[-0.11370796377532,52.56128466629468],"type":"Point"}
}