{
  "type": "Feature",
  "properties": {
    "date:inception_lower": "1980-01-01",
    "date:inception_upper": "1980-01-01",
    "iso:country": "GB",
    "wof:name": "PE7 1XN",
    "wof:placetype": "postalcode"
  },
  "geometry": {"coordinates":[-0.113708,52.561285],"type":"Point"}
}
