{
  "type": "Feature",
  "properties": {
    "iso:country": "GB",
    "wof:name": "WD25 7BJ",
    "wof:placetype": "postalcode"
  },
  "geometry": {"coordinates":[-0.408803,51.694591],"type":"Point"}
}
