{
  "type": "Feature",
  "properties": {
    "iso:country":"GB",
    "wof:name":"LE4 9HU",
    "wof:placetype":"postalcode"
},
  "geometry": {"coordinates":[-1.08209639218202,52.6620495333602],"type":"Point"}
}