{
  "type": "Feature",
  "properties": {
    "date:inception_lower": "1980-01-01",
    "date:inception_upper": "1980-01-01",
    "iso:country": "GB",
    "wof:name": "DN1 1BJ",
    "wof:placetype": "postalcode"
  },
  "geometry": {"coordinates":[-1.13564,53.523493],"type":"Point"}
}
