{
  "type": "Feature",
  "properties": {
    "iso:country":"GB",
    "wof:name":"DN1 1BJ",
    "wof:placetype":"postalcode"
},
  "geometry": {"coordinates":[-1.13563975528055,53.5234928298424],"type":"Point"}
}