{
  "type": "Feature",
  "properties": {
    "iso:country": "GB",
    "wof:name": "IP4 2NA",
    "wof:placetype": "postalcode"
  },
  "geometry": {"coordinates":[1.163173,52.057023],"type":"Point"}
}
