{
  "type": "Feature",
  "properties": {
    "date:inception_lower":"1980-01-01",
    "date:inception_upper":"1980-01-31",
    "iso:country":"GB",
    "wof:name":"IP4 2NA",
    "wof:placetype":"postalcode"
},
  "geometry": {"coordinates":[1.163173,52.057023],"type":"Point"}
}