{
  "type": "Feature",
  "properties": {
    "iso:country": "GB",
    "wof:name": "HD8 8PL",
    "wof:placetype": "postalcode"
  },
  "geometry": {"coordinates":[-1.667527,53.584407],"type":"Point"}
}
