{
  "type": "Feature",
  "properties": {
    "date:inception_lower": "1980-01-01",
    "date:inception_upper": "1980-01-01",
    "iso:country": "GB",
    "wof:name": "HD8 8PL",
    "wof:placetype": "postalcode"
  },
  "geometry": {"coordinates":[-1.667527,53.584407],"type":"Point"}
}
