{
  "type": "Feature",
  "properties": {
    "iso:country":"GB",
    "wof:name":"BD9 5QD",
    "wof:placetype":"postalcode"
},
  "geometry": {"coordinates":[-1.78866273657346,53.8131423401442],"type":"Point"}
}