{
  "type": "Feature",
  "properties": {
    "iso:country":"GB",
    "wof:name":"B19 3NR",
    "wof:placetype":"postalcode"
},
  "geometry": {"coordinates":[-1.89721472673587,52.49125416402229],"type":"Point"}
}