{
  "type": "Feature",
  "properties": {
    "iso:country": "GB",
    "wof:name": "PE14 7AS",
    "wof:placetype": "postalcode"
  },
  "geometry": {"coordinates":[0.190394,52.682272],"type":"Point"}
}
