{
  "type": "Feature",
  "properties": {
    "iso:country":"GB",
    "wof:name":"PE14 7AS",
    "wof:placetype":"postalcode"
},
  "geometry": {"coordinates":[0.19037903884773,52.68225251675747],"type":"Point"}
}