{
  "type": "Feature",
  "properties": {
    "date:inception_lower": "1983-03-01",
    "date:inception_upper": "1983-03-01",
    "iso:country": "GB",
    "wof:name": "PE14 7AS",
    "wof:placetype": "postalcode"
  },
  "geometry": {"coordinates":[0.190394,52.682272],"type":"Point"}
}
