{
  "type": "Feature",
  "properties": {
    "iso:country":"GB",
    "wof:name":"TR26 2PH",
    "wof:placetype":"postalcode"
},
  "geometry": {"coordinates":[-5.47412907125294,50.198846059662],"type":"Point"}
}