{
  "type": "Feature",
  "properties": {
    "date:inception_lower":"1980-01-01",
    "date:inception_upper":"1980-01-31",
    "iso:country":"GB",
    "wof:name":"NP7 0BY",
    "wof:placetype":"postalcode"
},
  "geometry": {"coordinates":[-3.098119,51.822297],"type":"Point"}
}