{
  "type": "Feature",
  "properties": {
    "iso:country": "GB",
    "wof:name": "SE19 2DY",
    "wof:placetype": "postalcode"
  },
  "geometry": {"coordinates":[-0.083373,51.411108],"type":"Point"}
}
