{
  "type": "Feature",
  "properties": {
    "date:inception_lower":"1980-01-01",
    "date:inception_upper":"1980-01-31",
    "iso:country":"GB",
    "wof:name":"SE19 2DY",
    "wof:placetype":"postalcode"
},
  "geometry": {"coordinates":[-0.083373,51.411108],"type":"Point"}
}