{
  "type": "Feature",
  "properties": {
    "iso:country":"GB",
    "wof:name":"G81 1RB",
    "wof:placetype":"postalcode"
},
  "geometry": {"coordinates":[-4.39456435739128,55.89843702362211],"type":"Point"}
}