{
  "type": "Feature",
  "properties": {
    "date:inception_lower": "1999-06-01",
    "date:inception_upper": "1999-06-01",
    "iso:country": "GB",
    "wof:name": "CH45 2JT",
    "wof:placetype": "postalcode"
  },
  "geometry": {"coordinates":[-3.043912,53.439806],"type":"Point"}
}
