{
  "type": "Feature",
  "properties": {
    "iso:country": "GB",
    "wof:name": "CH45 2JT",
    "wof:placetype": "postalcode"
  },
  "geometry": {"coordinates":[-3.043387,53.439892],"type":"Point"}
}
