{
  "type": "Feature",
  "properties": {
    "iso:country":"GB",
    "wof:name":"LE4 2RJ",
    "wof:placetype":"postalcode"
},
  "geometry": {"coordinates":[-1.13858876323004,52.66825401765347],"type":"Point"}
}