{
  "type": "Feature",
  "properties": {
    "iso:country": "GB",
    "wof:name": "DE4 2EH",
    "wof:placetype": "postalcode"
  },
  "geometry": {"coordinates":[-1.612151,53.192165],"type":"Point"}
}
