{
  "type": "Feature",
  "properties": {
    "iso:country":"GB",
    "wof:name":"DE4 2EH",
    "wof:placetype":"postalcode"
},
  "geometry": {"coordinates":[-1.6121510637753,53.19216543134586],"type":"Point"}
}