{
  "type": "Feature",
  "properties": {
    "iso:country":"GB",
    "wof:name":"NG12 3FP",
    "wof:placetype":"postalcode"
},
  "geometry": {"coordinates":[-0.95902327673438,52.89494983095835],"type":"Point"}
}