{
  "type": "Feature",
  "properties": {
    "iso:country": "GB",
    "wof:name": "NR18 0YT",
    "wof:placetype": "postalcode"
  },
  "geometry": {"coordinates":[1.140045,52.581427],"type":"Point"}
}
