{
  "type": "Feature",
  "properties": {
    "date:inception_lower": "1980-01-01",
    "date:inception_upper": "1980-01-01",
    "iso:country": "GB",
    "wof:name": "GU4 7NT",
    "wof:placetype": "postalcode"
  },
  "geometry": {"coordinates":[-0.572565,51.267375],"type":"Point"}
}
