{
  "type": "Feature",
  "properties": {
    "iso:country":"GB",
    "wof:name":"GU35 8PE",
    "wof:placetype":"postalcode"
},
  "geometry": {"coordinates":[-0.83077094139106,51.12011141334269],"type":"Point"}
}