{
  "type": "Feature",
  "properties": {
    "iso:country": "GB",
    "wof:name": "AB41 8XB",
    "wof:placetype": "postalcode"
  },
  "geometry": {"coordinates":[-2.077393,57.45472],"type":"Point"}
}
