{
  "type": "Feature",
  "properties": {
    "iso:country":"GB",
    "wof:name":"AB41 8XB",
    "wof:placetype":"postalcode"
},
  "geometry": {"coordinates":[-2.07739278703489,57.45471989366236],"type":"Point"}
}