{
  "type": "Feature",
  "properties": {
    "date:inception_lower": "1980-01-01",
    "date:inception_upper": "1980-01-01",
    "iso:country": "GB",
    "wof:name": "BA1 8BU",
    "wof:placetype": "postalcode"
  },
  "geometry": {"coordinates":[-2.347582,51.414111],"type":"Point"}
}
