{
  "type": "Feature",
  "properties": {
    "iso:country":"GB",
    "wof:name":"LL13 8RG",
    "wof:placetype":"postalcode"
},
  "geometry": {"coordinates":[-2.98424136906935,53.04951921569607],"type":"Point"}
}