{
  "type": "Feature",
  "properties": {
    "iso:country":"GB",
    "wof:name":"TF1 3EZ",
    "wof:placetype":"postalcode"
},
  "geometry": {"coordinates":[-2.52368247881248,52.70425046822189],"type":"Point"}
}