{
  "type": "Feature",
  "properties": {
    "iso:country": "GB",
    "wof:name": "TF1 3EZ",
    "wof:placetype": "postalcode"
  },
  "geometry": {"coordinates":[-2.52325,52.704169],"type":"Point"}
}
