{
  "type": "Feature",
  "properties": {
    "date:inception_lower": "1996-12-01",
    "date:inception_upper": "1996-12-01",
    "iso:country": "GB",
    "wof:name": "TF1 3EZ",
    "wof:placetype": "postalcode"
  },
  "geometry": {"coordinates":[-2.52325,52.704169],"type":"Point"}
}
