{
  "type": "Feature",
  "properties": {
    "iso:country":"GB",
    "wof:name":"CH6 5EQ",
    "wof:placetype":"postalcode"
},
  "geometry": {"coordinates":[-3.12366378005795,53.24296773432344],"type":"Point"}
}