{
  "type": "Feature",
  "properties": {
    "iso:country": "GB",
    "wof:name": "PO21 5TP",
    "wof:placetype": "postalcode"
  },
  "geometry": {"coordinates":[-0.699973,50.7941],"type":"Point"}
}
