{
  "type": "Feature",
  "properties": {
    "date:inception_lower": "1995-12-01",
    "date:inception_upper": "1995-12-01",
    "iso:country": "GB",
    "wof:name": "GL4 4NS",
    "wof:placetype": "postalcode"
  },
  "geometry": {"coordinates":[-2.217098,51.851732],"type":"Point"}
}
