{
  "type": "Feature",
  "properties": {
    "iso:country": "GB",
    "wof:name": "GL4 4NS",
    "wof:placetype": "postalcode"
  },
  "geometry": {"coordinates":[-2.217273,51.851849],"type":"Point"}
}
