{
  "type": "Feature",
  "properties": {
    "iso:country":"GB",
    "wof:name":"DA8 1DT",
    "wof:placetype":"postalcode"
},
  "geometry": {"coordinates":[0.15852616880755,51.47874623977191],"type":"Point"}
}