{
  "type": "Feature",
  "properties": {
    "date:inception_lower": "1980-01-01",
    "date:inception_upper": "1980-01-01",
    "iso:country": "GB",
    "wof:name": "DA8 1DT",
    "wof:placetype": "postalcode"
  },
  "geometry": {"coordinates":[0.158526,51.478746],"type":"Point"}
}
