{
  "type": "Feature",
  "properties": {
    "iso:country":"GB",
    "wof:name":"PE4 6HF",
    "wof:placetype":"postalcode"
},
  "geometry": {"coordinates":[-0.2656269701613,52.60303274125643],"type":"Point"}
}