{
  "type": "Feature",
  "properties": {
    "iso:country": "GB",
    "wof:name": "BS25 1TD",
    "wof:placetype": "postalcode"
  },
  "geometry": {"coordinates":[-2.795673,51.314048],"type":"Point"}
}
