{
  "type": "Feature",
  "properties": {
    "iso:country":"GB",
    "wof:name":"HA0 4EB",
    "wof:placetype":"postalcode"
},
  "geometry": {"coordinates":[-0.28879773838733,51.54553112430284],"type":"Point"}
}