{
  "type": "Feature",
  "properties": {
    "iso:country":"GB",
    "wof:name":"HR4 7FF",
    "wof:placetype":"postalcode"
},
  "geometry": {"coordinates":[-2.80048922989637,52.08678684025169],"type":"Point"}
}