{
  "type": "Feature",
  "properties": {
    "date:inception_lower": "2000-06-01",
    "date:inception_upper": "2000-06-01",
    "iso:country": "GB",
    "wof:name": "HR4 7FF",
    "wof:placetype": "postalcode"
  },
  "geometry": {"coordinates":[-2.800489,52.086787],"type":"Point"}
}
