{
  "type": "Feature",
  "properties": {
    "iso:country":"GB",
    "wof:name":"SY5 7EJ",
    "wof:placetype":"postalcode"
},
  "geometry": {"coordinates":[-2.79004477376575,52.63441503574645],"type":"Point"}
}