{
  "type": "Feature",
  "properties": {
    "iso:country": "GB",
    "wof:name": "SY5 7EJ",
    "wof:placetype": "postalcode"
  },
  "geometry": {"coordinates":[-2.790045,52.634415],"type":"Point"}
}
