{
  "type": "Feature",
  "properties": {
    "iso:country":"GB",
    "wof:name":"NP22 3HP",
    "wof:placetype":"postalcode"
},
  "geometry": {"coordinates":[-3.25238020441501,51.78240619557273],"type":"Point"}
}