{
  "type": "Feature",
  "properties": {
    "date:inception_lower": "1980-01-01",
    "date:inception_upper": "1980-01-01",
    "iso:country": "GB",
    "wof:name": "DA2 6NL",
    "wof:placetype": "postalcode"
  },
  "geometry": {"coordinates":[0.244869,51.436287],"type":"Point"}
}
