{
  "type": "Feature",
  "properties": {
    "iso:country": "GB",
    "wof:name": "YO17 1ST",
    "wof:placetype": "postalcode"
  },
  "geometry": {"coordinates":[-0.789347,54.139186],"type":"Point"}
}
