{
  "type": "Feature",
  "properties": {
    "iso:country":"GB",
    "wof:name":"HR8 1RP",
    "wof:placetype":"postalcode"
},
  "geometry": {"coordinates":[-2.38990354267575,52.02177246319612],"type":"Point"}
}