{
  "type": "Feature",
  "properties": {
    "date:inception_lower": "1980-01-01",
    "date:inception_upper": "1980-01-01",
    "iso:country": "GB",
    "wof:name": "HR8 1RP",
    "wof:placetype": "postalcode"
  },
  "geometry": {"coordinates":[-2.389903,52.021772],"type":"Point"}
}
