{
  "type": "Feature",
  "properties": {
    "iso:country": "GB",
    "wof:name": "EX33 2PE",
    "wof:placetype": "postalcode"
  },
  "geometry": {"coordinates":[-4.150249,51.10462],"type":"Point"}
}
