{
  "type": "Feature",
  "properties": {
    "iso:country":"GB",
    "wof:name":"EX33 2PE",
    "wof:placetype":"postalcode"
},
  "geometry": {"coordinates":[-4.15024856564742,51.1046202305706],"type":"Point"}
}