{
  "type": "Feature",
  "properties": {
    "date:inception_lower": "1990-07-01",
    "date:inception_upper": "1990-07-01",
    "iso:country": "GB",
    "wof:name": "EX33 2PE",
    "wof:placetype": "postalcode"
  },
  "geometry": {"coordinates":[-4.150249,51.10462],"type":"Point"}
}
