{
  "type": "Feature",
  "properties": {
    "date:inception_lower": "1993-01-01",
    "date:inception_upper": "1993-01-01",
    "iso:country": "GB",
    "wof:name": "YO25 8NQ",
    "wof:placetype": "postalcode"
  },
  "geometry": {"coordinates":[-0.387731,53.98932],"type":"Point"}
}
