{
  "type": "Feature",
  "properties": {
    "iso:country":"GB",
    "wof:name":"YO25 8NQ",
    "wof:placetype":"postalcode"
},
  "geometry": {"coordinates":[-0.38017971049985,53.99014400461737],"type":"Point"}
}