{
  "type": "Feature",
  "properties": {
    "date:inception_lower": "2018-01-01",
    "date:inception_upper": "2018-01-01",
    "iso:country": "GB",
    "wof:name": "PE20 3FE",
    "wof:placetype": "postalcode"
  },
  "geometry": {"coordinates":[-0.167403,52.952467],"type":"Point"}
}
