{
  "type": "Feature",
  "properties": {
    "iso:country": "GB",
    "wof:name": "BN18 9EU",
    "wof:placetype": "postalcode"
  },
  "geometry": {"coordinates":[-0.568191,50.84826],"type":"Point"}
}
