{
  "type": "Feature",
  "properties": {
    "iso:country":"GB",
    "wof:name":"BN18 9EU",
    "wof:placetype":"postalcode"
},
  "geometry": {"coordinates":[-0.56819117334904,50.84826047629772],"type":"Point"}
}