{
  "type": "Feature",
  "properties": {
    "iso:country":"GB",
    "wof:name":"WV4 5EZ",
    "wof:placetype":"postalcode"
},
  "geometry": {"coordinates":[-2.12567268941414,52.56319563919464],"type":"Point"}
}