{
  "type": "Feature",
  "properties": {
    "date:inception_lower":"2008-03-01",
    "date:inception_upper":"2008-03-31",
    "iso:country":"GB",
    "wof:name":"S60 3BL",
    "wof:placetype":"postalcode"
},
  "geometry": {"coordinates":[-1.338443,53.411988],"type":"Point"}
}