{
  "type": "Feature",
  "properties": {
    "iso:country": "GB",
    "wof:name": "S60 3BL",
    "wof:placetype": "postalcode"
  },
  "geometry": {"coordinates":[-1.338443,53.411988],"type":"Point"}
}
