{
  "type": "Feature",
  "properties": {
    "iso:country":"GB",
    "wof:name":"S60 3BL",
    "wof:placetype":"postalcode"
},
  "geometry": {"coordinates":[-1.33844287018105,53.41198819330648],"type":"Point"}
}