{
  "type": "Feature",
  "properties": {
    "iso:country":"GB",
    "wof:name":"B6 4RU",
    "wof:placetype":"postalcode"
},
  "geometry": {"coordinates":[-1.88856010522707,52.49496818513592],"type":"Point"}
}