{
  "type": "Feature",
  "properties": {
    "date:inception_lower": "2001-06-01",
    "date:inception_upper": "2001-06-01",
    "iso:country": "GB",
    "wof:name": "B6 4RU",
    "wof:placetype": "postalcode"
  },
  "geometry": {"coordinates":[-1.888555,52.494983],"type":"Point"}
}
