{
  "type": "Feature",
  "properties": {
    "date:inception_lower": "1980-12-01",
    "date:inception_upper": "1980-12-01",
    "iso:country": "GB",
    "wof:name": "G71 6RW",
    "wof:placetype": "postalcode"
  },
  "geometry": {"coordinates":[-4.085018,55.829441],"type":"Point"}
}
