{
  "type": "Feature",
  "properties": {
    "iso:country":"GB",
    "wof:name":"G71 6RW",
    "wof:placetype":"postalcode"
},
  "geometry": {"coordinates":[-4.08501852119558,55.82944135476513],"type":"Point"}
}