{
  "type": "Feature",
  "properties": {
    "iso:country":"GB",
    "wof:name":"PR1 9LE",
    "wof:placetype":"postalcode"
},
  "geometry": {"coordinates":[-2.70414425710408,53.73270288897908],"type":"Point"}
}