{
  "type": "Feature",
  "properties": {
    "iso:country": "GB",
    "wof:name": "SW15 5LZ",
    "wof:placetype": "postalcode"
  },
  "geometry": {"coordinates":[-0.242344,51.462789],"type":"Point"}
}
