{
  "type": "Feature",
  "properties": {
    "date:inception_lower": "1981-09-01",
    "date:inception_upper": "1981-09-01",
    "iso:country": "GB",
    "wof:name": "SW15 5LZ",
    "wof:placetype": "postalcode"
  },
  "geometry": {"coordinates":[-0.242344,51.462789],"type":"Point"}
}
