{
  "type": "Feature",
  "properties": {
    "iso:country":"GB",
    "wof:name":"NW6 5BS",
    "wof:placetype":"postalcode"
},
  "geometry": {"coordinates":[-0.1990355310706,51.53345964528246],"type":"Point"}
}