{
  "type": "Feature",
  "properties": {
    "iso:country":"GB",
    "wof:name":"OL1 3UF",
    "wof:placetype":"postalcode"
},
  "geometry": {"coordinates":[-2.10330595887147,53.54515816735416],"type":"Point"}
}