{
  "type": "Feature",
  "properties": {
    "date:inception_lower": "2001-12-01",
    "date:inception_upper": "2001-12-01",
    "iso:country": "GB",
    "wof:name": "CA11 7US",
    "wof:placetype": "postalcode"
  },
  "geometry": {"coordinates":[-2.750988,54.669041],"type":"Point"}
}
