{
  "type": "Feature",
  "properties": {
    "iso:country": "GB",
    "wof:name": "OX27 8TW",
    "wof:placetype": "postalcode"
  },
  "geometry": {"coordinates":[-1.147782,51.921894],"type":"Point"}
}
