{
  "type": "Feature",
  "properties": {
    "iso:country":"GB",
    "wof:name":"SR8 3PL",
    "wof:placetype":"postalcode"
},
  "geometry": {"coordinates":[-1.32945502845189,54.78759442924854],"type":"Point"}
}