{
  "type": "Feature",
  "properties": {
    "iso:country": "GB",
    "wof:name": "SR8 3PL",
    "wof:placetype": "postalcode"
  },
  "geometry": {"coordinates":[-1.329455,54.787594],"type":"Point"}
}
