{
  "type": "Feature",
  "properties": {
    "iso:country":"GB",
    "wof:name":"SW3 2RJ",
    "wof:placetype":"postalcode"
},
  "geometry": {"coordinates":[-0.1591860576015,51.49370580299261],"type":"Point"}
}