{
  "type": "Feature",
  "properties": {
    "iso:country":"GB",
    "wof:name":"CM3 6DT",
    "wof:placetype":"postalcode"
},
  "geometry": {"coordinates":[0.77714338666049,51.65159579900551],"type":"Point"}
}