{
  "type": "Feature",
  "properties": {
    "date:inception_lower": "1980-01-01",
    "date:inception_upper": "1980-01-01",
    "iso:country": "GB",
    "wof:name": "CM3 6DT",
    "wof:placetype": "postalcode"
  },
  "geometry": {"coordinates":[0.777143,51.651596],"type":"Point"}
}
