{
  "type": "Feature",
  "properties": {
    "iso:country":"GB",
    "wof:name":"DH4 7TQ",
    "wof:placetype":"postalcode"
},
  "geometry": {"coordinates":[-1.50451421270777,54.86455100647864],"type":"Point"}
}