{
  "type": "Feature",
  "properties": {
    "iso:country": "GB",
    "wof:name": "DH4 7TQ",
    "wof:placetype": "postalcode"
  },
  "geometry": {"coordinates":[-1.504514,54.864551],"type":"Point"}
}
