{
  "type": "Feature",
  "properties": {
    "iso:country":"GB",
    "wof:name":"NN3 2JA",
    "wof:placetype":"postalcode"
},
  "geometry": {"coordinates":[-0.87064234531099,52.25654386304807],"type":"Point"}
}