{
  "type": "Feature",
  "properties": {
    "iso:country":"GB",
    "wof:name":"LS2 9DU",
    "wof:placetype":"postalcode"
},
  "geometry": {"coordinates":[-1.55773784753534,53.81040153178751],"type":"Point"}
}