{
  "type": "Feature",
  "properties": {
    "iso:country":"GB",
    "wof:name":"DY5 2TU",
    "wof:placetype":"postalcode"
},
  "geometry": {"coordinates":[-2.13459055298686,52.45980178349858],"type":"Point"}
}