{
  "type": "Feature",
  "properties": {
    "date:inception_lower": "1990-07-01",
    "date:inception_upper": "1990-07-01",
    "iso:country": "GB",
    "wof:name": "DY5 2TU",
    "wof:placetype": "postalcode"
  },
  "geometry": {"coordinates":[-2.13457,52.459825],"type":"Point"}
}
