{
  "type": "Feature",
  "properties": {
    "iso:country":"GB",
    "wof:name":"WC2B 5RB",
    "wof:placetype":"postalcode"
},
  "geometry": {"coordinates":[-0.12381189958936,51.515644519231],"type":"Point"}
}