{
  "type": "Feature",
  "properties": {
    "iso:country":"GB",
    "wof:name":"DN3 3LZ",
    "wof:placetype":"postalcode"
},
  "geometry": {"coordinates":[-1.03920679282358,53.50886039703185],"type":"Point"}
}