{
  "type": "Feature",
  "properties": {
    "iso:country":"GB",
    "wof:name":"DE56 0PD",
    "wof:placetype":"postalcode"
},
  "geometry": {"coordinates":[-1.42297948144562,53.01035867471521],"type":"Point"}
}