{
  "type": "Feature",
  "properties": {
    "date:inception_lower":"1992-08-01",
    "date:inception_upper":"1992-08-31",
    "iso:country":"GB",
    "wof:name":"DE56 0PD",
    "wof:placetype":"postalcode"
},
  "geometry": {"coordinates":[-1.422979,53.010359],"type":"Point"}
}