{
  "type": "Feature",
  "properties": {
    "iso:country":"GB",
    "wof:name":"LE4 4HY",
    "wof:placetype":"postalcode"
},
  "geometry": {"coordinates":[-1.12047699725816,52.67987987941638],"type":"Point"}
}