{
  "type": "Feature",
  "properties": {
    "date:inception_lower": "1980-01-01",
    "date:inception_upper": "1980-01-01",
    "iso:country": "GB",
    "wof:name": "LE4 4HY",
    "wof:placetype": "postalcode"
  },
  "geometry": {"coordinates":[-1.120477,52.67988],"type":"Point"}
}
