{
  "type": "Feature",
  "properties": {
    "iso:country": "GB",
    "wof:name": "WF7 5FB",
    "wof:placetype": "postalcode"
  },
  "geometry": {"coordinates":[-1.360301,53.670437],"type":"Point"}
}
