{
  "type": "Feature",
  "properties": {
    "iso:country":"GB",
    "wof:name":"WF7 5FB",
    "wof:placetype":"postalcode"
},
  "geometry": {"coordinates":[-1.36030068219043,53.67043691408609],"type":"Point"}
}