{
  "type": "Feature",
  "properties": {
    "iso:country":"GB",
    "wof:name":"E3 3AP",
    "wof:placetype":"postalcode"
},
  "geometry": {"coordinates":[-0.01457982402808,51.52915178298133],"type":"Point"}
}