{
  "type": "Feature",
  "properties": {
    "iso:country":"GB",
    "wof:name":"UB6 9JQ",
    "wof:placetype":"postalcode"
},
  "geometry": {"coordinates":[-0.36463828399125,51.52875414316902],"type":"Point"}
}