{
  "type": "Feature",
  "properties": {
    "iso:country":"GB",
    "wof:name":"OX25 6NQ",
    "wof:placetype":"postalcode"
},
  "geometry": {"coordinates":[-1.27310217468773,51.95312372663366],"type":"Point"}
}