{
  "type": "Feature",
  "properties": {
    "date:inception_lower":"2000-10-01",
    "date:inception_upper":"2000-10-31",
    "iso:country":"GB",
    "wof:name":"OX25 6NQ",
    "wof:placetype":"postalcode"
},
  "geometry": {"coordinates":[-1.273102,51.953124],"type":"Point"}
}