{
  "type": "Feature",
  "properties": {
    "date:inception_lower": "1980-01-01",
    "date:inception_upper": "1980-01-01",
    "iso:country": "GB",
    "wof:name": "SK16 5JZ",
    "wof:placetype": "postalcode"
  },
  "geometry": {"coordinates":[-2.074366,53.470612],"type":"Point"}
}
