{
  "type": "Feature",
  "properties": {
    "iso:country":"GB",
    "wof:name":"HX6 2AH",
    "wof:placetype":"postalcode"
},
  "geometry": {"coordinates":[-1.90559358892184,53.70959638674943],"type":"Point"}
}