{
  "type": "Feature",
  "properties": {
    "date:inception_lower": "1994-12-01",
    "date:inception_upper": "1994-12-01",
    "iso:country": "GB",
    "wof:name": "HX6 2AH",
    "wof:placetype": "postalcode"
  },
  "geometry": {"coordinates":[-1.905594,53.709596],"type":"Point"}
}
