{
  "type": "Feature",
  "properties": {
    "iso:country":"GB",
    "wof:name":"CV21 3SD",
    "wof:placetype":"postalcode"
},
  "geometry": {"coordinates":[-1.23896720928376,52.37393971044878],"type":"Point"}
}