{
  "type": "Feature",
  "properties": {
    "iso:country":"GB",
    "wof:name":"BD13 3GE",
    "wof:placetype":"postalcode"
},
  "geometry": {"coordinates":[-1.86648971280764,53.79165598143653],"type":"Point"}
}