{
  "type": "Feature",
  "properties": {
    "date:inception_lower": "2010-02-01",
    "date:inception_upper": "2010-02-01",
    "iso:country": "GB",
    "wof:name": "BD13 3GE",
    "wof:placetype": "postalcode"
  },
  "geometry": {"coordinates":[-1.866492,53.79167],"type":"Point"}
}
