{
  "type": "Feature",
  "properties": {
    "iso:country":"GB",
    "wof:name":"SN10 4PD",
    "wof:placetype":"postalcode"
},
  "geometry": {"coordinates":[-1.97472344899696,51.29429784444407],"type":"Point"}
}