{
  "type": "Feature",
  "properties": {
    "date:inception_lower": "1980-01-01",
    "date:inception_upper": "1980-01-01",
    "iso:country": "GB",
    "wof:name": "SN10 4PD",
    "wof:placetype": "postalcode"
  },
  "geometry": {"coordinates":[-1.974723,51.294298],"type":"Point"}
}
