{
  "type": "Feature",
  "properties": {
    "date:inception_lower": "2022-05-01",
    "date:inception_upper": "2022-05-01",
    "iso:country": "GB",
    "wof:name": "CF5 9GZ",
    "wof:placetype": "postalcode"
  },
  "geometry": {"coordinates":[-3.223633,51.483609],"type":"Point"}
}
