{
  "type": "Feature",
  "properties": {
    "date:inception_lower":"2006-03-01",
    "date:inception_upper":"2006-03-31",
    "iso:country":"GB",
    "wof:name":"GU26 6JP",
    "wof:placetype":"postalcode"
},
  "geometry": {"coordinates":[-0.747754,51.121558],"type":"Point"}
}