{
  "type": "Feature",
  "properties": {
    "iso:country":"GB",
    "wof:name":"GU26 6JP",
    "wof:placetype":"postalcode"
},
  "geometry": {"coordinates":[-0.74777200447521,51.12161723217794],"type":"Point"}
}