{
  "type": "Feature",
  "properties": {
    "iso:country":"GB",
    "wof:name":"ML4 1DX",
    "wof:placetype":"postalcode"
},
  "geometry": {"coordinates":[-4.00248958494083,55.81989384733175],"type":"Point"}
}