{
  "type": "Feature",
  "properties": {
    "iso:country": "GB",
    "wof:name": "RG21 6AP",
    "wof:placetype": "postalcode"
  },
  "geometry": {"coordinates":[-1.095393,51.268805],"type":"Point"}
}
