{
  "type": "Feature",
  "properties": {
    "iso:country": "GB",
    "wof:name": "CA15 7LU",
    "wof:placetype": "postalcode"
  },
  "geometry": {"coordinates":[-3.488403,54.710309],"type":"Point"}
}
