{
  "type": "Feature",
  "properties": {
    "iso:country":"GB",
    "wof:name":"YO32 5SB",
    "wof:placetype":"postalcode"
},
  "geometry": {"coordinates":[-1.04122235177671,54.02592410189094],"type":"Point"}
}