{
  "type": "Feature",
  "properties": {
    "date:inception_lower":"1998-06-01",
    "date:inception_upper":"1998-06-30",
    "iso:country":"GB",
    "wof:name":"YO32 5SB",
    "wof:placetype":"postalcode"
},
  "geometry": {"coordinates":[-1.041222,54.025924],"type":"Point"}
}