{
  "type": "Feature",
  "properties": {
    "date:inception_lower": "1980-01-01",
    "date:inception_upper": "1980-01-01",
    "iso:country": "GB",
    "wof:name": "WV4 6RA",
    "wof:placetype": "postalcode"
  },
  "geometry": {"coordinates":[-2.11655,52.555519],"type":"Point"}
}
