{
  "type": "Feature",
  "properties": {
    "iso:country":"GB",
    "wof:name":"WV4 6RA",
    "wof:placetype":"postalcode"
},
  "geometry": {"coordinates":[-2.11655034463121,52.55551867567088],"type":"Point"}
}