{
  "type": "Feature",
  "properties": {
    "iso:country":"GB",
    "wof:name":"PA4 8PA",
    "wof:placetype":"postalcode"
},
  "geometry": {"coordinates":[-4.39061302339522,55.88127535579954],"type":"Point"}
}