{
  "type": "Feature",
  "properties": {
    "iso:country": "GB",
    "wof:name": "PA4 8PA",
    "wof:placetype": "postalcode"
  },
  "geometry": {"coordinates":[-4.390613,55.881275],"type":"Point"}
}
