{
  "type": "Feature",
  "properties": {
    "iso:country": "GB",
    "wof:name": "LE13 0EZ",
    "wof:placetype": "postalcode"
  },
  "geometry": {"coordinates":[-0.896193,52.75771],"type":"Point"}
}
