{
  "type": "Feature",
  "properties": {
    "date:inception_lower": "2003-11-01",
    "date:inception_upper": "2003-11-01",
    "iso:country": "GB",
    "wof:name": "BD23 4NF",
    "wof:placetype": "postalcode"
  },
  "geometry": {"coordinates":[-2.253836,54.019248],"type":"Point"}
}
