{
  "type": "Feature",
  "properties": {
    "iso:country":"GB",
    "wof:name":"PL14 3RD",
    "wof:placetype":"postalcode"
},
  "geometry": {"coordinates":[-4.401253980197,50.43680753891638],"type":"Point"}
}