{
  "type": "Feature",
  "properties": {
    "iso:country": "GB",
    "wof:name": "BD11 1HY",
    "wof:placetype": "postalcode"
  },
  "geometry": {"coordinates":[-1.660715,53.750364],"type":"Point"}
}
