{
  "type": "Feature",
  "properties": {
    "iso:country": "GB",
    "wof:name": "S72 8FL",
    "wof:placetype": "postalcode"
  },
  "geometry": {"coordinates":[-1.411744,53.583711],"type":"Point"}
}
