{
  "type": "Feature",
  "properties": {
    "date:inception_lower":"2013-07-01",
    "date:inception_upper":"2013-07-31",
    "iso:country":"GB",
    "wof:name":"NE38 8FB",
    "wof:placetype":"postalcode"
},
  "geometry": {"coordinates":[-1.494121,54.894343],"type":"Point"}
}