{
  "type": "Feature",
  "properties": {
    "iso:country": "GB",
    "wof:name": "NE38 8FB",
    "wof:placetype": "postalcode"
  },
  "geometry": {"coordinates":[-1.494121,54.894343],"type":"Point"}
}
