{
  "type": "Feature",
  "properties": {
    "iso:country": "GB",
    "wof:name": "G67 4JP",
    "wof:placetype": "postalcode"
  },
  "geometry": {"coordinates":[-4.01971,55.934941],"type":"Point"}
}
