{
  "type": "Feature",
  "properties": {
    "iso:country":"GB",
    "wof:name":"G67 4JP",
    "wof:placetype":"postalcode"
},
  "geometry": {"coordinates":[-4.01971004399833,55.93494138782195],"type":"Point"}
}