{
  "type": "Feature",
  "properties": {
    "iso:country":"GB",
    "wof:name":"WR6 6JG",
    "wof:placetype":"postalcode"
},
  "geometry": {"coordinates":[-2.37915626149209,52.29260145337558],"type":"Point"}
}