{
  "type": "Feature",
  "properties": {
    "iso:country": "GB",
    "wof:name": "WR6 6JG",
    "wof:placetype": "postalcode"
  },
  "geometry": {"coordinates":[-2.379094,52.292624],"type":"Point"}
}
