{
  "type": "Feature",
  "properties": {
    "iso:country":"GB",
    "wof:name":"SN8 2BL",
    "wof:placetype":"postalcode"
},
  "geometry": {"coordinates":[-1.62489242165439,51.47997225983657],"type":"Point"}
}