{
  "type": "Feature",
  "properties": {
    "iso:country": "GB",
    "wof:name": "N7 8XW",
    "wof:placetype": "postalcode"
  },
  "geometry": {"coordinates":[-0.115378,51.547478],"type":"Point"}
}
