{
  "type": "Feature",
  "properties": {
    "date:inception_lower": "2008-04-01",
    "date:inception_upper": "2008-04-01",
    "iso:country": "GB",
    "wof:name": "BN12 6GD",
    "wof:placetype": "postalcode"
  },
  "geometry": {"coordinates":[-0.44701,50.817717],"type":"Point"}
}
