{
  "type": "Feature",
  "properties": {
    "iso:country": "GB",
    "wof:name": "BN12 6GD",
    "wof:placetype": "postalcode"
  },
  "geometry": {"coordinates":[-0.44701,50.817717],"type":"Point"}
}
