{
  "type": "Feature",
  "properties": {
    "iso:country":"GB",
    "wof:name":"EH6 4TY",
    "wof:placetype":"postalcode"
},
  "geometry": {"coordinates":[-3.19274949107645,55.98173009193736],"type":"Point"}
}