{
  "type": "Feature",
  "properties": {
    "date:inception_lower": "2010-02-01",
    "date:inception_upper": "2010-02-01",
    "iso:country": "GB",
    "wof:name": "EH6 4TY",
    "wof:placetype": "postalcode"
  },
  "geometry": {"coordinates":[-3.192749,55.98173],"type":"Point"}
}
