{
  "type": "Feature",
  "properties": {
    "iso:country": "GB",
    "wof:name": "EH6 4TY",
    "wof:placetype": "postalcode"
  },
  "geometry": {"coordinates":[-3.192749,55.98173],"type":"Point"}
}
