{
  "type": "Feature",
  "properties": {
    "iso:country":"GB",
    "wof:name":"BD12 8LB",
    "wof:placetype":"postalcode"
},
  "geometry": {"coordinates":[-1.77396174834662,53.73674444347463],"type":"Point"}
}