{
  "type": "Feature",
  "properties": {
    "iso:country": "GB",
    "wof:name": "BS1 1QZ",
    "wof:placetype": "postalcode"
  },
  "geometry": {"coordinates":[-2.59283,51.453778],"type":"Point"}
}
