{
  "type": "Feature",
  "properties": {
    "date:inception_lower": "1980-01-01",
    "date:inception_upper": "1980-01-01",
    "iso:country": "GB",
    "wof:name": "BS1 1QZ",
    "wof:placetype": "postalcode"
  },
  "geometry": {"coordinates":[-2.59283,51.453778],"type":"Point"}
}
