{
  "type": "Feature",
  "properties": {
    "iso:country":"GB",
    "wof:name":"BS1 1QZ",
    "wof:placetype":"postalcode"
},
  "geometry": {"coordinates":[-2.5928299931136,51.45377816328999],"type":"Point"}
}