{
  "type": "Feature",
  "properties": {
    "iso:country":"GB",
    "wof:name":"TS11 7HB",
    "wof:placetype":"postalcode"
},
  "geometry": {"coordinates":[-1.01129409675629,54.58942091630231],"type":"Point"}
}