{
  "type": "Feature",
  "properties": {
    "iso:country":"GB",
    "wof:name":"ME13 8AE",
    "wof:placetype":"postalcode"
},
  "geometry": {"coordinates":[0.89310319807407,51.31477316545161],"type":"Point"}
}