{
  "type": "Feature",
  "properties": {
    "date:inception_lower": "1987-10-01",
    "date:inception_upper": "1987-10-01",
    "iso:country": "GB",
    "wof:name": "ME13 8AE",
    "wof:placetype": "postalcode"
  },
  "geometry": {"coordinates":[0.893103,51.314773],"type":"Point"}
}
