{
  "type": "Feature",
  "properties": {
    "iso:country": "GB",
    "wof:name": "ME13 8AE",
    "wof:placetype": "postalcode"
  },
  "geometry": {"coordinates":[0.893103,51.314773],"type":"Point"}
}
