{
  "type": "Feature",
  "properties": {
    "iso:country":"GB",
    "wof:name":"SK7 4EU",
    "wof:placetype":"postalcode"
},
  "geometry": {"coordinates":[-2.12020428886899,53.37888263474737],"type":"Point"}
}