{
  "type": "Feature",
  "properties": {
    "iso:country":"GB",
    "wof:name":"B44 9BH",
    "wof:placetype":"postalcode"
},
  "geometry": {"coordinates":[-1.90465127099231,52.55316480041287],"type":"Point"}
}