{
  "type": "Feature",
  "properties": {
    "iso:country": "GB",
    "wof:name": "B44 9BH",
    "wof:placetype": "postalcode"
  },
  "geometry": {"coordinates":[-1.904651,52.553165],"type":"Point"}
}
