{
  "type": "Feature",
  "properties": {
    "iso:country": "GB",
    "wof:name": "B15 1LZ",
    "wof:placetype": "postalcode"
  },
  "geometry": {"coordinates":[-1.908471,52.472642],"type":"Point"}
}
