{
  "type": "Feature",
  "properties": {
    "iso:country": "GB",
    "wof:name": "NE33 3HA",
    "wof:placetype": "postalcode"
  },
  "geometry": {"coordinates":[-1.419299,54.989759],"type":"Point"}
}
