{
  "type": "Feature",
  "properties": {
    "iso:country":"GB",
    "wof:name":"NE4 5AF",
    "wof:placetype":"postalcode"
},
  "geometry": {"coordinates":[-1.63468596304998,54.97814092053594],"type":"Point"}
}