{
  "type": "Feature",
  "properties": {
    "iso:country": "GB",
    "wof:name": "CW7 2SP",
    "wof:placetype": "postalcode"
  },
  "geometry": {"coordinates":[-2.519147,53.194519],"type":"Point"}
}
