{
  "type": "Feature",
  "properties": {
    "iso:country":"GB",
    "wof:name":"SY10 7QB",
    "wof:placetype":"postalcode"
},
  "geometry": {"coordinates":[-3.17563525843918,52.8451341159038],"type":"Point"}
}