{
  "type": "Feature",
  "properties": {
    "iso:country":"GB",
    "wof:name":"NP15 1HY",
    "wof:placetype":"postalcode"
},
  "geometry": {"coordinates":[-2.91745304568362,51.72240551110488],"type":"Point"}
}