{
  "type": "Feature",
  "properties": {
    "iso:country":"GB",
    "wof:name":"TF7 4EU",
    "wof:placetype":"postalcode"
},
  "geometry": {"coordinates":[-2.4473257916921,52.62555240792295],"type":"Point"}
}