{
  "type": "Feature",
  "properties": {
    "date:inception_lower": "1993-01-01",
    "date:inception_upper": "1993-01-01",
    "iso:country": "GB",
    "wof:name": "PR6 7BT",
    "wof:placetype": "postalcode"
  },
  "geometry": {"coordinates":[-2.624963,53.664679],"type":"Point"}
}
