{
  "type": "Feature",
  "properties": {
    "iso:country":"GB",
    "wof:name":"TW18 2ED",
    "wof:placetype":"postalcode"
},
  "geometry": {"coordinates":[-0.50835354014565,51.42772698799396],"type":"Point"}
}