{
  "type": "Feature",
  "properties": {
    "date:inception_lower":"1980-01-01",
    "date:inception_upper":"1980-01-31",
    "iso:country":"GB",
    "wof:name":"DT9 4SD",
    "wof:placetype":"postalcode"
},
  "geometry": {"coordinates":[-2.543774,50.994961],"type":"Point"}
}