{
  "type": "Feature",
  "properties": {
    "iso:country":"GB",
    "wof:name":"DT9 4SD",
    "wof:placetype":"postalcode"
},
  "geometry": {"coordinates":[-2.54340900654338,50.99556183885053],"type":"Point"}
}