{
  "type": "Feature",
  "properties": {
    "iso:country": "GB",
    "wof:name": "DT9 4SD",
    "wof:placetype": "postalcode"
  },
  "geometry": {"coordinates":[-2.543774,50.994961],"type":"Point"}
}
