{
  "type": "Feature",
  "properties": {
    "date:inception_lower":"1995-07-01",
    "date:inception_upper":"1995-07-31",
    "iso:country":"GB",
    "wof:name":"DT2 9TP",
    "wof:placetype":"postalcode"
},
  "geometry": {"coordinates":[-2.521219,50.794087],"type":"Point"}
}