{
  "type": "Feature",
  "properties": {
    "iso:country": "GB",
    "wof:name": "DT2 9TP",
    "wof:placetype": "postalcode"
  },
  "geometry": {"coordinates":[-2.521234,50.794177],"type":"Point"}
}
