{
  "type": "Feature",
  "properties": {
    "iso:country":"GB",
    "wof:name":"BD4 0ND",
    "wof:placetype":"postalcode"
},
  "geometry": {"coordinates":[-1.70365337488098,53.77304693090015],"type":"Point"}
}