{
  "type": "Feature",
  "properties": {
    "date:inception_lower": "2022-04-01",
    "date:inception_upper": "2022-04-01",
    "iso:country": "GB",
    "wof:name": "TF6 6FG",
    "wof:placetype": "postalcode"
  },
  "geometry": {"coordinates":[-2.633771,52.744802],"type":"Point"}
}
