{
  "type": "Feature",
  "properties": {
    "iso:country":"GB",
    "wof:name":"AL8 6HH",
    "wof:placetype":"postalcode"
},
  "geometry": {"coordinates":[-0.21059672750387,51.79959029125571],"type":"Point"}
}