{
  "type": "Feature",
  "properties": {
    "iso:country": "GB",
    "wof:name": "AL8 6HH",
    "wof:placetype": "postalcode"
  },
  "geometry": {"coordinates":[-0.210597,51.79959],"type":"Point"}
}
