{
  "type": "Feature",
  "properties": {
    "iso:country": "GB",
    "wof:name": "CA7 9LZ",
    "wof:placetype": "postalcode"
  },
  "geometry": {"coordinates":[-3.150287,54.817135],"type":"Point"}
}
