{
  "type": "Feature",
  "properties": {
    "iso:country":"GB",
    "wof:name":"TA6 4DQ",
    "wof:placetype":"postalcode"
},
  "geometry": {"coordinates":[-2.97567654257454,51.1321419197511],"type":"Point"}
}