{
  "type": "Feature",
  "properties": {
    "date:inception_lower": "2022-04-01",
    "date:inception_upper": "2022-04-01",
    "iso:country": "GB",
    "wof:name": "RG5 4SB",
    "wof:placetype": "postalcode"
  },
  "geometry": {"coordinates":[-0.89612,51.452792],"type":"Point"}
}
