{
  "type": "Feature",
  "properties": {
    "date:inception_lower": "2021-01-01",
    "date:inception_upper": "2021-01-01",
    "iso:country": "GB",
    "wof:name": "WR5 1TQ",
    "wof:placetype": "postalcode"
  },
  "geometry": {"coordinates":[-2.203231,52.188562],"type":"Point"}
}
