{
  "type": "Feature",
  "properties": {
    "iso:country": "GB",
    "wof:name": "NP4 7RD",
    "wof:placetype": "postalcode"
  },
  "geometry": {"coordinates":[-3.072771,51.73428],"type":"Point"}
}
