{
  "type": "Feature",
  "properties": {
    "iso:country":"GB",
    "wof:name":"NP4 7RD",
    "wof:placetype":"postalcode"
},
  "geometry": {"coordinates":[-3.07277088062051,51.73428032113322],"type":"Point"}
}