{
  "type": "Feature",
  "properties": {
    "iso:country":"GB",
    "wof:name":"BD23 2BP",
    "wof:placetype":"postalcode"
},
  "geometry": {"coordinates":[-2.02271421519703,53.95294274693381],"type":"Point"}
}