{
  "type": "Feature",
  "properties": {
    "iso:country":"GB",
    "wof:name":"WD18 0AG",
    "wof:placetype":"postalcode"
},
  "geometry": {"coordinates":[-0.39391183533935,51.65255750113776],"type":"Point"}
}