{
  "type": "Feature",
  "properties": {
    "iso:country":"GB",
    "wof:name":"LE7 4WH",
    "wof:placetype":"postalcode"
},
  "geometry": {"coordinates":[-0.98248372989581,52.71365713869768],"type":"Point"}
}