{
  "type": "Feature",
  "properties": {
    "iso:country": "GB",
    "wof:name": "LE7 4WH",
    "wof:placetype": "postalcode"
  },
  "geometry": {"coordinates":[-0.982484,52.713657],"type":"Point"}
}
