{
  "type": "Feature",
  "properties": {
    "iso:country": "GB",
    "wof:name": "CT18 7HP",
    "wof:placetype": "postalcode"
  },
  "geometry": {"coordinates":[1.214661,51.100712],"type":"Point"}
}
