{
  "type": "Feature",
  "properties": {
    "date:inception_lower": "1980-01-01",
    "date:inception_upper": "1980-01-01",
    "iso:country": "GB",
    "wof:name": "G4 9HG",
    "wof:placetype": "postalcode"
  },
  "geometry": {"coordinates":[-4.279423,55.873922],"type":"Point"}
}
