{
  "type": "Feature",
  "properties": {
    "date:inception_lower": "1980-01-01",
    "date:inception_upper": "1980-01-01",
    "iso:country": "GB",
    "wof:name": "NP7 6EY",
    "wof:placetype": "postalcode"
  },
  "geometry": {"coordinates":[-3.009387,51.831031],"type":"Point"}
}
