{
  "type": "Feature",
  "properties": {
    "iso:country":"GB",
    "wof:name":"EX16 8LN",
    "wof:placetype":"postalcode"
},
  "geometry": {"coordinates":[-3.65413904622124,50.88327365797758],"type":"Point"}
}