{
  "type": "Feature",
  "properties": {
    "iso:country":"GB",
    "wof:name":"RH17 5LS",
    "wof:placetype":"postalcode"
},
  "geometry": {"coordinates":[-0.13590471110315,51.00721916051098],"type":"Point"}
}