{
  "type": "Feature",
  "properties": {
    "date:inception_lower":"1993-08-01",
    "date:inception_upper":"1993-08-31",
    "iso:country":"GB",
    "wof:name":"NE65 9NB",
    "wof:placetype":"postalcode"
},
  "geometry": {"coordinates":[-1.738626,55.327369],"type":"Point"}
}