{
  "type": "Feature",
  "properties": {
    "iso:country":"GB",
    "wof:name":"NE65 9NB",
    "wof:placetype":"postalcode"
},
  "geometry": {"coordinates":[-1.73862564311675,55.3273691947965],"type":"Point"}
}