{
  "type": "Feature",
  "properties": {
    "iso:country":"GB",
    "wof:name":"CF83 8QS",
    "wof:placetype":"postalcode"
},
  "geometry": {"coordinates":[-3.14386826519473,51.59690101469236],"type":"Point"}
}