{
  "type": "Feature",
  "properties": {
    "date:inception_lower":"2004-11-01",
    "date:inception_upper":"2004-11-30",
    "iso:country":"GB",
    "wof:name":"SE16 2NX",
    "wof:placetype":"postalcode"
},
  "geometry": {"coordinates":[-0.047879,51.489145],"type":"Point"}
}