{
  "type": "Feature",
  "properties": {
    "iso:country":"GB",
    "wof:name":"SE16 2NX",
    "wof:placetype":"postalcode"
},
  "geometry": {"coordinates":[-0.04787894336512,51.48914497529059],"type":"Point"}
}