{
  "type": "Feature",
  "properties": {
    "iso:country":"GB",
    "wof:name":"S80 1TL",
    "wof:placetype":"postalcode"
},
  "geometry": {"coordinates":[-1.13443255679614,53.31154555264836],"type":"Point"}
}