{
  "type": "Feature",
  "properties": {
    "iso:country": "GB",
    "wof:name": "GL10 3AU",
    "wof:placetype": "postalcode"
  },
  "geometry": {"coordinates":[-2.325069,51.746272],"type":"Point"}
}
