{
  "type": "Feature",
  "properties": {
    "iso:country":"GB",
    "wof:name":"DA10 0LW",
    "wof:placetype":"postalcode"
},
  "geometry": {"coordinates":[0.30044973011628,51.44940952926012],"type":"Point"}
}