{
  "type": "Feature",
  "properties": {
    "iso:country": "GB",
    "wof:name": "DA10 0LW",
    "wof:placetype": "postalcode"
  },
  "geometry": {"coordinates":[0.30045,51.44941],"type":"Point"}
}
