{
  "type": "Feature",
  "properties": {
    "iso:country":"GB",
    "wof:name":"EN2 0ST",
    "wof:placetype":"postalcode"
},
  "geometry": {"coordinates":[-0.07932723812297,51.66468513344384],"type":"Point"}
}