{
  "type": "Feature",
  "properties": {
    "date:inception_lower":"1980-01-01",
    "date:inception_upper":"1980-01-31",
    "iso:country":"GB",
    "wof:name":"EN2 0ST",
    "wof:placetype":"postalcode"
},
  "geometry": {"coordinates":[-0.079327,51.664685],"type":"Point"}
}