{
  "type": "Feature",
  "properties": {
    "iso:country":"GB",
    "wof:name":"LN4 2EU",
    "wof:placetype":"postalcode"
},
  "geometry": {"coordinates":[-0.40725866670919,53.1501033608395],"type":"Point"}
}