{
  "type": "Feature",
  "properties": {
    "iso:country":"GB",
    "wof:name":"LE7 9SN",
    "wof:placetype":"postalcode"
},
  "geometry": {"coordinates":[-1.04403863007607,52.64371475524916],"type":"Point"}
}