{
  "type": "Feature",
  "properties": {
    "iso:country": "GB",
    "wof:name": "LE7 9SN",
    "wof:placetype": "postalcode"
  },
  "geometry": {"coordinates":[-1.043665,52.643541],"type":"Point"}
}
