{
  "type": "Feature",
  "properties": {
    "iso:country":"GB",
    "wof:name":"W10 5NW",
    "wof:placetype":"postalcode"
},
  "geometry": {"coordinates":[-0.20596006168324,51.52419565401325],"type":"Point"}
}