{
  "type": "Feature",
  "properties": {
    "iso:country": "GB",
    "wof:name": "BS3 3DA",
    "wof:placetype": "postalcode"
  },
  "geometry": {"coordinates":[-2.606406,51.436732],"type":"Point"}
}
