{
  "type": "Feature",
  "properties": {
    "date:inception_lower": "2004-08-01",
    "date:inception_upper": "2004-08-01",
    "iso:country": "GB",
    "wof:name": "FY4 1RW",
    "wof:placetype": "postalcode"
  },
  "geometry": {"coordinates":[-3.057496,53.783407],"type":"Point"}
}
