{
  "type": "Feature",
  "properties": {
    "iso:country": "GB",
    "wof:name": "FY4 1RW",
    "wof:placetype": "postalcode"
  },
  "geometry": {"coordinates":[-3.057496,53.783407],"type":"Point"}
}
