{
  "type": "Feature",
  "properties": {
    "iso:country": "GB",
    "wof:name": "B69 3LH",
    "wof:placetype": "postalcode"
  },
  "geometry": {"coordinates":[-2.035866,52.513804],"type":"Point"}
}
