{
  "type": "Feature",
  "properties": {
    "iso:country": "GB",
    "wof:name": "L36 8DD",
    "wof:placetype": "postalcode"
  },
  "geometry": {"coordinates":[-2.837753,53.42651],"type":"Point"}
}
