{
  "type": "Feature",
  "properties": {
    "iso:country": "GB",
    "wof:name": "PL11 3LR",
    "wof:placetype": "postalcode"
  },
  "geometry": {"coordinates":[-4.36487,50.361765],"type":"Point"}
}
