{
  "type": "Feature",
  "properties": {
    "iso:country":"GB",
    "wof:name":"PL11 3LR",
    "wof:placetype":"postalcode"
},
  "geometry": {"coordinates":[-4.36486968397301,50.36176464601311],"type":"Point"}
}