{
  "type": "Feature",
  "properties": {
    "iso:country":"GB",
    "wof:name":"WF6 1RB",
    "wof:placetype":"postalcode"
},
  "geometry": {"coordinates":[-1.4014423786326,53.70663853187221],"type":"Point"}
}