{
  "type": "Feature",
  "properties": {
    "date:inception_lower":"1980-01-01",
    "date:inception_upper":"1980-01-31",
    "iso:country":"GB",
    "wof:name":"WF6 1RB",
    "wof:placetype":"postalcode"
},
  "geometry": {"coordinates":[-1.401507,53.706621],"type":"Point"}
}