{
  "type": "Feature",
  "properties": {
    "iso:country":"GB",
    "wof:name":"PL23 1JS",
    "wof:placetype":"postalcode"
},
  "geometry": {"coordinates":[-4.64592513923887,50.34177259451693],"type":"Point"}
}