{
  "type": "Feature",
  "properties": {
    "iso:country":"GB",
    "wof:name":"TN5 7EF",
    "wof:placetype":"postalcode"
},
  "geometry": {"coordinates":[0.38012221457351,51.03691302487151],"type":"Point"}
}