{
  "type": "Feature",
  "properties": {
    "iso:country":"GB",
    "wof:name":"SP2 9RA",
    "wof:placetype":"postalcode"
},
  "geometry": {"coordinates":[-1.82834377423941,51.08437486023939],"type":"Point"}
}