{
  "type": "Feature",
  "properties": {
    "iso:country": "GB",
    "wof:name": "KT1 4DB",
    "wof:placetype": "postalcode"
  },
  "geometry": {"coordinates":[-0.310991,51.412856],"type":"Point"}
}
