{
  "type": "Feature",
  "properties": {
    "iso:country":"GB",
    "wof:name":"DT1 2DP",
    "wof:placetype":"postalcode"
},
  "geometry": {"coordinates":[-2.43056583788815,50.70860461759354],"type":"Point"}
}