{
  "type": "Feature",
  "properties": {
    "iso:country":"GB",
    "wof:name":"AB16 7NL",
    "wof:placetype":"postalcode"
},
  "geometry": {"coordinates":[-2.16151747750911,57.16762199061883],"type":"Point"}
}