{
  "type": "Feature",
  "properties": {
    "iso:country":"GB",
    "wof:name":"M25 3DZ",
    "wof:placetype":"postalcode"
},
  "geometry": {"coordinates":[-2.28450297164932,53.53798789306107],"type":"Point"}
}