{
  "type": "Feature",
  "properties": {
    "date:inception_lower": "2018-01-01",
    "date:inception_upper": "2018-01-01",
    "iso:country": "GB",
    "wof:name": "SE9 5AA",
    "wof:placetype": "postalcode"
  },
  "geometry": {"coordinates":[0.050931,51.450535],"type":"Point"}
}
