{
  "type": "Feature",
  "properties": {
    "iso:country": "GB",
    "wof:name": "LS25 1AQ",
    "wof:placetype": "postalcode"
  },
  "geometry": {"coordinates":[-1.38881,53.795592],"type":"Point"}
}
