{
  "type": "Feature",
  "properties": {
    "iso:country":"GB",
    "wof:name":"LS25 1AQ",
    "wof:placetype":"postalcode"
},
  "geometry": {"coordinates":[-1.38883661744684,53.79560283134278],"type":"Point"}
}