{
  "type": "Feature",
  "properties": {
    "iso:country": "GB",
    "wof:name": "PR1 8XD",
    "wof:placetype": "postalcode"
  },
  "geometry": {"coordinates":[-2.714672,53.760873],"type":"Point"}
}
