{
  "type": "Feature",
  "properties": {
    "date:inception_lower": "1993-08-01",
    "date:inception_upper": "1993-08-01",
    "iso:country": "GB",
    "wof:name": "PR1 8XD",
    "wof:placetype": "postalcode"
  },
  "geometry": {"coordinates":[-2.714672,53.760873],"type":"Point"}
}
