{
  "type": "Feature",
  "properties": {
    "iso:country":"GB",
    "wof:name":"PR1 8XD",
    "wof:placetype":"postalcode"
},
  "geometry": {"coordinates":[-2.71467247071633,53.76087261209905],"type":"Point"}
}