{
  "type": "Feature",
  "properties": {
    "iso:country":"GB",
    "wof:name":"SR5 5HR",
    "wof:placetype":"postalcode"
},
  "geometry": {"coordinates":[-1.43434091420033,54.92695212750495],"type":"Point"}
}