{
  "type": "Feature",
  "properties": {
    "date:inception_lower":"1980-01-01",
    "date:inception_upper":"1980-01-31",
    "iso:country":"GB",
    "wof:name":"SR5 5HR",
    "wof:placetype":"postalcode"
},
  "geometry": {"coordinates":[-1.434341,54.926952],"type":"Point"}
}