{
  "type": "Feature",
  "properties": {
    "iso:country":"GB",
    "wof:name":"S36 2ND",
    "wof:placetype":"postalcode"
},
  "geometry": {"coordinates":[-1.56794449078825,53.47408881153753],"type":"Point"}
}