{
  "type": "Feature",
  "properties": {
    "iso:country":"GB",
    "wof:name":"ST6 6RP",
    "wof:placetype":"postalcode"
},
  "geometry": {"coordinates":[-2.18862285411292,53.07398262899835],"type":"Point"}
}