{
  "type": "Feature",
  "properties": {
    "iso:country":"GB",
    "wof:name":"CW5 6JH",
    "wof:placetype":"postalcode"
},
  "geometry": {"coordinates":[-2.51080447789052,53.06801920435337],"type":"Point"}
}