{
  "type": "Feature",
  "properties": {
    "iso:country": "GB",
    "wof:name": "CO14 8FD",
    "wof:placetype": "postalcode"
  },
  "geometry": {"coordinates":[1.264742,51.850858],"type":"Point"}
}
