{
  "type": "Feature",
  "properties": {
    "iso:country":"GB",
    "wof:name":"BN14 9NY",
    "wof:placetype":"postalcode"
},
  "geometry": {"coordinates":[-0.37368023877723,50.8366737198674],"type":"Point"}
}