{
  "type": "Feature",
  "properties": {
    "iso:country": "GB",
    "wof:name": "CT7 0NA",
    "wof:placetype": "postalcode"
  },
  "geometry": {"coordinates":[1.258196,51.356761],"type":"Point"}
}
