{
  "type": "Feature",
  "properties": {
    "iso:country":"GB",
    "wof:name":"CT7 0NA",
    "wof:placetype":"postalcode"
},
  "geometry": {"coordinates":[1.25823961998142,51.35695969251697],"type":"Point"}
}