{
  "type": "Feature",
  "properties": {
    "date:inception_lower": "1980-01-01",
    "date:inception_upper": "1980-01-01",
    "iso:country": "GB",
    "wof:name": "CT7 0NA",
    "wof:placetype": "postalcode"
  },
  "geometry": {"coordinates":[1.258194,51.356734],"type":"Point"}
}
