{
  "type": "Feature",
  "properties": {
    "iso:country": "GB",
    "wof:name": "SA7 9PD",
    "wof:placetype": "postalcode"
  },
  "geometry": {"coordinates":[-3.876123,51.664548],"type":"Point"}
}
