{
  "type": "Feature",
  "properties": {
    "iso:country":"GB",
    "wof:name":"DT7 3XW",
    "wof:placetype":"postalcode"
},
  "geometry": {"coordinates":[-2.99838468642452,50.71739882561903],"type":"Point"}
}