{
  "type": "Feature",
  "properties": {
    "iso:country": "GB",
    "wof:name": "DT7 3XW",
    "wof:placetype": "postalcode"
  },
  "geometry": {"coordinates":[-2.998385,50.717399],"type":"Point"}
}
