{
  "type": "Feature",
  "properties": {
    "iso:country":"GB",
    "wof:name":"KY14 7FB",
    "wof:placetype":"postalcode"
},
  "geometry": {"coordinates":[-3.23206158898292,56.29000521687636],"type":"Point"}
}