{
  "type": "Feature",
  "properties": {
    "iso:country":"GB",
    "wof:name":"IP20 9NH",
    "wof:placetype":"postalcode"
},
  "geometry": {"coordinates":[1.27502524164334,52.40525267550829],"type":"Point"}
}