{
  "type": "Feature",
  "properties": {
    "iso:country": "GB",
    "wof:name": "IP20 9NH",
    "wof:placetype": "postalcode"
  },
  "geometry": {"coordinates":[1.275025,52.405253],"type":"Point"}
}
