{
  "type": "Feature",
  "properties": {
    "iso:country": "GB",
    "wof:name": "OX7 3LQ",
    "wof:placetype": "postalcode"
  },
  "geometry": {"coordinates":[-1.524158,51.896171],"type":"Point"}
}
