{
  "type": "Feature",
  "properties": {
    "iso:country":"GB",
    "wof:name":"OX7 3LQ",
    "wof:placetype":"postalcode"
},
  "geometry": {"coordinates":[-1.52415796531927,51.89617143408688],"type":"Point"}
}