{
  "type": "Feature",
  "properties": {
    "date:inception_lower": "1995-07-01",
    "date:inception_upper": "1995-07-01",
    "iso:country": "GB",
    "wof:name": "ST16 3FD",
    "wof:placetype": "postalcode"
  },
  "geometry": {"coordinates":[-2.101417,52.810048],"type":"Point"}
}
