{
  "type": "Feature",
  "properties": {
    "date:inception_lower": "1980-01-01",
    "date:inception_upper": "1980-01-01",
    "iso:country": "GB",
    "wof:name": "CH7 4QU",
    "wof:placetype": "postalcode"
  },
  "geometry": {"coordinates":[-3.180383,53.089266],"type":"Point"}
}
