{
  "type": "Feature",
  "properties": {
    "iso:country":"GB",
    "wof:name":"CH7 4QU",
    "wof:placetype":"postalcode"
},
  "geometry": {"coordinates":[-3.18038343294949,53.08926622292496],"type":"Point"}
}