{
  "type": "Feature",
  "properties": {
    "iso:country":"GB",
    "wof:name":"ST4 5EP",
    "wof:placetype":"postalcode"
},
  "geometry": {"coordinates":[-2.19306218724486,52.99870957173201],"type":"Point"}
}