{
  "type": "Feature",
  "properties": {
    "date:inception_lower":"1980-01-01",
    "date:inception_upper":"1980-01-31",
    "iso:country":"GB",
    "wof:name":"ST4 5EP",
    "wof:placetype":"postalcode"
},
  "geometry": {"coordinates":[-2.19348,52.99888],"type":"Point"}
}