{
  "type": "Feature",
  "properties": {
    "date:inception_lower": "1990-02-01",
    "date:inception_upper": "1990-02-01",
    "iso:country": "GB",
    "wof:name": "SG6 1LW",
    "wof:placetype": "postalcode"
  },
  "geometry": {"coordinates":[-0.204175,51.985058],"type":"Point"}
}
