{
  "type": "Feature",
  "properties": {
    "iso:country":"GB",
    "wof:name":"SG6 1LW",
    "wof:placetype":"postalcode"
},
  "geometry": {"coordinates":[-0.20417509288467,51.9850583856687],"type":"Point"}
}