{
  "type": "Feature",
  "properties": {
    "iso:country":"GB",
    "wof:name":"PL13 2BT",
    "wof:placetype":"postalcode"
},
  "geometry": {"coordinates":[-4.50481911444744,50.35480313721888],"type":"Point"}
}