{
  "type": "Feature",
  "properties": {
    "date:inception_lower":"1990-07-01",
    "date:inception_upper":"1990-07-31",
    "iso:country":"GB",
    "wof:name":"BN42 4DW",
    "wof:placetype":"postalcode"
},
  "geometry": {"coordinates":[-0.238694,50.831611],"type":"Point"}
}