{
  "type": "Feature",
  "properties": {
    "iso:country": "GB",
    "wof:name": "BA12 6LX",
    "wof:placetype": "postalcode"
  },
  "geometry": {"coordinates":[-2.278752,51.090372],"type":"Point"}
}
