{
  "type": "Feature",
  "properties": {
    "iso:country":"GB",
    "wof:name":"BA12 6LX",
    "wof:placetype":"postalcode"
},
  "geometry": {"coordinates":[-2.2787522197681,51.09037211154721],"type":"Point"}
}