{
  "type": "Feature",
  "properties": {
    "iso:country":"GB",
    "wof:name":"AB53 4BE",
    "wof:placetype":"postalcode"
},
  "geometry": {"coordinates":[-2.46545564033337,57.53895829489834],"type":"Point"}
}