{
  "type": "Feature",
  "properties": {
    "date:inception_lower": "1980-01-01",
    "date:inception_upper": "1980-01-01",
    "iso:country": "GB",
    "wof:name": "PL17 8NL",
    "wof:placetype": "postalcode"
  },
  "geometry": {"coordinates":[-4.275149,50.540296],"type":"Point"}
}
