{
  "type": "Feature",
  "properties": {
    "iso:country":"GB",
    "wof:name":"S63 7ND",
    "wof:placetype":"postalcode"
},
  "geometry": {"coordinates":[-1.33860983394211,53.50109355284663],"type":"Point"}
}