{
  "type": "Feature",
  "properties": {
    "date:inception_lower": "1992-08-01",
    "date:inception_upper": "1992-08-01",
    "iso:country": "GB",
    "wof:name": "DE56 1UU",
    "wof:placetype": "postalcode"
  },
  "geometry": {"coordinates":[-1.483736,53.017111],"type":"Point"}
}
