{
  "type": "Feature",
  "properties": {
    "iso:country":"GB",
    "wof:name":"DN3 2LR",
    "wof:placetype":"postalcode"
},
  "geometry": {"coordinates":[-1.06147408582918,53.55204822609906],"type":"Point"}
}