{
  "type": "Feature",
  "properties": {
    "iso:country": "GB",
    "wof:name": "WA13 0RD",
    "wof:placetype": "postalcode"
  },
  "geometry": {"coordinates":[-2.460527,53.375196],"type":"Point"}
}
