{
  "type": "Feature",
  "properties": {
    "iso:country":"GB",
    "wof:name":"WA13 0RD",
    "wof:placetype":"postalcode"
},
  "geometry": {"coordinates":[-2.46052745782864,53.37519576622277],"type":"Point"}
}