{
  "type": "Feature",
  "properties": {
    "date:inception_lower": "1985-10-01",
    "date:inception_upper": "1985-10-01",
    "iso:country": "GB",
    "wof:name": "BS16 2UA",
    "wof:placetype": "postalcode"
  },
  "geometry": {"coordinates":[-2.514818,51.488818],"type":"Point"}
}
