{
  "type": "Feature",
  "properties": {
    "date:inception_lower": "1980-01-01",
    "date:inception_upper": "1980-01-01",
    "iso:country": "GB",
    "wof:name": "CT16 3HT",
    "wof:placetype": "postalcode"
  },
  "geometry": {"coordinates":[1.296306,51.158641],"type":"Point"}
}
