{
  "type": "Feature",
  "properties": {
    "iso:country":"GB",
    "wof:name":"CT16 3HT",
    "wof:placetype":"postalcode"
},
  "geometry": {"coordinates":[1.29630572954681,51.15864116390766],"type":"Point"}
}