{
  "type": "Feature",
  "properties": {
    "date:inception_lower": "1980-01-01",
    "date:inception_upper": "1980-01-01",
    "iso:country": "GB",
    "wof:name": "NW1 5AZ",
    "wof:placetype": "postalcode"
  },
  "geometry": {"coordinates":[-0.167672,51.518829],"type":"Point"}
}
