{
  "type": "Feature",
  "properties": {
    "iso:country":"GB",
    "wof:name":"NW1 5AZ",
    "wof:placetype":"postalcode"
},
  "geometry": {"coordinates":[-0.16767192746073,51.51882881603039],"type":"Point"}
}