{
  "type": "Feature",
  "properties": {
    "iso:country": "GB",
    "wof:name": "MK12 5PN",
    "wof:placetype": "postalcode"
  },
  "geometry": {"coordinates":[-0.827042,52.063524],"type":"Point"}
}
