{
  "type": "Feature",
  "properties": {
    "iso:country":"GB",
    "wof:name":"E3 2PD",
    "wof:placetype":"postalcode"
},
  "geometry": {"coordinates":[-0.02152430943899,51.54156203019462],"type":"Point"}
}