{
  "type": "Feature",
  "properties": {
    "date:inception_lower":"2004-11-01",
    "date:inception_upper":"2004-11-30",
    "iso:country":"GB",
    "wof:name":"E3 2PD",
    "wof:placetype":"postalcode"
},
  "geometry": {"coordinates":[-0.021524,51.541562],"type":"Point"}
}