{
  "type": "Feature",
  "properties": {
    "date:inception_lower": "1980-01-01",
    "date:inception_upper": "1980-01-01",
    "iso:country": "GB",
    "wof:name": "SL2 2BX",
    "wof:placetype": "postalcode"
  },
  "geometry": {"coordinates":[-0.62911,51.535829],"type":"Point"}
}
