{
  "type": "Feature",
  "properties": {
    "iso:country":"GB",
    "wof:name":"SL2 2BX",
    "wof:placetype":"postalcode"
},
  "geometry": {"coordinates":[-0.62910990202077,51.53582923020126],"type":"Point"}
}