{
  "type": "Feature",
  "properties": {
    "iso:country": "GB",
    "wof:name": "SL2 2BX",
    "wof:placetype": "postalcode"
  },
  "geometry": {"coordinates":[-0.62911,51.535829],"type":"Point"}
}
