{
  "type": "Feature",
  "properties": {
    "iso:country":"GB",
    "wof:name":"UB7 7QJ",
    "wof:placetype":"postalcode"
},
  "geometry": {"coordinates":[-0.47358250428752,51.51283137499163],"type":"Point"}
}