{
  "type": "Feature",
  "properties": {
    "date:inception_lower": "1980-01-01",
    "date:inception_upper": "1980-01-01",
    "iso:country": "GB",
    "wof:name": "MK43 8RX",
    "wof:placetype": "postalcode"
  },
  "geometry": {"coordinates":[-0.537654,52.128182],"type":"Point"}
}
