{
  "type": "Feature",
  "properties": {
    "iso:country":"GB",
    "wof:name":"TW14 8ND",
    "wof:placetype":"postalcode"
},
  "geometry": {"coordinates":[-0.44285793898569,51.45404098986944],"type":"Point"}
}