{
  "type": "Feature",
  "properties": {
    "iso:country":"GB",
    "wof:name":"ST3 1TD",
    "wof:placetype":"postalcode"
},
  "geometry": {"coordinates":[-2.1247133881924,52.99261649122053],"type":"Point"}
}