{
  "type": "Feature",
  "properties": {
    "date:inception_lower": "1995-07-01",
    "date:inception_upper": "1995-07-01",
    "iso:country": "GB",
    "wof:name": "M5 4BE",
    "wof:placetype": "postalcode"
  },
  "geometry": {"coordinates":[-2.275554,53.482011],"type":"Point"}
}
