{
  "type": "Feature",
  "properties": {
    "iso:country": "GB",
    "wof:name": "M5 4BE",
    "wof:placetype": "postalcode"
  },
  "geometry": {"coordinates":[-2.275554,53.482011],"type":"Point"}
}
