{
  "type": "Feature",
  "properties": {
    "iso:country": "GB",
    "wof:name": "TF9 4DA",
    "wof:placetype": "postalcode"
  },
  "geometry": {"coordinates":[-2.39065,52.921069],"type":"Point"}
}
