{
  "type": "Feature",
  "properties": {
    "iso:country":"GB",
    "wof:name":"GU1 2EU",
    "wof:placetype":"postalcode"
},
  "geometry": {"coordinates":[-0.55922452049392,51.24017155516065],"type":"Point"}
}