{
  "type": "Feature",
  "properties": {
    "iso:country":"GB",
    "wof:name":"M24 4BT",
    "wof:placetype":"postalcode"
},
  "geometry": {"coordinates":[-2.22199693488913,53.54494256213172],"type":"Point"}
}