{
  "type": "Feature",
  "properties": {
    "date:inception_lower":"1995-07-01",
    "date:inception_upper":"1995-07-31",
    "iso:country":"GB",
    "wof:name":"M24 4BT",
    "wof:placetype":"postalcode"
},
  "geometry": {"coordinates":[-2.221997,53.544943],"type":"Point"}
}