{
  "type": "Feature",
  "properties": {
    "date:inception_lower": "1990-02-01",
    "date:inception_upper": "1990-02-01",
    "iso:country": "GB",
    "wof:name": "ME6 5HZ",
    "wof:placetype": "postalcode"
  },
  "geometry": {"coordinates":[0.444477,51.324777],"type":"Point"}
}
