{
  "type": "Feature",
  "properties": {
    "date:inception_lower": "1980-01-01",
    "date:inception_upper": "1980-01-01",
    "iso:country": "GB",
    "wof:name": "TA23 0NP",
    "wof:placetype": "postalcode"
  },
  "geometry": {"coordinates":[-3.359565,51.15953],"type":"Point"}
}
