{
  "type": "Feature",
  "properties": {
    "iso:country":"GB",
    "wof:name":"WN1 3PX",
    "wof:placetype":"postalcode"
},
  "geometry": {"coordinates":[-2.61560456993749,53.55317207028531],"type":"Point"}
}