{
  "type": "Feature",
  "properties": {
    "iso:country":"GB",
    "wof:name":"BN3 7GB",
    "wof:placetype":"postalcode"
},
  "geometry": {"coordinates":[-0.20462978092344,50.83707289111207],"type":"Point"}
}