{
  "type": "Feature",
  "properties": {
    "iso:country": "GB",
    "wof:name": "BN3 7GB",
    "wof:placetype": "postalcode"
  },
  "geometry": {"coordinates":[-0.204542,50.837138],"type":"Point"}
}
