{
  "type": "Feature",
  "properties": {
    "date:inception_lower": "2016-07-01",
    "date:inception_upper": "2016-07-01",
    "iso:country": "GB",
    "wof:name": "GL1 1AP",
    "wof:placetype": "postalcode"
  },
  "geometry": {"coordinates":[-2.238826,51.863623],"type":"Point"}
}
