{
  "type": "Feature",
  "properties": {
    "iso:country":"GB",
    "wof:name":"B33 9TN",
    "wof:placetype":"postalcode"
},
  "geometry": {"coordinates":[-1.77673961818042,52.48564952575437],"type":"Point"}
}