{
  "type": "Feature",
  "properties": {
    "iso:country": "GB",
    "wof:name": "CM23 1HH",
    "wof:placetype": "postalcode"
  },
  "geometry": {"coordinates":[0.169571,51.898094],"type":"Point"}
}
