{
  "type": "Feature",
  "properties": {
    "iso:country":"GB",
    "wof:name":"CR3 7EN",
    "wof:placetype":"postalcode"
},
  "geometry": {"coordinates":[-0.03529583142998,51.28733420261023],"type":"Point"}
}