{
  "type": "Feature",
  "properties": {
    "iso:country":"GB",
    "wof:name":"CM5 9EA",
    "wof:placetype":"postalcode"
},
  "geometry": {"coordinates":[0.24420646922635,51.70200469207681],"type":"Point"}
}