{
  "type": "Feature",
  "properties": {
    "iso:country":"GB",
    "wof:name":"RM7 0YB",
    "wof:placetype":"postalcode"
},
  "geometry": {"coordinates":[0.17689305814822,51.55773296610206],"type":"Point"}
}