{
  "type": "Feature",
  "properties": {
    "date:inception_lower": "1980-01-01",
    "date:inception_upper": "1980-01-01",
    "iso:country": "GB",
    "wof:name": "ME16 8SB",
    "wof:placetype": "postalcode"
  },
  "geometry": {"coordinates":[0.508446,51.271233],"type":"Point"}
}
