{
  "type": "Feature",
  "properties": {
    "iso:country":"GB",
    "wof:name":"TA20 3PT",
    "wof:placetype":"postalcode"
},
  "geometry": {"coordinates":[-3.009895890987,50.88563633773346],"type":"Point"}
}