{
  "type": "Feature",
  "properties": {
    "date:inception_lower":"1980-01-01",
    "date:inception_upper":"1980-01-31",
    "iso:country":"GB",
    "wof:name":"TA20 3PT",
    "wof:placetype":"postalcode"
},
  "geometry": {"coordinates":[-3.008353,50.884958],"type":"Point"}
}