{
  "type": "Feature",
  "properties": {
    "iso:country":"GB",
    "wof:name":"BA16 9QL",
    "wof:placetype":"postalcode"
},
  "geometry": {"coordinates":[-2.77528938252456,51.12346328327516],"type":"Point"}
}