{
  "type": "Feature",
  "properties": {
    "iso:country": "GB",
    "wof:name": "BA16 9QL",
    "wof:placetype": "postalcode"
  },
  "geometry": {"coordinates":[-2.775289,51.123463],"type":"Point"}
}
