{
  "type": "Feature",
  "properties": {
    "date:inception_lower":"2001-06-01",
    "date:inception_upper":"2001-06-30",
    "iso:country":"GB",
    "wof:name":"NN6 7GR",
    "wof:placetype":"postalcode"
},
  "geometry": {"coordinates":[-1.084937,52.298497],"type":"Point"}
}