{
  "type": "Feature",
  "properties": {
    "iso:country":"GB",
    "wof:name":"NN6 7GR",
    "wof:placetype":"postalcode"
},
  "geometry": {"coordinates":[-1.08493723693938,52.29849670827261],"type":"Point"}
}