{
  "type": "Feature",
  "properties": {
    "iso:country": "GB",
    "wof:name": "G13 1YD",
    "wof:placetype": "postalcode"
  },
  "geometry": {"coordinates":[-4.347737,55.885897],"type":"Point"}
}
