{
  "type": "Feature",
  "properties": {
    "date:inception_lower": "1994-05-01",
    "date:inception_upper": "1994-05-01",
    "iso:country": "GB",
    "wof:name": "NN29 7RG",
    "wof:placetype": "postalcode"
  },
  "geometry": {"coordinates":[-0.66594,52.252633],"type":"Point"}
}
