{
  "type": "Feature",
  "properties": {
    "iso:country":"GB",
    "wof:name":"NN29 7RG",
    "wof:placetype":"postalcode"
},
  "geometry": {"coordinates":[-0.66577292183864,52.2523746971928],"type":"Point"}
}