{
  "type": "Feature",
  "properties": {
    "iso:country":"GB",
    "wof:name":"BH21 2JA",
    "wof:placetype":"postalcode"
},
  "geometry": {"coordinates":[-1.9506800181238,50.80095314805742],"type":"Point"}
}