{
  "type": "Feature",
  "properties": {
    "iso:country": "GB",
    "wof:name": "NR12 0NH",
    "wof:placetype": "postalcode"
  },
  "geometry": {"coordinates":[1.505391,52.839678],"type":"Point"}
}
