{
  "type": "Feature",
  "properties": {
    "iso:country":"GB",
    "wof:name":"BS10 7QT",
    "wof:placetype":"postalcode"
},
  "geometry": {"coordinates":[-2.63694459374885,51.50571609465772],"type":"Point"}
}