{
  "type": "Feature",
  "properties": {
    "iso:country": "GB",
    "wof:name": "SA48 7BJ",
    "wof:placetype": "postalcode"
  },
  "geometry": {"coordinates":[-4.083092,52.113517],"type":"Point"}
}
