{
  "type": "Feature",
  "properties": {
    "iso:country":"GB",
    "wof:name":"NE49 9LR",
    "wof:placetype":"postalcode"
},
  "geometry": {"coordinates":[-2.45091213407331,54.97335883380315],"type":"Point"}
}