{
  "type": "Feature",
  "properties": {
    "iso:country": "GB",
    "wof:name": "NE49 9LR",
    "wof:placetype": "postalcode"
  },
  "geometry": {"coordinates":[-2.450912,54.973359],"type":"Point"}
}
