{
  "type": "Feature",
  "properties": {
    "date:inception_lower": "1981-09-01",
    "date:inception_upper": "1981-09-01",
    "iso:country": "GB",
    "wof:name": "ME9 9HQ",
    "wof:placetype": "postalcode"
  },
  "geometry": {"coordinates":[0.817721,51.345816],"type":"Point"}
}
