{
  "type": "Feature",
  "properties": {
    "iso:country":"GB",
    "wof:name":"ME9 9HQ",
    "wof:placetype":"postalcode"
},
  "geometry": {"coordinates":[0.817721248749,51.34581610402451],"type":"Point"}
}