{
  "type": "Feature",
  "properties": {
    "iso:country":"GB",
    "wof:name":"LS17 9AS",
    "wof:placetype":"postalcode"
},
  "geometry": {"coordinates":[-1.43889566329738,53.88948455229604],"type":"Point"}
}