{
  "type": "Feature",
  "properties": {
    "date:inception_lower": "1980-01-01",
    "date:inception_upper": "1980-01-01",
    "iso:country": "GB",
    "wof:name": "NW1 1LE",
    "wof:placetype": "postalcode"
  },
  "geometry": {"coordinates":[-0.131687,51.529601],"type":"Point"}
}
