{
  "type": "Feature",
  "properties": {
    "iso:country":"GB",
    "wof:name":"NW1 1LE",
    "wof:placetype":"postalcode"
},
  "geometry": {"coordinates":[-0.13168668456345,51.52960069159128],"type":"Point"}
}