{
  "type": "Feature",
  "properties": {
    "iso:country": "GB",
    "wof:name": "HG4 1RY",
    "wof:placetype": "postalcode"
  },
  "geometry": {"coordinates":[-1.52692,54.128596],"type":"Point"}
}
