{
  "type": "Feature",
  "properties": {
    "iso:country":"GB",
    "wof:name":"DT10 2EX",
    "wof:placetype":"postalcode"
},
  "geometry": {"coordinates":[-2.33220205990868,50.94157256747564],"type":"Point"}
}