{
  "type": "Feature",
  "properties": {
    "iso:country": "GB",
    "wof:name": "DT10 2EX",
    "wof:placetype": "postalcode"
  },
  "geometry": {"coordinates":[-2.332128,50.941521],"type":"Point"}
}
