{
  "type": "Feature",
  "properties": {
    "iso:country": "GB",
    "wof:name": "SA72 6NW",
    "wof:placetype": "postalcode"
  },
  "geometry": {"coordinates":[-4.947727,51.687202],"type":"Point"}
}
