{
  "type": "Feature",
  "properties": {
    "iso:country":"GB",
    "wof:name":"SA72 6NW",
    "wof:placetype":"postalcode"
},
  "geometry": {"coordinates":[-4.94772716546813,51.6872020766591],"type":"Point"}
}