{
  "type": "Feature",
  "properties": {
    "iso:country":"GB",
    "wof:name":"BH9 2DF",
    "wof:placetype":"postalcode"
},
  "geometry": {"coordinates":[-1.87458613512582,50.75549277617719],"type":"Point"}
}