{
  "type": "Feature",
  "properties": {
    "iso:country":"GB",
    "wof:name":"NG16 2DH",
    "wof:placetype":"postalcode"
},
  "geometry": {"coordinates":[-1.28265733827627,53.0138922780777],"type":"Point"}
}