{
  "type": "Feature",
  "properties": {
    "iso:country":"GB",
    "wof:name":"NR21 7QY",
    "wof:placetype":"postalcode"
},
  "geometry": {"coordinates":[0.7351771278117,52.85401940492329],"type":"Point"}
}