{
  "type": "Feature",
  "properties": {
    "date:inception_lower": "1980-01-01",
    "date:inception_upper": "1980-01-01",
    "iso:country": "GB",
    "wof:name": "BA3 3QH",
    "wof:placetype": "postalcode"
  },
  "geometry": {"coordinates":[-2.445901,51.289319],"type":"Point"}
}
