{
  "type": "Feature",
  "properties": {
    "iso:country":"GB",
    "wof:name":"BA3 3QH",
    "wof:placetype":"postalcode"
},
  "geometry": {"coordinates":[-2.44647187793545,51.28904239399411],"type":"Point"}
}