{
  "type": "Feature",
  "properties": {
    "iso:country":"GB",
    "wof:name":"HG1 5RX",
    "wof:placetype":"postalcode"
},
  "geometry": {"coordinates":[-1.53147305192241,53.99209095420613],"type":"Point"}
}