{
  "type": "Feature",
  "properties": {
    "iso:country":"GB",
    "wof:name":"CH45 8QD",
    "wof:placetype":"postalcode"
},
  "geometry": {"coordinates":[-3.07173379890716,53.42122367216209],"type":"Point"}
}