{
  "type": "Feature",
  "properties": {
    "date:inception_lower": "1999-06-01",
    "date:inception_upper": "1999-06-01",
    "iso:country": "GB",
    "wof:name": "CH45 8QD",
    "wof:placetype": "postalcode"
  },
  "geometry": {"coordinates":[-3.071734,53.421224],"type":"Point"}
}
