{
  "type": "Feature",
  "properties": {
    "iso:country":"GB",
    "wof:name":"SR6 7PX",
    "wof:placetype":"postalcode"
},
  "geometry": {"coordinates":[-1.40376158909658,54.96039722434699],"type":"Point"}
}