{
  "type": "Feature",
  "properties": {
    "date:inception_lower": "1980-01-01",
    "date:inception_upper": "1980-01-01",
    "iso:country": "GB",
    "wof:name": "SR6 7PX",
    "wof:placetype": "postalcode"
  },
  "geometry": {"coordinates":[-1.403762,54.960397],"type":"Point"}
}
