{
  "type": "Feature",
  "properties": {
    "iso:country":"GB",
    "wof:name":"G46 8JP",
    "wof:placetype":"postalcode"
},
  "geometry": {"coordinates":[-4.31336160296421,55.81262173104679],"type":"Point"}
}