{
  "type": "Feature",
  "properties": {
    "iso:country": "GB",
    "wof:name": "HU9 2EY",
    "wof:placetype": "postalcode"
  },
  "geometry": {"coordinates":[-0.310582,53.753412],"type":"Point"}
}
