{
  "type": "Feature",
  "properties": {
    "iso:country":"GB",
    "wof:name":"HU9 2EY",
    "wof:placetype":"postalcode"
},
  "geometry": {"coordinates":[-0.31058214041044,53.75341247253024],"type":"Point"}
}