{
  "type": "Feature",
  "properties": {
    "iso:country": "GB",
    "wof:name": "WF1 2DJ",
    "wof:placetype": "postalcode"
  },
  "geometry": {"coordinates":[-1.505822,53.685955],"type":"Point"}
}
