{
  "type": "Feature",
  "properties": {
    "iso:country":"GB",
    "wof:name":"WF1 2DJ",
    "wof:placetype":"postalcode"
},
  "geometry": {"coordinates":[-1.50604582480726,53.68601091656235],"type":"Point"}
}