{
  "type": "Feature",
  "properties": {
    "iso:country":"GB",
    "wof:name":"NW6 5TJ",
    "wof:placetype":"postalcode"
},
  "geometry": {"coordinates":[-0.19371130405337,51.53647117776941],"type":"Point"}
}