{
  "type": "Feature",
  "properties": {
    "iso:country": "GB",
    "wof:name": "NW6 5TJ",
    "wof:placetype": "postalcode"
  },
  "geometry": {"coordinates":[-0.193711,51.536471],"type":"Point"}
}
