{
  "type": "Feature",
  "properties": {
    "iso:country":"GB",
    "wof:name":"M20 3JW",
    "wof:placetype":"postalcode"
},
  "geometry": {"coordinates":[-2.23504847309467,53.42743857491347],"type":"Point"}
}