{
  "type": "Feature",
  "properties": {
    "date:inception_lower": "1980-01-01",
    "date:inception_upper": "1980-01-01",
    "iso:country": "GB",
    "wof:name": "BN2 5EL",
    "wof:placetype": "postalcode"
  },
  "geometry": {"coordinates":[-0.109333,50.824353],"type":"Point"}
}
