{
  "type": "Feature",
  "properties": {
    "iso:country":"GB",
    "wof:name":"BN2 5EL",
    "wof:placetype":"postalcode"
},
  "geometry": {"coordinates":[-0.10933324757249,50.82435269675381],"type":"Point"}
}