{
  "type": "Feature",
  "properties": {
    "iso:country": "GB",
    "wof:name": "BN2 5EL",
    "wof:placetype": "postalcode"
  },
  "geometry": {"coordinates":[-0.109333,50.824353],"type":"Point"}
}
