{
  "type": "Feature",
  "properties": {
    "iso:country":"GB",
    "wof:name":"TN17 3AU",
    "wof:placetype":"postalcode"
},
  "geometry": {"coordinates":[0.53826757038358,51.09335770502351],"type":"Point"}
}