{
  "type": "Feature",
  "properties": {
    "iso:country": "GB",
    "wof:name": "RG4 7TS",
    "wof:placetype": "postalcode"
  },
  "geometry": {"coordinates":[-1.035746,51.486304],"type":"Point"}
}
