{
  "type": "Feature",
  "properties": {
    "date:inception_lower":"1980-01-01",
    "date:inception_upper":"1980-01-31",
    "iso:country":"GB",
    "wof:name":"RG4 7TS",
    "wof:placetype":"postalcode"
},
  "geometry": {"coordinates":[-1.035746,51.486304],"type":"Point"}
}