{
  "type": "Feature",
  "properties": {
    "iso:country": "GB",
    "wof:name": "M6 5UD",
    "wof:placetype": "postalcode"
  },
  "geometry": {"coordinates":[-2.280023,53.485605],"type":"Point"}
}
