{
  "type": "Feature",
  "properties": {
    "date:inception_lower":"2010-02-01",
    "date:inception_upper":"2010-02-28",
    "iso:country":"GB",
    "wof:name":"M6 5UD",
    "wof:placetype":"postalcode"
},
  "geometry": {"coordinates":[-2.280023,53.485605],"type":"Point"}
}