{
  "type": "Feature",
  "properties": {
    "iso:country":"GB",
    "wof:name":"KA22 8DS",
    "wof:placetype":"postalcode"
},
  "geometry": {"coordinates":[-4.81153890642739,55.63959618785529],"type":"Point"}
}