{
  "type": "Feature",
  "properties": {
    "date:inception_lower": "1980-01-01",
    "date:inception_upper": "1980-01-01",
    "iso:country": "GB",
    "wof:name": "TF3 2HF",
    "wof:placetype": "postalcode"
  },
  "geometry": {"coordinates":[-2.453292,52.668204],"type":"Point"}
}
