{
  "type": "Feature",
  "properties": {
    "iso:country":"GB",
    "wof:name":"TF3 2HF",
    "wof:placetype":"postalcode"
},
  "geometry": {"coordinates":[-2.45329195332425,52.6682041892379],"type":"Point"}
}