{
  "type": "Feature",
  "properties": {
    "iso:country":"GB",
    "wof:name":"YO32 9TS",
    "wof:placetype":"postalcode"
},
  "geometry": {"coordinates":[-0.99306985574947,54.00276383065835],"type":"Point"}
}