{
  "type": "Feature",
  "properties": {
    "iso:country": "GB",
    "wof:name": "YO32 9TS",
    "wof:placetype": "postalcode"
  },
  "geometry": {"coordinates":[-0.993079,54.002772],"type":"Point"}
}
