{
  "type": "Feature",
  "properties": {
    "iso:country":"GB",
    "wof:name":"NW2 5EL",
    "wof:placetype":"postalcode"
},
  "geometry": {"coordinates":[-0.23383287798182,51.54932066810289],"type":"Point"}
}