{
  "type": "Feature",
  "properties": {
    "iso:country":"GB",
    "wof:name":"NE5 2NG",
    "wof:placetype":"postalcode"
},
  "geometry": {"coordinates":[-1.67195300779486,54.97954107076652],"type":"Point"}
}