{
  "type": "Feature",
  "properties": {
    "iso:country":"GB",
    "wof:name":"NR6 6XA",
    "wof:placetype":"postalcode"
},
  "geometry": {"coordinates":[1.27310812047067,52.66534926148476],"type":"Point"}
}