{
  "type": "Feature",
  "properties": {
    "date:inception_lower": "1980-01-01",
    "date:inception_upper": "1980-01-01",
    "iso:country": "GB",
    "wof:name": "NR6 6XA",
    "wof:placetype": "postalcode"
  },
  "geometry": {"coordinates":[1.273131,52.665374],"type":"Point"}
}
