{
  "type": "Feature",
  "properties": {
    "iso:country":"GB",
    "wof:name":"BS2 9UX",
    "wof:placetype":"postalcode"
},
  "geometry": {"coordinates":[-2.57291574535428,51.4713299418803],"type":"Point"}
}