{
  "type": "Feature",
  "properties": {
    "date:inception_lower": "1980-01-01",
    "date:inception_upper": "1980-01-01",
    "iso:country": "GB",
    "wof:name": "BS2 9UX",
    "wof:placetype": "postalcode"
  },
  "geometry": {"coordinates":[-2.572874,51.471338],"type":"Point"}
}
