{
  "type": "Feature",
  "properties": {
    "iso:country": "GB",
    "wof:name": "DL13 2SB",
    "wof:placetype": "postalcode"
  },
  "geometry": {"coordinates":[-1.950468,54.727042],"type":"Point"}
}
