{
  "type": "Feature",
  "properties": {
    "iso:country":"GB",
    "wof:name":"DL13 2SB",
    "wof:placetype":"postalcode"
},
  "geometry": {"coordinates":[-1.95046810498913,54.7270422558129],"type":"Point"}
}