{
  "type": "Feature",
  "properties": {
    "iso:country": "GB",
    "wof:name": "EX4 2DU",
    "wof:placetype": "postalcode"
  },
  "geometry": {"coordinates":[-3.551102,50.72782],"type":"Point"}
}
