{
  "type": "Feature",
  "properties": {
    "iso:country": "GB",
    "wof:name": "CH44 7HW",
    "wof:placetype": "postalcode"
  },
  "geometry": {"coordinates":[-3.029401,53.410504],"type":"Point"}
}
