{
  "type": "Feature",
  "properties": {
    "iso:country":"GB",
    "wof:name":"SO40 8EH",
    "wof:placetype":"postalcode"
},
  "geometry": {"coordinates":[-1.50770725731506,50.91821357096919],"type":"Point"}
}