{
  "type": "Feature",
  "properties": {
    "date:inception_lower":"1994-12-01",
    "date:inception_upper":"1994-12-31",
    "iso:country":"GB",
    "wof:name":"SO40 8EH",
    "wof:placetype":"postalcode"
},
  "geometry": {"coordinates":[-1.507707,50.918214],"type":"Point"}
}