{
  "type": "Feature",
  "properties": {
    "iso:country": "GB",
    "wof:name": "LS18 5SE",
    "wof:placetype": "postalcode"
  },
  "geometry": {"coordinates":[-1.640327,53.850539],"type":"Point"}
}
