{
  "type": "Feature",
  "properties": {
    "iso:country":"GB",
    "wof:name":"LS18 5SE",
    "wof:placetype":"postalcode"
},
  "geometry": {"coordinates":[-1.64032720752164,53.85053903007506],"type":"Point"}
}