{
  "type": "Feature",
  "properties": {
    "iso:country":"GB",
    "wof:name":"PR2 8NY",
    "wof:placetype":"postalcode"
},
  "geometry": {"coordinates":[-2.69159346781301,53.77703398205363],"type":"Point"}
}