{
  "type": "Feature",
  "properties": {
    "date:inception_lower":"2019-02-01",
    "date:inception_upper":"2019-02-28",
    "iso:country":"GB",
    "wof:name":"NG5 1AT",
    "wof:placetype":"postalcode"
},
  "geometry": {"coordinates":[-1.156511,52.970978],"type":"Point"}
}