{
  "type": "Feature",
  "properties": {
    "date:inception_lower": "1980-01-01",
    "date:inception_upper": "1980-01-01",
    "iso:country": "GB",
    "wof:name": "PL6 5TF",
    "wof:placetype": "postalcode"
  },
  "geometry": {"coordinates":[-4.106916,50.39996],"type":"Point"}
}
