{
  "type": "Feature",
  "properties": {
    "iso:country": "GB",
    "wof:name": "TQ7 4EX",
    "wof:placetype": "postalcode"
  },
  "geometry": {"coordinates":[-3.926102,50.312329],"type":"Point"}
}
