{
  "type": "Feature",
  "properties": {
    "iso:country":"GB",
    "wof:name":"TQ7 4EX",
    "wof:placetype":"postalcode"
},
  "geometry": {"coordinates":[-3.9260764690515,50.31234539090936],"type":"Point"}
}