{
  "type": "Feature",
  "properties": {
    "iso:country":"GB",
    "wof:name":"M24 6AA",
    "wof:placetype":"postalcode"
},
  "geometry": {"coordinates":[-2.19388156403992,53.55140019759103],"type":"Point"}
}