{
  "type": "Feature",
  "properties": {
    "date:inception_lower": "1994-05-01",
    "date:inception_upper": "1994-05-01",
    "iso:country": "GB",
    "wof:name": "M24 6AA",
    "wof:placetype": "postalcode"
  },
  "geometry": {"coordinates":[-2.193716,53.551427],"type":"Point"}
}
