{
  "type": "Feature",
  "properties": {
    "date:inception_lower": "1980-01-01",
    "date:inception_upper": "1980-01-01",
    "iso:country": "GB",
    "wof:name": "BN15 0LJ",
    "wof:placetype": "postalcode"
  },
  "geometry": {"coordinates":[-0.335545,50.839592],"type":"Point"}
}
