{
  "type": "Feature",
  "properties": {
    "iso:country":"GB",
    "wof:name":"BN15 0LJ",
    "wof:placetype":"postalcode"
},
  "geometry": {"coordinates":[-0.33554667594839,50.83949048040212],"type":"Point"}
}