{
  "type": "Feature",
  "properties": {
    "iso:country": "GB",
    "wof:name": "BN15 0LJ",
    "wof:placetype": "postalcode"
  },
  "geometry": {"coordinates":[-0.335547,50.83949],"type":"Point"}
}
