{
  "type": "Feature",
  "properties": {
    "iso:country":"GB",
    "wof:name":"DA16 1HX",
    "wof:placetype":"postalcode"
},
  "geometry": {"coordinates":[0.12398359569313,51.46711981856099],"type":"Point"}
}