{
  "type": "Feature",
  "properties": {
    "date:inception_lower": "1980-01-01",
    "date:inception_upper": "1980-01-01",
    "iso:country": "GB",
    "wof:name": "DA16 1HX",
    "wof:placetype": "postalcode"
  },
  "geometry": {"coordinates":[0.123984,51.46712],"type":"Point"}
}
