{
  "type": "Feature",
  "properties": {
    "date:inception_lower":"1990-07-01",
    "date:inception_upper":"1990-07-31",
    "iso:country":"GB",
    "wof:name":"PR4 5RF",
    "wof:placetype":"postalcode"
},
  "geometry": {"coordinates":[-2.793697,53.71236],"type":"Point"}
}