{
  "type": "Feature",
  "properties": {
    "iso:country":"GB",
    "wof:name":"ST6 8RF",
    "wof:placetype":"postalcode"
},
  "geometry": {"coordinates":[-2.14438864705689,53.08030099728962],"type":"Point"}
}