{
  "type": "Feature",
  "properties": {
    "date:inception_lower":"1980-01-01",
    "date:inception_upper":"1980-01-31",
    "iso:country":"GB",
    "wof:name":"ST6 8RF",
    "wof:placetype":"postalcode"
},
  "geometry": {"coordinates":[-2.144389,53.080301],"type":"Point"}
}