{
  "type": "Feature",
  "properties": {
    "date:inception_lower": "2011-05-01",
    "date:inception_upper": "2011-05-01",
    "iso:country": "GB",
    "wof:name": "G1 1QX",
    "wof:placetype": "postalcode"
  },
  "geometry": {"coordinates":[-4.247626,55.861416],"type":"Point"}
}
