{
  "type": "Feature",
  "properties": {
    "iso:country": "GB",
    "wof:name": "GU32 3FR",
    "wof:placetype": "postalcode"
  },
  "geometry": {"coordinates":[-0.934754,51.007084],"type":"Point"}
}
