{
  "type": "Feature",
  "properties": {
    "iso:country": "GB",
    "wof:name": "BH13 7AY",
    "wof:placetype": "postalcode"
  },
  "geometry": {"coordinates":[-1.931189,50.694198],"type":"Point"}
}
