{
  "type": "Feature",
  "properties": {
    "date:inception_lower":"2009-11-01",
    "date:inception_upper":"2009-11-30",
    "iso:country":"GB",
    "wof:name":"BS2 0AF",
    "wof:placetype":"postalcode"
},
  "geometry": {"coordinates":[-2.580965,51.4556],"type":"Point"}
}