{
  "type": "Feature",
  "properties": {
    "iso:country":"GB",
    "wof:name":"BS2 0AF",
    "wof:placetype":"postalcode"
},
  "geometry": {"coordinates":[-2.58096552699593,51.45559993770751],"type":"Point"}
}