{
  "type": "Feature",
  "properties": {
    "iso:country":"GB",
    "wof:name":"EH54 6HA",
    "wof:placetype":"postalcode"
},
  "geometry": {"coordinates":[-3.51455935445182,55.90115022343372],"type":"Point"}
}