{
  "type": "Feature",
  "properties": {
    "iso:country":"GB",
    "wof:name":"G33 2RA",
    "wof:placetype":"postalcode"
},
  "geometry": {"coordinates":[-4.1893486930193,55.86778336478893],"type":"Point"}
}