{
  "type": "Feature",
  "properties": {
    "iso:country":"GB",
    "wof:name":"LA1 4BJ",
    "wof:placetype":"postalcode"
},
  "geometry": {"coordinates":[-2.78034770835707,54.03734903575431],"type":"Point"}
}