{
  "type": "Feature",
  "properties": {
    "iso:country": "GB",
    "wof:name": "LA1 4BJ",
    "wof:placetype": "postalcode"
  },
  "geometry": {"coordinates":[-2.780348,54.037349],"type":"Point"}
}
