{
  "type": "Feature",
  "properties": {
    "date:inception_lower": "1980-01-01",
    "date:inception_upper": "1980-01-01",
    "iso:country": "GB",
    "wof:name": "BA20 2PP",
    "wof:placetype": "postalcode"
  },
  "geometry": {"coordinates":[-2.653409,50.931161],"type":"Point"}
}
