{
  "type": "Feature",
  "properties": {
    "date:inception_lower": "1980-01-01",
    "date:inception_upper": "1980-01-01",
    "iso:country": "GB",
    "wof:name": "PO15 6DD",
    "wof:placetype": "postalcode"
  },
  "geometry": {"coordinates":[-1.202193,50.862274],"type":"Point"}
}
