{
  "type": "Feature",
  "properties": {
    "iso:country": "GB",
    "wof:name": "G1 1LH",
    "wof:placetype": "postalcode"
  },
  "geometry": {"coordinates":[-4.244523,55.8575],"type":"Point"}
}
