{
  "type": "Feature",
  "properties": {
    "date:inception_lower": "1980-01-01",
    "date:inception_upper": "1980-01-01",
    "iso:country": "GB",
    "wof:name": "G1 1LH",
    "wof:placetype": "postalcode"
  },
  "geometry": {"coordinates":[-4.244523,55.8575],"type":"Point"}
}
