{
  "type": "Feature",
  "properties": {
    "iso:country":"GB",
    "wof:name":"G1 1LH",
    "wof:placetype":"postalcode"
},
  "geometry": {"coordinates":[-4.24461163669751,55.8574046109809],"type":"Point"}
}