{
  "type": "Feature",
  "properties": {
    "iso:country":"GB",
    "wof:name":"B20 1JA",
    "wof:placetype":"postalcode"
},
  "geometry": {"coordinates":[-1.93534206297729,52.52361778773462],"type":"Point"}
}