{
  "type": "Feature",
  "properties": {
    "iso:country": "GB",
    "wof:name": "RG24 4DL",
    "wof:placetype": "postalcode"
  },
  "geometry": {"coordinates":[-1.107856,51.277326],"type":"Point"}
}
