{
  "type": "Feature",
  "properties": {
    "iso:country": "GB",
    "wof:name": "ME13 0SP",
    "wof:placetype": "postalcode"
  },
  "geometry": {"coordinates":[0.827805,51.292651],"type":"Point"}
}
