{
  "type": "Feature",
  "properties": {
    "date:inception_lower":"2007-02-01",
    "date:inception_upper":"2007-02-28",
    "iso:country":"GB",
    "wof:name":"ME13 0SP",
    "wof:placetype":"postalcode"
},
  "geometry": {"coordinates":[0.827805,51.292651],"type":"Point"}
}