{
  "type": "Feature",
  "properties": {
    "iso:country":"GB",
    "wof:name":"ME13 0SP",
    "wof:placetype":"postalcode"
},
  "geometry": {"coordinates":[0.8278044675789,51.29265149408223],"type":"Point"}
}