{
  "type": "Feature",
  "properties": {
    "iso:country": "GB",
    "wof:name": "EX15 1RS",
    "wof:placetype": "postalcode"
  },
  "geometry": {"coordinates":[-3.396215,50.850466],"type":"Point"}
}
