{
  "type": "Feature",
  "properties": {
    "iso:country":"GB",
    "wof:name":"EX15 1RS",
    "wof:placetype":"postalcode"
},
  "geometry": {"coordinates":[-3.39621552948634,50.85046597246646],"type":"Point"}
}