{
  "type": "Feature",
  "properties": {
    "date:inception_lower": "1992-08-01",
    "date:inception_upper": "1992-08-01",
    "iso:country": "GB",
    "wof:name": "EX15 1RS",
    "wof:placetype": "postalcode"
  },
  "geometry": {"coordinates":[-3.396215,50.850466],"type":"Point"}
}
