{
  "type": "Feature",
  "properties": {
    "iso:country": "GB",
    "wof:name": "FK1 2QY",
    "wof:placetype": "postalcode"
  },
  "geometry": {"coordinates":[-3.769135,55.986073],"type":"Point"}
}
