{
  "type": "Feature",
  "properties": {
    "iso:country":"GB",
    "wof:name":"B67 6SH",
    "wof:placetype":"postalcode"
},
  "geometry": {"coordinates":[-1.98276951903117,52.4895443214896],"type":"Point"}
}