{
  "type": "Feature",
  "properties": {
    "iso:country":"GB",
    "wof:name":"PE7 1US",
    "wof:placetype":"postalcode"
},
  "geometry": {"coordinates":[-0.12652700109944,52.55682185589989],"type":"Point"}
}