{
  "type": "Feature",
  "properties": {
    "iso:country":"GB",
    "wof:name":"DL11 7HN",
    "wof:placetype":"postalcode"
},
  "geometry": {"coordinates":[-1.8200653876676,54.49660678519071],"type":"Point"}
}