{
  "type": "Feature",
  "properties": {
    "iso:country": "GB",
    "wof:name": "DL11 7HN",
    "wof:placetype": "postalcode"
  },
  "geometry": {"coordinates":[-1.820065,54.496607],"type":"Point"}
}
