{
  "type": "Feature",
  "properties": {
    "iso:country":"GB",
    "wof:name":"DG5 4HX",
    "wof:placetype":"postalcode"
},
  "geometry": {"coordinates":[-3.80778108187321,54.93355756297822],"type":"Point"}
}