{
  "type": "Feature",
  "properties": {
    "iso:country": "GB",
    "wof:name": "DG5 4HX",
    "wof:placetype": "postalcode"
  },
  "geometry": {"coordinates":[-3.807781,54.933558],"type":"Point"}
}
