{
  "type": "Feature",
  "properties": {
    "iso:country": "GB",
    "wof:name": "KT13 9PZ",
    "wof:placetype": "postalcode"
  },
  "geometry": {"coordinates":[-0.437573,51.370603],"type":"Point"}
}
