{
  "type": "Feature",
  "properties": {
    "iso:country":"GB",
    "wof:name":"E2 8NS",
    "wof:placetype":"postalcode"
},
  "geometry": {"coordinates":[-0.06955281067436,51.53221860622678],"type":"Point"}
}