{
  "type": "Feature",
  "properties": {
    "date:inception_lower": "1980-01-01",
    "date:inception_upper": "1980-01-01",
    "iso:country": "GB",
    "wof:name": "E2 8NS",
    "wof:placetype": "postalcode"
  },
  "geometry": {"coordinates":[-0.069553,51.532219],"type":"Point"}
}
