{
  "type": "Feature",
  "properties": {
    "date:inception_lower":"2014-02-01",
    "date:inception_upper":"2014-02-28",
    "iso:country":"GB",
    "wof:name":"UB4 8HW",
    "wof:placetype":"postalcode"
},
  "geometry": {"coordinates":[-0.436124,51.525979],"type":"Point"}
}