{
  "type": "Feature",
  "properties": {
    "date:inception_lower": "1998-06-01",
    "date:inception_upper": "1998-06-01",
    "iso:country": "GB",
    "wof:name": "YO51 9JB",
    "wof:placetype": "postalcode"
  },
  "geometry": {"coordinates":[-1.406662,54.070389],"type":"Point"}
}
