{
  "type": "Feature",
  "properties": {
    "iso:country": "GB",
    "wof:name": "SY22 6QB",
    "wof:placetype": "postalcode"
  },
  "geometry": {"coordinates":[-3.107599,52.740579],"type":"Point"}
}
