{
  "type": "Feature",
  "properties": {
    "iso:country": "GB",
    "wof:name": "TR20 9BL",
    "wof:placetype": "postalcode"
  },
  "geometry": {"coordinates":[-5.466115,50.139511],"type":"Point"}
}
