{
  "type": "Feature",
  "properties": {
    "iso:country":"GB",
    "wof:name":"ME16 9DQ",
    "wof:placetype":"postalcode"
},
  "geometry": {"coordinates":[0.47803923114584,51.26356206005576],"type":"Point"}
}