{
  "type": "Feature",
  "properties": {
    "iso:country":"GB",
    "wof:name":"AL2 1RQ",
    "wof:placetype":"postalcode"
},
  "geometry": {"coordinates":[-0.29479433719606,51.72169406917681],"type":"Point"}
}