{
  "type": "Feature",
  "properties": {
    "iso:country": "GB",
    "wof:name": "IV30 1DQ",
    "wof:placetype": "postalcode"
  },
  "geometry": {"coordinates":[-3.322355,57.64758],"type":"Point"}
}
