{
  "type": "Feature",
  "properties": {
    "iso:country":"GB",
    "wof:name":"IV30 1DQ",
    "wof:placetype":"postalcode"
},
  "geometry": {"coordinates":[-3.32235538769211,57.64758043390903],"type":"Point"}
}