{
  "type": "Feature",
  "properties": {
    "date:inception_lower":"1987-07-01",
    "date:inception_upper":"1987-07-31",
    "iso:country":"GB",
    "wof:name":"IV30 1DQ",
    "wof:placetype":"postalcode"
},
  "geometry": {"coordinates":[-3.322355,57.64758],"type":"Point"}
}