{
  "type": "Feature",
  "properties": {
    "iso:country":"GB",
    "wof:name":"DT9 6LY",
    "wof:placetype":"postalcode"
},
  "geometry": {"coordinates":[-2.58107924513203,50.89354133660336],"type":"Point"}
}