{
  "type": "Feature",
  "properties": {
    "iso:country": "GB",
    "wof:name": "LS14 3HW",
    "wof:placetype": "postalcode"
  },
  "geometry": {"coordinates":[-1.451655,53.86435],"type":"Point"}
}
