{
  "type": "Feature",
  "properties": {
    "iso:country":"GB",
    "wof:name":"S42 5UP",
    "wof:placetype":"postalcode"
},
  "geometry": {"coordinates":[-1.36282082379717,53.1866709062471],"type":"Point"}
}