{
  "type": "Feature",
  "properties": {
    "date:inception_lower": "1985-04-01",
    "date:inception_upper": "1985-04-01",
    "iso:country": "GB",
    "wof:name": "S42 5UP",
    "wof:placetype": "postalcode"
  },
  "geometry": {"coordinates":[-1.362821,53.186671],"type":"Point"}
}
