{
  "type": "Feature",
  "properties": {
    "iso:country":"GB",
    "wof:name":"TW3 1LS",
    "wof:placetype":"postalcode"
},
  "geometry": {"coordinates":[-0.36348341096867,51.46966770870038],"type":"Point"}
}