{
  "type": "Feature",
  "properties": {
    "iso:country":"GB",
    "wof:name":"GL3 2HT",
    "wof:placetype":"postalcode"
},
  "geometry": {"coordinates":[-2.16914191560776,51.87714954019567],"type":"Point"}
}