{
  "type": "Feature",
  "properties": {
    "iso:country":"GB",
    "wof:name":"BS8 3SJ",
    "wof:placetype":"postalcode"
},
  "geometry": {"coordinates":[-2.69118321780441,51.45851752345064],"type":"Point"}
}