{
  "type": "Feature",
  "properties": {
    "iso:country":"GB",
    "wof:name":"KA22 7HB",
    "wof:placetype":"postalcode"
},
  "geometry": {"coordinates":[-4.80747637233827,55.65366735719456],"type":"Point"}
}