{
  "type": "Feature",
  "properties": {
    "iso:country":"GB",
    "wof:name":"BN6 9DU",
    "wof:placetype":"postalcode"
},
  "geometry": {"coordinates":[-0.22457595428613,50.9292985621001],"type":"Point"}
}