{
  "type": "Feature",
  "properties": {
    "date:inception_lower":"2007-11-01",
    "date:inception_upper":"2007-11-30",
    "iso:country":"GB",
    "wof:name":"B15 2BL",
    "wof:placetype":"postalcode"
},
  "geometry": {"coordinates":[-1.90433,52.469837],"type":"Point"}
}