{
  "type": "Feature",
  "properties": {
    "iso:country": "GB",
    "wof:name": "PE28 3EN",
    "wof:placetype": "postalcode"
  },
  "geometry": {"coordinates":[-0.005892,52.382424],"type":"Point"}
}
