{
  "type": "Feature",
  "properties": {
    "iso:country": "GB",
    "wof:name": "CT4 7EF",
    "wof:placetype": "postalcode"
  },
  "geometry": {"coordinates":[0.972701,51.202848],"type":"Point"}
}
