{
  "type": "Feature",
  "properties": {
    "iso:country":"GB",
    "wof:name":"CT4 7EF",
    "wof:placetype":"postalcode"
},
  "geometry": {"coordinates":[0.97270062927774,51.20284816686377],"type":"Point"}
}