{
  "type": "Feature",
  "properties": {
    "iso:country": "GB",
    "wof:name": "CW7 1ER",
    "wof:placetype": "postalcode"
  },
  "geometry": {"coordinates":[-2.536563,53.184287],"type":"Point"}
}
