{
  "type": "Feature",
  "properties": {
    "iso:country":"GB",
    "wof:name":"L39 3NX",
    "wof:placetype":"postalcode"
},
  "geometry": {"coordinates":[-2.89667549653092,53.56592913422231],"type":"Point"}
}