{
  "type": "Feature",
  "properties": {
    "iso:country":"GB",
    "wof:name":"NE49 0AD",
    "wof:placetype":"postalcode"
},
  "geometry": {"coordinates":[-2.46075908398121,54.96970941879188],"type":"Point"}
}