{
  "type": "Feature",
  "properties": {
    "iso:country":"GB",
    "wof:name":"WR15 8TL",
    "wof:placetype":"postalcode"
},
  "geometry": {"coordinates":[-2.63093464994946,52.28345985866156],"type":"Point"}
}