{
  "type": "Feature",
  "properties": {
    "iso:country":"GB",
    "wof:name":"OL3 6EJ",
    "wof:placetype":"postalcode"
},
  "geometry": {"coordinates":[-1.99689787011027,53.54988589822516],"type":"Point"}
}