{
  "type": "Feature",
  "properties": {
    "iso:country":"GB",
    "wof:name":"WV10 8SG",
    "wof:placetype":"postalcode"
},
  "geometry": {"coordinates":[-2.10286002306452,52.61716545312364],"type":"Point"}
}