{
  "type": "Feature",
  "properties": {
    "date:inception_lower": "2001-06-01",
    "date:inception_upper": "2001-06-01",
    "iso:country": "GB",
    "wof:name": "PO31 7UQ",
    "wof:placetype": "postalcode"
  },
  "geometry": {"coordinates":[-1.307836,50.754063],"type":"Point"}
}
