{
  "type": "Feature",
  "properties": {
    "iso:country":"GB",
    "wof:name":"PO31 7UQ",
    "wof:placetype":"postalcode"
},
  "geometry": {"coordinates":[-1.30780326207996,50.75407389393671],"type":"Point"}
}