{
  "type": "Feature",
  "properties": {
    "iso:country": "GB",
    "wof:name": "NE63 9YA",
    "wof:placetype": "postalcode"
  },
  "geometry": {"coordinates":[-1.530234,55.192668],"type":"Point"}
}
