{
  "type": "Feature",
  "properties": {
    "date:inception_lower": "2004-04-01",
    "date:inception_upper": "2004-04-01",
    "iso:country": "GB",
    "wof:name": "DN20 9SQ",
    "wof:placetype": "postalcode"
  },
  "geometry": {"coordinates":[-0.52959,53.510969],"type":"Point"}
}
