{
  "type": "Feature",
  "properties": {
    "iso:country": "GB",
    "wof:name": "DN20 9SQ",
    "wof:placetype": "postalcode"
  },
  "geometry": {"coordinates":[-0.52959,53.510969],"type":"Point"}
}
