{
  "type": "Feature",
  "properties": {
    "iso:country":"GB",
    "wof:name":"E1 6BX",
    "wof:placetype":"postalcode"
},
  "geometry": {"coordinates":[-0.07735073230835,51.52098007864129],"type":"Point"}
}