{
  "type": "Feature",
  "properties": {
    "date:inception_lower": "1980-01-01",
    "date:inception_upper": "1980-01-01",
    "iso:country": "GB",
    "wof:name": "E1 6BX",
    "wof:placetype": "postalcode"
  },
  "geometry": {"coordinates":[-0.077351,51.52098],"type":"Point"}
}
