{
  "type": "Feature",
  "properties": {
    "iso:country":"GB",
    "wof:name":"CF38 1LJ",
    "wof:placetype":"postalcode"
},
  "geometry": {"coordinates":[-3.30948536433969,51.57194379505928],"type":"Point"}
}