{
  "type": "Feature",
  "properties": {
    "iso:country": "GB",
    "wof:name": "WD23 2LN",
    "wof:placetype": "postalcode"
  },
  "geometry": {"coordinates":[-0.369577,51.653684],"type":"Point"}
}
