{
  "type": "Feature",
  "properties": {
    "date:inception_lower": "1980-01-01",
    "date:inception_upper": "1980-01-01",
    "iso:country": "GB",
    "wof:name": "LS17 6QL",
    "wof:placetype": "postalcode"
  },
  "geometry": {"coordinates":[-1.530272,53.842411],"type":"Point"}
}
