{
  "type": "Feature",
  "properties": {
    "iso:country":"GB",
    "wof:name":"LS17 6QL",
    "wof:placetype":"postalcode"
},
  "geometry": {"coordinates":[-1.53027237647893,53.84241131598589],"type":"Point"}
}