{
  "type": "Feature",
  "properties": {
    "iso:country":"GB",
    "wof:name":"LA14 4DT",
    "wof:placetype":"postalcode"
},
  "geometry": {"coordinates":[-3.22761244688522,54.13997057418499],"type":"Point"}
}