{
  "type": "Feature",
  "properties": {
    "iso:country":"GB",
    "wof:name":"OL13 9RF",
    "wof:placetype":"postalcode"
},
  "geometry": {"coordinates":[-2.19108732761767,53.69470411633669],"type":"Point"}
}