{
  "type": "Feature",
  "properties": {
    "iso:country": "GB",
    "wof:name": "CF11 6DB",
    "wof:placetype": "postalcode"
  },
  "geometry": {"coordinates":[-3.198211,51.479429],"type":"Point"}
}
