{
  "type": "Feature",
  "properties": {
    "iso:country":"GB",
    "wof:name":"OX29 9SX",
    "wof:placetype":"postalcode"
},
  "geometry": {"coordinates":[-1.50537843609684,51.79709405406041],"type":"Point"}
}