{
  "type": "Feature",
  "properties": {
    "iso:country": "GB",
    "wof:name": "OX29 9SX",
    "wof:placetype": "postalcode"
  },
  "geometry": {"coordinates":[-1.505378,51.797094],"type":"Point"}
}
