{
  "type": "Feature",
  "properties": {
    "iso:country":"GB",
    "wof:name":"EX18 7JA",
    "wof:placetype":"postalcode"
},
  "geometry": {"coordinates":[-3.78437197108935,50.90772310580014],"type":"Point"}
}