{
  "type": "Feature",
  "properties": {
    "iso:country":"GB",
    "wof:name":"CO16 7BX",
    "wof:placetype":"postalcode"
},
  "geometry": {"coordinates":[1.13200420607448,51.79927796319657],"type":"Point"}
}