{
  "type": "Feature",
  "properties": {
    "iso:country": "GB",
    "wof:name": "HR3 6PA",
    "wof:placetype": "postalcode"
  },
  "geometry": {"coordinates":[-2.964433,52.129452],"type":"Point"}
}
