{
  "type": "Feature",
  "properties": {
    "iso:country":"GB",
    "wof:name":"CF43 4HB",
    "wof:placetype":"postalcode"
},
  "geometry": {"coordinates":[-3.44758798130937,51.65891870736519],"type":"Point"}
}