{
  "type": "Feature",
  "properties": {
    "iso:country": "GB",
    "wof:name": "WF15 8ET",
    "wof:placetype": "postalcode"
  },
  "geometry": {"coordinates":[-1.72841,53.706088],"type":"Point"}
}
