{
  "type": "Feature",
  "properties": {
    "iso:country": "GB",
    "wof:name": "ML8 4BW",
    "wof:placetype": "postalcode"
  },
  "geometry": {"coordinates":[-3.814202,55.72878],"type":"Point"}
}
