{
  "type": "Feature",
  "properties": {
    "iso:country":"GB",
    "wof:name":"ML8 4BW",
    "wof:placetype":"postalcode"
},
  "geometry": {"coordinates":[-3.81420214568853,55.72877970006981],"type":"Point"}
}