{
  "type": "Feature",
  "properties": {
    "date:inception_lower":"1980-01-01",
    "date:inception_upper":"1980-01-31",
    "iso:country":"GB",
    "wof:name":"FK8 1NQ",
    "wof:placetype":"postalcode"
},
  "geometry": {"coordinates":[-3.938583,56.122251],"type":"Point"}
}