{
  "type": "Feature",
  "properties": {
    "date:inception_lower": "2006-07-01",
    "date:inception_upper": "2006-07-01",
    "iso:country": "GB",
    "wof:name": "SN1 1BD",
    "wof:placetype": "postalcode"
  },
  "geometry": {"coordinates":[-1.786559,51.56344],"type":"Point"}
}
