{
  "type": "Feature",
  "properties": {
    "iso:country":"GB",
    "wof:name":"WD4 8SL",
    "wof:placetype":"postalcode"
},
  "geometry": {"coordinates":[-0.44181732541194,51.71073337212022],"type":"Point"}
}