{
  "type": "Feature",
  "properties": {
    "date:inception_lower":"2006-10-01",
    "date:inception_upper":"2006-10-31",
    "iso:country":"GB",
    "wof:name":"WD4 8SL",
    "wof:placetype":"postalcode"
},
  "geometry": {"coordinates":[-0.441817,51.710733],"type":"Point"}
}