{
  "type": "Feature",
  "properties": {
    "date:inception_lower": "1980-01-01",
    "date:inception_upper": "1980-01-01",
    "iso:country": "GB",
    "wof:name": "RH17 6EF",
    "wof:placetype": "postalcode"
  },
  "geometry": {"coordinates":[-0.184996,51.040844],"type":"Point"}
}
