{
  "type": "Feature",
  "properties": {
    "iso:country": "GB",
    "wof:name": "RH17 6EF",
    "wof:placetype": "postalcode"
  },
  "geometry": {"coordinates":[-0.184996,51.040844],"type":"Point"}
}
