{
  "type": "Feature",
  "properties": {
    "iso:country":"GB",
    "wof:name":"RH17 6EF",
    "wof:placetype":"postalcode"
},
  "geometry": {"coordinates":[-0.18499587372513,51.04084409466057],"type":"Point"}
}