{
  "type": "Feature",
  "properties": {
    "iso:country":"GB",
    "wof:name":"RH10 5JG",
    "wof:placetype":"postalcode"
},
  "geometry": {"coordinates":[-0.1822415688952,51.09698103784006],"type":"Point"}
}