{
  "type": "Feature",
  "properties": {
    "iso:country": "GB",
    "wof:name": "SG18 0JA",
    "wof:placetype": "postalcode"
  },
  "geometry": {"coordinates":[-0.26655,52.086927],"type":"Point"}
}
