{
  "type": "Feature",
  "properties": {
    "date:inception_lower": "1980-01-01",
    "date:inception_upper": "1980-01-01",
    "iso:country": "GB",
    "wof:name": "SG18 0JA",
    "wof:placetype": "postalcode"
  },
  "geometry": {"coordinates":[-0.266619,52.087027],"type":"Point"}
}
