{
  "type": "Feature",
  "properties": {
    "iso:country":"GB",
    "wof:name":"KA10 6EQ",
    "wof:placetype":"postalcode"
},
  "geometry": {"coordinates":[-4.65357156752364,55.53716619022929],"type":"Point"}
}