{
  "type": "Feature",
  "properties": {
    "iso:country":"GB",
    "wof:name":"NG13 8UE",
    "wof:placetype":"postalcode"
},
  "geometry": {"coordinates":[-0.93830929706798,52.94997229877318],"type":"Point"}
}