{
  "type": "Feature",
  "properties": {
    "iso:country": "GB",
    "wof:name": "NG13 8UE",
    "wof:placetype": "postalcode"
  },
  "geometry": {"coordinates":[-0.938309,52.949972],"type":"Point"}
}
