{
  "type": "Feature",
  "properties": {
    "iso:country": "GB",
    "wof:name": "NW6 3NS",
    "wof:placetype": "postalcode"
  },
  "geometry": {"coordinates":[-0.188545,51.545654],"type":"Point"}
}
