{
  "type": "Feature",
  "properties": {
    "iso:country":"GB",
    "wof:name":"SL1 4HY",
    "wof:placetype":"postalcode"
},
  "geometry": {"coordinates":[-0.61699102122381,51.51942046578033],"type":"Point"}
}