{
  "type": "Feature",
  "properties": {
    "iso:country":"GB",
    "wof:name":"EH21 9AT",
    "wof:placetype":"postalcode"
},
  "geometry": {"coordinates":[-3.04791080697334,55.94370899271333],"type":"Point"}
}