{
  "type": "Feature",
  "properties": {
    "iso:country":"GB",
    "wof:name":"B31 5PE",
    "wof:placetype":"postalcode"
},
  "geometry": {"coordinates":[-1.99476640790672,52.41073007259227],"type":"Point"}
}