{
  "type": "Feature",
  "properties": {
    "iso:country":"GB",
    "wof:name":"CF24 3QA",
    "wof:placetype":"postalcode"
},
  "geometry": {"coordinates":[-3.16239066902928,51.49163168694157],"type":"Point"}
}