{
  "type": "Feature",
  "properties": {
    "iso:country": "GB",
    "wof:name": "CF24 3QA",
    "wof:placetype": "postalcode"
  },
  "geometry": {"coordinates":[-3.162886,51.49152],"type":"Point"}
}
