{
  "type": "Feature",
  "properties": {
    "iso:country":"GB",
    "wof:name":"MK17 9HY",
    "wof:placetype":"postalcode"
},
  "geometry": {"coordinates":[-0.63040323760419,51.99952573214667],"type":"Point"}
}