{
  "type": "Feature",
  "properties": {
    "iso:country":"GB",
    "wof:name":"BH16 5JH",
    "wof:placetype":"postalcode"
},
  "geometry": {"coordinates":[-2.02571114748457,50.738300170713],"type":"Point"}
}