{
  "type": "Feature",
  "properties": {
    "iso:country":"GB",
    "wof:name":"WF4 4LL",
    "wof:placetype":"postalcode"
},
  "geometry": {"coordinates":[-1.57832523682165,53.64268511377414],"type":"Point"}
}