{
  "type": "Feature",
  "properties": {
    "iso:country": "GB",
    "wof:name": "WF4 4LL",
    "wof:placetype": "postalcode"
  },
  "geometry": {"coordinates":[-1.578325,53.642685],"type":"Point"}
}
