{
  "type": "Feature",
  "properties": {
    "iso:country": "GB",
    "wof:name": "L30 0RF",
    "wof:placetype": "postalcode"
  },
  "geometry": {"coordinates":[-2.977564,53.494671],"type":"Point"}
}
