{
  "type": "Feature",
  "properties": {
    "iso:country":"GB",
    "wof:name":"L30 0RF",
    "wof:placetype":"postalcode"
},
  "geometry": {"coordinates":[-2.97756449498466,53.49467069109814],"type":"Point"}
}