{
  "type": "Feature",
  "properties": {
    "iso:country":"GB",
    "wof:name":"LL30 3LP",
    "wof:placetype":"postalcode"
},
  "geometry": {"coordinates":[-3.76823828391374,53.31697302546072],"type":"Point"}
}