{
  "type": "Feature",
  "properties": {
    "iso:country":"GB",
    "wof:name":"HG2 9AN",
    "wof:placetype":"postalcode"
},
  "geometry": {"coordinates":[-1.55062303120639,53.97857454472174],"type":"Point"}
}