{
  "type": "Feature",
  "properties": {
    "date:inception_lower": "1980-01-01",
    "date:inception_upper": "1980-01-01",
    "iso:country": "GB",
    "wof:name": "SY12 0EG",
    "wof:placetype": "postalcode"
  },
  "geometry": {"coordinates":[-2.895327,52.906827],"type":"Point"}
}
