{
  "type": "Feature",
  "properties": {
    "iso:country":"GB",
    "wof:name":"TR15 2TS",
    "wof:placetype":"postalcode"
},
  "geometry": {"coordinates":[-5.23395597506887,50.23186729424356],"type":"Point"}
}