{
  "type": "Feature",
  "properties": {
    "date:inception_lower": "1990-02-01",
    "date:inception_upper": "1990-02-01",
    "iso:country": "GB",
    "wof:name": "TR15 2TS",
    "wof:placetype": "postalcode"
  },
  "geometry": {"coordinates":[-5.234004,50.231848],"type":"Point"}
}
