{
  "type": "Feature",
  "properties": {
    "iso:country": "GB",
    "wof:name": "TR15 2TS",
    "wof:placetype": "postalcode"
  },
  "geometry": {"coordinates":[-5.234004,50.231848],"type":"Point"}
}
