{
  "type": "Feature",
  "properties": {
    "iso:country":"GB",
    "wof:name":"DT2 8HF",
    "wof:placetype":"postalcode"
},
  "geometry": {"coordinates":[-2.35112444761965,50.67382636978294],"type":"Point"}
}