{
  "type": "Feature",
  "properties": {
    "iso:country": "GB",
    "wof:name": "DT2 8HF",
    "wof:placetype": "postalcode"
  },
  "geometry": {"coordinates":[-2.351153,50.673817],"type":"Point"}
}
