{
  "type": "Feature",
  "properties": {
    "date:inception_lower":"1980-01-01",
    "date:inception_upper":"1980-01-31",
    "iso:country":"GB",
    "wof:name":"DT2 8HF",
    "wof:placetype":"postalcode"
},
  "geometry": {"coordinates":[-2.351153,50.673817],"type":"Point"}
}