{
  "type": "Feature",
  "properties": {
    "iso:country":"GB",
    "wof:name":"SE26 6UQ",
    "wof:placetype":"postalcode"
},
  "geometry": {"coordinates":[-0.06222616177888,51.42252239543176],"type":"Point"}
}