{
  "type": "Feature",
  "properties": {
    "iso:country":"GB",
    "wof:name":"AB16 7SX",
    "wof:placetype":"postalcode"
},
  "geometry": {"coordinates":[-2.17066209709445,57.16773563306245],"type":"Point"}
}