{
  "type": "Feature",
  "properties": {
    "iso:country":"GB",
    "wof:name":"DN40 1HF",
    "wof:placetype":"postalcode"
},
  "geometry": {"coordinates":[-0.20581008633596,53.61111518823891],"type":"Point"}
}