{
  "type": "Feature",
  "properties": {
    "iso:country":"GB",
    "wof:name":"BS4 5DW",
    "wof:placetype":"postalcode"
},
  "geometry": {"coordinates":[-2.55109392021779,51.42868834565295],"type":"Point"}
}