{
  "type": "Feature",
  "properties": {
    "iso:country":"GB",
    "wof:name":"NG32 2AZ",
    "wof:placetype":"postalcode"
},
  "geometry": {"coordinates":[-0.62464360207454,53.00713304931994],"type":"Point"}
}