{
  "type": "Feature",
  "properties": {
    "date:inception_lower":"1980-01-01",
    "date:inception_upper":"1980-01-31",
    "iso:country":"GB",
    "wof:name":"NG32 2AZ",
    "wof:placetype":"postalcode"
},
  "geometry": {"coordinates":[-0.624644,53.007133],"type":"Point"}
}