{
  "type": "Feature",
  "properties": {
    "iso:country":"GB",
    "wof:name":"SO17 2LS",
    "wof:placetype":"postalcode"
},
  "geometry": {"coordinates":[-1.3815162059475,50.92627338055715],"type":"Point"}
}