{
  "type": "Feature",
  "properties": {
    "iso:country":"GB",
    "wof:name":"M41 9PW",
    "wof:placetype":"postalcode"
},
  "geometry": {"coordinates":[-2.32889178389406,53.45012863361686],"type":"Point"}
}