{
  "type": "Feature",
  "properties": {
    "date:inception_lower": "1993-08-01",
    "date:inception_upper": "1993-08-01",
    "iso:country": "GB",
    "wof:name": "NN4 6DD",
    "wof:placetype": "postalcode"
  },
  "geometry": {"coordinates":[-0.886815,52.213865],"type":"Point"}
}
