{
  "type": "Feature",
  "properties": {
    "iso:country": "GB",
    "wof:name": "NN4 6DD",
    "wof:placetype": "postalcode"
  },
  "geometry": {"coordinates":[-0.886815,52.213865],"type":"Point"}
}
