{
  "type": "Feature",
  "properties": {
    "iso:country": "GB",
    "wof:name": "ML5 4UB",
    "wof:placetype": "postalcode"
  },
  "geometry": {"coordinates":[-4.000391,55.848363],"type":"Point"}
}
