{
  "type": "Feature",
  "properties": {
    "iso:country":"GB",
    "wof:name":"ML5 4UB",
    "wof:placetype":"postalcode"
},
  "geometry": {"coordinates":[-4.00039142741337,55.84836268470044],"type":"Point"}
}