{
  "type": "Feature",
  "properties": {
    "iso:country": "GB",
    "wof:name": "BB7 4DF",
    "wof:placetype": "postalcode"
  },
  "geometry": {"coordinates":[-2.314305,53.89777],"type":"Point"}
}
