{
  "type": "Feature",
  "properties": {
    "iso:country":"GB",
    "wof:name":"BB7 4DF",
    "wof:placetype":"postalcode"
},
  "geometry": {"coordinates":[-2.31430548158252,53.8977704387639],"type":"Point"}
}