{
  "type": "Feature",
  "properties": {
    "date:inception_lower": "2014-03-01",
    "date:inception_upper": "2014-03-01",
    "iso:country": "GB",
    "wof:name": "LD3 0LR",
    "wof:placetype": "postalcode"
  },
  "geometry": {"coordinates":[-3.250357,52.006133],"type":"Point"}
}
