{
  "type": "Feature",
  "properties": {
    "iso:country":"GB",
    "wof:name":"LD3 0LR",
    "wof:placetype":"postalcode"
},
  "geometry": {"coordinates":[-3.25035691318424,52.00613289838239],"type":"Point"}
}