{
  "type": "Feature",
  "properties": {
    "iso:country": "GB",
    "wof:name": "GL2 4DS",
    "wof:placetype": "postalcode"
  },
  "geometry": {"coordinates":[-2.270338,51.805929],"type":"Point"}
}
