{
  "type": "Feature",
  "properties": {
    "iso:country":"GB",
    "wof:name":"ST17 4BN",
    "wof:placetype":"postalcode"
},
  "geometry": {"coordinates":[-2.11369645515044,52.80279099504749],"type":"Point"}
}