{
  "type": "Feature",
  "properties": {
    "iso:country": "GB",
    "wof:name": "ST17 4BN",
    "wof:placetype": "postalcode"
  },
  "geometry": {"coordinates":[-2.113663,52.802762],"type":"Point"}
}
