{
  "type": "Feature",
  "properties": {
    "date:inception_lower": "1980-01-01",
    "date:inception_upper": "1980-01-01",
    "iso:country": "GB",
    "wof:name": "EN1 4PA",
    "wof:placetype": "postalcode"
  },
  "geometry": {"coordinates":[-0.047212,51.679128],"type":"Point"}
}
