{
  "type": "Feature",
  "properties": {
    "iso:country":"GB",
    "wof:name":"EN1 4PA",
    "wof:placetype":"postalcode"
},
  "geometry": {"coordinates":[-0.04721177410779,51.67912781653094],"type":"Point"}
}