{
  "type": "Feature",
  "properties": {
    "date:inception_lower": "1980-01-01",
    "date:inception_upper": "1980-01-01",
    "iso:country": "GB",
    "wof:name": "PO21 2AH",
    "wof:placetype": "postalcode"
  },
  "geometry": {"coordinates":[-0.678702,50.786622],"type":"Point"}
}
