{
  "type": "Feature",
  "properties": {
    "iso:country": "GB",
    "wof:name": "CW11 2LB",
    "wof:placetype": "postalcode"
  },
  "geometry": {"coordinates":[-2.346328,53.144272],"type":"Point"}
}
