{
  "type": "Feature",
  "properties": {
    "iso:country":"GB",
    "wof:name":"CW11 2LB",
    "wof:placetype":"postalcode"
},
  "geometry": {"coordinates":[-2.34632786910834,53.14425475433922],"type":"Point"}
}