{
  "type": "Feature",
  "properties": {
    "iso:country": "GB",
    "wof:name": "TN26 3TG",
    "wof:placetype": "postalcode"
  },
  "geometry": {"coordinates":[0.778627,51.071609],"type":"Point"}
}
