{
  "type": "Feature",
  "properties": {
    "date:inception_lower": "1980-01-01",
    "date:inception_upper": "1980-01-01",
    "iso:country": "GB",
    "wof:name": "TN26 3TG",
    "wof:placetype": "postalcode"
  },
  "geometry": {"coordinates":[0.778627,51.071609],"type":"Point"}
}
