{
  "type": "Feature",
  "properties": {
    "iso:country":"GB",
    "wof:name":"RG27 9UN",
    "wof:placetype":"postalcode"
},
  "geometry": {"coordinates":[-0.94707666611299,51.28528879576434],"type":"Point"}
}