{
  "type": "Feature",
  "properties": {
    "iso:country":"GB",
    "wof:name":"KT22 9DR",
    "wof:placetype":"postalcode"
},
  "geometry": {"coordinates":[-0.33483540152415,51.29374911531574],"type":"Point"}
}