{
  "type": "Feature",
  "properties": {
    "iso:country": "GB",
    "wof:name": "KT22 9DR",
    "wof:placetype": "postalcode"
  },
  "geometry": {"coordinates":[-0.334835,51.293749],"type":"Point"}
}
