{
  "type": "Feature",
  "properties": {
    "iso:country":"GB",
    "wof:name":"CM6 1YN",
    "wof:placetype":"postalcode"
},
  "geometry": {"coordinates":[0.35967574008932,51.87264620223119],"type":"Point"}
}