{
  "type": "Feature",
  "properties": {
    "date:inception_lower": "2009-09-01",
    "date:inception_upper": "2009-09-01",
    "iso:country": "GB",
    "wof:name": "CM6 1YN",
    "wof:placetype": "postalcode"
  },
  "geometry": {"coordinates":[0.35955,51.872486],"type":"Point"}
}
