{
  "type": "Feature",
  "properties": {
    "iso:country":"GB",
    "wof:name":"IP9 2QP",
    "wof:placetype":"postalcode"
},
  "geometry": {"coordinates":[1.15856869852416,51.98058967881808],"type":"Point"}
}