{
  "type": "Feature",
  "properties": {
    "iso:country":"GB",
    "wof:name":"BA8 0EQ",
    "wof:placetype":"postalcode"
},
  "geometry": {"coordinates":[-2.41841577996809,51.01336877263174],"type":"Point"}
}