{
  "type": "Feature",
  "properties": {
    "iso:country":"GB",
    "wof:name":"HD9 1UE",
    "wof:placetype":"postalcode"
},
  "geometry": {"coordinates":[-1.75970256508197,53.56518591661681],"type":"Point"}
}