{
  "type": "Feature",
  "properties": {
    "date:inception_lower": "2022-07-01",
    "date:inception_upper": "2022-07-01",
    "iso:country": "GB",
    "wof:name": "IV36 2AJ",
    "wof:placetype": "postalcode"
  },
  "geometry": {"coordinates":[-3.629108,57.594745],"type":"Point"}
}
