{
  "type": "Feature",
  "properties": {
    "date:inception_lower": "1995-12-01",
    "date:inception_upper": "1995-12-01",
    "iso:country": "GB",
    "wof:name": "DG2 8LT",
    "wof:placetype": "postalcode"
  },
  "geometry": {"coordinates":[-3.641888,55.055675],"type":"Point"}
}
