{
  "type": "Feature",
  "properties": {
    "iso:country":"GB",
    "wof:name":"PA20 0BG",
    "wof:placetype":"postalcode"
},
  "geometry": {"coordinates":[-5.06302341811298,55.83961596652612],"type":"Point"}
}