{
  "type": "Feature",
  "properties": {
    "iso:country": "GB",
    "wof:name": "PO6 1QH",
    "wof:placetype": "postalcode"
  },
  "geometry": {"coordinates":[-1.04516,50.845286],"type":"Point"}
}
