{
  "type": "Feature",
  "properties": {
    "iso:country":"GB",
    "wof:name":"PO6 1QH",
    "wof:placetype":"postalcode"
},
  "geometry": {"coordinates":[-1.04516029217287,50.84528629731572],"type":"Point"}
}