{
  "type": "Feature",
  "properties": {
    "iso:country":"GB",
    "wof:name":"KA28 0AW",
    "wof:placetype":"postalcode"
},
  "geometry": {"coordinates":[-4.93272615175161,55.75070696523214],"type":"Point"}
}