{
  "type": "Feature",
  "properties": {
    "date:inception_lower": "1980-01-01",
    "date:inception_upper": "1980-01-01",
    "iso:country": "GB",
    "wof:name": "KA28 0AW",
    "wof:placetype": "postalcode"
  },
  "geometry": {"coordinates":[-4.932726,55.750707],"type":"Point"}
}
