{
  "type": "Feature",
  "properties": {
    "iso:country": "GB",
    "wof:name": "SO19 0PX",
    "wof:placetype": "postalcode"
  },
  "geometry": {"coordinates":[-1.333716,50.899824],"type":"Point"}
}
