{
  "type": "Feature",
  "properties": {
    "iso:country": "GB",
    "wof:name": "L16 1LA",
    "wof:placetype": "postalcode"
  },
  "geometry": {"coordinates":[-2.884767,53.399645],"type":"Point"}
}
