{
  "type": "Feature",
  "properties": {
    "iso:country":"GB",
    "wof:name":"CH45 8RE",
    "wof:placetype":"postalcode"
},
  "geometry": {"coordinates":[-3.07923901196176,53.42048189473773],"type":"Point"}
}