{
  "type": "Feature",
  "properties": {
    "iso:country":"GB",
    "wof:name":"EX4 1DW",
    "wof:placetype":"postalcode"
},
  "geometry": {"coordinates":[-3.53855889138715,50.7181929499293],"type":"Point"}
}