{
  "type": "Feature",
  "properties": {
    "date:inception_lower": "2024-03-01",
    "date:inception_upper": "2024-03-01",
    "iso:country": "GB",
    "wof:name": "SN1 7ER",
    "wof:placetype": "postalcode"
  },
  "geometry": {"coordinates":[-1.81432,51.549085],"type":"Point"}
}
