{
  "type": "Feature",
  "properties": {
    "iso:country":"GB",
    "wof:name":"S40 4RZ",
    "wof:placetype":"postalcode"
},
  "geometry": {"coordinates":[-1.46800127833078,53.2467474918598],"type":"Point"}
}