{
  "type": "Feature",
  "properties": {
    "iso:country":"GB",
    "wof:name":"CF34 0HX",
    "wof:placetype":"postalcode"
},
  "geometry": {"coordinates":[-3.63995847353964,51.60394723798952],"type":"Point"}
}