{
  "type": "Feature",
  "properties": {
    "iso:country":"GB",
    "wof:name":"DH1 2PD",
    "wof:placetype":"postalcode"
},
  "geometry": {"coordinates":[-1.54469781390004,54.75768760423077],"type":"Point"}
}