{
  "type": "Feature",
  "properties": {
    "iso:country": "GB",
    "wof:name": "SN15 4HB",
    "wof:placetype": "postalcode"
  },
  "geometry": {"coordinates":[-2.00816,51.52061],"type":"Point"}
}
