{
  "type": "Feature",
  "properties": {
    "date:inception_lower":"1980-01-01",
    "date:inception_upper":"1980-01-31",
    "iso:country":"GB",
    "wof:name":"TA20 1NU",
    "wof:placetype":"postalcode"
},
  "geometry": {"coordinates":[-2.947657,50.87864],"type":"Point"}
}