{
  "type": "Feature",
  "properties": {
    "iso:country": "GB",
    "wof:name": "TA20 1NU",
    "wof:placetype": "postalcode"
  },
  "geometry": {"coordinates":[-2.947657,50.87864],"type":"Point"}
}
