{
  "type": "Feature",
  "properties": {
    "iso:country":"GB",
    "wof:name":"ST19 9LJ",
    "wof:placetype":"postalcode"
},
  "geometry": {"coordinates":[-2.17332669150867,52.69891636658259],"type":"Point"}
}