{
  "type": "Feature",
  "properties": {
    "iso:country": "GB",
    "wof:name": "ST19 9LJ",
    "wof:placetype": "postalcode"
  },
  "geometry": {"coordinates":[-2.173117,52.699283],"type":"Point"}
}
