{
  "type": "Feature",
  "properties": {
    "date:inception_lower":"1998-12-01",
    "date:inception_upper":"1998-12-31",
    "iso:country":"GB",
    "wof:name":"SN13 0RD",
    "wof:placetype":"postalcode"
},
  "geometry": {"coordinates":[-2.185464,51.433668],"type":"Point"}
}