{
  "type": "Feature",
  "properties": {
    "iso:country":"GB",
    "wof:name":"YO31 9JE",
    "wof:placetype":"postalcode"
},
  "geometry": {"coordinates":[-1.06195494752463,53.98645944962863],"type":"Point"}
}