{
  "type": "Feature",
  "properties": {
    "date:inception_lower":"2001-12-01",
    "date:inception_upper":"2001-12-31",
    "iso:country":"GB",
    "wof:name":"CV34 6GJ",
    "wof:placetype":"postalcode"
},
  "geometry": {"coordinates":[-1.543975,52.269583],"type":"Point"}
}