{
  "type": "Feature",
  "properties": {
    "iso:country": "GB",
    "wof:name": "CV34 6GJ",
    "wof:placetype": "postalcode"
  },
  "geometry": {"coordinates":[-1.543975,52.269583],"type":"Point"}
}
