{
  "type": "Feature",
  "properties": {
    "date:inception_lower":"1980-01-01",
    "date:inception_upper":"1980-01-31",
    "iso:country":"GB",
    "wof:name":"SS0 0QP",
    "wof:placetype":"postalcode"
},
  "geometry": {"coordinates":[0.692413,51.555324],"type":"Point"}
}