{
  "type": "Feature",
  "properties": {
    "iso:country":"GB",
    "wof:name":"SS0 0QP",
    "wof:placetype":"postalcode"
},
  "geometry": {"coordinates":[0.69241290263866,51.55532433779009],"type":"Point"}
}