{
  "type": "Feature",
  "properties": {
    "iso:country": "GB",
    "wof:name": "BN11 2DQ",
    "wof:placetype": "postalcode"
  },
  "geometry": {"coordinates":[-0.35681,50.8164],"type":"Point"}
}
