{
  "type": "Feature",
  "properties": {
    "date:inception_lower": "1980-01-01",
    "date:inception_upper": "1980-01-01",
    "iso:country": "GB",
    "wof:name": "L11 2TE",
    "wof:placetype": "postalcode"
  },
  "geometry": {"coordinates":[-2.911679,53.443522],"type":"Point"}
}
