{
  "type": "Feature",
  "properties": {
    "iso:country": "GB",
    "wof:name": "L11 2TE",
    "wof:placetype": "postalcode"
  },
  "geometry": {"coordinates":[-2.911679,53.443522],"type":"Point"}
}
