{
  "type": "Feature",
  "properties": {
    "iso:country":"GB",
    "wof:name":"E5 0PD",
    "wof:placetype":"postalcode"
},
  "geometry": {"coordinates":[-0.05187235240528,51.55054093056211],"type":"Point"}
}