{
  "type": "Feature",
  "properties": {
    "date:inception_lower": "1998-06-01",
    "date:inception_upper": "1998-06-01",
    "iso:country": "GB",
    "wof:name": "YO31 8JR",
    "wof:placetype": "postalcode"
  },
  "geometry": {"coordinates":[-1.07649,53.97167],"type":"Point"}
}
