{
  "type": "Feature",
  "properties": {
    "date:inception_lower": "2003-07-01",
    "date:inception_upper": "2003-07-01",
    "iso:country": "GB",
    "wof:name": "M20 3LS",
    "wof:placetype": "postalcode"
  },
  "geometry": {"coordinates":[-2.233053,53.428485],"type":"Point"}
}
