{
  "type": "Feature",
  "properties": {
    "iso:country":"GB",
    "wof:name":"M20 3LS",
    "wof:placetype":"postalcode"
},
  "geometry": {"coordinates":[-2.23305262414365,53.42848516018908],"type":"Point"}
}