{
  "type": "Feature",
  "properties": {
    "iso:country":"GB",
    "wof:name":"LE67 1AJ",
    "wof:placetype":"postalcode"
},
  "geometry": {"coordinates":[-1.30950014127786,52.66383482752363],"type":"Point"}
}