{
  "type": "Feature",
  "properties": {
    "iso:country": "GB",
    "wof:name": "MK6 1BN",
    "wof:placetype": "postalcode"
  },
  "geometry": {"coordinates":[-0.764243,52.028952],"type":"Point"}
}
