{
  "type": "Feature",
  "properties": {
    "iso:country": "GB",
    "wof:name": "LS17 9DX",
    "wof:placetype": "postalcode"
  },
  "geometry": {"coordinates":[-1.452226,53.878886],"type":"Point"}
}
