{
  "type": "Feature",
  "properties": {
    "date:inception_lower":"1980-01-01",
    "date:inception_upper":"1980-01-31",
    "iso:country":"GB",
    "wof:name":"LS17 9DX",
    "wof:placetype":"postalcode"
},
  "geometry": {"coordinates":[-1.452226,53.878886],"type":"Point"}
}