{
  "type": "Feature",
  "properties": {
    "iso:country":"GB",
    "wof:name":"CT17 0AW",
    "wof:placetype":"postalcode"
},
  "geometry": {"coordinates":[1.30098051525393,51.1283573406361],"type":"Point"}
}