{
  "type": "Feature",
  "properties": {
    "iso:country":"GB",
    "wof:name":"G43 2BU",
    "wof:placetype":"postalcode"
},
  "geometry": {"coordinates":[-4.29024149995552,55.81763832894158],"type":"Point"}
}