{
  "type": "Feature",
  "properties": {
    "iso:country":"GB",
    "wof:name":"TD1 1PE",
    "wof:placetype":"postalcode"
},
  "geometry": {"coordinates":[-2.81318540670915,55.61821837866075],"type":"Point"}
}