{
  "type": "Feature",
  "properties": {
    "iso:country":"GB",
    "wof:name":"BN27 2EB",
    "wof:placetype":"postalcode"
},
  "geometry": {"coordinates":[0.26035323884143,50.85782478506815],"type":"Point"}
}