{
  "type": "Feature",
  "properties": {
    "iso:country": "GB",
    "wof:name": "BN27 2EB",
    "wof:placetype": "postalcode"
  },
  "geometry": {"coordinates":[0.260353,50.857825],"type":"Point"}
}
