{
  "type": "Feature",
  "properties": {
    "iso:country": "GB",
    "wof:name": "CT1 3XJ",
    "wof:placetype": "postalcode"
  },
  "geometry": {"coordinates":[1.054862,51.266508],"type":"Point"}
}
