{
  "type": "Feature",
  "properties": {
    "iso:country":"GB",
    "wof:name":"CT1 3XJ",
    "wof:placetype":"postalcode"
},
  "geometry": {"coordinates":[1.05486146257086,51.26650814768527],"type":"Point"}
}