{
  "type": "Feature",
  "properties": {
    "iso:country":"GB",
    "wof:name":"BD6 3DF",
    "wof:placetype":"postalcode"
},
  "geometry": {"coordinates":[-1.80571295143153,53.77148488337263],"type":"Point"}
}