{
  "type": "Feature",
  "properties": {
    "iso:country":"GB",
    "wof:name":"B64 6QP",
    "wof:placetype":"postalcode"
},
  "geometry": {"coordinates":[-2.06106842525319,52.47458833575104],"type":"Point"}
}