{
  "type": "Feature",
  "properties": {
    "date:inception_lower": "1980-01-01",
    "date:inception_upper": "1980-01-01",
    "iso:country": "GB",
    "wof:name": "B64 6QP",
    "wof:placetype": "postalcode"
  },
  "geometry": {"coordinates":[-2.061068,52.474588],"type":"Point"}
}
