{
  "type": "Feature",
  "properties": {
    "iso:country":"GB",
    "wof:name":"YO11 3FN",
    "wof:placetype":"postalcode"
},
  "geometry": {"coordinates":[-0.39586148578378,54.24012890522533],"type":"Point"}
}