{
  "type": "Feature",
  "properties": {
    "date:inception_lower": "2015-08-01",
    "date:inception_upper": "2015-08-01",
    "iso:country": "GB",
    "wof:name": "YO11 3FN",
    "wof:placetype": "postalcode"
  },
  "geometry": {"coordinates":[-0.395861,54.240129],"type":"Point"}
}
