{
  "type": "Feature",
  "properties": {
    "iso:country":"GB",
    "wof:name":"G71 7RL",
    "wof:placetype":"postalcode"
},
  "geometry": {"coordinates":[-4.11165115372411,55.84032869116481],"type":"Point"}
}