{
  "type": "Feature",
  "properties": {
    "date:inception_lower": "2006-04-01",
    "date:inception_upper": "2006-04-01",
    "iso:country": "GB",
    "wof:name": "G71 7RL",
    "wof:placetype": "postalcode"
  },
  "geometry": {"coordinates":[-4.111651,55.840329],"type":"Point"}
}
