{
  "type": "Feature",
  "properties": {
    "date:inception_lower": "2018-07-01",
    "date:inception_upper": "2018-07-01",
    "iso:country": "GB",
    "wof:name": "BS2 0ES",
    "wof:placetype": "postalcode"
  },
  "geometry": {"coordinates":[-2.578927,51.451364],"type":"Point"}
}
