{
  "type": "Feature",
  "properties": {
    "iso:country":"GB",
    "wof:name":"OL3 7PU",
    "wof:placetype":"postalcode"
},
  "geometry": {"coordinates":[-2.01906038003876,53.53040662787426],"type":"Point"}
}