{
  "type": "Feature",
  "properties": {
    "iso:country": "GB",
    "wof:name": "OL3 7PU",
    "wof:placetype": "postalcode"
  },
  "geometry": {"coordinates":[-2.01906,53.530407],"type":"Point"}
}
