{
  "type": "Feature",
  "properties": {
    "date:inception_lower": "1994-05-01",
    "date:inception_upper": "1994-05-01",
    "iso:country": "GB",
    "wof:name": "DD10 9AU",
    "wof:placetype": "postalcode"
  },
  "geometry": {"coordinates":[-2.469324,56.718853],"type":"Point"}
}
