{
  "type": "Feature",
  "properties": {
    "date:inception_lower": "1980-01-01",
    "date:inception_upper": "1980-01-01",
    "iso:country": "GB",
    "wof:name": "HP10 8AL",
    "wof:placetype": "postalcode"
  },
  "geometry": {"coordinates":[-0.698666,51.644371],"type":"Point"}
}
