{
  "type": "Feature",
  "properties": {
    "iso:country":"GB",
    "wof:name":"HP10 8AL",
    "wof:placetype":"postalcode"
},
  "geometry": {"coordinates":[-0.69866653979722,51.6443706133233],"type":"Point"}
}