{
  "type": "Feature",
  "properties": {
    "iso:country": "GB",
    "wof:name": "HP10 8AL",
    "wof:placetype": "postalcode"
  },
  "geometry": {"coordinates":[-0.698666,51.644371],"type":"Point"}
}
