{
  "type": "Feature",
  "properties": {
    "iso:country": "GB",
    "wof:name": "G52 4FA",
    "wof:placetype": "postalcode"
  },
  "geometry": {"coordinates":[-4.3698,55.866115],"type":"Point"}
}
