{
  "type": "Feature",
  "properties": {
    "iso:country":"GB",
    "wof:name":"NR11 8HD",
    "wof:placetype":"postalcode"
},
  "geometry": {"coordinates":[1.39164910544901,52.8754702446119],"type":"Point"}
}