{
  "type": "Feature",
  "properties": {
    "iso:country": "GB",
    "wof:name": "NR11 8HD",
    "wof:placetype": "postalcode"
  },
  "geometry": {"coordinates":[1.391649,52.87547],"type":"Point"}
}
