{
  "type": "Feature",
  "properties": {
    "date:inception_lower":"1980-01-01",
    "date:inception_upper":"1980-01-31",
    "iso:country":"GB",
    "wof:name":"NR11 8HD",
    "wof:placetype":"postalcode"
},
  "geometry": {"coordinates":[1.391649,52.87547],"type":"Point"}
}