{
  "type": "Feature",
  "properties": {
    "iso:country": "GB",
    "wof:name": "WD6 9NB",
    "wof:placetype": "postalcode"
  },
  "geometry": {"coordinates":[-0.279031,51.655359],"type":"Point"}
}
