{
  "type": "Feature",
  "properties": {
    "iso:country":"GB",
    "wof:name":"DE4 5JR",
    "wof:placetype":"postalcode"
},
  "geometry": {"coordinates":[-1.52347769285462,53.11456540258007],"type":"Point"}
}