{
  "type": "Feature",
  "properties": {
    "date:inception_lower": "1980-01-01",
    "date:inception_upper": "1980-01-01",
    "iso:country": "GB",
    "wof:name": "DE4 5JR",
    "wof:placetype": "postalcode"
  },
  "geometry": {"coordinates":[-1.522845,53.114815],"type":"Point"}
}
