{
  "type": "Feature",
  "properties": {
    "iso:country": "GB",
    "wof:name": "B77 2RR",
    "wof:placetype": "postalcode"
  },
  "geometry": {"coordinates":[-1.672572,52.625802],"type":"Point"}
}
