{
  "type": "Feature",
  "properties": {
    "iso:country":"GB",
    "wof:name":"B77 2RR",
    "wof:placetype":"postalcode"
},
  "geometry": {"coordinates":[-1.67257243406447,52.6258023133506],"type":"Point"}
}