{
  "type": "Feature",
  "properties": {
    "iso:country":"GB",
    "wof:name":"NE16 4PL",
    "wof:placetype":"postalcode"
},
  "geometry": {"coordinates":[-1.67533886609165,54.93746746886573],"type":"Point"}
}