{
  "type": "Feature",
  "properties": {
    "iso:country":"GB",
    "wof:name":"B50 4AL",
    "wof:placetype":"postalcode"
},
  "geometry": {"coordinates":[-1.86110453161675,52.16654543503117],"type":"Point"}
}