{
  "type": "Feature",
  "properties": {
    "iso:country": "GB",
    "wof:name": "B50 4AL",
    "wof:placetype": "postalcode"
  },
  "geometry": {"coordinates":[-1.861256,52.16672],"type":"Point"}
}
