{
  "type": "Feature",
  "properties": {
    "date:inception_lower":"1980-01-01",
    "date:inception_upper":"1980-01-31",
    "iso:country":"GB",
    "wof:name":"B50 4AL",
    "wof:placetype":"postalcode"
},
  "geometry": {"coordinates":[-1.861256,52.16672],"type":"Point"}
}