{
  "type": "Feature",
  "properties": {
    "iso:country":"GB",
    "wof:name":"GU15 3RD",
    "wof:placetype":"postalcode"
},
  "geometry": {"coordinates":[-0.73579460324983,51.34024526409571],"type":"Point"}
}