{
  "type": "Feature",
  "properties": {
    "iso:country":"GB",
    "wof:name":"EH4 1HS",
    "wof:placetype":"postalcode"
},
  "geometry": {"coordinates":[-3.20874444846856,55.95911958618019],"type":"Point"}
}