{
  "type": "Feature",
  "properties": {
    "iso:country": "GB",
    "wof:name": "LE14 3ED",
    "wof:placetype": "postalcode"
  },
  "geometry": {"coordinates":[-1.012454,52.747362],"type":"Point"}
}
