{
  "type": "Feature",
  "properties": {
    "date:inception_lower": "1980-01-01",
    "date:inception_upper": "1980-01-01",
    "iso:country": "GB",
    "wof:name": "LE14 3ED",
    "wof:placetype": "postalcode"
  },
  "geometry": {"coordinates":[-1.012454,52.747362],"type":"Point"}
}
