{
  "type": "Feature",
  "properties": {
    "iso:country":"GB",
    "wof:name":"LE14 3ED",
    "wof:placetype":"postalcode"
},
  "geometry": {"coordinates":[-1.01245413609733,52.74736200429658],"type":"Point"}
}