{
  "type": "Feature",
  "properties": {
    "iso:country": "GB",
    "wof:name": "WD3 4HF",
    "wof:placetype": "postalcode"
  },
  "geometry": {"coordinates":[-0.473629,51.648001],"type":"Point"}
}
