{
  "type": "Feature",
  "properties": {
    "iso:country":"GB",
    "wof:name":"WD3 4HF",
    "wof:placetype":"postalcode"
},
  "geometry": {"coordinates":[-0.47362907884027,51.64800067270361],"type":"Point"}
}