{
  "type": "Feature",
  "properties": {
    "iso:country": "GB",
    "wof:name": "TR13 0QB",
    "wof:placetype": "postalcode"
  },
  "geometry": {"coordinates":[-5.246487,50.08802],"type":"Point"}
}
