{
  "type": "Feature",
  "properties": {
    "date:inception_lower": "1986-04-01",
    "date:inception_upper": "1986-04-01",
    "iso:country": "GB",
    "wof:name": "TR13 0QB",
    "wof:placetype": "postalcode"
  },
  "geometry": {"coordinates":[-5.246487,50.08802],"type":"Point"}
}
