{
  "type": "Feature",
  "properties": {
    "iso:country":"GB",
    "wof:name":"RH4 3HN",
    "wof:placetype":"postalcode"
},
  "geometry": {"coordinates":[-0.3381137591819,51.22913854630232],"type":"Point"}
}