{
  "type": "Feature",
  "properties": {
    "date:inception_lower": "1995-12-01",
    "date:inception_upper": "1995-12-01",
    "iso:country": "GB",
    "wof:name": "RH4 3HN",
    "wof:placetype": "postalcode"
  },
  "geometry": {"coordinates":[-0.338091,51.229136],"type":"Point"}
}
