{
  "type": "Feature",
  "properties": {
    "date:inception_lower": "1995-07-01",
    "date:inception_upper": "1995-07-01",
    "iso:country": "GB",
    "wof:name": "RH15 8TA",
    "wof:placetype": "postalcode"
  },
  "geometry": {"coordinates":[-0.132523,50.957594],"type":"Point"}
}
