{
  "type": "Feature",
  "properties": {
    "iso:country":"GB",
    "wof:name":"SN2 5HP",
    "wof:placetype":"postalcode"
},
  "geometry": {"coordinates":[-1.77907490180403,51.59566067859664],"type":"Point"}
}