{
  "type": "Feature",
  "properties": {
    "date:inception_lower": "1980-01-01",
    "date:inception_upper": "1980-01-01",
    "iso:country": "GB",
    "wof:name": "CT5 1AQ",
    "wof:placetype": "postalcode"
  },
  "geometry": {"coordinates":[1.024809,51.361331],"type":"Point"}
}
