{
  "type": "Feature",
  "properties": {
    "date:inception_lower":"1995-12-01",
    "date:inception_upper":"1995-12-31",
    "iso:country":"GB",
    "wof:name":"S61 1BS",
    "wof:placetype":"postalcode"
},
  "geometry": {"coordinates":[-1.375152,53.428329],"type":"Point"}
}