{
  "type": "Feature",
  "properties": {
    "iso:country":"GB",
    "wof:name":"S61 1BS",
    "wof:placetype":"postalcode"
},
  "geometry": {"coordinates":[-1.37515212766493,53.42832949178749],"type":"Point"}
}