{
  "type": "Feature",
  "properties": {
    "iso:country":"GB",
    "wof:name":"HA8 8FX",
    "wof:placetype":"postalcode"
},
  "geometry": {"coordinates":[-0.26980356806389,51.63141637721505],"type":"Point"}
}