{
  "type": "Feature",
  "properties": {
    "date:inception_lower": "2023-12-01",
    "date:inception_upper": "2023-12-01",
    "iso:country": "GB",
    "wof:name": "TF1 6BU",
    "wof:placetype": "postalcode"
  },
  "geometry": {"coordinates":[-2.520711,52.717152],"type":"Point"}
}
