{
  "type": "Feature",
  "properties": {
    "iso:country":"GB",
    "wof:name":"L13 5XY",
    "wof:placetype":"postalcode"
},
  "geometry": {"coordinates":[-2.91084026929211,53.41482005353853],"type":"Point"}
}