{
  "type": "Feature",
  "properties": {
    "iso:country":"GB",
    "wof:name":"LA2 7DY",
    "wof:placetype":"postalcode"
},
  "geometry": {"coordinates":[-2.53653636697429,54.11960935282334],"type":"Point"}
}