{
  "type": "Feature",
  "properties": {
    "date:inception_lower": "2017-01-01",
    "date:inception_upper": "2017-01-01",
    "iso:country": "GB",
    "wof:name": "KY13 9SF",
    "wof:placetype": "postalcode"
  },
  "geometry": {"coordinates":[-3.381948,56.237801],"type":"Point"}
}
