{
  "type": "Feature",
  "properties": {
    "iso:country": "GB",
    "wof:name": "KY13 9SF",
    "wof:placetype": "postalcode"
  },
  "geometry": {"coordinates":[-3.38193,56.237729],"type":"Point"}
}
