{
  "type": "Feature",
  "properties": {
    "date:inception_lower": "1980-01-01",
    "date:inception_upper": "1980-01-01",
    "iso:country": "GB",
    "wof:name": "NR20 4PN",
    "wof:placetype": "postalcode"
  },
  "geometry": {"coordinates":[0.981434,52.718933],"type":"Point"}
}
