{
  "type": "Feature",
  "properties": {
    "iso:country":"GB",
    "wof:name":"SK4 4HD",
    "wof:placetype":"postalcode"
},
  "geometry": {"coordinates":[-2.18853965392353,53.41929663155626],"type":"Point"}
}