{
  "type": "Feature",
  "properties": {
    "iso:country": "GB",
    "wof:name": "SK4 4HD",
    "wof:placetype": "postalcode"
  },
  "geometry": {"coordinates":[-2.18854,53.419297],"type":"Point"}
}
