{
  "type": "Feature",
  "properties": {
    "date:inception_lower": "1990-02-01",
    "date:inception_upper": "1990-02-01",
    "iso:country": "GB",
    "wof:name": "SK4 4HD",
    "wof:placetype": "postalcode"
  },
  "geometry": {"coordinates":[-2.18854,53.419297],"type":"Point"}
}
