{
  "type": "Feature",
  "properties": {
    "iso:country":"GB",
    "wof:name":"LL57 4SW",
    "wof:placetype":"postalcode"
},
  "geometry": {"coordinates":[-4.14301564963632,53.21518507089284],"type":"Point"}
}