{
  "type": "Feature",
  "properties": {
    "iso:country":"GB",
    "wof:name":"DY1 3TY",
    "wof:placetype":"postalcode"
},
  "geometry": {"coordinates":[-2.11116815172693,52.52692709135809],"type":"Point"}
}