{
  "type": "Feature",
  "properties": {
    "date:inception_lower":"1980-01-01",
    "date:inception_upper":"1980-01-31",
    "iso:country":"GB",
    "wof:name":"DY1 3TY",
    "wof:placetype":"postalcode"
},
  "geometry": {"coordinates":[-2.111168,52.526927],"type":"Point"}
}