{
  "type": "Feature",
  "properties": {
    "date:inception_lower": "1980-01-01",
    "date:inception_upper": "1980-01-01",
    "iso:country": "GB",
    "wof:name": "ST18 0SQ",
    "wof:placetype": "postalcode"
  },
  "geometry": {"coordinates":[-2.001515,52.802261],"type":"Point"}
}
