{
  "type": "Feature",
  "properties": {
    "iso:country": "GB",
    "wof:name": "ST18 0SQ",
    "wof:placetype": "postalcode"
  },
  "geometry": {"coordinates":[-2.001515,52.802261],"type":"Point"}
}
