{
  "type": "Feature",
  "properties": {
    "iso:country":"GB",
    "wof:name":"WD17 4QT",
    "wof:placetype":"postalcode"
},
  "geometry": {"coordinates":[-0.40239033632424,51.66509112869775],"type":"Point"}
}