{
  "type": "Feature",
  "properties": {
    "iso:country": "GB",
    "wof:name": "WD17 4QT",
    "wof:placetype": "postalcode"
  },
  "geometry": {"coordinates":[-0.40239,51.665091],"type":"Point"}
}
