{
  "type": "Feature",
  "properties": {
    "date:inception_lower":"1980-01-01",
    "date:inception_upper":"1980-01-31",
    "iso:country":"GB",
    "wof:name":"WR5 2PR",
    "wof:placetype":"postalcode"
},
  "geometry": {"coordinates":[-2.187418,52.163052],"type":"Point"}
}