{
  "type": "Feature",
  "properties": {
    "iso:country":"GB",
    "wof:name":"WR5 2PR",
    "wof:placetype":"postalcode"
},
  "geometry": {"coordinates":[-2.18741764990741,52.16305223571363],"type":"Point"}
}