{
  "type": "Feature",
  "properties": {
    "iso:country": "GB",
    "wof:name": "WR5 2PR",
    "wof:placetype": "postalcode"
  },
  "geometry": {"coordinates":[-2.187418,52.163052],"type":"Point"}
}
