{
  "type": "Feature",
  "properties": {
    "iso:country":"GB",
    "wof:name":"CV7 9QL",
    "wof:placetype":"postalcode"
},
  "geometry": {"coordinates":[-1.41201558597087,52.46598830128261],"type":"Point"}
}