{
  "type": "Feature",
  "properties": {
    "date:inception_lower": "1990-02-01",
    "date:inception_upper": "1990-02-01",
    "iso:country": "GB",
    "wof:name": "CV7 9QL",
    "wof:placetype": "postalcode"
  },
  "geometry": {"coordinates":[-1.412016,52.465988],"type":"Point"}
}
