{
  "type": "Feature",
  "properties": {
    "iso:country":"GB",
    "wof:name":"EC3R 7ND",
    "wof:placetype":"postalcode"
},
  "geometry": {"coordinates":[-0.08017498641723,51.51072085065572],"type":"Point"}
}