{
  "type": "Feature",
  "properties": {
    "iso:country":"GB",
    "wof:name":"SL8 5ER",
    "wof:placetype":"postalcode"
},
  "geometry": {"coordinates":[-0.70118279044626,51.57143881559701],"type":"Point"}
}