{
  "type": "Feature",
  "properties": {
    "iso:country": "GB",
    "wof:name": "SL8 5ER",
    "wof:placetype": "postalcode"
  },
  "geometry": {"coordinates":[-0.701183,51.571439],"type":"Point"}
}
