{
  "type": "Feature",
  "properties": {
    "date:inception_lower": "1992-01-01",
    "date:inception_upper": "1992-01-01",
    "iso:country": "GB",
    "wof:name": "E14 9WU",
    "wof:placetype": "postalcode"
  },
  "geometry": {"coordinates":[-0.021143,51.491152],"type":"Point"}
}
