{
  "type": "Feature",
  "properties": {
    "iso:country":"GB",
    "wof:name":"E14 9WU",
    "wof:placetype":"postalcode"
},
  "geometry": {"coordinates":[-0.02114347910073,51.49115183996923],"type":"Point"}
}