{
  "type": "Feature",
  "properties": {
    "iso:country":"GB",
    "wof:name":"W5 5PZ",
    "wof:placetype":"postalcode"
},
  "geometry": {"coordinates":[-0.30032160660539,51.506797885217],"type":"Point"}
}