{
  "type": "Feature",
  "properties": {
    "date:inception_lower": "2021-03-01",
    "date:inception_upper": "2021-03-01",
    "iso:country": "GB",
    "wof:name": "YO25 1DF",
    "wof:placetype": "postalcode"
  },
  "geometry": {"coordinates":[-0.459166,53.999409],"type":"Point"}
}
