{
  "type": "Feature",
  "properties": {
    "iso:country":"GB",
    "wof:name":"CM1 2NX",
    "wof:placetype":"postalcode"
},
  "geometry": {"coordinates":[0.4448706934056,51.73842242233404],"type":"Point"}
}