{
  "type": "Feature",
  "properties": {
    "iso:country":"GB",
    "wof:name":"CF44 0TX",
    "wof:placetype":"postalcode"
},
  "geometry": {"coordinates":[-3.51893510418858,51.77075734188902],"type":"Point"}
}