{
  "type": "Feature",
  "properties": {
    "date:inception_lower":"1980-01-01",
    "date:inception_upper":"1980-01-31",
    "iso:country":"GB",
    "wof:name":"CF44 0TX",
    "wof:placetype":"postalcode"
},
  "geometry": {"coordinates":[-3.518935,51.770757],"type":"Point"}
}