{
  "type": "Feature",
  "properties": {
    "iso:country":"GB",
    "wof:name":"B28 9NB",
    "wof:placetype":"postalcode"
},
  "geometry": {"coordinates":[-1.83009427535494,52.42376993590383],"type":"Point"}
}