{
  "type": "Feature",
  "properties": {
    "iso:country":"GB",
    "wof:name":"SW19 1YG",
    "wof:placetype":"postalcode"
},
  "geometry": {"coordinates":[-0.18352913794181,51.42089514506318],"type":"Point"}
}