{
  "type": "Feature",
  "properties": {
    "date:inception_lower":"2000-12-01",
    "date:inception_upper":"2000-12-31",
    "iso:country":"GB",
    "wof:name":"SW19 1YG",
    "wof:placetype":"postalcode"
},
  "geometry": {"coordinates":[-0.183505,51.420877],"type":"Point"}
}