{
  "type": "Feature",
  "properties": {
    "iso:country":"GB",
    "wof:name":"OX7 6PT",
    "wof:placetype":"postalcode"
},
  "geometry": {"coordinates":[-1.60243027423907,51.89455562582269],"type":"Point"}
}