{
  "type": "Feature",
  "properties": {
    "iso:country": "GB",
    "wof:name": "OX7 6PT",
    "wof:placetype": "postalcode"
  },
  "geometry": {"coordinates":[-1.60243,51.894556],"type":"Point"}
}
