{
  "type": "Feature",
  "properties": {
    "date:inception_lower":"1980-01-01",
    "date:inception_upper":"1980-01-31",
    "iso:country":"GB",
    "wof:name":"OX7 6PT",
    "wof:placetype":"postalcode"
},
  "geometry": {"coordinates":[-1.60243,51.894556],"type":"Point"}
}