{
  "type": "Feature",
  "properties": {
    "date:inception_lower": "1992-08-01",
    "date:inception_upper": "1992-08-01",
    "iso:country": "GB",
    "wof:name": "DE21 6LG",
    "wof:placetype": "postalcode"
  },
  "geometry": {"coordinates":[-1.428237,52.929354],"type":"Point"}
}
