{
  "type": "Feature",
  "properties": {
    "iso:country": "GB",
    "wof:name": "DE21 6LG",
    "wof:placetype": "postalcode"
  },
  "geometry": {"coordinates":[-1.428237,52.929354],"type":"Point"}
}
