{
  "type": "Feature",
  "properties": {
    "iso:country":"GB",
    "wof:name":"WV3 9SA",
    "wof:placetype":"postalcode"
},
  "geometry": {"coordinates":[-2.14242424412474,52.58387120833262],"type":"Point"}
}