{
  "type": "Feature",
  "properties": {
    "date:inception_lower":"1986-07-01",
    "date:inception_upper":"1986-07-31",
    "iso:country":"GB",
    "wof:name":"WV3 9SA",
    "wof:placetype":"postalcode"
},
  "geometry": {"coordinates":[-2.142424,52.583871],"type":"Point"}
}