{
  "type": "Feature",
  "properties": {
    "iso:country":"GB",
    "wof:name":"S60 2QW",
    "wof:placetype":"postalcode"
},
  "geometry": {"coordinates":[-1.34967709428617,53.4250655038629],"type":"Point"}
}