{
  "type": "Feature",
  "properties": {
    "iso:country":"GB",
    "wof:name":"SP11 0JN",
    "wof:placetype":"postalcode"
},
  "geometry": {"coordinates":[-1.4866455434648,51.29045193968962],"type":"Point"}
}