{
  "type": "Feature",
  "properties": {
    "iso:country": "GB",
    "wof:name": "BB12 6PD",
    "wof:placetype": "postalcode"
  },
  "geometry": {"coordinates":[-2.291192,53.788649],"type":"Point"}
}
