{
  "type": "Feature",
  "properties": {
    "iso:country":"GB",
    "wof:name":"KA3 1QG",
    "wof:placetype":"postalcode"
},
  "geometry": {"coordinates":[-4.50538270844886,55.62425748225737],"type":"Point"}
}