{
  "type": "Feature",
  "properties": {
    "iso:country":"GB",
    "wof:name":"WA10 4RN",
    "wof:placetype":"postalcode"
},
  "geometry": {"coordinates":[-2.7690713338989,53.46089596584424],"type":"Point"}
}