{
  "type": "Feature",
  "properties": {
    "iso:country":"GB",
    "wof:name":"TN20 6UL",
    "wof:placetype":"postalcode"
},
  "geometry": {"coordinates":[0.27053332324576,51.02447966055072],"type":"Point"}
}