{
  "type": "Feature",
  "properties": {
    "iso:country":"GB",
    "wof:name":"BR7 5QP",
    "wof:placetype":"postalcode"
},
  "geometry": {"coordinates":[0.06324207909432,51.41707125226984],"type":"Point"}
}