{
  "type": "Feature",
  "properties": {
    "iso:country":"GB",
    "wof:name":"PE4 6RT",
    "wof:placetype":"postalcode"
},
  "geometry": {"coordinates":[-0.26872888538171,52.61536859489185],"type":"Point"}
}