{
  "type": "Feature",
  "properties": {
    "iso:country": "GB",
    "wof:name": "S65 3LT",
    "wof:placetype": "postalcode"
  },
  "geometry": {"coordinates":[-1.319304,53.44042],"type":"Point"}
}
