{
  "type": "Feature",
  "properties": {
    "iso:country": "GB",
    "wof:name": "DN15 9PL",
    "wof:placetype": "postalcode"
  },
  "geometry": {"coordinates":[-0.593282,53.686339],"type":"Point"}
}
