{
  "type": "Feature",
  "properties": {
    "iso:country":"GB",
    "wof:name":"DN15 9PL",
    "wof:placetype":"postalcode"
},
  "geometry": {"coordinates":[-0.59328190146191,53.68633895577971],"type":"Point"}
}