{
  "type": "Feature",
  "properties": {
    "date:inception_lower":"1988-03-01",
    "date:inception_upper":"1988-03-31",
    "iso:country":"GB",
    "wof:name":"DN15 9PL",
    "wof:placetype":"postalcode"
},
  "geometry": {"coordinates":[-0.593282,53.686339],"type":"Point"}
}