{
  "type": "Feature",
  "properties": {
    "iso:country":"GB",
    "wof:name":"CO7 6XA",
    "wof:placetype":"postalcode"
},
  "geometry": {"coordinates":[1.05634049221074,51.97507788337089],"type":"Point"}
}