{
  "type": "Feature",
  "properties": {
    "iso:country":"GB",
    "wof:name":"YO30 6HA",
    "wof:placetype":"postalcode"
},
  "geometry": {"coordinates":[-1.08525591581172,53.97612301553524],"type":"Point"}
}