{
  "type": "Feature",
  "properties": {
    "iso:country": "GB",
    "wof:name": "CA23 3EU",
    "wof:placetype": "postalcode"
  },
  "geometry": {"coordinates":[-3.500499,54.513014],"type":"Point"}
}
