{
  "type": "Feature",
  "properties": {
    "date:inception_lower": "1980-01-01",
    "date:inception_upper": "1980-01-01",
    "iso:country": "GB",
    "wof:name": "CA23 3EU",
    "wof:placetype": "postalcode"
  },
  "geometry": {"coordinates":[-3.500499,54.513014],"type":"Point"}
}
