{
  "type": "Feature",
  "properties": {
    "iso:country":"GB",
    "wof:name":"PE27 4UE",
    "wof:placetype":"postalcode"
},
  "geometry": {"coordinates":[-0.02992980123465,52.32633311880348],"type":"Point"}
}