{
  "type": "Feature",
  "properties": {
    "iso:country": "GB",
    "wof:name": "PE27 4UE",
    "wof:placetype": "postalcode"
  },
  "geometry": {"coordinates":[-0.02993,52.326333],"type":"Point"}
}
