{
  "type": "Feature",
  "properties": {
    "date:inception_lower":"2000-06-01",
    "date:inception_upper":"2000-06-30",
    "iso:country":"GB",
    "wof:name":"PE27 4UE",
    "wof:placetype":"postalcode"
},
  "geometry": {"coordinates":[-0.02993,52.326333],"type":"Point"}
}