{
  "type": "Feature",
  "properties": {
    "iso:country":"GB",
    "wof:name":"ML4 1JU",
    "wof:placetype":"postalcode"
},
  "geometry": {"coordinates":[-4.0236479005679,55.82833671362677],"type":"Point"}
}