{
  "type": "Feature",
  "properties": {
    "iso:country":"GB",
    "wof:name":"RH14 9NL",
    "wof:placetype":"postalcode"
},
  "geometry": {"coordinates":[-0.45512514674616,51.0249429748714],"type":"Point"}
}