{
  "type": "Feature",
  "properties": {
    "date:inception_lower":"1980-01-01",
    "date:inception_upper":"1980-01-31",
    "iso:country":"GB",
    "wof:name":"LL19 7ES",
    "wof:placetype":"postalcode"
},
  "geometry": {"coordinates":[-3.407541,53.337066],"type":"Point"}
}