{
  "type": "Feature",
  "properties": {
    "date:inception_lower": "1981-06-01",
    "date:inception_upper": "1981-06-01",
    "iso:country": "GB",
    "wof:name": "YO18 8BL",
    "wof:placetype": "postalcode"
  },
  "geometry": {"coordinates":[-0.781447,54.244956],"type":"Point"}
}
