{
  "type": "Feature",
  "properties": {
    "iso:country": "GB",
    "wof:name": "M35 9NA",
    "wof:placetype": "postalcode"
  },
  "geometry": {"coordinates":[-2.143197,53.506368],"type":"Point"}
}
