{
  "type": "Feature",
  "properties": {
    "date:inception_lower":"1992-08-01",
    "date:inception_upper":"1992-08-31",
    "iso:country":"GB",
    "wof:name":"M35 9NA",
    "wof:placetype":"postalcode"
},
  "geometry": {"coordinates":[-2.143197,53.506368],"type":"Point"}
}