{
  "type": "Feature",
  "properties": {
    "iso:country":"GB",
    "wof:name":"M35 9NA",
    "wof:placetype":"postalcode"
},
  "geometry": {"coordinates":[-2.14319661086196,53.50636808830102],"type":"Point"}
}