{
  "type": "Feature",
  "properties": {
    "iso:country":"GB",
    "wof:name":"W1U 6HJ",
    "wof:placetype":"postalcode"
},
  "geometry": {"coordinates":[-0.15832347439267,51.51939281202482],"type":"Point"}
}