{
  "type": "Feature",
  "properties": {
    "iso:country":"GB",
    "wof:name":"WN7 2AN",
    "wof:placetype":"postalcode"
},
  "geometry": {"coordinates":[-2.50179122965588,53.49296885198046],"type":"Point"}
}