{
  "type": "Feature",
  "properties": {
    "date:inception_lower": "1980-01-01",
    "date:inception_upper": "1980-01-01",
    "iso:country": "GB",
    "wof:name": "DH9 9RP",
    "wof:placetype": "postalcode"
  },
  "geometry": {"coordinates":[-1.727773,54.885484],"type":"Point"}
}
