{
  "type": "Feature",
  "properties": {
    "date:inception_lower": "1980-01-01",
    "date:inception_upper": "1980-01-01",
    "iso:country": "GB",
    "wof:name": "BL0 9EP",
    "wof:placetype": "postalcode"
  },
  "geometry": {"coordinates":[-2.323622,53.649892],"type":"Point"}
}
