{
  "type": "Feature",
  "properties": {
    "iso:country":"GB",
    "wof:name":"PL19 8DP",
    "wof:placetype":"postalcode"
},
  "geometry": {"coordinates":[-4.14803457664078,50.54079569200567],"type":"Point"}
}