{
  "type": "Feature",
  "properties": {
    "iso:country": "GB",
    "wof:name": "PL19 8DP",
    "wof:placetype": "postalcode"
  },
  "geometry": {"coordinates":[-4.148035,50.540796],"type":"Point"}
}
