{
  "type": "Feature",
  "properties": {
    "date:inception_lower": "2013-04-01",
    "date:inception_upper": "2013-04-01",
    "iso:country": "GB",
    "wof:name": "PE21 7TZ",
    "wof:placetype": "postalcode"
  },
  "geometry": {"coordinates":[-0.054969,52.977098],"type":"Point"}
}
