{
  "type": "Feature",
  "properties": {
    "iso:country":"GB",
    "wof:name":"ST14 7DG",
    "wof:placetype":"postalcode"
},
  "geometry": {"coordinates":[-1.88117156720923,52.90798032409477],"type":"Point"}
}