{
  "type": "Feature",
  "properties": {
    "date:inception_lower":"1980-01-01",
    "date:inception_upper":"1980-01-31",
    "iso:country":"GB",
    "wof:name":"CH3 9BQ",
    "wof:placetype":"postalcode"
},
  "geometry": {"coordinates":[-2.730737,53.148005],"type":"Point"}
}