{
  "type": "Feature",
  "properties": {
    "iso:country":"GB",
    "wof:name":"CH3 9BQ",
    "wof:placetype":"postalcode"
},
  "geometry": {"coordinates":[-2.73075255007813,53.14798988057839],"type":"Point"}
}