{
  "type": "Feature",
  "properties": {
    "iso:country":"GB",
    "wof:name":"W9 3QP",
    "wof:placetype":"postalcode"
},
  "geometry": {"coordinates":[-0.20082455177095,51.52428785433008],"type":"Point"}
}