{
  "type": "Feature",
  "properties": {
    "iso:country": "GB",
    "wof:name": "M29 8SE",
    "wof:placetype": "postalcode"
  },
  "geometry": {"coordinates":[-2.435378,53.511924],"type":"Point"}
}
