{
  "type": "Feature",
  "properties": {
    "date:inception_lower": "2018-12-01",
    "date:inception_upper": "2018-12-01",
    "iso:country": "GB",
    "wof:name": "M29 8SE",
    "wof:placetype": "postalcode"
  },
  "geometry": {"coordinates":[-2.435845,53.511923],"type":"Point"}
}
