{
  "type": "Feature",
  "properties": {
    "iso:country": "GB",
    "wof:name": "YO8 8NS",
    "wof:placetype": "postalcode"
  },
  "geometry": {"coordinates":[-0.979878,53.728708],"type":"Point"}
}
