{
  "type": "Feature",
  "properties": {
    "iso:country":"GB",
    "wof:name":"ME16 9HJ",
    "wof:placetype":"postalcode"
},
  "geometry": {"coordinates":[0.47297667414812,51.26805805354412],"type":"Point"}
}