{
  "type": "Feature",
  "properties": {
    "iso:country": "GB",
    "wof:name": "SK7 2HF",
    "wof:placetype": "postalcode"
  },
  "geometry": {"coordinates":[-2.154165,53.362979],"type":"Point"}
}
