{
  "type": "Feature",
  "properties": {
    "iso:country": "GB",
    "wof:name": "NP20 1GG",
    "wof:placetype": "postalcode"
  },
  "geometry": {"coordinates":[-2.997208,51.588078],"type":"Point"}
}
