{
  "type": "Feature",
  "properties": {
    "iso:country":"GB",
    "wof:name":"NP20 1GG",
    "wof:placetype":"postalcode"
},
  "geometry": {"coordinates":[-2.99720793248261,51.58807837769828],"type":"Point"}
}