{
  "type": "Feature",
  "properties": {
    "iso:country":"GB",
    "wof:name":"SO41 6BS",
    "wof:placetype":"postalcode"
},
  "geometry": {"coordinates":[-1.59280550276743,50.78443579907724],"type":"Point"}
}