{
  "type": "Feature",
  "properties": {
    "date:inception_lower": "1986-01-01",
    "date:inception_upper": "1986-01-01",
    "iso:country": "GB",
    "wof:name": "SO41 6BS",
    "wof:placetype": "postalcode"
  },
  "geometry": {"coordinates":[-1.592826,50.784409],"type":"Point"}
}
