{
  "type": "Feature",
  "properties": {
    "iso:country": "GB",
    "wof:name": "SO41 6BS",
    "wof:placetype": "postalcode"
  },
  "geometry": {"coordinates":[-1.592826,50.784409],"type":"Point"}
}
