{
  "type": "Feature",
  "properties": {
    "date:inception_lower": "1980-01-01",
    "date:inception_upper": "1980-01-01",
    "iso:country": "GB",
    "wof:name": "BB8 9ND",
    "wof:placetype": "postalcode"
  },
  "geometry": {"coordinates":[-2.18051,53.855552],"type":"Point"}
}
