{
  "type": "Feature",
  "properties": {
    "iso:country":"GB",
    "wof:name":"SY2 5JP",
    "wof:placetype":"postalcode"
},
  "geometry": {"coordinates":[-2.72662937479649,52.71129774017831],"type":"Point"}
}