{
  "type": "Feature",
  "properties": {
    "iso:country":"GB",
    "wof:name":"W1H 7NB",
    "wof:placetype":"postalcode"
},
  "geometry": {"coordinates":[-0.16093498744881,51.51467676591461],"type":"Point"}
}