{
  "type": "Feature",
  "properties": {
    "iso:country":"GB",
    "wof:name":"WN6 0SA",
    "wof:placetype":"postalcode"
},
  "geometry": {"coordinates":[-2.688439436341,53.58971754540382],"type":"Point"}
}