{
  "type": "Feature",
  "properties": {
    "iso:country": "GB",
    "wof:name": "YO42 2DP",
    "wof:placetype": "postalcode"
  },
  "geometry": {"coordinates":[-0.78426,53.9321],"type":"Point"}
}
