{
  "type": "Feature",
  "properties": {
    "iso:country":"GB",
    "wof:name":"SS11 7PB",
    "wof:placetype":"postalcode"
},
  "geometry": {"coordinates":[0.50990597649182,51.6379641832558],"type":"Point"}
}