{
  "type": "Feature",
  "properties": {
    "iso:country": "GB",
    "wof:name": "DE55 7LR",
    "wof:placetype": "postalcode"
  },
  "geometry": {"coordinates":[-1.445694,53.082452],"type":"Point"}
}
