{
  "type": "Feature",
  "properties": {
    "iso:country":"GB",
    "wof:name":"DE55 7LR",
    "wof:placetype":"postalcode"
},
  "geometry": {"coordinates":[-1.44569377434639,53.08245225269066],"type":"Point"}
}