{
  "type": "Feature",
  "properties": {
    "iso:country":"GB",
    "wof:name":"TQ7 4LP",
    "wof:placetype":"postalcode"
},
  "geometry": {"coordinates":[-3.83629912763209,50.31349283861917],"type":"Point"}
}