{
  "type": "Feature",
  "properties": {
    "iso:country":"GB",
    "wof:name":"GL14 2PD",
    "wof:placetype":"postalcode"
},
  "geometry": {"coordinates":[-2.50675171638863,51.82943495138089],"type":"Point"}
}