{
  "type": "Feature",
  "properties": {
    "iso:country": "GB",
    "wof:name": "GL14 2PD",
    "wof:placetype": "postalcode"
  },
  "geometry": {"coordinates":[-2.506752,51.829435],"type":"Point"}
}
