{
  "type": "Feature",
  "properties": {
    "iso:country": "GB",
    "wof:name": "LL68 9TH",
    "wof:placetype": "postalcode"
  },
  "geometry": {"coordinates":[-4.352066,53.403788],"type":"Point"}
}
