{
  "type": "Feature",
  "properties": {
    "iso:country":"GB",
    "wof:name":"LL68 9TH",
    "wof:placetype":"postalcode"
},
  "geometry": {"coordinates":[-4.35206629617129,53.40378849692628],"type":"Point"}
}