{
  "type": "Feature",
  "properties": {
    "iso:country": "GB",
    "wof:name": "KT20 6XL",
    "wof:placetype": "postalcode"
  },
  "geometry": {"coordinates":[-0.199827,51.262156],"type":"Point"}
}
