{
  "type": "Feature",
  "properties": {
    "iso:country":"GB",
    "wof:name":"KT20 6XL",
    "wof:placetype":"postalcode"
},
  "geometry": {"coordinates":[-0.1998272155077,51.26215604671241],"type":"Point"}
}