{
  "type": "Feature",
  "properties": {
    "date:inception_lower": "2009-06-01",
    "date:inception_upper": "2009-06-01",
    "iso:country": "GB",
    "wof:name": "DH1 5FA",
    "wof:placetype": "postalcode"
  },
  "geometry": {"coordinates":[-1.577303,54.808004],"type":"Point"}
}
