{
  "type": "Feature",
  "properties": {
    "iso:country":"GB",
    "wof:name":"DH1 5FA",
    "wof:placetype":"postalcode"
},
  "geometry": {"coordinates":[-1.57730261355739,54.80800445221796],"type":"Point"}
}