{
  "type": "Feature",
  "properties": {
    "iso:country":"GB",
    "wof:name":"M20 2TX",
    "wof:placetype":"postalcode"
},
  "geometry": {"coordinates":[-2.24117488943616,53.41969620088573],"type":"Point"}
}