{
  "type": "Feature",
  "properties": {
    "iso:country":"GB",
    "wof:name":"W3 9RH",
    "wof:placetype":"postalcode"
},
  "geometry": {"coordinates":[-0.28064304419182,51.50819263890373],"type":"Point"}
}