{
  "type": "Feature",
  "properties": {
    "iso:country": "GB",
    "wof:name": "W3 9RH",
    "wof:placetype": "postalcode"
  },
  "geometry": {"coordinates":[-0.280643,51.508193],"type":"Point"}
}
