{
  "type": "Feature",
  "properties": {
    "iso:country":"GB",
    "wof:name":"BL6 4EY",
    "wof:placetype":"postalcode"
},
  "geometry": {"coordinates":[-2.50693670112379,53.56541212814975],"type":"Point"}
}