{
  "type": "Feature",
  "properties": {
    "iso:country":"GB",
    "wof:name":"HA4 6RU",
    "wof:placetype":"postalcode"
},
  "geometry": {"coordinates":[-0.40306253248519,51.5545874882257],"type":"Point"}
}