{
  "type": "Feature",
  "properties": {
    "iso:country":"GB",
    "wof:name":"ML1 2SF",
    "wof:placetype":"postalcode"
},
  "geometry": {"coordinates":[-3.99468593529615,55.77626310570752],"type":"Point"}
}