{
  "type": "Feature",
  "properties": {
    "date:inception_lower": "1989-07-01",
    "date:inception_upper": "1989-07-01",
    "iso:country": "GB",
    "wof:name": "ML1 2SF",
    "wof:placetype": "postalcode"
  },
  "geometry": {"coordinates":[-3.994686,55.776263],"type":"Point"}
}
