{
  "type": "Feature",
  "properties": {
    "date:inception_lower":"1980-01-01",
    "date:inception_upper":"1980-01-31",
    "iso:country":"GB",
    "wof:name":"NE29 8DS",
    "wof:placetype":"postalcode"
},
  "geometry": {"coordinates":[-1.484214,55.024298],"type":"Point"}
}