{
  "type": "Feature",
  "properties": {
    "iso:country":"GB",
    "wof:name":"NE29 8DS",
    "wof:placetype":"postalcode"
},
  "geometry": {"coordinates":[-1.48421450653682,55.02429795197394],"type":"Point"}
}