{
  "type": "Feature",
  "properties": {
    "date:inception_lower": "1980-01-01",
    "date:inception_upper": "1980-01-01",
    "iso:country": "GB",
    "wof:name": "BN25 1TJ",
    "wof:placetype": "postalcode"
  },
  "geometry": {"coordinates":[0.11025,50.772282],"type":"Point"}
}
