{
  "type": "Feature",
  "properties": {
    "iso:country": "GB",
    "wof:name": "KY11 4QT",
    "wof:placetype": "postalcode"
  },
  "geometry": {"coordinates":[-3.432171,56.06069],"type":"Point"}
}
