{
  "type": "Feature",
  "properties": {
    "iso:country":"GB",
    "wof:name":"HP19 9GU",
    "wof:placetype":"postalcode"
},
  "geometry": {"coordinates":[-0.83488296963043,51.82908423415834],"type":"Point"}
}