{
  "type": "Feature",
  "properties": {
    "iso:country":"GB",
    "wof:name":"ST3 3AN",
    "wof:placetype":"postalcode"
},
  "geometry": {"coordinates":[-2.15323834310286,52.97875770775338],"type":"Point"}
}