{
  "type": "Feature",
  "properties": {
    "iso:country": "GB",
    "wof:name": "SY22 6EP",
    "wof:placetype": "postalcode"
  },
  "geometry": {"coordinates":[-3.089879,52.779553],"type":"Point"}
}
