{
  "type": "Feature",
  "properties": {
    "iso:country":"GB",
    "wof:name":"BR8 8HX",
    "wof:placetype":"postalcode"
},
  "geometry": {"coordinates":[0.16851224732592,51.39168064548542],"type":"Point"}
}