{
  "type": "Feature",
  "properties": {
    "iso:country": "GB",
    "wof:name": "BR8 8HX",
    "wof:placetype": "postalcode"
  },
  "geometry": {"coordinates":[0.168512,51.391681],"type":"Point"}
}
