{
  "type": "Feature",
  "properties": {
    "iso:country":"GB",
    "wof:name":"B33 9NP",
    "wof:placetype":"postalcode"
},
  "geometry": {"coordinates":[-1.79366945269958,52.48988752305634],"type":"Point"}
}