{
  "type": "Feature",
  "properties": {
    "date:inception_lower": "2000-10-01",
    "date:inception_upper": "2000-10-01",
    "iso:country": "GB",
    "wof:name": "GL51 3DZ",
    "wof:placetype": "postalcode"
  },
  "geometry": {"coordinates":[-2.096299,51.880343],"type":"Point"}
}
