{
  "type": "Feature",
  "properties": {
    "iso:country":"GB",
    "wof:name":"DT9 3PW",
    "wof:placetype":"postalcode"
},
  "geometry": {"coordinates":[-2.52190382857793,50.94833315578381],"type":"Point"}
}