{
  "type": "Feature",
  "properties": {
    "iso:country":"GB",
    "wof:name":"SK4 2RB",
    "wof:placetype":"postalcode"
},
  "geometry": {"coordinates":[-2.16977855952597,53.42356740350913],"type":"Point"}
}