{
  "type": "Feature",
  "properties": {
    "date:inception_lower":"1997-12-01",
    "date:inception_upper":"1997-12-31",
    "iso:country":"GB",
    "wof:name":"SK4 2RB",
    "wof:placetype":"postalcode"
},
  "geometry": {"coordinates":[-2.169779,53.423567],"type":"Point"}
}