{
  "type": "Feature",
  "properties": {
    "iso:country":"GB",
    "wof:name":"CT2 9EB",
    "wof:placetype":"postalcode"
},
  "geometry": {"coordinates":[1.05129597460001,51.2983700232484],"type":"Point"}
}