{
  "type": "Feature",
  "properties": {
    "iso:country":"GB",
    "wof:name":"IP2 0NG",
    "wof:placetype":"postalcode"
},
  "geometry": {"coordinates":[1.12523537490902,52.05069682512074],"type":"Point"}
}