{
  "type": "Feature",
  "properties": {
    "iso:country": "GB",
    "wof:name": "IP2 0NG",
    "wof:placetype": "postalcode"
  },
  "geometry": {"coordinates":[1.125235,52.050697],"type":"Point"}
}
