{
  "type": "Feature",
  "properties": {
    "iso:country":"GB",
    "wof:name":"SE28 0AB",
    "wof:placetype":"postalcode"
},
  "geometry": {"coordinates":[0.09847923869224,51.4958616144052],"type":"Point"}
}