{
  "type": "Feature",
  "properties": {
    "iso:country":"GB",
    "wof:name":"ML8 4JE",
    "wof:placetype":"postalcode"
},
  "geometry": {"coordinates":[-3.82959098961978,55.7285513937289],"type":"Point"}
}