{
  "type": "Feature",
  "properties": {
    "iso:country":"GB",
    "wof:name":"NN5 6TJ",
    "wof:placetype":"postalcode"
},
  "geometry": {"coordinates":[-0.94483978595372,52.25256400298134],"type":"Point"}
}