{
  "type": "Feature",
  "properties": {
    "iso:country":"GB",
    "wof:name":"S18 2GS",
    "wof:placetype":"postalcode"
},
  "geometry": {"coordinates":[-1.46924274419827,53.30749968840416],"type":"Point"}
}