{
  "type": "Feature",
  "properties": {
    "date:inception_lower":"1991-09-01",
    "date:inception_upper":"1991-09-30",
    "iso:country":"GB",
    "wof:name":"KT8 2LX",
    "wof:placetype":"postalcode"
},
  "geometry": {"coordinates":[-0.371873,51.398574],"type":"Point"}
}