{
  "type": "Feature",
  "properties": {
    "iso:country":"GB",
    "wof:name":"SK8 6NE",
    "wof:placetype":"postalcode"
},
  "geometry": {"coordinates":[-2.19291153279216,53.36468399454515],"type":"Point"}
}