{
  "type": "Feature",
  "properties": {
    "date:inception_lower": "2008-01-01",
    "date:inception_upper": "2008-01-01",
    "iso:country": "GB",
    "wof:name": "TW7 5FD",
    "wof:placetype": "postalcode"
  },
  "geometry": {"coordinates":[-0.339516,51.480229],"type":"Point"}
}
