{
  "type": "Feature",
  "properties": {
    "date:inception_lower": "1992-08-01",
    "date:inception_upper": "1992-08-01",
    "iso:country": "GB",
    "wof:name": "LE18 1BP",
    "wof:placetype": "postalcode"
  },
  "geometry": {"coordinates":[-1.12353,52.595595],"type":"Point"}
}
