{
  "type": "Feature",
  "properties": {
    "iso:country":"GB",
    "wof:name":"LE18 1BP",
    "wof:placetype":"postalcode"
},
  "geometry": {"coordinates":[-1.12357397080604,52.59528899921384],"type":"Point"}
}