{
  "type": "Feature",
  "properties": {
    "date:inception_lower":"1980-01-01",
    "date:inception_upper":"1980-01-31",
    "iso:country":"GB",
    "wof:name":"KW17 2LG",
    "wof:placetype":"postalcode"
},
  "geometry": {"coordinates":[-3.218858,59.059096],"type":"Point"}
}