{
  "type": "Feature",
  "properties": {
    "iso:country":"GB",
    "wof:name":"KW17 2LG",
    "wof:placetype":"postalcode"
},
  "geometry": {"coordinates":[-3.21885826117664,59.05909553238568],"type":"Point"}
}