{
  "type": "Feature",
  "properties": {
    "iso:country": "GB",
    "wof:name": "L18 9TY",
    "wof:placetype": "postalcode"
  },
  "geometry": {"coordinates":[-2.898607,53.36764],"type":"Point"}
}
