{
  "type": "Feature",
  "properties": {
    "iso:country": "GB",
    "wof:name": "CV37 6DD",
    "wof:placetype": "postalcode"
  },
  "geometry": {"coordinates":[-1.710791,52.186969],"type":"Point"}
}
