{
  "type": "Feature",
  "properties": {
    "iso:country":"GB",
    "wof:name":"CV37 6DD",
    "wof:placetype":"postalcode"
},
  "geometry": {"coordinates":[-1.7107910381084,52.18696906050097],"type":"Point"}
}