{
  "type": "Feature",
  "properties": {
    "date:inception_lower": "1980-01-01",
    "date:inception_upper": "1980-01-01",
    "iso:country": "GB",
    "wof:name": "SA10 7YP",
    "wof:placetype": "postalcode"
  },
  "geometry": {"coordinates":[-3.813509,51.68446],"type":"Point"}
}
