{
  "type": "Feature",
  "properties": {
    "date:inception_lower":"1980-01-01",
    "date:inception_upper":"1980-01-31",
    "iso:country":"GB",
    "wof:name":"SA10 7YP",
    "wof:placetype":"postalcode"
},
  "geometry": {"coordinates":[-3.814438,51.684527],"type":"Point"}
}