{
  "type": "Feature",
  "properties": {
    "iso:country":"GB",
    "wof:name":"SN14 6RX",
    "wof:placetype":"postalcode"
},
  "geometry": {"coordinates":[-2.23877824526435,51.55257401829036],"type":"Point"}
}