{
  "type": "Feature",
  "properties": {
    "iso:country":"GB",
    "wof:name":"CT4 5RT",
    "wof:placetype":"postalcode"
},
  "geometry": {"coordinates":[1.02657422171652,51.23379265484294],"type":"Point"}
}