{
  "type": "Feature",
  "properties": {
    "iso:country":"GB",
    "wof:name":"NP4 9AZ",
    "wof:placetype":"postalcode"
},
  "geometry": {"coordinates":[-3.09715606250314,51.77846391323314],"type":"Point"}
}