{
  "type": "Feature",
  "properties": {
    "date:inception_lower":"2017-09-01",
    "date:inception_upper":"2017-09-30",
    "iso:country":"GB",
    "wof:name":"NP4 9AZ",
    "wof:placetype":"postalcode"
},
  "geometry": {"coordinates":[-3.097163,51.778468],"type":"Point"}
}