{
  "type": "Feature",
  "properties": {
    "iso:country": "GB",
    "wof:name": "NP4 9AZ",
    "wof:placetype": "postalcode"
  },
  "geometry": {"coordinates":[-3.097163,51.778468],"type":"Point"}
}
