{
  "type": "Feature",
  "properties": {
    "iso:country":"GB",
    "wof:name":"NG9 3GD",
    "wof:placetype":"postalcode"
},
  "geometry": {"coordinates":[-1.25087148301862,52.93937193513256],"type":"Point"}
}