{
  "type": "Feature",
  "properties": {
    "iso:country":"GB",
    "wof:name":"SL7 1EN",
    "wof:placetype":"postalcode"
},
  "geometry": {"coordinates":[-0.77219082800876,51.57196029879167],"type":"Point"}
}