{
  "type": "Feature",
  "properties": {
    "iso:country":"GB",
    "wof:name":"SA5 9BA",
    "wof:placetype":"postalcode"
},
  "geometry": {"coordinates":[-3.94993191243555,51.65593909751373],"type":"Point"}
}