{
  "type": "Feature",
  "properties": {
    "iso:country": "GB",
    "wof:name": "SA5 9BA",
    "wof:placetype": "postalcode"
  },
  "geometry": {"coordinates":[-3.949932,51.655939],"type":"Point"}
}
