{
  "type": "Feature",
  "properties": {
    "iso:country": "GB",
    "wof:name": "SY1 2EE",
    "wof:placetype": "postalcode"
  },
  "geometry": {"coordinates":[-2.750048,52.71313],"type":"Point"}
}
