{
  "type": "Feature",
  "properties": {
    "iso:country":"GB",
    "wof:name":"SY1 2EE",
    "wof:placetype":"postalcode"
},
  "geometry": {"coordinates":[-2.75004822783551,52.71312961919657],"type":"Point"}
}