{
  "type": "Feature",
  "properties": {
    "iso:country":"GB",
    "wof:name":"TD15 2EU",
    "wof:placetype":"postalcode"
},
  "geometry": {"coordinates":[-2.0114964317682,55.76454205422787],"type":"Point"}
}