{
  "type": "Feature",
  "properties": {
    "iso:country":"GB",
    "wof:name":"SY11 2PR",
    "wof:placetype":"postalcode"
},
  "geometry": {"coordinates":[-3.04634060768577,52.85881318048376],"type":"Point"}
}