{
  "type": "Feature",
  "properties": {
    "iso:country": "GB",
    "wof:name": "TS15 9UH",
    "wof:placetype": "postalcode"
  },
  "geometry": {"coordinates":[-1.353659,54.494933],"type":"Point"}
}
