{
  "type": "Feature",
  "properties": {
    "iso:country":"GB",
    "wof:name":"DA1 1HJ",
    "wof:placetype":"postalcode"
},
  "geometry": {"coordinates":[0.21608180211315,51.44202406409742],"type":"Point"}
}