{
  "type": "Feature",
  "properties": {
    "iso:country":"GB",
    "wof:name":"W7 3AW",
    "wof:placetype":"postalcode"
},
  "geometry": {"coordinates":[-0.34507052413893,51.52291352319961],"type":"Point"}
}