{
  "type": "Feature",
  "properties": {
    "iso:country":"GB",
    "wof:name":"AB24 1SY",
    "wof:placetype":"postalcode"
},
  "geometry": {"coordinates":[-2.09328585093132,57.16505937282938],"type":"Point"}
}