{
  "type": "Feature",
  "properties": {
    "date:inception_lower": "1996-06-01",
    "date:inception_upper": "1996-06-01",
    "iso:country": "GB",
    "wof:name": "AB24 1SY",
    "wof:placetype": "postalcode"
  },
  "geometry": {"coordinates":[-2.093286,57.165059],"type":"Point"}
}
