{
  "type": "Feature",
  "properties": {
    "iso:country": "GB",
    "wof:name": "WD23 2QL",
    "wof:placetype": "postalcode"
  },
  "geometry": {"coordinates":[-0.375661,51.6471],"type":"Point"}
}
