{
  "type": "Feature",
  "properties": {
    "iso:country":"GB",
    "wof:name":"WD23 2QL",
    "wof:placetype":"postalcode"
},
  "geometry": {"coordinates":[-0.37566133862473,51.6471000816281],"type":"Point"}
}