{
  "type": "Feature",
  "properties": {
    "iso:country":"GB",
    "wof:name":"NE43 7EJ",
    "wof:placetype":"postalcode"
},
  "geometry": {"coordinates":[-1.89710087857749,54.94218830294403],"type":"Point"}
}