{
  "type": "Feature",
  "properties": {
    "iso:country":"GB",
    "wof:name":"MK4 4GE",
    "wof:placetype":"postalcode"
},
  "geometry": {"coordinates":[-0.79743133486255,52.00152002916471],"type":"Point"}
}