{
  "type": "Feature",
  "properties": {
    "iso:country":"GB",
    "wof:name":"WR6 5NW",
    "wof:placetype":"postalcode"
},
  "geometry": {"coordinates":[-2.33692995873247,52.20181011475782],"type":"Point"}
}