{
  "type": "Feature",
  "properties": {
    "iso:country": "GB",
    "wof:name": "LN4 2EA",
    "wof:placetype": "postalcode"
  },
  "geometry": {"coordinates":[-0.420017,53.186278],"type":"Point"}
}
