{
  "type": "Feature",
  "properties": {
    "iso:country":"GB",
    "wof:name":"LN4 2EA",
    "wof:placetype":"postalcode"
},
  "geometry": {"coordinates":[-0.42001700581618,53.1862777256121],"type":"Point"}
}