{
  "type": "Feature",
  "properties": {
    "iso:country":"GB",
    "wof:name":"HA5 3AD",
    "wof:placetype":"postalcode"
},
  "geometry": {"coordinates":[-0.37529964855364,51.59290866424541],"type":"Point"}
}