{
  "type": "Feature",
  "properties": {
    "iso:country":"GB",
    "wof:name":"E3 5JQ",
    "wof:placetype":"postalcode"
},
  "geometry": {"coordinates":[-0.03307451924353,51.53389672845729],"type":"Point"}
}