{
  "type": "Feature",
  "properties": {
    "date:inception_lower": "1992-08-01",
    "date:inception_upper": "1992-08-01",
    "iso:country": "GB",
    "wof:name": "E3 5JQ",
    "wof:placetype": "postalcode"
  },
  "geometry": {"coordinates":[-0.033074,51.533897],"type":"Point"}
}
