{
  "type": "Feature",
  "properties": {
    "date:inception_lower":"1980-01-01",
    "date:inception_upper":"1980-01-31",
    "iso:country":"GB",
    "wof:name":"SY11 4NR",
    "wof:placetype":"postalcode"
},
  "geometry": {"coordinates":[-2.990907,52.889329],"type":"Point"}
}