{
  "type": "Feature",
  "properties": {
    "iso:country":"GB",
    "wof:name":"SY11 4NR",
    "wof:placetype":"postalcode"
},
  "geometry": {"coordinates":[-2.9909066781705,52.88926956769168],"type":"Point"}
}