{
  "type": "Feature",
  "properties": {
    "iso:country": "GB",
    "wof:name": "TN25 7GH",
    "wof:placetype": "postalcode"
  },
  "geometry": {"coordinates":[0.896807,51.117921],"type":"Point"}
}
