{
  "type": "Feature",
  "properties": {
    "iso:country": "GB",
    "wof:name": "EX4 4PT",
    "wof:placetype": "postalcode"
  },
  "geometry": {"coordinates":[-3.533202,50.735495],"type":"Point"}
}
