{
  "type": "Feature",
  "properties": {
    "iso:country": "GB",
    "wof:name": "WR14 4HW",
    "wof:placetype": "postalcode"
  },
  "geometry": {"coordinates":[-2.330568,52.070135],"type":"Point"}
}
