{
  "type": "Feature",
  "properties": {
    "iso:country":"GB",
    "wof:name":"WR14 4HW",
    "wof:placetype":"postalcode"
},
  "geometry": {"coordinates":[-2.33056847097719,52.07013495686712],"type":"Point"}
}