{
  "type": "Feature",
  "properties": {
    "iso:country": "GB",
    "wof:name": "WV4 5AL",
    "wof:placetype": "postalcode"
  },
  "geometry": {"coordinates":[-2.131055,52.562363],"type":"Point"}
}
