{
  "type": "Feature",
  "properties": {
    "iso:country":"GB",
    "wof:name":"WV4 5AL",
    "wof:placetype":"postalcode"
},
  "geometry": {"coordinates":[-2.13105466373884,52.5623627277631],"type":"Point"}
}