{
  "type": "Feature",
  "properties": {
    "iso:country":"GB",
    "wof:name":"SA3 5TG",
    "wof:placetype":"postalcode"
},
  "geometry": {"coordinates":[-4.00414366314475,51.5798034889016],"type":"Point"}
}