{
  "type": "Feature",
  "properties": {
    "iso:country": "GB",
    "wof:name": "NE66 5NF",
    "wof:placetype": "postalcode"
  },
  "geometry": {"coordinates":[-1.91826,55.53073],"type":"Point"}
}
