{
  "type": "Feature",
  "properties": {
    "iso:country":"GB",
    "wof:name":"NE66 5NF",
    "wof:placetype":"postalcode"
},
  "geometry": {"coordinates":[-1.91825969420616,55.53072972712299],"type":"Point"}
}