{
  "type": "Feature",
  "properties": {
    "date:inception_lower": "2006-09-01",
    "date:inception_upper": "2006-09-01",
    "iso:country": "GB",
    "wof:name": "CB25 9JQ",
    "wof:placetype": "postalcode"
  },
  "geometry": {"coordinates":[0.185145,52.242149],"type":"Point"}
}
