{
  "type": "Feature",
  "properties": {
    "iso:country":"GB",
    "wof:name":"CB25 9JQ",
    "wof:placetype":"postalcode"
},
  "geometry": {"coordinates":[0.18511578602554,52.2421357661997],"type":"Point"}
}