{
  "type": "Feature",
  "properties": {
    "date:inception_lower": "1992-08-01",
    "date:inception_upper": "1992-08-01",
    "iso:country": "GB",
    "wof:name": "LE67 1EW",
    "wof:placetype": "postalcode"
  },
  "geometry": {"coordinates":[-1.371496,52.701065],"type":"Point"}
}
