{
  "type": "Feature",
  "properties": {
    "date:inception_lower": "1983-03-01",
    "date:inception_upper": "1983-03-01",
    "iso:country": "GB",
    "wof:name": "OL1 3JA",
    "wof:placetype": "postalcode"
  },
  "geometry": {"coordinates":[-2.103481,53.549956],"type":"Point"}
}
