{
  "type": "Feature",
  "properties": {
    "iso:country": "GB",
    "wof:name": "OL1 3JA",
    "wof:placetype": "postalcode"
  },
  "geometry": {"coordinates":[-2.103481,53.549956],"type":"Point"}
}
