{
  "type": "Feature",
  "properties": {
    "iso:country":"GB",
    "wof:name":"MK42 0SD",
    "wof:placetype":"postalcode"
},
  "geometry": {"coordinates":[-0.43840578123409,52.11882670317756],"type":"Point"}
}