{
  "type": "Feature",
  "properties": {
    "iso:country": "GB",
    "wof:name": "G71 8FS",
    "wof:placetype": "postalcode"
  },
  "geometry": {"coordinates":[-4.077935,55.801347],"type":"Point"}
}
