{
  "type": "Feature",
  "properties": {
    "iso:country":"GB",
    "wof:name":"EX21 5TU",
    "wof:placetype":"postalcode"
},
  "geometry": {"coordinates":[-4.22856327898447,50.75257693486914],"type":"Point"}
}