{
  "type": "Feature",
  "properties": {
    "date:inception_lower": "1980-01-01",
    "date:inception_upper": "1980-01-01",
    "iso:country": "GB",
    "wof:name": "EX21 5TU",
    "wof:placetype": "postalcode"
  },
  "geometry": {"coordinates":[-4.230938,50.747677],"type":"Point"}
}
