{
  "type": "Feature",
  "properties": {
    "iso:country":"GB",
    "wof:name":"IG4 5EX",
    "wof:placetype":"postalcode"
},
  "geometry": {"coordinates":[0.05453712926207,51.58037086749184],"type":"Point"}
}