{
  "type": "Feature",
  "properties": {
    "iso:country":"GB",
    "wof:name":"SP11 9PN",
    "wof:placetype":"postalcode"
},
  "geometry": {"coordinates":[-1.60873918887201,51.26198746893262],"type":"Point"}
}