{
  "type": "Feature",
  "properties": {
    "iso:country": "GB",
    "wof:name": "SP11 9PN",
    "wof:placetype": "postalcode"
  },
  "geometry": {"coordinates":[-1.608739,51.261987],"type":"Point"}
}
