{
  "type": "Feature",
  "properties": {
    "iso:country": "GB",
    "wof:name": "SP1 3BP",
    "wof:placetype": "postalcode"
  },
  "geometry": {"coordinates":[-1.791727,51.08062],"type":"Point"}
}
