{
  "type": "Feature",
  "properties": {
    "date:inception_lower":"1980-01-01",
    "date:inception_upper":"1980-01-31",
    "iso:country":"GB",
    "wof:name":"YO15 1BL",
    "wof:placetype":"postalcode"
},
  "geometry": {"coordinates":[-0.107615,54.126813],"type":"Point"}
}