{
  "type": "Feature",
  "properties": {
    "iso:country": "GB",
    "wof:name": "YO15 1BL",
    "wof:placetype": "postalcode"
  },
  "geometry": {"coordinates":[-0.107615,54.126813],"type":"Point"}
}
