{
  "type": "Feature",
  "properties": {
    "date:inception_lower":"1980-01-01",
    "date:inception_upper":"1980-01-31",
    "iso:country":"GB",
    "wof:name":"B33 0QJ",
    "wof:placetype":"postalcode"
},
  "geometry": {"coordinates":[-1.769163,52.464473],"type":"Point"}
}