{
  "type": "Feature",
  "properties": {
    "iso:country":"GB",
    "wof:name":"CF11 7EY",
    "wof:placetype":"postalcode"
},
  "geometry": {"coordinates":[-3.18629107771661,51.46514486856016],"type":"Point"}
}