{
  "type": "Feature",
  "properties": {
    "iso:country": "GB",
    "wof:name": "TS19 8AZ",
    "wof:placetype": "postalcode"
  },
  "geometry": {"coordinates":[-1.342265,54.580509],"type":"Point"}
}
