{
  "type": "Feature",
  "properties": {
    "date:inception_lower":"1985-04-01",
    "date:inception_upper":"1985-04-30",
    "iso:country":"GB",
    "wof:name":"NR25 6JS",
    "wof:placetype":"postalcode"
},
  "geometry": {"coordinates":[1.099374,52.900857],"type":"Point"}
}