{
  "type": "Feature",
  "properties": {
    "date:inception_lower": "2021-11-01",
    "date:inception_upper": "2021-11-01",
    "iso:country": "GB",
    "wof:name": "BS40 5YX",
    "wof:placetype": "postalcode"
  },
  "geometry": {"coordinates":[-2.764192,51.361984],"type":"Point"}
}
