{
  "type": "Feature",
  "properties": {
    "iso:country":"GB",
    "wof:name":"TN37 6DB",
    "wof:placetype":"postalcode"
},
  "geometry": {"coordinates":[0.56917639950295,50.8531411921372],"type":"Point"}
}