{
  "type": "Feature",
  "properties": {
    "iso:country": "GB",
    "wof:name": "TN37 6DB",
    "wof:placetype": "postalcode"
  },
  "geometry": {"coordinates":[0.569176,50.853141],"type":"Point"}
}
