{
  "type": "Feature",
  "properties": {
    "iso:country":"GB",
    "wof:name":"M32 0QW",
    "wof:placetype":"postalcode"
},
  "geometry": {"coordinates":[-2.28935939183308,53.46025318784488],"type":"Point"}
}