{
  "type": "Feature",
  "properties": {
    "date:inception_lower": "1995-07-01",
    "date:inception_upper": "1995-07-01",
    "iso:country": "GB",
    "wof:name": "M32 0QW",
    "wof:placetype": "postalcode"
  },
  "geometry": {"coordinates":[-2.289359,53.460253],"type":"Point"}
}
