{
  "type": "Feature",
  "properties": {
    "date:inception_lower": "2003-09-01",
    "date:inception_upper": "2003-09-01",
    "iso:country": "GB",
    "wof:name": "E14 9PB",
    "wof:placetype": "postalcode"
  },
  "geometry": {"coordinates":[-0.005194,51.505738],"type":"Point"}
}
