{
  "type": "Feature",
  "properties": {
    "iso:country":"GB",
    "wof:name":"E14 9PB",
    "wof:placetype":"postalcode"
},
  "geometry": {"coordinates":[-0.00519386403692,51.50573751300973],"type":"Point"}
}