{
  "type": "Feature",
  "properties": {
    "date:inception_lower": "1980-01-01",
    "date:inception_upper": "1980-01-01",
    "iso:country": "GB",
    "wof:name": "WV1 1HQ",
    "wof:placetype": "postalcode"
  },
  "geometry": {"coordinates":[-2.125819,52.585784],"type":"Point"}
}
