{
  "type": "Feature",
  "properties": {
    "iso:country":"GB",
    "wof:name":"WV1 1HQ",
    "wof:placetype":"postalcode"
},
  "geometry": {"coordinates":[-2.12582593746726,52.58576891169057],"type":"Point"}
}