{
  "type": "Feature",
  "properties": {
    "iso:country": "GB",
    "wof:name": "WV1 1HQ",
    "wof:placetype": "postalcode"
  },
  "geometry": {"coordinates":[-2.125835,52.585892],"type":"Point"}
}
