{
  "type": "Feature",
  "properties": {
    "iso:country":"GB",
    "wof:name":"L39 9EN",
    "wof:placetype":"postalcode"
},
  "geometry": {"coordinates":[-2.84391974626679,53.54243933153509],"type":"Point"}
}