{
  "type": "Feature",
  "properties": {
    "iso:country": "GB",
    "wof:name": "EX15 3ES",
    "wof:placetype": "postalcode"
  },
  "geometry": {"coordinates":[-3.345856,50.917093],"type":"Point"}
}
