{
  "type": "Feature",
  "properties": {
    "iso:country":"GB",
    "wof:name":"M20 2WJ",
    "wof:placetype":"postalcode"
},
  "geometry": {"coordinates":[-2.24210758494622,53.42495261144375],"type":"Point"}
}