{
  "type": "Feature",
  "properties": {
    "iso:country": "GB",
    "wof:name": "EC1M 6EF",
    "wof:placetype": "postalcode"
  },
  "geometry": {"coordinates":[-0.104214,51.520059],"type":"Point"}
}
