{
  "type": "Feature",
  "properties": {
    "iso:country":"GB",
    "wof:name":"IG10 2DQ",
    "wof:placetype":"postalcode"
},
  "geometry": {"coordinates":[0.08629545448723,51.65038479629916],"type":"Point"}
}