{
  "type": "Feature",
  "properties": {
    "iso:country":"GB",
    "wof:name":"NE23 8HD",
    "wof:placetype":"postalcode"
},
  "geometry": {"coordinates":[-1.6063372170673,55.08586871850778],"type":"Point"}
}