{
  "type": "Feature",
  "properties": {
    "iso:country":"GB",
    "wof:name":"NP44 7JF",
    "wof:placetype":"postalcode"
},
  "geometry": {"coordinates":[-3.03899098677274,51.63655837661438],"type":"Point"}
}