{
  "type": "Feature",
  "properties": {
    "iso:country":"GB",
    "wof:name":"CV2 1GT",
    "wof:placetype":"postalcode"
},
  "geometry": {"coordinates":[-1.46445393627568,52.43991418968061],"type":"Point"}
}