{
  "type": "Feature",
  "properties": {
    "iso:country": "GB",
    "wof:name": "CV2 1GT",
    "wof:placetype": "postalcode"
  },
  "geometry": {"coordinates":[-1.464454,52.439914],"type":"Point"}
}
