{
  "type": "Feature",
  "properties": {
    "iso:country":"GB",
    "wof:name":"B1 2PJ",
    "wof:placetype":"postalcode"
},
  "geometry": {"coordinates":[-1.91667469742506,52.48106582994149],"type":"Point"}
}