{
  "type": "Feature",
  "properties": {
    "date:inception_lower":"1980-01-01",
    "date:inception_upper":"1980-01-31",
    "iso:country":"GB",
    "wof:name":"WA8 0BA",
    "wof:placetype":"postalcode"
},
  "geometry": {"coordinates":[-2.715599,53.369283],"type":"Point"}
}