{
  "type": "Feature",
  "properties": {
    "iso:country":"GB",
    "wof:name":"WA8 0BA",
    "wof:placetype":"postalcode"
},
  "geometry": {"coordinates":[-2.71559868856122,53.3692825106345],"type":"Point"}
}