{
  "type": "Feature",
  "properties": {
    "iso:country": "GB",
    "wof:name": "HD8 8TA",
    "wof:placetype": "postalcode"
  },
  "geometry": {"coordinates":[-1.63709,53.581315],"type":"Point"}
}
