{
  "type": "Feature",
  "properties": {
    "iso:country":"GB",
    "wof:name":"HD8 8TA",
    "wof:placetype":"postalcode"
},
  "geometry": {"coordinates":[-1.6370869228019,53.58129875431803],"type":"Point"}
}