{
  "type": "Feature",
  "properties": {
    "date:inception_lower": "1994-12-01",
    "date:inception_upper": "1994-12-01",
    "iso:country": "GB",
    "wof:name": "HP2 5UQ",
    "wof:placetype": "postalcode"
  },
  "geometry": {"coordinates":[-0.460965,51.753409],"type":"Point"}
}
