{
  "type": "Feature",
  "properties": {
    "iso:country":"GB",
    "wof:name":"HP2 5UQ",
    "wof:placetype":"postalcode"
},
  "geometry": {"coordinates":[-0.46096530589216,51.75340932705765],"type":"Point"}
}