{
  "type": "Feature",
  "properties": {
    "iso:country": "GB",
    "wof:name": "IP12 1NF",
    "wof:placetype": "postalcode"
  },
  "geometry": {"coordinates":[1.313464,52.106592],"type":"Point"}
}
