{
  "type": "Feature",
  "properties": {
    "date:inception_lower":"2018-06-01",
    "date:inception_upper":"2018-06-30",
    "iso:country":"GB",
    "wof:name":"IP12 1NF",
    "wof:placetype":"postalcode"
},
  "geometry": {"coordinates":[1.313992,52.106622],"type":"Point"}
}