{
  "type": "Feature",
  "properties": {
    "iso:country":"GB",
    "wof:name":"NP10 8LA",
    "wof:placetype":"postalcode"
},
  "geometry": {"coordinates":[-3.03942440014505,51.57839664427399],"type":"Point"}
}