{
  "type": "Feature",
  "properties": {
    "iso:country": "GB",
    "wof:name": "NP10 8LA",
    "wof:placetype": "postalcode"
  },
  "geometry": {"coordinates":[-3.039424,51.578397],"type":"Point"}
}
