{
  "type": "Feature",
  "properties": {
    "date:inception_lower":"2014-11-01",
    "date:inception_upper":"2014-11-30",
    "iso:country":"GB",
    "wof:name":"M15 6GT",
    "wof:placetype":"postalcode"
},
  "geometry": {"coordinates":[-2.246328,53.467657],"type":"Point"}
}