{
  "type": "Feature",
  "properties": {
    "iso:country":"GB",
    "wof:name":"TS14 6BL",
    "wof:placetype":"postalcode"
},
  "geometry": {"coordinates":[-1.0513120480898,54.53550329125006],"type":"Point"}
}