{
  "type": "Feature",
  "properties": {
    "iso:country": "GB",
    "wof:name": "TS14 6BL",
    "wof:placetype": "postalcode"
  },
  "geometry": {"coordinates":[-1.051342,54.535548],"type":"Point"}
}
