{
  "type": "Feature",
  "properties": {
    "iso:country":"GB",
    "wof:name":"PO37 6JD",
    "wof:placetype":"postalcode"
},
  "geometry": {"coordinates":[-1.1724128381766,50.63861356958098],"type":"Point"}
}