{
  "type": "Feature",
  "properties": {
    "iso:country":"GB",
    "wof:name":"CW9 8DZ",
    "wof:placetype":"postalcode"
},
  "geometry": {"coordinates":[-2.51108543620136,53.24525463206466],"type":"Point"}
}