{
  "type": "Feature",
  "properties": {
    "date:inception_lower": "1980-01-01",
    "date:inception_upper": "1980-01-01",
    "iso:country": "GB",
    "wof:name": "CA5 6PU",
    "wof:placetype": "postalcode"
  },
  "geometry": {"coordinates":[-3.050907,54.838176],"type":"Point"}
}
