{
  "type": "Feature",
  "properties": {
    "iso:country":"GB",
    "wof:name":"CA5 6PU",
    "wof:placetype":"postalcode"
},
  "geometry": {"coordinates":[-3.05090696727708,54.8381761420172],"type":"Point"}
}