{
  "type": "Feature",
  "properties": {
    "iso:country": "GB",
    "wof:name": "LS26 0RP",
    "wof:placetype": "postalcode"
  },
  "geometry": {"coordinates":[-1.50426,53.758465],"type":"Point"}
}
