{
  "type": "Feature",
  "properties": {
    "date:inception_lower":"2007-01-01",
    "date:inception_upper":"2007-01-31",
    "iso:country":"GB",
    "wof:name":"LS26 0RP",
    "wof:placetype":"postalcode"
},
  "geometry": {"coordinates":[-1.504195,53.758511],"type":"Point"}
}