{
  "type": "Feature",
  "properties": {
    "iso:country": "GB",
    "wof:name": "CF83 8UH",
    "wof:placetype": "postalcode"
  },
  "geometry": {"coordinates":[-3.1381,51.59168],"type":"Point"}
}
