{
  "type": "Feature",
  "properties": {
    "date:inception_lower":"1999-06-01",
    "date:inception_upper":"1999-06-30",
    "iso:country":"GB",
    "wof:name":"CF83 8UH",
    "wof:placetype":"postalcode"
},
  "geometry": {"coordinates":[-3.1381,51.59168],"type":"Point"}
}