{
  "type": "Feature",
  "properties": {
    "iso:country":"GB",
    "wof:name":"L3 2ET",
    "wof:placetype":"postalcode"
},
  "geometry": {"coordinates":[-2.98461598138428,53.41057592093359],"type":"Point"}
}