{
  "type": "Feature",
  "properties": {
    "iso:country":"GB",
    "wof:name":"TN15 8LG",
    "wof:placetype":"postalcode"
},
  "geometry": {"coordinates":[0.32185908317891,51.29110119134832],"type":"Point"}
}