{
  "type": "Feature",
  "properties": {
    "iso:country": "GB",
    "wof:name": "TN15 8LG",
    "wof:placetype": "postalcode"
  },
  "geometry": {"coordinates":[0.321859,51.291101],"type":"Point"}
}
