{
  "type": "Feature",
  "properties": {
    "iso:country": "GB",
    "wof:name": "PE23 4EP",
    "wof:placetype": "postalcode"
  },
  "geometry": {"coordinates":[0.026254,53.171637],"type":"Point"}
}
