{
  "type": "Feature",
  "properties": {
    "iso:country": "GB",
    "wof:name": "PE23 4EP",
    "wof:placetype": "postalcode"
  },
  "geometry": {"coordinates":[0.026706,53.171072],"type":"Point"}
}
