{
  "type": "Feature",
  "properties": {
    "iso:country":"GB",
    "wof:name":"PE23 4EP",
    "wof:placetype":"postalcode"
},
  "geometry": {"coordinates":[0.02629538653166,53.17161920211132],"type":"Point"}
}