{
  "type": "Feature",
  "properties": {
    "iso:country": "GB",
    "wof:name": "BA2 5BG",
    "wof:placetype": "postalcode"
  },
  "geometry": {"coordinates":[-2.353488,51.361723],"type":"Point"}
}
