{
  "type": "Feature",
  "properties": {
    "iso:country": "GB",
    "wof:name": "BN24 5JT",
    "wof:placetype": "postalcode"
  },
  "geometry": {"coordinates":[0.340516,50.821329],"type":"Point"}
}
