{
  "type": "Feature",
  "properties": {
    "date:inception_lower":"1980-01-01",
    "date:inception_upper":"1980-01-31",
    "iso:country":"GB",
    "wof:name":"BN24 5JT",
    "wof:placetype":"postalcode"
},
  "geometry": {"coordinates":[0.340516,50.821329],"type":"Point"}
}