{
  "type": "Feature",
  "properties": {
    "date:inception_lower": "1980-01-01",
    "date:inception_upper": "1980-01-01",
    "iso:country": "GB",
    "wof:name": "BL1 7HX",
    "wof:placetype": "postalcode"
  },
  "geometry": {"coordinates":[-2.433506,53.603324],"type":"Point"}
}
