{
  "type": "Feature",
  "properties": {
    "iso:country": "GB",
    "wof:name": "WF4 6DB",
    "wof:placetype": "postalcode"
  },
  "geometry": {"coordinates":[-1.551196,53.667646],"type":"Point"}
}
