{
  "type": "Feature",
  "properties": {
    "iso:country":"GB",
    "wof:name":"WF4 6DB",
    "wof:placetype":"postalcode"
},
  "geometry": {"coordinates":[-1.55092717812699,53.66734817967315],"type":"Point"}
}