{
  "type": "Feature",
  "properties": {
    "date:inception_lower": "1980-01-01",
    "date:inception_upper": "1980-01-01",
    "iso:country": "GB",
    "wof:name": "WF4 6DB",
    "wof:placetype": "postalcode"
  },
  "geometry": {"coordinates":[-1.551062,53.667779],"type":"Point"}
}
