{
  "type": "Feature",
  "properties": {
    "iso:country":"GB",
    "wof:name":"B91 1UL",
    "wof:placetype":"postalcode"
},
  "geometry": {"coordinates":[-1.80702076507497,52.41045625561743],"type":"Point"}
}