{
  "type": "Feature",
  "properties": {
    "iso:country": "GB",
    "wof:name": "OL10 2WJ",
    "wof:placetype": "postalcode"
  },
  "geometry": {"coordinates":[-2.207064,53.580473],"type":"Point"}
}
