{
  "type": "Feature",
  "properties": {
    "date:inception_lower": "2002-07-01",
    "date:inception_upper": "2002-07-01",
    "iso:country": "GB",
    "wof:name": "OL10 2WJ",
    "wof:placetype": "postalcode"
  },
  "geometry": {"coordinates":[-2.207064,53.580473],"type":"Point"}
}
