{
  "type": "Feature",
  "properties": {
    "iso:country": "GB",
    "wof:name": "DN22 7RL",
    "wof:placetype": "postalcode"
  },
  "geometry": {"coordinates":[-0.951536,53.310079],"type":"Point"}
}
