{
  "type": "Feature",
  "properties": {
    "iso:country":"GB",
    "wof:name":"CB7 5FN",
    "wof:placetype":"postalcode"
},
  "geometry": {"coordinates":[0.33246519207682,52.33125081072671],"type":"Point"}
}