{
  "type": "Feature",
  "properties": {
    "date:inception_lower":"2009-05-01",
    "date:inception_upper":"2009-05-31",
    "iso:country":"GB",
    "wof:name":"CB7 5FN",
    "wof:placetype":"postalcode"
},
  "geometry": {"coordinates":[0.332465,52.331251],"type":"Point"}
}