{
  "type": "Feature",
  "properties": {
    "date:inception_lower": "1980-01-01",
    "date:inception_upper": "1980-01-01",
    "iso:country": "GB",
    "wof:name": "CV6 4HB",
    "wof:placetype": "postalcode"
  },
  "geometry": {"coordinates":[-1.512682,52.450093],"type":"Point"}
}
