{
  "type": "Feature",
  "properties": {
    "iso:country":"GB",
    "wof:name":"WS14 0JB",
    "wof:placetype":"postalcode"
},
  "geometry": {"coordinates":[-1.84075267178998,52.63687210410605],"type":"Point"}
}