{
  "type": "Feature",
  "properties": {
    "iso:country": "GB",
    "wof:name": "HD1 4NP",
    "wof:placetype": "postalcode"
  },
  "geometry": {"coordinates":[-1.802219,53.652773],"type":"Point"}
}
