{
  "type": "Feature",
  "properties": {
    "iso:country":"GB",
    "wof:name":"HD1 4NP",
    "wof:placetype":"postalcode"
},
  "geometry": {"coordinates":[-1.80221879493807,53.65277333376619],"type":"Point"}
}