{
  "type": "Feature",
  "properties": {
    "date:inception_lower": "1980-01-01",
    "date:inception_upper": "1980-01-01",
    "iso:country": "GB",
    "wof:name": "HD1 4NP",
    "wof:placetype": "postalcode"
  },
  "geometry": {"coordinates":[-1.802219,53.652773],"type":"Point"}
}
