{
  "type": "Feature",
  "properties": {
    "iso:country":"GB",
    "wof:name":"PO14 1BS",
    "wof:placetype":"postalcode"
},
  "geometry": {"coordinates":[-1.19766701799458,50.84201873885081],"type":"Point"}
}