{
  "type": "Feature",
  "properties": {
    "iso:country":"GB",
    "wof:name":"CF41 7BL",
    "wof:placetype":"postalcode"
},
  "geometry": {"coordinates":[-3.48852125650596,51.65109644831116],"type":"Point"}
}