{
  "type": "Feature",
  "properties": {
    "iso:country": "GB",
    "wof:name": "NR1 2LS",
    "wof:placetype": "postalcode"
  },
  "geometry": {"coordinates":[1.296628,52.608954],"type":"Point"}
}
