{
  "type": "Feature",
  "properties": {
    "date:inception_lower": "2020-05-01",
    "date:inception_upper": "2020-05-01",
    "iso:country": "GB",
    "wof:name": "MK42 0DW",
    "wof:placetype": "postalcode"
  },
  "geometry": {"coordinates":[-0.425419,52.11578],"type":"Point"}
}
