{
  "type": "Feature",
  "properties": {
    "date:inception_lower":"1980-01-01",
    "date:inception_upper":"1980-01-31",
    "iso:country":"GB",
    "wof:name":"PE2 9EQ",
    "wof:placetype":"postalcode"
},
  "geometry": {"coordinates":[-0.246858,52.554934],"type":"Point"}
}