{
  "type": "Feature",
  "properties": {
    "iso:country":"GB",
    "wof:name":"PE2 9EQ",
    "wof:placetype":"postalcode"
},
  "geometry": {"coordinates":[-0.24685831496986,52.55493379096404],"type":"Point"}
}