{
  "type": "Feature",
  "properties": {
    "iso:country":"GB",
    "wof:name":"LE4 3GE",
    "wof:placetype":"postalcode"
},
  "geometry": {"coordinates":[-1.12963705538703,52.68339960329951],"type":"Point"}
}