{
  "type": "Feature",
  "properties": {
    "iso:country": "GB",
    "wof:name": "LE4 3GE",
    "wof:placetype": "postalcode"
  },
  "geometry": {"coordinates":[-1.129637,52.6834],"type":"Point"}
}
