{
  "type": "Feature",
  "properties": {
    "date:inception_lower": "2011-11-01",
    "date:inception_upper": "2011-11-01",
    "iso:country": "GB",
    "wof:name": "LE15 9EE",
    "wof:placetype": "postalcode"
  },
  "geometry": {"coordinates":[-0.723904,52.594598],"type":"Point"}
}
