{
  "type": "Feature",
  "properties": {
    "iso:country":"GB",
    "wof:name":"LE15 9EE",
    "wof:placetype":"postalcode"
},
  "geometry": {"coordinates":[-0.72390441490791,52.59459764828852],"type":"Point"}
}