{
  "type": "Feature",
  "properties": {
    "iso:country": "GB",
    "wof:name": "LE15 9EE",
    "wof:placetype": "postalcode"
  },
  "geometry": {"coordinates":[-0.723904,52.594598],"type":"Point"}
}
