{
  "type": "Feature",
  "properties": {
    "iso:country":"GB",
    "wof:name":"AB39 3PX",
    "wof:placetype":"postalcode"
},
  "geometry": {"coordinates":[-2.15425374330644,57.0316091808395],"type":"Point"}
}