{
  "type": "Feature",
  "properties": {
    "iso:country": "GB",
    "wof:name": "AB39 3PX",
    "wof:placetype": "postalcode"
  },
  "geometry": {"coordinates":[-2.154254,57.031609],"type":"Point"}
}
