{
  "type": "Feature",
  "properties": {
    "iso:country":"GB",
    "wof:name":"ME12 2LY",
    "wof:placetype":"postalcode"
},
  "geometry": {"coordinates":[0.80803118704303,51.42638353160702],"type":"Point"}
}