{
  "type": "Feature",
  "properties": {
    "date:inception_lower":"2008-08-01",
    "date:inception_upper":"2008-08-31",
    "iso:country":"GB",
    "wof:name":"DN20 9BN",
    "wof:placetype":"postalcode"
},
  "geometry": {"coordinates":[-0.537846,53.537508],"type":"Point"}
}