{
  "type": "Feature",
  "properties": {
    "iso:country": "GB",
    "wof:name": "DN20 9BN",
    "wof:placetype": "postalcode"
  },
  "geometry": {"coordinates":[-0.537846,53.537508],"type":"Point"}
}
