{
  "type": "Feature",
  "properties": {
    "iso:country":"GB",
    "wof:name":"WA5 1HZ",
    "wof:placetype":"postalcode"
},
  "geometry": {"coordinates":[-2.62821139389131,53.38511837287955],"type":"Point"}
}