{
  "type": "Feature",
  "properties": {
    "iso:country":"GB",
    "wof:name":"S70 4AN",
    "wof:placetype":"postalcode"
},
  "geometry": {"coordinates":[-1.46150855237139,53.5355068122088],"type":"Point"}
}