{
  "type": "Feature",
  "properties": {
    "date:inception_lower": "2022-06-01",
    "date:inception_upper": "2022-06-01",
    "iso:country": "GB",
    "wof:name": "BD8 0FE",
    "wof:placetype": "postalcode"
  },
  "geometry": {"coordinates":[-1.797097,53.800004],"type":"Point"}
}
