{
  "type": "Feature",
  "properties": {
    "iso:country":"GB",
    "wof:name":"S75 3JD",
    "wof:placetype":"postalcode"
},
  "geometry": {"coordinates":[-1.52820136915,53.54326676172303],"type":"Point"}
}