{
  "type": "Feature",
  "properties": {
    "iso:country": "GB",
    "wof:name": "S75 3JD",
    "wof:placetype": "postalcode"
  },
  "geometry": {"coordinates":[-1.528201,53.543267],"type":"Point"}
}
