{
  "type": "Feature",
  "properties": {
    "iso:country":"GB",
    "wof:name":"PE12 9TW",
    "wof:placetype":"postalcode"
},
  "geometry": {"coordinates":[0.19525233358024,52.76815548598177],"type":"Point"}
}