{
  "type": "Feature",
  "properties": {
    "date:inception_lower": "1990-02-01",
    "date:inception_upper": "1990-02-01",
    "iso:country": "GB",
    "wof:name": "PE12 9TW",
    "wof:placetype": "postalcode"
  },
  "geometry": {"coordinates":[0.195252,52.768155],"type":"Point"}
}
