{
  "type": "Feature",
  "properties": {
    "date:inception_lower":"1983-01-01",
    "date:inception_upper":"1983-01-31",
    "iso:country":"GB",
    "wof:name":"SY16 1QZ",
    "wof:placetype":"postalcode"
},
  "geometry": {"coordinates":[-3.337765,52.506856],"type":"Point"}
}