{
  "type": "Feature",
  "properties": {
    "iso:country":"GB",
    "wof:name":"SY16 1QZ",
    "wof:placetype":"postalcode"
},
  "geometry": {"coordinates":[-3.33776534751135,52.50685635201432],"type":"Point"}
}