{
  "type": "Feature",
  "properties": {
    "iso:country": "GB",
    "wof:name": "HU16 5NS",
    "wof:placetype": "postalcode"
  },
  "geometry": {"coordinates":[-0.430519,53.779268],"type":"Point"}
}
