{
  "type": "Feature",
  "properties": {
    "date:inception_lower": "1980-01-01",
    "date:inception_upper": "1980-01-01",
    "iso:country": "GB",
    "wof:name": "SN3 4BD",
    "wof:placetype": "postalcode"
  },
  "geometry": {"coordinates":[-1.740428,51.572959],"type":"Point"}
}
