{
  "type": "Feature",
  "properties": {
    "iso:country":"GB",
    "wof:name":"SN3 4BD",
    "wof:placetype":"postalcode"
},
  "geometry": {"coordinates":[-1.74042791126657,51.57295942465542],"type":"Point"}
}