{
  "type": "Feature",
  "properties": {
    "date:inception_lower": "1980-01-01",
    "date:inception_upper": "1980-01-01",
    "iso:country": "GB",
    "wof:name": "BN13 3BA",
    "wof:placetype": "postalcode"
  },
  "geometry": {"coordinates":[-0.409957,50.844899],"type":"Point"}
}
