{
  "type": "Feature",
  "properties": {
    "iso:country":"GB",
    "wof:name":"BN13 3BA",
    "wof:placetype":"postalcode"
},
  "geometry": {"coordinates":[-0.40995690909892,50.84489882418832],"type":"Point"}
}