{
  "type": "Feature",
  "properties": {
    "date:inception_lower": "2010-05-01",
    "date:inception_upper": "2010-05-01",
    "iso:country": "GB",
    "wof:name": "DA12 4AE",
    "wof:placetype": "postalcode"
  },
  "geometry": {"coordinates":[0.39017,51.428638],"type":"Point"}
}
