{
  "type": "Feature",
  "properties": {
    "iso:country": "GB",
    "wof:name": "DA12 4AE",
    "wof:placetype": "postalcode"
  },
  "geometry": {"coordinates":[0.39017,51.428638],"type":"Point"}
}
