{
  "type": "Feature",
  "properties": {
    "iso:country":"GB",
    "wof:name":"CA13 0XP",
    "wof:placetype":"postalcode"
},
  "geometry": {"coordinates":[-3.42406330594887,54.67222917781378],"type":"Point"}
}