{
  "type": "Feature",
  "properties": {
    "iso:country":"GB",
    "wof:name":"PH1 4BB",
    "wof:placetype":"postalcode"
},
  "geometry": {"coordinates":[-3.5188838960234,56.50147778482179],"type":"Point"}
}