{
  "type": "Feature",
  "properties": {
    "iso:country": "GB",
    "wof:name": "HR1 1HW",
    "wof:placetype": "postalcode"
  },
  "geometry": {"coordinates":[-2.711879,52.068061],"type":"Point"}
}
