{
  "type": "Feature",
  "properties": {
    "iso:country":"GB",
    "wof:name":"PO32 6SB",
    "wof:placetype":"postalcode"
},
  "geometry": {"coordinates":[-1.28731730807279,50.75323112989634],"type":"Point"}
}