{
  "type": "Feature",
  "properties": {
    "iso:country":"GB",
    "wof:name":"ME4 5HA",
    "wof:placetype":"postalcode"
},
  "geometry": {"coordinates":[0.53686245574673,51.37264488573567],"type":"Point"}
}