{
  "type": "Feature",
  "properties": {
    "iso:country": "GB",
    "wof:name": "BB10 2LU",
    "wof:placetype": "postalcode"
  },
  "geometry": {"coordinates":[-2.232867,53.819923],"type":"Point"}
}
