{
  "type": "Feature",
  "properties": {
    "date:inception_lower": "1994-12-01",
    "date:inception_upper": "1994-12-01",
    "iso:country": "GB",
    "wof:name": "LS12 2JA",
    "wof:placetype": "postalcode"
  },
  "geometry": {"coordinates":[-1.612342,53.809386],"type":"Point"}
}
