{
  "type": "Feature",
  "properties": {
    "iso:country":"GB",
    "wof:name":"LS12 2JA",
    "wof:placetype":"postalcode"
},
  "geometry": {"coordinates":[-1.612342253906,53.8093859220399],"type":"Point"}
}