{
  "type": "Feature",
  "properties": {
    "iso:country": "GB",
    "wof:name": "DL13 5RP",
    "wof:placetype": "postalcode"
  },
  "geometry": {"coordinates":[-1.898241,54.631356],"type":"Point"}
}
