{
  "type": "Feature",
  "properties": {
    "iso:country":"GB",
    "wof:name":"DL13 5RP",
    "wof:placetype":"postalcode"
},
  "geometry": {"coordinates":[-1.89824133697109,54.63135602382653],"type":"Point"}
}