{
  "type": "Feature",
  "properties": {
    "date:inception_lower":"1980-01-01",
    "date:inception_upper":"1980-01-31",
    "iso:country":"GB",
    "wof:name":"DL13 5RP",
    "wof:placetype":"postalcode"
},
  "geometry": {"coordinates":[-1.898241,54.631356],"type":"Point"}
}