{
  "type": "Feature",
  "properties": {
    "iso:country":"GB",
    "wof:name":"NG31 7JG",
    "wof:placetype":"postalcode"
},
  "geometry": {"coordinates":[-0.65247472101474,52.89632728722754],"type":"Point"}
}