{
  "type": "Feature",
  "properties": {
    "date:inception_lower": "1980-01-01",
    "date:inception_upper": "1980-01-01",
    "iso:country": "GB",
    "wof:name": "LN11 0LP",
    "wof:placetype": "postalcode"
  },
  "geometry": {"coordinates":[-0.006122,53.368045],"type":"Point"}
}
