{
  "type": "Feature",
  "properties": {
    "iso:country":"GB",
    "wof:name":"LN11 0LP",
    "wof:placetype":"postalcode"
},
  "geometry": {"coordinates":[-0.00609073153199,53.36802848881852],"type":"Point"}
}