{
  "type": "Feature",
  "properties": {
    "iso:country":"GB",
    "wof:name":"SW6 1JU",
    "wof:placetype":"postalcode"
},
  "geometry": {"coordinates":[-0.19797855485669,51.48353532518333],"type":"Point"}
}