{
  "type": "Feature",
  "properties": {
    "iso:country":"GB",
    "wof:name":"B92 8QA",
    "wof:placetype":"postalcode"
},
  "geometry": {"coordinates":[-1.792379547623,52.4416000079533],"type":"Point"}
}