{
  "type": "Feature",
  "properties": {
    "date:inception_lower": "1980-01-01",
    "date:inception_upper": "1980-01-01",
    "iso:country": "GB",
    "wof:name": "B92 8QA",
    "wof:placetype": "postalcode"
  },
  "geometry": {"coordinates":[-1.79238,52.4416],"type":"Point"}
}
