{
  "type": "Feature",
  "properties": {
    "date:inception_lower": "2019-01-01",
    "date:inception_upper": "2019-01-01",
    "iso:country": "GB",
    "wof:name": "EH11 4FA",
    "wof:placetype": "postalcode"
  },
  "geometry": {"coordinates":[-3.295653,55.92113],"type":"Point"}
}
