{
  "type": "Feature",
  "properties": {
    "iso:country": "GB",
    "wof:name": "EH11 4FA",
    "wof:placetype": "postalcode"
  },
  "geometry": {"coordinates":[-3.295653,55.92113],"type":"Point"}
}
