{
  "type": "Feature",
  "properties": {
    "iso:country":"GB",
    "wof:name":"S6 3NE",
    "wof:placetype":"postalcode"
},
  "geometry": {"coordinates":[-1.49150932603293,53.38996940251765],"type":"Point"}
}