{
  "type": "Feature",
  "properties": {
    "date:inception_lower":"1980-01-01",
    "date:inception_upper":"1980-01-31",
    "iso:country":"GB",
    "wof:name":"TS21 1LN",
    "wof:placetype":"postalcode"
},
  "geometry": {"coordinates":[-1.411514,54.590302],"type":"Point"}
}