{
  "type": "Feature",
  "properties": {
    "iso:country":"GB",
    "wof:name":"TS21 1LN",
    "wof:placetype":"postalcode"
},
  "geometry": {"coordinates":[-1.4115138670166,54.59030194168487],"type":"Point"}
}