{
  "type": "Feature",
  "properties": {
    "iso:country": "GB",
    "wof:name": "TS21 1LN",
    "wof:placetype": "postalcode"
  },
  "geometry": {"coordinates":[-1.411514,54.590302],"type":"Point"}
}
