{
  "type": "Feature",
  "properties": {
    "date:inception_lower": "2008-11-01",
    "date:inception_upper": "2008-11-01",
    "iso:country": "GB",
    "wof:name": "CR0 2NS",
    "wof:placetype": "postalcode"
  },
  "geometry": {"coordinates":[-0.110009,51.386235],"type":"Point"}
}
