{
  "type": "Feature",
  "properties": {
    "iso:country": "GB",
    "wof:name": "IP3 9EY",
    "wof:placetype": "postalcode"
  },
  "geometry": {"coordinates":[1.187465,52.040619],"type":"Point"}
}
