{
  "type": "Feature",
  "properties": {
    "iso:country": "GB",
    "wof:name": "TN27 9EJ",
    "wof:placetype": "postalcode"
  },
  "geometry": {"coordinates":[0.707857,51.18515],"type":"Point"}
}
