{
  "type": "Feature",
  "properties": {
    "iso:country":"GB",
    "wof:name":"TN27 9EJ",
    "wof:placetype":"postalcode"
},
  "geometry": {"coordinates":[0.70785654587102,51.18514967006384],"type":"Point"}
}