{
  "type": "Feature",
  "properties": {
    "date:inception_lower": "2018-03-01",
    "date:inception_upper": "2018-03-01",
    "iso:country": "GB",
    "wof:name": "W4 9HG",
    "wof:placetype": "postalcode"
  },
  "geometry": {"coordinates":[-0.262564,51.491534],"type":"Point"}
}
