{
  "type": "Feature",
  "properties": {
    "iso:country":"GB",
    "wof:name":"NG34 8QQ",
    "wof:placetype":"postalcode"
},
  "geometry": {"coordinates":[-0.4748810509812,52.99798884705055],"type":"Point"}
}