{
  "type": "Feature",
  "properties": {
    "iso:country": "GB",
    "wof:name": "NG34 8QQ",
    "wof:placetype": "postalcode"
  },
  "geometry": {"coordinates":[-0.474881,52.997989],"type":"Point"}
}
