{
  "type": "Feature",
  "properties": {
    "iso:country":"GB",
    "wof:name":"NN8 5YJ",
    "wof:placetype":"postalcode"
},
  "geometry": {"coordinates":[-0.71296924659875,52.31325402154711],"type":"Point"}
}