{
  "type": "Feature",
  "properties": {
    "date:inception_lower": "1991-09-01",
    "date:inception_upper": "1991-09-01",
    "iso:country": "GB",
    "wof:name": "NN8 5YJ",
    "wof:placetype": "postalcode"
  },
  "geometry": {"coordinates":[-0.712969,52.313254],"type":"Point"}
}
