{
  "type": "Feature",
  "properties": {
    "iso:country":"GB",
    "wof:name":"RH10 7DX",
    "wof:placetype":"postalcode"
},
  "geometry": {"coordinates":[-0.15643461506405,51.11886169193996],"type":"Point"}
}