{
  "type": "Feature",
  "properties": {
    "iso:country": "GB",
    "wof:name": "NE9 6JH",
    "wof:placetype": "postalcode"
  },
  "geometry": {"coordinates":[-1.602242,54.928426],"type":"Point"}
}
