{
  "type": "Feature",
  "properties": {
    "iso:country":"GB",
    "wof:name":"CF10 5GU",
    "wof:placetype":"postalcode"
},
  "geometry": {"coordinates":[-3.17421894353005,51.4631353254429],"type":"Point"}
}