{
  "type": "Feature",
  "properties": {
    "iso:country": "GB",
    "wof:name": "CF10 5GU",
    "wof:placetype": "postalcode"
  },
  "geometry": {"coordinates":[-3.174219,51.463135],"type":"Point"}
}
