{
  "type": "Feature",
  "properties": {
    "date:inception_lower": "1980-01-01",
    "date:inception_upper": "1980-01-01",
    "iso:country": "GB",
    "wof:name": "BL6 5EF",
    "wof:placetype": "postalcode"
  },
  "geometry": {"coordinates":[-2.584196,53.593991],"type":"Point"}
}
