{
  "type": "Feature",
  "properties": {
    "iso:country":"GB",
    "wof:name":"BL6 5EF",
    "wof:placetype":"postalcode"
},
  "geometry": {"coordinates":[-2.58427339679511,53.59401093410166],"type":"Point"}
}