{
  "type": "Feature",
  "properties": {
    "date:inception_lower": "1980-01-01",
    "date:inception_upper": "1980-01-01",
    "iso:country": "GB",
    "wof:name": "LE11 2JP",
    "wof:placetype": "postalcode"
  },
  "geometry": {"coordinates":[-1.20544,52.754861],"type":"Point"}
}
