{
  "type": "Feature",
  "properties": {
    "date:inception_lower": "1991-01-01",
    "date:inception_upper": "1991-01-01",
    "iso:country": "GB",
    "wof:name": "DH1 5FJ",
    "wof:placetype": "postalcode"
  },
  "geometry": {"coordinates":[-1.582037,54.804507],"type":"Point"}
}
