{
  "type": "Feature",
  "properties": {
    "iso:country":"GB",
    "wof:name":"RG27 0PD",
    "wof:placetype":"postalcode"
},
  "geometry": {"coordinates":[-0.8554436508317,51.34369629840241],"type":"Point"}
}