{
  "type": "Feature",
  "properties": {
    "iso:country":"GB",
    "wof:name":"KT9 2SW",
    "wof:placetype":"postalcode"
},
  "geometry": {"coordinates":[-0.31505501622195,51.35684586061304],"type":"Point"}
}