{
  "type": "Feature",
  "properties": {
    "iso:country":"GB",
    "wof:name":"W1W 7AY",
    "wof:placetype":"postalcode"
},
  "geometry": {"coordinates":[-0.14124717271684,51.51893460689828],"type":"Point"}
}