{
  "type": "Feature",
  "properties": {
    "iso:country": "GB",
    "wof:name": "SN11 0BQ",
    "wof:placetype": "postalcode"
  },
  "geometry": {"coordinates":[-2.002828,51.433123],"type":"Point"}
}
