{
  "type": "Feature",
  "properties": {
    "iso:country":"GB",
    "wof:name":"EN8 0JA",
    "wof:placetype":"postalcode"
},
  "geometry": {"coordinates":[-0.0502823789379,51.71135351063847],"type":"Point"}
}