{
  "type": "Feature",
  "properties": {
    "iso:country": "GB",
    "wof:name": "NR33 7SD",
    "wof:placetype": "postalcode"
  },
  "geometry": {"coordinates":[1.726905,52.414045],"type":"Point"}
}
