{
  "type": "Feature",
  "properties": {
    "iso:country":"GB",
    "wof:name":"NR33 7SD",
    "wof:placetype":"postalcode"
},
  "geometry": {"coordinates":[1.7268767417425,52.41417298013699],"type":"Point"}
}