{
  "type": "Feature",
  "properties": {
    "iso:country":"GB",
    "wof:name":"BH8 0QA",
    "wof:placetype":"postalcode"
},
  "geometry": {"coordinates":[-1.84662389406784,50.75310335216552],"type":"Point"}
}