{
  "type": "Feature",
  "properties": {
    "date:inception_lower": "1984-02-01",
    "date:inception_upper": "1984-02-01",
    "iso:country": "GB",
    "wof:name": "BH8 0QA",
    "wof:placetype": "postalcode"
  },
  "geometry": {"coordinates":[-1.846624,50.753103],"type":"Point"}
}
