{
  "type": "Feature",
  "properties": {
    "iso:country": "GB",
    "wof:name": "BH8 0QA",
    "wof:placetype": "postalcode"
  },
  "geometry": {"coordinates":[-1.846624,50.753103],"type":"Point"}
}
