{
  "type": "Feature",
  "properties": {
    "iso:country":"GB",
    "wof:name":"G69 7SD",
    "wof:placetype":"postalcode"
},
  "geometry": {"coordinates":[-4.07485197214834,55.85140700519483],"type":"Point"}
}