{
  "type": "Feature",
  "properties": {
    "iso:country": "GB",
    "wof:name": "G69 7SD",
    "wof:placetype": "postalcode"
  },
  "geometry": {"coordinates":[-4.074852,55.851407],"type":"Point"}
}
