{
  "type": "Feature",
  "properties": {
    "date:inception_lower": "2023-07-01",
    "date:inception_upper": "2023-07-01",
    "iso:country": "GB",
    "wof:name": "CA10 2FU",
    "wof:placetype": "postalcode"
  },
  "geometry": {"coordinates":[-2.716173,54.606128],"type":"Point"}
}
