{
  "type": "Feature",
  "properties": {
    "iso:country": "GB",
    "wof:name": "KT19 9HJ",
    "wof:placetype": "postalcode"
  },
  "geometry": {"coordinates":[-0.287529,51.362058],"type":"Point"}
}
