{
  "type": "Feature",
  "properties": {
    "iso:country":"GB",
    "wof:name":"KT19 9HJ",
    "wof:placetype":"postalcode"
},
  "geometry": {"coordinates":[-0.28752863641183,51.36205807336771],"type":"Point"}
}