{
  "type": "Feature",
  "properties": {
    "iso:country":"GB",
    "wof:name":"OL8 1PQ",
    "wof:placetype":"postalcode"
},
  "geometry": {"coordinates":[-2.10802067123812,53.52987379106222],"type":"Point"}
}