{
  "type": "Feature",
  "properties": {
    "iso:country":"GB",
    "wof:name":"WS9 8XE",
    "wof:placetype":"postalcode"
},
  "geometry": {"coordinates":[-1.9166148769973,52.62205361882447],"type":"Point"}
}