{
  "type": "Feature",
  "properties": {
    "date:inception_lower": "1980-01-01",
    "date:inception_upper": "1980-01-01",
    "iso:country": "GB",
    "wof:name": "WS9 8XE",
    "wof:placetype": "postalcode"
  },
  "geometry": {"coordinates":[-1.916615,52.622054],"type":"Point"}
}
