{
  "type": "Feature",
  "properties": {
    "iso:country": "GB",
    "wof:name": "WS9 8XE",
    "wof:placetype": "postalcode"
  },
  "geometry": {"coordinates":[-1.916615,52.622054],"type":"Point"}
}
