{
  "type": "Feature",
  "properties": {
    "iso:country":"GB",
    "wof:name":"TR18 3BL",
    "wof:placetype":"postalcode"
},
  "geometry": {"coordinates":[-5.5215339974211,50.13303748368249],"type":"Point"}
}