{
  "type": "Feature",
  "properties": {
    "date:inception_lower":"1980-01-01",
    "date:inception_upper":"1980-01-31",
    "iso:country":"GB",
    "wof:name":"TR18 3BL",
    "wof:placetype":"postalcode"
},
  "geometry": {"coordinates":[-5.521534,50.133037],"type":"Point"}
}