{
  "type": "Feature",
  "properties": {
    "iso:country": "GB",
    "wof:name": "PL26 8EN",
    "wof:placetype": "postalcode"
  },
  "geometry": {"coordinates":[-4.832327,50.405868],"type":"Point"}
}
