{
  "type": "Feature",
  "properties": {
    "iso:country":"GB",
    "wof:name":"PL26 8EN",
    "wof:placetype":"postalcode"
},
  "geometry": {"coordinates":[-4.83232740740361,50.40586823454127],"type":"Point"}
}