{
  "type": "Feature",
  "properties": {
    "iso:country":"GB",
    "wof:name":"ML2 8JD",
    "wof:placetype":"postalcode"
},
  "geometry": {"coordinates":[-3.90722763192187,55.77135189092913],"type":"Point"}
}