{
  "type": "Feature",
  "properties": {
    "iso:country":"GB",
    "wof:name":"N17 6XJ",
    "wof:placetype":"postalcode"
},
  "geometry": {"coordinates":[-0.07503380820787,51.59024746615994],"type":"Point"}
}