{
  "type": "Feature",
  "properties": {
    "iso:country": "GB",
    "wof:name": "SS8 0PR",
    "wof:placetype": "postalcode"
  },
  "geometry": {"coordinates":[0.556461,51.522033],"type":"Point"}
}
