{
  "type": "Feature",
  "properties": {
    "iso:country":"GB",
    "wof:name":"SS8 0PR",
    "wof:placetype":"postalcode"
},
  "geometry": {"coordinates":[0.5564610195816,51.52203306134807],"type":"Point"}
}