{
  "type": "Feature",
  "properties": {
    "date:inception_lower": "2002-06-01",
    "date:inception_upper": "2002-06-01",
    "iso:country": "GB",
    "wof:name": "GU21 8XF",
    "wof:placetype": "postalcode"
  },
  "geometry": {"coordinates":[-0.612234,51.310458],"type":"Point"}
}
