{
  "type": "Feature",
  "properties": {
    "iso:country":"GB",
    "wof:name":"EN3 4HF",
    "wof:placetype":"postalcode"
},
  "geometry": {"coordinates":[-0.04683277912141,51.64792683853758],"type":"Point"}
}