{
  "type": "Feature",
  "properties": {
    "iso:country":"GB",
    "wof:name":"CA7 3DY",
    "wof:placetype":"postalcode"
},
  "geometry": {"coordinates":[-3.31487285627357,54.76952052029215],"type":"Point"}
}