{
  "type": "Feature",
  "properties": {
    "iso:country": "GB",
    "wof:name": "CA7 3DY",
    "wof:placetype": "postalcode"
  },
  "geometry": {"coordinates":[-3.314843,54.769528],"type":"Point"}
}
