{
  "type": "Feature",
  "properties": {
    "date:inception_lower": "2000-06-01",
    "date:inception_upper": "2000-06-01",
    "iso:country": "GB",
    "wof:name": "CA7 3DY",
    "wof:placetype": "postalcode"
  },
  "geometry": {"coordinates":[-3.314843,54.769528],"type":"Point"}
}
