{
  "type": "Feature",
  "properties": {
    "iso:country":"GB",
    "wof:name":"B97 5DX",
    "wof:placetype":"postalcode"
},
  "geometry": {"coordinates":[-1.94818631572378,52.29075429000346],"type":"Point"}
}