{
  "type": "Feature",
  "properties": {
    "iso:country":"GB",
    "wof:name":"HX3 7QT",
    "wof:placetype":"postalcode"
},
  "geometry": {"coordinates":[-1.80954928592219,53.75519574591043],"type":"Point"}
}