{
  "type": "Feature",
  "properties": {
    "iso:country":"GB",
    "wof:name":"PE25 2SG",
    "wof:placetype":"postalcode"
},
  "geometry": {"coordinates":[0.33708421111576,53.14484130590423],"type":"Point"}
}