{
  "type": "Feature",
  "properties": {
    "iso:country":"GB",
    "wof:name":"DY8 3PS",
    "wof:placetype":"postalcode"
},
  "geometry": {"coordinates":[-2.17164741673015,52.45942110454939],"type":"Point"}
}