{
  "type": "Feature",
  "properties": {
    "iso:country":"GB",
    "wof:name":"PE1 3XU",
    "wof:placetype":"postalcode"
},
  "geometry": {"coordinates":[-0.24504305963273,52.60004125180221],"type":"Point"}
}