{
  "type": "Feature",
  "properties": {
    "date:inception_lower": "1984-10-01",
    "date:inception_upper": "1984-10-01",
    "iso:country": "GB",
    "wof:name": "PR1 7HT",
    "wof:placetype": "postalcode"
  },
  "geometry": {"coordinates":[-2.710126,53.766526],"type":"Point"}
}
