{
  "type": "Feature",
  "properties": {
    "iso:country":"GB",
    "wof:name":"PR1 7HT",
    "wof:placetype":"postalcode"
},
  "geometry": {"coordinates":[-2.7101262587578,53.76652626079705],"type":"Point"}
}