{
  "type": "Feature",
  "properties": {
    "iso:country":"GB",
    "wof:name":"L40 5XE",
    "wof:placetype":"postalcode"
},
  "geometry": {"coordinates":[-2.82210653829088,53.59110266804937],"type":"Point"}
}