{
  "type": "Feature",
  "properties": {
    "date:inception_lower": "1980-01-01",
    "date:inception_upper": "1980-01-01",
    "iso:country": "GB",
    "wof:name": "NG15 7JG",
    "wof:placetype": "postalcode"
  },
  "geometry": {"coordinates":[-1.206446,53.034965],"type":"Point"}
}
