{
  "type": "Feature",
  "properties": {
    "iso:country":"GB",
    "wof:name":"NG15 7JG",
    "wof:placetype":"postalcode"
},
  "geometry": {"coordinates":[-1.20644641313407,53.03496484663864],"type":"Point"}
}