{
  "type": "Feature",
  "properties": {
    "date:inception_lower":"1980-01-01",
    "date:inception_upper":"1980-01-31",
    "iso:country":"GB",
    "wof:name":"CW10 0NS",
    "wof:placetype":"postalcode"
},
  "geometry": {"coordinates":[-2.450044,53.181931],"type":"Point"}
}