{
  "type": "Feature",
  "properties": {
    "iso:country":"GB",
    "wof:name":"CW10 0NS",
    "wof:placetype":"postalcode"
},
  "geometry": {"coordinates":[-2.45004400514226,53.18193119803787],"type":"Point"}
}