{
  "type": "Feature",
  "properties": {
    "iso:country":"GB",
    "wof:name":"SN12 6GA",
    "wof:placetype":"postalcode"
},
  "geometry": {"coordinates":[-2.12570569359169,51.37029378536299],"type":"Point"}
}