{
  "type": "Feature",
  "properties": {
    "iso:country": "GB",
    "wof:name": "M19 1FF",
    "wof:placetype": "postalcode"
  },
  "geometry": {"coordinates":[-2.201517,53.433585],"type":"Point"}
}
