{
  "type": "Feature",
  "properties": {
    "iso:country":"GB",
    "wof:name":"M19 1FF",
    "wof:placetype":"postalcode"
},
  "geometry": {"coordinates":[-2.20151727200207,53.43358515662635],"type":"Point"}
}