{
  "type": "Feature",
  "properties": {
    "iso:country":"GB",
    "wof:name":"BD3 7FG",
    "wof:placetype":"postalcode"
},
  "geometry": {"coordinates":[-1.70314588723729,53.79768181285227],"type":"Point"}
}