{
  "type": "Feature",
  "properties": {
    "iso:country":"GB",
    "wof:name":"M6 8ES",
    "wof:placetype":"postalcode"
},
  "geometry": {"coordinates":[-2.32518854809445,53.48963421730513],"type":"Point"}
}