{
  "type": "Feature",
  "properties": {
    "iso:country": "GB",
    "wof:name": "HG1 5NL",
    "wof:placetype": "postalcode"
  },
  "geometry": {"coordinates":[-1.531132,53.995316],"type":"Point"}
}
