{
  "type": "Feature",
  "properties": {
    "iso:country":"GB",
    "wof:name":"HG1 5NL",
    "wof:placetype":"postalcode"
},
  "geometry": {"coordinates":[-1.53113178936595,53.99531622739154],"type":"Point"}
}