{
  "type": "Feature",
  "properties": {
    "iso:country": "GB",
    "wof:name": "E4 7DS",
    "wof:placetype": "postalcode"
  },
  "geometry": {"coordinates":[0.002368,51.632755],"type":"Point"}
}
