{
  "type": "Feature",
  "properties": {
    "iso:country":"GB",
    "wof:name":"KY8 6DR",
    "wof:placetype":"postalcode"
},
  "geometry": {"coordinates":[-2.94091914543602,56.21436577479066],"type":"Point"}
}