{
  "type": "Feature",
  "properties": {
    "iso:country": "GB",
    "wof:name": "KY8 6DR",
    "wof:placetype": "postalcode"
  },
  "geometry": {"coordinates":[-2.940919,56.214366],"type":"Point"}
}
