{
  "type": "Feature",
  "properties": {
    "date:inception_lower": "2002-06-01",
    "date:inception_upper": "2002-06-01",
    "iso:country": "GB",
    "wof:name": "PO19 8SX",
    "wof:placetype": "postalcode"
  },
  "geometry": {"coordinates":[-0.787338,50.822946],"type":"Point"}
}
