{
  "type": "Feature",
  "properties": {
    "iso:country":"GB",
    "wof:name":"PO19 8SX",
    "wof:placetype":"postalcode"
},
  "geometry": {"coordinates":[-0.7873382946725,50.82294615165508],"type":"Point"}
}