{
  "type": "Feature",
  "properties": {
    "iso:country": "GB",
    "wof:name": "NN16 9QD",
    "wof:placetype": "postalcode"
  },
  "geometry": {"coordinates":[-0.711122,52.407112],"type":"Point"}
}
