{
  "type": "Feature",
  "properties": {
    "iso:country":"GB",
    "wof:name":"HA1 3AJ",
    "wof:placetype":"postalcode"
},
  "geometry": {"coordinates":[-0.33903772071556,51.57777084029047],"type":"Point"}
}