{
  "type": "Feature",
  "properties": {
    "iso:country": "GB",
    "wof:name": "NR20 3GJ",
    "wof:placetype": "postalcode"
  },
  "geometry": {"coordinates":[0.966996,52.682845],"type":"Point"}
}
