{
  "type": "Feature",
  "properties": {
    "iso:country":"GB",
    "wof:name":"LE4 4AR",
    "wof:placetype":"postalcode"
},
  "geometry": {"coordinates":[-1.12640768355306,52.66879418259568],"type":"Point"}
}