{
  "type": "Feature",
  "properties": {
    "iso:country": "GB",
    "wof:name": "LE4 4AR",
    "wof:placetype": "postalcode"
  },
  "geometry": {"coordinates":[-1.126408,52.668794],"type":"Point"}
}
