{
  "type": "Feature",
  "properties": {
    "date:inception_lower": "1994-05-01",
    "date:inception_upper": "1994-05-01",
    "iso:country": "GB",
    "wof:name": "M20 6SP",
    "wof:placetype": "postalcode"
  },
  "geometry": {"coordinates":[-2.224584,53.420771],"type":"Point"}
}
