{
  "type": "Feature",
  "properties": {
    "iso:country":"GB",
    "wof:name":"LE5 0BA",
    "wof:placetype":"postalcode"
},
  "geometry": {"coordinates":[-1.0908684595027,52.64901871940737],"type":"Point"}
}