{
  "type": "Feature",
  "properties": {
    "iso:country": "GB",
    "wof:name": "LE5 0BA",
    "wof:placetype": "postalcode"
  },
  "geometry": {"coordinates":[-1.090868,52.649019],"type":"Point"}
}
