{
  "type": "Feature",
  "properties": {
    "iso:country":"GB",
    "wof:name":"SN12 7JQ",
    "wof:placetype":"postalcode"
},
  "geometry": {"coordinates":[-2.12554705974022,51.37531130483197],"type":"Point"}
}