{
  "type": "Feature",
  "properties": {
    "iso:country":"GB",
    "wof:name":"NP8 1PT",
    "wof:placetype":"postalcode"
},
  "geometry": {"coordinates":[-3.15262028456696,51.85881071122569],"type":"Point"}
}