{
  "type": "Feature",
  "properties": {
    "iso:country":"GB",
    "wof:name":"ML11 8RD",
    "wof:placetype":"postalcode"
},
  "geometry": {"coordinates":[-3.66472049929597,55.68921763156433],"type":"Point"}
}