{
  "type": "Feature",
  "properties": {
    "iso:country": "GB",
    "wof:name": "ML11 8RD",
    "wof:placetype": "postalcode"
  },
  "geometry": {"coordinates":[-3.66472,55.689218],"type":"Point"}
}
