{
  "type": "Feature",
  "properties": {
    "iso:country":"GB",
    "wof:name":"L1 7BY",
    "wof:placetype":"postalcode"
},
  "geometry": {"coordinates":[-2.973910378344,53.39634437509877],"type":"Point"}
}