{
  "type": "Feature",
  "properties": {
    "iso:country": "GB",
    "wof:name": "L1 7BY",
    "wof:placetype": "postalcode"
  },
  "geometry": {"coordinates":[-2.97391,53.396344],"type":"Point"}
}
