{
  "type": "Feature",
  "properties": {
    "date:inception_lower": "1999-06-01",
    "date:inception_upper": "1999-06-01",
    "iso:country": "GB",
    "wof:name": "L1 7BY",
    "wof:placetype": "postalcode"
  },
  "geometry": {"coordinates":[-2.97391,53.396344],"type":"Point"}
}
