{
  "type": "Feature",
  "properties": {
    "date:inception_lower":"1980-01-01",
    "date:inception_upper":"1980-01-31",
    "iso:country":"GB",
    "wof:name":"PH10 7DW",
    "wof:placetype":"postalcode"
},
  "geometry": {"coordinates":[-3.322517,56.596699],"type":"Point"}
}