{
  "type": "Feature",
  "properties": {
    "iso:country":"GB",
    "wof:name":"GL6 7JE",
    "wof:placetype":"postalcode"
},
  "geometry": {"coordinates":[-2.08889142052243,51.76345694883014],"type":"Point"}
}