{
  "type": "Feature",
  "properties": {
    "iso:country":"GB",
    "wof:name":"OX7 5PD",
    "wof:placetype":"postalcode"
},
  "geometry": {"coordinates":[-1.54134311180189,51.94539278628263],"type":"Point"}
}