{
  "type": "Feature",
  "properties": {
    "iso:country":"GB",
    "wof:name":"NP44 2EL",
    "wof:placetype":"postalcode"
},
  "geometry": {"coordinates":[-3.00934887737393,51.65908907223151],"type":"Point"}
}