{
  "type": "Feature",
  "properties": {
    "iso:country": "GB",
    "wof:name": "NP44 2EL",
    "wof:placetype": "postalcode"
  },
  "geometry": {"coordinates":[-3.009349,51.659089],"type":"Point"}
}
