{
  "type": "Feature",
  "properties": {
    "iso:country":"GB",
    "wof:name":"HA9 8JQ",
    "wof:placetype":"postalcode"
},
  "geometry": {"coordinates":[-0.28877044843975,51.5612492441464],"type":"Point"}
}