{
  "type": "Feature",
  "properties": {
    "iso:country": "GB",
    "wof:name": "BH14 0PR",
    "wof:placetype": "postalcode"
  },
  "geometry": {"coordinates":[-1.962729,50.72649],"type":"Point"}
}
