{
  "type": "Feature",
  "properties": {
    "iso:country": "GB",
    "wof:name": "AB15 9AT",
    "wof:placetype": "postalcode"
  },
  "geometry": {"coordinates":[-2.203979,57.113428],"type":"Point"}
}
