{
  "type": "Feature",
  "properties": {
    "iso:country": "GB",
    "wof:name": "AL2 3UP",
    "wof:placetype": "postalcode"
  },
  "geometry": {"coordinates":[-0.377435,51.707911],"type":"Point"}
}
