{
  "type": "Feature",
  "properties": {
    "iso:country":"GB",
    "wof:name":"DG11 3AJ",
    "wof:placetype":"postalcode"
},
  "geometry": {"coordinates":[-3.17004491967081,55.07806870413988],"type":"Point"}
}