{
  "type": "Feature",
  "properties": {
    "date:inception_lower":"1991-03-01",
    "date:inception_upper":"1991-03-31",
    "iso:country":"GB",
    "wof:name":"FK9 4DN",
    "wof:placetype":"postalcode"
},
  "geometry": {"coordinates":[-3.94639,56.15005],"type":"Point"}
}