{
  "type": "Feature",
  "properties": {
    "iso:country":"GB",
    "wof:name":"IP18 6UY",
    "wof:placetype":"postalcode"
},
  "geometry": {"coordinates":[1.65084846146868,52.31403447068949],"type":"Point"}
}