{
  "type": "Feature",
  "properties": {
    "iso:country":"GB",
    "wof:name":"IP4 3DH",
    "wof:placetype":"postalcode"
},
  "geometry": {"coordinates":[1.1824910881446,52.07118043025736],"type":"Point"}
}