{
  "type": "Feature",
  "properties": {
    "iso:country":"GB",
    "wof:name":"BS16 5FH",
    "wof:placetype":"postalcode"
},
  "geometry": {"coordinates":[-2.50952982496293,51.48213377988025],"type":"Point"}
}