{
  "type": "Feature",
  "properties": {
    "date:inception_lower":"2010-10-01",
    "date:inception_upper":"2010-10-31",
    "iso:country":"GB",
    "wof:name":"BS16 5FH",
    "wof:placetype":"postalcode"
},
  "geometry": {"coordinates":[-2.509473,51.482132],"type":"Point"}
}