{
  "type": "Feature",
  "properties": {
    "date:inception_lower": "1980-01-01",
    "date:inception_upper": "1980-01-01",
    "iso:country": "GB",
    "wof:name": "WR14 3PL",
    "wof:placetype": "postalcode"
  },
  "geometry": {"coordinates":[-2.31979,52.103205],"type":"Point"}
}
