{
  "type": "Feature",
  "properties": {
    "iso:country":"GB",
    "wof:name":"WR14 3PL",
    "wof:placetype":"postalcode"
},
  "geometry": {"coordinates":[-2.31979029651529,52.10320515159624],"type":"Point"}
}