{
  "type": "Feature",
  "properties": {
    "iso:country": "GB",
    "wof:name": "NE67 5BD",
    "wof:placetype": "postalcode"
  },
  "geometry": {"coordinates":[-1.629064,55.555841],"type":"Point"}
}
