{
  "type": "Feature",
  "properties": {
    "iso:country":"GB",
    "wof:name":"BD19 6LU",
    "wof:placetype":"postalcode"
},
  "geometry": {"coordinates":[-1.74797984078277,53.72120621224281],"type":"Point"}
}