{
  "type": "Feature",
  "properties": {
    "iso:country": "GB",
    "wof:name": "SK12 2HQ",
    "wof:placetype": "postalcode"
  },
  "geometry": {"coordinates":[-2.020725,53.356857],"type":"Point"}
}
