{
  "type": "Feature",
  "properties": {
    "iso:country":"GB",
    "wof:name":"DY13 8RD",
    "wof:placetype":"postalcode"
},
  "geometry": {"coordinates":[-2.29335214644042,52.34100662887849],"type":"Point"}
}