{
  "type": "Feature",
  "properties": {
    "date:inception_lower": "2004-08-01",
    "date:inception_upper": "2004-08-01",
    "iso:country": "GB",
    "wof:name": "L5 3BB",
    "wof:placetype": "postalcode"
  },
  "geometry": {"coordinates":[-2.975931,53.42288],"type":"Point"}
}
