{
  "type": "Feature",
  "properties": {
    "iso:country":"GB",
    "wof:name":"S64 9EZ",
    "wof:placetype":"postalcode"
},
  "geometry": {"coordinates":[-1.30574675198436,53.49726689849697],"type":"Point"}
}