{
  "type": "Feature",
  "properties": {
    "iso:country": "GB",
    "wof:name": "S64 9EZ",
    "wof:placetype": "postalcode"
  },
  "geometry": {"coordinates":[-1.305747,53.497267],"type":"Point"}
}
