{
  "type": "Feature",
  "properties": {
    "iso:country":"GB",
    "wof:name":"N8 7JJ",
    "wof:placetype":"postalcode"
},
  "geometry": {"coordinates":[-0.11922209797495,51.58539761567188],"type":"Point"}
}