{
  "type": "Feature",
  "properties": {
    "date:inception_lower": "1980-01-01",
    "date:inception_upper": "1980-01-01",
    "iso:country": "GB",
    "wof:name": "N8 7JJ",
    "wof:placetype": "postalcode"
  },
  "geometry": {"coordinates":[-0.119222,51.585398],"type":"Point"}
}
