{
  "type": "Feature",
  "properties": {
    "iso:country":"GB",
    "wof:name":"TW4 5LL",
    "wof:placetype":"postalcode"
},
  "geometry": {"coordinates":[-0.37494776141986,51.45294854901154],"type":"Point"}
}