{
  "type": "Feature",
  "properties": {
    "date:inception_lower": "1980-01-01",
    "date:inception_upper": "1980-01-01",
    "iso:country": "GB",
    "wof:name": "SM2 6BN",
    "wof:placetype": "postalcode"
  },
  "geometry": {"coordinates":[-0.200925,51.340921],"type":"Point"}
}
