{
  "type": "Feature",
  "properties": {
    "iso:country":"GB",
    "wof:name":"SM2 6BN",
    "wof:placetype":"postalcode"
},
  "geometry": {"coordinates":[-0.20092180723807,51.34090425680996],"type":"Point"}
}