{
  "type": "Feature",
  "properties": {
    "iso:country":"GB",
    "wof:name":"E1 4JU",
    "wof:placetype":"postalcode"
},
  "geometry": {"coordinates":[-0.0494447411929,51.52467390382541],"type":"Point"}
}