{
  "type": "Feature",
  "properties": {
    "iso:country": "GB",
    "wof:name": "CM7 5LF",
    "wof:placetype": "postalcode"
  },
  "geometry": {"coordinates":[0.55823,51.904602],"type":"Point"}
}
