{
  "type": "Feature",
  "properties": {
    "iso:country":"GB",
    "wof:name":"CM7 5LF",
    "wof:placetype":"postalcode"
},
  "geometry": {"coordinates":[0.55822971552902,51.90460165975858],"type":"Point"}
}