{
  "type": "Feature",
  "properties": {
    "iso:country": "GB",
    "wof:name": "NR20 4RS",
    "wof:placetype": "postalcode"
  },
  "geometry": {"coordinates":[1.021134,52.748115],"type":"Point"}
}
