{
  "type": "Feature",
  "properties": {
    "iso:country":"GB",
    "wof:name":"B60 1BU",
    "wof:placetype":"postalcode"
},
  "geometry": {"coordinates":[-2.01007078468954,52.35043305740216],"type":"Point"}
}