{
  "type": "Feature",
  "properties": {
    "date:inception_lower": "1995-07-01",
    "date:inception_upper": "1995-07-01",
    "iso:country": "GB",
    "wof:name": "RG40 4QY",
    "wof:placetype": "postalcode"
  },
  "geometry": {"coordinates":[-0.896852,51.375171],"type":"Point"}
}
