{
  "type": "Feature",
  "properties": {
    "iso:country":"GB",
    "wof:name":"RG40 4QY",
    "wof:placetype":"postalcode"
},
  "geometry": {"coordinates":[-0.8950824518005,51.37426311759718],"type":"Point"}
}