{
  "type": "Feature",
  "properties": {
    "iso:country": "GB",
    "wof:name": "NE3 4AE",
    "wof:placetype": "postalcode"
  },
  "geometry": {"coordinates":[-1.620665,55.00042],"type":"Point"}
}
