{
  "type": "Feature",
  "properties": {
    "iso:country":"GB",
    "wof:name":"NE3 4AE",
    "wof:placetype":"postalcode"
},
  "geometry": {"coordinates":[-1.62066458424846,55.00041984645139],"type":"Point"}
}