{
  "type": "Feature",
  "properties": {
    "date:inception_lower":"1980-01-01",
    "date:inception_upper":"1980-01-31",
    "iso:country":"GB",
    "wof:name":"PA2 6SZ",
    "wof:placetype":"postalcode"
},
  "geometry": {"coordinates":[-4.420421,55.83791],"type":"Point"}
}