{
  "type": "Feature",
  "properties": {
    "date:inception_lower": "1994-05-01",
    "date:inception_upper": "1994-05-01",
    "iso:country": "GB",
    "wof:name": "M27 5UU",
    "wof:placetype": "postalcode"
  },
  "geometry": {"coordinates":[-2.331156,53.506921],"type":"Point"}
}
