{
  "type": "Feature",
  "properties": {
    "iso:country":"GB",
    "wof:name":"M27 5UU",
    "wof:placetype":"postalcode"
},
  "geometry": {"coordinates":[-2.331155996895,53.50692059000199],"type":"Point"}
}