{
  "type": "Feature",
  "properties": {
    "iso:country":"GB",
    "wof:name":"DD5 3HY",
    "wof:placetype":"postalcode"
},
  "geometry": {"coordinates":[-2.86152658421597,56.47555060485833],"type":"Point"}
}