{
  "type": "Feature",
  "properties": {
    "iso:country":"GB",
    "wof:name":"ST7 4QR",
    "wof:placetype":"postalcode"
},
  "geometry": {"coordinates":[-2.20103631402804,53.07932875013171],"type":"Point"}
}