{
  "type": "Feature",
  "properties": {
    "date:inception_lower": "2018-12-01",
    "date:inception_upper": "2018-12-01",
    "iso:country": "GB",
    "wof:name": "SK14 5EA",
    "wof:placetype": "postalcode"
  },
  "geometry": {"coordinates":[-2.070496,53.444726],"type":"Point"}
}
