{
  "type": "Feature",
  "properties": {
    "iso:country": "GB",
    "wof:name": "CO9 1GB",
    "wof:placetype": "postalcode"
  },
  "geometry": {"coordinates":[0.630712,51.943483],"type":"Point"}
}
