{
  "type": "Feature",
  "properties": {
    "iso:country":"GB",
    "wof:name":"EX14 3EG",
    "wof:placetype":"postalcode"
},
  "geometry": {"coordinates":[-3.27927174726246,50.78811870223166],"type":"Point"}
}