{
  "type": "Feature",
  "properties": {
    "iso:country":"GB",
    "wof:name":"NP23 4NY",
    "wof:placetype":"postalcode"
},
  "geometry": {"coordinates":[-3.16866308410639,51.78357413210733],"type":"Point"}
}