{
  "type": "Feature",
  "properties": {
    "iso:country":"GB",
    "wof:name":"CW2 8NQ",
    "wof:placetype":"postalcode"
},
  "geometry": {"coordinates":[-2.46267770618126,53.09335873981281],"type":"Point"}
}