{
  "type": "Feature",
  "properties": {
    "iso:country":"GB",
    "wof:name":"G2 3NX",
    "wof:placetype":"postalcode"
},
  "geometry": {"coordinates":[-4.25194991634454,55.86464917841931],"type":"Point"}
}