{
  "type": "Feature",
  "properties": {
    "iso:country":"GB",
    "wof:name":"PO35 5UD",
    "wof:placetype":"postalcode"
},
  "geometry": {"coordinates":[-1.08354106009113,50.68693347560595],"type":"Point"}
}