{
  "type": "Feature",
  "properties": {
    "iso:country": "GB",
    "wof:name": "PO35 5UD",
    "wof:placetype": "postalcode"
  },
  "geometry": {"coordinates":[-1.0835,50.686949],"type":"Point"}
}
