{
  "type": "Feature",
  "properties": {
    "iso:country":"GB",
    "wof:name":"BD2 3SB",
    "wof:placetype":"postalcode"
},
  "geometry": {"coordinates":[-1.72637974475534,53.81546130149439],"type":"Point"}
}