{
  "type": "Feature",
  "properties": {
    "iso:country":"GB",
    "wof:name":"TS18 5JT",
    "wof:placetype":"postalcode"
},
  "geometry": {"coordinates":[-1.35733137456079,54.55807782666419],"type":"Point"}
}