{
  "type": "Feature",
  "properties": {
    "iso:country":"GB",
    "wof:name":"HA3 0TS",
    "wof:placetype":"postalcode"
},
  "geometry": {"coordinates":[-0.29553314730462,51.58372039638908],"type":"Point"}
}