{
  "type": "Feature",
  "properties": {
    "iso:country": "GB",
    "wof:name": "HA3 0TS",
    "wof:placetype": "postalcode"
  },
  "geometry": {"coordinates":[-0.295533,51.58372],"type":"Point"}
}
