{
  "type": "Feature",
  "properties": {
    "iso:country": "GB",
    "wof:name": "IP24 3EF",
    "wof:placetype": "postalcode"
  },
  "geometry": {"coordinates":[0.748638,52.406208],"type":"Point"}
}
