{
  "type": "Feature",
  "properties": {
    "iso:country": "GB",
    "wof:name": "DN17 3TN",
    "wof:placetype": "postalcode"
  },
  "geometry": {"coordinates":[-0.650495,53.529304],"type":"Point"}
}
