{
  "type": "Feature",
  "properties": {
    "iso:country":"GB",
    "wof:name":"DN17 3TN",
    "wof:placetype":"postalcode"
},
  "geometry": {"coordinates":[-0.65049507090292,53.52930354687974],"type":"Point"}
}