{
  "type": "Feature",
  "properties": {
    "date:inception_lower":"1980-01-01",
    "date:inception_upper":"1980-01-31",
    "iso:country":"GB",
    "wof:name":"DN17 3TN",
    "wof:placetype":"postalcode"
},
  "geometry": {"coordinates":[-0.650495,53.529304],"type":"Point"}
}