{
  "type": "Feature",
  "properties": {
    "iso:country":"GB",
    "wof:name":"SE3 7HF",
    "wof:placetype":"postalcode"
},
  "geometry": {"coordinates":[0.02141910545283,51.47931080826277],"type":"Point"}
}