{
  "type": "Feature",
  "properties": {
    "iso:country": "GB",
    "wof:name": "PE28 4WT",
    "wof:placetype": "postalcode"
  },
  "geometry": {"coordinates":[-0.261281,52.365247],"type":"Point"}
}
