{
  "type": "Feature",
  "properties": {
    "iso:country":"GB",
    "wof:name":"BA6 8LL",
    "wof:placetype":"postalcode"
},
  "geometry": {"coordinates":[-2.69003808704144,51.137620722464],"type":"Point"}
}