{
  "type": "Feature",
  "properties": {
    "iso:country":"GB",
    "wof:name":"NR21 8LE",
    "wof:placetype":"postalcode"
},
  "geometry": {"coordinates":[0.8641505069838,52.83689426608551],"type":"Point"}
}