{
  "type": "Feature",
  "properties": {
    "iso:country": "GB",
    "wof:name": "NR21 8LE",
    "wof:placetype": "postalcode"
  },
  "geometry": {"coordinates":[0.864064,52.836913],"type":"Point"}
}
