{
  "type": "Feature",
  "properties": {
    "date:inception_lower":"2005-02-01",
    "date:inception_upper":"2005-02-28",
    "iso:country":"GB",
    "wof:name":"NR21 8LE",
    "wof:placetype":"postalcode"
},
  "geometry": {"coordinates":[0.864064,52.836913],"type":"Point"}
}