{
  "type": "Feature",
  "properties": {
    "date:inception_lower": "2008-04-01",
    "date:inception_upper": "2008-04-01",
    "iso:country": "GB",
    "wof:name": "NR20 4FB",
    "wof:placetype": "postalcode"
  },
  "geometry": {"coordinates":[0.89082,52.736034],"type":"Point"}
}
