{
  "type": "Feature",
  "properties": {
    "iso:country": "GB",
    "wof:name": "TR8 4FJ",
    "wof:placetype": "postalcode"
  },
  "geometry": {"coordinates":[-5.040554,50.412141],"type":"Point"}
}
