{
  "type": "Feature",
  "properties": {
    "iso:country": "GB",
    "wof:name": "ME13 9DS",
    "wof:placetype": "postalcode"
  },
  "geometry": {"coordinates":[0.935383,51.326879],"type":"Point"}
}
