{
  "type": "Feature",
  "properties": {
    "iso:country": "GB",
    "wof:name": "E7 0QX",
    "wof:placetype": "postalcode"
  },
  "geometry": {"coordinates":[0.029243,51.547826],"type":"Point"}
}
