{
  "type": "Feature",
  "properties": {
    "iso:country":"GB",
    "wof:name":"E7 0QX",
    "wof:placetype":"postalcode"
},
  "geometry": {"coordinates":[0.0292432147592,51.54782599902919],"type":"Point"}
}