{
  "type": "Feature",
  "properties": {
    "iso:country": "GB",
    "wof:name": "SY2 5SW",
    "wof:placetype": "postalcode"
  },
  "geometry": {"coordinates":[-2.724468,52.717532],"type":"Point"}
}
