{
  "type": "Feature",
  "properties": {
    "iso:country":"GB",
    "wof:name":"SY2 5SW",
    "wof:placetype":"postalcode"
},
  "geometry": {"coordinates":[-2.72446795381316,52.71753190564213],"type":"Point"}
}