{
  "type": "Feature",
  "properties": {
    "date:inception_lower": "1980-01-01",
    "date:inception_upper": "1980-01-01",
    "iso:country": "GB",
    "wof:name": "SM6 8JE",
    "wof:placetype": "postalcode"
  },
  "geometry": {"coordinates":[-0.1357,51.368697],"type":"Point"}
}
