{
  "type": "Feature",
  "properties": {
    "iso:country":"GB",
    "wof:name":"OL3 5BW",
    "wof:placetype":"postalcode"
},
  "geometry": {"coordinates":[-2.02018815385383,53.55409970880837],"type":"Point"}
}