{
  "type": "Feature",
  "properties": {
    "iso:country":"GB",
    "wof:name":"E10 7JP",
    "wof:placetype":"postalcode"
},
  "geometry": {"coordinates":[-0.02254546860423,51.56756783252901],"type":"Point"}
}