{
  "type": "Feature",
  "properties": {
    "iso:country":"GB",
    "wof:name":"SL7 2ZU",
    "wof:placetype":"postalcode"
},
  "geometry": {"coordinates":[-0.7751657756144,51.57079546829885],"type":"Point"}
}