{
  "type": "Feature",
  "properties": {
    "date:inception_lower": "1980-01-01",
    "date:inception_upper": "1980-01-01",
    "iso:country": "GB",
    "wof:name": "LA1 2SB",
    "wof:placetype": "postalcode"
  },
  "geometry": {"coordinates":[-2.81596,54.060184],"type":"Point"}
}
