{
  "type": "Feature",
  "properties": {
    "iso:country":"GB",
    "wof:name":"LA1 2SB",
    "wof:placetype":"postalcode"
},
  "geometry": {"coordinates":[-2.81596035411884,54.06018442271054],"type":"Point"}
}