{
  "type": "Feature",
  "properties": {
    "iso:country":"GB",
    "wof:name":"KT22 7UA",
    "wof:placetype":"postalcode"
},
  "geometry": {"coordinates":[-0.33694989539545,51.30231314210945],"type":"Point"}
}