{
  "type": "Feature",
  "properties": {
    "iso:country":"GB",
    "wof:name":"BA3 4DG",
    "wof:placetype":"postalcode"
},
  "geometry": {"coordinates":[-2.53426025205522,51.2863906326866],"type":"Point"}
}