{
  "type": "Feature",
  "properties": {
    "iso:country":"GB",
    "wof:name":"PO40 9UP",
    "wof:placetype":"postalcode"
},
  "geometry": {"coordinates":[-1.52612317485417,50.68302512185178],"type":"Point"}
}