{
  "type": "Feature",
  "properties": {
    "date:inception_lower": "1980-01-01",
    "date:inception_upper": "1980-01-01",
    "iso:country": "GB",
    "wof:name": "TN3 0NP",
    "wof:placetype": "postalcode"
  },
  "geometry": {"coordinates":[0.219666,51.149451],"type":"Point"}
}
