{
  "type": "Feature",
  "properties": {
    "iso:country": "GB",
    "wof:name": "TS23 2HQ",
    "wof:placetype": "postalcode"
  },
  "geometry": {"coordinates":[-1.285604,54.609054],"type":"Point"}
}
