{
  "type": "Feature",
  "properties": {
    "iso:country":"GB",
    "wof:name":"TS23 2HQ",
    "wof:placetype":"postalcode"
},
  "geometry": {"coordinates":[-1.28560396280334,54.60905445577203],"type":"Point"}
}