{
  "type": "Feature",
  "properties": {
    "iso:country":"GB",
    "wof:name":"NN5 6XW",
    "wof:placetype":"postalcode"
},
  "geometry": {"coordinates":[-0.95726232751981,52.25256646564932],"type":"Point"}
}