{
  "type": "Feature",
  "properties": {
    "iso:country": "GB",
    "wof:name": "NN5 6XW",
    "wof:placetype": "postalcode"
  },
  "geometry": {"coordinates":[-0.957262,52.252566],"type":"Point"}
}
