{
  "type": "Feature",
  "properties": {
    "date:inception_lower": "1980-01-01",
    "date:inception_upper": "1980-01-01",
    "iso:country": "GB",
    "wof:name": "NN5 6XW",
    "wof:placetype": "postalcode"
  },
  "geometry": {"coordinates":[-0.957262,52.252566],"type":"Point"}
}
