{
  "type": "Feature",
  "properties": {
    "date:inception_lower": "1980-01-01",
    "date:inception_upper": "1980-01-01",
    "iso:country": "GB",
    "wof:name": "KA22 7BQ",
    "wof:placetype": "postalcode"
  },
  "geometry": {"coordinates":[-4.803237,55.649521],"type":"Point"}
}
