{
  "type": "Feature",
  "properties": {
    "iso:country":"GB",
    "wof:name":"RG4 7XB",
    "wof:placetype":"postalcode"
},
  "geometry": {"coordinates":[-0.98696024587517,51.48358039227337],"type":"Point"}
}