{
  "type": "Feature",
  "properties": {
    "date:inception_lower": "1994-05-01",
    "date:inception_upper": "1994-05-01",
    "iso:country": "GB",
    "wof:name": "RG4 7XB",
    "wof:placetype": "postalcode"
  },
  "geometry": {"coordinates":[-0.98696,51.48358],"type":"Point"}
}
