{
  "type": "Feature",
  "properties": {
    "iso:country": "GB",
    "wof:name": "HR6 8DD",
    "wof:placetype": "postalcode"
  },
  "geometry": {"coordinates":[-2.739717,52.22956],"type":"Point"}
}
