{
  "type": "Feature",
  "properties": {
    "iso:country":"GB",
    "wof:name":"HR6 8DD",
    "wof:placetype":"postalcode"
},
  "geometry": {"coordinates":[-2.73971666335216,52.2295596906095],"type":"Point"}
}