{
  "type": "Feature",
  "properties": {
    "iso:country": "GB",
    "wof:name": "CT5 4SL",
    "wof:placetype": "postalcode"
  },
  "geometry": {"coordinates":[1.00458,51.345118],"type":"Point"}
}
