{
  "type": "Feature",
  "properties": {
    "date:inception_lower": "1985-04-01",
    "date:inception_upper": "1985-04-01",
    "iso:country": "GB",
    "wof:name": "CT5 4SL",
    "wof:placetype": "postalcode"
  },
  "geometry": {"coordinates":[1.00458,51.345118],"type":"Point"}
}
