{
  "type": "Feature",
  "properties": {
    "iso:country":"GB",
    "wof:name":"CT5 4SL",
    "wof:placetype":"postalcode"
},
  "geometry": {"coordinates":[1.00458035123815,51.34511774427378],"type":"Point"}
}