{
  "type": "Feature",
  "properties": {
    "iso:country":"GB",
    "wof:name":"NW3 7SL",
    "wof:placetype":"postalcode"
},
  "geometry": {"coordinates":[-0.18867802609329,51.55792138938788],"type":"Point"}
}