{
  "type": "Feature",
  "properties": {
    "iso:country":"GB",
    "wof:name":"HS2 0AR",
    "wof:placetype":"postalcode"
},
  "geometry": {"coordinates":[-6.34094275959334,58.20264687590589],"type":"Point"}
}