{
  "type": "Feature",
  "properties": {
    "iso:country": "GB",
    "wof:name": "HS2 0AR",
    "wof:placetype": "postalcode"
  },
  "geometry": {"coordinates":[-6.340943,58.202647],"type":"Point"}
}
