{
  "type": "Feature",
  "properties": {
    "iso:country":"GB",
    "wof:name":"PH2 6PN",
    "wof:placetype":"postalcode"
},
  "geometry": {"coordinates":[-3.41362943969821,56.42522433294715],"type":"Point"}
}