{
  "type": "Feature",
  "properties": {
    "iso:country":"GB",
    "wof:name":"M33 2UN",
    "wof:placetype":"postalcode"
},
  "geometry": {"coordinates":[-2.30113226525727,53.41488589725309],"type":"Point"}
}