{
  "type": "Feature",
  "properties": {
    "iso:country":"GB",
    "wof:name":"HP17 8LY",
    "wof:placetype":"postalcode"
},
  "geometry": {"coordinates":[-0.92314195309925,51.75419982593277],"type":"Point"}
}