{
  "type": "Feature",
  "properties": {
    "iso:country": "GB",
    "wof:name": "HP17 8LY",
    "wof:placetype": "postalcode"
  },
  "geometry": {"coordinates":[-0.923063,51.754168],"type":"Point"}
}
