{
  "type": "Feature",
  "properties": {
    "iso:country":"GB",
    "wof:name":"HX3 8EB",
    "wof:placetype":"postalcode"
},
  "geometry": {"coordinates":[-1.81243122508784,53.72443416377021],"type":"Point"}
}