{
  "type": "Feature",
  "properties": {
    "iso:country":"GB",
    "wof:name":"TR3 6NT",
    "wof:placetype":"postalcode"
},
  "geometry": {"coordinates":[-5.07223942234973,50.20873276526466],"type":"Point"}
}