{
  "type": "Feature",
  "properties": {
    "iso:country":"GB",
    "wof:name":"SE25 5HQ",
    "wof:placetype":"postalcode"
},
  "geometry": {"coordinates":[-0.07054716306203,51.38716534942328],"type":"Point"}
}