{
  "type": "Feature",
  "properties": {
    "iso:country": "GB",
    "wof:name": "SE25 5HQ",
    "wof:placetype": "postalcode"
  },
  "geometry": {"coordinates":[-0.070547,51.387165],"type":"Point"}
}
