{
  "type": "Feature",
  "properties": {
    "date:inception_lower": "1980-01-01",
    "date:inception_upper": "1980-01-01",
    "iso:country": "GB",
    "wof:name": "DE4 3TA",
    "wof:placetype": "postalcode"
  },
  "geometry": {"coordinates":[-1.562649,53.141278],"type":"Point"}
}
