{
  "type": "Feature",
  "properties": {
    "iso:country":"GB",
    "wof:name":"DE4 3TA",
    "wof:placetype":"postalcode"
},
  "geometry": {"coordinates":[-1.56264859151988,53.14127827426597],"type":"Point"}
}