{
  "type": "Feature",
  "properties": {
    "date:inception_lower": "1980-01-01",
    "date:inception_upper": "1980-01-01",
    "iso:country": "GB",
    "wof:name": "EX16 8ND",
    "wof:placetype": "postalcode"
  },
  "geometry": {"coordinates":[-3.657457,50.882219],"type":"Point"}
}
