{
  "type": "Feature",
  "properties": {
    "iso:country": "GB",
    "wof:name": "EX16 8ND",
    "wof:placetype": "postalcode"
  },
  "geometry": {"coordinates":[-3.657457,50.882219],"type":"Point"}
}
