{
  "type": "Feature",
  "properties": {
    "iso:country":"GB",
    "wof:name":"TS4 3DQ",
    "wof:placetype":"postalcode"
},
  "geometry": {"coordinates":[-1.22368916630055,54.55208197785367],"type":"Point"}
}