{
  "type": "Feature",
  "properties": {
    "iso:country": "GB",
    "wof:name": "PL9 8FG",
    "wof:placetype": "postalcode"
  },
  "geometry": {"coordinates":[-4.054586,50.364887],"type":"Point"}
}
