{
  "type": "Feature",
  "properties": {
    "date:inception_lower": "1980-01-01",
    "date:inception_upper": "1980-01-01",
    "iso:country": "GB",
    "wof:name": "G64 1BY",
    "wof:placetype": "postalcode"
  },
  "geometry": {"coordinates":[-4.209586,55.907167],"type":"Point"}
}
