{
  "type": "Feature",
  "properties": {
    "iso:country":"GB",
    "wof:name":"NP12 2HW",
    "wof:placetype":"postalcode"
},
  "geometry": {"coordinates":[-3.18982681544037,51.64012583139378],"type":"Point"}
}