{
  "type": "Feature",
  "properties": {
    "iso:country":"GB",
    "wof:name":"CW7 3GZ",
    "wof:placetype":"postalcode"
},
  "geometry": {"coordinates":[-2.51408873580135,53.19826556680938],"type":"Point"}
}