{
  "type": "Feature",
  "properties": {
    "date:inception_lower": "1998-06-01",
    "date:inception_upper": "1998-06-01",
    "iso:country": "GB",
    "wof:name": "CW7 3GZ",
    "wof:placetype": "postalcode"
  },
  "geometry": {"coordinates":[-2.514253,53.198388],"type":"Point"}
}
