{
  "type": "Feature",
  "properties": {
    "iso:country":"GB",
    "wof:name":"BD7 2AB",
    "wof:placetype":"postalcode"
},
  "geometry": {"coordinates":[-1.78022445649225,53.79167291496695],"type":"Point"}
}