{
  "type": "Feature",
  "properties": {
    "date:inception_lower": "1981-06-01",
    "date:inception_upper": "1981-06-01",
    "iso:country": "GB",
    "wof:name": "BD7 2AB",
    "wof:placetype": "postalcode"
  },
  "geometry": {"coordinates":[-1.780224,53.791673],"type":"Point"}
}
