{
  "type": "Feature",
  "properties": {
    "iso:country": "GB",
    "wof:name": "RG2 0HA",
    "wof:placetype": "postalcode"
  },
  "geometry": {"coordinates":[-0.967364,51.438729],"type":"Point"}
}
