{
  "type": "Feature",
  "properties": {
    "iso:country":"GB",
    "wof:name":"RG2 0HA",
    "wof:placetype":"postalcode"
},
  "geometry": {"coordinates":[-0.96736422398663,51.43872902519705],"type":"Point"}
}