{
  "type": "Feature",
  "properties": {
    "date:inception_lower":"2005-02-01",
    "date:inception_upper":"2005-02-28",
    "iso:country":"GB",
    "wof:name":"LE18 9SF",
    "wof:placetype":"postalcode"
},
  "geometry": {"coordinates":[-1.114852,52.583411],"type":"Point"}
}