{
  "type": "Feature",
  "properties": {
    "date:inception_lower": "1980-01-01",
    "date:inception_upper": "1980-01-01",
    "iso:country": "GB",
    "wof:name": "WR2 4DP",
    "wof:placetype": "postalcode"
  },
  "geometry": {"coordinates":[-2.239683,52.176947],"type":"Point"}
}
