{
  "type": "Feature",
  "properties": {
    "iso:country":"GB",
    "wof:name":"WR2 4DP",
    "wof:placetype":"postalcode"
},
  "geometry": {"coordinates":[-2.23968327392771,52.1769466508614],"type":"Point"}
}