{
  "type": "Feature",
  "properties": {
    "iso:country":"GB",
    "wof:name":"NE61 3XE",
    "wof:placetype":"postalcode"
},
  "geometry": {"coordinates":[-1.79878849633063,55.12701792450049],"type":"Point"}
}