{
  "type": "Feature",
  "properties": {
    "date:inception_lower": "1991-09-01",
    "date:inception_upper": "1991-09-01",
    "iso:country": "GB",
    "wof:name": "PE15 8SJ",
    "wof:placetype": "postalcode"
  },
  "geometry": {"coordinates":[0.091857,52.5598],"type":"Point"}
}
