{
  "type": "Feature",
  "properties": {
    "iso:country": "GB",
    "wof:name": "TS19 9ED",
    "wof:placetype": "postalcode"
  },
  "geometry": {"coordinates":[-1.332692,54.586892],"type":"Point"}
}
