{
  "type": "Feature",
  "properties": {
    "date:inception_lower":"2009-07-01",
    "date:inception_upper":"2009-07-31",
    "iso:country":"GB",
    "wof:name":"LU1 3FD",
    "wof:placetype":"postalcode"
},
  "geometry": {"coordinates":[-0.412765,51.874355],"type":"Point"}
}