{
  "type": "Feature",
  "properties": {
    "iso:country":"GB",
    "wof:name":"LU1 3FD",
    "wof:placetype":"postalcode"
},
  "geometry": {"coordinates":[-0.41276548082468,51.87435530828471],"type":"Point"}
}