{
  "type": "Feature",
  "properties": {
    "iso:country":"GB",
    "wof:name":"N11 1LB",
    "wof:placetype":"postalcode"
},
  "geometry": {"coordinates":[-0.14514082118082,51.61921681090126],"type":"Point"}
}