{
  "type": "Feature",
  "properties": {
    "iso:country": "GB",
    "wof:name": "B46 1SA",
    "wof:placetype": "postalcode"
  },
  "geometry": {"coordinates":[-1.736735,52.514245],"type":"Point"}
}
