{
  "type": "Feature",
  "properties": {
    "iso:country":"GB",
    "wof:name":"TQ9 7UB",
    "wof:placetype":"postalcode"
},
  "geometry": {"coordinates":[-3.69203572114822,50.3803313935212],"type":"Point"}
}