{
  "type": "Feature",
  "properties": {
    "iso:country": "GB",
    "wof:name": "TQ9 7UB",
    "wof:placetype": "postalcode"
  },
  "geometry": {"coordinates":[-3.69207,50.380315],"type":"Point"}
}
