{
  "type": "Feature",
  "properties": {
    "iso:country":"GB",
    "wof:name":"LU2 7FJ",
    "wof:placetype":"postalcode"
},
  "geometry": {"coordinates":[-0.40169630371766,51.89196407639045],"type":"Point"}
}