{
  "type": "Feature",
  "properties": {
    "date:inception_lower":"2011-10-01",
    "date:inception_upper":"2011-10-31",
    "iso:country":"GB",
    "wof:name":"LU2 7FJ",
    "wof:placetype":"postalcode"
},
  "geometry": {"coordinates":[-0.401696,51.891964],"type":"Point"}
}