{
  "type": "Feature",
  "properties": {
    "iso:country": "GB",
    "wof:name": "LU2 7FJ",
    "wof:placetype": "postalcode"
  },
  "geometry": {"coordinates":[-0.401696,51.891964],"type":"Point"}
}
