{
  "type": "Feature",
  "properties": {
    "iso:country":"GB",
    "wof:name":"RM17 5LS",
    "wof:placetype":"postalcode"
},
  "geometry": {"coordinates":[0.32449248535966,51.48523156519975],"type":"Point"}
}