{
  "type": "Feature",
  "properties": {
    "iso:country": "GB",
    "wof:name": "RM17 5LS",
    "wof:placetype": "postalcode"
  },
  "geometry": {"coordinates":[0.324493,51.485232],"type":"Point"}
}
