{
  "type": "Feature",
  "properties": {
    "date:inception_lower": "2004-08-01",
    "date:inception_upper": "2004-08-01",
    "iso:country": "GB",
    "wof:name": "M17 1ED",
    "wof:placetype": "postalcode"
  },
  "geometry": {"coordinates":[-2.309481,53.458179],"type":"Point"}
}
