{
  "type": "Feature",
  "properties": {
    "iso:country":"GB",
    "wof:name":"M17 1ED",
    "wof:placetype":"postalcode"
},
  "geometry": {"coordinates":[-2.30948085897014,53.45816233239861],"type":"Point"}
}