{
  "type": "Feature",
  "properties": {
    "iso:country":"GB",
    "wof:name":"GL2 4RZ",
    "wof:placetype":"postalcode"
},
  "geometry": {"coordinates":[-2.28976640038533,51.82026205835722],"type":"Point"}
}