{
  "type": "Feature",
  "properties": {
    "date:inception_lower": "1995-12-01",
    "date:inception_upper": "1995-12-01",
    "iso:country": "GB",
    "wof:name": "GL2 4RZ",
    "wof:placetype": "postalcode"
  },
  "geometry": {"coordinates":[-2.289766,51.820262],"type":"Point"}
}
