{
  "type": "Feature",
  "properties": {
    "iso:country": "GB",
    "wof:name": "GL2 4RZ",
    "wof:placetype": "postalcode"
  },
  "geometry": {"coordinates":[-2.289766,51.820262],"type":"Point"}
}
