{
  "type": "Feature",
  "properties": {
    "date:inception_lower": "1980-01-01",
    "date:inception_upper": "1980-01-01",
    "iso:country": "GB",
    "wof:name": "TW9 4HP",
    "wof:placetype": "postalcode"
  },
  "geometry": {"coordinates":[-0.282694,51.473944],"type":"Point"}
}
