{
  "type": "Feature",
  "properties": {
    "iso:country":"GB",
    "wof:name":"TW9 4HP",
    "wof:placetype":"postalcode"
},
  "geometry": {"coordinates":[-0.28269419558786,51.47394373171311],"type":"Point"}
}