{
  "type": "Feature",
  "properties": {
    "date:inception_lower": "1980-01-01",
    "date:inception_upper": "1980-01-01",
    "iso:country": "GB",
    "wof:name": "DY8 4UW",
    "wof:placetype": "postalcode"
  },
  "geometry": {"coordinates":[-2.138793,52.459667],"type":"Point"}
}
