{
  "type": "Feature",
  "properties": {
    "iso:country":"GB",
    "wof:name":"HA2 8FJ",
    "wof:placetype":"postalcode"
},
  "geometry": {"coordinates":[-0.35728933588944,51.56189573390246],"type":"Point"}
}