{
  "type": "Feature",
  "properties": {
    "iso:country": "GB",
    "wof:name": "HA2 8FJ",
    "wof:placetype": "postalcode"
  },
  "geometry": {"coordinates":[-0.357289,51.561896],"type":"Point"}
}
