{
  "type": "Feature",
  "properties": {
    "date:inception_lower":"2013-02-01",
    "date:inception_upper":"2013-02-28",
    "iso:country":"GB",
    "wof:name":"HA2 8FJ",
    "wof:placetype":"postalcode"
},
  "geometry": {"coordinates":[-0.357289,51.561896],"type":"Point"}
}