{
  "type": "Feature",
  "properties": {
    "date:inception_lower":"2018-05-01",
    "date:inception_upper":"2018-05-31",
    "iso:country":"GB",
    "wof:name":"EN1 9DY",
    "wof:placetype":"postalcode"
},
  "geometry": {"coordinates":[-0.077079,51.651918],"type":"Point"}
}