{
  "type": "Feature",
  "properties": {
    "iso:country": "GB",
    "wof:name": "M34 5GF",
    "wof:placetype": "postalcode"
  },
  "geometry": {"coordinates":[-2.128801,53.478087],"type":"Point"}
}
