{
  "type": "Feature",
  "properties": {
    "iso:country":"GB",
    "wof:name":"M34 5GF",
    "wof:placetype":"postalcode"
},
  "geometry": {"coordinates":[-2.12872694430227,53.47808901797454],"type":"Point"}
}