{
  "type": "Feature",
  "properties": {
    "iso:country":"GB",
    "wof:name":"OX18 3NQ",
    "wof:placetype":"postalcode"
},
  "geometry": {"coordinates":[-1.55821647833542,51.77063675042746],"type":"Point"}
}