{
  "type": "Feature",
  "properties": {
    "date:inception_lower": "2002-06-01",
    "date:inception_upper": "2002-06-01",
    "iso:country": "GB",
    "wof:name": "CO3 9FB",
    "wof:placetype": "postalcode"
  },
  "geometry": {"coordinates":[0.858373,51.875962],"type":"Point"}
}
