{
  "type": "Feature",
  "properties": {
    "iso:country": "GB",
    "wof:name": "CO3 9FB",
    "wof:placetype": "postalcode"
  },
  "geometry": {"coordinates":[0.858373,51.875962],"type":"Point"}
}
