{
  "type": "Feature",
  "properties": {
    "iso:country":"GB",
    "wof:name":"W1J 0QP",
    "wof:placetype":"postalcode"
},
  "geometry": {"coordinates":[-0.13997335016353,51.50880683663389],"type":"Point"}
}