{
  "type": "Feature",
  "properties": {
    "date:inception_lower": "1981-06-01",
    "date:inception_upper": "1981-06-01",
    "iso:country": "GB",
    "wof:name": "DH1 5YE",
    "wof:placetype": "postalcode"
  },
  "geometry": {"coordinates":[-1.558218,54.807559],"type":"Point"}
}
