{
  "type": "Feature",
  "properties": {
    "iso:country":"GB",
    "wof:name":"BR3 4SG",
    "wof:placetype":"postalcode"
},
  "geometry": {"coordinates":[-0.05429841860792,51.40632101652177],"type":"Point"}
}