{
  "type": "Feature",
  "properties": {
    "iso:country": "GB",
    "wof:name": "CT14 7FD",
    "wof:placetype": "postalcode"
  },
  "geometry": {"coordinates":[1.400317,51.213834],"type":"Point"}
}
