{
  "type": "Feature",
  "properties": {
    "date:inception_lower": "2008-10-01",
    "date:inception_upper": "2008-10-01",
    "iso:country": "GB",
    "wof:name": "CT14 7FD",
    "wof:placetype": "postalcode"
  },
  "geometry": {"coordinates":[1.400317,51.213834],"type":"Point"}
}
