{
  "type": "Feature",
  "properties": {
    "iso:country": "GB",
    "wof:name": "CV22 7SA",
    "wof:placetype": "postalcode"
  },
  "geometry": {"coordinates":[-1.302867,52.352352],"type":"Point"}
}
