{
  "type": "Feature",
  "properties": {
    "iso:country":"GB",
    "wof:name":"CV22 7SA",
    "wof:placetype":"postalcode"
},
  "geometry": {"coordinates":[-1.30286669442136,52.35235244175291],"type":"Point"}
}