{
  "type": "Feature",
  "properties": {
    "iso:country":"GB",
    "wof:name":"SG12 9SZ",
    "wof:placetype":"postalcode"
},
  "geometry": {"coordinates":[-0.01716797755965,51.79889705354801],"type":"Point"}
}