{
  "type": "Feature",
  "properties": {
    "date:inception_lower": "1980-01-01",
    "date:inception_upper": "1980-01-01",
    "iso:country": "GB",
    "wof:name": "SE14 6TR",
    "wof:placetype": "postalcode"
  },
  "geometry": {"coordinates":[-0.029111,51.473472],"type":"Point"}
}
