{
  "type": "Feature",
  "properties": {
    "iso:country":"GB",
    "wof:name":"SE14 6TR",
    "wof:placetype":"postalcode"
},
  "geometry": {"coordinates":[-0.02909146872671,51.47353414766813],"type":"Point"}
}