{
  "type": "Feature",
  "properties": {
    "iso:country":"GB",
    "wof:name":"GL4 0XW",
    "wof:placetype":"postalcode"
},
  "geometry": {"coordinates":[-2.26885729587605,51.83194609445494],"type":"Point"}
}