{
  "type": "Feature",
  "properties": {
    "iso:country":"GB",
    "wof:name":"NR5 8NN",
    "wof:placetype":"postalcode"
},
  "geometry": {"coordinates":[1.22898096485927,52.6338515900338],"type":"Point"}
}