{
  "type": "Feature",
  "properties": {
    "date:inception_lower": "1980-01-01",
    "date:inception_upper": "1980-01-01",
    "iso:country": "GB",
    "wof:name": "LD3 0AP",
    "wof:placetype": "postalcode"
  },
  "geometry": {"coordinates":[-3.226969,52.001173],"type":"Point"}
}
