{
  "type": "Feature",
  "properties": {
    "iso:country":"GB",
    "wof:name":"LD3 0AP",
    "wof:placetype":"postalcode"
},
  "geometry": {"coordinates":[-3.2269692549193,52.00117300092788],"type":"Point"}
}