{
  "type": "Feature",
  "properties": {
    "iso:country": "GB",
    "wof:name": "LD3 0AP",
    "wof:placetype": "postalcode"
  },
  "geometry": {"coordinates":[-3.226969,52.001173],"type":"Point"}
}
