{
  "type": "Feature",
  "properties": {
    "date:inception_lower": "1980-01-01",
    "date:inception_upper": "1980-01-01",
    "iso:country": "GB",
    "wof:name": "TW2 6HR",
    "wof:placetype": "postalcode"
  },
  "geometry": {"coordinates":[-0.362449,51.447082],"type":"Point"}
}
