{
  "type": "Feature",
  "properties": {
    "iso:country":"GB",
    "wof:name":"TW2 6HR",
    "wof:placetype":"postalcode"
},
  "geometry": {"coordinates":[-0.3624489436196,51.4470824795093],"type":"Point"}
}