{
  "type": "Feature",
  "properties": {
    "date:inception_lower": "2017-08-01",
    "date:inception_upper": "2017-08-01",
    "iso:country": "GB",
    "wof:name": "ME13 7FH",
    "wof:placetype": "postalcode"
  },
  "geometry": {"coordinates":[0.873005,51.311899],"type":"Point"}
}
