{
  "type": "Feature",
  "properties": {
    "iso:country":"GB",
    "wof:name":"SP5 2SW",
    "wof:placetype":"postalcode"
},
  "geometry": {"coordinates":[-1.65774267977082,51.01000350453378],"type":"Point"}
}