{
  "type": "Feature",
  "properties": {
    "iso:country": "GB",
    "wof:name": "SP5 2SW",
    "wof:placetype": "postalcode"
  },
  "geometry": {"coordinates":[-1.657732,51.009997],"type":"Point"}
}
