{
  "type": "Feature",
  "properties": {
    "date:inception_lower":"1980-01-01",
    "date:inception_upper":"1980-01-31",
    "iso:country":"GB",
    "wof:name":"SP5 2SW",
    "wof:placetype":"postalcode"
},
  "geometry": {"coordinates":[-1.657647,51.009952],"type":"Point"}
}