{
  "type": "Feature",
  "properties": {
    "iso:country":"GB",
    "wof:name":"WF12 0PX",
    "wof:placetype":"postalcode"
},
  "geometry": {"coordinates":[-1.63723287045716,53.65953315401468],"type":"Point"}
}