{
  "type": "Feature",
  "properties": {
    "date:inception_lower": "1980-01-01",
    "date:inception_upper": "1980-01-01",
    "iso:country": "GB",
    "wof:name": "WF12 0PX",
    "wof:placetype": "postalcode"
  },
  "geometry": {"coordinates":[-1.637233,53.659533],"type":"Point"}
}
