{
  "type": "Feature",
  "properties": {
    "date:inception_lower": "1980-01-01",
    "date:inception_upper": "1980-01-01",
    "iso:country": "GB",
    "wof:name": "LS21 2AG",
    "wof:placetype": "postalcode"
  },
  "geometry": {"coordinates":[-1.694476,53.91684],"type":"Point"}
}
