{
  "type": "Feature",
  "properties": {
    "iso:country": "GB",
    "wof:name": "TW10 6PQ",
    "wof:placetype": "postalcode"
  },
  "geometry": {"coordinates":[-0.299439,51.459269],"type":"Point"}
}
