{
  "type": "Feature",
  "properties": {
    "iso:country":"GB",
    "wof:name":"TW10 6PQ",
    "wof:placetype":"postalcode"
},
  "geometry": {"coordinates":[-0.29951005251833,51.45929739059845],"type":"Point"}
}