{
  "type": "Feature",
  "properties": {
    "iso:country":"GB",
    "wof:name":"IP30 9RU",
    "wof:placetype":"postalcode"
},
  "geometry": {"coordinates":[0.89521199022571,52.22155015161751],"type":"Point"}
}