{
  "type": "Feature",
  "properties": {
    "iso:country":"GB",
    "wof:name":"SY2 5SJ",
    "wof:placetype":"postalcode"
},
  "geometry": {"coordinates":[-2.72508862615712,52.71746518212697],"type":"Point"}
}