{
  "type": "Feature",
  "properties": {
    "iso:country": "GB",
    "wof:name": "SY2 5SJ",
    "wof:placetype": "postalcode"
  },
  "geometry": {"coordinates":[-2.725089,52.717465],"type":"Point"}
}
