{
  "type": "Feature",
  "properties": {
    "iso:country":"GB",
    "wof:name":"SE16 3UB",
    "wof:placetype":"postalcode"
},
  "geometry": {"coordinates":[-0.06428065207228,51.49334665579475],"type":"Point"}
}