{
  "type": "Feature",
  "properties": {
    "iso:country":"GB",
    "wof:name":"KT6 5AL",
    "wof:placetype":"postalcode"
},
  "geometry": {"coordinates":[-0.30081239960201,51.37689133824208],"type":"Point"}
}