{
  "type": "Feature",
  "properties": {
    "iso:country":"GB",
    "wof:name":"WA16 6BN",
    "wof:placetype":"postalcode"
},
  "geometry": {"coordinates":[-2.37553707039666,53.30465359152821],"type":"Point"}
}