{
  "type": "Feature",
  "properties": {
    "iso:country": "GB",
    "wof:name": "WA16 6BN",
    "wof:placetype": "postalcode"
  },
  "geometry": {"coordinates":[-2.375537,53.304654],"type":"Point"}
}
