{
  "type": "Feature",
  "properties": {
    "date:inception_lower":"1980-01-01",
    "date:inception_upper":"1980-01-31",
    "iso:country":"GB",
    "wof:name":"BD21 1AD",
    "wof:placetype":"postalcode"
},
  "geometry": {"coordinates":[-1.91127,53.86352],"type":"Point"}
}