{
  "type": "Feature",
  "properties": {
    "iso:country":"GB",
    "wof:name":"BD21 1AD",
    "wof:placetype":"postalcode"
},
  "geometry": {"coordinates":[-1.91126975177348,53.86351979267527],"type":"Point"}
}