{
  "type": "Feature",
  "properties": {
    "iso:country": "GB",
    "wof:name": "BD18 1PJ",
    "wof:placetype": "postalcode"
  },
  "geometry": {"coordinates":[-1.753188,53.82564],"type":"Point"}
}
