{
  "type": "Feature",
  "properties": {
    "date:inception_lower": "1980-01-01",
    "date:inception_upper": "1980-01-01",
    "iso:country": "GB",
    "wof:name": "BD18 1PJ",
    "wof:placetype": "postalcode"
  },
  "geometry": {"coordinates":[-1.753188,53.82564],"type":"Point"}
}
