{
  "type": "Feature",
  "properties": {
    "iso:country": "GB",
    "wof:name": "PE28 9AF",
    "wof:placetype": "postalcode"
  },
  "geometry": {"coordinates":[-0.12003,52.321265],"type":"Point"}
}
