{
  "type": "Feature",
  "properties": {
    "iso:country": "GB",
    "wof:name": "SO50 4QP",
    "wof:placetype": "postalcode"
  },
  "geometry": {"coordinates":[-1.36001,50.977856],"type":"Point"}
}
