{
  "type": "Feature",
  "properties": {
    "iso:country": "GB",
    "wof:name": "EC1R 0EX",
    "wof:placetype": "postalcode"
  },
  "geometry": {"coordinates":[-0.10422,51.524088],"type":"Point"}
}
