{
  "type": "Feature",
  "properties": {
    "iso:country": "GB",
    "wof:name": "WA14 4HA",
    "wof:placetype": "postalcode"
  },
  "geometry": {"coordinates":[-2.355858,53.395841],"type":"Point"}
}
