{
  "type": "Feature",
  "properties": {
    "date:inception_lower": "2007-07-01",
    "date:inception_upper": "2007-07-01",
    "iso:country": "GB",
    "wof:name": "SM3 8DR",
    "wof:placetype": "postalcode"
  },
  "geometry": {"coordinates":[-0.21832,51.356916],"type":"Point"}
}
