{
  "type": "Feature",
  "properties": {
    "iso:country":"GB",
    "wof:name":"SM3 8DR",
    "wof:placetype":"postalcode"
},
  "geometry": {"coordinates":[-0.21831984373739,51.35691632247847],"type":"Point"}
}