{
  "type": "Feature",
  "properties": {
    "date:inception_lower": "1983-06-01",
    "date:inception_upper": "1983-06-01",
    "iso:country": "GB",
    "wof:name": "G40 2JH",
    "wof:placetype": "postalcode"
  },
  "geometry": {"coordinates":[-4.231224,55.854664],"type":"Point"}
}
