{
  "type": "Feature",
  "properties": {
    "iso:country": "GB",
    "wof:name": "G40 2JH",
    "wof:placetype": "postalcode"
  },
  "geometry": {"coordinates":[-4.231224,55.854664],"type":"Point"}
}
