{
  "type": "Feature",
  "properties": {
    "iso:country": "GB",
    "wof:name": "DE75 7BH",
    "wof:placetype": "postalcode"
  },
  "geometry": {"coordinates":[-1.345682,53.004718],"type":"Point"}
}
