{
  "type": "Feature",
  "properties": {
    "iso:country": "GB",
    "wof:name": "DE3 9NR",
    "wof:placetype": "postalcode"
  },
  "geometry": {"coordinates":[-1.537598,52.903698],"type":"Point"}
}
