{
  "type": "Feature",
  "properties": {
    "iso:country":"GB",
    "wof:name":"RG4 9EU",
    "wof:placetype":"postalcode"
},
  "geometry": {"coordinates":[-0.99145844936164,51.49315045331385],"type":"Point"}
}