{
  "type": "Feature",
  "properties": {
    "iso:country":"GB",
    "wof:name":"BN20 0JT",
    "wof:placetype":"postalcode"
},
  "geometry": {"coordinates":[0.21161109202623,50.76429625802503],"type":"Point"}
}