{
  "type": "Feature",
  "properties": {
    "iso:country":"GB",
    "wof:name":"TW17 8EU",
    "wof:placetype":"postalcode"
},
  "geometry": {"coordinates":[-0.43994989765525,51.3978812872075],"type":"Point"}
}