{
  "type": "Feature",
  "properties": {
    "date:inception_lower": "1980-01-01",
    "date:inception_upper": "1980-01-01",
    "iso:country": "GB",
    "wof:name": "TW17 8EU",
    "wof:placetype": "postalcode"
  },
  "geometry": {"coordinates":[-0.43995,51.397881],"type":"Point"}
}
