{
  "type": "Feature",
  "properties": {
    "iso:country":"GB",
    "wof:name":"N18 2SP",
    "wof:placetype":"postalcode"
},
  "geometry": {"coordinates":[-0.06567671293691,51.60932852017979],"type":"Point"}
}