{
  "type": "Feature",
  "properties": {
    "iso:country":"GB",
    "wof:name":"LA18 4LH",
    "wof:placetype":"postalcode"
},
  "geometry": {"coordinates":[-3.26578620225945,54.2065633202202],"type":"Point"}
}