{
  "type": "Feature",
  "properties": {
    "iso:country":"GB",
    "wof:name":"GL56 9PL",
    "wof:placetype":"postalcode"
},
  "geometry": {"coordinates":[-1.64751818499252,52.02519161374164],"type":"Point"}
}