{
  "type": "Feature",
  "properties": {
    "iso:country": "GB",
    "wof:name": "GL56 9PL",
    "wof:placetype": "postalcode"
  },
  "geometry": {"coordinates":[-1.647518,52.025192],"type":"Point"}
}
