{
  "type": "Feature",
  "properties": {
    "date:inception_lower":"1987-04-01",
    "date:inception_upper":"1987-04-30",
    "iso:country":"GB",
    "wof:name":"GL56 9PL",
    "wof:placetype":"postalcode"
},
  "geometry": {"coordinates":[-1.647518,52.025192],"type":"Point"}
}