{
  "type": "Feature",
  "properties": {
    "iso:country":"GB",
    "wof:name":"WS7 9DB",
    "wof:placetype":"postalcode"
},
  "geometry": {"coordinates":[-1.91559819695192,52.6823198310594],"type":"Point"}
}