{
  "type": "Feature",
  "properties": {
    "date:inception_lower":"1980-01-01",
    "date:inception_upper":"1980-01-31",
    "iso:country":"GB",
    "wof:name":"WS7 9DB",
    "wof:placetype":"postalcode"
},
  "geometry": {"coordinates":[-1.915598,52.68232],"type":"Point"}
}