{
  "type": "Feature",
  "properties": {
    "iso:country": "GB",
    "wof:name": "WS7 9DB",
    "wof:placetype": "postalcode"
  },
  "geometry": {"coordinates":[-1.915598,52.68232],"type":"Point"}
}
