{
  "type": "Feature",
  "properties": {
    "iso:country":"GB",
    "wof:name":"GU18 5SW",
    "wof:placetype":"postalcode"
},
  "geometry": {"coordinates":[-0.66121229397773,51.34709607273329],"type":"Point"}
}