{
  "type": "Feature",
  "properties": {
    "iso:country":"GB",
    "wof:name":"SN15 3QD",
    "wof:placetype":"postalcode"
},
  "geometry": {"coordinates":[-2.11201103093973,51.46240863277297],"type":"Point"}
}