{
  "type": "Feature",
  "properties": {
    "iso:country":"GB",
    "wof:name":"AB12 3TX",
    "wof:placetype":"postalcode"
},
  "geometry": {"coordinates":[-2.09514254564657,57.10271572514494],"type":"Point"}
}