{
  "type": "Feature",
  "properties": {
    "iso:country": "GB",
    "wof:name": "AB12 3TX",
    "wof:placetype": "postalcode"
  },
  "geometry": {"coordinates":[-2.095152,57.102736],"type":"Point"}
}
