{
  "type": "Feature",
  "properties": {
    "date:inception_lower":"1980-01-01",
    "date:inception_upper":"1980-01-31",
    "iso:country":"GB",
    "wof:name":"LL29 7RE",
    "wof:placetype":"postalcode"
},
  "geometry": {"coordinates":[-3.724327,53.290539],"type":"Point"}
}