{
  "type": "Feature",
  "properties": {
    "date:inception_lower":"1980-01-01",
    "date:inception_upper":"1980-01-31",
    "iso:country":"GB",
    "wof:name":"SA7 9BU",
    "wof:placetype":"postalcode"
},
  "geometry": {"coordinates":[-3.874477,51.660792],"type":"Point"}
}