{
  "type": "Feature",
  "properties": {
    "iso:country":"GB",
    "wof:name":"SA7 9BU",
    "wof:placetype":"postalcode"
},
  "geometry": {"coordinates":[-3.8744767037931,51.66079209471613],"type":"Point"}
}