{
  "type": "Feature",
  "properties": {
    "iso:country": "GB",
    "wof:name": "SA7 9BU",
    "wof:placetype": "postalcode"
  },
  "geometry": {"coordinates":[-3.874477,51.660792],"type":"Point"}
}
