{
  "type": "Feature",
  "properties": {
    "date:inception_lower": "1987-02-01",
    "date:inception_upper": "1987-02-01",
    "iso:country": "GB",
    "wof:name": "FK8 2DY",
    "wof:placetype": "postalcode"
  },
  "geometry": {"coordinates":[-3.934816,56.115344],"type":"Point"}
}
