{
  "type": "Feature",
  "properties": {
    "date:inception_lower":"1980-01-01",
    "date:inception_upper":"1980-01-31",
    "iso:country":"GB",
    "wof:name":"SW6 7RJ",
    "wof:placetype":"postalcode"
},
  "geometry": {"coordinates":[-0.211217,51.481625],"type":"Point"}
}