{
  "type": "Feature",
  "properties": {
    "iso:country":"GB",
    "wof:name":"SS13 3ET",
    "wof:placetype":"postalcode"
},
  "geometry": {"coordinates":[0.4964562499231,51.56647589266319],"type":"Point"}
}