{
  "type": "Feature",
  "properties": {
    "iso:country":"GB",
    "wof:name":"RG6 4HE",
    "wof:placetype":"postalcode"
},
  "geometry": {"coordinates":[-0.92490550135199,51.42653204298885],"type":"Point"}
}