{
  "type": "Feature",
  "properties": {
    "iso:country":"GB",
    "wof:name":"MK5 6BY",
    "wof:placetype":"postalcode"
},
  "geometry": {"coordinates":[-0.78551998283658,52.02125931932231],"type":"Point"}
}