{
  "type": "Feature",
  "properties": {
    "date:inception_lower": "1988-03-01",
    "date:inception_upper": "1988-03-01",
    "iso:country": "GB",
    "wof:name": "MK5 6BY",
    "wof:placetype": "postalcode"
  },
  "geometry": {"coordinates":[-0.78552,52.021259],"type":"Point"}
}
