{
  "type": "Feature",
  "properties": {
    "date:inception_lower":"1980-01-01",
    "date:inception_upper":"1980-01-31",
    "iso:country":"GB",
    "wof:name":"BN25 2PG",
    "wof:placetype":"postalcode"
},
  "geometry": {"coordinates":[0.092609,50.774911],"type":"Point"}
}