{
  "type": "Feature",
  "properties": {
    "iso:country":"GB",
    "wof:name":"BN25 2PG",
    "wof:placetype":"postalcode"
},
  "geometry": {"coordinates":[0.09260945423736,50.77491092080162],"type":"Point"}
}