{
  "type": "Feature",
  "properties": {
    "iso:country": "GB",
    "wof:name": "DE4 5NN",
    "wof:placetype": "postalcode"
  },
  "geometry": {"coordinates":[-1.498035,53.084986],"type":"Point"}
}
