{
  "type": "Feature",
  "properties": {
    "date:inception_lower": "2000-06-01",
    "date:inception_upper": "2000-06-01",
    "iso:country": "GB",
    "wof:name": "DE4 5NN",
    "wof:placetype": "postalcode"
  },
  "geometry": {"coordinates":[-1.498035,53.084986],"type":"Point"}
}
