{
  "type": "Feature",
  "properties": {
    "iso:country":"GB",
    "wof:name":"DL13 5AP",
    "wof:placetype":"postalcode"
},
  "geometry": {"coordinates":[-1.79936488564976,54.62196748395186],"type":"Point"}
}