{
  "type": "Feature",
  "properties": {
    "iso:country": "GB",
    "wof:name": "DL13 5AP",
    "wof:placetype": "postalcode"
  },
  "geometry": {"coordinates":[-1.799365,54.621967],"type":"Point"}
}
