{
  "type": "Feature",
  "properties": {
    "iso:country":"GB",
    "wof:name":"HX3 8PX",
    "wof:placetype":"postalcode"
},
  "geometry": {"coordinates":[-1.78536770566564,53.73559693833336],"type":"Point"}
}