{
  "type": "Feature",
  "properties": {
    "date:inception_lower": "1987-09-01",
    "date:inception_upper": "1987-09-01",
    "iso:country": "GB",
    "wof:name": "EH49 7SP",
    "wof:placetype": "postalcode"
  },
  "geometry": {"coordinates":[-3.590679,55.97809],"type":"Point"}
}
