{
  "type": "Feature",
  "properties": {
    "iso:country": "GB",
    "wof:name": "EH49 7SP",
    "wof:placetype": "postalcode"
  },
  "geometry": {"coordinates":[-3.590679,55.97809],"type":"Point"}
}
