{
  "type": "Feature",
  "properties": {
    "iso:country": "GB",
    "wof:name": "SN6 7RW",
    "wof:placetype": "postalcode"
  },
  "geometry": {"coordinates":[-1.737482,51.633527],"type":"Point"}
}
