{
  "type": "Feature",
  "properties": {
    "date:inception_lower":"1980-01-01",
    "date:inception_upper":"1980-01-31",
    "iso:country":"GB",
    "wof:name":"SN6 7RW",
    "wof:placetype":"postalcode"
},
  "geometry": {"coordinates":[-1.737482,51.633527],"type":"Point"}
}