{
  "type": "Feature",
  "properties": {
    "iso:country": "GB",
    "wof:name": "NG31 8BD",
    "wof:placetype": "postalcode"
  },
  "geometry": {"coordinates":[-0.644068,52.916558],"type":"Point"}
}
