{
  "type": "Feature",
  "properties": {
    "iso:country":"GB",
    "wof:name":"UB7 0EA",
    "wof:placetype":"postalcode"
},
  "geometry": {"coordinates":[-0.48083259962763,51.48202837746951],"type":"Point"}
}