{
  "type": "Feature",
  "properties": {
    "date:inception_lower": "1992-08-01",
    "date:inception_upper": "1992-08-01",
    "iso:country": "GB",
    "wof:name": "SA10 6PX",
    "wof:placetype": "postalcode"
  },
  "geometry": {"coordinates":[-3.838751,51.669042],"type":"Point"}
}
