{
  "type": "Feature",
  "properties": {
    "iso:country":"GB",
    "wof:name":"SA10 6PX",
    "wof:placetype":"postalcode"
},
  "geometry": {"coordinates":[-3.83914082383244,51.66903937023627],"type":"Point"}
}