{
  "type": "Feature",
  "properties": {
    "date:inception_lower": "1994-05-01",
    "date:inception_upper": "1994-05-01",
    "iso:country": "GB",
    "wof:name": "LA5 9DE",
    "wof:placetype": "postalcode"
  },
  "geometry": {"coordinates":[-2.771544,54.12749],"type":"Point"}
}
