{
  "type": "Feature",
  "properties": {
    "iso:country":"GB",
    "wof:name":"RH17 7ER",
    "wof:placetype":"postalcode"
},
  "geometry": {"coordinates":[-0.00137182645376,51.03136339998319],"type":"Point"}
}