{
  "type": "Feature",
  "properties": {
    "iso:country": "GB",
    "wof:name": "RH17 7ER",
    "wof:placetype": "postalcode"
  },
  "geometry": {"coordinates":[-0.001372,51.031363],"type":"Point"}
}
