{
  "type": "Feature",
  "properties": {
    "iso:country":"GB",
    "wof:name":"B96 6AX",
    "wof:placetype":"postalcode"
},
  "geometry": {"coordinates":[-1.93734041488792,52.25699057635777],"type":"Point"}
}