{
  "type": "Feature",
  "properties": {
    "date:inception_lower": "2021-08-01",
    "date:inception_upper": "2021-08-01",
    "iso:country": "GB",
    "wof:name": "UB3 1FN",
    "wof:placetype": "postalcode"
  },
  "geometry": {"coordinates":[-0.426304,51.504151],"type":"Point"}
}
