{
  "type": "Feature",
  "properties": {
    "iso:country": "GB",
    "wof:name": "SA31 3LL",
    "wof:placetype": "postalcode"
  },
  "geometry": {"coordinates":[-4.309497,51.854909],"type":"Point"}
}
