{
  "type": "Feature",
  "properties": {
    "iso:country":"GB",
    "wof:name":"SA31 3LL",
    "wof:placetype":"postalcode"
},
  "geometry": {"coordinates":[-4.30949675444264,51.8549091483356],"type":"Point"}
}