{
  "type": "Feature",
  "properties": {
    "date:inception_lower":"1980-01-01",
    "date:inception_upper":"1980-01-31",
    "iso:country":"GB",
    "wof:name":"SA31 3LL",
    "wof:placetype":"postalcode"
},
  "geometry": {"coordinates":[-4.309497,51.854909],"type":"Point"}
}