{
  "type": "Feature",
  "properties": {
    "iso:country":"GB",
    "wof:name":"FY8 1AL",
    "wof:placetype":"postalcode"
},
  "geometry": {"coordinates":[-2.99197507414557,53.73963582280045],"type":"Point"}
}