{
  "type": "Feature",
  "properties": {
    "date:inception_lower": "1980-01-01",
    "date:inception_upper": "1980-01-01",
    "iso:country": "GB",
    "wof:name": "FY8 1AL",
    "wof:placetype": "postalcode"
  },
  "geometry": {"coordinates":[-2.991975,53.739636],"type":"Point"}
}
