{
  "type": "Feature",
  "properties": {
    "iso:country": "GB",
    "wof:name": "LL11 2EY",
    "wof:placetype": "postalcode"
  },
  "geometry": {"coordinates":[-2.999019,53.058278],"type":"Point"}
}
