{
  "type": "Feature",
  "properties": {
    "iso:country":"GB",
    "wof:name":"LL11 2EY",
    "wof:placetype":"postalcode"
},
  "geometry": {"coordinates":[-2.99901894330441,53.05827759473802],"type":"Point"}
}