{
  "type": "Feature",
  "properties": {
    "date:inception_lower":"1980-01-01",
    "date:inception_upper":"1980-01-31",
    "iso:country":"GB",
    "wof:name":"BS9 4TF",
    "wof:placetype":"postalcode"
},
  "geometry": {"coordinates":[-2.593842,51.487384],"type":"Point"}
}