{
  "type": "Feature",
  "properties": {
    "iso:country":"GB",
    "wof:name":"MK2 3DD",
    "wof:placetype":"postalcode"
},
  "geometry": {"coordinates":[-0.72471519703705,51.98188268786983],"type":"Point"}
}