{
  "type": "Feature",
  "properties": {
    "date:inception_lower": "2007-01-01",
    "date:inception_upper": "2007-01-01",
    "iso:country": "GB",
    "wof:name": "MK2 3DD",
    "wof:placetype": "postalcode"
  },
  "geometry": {"coordinates":[-0.724715,51.981883],"type":"Point"}
}
