{
  "type": "Feature",
  "properties": {
    "iso:country": "GB",
    "wof:name": "CW10 0FW",
    "wof:placetype": "postalcode"
  },
  "geometry": {"coordinates":[-2.437213,53.174013],"type":"Point"}
}
