{
  "type": "Feature",
  "properties": {
    "date:inception_lower":"2015-05-01",
    "date:inception_upper":"2015-05-31",
    "iso:country":"GB",
    "wof:name":"CW10 0FW",
    "wof:placetype":"postalcode"
},
  "geometry": {"coordinates":[-2.437213,53.174013],"type":"Point"}
}