{
  "type": "Feature",
  "properties": {
    "iso:country":"GB",
    "wof:name":"B75 5BW",
    "wof:placetype":"postalcode"
},
  "geometry": {"coordinates":[-1.82436822704853,52.58807950599236],"type":"Point"}
}