{
  "type": "Feature",
  "properties": {
    "iso:country":"GB",
    "wof:name":"HD5 9NS",
    "wof:placetype":"postalcode"
},
  "geometry": {"coordinates":[-1.76384762637654,53.65322520621528],"type":"Point"}
}