{
  "type": "Feature",
  "properties": {
    "iso:country":"GB",
    "wof:name":"UB10 0LE",
    "wof:placetype":"postalcode"
},
  "geometry": {"coordinates":[-0.45532336648022,51.53498284057903],"type":"Point"}
}