{
  "type": "Feature",
  "properties": {
    "iso:country":"GB",
    "wof:name":"PE21 8PD",
    "wof:placetype":"postalcode"
},
  "geometry": {"coordinates":[-0.03459091643168,52.97977499672556],"type":"Point"}
}