{
  "type": "Feature",
  "properties": {
    "date:inception_lower": "1980-01-01",
    "date:inception_upper": "1980-01-01",
    "iso:country": "GB",
    "wof:name": "SE24 9LR",
    "wof:placetype": "postalcode"
  },
  "geometry": {"coordinates":[-0.100832,51.453388],"type":"Point"}
}
