{
  "type": "Feature",
  "properties": {
    "iso:country":"GB",
    "wof:name":"NR31 7AE",
    "wof:placetype":"postalcode"
},
  "geometry": {"coordinates":[1.72424315106903,52.57739567118236],"type":"Point"}
}