{
  "type": "Feature",
  "properties": {
    "iso:country": "GB",
    "wof:name": "NR31 7AE",
    "wof:placetype": "postalcode"
  },
  "geometry": {"coordinates":[1.724243,52.577396],"type":"Point"}
}
