{
  "type": "Feature",
  "properties": {
    "iso:country": "GB",
    "wof:name": "HP17 8LA",
    "wof:placetype": "postalcode"
  },
  "geometry": {"coordinates":[-0.928807,51.771335],"type":"Point"}
}
