{
  "type": "Feature",
  "properties": {
    "iso:country":"GB",
    "wof:name":"HP17 8LA",
    "wof:placetype":"postalcode"
},
  "geometry": {"coordinates":[-0.9288068234233,51.77133528452725],"type":"Point"}
}