{
  "type": "Feature",
  "properties": {
    "date:inception_lower": "1995-12-01",
    "date:inception_upper": "1995-12-01",
    "iso:country": "GB",
    "wof:name": "HP17 8LA",
    "wof:placetype": "postalcode"
  },
  "geometry": {"coordinates":[-0.928807,51.771335],"type":"Point"}
}
