{
  "type": "Feature",
  "properties": {
    "date:inception_lower":"1980-01-01",
    "date:inception_upper":"1980-01-31",
    "iso:country":"GB",
    "wof:name":"NR7 0SB",
    "wof:placetype":"postalcode"
},
  "geometry": {"coordinates":[1.356534,52.627839],"type":"Point"}
}