{
  "type": "Feature",
  "properties": {
    "iso:country":"GB",
    "wof:name":"NR7 0SB",
    "wof:placetype":"postalcode"
},
  "geometry": {"coordinates":[1.35653351517733,52.62783901011763],"type":"Point"}
}