{
  "type": "Feature",
  "properties": {
    "iso:country": "GB",
    "wof:name": "NR7 0SB",
    "wof:placetype": "postalcode"
  },
  "geometry": {"coordinates":[1.356534,52.627839],"type":"Point"}
}
