{
  "type": "Feature",
  "properties": {
    "iso:country":"GB",
    "wof:name":"CF3 2TH",
    "wof:placetype":"postalcode"
},
  "geometry": {"coordinates":[-3.06794358760696,51.53232766143753],"type":"Point"}
}