{
  "type": "Feature",
  "properties": {
    "date:inception_lower":"1999-06-01",
    "date:inception_upper":"1999-06-30",
    "iso:country":"GB",
    "wof:name":"CF3 2TH",
    "wof:placetype":"postalcode"
},
  "geometry": {"coordinates":[-3.067944,51.532328],"type":"Point"}
}