{
  "type": "Feature",
  "properties": {
    "iso:country":"GB",
    "wof:name":"L11 8LW",
    "wof:placetype":"postalcode"
},
  "geometry": {"coordinates":[-2.93084099462672,53.43778513804974],"type":"Point"}
}