{
  "type": "Feature",
  "properties": {
    "iso:country":"GB",
    "wof:name":"HA5 1AR",
    "wof:placetype":"postalcode"
},
  "geometry": {"coordinates":[-0.39025138579259,51.59181980147937],"type":"Point"}
}