{
  "type": "Feature",
  "properties": {
    "date:inception_lower": "1980-01-01",
    "date:inception_upper": "1980-01-01",
    "iso:country": "GB",
    "wof:name": "HA5 1AR",
    "wof:placetype": "postalcode"
  },
  "geometry": {"coordinates":[-0.390251,51.59182],"type":"Point"}
}
