{
  "type": "Feature",
  "properties": {
    "iso:country":"GB",
    "wof:name":"HX6 2DP",
    "wof:placetype":"postalcode"
},
  "geometry": {"coordinates":[-1.90495363600016,53.71122272666204],"type":"Point"}
}