{
  "type": "Feature",
  "properties": {
    "date:inception_lower": "1998-12-01",
    "date:inception_upper": "1998-12-01",
    "iso:country": "GB",
    "wof:name": "HX6 2DP",
    "wof:placetype": "postalcode"
  },
  "geometry": {"coordinates":[-1.904954,53.711223],"type":"Point"}
}
