{
  "type": "Feature",
  "properties": {
    "iso:country":"GB",
    "wof:name":"SW11 6QW",
    "wof:placetype":"postalcode"
},
  "geometry": {"coordinates":[-0.1660042342491,51.45733892951139],"type":"Point"}
}