{
  "type": "Feature",
  "properties": {
    "iso:country":"GB",
    "wof:name":"LS4 2TN",
    "wof:placetype":"postalcode"
},
  "geometry": {"coordinates":[-1.59097856802992,53.81531900703676],"type":"Point"}
}