{
  "type": "Feature",
  "properties": {
    "iso:country":"GB",
    "wof:name":"G66 8EF",
    "wof:placetype":"postalcode"
},
  "geometry": {"coordinates":[-4.16966831428784,55.96592167375136],"type":"Point"}
}