{
  "type": "Feature",
  "properties": {
    "iso:country": "GB",
    "wof:name": "NE5 2HN",
    "wof:placetype": "postalcode"
  },
  "geometry": {"coordinates":[-1.677679,54.984427],"type":"Point"}
}
