{
  "type": "Feature",
  "properties": {
    "iso:country":"GB",
    "wof:name":"CR0 9JG",
    "wof:placetype":"postalcode"
},
  "geometry": {"coordinates":[-0.03752012807658,51.34547461395847],"type":"Point"}
}