{
  "type": "Feature",
  "properties": {
    "iso:country":"GB",
    "wof:name":"PO20 8BH",
    "wof:placetype":"postalcode"
},
  "geometry": {"coordinates":[-0.8744904667426,50.77000574097797],"type":"Point"}
}