{
  "type": "Feature",
  "properties": {
    "iso:country":"GB",
    "wof:name":"IP32 6QD",
    "wof:placetype":"postalcode"
},
  "geometry": {"coordinates":[0.69344570511836,52.25463037696612],"type":"Point"}
}