{
  "type": "Feature",
  "properties": {
    "date:inception_lower":"1980-01-01",
    "date:inception_upper":"1980-01-31",
    "iso:country":"GB",
    "wof:name":"RG22 5HS",
    "wof:placetype":"postalcode"
},
  "geometry": {"coordinates":[-1.132012,51.249479],"type":"Point"}
}