{
  "type": "Feature",
  "properties": {
    "iso:country":"GB",
    "wof:name":"RG22 5HS",
    "wof:placetype":"postalcode"
},
  "geometry": {"coordinates":[-1.13201156508867,51.24947939632828],"type":"Point"}
}