{
  "type": "Feature",
  "properties": {
    "date:inception_lower": "1980-01-01",
    "date:inception_upper": "1980-01-01",
    "iso:country": "GB",
    "wof:name": "BD20 6BY",
    "wof:placetype": "postalcode"
  },
  "geometry": {"coordinates":[-1.917345,53.882515],"type":"Point"}
}
