{
  "type": "Feature",
  "properties": {
    "iso:country":"GB",
    "wof:name":"GL6 0AU",
    "wof:placetype":"postalcode"
},
  "geometry": {"coordinates":[-2.22086068238131,51.70023704189428],"type":"Point"}
}