{
  "type": "Feature",
  "properties": {
    "iso:country":"GB",
    "wof:name":"LE7 7BU",
    "wof:placetype":"postalcode"
},
  "geometry": {"coordinates":[-1.18206059169442,52.67639210785057],"type":"Point"}
}