{
  "type": "Feature",
  "properties": {
    "date:inception_lower": "1980-01-01",
    "date:inception_upper": "1980-01-01",
    "iso:country": "GB",
    "wof:name": "LE7 7BU",
    "wof:placetype": "postalcode"
  },
  "geometry": {"coordinates":[-1.182061,52.676392],"type":"Point"}
}
