{
  "type": "Feature",
  "properties": {
    "iso:country":"GB",
    "wof:name":"GU21 3RP",
    "wof:placetype":"postalcode"
},
  "geometry": {"coordinates":[-0.60324412368233,51.32444212069711],"type":"Point"}
}