{
  "type": "Feature",
  "properties": {
    "date:inception_lower": "2006-08-01",
    "date:inception_upper": "2006-08-01",
    "iso:country": "GB",
    "wof:name": "LS7 3NZ",
    "wof:placetype": "postalcode"
  },
  "geometry": {"coordinates":[-1.540507,53.830668],"type":"Point"}
}
