{
  "type": "Feature",
  "properties": {
    "iso:country":"GB",
    "wof:name":"LS7 3NZ",
    "wof:placetype":"postalcode"
},
  "geometry": {"coordinates":[-1.54050754008887,53.8306676769869],"type":"Point"}
}