{
  "type": "Feature",
  "properties": {
    "date:inception_lower": "1980-01-01",
    "date:inception_upper": "1980-01-01",
    "iso:country": "GB",
    "wof:name": "DG7 2AS",
    "wof:placetype": "postalcode"
  },
  "geometry": {"coordinates":[-4.05298,54.900891],"type":"Point"}
}
