{
  "type": "Feature",
  "properties": {
    "iso:country":"GB",
    "wof:name":"S10 4QH",
    "wof:placetype":"postalcode"
},
  "geometry": {"coordinates":[-1.57651197883947,53.35791479547122],"type":"Point"}
}