{
  "type": "Feature",
  "properties": {
    "iso:country": "GB",
    "wof:name": "S10 4QH",
    "wof:placetype": "postalcode"
  },
  "geometry": {"coordinates":[-1.575928,53.357643],"type":"Point"}
}
