{
  "type": "Feature",
  "properties": {
    "date:inception_lower": "2022-10-01",
    "date:inception_upper": "2022-10-01",
    "iso:country": "GB",
    "wof:name": "YO25 4BB",
    "wof:placetype": "postalcode"
  },
  "geometry": {"coordinates":[-0.376568,54.06526],"type":"Point"}
}
