{
  "type": "Feature",
  "properties": {
    "date:inception_lower": "1981-09-01",
    "date:inception_upper": "1981-09-01",
    "iso:country": "GB",
    "wof:name": "N22 6AX",
    "wof:placetype": "postalcode"
  },
  "geometry": {"coordinates":[-0.108808,51.594334],"type":"Point"}
}
