{
  "type": "Feature",
  "properties": {
    "iso:country":"GB",
    "wof:name":"N22 6AX",
    "wof:placetype":"postalcode"
},
  "geometry": {"coordinates":[-0.10883329291611,51.59433101020967],"type":"Point"}
}