{
  "type": "Feature",
  "properties": {
    "date:inception_lower":"1980-01-01",
    "date:inception_upper":"1980-01-31",
    "iso:country":"GB",
    "wof:name":"UB6 0RN",
    "wof:placetype":"postalcode"
},
  "geometry": {"coordinates":[-0.319572,51.549114],"type":"Point"}
}