{
  "type": "Feature",
  "properties": {
    "iso:country":"GB",
    "wof:name":"BR3 6PX",
    "wof:placetype":"postalcode"
},
  "geometry": {"coordinates":[-0.01134152293581,51.40186785758324],"type":"Point"}
}