{
  "type": "Feature",
  "properties": {
    "date:inception_lower":"1995-12-01",
    "date:inception_upper":"1995-12-31",
    "iso:country":"GB",
    "wof:name":"BR3 6PX",
    "wof:placetype":"postalcode"
},
  "geometry": {"coordinates":[-0.011341,51.401868],"type":"Point"}
}