{
  "type": "Feature",
  "properties": {
    "iso:country":"GB",
    "wof:name":"M22 5NE",
    "wof:placetype":"postalcode"
},
  "geometry": {"coordinates":[-2.2475684751425,53.36511335982471],"type":"Point"}
}