{
  "type": "Feature",
  "properties": {
    "iso:country": "GB",
    "wof:name": "DN3 2PZ",
    "wof:placetype": "postalcode"
  },
  "geometry": {"coordinates":[-1.076822,53.557013],"type":"Point"}
}
