{
  "type": "Feature",
  "properties": {
    "iso:country": "GB",
    "wof:name": "E2 9RH",
    "wof:placetype": "postalcode"
  },
  "geometry": {"coordinates":[-0.057701,51.531214],"type":"Point"}
}
