{
  "type": "Feature",
  "properties": {
    "iso:country":"GB",
    "wof:name":"E2 9RH",
    "wof:placetype":"postalcode"
},
  "geometry": {"coordinates":[-0.05770059357252,51.53121362340958],"type":"Point"}
}