{
  "type": "Feature",
  "properties": {
    "date:inception_lower": "1999-06-01",
    "date:inception_upper": "1999-06-01",
    "iso:country": "GB",
    "wof:name": "NP22 4AE",
    "wof:placetype": "postalcode"
  },
  "geometry": {"coordinates":[-3.250064,51.782742],"type":"Point"}
}
