{
  "type": "Feature",
  "properties": {
    "iso:country":"GB",
    "wof:name":"KA18 2LJ",
    "wof:placetype":"postalcode"
},
  "geometry": {"coordinates":[-4.36152127946957,55.46158818180348],"type":"Point"}
}