{
  "type": "Feature",
  "properties": {
    "iso:country":"GB",
    "wof:name":"NG8 5HF",
    "wof:placetype":"postalcode"
},
  "geometry": {"coordinates":[-1.18133320532037,52.97114069364932],"type":"Point"}
}