{
  "type": "Feature",
  "properties": {
    "iso:country": "GB",
    "wof:name": "SW6 2GH",
    "wof:placetype": "postalcode"
  },
  "geometry": {"coordinates":[-0.184816,51.474421],"type":"Point"}
}
