{
  "type": "Feature",
  "properties": {
    "date:inception_lower":"2014-07-01",
    "date:inception_upper":"2014-07-31",
    "iso:country":"GB",
    "wof:name":"SW6 2GH",
    "wof:placetype":"postalcode"
},
  "geometry": {"coordinates":[-0.184816,51.474421],"type":"Point"}
}