{
  "type": "Feature",
  "properties": {
    "iso:country":"GB",
    "wof:name":"SW6 2GH",
    "wof:placetype":"postalcode"
},
  "geometry": {"coordinates":[-0.18481644349521,51.47442074740287],"type":"Point"}
}