{
  "type": "Feature",
  "properties": {
    "iso:country": "GB",
    "wof:name": "PE1 1TU",
    "wof:placetype": "postalcode"
  },
  "geometry": {"coordinates":[-0.23798,52.576236],"type":"Point"}
}
