{
  "type": "Feature",
  "properties": {
    "date:inception_lower": "1980-01-01",
    "date:inception_upper": "1980-01-01",
    "iso:country": "GB",
    "wof:name": "WN8 9BS",
    "wof:placetype": "postalcode"
  },
  "geometry": {"coordinates":[-2.757304,53.537608],"type":"Point"}
}
