{
  "type": "Feature",
  "properties": {
    "iso:country":"GB",
    "wof:name":"TS17 9JW",
    "wof:placetype":"postalcode"
},
  "geometry": {"coordinates":[-1.29720362412083,54.53330786350085],"type":"Point"}
}