{
  "type": "Feature",
  "properties": {
    "date:inception_lower":"1998-12-01",
    "date:inception_upper":"1998-12-31",
    "iso:country":"GB",
    "wof:name":"CT12 5EF",
    "wof:placetype":"postalcode"
},
  "geometry": {"coordinates":[1.371843,51.345907],"type":"Point"}
}