{
  "type": "Feature",
  "properties": {
    "date:inception_lower": "2022-08-01",
    "date:inception_upper": "2022-08-01",
    "iso:country": "GB",
    "wof:name": "GL2 9RQ",
    "wof:placetype": "postalcode"
  },
  "geometry": {"coordinates":[-2.221736,51.897335],"type":"Point"}
}
