{
  "type": "Feature",
  "properties": {
    "date:inception_lower": "1980-01-01",
    "date:inception_upper": "1980-01-01",
    "iso:country": "GB",
    "wof:name": "EX34 9BD",
    "wof:placetype": "postalcode"
  },
  "geometry": {"coordinates":[-4.120684,51.21013],"type":"Point"}
}
