{
  "type": "Feature",
  "properties": {
    "iso:country":"GB",
    "wof:name":"SS8 9BE",
    "wof:placetype":"postalcode"
},
  "geometry": {"coordinates":[0.58423109410212,51.52643368240542],"type":"Point"}
}