{
  "type": "Feature",
  "properties": {
    "iso:country":"GB",
    "wof:name":"MK41 7FQ",
    "wof:placetype":"postalcode"
},
  "geometry": {"coordinates":[-0.4575516436976,52.16881843049882],"type":"Point"}
}