{
  "type": "Feature",
  "properties": {
    "iso:country": "GB",
    "wof:name": "MK41 7FQ",
    "wof:placetype": "postalcode"
  },
  "geometry": {"coordinates":[-0.457552,52.168818],"type":"Point"}
}
