{
  "type": "Feature",
  "properties": {
    "iso:country": "GB",
    "wof:name": "OX39 4LR",
    "wof:placetype": "postalcode"
  },
  "geometry": {"coordinates":[-0.941859,51.711107],"type":"Point"}
}
