{
  "type": "Feature",
  "properties": {
    "iso:country":"GB",
    "wof:name":"YO41 1AU",
    "wof:placetype":"postalcode"
},
  "geometry": {"coordinates":[-0.88193594635414,54.01422132469459],"type":"Point"}
}