{
  "type": "Feature",
  "properties": {
    "iso:country": "GB",
    "wof:name": "SA72 6BX",
    "wof:placetype": "postalcode"
  },
  "geometry": {"coordinates":[-4.940268,51.693784],"type":"Point"}
}
