{
  "type": "Feature",
  "properties": {
    "iso:country":"GB",
    "wof:name":"BN24 5QX",
    "wof:placetype":"postalcode"
},
  "geometry": {"coordinates":[0.2884231435612,50.81410668138899],"type":"Point"}
}