{
  "type": "Feature",
  "properties": {
    "iso:country":"GB",
    "wof:name":"AB39 3UN",
    "wof:placetype":"postalcode"
},
  "geometry": {"coordinates":[-2.14523831842315,57.03068572680872],"type":"Point"}
}