{
  "type": "Feature",
  "properties": {
    "iso:country":"GB",
    "wof:name":"SA34 0UJ",
    "wof:placetype":"postalcode"
},
  "geometry": {"coordinates":[-4.66386426202504,51.84344738038439],"type":"Point"}
}