{
  "type": "Feature",
  "properties": {
    "iso:country":"GB",
    "wof:name":"PL23 1BE",
    "wof:placetype":"postalcode"
},
  "geometry": {"coordinates":[-4.63643378670472,50.3351071353117],"type":"Point"}
}