{
  "type": "Feature",
  "properties": {
    "iso:country": "GB",
    "wof:name": "RG7 2JT",
    "wof:placetype": "postalcode"
  },
  "geometry": {"coordinates":[-1.06667,51.374209],"type":"Point"}
}
