{
  "type": "Feature",
  "properties": {
    "date:inception_lower": "1980-01-01",
    "date:inception_upper": "1980-01-01",
    "iso:country": "GB",
    "wof:name": "CW1 3RJ",
    "wof:placetype": "postalcode"
  },
  "geometry": {"coordinates":[-2.460454,53.113009],"type":"Point"}
}
