{
  "type": "Feature",
  "properties": {
    "iso:country": "GB",
    "wof:name": "SG1 3LE",
    "wof:placetype": "postalcode"
  },
  "geometry": {"coordinates":[-0.194855,51.908016],"type":"Point"}
}
