{
  "type": "Feature",
  "properties": {
    "iso:country":"GB",
    "wof:name":"SG1 3LE",
    "wof:placetype":"postalcode"
},
  "geometry": {"coordinates":[-0.19468836651924,51.90803306984989],"type":"Point"}
}