{
  "type": "Feature",
  "properties": {
    "iso:country":"GB",
    "wof:name":"GL54 4HN",
    "wof:placetype":"postalcode"
},
  "geometry": {"coordinates":[-1.96700854434296,51.87563958152231],"type":"Point"}
}