{
  "type": "Feature",
  "properties": {
    "date:inception_lower": "2001-06-01",
    "date:inception_upper": "2001-06-01",
    "iso:country": "GB",
    "wof:name": "GL54 4HN",
    "wof:placetype": "postalcode"
  },
  "geometry": {"coordinates":[-1.967009,51.87564],"type":"Point"}
}
