{
  "type": "Feature",
  "properties": {
    "iso:country":"GB",
    "wof:name":"PR2 2EY",
    "wof:placetype":"postalcode"
},
  "geometry": {"coordinates":[-2.72627036256152,53.77457283316178],"type":"Point"}
}