{
  "type": "Feature",
  "properties": {
    "iso:country":"GB",
    "wof:name":"G21 4RP",
    "wof:placetype":"postalcode"
},
  "geometry": {"coordinates":[-4.22927672794494,55.87673675155185],"type":"Point"}
}