{
  "type": "Feature",
  "properties": {
    "iso:country":"GB",
    "wof:name":"BN24 5PL",
    "wof:placetype":"postalcode"
},
  "geometry": {"coordinates":[0.28275653304864,50.81522505150672],"type":"Point"}
}