{
  "type": "Feature",
  "properties": {
    "iso:country": "GB",
    "wof:name": "BN24 5PL",
    "wof:placetype": "postalcode"
  },
  "geometry": {"coordinates":[0.282757,50.815225],"type":"Point"}
}
