{
  "type": "Feature",
  "properties": {
    "iso:country":"GB",
    "wof:name":"TD14 5LS",
    "wof:placetype":"postalcode"
},
  "geometry": {"coordinates":[-2.23838165016178,55.83927279762834],"type":"Point"}
}