{
  "type": "Feature",
  "properties": {
    "iso:country": "GB",
    "wof:name": "MK10 9JN",
    "wof:placetype": "postalcode"
  },
  "geometry": {"coordinates":[-0.712528,52.045831],"type":"Point"}
}
