{
  "type": "Feature",
  "properties": {
    "date:inception_lower": "2012-04-01",
    "date:inception_upper": "2012-04-01",
    "iso:country": "GB",
    "wof:name": "DG1 3GT",
    "wof:placetype": "postalcode"
  },
  "geometry": {"coordinates":[-3.58562,55.077046],"type":"Point"}
}
