{
  "type": "Feature",
  "properties": {
    "iso:country": "GB",
    "wof:name": "DG1 3GT",
    "wof:placetype": "postalcode"
  },
  "geometry": {"coordinates":[-3.585376,55.076748],"type":"Point"}
}
