{
  "type": "Feature",
  "properties": {
    "iso:country": "GB",
    "wof:name": "OL16 3AD",
    "wof:placetype": "postalcode"
  },
  "geometry": {"coordinates":[-2.128431,53.619305],"type":"Point"}
}
