{
  "type": "Feature",
  "properties": {
    "iso:country":"GB",
    "wof:name":"OL16 3AD",
    "wof:placetype":"postalcode"
},
  "geometry": {"coordinates":[-2.12843140119417,53.61930512057808],"type":"Point"}
}