{
  "type": "Feature",
  "properties": {
    "iso:country":"GB",
    "wof:name":"DL12 8NL",
    "wof:placetype":"postalcode"
},
  "geometry": {"coordinates":[-1.92008714790512,54.54197193995536],"type":"Point"}
}