{
  "type": "Feature",
  "properties": {
    "date:inception_lower": "1980-01-01",
    "date:inception_upper": "1980-01-01",
    "iso:country": "GB",
    "wof:name": "DL12 8NL",
    "wof:placetype": "postalcode"
  },
  "geometry": {"coordinates":[-1.920087,54.541972],"type":"Point"}
}
