{
  "type": "Feature",
  "properties": {
    "iso:country":"GB",
    "wof:name":"BH19 2JS",
    "wof:placetype":"postalcode"
},
  "geometry": {"coordinates":[-1.98421824691848,50.60837486935684],"type":"Point"}
}