{
  "type": "Feature",
  "properties": {
    "iso:country":"GB",
    "wof:name":"TN27 0AT",
    "wof:placetype":"postalcode"
},
  "geometry": {"coordinates":[0.76899253939418,51.20707576838499],"type":"Point"}
}