{
  "type": "Feature",
  "properties": {
    "date:inception_lower": "1980-01-01",
    "date:inception_upper": "1980-01-01",
    "iso:country": "GB",
    "wof:name": "OX16 9JF",
    "wof:placetype": "postalcode"
  },
  "geometry": {"coordinates":[-1.34116,52.050247],"type":"Point"}
}
