{
  "type": "Feature",
  "properties": {
    "iso:country":"GB",
    "wof:name":"OX16 9JF",
    "wof:placetype":"postalcode"
},
  "geometry": {"coordinates":[-1.34116011021765,52.05024744995062],"type":"Point"}
}