{
  "type": "Feature",
  "properties": {
    "date:inception_lower":"2004-01-01",
    "date:inception_upper":"2004-01-31",
    "iso:country":"GB",
    "wof:name":"HP19 7AJ",
    "wof:placetype":"postalcode"
},
  "geometry": {"coordinates":[-0.84509,51.817514],"type":"Point"}
}