{
  "type": "Feature",
  "properties": {
    "iso:country":"GB",
    "wof:name":"L7 8RX",
    "wof:placetype":"postalcode"
},
  "geometry": {"coordinates":[-2.95754456459931,53.40825226103034],"type":"Point"}
}