{
  "type": "Feature",
  "properties": {
    "date:inception_lower": "2023-08-01",
    "date:inception_upper": "2023-08-01",
    "iso:country": "GB",
    "wof:name": "M7 4BT",
    "wof:placetype": "postalcode"
  },
  "geometry": {"coordinates":[-2.258371,53.51632],"type":"Point"}
}
