{
  "type": "Feature",
  "properties": {
    "iso:country":"GB",
    "wof:name":"SG17 5RR",
    "wof:placetype":"postalcode"
},
  "geometry": {"coordinates":[-0.29907898352809,52.03507611701697],"type":"Point"}
}