{
  "type": "Feature",
  "properties": {
    "iso:country": "GB",
    "wof:name": "SG17 5RR",
    "wof:placetype": "postalcode"
  },
  "geometry": {"coordinates":[-0.299079,52.035076],"type":"Point"}
}
