{
  "type": "Feature",
  "properties": {
    "iso:country": "GB",
    "wof:name": "NG7 5LF",
    "wof:placetype": "postalcode"
  },
  "geometry": {"coordinates":[-1.178071,52.964933],"type":"Point"}
}
