{
  "type": "Feature",
  "properties": {
    "iso:country":"GB",
    "wof:name":"NG7 5LF",
    "wof:placetype":"postalcode"
},
  "geometry": {"coordinates":[-1.17807069690771,52.96493343572998],"type":"Point"}
}