{
  "type": "Feature",
  "properties": {
    "date:inception_lower": "2002-06-01",
    "date:inception_upper": "2002-06-01",
    "iso:country": "GB",
    "wof:name": "BD23 3EA",
    "wof:placetype": "postalcode"
  },
  "geometry": {"coordinates":[-2.0439,53.943661],"type":"Point"}
}
