{
  "type": "Feature",
  "properties": {
    "date:inception_lower":"1990-08-01",
    "date:inception_upper":"1990-08-31",
    "iso:country":"GB",
    "wof:name":"AB52 6SL",
    "wof:placetype":"postalcode"
},
  "geometry": {"coordinates":[-2.562908,57.357975],"type":"Point"}
}