{
  "type": "Feature",
  "properties": {
    "iso:country":"GB",
    "wof:name":"AB52 6SL",
    "wof:placetype":"postalcode"
},
  "geometry": {"coordinates":[-2.56428220972174,57.35674405456906],"type":"Point"}
}