{
  "type": "Feature",
  "properties": {
    "date:inception_lower": "1990-08-01",
    "date:inception_upper": "1990-08-01",
    "iso:country": "GB",
    "wof:name": "AB52 6SL",
    "wof:placetype": "postalcode"
  },
  "geometry": {"coordinates":[-2.564253,57.35681],"type":"Point"}
}
