{
  "type": "Feature",
  "properties": {
    "iso:country":"GB",
    "wof:name":"NW3 4LH",
    "wof:placetype":"postalcode"
},
  "geometry": {"coordinates":[-0.16773940177767,51.54802834752794],"type":"Point"}
}