{
  "type": "Feature",
  "properties": {
    "iso:country":"GB",
    "wof:name":"IP31 2BN",
    "wof:placetype":"postalcode"
},
  "geometry": {"coordinates":[0.90581159050569,52.31897338462602],"type":"Point"}
}