{
  "type": "Feature",
  "properties": {
    "iso:country":"GB",
    "wof:name":"AB32 6AX",
    "wof:placetype":"postalcode"
},
  "geometry": {"coordinates":[-2.31050349084904,57.15991256741473],"type":"Point"}
}