{
  "type": "Feature",
  "properties": {
    "iso:country": "GB",
    "wof:name": "RH14 9QS",
    "wof:placetype": "postalcode"
  },
  "geometry": {"coordinates":[-0.452384,51.021691],"type":"Point"}
}
