{
  "type": "Feature",
  "properties": {
    "date:inception_lower": "1981-06-01",
    "date:inception_upper": "1981-06-01",
    "iso:country": "GB",
    "wof:name": "BH23 5SG",
    "wof:placetype": "postalcode"
  },
  "geometry": {"coordinates":[-1.696342,50.751721],"type":"Point"}
}
