{
  "type": "Feature",
  "properties": {
    "iso:country":"GB",
    "wof:name":"BH23 5SG",
    "wof:placetype":"postalcode"
},
  "geometry": {"coordinates":[-1.69634213530676,50.75172112617214],"type":"Point"}
}