{
  "type": "Feature",
  "properties": {
    "iso:country": "GB",
    "wof:name": "BH23 5SG",
    "wof:placetype": "postalcode"
  },
  "geometry": {"coordinates":[-1.696342,50.751721],"type":"Point"}
}
