{
  "type": "Feature",
  "properties": {
    "iso:country":"GB",
    "wof:name":"EC3N 2EX",
    "wof:placetype":"postalcode"
},
  "geometry": {"coordinates":[-0.0768839967085,51.512555375992],"type":"Point"}
}