{
  "type": "Feature",
  "properties": {
    "iso:country": "GB",
    "wof:name": "NE12 8AX",
    "wof:placetype": "postalcode"
  },
  "geometry": {"coordinates":[-1.569145,55.017421],"type":"Point"}
}
