{
  "type": "Feature",
  "properties": {
    "iso:country":"GB",
    "wof:name":"NE12 8AX",
    "wof:placetype":"postalcode"
},
  "geometry": {"coordinates":[-1.56914529920395,55.01742111375911],"type":"Point"}
}