{
  "type": "Feature",
  "properties": {
    "iso:country": "GB",
    "wof:name": "BD21 4LZ",
    "wof:placetype": "postalcode"
  },
  "geometry": {"coordinates":[-1.883702,53.868979],"type":"Point"}
}
