{
  "type": "Feature",
  "properties": {
    "iso:country":"GB",
    "wof:name":"BD21 4LZ",
    "wof:placetype":"postalcode"
},
  "geometry": {"coordinates":[-1.88370228238738,53.86897890022685],"type":"Point"}
}