{
  "type": "Feature",
  "properties": {
    "iso:country": "GB",
    "wof:name": "EN6 1SF",
    "wof:placetype": "postalcode"
  },
  "geometry": {"coordinates":[-0.180015,51.706475],"type":"Point"}
}
