{
  "type": "Feature",
  "properties": {
    "iso:country":"GB",
    "wof:name":"EN6 1SF",
    "wof:placetype":"postalcode"
},
  "geometry": {"coordinates":[-0.18001506394905,51.70647496435065],"type":"Point"}
}