{
  "type": "Feature",
  "properties": {
    "date:inception_lower": "1980-01-01",
    "date:inception_upper": "1980-01-01",
    "iso:country": "GB",
    "wof:name": "PO10 8QX",
    "wof:placetype": "postalcode"
  },
  "geometry": {"coordinates":[-0.90049,50.869535],"type":"Point"}
}
