{
  "type": "Feature",
  "properties": {
    "iso:country":"GB",
    "wof:name":"SN12 7RY",
    "wof:placetype":"postalcode"
},
  "geometry": {"coordinates":[-2.12222063972697,51.37244648852572],"type":"Point"}
}