{
  "type": "Feature",
  "properties": {
    "iso:country": "GB",
    "wof:name": "SS9 2HA",
    "wof:placetype": "postalcode"
  },
  "geometry": {"coordinates":[0.652573,51.542562],"type":"Point"}
}
