{
  "type": "Feature",
  "properties": {
    "iso:country":"GB",
    "wof:name":"LN9 6JE",
    "wof:placetype":"postalcode"
},
  "geometry": {"coordinates":[-0.13400052903433,53.16320746462981],"type":"Point"}
}