{
  "type": "Feature",
  "properties": {
    "iso:country":"GB",
    "wof:name":"PE12 8NZ",
    "wof:placetype":"postalcode"
},
  "geometry": {"coordinates":[0.03539231110386,52.80405747062793],"type":"Point"}
}