{
  "type": "Feature",
  "properties": {
    "iso:country":"GB",
    "wof:name":"S43 3TU",
    "wof:placetype":"postalcode"
},
  "geometry": {"coordinates":[-1.3418786920777,53.26913892012405],"type":"Point"}
}