{
  "type": "Feature",
  "properties": {
    "iso:country":"GB",
    "wof:name":"PO13 0JR",
    "wof:placetype":"postalcode"
},
  "geometry": {"coordinates":[-1.17951372466524,50.81863747245703],"type":"Point"}
}