{
  "type": "Feature",
  "properties": {
    "date:inception_lower":"2003-03-01",
    "date:inception_upper":"2003-03-31",
    "iso:country":"GB",
    "wof:name":"DE72 2GE",
    "wof:placetype":"postalcode"
},
  "geometry": {"coordinates":[-1.36125,52.870582],"type":"Point"}
}