{
  "type": "Feature",
  "properties": {
    "iso:country": "GB",
    "wof:name": "CH3 5SH",
    "wof:placetype": "postalcode"
  },
  "geometry": {"coordinates":[-2.860957,53.182492],"type":"Point"}
}
