{
  "type": "Feature",
  "properties": {
    "iso:country":"GB",
    "wof:name":"TA21 0NE",
    "wof:placetype":"postalcode"
},
  "geometry": {"coordinates":[-3.32911145247603,50.96747361277329],"type":"Point"}
}