{
  "type": "Feature",
  "properties": {
    "date:inception_lower":"1980-01-01",
    "date:inception_upper":"1980-01-31",
    "iso:country":"GB",
    "wof:name":"LL53 8RD",
    "wof:placetype":"postalcode"
},
  "geometry": {"coordinates":[-4.583399,52.848552],"type":"Point"}
}