{
  "type": "Feature",
  "properties": {
    "iso:country":"GB",
    "wof:name":"LL53 8RD",
    "wof:placetype":"postalcode"
},
  "geometry": {"coordinates":[-4.5833995444623,52.84855202392749],"type":"Point"}
}