{
  "type": "Feature",
  "properties": {
    "date:inception_lower": "1980-01-01",
    "date:inception_upper": "1980-01-01",
    "iso:country": "GB",
    "wof:name": "KA19 8DU",
    "wof:placetype": "postalcode"
  },
  "geometry": {"coordinates":[-4.70602,55.356214],"type":"Point"}
}
