{
  "type": "Feature",
  "properties": {
    "iso:country":"GB",
    "wof:name":"KA19 8DU",
    "wof:placetype":"postalcode"
},
  "geometry": {"coordinates":[-4.70528304146109,55.35594761194255],"type":"Point"}
}