{
  "type": "Feature",
  "properties": {
    "iso:country":"GB",
    "wof:name":"SA62 5SY",
    "wof:placetype":"postalcode"
},
  "geometry": {"coordinates":[-4.97636228685076,51.92838679853312],"type":"Point"}
}