{
  "type": "Feature",
  "properties": {
    "date:inception_lower": "1980-01-01",
    "date:inception_upper": "1980-01-01",
    "iso:country": "GB",
    "wof:name": "SG19 1BA",
    "wof:placetype": "postalcode"
  },
  "geometry": {"coordinates":[-0.284999,52.12521],"type":"Point"}
}
