{
  "type": "Feature",
  "properties": {
    "iso:country":"GB",
    "wof:name":"WN6 0XA",
    "wof:placetype":"postalcode"
},
  "geometry": {"coordinates":[-2.65897697428561,53.58757346718169],"type":"Point"}
}