{
  "type": "Feature",
  "properties": {
    "date:inception_lower":"1980-01-01",
    "date:inception_upper":"1980-01-31",
    "iso:country":"GB",
    "wof:name":"WN6 0XA",
    "wof:placetype":"postalcode"
},
  "geometry": {"coordinates":[-2.658977,53.587573],"type":"Point"}
}