{
  "type": "Feature",
  "properties": {
    "iso:country":"GB",
    "wof:name":"PR6 9DZ",
    "wof:placetype":"postalcode"
},
  "geometry": {"coordinates":[-2.61194244744979,53.64345246336536],"type":"Point"}
}