{
  "type": "Feature",
  "properties": {
    "iso:country":"GB",
    "wof:name":"B20 2LE",
    "wof:placetype":"postalcode"
},
  "geometry": {"coordinates":[-1.92215548673764,52.52103876933594],"type":"Point"}
}