{
  "type": "Feature",
  "properties": {
    "iso:country": "GB",
    "wof:name": "WF4 2DQ",
    "wof:placetype": "postalcode"
  },
  "geometry": {"coordinates":[-1.413643,53.628761],"type":"Point"}
}
