{
  "type": "Feature",
  "properties": {
    "iso:country": "GB",
    "wof:name": "IP3 0RL",
    "wof:placetype": "postalcode"
  },
  "geometry": {"coordinates":[1.183045,52.033643],"type":"Point"}
}
