{
  "type": "Feature",
  "properties": {
    "iso:country":"GB",
    "wof:name":"IP3 0RL",
    "wof:placetype":"postalcode"
},
  "geometry": {"coordinates":[1.18304545227868,52.03364251331134],"type":"Point"}
}