{
  "type": "Feature",
  "properties": {
    "iso:country":"GB",
    "wof:name":"MK42 9JU",
    "wof:placetype":"postalcode"
},
  "geometry": {"coordinates":[-0.47211312375318,52.12704574619728],"type":"Point"}
}