{
  "type": "Feature",
  "properties": {
    "iso:country":"GB",
    "wof:name":"WC1R 5HP",
    "wof:placetype":"postalcode"
},
  "geometry": {"coordinates":[-0.11213441614165,51.51885632016273],"type":"Point"}
}