{
  "type": "Feature",
  "properties": {
    "iso:country":"GB",
    "wof:name":"G33 6NB",
    "wof:placetype":"postalcode"
},
  "geometry": {"coordinates":[-4.1633313617854,55.88364772347313],"type":"Point"}
}