{
  "type": "Feature",
  "properties": {
    "iso:country": "GB",
    "wof:name": "G33 6NB",
    "wof:placetype": "postalcode"
  },
  "geometry": {"coordinates":[-4.163331,55.883648],"type":"Point"}
}
