{
  "type": "Feature",
  "properties": {
    "iso:country":"GB",
    "wof:name":"AB21 9PA",
    "wof:placetype":"postalcode"
},
  "geometry": {"coordinates":[-2.16687817536194,57.17932878151225],"type":"Point"}
}