{
  "type": "Feature",
  "properties": {
    "iso:country": "GB",
    "wof:name": "DY4 9EA",
    "wof:placetype": "postalcode"
  },
  "geometry": {"coordinates":[-2.071948,52.537179],"type":"Point"}
}
