{
  "type": "Feature",
  "properties": {
    "iso:country":"GB",
    "wof:name":"S81 0DF",
    "wof:placetype":"postalcode"
},
  "geometry": {"coordinates":[-1.10670160390122,53.31126027997378],"type":"Point"}
}