{
  "type": "Feature",
  "properties": {
    "iso:country":"GB",
    "wof:name":"ST16 2NR",
    "wof:placetype":"postalcode"
},
  "geometry": {"coordinates":[-2.11756645997497,52.80776738025551],"type":"Point"}
}