{
  "type": "Feature",
  "properties": {
    "iso:country":"GB",
    "wof:name":"TR6 0DF",
    "wof:placetype":"postalcode"
},
  "geometry": {"coordinates":[-5.14534832750332,50.33846473724159],"type":"Point"}
}