{
  "type": "Feature",
  "properties": {
    "date:inception_lower": "1980-01-01",
    "date:inception_upper": "1980-01-01",
    "iso:country": "GB",
    "wof:name": "SY11 3AE",
    "wof:placetype": "postalcode"
  },
  "geometry": {"coordinates":[-3.008408,52.922878],"type":"Point"}
}
