{
  "type": "Feature",
  "properties": {
    "iso:country":"GB",
    "wof:name":"CT6 7EQ",
    "wof:placetype":"postalcode"
},
  "geometry": {"coordinates":[1.14640655452218,51.35979432822155],"type":"Point"}
}