{
  "type": "Feature",
  "properties": {
    "iso:country":"GB",
    "wof:name":"OL1 4RH",
    "wof:placetype":"postalcode"
},
  "geometry": {"coordinates":[-2.07622748117461,53.56753250861222],"type":"Point"}
}