{
  "type": "Feature",
  "properties": {
    "iso:country":"GB",
    "wof:name":"NG12 5HS",
    "wof:placetype":"postalcode"
},
  "geometry": {"coordinates":[-1.09031551520101,52.87552219955541],"type":"Point"}
}