{
  "type": "Feature",
  "properties": {
    "iso:country":"GB",
    "wof:name":"DG9 7BT",
    "wof:placetype":"postalcode"
},
  "geometry": {"coordinates":[-5.02333761256963,54.89468429549601],"type":"Point"}
}