{
  "type": "Feature",
  "properties": {
    "iso:country":"GB",
    "wof:name":"E17 9DE",
    "wof:placetype":"postalcode"
},
  "geometry": {"coordinates":[-0.00945090647324,51.57829938020975],"type":"Point"}
}