{
  "type": "Feature",
  "properties": {
    "iso:country":"GB",
    "wof:name":"TS1 3PF",
    "wof:placetype":"postalcode"
},
  "geometry": {"coordinates":[-1.23765869832887,54.56822168132432],"type":"Point"}
}