{
  "type": "Feature",
  "properties": {
    "date:inception_lower":"2017-08-01",
    "date:inception_upper":"2017-08-31",
    "iso:country":"GB",
    "wof:name":"BS37 7PP",
    "wof:placetype":"postalcode"
},
  "geometry": {"coordinates":[-2.428163,51.552673],"type":"Point"}
}