{
  "type": "Feature",
  "properties": {
    "iso:country": "GB",
    "wof:name": "BS37 7PP",
    "wof:placetype": "postalcode"
  },
  "geometry": {"coordinates":[-2.428163,51.552673],"type":"Point"}
}
