{
  "type": "Feature",
  "properties": {
    "date:inception_lower": "1997-12-01",
    "date:inception_upper": "1997-12-01",
    "iso:country": "GB",
    "wof:name": "BS36 2QD",
    "wof:placetype": "postalcode"
  },
  "geometry": {"coordinates":[-2.468344,51.527119],"type":"Point"}
}
