{
  "type": "Feature",
  "properties": {
    "iso:country": "GB",
    "wof:name": "BS36 2QD",
    "wof:placetype": "postalcode"
  },
  "geometry": {"coordinates":[-2.468344,51.527119],"type":"Point"}
}
