{
  "type": "Feature",
  "properties": {
    "iso:country":"GB",
    "wof:name":"W10 4HY",
    "wof:placetype":"postalcode"
},
  "geometry": {"coordinates":[-0.21021894696694,51.52954824920707],"type":"Point"}
}