{
  "type": "Feature",
  "properties": {
    "iso:country":"GB",
    "wof:name":"AL5 5LX",
    "wof:placetype":"postalcode"
},
  "geometry": {"coordinates":[-0.3475683114115,51.81332045136377],"type":"Point"}
}