{
  "type": "Feature",
  "properties": {
    "iso:country": "GB",
    "wof:name": "AL5 5LX",
    "wof:placetype": "postalcode"
  },
  "geometry": {"coordinates":[-0.347461,51.813209],"type":"Point"}
}
