{
  "type": "Feature",
  "properties": {
    "iso:country":"GB",
    "wof:name":"RH19 2DP",
    "wof:placetype":"postalcode"
},
  "geometry": {"coordinates":[-0.01116940079027,51.13690442559891],"type":"Point"}
}