{
  "type": "Feature",
  "properties": {
    "iso:country": "GB",
    "wof:name": "PR4 0QA",
    "wof:placetype": "postalcode"
  },
  "geometry": {"coordinates":[-2.815994,53.766201],"type":"Point"}
}
