{
  "type": "Feature",
  "properties": {
    "iso:country":"GB",
    "wof:name":"IP30 9FL",
    "wof:placetype":"postalcode"
},
  "geometry": {"coordinates":[0.91033021819525,52.23239263290583],"type":"Point"}
}