{
  "type": "Feature",
  "properties": {
    "iso:country": "GB",
    "wof:name": "IP30 9FL",
    "wof:placetype": "postalcode"
  },
  "geometry": {"coordinates":[0.910379,52.232436],"type":"Point"}
}
