{
  "type": "Feature",
  "properties": {
    "iso:country": "GB",
    "wof:name": "IP30 9FL",
    "wof:placetype": "postalcode"
  },
  "geometry": {"coordinates":[0.910377,52.232409],"type":"Point"}
}
