{
  "type": "Feature",
  "properties": {
    "iso:country":"GB",
    "wof:name":"TW13 4TL",
    "wof:placetype":"postalcode"
},
  "geometry": {"coordinates":[-0.42441091538249,51.44345340257254],"type":"Point"}
}