{
  "type": "Feature",
  "properties": {
    "date:inception_lower":"1980-01-01",
    "date:inception_upper":"1980-01-31",
    "iso:country":"GB",
    "wof:name":"GU3 1JJ",
    "wof:placetype":"postalcode"
},
  "geometry": {"coordinates":[-0.628051,51.213976],"type":"Point"}
}