{
  "type": "Feature",
  "properties": {
    "iso:country":"GB",
    "wof:name":"ML3 7UU",
    "wof:placetype":"postalcode"
},
  "geometry": {"coordinates":[-4.05483256444001,55.73933238506697],"type":"Point"}
}