{
  "type": "Feature",
  "properties": {
    "iso:country": "GB",
    "wof:name": "WV12 5DX",
    "wof:placetype": "postalcode"
  },
  "geometry": {"coordinates":[-2.046175,52.6197],"type":"Point"}
}
