{
  "type": "Feature",
  "properties": {
    "iso:country":"GB",
    "wof:name":"WV12 5DX",
    "wof:placetype":"postalcode"
},
  "geometry": {"coordinates":[-2.04617514733904,52.61970038342628],"type":"Point"}
}