{
  "type": "Feature",
  "properties": {
    "iso:country":"GB",
    "wof:name":"DH9 8PQ",
    "wof:placetype":"postalcode"
},
  "geometry": {"coordinates":[-1.7651929652889,54.85450549313986],"type":"Point"}
}