{
  "type": "Feature",
  "properties": {
    "iso:country": "GB",
    "wof:name": "SW17 7NH",
    "wof:placetype": "postalcode"
  },
  "geometry": {"coordinates":[-0.168649,51.434773],"type":"Point"}
}
