{
  "type": "Feature",
  "properties": {
    "iso:country":"GB",
    "wof:name":"SW17 7NH",
    "wof:placetype":"postalcode"
},
  "geometry": {"coordinates":[-0.16864900333195,51.43477295794531],"type":"Point"}
}