{
  "type": "Feature",
  "properties": {
    "date:inception_lower": "1980-01-01",
    "date:inception_upper": "1980-01-01",
    "iso:country": "GB",
    "wof:name": "TN20 6AR",
    "wof:placetype": "postalcode"
  },
  "geometry": {"coordinates":[0.255726,51.020249],"type":"Point"}
}
