{
  "type": "Feature",
  "properties": {
    "iso:country": "GB",
    "wof:name": "TN20 6AR",
    "wof:placetype": "postalcode"
  },
  "geometry": {"coordinates":[0.255683,51.020262],"type":"Point"}
}
