{
  "type": "Feature",
  "properties": {
    "date:inception_lower": "1994-12-01",
    "date:inception_upper": "1994-12-01",
    "iso:country": "GB",
    "wof:name": "SO50 5FF",
    "wof:placetype": "postalcode"
  },
  "geometry": {"coordinates":[-1.363873,50.964137],"type":"Point"}
}
