{
  "type": "Feature",
  "properties": {
    "iso:country":"GB",
    "wof:name":"SO50 5FF",
    "wof:placetype":"postalcode"
},
  "geometry": {"coordinates":[-1.36388301351371,50.96414475686728],"type":"Point"}
}