{
  "type": "Feature",
  "properties": {
    "iso:country": "GB",
    "wof:name": "SO50 5FF",
    "wof:placetype": "postalcode"
  },
  "geometry": {"coordinates":[-1.363873,50.964137],"type":"Point"}
}
