{
  "type": "Feature",
  "properties": {
    "iso:country":"GB",
    "wof:name":"PR25 5UN",
    "wof:placetype":"postalcode"
},
  "geometry": {"coordinates":[-2.67209799576361,53.69368014193961],"type":"Point"}
}