{
  "type": "Feature",
  "properties": {
    "iso:country":"GB",
    "wof:name":"NE65 0DZ",
    "wof:placetype":"postalcode"
},
  "geometry": {"coordinates":[-1.58496192263591,55.33291974096269],"type":"Point"}
}