{
  "type": "Feature",
  "properties": {
    "date:inception_lower":"1980-01-01",
    "date:inception_upper":"1980-01-31",
    "iso:country":"GB",
    "wof:name":"LL49 9AE",
    "wof:placetype":"postalcode"
},
  "geometry": {"coordinates":[-4.127368,52.924335],"type":"Point"}
}