{
  "type": "Feature",
  "properties": {
    "iso:country":"GB",
    "wof:name":"WV10 8QU",
    "wof:placetype":"postalcode"
},
  "geometry": {"coordinates":[-2.09271383570854,52.63151248618829],"type":"Point"}
}