{
  "type": "Feature",
  "properties": {
    "iso:country":"GB",
    "wof:name":"DA14 6TJ",
    "wof:placetype":"postalcode"
},
  "geometry": {"coordinates":[0.09470269538031,51.42634236607942],"type":"Point"}
}