{
  "type": "Feature",
  "properties": {
    "date:inception_lower":"1983-01-01",
    "date:inception_upper":"1983-01-31",
    "iso:country":"GB",
    "wof:name":"DA14 6TJ",
    "wof:placetype":"postalcode"
},
  "geometry": {"coordinates":[0.094703,51.426342],"type":"Point"}
}