{
  "type": "Feature",
  "properties": {
    "iso:country": "GB",
    "wof:name": "DA14 6TJ",
    "wof:placetype": "postalcode"
  },
  "geometry": {"coordinates":[0.094703,51.426342],"type":"Point"}
}
