{
  "type": "Feature",
  "properties": {
    "iso:country": "GB",
    "wof:name": "WD23 2GX",
    "wof:placetype": "postalcode"
  },
  "geometry": {"coordinates":[-0.378479,51.65159],"type":"Point"}
}
