{
  "type": "Feature",
  "properties": {
    "iso:country":"GB",
    "wof:name":"WD23 2GX",
    "wof:placetype":"postalcode"
},
  "geometry": {"coordinates":[-0.37847867444669,51.65159008695431],"type":"Point"}
}