{
  "type": "Feature",
  "properties": {
    "iso:country":"GB",
    "wof:name":"DY3 3PT",
    "wof:placetype":"postalcode"
},
  "geometry": {"coordinates":[-2.13503163366586,52.54603268121357],"type":"Point"}
}