{
  "type": "Feature",
  "properties": {
    "iso:country": "GB",
    "wof:name": "G78 2TL",
    "wof:placetype": "postalcode"
  },
  "geometry": {"coordinates":[-4.385555,55.799324],"type":"Point"}
}
