{
  "type": "Feature",
  "properties": {
    "iso:country": "GB",
    "wof:name": "HD9 2QN",
    "wof:placetype": "postalcode"
  },
  "geometry": {"coordinates":[-1.822845,53.557674],"type":"Point"}
}
