{
  "type": "Feature",
  "properties": {
    "iso:country":"GB",
    "wof:name":"HD9 2QN",
    "wof:placetype":"postalcode"
},
  "geometry": {"coordinates":[-1.8228448658114,53.5576738497488],"type":"Point"}
}