{
  "type": "Feature",
  "properties": {
    "iso:country": "GB",
    "wof:name": "DD8 2RE",
    "wof:placetype": "postalcode"
  },
  "geometry": {"coordinates":[-2.863956,56.638032],"type":"Point"}
}
