{
  "type": "Feature",
  "properties": {
    "iso:country": "GB",
    "wof:name": "OL12 0EE",
    "wof:placetype": "postalcode"
  },
  "geometry": {"coordinates":[-2.149439,53.626274],"type":"Point"}
}
