{
  "type": "Feature",
  "properties": {
    "date:inception_lower": "2021-08-01",
    "date:inception_upper": "2021-08-01",
    "iso:country": "GB",
    "wof:name": "LS12 4FD",
    "wof:placetype": "postalcode"
  },
  "geometry": {"coordinates":[-1.606575,53.791461],"type":"Point"}
}
