{
  "type": "Feature",
  "properties": {
    "iso:country": "GB",
    "wof:name": "G82 1BX",
    "wof:placetype": "postalcode"
  },
  "geometry": {"coordinates":[-4.550816,55.942404],"type":"Point"}
}
