{
  "type": "Feature",
  "properties": {
    "date:inception_lower": "1980-01-01",
    "date:inception_upper": "1980-01-01",
    "iso:country": "GB",
    "wof:name": "NG22 8RT",
    "wof:placetype": "postalcode"
  },
  "geometry": {"coordinates":[-1.026471,53.133842],"type":"Point"}
}
