{
  "type": "Feature",
  "properties": {
    "iso:country":"GB",
    "wof:name":"AL9 5ER",
    "wof:placetype":"postalcode"
},
  "geometry": {"coordinates":[-0.21455140133854,51.76445553248026],"type":"Point"}
}