{
  "type": "Feature",
  "properties": {
    "iso:country": "GB",
    "wof:name": "AL9 5ER",
    "wof:placetype": "postalcode"
  },
  "geometry": {"coordinates":[-0.214537,51.764455],"type":"Point"}
}
