{
  "type": "Feature",
  "properties": {
    "iso:country":"GB",
    "wof:name":"LN6 0RW",
    "wof:placetype":"postalcode"
},
  "geometry": {"coordinates":[-0.61421665934592,53.2142162546662],"type":"Point"}
}