{
  "type": "Feature",
  "properties": {
    "date:inception_lower":"2008-04-01",
    "date:inception_upper":"2008-04-30",
    "iso:country":"GB",
    "wof:name":"LN6 0RW",
    "wof:placetype":"postalcode"
},
  "geometry": {"coordinates":[-0.614217,53.214216],"type":"Point"}
}