{
  "type": "Feature",
  "properties": {
    "iso:country":"GB",
    "wof:name":"ML11 9RJ",
    "wof:placetype":"postalcode"
},
  "geometry": {"coordinates":[-3.91459797531443,55.66279204245294],"type":"Point"}
}