{
  "type": "Feature",
  "properties": {
    "iso:country": "GB",
    "wof:name": "HU1 1XD",
    "wof:placetype": "postalcode"
  },
  "geometry": {"coordinates":[-0.333507,53.738686],"type":"Point"}
}
