{
  "type": "Feature",
  "properties": {
    "iso:country":"GB",
    "wof:name":"SP3 5PW",
    "wof:placetype":"postalcode"
},
  "geometry": {"coordinates":[-2.06167270385482,51.04544021673918],"type":"Point"}
}