{
  "type": "Feature",
  "properties": {
    "iso:country":"GB",
    "wof:name":"M11 4RL",
    "wof:placetype":"postalcode"
},
  "geometry": {"coordinates":[-2.1784852437992,53.48306747559219],"type":"Point"}
}