{
  "type": "Feature",
  "properties": {
    "iso:country":"GB",
    "wof:name":"L14 6UA",
    "wof:placetype":"postalcode"
},
  "geometry": {"coordinates":[-2.88037746800833,53.4135744032619],"type":"Point"}
}