{
  "type": "Feature",
  "properties": {
    "iso:country":"GB",
    "wof:name":"S12 4YG",
    "wof:placetype":"postalcode"
},
  "geometry": {"coordinates":[-1.40125370677939,53.34543433956933],"type":"Point"}
}