{
  "type": "Feature",
  "properties": {
    "date:inception_lower": "2020-10-01",
    "date:inception_upper": "2020-10-01",
    "iso:country": "GB",
    "wof:name": "RH10 1LH",
    "wof:placetype": "postalcode"
  },
  "geometry": {"coordinates":[-0.187815,51.114825],"type":"Point"}
}
