{
  "type": "Feature",
  "properties": {
    "iso:country":"GB",
    "wof:name":"IG8 0BS",
    "wof:placetype":"postalcode"
},
  "geometry": {"coordinates":[0.02624329140188,51.60882981884892],"type":"Point"}
}