{
  "type": "Feature",
  "properties": {
    "iso:country": "GB",
    "wof:name": "SA70 7PG",
    "wof:placetype": "postalcode"
  },
  "geometry": {"coordinates":[-4.725227,51.66478],"type":"Point"}
}
