{
  "type": "Feature",
  "properties": {
    "iso:country":"GB",
    "wof:name":"SA70 7PG",
    "wof:placetype":"postalcode"
},
  "geometry": {"coordinates":[-4.725226648672,51.66477986715562],"type":"Point"}
}