{
  "type": "Feature",
  "properties": {
    "iso:country":"GB",
    "wof:name":"M30 8JQ",
    "wof:placetype":"postalcode"
},
  "geometry": {"coordinates":[-2.37743564920531,53.4923658403831],"type":"Point"}
}