{
  "type": "Feature",
  "properties": {
    "iso:country":"GB",
    "wof:name":"EX31 3DU",
    "wof:placetype":"postalcode"
},
  "geometry": {"coordinates":[-4.14359161598318,51.07003689912003],"type":"Point"}
}