{
  "type": "Feature",
  "properties": {
    "date:inception_lower":"1980-01-01",
    "date:inception_upper":"1980-01-31",
    "iso:country":"GB",
    "wof:name":"EX31 3DU",
    "wof:placetype":"postalcode"
},
  "geometry": {"coordinates":[-4.143833,51.070005],"type":"Point"}
}