{
  "type": "Feature",
  "properties": {
    "iso:country": "GB",
    "wof:name": "EX31 3DU",
    "wof:placetype": "postalcode"
  },
  "geometry": {"coordinates":[-4.143833,51.070005],"type":"Point"}
}
