{
  "type": "Feature",
  "properties": {
    "iso:country":"GB",
    "wof:name":"HP19 0WA",
    "wof:placetype":"postalcode"
},
  "geometry": {"coordinates":[-0.80608033336239,51.83171763896743],"type":"Point"}
}