{
  "type": "Feature",
  "properties": {
    "date:inception_lower":"2000-06-01",
    "date:inception_upper":"2000-06-30",
    "iso:country":"GB",
    "wof:name":"HP19 0WA",
    "wof:placetype":"postalcode"
},
  "geometry": {"coordinates":[-0.80608,51.831718],"type":"Point"}
}