{
  "type": "Feature",
  "properties": {
    "iso:country": "GB",
    "wof:name": "HP19 0WA",
    "wof:placetype": "postalcode"
  },
  "geometry": {"coordinates":[-0.80608,51.831718],"type":"Point"}
}
