{
  "type": "Feature",
  "properties": {
    "date:inception_lower": "1986-04-01",
    "date:inception_upper": "1986-04-01",
    "iso:country": "GB",
    "wof:name": "AL3 6NP",
    "wof:placetype": "postalcode"
  },
  "geometry": {"coordinates":[-0.334381,51.769641],"type":"Point"}
}
