{
  "type": "Feature",
  "properties": {
    "iso:country": "GB",
    "wof:name": "TN15 6XT",
    "wof:placetype": "postalcode"
  },
  "geometry": {"coordinates":[0.225057,51.335312],"type":"Point"}
}
