{
  "type": "Feature",
  "properties": {
    "iso:country":"GB",
    "wof:name":"TN15 6XT",
    "wof:placetype":"postalcode"
},
  "geometry": {"coordinates":[0.2250296492645,51.33531291652277],"type":"Point"}
}