{
  "type": "Feature",
  "properties": {
    "iso:country":"GB",
    "wof:name":"N4 1DG",
    "wof:placetype":"postalcode"
},
  "geometry": {"coordinates":[-0.09730710622389,51.57440626843222],"type":"Point"}
}