{
  "type": "Feature",
  "properties": {
    "iso:country":"GB",
    "wof:name":"SG4 8QT",
    "wof:placetype":"postalcode"
},
  "geometry": {"coordinates":[-0.30632659392443,51.84845842007256],"type":"Point"}
}