{
  "type": "Feature",
  "properties": {
    "iso:country":"GB",
    "wof:name":"CW8 1JF",
    "wof:placetype":"postalcode"
},
  "geometry": {"coordinates":[-2.53477323263157,53.25090357112912],"type":"Point"}
}