{
  "type": "Feature",
  "properties": {
    "iso:country": "GB",
    "wof:name": "CW8 1JF",
    "wof:placetype": "postalcode"
  },
  "geometry": {"coordinates":[-2.534773,53.250904],"type":"Point"}
}
