{
  "type": "Feature",
  "properties": {
    "iso:country":"GB",
    "wof:name":"NN1 5EH",
    "wof:placetype":"postalcode"
},
  "geometry": {"coordinates":[-0.88421811706008,52.24040867799203],"type":"Point"}
}