{
  "type": "Feature",
  "properties": {
    "iso:country":"GB",
    "wof:name":"SO30 0GE",
    "wof:placetype":"postalcode"
},
  "geometry": {"coordinates":[-1.29549732476356,50.91455465788802],"type":"Point"}
}