{
  "type": "Feature",
  "properties": {
    "iso:country":"GB",
    "wof:name":"CF64 5SS",
    "wof:placetype":"postalcode"
},
  "geometry": {"coordinates":[-3.21217537656285,51.40376136102229],"type":"Point"}
}