{
  "type": "Feature",
  "properties": {
    "iso:country": "GB",
    "wof:name": "CF64 5SS",
    "wof:placetype": "postalcode"
  },
  "geometry": {"coordinates":[-3.212171,51.403779],"type":"Point"}
}
