{
  "type": "Feature",
  "properties": {
    "iso:country":"GB",
    "wof:name":"BS35 4LR",
    "wof:placetype":"postalcode"
},
  "geometry": {"coordinates":[-2.64794680931689,51.56419073364155],"type":"Point"}
}