{
  "type": "Feature",
  "properties": {
    "iso:country": "GB",
    "wof:name": "BS35 4LR",
    "wof:placetype": "postalcode"
  },
  "geometry": {"coordinates":[-2.647947,51.564191],"type":"Point"}
}
