{
  "type": "Feature",
  "properties": {
    "date:inception_lower":"1980-01-01",
    "date:inception_upper":"1980-01-31",
    "iso:country":"GB",
    "wof:name":"G51 4BE",
    "wof:placetype":"postalcode"
},
  "geometry": {"coordinates":[-4.329134,55.858323],"type":"Point"}
}