{
  "type": "Feature",
  "properties": {
    "iso:country": "GB",
    "wof:name": "MK41 0AW",
    "wof:placetype": "postalcode"
  },
  "geometry": {"coordinates":[-0.428786,52.148154],"type":"Point"}
}
