{
  "type": "Feature",
  "properties": {
    "iso:country":"GB",
    "wof:name":"MK41 0AW",
    "wof:placetype":"postalcode"
},
  "geometry": {"coordinates":[-0.42878590035538,52.148154470923],"type":"Point"}
}