{
  "type": "Feature",
  "properties": {
    "iso:country": "GB",
    "wof:name": "DN9 3NF",
    "wof:placetype": "postalcode"
  },
  "geometry": {"coordinates":[-1.023469,53.488301],"type":"Point"}
}
