{
  "type": "Feature",
  "properties": {
    "iso:country":"GB",
    "wof:name":"GL4 5WL",
    "wof:placetype":"postalcode"
},
  "geometry": {"coordinates":[-2.19068813614392,51.84369729828624],"type":"Point"}
}