{
  "type": "Feature",
  "properties": {
    "date:inception_lower": "2011-01-01",
    "date:inception_upper": "2011-01-01",
    "iso:country": "GB",
    "wof:name": "CA10 1SJ",
    "wof:placetype": "postalcode"
  },
  "geometry": {"coordinates":[-2.611053,54.656501],"type":"Point"}
}
