{
  "type": "Feature",
  "properties": {
    "iso:country": "GB",
    "wof:name": "DY10 1SH",
    "wof:placetype": "postalcode"
  },
  "geometry": {"coordinates":[-2.239248,52.386996],"type":"Point"}
}
