{
  "type": "Feature",
  "properties": {
    "date:inception_lower": "2008-07-01",
    "date:inception_upper": "2008-07-01",
    "iso:country": "GB",
    "wof:name": "SW19 8JJ",
    "wof:placetype": "postalcode"
  },
  "geometry": {"coordinates":[-0.191338,51.427113],"type":"Point"}
}
