{
  "type": "Feature",
  "properties": {
    "date:inception_lower": "1980-01-01",
    "date:inception_upper": "1980-01-01",
    "iso:country": "GB",
    "wof:name": "ST10 4NQ",
    "wof:placetype": "postalcode"
  },
  "geometry": {"coordinates":[-1.949164,52.935976],"type":"Point"}
}
