{
  "type": "Feature",
  "properties": {
    "date:inception_lower": "2022-09-01",
    "date:inception_upper": "2022-09-01",
    "iso:country": "GB",
    "wof:name": "WF2 8FL",
    "wof:placetype": "postalcode"
  },
  "geometry": {"coordinates":[-1.542891,53.671801],"type":"Point"}
}
