{
  "type": "Feature",
  "properties": {
    "date:inception_lower": "2020-07-01",
    "date:inception_upper": "2020-07-01",
    "iso:country": "GB",
    "wof:name": "WF2 6UF",
    "wof:placetype": "postalcode"
  },
  "geometry": {"coordinates":[-1.457402,53.646754],"type":"Point"}
}
