{
  "type": "Feature",
  "properties": {
    "iso:country":"GB",
    "wof:name":"EX20 9AF",
    "wof:placetype":"postalcode"
},
  "geometry": {"coordinates":[-4.00318622647819,50.73767334105057],"type":"Point"}
}