{
  "type": "Feature",
  "properties": {
    "date:inception_lower":"2014-07-01",
    "date:inception_upper":"2014-07-31",
    "iso:country":"GB",
    "wof:name":"EX20 9AF",
    "wof:placetype":"postalcode"
},
  "geometry": {"coordinates":[-4.003186,50.737673],"type":"Point"}
}