{
  "type": "Feature",
  "properties": {
    "iso:country":"GB",
    "wof:name":"S60 2HB",
    "wof:placetype":"postalcode"
},
  "geometry": {"coordinates":[-1.35522451704583,53.42842137864975],"type":"Point"}
}