{
  "type": "Feature",
  "properties": {
    "iso:country":"GB",
    "wof:name":"PL9 7EG",
    "wof:placetype":"postalcode"
},
  "geometry": {"coordinates":[-4.08424375506884,50.36365436614819],"type":"Point"}
}