{
  "type": "Feature",
  "properties": {
    "iso:country":"GB",
    "wof:name":"WF17 8DX",
    "wof:placetype":"postalcode"
},
  "geometry": {"coordinates":[-1.65467588795795,53.7193200476113],"type":"Point"}
}