{
  "type": "Feature",
  "properties": {
    "iso:country":"GB",
    "wof:name":"TS7 0EF",
    "wof:placetype":"postalcode"
},
  "geometry": {"coordinates":[-1.17484816178752,54.5321488997531],"type":"Point"}
}