{
  "type": "Feature",
  "properties": {
    "iso:country":"GB",
    "wof:name":"CA1 1DE",
    "wof:placetype":"postalcode"
},
  "geometry": {"coordinates":[-2.92800442891941,54.89355681286351],"type":"Point"}
}