{
  "type": "Feature",
  "properties": {
    "iso:country":"GB",
    "wof:name":"SY8 2JU",
    "wof:placetype":"postalcode"
},
  "geometry": {"coordinates":[-2.766334747507,52.38834048156547],"type":"Point"}
}