{
  "type": "Feature",
  "properties": {
    "date:inception_lower": "1980-01-01",
    "date:inception_upper": "1980-01-01",
    "iso:country": "GB",
    "wof:name": "SY8 2JU",
    "wof:placetype": "postalcode"
  },
  "geometry": {"coordinates":[-2.76629,52.388363],"type":"Point"}
}
