{
  "type": "Feature",
  "properties": {
    "iso:country":"GB",
    "wof:name":"M16 0WN",
    "wof:placetype":"postalcode"
},
  "geometry": {"coordinates":[-2.27767055899915,53.45772821409926],"type":"Point"}
}