{
  "type": "Feature",
  "properties": {
    "iso:country":"GB",
    "wof:name":"WR14 2UW",
    "wof:placetype":"postalcode"
},
  "geometry": {"coordinates":[-2.30519693397478,52.12123395784414],"type":"Point"}
}