{
  "type": "Feature",
  "properties": {
    "date:inception_lower": "1980-01-01",
    "date:inception_upper": "1980-01-01",
    "iso:country": "GB",
    "wof:name": "EX5 3AY",
    "wof:placetype": "postalcode"
  },
  "geometry": {"coordinates":[-3.430015,50.745528],"type":"Point"}
}
