{
  "type": "Feature",
  "properties": {
    "iso:country":"GB",
    "wof:name":"EX5 3AY",
    "wof:placetype":"postalcode"
},
  "geometry": {"coordinates":[-3.429985287067,50.74548504107034],"type":"Point"}
}