{
  "type": "Feature",
  "properties": {
    "iso:country":"GB",
    "wof:name":"NE39 2JJ",
    "wof:placetype":"postalcode"
},
  "geometry": {"coordinates":[-1.75820247824735,54.92173663160199],"type":"Point"}
}