{
  "type": "Feature",
  "properties": {
    "date:inception_lower": "1980-01-01",
    "date:inception_upper": "1980-01-01",
    "iso:country": "GB",
    "wof:name": "NR23 1JZ",
    "wof:placetype": "postalcode"
  },
  "geometry": {"coordinates":[0.85539,52.955139],"type":"Point"}
}
