{
  "type": "Feature",
  "properties": {
    "date:inception_lower": "2024-07-01",
    "date:inception_upper": "2024-07-01",
    "iso:country": "GB",
    "wof:name": "CA16 6QG",
    "wof:placetype": "postalcode"
  },
  "geometry": {"coordinates":[-2.393716,54.53077],"type":"Point"}
}
