{
  "type": "Feature",
  "properties": {
    "date:inception_lower": "1980-01-01",
    "date:inception_upper": "1980-01-01",
    "iso:country": "GB",
    "wof:name": "DE15 0JN",
    "wof:placetype": "postalcode"
  },
  "geometry": {"coordinates":[-1.613196,52.807062],"type":"Point"}
}
