{
  "type": "Feature",
  "properties": {
    "iso:country":"GB",
    "wof:name":"DE15 0JN",
    "wof:placetype":"postalcode"
},
  "geometry": {"coordinates":[-1.6131960977162,52.80706160066728],"type":"Point"}
}