{
  "type": "Feature",
  "properties": {
    "iso:country":"GB",
    "wof:name":"LS9 7RT",
    "wof:placetype":"postalcode"
},
  "geometry": {"coordinates":[-1.51623681062599,53.79954565597549],"type":"Point"}
}