{
  "type": "Feature",
  "properties": {
    "iso:country":"GB",
    "wof:name":"GU22 8SA",
    "wof:placetype":"postalcode"
},
  "geometry": {"coordinates":[-0.51532197178993,51.32048310518974],"type":"Point"}
}