{
  "type": "Feature",
  "properties": {
    "iso:country": "GB",
    "wof:name": "DL1 4QT",
    "wof:placetype": "postalcode"
  },
  "geometry": {"coordinates":[-1.528057,54.511296],"type":"Point"}
}
