{
  "type": "Feature",
  "properties": {
    "iso:country":"GB",
    "wof:name":"DL1 4QT",
    "wof:placetype":"postalcode"
},
  "geometry": {"coordinates":[-1.52805664833693,54.51129586651702],"type":"Point"}
}