{
  "type": "Feature",
  "properties": {
    "iso:country":"GB",
    "wof:name":"SE6 4YH",
    "wof:placetype":"postalcode"
},
  "geometry": {"coordinates":[-0.03215781625663,51.44510574809894],"type":"Point"}
}