{
  "type": "Feature",
  "properties": {
    "iso:country":"GB",
    "wof:name":"NE40 3JT",
    "wof:placetype":"postalcode"
},
  "geometry": {"coordinates":[-1.75935711644008,54.96881794956029],"type":"Point"}
}