{
  "type": "Feature",
  "properties": {
    "date:inception_lower":"1985-10-01",
    "date:inception_upper":"1985-10-31",
    "iso:country":"GB",
    "wof:name":"NE40 3JT",
    "wof:placetype":"postalcode"
},
  "geometry": {"coordinates":[-1.759357,54.968818],"type":"Point"}
}