{
  "type": "Feature",
  "properties": {
    "iso:country": "GB",
    "wof:name": "NE40 3JT",
    "wof:placetype": "postalcode"
  },
  "geometry": {"coordinates":[-1.759357,54.968818],"type":"Point"}
}
