{
  "type": "Feature",
  "properties": {
    "date:inception_lower": "1991-09-01",
    "date:inception_upper": "1991-09-01",
    "iso:country": "GB",
    "wof:name": "GL5 4LH",
    "wof:placetype": "postalcode"
  },
  "geometry": {"coordinates":[-2.247035,51.742542],"type":"Point"}
}
