{
  "type": "Feature",
  "properties": {
    "iso:country":"GB",
    "wof:name":"PL13 2RP",
    "wof:placetype":"postalcode"
},
  "geometry": {"coordinates":[-4.52077955500941,50.33151214453803],"type":"Point"}
}