{
  "type": "Feature",
  "properties": {
    "iso:country": "GB",
    "wof:name": "PL13 2RP",
    "wof:placetype": "postalcode"
  },
  "geometry": {"coordinates":[-4.520932,50.331522],"type":"Point"}
}
