{
  "type": "Feature",
  "properties": {
    "iso:country": "GB",
    "wof:name": "NR30 4DA",
    "wof:placetype": "postalcode"
  },
  "geometry": {"coordinates":[1.727879,52.619323],"type":"Point"}
}
