{
  "type": "Feature",
  "properties": {
    "iso:country": "GB",
    "wof:name": "PE11 3GB",
    "wof:placetype": "postalcode"
  },
  "geometry": {"coordinates":[-0.163374,52.798445],"type":"Point"}
}
