{
  "type": "Feature",
  "properties": {
    "iso:country":"GB",
    "wof:name":"PE11 3GB",
    "wof:placetype":"postalcode"
},
  "geometry": {"coordinates":[-0.16337414377036,52.79844462358069],"type":"Point"}
}