{
  "type": "Feature",
  "properties": {
    "date:inception_lower": "1999-06-01",
    "date:inception_upper": "1999-06-01",
    "iso:country": "GB",
    "wof:name": "CH46 7TE",
    "wof:placetype": "postalcode"
  },
  "geometry": {"coordinates":[-3.112218,53.400753],"type":"Point"}
}
