{
  "type": "Feature",
  "properties": {
    "iso:country": "GB",
    "wof:name": "CH46 7TE",
    "wof:placetype": "postalcode"
  },
  "geometry": {"coordinates":[-3.11243,53.400805],"type":"Point"}
}
