{
  "type": "Feature",
  "properties": {
    "iso:country":"GB",
    "wof:name":"CH46 7TE",
    "wof:placetype":"postalcode"
},
  "geometry": {"coordinates":[-3.11233908870948,53.40068989606489],"type":"Point"}
}