{
  "type": "Feature",
  "properties": {
    "iso:country":"GB",
    "wof:name":"TA4 1NY",
    "wof:placetype":"postalcode"
},
  "geometry": {"coordinates":[-3.18792475464775,51.040702528529],"type":"Point"}
}