{
  "type": "Feature",
  "properties": {
    "iso:country":"GB",
    "wof:name":"NG22 8LH",
    "wof:placetype":"postalcode"
},
  "geometry": {"coordinates":[-1.03691121818805,53.10612309665147],"type":"Point"}
}