{
  "type": "Feature",
  "properties": {
    "iso:country":"GB",
    "wof:name":"RH6 9LY",
    "wof:placetype":"postalcode"
},
  "geometry": {"coordinates":[-0.1243700249056,51.17459413643898],"type":"Point"}
}