{
  "type": "Feature",
  "properties": {
    "iso:country": "GB",
    "wof:name": "WA16 9JR",
    "wof:placetype": "postalcode"
  },
  "geometry": {"coordinates":[-2.396685,53.237338],"type":"Point"}
}
