{
  "type": "Feature",
  "properties": {
    "iso:country": "GB",
    "wof:name": "WA16 9JR",
    "wof:placetype": "postalcode"
  },
  "geometry": {"coordinates":[-2.400065,53.239862],"type":"Point"}
}
