{
  "type": "Feature",
  "properties": {
    "iso:country":"GB",
    "wof:name":"SL2 4EH",
    "wof:placetype":"postalcode"
},
  "geometry": {"coordinates":[-0.58558595526768,51.54868376600066],"type":"Point"}
}