{
  "type": "Feature",
  "properties": {
    "iso:country": "GB",
    "wof:name": "SL2 4EH",
    "wof:placetype": "postalcode"
  },
  "geometry": {"coordinates":[-0.585567,51.548686],"type":"Point"}
}
