{
  "type": "Feature",
  "properties": {
    "iso:country":"GB",
    "wof:name":"WA7 1HX",
    "wof:placetype":"postalcode"
},
  "geometry": {"coordinates":[-2.74002509537377,53.342625439556],"type":"Point"}
}