{
  "type": "Feature",
  "properties": {
    "iso:country":"GB",
    "wof:name":"LN2 2BQ",
    "wof:placetype":"postalcode"
},
  "geometry": {"coordinates":[-0.53039521448201,53.25318906957218],"type":"Point"}
}