{
  "type": "Feature",
  "properties": {
    "iso:country": "GB",
    "wof:name": "L23 0RU",
    "wof:placetype": "postalcode"
  },
  "geometry": {"coordinates":[-3.026726,53.484299],"type":"Point"}
}
