{
  "type": "Feature",
  "properties": {
    "iso:country":"GB",
    "wof:name":"L23 0RU",
    "wof:placetype":"postalcode"
},
  "geometry": {"coordinates":[-3.02672613380325,53.48429874987045],"type":"Point"}
}