{
  "type": "Feature",
  "properties": {
    "date:inception_lower": "1980-01-01",
    "date:inception_upper": "1980-01-01",
    "iso:country": "GB",
    "wof:name": "L23 0RU",
    "wof:placetype": "postalcode"
  },
  "geometry": {"coordinates":[-3.026726,53.484299],"type":"Point"}
}
