{
  "type": "Feature",
  "properties": {
    "date:inception_lower": "1999-12-01",
    "date:inception_upper": "1999-12-01",
    "iso:country": "GB",
    "wof:name": "BB7 2QT",
    "wof:placetype": "postalcode"
  },
  "geometry": {"coordinates":[-2.412129,53.873221],"type":"Point"}
}
