{
  "type": "Feature",
  "properties": {
    "iso:country": "GB",
    "wof:name": "BB7 2QT",
    "wof:placetype": "postalcode"
  },
  "geometry": {"coordinates":[-2.412129,53.873221],"type":"Point"}
}
