{
  "type": "Feature",
  "properties": {
    "date:inception_lower":"1980-01-01",
    "date:inception_upper":"1980-01-31",
    "iso:country":"GB",
    "wof:name":"ST1 2NU",
    "wof:placetype":"postalcode"
},
  "geometry": {"coordinates":[-2.167093,53.026085],"type":"Point"}
}