{
  "type": "Feature",
  "properties": {
    "iso:country":"GB",
    "wof:name":"DN16 1DT",
    "wof:placetype":"postalcode"
},
  "geometry": {"coordinates":[-0.62583420438827,53.57571200289711],"type":"Point"}
}