{
  "type": "Feature",
  "properties": {
    "date:inception_lower": "1983-01-01",
    "date:inception_upper": "1983-01-01",
    "iso:country": "GB",
    "wof:name": "B32 1JL",
    "wof:placetype": "postalcode"
  },
  "geometry": {"coordinates":[-1.991032,52.456603],"type":"Point"}
}
