{
  "type": "Feature",
  "properties": {
    "iso:country":"GB",
    "wof:name":"CH45 2LS",
    "wof:placetype":"postalcode"
},
  "geometry": {"coordinates":[-3.03789901287081,53.43823301875048],"type":"Point"}
}