{
  "type": "Feature",
  "properties": {
    "date:inception_lower": "1999-06-01",
    "date:inception_upper": "1999-06-01",
    "iso:country": "GB",
    "wof:name": "CH45 2LS",
    "wof:placetype": "postalcode"
  },
  "geometry": {"coordinates":[-3.037974,53.438214],"type":"Point"}
}
