{
  "type": "Feature",
  "properties": {
    "iso:country":"GB",
    "wof:name":"NG34 9NN",
    "wof:placetype":"postalcode"
},
  "geometry": {"coordinates":[-0.3918365021694,52.99879162623363],"type":"Point"}
}