{
  "type": "Feature",
  "properties": {
    "iso:country": "GB",
    "wof:name": "NR26 8UU",
    "wof:placetype": "postalcode"
  },
  "geometry": {"coordinates":[1.196596,52.937193],"type":"Point"}
}
