{
  "type": "Feature",
  "properties": {
    "iso:country": "GB",
    "wof:name": "EN2 7JL",
    "wof:placetype": "postalcode"
  },
  "geometry": {"coordinates":[-0.121953,51.651472],"type":"Point"}
}
