{
  "type": "Feature",
  "properties": {
    "iso:country":"GB",
    "wof:name":"LS24 9EP",
    "wof:placetype":"postalcode"
},
  "geometry": {"coordinates":[-1.17268950735174,53.83937385969033],"type":"Point"}
}