{
  "type": "Feature",
  "properties": {
    "iso:country": "GB",
    "wof:name": "PR8 3PJ",
    "wof:placetype": "postalcode"
  },
  "geometry": {"coordinates":[-3.03932,53.599255],"type":"Point"}
}
