{
  "type": "Feature",
  "properties": {
    "iso:country":"GB",
    "wof:name":"PR8 3PJ",
    "wof:placetype":"postalcode"
},
  "geometry": {"coordinates":[-3.03931959928435,53.59925518515516],"type":"Point"}
}