{
  "type": "Feature",
  "properties": {
    "iso:country":"GB",
    "wof:name":"TN23 5GA",
    "wof:placetype":"postalcode"
},
  "geometry": {"coordinates":[0.83775462224447,51.14031749458343],"type":"Point"}
}