{
  "type": "Feature",
  "properties": {
    "iso:country": "GB",
    "wof:name": "TN23 5GA",
    "wof:placetype": "postalcode"
  },
  "geometry": {"coordinates":[0.837755,51.140317],"type":"Point"}
}
