{
  "type": "Feature",
  "properties": {
    "iso:country":"GB",
    "wof:name":"W1G 9PX",
    "wof:placetype":"postalcode"
},
  "geometry": {"coordinates":[-0.146751543982,51.51897674269549],"type":"Point"}
}