{
  "type": "Feature",
  "properties": {
    "iso:country":"GB",
    "wof:name":"WA8 3XL",
    "wof:placetype":"postalcode"
},
  "geometry": {"coordinates":[-2.69356741887363,53.39712498271552],"type":"Point"}
}