{
  "type": "Feature",
  "properties": {
    "iso:country": "GB",
    "wof:name": "WA8 3XL",
    "wof:placetype": "postalcode"
  },
  "geometry": {"coordinates":[-2.693567,53.397125],"type":"Point"}
}
