{
  "type": "Feature",
  "properties": {
    "date:inception_lower": "1985-10-01",
    "date:inception_upper": "1985-10-01",
    "iso:country": "GB",
    "wof:name": "CM23 4JL",
    "wof:placetype": "postalcode"
  },
  "geometry": {"coordinates":[0.146916,51.853369],"type":"Point"}
}
