{
  "type": "Feature",
  "properties": {
    "iso:country":"GB",
    "wof:name":"CM23 4JL",
    "wof:placetype":"postalcode"
},
  "geometry": {"coordinates":[0.14691638928681,51.85336875300156],"type":"Point"}
}