{
  "type": "Feature",
  "properties": {
    "iso:country":"GB",
    "wof:name":"NG13 9NA",
    "wof:placetype":"postalcode"
},
  "geometry": {"coordinates":[-0.85150123181373,52.95858652776576],"type":"Point"}
}