{
  "type": "Feature",
  "properties": {
    "date:inception_lower":"2013-01-01",
    "date:inception_upper":"2013-01-31",
    "iso:country":"GB",
    "wof:name":"NG13 9NA",
    "wof:placetype":"postalcode"
},
  "geometry": {"coordinates":[-0.851501,52.958587],"type":"Point"}
}