{
  "type": "Feature",
  "properties": {
    "iso:country": "GB",
    "wof:name": "NG13 9NA",
    "wof:placetype": "postalcode"
  },
  "geometry": {"coordinates":[-0.851501,52.958587],"type":"Point"}
}
