{
  "type": "Feature",
  "properties": {
    "date:inception_lower":"1998-06-01",
    "date:inception_upper":"1998-06-30",
    "iso:country":"GB",
    "wof:name":"YO43 3JZ",
    "wof:placetype":"postalcode"
},
  "geometry": {"coordinates":[-0.65928,53.86474],"type":"Point"}
}