{
  "type": "Feature",
  "properties": {
    "iso:country": "GB",
    "wof:name": "OX18 2AQ",
    "wof:placetype": "postalcode"
  },
  "geometry": {"coordinates":[-1.536513,51.727558],"type":"Point"}
}
