{
  "type": "Feature",
  "properties": {
    "iso:country":"GB",
    "wof:name":"OX18 2AQ",
    "wof:placetype":"postalcode"
},
  "geometry": {"coordinates":[-1.53651317144544,51.72755756837106],"type":"Point"}
}