{
  "type": "Feature",
  "properties": {
    "date:inception_lower": "1994-12-01",
    "date:inception_upper": "1994-12-01",
    "iso:country": "GB",
    "wof:name": "SO40 4WH",
    "wof:placetype": "postalcode"
  },
  "geometry": {"coordinates":[-1.458686,50.891676],"type":"Point"}
}
