{
  "type": "Feature",
  "properties": {
    "iso:country":"GB",
    "wof:name":"GL4 0BT",
    "wof:placetype":"postalcode"
},
  "geometry": {"coordinates":[-2.24371528676431,51.83056237523854],"type":"Point"}
}