{
  "type": "Feature",
  "properties": {
    "iso:country":"GB",
    "wof:name":"HD4 5SE",
    "wof:placetype":"postalcode"
},
  "geometry": {"coordinates":[-1.8155172659891,53.63898865883569],"type":"Point"}
}