{
  "type": "Feature",
  "properties": {
    "iso:country":"GB",
    "wof:name":"M24 5QP",
    "wof:placetype":"postalcode"
},
  "geometry": {"coordinates":[-2.21182461893898,53.55985471956028],"type":"Point"}
}