{
  "type": "Feature",
  "properties": {
    "iso:country":"GB",
    "wof:name":"M8 0LA",
    "wof:placetype":"postalcode"
},
  "geometry": {"coordinates":[-2.2245436608573,53.50151488790876],"type":"Point"}
}