{
  "type": "Feature",
  "properties": {
    "iso:country": "GB",
    "wof:name": "SW17 9RP",
    "wof:placetype": "postalcode"
  },
  "geometry": {"coordinates":[-0.16859,51.425465],"type":"Point"}
}
