{
  "type": "Feature",
  "properties": {
    "iso:country":"GB",
    "wof:name":"SW17 9RP",
    "wof:placetype":"postalcode"
},
  "geometry": {"coordinates":[-0.16858963093081,51.42546469969213],"type":"Point"}
}