{
  "type": "Feature",
  "properties": {
    "iso:country": "GB",
    "wof:name": "M46 0HD",
    "wof:placetype": "postalcode"
  },
  "geometry": {"coordinates":[-2.496113,53.529486],"type":"Point"}
}
