{
  "type": "Feature",
  "properties": {
    "iso:country":"GB",
    "wof:name":"M46 0HD",
    "wof:placetype":"postalcode"
},
  "geometry": {"coordinates":[-2.49611327098199,53.5294858224334],"type":"Point"}
}