{
  "type": "Feature",
  "properties": {
    "iso:country":"GB",
    "wof:name":"TW7 6DL",
    "wof:placetype":"postalcode"
},
  "geometry": {"coordinates":[-0.3282627882894,51.4701510252867],"type":"Point"}
}