{
  "type": "Feature",
  "properties": {
    "iso:country":"GB",
    "wof:name":"E14 7LA",
    "wof:placetype":"postalcode"
},
  "geometry": {"coordinates":[-0.03470942149216,51.51267457584202],"type":"Point"}
}