{
  "type": "Feature",
  "properties": {
    "date:inception_lower":"1980-01-01",
    "date:inception_upper":"1980-01-31",
    "iso:country":"GB",
    "wof:name":"CB9 7LB",
    "wof:placetype":"postalcode"
},
  "geometry": {"coordinates":[0.449743,52.128643],"type":"Point"}
}