{
  "type": "Feature",
  "properties": {
    "iso:country": "GB",
    "wof:name": "M30 8GJ",
    "wof:placetype": "postalcode"
  },
  "geometry": {"coordinates":[-2.363525,53.48023],"type":"Point"}
}
