{
  "type": "Feature",
  "properties": {
    "iso:country":"GB",
    "wof:name":"M30 8GJ",
    "wof:placetype":"postalcode"
},
  "geometry": {"coordinates":[-2.36352538511933,53.48022959616887],"type":"Point"}
}