{
  "type": "Feature",
  "properties": {
    "date:inception_lower":"2002-12-01",
    "date:inception_upper":"2002-12-31",
    "iso:country":"GB",
    "wof:name":"SS1 1HY",
    "wof:placetype":"postalcode"
},
  "geometry": {"coordinates":[0.706687,51.537184],"type":"Point"}
}