{
  "type": "Feature",
  "properties": {
    "iso:country":"GB",
    "wof:name":"SS1 1HY",
    "wof:placetype":"postalcode"
},
  "geometry": {"coordinates":[0.70665718374033,51.53718001771448],"type":"Point"}
}