{
  "type": "Feature",
  "properties": {
    "iso:country": "GB",
    "wof:name": "ST13 8UR",
    "wof:placetype": "postalcode"
  },
  "geometry": {"coordinates":[-1.980654,53.114716],"type":"Point"}
}
