{
  "type": "Feature",
  "properties": {
    "iso:country":"GB",
    "wof:name":"ST13 8UR",
    "wof:placetype":"postalcode"
},
  "geometry": {"coordinates":[-1.98065694829004,53.11469844689278],"type":"Point"}
}