{
  "type": "Feature",
  "properties": {
    "date:inception_lower":"1980-01-01",
    "date:inception_upper":"1980-01-31",
    "iso:country":"GB",
    "wof:name":"ST14 8PF",
    "wof:placetype":"postalcode"
},
  "geometry": {"coordinates":[-1.844077,52.861391],"type":"Point"}
}