{
  "type": "Feature",
  "properties": {
    "iso:country":"GB",
    "wof:name":"ST14 8PF",
    "wof:placetype":"postalcode"
},
  "geometry": {"coordinates":[-1.84407728929777,52.86139066657348],"type":"Point"}
}