{
  "type": "Feature",
  "properties": {
    "date:inception_lower": "1981-06-01",
    "date:inception_upper": "1981-06-01",
    "iso:country": "GB",
    "wof:name": "B18 6JA",
    "wof:placetype": "postalcode"
  },
  "geometry": {"coordinates":[-1.910771,52.48784],"type":"Point"}
}
