{
  "type": "Feature",
  "properties": {
    "date:inception_lower": "1985-10-01",
    "date:inception_upper": "1985-10-01",
    "iso:country": "GB",
    "wof:name": "GU18 5YN",
    "wof:placetype": "postalcode"
  },
  "geometry": {"coordinates":[-0.672641,51.345158],"type":"Point"}
}
