{
  "type": "Feature",
  "properties": {
    "iso:country":"GB",
    "wof:name":"RH11 9QH",
    "wof:placetype":"postalcode"
},
  "geometry": {"coordinates":[-0.19962631803144,51.09394962154781],"type":"Point"}
}