{
  "type": "Feature",
  "properties": {
    "iso:country":"GB",
    "wof:name":"BH17 8PS",
    "wof:placetype":"postalcode"
},
  "geometry": {"coordinates":[-1.96869732966868,50.74295712119415],"type":"Point"}
}