{
  "type": "Feature",
  "properties": {
    "iso:country":"GB",
    "wof:name":"B43 7DF",
    "wof:placetype":"postalcode"
},
  "geometry": {"coordinates":[-1.90725982567943,52.56110489785921],"type":"Point"}
}