{
  "type": "Feature",
  "properties": {
    "iso:country":"GB",
    "wof:name":"PE31 8LH",
    "wof:placetype":"postalcode"
},
  "geometry": {"coordinates":[0.62468565226472,52.90097957167167],"type":"Point"}
}