{
  "type": "Feature",
  "properties": {
    "iso:country": "GB",
    "wof:name": "SY11 1TB",
    "wof:placetype": "postalcode"
  },
  "geometry": {"coordinates":[-3.0689,52.86175],"type":"Point"}
}
