{
  "type": "Feature",
  "properties": {
    "iso:country":"GB",
    "wof:name":"WD23 3BJ",
    "wof:placetype":"postalcode"
},
  "geometry": {"coordinates":[-0.35836216890271,51.65063619210105],"type":"Point"}
}