{
  "type": "Feature",
  "properties": {
    "iso:country": "GB",
    "wof:name": "OL9 9SG",
    "wof:placetype": "postalcode"
  },
  "geometry": {"coordinates":[-2.16172,53.548176],"type":"Point"}
}
