{
  "type": "Feature",
  "properties": {
    "iso:country":"GB",
    "wof:name":"S71 2EF",
    "wof:placetype":"postalcode"
},
  "geometry": {"coordinates":[-1.45147445986804,53.56825108645479],"type":"Point"}
}