{
  "type": "Feature",
  "properties": {
    "iso:country": "GB",
    "wof:name": "B27 6TU",
    "wof:placetype": "postalcode"
  },
  "geometry": {"coordinates":[-1.819884,52.45388],"type":"Point"}
}
