{
  "type": "Feature",
  "properties": {
    "iso:country":"GB",
    "wof:name":"CT12 4HF",
    "wof:placetype":"postalcode"
},
  "geometry": {"coordinates":[1.317673774826,51.33132738048638],"type":"Point"}
}