{
  "type": "Feature",
  "properties": {
    "date:inception_lower": "1980-01-01",
    "date:inception_upper": "1980-01-01",
    "iso:country": "GB",
    "wof:name": "CT12 4HF",
    "wof:placetype": "postalcode"
  },
  "geometry": {"coordinates":[1.317674,51.331327],"type":"Point"}
}
