{
  "type": "Feature",
  "properties": {
    "iso:country":"GB",
    "wof:name":"CF47 9UA",
    "wof:placetype":"postalcode"
},
  "geometry": {"coordinates":[-3.37480064370761,51.76220945916272],"type":"Point"}
}