{
  "type": "Feature",
  "properties": {
    "iso:country": "GB",
    "wof:name": "LL65 4YP",
    "wof:placetype": "postalcode"
  },
  "geometry": {"coordinates":[-4.554213,53.30937],"type":"Point"}
}
