{
  "type": "Feature",
  "properties": {
    "iso:country":"GB",
    "wof:name":"LL65 4YP",
    "wof:placetype":"postalcode"
},
  "geometry": {"coordinates":[-4.55421333556347,53.30937029471174],"type":"Point"}
}