{
  "type": "Feature",
  "properties": {
    "iso:country": "GB",
    "wof:name": "NG4 1ED",
    "wof:placetype": "postalcode"
  },
  "geometry": {"coordinates":[-1.091894,52.966383],"type":"Point"}
}
