{
  "type": "Feature",
  "properties": {
    "iso:country":"GB",
    "wof:name":"SK1 4NF",
    "wof:placetype":"postalcode"
},
  "geometry": {"coordinates":[-2.14362169819456,53.40030346280894],"type":"Point"}
}