{
  "type": "Feature",
  "properties": {
    "iso:country":"GB",
    "wof:name":"SO24 9BN",
    "wof:placetype":"postalcode"
},
  "geometry": {"coordinates":[-1.16622642220188,51.09082729030744],"type":"Point"}
}