{
  "type": "Feature",
  "properties": {
    "date:inception_lower":"1983-03-01",
    "date:inception_upper":"1983-03-31",
    "iso:country":"GB",
    "wof:name":"NR5 9JH",
    "wof:placetype":"postalcode"
},
  "geometry": {"coordinates":[1.212658,52.642066],"type":"Point"}
}