{
  "type": "Feature",
  "properties": {
    "iso:country":"GB",
    "wof:name":"NR5 9JH",
    "wof:placetype":"postalcode"
},
  "geometry": {"coordinates":[1.21265805483781,52.64206604336418],"type":"Point"}
}