{
  "type": "Feature",
  "properties": {
    "iso:country":"GB",
    "wof:name":"HP1 3PY",
    "wof:placetype":"postalcode"
},
  "geometry": {"coordinates":[-0.50163865778905,51.76329529197344],"type":"Point"}
}