{
  "type": "Feature",
  "properties": {
    "iso:country":"GB",
    "wof:name":"RG26 3EE",
    "wof:placetype":"postalcode"
},
  "geometry": {"coordinates":[-1.12048263792159,51.35806164798446],"type":"Point"}
}