{
  "type": "Feature",
  "properties": {
    "iso:country":"GB",
    "wof:name":"DT10 2BD",
    "wof:placetype":"postalcode"
},
  "geometry": {"coordinates":[-2.40645272520088,50.90373135907643],"type":"Point"}
}