{
  "type": "Feature",
  "properties": {
    "iso:country": "GB",
    "wof:name": "LL16 5DH",
    "wof:placetype": "postalcode"
  },
  "geometry": {"coordinates":[-3.511293,53.205735],"type":"Point"}
}
