{
  "type": "Feature",
  "properties": {
    "date:inception_lower": "1980-01-01",
    "date:inception_upper": "1980-01-01",
    "iso:country": "GB",
    "wof:name": "LL16 5DH",
    "wof:placetype": "postalcode"
  },
  "geometry": {"coordinates":[-3.511293,53.205735],"type":"Point"}
}
