{
  "type": "Feature",
  "properties": {
    "iso:country":"GB",
    "wof:name":"LL16 5DH",
    "wof:placetype":"postalcode"
},
  "geometry": {"coordinates":[-3.51129264080851,53.20573500845151],"type":"Point"}
}