{
  "type": "Feature",
  "properties": {
    "iso:country":"GB",
    "wof:name":"M40 8QD",
    "wof:placetype":"postalcode"
},
  "geometry": {"coordinates":[-2.21039366036884,53.49969803342745],"type":"Point"}
}