{
  "type": "Feature",
  "properties": {
    "iso:country":"GB",
    "wof:name":"PL5 1SB",
    "wof:placetype":"postalcode"
},
  "geometry": {"coordinates":[-4.1837719593195,50.40903885173257],"type":"Point"}
}