{
  "type": "Feature",
  "properties": {
    "date:inception_lower": "1988-03-01",
    "date:inception_upper": "1988-03-01",
    "iso:country": "GB",
    "wof:name": "LE10 1PG",
    "wof:placetype": "postalcode"
  },
  "geometry": {"coordinates":[-1.37207,52.556771],"type":"Point"}
}
