{
  "type": "Feature",
  "properties": {
    "iso:country":"GB",
    "wof:name":"DY2 8UP",
    "wof:placetype":"postalcode"
},
  "geometry": {"coordinates":[-2.09185081559403,52.50186185644824],"type":"Point"}
}