{
  "type": "Feature",
  "properties": {
    "iso:country": "GB",
    "wof:name": "EN9 1DA",
    "wof:placetype": "postalcode"
  },
  "geometry": {"coordinates":[0.002538,51.685466],"type":"Point"}
}
