{
  "type": "Feature",
  "properties": {
    "iso:country":"GB",
    "wof:name":"L19 2LY",
    "wof:placetype":"postalcode"
},
  "geometry": {"coordinates":[-2.8992464733606,53.3552036793161],"type":"Point"}
}