{
  "type": "Feature",
  "properties": {
    "iso:country": "GB",
    "wof:name": "TW20 0JP",
    "wof:placetype": "postalcode"
  },
  "geometry": {"coordinates":[-0.567349,51.430792],"type":"Point"}
}
