{
  "type": "Feature",
  "properties": {
    "iso:country":"GB",
    "wof:name":"LE5 5HN",
    "wof:placetype":"postalcode"
},
  "geometry": {"coordinates":[-1.10924034865832,52.62652138170328],"type":"Point"}
}