{
  "type": "Feature",
  "properties": {
    "iso:country":"GB",
    "wof:name":"LU3 1RJ",
    "wof:placetype":"postalcode"
},
  "geometry": {"coordinates":[-0.43619542361637,51.89240960253922],"type":"Point"}
}