{
  "type": "Feature",
  "properties": {
    "iso:country": "GB",
    "wof:name": "LU3 1RJ",
    "wof:placetype": "postalcode"
  },
  "geometry": {"coordinates":[-0.43617,51.892418],"type":"Point"}
}
