{
  "type": "Feature",
  "properties": {
    "iso:country": "GB",
    "wof:name": "LU3 1RJ",
    "wof:placetype": "postalcode"
  },
  "geometry": {"coordinates":[-0.436567,51.89272],"type":"Point"}
}
