{
  "type": "Feature",
  "properties": {
    "iso:country":"GB",
    "wof:name":"TS1 2PX",
    "wof:placetype":"postalcode"
},
  "geometry": {"coordinates":[-1.2356315991902,54.57323266285453],"type":"Point"}
}