{
  "type": "Feature",
  "properties": {
    "date:inception_lower": "1980-01-01",
    "date:inception_upper": "1980-01-01",
    "iso:country": "GB",
    "wof:name": "DT11 7EY",
    "wof:placetype": "postalcode"
  },
  "geometry": {"coordinates":[-2.161292,50.859204],"type":"Point"}
}
