{
  "type": "Feature",
  "properties": {
    "iso:country":"GB",
    "wof:name":"HP21 8XL",
    "wof:placetype":"postalcode"
},
  "geometry": {"coordinates":[-0.82897241952066,51.80462284113433],"type":"Point"}
}