{
  "type": "Feature",
  "properties": {
    "iso:country": "GB",
    "wof:name": "HP21 8XL",
    "wof:placetype": "postalcode"
  },
  "geometry": {"coordinates":[-0.828972,51.804623],"type":"Point"}
}
