{
  "type": "Feature",
  "properties": {
    "iso:country":"GB",
    "wof:name":"SL4 2JX",
    "wof:placetype":"postalcode"
},
  "geometry": {"coordinates":[-0.57220551189004,51.46189200992757],"type":"Point"}
}