{
  "type": "Feature",
  "properties": {
    "iso:country": "GB",
    "wof:name": "SL4 2JX",
    "wof:placetype": "postalcode"
  },
  "geometry": {"coordinates":[-0.572205,51.461892],"type":"Point"}
}
