{
  "type": "Feature",
  "properties": {
    "iso:country": "GB",
    "wof:name": "S40 1HL",
    "wof:placetype": "postalcode"
  },
  "geometry": {"coordinates":[-1.449668,53.237783],"type":"Point"}
}
