{
  "type": "Feature",
  "properties": {
    "iso:country":"GB",
    "wof:name":"S40 1HL",
    "wof:placetype":"postalcode"
},
  "geometry": {"coordinates":[-1.44966828161048,53.23778326744686],"type":"Point"}
}