{
  "type": "Feature",
  "properties": {
    "iso:country":"GB",
    "wof:name":"BA12 9PT",
    "wof:placetype":"postalcode"
},
  "geometry": {"coordinates":[-2.18365574889414,51.19795211153679],"type":"Point"}
}