{
  "type": "Feature",
  "properties": {
    "date:inception_lower": "2002-08-01",
    "date:inception_upper": "2002-08-01",
    "iso:country": "GB",
    "wof:name": "SY8 1YG",
    "wof:placetype": "postalcode"
  },
  "geometry": {"coordinates":[-2.702526,52.370262],"type":"Point"}
}
