{
  "type": "Feature",
  "properties": {
    "iso:country":"GB",
    "wof:name":"SY8 1YG",
    "wof:placetype":"postalcode"
},
  "geometry": {"coordinates":[-2.70252597803231,52.37026203556744],"type":"Point"}
}