{
  "type": "Feature",
  "properties": {
    "iso:country":"GB",
    "wof:name":"BA12 8BA",
    "wof:placetype":"postalcode"
},
  "geometry": {"coordinates":[-2.18779376078204,51.19139040591482],"type":"Point"}
}