{
  "type": "Feature",
  "properties": {
    "date:inception_lower": "1980-01-01",
    "date:inception_upper": "1980-01-01",
    "iso:country": "GB",
    "wof:name": "CF48 1SU",
    "wof:placetype": "postalcode"
  },
  "geometry": {"coordinates":[-3.407419,51.743112],"type":"Point"}
}
