{
  "type": "Feature",
  "properties": {
    "iso:country":"GB",
    "wof:name":"CF48 1SU",
    "wof:placetype":"postalcode"
},
  "geometry": {"coordinates":[-3.40741879665879,51.74311158243957],"type":"Point"}
}