{
  "type": "Feature",
  "properties": {
    "iso:country":"GB",
    "wof:name":"HG4 2QW",
    "wof:placetype":"postalcode"
},
  "geometry": {"coordinates":[-1.54196865072087,54.1377940961135],"type":"Point"}
}