{
  "type": "Feature",
  "properties": {
    "iso:country":"GB",
    "wof:name":"CF31 4DW",
    "wof:placetype":"postalcode"
},
  "geometry": {"coordinates":[-3.59897029889586,51.50794598361582],"type":"Point"}
}