{
  "type": "Feature",
  "properties": {
    "iso:country":"GB",
    "wof:name":"CH2 3DS",
    "wof:placetype":"postalcode"
},
  "geometry": {"coordinates":[-2.87422083851482,53.19307448383121],"type":"Point"}
}