{
  "type": "Feature",
  "properties": {
    "iso:country":"GB",
    "wof:name":"PE30 5ND",
    "wof:placetype":"postalcode"
},
  "geometry": {"coordinates":[0.39624295827001,52.75039057614491],"type":"Point"}
}