{
  "type": "Feature",
  "properties": {
    "iso:country":"GB",
    "wof:name":"NG2 1HF",
    "wof:placetype":"postalcode"
},
  "geometry": {"coordinates":[-1.15348014977816,52.94252987346981],"type":"Point"}
}