{
  "type": "Feature",
  "properties": {
    "date:inception_lower": "1980-01-01",
    "date:inception_upper": "1980-01-01",
    "iso:country": "GB",
    "wof:name": "NG2 1HF",
    "wof:placetype": "postalcode"
  },
  "geometry": {"coordinates":[-1.15348,52.94253],"type":"Point"}
}
