{
  "type": "Feature",
  "properties": {
    "iso:country": "GB",
    "wof:name": "CO3 9EF",
    "wof:placetype": "postalcode"
  },
  "geometry": {"coordinates":[0.858339,51.874281],"type":"Point"}
}
