{
  "type": "Feature",
  "properties": {
    "iso:country":"GB",
    "wof:name":"PE26 2SJ",
    "wof:placetype":"postalcode"
},
  "geometry": {"coordinates":[-0.11545433398842,52.45575613868345],"type":"Point"}
}