{
  "type": "Feature",
  "properties": {
    "iso:country": "GB",
    "wof:name": "CW12 3PJ",
    "wof:placetype": "postalcode"
  },
  "geometry": {"coordinates":[-2.169853,53.151478],"type":"Point"}
}
