{
  "type": "Feature",
  "properties": {
    "date:inception_lower": "1980-01-01",
    "date:inception_upper": "1980-01-01",
    "iso:country": "GB",
    "wof:name": "CW12 3PJ",
    "wof:placetype": "postalcode"
  },
  "geometry": {"coordinates":[-2.169853,53.151478],"type":"Point"}
}
