{
  "type": "Feature",
  "properties": {
    "iso:country":"GB",
    "wof:name":"B79 8DT",
    "wof:placetype":"postalcode"
},
  "geometry": {"coordinates":[-1.70205554178826,52.63943661026016],"type":"Point"}
}