{
  "type": "Feature",
  "properties": {
    "iso:country": "GB",
    "wof:name": "B79 8DT",
    "wof:placetype": "postalcode"
  },
  "geometry": {"coordinates":[-1.702055,52.639437],"type":"Point"}
}
