{
  "type": "Feature",
  "properties": {
    "date:inception_lower": "1980-01-01",
    "date:inception_upper": "1980-01-01",
    "iso:country": "GB",
    "wof:name": "HR1 4HW",
    "wof:placetype": "postalcode"
  },
  "geometry": {"coordinates":[-2.589916,52.053415],"type":"Point"}
}
