{
  "type": "Feature",
  "properties": {
    "iso:country":"GB",
    "wof:name":"HR1 4HW",
    "wof:placetype":"postalcode"
},
  "geometry": {"coordinates":[-2.58991588426123,52.05340593585702],"type":"Point"}
}