{
  "type": "Feature",
  "properties": {
    "iso:country":"GB",
    "wof:name":"IG3 9DB",
    "wof:placetype":"postalcode"
},
  "geometry": {"coordinates":[0.10317179503463,51.55083140595305],"type":"Point"}
}