{
  "type": "Feature",
  "properties": {
    "date:inception_lower": "1980-01-01",
    "date:inception_upper": "1980-01-01",
    "iso:country": "GB",
    "wof:name": "L35 2YR",
    "wof:placetype": "postalcode"
  },
  "geometry": {"coordinates":[-2.78865,53.419384],"type":"Point"}
}
