{
  "type": "Feature",
  "properties": {
    "iso:country":"GB",
    "wof:name":"L35 2YR",
    "wof:placetype":"postalcode"
},
  "geometry": {"coordinates":[-2.78865030104951,53.41938412544585],"type":"Point"}
}