{
  "type": "Feature",
  "properties": {
    "iso:country": "GB",
    "wof:name": "TQ7 3ER",
    "wof:placetype": "postalcode"
  },
  "geometry": {"coordinates":[-3.790098,50.280198],"type":"Point"}
}
