{
  "type": "Feature",
  "properties": {
    "date:inception_lower": "1980-01-01",
    "date:inception_upper": "1980-01-01",
    "iso:country": "GB",
    "wof:name": "G22 7HW",
    "wof:placetype": "postalcode"
  },
  "geometry": {"coordinates":[-4.240521,55.893761],"type":"Point"}
}
