{
  "type": "Feature",
  "properties": {
    "iso:country":"GB",
    "wof:name":"G22 7HW",
    "wof:placetype":"postalcode"
},
  "geometry": {"coordinates":[-4.24052151534596,55.89376133246068],"type":"Point"}
}