{
  "type": "Feature",
  "properties": {
    "iso:country":"GB",
    "wof:name":"LE1 1GS",
    "wof:placetype":"postalcode"
},
  "geometry": {"coordinates":[-1.12908561038903,52.63375300591936],"type":"Point"}
}