{
  "type": "Feature",
  "properties": {
    "iso:country": "GB",
    "wof:name": "LE1 1GS",
    "wof:placetype": "postalcode"
  },
  "geometry": {"coordinates":[-1.129086,52.633753],"type":"Point"}
}
