{
  "type": "Feature",
  "properties": {
    "iso:country":"GB",
    "wof:name":"ME19 6AP",
    "wof:placetype":"postalcode"
},
  "geometry": {"coordinates":[0.43829092622905,51.2852711228914],"type":"Point"}
}