{
  "type": "Feature",
  "properties": {
    "date:inception_lower": "1983-01-01",
    "date:inception_upper": "1983-01-01",
    "iso:country": "GB",
    "wof:name": "WV9 5PJ",
    "wof:placetype": "postalcode"
  },
  "geometry": {"coordinates":[-2.149163,52.621144],"type":"Point"}
}
