{
  "type": "Feature",
  "properties": {
    "iso:country":"GB",
    "wof:name":"E10 6JE",
    "wof:placetype":"postalcode"
},
  "geometry": {"coordinates":[-0.00667621430642,51.5704647028931],"type":"Point"}
}