{
  "type": "Feature",
  "properties": {
    "iso:country":"GB",
    "wof:name":"WD6 3HA",
    "wof:placetype":"postalcode"
},
  "geometry": {"coordinates":[-0.298592246682,51.64400347478127],"type":"Point"}
}