{
  "type": "Feature",
  "properties": {
    "iso:country": "GB",
    "wof:name": "CH62 0BT",
    "wof:placetype": "postalcode"
  },
  "geometry": {"coordinates":[-2.957333,53.317717],"type":"Point"}
}
