{
  "type": "Feature",
  "properties": {
    "iso:country":"GB",
    "wof:name":"OL16 4XR",
    "wof:placetype":"postalcode"
},
  "geometry": {"coordinates":[-2.14061497366028,53.60077561250173],"type":"Point"}
}