{
  "type": "Feature",
  "properties": {
    "iso:country":"GB",
    "wof:name":"WA5 1QF",
    "wof:placetype":"postalcode"
},
  "geometry": {"coordinates":[-2.61218432181936,53.3955926229465],"type":"Point"}
}