{
  "type": "Feature",
  "properties": {
    "iso:country":"GB",
    "wof:name":"BR1 2JR",
    "wof:placetype":"postalcode"
},
  "geometry": {"coordinates":[0.04969183113214,51.39322610604458],"type":"Point"}
}