{
  "type": "Feature",
  "properties": {
    "iso:country":"GB",
    "wof:name":"NG1 2GP",
    "wof:placetype":"postalcode"
},
  "geometry": {"coordinates":[-1.14724187719137,52.95177145845155],"type":"Point"}
}