{
  "type": "Feature",
  "properties": {
    "iso:country": "GB",
    "wof:name": "CW2 5AY",
    "wof:placetype": "postalcode"
  },
  "geometry": {"coordinates":[-2.429754,53.065174],"type":"Point"}
}
