{
  "type": "Feature",
  "properties": {
    "date:inception_lower":"1980-01-01",
    "date:inception_upper":"1980-01-31",
    "iso:country":"GB",
    "wof:name":"CW2 5AY",
    "wof:placetype":"postalcode"
},
  "geometry": {"coordinates":[-2.429919,53.06529],"type":"Point"}
}