{
  "type": "Feature",
  "properties": {
    "iso:country":"GB",
    "wof:name":"CW2 5AY",
    "wof:placetype":"postalcode"
},
  "geometry": {"coordinates":[-2.4297840141681,53.06521136367402],"type":"Point"}
}