{
  "type": "Feature",
  "properties": {
    "date:inception_lower": "1999-06-01",
    "date:inception_upper": "1999-06-01",
    "iso:country": "GB",
    "wof:name": "NP18 3FW",
    "wof:placetype": "postalcode"
  },
  "geometry": {"coordinates":[-2.96637,51.620427],"type":"Point"}
}
