{
  "type": "Feature",
  "properties": {
    "iso:country":"GB",
    "wof:name":"NP18 3FW",
    "wof:placetype":"postalcode"
},
  "geometry": {"coordinates":[-2.96636975134419,51.62042739594079],"type":"Point"}
}