{
  "type": "Feature",
  "properties": {
    "iso:country":"GB",
    "wof:name":"E1 2DW",
    "wof:placetype":"postalcode"
},
  "geometry": {"coordinates":[-0.05835728264553,51.51510078272395],"type":"Point"}
}