{
  "type": "Feature",
  "properties": {
    "iso:country":"GB",
    "wof:name":"NP4 5EX",
    "wof:placetype":"postalcode"
},
  "geometry": {"coordinates":[-3.03227877963238,51.68266333384032],"type":"Point"}
}