{
  "type": "Feature",
  "properties": {
    "iso:country": "GB",
    "wof:name": "NP4 5EX",
    "wof:placetype": "postalcode"
  },
  "geometry": {"coordinates":[-3.032279,51.682663],"type":"Point"}
}
