{
  "type": "Feature",
  "properties": {
    "date:inception_lower": "2004-01-01",
    "date:inception_upper": "2004-01-01",
    "iso:country": "GB",
    "wof:name": "B78 3PY",
    "wof:placetype": "postalcode"
  },
  "geometry": {"coordinates":[-1.728453,52.619516],"type":"Point"}
}
