{
  "type": "Feature",
  "properties": {
    "iso:country":"GB",
    "wof:name":"GL10 3QF",
    "wof:placetype":"postalcode"
},
  "geometry": {"coordinates":[-2.26093194847548,51.72618419311952],"type":"Point"}
}