{
  "type": "Feature",
  "properties": {
    "iso:country": "GB",
    "wof:name": "TS6 7HQ",
    "wof:placetype": "postalcode"
  },
  "geometry": {"coordinates":[-1.150036,54.576472],"type":"Point"}
}
