{
  "type": "Feature",
  "properties": {
    "iso:country":"GB",
    "wof:name":"TS6 7HQ",
    "wof:placetype":"postalcode"
},
  "geometry": {"coordinates":[-1.15003622847379,54.57647248563551],"type":"Point"}
}