{
  "type": "Feature",
  "properties": {
    "iso:country":"GB",
    "wof:name":"DY10 1LB",
    "wof:placetype":"postalcode"
},
  "geometry": {"coordinates":[-2.25003041021726,52.37612302982831],"type":"Point"}
}