{
  "type": "Feature",
  "properties": {
    "iso:country":"GB",
    "wof:name":"TW13 6LU",
    "wof:placetype":"postalcode"
},
  "geometry": {"coordinates":[-0.38869762916382,51.43154770903563],"type":"Point"}
}