{
  "type": "Feature",
  "properties": {
    "iso:country":"GB",
    "wof:name":"BB7 1QQ",
    "wof:placetype":"postalcode"
},
  "geometry": {"coordinates":[-2.3863506392304,53.87337367156337],"type":"Point"}
}