{
  "type": "Feature",
  "properties": {
    "date:inception_lower": "1999-06-01",
    "date:inception_upper": "1999-06-01",
    "iso:country": "GB",
    "wof:name": "BB7 1QQ",
    "wof:placetype": "postalcode"
  },
  "geometry": {"coordinates":[-2.386351,53.873374],"type":"Point"}
}
