{
  "type": "Feature",
  "properties": {
    "iso:country": "GB",
    "wof:name": "BB7 1QQ",
    "wof:placetype": "postalcode"
  },
  "geometry": {"coordinates":[-2.386351,53.873374],"type":"Point"}
}
