{
  "type": "Feature",
  "properties": {
    "date:inception_lower": "2023-12-01",
    "date:inception_upper": "2023-12-01",
    "iso:country": "GB",
    "wof:name": "CT21 4FE",
    "wof:placetype": "postalcode"
  },
  "geometry": {"coordinates":[1.04036,51.059327],"type":"Point"}
}
