{
  "type": "Feature",
  "properties": {
    "iso:country":"GB",
    "wof:name":"CF42 5NR",
    "wof:placetype":"postalcode"
},
  "geometry": {"coordinates":[-3.53328066391419,51.67354879573609],"type":"Point"}
}