{
  "type": "Feature",
  "properties": {
    "date:inception_lower": "2019-08-01",
    "date:inception_upper": "2019-08-01",
    "iso:country": "GB",
    "wof:name": "LE3 6BP",
    "wof:placetype": "postalcode"
  },
  "geometry": {"coordinates":[-1.159137,52.633566],"type":"Point"}
}
