{
  "type": "Feature",
  "properties": {
    "date:inception_lower": "2012-11-01",
    "date:inception_upper": "2012-11-01",
    "iso:country": "GB",
    "wof:name": "RH17 6DG",
    "wof:placetype": "postalcode"
  },
  "geometry": {"coordinates":[-0.198022,51.044463],"type":"Point"}
}
