{
  "type": "Feature",
  "properties": {
    "iso:country": "GB",
    "wof:name": "OX1 4QJ",
    "wof:placetype": "postalcode"
  },
  "geometry": {"coordinates":[-1.259038,51.743112],"type":"Point"}
}
