{
  "type": "Feature",
  "properties": {
    "iso:country":"GB",
    "wof:name":"OX1 4QJ",
    "wof:placetype":"postalcode"
},
  "geometry": {"coordinates":[-1.25903794547377,51.7431117848374],"type":"Point"}
}