{
  "type": "Feature",
  "properties": {
    "date:inception_lower": "2014-02-01",
    "date:inception_upper": "2014-02-01",
    "iso:country": "GB",
    "wof:name": "CF64 1TB",
    "wof:placetype": "postalcode"
  },
  "geometry": {"coordinates":[-3.183144,51.443317],"type":"Point"}
}
