{
  "type": "Feature",
  "properties": {
    "iso:country":"GB",
    "wof:name":"CF64 1TB",
    "wof:placetype":"postalcode"
},
  "geometry": {"coordinates":[-3.18268742660372,51.44269238654248],"type":"Point"}
}