{
  "type": "Feature",
  "properties": {
    "iso:country": "GB",
    "wof:name": "CH49 1RT",
    "wof:placetype": "postalcode"
  },
  "geometry": {"coordinates":[-3.12004,53.374909],"type":"Point"}
}
