{
  "type": "Feature",
  "properties": {
    "iso:country":"GB",
    "wof:name":"N14 5RG",
    "wof:placetype":"postalcode"
},
  "geometry": {"coordinates":[-0.13858627479443,51.63253864517966],"type":"Point"}
}