{
  "type": "Feature",
  "properties": {
    "iso:country":"GB",
    "wof:name":"NG10 5QU",
    "wof:placetype":"postalcode"
},
  "geometry": {"coordinates":[-1.28613758566499,52.92394727152346],"type":"Point"}
}