{
  "type": "Feature",
  "properties": {
    "date:inception_lower": "2008-01-01",
    "date:inception_upper": "2008-01-01",
    "iso:country": "GB",
    "wof:name": "NG10 5QU",
    "wof:placetype": "postalcode"
  },
  "geometry": {"coordinates":[-1.286138,52.923947],"type":"Point"}
}
