{
  "type": "Feature",
  "properties": {
    "iso:country": "GB",
    "wof:name": "LA2 8EQ",
    "wof:placetype": "postalcode"
  },
  "geometry": {"coordinates":[-2.391328,54.11759],"type":"Point"}
}
