{
  "type": "Feature",
  "properties": {
    "iso:country":"GB",
    "wof:name":"LA2 8EQ",
    "wof:placetype":"postalcode"
},
  "geometry": {"coordinates":[-2.39132761574065,54.11758989893646],"type":"Point"}
}