{
  "type": "Feature",
  "properties": {
    "iso:country":"GB",
    "wof:name":"LN8 5SQ",
    "wof:placetype":"postalcode"
},
  "geometry": {"coordinates":[-0.29622786884287,53.32322296705254],"type":"Point"}
}