{
  "type": "Feature",
  "properties": {
    "date:inception_lower":"1996-12-01",
    "date:inception_upper":"1996-12-31",
    "iso:country":"GB",
    "wof:name":"LN8 5SQ",
    "wof:placetype":"postalcode"
},
  "geometry": {"coordinates":[-0.296228,53.323223],"type":"Point"}
}