{
  "type": "Feature",
  "properties": {
    "date:inception_lower": "2001-12-01",
    "date:inception_upper": "2001-12-01",
    "iso:country": "GB",
    "wof:name": "RM16 6BF",
    "wof:placetype": "postalcode"
  },
  "geometry": {"coordinates":[0.29234,51.480298],"type":"Point"}
}
