{
  "type": "Feature",
  "properties": {
    "iso:country":"GB",
    "wof:name":"RM16 6BF",
    "wof:placetype":"postalcode"
},
  "geometry": {"coordinates":[0.29233990035179,51.48029793002036],"type":"Point"}
}