{
  "type": "Feature",
  "properties": {
    "iso:country":"GB",
    "wof:name":"NE7 7SF",
    "wof:placetype":"postalcode"
},
  "geometry": {"coordinates":[-1.56185615900094,55.00318787824961],"type":"Point"}
}