{
  "type": "Feature",
  "properties": {
    "iso:country":"GB",
    "wof:name":"CM2 0DZ",
    "wof:placetype":"postalcode"
},
  "geometry": {"coordinates":[0.47399525691813,51.7282620469607],"type":"Point"}
}