{
  "type": "Feature",
  "properties": {
    "iso:country": "GB",
    "wof:name": "CT13 0EZ",
    "wof:placetype": "postalcode"
  },
  "geometry": {"coordinates":[1.296605,51.24379],"type":"Point"}
}
