{
  "type": "Feature",
  "properties": {
    "iso:country":"GB",
    "wof:name":"CT13 0EZ",
    "wof:placetype":"postalcode"
},
  "geometry": {"coordinates":[1.2966047323812,51.24378952277483],"type":"Point"}
}