{
  "type": "Feature",
  "properties": {
    "iso:country": "GB",
    "wof:name": "TA24 6PE",
    "wof:placetype": "postalcode"
  },
  "geometry": {"coordinates":[-3.420349,51.172764],"type":"Point"}
}
