{
  "type": "Feature",
  "properties": {
    "iso:country":"GB",
    "wof:name":"TN22 3FD",
    "wof:placetype":"postalcode"
},
  "geometry": {"coordinates":[0.10876203215489,51.00026160317861],"type":"Point"}
}