{
  "type": "Feature",
  "properties": {
    "iso:country": "GB",
    "wof:name": "NE20 9TR",
    "wof:placetype": "postalcode"
  },
  "geometry": {"coordinates":[-1.734393,55.054575],"type":"Point"}
}
