{
  "type": "Feature",
  "properties": {
    "iso:country":"GB",
    "wof:name":"NE20 9TR",
    "wof:placetype":"postalcode"
},
  "geometry": {"coordinates":[-1.73439283633916,55.05457498397999],"type":"Point"}
}