{
  "type": "Feature",
  "properties": {
    "date:inception_lower":"1980-01-01",
    "date:inception_upper":"1980-01-31",
    "iso:country":"GB",
    "wof:name":"DN20 0JN",
    "wof:placetype":"postalcode"
},
  "geometry": {"coordinates":[-0.540749,53.56585],"type":"Point"}
}