{
  "type": "Feature",
  "properties": {
    "iso:country":"GB",
    "wof:name":"DN20 0JN",
    "wof:placetype":"postalcode"
},
  "geometry": {"coordinates":[-0.54074896551728,53.56585013750184],"type":"Point"}
}