{
  "type": "Feature",
  "properties": {
    "iso:country": "GB",
    "wof:name": "DN20 0JN",
    "wof:placetype": "postalcode"
  },
  "geometry": {"coordinates":[-0.540749,53.56585],"type":"Point"}
}
