{
  "type": "Feature",
  "properties": {
    "iso:country": "GB",
    "wof:name": "CT1 1NG",
    "wof:placetype": "postalcode"
  },
  "geometry": {"coordinates":[1.086065,51.278983],"type":"Point"}
}
