{
  "type": "Feature",
  "properties": {
    "iso:country":"GB",
    "wof:name":"CT1 1NG",
    "wof:placetype":"postalcode"
},
  "geometry": {"coordinates":[1.08606457906807,51.27898320703715],"type":"Point"}
}