{
  "type": "Feature",
  "properties": {
    "iso:country":"GB",
    "wof:name":"ME1 3QD",
    "wof:placetype":"postalcode"
},
  "geometry": {"coordinates":[0.49978601067624,51.36334237489361],"type":"Point"}
}