{
  "type": "Feature",
  "properties": {
    "iso:country":"GB",
    "wof:name":"KY10 2QU",
    "wof:placetype":"postalcode"
},
  "geometry": {"coordinates":[-2.73506532519082,56.21575171601623],"type":"Point"}
}