{
  "type": "Feature",
  "properties": {
    "iso:country": "GB",
    "wof:name": "DE6 1SY",
    "wof:placetype": "postalcode"
  },
  "geometry": {"coordinates":[-1.72678,53.010932],"type":"Point"}
}
