{
  "type": "Feature",
  "properties": {
    "iso:country":"GB",
    "wof:name":"DE6 1SY",
    "wof:placetype":"postalcode"
},
  "geometry": {"coordinates":[-1.72678044422922,53.01093156248053],"type":"Point"}
}