{
  "type": "Feature",
  "properties": {
    "iso:country":"GB",
    "wof:name":"PR8 6UD",
    "wof:placetype":"postalcode"
},
  "geometry": {"coordinates":[-2.98180140136847,53.63029339433056],"type":"Point"}
}