{
  "type": "Feature",
  "properties": {
    "iso:country":"GB",
    "wof:name":"RM6 5QD",
    "wof:placetype":"postalcode"
},
  "geometry": {"coordinates":[0.13871468089007,51.5886688842851],"type":"Point"}
}