{
  "type": "Feature",
  "properties": {
    "iso:country":"GB",
    "wof:name":"G31 2LD",
    "wof:placetype":"postalcode"
},
  "geometry": {"coordinates":[-4.22093518226526,55.85888590091035],"type":"Point"}
}