{
  "type": "Feature",
  "properties": {
    "iso:country":"GB",
    "wof:name":"SG8 0AN",
    "wof:placetype":"postalcode"
},
  "geometry": {"coordinates":[-0.06774333589303,52.16393119227764],"type":"Point"}
}