{
  "type": "Feature",
  "properties": {
    "iso:country":"GB",
    "wof:name":"TQ7 4DQ",
    "wof:placetype":"postalcode"
},
  "geometry": {"coordinates":[-3.77317026844761,50.32689399300039],"type":"Point"}
}