{
  "type": "Feature",
  "properties": {
    "iso:country":"GB",
    "wof:name":"S26 3XR",
    "wof:placetype":"postalcode"
},
  "geometry": {"coordinates":[-1.32108803119042,53.37189089243743],"type":"Point"}
}