{
  "type": "Feature",
  "properties": {
    "iso:country":"GB",
    "wof:name":"S63 9BY",
    "wof:placetype":"postalcode"
},
  "geometry": {"coordinates":[-1.31780982841707,53.52710647853709],"type":"Point"}
}