{
  "type": "Feature",
  "properties": {
    "iso:country": "GB",
    "wof:name": "BS13 7QZ",
    "wof:placetype": "postalcode"
  },
  "geometry": {"coordinates":[-2.606615,51.42105],"type":"Point"}
}
