{
  "type": "Feature",
  "properties": {
    "iso:country":"GB",
    "wof:name":"BS13 7QZ",
    "wof:placetype":"postalcode"
},
  "geometry": {"coordinates":[-2.60661520099619,51.42104986922909],"type":"Point"}
}