{
  "type": "Feature",
  "properties": {
    "iso:country": "GB",
    "wof:name": "LN6 9LA",
    "wof:placetype": "postalcode"
  },
  "geometry": {"coordinates":[-0.685234,53.110382],"type":"Point"}
}
