{
  "type": "Feature",
  "properties": {
    "date:inception_lower": "1980-01-01",
    "date:inception_upper": "1980-01-01",
    "iso:country": "GB",
    "wof:name": "LN6 9LA",
    "wof:placetype": "postalcode"
  },
  "geometry": {"coordinates":[-0.685234,53.110382],"type":"Point"}
}
