{
  "type": "Feature",
  "properties": {
    "iso:country":"GB",
    "wof:name":"LN6 9LA",
    "wof:placetype":"postalcode"
},
  "geometry": {"coordinates":[-0.68523364258248,53.11038212378237],"type":"Point"}
}