{
  "type": "Feature",
  "properties": {
    "iso:country":"GB",
    "wof:name":"WV6 0AL",
    "wof:placetype":"postalcode"
},
  "geometry": {"coordinates":[-2.14891702852338,52.59223271220186],"type":"Point"}
}