{
  "type": "Feature",
  "properties": {
    "iso:country": "GB",
    "wof:name": "WV6 0AL",
    "wof:placetype": "postalcode"
  },
  "geometry": {"coordinates":[-2.148917,52.592233],"type":"Point"}
}
