{
  "type": "Feature",
  "properties": {
    "date:inception_lower":"1993-08-01",
    "date:inception_upper":"1993-08-31",
    "iso:country":"GB",
    "wof:name":"NN13 7EB",
    "wof:placetype":"postalcode"
},
  "geometry": {"coordinates":[-1.142565,52.026997],"type":"Point"}
}