{
  "type": "Feature",
  "properties": {
    "iso:country":"GB",
    "wof:name":"NN7 4NZ",
    "wof:placetype":"postalcode"
},
  "geometry": {"coordinates":[-1.08409375884726,52.23271513963638],"type":"Point"}
}