{
  "type": "Feature",
  "properties": {
    "iso:country":"GB",
    "wof:name":"BL4 8PF",
    "wof:placetype":"postalcode"
},
  "geometry": {"coordinates":[-2.36982091896444,53.53700826491966],"type":"Point"}
}