{
  "type": "Feature",
  "properties": {
    "date:inception_lower": "2001-06-01",
    "date:inception_upper": "2001-06-01",
    "iso:country": "GB",
    "wof:name": "PL19 8AE",
    "wof:placetype": "postalcode"
  },
  "geometry": {"coordinates":[-4.147418,50.547427],"type":"Point"}
}
