{
  "type": "Feature",
  "properties": {
    "iso:country":"GB",
    "wof:name":"KA24 4BJ",
    "wof:placetype":"postalcode"
},
  "geometry": {"coordinates":[-4.72800812698651,55.70425246290521],"type":"Point"}
}