{
  "type": "Feature",
  "properties": {
    "date:inception_lower": "1980-01-01",
    "date:inception_upper": "1980-01-01",
    "iso:country": "GB",
    "wof:name": "KA24 4BJ",
    "wof:placetype": "postalcode"
  },
  "geometry": {"coordinates":[-4.728008,55.704252],"type":"Point"}
}
