{
  "type": "Feature",
  "properties": {
    "iso:country":"GB",
    "wof:name":"SA62 5DB",
    "wof:placetype":"postalcode"
},
  "geometry": {"coordinates":[-4.9521022222526,51.87062918567617],"type":"Point"}
}