{
  "type": "Feature",
  "properties": {
    "date:inception_lower": "1980-01-01",
    "date:inception_upper": "1980-01-01",
    "iso:country": "GB",
    "wof:name": "SA62 5DB",
    "wof:placetype": "postalcode"
  },
  "geometry": {"coordinates":[-4.952102,51.870629],"type":"Point"}
}
