{
  "type": "Feature",
  "properties": {
    "iso:country":"GB",
    "wof:name":"TR26 1RY",
    "wof:placetype":"postalcode"
},
  "geometry": {"coordinates":[-5.48054676351833,50.2123013734249],"type":"Point"}
}