{
  "type": "Feature",
  "properties": {
    "iso:country":"GB",
    "wof:name":"OX5 2JD",
    "wof:placetype":"postalcode"
},
  "geometry": {"coordinates":[-1.27625432270059,51.82043542041377],"type":"Point"}
}