{
  "type": "Feature",
  "properties": {
    "iso:country":"GB",
    "wof:name":"EC1V 0AH",
    "wof:placetype":"postalcode"
},
  "geometry": {"coordinates":[-0.09976911771335,51.52400720623628],"type":"Point"}
}