{
  "type": "Feature",
  "properties": {
    "date:inception_lower":"1980-01-01",
    "date:inception_upper":"1980-01-31",
    "iso:country":"GB",
    "wof:name":"BL1 8TG",
    "wof:placetype":"postalcode"
},
  "geometry": {"coordinates":[-2.425969,53.600468],"type":"Point"}
}