{
  "type": "Feature",
  "properties": {
    "iso:country":"GB",
    "wof:name":"EX6 6JU",
    "wof:placetype":"postalcode"
},
  "geometry": {"coordinates":[-3.74154187221097,50.72873686298973],"type":"Point"}
}