{
  "type": "Feature",
  "properties": {
    "date:inception_lower": "1980-01-01",
    "date:inception_upper": "1980-01-01",
    "iso:country": "GB",
    "wof:name": "EX6 6JU",
    "wof:placetype": "postalcode"
  },
  "geometry": {"coordinates":[-3.741542,50.728737],"type":"Point"}
}
