{
  "type": "Feature",
  "properties": {
    "iso:country": "GB",
    "wof:name": "M26 3TJ",
    "wof:placetype": "postalcode"
  },
  "geometry": {"coordinates":[-2.351549,53.56064],"type":"Point"}
}
