{
  "type": "Feature",
  "properties": {
    "iso:country":"GB",
    "wof:name":"CV8 2FW",
    "wof:placetype":"postalcode"
},
  "geometry": {"coordinates":[-1.5743736023891,52.3481935629649],"type":"Point"}
}