{
  "type": "Feature",
  "properties": {
    "iso:country":"GB",
    "wof:name":"G66 2AF",
    "wof:placetype":"postalcode"
},
  "geometry": {"coordinates":[-4.14050080349745,55.93856294261314],"type":"Point"}
}