{
  "type": "Feature",
  "properties": {
    "date:inception_lower": "2012-11-01",
    "date:inception_upper": "2012-11-01",
    "iso:country": "GB",
    "wof:name": "G66 2AF",
    "wof:placetype": "postalcode"
  },
  "geometry": {"coordinates":[-4.140501,55.938563],"type":"Point"}
}
