{
  "type": "Feature",
  "properties": {
    "iso:country": "GB",
    "wof:name": "NG34 8HF",
    "wof:placetype": "postalcode"
  },
  "geometry": {"coordinates":[-0.428533,53.023573],"type":"Point"}
}
