{
  "type": "Feature",
  "properties": {
    "iso:country":"GB",
    "wof:name":"NG34 8HF",
    "wof:placetype":"postalcode"
},
  "geometry": {"coordinates":[-0.42853312773735,53.02357345465405],"type":"Point"}
}