{
  "type": "Feature",
  "properties": {
    "iso:country":"GB",
    "wof:name":"M16 7LN",
    "wof:placetype":"postalcode"
},
  "geometry": {"coordinates":[-2.24787913358607,53.45473770766348],"type":"Point"}
}