{
  "type": "Feature",
  "properties": {
    "iso:country": "GB",
    "wof:name": "SP8 5LH",
    "wof:placetype": "postalcode"
  },
  "geometry": {"coordinates":[-2.273531,51.006442],"type":"Point"}
}
