{
  "type": "Feature",
  "properties": {
    "iso:country":"GB",
    "wof:name":"SP8 5LH",
    "wof:placetype":"postalcode"
},
  "geometry": {"coordinates":[-2.27353075009851,51.00644242346298],"type":"Point"}
}