{
  "type": "Feature",
  "properties": {
    "iso:country":"GB",
    "wof:name":"OX1 4PQ",
    "wof:placetype":"postalcode"
},
  "geometry": {"coordinates":[-1.25721850327423,51.74277661889347],"type":"Point"}
}