{
  "type": "Feature",
  "properties": {
    "iso:country":"GB",
    "wof:name":"N1 2FS",
    "wof:placetype":"postalcode"
},
  "geometry": {"coordinates":[-0.08831407064335,51.54865845544184],"type":"Point"}
}