{
  "type": "Feature",
  "properties": {
    "date:inception_lower":"1998-12-01",
    "date:inception_upper":"1998-12-31",
    "iso:country":"GB",
    "wof:name":"N1 2FS",
    "wof:placetype":"postalcode"
},
  "geometry": {"coordinates":[-0.088397,51.548732],"type":"Point"}
}