{
  "type": "Feature",
  "properties": {
    "iso:country":"GB",
    "wof:name":"M41 8US",
    "wof:placetype":"postalcode"
},
  "geometry": {"coordinates":[-2.38912982122752,53.45099016545095],"type":"Point"}
}