{
  "type": "Feature",
  "properties": {
    "iso:country":"GB",
    "wof:name":"SW9 0UN",
    "wof:placetype":"postalcode"
},
  "geometry": {"coordinates":[-0.11551987460208,51.46650210035202],"type":"Point"}
}