{
  "type": "Feature",
  "properties": {
    "iso:country": "GB",
    "wof:name": "CT3 2BT",
    "wof:placetype": "postalcode"
  },
  "geometry": {"coordinates":[1.290281,51.277636],"type":"Point"}
}
