{
  "type": "Feature",
  "properties": {
    "iso:country": "GB",
    "wof:name": "NP44 1AS",
    "wof:placetype": "postalcode"
  },
  "geometry": {"coordinates":[-3.030932,51.662228],"type":"Point"}
}
