{
  "type": "Feature",
  "properties": {
    "iso:country":"GB",
    "wof:name":"NP44 1AS",
    "wof:placetype":"postalcode"
},
  "geometry": {"coordinates":[-3.03093225690471,51.6622284171399],"type":"Point"}
}