{
  "type": "Feature",
  "properties": {
    "iso:country":"GB",
    "wof:name":"EH19 2JF",
    "wof:placetype":"postalcode"
},
  "geometry": {"coordinates":[-3.11121668517431,55.88210717616599],"type":"Point"}
}