{
  "type": "Feature",
  "properties": {
    "iso:country":"GB",
    "wof:name":"FK10 2UA",
    "wof:placetype":"postalcode"
},
  "geometry": {"coordinates":[-3.82685054747723,56.13593119663565],"type":"Point"}
}