{
  "type": "Feature",
  "properties": {
    "iso:country": "GB",
    "wof:name": "B13 9NN",
    "wof:placetype": "postalcode"
  },
  "geometry": {"coordinates":[-1.858511,52.440448],"type":"Point"}
}
