{
  "type": "Feature",
  "properties": {
    "iso:country":"GB",
    "wof:name":"B13 9NN",
    "wof:placetype":"postalcode"
},
  "geometry": {"coordinates":[-1.85851057742455,52.44044784683334],"type":"Point"}
}