{
  "type": "Feature",
  "properties": {
    "iso:country":"GB",
    "wof:name":"HX1 2TD",
    "wof:placetype":"postalcode"
},
  "geometry": {"coordinates":[-1.86742936280684,53.71973483747211],"type":"Point"}
}