{
  "type": "Feature",
  "properties": {
    "iso:country": "GB",
    "wof:name": "TW15 1UH",
    "wof:placetype": "postalcode"
  },
  "geometry": {"coordinates":[-0.442956,51.418819],"type":"Point"}
}
