{
  "type": "Feature",
  "properties": {
    "iso:country": "GB",
    "wof:name": "TF1 6SY",
    "wof:placetype": "postalcode"
  },
  "geometry": {"coordinates":[-2.473856,52.708703],"type":"Point"}
}
