{
  "type": "Feature",
  "properties": {
    "iso:country":"GB",
    "wof:name":"TF1 6SY",
    "wof:placetype":"postalcode"
},
  "geometry": {"coordinates":[-2.4738560644843,52.70870331386588],"type":"Point"}
}