{
  "type": "Feature",
  "properties": {
    "date:inception_lower":"2014-01-01",
    "date:inception_upper":"2014-01-31",
    "iso:country":"GB",
    "wof:name":"TF1 6SY",
    "wof:placetype":"postalcode"
},
  "geometry": {"coordinates":[-2.473856,52.708703],"type":"Point"}
}