{
  "type": "Feature",
  "properties": {
    "iso:country":"GB",
    "wof:name":"ME9 7DD",
    "wof:placetype":"postalcode"
},
  "geometry": {"coordinates":[0.66284050872084,51.36994708196211],"type":"Point"}
}