{
  "type": "Feature",
  "properties": {
    "date:inception_lower": "1980-01-01",
    "date:inception_upper": "1980-01-01",
    "iso:country": "GB",
    "wof:name": "ME9 7DD",
    "wof:placetype": "postalcode"
  },
  "geometry": {"coordinates":[0.662841,51.369947],"type":"Point"}
}
