{
  "type": "Feature",
  "properties": {
    "iso:country":"GB",
    "wof:name":"TW3 1SU",
    "wof:placetype":"postalcode"
},
  "geometry": {"coordinates":[-0.35172486018955,51.47113961610434],"type":"Point"}
}