{
  "type": "Feature",
  "properties": {
    "date:inception_lower":"1986-04-01",
    "date:inception_upper":"1986-04-30",
    "iso:country":"GB",
    "wof:name":"IP25 6XD",
    "wof:placetype":"postalcode"
},
  "geometry": {"coordinates":[0.817771,52.567385],"type":"Point"}
}