{
  "type": "Feature",
  "properties": {
    "iso:country": "GB",
    "wof:name": "AB12 3NX",
    "wof:placetype": "postalcode"
  },
  "geometry": {"coordinates":[-2.083183,57.098754],"type":"Point"}
}
