{
  "type": "Feature",
  "properties": {
    "date:inception_lower": "1993-08-01",
    "date:inception_upper": "1993-08-01",
    "iso:country": "GB",
    "wof:name": "CH8 7LL",
    "wof:placetype": "postalcode"
  },
  "geometry": {"coordinates":[-3.22093,53.272799],"type":"Point"}
}
