{
  "type": "Feature",
  "properties": {
    "iso:country":"GB",
    "wof:name":"LS16 6BS",
    "wof:placetype":"postalcode"
},
  "geometry": {"coordinates":[-1.60386467142868,53.8500737557761],"type":"Point"}
}