{
  "type": "Feature",
  "properties": {
    "iso:country":"GB",
    "wof:name":"ST19 5EW",
    "wof:placetype":"postalcode"
},
  "geometry": {"coordinates":[-2.10377465507959,52.72254158366287],"type":"Point"}
}