{
  "type": "Feature",
  "properties": {
    "date:inception_lower": "1996-12-01",
    "date:inception_upper": "1996-12-01",
    "iso:country": "GB",
    "wof:name": "NP4 0SU",
    "wof:placetype": "postalcode"
  },
  "geometry": {"coordinates":[-3.016364,51.694467],"type":"Point"}
}
