{
  "type": "Feature",
  "properties": {
    "iso:country":"GB",
    "wof:name":"EX39 3HQ",
    "wof:placetype":"postalcode"
},
  "geometry": {"coordinates":[-4.22853067655099,51.00983631492764],"type":"Point"}
}