{
  "type": "Feature",
  "properties": {
    "iso:country": "GB",
    "wof:name": "DE21 4UE",
    "wof:placetype": "postalcode"
  },
  "geometry": {"coordinates":[-1.453123,52.946974],"type":"Point"}
}
