{
  "type": "Feature",
  "properties": {
    "iso:country":"GB",
    "wof:name":"ST6 1JT",
    "wof:placetype":"postalcode"
},
  "geometry": {"coordinates":[-2.17847865544695,53.05006037147752],"type":"Point"}
}