{
  "type": "Feature",
  "properties": {
    "iso:country":"GB",
    "wof:name":"NW6 1HA",
    "wof:placetype":"postalcode"
},
  "geometry": {"coordinates":[-0.20211654307982,51.55296644834853],"type":"Point"}
}