{
  "type": "Feature",
  "properties": {
    "date:inception_lower": "1980-01-01",
    "date:inception_upper": "1980-01-01",
    "iso:country": "GB",
    "wof:name": "SA61 2LE",
    "wof:placetype": "postalcode"
  },
  "geometry": {"coordinates":[-4.966429,51.802446],"type":"Point"}
}
