{
  "type": "Feature",
  "properties": {
    "iso:country":"GB",
    "wof:name":"ML2 8LT",
    "wof:placetype":"postalcode"
},
  "geometry": {"coordinates":[-3.90580212583873,55.77840171221182],"type":"Point"}
}