{
  "type": "Feature",
  "properties": {
    "iso:country":"GB",
    "wof:name":"SA38 9NP",
    "wof:placetype":"postalcode"
},
  "geometry": {"coordinates":[-4.47292712955362,52.04496588558466],"type":"Point"}
}