{
  "type": "Feature",
  "properties": {
    "iso:country": "GB",
    "wof:name": "WA15 8RP",
    "wof:placetype": "postalcode"
  },
  "geometry": {"coordinates":[-2.321168,53.374412],"type":"Point"}
}
