{
  "type": "Feature",
  "properties": {
    "iso:country":"GB",
    "wof:name":"SM6 0AT",
    "wof:placetype":"postalcode"
},
  "geometry": {"coordinates":[-0.14953581461232,51.36084989977368],"type":"Point"}
}