{
  "type": "Feature",
  "properties": {
    "iso:country":"GB",
    "wof:name":"SO19 6HR",
    "wof:placetype":"postalcode"
},
  "geometry": {"coordinates":[-1.33236018397946,50.90516718486322],"type":"Point"}
}