{
  "type": "Feature",
  "properties": {
    "iso:country": "GB",
    "wof:name": "CM15 8TG",
    "wof:placetype": "postalcode"
  },
  "geometry": {"coordinates":[0.305817,51.620541],"type":"Point"}
}
