{
  "type": "Feature",
  "properties": {
    "date:inception_lower": "2021-02-01",
    "date:inception_upper": "2021-02-01",
    "iso:country": "GB",
    "wof:name": "DG12 6FJ",
    "wof:placetype": "postalcode"
  },
  "geometry": {"coordinates":[-3.24453,54.992806],"type":"Point"}
}
