{
  "type": "Feature",
  "properties": {
    "iso:country":"GB",
    "wof:name":"PO3 6FB",
    "wof:placetype":"postalcode"
},
  "geometry": {"coordinates":[-1.05567954039616,50.80333973683338],"type":"Point"}
}