{
  "type": "Feature",
  "properties": {
    "date:inception_lower": "2009-09-01",
    "date:inception_upper": "2009-09-01",
    "iso:country": "GB",
    "wof:name": "OL3 5DB",
    "wof:placetype": "postalcode"
  },
  "geometry": {"coordinates":[-2.022998,53.561396],"type":"Point"}
}
