{
  "type": "Feature",
  "properties": {
    "date:inception_lower": "1996-06-01",
    "date:inception_upper": "1996-06-01",
    "iso:country": "GB",
    "wof:name": "AL1 4BT",
    "wof:placetype": "postalcode"
  },
  "geometry": {"coordinates":[-0.328965,51.758908],"type":"Point"}
}
