{
  "type": "Feature",
  "properties": {
    "iso:country":"GB",
    "wof:name":"AL1 4BT",
    "wof:placetype":"postalcode"
},
  "geometry": {"coordinates":[-0.32896537418394,51.75890824820545],"type":"Point"}
}