{
  "type": "Feature",
  "properties": {
    "iso:country":"GB",
    "wof:name":"OL8 2HJ",
    "wof:placetype":"postalcode"
},
  "geometry": {"coordinates":[-2.08616597444029,53.52468731936201],"type":"Point"}
}