{
  "type": "Feature",
  "properties": {
    "iso:country": "GB",
    "wof:name": "ST13 7JS",
    "wof:placetype": "postalcode"
  },
  "geometry": {"coordinates":[-2.053124,53.074911],"type":"Point"}
}
