{
  "type": "Feature",
  "properties": {
    "iso:country": "GB",
    "wof:name": "G81 6LN",
    "wof:placetype": "postalcode"
  },
  "geometry": {"coordinates":[-4.414623,55.928759],"type":"Point"}
}
