{
  "type": "Feature",
  "properties": {
    "iso:country": "GB",
    "wof:name": "NE18 0LL",
    "wof:placetype": "postalcode"
  },
  "geometry": {"coordinates":[-1.926366,55.008992],"type":"Point"}
}
