{
  "type": "Feature",
  "properties": {
    "iso:country":"GB",
    "wof:name":"NE18 0LL",
    "wof:placetype":"postalcode"
},
  "geometry": {"coordinates":[-1.92635690848085,55.00893196341293],"type":"Point"}
}