{
  "type": "Feature",
  "properties": {
    "iso:country":"GB",
    "wof:name":"IG1 3DP",
    "wof:placetype":"postalcode"
},
  "geometry": {"coordinates":[0.0595475678692,51.56285523936045],"type":"Point"}
}