{
  "type": "Feature",
  "properties": {
    "iso:country":"GB",
    "wof:name":"FK8 3HN",
    "wof:placetype":"postalcode"
},
  "geometry": {"coordinates":[-4.18588799888445,56.12152469094391],"type":"Point"}
}