{
  "type": "Feature",
  "properties": {
    "iso:country": "GB",
    "wof:name": "UB1 2HQ",
    "wof:placetype": "postalcode"
  },
  "geometry": {"coordinates":[-0.368532,51.51782],"type":"Point"}
}
