{
  "type": "Feature",
  "properties": {
    "date:inception_lower":"1980-01-01",
    "date:inception_upper":"1980-01-31",
    "iso:country":"GB",
    "wof:name":"UB1 2HQ",
    "wof:placetype":"postalcode"
},
  "geometry": {"coordinates":[-0.368532,51.51782],"type":"Point"}
}