{
  "type": "Feature",
  "properties": {
    "iso:country":"GB",
    "wof:name":"UB1 2HQ",
    "wof:placetype":"postalcode"
},
  "geometry": {"coordinates":[-0.36853231714459,51.51781983489302],"type":"Point"}
}