{
  "type": "Feature",
  "properties": {
    "iso:country": "GB",
    "wof:name": "CB22 6SX",
    "wof:placetype": "postalcode"
  },
  "geometry": {"coordinates":[0.048739,52.110873],"type":"Point"}
}
