{
  "type": "Feature",
  "properties": {
    "iso:country":"GB",
    "wof:name":"RG27 8PW",
    "wof:placetype":"postalcode"
},
  "geometry": {"coordinates":[-0.89805293512065,51.30374825389047],"type":"Point"}
}