{
  "type": "Feature",
  "properties": {
    "date:inception_lower": "1980-01-01",
    "date:inception_upper": "1980-01-01",
    "iso:country": "GB",
    "wof:name": "RG27 8PW",
    "wof:placetype": "postalcode"
  },
  "geometry": {"coordinates":[-0.898036,51.303748],"type":"Point"}
}
