{
  "type": "Feature",
  "properties": {
    "iso:country": "GB",
    "wof:name": "SY18 6HL",
    "wof:placetype": "postalcode"
  },
  "geometry": {"coordinates":[-3.542668,52.451963],"type":"Point"}
}
