{
  "type": "Feature",
  "properties": {
    "iso:country":"GB",
    "wof:name":"DE13 0LL",
    "wof:placetype":"postalcode"
},
  "geometry": {"coordinates":[-1.64104635718883,52.82975759712875],"type":"Point"}
}