{
  "type": "Feature",
  "properties": {
    "iso:country":"GB",
    "wof:name":"WF14 0BJ",
    "wof:placetype":"postalcode"
},
  "geometry": {"coordinates":[-1.72131087723921,53.68642607314026],"type":"Point"}
}