{
  "type": "Feature",
  "properties": {
    "date:inception_lower": "1994-05-01",
    "date:inception_upper": "1994-05-01",
    "iso:country": "GB",
    "wof:name": "WF14 0BJ",
    "wof:placetype": "postalcode"
  },
  "geometry": {"coordinates":[-1.721311,53.686426],"type":"Point"}
}
