{
  "type": "Feature",
  "properties": {
    "iso:country":"GB",
    "wof:name":"BR5 3BP",
    "wof:placetype":"postalcode"
},
  "geometry": {"coordinates":[0.11116502221159,51.4058667931211],"type":"Point"}
}