{
  "type": "Feature",
  "properties": {
    "date:inception_lower": "1980-01-01",
    "date:inception_upper": "1980-01-01",
    "iso:country": "GB",
    "wof:name": "BR5 3BP",
    "wof:placetype": "postalcode"
  },
  "geometry": {"coordinates":[0.111165,51.405867],"type":"Point"}
}
