{
  "type": "Feature",
  "properties": {
    "iso:country":"GB",
    "wof:name":"CH2 4AD",
    "wof:placetype":"postalcode"
},
  "geometry": {"coordinates":[-2.89544472574163,53.22392941023815],"type":"Point"}
}