{
  "type": "Feature",
  "properties": {
    "iso:country":"GB",
    "wof:name":"GL15 5PW",
    "wof:placetype":"postalcode"
},
  "geometry": {"coordinates":[-2.52301121699933,51.72477898280327],"type":"Point"}
}