{
  "type": "Feature",
  "properties": {
    "iso:country": "GB",
    "wof:name": "GL15 5PW",
    "wof:placetype": "postalcode"
  },
  "geometry": {"coordinates":[-2.522997,51.724788],"type":"Point"}
}
