{
  "type": "Feature",
  "properties": {
    "iso:country": "GB",
    "wof:name": "WD6 1NY",
    "wof:placetype": "postalcode"
  },
  "geometry": {"coordinates":[-0.277007,51.660198],"type":"Point"}
}
