{
  "type": "Feature",
  "properties": {
    "iso:country":"GB",
    "wof:name":"TS19 0LN",
    "wof:placetype":"postalcode"
},
  "geometry": {"coordinates":[-1.32577949307339,54.58195540812996],"type":"Point"}
}