{
  "type": "Feature",
  "properties": {
    "iso:country":"GB",
    "wof:name":"NN3 8YF",
    "wof:placetype":"postalcode"
},
  "geometry": {"coordinates":[-0.84210649087494,52.27327798605359],"type":"Point"}
}