{
  "type": "Feature",
  "properties": {
    "iso:country":"GB",
    "wof:name":"TS26 8LY",
    "wof:placetype":"postalcode"
},
  "geometry": {"coordinates":[-1.23344269707723,54.68653553220076],"type":"Point"}
}