{
  "type": "Feature",
  "properties": {
    "iso:country":"GB",
    "wof:name":"BH31 7LD",
    "wof:placetype":"postalcode"
},
  "geometry": {"coordinates":[-1.89414147879782,50.8849774125846],"type":"Point"}
}