{
  "type": "Feature",
  "properties": {
    "iso:country": "GB",
    "wof:name": "CF43 3AN",
    "wof:placetype": "postalcode"
  },
  "geometry": {"coordinates":[-3.43451,51.646751],"type":"Point"}
}
