{
  "type": "Feature",
  "properties": {
    "date:inception_lower":"1980-01-01",
    "date:inception_upper":"1980-01-31",
    "iso:country":"GB",
    "wof:name":"CF43 3AN",
    "wof:placetype":"postalcode"
},
  "geometry": {"coordinates":[-3.43451,51.646751],"type":"Point"}
}