{
  "type": "Feature",
  "properties": {
    "iso:country":"GB",
    "wof:name":"CF43 3AN",
    "wof:placetype":"postalcode"
},
  "geometry": {"coordinates":[-3.43450997918392,51.64675136467852],"type":"Point"}
}