{
  "type": "Feature",
  "properties": {
    "iso:country": "GB",
    "wof:name": "CF72 8LF",
    "wof:placetype": "postalcode"
  },
  "geometry": {"coordinates":[-3.382752,51.55322],"type":"Point"}
}
