{
  "type": "Feature",
  "properties": {
    "date:inception_lower": "1980-01-01",
    "date:inception_upper": "1980-01-01",
    "iso:country": "GB",
    "wof:name": "TW14 0DZ",
    "wof:placetype": "postalcode"
  },
  "geometry": {"coordinates":[-0.397457,51.450929],"type":"Point"}
}
