{
  "type": "Feature",
  "properties": {
    "iso:country":"GB",
    "wof:name":"TW14 0DZ",
    "wof:placetype":"postalcode"
},
  "geometry": {"coordinates":[-0.39745654138681,51.4509293596174],"type":"Point"}
}