{
  "type": "Feature",
  "properties": {
    "iso:country":"GB",
    "wof:name":"LA5 9AP",
    "wof:placetype":"postalcode"
},
  "geometry": {"coordinates":[-2.76569892444841,54.12172165244944],"type":"Point"}
}