{
  "type": "Feature",
  "properties": {
    "iso:country":"GB",
    "wof:name":"HX7 5PD",
    "wof:placetype":"postalcode"
},
  "geometry": {"coordinates":[-1.97378553580132,53.73086038956422],"type":"Point"}
}