{
  "type": "Feature",
  "properties": {
    "date:inception_lower":"1980-01-01",
    "date:inception_upper":"1980-01-31",
    "iso:country":"GB",
    "wof:name":"HX7 5PD",
    "wof:placetype":"postalcode"
},
  "geometry": {"coordinates":[-1.973785,53.73086],"type":"Point"}
}