{
  "type": "Feature",
  "properties": {
    "iso:country":"GB",
    "wof:name":"M40 8JP",
    "wof:placetype":"postalcode"
},
  "geometry": {"coordinates":[-2.21605903338523,53.49913962174302],"type":"Point"}
}