{
  "type": "Feature",
  "properties": {
    "date:inception_lower":"1980-01-01",
    "date:inception_upper":"1980-01-31",
    "iso:country":"GB",
    "wof:name":"WN6 7BN",
    "wof:placetype":"postalcode"
},
  "geometry": {"coordinates":[-2.643847,53.55421],"type":"Point"}
}