{
  "type": "Feature",
  "properties": {
    "iso:country":"GB",
    "wof:name":"WN6 7BN",
    "wof:placetype":"postalcode"
},
  "geometry": {"coordinates":[-2.64384662739939,53.55420979548312],"type":"Point"}
}