{
  "type": "Feature",
  "properties": {
    "iso:country": "GB",
    "wof:name": "GL7 6DL",
    "wof:placetype": "postalcode"
  },
  "geometry": {"coordinates":[-1.978224,51.658454],"type":"Point"}
}
