{
  "type": "Feature",
  "properties": {
    "date:inception_lower":"1980-01-01",
    "date:inception_upper":"1980-01-31",
    "iso:country":"GB",
    "wof:name":"GL7 6DL",
    "wof:placetype":"postalcode"
},
  "geometry": {"coordinates":[-1.978224,51.658454],"type":"Point"}
}