{
  "type": "Feature",
  "properties": {
    "iso:country": "GB",
    "wof:name": "S14 1BQ",
    "wof:placetype": "postalcode"
  },
  "geometry": {"coordinates":[-1.443733,53.338395],"type":"Point"}
}
