{
  "type": "Feature",
  "properties": {
    "iso:country":"GB",
    "wof:name":"S14 1BQ",
    "wof:placetype":"postalcode"
},
  "geometry": {"coordinates":[-1.44371897163546,53.33838580794452],"type":"Point"}
}