{
  "type": "Feature",
  "properties": {
    "iso:country":"GB",
    "wof:name":"BR1 2UD",
    "wof:placetype":"postalcode"
},
  "geometry": {"coordinates":[0.03498448955766,51.41034410185353],"type":"Point"}
}