{
  "type": "Feature",
  "properties": {
    "date:inception_lower": "1980-01-01",
    "date:inception_upper": "1980-01-01",
    "iso:country": "GB",
    "wof:name": "BR1 2UD",
    "wof:placetype": "postalcode"
  },
  "geometry": {"coordinates":[0.034985,51.410344],"type":"Point"}
}
