{
  "type": "Feature",
  "properties": {
    "iso:country":"GB",
    "wof:name":"G44 3ED",
    "wof:placetype":"postalcode"
},
  "geometry": {"coordinates":[-4.26975475407129,55.81205054956165],"type":"Point"}
}