{
  "type": "Feature",
  "properties": {
    "date:inception_lower": "2022-03-01",
    "date:inception_upper": "2022-03-01",
    "iso:country": "GB",
    "wof:name": "S60 8EF",
    "wof:placetype": "postalcode"
  },
  "geometry": {"coordinates":[-1.36237,53.385359],"type":"Point"}
}
