{
  "type": "Feature",
  "properties": {
    "date:inception_lower":"2000-12-01",
    "date:inception_upper":"2000-12-31",
    "iso:country":"GB",
    "wof:name":"W1T 4JR",
    "wof:placetype":"postalcode"
},
  "geometry": {"coordinates":[-0.139088,51.520636],"type":"Point"}
}