{
  "type": "Feature",
  "properties": {
    "iso:country":"GB",
    "wof:name":"W1T 4JR",
    "wof:placetype":"postalcode"
},
  "geometry": {"coordinates":[-0.13908781817999,51.52063592013999],"type":"Point"}
}