{
  "type": "Feature",
  "properties": {
    "iso:country": "GB",
    "wof:name": "W1T 4JR",
    "wof:placetype": "postalcode"
  },
  "geometry": {"coordinates":[-0.139088,51.520636],"type":"Point"}
}
