{
  "type": "Feature",
  "properties": {
    "iso:country":"GB",
    "wof:name":"UB4 8HG",
    "wof:placetype":"postalcode"
},
  "geometry": {"coordinates":[-0.43369748436039,51.52653123272807],"type":"Point"}
}