{
  "type": "Feature",
  "properties": {
    "date:inception_lower": "1990-02-01",
    "date:inception_upper": "1990-02-01",
    "iso:country": "GB",
    "wof:name": "NR4 6RT",
    "wof:placetype": "postalcode"
  },
  "geometry": {"coordinates":[1.257333,52.590292],"type":"Point"}
}
