{
  "type": "Feature",
  "properties": {
    "iso:country": "GB",
    "wof:name": "NR4 6RT",
    "wof:placetype": "postalcode"
  },
  "geometry": {"coordinates":[1.257333,52.590292],"type":"Point"}
}
