{
  "type": "Feature",
  "properties": {
    "iso:country": "GB",
    "wof:name": "CV35 0BS",
    "wof:placetype": "postalcode"
  },
  "geometry": {"coordinates":[-1.475737,52.126786],"type":"Point"}
}
