{
  "type": "Feature",
  "properties": {
    "date:inception_lower": "2005-09-01",
    "date:inception_upper": "2005-09-01",
    "iso:country": "GB",
    "wof:name": "DD3 9EH",
    "wof:placetype": "postalcode"
  },
  "geometry": {"coordinates":[-2.996425,56.490758],"type":"Point"}
}
