{
  "type": "Feature",
  "properties": {
    "date:inception_lower": "1980-01-01",
    "date:inception_upper": "1980-01-01",
    "iso:country": "GB",
    "wof:name": "WN6 7BD",
    "wof:placetype": "postalcode"
  },
  "geometry": {"coordinates":[-2.648944,53.553931],"type":"Point"}
}
