{
  "type": "Feature",
  "properties": {
    "iso:country":"GB",
    "wof:name":"WN6 7BD",
    "wof:placetype":"postalcode"
},
  "geometry": {"coordinates":[-2.64894434834137,53.55393055692833],"type":"Point"}
}