{
  "type": "Feature",
  "properties": {
    "date:inception_lower":"1980-01-01",
    "date:inception_upper":"1980-01-31",
    "iso:country":"GB",
    "wof:name":"DY12 3DP",
    "wof:placetype":"postalcode"
},
  "geometry": {"coordinates":[-2.3798,52.415729],"type":"Point"}
}