{
  "type": "Feature",
  "properties": {
    "iso:country":"GB",
    "wof:name":"DY12 3DP",
    "wof:placetype":"postalcode"
},
  "geometry": {"coordinates":[-2.37980043712096,52.41572916837072],"type":"Point"}
}