{
  "type": "Feature",
  "properties": {
    "iso:country": "GB",
    "wof:name": "LE8 0NU",
    "wof:placetype": "postalcode"
  },
  "geometry": {"coordinates":[-0.998781,52.542768],"type":"Point"}
}
