{
  "type": "Feature",
  "properties": {
    "iso:country":"GB",
    "wof:name":"LE8 0NU",
    "wof:placetype":"postalcode"
},
  "geometry": {"coordinates":[-0.99878111573856,52.54276835105308],"type":"Point"}
}