{
  "type": "Feature",
  "properties": {
    "date:inception_lower": "1999-12-01",
    "date:inception_upper": "1999-12-01",
    "iso:country": "GB",
    "wof:name": "SE10 0PH",
    "wof:placetype": "postalcode"
  },
  "geometry": {"coordinates":[0.00324,51.500298],"type":"Point"}
}
