{
  "type": "Feature",
  "properties": {
    "iso:country":"GB",
    "wof:name":"TS25 1RL",
    "wof:placetype":"postalcode"
},
  "geometry": {"coordinates":[-1.21663005835791,54.67754899454368],"type":"Point"}
}