{
  "type": "Feature",
  "properties": {
    "iso:country":"GB",
    "wof:name":"CO10 8UD",
    "wof:placetype":"postalcode"
},
  "geometry": {"coordinates":[0.50197562686259,52.05736697255308],"type":"Point"}
}