{
  "type": "Feature",
  "properties": {
    "iso:country": "GB",
    "wof:name": "CO10 8UD",
    "wof:placetype": "postalcode"
  },
  "geometry": {"coordinates":[0.501976,52.057367],"type":"Point"}
}
