{
  "type": "Feature",
  "properties": {
    "iso:country": "GB",
    "wof:name": "TR10 8EA",
    "wof:placetype": "postalcode"
  },
  "geometry": {"coordinates":[-5.103217,50.171143],"type":"Point"}
}
