{
  "type": "Feature",
  "properties": {
    "date:inception_lower":"1988-03-01",
    "date:inception_upper":"1988-03-31",
    "iso:country":"GB",
    "wof:name":"TR10 8EA",
    "wof:placetype":"postalcode"
},
  "geometry": {"coordinates":[-5.103217,50.171143],"type":"Point"}
}