{
  "type": "Feature",
  "properties": {
    "iso:country":"GB",
    "wof:name":"TR10 8EA",
    "wof:placetype":"postalcode"
},
  "geometry": {"coordinates":[-5.10321747089332,50.17114255725545],"type":"Point"}
}