{
  "type": "Feature",
  "properties": {
    "iso:country":"GB",
    "wof:name":"CH5 2QH",
    "wof:placetype":"postalcode"
},
  "geometry": {"coordinates":[-2.99420848277268,53.19785055250077],"type":"Point"}
}