{
  "type": "Feature",
  "properties": {
    "date:inception_lower":"1980-01-01",
    "date:inception_upper":"1980-01-31",
    "iso:country":"GB",
    "wof:name":"CH5 2QH",
    "wof:placetype":"postalcode"
},
  "geometry": {"coordinates":[-2.99418,53.197921],"type":"Point"}
}