{
  "type": "Feature",
  "properties": {
    "iso:country": "GB",
    "wof:name": "NN5 4FJ",
    "wof:placetype": "postalcode"
  },
  "geometry": {"coordinates":[-0.949664,52.24],"type":"Point"}
}
