{
  "type": "Feature",
  "properties": {
    "iso:country":"GB",
    "wof:name":"W1F 9UL",
    "wof:placetype":"postalcode"
},
  "geometry": {"coordinates":[-0.13544171272011,51.51144162864115],"type":"Point"}
}