{
  "type": "Feature",
  "properties": {
    "iso:country":"GB",
    "wof:name":"BS14 0HD",
    "wof:placetype":"postalcode"
},
  "geometry": {"coordinates":[-2.5676228357931,51.40446675178307],"type":"Point"}
}