{
  "type": "Feature",
  "properties": {
    "iso:country": "GB",
    "wof:name": "TA10 9JA",
    "wof:placetype": "postalcode"
  },
  "geometry": {"coordinates":[-2.736877,51.02352],"type":"Point"}
}
