{
  "type": "Feature",
  "properties": {
    "iso:country":"GB",
    "wof:name":"TA10 9JA",
    "wof:placetype":"postalcode"
},
  "geometry": {"coordinates":[-2.73687706191044,51.02351974912058],"type":"Point"}
}