{
  "type": "Feature",
  "properties": {
    "iso:country": "GB",
    "wof:name": "FK8 1TU",
    "wof:placetype": "postalcode"
  },
  "geometry": {"coordinates":[-3.960489,56.13481],"type":"Point"}
}
