{
  "type": "Feature",
  "properties": {
    "date:inception_lower":"2016-01-01",
    "date:inception_upper":"2016-01-31",
    "iso:country":"GB",
    "wof:name":"FK8 1TU",
    "wof:placetype":"postalcode"
},
  "geometry": {"coordinates":[-3.960489,56.13481],"type":"Point"}
}