{
  "type": "Feature",
  "properties": {
    "iso:country": "GB",
    "wof:name": "EX12 2SR",
    "wof:placetype": "postalcode"
  },
  "geometry": {"coordinates":[-3.069269,50.716186],"type":"Point"}
}
