{
  "type": "Feature",
  "properties": {
    "iso:country":"GB",
    "wof:name":"NE65 0PH",
    "wof:placetype":"postalcode"
},
  "geometry": {"coordinates":[-1.58048892227467,55.32957975052373],"type":"Point"}
}