{
  "type": "Feature",
  "properties": {
    "date:inception_lower": "1988-03-01",
    "date:inception_upper": "1988-03-01",
    "iso:country": "GB",
    "wof:name": "NE65 0PH",
    "wof:placetype": "postalcode"
  },
  "geometry": {"coordinates":[-1.580489,55.32958],"type":"Point"}
}
