{
  "type": "Feature",
  "properties": {
    "iso:country": "GB",
    "wof:name": "SG4 8XR",
    "wof:placetype": "postalcode"
  },
  "geometry": {"coordinates":[-0.233959,51.852095],"type":"Point"}
}
