{
  "type": "Feature",
  "properties": {
    "date:inception_lower":"1980-01-01",
    "date:inception_upper":"1980-01-31",
    "iso:country":"GB",
    "wof:name":"BS16 4RU",
    "wof:placetype":"postalcode"
},
  "geometry": {"coordinates":[-2.504959,51.47505],"type":"Point"}
}