{
  "type": "Feature",
  "properties": {
    "date:inception_lower": "2006-11-01",
    "date:inception_upper": "2006-11-01",
    "iso:country": "GB",
    "wof:name": "EX34 9DQ",
    "wof:placetype": "postalcode"
  },
  "geometry": {"coordinates":[-4.120906,51.208714],"type":"Point"}
}
