{
  "type": "Feature",
  "properties": {
    "iso:country":"GB",
    "wof:name":"EX34 9DQ",
    "wof:placetype":"postalcode"
},
  "geometry": {"coordinates":[-4.12090574166782,51.20871433271725],"type":"Point"}
}