{
  "type": "Feature",
  "properties": {
    "date:inception_lower":"1980-01-01",
    "date:inception_upper":"1980-01-31",
    "iso:country":"GB",
    "wof:name":"PL24 2AH",
    "wof:placetype":"postalcode"
},
  "geometry": {"coordinates":[-4.700125,50.352954],"type":"Point"}
}