{
  "type": "Feature",
  "properties": {
    "iso:country":"GB",
    "wof:name":"PL24 2AH",
    "wof:placetype":"postalcode"
},
  "geometry": {"coordinates":[-4.70010183555181,50.35277764303614],"type":"Point"}
}