{
  "type": "Feature",
  "properties": {
    "date:inception_lower": "2006-07-01",
    "date:inception_upper": "2006-07-01",
    "iso:country": "GB",
    "wof:name": "YO7 3NX",
    "wof:placetype": "postalcode"
  },
  "geometry": {"coordinates":[-1.332229,54.233008],"type":"Point"}
}
