{
  "type": "Feature",
  "properties": {
    "iso:country":"GB",
    "wof:name":"S40 4SD",
    "wof:placetype":"postalcode"
},
  "geometry": {"coordinates":[-1.43137509486473,53.23996266122448],"type":"Point"}
}