{
  "type": "Feature",
  "properties": {
    "iso:country": "GB",
    "wof:name": "SS7 4JU",
    "wof:placetype": "postalcode"
  },
  "geometry": {"coordinates":[0.561309,51.57346],"type":"Point"}
}
