{
  "type": "Feature",
  "properties": {
    "iso:country":"GB",
    "wof:name":"HP13 5JB",
    "wof:placetype":"postalcode"
},
  "geometry": {"coordinates":[-0.77822794413401,51.64170047322326],"type":"Point"}
}