{
  "type": "Feature",
  "properties": {
    "iso:country": "GB",
    "wof:name": "RG7 6JN",
    "wof:placetype": "postalcode"
  },
  "geometry": {"coordinates":[-1.158495,51.42926],"type":"Point"}
}
