{
  "type": "Feature",
  "properties": {
    "date:inception_lower": "1980-01-01",
    "date:inception_upper": "1980-01-01",
    "iso:country": "GB",
    "wof:name": "CB8 0JU",
    "wof:placetype": "postalcode"
  },
  "geometry": {"coordinates":[0.398952,52.24327],"type":"Point"}
}
