{
  "type": "Feature",
  "properties": {
    "iso:country":"GB",
    "wof:name":"CM15 9EJ",
    "wof:placetype":"postalcode"
},
  "geometry": {"coordinates":[0.29894475690316,51.62721342091226],"type":"Point"}
}