{
  "type": "Feature",
  "properties": {
    "date:inception_lower": "1980-01-01",
    "date:inception_upper": "1980-01-01",
    "iso:country": "GB",
    "wof:name": "CM15 9EJ",
    "wof:placetype": "postalcode"
  },
  "geometry": {"coordinates":[0.298987,51.627216],"type":"Point"}
}
