{
  "type": "Feature",
  "properties": {
    "iso:country":"GB",
    "wof:name":"M33 3AA",
    "wof:placetype":"postalcode"
},
  "geometry": {"coordinates":[-2.31797180864421,53.42349820536478],"type":"Point"}
}