{
  "type": "Feature",
  "properties": {
    "iso:country": "GB",
    "wof:name": "TR8 4JU",
    "wof:placetype": "postalcode"
  },
  "geometry": {"coordinates":[-5.046022,50.414039],"type":"Point"}
}
