{
  "type": "Feature",
  "properties": {
    "iso:country":"GB",
    "wof:name":"TR8 4JU",
    "wof:placetype":"postalcode"
},
  "geometry": {"coordinates":[-5.04602197609494,50.41403867717737],"type":"Point"}
}