{
  "type": "Feature",
  "properties": {
    "date:inception_lower": "1991-09-01",
    "date:inception_upper": "1991-09-01",
    "iso:country": "GB",
    "wof:name": "KT8 2PJ",
    "wof:placetype": "postalcode"
  },
  "geometry": {"coordinates":[-0.365767,51.399262],"type":"Point"}
}
