{
  "type": "Feature",
  "properties": {
    "iso:country":"GB",
    "wof:name":"KT8 2PJ",
    "wof:placetype":"postalcode"
},
  "geometry": {"coordinates":[-0.36576733408845,51.39926228049145],"type":"Point"}
}