{
  "type": "Feature",
  "properties": {
    "iso:country":"GB",
    "wof:name":"B31 4AW",
    "wof:placetype":"postalcode"
},
  "geometry": {"coordinates":[-1.96911655176707,52.40578167508053],"type":"Point"}
}