{
  "type": "Feature",
  "properties": {
    "date:inception_lower": "1980-01-01",
    "date:inception_upper": "1980-01-01",
    "iso:country": "GB",
    "wof:name": "B31 4AW",
    "wof:placetype": "postalcode"
  },
  "geometry": {"coordinates":[-1.969286,52.405734],"type":"Point"}
}
