{
  "type": "Feature",
  "properties": {
    "iso:country": "GB",
    "wof:name": "LA2 0BZ",
    "wof:placetype": "postalcode"
  },
  "geometry": {"coordinates":[-2.849874,53.997915],"type":"Point"}
}
