{
  "type": "Feature",
  "properties": {
    "iso:country":"GB",
    "wof:name":"LA2 0BZ",
    "wof:placetype":"postalcode"
},
  "geometry": {"coordinates":[-2.84987383801901,53.99791493580521],"type":"Point"}
}