{
  "type": "Feature",
  "properties": {
    "iso:country": "GB",
    "wof:name": "SA17 5AE",
    "wof:placetype": "postalcode"
  },
  "geometry": {"coordinates":[-4.294232,51.752178],"type":"Point"}
}
