{
  "type": "Feature",
  "properties": {
    "iso:country":"GB",
    "wof:name":"SA17 5AE",
    "wof:placetype":"postalcode"
},
  "geometry": {"coordinates":[-4.29329849859136,51.75307829486136],"type":"Point"}
}