{
  "type": "Feature",
  "properties": {
    "date:inception_lower": "1980-01-01",
    "date:inception_upper": "1980-01-01",
    "iso:country": "GB",
    "wof:name": "SA17 5AE",
    "wof:placetype": "postalcode"
  },
  "geometry": {"coordinates":[-4.293322,51.753086],"type":"Point"}
}
