{
  "type": "Feature",
  "properties": {
    "iso:country": "GB",
    "wof:name": "SP5 3PA",
    "wof:placetype": "postalcode"
  },
  "geometry": {"coordinates":[-1.726687,51.041892],"type":"Point"}
}
