{
  "type": "Feature",
  "properties": {
    "iso:country":"GB",
    "wof:name":"SP5 3PA",
    "wof:placetype":"postalcode"
},
  "geometry": {"coordinates":[-1.72668671158378,51.04189151005627],"type":"Point"}
}