{
  "type": "Feature",
  "properties": {
    "iso:country": "GB",
    "wof:name": "PR4 3DN",
    "wof:placetype": "postalcode"
  },
  "geometry": {"coordinates":[-2.889841,53.789523],"type":"Point"}
}
