{
  "type": "Feature",
  "properties": {
    "date:inception_lower": "2019-03-01",
    "date:inception_upper": "2019-03-01",
    "iso:country": "GB",
    "wof:name": "WN7 3FZ",
    "wof:placetype": "postalcode"
  },
  "geometry": {"coordinates":[-2.505276,53.483235],"type":"Point"}
}
