{
  "type": "Feature",
  "properties": {
    "date:inception_lower": "2023-04-01",
    "date:inception_upper": "2023-04-01",
    "iso:country": "GB",
    "wof:name": "S17 4BF",
    "wof:placetype": "postalcode"
  },
  "geometry": {"coordinates":[-1.540179,53.311965],"type":"Point"}
}
