{
  "type": "Feature",
  "properties": {
    "iso:country":"GB",
    "wof:name":"WS15 4LY",
    "wof:placetype":"postalcode"
},
  "geometry": {"coordinates":[-1.92626787378377,52.70601460526895],"type":"Point"}
}