{
  "type": "Feature",
  "properties": {
    "date:inception_lower": "2024-09-01",
    "date:inception_upper": "2024-09-01",
    "iso:country": "GB",
    "wof:name": "CW12 1TJ",
    "wof:placetype": "postalcode"
  },
  "geometry": {"coordinates":[-2.224528,53.17599],"type":"Point"}
}
