{
  "type": "Feature",
  "properties": {
    "date:inception_lower": "1996-12-01",
    "date:inception_upper": "1996-12-01",
    "iso:country": "GB",
    "wof:name": "LN8 2DP",
    "wof:placetype": "postalcode"
  },
  "geometry": {"coordinates":[-0.466344,53.370029],"type":"Point"}
}
