{
  "type": "Feature",
  "properties": {
    "iso:country":"GB",
    "wof:name":"LN8 2DP",
    "wof:placetype":"postalcode"
},
  "geometry": {"coordinates":[-0.46634436173588,53.37002936643309],"type":"Point"}
}