{
  "type": "Feature",
  "properties": {
    "iso:country":"GB",
    "wof:name":"CM7 5HS",
    "wof:placetype":"postalcode"
},
  "geometry": {"coordinates":[0.50231408033198,51.93727936833494],"type":"Point"}
}