{
  "type": "Feature",
  "properties": {
    "iso:country": "GB",
    "wof:name": "RG8 7QA",
    "wof:placetype": "postalcode"
  },
  "geometry": {"coordinates":[-1.084575,51.514406],"type":"Point"}
}
