{
  "type": "Feature",
  "properties": {
    "iso:country":"GB",
    "wof:name":"RG8 7QA",
    "wof:placetype":"postalcode"
},
  "geometry": {"coordinates":[-1.08457524391055,51.51440612539227],"type":"Point"}
}