{
  "type": "Feature",
  "properties": {
    "iso:country":"GB",
    "wof:name":"GL1 4TU",
    "wof:placetype":"postalcode"
},
  "geometry": {"coordinates":[-2.24133345027814,51.85460011344355],"type":"Point"}
}