{
  "type": "Feature",
  "properties": {
    "date:inception_lower": "2023-05-01",
    "date:inception_upper": "2023-05-01",
    "iso:country": "GB",
    "wof:name": "OX5 9FS",
    "wof:placetype": "postalcode"
  },
  "geometry": {"coordinates":[-1.287411,51.82301],"type":"Point"}
}
