{
  "type": "Feature",
  "properties": {
    "date:inception_lower": "1992-08-01",
    "date:inception_upper": "1992-08-01",
    "iso:country": "GB",
    "wof:name": "GL56 9RN",
    "wof:placetype": "postalcode"
  },
  "geometry": {"coordinates":[-1.680993,52.043961],"type":"Point"}
}
