{
  "type": "Feature",
  "properties": {
    "iso:country":"GB",
    "wof:name":"GL56 9RN",
    "wof:placetype":"postalcode"
},
  "geometry": {"coordinates":[-1.680993173125,52.04396055697574],"type":"Point"}
}