{
  "type": "Feature",
  "properties": {
    "iso:country": "GB",
    "wof:name": "TR18 3RQ",
    "wof:placetype": "postalcode"
  },
  "geometry": {"coordinates":[-5.524143,50.127804],"type":"Point"}
}
