{
  "type": "Feature",
  "properties": {
    "date:inception_lower":"1994-12-01",
    "date:inception_upper":"1994-12-31",
    "iso:country":"GB",
    "wof:name":"TR18 3RQ",
    "wof:placetype":"postalcode"
},
  "geometry": {"coordinates":[-5.524143,50.127804],"type":"Point"}
}