{
  "type": "Feature",
  "properties": {
    "iso:country": "GB",
    "wof:name": "LA5 5BE",
    "wof:placetype": "postalcode"
  },
  "geometry": {"coordinates":[-2.770026,54.129874],"type":"Point"}
}
