{
  "type": "Feature",
  "properties": {
    "iso:country":"GB",
    "wof:name":"TS10 1HX",
    "wof:placetype":"postalcode"
},
  "geometry": {"coordinates":[-1.06814378356055,54.61073096393669],"type":"Point"}
}