{
  "type": "Feature",
  "properties": {
    "date:inception_lower": "1980-01-01",
    "date:inception_upper": "1980-01-01",
    "iso:country": "GB",
    "wof:name": "G71 5EE",
    "wof:placetype": "postalcode"
  },
  "geometry": {"coordinates":[-4.062807,55.827911],"type":"Point"}
}
