{
  "type": "Feature",
  "properties": {
    "iso:country": "GB",
    "wof:name": "G71 5EE",
    "wof:placetype": "postalcode"
  },
  "geometry": {"coordinates":[-4.062807,55.827911],"type":"Point"}
}
