{
  "type": "Feature",
  "properties": {
    "iso:country":"GB",
    "wof:name":"G71 5EE",
    "wof:placetype":"postalcode"
},
  "geometry": {"coordinates":[-4.06280712326288,55.8279107059936],"type":"Point"}
}