{
  "type": "Feature",
  "properties": {
    "date:inception_lower": "2003-07-01",
    "date:inception_upper": "2003-07-01",
    "iso:country": "GB",
    "wof:name": "SG13 7BA",
    "wof:placetype": "postalcode"
  },
  "geometry": {"coordinates":[-0.066891,51.803844],"type":"Point"}
}
