{
  "type": "Feature",
  "properties": {
    "iso:country": "GB",
    "wof:name": "PO9 2HU",
    "wof:placetype": "postalcode"
  },
  "geometry": {"coordinates":[-0.982374,50.858496],"type":"Point"}
}
