{
  "type": "Feature",
  "properties": {
    "date:inception_lower": "2016-04-01",
    "date:inception_upper": "2016-04-01",
    "iso:country": "GB",
    "wof:name": "TR15 2TU",
    "wof:placetype": "postalcode"
  },
  "geometry": {"coordinates":[-5.232971,50.2314],"type":"Point"}
}
