{
  "type": "Feature",
  "properties": {
    "iso:country":"GB",
    "wof:name":"TR15 2TU",
    "wof:placetype":"postalcode"
},
  "geometry": {"coordinates":[-5.23229081717112,50.23171576184168],"type":"Point"}
}