{
  "type": "Feature",
  "properties": {
    "date:inception_lower": "2022-02-01",
    "date:inception_upper": "2022-02-01",
    "iso:country": "GB",
    "wof:name": "GL3 1GN",
    "wof:placetype": "postalcode"
  },
  "geometry": {"coordinates":[-2.199185,51.882046],"type":"Point"}
}
