{
  "type": "Feature",
  "properties": {
    "iso:country":"GB",
    "wof:name":"PL2 2RW",
    "wof:placetype":"postalcode"
},
  "geometry": {"coordinates":[-4.16129661609015,50.39547255239467],"type":"Point"}
}