{
  "type": "Feature",
  "properties": {
    "iso:country":"GB",
    "wof:name":"LU2 9RH",
    "wof:placetype":"postalcode"
},
  "geometry": {"coordinates":[-0.37909377443206,51.89330039728004],"type":"Point"}
}