{
  "type": "Feature",
  "properties": {
    "iso:country":"GB",
    "wof:name":"DL4 1AT",
    "wof:placetype":"postalcode"
},
  "geometry": {"coordinates":[-1.65502485104922,54.63308278404529],"type":"Point"}
}