{
  "type": "Feature",
  "properties": {
    "iso:country":"GB",
    "wof:name":"ME3 8LY",
    "wof:placetype":"postalcode"
},
  "geometry": {"coordinates":[0.53330758967251,51.41832820668365],"type":"Point"}
}