{
  "type": "Feature",
  "properties": {
    "iso:country": "GB",
    "wof:name": "CB9 7GH",
    "wof:placetype": "postalcode"
  },
  "geometry": {"coordinates":[0.419648,52.089329],"type":"Point"}
}
