{
  "type": "Feature",
  "properties": {
    "date:inception_lower": "1980-01-01",
    "date:inception_upper": "1980-01-01",
    "iso:country": "GB",
    "wof:name": "SR7 0EY",
    "wof:placetype": "postalcode"
  },
  "geometry": {"coordinates":[-1.359177,54.842376],"type":"Point"}
}
