{
  "type": "Feature",
  "properties": {
    "iso:country":"GB",
    "wof:name":"SR7 0EY",
    "wof:placetype":"postalcode"
},
  "geometry": {"coordinates":[-1.35917671489619,54.84237562943918],"type":"Point"}
}