{
  "type": "Feature",
  "properties": {
    "date:inception_lower": "1999-06-01",
    "date:inception_upper": "1999-06-01",
    "iso:country": "GB",
    "wof:name": "NE12 5XP",
    "wof:placetype": "postalcode"
  },
  "geometry": {"coordinates":[-1.577391,55.042333],"type":"Point"}
}
