{
  "type": "Feature",
  "properties": {
    "iso:country":"GB",
    "wof:name":"RG2 7HB",
    "wof:placetype":"postalcode"
},
  "geometry": {"coordinates":[-0.95569396405607,51.44008235675662],"type":"Point"}
}