{
  "type": "Feature",
  "properties": {
    "iso:country":"GB",
    "wof:name":"DG13 0PZ",
    "wof:placetype":"postalcode"
},
  "geometry": {"coordinates":[-3.01084252585391,55.15328237998317],"type":"Point"}
}