{
  "type": "Feature",
  "properties": {
    "iso:country":"GB",
    "wof:name":"W5 5NJ",
    "wof:placetype":"postalcode"
},
  "geometry": {"coordinates":[-0.30224853868758,51.50768006496551],"type":"Point"}
}