{
  "type": "Feature",
  "properties": {
    "date:inception_lower":"1987-04-01",
    "date:inception_upper":"1987-04-30",
    "iso:country":"GB",
    "wof:name":"LS29 8PR",
    "wof:placetype":"postalcode"
},
  "geometry": {"coordinates":[-1.820084,53.923439],"type":"Point"}
}