{
  "type": "Feature",
  "properties": {
    "iso:country": "GB",
    "wof:name": "EH52 5EN",
    "wof:placetype": "postalcode"
  },
  "geometry": {"coordinates":[-3.460039,55.934154],"type":"Point"}
}
