{
  "type": "Feature",
  "properties": {
    "iso:country":"GB",
    "wof:name":"B72 1TU",
    "wof:placetype":"postalcode"
},
  "geometry": {"coordinates":[-1.82124369100384,52.56513281401078],"type":"Point"}
}