{
  "type": "Feature",
  "properties": {
    "iso:country": "GB",
    "wof:name": "B72 1TU",
    "wof:placetype": "postalcode"
  },
  "geometry": {"coordinates":[-1.821244,52.565133],"type":"Point"}
}
