{
  "type": "Feature",
  "properties": {
    "iso:country":"GB",
    "wof:name":"CF11 7HH",
    "wof:placetype":"postalcode"
},
  "geometry": {"coordinates":[-3.18377335736036,51.46464878765177],"type":"Point"}
}