{
  "type": "Feature",
  "properties": {
    "iso:country": "GB",
    "wof:name": "EH26 8EW",
    "wof:placetype": "postalcode"
  },
  "geometry": {"coordinates":[-3.210575,55.832962],"type":"Point"}
}
