{
  "type": "Feature",
  "properties": {
    "iso:country":"GB",
    "wof:name":"EH26 8EW",
    "wof:placetype":"postalcode"
},
  "geometry": {"coordinates":[-3.2105750123301,55.83296213201416],"type":"Point"}
}