{
  "type": "Feature",
  "properties": {
    "date:inception_lower": "2017-01-01",
    "date:inception_upper": "2017-01-01",
    "iso:country": "GB",
    "wof:name": "LS18 4GJ",
    "wof:placetype": "postalcode"
  },
  "geometry": {"coordinates":[-1.67122,53.835022],"type":"Point"}
}
