{
  "type": "Feature",
  "properties": {
    "iso:country": "GB",
    "wof:name": "CW6 9EU",
    "wof:placetype": "postalcode"
  },
  "geometry": {"coordinates":[-2.605115,53.203579],"type":"Point"}
}
