{
  "type": "Feature",
  "properties": {
    "iso:country":"GB",
    "wof:name":"OL12 8SW",
    "wof:placetype":"postalcode"
},
  "geometry": {"coordinates":[-2.17738061479477,53.64772614092035],"type":"Point"}
}