{
  "type": "Feature",
  "properties": {
    "date:inception_lower": "1980-01-01",
    "date:inception_upper": "1980-01-01",
    "iso:country": "GB",
    "wof:name": "OL12 8SW",
    "wof:placetype": "postalcode"
  },
  "geometry": {"coordinates":[-2.177381,53.647726],"type":"Point"}
}
