{
  "type": "Feature",
  "properties": {
    "iso:country": "GB",
    "wof:name": "OL12 8SW",
    "wof:placetype": "postalcode"
  },
  "geometry": {"coordinates":[-2.177381,53.647726],"type":"Point"}
}
