{
  "type": "Feature",
  "properties": {
    "date:inception_lower": "2021-03-01",
    "date:inception_upper": "2021-03-01",
    "iso:country": "GB",
    "wof:name": "HR8 2SY",
    "wof:placetype": "postalcode"
  },
  "geometry": {"coordinates":[-2.428192,52.025515],"type":"Point"}
}
