{
  "type": "Feature",
  "properties": {
    "iso:country":"GB",
    "wof:name":"TF10 7QU",
    "wof:placetype":"postalcode"
},
  "geometry": {"coordinates":[-2.3819387494644,52.76258638630852],"type":"Point"}
}