{
  "type": "Feature",
  "properties": {
    "iso:country": "GB",
    "wof:name": "TF10 7QU",
    "wof:placetype": "postalcode"
  },
  "geometry": {"coordinates":[-2.381939,52.762586],"type":"Point"}
}
