{
  "type": "Feature",
  "properties": {
    "iso:country":"GB",
    "wof:name":"DL15 0TN",
    "wof:placetype":"postalcode"
},
  "geometry": {"coordinates":[-1.69908986083321,54.73276347324991],"type":"Point"}
}