{
  "type": "Feature",
  "properties": {
    "iso:country": "GB",
    "wof:name": "TN33 0ST",
    "wof:placetype": "postalcode"
  },
  "geometry": {"coordinates":[0.479313,50.897196],"type":"Point"}
}
