{
  "type": "Feature",
  "properties": {
    "iso:country":"GB",
    "wof:name":"TN33 0ST",
    "wof:placetype":"postalcode"
},
  "geometry": {"coordinates":[0.47931329474996,50.89719632897254],"type":"Point"}
}