{
  "type": "Feature",
  "properties": {
    "iso:country": "GB",
    "wof:name": "LS23 6GH",
    "wof:placetype": "postalcode"
  },
  "geometry": {"coordinates":[-1.344843,53.899056],"type":"Point"}
}
