{
  "type": "Feature",
  "properties": {
    "date:inception_lower":"2009-05-01",
    "date:inception_upper":"2009-05-31",
    "iso:country":"GB",
    "wof:name":"LS23 6GH",
    "wof:placetype":"postalcode"
},
  "geometry": {"coordinates":[-1.344843,53.899056],"type":"Point"}
}