{
  "type": "Feature",
  "properties": {
    "iso:country":"GB",
    "wof:name":"NE3 2BQ",
    "wof:placetype":"postalcode"
},
  "geometry": {"coordinates":[-1.64394438374628,55.02127522080833],"type":"Point"}
}