{
  "type": "Feature",
  "properties": {
    "iso:country": "GB",
    "wof:name": "HU5 5YN",
    "wof:placetype": "postalcode"
  },
  "geometry": {"coordinates":[-0.407817,53.749521],"type":"Point"}
}
