{
  "type": "Feature",
  "properties": {
    "iso:country": "GB",
    "wof:name": "HU10 7QD",
    "wof:placetype": "postalcode"
  },
  "geometry": {"coordinates":[-0.447436,53.751416],"type":"Point"}
}
