{
  "type": "Feature",
  "properties": {
    "date:inception_lower": "2005-04-01",
    "date:inception_upper": "2005-04-01",
    "iso:country": "GB",
    "wof:name": "NG6 8PN",
    "wof:placetype": "postalcode"
  },
  "geometry": {"coordinates":[-1.196349,52.992325],"type":"Point"}
}
