{
  "type": "Feature",
  "properties": {
    "date:inception_lower":"2005-04-01",
    "date:inception_upper":"2005-04-30",
    "iso:country":"GB",
    "wof:name":"NG6 8PN",
    "wof:placetype":"postalcode"
},
  "geometry": {"coordinates":[-1.196397,52.992324],"type":"Point"}
}