{
  "type": "Feature",
  "properties": {
    "iso:country":"GB",
    "wof:name":"NG6 8PN",
    "wof:placetype":"postalcode"
},
  "geometry": {"coordinates":[-1.19639708020411,52.99232366882708],"type":"Point"}
}