{
  "type": "Feature",
  "properties": {
    "iso:country":"GB",
    "wof:name":"TN2 4JZ",
    "wof:placetype":"postalcode"
},
  "geometry": {"coordinates":[0.33538006421535,51.14048776914809],"type":"Point"}
}