{
  "type": "Feature",
  "properties": {
    "iso:country":"GB",
    "wof:name":"ME13 7BD",
    "wof:placetype":"postalcode"
},
  "geometry": {"coordinates":[0.89415354162341,51.31777825932885],"type":"Point"}
}