{
  "type": "Feature",
  "properties": {
    "iso:country":"GB",
    "wof:name":"DE6 2EA",
    "wof:placetype":"postalcode"
},
  "geometry": {"coordinates":[-1.76503173157756,53.0068691919681],"type":"Point"}
}