{
  "type": "Feature",
  "properties": {
    "iso:country":"GB",
    "wof:name":"M34 6JE",
    "wof:placetype":"postalcode"
},
  "geometry": {"coordinates":[-2.11830288304358,53.44656826807169],"type":"Point"}
}