{
  "type": "Feature",
  "properties": {
    "iso:country": "GB",
    "wof:name": "DN5 8HH",
    "wof:placetype": "postalcode"
  },
  "geometry": {"coordinates":[-1.165681,53.533018],"type":"Point"}
}
