{
  "type": "Feature",
  "properties": {
    "date:inception_lower": "2000-12-01",
    "date:inception_upper": "2000-12-01",
    "iso:country": "GB",
    "wof:name": "DY3 2RG",
    "wof:placetype": "postalcode"
  },
  "geometry": {"coordinates":[-2.121198,52.520648],"type":"Point"}
}
