{
  "type": "Feature",
  "properties": {
    "date:inception_lower": "2017-02-01",
    "date:inception_upper": "2017-02-01",
    "iso:country": "GB",
    "wof:name": "M5 3TT",
    "wof:placetype": "postalcode"
  },
  "geometry": {"coordinates":[-2.279672,53.466801],"type":"Point"}
}
