{
  "type": "Feature",
  "properties": {
    "iso:country":"GB",
    "wof:name":"LS26 9AB",
    "wof:placetype":"postalcode"
},
  "geometry": {"coordinates":[-1.39392178960117,53.73556977686315],"type":"Point"}
}