{
  "type": "Feature",
  "properties": {
    "iso:country": "GB",
    "wof:name": "LS26 9AB",
    "wof:placetype": "postalcode"
  },
  "geometry": {"coordinates":[-1.393922,53.73557],"type":"Point"}
}
