{
  "type": "Feature",
  "properties": {
    "iso:country":"GB",
    "wof:name":"NG13 8ZH",
    "wof:placetype":"postalcode"
},
  "geometry": {"coordinates":[-0.97576998708653,52.96454950820366],"type":"Point"}
}