{
  "type": "Feature",
  "properties": {
    "iso:country": "GB",
    "wof:name": "NG13 8ZH",
    "wof:placetype": "postalcode"
  },
  "geometry": {"coordinates":[-0.97577,52.96455],"type":"Point"}
}
