{
  "type": "Feature",
  "properties": {
    "iso:country": "GB",
    "wof:name": "DL14 8UH",
    "wof:placetype": "postalcode"
  },
  "geometry": {"coordinates":[-1.64729,54.647341],"type":"Point"}
}
