{
  "type": "Feature",
  "properties": {
    "date:inception_lower":"1980-01-01",
    "date:inception_upper":"1980-01-31",
    "iso:country":"GB",
    "wof:name":"DL14 8UH",
    "wof:placetype":"postalcode"
},
  "geometry": {"coordinates":[-1.64729,54.647341],"type":"Point"}
}