{
  "type": "Feature",
  "properties": {
    "iso:country":"GB",
    "wof:name":"TW12 3AW",
    "wof:placetype":"postalcode"
},
  "geometry": {"coordinates":[-0.36630693235071,51.42325255729828],"type":"Point"}
}