{
  "type": "Feature",
  "properties": {
    "iso:country": "GB",
    "wof:name": "CV10 7AB",
    "wof:placetype": "postalcode"
  },
  "geometry": {"coordinates":[-1.467936,52.509909],"type":"Point"}
}
