{
  "type": "Feature",
  "properties": {
    "date:inception_lower": "1990-08-01",
    "date:inception_upper": "1990-08-01",
    "iso:country": "GB",
    "wof:name": "AB51 0YG",
    "wof:placetype": "postalcode"
  },
  "geometry": {"coordinates":[-2.369404,57.250679],"type":"Point"}
}
