{
  "type": "Feature",
  "properties": {
    "iso:country":"GB",
    "wof:name":"AB51 0YG",
    "wof:placetype":"postalcode"
},
  "geometry": {"coordinates":[-2.3694040272827,57.25067884706554],"type":"Point"}
}