{
  "type": "Feature",
  "properties": {
    "iso:country": "GB",
    "wof:name": "DN19 7JJ",
    "wof:placetype": "postalcode"
  },
  "geometry": {"coordinates":[-0.331546,53.679464],"type":"Point"}
}
