{
  "type": "Feature",
  "properties": {
    "iso:country":"GB",
    "wof:name":"DN19 7JJ",
    "wof:placetype":"postalcode"
},
  "geometry": {"coordinates":[-0.3315457354603,53.67946417918648],"type":"Point"}
}