{
  "type": "Feature",
  "properties": {
    "iso:country":"GB",
    "wof:name":"S62 7AY",
    "wof:placetype":"postalcode"
},
  "geometry": {"coordinates":[-1.34200206170121,53.46406124015662],"type":"Point"}
}