{
  "type": "Feature",
  "properties": {
    "iso:country": "GB",
    "wof:name": "S62 7AY",
    "wof:placetype": "postalcode"
  },
  "geometry": {"coordinates":[-1.342002,53.464061],"type":"Point"}
}
