{
  "type": "Feature",
  "properties": {
    "iso:country":"GB",
    "wof:name":"RG6 4HD",
    "wof:placetype":"postalcode"
},
  "geometry": {"coordinates":[-0.92502863747426,51.42741438085528],"type":"Point"}
}