{
  "type": "Feature",
  "properties": {
    "date:inception_lower": "1997-12-01",
    "date:inception_upper": "1997-12-01",
    "iso:country": "GB",
    "wof:name": "BS30 6PQ",
    "wof:placetype": "postalcode"
  },
  "geometry": {"coordinates":[-2.476656,51.436835],"type":"Point"}
}
