{
  "type": "Feature",
  "properties": {
    "iso:country":"GB",
    "wof:name":"BS30 6PQ",
    "wof:placetype":"postalcode"
},
  "geometry": {"coordinates":[-2.47655760072903,51.43705373575192],"type":"Point"}
}