{
  "type": "Feature",
  "properties": {
    "iso:country": "GB",
    "wof:name": "BA22 7NT",
    "wof:placetype": "postalcode"
  },
  "geometry": {"coordinates":[-2.574757,51.023144],"type":"Point"}
}
