{
  "type": "Feature",
  "properties": {
    "date:inception_lower": "1996-12-01",
    "date:inception_upper": "1996-12-01",
    "iso:country": "GB",
    "wof:name": "SK22 3AR",
    "wof:placetype": "postalcode"
  },
  "geometry": {"coordinates":[-2.023571,53.368541],"type":"Point"}
}
