{
  "type": "Feature",
  "properties": {
    "iso:country":"GB",
    "wof:name":"WV10 0RQ",
    "wof:placetype":"postalcode"
},
  "geometry": {"coordinates":[-2.10502696771175,52.60307658865765],"type":"Point"}
}