{
  "type": "Feature",
  "properties": {
    "iso:country":"GB",
    "wof:name":"YO42 2QU",
    "wof:placetype":"postalcode"
},
  "geometry": {"coordinates":[-0.78083640978775,53.92935973321624],"type":"Point"}
}