{
  "type": "Feature",
  "properties": {
    "iso:country":"GB",
    "wof:name":"BB18 6XB",
    "wof:placetype":"postalcode"
},
  "geometry": {"coordinates":[-2.14582533454809,53.91462219922227],"type":"Point"}
}