{
  "type": "Feature",
  "properties": {
    "date:inception_lower":"1997-12-01",
    "date:inception_upper":"1997-12-31",
    "iso:country":"GB",
    "wof:name":"BB18 6XB",
    "wof:placetype":"postalcode"
},
  "geometry": {"coordinates":[-2.145825,53.914622],"type":"Point"}
}