{
  "type": "Feature",
  "properties": {
    "iso:country":"GB",
    "wof:name":"AL5 1ET",
    "wof:placetype":"postalcode"
},
  "geometry": {"coordinates":[-0.33737721298153,51.80641491528555],"type":"Point"}
}