{
  "type": "Feature",
  "properties": {
    "iso:country":"GB",
    "wof:name":"HD1 4EN",
    "wof:placetype":"postalcode"
},
  "geometry": {"coordinates":[-1.78982607920743,53.64699980436587],"type":"Point"}
}