{
  "type": "Feature",
  "properties": {
    "iso:country":"GB",
    "wof:name":"YO32 9UR",
    "wof:placetype":"postalcode"
},
  "geometry": {"coordinates":[-0.9948073084683,54.00030664863031],"type":"Point"}
}