{
  "type": "Feature",
  "properties": {
    "iso:country": "GB",
    "wof:name": "BS6 6RT",
    "wof:placetype": "postalcode"
  },
  "geometry": {"coordinates":[-2.607825,51.469967],"type":"Point"}
}
