{
  "type": "Feature",
  "properties": {
    "date:inception_lower":"1980-01-01",
    "date:inception_upper":"1980-01-31",
    "iso:country":"GB",
    "wof:name":"IP22 1PB",
    "wof:placetype":"postalcode"
},
  "geometry": {"coordinates":[0.948883,52.324039],"type":"Point"}
}