{
  "type": "Feature",
  "properties": {
    "iso:country":"GB",
    "wof:name":"IP22 1PB",
    "wof:placetype":"postalcode"
},
  "geometry": {"coordinates":[0.94888340586851,52.32403864148935],"type":"Point"}
}