{
  "type": "Feature",
  "properties": {
    "date:inception_lower": "2004-10-01",
    "date:inception_upper": "2004-10-01",
    "iso:country": "GB",
    "wof:name": "BS15 3UE",
    "wof:placetype": "postalcode"
  },
  "geometry": {"coordinates":[-2.505901,51.461289],"type":"Point"}
}
