{
  "type": "Feature",
  "properties": {
    "iso:country":"GB",
    "wof:name":"M3 4FQ",
    "wof:placetype":"postalcode"
},
  "geometry": {"coordinates":[-2.25317836995468,53.47723374486053],"type":"Point"}
}