{
  "type": "Feature",
  "properties": {
    "iso:country":"GB",
    "wof:name":"SR5 1JG",
    "wof:placetype":"postalcode"
},
  "geometry": {"coordinates":[-1.38536392549993,54.91948935623508],"type":"Point"}
}