{
  "type": "Feature",
  "properties": {
    "iso:country":"GB",
    "wof:name":"WS8 7RH",
    "wof:placetype":"postalcode"
},
  "geometry": {"coordinates":[-1.94672695802169,52.64045491118456],"type":"Point"}
}