{
  "type": "Feature",
  "properties": {
    "date:inception_lower":"1997-12-01",
    "date:inception_upper":"1997-12-31",
    "iso:country":"GB",
    "wof:name":"WS8 7RH",
    "wof:placetype":"postalcode"
},
  "geometry": {"coordinates":[-1.946727,52.640455],"type":"Point"}
}