{
  "type": "Feature",
  "properties": {
    "iso:country": "GB",
    "wof:name": "WS8 7RH",
    "wof:placetype": "postalcode"
  },
  "geometry": {"coordinates":[-1.946727,52.640455],"type":"Point"}
}
