{
  "type": "Feature",
  "properties": {
    "date:inception_lower":"1980-01-01",
    "date:inception_upper":"1980-01-31",
    "iso:country":"GB",
    "wof:name":"WA3 7HQ",
    "wof:placetype":"postalcode"
},
  "geometry": {"coordinates":[-2.555199,53.436824],"type":"Point"}
}