{
  "type": "Feature",
  "properties": {
    "iso:country":"GB",
    "wof:name":"WA3 7HQ",
    "wof:placetype":"postalcode"
},
  "geometry": {"coordinates":[-2.55519936611763,53.43682361753176],"type":"Point"}
}