{
  "type": "Feature",
  "properties": {
    "iso:country":"GB",
    "wof:name":"B17 0QN",
    "wof:placetype":"postalcode"
},
  "geometry": {"coordinates":[-1.95985990850229,52.45027960313696],"type":"Point"}
}