{
  "type": "Feature",
  "properties": {
    "date:inception_lower": "1980-01-01",
    "date:inception_upper": "1980-01-01",
    "iso:country": "GB",
    "wof:name": "PL13 2JS",
    "wof:placetype": "postalcode"
  },
  "geometry": {"coordinates":[-4.49158,50.353374],"type":"Point"}
}
