{
  "type": "Feature",
  "properties": {
    "iso:country":"GB",
    "wof:name":"NE17 7EJ",
    "wof:placetype":"postalcode"
},
  "geometry": {"coordinates":[-1.81031383438308,54.9148826059012],"type":"Point"}
}