{
  "type": "Feature",
  "properties": {
    "iso:country":"GB",
    "wof:name":"EH49 6RA",
    "wof:placetype":"postalcode"
},
  "geometry": {"coordinates":[-3.52865277740183,55.97679055378786],"type":"Point"}
}