{
  "type": "Feature",
  "properties": {
    "iso:country":"GB",
    "wof:name":"SK10 5LU",
    "wof:placetype":"postalcode"
},
  "geometry": {"coordinates":[-2.10107898983264,53.29475758604381],"type":"Point"}
}