{
  "type": "Feature",
  "properties": {
    "iso:country": "GB",
    "wof:name": "G3 7HR",
    "wof:placetype": "postalcode"
  },
  "geometry": {"coordinates":[-4.277632,55.864904],"type":"Point"}
}
