{
  "type": "Feature",
  "properties": {
    "iso:country":"GB",
    "wof:name":"L39 5AB",
    "wof:placetype":"postalcode"
},
  "geometry": {"coordinates":[-2.90058951944236,53.55471785294787],"type":"Point"}
}