{
  "type": "Feature",
  "properties": {
    "iso:country":"GB",
    "wof:name":"CV37 8RW",
    "wof:placetype":"postalcode"
},
  "geometry": {"coordinates":[-1.77982878755635,52.13109832940864],"type":"Point"}
}