{
  "type": "Feature",
  "properties": {
    "iso:country": "GB",
    "wof:name": "NE49 9NB",
    "wof:placetype": "postalcode"
  },
  "geometry": {"coordinates":[-2.486821,54.972834],"type":"Point"}
}
