{
  "type": "Feature",
  "properties": {
    "iso:country":"GB",
    "wof:name":"NE49 9NB",
    "wof:placetype":"postalcode"
},
  "geometry": {"coordinates":[-2.48682087721192,54.97283392453555],"type":"Point"}
}