{
  "type": "Feature",
  "properties": {
    "iso:country":"GB",
    "wof:name":"L24 9HW",
    "wof:placetype":"postalcode"
},
  "geometry": {"coordinates":[-2.86139343609018,53.35414361916455],"type":"Point"}
}