{
  "type": "Feature",
  "properties": {
    "iso:country": "GB",
    "wof:name": "L17 0DD",
    "wof:placetype": "postalcode"
  },
  "geometry": {"coordinates":[-2.931249,53.374527],"type":"Point"}
}
