{
  "type": "Feature",
  "properties": {
    "iso:country":"GB",
    "wof:name":"NP16 6PF",
    "wof:placetype":"postalcode"
},
  "geometry": {"coordinates":[-2.74066032787482,51.68793969720056],"type":"Point"}
}