{
  "type": "Feature",
  "properties": {
    "iso:country": "GB",
    "wof:name": "NP16 6PF",
    "wof:placetype": "postalcode"
  },
  "geometry": {"coordinates":[-2.741046,51.688156],"type":"Point"}
}
