{
  "type": "Feature",
  "properties": {
    "date:inception_lower": "1985-10-01",
    "date:inception_upper": "1985-10-01",
    "iso:country": "GB",
    "wof:name": "FY4 4NX",
    "wof:placetype": "postalcode"
  },
  "geometry": {"coordinates":[-3.010009,53.800597],"type":"Point"}
}
