{
  "type": "Feature",
  "properties": {
    "iso:country":"GB",
    "wof:name":"FY4 4NX",
    "wof:placetype":"postalcode"
},
  "geometry": {"coordinates":[-3.01000923188189,53.80059740329988],"type":"Point"}
}