{
  "type": "Feature",
  "properties": {
    "iso:country":"GB",
    "wof:name":"PO12 1NQ",
    "wof:placetype":"postalcode"
},
  "geometry": {"coordinates":[-1.12655870055056,50.79528571126841],"type":"Point"}
}