{
  "type": "Feature",
  "properties": {
    "iso:country": "GB",
    "wof:name": "KA18 1TH",
    "wof:placetype": "postalcode"
  },
  "geometry": {"coordinates":[-4.252934,55.452825],"type":"Point"}
}
