{
  "type": "Feature",
  "properties": {
    "iso:country": "GB",
    "wof:name": "NG12 5NR",
    "wof:placetype": "postalcode"
  },
  "geometry": {"coordinates":[-1.088566,52.89075],"type":"Point"}
}
