{
  "type": "Feature",
  "properties": {
    "iso:country":"GB",
    "wof:name":"NG12 5NR",
    "wof:placetype":"postalcode"
},
  "geometry": {"coordinates":[-1.08837116694388,52.89101444105534],"type":"Point"}
}