{
  "type": "Feature",
  "properties": {
    "iso:country": "GB",
    "wof:name": "RG8 0TH",
    "wof:placetype": "postalcode"
  },
  "geometry": {"coordinates":[-1.046542,51.555933],"type":"Point"}
}
