{
  "type": "Feature",
  "properties": {
    "iso:country":"GB",
    "wof:name":"RG8 0TH",
    "wof:placetype":"postalcode"
},
  "geometry": {"coordinates":[-1.04654191758353,51.55593257852384],"type":"Point"}
}