{
  "type": "Feature",
  "properties": {
    "iso:country": "GB",
    "wof:name": "TS26 0ZG",
    "wof:placetype": "postalcode"
  },
  "geometry": {"coordinates":[-1.240336,54.701991],"type":"Point"}
}
