{
  "type": "Feature",
  "properties": {
    "date:inception_lower": "2013-04-01",
    "date:inception_upper": "2013-04-01",
    "iso:country": "GB",
    "wof:name": "TS26 0ZG",
    "wof:placetype": "postalcode"
  },
  "geometry": {"coordinates":[-1.240336,54.701991],"type":"Point"}
}
