{
  "type": "Feature",
  "properties": {
    "iso:country":"GB",
    "wof:name":"HX6 3BG",
    "wof:placetype":"postalcode"
},
  "geometry": {"coordinates":[-1.91732747906533,53.70558735372788],"type":"Point"}
}