{
  "type": "Feature",
  "properties": {
    "iso:country":"GB",
    "wof:name":"S2 5TR",
    "wof:placetype":"postalcode"
},
  "geometry": {"coordinates":[-1.46249911878357,53.38439524842521],"type":"Point"}
}