{
  "type": "Feature",
  "properties": {
    "date:inception_lower":"2007-04-01",
    "date:inception_upper":"2007-04-30",
    "iso:country":"GB",
    "wof:name":"GU51 3SL",
    "wof:placetype":"postalcode"
},
  "geometry": {"coordinates":[-0.844582,51.278289],"type":"Point"}
}