{
  "type": "Feature",
  "properties": {
    "iso:country": "GB",
    "wof:name": "WA8 9ZA",
    "wof:placetype": "postalcode"
  },
  "geometry": {"coordinates":[-2.756795,53.38208],"type":"Point"}
}
