{
  "type": "Feature",
  "properties": {
    "iso:country": "GB",
    "wof:name": "EH16 4FS",
    "wof:placetype": "postalcode"
  },
  "geometry": {"coordinates":[-3.128111,55.928754],"type":"Point"}
}
