{
  "type": "Feature",
  "properties": {
    "iso:country":"GB",
    "wof:name":"TN29 9QP",
    "wof:placetype":"postalcode"
},
  "geometry": {"coordinates":[0.83349421833916,50.99780506439036],"type":"Point"}
}