{
  "type": "Feature",
  "properties": {
    "iso:country": "GB",
    "wof:name": "TN29 9QP",
    "wof:placetype": "postalcode"
  },
  "geometry": {"coordinates":[0.833494,50.997805],"type":"Point"}
}
