{
  "type": "Feature",
  "properties": {
    "date:inception_lower": "2018-07-01",
    "date:inception_upper": "2018-07-01",
    "iso:country": "GB",
    "wof:name": "SN7 7LS",
    "wof:placetype": "postalcode"
  },
  "geometry": {"coordinates":[-1.597555,51.647584],"type":"Point"}
}
