{
  "type": "Feature",
  "properties": {
    "iso:country": "GB",
    "wof:name": "TA20 3BG",
    "wof:placetype": "postalcode"
  },
  "geometry": {"coordinates":[-2.962878,50.903705],"type":"Point"}
}
