{
  "type": "Feature",
  "properties": {
    "iso:country":"GB",
    "wof:name":"TA20 3BG",
    "wof:placetype":"postalcode"
},
  "geometry": {"coordinates":[-2.96287162335471,50.90371337320696],"type":"Point"}
}