{
  "type": "Feature",
  "properties": {
    "iso:country":"GB",
    "wof:name":"PR2 9LD",
    "wof:placetype":"postalcode"
},
  "geometry": {"coordinates":[-2.67151263944852,53.79002820864427],"type":"Point"}
}