{
  "type": "Feature",
  "properties": {
    "iso:country":"GB",
    "wof:name":"WN5 7NJ",
    "wof:placetype":"postalcode"
},
  "geometry": {"coordinates":[-2.71120458669336,53.49962702931681],"type":"Point"}
}