{
  "type": "Feature",
  "properties": {
    "iso:country":"GB",
    "wof:name":"BH11 8RB",
    "wof:placetype":"postalcode"
},
  "geometry": {"coordinates":[-1.91688346534345,50.75031477198288],"type":"Point"}
}