{
  "type": "Feature",
  "properties": {
    "iso:country":"GB",
    "wof:name":"HU16 4JQ",
    "wof:placetype":"postalcode"
},
  "geometry": {"coordinates":[-0.3951494689747,53.79218478653674],"type":"Point"}
}