{
  "type": "Feature",
  "properties": {
    "iso:country": "GB",
    "wof:name": "HU16 4JQ",
    "wof:placetype": "postalcode"
  },
  "geometry": {"coordinates":[-0.395149,53.792185],"type":"Point"}
}
