{
  "type": "Feature",
  "properties": {
    "date:inception_lower": "2008-08-01",
    "date:inception_upper": "2008-08-01",
    "iso:country": "GB",
    "wof:name": "G66 1XU",
    "wof:placetype": "postalcode"
  },
  "geometry": {"coordinates":[-4.159494,55.935454],"type":"Point"}
}
