{
  "type": "Feature",
  "properties": {
    "iso:country":"GB",
    "wof:name":"SR4 9AX",
    "wof:placetype":"postalcode"
},
  "geometry": {"coordinates":[-1.44364215677796,54.89857995099942],"type":"Point"}
}