{
  "type": "Feature",
  "properties": {
    "iso:country": "GB",
    "wof:name": "SR4 9AX",
    "wof:placetype": "postalcode"
  },
  "geometry": {"coordinates":[-1.44306,54.898801],"type":"Point"}
}
