{
  "type": "Feature",
  "properties": {
    "iso:country": "GB",
    "wof:name": "PL12 4XR",
    "wof:placetype": "postalcode"
  },
  "geometry": {"coordinates":[-4.240908,50.413348],"type":"Point"}
}
