{
  "type": "Feature",
  "properties": {
    "date:inception_lower": "1997-06-01",
    "date:inception_upper": "1997-06-01",
    "iso:country": "GB",
    "wof:name": "PL12 4XR",
    "wof:placetype": "postalcode"
  },
  "geometry": {"coordinates":[-4.240908,50.413348],"type":"Point"}
}
