{
  "type": "Feature",
  "properties": {
    "iso:country":"GB",
    "wof:name":"PL12 4XR",
    "wof:placetype":"postalcode"
},
  "geometry": {"coordinates":[-4.24090760273366,50.41334840834918],"type":"Point"}
}