{
  "type": "Feature",
  "properties": {
    "iso:country":"GB",
    "wof:name":"NR11 6HZ",
    "wof:placetype":"postalcode"
},
  "geometry": {"coordinates":[1.25890590640594,52.79950955060098],"type":"Point"}
}