{
  "type": "Feature",
  "properties": {
    "iso:country": "GB",
    "wof:name": "NN3 6XF",
    "wof:placetype": "postalcode"
  },
  "geometry": {"coordinates":[-0.871311,52.2804],"type":"Point"}
}
