{
  "type": "Feature",
  "properties": {
    "iso:country":"GB",
    "wof:name":"NG14 5GS",
    "wof:placetype":"postalcode"
},
  "geometry": {"coordinates":[-1.02756538656583,52.99386783967385],"type":"Point"}
}