{
  "type": "Feature",
  "properties": {
    "iso:country": "GB",
    "wof:name": "NG14 5GS",
    "wof:placetype": "postalcode"
  },
  "geometry": {"coordinates":[-1.027565,52.993868],"type":"Point"}
}
