{
  "type": "Feature",
  "properties": {
    "iso:country": "GB",
    "wof:name": "NE61 5LT",
    "wof:placetype": "postalcode"
  },
  "geometry": {"coordinates":[-1.557828,55.22424],"type":"Point"}
}
