{
  "type": "Feature",
  "properties": {
    "iso:country":"GB",
    "wof:name":"OL2 8JF",
    "wof:placetype":"postalcode"
},
  "geometry": {"coordinates":[-2.08376923336502,53.57882573873054],"type":"Point"}
}