{
  "type": "Feature",
  "properties": {
    "iso:country": "GB",
    "wof:name": "OL2 8JF",
    "wof:placetype": "postalcode"
  },
  "geometry": {"coordinates":[-2.083769,53.578826],"type":"Point"}
}
