{
  "type": "Feature",
  "properties": {
    "date:inception_lower": "2001-06-01",
    "date:inception_upper": "2001-06-01",
    "iso:country": "GB",
    "wof:name": "PR25 2SG",
    "wof:placetype": "postalcode"
  },
  "geometry": {"coordinates":[-2.691885,53.693244],"type":"Point"}
}
