{
  "type": "Feature",
  "properties": {
    "iso:country":"GB",
    "wof:name":"LS6 1QJ",
    "wof:placetype":"postalcode"
},
  "geometry": {"coordinates":[-1.57420442222333,53.80695575375149],"type":"Point"}
}