{
  "type": "Feature",
  "properties": {
    "iso:country": "GB",
    "wof:name": "LS6 1QJ",
    "wof:placetype": "postalcode"
  },
  "geometry": {"coordinates":[-1.574204,53.806956],"type":"Point"}
}
