{
  "type": "Feature",
  "properties": {
    "iso:country": "GB",
    "wof:name": "RG27 8NT",
    "wof:placetype": "postalcode"
  },
  "geometry": {"coordinates":[-0.897928,51.308369],"type":"Point"}
}
