{
  "type": "Feature",
  "properties": {
    "date:inception_lower":"1980-01-01",
    "date:inception_upper":"1980-01-31",
    "iso:country":"GB",
    "wof:name":"TW12 2NU",
    "wof:placetype":"postalcode"
},
  "geometry": {"coordinates":[-0.372551,51.419563],"type":"Point"}
}