{
  "type": "Feature",
  "properties": {
    "iso:country":"GB",
    "wof:name":"TW12 2NU",
    "wof:placetype":"postalcode"
},
  "geometry": {"coordinates":[-0.37255090452413,51.41956261423621],"type":"Point"}
}