{
  "type": "Feature",
  "properties": {
    "iso:country":"GB",
    "wof:name":"TF9 4JF",
    "wof:placetype":"postalcode"
},
  "geometry": {"coordinates":[-2.36605859456338,52.96613898625127],"type":"Point"}
}