{
  "type": "Feature",
  "properties": {
    "date:inception_lower": "1980-01-01",
    "date:inception_upper": "1980-01-01",
    "iso:country": "GB",
    "wof:name": "TF9 4JF",
    "wof:placetype": "postalcode"
  },
  "geometry": {"coordinates":[-2.365939,52.966139],"type":"Point"}
}
