{
  "type": "Feature",
  "properties": {
    "iso:country": "GB",
    "wof:name": "TF9 4JF",
    "wof:placetype": "postalcode"
  },
  "geometry": {"coordinates":[-2.365939,52.966139],"type":"Point"}
}
