{
  "type": "Feature",
  "properties": {
    "iso:country":"GB",
    "wof:name":"M34 6ZA",
    "wof:placetype":"postalcode"
},
  "geometry": {"coordinates":[-2.1140198599088,53.45515644493233],"type":"Point"}
}