{
  "type": "Feature",
  "properties": {
    "date:inception_lower": "2021-08-01",
    "date:inception_upper": "2021-08-01",
    "iso:country": "GB",
    "wof:name": "B91 1EZ",
    "wof:placetype": "postalcode"
  },
  "geometry": {"coordinates":[-1.79826,52.421559],"type":"Point"}
}
