{
  "type": "Feature",
  "properties": {
    "date:inception_lower":"1980-01-01",
    "date:inception_upper":"1980-01-31",
    "iso:country":"GB",
    "wof:name":"LE3 6NU",
    "wof:placetype":"postalcode"
},
  "geometry": {"coordinates":[-1.191271,52.638608],"type":"Point"}
}