{
  "type": "Feature",
  "properties": {
    "iso:country": "GB",
    "wof:name": "LE3 6NU",
    "wof:placetype": "postalcode"
  },
  "geometry": {"coordinates":[-1.191271,52.638608],"type":"Point"}
}
