{
  "type": "Feature",
  "properties": {
    "iso:country":"GB",
    "wof:name":"LE3 6NU",
    "wof:placetype":"postalcode"
},
  "geometry": {"coordinates":[-1.19136676022648,52.63856341916321],"type":"Point"}
}