{
  "type": "Feature",
  "properties": {
    "date:inception_lower": "2019-03-01",
    "date:inception_upper": "2019-03-01",
    "iso:country": "GB",
    "wof:name": "NN18 8TU",
    "wof:placetype": "postalcode"
  },
  "geometry": {"coordinates":[-0.695447,52.476007],"type":"Point"}
}
