{
  "type": "Feature",
  "properties": {
    "iso:country": "GB",
    "wof:name": "NN18 8TU",
    "wof:placetype": "postalcode"
  },
  "geometry": {"coordinates":[-0.695447,52.476007],"type":"Point"}
}
