{
  "type": "Feature",
  "properties": {
    "iso:country":"GB",
    "wof:name":"PA20 9HT",
    "wof:placetype":"postalcode"
},
  "geometry": {"coordinates":[-5.05042978928002,55.83038214485342],"type":"Point"}
}