{
  "type": "Feature",
  "properties": {
    "iso:country":"GB",
    "wof:name":"NG14 6FY",
    "wof:placetype":"postalcode"
},
  "geometry": {"coordinates":[-1.0740912295055,53.03511424077114],"type":"Point"}
}