{
  "type": "Feature",
  "properties": {
    "iso:country": "GB",
    "wof:name": "KY11 2ZJ",
    "wof:placetype": "postalcode"
  },
  "geometry": {"coordinates":[-3.429186,56.045134],"type":"Point"}
}
