{
  "type": "Feature",
  "properties": {
    "date:inception_lower":"2007-10-01",
    "date:inception_upper":"2007-10-31",
    "iso:country":"GB",
    "wof:name":"KY11 2ZJ",
    "wof:placetype":"postalcode"
},
  "geometry": {"coordinates":[-3.429186,56.045134],"type":"Point"}
}