{
  "type": "Feature",
  "properties": {
    "iso:country":"GB",
    "wof:name":"IP3 9QR",
    "wof:placetype":"postalcode"
},
  "geometry": {"coordinates":[1.1979994158859,52.03496408435359],"type":"Point"}
}