{
  "type": "Feature",
  "properties": {
    "iso:country": "GB",
    "wof:name": "S70 6QG",
    "wof:placetype": "postalcode"
  },
  "geometry": {"coordinates":[-1.506535,53.55073],"type":"Point"}
}
