{
  "type": "Feature",
  "properties": {
    "iso:country":"GB",
    "wof:name":"SO21 3NP",
    "wof:placetype":"postalcode"
},
  "geometry": {"coordinates":[-1.3760403648812,51.17572577501075],"type":"Point"}
}