{
  "type": "Feature",
  "properties": {
    "date:inception_lower": "1980-01-01",
    "date:inception_upper": "1980-01-01",
    "iso:country": "GB",
    "wof:name": "SO21 3NP",
    "wof:placetype": "postalcode"
  },
  "geometry": {"coordinates":[-1.37604,51.175726],"type":"Point"}
}
