{
  "type": "Feature",
  "properties": {
    "iso:country":"GB",
    "wof:name":"TN2 3UB",
    "wof:placetype":"postalcode"
},
  "geometry": {"coordinates":[0.28464083783499,51.14509667175987],"type":"Point"}
}