{
  "type": "Feature",
  "properties": {
    "date:inception_lower": "1980-01-01",
    "date:inception_upper": "1980-01-01",
    "iso:country": "GB",
    "wof:name": "DN20 0HR",
    "wof:placetype": "postalcode"
  },
  "geometry": {"coordinates":[-0.547072,53.567734],"type":"Point"}
}
