{
  "type": "Feature",
  "properties": {
    "iso:country":"GB",
    "wof:name":"SK17 6SY",
    "wof:placetype":"postalcode"
},
  "geometry": {"coordinates":[-1.92696654525022,53.26261671691096],"type":"Point"}
}