{
  "type": "Feature",
  "properties": {
    "iso:country":"GB",
    "wof:name":"G77 6NU",
    "wof:placetype":"postalcode"
},
  "geometry": {"coordinates":[-4.34630756884714,55.76969192823488],"type":"Point"}
}