{
  "type": "Feature",
  "properties": {
    "iso:country": "GB",
    "wof:name": "G77 6NU",
    "wof:placetype": "postalcode"
  },
  "geometry": {"coordinates":[-4.346308,55.769692],"type":"Point"}
}
