{
  "type": "Feature",
  "properties": {
    "date:inception_lower": "2016-10-01",
    "date:inception_upper": "2016-10-01",
    "iso:country": "GB",
    "wof:name": "CO2 7LE",
    "wof:placetype": "postalcode"
  },
  "geometry": {"coordinates":[0.903906,51.882413],"type":"Point"}
}
