{
  "type": "Feature",
  "properties": {
    "date:inception_lower": "2013-10-01",
    "date:inception_upper": "2013-10-01",
    "iso:country": "GB",
    "wof:name": "KA17 0BS",
    "wof:placetype": "postalcode"
  },
  "geometry": {"coordinates":[-4.287551,55.609711],"type":"Point"}
}
