{
  "type": "Feature",
  "properties": {
    "iso:country":"GB",
    "wof:name":"SE25 6XX",
    "wof:placetype":"postalcode"
},
  "geometry": {"coordinates":[-0.08040715351279,51.39676968679328],"type":"Point"}
}