{
  "type": "Feature",
  "properties": {
    "iso:country":"GB",
    "wof:name":"OL2 8LX",
    "wof:placetype":"postalcode"
},
  "geometry": {"coordinates":[-2.07578983997336,53.58449369596313],"type":"Point"}
}