{
  "type": "Feature",
  "properties": {
    "iso:country": "GB",
    "wof:name": "OL2 8LX",
    "wof:placetype": "postalcode"
  },
  "geometry": {"coordinates":[-2.07579,53.584494],"type":"Point"}
}
