{
  "type": "Feature",
  "properties": {
    "iso:country":"GB",
    "wof:name":"TN2 3PL",
    "wof:placetype":"postalcode"
},
  "geometry": {"coordinates":[0.28208746458539,51.14927456351218],"type":"Point"}
}