{
  "type": "Feature",
  "properties": {
    "date:inception_lower": "1991-01-01",
    "date:inception_upper": "1991-01-01",
    "iso:country": "GB",
    "wof:name": "TN2 3PL",
    "wof:placetype": "postalcode"
  },
  "geometry": {"coordinates":[0.282088,51.149275],"type":"Point"}
}
