{
  "type": "Feature",
  "properties": {
    "iso:country":"GB",
    "wof:name":"L21 7RF",
    "wof:placetype":"postalcode"
},
  "geometry": {"coordinates":[-2.99108192398367,53.47446932677578],"type":"Point"}
}