{
  "type": "Feature",
  "properties": {
    "iso:country":"GB",
    "wof:name":"ME4 5RS",
    "wof:placetype":"postalcode"
},
  "geometry": {"coordinates":[0.52693318334391,51.37733834851041],"type":"Point"}
}