{
  "type": "Feature",
  "properties": {
    "iso:country":"GB",
    "wof:name":"LL11 6UP",
    "wof:placetype":"postalcode"
},
  "geometry": {"coordinates":[-3.0299659697142,53.05705177443208],"type":"Point"}
}