{
  "type": "Feature",
  "properties": {
    "iso:country":"GB",
    "wof:name":"E2 7DL",
    "wof:placetype":"postalcode"
},
  "geometry": {"coordinates":[-0.0724454079644,51.52483831514293],"type":"Point"}
}