{
  "type": "Feature",
  "properties": {
    "date:inception_lower": "1980-01-01",
    "date:inception_upper": "1980-01-01",
    "iso:country": "GB",
    "wof:name": "WF11 0LY",
    "wof:placetype": "postalcode"
  },
  "geometry": {"coordinates":[-1.252951,53.697149],"type":"Point"}
}
