{
  "type": "Feature",
  "properties": {
    "iso:country": "GB",
    "wof:name": "WF11 0LY",
    "wof:placetype": "postalcode"
  },
  "geometry": {"coordinates":[-1.252951,53.697149],"type":"Point"}
}
