{
  "type": "Feature",
  "properties": {
    "iso:country":"GB",
    "wof:name":"DN39 6TQ",
    "wof:placetype":"postalcode"
},
  "geometry": {"coordinates":[-0.33099466517726,53.6190842904087],"type":"Point"}
}