{
  "type": "Feature",
  "properties": {
    "date:inception_lower": "1980-01-01",
    "date:inception_upper": "1980-01-01",
    "iso:country": "GB",
    "wof:name": "DN39 6TQ",
    "wof:placetype": "postalcode"
  },
  "geometry": {"coordinates":[-0.330995,53.619084],"type":"Point"}
}
