{
  "type": "Feature",
  "properties": {
    "iso:country": "GB",
    "wof:name": "YO1 9RF",
    "wof:placetype": "postalcode"
  },
  "geometry": {"coordinates":[-1.073375,53.957714],"type":"Point"}
}
