{
  "type": "Feature",
  "properties": {
    "iso:country":"GB",
    "wof:name":"YO1 9RF",
    "wof:placetype":"postalcode"
},
  "geometry": {"coordinates":[-1.07337511262108,53.95771434476678],"type":"Point"}
}