{
  "type": "Feature",
  "properties": {
    "date:inception_lower": "2010-10-01",
    "date:inception_upper": "2010-10-01",
    "iso:country": "GB",
    "wof:name": "YO1 9RF",
    "wof:placetype": "postalcode"
  },
  "geometry": {"coordinates":[-1.073375,53.957714],"type":"Point"}
}
