{
  "type": "Feature",
  "properties": {
    "date:inception_lower": "1980-01-01",
    "date:inception_upper": "1980-01-01",
    "iso:country": "GB",
    "wof:name": "OL14 7AT",
    "wof:placetype": "postalcode"
  },
  "geometry": {"coordinates":[-2.099025,53.714877],"type":"Point"}
}
