{
  "type": "Feature",
  "properties": {
    "date:inception_lower": "1980-01-01",
    "date:inception_upper": "1980-01-01",
    "iso:country": "GB",
    "wof:name": "SA62 5HN",
    "wof:placetype": "postalcode"
  },
  "geometry": {"coordinates":[-5.075625,51.957554],"type":"Point"}
}
