{
  "type": "Feature",
  "properties": {
    "iso:country":"GB",
    "wof:name":"TN25 6AN",
    "wof:placetype":"postalcode"
},
  "geometry": {"coordinates":[0.98889603957627,51.11352370372212],"type":"Point"}
}