{
  "type": "Feature",
  "properties": {
    "iso:country": "GB",
    "wof:name": "TN25 6AN",
    "wof:placetype": "postalcode"
  },
  "geometry": {"coordinates":[0.988896,51.113524],"type":"Point"}
}
