{
  "type": "Feature",
  "properties": {
    "date:inception_lower":"1980-01-01",
    "date:inception_upper":"1980-01-31",
    "iso:country":"GB",
    "wof:name":"TN25 6AN",
    "wof:placetype":"postalcode"
},
  "geometry": {"coordinates":[0.988896,51.113524],"type":"Point"}
}