{
  "type": "Feature",
  "properties": {
    "iso:country": "GB",
    "wof:name": "CO13 0JH",
    "wof:placetype": "postalcode"
  },
  "geometry": {"coordinates":[1.210566,51.829577],"type":"Point"}
}
