{
  "type": "Feature",
  "properties": {
    "iso:country":"GB",
    "wof:name":"EH49 6NH",
    "wof:placetype":"postalcode"
},
  "geometry": {"coordinates":[-3.53426516942326,55.96675542375535],"type":"Point"}
}