{
  "type": "Feature",
  "properties": {
    "date:inception_lower": "1980-01-01",
    "date:inception_upper": "1980-01-01",
    "iso:country": "GB",
    "wof:name": "OL10 2AR",
    "wof:placetype": "postalcode"
  },
  "geometry": {"coordinates":[-2.210954,53.585561],"type":"Point"}
}
