{
  "type": "Feature",
  "properties": {
    "iso:country": "GB",
    "wof:name": "WV14 7AT",
    "wof:placetype": "postalcode"
  },
  "geometry": {"coordinates":[-2.060023,52.571194],"type":"Point"}
}
